{
  "type": "Feature",
  "properties": {
    "addr:full":"138 W 179th St Bronx NY 10453",
    "addr:housenumber":"138",
    "addr:postcode":"10453",
    "addr:street":"W 179Th St",
    "iso:country":"US",
    "sg:address":"138 W 179th St",
    "sg:city":"Bronx",
    "sg:classifiers":[
        {
            "category":"Social Services",
            "subcategory":"Child Care",
            "type":"Services"
        }
    ],
    "sg:phone":"+1 718 716 8800",
    "sg:postcode":"10453",
    "sg:province":"NY",
    "sg:tags":[
        "day"
    ],
    "wof:name":"Loving Care Group Daycare",
    "wof:placetype":"venue"
},
  "geometry": {"coordinates":[-73.91330499999999,40.855226],"type":"Point"}
}