{
  "type": "Feature",
  "properties": {
    "addr:full":"1117 Brighton Beach Ave Brooklyn NY 11235",
    "addr:housenumber":"1117",
    "addr:postcode":"11235",
    "addr:street":"Brighton Beach Ave",
    "iso:country":"US",
    "sg:address":"1117 Brighton Beach Ave",
    "sg:city":"Brooklyn",
    "sg:classifiers":[
        {
            "category":"Restaurant",
            "type":"Food & Drink"
        }
    ],
    "sg:phone":"+1 718 648 6044",
    "sg:postcode":"11235",
    "sg:province":"NY",
    "sg:tags":[
        "deli",
        "delicatessen",
        "eating",
        "grocery"
    ],
    "wof:name":"Gastronome Odessa Inc",
    "wof:placetype":"venue"
},
  "geometry": {"coordinates":[-73.956299,40.5779],"type":"Point"}
}