{
  "type": "Feature",
  "properties": {
    "addr:full":"55 W 47th St New York NY 10036",
    "addr:housenumber":"55",
    "addr:postcode":"10036",
    "addr:street":"W 47Th St",
    "iso:country":"US",
    "sg:address":"55 W 47th St",
    "sg:city":"New York",
    "sg:classifiers":[
        {
            "category":"Travel",
            "subcategory":"Travel Agent",
            "type":"Entertainment"
        }
    ],
    "sg:phone":"+1   ",
    "sg:postcode":"10036",
    "sg:province":"NY",
    "sg:tags":[
        "agency"
    ],
    "wof:name":"D D M Travel",
    "wof:placetype":"venue"
},
  "geometry": {"coordinates":[-73.98041000000001,40.757333],"type":"Point"}
}