{
  "type": "Feature",
  "properties": {
    "iso:country":"US",
    "sg:address":"315 Park Ave S",
    "sg:city":"New York",
    "sg:classifiers":[
        {
            "category":"Professional",
            "subcategory":"Engineering",
            "type":"Services"
        }
    ],
    "sg:phone":"+1 212 564 0328",
    "sg:postcode":"10010",
    "sg:province":"NY",
    "sg:tags":[
        "firm",
        "consulting"
    ],
    "wof:name":"Edwards and Zuck PC",
    "wof:placetype":"venue"
},
  "geometry": {"coordinates":[-73.986071,40.740351],"type":"Point"}
}