{
  "type": "Feature",
  "properties": {
    "iso:country":"US",
    "sg:address":"545 Fenimore Rd",
    "sg:city":"Mamaroneck",
    "sg:classifiers":[
        {
            "category":"Education",
            "subcategory":"Special Training",
            "type":"Public Place"
        }
    ],
    "sg:phone":"+1 914 381 2070",
    "sg:postcode":"10543",
    "sg:province":"NY",
    "sg:tags":[
        "g"
    ],
    "wof:name":"Music School Of Westchester",
    "wof:placetype":"venue"
},
  "geometry": {"coordinates":[-73.74115399999999,40.950197],"type":"Point"}
}