{
  "type": "Feature",
  "properties": {
    "iso:country":"US",
    "sg:address":"12 Peekskill Hollow Rd",
    "sg:city":"Putnam Valley",
    "sg:classifiers":[
        {
            "category":"Education",
            "subcategory":"Dance Studio",
            "type":"Public Place"
        }
    ],
    "sg:phone":"+1 845 528 2200",
    "sg:postcode":"10579",
    "sg:province":"NY",
    "sg:tags":[
        "instruction",
        "dancing"
    ],
    "wof:name":"Darcy's Academy Of Dance Inc",
    "wof:placetype":"venue"
},
  "geometry": {"coordinates":[-73.868674,41.335755],"type":"Point"}
}