{
  "type": "Feature",
  "properties": {
    "iso:country":"US",
    "sg:address":"1167 39th St",
    "sg:city":"Brooklyn",
    "sg:classifiers":[
        {
            "category":"Food & Beverages",
            "subcategory":"Groceries & Convenience Stores",
            "type":"Retail Goods"
        }
    ],
    "sg:phone":"+1 718 972 7465",
    "sg:postcode":"11218",
    "sg:province":"NY",
    "sg:tags":[
        "market"
    ],
    "wof:name":"Rashmi Mini Market",
    "wof:placetype":"venue"
},
  "geometry": {"coordinates":[-73.98947,40.642828],"type":"Point"}
}