{
  "type": "Feature",
  "properties": {
    "iso:country":"US",
    "sg:address":"195 Mamaroneck Ave",
    "sg:city":"White Plains",
    "sg:classifiers":[
        {
            "category":"Utilities",
            "subcategory":"Mobile Phone",
            "type":"Services"
        }
    ],
    "sg:phone":"+1 914 997 9460",
    "sg:postcode":"10601",
    "sg:province":"NY",
    "sg:tags":[
        "telephone",
        "cellular"
    ],
    "wof:name":"E Z Connections Inc",
    "wof:placetype":"venue"
},
  "geometry": {"coordinates":[-73.76488500000001,41.028444],"type":"Point"}
}