{
  "type": "Feature",
  "properties": {
    "addr:full":"4201 Church Ave Brooklyn NY 11203",
    "addr:housenumber":"4201",
    "addr:postcode":"11203",
    "addr:street":"Church Ave",
    "iso:country":"US",
    "sg:address":"4201 Church Ave",
    "sg:city":"Brooklyn",
    "sg:classifiers":[
        {
            "category":"Wholesale",
            "subcategory":"Durable Goods & Equipment",
            "type":"Manufacturing & Wholesale Goods"
        },
        {
            "category":"Manufacturing",
            "subcategory":"Building Materials",
            "type":"Manufacturing & Wholesale Goods"
        }
    ],
    "sg:phone":"+1 718 826 6745",
    "sg:postcode":"11203",
    "sg:province":"NY",
    "sg:tags":[
        "filtering",
        "filters-liquid-wholesale",
        "supply"
    ],
    "wof:name":"Charles Irwin",
    "wof:placetype":"venue"
},
  "geometry": {"coordinates":[-73.93807200000001,40.65136],"type":"Point"}
}