{
  "type": "Feature",
  "properties": {
    "addr:full":"34 Neil Dr Farmingville NY 11738",
    "addr:housenumber":"34",
    "addr:postcode":"11738",
    "addr:street":"Neil Dr",
    "iso:country":"US",
    "sg:address":"34 Neil Dr",
    "sg:city":"Farmingville",
    "sg:classifiers":[
        {
            "category":"Professional",
            "subcategory":"Management & Consulting",
            "type":"Services"
        }
    ],
    "sg:phone":"+1 631 696 0502",
    "sg:postcode":"11738",
    "sg:province":"NY",
    "sg:tags":[
        "party",
        "planning"
    ],
    "wof:name":"Let's Party Together",
    "wof:placetype":"venue"
},
  "geometry": {"coordinates":[-73.01153600000001,40.830264],"type":"Point"}
}