{
  "type": "Feature",
  "properties": {
    "addr:full":"318 W Broad St Horseheads NY 14845",
    "addr:housenumber":"318",
    "addr:postcode":"14845",
    "addr:street":"W Broad St",
    "iso:country":"US",
    "sg:address":"318 W Broad St",
    "sg:city":"Horseheads",
    "sg:classifiers":[
        {
            "category":"Retail",
            "subcategory":"Funeral Services",
            "type":"Services"
        }
    ],
    "sg:phone":"+1 607 739 1301",
    "sg:postcode":"14845",
    "sg:province":"NY",
    "sg:tags":[
        "director",
        "supply"
    ],
    "sg:website":"http://www.lynchsfuneralhome.com",
    "wof:name":"Lynch Funeral Home Inc",
    "wof:placetype":"venue"
},
  "geometry": {"coordinates":[-76.824219,42.16626],"type":"Point"}
}