{
  "type": "Feature",
  "properties": {
    "addr:full":"200 Airport Executive Park Nanuet NY 10954",
    "addr:housenumber":"200",
    "addr:postcode":"10954",
    "addr:street":"Airport Executive Park",
    "iso:country":"US",
    "sg:address":"200 Airport Executive Park",
    "sg:city":"Nanuet",
    "sg:classifiers":[
        {
            "category":"Recreation",
            "type":"Entertainment"
        }
    ],
    "sg:phone":"+1 845 356 6619",
    "sg:postcode":"10954",
    "sg:province":"NY",
    "sg:tags":[
        "instruction",
        "gymnastic"
    ],
    "wof:name":"Gymboree Play & Music Ctr",
    "wof:placetype":"venue"
},
  "geometry": {"coordinates":[-74.02727,41.108652],"type":"Point"}
}