{
  "type": "Feature",
  "properties": {
    "addr:full":"1720 State Hwy 300 Newburgh NY 12550",
    "addr:housenumber":"1720",
    "addr:postcode":"12550",
    "addr:street":"State Hwy 300",
    "iso:country":"US",
    "sg:address":"1720 State Hwy 300",
    "sg:city":"Newburgh",
    "sg:classifiers":[
        {
            "category":"Manufacturing",
            "subcategory":"Printing",
            "type":"Manufacturing & Wholesale Goods"
        }
    ],
    "sg:phone":"+1   ",
    "sg:postcode":"12550",
    "sg:province":"NY",
    "sg:tags":[
        "commercial",
        "offset"
    ],
    "wof:name":"Newburgh Envelope Corp",
    "wof:placetype":"venue"
},
  "geometry": {"coordinates":[-74.06786,41.553982],"type":"Point"}
}