{
  "type": "Feature",
  "properties": {
    "iso:country":"US",
    "sg:address":"113 Southside Dr",
    "sg:city":"Owego",
    "sg:classifiers":[
        {
            "category":"Personal",
            "type":"Services"
        },
        {
            "category":"Wholesale",
            "subcategory":"Scrap",
            "type":"Manufacturing & Wholesale Goods"
        }
    ],
    "sg:phone":"+1 607 296 0927",
    "sg:postcode":"13827",
    "sg:province":"NY",
    "sg:tags":[
        "truck",
        "towing",
        "wrecking"
    ],
    "sg:website":"http://www.yext.com/p/superpages/value-towing-owego-new-york.html",
    "wof:name":"Val- U Towing",
    "wof:placetype":"venue"
},
  "geometry": {"coordinates":[-76.25553499999999,42.100099],"type":"Point"}
}