{
  "type": "Feature",
  "properties": {
    "addr:full":"142 Wheeler Rd Central Islip NY 11722",
    "addr:housenumber":"142",
    "addr:postcode":"11722",
    "addr:street":"Wheeler Rd",
    "iso:country":"US",
    "sg:address":"142 Wheeler Rd",
    "sg:city":"Central Islip",
    "sg:classifiers":[
        {
            "category":"Restaurant",
            "type":"Food & Drink"
        }
    ],
    "sg:menulink":"http://www.allmenus.com/ny/islip/255545-foo-chow/menu/",
    "sg:phone":"+1 631 234 1088",
    "sg:postcode":"11722",
    "sg:province":"NY",
    "sg:tags":[
        "asian",
        "chinese"
    ],
    "wof:name":"Foo Chow",
    "wof:placetype":"venue"
},
  "geometry": {"coordinates":[-73.21095,40.800964],"type":"Point"}
}