{
  "type": "Feature",
  "properties": {
    "iso:country":"US",
    "sg:address":"120 W Water St",
    "sg:city":"Elmira",
    "sg:classifiers":[
        {
            "category":"Professional",
            "subcategory":"Computer Services",
            "type":"Services"
        }
    ],
    "sg:phone":"+1 607 732 5122",
    "sg:postcode":"14901",
    "sg:province":"NY",
    "sg:tags":[
        "prepackaged",
        "software"
    ],
    "sg:website":"www.damomics.com",
    "wof:name":"DAMOMICS Computer Systs",
    "wof:placetype":"venue"
},
  "geometry": {"coordinates":[-76.806093,42.087824],"type":"Point"}
}