{
  "type": "Feature",
  "properties": {
    "addr:full":"88 Harbor Rd Port Washington NY 11050",
    "addr:housenumber":"88",
    "addr:postcode":"11050",
    "addr:street":"Harbor Rd",
    "iso:country":"US",
    "sg:address":"88 Harbor Rd",
    "sg:city":"Port Washington",
    "sg:classifiers":[
        {
            "category":"Professional",
            "subcategory":"Testing Lab",
            "type":"Services"
        }
    ],
    "sg:phone":"+1 516 944 9500",
    "sg:postcode":"11050",
    "sg:province":"NY",
    "sg:tags":[
        "laboratory",
        "trade",
        "special",
        "contractor"
    ],
    "wof:name":"N Y Environmental Mtl Tstg Lab",
    "wof:placetype":"venue"
},
  "geometry": {"coordinates":[-73.69679499999999,40.839808],"type":"Point"}
}