{
  "type": "Feature",
  "properties": {
    "addr:full":"57 Brooklyn Ave Merrick NY 11566",
    "addr:housenumber":"57",
    "addr:postcode":"11566",
    "addr:street":"Brooklyn Ave",
    "iso:country":"US",
    "sg:address":"57 Brooklyn Ave",
    "sg:city":"Merrick",
    "sg:classifiers":[
        {
            "category":"Retail",
            "subcategory":"Auto Repair",
            "type":"Services"
        }
    ],
    "sg:phone":"+1   ",
    "sg:postcode":"11566",
    "sg:province":"NY",
    "sg:tags":[
        "automobile",
        "also"
    ],
    "wof:name":"Barsan Service",
    "wof:placetype":"venue"
},
  "geometry": {"coordinates":[-73.554507,40.664287],"type":"Point"}
}