{
  "type": "Feature",
  "properties": {
    "addr:full":"175 Bay View Rd Rochester NY 14609",
    "addr:housenumber":"175",
    "addr:postcode":"14609",
    "addr:street":"Bay View Rd",
    "iso:country":"US",
    "sg:address":"175 Bay View Rd",
    "sg:city":"Rochester",
    "sg:classifiers":[
        {
            "category":"Building & Trades",
            "subcategory":"Construction",
            "type":"Services"
        }
    ],
    "sg:phone":"+1 585 482 9393",
    "sg:postcode":"14609",
    "sg:province":"NY",
    "sg:tags":[
        "house"
    ],
    "wof:name":"Piazza Construction Co",
    "wof:placetype":"venue"
},
  "geometry": {"coordinates":[-77.540631,43.188169],"type":"Point"}
}