{
  "type": "Feature",
  "properties": {
    "iso:country":"US",
    "sg:address":"1498 Rockaway Pkwy",
    "sg:city":"Brooklyn",
    "sg:classifiers":[
        {
            "category":"Shopping",
            "subcategory":"Shoes",
            "type":"Retail Goods"
        }
    ],
    "sg:phone":"+1 718 257 0595",
    "sg:postcode":"11236",
    "sg:province":"NY",
    "wof:name":"Training Camp",
    "wof:placetype":"venue"
},
  "geometry": {"coordinates":[-73.901073,40.644021],"type":"Point"}
}