{
  "type": "Feature",
  "properties": {
    "addr:full":"30 State Hwy 118 Baldwin Place NY 10541",
    "addr:housenumber":"30",
    "addr:postcode":"10541",
    "addr:street":"State Hwy 118 Baldwin Place",
    "iso:country":"US",
    "sg:address":"30 State Hwy 118",
    "sg:city":"Baldwin Place",
    "sg:classifiers":[
        {
            "category":"Shopping",
            "subcategory":"Bicycles & Sporting Goods",
            "type":"Retail Goods"
        }
    ],
    "sg:phone":"+1 845 628 6555",
    "sg:postcode":"10541",
    "sg:province":"NY",
    "sg:tags":[
        "tackle",
        "fishing"
    ],
    "wof:name":"Blue Mountain Sports Inc",
    "wof:placetype":"venue"
},
  "geometry": {"coordinates":[-73.721968,41.393032],"type":"Point"}
}