{
  "type": "Feature",
  "properties": {
    "iso:country":"US",
    "sg:address":"162 Greece Ridge Center Dr",
    "sg:city":"Rochester",
    "sg:classifiers":[
        {
            "category":"Shopping",
            "type":"Retail Goods"
        }
    ],
    "sg:phone":"+1   ",
    "sg:postcode":"14626",
    "sg:province":"NY",
    "sg:tags":[
        "merchandise"
    ],
    "wof:name":"DC Retail I Inc",
    "wof:placetype":"venue"
},
  "geometry": {"coordinates":[-77.696105,43.204839],"type":"Point"}
}