{
  "type": "Feature",
  "properties": {
    "iso:country":"US",
    "sg:address":"237 S 4th St",
    "sg:city":"Brooklyn",
    "sg:classifiers":[
        {
            "category":"Personal",
            "subcategory":"Beauty Salon",
            "type":"Services"
        }
    ],
    "sg:phone":"+1   ",
    "sg:postcode":"11211",
    "sg:province":"NY",
    "sg:tags":[
        "shop"
    ],
    "wof:name":"New York Star Nails",
    "wof:placetype":"venue"
},
  "geometry": {"coordinates":[-73.959188,40.710675],"type":"Point"}
}