{
  "type": "Feature",
  "properties": {
    "addr:full":"19 Eaton Ave Norwich NY 13815",
    "addr:housenumber":"19",
    "addr:postcode":"13815",
    "addr:street":"Eaton Ave",
    "iso:country":"US",
    "sg:address":"19 Eaton Ave",
    "sg:city":"Norwich",
    "sg:classifiers":[
        {
            "category":"Utilities",
            "subcategory":"Mobile Phone",
            "type":"Services"
        }
    ],
    "sg:phone":"+1 607 336 6752",
    "sg:postcode":"13815",
    "sg:province":"NY",
    "sg:tags":[
        "telephone",
        "cellular"
    ],
    "wof:name":"Cellular One",
    "wof:placetype":"venue"
},
  "geometry": {"coordinates":[-75.525409,42.527875],"type":"Point"}
}