{
  "type": "Feature",
  "properties": {
    "addr:full":"38 Keeler Ave Moravia NY 13118",
    "addr:housenumber":"38",
    "addr:postcode":"13118",
    "addr:street":"Keeler Ave",
    "iso:country":"US",
    "sg:address":"38 Keeler Ave",
    "sg:city":"Moravia",
    "sg:classifiers":[
        {
            "category":"Government",
            "subcategory":"Fire Station",
            "type":"Public Place"
        }
    ],
    "sg:phone":"+1 315 497 1700",
    "sg:postcode":"13118",
    "sg:province":"NY",
    "sg:tags":[
        "department"
    ],
    "wof:name":"Moravia, Town Of Inc",
    "wof:placetype":"venue"
},
  "geometry": {"coordinates":[-76.42778,42.715358],"type":"Point"}
}