{
  "type": "Feature",
  "properties": {
    "iso:country":"US",
    "sg:address":"99 Woodbury Rd",
    "sg:city":"Hicksville",
    "sg:classifiers":[
        {
            "category":"Professional",
            "type":"Services"
        },
        {
            "category":"Wholesale",
            "subcategory":"Chemicals & Plastics",
            "type":"Manufacturing & Wholesale Goods"
        }
    ],
    "sg:phone":"+1 516 932 3457",
    "sg:postcode":"11801",
    "sg:province":"NY",
    "sg:tags":[
        "establishment",
        "export",
        "resin"
    ],
    "wof:name":"Popular International Trading",
    "wof:placetype":"venue"
},
  "geometry": {"coordinates":[-73.518514,40.771367],"type":"Point"}
}