{
  "type": "Feature",
  "properties": {
    "iso:country":"US",
    "sg:address":"1133 Broadway",
    "sg:city":"New York",
    "sg:classifiers":[
        {
            "category":"Professional",
            "subcategory":"Management & Consulting",
            "type":"Services"
        },
        {
            "category":"Wholesale",
            "subcategory":"Durable Goods & Equipment",
            "type":"Manufacturing & Wholesale Goods"
        }
    ],
    "sg:phone":"+1 212 229 2255",
    "sg:postcode":"10010",
    "sg:province":"NY",
    "sg:tags":[
        "representative",
        "public",
        "relations",
        "manufacturer"
    ],
    "wof:name":"Gift Linker Inc",
    "wof:placetype":"venue"
},
  "geometry": {"coordinates":[-73.989161,40.74327],"type":"Point"}
}