{
  "type": "Feature",
  "properties": {
    "iso:country":"US",
    "sg:address":"210 Middle Country Rd",
    "sg:city":"Middle Island",
    "sg:classifiers":[
        {
            "category":"Building & Trades",
            "subcategory":"Construction",
            "type":"Services"
        }
    ],
    "sg:phone":"+1 631 698 5833",
    "sg:postcode":"11953",
    "sg:province":"NY",
    "sg:tags":[
        "excavating",
        "contractor"
    ],
    "wof:name":"Collins Construction Corp",
    "wof:placetype":"venue"
},
  "geometry": {"coordinates":[-72.968091,40.877492],"type":"Point"}
}