{
  "type": "Feature",
  "properties": {
    "iso:country":"US",
    "sg:address":"3783 State Hwy 9g",
    "sg:city":"Germantown",
    "sg:classifiers":[
        {
            "category":"Professional",
            "type":"Services"
        }
    ],
    "sg:phone":"+1 518 537 2365",
    "sg:postcode":"12526",
    "sg:province":"NY",
    "sg:tags":[
        "establishment"
    ],
    "wof:name":"Peter B Leggett Custom Woodwkg",
    "wof:placetype":"venue"
},
  "geometry": {"coordinates":[-73.89635199999999,42.096272],"type":"Point"}
}