{
  "type": "Feature",
  "properties": {
    "addr:full":"75 Buttonwood Dr Huntington Station NY 11746",
    "addr:housenumber":"75",
    "addr:postcode":"11746",
    "addr:street":"Buttonwood Dr",
    "iso:country":"US",
    "sg:address":"75 Buttonwood Dr",
    "sg:city":"Huntington Station",
    "sg:classifiers":[
        {
            "category":"Professional",
            "type":"Services"
        },
        {
            "category":"Health Services",
            "subcategory":"Clinic",
            "type":"Services"
        }
    ],
    "sg:phone":"+1 631 499 0335",
    "sg:postcode":"11746",
    "sg:province":"NY",
    "sg:tags":[
        "establishment"
    ],
    "wof:name":"Med-Probe Examiners Inc",
    "wof:placetype":"venue"
},
  "geometry": {"coordinates":[-73.322884,40.8192],"type":"Point"}
}