{
  "type": "Feature",
  "properties": {
    "iso:country":"US",
    "sg:address":"67 Grant Ave",
    "sg:city":"Harrison",
    "sg:classifiers":[
        {
            "category":"Building & Trades",
            "subcategory":"Landscaping Services",
            "type":"Services"
        }
    ],
    "sg:phone":"+1 914 835 5733",
    "sg:postcode":"10528",
    "sg:province":"NY",
    "sg:tags":[
        "landscape",
        "contractor"
    ],
    "wof:name":"Peter Navarra Landscape",
    "wof:placetype":"venue"
},
  "geometry": {"coordinates":[-73.707365,40.968952],"type":"Point"}
}