{
  "type": "Feature",
  "properties": {
    "addr:full":"323 Brighton Ave Hawthorne NY 10532",
    "addr:housenumber":"323",
    "addr:postcode":"10532",
    "addr:street":"Brighton Ave",
    "iso:country":"US",
    "sg:address":"323 Brighton Ave",
    "sg:city":"Hawthorne",
    "sg:classifiers":[
        {
            "category":"Professional",
            "type":"Services"
        }
    ],
    "sg:phone":"+1   ",
    "sg:postcode":"10532",
    "sg:province":"NY",
    "wof:name":"Mgt In Dragon Rescue",
    "wof:placetype":"venue"
},
  "geometry": {"coordinates":[-73.802736,41.105689],"type":"Point"}
}