{
  "type": "Feature",
  "properties": {
    "addr:full":"54 Palmer Ave Bronxville NY 10708",
    "addr:housenumber":"54",
    "addr:postcode":"10708",
    "addr:street":"Palmer Ave",
    "iso:country":"US",
    "sg:address":"54 Palmer Ave",
    "sg:city":"Bronxville",
    "sg:classifiers":[
        {
            "category":"Real Estate",
            "subcategory":"Real Estate Agent",
            "type":"Services"
        }
    ],
    "sg:phone":"+1 914 779 0405",
    "sg:postcode":"10708",
    "sg:province":"NY",
    "sg:website":"www.brozmanarcher.com",
    "wof:name":"Brozman Archer Realty Corp",
    "wof:placetype":"venue"
},
  "geometry": {"coordinates":[-73.835703,40.941656],"type":"Point"}
}