{
  "type": "Feature",
  "properties": {
    "iso:country":"US",
    "sg:address":"1126 Lake Park Ln",
    "sg:city":"Webster",
    "sg:classifiers":[
        {
            "category":"Manufacturing",
            "subcategory":"Tools & Machinery",
            "type":"Manufacturing & Wholesale Goods"
        }
    ],
    "sg:phone":"+1   ",
    "sg:postcode":"14580",
    "sg:province":"NY",
    "sg:tags":[
        "machine",
        "vending",
        "mfg"
    ],
    "wof:name":"Gold Star Vending",
    "wof:placetype":"venue"
},
  "geometry": {"coordinates":[-77.446522,43.239231],"type":"Point"}
}