{
  "type": "Feature",
  "properties": {
    "iso:country":"US",
    "sg:address":"6869 Furnace Rd",
    "sg:city":"Ontario",
    "sg:classifiers":[
        {
            "category":"Building & Trades",
            "subcategory":"Construction",
            "type":"Services"
        }
    ],
    "sg:phone":"+1 315 524 2421",
    "sg:postcode":"14519",
    "sg:province":"NY",
    "sg:tags":[
        "welder"
    ],
    "wof:name":"Jeff Ernst Welding",
    "wof:placetype":"venue"
},
  "geometry": {"coordinates":[-77.275612,43.246093],"type":"Point"}
}