{
  "type": "Feature",
  "properties": {
    "addr:full":"45 Roslyn Rd Roslyn Heights NY 11577",
    "addr:housenumber":"45",
    "addr:postcode":"11577",
    "addr:street":"Roslyn Rd",
    "iso:country":"US",
    "sg:address":"45 Roslyn Rd",
    "sg:city":"Roslyn Heights",
    "sg:classifiers":[
        {
            "category":"Banks & Credit Unions",
            "subcategory":"Investment Brokerage",
            "type":"Services"
        }
    ],
    "sg:phone":"+1 516 621 2986",
    "sg:postcode":"11577",
    "sg:province":"NY",
    "sg:tags":[
        "security"
    ],
    "wof:name":"Leonard Rosmarin",
    "wof:placetype":"venue"
},
  "geometry": {"coordinates":[-73.640963,40.792003],"type":"Point"}
}