{
  "type": "Feature",
  "properties": {
    "addr:full":"305 Ocean View Ave Brooklyn NY 11235",
    "addr:housenumber":"305",
    "addr:postcode":"11235",
    "addr:street":"Ocean View Ave",
    "iso:country":"US",
    "sg:address":"305 Ocean View Ave",
    "sg:city":"Brooklyn",
    "sg:classifiers":[
        {
            "category":"Community Center",
            "type":"Public Place"
        }
    ],
    "sg:phone":"+1 718 743 3100",
    "sg:postcode":"11235",
    "sg:province":"NY",
    "sg:tags":[
        "medical"
    ],
    "wof:name":"Bella Alloyts 21st Century Medical Center",
    "wof:placetype":"venue"
},
  "geometry": {"coordinates":[-73.964699,40.579102],"type":"Point"}
}