{
  "type": "Feature",
  "properties": {
    "addr:full":"150 Palm St Rochester NY 14615",
    "addr:housenumber":"150",
    "addr:postcode":"14615",
    "addr:street":"Palm St",
    "iso:country":"US",
    "sg:address":"150 Palm St",
    "sg:city":"Rochester",
    "sg:classifiers":[
        {
            "category":"Building & Trades",
            "subcategory":"Construction",
            "type":"Services"
        }
    ],
    "sg:phone":"+1 585 647 3030",
    "sg:postcode":"14615",
    "sg:province":"NY",
    "sg:tags":[
        "seal",
        "driveway",
        "cement",
        "plowing"
    ],
    "wof:name":"Kevin & Russ Driveway Sealing",
    "wof:placetype":"venue"
},
  "geometry": {"coordinates":[-77.636914,43.197427],"type":"Point"}
}