{
  "type": "Feature",
  "properties": {
    "addr:full":"40 Ufferts Rd Catskill NY 12414",
    "addr:housenumber":"40",
    "addr:postcode":"12414",
    "addr:street":"Ufferts Rd",
    "iso:country":"US",
    "sg:address":"40 Ufferts Rd",
    "sg:city":"Catskill",
    "sg:classifiers":[
        {
            "category":"Home & Garden",
            "subcategory":"Building Materials",
            "type":"Retail Goods"
        }
    ],
    "sg:phone":"+1   ",
    "sg:postcode":"12414",
    "sg:province":"NY",
    "wof:name":"C & R Overhead Garage Door",
    "wof:placetype":"venue"
},
  "geometry": {"coordinates":[-73.95335900000001,42.211955],"type":"Point"}
}