{
  "type": "Feature",
  "properties": {
    "iso:country":"US",
    "sg:address":"3326 Southwestern Blvd",
    "sg:city":"Orchard Park",
    "sg:classifiers":[
        {
            "category":"Health Services",
            "subcategory":"Doctor",
            "type":"Services"
        }
    ],
    "sg:phone":"+1 716 636 8686",
    "sg:postcode":"14127",
    "sg:province":"NY",
    "sg:tags":[
        "dentist"
    ],
    "wof:name":"Barzman Kasimov & Vieth",
    "wof:placetype":"venue"
},
  "geometry": {"coordinates":[-78.755814,42.793383],"type":"Point"}
}