{
  "type": "Feature",
  "properties": {
    "iso:country":"US",
    "sg:address":"1553 Broadway",
    "sg:city":"New York",
    "sg:classifiers":[
        {
            "category":"Cinema",
            "subcategory":"Movie Theater",
            "type":"Entertainment"
        }
    ],
    "sg:phone":"+1 212 575 9767",
    "sg:postcode":"10036",
    "sg:province":"NY",
    "wof:name":"Aronseven Theatre",
    "wof:placetype":"venue"
},
  "geometry": {"coordinates":[-73.98516499999999,40.759332],"type":"Point"}
}