{
  "type": "Feature",
  "properties": {
    "iso:country":"US",
    "sg:address":"3535 Merrick Rd",
    "sg:city":"Seaford",
    "sg:classifiers":[
        {
            "category":"Restaurant",
            "type":"Food & Drink"
        }
    ],
    "sg:menulink":"http://www.allmenus.com/ny/bellmore-merrick/58105-pantanos-pizza-kitchen/menu/",
    "sg:phone":"+1 516 546 6500",
    "sg:postcode":"11783",
    "sg:province":"NY",
    "sg:tags":[
        "american",
        "sandwich",
        "pizza"
    ],
    "wof:name":"Pantano's Pizza Kitchen",
    "wof:placetype":"venue"
},
  "geometry": {"coordinates":[-73.499762,40.665458],"type":"Point"}
}