{
  "type": "Feature",
  "properties": {
    "addr:full":"1859 Lakeland Ave Ronkonkoma NY 11779",
    "addr:housenumber":"1859",
    "addr:postcode":"11779",
    "addr:street":"Lakeland Ave",
    "iso:country":"US",
    "sg:address":"1859 Lakeland Ave",
    "sg:city":"Ronkonkoma",
    "sg:classifiers":[
        {
            "category":"Wholesale",
            "subcategory":"Electrical",
            "type":"Manufacturing & Wholesale Goods"
        }
    ],
    "sg:phone":"+1 631 471 2202",
    "sg:postcode":"11779",
    "sg:province":"NY",
    "sg:tags":[
        "equipment"
    ],
    "wof:name":"Honeywell",
    "wof:placetype":"venue"
},
  "geometry": {"coordinates":[-73.117766,40.791576],"type":"Point"}
}