{
  "type": "Feature",
  "properties": {
    "iso:country":"US",
    "sg:address":"18 Corporate Woods Blvd # 200",
    "sg:city":"Albany",
    "sg:classifiers":[
        {
            "category":"Wholesale",
            "subcategory":"Computers",
            "type":"Manufacturing & Wholesale Goods"
        }
    ],
    "sg:phone":"+1 518 427 5200",
    "sg:postcode":"12211",
    "sg:province":"NY",
    "sg:tags":[
        "equipment",
        "computer-wholesale",
        "manufacturer"
    ],
    "sg:website":"http://www.cisco.com",
    "wof:name":"Cisco Systems",
    "wof:placetype":"venue"
},
  "geometry": {"coordinates":[-73.764748,42.680691],"type":"Point"}
}