{
  "type": "Feature",
  "properties": {
    "iso:country":"US",
    "sg:address":"3624 Middle Reservation Rd",
    "sg:city":"Perry",
    "sg:classifiers":[
        {
            "category":"Real Estate",
            "subcategory":"Real Estate Agent",
            "type":"Services"
        }
    ],
    "sg:phone":"+1 585 237 5300",
    "sg:postcode":"14530",
    "sg:province":"NY",
    "wof:name":"Mazzarella Realestate Office",
    "wof:placetype":"venue"
},
  "geometry": {"coordinates":[-77.995999,42.713016],"type":"Point"}
}