{
  "type": "Feature",
  "properties": {
    "iso:country":"US",
    "sg:address":"200 Bus Park Dr",
    "sg:city":"Armonk",
    "sg:classifiers":[
        {
            "category":"Health Services",
            "subcategory":"Health Practitioner",
            "type":"Services"
        }
    ],
    "sg:phone":"+1 914 730 0210",
    "sg:postcode":"10504",
    "sg:province":"NY",
    "sg:tags":[
        "occupational",
        "therapist"
    ],
    "wof:name":"Westchester Occupational Thrpy",
    "wof:placetype":"venue"
},
  "geometry": {"coordinates":[-73.708921,41.118256],"type":"Point"}
}