{
  "type": "Feature",
  "properties": {
    "addr:full":"750 Bradley St Watertown NY 13601",
    "addr:housenumber":"750",
    "addr:postcode":"13601",
    "addr:street":"Bradley St",
    "iso:country":"US",
    "sg:address":"750 Bradley St",
    "sg:city":"Watertown",
    "sg:classifiers":[
        {
            "category":"Shopping",
            "subcategory":"Books",
            "type":"Retail Goods"
        }
    ],
    "sg:phone":"+1   ",
    "sg:postcode":"13601",
    "sg:province":"NY",
    "wof:name":"Sanctuary Comics",
    "wof:placetype":"venue"
},
  "geometry": {"coordinates":[-75.915481,43.988059],"type":"Point"}
}