{
  "type": "Feature",
  "properties": {
    "iso:country":"US",
    "sg:address":"902 Gill St",
    "sg:city":"Chittenango",
    "sg:classifiers":[
        {
            "category":"Professional",
            "subcategory":"Art Services",
            "type":"Services"
        }
    ],
    "sg:phone":"+1 315 687 3528",
    "sg:postcode":"13037",
    "sg:province":"NY",
    "sg:tags":[
        "photographer"
    ],
    "wof:name":"Susan Kahn Photography",
    "wof:placetype":"venue"
},
  "geometry": {"coordinates":[-75.892792,43.048988],"type":"Point"}
}