{
  "type": "Feature",
  "properties": {
    "addr:full":"9034 139th St Jamaica NY 11435",
    "addr:housenumber":"9034",
    "addr:postcode":"11435",
    "addr:street":"139Th St",
    "iso:country":"US",
    "sg:address":"9034 139th St",
    "sg:city":"Jamaica",
    "sg:classifiers":[
        {
            "category":"Banks & Credit Unions",
            "subcategory":"Bank",
            "type":"Services"
        }
    ],
    "sg:phone":"+1 718 658 8588",
    "sg:postcode":"11435",
    "sg:province":"NY",
    "sg:tags":[
        "bond",
        "broker",
        "stock"
    ],
    "sg:website":"http://www.kashmirrelief.org",
    "wof:name":"Kashmir Fund",
    "wof:placetype":"venue"
},
  "geometry": {"coordinates":[-73.813396,40.702841],"type":"Point"}
}