{
  "type": "Feature",
  "properties": {
    "addr:full":"24 Clinton Ave Tappan NY 10983",
    "addr:housenumber":"24",
    "addr:postcode":"10983",
    "addr:street":"Clinton Ave",
    "iso:country":"US",
    "sg:address":"24 Clinton Ave",
    "sg:city":"Tappan",
    "sg:classifiers":[
        {
            "category":"Professional",
            "subcategory":"Management & Consulting",
            "type":"Services"
        }
    ],
    "sg:phone":"+1 845 398 0996",
    "sg:postcode":"10983",
    "sg:province":"NY",
    "sg:tags":[
        "grocery"
    ],
    "wof:name":"Claudia P Alfonso",
    "wof:placetype":"venue"
},
  "geometry": {"coordinates":[-73.956653,41.027103],"type":"Point"}
}