{
  "type": "Feature",
  "properties": {
    "iso:country":"US",
    "sg:address":"565 Ratta Rd",
    "sg:city":"Chazy",
    "sg:classifiers":[
        {
            "category":"Autos & Motor Vehicles",
            "subcategory":"Automobile Sales",
            "type":"Retail Goods"
        }
    ],
    "sg:phone":"+1 518 846 8546",
    "sg:postcode":"12921",
    "sg:province":"NY",
    "sg:tags":[
        "truck"
    ],
    "wof:name":"Neway Truck Ctr",
    "wof:placetype":"venue"
},
  "geometry": {"coordinates":[-73.44207,44.866466],"type":"Point"}
}