{
  "type": "Feature",
  "properties": {
    "iso:country":"US",
    "sg:address":"61 Delano St",
    "sg:city":"Pulaski",
    "sg:classifiers":[
        {
            "category":"Health Services",
            "subcategory":"Doctor",
            "type":"Services"
        },
        {
            "category":"Health Services",
            "subcategory":"Clinic",
            "type":"Services"
        },
        {
            "category":"Health Services",
            "subcategory":"Dentist",
            "type":"Services"
        }
    ],
    "sg:phone":"+1 315 298 6564",
    "sg:postcode":"13142",
    "sg:province":"NY",
    "sg:tags":[
        "physician",
        "family",
        "medical",
        "practice",
        "surgeons",
        "medicine"
    ],
    "wof:name":"Pulaski Health Center",
    "wof:placetype":"venue"
},
  "geometry": {"coordinates":[-76.117487,43.569483],"type":"Point"}
}