{
  "type": "Feature",
  "properties": {
    "iso:country":"US",
    "sg:address":"1053 Allerton Ave",
    "sg:city":"Bronx",
    "sg:classifiers":[
        {
            "category":"Building & Trades",
            "subcategory":"Construction",
            "type":"Services"
        }
    ],
    "sg:phone":"+1 718 325 3300",
    "sg:postcode":"10469",
    "sg:province":"NY",
    "wof:name":"Atlantic Water & Sewer",
    "wof:placetype":"venue"
},
  "geometry": {"coordinates":[-73.85685599999999,40.865537],"type":"Point"}
}