{
  "type": "Feature",
  "properties": {
    "iso:country":"US",
    "sg:address":"514 5th Ave",
    "sg:city":"Brooklyn",
    "sg:classifiers":[
        {
            "category":"Cinema",
            "subcategory":"Movie Rental",
            "type":"Entertainment"
        }
    ],
    "sg:phone":"+1 718 369 4847",
    "sg:postcode":"11215",
    "sg:province":"NY",
    "sg:tags":[
        "game",
        "video"
    ],
    "wof:name":"Game Champ",
    "wof:placetype":"venue"
},
  "geometry": {"coordinates":[-73.988241,40.666876],"type":"Point"}
}