{
  "type": "Feature",
  "properties": {
    "addr:full":"10380 Chestnut Rd Dunkirk NY 14048",
    "addr:housenumber":"10380",
    "addr:postcode":"14048",
    "addr:street":"Chestnut Rd",
    "iso:country":"US",
    "sg:address":"10380 Chestnut Rd",
    "sg:city":"Dunkirk",
    "sg:classifiers":[
        {
            "category":"Real Estate",
            "subcategory":"Real Estate Agent",
            "type":"Services"
        }
    ],
    "sg:phone":"+1 716 672 6162",
    "sg:postcode":"14048",
    "sg:province":"NY",
    "sg:tags":[
        "inspection"
    ],
    "wof:name":"Atb Home Inspection",
    "wof:placetype":"venue"
},
  "geometry": {"coordinates":[-79.354494,42.449816],"type":"Point"}
}