{
  "type": "Feature",
  "properties": {
    "addr:full":"510 Broad Hollow Rd Melville NY 11747",
    "addr:housenumber":"510",
    "addr:postcode":"11747",
    "addr:street":"Broad Hollow Rd",
    "iso:country":"US",
    "sg:address":"510 Broad Hollow Rd",
    "sg:city":"Melville",
    "sg:classifiers":[
        {
            "category":"Professional",
            "subcategory":"Lawyer & Legal Services",
            "type":"Services"
        }
    ],
    "sg:phone":"+1 631 249 3978",
    "sg:postcode":"11747",
    "sg:province":"NY",
    "sg:tags":[
        "attorney"
    ],
    "wof:name":"Burke & Burke PC Atty",
    "wof:placetype":"venue"
},
  "geometry": {"coordinates":[-73.423402,40.763455],"type":"Point"}
}