{
  "type": "Feature",
  "properties": {
    "iso:country":"US",
    "sg:address":"935 Northern Boulevard Suite 300",
    "sg:city":"Great Neck",
    "sg:classifiers":[
        {
            "category":"Health Services",
            "subcategory":"Doctor",
            "type":"Services"
        }
    ],
    "sg:phone":"+1 516 466 5437",
    "sg:postcode":"11021",
    "sg:province":"NY",
    "sg:tags":[
        "pediatrician"
    ],
    "sg:website":"www.mds4kids.com",
    "wof:name":"MDS 4 Kids Medical Pllc",
    "wof:placetype":"venue"
},
  "geometry": {"coordinates":[-73.706709,40.786129],"type":"Point"}
}