{
  "type": "Feature",
  "properties": {
    "iso:country":"US",
    "sg:address":"323 Long Island Ave",
    "sg:city":"Holtsville",
    "sg:classifiers":[
        {
            "category":"Professional",
            "subcategory":"Business Services",
            "type":"Services"
        }
    ],
    "sg:phone":"+1 631 289 3508",
    "sg:postcode":"11742",
    "sg:province":"NY",
    "sg:tags":[
        "organizing",
        "services-household"
    ],
    "wof:name":"Realtime Media Management",
    "wof:placetype":"venue"
},
  "geometry": {"coordinates":[-73.02564599999999,40.815985],"type":"Point"}
}