{
  "type": "Feature",
  "properties": {
    "iso:country":"US",
    "sg:address":"207 Main St",
    "sg:city":"Nyack",
    "sg:classifiers":[
        {
            "category":"Manufacturing",
            "subcategory":"Printing",
            "type":"Manufacturing & Wholesale Goods"
        }
    ],
    "sg:phone":"+1 845 353 1832",
    "sg:postcode":"10960",
    "sg:province":"NY",
    "sg:tags":[
        "printer"
    ],
    "wof:name":"Harrington Press",
    "wof:placetype":"venue"
},
  "geometry": {"coordinates":[-73.92339699999999,41.09174],"type":"Point"}
}