{
  "type": "Feature",
  "properties": {
    "addr:full":"21 Seabro Ave Amityville NY 11701",
    "addr:housenumber":"21",
    "addr:postcode":"11701",
    "addr:street":"Seabro Ave",
    "iso:country":"US",
    "sg:address":"21 Seabro Ave",
    "sg:city":"Amityville",
    "sg:classifiers":[
        {
            "category":"Manufacturing",
            "subcategory":"Furniture",
            "type":"Manufacturing & Wholesale Goods"
        }
    ],
    "sg:phone":"+1   ",
    "sg:postcode":"11701",
    "sg:province":"NY",
    "sg:tags":[
        "repair",
        "business",
        "mfg",
        "household",
        "wood",
        "furn"
    ],
    "wof:name":"Cavalieri Pianos",
    "wof:placetype":"venue"
},
  "geometry": {"coordinates":[-73.398178,40.713731],"type":"Point"}
}