{
  "type": "Feature",
  "properties": {
    "addr:full":"620 W 135th St New York NY 10031",
    "addr:housenumber":"620",
    "addr:postcode":"10031",
    "addr:street":"W 135Th St",
    "iso:country":"US",
    "sg:address":"620 W 135th St",
    "sg:city":"New York",
    "sg:classifiers":[
        {
            "category":"Social Services",
            "subcategory":"Child Care",
            "type":"Services"
        }
    ],
    "sg:phone":"+1   ",
    "sg:postcode":"10031",
    "sg:province":"NY",
    "sg:tags":[
        "day"
    ],
    "wof:name":"Nanas Place 4 Tots",
    "wof:placetype":"venue"
},
  "geometry": {"coordinates":[-73.957126,40.820849],"type":"Point"}
}