{
  "type": "Feature",
  "properties": {
    "addr:full":"179 Temple Hill Rd New Windsor NY 12553",
    "addr:housenumber":"179",
    "addr:postcode":"12553",
    "addr:street":"Temple Hill Rd",
    "iso:country":"US",
    "sg:address":"179 Temple Hill Rd",
    "sg:city":"New Windsor",
    "sg:classifiers":[
        {
            "category":"Personal",
            "subcategory":"Beauty Salon",
            "type":"Services"
        }
    ],
    "sg:phone":"+1 845 565 3940",
    "sg:postcode":"12553",
    "sg:province":"NY",
    "wof:name":"Le Vie Salon Spa",
    "wof:placetype":"venue"
},
  "geometry": {"coordinates":[-74.06106699999999,41.460109],"type":"Point"}
}