{
  "type": "Feature",
  "properties": {
    "addr:full":"51 Wood Rd Round Lake NY 12151",
    "addr:housenumber":"51",
    "addr:postcode":"12151",
    "addr:street":"Wood Rd",
    "iso:country":"US",
    "sg:address":"51 Wood Rd",
    "sg:city":"Round Lake",
    "sg:classifiers":[
        {
            "category":"Autos & Motor Vehicles",
            "subcategory":"Recreational Vehicle Sales",
            "type":"Retail Goods"
        }
    ],
    "sg:phone":"+1 518 877 5001",
    "sg:postcode":"12151",
    "sg:province":"NY",
    "sg:tags":[
        "parts",
        "trailer"
    ],
    "wof:name":"Red Neck Trailer Supply",
    "wof:placetype":"venue"
},
  "geometry": {"coordinates":[-73.79350100000001,42.92626],"type":"Point"}
}