{
  "type": "Feature",
  "properties": {
    "iso:country":"US",
    "sg:address":"590 Duke Rd",
    "sg:city":"Buffalo",
    "sg:classifiers":[
        {
            "category":"Manufacturing",
            "subcategory":"Tools & Machinery",
            "type":"Manufacturing & Wholesale Goods"
        }
    ],
    "sg:phone":"+1 716 683 9010",
    "sg:postcode":"14225",
    "sg:province":"NY",
    "sg:tags":[
        "equipment",
        "screening",
        "sifting"
    ],
    "sg:website":"www.derrickcorp.com",
    "wof:name":"Derrick Corp",
    "wof:placetype":"venue"
},
  "geometry": {"coordinates":[-78.76014499999999,42.90404],"type":"Point"}
}