{
  "type": "Feature",
  "properties": {
    "iso:country":"US",
    "sg:address":"1418 Old Rte 9",
    "sg:city":"Fishkill",
    "sg:classifiers":[
        {
            "category":"Wholesale",
            "subcategory":"Machinery & Supplies",
            "type":"Manufacturing & Wholesale Goods"
        }
    ],
    "sg:phone":"+1 845 838 6340",
    "sg:postcode":"12524",
    "sg:province":"NY",
    "wof:name":"Granite Halmar Construction",
    "wof:placetype":"venue"
},
  "geometry": {"coordinates":[-73.90112499999999,41.551907],"type":"Point"}
}