{
  "type": "Feature",
  "properties": {
    "addr:full":"22125 Linden Blvd Cambria Heights NY 11411",
    "addr:housenumber":"22125",
    "addr:postcode":"11411",
    "addr:street":"Linden Blvd",
    "iso:country":"US",
    "sg:address":"22125 Linden Blvd",
    "sg:city":"Cambria Heights",
    "sg:classifiers":[
        {
            "category":"Restaurant",
            "type":"Food & Drink"
        }
    ],
    "sg:menulink":"http://www.allmenus.com/ny/queens/236603-great-wall/menu/",
    "sg:phone":"+1 718 723 7221",
    "sg:postcode":"11411",
    "sg:province":"NY",
    "sg:tags":[
        "asian",
        "chinese"
    ],
    "wof:name":"Great Wall",
    "wof:placetype":"venue"
},
  "geometry": {"coordinates":[-73.73905000000001,40.694799],"type":"Point"}
}