{
  "type": "Feature",
  "properties": {
    "iso:country":"US",
    "sg:address":"4 Pleasantview Ave",
    "sg:city":"Albany",
    "sg:classifiers":[
        {
            "category":"Social Services",
            "subcategory":"Adult Care",
            "type":"Services"
        }
    ],
    "sg:phone":"+1 518 489 7421",
    "sg:postcode":"12203",
    "sg:province":"NY",
    "sg:tags":[
        "management",
        "disability"
    ],
    "wof:name":"Crawford Care Management Svcs",
    "wof:placetype":"venue"
},
  "geometry": {"coordinates":[-73.82317500000001,42.672868],"type":"Point"}
}