{
  "type": "Feature",
  "properties": {
    "addr:full":"1623 Eggert Rd Buffalo NY 14226",
    "addr:housenumber":"1623",
    "addr:postcode":"14226",
    "addr:street":"Eggert Rd",
    "iso:country":"US",
    "sg:address":"1623 Eggert Rd",
    "sg:city":"Buffalo",
    "sg:classifiers":[
        {
            "category":"Food & Beverages",
            "subcategory":"Groceries & Convenience Stores",
            "type":"Retail Goods"
        }
    ],
    "sg:phone":"+1   ",
    "sg:postcode":"14226",
    "sg:province":"NY",
    "wof:name":"Wilson Farms 340",
    "wof:placetype":"venue"
},
  "geometry": {"coordinates":[-78.807209,42.973105],"type":"Point"}
}