{
  "type": "Feature",
  "properties": {
    "addr:full":"98 Hawxhurst Rd Monroe NY 10950",
    "addr:housenumber":"98",
    "addr:postcode":"10950",
    "addr:street":"Hawxhurst Rd",
    "iso:country":"US",
    "sg:address":"98 Hawxhurst Rd",
    "sg:city":"Monroe",
    "sg:classifiers":[
        {
            "category":"Building & Trades",
            "subcategory":"Construction",
            "type":"Services"
        }
    ],
    "sg:phone":"+1 845 783 9265",
    "sg:postcode":"10950",
    "sg:province":"NY",
    "sg:tags":[
        "contractor"
    ],
    "wof:name":"Parking Lot Striping",
    "wof:placetype":"venue"
},
  "geometry": {"coordinates":[-74.185552,41.30057],"type":"Point"}
}