{
  "type": "Feature",
  "properties": {
    "addr:full":"68 Jay St #101 New York NY 11201",
    "addr:housenumber":"68;101",
    "addr:postcode":"11201",
    "addr:street":"Jay St #",
    "iso:country":"US",
    "sg:address":"68 Jay St #101",
    "sg:city":"New York",
    "sg:classifiers":[
        {
            "category":"Shopping",
            "subcategory":"Clothing, Apparel, & Fashions",
            "type":"Retail Goods"
        }
    ],
    "sg:phone":"+1 718 522 6488",
    "sg:postcode":"11201",
    "sg:province":"NY",
    "sg:tags":[
        "clothing",
        "women's"
    ],
    "sg:website":"www.trunkbrooklyn.com",
    "wof:name":"Trunk",
    "wof:placetype":"venue"
},
  "geometry": {"coordinates":[-73.986745,40.703005],"type":"Point"}
}