{
  "type": "Feature",
  "properties": {
    "addr:full":"760 E 149th Street Bronx NY 10455",
    "addr:housenumber":"760",
    "addr:postcode":"10455",
    "addr:street":"E 149Th Street",
    "iso:country":"US",
    "sg:address":"760 E 149th Street",
    "sg:city":"Bronx",
    "sg:classifiers":[
        {
            "category":"Restaurant",
            "type":"Food & Drink"
        }
    ],
    "sg:phone":"+1 718 665 0993",
    "sg:postcode":"10455",
    "sg:province":"NY",
    "wof:name":"New Fuh Wah Restaurant",
    "wof:placetype":"venue"
},
  "geometry": {"coordinates":[-73.907567,40.812804],"type":"Point"}
}