{
  "type": "Feature",
  "properties": {
    "addr:full":"25 Broad St Hamilton NY 13346",
    "addr:housenumber":"25",
    "addr:postcode":"13346",
    "addr:street":"Broad St",
    "iso:country":"US",
    "sg:address":"25 Broad St",
    "sg:city":"Hamilton",
    "sg:classifiers":[
        {
            "category":"Retail",
            "subcategory":"Funeral Services",
            "type":"Services"
        }
    ],
    "sg:phone":"+1 315 824 2417",
    "sg:postcode":"13346",
    "sg:province":"NY",
    "sg:tags":[
        "director"
    ],
    "wof:name":"Burgess & Tedesco Funeral",
    "wof:placetype":"venue"
},
  "geometry": {"coordinates":[-75.54284699999999,42.825272],"type":"Point"}
}