{
  "type": "Feature",
  "properties": {
    "addr:full":"172 W Okara Dr Schenectady NY 12303",
    "addr:housenumber":"172",
    "addr:postcode":"12303",
    "addr:street":"W Okara Dr",
    "iso:country":"US",
    "sg:address":"172 W Okara Dr",
    "sg:city":"Schenectady",
    "sg:classifiers":[
        {
            "category":"Sports & Exercise",
            "subcategory":"Gym",
            "type":"Entertainment"
        }
    ],
    "sg:phone":"+1 518 674 1226",
    "sg:postcode":"12303",
    "sg:province":"NY",
    "sg:tags":[
        "club",
        "health",
        "studio",
        "gymnasium"
    ],
    "wof:name":"Curves",
    "wof:placetype":"venue"
},
  "geometry": {"coordinates":[-73.92612699999999,42.713696],"type":"Point"}
}