{
  "type": "Feature",
  "properties": {
    "iso:country":"US",
    "sg:address":"341 Clinton St",
    "sg:city":"Brooklyn",
    "sg:classifiers":[
        {
            "category":"Building & Trades",
            "subcategory":"Construction",
            "type":"Services"
        }
    ],
    "sg:phone":"+1 718 386 4134",
    "sg:postcode":"11231",
    "sg:province":"NY",
    "sg:tags":[
        "carpentry",
        "contractor"
    ],
    "wof:name":"Red River Woodworking",
    "wof:placetype":"venue"
},
  "geometry": {"coordinates":[-73.996702,40.685512],"type":"Point"}
}