{
  "type": "Feature",
  "properties": {
    "iso:country":"US",
    "sg:address":"2008 Eastchester Rd",
    "sg:city":"Bronx",
    "sg:classifiers":[
        {
            "category":"Food & Beverages",
            "subcategory":"Specialty",
            "type":"Retail Goods"
        }
    ],
    "sg:phone":"+1 718 239 2030",
    "sg:postcode":"10461",
    "sg:province":"NY",
    "sg:tags":[
        "health",
        "diet"
    ],
    "wof:name":"Natures Choice Health Food",
    "wof:placetype":"venue"
},
  "geometry": {"coordinates":[-73.843524,40.854432],"type":"Point"}
}