{
  "type": "Feature",
  "properties": {
    "iso:country":"US",
    "sg:address":"2060 Fairport Nine Mile Point Rd",
    "sg:city":"Penfield",
    "sg:classifiers":[
        {
            "category":"Professional",
            "subcategory":"Employment Agencies",
            "type":"Services"
        }
    ],
    "sg:phone":"+1 585 377 1100",
    "sg:postcode":"14526",
    "sg:province":"NY",
    "sg:tags":[
        "help",
        "contractor"
    ],
    "sg:website":"www.cdicorp.com",
    "wof:name":"CDI Information Svc",
    "wof:placetype":"venue"
},
  "geometry": {"coordinates":[-77.44147,43.132747],"type":"Point"}
}