{
  "type": "Feature",
  "properties": {
    "iso:country":"US",
    "sg:address":"134 W 37th St",
    "sg:city":"New York",
    "sg:classifiers":[
        {
            "category":"Restaurant",
            "type":"Food & Drink"
        }
    ],
    "sg:menulink":"http://www.allmenus.com/ny/new-york/247892-just-salad/menu/",
    "sg:phone":"+1 212 244 1111",
    "sg:postcode":"10018",
    "sg:province":"NY",
    "sg:tags":[
        "american"
    ],
    "wof:name":"Just Salad",
    "wof:placetype":"venue"
},
  "geometry": {"coordinates":[-73.988477,40.752325],"type":"Point"}
}