{
  "type": "Feature",
  "properties": {
    "addr:full":"890 State Hwy 122 Constable NY 12926",
    "addr:housenumber":"890",
    "addr:postcode":"12926",
    "addr:street":"State Hwy 122 Constable",
    "iso:country":"US",
    "sg:address":"890 State Hwy 122",
    "sg:city":"Constable",
    "sg:classifiers":[
        {
            "category":"Restaurant",
            "type":"Food & Drink"
        }
    ],
    "sg:phone":"+1   ",
    "sg:postcode":"12926",
    "sg:province":"NY",
    "sg:tags":[
        "eating"
    ],
    "wof:name":"Elm Circle Restaurant",
    "wof:placetype":"venue"
},
  "geometry": {"coordinates":[-74.30735199999999,44.928652],"type":"Point"}
}