{
  "type": "Feature",
  "properties": {
    "iso:country":"US",
    "sg:address":"1481 Troy Ave",
    "sg:city":"Brooklyn",
    "sg:classifiers":[
        {
            "category":"Utilities",
            "subcategory":"Refuse",
            "type":"Services"
        },
        {
            "category":"Utilities",
            "subcategory":"Recycling",
            "type":"Services"
        },
        {
            "category":"Wholesale",
            "subcategory":"Drugs",
            "type":"Manufacturing & Wholesale Goods"
        }
    ],
    "sg:phone":"+1 718 338 7252",
    "sg:postcode":"11203",
    "sg:province":"NY",
    "sg:tags":[
        "industrial",
        "garbage",
        "disposal",
        "commercial",
        "collection",
        "equipment",
        "waste"
    ],
    "sg:website":"http://www.decostole.com",
    "wof:name":"Decostole Carting",
    "wof:placetype":"venue"
},
  "geometry": {"coordinates":[-73.934551,40.636259],"type":"Point"}
}