{
  "type": "Feature",
  "properties": {
    "addr:full":"24 09 Steinway St Queens NY 11103",
    "addr:housenumber":"09",
    "addr:postcode":"11103",
    "addr:street":"Steinway St",
    "iso:country":"US",
    "sg:address":"24 09 Steinway St",
    "sg:city":"Queens",
    "sg:classifiers":[
        {
            "category":"Coffee & Tea",
            "type":"Food & Drink"
        },
        {
            "category":"Cafe",
            "type":"Food & Drink"
        }
    ],
    "sg:menulink":"http://www.allmenus.com/ny/queens/294319-cafe-via-espresso/menu/",
    "sg:phone":"+1 718 545 3290",
    "sg:postcode":"11103",
    "sg:province":"NY",
    "sg:tags":[
        "smoothy",
        "sandwich",
        "salad",
        "juice",
        "american",
        "wrap"
    ],
    "wof:name":"Cafe Via Espresso",
    "wof:placetype":"venue"
},
  "geometry": {"coordinates":[-73.911914,40.767649],"type":"Point"}
}