{
  "type": "Feature",
  "properties": {
    "iso:country":"US",
    "sg:address":"645 Lydig Ave",
    "sg:city":"Bronx",
    "sg:classifiers":[
        {
            "category":"Personal",
            "subcategory":"Shoe Repair & Shine",
            "type":"Services"
        }
    ],
    "sg:phone":"+1 718 824 7053",
    "sg:postcode":"10462",
    "sg:province":"NY",
    "sg:tags":[
        "repairing",
        "boot"
    ],
    "wof:name":"Robert's Shoe Repair",
    "wof:placetype":"venue"
},
  "geometry": {"coordinates":[-73.867947,40.854528],"type":"Point"}
}