{
  "type": "Feature",
  "properties": {
    "addr:full":"250 W 57th St Ste 1330 New York NY 10107",
    "addr:housenumber":"250",
    "addr:postcode":"10107",
    "addr:street":"W 57Th St Ste 1330",
    "iso:country":"US",
    "sg:address":"250 W 57th St Ste 1330",
    "sg:city":"New York",
    "sg:classifiers":[
        {
            "category":"Health Services",
            "subcategory":"Health Practitioner",
            "type":"Services"
        }
    ],
    "sg:phone":"+1 212 581 1228",
    "sg:postcode":"10107",
    "sg:province":"NY",
    "sg:tags":[
        "acupuncture"
    ],
    "wof:name":"Zheng Accupuncture PLLC",
    "wof:placetype":"venue"
},
  "geometry": {"coordinates":[-73.982212,40.766279],"type":"Point"}
}