{
  "type": "Feature",
  "properties": {
    "addr:full":"1028 Freeman St Bronx NY 10459",
    "addr:housenumber":"1028",
    "addr:postcode":"10459",
    "addr:street":"Freeman St",
    "iso:country":"US",
    "sg:address":"1028 Freeman St",
    "sg:city":"Bronx",
    "sg:classifiers":[
        {
            "category":"Local Transit",
            "type":"Transportation"
        }
    ],
    "sg:phone":"+1 718 617 1522",
    "sg:postcode":"10459",
    "sg:province":"NY",
    "sg:tags":[
        "ambulance"
    ],
    "wof:name":"Medical Express",
    "wof:placetype":"venue"
},
  "geometry": {"coordinates":[-73.886628,40.828695],"type":"Point"}
}