{
  "type": "Feature",
  "properties": {
    "iso:country":"US",
    "sg:address":"1080 Main St",
    "sg:city":"Fishkill",
    "sg:classifiers":[
        {
            "category":"Autos & Motor Vehicles",
            "subcategory":"Automobile Sales",
            "type":"Retail Goods"
        },
        {
            "category":"Airline",
            "type":"Transportation"
        }
    ],
    "sg:phone":"+1 845 897 0010",
    "sg:postcode":"12524",
    "sg:province":"NY",
    "sg:tags":[
        "shuttle",
        "airport",
        "limo"
    ],
    "sg:website":"www.shamrocklimousines.com",
    "wof:name":"Shamrock Limousine Service",
    "wof:placetype":"venue"
},
  "geometry": {"coordinates":[-73.90311699999999,41.534985],"type":"Point"}
}