{
  "type": "Feature",
  "properties": {
    "addr:full":"1406 1st Ave New York NY 10021",
    "addr:housenumber":"1406",
    "addr:postcode":"10021",
    "addr:street":"1St Ave",
    "iso:country":"US",
    "sg:address":"1406 1st Ave",
    "sg:city":"New York",
    "sg:classifiers":[
        {
            "category":"Retail",
            "subcategory":"Laundry & Dry Cleaning",
            "type":"Services"
        }
    ],
    "sg:phone":"+1 212 772 6472",
    "sg:postcode":"10021",
    "sg:province":"NY",
    "wof:name":"Bright Cleaners",
    "wof:placetype":"venue"
},
  "geometry": {"coordinates":[-73.954803,40.769199],"type":"Point"}
}