{
  "type": "Feature",
  "properties": {
    "iso:country":"US",
    "sg:address":"123 Linden Blvd",
    "sg:city":"Brooklyn",
    "sg:classifiers":[
        {
            "category":"Health Services",
            "subcategory":"Doctor",
            "type":"Services"
        }
    ],
    "sg:phone":"+1 718 940 8386",
    "sg:postcode":"11226",
    "sg:province":"NY",
    "wof:name":"Caribbean Womens Health Assoc",
    "wof:placetype":"venue"
},
  "geometry": {"coordinates":[-73.955299,40.6525],"type":"Point"}
}