{
  "type": "Feature",
  "properties": {
    "addr:full":"122 Lantern Ridge Rd New Canaan NY 06840",
    "addr:housenumber":"122",
    "addr:postcode":"06840",
    "addr:street":"Lantern Ridge Rd",
    "iso:country":"US",
    "sg:address":"122 Lantern Ridge Rd",
    "sg:city":"New Canaan",
    "sg:classifiers":[
        {
            "category":"Professional",
            "subcategory":"Engineering",
            "type":"Services"
        }
    ],
    "sg:phone":"+1   ",
    "sg:postcode":"06840",
    "sg:province":"NY",
    "wof:name":"Thermal Processes LLC",
    "wof:placetype":"venue"
},
  "geometry": {"coordinates":[-73.48994,41.203973],"type":"Point"}
}