{
  "type": "Feature",
  "properties": {
    "iso:country":"US",
    "sg:address":"24 Londonderry Ln",
    "sg:city":"Somers",
    "sg:classifiers":[
        {
            "category":"Professional",
            "subcategory":"Management & Consulting",
            "type":"Services"
        }
    ],
    "sg:phone":"+1 914 248 6952",
    "sg:postcode":"10589",
    "sg:province":"NY",
    "wof:name":"Global Development Group",
    "wof:placetype":"venue"
},
  "geometry": {"coordinates":[-73.70165799999999,41.330812],"type":"Point"}
}