{
  "type": "Feature",
  "properties": {
    "addr:full":"6001 Church Ave Brooklyn NY 11236",
    "addr:housenumber":"6001",
    "addr:postcode":"11236",
    "addr:street":"Church Ave",
    "iso:country":"US",
    "sg:address":"6001 Church Ave",
    "sg:city":"Brooklyn",
    "sg:classifiers":[
        {
            "category":"Wholesale",
            "subcategory":"Petroleum",
            "type":"Manufacturing & Wholesale Goods"
        }
    ],
    "sg:phone":"+1 718 342 8602",
    "sg:postcode":"11236",
    "sg:province":"NY",
    "sg:tags":[
        "bulk",
        "station"
    ],
    "wof:name":"ASEF Petroleum Corp",
    "wof:placetype":"venue"
},
  "geometry": {"coordinates":[-73.919962,40.652789],"type":"Point"}
}