{
  "type": "Feature",
  "properties": {
    "iso:country":"US",
    "sg:address":"14 Sandra St",
    "sg:city":"Ellenville",
    "sg:classifiers":[
        {
            "category":"Shopping",
            "subcategory":"Pharmacy",
            "type":"Retail Goods"
        }
    ],
    "sg:phone":"+1   ",
    "sg:postcode":"12428",
    "sg:province":"NY",
    "sg:tags":[
        "drug",
        "store"
    ],
    "wof:name":"J C D Pharmacy Inc",
    "wof:placetype":"venue"
},
  "geometry": {"coordinates":[-74.396688,41.709453],"type":"Point"}
}