{
  "type": "Feature",
  "properties": {
    "iso:country":"US",
    "sg:address":"75 US Hwy 20",
    "sg:city":"Seneca Falls",
    "sg:classifiers":[
        {
            "category":"Retail",
            "subcategory":"Auto Repair",
            "type":"Services"
        }
    ],
    "sg:phone":"+1 315 568 1748",
    "sg:postcode":"13148",
    "sg:province":"NY",
    "sg:tags":[
        "repairing",
        "automobile"
    ],
    "wof:name":"Adams Auto",
    "wof:placetype":"venue"
},
  "geometry": {"coordinates":[-76.79346099999999,42.916341],"type":"Point"}
}