{
  "type": "Feature",
  "properties": {
    "addr:full":"19 Pond Park Rd Great Neck NY 11023",
    "addr:housenumber":"19",
    "addr:postcode":"11023",
    "addr:street":"Pond Park Rd",
    "iso:country":"US",
    "sg:address":"19 Pond Park Rd",
    "sg:city":"Great Neck",
    "sg:classifiers":[
        {
            "category":"Insurance",
            "subcategory":"Insurance Agent",
            "type":"Services"
        }
    ],
    "sg:phone":"+1 516 829 1177",
    "sg:postcode":"11023",
    "sg:province":"NY",
    "sg:tags":[
        "adjuster"
    ],
    "wof:name":"Advanced Public Adjusters Inc",
    "wof:placetype":"venue"
},
  "geometry": {"coordinates":[-73.74534,40.789274],"type":"Point"}
}