{
  "type": "Feature",
  "properties": {
    "addr:full":"1046 Esther St Franklin Square NY 11010",
    "addr:housenumber":"1046",
    "addr:postcode":"11010",
    "addr:street":"Esther St",
    "iso:country":"US",
    "sg:address":"1046 Esther St",
    "sg:city":"Franklin Square",
    "sg:classifiers":[
        {
            "category":"Health Services",
            "subcategory":"Doctor",
            "type":"Services"
        }
    ],
    "sg:phone":"+1 516 775 9292",
    "sg:postcode":"11010",
    "sg:province":"NY",
    "sg:tags":[
        "medicine",
        "internal"
    ],
    "wof:name":"Patelli Annamaria MD",
    "wof:placetype":"venue"
},
  "geometry": {"coordinates":[-73.679001,40.7029],"type":"Point"}
}