{
  "type": "Feature",
  "properties": {
    "addr:full":"4 Windsor Ter White Plains NY 10601",
    "addr:housenumber":"4",
    "addr:postcode":"10601",
    "addr:street":"Windsor Ter",
    "iso:country":"US",
    "sg:address":"4 Windsor Ter",
    "sg:city":"White Plains",
    "sg:classifiers":[
        {
            "category":"Real Estate",
            "subcategory":"Architect",
            "type":"Services"
        }
    ],
    "sg:phone":"+1 914 946 3477",
    "sg:postcode":"10601",
    "sg:province":"NY",
    "wof:name":"Oag Design Svc",
    "wof:placetype":"venue"
},
  "geometry": {"coordinates":[-73.760683,41.034695],"type":"Point"}
}