{
  "type": "Feature",
  "properties": {
    "iso:country":"US",
    "sg:address":"1653 State St",
    "sg:city":"Watertown",
    "sg:classifiers":[
        {
            "category":"Retail",
            "subcategory":"Auto Repair",
            "type":"Services"
        }
    ],
    "sg:phone":"+1 315 782 2231",
    "sg:postcode":"13601",
    "sg:province":"NY",
    "sg:tags":[
        "repairing",
        "automotive",
        "provides",
        "automobile"
    ],
    "wof:name":"Monro Muffler Brake & Svc",
    "wof:placetype":"venue"
},
  "geometry": {"coordinates":[-75.882542,43.967628],"type":"Point"}
}