{
  "type": "Feature",
  "properties": {
    "iso:country":"US",
    "sg:address":"334 Cedar St",
    "sg:city":"Hempstead",
    "sg:classifiers":[
        {
            "category":"Building & Trades",
            "subcategory":"Construction",
            "type":"Services"
        }
    ],
    "sg:phone":"+1 516 489 7162",
    "sg:postcode":"11550",
    "sg:province":"NY",
    "sg:tags":[
        "work",
        "carpentry"
    ],
    "wof:name":"Tom Mac Construction Inc",
    "wof:placetype":"venue"
},
  "geometry": {"coordinates":[-73.626767,40.681973],"type":"Point"}
}