{
  "type": "Feature",
  "properties": {
    "addr:full":"445 Park Avenue Koi Invest smba New York NY NY 10022",
    "addr:housenumber":"445",
    "addr:postcode":"10022",
    "addr:street":"Park Avenue",
    "iso:country":"US",
    "sg:address":"445 Park Avenue Koi Invest smba",
    "sg:city":"New York",
    "sg:classifiers":[
        {
            "category":"Professional",
            "subcategory":"Computer Services",
            "type":"Services"
        }
    ],
    "sg:phone":"+1 866 569 5010",
    "sg:postcode":"NY 10022",
    "sg:province":"NY",
    "sg:tags":[
        "green-card",
        "us-green-card",
        "visa",
        "work-permit"
    ],
    "sg:website":"http://www.usgreencardoffice.com",
    "wof:name":"US Green Card Office",
    "wof:placetype":"venue"
},
  "geometry": {"coordinates":[-73.970809,40.761349],"type":"Point"}
}