{
  "type": "Feature",
  "properties": {
    "iso:country":"US",
    "sg:address":"116 N Main St",
    "sg:city":"Brockport",
    "sg:classifiers":[
        {
            "category":"Professional",
            "subcategory":"Lawyer & Legal Services",
            "type":"Services"
        }
    ],
    "sg:phone":"+1 585 637 3148",
    "sg:postcode":"14420",
    "sg:province":"NY",
    "sg:tags":[
        "attorney"
    ],
    "wof:name":"Kenneth W Nelson",
    "wof:placetype":"venue"
},
  "geometry": {"coordinates":[-77.937258,43.219094],"type":"Point"}
}