{
  "type": "Feature",
  "properties": {
    "addr:full":"79 Maple Ave Catskill NY 12414",
    "addr:housenumber":"79",
    "addr:postcode":"12414",
    "addr:street":"Maple Ave",
    "iso:country":"US",
    "sg:address":"79 Maple Ave",
    "sg:city":"Catskill",
    "sg:classifiers":[
        {
            "category":"Retail",
            "subcategory":"Auto Rental",
            "type":"Services"
        }
    ],
    "sg:phone":"+1 518 945 2186",
    "sg:postcode":"12414",
    "sg:province":"NY",
    "sg:tags":[
        "renting",
        "truck",
        "leasing"
    ],
    "wof:name":"U-Haul Co",
    "wof:placetype":"venue"
},
  "geometry": {"coordinates":[-73.876183,42.216468],"type":"Point"}
}