{
  "type": "Feature",
  "properties": {
    "addr:full":"13165 Wright Rd Red Creek NY 13143",
    "addr:housenumber":"13165",
    "addr:postcode":"13143",
    "addr:street":"Wright Rd",
    "iso:country":"US",
    "sg:address":"13165 Wright Rd",
    "sg:city":"Red Creek",
    "sg:classifiers":[
        {
            "category":"Farming",
            "subcategory":"Farm",
            "type":"Manufacturing & Wholesale Goods"
        }
    ],
    "sg:phone":"+1 315 754 6396",
    "sg:postcode":"13143",
    "sg:province":"NY",
    "sg:tags":[
        "food",
        "ornamental",
        "nursery",
        "crop",
        "covered"
    ],
    "wof:name":"Mark Fitzgerald",
    "wof:placetype":"venue"
},
  "geometry": {"coordinates":[-76.683261,43.260229],"type":"Point"}
}