{
  "type": "Feature",
  "properties": {
    "addr:full":"241 Brookview Dr Rochester NY 14617",
    "addr:housenumber":"241",
    "addr:postcode":"14617",
    "addr:street":"Brookview Dr",
    "iso:country":"US",
    "sg:address":"241 Brookview Dr",
    "sg:city":"Rochester",
    "sg:classifiers":[
        {
            "category":"Wholesale",
            "subcategory":"Metals & Minerals",
            "type":"Manufacturing & Wholesale Goods"
        }
    ],
    "sg:phone":"+1 585 266 3946",
    "sg:postcode":"14617",
    "sg:province":"NY",
    "sg:tags":[
        "center"
    ],
    "wof:name":"Coast Sales",
    "wof:placetype":"venue"
},
  "geometry": {"coordinates":[-77.593645,43.205248],"type":"Point"}
}