{
  "type": "Feature",
  "properties": {
    "addr:full":"1445 Jefferson Rd Rochester NY 14623",
    "addr:housenumber":"1445",
    "addr:postcode":"14623",
    "addr:street":"Jefferson Rd",
    "iso:country":"US",
    "sg:address":"1445 Jefferson Rd",
    "sg:city":"Rochester",
    "sg:classifiers":[
        {
            "category":"Professional",
            "subcategory":"Printing & Photocopies",
            "type":"Services"
        }
    ],
    "sg:phone":"+1 585 256 1690",
    "sg:postcode":"14623",
    "sg:province":"NY",
    "sg:tags":[
        "duplicating",
        "copying"
    ],
    "sg:website":"www.advancedquickprinting.com",
    "wof:name":"Advanced Quickprinting Inc",
    "wof:placetype":"venue"
},
  "geometry": {"coordinates":[-77.590836,43.08695],"type":"Point"}
}