{
  "type": "Feature",
  "properties": {
    "iso:country":"US",
    "sg:address":"7 Pleasant Ave",
    "sg:city":"Middletown",
    "sg:classifiers":[
        {
            "category":"Building & Trades",
            "subcategory":"Construction",
            "type":"Services"
        }
    ],
    "sg:phone":"+1 845 342 6680",
    "sg:postcode":"10940",
    "sg:province":"NY",
    "sg:tags":[
        "designer",
        "dealer",
        "pool",
        "swimming"
    ],
    "wof:name":"Pool-It",
    "wof:placetype":"venue"
},
  "geometry": {"coordinates":[-74.412628,41.473308],"type":"Point"}
}