{
  "type": "Feature",
  "properties": {
    "addr:full":"12360 83rd Ave Ste 1T Kew Gardens NY 11415",
    "addr:housenumber":"12360",
    "addr:postcode":"11415",
    "addr:street":"83Rd Ave Ste 1T",
    "iso:country":"US",
    "sg:address":"12360 83rd Ave Ste 1T",
    "sg:city":"Kew Gardens",
    "sg:classifiers":[
        {
            "category":"Professional",
            "subcategory":"Lawyer & Legal Services",
            "type":"Services"
        }
    ],
    "sg:phone":"+1 718 261 5151",
    "sg:postcode":"11415",
    "sg:province":"NY",
    "wof:name":"Scardigno Luke Atty",
    "wof:placetype":"venue"
},
  "geometry": {"coordinates":[-73.826897,40.711399],"type":"Point"}
}