{
  "type": "Feature",
  "properties": {
    "iso:country":"US",
    "sg:address":"895 Montauk Hwy",
    "sg:city":"West Babylon",
    "sg:classifiers":[
        {
            "category":"Insurance",
            "subcategory":"Hazard Insurance",
            "type":"Services"
        }
    ],
    "sg:phone":"+1 631 587 9100",
    "sg:postcode":"11704",
    "sg:province":"NY",
    "sg:tags":[
        "life",
        "carrier"
    ],
    "wof:name":"Liberty Mutual Insurance Co",
    "wof:placetype":"venue"
},
  "geometry": {"coordinates":[-73.350133,40.684926],"type":"Point"}
}