{
  "type": "Feature",
  "properties": {
    "iso:country":"US",
    "sg:address":"852 Main St",
    "sg:city":"Dunkirk",
    "sg:classifiers":[
        {
            "category":"Manufacturing",
            "subcategory":"Glass & Minerals",
            "type":"Manufacturing & Wholesale Goods"
        }
    ],
    "sg:phone":"+1 716 366 5220",
    "sg:postcode":"14048",
    "sg:province":"NY",
    "sg:tags":[
        "ready"
    ],
    "wof:name":"Dunkirk Construction Products",
    "wof:placetype":"venue"
},
  "geometry": {"coordinates":[-79.32682800000001,42.469901],"type":"Point"}
}