{
  "type": "Feature",
  "properties": {
    "iso:country":"US",
    "sg:address":"1053 Winthrop St",
    "sg:city":"Brooklyn",
    "sg:classifiers":[
        {
            "category":"Organizations",
            "subcategory":"Religious Organization",
            "type":"Services"
        }
    ],
    "sg:phone":"+1 718 467 5735",
    "sg:postcode":"11212",
    "sg:province":"NY",
    "sg:tags":[
        "clergy"
    ],
    "wof:name":"Church Fellowship Baptist",
    "wof:placetype":"venue"
},
  "geometry": {"coordinates":[-73.925003,40.6609],"type":"Point"}
}