{
  "type": "Feature",
  "properties": {
    "iso:country":"US",
    "sg:address":"677 Ridge Rd",
    "sg:city":"Buffalo",
    "sg:classifiers":[
        {
            "category":"Restaurant",
            "type":"Food & Drink"
        }
    ],
    "sg:phone":"+1 716 827 8750",
    "sg:postcode":"14218",
    "sg:province":"NY",
    "sg:tags":[
        "pizza"
    ],
    "wof:name":"Broadway Bobby's Pizzeria",
    "wof:placetype":"venue"
},
  "geometry": {"coordinates":[-78.826599,42.825901],"type":"Point"}
}