{
  "type": "Feature",
  "properties": {
    "addr:full":"158 Summit St Brooklyn NY 11231",
    "addr:housenumber":"158",
    "addr:postcode":"11231",
    "addr:street":"Summit St",
    "iso:country":"US",
    "sg:address":"158 Summit St",
    "sg:city":"Brooklyn",
    "sg:classifiers":[
        {
            "category":"Wholesale",
            "subcategory":"Non-durable Goods",
            "type":"Manufacturing & Wholesale Goods"
        }
    ],
    "sg:phone":"+1 718 237 5772",
    "sg:postcode":"11231",
    "sg:province":"NY",
    "sg:tags":[
        "pet",
        "product"
    ],
    "wof:name":"Dogmatic Products Inc",
    "wof:placetype":"venue"
},
  "geometry": {"coordinates":[-74.001161,40.681416],"type":"Point"}
}