{
  "type": "Feature",
  "properties": {
    "iso:country":"US",
    "sg:address":"195 Lauman Ln",
    "sg:city":"Hicksville",
    "sg:classifiers":[
        {
            "category":"Building & Trades",
            "subcategory":"Construction",
            "type":"Services"
        }
    ],
    "sg:phone":"+1 516 827 5199",
    "sg:postcode":"11801",
    "sg:province":"NY",
    "sg:tags":[
        "resurfacing",
        "laying",
        "refinishing",
        "floor"
    ],
    "wof:name":"Pyramid Floors",
    "wof:placetype":"venue"
},
  "geometry": {"coordinates":[-73.49805000000001,40.743798],"type":"Point"}
}