{
  "type": "Feature",
  "properties": {
    "addr:full":"1 Flowerfield St James NY 11780",
    "addr:housenumber":"1",
    "addr:postcode":"11780",
    "addr:street":"Flowerfield St",
    "iso:country":"US",
    "sg:address":"1 Flowerfield",
    "sg:city":"St James",
    "sg:classifiers":[
        {
            "category":"Wholesale",
            "subcategory":"Hardware",
            "type":"Manufacturing & Wholesale Goods"
        }
    ],
    "sg:phone":"+1 631 862 2233",
    "sg:postcode":"11780",
    "sg:province":"NY",
    "sg:tags":[
        "screw"
    ],
    "wof:name":"Prime Fasteners Corp",
    "wof:placetype":"venue"
},
  "geometry": {"coordinates":[-73.14377899999999,40.896704],"type":"Point"}
}