{
  "type": "Feature",
  "properties": {
    "iso:country":"US",
    "sg:address":"20 Michael Dr",
    "sg:city":"Old Bethpage",
    "sg:classifiers":[
        {
            "category":"Wholesale",
            "subcategory":"Machinery & Supplies",
            "type":"Manufacturing & Wholesale Goods"
        }
    ],
    "sg:phone":"+1 516 752 8970",
    "sg:postcode":"11804",
    "sg:province":"NY",
    "sg:tags":[
        "tool"
    ],
    "wof:name":"Cooper Power Tools",
    "wof:placetype":"venue"
},
  "geometry": {"coordinates":[-73.46117599999999,40.769448],"type":"Point"}
}