{
  "type": "Feature",
  "properties": {
    "iso:country":"US",
    "sg:address":"284 Waverly Ave",
    "sg:city":"Medford",
    "sg:classifiers":[
        {
            "category":"Real Estate",
            "subcategory":"Developer",
            "type":"Services"
        }
    ],
    "sg:phone":"+1 631 289 6700",
    "sg:postcode":"11763",
    "sg:province":"NY",
    "wof:name":"Jd Site Development",
    "wof:placetype":"venue"
},
  "geometry": {"coordinates":[-72.999313,40.822842],"type":"Point"}
}