{
  "type": "Feature",
  "properties": {
    "addr:full":"18 S Village Ave Rockville Centre NY 11570",
    "addr:housenumber":"18",
    "addr:postcode":"11570",
    "addr:street":"S Village Ave",
    "iso:country":"US",
    "sg:address":"18 S Village Ave",
    "sg:city":"Rockville Centre",
    "sg:classifiers":[
        {
            "category":"Restaurant",
            "type":"Food & Drink"
        }
    ],
    "sg:phone":"+1 516 766 3355",
    "sg:postcode":"11570",
    "sg:province":"NY",
    "wof:name":"Tung's Garden",
    "wof:placetype":"venue"
},
  "geometry": {"coordinates":[-73.64859800000001,40.655499],"type":"Point"}
}