{
  "type": "Feature",
  "properties": {
    "addr:full":"915 E 7th St Brooklyn NY 11230",
    "addr:housenumber":"915",
    "addr:postcode":"11230",
    "addr:street":"E 7Th St",
    "iso:country":"US",
    "sg:address":"915 E 7th St",
    "sg:city":"Brooklyn",
    "sg:classifiers":[
        {
            "category":"Shopping",
            "subcategory":"Jewelry",
            "type":"Retail Goods"
        }
    ],
    "sg:phone":"+1   ",
    "sg:postcode":"11230",
    "sg:province":"NY",
    "wof:name":"American Quality Jewelry Corp",
    "wof:placetype":"venue"
},
  "geometry": {"coordinates":[-73.969819,40.628611],"type":"Point"}
}