{
  "type": "Feature",
  "properties": {
    "iso:country":"US",
    "sg:address":"48 Broad St",
    "sg:city":"Amsterdam",
    "sg:classifiers":[
        {
            "category":"Wholesale",
            "subcategory":"Machinery & Supplies",
            "type":"Manufacturing & Wholesale Goods"
        }
    ],
    "sg:phone":"+1 518 842 0396",
    "sg:postcode":"12010",
    "sg:province":"NY",
    "sg:tags":[
        "contractor"
    ],
    "wof:name":"Carfel Supplies Inc",
    "wof:placetype":"venue"
},
  "geometry": {"coordinates":[-74.20083200000001,42.934597],"type":"Point"}
}