{
  "type": "Feature",
  "properties": {
    "addr:full":"44 Eagle St Brooklyn NY 11222",
    "addr:housenumber":"44",
    "addr:postcode":"11222",
    "addr:street":"Eagle St",
    "iso:country":"US",
    "sg:address":"44 Eagle St",
    "sg:city":"Brooklyn",
    "sg:classifiers":[
        {
            "category":"Food & Beverages",
            "subcategory":"Groceries & Convenience Stores",
            "type":"Retail Goods"
        }
    ],
    "sg:postcode":"11222",
    "sg:province":"NY",
    "sg:tags":[
        "do-it-yourself"
    ],
    "sg:website":"rooftopfarms.org/",
    "wof:name":"Eagle Street Rooftop Farm",
    "wof:placetype":"venue"
},
  "geometry": {"coordinates":[-73.959565,40.734719],"type":"Point"}
}