{
  "type": "Feature",
  "properties": {
    "iso:country":"US",
    "sg:address":"1 Wilson St",
    "sg:city":"Greenwich",
    "sg:classifiers":[
        {
            "category":"Building & Trades",
            "subcategory":"Construction",
            "type":"Services"
        }
    ],
    "sg:phone":"+1 518 505 2244",
    "sg:postcode":"12834",
    "sg:province":"NY",
    "sg:tags":[
        "downspouts",
        "gutter",
        "contractor"
    ],
    "wof:name":"Capital Dist Seamless Gutter",
    "wof:placetype":"venue"
},
  "geometry": {"coordinates":[-73.50863,43.095475],"type":"Point"}
}