{
  "type": "Feature",
  "properties": {
    "addr:full":"766 9th Ave New York NY 10019",
    "addr:housenumber":"766",
    "addr:postcode":"10019",
    "addr:street":"9Th Ave",
    "iso:country":"US",
    "sg:address":"766 9th Ave",
    "sg:city":"New York",
    "sg:classifiers":[
        {
            "category":"Fast Food",
            "type":"Food & Drink"
        }
    ],
    "sg:phone":"+1 212 307 7934",
    "sg:postcode":"10019",
    "sg:province":"NY",
    "sg:tags":[
        "burger"
    ],
    "sg:website":"www.islandburgersny.com",
    "wof:name":"Island Burgers & Shakes",
    "wof:placetype":"venue"
},
  "geometry": {"coordinates":[-73.98800799999999,40.764249],"type":"Point"}
}