{
  "type": "Feature",
  "properties": {
    "iso:country":"US",
    "sg:address":"8301 Shore Road",
    "sg:city":"Brooklyn",
    "sg:classifiers":[
        {
            "category":"Education",
            "subcategory":"School",
            "type":"Public Place"
        }
    ],
    "sg:phone":"+1 718 748 1537",
    "sg:postcode":"11209",
    "sg:province":"NY",
    "sg:tags":[
        "high",
        "middle",
        "elementary"
    ],
    "wof:name":"New York City Community School District 20 Region 7",
    "wof:placetype":"venue"
},
  "geometry": {"coordinates":[-74.039852,40.627883],"type":"Point"}
}