{
  "type": "Feature",
  "properties": {
    "addr:full":"76 Webster St North Tonawanda NY 14120",
    "addr:housenumber":"76",
    "addr:postcode":"14120",
    "addr:street":"Webster St",
    "iso:country":"US",
    "sg:address":"76 Webster St",
    "sg:city":"North Tonawanda",
    "sg:classifiers":[
        {
            "category":"Personal",
            "subcategory":"Beauty Salon",
            "type":"Services"
        }
    ],
    "sg:phone":"+1 716 694 9315",
    "sg:postcode":"14120",
    "sg:province":"NY",
    "wof:name":"Creative Hair Design",
    "wof:placetype":"venue"
},
  "geometry": {"coordinates":[-78.877458,43.02362],"type":"Point"}
}