{
  "type": "Feature",
  "properties": {
    "addr:full":"100 Merrick Rd Ste 106E Rockville Centre NY 11570",
    "addr:housenumber":"100",
    "addr:postcode":"11570",
    "addr:street":"Merrick Rd Ste 106E",
    "iso:country":"US",
    "sg:address":"100 Merrick Rd Ste 106E",
    "sg:city":"Rockville Centre",
    "sg:classifiers":[
        {
            "category":"Health Services",
            "subcategory":"Doctor",
            "type":"Services"
        }
    ],
    "sg:phone":"+1 516 766 5558",
    "sg:postcode":"11570",
    "sg:province":"NY",
    "sg:tags":[
        "surgeon",
        "oral"
    ],
    "wof:name":"Andrew Rutman, DDS",
    "wof:placetype":"venue"
},
  "geometry": {"coordinates":[-73.65045000000001,40.656252],"type":"Point"}
}