{
  "type": "Feature",
  "properties": {
    "iso:country":"US",
    "sg:address":"6929 Williams Rd",
    "sg:city":"Niagara Falls",
    "sg:classifiers":[
        {
            "category":"Retail",
            "subcategory":"Portrait Studio",
            "type":"Services"
        }
    ],
    "sg:phone":"+1 716 298 3282",
    "sg:postcode":"14304",
    "sg:province":"NY",
    "sg:tags":[
        "photo"
    ],
    "wof:name":"Sears Portrait Studio N25",
    "wof:placetype":"venue"
},
  "geometry": {"coordinates":[-78.940699,43.088004],"type":"Point"}
}