{
  "type": "Feature",
  "properties": {
    "addr:full":"1401 Church St Bohemia NY 11716",
    "addr:housenumber":"1401",
    "addr:postcode":"11716",
    "addr:street":"Church St",
    "iso:country":"US",
    "sg:address":"1401 Church St",
    "sg:city":"Bohemia",
    "sg:classifiers":[
        {
            "category":"Building & Trades",
            "subcategory":"Electrical",
            "type":"Services"
        }
    ],
    "sg:phone":"+1 631 567 8502",
    "sg:postcode":"11716",
    "sg:province":"NY",
    "sg:tags":[
        "electrical",
        "contractor"
    ],
    "wof:name":"Delcon Systems Inc",
    "wof:placetype":"venue"
},
  "geometry": {"coordinates":[-73.08544500000001,40.770505],"type":"Point"}
}