{
  "type": "Feature",
  "properties": {
    "iso:country":"US",
    "sg:address":"145 Lincoln Ave",
    "sg:city":"Staten Island",
    "sg:classifiers":[
        {
            "category":"Professional",
            "subcategory":"Lawyer & Legal Services",
            "type":"Services"
        }
    ],
    "sg:phone":"+1 718 668 2615",
    "sg:postcode":"10306",
    "sg:province":"NY",
    "sg:tags":[
        "attorney"
    ],
    "wof:name":"Barbara A Sauter & Assoc",
    "wof:placetype":"venue"
},
  "geometry": {"coordinates":[-74.107752,40.57908],"type":"Point"}
}