{
  "type": "Feature",
  "properties": {
    "addr:full":"185 Wadsworth Ave New York NY 10033",
    "addr:housenumber":"185",
    "addr:postcode":"10033",
    "addr:street":"Wadsworth Ave",
    "iso:country":"US",
    "sg:address":"185 Wadsworth Ave",
    "sg:city":"New York",
    "sg:classifiers":[
        {
            "category":"Education",
            "subcategory":"School",
            "type":"Public Place"
        }
    ],
    "sg:phone":"+1 646 435 0833",
    "sg:postcode":"10033",
    "sg:province":"NY",
    "wof:name":"Alianza Dominicana",
    "wof:placetype":"venue"
},
  "geometry": {"coordinates":[-73.93427699999999,40.850481],"type":"Point"}
}