{
  "type": "Feature",
  "properties": {
    "addr:full":"301 N Washington St Herkimer NY 13350",
    "addr:housenumber":"301",
    "addr:postcode":"13350",
    "addr:street":"N Washington St",
    "iso:country":"US",
    "sg:address":"301 N Washington St",
    "sg:city":"Herkimer",
    "sg:classifiers":[
        {
            "category":"Health Services",
            "subcategory":"Health Practitioner",
            "type":"Services"
        }
    ],
    "sg:phone":"+1 315 867 1176",
    "sg:postcode":"13350",
    "sg:province":"NY",
    "sg:tags":[
        "home",
        "heal",
        "executive"
    ],
    "wof:name":"Herkimer Pub Hlth Nursing Srvc",
    "wof:placetype":"venue"
},
  "geometry": {"coordinates":[-74.98804699999999,43.029818],"type":"Point"}
}