{
  "type": "Feature",
  "properties": {
    "addr:full":"2 Wicker St Ticonderoga NY 12883",
    "addr:housenumber":"2",
    "addr:postcode":"12883",
    "addr:street":"Wicker St",
    "iso:country":"US",
    "sg:address":"2 Wicker St",
    "sg:city":"Ticonderoga",
    "sg:classifiers":[
        {
            "category":"Health Services",
            "subcategory":"Doctor",
            "type":"Services"
        }
    ],
    "sg:phone":"+1 518 585 2831",
    "sg:postcode":"12883",
    "sg:province":"NY",
    "sg:tags":[
        "medical"
    ],
    "wof:name":"Douglas Kirkpatrick",
    "wof:placetype":"venue"
},
  "geometry": {"coordinates":[-73.43723799999999,43.852565],"type":"Point"}
}