{
  "type": "Feature",
  "properties": {
    "addr:full":"201 W 107th St New York NY 10025",
    "addr:housenumber":"201",
    "addr:postcode":"10025",
    "addr:street":"W 107Th St",
    "iso:country":"US",
    "sg:address":"201 W 107th St",
    "sg:city":"New York",
    "sg:classifiers":[
        {
            "category":"Health Services",
            "subcategory":"Health Practitioner",
            "type":"Services"
        }
    ],
    "sg:phone":"+1 212 678 0124",
    "sg:postcode":"10025",
    "sg:province":"NY",
    "sg:tags":[
        "speech",
        "therapy",
        "bilingual"
    ],
    "wof:name":"Bilingual Assoc Inc",
    "wof:placetype":"venue"
},
  "geometry": {"coordinates":[-73.967789,40.8022],"type":"Point"}
}