{
  "type": "Feature",
  "properties": {
    "addr:full":"728 E 136th St Bronx NY 10454",
    "addr:housenumber":"728",
    "addr:postcode":"10454",
    "addr:street":"E 136Th St",
    "iso:country":"US",
    "sg:address":"728 E 136th St",
    "sg:city":"Bronx",
    "sg:classifiers":[
        {
            "category":"Manufacturing",
            "subcategory":"Apparel",
            "type":"Manufacturing & Wholesale Goods"
        }
    ],
    "sg:phone":"+1   ",
    "sg:postcode":"10454",
    "sg:province":"NY",
    "sg:tags":[
        "bridal",
        "evening",
        "slip",
        "mfg"
    ],
    "wof:name":"Sidney A Bush Co",
    "wof:placetype":"venue"
},
  "geometry": {"coordinates":[-73.912702,40.803079],"type":"Point"}
}