{
  "type": "Feature",
  "properties": {
    "addr:full":"11 Rugby Rd Merrick NY 11566",
    "addr:housenumber":"11",
    "addr:postcode":"11566",
    "addr:street":"Rugby Rd",
    "iso:country":"US",
    "sg:address":"11 Rugby Rd",
    "sg:city":"Merrick",
    "sg:classifiers":[
        {
            "category":"Home & Garden",
            "subcategory":"Building Materials",
            "type":"Retail Goods"
        }
    ],
    "sg:phone":"+1 516 868 1250",
    "sg:postcode":"11566",
    "sg:province":"NY",
    "sg:tags":[
        "door"
    ],
    "wof:name":"Affordable Garage Doors",
    "wof:placetype":"venue"
},
  "geometry": {"coordinates":[-73.563619,40.656033],"type":"Point"}
}