{
  "type": "Feature",
  "properties": {
    "iso:country":"US",
    "sg:address":"101 Craig Cir",
    "sg:city":"Syracuse",
    "sg:classifiers":[
        {
            "category":"Real Estate",
            "subcategory":"Real Estate Operator",
            "type":"Services"
        }
    ],
    "sg:phone":"+1 315 345 6624",
    "sg:postcode":"13214",
    "sg:province":"NY",
    "sg:tags":[
        "apartment"
    ],
    "wof:name":"Hugh Lowery",
    "wof:placetype":"venue"
},
  "geometry": {"coordinates":[-76.054237,43.047611],"type":"Point"}
}