{
  "type": "Feature",
  "properties": {
    "iso:country":"US",
    "sg:address":"684 W Falls Rd",
    "sg:city":"West Falls",
    "sg:classifiers":[
        {
            "category":"Farming",
            "subcategory":"Farm & Veterinary Services",
            "type":"Manufacturing & Wholesale Goods"
        }
    ],
    "sg:phone":"+1 716 655 4353",
    "sg:postcode":"14170",
    "sg:province":"NY",
    "sg:tags":[
        "management"
    ],
    "wof:name":"Deibel Corp",
    "wof:placetype":"venue"
},
  "geometry": {"coordinates":[-78.68013999999999,42.703284],"type":"Point"}
}