{
  "type": "Feature",
  "properties": {
    "addr:full":"103 W 90 St New York NY 10024",
    "addr:housenumber":"103",
    "addr:postcode":"10024",
    "addr:street":"W 90 St",
    "iso:country":"US",
    "sg:address":"103 W 90 St",
    "sg:city":"New York",
    "sg:classifiers":[
        {
            "category":"Banks & Credit Unions",
            "subcategory":"Financial Services",
            "type":"Services"
        }
    ],
    "sg:phone":"+1 212 724 9689",
    "sg:postcode":"10024",
    "sg:province":"NY",
    "sg:tags":[
        "management",
        "open",
        "investment"
    ],
    "wof:name":"Rainmaker Entertainment",
    "wof:placetype":"venue"
},
  "geometry": {"coordinates":[-73.97184799999999,40.789769],"type":"Point"}
}