{
  "type": "Feature",
  "properties": {
    "iso:country":"US",
    "sg:address":"3290 Edgemere Dr",
    "sg:city":"Rochester",
    "sg:classifiers":[
        {
            "category":"Shopping",
            "subcategory":"Bicycles & Sporting Goods",
            "type":"Retail Goods"
        }
    ],
    "sg:phone":"+1 585 720 6107",
    "sg:postcode":"14612",
    "sg:province":"NY",
    "sg:tags":[
        "equipment",
        "golf",
        "supply"
    ],
    "wof:name":"Golfman",
    "wof:placetype":"venue"
},
  "geometry": {"coordinates":[-77.698756,43.30641],"type":"Point"}
}