{
  "type": "Feature",
  "properties": {
    "addr:full":"156 W 166th St Bronx NY 10452",
    "addr:housenumber":"156",
    "addr:postcode":"10452",
    "addr:street":"W 166Th St",
    "iso:country":"US",
    "sg:address":"156 W 166th St",
    "sg:city":"Bronx",
    "sg:classifiers":[
        {
            "category":"Parking",
            "type":"Transportation"
        }
    ],
    "sg:phone":"+1 718 293 4103",
    "sg:postcode":"10452",
    "sg:province":"NY",
    "sg:tags":[
        "garage"
    ],
    "wof:name":"Ogden Parking Inc",
    "wof:placetype":"venue"
},
  "geometry": {"coordinates":[-73.928298,40.835643],"type":"Point"}
}