{
  "type": "Feature",
  "properties": {
    "addr:full":"3921 Greenpoint Avenue Sunnyside NY 11104",
    "addr:housenumber":"3921",
    "addr:postcode":"11104",
    "addr:street":"Greenpoint Avenue",
    "iso:country":"US",
    "sg:address":"3921 Greenpoint Avenue",
    "sg:city":"Sunnyside",
    "sg:classifiers":[
        {
            "category":"Restaurant",
            "type":"Food & Drink"
        }
    ],
    "sg:phone":"+1 718 784 9398",
    "sg:postcode":"11104",
    "sg:province":"NY",
    "wof:name":"New Chinatown",
    "wof:placetype":"venue"
},
  "geometry": {"coordinates":[-73.92632399999999,40.739118],"type":"Point"}
}