{
  "type": "Feature",
  "properties": {
    "addr:full":"58 E Merrick Rd Valley Stream NY 11580",
    "addr:housenumber":"58",
    "addr:postcode":"11580",
    "addr:street":"E Merrick Rd",
    "iso:country":"US",
    "sg:address":"58 E Merrick Rd",
    "sg:city":"Valley Stream",
    "sg:classifiers":[
        {
            "category":"Cinema",
            "subcategory":"Movie Rental",
            "type":"Entertainment"
        }
    ],
    "sg:phone":"+1 516 872 4553",
    "sg:postcode":"11580",
    "sg:province":"NY",
    "sg:tags":[
        "video",
        "game",
        "disc",
        "leasing",
        "tape"
    ],
    "sg:website":"www.blockbuster.com",
    "wof:name":"Blockbuster Video",
    "wof:placetype":"venue"
},
  "geometry": {"coordinates":[-73.696198,40.664101],"type":"Point"}
}