{
  "type": "Feature",
  "properties": {
    "addr:full":"167 Madison Avenue New York NY 10016",
    "addr:housenumber":"167",
    "addr:postcode":"10016",
    "addr:street":"Madison Avenue",
    "iso:country":"US",
    "sg:address":"167 Madison Avenue",
    "sg:city":"New York",
    "sg:classifiers":[
        {
            "category":"Building & Trades",
            "subcategory":"Construction",
            "type":"Services"
        }
    ],
    "sg:phone":"+1 212 213 1191",
    "sg:postcode":"10016",
    "sg:province":"NY",
    "sg:tags":[
        "contractor"
    ],
    "wof:name":"L Lyons Enterprises",
    "wof:placetype":"venue"
},
  "geometry": {"coordinates":[-73.98331899999999,40.74717],"type":"Point"}
}