{
  "type": "Feature",
  "properties": {
    "iso:country":"US",
    "sg:address":"1118 Union Ave",
    "sg:city":"Newburgh",
    "sg:classifiers":[
        {
            "category":"Restaurant",
            "type":"Food & Drink"
        }
    ],
    "sg:phone":"+1 845 566 3650",
    "sg:postcode":"12550",
    "sg:province":"NY",
    "sg:website":"www.tacobell.com",
    "wof:name":"Taco Bell",
    "wof:placetype":"venue"
},
  "geometry": {"coordinates":[-74.0299,41.5131],"type":"Point"}
}