{
  "type": "Feature",
  "properties": {
    "iso:country":"US",
    "sg:address":"541 N Highland Ave",
    "sg:city":"Nyack",
    "sg:classifiers":[
        {
            "category":"Organizations",
            "subcategory":"Membership Organization",
            "type":"Services"
        }
    ],
    "sg:phone":"+1 845 348 9880",
    "sg:postcode":"10960",
    "sg:province":"NY",
    "sg:tags":[
        "luggage-wholesale",
        "manufacturer"
    ],
    "sg:website":"http://www.caseconcepts.com",
    "wof:name":"Case Concepts International",
    "wof:placetype":"venue"
},
  "geometry": {"coordinates":[-73.92700499999999,41.113075],"type":"Point"}
}