{
  "type": "Feature",
  "properties": {
    "addr:full":"555 Central Ave Lancaster NY 14086",
    "addr:housenumber":"555",
    "addr:postcode":"14086",
    "addr:street":"Central Ave",
    "iso:country":"US",
    "sg:address":"555 Central Ave",
    "sg:city":"Lancaster",
    "sg:classifiers":[
        {
            "category":"Organizations",
            "subcategory":"Religious Organization",
            "type":"Services"
        }
    ],
    "sg:phone":"+1   ",
    "sg:postcode":"14086",
    "sg:province":"NY",
    "wof:name":"First Bible Baptist Church",
    "wof:placetype":"venue"
},
  "geometry": {"coordinates":[-78.67329100000001,42.928611],"type":"Point"}
}