{
  "type": "Feature",
  "properties": {
    "addr:full":"317 Madison Ave Rm 1511 New York NY 10017",
    "addr:housenumber":"317;1511",
    "addr:postcode":"10017",
    "addr:street":"Madison Ave Rm",
    "iso:country":"US",
    "sg:address":"317 Madison Ave Rm 1511",
    "sg:city":"New York",
    "sg:classifiers":[
        {
            "category":"Professional",
            "subcategory":"Lawyer & Legal Services",
            "type":"Services"
        }
    ],
    "sg:phone":"+1 212 867 0100",
    "sg:postcode":"10017",
    "sg:province":"NY",
    "wof:name":"McGarry & Simon",
    "wof:placetype":"venue"
},
  "geometry": {"coordinates":[-73.93122700000001,40.815544],"type":"Point"}
}