{
  "type": "Feature",
  "properties": {
    "iso:country":"US",
    "sg:address":"425 Park Ave",
    "sg:city":"New York",
    "sg:classifiers":[
        {
            "category":"Education",
            "subcategory":"Library",
            "type":"Public Place"
        }
    ],
    "sg:phone":"+1 212 559 2503",
    "sg:postcode":"10022",
    "sg:province":"NY",
    "sg:tags":[
        "law"
    ],
    "wof:name":"Citibank",
    "wof:placetype":"venue"
},
  "geometry": {"coordinates":[-73.97126299999999,40.760745],"type":"Point"}
}