{
  "type": "Feature",
  "properties": {
    "iso:country":"US",
    "sg:address":"41 Evelyn Dr",
    "sg:city":"Commack",
    "sg:classifiers":[
        {
            "category":"Professional",
            "type":"Services"
        }
    ],
    "sg:phone":"+1   ",
    "sg:postcode":"11725",
    "sg:province":"NY",
    "wof:name":"Manikas Inc",
    "wof:placetype":"venue"
},
  "geometry": {"coordinates":[-73.306887,40.835886],"type":"Point"}
}