{
  "type": "Feature",
  "properties": {
    "iso:country":"US",
    "sg:address":"10663 S Roberts Rd",
    "sg:city":"Fredonia",
    "sg:classifiers":[
        {
            "category":"Shopping",
            "subcategory":"Used Merchandise",
            "type":"Retail Goods"
        }
    ],
    "sg:phone":"+1   ",
    "sg:postcode":"14063",
    "sg:province":"NY",
    "wof:name":"Justa Barn",
    "wof:placetype":"venue"
},
  "geometry": {"coordinates":[-79.290103,42.461965],"type":"Point"}
}