{
  "type": "Feature",
  "properties": {
    "addr:full":"70 Tenafly Dr New Hyde Park NY 11040",
    "addr:housenumber":"70",
    "addr:postcode":"11040",
    "addr:street":"Tenafly Dr New",
    "iso:country":"US",
    "sg:address":"70 Tenafly Dr",
    "sg:city":"New Hyde Park",
    "sg:classifiers":[
        {
            "category":"Retail",
            "subcategory":"Laundry & Dry Cleaning",
            "type":"Services"
        }
    ],
    "sg:phone":"+1   ",
    "sg:postcode":"11040",
    "sg:province":"NY",
    "sg:tags":[
        "drycleaning",
        "plant"
    ],
    "wof:name":"Lanryl Cleaners Inc",
    "wof:placetype":"venue"
},
  "geometry": {"coordinates":[-73.66466699999999,40.750893],"type":"Point"}
}