{
  "type": "Feature",
  "properties": {
    "addr:full":"275 Hillside Ave Williston Park NY 11596",
    "addr:housenumber":"275",
    "addr:postcode":"11596",
    "addr:street":"Hillside Ave",
    "iso:country":"US",
    "sg:address":"275 Hillside Ave",
    "sg:city":"Williston Park",
    "sg:classifiers":[
        {
            "category":"Building & Trades",
            "subcategory":"Electrical",
            "type":"Services"
        }
    ],
    "sg:phone":"+1 516 248 6085",
    "sg:postcode":"11596",
    "sg:province":"NY",
    "sg:tags":[
        "general",
        "contractor"
    ],
    "wof:name":"Bid Industries",
    "wof:placetype":"venue"
},
  "geometry": {"coordinates":[-73.650301,40.754667],"type":"Point"}
}