{
  "type": "Feature",
  "properties": {
    "addr:full":"239 Nassau Blvd West Hempstead NY 11552",
    "addr:housenumber":"239",
    "addr:postcode":"11552",
    "addr:street":"Nassau Blvd West",
    "iso:country":"US",
    "sg:address":"239 Nassau Blvd",
    "sg:city":"West Hempstead",
    "sg:classifiers":[
        {
            "category":"Restaurant",
            "type":"Food & Drink"
        }
    ],
    "sg:phone":"+1 516 292 0374",
    "sg:postcode":"11552",
    "sg:province":"NY",
    "sg:tags":[
        "pizza"
    ],
    "sg:website":"www.peppinos-pizzeria.com",
    "wof:name":"Peppino's Pizzeria",
    "wof:placetype":"venue"
},
  "geometry": {"coordinates":[-73.6605,40.699699],"type":"Point"}
}