{
  "type": "Feature",
  "properties": {
    "iso:country":"US",
    "sg:address":"3290 Canandaigua Rd",
    "sg:city":"Macedon",
    "sg:classifiers":[
        {
            "category":"Restaurant",
            "type":"Food & Drink"
        }
    ],
    "sg:phone":"+1 315 986 5678",
    "sg:postcode":"14502",
    "sg:province":"NY",
    "sg:tags":[
        "pizza"
    ],
    "wof:name":"Pontillo's Gananda Pizzeria",
    "wof:placetype":"venue"
},
  "geometry": {"coordinates":[-77.320892,43.123614],"type":"Point"}
}