{
  "type": "Feature",
  "properties": {
    "addr:full":"820 Rensselaer Ave Staten Island NY 10309",
    "addr:housenumber":"820",
    "addr:postcode":"10309",
    "addr:street":"Rensselaer Ave",
    "iso:country":"US",
    "sg:address":"820 Rensselaer Ave",
    "sg:city":"Staten Island",
    "sg:classifiers":[
        {
            "category":"Professional",
            "type":"Services"
        }
    ],
    "sg:phone":"+1   ",
    "sg:postcode":"10309",
    "sg:province":"NY",
    "wof:name":"Onnuri Corp",
    "wof:placetype":"venue"
},
  "geometry": {"coordinates":[-74.201588,40.538832],"type":"Point"}
}