{
  "type": "Feature",
  "properties": {
    "iso:country":"US",
    "sg:address":"74 W Lake Blvd",
    "sg:city":"Mahopac",
    "sg:classifiers":[
        {
            "category":"Professional",
            "subcategory":"Advertising",
            "type":"Services"
        }
    ],
    "sg:phone":"+1 845 628 1341",
    "sg:postcode":"10541",
    "sg:province":"NY",
    "sg:tags":[
        "counselor"
    ],
    "sg:website":"www.pointmarketing.com",
    "wof:name":"Point Marketing Svc",
    "wof:placetype":"venue"
},
  "geometry": {"coordinates":[-73.75211899999999,41.375969],"type":"Point"}
}