{
  "type": "Feature",
  "properties": {
    "addr:full":"377 Madison Ave New York NY 10017",
    "addr:housenumber":"377",
    "addr:postcode":"10017",
    "addr:street":"Madison Ave",
    "iso:country":"US",
    "sg:address":"377 Madison Ave",
    "sg:city":"New York",
    "sg:classifiers":[
        {
            "category":"Shopping",
            "subcategory":"Clothing, Apparel, & Fashions",
            "type":"Retail Goods"
        }
    ],
    "sg:phone":"+1 212 286 8988",
    "sg:postcode":"10017",
    "sg:province":"NY",
    "sg:tags":[
        "men's",
        "clothing"
    ],
    "sg:website":"www.ctshirts.co.uk",
    "wof:name":"Charles Tyrwhitt",
    "wof:placetype":"venue"
},
  "geometry": {"coordinates":[-73.977164,40.755414],"type":"Point"}
}