{
  "type": "Feature",
  "properties": {
    "addr:full":"11 Windham Way Buffalo NY 14228",
    "addr:housenumber":"11",
    "addr:postcode":"14228",
    "addr:street":"Windham Way",
    "iso:country":"US",
    "sg:address":"11 Windham Way",
    "sg:city":"Buffalo",
    "sg:classifiers":[
        {
            "category":"Building & Trades",
            "subcategory":"Landscaping Services",
            "type":"Services"
        }
    ],
    "sg:phone":"+1 716 639 0873",
    "sg:postcode":"14228",
    "sg:province":"NY",
    "sg:tags":[
        "landscape"
    ],
    "wof:name":"Ferreri Landscaping",
    "wof:placetype":"venue"
},
  "geometry": {"coordinates":[-78.796639,43.016118],"type":"Point"}
}