{
  "type": "Feature",
  "properties": {
    "iso:country":"US",
    "sg:address":"735 E Boston Post Rd",
    "sg:city":"Mamaroneck",
    "sg:classifiers":[
        {
            "category":"Personal",
            "type":"Services"
        }
    ],
    "sg:phone":"+1 914 777 2873",
    "sg:postcode":"10543",
    "sg:province":"NY",
    "wof:name":"Bodicures Ltd",
    "wof:placetype":"venue"
},
  "geometry": {"coordinates":[-73.725511,40.952879],"type":"Point"}
}