{
  "type": "Feature",
  "properties": {
    "addr:full":"378 Coney Island Ave Brooklyn NY 11218",
    "addr:housenumber":"378",
    "addr:postcode":"11218",
    "addr:street":"Coney Island Ave",
    "iso:country":"US",
    "sg:address":"378 Coney Island Ave",
    "sg:city":"Brooklyn",
    "sg:classifiers":[
        {
            "category":"Autos & Motor Vehicles",
            "subcategory":"Fuel & Gas Station",
            "type":"Retail Goods"
        },
        {
            "category":"Retail",
            "subcategory":"Auto Repair",
            "type":"Services"
        }
    ],
    "sg:phone":"+1 718 514 2168",
    "sg:postcode":"11218",
    "sg:province":"NY",
    "sg:website":"aitrk.bollacarcare.com",
    "wof:name":"Caton & Coney Car Care Center",
    "wof:placetype":"venue"
},
  "geometry": {"coordinates":[-73.971799,40.648502],"type":"Point"}
}