{
  "type": "Feature",
  "properties": {
    "addr:full":"32 Broadhead Ave Jamestown NY 14701",
    "addr:housenumber":"32",
    "addr:postcode":"14701",
    "addr:street":"Broadhead Ave",
    "iso:country":"US",
    "sg:address":"32 Broadhead Ave",
    "sg:city":"Jamestown",
    "sg:classifiers":[
        {
            "category":"Building & Trades",
            "subcategory":"Construction",
            "type":"Services"
        }
    ],
    "sg:phone":"+1 716 484 7828",
    "sg:postcode":"14701",
    "sg:province":"NY",
    "sg:tags":[
        "floor",
        "laying",
        "contractor"
    ],
    "wof:name":"Southern Tier Crpt Instllation",
    "wof:placetype":"venue"
},
  "geometry": {"coordinates":[-79.235972,42.088649],"type":"Point"}
}