{
  "type": "Feature",
  "properties": {
    "addr:full":"1818 Bath Ave Brooklyn NY 11214",
    "addr:housenumber":"1818",
    "addr:postcode":"11214",
    "addr:street":"Bath Ave",
    "iso:country":"US",
    "sg:address":"1818 Bath Ave",
    "sg:city":"Brooklyn",
    "sg:classifiers":[
        {
            "category":"Restaurant",
            "type":"Food & Drink"
        }
    ],
    "sg:phone":"+1   ",
    "sg:postcode":"11214",
    "sg:province":"NY",
    "sg:tags":[
        "grocery",
        "eating"
    ],
    "wof:name":"Z & A Deli & Grocery",
    "wof:placetype":"venue"
},
  "geometry": {"coordinates":[-74.004729,40.603052],"type":"Point"}
}