{
  "type": "Feature",
  "properties": {
    "addr:full":"187 Center St Massena NY 13662",
    "addr:housenumber":"187",
    "addr:postcode":"13662",
    "addr:street":"Center St",
    "iso:country":"US",
    "sg:address":"187 Center St",
    "sg:city":"Massena",
    "sg:classifiers":[
        {
            "category":"Place Of Worship",
            "type":"Public Place"
        }
    ],
    "sg:phone":"+1 315 769 3248",
    "sg:postcode":"13662",
    "sg:province":"NY",
    "sg:tags":[
        "church"
    ],
    "wof:name":"Graffis Faith Tarbell",
    "wof:placetype":"venue"
},
  "geometry": {"coordinates":[-74.884334,44.934174],"type":"Point"}
}