{
  "type": "Feature",
  "properties": {
    "addr:full":"16W. 45th Street (7th Floor) New York NY 10036",
    "addr:housenumber":"16w;7th floor",
    "addr:postcode":"10036",
    "addr:street":"45Th Street",
    "iso:country":"US",
    "sg:address":"16W. 45th Street (7th Floor)",
    "sg:city":"New York",
    "sg:classifiers":[
        {
            "category":"Professional",
            "subcategory":"Computer Services",
            "type":"Services"
        }
    ],
    "sg:postcode":"10036",
    "sg:province":"NY",
    "sg:website":"http://www.americantelephonecompany.com/",
    "wof:name":"American Telephone Company",
    "wof:placetype":"venue"
},
  "geometry": {"coordinates":[-73.98239100000001,40.756506],"type":"Point"}
}