{
  "type": "Feature",
  "properties": {
    "iso:country":"US",
    "sg:address":"932 Garfield St",
    "sg:city":"Peekskill",
    "sg:classifiers":[
        {
            "category":"Professional",
            "subcategory":"Computer Services",
            "type":"Services"
        }
    ],
    "sg:phone":"+1 914 739 2161",
    "sg:postcode":"10566",
    "sg:province":"NY",
    "sg:tags":[
        "repair"
    ],
    "wof:name":"Yeah Right",
    "wof:placetype":"venue"
},
  "geometry": {"coordinates":[-73.921218,41.300227],"type":"Point"}
}