{
  "type": "Feature",
  "properties": {
    "addr:full":"38 Riverside Dr Binghamton NY 13905",
    "addr:housenumber":"38",
    "addr:postcode":"13905",
    "addr:street":"Riverside Dr",
    "iso:country":"US",
    "sg:address":"38 Riverside Dr",
    "sg:city":"Binghamton",
    "sg:classifiers":[
        {
            "category":"Health Services",
            "subcategory":"Health Practitioner",
            "type":"Services"
        },
        {
            "category":"Health Services",
            "subcategory":"Doctor",
            "type":"Services"
        }
    ],
    "sg:phone":"+1 607 724 2245",
    "sg:postcode":"13905",
    "sg:province":"NY",
    "sg:tags":[
        "psychotherapist",
        "medical",
        "heal"
    ],
    "wof:name":"Institute For Psychoanalytic",
    "wof:placetype":"venue"
},
  "geometry": {"coordinates":[-75.92200699999999,42.092648],"type":"Point"}
}