{
  "type": "Feature",
  "properties": {
    "iso:country":"US",
    "sg:address":"439 9th St",
    "sg:city":"Brooklyn",
    "sg:classifiers":[
        {
            "category":"Health Services",
            "subcategory":"Doctor",
            "type":"Services"
        }
    ],
    "sg:phone":"+1   ",
    "sg:postcode":"11215",
    "sg:province":"NY",
    "wof:name":"Boris Magid",
    "wof:placetype":"venue"
},
  "geometry": {"coordinates":[-73.979235,40.665845],"type":"Point"}
}