{
  "type": "Feature",
  "properties": {
    "addr:full":"33 Packwood Rd Geneva NY 14456",
    "addr:housenumber":"33",
    "addr:postcode":"14456",
    "addr:street":"Packwood Rd",
    "iso:country":"US",
    "sg:address":"33 Packwood Rd",
    "sg:city":"Geneva",
    "sg:classifiers":[
        {
            "category":"Sports & Exercise",
            "subcategory":"Golf",
            "type":"Entertainment"
        }
    ],
    "sg:phone":"+1   ",
    "sg:postcode":"14456",
    "sg:province":"NY",
    "sg:tags":[
        "course",
        "public"
    ],
    "wof:name":"Big Oak Public Golf Course",
    "wof:placetype":"venue"
},
  "geometry": {"coordinates":[-76.967054,42.906227],"type":"Point"}
}