{
  "type": "Feature",
  "properties": {
    "addr:full":"187 Delaware Ave Buffalo NY 14202",
    "addr:housenumber":"187",
    "addr:postcode":"14202",
    "addr:street":"Delaware Ave",
    "iso:country":"US",
    "sg:address":"187 Delaware Ave",
    "sg:city":"Buffalo",
    "sg:classifiers":[
        {
            "category":"Professional",
            "subcategory":"Printing & Photocopies",
            "type":"Services"
        }
    ],
    "sg:phone":"+1 716 854 6772",
    "sg:postcode":"14202",
    "sg:province":"NY",
    "sg:tags":[
        "blueprinting",
        "computer",
        "printer",
        "supply"
    ],
    "wof:name":"Seneca Copy Center",
    "wof:placetype":"venue"
},
  "geometry": {"coordinates":[-78.877095,42.889698],"type":"Point"}
}