{
  "type": "Feature",
  "properties": {
    "addr:full":"5717 5th Ave Brooklyn NY 11220",
    "addr:housenumber":"5717",
    "addr:postcode":"11220",
    "addr:street":"5Th Ave",
    "iso:country":"US",
    "sg:address":"5717 5th Ave",
    "sg:city":"Brooklyn",
    "sg:classifiers":[
        {
            "category":"Restaurant",
            "type":"Food & Drink"
        }
    ],
    "sg:phone":"+1 718 439 5647",
    "sg:postcode":"11220",
    "sg:province":"NY",
    "wof:name":"Taco Mex Inc",
    "wof:placetype":"venue"
},
  "geometry": {"coordinates":[-74.014849,40.640671],"type":"Point"}
}