{
  "type": "Feature",
  "properties": {
    "iso:country":"US",
    "sg:address":"2060 Lakeville Rd",
    "sg:city":"Avon",
    "sg:classifiers":[
        {
            "category":"Building & Trades",
            "subcategory":"Construction",
            "type":"Services"
        },
        {
            "category":"Building & Trades",
            "subcategory":"Plumbing",
            "type":"Services"
        }
    ],
    "sg:phone":"+1 585 226 6244",
    "sg:postcode":"14414",
    "sg:province":"NY",
    "sg:tags":[
        "installs",
        "mechanical",
        "millwright",
        "contractor"
    ],
    "wof:name":"LMC Industrial Contractors",
    "wof:placetype":"venue"
},
  "geometry": {"coordinates":[-77.709363,42.891773],"type":"Point"}
}