{
  "type": "Feature",
  "properties": {
    "iso:country":"US",
    "sg:address":"1967 7th Ave",
    "sg:city":"New York",
    "sg:classifiers":[
        {
            "category":"Restaurant",
            "type":"Food & Drink"
        }
    ],
    "sg:phone":"+1   ",
    "sg:postcode":"10026",
    "sg:province":"NY",
    "sg:tags":[
        "eating"
    ],
    "wof:name":"King Wok Kitchen",
    "wof:placetype":"venue"
},
  "geometry": {"coordinates":[-73.951838,40.803894],"type":"Point"}
}