{
  "type": "Feature",
  "properties": {
    "iso:country":"US",
    "sg:address":"367 E Rockaway Rd",
    "sg:city":"East Rockaway",
    "sg:classifiers":[
        {
            "category":"Retail",
            "subcategory":"Animal Services",
            "type":"Services"
        }
    ],
    "sg:phone":"+1 516 599 6347",
    "sg:postcode":"11518",
    "sg:province":"NY",
    "sg:tags":[
        "pet",
        "product",
        "washing",
        "grooming",
        "mfg"
    ],
    "wof:name":"Atlantis Grooming Parlor Inc",
    "wof:placetype":"venue"
},
  "geometry": {"coordinates":[-73.678747,40.639927],"type":"Point"}
}