{
  "type": "Feature",
  "properties": {
    "addr:full":"46 Mount Hope Ave Rochester NY 14620",
    "addr:housenumber":"46",
    "addr:postcode":"14620",
    "addr:street":"Mount Hope Ave",
    "iso:country":"US",
    "sg:address":"46 Mount Hope Ave",
    "sg:city":"Rochester",
    "sg:classifiers":[
        {
            "category":"Professional",
            "type":"Services"
        }
    ],
    "sg:phone":"+1 585 234 0611",
    "sg:postcode":"14620",
    "sg:province":"NY",
    "sg:tags":[
        "establishment"
    ],
    "wof:name":"Job Development Network",
    "wof:placetype":"venue"
},
  "geometry": {"coordinates":[-77.60740199999999,43.147853],"type":"Point"}
}