{
  "type": "Feature",
  "properties": {
    "iso:country":"US",
    "sg:address":"20 W Park Ave",
    "sg:city":"Long Beach",
    "sg:classifiers":[
        {
            "category":"Building & Trades",
            "subcategory":"Electrical",
            "type":"Services"
        }
    ],
    "sg:phone":"+1 516 897 2671",
    "sg:postcode":"11561",
    "sg:province":"NY",
    "sg:tags":[
        "booth",
        "equipment",
        "telephone",
        "pay"
    ],
    "wof:name":"Pay Telephone Svc",
    "wof:placetype":"venue"
},
  "geometry": {"coordinates":[-73.664832,40.588403],"type":"Point"}
}