{
  "type": "Feature",
  "properties": {
    "addr:full":"353 Pine Tree Rd Ithaca NY 14850",
    "addr:housenumber":"353",
    "addr:postcode":"14850",
    "addr:street":"Pine Tree Rd",
    "iso:country":"US",
    "sg:address":"353 Pine Tree Rd",
    "sg:city":"Ithaca",
    "sg:classifiers":[
        {
            "category":"Manufacturing",
            "subcategory":"Printing",
            "type":"Manufacturing & Wholesale Goods"
        }
    ],
    "sg:phone":"+1   ",
    "sg:postcode":"14850",
    "sg:province":"NY",
    "sg:tags":[
        "commercial"
    ],
    "wof:name":"Communication & Marketing Svcs",
    "wof:placetype":"venue"
},
  "geometry": {"coordinates":[-76.462912,42.432632],"type":"Point"}
}