{
  "type": "Feature",
  "properties": {
    "iso:country":"US",
    "sg:address":"322 W 57 St",
    "sg:city":"New York",
    "sg:classifiers":[
        {
            "category":"Shopping",
            "subcategory":"Clothing, Apparel, & Fashions",
            "type":"Retail Goods"
        }
    ],
    "sg:phone":"+1   ",
    "sg:postcode":"10019",
    "sg:province":"NY",
    "wof:name":"Tie Rack West",
    "wof:placetype":"venue"
},
  "geometry": {"coordinates":[-73.982877,40.766715],"type":"Point"}
}