{
  "type": "Feature",
  "properties": {
    "addr:full":"535 Smith St Farmingdale NY 11735",
    "addr:housenumber":"535",
    "addr:postcode":"11735",
    "addr:street":"Smith St",
    "iso:country":"US",
    "sg:address":"535 Smith St",
    "sg:city":"Farmingdale",
    "sg:classifiers":[
        {
            "category":"Wholesale",
            "subcategory":"Groceries",
            "type":"Manufacturing & Wholesale Goods"
        }
    ],
    "sg:phone":"+1 631 694 9500",
    "sg:postcode":"11735",
    "sg:province":"NY",
    "sg:tags":[
        "food",
        "product"
    ],
    "sg:website":"www.carouselfoods.com",
    "wof:name":"Carousel Foods Of America Inc",
    "wof:placetype":"venue"
},
  "geometry": {"coordinates":[-73.412491,40.754874],"type":"Point"}
}