{
  "type": "Feature",
  "properties": {
    "iso:country":"US",
    "sg:address":"4904 Independence Ave",
    "sg:city":"Bronx",
    "sg:classifiers":[
        {
            "category":"Education",
            "subcategory":"School",
            "type":"Public Place"
        }
    ],
    "sg:phone":"+1 718 601 4629",
    "sg:postcode":"10471",
    "sg:province":"NY",
    "sg:tags":[
        "high",
        "prep"
    ],
    "wof:name":"Yeshiva Of Telshe Alumni",
    "wof:placetype":"venue"
},
  "geometry": {"coordinates":[-73.911044,40.898708],"type":"Point"}
}