{
  "type": "Feature",
  "properties": {
    "iso:country":"US",
    "sg:address":"510 Commack Rd",
    "sg:city":"Islip",
    "sg:classifiers":[
        {
            "category":"Organizations",
            "subcategory":"Religious Organization",
            "type":"Services"
        }
    ],
    "sg:phone":"+1 631 581 6312",
    "sg:postcode":"11751",
    "sg:province":"NY",
    "sg:tags":[
        "church"
    ],
    "wof:name":"New Bethany Baptist Church",
    "wof:placetype":"venue"
},
  "geometry": {"coordinates":[-73.2265,40.753141],"type":"Point"}
}