{
  "type": "Feature",
  "properties": {
    "iso:country":"US",
    "sg:address":"1685 Elmwood Ave",
    "sg:city":"Buffalo",
    "sg:classifiers":[
        {
            "category":"Manufacturing",
            "subcategory":"Textiles",
            "type":"Manufacturing & Wholesale Goods"
        }
    ],
    "sg:phone":"+1 716 876 3023",
    "sg:postcode":"14207",
    "sg:province":"NY",
    "sg:tags":[
        "curtain"
    ],
    "wof:name":"Pierce Arrow Draperies",
    "wof:placetype":"venue"
},
  "geometry": {"coordinates":[-78.878473,42.943525],"type":"Point"}
}