{
  "type": "Feature",
  "properties": {
    "iso:country":"US",
    "sg:address":"304 7th St",
    "sg:city":"Watkins Glen",
    "sg:classifiers":[
        {
            "category":"Government",
            "subcategory":"Office",
            "type":"Public Place"
        }
    ],
    "sg:phone":"+1 607 535 2139",
    "sg:postcode":"14891",
    "sg:province":"NY",
    "sg:tags":[
        "city",
        "inspection"
    ],
    "wof:name":"Building Inspectors",
    "wof:placetype":"venue"
},
  "geometry": {"coordinates":[-76.867328,42.380135],"type":"Point"}
}