{
  "type": "Feature",
  "properties": {
    "addr:full":"894 E 51st St Brooklyn NY 11203",
    "addr:housenumber":"894",
    "addr:postcode":"11203",
    "addr:street":"E 51St St",
    "iso:country":"US",
    "sg:address":"894 E 51st St",
    "sg:city":"Brooklyn",
    "sg:classifiers":[
        {
            "category":"Manufacturing",
            "subcategory":"Furniture",
            "type":"Manufacturing & Wholesale Goods"
        }
    ],
    "sg:phone":"+1 718 451 0660",
    "sg:postcode":"11203",
    "sg:province":"NY",
    "sg:tags":[
        "assembles"
    ],
    "wof:name":"Francesca Imports Inc",
    "wof:placetype":"venue"
},
  "geometry": {"coordinates":[-73.92796199999999,40.637995],"type":"Point"}
}