{
  "type": "Feature",
  "properties": {
    "addr:full":"255 Brookville Rd Glen Head NY 11545",
    "addr:housenumber":"255",
    "addr:postcode":"11545",
    "addr:street":"Brookville Rd",
    "iso:country":"US",
    "sg:address":"255 Brookville Rd",
    "sg:city":"Glen Head",
    "sg:classifiers":[
        {
            "category":"Organizations",
            "subcategory":"Religious Organization",
            "type":"Services"
        }
    ],
    "sg:phone":"+1 516 921 2379",
    "sg:postcode":"11545",
    "sg:province":"NY",
    "sg:tags":[
        "church"
    ],
    "wof:name":"Jericho Monthly Meeting",
    "wof:placetype":"venue"
},
  "geometry": {"coordinates":[-73.53778,40.804137],"type":"Point"}
}