{
  "type": "Feature",
  "properties": {
    "addr:full":"6309 20th Ave Brooklyn NY 11204",
    "addr:housenumber":"6309",
    "addr:postcode":"11204",
    "addr:street":"20Th Ave",
    "iso:country":"US",
    "sg:address":"6309 20th Ave",
    "sg:city":"Brooklyn",
    "sg:classifiers":[
        {
            "category":"Food & Beverages",
            "subcategory":"Bakery",
            "type":"Retail Goods"
        }
    ],
    "sg:phone":"+1 718 256 3636",
    "sg:postcode":"11204",
    "sg:province":"NY",
    "sg:tags":[
        "baker"
    ],
    "wof:name":"Gondola Bakery",
    "wof:placetype":"venue"
},
  "geometry": {"coordinates":[-73.98463,40.61759],"type":"Point"}
}