{
  "type": "Feature",
  "properties": {
    "addr:full":"95 Dahlia St Schenectady NY 12306",
    "addr:housenumber":"95",
    "addr:postcode":"12306",
    "addr:street":"Dahlia St",
    "iso:country":"US",
    "sg:address":"95 Dahlia St",
    "sg:city":"Schenectady",
    "sg:classifiers":[
        {
            "category":"Building & Trades",
            "subcategory":"Construction",
            "type":"Services"
        }
    ],
    "sg:phone":"+1 518 355 1727",
    "sg:postcode":"12306",
    "sg:province":"NY",
    "sg:tags":[
        "contractor"
    ],
    "wof:name":"A E Rossi Builders",
    "wof:placetype":"venue"
},
  "geometry": {"coordinates":[-73.976609,42.775793],"type":"Point"}
}