{
  "type": "Feature",
  "properties": {
    "addr:full":"29 Wooster St Gloversville NY 12078",
    "addr:housenumber":"29",
    "addr:postcode":"12078",
    "addr:street":"Wooster St",
    "iso:country":"US",
    "sg:address":"29 Wooster St",
    "sg:city":"Gloversville",
    "sg:classifiers":[
        {
            "category":"Arts & Performance",
            "subcategory":"Theater",
            "type":"Entertainment"
        }
    ],
    "sg:phone":"+1 518 725 7099",
    "sg:postcode":"12078",
    "sg:province":"NY",
    "sg:tags":[
        "jockey",
        "live",
        "disc",
        "music"
    ],
    "wof:name":"Party Mix With D J Dave",
    "wof:placetype":"venue"
},
  "geometry": {"coordinates":[-74.34348300000001,43.065868],"type":"Point"}
}