{
  "type": "Feature",
  "properties": {
    "iso:country":"US",
    "sg:address":"3 Otsego St",
    "sg:city":"Canajoharie",
    "sg:classifiers":[
        {
            "category":"Education",
            "subcategory":"School",
            "type":"Public Place"
        }
    ],
    "sg:phone":"+1 518 673 4585",
    "sg:postcode":"13317",
    "sg:province":"NY",
    "sg:tags":[
        "elementary",
        "secondary"
    ],
    "wof:name":"Canajoharie Central School Dst",
    "wof:placetype":"venue"
},
  "geometry": {"coordinates":[-74.573639,42.904922],"type":"Point"}
}