{
  "type": "Feature",
  "properties": {
    "iso:country":"US",
    "sg:address":"72 Wall Street",
    "sg:city":"New York",
    "sg:classifiers":[
        {
            "category":"Professional",
            "subcategory":"Lawyer & Legal Services",
            "type":"Services"
        }
    ],
    "sg:phone":"+1 212 770 3595",
    "sg:postcode":"10005",
    "sg:province":"NY",
    "wof:name":"Rienzo & Diakow Attys",
    "wof:placetype":"venue"
},
  "geometry": {"coordinates":[-74.00822700000001,40.705605],"type":"Point"}
}