{
  "type": "Feature",
  "properties": {
    "addr:full":"148 Dwight St Oceanside NY 11572",
    "addr:housenumber":"148",
    "addr:postcode":"11572",
    "addr:street":"Dwight St",
    "iso:country":"US",
    "sg:address":"148 Dwight St",
    "sg:city":"Oceanside",
    "sg:classifiers":[
        {
            "category":"Cinema",
            "subcategory":"Movie Rental",
            "type":"Entertainment"
        }
    ],
    "sg:phone":"+1   ",
    "sg:postcode":"11572",
    "sg:province":"NY",
    "sg:tags":[
        "video",
        "tape"
    ],
    "wof:name":"2 Brothers Video Inc",
    "wof:placetype":"venue"
},
  "geometry": {"coordinates":[-73.635571,40.63591],"type":"Point"}
}