{
  "type": "Feature",
  "properties": {
    "iso:country":"US",
    "sg:address":"169 Amsterdam Ave",
    "sg:city":"New York",
    "sg:classifiers":[
        {
            "category":"Professional",
            "type":"Services"
        },
        {
            "category":"Education",
            "subcategory":"School",
            "type":"Public Place"
        }
    ],
    "sg:phone":"+1 212 721 4100",
    "sg:postcode":"10023",
    "sg:province":"NY",
    "sg:tags":[
        "planning",
        "event"
    ],
    "sg:website":"www.nykidsclub.com",
    "wof:name":"NY Kids Club Child Enrichment Center NYC",
    "wof:placetype":"venue"
},
  "geometry": {"coordinates":[-73.983456,40.775754],"type":"Point"}
}