{
  "type": "Feature",
  "properties": {
    "addr:full":"151 2nd Ave New York NY 10003",
    "addr:housenumber":"151",
    "addr:postcode":"10003",
    "addr:street":"2Nd Ave",
    "iso:country":"US",
    "sg:address":"151 2nd Ave",
    "sg:city":"New York",
    "sg:classifiers":[
        {
            "category":"Bars & Pubs",
            "type":"Food & Drink"
        }
    ],
    "sg:phone":"+1 212 979 9511",
    "sg:postcode":"10003",
    "sg:province":"NY",
    "sg:website":"ryansnyc.com/",
    "wof:name":"Ryan's Irish Pub",
    "wof:placetype":"venue"
},
  "geometry": {"coordinates":[-73.987255,40.729509],"type":"Point"}
}