{
  "type": "Feature",
  "properties": {
    "addr:full":"1 Main St Yonkers NY 10701",
    "addr:housenumber":"1",
    "addr:postcode":"10701",
    "addr:street":"Main St",
    "iso:country":"US",
    "sg:address":"1 Main St",
    "sg:city":"Yonkers",
    "sg:classifiers":[
        {
            "category":"Restaurant",
            "type":"Food & Drink"
        }
    ],
    "sg:phone":"+1   ",
    "sg:postcode":"10701",
    "sg:province":"NY",
    "sg:tags":[
        "eating"
    ],
    "wof:name":"Coffee Break",
    "wof:placetype":"venue"
},
  "geometry": {"coordinates":[-73.898769,40.934228],"type":"Point"}
}