{
  "type": "Feature",
  "properties": {
    "iso:country":"US",
    "sg:address":"192 W Old Country Rd",
    "sg:city":"Hicksville",
    "sg:classifiers":[
        {
            "category":"Retail",
            "subcategory":"Repair Shop",
            "type":"Services"
        }
    ],
    "sg:phone":"+1 516 467 0558",
    "sg:postcode":"11801",
    "sg:province":"NY",
    "sg:tags":[
        "lock",
        "locksmith"
    ],
    "wof:name":"1 Hour Emerg A Locksmith",
    "wof:placetype":"venue"
},
  "geometry": {"coordinates":[-73.53062799999999,40.761174],"type":"Point"}
}