{
  "type": "Feature",
  "properties": {
    "iso:country":"US",
    "sg:address":"1900 Military Rd",
    "sg:city":"Niagara Falls",
    "sg:classifiers":[
        {
            "category":"Restaurant",
            "type":"Food & Drink"
        }
    ],
    "sg:phone":"+1 716 297 2949",
    "sg:postcode":"14304",
    "sg:province":"NY",
    "wof:name":"Panda Express",
    "wof:placetype":"venue"
},
  "geometry": {"coordinates":[-78.97384,43.095805],"type":"Point"}
}