{
  "type": "Feature",
  "properties": {
    "iso:country":"US",
    "sg:address":"10136 State Hwy 60",
    "sg:city":"Fredonia",
    "sg:classifiers":[
        {
            "category":"Restaurant",
            "type":"Food & Drink"
        }
    ],
    "sg:phone":"+1 716 672 5133",
    "sg:postcode":"14063",
    "sg:province":"NY",
    "wof:name":"Aldrich Beef & Ice Cream Prlr",
    "wof:placetype":"venue"
},
  "geometry": {"coordinates":[-79.304855,42.441703],"type":"Point"}
}