{
  "type": "Feature",
  "properties": {
    "addr:full":"128 E 91 St New York NY 10128",
    "addr:housenumber":"128;91",
    "addr:postcode":"10128",
    "addr:street":"E;St",
    "iso:country":"US",
    "sg:address":"128 E 91 St",
    "sg:city":"New York",
    "sg:classifiers":[
        {
            "category":"Health Services",
            "subcategory":"Health Practitioner",
            "type":"Services"
        }
    ],
    "sg:phone":"+1 917 492 4667",
    "sg:postcode":"10128",
    "sg:province":"NY",
    "sg:tags":[
        "psychotherapist"
    ],
    "wof:name":"Louis Birner",
    "wof:placetype":"venue"
},
  "geometry": {"coordinates":[-73.95401099999999,40.783014],"type":"Point"}
}