{
  "type": "Feature",
  "properties": {
    "iso:country":"US",
    "sg:address":"432 W 45 St",
    "sg:city":"New York",
    "sg:classifiers":[
        {
            "category":"Arts & Performance",
            "subcategory":"Theater",
            "type":"Entertainment"
        }
    ],
    "sg:phone":"+1 212 974 9050",
    "sg:postcode":"10036",
    "sg:province":"NY",
    "sg:tags":[
        "theatrical",
        "television",
        "program",
        "producer"
    ],
    "wof:name":"B B C Production",
    "wof:placetype":"venue"
},
  "geometry": {"coordinates":[-73.992332,40.760639],"type":"Point"}
}