{
  "type": "Feature",
  "properties": {
    "iso:country":"US",
    "sg:address":"173 Pearl St",
    "sg:city":"Kingston",
    "sg:classifiers":[
        {
            "category":"Professional",
            "subcategory":"Engineering",
            "type":"Services"
        }
    ],
    "sg:phone":"+1   ",
    "sg:postcode":"12401",
    "sg:province":"NY",
    "wof:name":"Stinemire & Associates",
    "wof:placetype":"venue"
},
  "geometry": {"coordinates":[-74.021682,41.928538],"type":"Point"}
}