{
  "type": "Feature",
  "properties": {
    "addr:full":"4 Hyson Way Coram NY 11727",
    "addr:housenumber":"4",
    "addr:postcode":"11727",
    "addr:street":"Hyson Way",
    "iso:country":"US",
    "sg:address":"4 Hyson Way",
    "sg:city":"Coram",
    "sg:classifiers":[
        {
            "category":"Building & Trades",
            "subcategory":"Plumbing",
            "type":"Services"
        }
    ],
    "sg:phone":"+1 631 698 0704",
    "sg:postcode":"11727",
    "sg:province":"NY",
    "sg:tags":[
        "m",
        "contractor"
    ],
    "wof:name":"Perfect Lawn Irrigation & Main",
    "wof:placetype":"venue"
},
  "geometry": {"coordinates":[-73.025248,40.878803],"type":"Point"}
}