{
  "type": "Feature",
  "properties": {
    "addr:full":"16 Main St Warwick NY 10990",
    "addr:housenumber":"16",
    "addr:postcode":"10990",
    "addr:street":"Main St",
    "iso:country":"US",
    "sg:address":"16 Main St",
    "sg:city":"Warwick",
    "sg:classifiers":[
        {
            "category":"Restaurant",
            "type":"Food & Drink"
        }
    ],
    "sg:phone":"+1 845 986 5565",
    "sg:postcode":"10990",
    "sg:province":"NY",
    "wof:name":"Bistro West & Main",
    "wof:placetype":"venue"
},
  "geometry": {"coordinates":[-74.356866,41.260915],"type":"Point"}
}