{
  "type": "Feature",
  "properties": {
    "iso:country":"US",
    "sg:address":"8207 Roosevelt Avenue",
    "sg:city":"Jackson Heights",
    "sg:classifiers":[
        {
            "category":"Personal",
            "subcategory":"Tattoo Parlor",
            "type":"Services"
        }
    ],
    "sg:phone":"+1 347 846 1411",
    "sg:postcode":"11372",
    "sg:province":"NY",
    "wof:name":"Crazy Tattoos",
    "wof:placetype":"venue"
},
  "geometry": {"coordinates":[-73.883611,40.747777],"type":"Point"}
}