{
  "type": "Feature",
  "properties": {
    "iso:country":"US",
    "sg:address":"9534 Short Tract Rd",
    "sg:city":"Hunt",
    "sg:classifiers":[
        {
            "category":"Travel",
            "subcategory":"Campground",
            "type":"Entertainment"
        }
    ],
    "sg:phone":"+1 585 468 3850",
    "sg:postcode":"14846",
    "sg:province":"NY",
    "sg:tags":[
        "camp"
    ],
    "wof:name":"Camp Cherith",
    "wof:placetype":"venue"
},
  "geometry": {"coordinates":[-77.998093,42.565383],"type":"Point"}
}