{
  "type": "Feature",
  "properties": {
    "addr:full":"23 Spring Ave Latham NY 12110",
    "addr:housenumber":"23",
    "addr:postcode":"12110",
    "addr:street":"Spring Ave",
    "iso:country":"US",
    "sg:address":"23 Spring Ave",
    "sg:city":"Latham",
    "sg:classifiers":[
        {
            "category":"Manufacturing",
            "subcategory":"Printing",
            "type":"Manufacturing & Wholesale Goods"
        }
    ],
    "sg:phone":"+1 518 783 5082",
    "sg:postcode":"12110",
    "sg:province":"NY",
    "sg:tags":[
        "publisher"
    ],
    "wof:name":"Latham Book Publishing",
    "wof:placetype":"venue"
},
  "geometry": {"coordinates":[-73.75564199999999,42.744689],"type":"Point"}
}