{
  "type": "Feature",
  "properties": {
    "addr:full":"220 Brandle Rd Altamont NY 12009",
    "addr:housenumber":"220",
    "addr:postcode":"12009",
    "addr:street":"Brandle Rd",
    "iso:country":"US",
    "sg:address":"220 Brandle Rd",
    "sg:city":"Altamont",
    "sg:classifiers":[
        {
            "category":"Retail",
            "subcategory":"Animal Services",
            "type":"Services"
        }
    ],
    "sg:phone":"+1 518 861 8391",
    "sg:postcode":"12009",
    "sg:province":"NY",
    "wof:name":"Altamont Country Kennels",
    "wof:placetype":"venue"
},
  "geometry": {"coordinates":[-74.021745,42.697014],"type":"Point"}
}