{
  "type": "Feature",
  "properties": {
    "iso:country":"US",
    "sg:address":"25 Broad St",
    "sg:city":"Kinderhook",
    "sg:classifiers":[
        {
            "category":"Education",
            "subcategory":"School",
            "type":"Public Place"
        }
    ],
    "sg:phone":"+1 518 758 7569",
    "sg:postcode":"12106",
    "sg:province":"NY",
    "wof:name":"Ichabod Crane Central School",
    "wof:placetype":"venue"
},
  "geometry": {"coordinates":[-73.701842,42.393313],"type":"Point"}
}