{
  "type": "Feature",
  "properties": {
    "iso:country":"US",
    "sg:address":"4512 Fort Hamilton Pkwy",
    "sg:city":"Brooklyn",
    "sg:classifiers":[
        {
            "category":"Retail",
            "subcategory":"Laundry & Dry Cleaning",
            "type":"Services"
        }
    ],
    "sg:phone":"+1 718 871 1240",
    "sg:postcode":"11219",
    "sg:province":"NY",
    "wof:name":"Landaus French Cleaners",
    "wof:placetype":"venue"
},
  "geometry": {"coordinates":[-73.99520099999999,40.640202],"type":"Point"}
}