{
  "type": "Feature",
  "properties": {
    "iso:country":"US",
    "sg:address":"338 E 11th St",
    "sg:city":"Manhattan",
    "sg:classifiers":[
        {
            "category":"Shopping",
            "subcategory":"Clothing, Apparel, & Fashions",
            "type":"Retail Goods"
        }
    ],
    "sg:phone":"+1 347 694 0633",
    "sg:postcode":"10003",
    "sg:province":"NY",
    "sg:tags":[
        "clothing",
        "women's"
    ],
    "sg:website":"www.crown2.com",
    "wof:name":"Crown2",
    "wof:placetype":"venue"
},
  "geometry": {"coordinates":[-73.98472700000001,40.729436],"type":"Point"}
}