{
  "type": "Feature",
  "properties": {
    "addr:full":"4 E William St Bath NY 14810",
    "addr:housenumber":"4",
    "addr:postcode":"14810",
    "addr:street":"E William St",
    "iso:country":"US",
    "sg:address":"4 E William St",
    "sg:city":"Bath",
    "sg:classifiers":[
        {
            "category":"Personal",
            "subcategory":"Beauty Salon",
            "type":"Services"
        }
    ],
    "sg:phone":"+1 607 776 3240",
    "sg:postcode":"14810",
    "sg:province":"NY",
    "wof:name":"Hair Styling By Emily",
    "wof:placetype":"venue"
},
  "geometry": {"coordinates":[-77.318172,42.335244],"type":"Point"}
}