{
  "type": "Feature",
  "properties": {
    "addr:full":"8520 Tonawanda Creek Rd East Amherst NY 14051",
    "addr:housenumber":"8520",
    "addr:postcode":"14051",
    "addr:street":"Tonawanda Creek Rd",
    "iso:country":"US",
    "sg:address":"8520 Tonawanda Creek Rd",
    "sg:city":"East Amherst",
    "sg:classifiers":[
        {
            "category":"Organizations",
            "subcategory":"Religious Organization",
            "type":"Services"
        }
    ],
    "sg:phone":"+1 716 639 7512",
    "sg:postcode":"14051",
    "sg:province":"NY",
    "sg:tags":[
        "church"
    ],
    "wof:name":"St Stephen United Chr-Christ",
    "wof:placetype":"venue"
},
  "geometry": {"coordinates":[-78.666648,43.084832],"type":"Point"}
}