{
  "type": "Feature",
  "properties": {
    "addr:full":"95 E 161st St Bronx NY 10451",
    "addr:housenumber":"95",
    "addr:postcode":"10451",
    "addr:street":"E 161St St",
    "iso:country":"US",
    "sg:address":"95 E 161st St",
    "sg:city":"Bronx",
    "sg:classifiers":[
        {
            "category":"Professional",
            "subcategory":"Lawyer & Legal Services",
            "type":"Services"
        }
    ],
    "sg:phone":"+1 718 590 1600",
    "sg:postcode":"10451",
    "sg:province":"NY",
    "wof:name":"Jobi Kehinde",
    "wof:placetype":"venue"
},
  "geometry": {"coordinates":[-73.92440000000001,40.827599],"type":"Point"}
}