{
  "type": "Feature",
  "properties": {
    "addr:full":"251 Ft Washington Ave Apt 1 Manhattan NY 10032",
    "addr:housenumber":"1",
    "addr:postcode":"10032",
    "addr:street":"251 Ft Washington Ave Apt",
    "iso:country":"US",
    "sg:address":"251 Ft Washington Ave Apt 1",
    "sg:city":"Manhattan",
    "sg:classifiers":[
        {
            "category":"Personal",
            "subcategory":"Massage",
            "type":"Services"
        },
        {
            "category":"Health Services",
            "subcategory":"Clinic",
            "type":"Services"
        },
        {
            "category":"Health Services",
            "subcategory":"Health Practitioner",
            "type":"Services"
        }
    ],
    "sg:phone":"+1 212 927 8039",
    "sg:postcode":"10032",
    "sg:province":"NY",
    "sg:tags":[
        "acupuncture",
        "loss",
        "weight"
    ],
    "sg:website":"www.acu-columbia.com",
    "wof:name":"Columbia Acu-Herb",
    "wof:placetype":"venue"
},
  "geometry": {"coordinates":[-73.941743,40.843752],"type":"Point"}
}