{
  "type": "Feature",
  "properties": {
    "addr:full":"1393 Wisconsin Rd Derby NY 14047",
    "addr:housenumber":"1393",
    "addr:postcode":"14047",
    "addr:street":"Wisconsin Rd",
    "iso:country":"US",
    "sg:address":"1393 Wisconsin Rd",
    "sg:city":"Derby",
    "sg:phone":"+1   ",
    "sg:postcode":"14047",
    "sg:province":"NY",
    "sg:tags":[
        "irrigation",
        "system"
    ],
    "wof:name":"Irrigation & Pump Specialties",
    "wof:placetype":"venue"
},
  "geometry": {"coordinates":[-78.97839999999999,42.691734],"type":"Point"}
}