{
  "type": "Feature",
  "properties": {
    "addr:full":"30 Greencliff Ln Garrison NY 10524",
    "addr:housenumber":"30",
    "addr:postcode":"10524",
    "addr:street":"Greencliff Ln",
    "iso:country":"US",
    "sg:address":"30 Greencliff Ln",
    "sg:city":"Garrison",
    "sg:classifiers":[
        {
            "category":"Arts & Performance",
            "subcategory":"Theater",
            "type":"Entertainment"
        }
    ],
    "sg:phone":"+1 212 260 1600",
    "sg:postcode":"10524",
    "sg:province":"NY",
    "sg:tags":[
        "music",
        "agent"
    ],
    "wof:name":"Art Labriola Productions",
    "wof:placetype":"venue"
},
  "geometry": {"coordinates":[-73.925073,41.391374],"type":"Point"}
}