{
  "type": "Feature",
  "properties": {
    "addr:full":"57 E 11 St New York NY 10003",
    "addr:housenumber":"57;11",
    "addr:postcode":"10003",
    "addr:street":"E;St",
    "iso:country":"US",
    "sg:address":"57 E 11 St",
    "sg:city":"New York",
    "sg:classifiers":[
        {
            "category":"Shopping",
            "subcategory":"Shoes",
            "type":"Retail Goods"
        }
    ],
    "sg:phone":"+1 212 780 6033",
    "sg:postcode":"10003",
    "sg:province":"NY",
    "wof:name":"Nice Shoes LLC",
    "wof:placetype":"venue"
},
  "geometry": {"coordinates":[-73.991671,40.732748],"type":"Point"}
}