{
  "type": "Feature",
  "properties": {
    "addr:full":"605 W Genesee St Syracuse NY 13204",
    "addr:housenumber":"605",
    "addr:postcode":"13204",
    "addr:street":"W Genesee St",
    "iso:country":"US",
    "sg:address":"605 W Genesee St",
    "sg:city":"Syracuse",
    "sg:classifiers":[
        {
            "category":"Building & Trades",
            "subcategory":"Construction",
            "type":"Services"
        }
    ],
    "sg:phone":"+1 315 472 3139",
    "sg:postcode":"13204",
    "sg:province":"NY",
    "sg:tags":[
        "buyer",
        "cooperative"
    ],
    "wof:name":"National Buyers Group Inc",
    "wof:placetype":"venue"
},
  "geometry": {"coordinates":[-76.162969,43.053386],"type":"Point"}
}