{
  "type": "Feature",
  "properties": {
    "addr:full":"530 N Main St Brewster NY 10509",
    "addr:housenumber":"530",
    "addr:postcode":"10509",
    "addr:street":"N Main St",
    "iso:country":"US",
    "sg:address":"530 N Main St",
    "sg:city":"Brewster",
    "sg:classifiers":[
        {
            "category":"Health Services",
            "subcategory":"Doctor",
            "type":"Services"
        }
    ],
    "sg:phone":"+1 845 279 3330",
    "sg:postcode":"10509",
    "sg:province":"NY",
    "sg:tags":[
        "surgeon",
        "oral"
    ],
    "wof:name":"Raskob Gerald V DDS",
    "wof:placetype":"venue"
},
  "geometry": {"coordinates":[-73.61889600000001,41.399899],"type":"Point"}
}