{
  "type": "Feature",
  "properties": {
    "iso:country":"US",
    "sg:address":"5 E 51 St",
    "sg:city":"New York",
    "sg:classifiers":[
        {
            "category":"Restaurant",
            "type":"Food & Drink"
        }
    ],
    "sg:phone":"+1   ",
    "sg:postcode":"10022",
    "sg:province":"NY",
    "wof:name":"Prime Burger",
    "wof:placetype":"venue"
},
  "geometry": {"coordinates":[-73.975285,40.758656],"type":"Point"}
}