{
  "type": "Feature",
  "properties": {
    "iso:country":"US",
    "sg:address":"440 Harold Ave",
    "sg:city":"Staten Island",
    "sg:classifiers":[
        {
            "category":"Building & Trades",
            "subcategory":"Electrical",
            "type":"Services"
        }
    ],
    "sg:phone":"+1 718 317 5615",
    "sg:postcode":"10312",
    "sg:province":"NY",
    "sg:tags":[
        "contracting",
        "electrical"
    ],
    "wof:name":"Alcole Elec Contg Comp Inc",
    "wof:placetype":"venue"
},
  "geometry": {"coordinates":[-74.163332,40.529054],"type":"Point"}
}