{
  "type": "Feature",
  "properties": {
    "addr:full":"431 7th Avenue New York NY 10001",
    "addr:housenumber":"431",
    "addr:postcode":"10001",
    "addr:street":"7Th Avenue",
    "iso:country":"US",
    "sg:address":"431 7th Avenue",
    "sg:city":"New York",
    "sg:classifiers":[
        {
            "category":"Building & Trades",
            "subcategory":"Plumbing",
            "type":"Services"
        }
    ],
    "sg:phone":"+1 646 509 2089",
    "sg:postcode":"10001",
    "sg:province":"NY",
    "wof:name":"0 # 0 & 0 1 Emergency A 24 Hour A Plumbing",
    "wof:placetype":"venue"
},
  "geometry": {"coordinates":[-73.99082,40.750935],"type":"Point"}
}