{
  "type": "Feature",
  "properties": {
    "addr:full":"20 E 46th St Ste 1000 New York NY 10017",
    "addr:housenumber":"20",
    "addr:postcode":"10017",
    "addr:street":"E 46Th St Ste 1000",
    "iso:country":"US",
    "sg:address":"20 E 46th St Ste 1000",
    "sg:city":"New York",
    "sg:classifiers":[
        {
            "category":"Health Services",
            "subcategory":"Dentist",
            "type":"Services"
        }
    ],
    "sg:phone":"+1 212 813 0850",
    "sg:postcode":"10017",
    "sg:province":"NY",
    "sg:website":"www.meridiandentalgroup.com",
    "wof:name":"Meridian Dental Group",
    "wof:placetype":"venue"
},
  "geometry": {"coordinates":[-73.977763,40.755484],"type":"Point"}
}