{
  "type": "Feature",
  "properties": {
    "iso:country":"US",
    "sg:address":"320 N Willow St",
    "sg:city":"Oneida",
    "sg:classifiers":[
        {
            "category":"Government",
            "subcategory":"Office",
            "type":"Public Place"
        }
    ],
    "sg:phone":"+1 315 363 0447",
    "sg:postcode":"13421",
    "sg:province":"NY",
    "sg:tags":[
        "county"
    ],
    "wof:name":"Madison County Chapter Nysarc",
    "wof:placetype":"venue"
},
  "geometry": {"coordinates":[-75.66267999999999,43.100122],"type":"Point"}
}