{
  "type": "Feature",
  "properties": {
    "iso:country":"US",
    "sg:address":"2405 Vestal Pkwy E",
    "sg:city":"Vestal",
    "sg:classifiers":[
        {
            "category":"Personal",
            "subcategory":"Beauty Salon",
            "type":"Services"
        }
    ],
    "sg:phone":"+1 607 729 5381",
    "sg:postcode":"13850",
    "sg:province":"NY",
    "wof:name":"Smart Style Family Hair Salon",
    "wof:placetype":"venue"
},
  "geometry": {"coordinates":[-76.00994,42.094791],"type":"Point"}
}