{
  "type": "Feature",
  "properties": {
    "addr:full":"6700 Main St Williamsville NY 14221",
    "addr:housenumber":"6700",
    "addr:postcode":"14221",
    "addr:street":"Main St",
    "iso:country":"US",
    "sg:address":"6700 Main St",
    "sg:city":"Williamsville",
    "sg:classifiers":[
        {
            "category":"Banks & Credit Unions",
            "subcategory":"Investment Brokerage",
            "type":"Services"
        }
    ],
    "sg:phone":"+1 716 626 1300",
    "sg:postcode":"14221",
    "sg:province":"NY",
    "sg:tags":[
        "consultant",
        "planning",
        "financial"
    ],
    "sg:website":"www.agedwards.com",
    "wof:name":"A G Edwards & Sons Inc",
    "wof:placetype":"venue"
},
  "geometry": {"coordinates":[-78.70363500000001,42.965564],"type":"Point"}
}