{
  "type": "Feature",
  "properties": {
    "iso:country":"US",
    "sg:address":"143 W 41st St",
    "sg:city":"New York",
    "sg:classifiers":[
        {
            "category":"Food & Beverages",
            "subcategory":"Candy",
            "type":"Retail Goods"
        },
        {
            "category":"Food & Beverages",
            "subcategory":"Groceries & Convenience Stores",
            "type":"Retail Goods"
        }
    ],
    "sg:phone":"+1 212 398 3825",
    "sg:postcode":"10036",
    "sg:province":"NY",
    "wof:name":"S & P Newstand & Grocery Store",
    "wof:placetype":"venue"
},
  "geometry": {"coordinates":[-73.986198,40.7547],"type":"Point"}
}