{
  "type": "Feature",
  "properties": {
    "iso:country":"US",
    "sg:address":"1707 Middle Country Rd",
    "sg:city":"Centereach",
    "sg:classifiers":[
        {
            "category":"Personal",
            "subcategory":"Barber",
            "type":"Services"
        }
    ],
    "sg:phone":"+1 631 736 6339",
    "sg:postcode":"11720",
    "sg:province":"NY",
    "wof:name":"Vinnie's Barber Shop",
    "wof:placetype":"venue"
},
  "geometry": {"coordinates":[-73.09339900000001,40.858101],"type":"Point"}
}