{
  "type": "Feature",
  "properties": {
    "addr:full":"67 Pond Rd Yonkers NY 10701",
    "addr:housenumber":"67",
    "addr:postcode":"10701",
    "addr:street":"Pond Rd",
    "iso:country":"US",
    "sg:address":"67 Pond Rd",
    "sg:city":"Yonkers",
    "sg:classifiers":[
        {
            "category":"Organizations",
            "subcategory":"Religious Organization",
            "type":"Services"
        }
    ],
    "sg:phone":"+1 914 709 1939",
    "sg:postcode":"10701",
    "sg:province":"NY",
    "sg:tags":[
        "church"
    ],
    "wof:name":"Iglesia Pentecostal Jesucristo",
    "wof:placetype":"venue"
},
  "geometry": {"coordinates":[-73.886517,40.935753],"type":"Point"}
}