{
  "type": "Feature",
  "properties": {
    "iso:country":"US",
    "sg:address":"319 Browncroft Blvd",
    "sg:city":"Rochester",
    "sg:classifiers":[
        {
            "category":"Organizations",
            "subcategory":"Religious Organization",
            "type":"Services"
        }
    ],
    "sg:phone":"+1 585 482 7440",
    "sg:postcode":"14609",
    "sg:province":"NY",
    "sg:tags":[
        "church"
    ],
    "wof:name":"A Christ Centered Church",
    "wof:placetype":"venue"
},
  "geometry": {"coordinates":[-77.53954899999999,43.157332],"type":"Point"}
}