{
  "type": "Feature",
  "properties": {
    "addr:full":"148 W 136th St New York NY 10030",
    "addr:housenumber":"148",
    "addr:postcode":"10030",
    "addr:street":"W 136Th St",
    "iso:country":"US",
    "sg:address":"148 W 136th St",
    "sg:city":"New York",
    "sg:classifiers":[
        {
            "category":"Real Estate",
            "subcategory":"Real Estate Operator",
            "type":"Services"
        }
    ],
    "sg:phone":"+1 212 926 8442",
    "sg:postcode":"10030",
    "sg:province":"NY",
    "sg:tags":[
        "building",
        "apartment",
        "operates"
    ],
    "wof:name":"Melvin C Galloway",
    "wof:placetype":"venue"
},
  "geometry": {"coordinates":[-73.942218,40.815336],"type":"Point"}
}