{
  "type": "Feature",
  "properties": {
    "iso:country":"US",
    "sg:address":"54 Bay St",
    "sg:city":"Glens Falls",
    "sg:classifiers":[
        {
            "category":"Organizations",
            "subcategory":"Non-profit Organization",
            "type":"Services"
        },
        {
            "category":"Health Services",
            "subcategory":"Clinic",
            "type":"Services"
        }
    ],
    "sg:phone":"+1 518 798 1066",
    "sg:postcode":"12801",
    "sg:province":"NY",
    "sg:tags":[
        "mental",
        "outpatient",
        "facility"
    ],
    "wof:name":"Liberty House",
    "wof:placetype":"venue"
},
  "geometry": {"coordinates":[-73.647386,43.313397],"type":"Point"}
}