{
  "type": "Feature",
  "properties": {
    "iso:country":"US",
    "sg:address":"122 Plum St",
    "sg:city":"Syracuse",
    "sg:classifiers":[
        {
            "category":"Health Services",
            "subcategory":"Health Practitioner",
            "type":"Services"
        }
    ],
    "sg:phone":"+1 315 478 0356",
    "sg:postcode":"13204",
    "sg:province":"NY",
    "sg:tags":[
        "dietitian"
    ],
    "wof:name":"Maureen BURKE Nutrition",
    "wof:placetype":"venue"
},
  "geometry": {"coordinates":[-76.16042400000001,43.050629],"type":"Point"}
}