{
  "type": "Feature",
  "properties": {
    "iso:country":"US",
    "sg:address":"319 E Shore Rd",
    "sg:city":"Great Neck",
    "sg:classifiers":[
        {
            "category":"Real Estate",
            "subcategory":"Real Estate Operator",
            "type":"Services"
        }
    ],
    "sg:phone":"+1 516 829 3810",
    "sg:postcode":"11030",
    "sg:province":"NY",
    "sg:tags":[
        "building",
        "nonresidential"
    ],
    "wof:name":"Armon & Eisenberg",
    "wof:placetype":"venue"
},
  "geometry": {"coordinates":[-73.70907200000001,40.790819],"type":"Point"}
}