{
  "type": "Feature",
  "properties": {
    "iso:country":"US",
    "sg:address":"97 Harrison Ave",
    "sg:city":"Island Park",
    "sg:classifiers":[
        {
            "category":"Home & Garden",
            "subcategory":"Building Materials",
            "type":"Retail Goods"
        }
    ],
    "sg:phone":"+1 516 678 3864",
    "sg:postcode":"11558",
    "sg:province":"NY",
    "sg:tags":[
        "door"
    ],
    "wof:name":"Electronic Door Lift Co",
    "wof:placetype":"venue"
},
  "geometry": {"coordinates":[-73.666248,40.599457],"type":"Point"}
}