{
  "type": "Feature",
  "properties": {
    "addr:full":"4009 Drexel Dr Vestal NY 13850",
    "addr:housenumber":"4009",
    "addr:postcode":"13850",
    "addr:street":"Drexel Dr",
    "iso:country":"US",
    "sg:address":"4009 Drexel Dr",
    "sg:city":"Vestal",
    "sg:classifiers":[
        {
            "category":"Organizations",
            "subcategory":"Membership Organization",
            "type":"Services"
        }
    ],
    "sg:phone":"+1 607 722 6005",
    "sg:postcode":"13850",
    "sg:province":"NY",
    "sg:tags":[
        "club",
        "private"
    ],
    "wof:name":"Vaaland Club",
    "wof:placetype":"venue"
},
  "geometry": {"coordinates":[-75.966095,42.064459],"type":"Point"}
}