{
  "type": "Feature",
  "properties": {
    "iso:country":"US",
    "sg:address":"1930 State Hwy 300",
    "sg:city":"Newburgh",
    "sg:classifiers":[
        {
            "category":"Wholesale",
            "subcategory":"Electrical",
            "type":"Manufacturing & Wholesale Goods"
        }
    ],
    "sg:phone":"+1 845 742 8797",
    "sg:postcode":"12550",
    "sg:province":"NY",
    "sg:tags":[
        "control",
        "security",
        "system"
    ],
    "wof:name":"Your Eyes Security Solutions",
    "wof:placetype":"venue"
},
  "geometry": {"coordinates":[-74.095052,41.574363],"type":"Point"}
}