{
  "type": "Feature",
  "properties": {
    "iso:country":"US",
    "sg:address":"8 Wade Rd",
    "sg:city":"Latham",
    "sg:classifiers":[
        {
            "category":"Social Services",
            "type":"Services"
        }
    ],
    "sg:phone":"+1 518 782 9833",
    "sg:postcode":"12110",
    "sg:province":"NY",
    "sg:tags":[
        "organization",
        "welfare"
    ],
    "wof:name":"Gilda's Club Capital Region Ny",
    "wof:placetype":"venue"
},
  "geometry": {"coordinates":[-73.776994,42.755648],"type":"Point"}
}