{
  "type": "Feature",
  "properties": {
    "iso:country":"US",
    "sg:address":"1908 Ridge Rd W",
    "sg:city":"Rochester",
    "sg:classifiers":[
        {
            "category":"Retail",
            "subcategory":"Veterinary Services",
            "type":"Services"
        }
    ],
    "sg:phone":"+1 585 227 4990",
    "sg:postcode":"14615",
    "sg:province":"NY",
    "sg:tags":[
        "veterinarian",
        "specialty"
    ],
    "wof:name":"Linda A Banks Dvm",
    "wof:placetype":"venue"
},
  "geometry": {"coordinates":[-77.678935,43.207093],"type":"Point"}
}