{
  "type": "Feature",
  "properties": {
    "addr:full":"200 Rustic Rd Ronkonkoma NY 11779",
    "addr:housenumber":"200",
    "addr:postcode":"11779",
    "addr:street":"Rustic Rd",
    "iso:country":"US",
    "sg:address":"200 Rustic Rd",
    "sg:city":"Ronkonkoma",
    "sg:classifiers":[
        {
            "category":"Building & Trades",
            "subcategory":"Construction",
            "type":"Services"
        }
    ],
    "sg:phone":"+1 631 588 5775",
    "sg:postcode":"11779",
    "sg:province":"NY",
    "sg:tags":[
        "general",
        "contractor"
    ],
    "wof:name":"Richard P Martin & Son Constru",
    "wof:placetype":"venue"
},
  "geometry": {"coordinates":[-73.090981,40.842983],"type":"Point"}
}