{
  "type": "Feature",
  "properties": {
    "addr:full":"1967 Wehrle Dr Williamsville NY 14221",
    "addr:housenumber":"1967",
    "addr:postcode":"14221",
    "addr:street":"Wehrle Dr",
    "iso:country":"US",
    "sg:address":"1967 Wehrle Dr",
    "sg:city":"Williamsville",
    "sg:classifiers":[
        {
            "category":"Wholesale",
            "subcategory":"Office Equipment",
            "type":"Manufacturing & Wholesale Goods"
        }
    ],
    "sg:phone":"+1 716 634 5814",
    "sg:postcode":"14221",
    "sg:province":"NY",
    "sg:tags":[
        "bank",
        "supply"
    ],
    "wof:name":"International Transaction Sys",
    "wof:placetype":"venue"
},
  "geometry": {"coordinates":[-78.72204000000001,42.95657],"type":"Point"}
}