{
  "type": "Feature",
  "properties": {
    "iso:country":"US",
    "sg:address":"15 Paradise Rd",
    "sg:city":"Cuddebackville",
    "sg:classifiers":[
        {
            "category":"Building & Trades",
            "subcategory":"Construction",
            "type":"Services"
        }
    ],
    "sg:phone":"+1 845 754 8609",
    "sg:postcode":"12729",
    "sg:province":"NY",
    "sg:tags":[
        "house"
    ],
    "wof:name":"Galligan Construction",
    "wof:placetype":"venue"
},
  "geometry": {"coordinates":[-74.645814,41.496653],"type":"Point"}
}