{
  "type": "Feature",
  "properties": {
    "addr:full":"274 Troutman Street Brooklyn NY 11237",
    "addr:housenumber":"274",
    "addr:postcode":"11237",
    "addr:street":"Troutman Street",
    "iso:country":"US",
    "sg:address":"274 Troutman Street",
    "sg:city":"Brooklyn",
    "sg:classifiers":[
        {
            "category":"Restaurant",
            "type":"Food & Drink"
        }
    ],
    "sg:phone":"+1 718 386 8787",
    "sg:postcode":"11237",
    "sg:province":"NY",
    "sg:tags":[
        "chinese"
    ],
    "wof:name":"Fei Wok Chinese Restaurant",
    "wof:placetype":"venue"
},
  "geometry": {"coordinates":[-73.91752099999999,40.701279],"type":"Point"}
}