{
  "type": "Feature",
  "properties": {
    "iso:country":"US",
    "sg:address":"1205 Erie Blvd W",
    "sg:city":"Syracuse",
    "sg:classifiers":[
        {
            "category":"Restaurant",
            "type":"Food & Drink"
        }
    ],
    "sg:menulink":"http://www.allmenus.com/ny/syracuse/256085-patsys-pizza/menu/",
    "sg:phone":"+1 315 472 4626",
    "sg:postcode":"13204",
    "sg:province":"NY",
    "sg:tags":[
        "american",
        "pizza"
    ],
    "wof:name":"Patsy's Pizza",
    "wof:placetype":"venue"
},
  "geometry": {"coordinates":[-76.178726,43.049723],"type":"Point"}
}