{
  "type": "Feature",
  "properties": {
    "addr:full":"2430 E Tremont Ave Bronx NY 10461",
    "addr:housenumber":"2430",
    "addr:postcode":"10461",
    "addr:street":"E Tremont Ave",
    "iso:country":"US",
    "sg:address":"2430 E Tremont Ave",
    "sg:city":"Bronx",
    "sg:classifiers":[
        {
            "category":"Restaurant",
            "type":"Food & Drink"
        }
    ],
    "sg:phone":"+1 718 239 5809",
    "sg:postcode":"10461",
    "sg:province":"NY",
    "sg:tags":[
        "deli",
        "delicatessen"
    ],
    "wof:name":"Mlasa",
    "wof:placetype":"venue"
},
  "geometry": {"coordinates":[-73.852203,40.842499],"type":"Point"}
}