{
  "type": "Feature",
  "properties": {
    "addr:full":"1780 University Ave Bronx NY 10453",
    "addr:housenumber":"1780",
    "addr:postcode":"10453",
    "addr:street":"University Ave",
    "iso:country":"US",
    "sg:address":"1780 University Ave",
    "sg:city":"Bronx",
    "sg:classifiers":[
        {
            "category":"Retail",
            "subcategory":"Repair Shop",
            "type":"Services"
        }
    ],
    "sg:phone":"+1 718 304 8029",
    "sg:postcode":"10453",
    "sg:province":"NY",
    "sg:tags":[
        "lock",
        "locksmith"
    ],
    "wof:name":"123 Locksmith",
    "wof:placetype":"venue"
},
  "geometry": {"coordinates":[-73.91669400000001,40.849353],"type":"Point"}
}