{
  "type": "Feature",
  "properties": {
    "addr:full":"4510 Kissena Boulevard Flushing NY 11355",
    "addr:housenumber":"4510",
    "addr:postcode":"11355",
    "addr:street":"Kissena Boulevard",
    "iso:country":"US",
    "sg:address":"4510 Kissena Boulevard",
    "sg:city":"Flushing",
    "sg:classifiers":[
        {
            "category":"Health Services",
            "subcategory":"Dentist",
            "type":"Services"
        }
    ],
    "sg:phone":"+1 718 461 7106",
    "sg:postcode":"11355",
    "sg:province":"NY",
    "wof:name":"Queen Alan N DDS",
    "wof:placetype":"venue"
},
  "geometry": {"coordinates":[-73.820623,40.752026],"type":"Point"}
}