{
  "type": "Feature",
  "properties": {
    "iso:country":"US",
    "sg:address":"777 Sunrise Hwy Ste 204",
    "sg:city":"Lynbrook",
    "sg:classifiers":[
        {
            "category":"Professional",
            "subcategory":"Employment Agencies",
            "type":"Services"
        },
        {
            "category":"Professional",
            "subcategory":"Business Services",
            "type":"Services"
        }
    ],
    "sg:phone":"+1 212 329 2400",
    "sg:postcode":"11563",
    "sg:province":"NY",
    "sg:tags":[
        "consultant",
        "broker",
        "custom"
    ],
    "wof:name":"Charles Happel Inc",
    "wof:placetype":"venue"
},
  "geometry": {"coordinates":[-73.67971799999999,40.656215],"type":"Point"}
}