{
  "type": "Feature",
  "properties": {
    "addr:full":"8275 Broadway Elmhurst NY 11373",
    "addr:housenumber":"8275",
    "addr:postcode":"11373",
    "addr:street":"Broadway",
    "iso:country":"US",
    "sg:address":"8275 Broadway",
    "sg:city":"Elmhurst",
    "sg:classifiers":[
        {
            "category":"Retail",
            "subcategory":"Laundry & Dry Cleaning",
            "type":"Services"
        }
    ],
    "sg:phone":"+1 718 446 5339",
    "sg:postcode":"11373",
    "sg:province":"NY",
    "wof:name":"Eric's Dry Cleaners",
    "wof:placetype":"venue"
},
  "geometry": {"coordinates":[-73.8806,40.741699],"type":"Point"}
}