{
  "type": "Feature",
  "properties": {
    "iso:country":"US",
    "sg:address":"70 Fairmont Ave",
    "sg:city":"Medford",
    "sg:classifiers":[
        {
            "category":"Social Services",
            "type":"Services"
        }
    ],
    "sg:phone":"+1 631 736 6299",
    "sg:postcode":"11763",
    "sg:province":"NY",
    "sg:tags":[
        "youth",
        "organization",
        "center"
    ],
    "wof:name":"Sachem Teen Ctr",
    "wof:placetype":"venue"
},
  "geometry": {"coordinates":[-73.00403799999999,40.828451],"type":"Point"}
}