{
  "type": "Feature",
  "properties": {
    "addr:full":"360 S Sunrise Rd West Babylon NY 11704",
    "addr:housenumber":"360",
    "addr:postcode":"11704",
    "addr:street":"S Sunrise Rd",
    "iso:country":"US",
    "sg:address":"360 S Sunrise Rd",
    "sg:city":"West Babylon",
    "sg:classifiers":[
        {
            "category":"Real Estate",
            "subcategory":"Architect",
            "type":"Services"
        }
    ],
    "sg:phone":"+1 631 321 4050",
    "sg:postcode":"11704",
    "sg:province":"NY",
    "wof:name":"Joseph C Corridore Architect",
    "wof:placetype":"venue"
},
  "geometry": {"coordinates":[-73.363516,40.712549],"type":"Point"}
}