{
  "type": "Feature",
  "properties": {
    "iso:country":"US",
    "sg:address":"3399 S Winton Rd",
    "sg:city":"Rochester",
    "sg:classifiers":[
        {
            "category":"Health Services",
            "subcategory":"Health Practitioner",
            "type":"Services"
        }
    ],
    "sg:phone":"+1 585 334 4563",
    "sg:postcode":"14623",
    "sg:province":"NY",
    "sg:tags":[
        "therapist",
        "physical"
    ],
    "wof:name":"Individual Health Svc",
    "wof:placetype":"venue"
},
  "geometry": {"coordinates":[-77.58193300000001,43.085436],"type":"Point"}
}