{
  "type": "Feature",
  "properties": {
    "iso:country":"US",
    "sg:address":"89 Joline Ave",
    "sg:city":"Staten Island",
    "sg:classifiers":[
        {
            "category":"Real Estate",
            "subcategory":"Real Estate Agent",
            "type":"Services"
        }
    ],
    "sg:phone":"+1 718 967 6500",
    "sg:postcode":"10307",
    "sg:province":"NY",
    "sg:tags":[
        "broker",
        "mortgage"
    ],
    "wof:name":"A J Licausi",
    "wof:placetype":"venue"
},
  "geometry": {"coordinates":[-74.236553,40.511699],"type":"Point"}
}