{
  "type": "Feature",
  "properties": {
    "addr:full":"165 Rand St Rochester NY 14615",
    "addr:housenumber":"165",
    "addr:postcode":"14615",
    "addr:street":"Rand St",
    "iso:country":"US",
    "sg:address":"165 Rand St",
    "sg:city":"Rochester",
    "sg:classifiers":[
        {
            "category":"Organizations",
            "subcategory":"Religious Organization",
            "type":"Services"
        }
    ],
    "sg:phone":"+1 585 458 1261",
    "sg:postcode":"14615",
    "sg:province":"NY",
    "sg:tags":[
        "clergy"
    ],
    "wof:name":"James E Jackson",
    "wof:placetype":"venue"
},
  "geometry": {"coordinates":[-77.641751,43.197762],"type":"Point"}
}