{
  "type": "Feature",
  "properties": {
    "iso:country":"US",
    "sg:address":"160 Skyline Dr",
    "sg:city":"Coram",
    "sg:classifiers":[
        {
            "category":"Shopping",
            "subcategory":"Gifts & Souvenirs",
            "type":"Retail Goods"
        }
    ],
    "sg:phone":"+1   ",
    "sg:postcode":"11727",
    "sg:province":"NY",
    "wof:name":"By Candlelight",
    "wof:placetype":"venue"
},
  "geometry": {"coordinates":[-73.015264,40.861524],"type":"Point"}
}