{
  "type": "Feature",
  "properties": {
    "addr:full":"171 W 80 St New York NY 10024",
    "addr:housenumber":"171",
    "addr:postcode":"10024",
    "addr:street":"W 80 St",
    "iso:country":"US",
    "sg:address":"171 W 80 St",
    "sg:city":"New York",
    "sg:classifiers":[
        {
            "category":"Personal",
            "subcategory":"Beauty Salon",
            "type":"Services"
        }
    ],
    "sg:phone":"+1 212 875 8518",
    "sg:postcode":"10024",
    "sg:province":"NY",
    "sg:tags":[
        "shop"
    ],
    "wof:name":"Kathe & Bernard Hair Salon",
    "wof:placetype":"venue"
},
  "geometry": {"coordinates":[-73.977329,40.783721],"type":"Point"}
}