{
  "type": "Feature",
  "properties": {
    "addr:full":"21 Erin Ct Cornwall NY 12518",
    "addr:housenumber":"21",
    "addr:postcode":"12518",
    "addr:street":"Erin Ct",
    "iso:country":"US",
    "sg:address":"21 Erin Ct",
    "sg:city":"Cornwall",
    "sg:classifiers":[
        {
            "category":"Professional",
            "subcategory":"Management & Consulting",
            "type":"Services"
        }
    ],
    "sg:phone":"+1 845 534 7653",
    "sg:postcode":"12518",
    "sg:province":"NY",
    "sg:tags":[
        "environmental",
        "consultant"
    ],
    "wof:name":"American Resource Recycling",
    "wof:placetype":"venue"
},
  "geometry": {"coordinates":[-74.05166,41.416744],"type":"Point"}
}