{
  "type": "Feature",
  "properties": {
    "iso:country":"US",
    "sg:address":"20 White Gate Rd",
    "sg:city":"Wappingers Falls",
    "sg:classifiers":[
        {
            "category":"Building & Trades",
            "subcategory":"Plumbing",
            "type":"Services"
        }
    ],
    "sg:phone":"+1 845 296 0206",
    "sg:postcode":"12590",
    "sg:province":"NY",
    "sg:tags":[
        "contractor"
    ],
    "wof:name":"Community Plumbing & Heating",
    "wof:placetype":"venue"
},
  "geometry": {"coordinates":[-73.900408,41.577099],"type":"Point"}
}