{
  "type": "Feature",
  "properties": {
    "iso:country":"US",
    "sg:address":"530 Main St",
    "sg:city":"East Aurora",
    "sg:classifiers":[
        {
            "category":"Retail",
            "subcategory":"Car Wash",
            "type":"Services"
        }
    ],
    "sg:phone":"+1 716 652 4654",
    "sg:postcode":"14052",
    "sg:province":"NY",
    "sg:tags":[
        "truck",
        "cleaning"
    ],
    "wof:name":"Allied Mobile Power Wash",
    "wof:placetype":"venue"
},
  "geometry": {"coordinates":[-78.61779199999999,42.768014],"type":"Point"}
}