{
  "type": "Feature",
  "properties": {
    "iso:country":"US",
    "sg:address":"1655 Whitehaven Rd",
    "sg:city":"Grand Island",
    "sg:classifiers":[
        {
            "category":"Building & Trades",
            "subcategory":"Construction",
            "type":"Services"
        }
    ],
    "sg:phone":"+1 716 773 4161",
    "sg:postcode":"14072",
    "sg:province":"NY",
    "sg:tags":[
        "house",
        "builder",
        "home"
    ],
    "wof:name":"J R Building & Remodeling Co",
    "wof:placetype":"venue"
},
  "geometry": {"coordinates":[-78.95159700000001,43.021925],"type":"Point"}
}