{
  "type": "Feature",
  "properties": {
    "addr:full":"8201 19th Ave Brooklyn NY 11214",
    "addr:housenumber":"8201",
    "addr:postcode":"11214",
    "addr:street":"19Th Ave",
    "iso:country":"US",
    "sg:address":"8201 19th Ave",
    "sg:city":"Brooklyn",
    "sg:classifiers":[
        {
            "category":"Shopping",
            "subcategory":"Florist",
            "type":"Retail Goods"
        }
    ],
    "sg:phone":"+1 718 232 4854",
    "sg:postcode":"11214",
    "sg:province":"NY",
    "wof:name":"Yellow Stone Flowers Inc",
    "wof:placetype":"venue"
},
  "geometry": {"coordinates":[-73.998667,40.607656],"type":"Point"}
}