{
  "type": "Feature",
  "properties": {
    "iso:country":"US",
    "sg:address":"223 W 1st St",
    "sg:city":"Mount Vernon",
    "sg:classifiers":[
        {
            "category":"Food & Beverages",
            "subcategory":"Groceries & Convenience Stores",
            "type":"Retail Goods"
        }
    ],
    "sg:phone":"+1 914 665 3737",
    "sg:postcode":"10550",
    "sg:province":"NY",
    "sg:tags":[
        "grocer"
    ],
    "wof:name":"Caribbean Supermarket",
    "wof:placetype":"venue"
},
  "geometry": {"coordinates":[-73.84663399999999,40.90904],"type":"Point"}
}