{
  "type": "Feature",
  "properties": {
    "addr:full":"1016 Edison Avenue Bronx NY 10465",
    "addr:housenumber":"1016",
    "addr:postcode":"10465",
    "addr:street":"Edison Avenue",
    "iso:country":"US",
    "sg:address":"1016 Edison Avenue",
    "sg:city":"Bronx",
    "sg:classifiers":[
        {
            "category":"Education",
            "subcategory":"School",
            "type":"Public Place"
        }
    ],
    "sg:phone":"+1 718 829 9557",
    "sg:postcode":"10465",
    "sg:province":"NY",
    "wof:name":"St Benedict's School",
    "wof:placetype":"venue"
},
  "geometry": {"coordinates":[-73.825395,40.832182],"type":"Point"}
}