{
  "type": "Feature",
  "properties": {
    "addr:full":"207 N Brewster Rd Brewster NY 10509",
    "addr:housenumber":"207",
    "addr:postcode":"10509",
    "addr:street":"N Brewster Rd",
    "iso:country":"US",
    "sg:address":"207 N Brewster Rd",
    "sg:city":"Brewster",
    "sg:classifiers":[
        {
            "category":"Health Services",
            "subcategory":"Chiropractor",
            "type":"Services"
        }
    ],
    "sg:phone":"+1 845 278 7700",
    "sg:postcode":"10509",
    "sg:province":"NY",
    "wof:name":"Complete Chiropractic Care",
    "wof:placetype":"venue"
},
  "geometry": {"coordinates":[-73.608501,41.432364],"type":"Point"}
}