{
  "type": "Feature",
  "properties": {
    "iso:country":"US",
    "sg:address":"287 Hewes St",
    "sg:city":"Brooklyn",
    "sg:classifiers":[
        {
            "category":"Organizations",
            "subcategory":"Religious Organization",
            "type":"Services"
        }
    ],
    "sg:phone":"+1 718 388 6149",
    "sg:postcode":"11211",
    "sg:province":"NY",
    "sg:tags":[
        "clergy"
    ],
    "wof:name":"Isaac Eichenstein",
    "wof:placetype":"venue"
},
  "geometry": {"coordinates":[-73.95475999999999,40.705385],"type":"Point"}
}