{
  "type": "Feature",
  "properties": {
    "iso:country":"US",
    "sg:address":"900 Rte 109",
    "sg:city":"Lindenhurst",
    "sg:classifiers":[
        {
            "category":"Food & Beverages",
            "subcategory":"Groceries & Convenience Stores",
            "type":"Retail Goods"
        }
    ],
    "sg:phone":"+1   ",
    "sg:postcode":"11757",
    "sg:province":"NY",
    "sg:tags":[
        "deli",
        "italian"
    ],
    "wof:name":"Giovan Italian Deli",
    "wof:placetype":"venue"
},
  "geometry": {"coordinates":[-73.39006999999999,40.715331],"type":"Point"}
}