{
  "type": "Feature",
  "properties": {
    "iso:country":"US",
    "sg:address":"406 River Rd",
    "sg:city":"Shirley",
    "sg:classifiers":[
        {
            "category":"Shopping",
            "type":"Retail Goods"
        }
    ],
    "sg:phone":"+1 631 281 0141",
    "sg:postcode":"11967",
    "sg:province":"NY",
    "sg:tags":[
        "wedding",
        "supply"
    ],
    "wof:name":"Majestic Limousine",
    "wof:placetype":"venue"
},
  "geometry": {"coordinates":[-72.891696,40.826933],"type":"Point"}
}