{
  "type": "Feature",
  "properties": {
    "addr:full":"1706 Nelson Ave Bronx NY 10453",
    "addr:housenumber":"1706",
    "addr:postcode":"10453",
    "addr:street":"Nelson Ave",
    "iso:country":"US",
    "sg:address":"1706 Nelson Ave",
    "sg:city":"Bronx",
    "sg:classifiers":[
        {
            "category":"Real Estate",
            "subcategory":"Real Estate Agent",
            "type":"Services"
        }
    ],
    "sg:phone":"+1 718 731 1852",
    "sg:postcode":"10453",
    "sg:province":"NY",
    "wof:name":"1706 Realty",
    "wof:placetype":"venue"
},
  "geometry": {"coordinates":[-73.91663,40.848279],"type":"Point"}
}