{
  "type": "Feature",
  "properties": {
    "addr:full":"59 W 19th St Suite 3C New York NY 10011",
    "addr:housenumber":"59",
    "addr:postcode":"10011",
    "addr:street":"W 19Th St Suite 3C",
    "iso:country":"US",
    "sg:address":"59 W 19th St Suite 3C",
    "sg:city":"New York",
    "sg:classifiers":[
        {
            "category":"Sports & Exercise",
            "subcategory":"Gym",
            "type":"Entertainment"
        }
    ],
    "sg:phone":"+1 212 414 2903",
    "sg:postcode":"10011",
    "sg:province":"NY",
    "sg:tags":[
        "yoga"
    ],
    "sg:website":"www.laughinglotus.com",
    "wof:name":"Laughing Lotus Yoga",
    "wof:placetype":"venue"
},
  "geometry": {"coordinates":[-73.99397999999999,40.740175],"type":"Point"}
}