{
  "type": "Feature",
  "properties": {
    "addr:full":"33 Nectarine Ln Liverpool NY 13090",
    "addr:housenumber":"33",
    "addr:postcode":"13090",
    "addr:street":"Nectarine Ln",
    "iso:country":"US",
    "sg:address":"33 Nectarine Ln",
    "sg:city":"Liverpool",
    "sg:classifiers":[
        {
            "category":"Building & Trades",
            "subcategory":"Construction",
            "type":"Services"
        }
    ],
    "sg:phone":"+1 315 622 0572",
    "sg:postcode":"13090",
    "sg:province":"NY",
    "sg:tags":[
        "general",
        "contractor"
    ],
    "wof:name":"Bcb Construction",
    "wof:placetype":"venue"
},
  "geometry": {"coordinates":[-76.21057,43.143419],"type":"Point"}
}