{
  "type": "Feature",
  "properties": {
    "iso:country":"US",
    "sg:address":"500 Clinton Ave",
    "sg:city":"Rockville Centre",
    "sg:classifiers":[
        {
            "category":"Organizations",
            "subcategory":"Religious Organization",
            "type":"Services"
        }
    ],
    "sg:phone":"+1 516 763 4786",
    "sg:postcode":"11570",
    "sg:province":"NY",
    "sg:tags":[
        "clergy"
    ],
    "wof:name":"Arthur W Davenport",
    "wof:placetype":"venue"
},
  "geometry": {"coordinates":[-73.657904,40.671551],"type":"Point"}
}