{
  "type": "Feature",
  "properties": {
    "iso:country":"US",
    "sg:address":"1457 Broadway",
    "sg:city":"New York",
    "sg:classifiers":[
        {
            "category":"Real Estate",
            "subcategory":"Real Estate Services",
            "type":"Services"
        }
    ],
    "sg:phone":"+1 212 947 8184",
    "sg:postcode":"10036",
    "sg:province":"NY",
    "sg:tags":[
        "home",
        "inspector"
    ],
    "wof:name":"Tauscher Arthur Professional Engineer PC",
    "wof:placetype":"venue"
},
  "geometry": {"coordinates":[-73.986603,40.755402],"type":"Point"}
}