{
  "type": "Feature",
  "properties": {
    "iso:country":"US",
    "sg:address":"861 E 27th St",
    "sg:city":"Brooklyn",
    "sg:classifiers":[
        {
            "category":"Shopping",
            "subcategory":"Clothing, Apparel, & Fashions",
            "type":"Retail Goods"
        }
    ],
    "sg:phone":"+1   ",
    "sg:postcode":"11210",
    "sg:province":"NY",
    "sg:tags":[
        "wear"
    ],
    "wof:name":"Customs Kids",
    "wof:placetype":"venue"
},
  "geometry": {"coordinates":[-73.95021300000001,40.629611],"type":"Point"}
}