{
  "type": "Feature",
  "properties": {
    "addr:full":"1881 Victory Blvd Staten Island NY 10314",
    "addr:housenumber":"1881",
    "addr:postcode":"10314",
    "addr:street":"Victory Blvd",
    "iso:country":"US",
    "sg:address":"1881 Victory Blvd",
    "sg:city":"Staten Island",
    "sg:classifiers":[
        {
            "category":"Shopping",
            "type":"Retail Goods"
        }
    ],
    "sg:phone":"+1 718 816 8040",
    "sg:postcode":"10314",
    "sg:province":"NY",
    "sg:tags":[
        "telephone",
        "cellular"
    ],
    "wof:name":"Wireless RUS Inc",
    "wof:placetype":"venue"
},
  "geometry": {"coordinates":[-74.12553800000001,40.61299],"type":"Point"}
}