{
  "type": "Feature",
  "properties": {
    "addr:full":"180 Denton Ave Lynbrook NY 11563",
    "addr:housenumber":"180",
    "addr:postcode":"11563",
    "addr:street":"Denton Ave",
    "iso:country":"US",
    "sg:address":"180 Denton Ave",
    "sg:city":"Lynbrook",
    "sg:classifiers":[
        {
            "category":"Organizations",
            "subcategory":"Religious Organization",
            "type":"Services"
        }
    ],
    "sg:phone":"+1 516 599 4435",
    "sg:postcode":"11563",
    "sg:province":"NY",
    "sg:tags":[
        "place",
        "worship",
        "church"
    ],
    "sg:website":"http://www.lefc.net",
    "wof:name":"Trinity Evangelical Free Ch",
    "wof:placetype":"venue"
},
  "geometry": {"coordinates":[-73.66603000000001,40.657301],"type":"Point"}
}