{
  "type": "Feature",
  "properties": {
    "iso:country":"US",
    "sg:address":"1135 Old Country Rd",
    "sg:city":"Plainview",
    "sg:classifiers":[
        {
            "category":"Restaurant",
            "type":"Food & Drink"
        }
    ],
    "sg:phone":"+1   ",
    "sg:postcode":"11803",
    "sg:province":"NY",
    "wof:name":"Aegean Greek American Cuisine",
    "wof:placetype":"venue"
},
  "geometry": {"coordinates":[-73.466093,40.776308],"type":"Point"}
}