{
  "type": "Feature",
  "properties": {
    "addr:full":"100 W Shore Rd Huntington NY 11743",
    "addr:housenumber":"100",
    "addr:postcode":"11743",
    "addr:street":"W Shore Rd",
    "iso:country":"US",
    "sg:address":"100 W Shore Rd",
    "sg:city":"Huntington",
    "sg:classifiers":[
        {
            "category":"Retail",
            "subcategory":"Repair Shop",
            "type":"Services"
        }
    ],
    "sg:phone":"+1 631 223 0419",
    "sg:postcode":"11743",
    "sg:province":"NY",
    "sg:tags":[
        "lock",
        "locksmith"
    ],
    "wof:name":"Locksmith 24 Hour",
    "wof:placetype":"venue"
},
  "geometry": {"coordinates":[-73.42367900000001,40.891427],"type":"Point"}
}