{
  "type": "Feature",
  "properties": {
    "addr:full":"45 W 46th Street Fl 5 New York NY 10036",
    "addr:housenumber":"45;5",
    "addr:postcode":"10036",
    "addr:street":"W 46Th Street",
    "iso:country":"US",
    "sg:address":"45 W 46th Street Fl 5",
    "sg:city":"New York",
    "sg:classifiers":[
        {
            "category":"Shopping",
            "subcategory":"Jewelry",
            "type":"Retail Goods"
        }
    ],
    "sg:phone":"+1 212 944 2606",
    "sg:postcode":"10036",
    "sg:province":"NY",
    "wof:name":"Jewelry Pak",
    "wof:placetype":"venue"
},
  "geometry": {"coordinates":[-73.980442,40.756627],"type":"Point"}
}