{
  "type": "Feature",
  "properties": {
    "iso:country":"US",
    "sg:address":"240 7th Ave",
    "sg:city":"Brooklyn",
    "sg:classifiers":[
        {
            "category":"Shopping",
            "subcategory":"Clothing, Apparel, & Fashions",
            "type":"Retail Goods"
        }
    ],
    "sg:phone":"+1 718 965 3535",
    "sg:postcode":"11215",
    "sg:province":"NY",
    "sg:tags":[
        "children's",
        "clothing"
    ],
    "sg:website":"www.fireflychildrensboutique.com",
    "wof:name":"Firefly Childrens Boutique",
    "wof:placetype":"venue"
},
  "geometry": {"coordinates":[-73.979303,40.669653],"type":"Point"}
}