{
  "type": "Feature",
  "properties": {
    "addr:full":"152 Lincoln Rd Brooklyn NY 11225",
    "addr:housenumber":"152",
    "addr:postcode":"11225",
    "addr:street":"Lincoln Rd",
    "iso:country":"US",
    "sg:address":"152 Lincoln Rd",
    "sg:city":"Brooklyn",
    "sg:classifiers":[
        {
            "category":"Health Services",
            "subcategory":"Doctor",
            "type":"Services"
        }
    ],
    "sg:phone":"+1   ",
    "sg:postcode":"11225",
    "sg:province":"NY",
    "sg:tags":[
        "medical"
    ],
    "wof:name":"Frederick Lue MD",
    "wof:placetype":"venue"
},
  "geometry": {"coordinates":[-73.95926900000001,40.660913],"type":"Point"}
}