{
  "type": "Feature",
  "properties": {
    "iso:country":"US",
    "sg:address":"1101 Kings Hwy",
    "sg:city":"Brooklyn",
    "sg:classifiers":[
        {
            "category":"Shopping",
            "subcategory":"Mobile Phones",
            "type":"Retail Goods"
        }
    ],
    "sg:phone":"+1 718 787 0142",
    "sg:postcode":"11229",
    "sg:province":"NY",
    "sg:website":"www.wireless.att.com",
    "wof:name":"AT&T",
    "wof:placetype":"venue"
},
  "geometry": {"coordinates":[-73.961873,40.607478],"type":"Point"}
}