{
  "type": "Feature",
  "properties": {
    "addr:full":"9512 Shanagarry Dr Baldwinsville NY 13027",
    "addr:postcode":"9512;13027",
    "addr:street":"Shanagarry Dr",
    "iso:country":"US",
    "sg:address":"9512 Shanagarry Dr",
    "sg:city":"Baldwinsville",
    "sg:classifiers":[
        {
            "category":"Building & Trades",
            "subcategory":"Construction",
            "type":"Services"
        }
    ],
    "sg:phone":"+1 315 635 8555",
    "sg:postcode":"13027",
    "sg:province":"NY",
    "sg:tags":[
        "contractor"
    ],
    "wof:name":"Magnolia Designs",
    "wof:placetype":"venue"
},
  "geometry": {"coordinates":[-76.299328,43.149725],"type":"Point"}
}