{
  "type": "Feature",
  "properties": {
    "addr:full":"12 Fletcher Ct Spring Valley NY 10977",
    "addr:housenumber":"12",
    "addr:postcode":"10977",
    "addr:street":"Fletcher Ct",
    "iso:country":"US",
    "sg:address":"12 Fletcher Ct",
    "sg:city":"Spring Valley",
    "sg:classifiers":[
        {
            "category":"Building & Trades",
            "subcategory":"Construction",
            "type":"Services"
        }
    ],
    "sg:phone":"+1 845 425 2048",
    "sg:postcode":"10977",
    "sg:province":"NY",
    "sg:tags":[
        "hanging",
        "contractor"
    ],
    "wof:name":"Suddenly Beautiful Painting",
    "wof:placetype":"venue"
},
  "geometry": {"coordinates":[-74.032099,41.137059],"type":"Point"}
}