{
  "type": "Feature",
  "properties": {
    "addr:full":"34 Main St Mt Morris NY 14510",
    "addr:housenumber":"34",
    "addr:postcode":"14510",
    "addr:street":"Main St",
    "iso:country":"US",
    "sg:address":"34 Main St",
    "sg:city":"Mt Morris",
    "sg:classifiers":[
        {
            "category":"Bars & Pubs",
            "type":"Food & Drink"
        }
    ],
    "sg:phone":"+1 585 658 4155",
    "sg:postcode":"14510",
    "sg:province":"NY",
    "wof:name":"EFAC Inc",
    "wof:placetype":"venue"
},
  "geometry": {"coordinates":[-77.874574,42.72636],"type":"Point"}
}