{
  "type": "Feature",
  "properties": {
    "iso:country":"US",
    "sg:address":"134 W Post Rd",
    "sg:city":"White Plains",
    "sg:classifiers":[
        {
            "category":"Restaurant",
            "type":"Food & Drink"
        }
    ],
    "sg:phone":"+1 914 761 4151",
    "sg:postcode":"10606",
    "sg:province":"NY",
    "sg:tags":[
        "eating",
        "out"
    ],
    "wof:name":"Young's Chinese Kitchen",
    "wof:placetype":"venue"
},
  "geometry": {"coordinates":[-73.775233,41.022221],"type":"Point"}
}