{
  "type": "Feature",
  "properties": {
    "addr:full":"61 Mount Sinai Coram Rd Coram NY 11727",
    "addr:housenumber":"61",
    "addr:postcode":"11727",
    "addr:street":"Mount;Coram Rd",
    "iso:country":"US",
    "sg:address":"61 Mount Sinai Coram Rd",
    "sg:city":"Coram",
    "sg:classifiers":[
        {
            "category":"Education",
            "subcategory":"Special Training",
            "type":"Public Place"
        }
    ],
    "sg:phone":"+1 631 698 1854",
    "sg:postcode":"11727",
    "sg:province":"NY",
    "sg:tags":[
        "educational"
    ],
    "wof:name":"Board Of Co-Op Educational Svc",
    "wof:placetype":"venue"
},
  "geometry": {"coordinates":[-72.99473399999999,40.877234],"type":"Point"}
}