{
  "type": "Feature",
  "properties": {
    "iso:country":"US",
    "sg:address":"1549 45th St",
    "sg:city":"Brooklyn",
    "sg:classifiers":[
        {
            "category":"Travel",
            "subcategory":"Travel Agent",
            "type":"Entertainment"
        }
    ],
    "sg:phone":"+1 718 972 1200",
    "sg:postcode":"11219",
    "sg:province":"NY",
    "sg:tags":[
        "agency",
        "bureau"
    ],
    "wof:name":"SST Tours",
    "wof:placetype":"venue"
},
  "geometry": {"coordinates":[-73.98394999999999,40.633988],"type":"Point"}
}