{
  "type": "Feature",
  "properties": {
    "addr:full":"236 5th Ave New York NY 10001",
    "addr:housenumber":"236",
    "addr:postcode":"10001",
    "addr:street":"5Th Ave",
    "iso:country":"US",
    "sg:address":"236 5th Ave",
    "sg:city":"New York",
    "sg:classifiers":[
        {
            "category":"Professional",
            "type":"Services"
        }
    ],
    "sg:phone":"+1 212 889 1022",
    "sg:postcode":"10001",
    "sg:province":"NY",
    "sg:tags":[
        "establishment"
    ],
    "wof:name":"Lct Associates",
    "wof:placetype":"venue"
},
  "geometry": {"coordinates":[-73.98742,40.744616],"type":"Point"}
}