{
  "type": "Feature",
  "properties": {
    "addr:full":"318 Charlton Rd Ballston Spa NY 12020",
    "addr:housenumber":"318",
    "addr:postcode":"12020",
    "addr:street":"Charlton Rd",
    "iso:country":"US",
    "sg:address":"318 Charlton Rd",
    "sg:city":"Ballston Spa",
    "sg:classifiers":[
        {
            "category":"Building & Trades",
            "subcategory":"Construction",
            "type":"Services"
        }
    ],
    "sg:phone":"+1 518 884 8632",
    "sg:postcode":"12020",
    "sg:province":"NY",
    "sg:tags":[
        "general",
        "contractor"
    ],
    "wof:name":"Capital North Corp",
    "wof:placetype":"venue"
},
  "geometry": {"coordinates":[-73.912436,42.947861],"type":"Point"}
}