{
  "type": "Feature",
  "properties": {
    "addr:full":"83 Mansion St Coxsackie NY 12051",
    "addr:housenumber":"83",
    "addr:postcode":"12051",
    "addr:street":"Mansion St",
    "iso:country":"US",
    "sg:address":"83 Mansion St",
    "sg:city":"Coxsackie",
    "sg:classifiers":[
        {
            "category":"Health Services",
            "subcategory":"Optometrist",
            "type":"Services"
        },
        {
            "category":"Professional",
            "type":"Services"
        }
    ],
    "sg:phone":"+1 518 731 9405",
    "sg:postcode":"12051",
    "sg:province":"NY",
    "sg:tags":[
        "optical",
        "good",
        "lense",
        "contact"
    ],
    "wof:name":"Coxsackie Eye Associates",
    "wof:placetype":"venue"
},
  "geometry": {"coordinates":[-73.80046900000001,42.353068],"type":"Point"}
}