{
  "type": "Feature",
  "properties": {
    "addr:full":"66 Seifert Ln Putnam Valley NY 10579",
    "addr:housenumber":"66",
    "addr:postcode":"10579",
    "addr:street":"Seifert Ln Putnam",
    "iso:country":"US",
    "sg:address":"66 Seifert Ln",
    "sg:city":"Putnam Valley",
    "sg:classifiers":[
        {
            "category":"Building & Trades",
            "subcategory":"Construction",
            "type":"Services"
        }
    ],
    "sg:phone":"+1 914 804 8730",
    "sg:postcode":"10579",
    "sg:province":"NY",
    "sg:tags":[
        "house"
    ],
    "wof:name":"Euro Homes Remodeling Inc",
    "wof:placetype":"venue"
},
  "geometry": {"coordinates":[-73.779725,41.428773],"type":"Point"}
}