{
  "type": "Feature",
  "properties": {
    "iso:country":"US",
    "sg:address":"451 Clarkson Ave",
    "sg:city":"Brooklyn",
    "sg:classifiers":[
        {
            "category":"Building & Trades",
            "subcategory":"Construction",
            "type":"Services"
        }
    ],
    "sg:phone":"+1 718 604 8756",
    "sg:postcode":"11225",
    "sg:province":"NY",
    "sg:tags":[
        "contractor"
    ],
    "wof:name":"Tri-Built Construction",
    "wof:placetype":"venue"
},
  "geometry": {"coordinates":[-73.943468,40.656686],"type":"Point"}
}