{
  "type": "Feature",
  "properties": {
    "addr:full":"38 Eastview Mall Dr Victor NY 14564",
    "addr:housenumber":"38",
    "addr:postcode":"14564",
    "addr:street":"Eastview Mall Dr",
    "iso:country":"US",
    "sg:address":"38 Eastview Mall Dr",
    "sg:city":"Victor",
    "sg:classifiers":[
        {
            "category":"Real Estate",
            "subcategory":"Real Estate Agent",
            "type":"Services"
        }
    ],
    "sg:phone":"+1 585 425 1561",
    "sg:postcode":"14564",
    "sg:province":"NY",
    "sg:tags":[
        "desk",
        "space"
    ],
    "wof:name":"Systems In Place At Eastview",
    "wof:placetype":"venue"
},
  "geometry": {"coordinates":[-77.439284,43.026037],"type":"Point"}
}