{
  "type": "Feature",
  "properties": {
    "addr:full":"82 Wall St Ste 1105 New York NY 10005",
    "addr:housenumber":"82",
    "addr:postcode":"10005",
    "addr:street":"Wall St Ste 1105",
    "iso:country":"US",
    "sg:address":"82 Wall St Ste 1105",
    "sg:city":"New York",
    "sg:classifiers":[
        {
            "category":"Health Services",
            "subcategory":"Clinic",
            "type":"Services"
        }
    ],
    "sg:phone":"+1 212 509 2411",
    "sg:postcode":"10005",
    "sg:province":"NY",
    "sg:tags":[
        "counseling",
        "mental"
    ],
    "wof:name":"Wall St Counseling Center",
    "wof:placetype":"venue"
},
  "geometry": {"coordinates":[-74.007698,40.705502],"type":"Point"}
}