{
  "type": "Feature",
  "properties": {
    "addr:full":"182 Ramapo Rd Garnerville NY 10923",
    "addr:housenumber":"182",
    "addr:postcode":"10923",
    "addr:street":"Ramapo Rd",
    "iso:country":"US",
    "sg:address":"182 Ramapo Rd",
    "sg:city":"Garnerville",
    "sg:classifiers":[
        {
            "category":"Real Estate",
            "subcategory":"Real Estate Operator",
            "type":"Services"
        }
    ],
    "sg:phone":"+1 845 429 4549",
    "sg:postcode":"10923",
    "sg:province":"NY",
    "sg:tags":[
        "apartment"
    ],
    "wof:name":"Hudson Valley Assoc",
    "wof:placetype":"venue"
},
  "geometry": {"coordinates":[-73.988968,41.20118],"type":"Point"}
}