{
  "type": "Feature",
  "properties": {
    "addr:full":"2101 66th Street Brooklyn NY 11204",
    "addr:housenumber":"2101",
    "addr:postcode":"11204",
    "addr:street":"66Th Street",
    "iso:country":"US",
    "sg:address":"2101 66th Street",
    "sg:city":"Brooklyn",
    "sg:classifiers":[
        {
            "category":"Shopping",
            "subcategory":"Stationery & Office Supplies",
            "type":"Retail Goods"
        }
    ],
    "sg:phone":"+1 718 331 9670",
    "sg:postcode":"11204",
    "sg:province":"NY",
    "sg:tags":[
        "equipment"
    ],
    "wof:name":"Genuine Supply",
    "wof:placetype":"venue"
},
  "geometry": {"coordinates":[-73.982321,40.613265],"type":"Point"}
}