{
  "type": "Feature",
  "properties": {
    "iso:country":"US",
    "sg:address":"405 Warren St",
    "sg:city":"Hudson",
    "sg:classifiers":[
        {
            "category":"Personal",
            "subcategory":"Beauty Salon",
            "type":"Services"
        }
    ],
    "sg:phone":"+1 518 828 6602",
    "sg:postcode":"12534",
    "sg:province":"NY",
    "wof:name":"Aprile's House Of Beauty",
    "wof:placetype":"venue"
},
  "geometry": {"coordinates":[-73.788708,42.251027],"type":"Point"}
}