{
  "type": "Feature",
  "properties": {
    "addr:full":"30 W 183rd St Bronx NY 10453",
    "addr:housenumber":"30",
    "addr:postcode":"10453",
    "addr:street":"W 183Rd St",
    "iso:country":"US",
    "sg:address":"30 W 183rd St",
    "sg:city":"Bronx",
    "sg:classifiers":[
        {
            "category":"Restaurant",
            "type":"Food & Drink"
        }
    ],
    "sg:menulink":"http://www.allmenus.com/ny/bronx/62486-hong-kong-restaurant/menu/",
    "sg:phone":"+1 718 562 9059",
    "sg:postcode":"10453",
    "sg:province":"NY",
    "sg:tags":[
        "asian",
        "chinese"
    ],
    "wof:name":"Hong Kong Restaurant",
    "wof:placetype":"venue"
},
  "geometry": {"coordinates":[-73.905112,40.858792],"type":"Point"}
}