{
  "type": "Feature",
  "properties": {
    "addr:full":"520 North Rd Pattersonville NY 12137",
    "addr:housenumber":"520",
    "addr:postcode":"12137",
    "addr:street":"North Rd",
    "iso:country":"US",
    "sg:address":"520 North Rd",
    "sg:city":"Pattersonville",
    "sg:classifiers":[
        {
            "category":"Building & Trades",
            "subcategory":"Construction",
            "type":"Services"
        }
    ],
    "sg:phone":"+1 518 864 7087",
    "sg:postcode":"12137",
    "sg:province":"NY",
    "sg:tags":[
        "floor",
        "laying",
        "contractor"
    ],
    "wof:name":"Thomas Michaelcurly",
    "wof:placetype":"venue"
},
  "geometry": {"coordinates":[-74.174115,42.8236],"type":"Point"}
}