{
  "type": "Feature",
  "properties": {
    "addr:full":"421 E 13 St New York NY 10009",
    "addr:housenumber":"421;13",
    "addr:postcode":"10009",
    "addr:street":"E",
    "iso:country":"US",
    "sg:address":"421 E 13 St",
    "sg:city":"New York",
    "sg:classifiers":[
        {
            "category":"Home & Garden",
            "subcategory":"Building Materials",
            "type":"Retail Goods"
        },
        {
            "category":"Home & Garden",
            "subcategory":"Hardware",
            "type":"Retail Goods"
        }
    ],
    "sg:phone":"+1 212 228 8388",
    "sg:postcode":"10009",
    "sg:province":"NY",
    "sg:tags":[
        "lumber"
    ],
    "wof:name":"East Side Lumber Co",
    "wof:placetype":"venue"
},
  "geometry": {"coordinates":[-73.981165,40.72998],"type":"Point"}
}