{
  "type": "Feature",
  "properties": {
    "addr:full":"250 Fulton Ave Hempstead NY 11550",
    "addr:housenumber":"250",
    "addr:postcode":"11550",
    "addr:street":"Fulton Ave",
    "iso:country":"US",
    "sg:address":"250 Fulton Ave",
    "sg:city":"Hempstead",
    "sg:classifiers":[
        {
            "category":"Health Services",
            "subcategory":"Doctor",
            "type":"Services"
        }
    ],
    "sg:phone":"+1 516 505 1364",
    "sg:postcode":"11550",
    "sg:province":"NY",
    "wof:name":"Industrial Medicine Associates",
    "wof:placetype":"venue"
},
  "geometry": {"coordinates":[-73.630798,40.707001],"type":"Point"}
}