{
  "type": "Feature",
  "properties": {
    "iso:country":"US",
    "sg:address":"2 Naples Hill Rd",
    "sg:city":"Prattsburgh",
    "sg:classifiers":[
        {
            "category":"Education",
            "subcategory":"School",
            "type":"Public Place"
        }
    ],
    "sg:phone":"+1 607 522 6240",
    "sg:postcode":"14873",
    "sg:province":"NY",
    "wof:name":"Prattsburgh Central School",
    "wof:placetype":"venue"
},
  "geometry": {"coordinates":[-77.293385,42.528029],"type":"Point"}
}