{
  "type": "Feature",
  "properties": {
    "iso:country":"US",
    "sg:address":"242 James St",
    "sg:city":"Franklin Square",
    "sg:classifiers":[
        {
            "category":"Wholesale",
            "subcategory":"Non-durable Goods",
            "type":"Manufacturing & Wholesale Goods"
        }
    ],
    "sg:phone":"+1 516 328 0456",
    "sg:postcode":"11010",
    "sg:province":"NY",
    "wof:name":"Lucky 3 Distributors Inc",
    "wof:placetype":"venue"
},
  "geometry": {"coordinates":[-73.674674,40.70206],"type":"Point"}
}