{
  "type": "Feature",
  "properties": {
    "addr:full":"836 Flatbush Ave Brooklyn NY 11226",
    "addr:housenumber":"836",
    "addr:postcode":"11226",
    "addr:street":"Flatbush Ave",
    "iso:country":"US",
    "sg:address":"836 Flatbush Ave",
    "sg:city":"Brooklyn",
    "sg:classifiers":[
        {
            "category":"Shopping",
            "subcategory":"Clothing, Apparel, & Fashions",
            "type":"Retail Goods"
        }
    ],
    "sg:phone":"+1   ",
    "sg:postcode":"11226",
    "sg:province":"NY",
    "wof:name":"Tikvam Army Corp",
    "wof:placetype":"venue"
},
  "geometry": {"coordinates":[-73.959011,40.651265],"type":"Point"}
}