{
  "type": "Feature",
  "properties": {
    "addr:full":"135 7th Ave Brooklyn NY 11215",
    "addr:housenumber":"135",
    "addr:postcode":"11215",
    "addr:street":"7Th Ave",
    "iso:country":"US",
    "sg:address":"135 7th Ave",
    "sg:city":"Brooklyn",
    "sg:classifiers":[
        {
            "category":"Shopping",
            "subcategory":"Gifts & Souvenirs",
            "type":"Retail Goods"
        }
    ],
    "sg:phone":"+1   ",
    "sg:postcode":"11215",
    "sg:province":"NY",
    "sg:tags":[
        "toy",
        "novelty"
    ],
    "wof:name":"Little Things Gift Store",
    "wof:placetype":"venue"
},
  "geometry": {"coordinates":[-73.976843,40.672513],"type":"Point"}
}