{
  "type": "Feature",
  "properties": {
    "iso:country":"US",
    "sg:address":"491 Main St",
    "sg:city":"Northport",
    "sg:classifiers":[
        {
            "category":"Shopping",
            "subcategory":"Clothing, Apparel, & Fashions",
            "type":"Retail Goods"
        }
    ],
    "sg:phone":"+1   ",
    "sg:postcode":"11768",
    "sg:province":"NY",
    "wof:name":"Cow Harbor Kids Ltd",
    "wof:placetype":"venue"
},
  "geometry": {"coordinates":[-73.336563,40.901198],"type":"Point"}
}