{
  "type": "Feature",
  "properties": {
    "iso:country":"US",
    "sg:address":"302 5th Ave",
    "sg:city":"New York",
    "sg:classifiers":[
        {
            "category":"Professional",
            "subcategory":"Business Services",
            "type":"Services"
        }
    ],
    "sg:phone":"+1 212 290 1132",
    "sg:postcode":"10001",
    "sg:province":"NY",
    "sg:tags":[
        "messenger"
    ],
    "wof:name":"Express It",
    "wof:placetype":"venue"
},
  "geometry": {"coordinates":[-73.98559299999999,40.747132],"type":"Point"}
}