{
  "type": "Feature",
  "properties": {
    "iso:country":"US",
    "sg:address":"371 Merrick Rd",
    "sg:city":"Rockville Centre",
    "sg:classifiers":[
        {
            "category":"Health Services",
            "subcategory":"Doctor",
            "type":"Services"
        }
    ],
    "sg:phone":"+1 516 766 7626",
    "sg:postcode":"11570",
    "sg:province":"NY",
    "sg:tags":[
        "medical"
    ],
    "wof:name":"Annette M Baggott",
    "wof:placetype":"venue"
},
  "geometry": {"coordinates":[-73.644021,40.656022],"type":"Point"}
}