{
  "type": "Feature",
  "properties": {
    "addr:full":"1437 1st Ave Manhattan NY 10021",
    "addr:housenumber":"1437",
    "addr:postcode":"10021",
    "addr:street":"1St Ave",
    "iso:country":"US",
    "sg:address":"1437 1st Ave",
    "sg:city":"Manhattan",
    "sg:classifiers":[
        {
            "category":"Restaurant",
            "type":"Food & Drink"
        },
        {
            "category":"Ice Cream",
            "type":"Food & Drink"
        }
    ],
    "sg:phone":"+1 212 772 7222",
    "sg:postcode":"10021",
    "sg:province":"NY",
    "sg:tags":[
        "frozen",
        "yogurt",
        "flavor",
        "local"
    ],
    "sg:website":"www.thelitechoice.com",
    "wof:name":"The Lite Choice",
    "wof:placetype":"venue"
},
  "geometry": {"coordinates":[-73.954785,40.769519],"type":"Point"}
}