{
  "type": "Feature",
  "properties": {
    "addr:full":"4641 White Plains Rd Bronx NY 10470",
    "addr:housenumber":"4641",
    "addr:postcode":"10470",
    "addr:street":"White Plains Rd",
    "iso:country":"US",
    "sg:address":"4641 White Plains Rd",
    "sg:city":"Bronx",
    "sg:classifiers":[
        {
            "category":"Personal",
            "subcategory":"Beauty Salon",
            "type":"Services"
        }
    ],
    "sg:phone":"+1 718 798 5148",
    "sg:postcode":"10470",
    "sg:province":"NY",
    "wof:name":"Charming Hair",
    "wof:placetype":"venue"
},
  "geometry": {"coordinates":[-73.850801,40.902904],"type":"Point"}
}