{
  "type": "Feature",
  "properties": {
    "iso:country":"US",
    "sg:address":"2747 Lee Pl",
    "sg:city":"Bellmore",
    "sg:classifiers":[
        {
            "category":"Manufacturing",
            "subcategory":"Wood Products",
            "type":"Manufacturing & Wholesale Goods"
        }
    ],
    "sg:phone":"+1   ",
    "sg:postcode":"11710",
    "sg:province":"NY",
    "sg:tags":[
        "mfg"
    ],
    "wof:name":"Hyacinth Inc",
    "wof:placetype":"venue"
},
  "geometry": {"coordinates":[-73.526819,40.650942],"type":"Point"}
}