{
  "type": "Feature",
  "properties": {
    "iso:country":"US",
    "sg:address":"147 Woodbury Rd Ste G",
    "sg:city":"Huntington",
    "sg:classifiers":[
        {
            "category":"Shopping",
            "subcategory":"Gifts & Souvenirs",
            "type":"Retail Goods"
        }
    ],
    "sg:phone":"+1 631 470 5678",
    "sg:postcode":"11743",
    "sg:province":"NY",
    "sg:tags":[
        "flower"
    ],
    "wof:name":"Signature Gifts & Mongr",
    "wof:placetype":"venue"
},
  "geometry": {"coordinates":[-73.433302,40.865749],"type":"Point"}
}