{
  "type": "Feature",
  "properties": {
    "addr:full":"95 University Pl New York NY 10003",
    "addr:housenumber":"95",
    "addr:postcode":"10003",
    "addr:street":"University Pl",
    "iso:country":"US",
    "sg:address":"95 University Pl",
    "sg:city":"New York",
    "sg:classifiers":[
        {
            "category":"Health Services",
            "subcategory":"Doctor",
            "type":"Services"
        }
    ],
    "sg:phone":"+1 212 604 1362",
    "sg:postcode":"10003",
    "sg:province":"NY",
    "sg:tags":[
        "physician",
        "surgeon"
    ],
    "wof:name":"Joel Grad MD",
    "wof:placetype":"venue"
},
  "geometry": {"coordinates":[-73.99305,40.733387],"type":"Point"}
}