{
  "type": "Feature",
  "properties": {
    "addr:full":"50 Wallabout St Brooklyn NY 11211",
    "addr:housenumber":"50",
    "addr:postcode":"11211",
    "addr:street":"Wallabout St",
    "iso:country":"US",
    "sg:address":"50 Wallabout St",
    "sg:city":"Brooklyn",
    "sg:classifiers":[
        {
            "category":"Wholesale",
            "subcategory":"Apparel",
            "type":"Manufacturing & Wholesale Goods"
        }
    ],
    "sg:phone":"+1 718 855 7516",
    "sg:postcode":"11211",
    "sg:province":"NY",
    "sg:tags":[
        "sportswear"
    ],
    "wof:name":"Pous Apparel",
    "wof:placetype":"venue"
},
  "geometry": {"coordinates":[-73.960662,40.699065],"type":"Point"}
}