{
  "type": "Feature",
  "properties": {
    "addr:full":"7425 Surbrook Rd Baldwinsville NY 13027",
    "addr:housenumber":"7425",
    "addr:postcode":"13027",
    "addr:street":"Surbrook Rd",
    "iso:country":"US",
    "sg:address":"7425 Surbrook Rd",
    "sg:city":"Baldwinsville",
    "sg:classifiers":[
        {
            "category":"Building & Trades",
            "subcategory":"Construction",
            "type":"Services"
        }
    ],
    "sg:phone":"+1 315 638 1934",
    "sg:postcode":"13027",
    "sg:province":"NY",
    "sg:tags":[
        "house"
    ],
    "wof:name":"Bob Mariano Remodeling",
    "wof:placetype":"venue"
},
  "geometry": {"coordinates":[-76.285425,43.129527],"type":"Point"}
}