{
  "type": "Feature",
  "properties": {
    "addr:full":"112 Center St Canastota NY 13032",
    "addr:housenumber":"112",
    "addr:postcode":"13032",
    "addr:street":"Center St",
    "iso:country":"US",
    "sg:address":"112 Center St",
    "sg:city":"Canastota",
    "sg:classifiers":[
        {
            "category":"Organizations",
            "subcategory":"Membership Organization",
            "type":"Services"
        }
    ],
    "sg:phone":"+1 315 697 3588",
    "sg:postcode":"13032",
    "sg:province":"NY",
    "sg:website":"www.capmadco.org",
    "wof:name":"Community Action Program",
    "wof:placetype":"venue"
},
  "geometry": {"coordinates":[-75.752404,43.078228],"type":"Point"}
}