{
  "type": "Feature",
  "properties": {
    "iso:country":"US",
    "sg:address":"38 Classic St",
    "sg:city":"Sherburne",
    "sg:classifiers":[
        {
            "category":"Health Services",
            "subcategory":"Doctor",
            "type":"Services"
        }
    ],
    "sg:phone":"+1 607 674 4495",
    "sg:postcode":"13460",
    "sg:province":"NY",
    "sg:tags":[
        "clinic"
    ],
    "wof:name":"Cmh Family Health Ctr",
    "wof:placetype":"venue"
},
  "geometry": {"coordinates":[-75.49970399999999,42.688584],"type":"Point"}
}