{
  "type": "Feature",
  "properties": {
    "iso:country":"US",
    "sg:address":"654 Washington Ave",
    "sg:city":"Pleasantville",
    "sg:classifiers":[
        {
            "category":"Professional",
            "subcategory":"Management & Consulting",
            "type":"Services"
        },
        {
            "category":"Banks & Credit Unions",
            "subcategory":"Financial Services",
            "type":"Services"
        }
    ],
    "sg:phone":"+1 914 769 5392",
    "sg:postcode":"10570",
    "sg:province":"NY",
    "sg:tags":[
        "consultant",
        "financing",
        "planning"
    ],
    "wof:name":"Arthur Epstein",
    "wof:placetype":"venue"
},
  "geometry": {"coordinates":[-73.778291,41.153405],"type":"Point"}
}