{
  "type": "Feature",
  "properties": {
    "addr:full":"455 Amsterdam Ave New York NY 10024",
    "addr:housenumber":"455",
    "addr:postcode":"10024",
    "addr:street":"Amsterdam Ave",
    "iso:country":"US",
    "sg:address":"455 Amsterdam Ave",
    "sg:city":"New York",
    "sg:classifiers":[
        {
            "category":"Personal",
            "subcategory":"Barber",
            "type":"Services"
        }
    ],
    "sg:phone":"+1 212 595 3837",
    "sg:postcode":"10024",
    "sg:province":"NY",
    "wof:name":"Antonio Barber Shop",
    "wof:placetype":"venue"
},
  "geometry": {"coordinates":[-73.977006,40.784942],"type":"Point"}
}