{
  "type": "Feature",
  "properties": {
    "addr:full":"675 9 Ave New York NY 10036",
    "addr:housenumber":"675",
    "addr:postcode":"10036",
    "addr:street":"9 Ave",
    "iso:country":"US",
    "sg:address":"675 9 Ave",
    "sg:city":"New York",
    "sg:classifiers":[
        {
            "category":"Restaurant",
            "type":"Food & Drink"
        }
    ],
    "sg:phone":"+1   ",
    "sg:postcode":"10036",
    "sg:province":"NY",
    "sg:tags":[
        "eating"
    ],
    "wof:name":"Chez Suzette",
    "wof:placetype":"venue"
},
  "geometry": {"coordinates":[-73.992633,40.75843],"type":"Point"}
}