{
  "type": "Feature",
  "properties": {
    "addr:full":"4 Wells St Johnstown NY 12095",
    "addr:housenumber":"4",
    "addr:postcode":"12095",
    "addr:street":"Wells St",
    "iso:country":"US",
    "sg:address":"4 Wells St",
    "sg:city":"Johnstown",
    "sg:classifiers":[
        {
            "category":"Professional",
            "subcategory":"Lawyer & Legal Services",
            "type":"Services"
        }
    ],
    "sg:phone":"+1 518 762 5517",
    "sg:postcode":"12095",
    "sg:province":"NY",
    "sg:tags":[
        "attorney"
    ],
    "wof:name":"Fulton Cty Law Guardian Ofc",
    "wof:placetype":"venue"
},
  "geometry": {"coordinates":[-74.379403,43.009628],"type":"Point"}
}