{
  "type": "Feature",
  "properties": {
    "iso:country":"US",
    "sg:address":"3242 Nys Route 417",
    "sg:city":"Olean",
    "sg:classifiers":[
        {
            "category":"Bakery",
            "type":"Food & Drink"
        },
        {
            "category":"Coffee & Tea",
            "type":"Food & Drink"
        },
        {
            "category":"Bagels",
            "type":"Food & Drink"
        },
        {
            "category":"Donuts",
            "type":"Food & Drink"
        }
    ],
    "sg:menulink":"http://www.allmenus.com/ny/allegany/138602-dunkin-donuts/menu/",
    "sg:phone":"+1 516 932 2245",
    "sg:postcode":"14760",
    "sg:province":"NY",
    "sg:tags":[
        "american",
        "pastry"
    ],
    "wof:name":"Dunkin' Donuts",
    "wof:placetype":"venue"
},
  "geometry": {"coordinates":[-78.477075,42.079367],"type":"Point"}
}