{
  "type": "Feature",
  "properties": {
    "iso:country":"US",
    "sg:address":"229 East Ave",
    "sg:city":"Lockport",
    "sg:classifiers":[
        {
            "category":"Health Services",
            "subcategory":"Doctor",
            "type":"Services"
        }
    ],
    "sg:phone":"+1 716 434 1149",
    "sg:postcode":"14094",
    "sg:province":"NY",
    "sg:tags":[
        "medical"
    ],
    "wof:name":"Muscato George MD",
    "wof:placetype":"venue"
},
  "geometry": {"coordinates":[-78.68114300000001,43.173024],"type":"Point"}
}