{
  "type": "Feature",
  "properties": {
    "iso:country":"US",
    "sg:address":"314 E 14th St",
    "sg:city":"Elmira Heights",
    "sg:classifiers":[
        {
            "category":"Home & Garden",
            "subcategory":"Furniture",
            "type":"Retail Goods"
        }
    ],
    "sg:phone":"+1 607 733 0400",
    "sg:postcode":"14903",
    "sg:province":"NY",
    "wof:name":"Morich Inc",
    "wof:placetype":"venue"
},
  "geometry": {"coordinates":[-76.820212,42.129582],"type":"Point"}
}