{
  "type": "Feature",
  "properties": {
    "addr:full":"840 Hanshaw Rd Ithaca NY 14850",
    "addr:housenumber":"840",
    "addr:postcode":"14850",
    "addr:street":"Hanshaw Rd",
    "iso:country":"US",
    "sg:address":"840 Hanshaw Rd",
    "sg:city":"Ithaca",
    "sg:classifiers":[
        {
            "category":"Insurance",
            "subcategory":"Insurance Agent",
            "type":"Services"
        },
        {
            "category":"Insurance",
            "subcategory":"Hazard Insurance",
            "type":"Services"
        },
        {
            "category":"Insurance",
            "subcategory":"Title Insurance",
            "type":"Services"
        },
        {
            "category":"Insurance",
            "subcategory":"Life Insurance",
            "type":"Services"
        }
    ],
    "sg:phone":"+1 607 257 0606",
    "sg:postcode":"14850",
    "sg:province":"NY",
    "sg:tags":[
        "business",
        "auto",
        "commercial",
        "homeowner",
        "motorcycle",
        "renter"
    ],
    "wof:name":"Allstate Insurance Company - Gerald Tilebein",
    "wof:placetype":"venue"
},
  "geometry": {"coordinates":[-76.47963900000001,42.469552],"type":"Point"}
}