{
  "type": "Feature",
  "properties": {
    "iso:country":"US",
    "sg:address":"3 Burns Ave",
    "sg:city":"Hicksville",
    "sg:classifiers":[
        {
            "category":"Utilities",
            "subcategory":"Cable",
            "type":"Services"
        }
    ],
    "sg:phone":"+1 516 931 2530",
    "sg:postcode":"11801",
    "sg:province":"NY",
    "sg:tags":[
        "television"
    ],
    "wof:name":"RCH Cable Outsourcing Svc",
    "wof:placetype":"venue"
},
  "geometry": {"coordinates":[-73.536056,40.767792],"type":"Point"}
}