{
  "type": "Feature",
  "properties": {
    "iso:country":"US",
    "sg:address":"36 Pond Meadow",
    "sg:city":"Rochester",
    "sg:classifiers":[
        {
            "category":"Building & Trades",
            "subcategory":"Construction",
            "type":"Services"
        }
    ],
    "sg:phone":"+1 585 426 8789",
    "sg:postcode":"14624",
    "sg:province":"NY",
    "sg:tags":[
        "carpentry",
        "contractor"
    ],
    "wof:name":"Demonte Construction",
    "wof:placetype":"venue"
},
  "geometry": {"coordinates":[-77.769683,43.113461],"type":"Point"}
}