{
  "type": "Feature",
  "properties": {
    "addr:full":"1952 Hendrickson Street Brooklyn NY 11234",
    "addr:housenumber":"1952",
    "addr:postcode":"11234",
    "addr:street":"Hendrickson Street",
    "iso:country":"US",
    "sg:address":"1952 Hendrickson Street",
    "sg:city":"Brooklyn",
    "sg:classifiers":[
        {
            "category":"Personal",
            "type":"Services"
        }
    ],
    "sg:phone":"+1 212 563 6667",
    "sg:postcode":"11234",
    "sg:province":"NY",
    "sg:tags":[
        "mover"
    ],
    "wof:name":"Drayton Worldwide",
    "wof:placetype":"venue"
},
  "geometry": {"coordinates":[-73.92788400000001,40.613119],"type":"Point"}
}