{
  "type": "Feature",
  "properties": {
    "iso:country":"US",
    "sg:address":"22 Park Ave",
    "sg:city":"Roosevelt",
    "sg:classifiers":[
        {
            "category":"Building & Trades",
            "subcategory":"Construction",
            "type":"Services"
        }
    ],
    "sg:phone":"+1 516 223 1538",
    "sg:postcode":"11575",
    "sg:province":"NY",
    "sg:tags":[
        "house"
    ],
    "wof:name":"Stephen Repair",
    "wof:placetype":"venue"
},
  "geometry": {"coordinates":[-73.584124,40.681054],"type":"Point"}
}