{
  "type": "Feature",
  "properties": {
    "addr:full":"6 E 50 St New York NY 10022",
    "addr:housenumber":"6;50",
    "addr:postcode":"10022",
    "addr:street":"E",
    "iso:country":"US",
    "sg:address":"6 E 50 St",
    "sg:city":"New York",
    "sg:classifiers":[
        {
            "category":"Retail",
            "subcategory":"Auto Repair",
            "type":"Services"
        }
    ],
    "sg:phone":"+1 646 307 4575",
    "sg:postcode":"10022",
    "sg:province":"NY",
    "sg:tags":[
        "wrecker"
    ],
    "wof:name":"A Number 1 Abwaa 24 Hours Twng",
    "wof:placetype":"venue"
},
  "geometry": {"coordinates":[-73.975815,40.757899],"type":"Point"}
}