{
  "type": "Feature",
  "properties": {
    "iso:country":"US",
    "sg:address":"10 Winding Brook Ln",
    "sg:city":"Rhinebeck",
    "sg:classifiers":[
        {
            "category":"Building & Trades",
            "subcategory":"Construction",
            "type":"Services"
        }
    ],
    "sg:phone":"+1 845 876 1003",
    "sg:postcode":"12572",
    "sg:province":"NY",
    "sg:tags":[
        "general",
        "contractor"
    ],
    "wof:name":"M F Pottenburgh General Contg",
    "wof:placetype":"venue"
},
  "geometry": {"coordinates":[-73.830101,41.971269],"type":"Point"}
}