{
  "type": "Feature",
  "properties": {
    "iso:country":"US",
    "sg:address":"304 Huguenot St",
    "sg:city":"New Rochelle",
    "sg:classifiers":[
        {
            "category":"Taxi",
            "type":"Transportation"
        }
    ],
    "sg:phone":"+1 914 576 8400",
    "sg:postcode":"10801",
    "sg:province":"NY",
    "sg:tags":[
        "taxicab"
    ],
    "wof:name":"America Taxi",
    "wof:placetype":"venue"
},
  "geometry": {"coordinates":[-73.784622,40.908583],"type":"Point"}
}