{
  "type": "Feature",
  "properties": {
    "iso:country":"US",
    "sg:address":"46 W Merrick Rd",
    "sg:city":"Freeport",
    "sg:classifiers":[
        {
            "category":"Insurance",
            "subcategory":"Insurance Agent",
            "type":"Services"
        },
        {
            "category":"Professional",
            "subcategory":"Lawyer & Legal Services",
            "type":"Services"
        },
        {
            "category":"Insurance",
            "subcategory":"Title Insurance",
            "type":"Services"
        },
        {
            "category":"Insurance",
            "subcategory":"Health Insurance",
            "type":"Services"
        },
        {
            "category":"Insurance",
            "subcategory":"Life Insurance",
            "type":"Services"
        },
        {
            "category":"Insurance",
            "subcategory":"Hazard Insurance",
            "type":"Services"
        }
    ],
    "sg:phone":"+1 516 543 0209",
    "sg:postcode":"11520",
    "sg:province":"NY",
    "sg:tags":[
        "attorney",
        "business",
        "auto",
        "commercial",
        "homeowner",
        "renter",
        "property",
        "casualty"
    ],
    "sg:website":"http://statefarm.mqgroup.com/url.asp?usr=322083",
    "wof:name":"Kasprzak, Fran - State Farm Insurance Agent",
    "wof:placetype":"venue"
},
  "geometry": {"coordinates":[-73.581997,40.654007],"type":"Point"}
}