{
  "type": "Feature",
  "properties": {
    "addr:full":"5647 Broadway St Lancaster NY 14086",
    "addr:housenumber":"5647",
    "addr:postcode":"14086",
    "addr:street":"Broadway St",
    "iso:country":"US",
    "sg:address":"5647 Broadway St",
    "sg:city":"Lancaster",
    "sg:classifiers":[
        {
            "category":"Professional",
            "subcategory":"Lawyer & Legal Services",
            "type":"Services"
        }
    ],
    "sg:phone":"+1 716 683 0717",
    "sg:postcode":"14086",
    "sg:province":"NY",
    "sg:tags":[
        "attorney"
    ],
    "wof:name":"Dominic J Terranova",
    "wof:placetype":"venue"
},
  "geometry": {"coordinates":[-78.659249,42.897456],"type":"Point"}
}