{
  "type": "Feature",
  "properties": {
    "iso:country":"US",
    "sg:address":"1879 Rockaway Pkwy",
    "sg:city":"Brooklyn",
    "sg:classifiers":[
        {
            "category":"Retail",
            "subcategory":"Laundry & Dry Cleaning",
            "type":"Services"
        }
    ],
    "sg:phone":"+1 718 968 8447",
    "sg:postcode":"11236",
    "sg:province":"NY",
    "sg:tags":[
        "drycleaning",
        "plant"
    ],
    "wof:name":"Evergreen Cleaner",
    "wof:placetype":"venue"
},
  "geometry": {"coordinates":[-73.891701,40.6357],"type":"Point"}
}