{
  "type": "Feature",
  "properties": {
    "addr:full":"380 Lexington Ave New York NY 10168",
    "addr:housenumber":"380",
    "addr:postcode":"10168",
    "addr:street":"Lexington Ave",
    "iso:country":"US",
    "sg:address":"380 Lexington Ave",
    "sg:city":"New York",
    "sg:classifiers":[
        {
            "category":"Professional",
            "subcategory":"Employment Agencies",
            "type":"Services"
        }
    ],
    "sg:phone":"+1 212 551 7889",
    "sg:postcode":"10168",
    "sg:province":"NY",
    "wof:name":"Greenwood Legal Inc",
    "wof:placetype":"venue"
},
  "geometry": {"coordinates":[-73.976287,40.751191],"type":"Point"}
}