{
  "type": "Feature",
  "properties": {
    "iso:country":"US",
    "sg:address":"Central Park",
    "sg:city":"New York",
    "sg:classifiers":[
        {
            "category":"Professional",
            "subcategory":"Computer Services",
            "type":"Services"
        }
    ],
    "sg:postcode":"12345",
    "sg:province":"NY",
    "sg:tags":[
        "video-sharing",
        "youtube-clone",
        "youtube-software",
        "youtube-script",
        "media-sharing"
    ],
    "sg:website":"http://www.clip-center.com",
    "wof:name":"ClipCenter",
    "wof:placetype":"venue"
},
  "geometry": {"coordinates":[-73.91553999999999,42.794428],"type":"Point"}
}