{
  "type": "Feature",
  "properties": {
    "iso:country":"US",
    "sg:address":"2625 E 14th St",
    "sg:city":"Brooklyn",
    "sg:classifiers":[
        {
            "category":"Professional",
            "subcategory":"Lawyer & Legal Services",
            "type":"Services"
        }
    ],
    "sg:phone":"+1 718 332 4778",
    "sg:postcode":"11235",
    "sg:province":"NY",
    "sg:tags":[
        "attorney"
    ],
    "wof:name":"Bruce Newborough Law Offices",
    "wof:placetype":"venue"
},
  "geometry": {"coordinates":[-73.954829,40.586],"type":"Point"}
}