{
  "type": "Feature",
  "properties": {
    "addr:full":"2168 Central Park Ave Yonkers NY 10710",
    "addr:housenumber":"2168",
    "addr:postcode":"10710",
    "addr:street":"Central Park Ave",
    "iso:country":"US",
    "sg:address":"2168 Central Park Ave",
    "sg:city":"Yonkers",
    "sg:classifiers":[
        {
            "category":"Professional",
            "subcategory":"Lawyer & Legal Services",
            "type":"Services"
        }
    ],
    "sg:phone":"+1 914 779 7222",
    "sg:postcode":"10710",
    "sg:province":"NY",
    "sg:tags":[
        "attorney"
    ],
    "wof:name":"Daniel P Romano",
    "wof:placetype":"venue"
},
  "geometry": {"coordinates":[-73.834924,40.972465],"type":"Point"}
}