{
  "type": "Feature",
  "properties": {
    "iso:country":"US",
    "sg:address":"864 Clarkson Ave",
    "sg:city":"Brooklyn",
    "sg:classifiers":[
        {
            "category":"Organizations",
            "subcategory":"Religious Organization",
            "type":"Services"
        }
    ],
    "sg:phone":"+1 718 467 0204",
    "sg:postcode":"11203",
    "sg:province":"NY",
    "wof:name":"Bethel Worship Center",
    "wof:placetype":"venue"
},
  "geometry": {"coordinates":[-73.929457,40.656575],"type":"Point"}
}