{
  "type": "Feature",
  "properties": {
    "addr:full":"2600 Netherland Ave Bronx NY 10463",
    "addr:housenumber":"2600",
    "addr:postcode":"10463",
    "addr:street":"Netherland Ave",
    "iso:country":"US",
    "sg:address":"2600 Netherland Ave",
    "sg:city":"Bronx",
    "sg:classifiers":[
        {
            "category":"Sports & Exercise",
            "subcategory":"Gym",
            "type":"Entertainment"
        },
        {
            "category":"Organizations",
            "subcategory":"Community Association",
            "type":"Services"
        }
    ],
    "sg:phone":"+1 718 796 9099",
    "sg:postcode":"10463",
    "sg:province":"NY",
    "sg:tags":[
        "club",
        "recreation",
        "center"
    ],
    "wof:name":"TCR Tennis Club Of Riverdale",
    "wof:placetype":"venue"
},
  "geometry": {"coordinates":[-73.91448699999999,40.879612],"type":"Point"}
}