{
  "type": "Feature",
  "properties": {
    "iso:country":"US",
    "sg:address":"5430 Curtis Rd",
    "sg:city":"Hemlock",
    "sg:classifiers":[
        {
            "category":"Professional",
            "type":"Services"
        }
    ],
    "sg:phone":"+1 585 367 8413",
    "sg:postcode":"14466",
    "sg:province":"NY",
    "sg:tags":[
        "establishment"
    ],
    "wof:name":"Country Colony Estates",
    "wof:placetype":"venue"
},
  "geometry": {"coordinates":[-77.554726,42.759338],"type":"Point"}
}