{
  "type": "Feature",
  "properties": {
    "addr:full":"311 E 42nd St New York NY 10017",
    "addr:housenumber":"311",
    "addr:postcode":"10017",
    "addr:street":"E 42Nd St",
    "iso:country":"US",
    "sg:address":"311 E 42nd St",
    "sg:city":"New York",
    "sg:classifiers":[
        {
            "category":"Building & Trades",
            "subcategory":"Locksmith",
            "type":"Services"
        }
    ],
    "sg:phone":"+1 646 365 3016",
    "sg:postcode":"10017",
    "sg:province":"NY",
    "sg:tags":[
        "key"
    ],
    "wof:name":"Aruba Locks & Gates",
    "wof:placetype":"venue"
},
  "geometry": {"coordinates":[-73.9714,40.749504],"type":"Point"}
}