{
  "type": "Feature",
  "properties": {
    "iso:country":"US",
    "sg:address":"6614 Thompson Rd",
    "sg:city":"Syracuse",
    "sg:classifiers":[
        {
            "category":"Travel",
            "subcategory":"Hotels & Motels",
            "type":"Entertainment"
        }
    ],
    "sg:phone":"+1 315 437 3309",
    "sg:postcode":"13206",
    "sg:province":"NY",
    "wof:name":"Red Roof Inn",
    "wof:placetype":"venue"
},
  "geometry": {"coordinates":[-76.092389,43.090071],"type":"Point"}
}