{
  "type": "Feature",
  "properties": {
    "addr:full":"873 8th Avenue New York NY 10019",
    "addr:housenumber":"873",
    "addr:postcode":"10019",
    "addr:street":"8Th Avenue",
    "iso:country":"US",
    "sg:address":"873 8th Avenue",
    "sg:city":"New York",
    "sg:classifiers":[
        {
            "category":"Professional",
            "type":"Services"
        }
    ],
    "sg:phone":"+1 212 247 1942",
    "sg:postcode":"10019",
    "sg:province":"NY",
    "sg:tags":[
        "caterer"
    ],
    "wof:name":"D'aiuto's Pastry Corporation",
    "wof:placetype":"venue"
},
  "geometry": {"coordinates":[-73.985192,40.763747],"type":"Point"}
}