{
  "type": "Feature",
  "properties": {
    "iso:country":"US",
    "sg:address":"55 Old Turnpike Rd",
    "sg:city":"Nanuet",
    "sg:classifiers":[
        {
            "category":"Health Services",
            "subcategory":"Doctor",
            "type":"Services"
        }
    ],
    "sg:phone":"+1 845 623 4154",
    "sg:postcode":"10954",
    "sg:province":"NY",
    "sg:tags":[
        "physician",
        "surgeon"
    ],
    "wof:name":"Norbert Rainford Md",
    "wof:placetype":"venue"
},
  "geometry": {"coordinates":[-74.028931,41.100224],"type":"Point"}
}