{
  "type": "Feature",
  "properties": {
    "iso:country":"US",
    "sg:address":"510 Pletcher Rd",
    "sg:city":"Lewiston",
    "sg:classifiers":[
        {
            "category":"Coffee & Tea",
            "type":"Food & Drink"
        },
        {
            "category":"Restaurant",
            "type":"Food & Drink"
        }
    ],
    "sg:phone":"+1 716 754 1106",
    "sg:postcode":"14092",
    "sg:province":"NY",
    "sg:tags":[
        "espresso"
    ],
    "wof:name":"Sisters Cafe Jennifer L Diez",
    "wof:placetype":"venue"
},
  "geometry": {"coordinates":[-79.036011,43.204088],"type":"Point"}
}