{
  "type": "Feature",
  "properties": {
    "addr:full":"414 E 88th St New York NY 10128",
    "addr:housenumber":"414",
    "addr:postcode":"10128",
    "addr:street":"E 88Th St",
    "iso:country":"US",
    "sg:address":"414 E 88th St",
    "sg:city":"New York",
    "sg:classifiers":[
        {
            "category":"Building & Trades",
            "subcategory":"Construction",
            "type":"Services"
        }
    ],
    "sg:phone":"+1 212 360 7387",
    "sg:postcode":"10128",
    "sg:province":"NY",
    "sg:tags":[
        "contractor"
    ],
    "wof:name":"Linden Marshall Contracting Inc",
    "wof:placetype":"venue"
},
  "geometry": {"coordinates":[-73.9515,40.7822],"type":"Point"}
}