{
  "type": "Feature",
  "properties": {
    "addr:full":"82 Rockaway Ave Valley Stream NY 11580",
    "addr:housenumber":"82",
    "addr:postcode":"11580",
    "addr:street":"Rockaway Ave",
    "iso:country":"US",
    "sg:address":"82 Rockaway Ave",
    "sg:city":"Valley Stream",
    "sg:classifiers":[
        {
            "category":"Shopping",
            "type":"Retail Goods"
        }
    ],
    "sg:phone":"+1 516 825 5511",
    "sg:postcode":"11580",
    "sg:province":"NY",
    "sg:tags":[
        "stamp",
        "collector",
        "for",
        "merchandise"
    ],
    "wof:name":"Arrow Stamp & Coin Center",
    "wof:placetype":"venue"
},
  "geometry": {"coordinates":[-73.698975,40.662908],"type":"Point"}
}