{
  "type": "Feature",
  "properties": {
    "addr:full":"16 Birchwood Dr Plattsburgh NY 12901",
    "addr:housenumber":"16",
    "addr:postcode":"12901",
    "addr:street":"Birchwood Dr",
    "iso:country":"US",
    "sg:address":"16 Birchwood Dr",
    "sg:city":"Plattsburgh",
    "sg:classifiers":[
        {
            "category":"Cinema",
            "subcategory":"Movie Rental",
            "type":"Entertainment"
        }
    ],
    "sg:phone":"+1   ",
    "sg:postcode":"12901",
    "sg:province":"NY",
    "sg:tags":[
        "video",
        "tape"
    ],
    "wof:name":"Photo Video Images Inc",
    "wof:placetype":"venue"
},
  "geometry": {"coordinates":[-73.510775,44.665853],"type":"Point"}
}