{
  "type": "Feature",
  "properties": {
    "iso:country":"US",
    "sg:address":"122 Bus Park Dr",
    "sg:city":"Utica",
    "sg:classifiers":[
        {
            "category":"Professional",
            "subcategory":"Business Services",
            "type":"Services"
        }
    ],
    "sg:phone":"+1 315 724 2104",
    "sg:postcode":"13502",
    "sg:province":"NY",
    "sg:tags":[
        "inventory"
    ],
    "sg:website":"www.rgisinv.com",
    "wof:name":"RGIS Inventory Specialists",
    "wof:placetype":"venue"
},
  "geometry": {"coordinates":[-75.285492,43.091533],"type":"Point"}
}