{
  "type": "Feature",
  "properties": {
    "iso:country":"US",
    "sg:address":"766 Drew St",
    "sg:city":"Brooklyn",
    "sg:classifiers":[
        {
            "category":"Professional",
            "subcategory":"Business Services",
            "type":"Services"
        }
    ],
    "sg:phone":"+1 718 277 3535",
    "sg:postcode":"11208",
    "sg:province":"NY",
    "sg:tags":[
        "recording",
        "studio"
    ],
    "wof:name":"Sound Of Brooklyn",
    "wof:placetype":"venue"
},
  "geometry": {"coordinates":[-73.861664,40.672598],"type":"Point"}
}