{
  "type": "Feature",
  "properties": {
    "addr:full":"2511 Western Ave Altamont NY 12009",
    "addr:housenumber":"2511",
    "addr:postcode":"12009",
    "addr:street":"Western Ave",
    "iso:country":"US",
    "sg:address":"2511 Western Ave",
    "sg:city":"Altamont",
    "sg:classifiers":[
        {
            "category":"Sports & Exercise",
            "subcategory":"Gym",
            "type":"Entertainment"
        }
    ],
    "sg:phone":"+1 518 464 0180",
    "sg:postcode":"12009",
    "sg:province":"NY",
    "sg:tags":[
        "club",
        "health",
        "studio",
        "gymnasium"
    ],
    "wof:name":"Curves",
    "wof:placetype":"venue"
},
  "geometry": {"coordinates":[-73.927094,42.711653],"type":"Point"}
}