{
  "type": "Feature",
  "properties": {
    "addr:full":"111 Worth Street Manhattan NY 10013",
    "addr:housenumber":"111",
    "addr:postcode":"10013",
    "addr:street":"Worth Street",
    "iso:country":"US",
    "sg:address":"111 Worth Street",
    "sg:city":"Manhattan",
    "sg:classifiers":[
        {
            "category":"Real Estate",
            "subcategory":"Real Estate Operator",
            "type":"Services"
        }
    ],
    "sg:postcode":"10013",
    "sg:province":"NY",
    "sg:tags":[
        "apartment"
    ],
    "wof:name":"111 Worth Street Apartments",
    "wof:placetype":"venue"
},
  "geometry": {"coordinates":[-74.00323299999999,40.715703],"type":"Point"}
}