{
  "type": "Feature",
  "properties": {
    "addr:full":"155 Beach Ave Larchmont NY 10538",
    "addr:housenumber":"155",
    "addr:postcode":"10538",
    "addr:street":"Beach Ave",
    "iso:country":"US",
    "sg:address":"155 Beach Ave",
    "sg:city":"Larchmont",
    "sg:classifiers":[
        {
            "category":"Health Services",
            "subcategory":"Doctor",
            "type":"Services"
        }
    ],
    "sg:phone":"+1 914 725 5877",
    "sg:postcode":"10538",
    "sg:province":"NY",
    "sg:tags":[
        "physician",
        "family",
        "medical",
        "practice",
        "surgeons",
        "medicine"
    ],
    "wof:name":"T P Jacobs Md",
    "wof:placetype":"venue"
},
  "geometry": {"coordinates":[-73.754019,40.927569],"type":"Point"}
}