{
  "type": "Feature",
  "properties": {
    "addr:full":"135 E 28th St New York NY 10016",
    "addr:housenumber":"135",
    "addr:postcode":"10016",
    "addr:street":"E 28Th St",
    "iso:country":"US",
    "sg:address":"135 E 28th St",
    "sg:city":"New York",
    "sg:classifiers":[
        {
            "category":"Deli",
            "type":"Food & Drink"
        }
    ],
    "sg:menulink":"http://www.allmenus.com/ny/new-york/2872-stop-28-luncheonette/menu/",
    "sg:phone":"+1 212 251 0110",
    "sg:postcode":"10016",
    "sg:province":"NY",
    "sg:tags":[
        "american"
    ],
    "wof:name":"Stop 28 Luncheonette",
    "wof:placetype":"venue"
},
  "geometry": {"coordinates":[-73.982147,40.742513],"type":"Point"}
}