{
  "type": "Feature",
  "properties": {
    "iso:country":"US",
    "sg:address":"7 Moreland Rd",
    "sg:city":"New City",
    "sg:classifiers":[
        {
            "category":"Professional",
            "type":"Services"
        }
    ],
    "sg:phone":"+1   ",
    "sg:postcode":"10956",
    "sg:province":"NY",
    "wof:name":"J Krouskoff Compu",
    "wof:placetype":"venue"
},
  "geometry": {"coordinates":[-74.001678,41.168962],"type":"Point"}
}