{
  "type": "Feature",
  "properties": {
    "addr:full":"1430 Watson Avenue Bronx NY 10472",
    "addr:housenumber":"1430",
    "addr:postcode":"10472",
    "addr:street":"Watson Avenue",
    "iso:country":"US",
    "sg:address":"1430 Watson Avenue",
    "sg:city":"Bronx",
    "sg:classifiers":[
        {
            "category":"Retail",
            "subcategory":"Auto Repair",
            "type":"Services"
        }
    ],
    "sg:phone":"+1 718 893 5304",
    "sg:postcode":"10472",
    "sg:province":"NY",
    "wof:name":"Frankie's Auto Repr",
    "wof:placetype":"venue"
},
  "geometry": {"coordinates":[-73.88273700000001,40.825472],"type":"Point"}
}