{
  "type": "Feature",
  "properties": {
    "iso:country":"US",
    "sg:address":"47 W 20th St",
    "sg:city":"New York",
    "sg:classifiers":[
        {
            "category":"Shopping",
            "subcategory":"Clothing, Apparel, & Fashions",
            "type":"Retail Goods"
        }
    ],
    "sg:phone":"+1 212 226 7585",
    "sg:postcode":"10011",
    "sg:province":"NY",
    "wof:name":"Lounge Soho",
    "wof:placetype":"venue"
},
  "geometry": {"coordinates":[-73.99342,40.740611],"type":"Point"}
}