{
  "type": "Feature",
  "properties": {
    "addr:full":"2090 State Hwy 110 Farmingdale NY 11735",
    "addr:housenumber":"2090",
    "addr:postcode":"11735",
    "addr:street":"State Hwy 110",
    "iso:country":"US",
    "sg:address":"2090 State Hwy 110",
    "sg:city":"Farmingdale",
    "sg:classifiers":[
        {
            "category":"Home & Garden",
            "subcategory":"Furniture",
            "type":"Retail Goods"
        }
    ],
    "sg:phone":"+1 631 777 1118",
    "sg:postcode":"11735",
    "sg:province":"NY",
    "wof:name":"Design Furniture Source Inc",
    "wof:placetype":"venue"
},
  "geometry": {"coordinates":[-73.422613,40.745478],"type":"Point"}
}