{
  "type": "Feature",
  "properties": {
    "iso:country":"US",
    "sg:address":"970 Emerson St",
    "sg:city":"Rochester",
    "sg:classifiers":[
        {
            "category":"School Buses",
            "type":"Transportation"
        }
    ],
    "sg:phone":"+1   ",
    "sg:postcode":"14606",
    "sg:province":"NY",
    "sg:website":"www.monroeschooltrans.com",
    "wof:name":"Monroe School Transportation",
    "wof:placetype":"venue"
},
  "geometry": {"coordinates":[-77.657357,43.173934],"type":"Point"}
}