{
  "type": "Feature",
  "properties": {
    "iso:country":"US",
    "sg:address":"4934 Chevalier Rd",
    "sg:city":"Locke",
    "sg:classifiers":[
        {
            "category":"Building & Trades",
            "subcategory":"Construction",
            "type":"Services"
        }
    ],
    "sg:phone":"+1 315 497 0098",
    "sg:postcode":"13092",
    "sg:province":"NY",
    "sg:tags":[
        "welder"
    ],
    "wof:name":"Innovative Metal Works",
    "wof:placetype":"venue"
},
  "geometry": {"coordinates":[-76.420068,42.629991],"type":"Point"}
}