{
  "type": "Feature",
  "properties": {
    "iso:country":"US",
    "sg:address":"1739 Peninsula Blvd",
    "sg:city":"Hewlett",
    "sg:classifiers":[
        {
            "category":"Restaurant",
            "type":"Food & Drink"
        }
    ],
    "sg:phone":"+1 516 295 2888",
    "sg:postcode":"11557",
    "sg:province":"NY",
    "wof:name":"Little Fu's",
    "wof:placetype":"venue"
},
  "geometry": {"coordinates":[-73.692802,40.648399],"type":"Point"}
}