{
  "type": "Feature",
  "properties": {
    "addr:full":"285 Delancey Street New York NY 10002",
    "addr:housenumber":"285",
    "addr:postcode":"10002",
    "addr:street":"Delancey Street",
    "iso:country":"US",
    "sg:address":"285 Delancey Street",
    "sg:city":"New York",
    "sg:classifiers":[
        {
            "category":"Education",
            "subcategory":"School",
            "type":"Public Place"
        }
    ],
    "sg:phone":"+1 212 674 2690",
    "sg:postcode":"10002",
    "sg:province":"NY",
    "sg:tags":[
        "high",
        "middle",
        "elementary"
    ],
    "wof:name":"N Y City of",
    "wof:placetype":"venue"
},
  "geometry": {"coordinates":[-73.980025,40.715671],"type":"Point"}
}