{
  "type": "Feature",
  "properties": {
    "addr:full":"82 Reade St New York NY 10007",
    "addr:housenumber":"82",
    "addr:postcode":"10007",
    "addr:street":"Reade St",
    "iso:country":"US",
    "sg:address":"82 Reade St",
    "sg:city":"New York",
    "sg:classifiers":[
        {
            "category":"Food & Beverages",
            "subcategory":"Bakery",
            "type":"Retail Goods"
        }
    ],
    "sg:phone":"+1 212 964 2510",
    "sg:postcode":"10007",
    "sg:province":"NY",
    "sg:tags":[
        "sandwich"
    ],
    "wof:name":"Blimpie Sub Sandwiches",
    "wof:placetype":"venue"
},
  "geometry": {"coordinates":[-74.47524799999999,40.715564],"type":"Point"}
}