{
  "type": "Feature",
  "properties": {
    "iso:country":"US",
    "sg:address":"19 S Erie St",
    "sg:city":"Mayville",
    "sg:classifiers":[
        {
            "category":"Real Estate",
            "subcategory":"Real Estate Agent",
            "type":"Services"
        }
    ],
    "sg:phone":"+1 716 753 3403",
    "sg:postcode":"14757",
    "sg:province":"NY",
    "wof:name":"Century 21",
    "wof:placetype":"venue"
},
  "geometry": {"coordinates":[-79.50377899999999,42.253274],"type":"Point"}
}