{
  "type": "Feature",
  "properties": {
    "addr:full":"266 W 11th St New York NY 10014",
    "addr:housenumber":"266",
    "addr:postcode":"10014",
    "addr:street":"W 11Th St",
    "iso:country":"US",
    "sg:address":"266 W 11th St",
    "sg:city":"New York",
    "sg:classifiers":[
        {
            "category":"Building & Trades",
            "subcategory":"Plumbing",
            "type":"Services"
        }
    ],
    "sg:phone":"+1 212 937 1100",
    "sg:postcode":"10014",
    "sg:province":"NY",
    "wof:name":"A and A Locksmith",
    "wof:placetype":"venue"
},
  "geometry": {"coordinates":[-74.004046,40.7359],"type":"Point"}
}