{
  "type": "Feature",
  "properties": {
    "iso:country":"US",
    "sg:address":"147 Oak St",
    "sg:city":"Binghamton",
    "sg:classifiers":[
        {
            "category":"Building & Trades",
            "subcategory":"Plumbing",
            "type":"Services"
        }
    ],
    "sg:phone":"+1 607 722 0464",
    "sg:postcode":"13905",
    "sg:province":"NY",
    "sg:tags":[
        "system",
        "heating",
        "contractor",
        "air conditioning"
    ],
    "wof:name":"A Linz Heating",
    "wof:placetype":"venue"
},
  "geometry": {"coordinates":[-75.91883900000001,42.10203],"type":"Point"}
}