{
  "type": "Feature",
  "properties": {
    "iso:country":"US",
    "sg:address":"101 N Middletown Rd",
    "sg:city":"Nanuet",
    "sg:classifiers":[
        {
            "category":"Professional",
            "subcategory":"Lawyer & Legal Services",
            "type":"Services"
        }
    ],
    "sg:phone":"+1 845 627 1627",
    "sg:postcode":"10954",
    "sg:province":"NY",
    "sg:tags":[
        "attorney"
    ],
    "wof:name":"David M Bushman",
    "wof:placetype":"venue"
},
  "geometry": {"coordinates":[-74.010278,41.103889],"type":"Point"}
}