{
  "type": "Feature",
  "properties": {
    "iso:country":"US",
    "sg:address":"2331 Arthur Ave",
    "sg:city":"Bronx",
    "sg:classifiers":[
        {
            "category":"Professional",
            "subcategory":"Employment Agencies",
            "type":"Services"
        }
    ],
    "sg:phone":"+1 718 450 8209",
    "sg:postcode":"10458",
    "sg:province":"NY",
    "wof:name":"Canamfil International Man Power",
    "wof:placetype":"venue"
},
  "geometry": {"coordinates":[-73.889021,40.854088],"type":"Point"}
}