{
  "type": "Feature",
  "properties": {
    "addr:full":"66 York Ave Saratoga Springs NY 12866",
    "addr:housenumber":"66",
    "addr:postcode":"12866",
    "addr:street":"York Ave",
    "iso:country":"US",
    "sg:address":"66 York Ave",
    "sg:city":"Saratoga Springs",
    "sg:classifiers":[
        {
            "category":"Education",
            "subcategory":"School",
            "type":"Public Place"
        }
    ],
    "sg:phone":"+1 518 584 7643",
    "sg:postcode":"12866",
    "sg:province":"NY",
    "wof:name":"Spring Hill Waldorf School",
    "wof:placetype":"venue"
},
  "geometry": {"coordinates":[-73.77601199999999,43.084842],"type":"Point"}
}