{
  "type": "Feature",
  "properties": {
    "iso:country":"US",
    "sg:address":"2 W Carver St",
    "sg:city":"Huntington",
    "sg:classifiers":[
        {
            "category":"Home & Garden",
            "subcategory":"Home Furnishings",
            "type":"Retail Goods"
        }
    ],
    "sg:phone":"+1 631 424 5533",
    "sg:postcode":"11743",
    "sg:province":"NY",
    "sg:tags":[
        "bathroom",
        "fixture",
        "accessory"
    ],
    "wof:name":"Jennifer Gilden Designs",
    "wof:placetype":"venue"
},
  "geometry": {"coordinates":[-73.428201,40.868976],"type":"Point"}
}