{
  "type": "Feature",
  "properties": {
    "addr:full":"1568 Central Ave Albany NY 12205",
    "addr:housenumber":"1568",
    "addr:postcode":"12205",
    "addr:street":"Central Ave",
    "iso:country":"US",
    "sg:address":"1568 Central Ave",
    "sg:city":"Albany",
    "sg:classifiers":[
        {
            "category":"Wholesale",
            "subcategory":"Motor Vehicles",
            "type":"Manufacturing & Wholesale Goods"
        }
    ],
    "sg:phone":"+1 518 463 5338",
    "sg:postcode":"12205",
    "sg:province":"NY",
    "wof:name":"Navistar",
    "wof:placetype":"venue"
},
  "geometry": {"coordinates":[-73.830539,42.71554],"type":"Point"}
}