{
  "type": "Feature",
  "properties": {
    "iso:country":"US",
    "sg:address":"993 Church St",
    "sg:city":"Baldwin",
    "sg:classifiers":[
        {
            "category":"Recreation",
            "subcategory":"Arcade",
            "type":"Entertainment"
        }
    ],
    "sg:phone":"+1 516 867 1700",
    "sg:postcode":"11510",
    "sg:province":"NY",
    "sg:tags":[
        "casino"
    ],
    "wof:name":"Casino Parties By Fullhouse",
    "wof:placetype":"venue"
},
  "geometry": {"coordinates":[-73.60574699999999,40.641467],"type":"Point"}
}