{
  "type": "Feature",
  "properties": {
    "addr:full":"5145 Redman Rd Brockport NY 14420",
    "addr:housenumber":"5145",
    "addr:postcode":"14420",
    "addr:street":"Redman Rd",
    "iso:country":"US",
    "sg:address":"5145 Redman Rd",
    "sg:city":"Brockport",
    "sg:classifiers":[
        {
            "category":"Building & Trades",
            "subcategory":"Construction",
            "type":"Services"
        }
    ],
    "sg:phone":"+1 585 637 0847",
    "sg:postcode":"14420",
    "sg:province":"NY",
    "sg:tags":[
        "home",
        "general",
        "family",
        "contractor"
    ],
    "wof:name":"M Eldridge & Sons",
    "wof:placetype":"venue"
},
  "geometry": {"coordinates":[-77.96246499999999,43.178144],"type":"Point"}
}