{
  "type": "Feature",
  "properties": {
    "iso:country":"US",
    "sg:address":"10 W 18 St",
    "sg:city":"New York",
    "sg:classifiers":[
        {
            "category":"Professional",
            "subcategory":"Advertising",
            "type":"Services"
        }
    ],
    "sg:phone":"+1 212 243 8100",
    "sg:postcode":"10011",
    "sg:province":"NY",
    "sg:tags":[
        "agency"
    ],
    "wof:name":"Angels Avenging Inc",
    "wof:placetype":"venue"
},
  "geometry": {"coordinates":[-73.994851,40.739681],"type":"Point"}
}