{
  "type": "Feature",
  "properties": {
    "iso:country":"US",
    "sg:address":"79 Glasgow St",
    "sg:city":"Clyde",
    "sg:classifiers":[
        {
            "category":"Shopping",
            "subcategory":"Discount & Variety Stores",
            "type":"Retail Goods"
        }
    ],
    "sg:phone":"+1 315 923 2031",
    "sg:postcode":"14433",
    "sg:province":"NY",
    "sg:tags":[
        "merchandise",
        "general"
    ],
    "wof:name":"Clyde Bargain Center",
    "wof:placetype":"venue"
},
  "geometry": {"coordinates":[-76.8698,43.083501],"type":"Point"}
}