{
  "type": "Feature",
  "properties": {
    "iso:country":"US",
    "sg:address":"92 Main St",
    "sg:city":"Massena",
    "sg:classifiers":[
        {
            "category":"Retail",
            "subcategory":"Laundry & Dry Cleaning",
            "type":"Services"
        }
    ],
    "sg:phone":"+1 315 769 3879",
    "sg:postcode":"13662",
    "sg:province":"NY",
    "sg:tags":[
        "commercial"
    ],
    "wof:name":"Cornell's Dry Cleaners Corp",
    "wof:placetype":"venue"
},
  "geometry": {"coordinates":[-74.89278299999999,44.930434],"type":"Point"}
}