{
  "type": "Feature",
  "properties": {
    "addr:full":"207 W Taylor St Syracuse NY 13202",
    "addr:housenumber":"207",
    "addr:postcode":"13202",
    "addr:street":"W Taylor St",
    "iso:country":"US",
    "sg:address":"207 W Taylor St",
    "sg:city":"Syracuse",
    "sg:classifiers":[
        {
            "category":"Retail",
            "subcategory":"Laundry & Dry Cleaning",
            "type":"Services"
        }
    ],
    "sg:phone":"+1 315 475 9522",
    "sg:postcode":"13202",
    "sg:province":"NY",
    "sg:tags":[
        "launderer",
        "industrial"
    ],
    "wof:name":"Coyne Textile Services",
    "wof:placetype":"venue"
},
  "geometry": {"coordinates":[-76.15271199999999,43.038738],"type":"Point"}
}