{
  "type": "Feature",
  "properties": {
    "iso:country":"US",
    "sg:address":"112 S Broad St",
    "sg:city":"Norwich",
    "sg:classifiers":[
        {
            "category":"Education",
            "subcategory":"School",
            "type":"Public Place"
        }
    ],
    "sg:phone":"+1 607 334 1600",
    "sg:postcode":"13815",
    "sg:province":"NY",
    "wof:name":"Norwich City Schools",
    "wof:placetype":"venue"
},
  "geometry": {"coordinates":[-75.523262,42.524218],"type":"Point"}
}