{
  "type": "Feature",
  "properties": {
    "iso:country":"US",
    "sg:address":"40 Borden Ave",
    "sg:city":"Norwich",
    "sg:classifiers":[
        {
            "category":"Professional",
            "subcategory":"Management & Consulting",
            "type":"Services"
        }
    ],
    "sg:phone":"+1 607 336 2250",
    "sg:postcode":"13815",
    "sg:province":"NY",
    "sg:tags":[
        "consultant",
        "business"
    ],
    "wof:name":"Consulting Wright",
    "wof:placetype":"venue"
},
  "geometry": {"coordinates":[-75.5236,42.542027],"type":"Point"}
}