{
  "type": "Feature",
  "properties": {
    "iso:country":"US",
    "sg:address":"363 7th Ave 18th Fl",
    "sg:city":"Manhattan",
    "sg:classifiers":[
        {
            "category":"Professional",
            "subcategory":"Accounting & Tax Preparation",
            "type":"Services"
        }
    ],
    "sg:phone":"+1 917 285 0550",
    "sg:postcode":"10001",
    "sg:province":"NY",
    "sg:tags":[
        "accountant"
    ],
    "sg:website":"www.dgmcpany.com",
    "wof:name":"DGM CPA",
    "wof:placetype":"venue"
},
  "geometry": {"coordinates":[-73.992064,40.748476],"type":"Point"}
}