{
  "type": "Feature",
  "properties": {
    "addr:full":"805 3rd Ave New York NY 10022",
    "addr:housenumber":"805",
    "addr:postcode":"10022",
    "addr:street":"3Rd Ave",
    "iso:country":"US",
    "sg:address":"805 3rd Ave",
    "sg:city":"New York",
    "sg:classifiers":[
        {
            "category":"Personal",
            "type":"Services"
        }
    ],
    "sg:phone":"+1 917 289 1918",
    "sg:postcode":"10022",
    "sg:province":"NY",
    "sg:tags":[
        "towing"
    ],
    "wof:name":"24 Hour 7 Day Emergency Towing",
    "wof:placetype":"venue"
},
  "geometry": {"coordinates":[-73.971001,40.755501],"type":"Point"}
}