{
  "type": "Feature",
  "properties": {
    "addr:full":"8 Cyrus Field Rd Irvington NY 10533",
    "addr:housenumber":"8",
    "addr:postcode":"ny 10533",
    "addr:street":"Cyrus Field Rd",
    "iso:country":"US",
    "sg:address":"8 Cyrus Field Rd",
    "sg:city":"Irvington",
    "sg:classifiers":[
        {
            "category":"Professional",
            "subcategory":"Management & Consulting",
            "type":"Services"
        }
    ],
    "sg:phone":"+1 914 591 4503",
    "sg:postcode":"10533",
    "sg:province":"NY",
    "sg:tags":[
        "counselor",
        "public",
        "relations"
    ],
    "wof:name":"Vintage Hudson Valley",
    "wof:placetype":"venue"
},
  "geometry": {"coordinates":[-73.84768699999999,41.023765],"type":"Point"}
}