{
  "type": "Feature",
  "properties": {
    "addr:full":"271 Central Ave Silver Creek NY 14136",
    "addr:housenumber":"271",
    "addr:postcode":"14136",
    "addr:street":"Central Ave",
    "iso:country":"US",
    "sg:address":"271 Central Ave",
    "sg:city":"Silver Creek",
    "sg:classifiers":[
        {
            "category":"Professional",
            "subcategory":"Lawyer & Legal Services",
            "type":"Services"
        }
    ],
    "sg:phone":"+1 716 934 2600",
    "sg:postcode":"14136",
    "sg:province":"NY",
    "sg:tags":[
        "attorney"
    ],
    "wof:name":"Pelletter Mc Kelvey Pelletter",
    "wof:placetype":"venue"
},
  "geometry": {"coordinates":[-79.164908,42.543804],"type":"Point"}
}