{
  "type": "Feature",
  "properties": {
    "iso:country":"US",
    "sg:address":"1815 Broad Hollow Rd",
    "sg:city":"Farmingdale",
    "sg:classifiers":[
        {
            "category":"Home & Garden",
            "subcategory":"Furniture",
            "type":"Retail Goods"
        }
    ],
    "sg:phone":"+1 631 249 7124",
    "sg:postcode":"11735",
    "sg:province":"NY",
    "sg:website":"www.furniturenowonline.com",
    "wof:name":"Furniture Now",
    "wof:placetype":"venue"
},
  "geometry": {"coordinates":[-73.422616,40.743546],"type":"Point"}
}