{
  "type": "Feature",
  "properties": {
    "addr:full":"377 Park Ave S New York NY 10016",
    "addr:housenumber":"377",
    "addr:postcode":"10016",
    "addr:street":"Park Ave S",
    "iso:country":"US",
    "sg:address":"377 Park Ave S",
    "sg:city":"New York",
    "sg:classifiers":[
        {
            "category":"Shopping",
            "subcategory":"Computers & Home Electronics",
            "type":"Retail Goods"
        }
    ],
    "sg:phone":"+1   ",
    "sg:postcode":"10016",
    "sg:province":"NY",
    "sg:tags":[
        "production",
        "video"
    ],
    "wof:name":"H Q Inc",
    "wof:placetype":"venue"
},
  "geometry": {"coordinates":[-73.984667,40.742301],"type":"Point"}
}