{
  "type": "Feature",
  "properties": {
    "addr:full":"1892 Grand Ave North Baldwin NY 11510",
    "addr:housenumber":"1892",
    "addr:postcode":"11510",
    "addr:street":"Grand Ave North",
    "iso:country":"US",
    "sg:address":"1892 Grand Ave",
    "sg:city":"North Baldwin",
    "sg:classifiers":[
        {
            "category":"Building & Trades",
            "subcategory":"Plumbing",
            "type":"Services"
        }
    ],
    "sg:phone":"+1 516 868 2600",
    "sg:postcode":"11510",
    "sg:province":"NY",
    "sg:tags":[
        "heating",
        "contractor"
    ],
    "wof:name":"A & F Heating",
    "wof:placetype":"venue"
},
  "geometry": {"coordinates":[-73.608054,40.666436],"type":"Point"}
}