{
  "type": "Feature",
  "properties": {
    "addr:full":"239 E 88 St New York NY 10128",
    "addr:housenumber":"239;88",
    "addr:postcode":"10128",
    "addr:street":"E;St",
    "iso:country":"US",
    "sg:address":"239 E 88 St",
    "sg:city":"New York",
    "sg:classifiers":[
        {
            "category":"Wholesale",
            "subcategory":"Non-durable Goods",
            "type":"Manufacturing & Wholesale Goods"
        }
    ],
    "sg:phone":"+1 212 737 1742",
    "sg:postcode":"10128",
    "sg:province":"NY",
    "sg:tags":[
        "ice"
    ],
    "wof:name":"Armato Ice",
    "wof:placetype":"venue"
},
  "geometry": {"coordinates":[-73.951134,40.779455],"type":"Point"}
}