{
  "type": "Feature",
  "properties": {
    "iso:country":"US",
    "sg:address":"1691 Eden Evans Center Rd",
    "sg:city":"Angola",
    "sg:classifiers":[
        {
            "category":"Professional",
            "subcategory":"Management & Consulting",
            "type":"Services"
        }
    ],
    "sg:phone":"+1 716 549 5900",
    "sg:postcode":"14006",
    "sg:province":"NY",
    "sg:tags":[
        "consultant",
        "energy",
        "conservation",
        "business"
    ],
    "wof:name":"C M W Energy Utilizers Inc",
    "wof:placetype":"venue"
},
  "geometry": {"coordinates":[-78.97717900000001,42.652471],"type":"Point"}
}