{
  "type": "Feature",
  "properties": {
    "iso:country":"US",
    "sg:address":"49 White Cliff Ln",
    "sg:city":"Nesconset",
    "sg:classifiers":[
        {
            "category":"Manufacturing",
            "subcategory":"Electronics",
            "type":"Manufacturing & Wholesale Goods"
        }
    ],
    "sg:phone":"+1   ",
    "sg:postcode":"11767",
    "sg:province":"NY",
    "sg:tags":[
        "use",
        "wire",
        "assembly",
        "cable",
        "for",
        "harness",
        "or"
    ],
    "wof:name":"Paal Technologies Inc",
    "wof:placetype":"venue"
},
  "geometry": {"coordinates":[-73.132997,40.857031],"type":"Point"}
}