{
  "type": "Feature",
  "properties": {
    "addr:full":"4677 Alabama Rd Medina NY 14103",
    "addr:housenumber":"4677",
    "addr:postcode":"14103",
    "addr:street":"Alabama Rd",
    "iso:country":"US",
    "sg:address":"4677 Alabama Rd",
    "sg:city":"Medina",
    "sg:classifiers":[
        {
            "category":"Government",
            "subcategory":"Fire Station",
            "type":"Public Place"
        }
    ],
    "sg:phone":"+1 585 798 2015",
    "sg:postcode":"14103",
    "sg:province":"NY",
    "sg:tags":[
        "department"
    ],
    "wof:name":"Volunteer Fire Co",
    "wof:placetype":"venue"
},
  "geometry": {"coordinates":[-78.390502,43.186276],"type":"Point"}
}