{
  "type": "Feature",
  "properties": {
    "addr:full":"1500 Sunrise Hwy Copiague NY 11726",
    "addr:housenumber":"1500",
    "addr:postcode":"11726",
    "addr:street":"Sunrise Hwy",
    "iso:country":"US",
    "sg:address":"1500 Sunrise Hwy",
    "sg:city":"Copiague",
    "sg:classifiers":[
        {
            "category":"Food & Beverages",
            "subcategory":"Fruits & Vegetables",
            "type":"Retail Goods"
        }
    ],
    "sg:phone":"+1   ",
    "sg:postcode":"11726",
    "sg:province":"NY",
    "wof:name":"The Fruit Tree",
    "wof:placetype":"venue"
},
  "geometry": {"coordinates":[-73.397254,40.692578],"type":"Point"}
}