{
  "type": "Feature",
  "properties": {
    "addr:full":"5116 13th Ave Brooklyn NY 11219",
    "addr:housenumber":"5116",
    "addr:postcode":"11219",
    "addr:street":"13Th Ave",
    "iso:country":"US",
    "sg:address":"5116 13th Ave",
    "sg:city":"Brooklyn",
    "sg:classifiers":[
        {
            "category":"Shopping",
            "subcategory":"Clothing, Apparel, & Fashions",
            "type":"Retail Goods"
        }
    ],
    "sg:phone":"+1 718 435 7399",
    "sg:postcode":"11219",
    "sg:province":"NY",
    "wof:name":"Tiny Town Children's Wear",
    "wof:placetype":"venue"
},
  "geometry": {"coordinates":[-73.993853,40.633485],"type":"Point"}
}