{
  "type": "Feature",
  "properties": {
    "addr:full":"4 Nassau Blvd Garden City NY 11599",
    "addr:housenumber":"4",
    "addr:postcode":"11599",
    "addr:street":"Nassau Blvd",
    "iso:country":"US",
    "sg:address":"4 Nassau Blvd",
    "sg:city":"Garden City",
    "sg:classifiers":[
        {
            "category":"Professional",
            "type":"Services"
        },
        {
            "category":"Food & Beverages",
            "subcategory":"Meat & Fish",
            "type":"Retail Goods"
        }
    ],
    "sg:phone":"+1 516 505 3255",
    "sg:postcode":"11599",
    "sg:province":"NY",
    "sg:tags":[
        "shop",
        "caterer"
    ],
    "wof:name":"Prime Fine Catering",
    "wof:placetype":"venue"
},
  "geometry": {"coordinates":[-73.64057099999999,40.753475],"type":"Point"}
}