{
  "type": "Feature",
  "properties": {
    "addr:full":"177 Landon Ave Catskill NY 12414",
    "addr:housenumber":"177",
    "addr:postcode":"12414",
    "addr:street":"Landon Ave",
    "iso:country":"US",
    "sg:address":"177 Landon Ave",
    "sg:city":"Catskill",
    "sg:classifiers":[
        {
            "category":"Retail",
            "subcategory":"Auto Repair",
            "type":"Services"
        }
    ],
    "sg:phone":"+1   ",
    "sg:postcode":"12414",
    "sg:province":"NY",
    "sg:tags":[
        "general"
    ],
    "wof:name":"Schindler Automotive",
    "wof:placetype":"venue"
},
  "geometry": {"coordinates":[-73.879299,42.209647],"type":"Point"}
}