{
  "type": "Feature",
  "properties": {
    "addr:full":"58 Dutchess Ave Staten Island NY 10304",
    "addr:housenumber":"58",
    "addr:postcode":"10304",
    "addr:street":"Dutchess Ave",
    "iso:country":"US",
    "sg:address":"58 Dutchess Ave",
    "sg:city":"Staten Island",
    "sg:classifiers":[
        {
            "category":"Food & Beverages",
            "subcategory":"Specialty",
            "type":"Retail Goods"
        }
    ],
    "sg:phone":"+1 718 667 0028",
    "sg:postcode":"10304",
    "sg:province":"NY",
    "sg:tags":[
        "distributor",
        "drink",
        "soft",
        "private",
        "label"
    ],
    "wof:name":"My Sodas Inc",
    "wof:placetype":"venue"
},
  "geometry": {"coordinates":[-74.097869,40.597072],"type":"Point"}
}