{
  "type": "Feature",
  "properties": {
    "iso:country":"US",
    "sg:address":"23 Sampson Pl",
    "sg:city":"Lindenhurst",
    "sg:classifiers":[
        {
            "category":"Building & Trades",
            "subcategory":"Construction",
            "type":"Services"
        }
    ],
    "sg:phone":"+1 631 225 6105",
    "sg:postcode":"11757",
    "sg:province":"NY",
    "sg:tags":[
        "hanging",
        "contractor"
    ],
    "wof:name":"Prime Seal Coatings",
    "wof:placetype":"venue"
},
  "geometry": {"coordinates":[-73.358023,40.677786],"type":"Point"}
}