{
  "type": "Feature",
  "properties": {
    "iso:country":"US",
    "sg:address":"551 Amsterdam Ave",
    "sg:city":"New York",
    "sg:classifiers":[
        {
            "category":"Cafe",
            "type":"Food & Drink"
        },
        {
            "category":"Restaurant",
            "type":"Food & Drink"
        }
    ],
    "sg:menulink":"http://www.allmenus.com/ny/new-york/2352-popover-cafe/menu/",
    "sg:phone":"+1 212 595 8555",
    "sg:postcode":"10024",
    "sg:province":"NY",
    "sg:tags":[
        "american"
    ],
    "wof:name":"Popover Cafe",
    "wof:placetype":"venue"
},
  "geometry": {"coordinates":[-73.97461199999999,40.78824],"type":"Point"}
}