{
  "type": "Feature",
  "properties": {
    "iso:country":"US",
    "sg:address":"2696 Sheridan Dr",
    "sg:city":"Tonawanda",
    "sg:classifiers":[
        {
            "category":"Professional",
            "subcategory":"Lawyer & Legal Services",
            "type":"Services"
        }
    ],
    "sg:phone":"+1 716 693 4529",
    "sg:postcode":"14150",
    "sg:province":"NY",
    "sg:tags":[
        "law"
    ],
    "wof:name":"Horwitz & Frankel",
    "wof:placetype":"venue"
},
  "geometry": {"coordinates":[-78.836046,42.980822],"type":"Point"}
}