{
  "type": "Feature",
  "properties": {
    "iso:country":"US",
    "sg:address":"390 Everit Ave",
    "sg:city":"Hewlett",
    "sg:classifiers":[
        {
            "category":"Wholesale",
            "subcategory":"Non-durable Goods",
            "type":"Manufacturing & Wholesale Goods"
        }
    ],
    "sg:phone":"+1 516 569 6823",
    "sg:postcode":"11557",
    "sg:province":"NY",
    "wof:name":"Hitek Promotions Inc",
    "wof:placetype":"venue"
},
  "geometry": {"coordinates":[-73.676648,40.636956],"type":"Point"}
}