{
  "type": "Feature",
  "properties": {
    "addr:full":"8460 Oak Hill Rd Arkport NY 14807",
    "addr:housenumber":"8460",
    "addr:postcode":"14807",
    "addr:street":"Oak Hill Rd",
    "iso:country":"US",
    "sg:address":"8460 Oak Hill Rd",
    "sg:city":"Arkport",
    "sg:classifiers":[
        {
            "category":"Wholesale",
            "subcategory":"Office Equipment",
            "type":"Manufacturing & Wholesale Goods"
        }
    ],
    "sg:phone":"+1 607 295 7367",
    "sg:postcode":"14807",
    "sg:province":"NY",
    "sg:tags":[
        "equipment-installation",
        "furniture"
    ],
    "sg:website":"http://www.cranetechinc.com",
    "wof:name":"Cranetech, Inc.",
    "wof:placetype":"venue"
},
  "geometry": {"coordinates":[-77.687602,42.413323],"type":"Point"}
}