{
  "type": "Feature",
  "properties": {
    "addr:full":"571 W 183rd Street New York NY 10033",
    "addr:housenumber":"571",
    "addr:postcode":"10033",
    "addr:street":"W 183Rd Street",
    "iso:country":"US",
    "sg:address":"571 W 183rd Street",
    "sg:city":"New York",
    "sg:classifiers":[
        {
            "category":"Building & Trades",
            "subcategory":"Construction",
            "type":"Services"
        }
    ],
    "sg:phone":"+1 212 568 6600",
    "sg:postcode":"10033",
    "sg:province":"NY",
    "sg:tags":[
        "contractor"
    ],
    "wof:name":"Ortega Group",
    "wof:placetype":"venue"
},
  "geometry": {"coordinates":[-73.932756,40.850348],"type":"Point"}
}