{
  "type": "Feature",
  "properties": {
    "iso:country":"US",
    "sg:address":"57 Temple St",
    "sg:city":"Fredonia",
    "sg:classifiers":[
        {
            "category":"Real Estate",
            "subcategory":"Real Estate Agent",
            "type":"Services"
        }
    ],
    "sg:phone":"+1 716 672 7222",
    "sg:postcode":"14063",
    "sg:province":"NY",
    "sg:tags":[
        "school"
    ],
    "wof:name":"Northern Chautauqua Realty",
    "wof:placetype":"venue"
},
  "geometry": {"coordinates":[-79.334526,42.442087],"type":"Point"}
}