{
  "type": "Feature",
  "properties": {
    "iso:country":"US",
    "sg:address":"738 Broadway",
    "sg:city":"New York",
    "sg:classifiers":[
        {
            "category":"Cinema",
            "subcategory":"Movie Rental",
            "type":"Entertainment"
        }
    ],
    "sg:phone":"+1 212 529 8204",
    "sg:postcode":"10003",
    "sg:province":"NY",
    "sg:tags":[
        "leasing",
        "video",
        "disc",
        "tape"
    ],
    "wof:name":"DV8 Video Inc",
    "wof:placetype":"venue"
},
  "geometry": {"coordinates":[-73.992937,40.729789],"type":"Point"}
}