{
  "type": "Feature",
  "properties": {
    "iso:country":"US",
    "sg:address":"2070 Jericho Tpke",
    "sg:city":"New Hyde Park",
    "sg:classifiers":[
        {
            "category":"Autos & Motor Vehicles",
            "subcategory":"Motorcycle Sales",
            "type":"Retail Goods"
        }
    ],
    "sg:phone":"+1 516 352 7474",
    "sg:postcode":"11040",
    "sg:province":"NY",
    "sg:website":"www.goldcoast-motorsports.com",
    "wof:name":"Gold Coast Motorsports",
    "wof:placetype":"venue"
},
  "geometry": {"coordinates":[-73.674896,40.7351],"type":"Point"}
}