{
  "type": "Feature",
  "properties": {
    "addr:full":"49 N Front St Kingston NY 12401",
    "addr:housenumber":"49",
    "addr:postcode":"12401",
    "addr:street":"N Front St",
    "iso:country":"US",
    "sg:address":"49 N Front St",
    "sg:city":"Kingston",
    "sg:classifiers":[
        {
            "category":"Personal",
            "subcategory":"Beauty Salon",
            "type":"Services"
        }
    ],
    "sg:phone":"+1 845 339 6323",
    "sg:postcode":"12401",
    "sg:province":"NY",
    "wof:name":"Village Nails",
    "wof:placetype":"venue"
},
  "geometry": {"coordinates":[-74.020611,41.93519],"type":"Point"}
}