{
  "type": "Feature",
  "properties": {
    "iso:country":"US",
    "sg:address":"68 Soundview Ave",
    "sg:city":"Rye",
    "sg:classifiers":[
        {
            "category":"Professional",
            "subcategory":"Management & Consulting",
            "type":"Services"
        }
    ],
    "sg:phone":"+1 914 835 7993",
    "sg:postcode":"10580",
    "sg:province":"NY",
    "wof:name":"Emerging Market Management",
    "wof:placetype":"venue"
},
  "geometry": {"coordinates":[-73.69886700000001,40.961256],"type":"Point"}
}