{
  "type": "Feature",
  "properties": {
    "iso:country":"US",
    "sg:address":"504 E 3rd St",
    "sg:city":"Mount Vernon",
    "sg:classifiers":[
        {
            "category":"Wholesale",
            "subcategory":"Auto Parts",
            "type":"Manufacturing & Wholesale Goods"
        }
    ],
    "sg:phone":"+1 914 664 4200",
    "sg:postcode":"10553",
    "sg:province":"NY",
    "sg:tags":[
        "body",
        "automotive",
        "supply",
        "shop",
        "automobile"
    ],
    "wof:name":"A R C Auto Body Supplies",
    "wof:placetype":"venue"
},
  "geometry": {"coordinates":[-73.817269,40.908389],"type":"Point"}
}