{
  "type": "Feature",
  "properties": {
    "iso:country":"US",
    "sg:address":"4705 Rustic Ln",
    "sg:city":"Manlius",
    "sg:classifiers":[
        {
            "category":"Manufacturing",
            "subcategory":"Paper Products",
            "type":"Manufacturing & Wholesale Goods"
        }
    ],
    "sg:phone":"+1 315 682 6340",
    "sg:postcode":"13104",
    "sg:province":"NY",
    "sg:tags":[
        "products-wholesale",
        "manufacturer"
    ],
    "wof:name":"Fournier Group",
    "wof:placetype":"venue"
},
  "geometry": {"coordinates":[-75.92826100000001,42.999234],"type":"Point"}
}