{
  "type": "Feature",
  "properties": {
    "addr:full":"127 Fordham Rd Valatie NY 12184",
    "addr:housenumber":"127",
    "addr:postcode":"12184",
    "addr:street":"Fordham Rd",
    "iso:country":"US",
    "sg:address":"127 Fordham Rd",
    "sg:city":"Valatie",
    "sg:classifiers":[
        {
            "category":"Professional",
            "subcategory":"Engineering",
            "type":"Services"
        }
    ],
    "sg:phone":"+1 518 758 7500",
    "sg:postcode":"12184",
    "sg:province":"NY",
    "sg:tags":[
        "engineer"
    ],
    "wof:name":"Patrick J Prendergast Consutin",
    "wof:placetype":"venue"
},
  "geometry": {"coordinates":[-73.70415800000001,42.431827],"type":"Point"}
}