{
  "type": "Feature",
  "properties": {
    "addr:full":"253 E 62nd Street New York NY 10021",
    "addr:housenumber":"253",
    "addr:postcode":"10021",
    "addr:street":"E 62Nd Street",
    "iso:country":"US",
    "sg:address":"253 E 62nd Street",
    "sg:city":"New York",
    "sg:classifiers":[
        {
            "category":"Shopping",
            "subcategory":"Florist",
            "type":"Retail Goods"
        }
    ],
    "sg:phone":"+1 212 355 4557",
    "sg:postcode":"10021",
    "sg:province":"NY",
    "wof:name":"Flowers",
    "wof:placetype":"venue"
},
  "geometry": {"coordinates":[-73.96414,40.762988],"type":"Point"}
}