{
  "type": "Feature",
  "properties": {
    "addr:full":"70 Bowery New York NY 10013",
    "addr:housenumber":"70",
    "addr:postcode":"10013",
    "addr:street":"Bowery",
    "iso:country":"US",
    "sg:address":"70 Bowery",
    "sg:city":"New York",
    "sg:classifiers":[
        {
            "category":"Wholesale",
            "subcategory":"Jewelry",
            "type":"Manufacturing & Wholesale Goods"
        }
    ],
    "sg:phone":"+1 212 431 9260",
    "sg:postcode":"10013",
    "sg:province":"NY",
    "sg:tags":[
        "jeweler"
    ],
    "wof:name":"Kreidman Diamond Co",
    "wof:placetype":"venue"
},
  "geometry": {"coordinates":[-73.995649,40.716977],"type":"Point"}
}