{
  "type": "Feature",
  "properties": {
    "iso:country":"US",
    "sg:address":"40 Schoharie Ct",
    "sg:city":"Jericho",
    "sg:classifiers":[
        {
            "category":"Manufacturing",
            "subcategory":"Jewelry",
            "type":"Manufacturing & Wholesale Goods"
        }
    ],
    "sg:phone":"+1 516 433 4326",
    "sg:postcode":"11753",
    "sg:province":"NY",
    "sg:tags":[
        "stone",
        "manufacturer",
        "jewelers-wholesale",
        "jewels-imitation"
    ],
    "sg:website":"http://www.jeweline.com",
    "wof:name":"Jeweline Inc",
    "wof:placetype":"venue"
},
  "geometry": {"coordinates":[-73.53841300000001,40.789717],"type":"Point"}
}