{
  "type": "Feature",
  "properties": {
    "iso:country":"US",
    "sg:address":"285 E Main St",
    "sg:city":"Smithtown",
    "sg:classifiers":[
        {
            "category":"Health Services",
            "subcategory":"Doctor",
            "type":"Services"
        }
    ],
    "sg:phone":"+1   ",
    "sg:postcode":"11787",
    "sg:province":"NY",
    "wof:name":"Berman Stuart A DDS",
    "wof:placetype":"venue"
},
  "geometry": {"coordinates":[-73.182693,40.856124],"type":"Point"}
}