{
  "type": "Feature",
  "properties": {
    "iso:country":"US",
    "sg:address":"324 Powell Ave",
    "sg:city":"Newburgh",
    "sg:classifiers":[
        {
            "category":"Home & Garden",
            "subcategory":"Household Appliances",
            "type":"Retail Goods"
        }
    ],
    "sg:phone":"+1 212 996 0820",
    "sg:postcode":"12550",
    "sg:province":"NY",
    "sg:tags":[
        "refrigerator",
        "freezer"
    ],
    "wof:name":"Metropolitan Refrigeration",
    "wof:placetype":"venue"
},
  "geometry": {"coordinates":[-74.014516,41.515483],"type":"Point"}
}