{
  "type": "Feature",
  "properties": {
    "addr:full":"270 Anderson Ave Rochester NY 14607",
    "addr:housenumber":"270",
    "addr:postcode":"14607",
    "addr:street":"Anderson Ave",
    "iso:country":"US",
    "sg:address":"270 Anderson Ave",
    "sg:city":"Rochester",
    "sg:classifiers":[
        {
            "category":"Retail",
            "subcategory":"Auto Repair",
            "type":"Services"
        }
    ],
    "sg:phone":"+1   ",
    "sg:postcode":"14607",
    "sg:province":"NY",
    "sg:tags":[
        "body"
    ],
    "wof:name":"Tony S Collision Inc",
    "wof:placetype":"venue"
},
  "geometry": {"coordinates":[-77.579689,43.157541],"type":"Point"}
}