{
  "type": "Feature",
  "properties": {
    "iso:country":"US",
    "sg:address":"32 Main St",
    "sg:city":"Geneseo",
    "sg:classifiers":[
        {
            "category":"Professional",
            "subcategory":"Lawyer & Legal Services",
            "type":"Services"
        }
    ],
    "sg:phone":"+1 585 243 4320",
    "sg:postcode":"14454",
    "sg:province":"NY",
    "sg:tags":[
        "attorney"
    ],
    "wof:name":"Robert A Presutti Law Office",
    "wof:placetype":"venue"
},
  "geometry": {"coordinates":[-77.816496,42.797572],"type":"Point"}
}