{
  "type": "Feature",
  "properties": {
    "addr:full":"87 E Bethpage Rd Plainview NY 11803",
    "addr:housenumber":"87",
    "addr:postcode":"11803",
    "addr:street":"E Bethpage Rd",
    "iso:country":"US",
    "sg:address":"87 E Bethpage Rd",
    "sg:city":"Plainview",
    "sg:classifiers":[
        {
            "category":"Wholesale",
            "subcategory":"Electrical",
            "type":"Manufacturing & Wholesale Goods"
        }
    ],
    "sg:phone":"+1 516 756 7100",
    "sg:postcode":"11803",
    "sg:province":"NY",
    "sg:tags":[
        "equipment",
        "electronic",
        "supply"
    ],
    "wof:name":"Diplomat Electronics Inc",
    "wof:placetype":"venue"
},
  "geometry": {"coordinates":[-73.455866,40.784833],"type":"Point"}
}