{
  "type": "Feature",
  "properties": {
    "addr:full":"74 Ovid St Seneca Falls NY 13148",
    "addr:housenumber":"74",
    "addr:postcode":"13148",
    "addr:street":"Ovid St",
    "iso:country":"US",
    "sg:address":"74 Ovid St",
    "sg:city":"Seneca Falls",
    "sg:classifiers":[
        {
            "category":"Shopping",
            "type":"Retail Goods"
        }
    ],
    "sg:phone":"+1 315 568 5026",
    "sg:postcode":"13148",
    "sg:province":"NY",
    "sg:tags":[
        "picture",
        "frame"
    ],
    "wof:name":"Judy's Mirror & Glass",
    "wof:placetype":"venue"
},
  "geometry": {"coordinates":[-76.797506,42.90551],"type":"Point"}
}