{
  "type": "Feature",
  "properties": {
    "addr:full":"628 Courtlandt Ave Bronx NY 10451",
    "addr:housenumber":"628",
    "addr:postcode":"10451",
    "addr:street":"Courtlandt Ave",
    "iso:country":"US",
    "sg:address":"628 Courtlandt Ave",
    "sg:city":"Bronx",
    "sg:classifiers":[
        {
            "category":"Restaurant",
            "type":"Food & Drink"
        }
    ],
    "sg:menulink":"http://www.allmenus.com/ny/bronx/59297-new-kin-wah-chinese-restaurant/menu/",
    "sg:phone":"+1 718 585 9095",
    "sg:postcode":"10451",
    "sg:province":"NY",
    "sg:tags":[
        "asian",
        "chinese"
    ],
    "wof:name":"New Kin Wah Chinese Restaurant",
    "wof:placetype":"venue"
},
  "geometry": {"coordinates":[-73.918685,40.818451],"type":"Point"}
}