{
  "type": "Feature",
  "properties": {
    "addr:full":"222 E 46th St New York NY 10017",
    "addr:housenumber":"222",
    "addr:postcode":"10017",
    "addr:street":"E 46Th St",
    "iso:country":"US",
    "sg:address":"222 E 46th St",
    "sg:city":"New York",
    "sg:classifiers":[
        {
            "category":"Professional",
            "type":"Services"
        }
    ],
    "sg:phone":"+1 212 661 8810",
    "sg:postcode":"10017",
    "sg:province":"NY",
    "sg:tags":[
        "establishment"
    ],
    "wof:name":"Dupler Group Inc",
    "wof:placetype":"venue"
},
  "geometry": {"coordinates":[-73.970759,40.752524],"type":"Point"}
}