{
  "type": "Feature",
  "properties": {
    "addr:full":"36 Howard Ave Brooklyn NY 11221",
    "addr:housenumber":"36",
    "addr:postcode":"11221",
    "addr:street":"Howard Ave",
    "iso:country":"US",
    "sg:address":"36 Howard Ave",
    "sg:city":"Brooklyn",
    "sg:classifiers":[
        {
            "category":"Food & Beverages",
            "subcategory":"Groceries & Convenience Stores",
            "type":"Retail Goods"
        }
    ],
    "sg:phone":"+1 718 804 1557",
    "sg:postcode":"11221",
    "sg:province":"NY",
    "wof:name":"Cmen Food Corp",
    "wof:placetype":"venue"
},
  "geometry": {"coordinates":[-73.921097,40.687698],"type":"Point"}
}