{
  "type": "Feature",
  "properties": {
    "addr:full":"134 Greene St New York NY 10012",
    "addr:housenumber":"134",
    "addr:postcode":"10012",
    "addr:street":"Greene St",
    "iso:country":"US",
    "sg:address":"134 Greene St",
    "sg:city":"New York",
    "sg:classifiers":[
        {
            "category":"Real Estate",
            "subcategory":"Architect",
            "type":"Services"
        }
    ],
    "sg:phone":"+1 212 343 0542",
    "sg:postcode":"10012",
    "sg:province":"NY",
    "wof:name":"B&R Projection",
    "wof:placetype":"venue"
},
  "geometry": {"coordinates":[-73.99839900000001,40.725971],"type":"Point"}
}