{
  "type": "Feature",
  "properties": {
    "iso:country":"US",
    "sg:address":"185 Hale Rd",
    "sg:city":"Norwich",
    "sg:classifiers":[
        {
            "category":"Professional",
            "subcategory":"Art Services",
            "type":"Services"
        }
    ],
    "sg:phone":"+1   ",
    "sg:postcode":"13815",
    "sg:province":"NY",
    "sg:tags":[
        "commercial",
        "design"
    ],
    "wof:name":"Advanced Graphics",
    "wof:placetype":"venue"
},
  "geometry": {"coordinates":[-75.543183,42.545305],"type":"Point"}
}