{
  "type": "Feature",
  "properties": {
    "addr:full":"64 5th St New Hyde Park NY 11040",
    "addr:housenumber":"64",
    "addr:postcode":"11040",
    "addr:street":"5Th St",
    "iso:country":"US",
    "sg:address":"64 5th St",
    "sg:city":"New Hyde Park",
    "sg:classifiers":[
        {
            "category":"Building & Trades",
            "subcategory":"Electrical",
            "type":"Services"
        }
    ],
    "sg:phone":"+1 516 739 5345",
    "sg:postcode":"11040",
    "sg:province":"NY",
    "sg:tags":[
        "electrician"
    ],
    "wof:name":"R & S Elec Svce",
    "wof:placetype":"venue"
},
  "geometry": {"coordinates":[-73.666298,40.743401],"type":"Point"}
}