{
  "type": "Feature",
  "properties": {
    "iso:country":"US",
    "sg:address":"451 Mount Merino Rd",
    "sg:city":"Hudson",
    "sg:classifiers":[
        {
            "category":"Shopping",
            "subcategory":"Gifts & Souvenirs",
            "type":"Retail Goods"
        }
    ],
    "sg:phone":"+1 845 876 4800",
    "sg:postcode":"12534",
    "sg:province":"NY",
    "sg:tags":[
        "collectible"
    ],
    "wof:name":"Old Post Miniatures",
    "wof:placetype":"venue"
},
  "geometry": {"coordinates":[-73.827665,42.227861],"type":"Point"}
}