{
  "type": "Feature",
  "properties": {
    "iso:country":"US",
    "sg:address":"76 Hudson Watch Dr",
    "sg:city":"Ossining",
    "sg:classifiers":[
        {
            "category":"Professional",
            "subcategory":"Engineering",
            "type":"Services"
        }
    ],
    "sg:phone":"+1   ",
    "sg:postcode":"10562",
    "sg:province":"NY",
    "wof:name":"John V DAquino Pe",
    "wof:placetype":"venue"
},
  "geometry": {"coordinates":[-73.86262000000001,41.176073],"type":"Point"}
}