{
  "type": "Feature",
  "properties": {
    "addr:full":"483 10th Ave New York NY 10018",
    "addr:housenumber":"483",
    "addr:postcode":"10018",
    "addr:street":"10Th Ave",
    "iso:country":"US",
    "sg:address":"483 10th Ave",
    "sg:city":"New York",
    "sg:classifiers":[
        {
            "category":"Professional",
            "subcategory":"Advertising",
            "type":"Services"
        }
    ],
    "sg:phone":"+1 212 660 2400",
    "sg:postcode":"10018",
    "sg:province":"NY",
    "sg:tags":[
        "marketing"
    ],
    "sg:website":"www.aimediagroup.com/",
    "wof:name":"Ai Media Group",
    "wof:placetype":"venue"
},
  "geometry": {"coordinates":[-73.99780199999999,40.756459],"type":"Point"}
}