{
  "type": "Feature",
  "properties": {
    "addr:full":"342 Sycamore St East Aurora NY 14052",
    "addr:housenumber":"342",
    "addr:postcode":"14052",
    "addr:street":"Sycamore St",
    "iso:country":"US",
    "sg:address":"342 Sycamore St",
    "sg:city":"East Aurora",
    "sg:classifiers":[
        {
            "category":"Real Estate",
            "subcategory":"Real Estate Agent",
            "type":"Services"
        }
    ],
    "sg:phone":"+1 716 652 1785",
    "sg:postcode":"14052",
    "sg:province":"NY",
    "wof:name":"Aubrey Leonard Realty",
    "wof:placetype":"venue"
},
  "geometry": {"coordinates":[-78.61465699999999,42.757833],"type":"Point"}
}