{
  "type": "Feature",
  "properties": {
    "addr:full":"125 Buffalo Ave Medford NY 11763",
    "addr:housenumber":"125",
    "addr:postcode":"11763",
    "addr:street":"Buffalo Ave",
    "iso:country":"US",
    "sg:address":"125 Buffalo Ave",
    "sg:city":"Medford",
    "sg:classifiers":[
        {
            "category":"Wholesale",
            "subcategory":"Office Equipment",
            "type":"Manufacturing & Wholesale Goods"
        }
    ],
    "sg:phone":"+1 631 758 1955",
    "sg:postcode":"11763",
    "sg:province":"NY",
    "sg:tags":[
        "blueprinting",
        "supply"
    ],
    "wof:name":"RHE Svc Co",
    "wof:placetype":"venue"
},
  "geometry": {"coordinates":[-72.988907,40.799558],"type":"Point"}
}