{
  "type": "Feature",
  "properties": {
    "iso:country":"US",
    "sg:address":"2373 State Hwy 69",
    "sg:city":"Camden",
    "sg:classifiers":[
        {
            "category":"Building & Trades",
            "subcategory":"Construction",
            "type":"Services"
        }
    ],
    "sg:phone":"+1 315 245 0370",
    "sg:postcode":"13316",
    "sg:province":"NY",
    "sg:tags":[
        "excavation",
        "snowplowing",
        "local",
        "contractor"
    ],
    "wof:name":"Stace Backhoe & Trucking Inc",
    "wof:placetype":"venue"
},
  "geometry": {"coordinates":[-75.73298,43.333474],"type":"Point"}
}