{
  "type": "Feature",
  "properties": {
    "addr:full":"532 W 145th St New York NY 10031",
    "addr:housenumber":"532",
    "addr:postcode":"10031",
    "addr:street":"W 145Th St",
    "iso:country":"US",
    "sg:address":"532 W 145th St",
    "sg:city":"New York",
    "sg:classifiers":[
        {
            "category":"Personal",
            "subcategory":"Beauty Salon",
            "type":"Services"
        }
    ],
    "sg:phone":"+1 212 283 8532",
    "sg:postcode":"10031",
    "sg:province":"NY",
    "wof:name":"Cora's Beauty Salon",
    "wof:placetype":"venue"
},
  "geometry": {"coordinates":[-73.94978500000001,40.825973],"type":"Point"}
}