{
  "type": "Feature",
  "properties": {
    "addr:full":"8 Woods Xing Glen Head NY 11545",
    "addr:housenumber":"8",
    "addr:postcode":"11545",
    "addr:street":"Woods Xing Glen Head",
    "iso:country":"US",
    "sg:address":"8 Woods Xing",
    "sg:city":"Glen Head",
    "sg:classifiers":[
        {
            "category":"Farming",
            "subcategory":"Farm",
            "type":"Manufacturing & Wholesale Goods"
        }
    ],
    "sg:phone":"+1 516 626 1425",
    "sg:postcode":"11545",
    "sg:province":"NY",
    "sg:tags":[
        "crop",
        "general"
    ],
    "wof:name":"R&I Farms",
    "wof:placetype":"venue"
},
  "geometry": {"coordinates":[-73.57275,40.810065],"type":"Point"}
}