{
  "type": "Feature",
  "properties": {
    "addr:full":"45 1st Ave New York NY 10003",
    "addr:housenumber":"45",
    "addr:postcode":"10003",
    "addr:street":"1St Ave",
    "iso:country":"US",
    "sg:address":"45 1st Ave",
    "sg:city":"New York",
    "sg:classifiers":[
        {
            "category":"Autos & Motor Vehicles",
            "subcategory":"Automobile Sales",
            "type":"Retail Goods"
        }
    ],
    "sg:phone":"+1 212 777 1008",
    "sg:postcode":"10003",
    "sg:province":"NY",
    "sg:tags":[
        "limo"
    ],
    "wof:name":"Spirit Limousine Inc",
    "wof:placetype":"venue"
},
  "geometry": {"coordinates":[-73.987634,40.724662],"type":"Point"}
}