{
  "type": "Feature",
  "properties": {
    "iso:country":"US",
    "sg:address":"302 E Fordham Rd",
    "sg:city":"Bronx",
    "sg:classifiers":[
        {
            "category":"Shopping",
            "type":"Retail Goods"
        }
    ],
    "sg:phone":"+1 718 562 7089",
    "sg:postcode":"10458",
    "sg:province":"NY",
    "sg:tags":[
        "telephone",
        "cellular"
    ],
    "wof:name":"Two Mobile",
    "wof:placetype":"venue"
},
  "geometry": {"coordinates":[-73.893793,40.861878],"type":"Point"}
}