{
  "type": "Feature",
  "properties": {
    "addr:full":"3100 Ocean Pkwy Brooklyn NY 11235",
    "addr:housenumber":"3100",
    "addr:postcode":"11235",
    "addr:street":"Ocean Pkwy",
    "iso:country":"US",
    "sg:address":"3100 Ocean Pkwy",
    "sg:city":"Brooklyn",
    "sg:classifiers":[
        {
            "category":"Food & Beverages",
            "subcategory":"Groceries & Convenience Stores",
            "type":"Retail Goods"
        }
    ],
    "sg:phone":"+1 718 373 1515",
    "sg:postcode":"11235",
    "sg:province":"NY",
    "wof:name":"Royal Seafood",
    "wof:placetype":"venue"
},
  "geometry": {"coordinates":[-73.969353,40.575876],"type":"Point"}
}