{
  "type": "Feature",
  "properties": {
    "addr:full":"230 Renwick Dr Ithaca NY 14850",
    "addr:housenumber":"230",
    "addr:postcode":"14850",
    "addr:street":"Renwick Dr",
    "iso:country":"US",
    "sg:address":"230 Renwick Dr",
    "sg:city":"Ithaca",
    "sg:classifiers":[
        {
            "category":"Social Services",
            "type":"Services"
        }
    ],
    "sg:phone":"+1 607 273 1000",
    "sg:postcode":"14850",
    "sg:province":"NY",
    "sg:tags":[
        "worker"
    ],
    "wof:name":"Helene M Eberts",
    "wof:placetype":"venue"
},
  "geometry": {"coordinates":[-76.495002,42.461498],"type":"Point"}
}