{
  "type": "Feature",
  "properties": {
    "iso:country":"US",
    "sg:address":"8055 Victor-Pittsford Rd",
    "sg:city":"Victor",
    "sg:classifiers":[
        {
            "category":"Home & Garden",
            "subcategory":"Building Materials",
            "type":"Retail Goods"
        }
    ],
    "sg:phone":"+1   ",
    "sg:postcode":"14564",
    "sg:province":"NY",
    "sg:tags":[
        "lumber"
    ],
    "sg:website":"www.84lumber.com",
    "wof:name":"84 Lumber",
    "wof:placetype":"venue"
},
  "geometry": {"coordinates":[-77.442866,43.033106],"type":"Point"}
}