{
  "type": "Feature",
  "properties": {
    "addr:full":"1285 Avenue of the Americ New York NY 10019",
    "addr:housenumber":"1285",
    "addr:postcode":"10019",
    "addr:street":"Avenue Of The",
    "iso:country":"US",
    "sg:address":"1285 Avenue of the Americ",
    "sg:city":"New York",
    "sg:classifiers":[
        {
            "category":"Professional",
            "subcategory":"Lawyer & Legal Services",
            "type":"Services"
        }
    ],
    "sg:phone":"+1 212 373 3028",
    "sg:postcode":"10019",
    "sg:province":"NY",
    "wof:name":"Chen Peggy Lwyr",
    "wof:placetype":"venue"
},
  "geometry": {"coordinates":[-73.97995899999999,40.760601],"type":"Point"}
}