{
  "type": "Feature",
  "properties": {
    "addr:full":"4608 Kennison Pkwy Hamburg NY 14075",
    "addr:housenumber":"4608",
    "addr:postcode":"14075",
    "addr:street":"Kennison Pkwy",
    "iso:country":"US",
    "sg:address":"4608 Kennison Pkwy",
    "sg:city":"Hamburg",
    "sg:classifiers":[
        {
            "category":"Building & Trades",
            "subcategory":"Construction",
            "type":"Services"
        }
    ],
    "sg:phone":"+1 716 627 4605",
    "sg:postcode":"14075",
    "sg:province":"NY",
    "sg:tags":[
        "contractor"
    ],
    "wof:name":"Timothy J Barry Siding Co",
    "wof:placetype":"venue"
},
  "geometry": {"coordinates":[-78.879913,42.760698],"type":"Point"}
}