{
  "type": "Feature",
  "properties": {
    "addr:full":"594 State Hwy 299 Highland NY 12528",
    "addr:housenumber":"594",
    "addr:postcode":"12528",
    "addr:street":"State Hwy 299",
    "iso:country":"US",
    "sg:address":"594 State Hwy 299",
    "sg:city":"Highland",
    "sg:classifiers":[
        {
            "category":"Organizations",
            "subcategory":"Labor Organization",
            "type":"Services"
        }
    ],
    "sg:phone":"+1 845 883 6418",
    "sg:postcode":"12528",
    "sg:province":"NY",
    "sg:tags":[
        "union"
    ],
    "wof:name":"Service Employees Intl Union",
    "wof:placetype":"venue"
},
  "geometry": {"coordinates":[-74.035495,41.73795],"type":"Point"}
}