{
  "type": "Feature",
  "properties": {
    "iso:country":"US",
    "sg:address":"300 Community Dr",
    "sg:city":"Manhasset",
    "sg:classifiers":[
        {
            "category":"Health Services",
            "subcategory":"Doctor",
            "type":"Services"
        }
    ],
    "sg:phone":"+1 516 562 4865",
    "sg:postcode":"11030",
    "sg:province":"NY",
    "sg:tags":[
        "physician",
        "family",
        "practice",
        "surgeons",
        "medicine",
        "surgeon"
    ],
    "wof:name":"Leitman Michael I Md",
    "wof:placetype":"venue"
},
  "geometry": {"coordinates":[-73.703087,40.779491],"type":"Point"}
}