{
  "type": "Feature",
  "properties": {
    "iso:country":"US",
    "sg:address":"500 Bradley Hill Rd",
    "sg:city":"Blauvelt",
    "sg:classifiers":[
        {
            "category":"Wholesale",
            "subcategory":"Machinery & Supplies",
            "type":"Manufacturing & Wholesale Goods"
        }
    ],
    "sg:phone":"+1 845 353 5042",
    "sg:postcode":"10913",
    "sg:province":"NY",
    "sg:tags":[
        "construction"
    ],
    "wof:name":"Heatherdell Equipment Corp",
    "wof:placetype":"venue"
},
  "geometry": {"coordinates":[-73.95423,41.075747],"type":"Point"}
}