{
  "type": "Feature",
  "properties": {
    "addr:full":"316 W 34th St Manhattan NY 10001",
    "addr:housenumber":"316",
    "addr:postcode":"10001",
    "addr:street":"W 34Th St",
    "iso:country":"US",
    "sg:address":"316 W 34th St",
    "sg:city":"Manhattan",
    "sg:classifiers":[
        {
            "category":"Fast Food",
            "type":"Food & Drink"
        }
    ],
    "sg:phone":"+1 212 564 6115",
    "sg:postcode":"10001",
    "sg:province":"NY",
    "sg:tags":[
        "burger"
    ],
    "sg:website":"www.fiveguys.com",
    "wof:name":"Five Guys Famous Burgers and Fries",
    "wof:placetype":"venue"
},
  "geometry": {"coordinates":[-73.994449,40.752586],"type":"Point"}
}