{
  "type": "Feature",
  "properties": {
    "addr:full":"730 Bryant Avenue Bronx NY 10474",
    "addr:housenumber":"730",
    "addr:postcode":"10474",
    "addr:street":"Bryant Avenue",
    "iso:country":"US",
    "sg:address":"730 Bryant Avenue",
    "sg:city":"Bronx",
    "sg:classifiers":[
        {
            "category":"Education",
            "subcategory":"School",
            "type":"Public Place"
        }
    ],
    "sg:phone":"+1 718 991 5500",
    "sg:postcode":"10474",
    "sg:province":"NY",
    "sg:tags":[
        "high",
        "middle"
    ],
    "wof:name":"Hyde Leadership Charter School",
    "wof:placetype":"venue"
},
  "geometry": {"coordinates":[-73.88552199999999,40.815028],"type":"Point"}
}