{
  "type": "Feature",
  "properties": {
    "iso:country":"US",
    "sg:address":"16010 Morris Tract Rd",
    "sg:city":"Chaumont",
    "sg:classifiers":[
        {
            "category":"Shopping",
            "subcategory":"Florist",
            "type":"Retail Goods"
        }
    ],
    "sg:phone":"+1 315 649 5922",
    "sg:postcode":"13622",
    "sg:province":"NY",
    "wof:name":"B&L Florist",
    "wof:placetype":"venue"
},
  "geometry": {"coordinates":[-76.05153199999999,44.088556],"type":"Point"}
}