{
  "type": "Feature",
  "properties": {
    "iso:country":"US",
    "sg:address":"47 Bayberry Rd",
    "sg:city":"Northport",
    "sg:classifiers":[
        {
            "category":"Real Estate",
            "subcategory":"Real Estate Services",
            "type":"Services"
        }
    ],
    "sg:phone":"+1 631 751 1177",
    "sg:postcode":"11768",
    "sg:province":"NY",
    "wof:name":"Buyer's Broker Network",
    "wof:placetype":"venue"
},
  "geometry": {"coordinates":[-73.388802,40.935101],"type":"Point"}
}