{
  "type": "Feature",
  "properties": {
    "addr:full":"68 Bangor St Staten Island NY 10314",
    "addr:housenumber":"68",
    "addr:postcode":"10314",
    "addr:street":"Bangor St",
    "iso:country":"US",
    "sg:address":"68 Bangor St",
    "sg:city":"Staten Island",
    "sg:classifiers":[
        {
            "category":"Utilities",
            "subcategory":"Telephone",
            "type":"Services"
        }
    ],
    "sg:phone":"+1 718 761 4009",
    "sg:postcode":"10314",
    "sg:province":"NY",
    "sg:tags":[
        "telecommunication"
    ],
    "wof:name":"Telengy Telecommunication",
    "wof:placetype":"venue"
},
  "geometry": {"coordinates":[-74.153983,40.585456],"type":"Point"}
}