{
  "type": "Feature",
  "properties": {
    "addr:full":"123 W 28 St New York NY 10001",
    "addr:housenumber":"123",
    "addr:postcode":"10001",
    "addr:street":"W 28 St",
    "iso:country":"US",
    "sg:address":"123 W 28 St",
    "sg:city":"New York",
    "sg:classifiers":[
        {
            "category":"Wholesale",
            "subcategory":"Apparel",
            "type":"Manufacturing & Wholesale Goods"
        }
    ],
    "sg:phone":"+1 212 695 5678",
    "sg:postcode":"10001",
    "sg:province":"NY",
    "sg:tags":[
        "hat"
    ],
    "wof:name":"Alice Fashion Inc",
    "wof:placetype":"venue"
},
  "geometry": {"coordinates":[-73.992839,40.747032],"type":"Point"}
}