{
  "type": "Feature",
  "properties": {
    "addr:full":"605 Fillmore Ave Buffalo NY 14212",
    "addr:housenumber":"605",
    "addr:postcode":"14212",
    "addr:street":"Fillmore Ave",
    "iso:country":"US",
    "sg:address":"605 Fillmore Ave",
    "sg:city":"Buffalo",
    "sg:classifiers":[
        {
            "category":"Social Services",
            "type":"Services"
        }
    ],
    "sg:phone":"+1 716 894 7274",
    "sg:postcode":"14212",
    "sg:province":"NY",
    "sg:tags":[
        "individual",
        "family"
    ],
    "wof:name":"Supportive Living Program",
    "wof:placetype":"venue"
},
  "geometry": {"coordinates":[-78.83926099999999,42.892043],"type":"Point"}
}