{
  "type": "Feature",
  "properties": {
    "iso:country":"US",
    "sg:address":"61 N Cross Rd",
    "sg:city":"Lagrangeville",
    "sg:classifiers":[
        {
            "category":"Manufacturing",
            "subcategory":"Metals",
            "type":"Manufacturing & Wholesale Goods"
        },
        {
            "category":"Professional",
            "subcategory":"Art Services",
            "type":"Services"
        },
        {
            "category":"Manufacturing",
            "subcategory":"Building Materials",
            "type":"Manufacturing & Wholesale Goods"
        }
    ],
    "sg:phone":"+1 845 223 4815",
    "sg:postcode":"12540",
    "sg:province":"NY",
    "sg:tags":[
        "ornamental",
        "gate",
        "work",
        "iron",
        "accessory"
    ],
    "sg:website":"http://www.horstaroundthehouse.com",
    "wof:name":"Horst Around The House",
    "wof:placetype":"venue"
},
  "geometry": {"coordinates":[-73.743944,41.665277],"type":"Point"}
}