{
  "type": "Feature",
  "properties": {
    "addr:full":"454 Greece Ridge Center Dr Rochester NY 14626",
    "addr:housenumber":"454",
    "addr:postcode":"14626",
    "addr:street":"Greece Ridge Center Dr",
    "iso:country":"US",
    "sg:address":"454 Greece Ridge Center Dr",
    "sg:city":"Rochester",
    "sg:classifiers":[
        {
            "category":"Shopping",
            "subcategory":"Bicycles & Sporting Goods",
            "type":"Retail Goods"
        }
    ],
    "sg:phone":"+1 585 720 1570",
    "sg:postcode":"14626",
    "sg:province":"NY",
    "sg:website":"www.zumiez.com",
    "wof:name":"Zumiez Inc",
    "wof:placetype":"venue"
},
  "geometry": {"coordinates":[-77.695544,43.20472],"type":"Point"}
}