{
  "type": "Feature",
  "properties": {
    "iso:country":"US",
    "sg:address":"110 Church St",
    "sg:city":"New York",
    "sg:classifiers":[
        {
            "category":"Building & Trades",
            "subcategory":"Plumbing",
            "type":"Services"
        }
    ],
    "sg:phone":"+1 212 766 8329",
    "sg:postcode":"10007",
    "sg:province":"NY",
    "sg:tags":[
        "plumbing",
        "contractor"
    ],
    "wof:name":"Liberty Mechanical Contractors",
    "wof:placetype":"venue"
},
  "geometry": {"coordinates":[-74.008832,40.713795],"type":"Point"}
}