{
  "type": "Feature",
  "properties": {
    "addr:full":"1232 Broadway New York NY 10001",
    "addr:housenumber":"1232",
    "addr:postcode":"10001",
    "addr:street":"Broadway",
    "iso:country":"US",
    "sg:address":"1232 Broadway",
    "sg:city":"New York",
    "sg:classifiers":[
        {
            "category":"Shopping",
            "subcategory":"Jewelry",
            "type":"Retail Goods"
        }
    ],
    "sg:phone":"+1 212 213 8428",
    "sg:postcode":"10001",
    "sg:province":"NY",
    "wof:name":"Raj Jewelers",
    "wof:placetype":"venue"
},
  "geometry": {"coordinates":[-73.988617,40.74741],"type":"Point"}
}