{
  "type": "Feature",
  "properties": {
    "addr:full":"2020 Jericho Tpke Commack NY 11725",
    "addr:housenumber":"2020",
    "addr:postcode":"11725",
    "addr:street":"Jericho Tpke",
    "iso:country":"US",
    "sg:address":"2020 Jericho Tpke",
    "sg:city":"Commack",
    "sg:classifiers":[
        {
            "category":"Banks & Credit Unions",
            "subcategory":"Bank",
            "type":"Services"
        }
    ],
    "sg:phone":"+1 631 543 7400",
    "sg:postcode":"11725",
    "sg:province":"NY",
    "sg:tags":[
        "commercial",
        "saving"
    ],
    "sg:website":"www.bankofsmithtown.com",
    "wof:name":"Bank of Smithtown",
    "wof:placetype":"venue"
},
  "geometry": {"coordinates":[-73.27330000000001,40.8452],"type":"Point"}
}