{
  "type": "Feature",
  "properties": {
    "addr:full":"357 Avenue X Brooklyn NY 11223",
    "addr:housenumber":"357",
    "addr:postcode":"11223",
    "addr:street":"Avenue X",
    "iso:country":"US",
    "sg:address":"357 Avenue X",
    "sg:city":"Brooklyn",
    "sg:classifiers":[
        {
            "category":"Professional",
            "subcategory":"Employment Agencies",
            "type":"Services"
        },
        {
            "category":"Organizations",
            "subcategory":"Religious Organization",
            "type":"Services"
        }
    ],
    "sg:phone":"+1 718 336 2772",
    "sg:postcode":"11223",
    "sg:province":"NY",
    "wof:name":"St Peters Company",
    "wof:placetype":"venue"
},
  "geometry": {"coordinates":[-73.969729,40.590736],"type":"Point"}
}