{
  "type": "Feature",
  "properties": {
    "addr:full":"222 Thompson St New York NY 10012",
    "addr:housenumber":"222",
    "addr:postcode":"10012",
    "addr:street":"Thompson St",
    "iso:country":"US",
    "sg:address":"222 Thompson St",
    "sg:city":"New York",
    "sg:classifiers":[
        {
            "category":"Retail",
            "subcategory":"Auto Repair",
            "type":"Services"
        }
    ],
    "sg:phone":"+1 917 289 1732",
    "sg:postcode":"10012",
    "sg:province":"NY",
    "sg:tags":[
        "wrecker"
    ],
    "wof:name":"24 Hour Always Emergency",
    "wof:placetype":"venue"
},
  "geometry": {"coordinates":[-73.999056,40.728847],"type":"Point"}
}