{
  "type": "Feature",
  "properties": {
    "addr:full":"570 Cherry Ln Floral Park NY 11001",
    "addr:housenumber":"570",
    "addr:postcode":"11001",
    "addr:street":"Cherry Ln",
    "iso:country":"US",
    "sg:address":"570 Cherry Ln",
    "sg:city":"Floral Park",
    "sg:classifiers":[
        {
            "category":"Building & Trades",
            "subcategory":"Construction",
            "type":"Services"
        }
    ],
    "sg:phone":"+1 516 358 0200",
    "sg:postcode":"11001",
    "sg:province":"NY",
    "sg:tags":[
        "erectors",
        "machinery"
    ],
    "wof:name":"Astro Hi-Lifts Corp",
    "wof:placetype":"venue"
},
  "geometry": {"coordinates":[-73.69789,40.735805],"type":"Point"}
}