{
  "type": "Feature",
  "properties": {
    "iso:country":"US",
    "sg:address":"38 Portman Rd",
    "sg:city":"New Rochelle",
    "sg:classifiers":[
        {
            "category":"Manufacturing",
            "subcategory":"Chemicals & Compounds",
            "type":"Manufacturing & Wholesale Goods"
        }
    ],
    "sg:phone":"+1   ",
    "sg:postcode":"10801",
    "sg:province":"NY",
    "sg:tags":[
        "varnish",
        "coating",
        "polyurethane",
        "mfg"
    ],
    "wof:name":"Absolute Coatings Inc",
    "wof:placetype":"venue"
},
  "geometry": {"coordinates":[-73.771708,40.927488],"type":"Point"}
}