{
  "type": "Feature",
  "properties": {
    "iso:country":"US",
    "sg:address":"106 State Hwy 374",
    "sg:city":"Dannemora",
    "sg:classifiers":[
        {
            "category":"Restaurant",
            "type":"Food & Drink"
        }
    ],
    "sg:phone":"+1   ",
    "sg:postcode":"12929",
    "sg:province":"NY",
    "sg:tags":[
        "eating"
    ],
    "wof:name":"Cook Street Cafe",
    "wof:placetype":"venue"
},
  "geometry": {"coordinates":[-73.721632,44.72197],"type":"Point"}
}