{
  "type": "Feature",
  "properties": {
    "iso:country":"US",
    "sg:address":"22 Middleton St",
    "sg:city":"Brooklyn",
    "sg:classifiers":[
        {
            "category":"Social Services",
            "subcategory":"Child Care",
            "type":"Services"
        }
    ],
    "sg:phone":"+1 718 303 9400",
    "sg:postcode":"11206",
    "sg:province":"NY",
    "sg:tags":[
        "kindergarten",
        "academic",
        "school"
    ],
    "wof:name":"Eis Laasois",
    "wof:placetype":"venue"
},
  "geometry": {"coordinates":[-73.955015,40.70023],"type":"Point"}
}