{
  "type": "Feature",
  "properties": {
    "iso:country":"US",
    "sg:address":"15 W Main St",
    "sg:city":"Cambridge",
    "sg:classifiers":[
        {
            "category":"Personal",
            "subcategory":"Beauty Salon",
            "type":"Services"
        }
    ],
    "sg:phone":"+1 518 677 8560",
    "sg:postcode":"12816",
    "sg:province":"NY",
    "wof:name":"Golden Image Hair Salon",
    "wof:placetype":"venue"
},
  "geometry": {"coordinates":[-73.38415000000001,43.02805],"type":"Point"}
}