{
  "type": "Feature",
  "properties": {
    "addr:full":"14 Van St Staten Island NY 10310",
    "addr:housenumber":"14",
    "addr:postcode":"10310",
    "addr:street":"Van St",
    "iso:country":"US",
    "sg:address":"14 Van St",
    "sg:city":"Staten Island",
    "sg:classifiers":[
        {
            "category":"Manufacturing",
            "subcategory":"Chemicals & Compounds",
            "type":"Manufacturing & Wholesale Goods"
        }
    ],
    "sg:phone":"+1   ",
    "sg:postcode":"10310",
    "sg:province":"NY",
    "sg:tags":[
        "finishing",
        "metal",
        "plating",
        "mfg"
    ],
    "wof:name":"Plating Systems Inc",
    "wof:placetype":"venue"
},
  "geometry": {"coordinates":[-74.119646,40.639804],"type":"Point"}
}