{
  "type": "Feature",
  "properties": {
    "addr:full":"5920 Airport Rd Oriskany NY 13424",
    "addr:housenumber":"5920",
    "addr:postcode":"13424",
    "addr:street":"Airport Rd",
    "iso:country":"US",
    "sg:address":"5920 Airport Rd",
    "sg:city":"Oriskany",
    "sg:classifiers":[
        {
            "category":"Travel",
            "subcategory":"Hotels & Motels",
            "type":"Entertainment"
        },
        {
            "category":"Retail",
            "subcategory":"Event Space",
            "type":"Services"
        }
    ],
    "sg:phone":"+1 315 736 3377",
    "sg:postcode":"13424",
    "sg:province":"NY",
    "sg:tags":[
        "hall",
        "lodging",
        "banquet",
        "reception",
        "facility"
    ],
    "sg:website":"http://www.ramada.com/hotel/11400&cid=RANE",
    "wof:name":"Ramada Inn - Oriskany",
    "wof:placetype":"venue"
},
  "geometry": {"coordinates":[-75.37858199999999,43.148581],"type":"Point"}
}