{
  "type": "Feature",
  "properties": {
    "iso:country":"US",
    "sg:address":"72 Dunning Rd",
    "sg:city":"Middletown",
    "sg:classifiers":[
        {
            "category":"Shopping",
            "subcategory":"Pharmacy",
            "type":"Retail Goods"
        }
    ],
    "sg:phone":"+1   ",
    "sg:postcode":"10940",
    "sg:province":"NY",
    "wof:name":"Rx Place Pharmacy",
    "wof:placetype":"venue"
},
  "geometry": {"coordinates":[-74.38326499999999,41.455278],"type":"Point"}
}