{
  "type": "Feature",
  "properties": {
    "addr:full":"30 Wall St New York NY 10005",
    "addr:housenumber":"30",
    "addr:postcode":"10005",
    "addr:street":"Wall St",
    "iso:country":"US",
    "sg:address":"30 Wall St",
    "sg:city":"New York",
    "sg:classifiers":[
        {
            "category":"Professional",
            "subcategory":"Employment Agencies",
            "type":"Services"
        }
    ],
    "sg:phone":"+1 212 809 0460",
    "sg:postcode":"10005",
    "sg:province":"NY",
    "sg:tags":[
        "permanent",
        "temporary"
    ],
    "wof:name":"Guidance International Cons",
    "wof:placetype":"venue"
},
  "geometry": {"coordinates":[-74.00975099999999,40.706682],"type":"Point"}
}