{
  "type": "Feature",
  "properties": {
    "iso:country":"US",
    "sg:address":"135 S Lexington Ave",
    "sg:city":"White Plains",
    "sg:classifiers":[
        {
            "category":"Professional",
            "subcategory":"Computer Services",
            "type":"Services"
        }
    ],
    "sg:phone":"+1   ",
    "sg:postcode":"10601",
    "sg:province":"NY",
    "sg:tags":[
        "consultant",
        "instruction",
        "software"
    ],
    "wof:name":"Blair Consulting",
    "wof:placetype":"venue"
},
  "geometry": {"coordinates":[-73.771305,41.026002],"type":"Point"}
}