{
  "type": "Feature",
  "properties": {
    "addr:full":"21 Old Wagon Rd Woodstock NY 12498",
    "addr:housenumber":"21",
    "addr:postcode":"12498",
    "addr:street":"Old Wagon Rd",
    "iso:country":"US",
    "sg:address":"21 Old Wagon Rd",
    "sg:city":"Woodstock",
    "sg:classifiers":[
        {
            "category":"Real Estate",
            "subcategory":"Real Estate Agent",
            "type":"Services"
        }
    ],
    "sg:phone":"+1 845 679 7181",
    "sg:postcode":"12498",
    "sg:province":"NY",
    "wof:name":"Riley Real Estate",
    "wof:placetype":"venue"
},
  "geometry": {"coordinates":[-74.117769,42.030077],"type":"Point"}
}