{
  "type": "Feature",
  "properties": {
    "addr:full":"4242 Merrick Rd Massapequa NY 11758",
    "addr:housenumber":"4242",
    "addr:postcode":"11758",
    "addr:street":"Merrick Rd",
    "iso:country":"US",
    "sg:address":"4242 Merrick Rd",
    "sg:city":"Massapequa",
    "sg:classifiers":[
        {
            "category":"Building & Trades",
            "subcategory":"Electrical",
            "type":"Services"
        }
    ],
    "sg:phone":"+1 516 797 4242",
    "sg:postcode":"11758",
    "sg:province":"NY",
    "sg:tags":[
        "electrical",
        "contractor"
    ],
    "wof:name":"Fj Construction New York",
    "wof:placetype":"venue"
},
  "geometry": {"coordinates":[-73.476744,40.666685],"type":"Point"}
}