{
  "type": "Feature",
  "properties": {
    "addr:full":"221 W 82 St New York NY 10024",
    "addr:housenumber":"221",
    "addr:postcode":"10024",
    "addr:street":"W 82 St",
    "iso:country":"US",
    "sg:address":"221 W 82 St",
    "sg:city":"New York",
    "sg:classifiers":[
        {
            "category":"Retail",
            "subcategory":"Photofinishing",
            "type":"Services"
        }
    ],
    "sg:phone":"+1   ",
    "sg:postcode":"10024",
    "sg:province":"NY",
    "sg:tags":[
        "travel"
    ],
    "wof:name":"Lee Snider Photo Images",
    "wof:placetype":"venue"
},
  "geometry": {"coordinates":[-73.97798299999999,40.785565],"type":"Point"}
}