{
  "type": "Feature",
  "properties": {
    "addr:full":"91 Schilling Ln Rochester NY 14618",
    "addr:housenumber":"91",
    "addr:postcode":"14618",
    "addr:street":"Schilling Ln",
    "iso:country":"US",
    "sg:address":"91 Schilling Ln",
    "sg:city":"Rochester",
    "sg:classifiers":[
        {
            "category":"Professional",
            "subcategory":"Employment Agencies",
            "type":"Services"
        }
    ],
    "sg:phone":"+1 585 256 2810",
    "sg:postcode":"14618",
    "sg:province":"NY",
    "sg:tags":[
        "help",
        "supply"
    ],
    "wof:name":"Budget Cleaning",
    "wof:placetype":"venue"
},
  "geometry": {"coordinates":[-77.599802,43.116435],"type":"Point"}
}