{
  "type": "Feature",
  "properties": {
    "addr:full":"1800 Western Ave Albany NY 12203",
    "addr:housenumber":"1800",
    "addr:postcode":"12203",
    "addr:street":"Western Ave",
    "iso:country":"US",
    "sg:address":"1800 Western Ave",
    "sg:city":"Albany",
    "sg:classifiers":[
        {
            "category":"Fast Food",
            "type":"Food & Drink"
        },
        {
            "category":"Restaurant",
            "type":"Food & Drink"
        },
        {
            "category":"Food & Beverages",
            "subcategory":"Groceries & Convenience Stores",
            "type":"Retail Goods"
        }
    ],
    "sg:phone":"+1 518 456 0266",
    "sg:postcode":"12203",
    "sg:province":"NY",
    "sg:tags":[
        "shop",
        "american",
        "sandwich",
        "take"
    ],
    "sg:website":"http://www.subway.com",
    "wof:name":"Subway",
    "wof:placetype":"venue"
},
  "geometry": {"coordinates":[-73.866186,42.690162],"type":"Point"}
}