{
  "type": "Feature",
  "properties": {
    "addr:full":"360 Central Ave Ste 113 Lawrence NY 11559",
    "addr:housenumber":"360",
    "addr:postcode":"11559",
    "addr:street":"Central Ave Ste 113",
    "iso:country":"US",
    "sg:address":"360 Central Ave Ste 113",
    "sg:city":"Lawrence",
    "sg:classifiers":[
        {
            "category":"Health Services",
            "subcategory":"Doctor",
            "type":"Services"
        }
    ],
    "sg:phone":"+1 516 569 6966",
    "sg:postcode":"11559",
    "sg:province":"NY",
    "wof:name":"ROTHMAN NATHAN MD",
    "wof:placetype":"venue"
},
  "geometry": {"coordinates":[-73.728373,40.618635],"type":"Point"}
}