{
  "type": "Feature",
  "properties": {
    "addr:full":"489 Peninsula Blvd Lynbrook NY 11563",
    "addr:housenumber":"489",
    "addr:postcode":"11563",
    "addr:street":"Peninsula Blvd",
    "iso:country":"US",
    "sg:address":"489 Peninsula Blvd",
    "sg:city":"Lynbrook",
    "sg:classifiers":[
        {
            "category":"Building & Trades",
            "subcategory":"Construction",
            "type":"Services"
        }
    ],
    "sg:phone":"+1 516 887 1422",
    "sg:postcode":"11563",
    "sg:province":"NY",
    "sg:tags":[
        "house"
    ],
    "wof:name":"Lighthouse Home Improvement",
    "wof:placetype":"venue"
},
  "geometry": {"coordinates":[-73.68986099999999,40.649978],"type":"Point"}
}