{
  "type": "Feature",
  "properties": {
    "addr:full":"14168 85th Road Jamaica NY 11435",
    "addr:housenumber":"14168",
    "addr:postcode":"11435",
    "addr:street":"85Th Road",
    "iso:country":"US",
    "sg:address":"14168 85th Road",
    "sg:city":"Jamaica",
    "sg:classifiers":[
        {
            "category":"Real Estate",
            "subcategory":"Real Estate Operator",
            "type":"Services"
        }
    ],
    "sg:phone":"+1 718 206 9673",
    "sg:postcode":"11435",
    "sg:province":"NY",
    "sg:tags":[
        "apartment"
    ],
    "wof:name":"Crescent Five Associates",
    "wof:placetype":"venue"
},
  "geometry": {"coordinates":[-73.814047,40.709631],"type":"Point"}
}