{
  "type": "Feature",
  "properties": {
    "addr:full":"33 Berkshire Blvd Albany NY 12203",
    "addr:housenumber":"33",
    "addr:postcode":"12203",
    "addr:street":"Berkshire Blvd",
    "iso:country":"US",
    "sg:address":"33 Berkshire Blvd",
    "sg:city":"Albany",
    "sg:classifiers":[
        {
            "category":"Professional",
            "subcategory":"Lawyer & Legal Services",
            "type":"Services"
        }
    ],
    "sg:phone":"+1   ",
    "sg:postcode":"12203",
    "sg:province":"NY",
    "wof:name":"Robert J Beshaw",
    "wof:placetype":"venue"
},
  "geometry": {"coordinates":[-73.807712,42.664207],"type":"Point"}
}