{
  "type": "Feature",
  "properties": {
    "addr:full":"10 Lake Oniad Dr Wappingers Falls NY 12590",
    "addr:housenumber":"10",
    "addr:postcode":"12590",
    "addr:street":"Lake Oniad Dr",
    "iso:country":"US",
    "sg:address":"10 Lake Oniad Dr",
    "sg:city":"Wappingers Falls",
    "sg:classifiers":[
        {
            "category":"Social Services",
            "subcategory":"Child Care",
            "type":"Services"
        }
    ],
    "sg:phone":"+1   ",
    "sg:postcode":"12590",
    "sg:province":"NY",
    "sg:tags":[
        "day"
    ],
    "wof:name":"James P Cogan Jr",
    "wof:placetype":"venue"
},
  "geometry": {"coordinates":[-73.881221,41.58944],"type":"Point"}
}