{
  "type": "Feature",
  "properties": {
    "addr:full":"220 W Court St Rome NY 13440",
    "addr:housenumber":"220",
    "addr:postcode":"13440",
    "addr:street":"W Court St",
    "iso:country":"US",
    "sg:address":"220 W Court St",
    "sg:city":"Rome",
    "sg:classifiers":[
        {
            "category":"Health Services",
            "subcategory":"Doctor",
            "type":"Services"
        }
    ],
    "sg:phone":"+1 315 336 6380",
    "sg:postcode":"13440",
    "sg:province":"NY",
    "wof:name":"Richard J Klockowski DDS",
    "wof:placetype":"venue"
},
  "geometry": {"coordinates":[-75.45838999999999,43.214585],"type":"Point"}
}