{
  "type": "Feature",
  "properties": {
    "iso:country":"US",
    "sg:address":"208 E Broadway J10006",
    "sg:city":"New York",
    "sg:classifiers":[
        {
            "category":"Communications",
            "subcategory":"Film & Video Production",
            "type":"Services"
        },
        {
            "category":"Professional",
            "subcategory":"Art Services",
            "type":"Services"
        }
    ],
    "sg:phone":"+1 917 669 4410",
    "sg:postcode":"10002",
    "sg:province":"NY",
    "sg:tags":[
        "photographer",
        "video/film"
    ],
    "sg:website":"www.mikewebbphotography.com",
    "wof:name":"Mike Webb Photography",
    "wof:placetype":"venue"
},
  "geometry": {"coordinates":[-73.987846,40.714272],"type":"Point"}
}