{
  "type": "Feature",
  "properties": {
    "iso:country":"US",
    "sg:address":"54 Covert Ave",
    "sg:city":"Garden City",
    "sg:classifiers":[
        {
            "category":"Shopping",
            "subcategory":"Gifts & Souvenirs",
            "type":"Retail Goods"
        }
    ],
    "sg:phone":"+1   ",
    "sg:postcode":"11530",
    "sg:province":"NY",
    "sg:tags":[
        "clothing"
    ],
    "wof:name":"Victoria Rosa",
    "wof:placetype":"venue"
},
  "geometry": {"coordinates":[-73.68833100000001,40.721288],"type":"Point"}
}