{
  "type": "Feature",
  "properties": {
    "addr:full":"116 N Sea Rd Southampton NY 11968",
    "addr:housenumber":"116",
    "addr:postcode":"11968",
    "addr:street":"N Sea Rd",
    "iso:country":"US",
    "sg:address":"116 N Sea Rd",
    "sg:city":"Southampton",
    "sg:classifiers":[
        {
            "category":"Shopping",
            "subcategory":"Used Merchandise",
            "type":"Retail Goods"
        }
    ],
    "sg:phone":"+1 631 287 0020",
    "sg:postcode":"11968",
    "sg:province":"NY",
    "sg:tags":[
        "antique"
    ],
    "wof:name":"Barn Antiques & Architectural",
    "wof:placetype":"venue"
},
  "geometry": {"coordinates":[-72.394595,40.891212],"type":"Point"}
}