{
  "type": "Feature",
  "properties": {
    "addr:full":"141 Banker St Brooklyn NY 11222",
    "addr:housenumber":"141",
    "addr:postcode":"11222",
    "addr:street":"Banker St",
    "iso:country":"US",
    "sg:address":"141 Banker St",
    "sg:city":"Brooklyn",
    "sg:classifiers":[
        {
            "category":"Building & Trades",
            "subcategory":"Construction",
            "type":"Services"
        }
    ],
    "sg:phone":"+1 718 384 1155",
    "sg:postcode":"11222",
    "sg:province":"NY",
    "sg:tags":[
        "marble",
        "contractor"
    ],
    "wof:name":"Splendor Marble LLC",
    "wof:placetype":"venue"
},
  "geometry": {"coordinates":[-73.954813,40.723761],"type":"Point"}
}