{
  "type": "Feature",
  "properties": {
    "addr:full":"601 W 26th St New York NY 10001",
    "addr:housenumber":"601",
    "addr:postcode":"10001",
    "addr:street":"W 26Th St",
    "iso:country":"US",
    "sg:address":"601 W 26th St",
    "sg:city":"New York",
    "sg:classifiers":[
        {
            "category":"Wholesale",
            "subcategory":"Wine & Distilled Alcoholic Beverages",
            "type":"Manufacturing & Wholesale Goods"
        }
    ],
    "sg:phone":"+1 212 888 7575",
    "sg:postcode":"10001",
    "sg:province":"NY",
    "sg:tags":[
        "champagne",
        "spirits"
    ],
    "wof:name":"Clicquot Inc",
    "wof:placetype":"venue"
},
  "geometry": {"coordinates":[-74.00794399999999,40.75176],"type":"Point"}
}