{
  "type": "Feature",
  "properties": {
    "addr:full":"408 E 65 St New York NY 10065",
    "addr:housenumber":"408;65",
    "addr:postcode":"10065",
    "addr:street":"E;St",
    "iso:country":"US",
    "sg:address":"408 E 65 St",
    "sg:city":"New York",
    "sg:classifiers":[
        {
            "category":"Building & Trades",
            "subcategory":"Construction",
            "type":"Services"
        }
    ],
    "sg:phone":"+1 212 861 0360",
    "sg:postcode":"10065",
    "sg:province":"NY",
    "sg:tags":[
        "waterproofing",
        "contractor"
    ],
    "wof:name":"3 J's Waterproofing & Rstrtn",
    "wof:placetype":"venue"
},
  "geometry": {"coordinates":[-73.957159,40.762429],"type":"Point"}
}