{
  "type": "Feature",
  "properties": {
    "iso:country":"US",
    "sg:address":"54 Champlain Ave",
    "sg:city":"Whitehall",
    "sg:classifiers":[
        {
            "category":"Real Estate",
            "subcategory":"Real Estate Operator",
            "type":"Services"
        }
    ],
    "sg:phone":"+1 518 499 0347",
    "sg:postcode":"12887",
    "sg:province":"NY",
    "sg:tags":[
        "apartment"
    ],
    "wof:name":"Daniel B Manor",
    "wof:placetype":"venue"
},
  "geometry": {"coordinates":[-73.391009,43.547128],"type":"Point"}
}