{
  "type": "Feature",
  "properties": {
    "addr:full":"36 Mechanic St Amenia NY 12501",
    "addr:housenumber":"36",
    "addr:postcode":"12501",
    "addr:street":"Mechanic St",
    "iso:country":"US",
    "sg:address":"36 Mechanic St",
    "sg:city":"Amenia",
    "sg:classifiers":[
        {
            "category":"Government",
            "subcategory":"Fire Station",
            "type":"Public Place"
        }
    ],
    "sg:phone":"+1 845 373 8467",
    "sg:postcode":"12501",
    "sg:province":"NY",
    "sg:tags":[
        "department"
    ],
    "wof:name":"Amenia Fire House",
    "wof:placetype":"venue"
},
  "geometry": {"coordinates":[-73.552471,41.848074],"type":"Point"}
}