{
  "type": "Feature",
  "properties": {
    "iso:country":"US",
    "sg:address":"1360 Midland Ave",
    "sg:city":"Bronxville",
    "sg:classifiers":[
        {
            "category":"Professional",
            "subcategory":"Business Services",
            "type":"Services"
        }
    ],
    "sg:phone":"+1 914 237 8341",
    "sg:postcode":"10708",
    "sg:province":"NY",
    "sg:tags":[
        "interior",
        "consultant",
        "design",
        "decorator"
    ],
    "wof:name":"Nialexia",
    "wof:placetype":"venue"
},
  "geometry": {"coordinates":[-73.84360700000001,40.928546],"type":"Point"}
}