{
  "type": "Feature",
  "properties": {
    "iso:country":"US",
    "sg:address":"632 Rte 25A",
    "sg:city":"Rocky Point",
    "sg:classifiers":[
        {
            "category":"Food & Beverages",
            "subcategory":"Specialty",
            "type":"Retail Goods"
        }
    ],
    "sg:phone":"+1 631 821 0444",
    "sg:postcode":"11778",
    "sg:province":"NY",
    "sg:tags":[
        "health",
        "diet"
    ],
    "wof:name":"Back To Basics Natural Food",
    "wof:placetype":"venue"
},
  "geometry": {"coordinates":[-72.92292,40.947442],"type":"Point"}
}