{
  "type": "Feature",
  "properties": {
    "iso:country":"US",
    "sg:address":"932 McDonald Ave",
    "sg:city":"Brooklyn",
    "sg:classifiers":[
        {
            "category":"Home & Garden",
            "subcategory":"Furniture",
            "type":"Retail Goods"
        }
    ],
    "sg:phone":"+1 718 923 9011",
    "sg:postcode":"11218",
    "sg:province":"NY",
    "sg:tags":[
        "builder",
        "custom"
    ],
    "wof:name":"F & V Trading Corp",
    "wof:placetype":"venue"
},
  "geometry": {"coordinates":[-73.977509,40.632631],"type":"Point"}
}