{
  "type": "Feature",
  "properties": {
    "addr:full":"255 Schenectady Avenue Brooklyn NY 11213",
    "addr:housenumber":"255",
    "addr:postcode":"11213",
    "addr:street":"Schenectady Avenue",
    "iso:country":"US",
    "sg:address":"255 Schenectady Avenue",
    "sg:city":"Brooklyn",
    "sg:classifiers":[
        {
            "category":"Food & Beverages",
            "subcategory":"Meat & Fish",
            "type":"Retail Goods"
        }
    ],
    "sg:phone":"+1 718 493 0916",
    "sg:postcode":"11213",
    "sg:province":"NY",
    "sg:tags":[
        "shop"
    ],
    "wof:name":"Three Brothers Meat",
    "wof:placetype":"venue"
},
  "geometry": {"coordinates":[-73.93367000000001,40.669697],"type":"Point"}
}