{
  "type": "Feature",
  "properties": {
    "iso:country":"US",
    "sg:address":"1600 E 26th St",
    "sg:city":"Brooklyn",
    "sg:classifiers":[
        {
            "category":"Banks & Credit Unions",
            "subcategory":"Bank",
            "type":"Services"
        }
    ],
    "sg:phone":"+1 347 673 5787",
    "sg:postcode":"11229",
    "sg:province":"NY",
    "wof:name":"Citigroup Incorporated",
    "wof:placetype":"venue"
},
  "geometry": {"coordinates":[-73.948212,40.612524],"type":"Point"}
}