{
  "type": "Feature",
  "properties": {
    "iso:country":"US",
    "sg:address":"62 Canoe Place Rd",
    "sg:city":"Hampton Bays",
    "sg:classifiers":[
        {
            "category":"Professional",
            "subcategory":"Business Services",
            "type":"Services"
        }
    ],
    "sg:phone":"+1 631 728 7200",
    "sg:postcode":"11946",
    "sg:province":"NY",
    "sg:tags":[
        "reservation",
        "motel",
        "hotel"
    ],
    "wof:name":"Shinnecick Mist Inc",
    "wof:placetype":"venue"
},
  "geometry": {"coordinates":[-72.502014,40.877669],"type":"Point"}
}