{
  "type": "Feature",
  "properties": {
    "addr:full":"38 College Rd Monsey NY 10952",
    "addr:housenumber":"38",
    "addr:postcode":"10952",
    "addr:street":"College Rd",
    "iso:country":"US",
    "sg:address":"38 College Rd",
    "sg:city":"Monsey",
    "sg:classifiers":[
        {
            "category":"Organizations",
            "subcategory":"Religious Organization",
            "type":"Services"
        }
    ],
    "sg:phone":"+1 845 371 8192",
    "sg:postcode":"10952",
    "sg:province":"NY",
    "sg:tags":[
        "clergy"
    ],
    "wof:name":"Congregation Kol Juda",
    "wof:placetype":"venue"
},
  "geometry": {"coordinates":[-74.089443,41.112767],"type":"Point"}
}