{
  "type": "Feature",
  "properties": {
    "iso:country":"US",
    "sg:address":"21 Houston Rd",
    "sg:city":"Goshen",
    "sg:classifiers":[
        {
            "category":"Farming",
            "subcategory":"Farm",
            "type":"Manufacturing & Wholesale Goods"
        }
    ],
    "sg:phone":"+1 845 294 5059",
    "sg:postcode":"10924",
    "sg:province":"NY",
    "sg:tags":[
        "crop",
        "general"
    ],
    "wof:name":"Lupinski John",
    "wof:placetype":"venue"
},
  "geometry": {"coordinates":[-74.362691,41.380337],"type":"Point"}
}