{
  "type": "Feature",
  "properties": {
    "addr:full":"71 Merrick Rd Amityville NY 11701",
    "addr:housenumber":"71",
    "addr:postcode":"11701",
    "addr:street":"Merrick Rd",
    "iso:country":"US",
    "sg:address":"71 Merrick Rd",
    "sg:city":"Amityville",
    "sg:phone":"+1 631 598 1150",
    "sg:postcode":"11701",
    "sg:province":"NY",
    "wof:name":"Villa D'avanzo",
    "wof:placetype":"venue"
},
  "geometry": {"coordinates":[-73.42028000000001,40.671493],"type":"Point"}
}