{
  "type": "Feature",
  "properties": {
    "addr:full":"40 Broad St New York NY 10004",
    "addr:housenumber":"40",
    "addr:postcode":"10004",
    "addr:street":"Broad St",
    "iso:country":"US",
    "sg:address":"40 Broad St",
    "sg:city":"New York",
    "sg:classifiers":[
        {
            "category":"Food & Beverages",
            "subcategory":"Bakery",
            "type":"Retail Goods"
        }
    ],
    "sg:phone":"+1 212 809 1077",
    "sg:postcode":"10004",
    "sg:province":"NY",
    "sg:tags":[
        "doughnut"
    ],
    "wof:name":"Madison Donut Plaza Inc",
    "wof:placetype":"venue"
},
  "geometry": {"coordinates":[-74.011579,40.705366],"type":"Point"}
}