{
  "type": "Feature",
  "properties": {
    "addr:full":"5762 Chili Riga Center Rd Churchville NY 14428",
    "addr:housenumber":"5762",
    "addr:postcode":"14428",
    "addr:street":"Chili Riga Center Rd",
    "iso:country":"US",
    "sg:address":"5762 Chili Riga Center Rd",
    "sg:city":"Churchville",
    "sg:classifiers":[
        {
            "category":"Organizations",
            "subcategory":"Community Association",
            "type":"Services"
        }
    ],
    "sg:phone":"+1 585 251 1784",
    "sg:postcode":"14428",
    "sg:province":"NY",
    "sg:tags":[
        "club"
    ],
    "wof:name":"Dog Obedience Training Club",
    "wof:placetype":"venue"
},
  "geometry": {"coordinates":[-77.841802,43.069635],"type":"Point"}
}