{
  "type": "Feature",
  "properties": {
    "iso:country":"US",
    "sg:address":"97 Zoa Ave",
    "sg:city":"Johnson City",
    "sg:classifiers":[
        {
            "category":"Freight",
            "type":"Transportation"
        }
    ],
    "sg:phone":"+1   ",
    "sg:postcode":"13790",
    "sg:province":"NY",
    "sg:tags":[
        "local",
        "trucking"
    ],
    "wof:name":"William Chalker Trucking",
    "wof:placetype":"venue"
},
  "geometry": {"coordinates":[-75.95072999999999,42.125208],"type":"Point"}
}