{
  "type": "Feature",
  "properties": {
    "iso:country":"US",
    "sg:address":"553 E Mountain Rd S",
    "sg:city":"Cold Spring",
    "sg:classifiers":[
        {
            "category":"Manufacturing",
            "subcategory":"Tools & Machinery",
            "type":"Manufacturing & Wholesale Goods"
        }
    ],
    "sg:phone":"+1 845 265 6502",
    "sg:postcode":"10516",
    "sg:province":"NY",
    "sg:tags":[
        "machine",
        "shop"
    ],
    "wof:name":"Integrity Tool & Metal Works",
    "wof:placetype":"venue"
},
  "geometry": {"coordinates":[-73.91377,41.45888],"type":"Point"}
}