{
  "type": "Feature",
  "properties": {
    "addr:full":"8701 Atlantic Ave Woodhaven NY 11421",
    "addr:housenumber":"8701",
    "addr:postcode":"11421",
    "addr:street":"Atlantic Ave",
    "iso:country":"US",
    "sg:address":"8701 Atlantic Ave",
    "sg:city":"Woodhaven",
    "sg:classifiers":[
        {
            "category":"Building & Trades",
            "subcategory":"Pest Control",
            "type":"Services"
        }
    ],
    "sg:phone":"+1 718 296 5900",
    "sg:postcode":"11421",
    "sg:province":"NY",
    "sg:website":"www.bedbugking.com",
    "wof:name":"HILLS PEST MANAGEMENT",
    "wof:placetype":"venue"
},
  "geometry": {"coordinates":[-73.85491,40.686641],"type":"Point"}
}