{
  "type": "Feature",
  "properties": {
    "addr:full":"18 Stuyvesant Oval New York NY 10009",
    "addr:housenumber":"18",
    "addr:postcode":"10009",
    "addr:street":"Stuyvesant Oval",
    "iso:country":"US",
    "sg:address":"18 Stuyvesant Oval",
    "sg:city":"New York",
    "sg:classifiers":[
        {
            "category":"Travel",
            "subcategory":"Travel Agent",
            "type":"Entertainment"
        }
    ],
    "sg:phone":"+1   ",
    "sg:postcode":"10009",
    "sg:province":"NY",
    "sg:tags":[
        "agency"
    ],
    "wof:name":"English Lakeland Ramblers",
    "wof:placetype":"venue"
},
  "geometry": {"coordinates":[-73.97670599999999,40.731765],"type":"Point"}
}