{
  "type": "Feature",
  "properties": {
    "addr:full":"766 2nd Ave New York NY 10017",
    "addr:housenumber":"766",
    "addr:postcode":"10017",
    "addr:street":"2Nd Ave",
    "iso:country":"US",
    "sg:address":"766 2nd Ave",
    "sg:city":"New York",
    "sg:classifiers":[
        {
            "category":"Restaurant",
            "type":"Food & Drink"
        }
    ],
    "sg:phone":"+1 212 986 1234",
    "sg:postcode":"10017",
    "sg:province":"NY",
    "sg:tags":[
        "pizza"
    ],
    "sg:website":"www.newyorkdeliciouspizza.com",
    "wof:name":"New York's Delicious Pizza",
    "wof:placetype":"venue"
},
  "geometry": {"coordinates":[-73.972702,40.748901],"type":"Point"}
}