{
  "type": "Feature",
  "properties": {
    "iso:country":"US",
    "sg:address":"18 E 77th Street",
    "sg:city":"New York",
    "sg:classifiers":[
        {
            "category":"Health Services",
            "subcategory":"Doctor",
            "type":"Services"
        }
    ],
    "sg:phone":"+1 212 717 5500",
    "sg:postcode":"10021",
    "sg:province":"NY",
    "wof:name":"Bello Gaetano MD",
    "wof:placetype":"venue"
},
  "geometry": {"coordinates":[-73.964142,40.775417],"type":"Point"}
}