{
  "type": "Feature",
  "properties": {
    "addr:full":"185 State Hwy 94 Warwick NY 10990",
    "addr:housenumber":"185",
    "addr:postcode":"10990",
    "addr:street":"State Hwy 94",
    "iso:country":"US",
    "sg:address":"185 State Hwy 94",
    "sg:city":"Warwick",
    "sg:classifiers":[
        {
            "category":"Autos & Motor Vehicles",
            "subcategory":"Automobile Sales",
            "type":"Retail Goods"
        },
        {
            "category":"Retail",
            "subcategory":"Auto Repair",
            "type":"Services"
        }
    ],
    "sg:phone":"+1 845 986 2021",
    "sg:postcode":"10990",
    "sg:province":"NY",
    "sg:tags":[
        "repairing",
        "car",
        "dealer"
    ],
    "wof:name":"Chrysler Jeep Dodge Of Warwick",
    "wof:placetype":"venue"
},
  "geometry": {"coordinates":[-74.38362499999999,41.236229],"type":"Point"}
}