{
  "type": "Feature",
  "properties": {
    "addr:full":"1440 Amsterdam Ave New York NY 10027",
    "addr:housenumber":"1440",
    "addr:postcode":"10027",
    "addr:street":"Amsterdam Ave",
    "iso:country":"US",
    "sg:address":"1440 Amsterdam Ave",
    "sg:city":"New York",
    "sg:classifiers":[
        {
            "category":"Wholesale",
            "subcategory":"Machinery & Supplies",
            "type":"Manufacturing & Wholesale Goods"
        }
    ],
    "sg:phone":"+1 888 577 7900",
    "sg:postcode":"10027",
    "sg:province":"NY",
    "sg:tags":[
        "salon",
        "cosmetic",
        "beauty"
    ],
    "wof:name":"European Beauty Products",
    "wof:placetype":"venue"
},
  "geometry": {"coordinates":[-73.9534,40.817101],"type":"Point"}
}