{
  "type": "Feature",
  "properties": {
    "iso:country":"US",
    "sg:address":"826 Broadway",
    "sg:city":"New York",
    "sg:classifiers":[
        {
            "category":"Professional",
            "type":"Services"
        }
    ],
    "sg:phone":"+1 212 780 7521",
    "sg:postcode":"10003",
    "sg:province":"NY",
    "sg:tags":[
        "establishment"
    ],
    "wof:name":"Belgo",
    "wof:placetype":"venue"
},
  "geometry": {"coordinates":[-73.990945,40.733978],"type":"Point"}
}