{
  "type": "Feature",
  "properties": {
    "iso:country":"US",
    "sg:address":"519 W 47th St",
    "sg:city":"New York",
    "sg:classifiers":[
        {
            "category":"Retail",
            "subcategory":"Auto Repair",
            "type":"Services"
        }
    ],
    "sg:phone":"+1 212 582 8877",
    "sg:postcode":"10036",
    "sg:province":"NY",
    "wof:name":"NYC Star Auto",
    "wof:placetype":"venue"
},
  "geometry": {"coordinates":[-73.993934,40.763292],"type":"Point"}
}