{
  "type": "Feature",
  "properties": {
    "addr:full":"1391 Nelson Ave Bronx NY 10452",
    "addr:housenumber":"1391",
    "addr:postcode":"10452",
    "addr:street":"Nelson Ave",
    "iso:country":"US",
    "sg:address":"1391 Nelson Ave",
    "sg:city":"Bronx",
    "sg:classifiers":[
        {
            "category":"Personal",
            "subcategory":"Beauty Salon",
            "type":"Services"
        }
    ],
    "sg:phone":"+1   ",
    "sg:postcode":"10452",
    "sg:province":"NY",
    "sg:tags":[
        "shop"
    ],
    "wof:name":"New Generation Beauty Salon",
    "wof:placetype":"venue"
},
  "geometry": {"coordinates":[-73.923007,40.840941],"type":"Point"}
}