{
  "type": "Feature",
  "properties": {
    "addr:full":"107 Rockaway Ave Valley Stream NY 11580",
    "addr:housenumber":"107",
    "addr:postcode":"11580",
    "addr:street":"Rockaway Ave",
    "iso:country":"US",
    "sg:address":"107 Rockaway Ave",
    "sg:city":"Valley Stream",
    "sg:classifiers":[
        {
            "category":"Retail",
            "subcategory":"Repair Shop",
            "type":"Services"
        }
    ],
    "sg:phone":"+1 516 213 2564",
    "sg:postcode":"11580",
    "sg:province":"NY",
    "sg:tags":[
        "lock",
        "locksmith"
    ],
    "wof:name":"0 Emergency A Locksmith",
    "wof:placetype":"venue"
},
  "geometry": {"coordinates":[-73.698672,40.663308],"type":"Point"}
}