{
  "type": "Feature",
  "properties": {
    "iso:country":"US",
    "sg:address":"4124 W Henrietta Rd",
    "sg:city":"Rochester",
    "sg:classifiers":[
        {
            "category":"Insurance",
            "subcategory":"Insurance Agent",
            "type":"Services"
        }
    ],
    "sg:phone":"+1 585 359 4280",
    "sg:postcode":"14623",
    "sg:province":"NY",
    "wof:name":"State Farm Insurance",
    "wof:placetype":"venue"
},
  "geometry": {"coordinates":[-77.64637399999999,43.069573],"type":"Point"}
}