{
  "type": "Feature",
  "properties": {
    "addr:full":"1312 Avenue H Brooklyn NY 11230",
    "addr:housenumber":"1312",
    "addr:postcode":"11230",
    "addr:street":"Avenue H",
    "iso:country":"US",
    "sg:address":"1312 Avenue H",
    "sg:city":"Brooklyn",
    "sg:classifiers":[
        {
            "category":"Personal",
            "type":"Services"
        }
    ],
    "sg:phone":"+1 718 434 2198",
    "sg:postcode":"11230",
    "sg:province":"NY",
    "sg:tags":[
        "sewing",
        "alteration"
    ],
    "wof:name":"Avenue H Cleaners",
    "wof:placetype":"venue"
},
  "geometry": {"coordinates":[-73.963667,40.629695],"type":"Point"}
}