{
  "type": "Feature",
  "properties": {
    "iso:country":"US",
    "sg:address":"450 W 15th St",
    "sg:city":"New York",
    "sg:classifiers":[
        {
            "category":"Arts & Performance",
            "subcategory":"Art Gallery",
            "type":"Entertainment"
        }
    ],
    "sg:phone":"+1 212 940 1200",
    "sg:postcode":"10011",
    "sg:province":"NY",
    "sg:website":"www.phillipsdepury.com",
    "wof:name":"Phillips De Pury & Company",
    "wof:placetype":"venue"
},
  "geometry": {"coordinates":[-74.007355,40.742726],"type":"Point"}
}