{
  "type": "Feature",
  "properties": {
    "addr:full":"888 Salisbury Park Dr Westbury NY 11590",
    "addr:housenumber":"888",
    "addr:postcode":"11590",
    "addr:street":"Salisbury Park Dr",
    "iso:country":"US",
    "sg:address":"888 Salisbury Park Dr",
    "sg:city":"Westbury",
    "sg:classifiers":[
        {
            "category":"Building & Trades",
            "subcategory":"Construction",
            "type":"Services"
        }
    ],
    "sg:phone":"+1 516 997 6500",
    "sg:postcode":"11590",
    "sg:province":"NY",
    "sg:tags":[
        "general",
        "contractor"
    ],
    "wof:name":"Apollo Equity Assoc Imprvmts",
    "wof:placetype":"venue"
},
  "geometry": {"coordinates":[-73.57755899999999,40.744074],"type":"Point"}
}