{
  "type": "Feature",
  "properties": {
    "addr:full":"35 Androvette St Staten Island NY 10309",
    "addr:housenumber":"35",
    "addr:postcode":"10309",
    "addr:street":"Androvette St",
    "iso:country":"US",
    "sg:address":"35 Androvette St",
    "sg:city":"Staten Island",
    "sg:classifiers":[
        {
            "category":"Bars & Pubs",
            "type":"Food & Drink"
        }
    ],
    "sg:phone":"+1   ",
    "sg:postcode":"10309",
    "sg:province":"NY",
    "sg:tags":[
        "drinking"
    ],
    "wof:name":"Black Garter",
    "wof:placetype":"venue"
},
  "geometry": {"coordinates":[-74.236346,40.534892],"type":"Point"}
}