{
  "type": "Feature",
  "properties": {
    "addr:full":"8797 Genesee Tpke Chittenango NY 13037",
    "addr:housenumber":"8797",
    "addr:postcode":"13037",
    "addr:street":"Genesee Tpke",
    "iso:country":"US",
    "sg:address":"8797 Genesee Tpke",
    "sg:city":"Chittenango",
    "sg:classifiers":[
        {
            "category":"Home & Garden",
            "subcategory":"Garden Supply",
            "type":"Retail Goods"
        }
    ],
    "sg:phone":"+1 315 687 5282",
    "sg:postcode":"13037",
    "sg:province":"NY",
    "sg:tags":[
        "nurseryman"
    ],
    "sg:website":"www.aspinallstree.com",
    "wof:name":"Aspinall Landscaping & Nursery",
    "wof:placetype":"venue"
},
  "geometry": {"coordinates":[-75.921741,43.050874],"type":"Point"}
}