{
  "type": "Feature",
  "properties": {
    "addr:full":"175 E 79th St New York NY 10021",
    "addr:housenumber":"175",
    "addr:postcode":"10021",
    "addr:street":"E 79Th St",
    "iso:country":"US",
    "sg:address":"175 E 79th St",
    "sg:city":"New York",
    "sg:classifiers":[
        {
            "category":"Health Services",
            "subcategory":"Doctor",
            "type":"Services"
        }
    ],
    "sg:phone":"+1 212 249 7867",
    "sg:postcode":"10021",
    "sg:province":"NY",
    "wof:name":"Rosenblum Jay MD",
    "wof:placetype":"venue"
},
  "geometry": {"coordinates":[-73.95790100000001,40.774502],"type":"Point"}
}