{
  "type": "Feature",
  "properties": {
    "iso:country":"US",
    "sg:address":"11568 Gleason Rd",
    "sg:city":"Prattsburgh",
    "sg:classifiers":[
        {
            "category":"Restaurant",
            "type":"Food & Drink"
        },
        {
            "category":"Ice Cream",
            "type":"Food & Drink"
        }
    ],
    "sg:phone":"+1 607 522 6395",
    "sg:postcode":"14873",
    "sg:province":"NY",
    "sg:tags":[
        "frozen",
        "dessert"
    ],
    "sg:website":"http://www.lisafields.com",
    "wof:name":"Lisa Fields",
    "wof:placetype":"venue"
},
  "geometry": {"coordinates":[-77.321725,42.560592],"type":"Point"}
}