{
  "type": "Feature",
  "properties": {
    "addr:full":"1002 Quentin Rd Brooklyn NY 11223",
    "addr:housenumber":"1002",
    "addr:postcode":"11223",
    "addr:street":"Quentin Rd",
    "iso:country":"US",
    "sg:address":"1002 Quentin Rd",
    "sg:city":"Brooklyn",
    "sg:classifiers":[
        {
            "category":"Arts & Performance",
            "subcategory":"Theater",
            "type":"Entertainment"
        }
    ],
    "sg:phone":"+1 718 336 5129",
    "sg:postcode":"11223",
    "sg:province":"NY",
    "sg:tags":[
        "program",
        "radio",
        "producer"
    ],
    "wof:name":"WORLDTAINMENT.COM",
    "wof:placetype":"venue"
},
  "geometry": {"coordinates":[-73.96228600000001,40.607719],"type":"Point"}
}