{
  "type": "Feature",
  "properties": {
    "addr:full":"322 8th Ave Fl 11 New York NY 10001",
    "addr:housenumber":"322;11",
    "addr:postcode":"10001",
    "addr:street":"8Th Ave Fl",
    "iso:country":"US",
    "sg:address":"322 8th Ave Fl 11",
    "sg:city":"New York",
    "sg:classifiers":[
        {
            "category":"Real Estate",
            "subcategory":"Architect",
            "type":"Services"
        }
    ],
    "sg:phone":"+1 212 417 9496",
    "sg:postcode":"10001",
    "sg:province":"NY",
    "wof:name":"Cesar Pelli & Associates",
    "wof:placetype":"venue"
},
  "geometry": {"coordinates":[-73.99664,40.747105],"type":"Point"}
}