{
  "type": "Feature",
  "properties": {
    "iso:country":"US",
    "sg:address":"42 Pleasant Ave",
    "sg:city":"Schaghticoke",
    "sg:classifiers":[
        {
            "category":"Education",
            "subcategory":"School",
            "type":"Public Place"
        }
    ],
    "sg:phone":"+1 518 753 4450",
    "sg:postcode":"12154",
    "sg:province":"NY",
    "wof:name":"Hoosic Valley Central School",
    "wof:placetype":"venue"
},
  "geometry": {"coordinates":[-73.581384,42.905894],"type":"Point"}
}