{
  "type": "Feature",
  "properties": {
    "iso:country":"US",
    "sg:address":"201 W 52nd St",
    "sg:city":"New York",
    "sg:classifiers":[
        {
            "category":"Insurance",
            "subcategory":"Insurance Agent",
            "type":"Services"
        }
    ],
    "sg:phone":"+1 212 586 8311",
    "sg:postcode":"10019",
    "sg:province":"NY",
    "sg:tags":[
        "consultant"
    ],
    "sg:website":"www.emc-advisors.com",
    "wof:name":"Equity Maintenance Corp",
    "wof:placetype":"venue"
},
  "geometry": {"coordinates":[-73.983215,40.762707],"type":"Point"}
}