{
  "type": "Feature",
  "properties": {
    "addr:full":"55 Central Plz Ilion NY 13357",
    "addr:housenumber":"55",
    "addr:postcode":"13357",
    "addr:street":"Central Plz",
    "iso:country":"US",
    "sg:address":"55 Central Plz",
    "sg:city":"Ilion",
    "sg:classifiers":[
        {
            "category":"Shopping",
            "subcategory":"Discount & Variety Stores",
            "type":"Retail Goods"
        }
    ],
    "sg:phone":"+1 315 894 4554",
    "sg:postcode":"13357",
    "sg:province":"NY",
    "wof:name":"Mary's Place",
    "wof:placetype":"venue"
},
  "geometry": {"coordinates":[-75.036509,43.015281],"type":"Point"}
}