{
  "type": "Feature",
  "properties": {
    "addr:full":"134 W 32 St New York NY 10001",
    "addr:housenumber":"134",
    "addr:postcode":"10001",
    "addr:street":"W 32 St",
    "iso:country":"US",
    "sg:address":"134 W 32 St",
    "sg:city":"New York",
    "sg:classifiers":[
        {
            "category":"Building & Trades",
            "subcategory":"Plumbing",
            "type":"Services"
        }
    ],
    "sg:phone":"+1 212 613 9097",
    "sg:postcode":"10001",
    "sg:province":"NY",
    "sg:tags":[
        "plumbing",
        "contractor"
    ],
    "wof:name":"Nil Plumbing Inc",
    "wof:placetype":"venue"
},
  "geometry": {"coordinates":[-73.99084999999999,40.749225],"type":"Point"}
}