{
  "type": "Feature",
  "properties": {
    "iso:country":"US",
    "sg:address":"74 Pearl St",
    "sg:city":"New York",
    "sg:classifiers":[
        {
            "category":"Real Estate",
            "subcategory":"Real Estate Operator",
            "type":"Services"
        }
    ],
    "sg:phone":"+1 212 772 7372",
    "sg:postcode":"10004",
    "sg:province":"NY",
    "sg:tags":[
        "dwelling"
    ],
    "wof:name":"Jordan Ringel",
    "wof:placetype":"venue"
},
  "geometry": {"coordinates":[-74.009455,40.704447],"type":"Point"}
}