{
  "type": "Feature",
  "properties": {
    "addr:full":"3993 Austin Blvd Island Park NY 11558",
    "addr:housenumber":"3993",
    "addr:postcode":"11558",
    "addr:street":"Austin Blvd;Park",
    "iso:country":"US",
    "sg:address":"3993 Austin Blvd",
    "sg:city":"Island Park",
    "sg:classifiers":[
        {
            "category":"Food & Beverages",
            "subcategory":"Groceries & Convenience Stores",
            "type":"Retail Goods"
        }
    ],
    "sg:phone":"+1 516 431 2614",
    "sg:postcode":"11558",
    "sg:province":"NY",
    "sg:website":"www.7-eleven.com",
    "wof:name":"7-Eleven",
    "wof:placetype":"venue"
},
  "geometry": {"coordinates":[-73.644492,40.611703],"type":"Point"}
}