{
  "type": "Feature",
  "properties": {
    "iso:country":"US",
    "sg:address":"46 Pasadena Dr",
    "sg:city":"Plainview",
    "sg:classifiers":[
        {
            "category":"Health Services",
            "subcategory":"Doctor",
            "type":"Services"
        }
    ],
    "sg:phone":"+1 631 261 4400",
    "sg:postcode":"11803",
    "sg:province":"NY",
    "sg:tags":[
        "physician",
        "surgeon"
    ],
    "wof:name":"Avram R Gold MD",
    "wof:placetype":"venue"
},
  "geometry": {"coordinates":[-73.490393,40.777595],"type":"Point"}
}