{
  "type": "Feature",
  "properties": {
    "iso:country":"US",
    "sg:address":"350 State St",
    "sg:city":"Brooklyn",
    "sg:classifiers":[
        {
            "category":"Organizations",
            "subcategory":"Labor Organization",
            "type":"Services"
        }
    ],
    "sg:phone":"+1 718 858 2113",
    "sg:postcode":"11217",
    "sg:province":"NY",
    "sg:tags":[
        "city",
        "for",
        "union",
        "personnel",
        "transit",
        "authority",
        "york",
        "new"
    ],
    "wof:name":"Subway Supervisors Association",
    "wof:placetype":"venue"
},
  "geometry": {"coordinates":[-73.984877,40.687724],"type":"Point"}
}