{
  "type": "Feature",
  "properties": {
    "addr:full":"104 Sherwin Dr Tonawanda NY 14150",
    "addr:housenumber":"104",
    "addr:postcode":"14150",
    "addr:street":"Sherwin Dr",
    "iso:country":"US",
    "sg:address":"104 Sherwin Dr",
    "sg:city":"Tonawanda",
    "sg:classifiers":[
        {
            "category":"Organizations",
            "subcategory":"Religious Organization",
            "type":"Services"
        }
    ],
    "sg:phone":"+1 716 693 1898",
    "sg:postcode":"14150",
    "sg:province":"NY",
    "sg:tags":[
        "clergy"
    ],
    "wof:name":"E Werner Weinreich",
    "wof:placetype":"venue"
},
  "geometry": {"coordinates":[-78.82598900000001,43.01875],"type":"Point"}
}