{
  "type": "Feature",
  "properties": {
    "iso:country":"US",
    "sg:address":"47 W 34th St",
    "sg:city":"New York",
    "sg:classifiers":[
        {
            "category":"Professional",
            "subcategory":"Computer Services",
            "type":"Services"
        }
    ],
    "sg:phone":"+1 212 252 8447",
    "sg:postcode":"10001",
    "sg:province":"NY",
    "sg:tags":[
        "website",
        "design"
    ],
    "wof:name":"KIN Group",
    "wof:placetype":"venue"
},
  "geometry": {"coordinates":[-73.986599,40.749212],"type":"Point"}
}