{
  "type": "Feature",
  "properties": {
    "iso:country":"US",
    "sg:address":"5919 New Utrecht Ave",
    "sg:city":"Brooklyn",
    "sg:classifiers":[
        {
            "category":"Local Transit",
            "type":"Transportation"
        }
    ],
    "sg:phone":"+1 718 437 0200",
    "sg:postcode":"11219",
    "sg:province":"NY",
    "sg:tags":[
        "car"
    ],
    "wof:name":"Your II",
    "wof:placetype":"venue"
},
  "geometry": {"coordinates":[-73.996453,40.627773],"type":"Point"}
}