{
  "type": "Feature",
  "properties": {
    "addr:full":"306 Rutledge St Brooklyn NY 11211",
    "addr:housenumber":"306",
    "addr:postcode":"11211",
    "addr:street":"Rutledge St",
    "iso:country":"US",
    "sg:address":"306 Rutledge St",
    "sg:city":"Brooklyn",
    "sg:classifiers":[
        {
            "category":"Government",
            "subcategory":"Office",
            "type":"Public Place"
        }
    ],
    "sg:phone":"+1 718 387 1378",
    "sg:postcode":"11211",
    "sg:province":"NY",
    "sg:tags":[
        "village"
    ],
    "wof:name":"Bkn 03 District Sani Office",
    "wof:placetype":"venue"
},
  "geometry": {"coordinates":[-73.95129799999999,40.705634],"type":"Point"}
}