{
  "type": "Feature",
  "properties": {
    "addr:full":"3724 13th Ave Brooklyn NY 11218",
    "addr:housenumber":"3724",
    "addr:postcode":"11218",
    "addr:street":"13Th Ave",
    "iso:country":"US",
    "sg:address":"3724 13th Ave",
    "sg:city":"Brooklyn",
    "sg:classifiers":[
        {
            "category":"Restaurant",
            "type":"Food & Drink"
        }
    ],
    "sg:phone":"+1 718 686 7373",
    "sg:postcode":"11218",
    "sg:province":"NY",
    "sg:tags":[
        "delicatessen"
    ],
    "wof:name":"National Deli Grocery",
    "wof:placetype":"venue"
},
  "geometry": {"coordinates":[-73.98566,40.641369],"type":"Point"}
}