{
  "type": "Feature",
  "properties": {
    "iso:country":"US",
    "sg:address":"283 W Ferry St",
    "sg:city":"Buffalo",
    "sg:classifiers":[
        {
            "category":"Building & Trades",
            "subcategory":"Equipment Rental",
            "type":"Services"
        }
    ],
    "sg:phone":"+1 716 883 3435",
    "sg:postcode":"14213",
    "sg:province":"NY",
    "sg:tags":[
        "leasing",
        "furniture"
    ],
    "sg:website":"www.rentway.com",
    "wof:name":"Rent Way",
    "wof:placetype":"venue"
},
  "geometry": {"coordinates":[-78.891944,42.91516],"type":"Point"}
}