{
  "type": "Feature",
  "properties": {
    "addr:full":"70 E 55th St New York NY 10022",
    "addr:housenumber":"70",
    "addr:postcode":"10022",
    "addr:street":"E 55Th St",
    "iso:country":"US",
    "sg:address":"70 E 55th St",
    "sg:city":"New York",
    "sg:classifiers":[
        {
            "category":"Wholesale",
            "subcategory":"Computers",
            "type":"Manufacturing & Wholesale Goods"
        }
    ],
    "sg:phone":"+1 212 207 4602",
    "sg:postcode":"10022",
    "sg:province":"NY",
    "sg:website":"www.wildtangent.com",
    "wof:name":"Wildtangent",
    "wof:placetype":"venue"
},
  "geometry": {"coordinates":[-73.97248399999999,40.760487],"type":"Point"}
}