{
  "type": "Feature",
  "properties": {
    "iso:country":"US",
    "sg:address":"315 Wagner Ave",
    "sg:city":"Mamaroneck",
    "sg:classifiers":[
        {
            "category":"Professional",
            "subcategory":"Lawyer & Legal Services",
            "type":"Services"
        }
    ],
    "sg:phone":"+1   ",
    "sg:postcode":"10543",
    "sg:province":"NY",
    "wof:name":"Richard E Lanza",
    "wof:placetype":"venue"
},
  "geometry": {"coordinates":[-73.727076,40.957282],"type":"Point"}
}