{
  "type": "Feature",
  "properties": {
    "iso:country":"US",
    "sg:address":"2363 Southern Blvd",
    "sg:city":"Bronx",
    "sg:classifiers":[
        {
            "category":"Real Estate",
            "subcategory":"Real Estate Operator",
            "type":"Services"
        }
    ],
    "sg:phone":"+1 718 741 5030",
    "sg:postcode":"10460",
    "sg:province":"NY",
    "sg:tags":[
        "apartment"
    ],
    "wof:name":"Parkview Apartments",
    "wof:placetype":"venue"
},
  "geometry": {"coordinates":[-73.881804,40.853074],"type":"Point"}
}