{
  "type": "Feature",
  "properties": {
    "iso:country":"US",
    "sg:address":"821 Mclean Ave",
    "sg:city":"Yonkers",
    "sg:classifiers":[
        {
            "category":"Food & Beverages",
            "subcategory":"Groceries & Convenience Stores",
            "type":"Retail Goods"
        }
    ],
    "sg:phone":"+1 914 776 1145",
    "sg:postcode":"10704",
    "sg:province":"NY",
    "wof:name":"Irish Mini Market",
    "wof:placetype":"venue"
},
  "geometry": {"coordinates":[-73.87133799999999,40.906559],"type":"Point"}
}