{
  "type": "Feature",
  "properties": {
    "iso:country":"US",
    "sg:address":"223 Raritan Avenue",
    "sg:city":"Staten Island",
    "sg:classifiers":[
        {
            "category":"Building & Trades",
            "subcategory":"Cleaning & Sanitation",
            "type":"Services"
        }
    ],
    "sg:phone":"+1 718 983 6945",
    "sg:postcode":"10305",
    "sg:province":"NY",
    "sg:tags":[
        "carpet"
    ],
    "wof:name":"Grecco's Carpet Care",
    "wof:placetype":"venue"
},
  "geometry": {"coordinates":[-74.09193,40.59095],"type":"Point"}
}