{
  "type": "Feature",
  "properties": {
    "addr:full":"139 Centre St New York NY 10013",
    "addr:housenumber":"139",
    "addr:postcode":"10013",
    "addr:street":"Centre St",
    "iso:country":"US",
    "sg:address":"139 Centre St",
    "sg:city":"New York",
    "sg:classifiers":[
        {
            "category":"Manufacturing",
            "subcategory":"Printing",
            "type":"Manufacturing & Wholesale Goods"
        }
    ],
    "sg:phone":"+1 212 625 0751",
    "sg:postcode":"10013",
    "sg:province":"NY",
    "sg:tags":[
        "newspaper"
    ],
    "wof:name":"New York Post",
    "wof:placetype":"venue"
},
  "geometry": {"coordinates":[-74.00049199999999,40.717399],"type":"Point"}
}