{
  "type": "Feature",
  "properties": {
    "iso:country":"US",
    "sg:address":"136 Walnut St",
    "sg:city":"Lockport",
    "sg:classifiers":[
        {
            "category":"Shopping",
            "subcategory":"Computers & Home Electronics",
            "type":"Retail Goods"
        }
    ],
    "sg:phone":"+1 716 434 3360",
    "sg:postcode":"14094",
    "sg:province":"NY",
    "sg:tags":[
        "parts",
        "supply"
    ],
    "wof:name":"Laser Solutions",
    "wof:placetype":"venue"
},
  "geometry": {"coordinates":[-78.690888,43.168937],"type":"Point"}
}