{
  "type": "Feature",
  "properties": {
    "iso:country":"US",
    "sg:address":"526 W 47 St",
    "sg:city":"New York",
    "sg:classifiers":[
        {
            "category":"Building & Trades",
            "subcategory":"Electrical",
            "type":"Services"
        }
    ],
    "sg:phone":"+1 212 974 5585",
    "sg:postcode":"10036",
    "sg:province":"NY",
    "sg:tags":[
        "electrical",
        "contractor"
    ],
    "wof:name":"Advance Electric",
    "wof:placetype":"venue"
},
  "geometry": {"coordinates":[-73.99571299999999,40.763755],"type":"Point"}
}