{
  "type": "Feature",
  "properties": {
    "addr:full":"32 E Market St Corning NY 14830",
    "addr:housenumber":"32",
    "addr:postcode":"14830",
    "addr:street":"E Market St",
    "iso:country":"US",
    "sg:address":"32 E Market St",
    "sg:city":"Corning",
    "sg:classifiers":[
        {
            "category":"Restaurant",
            "type":"Food & Drink"
        }
    ],
    "sg:phone":"+1 607 937 3313",
    "sg:postcode":"14830",
    "sg:province":"NY",
    "wof:name":"Fat Cats",
    "wof:placetype":"venue"
},
  "geometry": {"coordinates":[-77.053541,42.143108],"type":"Point"}
}