{
  "type": "Feature",
  "properties": {
    "iso:country":"US",
    "sg:address":"1329 Vroom Rd",
    "sg:city":"Spencerport",
    "sg:classifiers":[
        {
            "category":"Shopping",
            "subcategory":"Computers & Home Electronics",
            "type":"Retail Goods"
        }
    ],
    "sg:phone":"+1   ",
    "sg:postcode":"14559",
    "sg:province":"NY",
    "wof:name":"Reliant Computer Services",
    "wof:placetype":"venue"
},
  "geometry": {"coordinates":[-77.82624199999999,43.157834],"type":"Point"}
}