{
  "type": "Feature",
  "properties": {
    "addr:full":"746 Franklin Ave Franklin Square NY 11010",
    "addr:housenumber":"746",
    "addr:postcode":"11010",
    "addr:street":"Franklin Ave",
    "iso:country":"US",
    "sg:address":"746 Franklin Ave",
    "sg:city":"Franklin Square",
    "sg:classifiers":[
        {
            "category":"Retail",
            "subcategory":"Laundry & Dry Cleaning",
            "type":"Services"
        }
    ],
    "sg:phone":"+1 516 872 0659",
    "sg:postcode":"11010",
    "sg:province":"NY",
    "wof:name":"Galaxy Cleaners",
    "wof:placetype":"venue"
},
  "geometry": {"coordinates":[-73.68620300000001,40.6884],"type":"Point"}
}