{
  "type": "Feature",
  "properties": {
    "addr:full":"448 Suffolk Ave Brentwood NY 11717",
    "addr:housenumber":"448",
    "addr:postcode":"11717",
    "addr:street":"Suffolk Ave",
    "iso:country":"US",
    "sg:address":"448 Suffolk Ave",
    "sg:city":"Brentwood",
    "sg:classifiers":[
        {
            "category":"Utilities",
            "subcategory":"Mobile Phone",
            "type":"Services"
        },
        {
            "category":"Shopping",
            "subcategory":"Mobile Phones",
            "type":"Retail Goods"
        },
        {
            "category":"Utilities",
            "subcategory":"Telephone",
            "type":"Services"
        },
        {
            "category":"Professional",
            "subcategory":"Computer Services",
            "type":"Services"
        }
    ],
    "sg:phone":"+1 631 617 6411",
    "sg:postcode":"11717",
    "sg:province":"NY",
    "sg:tags":[
        "telecommunication",
        "supply",
        "communication",
        "system",
        "wireless",
        "equipment",
        "cellular"
    ],
    "sg:website":"http://clickserve.dartsearch.net/link/click?lid=43000000308049899",
    "wof:name":"T-Mobile",
    "wof:placetype":"venue"
},
  "geometry": {"coordinates":[-73.258562,40.778398],"type":"Point"}
}