{
  "type": "Feature",
  "properties": {
    "iso:country":"US",
    "sg:address":"91 Lakewood Dr",
    "sg:city":"Congers",
    "sg:classifiers":[
        {
            "category":"Building & Trades",
            "subcategory":"Construction",
            "type":"Services"
        }
    ],
    "sg:phone":"+1 845 268 9102",
    "sg:postcode":"10920",
    "sg:province":"NY",
    "sg:tags":[
        "painter"
    ],
    "wof:name":"John Laurenzi Paint Contr",
    "wof:placetype":"venue"
},
  "geometry": {"coordinates":[-73.931827,41.15425],"type":"Point"}
}