{
  "type": "Feature",
  "properties": {
    "addr:full":"814 Hempstead Tpke Franklin Square NY 11010",
    "addr:housenumber":"814",
    "addr:postcode":"11010",
    "addr:street":"Hempstead Tpke",
    "iso:country":"US",
    "sg:address":"814 Hempstead Tpke",
    "sg:city":"Franklin Square",
    "sg:classifiers":[
        {
            "category":"Retail",
            "subcategory":"Auto Repair",
            "type":"Services"
        }
    ],
    "sg:phone":"+1 516 488 4449",
    "sg:postcode":"11010",
    "sg:province":"NY",
    "wof:name":"Vinnys Classic Garage Inc",
    "wof:placetype":"venue"
},
  "geometry": {"coordinates":[-73.669742,40.707047],"type":"Point"}
}