{
  "type": "Feature",
  "properties": {
    "iso:country":"US",
    "sg:address":"1353 Long Pond Rd",
    "sg:city":"Rochester",
    "sg:classifiers":[
        {
            "category":"Personal",
            "subcategory":"Beauty Salon",
            "type":"Services"
        }
    ],
    "sg:phone":"+1 585 227 1600",
    "sg:postcode":"14626",
    "sg:province":"NY",
    "sg:tags":[
        "shop"
    ],
    "wof:name":"Solutions Studio & Spa",
    "wof:placetype":"venue"
},
  "geometry": {"coordinates":[-77.696899,43.204713],"type":"Point"}
}