{
  "type": "Feature",
  "properties": {
    "addr:full":"319 W 42nd St New York NY 10036",
    "addr:housenumber":"319",
    "addr:postcode":"10036",
    "addr:street":"W 42Nd St",
    "iso:country":"US",
    "sg:address":"319 W 42nd St",
    "sg:city":"New York",
    "sg:classifiers":[
        {
            "category":"Shopping",
            "subcategory":"Discount & Variety Stores",
            "type":"Retail Goods"
        },
        {
            "category":"Shopping",
            "subcategory":"Bicycles & Sporting Goods",
            "type":"Retail Goods"
        }
    ],
    "sg:phone":"+1 212 757 5670",
    "sg:postcode":"10036",
    "sg:province":"NY",
    "sg:tags":[
        "parachute",
        "wholesale",
        "merchandise",
        "general"
    ],
    "sg:website":"www.kaufmansarmynavy.com",
    "wof:name":"Kaufman's Army & Navy",
    "wof:placetype":"venue"
},
  "geometry": {"coordinates":[-73.99220099999999,40.758276],"type":"Point"}
}