{
  "type": "Feature",
  "properties": {
    "iso:country":"US",
    "sg:address":"77 Pondfield Rd",
    "sg:city":"Bronxville",
    "sg:classifiers":[
        {
            "category":"Banks & Credit Unions",
            "subcategory":"Investment Brokerage",
            "type":"Services"
        }
    ],
    "sg:phone":"+1 914 771 5252",
    "sg:postcode":"10708",
    "sg:province":"NY",
    "sg:tags":[
        "advisory",
        "financial"
    ],
    "wof:name":"Griffin Organization",
    "wof:placetype":"venue"
},
  "geometry": {"coordinates":[-73.833259,40.940399],"type":"Point"}
}