{
  "type": "Feature",
  "properties": {
    "addr:full":"4465 Lake Shore Rd Hamburg NY 14075",
    "addr:housenumber":"4465",
    "addr:postcode":"14075",
    "addr:street":"Lake Shore Rd",
    "iso:country":"US",
    "sg:address":"4465 Lake Shore Rd",
    "sg:city":"Hamburg",
    "sg:classifiers":[
        {
            "category":"Shopping",
            "subcategory":"Clothing, Apparel, & Fashions",
            "type":"Retail Goods"
        }
    ],
    "sg:phone":"+1 716 947 4689",
    "sg:postcode":"14075",
    "sg:province":"NY",
    "sg:tags":[
        "tailor"
    ],
    "wof:name":"Pacifico Cleaners",
    "wof:placetype":"venue"
},
  "geometry": {"coordinates":[-78.878895,42.762639],"type":"Point"}
}