{
  "type": "Feature",
  "properties": {
    "addr:full":"3915 Flatlands Ave Brooklyn NY 11234",
    "addr:housenumber":"3915",
    "addr:postcode":"11234",
    "addr:street":"Flatlands Ave",
    "iso:country":"US",
    "sg:address":"3915 Flatlands Ave",
    "sg:city":"Brooklyn",
    "sg:classifiers":[
        {
            "category":"Organizations",
            "subcategory":"Non-profit Organization",
            "type":"Services"
        }
    ],
    "sg:phone":"+1 718 951 0515",
    "sg:postcode":"11234",
    "sg:province":"NY",
    "wof:name":"Flatlands Christian Ctr",
    "wof:placetype":"venue"
},
  "geometry": {"coordinates":[-73.934417,40.621854],"type":"Point"}
}