{
  "type": "Feature",
  "properties": {
    "addr:full":"2 Borthwick Ave Delmar NY 12054",
    "addr:housenumber":"2",
    "addr:postcode":"12054",
    "addr:street":"Borthwick Ave",
    "iso:country":"US",
    "sg:address":"2 Borthwick Ave",
    "sg:city":"Delmar",
    "sg:classifiers":[
        {
            "category":"Professional",
            "subcategory":"Detective & Security Services",
            "type":"Services"
        }
    ],
    "sg:phone":"+1 518 439 0595",
    "sg:postcode":"12054",
    "sg:province":"NY",
    "sg:tags":[
        "private",
        "investigator"
    ],
    "wof:name":"C.D.I. Investigations",
    "wof:placetype":"venue"
},
  "geometry": {"coordinates":[-73.841469,42.623749],"type":"Point"}
}