{
  "type": "Feature",
  "properties": {
    "iso:country":"US",
    "sg:address":"122 Saxon Ave",
    "sg:city":"Bay Shore",
    "sg:classifiers":[
        {
            "category":"Freight",
            "type":"Transportation"
        }
    ],
    "sg:phone":"+1 631 666 7245",
    "sg:postcode":"11706",
    "sg:province":"NY",
    "sg:tags":[
        "commercial",
        "storage",
        "general"
    ],
    "sg:website":"www.publicstorage.com",
    "wof:name":"Public Storage Inc",
    "wof:placetype":"venue"
},
  "geometry": {"coordinates":[-73.22860799999999,40.73775],"type":"Point"}
}