{
  "type": "Feature",
  "properties": {
    "addr:full":"8 Livingston St Huntington Sta NY 11746",
    "addr:housenumber":"8",
    "addr:postcode":"11746",
    "addr:street":"Livingston St",
    "iso:country":"US",
    "sg:address":"8 Livingston St",
    "sg:city":"Huntington Sta",
    "sg:classifiers":[
        {
            "category":"Arts & Performance",
            "subcategory":"Theater",
            "type":"Entertainment"
        }
    ],
    "sg:phone":"+1 631 427 9759",
    "sg:postcode":"11746",
    "sg:province":"NY",
    "sg:tags":[
        "entertainer"
    ],
    "sg:website":"www.tailoredevents.net",
    "wof:name":"Tailored Tunes Singing Tlgrms",
    "wof:placetype":"venue"
},
  "geometry": {"coordinates":[-73.41577100000001,40.82038],"type":"Point"}
}