{
  "type": "Feature",
  "properties": {
    "addr:full":"1698 E 14th St Brooklyn NY 11229",
    "addr:housenumber":"1698",
    "addr:postcode":"11229",
    "addr:street":"E 14Th St",
    "iso:country":"US",
    "sg:address":"1698 E 14th St",
    "sg:city":"Brooklyn",
    "sg:classifiers":[
        {
            "category":"Food & Beverages",
            "subcategory":"Groceries & Convenience Stores",
            "type":"Retail Goods"
        }
    ],
    "sg:phone":"+1 718 375 6462",
    "sg:postcode":"11229",
    "sg:province":"NY",
    "sg:tags":[
        "grocer"
    ],
    "wof:name":"S & E 14th Street Market",
    "wof:placetype":"venue"
},
  "geometry": {"coordinates":[-73.958764,40.605975],"type":"Point"}
}