{
  "type": "Feature",
  "properties": {
    "iso:country":"US",
    "sg:address":"138 Wortman Ave",
    "sg:city":"Brooklyn",
    "sg:classifiers":[
        {
            "category":"Shopping",
            "subcategory":"Beauty & Cosmetics",
            "type":"Retail Goods"
        }
    ],
    "sg:phone":"+1   ",
    "sg:postcode":"11207",
    "sg:province":"NY",
    "sg:tags":[
        "merchandise"
    ],
    "wof:name":"M & M Plaza Inc",
    "wof:placetype":"venue"
},
  "geometry": {"coordinates":[-73.887894,40.655543],"type":"Point"}
}