{
  "type": "Feature",
  "properties": {
    "iso:country":"US",
    "sg:address":"800 Grand Concourse",
    "sg:city":"Bronx",
    "sg:classifiers":[
        {
            "category":"Building & Trades",
            "subcategory":"Landscaping Services",
            "type":"Services"
        }
    ],
    "sg:phone":"+1 917 202 1006",
    "sg:postcode":"10451",
    "sg:province":"NY",
    "sg:tags":[
        "landscape",
        "contractor"
    ],
    "wof:name":"Glorietta Group",
    "wof:placetype":"venue"
},
  "geometry": {"coordinates":[-73.92377500000001,40.824389],"type":"Point"}
}