{
  "type": "Feature",
  "properties": {
    "iso:country":"US",
    "sg:address":"3760 Main St",
    "sg:city":"Warrensburg",
    "sg:classifiers":[
        {
            "category":"Travel",
            "subcategory":"Hotels & Motels",
            "type":"Entertainment"
        }
    ],
    "sg:phone":"+1 518 623 3640",
    "sg:postcode":"12885",
    "sg:province":"NY",
    "wof:name":"White House Lodge",
    "wof:placetype":"venue"
},
  "geometry": {"coordinates":[-73.767697,43.492037],"type":"Point"}
}