{
  "type": "Feature",
  "properties": {
    "addr:full":"215 Alexander Ave Bronx NY 10454",
    "addr:housenumber":"215",
    "addr:postcode":"10454",
    "addr:street":"Alexander Ave",
    "iso:country":"US",
    "sg:address":"215 Alexander Ave",
    "sg:city":"Bronx",
    "sg:classifiers":[
        {
            "category":"Government",
            "subcategory":"Office",
            "type":"Public Place"
        }
    ],
    "sg:phone":"+1 718 993 0683",
    "sg:postcode":"10454",
    "sg:province":"NY",
    "sg:tags":[
        "housing",
        "program"
    ],
    "wof:name":"Mitchell Housing",
    "wof:placetype":"venue"
},
  "geometry": {"coordinates":[-73.925315,40.809895],"type":"Point"}
}