{
  "type": "Feature",
  "properties": {
    "iso:country":"US",
    "sg:address":"400 Sheffield Ave",
    "sg:city":"West Babylon",
    "sg:classifiers":[
        {
            "category":"Manufacturing",
            "subcategory":"Paper Products",
            "type":"Manufacturing & Wholesale Goods"
        }
    ],
    "sg:phone":"+1 631 669 9792",
    "sg:postcode":"11704",
    "sg:province":"NY",
    "sg:tags":[
        "fiber"
    ],
    "sg:website":"www.americanacrylic.com",
    "wof:name":"Amer Acrylic Corp",
    "wof:placetype":"venue"
},
  "geometry": {"coordinates":[-73.33653700000001,40.719169],"type":"Point"}
}