{
  "type": "Feature",
  "properties": {
    "iso:country":"US",
    "sg:address":"1130 Zerega Avenue",
    "sg:city":"Bronx",
    "sg:classifiers":[
        {
            "category":"Retail",
            "subcategory":"Auto Rental",
            "type":"Services"
        }
    ],
    "sg:phone":"+1 718 239 1725",
    "sg:postcode":"10462",
    "sg:province":"NY",
    "sg:tags":[
        "car"
    ],
    "wof:name":"Trucknology Truck Rental",
    "wof:placetype":"venue"
},
  "geometry": {"coordinates":[-73.844494,40.831574],"type":"Point"}
}