{
  "type": "Feature",
  "properties": {
    "addr:full":"9801 3rd Ave Brooklyn NY 11209",
    "addr:housenumber":"9801",
    "addr:postcode":"11209",
    "addr:street":"3Rd Ave",
    "iso:country":"US",
    "sg:address":"9801 3rd Ave",
    "sg:city":"Brooklyn",
    "sg:classifiers":[
        {
            "category":"Deli",
            "type":"Food & Drink"
        },
        {
            "category":"Food & Beverages",
            "subcategory":"Bakery",
            "type":"Retail Goods"
        }
    ],
    "sg:phone":"+1 718 836 1913",
    "sg:postcode":"11209",
    "sg:province":"NY",
    "sg:tags":[
        "sandwich"
    ],
    "wof:name":"D'agostino Deli",
    "wof:placetype":"venue"
},
  "geometry": {"coordinates":[-74.03449999999999,40.614799],"type":"Point"}
}