{
  "type": "Feature",
  "properties": {
    "addr:full":"146 Glenmore Rd Eagle Bay NY 13331",
    "addr:housenumber":"146",
    "addr:postcode":"13331",
    "addr:street":"Glenmore Rd",
    "iso:country":"US",
    "sg:address":"146 Glenmore Rd",
    "sg:city":"Eagle Bay",
    "sg:classifiers":[
        {
            "category":"Bars & Pubs",
            "type":"Food & Drink"
        }
    ],
    "sg:phone":"+1   ",
    "sg:postcode":"13331",
    "sg:province":"NY",
    "sg:tags":[
        "drinking",
        "eating"
    ],
    "wof:name":"Glenmore Bar & Grill",
    "wof:placetype":"venue"
},
  "geometry": {"coordinates":[-74.884089,43.819768],"type":"Point"}
}