{
  "type": "Feature",
  "properties": {
    "iso:country":"US",
    "sg:address":"874 Long Island Ave",
    "sg:city":"Deer Park",
    "sg:classifiers":[
        {
            "category":"Professional",
            "subcategory":"Business Services",
            "type":"Services"
        }
    ],
    "sg:phone":"+1 631 254 2218",
    "sg:postcode":"11729",
    "sg:province":"NY",
    "wof:name":"ASAP",
    "wof:placetype":"venue"
},
  "geometry": {"coordinates":[-73.31713499999999,40.764627],"type":"Point"}
}