{
  "type": "Feature",
  "properties": {
    "iso:country":"US",
    "sg:address":"183 Broadway",
    "sg:city":"Amityville",
    "sg:classifiers":[
        {
            "category":"Personal",
            "subcategory":"Beauty Salon",
            "type":"Services"
        }
    ],
    "sg:phone":"+1   ",
    "sg:postcode":"11701",
    "sg:province":"NY",
    "sg:tags":[
        "shop"
    ],
    "wof:name":"Styles On Broadway",
    "wof:placetype":"venue"
},
  "geometry": {"coordinates":[-73.41739200000001,40.677507],"type":"Point"}
}