{
  "type": "Feature",
  "properties": {
    "addr:full":"224 Lake St Elmira NY 14901",
    "addr:housenumber":"224",
    "addr:postcode":"14901",
    "addr:street":"Lake St",
    "iso:country":"US",
    "sg:address":"224 Lake St",
    "sg:city":"Elmira",
    "sg:classifiers":[
        {
            "category":"Government",
            "subcategory":"Office",
            "type":"Public Place"
        }
    ],
    "sg:phone":"+1 607 737 2940",
    "sg:postcode":"14901",
    "sg:province":"NY",
    "sg:tags":[
        "executive"
    ],
    "wof:name":"Judge Buckley Chamber",
    "wof:placetype":"venue"
},
  "geometry": {"coordinates":[-76.801799,42.090037],"type":"Point"}
}