{
  "type": "Feature",
  "properties": {
    "addr:full":"2254 Cedar Ave Bronx NY 10468",
    "addr:housenumber":"2254",
    "addr:postcode":"10468",
    "addr:street":"Cedar Ave",
    "iso:country":"US",
    "sg:address":"2254 Cedar Ave",
    "sg:city":"Bronx",
    "sg:classifiers":[
        {
            "category":"Arts & Performance",
            "subcategory":"Theater",
            "type":"Entertainment"
        }
    ],
    "sg:phone":"+1 718 561 4034",
    "sg:postcode":"10468",
    "sg:province":"NY",
    "sg:tags":[
        "bureau"
    ],
    "wof:name":"RDK Entertainment Inc",
    "wof:placetype":"venue"
},
  "geometry": {"coordinates":[-73.911081,40.862161],"type":"Point"}
}