{
  "type": "Feature",
  "properties": {
    "addr:full":"450 Atlantic Ave Brooklyn NY 11217",
    "addr:housenumber":"450",
    "addr:postcode":"11217",
    "addr:street":"Atlantic Ave",
    "iso:country":"US",
    "sg:address":"450 Atlantic Ave",
    "sg:city":"Brooklyn",
    "sg:classifiers":[
        {
            "category":"Shopping",
            "type":"Retail Goods"
        }
    ],
    "sg:phone":"+1 718 875 5366",
    "sg:postcode":"11217",
    "sg:province":"NY",
    "sg:tags":[
        "religious"
    ],
    "wof:name":"Islamic Books & Tapes",
    "wof:placetype":"venue"
},
  "geometry": {"coordinates":[-73.98404499999999,40.686712],"type":"Point"}
}