{
  "type": "Feature",
  "properties": {
    "iso:country":"US",
    "sg:address":"267 Woodbury Rd",
    "sg:city":"Huntington",
    "sg:classifiers":[
        {
            "category":"Manufacturing",
            "subcategory":"Printing",
            "type":"Manufacturing & Wholesale Goods"
        }
    ],
    "sg:phone":"+1   ",
    "sg:postcode":"11743",
    "sg:province":"NY",
    "sg:tags":[
        "book"
    ],
    "wof:name":"Angels Fore Press",
    "wof:placetype":"venue"
},
  "geometry": {"coordinates":[-73.437231,40.862153],"type":"Point"}
}