{
  "type": "Feature",
  "properties": {
    "iso:country":"US",
    "sg:address":"118 W Main St",
    "sg:city":"Riverhead",
    "sg:classifiers":[
        {
            "category":"Building & Trades",
            "subcategory":"Equipment Rental",
            "type":"Services"
        }
    ],
    "sg:phone":"+1 631 727 9429",
    "sg:postcode":"11901",
    "sg:province":"NY",
    "sg:tags":[
        "leasing",
        "furniture"
    ],
    "wof:name":"National Rental Svc Inc",
    "wof:placetype":"venue"
},
  "geometry": {"coordinates":[-72.663043,40.917003],"type":"Point"}
}