{
  "type": "Feature",
  "properties": {
    "iso:country":"US",
    "sg:address":"273 N Central Ave",
    "sg:city":"Hartsdale",
    "sg:classifiers":[
        {
            "category":"Wholesale",
            "subcategory":"Jewelry",
            "type":"Manufacturing & Wholesale Goods"
        },
        {
            "category":"Shopping",
            "subcategory":"Jewelry",
            "type":"Retail Goods"
        },
        {
            "category":"Manufacturing",
            "subcategory":"Jewelry",
            "type":"Manufacturing & Wholesale Goods"
        },
        {
            "category":"Shopping",
            "subcategory":"Hobbies, Toys, & Games",
            "type":"Retail Goods"
        }
    ],
    "sg:phone":"+1 914 949 0481",
    "sg:postcode":"10530",
    "sg:province":"NY",
    "sg:tags":[
        "shop",
        "diamonds-wholesale",
        "designer",
        "supply",
        "jeweler",
        "hobby",
        "model",
        "coin"
    ],
    "sg:website":"http://www.larrytownjewelers.com",
    "wof:name":"Westchester Estate Buyers",
    "wof:placetype":"venue"
},
  "geometry": {"coordinates":[-73.792835,41.024393],"type":"Point"}
}