{
  "type": "Feature",
  "properties": {
    "addr:full":"1231 Broadway Brooklyn NY 11221",
    "addr:housenumber":"1231",
    "addr:postcode":"11221",
    "addr:street":"Broadway",
    "iso:country":"US",
    "sg:address":"1231 Broadway",
    "sg:city":"Brooklyn",
    "sg:classifiers":[
        {
            "category":"Home & Garden",
            "subcategory":"Furniture",
            "type":"Retail Goods"
        }
    ],
    "sg:phone":"+1 718 453 5555",
    "sg:postcode":"11221",
    "sg:province":"NY",
    "wof:name":"Stop Furniture Store",
    "wof:placetype":"venue"
},
  "geometry": {"coordinates":[-73.925743,40.691725],"type":"Point"}
}