{
  "type": "Feature",
  "properties": {
    "iso:country":"US",
    "sg:address":"6614 14th Ave",
    "sg:city":"Brooklyn",
    "sg:classifiers":[
        {
            "category":"Shopping",
            "subcategory":"Clothing, Apparel, & Fashions",
            "type":"Retail Goods"
        }
    ],
    "sg:phone":"+1 718 236 3107",
    "sg:postcode":"11219",
    "sg:province":"NY",
    "sg:tags":[
        "tailor"
    ],
    "wof:name":"Emerly Tailoring",
    "wof:placetype":"venue"
},
  "geometry": {"coordinates":[-74.00052599999999,40.623617],"type":"Point"}
}