{
  "type": "Feature",
  "properties": {
    "iso:country":"US",
    "sg:address":"1167 Broadway",
    "sg:city":"Hewlett",
    "sg:classifiers":[
        {
            "category":"Personal",
            "subcategory":"Shoe Repair & Shine",
            "type":"Services"
        }
    ],
    "sg:phone":"+1 516 374 5982",
    "sg:postcode":"11557",
    "sg:province":"NY",
    "wof:name":"Kang's Shoe Repair",
    "wof:placetype":"venue"
},
  "geometry": {"coordinates":[-73.704498,40.6348],"type":"Point"}
}