{
  "type": "Feature",
  "properties": {
    "iso:country":"US",
    "sg:address":"92 Whitney Pl",
    "sg:city":"Buffalo",
    "sg:classifiers":[
        {
            "category":"Personal",
            "subcategory":"Beauty Salon",
            "type":"Services"
        }
    ],
    "sg:phone":"+1 716 854 5584",
    "sg:postcode":"14201",
    "sg:province":"NY",
    "wof:name":"Liz's Nail Salon",
    "wof:placetype":"venue"
},
  "geometry": {"coordinates":[-78.882554,42.89405],"type":"Point"}
}