{
  "type": "Feature",
  "properties": {
    "addr:full":"3570 White Plains Rd Bronx NY 10467",
    "addr:housenumber":"3570",
    "addr:postcode":"10467",
    "addr:street":"White Plains Rd",
    "iso:country":"US",
    "sg:address":"3570 White Plains Rd",
    "sg:city":"Bronx",
    "sg:classifiers":[
        {
            "category":"Shopping",
            "subcategory":"Beauty & Cosmetics",
            "type":"Retail Goods"
        }
    ],
    "sg:phone":"+1   ",
    "sg:postcode":"10467",
    "sg:province":"NY",
    "sg:tags":[
        "hair",
        "product",
        "care"
    ],
    "wof:name":"Kiss Beauty Supply",
    "wof:placetype":"venue"
},
  "geometry": {"coordinates":[-73.865353,40.878981],"type":"Point"}
}