{
  "type": "Feature",
  "properties": {
    "iso:country":"US",
    "sg:address":"8914 Ditmas Ave",
    "sg:city":"Brooklyn",
    "sg:classifiers":[
        {
            "category":"Retail",
            "subcategory":"Auto Repair",
            "type":"Services"
        }
    ],
    "sg:phone":"+1   ",
    "sg:postcode":"11236",
    "sg:province":"NY",
    "sg:tags":[
        "shop",
        "automotive",
        "gasoline",
        "general"
    ],
    "wof:name":"Amoco",
    "wof:placetype":"venue"
},
  "geometry": {"coordinates":[-73.914767,40.647973],"type":"Point"}
}