{
  "type": "Feature",
  "properties": {
    "addr:full":"21 Springside Ave Poughkeepsie NY 12603",
    "addr:housenumber":"21",
    "addr:postcode":"12603",
    "addr:street":"Springside Ave",
    "iso:country":"US",
    "sg:address":"21 Springside Ave",
    "sg:city":"Poughkeepsie",
    "sg:classifiers":[
        {
            "category":"Health Services",
            "subcategory":"Doctor",
            "type":"Services"
        }
    ],
    "sg:phone":"+1 845 485 2720",
    "sg:postcode":"12603",
    "sg:province":"NY",
    "sg:tags":[
        "physician",
        "surgeon"
    ],
    "wof:name":"Thomas S Robinson MD",
    "wof:placetype":"venue"
},
  "geometry": {"coordinates":[-73.903347,41.697255],"type":"Point"}
}