{
  "type": "Feature",
  "properties": {
    "iso:country":"US",
    "sg:address":"54 Mathias Ave",
    "sg:city":"Amsterdam",
    "sg:classifiers":[
        {
            "category":"Building & Trades",
            "subcategory":"Cleaning & Sanitation",
            "type":"Services"
        }
    ],
    "sg:phone":"+1   ",
    "sg:postcode":"12010",
    "sg:province":"NY",
    "sg:tags":[
        "maintenance"
    ],
    "wof:name":"Miles Cleaning Services",
    "wof:placetype":"venue"
},
  "geometry": {"coordinates":[-74.175026,42.933235],"type":"Point"}
}