{
  "type": "Feature",
  "properties": {
    "iso:country":"US",
    "sg:address":"30 Warren Pl",
    "sg:city":"Mount Vernon",
    "sg:classifiers":[
        {
            "category":"Manufacturing",
            "subcategory":"Jewelry",
            "type":"Manufacturing & Wholesale Goods"
        }
    ],
    "sg:phone":"+1   ",
    "sg:postcode":"10550",
    "sg:province":"NY",
    "sg:tags":[
        "home",
        "import",
        "accessory"
    ],
    "wof:name":"Passport Collections",
    "wof:placetype":"venue"
},
  "geometry": {"coordinates":[-73.82666399999999,40.896108],"type":"Point"}
}