{
  "type": "Feature",
  "properties": {
    "addr:full":"727 Marjorie Ln Endicott NY 13760",
    "addr:housenumber":"727",
    "addr:postcode":"13760",
    "addr:street":"Marjorie Ln",
    "iso:country":"US",
    "sg:address":"727 Marjorie Ln",
    "sg:city":"Endicott",
    "sg:classifiers":[
        {
            "category":"Building & Trades",
            "subcategory":"Landscaping Services",
            "type":"Services"
        }
    ],
    "sg:phone":"+1 607 785 1499",
    "sg:postcode":"13760",
    "sg:province":"NY",
    "sg:tags":[
        "landscape",
        "contractor"
    ],
    "wof:name":"Paniccia Group",
    "wof:placetype":"venue"
},
  "geometry": {"coordinates":[-76.05588400000001,42.123002],"type":"Point"}
}