{
  "type": "Feature",
  "properties": {
    "addr:full":"16 Hillcrest Ave Port Jefferson NY 11777",
    "addr:housenumber":"16",
    "addr:postcode":"11777",
    "addr:street":"Hillcrest Ave",
    "iso:country":"US",
    "sg:address":"16 Hillcrest Ave",
    "sg:city":"Port Jefferson",
    "sg:classifiers":[
        {
            "category":"Manufacturing",
            "subcategory":"Furniture",
            "type":"Manufacturing & Wholesale Goods"
        }
    ],
    "sg:phone":"+1 631 831 5638",
    "sg:postcode":"11777",
    "sg:province":"NY",
    "sg:tags":[
        "metal"
    ],
    "wof:name":"Dragon Iron",
    "wof:placetype":"venue"
},
  "geometry": {"coordinates":[-73.046134,40.940025],"type":"Point"}
}