{
  "type": "Feature",
  "properties": {
    "addr:full":"13 Holbrook Ave Yonkers NY 10710",
    "addr:housenumber":"13",
    "addr:postcode":"10710",
    "addr:street":"Holbrook Ave",
    "iso:country":"US",
    "sg:address":"13 Holbrook Ave",
    "sg:city":"Yonkers",
    "sg:classifiers":[
        {
            "category":"Manufacturing",
            "subcategory":"Motor Vehicles & Parts",
            "type":"Manufacturing & Wholesale Goods"
        }
    ],
    "sg:phone":"+1   ",
    "sg:postcode":"10710",
    "sg:province":"NY",
    "sg:tags":[
        "mfg",
        "trimming"
    ],
    "wof:name":"Funforbridescom",
    "wof:placetype":"venue"
},
  "geometry": {"coordinates":[-73.841151,40.960454],"type":"Point"}
}