{
  "type": "Feature",
  "properties": {
    "iso:country":"US",
    "sg:address":"94 Grand St",
    "sg:city":"New York",
    "sg:classifiers":[
        {
            "category":"Manufacturing",
            "subcategory":"Tools & Machinery",
            "type":"Manufacturing & Wholesale Goods"
        }
    ],
    "sg:phone":"+1   ",
    "sg:postcode":"10013",
    "sg:province":"NY",
    "sg:tags":[
        "equipment",
        "heating",
        "mfg"
    ],
    "wof:name":"Fisonic Corp",
    "wof:placetype":"venue"
},
  "geometry": {"coordinates":[-74.001571,40.721421],"type":"Point"}
}