{
  "type": "Feature",
  "properties": {
    "addr:full":"1403 Foster Ave Brooklyn NY 11230",
    "addr:housenumber":"1403",
    "addr:postcode":"11230",
    "addr:street":"Foster Ave",
    "iso:country":"US",
    "sg:address":"1403 Foster Ave",
    "sg:city":"Brooklyn",
    "sg:classifiers":[
        {
            "category":"Building & Trades",
            "subcategory":"Construction",
            "type":"Services"
        }
    ],
    "sg:phone":"+1 718 859 4833",
    "sg:postcode":"11230",
    "sg:province":"NY",
    "sg:tags":[
        "general",
        "contractor"
    ],
    "wof:name":"S N Ahmed & Sons Construction",
    "wof:placetype":"venue"
},
  "geometry": {"coordinates":[-73.96315800000001,40.63412],"type":"Point"}
}