{
  "type": "Feature",
  "properties": {
    "addr:full":"3605 12th Ave Brooklyn NY 11218",
    "addr:housenumber":"3605",
    "addr:postcode":"11218",
    "addr:street":"12Th Ave",
    "iso:country":"US",
    "sg:address":"3605 12th Ave",
    "sg:city":"Brooklyn",
    "sg:classifiers":[
        {
            "category":"Retail",
            "subcategory":"Auto Repair",
            "type":"Services"
        }
    ],
    "sg:phone":"+1 718 633 5575",
    "sg:postcode":"11218",
    "sg:province":"NY",
    "wof:name":"I & R Auto Rpr",
    "wof:placetype":"venue"
},
  "geometry": {"coordinates":[-73.98670199999999,40.643501],"type":"Point"}
}