{
  "type": "Feature",
  "properties": {
    "addr:full":"65 South Ave Salamanca NY 14779",
    "addr:housenumber":"65",
    "addr:postcode":"14779",
    "addr:street":"South Ave",
    "iso:country":"US",
    "sg:address":"65 South Ave",
    "sg:city":"Salamanca",
    "sg:classifiers":[
        {
            "category":"Social Services",
            "subcategory":"Job Training",
            "type":"Services"
        }
    ],
    "sg:phone":"+1 716 945 4430",
    "sg:postcode":"14779",
    "sg:province":"NY",
    "sg:tags":[
        "rehabilitation"
    ],
    "wof:name":"Rehabilitation Center",
    "wof:placetype":"venue"
},
  "geometry": {"coordinates":[-78.71973800000001,42.151624],"type":"Point"}
}