{
  "type": "Feature",
  "properties": {
    "iso:country":"US",
    "sg:address":"70 Elm St",
    "sg:city":"Mayville",
    "sg:classifiers":[
        {
            "category":"Building & Trades",
            "subcategory":"Plumbing",
            "type":"Services"
        }
    ],
    "sg:phone":"+1 716 753 3371",
    "sg:postcode":"14757",
    "sg:province":"NY",
    "sg:tags":[
        "contractor"
    ],
    "wof:name":"Cummings Plumbing & Heating",
    "wof:placetype":"venue"
},
  "geometry": {"coordinates":[-79.49890000000001,42.251866],"type":"Point"}
}