{
  "type": "Feature",
  "properties": {
    "iso:country":"US",
    "sg:address":"6 Thorn Ln",
    "sg:city":"Nanuet",
    "sg:classifiers":[
        {
            "category":"Restaurant",
            "type":"Food & Drink"
        }
    ],
    "sg:phone":"+1 845 624 7555",
    "sg:postcode":"10954",
    "sg:province":"NY",
    "sg:tags":[
        "caterer"
    ],
    "wof:name":"A Hostess Helper",
    "wof:placetype":"venue"
},
  "geometry": {"coordinates":[-74.030575,41.096775],"type":"Point"}
}