{
  "type": "Feature",
  "properties": {
    "addr:full":"638 Rachel Dr Yorktown Heights NY 10598",
    "addr:housenumber":"638",
    "addr:postcode":"10598",
    "addr:street":"Rachel Dr",
    "iso:country":"US",
    "sg:address":"638 Rachel Dr",
    "sg:city":"Yorktown Heights",
    "sg:classifiers":[
        {
            "category":"Restaurant",
            "type":"Food & Drink"
        }
    ],
    "sg:phone":"+1   ",
    "sg:postcode":"10598",
    "sg:province":"NY",
    "sg:tags":[
        "carry"
    ],
    "wof:name":"Jean-Jacques Culinary Creat",
    "wof:placetype":"venue"
},
  "geometry": {"coordinates":[-73.80546699999999,41.316521],"type":"Point"}
}