{
  "type": "Feature",
  "properties": {
    "iso:country":"US",
    "sg:address":"33 Farley Dr",
    "sg:city":"Rensselaer",
    "sg:classifiers":[
        {
            "category":"Shopping",
            "subcategory":"Gifts & Souvenirs",
            "type":"Retail Goods"
        }
    ],
    "sg:phone":"+1   ",
    "sg:postcode":"12144",
    "sg:province":"NY",
    "wof:name":"Undercovers",
    "wof:placetype":"venue"
},
  "geometry": {"coordinates":[-73.718014,42.658358],"type":"Point"}
}