{
  "type": "Feature",
  "properties": {
    "iso:country":"US",
    "sg:address":"3629 Oxford Rd",
    "sg:city":"New Hartford",
    "sg:classifiers":[
        {
            "category":"Utilities",
            "subcategory":"Refuse",
            "type":"Services"
        }
    ],
    "sg:phone":"+1   ",
    "sg:postcode":"13413",
    "sg:province":"NY",
    "sg:tags":[
        "system"
    ],
    "wof:name":"Marshall Przyluke Inc",
    "wof:placetype":"venue"
},
  "geometry": {"coordinates":[-75.27660899999999,43.038593],"type":"Point"}
}