{
  "type": "Feature",
  "properties": {
    "addr:full":"191 State Hwy 17 Tuxedo Park NY 10987",
    "addr:housenumber":"191",
    "addr:postcode":"10987",
    "addr:street":"State Hwy 17",
    "iso:country":"US",
    "sg:address":"191 State Hwy 17",
    "sg:city":"Tuxedo Park",
    "sg:classifiers":[
        {
            "category":"Autos & Motor Vehicles",
            "subcategory":"Fuel & Gas Station",
            "type":"Retail Goods"
        }
    ],
    "sg:phone":"+1   ",
    "sg:postcode":"10987",
    "sg:province":"NY",
    "sg:tags":[
        "station"
    ],
    "wof:name":"Gulf",
    "wof:placetype":"venue"
},
  "geometry": {"coordinates":[-74.184302,41.190867],"type":"Point"}
}