{
  "type": "Feature",
  "properties": {
    "addr:full":"869 Mclean Ave Yonkers NY 10704",
    "addr:housenumber":"869",
    "addr:postcode":"10704",
    "addr:street":"Mclean Ave",
    "iso:country":"US",
    "sg:address":"869 Mclean Ave",
    "sg:city":"Yonkers",
    "sg:classifiers":[
        {
            "category":"Bars & Pubs",
            "type":"Food & Drink"
        }
    ],
    "sg:phone":"+1 914 237 2320",
    "sg:postcode":"10704",
    "sg:province":"NY",
    "sg:tags":[
        "tavern"
    ],
    "wof:name":"Fibber Magee's",
    "wof:placetype":"venue"
},
  "geometry": {"coordinates":[-73.86992499999999,40.905314],"type":"Point"}
}