{
  "type": "Feature",
  "properties": {
    "addr:full":"33 Quarry Rd Ithaca NY 14850",
    "addr:housenumber":"33",
    "addr:postcode":"14850",
    "addr:street":"Quarry Rd",
    "iso:country":"US",
    "sg:address":"33 Quarry Rd",
    "sg:city":"Ithaca",
    "sg:classifiers":[
        {
            "category":"Mining & Drilling",
            "type":"Manufacturing & Wholesale Goods"
        }
    ],
    "sg:phone":"+1 607 273 4646",
    "sg:postcode":"14850",
    "sg:province":"NY",
    "sg:tags":[
        "building",
        "stone",
        "producing",
        "quarry"
    ],
    "sg:website":"www.fingerlakesstone.net",
    "wof:name":"Finger Lakes Stone Co Inc",
    "wof:placetype":"venue"
},
  "geometry": {"coordinates":[-76.427509,42.423531],"type":"Point"}
}