{
  "type": "Feature",
  "properties": {
    "addr:full":"1714 Newbridge Rd North Bellmore NY 11710",
    "addr:housenumber":"1714",
    "addr:postcode":"11710",
    "addr:street":"Newbridge Rd",
    "iso:country":"US",
    "sg:address":"1714 Newbridge Rd",
    "sg:city":"North Bellmore",
    "sg:classifiers":[
        {
            "category":"Food & Beverages",
            "subcategory":"Groceries & Convenience Stores",
            "type":"Retail Goods"
        }
    ],
    "sg:phone":"+1 516 785 8347",
    "sg:postcode":"11710",
    "sg:province":"NY",
    "sg:website":"www.7-eleven.com",
    "wof:name":"7-Eleven",
    "wof:placetype":"venue"
},
  "geometry": {"coordinates":[-73.539948,40.680776],"type":"Point"}
}