{
  "type": "Feature",
  "properties": {
    "addr:full":"183 Bannon Pl Massapequa Park NY 11762",
    "addr:housenumber":"183",
    "addr:postcode":"11762",
    "addr:street":"Bannon Pl",
    "iso:country":"US",
    "sg:address":"183 Bannon Pl",
    "sg:city":"Massapequa Park",
    "sg:classifiers":[
        {
            "category":"Real Estate",
            "subcategory":"Architect",
            "type":"Services"
        }
    ],
    "sg:phone":"+1 516 795 1212",
    "sg:postcode":"11762",
    "sg:province":"NY",
    "wof:name":"Philippe Karver",
    "wof:placetype":"venue"
},
  "geometry": {"coordinates":[-73.455443,40.672265],"type":"Point"}
}