{
  "type": "Feature",
  "properties": {
    "addr:full":"359 Bay Shore Rd Deer Park NY 11729",
    "addr:housenumber":"359",
    "addr:postcode":"11729",
    "addr:street":"Bay Shore Rd",
    "iso:country":"US",
    "sg:address":"359 Bay Shore Rd",
    "sg:city":"Deer Park",
    "sg:classifiers":[
        {
            "category":"Professional",
            "subcategory":"Management & Consulting",
            "type":"Services"
        }
    ],
    "sg:phone":"+1 631 242 0027",
    "sg:postcode":"11729",
    "sg:province":"NY",
    "sg:tags":[
        "marketing",
        "program"
    ],
    "wof:name":"Express Marketing",
    "wof:placetype":"venue"
},
  "geometry": {"coordinates":[-73.322574,40.749215],"type":"Point"}
}