{
  "type": "Feature",
  "properties": {
    "addr:full":"307 Northwood Dr Syracuse NY 13211",
    "addr:housenumber":"307",
    "addr:postcode":"13211",
    "addr:street":"Northwood Dr",
    "iso:country":"US",
    "sg:address":"307 Northwood Dr",
    "sg:city":"Syracuse",
    "sg:classifiers":[
        {
            "category":"Shopping",
            "subcategory":"Gifts & Souvenirs",
            "type":"Retail Goods"
        }
    ],
    "sg:phone":"+1   ",
    "sg:postcode":"13211",
    "sg:province":"NY",
    "wof:name":"Sunnydale Gifts",
    "wof:placetype":"venue"
},
  "geometry": {"coordinates":[-76.128055,43.101116],"type":"Point"}
}