{
  "type": "Feature",
  "properties": {
    "addr:full":"109 Park Ln Ithaca NY 14850",
    "addr:housenumber":"109",
    "addr:postcode":"14850",
    "addr:street":"Park Ln",
    "iso:country":"US",
    "sg:address":"109 Park Ln",
    "sg:city":"Ithaca",
    "sg:classifiers":[
        {
            "category":"Shopping",
            "subcategory":"Music",
            "type":"Retail Goods"
        }
    ],
    "sg:phone":"+1   ",
    "sg:postcode":"14850",
    "sg:province":"NY",
    "sg:tags":[
        "compact",
        "record",
        "disc",
        "tape",
        "prerecorded",
        "audio"
    ],
    "wof:name":"Sounds Fine",
    "wof:placetype":"venue"
},
  "geometry": {"coordinates":[-76.457283,42.4241],"type":"Point"}
}