{
  "type": "Feature",
  "properties": {
    "addr:full":"499 S Main St Freeport NY 11520",
    "addr:housenumber":"499",
    "addr:postcode":"11520",
    "addr:street":"S Main St",
    "iso:country":"US",
    "sg:address":"499 S Main St",
    "sg:city":"Freeport",
    "sg:classifiers":[
        {
            "category":"Wholesale",
            "subcategory":"Machinery & Supplies",
            "type":"Manufacturing & Wholesale Goods"
        },
        {
            "category":"Home & Garden",
            "subcategory":"Garden Supply",
            "type":"Retail Goods"
        }
    ],
    "sg:phone":"+1 516 546 1177",
    "sg:postcode":"11520",
    "sg:province":"NY",
    "sg:tags":[
        "engine",
        "equipment",
        "industrial"
    ],
    "wof:name":"Lawrence B Fels & Son",
    "wof:placetype":"venue"
},
  "geometry": {"coordinates":[-73.57464,40.643284],"type":"Point"}
}