{
  "type": "Feature",
  "properties": {
    "addr:full":"1879 E Main St Mohegan Lake NY 10547",
    "addr:housenumber":"1879",
    "addr:postcode":"10547",
    "addr:street":"E Main St",
    "iso:country":"US",
    "sg:address":"1879 E Main St",
    "sg:city":"Mohegan Lake",
    "sg:classifiers":[
        {
            "category":"Shopping",
            "subcategory":"Beauty & Cosmetics",
            "type":"Retail Goods"
        }
    ],
    "sg:phone":"+1   ",
    "sg:postcode":"10547",
    "sg:province":"NY",
    "sg:tags":[
        "supply"
    ],
    "wof:name":"Four Seasons Beauty Supply",
    "wof:placetype":"venue"
},
  "geometry": {"coordinates":[-73.845962,41.327604],"type":"Point"}
}