{
  "type": "Feature",
  "properties": {
    "addr:full":"240 Motor Pkwy Hauppauge NY 11788",
    "addr:housenumber":"240",
    "addr:postcode":"11788",
    "addr:street":"Motor Pkwy",
    "iso:country":"US",
    "sg:address":"240 Motor Pkwy",
    "sg:city":"Hauppauge",
    "sg:classifiers":[
        {
            "category":"Health Services",
            "subcategory":"Medical Lab",
            "type":"Services"
        }
    ],
    "sg:phone":"+1 631 435 1515",
    "sg:postcode":"11788",
    "sg:province":"NY",
    "sg:tags":[
        "laboratory"
    ],
    "wof:name":"Sunrise Medical Laboratories",
    "wof:placetype":"venue"
},
  "geometry": {"coordinates":[-73.244854,40.807288],"type":"Point"}
}