{
  "type": "Feature",
  "properties": {
    "addr:full":"708 Fulton St Brooklyn NY 11217",
    "addr:housenumber":"708",
    "addr:postcode":"11217",
    "addr:street":"Fulton St",
    "iso:country":"US",
    "sg:address":"708 Fulton St",
    "sg:city":"Brooklyn",
    "sg:classifiers":[
        {
            "category":"Food & Beverages",
            "subcategory":"Bakery",
            "type":"Retail Goods"
        },
        {
            "category":"Bakery",
            "type":"Food & Drink"
        }
    ],
    "sg:menulink":"http://www.allmenus.com/ny/brooklyn/284186-cake-man-raven/menu/",
    "sg:phone":"+1 718 797 2598",
    "sg:postcode":"11217",
    "sg:province":"NY",
    "sg:tags":[
        "american",
        "bakery",
        "pastry"
    ],
    "wof:name":"Cake Man Raven",
    "wof:placetype":"venue"
},
  "geometry": {"coordinates":[-73.973636,40.685981],"type":"Point"}
}