{
  "type": "Feature",
  "properties": {
    "addr:full":"174 Avenue B New York NY 10009",
    "addr:housenumber":"174",
    "addr:postcode":"10009",
    "addr:street":"Avenue B",
    "iso:country":"US",
    "sg:address":"174 Avenue B",
    "sg:city":"New York",
    "sg:classifiers":[
        {
            "category":"Restaurant",
            "type":"Food & Drink"
        }
    ],
    "sg:menulink":"http://www.allmenus.com/ny/new-york/259068-eleven-b/menu/",
    "sg:phone":"+1 212 388 9811",
    "sg:postcode":"10009",
    "sg:province":"NY",
    "sg:tags":[
        "american",
        "italian",
        "pizza"
    ],
    "wof:name":"Eleven B",
    "wof:placetype":"venue"
},
  "geometry": {"coordinates":[-73.979767,40.727457],"type":"Point"}
}