{
  "type": "Feature",
  "properties": {
    "iso:country":"US",
    "sg:address":"64 Trinity Pl",
    "sg:city":"Selkirk",
    "sg:classifiers":[
        {
            "category":"Building & Trades",
            "subcategory":"Construction",
            "type":"Services"
        }
    ],
    "sg:phone":"+1 518 767 3375",
    "sg:postcode":"12158",
    "sg:province":"NY",
    "sg:tags":[
        "hanging",
        "contractor"
    ],
    "wof:name":"Rob Prior",
    "wof:placetype":"venue"
},
  "geometry": {"coordinates":[-73.789536,42.541206],"type":"Point"}
}