{
  "type": "Feature",
  "properties": {
    "iso:country":"US",
    "sg:address":"254 Nassau Blvd S",
    "sg:city":"Garden City",
    "sg:classifiers":[
        {
            "category":"Professional",
            "subcategory":"Lawyer & Legal Services",
            "type":"Services"
        }
    ],
    "sg:phone":"+1 516 538 1111",
    "sg:postcode":"11530",
    "sg:province":"NY",
    "wof:name":"Mahon Mahon Mahon",
    "wof:placetype":"venue"
},
  "geometry": {"coordinates":[-73.660797,40.7136],"type":"Point"}
}