{
  "type": "Feature",
  "properties": {
    "addr:full":"3712 23rd Street Long Island City NY 11101",
    "addr:housenumber":"3712",
    "addr:postcode":"11101",
    "addr:street":"23Rd Street",
    "iso:country":"US",
    "sg:address":"3712 23rd Street",
    "sg:city":"Long Island City",
    "sg:classifiers":[
        {
            "category":"Banks & Credit Unions",
            "subcategory":"Financial Services",
            "type":"Services"
        }
    ],
    "sg:phone":"+1 718 267 1165",
    "sg:postcode":"11101",
    "sg:province":"NY",
    "sg:tags":[
        "broker",
        "mortgage"
    ],
    "wof:name":"Zalahova Jana",
    "wof:placetype":"venue"
},
  "geometry": {"coordinates":[-73.93671000000001,40.757469],"type":"Point"}
}