{
  "type": "Feature",
  "properties": {
    "addr:full":"96 N Jay St Schenectady NY 12305",
    "addr:housenumber":"96",
    "addr:postcode":"12305",
    "addr:street":"N Jay St",
    "iso:country":"US",
    "sg:address":"96 N Jay St",
    "sg:city":"Schenectady",
    "sg:classifiers":[
        {
            "category":"Manufacturing",
            "subcategory":"Printing",
            "type":"Manufacturing & Wholesale Goods"
        }
    ],
    "sg:phone":"+1 518 388 9182",
    "sg:postcode":"12305",
    "sg:province":"NY",
    "sg:tags":[
        "printer"
    ],
    "sg:website":"www.mediawelldone.org",
    "wof:name":"Well-Done Media",
    "wof:placetype":"venue"
},
  "geometry": {"coordinates":[-73.937625,42.818013],"type":"Point"}
}