{
  "type": "Feature",
  "properties": {
    "iso:country":"US",
    "sg:address":"218 W 40 St",
    "sg:city":"New York",
    "sg:classifiers":[
        {
            "category":"Banks & Credit Unions",
            "subcategory":"Bank",
            "type":"Services"
        }
    ],
    "sg:phone":"+1 212 730 7500",
    "sg:postcode":"10018",
    "sg:province":"NY",
    "wof:name":"Dressmakers Credit Union",
    "wof:placetype":"venue"
},
  "geometry": {"coordinates":[-73.990368,40.755664],"type":"Point"}
}