{
  "type": "Feature",
  "properties": {
    "iso:country":"US",
    "sg:address":"3105 Veterans Memorial Hwy",
    "sg:city":"Ronkonkoma",
    "sg:classifiers":[
        {
            "category":"Government",
            "subcategory":"Office",
            "type":"Public Place"
        }
    ],
    "sg:phone":"+1 631 854 9676",
    "sg:postcode":"11779",
    "sg:province":"NY",
    "wof:name":"Suffolk Cnty 5th District Crt",
    "wof:placetype":"venue"
},
  "geometry": {"coordinates":[-73.163803,40.792607],"type":"Point"}
}