{
  "type": "Feature",
  "properties": {
    "iso:country":"US",
    "sg:address":"45 Broadway",
    "sg:city":"Greenlawn",
    "sg:classifiers":[
        {
            "category":"Professional",
            "type":"Services"
        }
    ],
    "sg:phone":"+1 631 757 2661",
    "sg:postcode":"11740",
    "sg:province":"NY",
    "sg:tags":[
        "establishment"
    ],
    "wof:name":"Pixie Sage Ctr",
    "wof:placetype":"venue"
},
  "geometry": {"coordinates":[-73.365629,40.870883],"type":"Point"}
}