{
  "type": "Feature",
  "properties": {
    "addr:full":"58 Locust St Auburn NY 13021",
    "addr:housenumber":"58",
    "addr:postcode":"13021",
    "addr:street":"Locust St",
    "iso:country":"US",
    "sg:address":"58 Locust St",
    "sg:city":"Auburn",
    "sg:classifiers":[
        {
            "category":"Building & Trades",
            "subcategory":"Construction",
            "type":"Services"
        }
    ],
    "sg:phone":"+1 315 253 9307",
    "sg:postcode":"13021",
    "sg:province":"NY",
    "sg:tags":[
        "heavy"
    ],
    "wof:name":"Jml Construction",
    "wof:placetype":"venue"
},
  "geometry": {"coordinates":[-76.550498,42.912823],"type":"Point"}
}