{
  "type": "Feature",
  "properties": {
    "iso:country":"US",
    "sg:address":"4120 N Buffalo St",
    "sg:city":"Orchard Park",
    "sg:classifiers":[
        {
            "category":"Personal",
            "subcategory":"Beauty Salon",
            "type":"Services"
        }
    ],
    "sg:phone":"+1 716 667 7277",
    "sg:postcode":"14127",
    "sg:province":"NY",
    "wof:name":"Sass",
    "wof:placetype":"venue"
},
  "geometry": {"coordinates":[-78.744365,42.769249],"type":"Point"}
}