{
  "type": "Feature",
  "properties": {
    "addr:full":"221 Dover Pkwy Garden City NY 11530",
    "addr:housenumber":"221",
    "addr:postcode":"11530",
    "addr:street":"Dover Pkwy",
    "iso:country":"US",
    "sg:address":"221 Dover Pkwy",
    "sg:city":"Garden City",
    "sg:classifiers":[
        {
            "category":"Banks & Credit Unions",
            "subcategory":"Investment Brokerage",
            "type":"Services"
        }
    ],
    "sg:phone":"+1 516 326 6810",
    "sg:postcode":"11530",
    "sg:province":"NY",
    "sg:tags":[
        "advisory",
        "financial"
    ],
    "wof:name":"TAS Financial Svc",
    "wof:placetype":"venue"
},
  "geometry": {"coordinates":[-73.68541999999999,40.715643],"type":"Point"}
}