{
  "type": "Feature",
  "properties": {
    "addr:full":"56 W Kingsbridge Rd Bronx NY 10468",
    "addr:housenumber":"56",
    "addr:postcode":"10468",
    "addr:street":"W Kingsbridge Rd",
    "iso:country":"US",
    "sg:address":"56 W Kingsbridge Rd",
    "sg:city":"Bronx",
    "sg:classifiers":[
        {
            "category":"Professional",
            "type":"Services"
        }
    ],
    "sg:phone":"+1 718 584 2206",
    "sg:postcode":"10468",
    "sg:province":"NY",
    "sg:tags":[
        "establishment"
    ],
    "wof:name":"99 Cent Discounts Inc",
    "wof:placetype":"venue"
},
  "geometry": {"coordinates":[-73.89992599999999,40.867841],"type":"Point"}
}