{
  "type": "Feature",
  "properties": {
    "iso:country":"US",
    "sg:address":"846 Tinton Ave",
    "sg:city":"Bronx",
    "sg:classifiers":[
        {
            "category":"Professional",
            "type":"Services"
        },
        {
            "category":"Social Services",
            "type":"Services"
        }
    ],
    "sg:phone":"+1 718 542 1038",
    "sg:postcode":"10456",
    "sg:province":"NY",
    "sg:tags":[
        "for",
        "agency",
        "human",
        "retarded",
        "establishment",
        "mentally"
    ],
    "wof:name":"Creative Lifestyles Inc",
    "wof:placetype":"venue"
},
  "geometry": {"coordinates":[-73.90375899999999,40.820943],"type":"Point"}
}