{
  "type": "Feature",
  "properties": {
    "addr:full":"105 Route 112 Port Jefferson Sta NY 11776",
    "addr:housenumber":"105",
    "addr:postcode":"11776",
    "addr:street":"Route 112",
    "iso:country":"US",
    "sg:address":"105 Route 112",
    "sg:city":"Port Jefferson Sta",
    "sg:classifiers":[
        {
            "category":"Professional",
            "subcategory":"Lawyer & Legal Services",
            "type":"Services"
        }
    ],
    "sg:phone":"+1 631 689 0123",
    "sg:postcode":"11776",
    "sg:province":"NY",
    "wof:name":"Yanaros William D Attys",
    "wof:placetype":"venue"
},
  "geometry": {"coordinates":[-73.05349699999999,40.9333],"type":"Point"}
}