{
  "type": "Feature",
  "properties": {
    "addr:full":"45 Ramsey Rd. Ste 8 Shirley NY 11967",
    "addr:housenumber":"45",
    "addr:postcode":"11967",
    "addr:street":"Ramsey Rd. Ste 8",
    "iso:country":"US",
    "sg:address":"45 Ramsey Rd. Ste 8",
    "sg:city":"Shirley",
    "sg:classifiers":[
        {
            "category":"Shopping",
            "subcategory":"Music",
            "type":"Retail Goods"
        }
    ],
    "sg:phone":"+1 631 585 3294",
    "sg:postcode":"11967",
    "sg:province":"NY",
    "sg:tags":[
        "dvd's"
    ],
    "wof:name":"Record Stop",
    "wof:placetype":"venue"
},
  "geometry": {"coordinates":[-72.88057999999999,40.844476],"type":"Point"}
}