{
  "type": "Feature",
  "properties": {
    "addr:full":"36 7th Avenue New York NY 10011",
    "addr:housenumber":"36",
    "addr:postcode":"10011",
    "addr:street":"7Th Avenue",
    "iso:country":"US",
    "sg:address":"36 7th Avenue",
    "sg:city":"New York",
    "sg:classifiers":[
        {
            "category":"Health Services",
            "subcategory":"Doctor",
            "type":"Services"
        }
    ],
    "sg:phone":"+1 212 929 3747",
    "sg:postcode":"10011",
    "sg:province":"NY",
    "wof:name":"Mc Veigh Anne Marie MD",
    "wof:placetype":"venue"
},
  "geometry": {"coordinates":[-74.000288,40.737747],"type":"Point"}
}