{
  "type": "Feature",
  "properties": {
    "iso:country":"US",
    "sg:address":"761 Central Ave",
    "sg:city":"Dunkirk",
    "sg:classifiers":[
        {
            "category":"Professional",
            "type":"Services"
        }
    ],
    "sg:phone":"+1 716 366 2127",
    "sg:postcode":"14048",
    "sg:province":"NY",
    "sg:tags":[
        "establishment"
    ],
    "wof:name":"Environments For Living S Tier",
    "wof:placetype":"venue"
},
  "geometry": {"coordinates":[-79.333074,42.475144],"type":"Point"}
}