{
  "type": "Feature",
  "properties": {
    "iso:country":"US",
    "sg:address":"3018 State Hwy 430",
    "sg:city":"Bemus Point",
    "sg:classifiers":[
        {
            "category":"Food & Beverages",
            "subcategory":"Groceries & Convenience Stores",
            "type":"Retail Goods"
        }
    ],
    "sg:phone":"+1 716 488 2580",
    "sg:postcode":"14712",
    "sg:province":"NY",
    "wof:name":"Lake County Dairy",
    "wof:placetype":"venue"
},
  "geometry": {"coordinates":[-79.388729,42.168721],"type":"Point"}
}