{
  "type": "Feature",
  "properties": {
    "addr:full":"1442 1st Ave New York NY 10021",
    "addr:housenumber":"1442",
    "addr:postcode":"10021",
    "addr:street":"1St Ave",
    "iso:country":"US",
    "sg:address":"1442 1st Ave",
    "sg:city":"New York",
    "sg:classifiers":[
        {
            "category":"Bars & Pubs",
            "type":"Food & Drink"
        }
    ],
    "sg:menulink":"http://www.allmenus.com/ny/new-york/249459-the-wicked-wolf-bar--restaurant/menu/",
    "sg:phone":"+1 212 744 7446",
    "sg:postcode":"10021",
    "sg:province":"NY",
    "sg:tags":[
        "american"
    ],
    "wof:name":"The Wicked Wolf Bar & Restaurant",
    "wof:placetype":"venue"
},
  "geometry": {"coordinates":[-73.95433300000001,40.769544],"type":"Point"}
}