{
  "type": "Feature",
  "properties": {
    "iso:country":"US",
    "sg:address":"868 Lafayette Ave",
    "sg:city":"Brooklyn",
    "sg:classifiers":[
        {
            "category":"Organizations",
            "subcategory":"Professional Association",
            "type":"Services"
        }
    ],
    "sg:phone":"+1 718 230 3166",
    "sg:postcode":"11221",
    "sg:province":"NY",
    "sg:tags":[
        "sale"
    ],
    "wof:name":"C & D Fuel Oil Corp",
    "wof:placetype":"venue"
},
  "geometry": {"coordinates":[-73.93793700000001,40.691402],"type":"Point"}
}