{
  "type": "Feature",
  "properties": {
    "iso:country":"US",
    "sg:address":"2268 Grand Concourse",
    "sg:city":"Bronx",
    "sg:classifiers":[
        {
            "category":"Fast Food",
            "type":"Food & Drink"
        }
    ],
    "sg:phone":"+1 718 562 4818",
    "sg:postcode":"10457",
    "sg:province":"NY",
    "sg:tags":[
        "chicken",
        "wing"
    ],
    "wof:name":"Kainth Crown Fried Chicken",
    "wof:placetype":"venue"
},
  "geometry": {"coordinates":[-73.90010100000001,40.856602],"type":"Point"}
}