{
  "type": "Feature",
  "properties": {
    "addr:full":"101 E 10th St Manhattan NY 10003",
    "addr:housenumber":"101",
    "addr:postcode":"10003",
    "addr:street":"E 10Th St",
    "iso:country":"US",
    "sg:address":"101 E 10th St",
    "sg:city":"Manhattan",
    "sg:classifiers":[
        {
            "category":"Education",
            "subcategory":"University",
            "type":"Public Place"
        }
    ],
    "sg:phone":"+1 212 592 2140",
    "sg:postcode":"10003",
    "sg:province":"NY",
    "sg:tags":[
        "housing"
    ],
    "sg:website":"www.sva.edu/ResHalls/index.php?R...",
    "wof:name":"10th Street Residence Hall - School of Visual Arts",
    "wof:placetype":"venue"
},
  "geometry": {"coordinates":[-73.98898800000001,40.730708],"type":"Point"}
}