{
  "type": "Feature",
  "properties": {
    "iso:country":"US",
    "sg:address":"1 Patchogue St",
    "sg:city":"East Patchogue",
    "sg:classifiers":[
        {
            "category":"Retail",
            "subcategory":"Laundry & Dry Cleaning",
            "type":"Services"
        }
    ],
    "sg:phone":"+1 631 289 0400",
    "sg:postcode":"11772",
    "sg:province":"NY",
    "sg:tags":[
        "cleaners"
    ],
    "wof:name":"Swan Cleaners",
    "wof:placetype":"venue"
},
  "geometry": {"coordinates":[-73.013561,40.751846],"type":"Point"}
}