{
  "type": "Feature",
  "properties": {
    "iso:country":"US",
    "sg:address":"12 W 57th St Fl 6",
    "sg:city":"New York",
    "sg:classifiers":[
        {
            "category":"Shopping",
            "subcategory":"Jewelry",
            "type":"Retail Goods"
        }
    ],
    "sg:phone":"+1 646 344 7935",
    "sg:postcode":"10019",
    "sg:province":"NY",
    "wof:name":"Richemont Van Cleef & Arpels",
    "wof:placetype":"venue"
},
  "geometry": {"coordinates":[-73.974356,40.762984],"type":"Point"}
}