{
  "type": "Feature",
  "properties": {
    "addr:full":"561 Beach 69th St Arverne NY 11692",
    "addr:housenumber":"561",
    "addr:postcode":"11692",
    "addr:street":"Beach 69Th St",
    "iso:country":"US",
    "sg:address":"561 Beach 69th St",
    "sg:city":"Arverne",
    "sg:classifiers":[
        {
            "category":"Home & Garden",
            "subcategory":"Carpets & Floor Coverings",
            "type":"Retail Goods"
        }
    ],
    "sg:phone":"+1 718 291 9614",
    "sg:postcode":"11692",
    "sg:province":"NY",
    "sg:tags":[
        "material",
        "rug",
        "carpeting"
    ],
    "wof:name":"Lobban Carpet Inc",
    "wof:placetype":"venue"
},
  "geometry": {"coordinates":[-73.798698,40.5966],"type":"Point"}
}