{
  "type": "Feature",
  "properties": {
    "iso:country":"US",
    "sg:address":"207 Ransom Rd",
    "sg:city":"Lancaster",
    "sg:classifiers":[
        {
            "category":"Building & Trades",
            "subcategory":"Construction",
            "type":"Services"
        }
    ],
    "sg:phone":"+1 716 685 4668",
    "sg:postcode":"14086",
    "sg:province":"NY",
    "sg:tags":[
        "house"
    ],
    "wof:name":"Wienckowski Builders",
    "wof:placetype":"venue"
},
  "geometry": {"coordinates":[-78.591402,42.870018],"type":"Point"}
}