{
  "type": "Feature",
  "properties": {
    "addr:full":"946 Fulton St Brooklyn NY 11238",
    "addr:housenumber":"946",
    "addr:postcode":"11238",
    "addr:street":"Fulton St",
    "iso:country":"US",
    "sg:address":"946 Fulton St",
    "sg:city":"Brooklyn",
    "sg:classifiers":[
        {
            "category":"Professional",
            "subcategory":"Management & Consulting",
            "type":"Services"
        }
    ],
    "sg:phone":"+1 718 230 0135",
    "sg:postcode":"11238",
    "sg:province":"NY",
    "sg:tags":[
        "consultant"
    ],
    "wof:name":"527 Maple Court Corp",
    "wof:placetype":"venue"
},
  "geometry": {"coordinates":[-73.963061,40.682633],"type":"Point"}
}