{
  "type": "Feature",
  "properties": {
    "iso:country":"US",
    "sg:address":"18 Upper East Brook Rd",
    "sg:city":"Walton",
    "sg:classifiers":[
        {
            "category":"Transit Center",
            "subcategory":"Freight",
            "type":"Transportation"
        },
        {
            "category":"Freight",
            "type":"Transportation"
        }
    ],
    "sg:phone":"+1 607 865 5236",
    "sg:postcode":"13856",
    "sg:province":"NY",
    "sg:tags":[
        "local",
        "trucking-motor",
        "trucking"
    ],
    "wof:name":"Cpr Trucking",
    "wof:placetype":"venue"
},
  "geometry": {"coordinates":[-75.11916100000001,42.177387],"type":"Point"}
}