{
  "type": "Feature",
  "properties": {
    "addr:full":"24 Ave A Port Washington NY 11050",
    "addr:postcode":"11050",
    "addr:street":"24 Ave A",
    "iso:country":"US",
    "sg:address":"24 Ave A",
    "sg:city":"Port Washington",
    "sg:classifiers":[
        {
            "category":"Restaurant",
            "type":"Food & Drink"
        }
    ],
    "sg:phone":"+1 516 767 9059",
    "sg:postcode":"11050",
    "sg:province":"NY",
    "sg:tags":[
        "delicatessen"
    ],
    "wof:name":"Country Deli",
    "wof:placetype":"venue"
},
  "geometry": {"coordinates":[-73.693637,40.843912],"type":"Point"}
}