{
  "type": "Feature",
  "properties": {
    "addr:full":"14 Ungava Dr New City NY 10956",
    "addr:housenumber":"14",
    "addr:postcode":"10956",
    "addr:street":"Ungava Dr",
    "iso:country":"US",
    "sg:address":"14 Ungava Dr",
    "sg:city":"New City",
    "sg:classifiers":[
        {
            "category":"Health Services",
            "subcategory":"Medical Lab",
            "type":"Services"
        }
    ],
    "sg:phone":"+1 845 634 4577",
    "sg:postcode":"10956",
    "sg:province":"NY",
    "sg:tags":[
        "laboratory"
    ],
    "wof:name":"Jeff Sanders Dental Lab",
    "wof:placetype":"venue"
},
  "geometry": {"coordinates":[-73.99742000000001,41.16214],"type":"Point"}
}