{
  "type": "Feature",
  "properties": {
    "addr:full":"720 State Hwy 9a New York NY 10019",
    "addr:housenumber":"720",
    "addr:postcode":"10019",
    "addr:street":"State Hwy 9A",
    "iso:country":"US",
    "sg:address":"720 State Hwy 9a",
    "sg:city":"New York",
    "sg:classifiers":[
        {
            "category":"Professional",
            "subcategory":"Management & Consulting",
            "type":"Services"
        }
    ],
    "sg:phone":"+1   ",
    "sg:postcode":"10019",
    "sg:province":"NY",
    "sg:tags":[
        "company",
        "investment"
    ],
    "wof:name":"Quadrant Management Inc",
    "wof:placetype":"venue"
},
  "geometry": {"coordinates":[-73.994658,40.769119],"type":"Point"}
}