{
  "type": "Feature",
  "properties": {
    "addr:full":"4048 Sweden Walker Rd Brockport NY 14420",
    "addr:housenumber":"4048",
    "addr:postcode":"14420",
    "addr:street":"Sweden Walker Rd",
    "iso:country":"US",
    "sg:address":"4048 Sweden Walker Rd",
    "sg:city":"Brockport",
    "sg:classifiers":[
        {
            "category":"Shopping",
            "subcategory":"Antiques",
            "type":"Retail Goods"
        }
    ],
    "sg:phone":"+1 585 637 2702",
    "sg:postcode":"14420",
    "sg:province":"NY",
    "wof:name":"Frederick Porter Antiques",
    "wof:placetype":"venue"
},
  "geometry": {"coordinates":[-77.894707,43.212021],"type":"Point"}
}