{
  "type": "Feature",
  "properties": {
    "addr:full":"332 E 86th St Apt 2 New York NY 10028",
    "addr:housenumber":"332;2",
    "addr:postcode":"10028",
    "addr:street":"E 86Th St Apt",
    "iso:country":"US",
    "sg:address":"332 E 86th St Apt 2",
    "sg:city":"New York",
    "sg:classifiers":[
        {
            "category":"Real Estate",
            "subcategory":"Real Estate Services",
            "type":"Services"
        }
    ],
    "sg:phone":"+1 212 999 4880",
    "sg:postcode":"10028",
    "sg:province":"NY",
    "sg:tags":[
        "management",
        "property"
    ],
    "wof:name":"Prince Real Estate Association",
    "wof:placetype":"venue"
},
  "geometry": {"coordinates":[-73.95101200000001,40.777425],"type":"Point"}
}