{
  "type": "Feature",
  "properties": {
    "iso:country":"US",
    "sg:address":"96 Grove St",
    "sg:city":"New York",
    "sg:classifiers":[
        {
            "category":"Restaurant",
            "type":"Food & Drink"
        }
    ],
    "sg:phone":"+1 212 274 1027",
    "sg:postcode":"10014",
    "sg:province":"NY",
    "wof:name":"Bistrot Margot",
    "wof:placetype":"venue"
},
  "geometry": {"coordinates":[-74.002027,40.733443],"type":"Point"}
}