{
  "type": "Feature",
  "properties": {
    "addr:full":"1492 3rd Ave New York NY 10028",
    "addr:housenumber":"1492",
    "addr:postcode":"10028",
    "addr:street":"3Rd Ave",
    "iso:country":"US",
    "sg:address":"1492 3rd Ave",
    "sg:city":"New York",
    "sg:classifiers":[
        {
            "category":"Shopping",
            "subcategory":"Clothing, Apparel, & Fashions",
            "type":"Retail Goods"
        }
    ],
    "sg:phone":"+1 212 472 7281",
    "sg:postcode":"10028",
    "sg:province":"NY",
    "sg:tags":[
        "accessory"
    ],
    "wof:name":"Ann Taylor Loft",
    "wof:placetype":"venue"
},
  "geometry": {"coordinates":[-73.954697,40.777802],"type":"Point"}
}