{
  "type": "Feature",
  "properties": {
    "addr:full":"545 8th Ave New York NY 10018",
    "addr:housenumber":"545",
    "addr:postcode":"10018",
    "addr:street":"8Th Ave",
    "iso:country":"US",
    "sg:address":"545 8th Ave",
    "sg:city":"New York",
    "sg:classifiers":[
        {
            "category":"Cinema",
            "subcategory":"Movie Rental",
            "type":"Entertainment"
        }
    ],
    "sg:phone":"+1 212 502 1162",
    "sg:postcode":"10018",
    "sg:province":"NY",
    "sg:tags":[
        "game",
        "video"
    ],
    "wof:name":"World Domination",
    "wof:placetype":"venue"
},
  "geometry": {"coordinates":[-73.991997,40.7542],"type":"Point"}
}