{
  "type": "Feature",
  "properties": {
    "iso:country":"US",
    "sg:address":"528 Bryant Ave",
    "sg:city":"Bronx",
    "sg:classifiers":[
        {
            "category":"Building & Trades",
            "subcategory":"Construction",
            "type":"Services"
        }
    ],
    "sg:phone":"+1 718 861 3570",
    "sg:postcode":"10474",
    "sg:province":"NY",
    "sg:tags":[
        "industrial",
        "concrete",
        "breaking",
        "contractor",
        "equipment",
        "cutting",
        "sawing"
    ],
    "wof:name":"Hi-Tech Breaking Inc",
    "wof:placetype":"venue"
},
  "geometry": {"coordinates":[-73.88478000000001,40.811831],"type":"Point"}
}