{
  "type": "Feature",
  "properties": {
    "iso:country":"US",
    "sg:address":"640 W 43rd St",
    "sg:city":"New York",
    "sg:classifiers":[
        {
            "category":"Retail",
            "subcategory":"Auto Repair",
            "type":"Services"
        }
    ],
    "sg:phone":"+1 646 237 1506",
    "sg:postcode":"10036",
    "sg:province":"NY",
    "sg:tags":[
        "repairing",
        "automobile"
    ],
    "wof:name":"Ali Auto Repair",
    "wof:placetype":"venue"
},
  "geometry": {"coordinates":[-73.998901,40.761799],"type":"Point"}
}