{
  "type": "Feature",
  "properties": {
    "iso:country":"US",
    "sg:address":"261 Akin Rd",
    "sg:city":"Johnsonville",
    "sg:classifiers":[
        {
            "category":"Farming",
            "subcategory":"Dairy Farm",
            "type":"Manufacturing & Wholesale Goods"
        }
    ],
    "sg:phone":"+1 518 753 4128",
    "sg:postcode":"12094",
    "sg:province":"NY",
    "wof:name":"Aiken Brothers",
    "wof:placetype":"venue"
},
  "geometry": {"coordinates":[-73.519886,42.943309],"type":"Point"}
}