{
  "type": "Feature",
  "properties": {
    "addr:full":"440 W 4th St Elmira NY 14901",
    "addr:housenumber":"440",
    "addr:postcode":"14901",
    "addr:street":"W 4Th St",
    "iso:country":"US",
    "sg:address":"440 W 4th St",
    "sg:city":"Elmira",
    "sg:classifiers":[
        {
            "category":"Food & Beverages",
            "subcategory":"Specialty",
            "type":"Retail Goods"
        }
    ],
    "sg:phone":"+1 607 737 0374",
    "sg:postcode":"14901",
    "sg:province":"NY",
    "sg:tags":[
        "vitamin"
    ],
    "wof:name":"Herbalife",
    "wof:placetype":"venue"
},
  "geometry": {"coordinates":[-76.819132,42.09257],"type":"Point"}
}