{
  "type": "Feature",
  "properties": {
    "addr:full":"2815 Middletown Rd Bronx NY 10461",
    "addr:housenumber":"2815",
    "addr:postcode":"10461",
    "addr:street":"Middletown Rd",
    "iso:country":"US",
    "sg:address":"2815 Middletown Rd",
    "sg:city":"Bronx",
    "sg:classifiers":[
        {
            "category":"Shopping",
            "subcategory":"Florist",
            "type":"Retail Goods"
        }
    ],
    "sg:phone":"+1 718 829 2696",
    "sg:postcode":"10461",
    "sg:province":"NY",
    "wof:name":"Country Club Florists",
    "wof:placetype":"venue"
},
  "geometry": {"coordinates":[-73.836348,40.843484],"type":"Point"}
}