{
  "type": "Feature",
  "properties": {
    "iso:country":"US",
    "sg:address":"226 Main St",
    "sg:city":"Otego",
    "sg:classifiers":[
        {
            "category":"Farming",
            "subcategory":"Farm",
            "type":"Manufacturing & Wholesale Goods"
        }
    ],
    "sg:phone":"+1 607 988 9048",
    "sg:postcode":"13825",
    "sg:province":"NY",
    "wof:name":"Elmer Johnson Barn",
    "wof:placetype":"venue"
},
  "geometry": {"coordinates":[-75.190404,42.38701],"type":"Point"}
}