{
  "type": "Feature",
  "properties": {
    "addr:full":"778 8 Ave New York NY 10036",
    "addr:housenumber":"778",
    "addr:postcode":"10036",
    "addr:street":"8 Ave",
    "iso:country":"US",
    "sg:address":"778 8 Ave",
    "sg:city":"New York",
    "sg:classifiers":[
        {
            "category":"Freight",
            "type":"Transportation"
        }
    ],
    "sg:phone":"+1 212 376 4095",
    "sg:postcode":"10036",
    "sg:province":"NY",
    "sg:tags":[
        "delivery"
    ],
    "wof:name":"Deluxe Delivery",
    "wof:placetype":"venue"
},
  "geometry": {"coordinates":[-73.989791,40.757234],"type":"Point"}
}