{
  "type": "Feature",
  "properties": {
    "iso:country":"US",
    "sg:address":"498 Route 111",
    "sg:city":"Smithtown",
    "sg:classifiers":[
        {
            "category":"Health Services",
            "subcategory":"Doctor",
            "type":"Services"
        }
    ],
    "sg:phone":"+1 631 751 2222",
    "sg:postcode":"11787",
    "sg:province":"NY",
    "sg:tags":[
        "obstetrician",
        "gynecologist"
    ],
    "wof:name":"Alternatives For Women",
    "wof:placetype":"venue"
},
  "geometry": {"coordinates":[-73.19786000000001,40.830823],"type":"Point"}
}