{
  "type": "Feature",
  "properties": {
    "iso:country":"US",
    "sg:address":"42 Creamery Rd",
    "sg:city":"Oswego",
    "sg:classifiers":[
        {
            "category":"Government",
            "subcategory":"Office",
            "type":"Public Place"
        }
    ],
    "sg:phone":"+1 315 343 3894",
    "sg:postcode":"13126",
    "sg:province":"NY",
    "sg:tags":[
        "city",
        "taxation"
    ],
    "wof:name":"Scriba Assessors",
    "wof:placetype":"venue"
},
  "geometry": {"coordinates":[-76.431152,43.473875],"type":"Point"}
}