{
  "type": "Feature",
  "properties": {
    "iso:country":"US",
    "sg:address":"2060 Lexington Ave",
    "sg:city":"New York",
    "sg:classifiers":[
        {
            "category":"Shopping",
            "subcategory":"Pawn Shop",
            "type":"Retail Goods"
        }
    ],
    "sg:phone":"+1 212 410 6084",
    "sg:postcode":"10035",
    "sg:province":"NY",
    "wof:name":"Mega Pawn Corp",
    "wof:placetype":"venue"
},
  "geometry": {"coordinates":[-73.93740099999999,40.804199],"type":"Point"}
}