{
  "type": "Feature",
  "properties": {
    "addr:full":"845 3rd Ave Frnt 1 New York NY 10022",
    "addr:housenumber":"845;1",
    "addr:postcode":"10022",
    "addr:street":"3Rd Ave Frnt",
    "iso:country":"US",
    "sg:address":"845 3rd Ave Frnt 1",
    "sg:city":"New York",
    "sg:classifiers":[
        {
            "category":"Banks & Credit Unions",
            "subcategory":"Bank",
            "type":"Services"
        }
    ],
    "sg:phone":"+1 212 935 7564",
    "sg:postcode":"10022",
    "sg:province":"NY",
    "sg:website":"www.northforkbank.com",
    "wof:name":"CapitalOne",
    "wof:placetype":"venue"
},
  "geometry": {"coordinates":[-73.969684,40.756998],"type":"Point"}
}