{
  "type": "Feature",
  "properties": {
    "iso:country":"US",
    "sg:address":"752 Metropolitan Ave",
    "sg:city":"Brooklyn",
    "sg:classifiers":[
        {
            "category":"Retail",
            "subcategory":"Auto Repair",
            "type":"Services"
        }
    ],
    "sg:phone":"+1 718 366 3460",
    "sg:postcode":"11211",
    "sg:province":"NY",
    "wof:name":"Metro Wheel Alignment",
    "wof:placetype":"venue"
},
  "geometry": {"coordinates":[-73.94380200000001,40.7145],"type":"Point"}
}