{
  "type": "Feature",
  "properties": {
    "iso:country":"US",
    "sg:address":"1504 Old Country Rd",
    "sg:city":"Westbury",
    "sg:classifiers":[
        {
            "category":"Shopping",
            "type":"Retail Goods"
        }
    ],
    "sg:phone":"+1 516 222 7878",
    "sg:postcode":"11590",
    "sg:province":"NY",
    "sg:tags":[
        "candle"
    ],
    "sg:website":"www.yankeecandle.com",
    "wof:name":"Yankee Candle Co",
    "wof:placetype":"venue"
},
  "geometry": {"coordinates":[-73.593333,40.747084],"type":"Point"}
}