{
  "type": "Feature",
  "properties": {
    "iso:country":"US",
    "sg:address":"23072 State Hwy 12",
    "sg:city":"Watertown",
    "sg:classifiers":[
        {
            "category":"Wholesale",
            "subcategory":"Electrical",
            "type":"Manufacturing & Wholesale Goods"
        }
    ],
    "sg:phone":"+1 315 779 8563",
    "sg:postcode":"13601",
    "sg:province":"NY",
    "sg:tags":[
        "equipment"
    ],
    "wof:name":"Rexel Inc",
    "wof:placetype":"venue"
},
  "geometry": {"coordinates":[-75.87482300000001,43.957424],"type":"Point"}
}