{
  "type": "Feature",
  "properties": {
    "iso:country":"US",
    "sg:address":"835 Tracy St",
    "sg:city":"Olean",
    "sg:classifiers":[
        {
            "category":"Recreation",
            "subcategory":"Arcade",
            "type":"Entertainment"
        }
    ],
    "sg:phone":"+1 716 373 6797",
    "sg:postcode":"14760",
    "sg:province":"NY",
    "sg:tags":[
        "amusement",
        "devices"
    ],
    "sg:website":"www.rentfun1.com",
    "wof:name":"American Amusement Rentals",
    "wof:placetype":"venue"
},
  "geometry": {"coordinates":[-78.41148200000001,42.079206],"type":"Point"}
}