{
  "type": "Feature",
  "properties": {
    "iso:country":"US",
    "sg:address":"3 Lincoln Center Plz",
    "sg:city":"New York",
    "sg:classifiers":[
        {
            "category":"Parking",
            "type":"Transportation"
        }
    ],
    "sg:phone":"+1   ",
    "sg:postcode":"10023",
    "sg:province":"NY",
    "sg:tags":[
        "automobile"
    ],
    "wof:name":"Performance Parking Corp",
    "wof:placetype":"venue"
},
  "geometry": {"coordinates":[-73.98112999999999,40.771023],"type":"Point"}
}