{
  "type": "Feature",
  "properties": {
    "addr:full":"7 Panorama Dr Patterson NY 12563",
    "addr:housenumber":"7",
    "addr:postcode":"12563",
    "addr:street":"Panorama Dr",
    "iso:country":"US",
    "sg:address":"7 Panorama Dr",
    "sg:city":"Patterson",
    "sg:classifiers":[
        {
            "category":"Home & Garden",
            "subcategory":"Building Materials",
            "type":"Retail Goods"
        }
    ],
    "sg:phone":"+1 845 878 3435",
    "sg:postcode":"12563",
    "sg:province":"NY",
    "sg:tags":[
        "windows",
        "door",
        "storm"
    ],
    "wof:name":"Panorama",
    "wof:placetype":"venue"
},
  "geometry": {"coordinates":[-73.583983,41.51302],"type":"Point"}
}