{
  "type": "Feature",
  "properties": {
    "addr:full":"385 Main St Catskill NY 12414",
    "addr:housenumber":"385",
    "addr:postcode":"12414",
    "addr:street":"Main St",
    "iso:country":"US",
    "sg:address":"385 Main St",
    "sg:city":"Catskill",
    "sg:classifiers":[
        {
            "category":"Professional",
            "subcategory":"Management & Consulting",
            "type":"Services"
        }
    ],
    "sg:phone":"+1 518 943 0708",
    "sg:postcode":"12414",
    "sg:province":"NY",
    "sg:tags":[
        "consultant",
        "educational"
    ],
    "sg:website":"www.mgtadvgroup.com",
    "wof:name":"Management Advisory GROUP-Ny",
    "wof:placetype":"venue"
},
  "geometry": {"coordinates":[-73.866237,42.221192],"type":"Point"}
}