{
  "type": "Feature",
  "properties": {
    "addr:full":"6453 Hatter Rd Newfane NY 14108",
    "addr:postcode":"6453;14108",
    "addr:street":"Hatter Rd",
    "iso:country":"US",
    "sg:address":"6453 Hatter Rd",
    "sg:city":"Newfane",
    "sg:classifiers":[
        {
            "category":"Manufacturing",
            "subcategory":"Pet Food",
            "type":"Manufacturing & Wholesale Goods"
        },
        {
            "category":"Farming",
            "subcategory":"Farm",
            "type":"Manufacturing & Wholesale Goods"
        }
    ],
    "sg:phone":"+1 716 778 9924",
    "sg:postcode":"14108",
    "sg:province":"NY",
    "sg:tags":[
        "hay"
    ],
    "wof:name":"Clarence Say",
    "wof:placetype":"venue"
},
  "geometry": {"coordinates":[-78.67409499999999,43.257777],"type":"Point"}
}