{
  "type": "Feature",
  "properties": {
    "iso:country":"US",
    "sg:address":"48 Seley Dr",
    "sg:city":"North Babylon",
    "sg:classifiers":[
        {
            "category":"Building & Trades",
            "subcategory":"Construction",
            "type":"Services"
        }
    ],
    "sg:phone":"+1 631 242 3851",
    "sg:postcode":"11703",
    "sg:province":"NY",
    "sg:tags":[
        "contractor"
    ],
    "wof:name":"Richard Pfister General Contg",
    "wof:placetype":"venue"
},
  "geometry": {"coordinates":[-73.310787,40.735841],"type":"Point"}
}