{
  "type": "Feature",
  "properties": {
    "iso:country":"US",
    "sg:address":"769 65th Street",
    "sg:city":"Brooklyn",
    "sg:classifiers":[
        {
            "category":"Retail",
            "subcategory":"Auto Repair",
            "type":"Services"
        }
    ],
    "sg:phone":"+1 718 833 6220",
    "sg:postcode":"11220",
    "sg:province":"NY",
    "wof:name":"Sun Lung Auto Repair",
    "wof:placetype":"venue"
},
  "geometry": {"coordinates":[-74.01275699999999,40.632907],"type":"Point"}
}