{
  "type": "Feature",
  "properties": {
    "iso:country":"US",
    "sg:address":"725 10th Ave",
    "sg:city":"New York",
    "sg:classifiers":[
        {
            "category":"Communications",
            "subcategory":"Newspaper",
            "type":"Services"
        }
    ],
    "sg:phone":"+1 212 315 1997",
    "sg:postcode":"10019",
    "sg:province":"NY",
    "sg:tags":[
        "magazine"
    ],
    "wof:name":"Schanzer Newstand",
    "wof:placetype":"venue"
},
  "geometry": {"coordinates":[-73.992104,40.7645],"type":"Point"}
}