{
  "type": "Feature",
  "properties": {
    "addr:full":"3817 Broadway New York NY 10032",
    "addr:housenumber":"3817",
    "addr:postcode":"10032",
    "addr:street":"Broadway",
    "iso:country":"US",
    "sg:address":"3817 Broadway",
    "sg:city":"New York",
    "sg:classifiers":[
        {
            "category":"Shopping",
            "subcategory":"Pharmacy",
            "type":"Retail Goods"
        }
    ],
    "sg:phone":"+1   ",
    "sg:postcode":"10032",
    "sg:province":"NY",
    "sg:tags":[
        "drug",
        "store"
    ],
    "wof:name":"Vims Drugs",
    "wof:placetype":"venue"
},
  "geometry": {"coordinates":[-73.94434099999999,40.834786],"type":"Point"}
}