{
  "type": "Feature",
  "properties": {
    "iso:country":"US",
    "sg:address":"3945 State Hwy 31",
    "sg:city":"Liverpool",
    "sg:classifiers":[
        {
            "category":"Banks & Credit Unions",
            "subcategory":"Bank",
            "type":"Services"
        }
    ],
    "sg:phone":"+1 315 652 1640",
    "sg:postcode":"13090",
    "sg:province":"NY",
    "sg:website":"www.mandtbank.com",
    "wof:name":"M & T Bank",
    "wof:placetype":"venue"
},
  "geometry": {"coordinates":[-76.242535,43.185294],"type":"Point"}
}