{
  "type": "Feature",
  "properties": {
    "addr:full":"2727 Palisade Ave Bronx NY 10463",
    "addr:housenumber":"2727",
    "addr:postcode":"10463",
    "addr:street":"Palisade Ave",
    "iso:country":"US",
    "sg:address":"2727 Palisade Ave",
    "sg:city":"Bronx",
    "sg:classifiers":[
        {
            "category":"Social Services",
            "type":"Services"
        }
    ],
    "sg:phone":"+1 718 548 7330",
    "sg:postcode":"10463",
    "sg:province":"NY",
    "sg:tags":[
        "counselor",
        "marriage",
        "family"
    ],
    "wof:name":"ABC Meditation",
    "wof:placetype":"venue"
},
  "geometry": {"coordinates":[-73.920513,40.88245],"type":"Point"}
}