{
  "type": "Feature",
  "properties": {
    "iso:country":"US",
    "sg:address":"3505 Old Yorktown Rd",
    "sg:city":"Yorktown Heights",
    "sg:classifiers":[
        {
            "category":"Health Services",
            "subcategory":"Doctor",
            "type":"Services"
        }
    ],
    "sg:phone":"+1 914 962 3413",
    "sg:postcode":"10598",
    "sg:province":"NY",
    "sg:tags":[
        "medical"
    ],
    "wof:name":"Martin Zisblatt PHD MD",
    "wof:placetype":"venue"
},
  "geometry": {"coordinates":[-73.817727,41.323976],"type":"Point"}
}