{
  "type": "Feature",
  "properties": {
    "addr:full":"6502 20th Ave Brooklyn NY 11204",
    "addr:housenumber":"6502",
    "addr:postcode":"11204",
    "addr:street":"20Th Ave",
    "iso:country":"US",
    "sg:address":"6502 20th Ave",
    "sg:city":"Brooklyn",
    "sg:classifiers":[
        {
            "category":"Wholesale",
            "subcategory":"Machinery & Supplies",
            "type":"Manufacturing & Wholesale Goods"
        }
    ],
    "sg:phone":"+1 718 234 7985",
    "sg:postcode":"11204",
    "sg:province":"NY",
    "sg:tags":[
        "equipment",
        "industrial"
    ],
    "wof:name":"Alex and Nicky Inc",
    "wof:placetype":"venue"
},
  "geometry": {"coordinates":[-73.986536,40.615977],"type":"Point"}
}