{
  "type": "Feature",
  "properties": {
    "addr:full":"87 Church St Little Falls NY 13365",
    "addr:housenumber":"87",
    "addr:postcode":"13365",
    "addr:street":"Church St",
    "iso:country":"US",
    "sg:address":"87 Church St",
    "sg:city":"Little Falls",
    "sg:classifiers":[
        {
            "category":"Home & Garden",
            "subcategory":"Furniture",
            "type":"Retail Goods"
        }
    ],
    "sg:phone":"+1 315 823 2951",
    "sg:postcode":"13365",
    "sg:province":"NY",
    "wof:name":"Valley Home Furnishings",
    "wof:placetype":"venue"
},
  "geometry": {"coordinates":[-74.864163,43.044251],"type":"Point"}
}