{
  "type": "Feature",
  "properties": {
    "addr:full":"4488 Broadway New York NY 10040",
    "addr:housenumber":"4488",
    "addr:postcode":"10040",
    "addr:street":"Broadway",
    "iso:country":"US",
    "sg:address":"4488 Broadway",
    "sg:city":"New York",
    "sg:classifiers":[
        {
            "category":"Professional",
            "type":"Services"
        }
    ],
    "sg:phone":"+1 212 569 2357",
    "sg:postcode":"10040",
    "sg:province":"NY",
    "sg:tags":[
        "establishment"
    ],
    "wof:name":"Junquito",
    "wof:placetype":"venue"
},
  "geometry": {"coordinates":[-73.932362,40.856829],"type":"Point"}
}