{
  "type": "Feature",
  "properties": {
    "iso:country":"US",
    "sg:address":"1772 E Jericho Tpke Ste 2",
    "sg:city":"Huntington",
    "sg:classifiers":[
        {
            "category":"Professional",
            "subcategory":"Lawyer & Legal Services",
            "type":"Services"
        }
    ],
    "sg:phone":"+1 631 499 3333",
    "sg:postcode":"11743",
    "sg:province":"NY",
    "sg:website":"www.accidentattorneylongisland.com",
    "wof:name":"The Law Office of Laurence A Silverman",
    "wof:placetype":"venue"
},
  "geometry": {"coordinates":[-73.33774099999999,40.833702],"type":"Point"}
}