{
  "type": "Feature",
  "properties": {
    "iso:country":"US",
    "sg:address":"1852 8th Ave",
    "sg:city":"Watervliet",
    "sg:classifiers":[
        {
            "category":"Bars & Pubs",
            "type":"Food & Drink"
        }
    ],
    "sg:phone":"+1   ",
    "sg:postcode":"12189",
    "sg:province":"NY",
    "sg:tags":[
        "drinking"
    ],
    "wof:name":"Larrys Place",
    "wof:placetype":"venue"
},
  "geometry": {"coordinates":[-73.707367,42.731719],"type":"Point"}
}