{
  "type": "Feature",
  "properties": {
    "iso:country":"US",
    "sg:address":"954 State Hwy 29A",
    "sg:city":"Gloversville",
    "sg:classifiers":[
        {
            "category":"Home & Garden",
            "subcategory":"Building Materials",
            "type":"Retail Goods"
        }
    ],
    "sg:phone":"+1   ",
    "sg:postcode":"12078",
    "sg:province":"NY",
    "wof:name":"G&G Contracting",
    "wof:placetype":"venue"
},
  "geometry": {"coordinates":[-74.319472,43.049729],"type":"Point"}
}