{
  "type": "Feature",
  "properties": {
    "addr:full":"27 Race Ln East Hampton NY 11937",
    "addr:housenumber":"27",
    "addr:postcode":"11937",
    "addr:street":"Race Ln East",
    "iso:country":"US",
    "sg:address":"27 Race Ln",
    "sg:city":"East Hampton",
    "sg:classifiers":[
        {
            "category":"Home & Garden",
            "subcategory":"Furniture",
            "type":"Retail Goods"
        }
    ],
    "sg:phone":"+1 631 324 7111",
    "sg:postcode":"11937",
    "sg:province":"NY",
    "sg:tags":[
        "builder",
        "custom"
    ],
    "wof:name":"Pritam & Eames",
    "wof:placetype":"venue"
},
  "geometry": {"coordinates":[-72.195595,40.962984],"type":"Point"}
}