{
  "type": "Feature",
  "properties": {
    "iso:country":"US",
    "sg:address":"9 Park St",
    "sg:city":"Glens Falls",
    "sg:classifiers":[
        {
            "category":"Retail",
            "subcategory":"Repair Shop",
            "type":"Services"
        }
    ],
    "sg:phone":"+1 518 793 2848",
    "sg:postcode":"12801",
    "sg:province":"NY",
    "sg:tags":[
        "instrument",
        "musical"
    ],
    "wof:name":"Triad's Music Ctr",
    "wof:placetype":"venue"
},
  "geometry": {"coordinates":[-73.644188,43.308668],"type":"Point"}
}