{
  "type": "Feature",
  "properties": {
    "addr:full":"347 5th Ave New York NY 10016",
    "addr:housenumber":"347",
    "addr:postcode":"10016",
    "addr:street":"5Th Ave",
    "iso:country":"US",
    "sg:address":"347 5th Ave",
    "sg:city":"New York",
    "sg:classifiers":[
        {
            "category":"Restaurant",
            "type":"Food & Drink"
        }
    ],
    "sg:phone":"+1 212 725 9058",
    "sg:postcode":"10016",
    "sg:province":"NY",
    "wof:name":"China Us",
    "wof:placetype":"venue"
},
  "geometry": {"coordinates":[-73.98474,40.747958],"type":"Point"}
}