{
  "type": "Feature",
  "properties": {
    "addr:full":"59 Cecil St Buffalo NY 14216",
    "addr:housenumber":"59",
    "addr:postcode":"14216",
    "addr:street":"Cecil St",
    "iso:country":"US",
    "sg:address":"59 Cecil St",
    "sg:city":"Buffalo",
    "sg:classifiers":[
        {
            "category":"Wholesale",
            "subcategory":"Fruits & Vegetables",
            "type":"Manufacturing & Wholesale Goods"
        }
    ],
    "sg:phone":"+1 716 895 3744",
    "sg:postcode":"14216",
    "sg:province":"NY",
    "sg:tags":[
        "citrus",
        "fresh"
    ],
    "wof:name":"Sunkist Growers Inc",
    "wof:placetype":"venue"
},
  "geometry": {"coordinates":[-78.87376999999999,42.95354],"type":"Point"}
}