{
  "type": "Feature",
  "properties": {
    "addr:full":"26 Round Table Rd Saratoga Springs NY 12866",
    "addr:housenumber":"26",
    "addr:postcode":"12866",
    "addr:street":"Round Table Rd",
    "iso:country":"US",
    "sg:address":"26 Round Table Rd",
    "sg:city":"Saratoga Springs",
    "sg:classifiers":[
        {
            "category":"Building & Trades",
            "subcategory":"Construction",
            "type":"Services"
        }
    ],
    "sg:phone":"+1 518 583 3813",
    "sg:postcode":"12866",
    "sg:province":"NY",
    "sg:tags":[
        "house",
        "contractor",
        "roofing"
    ],
    "wof:name":"Northeast Construction & Repr",
    "wof:placetype":"venue"
},
  "geometry": {"coordinates":[-73.83352600000001,43.071674],"type":"Point"}
}