{
  "type": "Feature",
  "properties": {
    "addr:full":"15 Newfield St Buffalo NY 14207",
    "addr:housenumber":"15",
    "addr:postcode":"14207",
    "addr:street":"Newfield St",
    "iso:country":"US",
    "sg:address":"15 Newfield St",
    "sg:city":"Buffalo",
    "sg:classifiers":[
        {
            "category":"Autos & Motor Vehicles",
            "subcategory":"Automobile Sales",
            "type":"Retail Goods"
        }
    ],
    "sg:phone":"+1   ",
    "sg:postcode":"14207",
    "sg:province":"NY",
    "sg:tags":[
        "used"
    ],
    "wof:name":"Up State Salvage",
    "wof:placetype":"venue"
},
  "geometry": {"coordinates":[-78.895145,42.95841],"type":"Point"}
}