{
  "type": "Feature",
  "properties": {
    "addr:full":"305 Montauk Hwy Lindenhurst NY 11757",
    "addr:housenumber":"305",
    "addr:postcode":"11757",
    "addr:street":"Montauk Hwy",
    "iso:country":"US",
    "sg:address":"305 Montauk Hwy",
    "sg:city":"Lindenhurst",
    "sg:classifiers":[
        {
            "category":"Manufacturing",
            "subcategory":"Apparel",
            "type":"Manufacturing & Wholesale Goods"
        }
    ],
    "sg:phone":"+1 631 957 7100",
    "sg:postcode":"11757",
    "sg:province":"NY",
    "sg:tags":[
        "canvas",
        "product",
        "related"
    ],
    "wof:name":"Baldwin Auto Upholstery",
    "wof:placetype":"venue"
},
  "geometry": {"coordinates":[-73.370683,40.675418],"type":"Point"}
}