{
  "type": "Feature",
  "properties": {
    "addr:full":"2138 Williamsbridge Rd Bronx NY 10461",
    "addr:housenumber":"2138",
    "addr:postcode":"10461",
    "addr:street":"Williamsbridge Rd",
    "iso:country":"US",
    "sg:address":"2138 Williamsbridge Rd",
    "sg:city":"Bronx",
    "sg:classifiers":[
        {
            "category":"Professional",
            "subcategory":"Engineering",
            "type":"Services"
        },
        {
            "category":"Retail",
            "subcategory":"Repair Shop",
            "type":"Services"
        }
    ],
    "sg:phone":"+1 718 863 4207",
    "sg:postcode":"10461",
    "sg:province":"NY",
    "sg:tags":[
        "plumbing",
        "drain",
        "cleaning",
        "sewer"
    ],
    "wof:name":"Pyramid Fire Protection Inc",
    "wof:placetype":"venue"
},
  "geometry": {"coordinates":[-73.855807,40.856383],"type":"Point"}
}