{
  "type": "Feature",
  "properties": {
    "addr:full":"39 Albion St Liberty NY 12754",
    "addr:housenumber":"39",
    "addr:postcode":"12754",
    "addr:street":"Albion St",
    "iso:country":"US",
    "sg:address":"39 Albion St",
    "sg:city":"Liberty",
    "sg:classifiers":[
        {
            "category":"Building & Trades",
            "subcategory":"Plumbing",
            "type":"Services"
        }
    ],
    "sg:phone":"+1 845 295 0004",
    "sg:postcode":"12754",
    "sg:province":"NY",
    "sg:tags":[
        "plumbing",
        "contractor"
    ],
    "wof:name":"Integrity Plumbing & Htg Inc",
    "wof:placetype":"venue"
},
  "geometry": {"coordinates":[-74.74942799999999,41.791225],"type":"Point"}
}