{
  "type": "Feature",
  "properties": {
    "addr:full":"90 John St New York NY 10038",
    "addr:housenumber":"90",
    "addr:postcode":"10038",
    "addr:street":"John St",
    "iso:country":"US",
    "sg:address":"90 John St",
    "sg:city":"New York",
    "sg:classifiers":[
        {
            "category":"Professional",
            "subcategory":"Employment Agencies",
            "type":"Services"
        }
    ],
    "sg:phone":"+1 212 693 3353",
    "sg:postcode":"10038",
    "sg:province":"NY",
    "sg:tags":[
        "consulting",
        "staffing",
        "technology",
        "it",
        "dev"
    ],
    "wof:name":"Neotecra Inc",
    "wof:placetype":"venue"
},
  "geometry": {"coordinates":[-74.006987,40.708506],"type":"Point"}
}