{
  "type": "Feature",
  "properties": {
    "iso:country":"US",
    "sg:address":"5100 W Taft Rd",
    "sg:city":"Liverpool",
    "sg:classifiers":[
        {
            "category":"Health Services",
            "subcategory":"Doctor",
            "type":"Services"
        }
    ],
    "sg:phone":"+1 315 452 2240",
    "sg:postcode":"13088",
    "sg:province":"NY",
    "sg:tags":[
        "physician",
        "surgeon",
        "medical"
    ],
    "wof:name":"Nabil Aziz MD",
    "wof:placetype":"venue"
},
  "geometry": {"coordinates":[-76.160965,43.121743],"type":"Point"}
}