{
  "type": "Feature",
  "properties": {
    "addr:full":"2375 Marion Ave Bronx NY 10458",
    "addr:housenumber":"2375",
    "addr:postcode":"10458",
    "addr:street":"Marion Ave",
    "iso:country":"US",
    "sg:address":"2375 Marion Ave",
    "sg:city":"Bronx",
    "sg:classifiers":[
        {
            "category":"Building & Trades",
            "subcategory":"Construction",
            "type":"Services"
        }
    ],
    "sg:phone":"+1 718 733 6928",
    "sg:postcode":"10458",
    "sg:province":"NY",
    "sg:tags":[
        "carpentry",
        "contractor"
    ],
    "wof:name":"Carpentry By Carle",
    "wof:placetype":"venue"
},
  "geometry": {"coordinates":[-73.89484299999999,40.859327],"type":"Point"}
}