{
  "type": "Feature",
  "properties": {
    "addr:full":"53 Mott St New York NY 10013",
    "addr:housenumber":"53",
    "addr:postcode":"10013",
    "addr:street":"Mott St",
    "iso:country":"US",
    "sg:address":"53 Mott St",
    "sg:city":"New York",
    "sg:classifiers":[
        {
            "category":"Food & Beverages",
            "subcategory":"Liquor & Beverages",
            "type":"Retail Goods"
        }
    ],
    "sg:phone":"+1 212 962 1982",
    "sg:postcode":"10013",
    "sg:province":"NY",
    "sg:tags":[
        "beer",
        "spirit",
        "wine"
    ],
    "wof:name":"Marks Wine & Spirits Ltd",
    "wof:placetype":"venue"
},
  "geometry": {"coordinates":[-73.998666,40.715544],"type":"Point"}
}