{
  "type": "Feature",
  "properties": {
    "addr:full":"741 Forest Ave Staten Island NY 10310",
    "addr:housenumber":"741",
    "addr:postcode":"10310",
    "addr:street":"Forest Ave",
    "iso:country":"US",
    "sg:address":"741 Forest Ave",
    "sg:city":"Staten Island",
    "sg:classifiers":[
        {
            "category":"Retail",
            "subcategory":"Auto Repair",
            "type":"Services"
        }
    ],
    "sg:phone":"+1 718 727 5610",
    "sg:postcode":"10310",
    "sg:province":"NY",
    "wof:name":"MOBIL SERVICE STATION",
    "wof:placetype":"venue"
},
  "geometry": {"coordinates":[-74.113716,40.629374],"type":"Point"}
}