{
  "type": "Feature",
  "properties": {
    "addr:full":"903 Forest Ave Staten Island NY 10310",
    "addr:housenumber":"903",
    "addr:postcode":"10310",
    "addr:street":"Forest Ave",
    "iso:country":"US",
    "sg:address":"903 Forest Ave",
    "sg:city":"Staten Island",
    "sg:classifiers":[
        {
            "category":"Health Services",
            "subcategory":"Doctor",
            "type":"Services"
        }
    ],
    "sg:phone":"+1 718 273 3347",
    "sg:postcode":"10310",
    "sg:province":"NY",
    "wof:name":"Oghia Hady",
    "wof:placetype":"venue"
},
  "geometry": {"coordinates":[-74.119153,40.628797],"type":"Point"}
}