{
  "type": "Feature",
  "properties": {
    "addr:full":"2172 2 Ave New York NY 10029",
    "addr:housenumber":"2172",
    "addr:postcode":"10029",
    "addr:street":"2 Ave",
    "iso:country":"US",
    "sg:address":"2172 2 Ave",
    "sg:city":"New York",
    "sg:classifiers":[
        {
            "category":"Building & Trades",
            "subcategory":"Plumbing",
            "type":"Services"
        }
    ],
    "sg:phone":"+1 212 722 7859",
    "sg:postcode":"10029",
    "sg:province":"NY",
    "sg:tags":[
        "plumbing",
        "contractor"
    ],
    "wof:name":"Johnnie On The Spot",
    "wof:placetype":"venue"
},
  "geometry": {"coordinates":[-73.94658699999999,40.784941],"type":"Point"}
}