{
  "type": "Feature",
  "properties": {
    "addr:full":"1151 Front St Uniondale NY 11553",
    "addr:housenumber":"1151",
    "addr:postcode":"11553",
    "addr:street":"Front St",
    "iso:country":"US",
    "sg:address":"1151 Front St",
    "sg:city":"Uniondale",
    "sg:classifiers":[
        {
            "category":"Health Services",
            "subcategory":"Doctor",
            "type":"Services"
        }
    ],
    "sg:phone":"+1 516 481 2080",
    "sg:postcode":"11553",
    "sg:province":"NY",
    "wof:name":"Japal Bianca H MD",
    "wof:placetype":"venue"
},
  "geometry": {"coordinates":[-73.5877,40.710098],"type":"Point"}
}