{
  "type": "Feature",
  "properties": {
    "iso:country":"US",
    "sg:address":"1 Ontario Ave",
    "sg:city":"New Hartford",
    "sg:classifiers":[
        {
            "category":"Retail",
            "subcategory":"Auto Rental",
            "type":"Services"
        }
    ],
    "sg:phone":"+1 315 738 1823",
    "sg:postcode":"13413",
    "sg:province":"NY",
    "sg:tags":[
        "renting",
        "automobile",
        "passenger",
        "car"
    ],
    "sg:website":"www.pricelessrentacar.com",
    "wof:name":"Priceless Rent A Car",
    "wof:placetype":"venue"
},
  "geometry": {"coordinates":[-75.29755900000001,43.08049],"type":"Point"}
}