{
  "type": "Feature",
  "properties": {
    "iso:country":"US",
    "sg:address":"1203 Sutter Avenue",
    "sg:city":"Brooklyn",
    "sg:classifiers":[
        {
            "category":"Health Services",
            "subcategory":"Dentist",
            "type":"Services"
        }
    ],
    "sg:phone":"+1 718 277 0903",
    "sg:postcode":"11208",
    "sg:province":"NY",
    "wof:name":"Pati John F DDS",
    "wof:placetype":"venue"
},
  "geometry": {"coordinates":[-73.873389,40.672685],"type":"Point"}
}