{
  "type": "Feature",
  "properties": {
    "iso:country":"US",
    "sg:address":"451 W Church St",
    "sg:city":"Elmira",
    "sg:classifiers":[
        {
            "category":"Health Services",
            "subcategory":"Dentist",
            "type":"Services"
        }
    ],
    "sg:phone":"+1 607 733 3760",
    "sg:postcode":"14901",
    "sg:province":"NY",
    "wof:name":"Oral Maxillofacial Surgery Of Southern Tier Pc",
    "wof:placetype":"venue"
},
  "geometry": {"coordinates":[-76.815887,42.087589],"type":"Point"}
}