{
  "type": "Feature",
  "properties": {
    "addr:full":"115 W 11 St New York NY 10011",
    "addr:housenumber":"115",
    "addr:postcode":"10011",
    "addr:street":"W 11 St",
    "iso:country":"US",
    "sg:address":"115 W 11 St",
    "sg:city":"New York",
    "sg:classifiers":[
        {
            "category":"Professional",
            "subcategory":"Research",
            "type":"Services"
        }
    ],
    "sg:phone":"+1 212 929 2901",
    "sg:postcode":"10011",
    "sg:province":"NY",
    "sg:tags":[
        "market"
    ],
    "wof:name":"Intermarket Research Inc",
    "wof:placetype":"venue"
},
  "geometry": {"coordinates":[-74.00096600000001,40.736579],"type":"Point"}
}