{
  "type": "Feature",
  "properties": {
    "addr:full":"2268 Amsterdam Ave New York NY 10032",
    "addr:housenumber":"2268",
    "addr:postcode":"10032",
    "addr:street":"Amsterdam Ave",
    "iso:country":"US",
    "sg:address":"2268 Amsterdam Ave",
    "sg:city":"New York",
    "sg:classifiers":[
        {
            "category":"Professional",
            "type":"Services"
        }
    ],
    "sg:phone":"+1 212 781 4955",
    "sg:postcode":"10032",
    "sg:province":"NY",
    "sg:tags":[
        "service/non-profit",
        "community"
    ],
    "wof:name":"Community Association",
    "wof:placetype":"venue"
},
  "geometry": {"coordinates":[-73.934799,40.842602],"type":"Point"}
}