{
  "type": "Feature",
  "properties": {
    "addr:full":"625 Pennsylvania Ave Elmira NY 14904",
    "addr:housenumber":"625",
    "addr:postcode":"14904",
    "addr:street":"Pennsylvania Ave",
    "iso:country":"US",
    "sg:address":"625 Pennsylvania Ave",
    "sg:city":"Elmira",
    "sg:classifiers":[
        {
            "category":"Autos & Motor Vehicles",
            "subcategory":"Fuel & Gas Station",
            "type":"Retail Goods"
        }
    ],
    "sg:phone":"+1 607 732 1275",
    "sg:postcode":"14904",
    "sg:province":"NY",
    "sg:tags":[
        "oil"
    ],
    "wof:name":"Sunoco",
    "wof:placetype":"venue"
},
  "geometry": {"coordinates":[-76.80472399999999,42.073609],"type":"Point"}
}