{
  "type": "Feature",
  "properties": {
    "addr:full":"8 Bethpage Rd Copiague NY 11726",
    "addr:housenumber":"8",
    "addr:postcode":"11726",
    "addr:street":"Bethpage Rd",
    "iso:country":"US",
    "sg:address":"8 Bethpage Rd",
    "sg:city":"Copiague",
    "sg:classifiers":[
        {
            "category":"Utilities",
            "subcategory":"Refuse",
            "type":"Services"
        }
    ],
    "sg:phone":"+1   ",
    "sg:postcode":"11726",
    "sg:province":"NY",
    "sg:tags":[
        "recycling"
    ],
    "wof:name":"Tri State Group Inc",
    "wof:placetype":"venue"
},
  "geometry": {"coordinates":[-73.39957699999999,40.692639],"type":"Point"}
}