{
  "type": "Feature",
  "properties": {
    "addr:full":"20 W 20th St Ste 600 New York NY 10011",
    "addr:housenumber":"20;600",
    "addr:postcode":"10011",
    "addr:street":"W 20Th St Ste",
    "iso:country":"US",
    "sg:address":"20 W 20th St Ste 600",
    "sg:city":"New York",
    "sg:classifiers":[
        {
            "category":"Communications",
            "subcategory":"Newspaper",
            "type":"Services"
        }
    ],
    "sg:phone":"+1 212 366 6505",
    "sg:postcode":"10011",
    "sg:province":"NY",
    "sg:tags":[
        "magazine"
    ],
    "sg:website":"www.beyondracemagazine.com",
    "wof:name":"Beyond Race LLC",
    "wof:placetype":"venue"
},
  "geometry": {"coordinates":[-73.991613,40.739816],"type":"Point"}
}