{
  "type": "Feature",
  "properties": {
    "addr:full":"711 5th Ave New York NY 10022",
    "addr:housenumber":"711",
    "addr:postcode":"10022",
    "addr:street":"5Th Ave",
    "iso:country":"US",
    "sg:address":"711 5th Ave",
    "sg:city":"New York",
    "sg:classifiers":[
        {
            "category":"Banks & Credit Unions",
            "subcategory":"Financial Services",
            "type":"Services"
        }
    ],
    "sg:phone":"+1 212 813 2720",
    "sg:postcode":"10022",
    "sg:province":"NY",
    "sg:tags":[
        "investing",
        "management",
        "investment"
    ],
    "wof:name":"Zinc Capital Management",
    "wof:placetype":"venue"
},
  "geometry": {"coordinates":[-73.974602,40.762001],"type":"Point"}
}