{
  "type": "Feature",
  "properties": {
    "iso:country":"US",
    "sg:address":"118 Roxboro Cir",
    "sg:city":"Syracuse",
    "sg:classifiers":[
        {
            "category":"Freight",
            "type":"Transportation"
        }
    ],
    "sg:phone":"+1   ",
    "sg:postcode":"13211",
    "sg:province":"NY",
    "sg:tags":[
        "local",
        "without",
        "storage",
        "trucking"
    ],
    "wof:name":"Watrous Express",
    "wof:placetype":"venue"
},
  "geometry": {"coordinates":[-76.15046599999999,43.10363],"type":"Point"}
}