{
  "type": "Feature",
  "properties": {
    "iso:country":"US",
    "sg:address":"1263 59th St",
    "sg:city":"Brooklyn",
    "sg:classifiers":[
        {
            "category":"Food & Beverages",
            "subcategory":"Groceries & Convenience Stores",
            "type":"Retail Goods"
        }
    ],
    "sg:phone":"+1 718 437 0004",
    "sg:postcode":"11219",
    "sg:province":"NY",
    "wof:name":"Kosher Corner Inc",
    "wof:placetype":"venue"
},
  "geometry": {"coordinates":[-73.998001,40.629601],"type":"Point"}
}