{
  "type": "Feature",
  "properties": {
    "iso:country":"US",
    "sg:address":"135 Ward St",
    "sg:city":"Montgomery",
    "sg:classifiers":[
        {
            "category":"Restaurant",
            "type":"Food & Drink"
        }
    ],
    "sg:phone":"+1 845 457 1404",
    "sg:postcode":"12549",
    "sg:province":"NY",
    "wof:name":"Empire House Restaurant",
    "wof:placetype":"venue"
},
  "geometry": {"coordinates":[-74.235252,41.526772],"type":"Point"}
}