{
  "type": "Feature",
  "properties": {
    "iso:country":"US",
    "sg:address":"15 Kisco Ave",
    "sg:city":"Mt Kisco",
    "sg:classifiers":[
        {
            "category":"Health Services",
            "subcategory":"Health Practitioner",
            "type":"Services"
        }
    ],
    "sg:phone":"+1 914 666 3386",
    "sg:postcode":"10549",
    "sg:province":"NY",
    "sg:tags":[
        "psychologist"
    ],
    "wof:name":"Michael G Rothenberg",
    "wof:placetype":"venue"
},
  "geometry": {"coordinates":[-73.729395,41.209652],"type":"Point"}
}