{
  "type": "Feature",
  "properties": {
    "iso:country":"US",
    "sg:address":"70 4th Ave",
    "sg:city":"East Rockaway",
    "sg:classifiers":[
        {
            "category":"Wholesale",
            "subcategory":"Construction Materials",
            "type":"Manufacturing & Wholesale Goods"
        }
    ],
    "sg:phone":"+1 516 887 4090",
    "sg:postcode":"11518",
    "sg:province":"NY",
    "wof:name":"Annunziata Fence Co",
    "wof:placetype":"venue"
},
  "geometry": {"coordinates":[-73.661417,40.637208],"type":"Point"}
}