{
  "type": "Feature",
  "properties": {
    "addr:full":"100 Independent Way Ste E Brewster NY 10509",
    "addr:housenumber":"100",
    "addr:postcode":"10509",
    "addr:street":"Independent Way Ste E",
    "iso:country":"US",
    "sg:address":"100 Independent Way Ste E",
    "sg:city":"Brewster",
    "sg:classifiers":[
        {
            "category":"Restaurant",
            "type":"Food & Drink"
        }
    ],
    "sg:phone":"+1 845 278 9500",
    "sg:postcode":"10509",
    "sg:province":"NY",
    "sg:tags":[
        "pizza"
    ],
    "wof:name":"Gaetano Pizza",
    "wof:placetype":"venue"
},
  "geometry": {"coordinates":[-73.629497,41.420353],"type":"Point"}
}