{
  "type": "Feature",
  "properties": {
    "addr:full":"216 W 14 St New York NY 10011",
    "addr:housenumber":"216",
    "addr:postcode":"10011",
    "addr:street":"W 14 St",
    "iso:country":"US",
    "sg:address":"216 W 14 St",
    "sg:city":"New York",
    "sg:classifiers":[
        {
            "category":"Organizations",
            "subcategory":"Labor Organization",
            "type":"Services"
        }
    ],
    "sg:phone":"+1 212 924 2000",
    "sg:postcode":"10011",
    "sg:province":"NY",
    "wof:name":"Teamstrs Lcl 237 Traing/Eductn",
    "wof:placetype":"venue"
},
  "geometry": {"coordinates":[-74.002208,40.739491],"type":"Point"}
}