{
  "type": "Feature",
  "properties": {
    "addr:full":"53 N Bleeker St Mt Vernon NY 10550",
    "addr:housenumber":"53",
    "addr:postcode":"10550",
    "addr:street":"N Bleeker St",
    "iso:country":"US",
    "sg:address":"53 N Bleeker St",
    "sg:city":"Mt Vernon",
    "sg:classifiers":[
        {
            "category":"Building & Trades",
            "subcategory":"Construction",
            "type":"Services"
        }
    ],
    "sg:phone":"+1 914 699 6882",
    "sg:postcode":"10550",
    "sg:province":"NY",
    "sg:tags":[
        "general",
        "contractor"
    ],
    "wof:name":"Surface Specialists LLC",
    "wof:placetype":"venue"
},
  "geometry": {"coordinates":[-73.845399,40.91229],"type":"Point"}
}