{
  "type": "Feature",
  "properties": {
    "addr:full":"7585 Rania Rd Baldwinsville NY 13027",
    "addr:housenumber":"7585",
    "addr:postcode":"13027",
    "addr:street":"Rania Rd",
    "iso:country":"US",
    "sg:address":"7585 Rania Rd",
    "sg:city":"Baldwinsville",
    "sg:classifiers":[
        {
            "category":"Professional",
            "subcategory":"Business Services",
            "type":"Services"
        }
    ],
    "sg:phone":"+1   ",
    "sg:postcode":"13027",
    "sg:province":"NY",
    "wof:name":"Ciotti Agency Inc",
    "wof:placetype":"venue"
},
  "geometry": {"coordinates":[-76.271286,43.136121],"type":"Point"}
}