{
  "type": "Feature",
  "properties": {
    "addr:full":"1517 E 172nd St Bronx NY 10472",
    "addr:housenumber":"1517",
    "addr:postcode":"10472",
    "addr:street":"E 172Nd St",
    "iso:country":"US",
    "sg:address":"1517 E 172nd St",
    "sg:city":"Bronx",
    "sg:classifiers":[
        {
            "category":"Real Estate",
            "subcategory":"Real Estate Agent",
            "type":"Services"
        }
    ],
    "sg:phone":"+1 718 991 0215",
    "sg:postcode":"10472",
    "sg:province":"NY",
    "wof:name":"Evelyn I Rey",
    "wof:placetype":"venue"
},
  "geometry": {"coordinates":[-73.880405,40.831129],"type":"Point"}
}