{
  "type": "Feature",
  "properties": {
    "addr:full":"185 Marbledale Rd Tuckahoe NY 10707",
    "addr:housenumber":"185",
    "addr:postcode":"10707",
    "addr:street":"Marbledale Rd",
    "iso:country":"US",
    "sg:address":"185 Marbledale Rd",
    "sg:city":"Tuckahoe",
    "sg:classifiers":[
        {
            "category":"Utilities",
            "subcategory":"Fuel Oil & Lpg",
            "type":"Services"
        }
    ],
    "sg:phone":"+1   ",
    "sg:postcode":"10707",
    "sg:province":"NY",
    "wof:name":"Marciano Fuel Co Inc",
    "wof:placetype":"venue"
},
  "geometry": {"coordinates":[-73.819383,40.953939],"type":"Point"}
}