{
  "type": "Feature",
  "properties": {
    "iso:country":"US",
    "sg:address":"211 Hastings Pl",
    "sg:city":"Syracuse",
    "sg:classifiers":[
        {
            "category":"Professional",
            "subcategory":"Computer Services",
            "type":"Services"
        }
    ],
    "sg:phone":"+1 315 432 9364",
    "sg:postcode":"13206",
    "sg:province":"NY",
    "sg:tags":[
        "repair"
    ],
    "wof:name":"Envisions Electronics",
    "wof:placetype":"venue"
},
  "geometry": {"coordinates":[-76.117518,43.063665],"type":"Point"}
}