{
  "type": "Feature",
  "properties": {
    "addr:full":"228 Owego St Candor NY 13743",
    "addr:housenumber":"228",
    "addr:postcode":"13743",
    "addr:street":"Owego St",
    "iso:country":"US",
    "sg:address":"228 Owego St",
    "sg:city":"Candor",
    "sg:classifiers":[
        {
            "category":"Professional",
            "type":"Services"
        }
    ],
    "sg:phone":"+1 607 659 7209",
    "sg:postcode":"13743",
    "sg:province":"NY",
    "sg:tags":[
        "establishment"
    ],
    "wof:name":"Bernier Car & Assoc",
    "wof:placetype":"venue"
},
  "geometry": {"coordinates":[-76.33173600000001,42.223798],"type":"Point"}
}