{
  "type": "Feature",
  "properties": {
    "addr:full":"15 Parker St Fairport NY 14450",
    "addr:housenumber":"15",
    "addr:postcode":"14450",
    "addr:street":"Parker St",
    "iso:country":"US",
    "sg:address":"15 Parker St",
    "sg:city":"Fairport",
    "sg:classifiers":[
        {
            "category":"Utilities",
            "type":"Services"
        }
    ],
    "sg:phone":"+1   ",
    "sg:postcode":"14450",
    "sg:province":"NY",
    "sg:tags":[
        "other",
        "gas",
        "combined"
    ],
    "wof:name":"Department of Public Works",
    "wof:placetype":"venue"
},
  "geometry": {"coordinates":[-77.439475,43.099636],"type":"Point"}
}