{
  "type": "Feature",
  "properties": {
    "addr:full":"1214 Burnet Ave Syracuse NY 13203",
    "addr:housenumber":"1214",
    "addr:postcode":"13203",
    "addr:street":"Burnet Ave",
    "iso:country":"US",
    "sg:address":"1214 Burnet Ave",
    "sg:city":"Syracuse",
    "sg:classifiers":[
        {
            "category":"Professional",
            "subcategory":"Advertising",
            "type":"Services"
        }
    ],
    "sg:phone":"+1 315 476 3718",
    "sg:postcode":"13203",
    "sg:province":"NY",
    "sg:tags":[
        "counselor"
    ],
    "sg:website":"www.lamar.com",
    "wof:name":"Lamar Advertising Co",
    "wof:placetype":"venue"
},
  "geometry": {"coordinates":[-76.122051,43.054137],"type":"Point"}
}