{
  "type": "Feature",
  "properties": {
    "iso:country":"US",
    "sg:address":"29 W Main St",
    "sg:city":"Cuba",
    "sg:classifiers":[
        {
            "category":"Shopping",
            "subcategory":"Department Store",
            "type":"Retail Goods"
        }
    ],
    "sg:phone":"+1 585 968 3692",
    "sg:postcode":"14727",
    "sg:province":"NY",
    "sg:tags":[
        "variety"
    ],
    "sg:website":"http://www.familydollar.com",
    "wof:name":"Family Dollar Stores",
    "wof:placetype":"venue"
},
  "geometry": {"coordinates":[-78.276499,42.217],"type":"Point"}
}