{
  "type": "Feature",
  "properties": {
    "addr:full":"240 Plandome Rd Manhasset NY 11030",
    "addr:housenumber":"240",
    "addr:postcode":"11030",
    "addr:street":"Plandome Rd",
    "iso:country":"US",
    "sg:address":"240 Plandome Rd",
    "sg:city":"Manhasset",
    "sg:classifiers":[
        {
            "category":"Banks & Credit Unions",
            "subcategory":"Bank",
            "type":"Services"
        }
    ],
    "sg:phone":"+1 516 627 7840",
    "sg:postcode":"11030",
    "sg:province":"NY",
    "sg:tags":[
        "national",
        "commercial"
    ],
    "wof:name":"Fleet",
    "wof:placetype":"venue"
},
  "geometry": {"coordinates":[-73.698866,40.795494],"type":"Point"}
}