{
  "type": "Feature",
  "properties": {
    "addr:full":"645 Hudson Street New York NY 10014",
    "addr:housenumber":"645",
    "addr:postcode":"10014",
    "addr:street":"Hudson Street",
    "iso:country":"US",
    "sg:address":"645 Hudson Street",
    "sg:city":"New York",
    "sg:classifiers":[
        {
            "category":"Professional",
            "type":"Services"
        }
    ],
    "sg:phone":"+1 212 242 8231",
    "sg:postcode":"10014",
    "sg:province":"NY",
    "sg:tags":[
        "caterer"
    ],
    "wof:name":"Feast On US",
    "wof:placetype":"venue"
},
  "geometry": {"coordinates":[-74.005453,40.739128],"type":"Point"}
}