{
  "type": "Feature",
  "properties": {
    "iso:country":"US",
    "sg:address":"15333 Sanford Avenue",
    "sg:city":"Flushing",
    "sg:classifiers":[
        {
            "category":"Education",
            "subcategory":"School",
            "type":"Public Place"
        }
    ],
    "sg:phone":"+1 718 762 4141",
    "sg:postcode":"11355",
    "sg:province":"NY",
    "sg:tags":[
        "high",
        "middle",
        "elementary"
    ],
    "wof:name":"New York City Community School District 25 Region 3",
    "wof:placetype":"venue"
},
  "geometry": {"coordinates":[-73.811718,40.761377],"type":"Point"}
}