{
  "type": "Feature",
  "properties": {
    "addr:full":"206 N Grand Ave Poughkeepsie NY 12603",
    "addr:housenumber":"206",
    "addr:postcode":"12603",
    "addr:street":"N Grand Ave",
    "iso:country":"US",
    "sg:address":"206 N Grand Ave",
    "sg:city":"Poughkeepsie",
    "sg:classifiers":[
        {
            "category":"Building & Trades",
            "subcategory":"Plumbing",
            "type":"Services"
        }
    ],
    "sg:phone":"+1 845 473 0978",
    "sg:postcode":"12603",
    "sg:province":"NY",
    "sg:tags":[
        "heating",
        "contractor"
    ],
    "wof:name":"Hastings Heating Svc Inc",
    "wof:placetype":"venue"
},
  "geometry": {"coordinates":[-73.900007,41.70952],"type":"Point"}
}