{
  "type": "Feature",
  "properties": {
    "iso:country":"US",
    "sg:address":"1106 Main St",
    "sg:city":"Peekskill",
    "sg:classifiers":[
        {
            "category":"Education",
            "subcategory":"School",
            "type":"Public Place"
        }
    ],
    "sg:phone":"+1 914 737 7600",
    "sg:postcode":"10566",
    "sg:province":"NY",
    "wof:name":"Peekskill-Cortlandt Music",
    "wof:placetype":"venue"
},
  "geometry": {"coordinates":[-73.915385,41.291958],"type":"Point"}
}