{
  "type": "Feature",
  "properties": {
    "addr:full":"561 W 235th St Bronx NY 10463",
    "addr:housenumber":"561",
    "addr:postcode":"10463",
    "addr:street":"W 235Th St",
    "iso:country":"US",
    "sg:address":"561 W 235th St",
    "sg:city":"Bronx",
    "sg:classifiers":[
        {
            "category":"Shopping",
            "subcategory":"Shoes",
            "type":"Retail Goods"
        }
    ],
    "sg:phone":"+1   ",
    "sg:postcode":"10463",
    "sg:province":"NY",
    "sg:tags":[
        "athletic",
        "footwear"
    ],
    "wof:name":"Sneakers-R-Me Ltd Inc",
    "wof:placetype":"venue"
},
  "geometry": {"coordinates":[-73.910933,40.885833],"type":"Point"}
}