{
  "type": "Feature",
  "properties": {
    "iso:country":"US",
    "sg:address":"595 Academy St",
    "sg:city":"New York",
    "sg:classifiers":[
        {
            "category":"Food & Beverages",
            "subcategory":"Groceries & Convenience Stores",
            "type":"Retail Goods"
        }
    ],
    "sg:phone":"+1 212 942 9200",
    "sg:postcode":"10034",
    "sg:province":"NY",
    "wof:name":"I & H Mini Market",
    "wof:placetype":"venue"
},
  "geometry": {"coordinates":[-73.923502,40.864296],"type":"Point"}
}