{
  "type": "Feature",
  "properties": {
    "addr:full":"1805 W 6th St Brooklyn NY 11223",
    "addr:housenumber":"1805",
    "addr:postcode":"11223",
    "addr:street":"W 6Th St",
    "iso:country":"US",
    "sg:address":"1805 W 6th St",
    "sg:city":"Brooklyn",
    "sg:classifiers":[
        {
            "category":"Health Services",
            "subcategory":"Dentist",
            "type":"Services"
        }
    ],
    "sg:phone":"+1 718 382 7338",
    "sg:postcode":"11223",
    "sg:province":"NY",
    "wof:name":"Rosen Michael DDS PC",
    "wof:placetype":"venue"
},
  "geometry": {"coordinates":[-73.97869900000001,40.603298],"type":"Point"}
}