{
  "type": "Feature",
  "properties": {
    "iso:country":"US",
    "sg:address":"272 W Jefferson St",
    "sg:city":"Syracuse",
    "sg:classifiers":[
        {
            "category":"Utilities",
            "subcategory":"Mobile Phone",
            "type":"Services"
        }
    ],
    "sg:phone":"+1 315 476 7464",
    "sg:postcode":"13202",
    "sg:province":"NY",
    "sg:tags":[
        "telephone",
        "cellular"
    ],
    "wof:name":"Intouch Wireless Of Syracuse",
    "wof:placetype":"venue"
},
  "geometry": {"coordinates":[-76.15431,43.047413],"type":"Point"}
}