{
  "type": "Feature",
  "properties": {
    "iso:country":"US",
    "sg:address":"1470 East Ave",
    "sg:city":"Bronx",
    "sg:classifiers":[
        {
            "category":"Restaurant",
            "type":"Food & Drink"
        }
    ],
    "sg:phone":"+1 718 597 1688",
    "sg:postcode":"10462",
    "sg:province":"NY",
    "sg:tags":[
        "eating",
        "chinese"
    ],
    "wof:name":"Dynasty Chinese Restaurant",
    "wof:placetype":"venue"
},
  "geometry": {"coordinates":[-73.859174,40.836532],"type":"Point"}
}