{
  "type": "Feature",
  "properties": {
    "iso:country":"US",
    "sg:address":"26 Plymouth Ave",
    "sg:city":"Franklinville",
    "sg:classifiers":[
        {
            "category":"Organizations",
            "subcategory":"Religious Organization",
            "type":"Services"
        }
    ],
    "sg:phone":"+1 716 676 3629",
    "sg:postcode":"14737",
    "sg:province":"NY",
    "sg:tags":[
        "clergy"
    ],
    "wof:name":"Michael O'Hara",
    "wof:placetype":"venue"
},
  "geometry": {"coordinates":[-78.45200699999999,42.343986],"type":"Point"}
}