{
  "type": "Feature",
  "properties": {
    "addr:full":"90 Old Orangeburg Rd Orangeburg NY 10962",
    "addr:housenumber":"90",
    "addr:postcode":"10962",
    "addr:street":"Old Orangeburg Rd",
    "iso:country":"US",
    "sg:address":"90 Old Orangeburg Rd",
    "sg:city":"Orangeburg",
    "sg:classifiers":[
        {
            "category":"Place Of Worship",
            "subcategory":"Church",
            "type":"Public Place"
        },
        {
            "category":"Place Of Worship",
            "type":"Public Place"
        }
    ],
    "sg:phone":"+1 845 359 0950",
    "sg:postcode":"10962",
    "sg:province":"NY",
    "sg:tags":[
        "churches-interdenominational",
        "churches-various",
        "denomination"
    ],
    "wof:name":"Bethany Mar Thoma Church",
    "wof:placetype":"venue"
},
  "geometry": {"coordinates":[-73.972719,41.044285],"type":"Point"}
}