{
  "type": "Feature",
  "properties": {
    "addr:full":"21 Huckleberry Ln Albany NY 12205",
    "addr:housenumber":"21",
    "addr:postcode":"12205",
    "addr:street":"Huckleberry Ln",
    "iso:country":"US",
    "sg:address":"21 Huckleberry Ln",
    "sg:city":"Albany",
    "sg:classifiers":[
        {
            "category":"Building & Trades",
            "subcategory":"Electrical",
            "type":"Services"
        }
    ],
    "sg:phone":"+1 518 456 2239",
    "sg:postcode":"12205",
    "sg:province":"NY",
    "sg:tags":[
        "electrician"
    ],
    "wof:name":"Electric Power Enterprises",
    "wof:placetype":"venue"
},
  "geometry": {"coordinates":[-73.830291,42.708577],"type":"Point"}
}