{
  "type": "Feature",
  "properties": {
    "iso:country":"US",
    "sg:address":"520 E 85th St",
    "sg:city":"New York",
    "sg:classifiers":[
        {
            "category":"Wholesale",
            "subcategory":"Apparel",
            "type":"Manufacturing & Wholesale Goods"
        }
    ],
    "sg:phone":"+1 212 861 2650",
    "sg:postcode":"10028",
    "sg:province":"NY",
    "sg:tags":[
        "product",
        "fiber",
        "gr",
        "broker",
        "textile",
        "brokerage"
    ],
    "wof:name":"Lerner Textile Associates",
    "wof:placetype":"venue"
},
  "geometry": {"coordinates":[-73.945668,40.774389],"type":"Point"}
}