{
  "type": "Feature",
  "properties": {
    "addr:full":"4585 Chestnut Ridge Rd Buffalo NY 14228",
    "addr:housenumber":"4585",
    "addr:postcode":"14228",
    "addr:street":"Chestnut Ridge Rd",
    "iso:country":"US",
    "sg:address":"4585 Chestnut Ridge Rd",
    "sg:city":"Buffalo",
    "sg:classifiers":[
        {
            "category":"Organizations",
            "subcategory":"Community Association",
            "type":"Services"
        }
    ],
    "sg:phone":"+1   ",
    "sg:postcode":"14228",
    "sg:province":"NY",
    "wof:name":"Womens League Weinburg C",
    "wof:placetype":"venue"
},
  "geometry": {"coordinates":[-78.808286,43.004548],"type":"Point"}
}