{
  "type": "Feature",
  "properties": {
    "addr:full":"28 Tyler St Freeport NY 11520",
    "addr:housenumber":"28",
    "addr:postcode":"11520",
    "addr:street":"Tyler St",
    "iso:country":"US",
    "sg:address":"28 Tyler St",
    "sg:city":"Freeport",
    "sg:classifiers":[
        {
            "category":"Building & Trades",
            "subcategory":"Construction",
            "type":"Services"
        }
    ],
    "sg:phone":"+1 516 546 2109",
    "sg:postcode":"11520",
    "sg:province":"NY",
    "sg:tags":[
        "equipment",
        "supply",
        "drywall",
        "contractor"
    ],
    "wof:name":"Johnson F L",
    "wof:placetype":"venue"
},
  "geometry": {"coordinates":[-73.579007,40.631956],"type":"Point"}
}