{
  "type": "Feature",
  "properties": {
    "iso:country":"US",
    "sg:address":"344 Red Apple Ln",
    "sg:city":"Rochester",
    "sg:classifiers":[
        {
            "category":"Retail",
            "subcategory":"Repair Shop",
            "type":"Services"
        }
    ],
    "sg:phone":"+1 585 225 2490",
    "sg:postcode":"14612",
    "sg:province":"NY",
    "sg:tags":[
        "refrigerator",
        "freezer"
    ],
    "wof:name":"Tony Vacca Appliance Svc & Rpr",
    "wof:placetype":"venue"
},
  "geometry": {"coordinates":[-77.676256,43.243418],"type":"Point"}
}