{
  "type": "Feature",
  "properties": {
    "addr:full":"143 Parkway Dr Roslyn Heights NY 11577",
    "addr:housenumber":"143",
    "addr:postcode":"11577",
    "addr:street":"Parkway Dr",
    "iso:country":"US",
    "sg:address":"143 Parkway Dr",
    "sg:city":"Roslyn Heights",
    "sg:classifiers":[
        {
            "category":"Insurance",
            "subcategory":"Insurance Agent",
            "type":"Services"
        }
    ],
    "sg:phone":"+1 516 484 4907",
    "sg:postcode":"11577",
    "sg:province":"NY",
    "wof:name":"Zappa Co",
    "wof:placetype":"venue"
},
  "geometry": {"coordinates":[-73.62624599999999,40.775224],"type":"Point"}
}