{
  "type": "Feature",
  "properties": {
    "addr:full":"480 Bedford Rd Pleasantville NY 10570",
    "addr:housenumber":"480",
    "addr:postcode":"10570",
    "addr:street":"Bedford Rd",
    "iso:country":"US",
    "sg:address":"480 Bedford Rd",
    "sg:city":"Pleasantville",
    "sg:classifiers":[
        {
            "category":"Communications",
            "subcategory":"Newspaper",
            "type":"Services"
        }
    ],
    "sg:phone":"+1 914 244 4900",
    "sg:postcode":"10570",
    "sg:province":"NY",
    "sg:tags":[
        "print",
        "medium"
    ],
    "sg:website":"www.readersdigest.com",
    "wof:name":"Reader's Digest Association Inc",
    "wof:placetype":"venue"
},
  "geometry": {"coordinates":[-73.79339,41.132803],"type":"Point"}
}