{
  "type": "Feature",
  "properties": {
    "iso:country":"US",
    "sg:address":"4966 E Lake Rd",
    "sg:city":"Romulus",
    "sg:classifiers":[
        {
            "category":"Banks & Credit Unions",
            "subcategory":"Financial Services",
            "type":"Services"
        }
    ],
    "sg:phone":"+1 315 585 4400",
    "sg:postcode":"14541",
    "sg:province":"NY",
    "sg:tags":[
        "company",
        "holding"
    ],
    "wof:name":"S P N Holdings Inc",
    "wof:placetype":"venue"
},
  "geometry": {"coordinates":[-76.92673000000001,42.783159],"type":"Point"}
}