{
  "type": "Feature",
  "properties": {
    "iso:country":"US",
    "sg:address":"2386 Lincoln St",
    "sg:city":"North Bellmore",
    "sg:classifiers":[
        {
            "category":"Personal",
            "subcategory":"Beauty Salon",
            "type":"Services"
        }
    ],
    "sg:phone":"+1 516 783 5616",
    "sg:postcode":"11710",
    "sg:province":"NY",
    "sg:tags":[
        "shop",
        "manicuring"
    ],
    "wof:name":"Not Just Nails",
    "wof:placetype":"venue"
},
  "geometry": {"coordinates":[-73.54432799999999,40.682439],"type":"Point"}
}