{
  "type": "Feature",
  "properties": {
    "addr:full":"130 John St New York NY 10038",
    "addr:housenumber":"130",
    "addr:postcode":"10038",
    "addr:street":"John St",
    "iso:country":"US",
    "sg:address":"130 John St",
    "sg:city":"New York",
    "sg:classifiers":[
        {
            "category":"Communications",
            "subcategory":"Newspaper",
            "type":"Services"
        }
    ],
    "sg:phone":"+1 212 248 9092",
    "sg:postcode":"10038",
    "sg:province":"NY",
    "sg:tags":[
        "print",
        "medium"
    ],
    "wof:name":"Monali Newstand",
    "wof:placetype":"venue"
},
  "geometry": {"coordinates":[-74.445491,40.707144],"type":"Point"}
}