{
  "type": "Feature",
  "properties": {
    "addr:full":"133 2nd Ave New York NY 10003",
    "addr:housenumber":"133",
    "addr:postcode":"10003",
    "addr:street":"2Nd Ave",
    "iso:country":"US",
    "sg:address":"133 2nd Ave",
    "sg:city":"New York",
    "sg:classifiers":[
        {
            "category":"Health Services",
            "subcategory":"Optometrist",
            "type":"Services"
        },
        {
            "category":"Shopping",
            "subcategory":"Optician",
            "type":"Retail Goods"
        }
    ],
    "sg:phone":"+1 212 254 0246",
    "sg:postcode":"10003",
    "sg:province":"NY",
    "sg:tags":[
        "eyewear"
    ],
    "sg:website":"www.cohensfashionoptical.com",
    "wof:name":"Cohens Fashion Optical Best Deal",
    "wof:placetype":"venue"
},
  "geometry": {"coordinates":[-73.9879,40.728901],"type":"Point"}
}