{
  "type": "Feature",
  "properties": {
    "addr:full":"2687 Bedford Ave Brooklyn NY 11210",
    "addr:housenumber":"2687",
    "addr:postcode":"11210",
    "addr:street":"Bedford Ave",
    "iso:country":"US",
    "sg:address":"2687 Bedford Ave",
    "sg:city":"Brooklyn",
    "sg:classifiers":[
        {
            "category":"Health Services",
            "subcategory":"Doctor",
            "type":"Services"
        }
    ],
    "sg:phone":"+1 718 434 1924",
    "sg:postcode":"11210",
    "sg:province":"NY",
    "sg:tags":[
        "physician",
        "surgeon"
    ],
    "wof:name":"Edouard Guillaume MD",
    "wof:placetype":"venue"
},
  "geometry": {"coordinates":[-73.95347599999999,40.636692],"type":"Point"}
}