{
  "type": "Feature",
  "properties": {
    "addr:full":"35 Victory Blvd Staten Island NY 10301",
    "addr:housenumber":"35",
    "addr:postcode":"10301",
    "addr:street":"Victory Blvd",
    "iso:country":"US",
    "sg:address":"35 Victory Blvd",
    "sg:city":"Staten Island",
    "sg:classifiers":[
        {
            "category":"Restaurant",
            "type":"Food & Drink"
        }
    ],
    "sg:menulink":"http://www.allmenus.com/ny/staten-island/43405-el-coqui/menu/",
    "sg:phone":"+1 718 662 3726",
    "sg:postcode":"10301",
    "sg:province":"NY",
    "sg:tags":[
        "spanish"
    ],
    "wof:name":"El Coqui",
    "wof:placetype":"venue"
},
  "geometry": {"coordinates":[-74.076471,40.637769],"type":"Point"}
}