{
  "type": "Feature",
  "properties": {
    "addr:full":"344 Main St Sag Harbor NY 11963",
    "addr:housenumber":"344",
    "addr:postcode":"11963",
    "addr:street":"Main St",
    "iso:country":"US",
    "sg:address":"344 Main St",
    "sg:city":"Sag Harbor",
    "sg:classifiers":[
        {
            "category":"Building & Trades",
            "subcategory":"Electrical",
            "type":"Services"
        }
    ],
    "sg:phone":"+1 631 725 2930",
    "sg:postcode":"11963",
    "sg:province":"NY",
    "sg:tags":[
        "electric",
        "contractor"
    ],
    "wof:name":"Electrician",
    "wof:placetype":"venue"
},
  "geometry": {"coordinates":[-72.300608,40.991428],"type":"Point"}
}