{
  "type": "Feature",
  "properties": {
    "addr:full":"6 E Fordham Rd Bronx NY 10468",
    "addr:housenumber":"6",
    "addr:postcode":"10468",
    "addr:street":"E Fordham Rd",
    "iso:country":"US",
    "sg:address":"6 E Fordham Rd",
    "sg:city":"Bronx",
    "sg:classifiers":[
        {
            "category":"Wholesale",
            "subcategory":"Apparel",
            "type":"Manufacturing & Wholesale Goods"
        }
    ],
    "sg:phone":"+1 718 329 2923",
    "sg:postcode":"10468",
    "sg:province":"NY",
    "sg:tags":[
        "shoes"
    ],
    "wof:name":"Hot Spot",
    "wof:placetype":"venue"
},
  "geometry": {"coordinates":[-73.900368,40.862429],"type":"Point"}
}