{
  "type": "Feature",
  "properties": {
    "addr:full":"5603 8th Avenue Brooklyn NY 11220",
    "addr:housenumber":"5603",
    "addr:postcode":"11220",
    "addr:street":"8Th Avenue",
    "iso:country":"US",
    "sg:address":"5603 8th Avenue",
    "sg:city":"Brooklyn",
    "sg:classifiers":[
        {
            "category":"Restaurant",
            "type":"Food & Drink"
        }
    ],
    "sg:phone":"+1 718 851 8208",
    "sg:postcode":"11220",
    "sg:province":"NY",
    "wof:name":"Fung Sing Restaurant",
    "wof:placetype":"venue"
},
  "geometry": {"coordinates":[-74.00720800000001,40.637554],"type":"Point"}
}