{
  "type": "Feature",
  "properties": {
    "iso:country":"US",
    "sg:address":"190 Atlantic Ave Ste 2",
    "sg:city":"Garden City Park",
    "sg:classifiers":[
        {
            "category":"Professional",
            "subcategory":"Advertising",
            "type":"Services"
        }
    ],
    "sg:phone":"+1 516 248 2501",
    "sg:postcode":"11040",
    "sg:province":"NY",
    "sg:tags":[
        "marketing"
    ],
    "wof:name":"Conquer Marketing Now",
    "wof:placetype":"venue"
},
  "geometry": {"coordinates":[-73.659317,40.736177],"type":"Point"}
}