{
  "type": "Feature",
  "properties": {
    "addr:full":"163-24 Northern Blvd Flushing NY 11369",
    "addr:housenumber":"163-24",
    "addr:postcode":"11369",
    "addr:street":"Northern Blvd",
    "iso:country":"US",
    "sg:address":"163-24 Northern Blvd",
    "sg:city":"Flushing",
    "sg:classifiers":[
        {
            "category":"Restaurant",
            "type":"Food & Drink"
        }
    ],
    "sg:phone":"+1 718 539 0288",
    "sg:postcode":"11369",
    "sg:province":"NY",
    "sg:tags":[
        "korean"
    ],
    "wof:name":"Mani Mani",
    "wof:placetype":"venue"
},
  "geometry": {"coordinates":[-73.82976600000001,40.763653],"type":"Point"}
}