{
  "type": "Feature",
  "properties": {
    "addr:full":"2255 Grand Concourse Bronx NY 10453",
    "addr:housenumber":"2255",
    "addr:postcode":"10453",
    "addr:street":"Grand Concourse",
    "iso:country":"US",
    "sg:address":"2255 Grand Concourse",
    "sg:city":"Bronx",
    "sg:classifiers":[
        {
            "category":"Communications",
            "type":"Services"
        }
    ],
    "sg:phone":"+1 718 329 4000",
    "sg:postcode":"10453",
    "sg:province":"NY",
    "wof:name":"Teleremesas Communication",
    "wof:placetype":"venue"
},
  "geometry": {"coordinates":[-73.900363,40.856695],"type":"Point"}
}