{
  "type": "Feature",
  "properties": {
    "addr:full":"15034 - 15037 14 Ave Queens NY 11357",
    "addr:housenumber":"15034",
    "addr:postcode":"11357",
    "addr:street":"15037 14 Ave",
    "iso:country":"US",
    "sg:address":"15034 - 15037 14 Ave",
    "sg:city":"Queens",
    "sg:classifiers":[
        {
            "category":"Communications",
            "type":"Services"
        }
    ],
    "sg:phone":"+1 718 767 4452",
    "sg:postcode":"11357",
    "sg:province":"NY",
    "sg:tags":[
        "recording",
        "rehearsal",
        "studio"
    ],
    "sg:website":"www.multisoundstudios.com/record...",
    "wof:name":"MULTI-SOUND - Queens Music Building",
    "wof:placetype":"venue"
},
  "geometry": {"coordinates":[-73.812393,40.789176],"type":"Point"}
}