{
  "type": "Feature",
  "properties": {
    "iso:country":"US",
    "sg:address":"111 Hicks St",
    "sg:city":"Brooklyn",
    "sg:classifiers":[
        {
            "category":"Professional",
            "subcategory":"Management & Consulting",
            "type":"Services"
        }
    ],
    "sg:phone":"+1   ",
    "sg:postcode":"11201",
    "sg:province":"NY",
    "sg:tags":[
        "training",
        "program",
        "delivers",
        "develops"
    ],
    "wof:name":"Situation Management Systems",
    "wof:placetype":"venue"
},
  "geometry": {"coordinates":[-73.994416,40.698186],"type":"Point"}
}