{
  "type": "Feature",
  "properties": {
    "iso:country":"US",
    "sg:address":"138 S Country Rd",
    "sg:city":"Bellport",
    "sg:classifiers":[
        {
            "category":"Shopping",
            "subcategory":"Discount & Variety Stores",
            "type":"Retail Goods"
        }
    ],
    "sg:phone":"+1 631 286 2210",
    "sg:postcode":"11713",
    "sg:province":"NY",
    "wof:name":"Variety Mart",
    "wof:placetype":"venue"
},
  "geometry": {"coordinates":[-72.938164,40.758176],"type":"Point"}
}