{
  "type": "Feature",
  "properties": {
    "addr:full":"112 Hayrick Ln Commack NY 11725",
    "addr:housenumber":"112",
    "addr:postcode":"11725",
    "addr:street":"Hayrick Ln",
    "iso:country":"US",
    "sg:address":"112 Hayrick Ln",
    "sg:city":"Commack",
    "sg:classifiers":[
        {
            "category":"Building & Trades",
            "subcategory":"Construction",
            "type":"Services"
        }
    ],
    "sg:phone":"+1 631 858 1888",
    "sg:postcode":"11725",
    "sg:province":"NY",
    "sg:tags":[
        "contractor",
        "carpenter",
        "carpentry"
    ],
    "wof:name":"Wolf Lone Contractor",
    "wof:placetype":"venue"
},
  "geometry": {"coordinates":[-73.280731,40.85553],"type":"Point"}
}