{
  "type": "Feature",
  "properties": {
    "iso:country":"US",
    "sg:address":"219 Davis Rd",
    "sg:city":"East Aurora",
    "sg:classifiers":[
        {
            "category":"Recreation",
            "type":"Entertainment"
        }
    ],
    "sg:phone":"+1 716 655 1422",
    "sg:postcode":"14127",
    "sg:province":"NY",
    "sg:tags":[
        "tennis",
        "court"
    ],
    "wof:name":"Quaker Aurora Tennis Club",
    "wof:placetype":"venue"
},
  "geometry": {"coordinates":[-78.681409,42.75812],"type":"Point"}
}