{
  "type": "Feature",
  "properties": {
    "addr:full":"2140 Ocean Ave Brooklyn NY 11229",
    "addr:housenumber":"2140",
    "addr:postcode":"11229",
    "addr:street":"Ocean Ave",
    "iso:country":"US",
    "sg:address":"2140 Ocean Ave",
    "sg:city":"Brooklyn",
    "sg:classifiers":[
        {
            "category":"Health Services",
            "subcategory":"Doctor",
            "type":"Services"
        }
    ],
    "sg:phone":"+1 718 645 4422",
    "sg:postcode":"11229",
    "sg:province":"NY",
    "sg:tags":[
        "throat",
        "ear",
        "nose"
    ],
    "wof:name":"Wein Stanley MD",
    "wof:placetype":"venue"
},
  "geometry": {"coordinates":[-73.95349899999999,40.609501],"type":"Point"}
}