{
  "type": "Feature",
  "properties": {
    "addr:full":"137 Chauncey Ave New Rochelle NY 10801",
    "addr:housenumber":"137",
    "addr:postcode":"10801",
    "addr:street":"Chauncey Ave",
    "iso:country":"US",
    "sg:address":"137 Chauncey Ave",
    "sg:city":"New Rochelle",
    "sg:classifiers":[
        {
            "category":"Building & Trades",
            "subcategory":"Construction",
            "type":"Services"
        }
    ],
    "sg:phone":"+1 914 235 1611",
    "sg:postcode":"10801",
    "sg:province":"NY",
    "sg:tags":[
        "contractor"
    ],
    "wof:name":"Rogers Brothers",
    "wof:placetype":"venue"
},
  "geometry": {"coordinates":[-73.793571,40.922361],"type":"Point"}
}