{
  "type": "Feature",
  "properties": {
    "addr:full":"1193 Walton Avenue Bronx NY 10452",
    "addr:housenumber":"1193",
    "addr:postcode":"10452",
    "addr:street":"Walton Avenue",
    "iso:country":"US",
    "sg:address":"1193 Walton Avenue",
    "sg:city":"Bronx",
    "sg:classifiers":[
        {
            "category":"Bakery",
            "type":"Food & Drink"
        }
    ],
    "sg:phone":"+1 718 537 5105",
    "sg:postcode":"10452",
    "sg:province":"NY",
    "wof:name":"National Bakery",
    "wof:placetype":"venue"
},
  "geometry": {"coordinates":[-73.92012099999999,40.83422],"type":"Point"}
}