{
  "type": "Feature",
  "properties": {
    "addr:full":"30 Central Park S New York NY 10019",
    "addr:housenumber":"30",
    "addr:postcode":"10019",
    "addr:street":"Central Park S",
    "iso:country":"US",
    "sg:address":"30 Central Park S",
    "sg:city":"New York",
    "sg:classifiers":[
        {
            "category":"Health Services",
            "subcategory":"Doctor",
            "type":"Services"
        }
    ],
    "sg:phone":"+1   ",
    "sg:postcode":"10019",
    "sg:province":"NY",
    "wof:name":"Sonoak Rhee DDS",
    "wof:placetype":"venue"
},
  "geometry": {"coordinates":[-73.975696,40.765287],"type":"Point"}
}