{
  "type": "Feature",
  "properties": {
    "iso:country":"US",
    "sg:address":"1910 Southwestern Dr",
    "sg:city":"Lakewood",
    "sg:classifiers":[
        {
            "category":"Mining & Drilling",
            "type":"Manufacturing & Wholesale Goods"
        }
    ],
    "sg:phone":"+1 716 450 3360",
    "sg:postcode":"14750",
    "sg:province":"NY",
    "sg:tags":[
        "rigger"
    ],
    "wof:name":"Afab Sales LLC",
    "wof:placetype":"venue"
},
  "geometry": {"coordinates":[-79.29506499999999,42.081152],"type":"Point"}
}