{
  "type": "Feature",
  "properties": {
    "addr:full":"302 Vanderbilt St Brooklyn NY 11218",
    "addr:housenumber":"302",
    "addr:postcode":"11218",
    "addr:street":"Vanderbilt St",
    "iso:country":"US",
    "sg:address":"302 Vanderbilt St",
    "sg:city":"Brooklyn",
    "sg:classifiers":[
        {
            "category":"Education",
            "subcategory":"School",
            "type":"Public Place"
        }
    ],
    "sg:phone":"+1 718 436 3779",
    "sg:postcode":"11218",
    "sg:province":"NY",
    "wof:name":"International Christian School",
    "wof:placetype":"venue"
},
  "geometry": {"coordinates":[-73.97911499999999,40.652378],"type":"Point"}
}