{
  "type": "Feature",
  "properties": {
    "addr:full":"150 W 28th St Ste 904 New York NY 10001",
    "addr:housenumber":"150;904",
    "addr:postcode":"10001",
    "addr:street":"W 28Th St Ste",
    "iso:country":"US",
    "sg:address":"150 W 28th St Ste 904",
    "sg:city":"New York",
    "sg:classifiers":[
        {
            "category":"Health Services",
            "subcategory":"Clinic",
            "type":"Services"
        }
    ],
    "sg:phone":"+1 917 656 1987",
    "sg:postcode":"10001",
    "sg:province":"NY",
    "sg:tags":[
        "medical"
    ],
    "wof:name":"Muscle Mechanic, LLC",
    "wof:placetype":"venue"
},
  "geometry": {"coordinates":[-73.992805,40.7469],"type":"Point"}
}