{
  "type": "Feature",
  "properties": {
    "addr:full":"128 Rutledge St Brooklyn NY 11211",
    "addr:housenumber":"128",
    "addr:postcode":"11211",
    "addr:street":"Rutledge St",
    "iso:country":"US",
    "sg:address":"128 Rutledge St",
    "sg:city":"Brooklyn",
    "sg:classifiers":[
        {
            "category":"Professional",
            "type":"Services"
        }
    ],
    "sg:phone":"+1 718 852 3048",
    "sg:postcode":"11211",
    "sg:province":"NY",
    "sg:tags":[
        "establishment"
    ],
    "wof:name":"Gemilas Chasudim Moshe Elya",
    "wof:placetype":"venue"
},
  "geometry": {"coordinates":[-73.956644,40.702163],"type":"Point"}
}