{
  "type": "Feature",
  "properties": {
    "iso:country":"US",
    "sg:address":"181 E 1st St",
    "sg:city":"Oswego",
    "sg:classifiers":[
        {
            "category":"Freight",
            "type":"Transportation"
        }
    ],
    "sg:phone":"+1 315 207 0210",
    "sg:postcode":"13126",
    "sg:province":"NY",
    "sg:tags":[
        "commercial",
        "storage"
    ],
    "wof:name":"Corner Quick Stor",
    "wof:placetype":"venue"
},
  "geometry": {"coordinates":[-76.506417,43.455321],"type":"Point"}
}