{
  "type": "Feature",
  "properties": {
    "iso:country":"US",
    "sg:address":"601 Oriskany Blvd",
    "sg:city":"Yorkville",
    "sg:classifiers":[
        {
            "category":"Restaurant",
            "type":"Food & Drink"
        }
    ],
    "sg:phone":"+1 315 768 6688",
    "sg:postcode":"13495",
    "sg:province":"NY",
    "sg:tags":[
        "asian",
        "chinese",
        "pan"
    ],
    "wof:name":"China Wong",
    "wof:placetype":"venue"
},
  "geometry": {"coordinates":[-75.278091,43.114128],"type":"Point"}
}