{
  "type": "Feature",
  "properties": {
    "addr:full":"3641 Hayes Rd Baldwinsville NY 13027",
    "addr:housenumber":"3641",
    "addr:postcode":"13027",
    "addr:street":"Hayes Rd",
    "iso:country":"US",
    "sg:address":"3641 Hayes Rd",
    "sg:city":"Baldwinsville",
    "sg:classifiers":[
        {
            "category":"Retail",
            "subcategory":"Auto Repair",
            "type":"Services"
        }
    ],
    "sg:phone":"+1 315 652 3241",
    "sg:postcode":"13027",
    "sg:province":"NY",
    "sg:tags":[
        "transmission"
    ],
    "wof:name":"B & M Transmission",
    "wof:placetype":"venue"
},
  "geometry": {"coordinates":[-76.283559,43.128426],"type":"Point"}
}