{
  "type": "Feature",
  "properties": {
    "addr:full":"223 Broadway Greenlawn Huntington NY 11743",
    "addr:housenumber":"223",
    "addr:postcode":"11743",
    "addr:street":"Broadway",
    "iso:country":"US",
    "sg:address":"223 Broadway Greenlawn",
    "sg:city":"Huntington",
    "sg:classifiers":[
        {
            "category":"Food & Beverages",
            "subcategory":"Groceries & Convenience Stores",
            "type":"Retail Goods"
        }
    ],
    "sg:phone":"+1 631 239 6836",
    "sg:postcode":"11743",
    "sg:province":"NY",
    "wof:name":"Friends Food Market",
    "wof:placetype":"venue"
},
  "geometry": {"coordinates":[-73.365669,40.852801],"type":"Point"}
}