{
  "type": "Feature",
  "properties": {
    "iso:country":"US",
    "sg:address":"112 Glenwood Ln",
    "sg:city":"Port Jefferson",
    "sg:classifiers":[
        {
            "category":"Professional",
            "type":"Services"
        }
    ],
    "sg:phone":"+1 631 928 2389",
    "sg:postcode":"11777",
    "sg:province":"NY",
    "sg:tags":[
        "psychologist"
    ],
    "wof:name":"Jennifer A Flynn PHD",
    "wof:placetype":"venue"
},
  "geometry": {"coordinates":[-73.083567,40.941341],"type":"Point"}
}