{
  "type": "Feature",
  "properties": {
    "addr:full":"219 W 48 St New York NY 10036",
    "addr:housenumber":"219",
    "addr:postcode":"10036",
    "addr:street":"W 48 St",
    "iso:country":"US",
    "sg:address":"219 W 48 St",
    "sg:city":"New York",
    "sg:classifiers":[
        {
            "category":"Professional",
            "subcategory":"Management & Consulting",
            "type":"Services"
        }
    ],
    "sg:phone":"+1 212 977 4542",
    "sg:postcode":"10036",
    "sg:province":"NY",
    "sg:tags":[
        "business"
    ],
    "wof:name":"Valvo Vincent",
    "wof:placetype":"venue"
},
  "geometry": {"coordinates":[-73.9867,40.760948],"type":"Point"}
}