{
  "type": "Feature",
  "properties": {
    "addr:full":"4 Forrest Dr Huntington NY 11743",
    "addr:housenumber":"4",
    "addr:postcode":"11743",
    "addr:street":"Forrest Dr",
    "iso:country":"US",
    "sg:address":"4 Forrest Dr",
    "sg:city":"Huntington",
    "sg:classifiers":[
        {
            "category":"Organizations",
            "subcategory":"Professional Association",
            "type":"Services"
        }
    ],
    "sg:phone":"+1   ",
    "sg:postcode":"11743",
    "sg:province":"NY",
    "wof:name":"American Assoc of Univers",
    "wof:placetype":"venue"
},
  "geometry": {"coordinates":[-73.443443,40.924178],"type":"Point"}
}