{
  "type": "Feature",
  "properties": {
    "addr:full":"3015 Atlantic Ave Brooklyn NY 11208",
    "addr:housenumber":"3015",
    "addr:postcode":"11208",
    "addr:street":"Atlantic Ave",
    "iso:country":"US",
    "sg:address":"3015 Atlantic Ave",
    "sg:city":"Brooklyn",
    "sg:classifiers":[
        {
            "category":"Organizations",
            "subcategory":"Religious Organization",
            "type":"Services"
        }
    ],
    "sg:phone":"+1 718 385 8192",
    "sg:postcode":"11208",
    "sg:province":"NY",
    "sg:tags":[
        "pentecostal",
        "church"
    ],
    "wof:name":"First Crstana Misionera Church",
    "wof:placetype":"venue"
},
  "geometry": {"coordinates":[-73.882818,40.67848],"type":"Point"}
}