{
  "type": "Feature",
  "properties": {
    "addr:full":"5856 Mud Mill Rd Brewerton NY 13029",
    "addr:housenumber":"5856",
    "addr:postcode":"13029",
    "addr:street":"Mud Mill Rd",
    "iso:country":"US",
    "sg:address":"5856 Mud Mill Rd",
    "sg:city":"Brewerton",
    "sg:classifiers":[
        {
            "category":"Personal",
            "type":"Services"
        }
    ],
    "sg:phone":"+1 315 475 8941",
    "sg:postcode":"13029",
    "sg:province":"NY",
    "sg:tags":[
        "towing"
    ],
    "wof:name":"Cesta Towing",
    "wof:placetype":"venue"
},
  "geometry": {"coordinates":[-76.117137,43.208998],"type":"Point"}
}