{
  "type": "Feature",
  "properties": {
    "addr:full":"66 Millpond Pkwy Monroe NY 10950",
    "addr:housenumber":"66",
    "addr:postcode":"10950",
    "addr:street":"Millpond Pkwy",
    "iso:country":"US",
    "sg:address":"66 Millpond Pkwy",
    "sg:city":"Monroe",
    "sg:classifiers":[
        {
            "category":"Restaurant",
            "type":"Food & Drink"
        }
    ],
    "sg:phone":"+1 845 492 2067",
    "sg:postcode":"10950",
    "sg:province":"NY",
    "sg:tags":[
        "delicatessen"
    ],
    "wof:name":"Guelaguepza Inc",
    "wof:placetype":"venue"
},
  "geometry": {"coordinates":[-74.191242,41.333473],"type":"Point"}
}