{
  "type": "Feature",
  "properties": {
    "addr:full":"977 E 82nd St Brooklyn NY 11236",
    "addr:housenumber":"977",
    "addr:postcode":"11236",
    "addr:street":"E 82Nd St",
    "iso:country":"US",
    "sg:address":"977 E 82nd St",
    "sg:city":"Brooklyn",
    "sg:classifiers":[
        {
            "category":"Professional",
            "type":"Services"
        }
    ],
    "sg:phone":"+1   ",
    "sg:postcode":"11236",
    "sg:province":"NY",
    "wof:name":"Best Radiant Inc",
    "wof:placetype":"venue"
},
  "geometry": {"coordinates":[-73.911136,40.636331],"type":"Point"}
}