{
  "type": "Feature",
  "properties": {
    "addr:full":"10 Ave P Brooklyn NY 11204",
    "addr:postcode":"11204",
    "addr:street":"10 Ave",
    "iso:country":"US",
    "sg:address":"10 Ave P",
    "sg:city":"Brooklyn",
    "sg:classifiers":[
        {
            "category":"Real Estate",
            "subcategory":"Real Estate Agent",
            "type":"Services"
        }
    ],
    "sg:phone":"+1 718 236 5876",
    "sg:postcode":"11204",
    "sg:province":"NY",
    "wof:name":"10 Avenue P Condominium",
    "wof:placetype":"venue"
},
  "geometry": {"coordinates":[-73.98748000000001,40.607137],"type":"Point"}
}