{
  "type": "Feature",
  "properties": {
    "iso:country":"US",
    "sg:address":"7901 3rd Ave",
    "sg:city":"Brooklyn",
    "sg:classifiers":[
        {
            "category":"Bars & Pubs",
            "type":"Food & Drink"
        },
        {
            "category":"Restaurant",
            "type":"Food & Drink"
        },
        {
            "category":"Bars & Pubs",
            "subcategory":"Lounge",
            "type":"Food & Drink"
        }
    ],
    "sg:phone":"+1 718 491 2967",
    "sg:postcode":"11209",
    "sg:province":"NY",
    "sg:tags":[
        "cocktail"
    ],
    "wof:name":"Judge & Jury",
    "wof:placetype":"venue"
},
  "geometry": {"coordinates":[-74.028992,40.628559],"type":"Point"}
}