{
  "type": "Feature",
  "properties": {
    "iso:country":"US",
    "sg:address":"823 Franklin Ave",
    "sg:city":"Brooklyn",
    "sg:classifiers":[
        {
            "category":"Bakery",
            "type":"Food & Drink"
        }
    ],
    "sg:phone":"+1 718 493 3865",
    "sg:postcode":"11225",
    "sg:province":"NY",
    "wof:name":"Golden Crust",
    "wof:placetype":"venue"
},
  "geometry": {"coordinates":[-73.956902,40.6702],"type":"Point"}
}