{
  "type": "Feature",
  "properties": {
    "addr:full":"2801 Tilden Ave Brooklyn NY 11226",
    "addr:housenumber":"2801",
    "addr:postcode":"11226",
    "addr:street":"Tilden Ave",
    "iso:country":"US",
    "sg:address":"2801 Tilden Ave",
    "sg:city":"Brooklyn",
    "sg:classifiers":[
        {
            "category":"Manufacturing",
            "subcategory":"Tools & Machinery",
            "type":"Manufacturing & Wholesale Goods"
        },
        {
            "category":"Manufacturing",
            "subcategory":"Motor Vehicles & Parts",
            "type":"Manufacturing & Wholesale Goods"
        }
    ],
    "sg:phone":"+1 718 693 5033",
    "sg:postcode":"11226",
    "sg:province":"NY",
    "sg:tags":[
        "equipment",
        "clothing",
        "safety",
        "mfg"
    ],
    "wof:name":"Roger's Taxi Partitions",
    "wof:placetype":"venue"
},
  "geometry": {"coordinates":[-73.950125,40.646847],"type":"Point"}
}