{
  "type": "Feature",
  "properties": {
    "addr:full":"55 W 47th St Ste 1125 New York NY 10036",
    "addr:housenumber":"55",
    "addr:postcode":"10036",
    "addr:street":"W 47Th St Ste 1125",
    "iso:country":"US",
    "sg:address":"55 W 47th St Ste 1125",
    "sg:city":"New York",
    "sg:classifiers":[
        {
            "category":"Shopping",
            "subcategory":"Jewelry",
            "type":"Retail Goods"
        }
    ],
    "sg:phone":"+1 212 354 7579",
    "sg:postcode":"10036",
    "sg:province":"NY",
    "wof:name":"Blue Gems & Beads",
    "wof:placetype":"venue"
},
  "geometry": {"coordinates":[-73.980268,40.757532],"type":"Point"}
}