{
  "type": "Feature",
  "properties": {
    "addr:full":"417 Canal St Fl 4 New York NY 10013",
    "addr:housenumber":"417;4",
    "addr:postcode":"10013",
    "addr:street":"Canal St",
    "iso:country":"US",
    "sg:address":"417 Canal St Fl 4",
    "sg:city":"New York",
    "sg:classifiers":[
        {
            "category":"Professional",
            "subcategory":"Lawyer & Legal Services",
            "type":"Services"
        }
    ],
    "sg:phone":"+1 212 226 5054",
    "sg:postcode":"10013",
    "sg:province":"NY",
    "wof:name":"Robert L Powley PC",
    "wof:placetype":"venue"
},
  "geometry": {"coordinates":[-74.00610399999999,40.722401],"type":"Point"}
}