{
  "type": "Feature",
  "properties": {
    "iso:country":"US",
    "sg:address":"309 Washington St",
    "sg:city":"Newark",
    "sg:classifiers":[
        {
            "category":"Real Estate",
            "subcategory":"Real Estate Operator",
            "type":"Services"
        }
    ],
    "sg:phone":"+1 315 331 4486",
    "sg:postcode":"14513",
    "sg:province":"NY",
    "sg:tags":[
        "apartment"
    ],
    "wof:name":"Antillie Properties Inc",
    "wof:placetype":"venue"
},
  "geometry": {"coordinates":[-77.098722,43.041174],"type":"Point"}
}