{
  "type": "Feature",
  "properties": {
    "addr:full":"1938 Deer Park Ave Deer Park NY 11729",
    "addr:housenumber":"1938",
    "addr:postcode":"11729",
    "addr:street":"Deer Park Ave",
    "iso:country":"US",
    "sg:address":"1938 Deer Park Ave",
    "sg:city":"Deer Park",
    "sg:classifiers":[
        {
            "category":"Shopping",
            "subcategory":"Gifts & Souvenirs",
            "type":"Retail Goods"
        }
    ],
    "sg:phone":"+1 631 586 6887",
    "sg:postcode":"11729",
    "sg:province":"NY",
    "sg:tags":[
        "basket",
        "parcel"
    ],
    "sg:website":"www.atsweetnuthut.com",
    "wof:name":"Sweet Nut Hut LTD",
    "wof:placetype":"venue"
},
  "geometry": {"coordinates":[-73.33008100000001,40.763153],"type":"Point"}
}