{
  "type": "Feature",
  "properties": {
    "addr:full":"461 20th St Brooklyn NY 11215",
    "addr:housenumber":"461",
    "addr:postcode":"11215",
    "addr:street":"20Th St",
    "iso:country":"US",
    "sg:address":"461 20th St",
    "sg:city":"Brooklyn",
    "sg:classifiers":[
        {
            "category":"Building & Trades",
            "subcategory":"Construction",
            "type":"Services"
        }
    ],
    "sg:phone":"+1 718 832 1058",
    "sg:postcode":"11215",
    "sg:province":"NY",
    "sg:tags":[
        "woodworker"
    ],
    "wof:name":"South Slope Woodworks",
    "wof:placetype":"venue"
},
  "geometry": {"coordinates":[-73.98472599999999,40.657246],"type":"Point"}
}