{
  "type": "Feature",
  "properties": {
    "addr:full":"4920 15th Ave Brooklyn NY 11219",
    "addr:housenumber":"4920",
    "addr:postcode":"11219",
    "addr:street":"15Th Ave",
    "iso:country":"US",
    "sg:address":"4920 15th Ave",
    "sg:city":"Brooklyn",
    "sg:classifiers":[
        {
            "category":"Professional",
            "subcategory":"Credit Reporting & Collection",
            "type":"Services"
        }
    ],
    "sg:phone":"+1 718 854 6555",
    "sg:postcode":"11219",
    "sg:province":"NY",
    "sg:tags":[
        "agency"
    ],
    "wof:name":"Certified Collections Funds",
    "wof:placetype":"venue"
},
  "geometry": {"coordinates":[-73.988264,40.631964],"type":"Point"}
}