{
  "type": "Feature",
  "properties": {
    "addr:full":"436 Lockwood Dr Shirley NY 11967",
    "addr:housenumber":"436",
    "addr:postcode":"11967",
    "addr:street":"Lockwood Dr",
    "iso:country":"US",
    "sg:address":"436 Lockwood Dr",
    "sg:city":"Shirley",
    "sg:classifiers":[
        {
            "category":"Transit Center",
            "subcategory":"Freight",
            "type":"Transportation"
        },
        {
            "category":"Freight",
            "type":"Transportation"
        }
    ],
    "sg:phone":"+1 631 924 4189",
    "sg:postcode":"11967",
    "sg:province":"NY",
    "sg:tags":[
        "local",
        "trucking-motor",
        "trucking"
    ],
    "wof:name":"J. P. M .Trucking Inc.",
    "wof:placetype":"venue"
},
  "geometry": {"coordinates":[-72.87617899999999,40.836187],"type":"Point"}
}