{
  "type": "Feature",
  "properties": {
    "iso:country":"US",
    "sg:address":"482 Lenox Ave",
    "sg:city":"New York",
    "sg:classifiers":[
        {
            "category":"Shopping",
            "subcategory":"Shoes",
            "type":"Retail Goods"
        }
    ],
    "sg:phone":"+1 212 491 7266",
    "sg:postcode":"10037",
    "sg:province":"NY",
    "sg:tags":[
        "apparel",
        "footwear"
    ],
    "wof:name":"Ace Footwear Inc",
    "wof:placetype":"venue"
},
  "geometry": {"coordinates":[-73.940831,40.813994],"type":"Point"}
}