{
  "type": "Feature",
  "properties": {
    "addr:full":"5351 Onondaga Rd Camillus NY 13031",
    "addr:housenumber":"5351",
    "addr:postcode":"13031",
    "addr:street":"Onondaga Rd",
    "iso:country":"US",
    "sg:address":"5351 Onondaga Rd",
    "sg:city":"Camillus",
    "sg:classifiers":[
        {
            "category":"Building & Trades",
            "subcategory":"Construction",
            "type":"Services"
        }
    ],
    "sg:phone":"+1 315 468 0862",
    "sg:postcode":"13031",
    "sg:province":"NY",
    "sg:tags":[
        "hanging",
        "contractor"
    ],
    "wof:name":"Murco Painting",
    "wof:placetype":"venue"
},
  "geometry": {"coordinates":[-76.22759000000001,43.030392],"type":"Point"}
}