{
  "type": "Feature",
  "properties": {
    "iso:country":"US",
    "sg:address":"206 Rogers Ave",
    "sg:city":"Endicott",
    "sg:classifiers":[
        {
            "category":"Organizations",
            "subcategory":"Religious Organization",
            "type":"Services"
        }
    ],
    "sg:phone":"+1 607 748 8005",
    "sg:postcode":"13760",
    "sg:province":"NY",
    "sg:tags":[
        "church"
    ],
    "wof:name":"Christian Apostolic Church",
    "wof:placetype":"venue"
},
  "geometry": {"coordinates":[-76.046041,42.112815],"type":"Point"}
}