{
  "type": "Feature",
  "properties": {
    "iso:country":"US",
    "sg:address":"5920 8th Avenue",
    "sg:city":"Brooklyn",
    "sg:classifiers":[
        {
            "category":"Building & Trades",
            "subcategory":"Construction",
            "type":"Services"
        }
    ],
    "sg:phone":"+1 718 256 1167",
    "sg:postcode":"11220",
    "sg:province":"NY",
    "sg:tags":[
        "contractor"
    ],
    "wof:name":"Aura Waterproofing Corporation",
    "wof:placetype":"venue"
},
  "geometry": {"coordinates":[-74.009518,40.635674],"type":"Point"}
}