{
  "type": "Feature",
  "properties": {
    "iso:country":"US",
    "sg:address":"952 State Hwy 420",
    "sg:city":"Brasher Falls",
    "sg:classifiers":[
        {
            "category":"Building & Trades",
            "subcategory":"Construction",
            "type":"Services"
        }
    ],
    "sg:phone":"+1 315 764 1697",
    "sg:postcode":"13613",
    "sg:province":"NY",
    "sg:tags":[
        "residential"
    ],
    "wof:name":"O W Construction",
    "wof:placetype":"venue"
},
  "geometry": {"coordinates":[-74.81036400000001,44.814077],"type":"Point"}
}