{
  "type": "Feature",
  "properties": {
    "addr:full":"305 Foch Blvd Mineola NY 11501",
    "addr:housenumber":"305",
    "addr:postcode":"11501",
    "addr:street":"Foch Blvd",
    "iso:country":"US",
    "sg:address":"305 Foch Blvd",
    "sg:city":"Mineola",
    "sg:classifiers":[
        {
            "category":"Professional",
            "subcategory":"Research",
            "type":"Services"
        }
    ],
    "sg:phone":"+1   ",
    "sg:postcode":"11501",
    "sg:province":"NY",
    "sg:tags":[
        "commercial",
        "physical"
    ],
    "wof:name":"National Inst For Humn Growth",
    "wof:placetype":"venue"
},
  "geometry": {"coordinates":[-73.651055,40.747239],"type":"Point"}
}