{
  "type": "Feature",
  "properties": {
    "addr:full":"3155 Mccorkindale Rd Caledonia NY 14423",
    "addr:housenumber":"3155",
    "addr:postcode":"14423",
    "addr:street":"Mccorkindale Rd",
    "iso:country":"US",
    "sg:address":"3155 Mccorkindale Rd",
    "sg:city":"Caledonia",
    "sg:classifiers":[
        {
            "category":"Professional",
            "subcategory":"Printing & Photocopies",
            "type":"Services"
        }
    ],
    "sg:phone":"+1 585 538 2024",
    "sg:postcode":"14423",
    "sg:province":"NY",
    "sg:tags":[
        "lithographer"
    ],
    "wof:name":"Printing Terzo",
    "wof:placetype":"venue"
},
  "geometry": {"coordinates":[-77.853759,42.930321],"type":"Point"}
}