{
  "type": "Feature",
  "properties": {
    "addr:full":"31 W 11th St Apt 6D New York NY 10011",
    "addr:housenumber":"31",
    "addr:postcode":"10011",
    "addr:street":"W 11Th St Apt 6D",
    "iso:country":"US",
    "sg:address":"31 W 11th St Apt 6D",
    "sg:city":"New York",
    "sg:classifiers":[
        {
            "category":"Health Services",
            "subcategory":"Doctor",
            "type":"Services"
        },
        {
            "category":"Health Services",
            "subcategory":"Clinic",
            "type":"Services"
        }
    ],
    "sg:phone":"+1 212 633 8157",
    "sg:postcode":"10011",
    "sg:province":"NY",
    "sg:tags":[
        "counseling",
        "mental"
    ],
    "wof:name":"Tatarsky Andrew PHD",
    "wof:placetype":"venue"
},
  "geometry": {"coordinates":[-73.996002,40.734501],"type":"Point"}
}