{
  "type": "Feature",
  "properties": {
    "iso:country":"US",
    "sg:address":"866 United Nations Plz",
    "sg:city":"New York",
    "sg:classifiers":[
        {
            "category":"Professional",
            "subcategory":"Accounting & Tax Preparation",
            "type":"Services"
        }
    ],
    "sg:phone":"+1 212 752 6983",
    "sg:postcode":"10017",
    "sg:province":"NY",
    "sg:tags":[
        "return",
        "filing"
    ],
    "sg:website":"www.silvermanstaxadvice.com",
    "wof:name":"David J Silverman & Co",
    "wof:placetype":"venue"
},
  "geometry": {"coordinates":[-73.966677,40.752935],"type":"Point"}
}