{
  "type": "Feature",
  "properties": {
    "addr:full":"825 Pirates Cove Mamaroneck NY 10543",
    "addr:housenumber":"825",
    "addr:postcode":"10543",
    "addr:street":"Pirates Cove",
    "iso:country":"US",
    "sg:address":"825 Pirates Cove",
    "sg:city":"Mamaroneck",
    "sg:classifiers":[
        {
            "category":"Professional",
            "subcategory":"Management & Consulting",
            "type":"Services"
        }
    ],
    "sg:phone":"+1 914 777 3990",
    "sg:postcode":"10543",
    "sg:province":"NY",
    "sg:tags":[
        "marketing",
        "consultant"
    ],
    "sg:website":"www.marketingmattersltd.com",
    "wof:name":"Marketing Matters LTD",
    "wof:placetype":"venue"
},
  "geometry": {"coordinates":[-73.730363,40.931273],"type":"Point"}
}