{
  "type": "Feature",
  "properties": {
    "iso:country":"US",
    "sg:address":"1132 State Route 23",
    "sg:city":"Catskill",
    "sg:classifiers":[
        {
            "category":"Wholesale",
            "subcategory":"Computers",
            "type":"Manufacturing & Wholesale Goods"
        }
    ],
    "sg:phone":"+1 518 828 0300",
    "sg:postcode":"12414",
    "sg:province":"NY",
    "wof:name":"Surfer's Cybercafe",
    "wof:placetype":"venue"
},
  "geometry": {"coordinates":[-73.861,42.2267],"type":"Point"}
}