{
  "type": "Feature",
  "properties": {
    "iso:country":"US",
    "sg:address":"220 Greengrove Ave",
    "sg:city":"Uniondale",
    "sg:classifiers":[
        {
            "category":"Building & Trades",
            "subcategory":"Plumbing",
            "type":"Services"
        }
    ],
    "sg:phone":"+1 516 486 2973",
    "sg:postcode":"11553",
    "sg:province":"NY",
    "sg:tags":[
        "contractor"
    ],
    "wof:name":"JB Refrigeration Inc",
    "wof:placetype":"venue"
},
  "geometry": {"coordinates":[-73.595551,40.709658],"type":"Point"}
}