{
  "type": "Feature",
  "properties": {
    "iso:country":"US",
    "sg:address":"2026 Western Ave",
    "sg:city":"Albany",
    "sg:classifiers":[
        {
            "category":"Restaurant",
            "type":"Food & Drink"
        }
    ],
    "sg:menulink":"http://www.allmenus.com/ny/guilderland/61356-mezza-notte-ristorante/menu/",
    "sg:phone":"+1 518 689 4433",
    "sg:postcode":"12203",
    "sg:province":"NY",
    "sg:tags":[
        "american"
    ],
    "wof:name":"Mezza Notte Ristorante",
    "wof:placetype":"venue"
},
  "geometry": {"coordinates":[-73.886342,42.696722],"type":"Point"}
}