{
  "type": "Feature",
  "properties": {
    "addr:full":"9506 243rd St Floral Park NY 11001",
    "addr:housenumber":"9506",
    "addr:postcode":"11001",
    "addr:street":"243Rd St",
    "iso:country":"US",
    "sg:address":"9506 243rd St",
    "sg:city":"Floral Park",
    "sg:classifiers":[
        {
            "category":"Freight",
            "type":"Transportation"
        }
    ],
    "sg:phone":"+1   ",
    "sg:postcode":"11001",
    "sg:province":"NY",
    "sg:tags":[
        "operator",
        "local",
        "trucking"
    ],
    "wof:name":"Russo Lettieri Trckg",
    "wof:placetype":"venue"
},
  "geometry": {"coordinates":[-73.723834,40.721256],"type":"Point"}
}