{
  "type": "Feature",
  "properties": {
    "addr:full":"2319 65th St Brooklyn NY 11204",
    "addr:housenumber":"2319",
    "addr:postcode":"11204",
    "addr:street":"65Th St",
    "iso:country":"US",
    "sg:address":"2319 65th St",
    "sg:city":"Brooklyn",
    "sg:classifiers":[
        {
            "category":"Personal",
            "subcategory":"Beauty Salon",
            "type":"Services"
        }
    ],
    "sg:phone":"+1 718 376 1865",
    "sg:postcode":"11204",
    "sg:province":"NY",
    "wof:name":"F B Hair Metrix",
    "wof:placetype":"venue"
},
  "geometry": {"coordinates":[-73.978844,40.612442],"type":"Point"}
}