{
  "type": "Feature",
  "properties": {
    "addr:full":"23107 Linden Blvd Queens NY 11411",
    "addr:housenumber":"23107",
    "addr:postcode":"11411",
    "addr:street":"Linden Blvd",
    "iso:country":"US",
    "sg:address":"23107 Linden Blvd",
    "sg:city":"Queens",
    "sg:classifiers":[
        {
            "category":"Building & Trades",
            "subcategory":"Plumbing",
            "type":"Services"
        },
        {
            "category":"Building & Trades",
            "subcategory":"Construction",
            "type":"Services"
        }
    ],
    "sg:phone":"+1 718 749 0449",
    "sg:postcode":"11411",
    "sg:province":"NY",
    "sg:tags":[
        "air",
        "heating",
        "conditioning/hvac"
    ],
    "sg:website":"williamsplumbingheatingandcoolin...",
    "wof:name":"Williams Plumbing Heating and Cooling",
    "wof:placetype":"venue"
},
  "geometry": {"coordinates":[-73.73031,40.691896],"type":"Point"}
}