{
  "type": "Feature",
  "properties": {
    "addr:full":"3500 Winton Pl Rochester NY 14623",
    "addr:housenumber":"3500",
    "addr:postcode":"14623",
    "addr:street":"Winton Pl",
    "iso:country":"US",
    "sg:address":"3500 Winton Pl",
    "sg:city":"Rochester",
    "sg:classifiers":[
        {
            "category":"Utilities",
            "subcategory":"Mobile Phone",
            "type":"Services"
        }
    ],
    "sg:phone":"+1 585 350 2000",
    "sg:postcode":"14623",
    "sg:province":"NY",
    "sg:tags":[
        "paging",
        "telephone",
        "cellular"
    ],
    "sg:website":"www.nextelpartners.com",
    "wof:name":"Nextel",
    "wof:placetype":"venue"
},
  "geometry": {"coordinates":[-77.57713099999999,43.09616],"type":"Point"}
}