{
  "type": "Feature",
  "properties": {
    "addr:full":"442 Center St Lewiston NY 14092",
    "addr:housenumber":"442",
    "addr:postcode":"14092",
    "addr:street":"Center St",
    "iso:country":"US",
    "sg:address":"442 Center St",
    "sg:city":"Lewiston",
    "sg:classifiers":[
        {
            "category":"Manufacturing",
            "subcategory":"Printing",
            "type":"Manufacturing & Wholesale Goods"
        }
    ],
    "sg:phone":"+1   ",
    "sg:postcode":"14092",
    "sg:province":"NY",
    "sg:tags":[
        "book"
    ],
    "wof:name":"Edwin Mellen Press Inc",
    "wof:placetype":"venue"
},
  "geometry": {"coordinates":[-79.043713,43.172973],"type":"Point"}
}