{
  "type": "Feature",
  "properties": {
    "addr:full":"6815 Route 9 Rhinebeck NY 12572",
    "addr:housenumber":"6815",
    "addr:postcode":"12572",
    "addr:street":"Route 9",
    "iso:country":"US",
    "sg:address":"6815 Route 9",
    "sg:city":"Rhinebeck",
    "sg:classifiers":[
        {
            "category":"Food & Beverages",
            "subcategory":"Liquor & Beverages",
            "type":"Retail Goods"
        }
    ],
    "sg:phone":"+1 845 876 8444",
    "sg:postcode":"12572",
    "sg:province":"NY",
    "sg:tags":[
        "store"
    ],
    "wof:name":"Astor Square Wine & Liquor",
    "wof:placetype":"venue"
},
  "geometry": {"coordinates":[-73.897277,41.95291],"type":"Point"}
}