{
  "type": "Feature",
  "properties": {
    "iso:country":"US",
    "sg:address":"14 Oaks Hunt Rd",
    "sg:city":"Great Neck",
    "sg:classifiers":[
        {
            "category":"Professional",
            "type":"Services"
        }
    ],
    "sg:phone":"+1   ",
    "sg:postcode":"11020",
    "sg:province":"NY",
    "wof:name":"Anne Hellman",
    "wof:placetype":"venue"
},
  "geometry": {"coordinates":[-73.727057,40.77135],"type":"Point"}
}