{
  "type": "Feature",
  "properties": {
    "iso:country":"US",
    "sg:address":"535 W 22 St",
    "sg:city":"New York",
    "sg:classifiers":[
        {
            "category":"Wholesale",
            "subcategory":"Durable Goods & Equipment",
            "type":"Manufacturing & Wholesale Goods"
        }
    ],
    "sg:phone":"+1 212 337 0680",
    "sg:postcode":"10011",
    "sg:province":"NY",
    "sg:tags":[
        "video",
        "art"
    ],
    "wof:name":"Eai",
    "wof:placetype":"venue"
},
  "geometry": {"coordinates":[-74.007075,40.74808],"type":"Point"}
}