{
  "type": "Feature",
  "properties": {
    "addr:full":"91 Willow Ave Bronx NY 10454",
    "addr:housenumber":"91",
    "addr:postcode":"10454",
    "addr:street":"Willow Ave",
    "iso:country":"US",
    "sg:address":"91 Willow Ave",
    "sg:city":"Bronx",
    "sg:classifiers":[
        {
            "category":"Retail",
            "subcategory":"Auto Repair",
            "type":"Services"
        }
    ],
    "sg:phone":"+1 718 328 7247",
    "sg:postcode":"10454",
    "sg:province":"NY",
    "sg:tags":[
        "carburetor"
    ],
    "wof:name":"Metric Carburetor Co Inc",
    "wof:placetype":"venue"
},
  "geometry": {"coordinates":[-73.913955,40.800706],"type":"Point"}
}