{
  "type": "Feature",
  "properties": {
    "iso:country":"US",
    "sg:address":"5431 S Abbott Rd",
    "sg:city":"Orchard Park",
    "sg:classifiers":[
        {
            "category":"Health Services",
            "subcategory":"Medical Lab",
            "type":"Services"
        }
    ],
    "sg:phone":"+1 716 648 1010",
    "sg:postcode":"14127",
    "sg:province":"NY",
    "sg:tags":[
        "laboratory"
    ],
    "wof:name":"Len-Tec Dental Inc",
    "wof:placetype":"venue"
},
  "geometry": {"coordinates":[-78.7976,42.738924],"type":"Point"}
}