{
  "type": "Feature",
  "properties": {
    "iso:country":"US",
    "sg:address":"137 W 2nd St",
    "sg:city":"Oswego",
    "sg:classifiers":[
        {
            "category":"Food & Beverages",
            "subcategory":"Groceries & Convenience Stores",
            "type":"Retail Goods"
        }
    ],
    "sg:phone":"+1 315 342 7748",
    "sg:postcode":"13126",
    "sg:province":"NY",
    "sg:tags":[
        "product"
    ],
    "wof:name":"Lola's Asian Food",
    "wof:placetype":"venue"
},
  "geometry": {"coordinates":[-76.512078,43.455937],"type":"Point"}
}