{
  "type": "Feature",
  "properties": {
    "addr:full":"25 Corporate Cir Albany NY 12203",
    "addr:housenumber":"25",
    "addr:postcode":"12203",
    "addr:street":"Corporate Cir",
    "iso:country":"US",
    "sg:address":"25 Corporate Cir",
    "sg:city":"Albany",
    "sg:classifiers":[
        {
            "category":"Building & Trades",
            "subcategory":"Plumbing",
            "type":"Services"
        }
    ],
    "sg:phone":"+1 518 452 0065",
    "sg:postcode":"12203",
    "sg:province":"NY",
    "sg:tags":[
        "control",
        "air",
        "pollution"
    ],
    "wof:name":"Rupprecht & Patashnick",
    "wof:placetype":"venue"
},
  "geometry": {"coordinates":[-73.878249,42.701979],"type":"Point"}
}