{
  "type": "Feature",
  "properties": {
    "iso:country":"US",
    "sg:address":"28 Creek Ridge",
    "sg:city":"Pittsford",
    "sg:classifiers":[
        {
            "category":"Professional",
            "subcategory":"Management & Consulting",
            "type":"Services"
        }
    ],
    "sg:phone":"+1 585 387 9379",
    "sg:postcode":"14534",
    "sg:province":"NY",
    "sg:tags":[
        "business"
    ],
    "wof:name":"Pictor International Group USA",
    "wof:placetype":"venue"
},
  "geometry": {"coordinates":[-77.503514,43.090143],"type":"Point"}
}