{
  "type": "Feature",
  "properties": {
    "addr:full":"1495 Hoe Ave Bronx NY 10460",
    "addr:housenumber":"1495",
    "addr:postcode":"10460",
    "addr:street":"Hoe Ave",
    "iso:country":"US",
    "sg:address":"1495 Hoe Ave",
    "sg:city":"Bronx",
    "sg:classifiers":[
        {
            "category":"Organizations",
            "subcategory":"Religious Organization",
            "type":"Services"
        }
    ],
    "sg:phone":"+1 347 702 6640",
    "sg:postcode":"10460",
    "sg:province":"NY",
    "wof:name":"Divine Union Grove",
    "wof:placetype":"venue"
},
  "geometry": {"coordinates":[-73.88935499999999,40.833127],"type":"Point"}
}