{
  "type": "Feature",
  "properties": {
    "addr:full":"43 W 33 St New York NY 10001",
    "addr:housenumber":"43",
    "addr:postcode":"10001",
    "addr:street":"W 33 St",
    "iso:country":"US",
    "sg:address":"43 W 33 St",
    "sg:city":"New York",
    "sg:classifiers":[
        {
            "category":"Wholesale",
            "subcategory":"Durable Goods & Equipment",
            "type":"Manufacturing & Wholesale Goods"
        }
    ],
    "sg:phone":"+1 212 268 7933",
    "sg:postcode":"10001",
    "sg:province":"NY",
    "sg:tags":[
        "importer"
    ],
    "wof:name":"Jomar Fashions",
    "wof:placetype":"venue"
},
  "geometry": {"coordinates":[-73.985046,40.747772],"type":"Point"}
}