{
  "type": "Feature",
  "properties": {
    "addr:full":"777 3rd Ave New York NY 10017",
    "addr:housenumber":"777",
    "addr:postcode":"10017",
    "addr:street":"3Rd Ave",
    "iso:country":"US",
    "sg:address":"777 3rd Ave",
    "sg:city":"New York",
    "sg:classifiers":[
        {
            "category":"Professional",
            "subcategory":"Lawyer & Legal Services",
            "type":"Services"
        }
    ],
    "sg:phone":"+1 212 230 1616",
    "sg:postcode":"10017",
    "sg:province":"NY",
    "wof:name":"Moriwaki Gary S Atty",
    "wof:placetype":"venue"
},
  "geometry": {"coordinates":[-73.971497,40.754601],"type":"Point"}
}