{
  "type": "Feature",
  "properties": {
    "addr:full":"1157 42nd St Brooklyn NY 11219",
    "addr:housenumber":"1157",
    "addr:postcode":"11219",
    "addr:street":"42Nd St",
    "iso:country":"US",
    "sg:address":"1157 42nd St",
    "sg:city":"Brooklyn",
    "sg:classifiers":[
        {
            "category":"Manufacturing",
            "subcategory":"Chemicals & Compounds",
            "type":"Manufacturing & Wholesale Goods"
        }
    ],
    "sg:phone":"+1 718 633 1030",
    "sg:postcode":"11219",
    "sg:province":"NY",
    "sg:tags":[
        "plastic"
    ],
    "wof:name":"Advance Chemical USA",
    "wof:placetype":"venue"
},
  "geometry": {"coordinates":[-73.991237,40.641163],"type":"Point"}
}