{
  "type": "Feature",
  "properties": {
    "iso:country":"US",
    "sg:address":"503 Brookwood Dr",
    "sg:city":"Farmington",
    "sg:classifiers":[
        {
            "category":"Building & Trades",
            "subcategory":"Construction",
            "type":"Services"
        }
    ],
    "sg:phone":"+1 585 424 5545",
    "sg:postcode":"14425",
    "sg:province":"NY",
    "sg:tags":[
        "dry wall",
        "contractor"
    ],
    "wof:name":"Advanced Eifs & Custom Drywall",
    "wof:placetype":"venue"
},
  "geometry": {"coordinates":[-77.36994900000001,42.989738],"type":"Point"}
}