{
  "type": "Feature",
  "properties": {
    "addr:full":"155 W 68th Street New York NY 10023",
    "addr:housenumber":"155",
    "addr:postcode":"10023",
    "addr:street":"W 68Th Street",
    "iso:country":"US",
    "sg:address":"155 W 68th Street",
    "sg:city":"New York",
    "sg:classifiers":[
        {
            "category":"Retail",
            "subcategory":"Laundry & Dry Cleaning",
            "type":"Services"
        }
    ],
    "sg:phone":"+1 212 787 0031",
    "sg:postcode":"10023",
    "sg:province":"NY",
    "wof:name":"Dorchester Cleaners Corporation",
    "wof:placetype":"venue"
},
  "geometry": {"coordinates":[-73.982674,40.775708],"type":"Point"}
}