{
  "type": "Feature",
  "properties": {
    "addr:full":"555 Madison Avenue New York NY 10022",
    "addr:housenumber":"555",
    "addr:postcode":"10022",
    "addr:street":"Madison Avenue",
    "iso:country":"US",
    "sg:address":"555 Madison Avenue",
    "sg:city":"New York",
    "sg:classifiers":[
        {
            "category":"Restaurant",
            "type":"Food & Drink"
        }
    ],
    "sg:phone":"+1 212 759 8364",
    "sg:postcode":"10022",
    "sg:province":"NY",
    "wof:name":"Carrols Corporation",
    "wof:placetype":"venue"
},
  "geometry": {"coordinates":[-73.973202,40.761126],"type":"Point"}
}