{
  "type": "Feature",
  "properties": {
    "iso:country":"US",
    "sg:address":"2 Chase Rd",
    "sg:city":"Wallkill",
    "sg:classifiers":[
        {
            "category":"Autos & Motor Vehicles",
            "subcategory":"Automobile Sales",
            "type":"Retail Goods"
        }
    ],
    "sg:phone":"+1   ",
    "sg:postcode":"12589",
    "sg:province":"NY",
    "sg:tags":[
        "new",
        "used"
    ],
    "wof:name":"Wallkill Ford",
    "wof:placetype":"venue"
},
  "geometry": {"coordinates":[-74.170272,41.607564],"type":"Point"}
}