{
  "type": "Feature",
  "properties": {
    "iso:country":"US",
    "sg:address":"2890 Delaware Ave",
    "sg:city":"Buffalo",
    "sg:classifiers":[
        {
            "category":"Shopping",
            "subcategory":"Discount & Variety Stores",
            "type":"Retail Goods"
        }
    ],
    "sg:phone":"+1 716 447 4305",
    "sg:postcode":"14217",
    "sg:province":"NY",
    "wof:name":"Dollar General",
    "wof:placetype":"venue"
},
  "geometry": {"coordinates":[-78.870197,42.963474],"type":"Point"}
}