{
  "type": "Feature",
  "properties": {
    "addr:full":"847 Flatbush Ave Brooklyn NY 11226",
    "addr:housenumber":"847",
    "addr:postcode":"11226",
    "addr:street":"Flatbush Ave",
    "iso:country":"US",
    "sg:address":"847 Flatbush Ave",
    "sg:city":"Brooklyn",
    "sg:classifiers":[
        {
            "category":"Education",
            "subcategory":"Special Training",
            "type":"Public Place"
        }
    ],
    "sg:phone":"+1 718 564 1168",
    "sg:postcode":"11226",
    "sg:province":"NY",
    "sg:tags":[
        "tutoring"
    ],
    "wof:name":"Score! Educational Ctr",
    "wof:placetype":"venue"
},
  "geometry": {"coordinates":[-73.95893700000001,40.651692],"type":"Point"}
}