{
  "type": "Feature",
  "properties": {
    "addr:full":"503 Fair Oak St Little Valley NY 14755",
    "addr:housenumber":"503",
    "addr:postcode":"14755",
    "addr:street":"Fair Oak St",
    "iso:country":"US",
    "sg:address":"503 Fair Oak St",
    "sg:city":"Little Valley",
    "sg:classifiers":[
        {
            "category":"Government",
            "subcategory":"Office",
            "type":"Public Place"
        }
    ],
    "sg:phone":"+1 716 938 9111",
    "sg:postcode":"14755",
    "sg:province":"NY",
    "sg:tags":[
        "county",
        "program"
    ],
    "wof:name":"Cattaraugus Cnty Environmental",
    "wof:placetype":"venue"
},
  "geometry": {"coordinates":[-78.807445,42.24906],"type":"Point"}
}