{
  "type": "Feature",
  "properties": {
    "iso:country":"US",
    "sg:address":"445 Park Ave",
    "sg:city":"New York",
    "sg:classifiers":[
        {
            "category":"Real Estate",
            "subcategory":"Real Estate Agent",
            "type":"Services"
        }
    ],
    "sg:phone":"+1 212 838 4509",
    "sg:postcode":"10022",
    "sg:province":"NY",
    "sg:website":"www.gardnercmc.com",
    "wof:name":"Gardner Capital Corp",
    "wof:placetype":"venue"
},
  "geometry": {"coordinates":[-73.970809,40.761349],"type":"Point"}
}