{
  "type": "Feature",
  "properties": {
    "addr:full":"5507 Nesconset Hwy Ste 10 Mount Sinai NY 11766",
    "addr:housenumber":"10",
    "addr:postcode":"5507;11766",
    "addr:street":"Nesconset Hwy Ste",
    "iso:country":"US",
    "sg:address":"5507 Nesconset Hwy Ste 10",
    "sg:city":"Mount Sinai",
    "sg:classifiers":[
        {
            "category":"Personal",
            "subcategory":"Tanning Parlor",
            "type":"Services"
        }
    ],
    "sg:phone":"+1 631 476 9300",
    "sg:postcode":"11766",
    "sg:province":"NY",
    "wof:name":"Casa Del Sol",
    "wof:placetype":"venue"
},
  "geometry": {"coordinates":[-73.031171,40.932445],"type":"Point"}
}