{
  "type": "Feature",
  "properties": {
    "iso:country":"US",
    "sg:address":"8 Sloop Hill Rd",
    "sg:city":"New Windsor",
    "sg:classifiers":[
        {
            "category":"Wholesale",
            "subcategory":"Auto Parts",
            "type":"Manufacturing & Wholesale Goods"
        }
    ],
    "sg:phone":"+1 845 534 5944",
    "sg:postcode":"12553",
    "sg:province":"NY",
    "sg:tags":[
        "automobile"
    ],
    "wof:name":"Craig's Auto & Truck Svc",
    "wof:placetype":"venue"
},
  "geometry": {"coordinates":[-74.02503400000001,41.454978],"type":"Point"}
}