{
  "type": "Feature",
  "properties": {
    "addr:full":"8217 Northern Boulevard Jackson Heights NY 11372",
    "addr:housenumber":"8217",
    "addr:postcode":"11372",
    "addr:street":"Northern Boulevard",
    "iso:country":"US",
    "sg:address":"8217 Northern Boulevard",
    "sg:city":"Jackson Heights",
    "sg:classifiers":[
        {
            "category":"Building & Trades",
            "subcategory":"Locksmith",
            "type":"Services"
        }
    ],
    "sg:phone":"+1 718 476 3335",
    "sg:postcode":"11372",
    "sg:province":"NY",
    "sg:tags":[
        "key"
    ],
    "wof:name":"All Purpose Locksmith Company",
    "wof:placetype":"venue"
},
  "geometry": {"coordinates":[-73.884626,40.755749],"type":"Point"}
}