{
  "type": "Feature",
  "properties": {
    "addr:full":"15 Main St Chatham NY 12037",
    "addr:housenumber":"15",
    "addr:postcode":"12037",
    "addr:street":"Main St",
    "iso:country":"US",
    "sg:address":"15 Main St",
    "sg:city":"Chatham",
    "sg:classifiers":[
        {
            "category":"Food & Beverages",
            "subcategory":"Specialty",
            "type":"Retail Goods"
        }
    ],
    "sg:phone":"+1   ",
    "sg:postcode":"12037",
    "sg:province":"NY",
    "wof:name":"Grainery The",
    "wof:placetype":"venue"
},
  "geometry": {"coordinates":[-73.59515399999999,42.36348],"type":"Point"}
}