{
  "type": "Feature",
  "properties": {
    "addr:full":"310 W 138th St New York NY 10030",
    "addr:housenumber":"310",
    "addr:postcode":"10030",
    "addr:street":"W 138Th St",
    "iso:country":"US",
    "sg:address":"310 W 138th St",
    "sg:city":"New York",
    "sg:classifiers":[
        {
            "category":"Organizations",
            "subcategory":"Community Association",
            "type":"Services"
        }
    ],
    "sg:phone":"+1 917 507 4310",
    "sg:postcode":"10030",
    "sg:province":"NY",
    "sg:tags":[
        "sorority",
        "fraternity"
    ],
    "wof:name":"Alpha Kappa Alpha/Tau Omega",
    "wof:placetype":"venue"
},
  "geometry": {"coordinates":[-73.946378,40.81884],"type":"Point"}
}