{
  "type": "Feature",
  "properties": {
    "addr:full":"139 Alexander Ave Lake Grove NY 11755",
    "addr:housenumber":"139",
    "addr:postcode":"11755",
    "addr:street":"Alexander Ave",
    "iso:country":"US",
    "sg:address":"139 Alexander Ave",
    "sg:city":"Lake Grove",
    "sg:classifiers":[
        {
            "category":"Autos & Motor Vehicles",
            "subcategory":"Auto Supplies",
            "type":"Retail Goods"
        }
    ],
    "sg:phone":"+1 631 724 9170",
    "sg:postcode":"11755",
    "sg:province":"NY",
    "sg:tags":[
        "automobile",
        "stereo",
        "installation",
        "radio"
    ],
    "sg:website":"www.circuitcity.com",
    "wof:name":"Circuit City",
    "wof:placetype":"venue"
},
  "geometry": {"coordinates":[-73.134102,40.863602],"type":"Point"}
}