{
  "type": "Feature",
  "properties": {
    "iso:country":"US",
    "sg:address":"658 Christie St",
    "sg:city":"South Hempstead",
    "sg:classifiers":[
        {
            "category":"Professional",
            "subcategory":"Management & Consulting",
            "type":"Services"
        },
        {
            "category":"Professional",
            "subcategory":"Employment Agencies",
            "type":"Services"
        }
    ],
    "sg:phone":"+1 516 489 7201",
    "sg:postcode":"11550",
    "sg:province":"NY",
    "sg:tags":[
        "consultant",
        "personnel",
        "health",
        "care",
        "recruitment"
    ],
    "wof:name":"One Call Staffing Inc",
    "wof:placetype":"venue"
},
  "geometry": {"coordinates":[-73.61661100000001,40.682598],"type":"Point"}
}