{
  "type": "Feature",
  "properties": {
    "iso:country":"US",
    "sg:address":"23 Bond St",
    "sg:city":"Great Neck",
    "sg:classifiers":[
        {
            "category":"Health Services",
            "subcategory":"Doctor",
            "type":"Services"
        }
    ],
    "sg:phone":"+1 516 482 5416",
    "sg:postcode":"11021",
    "sg:province":"NY",
    "sg:tags":[
        "dentist"
    ],
    "wof:name":"North Shore Prosthodontics",
    "wof:placetype":"venue"
},
  "geometry": {"coordinates":[-73.728048,40.790572],"type":"Point"}
}