{
  "type": "Feature",
  "properties": {
    "addr:full":"3709 Erie Blvd E Syracuse NY 13214",
    "addr:housenumber":"3709",
    "addr:postcode":"13214",
    "addr:street":"Erie Blvd E",
    "iso:country":"US",
    "sg:address":"3709 Erie Blvd E",
    "sg:city":"Syracuse",
    "sg:classifiers":[
        {
            "category":"Restaurant",
            "type":"Food & Drink"
        }
    ],
    "sg:phone":"+1   ",
    "sg:postcode":"13214",
    "sg:province":"NY",
    "sg:tags":[
        "eating"
    ],
    "wof:name":"Ponderosa Steakhouse",
    "wof:placetype":"venue"
},
  "geometry": {"coordinates":[-76.06558699999999,43.034796],"type":"Point"}
}