{
  "type": "Feature",
  "properties": {
    "addr:full":"593 Avalon Gardens Dr Nanuet NY 10954",
    "addr:housenumber":"593",
    "addr:postcode":"10954",
    "addr:street":"Avalon Gardens Dr",
    "iso:country":"US",
    "sg:address":"593 Avalon Gardens Dr",
    "sg:city":"Nanuet",
    "sg:classifiers":[
        {
            "category":"Building & Trades",
            "subcategory":"Construction",
            "type":"Services"
        }
    ],
    "sg:phone":"+1 845 371 7009",
    "sg:postcode":"10954",
    "sg:province":"NY",
    "sg:tags":[
        "house"
    ],
    "wof:name":"H & S Home Improvements Inc",
    "wof:placetype":"venue"
},
  "geometry": {"coordinates":[-74.021754,41.10881],"type":"Point"}
}