{
  "type": "Feature",
  "properties": {
    "iso:country":"US",
    "sg:address":"46 Kirklees Rd",
    "sg:city":"Pittsford",
    "sg:classifiers":[
        {
            "category":"Wholesale",
            "subcategory":"Durable Goods & Equipment",
            "type":"Manufacturing & Wholesale Goods"
        }
    ],
    "sg:phone":"+1 585 586 2275",
    "sg:postcode":"14534",
    "sg:province":"NY",
    "sg:tags":[
        "representative",
        "manufacturer"
    ],
    "wof:name":"Schyler & Assoc",
    "wof:placetype":"venue"
},
  "geometry": {"coordinates":[-77.49849500000001,43.098994],"type":"Point"}
}