{
  "type": "Feature",
  "properties": {
    "iso:country":"US",
    "sg:address":"142 Mineola Ave",
    "sg:city":"Roslyn Heights",
    "sg:classifiers":[
        {
            "category":"Arts & Performance",
            "subcategory":"Art Gallery",
            "type":"Entertainment"
        }
    ],
    "sg:phone":"+1 516 625 5609",
    "sg:postcode":"11577",
    "sg:province":"NY",
    "wof:name":"Tintern Art Glass",
    "wof:placetype":"venue"
},
  "geometry": {"coordinates":[-73.65051099999999,40.787788],"type":"Point"}
}