{
  "type": "Feature",
  "properties": {
    "addr:full":"28 Richmond St Rochester NY 14607",
    "addr:housenumber":"28",
    "addr:postcode":"14607",
    "addr:street":"Richmond St",
    "iso:country":"US",
    "sg:address":"28 Richmond St",
    "sg:city":"Rochester",
    "sg:classifiers":[
        {
            "category":"Real Estate",
            "subcategory":"Real Estate Agent",
            "type":"Services"
        }
    ],
    "sg:phone":"+1 585 325 5359",
    "sg:postcode":"14607",
    "sg:province":"NY",
    "wof:name":"Industrial Appraisal Co",
    "wof:placetype":"venue"
},
  "geometry": {"coordinates":[-77.596649,43.158638],"type":"Point"}
}