{
  "type": "Feature",
  "properties": {
    "addr:full":"1 W Fordham Rd Bronx NY 10468",
    "addr:housenumber":"1",
    "addr:postcode":"10468",
    "addr:street":"W Fordham Rd",
    "iso:country":"US",
    "sg:address":"1 W Fordham Rd",
    "sg:city":"Bronx",
    "sg:classifiers":[
        {
            "category":"Restaurant",
            "type":"Food & Drink"
        }
    ],
    "sg:menulink":"http://www.allmenus.com/ny/bronx/210419-kfc---kentucky-fried-chicken/menu/",
    "sg:phone":"+1 718 563 2046",
    "sg:postcode":"10468",
    "sg:province":"NY",
    "sg:tags":[
        "american",
        "chicken"
    ],
    "wof:name":"KFC - Kentucky Fried Chicken",
    "wof:placetype":"venue"
},
  "geometry": {"coordinates":[-73.901139,40.862792],"type":"Point"}
}