{
  "type": "Feature",
  "properties": {
    "addr:full":"1037 Johnston Ave Wantagh NY 11793",
    "addr:housenumber":"1037",
    "addr:postcode":"11793",
    "addr:street":"Johnston Ave",
    "iso:country":"US",
    "sg:address":"1037 Johnston Ave",
    "sg:city":"Wantagh",
    "sg:classifiers":[
        {
            "category":"Organizations",
            "subcategory":"Community Association",
            "type":"Services"
        }
    ],
    "sg:phone":"+1   ",
    "sg:postcode":"11793",
    "sg:province":"NY",
    "wof:name":"Nasaw Suffolk District Council",
    "wof:placetype":"venue"
},
  "geometry": {"coordinates":[-73.525437,40.695645],"type":"Point"}
}