{
  "type": "Feature",
  "properties": {
    "addr:full":"4982 Commercial Dr Yorkville NY 13495",
    "addr:housenumber":"4982",
    "addr:postcode":"13495",
    "addr:street":"Commercial Dr",
    "iso:country":"US",
    "sg:address":"4982 Commercial Dr",
    "sg:city":"Yorkville",
    "sg:classifiers":[
        {
            "category":"Restaurant",
            "type":"Food & Drink"
        }
    ],
    "sg:phone":"+1 315 736 4141",
    "sg:postcode":"13495",
    "sg:province":"NY",
    "sg:tags":[
        "barbecue",
        "american"
    ],
    "wof:name":"Kirby's American Restaurant",
    "wof:placetype":"venue"
},
  "geometry": {"coordinates":[-75.297256,43.10487],"type":"Point"}
}