{
  "type": "Feature",
  "properties": {
    "addr:full":"15 Stuyvesant Ln East Setauket NY 11733",
    "addr:housenumber":"15",
    "addr:postcode":"11733",
    "addr:street":"Stuyvesant Ln East",
    "iso:country":"US",
    "sg:address":"15 Stuyvesant Ln",
    "sg:city":"East Setauket",
    "sg:classifiers":[
        {
            "category":"Building & Trades",
            "subcategory":"Plumbing",
            "type":"Services"
        }
    ],
    "sg:phone":"+1 631 689 5563",
    "sg:postcode":"11733",
    "sg:province":"NY",
    "sg:tags":[
        "plumbing",
        "heating",
        "contractor"
    ],
    "wof:name":"Stony Brook Plumbing & Heating",
    "wof:placetype":"venue"
},
  "geometry": {"coordinates":[-73.097278,40.891062],"type":"Point"}
}