{
  "type": "Feature",
  "properties": {
    "addr:full":"131 Orchard Street Manhattan NY 10002",
    "addr:housenumber":"131",
    "addr:postcode":"10002",
    "addr:street":"Orchard Street",
    "iso:country":"US",
    "sg:address":"131 Orchard Street",
    "sg:city":"Manhattan",
    "sg:classifiers":[
        {
            "category":"Shopping",
            "subcategory":"Luggage & Leather Goods",
            "type":"Retail Goods"
        }
    ],
    "sg:phone":"+1 212 254 3079",
    "sg:postcode":"10002",
    "sg:province":"NY",
    "wof:name":"International Luggage",
    "wof:placetype":"venue"
},
  "geometry": {"coordinates":[-73.98965,40.719761],"type":"Point"}
}