{
  "type": "Feature",
  "properties": {
    "addr:full":"189 Montague St Brooklyn NY 11201",
    "addr:housenumber":"189",
    "addr:postcode":"11201",
    "addr:street":"Montague St",
    "iso:country":"US",
    "sg:address":"189 Montague St",
    "sg:city":"Brooklyn",
    "sg:classifiers":[
        {
            "category":"Real Estate",
            "subcategory":"Real Estate Agent",
            "type":"Services"
        }
    ],
    "sg:phone":"+1 718 625 5194",
    "sg:postcode":"11201",
    "sg:province":"NY",
    "sg:tags":[
        "business"
    ],
    "wof:name":"Nationwide Court Services Inc",
    "wof:placetype":"venue"
},
  "geometry": {"coordinates":[-73.99089499999999,40.693976],"type":"Point"}
}