{
  "type": "Feature",
  "properties": {
    "iso:country":"US",
    "sg:address":"423 W 203rd St",
    "sg:city":"New York",
    "sg:classifiers":[
        {
            "category":"Wholesale",
            "subcategory":"Metals & Minerals",
            "type":"Manufacturing & Wholesale Goods"
        }
    ],
    "sg:phone":"+1 212 942 8400",
    "sg:postcode":"10034",
    "sg:province":"NY",
    "sg:tags":[
        "merchandise",
        "spanish"
    ],
    "wof:name":"Productos Mexicanos Veer-Mex",
    "wof:placetype":"venue"
},
  "geometry": {"coordinates":[-73.920423,40.861823],"type":"Point"}
}