{
  "type": "Feature",
  "properties": {
    "iso:country":"US",
    "sg:address":"18 Grove St",
    "sg:city":"Middletown",
    "sg:classifiers":[
        {
            "category":"Professional",
            "subcategory":"Lawyer & Legal Services",
            "type":"Services"
        }
    ],
    "sg:phone":"+1 845 342 0024",
    "sg:postcode":"10940",
    "sg:province":"NY",
    "sg:tags":[
        "attorney"
    ],
    "wof:name":"Jacquelynn Vance-Pauls Law Ofc",
    "wof:placetype":"venue"
},
  "geometry": {"coordinates":[-74.415359,41.449578],"type":"Point"}
}