{
  "type": "Feature",
  "properties": {
    "iso:country":"US",
    "sg:address":"36 Arden Ave",
    "sg:city":"Buffalo",
    "sg:classifiers":[
        {
            "category":"Social Services",
            "subcategory":"Child Care",
            "type":"Services"
        }
    ],
    "sg:phone":"+1 716 893 2396",
    "sg:postcode":"14215",
    "sg:province":"NY",
    "sg:tags":[
        "day"
    ],
    "wof:name":"Budding Roses Community Childcare",
    "wof:placetype":"venue"
},
  "geometry": {"coordinates":[-78.81237400000001,42.926065],"type":"Point"}
}