{
  "type": "Feature",
  "properties": {
    "addr:full":"1616 Waterford Rd Walworth NY 14568",
    "addr:housenumber":"1616",
    "addr:postcode":"14568",
    "addr:street":"Waterford Rd",
    "iso:country":"US",
    "sg:address":"1616 Waterford Rd",
    "sg:city":"Walworth",
    "sg:classifiers":[
        {
            "category":"Retail",
            "subcategory":"Auto Repair",
            "type":"Services"
        }
    ],
    "sg:phone":"+1 315 986 8008",
    "sg:postcode":"14568",
    "sg:province":"NY",
    "sg:tags":[
        "transmission"
    ],
    "wof:name":"Transtar Industries",
    "wof:placetype":"venue"
},
  "geometry": {"coordinates":[-77.299102,43.124547],"type":"Point"}
}