{
  "type": "Feature",
  "properties": {
    "addr:full":"155 S Main St Cattaraugus NY 14719",
    "addr:housenumber":"155",
    "addr:postcode":"14719",
    "addr:street":"S Main St",
    "iso:country":"US",
    "sg:address":"155 S Main St",
    "sg:city":"Cattaraugus",
    "sg:classifiers":[
        {
            "category":"Building & Trades",
            "subcategory":"Construction",
            "type":"Services"
        },
        {
            "category":"Retail",
            "subcategory":"Auto Repair",
            "type":"Services"
        }
    ],
    "sg:phone":"+1 716 257 9650",
    "sg:postcode":"14719",
    "sg:province":"NY",
    "sg:tags":[
        "body",
        "automobile",
        "contractor",
        "painting",
        "hanging"
    ],
    "wof:name":"Dale's Custom Painting",
    "wof:placetype":"venue"
},
  "geometry": {"coordinates":[-78.868647,42.323064],"type":"Point"}
}