{
  "type": "Feature",
  "properties": {
    "addr:full":"180 Helme Ave Miller Place NY 11764",
    "addr:housenumber":"180",
    "addr:postcode":"11764",
    "addr:street":"Helme Ave",
    "iso:country":"US",
    "sg:address":"180 Helme Ave",
    "sg:city":"Miller Place",
    "sg:classifiers":[
        {
            "category":"Building & Trades",
            "subcategory":"Construction",
            "type":"Services"
        }
    ],
    "sg:phone":"+1 631 473 6459",
    "sg:postcode":"11764",
    "sg:province":"NY",
    "sg:tags":[
        "repairing",
        "house",
        "remodeling",
        "contractor"
    ],
    "wof:name":"Golden Bear Home Repair Inc",
    "wof:placetype":"venue"
},
  "geometry": {"coordinates":[-72.985407,40.919775],"type":"Point"}
}