{
  "type": "Feature",
  "properties": {
    "addr:full":"737 Main St New Rochelle NY 10801",
    "addr:housenumber":"737",
    "addr:postcode":"10801",
    "addr:street":"Main St",
    "iso:country":"US",
    "sg:address":"737 Main St",
    "sg:city":"New Rochelle",
    "sg:classifiers":[
        {
            "category":"Building & Trades",
            "subcategory":"Pest Control",
            "type":"Services"
        }
    ],
    "sg:phone":"+1 914 632 5374",
    "sg:postcode":"10801",
    "sg:province":"NY",
    "sg:tags":[
        "exterminating"
    ],
    "wof:name":"Formily R & K Exterminators",
    "wof:placetype":"venue"
},
  "geometry": {"coordinates":[-73.789165,40.903429],"type":"Point"}
}