{
  "type": "Feature",
  "properties": {
    "iso:country":"US",
    "sg:address":"446 Bay St",
    "sg:city":"Rochester",
    "sg:classifiers":[
        {
            "category":"Retail",
            "subcategory":"Auto Repair",
            "type":"Services"
        }
    ],
    "sg:phone":"+1 585 288 2099",
    "sg:postcode":"14609",
    "sg:province":"NY",
    "sg:tags":[
        "repairing",
        "automobile"
    ],
    "wof:name":"Sid & Johnny's Garage",
    "wof:placetype":"venue"
},
  "geometry": {"coordinates":[-77.58151700000001,43.171045],"type":"Point"}
}