{
  "type": "Feature",
  "properties": {
    "addr:full":"66 Gilbert Street Northport NY 11768",
    "addr:housenumber":"66",
    "addr:postcode":"11768",
    "addr:street":"Gilbert Street",
    "iso:country":"US",
    "sg:address":"66 Gilbert Street",
    "sg:city":"Northport",
    "sg:classifiers":[
        {
            "category":"Real Estate",
            "subcategory":"Real Estate Services",
            "type":"Services"
        }
    ],
    "sg:phone":"+1 631 757 9000",
    "sg:postcode":"11768",
    "sg:province":"NY",
    "sg:website":"www.coachrealtors.com/",
    "wof:name":"Coach Realtors",
    "wof:placetype":"venue"
},
  "geometry": {"coordinates":[-73.334756,40.896884],"type":"Point"}
}