{
  "type": "Feature",
  "properties": {
    "addr:full":"158 Sullivan St New York NY 10012",
    "addr:housenumber":"158",
    "addr:postcode":"10012",
    "addr:street":"Sullivan St",
    "iso:country":"US",
    "sg:address":"158 Sullivan St",
    "sg:city":"New York",
    "sg:classifiers":[
        {
            "category":"Food & Beverages",
            "subcategory":"Meat & Fish",
            "type":"Retail Goods"
        }
    ],
    "sg:phone":"+1 212 777 5250",
    "sg:postcode":"10012",
    "sg:province":"NY",
    "sg:tags":[
        "seafood"
    ],
    "wof:name":"Fresh Catch Seafood Market",
    "wof:placetype":"venue"
},
  "geometry": {"coordinates":[-74.00209599999999,40.726673],"type":"Point"}
}