{
  "type": "Feature",
  "properties": {
    "addr:full":"2300 Main St E Rochester NY 14609",
    "addr:housenumber":"2300",
    "addr:postcode":"14609",
    "addr:street":"Main St E",
    "iso:country":"US",
    "sg:address":"2300 Main St E",
    "sg:city":"Rochester",
    "sg:classifiers":[
        {
            "category":"Food & Beverages",
            "subcategory":"Liquor & Beverages",
            "type":"Retail Goods"
        }
    ],
    "sg:phone":"+1 585 482 6024",
    "sg:postcode":"14609",
    "sg:province":"NY",
    "sg:tags":[
        "alcoholic"
    ],
    "wof:name":"Euphoria Liquor Inc",
    "wof:placetype":"venue"
},
  "geometry": {"coordinates":[-77.549836,43.159598],"type":"Point"}
}