{
  "type": "Feature",
  "properties": {
    "iso:country":"US",
    "sg:address":"701 Atlantic Ave",
    "sg:city":"Rochester",
    "sg:classifiers":[
        {
            "category":"Retail",
            "subcategory":"Auto Repair",
            "type":"Services"
        }
    ],
    "sg:phone":"+1 585 482 5573",
    "sg:postcode":"14609",
    "sg:province":"NY",
    "sg:tags":[
        "shop",
        "automobile",
        "part",
        "supply",
        "automotive"
    ],
    "sg:website":"http://jeromes.mechanicnet.com",
    "wof:name":"Jerome's Ignition Service",
    "wof:placetype":"venue"
},
  "geometry": {"coordinates":[-77.565753,43.15648],"type":"Point"}
}