{
  "type": "Feature",
  "properties": {
    "addr:full":"7301 Hinman Hollow Rd Little Valley NY 14755",
    "addr:housenumber":"7301",
    "addr:postcode":"14755",
    "addr:street":"Hinman Hollow Rd",
    "iso:country":"US",
    "sg:address":"7301 Hinman Hollow Rd",
    "sg:city":"Little Valley",
    "sg:classifiers":[
        {
            "category":"Farming",
            "subcategory":"Dairy Farm",
            "type":"Manufacturing & Wholesale Goods"
        }
    ],
    "sg:phone":"+1 716 699 5362",
    "sg:postcode":"14755",
    "sg:province":"NY",
    "wof:name":"Telaak Farms",
    "wof:placetype":"venue"
},
  "geometry": {"coordinates":[-78.72143800000001,42.330791],"type":"Point"}
}