{
  "type": "Feature",
  "properties": {
    "iso:country":"US",
    "sg:address":"455 Madison Ave New York Palace",
    "sg:city":"New York",
    "sg:classifiers":[
        {
            "category":"Restaurant",
            "type":"Food & Drink"
        }
    ],
    "sg:phone":"+1 212 303 6032",
    "sg:postcode":"10022",
    "sg:province":"NY",
    "sg:tags":[
        "traditional",
        "new",
        "american"
    ],
    "sg:website":"www.newyorkpalace.com/dining/ist...",
    "wof:name":"Istana Restaurant & Bar",
    "wof:placetype":"venue"
},
  "geometry": {"coordinates":[-73.975177,40.758361],"type":"Point"}
}