{
  "type": "Feature",
  "properties": {
    "iso:country":"US",
    "sg:address":"45 8th Ave",
    "sg:city":"New York",
    "sg:classifiers":[
        {
            "category":"Restaurant",
            "type":"Food & Drink"
        }
    ],
    "sg:menulink":"http://www.allmenus.com/ny/new-york/141111-snice/menu/",
    "sg:phone":"+1 212 645 0310",
    "sg:postcode":"10014",
    "sg:province":"NY",
    "sg:tags":[
        "italian"
    ],
    "wof:name":"'snice",
    "wof:placetype":"venue"
},
  "geometry": {"coordinates":[-74.00409399999999,40.738449],"type":"Point"}
}