{
  "type": "Feature",
  "properties": {
    "iso:country":"US",
    "sg:address":"2184 Jerome Ave",
    "sg:city":"Bronx",
    "sg:classifiers":[
        {
            "category":"Home & Garden",
            "subcategory":"Building Materials",
            "type":"Retail Goods"
        }
    ],
    "sg:phone":"+1 718 295 1520",
    "sg:postcode":"10453",
    "sg:province":"NY",
    "sg:tags":[
        "glass",
        "window",
        "plate"
    ],
    "sg:website":"www.bartelstone.com",
    "wof:name":"Bartelstone Glass Distributors",
    "wof:placetype":"venue"
},
  "geometry": {"coordinates":[-73.905044,40.856328],"type":"Point"}
}