{
  "type": "Feature",
  "properties": {
    "addr:full":"700 White Plains Rd Scarsdale NY 10583",
    "addr:housenumber":"700",
    "addr:postcode":"10583",
    "addr:street":"White Plains Rd",
    "iso:country":"US",
    "sg:address":"700 White Plains Rd",
    "sg:city":"Scarsdale",
    "sg:classifiers":[
        {
            "category":"Health Services",
            "subcategory":"Podiatrist",
            "type":"Services"
        }
    ],
    "sg:phone":"+1 914 472 3030",
    "sg:postcode":"10583",
    "sg:province":"NY",
    "wof:name":"Scaggs Clifton G",
    "wof:placetype":"venue"
},
  "geometry": {"coordinates":[-73.80483099999999,40.972014],"type":"Point"}
}