{
  "type": "Feature",
  "properties": {
    "addr:full":"1031 King St Chappaqua NY 10514",
    "addr:housenumber":"1031",
    "addr:postcode":"10514",
    "addr:street":"King St",
    "iso:country":"US",
    "sg:address":"1031 King St",
    "sg:city":"Chappaqua",
    "sg:classifiers":[
        {
            "category":"Real Estate",
            "subcategory":"Architect",
            "type":"Services"
        }
    ],
    "sg:phone":"+1 914 773 1618",
    "sg:postcode":"10514",
    "sg:province":"NY",
    "sg:tags":[
        "architects'",
        "specification",
        "construction",
        "builders'",
        "architectural"
    ],
    "wof:name":"Gabrielle Salman Architect Pc",
    "wof:placetype":"venue"
},
  "geometry": {"coordinates":[-73.748628,41.132693],"type":"Point"}
}