{
  "type": "Feature",
  "properties": {
    "addr:full":"76 Degraw St Brooklyn NY 11231",
    "addr:housenumber":"76",
    "addr:postcode":"11231",
    "addr:street":"Degraw St",
    "iso:country":"US",
    "sg:address":"76 Degraw St",
    "sg:city":"Brooklyn",
    "sg:classifiers":[
        {
            "category":"Building & Trades",
            "subcategory":"Electrical",
            "type":"Services"
        }
    ],
    "sg:phone":"+1 718 624 2255",
    "sg:postcode":"11231",
    "sg:province":"NY",
    "sg:tags":[
        "electrical",
        "contractor"
    ],
    "wof:name":"Fritzmartin Electric Inc",
    "wof:placetype":"venue"
},
  "geometry": {"coordinates":[-74.00286,40.685829],"type":"Point"}
}