{
  "type": "Feature",
  "properties": {
    "addr:full":"445 Cedarwood Ter Rochester NY 14609",
    "addr:housenumber":"445",
    "addr:postcode":"14609",
    "addr:street":"Cedarwood Ter",
    "iso:country":"US",
    "sg:address":"445 Cedarwood Ter",
    "sg:city":"Rochester",
    "sg:classifiers":[
        {
            "category":"Travel",
            "subcategory":"Travel Agent",
            "type":"Entertainment"
        }
    ],
    "sg:phone":"+1   ",
    "sg:postcode":"14609",
    "sg:province":"NY",
    "sg:tags":[
        "agency"
    ],
    "wof:name":"Traveling Bag Lady",
    "wof:placetype":"venue"
},
  "geometry": {"coordinates":[-77.561348,43.162415],"type":"Point"}
}