{
  "type": "Feature",
  "properties": {
    "iso:country":"US",
    "sg:address":"4228 Peterboro St",
    "sg:city":"Vernon",
    "sg:classifiers":[
        {
            "category":"Wholesale",
            "subcategory":"Machinery & Supplies",
            "type":"Manufacturing & Wholesale Goods"
        }
    ],
    "sg:phone":"+1 315 829 3505",
    "sg:postcode":"13476",
    "sg:province":"NY",
    "sg:tags":[
        "equipment",
        "dairy"
    ],
    "wof:name":"Eastern Crown Inc",
    "wof:placetype":"venue"
},
  "geometry": {"coordinates":[-75.54766499999999,43.067691],"type":"Point"}
}