{
  "type": "Feature",
  "properties": {
    "iso:country":"US",
    "sg:address":"231 W 231st St",
    "sg:city":"Bronx",
    "sg:classifiers":[
        {
            "category":"Shopping",
            "subcategory":"Beauty & Cosmetics",
            "type":"Retail Goods"
        },
        {
            "category":"Personal",
            "subcategory":"Beauty Salon",
            "type":"Services"
        }
    ],
    "sg:phone":"+1 718 884 7015",
    "sg:postcode":"10463",
    "sg:province":"NY",
    "sg:tags":[
        "studio",
        "make",
        "health",
        "aids"
    ],
    "wof:name":"Saveway Discount Corp",
    "wof:placetype":"venue"
},
  "geometry": {"coordinates":[-73.906575,40.879808],"type":"Point"}
}