{
  "type": "Feature",
  "properties": {
    "addr:full":"2022 Ave M Brooklyn NY 11210",
    "addr:postcode":"11210",
    "addr:street":"2022 Ave M",
    "iso:country":"US",
    "sg:address":"2022 Ave M",
    "sg:city":"Brooklyn",
    "sg:classifiers":[
        {
            "category":"Organizations",
            "subcategory":"Religious Organization",
            "type":"Services"
        }
    ],
    "sg:phone":"+1 718 252 3843",
    "sg:postcode":"11210",
    "sg:province":"NY",
    "sg:tags":[
        "clergy"
    ],
    "wof:name":"Karl Sodden",
    "wof:placetype":"venue"
},
  "geometry": {"coordinates":[-73.954168,40.618572],"type":"Point"}
}