{
  "type": "Feature",
  "properties": {
    "iso:country":"US",
    "sg:address":"461 N Main St",
    "sg:city":"Warsaw",
    "sg:classifiers":[
        {
            "category":"Restaurant",
            "type":"Food & Drink"
        }
    ],
    "sg:phone":"+1 585 786 5828",
    "sg:postcode":"14569",
    "sg:province":"NY",
    "sg:tags":[
        "eating"
    ],
    "wof:name":"Ho Ho China Buffet",
    "wof:placetype":"venue"
},
  "geometry": {"coordinates":[-78.131175,42.757801],"type":"Point"}
}