{
  "type": "Feature",
  "properties": {
    "addr:full":"160 Middle Rd Riverhead NY 11901",
    "addr:housenumber":"160",
    "addr:postcode":"11901",
    "addr:street":"Middle Rd",
    "iso:country":"US",
    "sg:address":"160 Middle Rd",
    "sg:city":"Riverhead",
    "sg:classifiers":[
        {
            "category":"Social Services",
            "subcategory":"Adult Care",
            "type":"Services"
        }
    ],
    "sg:phone":"+1 631 727 4774",
    "sg:postcode":"11901",
    "sg:province":"NY",
    "sg:tags":[
        "residential"
    ],
    "wof:name":"Aid To The Dvlpmntlly Disabled",
    "wof:placetype":"venue"
},
  "geometry": {"coordinates":[-72.655483,40.939417],"type":"Point"}
}