{
  "type": "Feature",
  "properties": {
    "iso:country":"US",
    "sg:address":"143 Mohawk Ave",
    "sg:city":"Scotia",
    "sg:classifiers":[
        {
            "category":"Personal",
            "type":"Services"
        },
        {
            "category":"Personal",
            "subcategory":"Tattoo Parlor",
            "type":"Services"
        }
    ],
    "sg:phone":"+1 518 377 7317",
    "sg:postcode":"12302",
    "sg:province":"NY",
    "sg:tags":[
        "tattooing"
    ],
    "wof:name":"All Star Body Art",
    "wof:placetype":"venue"
},
  "geometry": {"coordinates":[-73.963521,42.825926],"type":"Point"}
}