{
  "type": "Feature",
  "properties": {
    "addr:full":"151 Orchard St Manhattan NY 10002",
    "addr:housenumber":"151",
    "addr:postcode":"10002",
    "addr:street":"Orchard St",
    "iso:country":"US",
    "sg:address":"151 Orchard St",
    "sg:city":"Manhattan",
    "sg:classifiers":[
        {
            "category":"Shopping",
            "subcategory":"Clothing, Apparel, & Fashions",
            "type":"Retail Goods"
        }
    ],
    "sg:postcode":"10002",
    "sg:province":"NY",
    "sg:tags":[
        "men's",
        "clothing"
    ],
    "sg:website":"www.epauletshop.com/servlet/Stor...",
    "wof:name":"Epaulet Shop",
    "wof:placetype":"venue"
},
  "geometry": {"coordinates":[-73.988966,40.720703],"type":"Point"}
}