{
  "type": "Feature",
  "properties": {
    "iso:country":"US",
    "sg:address":"1 Arlington Ave",
    "sg:city":"Malverne",
    "sg:classifiers":[
        {
            "category":"Wholesale",
            "subcategory":"Medical Equipment & Supplies",
            "type":"Manufacturing & Wholesale Goods"
        }
    ],
    "sg:phone":"+1 516 564 6720",
    "sg:postcode":"11565",
    "sg:province":"NY",
    "sg:tags":[
        "hospital",
        "supplies-wholesale",
        "manufacturer"
    ],
    "wof:name":"Lyn N Medical Pc",
    "wof:placetype":"venue"
},
  "geometry": {"coordinates":[-73.66738100000001,40.677952],"type":"Point"}
}