{
  "type": "Feature",
  "properties": {
    "iso:country":"US",
    "sg:address":"1137 Coney Island Ave",
    "sg:city":"Brooklyn",
    "sg:classifiers":[
        {
            "category":"Shopping",
            "type":"Retail Goods"
        }
    ],
    "sg:phone":"+1   ",
    "sg:postcode":"11230",
    "sg:province":"NY",
    "sg:tags":[
        "electronics"
    ],
    "wof:name":"Mega Sonic",
    "wof:placetype":"venue"
},
  "geometry": {"coordinates":[-73.966391,40.631596],"type":"Point"}
}