{
  "type": "Feature",
  "properties": {
    "iso:country":"US",
    "sg:address":"97 Glen Cove Ave",
    "sg:city":"Glen Cove",
    "sg:classifiers":[
        {
            "category":"Autos & Motor Vehicles",
            "subcategory":"Auto Supplies",
            "type":"Retail Goods"
        }
    ],
    "sg:phone":"+1   ",
    "sg:postcode":"11542",
    "sg:province":"NY",
    "wof:name":"Tire Works",
    "wof:placetype":"venue"
},
  "geometry": {"coordinates":[-73.635228,40.85716],"type":"Point"}
}