{
  "type": "Feature",
  "properties": {
    "addr:full":"39 Union St Westfield NY 14787",
    "addr:housenumber":"39",
    "addr:postcode":"14787",
    "addr:street":"Union St",
    "iso:country":"US",
    "sg:address":"39 Union St",
    "sg:city":"Westfield",
    "sg:classifiers":[
        {
            "category":"Building & Trades",
            "subcategory":"Construction",
            "type":"Services"
        }
    ],
    "sg:phone":"+1 716 326 2434",
    "sg:postcode":"14787",
    "sg:province":"NY",
    "sg:tags":[
        "house"
    ],
    "wof:name":"Jackson Builders",
    "wof:placetype":"venue"
},
  "geometry": {"coordinates":[-79.574147,42.321132],"type":"Point"}
}