{
  "type": "Feature",
  "properties": {
    "addr:full":"5001 14th Ave Brooklyn NY 11219",
    "addr:housenumber":"5001",
    "addr:postcode":"11219",
    "addr:street":"14Th Ave",
    "iso:country":"US",
    "sg:address":"5001 14th Ave",
    "sg:city":"Brooklyn",
    "sg:classifiers":[
        {
            "category":"Organizations",
            "subcategory":"Religious Organization",
            "type":"Services"
        }
    ],
    "sg:phone":"+1 718 851 0858",
    "sg:postcode":"11219",
    "sg:province":"NY",
    "sg:tags":[
        "clergy"
    ],
    "wof:name":"Abraham Shkop",
    "wof:placetype":"venue"
},
  "geometry": {"coordinates":[-73.99108099999999,40.632574],"type":"Point"}
}