{
  "type": "Feature",
  "properties": {
    "addr:full":"210 W Main St Waterloo NY 13165",
    "addr:housenumber":"210",
    "addr:postcode":"13165",
    "addr:street":"W Main St",
    "iso:country":"US",
    "sg:address":"210 W Main St",
    "sg:city":"Waterloo",
    "sg:classifiers":[
        {
            "category":"Organizations",
            "subcategory":"Non-profit Organization",
            "type":"Services"
        }
    ],
    "sg:phone":"+1 315 539 5647",
    "sg:postcode":"13165",
    "sg:province":"NY",
    "sg:tags":[
        "social"
    ],
    "wof:name":"Cayuga Sneca Cmnty Action Agcy",
    "wof:placetype":"venue"
},
  "geometry": {"coordinates":[-76.867456,42.904336],"type":"Point"}
}