{
  "type": "Feature",
  "properties": {
    "iso:country":"US",
    "sg:address":"20 Exchange Pl",
    "sg:city":"New York",
    "sg:classifiers":[
        {
            "category":"Professional",
            "subcategory":"Lawyer & Legal Services",
            "type":"Services"
        }
    ],
    "sg:phone":"+1 212 309 1000",
    "sg:postcode":"10005",
    "sg:province":"NY",
    "wof:name":"Sheehen Francis Atty",
    "wof:placetype":"venue"
},
  "geometry": {"coordinates":[-74.009102,40.705399],"type":"Point"}
}