{
  "type": "Feature",
  "properties": {
    "addr:full":"13127 31st Ave Flushing NY 11354",
    "addr:housenumber":"13127",
    "addr:postcode":"11354",
    "addr:street":"31St Ave",
    "iso:country":"US",
    "sg:address":"13127 31st Ave",
    "sg:city":"Flushing",
    "sg:classifiers":[
        {
            "category":"Manufacturing",
            "subcategory":"Tools & Machinery",
            "type":"Manufacturing & Wholesale Goods"
        }
    ],
    "sg:phone":"+1 800 823 3016",
    "sg:postcode":"11354",
    "sg:province":"NY",
    "sg:tags":[
        "hand"
    ],
    "wof:name":"Milwaukee Electric Tool Corp Toll Free-Dial '1' & Then",
    "wof:placetype":"venue"
},
  "geometry": {"coordinates":[-73.84174299999999,40.769344],"type":"Point"}
}