{
  "type": "Feature",
  "properties": {
    "addr:full":"7 E 54th St New York NY 10022",
    "addr:housenumber":"7",
    "addr:postcode":"10022",
    "addr:street":"E 54Th St",
    "iso:country":"US",
    "sg:address":"7 E 54th St",
    "sg:city":"New York",
    "sg:classifiers":[
        {
            "category":"Restaurant",
            "type":"Food & Drink"
        }
    ],
    "sg:menulink":"http://www.allmenus.com/ny/new-york/22395-bice-ristorante/menu/",
    "sg:phone":"+1 212 688 1999",
    "sg:postcode":"10022",
    "sg:province":"NY",
    "sg:tags":[
        "italian"
    ],
    "wof:name":"Bice Ristorante",
    "wof:placetype":"venue"
},
  "geometry": {"coordinates":[-73.97446100000001,40.760655],"type":"Point"}
}