{
  "type": "Feature",
  "properties": {
    "addr:full":"157 E Broadway New York NY 10002",
    "addr:housenumber":"157",
    "addr:postcode":"10002",
    "addr:street":"E Broadway",
    "iso:country":"US",
    "sg:address":"157 E Broadway",
    "sg:city":"New York",
    "sg:classifiers":[
        {
            "category":"Education",
            "subcategory":"Special Training",
            "type":"Public Place"
        }
    ],
    "sg:phone":"+1 212 406 7989",
    "sg:postcode":"10002",
    "sg:province":"NY",
    "sg:tags":[
        "tutoring"
    ],
    "sg:website":"www.scorelearning.com",
    "wof:name":"Score Educational Centers",
    "wof:placetype":"venue"
},
  "geometry": {"coordinates":[-73.990403,40.71414],"type":"Point"}
}