{
  "type": "Feature",
  "properties": {
    "iso:country":"US",
    "sg:address":"3549 Merrick Rd",
    "sg:city":"Seaford",
    "sg:classifiers":[
        {
            "category":"Restaurant",
            "type":"Food & Drink"
        }
    ],
    "sg:menulink":"http://www.allmenus.com/ny/seaford/114106-great-asian-kitchen/menu/",
    "sg:phone":"+1 516 781 6640",
    "sg:postcode":"11783",
    "sg:province":"NY",
    "sg:tags":[
        "asian",
        "chinese"
    ],
    "wof:name":"Great Asian Kitchen",
    "wof:placetype":"venue"
},
  "geometry": {"coordinates":[-73.499426,40.665162],"type":"Point"}
}