{
  "type": "Feature",
  "properties": {
    "iso:country":"US",
    "sg:address":"13 Folger St",
    "sg:city":"Buffalo",
    "sg:classifiers":[
        {
            "category":"Real Estate",
            "subcategory":"Architect",
            "type":"Services"
        }
    ],
    "sg:phone":"+1 716 646 6927",
    "sg:postcode":"14220",
    "sg:province":"NY",
    "wof:name":"James J Wittmann",
    "wof:placetype":"venue"
},
  "geometry": {"coordinates":[-78.827888,42.848132],"type":"Point"}
}