{
  "type": "Feature",
  "properties": {
    "addr:full":"4391 Walden Ave Lancaster NY 14086",
    "addr:housenumber":"4391",
    "addr:postcode":"14086",
    "addr:street":"Walden Ave",
    "iso:country":"US",
    "sg:address":"4391 Walden Ave",
    "sg:city":"Lancaster",
    "sg:classifiers":[
        {
            "category":"Professional",
            "subcategory":"Business Services",
            "type":"Services"
        }
    ],
    "sg:phone":"+1 716 681 3758",
    "sg:postcode":"14086",
    "sg:province":"NY",
    "sg:tags":[
        "water",
        "treatment"
    ],
    "wof:name":"MIS Of America Inc",
    "wof:placetype":"venue"
},
  "geometry": {"coordinates":[-78.619242,42.923879],"type":"Point"}
}