{
  "type": "Feature",
  "properties": {
    "addr:full":"2044 Latta Rd Rochester NY 14612",
    "addr:housenumber":"2044",
    "addr:postcode":"14612",
    "addr:street":"Latta Rd",
    "iso:country":"US",
    "sg:address":"2044 Latta Rd",
    "sg:city":"Rochester",
    "sg:classifiers":[
        {
            "category":"Food & Beverages",
            "subcategory":"Groceries & Convenience Stores",
            "type":"Retail Goods"
        },
        {
            "category":"Autos & Motor Vehicles",
            "subcategory":"Fuel & Gas Station",
            "type":"Retail Goods"
        }
    ],
    "sg:phone":"+1 585 663 5420",
    "sg:postcode":"14612",
    "sg:province":"NY",
    "sg:tags":[
        "station",
        "gasoline"
    ],
    "wof:name":"Quality Service Stations Inc",
    "wof:placetype":"venue"
},
  "geometry": {"coordinates":[-77.666432,43.252969],"type":"Point"}
}