{
  "type": "Feature",
  "properties": {
    "iso:country":"US",
    "sg:address":"1333 Roanoke Ave",
    "sg:city":"Riverhead",
    "sg:classifiers":[
        {
            "category":"Health Services",
            "subcategory":"Doctor",
            "type":"Services"
        }
    ],
    "sg:phone":"+1 631 727 2755",
    "sg:postcode":"11901",
    "sg:province":"NY",
    "wof:name":"Vandyne Martin J MD",
    "wof:placetype":"venue"
},
  "geometry": {"coordinates":[-72.674797,40.9342],"type":"Point"}
}