{
  "type": "Feature",
  "properties": {
    "iso:country":"US",
    "sg:address":"230 Ridge St",
    "sg:city":"Rome",
    "sg:classifiers":[
        {
            "category":"Restaurant",
            "type":"Food & Drink"
        }
    ],
    "sg:phone":"+1   ",
    "sg:postcode":"13440",
    "sg:province":"NY",
    "sg:tags":[
        "eating"
    ],
    "wof:name":"Tonys Side Track Diner",
    "wof:placetype":"venue"
},
  "geometry": {"coordinates":[-75.46394600000001,43.209548],"type":"Point"}
}