{
  "type": "Feature",
  "properties": {
    "addr:full":"2316 Amsterdam Ave New York NY 10033",
    "addr:housenumber":"2316",
    "addr:postcode":"10033",
    "addr:street":"Amsterdam Ave",
    "iso:country":"US",
    "sg:address":"2316 Amsterdam Ave",
    "sg:city":"New York",
    "sg:classifiers":[
        {
            "category":"Restaurant",
            "type":"Food & Drink"
        }
    ],
    "sg:phone":"+1 212 927 4190",
    "sg:postcode":"10033",
    "sg:province":"NY",
    "sg:tags":[
        "eating"
    ],
    "wof:name":"Marco Juan Restaurant Corp",
    "wof:placetype":"venue"
},
  "geometry": {"coordinates":[-73.933233,40.84491],"type":"Point"}
}