{
  "type": "Feature",
  "properties": {
    "iso:country":"US",
    "sg:address":"189 Broadway",
    "sg:city":"Whitehall",
    "sg:classifiers":[
        {
            "category":"Home & Garden",
            "subcategory":"Garden Supply",
            "type":"Retail Goods"
        },
        {
            "category":"Shopping",
            "subcategory":"Gifts & Souvenirs",
            "type":"Retail Goods"
        },
        {
            "category":"Shopping",
            "subcategory":"Crafts & Fabrics",
            "type":"Retail Goods"
        },
        {
            "category":"Shopping",
            "subcategory":"Florist",
            "type":"Retail Goods"
        }
    ],
    "sg:phone":"+1 518 499 0033",
    "sg:postcode":"12887",
    "sg:province":"NY",
    "sg:tags":[
        "plant",
        "etc-retail",
        "dried",
        "basket",
        "trees-silk",
        "flowers"
    ],
    "sg:website":"http://www.skenesboroughgardens.net",
    "wof:name":"Skenesborough Gardens",
    "wof:placetype":"venue"
},
  "geometry": {"coordinates":[-73.406052,43.547169],"type":"Point"}
}