{
  "type": "Feature",
  "properties": {
    "iso:country":"US",
    "sg:address":"22 W 22nd St",
    "sg:city":"New York",
    "sg:classifiers":[
        {
            "category":"Deli",
            "type":"Food & Drink"
        },
        {
            "category":"Food & Beverages",
            "subcategory":"Bakery",
            "type":"Retail Goods"
        }
    ],
    "sg:phone":"+1 212 633 6793",
    "sg:postcode":"10010",
    "sg:province":"NY",
    "sg:tags":[
        "sandwich"
    ],
    "wof:name":"Capital",
    "wof:placetype":"venue"
},
  "geometry": {"coordinates":[-73.990859,40.741048],"type":"Point"}
}