{
  "type": "Feature",
  "properties": {
    "iso:country":"US",
    "sg:address":"12 S Canal St P.O. Box 920",
    "sg:city":"Oxford",
    "sg:classifiers":[
        {
            "category":"Autos & Motor Vehicles",
            "subcategory":"Auto Supplies",
            "type":"Retail Goods"
        },
        {
            "category":"Manufacturing",
            "subcategory":"Motor Vehicles & Parts",
            "type":"Manufacturing & Wholesale Goods"
        },
        {
            "category":"Local Transit",
            "type":"Transportation"
        }
    ],
    "sg:phone":"+1 607 843 9885",
    "sg:postcode":"13830",
    "sg:province":"NY",
    "sg:tags":[
        "body",
        "trucks-wholesale",
        "snow",
        "removal",
        "equipment",
        "truck",
        "manufacturer"
    ],
    "sg:website":"http://www.chenangotruck.com",
    "wof:name":"Chenango Truck LLC",
    "wof:placetype":"venue"
},
  "geometry": {"coordinates":[-75.59863300000001,42.44101],"type":"Point"}
}