{
  "type": "Feature",
  "properties": {
    "iso:country":"US",
    "sg:address":"30 Wall St",
    "sg:city":"New York",
    "sg:classifiers":[
        {
            "category":"Communications",
            "subcategory":"Radio Station",
            "type":"Services"
        }
    ],
    "sg:phone":"+1   ",
    "sg:postcode":"10005",
    "sg:province":"NY",
    "sg:tags":[
        "educational"
    ],
    "wof:name":"The Parents Circle",
    "wof:placetype":"venue"
},
  "geometry": {"coordinates":[-74.00975099999999,40.706682],"type":"Point"}
}