{
  "type": "Feature",
  "properties": {
    "addr:full":"5936 Cooper Ave Ridgewood NY 11385",
    "addr:housenumber":"5936",
    "addr:postcode":"11385",
    "addr:street":"Cooper Ave",
    "iso:country":"US",
    "sg:address":"5936 Cooper Ave",
    "sg:city":"Ridgewood",
    "sg:classifiers":[
        {
            "category":"Retail",
            "subcategory":"Auto Repair",
            "type":"Services"
        }
    ],
    "sg:phone":"+1 718 386 2790",
    "sg:postcode":"11385",
    "sg:province":"NY",
    "wof:name":"M-Spec Performance Inc",
    "wof:placetype":"venue"
},
  "geometry": {"coordinates":[-73.895602,40.694803],"type":"Point"}
}