{
  "type": "Feature",
  "properties": {
    "iso:country":"US",
    "sg:address":"3584 US Hwy 9",
    "sg:city":"Highland",
    "sg:classifiers":[
        {
            "category":"Home & Garden",
            "subcategory":"Building Materials",
            "type":"Retail Goods"
        }
    ],
    "sg:phone":"+1 845 691 4527",
    "sg:postcode":"12528",
    "sg:province":"NY",
    "sg:tags":[
        "glass",
        "window",
        "plate"
    ],
    "wof:name":"Valley Glass",
    "wof:placetype":"venue"
},
  "geometry": {"coordinates":[-73.964022,41.712844],"type":"Point"}
}