{
  "type": "Feature",
  "properties": {
    "iso:country":"US",
    "sg:address":"6199 Lorena Rd",
    "sg:city":"Rome",
    "sg:classifiers":[
        {
            "category":"Real Estate",
            "subcategory":"Architect",
            "type":"Services"
        }
    ],
    "sg:phone":"+1   ",
    "sg:postcode":"13440",
    "sg:province":"NY",
    "sg:tags":[
        "architectural"
    ],
    "wof:name":"Donald A Engelbert Architect",
    "wof:placetype":"venue"
},
  "geometry": {"coordinates":[-75.483256,43.26781],"type":"Point"}
}