{
  "type": "Feature",
  "properties": {
    "iso:country":"US",
    "sg:address":"21 Airport Rd",
    "sg:city":"Schenectady",
    "sg:classifiers":[
        {
            "category":"Airline",
            "type":"Transportation"
        },
        {
            "category":"Government",
            "subcategory":"Office",
            "type":"Public Place"
        }
    ],
    "sg:phone":"+1 518 399 0111",
    "sg:postcode":"12302",
    "sg:province":"NY",
    "sg:tags":[
        "parish",
        "airport",
        "government-county"
    ],
    "wof:name":"SCH - Schenectady County Airport",
    "wof:placetype":"venue"
},
  "geometry": {"coordinates":[-73.940257,42.849252],"type":"Point"}
}