{
  "type": "Feature",
  "properties": {
    "addr:full":"345 E 9th St New York NY 10003",
    "addr:housenumber":"345",
    "addr:postcode":"10003",
    "addr:street":"E 9Th St",
    "iso:country":"US",
    "sg:address":"345 E 9th St",
    "sg:city":"New York",
    "sg:classifiers":[
        {
            "category":"Personal",
            "subcategory":"Skin Care",
            "type":"Services"
        }
    ],
    "sg:phone":"+1 212 673 2041",
    "sg:postcode":"10003",
    "sg:province":"NY",
    "sg:website":"www.moniquek.com",
    "wof:name":"Monique K",
    "wof:placetype":"venue"
},
  "geometry": {"coordinates":[-73.98617299999999,40.728731],"type":"Point"}
}