{
  "type": "Feature",
  "properties": {
    "iso:country":"US",
    "sg:address":"11828 US Hwy 11",
    "sg:city":"North Lawrence",
    "sg:classifiers":[
        {
            "category":"Shopping",
            "subcategory":"Discount & Variety Stores",
            "type":"Retail Goods"
        },
        {
            "category":"Food & Beverages",
            "subcategory":"Groceries & Convenience Stores",
            "type":"Retail Goods"
        }
    ],
    "sg:phone":"+1 315 389 4283",
    "sg:postcode":"12967",
    "sg:province":"NY",
    "sg:tags":[
        "merchandise",
        "general"
    ],
    "wof:name":"Martin's Country Store",
    "wof:placetype":"venue"
},
  "geometry": {"coordinates":[-74.626103,44.788835],"type":"Point"}
}