{
  "type": "Feature",
  "properties": {
    "addr:full":"134 E 17th Street New York NY 10003",
    "addr:housenumber":"134",
    "addr:postcode":"10003",
    "addr:street":"E 17Th Street",
    "iso:country":"US",
    "sg:address":"134 E 17th Street",
    "sg:city":"New York",
    "sg:classifiers":[
        {
            "category":"Personal",
            "type":"Services"
        },
        {
            "category":"Retail",
            "subcategory":"Laundry & Dry Cleaning",
            "type":"Services"
        }
    ],
    "sg:phone":"+1 212 529 5926",
    "sg:postcode":"10003",
    "sg:province":"NY",
    "sg:tags":[
        "sewing",
        "alteration"
    ],
    "wof:name":"New Cleaners & Tailors",
    "wof:placetype":"venue"
},
  "geometry": {"coordinates":[-73.990112,40.732365],"type":"Point"}
}