{
  "type": "Feature",
  "properties": {
    "iso:country":"US",
    "sg:address":"8970 Fleet Rd",
    "sg:city":"Hammondsport",
    "sg:classifiers":[
        {
            "category":"Real Estate",
            "subcategory":"Real Estate Agent",
            "type":"Services"
        }
    ],
    "sg:phone":"+1 607 569 2256",
    "sg:postcode":"14840",
    "sg:province":"NY",
    "wof:name":"West Kashmer Realtor",
    "wof:placetype":"venue"
},
  "geometry": {"coordinates":[-77.158708,42.413126],"type":"Point"}
}