{
  "type": "Feature",
  "properties": {
    "iso:country":"US",
    "sg:address":"2501 S Work St",
    "sg:city":"Falconer",
    "sg:classifiers":[
        {
            "category":"Food & Beverages",
            "subcategory":"Groceries & Convenience Stores",
            "type":"Retail Goods"
        }
    ],
    "sg:phone":"+1 716 484 2400",
    "sg:postcode":"14733",
    "sg:province":"NY",
    "wof:name":"General Store",
    "wof:placetype":"venue"
},
  "geometry": {"coordinates":[-79.17974100000001,42.109024],"type":"Point"}
}