{
  "type": "Feature",
  "properties": {
    "addr:full":"405 Washington Ave Albany NY 12206",
    "addr:housenumber":"405",
    "addr:postcode":"12206",
    "addr:street":"Washington Ave",
    "iso:country":"US",
    "sg:address":"405 Washington Ave",
    "sg:city":"Albany",
    "sg:classifiers":[
        {
            "category":"Building & Trades",
            "subcategory":"Construction",
            "type":"Services"
        }
    ],
    "sg:phone":"+1 518 426 4132",
    "sg:postcode":"12206",
    "sg:province":"NY",
    "sg:tags":[
        "contractor"
    ],
    "wof:name":"Bunkoff General Contracting",
    "wof:placetype":"venue"
},
  "geometry": {"coordinates":[-73.772682,42.662248],"type":"Point"}
}