{
  "type": "Feature",
  "properties": {
    "addr:full":"2135 Mill Ave Brooklyn NY 11234",
    "addr:housenumber":"2135",
    "addr:postcode":"11234",
    "addr:street":"Mill Ave",
    "iso:country":"US",
    "sg:address":"2135 Mill Ave",
    "sg:city":"Brooklyn",
    "sg:classifiers":[
        {
            "category":"Health Services",
            "subcategory":"Dentist",
            "type":"Services"
        }
    ],
    "sg:phone":"+1 718 531 7700",
    "sg:postcode":"11234",
    "sg:province":"NY",
    "wof:name":"Millbasin Cosmetic & Restorat Ive Denistry",
    "wof:placetype":"venue"
},
  "geometry": {"coordinates":[-73.913028,40.614956],"type":"Point"}
}