{
  "type": "Feature",
  "properties": {
    "addr:full":"88 Lexington Ave New York NY 10016",
    "addr:housenumber":"88",
    "addr:postcode":"10016",
    "addr:street":"Lexington Ave",
    "iso:country":"US",
    "sg:address":"88 Lexington Ave",
    "sg:city":"New York",
    "sg:classifiers":[
        {
            "category":"Professional",
            "subcategory":"Art Services",
            "type":"Services"
        }
    ],
    "sg:phone":"+1 212 779 3689",
    "sg:postcode":"10016",
    "sg:province":"NY",
    "sg:tags":[
        "graphic",
        "designer"
    ],
    "wof:name":"Lee Anders",
    "wof:placetype":"venue"
},
  "geometry": {"coordinates":[-73.98312900000001,40.741787],"type":"Point"}
}