{
  "type": "Feature",
  "properties": {
    "addr:full":"10 Campsite Way Warwick NY 10990",
    "addr:housenumber":"10",
    "addr:postcode":"10990",
    "addr:street":"Campsite Way",
    "iso:country":"US",
    "sg:address":"10 Campsite Way",
    "sg:city":"Warwick",
    "sg:classifiers":[
        {
            "category":"Health Services",
            "subcategory":"Dentist",
            "type":"Services"
        }
    ],
    "sg:phone":"+1 845 987 8689",
    "sg:postcode":"10990",
    "sg:province":"NY",
    "wof:name":"John P Castracane",
    "wof:placetype":"venue"
},
  "geometry": {"coordinates":[-74.34909,41.253723],"type":"Point"}
}