{
  "type": "Feature",
  "properties": {
    "iso:country":"US",
    "sg:address":"156 Remington Blvd",
    "sg:city":"Ronkonkoma",
    "sg:classifiers":[
        {
            "category":"Retail",
            "subcategory":"Auto Repair",
            "type":"Services"
        }
    ],
    "sg:phone":"+1   ",
    "sg:postcode":"11779",
    "sg:province":"NY",
    "sg:tags":[
        "automotive",
        "supply"
    ],
    "wof:name":"Schenker Auto Radiator Inc",
    "wof:placetype":"venue"
},
  "geometry": {"coordinates":[-73.13636099999999,40.791605],"type":"Point"}
}