{
  "type": "Feature",
  "properties": {
    "addr:full":"4 Harris Ave Albany NY 12208",
    "addr:housenumber":"4",
    "addr:postcode":"12208",
    "addr:street":"Harris Ave",
    "iso:country":"US",
    "sg:address":"4 Harris Ave",
    "sg:city":"Albany",
    "sg:classifiers":[
        {
            "category":"Shopping",
            "type":"Retail Goods"
        }
    ],
    "sg:phone":"+1   ",
    "sg:postcode":"12208",
    "sg:province":"NY",
    "sg:tags":[
        "medical"
    ],
    "wof:name":"Ken Maury Enterprises Ltd",
    "wof:placetype":"venue"
},
  "geometry": {"coordinates":[-73.790823,42.65094],"type":"Point"}
}