{
  "type": "Feature",
  "properties": {
    "addr:full":"1 West 58th St Floor 2 New York NY 10019",
    "addr:housenumber":"1",
    "addr:postcode":"10019",
    "addr:street":"West 58Th St",
    "iso:country":"US",
    "sg:address":"1 West 58th St Floor 2",
    "sg:city":"New York",
    "sg:classifiers":[
        {
            "category":"Personal",
            "subcategory":"Beauty Salon",
            "type":"Services"
        },
        {
            "category":"Personal",
            "subcategory":"Hair Removal",
            "type":"Services"
        },
        {
            "category":"Personal",
            "subcategory":"Nail Salon",
            "type":"Services"
        }
    ],
    "sg:phone":"+1 212 262 8899",
    "sg:postcode":"10019",
    "sg:province":"NY",
    "sg:website":"www.warrentricomi.com",
    "wof:name":"Warren Tricomi Salon",
    "wof:placetype":"venue"
},
  "geometry": {"coordinates":[-73.974729,40.764115],"type":"Point"}
}