{
  "type": "Feature",
  "properties": {
    "addr:full":"531 Faile St Bronx NY 10474",
    "addr:housenumber":"531",
    "addr:postcode":"10474",
    "addr:street":"Faile St",
    "iso:country":"US",
    "sg:address":"531 Faile St",
    "sg:city":"Bronx",
    "sg:classifiers":[
        {
            "category":"Retail",
            "subcategory":"Auto Repair",
            "type":"Services"
        }
    ],
    "sg:phone":"+1 718 542 6622",
    "sg:postcode":"10474",
    "sg:province":"NY",
    "sg:tags":[
        "truck"
    ],
    "wof:name":"Rodriguez Truck & Machinery",
    "wof:placetype":"venue"
},
  "geometry": {"coordinates":[-73.88584299999999,40.811623],"type":"Point"}
}