{
  "type": "Feature",
  "properties": {
    "addr:full":"2830 Union St Flushing NY 11354",
    "addr:housenumber":"2830",
    "addr:postcode":"11354",
    "addr:street":"Union St",
    "iso:country":"US",
    "sg:address":"2830 Union St",
    "sg:city":"Flushing",
    "sg:classifiers":[
        {
            "category":"Utilities",
            "subcategory":"Mobile Phone",
            "type":"Services"
        },
        {
            "category":"Shopping",
            "subcategory":"Mobile Phones",
            "type":"Retail Goods"
        },
        {
            "category":"Utilities",
            "subcategory":"Telephone",
            "type":"Services"
        },
        {
            "category":"Communications",
            "type":"Services"
        }
    ],
    "sg:phone":"+1 718 661 3323",
    "sg:postcode":"11354",
    "sg:province":"NY",
    "sg:tags":[
        "data",
        "cellular"
    ],
    "sg:website":"www.bellsouth.com",
    "wof:name":"Cingular Wireless",
    "wof:placetype":"venue"
},
  "geometry": {"coordinates":[-73.826611,40.771956],"type":"Point"}
}