{
  "type": "Feature",
  "properties": {
    "addr:full":"22 Remsen St Brooklyn NY 11201",
    "addr:housenumber":"22",
    "addr:postcode":"11201",
    "addr:street":"Remsen St",
    "iso:country":"US",
    "sg:address":"22 Remsen St",
    "sg:city":"Brooklyn",
    "sg:classifiers":[
        {
            "category":"Communications",
            "subcategory":"Radio Station",
            "type":"Services"
        }
    ],
    "sg:phone":"+1 718 522 0368",
    "sg:postcode":"11201",
    "sg:province":"NY",
    "wof:name":"Radio France",
    "wof:placetype":"venue"
},
  "geometry": {"coordinates":[-73.997741,40.694861],"type":"Point"}
}