{
  "type": "Feature",
  "properties": {
    "addr:full":"700 Old Country Rd Plainview NY 11803",
    "addr:housenumber":"700",
    "addr:postcode":"11803",
    "addr:street":"Old Country Rd",
    "iso:country":"US",
    "sg:address":"700 Old Country Rd",
    "sg:city":"Plainview",
    "sg:classifiers":[
        {
            "category":"Health Services",
            "subcategory":"Doctor",
            "type":"Services"
        }
    ],
    "sg:phone":"+1 516 935 5504",
    "sg:postcode":"11803",
    "sg:province":"NY",
    "sg:tags":[
        "physician",
        "surgeon"
    ],
    "wof:name":"Dr Lauren Scwartz",
    "wof:placetype":"venue"
},
  "geometry": {"coordinates":[-73.489063,40.77218],"type":"Point"}
}