{
  "type": "Feature",
  "properties": {
    "addr:full":"122 Riverside Blvd New York NY 10069",
    "addr:housenumber":"122",
    "addr:postcode":"10069",
    "addr:street":"Riverside Blvd",
    "iso:country":"US",
    "sg:address":"122 Riverside Blvd",
    "sg:city":"New York",
    "sg:classifiers":[
        {
            "category":"Recreation",
            "subcategory":"Amusement Park",
            "type":"Entertainment"
        }
    ],
    "sg:phone":"+1 212 666 1668",
    "sg:postcode":"10069",
    "sg:province":"NY",
    "wof:name":"General Grant National Memorial",
    "wof:placetype":"venue"
},
  "geometry": {"coordinates":[-73.989175,40.776485],"type":"Point"}
}