{
  "type": "Feature",
  "properties": {
    "addr:full":"2325 Richmond Ave Staten Island NY 10314",
    "addr:housenumber":"2325",
    "addr:postcode":"10314",
    "addr:street":"Richmond Ave",
    "iso:country":"US",
    "sg:address":"2325 Richmond Ave",
    "sg:city":"Staten Island",
    "sg:classifiers":[
        {
            "category":"Manufacturing",
            "subcategory":"Printing",
            "type":"Manufacturing & Wholesale Goods"
        }
    ],
    "sg:phone":"+1 718 370 0044",
    "sg:postcode":"10314",
    "sg:province":"NY",
    "sg:tags":[
        "screen"
    ],
    "wof:name":"Work 'n Gear",
    "wof:placetype":"venue"
},
  "geometry": {"coordinates":[-74.167406,40.589072],"type":"Point"}
}