{
  "type": "Feature",
  "properties": {
    "iso:country":"US",
    "sg:address":"1420 State Rte 196",
    "sg:city":"Hudson Falls",
    "sg:classifiers":[
        {
            "category":"Organizations",
            "subcategory":"Community Association",
            "type":"Services"
        }
    ],
    "sg:phone":"+1 518 747 4850",
    "sg:postcode":"12839",
    "sg:province":"NY",
    "sg:tags":[
        "club"
    ],
    "wof:name":"Hudson Falls Fish & Game",
    "wof:placetype":"venue"
},
  "geometry": {"coordinates":[-73.547718,43.305091],"type":"Point"}
}