{
  "type": "Feature",
  "properties": {
    "iso:country":"US",
    "sg:address":"281 W Fordham Rd",
    "sg:city":"Bronx",
    "sg:classifiers":[
        {
            "category":"Restaurant",
            "type":"Food & Drink"
        }
    ],
    "sg:phone":"+1 718 329 2000",
    "sg:postcode":"10468",
    "sg:province":"NY",
    "wof:name":"Jimmy's Dowtown",
    "wof:placetype":"venue"
},
  "geometry": {"coordinates":[-73.91243799999999,40.861861],"type":"Point"}
}