{
  "type": "Feature",
  "properties": {
    "addr:full":"71 Queen Anne Dr Slingerlands NY 12159",
    "addr:housenumber":"71",
    "addr:postcode":"12159",
    "addr:street":"Queen Anne Dr",
    "iso:country":"US",
    "sg:address":"71 Queen Anne Dr",
    "sg:city":"Slingerlands",
    "sg:classifiers":[
        {
            "category":"Home & Garden",
            "subcategory":"Furniture",
            "type":"Retail Goods"
        }
    ],
    "sg:phone":"+1 518 439 1319",
    "sg:postcode":"12159",
    "sg:province":"NY",
    "sg:tags":[
        "mattress"
    ],
    "wof:name":"Mattress Kings",
    "wof:placetype":"venue"
},
  "geometry": {"coordinates":[-73.842084,42.631396],"type":"Point"}
}