{
  "type": "Feature",
  "properties": {
    "iso:country":"US",
    "sg:address":"6505 Old Collamer Rd",
    "sg:city":"East Syracuse",
    "sg:classifiers":[
        {
            "category":"Building & Trades",
            "subcategory":"Construction",
            "type":"Services"
        }
    ],
    "sg:phone":"+1 315 437 9144",
    "sg:postcode":"13057",
    "sg:province":"NY",
    "sg:tags":[
        "specializing",
        "c",
        "general",
        "concrete",
        "masonry",
        "contractor"
    ],
    "wof:name":"Upstate Construction Services",
    "wof:placetype":"venue"
},
  "geometry": {"coordinates":[-76.085966,43.088249],"type":"Point"}
}