{
  "type": "Feature",
  "properties": {
    "iso:country":"US",
    "sg:address":"6 Sunset Dr",
    "sg:city":"Fredonia",
    "sg:classifiers":[
        {
            "category":"Real Estate",
            "subcategory":"Real Estate Operator",
            "type":"Services"
        }
    ],
    "sg:phone":"+1 716 679 1349",
    "sg:postcode":"14063",
    "sg:province":"NY",
    "sg:tags":[
        "building",
        "apartment"
    ],
    "wof:name":"Arcoraci Apartments",
    "wof:placetype":"venue"
},
  "geometry": {"coordinates":[-79.350925,42.438937],"type":"Point"}
}