{
  "type": "Feature",
  "properties": {
    "iso:country":"US",
    "sg:address":"35 Andrews St",
    "sg:city":"Massena",
    "sg:classifiers":[
        {
            "category":"Banks & Credit Unions",
            "subcategory":"Bank",
            "type":"Services"
        }
    ],
    "sg:phone":"+1 315 764 1751",
    "sg:postcode":"13662",
    "sg:province":"NY",
    "sg:tags":[
        "federal"
    ],
    "wof:name":"Sea Comm Federal Credit Union",
    "wof:placetype":"venue"
},
  "geometry": {"coordinates":[-74.89407199999999,44.931722],"type":"Point"}
}