{
  "type": "Feature",
  "properties": {
    "iso:country":"US",
    "sg:address":"313 Grant St",
    "sg:city":"Buffalo",
    "sg:classifiers":[
        {
            "category":"Restaurant",
            "type":"Food & Drink"
        }
    ],
    "sg:phone":"+1   ",
    "sg:postcode":"14213",
    "sg:province":"NY",
    "sg:tags":[
        "eating"
    ],
    "wof:name":"Italian Village",
    "wof:placetype":"venue"
},
  "geometry": {"coordinates":[-78.88983899999999,42.923717],"type":"Point"}
}