{
  "type": "Feature",
  "properties": {
    "iso:country":"US",
    "sg:address":"1005 Park St",
    "sg:city":"Peekskill",
    "sg:classifiers":[
        {
            "category":"Freight",
            "type":"Transportation"
        }
    ],
    "sg:phone":"+1 914 788 3488",
    "sg:postcode":"10566",
    "sg:province":"NY",
    "sg:tags":[
        "shipping",
        "agent"
    ],
    "wof:name":"Herj's Miscellaneous Express",
    "wof:placetype":"venue"
},
  "geometry": {"coordinates":[-73.919253,41.290733],"type":"Point"}
}