{
  "type": "Feature",
  "properties": {
    "addr:full":"2660 Sunrise Hwy Bellmore NY 11710",
    "addr:housenumber":"2660",
    "addr:postcode":"11710",
    "addr:street":"Sunrise Hwy",
    "iso:country":"US",
    "sg:address":"2660 Sunrise Hwy",
    "sg:city":"Bellmore",
    "sg:classifiers":[
        {
            "category":"Restaurant",
            "type":"Food & Drink"
        }
    ],
    "sg:menulink":"http://www.allmenus.com/ny/bellmore-merrick/32755-applebees/menu/",
    "sg:phone":"+1 516 783 9014",
    "sg:postcode":"11710",
    "sg:province":"NY",
    "sg:tags":[
        "burger",
        "american",
        "sandwich",
        "soup"
    ],
    "wof:name":"Applebee's",
    "wof:placetype":"venue"
},
  "geometry": {"coordinates":[-73.529027,40.668192],"type":"Point"}
}