{
  "type": "Feature",
  "properties": {
    "iso:country":"US",
    "sg:address":"333 E 56 St",
    "sg:city":"New York",
    "sg:classifiers":[
        {
            "category":"Professional",
            "subcategory":"Employment Agencies",
            "type":"Services"
        }
    ],
    "sg:phone":"+1 212 593 2819",
    "sg:postcode":"10022",
    "sg:province":"NY",
    "sg:tags":[
        "consultant",
        "search",
        "executive"
    ],
    "wof:name":"Executive Resources LTD",
    "wof:placetype":"venue"
},
  "geometry": {"coordinates":[-73.963961,40.758027],"type":"Point"}
}