{
  "type": "Feature",
  "properties": {
    "iso:country":"US",
    "sg:address":"1065 Avenue of the Americ",
    "sg:city":"New York",
    "sg:classifiers":[
        {
            "category":"Professional",
            "subcategory":"Employment Agencies",
            "type":"Services"
        }
    ],
    "sg:phone":"+1 212 354 3933",
    "sg:postcode":"10018",
    "sg:province":"NY",
    "wof:name":"Career Partners",
    "wof:placetype":"venue"
},
  "geometry": {"coordinates":[-73.9849,40.753751],"type":"Point"}
}