{
  "type": "Feature",
  "properties": {
    "addr:full":"85 Livingston St Brooklyn NY 11201",
    "addr:housenumber":"85",
    "addr:postcode":"11201",
    "addr:street":"Livingston St",
    "iso:country":"US",
    "sg:address":"85 Livingston St",
    "sg:city":"Brooklyn",
    "sg:classifiers":[
        {
            "category":"Real Estate",
            "subcategory":"Real Estate Operator",
            "type":"Services"
        }
    ],
    "sg:phone":"+1 718 596 4067",
    "sg:postcode":"11201",
    "sg:province":"NY",
    "sg:tags":[
        "building",
        "nonresidential"
    ],
    "wof:name":"Catskill Resort Properties LLC",
    "wof:placetype":"venue"
},
  "geometry": {"coordinates":[-73.989659,40.691205],"type":"Point"}
}