{
  "type": "Feature",
  "properties": {
    "addr:full":"321 Main St Utica NY 13501",
    "addr:housenumber":"321",
    "addr:postcode":"13501",
    "addr:street":"Main St",
    "iso:country":"US",
    "sg:address":"321 Main St",
    "sg:city":"Utica",
    "sg:classifiers":[
        {
            "category":"Government",
            "subcategory":"Office",
            "type":"Public Place"
        }
    ],
    "sg:phone":"+1 315 798 3604",
    "sg:postcode":"13501",
    "sg:province":"NY",
    "wof:name":"Oneida County Maintenance",
    "wof:placetype":"venue"
},
  "geometry": {"coordinates":[-75.223004,43.103638],"type":"Point"}
}