{
  "type": "Feature",
  "properties": {
    "iso:country":"US",
    "sg:address":"78 Cedar Dr",
    "sg:city":"Miller Place",
    "sg:classifiers":[
        {
            "category":"Professional",
            "subcategory":"Management & Consulting",
            "type":"Services"
        }
    ],
    "sg:phone":"+1 631 476 9730",
    "sg:postcode":"11764",
    "sg:province":"NY",
    "sg:tags":[
        "consultant"
    ],
    "wof:name":"Clearview Consultants Inc",
    "wof:placetype":"venue"
},
  "geometry": {"coordinates":[-73.01436,40.960035],"type":"Point"}
}