{
  "type": "Feature",
  "properties": {
    "iso:country":"US",
    "sg:address":"483 Merrick Rd",
    "sg:city":"Lynbrook",
    "sg:classifiers":[
        {
            "category":"Health Services",
            "subcategory":"Doctor",
            "type":"Services"
        }
    ],
    "sg:phone":"+1 516 561 5102",
    "sg:postcode":"11563",
    "sg:province":"NY",
    "wof:name":"Advanced Sports Medicine",
    "wof:placetype":"venue"
},
  "geometry": {"coordinates":[-73.678692,40.659075],"type":"Point"}
}