{
  "type": "Feature",
  "properties": {
    "iso:country":"US",
    "sg:address":"5125 State Hwy 12",
    "sg:city":"Norwich",
    "sg:classifiers":[
        {
            "category":"Professional",
            "subcategory":"Business Services",
            "type":"Services"
        }
    ],
    "sg:phone":"+1 607 334 7915",
    "sg:postcode":"13815",
    "sg:province":"NY",
    "sg:tags":[
        "embroidery"
    ],
    "wof:name":"Embroidered Expressions",
    "wof:placetype":"venue"
},
  "geometry": {"coordinates":[-75.52742000000001,42.556701],"type":"Point"}
}