{
  "type": "Feature",
  "properties": {
    "addr:full":"51 Sprague Ave Amityville NY 11701",
    "addr:housenumber":"51",
    "addr:postcode":"11701",
    "addr:street":"Sprague Ave",
    "iso:country":"US",
    "sg:address":"51 Sprague Ave",
    "sg:city":"Amityville",
    "sg:classifiers":[
        {
            "category":"Retail",
            "subcategory":"Auto Repair",
            "type":"Services"
        }
    ],
    "sg:phone":"+1   ",
    "sg:postcode":"11701",
    "sg:province":"NY",
    "sg:tags":[
        "body"
    ],
    "wof:name":"Alfredos Auto Collision",
    "wof:placetype":"venue"
},
  "geometry": {"coordinates":[-73.41772899999999,40.685325],"type":"Point"}
}