{
  "type": "Feature",
  "properties": {
    "iso:country":"US",
    "sg:address":"37 Wallace Ave",
    "sg:city":"Auburn",
    "sg:classifiers":[
        {
            "category":"Home & Garden",
            "subcategory":"Home Furnishings",
            "type":"Retail Goods"
        },
        {
            "category":"Building & Trades",
            "subcategory":"Construction",
            "type":"Services"
        }
    ],
    "sg:phone":"+1 315 252 3165",
    "sg:postcode":"13021",
    "sg:province":"NY",
    "sg:tags":[
        "stove",
        "wood",
        "fireplace",
        "burning",
        "contractor"
    ],
    "wof:name":"Lake Country Hearth & Leisure",
    "wof:placetype":"venue"
},
  "geometry": {"coordinates":[-76.58679100000001,42.92868],"type":"Point"}
}