{
  "type": "Feature",
  "properties": {
    "iso:country":"US",
    "sg:address":"1585 Broadway",
    "sg:city":"New York",
    "sg:classifiers":[
        {
            "category":"Personal",
            "type":"Services"
        }
    ],
    "sg:phone":"+1 212 492 9466",
    "sg:postcode":"10036",
    "sg:province":"NY",
    "sg:tags":[
        "towing"
    ],
    "wof:name":"A 7 Day Emergency 24 Hr Towing",
    "wof:placetype":"venue"
},
  "geometry": {"coordinates":[-73.98557099999999,40.759944],"type":"Point"}
}