{
  "type": "Feature",
  "properties": {
    "iso:country":"US",
    "sg:address":"686 Burnside Ave",
    "sg:city":"Inwood",
    "sg:classifiers":[
        {
            "category":"Retail",
            "subcategory":"Auto Rental",
            "type":"Services"
        }
    ],
    "sg:phone":"+1 516 239 0198",
    "sg:postcode":"11096",
    "sg:province":"NY",
    "sg:tags":[
        "car",
        "truck"
    ],
    "sg:website":"www.hertz.com",
    "wof:name":"Hertz Rent-A-Car",
    "wof:placetype":"venue"
},
  "geometry": {"coordinates":[-73.738344,40.623233],"type":"Point"}
}