{
  "type": "Feature",
  "properties": {
    "iso:country":"US",
    "sg:address":"883 Flatbush Avenue",
    "sg:city":"Brooklyn",
    "sg:classifiers":[
        {
            "category":"Banks & Credit Unions",
            "subcategory":"Bank",
            "type":"Services"
        }
    ],
    "sg:phone":"+1 718 935 9935",
    "sg:postcode":"11226",
    "sg:province":"NY",
    "wof:name":"Chase Bank",
    "wof:placetype":"venue"
},
  "geometry": {"coordinates":[-73.958608,40.650564],"type":"Point"}
}