{
  "type": "Feature",
  "properties": {
    "iso:country":"US",
    "sg:address":"35 Saratoga Ave",
    "sg:city":"Waterford",
    "sg:classifiers":[
        {
            "category":"Food & Beverages",
            "subcategory":"Liquor & Beverages",
            "type":"Retail Goods"
        }
    ],
    "sg:phone":"+1 518 238 0253",
    "sg:postcode":"12188",
    "sg:province":"NY",
    "sg:tags":[
        "beer",
        "ale"
    ],
    "wof:name":"Waterford Beverage Mart",
    "wof:placetype":"venue"
},
  "geometry": {"coordinates":[-73.69591,42.781137],"type":"Point"}
}