{
  "type": "Feature",
  "properties": {
    "iso:country":"US",
    "sg:address":"100 Huntleigh Cir",
    "sg:city":"Buffalo",
    "sg:classifiers":[
        {
            "category":"Professional",
            "subcategory":"Accounting & Tax Preparation",
            "type":"Services"
        }
    ],
    "sg:phone":"+1 716 834 5111",
    "sg:postcode":"14226",
    "sg:province":"NY",
    "sg:tags":[
        "accountant"
    ],
    "wof:name":"Peter R Costanzo Accountant",
    "wof:placetype":"venue"
},
  "geometry": {"coordinates":[-78.800579,42.982451],"type":"Point"}
}