{
  "type": "Feature",
  "properties": {
    "iso:country":"US",
    "sg:address":"29 Eason Dr",
    "sg:city":"Ridge",
    "sg:classifiers":[
        {
            "category":"Building & Trades",
            "subcategory":"Plumbing",
            "type":"Services"
        }
    ],
    "sg:phone":"+1 631 924 0356",
    "sg:postcode":"11961",
    "sg:province":"NY",
    "sg:tags":[
        "m",
        "contractor"
    ],
    "wof:name":"Morning Mist Lawn Sprinklers",
    "wof:placetype":"venue"
},
  "geometry": {"coordinates":[-72.914581,40.872771],"type":"Point"}
}