{
  "type": "Feature",
  "properties": {
    "addr:full":"86 Pine St Freeport NY 11520",
    "addr:housenumber":"86",
    "addr:postcode":"11520",
    "addr:street":"Pine St",
    "iso:country":"US",
    "sg:address":"86 Pine St",
    "sg:city":"Freeport",
    "sg:classifiers":[
        {
            "category":"Bakery",
            "type":"Food & Drink"
        }
    ],
    "sg:phone":"+1 516 867 4440",
    "sg:postcode":"11520",
    "sg:province":"NY",
    "wof:name":"Yummy Foods Corp",
    "wof:placetype":"venue"
},
  "geometry": {"coordinates":[-73.585826,40.655226],"type":"Point"}
}