{
  "type": "Feature",
  "properties": {
    "iso:country":"US",
    "sg:address":"3000 Marcus Ave",
    "sg:city":"New Hyde Park",
    "sg:classifiers":[
        {
            "category":"Professional",
            "subcategory":"Lawyer & Legal Services",
            "type":"Services"
        }
    ],
    "sg:phone":"+1 516 775 5300",
    "sg:postcode":"11042",
    "sg:province":"NY",
    "wof:name":"Bruday Insurance Svce",
    "wof:placetype":"venue"
},
  "geometry": {"coordinates":[-73.709999,40.7589],"type":"Point"}
}