{
  "type": "Feature",
  "properties": {
    "iso:country":"US",
    "sg:address":"26 S River Rd",
    "sg:city":"Saint Regis Falls",
    "sg:classifiers":[
        {
            "category":"Social Services",
            "type":"Services"
        }
    ],
    "sg:phone":"+1 518 856 9861",
    "sg:postcode":"12980",
    "sg:province":"NY",
    "sg:tags":[
        "adult",
        "center"
    ],
    "wof:name":"Saint Regis Falls Adult Center",
    "wof:placetype":"venue"
},
  "geometry": {"coordinates":[-74.508735,44.666891],"type":"Point"}
}