{
  "type": "Feature",
  "properties": {
    "addr:full":"262 Hull Ave Clintondale NY 12515",
    "addr:housenumber":"262",
    "addr:postcode":"12515",
    "addr:street":"Hull Ave",
    "iso:country":"US",
    "sg:address":"262 Hull Ave",
    "sg:city":"Clintondale",
    "sg:classifiers":[
        {
            "category":"Health Services",
            "subcategory":"Hospital",
            "type":"Services"
        }
    ],
    "sg:phone":"+1 845 883 5807",
    "sg:postcode":"12515",
    "sg:province":"NY",
    "sg:tags":[
        "mental"
    ],
    "wof:name":"Multi-County Community Dev",
    "wof:placetype":"venue"
},
  "geometry": {"coordinates":[-74.05154400000001,41.678238],"type":"Point"}
}