{
  "type": "Feature",
  "properties": {
    "iso:country":"US",
    "sg:address":"32 Cemetery Rd",
    "sg:city":"Corinth",
    "sg:classifiers":[
        {
            "category":"Travel",
            "subcategory":"Campground",
            "type":"Entertainment"
        }
    ],
    "sg:phone":"+1   ",
    "sg:postcode":"12856",
    "sg:province":"NY",
    "sg:tags":[
        "trailer"
    ],
    "wof:name":"Fort Bink Camp Grounds",
    "wof:placetype":"venue"
},
  "geometry": {"coordinates":[-74.076258,43.738112],"type":"Point"}
}