{
  "type": "Feature",
  "properties": {
    "addr:full":"361 Mamaroneck Ave White Plains NY 10605",
    "addr:housenumber":"361",
    "addr:postcode":"10605",
    "addr:street":"Mamaroneck Ave",
    "iso:country":"US",
    "sg:address":"361 Mamaroneck Ave",
    "sg:city":"White Plains",
    "sg:classifiers":[
        {
            "category":"Personal",
            "subcategory":"Beauty Salon",
            "type":"Services"
        }
    ],
    "sg:phone":"+1 914 761 1554",
    "sg:postcode":"10605",
    "sg:province":"NY",
    "wof:name":"Flying Machine",
    "wof:placetype":"venue"
},
  "geometry": {"coordinates":[-73.762413,41.023833],"type":"Point"}
}