{
  "type": "Feature",
  "properties": {
    "addr:full":"1816 Eastchester Rd Bronx NY 10461",
    "addr:housenumber":"1816",
    "addr:postcode":"10461",
    "addr:street":"Eastchester Rd",
    "iso:country":"US",
    "sg:address":"1816 Eastchester Rd",
    "sg:city":"Bronx",
    "sg:classifiers":[
        {
            "category":"Retail",
            "subcategory":"Repair Shop",
            "type":"Services"
        }
    ],
    "sg:phone":"+1 718 732 0074",
    "sg:postcode":"10461",
    "sg:province":"NY",
    "sg:tags":[
        "lock",
        "locksmith"
    ],
    "wof:name":"Any Locksmith 24 Hours",
    "wof:placetype":"venue"
},
  "geometry": {"coordinates":[-73.8446,40.846555],"type":"Point"}
}