{
  "type": "Feature",
  "properties": {
    "addr:full":"274 Rte 25A East Setauket NY 11733",
    "addr:housenumber":"274",
    "addr:postcode":"11733",
    "addr:street":"Rte 25A East",
    "iso:country":"US",
    "sg:address":"274 Rte 25A",
    "sg:city":"East Setauket",
    "sg:classifiers":[
        {
            "category":"Professional",
            "subcategory":"Business Services",
            "type":"Services"
        }
    ],
    "sg:phone":"+1   ",
    "sg:postcode":"11733",
    "sg:province":"NY",
    "sg:tags":[
        "interior",
        "shop",
        "decorator",
        "gift"
    ],
    "wof:name":"Home Decor Inc",
    "wof:placetype":"venue"
},
  "geometry": {"coordinates":[-73.103144,40.94281],"type":"Point"}
}