{
  "type": "Feature",
  "properties": {
    "addr:full":"6352 108th St Forest Hills NY 11375",
    "addr:housenumber":"6352",
    "addr:postcode":"11375",
    "addr:street":"108Th St",
    "iso:country":"US",
    "sg:address":"6352 108th St",
    "sg:city":"Forest Hills",
    "sg:classifiers":[
        {
            "category":"Landmark",
            "subcategory":"Tourist Information",
            "type":"Public Place"
        }
    ],
    "sg:phone":"+1 718 275 0727",
    "sg:postcode":"11375",
    "sg:province":"NY",
    "sg:tags":[
        "tour"
    ],
    "wof:name":"Star Tours",
    "wof:placetype":"venue"
},
  "geometry": {"coordinates":[-73.850086,40.733509],"type":"Point"}
}