{
  "type": "Feature",
  "properties": {
    "iso:country":"US",
    "sg:address":"3922 Seneca St",
    "sg:city":"Buffalo",
    "sg:classifiers":[
        {
            "category":"Professional",
            "subcategory":"Management & Consulting",
            "type":"Services"
        }
    ],
    "sg:phone":"+1 716 674 9245",
    "sg:postcode":"14224",
    "sg:province":"NY",
    "sg:tags":[
        "real estate"
    ],
    "wof:name":"F J Wailand Associates Inc",
    "wof:placetype":"venue"
},
  "geometry": {"coordinates":[-78.75799000000001,42.829993],"type":"Point"}
}