{
  "type": "Feature",
  "properties": {
    "addr:full":"386 Sanitaria Springs Rd Port Crane NY 13833",
    "addr:housenumber":"386",
    "addr:postcode":"13833",
    "addr:street":"Sanitaria Springs Rd",
    "iso:country":"US",
    "sg:address":"386 Sanitaria Springs Rd",
    "sg:city":"Port Crane",
    "sg:classifiers":[
        {
            "category":"Organizations",
            "subcategory":"Religious Organization",
            "type":"Services"
        }
    ],
    "sg:phone":"+1 607 648 9894",
    "sg:postcode":"13833",
    "sg:province":"NY",
    "sg:tags":[
        "church"
    ],
    "wof:name":"Sanitaria Springs Methodist Ch",
    "wof:placetype":"venue"
},
  "geometry": {"coordinates":[-75.76660200000001,42.160176],"type":"Point"}
}