{
  "type": "Feature",
  "properties": {
    "addr:full":"2 Convent Ave Wappingers Falls NY 12590",
    "addr:housenumber":"2",
    "addr:postcode":"12590",
    "addr:street":"Convent Ave",
    "iso:country":"US",
    "sg:address":"2 Convent Ave",
    "sg:city":"Wappingers Falls",
    "sg:classifiers":[
        {
            "category":"Education",
            "subcategory":"School",
            "type":"Public Place"
        }
    ],
    "sg:phone":"+1 845 297 7500",
    "sg:postcode":"12590",
    "sg:province":"NY",
    "sg:tags":[
        "religious"
    ],
    "sg:website":"www.stmarywf.org",
    "wof:name":"St Mary's School",
    "wof:placetype":"venue"
},
  "geometry": {"coordinates":[-73.922511,41.604296],"type":"Point"}
}