{
  "type": "Feature",
  "properties": {
    "addr:full":"50 Main St Mt Kisco NY 10549",
    "addr:housenumber":"50",
    "addr:postcode":"10549",
    "addr:street":"Main St;Kisco",
    "iso:country":"US",
    "sg:address":"50 Main St",
    "sg:city":"Mt Kisco",
    "sg:classifiers":[
        {
            "category":"Professional",
            "subcategory":"Lawyer & Legal Services",
            "type":"Services"
        }
    ],
    "sg:phone":"+1 914 241 0954",
    "sg:postcode":"10549",
    "sg:province":"NY",
    "sg:tags":[
        "attorney"
    ],
    "wof:name":"Peter A Spagnuolo",
    "wof:placetype":"venue"
},
  "geometry": {"coordinates":[-73.72682399999999,41.206554],"type":"Point"}
}