{
  "type": "Feature",
  "properties": {
    "addr:full":"14 Oakland Ave Walden NY 12586",
    "addr:housenumber":"14",
    "addr:postcode":"12586",
    "addr:street":"Oakland Ave",
    "iso:country":"US",
    "sg:address":"14 Oakland Ave",
    "sg:city":"Walden",
    "sg:classifiers":[
        {
            "category":"Professional",
            "subcategory":"Detective & Security Services",
            "type":"Services"
        }
    ],
    "sg:phone":"+1 845 457 1791",
    "sg:postcode":"12586",
    "sg:province":"NY",
    "sg:tags":[
        "information",
        "bureau"
    ],
    "wof:name":"Sky Computer Services",
    "wof:placetype":"venue"
},
  "geometry": {"coordinates":[-74.181453,41.562257],"type":"Point"}
}