{
  "type": "Feature",
  "properties": {
    "addr:full":"45 N Village Ave Rockville Centre NY 11570",
    "addr:housenumber":"45",
    "addr:postcode":"11570",
    "addr:street":"N Village Ave",
    "iso:country":"US",
    "sg:address":"45 N Village Ave",
    "sg:city":"Rockville Centre",
    "sg:classifiers":[
        {
            "category":"Professional",
            "subcategory":"Business Services",
            "type":"Services"
        }
    ],
    "sg:phone":"+1 516 536 9001",
    "sg:postcode":"11570",
    "sg:province":"NY",
    "sg:tags":[
        "arbitration"
    ],
    "wof:name":"Family Mediation Svc",
    "wof:placetype":"venue"
},
  "geometry": {"coordinates":[-73.647738,40.657881],"type":"Point"}
}