{
  "type": "Feature",
  "properties": {
    "addr:full":"421 Sunrise Hwy Lynbrook NY 11563",
    "addr:housenumber":"421",
    "addr:postcode":"11563",
    "addr:street":"Sunrise Hwy",
    "iso:country":"US",
    "sg:address":"421 Sunrise Hwy",
    "sg:city":"Lynbrook",
    "sg:classifiers":[
        {
            "category":"Personal",
            "subcategory":"Barber",
            "type":"Services"
        }
    ],
    "sg:phone":"+1 516 599 5445",
    "sg:postcode":"11563",
    "sg:province":"NY",
    "wof:name":"Best Barber Shop",
    "wof:placetype":"venue"
},
  "geometry": {"coordinates":[-73.671898,40.6548],"type":"Point"}
}