{
  "type": "Feature",
  "properties": {
    "iso:country":"US",
    "sg:address":"34 N Main St",
    "sg:city":"Spring Valley",
    "sg:classifiers":[
        {
            "category":"Food & Beverages",
            "subcategory":"Groceries & Convenience Stores",
            "type":"Retail Goods"
        }
    ],
    "sg:phone":"+1 845 352 6609",
    "sg:postcode":"10977",
    "sg:province":"NY",
    "sg:tags":[
        "market"
    ],
    "wof:name":"Food Star Grocery Store",
    "wof:placetype":"venue"
},
  "geometry": {"coordinates":[-74.04478400000001,41.112499],"type":"Point"}
}