{
  "type": "Feature",
  "properties": {
    "iso:country":"US",
    "sg:address":"2225 Brewerton Rd",
    "sg:city":"Syracuse",
    "sg:classifiers":[
        {
            "category":"Shopping",
            "subcategory":"Clothing, Apparel, & Fashions",
            "type":"Retail Goods"
        }
    ],
    "sg:phone":"+1 315 455 5304",
    "sg:postcode":"13211",
    "sg:province":"NY",
    "wof:name":"Saigon Fashions",
    "wof:placetype":"venue"
},
  "geometry": {"coordinates":[-76.145444,43.097778],"type":"Point"}
}