{
  "type": "Feature",
  "properties": {
    "iso:country":"US",
    "sg:address":"157 River Rd N",
    "sg:city":"Wappingers Falls",
    "sg:classifiers":[
        {
            "category":"Wholesale",
            "subcategory":"Construction Materials",
            "type":"Manufacturing & Wholesale Goods"
        }
    ],
    "sg:phone":"+1 845 440 0800",
    "sg:postcode":"12590",
    "sg:province":"NY",
    "sg:tags":[
        "lumber"
    ],
    "wof:name":"Chelsea Forest Products",
    "wof:placetype":"venue"
},
  "geometry": {"coordinates":[-73.95573,41.56148],"type":"Point"}
}