{
  "type": "Feature",
  "properties": {
    "addr:full":"218 Milburn St Rochester NY 14607",
    "addr:housenumber":"218",
    "addr:postcode":"14607",
    "addr:street":"Milburn St",
    "iso:country":"US",
    "sg:address":"218 Milburn St",
    "sg:city":"Rochester",
    "sg:classifiers":[
        {
            "category":"Organizations",
            "subcategory":"Religious Organization",
            "type":"Services"
        }
    ],
    "sg:phone":"+1 585 271 0921",
    "sg:postcode":"14607",
    "sg:province":"NY",
    "sg:tags":[
        "clergy"
    ],
    "wof:name":"Frank D Howden",
    "wof:placetype":"venue"
},
  "geometry": {"coordinates":[-77.57653500000001,43.145709],"type":"Point"}
}