{
  "type": "Feature",
  "properties": {
    "addr:full":"416 E 52 St New York NY 10022",
    "addr:housenumber":"416;52",
    "addr:postcode":"10022",
    "addr:street":"E;St",
    "iso:country":"US",
    "sg:address":"416 E 52 St",
    "sg:city":"New York",
    "sg:classifiers":[
        {
            "category":"Retail",
            "subcategory":"Auto Repair",
            "type":"Services"
        }
    ],
    "sg:phone":"+1 212 792 0768",
    "sg:postcode":"10022",
    "sg:province":"NY",
    "sg:tags":[
        "wrecker"
    ],
    "wof:name":"A Anyplace Towing",
    "wof:placetype":"venue"
},
  "geometry": {"coordinates":[-73.96405,40.754591],"type":"Point"}
}