{
  "type": "Feature",
  "properties": {
    "addr:full":"179 Edgewood Ave Ronkonkoma NY 11779",
    "addr:housenumber":"179",
    "addr:postcode":"11779",
    "addr:street":"Edgewood Ave",
    "iso:country":"US",
    "sg:address":"179 Edgewood Ave",
    "sg:city":"Ronkonkoma",
    "sg:classifiers":[
        {
            "category":"Professional",
            "subcategory":"Management & Consulting",
            "type":"Services"
        }
    ],
    "sg:phone":"+1 631 585 6486",
    "sg:postcode":"11779",
    "sg:province":"NY",
    "sg:tags":[
        "home",
        "demonstration"
    ],
    "wof:name":"Amway Distributors",
    "wof:placetype":"venue"
},
  "geometry": {"coordinates":[-73.147216,40.816504],"type":"Point"}
}