{
  "type": "Feature",
  "properties": {
    "addr:full":"82 E 18th Street Brooklyn NY 11226",
    "addr:housenumber":"82",
    "addr:postcode":"11226",
    "addr:street":"E 18Th Street",
    "iso:country":"US",
    "sg:address":"82 E 18th Street",
    "sg:city":"Brooklyn",
    "sg:classifiers":[
        {
            "category":"Restaurant",
            "type":"Food & Drink"
        }
    ],
    "sg:phone":"+1 718 282 8898",
    "sg:postcode":"11226",
    "sg:province":"NY",
    "wof:name":"Exquisite Supreme",
    "wof:placetype":"venue"
},
  "geometry": {"coordinates":[-73.963086,40.64935],"type":"Point"}
}