{
  "type": "Feature",
  "properties": {
    "addr:full":"77 Oswego St Camden NY 13316",
    "addr:housenumber":"77",
    "addr:postcode":"13316",
    "addr:street":"Oswego St",
    "iso:country":"US",
    "sg:address":"77 Oswego St",
    "sg:city":"Camden",
    "sg:classifiers":[
        {
            "category":"Freight",
            "type":"Transportation"
        }
    ],
    "sg:phone":"+1   ",
    "sg:postcode":"13316",
    "sg:province":"NY",
    "sg:tags":[
        "operator",
        "trucking"
    ],
    "wof:name":"Schinn Transport Inc",
    "wof:placetype":"venue"
},
  "geometry": {"coordinates":[-75.75923299999999,43.346624],"type":"Point"}
}