{
  "type": "Feature",
  "properties": {
    "addr:full":"537 W 125th St New York NY 10027",
    "addr:housenumber":"537",
    "addr:postcode":"10027",
    "addr:street":"W 125Th St",
    "iso:country":"US",
    "sg:address":"537 W 125th St",
    "sg:city":"New York",
    "sg:classifiers":[
        {
            "category":"Wholesale",
            "subcategory":"Painting Supplies",
            "type":"Manufacturing & Wholesale Goods"
        }
    ],
    "sg:phone":"+1 212 864 2460",
    "sg:postcode":"10027",
    "sg:province":"NY",
    "sg:tags":[
        "building",
        "paint"
    ],
    "wof:name":"Franklin & Lennon Paint Company",
    "wof:placetype":"venue"
},
  "geometry": {"coordinates":[-73.957004,40.814693],"type":"Point"}
}