{
  "type": "Feature",
  "properties": {
    "addr:full":"1610 Route 112 Medford NY 11763",
    "addr:housenumber":"1610",
    "addr:postcode":"11763",
    "addr:street":"Route 112",
    "iso:country":"US",
    "sg:address":"1610 Route 112",
    "sg:city":"Medford",
    "sg:classifiers":[
        {
            "category":"Food & Beverages",
            "subcategory":"Groceries & Convenience Stores",
            "type":"Retail Goods"
        }
    ],
    "sg:phone":"+1 631 654 9622",
    "sg:postcode":"11763",
    "sg:province":"NY",
    "wof:name":"Giuntas Meat Farms",
    "wof:placetype":"venue"
},
  "geometry": {"coordinates":[-73.006203,40.7967],"type":"Point"}
}