{
  "type": "Feature",
  "properties": {
    "iso:country":"US",
    "sg:address":"518 Dewitt Ave",
    "sg:city":"North Babylon",
    "sg:classifiers":[
        {
            "category":"Professional",
            "subcategory":"Business Services",
            "type":"Services"
        }
    ],
    "sg:phone":"+1 631 667 5420",
    "sg:postcode":"11703",
    "sg:province":"NY",
    "sg:tags":[
        "appraiser"
    ],
    "wof:name":"Market Data Ctr",
    "wof:placetype":"venue"
},
  "geometry": {"coordinates":[-73.32903899999999,40.743768],"type":"Point"}
}