{
  "type": "Feature",
  "properties": {
    "addr:full":"8317 Harwood Dr Lacona NY 13083",
    "addr:housenumber":"8317",
    "addr:postcode":"13083",
    "addr:street":"Harwood Dr",
    "iso:country":"US",
    "sg:address":"8317 Harwood Dr",
    "sg:city":"Lacona",
    "sg:classifiers":[
        {
            "category":"Travel",
            "subcategory":"Hotels & Motels",
            "type":"Entertainment"
        }
    ],
    "sg:phone":"+1 315 387 3850",
    "sg:postcode":"13083",
    "sg:province":"NY",
    "wof:name":"Central Hotel",
    "wof:placetype":"venue"
},
  "geometry": {"coordinates":[-76.07003899999999,43.643432],"type":"Point"}
}