{
  "type": "Feature",
  "properties": {
    "iso:country":"US",
    "sg:address":"421 W 146th St",
    "sg:city":"New York",
    "sg:classifiers":[
        {
            "category":"Building & Trades",
            "subcategory":"Construction",
            "type":"Services"
        }
    ],
    "sg:phone":"+1 212 368 4970",
    "sg:postcode":"10031",
    "sg:province":"NY",
    "sg:tags":[
        "general",
        "contractor"
    ],
    "wof:name":"New World General Contractor",
    "wof:placetype":"venue"
},
  "geometry": {"coordinates":[-73.945233,40.82513],"type":"Point"}
}