{
  "type": "Feature",
  "properties": {
    "iso:country":"US",
    "sg:address":"5112 Olympic Ave",
    "sg:city":"Buffalo",
    "sg:classifiers":[
        {
            "category":"Building & Trades",
            "subcategory":"Construction",
            "type":"Services"
        }
    ],
    "sg:phone":"+1 716 648 9072",
    "sg:postcode":"14219",
    "sg:province":"NY",
    "sg:tags":[
        "contractor"
    ],
    "wof:name":"Caggiano Masonry Inc",
    "wof:placetype":"venue"
},
  "geometry": {"coordinates":[-78.796238,42.782132],"type":"Point"}
}