{
  "type": "Feature",
  "properties": {
    "addr:full":"511 Holmes Rd Holmes NY 12531",
    "addr:housenumber":"511",
    "addr:postcode":"12531",
    "addr:street":"Holmes Rd",
    "iso:country":"US",
    "sg:address":"511 Holmes Rd",
    "sg:city":"Holmes",
    "sg:classifiers":[
        {
            "category":"Building & Trades",
            "subcategory":"Plumbing",
            "type":"Services"
        }
    ],
    "sg:phone":"+1 914 907 7860",
    "sg:postcode":"12531",
    "sg:province":"NY",
    "sg:tags":[
        "plumbing",
        "contractor"
    ],
    "wof:name":"Adept Plumbing & Drain Clng",
    "wof:placetype":"venue"
},
  "geometry": {"coordinates":[-73.668076,41.522052],"type":"Point"}
}