{
  "type": "Feature",
  "properties": {
    "addr:full":"221 Mineola Blvd Mineola NY 11501",
    "addr:housenumber":"221",
    "addr:postcode":"11501",
    "addr:street":"Mineola Blvd",
    "iso:country":"US",
    "sg:address":"221 Mineola Blvd",
    "sg:city":"Mineola",
    "sg:classifiers":[
        {
            "category":"Professional",
            "subcategory":"Lawyer & Legal Services",
            "type":"Services"
        }
    ],
    "sg:phone":"+1 516 742 1460",
    "sg:postcode":"11501",
    "sg:province":"NY",
    "wof:name":"Trueman David L ESQ",
    "wof:placetype":"venue"
},
  "geometry": {"coordinates":[-73.642899,40.746201],"type":"Point"}
}