{
  "type": "Feature",
  "properties": {
    "addr:full":"8 Quaker Ridge Rd New Rochelle NY 10804",
    "addr:housenumber":"8",
    "addr:postcode":"10804",
    "addr:street":"Quaker Ridge Rd",
    "iso:country":"US",
    "sg:address":"8 Quaker Ridge Rd",
    "sg:city":"New Rochelle",
    "sg:classifiers":[
        {
            "category":"Food & Beverages",
            "subcategory":"Bakery",
            "type":"Retail Goods"
        }
    ],
    "sg:phone":"+1   ",
    "sg:postcode":"10804",
    "sg:province":"NY",
    "sg:tags":[
        "product",
        "mfg"
    ],
    "wof:name":"Donut World Inc",
    "wof:placetype":"venue"
},
  "geometry": {"coordinates":[-73.791225,40.949781],"type":"Point"}
}