{
  "type": "Feature",
  "properties": {
    "addr:full":"2 Horatio St. 11th floor Manhattan NY 10014",
    "addr:housenumber":"2;11th",
    "addr:postcode":"10014",
    "addr:street":"Horatio St.;Floor",
    "iso:country":"US",
    "sg:address":"2 Horatio St. 11th floor",
    "sg:city":"Manhattan",
    "sg:classifiers":[
        {
            "category":"Shopping",
            "subcategory":"Crafts & Fabrics",
            "type":"Retail Goods"
        },
        {
            "category":"Education",
            "subcategory":"School",
            "type":"Public Place"
        }
    ],
    "sg:phone":"+1 845 290 1561",
    "sg:postcode":"10014",
    "sg:province":"NY",
    "sg:tags":[
        "art"
    ],
    "sg:website":"african.ethidolls.com",
    "wof:name":"EthiDolls",
    "wof:placetype":"venue"
},
  "geometry": {"coordinates":[-74.002571,40.738548],"type":"Point"}
}