{
  "type": "Feature",
  "properties": {
    "iso:country":"US",
    "sg:address":"111 Brook St",
    "sg:city":"Scarsdale",
    "sg:classifiers":[
        {
            "category":"Insurance",
            "subcategory":"Health Insurance",
            "type":"Services"
        }
    ],
    "sg:phone":"+1 914 722 4807",
    "sg:postcode":"10583",
    "sg:province":"NY",
    "sg:tags":[
        "life",
        "carrier",
        "carrie"
    ],
    "wof:name":"Insmed Insurance Agency Inc",
    "wof:placetype":"venue"
},
  "geometry": {"coordinates":[-73.80645,40.977829],"type":"Point"}
}