{
  "type": "Feature",
  "properties": {
    "iso:country":"US",
    "sg:address":"1 Civic Center Plz",
    "sg:city":"Poughkeepsie",
    "sg:classifiers":[
        {
            "category":"Professional",
            "subcategory":"Lawyer & Legal Services",
            "type":"Services"
        }
    ],
    "sg:phone":"+1 845 483 7327",
    "sg:postcode":"12601",
    "sg:province":"NY",
    "sg:tags":[
        "attorney"
    ],
    "wof:name":"David A Sears",
    "wof:placetype":"venue"
},
  "geometry": {"coordinates":[-73.928556,41.704975],"type":"Point"}
}