{
  "type": "Feature",
  "properties": {
    "iso:country":"US",
    "sg:address":"15 Boulevard",
    "sg:city":"Hudson Falls",
    "sg:classifiers":[
        {
            "category":"Health Services",
            "subcategory":"Health Practitioner",
            "type":"Services"
        }
    ],
    "sg:phone":"+1   ",
    "sg:postcode":"12839",
    "sg:province":"NY",
    "wof:name":"David J Funari",
    "wof:placetype":"venue"
},
  "geometry": {"coordinates":[-73.58927300000001,43.314675],"type":"Point"}
}