{
  "type": "Feature",
  "properties": {
    "addr:full":"13331 39th Ave Flushing NY 11354",
    "addr:housenumber":"13331",
    "addr:postcode":"11354",
    "addr:street":"39Th Ave",
    "iso:country":"US",
    "sg:address":"13331 39th Ave",
    "sg:city":"Flushing",
    "sg:classifiers":[
        {
            "category":"Shopping",
            "subcategory":"Clothing, Apparel, & Fashions",
            "type":"Retail Goods"
        },
        {
            "category":"Shopping",
            "subcategory":"Jewelry",
            "type":"Retail Goods"
        }
    ],
    "sg:phone":"+1 718 661 2203",
    "sg:postcode":"11354",
    "sg:province":"NY",
    "sg:tags":[
        "clothing",
        "women's"
    ],
    "wof:name":"MAS Jewelry",
    "wof:placetype":"venue"
},
  "geometry": {"coordinates":[-73.834137,40.759112],"type":"Point"}
}