{
  "type": "Feature",
  "properties": {
    "addr:full":"98 Sally Ln Ridge NY 11961",
    "addr:housenumber":"98",
    "addr:postcode":"11961",
    "addr:street":"Sally Ln",
    "iso:country":"US",
    "sg:address":"98 Sally Ln",
    "sg:city":"Ridge",
    "sg:classifiers":[
        {
            "category":"Building & Trades",
            "subcategory":"Landscaping Services",
            "type":"Services"
        }
    ],
    "sg:phone":"+1 631 345 0268",
    "sg:postcode":"11961",
    "sg:province":"NY",
    "sg:tags":[
        "landscape"
    ],
    "wof:name":"RN Farms Inc",
    "wof:placetype":"venue"
},
  "geometry": {"coordinates":[-72.894403,40.879138],"type":"Point"}
}