{
  "type": "Feature",
  "properties": {
    "addr:full":"215 N Linden St Buffalo NY 14221",
    "addr:housenumber":"215",
    "addr:postcode":"14221",
    "addr:street":"N Linden St",
    "iso:country":"US",
    "sg:address":"215 N Linden St",
    "sg:city":"Buffalo",
    "sg:classifiers":[
        {
            "category":"Arts & Performance",
            "subcategory":"Theater",
            "type":"Entertainment"
        }
    ],
    "sg:phone":"+1 716 836 6995",
    "sg:postcode":"14221",
    "sg:province":"NY",
    "sg:tags":[
        "entertainer",
        "business"
    ],
    "wof:name":"Enchanted Theater Puppet Shows",
    "wof:placetype":"venue"
},
  "geometry": {"coordinates":[-78.749465,42.953926],"type":"Point"}
}