{
  "type": "Feature",
  "properties": {
    "addr:full":"3998 White Plains Rd Bronx NY 10466",
    "addr:housenumber":"3998",
    "addr:postcode":"10466",
    "addr:street":"White Plains Rd",
    "iso:country":"US",
    "sg:address":"3998 White Plains Rd",
    "sg:city":"Bronx",
    "sg:classifiers":[
        {
            "category":"Restaurant",
            "type":"Food & Drink"
        }
    ],
    "sg:phone":"+1 718 547 2896",
    "sg:postcode":"10466",
    "sg:province":"NY",
    "sg:tags":[
        "delicatessen"
    ],
    "wof:name":"New York Deli",
    "wof:placetype":"venue"
},
  "geometry": {"coordinates":[-73.860452,40.887803],"type":"Point"}
}