{
  "type": "Feature",
  "properties": {
    "iso:country":"US",
    "sg:address":"711 E 241st St",
    "sg:city":"Bronx",
    "sg:classifiers":[
        {
            "category":"Taxi",
            "type":"Transportation"
        }
    ],
    "sg:phone":"+1 914 668 7777",
    "sg:postcode":"10470",
    "sg:province":"NY",
    "sg:tags":[
        "taxicab"
    ],
    "wof:name":"MPC Auto Svc",
    "wof:placetype":"venue"
},
  "geometry": {"coordinates":[-73.850084,40.903366],"type":"Point"}
}