{
  "type": "Feature",
  "properties": {
    "iso:country":"US",
    "sg:address":"280 Marsh Ave",
    "sg:city":"Staten Island",
    "sg:classifiers":[
        {
            "category":"Restaurant",
            "type":"Food & Drink"
        }
    ],
    "sg:menulink":"http://www.allmenus.com/ny/staten-island/43395-carrabbas/menu/",
    "sg:phone":"+1 718 477 9000",
    "sg:postcode":"10314",
    "sg:province":"NY",
    "sg:tags":[
        "italian"
    ],
    "wof:name":"Carrabba's",
    "wof:placetype":"venue"
},
  "geometry": {"coordinates":[-74.16374999999999,40.576858],"type":"Point"}
}