{
  "type": "Feature",
  "properties": {
    "addr:full":"385 Harman Street Brooklyn NY 11237",
    "addr:housenumber":"385",
    "addr:postcode":"11237",
    "addr:street":"Harman Street",
    "iso:country":"US",
    "sg:address":"385 Harman Street",
    "sg:city":"Brooklyn",
    "sg:classifiers":[
        {
            "category":"Building & Trades",
            "subcategory":"Construction",
            "type":"Services"
        }
    ],
    "sg:phone":"+1 718 456 4648",
    "sg:postcode":"11237",
    "sg:province":"NY",
    "sg:tags":[
        "contractor"
    ],
    "wof:name":"Baglio Salvatore",
    "wof:placetype":"venue"
},
  "geometry": {"coordinates":[-73.91805600000001,40.70092],"type":"Point"}
}