{
  "type": "Feature",
  "properties": {
    "iso:country":"US",
    "sg:address":"516 5th Ave",
    "sg:city":"New York",
    "sg:classifiers":[
        {
            "category":"Health Services",
            "subcategory":"Podiatrist",
            "type":"Services"
        }
    ],
    "sg:phone":"+1 212 768 7999",
    "sg:postcode":"10036",
    "sg:province":"NY",
    "wof:name":"Manhattan Podiatry Assoc",
    "wof:placetype":"venue"
},
  "geometry": {"coordinates":[-73.979936,40.754782],"type":"Point"}
}