{
  "type": "Feature",
  "properties": {
    "iso:country":"US",
    "sg:address":"1271 Hempstead Tpke",
    "sg:city":"Elmont",
    "sg:classifiers":[
        {
            "category":"Shopping",
            "subcategory":"Clothing, Apparel, & Fashions",
            "type":"Retail Goods"
        }
    ],
    "sg:phone":"+1   ",
    "sg:postcode":"11003",
    "sg:province":"NY",
    "sg:tags":[
        "school",
        "uniform"
    ],
    "wof:name":"Kids Country LLC",
    "wof:placetype":"venue"
},
  "geometry": {"coordinates":[-73.686949,40.708356],"type":"Point"}
}