{
  "type": "Feature",
  "properties": {
    "iso:country":"US",
    "sg:address":"222 Highland Dr",
    "sg:city":"Buffalo",
    "sg:classifiers":[
        {
            "category":"Shopping",
            "subcategory":"Gifts & Souvenirs",
            "type":"Retail Goods"
        }
    ],
    "sg:phone":"+1   ",
    "sg:postcode":"14221",
    "sg:province":"NY",
    "wof:name":"Frans Fence Folks",
    "wof:placetype":"venue"
},
  "geometry": {"coordinates":[-78.733797,42.957369],"type":"Point"}
}