{
  "type": "Feature",
  "properties": {
    "addr:full":"50 Morsemere Pl Yonkers NY 10701",
    "addr:housenumber":"50",
    "addr:postcode":"10701",
    "addr:street":"Morsemere Pl",
    "iso:country":"US",
    "sg:address":"50 Morsemere Pl",
    "sg:city":"Yonkers",
    "sg:classifiers":[
        {
            "category":"Health Services",
            "subcategory":"Doctor",
            "type":"Services"
        }
    ],
    "sg:phone":"+1 914 968 6619",
    "sg:postcode":"10701",
    "sg:province":"NY",
    "sg:tags":[
        "physician",
        "surgeon"
    ],
    "wof:name":"A O A",
    "wof:placetype":"venue"
},
  "geometry": {"coordinates":[-73.888261,40.959064],"type":"Point"}
}