{
  "type": "Feature",
  "properties": {
    "addr:full":"45 Main St Irvington NY 10533",
    "addr:housenumber":"45",
    "addr:postcode":"ny 10533",
    "addr:street":"Main St",
    "iso:country":"US",
    "sg:address":"45 Main St",
    "sg:city":"Irvington",
    "sg:classifiers":[
        {
            "category":"Restaurant",
            "type":"Food & Drink"
        }
    ],
    "sg:phone":"+1 914 591 7406",
    "sg:postcode":"10533",
    "sg:province":"NY",
    "sg:tags":[
        "caterer"
    ],
    "wof:name":"Rich Bean Bakery",
    "wof:placetype":"venue"
},
  "geometry": {"coordinates":[-73.870572,41.039623],"type":"Point"}
}