{
  "type": "Feature",
  "properties": {
    "addr:full":"764 Columbus Ave New York NY 10025",
    "addr:housenumber":"764",
    "addr:postcode":"10025",
    "addr:street":"Columbus Ave",
    "iso:country":"US",
    "sg:address":"764 Columbus Ave",
    "sg:city":"New York",
    "sg:classifiers":[
        {
            "category":"Retail",
            "subcategory":"Auto Repair",
            "type":"Services"
        }
    ],
    "sg:phone":"+1 917 463 2815",
    "sg:postcode":"10025",
    "sg:province":"NY",
    "sg:tags":[
        "wrecker"
    ],
    "wof:name":"All Day Emergency Towing",
    "wof:placetype":"venue"
},
  "geometry": {"coordinates":[-73.96677099999999,40.793977],"type":"Point"}
}