{
  "type": "Feature",
  "properties": {
    "addr:full":"2417 7th Ave New York NY 10030",
    "addr:housenumber":"2417",
    "addr:postcode":"10030",
    "addr:street":"7Th Ave",
    "iso:country":"US",
    "sg:address":"2417 7th Ave",
    "sg:city":"New York",
    "sg:classifiers":[
        {
            "category":"Food & Beverages",
            "subcategory":"Groceries & Convenience Stores",
            "type":"Retail Goods"
        }
    ],
    "sg:phone":"+1 212 491 5159",
    "sg:postcode":"10030",
    "sg:province":"NY",
    "sg:tags":[
        "grocer"
    ],
    "wof:name":"Lara Grocery",
    "wof:placetype":"venue"
},
  "geometry": {"coordinates":[-73.94044,40.819633],"type":"Point"}
}