{
  "type": "Feature",
  "properties": {
    "iso:country":"US",
    "sg:address":"77-20 Jamaica Avenue",
    "sg:city":"Queens",
    "sg:classifiers":[
        {
            "category":"Food & Beverages",
            "subcategory":"Groceries & Convenience Stores",
            "type":"Retail Goods"
        }
    ],
    "sg:phone":"+1 718 296 3627",
    "sg:postcode":"11421",
    "sg:province":"NY",
    "wof:name":"Compare Foods",
    "wof:placetype":"venue"
},
  "geometry": {"coordinates":[-73.864648,40.691718],"type":"Point"}
}