{
  "type": "Feature",
  "properties": {
    "iso:country":"US",
    "sg:address":"8 Woodcliff Ter",
    "sg:city":"Fairport",
    "sg:classifiers":[
        {
            "category":"Building & Trades",
            "subcategory":"Construction",
            "type":"Services"
        }
    ],
    "sg:phone":"+1 585 586 8866",
    "sg:postcode":"14450",
    "sg:province":"NY",
    "sg:tags":[
        "contractor"
    ],
    "wof:name":"Sealcoat Pros",
    "wof:placetype":"venue"
},
  "geometry": {"coordinates":[-77.45438300000001,43.045726],"type":"Point"}
}