{
  "type": "Feature",
  "properties": {
    "iso:country":"US",
    "sg:address":"16 E Fordham Rd",
    "sg:city":"Bronx",
    "sg:classifiers":[
        {
            "category":"Shopping",
            "subcategory":"Department Store",
            "type":"Retail Goods"
        },
        {
            "category":"Shopping",
            "subcategory":"Clothing, Apparel, & Fashions",
            "type":"Retail Goods"
        }
    ],
    "sg:phone":"+1 718 364 6651",
    "sg:postcode":"10468",
    "sg:province":"NY",
    "wof:name":"One Stop Fashions",
    "wof:placetype":"venue"
},
  "geometry": {"coordinates":[-73.900499,40.862491],"type":"Point"}
}