{
  "type": "Feature",
  "properties": {
    "iso:country":"US",
    "sg:address":"13915 243rd St",
    "sg:city":"Rosedale",
    "sg:classifiers":[
        {
            "category":"Professional",
            "subcategory":"Lawyer & Legal Services",
            "type":"Services"
        }
    ],
    "sg:phone":"+1 718 276 0010",
    "sg:postcode":"11422",
    "sg:province":"NY",
    "wof:name":"Sarlis James Atty",
    "wof:placetype":"venue"
},
  "geometry": {"coordinates":[-73.735517,40.665139],"type":"Point"}
}