{
  "type": "Feature",
  "properties": {
    "addr:full":"16 Windham Dr Huntington Sta NY 11746",
    "addr:housenumber":"16",
    "addr:postcode":"11746",
    "addr:street":"Windham Dr",
    "iso:country":"US",
    "sg:address":"16 Windham Dr",
    "sg:city":"Huntington Sta",
    "sg:classifiers":[
        {
            "category":"Professional",
            "subcategory":"Management & Consulting",
            "type":"Services"
        }
    ],
    "sg:phone":"+1 631 547 9116",
    "sg:postcode":"11746",
    "sg:province":"NY",
    "sg:tags":[
        "consultant"
    ],
    "wof:name":"First National Qualified",
    "wof:placetype":"venue"
},
  "geometry": {"coordinates":[-73.391998,40.814392],"type":"Point"}
}