{
  "type": "Feature",
  "properties": {
    "iso:country":"US",
    "sg:address":"5 E 125th St",
    "sg:city":"New York",
    "sg:classifiers":[
        {
            "category":"Education",
            "subcategory":"Vocational School",
            "type":"Public Place"
        }
    ],
    "sg:phone":"+1 212 340 9478",
    "sg:postcode":"10035",
    "sg:province":"NY",
    "sg:tags":[
        "profit",
        "organization",
        "dealing"
    ],
    "wof:name":"Greentree Foundation Inc",
    "wof:placetype":"venue"
},
  "geometry": {"coordinates":[-73.940712,40.805859],"type":"Point"}
}