{
  "type": "Feature",
  "properties": {
    "iso:country":"US",
    "sg:address":"242 Johnson St",
    "sg:city":"East Syracuse",
    "sg:classifiers":[
        {
            "category":"Building & Trades",
            "subcategory":"Construction",
            "type":"Services"
        }
    ],
    "sg:phone":"+1 315 432 1767",
    "sg:postcode":"13057",
    "sg:province":"NY",
    "sg:tags":[
        "pavement",
        "marking",
        "contractor"
    ],
    "wof:name":"Cross & Moore Line Striping",
    "wof:placetype":"venue"
},
  "geometry": {"coordinates":[-76.071382,43.059088],"type":"Point"}
}