{
  "type": "Feature",
  "properties": {
    "addr:full":"1716 Veterans Hwy Islandia NY 11749",
    "addr:housenumber":"1716",
    "addr:postcode":"11749",
    "addr:street":"Veterans Hwy Islandia",
    "iso:country":"US",
    "sg:address":"1716 Veterans Hwy",
    "sg:city":"Islandia",
    "sg:classifiers":[
        {
            "category":"Restaurant",
            "type":"Food & Drink"
        }
    ],
    "sg:menulink":"http://www.allmenus.com/ny/islip/59020-golden-million/menu/",
    "sg:phone":"+1 631 582 1177",
    "sg:postcode":"11749",
    "sg:province":"NY",
    "sg:tags":[
        "asian",
        "chinese"
    ],
    "wof:name":"Golden Million",
    "wof:placetype":"venue"
},
  "geometry": {"coordinates":[-73.18337099999999,40.80735],"type":"Point"}
}