{
  "type": "Feature",
  "properties": {
    "iso:country":"US",
    "sg:address":"15 Carmen Dr",
    "sg:city":"Poughkeepsie",
    "sg:classifiers":[
        {
            "category":"Building & Trades",
            "subcategory":"Plumbing",
            "type":"Services"
        }
    ],
    "sg:phone":"+1 845 463 3661",
    "sg:postcode":"12603",
    "sg:province":"NY",
    "sg:tags":[
        "contractor"
    ],
    "wof:name":"Joseph H Flanagan AC",
    "wof:placetype":"venue"
},
  "geometry": {"coordinates":[-73.88065400000001,41.64859],"type":"Point"}
}