{
  "type": "Feature",
  "properties": {
    "addr:full":"161 Maple St Hudson Falls NY 12839",
    "addr:housenumber":"161",
    "addr:postcode":"12839",
    "addr:street":"Maple St",
    "iso:country":"US",
    "sg:address":"161 Maple St",
    "sg:city":"Hudson Falls",
    "sg:classifiers":[
        {
            "category":"Food & Beverages",
            "subcategory":"Groceries & Convenience Stores",
            "type":"Retail Goods"
        }
    ],
    "sg:phone":"+1 518 747 1133",
    "sg:postcode":"12839",
    "sg:province":"NY",
    "sg:website":"www.cumberlandfarms.com",
    "wof:name":"Cumberland Farms",
    "wof:placetype":"venue"
},
  "geometry": {"coordinates":[-73.572914,43.303735],"type":"Point"}
}