{
  "type": "Feature",
  "properties": {
    "addr:full":"431 E 160th St Bronx NY 10451",
    "addr:housenumber":"431",
    "addr:postcode":"10451",
    "addr:street":"E 160Th St",
    "iso:country":"US",
    "sg:address":"431 E 160th St",
    "sg:city":"Bronx",
    "sg:classifiers":[
        {
            "category":"Utilities",
            "subcategory":"Fuel Oil & Lpg",
            "type":"Services"
        }
    ],
    "sg:phone":"+1   ",
    "sg:postcode":"10451",
    "sg:province":"NY",
    "sg:tags":[
        "dealer"
    ],
    "wof:name":"Peoples Oil Co",
    "wof:placetype":"venue"
},
  "geometry": {"coordinates":[-73.91325000000001,40.823446],"type":"Point"}
}