{
  "type": "Feature",
  "properties": {
    "addr:full":"4246 Hicksville Rd Bethpage NY 11714",
    "addr:housenumber":"4246",
    "addr:postcode":"11714",
    "addr:street":"Hicksville Rd",
    "iso:country":"US",
    "sg:address":"4246 Hicksville Rd",
    "sg:city":"Bethpage",
    "sg:classifiers":[
        {
            "category":"Restaurant",
            "type":"Food & Drink"
        }
    ],
    "sg:phone":"+1 516 579 1282",
    "sg:postcode":"11714",
    "sg:province":"NY",
    "sg:tags":[
        "parlor",
        "ice",
        "cream"
    ],
    "wof:name":"Carvel Ice Cream & Bakery",
    "wof:placetype":"venue"
},
  "geometry": {"coordinates":[-73.48339199999999,40.716223],"type":"Point"}
}