{
  "type": "Feature",
  "properties": {
    "addr:full":"28 W 12 St New York NY 10011",
    "addr:housenumber":"28",
    "addr:postcode":"10011",
    "addr:street":"W 12 St",
    "iso:country":"US",
    "sg:address":"28 W 12 St",
    "sg:city":"New York",
    "sg:classifiers":[
        {
            "category":"Professional",
            "type":"Services"
        }
    ],
    "sg:phone":"+1 212 647 8299",
    "sg:postcode":"10011",
    "sg:province":"NY",
    "sg:tags":[
        "establishment"
    ],
    "wof:name":"Derspiegal Publisher",
    "wof:placetype":"venue"
},
  "geometry": {"coordinates":[-73.997181,40.735598],"type":"Point"}
}