{
  "type": "Feature",
  "properties": {
    "iso:country":"US",
    "sg:address":"127 Lena Ter",
    "sg:city":"Syracuse",
    "sg:classifiers":[
        {
            "category":"Wholesale",
            "subcategory":"Office Equipment",
            "type":"Manufacturing & Wholesale Goods"
        }
    ],
    "sg:phone":"+1 315 453 2033",
    "sg:postcode":"13212",
    "sg:province":"NY",
    "wof:name":"Express Mailing Systems-Ascom",
    "wof:placetype":"venue"
},
  "geometry": {"coordinates":[-76.146793,43.141054],"type":"Point"}
}