{
  "type": "Feature",
  "properties": {
    "addr:full":"52 S Portage St Westfield NY 14787",
    "addr:housenumber":"52",
    "addr:postcode":"14787",
    "addr:street":"S Portage St",
    "iso:country":"US",
    "sg:address":"52 S Portage St",
    "sg:city":"Westfield",
    "sg:classifiers":[
        {
            "category":"Retail",
            "subcategory":"Funeral Services",
            "type":"Services"
        }
    ],
    "sg:phone":"+1 716 326 3232",
    "sg:postcode":"14787",
    "sg:province":"NY",
    "sg:tags":[
        "director"
    ],
    "wof:name":"Fantauzzi Funeral Home",
    "wof:placetype":"venue"
},
  "geometry": {"coordinates":[-79.577327,42.320552],"type":"Point"}
}