{
  "type": "Feature",
  "properties": {
    "iso:country":"US",
    "sg:address":"104 Main St",
    "sg:city":"Silver Creek",
    "sg:classifiers":[
        {
            "category":"Building & Trades",
            "subcategory":"Construction",
            "type":"Services"
        }
    ],
    "sg:phone":"+1 716 934 2658",
    "sg:postcode":"14136",
    "sg:province":"NY",
    "sg:tags":[
        "water",
        "well",
        "drilling"
    ],
    "wof:name":"Ehmke Well Drillers Inc",
    "wof:placetype":"venue"
},
  "geometry": {"coordinates":[-79.16982899999999,42.537824],"type":"Point"}
}