{
  "type": "Feature",
  "properties": {
    "addr:full":"25 Woodard Rd Monroe NY 10950",
    "addr:housenumber":"25",
    "addr:postcode":"10950",
    "addr:street":"Woodard Rd",
    "iso:country":"US",
    "sg:address":"25 Woodard Rd",
    "sg:city":"Monroe",
    "sg:classifiers":[
        {
            "category":"Social Services",
            "type":"Services"
        }
    ],
    "sg:phone":"+1 845 496 7186",
    "sg:postcode":"10950",
    "sg:province":"NY",
    "sg:tags":[
        "support",
        "group"
    ],
    "wof:name":"Parents Of Hearing Impaired",
    "wof:placetype":"venue"
},
  "geometry": {"coordinates":[-74.135666,41.398767],"type":"Point"}
}