{
  "type": "Feature",
  "properties": {
    "addr:full":"19 Jay St New York NY 10013",
    "addr:housenumber":"19",
    "addr:postcode":"10013",
    "addr:street":"Jay St",
    "iso:country":"US",
    "sg:address":"19 Jay St",
    "sg:city":"New York",
    "sg:classifiers":[
        {
            "category":"Communications",
            "subcategory":"Film & Video Production",
            "type":"Services"
        }
    ],
    "sg:phone":"+1 212 941 4646",
    "sg:postcode":"10013",
    "sg:province":"NY",
    "sg:tags":[
        "motion",
        "picture",
        "television",
        "producer"
    ],
    "wof:name":"Polar Entertainment Corp",
    "wof:placetype":"venue"
},
  "geometry": {"coordinates":[-74.010026,40.718113],"type":"Point"}
}