{
  "type": "Feature",
  "properties": {
    "addr:full":"15 Ave B Johnson City NY 13790",
    "addr:postcode":"13790",
    "addr:street":"15 Ave B",
    "iso:country":"US",
    "sg:address":"15 Ave B",
    "sg:city":"Johnson City",
    "sg:classifiers":[
        {
            "category":"Professional",
            "subcategory":"Detective & Security Services",
            "type":"Services"
        }
    ],
    "sg:phone":"+1 607 773 1344",
    "sg:postcode":"13790",
    "sg:province":"NY",
    "sg:tags":[
        "investigator"
    ],
    "wof:name":"Albright Investigative Assoc",
    "wof:placetype":"venue"
},
  "geometry": {"coordinates":[-75.953185,42.115299],"type":"Point"}
}