{
  "type": "Feature",
  "properties": {
    "iso:country":"US",
    "sg:address":"16 Woodmere Pl",
    "sg:city":"Selden",
    "sg:classifiers":[
        {
            "category":"Building & Trades",
            "subcategory":"Plumbing",
            "type":"Services"
        }
    ],
    "sg:phone":"+1 631 366 2116",
    "sg:postcode":"11784",
    "sg:province":"NY",
    "sg:tags":[
        "plumbing",
        "contractor"
    ],
    "wof:name":"Motta S Cesspool & Excavation",
    "wof:placetype":"venue"
},
  "geometry": {"coordinates":[-73.038217,40.865027],"type":"Point"}
}