{
  "type": "Feature",
  "properties": {
    "iso:country":"US",
    "sg:address":"383 Knickerbocker Ave",
    "sg:city":"Brooklyn",
    "sg:classifiers":[
        {
            "category":"Shopping",
            "subcategory":"Clothing, Apparel, & Fashions",
            "type":"Retail Goods"
        }
    ],
    "sg:phone":"+1   ",
    "sg:postcode":"11237",
    "sg:province":"NY",
    "sg:tags":[
        "family"
    ],
    "wof:name":"Plaza Youth Center Inc",
    "wof:placetype":"venue"
},
  "geometry": {"coordinates":[-73.92162999999999,40.700675],"type":"Point"}
}