{
  "type": "Feature",
  "properties": {
    "addr:full":"193 Lancaster Ave Buffalo NY 14222",
    "addr:housenumber":"193",
    "addr:postcode":"14222",
    "addr:street":"Lancaster Ave",
    "iso:country":"US",
    "sg:address":"193 Lancaster Ave",
    "sg:city":"Buffalo",
    "sg:classifiers":[
        {
            "category":"Home & Garden",
            "subcategory":"Building Materials",
            "type":"Retail Goods"
        }
    ],
    "sg:phone":"+1 716 854 1744",
    "sg:postcode":"14222",
    "sg:province":"NY",
    "wof:name":"Alliance Franc Aise De Buf",
    "wof:placetype":"venue"
},
  "geometry": {"coordinates":[-78.874161,42.91946],"type":"Point"}
}