{
  "type": "Feature",
  "properties": {
    "iso:country":"US",
    "sg:address":"259 Main St",
    "sg:city":"Cornwall",
    "sg:classifiers":[
        {
            "category":"Professional",
            "subcategory":"Business Services",
            "type":"Services"
        }
    ],
    "sg:phone":"+1 845 534 5636",
    "sg:postcode":"12518",
    "sg:province":"NY",
    "sg:tags":[
        "interior",
        "consultant",
        "design",
        "decorator"
    ],
    "wof:name":"Gift Horse Interiors",
    "wof:placetype":"venue"
},
  "geometry": {"coordinates":[-74.03258099999999,41.436097],"type":"Point"}
}