{
  "type": "Feature",
  "properties": {
    "addr:full":"19301 Northern Blvd Flushing NY 11358",
    "addr:housenumber":"19301",
    "addr:postcode":"11358",
    "addr:street":"Northern Blvd",
    "iso:country":"US",
    "sg:address":"19301 Northern Blvd",
    "sg:city":"Flushing",
    "sg:classifiers":[
        {
            "category":"Wholesale",
            "subcategory":"Medical Equipment & Supplies",
            "type":"Manufacturing & Wholesale Goods"
        },
        {
            "category":"Shopping",
            "subcategory":"Beauty & Cosmetics",
            "type":"Retail Goods"
        },
        {
            "category":"Food & Beverages",
            "subcategory":"Specialty",
            "type":"Retail Goods"
        },
        {
            "category":"Shopping",
            "subcategory":"Gifts & Souvenirs",
            "type":"Retail Goods"
        },
        {
            "category":"Retail",
            "subcategory":"Photofinishing",
            "type":"Services"
        },
        {
            "category":"Shopping",
            "subcategory":"Pharmacy",
            "type":"Retail Goods"
        }
    ],
    "sg:phone":"+1 718 357 2050",
    "sg:postcode":"11358",
    "sg:province":"NY",
    "sg:tags":[
        "product",
        "photo",
        "vitamin",
        "perfume",
        "supplement",
        "health",
        "wellness",
        "aid",
        "finishing",
        "first",
        "card",
        "greeting"
    ],
    "sg:website":"http://www.riteaid.com",
    "wof:name":"Rite Aid",
    "wof:placetype":"venue"
},
  "geometry": {"coordinates":[-73.804592,40.7626],"type":"Point"}
}