{
  "type": "Feature",
  "properties": {
    "iso:country":"US",
    "sg:address":"1109 State Hwy 41",
    "sg:city":"Deposit",
    "sg:classifiers":[
        {
            "category":"Freight",
            "type":"Transportation"
        }
    ],
    "sg:phone":"+1   ",
    "sg:postcode":"13754",
    "sg:province":"NY",
    "sg:tags":[
        "operator",
        "local",
        "trucking"
    ],
    "wof:name":"Ken Strong Hauling",
    "wof:placetype":"venue"
},
  "geometry": {"coordinates":[-75.493126,42.119017],"type":"Point"}
}