{
  "type": "Feature",
  "properties": {
    "addr:full":"505 Pinyon Dr Schenectady NY 12303",
    "addr:housenumber":"505",
    "addr:postcode":"12303",
    "addr:street":"Pinyon Dr",
    "iso:country":"US",
    "sg:address":"505 Pinyon Dr",
    "sg:city":"Schenectady",
    "sg:classifiers":[
        {
            "category":"Personal",
            "subcategory":"Beauty Salon",
            "type":"Services"
        }
    ],
    "sg:phone":"+1   ",
    "sg:postcode":"12303",
    "sg:province":"NY",
    "sg:tags":[
        "shop",
        "barber"
    ],
    "wof:name":"Josephs Mens Styling",
    "wof:placetype":"venue"
},
  "geometry": {"coordinates":[-73.93535,42.730817],"type":"Point"}
}