{
  "type": "Feature",
  "properties": {
    "iso:country":"US",
    "sg:address":"1463 Co Rd 39",
    "sg:city":"Worcester",
    "sg:classifiers":[
        {
            "category":"Banks & Credit Unions",
            "subcategory":"Bank",
            "type":"Services"
        }
    ],
    "sg:phone":"+1 607 397 9354",
    "sg:postcode":"12197",
    "sg:province":"NY",
    "sg:tags":[
        "short",
        "institution",
        "business"
    ],
    "wof:name":"Southworth Tees",
    "wof:placetype":"venue"
},
  "geometry": {"coordinates":[-74.75256299999999,42.595346],"type":"Point"}
}