{
  "type": "Feature",
  "properties": {
    "addr:full":"1706 E 172nd St Bronx NY 10472",
    "addr:housenumber":"1706",
    "addr:postcode":"10472",
    "addr:street":"E 172Nd St",
    "iso:country":"US",
    "sg:address":"1706 E 172nd St",
    "sg:city":"Bronx",
    "sg:classifiers":[
        {
            "category":"Arena",
            "subcategory":"Sports Club",
            "type":"Entertainment"
        }
    ],
    "sg:phone":"+1 718 378 1433",
    "sg:postcode":"10472",
    "sg:province":"NY",
    "wof:name":"Day Star Audio Co",
    "wof:placetype":"venue"
},
  "geometry": {"coordinates":[-73.87059600000001,40.832289],"type":"Point"}
}