{
  "type": "Feature",
  "properties": {
    "iso:country":"US",
    "sg:address":"187 W Islip Rd",
    "sg:city":"West Islip",
    "sg:classifiers":[
        {
            "category":"Personal",
            "subcategory":"Tanning Parlor",
            "type":"Services"
        }
    ],
    "sg:phone":"+1 631 587 1212",
    "sg:postcode":"11795",
    "sg:province":"NY",
    "sg:tags":[
        "salon"
    ],
    "wof:name":"Planet Beach Tanning Salon",
    "wof:placetype":"venue"
},
  "geometry": {"coordinates":[-73.316805,40.693879],"type":"Point"}
}