{
  "type": "Feature",
  "properties": {
    "addr:full":"105 Valley Ln Horseheads NY 14845",
    "addr:housenumber":"105",
    "addr:postcode":"14845",
    "addr:street":"Valley Ln",
    "iso:country":"US",
    "sg:address":"105 Valley Ln",
    "sg:city":"Horseheads",
    "sg:classifiers":[
        {
            "category":"Restaurant",
            "type":"Food & Drink"
        }
    ],
    "sg:phone":"+1 607 733 2425",
    "sg:postcode":"14845",
    "sg:province":"NY",
    "sg:tags":[
        "caterer"
    ],
    "wof:name":"Humingbird Catering & Bakery",
    "wof:placetype":"venue"
},
  "geometry": {"coordinates":[-76.799617,42.191666],"type":"Point"}
}