{
  "type": "Feature",
  "properties": {
    "addr:full":"15535 116th Dr Jamaica NY 11434",
    "addr:housenumber":"15535",
    "addr:postcode":"11434",
    "addr:street":"116Th Dr",
    "iso:country":"US",
    "sg:address":"15535 116th Dr",
    "sg:city":"Jamaica",
    "sg:classifiers":[
        {
            "category":"Building & Trades",
            "subcategory":"Cleaning & Sanitation",
            "type":"Services"
        }
    ],
    "sg:phone":"+1 718 529 6433",
    "sg:postcode":"11434",
    "sg:province":"NY",
    "sg:tags":[
        "cleaning-industrial",
        "contractor"
    ],
    "wof:name":"Cintg Management Inc",
    "wof:placetype":"venue"
},
  "geometry": {"coordinates":[-73.78805699999999,40.68292],"type":"Point"}
}