{
  "type": "Feature",
  "properties": {
    "iso:country":"US",
    "sg:address":"381 Hamilton St",
    "sg:city":"Geneva",
    "sg:classifiers":[
        {
            "category":"Shopping",
            "subcategory":"Clothing, Apparel, & Fashions",
            "type":"Retail Goods"
        },
        {
            "category":"Shopping",
            "subcategory":"Department Store",
            "type":"Retail Goods"
        },
        {
            "category":"Shopping",
            "subcategory":"Shoes",
            "type":"Retail Goods"
        }
    ],
    "sg:postcode":"14456",
    "sg:province":"NY",
    "sg:tags":[
        "men's",
        "women's",
        "apparel",
        "clothing",
        "boys'",
        "sportswear"
    ],
    "sg:website":"http://promotion.peebles.com/promotion.php?referrer=PPC&subreferrer=N&landing=LPA&utm_source=Superpages&utm_medium=PPC&utm_campaign=Superpages",
    "wof:name":"Peebles Stores Exclusive Offer",
    "wof:placetype":"venue"
},
  "geometry": {"coordinates":[-76.99905099999999,42.857931],"type":"Point"}
}