{
  "type": "Feature",
  "properties": {
    "addr:full":"4226 28th Street Long Island City NY 11101",
    "addr:housenumber":"4226",
    "addr:postcode":"11101",
    "addr:street":"28Th Street",
    "iso:country":"US",
    "sg:address":"4226 28th Street",
    "sg:city":"Long Island City",
    "sg:classifiers":[
        {
            "category":"Building & Trades",
            "subcategory":"Construction",
            "type":"Services"
        }
    ],
    "sg:phone":"+1 718 729 5751",
    "sg:postcode":"11101",
    "sg:province":"NY",
    "sg:tags":[
        "contractor"
    ],
    "wof:name":"Creative Renovations",
    "wof:placetype":"venue"
},
  "geometry": {"coordinates":[-73.939198,40.749632],"type":"Point"}
}