{
  "type": "Feature",
  "properties": {
    "addr:full":"25 Mott Ave Far Rockaway NY 11691",
    "addr:housenumber":"25",
    "addr:postcode":"11691",
    "addr:street":"Mott Ave",
    "iso:country":"US",
    "sg:address":"25 Mott Ave",
    "sg:city":"Far Rockaway",
    "sg:classifiers":[
        {
            "category":"Shopping",
            "subcategory":"Jewelry",
            "type":"Retail Goods"
        }
    ],
    "sg:phone":"+1   ",
    "sg:postcode":"11691",
    "sg:province":"NY",
    "wof:name":"Gold Fashion",
    "wof:placetype":"venue"
},
  "geometry": {"coordinates":[-73.76599299999999,40.60935],"type":"Point"}
}