{
  "type": "Feature",
  "properties": {
    "addr:full":"500 Canal View Blvd Rochester NY 14623",
    "addr:housenumber":"500",
    "addr:postcode":"14623",
    "addr:street":"Canal View Blvd",
    "iso:country":"US",
    "sg:address":"500 Canal View Blvd",
    "sg:city":"Rochester",
    "sg:classifiers":[
        {
            "category":"Shopping",
            "type":"Retail Goods"
        }
    ],
    "sg:phone":"+1   ",
    "sg:postcode":"14623",
    "sg:province":"NY",
    "sg:tags":[
        "aids",
        "educational",
        "material",
        "electronic",
        "training"
    ],
    "wof:name":"Element K Content LLC",
    "wof:placetype":"venue"
},
  "geometry": {"coordinates":[-77.586232,43.098123],"type":"Point"}
}