{
  "type": "Feature",
  "properties": {
    "addr:full":"122 Main St Cornwall NY 12518",
    "addr:housenumber":"122",
    "addr:postcode":"12518",
    "addr:street":"Main St",
    "iso:country":"US",
    "sg:address":"122 Main St",
    "sg:city":"Cornwall",
    "sg:classifiers":[
        {
            "category":"Education",
            "subcategory":"School",
            "type":"Public Place"
        }
    ],
    "sg:phone":"+1 845 534 8939",
    "sg:postcode":"12518",
    "sg:province":"NY",
    "wof:name":"Corwall Central High School",
    "wof:placetype":"venue"
},
  "geometry": {"coordinates":[-74.029417,41.444613],"type":"Point"}
}