{
  "type": "Feature",
  "properties": {
    "addr:full":"17 1st Ave New York NY 10003",
    "addr:housenumber":"17",
    "addr:postcode":"10003",
    "addr:street":"1St Ave",
    "iso:country":"US",
    "sg:address":"17 1st Ave",
    "sg:city":"New York",
    "sg:classifiers":[
        {
            "category":"Building & Trades",
            "subcategory":"Locksmith",
            "type":"Services"
        }
    ],
    "sg:phone":"+1 212 475 6840",
    "sg:postcode":"10003",
    "sg:province":"NY",
    "sg:tags":[
        "key"
    ],
    "sg:website":"www.speedylockanddoor.com",
    "wof:name":"Speedy Lock & Door Company",
    "wof:placetype":"venue"
},
  "geometry": {"coordinates":[-73.988527,40.723528],"type":"Point"}
}