{
  "type": "Feature",
  "properties": {
    "addr:full":"50 Hempstead Ave Ste K Lynbrook NY 11563",
    "addr:housenumber":"50",
    "addr:postcode":"11563",
    "addr:street":"Hempstead Ave Ste K",
    "iso:country":"US",
    "sg:address":"50 Hempstead Ave Ste K",
    "sg:city":"Lynbrook",
    "sg:classifiers":[
        {
            "category":"Health Services",
            "subcategory":"Dentist",
            "type":"Services"
        }
    ],
    "sg:phone":"+1 516 593 9228",
    "sg:postcode":"11563",
    "sg:province":"NY",
    "wof:name":"Horowitz Carole DMD",
    "wof:placetype":"venue"
},
  "geometry": {"coordinates":[-73.670998,40.659401],"type":"Point"}
}