{
  "type": "Feature",
  "properties": {
    "addr:full":"16 Croton Ave Ossining NY 10562",
    "addr:housenumber":"16",
    "addr:postcode":"10562",
    "addr:street":"Croton Ave",
    "iso:country":"US",
    "sg:address":"16 Croton Ave",
    "sg:city":"Ossining",
    "sg:classifiers":[
        {
            "category":"Government",
            "subcategory":"Office",
            "type":"Public Place"
        }
    ],
    "sg:phone":"+1 914 941 2581",
    "sg:postcode":"10562",
    "sg:province":"NY",
    "sg:tags":[
        "executive"
    ],
    "wof:name":"Finance Dept",
    "wof:placetype":"venue"
},
  "geometry": {"coordinates":[-73.854091,41.166508],"type":"Point"}
}