{
  "type": "Feature",
  "properties": {
    "iso:country":"US",
    "sg:address":"45 Arden Ave",
    "sg:city":"Staten Island",
    "sg:classifiers":[
        {
            "category":"Home & Garden",
            "subcategory":"Carpets & Floor Coverings",
            "type":"Retail Goods"
        }
    ],
    "sg:phone":"+1 718 982 8333",
    "sg:postcode":"10312",
    "sg:province":"NY",
    "sg:tags":[
        "dealer",
        "rug"
    ],
    "wof:name":"Galaxy Carpet & Floor Care Inc",
    "wof:placetype":"venue"
},
  "geometry": {"coordinates":[-74.19728600000001,40.55882],"type":"Point"}
}