{
  "type": "Feature",
  "properties": {
    "addr:full":"671 Mill St Watertown NY 13601",
    "addr:housenumber":"671",
    "addr:postcode":"13601",
    "addr:street":"Mill St",
    "iso:country":"US",
    "sg:address":"671 Mill St",
    "sg:city":"Watertown",
    "sg:phone":"+1 315 788 9916",
    "sg:postcode":"13601",
    "sg:province":"NY",
    "wof:name":"Trip On Wild Side",
    "wof:placetype":"venue"
},
  "geometry": {"coordinates":[-75.905809,43.982932],"type":"Point"}
}