{
  "type": "Feature",
  "properties": {
    "addr:full":"790 Railroad Ave West Babylon NY 11704",
    "addr:housenumber":"790",
    "addr:postcode":"11704",
    "addr:street":"Railroad Ave",
    "iso:country":"US",
    "sg:address":"790 Railroad Ave",
    "sg:city":"West Babylon",
    "sg:classifiers":[
        {
            "category":"Manufacturing",
            "subcategory":"Retail Goods",
            "type":"Manufacturing & Wholesale Goods"
        }
    ],
    "sg:phone":"+1 631 321 7161",
    "sg:postcode":"11704",
    "sg:province":"NY",
    "sg:tags":[
        "manufacturer"
    ],
    "wof:name":"East Penn Mfg Co",
    "wof:placetype":"venue"
},
  "geometry": {"coordinates":[-73.35344000000001,40.692086],"type":"Point"}
}