{
  "type": "Feature",
  "properties": {
    "addr:full":"7 Maple Ave Ripley NY 14775",
    "addr:housenumber":"7",
    "addr:postcode":"14775",
    "addr:street":"Maple Ave",
    "iso:country":"US",
    "sg:address":"7 Maple Ave",
    "sg:city":"Ripley",
    "sg:classifiers":[
        {
            "category":"Real Estate",
            "subcategory":"Surveying",
            "type":"Services"
        }
    ],
    "sg:phone":"+1 716 736 5263",
    "sg:postcode":"14775",
    "sg:province":"NY",
    "sg:tags":[
        "surveyor",
        "engineer"
    ],
    "wof:name":"Nypenn Surveying P",
    "wof:placetype":"venue"
},
  "geometry": {"coordinates":[-79.715942,42.263656],"type":"Point"}
}