{
  "type": "Feature",
  "properties": {
    "addr:full":"80 5th Ave New York NY 10011",
    "addr:housenumber":"80",
    "addr:postcode":"10011",
    "addr:street":"5Th Ave",
    "iso:country":"US",
    "sg:address":"80 5th Ave",
    "sg:city":"New York",
    "sg:classifiers":[
        {
            "category":"Health Services",
            "subcategory":"Doctor",
            "type":"Services"
        }
    ],
    "sg:phone":"+1 212 627 9119",
    "sg:postcode":"10011",
    "sg:province":"NY",
    "sg:tags":[
        "physician",
        "surgeon"
    ],
    "wof:name":"Greenwich Medical Anesthesia",
    "wof:placetype":"venue"
},
  "geometry": {"coordinates":[-73.994118,40.735313],"type":"Point"}
}