{
  "type": "Feature",
  "properties": {
    "addr:full":"Lifestyle Skin Technology 30 E 67th St Manhattan NY 10065",
    "addr:housenumber":"30",
    "addr:postcode":"10065",
    "addr:street":"E 67Th St",
    "iso:country":"US",
    "sg:address":"Lifestyle Skin Technology 30 E 67th St",
    "sg:city":"Manhattan",
    "sg:classifiers":[
        {
            "category":"Health Services",
            "subcategory":"Clinic",
            "type":"Services"
        },
        {
            "category":"Personal",
            "subcategory":"Skin Care",
            "type":"Services"
        }
    ],
    "sg:phone":"+1 917 650 3408",
    "sg:postcode":"10065",
    "sg:province":"NY",
    "sg:tags":[
        "spa",
        "medical"
    ],
    "wof:name":"Nicole DeVincentis, RPA",
    "wof:placetype":"venue"
},
  "geometry": {"coordinates":[-73.96774600000001,40.768584],"type":"Point"}
}