{
  "type": "Feature",
  "properties": {
    "iso:country":"US",
    "sg:address":"1573 Brentwood Rd",
    "sg:city":"Bay Shore",
    "sg:classifiers":[
        {
            "category":"Autos & Motor Vehicles",
            "subcategory":"Fuel & Gas Station",
            "type":"Retail Goods"
        }
    ],
    "sg:phone":"+1 631 665 5467",
    "sg:postcode":"11706",
    "sg:province":"NY",
    "wof:name":"Taner Auto Inc",
    "wof:placetype":"venue"
},
  "geometry": {"coordinates":[-73.245499,40.757599],"type":"Point"}
}