{
  "type": "Feature",
  "properties": {
    "addr:full":"7146 110th Street Forest Hills NY 11375",
    "addr:housenumber":"7146",
    "addr:postcode":"11375",
    "addr:street":"110Th Street",
    "iso:country":"US",
    "sg:address":"7146 110th Street",
    "sg:city":"Forest Hills",
    "sg:classifiers":[
        {
            "category":"Health Services",
            "subcategory":"Doctor",
            "type":"Services"
        }
    ],
    "sg:phone":"+1 718 261 2500",
    "sg:postcode":"11375",
    "sg:province":"NY",
    "wof:name":"Friedman Mark MD",
    "wof:placetype":"venue"
},
  "geometry": {"coordinates":[-73.84114599999999,40.721462],"type":"Point"}
}