{
  "type": "Feature",
  "properties": {
    "iso:country":"US",
    "sg:address":"172 Madison Ave",
    "sg:city":"New York",
    "sg:classifiers":[
        {
            "category":"Wholesale",
            "subcategory":"Stationery",
            "type":"Manufacturing & Wholesale Goods"
        }
    ],
    "sg:phone":"+1 212 252 8988",
    "sg:postcode":"10016",
    "sg:province":"NY",
    "sg:tags":[
        "supply",
        "furniture"
    ],
    "wof:name":"Asian Hispanic Trdg Consulting",
    "wof:placetype":"venue"
},
  "geometry": {"coordinates":[-73.982957,40.747765],"type":"Point"}
}