{
  "type": "Feature",
  "properties": {
    "addr:full":"443 Bay Ridge Pkwy Brooklyn NY 11209",
    "addr:housenumber":"443",
    "addr:postcode":"11209",
    "addr:street":"Bay Ridge Pkwy",
    "iso:country":"US",
    "sg:address":"443 Bay Ridge Pkwy",
    "sg:city":"Brooklyn",
    "sg:classifiers":[
        {
            "category":"Health Services",
            "subcategory":"Doctor",
            "type":"Services"
        }
    ],
    "sg:phone":"+1 718 680 8105",
    "sg:postcode":"11209",
    "sg:province":"NY",
    "sg:tags":[
        "physician",
        "surgeon"
    ],
    "wof:name":"Idan Sharon MD",
    "wof:placetype":"venue"
},
  "geometry": {"coordinates":[-74.023374,40.630167],"type":"Point"}
}