{
  "type": "Feature",
  "properties": {
    "iso:country":"US",
    "sg:address":"62 E Main St",
    "sg:city":"Wappingers Falls",
    "sg:classifiers":[
        {
            "category":"Professional",
            "subcategory":"Lawyer & Legal Services",
            "type":"Services"
        }
    ],
    "sg:phone":"+1 845 297 4777",
    "sg:postcode":"12590",
    "sg:province":"NY",
    "wof:name":"Robert Tendy Atty",
    "wof:placetype":"venue"
},
  "geometry": {"coordinates":[-73.915744,41.597382],"type":"Point"}
}