{
  "type": "Feature",
  "properties": {
    "addr:full":"15 Windcrest Dr Fort Edward NY 12828",
    "addr:housenumber":"15",
    "addr:postcode":"12828",
    "addr:street":"Windcrest Dr",
    "iso:country":"US",
    "sg:address":"15 Windcrest Dr",
    "sg:city":"Fort Edward",
    "sg:classifiers":[
        {
            "category":"Building & Trades",
            "subcategory":"Construction",
            "type":"Services"
        }
    ],
    "sg:phone":"+1 518 747 8122",
    "sg:postcode":"12828",
    "sg:province":"NY",
    "sg:tags":[
        "paving",
        "contractor"
    ],
    "wof:name":"Greenough Paving",
    "wof:placetype":"venue"
},
  "geometry": {"coordinates":[-73.59405,43.276195],"type":"Point"}
}