{
  "type": "Feature",
  "properties": {
    "addr:full":"1335 Central Ave Albany NY 12205",
    "addr:housenumber":"1335",
    "addr:postcode":"12205",
    "addr:street":"Central Ave",
    "iso:country":"US",
    "sg:address":"1335 Central Ave",
    "sg:city":"Albany",
    "sg:classifiers":[
        {
            "category":"Restaurant",
            "type":"Food & Drink"
        }
    ],
    "sg:phone":"+1   ",
    "sg:postcode":"12205",
    "sg:province":"NY",
    "sg:tags":[
        "eating"
    ],
    "wof:name":"Wendys",
    "wof:placetype":"venue"
},
  "geometry": {"coordinates":[-73.81483799999999,42.701809],"type":"Point"}
}