{
  "type": "Feature",
  "properties": {
    "iso:country":"US",
    "sg:address":"7526 37th Avenue",
    "sg:city":"Flushing",
    "sg:classifiers":[
        {
            "category":"Personal",
            "subcategory":"Barber",
            "type":"Services"
        }
    ],
    "sg:phone":"+1 718 429 6841",
    "sg:postcode":"11372",
    "sg:province":"NY",
    "wof:name":"Heads Ain't Ready",
    "wof:placetype":"venue"
},
  "geometry": {"coordinates":[-73.889996,40.749037],"type":"Point"}
}