{
  "type": "Feature",
  "properties": {
    "addr:full":"40 E 52nd Street New York NY 10022",
    "addr:housenumber":"40",
    "addr:postcode":"10022",
    "addr:street":"E 52Nd Street",
    "iso:country":"US",
    "sg:address":"40 E 52nd Street",
    "sg:city":"New York",
    "sg:classifiers":[
        {
            "category":"Banks & Credit Unions",
            "subcategory":"Financial Services",
            "type":"Services"
        }
    ],
    "sg:phone":"+1 212 224 8240",
    "sg:postcode":"10022",
    "sg:province":"NY",
    "sg:website":"www.blackrock.com",
    "wof:name":"BlackRock",
    "wof:placetype":"venue"
},
  "geometry": {"coordinates":[-73.974401,40.75898],"type":"Point"}
}