{
  "type": "Feature",
  "properties": {
    "addr:full":"12 Connelly Dr Staatsburg NY 12580",
    "addr:housenumber":"12",
    "addr:postcode":"12580",
    "addr:street":"Connelly Dr",
    "iso:country":"US",
    "sg:address":"12 Connelly Dr",
    "sg:city":"Staatsburg",
    "sg:classifiers":[
        {
            "category":"Building & Trades",
            "subcategory":"Plumbing",
            "type":"Services"
        }
    ],
    "sg:phone":"+1 845 889 8228",
    "sg:postcode":"12580",
    "sg:province":"NY",
    "sg:tags":[
        "contractor"
    ],
    "wof:name":"Noonan Plumbing & Heating Inc",
    "wof:placetype":"venue"
},
  "geometry": {"coordinates":[-73.895875,41.841367],"type":"Point"}
}