{
  "type": "Feature",
  "properties": {
    "iso:country":"US",
    "sg:address":"590 E 187th Street",
    "sg:city":"Bronx",
    "sg:classifiers":[
        {
            "category":"Banks & Credit Unions",
            "subcategory":"Bank",
            "type":"Services"
        }
    ],
    "sg:phone":"+1 718 584 7400",
    "sg:postcode":"10458",
    "sg:province":"NY",
    "wof:name":"Fourth Federal Savings Bank",
    "wof:placetype":"venue"
},
  "geometry": {"coordinates":[-73.887822,40.855688],"type":"Point"}
}