{
  "type": "Feature",
  "properties": {
    "addr:full":"590 E 187th Street Bronx NY 10458",
    "addr:housenumber":"590",
    "addr:postcode":"10458",
    "addr:street":"E 187Th Street",
    "iso:country":"US",
    "sg:address":"590 E 187th Street",
    "sg:city":"Bronx",
    "sg:classifiers":[
        {
            "category":"Banks & Credit Unions",
            "subcategory":"Bank",
            "type":"Services"
        }
    ],
    "sg:phone":"+1 718 584 7400",
    "sg:postcode":"10458",
    "sg:province":"NY",
    "wof:name":"Fourth Federal Savings Bank",
    "wof:placetype":"venue"
},
  "geometry": {"coordinates":[-73.887822,40.855688],"type":"Point"}
}