{
  "type": "Feature",
  "properties": {
    "addr:full":"306 Margaret Blvd Merrick NY 11566",
    "addr:housenumber":"306",
    "addr:postcode":"11566",
    "addr:street":"Margaret Blvd",
    "iso:country":"US",
    "sg:address":"306 Margaret Blvd",
    "sg:city":"Merrick",
    "sg:classifiers":[
        {
            "category":"Wholesale",
            "subcategory":"Drugs",
            "type":"Manufacturing & Wholesale Goods"
        }
    ],
    "sg:phone":"+1 516 868 9111",
    "sg:postcode":"11566",
    "sg:province":"NY",
    "sg:tags":[
        "aids",
        "health",
        "beauty"
    ],
    "wof:name":"Powers Martin Sales Inc",
    "wof:placetype":"venue"
},
  "geometry": {"coordinates":[-73.545588,40.673421],"type":"Point"}
}