{
  "type": "Feature",
  "properties": {
    "addr:full":"47 Thorne Ave Hempstead NY 11550",
    "addr:housenumber":"47",
    "addr:postcode":"11550",
    "addr:street":"Thorne Ave",
    "iso:country":"US",
    "sg:address":"47 Thorne Ave",
    "sg:city":"Hempstead",
    "sg:classifiers":[
        {
            "category":"Food & Beverages",
            "subcategory":"Bakery",
            "type":"Retail Goods"
        }
    ],
    "sg:phone":"+1   ",
    "sg:postcode":"11550",
    "sg:province":"NY",
    "wof:name":"Real World Bakery Corp",
    "wof:placetype":"venue"
},
  "geometry": {"coordinates":[-73.61504600000001,40.703124],"type":"Point"}
}