{
  "type": "Feature",
  "properties": {
    "addr:full":"404 Grand St New York NY 10002",
    "addr:housenumber":"404",
    "addr:postcode":"10002",
    "addr:street":"Grand St",
    "iso:country":"US",
    "sg:address":"404 Grand St",
    "sg:city":"New York",
    "sg:classifiers":[
        {
            "category":"Restaurant",
            "type":"Food & Drink"
        }
    ],
    "sg:phone":"+1   ",
    "sg:postcode":"10002",
    "sg:province":"NY",
    "wof:name":"Metrazur Restaurant",
    "wof:placetype":"venue"
},
  "geometry": {"coordinates":[-73.987233,40.716236],"type":"Point"}
}