{
  "type": "Feature",
  "properties": {
    "iso:country":"US",
    "sg:address":"110 S Work St",
    "sg:city":"Falconer",
    "sg:classifiers":[
        {
            "category":"Food & Beverages",
            "subcategory":"Groceries & Convenience Stores",
            "type":"Retail Goods"
        }
    ],
    "sg:phone":"+1 716 665 1150",
    "sg:postcode":"14733",
    "sg:province":"NY",
    "sg:tags":[
        "grocer",
        "supermarket",
        "pharmacy"
    ],
    "sg:website":"www.qualitymarkets.com",
    "wof:name":"Quality Markets",
    "wof:placetype":"venue"
},
  "geometry": {"coordinates":[-79.196628,42.118199],"type":"Point"}
}