{
  "type": "Feature",
  "properties": {
    "addr:full":"55 Columbia St New York NY 10002",
    "addr:housenumber":"55",
    "addr:postcode":"10002",
    "addr:street":"Columbia",
    "iso:country":"US",
    "sg:address":"55 Columbia St",
    "sg:city":"New York",
    "sg:classifiers":[
        {
            "category":"Shopping",
            "subcategory":"Pharmacy",
            "type":"Retail Goods"
        }
    ],
    "sg:phone":"+1 212 533 8120",
    "sg:postcode":"10002",
    "sg:province":"NY",
    "wof:name":"Clearfield Pharmacy",
    "wof:placetype":"venue"
},
  "geometry": {"coordinates":[-73.98043800000001,40.716785],"type":"Point"}
}