{
  "type": "Feature",
  "properties": {
    "iso:country":"US",
    "sg:address":"596 Main St",
    "sg:city":"New Rochelle",
    "sg:classifiers":[
        {
            "category":"Bars & Pubs",
            "type":"Food & Drink"
        }
    ],
    "sg:phone":"+1   ",
    "sg:postcode":"10801",
    "sg:province":"NY",
    "sg:tags":[
        "drinking"
    ],
    "wof:name":"Lollipop II",
    "wof:placetype":"venue"
},
  "geometry": {"coordinates":[-73.784593,40.906959],"type":"Point"}
}