{
  "type": "Feature",
  "properties": {
    "addr:full":"7 Christman Pl Amsterdam NY 12010",
    "addr:housenumber":"7",
    "addr:postcode":"12010",
    "addr:street":"Christman Pl",
    "iso:country":"US",
    "sg:address":"7 Christman Pl",
    "sg:city":"Amsterdam",
    "sg:classifiers":[
        {
            "category":"Building & Trades",
            "subcategory":"Construction",
            "type":"Services"
        }
    ],
    "sg:phone":"+1 518 843 5614",
    "sg:postcode":"12010",
    "sg:province":"NY",
    "sg:tags":[
        "contractor"
    ],
    "wof:name":"Globe Construction Co",
    "wof:placetype":"venue"
},
  "geometry": {"coordinates":[-74.184634,42.952381],"type":"Point"}
}