{
  "type": "Feature",
  "properties": {
    "addr:full":"3200 West St Canandaigua NY 14424",
    "addr:housenumber":"3200",
    "addr:postcode":"14424",
    "addr:street":"West St",
    "iso:country":"US",
    "sg:address":"3200 West St",
    "sg:city":"Canandaigua",
    "sg:classifiers":[
        {
            "category":"Real Estate",
            "subcategory":"Architect",
            "type":"Services"
        }
    ],
    "sg:phone":"+1 585 394 7374",
    "sg:postcode":"14424",
    "sg:province":"NY",
    "sg:tags":[
        "architectural"
    ],
    "wof:name":"El Rayess Majed",
    "wof:placetype":"venue"
},
  "geometry": {"coordinates":[-77.29235199999999,42.875147],"type":"Point"}
}