{
  "type": "Feature",
  "properties": {
    "iso:country":"US",
    "sg:address":"855 Franklin Ave",
    "sg:city":"Brooklyn",
    "sg:classifiers":[
        {
            "category":"Food & Beverages",
            "subcategory":"Meat & Fish",
            "type":"Retail Goods"
        }
    ],
    "sg:phone":"+1 718 756 8473",
    "sg:postcode":"11225",
    "sg:province":"NY",
    "sg:tags":[
        "shop"
    ],
    "wof:name":"C & A Meat Market",
    "wof:placetype":"venue"
},
  "geometry": {"coordinates":[-73.958298,40.6693],"type":"Point"}
}