{
  "type": "Feature",
  "properties": {
    "addr:full":"150 Anderson Hill Rd Purchase NY 10577",
    "addr:housenumber":"150",
    "addr:postcode":"10577",
    "addr:street":"Anderson Hill Rd",
    "iso:country":"US",
    "sg:address":"150 Anderson Hill Rd",
    "sg:city":"Purchase",
    "sg:classifiers":[
        {
            "category":"Organizations",
            "subcategory":"Religious Organization",
            "type":"Services"
        }
    ],
    "sg:phone":"+1 914 761 7965",
    "sg:postcode":"10577",
    "sg:province":"NY",
    "sg:tags":[
        "monastery",
        "convent"
    ],
    "wof:name":"Sisters Of St John The Baptist",
    "wof:placetype":"venue"
},
  "geometry": {"coordinates":[-73.72782599999999,41.033595],"type":"Point"}
}