{
  "type": "Feature",
  "properties": {
    "addr:full":"476 Woodward Ave Ridgewood NY 11385",
    "addr:housenumber":"476",
    "addr:postcode":"11385",
    "addr:street":"Woodward Ave",
    "iso:country":"US",
    "sg:address":"476 Woodward Ave",
    "sg:city":"Ridgewood",
    "sg:classifiers":[
        {
            "category":"Restaurant",
            "type":"Food & Drink"
        }
    ],
    "sg:phone":"+1 347 599 2565",
    "sg:postcode":"11385",
    "sg:province":"NY",
    "sg:tags":[
        "pizza"
    ],
    "wof:name":"Bellisima Pizzeria Restaurant",
    "wof:placetype":"venue"
},
  "geometry": {"coordinates":[-73.910786,40.707878],"type":"Point"}
}