{
  "type": "Feature",
  "properties": {
    "addr:full":"84 Ross St Brooklyn NY 11211",
    "addr:housenumber":"84",
    "addr:postcode":"11211",
    "addr:street":"Ross St",
    "iso:country":"US",
    "sg:address":"84 Ross St",
    "sg:city":"Brooklyn",
    "sg:classifiers":[
        {
            "category":"Organizations",
            "subcategory":"Religious Organization",
            "type":"Services"
        }
    ],
    "sg:phone":"+1 718 388 8312",
    "sg:postcode":"11211",
    "sg:province":"NY",
    "sg:tags":[
        "clergy"
    ],
    "wof:name":"Mendel Goldberger",
    "wof:placetype":"venue"
},
  "geometry": {"coordinates":[-73.962514,40.704124],"type":"Point"}
}