{
  "type": "Feature",
  "properties": {
    "addr:full":"330 W 145th Street New York NY 10039",
    "addr:housenumber":"330",
    "addr:postcode":"10039",
    "addr:street":"W 145Th Street",
    "iso:country":"US",
    "sg:address":"330 W 145th Street",
    "sg:city":"New York",
    "sg:classifiers":[
        {
            "category":"Shopping",
            "subcategory":"Pharmacy",
            "type":"Retail Goods"
        }
    ],
    "sg:phone":"+1 212 690 0524",
    "sg:postcode":"10039",
    "sg:province":"NY",
    "sg:tags":[
        "drugstore"
    ],
    "wof:name":"Duane Reade Drugs",
    "wof:placetype":"venue"
},
  "geometry": {"coordinates":[-73.94344,40.823461],"type":"Point"}
}