{
  "type": "Feature",
  "properties": {
    "addr:full":"665 Amsterdam Ave New York NY 10025",
    "addr:housenumber":"665",
    "addr:postcode":"10025",
    "addr:street":"Amsterdam Ave",
    "iso:country":"US",
    "sg:address":"665 Amsterdam Ave",
    "sg:city":"New York",
    "sg:classifiers":[
        {
            "category":"Restaurant",
            "type":"Food & Drink"
        }
    ],
    "sg:phone":"+1 212 665 5348",
    "sg:postcode":"10025",
    "sg:province":"NY",
    "sg:tags":[
        "italian"
    ],
    "wof:name":"Gennaro",
    "wof:placetype":"venue"
},
  "geometry": {"coordinates":[-73.97210699999999,40.791649],"type":"Point"}
}