{
  "type": "Feature",
  "properties": {
    "iso:country":"US",
    "sg:address":"17 E Jericho Tpke",
    "sg:city":"Mineola",
    "sg:classifiers":[
        {
            "category":"Restaurant",
            "type":"Food & Drink"
        }
    ],
    "sg:phone":"+1   ",
    "sg:postcode":"11501",
    "sg:province":"NY",
    "sg:tags":[
        "diner"
    ],
    "wof:name":"Jericho Diner",
    "wof:placetype":"venue"
},
  "geometry": {"coordinates":[-73.634297,40.751308],"type":"Point"}
}