{
  "type": "Feature",
  "properties": {
    "iso:country":"US",
    "sg:address":"71 Lafayette Ave",
    "sg:city":"Suffern",
    "sg:classifiers":[
        {
            "category":"Organizations",
            "subcategory":"Professional Association",
            "type":"Services"
        }
    ],
    "sg:phone":"+1 845 357 8424",
    "sg:postcode":"10901",
    "sg:province":"NY",
    "sg:tags":[
        "business",
        "trade"
    ],
    "wof:name":"Suffern Chamber Of Commerce",
    "wof:placetype":"venue"
},
  "geometry": {"coordinates":[-74.15060200000001,41.115086],"type":"Point"}
}