{
  "type": "Feature",
  "properties": {
    "addr:full":"474 Central Ave Brooklyn NY 11221",
    "addr:housenumber":"474",
    "addr:postcode":"11221",
    "addr:street":"Central Ave",
    "iso:country":"US",
    "sg:address":"474 Central Ave",
    "sg:city":"Brooklyn",
    "sg:classifiers":[
        {
            "category":"Real Estate",
            "subcategory":"Real Estate Agent",
            "type":"Services"
        }
    ],
    "sg:phone":"+1 718 919 1661",
    "sg:postcode":"11221",
    "sg:province":"NY",
    "wof:name":"Direct Building Management Inc",
    "wof:placetype":"venue"
},
  "geometry": {"coordinates":[-73.914174,40.691772],"type":"Point"}
}