{
  "type": "Feature",
  "properties": {
    "addr:full":"490 W Old Country Rd Hicksville NY 11801",
    "addr:housenumber":"490",
    "addr:postcode":"11801",
    "addr:street":"W Old Country Rd",
    "iso:country":"US",
    "sg:address":"490 W Old Country Rd",
    "sg:city":"Hicksville",
    "sg:classifiers":[
        {
            "category":"Bagels",
            "type":"Food & Drink"
        },
        {
            "category":"Coffee & Tea",
            "type":"Food & Drink"
        },
        {
            "category":"Food & Beverages",
            "subcategory":"Bakery",
            "type":"Retail Goods"
        },
        {
            "category":"Bakery",
            "type":"Food & Drink"
        },
        {
            "category":"Donuts",
            "type":"Food & Drink"
        }
    ],
    "sg:menulink":"http://www.allmenus.com/ny/hicksville/138422-dunkin-donuts/menu/",
    "sg:phone":"+1 516 938 5768",
    "sg:postcode":"11801",
    "sg:province":"NY",
    "sg:tags":[
        "coffee",
        "tea",
        "american",
        "bagel",
        "bakery",
        "pastry"
    ],
    "wof:name":"Dunkin' Donuts",
    "wof:placetype":"venue"
},
  "geometry": {"coordinates":[-73.54386700000001,40.757788],"type":"Point"}
}