{
  "type": "Feature",
  "properties": {
    "addr:full":"320 Wythe Avenue Brooklyn NY 11211",
    "addr:housenumber":"320",
    "addr:postcode":"11211",
    "addr:street":"Wythe Avenue",
    "iso:country":"US",
    "sg:address":"320 Wythe Avenue",
    "sg:city":"Brooklyn",
    "sg:classifiers":[
        {
            "category":"Shopping",
            "subcategory":"Stationery & Office Supplies",
            "type":"Retail Goods"
        }
    ],
    "sg:phone":"+1 718 388 3810",
    "sg:postcode":"11211",
    "sg:province":"NY",
    "sg:tags":[
        "equipment"
    ],
    "wof:name":"The Office Purchasing Corporation",
    "wof:placetype":"venue"
},
  "geometry": {"coordinates":[-73.964682,40.715645],"type":"Point"}
}