{
  "type": "Feature",
  "properties": {
    "iso:country":"US",
    "sg:address":"8748 Reeds Corners Rd",
    "sg:city":"Dansville",
    "sg:classifiers":[
        {
            "category":"Manufacturing",
            "subcategory":"Lumber",
            "type":"Manufacturing & Wholesale Goods"
        }
    ],
    "sg:phone":"+1   ",
    "sg:postcode":"14437",
    "sg:province":"NY",
    "sg:tags":[
        "mill",
        "saw"
    ],
    "wof:name":"Trescott Lumber",
    "wof:placetype":"venue"
},
  "geometry": {"coordinates":[-77.68400699999999,42.599045],"type":"Point"}
}