{
  "type": "Feature",
  "properties": {
    "iso:country":"US",
    "sg:address":"250 Central Avenue",
    "sg:city":"Brooklyn",
    "sg:classifiers":[
        {
            "category":"Retail",
            "subcategory":"Auto Repair",
            "type":"Services"
        }
    ],
    "sg:phone":"+1 718 919 6840",
    "sg:postcode":"11221",
    "sg:province":"NY",
    "wof:name":"Vadi William",
    "wof:placetype":"venue"
},
  "geometry": {"coordinates":[-73.923502,40.696981],"type":"Point"}
}