{
  "type": "Feature",
  "properties": {
    "addr:full":"2 Green Street Staten Island NY 10310",
    "addr:housenumber":"2",
    "addr:postcode":"10310",
    "addr:street":"Green Street",
    "iso:country":"US",
    "sg:address":"2 Green Street",
    "sg:city":"Staten Island",
    "sg:classifiers":[
        {
            "category":"Real Estate",
            "subcategory":"Architect",
            "type":"Services"
        }
    ],
    "sg:phone":"+1 718 448 2740",
    "sg:postcode":"10310",
    "sg:province":"NY",
    "wof:name":"De Ruvo Michael & Associates Architects",
    "wof:placetype":"venue"
},
  "geometry": {"coordinates":[-74.11100500000001,40.629179],"type":"Point"}
}