{
  "type": "Feature",
  "properties": {
    "iso:country":"US",
    "sg:address":"575 E Main St",
    "sg:city":"Little Falls",
    "sg:classifiers":[
        {
            "category":"Cinema",
            "subcategory":"Movie Rental",
            "type":"Entertainment"
        }
    ],
    "sg:phone":"+1 315 823 3230",
    "sg:postcode":"13365",
    "sg:province":"NY",
    "sg:tags":[
        "leasing",
        "video",
        "disc",
        "tape"
    ],
    "sg:website":"www.moviegallery.com",
    "wof:name":"Movie Gallery",
    "wof:placetype":"venue"
},
  "geometry": {"coordinates":[-74.858037,43.043714],"type":"Point"}
}