{
  "type": "Feature",
  "properties": {
    "addr:full":"24827 Jericho Tpke Bellerose NY 11426",
    "addr:housenumber":"24827",
    "addr:postcode":"11426",
    "addr:street":"Jericho Tpke",
    "iso:country":"US",
    "sg:address":"24827 Jericho Tpke",
    "sg:city":"Bellerose",
    "sg:classifiers":[
        {
            "category":"Restaurant",
            "type":"Food & Drink"
        }
    ],
    "sg:menulink":"http://www.allmenus.com/ny/queens/171456-triple-crown-restaurant-diner/menu/",
    "sg:phone":"+1 718 347 4600",
    "sg:postcode":"11426",
    "sg:province":"NY",
    "sg:tags":[
        "american",
        "diner"
    ],
    "wof:name":"Triple Crown Restaurant-diner",
    "wof:placetype":"venue"
},
  "geometry": {"coordinates":[-73.71766700000001,40.726265],"type":"Point"}
}