{
  "type": "Feature",
  "properties": {
    "iso:country":"US",
    "sg:address":"375 E Main St Ste 26",
    "sg:city":"Bay Shore",
    "sg:classifiers":[
        {
            "category":"Health Services",
            "subcategory":"Doctor",
            "type":"Services"
        }
    ],
    "sg:phone":"+1 631 665 2255",
    "sg:postcode":"11706",
    "sg:province":"NY",
    "wof:name":"Suffolk Heart Group",
    "wof:placetype":"venue"
},
  "geometry": {"coordinates":[-73.236068,40.726449],"type":"Point"}
}