{
  "type": "Feature",
  "properties": {
    "iso:country":"US",
    "sg:address":"2000 State Hwy 392",
    "sg:city":"Cortland",
    "sg:classifiers":[
        {
            "category":"Travel",
            "subcategory":"Hotels & Motels",
            "type":"Entertainment"
        }
    ],
    "sg:phone":"+1 607 835 6111",
    "sg:postcode":"13045",
    "sg:province":"NY",
    "sg:tags":[
        "resort",
        "center",
        "skiing"
    ],
    "wof:name":"Greek Peak Ski Resort",
    "wof:placetype":"venue"
},
  "geometry": {"coordinates":[-76.141081,42.507861],"type":"Point"}
}