{
  "type": "Feature",
  "properties": {
    "addr:full":"3570 Broadway New York NY 10031",
    "addr:housenumber":"3570",
    "addr:postcode":"10031",
    "addr:street":"Broadway",
    "iso:country":"US",
    "sg:address":"3570 Broadway",
    "sg:city":"New York",
    "sg:classifiers":[
        {
            "category":"Insurance",
            "subcategory":"Insurance Agent",
            "type":"Services"
        }
    ],
    "sg:phone":"+1 212 368 1338",
    "sg:postcode":"10031",
    "sg:province":"NY",
    "wof:name":"Manhattan Pawn Broker",
    "wof:placetype":"venue"
},
  "geometry": {"coordinates":[-73.94963,40.827345],"type":"Point"}
}