{
  "type": "Feature",
  "properties": {
    "addr:full":"601 E 187th St Bronx NY 10458",
    "addr:housenumber":"601",
    "addr:postcode":"10458",
    "addr:street":"E 187Th St",
    "iso:country":"US",
    "sg:address":"601 E 187th St",
    "sg:city":"Bronx",
    "sg:classifiers":[
        {
            "category":"Shopping",
            "subcategory":"Optical Goods",
            "type":"Retail Goods"
        }
    ],
    "sg:phone":"+1 718 562 2020",
    "sg:postcode":"10458",
    "sg:province":"NY",
    "sg:tags":[
        "optician"
    ],
    "wof:name":"Eye Care Unlimited",
    "wof:placetype":"venue"
},
  "geometry": {"coordinates":[-73.88687299999999,40.855202],"type":"Point"}
}