{
  "type": "Feature",
  "properties": {
    "addr:full":"1929 Avenue U Brooklyn NY 11229",
    "addr:housenumber":"1929",
    "addr:postcode":"11229",
    "addr:street":"Avenue U",
    "iso:country":"US",
    "sg:address":"1929 Avenue U",
    "sg:city":"Brooklyn",
    "sg:classifiers":[
        {
            "category":"Shopping",
            "subcategory":"Tobacco",
            "type":"Retail Goods"
        },
        {
            "category":"Food & Beverages",
            "subcategory":"Groceries & Convenience Stores",
            "type":"Retail Goods"
        }
    ],
    "sg:phone":"+1 718 368 1235",
    "sg:postcode":"11229",
    "sg:province":"NY",
    "sg:tags":[
        "shop"
    ],
    "wof:name":"Cigar Palace",
    "wof:placetype":"venue"
},
  "geometry": {"coordinates":[-73.952281,40.599292],"type":"Point"}
}