{
  "type": "Feature",
  "properties": {
    "iso:country":"US",
    "sg:address":"12 Downey Dr",
    "sg:city":"Huntington",
    "sg:classifiers":[
        {
            "category":"Building & Trades",
            "subcategory":"Construction",
            "type":"Services"
        }
    ],
    "sg:phone":"+1 631 424 4625",
    "sg:postcode":"11743",
    "sg:province":"NY",
    "sg:tags":[
        "contractor"
    ],
    "wof:name":"Contracting Corp Miksco",
    "wof:placetype":"venue"
},
  "geometry": {"coordinates":[-73.43338799999999,40.834745],"type":"Point"}
}