{
  "type": "Feature",
  "properties": {
    "addr:full":"2 Dogwood Ln Brewster NY 10509",
    "addr:housenumber":"2",
    "addr:postcode":"10509",
    "addr:street":"Dogwood Ln",
    "iso:country":"US",
    "sg:address":"2 Dogwood Ln",
    "sg:city":"Brewster",
    "sg:classifiers":[
        {
            "category":"Real Estate",
            "subcategory":"Real Estate Services",
            "type":"Services"
        },
        {
            "category":"Real Estate",
            "subcategory":"Real Estate Agent",
            "type":"Services"
        }
    ],
    "sg:phone":"+1 845 721 3593",
    "sg:postcode":"10509",
    "sg:province":"NY",
    "sg:tags":[
        "buyer",
        "broker"
    ],
    "wof:name":"Mancini Realty Inc.",
    "wof:placetype":"venue"
},
  "geometry": {"coordinates":[-73.596031,41.411419],"type":"Point"}
}