{
  "type": "Feature",
  "properties": {
    "iso:country":"US",
    "sg:address":"435 State St",
    "sg:city":"Binghamton",
    "sg:classifiers":[
        {
            "category":"Government",
            "subcategory":"Office",
            "type":"Public Place"
        }
    ],
    "sg:phone":"+1 607 778 3075",
    "sg:postcode":"13901",
    "sg:province":"NY",
    "wof:name":"Broome County Child Assistance",
    "wof:placetype":"venue"
},
  "geometry": {"coordinates":[-75.90390499999999,42.108321],"type":"Point"}
}