{
  "type": "Feature",
  "properties": {
    "addr:full":"104 W 37th St New York NY 10018",
    "addr:housenumber":"104",
    "addr:postcode":"10018",
    "addr:street":"W 37Th St",
    "iso:country":"US",
    "sg:address":"104 W 37th St",
    "sg:city":"New York",
    "sg:classifiers":[
        {
            "category":"Retail",
            "subcategory":"Auto Repair",
            "type":"Services"
        }
    ],
    "sg:phone":"+1 212 937 1327",
    "sg:postcode":"10018",
    "sg:province":"NY",
    "sg:tags":[
        "wrecker"
    ],
    "wof:name":"Ashimi Towing",
    "wof:placetype":"venue"
},
  "geometry": {"coordinates":[-73.98729,40.751962],"type":"Point"}
}