{
  "type": "Feature",
  "properties": {
    "iso:country":"US",
    "sg:address":"13993 Smith Rd",
    "sg:city":"Sterling",
    "sg:classifiers":[
        {
            "category":"Building & Trades",
            "subcategory":"Electrical",
            "type":"Services"
        }
    ],
    "sg:phone":"+1 315 947 5306",
    "sg:postcode":"13156",
    "sg:province":"NY",
    "sg:tags":[
        "electrician"
    ],
    "wof:name":"D Lux Plumbing & Electric",
    "wof:placetype":"venue"
},
  "geometry": {"coordinates":[-76.719736,43.311075],"type":"Point"}
}