{
  "type": "Feature",
  "properties": {
    "addr:full":"105 W 73 St New York NY 10023",
    "addr:housenumber":"105",
    "addr:postcode":"10023",
    "addr:street":"W 73 St",
    "iso:country":"US",
    "sg:address":"105 W 73 St",
    "sg:city":"New York",
    "sg:classifiers":[
        {
            "category":"Arts & Performance",
            "subcategory":"Theater",
            "type":"Entertainment"
        }
    ],
    "sg:phone":"+1 212 580 9933",
    "sg:postcode":"10023",
    "sg:province":"NY",
    "sg:tags":[
        "band",
        "orchestra"
    ],
    "sg:website":"www.nyphilomusica.org",
    "wof:name":"N Y Philomusica",
    "wof:placetype":"venue"
},
  "geometry": {"coordinates":[-73.981011,40.779309],"type":"Point"}
}