{
  "type": "Feature",
  "properties": {
    "iso:country":"US",
    "sg:address":"159 Prince St",
    "sg:city":"Manhattan",
    "sg:classifiers":[
        {
            "category":"Shopping",
            "subcategory":"Clothing, Apparel, & Fashions",
            "type":"Retail Goods"
        }
    ],
    "sg:phone":"+1 212 533 2107",
    "sg:postcode":"10012",
    "sg:province":"NY",
    "sg:tags":[
        "accessory"
    ],
    "sg:website":"www.badichibelts.com",
    "wof:name":"Badichi Belts",
    "wof:placetype":"venue"
},
  "geometry": {"coordinates":[-74.001136,40.726126],"type":"Point"}
}