{
  "type": "Feature",
  "properties": {
    "addr:full":"1055 Brighton Beach Ave Brooklyn NY 11235",
    "addr:housenumber":"1055",
    "addr:postcode":"11235",
    "addr:street":"Brighton Beach Ave",
    "iso:country":"US",
    "sg:address":"1055 Brighton Beach Ave",
    "sg:city":"Brooklyn",
    "sg:classifiers":[
        {
            "category":"Food & Beverages",
            "subcategory":"Fruits & Vegetables",
            "type":"Retail Goods"
        }
    ],
    "sg:phone":"+1 718 368 9799",
    "sg:postcode":"11235",
    "sg:province":"NY",
    "sg:tags":[
        "produce",
        "veggie"
    ],
    "wof:name":"Ke Produce",
    "wof:placetype":"venue"
},
  "geometry": {"coordinates":[-73.957802,40.5783],"type":"Point"}
}