{
  "type": "Feature",
  "properties": {
    "iso:country":"US",
    "sg:address":"40 Bus Park Dr",
    "sg:city":"Armonk",
    "sg:classifiers":[
        {
            "category":"Farming",
            "subcategory":"Farm",
            "type":"Manufacturing & Wholesale Goods"
        }
    ],
    "sg:phone":"+1 914 273 6278",
    "sg:postcode":"10504",
    "sg:province":"NY",
    "sg:tags":[
        "crop",
        "general"
    ],
    "wof:name":"October Farm",
    "wof:placetype":"venue"
},
  "geometry": {"coordinates":[-73.709576,41.122179],"type":"Point"}
}