{
  "type": "Feature",
  "properties": {
    "addr:full":"2 Whitman Ave Syosset NY 11791",
    "addr:housenumber":"2",
    "addr:postcode":"11791",
    "addr:street":"Whitman Ave",
    "iso:country":"US",
    "sg:address":"2 Whitman Ave",
    "sg:city":"Syosset",
    "sg:classifiers":[
        {
            "category":"Manufacturing",
            "subcategory":"Food",
            "type":"Manufacturing & Wholesale Goods"
        },
        {
            "category":"Wholesale",
            "subcategory":"Groceries",
            "type":"Manufacturing & Wholesale Goods"
        },
        {
            "category":"Ice Cream",
            "type":"Food & Drink"
        },
        {
            "category":"Food & Beverages",
            "subcategory":"Dairy",
            "type":"Retail Goods"
        }
    ],
    "sg:phone":"+1 516 364 6303",
    "sg:postcode":"11791",
    "sg:province":"NY",
    "sg:tags":[
        "products-wholesale",
        "frozen",
        "dessert",
        "desserts-manufacturers",
        "foods-wholesale",
        "distributor"
    ],
    "sg:website":"http://www.koolkreationswebdesigns.com",
    "wof:name":"Kool Kreations",
    "wof:placetype":"venue"
},
  "geometry": {"coordinates":[-73.499527,40.809151],"type":"Point"}
}