{
  "type": "Feature",
  "properties": {
    "addr:full":"4 Little Rd Newburgh NY 12590",
    "addr:housenumber":"4",
    "addr:postcode":"12590",
    "addr:street":"Little Rd",
    "iso:country":"US",
    "sg:address":"4 Little Rd",
    "sg:city":"Newburgh",
    "sg:classifiers":[
        {
            "category":"Building & Trades",
            "subcategory":"Construction",
            "type":"Services"
        }
    ],
    "sg:phone":"+1 845 566 1759",
    "sg:postcode":"12590",
    "sg:province":"NY",
    "sg:tags":[
        "contractor"
    ],
    "wof:name":"Daniel Olivo Drywall Inc",
    "wof:placetype":"venue"
},
  "geometry": {"coordinates":[-73.85207200000001,41.594135],"type":"Point"}
}