{
  "type": "Feature",
  "properties": {
    "iso:country":"US",
    "sg:address":"99 Maple Pl",
    "sg:city":"Freeport",
    "sg:classifiers":[
        {
            "category":"Manufacturing",
            "subcategory":"Metals",
            "type":"Manufacturing & Wholesale Goods"
        },
        {
            "category":"Manufacturing",
            "subcategory":"Building Materials",
            "type":"Manufacturing & Wholesale Goods"
        }
    ],
    "sg:phone":"+1 516 678 6627",
    "sg:postcode":"11520",
    "sg:province":"NY",
    "sg:tags":[
        "fabricator",
        "work",
        "sheet"
    ],
    "wof:name":"Oceanside Sheet Metal",
    "wof:placetype":"venue"
},
  "geometry": {"coordinates":[-73.57260100000001,40.65202],"type":"Point"}
}