{
  "type": "Feature",
  "properties": {
    "addr:full":"159 E Houston St New York NY 10002",
    "addr:housenumber":"159",
    "addr:postcode":"10002",
    "addr:street":"E Houston St",
    "iso:country":"US",
    "sg:address":"159 E Houston St",
    "sg:city":"New York",
    "sg:classifiers":[
        {
            "category":"Restaurant",
            "type":"Food & Drink"
        }
    ],
    "sg:phone":"+1 212 995 0330",
    "sg:postcode":"10002",
    "sg:province":"NY",
    "wof:name":"Martignetti Liquors",
    "wof:placetype":"venue"
},
  "geometry": {"coordinates":[-73.988916,40.722967],"type":"Point"}
}