{
  "type": "Feature",
  "properties": {
    "iso:country":"US",
    "sg:address":"133 Esplanade Dr",
    "sg:city":"Rochester",
    "sg:classifiers":[
        {
            "category":"Professional",
            "subcategory":"Research",
            "type":"Services"
        }
    ],
    "sg:phone":"+1 585 244 4307",
    "sg:postcode":"14610",
    "sg:province":"NY",
    "sg:tags":[
        "economic",
        "analysis"
    ],
    "wof:name":"Rochester Economic Consultants",
    "wof:placetype":"venue"
},
  "geometry": {"coordinates":[-77.54657400000001,43.132211],"type":"Point"}
}