{
  "type": "Feature",
  "properties": {
    "addr:full":"81 Landing Ave Smithtown NY 11787",
    "addr:housenumber":"81",
    "addr:postcode":"11787",
    "addr:street":"Landing Ave",
    "iso:country":"US",
    "sg:address":"81 Landing Ave",
    "sg:city":"Smithtown",
    "sg:classifiers":[
        {
            "category":"Professional",
            "subcategory":"Art Services",
            "type":"Services"
        }
    ],
    "sg:phone":"+1 516 721 1364",
    "sg:postcode":"11787",
    "sg:province":"NY",
    "sg:tags":[
        "photographer"
    ],
    "sg:website":"lanarowephoto.com",
    "wof:name":"Lana Rowe Photography",
    "wof:placetype":"venue"
},
  "geometry": {"coordinates":[-73.19392000000001,40.857312],"type":"Point"}
}