{
  "type": "Feature",
  "properties": {
    "addr:full":"1542 Central Ave Albany NY 12205",
    "addr:housenumber":"1542",
    "addr:postcode":"12205",
    "addr:street":"Central Ave",
    "iso:country":"US",
    "sg:address":"1542 Central Ave",
    "sg:city":"Albany",
    "sg:classifiers":[
        {
            "category":"Shopping",
            "type":"Retail Goods"
        }
    ],
    "sg:phone":"+1 518 218 3378",
    "sg:postcode":"12205",
    "sg:province":"NY",
    "sg:tags":[
        "cosmetic",
        "perfume"
    ],
    "wof:name":"Avon Products Inc",
    "wof:placetype":"venue"
},
  "geometry": {"coordinates":[-73.829702,42.714819],"type":"Point"}
}