{
  "type": "Feature",
  "properties": {
    "addr:full":"8611 Northern Blvd Jackson Heights NY 11372",
    "addr:housenumber":"8611",
    "addr:postcode":"11372",
    "addr:street":"Northern Blvd",
    "iso:country":"US",
    "sg:address":"8611 Northern Blvd",
    "sg:city":"Jackson Heights",
    "sg:classifiers":[
        {
            "category":"Restaurant",
            "type":"Food & Drink"
        }
    ],
    "sg:phone":"+1 718 806 1578",
    "sg:postcode":"11372",
    "sg:province":"NY",
    "sg:tags":[
        "mexican"
    ],
    "wof:name":"La Gloria Inc",
    "wof:placetype":"venue"
},
  "geometry": {"coordinates":[-73.881575,40.756136],"type":"Point"}
}