{
  "type": "Feature",
  "properties": {
    "iso:country":"US",
    "sg:address":"509 Boston Post Rd",
    "sg:city":"Port Chester",
    "sg:classifiers":[
        {
            "category":"Shopping",
            "subcategory":"Clothing, Apparel, & Fashions",
            "type":"Retail Goods"
        }
    ],
    "sg:phone":"+1 914 939 1037",
    "sg:postcode":"10573",
    "sg:province":"NY",
    "wof:name":"Dress Barn Woman",
    "wof:placetype":"venue"
},
  "geometry": {"coordinates":[-73.67577900000001,40.993192],"type":"Point"}
}