{
  "type": "Feature",
  "properties": {
    "iso:country":"US",
    "sg:address":"1440 Central Ave",
    "sg:city":"Albany",
    "sg:classifiers":[
        {
            "category":"Food & Beverages",
            "subcategory":"Specialty",
            "type":"Retail Goods"
        }
    ],
    "sg:phone":"+1   ",
    "sg:postcode":"12205",
    "sg:province":"NY",
    "wof:name":"GNC",
    "wof:placetype":"venue"
},
  "geometry": {"coordinates":[-73.82128299999999,42.70745],"type":"Point"}
}