{
  "type": "Feature",
  "properties": {
    "iso:country":"US",
    "sg:address":"828 Hanshaw Rd",
    "sg:city":"Ithaca",
    "sg:classifiers":[
        {
            "category":"Personal",
            "subcategory":"Beauty Salon",
            "type":"Services"
        }
    ],
    "sg:phone":"+1 607 257 1883",
    "sg:postcode":"14850",
    "sg:province":"NY",
    "sg:tags":[
        "shop"
    ],
    "wof:name":"Michelle Newhart At Hair Etc",
    "wof:placetype":"venue"
},
  "geometry": {"coordinates":[-76.480118,42.470014],"type":"Point"}
}