{
  "type": "Feature",
  "properties": {
    "iso:country":"US",
    "sg:address":"4334 Union Street",
    "sg:city":"Flushing",
    "sg:classifiers":[
        {
            "category":"Real Estate",
            "subcategory":"Architect",
            "type":"Services"
        }
    ],
    "sg:phone":"+1 718 206 1229",
    "sg:postcode":"11355",
    "sg:province":"NY",
    "wof:name":"S V Associates",
    "wof:placetype":"venue"
},
  "geometry": {"coordinates":[-73.82135599999999,40.754316],"type":"Point"}
}