{
  "type": "Feature",
  "properties": {
    "addr:full":"1800 Seagirt Blvd Far Rockaway NY 11691",
    "addr:housenumber":"1800",
    "addr:postcode":"11691",
    "addr:street":"Seagirt Blvd",
    "iso:country":"US",
    "sg:address":"1800 Seagirt Blvd",
    "sg:city":"Far Rockaway",
    "sg:classifiers":[
        {
            "category":"Education",
            "subcategory":"School",
            "type":"Public Place"
        }
    ],
    "sg:phone":"+1 718 327 7380",
    "sg:postcode":"11691",
    "sg:province":"NY",
    "sg:tags":[
        "high",
        "middle",
        "elementary"
    ],
    "wof:name":"Darchei Torah",
    "wof:placetype":"venue"
},
  "geometry": {"coordinates":[-73.752225,40.595352],"type":"Point"}
}