{
  "type": "Feature",
  "properties": {
    "iso:country":"US",
    "sg:address":"330 W 56th Street",
    "sg:city":"Manhattan",
    "sg:classifiers":[
        {
            "category":"Professional",
            "subcategory":"Art Services",
            "type":"Services"
        }
    ],
    "sg:phone":"+1 917 861 9052",
    "sg:postcode":"10019",
    "sg:province":"NY",
    "sg:tags":[
        "photographer"
    ],
    "sg:website":"www.maternitybykoren.com",
    "wof:name":"Koren Reyes Photography",
    "wof:placetype":"venue"
},
  "geometry": {"coordinates":[-73.98504699999999,40.766506],"type":"Point"}
}