{
  "type": "Feature",
  "properties": {
    "iso:country":"US",
    "sg:address":"3050 W 21st St",
    "sg:city":"Brooklyn",
    "sg:classifiers":[
        {
            "category":"Government",
            "subcategory":"Office",
            "type":"Public Place"
        }
    ],
    "sg:phone":"+1 718 333 3014",
    "sg:postcode":"11224",
    "sg:province":"NY",
    "sg:tags":[
        "village"
    ],
    "wof:name":"Brooklyn Job Income Support",
    "wof:placetype":"venue"
},
  "geometry": {"coordinates":[-73.987469,40.573556],"type":"Point"}
}