{
  "type": "Feature",
  "properties": {
    "iso:country":"US",
    "sg:address":"229 Old Town Rd",
    "sg:city":"Setauket",
    "sg:classifiers":[
        {
            "category":"Building & Trades",
            "subcategory":"Plumbing",
            "type":"Services"
        }
    ],
    "sg:phone":"+1 631 689 3702",
    "sg:postcode":"11733",
    "sg:province":"NY",
    "wof:name":"McIntosh Plumbing & Heating Inc",
    "wof:placetype":"venue"
},
  "geometry": {"coordinates":[-73.09030199999999,40.9314],"type":"Point"}
}