{
  "type": "Feature",
  "properties": {
    "addr:full":"16 Amity Pt Clifton Park NY 12065",
    "addr:housenumber":"16",
    "addr:postcode":"12065",
    "addr:street":"Amity Pt",
    "iso:country":"US",
    "sg:address":"16 Amity Pt",
    "sg:city":"Clifton Park",
    "sg:classifiers":[
        {
            "category":"Food & Beverages",
            "subcategory":"Liquor & Beverages",
            "type":"Retail Goods"
        }
    ],
    "sg:phone":"+1   ",
    "sg:postcode":"12065",
    "sg:province":"NY",
    "sg:tags":[
        "alcoholic"
    ],
    "wof:name":"Wine Bar Ltd",
    "wof:placetype":"venue"
},
  "geometry": {"coordinates":[-73.78407799999999,42.806182],"type":"Point"}
}