{
  "type": "Feature",
  "properties": {
    "addr:full":"378 E Main St Patchogue NY 11772",
    "addr:housenumber":"378",
    "addr:postcode":"11772",
    "addr:street":"E Main St",
    "iso:country":"US",
    "sg:address":"378 E Main St",
    "sg:city":"Patchogue",
    "sg:classifiers":[
        {
            "category":"Personal",
            "subcategory":"Tanning Parlor",
            "type":"Services"
        }
    ],
    "sg:phone":"+1 631 475 2934",
    "sg:postcode":"11772",
    "sg:province":"NY",
    "sg:tags":[
        "salon"
    ],
    "wof:name":"Boca Tanning",
    "wof:placetype":"venue"
},
  "geometry": {"coordinates":[-73.008309,40.765833],"type":"Point"}
}