{
  "type": "Feature",
  "properties": {
    "addr:full":"2635 Delaware Ave Buffalo NY 14216",
    "addr:housenumber":"2635",
    "addr:postcode":"14216",
    "addr:street":"Delaware Ave",
    "iso:country":"US",
    "sg:address":"2635 Delaware Ave",
    "sg:city":"Buffalo",
    "sg:classifiers":[
        {
            "category":"Retail",
            "subcategory":"Portrait Studio",
            "type":"Services"
        }
    ],
    "sg:phone":"+1 716 877 3317",
    "sg:postcode":"14216",
    "sg:province":"NY",
    "sg:tags":[
        "photography",
        "store"
    ],
    "wof:name":"Delaware Camera & Video",
    "wof:placetype":"venue"
},
  "geometry": {"coordinates":[-78.860497,42.950001],"type":"Point"}
}