{
  "type": "Feature",
  "properties": {
    "addr:full":"777 United Nations Plz New York NY 10017",
    "addr:housenumber":"777",
    "addr:postcode":"10017",
    "addr:street":"United Nations Plz",
    "iso:country":"US",
    "sg:address":"777 United Nations Plz",
    "sg:city":"New York",
    "sg:classifiers":[
        {
            "category":"Organizations",
            "subcategory":"Non-profit Organization",
            "type":"Services"
        },
        {
            "category":"Organizations",
            "subcategory":"Community Association",
            "type":"Services"
        }
    ],
    "sg:phone":"+1 212 687 4300",
    "sg:postcode":"10017",
    "sg:province":"NY",
    "sg:website":"www.ipacademy.org",
    "wof:name":"International Peace Academy",
    "wof:placetype":"venue"
},
  "geometry": {"coordinates":[-73.969173,40.74976],"type":"Point"}
}