{
  "type": "Feature",
  "properties": {
    "iso:country":"US",
    "sg:address":"254 W 14 St",
    "sg:city":"New York",
    "sg:classifiers":[
        {
            "category":"Food & Beverages",
            "subcategory":"Groceries & Convenience Stores",
            "type":"Retail Goods"
        }
    ],
    "sg:phone":"+1   ",
    "sg:postcode":"10011",
    "sg:province":"NY",
    "wof:name":"NM Grocery Candy",
    "wof:placetype":"venue"
},
  "geometry": {"coordinates":[-74.001374,40.739026],"type":"Point"}
}