{
  "type": "Feature",
  "properties": {
    "iso:country":"US",
    "sg:address":"1289 Hempstead Tpke",
    "sg:city":"Elmont",
    "sg:classifiers":[
        {
            "category":"Retail",
            "subcategory":"Auto Repair",
            "type":"Services"
        }
    ],
    "sg:phone":"+1 516 355 0463",
    "sg:postcode":"11003",
    "sg:province":"NY",
    "sg:tags":[
        "body",
        "shop"
    ],
    "wof:name":"Cross Island Collision",
    "wof:placetype":"venue"
},
  "geometry": {"coordinates":[-73.70590199999999,40.707699],"type":"Point"}
}