{
  "type": "Feature",
  "properties": {
    "addr:full":"80 Beekman Rd Hopewell Jct NY 12533",
    "addr:housenumber":"80",
    "addr:postcode":"12533",
    "addr:street":"Beekman Rd",
    "iso:country":"US",
    "sg:address":"80 Beekman Rd",
    "sg:city":"Hopewell Jct",
    "sg:classifiers":[
        {
            "category":"Organizations",
            "subcategory":"Religious Organization",
            "type":"Services"
        }
    ],
    "sg:phone":"+1 845 221 9542",
    "sg:postcode":"12533",
    "sg:province":"NY",
    "sg:tags":[
        "clergy"
    ],
    "wof:name":"David W Hondorp",
    "wof:placetype":"venue"
},
  "geometry": {"coordinates":[-73.790944,41.587275],"type":"Point"}
}