{
  "type": "Feature",
  "properties": {
    "addr:full":"100 Park Ave New York NY 10017",
    "addr:housenumber":"100",
    "addr:postcode":"10017",
    "addr:street":"Park Ave",
    "iso:country":"US",
    "sg:address":"100 Park Ave",
    "sg:city":"New York",
    "sg:classifiers":[
        {
            "category":"Restaurant",
            "type":"Food & Drink"
        }
    ],
    "sg:phone":"+1 212 725 5570",
    "sg:postcode":"10017",
    "sg:province":"NY",
    "sg:tags":[
        "chinese"
    ],
    "sg:website":"www.pekinghunanpark.com",
    "wof:name":"Peking Hunan Park",
    "wof:placetype":"venue"
},
  "geometry": {"coordinates":[-73.978576,40.750976],"type":"Point"}
}