{
  "type": "Feature",
  "properties": {
    "addr:full":"38 Scotchtown Ave Goshen NY 10924",
    "addr:housenumber":"38",
    "addr:postcode":"10924",
    "addr:street":"Scotchtown Ave",
    "iso:country":"US",
    "sg:address":"38 Scotchtown Ave",
    "sg:city":"Goshen",
    "sg:classifiers":[
        {
            "category":"Professional",
            "subcategory":"Lawyer & Legal Services",
            "type":"Services"
        }
    ],
    "sg:phone":"+1 845 294 7971",
    "sg:postcode":"10924",
    "sg:province":"NY",
    "wof:name":"Bach John E Jr Atty",
    "wof:placetype":"venue"
},
  "geometry": {"coordinates":[-74.31860399999999,41.408401],"type":"Point"}
}