{
  "type": "Feature",
  "properties": {
    "iso:country":"US",
    "sg:address":"27 Kingwood Rd",
    "sg:city":"Scarsdale",
    "sg:classifiers":[
        {
            "category":"Professional",
            "subcategory":"Management & Consulting",
            "type":"Services"
        }
    ],
    "sg:phone":"+1   ",
    "sg:postcode":"10583",
    "sg:province":"NY",
    "sg:tags":[
        "consultant",
        "business"
    ],
    "wof:name":"Albert Sam Associates Inc",
    "wof:placetype":"venue"
},
  "geometry": {"coordinates":[-73.830455,40.9859],"type":"Point"}
}