{
  "type": "Feature",
  "properties": {
    "addr:full":"1950 Monroe Ave Rochester NY 14618",
    "addr:housenumber":"1950",
    "addr:postcode":"14618",
    "addr:street":"Monroe Ave",
    "iso:country":"US",
    "sg:address":"1950 Monroe Ave",
    "sg:city":"Rochester",
    "sg:classifiers":[
        {
            "category":"Autos & Motor Vehicles",
            "subcategory":"Fuel & Gas Station",
            "type":"Retail Goods"
        }
    ],
    "sg:phone":"+1 585 244 2825",
    "sg:postcode":"14618",
    "sg:province":"NY",
    "sg:tags":[
        "oil"
    ],
    "wof:name":"Twelve Corners Mobil",
    "wof:placetype":"venue"
},
  "geometry": {"coordinates":[-77.56337000000001,43.125512],"type":"Point"}
}