{
  "type": "Feature",
  "properties": {
    "iso:country":"US",
    "sg:address":"4850 State Hwy 69",
    "sg:city":"Rome",
    "sg:classifiers":[
        {
            "category":"Shopping",
            "subcategory":"Gifts & Souvenirs",
            "type":"Retail Goods"
        }
    ],
    "sg:phone":"+1   ",
    "sg:postcode":"13440",
    "sg:province":"NY",
    "wof:name":"Twas A Christmas Past",
    "wof:placetype":"venue"
},
  "geometry": {"coordinates":[-75.488572,43.226331],"type":"Point"}
}