{
  "type": "Feature",
  "properties": {
    "iso:country":"US",
    "sg:address":"173 Sea Lion Dr",
    "sg:city":"Mayville",
    "sg:classifiers":[
        {
            "category":"Real Estate",
            "subcategory":"Real Estate Operator",
            "type":"Services"
        }
    ],
    "sg:phone":"+1   ",
    "sg:postcode":"14757",
    "sg:province":"NY",
    "sg:tags":[
        "building",
        "marina",
        "operation",
        "nonresidential"
    ],
    "wof:name":"Creative Marine",
    "wof:placetype":"venue"
},
  "geometry": {"coordinates":[-79.485973,42.260746],"type":"Point"}
}