{
  "type": "Feature",
  "properties": {
    "addr:full":"43 Fort St Cortland NY 13021",
    "addr:housenumber":"43",
    "addr:postcode":"13021",
    "addr:street":"Fort St",
    "iso:country":"US",
    "sg:address":"43 Fort St",
    "sg:city":"Cortland",
    "sg:classifiers":[
        {
            "category":"Real Estate",
            "subcategory":"Surveying",
            "type":"Services"
        }
    ],
    "sg:phone":"+1 607 732 1500",
    "sg:postcode":"13021",
    "sg:province":"NY",
    "wof:name":"James Denkenberger Pls",
    "wof:placetype":"venue"
},
  "geometry": {"coordinates":[-76.571072,42.927246],"type":"Point"}
}