{
  "type": "Feature",
  "properties": {
    "addr:full":"226 Farrier Ave Oneida NY 13421",
    "addr:housenumber":"226",
    "addr:postcode":"13421",
    "addr:street":"Farrier Ave",
    "iso:country":"US",
    "sg:address":"226 Farrier Ave",
    "sg:city":"Oneida",
    "sg:classifiers":[
        {
            "category":"Government",
            "subcategory":"Office",
            "type":"Public Place"
        }
    ],
    "sg:phone":"+1 315 363 8450",
    "sg:postcode":"13421",
    "sg:province":"NY",
    "sg:tags":[
        "housing",
        "program"
    ],
    "wof:name":"Oneida City Housing Authority",
    "wof:placetype":"venue"
},
  "geometry": {"coordinates":[-75.653784,43.094272],"type":"Point"}
}