{
  "type": "Feature",
  "properties": {
    "addr:full":"199 Main St Beacon NY 12508",
    "addr:housenumber":"199",
    "addr:postcode":"12508",
    "addr:street":"Main St",
    "iso:country":"US",
    "sg:address":"199 Main St",
    "sg:city":"Beacon",
    "sg:classifiers":[
        {
            "category":"Organizations",
            "subcategory":"Non-profit Organization",
            "type":"Services"
        }
    ],
    "sg:phone":"+1 845 838 1600",
    "sg:postcode":"12508",
    "sg:province":"NY",
    "sg:tags":[
        "service/non-profit",
        "community"
    ],
    "wof:name":"The Beacon Institute Inc",
    "wof:placetype":"venue"
},
  "geometry": {"coordinates":[-73.97466,41.50752],"type":"Point"}
}