{
  "type": "Feature",
  "properties": {
    "iso:country":"US",
    "sg:address":"4105 Vestal Pkwy E",
    "sg:city":"Vestal",
    "sg:classifiers":[
        {
            "category":"Travel",
            "subcategory":"Hotels & Motels",
            "type":"Entertainment"
        }
    ],
    "sg:phone":"+1 607 729 6371",
    "sg:postcode":"13850",
    "sg:province":"NY",
    "wof:name":"Holiday Inn University",
    "wof:placetype":"venue"
},
  "geometry": {"coordinates":[-75.9734,42.095824],"type":"Point"}
}