{
  "type": "Feature",
  "properties": {
    "addr:full":"3449 Boston Rd Bronx NY 10469",
    "addr:housenumber":"3449",
    "addr:postcode":"10469",
    "addr:street":"Boston Rd",
    "iso:country":"US",
    "sg:address":"3449 Boston Rd",
    "sg:city":"Bronx",
    "sg:classifiers":[
        {
            "category":"Food & Beverages",
            "subcategory":"Groceries & Convenience Stores",
            "type":"Retail Goods"
        }
    ],
    "sg:phone":"+1   ",
    "sg:postcode":"10469",
    "sg:province":"NY",
    "wof:name":"Fine Fare Supermarket",
    "wof:placetype":"venue"
},
  "geometry": {"coordinates":[-73.848439,40.876416],"type":"Point"}
}