{
  "type": "Feature",
  "properties": {
    "addr:full":"258 E 7 St New York NY 10009",
    "addr:housenumber":"258;7",
    "addr:postcode":"10009",
    "addr:street":"E",
    "iso:country":"US",
    "sg:address":"258 E 7 St",
    "sg:city":"New York",
    "sg:classifiers":[
        {
            "category":"Real Estate",
            "subcategory":"Real Estate Operator",
            "type":"Services"
        }
    ],
    "sg:phone":"+1 212 475 6351",
    "sg:postcode":"10009",
    "sg:province":"NY",
    "sg:tags":[
        "owner",
        "building",
        "apartment"
    ],
    "wof:name":"Ora Shack",
    "wof:placetype":"venue"
},
  "geometry": {"coordinates":[-73.977256,40.723425],"type":"Point"}
}