{
  "type": "Feature",
  "properties": {
    "iso:country":"US",
    "sg:address":"137 Willett Ave",
    "sg:city":"Port Chester",
    "sg:classifiers":[
        {
            "category":"Food & Beverages",
            "subcategory":"Groceries & Convenience Stores",
            "type":"Retail Goods"
        }
    ],
    "sg:phone":"+1 914 939 8756",
    "sg:postcode":"10573",
    "sg:province":"NY",
    "wof:name":"L L Market",
    "wof:placetype":"venue"
},
  "geometry": {"coordinates":[-73.66262999999999,41.003126],"type":"Point"}
}