{
  "type": "Feature",
  "properties": {
    "addr:full":"4038 Victory Boulevard Staten Island NY 10314",
    "addr:housenumber":"4038",
    "addr:postcode":"10314",
    "addr:street":"Victory Boulevard",
    "iso:country":"US",
    "sg:address":"4038 Victory Boulevard",
    "sg:city":"Staten Island",
    "sg:classifiers":[
        {
            "category":"Arts & Performance",
            "subcategory":"Arts Center",
            "type":"Entertainment"
        }
    ],
    "sg:phone":"+1 718 982 0315",
    "sg:postcode":"10314",
    "sg:province":"NY",
    "sg:tags":[
        "performing"
    ],
    "wof:name":"Driven Dance Studio",
    "wof:placetype":"venue"
},
  "geometry": {"coordinates":[-74.188794,40.592785],"type":"Point"}
}