{
  "type": "Feature",
  "properties": {
    "iso:country":"US",
    "sg:address":"320 E 49 St",
    "sg:city":"Manhattan",
    "sg:classifiers":[
        {
            "category":"Personal",
            "subcategory":"Beauty Salon",
            "type":"Services"
        }
    ],
    "sg:phone":"+1 212 759 8160",
    "sg:postcode":"10017",
    "sg:province":"NY",
    "sg:tags":[
        "hair"
    ],
    "sg:website":"www.haircuttersofparis.com",
    "wof:name":"Hair Cutters Of Paris",
    "wof:placetype":"venue"
},
  "geometry": {"coordinates":[-73.96795899999999,40.753792],"type":"Point"}
}