{
  "type": "Feature",
  "properties": {
    "addr:full":"100 Corporate Woods Rochester NY 14623",
    "addr:housenumber":"100",
    "addr:postcode":"14623",
    "addr:street":"Corporate Woods",
    "iso:country":"US",
    "sg:address":"100 Corporate Woods",
    "sg:city":"Rochester",
    "sg:classifiers":[
        {
            "category":"Shopping",
            "subcategory":"Computers & Home Electronics",
            "type":"Retail Goods"
        }
    ],
    "sg:phone":"+1 585 240 6037",
    "sg:postcode":"14623",
    "sg:province":"NY",
    "sg:tags":[
        "software"
    ],
    "wof:name":"Microsoft Corp",
    "wof:placetype":"venue"
},
  "geometry": {"coordinates":[-77.621161,43.108034],"type":"Point"}
}