{
  "type": "Feature",
  "properties": {
    "addr:full":"201 W 21st St New York NY 10011",
    "addr:housenumber":"201",
    "addr:postcode":"10011",
    "addr:street":"W 21St St",
    "iso:country":"US",
    "sg:address":"201 W 21st St",
    "sg:city":"New York",
    "sg:classifiers":[
        {
            "category":"Building & Trades",
            "subcategory":"Locksmith",
            "type":"Services"
        }
    ],
    "sg:phone":"+1 212 367 9805",
    "sg:postcode":"10011",
    "sg:province":"NY",
    "sg:tags":[
        "key"
    ],
    "wof:name":"2nd Av Locksmith 24-Hr Service",
    "wof:placetype":"venue"
},
  "geometry": {"coordinates":[-73.998802,40.741501],"type":"Point"}
}