{
  "type": "Feature",
  "properties": {
    "iso:country":"US",
    "sg:address":"6795 Route 9",
    "sg:city":"Rhinebeck",
    "sg:classifiers":[
        {
            "category":"Fast Food",
            "type":"Food & Drink"
        },
        {
            "category":"Restaurant",
            "type":"Food & Drink"
        }
    ],
    "sg:phone":"+1 845 876 3499",
    "sg:postcode":"12572",
    "sg:province":"NY",
    "sg:tags":[
        "take"
    ],
    "wof:name":"Jade Palace",
    "wof:placetype":"venue"
},
  "geometry": {"coordinates":[-73.899086,41.950556],"type":"Point"}
}