{
  "type": "Feature",
  "properties": {
    "iso:country":"US",
    "sg:address":"1764 Walton Ave",
    "sg:city":"Bronx",
    "sg:classifiers":[
        {
            "category":"Personal",
            "subcategory":"Beauty Salon",
            "type":"Services"
        }
    ],
    "sg:phone":"+1   ",
    "sg:postcode":"10453",
    "sg:province":"NY",
    "sg:tags":[
        "shop"
    ],
    "wof:name":"5 Stars Unisex",
    "wof:placetype":"venue"
},
  "geometry": {"coordinates":[-73.910647,40.846979],"type":"Point"}
}