{
  "type": "Feature",
  "properties": {
    "addr:full":"1221 Western Ave Albany NY 12203",
    "addr:housenumber":"1221",
    "addr:postcode":"12203",
    "addr:street":"Western Ave",
    "iso:country":"US",
    "sg:address":"1221 Western Ave",
    "sg:city":"Albany",
    "sg:classifiers":[
        {
            "category":"Autos & Motor Vehicles",
            "subcategory":"Fuel & Gas Station",
            "type":"Retail Goods"
        }
    ],
    "sg:phone":"+1 518 489 1746",
    "sg:postcode":"12203",
    "sg:province":"NY",
    "sg:tags":[
        "oil"
    ],
    "wof:name":"Sunoco",
    "wof:placetype":"venue"
},
  "geometry": {"coordinates":[-73.82225,42.676172],"type":"Point"}
}