{
  "type": "Feature",
  "properties": {
    "addr:full":"2364 Lyell Ave Rochester NY 14606",
    "addr:housenumber":"2364",
    "addr:postcode":"14606",
    "addr:street":"Lyell Ave",
    "iso:country":"US",
    "sg:address":"2364 Lyell Ave",
    "sg:city":"Rochester",
    "sg:classifiers":[
        {
            "category":"Health Services",
            "subcategory":"Chiropractor",
            "type":"Services"
        }
    ],
    "sg:phone":"+1 585 429 5100",
    "sg:postcode":"14606",
    "sg:province":"NY",
    "wof:name":"Natural Health Chiropractic",
    "wof:placetype":"venue"
},
  "geometry": {"coordinates":[-77.69004,43.164779],"type":"Point"}
}