{
  "type": "Feature",
  "properties": {
    "iso:country":"US",
    "sg:address":"11 W 12th Rd",
    "sg:city":"Far Rockaway",
    "sg:classifiers":[
        {
            "category":"Manufacturing",
            "subcategory":"Printing",
            "type":"Manufacturing & Wholesale Goods"
        }
    ],
    "sg:phone":"+1   ",
    "sg:postcode":"11693",
    "sg:province":"NY",
    "sg:tags":[
        "cards",
        "greeting",
        "mfg"
    ],
    "wof:name":"Indigo Invitation",
    "wof:placetype":"venue"
},
  "geometry": {"coordinates":[-73.82247099999999,40.604727],"type":"Point"}
}