{
  "type": "Feature",
  "properties": {
    "addr:full":"638 Hertel Ave Buffalo NY 14207",
    "addr:housenumber":"638",
    "addr:postcode":"14207",
    "addr:street":"Hertel Ave",
    "iso:country":"US",
    "sg:address":"638 Hertel Ave",
    "sg:city":"Buffalo",
    "sg:classifiers":[
        {
            "category":"Building & Trades",
            "subcategory":"Construction",
            "type":"Services"
        }
    ],
    "sg:phone":"+1 716 836 8733",
    "sg:postcode":"14207",
    "sg:province":"NY",
    "sg:tags":[
        "contractor",
        "painter",
        "hanging"
    ],
    "wof:name":"Bennett Painting",
    "wof:placetype":"venue"
},
  "geometry": {"coordinates":[-78.884697,42.947498],"type":"Point"}
}