{
  "type": "Feature",
  "properties": {
    "addr:full":"3901 Hempstead Tpke Bethpage NY 11714",
    "addr:housenumber":"3901",
    "addr:postcode":"11714",
    "addr:street":"Hempstead Tpke",
    "iso:country":"US",
    "sg:address":"3901 Hempstead Tpke",
    "sg:city":"Bethpage",
    "sg:classifiers":[
        {
            "category":"Food & Beverages",
            "subcategory":"Groceries & Convenience Stores",
            "type":"Retail Goods"
        }
    ],
    "sg:phone":"+1   ",
    "sg:postcode":"11714",
    "sg:province":"NY",
    "sg:website":"www.pathmark.com",
    "wof:name":"Pathmark",
    "wof:placetype":"venue"
},
  "geometry": {"coordinates":[-73.491837,40.725614],"type":"Point"}
}