{
  "type": "Feature",
  "properties": {
    "addr:full":"4280 Richmond Ave Staten Island NY 10312",
    "addr:housenumber":"4280",
    "addr:postcode":"10312",
    "addr:street":"Richmond Ave",
    "iso:country":"US",
    "sg:address":"4280 Richmond Ave",
    "sg:city":"Staten Island",
    "sg:classifiers":[
        {
            "category":"Professional",
            "subcategory":"Management & Consulting",
            "type":"Services"
        }
    ],
    "sg:phone":"+1 718 984 6713",
    "sg:postcode":"10312",
    "sg:province":"NY",
    "wof:name":"Starr Management",
    "wof:placetype":"venue"
},
  "geometry": {"coordinates":[-74.154515,40.534569],"type":"Point"}
}