{
  "type": "Feature",
  "properties": {
    "addr:full":"240 E 58th St New York NY 10022",
    "addr:housenumber":"240",
    "addr:postcode":"10022",
    "addr:street":"E 58Th St",
    "iso:country":"US",
    "sg:address":"240 E 58th St",
    "sg:city":"New York",
    "sg:classifiers":[
        {
            "category":"Restaurant",
            "type":"Food & Drink"
        },
        {
            "category":"Retail",
            "subcategory":"Event Space",
            "type":"Services"
        }
    ],
    "sg:phone":"+1 212 688 4190",
    "sg:postcode":"10022",
    "sg:province":"NY",
    "sg:tags":[
        "venue",
        "steakhouse"
    ],
    "sg:website":"www.clubasteakhouse.com",
    "wof:name":"Club A Steakhouse",
    "wof:placetype":"venue"
},
  "geometry": {"coordinates":[-73.965547,40.760178],"type":"Point"}
}