{
  "type": "Feature",
  "properties": {
    "addr:full":"6 Green Ln Woodridge NY 12754",
    "addr:housenumber":"6",
    "addr:postcode":"12754",
    "addr:street":"Green Ln",
    "iso:country":"US",
    "sg:address":"6 Green Ln",
    "sg:city":"Woodridge",
    "sg:classifiers":[
        {
            "category":"Restaurant",
            "type":"Food & Drink"
        }
    ],
    "sg:phone":"+1 845 434 1088",
    "sg:postcode":"12754",
    "sg:province":"NY",
    "sg:tags":[
        "caterer"
    ],
    "wof:name":"Yoni's",
    "wof:placetype":"venue"
},
  "geometry": {"coordinates":[-74.747962,41.798547],"type":"Point"}
}