{
  "type": "Feature",
  "properties": {
    "iso:country":"US",
    "sg:address":"1666 Bathgate Ave",
    "sg:city":"Bronx",
    "sg:classifiers":[
        {
            "category":"Government",
            "subcategory":"Office",
            "type":"Public Place"
        }
    ],
    "sg:phone":"+1 718 716 7030",
    "sg:postcode":"10457",
    "sg:province":"NY",
    "sg:tags":[
        "job"
    ],
    "wof:name":"S U N Y Brnx Ed Opprtnty Cntr",
    "wof:placetype":"venue"
},
  "geometry": {"coordinates":[-73.90057899999999,40.840099],"type":"Point"}
}