{
  "type": "Feature",
  "properties": {
    "addr:full":"5002 S Catherine St Plattsburgh NY 12901",
    "addr:housenumber":"5002",
    "addr:postcode":"12901",
    "addr:street":"S Catherine St",
    "iso:country":"US",
    "sg:address":"5002 S Catherine St",
    "sg:city":"Plattsburgh",
    "sg:classifiers":[
        {
            "category":"Utilities",
            "subcategory":"Telephone",
            "type":"Services"
        }
    ],
    "sg:phone":"+1   ",
    "sg:postcode":"12901",
    "sg:province":"NY",
    "sg:tags":[
        "company"
    ],
    "wof:name":"Verizon",
    "wof:placetype":"venue"
},
  "geometry": {"coordinates":[-73.457589,44.689521],"type":"Point"}
}