{
  "type": "Feature",
  "properties": {
    "addr:full":"21 E 40th Street Suite 2002 New York NY 10016",
    "addr:housenumber":"21",
    "addr:postcode":"10016",
    "addr:street":"E 40Th Street Suite 2002",
    "iso:country":"US",
    "sg:address":"21 E 40th Street Suite 2002",
    "sg:city":"New York",
    "sg:classifiers":[
        {
            "category":"Professional",
            "subcategory":"Lawyer & Legal Services",
            "type":"Services"
        }
    ],
    "sg:phone":"+1 212 889 5511",
    "sg:postcode":"10016",
    "sg:province":"NY",
    "wof:name":"John Rodriquez Esquire",
    "wof:placetype":"venue"
},
  "geometry": {"coordinates":[-73.980189,40.751507],"type":"Point"}
}