{
  "type": "Feature",
  "properties": {
    "iso:country":"US",
    "sg:address":"156 E Main St",
    "sg:city":"Amsterdam",
    "sg:classifiers":[
        {
            "category":"Organizations",
            "subcategory":"Religious Organization",
            "type":"Services"
        }
    ],
    "sg:phone":"+1 518 842 4500",
    "sg:postcode":"12010",
    "sg:province":"NY",
    "sg:tags":[
        "clergy"
    ],
    "wof:name":"St Mary's Rectory",
    "wof:placetype":"venue"
},
  "geometry": {"coordinates":[-74.187439,42.93491],"type":"Point"}
}