{
  "type": "Feature",
  "properties": {
    "iso:country":"US",
    "sg:address":"9010 Jamaica Avenue",
    "sg:city":"Woodhaven",
    "sg:classifiers":[
        {
            "category":"Restaurant",
            "type":"Food & Drink"
        }
    ],
    "sg:phone":"+1 718 849 9300",
    "sg:postcode":"11421",
    "sg:province":"NY",
    "sg:tags":[
        "pizza"
    ],
    "wof:name":"Daleo's Pizza & Italian Corporation",
    "wof:placetype":"venue"
},
  "geometry": {"coordinates":[-73.854349,40.69279],"type":"Point"}
}