{
  "type": "Feature",
  "properties": {
    "iso:country":"US",
    "sg:address":"91 Chichester Rd",
    "sg:city":"Huntington",
    "sg:classifiers":[
        {
            "category":"Health Services",
            "subcategory":"Doctor",
            "type":"Services"
        }
    ],
    "sg:phone":"+1 631 423 0290",
    "sg:postcode":"11743",
    "sg:province":"NY",
    "sg:tags":[
        "medical"
    ],
    "wof:name":"Marvin Glassmann",
    "wof:placetype":"venue"
},
  "geometry": {"coordinates":[-73.42128200000001,40.819939],"type":"Point"}
}