{
  "type": "Feature",
  "properties": {
    "addr:full":"1800 Old Country Rd Riverhead NY 11901",
    "addr:housenumber":"1800",
    "addr:postcode":"11901",
    "addr:street":"Old Country Rd",
    "iso:country":"US",
    "sg:address":"1800 Old Country Rd",
    "sg:city":"Riverhead",
    "sg:classifiers":[
        {
            "category":"Autos & Motor Vehicles",
            "subcategory":"Automobile Sales",
            "type":"Retail Goods"
        },
        {
            "category":"Retail",
            "subcategory":"Auto Rental",
            "type":"Services"
        },
        {
            "category":"Retail",
            "subcategory":"Auto Repair",
            "type":"Services"
        }
    ],
    "sg:phone":"+1 631 369 2108",
    "sg:postcode":"11901",
    "sg:province":"NY",
    "sg:tags":[
        "car"
    ],
    "wof:name":"Riverhead Auto Mall",
    "wof:placetype":"venue"
},
  "geometry": {"coordinates":[-72.70819899999999,40.923901],"type":"Point"}
}