{
  "type": "Feature",
  "properties": {
    "iso:country":"US",
    "sg:address":"147 Jay St",
    "sg:city":"Schenectady",
    "sg:classifiers":[
        {
            "category":"Personal",
            "subcategory":"Beauty Salon",
            "type":"Services"
        }
    ],
    "sg:phone":"+1 518 393 3654",
    "sg:postcode":"12305",
    "sg:province":"NY",
    "sg:tags":[
        "parlor"
    ],
    "wof:name":"Majestic Beauty Salon",
    "wof:placetype":"venue"
},
  "geometry": {"coordinates":[-73.940617,42.813321],"type":"Point"}
}