{
  "type": "Feature",
  "properties": {
    "addr:full":"126 W 25th St New York NY 10001",
    "addr:housenumber":"126",
    "addr:postcode":"10001",
    "addr:street":"W 25Th St",
    "iso:country":"US",
    "sg:address":"126 W 25th St",
    "sg:city":"New York",
    "sg:classifiers":[
        {
            "category":"Wholesale",
            "subcategory":"Chemicals & Plastics",
            "type":"Manufacturing & Wholesale Goods"
        }
    ],
    "sg:phone":"+1 212 633 1508",
    "sg:postcode":"10001",
    "sg:province":"NY",
    "sg:tags":[
        "clothing"
    ],
    "wof:name":"Siegel & Stockman Inc",
    "wof:placetype":"venue"
},
  "geometry": {"coordinates":[-73.994175,40.745],"type":"Point"}
}