{
  "type": "Feature",
  "properties": {
    "iso:country":"US",
    "sg:address":"1972 65th St",
    "sg:city":"Brooklyn",
    "sg:classifiers":[
        {
            "category":"Restaurant",
            "type":"Food & Drink"
        }
    ],
    "sg:phone":"+1   ",
    "sg:postcode":"11204",
    "sg:province":"NY",
    "sg:tags":[
        "eating"
    ],
    "wof:name":"Chan Fat Keung",
    "wof:placetype":"venue"
},
  "geometry": {"coordinates":[-73.987137,40.61744],"type":"Point"}
}