{
  "type": "Feature",
  "properties": {
    "iso:country":"US",
    "sg:address":"107 South St",
    "sg:city":"Oyster Bay",
    "sg:classifiers":[
        {
            "category":"Restaurant",
            "type":"Food & Drink"
        }
    ],
    "sg:phone":"+1 516 624 7410",
    "sg:postcode":"11771",
    "sg:province":"NY",
    "wof:name":"Homestead Restaurant",
    "wof:placetype":"venue"
},
  "geometry": {"coordinates":[-73.530582,40.872282],"type":"Point"}
}