{
  "type": "Feature",
  "properties": {
    "iso:country":"US",
    "sg:address":"91 E Main St",
    "sg:city":"Webster",
    "sg:classifiers":[
        {
            "category":"Farming",
            "subcategory":"Farm",
            "type":"Manufacturing & Wholesale Goods"
        }
    ],
    "sg:phone":"+1 585 265 9809",
    "sg:postcode":"14580",
    "sg:province":"NY",
    "sg:tags":[
        "crop",
        "general"
    ],
    "wof:name":"Mark E Schreiber Farms Inc",
    "wof:placetype":"venue"
},
  "geometry": {"coordinates":[-77.42661699999999,43.212634],"type":"Point"}
}