{
  "type": "Feature",
  "properties": {
    "addr:full":"311 East 38th Street Suite 19B New York NY 10016",
    "addr:housenumber":"311;19b",
    "addr:postcode":"10016",
    "addr:street":"East 38Th Street Suite",
    "iso:country":"US",
    "sg:address":"311 East 38th Street Suite 19B",
    "sg:city":"New York",
    "sg:classifiers":[
        {
            "category":"Professional",
            "subcategory":"Advertising",
            "type":"Services"
        }
    ],
    "sg:phone":"+1 646 706 1001",
    "sg:postcode":"10016",
    "sg:province":"NY",
    "sg:website":"http://www.transittreasure.com",
    "wof:name":"Transit Treasure",
    "wof:placetype":"venue"
},
  "geometry": {"coordinates":[-73.973693,40.747303],"type":"Point"}
}