{
  "type": "Feature",
  "properties": {
    "iso:country":"US",
    "sg:address":"138 Roosevelt Dr",
    "sg:city":"West Haverstraw",
    "sg:classifiers":[
        {
            "category":"Shopping",
            "subcategory":"Catalog Store",
            "type":"Retail Goods"
        }
    ],
    "sg:phone":"+1 845 786 5819",
    "sg:postcode":"10993",
    "sg:province":"NY",
    "sg:tags":[
        "internet"
    ],
    "sg:website":"www.kidbrook.com",
    "wof:name":"Kidbrook Industries",
    "wof:placetype":"venue"
},
  "geometry": {"coordinates":[-73.98797500000001,41.206243],"type":"Point"}
}