{
  "type": "Feature",
  "properties": {
    "iso:country":"US",
    "sg:address":"1109 Delaware Ave",
    "sg:city":"Buffalo",
    "sg:classifiers":[
        {
            "category":"Social Services",
            "type":"Services"
        }
    ],
    "sg:phone":"+1 716 882 2861",
    "sg:postcode":"14209",
    "sg:province":"NY",
    "sg:tags":[
        "counselor",
        "marriage",
        "family"
    ],
    "wof:name":"Stephanie A Artis",
    "wof:placetype":"venue"
},
  "geometry": {"coordinates":[-78.869111,42.915324],"type":"Point"}
}