{
  "type": "Feature",
  "properties": {
    "addr:full":"7475 State Hwy 5 St Johnsville NY 13452",
    "addr:housenumber":"7475",
    "addr:postcode":"13452",
    "addr:street":"State Hwy 5 St",
    "iso:country":"US",
    "sg:address":"7475 State Hwy 5",
    "sg:city":"St Johnsville",
    "sg:classifiers":[
        {
            "category":"Manufacturing",
            "subcategory":"Chemicals & Compounds",
            "type":"Manufacturing & Wholesale Goods"
        }
    ],
    "sg:phone":"+1 518 568 5468",
    "sg:postcode":"13452",
    "sg:province":"NY",
    "sg:tags":[
        "compost"
    ],
    "wof:name":"Mohawk Valley Organics",
    "wof:placetype":"venue"
},
  "geometry": {"coordinates":[-74.65752999999999,42.992945],"type":"Point"}
}