{
  "type": "Feature",
  "properties": {
    "addr:full":"300 Park Ave Deer Park NY 11729",
    "addr:housenumber":"300",
    "addr:postcode":"11729",
    "addr:street":"Park Ave",
    "iso:country":"US",
    "sg:address":"300 Park Ave",
    "sg:city":"Deer Park",
    "sg:classifiers":[
        {
            "category":"Education",
            "subcategory":"School",
            "type":"Public Place"
        }
    ],
    "sg:phone":"+1 631 242 5731",
    "sg:postcode":"11729",
    "sg:province":"NY",
    "wof:name":"Abraham Lincoln School",
    "wof:placetype":"venue"
},
  "geometry": {"coordinates":[-73.33829299999999,40.75241],"type":"Point"}
}