{
  "type": "Feature",
  "properties": {
    "addr:full":"2159 Welker Rd Penn Yan NY 14527",
    "addr:housenumber":"2159",
    "addr:postcode":"14527",
    "addr:street":"Welker Rd",
    "iso:country":"US",
    "sg:address":"2159 Welker Rd",
    "sg:city":"Penn Yan",
    "sg:classifiers":[
        {
            "category":"Farming",
            "subcategory":"Farm",
            "type":"Manufacturing & Wholesale Goods"
        }
    ],
    "sg:phone":"+1 315 536 6532",
    "sg:postcode":"14527",
    "sg:province":"NY",
    "sg:tags":[
        "crop",
        "general"
    ],
    "wof:name":"Irvin Zimmerman",
    "wof:placetype":"venue"
},
  "geometry": {"coordinates":[-77.047704,42.559105],"type":"Point"}
}