{
  "type": "Feature",
  "properties": {
    "iso:country":"US",
    "sg:address":"125 Malcolm X Blvd",
    "sg:city":"Brooklyn",
    "sg:classifiers":[
        {
            "category":"Shopping",
            "subcategory":"Discount & Variety Stores",
            "type":"Retail Goods"
        }
    ],
    "sg:phone":"+1 718 919 6513",
    "sg:postcode":"11221",
    "sg:province":"NY",
    "sg:tags":[
        "merchandise",
        "general"
    ],
    "wof:name":"Jo Store",
    "wof:placetype":"venue"
},
  "geometry": {"coordinates":[-73.93017999999999,40.688565],"type":"Point"}
}