{
  "type": "Feature",
  "properties": {
    "iso:country":"US",
    "sg:address":"195 Jasper St",
    "sg:city":"Syracuse",
    "sg:classifiers":[
        {
            "category":"Personal",
            "subcategory":"Barber",
            "type":"Services"
        }
    ],
    "sg:phone":"+1 315 426 0791",
    "sg:postcode":"13203",
    "sg:province":"NY",
    "wof:name":"James P Wachter",
    "wof:placetype":"venue"
},
  "geometry": {"coordinates":[-76.14123499999999,43.062187],"type":"Point"}
}