{
  "type": "Feature",
  "properties": {
    "addr:full":"7 Wainer Ct Centerport NY 11721",
    "addr:housenumber":"7",
    "addr:postcode":"11721",
    "addr:street":"Wainer Ct",
    "iso:country":"US",
    "sg:address":"7 Wainer Ct",
    "sg:city":"Centerport",
    "sg:classifiers":[
        {
            "category":"Professional",
            "subcategory":"Management & Consulting",
            "type":"Services"
        }
    ],
    "sg:phone":"+1   ",
    "sg:postcode":"11721",
    "sg:province":"NY",
    "sg:tags":[
        "marketing",
        "consultant"
    ],
    "wof:name":"Proactive Marketing",
    "wof:placetype":"venue"
},
  "geometry": {"coordinates":[-73.374982,40.890118],"type":"Point"}
}