{
  "type": "Feature",
  "properties": {
    "addr:full":"1959 Birchall Avenue Bronx NY 10462",
    "addr:housenumber":"1959",
    "addr:postcode":"10462",
    "addr:street":"Birchall Avenue",
    "iso:country":"US",
    "sg:address":"1959 Birchall Avenue",
    "sg:city":"Bronx",
    "sg:classifiers":[
        {
            "category":"Autos & Motor Vehicles",
            "subcategory":"Auto Supplies",
            "type":"Retail Goods"
        }
    ],
    "sg:phone":"+1 718 829 8989",
    "sg:postcode":"10462",
    "sg:province":"NY",
    "sg:tags":[
        "tire"
    ],
    "wof:name":"National Discount Tires",
    "wof:placetype":"venue"
},
  "geometry": {"coordinates":[-73.868786,40.848556],"type":"Point"}
}