{
  "type": "Feature",
  "properties": {
    "iso:country":"US",
    "sg:address":"119 Russet Ln",
    "sg:city":"Syracuse",
    "sg:classifiers":[
        {
            "category":"Banks & Credit Unions",
            "subcategory":"Investment Brokerage",
            "type":"Services"
        }
    ],
    "sg:phone":"+1 315 488 4806",
    "sg:postcode":"13209",
    "sg:province":"NY",
    "sg:tags":[
        "security"
    ],
    "wof:name":"Brusa Enterprises",
    "wof:placetype":"venue"
},
  "geometry": {"coordinates":[-76.209424,43.058879],"type":"Point"}
}