{
  "type": "Feature",
  "properties": {
    "addr:full":"2170 3rd Ave New York NY 10035",
    "addr:housenumber":"2170",
    "addr:postcode":"10035",
    "addr:street":"3Rd Ave",
    "iso:country":"US",
    "sg:address":"2170 3rd Ave",
    "sg:city":"New York",
    "sg:classifiers":[
        {
            "category":"Restaurant",
            "type":"Food & Drink"
        }
    ],
    "sg:menulink":"http://www.allmenus.com/ny/new-york/254634-unicorn-restaurant/menu/",
    "sg:phone":"+1 212 426 8821",
    "sg:postcode":"10035",
    "sg:province":"NY",
    "sg:tags":[
        "asian",
        "chinese"
    ],
    "wof:name":"Unicorn Restaurant",
    "wof:placetype":"venue"
},
  "geometry": {"coordinates":[-73.938777,40.799632],"type":"Point"}
}