{
  "type": "Feature",
  "properties": {
    "addr:full":"1673 Empire Blvd Webster NY 14580",
    "addr:housenumber":"1673",
    "addr:postcode":"14580",
    "addr:street":"Empire Blvd",
    "iso:country":"US",
    "sg:address":"1673 Empire Blvd",
    "sg:city":"Webster",
    "sg:classifiers":[
        {
            "category":"Personal",
            "subcategory":"Beauty Salon",
            "type":"Services"
        }
    ],
    "sg:phone":"+1 585 671 6131",
    "sg:postcode":"14580",
    "sg:province":"NY",
    "wof:name":"Hair Zoo Family Hair Salons",
    "wof:placetype":"venue"
},
  "geometry": {"coordinates":[-77.506826,43.184493],"type":"Point"}
}