{
  "type": "Feature",
  "properties": {
    "iso:country":"US",
    "sg:address":"23 Treyer St",
    "sg:city":"Rochester",
    "sg:classifiers":[
        {
            "category":"Building & Trades",
            "subcategory":"Construction",
            "type":"Services"
        }
    ],
    "sg:phone":"+1 585 467 7056",
    "sg:postcode":"14621",
    "sg:province":"NY",
    "sg:tags":[
        "remodeling",
        "general"
    ],
    "wof:name":"Alvardo Construction",
    "wof:placetype":"venue"
},
  "geometry": {"coordinates":[-77.61543500000001,43.177094],"type":"Point"}
}