{
  "type": "Feature",
  "properties": {
    "addr:full":"1044 3rd Avenue New York NY 10021",
    "addr:housenumber":"1044",
    "addr:postcode":"10021",
    "addr:street":"3Rd Avenue",
    "iso:country":"US",
    "sg:address":"1044 3rd Avenue",
    "sg:city":"New York",
    "sg:classifiers":[
        {
            "category":"Retail",
            "subcategory":"Pet Boarding",
            "type":"Services"
        }
    ],
    "sg:phone":"+1 212 861 8100",
    "sg:postcode":"10021",
    "sg:province":"NY",
    "sg:tags":[
        "boarding/pet",
        "sitting"
    ],
    "wof:name":"Le Chien Pet Salon",
    "wof:placetype":"venue"
},
  "geometry": {"coordinates":[-73.965232,40.763163],"type":"Point"}
}