{
  "type": "Feature",
  "properties": {
    "iso:country":"US",
    "sg:address":"63 W Barney St",
    "sg:city":"Gouverneur",
    "sg:classifiers":[
        {
            "category":"Health Services",
            "subcategory":"Doctor",
            "type":"Services"
        }
    ],
    "sg:phone":"+1 315 287 1170",
    "sg:postcode":"13642",
    "sg:province":"NY",
    "sg:tags":[
        "physician",
        "family",
        "medical",
        "practice",
        "surgeons",
        "medicine",
        "surgeon"
    ],
    "wof:name":"Abdur Jalalzai Md Pc",
    "wof:placetype":"venue"
},
  "geometry": {"coordinates":[-75.47395899999999,44.338376],"type":"Point"}
}