{
  "type": "Feature",
  "properties": {
    "addr:full":"873 State Hwy 36 Troupsburg NY 14885",
    "addr:housenumber":"873",
    "addr:postcode":"14885",
    "addr:street":"State Hwy 36",
    "iso:country":"US",
    "sg:address":"873 State Hwy 36",
    "sg:city":"Troupsburg",
    "sg:classifiers":[
        {
            "category":"Health Services",
            "subcategory":"Hospital",
            "type":"Services"
        }
    ],
    "sg:phone":"+1   ",
    "sg:postcode":"14885",
    "sg:province":"NY",
    "sg:tags":[
        "medical",
        "specialty"
    ],
    "wof:name":"Greenwood Health Center",
    "wof:placetype":"venue"
},
  "geometry": {"coordinates":[-77.54513300000001,42.04118],"type":"Point"}
}