{
  "type": "Feature",
  "properties": {
    "iso:country":"US",
    "sg:address":"813 Southern Blvd",
    "sg:city":"Bronx",
    "sg:classifiers":[
        {
            "category":"Health Services",
            "subcategory":"Health Practitioner",
            "type":"Services"
        }
    ],
    "sg:phone":"+1   ",
    "sg:postcode":"10459",
    "sg:province":"NY",
    "wof:name":"Fred M Daniels",
    "wof:placetype":"venue"
},
  "geometry": {"coordinates":[-73.89561500000001,40.816934],"type":"Point"}
}