{
  "type": "Feature",
  "properties": {
    "addr:full":"19219 Linden Blvd Saint Albans NY 11412",
    "addr:housenumber":"19219",
    "addr:postcode":"11412",
    "addr:street":"Linden Blvd",
    "iso:country":"US",
    "sg:address":"19219 Linden Blvd",
    "sg:city":"Saint Albans",
    "sg:classifiers":[
        {
            "category":"Building & Trades",
            "subcategory":"Plumbing",
            "type":"Services"
        }
    ],
    "sg:phone":"+1 718 527 8318",
    "sg:postcode":"11412",
    "sg:province":"NY",
    "wof:name":"Hydroflow Plumbing & Heating",
    "wof:placetype":"venue"
},
  "geometry": {"coordinates":[-73.758698,40.692799],"type":"Point"}
}