{
  "type": "Feature",
  "properties": {
    "iso:country":"US",
    "sg:address":"672 Seaview Ave",
    "sg:city":"Staten Island",
    "sg:classifiers":[
        {
            "category":"Building & Trades",
            "subcategory":"Construction",
            "type":"Services"
        }
    ],
    "sg:phone":"+1 718 987 9494",
    "sg:postcode":"10305",
    "sg:province":"NY",
    "sg:tags":[
        "contractor"
    ],
    "wof:name":"NS T Contracting",
    "wof:placetype":"venue"
},
  "geometry": {"coordinates":[-74.081632,40.581354],"type":"Point"}
}