{
  "type": "Feature",
  "properties": {
    "addr:full":"28 Vine Rd Rocky Point NY 11778",
    "addr:housenumber":"28",
    "addr:postcode":"11778",
    "addr:street":"Vine Rd",
    "iso:country":"US",
    "sg:address":"28 Vine Rd",
    "sg:city":"Rocky Point",
    "sg:classifiers":[
        {
            "category":"Building & Trades",
            "subcategory":"Construction",
            "type":"Services"
        }
    ],
    "sg:phone":"+1 631 744 0978",
    "sg:postcode":"11778",
    "sg:province":"NY",
    "sg:tags":[
        "flooring",
        "contractor"
    ],
    "wof:name":"North Shore Hardwood Flooring",
    "wof:placetype":"venue"
},
  "geometry": {"coordinates":[-72.93136800000001,40.961057],"type":"Point"}
}