{
  "type": "Feature",
  "properties": {
    "iso:country":"US",
    "sg:address":"151 W Matson Ave",
    "sg:city":"Syracuse",
    "sg:classifiers":[
        {
            "category":"Social Services",
            "subcategory":"Child Care",
            "type":"Services"
        }
    ],
    "sg:phone":"+1 315 469 1802",
    "sg:postcode":"13205",
    "sg:province":"NY",
    "wof:name":"Moments Daycare",
    "wof:placetype":"venue"
},
  "geometry": {"coordinates":[-76.14639699999999,43.01307],"type":"Point"}
}