{
  "type": "Feature",
  "properties": {
    "iso:country":"US",
    "sg:address":"32 Park St",
    "sg:city":"Canton",
    "sg:classifiers":[
        {
            "category":"Retail",
            "subcategory":"Funeral Services",
            "type":"Services"
        }
    ],
    "sg:phone":"+1 315 386 8528",
    "sg:postcode":"13617",
    "sg:province":"NY",
    "sg:tags":[
        "director"
    ],
    "wof:name":"O'Leary Funeral Svc",
    "wof:placetype":"venue"
},
  "geometry": {"coordinates":[-75.168027,44.593742],"type":"Point"}
}