{
  "type": "Feature",
  "properties": {
    "addr:full":"140 Cabrini Blvd New York NY 10033",
    "addr:housenumber":"140",
    "addr:postcode":"10033",
    "addr:street":"Cabrini Blvd",
    "iso:country":"US",
    "sg:address":"140 Cabrini Blvd",
    "sg:city":"New York",
    "sg:classifiers":[
        {
            "category":"Professional",
            "subcategory":"Business Services",
            "type":"Services"
        }
    ],
    "sg:phone":"+1 212 795 5503",
    "sg:postcode":"10033",
    "sg:province":"NY",
    "sg:tags":[
        "computerized",
        "translation"
    ],
    "wof:name":"Applied Knowledge Systems Intl",
    "wof:placetype":"venue"
},
  "geometry": {"coordinates":[-73.93865099999999,40.854676],"type":"Point"}
}