{
  "type": "Feature",
  "properties": {
    "addr:full":"25173 Jericho Tpke Bellerose NY 11426",
    "addr:housenumber":"25173",
    "addr:postcode":"11426",
    "addr:street":"Jericho Tpke",
    "iso:country":"US",
    "sg:address":"25173 Jericho Tpke",
    "sg:city":"Bellerose",
    "sg:classifiers":[
        {
            "category":"Building & Trades",
            "subcategory":"Construction",
            "type":"Services"
        }
    ],
    "sg:phone":"+1 718 347 0880",
    "sg:postcode":"11426",
    "sg:province":"NY",
    "sg:tags":[
        "contractor",
        "mechanical"
    ],
    "wof:name":"Carl Hilaire",
    "wof:placetype":"venue"
},
  "geometry": {"coordinates":[-73.722752,40.724855],"type":"Point"}
}