{
  "type": "Feature",
  "properties": {
    "addr:full":"15 Valencia Dr Rochester NY 14606",
    "addr:housenumber":"15",
    "addr:postcode":"14606",
    "addr:street":"Valencia Dr",
    "iso:country":"US",
    "sg:address":"15 Valencia Dr",
    "sg:city":"Rochester",
    "sg:classifiers":[
        {
            "category":"Building & Trades",
            "subcategory":"Landscaping Services",
            "type":"Services"
        }
    ],
    "sg:phone":"+1 585 426 6834",
    "sg:postcode":"14606",
    "sg:province":"NY",
    "sg:tags":[
        "lawn",
        "maintenance",
        "grounds"
    ],
    "wof:name":"Field's Of Green Lawncare",
    "wof:placetype":"venue"
},
  "geometry": {"coordinates":[-77.69156,43.177229],"type":"Point"}
}