{
  "type": "Feature",
  "properties": {
    "addr:full":"174 Broadway New York NY 10038",
    "addr:housenumber":"174",
    "addr:postcode":"10038",
    "addr:street":"Broadway",
    "iso:country":"US",
    "sg:address":"174 Broadway",
    "sg:city":"New York",
    "sg:classifiers":[
        {
            "category":"Insurance",
            "subcategory":"Health Insurance",
            "type":"Services"
        }
    ],
    "sg:phone":"+1 212 233 4588",
    "sg:postcode":"10038",
    "sg:province":"NY",
    "sg:tags":[
        "market"
    ],
    "sg:website":"www.vitaminshoppe.com/",
    "wof:name":"The Vitamin Shoppe",
    "wof:placetype":"venue"
},
  "geometry": {"coordinates":[-74.009705,40.709802],"type":"Point"}
}