{
  "type": "Feature",
  "properties": {
    "iso:country":"US",
    "sg:address":"2253 State Hwy 5",
    "sg:city":"Utica",
    "sg:classifiers":[
        {
            "category":"Real Estate",
            "subcategory":"Developer",
            "type":"Services"
        }
    ],
    "sg:phone":"+1 315 866 9044",
    "sg:postcode":"13502",
    "sg:province":"NY",
    "wof:name":"Para-Future Development Corp",
    "wof:placetype":"venue"
},
  "geometry": {"coordinates":[-75.15554299999999,43.100439],"type":"Point"}
}