{
  "type": "Feature",
  "properties": {
    "iso:country":"US",
    "sg:address":"1860 E Tremont Ave",
    "sg:city":"Bronx",
    "sg:classifiers":[
        {
            "category":"Professional",
            "type":"Services"
        }
    ],
    "sg:phone":"+1 718 792 7688",
    "sg:postcode":"10460",
    "sg:province":"NY",
    "sg:tags":[
        "establishment"
    ],
    "wof:name":"CBNA",
    "wof:placetype":"venue"
},
  "geometry": {"coordinates":[-73.864465,40.841088],"type":"Point"}
}