{
  "type": "Feature",
  "properties": {
    "iso:country":"US",
    "sg:address":"251 Seeley St",
    "sg:city":"Brooklyn",
    "sg:classifiers":[
        {
            "category":"Food & Beverages",
            "subcategory":"Liquor & Beverages",
            "type":"Retail Goods"
        }
    ],
    "sg:phone":"+1   ",
    "sg:postcode":"11218",
    "sg:province":"NY",
    "sg:tags":[
        "grocery",
        "alcoholic"
    ],
    "wof:name":"Jaffal Grocery Inc",
    "wof:placetype":"venue"
},
  "geometry": {"coordinates":[-73.974098,40.655462],"type":"Point"}
}