{
  "type": "Feature",
  "properties": {
    "iso:country":"US",
    "sg:address":"7822 3rd Avenue",
    "sg:city":"Brooklyn",
    "sg:classifiers":[
        {
            "category":"Restaurant",
            "type":"Food & Drink"
        }
    ],
    "sg:phone":"+1 718 921 5900",
    "sg:postcode":"11209",
    "sg:province":"NY",
    "wof:name":"Off Shore Restaurant",
    "wof:placetype":"venue"
},
  "geometry": {"coordinates":[-74.02907999999999,40.628685],"type":"Point"}
}