{
  "type": "Feature",
  "properties": {
    "iso:country":"US",
    "sg:address":"159 Woodland Dr",
    "sg:city":"Mastic Beach",
    "sg:classifiers":[
        {
            "category":"Retail",
            "subcategory":"Animal Services",
            "type":"Services"
        }
    ],
    "sg:phone":"+1 631 878 2919",
    "sg:postcode":"11951",
    "sg:province":"NY",
    "sg:tags":[
        "shelter"
    ],
    "wof:name":"Manorville Humane Society",
    "wof:placetype":"venue"
},
  "geometry": {"coordinates":[-72.835932,40.769369],"type":"Point"}
}