{
  "type": "Feature",
  "properties": {
    "iso:country":"US",
    "sg:address":"34 Saint Johns Place",
    "sg:city":"Brooklyn",
    "sg:classifiers":[
        {
            "category":"Social Services",
            "subcategory":"Child Care",
            "type":"Services"
        }
    ],
    "sg:phone":"+1 718 789 0008",
    "sg:postcode":"11217",
    "sg:province":"NY",
    "sg:tags":[
        "day"
    ],
    "wof:name":"St Johns Kidz",
    "wof:placetype":"venue"
},
  "geometry": {"coordinates":[-73.97814200000001,40.677912],"type":"Point"}
}