{
  "type": "Feature",
  "properties": {
    "addr:full":"930 McDonald Ave Brooklyn NY 11218",
    "addr:housenumber":"930",
    "addr:postcode":"11218",
    "addr:street":"Mcdonald Ave",
    "iso:country":"US",
    "sg:address":"930 McDonald Ave",
    "sg:city":"Brooklyn",
    "sg:classifiers":[
        {
            "category":"Building & Trades",
            "subcategory":"Construction",
            "type":"Services"
        }
    ],
    "sg:phone":"+1 718 338 7773",
    "sg:postcode":"11218",
    "sg:province":"NY",
    "sg:tags":[
        "contractor"
    ],
    "wof:name":"L B Glass & Mirror Inc",
    "wof:placetype":"venue"
},
  "geometry": {"coordinates":[-73.977502,40.63258],"type":"Point"}
}