{
  "type": "Feature",
  "properties": {
    "addr:full":"165 S Wellwood Ave Lindenhurst NY 11757",
    "addr:housenumber":"165",
    "addr:postcode":"11757",
    "addr:street":"S Wellwood Ave",
    "iso:country":"US",
    "sg:address":"165 S Wellwood Ave",
    "sg:city":"Lindenhurst",
    "sg:classifiers":[
        {
            "category":"Building & Trades",
            "subcategory":"Equipment Rental",
            "type":"Services"
        }
    ],
    "sg:phone":"+1 631 225 5111",
    "sg:postcode":"11757",
    "sg:province":"NY",
    "sg:tags":[
        "leasing"
    ],
    "wof:name":"Cozza Associates NA Inc",
    "wof:placetype":"venue"
},
  "geometry": {"coordinates":[-73.371323,40.685059],"type":"Point"}
}