{
  "type": "Feature",
  "properties": {
    "iso:country":"US",
    "sg:address":"10 Lucille Ln",
    "sg:city":"Commack",
    "sg:classifiers":[
        {
            "category":"Wholesale",
            "subcategory":"Machinery & Supplies",
            "type":"Manufacturing & Wholesale Goods"
        },
        {
            "category":"Manufacturing",
            "subcategory":"Tools & Machinery",
            "type":"Manufacturing & Wholesale Goods"
        }
    ],
    "sg:phone":"+1 631 462 5356",
    "sg:postcode":"11725",
    "sg:province":"NY",
    "sg:tags":[
        "plastic",
        "equipment",
        "industrial",
        "general",
        "mfg"
    ],
    "wof:name":"Davis-Standard Corporation",
    "wof:placetype":"venue"
},
  "geometry": {"coordinates":[-73.299623,40.834597],"type":"Point"}
}