{
  "type": "Feature",
  "properties": {
    "iso:country":"US",
    "sg:address":"55 Brook Ave",
    "sg:city":"Deer Park",
    "sg:classifiers":[
        {
            "category":"Building & Trades",
            "subcategory":"Construction",
            "type":"Services"
        }
    ],
    "sg:phone":"+1 631 254 6142",
    "sg:postcode":"11729",
    "sg:province":"NY",
    "sg:tags":[
        "maker",
        "cabinet"
    ],
    "wof:name":"Above All Cabinetry Inc",
    "wof:placetype":"venue"
},
  "geometry": {"coordinates":[-73.308598,40.743707],"type":"Point"}
}