{
  "type": "Feature",
  "properties": {
    "iso:country":"US",
    "sg:address":"1445 E Delavan Ave",
    "sg:city":"Buffalo",
    "sg:classifiers":[
        {
            "category":"Deli",
            "type":"Food & Drink"
        },
        {
            "category":"Food & Beverages",
            "subcategory":"Bakery",
            "type":"Retail Goods"
        }
    ],
    "sg:phone":"+1 716 896 9967",
    "sg:postcode":"14215",
    "sg:province":"NY",
    "sg:tags":[
        "sandwich"
    ],
    "wof:name":"King & Quots Deli",
    "wof:placetype":"venue"
},
  "geometry": {"coordinates":[-78.803358,42.922612],"type":"Point"}
}