{
  "type": "Feature",
  "properties": {
    "iso:country":"US",
    "sg:address":"280 Indian Lake Rd",
    "sg:city":"Millerton",
    "sg:classifiers":[
        {
            "category":"Building & Trades",
            "subcategory":"Construction",
            "type":"Services"
        }
    ],
    "sg:phone":"+1 518 789 0432",
    "sg:postcode":"12546",
    "sg:province":"NY",
    "sg:tags":[
        "house",
        "improvement",
        "home"
    ],
    "wof:name":"T C Home Improvements",
    "wof:placetype":"venue"
},
  "geometry": {"coordinates":[-73.508644,41.920045],"type":"Point"}
}