{
  "type": "Feature",
  "properties": {
    "addr:full":"302 Michigan Ave Schenectady NY 12303",
    "addr:housenumber":"302",
    "addr:postcode":"12303",
    "addr:street":"Michigan Ave",
    "iso:country":"US",
    "sg:address":"302 Michigan Ave",
    "sg:city":"Schenectady",
    "sg:classifiers":[
        {
            "category":"Real Estate",
            "subcategory":"Real Estate Operator",
            "type":"Services"
        }
    ],
    "sg:phone":"+1 518 377 5229",
    "sg:postcode":"12303",
    "sg:province":"NY",
    "sg:tags":[
        "building",
        "nonresidential"
    ],
    "wof:name":"Casa Mia Restaurant Inc",
    "wof:placetype":"venue"
},
  "geometry": {"coordinates":[-73.93294,42.796314],"type":"Point"}
}