{
  "type": "Feature",
  "properties": {
    "addr:full":"433 Kings Hwy Brooklyn NY 11223",
    "addr:housenumber":"433",
    "addr:postcode":"11223",
    "addr:street":"Kings Hwy",
    "iso:country":"US",
    "sg:address":"433 Kings Hwy",
    "sg:city":"Brooklyn",
    "sg:classifiers":[
        {
            "category":"Wholesale",
            "subcategory":"Machinery & Supplies",
            "type":"Manufacturing & Wholesale Goods"
        }
    ],
    "sg:phone":"+1 718 837 0709",
    "sg:postcode":"11223",
    "sg:province":"NY",
    "sg:tags":[
        "baker"
    ],
    "wof:name":"Venezia Bakery",
    "wof:placetype":"venue"
},
  "geometry": {"coordinates":[-73.97319400000001,40.604298],"type":"Point"}
}