{
  "type": "Feature",
  "properties": {
    "iso:country":"US",
    "sg:address":"82 S Franklin St",
    "sg:city":"Nyack",
    "sg:classifiers":[
        {
            "category":"Shopping",
            "subcategory":"Used Merchandise",
            "type":"Retail Goods"
        }
    ],
    "sg:phone":"+1 845 358 4240",
    "sg:postcode":"10960",
    "sg:province":"NY",
    "sg:tags":[
        "antique"
    ],
    "wof:name":"Christophers Antiques Wrhse",
    "wof:placetype":"venue"
},
  "geometry": {"coordinates":[-73.92201,41.0887],"type":"Point"}
}