{
  "type": "Feature",
  "properties": {
    "iso:country":"US",
    "sg:address":"255 Pulaski Rd",
    "sg:city":"East Northport",
    "sg:classifiers":[
        {
            "category":"Retail",
            "subcategory":"Auto Repair",
            "type":"Services"
        }
    ],
    "sg:phone":"+1 631 757 5660",
    "sg:postcode":"11731",
    "sg:province":"NY",
    "sg:tags":[
        "repairing",
        "automobile"
    ],
    "wof:name":"Dano Automotive Inc",
    "wof:placetype":"venue"
},
  "geometry": {"coordinates":[-73.32726599999999,40.876548],"type":"Point"}
}