{
  "type": "Feature",
  "properties": {
    "iso:country":"US",
    "sg:address":"111 Porter Ave",
    "sg:city":"Buffalo",
    "sg:classifiers":[
        {
            "category":"Building & Trades",
            "subcategory":"Construction",
            "type":"Services"
        }
    ],
    "sg:phone":"+1 716 885 2470",
    "sg:postcode":"14201",
    "sg:province":"NY",
    "sg:tags":[
        "concrete",
        "contractor"
    ],
    "wof:name":"Destro & Bro Concrete Co Inc",
    "wof:placetype":"venue"
},
  "geometry": {"coordinates":[-78.89664399999999,42.89904],"type":"Point"}
}