{
  "type": "Feature",
  "properties": {
    "iso:country":"US",
    "sg:address":"523 Sweet Home Rd",
    "sg:city":"Buffalo",
    "sg:classifiers":[
        {
            "category":"Building & Trades",
            "subcategory":"Landscaping Services",
            "type":"Services"
        }
    ],
    "sg:phone":"+1 716 834 2285",
    "sg:postcode":"14226",
    "sg:province":"NY",
    "sg:tags":[
        "landscape",
        "contractor"
    ],
    "wof:name":"Cappello's Landscaping",
    "wof:placetype":"venue"
},
  "geometry": {"coordinates":[-78.807872,42.979118],"type":"Point"}
}