{
  "type": "Feature",
  "properties": {
    "iso:country":"US",
    "sg:address":"2969 Bailey Ave",
    "sg:city":"Buffalo",
    "sg:classifiers":[
        {
            "category":"Government",
            "subcategory":"Office",
            "type":"Public Place"
        }
    ],
    "sg:phone":"+1 716 834 3837",
    "sg:postcode":"14215",
    "sg:province":"NY",
    "sg:tags":[
        "administrative",
        "program",
        "health"
    ],
    "wof:name":"Break The Circle Of Stigma",
    "wof:placetype":"venue"
},
  "geometry": {"coordinates":[-78.81357,42.935322],"type":"Point"}
}