{
  "type": "Feature",
  "properties": {
    "addr:full":"65 Acorn Ave Scotchtown NY 10941",
    "addr:housenumber":"65",
    "addr:postcode":"10941",
    "addr:street":"Acorn Ave",
    "iso:country":"US",
    "sg:address":"65 Acorn Ave",
    "sg:city":"Scotchtown",
    "sg:classifiers":[
        {
            "category":"Professional",
            "type":"Services"
        }
    ],
    "sg:phone":"+1 845 692 3511",
    "sg:postcode":"10941",
    "sg:province":"NY",
    "sg:tags":[
        "establishment"
    ],
    "wof:name":"Gem Community Management",
    "wof:placetype":"venue"
},
  "geometry": {"coordinates":[-74.366293,41.470197],"type":"Point"}
}