{
  "type": "Feature",
  "properties": {
    "iso:country":"US",
    "sg:address":"8338 Woodhaven Boulevard",
    "sg:city":"Glendale",
    "sg:classifiers":[
        {
            "category":"Restaurant",
            "type":"Food & Drink"
        }
    ],
    "sg:phone":"+1 718 847 0800",
    "sg:postcode":"11385",
    "sg:province":"NY",
    "wof:name":"Bollywood Lounge",
    "wof:placetype":"venue"
},
  "geometry": {"coordinates":[-73.855525,40.702367],"type":"Point"}
}