{
  "type": "Feature",
  "properties": {
    "addr:full":"4258 Albany St Albany NY 12205",
    "addr:housenumber":"4258",
    "addr:postcode":"12205",
    "addr:street":"Albany St",
    "iso:country":"US",
    "sg:address":"4258 Albany St",
    "sg:city":"Albany",
    "sg:classifiers":[
        {
            "category":"Manufacturing",
            "subcategory":"Chemicals & Compounds",
            "type":"Manufacturing & Wholesale Goods"
        }
    ],
    "sg:phone":"+1 518 869 2454",
    "sg:postcode":"12205",
    "sg:province":"NY",
    "sg:tags":[
        "adhesive",
        "glue"
    ],
    "sg:website":"www.adktapes.com",
    "wof:name":"Adirondack Specialty Adhesives",
    "wof:placetype":"venue"
},
  "geometry": {"coordinates":[-73.864604,42.734968],"type":"Point"}
}