{
  "type": "Feature",
  "properties": {
    "addr:full":"16 Gilmore Ave Cambridge NY 12816",
    "addr:housenumber":"16",
    "addr:postcode":"12816",
    "addr:street":"Gilmore Ave",
    "iso:country":"US",
    "sg:address":"16 Gilmore Ave",
    "sg:city":"Cambridge",
    "sg:classifiers":[
        {
            "category":"Professional",
            "subcategory":"Art Services",
            "type":"Services"
        }
    ],
    "sg:phone":"+1 518 677 0248",
    "sg:postcode":"12816",
    "sg:province":"NY",
    "sg:tags":[
        "calligrapher"
    ],
    "wof:name":"Calligraphy By Anna",
    "wof:placetype":"venue"
},
  "geometry": {"coordinates":[-73.388846,43.02758],"type":"Point"}
}