{
  "type": "Feature",
  "properties": {
    "addr:full":"909 Landing Rd N Rochester NY 14625",
    "addr:housenumber":"909",
    "addr:postcode":"14625",
    "addr:street":"Landing Rd N",
    "iso:country":"US",
    "sg:address":"909 Landing Rd N",
    "sg:city":"Rochester",
    "sg:classifiers":[
        {
            "category":"Organizations",
            "subcategory":"Religious Organization",
            "type":"Services"
        }
    ],
    "sg:phone":"+1 585 381 5330",
    "sg:postcode":"14625",
    "sg:province":"NY",
    "wof:name":"Trinity Reformed Church",
    "wof:placetype":"venue"
},
  "geometry": {"coordinates":[-77.530129,43.138974],"type":"Point"}
}