{
  "type": "Feature",
  "properties": {
    "addr:full":"200 60th St Brooklyn NY 11220",
    "addr:housenumber":"200",
    "addr:postcode":"11220",
    "addr:street":"60Th St",
    "iso:country":"US",
    "sg:address":"200 60th St",
    "sg:city":"Brooklyn",
    "sg:classifiers":[
        {
            "category":"Manufacturing",
            "subcategory":"Textiles",
            "type":"Manufacturing & Wholesale Goods"
        }
    ],
    "sg:phone":"+1 718 972 0669",
    "sg:postcode":"11220",
    "sg:province":"NY",
    "sg:tags":[
        "linen"
    ],
    "wof:name":"Elegant Linen",
    "wof:placetype":"venue"
},
  "geometry": {"coordinates":[-74.020803,40.642317],"type":"Point"}
}