{
  "type": "Feature",
  "properties": {
    "iso:country":"US",
    "sg:address":"596 Pawling Ave",
    "sg:city":"Troy",
    "sg:classifiers":[
        {
            "category":"Social Services",
            "subcategory":"Child Care",
            "type":"Services"
        },
        {
            "category":"Recreation",
            "type":"Entertainment"
        }
    ],
    "sg:phone":"+1 518 272 8029",
    "sg:postcode":"12180",
    "sg:province":"NY",
    "wof:name":"Hope No 7 Community Ctr Inc",
    "wof:placetype":"venue"
},
  "geometry": {"coordinates":[-73.65967999999999,42.704922],"type":"Point"}
}