{
  "type": "Feature",
  "properties": {
    "iso:country":"US",
    "sg:address":"43 Herkomer St",
    "sg:city":"New Hyde Park",
    "sg:classifiers":[
        {
            "category":"Building & Trades",
            "subcategory":"Construction",
            "type":"Services"
        }
    ],
    "sg:phone":"+1 516 488 1763",
    "sg:postcode":"11040",
    "sg:province":"NY",
    "sg:tags":[
        "contractor"
    ],
    "wof:name":"Enrico & Sons Contrctng Inc",
    "wof:placetype":"venue"
},
  "geometry": {"coordinates":[-73.68090100000001,40.732399],"type":"Point"}
}