{
  "type": "Feature",
  "properties": {
    "addr:full":"1208 Fairport Rd Fairport NY 14450",
    "addr:housenumber":"1208",
    "addr:postcode":"14450",
    "addr:street":"Fairport Rd",
    "iso:country":"US",
    "sg:address":"1208 Fairport Rd",
    "sg:city":"Fairport",
    "sg:classifiers":[
        {
            "category":"Sports & Exercise",
            "subcategory":"Golf",
            "type":"Entertainment"
        }
    ],
    "sg:phone":"+1 585 586 1300",
    "sg:postcode":"14450",
    "sg:province":"NY",
    "sg:tags":[
        "club",
        "course",
        "membership",
        "public"
    ],
    "wof:name":"Island Valley Golf Crse Pro Sp",
    "wof:placetype":"venue"
},
  "geometry": {"coordinates":[-77.465425,43.102306],"type":"Point"}
}