{
  "type": "Feature",
  "properties": {
    "addr:full":"595 Broad Hollow Rd Farmingdale NY 11735",
    "addr:housenumber":"595",
    "addr:postcode":"11735",
    "addr:street":"Broad Hollow Rd",
    "iso:country":"US",
    "sg:address":"595 Broad Hollow Rd",
    "sg:city":"Farmingdale",
    "sg:classifiers":[
        {
            "category":"Manufacturing",
            "subcategory":"Chemicals & Compounds",
            "type":"Manufacturing & Wholesale Goods"
        }
    ],
    "sg:phone":"+1   ",
    "sg:postcode":"11735",
    "sg:province":"NY",
    "sg:tags":[
        "manufacture",
        "color",
        "material",
        "plastic",
        "raw",
        "concentrate"
    ],
    "wof:name":"Amco Plastic Materials Inc",
    "wof:placetype":"venue"
},
  "geometry": {"coordinates":[-73.42610999999999,40.718635],"type":"Point"}
}