{
  "type": "Feature",
  "properties": {
    "addr:full":"335 8 Ave New York NY 10001",
    "addr:housenumber":"335",
    "addr:postcode":"10001",
    "addr:street":"8 Ave",
    "iso:country":"US",
    "sg:address":"335 8 Ave",
    "sg:city":"New York",
    "sg:classifiers":[
        {
            "category":"Retail",
            "subcategory":"Repair Shop",
            "type":"Services"
        }
    ],
    "sg:phone":"+1 917 463 2886",
    "sg:postcode":"10001",
    "sg:province":"NY",
    "sg:tags":[
        "lock",
        "locksmith"
    ],
    "wof:name":"Emergency Locksmith",
    "wof:placetype":"venue"
},
  "geometry": {"coordinates":[-73.997552,40.746581],"type":"Point"}
}