{
  "type": "Feature",
  "properties": {
    "iso:country":"US",
    "sg:address":"125 S Union St",
    "sg:city":"Olean",
    "sg:classifiers":[
        {
            "category":"Professional",
            "subcategory":"Accounting & Tax Preparation",
            "type":"Services"
        }
    ],
    "sg:phone":"+1 716 372 1620",
    "sg:postcode":"14760",
    "sg:province":"NY",
    "sg:tags":[
        "firm",
        "accountant"
    ],
    "wof:name":"Buffamnte Whipple Buttafaro PC",
    "wof:placetype":"venue"
},
  "geometry": {"coordinates":[-78.42992,42.077127],"type":"Point"}
}