{
  "type": "Feature",
  "properties": {
    "addr:full":"93 W Main St Friendship NY 14739",
    "addr:housenumber":"93",
    "addr:postcode":"14739",
    "addr:street":"W Main St",
    "iso:country":"US",
    "sg:address":"93 W Main St",
    "sg:city":"Friendship",
    "sg:classifiers":[
        {
            "category":"Real Estate",
            "subcategory":"Real Estate Agent",
            "type":"Services"
        }
    ],
    "sg:phone":"+1 585 973 7718",
    "sg:postcode":"14739",
    "sg:province":"NY",
    "wof:name":"Scott Realty",
    "wof:placetype":"venue"
},
  "geometry": {"coordinates":[-78.141542,42.204687],"type":"Point"}
}