{
  "type": "Feature",
  "properties": {
    "addr:full":"291 Broadway Brooklyn NY 11211",
    "addr:housenumber":"291",
    "addr:postcode":"11211",
    "addr:street":"Broadway",
    "iso:country":"US",
    "sg:address":"291 Broadway",
    "sg:city":"Brooklyn",
    "sg:classifiers":[
        {
            "category":"Restaurant",
            "type":"Food & Drink"
        }
    ],
    "sg:phone":"+1 718 782 7858",
    "sg:postcode":"11211",
    "sg:province":"NY",
    "wof:name":"Terry's Coffee Shop",
    "wof:placetype":"venue"
},
  "geometry": {"coordinates":[-73.958011,40.708579],"type":"Point"}
}