{
  "type": "Feature",
  "properties": {
    "iso:country":"US",
    "sg:address":"104 Duffy St",
    "sg:city":"Watertown",
    "sg:classifiers":[
        {
            "category":"Utilities",
            "subcategory":"Mobile Phone",
            "type":"Services"
        }
    ],
    "sg:phone":"+1 315 782 0501",
    "sg:postcode":"13601",
    "sg:province":"NY",
    "sg:tags":[
        "telephone",
        "cellular"
    ],
    "wof:name":"Hometown Wireless LLC",
    "wof:placetype":"venue"
},
  "geometry": {"coordinates":[-75.935644,43.975795],"type":"Point"}
}