{
  "type": "Feature",
  "properties": {
    "addr:full":"2228 Toll Rd Phelps NY 14532",
    "addr:housenumber":"2228",
    "addr:postcode":"14532",
    "addr:street":"Toll Rd",
    "iso:country":"US",
    "sg:address":"2228 Toll Rd",
    "sg:city":"Phelps",
    "sg:classifiers":[
        {
            "category":"Social Services",
            "type":"Services"
        }
    ],
    "sg:phone":"+1 315 548 3474",
    "sg:postcode":"14532",
    "sg:province":"NY",
    "sg:tags":[
        "youth",
        "organization",
        "center"
    ],
    "wof:name":"Camp Dittmer",
    "wof:placetype":"venue"
},
  "geometry": {"coordinates":[-77.08638000000001,42.924765],"type":"Point"}
}