{
  "type": "Feature",
  "properties": {
    "addr:full":"55 Allen Blvd Farmingdale NY 11735",
    "addr:housenumber":"55",
    "addr:postcode":"11735",
    "addr:street":"Allen Blvd",
    "iso:country":"US",
    "sg:address":"55 Allen Blvd",
    "sg:city":"Farmingdale",
    "sg:classifiers":[
        {
            "category":"Deli",
            "type":"Food & Drink"
        }
    ],
    "sg:phone":"+1 631 293 3437",
    "sg:postcode":"11735",
    "sg:province":"NY",
    "sg:tags":[
        "delicatessen"
    ],
    "wof:name":"John S Market Corp.",
    "wof:placetype":"venue"
},
  "geometry": {"coordinates":[-73.422691,40.715599],"type":"Point"}
}