{
  "type": "Feature",
  "properties": {
    "iso:country":"US",
    "sg:address":"8 W Main St",
    "sg:city":"Waterloo",
    "sg:classifiers":[
        {
            "category":"Shopping",
            "subcategory":"Clothing, Apparel, & Fashions",
            "type":"Retail Goods"
        }
    ],
    "sg:phone":"+1   ",
    "sg:postcode":"13165",
    "sg:province":"NY",
    "wof:name":"Tally-Ho Trading Post",
    "wof:placetype":"venue"
},
  "geometry": {"coordinates":[-76.863045,42.904724],"type":"Point"}
}