{
  "type": "Feature",
  "properties": {
    "addr:full":"350 Beebe Rd Mineola NY 11501",
    "addr:housenumber":"350",
    "addr:postcode":"11501",
    "addr:street":"Beebe Rd",
    "iso:country":"US",
    "sg:address":"350 Beebe Rd",
    "sg:city":"Mineola",
    "sg:classifiers":[
        {
            "category":"Shopping",
            "subcategory":"Computers & Home Electronics",
            "type":"Retail Goods"
        }
    ],
    "sg:phone":"+1   ",
    "sg:postcode":"11501",
    "sg:province":"NY",
    "wof:name":"Villani Computer Co",
    "wof:placetype":"venue"
},
  "geometry": {"coordinates":[-73.656144,40.746768],"type":"Point"}
}