{
  "type": "Feature",
  "properties": {
    "iso:country":"US",
    "sg:address":"860 Co Rd 1",
    "sg:city":"Pine Island",
    "sg:classifiers":[
        {
            "category":"Retail",
            "subcategory":"Auto Repair",
            "type":"Services"
        }
    ],
    "sg:phone":"+1 845 258 3030",
    "sg:postcode":"10969",
    "sg:province":"NY",
    "sg:tags":[
        "product",
        "dairy",
        "general"
    ],
    "wof:name":"Slesinskis Farm Repair",
    "wof:placetype":"venue"
},
  "geometry": {"coordinates":[-74.47898600000001,41.300663],"type":"Point"}
}