{
  "type": "Feature",
  "properties": {
    "addr:full":"2300 Nesconset Hwy Stony Brook NY 11790",
    "addr:postcode":"2300;11790",
    "addr:street":"Nesconset Hwy",
    "iso:country":"US",
    "sg:address":"2300 Nesconset Hwy",
    "sg:city":"Stony Brook",
    "sg:classifiers":[
        {
            "category":"Food & Beverages",
            "subcategory":"Bakery",
            "type":"Retail Goods"
        }
    ],
    "sg:phone":"+1   ",
    "sg:postcode":"11790",
    "sg:province":"NY",
    "wof:name":"Bagels & A Hole Lot More",
    "wof:placetype":"venue"
},
  "geometry": {"coordinates":[-73.113162,40.879273],"type":"Point"}
}