{
  "type": "Feature",
  "properties": {
    "iso:country":"US",
    "sg:address":"136 Prince St",
    "sg:city":"New York",
    "sg:classifiers":[
        {
            "category":"Shopping",
            "subcategory":"Clothing, Apparel, & Fashions",
            "type":"Retail Goods"
        },
        {
            "category":"Shopping",
            "subcategory":"Luggage & Leather Goods",
            "type":"Retail Goods"
        }
    ],
    "sg:phone":"+1 212 965 5714",
    "sg:postcode":"10012",
    "sg:province":"NY",
    "sg:tags":[
        "men's",
        "clothing",
        "women's"
    ],
    "wof:name":"Victorinox / Swiss Army",
    "wof:placetype":"venue"
},
  "geometry": {"coordinates":[-74.000603,40.7258],"type":"Point"}
}