{
  "type": "Feature",
  "properties": {
    "addr:full":"5918 Glenwood Rd Brooklyn NY 11234",
    "addr:housenumber":"5918",
    "addr:postcode":"11234",
    "addr:street":"Glenwood Rd",
    "iso:country":"US",
    "sg:address":"5918 Glenwood Rd",
    "sg:city":"Brooklyn",
    "sg:classifiers":[
        {
            "category":"Shopping",
            "type":"Retail Goods"
        }
    ],
    "sg:phone":"+1 718 444 8906",
    "sg:postcode":"11234",
    "sg:province":"NY",
    "sg:tags":[
        "picture",
        "frame"
    ],
    "wof:name":"Interventional Art Intl Inc",
    "wof:placetype":"venue"
},
  "geometry": {"coordinates":[-73.918937,40.634312],"type":"Point"}
}