{
  "type": "Feature",
  "properties": {
    "addr:full":"124 East 40th Street Suite 803 New York NY 10016",
    "addr:housenumber":"124;803",
    "addr:postcode":"10016",
    "addr:street":"East 40Th Street Suite",
    "iso:country":"US",
    "sg:address":"124 East 40th Street Suite 803",
    "sg:city":"New York",
    "sg:classifiers":[
        {
            "category":"Health Services",
            "subcategory":"Health Practitioner",
            "type":"Services"
        }
    ],
    "sg:phone":"+1 212 490 2477",
    "sg:postcode":"10016",
    "sg:province":"NY",
    "sg:tags":[
        "acupuncture",
        "nutritionist"
    ],
    "sg:website":"www.innerfirehealth.com",
    "wof:name":"Inner Fire Integrative Health Services",
    "wof:placetype":"venue"
},
  "geometry": {"coordinates":[-73.977317,40.750139],"type":"Point"}
}