{
  "type": "Feature",
  "properties": {
    "iso:country":"US",
    "sg:address":"1116 Altamont Ave",
    "sg:city":"Schenectady",
    "sg:classifiers":[
        {
            "category":"Sports & Exercise",
            "subcategory":"Gym",
            "type":"Entertainment"
        }
    ],
    "sg:phone":"+1 518 355 0023",
    "sg:postcode":"12303",
    "sg:province":"NY",
    "sg:tags":[
        "club",
        "health",
        "facility"
    ],
    "wof:name":"Powerhouse Gym Aerobic Fcilty",
    "wof:placetype":"venue"
},
  "geometry": {"coordinates":[-73.93888699999999,42.788965],"type":"Point"}
}