{
  "type": "Feature",
  "properties": {
    "addr:full":"26 Court St Ste 2810 Suite 1800 Brooklyn NY 11242",
    "addr:housenumber":"26;2810 suite 1800",
    "addr:postcode":"11242",
    "addr:street":"Court St Ste",
    "iso:country":"US",
    "sg:address":"26 Court St Ste 2810 Suite 1800",
    "sg:city":"Brooklyn",
    "sg:classifiers":[
        {
            "category":"Professional",
            "subcategory":"Lawyer & Legal Services",
            "type":"Services"
        }
    ],
    "sg:phone":"+1 718 852 9100",
    "sg:postcode":"11242",
    "sg:province":"NY",
    "wof:name":"Mure Joseph",
    "wof:placetype":"venue"
},
  "geometry": {"coordinates":[-73.99073199999999,40.693335],"type":"Point"}
}