{
  "type": "Feature",
  "properties": {
    "iso:country":"US",
    "sg:address":"61 West St",
    "sg:city":"Harrison",
    "sg:classifiers":[
        {
            "category":"Building & Trades",
            "subcategory":"Electrical",
            "type":"Services"
        }
    ],
    "sg:phone":"+1 914 381 4375",
    "sg:postcode":"10528",
    "sg:province":"NY",
    "sg:tags":[
        "electrician",
        "contractor"
    ],
    "wof:name":"Miele Electric",
    "wof:placetype":"venue"
},
  "geometry": {"coordinates":[-73.723046,40.96356],"type":"Point"}
}