{
  "type": "Feature",
  "properties": {
    "iso:country":"US",
    "sg:address":"105 Calvert St",
    "sg:city":"Harrison",
    "sg:classifiers":[
        {
            "category":"Manufacturing",
            "subcategory":"Aerospace",
            "type":"Manufacturing & Wholesale Goods"
        }
    ],
    "sg:phone":"+1 203 595 9797",
    "sg:postcode":"10528",
    "sg:province":"NY",
    "sg:tags":[
        "equipment",
        "industry",
        "part",
        "aircraft",
        "supply"
    ],
    "wof:name":"Messner-Hirth Export Corp.",
    "wof:placetype":"venue"
},
  "geometry": {"coordinates":[-73.71867899999999,40.968992],"type":"Point"}
}