{
  "type": "Feature",
  "properties": {
    "addr:full":"1254 Bay Street Staten Island NY 10305",
    "addr:housenumber":"1254",
    "addr:postcode":"10305",
    "addr:street":"Bay Street",
    "iso:country":"US",
    "sg:address":"1254 Bay Street",
    "sg:city":"Staten Island",
    "sg:classifiers":[
        {
            "category":"Airline",
            "type":"Transportation"
        }
    ],
    "sg:phone":"+1 718 442 4242",
    "sg:postcode":"10305",
    "sg:province":"NY",
    "sg:tags":[
        "shuttle",
        "airport"
    ],
    "wof:name":"Staten Island Management",
    "wof:placetype":"venue"
},
  "geometry": {"coordinates":[-74.065355,40.612816],"type":"Point"}
}