{
  "type": "Feature",
  "properties": {
    "addr:full":"712 Jericho Tpke Huntington Sta NY 11746",
    "addr:housenumber":"712",
    "addr:postcode":"11746",
    "addr:street":"Jericho Tpke",
    "iso:country":"US",
    "sg:address":"712 Jericho Tpke",
    "sg:city":"Huntington Sta",
    "sg:classifiers":[
        {
            "category":"Shopping",
            "type":"Retail Goods"
        }
    ],
    "sg:phone":"+1 631 427 3963",
    "sg:postcode":"11746",
    "sg:province":"NY",
    "sg:tags":[
        "art",
        "gallery",
        "dealer"
    ],
    "wof:name":"Soho Art",
    "wof:placetype":"venue"
},
  "geometry": {"coordinates":[-73.382149,40.834439],"type":"Point"}
}