{
  "type": "Feature",
  "properties": {
    "iso:country":"US",
    "sg:address":"5225 Nesconset Hwy Ste 43",
    "sg:city":"Port Jefferson Station",
    "sg:classifiers":[
        {
            "category":"Banks & Credit Unions",
            "subcategory":"Investment Brokerage",
            "type":"Services"
        }
    ],
    "sg:phone":"+1 631 473 7600",
    "sg:postcode":"11776",
    "sg:province":"NY",
    "sg:tags":[
        "investing"
    ],
    "sg:website":"www.barnesandsherry.com",
    "wof:name":"Barnes & Sherry",
    "wof:placetype":"venue"
},
  "geometry": {"coordinates":[-73.29741799999999,40.927293],"type":"Point"}
}