{
  "type": "Feature",
  "properties": {
    "addr:full":"2465 Haring St Brooklyn NY 11235",
    "addr:housenumber":"2465",
    "addr:postcode":"11235",
    "addr:street":"Haring St",
    "iso:country":"US",
    "sg:address":"2465 Haring St",
    "sg:city":"Brooklyn",
    "sg:classifiers":[
        {
            "category":"Real Estate",
            "subcategory":"Real Estate Services",
            "type":"Services"
        }
    ],
    "sg:phone":"+1 718 743 9840",
    "sg:postcode":"11235",
    "sg:province":"NY",
    "sg:tags":[
        "management",
        "property"
    ],
    "wof:name":"Nostrand Gardens Co-Operative Inc",
    "wof:placetype":"venue"
},
  "geometry": {"coordinates":[-73.93940000000001,40.592602],"type":"Point"}
}