{
  "type": "Feature",
  "properties": {
    "addr:full":"2022 Webster Avenue Bronx NY 10457",
    "addr:housenumber":"2022",
    "addr:postcode":"10457",
    "addr:street":"Webster Avenue",
    "iso:country":"US",
    "sg:address":"2022 Webster Avenue",
    "sg:city":"Bronx",
    "sg:classifiers":[
        {
            "category":"Professional",
            "subcategory":"Computer Services",
            "type":"Services"
        }
    ],
    "sg:phone":"+1 646 401 5997",
    "sg:postcode":"10457",
    "sg:province":"NY",
    "sg:tags":[
        "repair"
    ],
    "wof:name":"Computer Solutions",
    "wof:placetype":"venue"
},
  "geometry": {"coordinates":[-73.89904799999999,40.850607],"type":"Point"}
}