{
  "type": "Feature",
  "properties": {
    "addr:full":"245 5th Ave Rm 1902 New York NY 10016",
    "addr:housenumber":"245;1902",
    "addr:postcode":"10016",
    "addr:street":"5Th Ave Rm",
    "iso:country":"US",
    "sg:address":"245 5th Ave Rm 1902",
    "sg:city":"New York",
    "sg:classifiers":[
        {
            "category":"Professional",
            "subcategory":"Lawyer & Legal Services",
            "type":"Services"
        }
    ],
    "sg:phone":"+1 212 569 7853",
    "sg:postcode":"10016",
    "sg:province":"NY",
    "wof:name":"Law Office Of Daniel A Singer",
    "wof:placetype":"venue"
},
  "geometry": {"coordinates":[-73.98724300000001,40.744461],"type":"Point"}
}