{
  "type": "Feature",
  "properties": {
    "iso:country":"US",
    "sg:address":"2735 Doelner Cir",
    "sg:city":"Castletn On Hdsn",
    "sg:classifiers":[
        {
            "category":"Professional",
            "subcategory":"Computer Services",
            "type":"Services"
        }
    ],
    "sg:phone":"+1 518 479 2009",
    "sg:postcode":"12033",
    "sg:province":"NY",
    "sg:tags":[
        "processing",
        "datum"
    ],
    "wof:name":"Conbro Information Systems",
    "wof:placetype":"venue"
},
  "geometry": {"coordinates":[-73.700564,42.576508],"type":"Point"}
}