{
  "type": "Feature",
  "properties": {
    "addr:full":"55 Beekman St Saratoga Springs NY 12866",
    "addr:housenumber":"55",
    "addr:postcode":"12866",
    "addr:street":"Beekman St",
    "iso:country":"US",
    "sg:address":"55 Beekman St",
    "sg:city":"Saratoga Springs",
    "sg:classifiers":[
        {
            "category":"Shopping",
            "subcategory":"Shoes",
            "type":"Retail Goods"
        }
    ],
    "sg:phone":"+1 518 584 1713",
    "sg:postcode":"12866",
    "sg:province":"NY",
    "sg:tags":[
        "parlor",
        "footwear",
        "shoe"
    ],
    "wof:name":"Barts Shoe Hospital",
    "wof:placetype":"venue"
},
  "geometry": {"coordinates":[-73.792877,43.078554],"type":"Point"}
}