{
  "type": "Feature",
  "properties": {
    "iso:country":"US",
    "sg:address":"351 Myrtle Ave",
    "sg:city":"Brooklyn",
    "sg:classifiers":[
        {
            "category":"Personal",
            "subcategory":"Beauty Salon",
            "type":"Services"
        }
    ],
    "sg:phone":"+1 718 222 1222",
    "sg:postcode":"11205",
    "sg:province":"NY",
    "sg:tags":[
        "shop"
    ],
    "wof:name":"Precious Unisex",
    "wof:placetype":"venue"
},
  "geometry": {"coordinates":[-73.972459,40.693316],"type":"Point"}
}