{
  "type": "Feature",
  "properties": {
    "iso:country":"US",
    "sg:address":"1244 Montauk Hwy",
    "sg:city":"Oakdale",
    "sg:classifiers":[
        {
            "category":"Building & Trades",
            "subcategory":"Construction",
            "type":"Services"
        }
    ],
    "sg:phone":"+1 631 277 1471",
    "sg:postcode":"11769",
    "sg:province":"NY",
    "sg:tags":[
        "home",
        "builder"
    ],
    "wof:name":"Bianculli Custom Homes",
    "wof:placetype":"venue"
},
  "geometry": {"coordinates":[-73.13078899999999,40.741895],"type":"Point"}
}