{
  "type": "Feature",
  "properties": {
    "addr:full":"630 Arthur Kill Rd Staten Island NY 10308",
    "addr:housenumber":"630",
    "addr:postcode":"10308",
    "addr:street":"Arthur Kill Rd",
    "iso:country":"US",
    "sg:address":"630 Arthur Kill Rd",
    "sg:city":"Staten Island",
    "sg:classifiers":[
        {
            "category":"Retail",
            "subcategory":"Auto Repair",
            "type":"Services"
        }
    ],
    "sg:phone":"+1 718 605 6590",
    "sg:postcode":"10308",
    "sg:province":"NY",
    "wof:name":"Armstrong Auto Center Inc",
    "wof:placetype":"venue"
},
  "geometry": {"coordinates":[-74.162629,40.560643],"type":"Point"}
}