{
  "type": "Feature",
  "properties": {
    "addr:full":"106 W 80 St New York NY 10024",
    "addr:housenumber":"106",
    "addr:postcode":"10024",
    "addr:street":"W 80 St",
    "iso:country":"US",
    "sg:address":"106 W 80 St",
    "sg:city":"New York",
    "sg:classifiers":[
        {
            "category":"Professional",
            "subcategory":"Computer Services",
            "type":"Services"
        }
    ],
    "sg:phone":"+1 212 874 6265",
    "sg:postcode":"10024",
    "sg:province":"NY",
    "sg:tags":[
        "related"
    ],
    "wof:name":"Search Net Corporation",
    "wof:placetype":"venue"
},
  "geometry": {"coordinates":[-73.97773100000001,40.783692],"type":"Point"}
}