{
  "type": "Feature",
  "properties": {
    "addr:full":"4043 Libra Ln Ste 4 Liverpool NY 13090",
    "addr:housenumber":"4043",
    "addr:postcode":"13090",
    "addr:street":"Libra Ln Ste 4",
    "iso:country":"US",
    "sg:address":"4043 Libra Ln Ste 4",
    "sg:city":"Liverpool",
    "sg:classifiers":[
        {
            "category":"Autos & Motor Vehicles",
            "subcategory":"Auto Supplies",
            "type":"Retail Goods"
        }
    ],
    "sg:phone":"+1 315 622 5615",
    "sg:postcode":"13090",
    "sg:province":"NY",
    "sg:tags":[
        "polishing",
        "car",
        "washing",
        "equipment"
    ],
    "wof:name":"Squirt N Dirt Enterprises",
    "wof:placetype":"venue"
},
  "geometry": {"coordinates":[-76.23358899999999,43.167254],"type":"Point"}
}