{
  "type": "Feature",
  "properties": {
    "addr:full":"68 Nancy St West Babylon NY 11704",
    "addr:housenumber":"68",
    "addr:postcode":"11704",
    "addr:street":"Nancy St",
    "iso:country":"US",
    "sg:address":"68 Nancy St",
    "sg:city":"West Babylon",
    "sg:classifiers":[
        {
            "category":"Shopping",
            "subcategory":"Hobbies, Toys, & Games",
            "type":"Retail Goods"
        }
    ],
    "sg:phone":"+1 631 274 0393",
    "sg:postcode":"11704",
    "sg:province":"NY",
    "sg:website":"www.stupid.com",
    "wof:name":"STUPID.COM",
    "wof:placetype":"venue"
},
  "geometry": {"coordinates":[-73.37635400000001,40.7393],"type":"Point"}
}