{
  "type": "Feature",
  "properties": {
    "addr:full":"23 S Franklin St Hempstead NY 11550",
    "addr:housenumber":"23",
    "addr:postcode":"11550",
    "addr:street":"S Franklin St",
    "iso:country":"US",
    "sg:address":"23 S Franklin St",
    "sg:city":"Hempstead",
    "sg:classifiers":[
        {
            "category":"Building & Trades",
            "subcategory":"Construction",
            "type":"Services"
        }
    ],
    "sg:phone":"+1 516 693 0112",
    "sg:postcode":"11550",
    "sg:province":"NY",
    "sg:tags":[
        "contractor"
    ],
    "wof:name":"Universal Design and Development",
    "wof:placetype":"venue"
},
  "geometry": {"coordinates":[-73.625955,40.705058],"type":"Point"}
}