{
  "type": "Feature",
  "properties": {
    "iso:country":"US",
    "sg:address":"470 Pulaski St",
    "sg:city":"Brooklyn",
    "sg:classifiers":[
        {
            "category":"Freight",
            "type":"Transportation"
        }
    ],
    "sg:phone":"+1   ",
    "sg:postcode":"11221",
    "sg:province":"NY",
    "sg:tags":[
        "operator",
        "local",
        "trucking"
    ],
    "wof:name":"Good Luck Movers",
    "wof:placetype":"venue"
},
  "geometry": {"coordinates":[-73.934269,40.694089],"type":"Point"}
}