{
  "type": "Feature",
  "properties": {
    "addr:full":"11 Seacliffe Rd Rochester NY 14622",
    "addr:housenumber":"11",
    "addr:postcode":"14622",
    "addr:street":"Seacliffe Rd",
    "iso:country":"US",
    "sg:address":"11 Seacliffe Rd",
    "sg:city":"Rochester",
    "sg:classifiers":[
        {
            "category":"Building & Trades",
            "subcategory":"Construction",
            "type":"Services"
        }
    ],
    "sg:phone":"+1 585 338 9572",
    "sg:postcode":"14622",
    "sg:province":"NY",
    "sg:tags":[
        "home",
        "improvement"
    ],
    "wof:name":"Constant Remodeling",
    "wof:placetype":"venue"
},
  "geometry": {"coordinates":[-77.548666,43.231063],"type":"Point"}
}