{
  "type": "Feature",
  "properties": {
    "iso:country":"US",
    "sg:address":"155 E 55 St",
    "sg:city":"New York",
    "sg:classifiers":[
        {
            "category":"Building & Trades",
            "subcategory":"Construction",
            "type":"Services"
        }
    ],
    "sg:phone":"+1 212 223 2066",
    "sg:postcode":"10022",
    "sg:province":"NY",
    "sg:tags":[
        "contractor"
    ],
    "wof:name":"Gemini Wtr Profing Restoration",
    "wof:placetype":"venue"
},
  "geometry": {"coordinates":[-73.968822,40.759226],"type":"Point"}
}