{
  "type": "Feature",
  "properties": {
    "addr:full":"3 Maiden Ln New York NY 10038",
    "addr:housenumber":"3",
    "addr:postcode":"10038",
    "addr:street":"Maiden Ln",
    "iso:country":"US",
    "sg:address":"3 Maiden Ln",
    "sg:city":"New York",
    "sg:classifiers":[
        {
            "category":"Shopping",
            "subcategory":"Photographic Equipment",
            "type":"Retail Goods"
        }
    ],
    "sg:phone":"+1 212 285 0598",
    "sg:postcode":"10038",
    "sg:province":"NY",
    "sg:tags":[
        "supply"
    ],
    "wof:name":"Camera Gallery Corp",
    "wof:placetype":"venue"
},
  "geometry": {"coordinates":[-74.00921200000001,40.709469],"type":"Point"}
}