{
  "type": "Feature",
  "properties": {
    "iso:country":"US",
    "sg:address":"664 Glen Cove Ave",
    "sg:city":"Glen Head",
    "sg:classifiers":[
        {
            "category":"Autos & Motor Vehicles",
            "subcategory":"Automobile Sales",
            "type":"Retail Goods"
        },
        {
            "category":"Retail",
            "subcategory":"Auto Repair",
            "type":"Services"
        }
    ],
    "sg:phone":"+1 516 676 0570",
    "sg:postcode":"11545",
    "sg:province":"NY",
    "sg:tags":[
        "car",
        "station",
        "gasoline",
        "dealer",
        "general"
    ],
    "wof:name":"Glen Head Motors Inc",
    "wof:placetype":"venue"
},
  "geometry": {"coordinates":[-73.63276399999999,40.837568],"type":"Point"}
}