{
  "type": "Feature",
  "properties": {
    "addr:full":"235 E 42nd St Frnt New York NY 10017",
    "addr:housenumber":"235",
    "addr:postcode":"10017",
    "addr:street":"E 42Nd St",
    "iso:country":"US",
    "sg:address":"235 E 42nd St Frnt",
    "sg:city":"New York",
    "sg:classifiers":[
        {
            "category":"Professional",
            "subcategory":"Lawyer & Legal Services",
            "type":"Services"
        }
    ],
    "sg:phone":"+1 212 573 1960",
    "sg:postcode":"10017",
    "sg:province":"NY",
    "sg:website":"www.atlanticlegal.org",
    "wof:name":"Atlantic Legal Foundation Inc",
    "wof:placetype":"venue"
},
  "geometry": {"coordinates":[-73.973198,40.750198],"type":"Point"}
}