{
  "type": "Feature",
  "properties": {
    "addr:full":"831 Route 52 Fishkill NY 12524",
    "addr:housenumber":"831",
    "addr:postcode":"12524",
    "addr:street":"Route 52",
    "iso:country":"US",
    "sg:address":"831 Route 52",
    "sg:city":"Fishkill",
    "sg:classifiers":[
        {
            "category":"Health Services",
            "subcategory":"Dentist",
            "type":"Services"
        }
    ],
    "sg:phone":"+1 845 896 6749",
    "sg:postcode":"12524",
    "sg:province":"NY",
    "sg:tags":[
        "orthodontist"
    ],
    "sg:website":"www.fishkillortho.com",
    "wof:name":"Rosenthal Marvin PC",
    "wof:placetype":"venue"
},
  "geometry": {"coordinates":[-73.920306,41.5267],"type":"Point"}
}