{
  "type": "Feature",
  "properties": {
    "addr:full":"107 Everett Rd Albany NY 12205",
    "addr:housenumber":"107",
    "addr:postcode":"12205",
    "addr:street":"Everett Rd",
    "iso:country":"US",
    "sg:address":"107 Everett Rd",
    "sg:city":"Albany",
    "sg:classifiers":[
        {
            "category":"Professional",
            "subcategory":"Accounting & Tax Preparation",
            "type":"Services"
        }
    ],
    "sg:phone":"+1 518 459 0711",
    "sg:postcode":"12205",
    "sg:province":"NY",
    "sg:tags":[
        "bookkeeping",
        "billing"
    ],
    "sg:website":"http://www.b-e-s-t.com",
    "wof:name":"Best Systems",
    "wof:placetype":"venue"
},
  "geometry": {"coordinates":[-73.774609,42.693173],"type":"Point"}
}