{
  "type": "Feature",
  "properties": {
    "addr:full":"149 Homestead Ln Otisville NY 10940",
    "addr:housenumber":"149",
    "addr:postcode":"10940",
    "addr:street":"Homestead Ln",
    "iso:country":"US",
    "sg:address":"149 Homestead Ln",
    "sg:city":"Otisville",
    "sg:classifiers":[
        {
            "category":"Professional",
            "subcategory":"Management & Consulting",
            "type":"Services"
        }
    ],
    "sg:phone":"+1 845 386 3531",
    "sg:postcode":"10940",
    "sg:province":"NY",
    "sg:tags":[
        "business"
    ],
    "wof:name":"Harris Consulting Inc USA",
    "wof:placetype":"venue"
},
  "geometry": {"coordinates":[-74.55927800000001,41.441731],"type":"Point"}
}