{
  "type": "Feature",
  "properties": {
    "iso:country":"US",
    "sg:address":"215 Park Ave S Ste 1402",
    "sg:city":"New York",
    "sg:classifiers":[
        {
            "category":"Banks & Credit Unions",
            "subcategory":"Investment Brokerage",
            "type":"Services"
        }
    ],
    "sg:phone":"+1 212 242 2800",
    "sg:postcode":"10003",
    "sg:province":"NY",
    "sg:tags":[
        "investing"
    ],
    "sg:website":"www.christopherstreet.com",
    "wof:name":"Christopher Street Financial",
    "wof:placetype":"venue"
},
  "geometry": {"coordinates":[-73.988339,40.736796],"type":"Point"}
}