{
  "type": "Feature",
  "properties": {
    "addr:full":"138 Barrett Ave Bayport NY 11705",
    "addr:housenumber":"138",
    "addr:postcode":"11705",
    "addr:street":"Barrett Ave",
    "iso:country":"US",
    "sg:address":"138 Barrett Ave",
    "sg:city":"Bayport",
    "sg:classifiers":[
        {
            "category":"Building & Trades",
            "subcategory":"Electrical",
            "type":"Services"
        }
    ],
    "sg:phone":"+1 631 472 2970",
    "sg:postcode":"11705",
    "sg:province":"NY",
    "sg:tags":[
        "electric",
        "contractor"
    ],
    "wof:name":"Paumanock Electric Inc",
    "wof:placetype":"venue"
},
  "geometry": {"coordinates":[-73.049897,40.754828],"type":"Point"}
}