{
  "type": "Feature",
  "properties": {
    "iso:country":"US",
    "sg:address":"57 N Main St",
    "sg:city":"Pittsford",
    "sg:classifiers":[
        {
            "category":"Shopping",
            "subcategory":"Tobacco",
            "type":"Retail Goods"
        }
    ],
    "sg:phone":"+1 585 264 1060",
    "sg:postcode":"14534",
    "sg:province":"NY",
    "sg:tags":[
        "cigarette",
        "cigar",
        "dealer"
    ],
    "wof:name":"Pittsford Village Market",
    "wof:placetype":"venue"
},
  "geometry": {"coordinates":[-77.514133,43.094206],"type":"Point"}
}