{
  "type": "Feature",
  "properties": {
    "addr:full":"125 Industrial Loop Staten Island NY 10309",
    "addr:housenumber":"125",
    "addr:postcode":"10309",
    "addr:street":"Industrial Loop",
    "iso:country":"US",
    "sg:address":"125 Industrial Loop",
    "sg:city":"Staten Island",
    "sg:classifiers":[
        {
            "category":"Building & Trades",
            "subcategory":"Construction",
            "type":"Services"
        }
    ],
    "sg:phone":"+1 718 967 5522",
    "sg:postcode":"10309",
    "sg:province":"NY",
    "sg:tags":[
        "contractor"
    ],
    "wof:name":"Madonia Development Corporation",
    "wof:placetype":"venue"
},
  "geometry": {"coordinates":[-74.230373,40.549169],"type":"Point"}
}