{
  "type": "Feature",
  "properties": {
    "addr:full":"13 Vista Pl Hartsdale NY 10530",
    "addr:housenumber":"13",
    "addr:postcode":"10530",
    "addr:street":"Vista Pl",
    "iso:country":"US",
    "sg:address":"13 Vista Pl",
    "sg:city":"Hartsdale",
    "sg:classifiers":[
        {
            "category":"Arts & Performance",
            "subcategory":"Theater",
            "type":"Entertainment"
        }
    ],
    "sg:phone":"+1 914 674 4242",
    "sg:postcode":"10530",
    "sg:province":"NY",
    "sg:tags":[
        "entertainer"
    ],
    "wof:name":"Irwin Finger Singer/Guitarist",
    "wof:placetype":"venue"
},
  "geometry": {"coordinates":[-73.827011,41.024552],"type":"Point"}
}