{
  "type": "Feature",
  "properties": {
    "addr:full":"2337 Bath Ave Brooklyn NY 11214",
    "addr:housenumber":"2337",
    "addr:postcode":"11214",
    "addr:street":"Bath Ave",
    "iso:country":"US",
    "sg:address":"2337 Bath Ave",
    "sg:city":"Brooklyn",
    "sg:classifiers":[
        {
            "category":"Restaurant",
            "type":"Food & Drink"
        }
    ],
    "sg:menulink":"http://www.allmenus.com/ny/brooklyn/49588-mamma-mia-pizzeria--italian-restaurant/menu/",
    "sg:phone":"+1 718 373 6356",
    "sg:postcode":"11214",
    "sg:province":"NY",
    "sg:tags":[
        "italian"
    ],
    "wof:name":"Mamma Mia Pizzeria & Italian Restaurant",
    "wof:placetype":"venue"
},
  "geometry": {"coordinates":[-73.994221,40.596307],"type":"Point"}
}