{
  "type": "Feature",
  "properties": {
    "addr:full":"523 Lower Ravine Rd Norwich NY 13815",
    "addr:housenumber":"523",
    "addr:postcode":"13815",
    "addr:street":"Lower Ravine Rd",
    "iso:country":"US",
    "sg:address":"523 Lower Ravine Rd",
    "sg:city":"Norwich",
    "sg:classifiers":[
        {
            "category":"Manufacturing",
            "subcategory":"Lumber",
            "type":"Manufacturing & Wholesale Goods"
        }
    ],
    "sg:phone":"+1   ",
    "sg:postcode":"13815",
    "sg:province":"NY",
    "sg:tags":[
        "logging"
    ],
    "wof:name":"Lawrence Murray",
    "wof:placetype":"venue"
},
  "geometry": {"coordinates":[-75.53274399999999,42.499363],"type":"Point"}
}