{
  "type": "Feature",
  "properties": {
    "addr:full":"26 Carleton Ave East Islip NY 11730",
    "addr:housenumber":"26",
    "addr:postcode":"11730",
    "addr:street":"Carleton Ave",
    "iso:country":"US",
    "sg:address":"26 Carleton Ave",
    "sg:city":"East Islip",
    "sg:classifiers":[
        {
            "category":"Professional",
            "subcategory":"Lawyer & Legal Services",
            "type":"Services"
        }
    ],
    "sg:phone":"+1 631 224 3444",
    "sg:postcode":"11730",
    "sg:province":"NY",
    "sg:tags":[
        "attorney"
    ],
    "wof:name":"Steven R Savoia",
    "wof:placetype":"venue"
},
  "geometry": {"coordinates":[-73.19084599999999,40.731159],"type":"Point"}
}