{
  "type": "Feature",
  "properties": {
    "addr:full":"13 Stone Hill Rd Cold Spring NY 10516",
    "addr:housenumber":"13",
    "addr:postcode":"10516",
    "addr:street":"Stone Hill Rd",
    "iso:country":"US",
    "sg:address":"13 Stone Hill Rd",
    "sg:city":"Cold Spring",
    "sg:classifiers":[
        {
            "category":"Wholesale",
            "subcategory":"Non-durable Goods",
            "type":"Manufacturing & Wholesale Goods"
        }
    ],
    "sg:phone":"+1 845 265 3765",
    "sg:postcode":"10516",
    "sg:province":"NY",
    "wof:name":"Expressions Inc",
    "wof:placetype":"venue"
},
  "geometry": {"coordinates":[-73.894334,41.482474],"type":"Point"}
}