{
  "type": "Feature",
  "properties": {
    "iso:country":"US",
    "sg:address":"318 Roanoke Ave",
    "sg:city":"Riverhead",
    "sg:classifiers":[
        {
            "category":"Insurance",
            "subcategory":"Insurance Agent",
            "type":"Services"
        }
    ],
    "sg:phone":"+1 631 727 8111",
    "sg:postcode":"11901",
    "sg:province":"NY",
    "sg:tags":[
        "consultant",
        "planning",
        "financial"
    ],
    "wof:name":"East End Financial",
    "wof:placetype":"venue"
},
  "geometry": {"coordinates":[-72.66351400000001,40.919987],"type":"Point"}
}