{
  "type": "Feature",
  "properties": {
    "addr:full":"640 5th Ave New York NY 10019",
    "addr:housenumber":"640",
    "addr:postcode":"10019",
    "addr:street":"5Th Ave",
    "iso:country":"US",
    "sg:address":"640 5th Ave",
    "sg:city":"New York",
    "sg:classifiers":[
        {
            "category":"Building & Trades",
            "subcategory":"Cleaning & Sanitation",
            "type":"Services"
        }
    ],
    "sg:phone":"+1 212 957 0631",
    "sg:postcode":"10019",
    "sg:province":"NY",
    "sg:tags":[
        "maintenance"
    ],
    "wof:name":"Building Maintenance Svc Co",
    "wof:placetype":"venue"
},
  "geometry": {"coordinates":[-73.97628899999999,40.759786],"type":"Point"}
}