{
  "type": "Feature",
  "properties": {
    "iso:country":"US",
    "sg:address":"302 Burt St",
    "sg:city":"Syracuse",
    "sg:classifiers":[
        {
            "category":"Social Services",
            "type":"Services"
        }
    ],
    "sg:phone":"+1 315 474 1539",
    "sg:postcode":"13202",
    "sg:province":"NY",
    "sg:tags":[
        "organization",
        "welfare"
    ],
    "wof:name":"Huntington Family Ctr",
    "wof:placetype":"venue"
},
  "geometry": {"coordinates":[-76.145597,43.038232],"type":"Point"}
}