{
  "type": "Feature",
  "properties": {
    "addr:full":"257 Dyckman St New York NY 10034",
    "addr:housenumber":"257",
    "addr:postcode":"10034",
    "addr:street":"Dyckman St",
    "iso:country":"US",
    "sg:address":"257 Dyckman St",
    "sg:city":"New York",
    "sg:classifiers":[
        {
            "category":"Food & Beverages",
            "subcategory":"Groceries & Convenience Stores",
            "type":"Retail Goods"
        }
    ],
    "sg:phone":"+1   ",
    "sg:postcode":"10034",
    "sg:province":"NY",
    "wof:name":"Joaquin Grocery of New York",
    "wof:placetype":"venue"
},
  "geometry": {"coordinates":[-73.92835700000001,40.86646],"type":"Point"}
}