{
  "type": "Feature",
  "properties": {
    "iso:country":"US",
    "sg:address":"98 Traction Blvd",
    "sg:city":"Patchogue",
    "sg:classifiers":[
        {
            "category":"Food & Beverages",
            "subcategory":"Groceries & Convenience Stores",
            "type":"Retail Goods"
        }
    ],
    "sg:phone":"+1 631 447 7143",
    "sg:postcode":"11772",
    "sg:province":"NY",
    "sg:tags":[
        "restaurant"
    ],
    "wof:name":"I T S A",
    "wof:placetype":"venue"
},
  "geometry": {"coordinates":[-73.02413199999999,40.7873],"type":"Point"}
}