{
  "type": "Feature",
  "properties": {
    "iso:country":"US",
    "sg:address":"435 W Beech St",
    "sg:city":"Long Beach",
    "sg:classifiers":[
        {
            "category":"Wholesale",
            "subcategory":"Groceries",
            "type":"Manufacturing & Wholesale Goods"
        }
    ],
    "sg:phone":"+1 516 889 0997",
    "sg:postcode":"11561",
    "sg:province":"NY",
    "sg:tags":[
        "food",
        "product"
    ],
    "wof:name":"Trademark Commodities",
    "wof:placetype":"venue"
},
  "geometry": {"coordinates":[-73.67762,40.586176],"type":"Point"}
}