{
  "type": "Feature",
  "properties": {
    "addr:full":"1216 Southern Blvd Bronx NY 10459",
    "addr:housenumber":"1216",
    "addr:postcode":"10459",
    "addr:street":"Southern Blvd",
    "iso:country":"US",
    "sg:address":"1216 Southern Blvd",
    "sg:city":"Bronx",
    "sg:classifiers":[
        {
            "category":"Home & Garden",
            "subcategory":"Home Furnishings",
            "type":"Retail Goods"
        }
    ],
    "sg:phone":"+1 718 542 2122",
    "sg:postcode":"10459",
    "sg:province":"NY",
    "sg:tags":[
        "mirror"
    ],
    "wof:name":"Home Glass & Shade Co",
    "wof:placetype":"venue"
},
  "geometry": {"coordinates":[-73.891803,40.82981],"type":"Point"}
}