{
  "type": "Feature",
  "properties": {
    "iso:country":"US",
    "sg:address":"260 North St",
    "sg:city":"Geneva",
    "sg:classifiers":[
        {
            "category":"Real Estate",
            "subcategory":"Real Estate Operator",
            "type":"Services"
        }
    ],
    "sg:phone":"+1 315 789 0902",
    "sg:postcode":"14456",
    "sg:province":"NY",
    "sg:tags":[
        "building",
        "apartment"
    ],
    "wof:name":"North Street Apartments",
    "wof:placetype":"venue"
},
  "geometry": {"coordinates":[-76.988377,42.875775],"type":"Point"}
}