{
  "type": "Feature",
  "properties": {
    "iso:country":"US",
    "sg:address":"3723 Route 112",
    "sg:city":"Coram",
    "sg:classifiers":[
        {
            "category":"Food & Beverages",
            "subcategory":"Liquor & Beverages",
            "type":"Retail Goods"
        }
    ],
    "sg:phone":"+1 631 732 1169",
    "sg:postcode":"11727",
    "sg:province":"NY",
    "sg:tags":[
        "beer",
        "spirit",
        "wine"
    ],
    "wof:name":"Star's Beverage Depot",
    "wof:placetype":"venue"
},
  "geometry": {"coordinates":[-72.997398,40.848801],"type":"Point"}
}