{
  "type": "Feature",
  "properties": {
    "iso:country":"US",
    "sg:address":"55 E Main St",
    "sg:city":"Oyster Bay",
    "sg:classifiers":[
        {
            "category":"Freight",
            "type":"Transportation"
        }
    ],
    "sg:phone":"+1 516 922 5900",
    "sg:postcode":"11771",
    "sg:province":"NY",
    "sg:tags":[
        "mover"
    ],
    "wof:name":"You Do It Moving & Storage",
    "wof:placetype":"venue"
},
  "geometry": {"coordinates":[-73.528367,40.87225],"type":"Point"}
}