{
  "type": "Feature",
  "properties": {
    "iso:country":"US",
    "sg:address":"131 Ave C",
    "sg:city":"New York",
    "sg:classifiers":[
        {
            "category":"Restaurant",
            "type":"Food & Drink"
        }
    ],
    "sg:phone":"+1   ",
    "sg:postcode":"10009",
    "sg:province":"NY",
    "sg:tags":[
        "lebanese"
    ],
    "wof:name":"Babo Restaurant",
    "wof:placetype":"venue"
},
  "geometry": {"coordinates":[-73.97812500000001,40.725175],"type":"Point"}
}