{
  "type": "Feature",
  "properties": {
    "iso:country":"US",
    "sg:address":"609 Carter St",
    "sg:city":"New Canaan",
    "sg:classifiers":[
        {
            "category":"Professional",
            "type":"Services"
        }
    ],
    "sg:phone":"+1   ",
    "sg:postcode":"06840",
    "sg:province":"NY",
    "wof:name":"Peter Hemmers",
    "wof:placetype":"venue"
},
  "geometry": {"coordinates":[-73.462355,41.137685],"type":"Point"}
}