{
  "type": "Feature",
  "properties": {
    "iso:country":"US",
    "sg:address":"16 Caprice Dr",
    "sg:city":"Buffalo",
    "sg:classifiers":[
        {
            "category":"Wholesale",
            "subcategory":"Auto Parts",
            "type":"Manufacturing & Wholesale Goods"
        }
    ],
    "sg:phone":"+1 716 668 4577",
    "sg:postcode":"14227",
    "sg:province":"NY",
    "sg:tags":[
        "used"
    ],
    "wof:name":"Flatex Inc of Fort Myers",
    "wof:placetype":"venue"
},
  "geometry": {"coordinates":[-78.72559200000001,42.86652],"type":"Point"}
}