{
  "type": "Feature",
  "properties": {
    "iso:country":"US",
    "sg:address":"2155 Bedell Rd",
    "sg:city":"Grand Island",
    "sg:classifiers":[
        {
            "category":"Real Estate",
            "subcategory":"Real Estate Operator",
            "type":"Services"
        }
    ],
    "sg:phone":"+1 716 773 1102",
    "sg:postcode":"14072",
    "sg:province":"NY",
    "sg:tags":[
        "building",
        "apartment"
    ],
    "wof:name":"Grand Island Associates",
    "wof:placetype":"venue"
},
  "geometry": {"coordinates":[-78.9717,43.036371],"type":"Point"}
}