{
  "type": "Feature",
  "properties": {
    "addr:full":"484 Little Pond Rd Williamstown NY 13493",
    "addr:housenumber":"484",
    "addr:postcode":"13493",
    "addr:street":"Little Pond Rd",
    "iso:country":"US",
    "sg:address":"484 Little Pond Rd",
    "sg:city":"Williamstown",
    "sg:classifiers":[
        {
            "category":"Food & Beverages",
            "subcategory":"Groceries & Convenience Stores",
            "type":"Retail Goods"
        }
    ],
    "sg:phone":"+1 315 964 7709",
    "sg:postcode":"13493",
    "sg:province":"NY",
    "wof:name":"Jamieson Corner Conveniences Store Inc",
    "wof:placetype":"venue"
},
  "geometry": {"coordinates":[-75.971017,43.40238],"type":"Point"}
}