{
  "type": "Feature",
  "properties": {
    "addr:full":"2 Dr Girling Dr Haverstraw NY 10927",
    "addr:housenumber":"2",
    "addr:postcode":"10927",
    "addr:street":"Dr Girling Dr",
    "iso:country":"US",
    "sg:address":"2 Dr Girling Dr",
    "sg:city":"Haverstraw",
    "sg:classifiers":[
        {
            "category":"Building & Trades",
            "subcategory":"Landscaping Services",
            "type":"Services"
        },
        {
            "category":"Building & Trades",
            "subcategory":"Construction",
            "type":"Services"
        }
    ],
    "sg:phone":"+1 845 942 5555",
    "sg:postcode":"10927",
    "sg:province":"NY",
    "sg:tags":[
        "industrial",
        "consultant",
        "contractor",
        "designer",
        "contractors-commercial",
        "masonry",
        "mason",
        "landscape"
    ],
    "sg:website":"http://www.executivetouchlandscaping.com",
    "wof:name":"Executive Touch Landscaping & Construction",
    "wof:placetype":"venue"
},
  "geometry": {"coordinates":[-73.960267,41.191283],"type":"Point"}
}