{
  "type": "Feature",
  "properties": {
    "addr:full":"83 Oriskany Blvd Whitesboro NY 13492",
    "addr:housenumber":"83",
    "addr:postcode":"13492",
    "addr:street":"Oriskany Blvd",
    "iso:country":"US",
    "sg:address":"83 Oriskany Blvd",
    "sg:city":"Whitesboro",
    "sg:classifiers":[
        {
            "category":"Restaurant",
            "type":"Food & Drink"
        }
    ],
    "sg:phone":"+1 315 736 2509",
    "sg:postcode":"13492",
    "sg:province":"NY",
    "sg:tags":[
        "pizza"
    ],
    "wof:name":"Casa Motta's Pizza Pasta",
    "wof:placetype":"venue"
},
  "geometry": {"coordinates":[-75.292638,43.118673],"type":"Point"}
}