{
  "type": "Feature",
  "properties": {
    "iso:country":"US",
    "sg:address":"1360 85th St",
    "sg:city":"Brooklyn",
    "sg:classifiers":[
        {
            "category":"Food & Beverages",
            "subcategory":"Groceries & Convenience Stores",
            "type":"Retail Goods"
        }
    ],
    "sg:phone":"+1 718 234 6578",
    "sg:postcode":"11228",
    "sg:province":"NY",
    "sg:tags":[
        "grocer"
    ],
    "wof:name":"Fine Fast Foods Parkway",
    "wof:placetype":"venue"
},
  "geometry": {"coordinates":[-74.012156,40.614095],"type":"Point"}
}