{
  "type": "Feature",
  "properties": {
    "addr:full":"404 Smith St Brooklyn NY 11231",
    "addr:housenumber":"404",
    "addr:postcode":"11231",
    "addr:street":"Smith St",
    "iso:country":"US",
    "sg:address":"404 Smith St",
    "sg:city":"Brooklyn",
    "sg:classifiers":[
        {
            "category":"Retail",
            "subcategory":"Auto Rental",
            "type":"Services"
        }
    ],
    "sg:phone":"+1 718 694 0744",
    "sg:postcode":"11231",
    "sg:province":"NY",
    "sg:tags":[
        "renting",
        "truck",
        "leasing"
    ],
    "wof:name":"U-Haul Co",
    "wof:placetype":"venue"
},
  "geometry": {"coordinates":[-73.99682799999999,40.676694],"type":"Point"}
}