{
  "type": "Feature",
  "properties": {
    "iso:country":"US",
    "sg:address":"7 Lake Country Ave",
    "sg:city":"Ithaca",
    "sg:classifiers":[
        {
            "category":"Real Estate",
            "subcategory":"Real Estate Operator",
            "type":"Services"
        }
    ],
    "sg:phone":"+1 607 257 2707",
    "sg:postcode":"14850",
    "sg:province":"NY",
    "sg:tags":[
        "mobile",
        "home",
        "community"
    ],
    "wof:name":"Hanshaw Village MHP",
    "wof:placetype":"venue"
},
  "geometry": {"coordinates":[-76.430328,42.48322],"type":"Point"}
}