{
  "type": "Feature",
  "properties": {
    "iso:country":"US",
    "sg:address":"36 Sea Cliff Ave",
    "sg:city":"Glen Cove",
    "sg:classifiers":[
        {
            "category":"Manufacturing",
            "subcategory":"Metals",
            "type":"Manufacturing & Wholesale Goods"
        }
    ],
    "sg:phone":"+1   ",
    "sg:postcode":"11542",
    "sg:province":"NY",
    "sg:tags":[
        "manufacture",
        "utensil",
        "cooking"
    ],
    "sg:website":"www.atecousa.com",
    "wof:name":"August Thomsen Corp",
    "wof:placetype":"venue"
},
  "geometry": {"coordinates":[-73.625387,40.851628],"type":"Point"}
}