{
  "type": "Feature",
  "properties": {
    "addr:full":"30 Bay Ave East Moriches NY 11940",
    "addr:housenumber":"30",
    "addr:postcode":"11940",
    "addr:street":"Bay Ave East",
    "iso:country":"US",
    "sg:address":"30 Bay Ave",
    "sg:city":"East Moriches",
    "sg:classifiers":[
        {
            "category":"Real Estate",
            "subcategory":"Architect",
            "type":"Services"
        }
    ],
    "sg:phone":"+1 631 874 2925",
    "sg:postcode":"11940",
    "sg:province":"NY",
    "wof:name":"Kerri Kazel Architect",
    "wof:placetype":"venue"
},
  "geometry": {"coordinates":[-72.77079999999999,40.797084],"type":"Point"}
}