{
  "type": "Feature",
  "properties": {
    "addr:full":"274 Madison Avenue New York NY 10016",
    "addr:housenumber":"274",
    "addr:postcode":"10016",
    "addr:street":"Madison Avenue",
    "iso:country":"US",
    "sg:address":"274 Madison Avenue",
    "sg:city":"New York",
    "sg:classifiers":[
        {
            "category":"Professional",
            "subcategory":"Accounting & Tax Preparation",
            "type":"Services"
        }
    ],
    "sg:phone":"+1 212 533 6246",
    "sg:postcode":"10016",
    "sg:province":"NY",
    "sg:tags":[
        "accountant"
    ],
    "wof:name":"Briloff L A CPA",
    "wof:placetype":"venue"
},
  "geometry": {"coordinates":[-73.980379,40.751361],"type":"Point"}
}