{
  "type": "Feature",
  "properties": {
    "addr:full":"535 Westside Dr Rochester NY 14624",
    "addr:housenumber":"535",
    "addr:postcode":"14624",
    "addr:street":"Westside Dr",
    "iso:country":"US",
    "sg:address":"535 Westside Dr",
    "sg:city":"Rochester",
    "sg:classifiers":[
        {
            "category":"Building & Trades",
            "subcategory":"Landscaping Services",
            "type":"Services"
        }
    ],
    "sg:phone":"+1 585 247 6790",
    "sg:postcode":"14624",
    "sg:province":"NY",
    "sg:tags":[
        "landscape",
        "contractor"
    ],
    "wof:name":"Cerretto's Landscape & Lawn",
    "wof:placetype":"venue"
},
  "geometry": {"coordinates":[-77.71892800000001,43.125519],"type":"Point"}
}