{
  "type": "Feature",
  "properties": {
    "iso:country":"US",
    "sg:address":"28 Lovell Ln",
    "sg:city":"New Rochelle",
    "sg:classifiers":[
        {
            "category":"Building & Trades",
            "subcategory":"Construction",
            "type":"Services"
        }
    ],
    "sg:phone":"+1 914 633 3161",
    "sg:postcode":"10804",
    "sg:province":"NY",
    "sg:tags":[
        "house"
    ],
    "wof:name":"Cumberland Construction Inc",
    "wof:placetype":"venue"
},
  "geometry": {"coordinates":[-73.795253,40.951123],"type":"Point"}
}