{
  "type": "Feature",
  "properties": {
    "addr:full":"1508 Mermaid Ave Brooklyn NY 11224",
    "addr:housenumber":"1508",
    "addr:postcode":"11224",
    "addr:street":"Mermaid Ave",
    "iso:country":"US",
    "sg:address":"1508 Mermaid Ave",
    "sg:city":"Brooklyn",
    "sg:classifiers":[
        {
            "category":"Restaurant",
            "type":"Food & Drink"
        }
    ],
    "sg:phone":"+1 718 449 9132",
    "sg:postcode":"11224",
    "sg:province":"NY",
    "sg:tags":[
        "deli",
        "delicatessen"
    ],
    "wof:name":"Fronteras Grocery Corp",
    "wof:placetype":"venue"
},
  "geometry": {"coordinates":[-73.983002,40.5769],"type":"Point"}
}