{
  "type": "Feature",
  "properties": {
    "iso:country":"US",
    "sg:address":"51 Forest Rd",
    "sg:city":"Monroe",
    "sg:classifiers":[
        {
            "category":"Food & Beverages",
            "subcategory":"Bakery",
            "type":"Retail Goods"
        }
    ],
    "sg:phone":"+1 845 783 2772",
    "sg:postcode":"10950",
    "sg:province":"NY",
    "sg:tags":[
        "baker"
    ],
    "wof:name":"Joel Kiryas World Famous Bkry",
    "wof:placetype":"venue"
},
  "geometry": {"coordinates":[-74.170197,41.34009],"type":"Point"}
}