{
  "type": "Feature",
  "properties": {
    "iso:country":"US",
    "sg:address":"431 Hawthorne Ave",
    "sg:city":"Yonkers",
    "sg:classifiers":[
        {
            "category":"Professional",
            "subcategory":"Accounting & Tax Preparation",
            "type":"Services"
        }
    ],
    "sg:phone":"+1 914 709 9260",
    "sg:postcode":"10705",
    "sg:province":"NY",
    "sg:tags":[
        "bookkeeping",
        "general"
    ],
    "wof:name":"Accountability",
    "wof:placetype":"venue"
},
  "geometry": {"coordinates":[-73.904606,40.917803],"type":"Point"}
}