{
  "type": "Feature",
  "properties": {
    "addr:full":"219 W 40th St Manhattan NY 10018",
    "addr:housenumber":"219",
    "addr:postcode":"10018",
    "addr:street":"W 40Th St",
    "iso:country":"US",
    "sg:address":"219 W 40th St",
    "sg:city":"Manhattan",
    "sg:classifiers":[
        {
            "category":"Education",
            "subcategory":"University",
            "type":"Public Place"
        }
    ],
    "sg:phone":"+1 646 758 7800",
    "sg:postcode":"10018",
    "sg:province":"NY",
    "sg:tags":[
        "college"
    ],
    "sg:website":"www.journalism.cuny.edu",
    "wof:name":"CUNY Graduate School of Journalism",
    "wof:placetype":"venue"
},
  "geometry": {"coordinates":[-73.98894199999999,40.755573],"type":"Point"}
}