{
  "type": "Feature",
  "properties": {
    "iso:country":"US",
    "sg:address":"16 Brotherhood Plaza Dr",
    "sg:city":"Washingtonville",
    "sg:classifiers":[
        {
            "category":"Restaurant",
            "type":"Food & Drink"
        }
    ],
    "sg:phone":"+1 845 496 1473",
    "sg:postcode":"10992",
    "sg:province":"NY",
    "sg:tags":[
        "chinese"
    ],
    "wof:name":"Kam Fung Chinese Restaurant",
    "wof:placetype":"venue"
},
  "geometry": {"coordinates":[-74.16295100000001,41.428045],"type":"Point"}
}