{
  "type": "Feature",
  "properties": {
    "iso:country":"US",
    "sg:address":"7120 Snyder Hill Rd",
    "sg:city":"Cattaraugus",
    "sg:classifiers":[
        {
            "category":"Farming",
            "subcategory":"Dairy Farm",
            "type":"Manufacturing & Wholesale Goods"
        }
    ],
    "sg:phone":"+1 716 257 3544",
    "sg:postcode":"14719",
    "sg:province":"NY",
    "wof:name":"Windy-J-Crest Farm",
    "wof:placetype":"venue"
},
  "geometry": {"coordinates":[-78.88847699999999,42.289688],"type":"Point"}
}