{
  "type": "Feature",
  "properties": {
    "iso:country":"US",
    "sg:address":"16 Churchill Ave",
    "sg:city":"Staten Island",
    "sg:classifiers":[
        {
            "category":"Professional",
            "subcategory":"Lawyer & Legal Services",
            "type":"Services"
        }
    ],
    "sg:phone":"+1 718 966 3543",
    "sg:postcode":"10309",
    "sg:province":"NY",
    "sg:tags":[
        "attorney"
    ],
    "wof:name":"Joanne Olson",
    "wof:placetype":"venue"
},
  "geometry": {"coordinates":[-74.217473,40.529017],"type":"Point"}
}