{
  "type": "Feature",
  "properties": {
    "addr:full":"12 Wilkins Ave Albany NY 12205",
    "addr:housenumber":"12",
    "addr:postcode":"12205",
    "addr:street":"Wilkins Ave",
    "iso:country":"US",
    "sg:address":"12 Wilkins Ave",
    "sg:city":"Albany",
    "sg:classifiers":[
        {
            "category":"Transit Center",
            "subcategory":"Freight",
            "type":"Transportation"
        },
        {
            "category":"Freight",
            "type":"Transportation"
        }
    ],
    "sg:phone":"+1 518 459 5447",
    "sg:postcode":"12205",
    "sg:province":"NY",
    "sg:tags":[
        "local",
        "trucking-motor",
        "trucking"
    ],
    "wof:name":"Krug Trucking",
    "wof:placetype":"venue"
},
  "geometry": {"coordinates":[-73.790164,42.691022],"type":"Point"}
}