{
  "type": "Feature",
  "properties": {
    "iso:country":"US",
    "sg:address":"1806 Vestal Pkwy E",
    "sg:city":"Vestal",
    "sg:classifiers":[
        {
            "category":"Sports & Exercise",
            "subcategory":"Gym",
            "type":"Entertainment"
        }
    ],
    "sg:phone":"+1 607 786 0800",
    "sg:postcode":"13850",
    "sg:province":"NY",
    "sg:tags":[
        "club",
        "gymnasium",
        "program",
        "health",
        "fitness",
        "studio",
        "physical"
    ],
    "wof:name":"American Family Fitness",
    "wof:placetype":"venue"
},
  "geometry": {"coordinates":[-76.022396,42.093059],"type":"Point"}
}