{
  "type": "Feature",
  "properties": {
    "addr:full":"110 E 42nd St New York NY 10017",
    "addr:housenumber":"110",
    "addr:postcode":"10017",
    "addr:street":"E 42Nd St",
    "iso:country":"US",
    "sg:address":"110 E 42nd St",
    "sg:city":"New York",
    "sg:classifiers":[
        {
            "category":"Professional",
            "type":"Services"
        }
    ],
    "sg:phone":"+1 212 588 0416",
    "sg:postcode":"10017",
    "sg:province":"NY",
    "sg:tags":[
        "establishment"
    ],
    "wof:name":"Lighthouse Partners LLC",
    "wof:placetype":"venue"
},
  "geometry": {"coordinates":[-73.97637,40.751533],"type":"Point"}
}