{
  "type": "Feature",
  "properties": {
    "iso:country":"US",
    "sg:address":"488 Jericho Tpke",
    "sg:city":"Huntington Station",
    "sg:classifiers":[
        {
            "category":"Education",
            "subcategory":"Kindergarten",
            "type":"Public Place"
        }
    ],
    "sg:phone":"+1 631 271 6636",
    "sg:postcode":"11746",
    "sg:province":"NY",
    "sg:tags":[
        "school",
        "driving"
    ],
    "sg:website":"www.defensive-driving.org",
    "wof:name":"Defensive Driving School Inc",
    "wof:placetype":"venue"
},
  "geometry": {"coordinates":[-73.392905,40.831623],"type":"Point"}
}