{
  "type": "Feature",
  "properties": {
    "iso:country":"US",
    "sg:address":"195 Grove St",
    "sg:city":"Middleburgh",
    "sg:classifiers":[
        {
            "category":"Social Services",
            "type":"Services"
        }
    ],
    "sg:phone":"+1 518 827 7300",
    "sg:postcode":"12122",
    "sg:province":"NY",
    "sg:tags":[
        "organization",
        "welfare"
    ],
    "wof:name":"Capital District DDSO",
    "wof:placetype":"venue"
},
  "geometry": {"coordinates":[-74.324691,42.600606],"type":"Point"}
}