{
  "type": "Feature",
  "properties": {
    "addr:full":"2546 Lake Rd Silver Creek NY 14136",
    "addr:housenumber":"2546",
    "addr:postcode":"14136",
    "addr:street":"Lake Rd",
    "iso:country":"US",
    "sg:address":"2546 Lake Rd",
    "sg:city":"Silver Creek",
    "sg:classifiers":[
        {
            "category":"Organizations",
            "subcategory":"Religious Organization",
            "type":"Services"
        }
    ],
    "sg:phone":"+1 716 934 7979",
    "sg:postcode":"14136",
    "sg:province":"NY",
    "sg:tags":[
        "clergy"
    ],
    "wof:name":"Ralph P Federico",
    "wof:placetype":"venue"
},
  "geometry": {"coordinates":[-79.22743,42.534448],"type":"Point"}
}