{
  "type": "Feature",
  "properties": {
    "addr:full":"155 E 34th St New York NY 10016",
    "addr:housenumber":"155",
    "addr:postcode":"10016",
    "addr:street":"E 34Th St",
    "iso:country":"US",
    "sg:address":"155 E 34th St",
    "sg:city":"New York",
    "sg:classifiers":[
        {
            "category":"Professional",
            "subcategory":"Lawyer & Legal Services",
            "type":"Services"
        }
    ],
    "sg:phone":"+1 212 986 4181",
    "sg:postcode":"10016",
    "sg:province":"NY",
    "wof:name":"Halprin & Goler",
    "wof:placetype":"venue"
},
  "geometry": {"coordinates":[-73.978543,40.746168],"type":"Point"}
}