{
  "type": "Feature",
  "properties": {
    "addr:full":"390 Main Mall Poughkeepsie NY 12601",
    "addr:housenumber":"390",
    "addr:postcode":"12601",
    "addr:street":"Main Mall",
    "iso:country":"US",
    "sg:address":"390 Main Mall",
    "sg:city":"Poughkeepsie",
    "sg:classifiers":[
        {
            "category":"Personal",
            "subcategory":"Beauty Salon",
            "type":"Services"
        }
    ],
    "sg:phone":"+1 845 473 3275",
    "sg:postcode":"12601",
    "sg:province":"NY",
    "wof:name":"Ebony Hair Stylists",
    "wof:placetype":"venue"
},
  "geometry": {"coordinates":[-73.923959,41.702189],"type":"Point"}
}