{
  "type": "Feature",
  "properties": {
    "iso:country":"US",
    "sg:address":"33 Manor House Ln",
    "sg:city":"Dobbs Ferry",
    "sg:classifiers":[
        {
            "category":"Professional",
            "subcategory":"Business Services",
            "type":"Services"
        }
    ],
    "sg:phone":"+1 914 674 9420",
    "sg:postcode":"10522",
    "sg:province":"NY",
    "wof:name":"Angora Promotions Inc",
    "wof:placetype":"venue"
},
  "geometry": {"coordinates":[-73.861161,41.0112],"type":"Point"}
}