{
  "type": "Feature",
  "properties": {
    "addr:full":"1007 Prospect Ave Westbury NY 11590",
    "addr:housenumber":"1007",
    "addr:postcode":"11590",
    "addr:street":"Prospect Ave",
    "iso:country":"US",
    "sg:address":"1007 Prospect Ave",
    "sg:city":"Westbury",
    "sg:classifiers":[
        {
            "category":"Utilities",
            "subcategory":"Mobile Phone",
            "type":"Services"
        }
    ],
    "sg:phone":"+1   ",
    "sg:postcode":"11590",
    "sg:province":"NY",
    "sg:tags":[
        "communication",
        "radiotelephone"
    ],
    "wof:name":"Jeandi",
    "wof:placetype":"venue"
},
  "geometry": {"coordinates":[-73.560042,40.763042],"type":"Point"}
}