{
  "type": "Feature",
  "properties": {
    "iso:country":"US",
    "sg:address":"293 Alexander St",
    "sg:city":"Rochester",
    "sg:classifiers":[
        {
            "category":"Bars & Pubs",
            "type":"Food & Drink"
        }
    ],
    "sg:phone":"+1 585 232 2230",
    "sg:postcode":"14607",
    "sg:province":"NY",
    "wof:name":"Blue Room",
    "wof:placetype":"venue"
},
  "geometry": {"coordinates":[-77.594638,43.154657],"type":"Point"}
}