{
  "type": "Feature",
  "properties": {
    "addr:full":"286 Newtown Rd Plainview NY 11803",
    "addr:housenumber":"286",
    "addr:postcode":"11803",
    "addr:street":"Newtown Rd",
    "iso:country":"US",
    "sg:address":"286 Newtown Rd",
    "sg:city":"Plainview",
    "sg:classifiers":[
        {
            "category":"Building & Trades",
            "subcategory":"Plumbing",
            "type":"Services"
        }
    ],
    "sg:phone":"+1 516 753 2222",
    "sg:postcode":"11803",
    "sg:province":"NY",
    "sg:tags":[
        "conditioning",
        "contractor"
    ],
    "wof:name":"S A Fink Assoc",
    "wof:placetype":"venue"
},
  "geometry": {"coordinates":[-73.450903,40.786115],"type":"Point"}
}