{
  "type": "Feature",
  "properties": {
    "iso:country":"US",
    "sg:address":"530 Franklin St",
    "sg:city":"Schenectady",
    "sg:classifiers":[
        {
            "category":"Social Services",
            "subcategory":"Child Care",
            "type":"Services"
        },
        {
            "category":"Social Services",
            "type":"Services"
        }
    ],
    "sg:phone":"+1 518 370 2576",
    "sg:postcode":"12305",
    "sg:province":"NY",
    "sg:tags":[
        "worker",
        "day"
    ],
    "wof:name":"Parsons Child & Family Center",
    "wof:placetype":"venue"
},
  "geometry": {"coordinates":[-73.93814,42.812859],"type":"Point"}
}