{
  "type": "Feature",
  "properties": {
    "addr:full":"11279 Ridge Rd Medina NY 14103",
    "addr:housenumber":"11279",
    "addr:postcode":"14103",
    "addr:street":"Ridge Rd",
    "iso:country":"US",
    "sg:address":"11279 Ridge Rd",
    "sg:city":"Medina",
    "sg:classifiers":[
        {
            "category":"Wholesale",
            "subcategory":"Groceries",
            "type":"Manufacturing & Wholesale Goods"
        }
    ],
    "sg:phone":"+1 585 798 0048",
    "sg:postcode":"14103",
    "sg:province":"NY",
    "sg:tags":[
        "grocer"
    ],
    "wof:name":"Champs Mini Mart",
    "wof:placetype":"venue"
},
  "geometry": {"coordinates":[-78.39449500000001,43.267381],"type":"Point"}
}