{
  "type": "Feature",
  "properties": {
    "addr:full":"6 Broadway Bellmore NY 11710",
    "addr:housenumber":"6",
    "addr:postcode":"11710",
    "addr:street":"Broadway",
    "iso:country":"US",
    "sg:address":"6 Broadway",
    "sg:city":"Bellmore",
    "sg:classifiers":[
        {
            "category":"Real Estate",
            "subcategory":"Real Estate Services",
            "type":"Services"
        },
        {
            "category":"Real Estate",
            "subcategory":"Real Estate Agent",
            "type":"Services"
        }
    ],
    "sg:phone":"+1 516 785 0013",
    "sg:postcode":"11710",
    "sg:province":"NY",
    "sg:tags":[
        "buyer",
        "broker"
    ],
    "wof:name":"Zagarino Bros",
    "wof:placetype":"venue"
},
  "geometry": {"coordinates":[-73.527477,40.669427],"type":"Point"}
}