{
  "type": "Feature",
  "properties": {
    "addr:full":"3173 Rte 112 Medford NY 11763",
    "addr:housenumber":"3173",
    "addr:postcode":"11763",
    "addr:street":"Rte 112",
    "iso:country":"US",
    "sg:address":"3173 Rte 112",
    "sg:city":"Medford",
    "sg:classifiers":[
        {
            "category":"Autos & Motor Vehicles",
            "subcategory":"Fuel & Gas Station",
            "type":"Retail Goods"
        }
    ],
    "sg:phone":"+1   ",
    "sg:postcode":"11763",
    "sg:province":"NY",
    "sg:tags":[
        "station",
        "gasoline"
    ],
    "wof:name":"Giresun Corp",
    "wof:placetype":"venue"
},
  "geometry": {"coordinates":[-72.996565,40.841307],"type":"Point"}
}