{
  "type": "Feature",
  "properties": {
    "iso:country":"US",
    "sg:address":"14 Elm St",
    "sg:city":"Malone",
    "sg:classifiers":[
        {
            "category":"Professional",
            "subcategory":"Business Services",
            "type":"Services"
        }
    ],
    "sg:phone":"+1   ",
    "sg:postcode":"12953",
    "sg:province":"NY",
    "wof:name":"Building Insptr Cde Enfrcmnt",
    "wof:placetype":"venue"
},
  "geometry": {"coordinates":[-74.29163200000001,44.849017],"type":"Point"}
}