{
  "type": "Feature",
  "properties": {
    "addr:full":"425 E 53 St New York NY 10022",
    "addr:housenumber":"425;53",
    "addr:postcode":"10022",
    "addr:street":"E;St",
    "iso:country":"US",
    "sg:address":"425 E 53 St",
    "sg:city":"New York",
    "sg:classifiers":[
        {
            "category":"Retail",
            "subcategory":"Auto Repair",
            "type":"Services"
        }
    ],
    "sg:phone":"+1 646 237 1392",
    "sg:postcode":"10022",
    "sg:province":"NY",
    "sg:tags":[
        "wrecker"
    ],
    "wof:name":"Allstate 24 Hour Towing",
    "wof:placetype":"venue"
},
  "geometry": {"coordinates":[-73.963538,40.755357],"type":"Point"}
}