{
  "type": "Feature",
  "properties": {
    "addr:full":"105 Vermont St Long Beach NY 11561",
    "addr:housenumber":"105",
    "addr:postcode":"11561",
    "addr:street":"Vermont St",
    "iso:country":"US",
    "sg:address":"105 Vermont St",
    "sg:city":"Long Beach",
    "sg:classifiers":[
        {
            "category":"Building & Trades",
            "subcategory":"Plumbing",
            "type":"Services"
        }
    ],
    "sg:phone":"+1 516 889 5476",
    "sg:postcode":"11561",
    "sg:province":"NY",
    "sg:tags":[
        "contractor"
    ],
    "wof:name":"Four Star Air Conditioning Co",
    "wof:placetype":"venue"
},
  "geometry": {"coordinates":[-73.69319400000001,40.586267],"type":"Point"}
}