{
  "type": "Feature",
  "properties": {
    "iso:country":"US",
    "sg:address":"6395 Electric Railway",
    "sg:city":"Cicero",
    "sg:classifiers":[
        {
            "category":"Shopping",
            "subcategory":"Clothing, Apparel, & Fashions",
            "type":"Retail Goods"
        }
    ],
    "sg:phone":"+1 315 699 2229",
    "sg:postcode":"13039",
    "sg:province":"NY",
    "sg:tags":[
        "baby",
        "accessory"
    ],
    "wof:name":"Storks R Us",
    "wof:placetype":"venue"
},
  "geometry": {"coordinates":[-76.08403300000001,43.171827],"type":"Point"}
}