{
  "type": "Feature",
  "properties": {
    "iso:country":"US",
    "sg:address":"300 Temple Hill Rd",
    "sg:city":"New Windsor",
    "sg:classifiers":[
        {
            "category":"Autos & Motor Vehicles",
            "subcategory":"Automobile Sales",
            "type":"Retail Goods"
        }
    ],
    "sg:phone":"+1 845 565 7033",
    "sg:postcode":"12553",
    "sg:province":"NY",
    "sg:tags":[
        "car",
        "dealer"
    ],
    "sg:website":"www.healeybrothers.com",
    "wof:name":"Healey Used Car Outlet",
    "wof:placetype":"venue"
},
  "geometry": {"coordinates":[-74.06595799999999,41.480509],"type":"Point"}
}