{
  "type": "Feature",
  "properties": {
    "addr:full":"554 8th Ave. Manhattan NY 10018",
    "addr:housenumber":"554",
    "addr:postcode":"10018",
    "addr:street":"8Th Ave.",
    "iso:country":"US",
    "sg:address":"554 8th Ave.",
    "sg:city":"Manhattan",
    "sg:classifiers":[
        {
            "category":"Shopping",
            "subcategory":"Crafts & Fabrics",
            "type":"Retail Goods"
        }
    ],
    "sg:phone":"+1 646 319 2444",
    "sg:postcode":"10018",
    "sg:province":"NY",
    "sg:tags":[
        "store"
    ],
    "wof:name":"World Fabrics",
    "wof:placetype":"venue"
},
  "geometry": {"coordinates":[-73.991392,40.754358],"type":"Point"}
}