{
  "type": "Feature",
  "properties": {
    "addr:full":"19845 Foothill Ave Hollis NY 11423",
    "addr:housenumber":"19845",
    "addr:postcode":"11423",
    "addr:street":"Foothill Ave",
    "iso:country":"US",
    "sg:address":"19845 Foothill Ave",
    "sg:city":"Hollis",
    "sg:classifiers":[
        {
            "category":"Wholesale",
            "subcategory":"Medical Equipment & Supplies",
            "type":"Manufacturing & Wholesale Goods"
        },
        {
            "category":"Shopping",
            "subcategory":"Pharmacy",
            "type":"Retail Goods"
        },
        {
            "category":"Health Services",
            "subcategory":"Dentist",
            "type":"Services"
        }
    ],
    "sg:phone":"+1 718 465 1810",
    "sg:postcode":"11423",
    "sg:province":"NY",
    "sg:tags":[
        "home",
        "dental",
        "care"
    ],
    "sg:website":"http://www.impladentltd.com",
    "wof:name":"Impladent, Ltd.",
    "wof:placetype":"venue"
},
  "geometry": {"coordinates":[-73.760025,40.72175],"type":"Point"}
}