{
  "type": "Feature",
  "properties": {
    "addr:full":"4939 S Salina St Syracuse NY 13205",
    "addr:housenumber":"4939",
    "addr:postcode":"13205",
    "addr:street":"S Salina St",
    "iso:country":"US",
    "sg:address":"4939 S Salina St",
    "sg:city":"Syracuse",
    "sg:classifiers":[
        {
            "category":"Building & Trades",
            "subcategory":"Cleaning & Sanitation",
            "type":"Services"
        },
        {
            "category":"Building & Trades",
            "subcategory":"Landscaping Services",
            "type":"Services"
        }
    ],
    "sg:phone":"+1 315 469 4253",
    "sg:postcode":"13205",
    "sg:province":"NY",
    "sg:tags":[
        "wood",
        "product",
        "mfg",
        "snow",
        "removal",
        "construction"
    ],
    "wof:name":"Carfagno Buck LLC",
    "wof:placetype":"venue"
},
  "geometry": {"coordinates":[-76.143173,42.997151],"type":"Point"}
}