{
  "type": "Feature",
  "properties": {
    "addr:full":"77 Lexington Ave Entrance on 26th New York NY 10010",
    "addr:housenumber":"77",
    "addr:postcode":"10010",
    "addr:street":"Lexington Ave Entrance On",
    "iso:country":"US",
    "sg:address":"77 Lexington Ave Entrance on 26th",
    "sg:city":"New York",
    "sg:classifiers":[
        {
            "category":"Restaurant",
            "type":"Food & Drink"
        }
    ],
    "sg:phone":"+1 212 686 1166",
    "sg:postcode":"10010",
    "sg:province":"NY",
    "sg:tags":[
        "greek",
        "mediterranean"
    ],
    "sg:website":"favanyc.com",
    "wof:name":"Fava Mediterranean Grill",
    "wof:placetype":"venue"
},
  "geometry": {"coordinates":[-73.983204,40.741281],"type":"Point"}
}