{
  "type": "Feature",
  "properties": {
    "addr:full":"7924 Cypress Avenue Ridgewood NY 11385",
    "addr:housenumber":"7924",
    "addr:postcode":"11385",
    "addr:street":"Cypress Avenue",
    "iso:country":"US",
    "sg:address":"7924 Cypress Avenue",
    "sg:city":"Ridgewood",
    "sg:classifiers":[
        {
            "category":"Restaurant",
            "type":"Food & Drink"
        }
    ],
    "sg:phone":"+1 718 821 2000",
    "sg:postcode":"11385",
    "sg:province":"NY",
    "wof:name":"Vegas Grill",
    "wof:placetype":"venue"
},
  "geometry": {"coordinates":[-73.897586,40.694124],"type":"Point"}
}