{
  "type": "Feature",
  "properties": {
    "addr:full":"150 Glendale Dr Endicott NY 13760",
    "addr:housenumber":"150",
    "addr:postcode":"13760",
    "addr:street":"Glendale Dr",
    "iso:country":"US",
    "sg:address":"150 Glendale Dr",
    "sg:city":"Endicott",
    "sg:classifiers":[
        {
            "category":"Manufacturing",
            "subcategory":"Tools & Machinery",
            "type":"Manufacturing & Wholesale Goods"
        }
    ],
    "sg:phone":"+1 607 785 6005",
    "sg:postcode":"13760",
    "sg:province":"NY",
    "sg:tags":[
        "machine",
        "shop"
    ],
    "wof:name":"United Machine & Tool Co Inc",
    "wof:placetype":"venue"
},
  "geometry": {"coordinates":[-76.089697,42.096235],"type":"Point"}
}