{
  "type": "Feature",
  "properties": {
    "iso:country":"US",
    "sg:address":"130 S Park Ave",
    "sg:city":"Buffalo",
    "sg:classifiers":[
        {
            "category":"Restaurant",
            "type":"Food & Drink"
        }
    ],
    "sg:phone":"+1 716 848 1930",
    "sg:postcode":"14203",
    "sg:province":"NY",
    "wof:name":"Cobblestone",
    "wof:placetype":"venue"
},
  "geometry": {"coordinates":[-78.87550400000001,42.8736],"type":"Point"}
}