{
  "type": "Feature",
  "properties": {
    "iso:country":"US",
    "sg:address":"76 Clinton St",
    "sg:city":"New York",
    "sg:classifiers":[
        {
            "category":"Professional",
            "subcategory":"Management & Consulting",
            "type":"Services"
        }
    ],
    "sg:phone":"+1   ",
    "sg:postcode":"10002",
    "sg:province":"NY",
    "sg:tags":[
        "business"
    ],
    "wof:name":"G M Construction",
    "wof:placetype":"venue"
},
  "geometry": {"coordinates":[-73.985575,40.717967],"type":"Point"}
}