{
  "type": "Feature",
  "properties": {
    "addr:full":"6224 Roosevelt Ave Woodside NY 11377",
    "addr:housenumber":"6224",
    "addr:postcode":"11377",
    "addr:street":"Roosevelt Ave",
    "iso:country":"US",
    "sg:address":"6224 Roosevelt Ave",
    "sg:city":"Woodside",
    "sg:classifiers":[
        {
            "category":"Food & Beverages",
            "subcategory":"Meat & Fish",
            "type":"Retail Goods"
        }
    ],
    "sg:phone":"+1 718 426 2835",
    "sg:postcode":"11377",
    "sg:province":"NY",
    "sg:tags":[
        "seafood",
        "market"
    ],
    "wof:name":"Fish World of Ny Inc",
    "wof:placetype":"venue"
},
  "geometry": {"coordinates":[-73.90129899999999,40.745701],"type":"Point"}
}