{
  "type": "Feature",
  "properties": {
    "addr:full":"133 Chrystie St New York NY 10002",
    "addr:housenumber":"133",
    "addr:postcode":"10002",
    "addr:street":"Chrystie St",
    "iso:country":"US",
    "sg:address":"133 Chrystie St",
    "sg:city":"New York",
    "sg:classifiers":[
        {
            "category":"Food & Beverages",
            "subcategory":"Fruits & Vegetables",
            "type":"Retail Goods"
        }
    ],
    "sg:phone":"+1   ",
    "sg:postcode":"10002",
    "sg:province":"NY",
    "sg:tags":[
        "store",
        "market"
    ],
    "wof:name":"Ming Kee Produce Co Inc",
    "wof:placetype":"venue"
},
  "geometry": {"coordinates":[-73.99307399999999,40.719721],"type":"Point"}
}