{
  "type": "Feature",
  "properties": {
    "addr:full":"1965 Broadway New York NY 10023",
    "addr:housenumber":"1965",
    "addr:postcode":"10023",
    "addr:street":"Broadway",
    "iso:country":"US",
    "sg:address":"1965 Broadway",
    "sg:city":"New York",
    "sg:classifiers":[
        {
            "category":"Health Services",
            "subcategory":"Doctor",
            "type":"Services"
        }
    ],
    "sg:phone":"+1 212 501 0325",
    "sg:postcode":"10023",
    "sg:province":"NY",
    "sg:tags":[
        "medical"
    ],
    "wof:name":"Tom B Rudner MD PC",
    "wof:placetype":"venue"
},
  "geometry": {"coordinates":[-73.982201,40.774679],"type":"Point"}
}