{
  "type": "Feature",
  "properties": {
    "addr:full":"71 North St Le Roy NY 14482",
    "addr:housenumber":"71",
    "addr:postcode":"14482",
    "addr:street":"North St",
    "iso:country":"US",
    "sg:address":"71 North St",
    "sg:city":"Le Roy",
    "sg:classifiers":[
        {
            "category":"Real Estate",
            "subcategory":"Developer",
            "type":"Services"
        }
    ],
    "sg:phone":"+1 585 768 7070",
    "sg:postcode":"14482",
    "sg:province":"NY",
    "sg:tags":[
        "cemetery"
    ],
    "wof:name":"Machpelah Cemetery Assn",
    "wof:placetype":"venue"
},
  "geometry": {"coordinates":[-77.981346,42.989656],"type":"Point"}
}