{
  "type": "Feature",
  "properties": {
    "addr:full":"1891 White Plains Rd Bronx NY 10462",
    "addr:housenumber":"1891",
    "addr:postcode":"10462",
    "addr:street":"White Plains Rd",
    "iso:country":"US",
    "sg:address":"1891 White Plains Rd",
    "sg:city":"Bronx",
    "sg:phone":"+1 718 828 8444",
    "sg:postcode":"10462",
    "sg:province":"NY",
    "wof:name":"Actualidades Beauty Salon",
    "wof:placetype":"venue"
},
  "geometry": {"coordinates":[-73.866855,40.847313],"type":"Point"}
}