{
  "type": "Feature",
  "properties": {
    "iso:country":"US",
    "sg:address":"1127 Forest Hill Rd",
    "sg:city":"Apalachin",
    "sg:classifiers":[
        {
            "category":"Retail",
            "subcategory":"Portrait Studio",
            "type":"Services"
        }
    ],
    "sg:phone":"+1 607 426 6023",
    "sg:postcode":"13732",
    "sg:province":"NY",
    "sg:tags":[
        "photographer"
    ],
    "wof:name":"Through The Cameras Eye",
    "wof:placetype":"venue"
},
  "geometry": {"coordinates":[-76.184099,42.071789],"type":"Point"}
}