{
  "type": "Feature",
  "properties": {
    "iso:country":"US",
    "sg:address":"3105 Pilgrimport Rd",
    "sg:city":"Lyons",
    "sg:classifiers":[
        {
            "category":"Farming",
            "subcategory":"Dairy Farm",
            "type":"Manufacturing & Wholesale Goods"
        }
    ],
    "sg:phone":"+1 315 946 4910",
    "sg:postcode":"14489",
    "sg:province":"NY",
    "sg:tags":[
        "field",
        "corn",
        "crop"
    ],
    "wof:name":"Mayflower Farms",
    "wof:placetype":"venue"
},
  "geometry": {"coordinates":[-76.975309,43.123874],"type":"Point"}
}