{
  "type": "Feature",
  "properties": {
    "iso:country":"US",
    "sg:address":"442 Old Post Rd",
    "sg:city":"Bedford",
    "sg:classifiers":[
        {
            "category":"Utilities",
            "subcategory":"Sewage",
            "type":"Services"
        }
    ],
    "sg:phone":"+1 914 234 7455",
    "sg:postcode":"10506",
    "sg:province":"NY",
    "sg:tags":[
        "disposal",
        "system"
    ],
    "wof:name":"Powell Septic Svc Inc",
    "wof:placetype":"venue"
},
  "geometry": {"coordinates":[-73.65196,41.197433],"type":"Point"}
}