{
  "type": "Feature",
  "properties": {
    "addr:full":"174 Ludlow St New York NY 10002",
    "addr:housenumber":"174",
    "addr:postcode":"10002",
    "addr:street":"Ludlow St",
    "iso:country":"US",
    "sg:address":"174 Ludlow St",
    "sg:city":"New York",
    "sg:classifiers":[
        {
            "category":"Shopping",
            "subcategory":"Jewelry",
            "type":"Retail Goods"
        },
        {
            "category":"Personal",
            "subcategory":"Piercing",
            "type":"Services"
        }
    ],
    "sg:phone":"+1 212 253 6402",
    "sg:postcode":"10002",
    "sg:province":"NY",
    "sg:website":"www.leroimanhattan.com",
    "wof:name":"LeRoi",
    "wof:placetype":"venue"
},
  "geometry": {"coordinates":[-73.987323,40.721564],"type":"Point"}
}