{
  "type": "Feature",
  "properties": {
    "iso:country":"US",
    "sg:address":"312 W Pulteney St",
    "sg:city":"Corning",
    "sg:classifiers":[
        {
            "category":"Building & Trades",
            "subcategory":"Cleaning & Sanitation",
            "type":"Services"
        }
    ],
    "sg:phone":"+1 607 962 6153",
    "sg:postcode":"14830",
    "sg:province":"NY",
    "sg:tags":[
        "window"
    ],
    "wof:name":"Corning Window Cleaning Co",
    "wof:placetype":"venue"
},
  "geometry": {"coordinates":[-77.074415,42.152377],"type":"Point"}
}