{
  "type": "Feature",
  "properties": {
    "addr:full":"2 North St Broadalbin NY 12025",
    "addr:housenumber":"2",
    "addr:postcode":"12025",
    "addr:street":"North St",
    "iso:country":"US",
    "sg:address":"2 North St",
    "sg:city":"Broadalbin",
    "sg:classifiers":[
        {
            "category":"Organizations",
            "subcategory":"Religious Organization",
            "type":"Services"
        }
    ],
    "sg:phone":"+1   ",
    "sg:postcode":"12025",
    "sg:province":"NY",
    "wof:name":"St Josephs Church",
    "wof:placetype":"venue"
},
  "geometry": {"coordinates":[-74.19747,43.062867],"type":"Point"}
}