{
  "type": "Feature",
  "properties": {
    "iso:country":"US",
    "sg:address":"741 Union St",
    "sg:city":"Brooklyn",
    "sg:classifiers":[
        {
            "category":"Food & Beverages",
            "subcategory":"Candy",
            "type":"Retail Goods"
        }
    ],
    "sg:phone":"+1 718 623 6668",
    "sg:postcode":"11215",
    "sg:province":"NY",
    "sg:tags":[
        "dessert"
    ],
    "wof:name":"Uncle Louie G",
    "wof:placetype":"venue"
},
  "geometry": {"coordinates":[-73.98012900000001,40.676304],"type":"Point"}
}