{
  "type": "Feature",
  "properties": {
    "addr:full":"24 8th Ave Brooklyn NY 11217",
    "addr:housenumber":"24",
    "addr:postcode":"11217",
    "addr:street":"8Th Ave",
    "iso:country":"US",
    "sg:address":"24 8th Ave",
    "sg:city":"Brooklyn",
    "sg:classifiers":[
        {
            "category":"Manufacturing",
            "subcategory":"Chemicals & Compounds",
            "type":"Manufacturing & Wholesale Goods"
        }
    ],
    "sg:phone":"+1 718 237 0700",
    "sg:postcode":"11217",
    "sg:province":"NY",
    "sg:tags":[
        "salt"
    ],
    "wof:name":"Schoenberg Salt Company",
    "wof:placetype":"venue"
},
  "geometry": {"coordinates":[-73.97204600000001,40.674829],"type":"Point"}
}