{
  "type": "Feature",
  "properties": {
    "iso:country":"US",
    "sg:address":"2080 Oliver Way",
    "sg:city":"Merrick",
    "sg:classifiers":[
        {
            "category":"Social Services",
            "type":"Services"
        }
    ],
    "sg:phone":"+1 516 546 9170",
    "sg:postcode":"11566",
    "sg:province":"NY",
    "sg:tags":[
        "worker"
    ],
    "wof:name":"Kenneth J Levin, Lcsw",
    "wof:placetype":"venue"
},
  "geometry": {"coordinates":[-73.54116999999999,40.651271],"type":"Point"}
}