{
  "type": "Feature",
  "properties": {
    "addr:full":"406 Grove Street Brooklyn NY 11237",
    "addr:housenumber":"406",
    "addr:postcode":"11237",
    "addr:street":"Grove Street",
    "iso:country":"US",
    "sg:address":"406 Grove Street",
    "sg:city":"Brooklyn",
    "sg:classifiers":[
        {
            "category":"Education",
            "subcategory":"School",
            "type":"Public Place"
        }
    ],
    "sg:phone":"+1 718 381 8968",
    "sg:postcode":"11237",
    "sg:province":"NY",
    "sg:tags":[
        "high",
        "middle",
        "elementary"
    ],
    "wof:name":"New Life Head Start Child Development Center",
    "wof:placetype":"venue"
},
  "geometry": {"coordinates":[-73.912811,40.701104],"type":"Point"}
}