{
  "type": "Feature",
  "properties": {
    "iso:country":"US",
    "sg:address":"6 Elm St",
    "sg:city":"Delhi",
    "sg:classifiers":[
        {
            "category":"Building & Trades",
            "subcategory":"Construction",
            "type":"Services"
        }
    ],
    "sg:phone":"+1 607 746 8216",
    "sg:postcode":"13753",
    "sg:province":"NY",
    "sg:tags":[
        "painter"
    ],
    "wof:name":"Second Nature Painting",
    "wof:placetype":"venue"
},
  "geometry": {"coordinates":[-74.92147,42.272033],"type":"Point"}
}