{
  "type": "Feature",
  "properties": {
    "addr:full":"189 Schermerhorn St Brooklyn NY 11201",
    "addr:housenumber":"189",
    "addr:postcode":"11201",
    "addr:street":"Schermerhorn St",
    "iso:country":"US",
    "sg:address":"189 Schermerhorn St",
    "sg:city":"Brooklyn",
    "sg:classifiers":[
        {
            "category":"Real Estate",
            "subcategory":"Real Estate Operator",
            "type":"Services"
        }
    ],
    "sg:phone":"+1 718 246 0189",
    "sg:postcode":"11201",
    "sg:province":"NY",
    "sg:tags":[
        "apartment"
    ],
    "sg:website":"www.beatschermerhorn.com",
    "wof:name":"be@schermerhorn",
    "wof:placetype":"venue"
},
  "geometry": {"coordinates":[-73.987255,40.689746],"type":"Point"}
}