{
  "type": "Feature",
  "properties": {
    "iso:country":"US",
    "sg:address":"107 Water",
    "sg:city":"New York",
    "sg:classifiers":[
        {
            "category":"Building & Trades",
            "subcategory":"Locksmith",
            "type":"Services"
        }
    ],
    "sg:phone":"+1 646 822 6725",
    "sg:postcode":"10001",
    "sg:province":"NY",
    "sg:tags":[
        "key"
    ],
    "wof:name":"0 007 Lockl Service",
    "wof:placetype":"venue"
},
  "geometry": {"coordinates":[-74.736818,40.704734],"type":"Point"}
}