{
  "type": "Feature",
  "properties": {
    "addr:full":"1305 Travis Ave Staten Island NY 10314",
    "addr:housenumber":"1305",
    "addr:postcode":"10314",
    "addr:street":"Travis Ave",
    "iso:country":"US",
    "sg:address":"1305 Travis Ave",
    "sg:city":"Staten Island",
    "sg:classifiers":[
        {
            "category":"Retail",
            "subcategory":"Auto Repair",
            "type":"Services"
        }
    ],
    "sg:phone":"+1   ",
    "sg:postcode":"10314",
    "sg:province":"NY",
    "sg:tags":[
        "shop",
        "automotive"
    ],
    "wof:name":"Buyrite Muffler 2 Inc",
    "wof:placetype":"venue"
},
  "geometry": {"coordinates":[-74.183864,40.602613],"type":"Point"}
}