{
  "type": "Feature",
  "properties": {
    "addr:full":"601 W 26th St 12th Floor New York NY 10001",
    "addr:housenumber":"601;12th floor",
    "addr:postcode":"10001",
    "addr:street":"W 26Th St",
    "iso:country":"US",
    "sg:address":"601 W 26th St 12th Floor",
    "sg:city":"New York",
    "sg:classifiers":[
        {
            "category":"Arts & Performance",
            "subcategory":"Arts Center",
            "type":"Entertainment"
        },
        {
            "category":"Communications",
            "subcategory":"Film & Video Production",
            "type":"Services"
        }
    ],
    "sg:phone":"+1 212 367 7590",
    "sg:postcode":"10001",
    "sg:province":"NY",
    "sg:tags":[
        "performing",
        "video/film"
    ],
    "sg:website":"jackstudios.com",
    "wof:name":"Jack Studios Inc",
    "wof:placetype":"venue"
},
  "geometry": {"coordinates":[-74.00669600000001,40.751309],"type":"Point"}
}