{
  "type": "Feature",
  "properties": {
    "iso:country":"US",
    "sg:address":"271 Forest Ave",
    "sg:city":"Amsterdam",
    "sg:classifiers":[
        {
            "category":"Autos & Motor Vehicles",
            "subcategory":"Fuel & Gas Station",
            "type":"Retail Goods"
        }
    ],
    "sg:phone":"+1   ",
    "sg:postcode":"12010",
    "sg:province":"NY",
    "sg:tags":[
        "station",
        "gasoline"
    ],
    "wof:name":"Sftd Svce Centers",
    "wof:placetype":"venue"
},
  "geometry": {"coordinates":[-74.175697,42.948827],"type":"Point"}
}