{
  "type": "Feature",
  "properties": {
    "iso:country":"US",
    "sg:address":"53 Main St",
    "sg:city":"East Rockaway",
    "sg:classifiers":[
        {
            "category":"Education",
            "subcategory":"Special Training",
            "type":"Public Place"
        }
    ],
    "sg:phone":"+1 516 599 6693",
    "sg:postcode":"11518",
    "sg:province":"NY",
    "sg:tags":[
        "instrument",
        "instruction",
        "music",
        "teacher",
        "musical"
    ],
    "wof:name":"East Rockaway Music Center",
    "wof:placetype":"venue"
},
  "geometry": {"coordinates":[-73.662903,40.640301],"type":"Point"}
}