{
  "type": "Feature",
  "properties": {
    "addr:full":"1955 Central Park Ave Yonkers NY 10710",
    "addr:housenumber":"1955",
    "addr:postcode":"10710",
    "addr:street":"Central Park Ave",
    "iso:country":"US",
    "sg:address":"1955 Central Park Ave",
    "sg:city":"Yonkers",
    "sg:classifiers":[
        {
            "category":"Real Estate",
            "subcategory":"Real Estate Services",
            "type":"Services"
        },
        {
            "category":"Real Estate",
            "subcategory":"Real Estate Agent",
            "type":"Services"
        }
    ],
    "sg:phone":"+1 914 793 5000",
    "sg:postcode":"10710",
    "sg:province":"NY",
    "sg:tags":[
        "rental"
    ],
    "wof:name":"Century 21 Future Homes Realty",
    "wof:placetype":"venue"
},
  "geometry": {"coordinates":[-73.83901400000001,40.964586],"type":"Point"}
}