{
  "type": "Feature",
  "properties": {
    "addr:full":"398 N Wantagh Ave Bethpage NY 11714",
    "addr:housenumber":"398",
    "addr:postcode":"11714",
    "addr:street":"N Wantagh Ave",
    "iso:country":"US",
    "sg:address":"398 N Wantagh Ave",
    "sg:city":"Bethpage",
    "sg:classifiers":[
        {
            "category":"Restaurant",
            "type":"Food & Drink"
        }
    ],
    "sg:menulink":"http://www.allmenus.com/ny/levittown/243812-mei-wei-kitchen/menu/",
    "sg:phone":"+1 516 822 3926",
    "sg:postcode":"11714",
    "sg:province":"NY",
    "sg:tags":[
        "asian",
        "chinese"
    ],
    "wof:name":"Mei Wei Kitchen",
    "wof:placetype":"venue"
},
  "geometry": {"coordinates":[-73.495779,40.735675],"type":"Point"}
}