{
  "type": "Feature",
  "properties": {
    "iso:country":"US",
    "sg:address":"3385 Harlem Rd",
    "sg:city":"Buffalo",
    "sg:classifiers":[
        {
            "category":"Shopping",
            "subcategory":"Bicycles & Sporting Goods",
            "type":"Retail Goods"
        }
    ],
    "sg:phone":"+1 716 833 2581",
    "sg:postcode":"14225",
    "sg:province":"NY",
    "wof:name":"Gun Center Inc",
    "wof:placetype":"venue"
},
  "geometry": {"coordinates":[-78.784302,42.936001],"type":"Point"}
}