{
  "type": "Feature",
  "properties": {
    "addr:full":"201 E 42nd Street New York NY 10017",
    "addr:housenumber":"201",
    "addr:postcode":"10017",
    "addr:street":"E 42Nd Street",
    "iso:country":"US",
    "sg:address":"201 E 42nd Street",
    "sg:city":"New York",
    "sg:classifiers":[
        {
            "category":"Organizations",
            "subcategory":"Religious Organization",
            "type":"Services"
        }
    ],
    "sg:phone":"+1 212 986 1240",
    "sg:postcode":"10017",
    "sg:province":"NY",
    "wof:name":"Permanent Mission of Belize",
    "wof:placetype":"venue"
},
  "geometry": {"coordinates":[-73.974576,40.75085],"type":"Point"}
}