{
  "type": "Feature",
  "properties": {
    "addr:full":"402 E Tremont Ave Bronx NY 10457",
    "addr:housenumber":"402",
    "addr:postcode":"10457",
    "addr:street":"E Tremont Ave",
    "iso:country":"US",
    "sg:address":"402 E Tremont Ave",
    "sg:city":"Bronx",
    "sg:classifiers":[
        {
            "category":"Shopping",
            "subcategory":"Used Merchandise",
            "type":"Retail Goods"
        }
    ],
    "sg:phone":"+1   ",
    "sg:postcode":"10457",
    "sg:province":"NY",
    "wof:name":"Master Matches",
    "wof:placetype":"venue"
},
  "geometry": {"coordinates":[-73.89975099999999,40.847382],"type":"Point"}
}