{
  "type": "Feature",
  "properties": {
    "iso:country":"US",
    "sg:address":"592 5th Ave",
    "sg:city":"New York",
    "sg:classifiers":[
        {
            "category":"Professional",
            "subcategory":"Computer Services",
            "type":"Services"
        }
    ],
    "sg:phone":"+1 212 764 1032",
    "sg:postcode":"10036",
    "sg:province":"NY",
    "sg:tags":[
        "repair"
    ],
    "wof:name":"Adcomp Systems",
    "wof:placetype":"venue"
},
  "geometry": {"coordinates":[-73.97840600000001,40.757163],"type":"Point"}
}