{
  "type": "Feature",
  "properties": {
    "iso:country":"US",
    "sg:address":"16 Van Pelt Ln",
    "sg:city":"Moravia",
    "sg:classifiers":[
        {
            "category":"Personal",
            "subcategory":"Beauty Salon",
            "type":"Services"
        }
    ],
    "sg:phone":"+1   ",
    "sg:postcode":"13118",
    "sg:province":"NY",
    "sg:tags":[
        "shop"
    ],
    "wof:name":"New Creations Style Salon",
    "wof:placetype":"venue"
},
  "geometry": {"coordinates":[-76.422612,42.703166],"type":"Point"}
}