{
  "type": "Feature",
  "properties": {
    "addr:full":"7025 Mutton Hill Rd Auburn NY 13021",
    "addr:housenumber":"7025",
    "addr:postcode":"13021",
    "addr:street":"Mutton Hill Rd",
    "iso:country":"US",
    "sg:address":"7025 Mutton Hill Rd",
    "sg:city":"Auburn",
    "sg:classifiers":[
        {
            "category":"Utilities",
            "subcategory":"Refuse",
            "type":"Services"
        }
    ],
    "sg:phone":"+1 315 253 4797",
    "sg:postcode":"13021",
    "sg:province":"NY",
    "sg:tags":[
        "garbage",
        "collection"
    ],
    "wof:name":"Appleton Disposal",
    "wof:placetype":"venue"
},
  "geometry": {"coordinates":[-76.54405800000001,42.961738],"type":"Point"}
}