{
  "type": "Feature",
  "properties": {
    "addr:full":"181 7th Ave Brooklyn NY 11215",
    "addr:housenumber":"181",
    "addr:postcode":"11215",
    "addr:street":"7Th Ave",
    "iso:country":"US",
    "sg:address":"181 7th Ave",
    "sg:city":"Brooklyn",
    "sg:classifiers":[
        {
            "category":"Restaurant",
            "type":"Food & Drink"
        }
    ],
    "sg:phone":"+1   ",
    "sg:postcode":"11215",
    "sg:province":"NY",
    "sg:tags":[
        "pizzeria"
    ],
    "wof:name":"Piping Hot Pizza",
    "wof:placetype":"venue"
},
  "geometry": {"coordinates":[-73.977743,40.671474],"type":"Point"}
}