{
  "type": "Feature",
  "properties": {
    "addr:full":"710 State Hwy 22B Peru NY 12972",
    "addr:housenumber":"710",
    "addr:postcode":"12972",
    "addr:street":"State Hwy 22B",
    "iso:country":"US",
    "sg:address":"710 State Hwy 22B",
    "sg:city":"Peru",
    "sg:classifiers":[
        {
            "category":"Organizations",
            "subcategory":"Community Association",
            "type":"Services"
        }
    ],
    "sg:phone":"+1 518 643 2309",
    "sg:postcode":"12972",
    "sg:province":"NY",
    "sg:tags":[
        "military"
    ],
    "sg:website":"www.vfw.org",
    "wof:name":"Veterans Of Foreign Wars",
    "wof:placetype":"venue"
},
  "geometry": {"coordinates":[-73.54485099999999,44.613513],"type":"Point"}
}