{
  "type": "Feature",
  "properties": {
    "addr:full":"4714 Salt Works Rd Medina NY 14103",
    "addr:housenumber":"4714",
    "addr:postcode":"14103",
    "addr:street":"Salt Works Rd",
    "iso:country":"US",
    "sg:address":"4714 Salt Works Rd",
    "sg:city":"Medina",
    "sg:classifiers":[
        {
            "category":"Government",
            "subcategory":"Office",
            "type":"Public Place"
        }
    ],
    "sg:phone":"+1 585 798 8740",
    "sg:postcode":"14103",
    "sg:province":"NY",
    "sg:tags":[
        "federal",
        "program"
    ],
    "sg:website":"www.usda.gov",
    "wof:name":"US Agricultural Dept",
    "wof:placetype":"venue"
},
  "geometry": {"coordinates":[-78.433599,43.184833],"type":"Point"}
}