{
  "type": "Feature",
  "properties": {
    "iso:country":"US",
    "sg:address":"59 Main St",
    "sg:city":"Sayville",
    "sg:classifiers":[
        {
            "category":"Utilities",
            "subcategory":"Mobile Phone",
            "type":"Services"
        },
        {
            "category":"Coffee & Tea",
            "type":"Food & Drink"
        }
    ],
    "sg:phone":"+1 631 244 8983",
    "sg:postcode":"11782",
    "sg:province":"NY",
    "sg:tags":[
        "shop",
        "restaurant",
        "brewing",
        "espresso",
        "hotspot",
        "device",
        "wi-fi"
    ],
    "sg:website":"http://www.starbuckscoffee.com",
    "wof:name":"Starbucks Coffee",
    "wof:placetype":"venue"
},
  "geometry": {"coordinates":[-73.08330100000001,40.735526],"type":"Point"}
}