{
  "type": "Feature",
  "properties": {
    "addr:full":"179 Lexington Ave New York NY 10016",
    "addr:housenumber":"179",
    "addr:postcode":"10016",
    "addr:street":"Lexington Ave",
    "iso:country":"US",
    "sg:address":"179 Lexington Ave",
    "sg:city":"New York",
    "sg:classifiers":[
        {
            "category":"Home & Garden",
            "subcategory":"Furniture",
            "type":"Retail Goods"
        }
    ],
    "sg:phone":"+1   ",
    "sg:postcode":"10016",
    "sg:province":"NY",
    "sg:tags":[
        "store"
    ],
    "wof:name":"Insight",
    "wof:placetype":"venue"
},
  "geometry": {"coordinates":[-73.980659,40.745115],"type":"Point"}
}