{
  "type": "Feature",
  "properties": {
    "addr:full":"320 Webster Ave New Rochelle NY 10801",
    "addr:housenumber":"320",
    "addr:postcode":"10801",
    "addr:street":"Webster Ave",
    "iso:country":"US",
    "sg:address":"320 Webster Ave",
    "sg:city":"New Rochelle",
    "sg:classifiers":[
        {
            "category":"Retail",
            "subcategory":"Laundry & Dry Cleaning",
            "type":"Services"
        }
    ],
    "sg:phone":"+1   ",
    "sg:postcode":"10801",
    "sg:province":"NY",
    "sg:tags":[
        "drycleaning",
        "plant"
    ],
    "wof:name":"Pay and Save Cleaners",
    "wof:placetype":"venue"
},
  "geometry": {"coordinates":[-73.794635,40.91502],"type":"Point"}
}