{
  "type": "Feature",
  "properties": {
    "addr:full":"3402 Farragut Rd Brooklyn NY 11210",
    "addr:housenumber":"3402",
    "addr:postcode":"11210",
    "addr:street":"Farragut Rd",
    "iso:country":"US",
    "sg:address":"3402 Farragut Rd",
    "sg:city":"Brooklyn",
    "sg:classifiers":[
        {
            "category":"Real Estate",
            "subcategory":"Developer",
            "type":"Services"
        }
    ],
    "sg:phone":"+1 718 421 0735",
    "sg:postcode":"11210",
    "sg:province":"NY",
    "wof:name":"Tyler Development Inc",
    "wof:placetype":"venue"
},
  "geometry": {"coordinates":[-73.943229,40.636488],"type":"Point"}
}