{
  "type": "Feature",
  "properties": {
    "iso:country":"US",
    "sg:address":"251 Wyckoff Ave",
    "sg:city":"Brooklyn",
    "sg:classifiers":[
        {
            "category":"Shopping",
            "subcategory":"Department Store",
            "type":"Retail Goods"
        }
    ],
    "sg:phone":"+1 718 497 5127",
    "sg:postcode":"11237",
    "sg:province":"NY",
    "sg:tags":[
        "shop",
        "gift"
    ],
    "wof:name":"Justins Discounts 99",
    "wof:placetype":"venue"
},
  "geometry": {"coordinates":[-73.91440799999999,40.70137],"type":"Point"}
}