{
  "type": "Feature",
  "properties": {
    "iso:country":"US",
    "sg:address":"150 Price Pkwy",
    "sg:city":"Farmingdale",
    "sg:classifiers":[
        {
            "category":"Home & Garden",
            "subcategory":"Household Appliances",
            "type":"Retail Goods"
        }
    ],
    "sg:phone":"+1 516 843 4400",
    "sg:postcode":"11735",
    "sg:province":"NY",
    "wof:name":"Long Island Appliance Wholslrs",
    "wof:placetype":"venue"
},
  "geometry": {"coordinates":[-73.422742,40.742647],"type":"Point"}
}