{
  "type": "Feature",
  "properties": {
    "addr:full":"1809 51st St Brooklyn NY 11204",
    "addr:housenumber":"1809",
    "addr:postcode":"11204",
    "addr:street":"51St St",
    "iso:country":"US",
    "sg:address":"1809 51st St",
    "sg:city":"Brooklyn",
    "sg:classifiers":[
        {
            "category":"Organizations",
            "subcategory":"Religious Organization",
            "type":"Services"
        }
    ],
    "sg:phone":"+1 718 436 7893",
    "sg:postcode":"11204",
    "sg:province":"NY",
    "sg:tags":[
        "clergy"
    ],
    "wof:name":"Kalman Mendelsohn",
    "wof:placetype":"venue"
},
  "geometry": {"coordinates":[-73.981251,40.626732],"type":"Point"}
}