{
  "type": "Feature",
  "properties": {
    "addr:full":"113 Nanticoke Ave Endicott NY 13760",
    "addr:housenumber":"113",
    "addr:postcode":"13760",
    "addr:street":"Nanticoke Ave",
    "iso:country":"US",
    "sg:address":"113 Nanticoke Ave",
    "sg:city":"Endicott",
    "sg:classifiers":[
        {
            "category":"Restaurant",
            "type":"Food & Drink"
        }
    ],
    "sg:phone":"+1 607 754 2999",
    "sg:postcode":"13760",
    "sg:province":"NY",
    "wof:name":"Hurricane Rylie's Cafe",
    "wof:placetype":"venue"
},
  "geometry": {"coordinates":[-76.065231,42.095271],"type":"Point"}
}