{
  "type": "Feature",
  "properties": {
    "iso:country":"US",
    "sg:address":"4881 N Jefferson St",
    "sg:city":"Pulaski",
    "sg:classifiers":[
        {
            "category":"Shopping",
            "subcategory":"Clothing, Apparel, & Fashions",
            "type":"Retail Goods"
        }
    ],
    "sg:phone":"+1 315 298 4047",
    "sg:postcode":"13142",
    "sg:province":"NY",
    "sg:tags":[
        "shop",
        "bridal"
    ],
    "wof:name":"Garden Gate Bridals",
    "wof:placetype":"venue"
},
  "geometry": {"coordinates":[-76.127111,43.567763],"type":"Point"}
}