{
  "type": "Feature",
  "properties": {
    "addr:full":"687 Rowley Rd Victor NY 14564",
    "addr:housenumber":"687",
    "addr:postcode":"14564",
    "addr:street":"Rowley Rd",
    "iso:country":"US",
    "sg:address":"687 Rowley Rd",
    "sg:city":"Victor",
    "sg:classifiers":[
        {
            "category":"Retail",
            "subcategory":"Repair Shop",
            "type":"Services"
        }
    ],
    "sg:phone":"+1 585 924 5250",
    "sg:postcode":"14564",
    "sg:province":"NY",
    "sg:tags":[
        "machine"
    ],
    "sg:website":"http://www.pmdautomation.com",
    "wof:name":"Progressive Machine & Design",
    "wof:placetype":"venue"
},
  "geometry": {"coordinates":[-77.439584,43.005245],"type":"Point"}
}