{
  "type": "Feature",
  "properties": {
    "addr:full":"766 3 Ave New York NY 10017",
    "addr:housenumber":"766",
    "addr:postcode":"10017",
    "addr:street":"3 Ave",
    "iso:country":"US",
    "sg:address":"766 3 Ave",
    "sg:city":"New York",
    "sg:classifiers":[
        {
            "category":"Shopping",
            "subcategory":"Jewelry",
            "type":"Retail Goods"
        }
    ],
    "sg:phone":"+1   ",
    "sg:postcode":"10017",
    "sg:province":"NY",
    "wof:name":"Nancy Yoon Jewelry",
    "wof:placetype":"venue"
},
  "geometry": {"coordinates":[-73.974935,40.7501],"type":"Point"}
}