{
  "type": "Feature",
  "properties": {
    "addr:full":"475 W Main St Huntington NY 11743",
    "addr:housenumber":"475",
    "addr:postcode":"11743",
    "addr:street":"W Main St",
    "iso:country":"US",
    "sg:address":"475 W Main St",
    "sg:city":"Huntington",
    "sg:classifiers":[
        {
            "category":"Building & Trades",
            "subcategory":"Landscaping Services",
            "type":"Services"
        }
    ],
    "sg:phone":"+1 631 351 0184",
    "sg:postcode":"11743",
    "sg:province":"NY",
    "sg:tags":[
        "lawn",
        "designer",
        "consultant",
        "contractor",
        "maintenance",
        "landscape"
    ],
    "sg:website":"http://www.mainstreetnursery.com",
    "wof:name":"Sherwood Landscaping Inc",
    "wof:placetype":"venue"
},
  "geometry": {"coordinates":[-73.439888,40.871529],"type":"Point"}
}