{
  "type": "Feature",
  "properties": {
    "iso:country":"US",
    "sg:address":"351 87th Street",
    "sg:city":"Brooklyn",
    "sg:classifiers":[
        {
            "category":"Health Services",
            "subcategory":"Dentist",
            "type":"Services"
        }
    ],
    "sg:phone":"+1 718 238 2776",
    "sg:postcode":"11209",
    "sg:province":"NY",
    "wof:name":"Gounardes Steven DDS",
    "wof:placetype":"venue"
},
  "geometry": {"coordinates":[-74.02937,40.622376],"type":"Point"}
}