{
  "type": "Feature",
  "properties": {
    "addr:full":"570 Washington St New York NY 10014",
    "addr:housenumber":"570",
    "addr:postcode":"10014",
    "addr:street":"Washington St",
    "iso:country":"US",
    "sg:address":"570 Washington St",
    "sg:city":"New York",
    "sg:classifiers":[
        {
            "category":"Banks & Credit Unions",
            "subcategory":"Bank",
            "type":"Services"
        }
    ],
    "sg:phone":"+1 646 230 7399",
    "sg:postcode":"10014",
    "sg:province":"NY",
    "sg:tags":[
        "loan",
        "real estate"
    ],
    "wof:name":"Cendant Mortgage",
    "wof:placetype":"venue"
},
  "geometry": {"coordinates":[-74.00929600000001,40.729627],"type":"Point"}
}