{
  "type": "Feature",
  "properties": {
    "iso:country":"US",
    "sg:address":"689 E Main St",
    "sg:city":"Springville",
    "sg:classifiers":[
        {
            "category":"Deli",
            "type":"Food & Drink"
        },
        {
            "category":"Restaurant",
            "type":"Food & Drink"
        }
    ],
    "sg:phone":"+1 716 592 2567",
    "sg:postcode":"14141",
    "sg:province":"NY",
    "sg:tags":[
        "delicatessen",
        "pizza"
    ],
    "wof:name":"The Pitstop Pizza & Deli",
    "wof:placetype":"venue"
},
  "geometry": {"coordinates":[-78.641301,42.508291],"type":"Point"}
}