{
  "type": "Feature",
  "properties": {
    "addr:full":"31 South St Cattaraugus NY 14719",
    "addr:housenumber":"31",
    "addr:postcode":"14719",
    "addr:street":"South St",
    "iso:country":"US",
    "sg:address":"31 South St",
    "sg:city":"Cattaraugus",
    "sg:classifiers":[
        {
            "category":"Health Services",
            "subcategory":"Chiropractor",
            "type":"Services"
        }
    ],
    "sg:phone":"+1 716 257 5300",
    "sg:postcode":"14719",
    "sg:province":"NY",
    "wof:name":"Cattaraugus Chiropractic",
    "wof:placetype":"venue"
},
  "geometry": {"coordinates":[-78.86691500000001,42.328665],"type":"Point"}
}