{
  "type": "Feature",
  "properties": {
    "iso:country":"US",
    "sg:address":"6458 Bunting Rd",
    "sg:city":"Orchard Park",
    "sg:classifiers":[
        {
            "category":"Building & Trades",
            "subcategory":"Construction",
            "type":"Services"
        }
    ],
    "sg:phone":"+1 716 646 5352",
    "sg:postcode":"14127",
    "sg:province":"NY",
    "sg:tags":[
        "concrete",
        "contractor"
    ],
    "wof:name":"Accurate Concrete Leveling",
    "wof:placetype":"venue"
},
  "geometry": {"coordinates":[-78.777699,42.710556],"type":"Point"}
}