{
  "type": "Feature",
  "properties": {
    "addr:full":"6511 155th Street Flushing NY 11367",
    "addr:housenumber":"6511",
    "addr:postcode":"11367",
    "addr:street":"155Th Street",
    "iso:country":"US",
    "sg:address":"6511 155th Street",
    "sg:city":"Flushing",
    "sg:classifiers":[
        {
            "category":"Education",
            "subcategory":"School",
            "type":"Public Place"
        }
    ],
    "sg:phone":"+1 718 359 0620",
    "sg:postcode":"11367",
    "sg:province":"NY",
    "sg:tags":[
        "high",
        "middle",
        "elementary"
    ],
    "wof:name":"New York City Community School District 25 Region 3",
    "wof:placetype":"venue"
},
  "geometry": {"coordinates":[-73.813203,40.736795],"type":"Point"}
}