{
  "type": "Feature",
  "properties": {
    "addr:full":"100 Christopher St New York NY 10014",
    "addr:housenumber":"100",
    "addr:postcode":"10014",
    "addr:street":"Christopher St",
    "iso:country":"US",
    "sg:address":"100 Christopher St",
    "sg:city":"New York",
    "sg:classifiers":[
        {
            "category":"Personal",
            "type":"Services"
        }
    ],
    "sg:phone":"+1 212 993 8252",
    "sg:postcode":"10014",
    "sg:province":"NY",
    "sg:tags":[
        "towing"
    ],
    "wof:name":"West Side Towing Hotline",
    "wof:placetype":"venue"
},
  "geometry": {"coordinates":[-74.00460099999999,40.733501],"type":"Point"}
}