{
  "type": "Feature",
  "properties": {
    "iso:country":"US",
    "sg:address":"150 Merrick Rd",
    "sg:city":"Merrick",
    "sg:classifiers":[
        {
            "category":"Autos & Motor Vehicles",
            "subcategory":"Fuel & Gas Station",
            "type":"Retail Goods"
        }
    ],
    "sg:phone":"+1   ",
    "sg:postcode":"11566",
    "sg:province":"NY",
    "sg:tags":[
        "station"
    ],
    "wof:name":"Merrick Sunoco",
    "wof:placetype":"venue"
},
  "geometry": {"coordinates":[-73.542799,40.659613],"type":"Point"}
}