{
  "type": "Feature",
  "properties": {
    "iso:country":"US",
    "sg:address":"255 River St",
    "sg:city":"Troy",
    "sg:classifiers":[
        {
            "category":"Professional",
            "subcategory":"Research",
            "type":"Services"
        }
    ],
    "sg:phone":"+1 518 274 7474",
    "sg:postcode":"12180",
    "sg:province":"NY",
    "sg:tags":[
        "economic",
        "analysis"
    ],
    "wof:name":"Rensselaer Gateway Development",
    "wof:placetype":"venue"
},
  "geometry": {"coordinates":[-73.69164600000001,42.731706],"type":"Point"}
}