{
  "type": "Feature",
  "properties": {
    "iso:country":"US",
    "sg:address":"200 E 15 St",
    "sg:city":"New York",
    "sg:classifiers":[
        {
            "category":"Health Services",
            "subcategory":"Health Practitioner",
            "type":"Services"
        }
    ],
    "sg:phone":"+1 917 214 1272",
    "sg:postcode":"10003",
    "sg:province":"NY",
    "sg:tags":[
        "acupuncture"
    ],
    "wof:name":"Needle-Free Taoist Acupuncture",
    "wof:placetype":"venue"
},
  "geometry": {"coordinates":[-73.985242,40.733371],"type":"Point"}
}