{
  "type": "Feature",
  "properties": {
    "addr:full":"15 Dawning Ln Ossining NY 10562",
    "addr:housenumber":"15",
    "addr:postcode":"10562",
    "addr:street":"Dawning Ln",
    "iso:country":"US",
    "sg:address":"15 Dawning Ln",
    "sg:city":"Ossining",
    "sg:classifiers":[
        {
            "category":"Building & Trades",
            "subcategory":"Construction",
            "type":"Services"
        }
    ],
    "sg:phone":"+1 914 762 4972",
    "sg:postcode":"10562",
    "sg:province":"NY",
    "sg:tags":[
        "contractor",
        "painting",
        "hanging"
    ],
    "wof:name":"N B Painting & Decorating Corp",
    "wof:placetype":"venue"
},
  "geometry": {"coordinates":[-73.860181,41.197814],"type":"Point"}
}