{
  "type": "Feature",
  "properties": {
    "addr:full":"4363 Mapleton Rd Lockport NY 14094",
    "addr:housenumber":"4363",
    "addr:postcode":"14094",
    "addr:street":"Mapleton Rd",
    "iso:country":"US",
    "sg:address":"4363 Mapleton Rd",
    "sg:city":"Lockport",
    "sg:classifiers":[
        {
            "category":"Education",
            "subcategory":"School",
            "type":"Public Place"
        }
    ],
    "sg:phone":"+1 716 625 7272",
    "sg:postcode":"14094",
    "sg:province":"NY",
    "sg:tags":[
        "district"
    ],
    "wof:name":"Starpoint Central School Dst",
    "wof:placetype":"venue"
},
  "geometry": {"coordinates":[-78.822757,43.122478],"type":"Point"}
}