{
  "type": "Feature",
  "properties": {
    "iso:country":"US",
    "sg:address":"2337 Clinton Ave S",
    "sg:city":"Rochester",
    "sg:classifiers":[
        {
            "category":"Health Services",
            "subcategory":"Doctor",
            "type":"Services"
        }
    ],
    "sg:phone":"+1 585 341 7575",
    "sg:postcode":"14618",
    "sg:province":"NY",
    "sg:tags":[
        "physician",
        "surgeon"
    ],
    "wof:name":"Strong Sleep Disorders Ctr",
    "wof:placetype":"venue"
},
  "geometry": {"coordinates":[-77.597621,43.112417],"type":"Point"}
}