{
  "type": "Feature",
  "properties": {
    "iso:country":"US",
    "sg:address":"7120 Lane Rd",
    "sg:city":"Victor",
    "sg:classifiers":[
        {
            "category":"Health Services",
            "subcategory":"Doctor",
            "type":"Services"
        }
    ],
    "sg:phone":"+1 585 924 5500",
    "sg:postcode":"14564",
    "sg:province":"NY",
    "sg:tags":[
        "physician",
        "surgeon"
    ],
    "wof:name":"Rick Holton MD",
    "wof:placetype":"venue"
},
  "geometry": {"coordinates":[-77.420292,42.998006],"type":"Point"}
}