{
  "type": "Feature",
  "properties": {
    "addr:full":"180 Canal View Blvd Rochester NY 14623",
    "addr:housenumber":"180",
    "addr:postcode":"14623",
    "addr:street":"Canal View Blvd",
    "iso:country":"US",
    "sg:address":"180 Canal View Blvd",
    "sg:city":"Rochester",
    "sg:classifiers":[
        {
            "category":"Professional",
            "subcategory":"Accounting & Tax Preparation",
            "type":"Services"
        }
    ],
    "sg:phone":"+1   ",
    "sg:postcode":"14623",
    "sg:province":"NY",
    "sg:tags":[
        "corporate",
        "details",
        "certified"
    ],
    "wof:name":"Antionette S Lamb",
    "wof:placetype":"venue"
},
  "geometry": {"coordinates":[-77.58699799999999,43.099327],"type":"Point"}
}