{
  "type": "Feature",
  "properties": {
    "addr:full":"315 4th Ave Brooklyn NY 11215",
    "addr:housenumber":"315",
    "addr:postcode":"11215",
    "addr:street":"4Th Ave",
    "iso:country":"US",
    "sg:address":"315 4th Ave",
    "sg:city":"Brooklyn",
    "sg:classifiers":[
        {
            "category":"Arts & Performance",
            "subcategory":"Art Gallery",
            "type":"Entertainment"
        },
        {
            "category":"Coffee & Tea",
            "type":"Food & Drink"
        }
    ],
    "sg:phone":"+1 718 832 4870",
    "sg:postcode":"11215",
    "sg:province":"NY",
    "sg:website":"zoraspace.com/",
    "wof:name":"Zora Space",
    "wof:placetype":"venue"
},
  "geometry": {"coordinates":[-73.985169,40.674067],"type":"Point"}
}