{
  "type": "Feature",
  "properties": {
    "addr:full":"7705 Toad Hollow Rd Little Valley NY 14755",
    "addr:housenumber":"7705",
    "addr:postcode":"14755",
    "addr:street":"Toad Hollow Rd",
    "iso:country":"US",
    "sg:address":"7705 Toad Hollow Rd",
    "sg:city":"Little Valley",
    "sg:classifiers":[
        {
            "category":"Organizations",
            "subcategory":"Religious Organization",
            "type":"Services"
        }
    ],
    "sg:phone":"+1 716 257 3703",
    "sg:postcode":"14755",
    "sg:province":"NY",
    "sg:tags":[
        "clergy"
    ],
    "wof:name":"Community Church Of Eddyville",
    "wof:placetype":"venue"
},
  "geometry": {"coordinates":[-78.762395,42.330765],"type":"Point"}
}