{
  "type": "Feature",
  "properties": {
    "addr:full":"239 Waring Rd Syracuse NY 13078",
    "addr:housenumber":"239",
    "addr:postcode":"13078",
    "addr:street":"Waring Rd",
    "iso:country":"US",
    "sg:address":"239 Waring Rd",
    "sg:city":"Syracuse",
    "sg:classifiers":[
        {
            "category":"Social Services",
            "type":"Services"
        }
    ],
    "sg:phone":"+1 315 682 9008",
    "sg:postcode":"13078",
    "sg:province":"NY",
    "sg:tags":[
        "counselor",
        "marriage",
        "family"
    ],
    "wof:name":"Center For Family Stress & Lls",
    "wof:placetype":"venue"
},
  "geometry": {"coordinates":[-76.101536,43.020112],"type":"Point"}
}