{
  "type": "Feature",
  "properties": {
    "addr:full":"246 S Kingsboro Ave Gloversville NY 12078",
    "addr:housenumber":"246",
    "addr:postcode":"12078",
    "addr:street":"S Kingsboro Ave",
    "iso:country":"US",
    "sg:address":"246 S Kingsboro Ave",
    "sg:city":"Gloversville",
    "sg:classifiers":[
        {
            "category":"Personal",
            "subcategory":"Beauty Salon",
            "type":"Services"
        }
    ],
    "sg:phone":"+1 518 725 1115",
    "sg:postcode":"12078",
    "sg:province":"NY",
    "wof:name":"Renditions Hair Designs",
    "wof:placetype":"venue"
},
  "geometry": {"coordinates":[-74.344397,43.036334],"type":"Point"}
}