{
  "type": "Feature",
  "properties": {
    "addr:full":"3836 State Hwy 205 Hartwick NY 13348",
    "addr:housenumber":"3836",
    "addr:postcode":"13348",
    "addr:street":"State Hwy 205 Hartwick",
    "iso:country":"US",
    "sg:address":"3836 State Hwy 205",
    "sg:city":"Hartwick",
    "sg:classifiers":[
        {
            "category":"Retail",
            "subcategory":"Auto Repair",
            "type":"Services"
        }
    ],
    "sg:phone":"+1 607 293 7395",
    "sg:postcode":"13348",
    "sg:province":"NY",
    "sg:tags":[
        "repairing",
        "automobile"
    ],
    "wof:name":"West Transportation",
    "wof:placetype":"venue"
},
  "geometry": {"coordinates":[-75.05432500000001,42.685854],"type":"Point"}
}