{
  "type": "Feature",
  "properties": {
    "addr:full":"2066 Wallace Ave Bronx NY 10462",
    "addr:housenumber":"2066",
    "addr:postcode":"10462",
    "addr:street":"Wallace Ave",
    "iso:country":"US",
    "sg:address":"2066 Wallace Ave",
    "sg:city":"Bronx",
    "sg:classifiers":[
        {
            "category":"Building & Trades",
            "subcategory":"Construction",
            "type":"Services"
        }
    ],
    "sg:phone":"+1 718 763 7717",
    "sg:postcode":"10462",
    "sg:province":"NY",
    "sg:tags":[
        "general",
        "contractor"
    ],
    "wof:name":"Grace Contracting of NY Inc",
    "wof:placetype":"venue"
},
  "geometry": {"coordinates":[-73.864893,40.851531],"type":"Point"}
}