{
  "type": "Feature",
  "properties": {
    "iso:country":"US",
    "sg:address":"730 Rte 112",
    "sg:city":"Patchogue",
    "sg:classifiers":[
        {
            "category":"Autos & Motor Vehicles",
            "subcategory":"Automobile Sales",
            "type":"Retail Goods"
        }
    ],
    "sg:phone":"+1   ",
    "sg:postcode":"11772",
    "sg:province":"NY",
    "sg:tags":[
        "new"
    ],
    "wof:name":"Nissan 112",
    "wof:placetype":"venue"
},
  "geometry": {"coordinates":[-73.007481,40.793013],"type":"Point"}
}