{
  "type": "Feature",
  "properties": {
    "iso:country":"US",
    "sg:address":"1112 Park Ave",
    "sg:city":"New York",
    "sg:classifiers":[
        {
            "category":"Farming",
            "subcategory":"Farm",
            "type":"Manufacturing & Wholesale Goods"
        }
    ],
    "sg:phone":"+1 212 722 6347",
    "sg:postcode":"10128",
    "sg:province":"NY",
    "sg:tags":[
        "crop",
        "general"
    ],
    "wof:name":"Timothy Eland",
    "wof:placetype":"venue"
},
  "geometry": {"coordinates":[-73.955679,40.782271],"type":"Point"}
}