{
  "type": "Feature",
  "properties": {
    "addr:full":"60 Pine Cliff Rd Chappaqua NY 10514",
    "addr:housenumber":"60",
    "addr:postcode":"10514",
    "addr:street":"Pine Cliff Rd",
    "iso:country":"US",
    "sg:address":"60 Pine Cliff Rd",
    "sg:city":"Chappaqua",
    "sg:classifiers":[
        {
            "category":"Communications",
            "subcategory":"Film & Video Production",
            "type":"Services"
        }
    ],
    "sg:phone":"+1   ",
    "sg:postcode":"10514",
    "sg:province":"NY",
    "sg:tags":[
        "motion"
    ],
    "sg:website":"www.mediadynamicsnewyork.com",
    "wof:name":"Media Dynamics",
    "wof:placetype":"venue"
},
  "geometry": {"coordinates":[-73.77626600000001,41.166058],"type":"Point"}
}