{
  "type": "Feature",
  "properties": {
    "iso:country":"US",
    "sg:address":"260 Broadway St",
    "sg:city":"Fort Edward",
    "sg:classifiers":[
        {
            "category":"Building & Trades",
            "subcategory":"Construction",
            "type":"Services"
        }
    ],
    "sg:phone":"+1 518 747 6981",
    "sg:postcode":"12828",
    "sg:province":"NY",
    "sg:tags":[
        "roofing",
        "siding",
        "work",
        "window",
        "contractor"
    ],
    "wof:name":"Roof Masters",
    "wof:placetype":"venue"
},
  "geometry": {"coordinates":[-73.586412,43.274874],"type":"Point"}
}