{
  "type": "Feature",
  "properties": {
    "addr:full":"35 Beadel St Brooklyn NY 11222",
    "addr:housenumber":"35",
    "addr:postcode":"11222",
    "addr:street":"Beadel St",
    "iso:country":"US",
    "sg:address":"35 Beadel St",
    "sg:city":"Brooklyn",
    "sg:classifiers":[
        {
            "category":"Professional",
            "type":"Services"
        }
    ],
    "sg:phone":"+1   ",
    "sg:postcode":"11222",
    "sg:province":"NY",
    "wof:name":"Lombardy Corp",
    "wof:placetype":"venue"
},
  "geometry": {"coordinates":[-73.93909600000001,40.721356],"type":"Point"}
}