{
  "type": "Feature",
  "properties": {
    "iso:country":"US",
    "sg:address":"74 Trinity Pl Fl 11",
    "sg:city":"New York",
    "sg:classifiers":[
        {
            "category":"Professional",
            "subcategory":"Lawyer & Legal Services",
            "type":"Services"
        }
    ],
    "sg:phone":"+1 212 577 2523",
    "sg:postcode":"10006",
    "sg:province":"NY",
    "wof:name":"Center For Appellate Litigation",
    "wof:placetype":"venue"
},
  "geometry": {"coordinates":[-74.01291399999999,40.708317],"type":"Point"}
}