{
  "type": "Feature",
  "properties": {
    "iso:country":"US",
    "sg:address":"1239 Broadway",
    "sg:city":"New York",
    "sg:classifiers":[
        {
            "category":"Shopping",
            "type":"Retail Goods"
        }
    ],
    "sg:phone":"+1   ",
    "sg:postcode":"10001",
    "sg:province":"NY",
    "sg:tags":[
        "merchandise"
    ],
    "wof:name":"Song Choe",
    "wof:placetype":"venue"
},
  "geometry": {"coordinates":[-73.988429,40.747215],"type":"Point"}
}