{
  "type": "Feature",
  "properties": {
    "addr:full":"1448 Kemble St Utica NY 13501",
    "addr:housenumber":"1448",
    "addr:postcode":"13501",
    "addr:street":"Kemble St",
    "iso:country":"US",
    "sg:address":"1448 Kemble St",
    "sg:city":"Utica",
    "sg:classifiers":[
        {
            "category":"Building & Trades",
            "subcategory":"Construction",
            "type":"Services"
        }
    ],
    "sg:phone":"+1 315 793 0532",
    "sg:postcode":"13501",
    "sg:province":"NY",
    "sg:tags":[
        "concrete",
        "contractor"
    ],
    "wof:name":"Precision Plster Pnt Contg LLC",
    "wof:placetype":"venue"
},
  "geometry": {"coordinates":[-75.24304100000001,43.092651],"type":"Point"}
}