{
  "type": "Feature",
  "properties": {
    "addr:full":"1762 Chaladay Ln East Meadow NY 11554",
    "addr:housenumber":"1762",
    "addr:postcode":"11554",
    "addr:street":"Chaladay Ln",
    "iso:country":"US",
    "sg:address":"1762 Chaladay Ln",
    "sg:city":"East Meadow",
    "sg:classifiers":[
        {
            "category":"Personal",
            "type":"Services"
        }
    ],
    "sg:phone":"+1 516 485 8600",
    "sg:postcode":"11554",
    "sg:province":"NY",
    "sg:tags":[
        "mover"
    ],
    "wof:name":"A Network Moving Corp",
    "wof:placetype":"venue"
},
  "geometry": {"coordinates":[-73.55999799999999,40.701599],"type":"Point"}
}