{
  "type": "Feature",
  "properties": {
    "addr:full":"290 Broadway New Hyde Park NY 11040",
    "addr:housenumber":"290",
    "addr:postcode":"11040",
    "addr:street":"Broadway",
    "iso:country":"US",
    "sg:address":"290 Broadway",
    "sg:city":"New Hyde Park",
    "sg:classifiers":[
        {
            "category":"Retail",
            "subcategory":"Auto Repair",
            "type":"Services"
        }
    ],
    "sg:phone":"+1 516 742 5961",
    "sg:postcode":"11040",
    "sg:province":"NY",
    "sg:tags":[
        "body",
        "shop",
        "painting",
        "automobile"
    ],
    "wof:name":"Kidd Collision",
    "wof:placetype":"venue"
},
  "geometry": {"coordinates":[-73.653999,40.738998],"type":"Point"}
}