{
  "type": "Feature",
  "properties": {
    "iso:country":"US",
    "sg:address":"1507 42nd St",
    "sg:city":"Brooklyn",
    "sg:classifiers":[
        {
            "category":"Organizations",
            "subcategory":"Religious Organization",
            "type":"Services"
        }
    ],
    "sg:phone":"+1 718 871 1036",
    "sg:postcode":"11219",
    "sg:province":"NY",
    "sg:tags":[
        "clergy"
    ],
    "wof:name":"Jacob Zitronenbaum",
    "wof:placetype":"venue"
},
  "geometry": {"coordinates":[-73.981488,40.635095],"type":"Point"}
}