{
  "type": "Feature",
  "properties": {
    "addr:full":"10206 Atlantic Ave Ozone Park NY 11416",
    "addr:housenumber":"10206",
    "addr:postcode":"11416",
    "addr:street":"Atlantic Ave",
    "iso:country":"US",
    "sg:address":"10206 Atlantic Ave",
    "sg:city":"Ozone Park",
    "sg:classifiers":[
        {
            "category":"Ice Cream",
            "type":"Food & Drink"
        }
    ],
    "sg:menulink":"http://www.allmenus.com/ny/queens/243559-baskin-robbins/menu/",
    "sg:phone":"+1 718 847 3107",
    "sg:postcode":"11416",
    "sg:province":"NY",
    "sg:tags":[
        "american"
    ],
    "wof:name":"Baskin-Robbins",
    "wof:placetype":"venue"
},
  "geometry": {"coordinates":[-73.84271200000001,40.689809],"type":"Point"}
}