{
  "type": "Feature",
  "properties": {
    "iso:country":"US",
    "sg:address":"163 Nichols Ave",
    "sg:city":"Brooklyn",
    "sg:classifiers":[
        {
            "category":"Retail",
            "subcategory":"Repair Shop",
            "type":"Services"
        }
    ],
    "sg:phone":"+1 718 964 0404",
    "sg:postcode":"11208",
    "sg:province":"NY",
    "sg:tags":[
        "related"
    ],
    "wof:name":"Caribs Cargo Express",
    "wof:placetype":"venue"
},
  "geometry": {"coordinates":[-73.869288,40.687786],"type":"Point"}
}