{
  "type": "Feature",
  "properties": {
    "addr:full":"777 Sunrise Hwy Lynbrook NY 11563",
    "addr:housenumber":"777",
    "addr:postcode":"11563",
    "addr:street":"Sunrise Hwy",
    "iso:country":"US",
    "sg:address":"777 Sunrise Hwy",
    "sg:city":"Lynbrook",
    "sg:classifiers":[
        {
            "category":"Professional",
            "subcategory":"Advertising",
            "type":"Services"
        }
    ],
    "sg:phone":"+1 516 593 8787",
    "sg:postcode":"11563",
    "sg:province":"NY",
    "sg:tags":[
        "mail"
    ],
    "sg:website":"www.studentmarketing.net",
    "wof:name":"Rhina International Direct",
    "wof:placetype":"venue"
},
  "geometry": {"coordinates":[-73.681031,40.656408],"type":"Point"}
}