{
  "type": "Feature",
  "properties": {
    "addr:full":"125 Kings Hwy Brooklyn NY 11223",
    "addr:housenumber":"125",
    "addr:postcode":"11223",
    "addr:street":"Kings Hwy",
    "iso:country":"US",
    "sg:address":"125 Kings Hwy",
    "sg:city":"Brooklyn",
    "sg:classifiers":[
        {
            "category":"Autos & Motor Vehicles",
            "subcategory":"Fuel & Gas Station",
            "type":"Retail Goods"
        }
    ],
    "sg:phone":"+1 718 234 9752",
    "sg:postcode":"11223",
    "sg:province":"NY",
    "sg:tags":[
        "oil"
    ],
    "wof:name":"Auto Wiz Inc",
    "wof:placetype":"venue"
},
  "geometry": {"coordinates":[-73.986603,40.606098],"type":"Point"}
}