{
  "type": "Feature",
  "properties": {
    "addr:full":"310 Forest Dr Syracuse NY 13212",
    "addr:housenumber":"310",
    "addr:postcode":"13212",
    "addr:street":"Forest Dr",
    "iso:country":"US",
    "sg:address":"310 Forest Dr",
    "sg:city":"Syracuse",
    "sg:classifiers":[
        {
            "category":"Professional",
            "subcategory":"Lawyer & Legal Services",
            "type":"Services"
        }
    ],
    "sg:phone":"+1   ",
    "sg:postcode":"13212",
    "sg:province":"NY",
    "wof:name":"Upstate Affidavit & Process",
    "wof:placetype":"venue"
},
  "geometry": {"coordinates":[-76.111846,43.133076],"type":"Point"}
}