{
  "type": "Feature",
  "properties": {
    "addr:full":"9th Ave New York NY 10011",
    "addr:postcode":"10011",
    "addr:street":"9Th Ave",
    "iso:country":"US",
    "sg:address":"9th Ave",
    "sg:city":"New York",
    "sg:classifiers":[
        {
            "category":"Professional",
            "subcategory":"Art Services",
            "type":"Services"
        }
    ],
    "sg:phone":"+1 646 554 3774",
    "sg:postcode":"10011",
    "sg:province":"NY",
    "sg:tags":[
        "photographer"
    ],
    "wof:name":"Michael Creagh Photography",
    "wof:placetype":"venue"
},
  "geometry": {"coordinates":[-74.003108,40.744025],"type":"Point"}
}