{
  "type": "Feature",
  "properties": {
    "iso:country":"US",
    "sg:address":"1441 Old Rte 22",
    "sg:city":"Brewster",
    "sg:classifiers":[
        {
            "category":"Professional",
            "subcategory":"Lawyer & Legal Services",
            "type":"Services"
        }
    ],
    "sg:phone":"+1 845 279 4226",
    "sg:postcode":"10509",
    "sg:province":"NY",
    "wof:name":"Stevens & Charbonneau",
    "wof:placetype":"venue"
},
  "geometry": {"coordinates":[-73.58202,41.461121],"type":"Point"}
}