{
  "type": "Feature",
  "properties": {
    "iso:country":"US",
    "sg:address":"12233 Torrence Rd",
    "sg:city":"Randolph",
    "sg:classifiers":[
        {
            "category":"Real Estate",
            "subcategory":"Real Estate Operator",
            "type":"Services"
        }
    ],
    "sg:phone":"+1 716 358 6086",
    "sg:postcode":"14772",
    "sg:province":"NY",
    "sg:tags":[
        "property",
        "lessor"
    ],
    "wof:name":"Eccles Farm",
    "wof:placetype":"venue"
},
  "geometry": {"coordinates":[-79.01517,42.148612],"type":"Point"}
}