{
  "type": "Feature",
  "properties": {
    "iso:country":"US",
    "sg:address":"300 Garden City Plz Ste 136",
    "sg:city":"Garden City",
    "sg:classifiers":[
        {
            "category":"Health Services",
            "subcategory":"Doctor",
            "type":"Services"
        }
    ],
    "sg:phone":"+1 516 663 6400",
    "sg:postcode":"11530",
    "sg:province":"NY",
    "wof:name":"Terrani Michael MD PC",
    "wof:placetype":"venue"
},
  "geometry": {"coordinates":[-73.611921,40.735249],"type":"Point"}
}