{
  "type": "Feature",
  "properties": {
    "iso:country":"US",
    "sg:address":"221 E Main St",
    "sg:city":"Riverhead",
    "sg:classifiers":[
        {
            "category":"Shopping",
            "subcategory":"Stationery & Office Supplies",
            "type":"Retail Goods"
        }
    ],
    "sg:phone":"+1 800 339 4310",
    "sg:postcode":"11901",
    "sg:province":"NY",
    "sg:tags":[
        "equipment"
    ],
    "wof:name":"Mccabes Office Products",
    "wof:placetype":"venue"
},
  "geometry": {"coordinates":[-72.659205,40.917614],"type":"Point"}
}