{
  "type": "Feature",
  "properties": {
    "addr:full":"3172 Middle Country Rd Lake Grove NY 11755",
    "addr:housenumber":"3172",
    "addr:postcode":"11755",
    "addr:street":"Middle Country Rd",
    "iso:country":"US",
    "sg:address":"3172 Middle Country Rd",
    "sg:city":"Lake Grove",
    "sg:classifiers":[
        {
            "category":"Home & Garden",
            "subcategory":"Furniture",
            "type":"Retail Goods"
        }
    ],
    "sg:phone":"+1 631 656 8551",
    "sg:postcode":"11755",
    "sg:province":"NY",
    "sg:tags":[
        "store"
    ],
    "wof:name":"Home Elegance",
    "wof:placetype":"venue"
},
  "geometry": {"coordinates":[-73.124359,40.861607],"type":"Point"}
}