{
  "type": "Feature",
  "properties": {
    "iso:country":"US",
    "sg:address":"115 Chestnut St",
    "sg:city":"Oneonta",
    "sg:classifiers":[
        {
            "category":"Retail",
            "subcategory":"Repair Shop",
            "type":"Services"
        }
    ],
    "sg:phone":"+1 607 432 6734",
    "sg:postcode":"13820",
    "sg:province":"NY",
    "sg:tags":[
        "lock",
        "locksmith"
    ],
    "wof:name":"Gallusser Locksmithing",
    "wof:placetype":"venue"
},
  "geometry": {"coordinates":[-75.069374,42.454638],"type":"Point"}
}