{
  "type": "Feature",
  "properties": {
    "addr:full":"20 Mill St Newburgh NY 12550",
    "addr:housenumber":"20",
    "addr:postcode":"12550",
    "addr:street":"Mill St",
    "iso:country":"US",
    "sg:address":"20 Mill St",
    "sg:city":"Newburgh",
    "sg:classifiers":[
        {
            "category":"Organizations",
            "subcategory":"Religious Organization",
            "type":"Services"
        }
    ],
    "sg:phone":"+1 845 562 0191",
    "sg:postcode":"12550",
    "sg:province":"NY",
    "sg:tags":[
        "church"
    ],
    "wof:name":"New Hope Baptist Church",
    "wof:placetype":"venue"
},
  "geometry": {"coordinates":[-74.019733,41.498965],"type":"Point"}
}