{
  "type": "Feature",
  "properties": {
    "addr:full":"530 Willis Ave Bronx NY 10455",
    "addr:housenumber":"530",
    "addr:postcode":"10455",
    "addr:street":"Willis Ave",
    "iso:country":"US",
    "sg:address":"530 Willis Ave",
    "sg:city":"Bronx",
    "sg:classifiers":[
        {
            "category":"Professional",
            "subcategory":"Business Services",
            "type":"Services"
        }
    ],
    "sg:phone":"+1 718 993 2141",
    "sg:postcode":"10455",
    "sg:province":"NY",
    "wof:name":"Fordham Phone Cards",
    "wof:placetype":"venue"
},
  "geometry": {"coordinates":[-73.918038,40.815472],"type":"Point"}
}