{
  "type": "Feature",
  "properties": {
    "iso:country":"US",
    "sg:address":"266 Main St",
    "sg:city":"Huntington",
    "sg:classifiers":[
        {
            "category":"Personal",
            "subcategory":"Beauty Salon",
            "type":"Services"
        }
    ],
    "sg:phone":"+1 631 351 1555",
    "sg:postcode":"11743",
    "sg:province":"NY",
    "sg:tags":[
        "shop"
    ],
    "wof:name":"Adriana Spa",
    "wof:placetype":"venue"
},
  "geometry": {"coordinates":[-73.42558699999999,40.871239],"type":"Point"}
}