{
  "type": "Feature",
  "properties": {
    "addr:full":"45 Case Ave Patchogue NY 11772",
    "addr:housenumber":"45",
    "addr:postcode":"11772",
    "addr:street":"Case Ave",
    "iso:country":"US",
    "sg:address":"45 Case Ave",
    "sg:city":"Patchogue",
    "sg:classifiers":[
        {
            "category":"Autos & Motor Vehicles",
            "subcategory":"Fuel & Gas Station",
            "type":"Retail Goods"
        }
    ],
    "sg:phone":"+1   ",
    "sg:postcode":"11772",
    "sg:province":"NY",
    "sg:tags":[
        "shop",
        "station",
        "mechanic"
    ],
    "wof:name":"M & C Petroleum Inc",
    "wof:placetype":"venue"
},
  "geometry": {"coordinates":[-73.002894,40.766387],"type":"Point"}
}