{
  "type": "Feature",
  "properties": {
    "addr:full":"109 W 24th Street New York NY 10011",
    "addr:housenumber":"109",
    "addr:postcode":"10011",
    "addr:street":"W 24Th Street",
    "iso:country":"US",
    "sg:address":"109 W 24th Street",
    "sg:city":"New York",
    "sg:classifiers":[
        {
            "category":"Home & Garden",
            "subcategory":"Carpets & Floor Coverings",
            "type":"Retail Goods"
        }
    ],
    "sg:phone":"+1 212 691 2400",
    "sg:postcode":"10011",
    "sg:province":"NY",
    "sg:tags":[
        "flooring"
    ],
    "wof:name":"Montauk Rug & Carpet",
    "wof:placetype":"venue"
},
  "geometry": {"coordinates":[-73.992622,40.743561],"type":"Point"}
}