{
  "type": "Feature",
  "properties": {
    "iso:country":"US",
    "sg:address":"454 S Main St",
    "sg:city":"Syracuse",
    "sg:classifiers":[
        {
            "category":"Food & Beverages",
            "subcategory":"Meat & Fish",
            "type":"Retail Goods"
        }
    ],
    "sg:phone":"+1 315 458 5251",
    "sg:postcode":"13212",
    "sg:province":"NY",
    "wof:name":"Fish Cove",
    "wof:placetype":"venue"
},
  "geometry": {"coordinates":[-76.13542200000001,43.128085],"type":"Point"}
}