{
  "type": "Feature",
  "properties": {
    "iso:country":"US",
    "sg:address":"196 Moffitt Blvd",
    "sg:city":"Islip",
    "sg:classifiers":[
        {
            "category":"Shopping",
            "subcategory":"Tobacco",
            "type":"Retail Goods"
        }
    ],
    "sg:phone":"+1 631 376 1616",
    "sg:postcode":"11751",
    "sg:province":"NY",
    "sg:tags":[
        "cigarette",
        "cigar",
        "dealer"
    ],
    "wof:name":"East End Cigars Co",
    "wof:placetype":"venue"
},
  "geometry": {"coordinates":[-73.21778999999999,40.734726],"type":"Point"}
}