{
  "type": "Feature",
  "properties": {
    "iso:country":"US",
    "sg:address":"230 W 38th St",
    "sg:city":"New York",
    "sg:classifiers":[
        {
            "category":"Shopping",
            "subcategory":"Luggage & Leather Goods",
            "type":"Retail Goods"
        }
    ],
    "sg:phone":"+1 212 398 4158",
    "sg:postcode":"10018",
    "sg:province":"NY",
    "wof:name":"B & L High Fashion",
    "wof:placetype":"venue"
},
  "geometry": {"coordinates":[-73.99100900000001,40.754276],"type":"Point"}
}