{
  "type": "Feature",
  "properties": {
    "addr:full":"34 Monarch Dr Newburgh NY 12550",
    "addr:housenumber":"34",
    "addr:postcode":"12550",
    "addr:street":"Monarch Dr",
    "iso:country":"US",
    "sg:address":"34 Monarch Dr",
    "sg:city":"Newburgh",
    "sg:classifiers":[
        {
            "category":"Wholesale",
            "subcategory":"Office Equipment",
            "type":"Manufacturing & Wholesale Goods"
        }
    ],
    "sg:phone":"+1 845 564 1028",
    "sg:postcode":"12550",
    "sg:province":"NY",
    "wof:name":"Robert Galati",
    "wof:placetype":"venue"
},
  "geometry": {"coordinates":[-74.09704000000001,41.532675],"type":"Point"}
}