{
  "type": "Feature",
  "properties": {
    "addr:full":"38 Birch Hill Dr Poughkeepsie NY 12603",
    "addr:housenumber":"38",
    "addr:postcode":"12603",
    "addr:street":"Birch Hill Dr",
    "iso:country":"US",
    "sg:address":"38 Birch Hill Dr",
    "sg:city":"Poughkeepsie",
    "sg:classifiers":[
        {
            "category":"Farming",
            "subcategory":"Farm & Veterinary Services",
            "type":"Manufacturing & Wholesale Goods"
        }
    ],
    "sg:phone":"+1 845 452 2540",
    "sg:postcode":"12603",
    "sg:province":"NY",
    "sg:tags":[
        "tree",
        "harvesting"
    ],
    "wof:name":"Teds Trees",
    "wof:placetype":"venue"
},
  "geometry": {"coordinates":[-73.846271,41.698835],"type":"Point"}
}