{
  "type": "Feature",
  "properties": {
    "addr:full":"715 Ninth Avenue New York NY 10019",
    "addr:housenumber":"715",
    "addr:postcode":"10019",
    "addr:street":"Ninth Avenue",
    "iso:country":"US",
    "sg:address":"715 Ninth Avenue",
    "sg:city":"New York",
    "sg:classifiers":[
        {
            "category":"Shopping",
            "subcategory":"Baby Store",
            "type":"Retail Goods"
        },
        {
            "category":"Education",
            "subcategory":"Special Training",
            "type":"Public Place"
        }
    ],
    "sg:phone":"+1 212 245 0796",
    "sg:postcode":"10019",
    "sg:province":"NY",
    "sg:tags":[
        "school",
        "furniture",
        "gear",
        "specialty"
    ],
    "sg:website":"www.realbirth.com",
    "wof:name":"Realbirth",
    "wof:placetype":"venue"
},
  "geometry": {"coordinates":[-73.989901,40.762789],"type":"Point"}
}