{
  "type": "Feature",
  "properties": {
    "addr:full":"290 Hallock St Jamestown NY 14701",
    "addr:housenumber":"290",
    "addr:postcode":"14701",
    "addr:street":"Hallock St",
    "iso:country":"US",
    "sg:address":"290 Hallock St",
    "sg:city":"Jamestown",
    "sg:classifiers":[
        {
            "category":"Organizations",
            "subcategory":"Religious Organization",
            "type":"Services"
        }
    ],
    "sg:phone":"+1 716 487 9982",
    "sg:postcode":"14701",
    "sg:province":"NY",
    "sg:tags":[
        "clergy"
    ],
    "wof:name":"John W Steinhauser",
    "wof:placetype":"venue"
},
  "geometry": {"coordinates":[-79.26159199999999,42.096],"type":"Point"}
}