{
  "type": "Feature",
  "properties": {
    "addr:full":"145 Kent Ave Brooklyn NY 11211",
    "addr:housenumber":"145",
    "addr:postcode":"11211",
    "addr:street":"Kent Ave",
    "iso:country":"US",
    "sg:address":"145 Kent Ave",
    "sg:city":"Brooklyn",
    "sg:classifiers":[
        {
            "category":"Wholesale",
            "subcategory":"Home Furnishings",
            "type":"Manufacturing & Wholesale Goods"
        }
    ],
    "sg:phone":"+1 718 387 8440",
    "sg:postcode":"11211",
    "sg:province":"NY",
    "sg:tags":[
        "china"
    ],
    "wof:name":"Seymour Mann Inc",
    "wof:placetype":"venue"
},
  "geometry": {"coordinates":[-73.96252200000001,40.719568],"type":"Point"}
}