{
  "type": "Feature",
  "properties": {
    "iso:country":"US",
    "sg:address":"79 Bullis Rd",
    "sg:city":"Alden",
    "sg:classifiers":[
        {
            "category":"Farming",
            "subcategory":"Farm & Veterinary Services",
            "type":"Manufacturing & Wholesale Goods"
        }
    ],
    "sg:phone":"+1 585 937 7952",
    "sg:postcode":"14004",
    "sg:province":"NY",
    "sg:tags":[
        "dairy",
        "livestock"
    ],
    "wof:name":"Ron Heineman",
    "wof:placetype":"venue"
},
  "geometry": {"coordinates":[-78.481988,42.841612],"type":"Point"}
}