{
  "type": "Feature",
  "properties": {
    "addr:full":"435 New Karner Rd Albany NY 12205",
    "addr:housenumber":"435",
    "addr:postcode":"12205",
    "addr:street":"New Karner Rd",
    "iso:country":"US",
    "sg:address":"435 New Karner Rd",
    "sg:city":"Albany",
    "sg:classifiers":[
        {
            "category":"Real Estate",
            "subcategory":"Architect",
            "type":"Services"
        },
        {
            "category":"Professional",
            "subcategory":"Engineering",
            "type":"Services"
        }
    ],
    "sg:phone":"+1 518 452 1037",
    "sg:postcode":"12205",
    "sg:province":"NY",
    "sg:tags":[
        "architectural",
        "engineer"
    ],
    "sg:website":"www.foit-albert.com",
    "wof:name":"Foit-Albert Associates",
    "wof:placetype":"venue"
},
  "geometry": {"coordinates":[-73.846408,42.735392],"type":"Point"}
}