{
  "type": "Feature",
  "properties": {
    "addr:full":"1868 W 12th St Brooklyn NY 11223",
    "addr:housenumber":"1868",
    "addr:postcode":"11223",
    "addr:street":"W 12Th St",
    "iso:country":"US",
    "sg:address":"1868 W 12th St",
    "sg:city":"Brooklyn",
    "sg:classifiers":[
        {
            "category":"Manufacturing",
            "subcategory":"Metals",
            "type":"Manufacturing & Wholesale Goods"
        },
        {
            "category":"Government",
            "subcategory":"Fire Station",
            "type":"Public Place"
        },
        {
            "category":"Commercial Area",
            "type":"Public Place"
        },
        {
            "category":"Building & Trades",
            "subcategory":"Construction",
            "type":"Services"
        }
    ],
    "sg:phone":"+1 347 860 9353",
    "sg:postcode":"11223",
    "sg:province":"NY",
    "sg:tags":[
        "work",
        "iron",
        "escape",
        "front",
        "welder",
        "store"
    ],
    "sg:website":"http://www.lunawelding.com",
    "wof:name":"Luna Welding And Fabrication",
    "wof:placetype":"venue"
},
  "geometry": {"coordinates":[-73.984154,40.601233],"type":"Point"}
}