{
  "type": "Feature",
  "properties": {
    "iso:country":"US",
    "sg:address":"9 Catalina Dr",
    "sg:city":"Great Neck",
    "sg:classifiers":[
        {
            "category":"Real Estate",
            "subcategory":"Real Estate Operator",
            "type":"Services"
        }
    ],
    "sg:phone":"+1 516 487 6310",
    "sg:postcode":"11024",
    "sg:province":"NY",
    "sg:tags":[
        "building",
        "commercial",
        "operates"
    ],
    "wof:name":"Z D Jasper Realty Inc",
    "wof:placetype":"venue"
},
  "geometry": {"coordinates":[-73.743144,40.815957],"type":"Point"}
}