{
  "type": "Feature",
  "properties": {
    "addr:full":"14 Covert St Brooklyn NY 11207",
    "addr:housenumber":"14",
    "addr:postcode":"11207",
    "addr:street":"Covert St",
    "iso:country":"US",
    "sg:address":"14 Covert St",
    "sg:city":"Brooklyn",
    "sg:classifiers":[
        {
            "category":"Professional",
            "subcategory":"Business Services",
            "type":"Services"
        }
    ],
    "sg:phone":"+1 718 574 1458",
    "sg:postcode":"11207",
    "sg:province":"NY",
    "sg:tags":[
        "agent",
        "artist"
    ],
    "wof:name":"Mudu Multi Media Inc",
    "wof:placetype":"venue"
},
  "geometry": {"coordinates":[-73.912634,40.685771],"type":"Point"}
}