{
  "type": "Feature",
  "properties": {
    "addr:full":"944 Intervale Avenue Bronx NY 10459",
    "addr:housenumber":"944",
    "addr:postcode":"10459",
    "addr:street":"Intervale Avenue",
    "iso:country":"US",
    "sg:address":"944 Intervale Avenue",
    "sg:city":"Bronx",
    "sg:classifiers":[
        {
            "category":"Food & Beverages",
            "subcategory":"Liquor & Beverages",
            "type":"Retail Goods"
        }
    ],
    "sg:phone":"+1 718 842 0241",
    "sg:postcode":"10459",
    "sg:province":"NY",
    "sg:tags":[
        "beer",
        "spirit",
        "wine"
    ],
    "wof:name":"Intervale Liquors",
    "wof:placetype":"venue"
},
  "geometry": {"coordinates":[-73.896725,40.821149],"type":"Point"}
}