{
  "type": "Feature",
  "properties": {
    "iso:country":"US",
    "sg:address":"292 Madison Ave",
    "sg:city":"New York",
    "sg:classifiers":[
        {
            "category":"Professional",
            "subcategory":"Lawyer & Legal Services",
            "type":"Services"
        }
    ],
    "sg:phone":"+1 212 947 0500",
    "sg:postcode":"10017",
    "sg:province":"NY",
    "sg:tags":[
        "attorney"
    ],
    "wof:name":"Lieberman & Nowak",
    "wof:placetype":"venue"
},
  "geometry": {"coordinates":[-73.980048,40.75179],"type":"Point"}
}