{
  "type": "Feature",
  "properties": {
    "addr:full":"38 E Main St Elmsford NY 10523",
    "addr:housenumber":"38",
    "addr:postcode":"10523",
    "addr:street":"E Main St",
    "iso:country":"US",
    "sg:address":"38 E Main St",
    "sg:city":"Elmsford",
    "sg:classifiers":[
        {
            "category":"Bars & Pubs",
            "type":"Food & Drink"
        }
    ],
    "sg:phone":"+1 914 592 6824",
    "sg:postcode":"10523",
    "sg:province":"NY",
    "wof:name":"Maxwell's Pub",
    "wof:placetype":"venue"
},
  "geometry": {"coordinates":[-73.817865,41.054208],"type":"Point"}
}