{
  "type": "Feature",
  "properties": {
    "addr:full":"2 Brooklyn Ave Brooklyn NY 11216",
    "addr:housenumber":"2",
    "addr:postcode":"11216",
    "addr:street":"Brooklyn Ave",
    "iso:country":"US",
    "sg:address":"2 Brooklyn Ave",
    "sg:city":"Brooklyn",
    "sg:classifiers":[
        {
            "category":"Manufacturing",
            "subcategory":"Apparel",
            "type":"Manufacturing & Wholesale Goods"
        }
    ],
    "sg:phone":"+1   ",
    "sg:postcode":"11216",
    "sg:province":"NY",
    "sg:tags":[
        "equipment",
        "industrial"
    ],
    "wof:name":"Top Quality Sewing Machine Co",
    "wof:placetype":"venue"
},
  "geometry": {"coordinates":[-73.944048,40.679336],"type":"Point"}
}