{
  "type": "Feature",
  "properties": {
    "addr:full":"505 Gateway Dr Brooklyn NY 11239",
    "addr:housenumber":"505",
    "addr:postcode":"11239",
    "addr:street":"Gateway Dr",
    "iso:country":"US",
    "sg:address":"505 Gateway Dr",
    "sg:city":"Brooklyn",
    "sg:classifiers":[
        {
            "category":"Fast Food",
            "type":"Food & Drink"
        },
        {
            "category":"Restaurant",
            "type":"Food & Drink"
        }
    ],
    "sg:phone":"+1 718 348 1071",
    "sg:postcode":"11239",
    "sg:province":"NY",
    "sg:tags":[
        "style",
        "family",
        "american",
        "take",
        "pasta",
        "italian"
    ],
    "sg:website":"www.olivegarden.com",
    "wof:name":"Olive Garden",
    "wof:placetype":"venue"
},
  "geometry": {"coordinates":[-73.86909900000001,40.651423],"type":"Point"}
}