{
  "type": "Feature",
  "properties": {
    "addr:full":"708 Glen Cove Ave Glen Head NY 11545",
    "addr:housenumber":"708",
    "addr:postcode":"11545",
    "addr:street":"Glen Cove Ave Glen",
    "iso:country":"US",
    "sg:address":"708 Glen Cove Ave",
    "sg:city":"Glen Head",
    "sg:classifiers":[
        {
            "category":"Health Services",
            "subcategory":"Health Practitioner",
            "type":"Services"
        }
    ],
    "sg:phone":"+1 516 671 7010",
    "sg:postcode":"11545",
    "sg:province":"NY",
    "sg:tags":[
        "psychologist"
    ],
    "wof:name":"Diane Kopitowsky Lmsw",
    "wof:placetype":"venue"
},
  "geometry": {"coordinates":[-73.629526,40.831408],"type":"Point"}
}