{
  "type": "Feature",
  "properties": {
    "addr:full":"6 Johnson Dr Stony Point NY 10980",
    "addr:housenumber":"6",
    "addr:postcode":"10980",
    "addr:street":"Johnson Dr",
    "iso:country":"US",
    "sg:address":"6 Johnson Dr",
    "sg:city":"Stony Point",
    "sg:classifiers":[
        {
            "category":"Utilities",
            "type":"Services"
        }
    ],
    "sg:phone":"+1   ",
    "sg:postcode":"10980",
    "sg:province":"NY",
    "sg:tags":[
        "landscaping",
        "contractor"
    ],
    "wof:name":"Northastern Ldscp Lawncare LLC",
    "wof:placetype":"venue"
},
  "geometry": {"coordinates":[-74.02250100000001,41.233172],"type":"Point"}
}