{
  "type": "Feature",
  "properties": {
    "iso:country":"US",
    "sg:address":"23 W Islip Rd",
    "sg:city":"West Islip",
    "sg:classifiers":[
        {
            "category":"Professional",
            "type":"Services"
        }
    ],
    "sg:phone":"+1 631 422 3071",
    "sg:postcode":"11795",
    "sg:province":"NY",
    "sg:tags":[
        "establishment"
    ],
    "wof:name":"Daughters Of Wisdom",
    "wof:placetype":"venue"
},
  "geometry": {"coordinates":[-73.31558099999999,40.688038],"type":"Point"}
}