{
  "type": "Feature",
  "properties": {
    "iso:country":"US",
    "sg:address":"68 Main Ave",
    "sg:city":"Wynantskill",
    "sg:classifiers":[
        {
            "category":"Real Estate",
            "subcategory":"Real Estate Agent",
            "type":"Services"
        }
    ],
    "sg:phone":"+1 518 286 2955",
    "sg:postcode":"12198",
    "sg:province":"NY",
    "wof:name":"Berigan Real Estate",
    "wof:placetype":"venue"
},
  "geometry": {"coordinates":[-73.644683,42.69679],"type":"Point"}
}