{
  "type": "Feature",
  "properties": {
    "addr:full":"200 Administration Building Rd Massena NY 13662",
    "addr:housenumber":"200",
    "addr:postcode":"13662",
    "addr:street":"Building Rd",
    "iso:country":"US",
    "sg:address":"200 Administration Building Rd",
    "sg:city":"Massena",
    "sg:classifiers":[
        {
            "category":"Airline",
            "type":"Transportation"
        }
    ],
    "sg:phone":"+1 315 769 2089",
    "sg:postcode":"13662",
    "sg:province":"NY",
    "sg:tags":[
        "company",
        "regional"
    ],
    "wof:name":"US Airways Express",
    "wof:placetype":"venue"
},
  "geometry": {"coordinates":[-74.84219299999999,44.933073],"type":"Point"}
}