{
  "type": "Feature",
  "properties": {
    "iso:country":"US",
    "sg:address":"1011 Portion Rd",
    "sg:city":"Ronkonkoma",
    "sg:classifiers":[
        {
            "category":"Building & Trades",
            "subcategory":"Construction",
            "type":"Services"
        }
    ],
    "sg:phone":"+1 631 698 1062",
    "sg:postcode":"11779",
    "sg:province":"NY",
    "sg:tags":[
        "house"
    ],
    "wof:name":"David Redlo Construction",
    "wof:placetype":"venue"
},
  "geometry": {"coordinates":[-73.067139,40.835375],"type":"Point"}
}