{
  "type": "Feature",
  "properties": {
    "addr:full":"7607 3rd Ave Brooklyn NY 11209",
    "addr:housenumber":"7607",
    "addr:postcode":"11209",
    "addr:street":"3Rd Ave",
    "iso:country":"US",
    "sg:address":"7607 3rd Ave",
    "sg:city":"Brooklyn",
    "sg:classifiers":[
        {
            "category":"Building & Trades",
            "subcategory":"Construction",
            "type":"Services"
        }
    ],
    "sg:phone":"+1 718 745 1930",
    "sg:postcode":"11209",
    "sg:province":"NY",
    "sg:tags":[
        "plumbing",
        "electrical",
        "heating",
        "contractor"
    ],
    "wof:name":"Dimitri Enterprises Inc",
    "wof:placetype":"venue"
},
  "geometry": {"coordinates":[-74.028294,40.630045],"type":"Point"}
}