{
  "type": "Feature",
  "properties": {
    "addr:full":"105 Wooster St New York NY 10012",
    "addr:housenumber":"105",
    "addr:postcode":"10012",
    "addr:street":"Wooster St",
    "iso:country":"US",
    "sg:address":"105 Wooster St",
    "sg:city":"New York",
    "sg:classifiers":[
        {
            "category":"Home & Garden",
            "subcategory":"Furniture",
            "type":"Retail Goods"
        },
        {
            "category":"Home & Garden",
            "subcategory":"Carpets & Floor Coverings",
            "type":"Retail Goods"
        }
    ],
    "sg:phone":"+1 212 334 4343",
    "sg:postcode":"10012",
    "sg:province":"NY",
    "sg:tags":[
        "store",
        "mattress"
    ],
    "sg:website":"www.roomandboard.com",
    "wof:name":"Room & Board",
    "wof:placetype":"venue"
},
  "geometry": {"coordinates":[-74.000792,40.724617],"type":"Point"}
}