{
  "type": "Feature",
  "properties": {
    "iso:country":"US",
    "sg:address":"14 S Central Ave",
    "sg:city":"Mechanicville",
    "sg:classifiers":[
        {
            "category":"Autos & Motor Vehicles",
            "subcategory":"Motorcycle Sales",
            "type":"Retail Goods"
        }
    ],
    "sg:phone":"+1 518 664 9025",
    "sg:postcode":"12118",
    "sg:province":"NY",
    "sg:tags":[
        "car",
        "golf",
        "cart"
    ],
    "wof:name":"Haney's",
    "wof:placetype":"venue"
},
  "geometry": {"coordinates":[-73.68781,42.902951],"type":"Point"}
}