{
  "type": "Feature",
  "properties": {
    "addr:full":"3761 88th Street Jackson Heights NY 11372",
    "addr:housenumber":"3761",
    "addr:postcode":"11372",
    "addr:street":"88Th Street",
    "iso:country":"US",
    "sg:address":"3761 88th Street",
    "sg:city":"Jackson Heights",
    "sg:classifiers":[
        {
            "category":"Education",
            "subcategory":"School",
            "type":"Public Place"
        }
    ],
    "sg:phone":"+1 718 651 6878",
    "sg:postcode":"11372",
    "sg:province":"NY",
    "sg:tags":[
        "high",
        "middle",
        "elementary"
    ],
    "wof:name":"Educational Center of East Gate",
    "wof:placetype":"venue"
},
  "geometry": {"coordinates":[-73.87828,40.748657],"type":"Point"}
}