{
  "type": "Feature",
  "properties": {
    "addr:full":"58 N Park St Cambridge NY 12816",
    "addr:housenumber":"58",
    "addr:postcode":"12816",
    "addr:street":"N Park St",
    "iso:country":"US",
    "sg:address":"58 N Park St",
    "sg:city":"Cambridge",
    "sg:classifiers":[
        {
            "category":"Travel",
            "subcategory":"Hotels & Motels",
            "type":"Entertainment"
        }
    ],
    "sg:phone":"+1   ",
    "sg:postcode":"12816",
    "sg:province":"NY",
    "sg:tags":[
        "operation"
    ],
    "wof:name":"Town House Motor Inn LLC",
    "wof:placetype":"venue"
},
  "geometry": {"coordinates":[-73.378293,43.037913],"type":"Point"}
}