{
  "type": "Feature",
  "properties": {
    "iso:country":"US",
    "sg:address":"1229 Broadway",
    "sg:city":"Hewlett",
    "sg:classifiers":[
        {
            "category":"Health Services",
            "subcategory":"Health Practitioner",
            "type":"Services"
        }
    ],
    "sg:phone":"+1   ",
    "sg:postcode":"11557",
    "sg:province":"NY",
    "wof:name":"Paul C Liebman",
    "wof:placetype":"venue"
},
  "geometry": {"coordinates":[-73.702184,40.637425],"type":"Point"}
}