{
  "type": "Feature",
  "properties": {
    "iso:country":"US",
    "sg:address":"15705 Linden Blvd",
    "sg:city":"Jamaica",
    "sg:classifiers":[
        {
            "category":"Wholesale",
            "subcategory":"Fruits & Vegetables",
            "type":"Manufacturing & Wholesale Goods"
        }
    ],
    "sg:phone":"+1 718 529 4072",
    "sg:postcode":"11434",
    "sg:province":"NY",
    "sg:tags":[
        "veggie"
    ],
    "wof:name":"Produce Plus Corp",
    "wof:placetype":"venue"
},
  "geometry": {"coordinates":[-73.790199,40.687901],"type":"Point"}
}