{
  "type": "Feature",
  "properties": {
    "iso:country":"US",
    "sg:address":"302 Main St",
    "sg:city":"Northport",
    "sg:classifiers":[
        {
            "category":"Wholesale",
            "subcategory":"Chemicals & Plastics",
            "type":"Manufacturing & Wholesale Goods"
        }
    ],
    "sg:phone":"+1 631 261 5920",
    "sg:postcode":"11768",
    "sg:province":"NY",
    "wof:name":"S & S Chemical Co",
    "wof:placetype":"venue"
},
  "geometry": {"coordinates":[-73.343441,40.901121],"type":"Point"}
}