{
  "type": "Feature",
  "properties": {
    "iso:country":"US",
    "sg:address":"8955 Cattaraugus St",
    "sg:city":"Springville",
    "sg:classifiers":[
        {
            "category":"Education",
            "subcategory":"Special Training",
            "type":"Public Place"
        },
        {
            "category":"Arena",
            "subcategory":"Sports Club",
            "type":"Entertainment"
        }
    ],
    "sg:phone":"+1 716 592 5425",
    "sg:postcode":"14141",
    "sg:province":"NY",
    "sg:tags":[
        "instruction",
        "equipment",
        "self defense",
        "martial art"
    ],
    "wof:name":"Kempo Karate",
    "wof:placetype":"venue"
},
  "geometry": {"coordinates":[-78.66142000000001,42.499826],"type":"Point"}
}