{
  "type": "Feature",
  "properties": {
    "iso:country":"US",
    "sg:address":"23 Gramercy Park S",
    "sg:city":"New York",
    "sg:classifiers":[
        {
            "category":"Organizations",
            "subcategory":"Non-profit Organization",
            "type":"Services"
        }
    ],
    "sg:phone":"+1 646 602 2905",
    "sg:postcode":"10003",
    "sg:province":"NY",
    "wof:name":"Hispanic's In Philanthropy",
    "wof:placetype":"venue"
},
  "geometry": {"coordinates":[-73.98627500000001,40.73764],"type":"Point"}
}