{
  "type": "Feature",
  "properties": {
    "addr:full":"105 Columbia Ave Syracuse NY 13207",
    "addr:housenumber":"105",
    "addr:postcode":"13207",
    "addr:street":"Columbia Ave",
    "iso:country":"US",
    "sg:address":"105 Columbia Ave",
    "sg:city":"Syracuse",
    "sg:classifiers":[
        {
            "category":"Building & Trades",
            "subcategory":"Construction",
            "type":"Services"
        }
    ],
    "sg:phone":"+1 315 422 0322",
    "sg:postcode":"13207",
    "sg:province":"NY",
    "sg:tags":[
        "driveway",
        "paving",
        "contractor"
    ],
    "wof:name":"Bono Construction",
    "wof:placetype":"venue"
},
  "geometry": {"coordinates":[-76.168087,43.022619],"type":"Point"}
}