{
  "type": "Feature",
  "properties": {
    "iso:country":"US",
    "sg:address":"380 Columbus Ave",
    "sg:city":"New York",
    "sg:classifiers":[
        {
            "category":"Restaurant",
            "type":"Food & Drink"
        }
    ],
    "sg:phone":"+1 212 724 2363",
    "sg:postcode":"10024",
    "sg:province":"NY",
    "sg:website":"www.evelyn-lounge.com",
    "wof:name":"KAMA",
    "wof:placetype":"venue"
},
  "geometry": {"coordinates":[-73.97547900000001,40.781951],"type":"Point"}
}