{
  "type": "Feature",
  "properties": {
    "iso:country":"US",
    "sg:address":"187 3rd Ave Ofc 1",
    "sg:city":"New York",
    "sg:classifiers":[
        {
            "category":"Health Services",
            "subcategory":"Doctor",
            "type":"Services"
        }
    ],
    "sg:phone":"+1 212 228 6554",
    "sg:postcode":"10003",
    "sg:province":"NY",
    "wof:name":"Lower Manhattan Dialysis Ctr",
    "wof:placetype":"venue"
},
  "geometry": {"coordinates":[-73.985901,40.735199],"type":"Point"}
}