{
  "type": "Feature",
  "properties": {
    "addr:full":"1048 Nostrand Ave Brooklyn NY 11225",
    "addr:housenumber":"1048",
    "addr:postcode":"11225",
    "addr:street":"Nostrand Ave",
    "iso:country":"US",
    "sg:address":"1048 Nostrand Ave",
    "sg:city":"Brooklyn",
    "sg:classifiers":[
        {
            "category":"Personal",
            "type":"Services"
        }
    ],
    "sg:phone":"+1 718 778 7332",
    "sg:postcode":"11225",
    "sg:province":"NY",
    "sg:tags":[
        "hair",
        "replacement"
    ],
    "wof:name":"Seny African Hairbraiding",
    "wof:placetype":"venue"
},
  "geometry": {"coordinates":[-73.950924,40.662839],"type":"Point"}
}