{
  "type": "Feature",
  "properties": {
    "iso:country":"US",
    "sg:address":"54 Hastings Dr",
    "sg:city":"Northport",
    "sg:classifiers":[
        {
            "category":"Building & Trades",
            "subcategory":"Plumbing",
            "type":"Services"
        }
    ],
    "sg:phone":"+1 631 754 4161",
    "sg:postcode":"11768",
    "sg:province":"NY",
    "sg:tags":[
        "contractor"
    ],
    "wof:name":"Five Star Plumbing & Heating",
    "wof:placetype":"venue"
},
  "geometry": {"coordinates":[-73.28739899999999,40.904202],"type":"Point"}
}