{
  "type": "Feature",
  "properties": {
    "addr:full":"46 Sentinel Rd Lake Placid NY 12946",
    "addr:housenumber":"46",
    "addr:postcode":"12946",
    "addr:street":"Sentinel Rd",
    "iso:country":"US",
    "sg:address":"46 Sentinel Rd",
    "sg:city":"Lake Placid",
    "sg:classifiers":[
        {
            "category":"Restaurant",
            "type":"Food & Drink"
        }
    ],
    "sg:phone":"+1 518 523 3630",
    "sg:postcode":"12946",
    "sg:province":"NY",
    "wof:name":"Chair 6",
    "wof:placetype":"venue"
},
  "geometry": {"coordinates":[-73.980214,44.273413],"type":"Point"}
}