{
  "type": "Feature",
  "properties": {
    "addr:full":"240 W 35th Street Suite 605 New York NY 10001",
    "addr:housenumber":"240;605",
    "addr:postcode":"10001",
    "addr:street":"W 35Th Street Suite",
    "iso:country":"US",
    "sg:address":"240 W 35th Street Suite 605",
    "sg:city":"New York",
    "sg:classifiers":[
        {
            "category":"Health Services",
            "subcategory":"Doctor",
            "type":"Services"
        }
    ],
    "sg:phone":"+1 212 868 1030",
    "sg:postcode":"10001",
    "sg:province":"NY",
    "wof:name":"Optimum Health Group",
    "wof:placetype":"venue"
},
  "geometry": {"coordinates":[-73.991309,40.75213],"type":"Point"}
}