{
  "type": "Feature",
  "properties": {
    "addr:full":"35 Roselle St Mineola NY 11501",
    "addr:housenumber":"35",
    "addr:postcode":"11501",
    "addr:street":"Roselle St",
    "iso:country":"US",
    "sg:address":"35 Roselle St",
    "sg:city":"Mineola",
    "sg:classifiers":[
        {
            "category":"Wholesale",
            "subcategory":"Machinery & Supplies",
            "type":"Manufacturing & Wholesale Goods"
        }
    ],
    "sg:phone":"+1 516 742 1231",
    "sg:postcode":"11501",
    "sg:province":"NY",
    "sg:tags":[
        "equipment",
        "establishment"
    ],
    "wof:name":"Connors Associates LTD",
    "wof:placetype":"venue"
},
  "geometry": {"coordinates":[-73.63570199999999,40.753621],"type":"Point"}
}