{
  "type": "Feature",
  "properties": {
    "addr:full":"219 Forts Ferry Rd Latham NY 12110",
    "addr:housenumber":"219",
    "addr:postcode":"12110",
    "addr:street":"Forts Ferry Rd",
    "iso:country":"US",
    "sg:address":"219 Forts Ferry Rd",
    "sg:city":"Latham",
    "sg:classifiers":[
        {
            "category":"Real Estate",
            "subcategory":"Architect",
            "type":"Services"
        }
    ],
    "sg:phone":"+1 518 785 5851",
    "sg:postcode":"12110",
    "sg:province":"NY",
    "sg:tags":[
        "firm"
    ],
    "sg:website":"www.truarchs.com",
    "wof:name":"Trudeau Architects",
    "wof:placetype":"venue"
},
  "geometry": {"coordinates":[-73.78642499999999,42.787565],"type":"Point"}
}