{
  "type": "Feature",
  "properties": {
    "iso:country":"US",
    "sg:address":"318 Hendy Ave",
    "sg:city":"Elmira",
    "sg:classifiers":[
        {
            "category":"Building & Trades",
            "subcategory":"Electrical",
            "type":"Services"
        }
    ],
    "sg:phone":"+1 607 733 6719",
    "sg:postcode":"14905",
    "sg:province":"NY",
    "sg:tags":[
        "electrical",
        "contractor"
    ],
    "wof:name":"Lechliter Electric",
    "wof:placetype":"venue"
},
  "geometry": {"coordinates":[-76.8462,42.082018],"type":"Point"}
}