{
  "type": "Feature",
  "properties": {
    "addr:full":"860 E 180th St Bronx NY 10460",
    "addr:housenumber":"860",
    "addr:postcode":"10460",
    "addr:street":"E 180Th St",
    "iso:country":"US",
    "sg:address":"860 E 180th St",
    "sg:city":"Bronx",
    "sg:classifiers":[
        {
            "category":"Food & Beverages",
            "subcategory":"Groceries & Convenience Stores",
            "type":"Retail Goods"
        }
    ],
    "sg:phone":"+1 718 367 6366",
    "sg:postcode":"10460",
    "sg:province":"NY",
    "sg:tags":[
        "product"
    ],
    "wof:name":"Suceso RS Food",
    "wof:placetype":"venue"
},
  "geometry": {"coordinates":[-73.882429,40.844981],"type":"Point"}
}