{
  "type": "Feature",
  "properties": {
    "addr:full":"992 Carter St Rochester NY 14621",
    "addr:housenumber":"992",
    "addr:postcode":"14621",
    "addr:street":"Carter St",
    "iso:country":"US",
    "sg:address":"992 Carter St",
    "sg:city":"Rochester",
    "sg:classifiers":[
        {
            "category":"Real Estate",
            "subcategory":"Real Estate Agent",
            "type":"Services"
        }
    ],
    "sg:phone":"+1 585 749 6624",
    "sg:postcode":"14621",
    "sg:province":"NY",
    "wof:name":"Genesee Valley Group Inc",
    "wof:placetype":"venue"
},
  "geometry": {"coordinates":[-77.59225600000001,43.194703],"type":"Point"}
}