{
  "type": "Feature",
  "properties": {
    "addr:full":"51 Madison Ave New York NY 10010",
    "addr:housenumber":"51",
    "addr:postcode":"10010",
    "addr:street":"Madison Ave",
    "iso:country":"US",
    "sg:address":"51 Madison Ave",
    "sg:city":"New York",
    "sg:classifiers":[
        {
            "category":"Restaurant",
            "type":"Food & Drink"
        }
    ],
    "sg:phone":"+1   ",
    "sg:postcode":"10010",
    "sg:province":"NY",
    "sg:tags":[
        "eating"
    ],
    "wof:name":"Classic Fare Catering",
    "wof:placetype":"venue"
},
  "geometry": {"coordinates":[-73.986209,40.743121],"type":"Point"}
}