{
  "type": "Feature",
  "properties": {
    "iso:country":"US",
    "sg:address":"175 S 2nd St",
    "sg:city":"Fulton",
    "sg:classifiers":[
        {
            "category":"Professional",
            "subcategory":"Accounting & Tax Preparation",
            "type":"Services"
        }
    ],
    "sg:phone":"+1 315 598 4411",
    "sg:postcode":"13069",
    "sg:province":"NY",
    "sg:tags":[
        "accountant"
    ],
    "wof:name":"Jack B Alter CPA",
    "wof:placetype":"venue"
},
  "geometry": {"coordinates":[-76.41474100000001,43.321176],"type":"Point"}
}