{
  "type": "Feature",
  "properties": {
    "iso:country":"US",
    "sg:address":"1 Fulton Ave Ste 19",
    "sg:city":"Hempstead",
    "sg:classifiers":[
        {
            "category":"Health Services",
            "subcategory":"Doctor",
            "type":"Services"
        }
    ],
    "sg:phone":"+1 516 486 2300",
    "sg:postcode":"11550",
    "sg:province":"NY",
    "sg:tags":[
        "medicine",
        "internal"
    ],
    "wof:name":"Sakowitz Mervin MD",
    "wof:placetype":"venue"
},
  "geometry": {"coordinates":[-73.638397,40.7048],"type":"Point"}
}