{
  "type": "Feature",
  "properties": {
    "addr:full":"25 Dartmouth St Garden City NY 11530",
    "addr:housenumber":"25",
    "addr:postcode":"11530",
    "addr:street":"Dartmouth St",
    "iso:country":"US",
    "sg:address":"25 Dartmouth St",
    "sg:city":"Garden City",
    "sg:classifiers":[
        {
            "category":"Education",
            "subcategory":"School",
            "type":"Public Place"
        }
    ],
    "sg:phone":"+1 516 352 1205",
    "sg:postcode":"11530",
    "sg:province":"NY",
    "sg:website":"www.stannesgc.org",
    "wof:name":"St Anne's School",
    "wof:placetype":"venue"
},
  "geometry": {"coordinates":[-73.67744,40.718412],"type":"Point"}
}