{
  "type": "Feature",
  "properties": {
    "addr:full":"2000 Raynors Way Smithtown NY 11787",
    "addr:postcode":"11787",
    "addr:street":"Raynors Way",
    "iso:country":"US",
    "sg:address":"2000 Raynors Way",
    "sg:city":"Smithtown",
    "sg:classifiers":[
        {
            "category":"Professional",
            "type":"Services"
        },
        {
            "category":"Bars & Pubs",
            "subcategory":"Nightclub",
            "type":"Food & Drink"
        },
        {
            "category":"Sports & Exercise",
            "subcategory":"Golf",
            "type":"Entertainment"
        }
    ],
    "sg:phone":"+1 631 724 7500",
    "sg:postcode":"11787",
    "sg:province":"NY",
    "sg:tags":[
        "nightlife",
        "caterer"
    ],
    "wof:name":"Stonebridge Golf Links & Country Club",
    "wof:placetype":"venue"
},
  "geometry": {"coordinates":[-73.208,40.833698],"type":"Point"}
}