{
  "type": "Feature",
  "properties": {
    "iso:country":"US",
    "sg:address":"179 Islip Ave",
    "sg:city":"Islip",
    "sg:classifiers":[
        {
            "category":"Shopping",
            "subcategory":"Florist",
            "type":"Retail Goods"
        }
    ],
    "sg:phone":"+1 631 277 2101",
    "sg:postcode":"11751",
    "sg:province":"NY",
    "sg:tags":[
        "merchandise"
    ],
    "wof:name":"Flowers By Chazz Inc",
    "wof:placetype":"venue"
},
  "geometry": {"coordinates":[-73.207762,40.736844],"type":"Point"}
}