{
  "type": "Feature",
  "properties": {
    "addr:full":"8748 169th St Jamaica NY 11432",
    "addr:housenumber":"8748",
    "addr:postcode":"11432",
    "addr:street":"169Th St",
    "iso:country":"US",
    "sg:address":"8748 169th St",
    "sg:city":"Jamaica",
    "sg:classifiers":[
        {
            "category":"Restaurant",
            "type":"Food & Drink"
        },
        {
            "category":"Food & Beverages",
            "subcategory":"Meat & Fish",
            "type":"Retail Goods"
        }
    ],
    "sg:phone":"+1 718 739 0222",
    "sg:postcode":"11432",
    "sg:province":"NY",
    "sg:tags":[
        "seafood",
        "market"
    ],
    "wof:name":"Young's Seafood",
    "wof:placetype":"venue"
},
  "geometry": {"coordinates":[-73.793346,40.711241],"type":"Point"}
}