{
  "type": "Feature",
  "properties": {
    "addr:full":"49 W 24th St 4th Fl New York NY 10010",
    "addr:housenumber":"49",
    "addr:postcode":"10010",
    "addr:street":"W 24Th St",
    "iso:country":"US",
    "sg:address":"49 W 24th St 4th Fl",
    "sg:city":"New York",
    "sg:classifiers":[
        {
            "category":"Education",
            "subcategory":"Special Training",
            "type":"Public Place"
        },
        {
            "category":"Arts & Performance",
            "subcategory":"Music",
            "type":"Entertainment"
        }
    ],
    "sg:phone":"+1 212 366 0541",
    "sg:postcode":"10010",
    "sg:province":"NY",
    "sg:tags":[
        "school",
        "venue",
        "specialty"
    ],
    "sg:website":"www.singersforum.org",
    "wof:name":"Singers Forum",
    "wof:placetype":"venue"
},
  "geometry": {"coordinates":[-73.991473,40.743422],"type":"Point"}
}