{
  "type": "Feature",
  "properties": {
    "iso:country":"US",
    "sg:address":"2220 154th Street",
    "sg:city":"Whitestone",
    "sg:classifiers":[
        {
            "category":"Restaurant",
            "type":"Food & Drink"
        }
    ],
    "sg:phone":"+1 718 445 1215",
    "sg:postcode":"11357",
    "sg:province":"NY",
    "wof:name":"New Green Garden",
    "wof:placetype":"venue"
},
  "geometry": {"coordinates":[-73.809319,40.777997],"type":"Point"}
}