{
  "type": "Feature",
  "properties": {
    "addr:full":"8 Campus View Dr Loudonville NY 12211",
    "addr:housenumber":"8",
    "addr:postcode":"12211",
    "addr:street":"Campus View Dr",
    "iso:country":"US",
    "sg:address":"8 Campus View Dr",
    "sg:city":"Loudonville",
    "sg:classifiers":[
        {
            "category":"Government",
            "subcategory":"Office",
            "type":"Public Place"
        }
    ],
    "sg:phone":"+1 518 783 0478",
    "sg:postcode":"12211",
    "sg:province":"NY",
    "sg:tags":[
        "village"
    ],
    "wof:name":"Town Of Colonie",
    "wof:placetype":"venue"
},
  "geometry": {"coordinates":[-73.76244199999999,42.718961],"type":"Point"}
}