{
  "type": "Feature",
  "properties": {
    "iso:country":"US",
    "sg:address":"867 Merillon Ave",
    "sg:city":"Westbury",
    "sg:classifiers":[
        {
            "category":"Building & Trades",
            "subcategory":"Construction",
            "type":"Services"
        }
    ],
    "sg:phone":"+1 516 338 6098",
    "sg:postcode":"11590",
    "sg:province":"NY",
    "sg:tags":[
        "house"
    ],
    "wof:name":"Ferrara Custom Construction",
    "wof:placetype":"venue"
},
  "geometry": {"coordinates":[-73.55942899999999,40.749483],"type":"Point"}
}