{
  "type": "Feature",
  "properties": {
    "iso:country":"US",
    "sg:address":"2 Oakwood Pl",
    "sg:city":"Delmar",
    "sg:classifiers":[
        {
            "category":"Professional",
            "subcategory":"Accounting & Tax Preparation",
            "type":"Services"
        }
    ],
    "sg:phone":"+1 518 439 0994",
    "sg:postcode":"12054",
    "sg:province":"NY",
    "sg:tags":[
        "accountant"
    ],
    "wof:name":"Anthony M Gordon Inc",
    "wof:placetype":"venue"
},
  "geometry": {"coordinates":[-73.826825,42.623087],"type":"Point"}
}