{
  "type": "Feature",
  "properties": {
    "addr:full":"636 5th Avenue New York NY 10020",
    "addr:housenumber":"636",
    "addr:postcode":"10020",
    "addr:street":"5Th Avenue",
    "iso:country":"US",
    "sg:address":"636 5th Avenue",
    "sg:city":"New York",
    "sg:classifiers":[
        {
            "category":"Education",
            "subcategory":"School",
            "type":"Public Place"
        }
    ],
    "sg:phone":"+1 212 712 6220",
    "sg:postcode":"10020",
    "sg:province":"NY",
    "sg:website":"www.ecfs.org",
    "wof:name":"Ethical Cultural Schools",
    "wof:placetype":"venue"
},
  "geometry": {"coordinates":[-73.976732,40.758903],"type":"Point"}
}