{
  "type": "Feature",
  "properties": {
    "iso:country":"US",
    "sg:address":"47 Adams Ave",
    "sg:city":"Port Chester",
    "sg:classifiers":[
        {
            "category":"Building & Trades",
            "subcategory":"Electrical",
            "type":"Services"
        }
    ],
    "sg:phone":"+1 914 939 5215",
    "sg:postcode":"10573",
    "sg:province":"NY",
    "sg:tags":[
        "electrical",
        "contractor"
    ],
    "wof:name":"Dobart Lighting",
    "wof:placetype":"venue"
},
  "geometry": {"coordinates":[-73.67275100000001,41.01594],"type":"Point"}
}