{
  "type": "Feature",
  "properties": {
    "addr:full":"373 Rider Ave Bronx NY 10451",
    "addr:housenumber":"373",
    "addr:postcode":"10451",
    "addr:street":"Rider Ave",
    "iso:country":"US",
    "sg:address":"373 Rider Ave",
    "sg:city":"Bronx",
    "sg:classifiers":[
        {
            "category":"Wholesale",
            "subcategory":"Toys & Hobbies",
            "type":"Manufacturing & Wholesale Goods"
        }
    ],
    "sg:phone":"+1 718 401 9270",
    "sg:postcode":"10451",
    "sg:province":"NY",
    "sg:tags":[
        "wholesaler"
    ],
    "wof:name":"Bronco Wholesale Corp",
    "wof:placetype":"venue"
},
  "geometry": {"coordinates":[-73.92564299999999,40.814957],"type":"Point"}
}