{
  "type": "Feature",
  "properties": {
    "addr:full":"101 W 55th St New York NY 10019",
    "addr:housenumber":"101",
    "addr:postcode":"10019",
    "addr:street":"W 55Th St",
    "iso:country":"US",
    "sg:address":"101 W 55th St",
    "sg:city":"New York",
    "sg:classifiers":[
        {
            "category":"Personal",
            "subcategory":"Day Spa",
            "type":"Services"
        },
        {
            "category":"Personal",
            "subcategory":"Skin Care",
            "type":"Services"
        }
    ],
    "sg:phone":"+1 212 581 3343",
    "sg:postcode":"10019",
    "sg:province":"NY",
    "sg:website":"escape-nyc.com/",
    "wof:name":"Escape Skin Care Salon & Day Spa",
    "wof:placetype":"venue"
},
  "geometry": {"coordinates":[-73.978342,40.763257],"type":"Point"}
}