{
  "type": "Feature",
  "properties": {
    "iso:country":"US",
    "sg:address":"28 S Main St",
    "sg:city":"Bainbridge",
    "sg:classifiers":[
        {
            "category":"Building & Trades",
            "subcategory":"Plumbing",
            "type":"Services"
        }
    ],
    "sg:phone":"+1 607 967 8030",
    "sg:postcode":"13733",
    "sg:province":"NY",
    "sg:tags":[
        "plumbing",
        "electrical",
        "heating",
        "contractor"
    ],
    "wof:name":"Rice Plumbing Heating & Elc",
    "wof:placetype":"venue"
},
  "geometry": {"coordinates":[-75.481201,42.292026],"type":"Point"}
}