{
  "type": "Feature",
  "properties": {
    "addr:full":"8075 Main St Buffalo NY 14221",
    "addr:housenumber":"8075",
    "addr:postcode":"14221",
    "addr:street":"Main St",
    "iso:country":"US",
    "sg:address":"8075 Main St",
    "sg:city":"Buffalo",
    "sg:classifiers":[
        {
            "category":"Retail",
            "subcategory":"Laundry & Dry Cleaning",
            "type":"Services"
        }
    ],
    "sg:phone":"+1 716 631 5152",
    "sg:postcode":"14221",
    "sg:province":"NY",
    "sg:tags":[
        "cleaners"
    ],
    "wof:name":"Massaro Cleaners",
    "wof:placetype":"venue"
},
  "geometry": {"coordinates":[-78.692891,42.965052],"type":"Point"}
}