{
  "type": "Feature",
  "properties": {
    "iso:country":"US",
    "sg:address":"1183 Franklin Ave",
    "sg:city":"Bronx",
    "sg:classifiers":[
        {
            "category":"Education",
            "subcategory":"Vocational School",
            "type":"Public Place"
        }
    ],
    "sg:phone":"+1 718 328 0580",
    "sg:postcode":"10456",
    "sg:province":"NY",
    "wof:name":"Grace Institute Outreach",
    "wof:placetype":"venue"
},
  "geometry": {"coordinates":[-73.904067,40.829915],"type":"Point"}
}