{
  "type": "Feature",
  "properties": {
    "addr:full":"323 Washington St Geneva NY 14456",
    "addr:housenumber":"323",
    "addr:postcode":"14456",
    "addr:street":"Washington St",
    "iso:country":"US",
    "sg:address":"323 Washington St",
    "sg:city":"Geneva",
    "sg:classifiers":[
        {
            "category":"Building & Trades",
            "subcategory":"Electrical",
            "type":"Services"
        }
    ],
    "sg:phone":"+1 315 789 1885",
    "sg:postcode":"14456",
    "sg:province":"NY",
    "sg:tags":[
        "electric",
        "contractor"
    ],
    "wof:name":"HAAG Electric",
    "wof:placetype":"venue"
},
  "geometry": {"coordinates":[-76.996253,42.862083],"type":"Point"}
}