{
  "type": "Feature",
  "properties": {
    "iso:country":"US",
    "sg:address":"12 Prospect Ave",
    "sg:city":"Port Washington",
    "sg:classifiers":[
        {
            "category":"Building & Trades",
            "subcategory":"Landscaping Services",
            "type":"Services"
        }
    ],
    "sg:phone":"+1 516 944 2483",
    "sg:postcode":"11050",
    "sg:province":"NY",
    "sg:tags":[
        "tree"
    ],
    "wof:name":"Noga Tree Care Co",
    "wof:placetype":"venue"
},
  "geometry": {"coordinates":[-73.70137,40.830236],"type":"Point"}
}