{
  "type": "Feature",
  "properties": {
    "addr:full":"1551 Brewerton Rd Syracuse NY 13208",
    "addr:housenumber":"1551",
    "addr:postcode":"13208",
    "addr:street":"Brewerton Rd",
    "iso:country":"US",
    "sg:address":"1551 Brewerton Rd",
    "sg:city":"Syracuse",
    "sg:classifiers":[
        {
            "category":"Manufacturing",
            "subcategory":"Apparel",
            "type":"Manufacturing & Wholesale Goods"
        },
        {
            "category":"Manufacturing",
            "subcategory":"Printing",
            "type":"Manufacturing & Wholesale Goods"
        }
    ],
    "sg:phone":"+1 315 455 5551",
    "sg:postcode":"13208",
    "sg:province":"NY",
    "sg:tags":[
        "banner",
        "screen",
        "sign",
        "flag",
        "digital",
        "painting"
    ],
    "wof:name":"Paratore Signs Inc",
    "wof:placetype":"venue"
},
  "geometry": {"coordinates":[-76.14943599999999,43.089692],"type":"Point"}
}