{
  "type": "Feature",
  "properties": {
    "addr:full":"7919 17th Ave Brooklyn NY 11214",
    "addr:housenumber":"7919",
    "addr:postcode":"11214",
    "addr:street":"17Th Ave",
    "iso:country":"US",
    "sg:address":"7919 17th Ave",
    "sg:city":"Brooklyn",
    "sg:classifiers":[
        {
            "category":"Shopping",
            "subcategory":"Bicycles & Sporting Goods",
            "type":"Retail Goods"
        }
    ],
    "sg:phone":"+1 718 259 4924",
    "sg:postcode":"11214",
    "sg:province":"NY",
    "wof:name":"D F Brothers Sportscenter LTD",
    "wof:placetype":"venue"
},
  "geometry": {"coordinates":[-74.000828,40.612372],"type":"Point"}
}