{
  "type": "Feature",
  "properties": {
    "iso:country":"US",
    "sg:address":"21 W 102nd St",
    "sg:city":"New York",
    "sg:classifiers":[
        {
            "category":"Retail",
            "subcategory":"Repair Shop",
            "type":"Services"
        }
    ],
    "sg:phone":"+1 646 224 9201",
    "sg:postcode":"10025",
    "sg:province":"NY",
    "sg:tags":[
        "lock",
        "locksmith"
    ],
    "wof:name":"A Number 1 24 Hour Locksmith",
    "wof:placetype":"venue"
},
  "geometry": {"coordinates":[-73.96292099999999,40.795938],"type":"Point"}
}