{
  "type": "Feature",
  "properties": {
    "iso:country":"US",
    "sg:address":"1207 Park Ave",
    "sg:city":"Utica",
    "sg:classifiers":[
        {
            "category":"Restaurant",
            "type":"Food & Drink"
        }
    ],
    "sg:phone":"+1   ",
    "sg:postcode":"13501",
    "sg:province":"NY",
    "sg:tags":[
        "eating"
    ],
    "wof:name":"Emperors Choice The Inc",
    "wof:placetype":"venue"
},
  "geometry": {"coordinates":[-75.242046,43.09584],"type":"Point"}
}