{
  "type": "Feature",
  "properties": {
    "addr:full":"1052 Broadway Albany NY 12204",
    "addr:housenumber":"1052",
    "addr:postcode":"12204",
    "addr:street":"Broadway",
    "iso:country":"US",
    "sg:address":"1052 Broadway",
    "sg:city":"Albany",
    "sg:classifiers":[
        {
            "category":"Professional",
            "subcategory":"Engineering",
            "type":"Services"
        }
    ],
    "sg:phone":"+1 518 436 0392",
    "sg:postcode":"12204",
    "sg:province":"NY",
    "sg:tags":[
        "engineer"
    ],
    "wof:name":"Collins Engineers Inc",
    "wof:placetype":"venue"
},
  "geometry": {"coordinates":[-73.740782,42.667948],"type":"Point"}
}