{
  "type": "Feature",
  "properties": {
    "addr:full":"4320 4th Avenue Brooklyn NY 11232",
    "addr:housenumber":"4320",
    "addr:postcode":"11232",
    "addr:street":"4Th Avenue",
    "iso:country":"US",
    "sg:address":"4320 4th Avenue",
    "sg:city":"Brooklyn",
    "sg:classifiers":[
        {
            "category":"Food & Beverages",
            "subcategory":"Groceries & Convenience Stores",
            "type":"Retail Goods"
        }
    ],
    "sg:phone":"+1 718 965 1370",
    "sg:postcode":"11232",
    "sg:province":"NY",
    "wof:name":"Iglesias Grocery",
    "wof:placetype":"venue"
},
  "geometry": {"coordinates":[-74.00901399999999,40.65015],"type":"Point"}
}