{
  "type": "Feature",
  "properties": {
    "addr:full":"168 W 25th St New York NY 10001",
    "addr:housenumber":"168",
    "addr:postcode":"10001",
    "addr:street":"W 25Th St",
    "iso:country":"US",
    "sg:address":"168 W 25th St",
    "sg:city":"New York",
    "sg:classifiers":[
        {
            "category":"Restaurant",
            "type":"Food & Drink"
        }
    ],
    "sg:phone":"+1 212 352 0755",
    "sg:postcode":"10001",
    "sg:province":"NY",
    "wof:name":"Milanese Spanish Restaurant",
    "wof:placetype":"venue"
},
  "geometry": {"coordinates":[-73.994373,40.745003],"type":"Point"}
}