{
  "type": "Feature",
  "properties": {
    "addr:full":"724 5th Avenue New York NY 10019",
    "addr:housenumber":"724",
    "addr:postcode":"10019",
    "addr:street":"5Th Avenue",
    "iso:country":"US",
    "sg:address":"724 5th Avenue",
    "sg:city":"New York",
    "sg:classifiers":[
        {
            "category":"Arts & Performance",
            "subcategory":"Art Gallery",
            "type":"Entertainment"
        }
    ],
    "sg:phone":"+1 212 247 2111",
    "sg:postcode":"10019",
    "sg:province":"NY",
    "wof:name":"Moore Gallery DC",
    "wof:placetype":"venue"
},
  "geometry": {"coordinates":[-73.974329,40.762502],"type":"Point"}
}