{
  "type": "Feature",
  "properties": {
    "addr:full":"1122 E Lovejoy St Buffalo NY 14206",
    "addr:housenumber":"1122",
    "addr:postcode":"14206",
    "addr:street":"E Lovejoy St",
    "iso:country":"US",
    "sg:address":"1122 E Lovejoy St",
    "sg:city":"Buffalo",
    "sg:classifiers":[
        {
            "category":"Retail",
            "subcategory":"Funeral Services",
            "type":"Services"
        }
    ],
    "sg:phone":"+1 716 892 7713",
    "sg:postcode":"14206",
    "sg:province":"NY",
    "sg:tags":[
        "director"
    ],
    "wof:name":"Michael A Di Vincenzo Funeral",
    "wof:placetype":"venue"
},
  "geometry": {"coordinates":[-78.80674,42.889829],"type":"Point"}
}