{
  "type": "Feature",
  "properties": {
    "iso:country":"US",
    "sg:address":"2064 Baird Rd",
    "sg:city":"Penfield",
    "sg:classifiers":[
        {
            "category":"Building & Trades",
            "subcategory":"Landscaping Services",
            "type":"Services"
        }
    ],
    "sg:phone":"+1 585 586 7249",
    "sg:postcode":"14526",
    "sg:province":"NY",
    "wof:name":"Country Green Lawn Care Ldscpg",
    "wof:placetype":"venue"
},
  "geometry": {"coordinates":[-77.463864,43.132142],"type":"Point"}
}