{
  "type": "Feature",
  "properties": {
    "iso:country":"US",
    "sg:address":"61 Carmine St",
    "sg:city":"New York",
    "sg:classifiers":[
        {
            "category":"Real Estate",
            "subcategory":"Real Estate Agent",
            "type":"Services"
        }
    ],
    "sg:phone":"+1 212 929 5552",
    "sg:postcode":"10014",
    "sg:province":"NY",
    "wof:name":"Waverly Apartment Services",
    "wof:placetype":"venue"
},
  "geometry": {"coordinates":[-74.00445999999999,40.729834],"type":"Point"}
}