{
  "type": "Feature",
  "properties": {
    "addr:full":"7775 Barbara Ln Baldwinsville NY 13027",
    "addr:housenumber":"7775",
    "addr:postcode":"13027",
    "addr:street":"Barbara Ln",
    "iso:country":"US",
    "sg:address":"7775 Barbara Ln",
    "sg:city":"Baldwinsville",
    "sg:classifiers":[
        {
            "category":"Personal",
            "subcategory":"Beauty Salon",
            "type":"Services"
        }
    ],
    "sg:phone":"+1 315 638 4855",
    "sg:postcode":"13027",
    "sg:province":"NY",
    "wof:name":"Russell & Ruthie Appleby",
    "wof:placetype":"venue"
},
  "geometry": {"coordinates":[-76.29480700000001,43.147599],"type":"Point"}
}