{
  "type": "Feature",
  "properties": {
    "addr:full":"133 7th Ave S New York NY 10014",
    "addr:housenumber":"133",
    "addr:postcode":"10014",
    "addr:street":"7Th Ave S",
    "iso:country":"US",
    "sg:address":"133 7th Ave S",
    "sg:city":"New York",
    "sg:classifiers":[
        {
            "category":"Bars & Pubs",
            "type":"Food & Drink"
        },
        {
            "category":"Restaurant",
            "type":"Food & Drink"
        }
    ],
    "sg:phone":"+1 212 675 6220",
    "sg:postcode":"10014",
    "sg:province":"NY",
    "sg:tags":[
        "irish"
    ],
    "sg:website":"downtowngalwayhooker.com/",
    "wof:name":"Downtown Galway Hooker Pub",
    "wof:placetype":"venue"
},
  "geometry": {"coordinates":[-74.00199499999999,40.73456],"type":"Point"}
}