{
  "type": "Feature",
  "properties": {
    "addr:full":"600 3rd Ave Manhattan NY 10016",
    "addr:housenumber":"600",
    "addr:postcode":"10016",
    "addr:street":"3Rd Ave",
    "iso:country":"US",
    "sg:address":"600 3rd Ave",
    "sg:city":"Manhattan",
    "sg:classifiers":[
        {
            "category":"Coffee & Tea",
            "type":"Food & Drink"
        }
    ],
    "sg:phone":"+1 212 972 2092",
    "sg:postcode":"10016",
    "sg:province":"NY",
    "sg:website":"maps.google.com/maps/place?hl=en...",
    "wof:name":"Java Detour",
    "wof:placetype":"venue"
},
  "geometry": {"coordinates":[-73.97584000000001,40.749256],"type":"Point"}
}