{
  "type": "Feature",
  "properties": {
    "iso:country":"US",
    "sg:address":"665 Parkside Ave",
    "sg:city":"Brooklyn",
    "sg:classifiers":[
        {
            "category":"Education",
            "subcategory":"School",
            "type":"Public Place"
        }
    ],
    "sg:phone":"+1   ",
    "sg:postcode":"11226",
    "sg:province":"NY",
    "wof:name":"PS 141k At Is2",
    "wof:placetype":"venue"
},
  "geometry": {"coordinates":[-73.951542,40.656222],"type":"Point"}
}