{
  "type": "Feature",
  "properties": {
    "addr:full":"50 Sleepy Hollow Rd New Canaan NY 06840",
    "addr:housenumber":"50",
    "addr:postcode":"06840",
    "addr:street":"Sleepy Hollow Rd",
    "iso:country":"US",
    "sg:address":"50 Sleepy Hollow Rd",
    "sg:city":"New Canaan",
    "sg:classifiers":[
        {
            "category":"Insurance",
            "subcategory":"Insurance Agent",
            "type":"Services"
        }
    ],
    "sg:phone":"+1 203 966 4455",
    "sg:postcode":"06840",
    "sg:province":"NY",
    "wof:name":"Harrigan Insurance",
    "wof:placetype":"venue"
},
  "geometry": {"coordinates":[-73.49365400000001,41.177427],"type":"Point"}
}