{
  "type": "Feature",
  "properties": {
    "addr:full":"4278 Main St Ste 2 Flushing NY 11355",
    "addr:housenumber":"4278",
    "addr:postcode":"11355",
    "addr:street":"Main St Ste 2",
    "iso:country":"US",
    "sg:address":"4278 Main St Ste 2",
    "sg:city":"Flushing",
    "sg:classifiers":[
        {
            "category":"Professional",
            "subcategory":"Lawyer & Legal Services",
            "type":"Services"
        }
    ],
    "sg:phone":"+1 718 888 1411",
    "sg:postcode":"11355",
    "sg:province":"NY",
    "sg:tags":[
        "attorney",
        "criminal",
        "law"
    ],
    "wof:name":"Ticket Busters Inc",
    "wof:placetype":"venue"
},
  "geometry": {"coordinates":[-73.82543200000001,40.742479],"type":"Point"}
}