{
  "type": "Feature",
  "properties": {
    "iso:country":"US",
    "sg:address":"104 Westfield Rd",
    "sg:city":"Buffalo",
    "sg:classifiers":[
        {
            "category":"Building & Trades",
            "subcategory":"Construction",
            "type":"Services"
        }
    ],
    "sg:phone":"+1 716 837 8940",
    "sg:postcode":"14226",
    "sg:province":"NY",
    "sg:tags":[
        "house"
    ],
    "wof:name":"Long Remodeling & Design",
    "wof:placetype":"venue"
},
  "geometry": {"coordinates":[-78.801872,42.969126],"type":"Point"}
}