{
  "type": "Feature",
  "properties": {
    "iso:country":"US",
    "sg:address":"161 S Main St",
    "sg:city":"Gloversville",
    "sg:classifiers":[
        {
            "category":"Social Services",
            "subcategory":"Child Care",
            "type":"Services"
        }
    ],
    "sg:phone":"+1 518 725 9784",
    "sg:postcode":"12078",
    "sg:province":"NY",
    "wof:name":"Little Kids & Co",
    "wof:placetype":"venue"
},
  "geometry": {"coordinates":[-74.348961,43.045547],"type":"Point"}
}