{
  "type": "Feature",
  "properties": {
    "addr:full":"232 E 66 St New York NY 10065",
    "addr:housenumber":"232;66",
    "addr:postcode":"10065",
    "addr:street":"E;St",
    "iso:country":"US",
    "sg:address":"232 E 66 St",
    "sg:city":"New York",
    "sg:classifiers":[
        {
            "category":"Health Services",
            "subcategory":"Chiropractor",
            "type":"Services"
        }
    ],
    "sg:phone":"+1   ",
    "sg:postcode":"10065",
    "sg:province":"NY",
    "wof:name":"New York Ntwrk Chropractic Ctr",
    "wof:placetype":"venue"
},
  "geometry": {"coordinates":[-73.962101,40.765366],"type":"Point"}
}