{
  "type": "Feature",
  "properties": {
    "addr:full":"548 Broad Hollow Rd Melville NY 11747",
    "addr:housenumber":"548",
    "addr:postcode":"11747",
    "addr:street":"Broad Hollow Rd",
    "iso:country":"US",
    "sg:address":"548 Broad Hollow Rd",
    "sg:city":"Melville",
    "sg:classifiers":[
        {
            "category":"Manufacturing",
            "subcategory":"Printing",
            "type":"Manufacturing & Wholesale Goods"
        }
    ],
    "sg:phone":"+1   ",
    "sg:postcode":"11747",
    "sg:province":"NY",
    "sg:tags":[
        "publisher",
        "magazine"
    ],
    "wof:name":"National Organics",
    "wof:placetype":"venue"
},
  "geometry": {"coordinates":[-73.423377,40.763162],"type":"Point"}
}