{
  "type": "Feature",
  "properties": {
    "iso:country":"US",
    "sg:address":"3510 McKinley Pkwy",
    "sg:city":"Buffalo",
    "sg:classifiers":[
        {
            "category":"Travel",
            "subcategory":"Travel Agent",
            "type":"Entertainment"
        }
    ],
    "sg:phone":"+1 716 826 9401",
    "sg:postcode":"14219",
    "sg:province":"NY",
    "sg:tags":[
        "agency",
        "bureau"
    ],
    "sg:website":"www.libertytravel.com",
    "wof:name":"Liberty Travel",
    "wof:placetype":"venue"
},
  "geometry": {"coordinates":[-78.811318,42.782494],"type":"Point"}
}