{
  "type": "Feature",
  "properties": {
    "iso:country":"US",
    "sg:address":"123 Maple Ave Ste 204",
    "sg:city":"Cedarhurst",
    "sg:classifiers":[
        {
            "category":"Shopping",
            "subcategory":"Pharmacy",
            "type":"Retail Goods"
        }
    ],
    "sg:phone":"+1 516 569 1110",
    "sg:postcode":"11516",
    "sg:province":"NY",
    "sg:tags":[
        "drugstore"
    ],
    "wof:name":"Pharmaceutical Buyers",
    "wof:placetype":"venue"
},
  "geometry": {"coordinates":[-73.722099,40.623901],"type":"Point"}
}