{
  "type": "Feature",
  "properties": {
    "iso:country":"US",
    "sg:address":"Aida Bacaj Beauty Institute 61 East 75th Street",
    "sg:city":"Manhattan",
    "sg:classifiers":[
        {
            "category":"Personal",
            "subcategory":"Beauty Salon",
            "type":"Services"
        }
    ],
    "sg:phone":"+1 212 879 5257",
    "sg:postcode":"10021",
    "sg:province":"NY",
    "sg:tags":[
        "eyelash"
    ],
    "sg:website":"www.karinafreedman.com",
    "wof:name":"Karina Freedman",
    "wof:placetype":"venue"
},
  "geometry": {"coordinates":[-73.962664,40.773414],"type":"Point"}
}