{
  "type": "Feature",
  "properties": {
    "addr:full":"385 W Merrick Rd Valley Stream NY 11580",
    "addr:housenumber":"385",
    "addr:postcode":"11580",
    "addr:street":"W Merrick Rd",
    "iso:country":"US",
    "sg:address":"385 W Merrick Rd",
    "sg:city":"Valley Stream",
    "sg:classifiers":[
        {
            "category":"Retail",
            "subcategory":"Auto Repair",
            "type":"Services"
        }
    ],
    "sg:phone":"+1 516 825 9579",
    "sg:postcode":"11580",
    "sg:province":"NY",
    "wof:name":"Nor Stream Svcs Station Llc",
    "wof:placetype":"venue"
},
  "geometry": {"coordinates":[-73.711517,40.668524],"type":"Point"}
}