{
  "type": "Feature",
  "properties": {
    "iso:country":"US",
    "sg:address":"197 S Broadway",
    "sg:city":"Yonkers",
    "sg:classifiers":[
        {
            "category":"Professional",
            "subcategory":"Detective & Security Services",
            "type":"Services"
        }
    ],
    "sg:phone":"+1 914 207 1400",
    "sg:postcode":"10705",
    "sg:province":"NY",
    "sg:tags":[
        "information",
        "bureau"
    ],
    "wof:name":"Padrito Mechanic Svcs",
    "wof:placetype":"venue"
},
  "geometry": {"coordinates":[-73.895506,40.925099],"type":"Point"}
}