{
  "type": "Feature",
  "properties": {
    "addr:full":"2139 Broadway New York NY 10023",
    "addr:housenumber":"2139",
    "addr:postcode":"10023",
    "addr:street":"Broadway",
    "iso:country":"US",
    "sg:address":"2139 Broadway",
    "sg:city":"New York",
    "sg:classifiers":[
        {
            "category":"Banks & Credit Unions",
            "subcategory":"Bank",
            "type":"Services"
        },
        {
            "category":"Banks & Credit Unions",
            "subcategory":"Financial Services",
            "type":"Services"
        }
    ],
    "sg:phone":"+1 212 799 9357",
    "sg:postcode":"10023",
    "sg:province":"NY",
    "sg:tags":[
        "broker",
        "mortgage"
    ],
    "wof:name":"Washington Mutual",
    "wof:placetype":"venue"
},
  "geometry": {"coordinates":[-73.98146699999999,40.781333],"type":"Point"}
}