{
  "type": "Feature",
  "properties": {
    "iso:country":"US",
    "sg:address":"685 Flatbush Ave",
    "sg:city":"Brooklyn",
    "sg:classifiers":[
        {
            "category":"Restaurant",
            "type":"Food & Drink"
        }
    ],
    "sg:phone":"+1 718 856 2945",
    "sg:postcode":"11225",
    "sg:province":"NY",
    "sg:tags":[
        "caterer"
    ],
    "wof:name":"Sahara West India",
    "wof:placetype":"venue"
},
  "geometry": {"coordinates":[-73.959861,40.655635],"type":"Point"}
}