{
  "type": "Feature",
  "properties": {
    "addr:full":"27 Whitehall St New York NY 10004",
    "addr:housenumber":"27",
    "addr:postcode":"10004",
    "addr:street":"Whitehall St",
    "iso:country":"US",
    "sg:address":"27 Whitehall St",
    "sg:city":"New York",
    "sg:classifiers":[
        {
            "category":"Professional",
            "type":"Services"
        },
        {
            "category":"Food & Beverages",
            "subcategory":"Bakery",
            "type":"Retail Goods"
        }
    ],
    "sg:phone":"+1 212 269 6100",
    "sg:postcode":"10004",
    "sg:province":"NY",
    "sg:tags":[
        "sandwich",
        "caterer"
    ],
    "sg:website":"www.flavorsnyc.com",
    "wof:name":"Flavors",
    "wof:placetype":"venue"
},
  "geometry": {"coordinates":[-74.01307799999999,40.703522],"type":"Point"}
}