{
  "type": "Feature",
  "properties": {
    "iso:country":"US",
    "sg:address":"230 Bow Dr",
    "sg:city":"Hauppauge",
    "sg:classifiers":[
        {
            "category":"Professional",
            "subcategory":"Computer Services",
            "type":"Services"
        }
    ],
    "sg:phone":"+1   ",
    "sg:postcode":"11788",
    "sg:province":"NY",
    "sg:tags":[
        "programing",
        "custom"
    ],
    "wof:name":"Tech Systems International",
    "wof:placetype":"venue"
},
  "geometry": {"coordinates":[-73.176393,40.836274],"type":"Point"}
}