{
  "type": "Feature",
  "properties": {
    "iso:country":"US",
    "sg:address":"5155 Sheridan Dr",
    "sg:city":"Buffalo",
    "sg:classifiers":[
        {
            "category":"Retail",
            "subcategory":"Veterinary Services",
            "type":"Services"
        }
    ],
    "sg:phone":"+1 716 633 7123",
    "sg:postcode":"14221",
    "sg:province":"NY",
    "sg:tags":[
        "veterinarian"
    ],
    "wof:name":"Georgetown Small Animal Clinic",
    "wof:placetype":"venue"
},
  "geometry": {"coordinates":[-78.74102000000001,42.978491],"type":"Point"}
}