{
  "type": "Feature",
  "properties": {
    "addr:full":"4010 Erieville Rd Cazenovia NY 13061",
    "addr:housenumber":"4010",
    "addr:postcode":"13061",
    "addr:street":"Erieville Rd",
    "iso:country":"US",
    "sg:address":"4010 Erieville Rd",
    "sg:city":"Cazenovia",
    "sg:classifiers":[
        {
            "category":"Wholesale",
            "subcategory":"Durable Goods & Equipment",
            "type":"Manufacturing & Wholesale Goods"
        }
    ],
    "sg:phone":"+1 315 655 2146",
    "sg:postcode":"13061",
    "sg:province":"NY",
    "wof:name":"Alexandras Attic Alexand",
    "wof:placetype":"venue"
},
  "geometry": {"coordinates":[-75.77652,42.917092],"type":"Point"}
}