{
  "type": "Feature",
  "properties": {
    "iso:country":"US",
    "sg:address":"19 W 24th St",
    "sg:city":"New York",
    "sg:classifiers":[
        {
            "category":"Restaurant",
            "type":"Food & Drink"
        }
    ],
    "sg:phone":"+1   ",
    "sg:postcode":"10010",
    "sg:province":"NY",
    "wof:name":"Cutting Room LLC",
    "wof:placetype":"venue"
},
  "geometry": {"coordinates":[-73.992318,40.743567],"type":"Point"}
}