{
  "type": "Feature",
  "properties": {
    "addr:full":"1650 Elmwood Ave Rochester NY 14620",
    "addr:housenumber":"1650",
    "addr:postcode":"14620",
    "addr:street":"Elmwood Ave",
    "iso:country":"US",
    "sg:address":"1650 Elmwood Ave",
    "sg:city":"Rochester",
    "sg:classifiers":[
        {
            "category":"Health Services",
            "subcategory":"Doctor",
            "type":"Services"
        }
    ],
    "sg:phone":"+1 585 473 8309",
    "sg:postcode":"14620",
    "sg:province":"NY",
    "sg:tags":[
        "medical"
    ],
    "wof:name":"Robert C McVeigh MD PC",
    "wof:placetype":"venue"
},
  "geometry": {"coordinates":[-77.594658,43.125557],"type":"Point"}
}