{
  "type": "Feature",
  "properties": {
    "iso:country":"US",
    "sg:address":"7803 3rd Ave",
    "sg:city":"Brooklyn",
    "sg:classifiers":[
        {
            "category":"Restaurant",
            "type":"Food & Drink"
        }
    ],
    "sg:menulink":"http://www.allmenus.com/ny/brooklyn/52501-daruma-japanese-cuisine/menu/",
    "sg:phone":"+1 718 833 8818",
    "sg:postcode":"11209",
    "sg:province":"NY",
    "sg:tags":[
        "sushi",
        "japanese",
        "asian"
    ],
    "wof:name":"Daruma Japanese Cuisine",
    "wof:placetype":"venue"
},
  "geometry": {"coordinates":[-74.02870799999999,40.629163],"type":"Point"}
}