{
  "type": "Feature",
  "properties": {
    "iso:country":"US",
    "sg:address":"3432 E Tremont Ave",
    "sg:city":"Bronx",
    "sg:classifiers":[
        {
            "category":"Banks & Credit Unions",
            "subcategory":"Investment Brokerage",
            "type":"Services"
        }
    ],
    "sg:phone":"+1 718 822 2006",
    "sg:postcode":"10465",
    "sg:province":"NY",
    "sg:tags":[
        "advisory",
        "financial"
    ],
    "wof:name":"Global Financial Ctr",
    "wof:placetype":"venue"
},
  "geometry": {"coordinates":[-73.828003,40.832721],"type":"Point"}
}