{
  "type": "Feature",
  "properties": {
    "addr:full":"2390 Grand Concourse Bronx NY 10458",
    "addr:housenumber":"2390",
    "addr:postcode":"10458",
    "addr:street":"Grand Concourse",
    "iso:country":"US",
    "sg:address":"2390 Grand Concourse",
    "sg:city":"Bronx",
    "sg:classifiers":[
        {
            "category":"Home & Garden",
            "subcategory":"Furniture",
            "type":"Retail Goods"
        }
    ],
    "sg:phone":"+1 718 584 3600",
    "sg:postcode":"10458",
    "sg:province":"NY",
    "wof:name":"My Furniture",
    "wof:placetype":"venue"
},
  "geometry": {"coordinates":[-73.89836,40.85993],"type":"Point"}
}