{
  "type": "Feature",
  "properties": {
    "addr:full":"220 Hudson St Cornwall On Hudson NY 12520",
    "addr:housenumber":"220",
    "addr:postcode":"12520",
    "addr:street":"Hudson St",
    "iso:country":"US",
    "sg:address":"220 Hudson St",
    "sg:city":"Cornwall On Hudson",
    "sg:classifiers":[
        {
            "category":"Shopping",
            "subcategory":"Hobbies, Toys, & Games",
            "type":"Retail Goods"
        }
    ],
    "sg:phone":"+1   ",
    "sg:postcode":"12520",
    "sg:province":"NY",
    "wof:name":"Crafters Den",
    "wof:placetype":"venue"
},
  "geometry": {"coordinates":[-74.012677,41.444109],"type":"Point"}
}