{
  "type": "Feature",
  "properties": {
    "iso:country":"US",
    "sg:address":"32 W 28 St",
    "sg:city":"New York",
    "sg:classifiers":[
        {
            "category":"Shopping",
            "subcategory":"Clothing, Apparel, & Fashions",
            "type":"Retail Goods"
        }
    ],
    "sg:phone":"+1 212 725 8692",
    "sg:postcode":"10001",
    "sg:province":"NY",
    "wof:name":"A & M Sports Wear Corp",
    "wof:placetype":"venue"
},
  "geometry": {"coordinates":[-73.990346,40.745857],"type":"Point"}
}