{
  "type": "Feature",
  "properties": {
    "iso:country":"US",
    "sg:address":"26 Old Mill Rd",
    "sg:city":"Great Neck",
    "sg:classifiers":[
        {
            "category":"Restaurant",
            "type":"Food & Drink"
        }
    ],
    "sg:phone":"+1   ",
    "sg:postcode":"11023",
    "sg:province":"NY",
    "sg:tags":[
        "caterer"
    ],
    "sg:website":"www.prestigecaterers.com",
    "wof:name":"Prestige Caterers",
    "wof:placetype":"venue"
},
  "geometry": {"coordinates":[-73.73961799999999,40.796547],"type":"Point"}
}