{
  "type": "Feature",
  "properties": {
    "iso:country":"US",
    "sg:address":"3370 Prince St Ste 705",
    "sg:city":"Flushing",
    "sg:classifiers":[
        {
            "category":"Insurance",
            "subcategory":"Health Insurance",
            "type":"Services"
        }
    ],
    "sg:phone":"+1 718 939 5150",
    "sg:postcode":"11354",
    "sg:province":"NY",
    "sg:tags":[
        "market"
    ],
    "wof:name":"Green World",
    "wof:placetype":"venue"
},
  "geometry": {"coordinates":[-73.83339700000001,40.764801],"type":"Point"}
}