{
  "type": "Feature",
  "properties": {
    "addr:full":"28 Tec St Hicksville NY 11801",
    "addr:postcode":"11801",
    "addr:street":"Tec St",
    "iso:country":"US",
    "sg:address":"28 Tec St",
    "sg:city":"Hicksville",
    "sg:classifiers":[
        {
            "category":"Professional",
            "subcategory":"Business Services",
            "type":"Services"
        },
        {
            "category":"Recreation",
            "type":"Entertainment"
        }
    ],
    "sg:phone":"+1 516 610 8115",
    "sg:postcode":"11801",
    "sg:province":"NY",
    "sg:tags":[
        "active",
        "life",
        "relation",
        "public"
    ],
    "sg:website":"www.andgosports.com",
    "wof:name":"andGo Sports",
    "wof:placetype":"venue"
},
  "geometry": {"coordinates":[-73.544072,40.757936],"type":"Point"}
}