{
  "type": "Feature",
  "properties": {
    "addr:full":"224 Sherwood Ave Farmingdale NY 11735",
    "addr:housenumber":"224",
    "addr:postcode":"11735",
    "addr:street":"Sherwood Ave",
    "iso:country":"US",
    "sg:address":"224 Sherwood Ave",
    "sg:city":"Farmingdale",
    "sg:classifiers":[
        {
            "category":"Wholesale",
            "subcategory":"Groceries",
            "type":"Manufacturing & Wholesale Goods"
        }
    ],
    "sg:phone":"+1 631 293 3501",
    "sg:postcode":"11735",
    "sg:province":"NY",
    "sg:tags":[
        "beverage"
    ],
    "sg:website":"www.thebeverageworks.com",
    "wof:name":"Beverage Works",
    "wof:placetype":"venue"
},
  "geometry": {"coordinates":[-73.41851800000001,40.744401],"type":"Point"}
}