{
  "type": "Feature",
  "properties": {
    "addr:full":"12 Rolling Wood Ln Hampton Bays NY 11946",
    "addr:housenumber":"12",
    "addr:postcode":"11946",
    "addr:street":"Rolling Wood Ln",
    "iso:country":"US",
    "sg:address":"12 Rolling Wood Ln",
    "sg:city":"Hampton Bays",
    "sg:classifiers":[
        {
            "category":"Building & Trades",
            "subcategory":"Construction",
            "type":"Services"
        }
    ],
    "sg:phone":"+1 631 723 2020",
    "sg:postcode":"11946",
    "sg:province":"NY",
    "sg:tags":[
        "excavating",
        "contractor"
    ],
    "wof:name":"Micro Machines Excavating Inc",
    "wof:placetype":"venue"
},
  "geometry": {"coordinates":[-72.526966,40.885992],"type":"Point"}
}