{
  "type": "Feature",
  "properties": {
    "addr:full":"521 Fifth Ave 17th Fl New York NY 10175",
    "addr:housenumber":"521",
    "addr:postcode":"10175",
    "addr:street":"Fifth Ave 17Th Fl",
    "iso:country":"US",
    "sg:address":"521 Fifth Ave 17th Fl",
    "sg:city":"New York",
    "sg:classifiers":[
        {
            "category":"Professional",
            "subcategory":"Lawyer & Legal Services",
            "type":"Services"
        }
    ],
    "sg:phone":"+1 212 292 4233",
    "sg:postcode":"10175",
    "sg:province":"NY",
    "sg:website":"www.lawrodriguez.com/",
    "wof:name":"The Rodriguez Law Firm",
    "wof:placetype":"venue"
},
  "geometry": {"coordinates":[-73.97980699999999,40.754168],"type":"Point"}
}