{
  "type": "Feature",
  "properties": {
    "iso:country":"US",
    "sg:address":"41 Beers Dr",
    "sg:city":"Middletown",
    "sg:classifiers":[
        {
            "category":"Building & Trades",
            "subcategory":"Construction",
            "type":"Services"
        }
    ],
    "sg:phone":"+1 845 342 2986",
    "sg:postcode":"10940",
    "sg:province":"NY",
    "sg:tags":[
        "house"
    ],
    "wof:name":"Guys Gunthers",
    "wof:placetype":"venue"
},
  "geometry": {"coordinates":[-74.410471,41.438441],"type":"Point"}
}