{
  "type": "Feature",
  "properties": {
    "iso:country":"US",
    "sg:address":"4853 W Henrietta Rd",
    "sg:city":"Henrietta",
    "sg:classifiers":[
        {
            "category":"Bars & Pubs",
            "type":"Food & Drink"
        }
    ],
    "sg:phone":"+1   ",
    "sg:postcode":"14467",
    "sg:province":"NY",
    "sg:website":"www.roostcountry.com",
    "wof:name":"Roost Country Showcase",
    "wof:placetype":"venue"
},
  "geometry": {"coordinates":[-77.65279200000001,43.058437],"type":"Point"}
}