{
  "type": "Feature",
  "properties": {
    "addr:full":"2412 Ocean Ave Brooklyn NY 11229",
    "addr:housenumber":"2412",
    "addr:postcode":"11229",
    "addr:street":"Ocean Ave",
    "iso:country":"US",
    "sg:address":"2412 Ocean Ave",
    "sg:city":"Brooklyn",
    "sg:classifiers":[
        {
            "category":"Health Services",
            "subcategory":"Doctor",
            "type":"Services"
        }
    ],
    "sg:phone":"+1 718 616 0385",
    "sg:postcode":"11229",
    "sg:province":"NY",
    "sg:tags":[
        "medical"
    ],
    "wof:name":"Victor Navarro",
    "wof:placetype":"venue"
},
  "geometry": {"coordinates":[-73.952135,40.60318],"type":"Point"}
}