{
  "type": "Feature",
  "properties": {
    "iso:country":"US",
    "sg:address":"98 Grand St",
    "sg:city":"Newburgh",
    "sg:classifiers":[
        {
            "category":"Organizations",
            "subcategory":"Religious Organization",
            "type":"Services"
        }
    ],
    "sg:phone":"+1 845 562 7920",
    "sg:postcode":"12550",
    "sg:province":"NY",
    "wof:name":"Ecclesia Ministries Of Newburgh",
    "wof:placetype":"venue"
},
  "geometry": {"coordinates":[-74.253936,41.502566],"type":"Point"}
}