{
  "type": "Feature",
  "properties": {
    "addr:full":"PO Box 1407 Selden NY 11784",
    "addr:housenumber":"po",
    "addr:postcode":"1407;11784",
    "addr:street":"Box",
    "iso:country":"US",
    "sg:address":"PO Box 1407",
    "sg:city":"Selden",
    "sg:classifiers":[
        {
            "category":"Real Estate",
            "subcategory":"Real Estate Operator",
            "type":"Services"
        },
        {
            "category":"Building & Trades",
            "subcategory":"Pest Control",
            "type":"Services"
        }
    ],
    "sg:phone":"+1 631 744 2500",
    "sg:postcode":"11784",
    "sg:province":"NY",
    "sg:tags":[
        "apartment"
    ],
    "wof:name":"Frontier Exterminating Co",
    "wof:placetype":"venue"
},
  "geometry": {"coordinates":[-73.047798,40.871799],"type":"Point"}
}