{
  "type": "Feature",
  "properties": {
    "iso:country":"US",
    "sg:address":"1756 Forest Ave",
    "sg:city":"Staten Island",
    "sg:classifiers":[
        {
            "category":"Coffee & Tea",
            "type":"Food & Drink"
        }
    ],
    "sg:menulink":"http://www.allmenus.com/ny/staten-island/113583-starbucks-coffee/menu/",
    "sg:phone":"+1 718 697 0293",
    "sg:postcode":"10303",
    "sg:province":"NY",
    "sg:tags":[
        "american"
    ],
    "wof:name":"Starbucks Coffee",
    "wof:placetype":"venue"
},
  "geometry": {"coordinates":[-74.14730299999999,40.624905],"type":"Point"}
}