{
  "type": "Feature",
  "properties": {
    "addr:full":"461 Timpson Pl Bronx NY 10455",
    "addr:housenumber":"461",
    "addr:postcode":"10455",
    "addr:street":"Timpson Pl",
    "iso:country":"US",
    "sg:address":"461 Timpson Pl",
    "sg:city":"Bronx",
    "sg:classifiers":[
        {
            "category":"Wholesale",
            "subcategory":"Hardware",
            "type":"Manufacturing & Wholesale Goods"
        }
    ],
    "sg:phone":"+1 718 402 9765",
    "sg:postcode":"10455",
    "sg:province":"NY",
    "sg:tags":[
        "equipment",
        "heating",
        "system"
    ],
    "wof:name":"Mechanical Heating Supply",
    "wof:placetype":"venue"
},
  "geometry": {"coordinates":[-73.905545,40.810178],"type":"Point"}
}