{
  "type": "Feature",
  "properties": {
    "addr:full":"215 Western Ave Albany NY 12203",
    "addr:housenumber":"215",
    "addr:postcode":"12203",
    "addr:street":"Western Ave",
    "iso:country":"US",
    "sg:address":"215 Western Ave",
    "sg:city":"Albany",
    "sg:classifiers":[
        {
            "category":"Restaurant",
            "type":"Food & Drink"
        }
    ],
    "sg:menulink":"http://www.allmenus.com/ny/albany/30055-dcarlito-pizza/menu/",
    "sg:phone":"+1 518 463 0054",
    "sg:postcode":"12203",
    "sg:province":"NY",
    "sg:tags":[
        "american",
        "pizza"
    ],
    "wof:name":"D'Carlito Pizza",
    "wof:placetype":"venue"
},
  "geometry": {"coordinates":[-73.77676700000001,42.662027],"type":"Point"}
}