{
  "type": "Feature",
  "properties": {
    "iso:country":"US",
    "sg:address":"31 Allen Blvd",
    "sg:city":"Farmingdale",
    "sg:classifiers":[
        {
            "category":"Wholesale",
            "subcategory":"Stationery",
            "type":"Manufacturing & Wholesale Goods"
        },
        {
            "category":"Manufacturing",
            "subcategory":"Printing",
            "type":"Manufacturing & Wholesale Goods"
        }
    ],
    "sg:phone":"+1 631 753 2630",
    "sg:postcode":"11735",
    "sg:province":"NY",
    "sg:tags":[
        "lithographic",
        "printer",
        "commercial",
        "form",
        "supply"
    ],
    "sg:website":"www.commandbp.com",
    "wof:name":"Command Business Products Inc",
    "wof:placetype":"venue"
},
  "geometry": {"coordinates":[-73.425712,40.715497],"type":"Point"}
}