{
  "type": "Feature",
  "properties": {
    "addr:full":"380 Broadway Frnt 1 New York NY 10013",
    "addr:housenumber":"380;1",
    "addr:postcode":"10013",
    "addr:street":"Broadway Frnt",
    "iso:country":"US",
    "sg:address":"380 Broadway Frnt 1",
    "sg:city":"New York",
    "sg:classifiers":[
        {
            "category":"Sports & Exercise",
            "subcategory":"Bicycle Rental",
            "type":"Entertainment"
        }
    ],
    "sg:phone":"+1 212 397 4228",
    "sg:postcode":"10013",
    "sg:province":"NY",
    "sg:tags":[
        "wear"
    ],
    "wof:name":"Blues",
    "wof:placetype":"venue"
},
  "geometry": {"coordinates":[-73.86711699999999,40.681373],"type":"Point"}
}