{
  "type": "Feature",
  "properties": {
    "iso:country":"US",
    "sg:address":"12426 Queens Blvd",
    "sg:city":"Kew Gardens",
    "sg:classifiers":[
        {
            "category":"Professional",
            "subcategory":"Employment Agencies",
            "type":"Services"
        }
    ],
    "sg:phone":"+1 800 276 5069",
    "sg:postcode":"11415",
    "sg:province":"NY",
    "wof:name":"Court Employment Project Inc",
    "wof:placetype":"venue"
},
  "geometry": {"coordinates":[-73.827265,40.712494],"type":"Point"}
}