{
  "type": "Feature",
  "properties": {
    "iso:country":"US",
    "sg:address":"208 E Yates St",
    "sg:city":"Ithaca",
    "sg:classifiers":[
        {
            "category":"Manufacturing",
            "subcategory":"Buildings",
            "type":"Manufacturing & Wholesale Goods"
        },
        {
            "category":"Building & Trades",
            "subcategory":"Construction",
            "type":"Services"
        }
    ],
    "sg:phone":"+1 607 273 3428",
    "sg:postcode":"14850",
    "sg:province":"NY",
    "sg:tags":[
        "roofing",
        "industrial",
        "builder",
        "contractor",
        "contractors-commercial",
        "home"
    ],
    "wof:name":"Aztec Building Co",
    "wof:placetype":"venue"
},
  "geometry": {"coordinates":[-76.498211,42.447264],"type":"Point"}
}