{
  "type": "Feature",
  "properties": {
    "iso:country":"US",
    "sg:address":"1484 Williamsbridge Rd",
    "sg:city":"Bronx",
    "sg:classifiers":[
        {
            "category":"Wholesale",
            "subcategory":"Non-durable Goods",
            "type":"Manufacturing & Wholesale Goods"
        }
    ],
    "sg:phone":"+1 718 823 2720",
    "sg:postcode":"10461",
    "sg:province":"NY",
    "wof:name":"Distinguished Diagnostic Imgng",
    "wof:placetype":"venue"
},
  "geometry": {"coordinates":[-73.84623499999999,40.84449],"type":"Point"}
}