{
  "type": "Feature",
  "properties": {
    "addr:full":"3515 Eastchester Rd Bronx NY 10469",
    "addr:housenumber":"3515",
    "addr:postcode":"10469",
    "addr:street":"Eastchester Rd",
    "iso:country":"US",
    "sg:address":"3515 Eastchester Rd",
    "sg:city":"Bronx",
    "sg:classifiers":[
        {
            "category":"Health Services",
            "subcategory":"Clinic",
            "type":"Services"
        }
    ],
    "sg:phone":"+1 718 944 1776",
    "sg:postcode":"10469",
    "sg:province":"NY",
    "wof:name":"Balm Of Giled Home Care Agency",
    "wof:placetype":"venue"
},
  "geometry": {"coordinates":[-73.847674,40.87924],"type":"Point"}
}