{
  "type": "Feature",
  "properties": {
    "addr:full":"7 Littleworth Ln Sea Cliff NY 11579",
    "addr:housenumber":"7",
    "addr:postcode":"11579",
    "addr:street":"Littleworth Ln",
    "iso:country":"US",
    "sg:address":"7 Littleworth Ln",
    "sg:city":"Sea Cliff",
    "sg:classifiers":[
        {
            "category":"Shopping",
            "subcategory":"Florist",
            "type":"Retail Goods"
        }
    ],
    "sg:phone":"+1 516 671 8973",
    "sg:postcode":"11579",
    "sg:province":"NY",
    "wof:name":"Jill Chaffin Floral Designs",
    "wof:placetype":"venue"
},
  "geometry": {"coordinates":[-73.636399,40.847063],"type":"Point"}
}