{
  "type": "Feature",
  "properties": {
    "addr:full":"2316 Arthur Ave Bronx NY 10458",
    "addr:housenumber":"2316",
    "addr:postcode":"10458",
    "addr:street":"Arthur Ave",
    "iso:country":"US",
    "sg:address":"2316 Arthur Ave",
    "sg:city":"Bronx",
    "sg:classifiers":[
        {
            "category":"Restaurant",
            "type":"Food & Drink"
        }
    ],
    "sg:menulink":"http://www.allmenus.com/ny/bronx/53383-subway/menu/",
    "sg:phone":"+1 718 562 4495",
    "sg:postcode":"10458",
    "sg:province":"NY",
    "sg:tags":[
        "american",
        "sandwich"
    ],
    "wof:name":"Subway",
    "wof:placetype":"venue"
},
  "geometry": {"coordinates":[-73.888204,40.854846],"type":"Point"}
}