{
  "type": "Feature",
  "properties": {
    "addr:full":"2 Oak Ave Chautauqua NY 14722",
    "addr:housenumber":"2",
    "addr:postcode":"14722",
    "addr:street":"Oak Ave",
    "iso:country":"US",
    "sg:address":"2 Oak Ave",
    "sg:city":"Chautauqua",
    "sg:classifiers":[
        {
            "category":"Banks & Credit Unions",
            "subcategory":"Bank",
            "type":"Services"
        }
    ],
    "sg:phone":"+1 716 357 9724",
    "sg:postcode":"14722",
    "sg:province":"NY",
    "wof:name":"Mellon Bank",
    "wof:placetype":"venue"
},
  "geometry": {"coordinates":[-79.472365,42.214918],"type":"Point"}
}