{
  "type": "Feature",
  "properties": {
    "addr:full":"44 Donovan St Webster NY 14580",
    "addr:housenumber":"44",
    "addr:postcode":"14580",
    "addr:street":"Donovan St",
    "iso:country":"US",
    "sg:address":"44 Donovan St",
    "sg:city":"Webster",
    "sg:classifiers":[
        {
            "category":"Professional",
            "subcategory":"Engineering",
            "type":"Services"
        },
        {
            "category":"Building & Trades",
            "subcategory":"Plumbing",
            "type":"Services"
        },
        {
            "category":"Home & Garden",
            "subcategory":"Building Materials",
            "type":"Retail Goods"
        },
        {
            "category":"Building & Trades",
            "subcategory":"Construction",
            "type":"Services"
        }
    ],
    "sg:phone":"+1 585 872 4420",
    "sg:postcode":"14580",
    "sg:province":"NY",
    "sg:tags":[
        "system",
        "specialty",
        "heating",
        "equipment",
        "clean",
        "contractor",
        "air conditioning",
        "boilers-repair"
    ],
    "sg:website":"http://find.trane.com/tcs-dealer-412313?utm_source=YP&utm_medium=banner&utm_campaign=TL",
    "wof:name":"Crossfield Heating And Air Conditioning",
    "wof:placetype":"venue"
},
  "geometry": {"coordinates":[-77.42921,43.218602],"type":"Point"}
}