{
  "type": "Feature",
  "properties": {
    "addr:full":"158 Gramatan Ave Mt Vernon NY 10550",
    "addr:housenumber":"158",
    "addr:postcode":"10550",
    "addr:street":"Gramatan Ave",
    "iso:country":"US",
    "sg:address":"158 Gramatan Ave",
    "sg:city":"Mt Vernon",
    "sg:classifiers":[
        {
            "category":"Social Services",
            "type":"Services"
        }
    ],
    "sg:phone":"+1 914 663 4619",
    "sg:postcode":"10550",
    "sg:province":"NY",
    "sg:tags":[
        "counselor",
        "marriage",
        "family"
    ],
    "wof:name":"MHA Of Westchester",
    "wof:placetype":"venue"
},
  "geometry": {"coordinates":[-73.837513,40.915399],"type":"Point"}
}