{
  "type": "Feature",
  "properties": {
    "iso:country":"US",
    "sg:address":"99 Grattan St",
    "sg:city":"Brooklyn",
    "sg:classifiers":[
        {
            "category":"Personal",
            "type":"Services"
        }
    ],
    "sg:phone":"+1 407 399 4211",
    "sg:postcode":"11237",
    "sg:province":"NY",
    "sg:tags":[
        "mover"
    ],
    "wof:name":"Sweet Lou's Man With a Van",
    "wof:placetype":"venue"
},
  "geometry": {"coordinates":[-73.92918899999999,40.706263],"type":"Point"}
}