{
  "type": "Feature",
  "properties": {
    "addr:full":"949 Armory Dr Utica NY 13501",
    "addr:housenumber":"949",
    "addr:postcode":"13501",
    "addr:street":"Armory Dr",
    "iso:country":"US",
    "sg:address":"949 Armory Dr",
    "sg:city":"Utica",
    "sg:classifiers":[
        {
            "category":"Manufacturing",
            "subcategory":"Printing",
            "type":"Manufacturing & Wholesale Goods"
        }
    ],
    "sg:phone":"+1   ",
    "sg:postcode":"13501",
    "sg:province":"NY",
    "sg:tags":[
        "commercial"
    ],
    "wof:name":"Imagic",
    "wof:placetype":"venue"
},
  "geometry": {"coordinates":[-75.218211,43.080515],"type":"Point"}
}