{
  "type": "Feature",
  "properties": {
    "iso:country":"US",
    "sg:address":"24 Seth Canyon Dr",
    "sg:city":"Mount Kisco",
    "sg:classifiers":[
        {
            "category":"Building & Trades",
            "subcategory":"Construction",
            "type":"Services"
        }
    ],
    "sg:phone":"+1 914 241 2127",
    "sg:postcode":"10549",
    "sg:province":"NY",
    "sg:tags":[
        "carpentry",
        "contractor"
    ],
    "wof:name":"Creative Carpentry Inc",
    "wof:placetype":"venue"
},
  "geometry": {"coordinates":[-73.74323099999999,41.232462],"type":"Point"}
}