{
  "type": "Feature",
  "properties": {
    "addr:full":"9 Castle Point Rd Wappingers Falls NY 12590",
    "addr:housenumber":"9",
    "addr:postcode":"12590",
    "addr:street":"Castle Point Rd",
    "iso:country":"US",
    "sg:address":"9 Castle Point Rd",
    "sg:city":"Wappingers Falls",
    "sg:classifiers":[
        {
            "category":"Health Services",
            "subcategory":"Hospital",
            "type":"Services"
        }
    ],
    "sg:phone":"+1 845 831 2000",
    "sg:postcode":"12590",
    "sg:province":"NY",
    "wof:name":"V A Hudson Valley",
    "wof:placetype":"venue"
},
  "geometry": {"coordinates":[-73.960162,41.539963],"type":"Point"}
}