{
  "type": "Feature",
  "properties": {
    "addr:full":"72 Wellbrook Ave Staten Island NY 10314",
    "addr:housenumber":"72",
    "addr:postcode":"10314",
    "addr:street":"Wellbrook Ave",
    "iso:country":"US",
    "sg:address":"72 Wellbrook Ave",
    "sg:city":"Staten Island",
    "sg:classifiers":[
        {
            "category":"Professional",
            "type":"Services"
        }
    ],
    "sg:phone":"+1 718 698 2894",
    "sg:postcode":"10314",
    "sg:province":"NY",
    "wof:name":"St Vincents Svc",
    "wof:placetype":"venue"
},
  "geometry": {"coordinates":[-74.130544,40.602833],"type":"Point"}
}