{
  "type": "Feature",
  "properties": {
    "addr:full":"49 Ludlow Street New York NY 10002",
    "addr:housenumber":"49",
    "addr:postcode":"10002",
    "addr:street":"Ludlow Street",
    "iso:country":"US",
    "sg:address":"49 Ludlow Street",
    "sg:city":"New York",
    "sg:classifiers":[
        {
            "category":"Food & Beverages",
            "subcategory":"Meat & Fish",
            "type":"Retail Goods"
        }
    ],
    "sg:phone":"+1 212 431 6256",
    "sg:postcode":"10002",
    "sg:province":"NY",
    "sg:tags":[
        "seafood",
        "market"
    ],
    "wof:name":"Michael's Seafood",
    "wof:placetype":"venue"
},
  "geometry": {"coordinates":[-73.99022100000001,40.716458],"type":"Point"}
}