{
  "type": "Feature",
  "properties": {
    "addr:full":"491 E 166th St Bronx NY 10456",
    "addr:housenumber":"491",
    "addr:postcode":"10456",
    "addr:street":"E 166Th St",
    "iso:country":"US",
    "sg:address":"491 E 166th St",
    "sg:city":"Bronx",
    "sg:classifiers":[
        {
            "category":"Building & Trades",
            "subcategory":"Electrical",
            "type":"Services"
        }
    ],
    "sg:phone":"+1 718 585 4100",
    "sg:postcode":"10456",
    "sg:province":"NY",
    "sg:tags":[
        "electrical",
        "contractor"
    ],
    "wof:name":"G S H Electric Inc",
    "wof:placetype":"venue"
},
  "geometry": {"coordinates":[-73.90755299999999,40.828002],"type":"Point"}
}