{
  "type": "Feature",
  "properties": {
    "iso:country":"US",
    "sg:address":"184 Broadway",
    "sg:city":"Bethpage",
    "sg:classifiers":[
        {
            "category":"Travel",
            "subcategory":"Travel Agent",
            "type":"Entertainment"
        }
    ],
    "sg:phone":"+1   ",
    "sg:postcode":"11714",
    "sg:province":"NY",
    "sg:tags":[
        "agency"
    ],
    "wof:name":"Elite Travel",
    "wof:placetype":"venue"
},
  "geometry": {"coordinates":[-73.47952600000001,40.738122],"type":"Point"}
}