{
  "type": "Feature",
  "properties": {
    "iso:country":"US",
    "sg:address":"15 Tappan Dr",
    "sg:city":"Melville",
    "sg:classifiers":[
        {
            "category":"Professional",
            "subcategory":"Detective & Security Services",
            "type":"Services"
        }
    ],
    "sg:phone":"+1 631 549 0994",
    "sg:postcode":"11747",
    "sg:province":"NY",
    "sg:tags":[
        "investigator"
    ],
    "wof:name":"De Veux Investigations Inc",
    "wof:placetype":"venue"
},
  "geometry": {"coordinates":[-73.416405,40.813275],"type":"Point"}
}