{
  "type": "Feature",
  "properties": {
    "addr:full":"210 E 64th St New York NY 10021",
    "addr:housenumber":"210",
    "addr:postcode":"10021",
    "addr:street":"E 64Th St",
    "iso:country":"US",
    "sg:address":"210 E 64th St",
    "sg:city":"New York",
    "sg:classifiers":[
        {
            "category":"Health Services",
            "subcategory":"Hospital",
            "type":"Services"
        }
    ],
    "sg:phone":"+1 212 838 9200",
    "sg:postcode":"10021",
    "sg:province":"NY",
    "wof:name":"Manhattan Eye Ear & Throat Hospital",
    "wof:placetype":"venue"
},
  "geometry": {"coordinates":[-73.96410400000001,40.764599],"type":"Point"}
}