{
  "type": "Feature",
  "properties": {
    "addr:full":"199 Sherman Ave New York NY 10034",
    "addr:housenumber":"199",
    "addr:postcode":"10034",
    "addr:street":"Sherman Ave",
    "iso:country":"US",
    "sg:address":"199 Sherman Ave",
    "sg:city":"New York",
    "sg:classifiers":[
        {
            "category":"Personal",
            "subcategory":"Barber",
            "type":"Services"
        }
    ],
    "sg:phone":"+1 212 544 8660",
    "sg:postcode":"10034",
    "sg:province":"NY",
    "sg:tags":[
        "shop"
    ],
    "wof:name":"Diaz Barber Shop",
    "wof:placetype":"venue"
},
  "geometry": {"coordinates":[-73.921204,40.865299],"type":"Point"}
}