{
  "type": "Feature",
  "properties": {
    "addr:full":"2234 Chili Ave Rochester NY 14624",
    "addr:housenumber":"2234",
    "addr:postcode":"14624",
    "addr:street":"Chili Ave",
    "iso:country":"US",
    "sg:address":"2234 Chili Ave",
    "sg:city":"Rochester",
    "sg:classifiers":[
        {
            "category":"Retail",
            "subcategory":"Car Wash",
            "type":"Services"
        }
    ],
    "sg:phone":"+1 585 247 1798",
    "sg:postcode":"14624",
    "sg:province":"NY",
    "sg:tags":[
        "carwash",
        "polishing",
        "washing"
    ],
    "wof:name":"Buckmans Car Wash Inc",
    "wof:placetype":"venue"
},
  "geometry": {"coordinates":[-77.693782,43.130224],"type":"Point"}
}