{
  "type": "Feature",
  "properties": {
    "addr:full":"1114 Delray Dr Rome NY 13440",
    "addr:housenumber":"1114",
    "addr:postcode":"13440",
    "addr:street":"Delray Dr",
    "iso:country":"US",
    "sg:address":"1114 Delray Dr",
    "sg:city":"Rome",
    "sg:classifiers":[
        {
            "category":"Building & Trades",
            "subcategory":"Construction",
            "type":"Services"
        }
    ],
    "sg:phone":"+1 315 336 1557",
    "sg:postcode":"13440",
    "sg:province":"NY",
    "sg:tags":[
        "house"
    ],
    "wof:name":"Arena Construction",
    "wof:placetype":"venue"
},
  "geometry": {"coordinates":[-75.468512,43.231547],"type":"Point"}
}