{
  "type": "Feature",
  "properties": {
    "addr:full":"1180 Ave of the Americas New York NY 10036",
    "addr:housenumber":"1180",
    "addr:postcode":"10036",
    "addr:street":"Ave Of The Americas",
    "iso:country":"US",
    "sg:address":"1180 Ave of the Americas",
    "sg:city":"New York",
    "sg:classifiers":[
        {
            "category":"Building & Trades",
            "subcategory":"Cleaning & Sanitation",
            "type":"Services"
        }
    ],
    "sg:phone":"+1 212 899 5190",
    "sg:postcode":"10036",
    "sg:province":"NY",
    "wof:name":"Johnson Controls Inc",
    "wof:placetype":"venue"
},
  "geometry": {"coordinates":[-73.98179399999999,40.758021],"type":"Point"}
}