{
  "type": "Feature",
  "properties": {
    "iso:country":"US",
    "sg:address":"39 Arpad St",
    "sg:city":"Hicksville",
    "sg:classifiers":[
        {
            "category":"Landmark",
            "subcategory":"Tourist Information",
            "type":"Public Place"
        }
    ],
    "sg:phone":"+1 516 681 3228",
    "sg:postcode":"11801",
    "sg:province":"NY",
    "sg:tags":[
        "promoter",
        "tours-operators"
    ],
    "wof:name":"Mikes Bike Tours",
    "wof:placetype":"venue"
},
  "geometry": {"coordinates":[-73.507942,40.783101],"type":"Point"}
}