{
  "type": "Feature",
  "properties": {
    "addr:full":"334 Mamaroneck Ave Mamaroneck NY 10543",
    "addr:housenumber":"334",
    "addr:postcode":"10543",
    "addr:street":"Mamaroneck Ave",
    "iso:country":"US",
    "sg:address":"334 Mamaroneck Ave",
    "sg:city":"Mamaroneck",
    "sg:phone":"+1 914 371 5231",
    "sg:postcode":"10543",
    "sg:province":"NY",
    "sg:website":"http://www.upstatenewyorklocksmith.biz",
    "wof:name":"Danny's Locksmith24HR",
    "wof:placetype":"venue"
},
  "geometry": {"coordinates":[-73.734982,40.951187],"type":"Point"}
}