{
  "type": "Feature",
  "properties": {
    "addr:full":"8 Dean St Port Jefferson Station NY 11776",
    "addr:housenumber":"8",
    "addr:postcode":"11776",
    "addr:street":"Dean St",
    "iso:country":"US",
    "sg:address":"8 Dean St",
    "sg:city":"Port Jefferson Station",
    "sg:classifiers":[
        {
            "category":"Building & Trades",
            "subcategory":"Construction",
            "type":"Services"
        }
    ],
    "sg:phone":"+1 631 928 5496",
    "sg:postcode":"11776",
    "sg:province":"NY",
    "sg:tags":[
        "general",
        "contractor"
    ],
    "wof:name":"Huge Construction",
    "wof:placetype":"venue"
},
  "geometry": {"coordinates":[-73.059786,40.907021],"type":"Point"}
}