{
  "type": "Feature",
  "properties": {
    "addr:full":"14 Western Ave Marlboro NY 12542",
    "addr:housenumber":"14",
    "addr:postcode":"12542",
    "addr:street":"Western Ave",
    "iso:country":"US",
    "sg:address":"14 Western Ave",
    "sg:city":"Marlboro",
    "sg:classifiers":[
        {
            "category":"Health Services",
            "subcategory":"Optometrist",
            "type":"Services"
        }
    ],
    "sg:phone":"+1 845 236 3341",
    "sg:postcode":"12542",
    "sg:province":"NY",
    "wof:name":"Schenker Samuel OD",
    "wof:placetype":"venue"
},
  "geometry": {"coordinates":[-73.971901,41.605701],"type":"Point"}
}