{
  "type": "Feature",
  "properties": {
    "addr:full":"21 Kisco Ave Mt Kisco NY 10549",
    "addr:housenumber":"21",
    "addr:postcode":"10549",
    "addr:street":"Kisco Ave Mt Kisco",
    "iso:country":"US",
    "sg:address":"21 Kisco Ave",
    "sg:city":"Mt Kisco",
    "sg:classifiers":[
        {
            "category":"Food & Beverages",
            "subcategory":"Fruits & Vegetables",
            "type":"Retail Goods"
        }
    ],
    "sg:phone":"+1 914 666 2369",
    "sg:postcode":"10549",
    "sg:province":"NY",
    "sg:tags":[
        "produce"
    ],
    "wof:name":"Kisco Farm",
    "wof:placetype":"venue"
},
  "geometry": {"coordinates":[-73.72965499999999,41.209457],"type":"Point"}
}