{
  "type": "Feature",
  "properties": {
    "iso:country":"US",
    "sg:address":"1805 W Creek Rd",
    "sg:city":"Burt",
    "sg:classifiers":[
        {
            "category":"Shopping",
            "subcategory":"Gifts & Souvenirs",
            "type":"Retail Goods"
        }
    ],
    "sg:phone":"+1 716 778 0289",
    "sg:postcode":"14028",
    "sg:province":"NY",
    "sg:tags":[
        "greeting",
        "card"
    ],
    "wof:name":"Favorite Players Sports Cards",
    "wof:placetype":"venue"
},
  "geometry": {"coordinates":[-78.718283,43.317801],"type":"Point"}
}