{
  "type": "Feature",
  "properties": {
    "iso:country":"US",
    "sg:address":"115 Main St",
    "sg:city":"Antwerp",
    "sg:classifiers":[
        {
            "category":"Building & Trades",
            "subcategory":"Construction",
            "type":"Services"
        }
    ],
    "sg:phone":"+1 315 659 2448",
    "sg:postcode":"13608",
    "sg:province":"NY",
    "sg:tags":[
        "roofing",
        "industrial",
        "contractors-commercial",
        "contractor"
    ],
    "wof:name":"Sands Brothers Roofing Co Inc",
    "wof:placetype":"venue"
},
  "geometry": {"coordinates":[-75.607063,44.198711],"type":"Point"}
}