{
  "type": "Feature",
  "properties": {
    "iso:country":"US",
    "sg:address":"159 5th Ave",
    "sg:city":"New York",
    "sg:classifiers":[
        {
            "category":"Professional",
            "subcategory":"Business Services",
            "type":"Services"
        }
    ],
    "sg:phone":"+1 212 489 0880",
    "sg:postcode":"10010",
    "sg:province":"NY",
    "sg:tags":[
        "theatrical"
    ],
    "wof:name":"Pinder Lane Productions Ltd",
    "wof:placetype":"venue"
},
  "geometry": {"coordinates":[-73.990193,40.740501],"type":"Point"}
}