{
  "type": "Feature",
  "properties": {
    "iso:country":"US",
    "sg:address":"667 Grand Ave",
    "sg:city":"Lindenhurst",
    "sg:classifiers":[
        {
            "category":"Building & Trades",
            "subcategory":"Construction",
            "type":"Services"
        }
    ],
    "sg:phone":"+1 516 242 2183",
    "sg:postcode":"11757",
    "sg:province":"NY",
    "sg:tags":[
        "contractor",
        "mechanical"
    ],
    "wof:name":"Accurate Mechanical Works Inc",
    "wof:placetype":"venue"
},
  "geometry": {"coordinates":[-73.366812,40.708496],"type":"Point"}
}