{
  "type": "Feature",
  "properties": {
    "iso:country":"US",
    "sg:address":"2010 Western Ave",
    "sg:city":"Albany",
    "sg:classifiers":[
        {
            "category":"Professional",
            "subcategory":"Research",
            "type":"Services"
        }
    ],
    "sg:phone":"+1 518 242 2000",
    "sg:postcode":"12203",
    "sg:province":"NY",
    "sg:tags":[
        "opinion",
        "survey",
        "market"
    ],
    "wof:name":"Fact Finders Inc",
    "wof:placetype":"venue"
},
  "geometry": {"coordinates":[-73.88664900000001,42.697138],"type":"Point"}
}