{
  "type": "Feature",
  "properties": {
    "addr:full":"1202 Jefferson Ave Buffalo NY 14208",
    "addr:housenumber":"1202",
    "addr:postcode":"14208",
    "addr:street":"Jefferson Ave",
    "iso:country":"US",
    "sg:address":"1202 Jefferson Ave",
    "sg:city":"Buffalo",
    "sg:classifiers":[
        {
            "category":"Parking",
            "type":"Transportation"
        }
    ],
    "sg:phone":"+1 716 854 3079",
    "sg:postcode":"14208",
    "sg:province":"NY",
    "sg:tags":[
        "garage"
    ],
    "wof:name":"FFG Enterprise LTD",
    "wof:placetype":"venue"
},
  "geometry": {"coordinates":[-78.85404,42.90804],"type":"Point"}
}