{
  "type": "Feature",
  "properties": {
    "iso:country":"US",
    "sg:address":"133 N. 4th Street",
    "sg:city":"Brooklyn",
    "sg:classifiers":[
        {
            "category":"Travel",
            "subcategory":"Hostel",
            "type":"Entertainment"
        }
    ],
    "sg:phone":"+1 888 529 2826",
    "sg:postcode":"11211",
    "sg:province":"NY",
    "sg:website":"www.laydownatmetropol.com/",
    "wof:name":"Metropol Hostel",
    "wof:placetype":"venue"
},
  "geometry": {"coordinates":[-73.959631,40.716537],"type":"Point"}
}