{
  "type": "Feature",
  "properties": {
    "iso:country":"US",
    "sg:address":"27 Jones St",
    "sg:city":"New Rochelle",
    "sg:classifiers":[
        {
            "category":"Building & Trades",
            "subcategory":"Landscaping Services",
            "type":"Services"
        }
    ],
    "sg:phone":"+1 914 633 9754",
    "sg:postcode":"10801",
    "sg:province":"NY",
    "sg:tags":[
        "landscape"
    ],
    "wof:name":"P D Landscaping",
    "wof:placetype":"venue"
},
  "geometry": {"coordinates":[-73.793345,40.907639],"type":"Point"}
}