{
  "type": "Feature",
  "properties": {
    "iso:country":"US",
    "sg:address":"598 Jericho Tpke",
    "sg:city":"Syosset",
    "sg:classifiers":[
        {
            "category":"Sports & Exercise",
            "subcategory":"Gym",
            "type":"Entertainment"
        }
    ],
    "sg:phone":"+1 516 677 0377",
    "sg:postcode":"11791",
    "sg:province":"NY",
    "sg:tags":[
        "club",
        "health",
        "studio",
        "gymnasium"
    ],
    "wof:name":"Lady Of America",
    "wof:placetype":"venue"
},
  "geometry": {"coordinates":[-73.494074,40.811397],"type":"Point"}
}