{
  "type": "Feature",
  "properties": {
    "iso:country":"US",
    "sg:address":"876 Broadway",
    "sg:city":"New York",
    "sg:classifiers":[
        {
            "category":"Professional",
            "type":"Services"
        }
    ],
    "sg:phone":"+1   ",
    "sg:postcode":"10003",
    "sg:province":"NY",
    "wof:name":"Wendy Doremus",
    "wof:placetype":"venue"
},
  "geometry": {"coordinates":[-73.989897,40.738375],"type":"Point"}
}