{
  "type": "Feature",
  "properties": {
    "iso:country":"US",
    "sg:address":"257 Edgegrove Ave",
    "sg:city":"Staten Island",
    "sg:classifiers":[
        {
            "category":"Building & Trades",
            "subcategory":"Construction",
            "type":"Services"
        }
    ],
    "sg:phone":"+1 718 980 0430",
    "sg:postcode":"10312",
    "sg:province":"NY",
    "sg:tags":[
        "house",
        "contractor"
    ],
    "wof:name":"A & E Construction Corp",
    "wof:placetype":"venue"
},
  "geometry": {"coordinates":[-74.181066,40.543668],"type":"Point"}
}