{
  "type": "Feature",
  "properties": {
    "iso:country":"US",
    "sg:address":"4 Interstate Ave",
    "sg:city":"Albany",
    "sg:classifiers":[
        {
            "category":"Utilities",
            "subcategory":"Telephone",
            "type":"Services"
        }
    ],
    "sg:phone":"+1   ",
    "sg:postcode":"12205",
    "sg:province":"NY",
    "sg:tags":[
        "communications"
    ],
    "wof:name":"Wsg Net",
    "wof:placetype":"venue"
},
  "geometry": {"coordinates":[-73.813068,42.694851],"type":"Point"}
}