{
  "type": "Feature",
  "properties": {
    "addr:full":"4 Airline Dr Colonie NY 12205",
    "addr:housenumber":"4",
    "addr:postcode":"12205",
    "addr:street":"Airline Dr",
    "iso:country":"US",
    "sg:address":"4 Airline Dr",
    "sg:city":"Colonie",
    "sg:classifiers":[
        {
            "category":"Insurance",
            "subcategory":"Insurance Agent",
            "type":"Services"
        }
    ],
    "sg:phone":"+1 518 690 2072",
    "sg:postcode":"12205",
    "sg:province":"NY",
    "wof:name":"Arm Of Ny Inc",
    "wof:placetype":"venue"
},
  "geometry": {"coordinates":[-73.818299,42.737373],"type":"Point"}
}