{
  "type": "Feature",
  "properties": {
    "addr:full":"6911 Juniper Blvd S Middle Village NY 11379",
    "addr:housenumber":"6911",
    "addr:postcode":"11379",
    "addr:street":"Juniper Blvd S Middle",
    "iso:country":"US",
    "sg:address":"6911 Juniper Blvd S",
    "sg:city":"Middle Village",
    "sg:classifiers":[
        {
            "category":"Retail",
            "subcategory":"Auto Repair",
            "type":"Services"
        }
    ],
    "sg:phone":"+1 718 326 5180",
    "sg:postcode":"11379",
    "sg:province":"NY",
    "sg:tags":[
        "body",
        "shop"
    ],
    "wof:name":"Columbia Bros",
    "wof:placetype":"venue"
},
  "geometry": {"coordinates":[-73.8871,40.716301],"type":"Point"}
}