{
  "type": "Feature",
  "properties": {
    "addr:full":"327 Fullerton Ave Newburgh NY 12550",
    "addr:housenumber":"327",
    "addr:postcode":"12550",
    "addr:street":"Fullerton Ave",
    "iso:country":"US",
    "sg:address":"327 Fullerton Ave",
    "sg:city":"Newburgh",
    "sg:classifiers":[
        {
            "category":"Health Services",
            "subcategory":"Doctor",
            "type":"Services"
        }
    ],
    "sg:phone":"+1 845 561 4032",
    "sg:postcode":"12550",
    "sg:province":"NY",
    "wof:name":"Chowdhury Muhammad",
    "wof:placetype":"venue"
},
  "geometry": {"coordinates":[-74.024715,41.513322],"type":"Point"}
}