{
  "type": "Feature",
  "properties": {
    "addr:full":"190 Bleecker St New York NY 10012",
    "addr:housenumber":"190",
    "addr:postcode":"10012",
    "addr:street":"Bleecker St",
    "iso:country":"US",
    "sg:address":"190 Bleecker St",
    "sg:city":"New York",
    "sg:classifiers":[
        {
            "category":"Restaurant",
            "type":"Food & Drink"
        }
    ],
    "sg:menulink":"http://www.allmenus.com/ny/new-york/2312-the-burger-joint/menu/",
    "sg:phone":"0",
    "sg:postcode":"10012",
    "sg:province":"NY",
    "sg:tags":[
        "burger",
        "american"
    ],
    "wof:name":"The Burger Joint",
    "wof:placetype":"venue"
},
  "geometry": {"coordinates":[-74.001507,40.729074],"type":"Point"}
}