{
  "type": "Feature",
  "properties": {
    "iso:country":"US",
    "sg:address":"2439 Southern Blvd",
    "sg:city":"Bronx",
    "sg:classifiers":[
        {
            "category":"Professional",
            "subcategory":"Lawyer & Legal Services",
            "type":"Services"
        }
    ],
    "sg:phone":"+1 212 682 1686",
    "sg:postcode":"10458",
    "sg:province":"NY",
    "sg:tags":[
        "attorney"
    ],
    "wof:name":"Gene Crescenzi",
    "wof:placetype":"venue"
},
  "geometry": {"coordinates":[-73.881067,40.855476],"type":"Point"}
}