{
  "type": "Feature",
  "properties": {
    "iso:country":"US",
    "sg:address":"944 N Broadway",
    "sg:city":"Yonkers",
    "sg:classifiers":[
        {
            "category":"Professional",
            "subcategory":"Computer Services",
            "type":"Services"
        }
    ],
    "sg:phone":"+1 914 376 7151",
    "sg:postcode":"10701",
    "sg:province":"NY",
    "sg:tags":[
        "prepackaged",
        "software"
    ],
    "wof:name":"J M K/R M S Computers",
    "wof:placetype":"venue"
},
  "geometry": {"coordinates":[-73.884738,40.968366],"type":"Point"}
}