{
  "type": "Feature",
  "properties": {
    "addr:full":"42 Orchard St Manhasset NY 11030",
    "addr:housenumber":"42",
    "addr:postcode":"11030",
    "addr:street":"Orchard St",
    "iso:country":"US",
    "sg:address":"42 Orchard St",
    "sg:city":"Manhasset",
    "sg:classifiers":[
        {
            "category":"Health Services",
            "subcategory":"Chiropractor",
            "type":"Services"
        }
    ],
    "sg:phone":"+1 516 869 0411",
    "sg:postcode":"11030",
    "sg:province":"NY",
    "sg:tags":[
        "chiropractic"
    ],
    "wof:name":"Patestas, Michael D C",
    "wof:placetype":"venue"
},
  "geometry": {"coordinates":[-73.697931,40.798601],"type":"Point"}
}