{
  "type": "Feature",
  "properties": {
    "addr:full":"15 Thomas Rd Poughquag NY 12570",
    "addr:housenumber":"15",
    "addr:postcode":"12570",
    "addr:street":"Thomas Rd",
    "iso:country":"US",
    "sg:address":"15 Thomas Rd",
    "sg:city":"Poughquag",
    "sg:classifiers":[
        {
            "category":"Real Estate",
            "subcategory":"Real Estate Agent",
            "type":"Services"
        }
    ],
    "sg:phone":"+1 845 226 6096",
    "sg:postcode":"12570",
    "sg:province":"NY",
    "wof:name":"Barnwell Associates",
    "wof:placetype":"venue"
},
  "geometry": {"coordinates":[-73.697067,41.616965],"type":"Point"}
}