{
  "type": "Feature",
  "properties": {
    "iso:country":"US",
    "sg:address":"12 Salem Ln",
    "sg:city":"South Salem",
    "sg:classifiers":[
        {
            "category":"Building & Trades",
            "subcategory":"Construction",
            "type":"Services"
        }
    ],
    "sg:phone":"+1 914 533 2005",
    "sg:postcode":"10590",
    "sg:province":"NY",
    "sg:tags":[
        "excavation",
        "contractor"
    ],
    "wof:name":"Duff Price Excavating",
    "wof:placetype":"venue"
},
  "geometry": {"coordinates":[-73.549041,41.277745],"type":"Point"}
}