{
  "type": "Feature",
  "properties": {
    "addr:full":"380 Lake Ave Saint James NY 11780",
    "addr:housenumber":"380",
    "addr:postcode":"11780",
    "addr:street":"Lake Ave",
    "iso:country":"US",
    "sg:address":"380 Lake Ave",
    "sg:city":"Saint James",
    "sg:classifiers":[
        {
            "category":"Arts & Performance",
            "subcategory":"Arts Center",
            "type":"Entertainment"
        }
    ],
    "sg:phone":"+1 631 584 7575",
    "sg:postcode":"11780",
    "sg:province":"NY",
    "sg:tags":[
        "performing"
    ],
    "sg:website":"www.choruslinedance.com",
    "wof:name":"Chorus Line Dance Studio Inc",
    "wof:placetype":"venue"
},
  "geometry": {"coordinates":[-73.157303,40.882],"type":"Point"}
}