{
  "type": "Feature",
  "properties": {
    "addr:full":"24 Cherry St Johnson City NY 13790",
    "addr:housenumber":"24",
    "addr:postcode":"13790",
    "addr:street":"Cherry St",
    "iso:country":"US",
    "sg:address":"24 Cherry St",
    "sg:city":"Johnson City",
    "sg:classifiers":[
        {
            "category":"Education",
            "subcategory":"School",
            "type":"Public Place"
        }
    ],
    "sg:phone":"+1 607 763 1254",
    "sg:postcode":"13790",
    "sg:province":"NY",
    "sg:tags":[
        "elementary"
    ],
    "wof:name":"Lincoln Elementary School",
    "wof:placetype":"venue"
},
  "geometry": {"coordinates":[-75.955386,42.10887],"type":"Point"}
}