{
  "type": "Feature",
  "properties": {
    "addr:full":"498 Ave of the Americas New York NY 10011",
    "addr:housenumber":"498",
    "addr:postcode":"10011",
    "addr:street":"Ave Of The Americas",
    "iso:country":"US",
    "sg:address":"498 Ave of the Americas",
    "sg:city":"New York",
    "sg:classifiers":[
        {
            "category":"Shopping",
            "subcategory":"Crafts & Fabrics",
            "type":"Retail Goods"
        }
    ],
    "sg:phone":"+1 212 989 3030",
    "sg:postcode":"10011",
    "sg:province":"NY",
    "sg:tags":[
        "yarn"
    ],
    "wof:name":"Gotta Knit",
    "wof:placetype":"venue"
},
  "geometry": {"coordinates":[-73.99748,40.736261],"type":"Point"}
}