{
  "type": "Feature",
  "properties": {
    "addr:full":"117 Orchard Street New York NY 10002",
    "addr:housenumber":"117",
    "addr:postcode":"10002",
    "addr:street":"Orchard Street",
    "iso:country":"US",
    "sg:address":"117 Orchard Street",
    "sg:city":"New York",
    "sg:classifiers":[
        {
            "category":"Health Services",
            "subcategory":"Optometrist",
            "type":"Services"
        },
        {
            "category":"Shopping",
            "subcategory":"Optician",
            "type":"Retail Goods"
        }
    ],
    "sg:phone":"+1 212 674 1986",
    "sg:postcode":"10002",
    "sg:province":"NY",
    "sg:tags":[
        "eyewear"
    ],
    "wof:name":"Cohen's Fashion Optical",
    "wof:placetype":"venue"
},
  "geometry": {"coordinates":[-73.989722,40.719093],"type":"Point"}
}