{
  "type": "Feature",
  "properties": {
    "iso:country":"US",
    "sg:address":"200 Hunnewell Ave",
    "sg:city":"Elmont",
    "sg:classifiers":[
        {
            "category":"Shopping",
            "subcategory":"Computers & Home Electronics",
            "type":"Retail Goods"
        }
    ],
    "sg:phone":"+1   ",
    "sg:postcode":"11003",
    "sg:province":"NY",
    "wof:name":"Mr Mnm PC",
    "wof:placetype":"venue"
},
  "geometry": {"coordinates":[-73.687966,40.703765],"type":"Point"}
}