{
  "type": "Feature",
  "properties": {
    "iso:country":"US",
    "sg:address":"189a Quail St",
    "sg:city":"Albany",
    "sg:classifiers":[
        {
            "category":"Restaurant",
            "type":"Food & Drink"
        }
    ],
    "sg:menulink":"http://www.allmenus.com/ny/albany/18506-mild-wallys-delivery-restaurant/menu/",
    "sg:phone":"+1 518 433 7436",
    "sg:postcode":"12203",
    "sg:province":"NY",
    "sg:tags":[
        "american"
    ],
    "wof:name":"Mild Wally's Delivery Restaurant",
    "wof:placetype":"venue"
},
  "geometry": {"coordinates":[-73.777219,42.661929],"type":"Point"}
}