{
  "type": "Feature",
  "properties": {
    "addr:full":"5 Eton Pl Plainview NY 11803",
    "addr:housenumber":"5",
    "addr:postcode":"11803",
    "addr:street":"Eton Pl",
    "iso:country":"US",
    "sg:address":"5 Eton Pl",
    "sg:city":"Plainview",
    "sg:classifiers":[
        {
            "category":"Professional",
            "type":"Services"
        }
    ],
    "sg:phone":"+1   ",
    "sg:postcode":"11803",
    "sg:province":"NY",
    "wof:name":"Dmg Designs Inc",
    "wof:placetype":"venue"
},
  "geometry": {"coordinates":[-73.48214,40.792623],"type":"Point"}
}