{
  "type": "Feature",
  "properties": {
    "addr:full":"217 Lake Ave Rochester NY 14608",
    "addr:housenumber":"217",
    "addr:postcode":"14608",
    "addr:street":"Lake Ave",
    "iso:country":"US",
    "sg:address":"217 Lake Ave",
    "sg:city":"Rochester",
    "sg:classifiers":[
        {
            "category":"Professional",
            "subcategory":"Engineering",
            "type":"Services"
        }
    ],
    "sg:phone":"+1 585 458 3020",
    "sg:postcode":"14608",
    "sg:province":"NY",
    "sg:tags":[
        "engineer"
    ],
    "sg:website":"www.costich.com",
    "wof:name":"Costich Engineering",
    "wof:placetype":"venue"
},
  "geometry": {"coordinates":[-77.626324,43.1683],"type":"Point"}
}