{
  "type": "Feature",
  "properties": {
    "addr:full":"104 Krispin Ln East Setauket NY 11733",
    "addr:housenumber":"104",
    "addr:postcode":"11733",
    "addr:street":"Krispin Ln East",
    "iso:country":"US",
    "sg:address":"104 Krispin Ln",
    "sg:city":"East Setauket",
    "sg:classifiers":[
        {
            "category":"Building & Trades",
            "subcategory":"Construction",
            "type":"Services"
        }
    ],
    "sg:phone":"+1 631 246 8731",
    "sg:postcode":"11733",
    "sg:province":"NY",
    "sg:tags":[
        "carpentry"
    ],
    "wof:name":"C V S Construction Company",
    "wof:placetype":"venue"
},
  "geometry": {"coordinates":[-73.09563,40.892652],"type":"Point"}
}