{
  "type": "Feature",
  "properties": {
    "addr:full":"45 Quaker Ave Cornwall NY 12518",
    "addr:housenumber":"45",
    "addr:postcode":"12518",
    "addr:street":"Quaker Ave",
    "iso:country":"US",
    "sg:address":"45 Quaker Ave",
    "sg:city":"Cornwall",
    "sg:classifiers":[
        {
            "category":"Personal",
            "subcategory":"Beauty Salon",
            "type":"Services"
        }
    ],
    "sg:phone":"+1 845 534 4034",
    "sg:postcode":"12518",
    "sg:province":"NY",
    "sg:tags":[
        "manicuring"
    ],
    "wof:name":"Nail Boutique",
    "wof:placetype":"venue"
},
  "geometry": {"coordinates":[-74.039799,41.434187],"type":"Point"}
}