{
  "type": "Feature",
  "properties": {
    "addr:full":"15 Blossom Ln Brewster NY 10509",
    "addr:housenumber":"15",
    "addr:postcode":"10509",
    "addr:street":"Blossom Ln",
    "iso:country":"US",
    "sg:address":"15 Blossom Ln",
    "sg:city":"Brewster",
    "sg:classifiers":[
        {
            "category":"Building & Trades",
            "subcategory":"Construction",
            "type":"Services"
        },
        {
            "category":"Building & Trades",
            "subcategory":"Landscaping Services",
            "type":"Services"
        }
    ],
    "sg:phone":"+1 845 278 7214",
    "sg:postcode":"10509",
    "sg:province":"NY",
    "sg:tags":[
        "excavation",
        "landscape",
        "contractor"
    ],
    "wof:name":"Le Donne Landscaping & Design",
    "wof:placetype":"venue"
},
  "geometry": {"coordinates":[-73.58484300000001,41.45998],"type":"Point"}
}