{
  "type": "Feature",
  "properties": {
    "iso:country":"US",
    "sg:address":"82 Havemeyer St",
    "sg:city":"Brooklyn",
    "sg:classifiers":[
        {
            "category":"Deli",
            "type":"Food & Drink"
        },
        {
            "category":"Food & Beverages",
            "subcategory":"Bakery",
            "type":"Retail Goods"
        }
    ],
    "sg:phone":"+1 718 388 1849",
    "sg:postcode":"11211",
    "sg:province":"NY",
    "sg:tags":[
        "sandwich"
    ],
    "wof:name":"New Tork Deli Grocery",
    "wof:placetype":"venue"
},
  "geometry": {"coordinates":[-73.956137,40.714081],"type":"Point"}
}