{
  "type": "Feature",
  "properties": {
    "addr:full":"1675 Broadway Brooklyn NY 11207",
    "addr:housenumber":"1675",
    "addr:postcode":"11207",
    "addr:street":"Broadway",
    "iso:country":"US",
    "sg:address":"1675 Broadway",
    "sg:city":"Brooklyn",
    "sg:classifiers":[
        {
            "category":"Organizations",
            "subcategory":"Membership Organization",
            "type":"Services"
        }
    ],
    "sg:phone":"+1 718 574 2701",
    "sg:postcode":"11207",
    "sg:province":"NY",
    "wof:name":"Salvation Army",
    "wof:placetype":"venue"
},
  "geometry": {"coordinates":[-73.912451,40.684162],"type":"Point"}
}