{
  "type": "Feature",
  "properties": {
    "addr:full":"59 Diamond Dr Plainview NY 11803",
    "addr:housenumber":"59",
    "addr:postcode":"11803",
    "addr:street":"Diamond Dr",
    "iso:country":"US",
    "sg:address":"59 Diamond Dr",
    "sg:city":"Plainview",
    "sg:classifiers":[
        {
            "category":"Banks & Credit Unions",
            "subcategory":"Financial Services",
            "type":"Services"
        }
    ],
    "sg:phone":"+1 516 349 0852",
    "sg:postcode":"11803",
    "sg:province":"NY",
    "sg:tags":[
        "company",
        "holding"
    ],
    "wof:name":"Kendall Holdings Ltd",
    "wof:placetype":"venue"
},
  "geometry": {"coordinates":[-73.476668,40.790035],"type":"Point"}
}