{
  "type": "Feature",
  "properties": {
    "iso:country":"US",
    "sg:address":"6626 Snake Rd",
    "sg:city":"Newark",
    "sg:classifiers":[
        {
            "category":"Retail",
            "subcategory":"Auto Repair",
            "type":"Services"
        }
    ],
    "sg:phone":"+1   ",
    "sg:postcode":"14513",
    "sg:province":"NY",
    "sg:tags":[
        "general"
    ],
    "wof:name":"Arcadia Automotive",
    "wof:placetype":"venue"
},
  "geometry": {"coordinates":[-77.067172,43.037201],"type":"Point"}
}