{
  "type": "Feature",
  "properties": {
    "addr:full":"9612 Carousel Ctr  Syracuse NY 13290",
    "addr:housenumber":"9612",
    "addr:postcode":"13290",
    "addr:street":"Carousel Ctr",
    "iso:country":"US",
    "sg:address":"9612 Carousel Ctr ",
    "sg:city":"Syracuse",
    "sg:classifiers":[
        {
            "category":"Restaurant",
            "type":"Food & Drink"
        }
    ],
    "sg:menulink":"http://www.allmenus.com/ny/syracuse/72559-sbarro/menu/",
    "sg:phone":"+1 315 476 8626",
    "sg:postcode":"13290",
    "sg:province":"NY",
    "sg:tags":[
        "american",
        "pizza"
    ],
    "wof:name":"Sbarro",
    "wof:placetype":"venue"
},
  "geometry": {"coordinates":[-76.169698,43.070296],"type":"Point"}
}