{
  "type": "Feature",
  "properties": {
    "iso:country":"US",
    "sg:address":"634 Gravel Rd",
    "sg:city":"Webster",
    "sg:classifiers":[
        {
            "category":"Building & Trades",
            "subcategory":"Electrical",
            "type":"Services"
        }
    ],
    "sg:phone":"+1 585 671 4064",
    "sg:postcode":"14580",
    "sg:province":"NY",
    "sg:tags":[
        "electrical",
        "electric",
        "contractor"
    ],
    "wof:name":"Jim Lester Electrical Contrng",
    "wof:placetype":"venue"
},
  "geometry": {"coordinates":[-77.486892,43.222435],"type":"Point"}
}