{
  "type": "Feature",
  "properties": {
    "addr:full":"39 High Country Trl Pittsford NY 14534",
    "addr:housenumber":"39",
    "addr:postcode":"14534",
    "addr:street":"High Country Trl",
    "iso:country":"US",
    "sg:address":"39 High Country Trl",
    "sg:city":"Pittsford",
    "sg:classifiers":[
        {
            "category":"Health Services",
            "subcategory":"Doctor",
            "type":"Services"
        }
    ],
    "sg:phone":"+1 585 624 2017",
    "sg:postcode":"14534",
    "sg:province":"NY",
    "sg:tags":[
        "medical"
    ],
    "wof:name":"Richard H Sterns",
    "wof:placetype":"venue"
},
  "geometry": {"coordinates":[-77.487922,43.028825],"type":"Point"}
}