{
  "type": "Feature",
  "properties": {
    "iso:country":"US",
    "sg:address":"500 Brookford Rd",
    "sg:city":"Syracuse",
    "sg:classifiers":[
        {
            "category":"Professional",
            "subcategory":"Business Services",
            "type":"Services"
        }
    ],
    "sg:phone":"+1 315 446 2680",
    "sg:postcode":"13224",
    "sg:province":"NY",
    "sg:tags":[
        "conference",
        "center"
    ],
    "sg:website":"www.christthekingretreat.com",
    "wof:name":"Christ The King Retreat House",
    "wof:placetype":"venue"
},
  "geometry": {"coordinates":[-76.097195,43.034773],"type":"Point"}
}