{
  "type": "Feature",
  "properties": {
    "addr:full":"269 S Middletown Rd Nanuet NY 10954",
    "addr:housenumber":"269",
    "addr:postcode":"10954",
    "addr:street":"S Middletown Rd",
    "iso:country":"US",
    "sg:address":"269 S Middletown Rd",
    "sg:city":"Nanuet",
    "sg:classifiers":[
        {
            "category":"Food & Beverages",
            "subcategory":"Bakery",
            "type":"Retail Goods"
        }
    ],
    "sg:phone":"+1 845 627 7700",
    "sg:postcode":"10954",
    "sg:province":"NY",
    "sg:tags":[
        "bagel"
    ],
    "wof:name":"Pete's Hot Bagels",
    "wof:placetype":"venue"
},
  "geometry": {"coordinates":[-74.015742,41.084809],"type":"Point"}
}