{
  "type": "Feature",
  "properties": {
    "iso:country":"US",
    "sg:address":"75 Commercial Ave",
    "sg:city":"Garden City",
    "sg:classifiers":[
        {
            "category":"Wholesale",
            "subcategory":"Drugs",
            "type":"Manufacturing & Wholesale Goods"
        }
    ],
    "sg:phone":"+1 516 248 4090",
    "sg:postcode":"11530",
    "sg:province":"NY",
    "sg:tags":[
        "aids",
        "electronics",
        "health",
        "beauty"
    ],
    "wof:name":"Stealth International Inc",
    "wof:placetype":"venue"
},
  "geometry": {"coordinates":[-73.61273199999999,40.728867],"type":"Point"}
}