{
  "type": "Feature",
  "properties": {
    "addr:full":"125 Broad St New York NY 10004",
    "addr:housenumber":"125",
    "addr:postcode":"10004",
    "addr:street":"Broad St",
    "iso:country":"US",
    "sg:address":"125 Broad St",
    "sg:city":"New York",
    "sg:classifiers":[
        {
            "category":"Professional",
            "subcategory":"Lawyer & Legal Services",
            "type":"Services"
        }
    ],
    "sg:phone":"+1 212 558 4000",
    "sg:postcode":"10004",
    "sg:province":"NY",
    "sg:website":"www.sullcrom.com/offices/detail....",
    "wof:name":"Sullivan and Crommwell LLP",
    "wof:placetype":"venue"
},
  "geometry": {"coordinates":[-74.010581,40.702235],"type":"Point"}
}