{
  "type": "Feature",
  "properties": {
    "iso:country":"US",
    "sg:address":"70 Roslyn Rd",
    "sg:city":"Roslyn Heights",
    "sg:classifiers":[
        {
            "category":"Health Services",
            "subcategory":"Health Practitioner",
            "type":"Services"
        }
    ],
    "sg:phone":"+1 631 754 6916",
    "sg:postcode":"11577",
    "sg:province":"NY",
    "sg:tags":[
        "nutritionist"
    ],
    "wof:name":"Pediatric Nutrition & Eating",
    "wof:placetype":"venue"
},
  "geometry": {"coordinates":[-73.640697,40.791452],"type":"Point"}
}