{
  "type": "Feature",
  "properties": {
    "addr:full":"5 Strathmore Rd Scarsdale NY 10583",
    "addr:housenumber":"5",
    "addr:postcode":"10583",
    "addr:street":"Strathmore Rd",
    "iso:country":"US",
    "sg:address":"5 Strathmore Rd",
    "sg:city":"Scarsdale",
    "sg:classifiers":[
        {
            "category":"Organizations",
            "subcategory":"Religious Organization",
            "type":"Services"
        }
    ],
    "sg:phone":"+1 914 723 7421",
    "sg:postcode":"10583",
    "sg:province":"NY",
    "wof:name":"Our Lady Of Fatima Church",
    "wof:placetype":"venue"
},
  "geometry": {"coordinates":[-73.815601,40.979644],"type":"Point"}
}