{
  "type": "Feature",
  "properties": {
    "iso:country":"US",
    "sg:address":"61 Capital Dr",
    "sg:city":"Washingtonville",
    "sg:classifiers":[
        {
            "category":"Professional",
            "subcategory":"Art Services",
            "type":"Services"
        }
    ],
    "sg:phone":"+1 845 496 9929",
    "sg:postcode":"10992",
    "sg:province":"NY",
    "sg:tags":[
        "graphic",
        "commercial",
        "designer",
        "artist"
    ],
    "sg:website":"http://www.apmgraphics.com",
    "wof:name":"Apm Graphics",
    "wof:placetype":"venue"
},
  "geometry": {"coordinates":[-74.14115099999999,41.439671],"type":"Point"}
}