{
  "type": "Feature",
  "properties": {
    "addr:full":"2071 Crompond Rd Yorktown Heights NY 10598",
    "addr:housenumber":"2071",
    "addr:postcode":"10598",
    "addr:street":"Crompond Rd",
    "iso:country":"US",
    "sg:address":"2071 Crompond Rd",
    "sg:city":"Yorktown Heights",
    "sg:classifiers":[
        {
            "category":"Building & Trades",
            "subcategory":"Construction",
            "type":"Services"
        }
    ],
    "sg:phone":"+1 914 962 1626",
    "sg:postcode":"10598",
    "sg:province":"NY",
    "sg:tags":[
        "contractor"
    ],
    "wof:name":"John L Bushelljr",
    "wof:placetype":"venue"
},
  "geometry": {"coordinates":[-73.787837,41.279038],"type":"Point"}
}