{
  "type": "Feature",
  "properties": {
    "addr:full":"19 Main St Yonkers NY 10701",
    "addr:housenumber":"19",
    "addr:postcode":"10701",
    "addr:street":"Main St",
    "iso:country":"US",
    "sg:address":"19 Main St",
    "sg:city":"Yonkers",
    "sg:classifiers":[
        {
            "category":"Shopping",
            "subcategory":"Department Store",
            "type":"Retail Goods"
        }
    ],
    "sg:phone":"+1 914 376 0940",
    "sg:postcode":"10701",
    "sg:province":"NY",
    "sg:tags":[
        "shop"
    ],
    "wof:name":"Klein's Discount",
    "wof:placetype":"venue"
},
  "geometry": {"coordinates":[-73.898088,40.934075],"type":"Point"}
}