{
  "type": "Feature",
  "properties": {
    "addr:full":"16 Yennicock Ave Port Washington NY 11050",
    "addr:housenumber":"16",
    "addr:postcode":"11050",
    "addr:street":"Yennicock Ave",
    "iso:country":"US",
    "sg:address":"16 Yennicock Ave",
    "sg:city":"Port Washington",
    "sg:classifiers":[
        {
            "category":"Professional",
            "subcategory":"Business Services",
            "type":"Services"
        }
    ],
    "sg:phone":"+1 516 883 9171",
    "sg:postcode":"11050",
    "sg:province":"NY",
    "sg:tags":[
        "interior",
        "consultant",
        "design",
        "decorator"
    ],
    "wof:name":"Kiku Contract Interiors",
    "wof:placetype":"venue"
},
  "geometry": {"coordinates":[-73.707712,40.837211],"type":"Point"}
}