{
  "type": "Feature",
  "properties": {
    "addr:full":"9 E 93 St New York NY 10128",
    "addr:housenumber":"9;93",
    "addr:postcode":"10128",
    "addr:street":"E",
    "iso:country":"US",
    "sg:address":"9 E 93 St",
    "sg:city":"New York",
    "sg:classifiers":[
        {
            "category":"Health Services",
            "subcategory":"Doctor",
            "type":"Services"
        }
    ],
    "sg:phone":"+1 212 722 8896",
    "sg:postcode":"10128",
    "sg:province":"NY",
    "sg:tags":[
        "physician",
        "surgeon"
    ],
    "wof:name":"Howard E Millman MD",
    "wof:placetype":"venue"
},
  "geometry": {"coordinates":[-73.95573400000001,40.785477],"type":"Point"}
}