{
  "type": "Feature",
  "properties": {
    "addr:full":"1763 Hendrickson St Brooklyn NY 11234",
    "addr:housenumber":"1763",
    "addr:postcode":"11234",
    "addr:street":"Hendrickson St",
    "iso:country":"US",
    "sg:address":"1763 Hendrickson St",
    "sg:city":"Brooklyn",
    "sg:classifiers":[
        {
            "category":"Manufacturing",
            "subcategory":"Electronics",
            "type":"Manufacturing & Wholesale Goods"
        },
        {
            "category":"Shopping",
            "subcategory":"Computers & Home Electronics",
            "type":"Retail Goods"
        }
    ],
    "sg:phone":"+1 718 258 6165",
    "sg:postcode":"11234",
    "sg:province":"NY",
    "sg:tags":[
        "equipment",
        "satellite",
        "mfg",
        "system",
        "communications"
    ],
    "wof:name":"Silvain Communications Corp",
    "wof:placetype":"venue"
},
  "geometry": {"coordinates":[-73.931485,40.616881],"type":"Point"}
}