{
  "type": "Feature",
  "properties": {
    "addr:full":"6273 Charlotteville Rd Newfane NY 14108",
    "addr:housenumber":"6273",
    "addr:postcode":"14108",
    "addr:street":"Charlotteville Rd",
    "iso:country":"US",
    "sg:address":"6273 Charlotteville Rd",
    "sg:city":"Newfane",
    "sg:classifiers":[
        {
            "category":"Education",
            "subcategory":"School",
            "type":"Public Place"
        }
    ],
    "sg:phone":"+1 716 778 6351",
    "sg:postcode":"14108",
    "sg:province":"NY",
    "wof:name":"Newfane Central School Dst 1",
    "wof:placetype":"venue"
},
  "geometry": {"coordinates":[-78.69495999999999,43.283681],"type":"Point"}
}