{
  "type": "Feature",
  "properties": {
    "iso:country":"US",
    "sg:address":"174 S Main St",
    "sg:city":"New City",
    "sg:classifiers":[
        {
            "category":"Shopping",
            "subcategory":"Gifts & Souvenirs",
            "type":"Retail Goods"
        }
    ],
    "sg:phone":"+1   ",
    "sg:postcode":"10956",
    "sg:province":"NY",
    "sg:tags":[
        "shop",
        "card"
    ],
    "wof:name":"Card Gallery of New City Inc",
    "wof:placetype":"venue"
},
  "geometry": {"coordinates":[-73.990132,41.143163],"type":"Point"}
}