{
  "type": "Feature",
  "properties": {
    "iso:country":"US",
    "sg:address":"604 Woodmere Blvd",
    "sg:city":"Woodmere",
    "sg:classifiers":[
        {
            "category":"Banks & Credit Unions",
            "subcategory":"Financial Services",
            "type":"Services"
        },
        {
            "category":"Professional",
            "subcategory":"Credit Reporting & Collection",
            "type":"Services"
        }
    ],
    "sg:phone":"+1 516 295 8722",
    "sg:postcode":"11598",
    "sg:province":"NY",
    "sg:tags":[
        "debt",
        "adjuster",
        "agency"
    ],
    "wof:name":"Attain Enterprises",
    "wof:placetype":"venue"
},
  "geometry": {"coordinates":[-73.722705,40.640494],"type":"Point"}
}