{
  "type": "Feature",
  "properties": {
    "addr:full":"620 Bedford Ave Brooklyn NY 11211",
    "addr:housenumber":"620",
    "addr:postcode":"11211",
    "addr:street":"Bedford Ave",
    "iso:country":"US",
    "sg:address":"620 Bedford Ave",
    "sg:city":"Brooklyn",
    "sg:classifiers":[
        {
            "category":"Education",
            "subcategory":"School",
            "type":"Public Place"
        }
    ],
    "sg:phone":"+1 718 522 7406",
    "sg:postcode":"11211",
    "sg:province":"NY",
    "wof:name":"Bnos Sanz",
    "wof:placetype":"venue"
},
  "geometry": {"coordinates":[-73.95988800000001,40.703032],"type":"Point"}
}