{
  "type": "Feature",
  "properties": {
    "iso:country":"US",
    "sg:address":"43 Hillel Pl",
    "sg:city":"Brooklyn",
    "sg:classifiers":[
        {
            "category":"Professional",
            "subcategory":"Printing & Photocopies",
            "type":"Services"
        }
    ],
    "sg:phone":"+1 718 859 3137",
    "sg:postcode":"11210",
    "sg:province":"NY",
    "sg:tags":[
        "photocopying"
    ],
    "sg:website":"farbetterprinting.com",
    "wof:name":"Far Better Printing & Copy Center",
    "wof:placetype":"venue"
},
  "geometry": {"coordinates":[-73.948482,40.632252],"type":"Point"}
}