{
  "type": "Feature",
  "properties": {
    "iso:country":"US",
    "sg:address":"7122 Owasco Rd",
    "sg:city":"Auburn",
    "sg:classifiers":[
        {
            "category":"Arena",
            "subcategory":"Sports Club",
            "type":"Entertainment"
        }
    ],
    "sg:phone":"+1 315 730 8439",
    "sg:postcode":"13021",
    "sg:province":"NY",
    "sg:tags":[
        "martial art",
        "instruction"
    ],
    "wof:name":"Underground Mma",
    "wof:placetype":"venue"
},
  "geometry": {"coordinates":[-76.544786,42.914309],"type":"Point"}
}