{
  "type": "Feature",
  "properties": {
    "addr:full":"4 Dubon Ct Farmingdale NY 11735",
    "addr:housenumber":"4",
    "addr:postcode":"11735",
    "addr:street":"Dubon Ct",
    "iso:country":"US",
    "sg:address":"4 Dubon Ct",
    "sg:city":"Farmingdale",
    "sg:classifiers":[
        {
            "category":"Professional",
            "subcategory":"Computer Services",
            "type":"Services"
        }
    ],
    "sg:phone":"+1 631 845 0400",
    "sg:postcode":"11735",
    "sg:province":"NY",
    "sg:tags":[
        "repair"
    ],
    "sg:website":"www.deltacomputersvcs.com",
    "wof:name":"Delta Computer Group Inc",
    "wof:placetype":"venue"
},
  "geometry": {"coordinates":[-73.417249,40.751807],"type":"Point"}
}