{
  "type": "Feature",
  "properties": {
    "iso:country":"US",
    "sg:address":"176 Ross Street",
    "sg:city":"Brooklyn",
    "sg:classifiers":[
        {
            "category":"Health Services",
            "subcategory":"Doctor",
            "type":"Services"
        }
    ],
    "sg:phone":"+1 718 782 5858",
    "sg:postcode":"11211",
    "sg:province":"NY",
    "wof:name":"Lipton Arnold MD",
    "wof:placetype":"venue"
},
  "geometry": {"coordinates":[-73.959186,40.706351],"type":"Point"}
}