{
  "type": "Feature",
  "properties": {
    "iso:country":"US",
    "sg:address":"40 Linden Ln",
    "sg:city":"Farmingville",
    "sg:classifiers":[
        {
            "category":"Banks & Credit Unions",
            "subcategory":"Bank",
            "type":"Services"
        }
    ],
    "sg:phone":"+1 631 698 0310",
    "sg:postcode":"11738",
    "sg:province":"NY",
    "wof:name":"Comp U Nited Ltd",
    "wof:placetype":"venue"
},
  "geometry": {"coordinates":[-73.065006,40.84124],"type":"Point"}
}