{
  "type": "Feature",
  "properties": {
    "iso:country":"US",
    "sg:address":"24 N Lake Ave",
    "sg:city":"Bergen",
    "sg:classifiers":[
        {
            "category":"Autos & Motor Vehicles",
            "subcategory":"Fuel & Gas Station",
            "type":"Retail Goods"
        }
    ],
    "sg:phone":"+1 585 494 1234",
    "sg:postcode":"14416",
    "sg:province":"NY",
    "sg:tags":[
        "oil"
    ],
    "wof:name":"H & K Automotive Repair Ctr",
    "wof:placetype":"venue"
},
  "geometry": {"coordinates":[-77.941847,43.086702],"type":"Point"}
}