{
  "type": "Feature",
  "properties": {
    "iso:country":"US",
    "sg:address":"95 Catherine St",
    "sg:city":"Saratoga Springs",
    "sg:classifiers":[
        {
            "category":"Restaurant",
            "type":"Food & Drink"
        }
    ],
    "sg:phone":"+1   ",
    "sg:postcode":"12866",
    "sg:province":"NY",
    "sg:tags":[
        "catering"
    ],
    "wof:name":"Springs Caterers Inc",
    "wof:placetype":"venue"
},
  "geometry": {"coordinates":[-73.778674,43.090993],"type":"Point"}
}