{
  "type": "Feature",
  "properties": {
    "iso:country":"US",
    "sg:address":"20 N America Dr",
    "sg:city":"Buffalo",
    "sg:classifiers":[
        {
            "category":"Wholesale",
            "subcategory":"Office Equipment",
            "type":"Manufacturing & Wholesale Goods"
        }
    ],
    "sg:phone":"+1 716 332 0502",
    "sg:postcode":"14224",
    "sg:province":"NY",
    "sg:tags":[
        "machine",
        "supply"
    ],
    "wof:name":"Pride Office Products Inc",
    "wof:placetype":"venue"
},
  "geometry": {"coordinates":[-78.74725100000001,42.847485],"type":"Point"}
}