{
  "type": "Feature",
  "properties": {
    "addr:full":"8910 3rd Avenue Brooklyn NY 11209",
    "addr:housenumber":"8910",
    "addr:postcode":"11209",
    "addr:street":"3Rd Avenue",
    "iso:country":"US",
    "sg:address":"8910 3rd Avenue",
    "sg:city":"Brooklyn",
    "sg:classifiers":[
        {
            "category":"Professional",
            "subcategory":"Lawyer & Legal Services",
            "type":"Services"
        }
    ],
    "sg:phone":"+1 718 921 2610",
    "sg:postcode":"11209",
    "sg:province":"NY",
    "wof:name":"Vetri Matthew",
    "wof:placetype":"venue"
},
  "geometry": {"coordinates":[-74.032033,40.621122],"type":"Point"}
}