{
  "type": "Feature",
  "properties": {
    "addr:full":"79 77th Ave Ridgewood NY 11385",
    "addr:housenumber":"79",
    "addr:postcode":"11385",
    "addr:street":"77Th Ave",
    "iso:country":"US",
    "sg:address":"79 77th Ave",
    "sg:city":"Ridgewood",
    "sg:classifiers":[
        {
            "category":"Building & Trades",
            "subcategory":"Plumbing",
            "type":"Services"
        }
    ],
    "sg:phone":"+1 718 456 1954",
    "sg:postcode":"11385",
    "sg:province":"NY",
    "sg:tags":[
        "plumbing",
        "heating",
        "contractor"
    ],
    "wof:name":"Al Haag Plumbing & Heating",
    "wof:placetype":"venue"
},
  "geometry": {"coordinates":[-73.873721,40.706282],"type":"Point"}
}