{
  "type": "Feature",
  "properties": {
    "addr:full":"123 Oak Tree Rd Tappan NY 10983",
    "addr:housenumber":"123",
    "addr:postcode":"10983",
    "addr:street":"Oak Tree Rd",
    "iso:country":"US",
    "sg:address":"123 Oak Tree Rd",
    "sg:city":"Tappan",
    "sg:classifiers":[
        {
            "category":"Personal",
            "subcategory":"Beauty Salon",
            "type":"Services"
        }
    ],
    "sg:phone":"+1 845 359 5284",
    "sg:postcode":"10983",
    "sg:province":"NY",
    "wof:name":"Joe's Hair Styling & Barber Shop",
    "wof:placetype":"venue"
},
  "geometry": {"coordinates":[-73.942886,41.018945],"type":"Point"}
}