{
  "type": "Feature",
  "properties": {
    "addr:full":"347 E 85 St Manhattan NY 10028",
    "addr:housenumber":"347;85",
    "addr:postcode":"10028",
    "addr:street":"E;St",
    "iso:country":"US",
    "sg:address":"347 E 85 St",
    "sg:city":"Manhattan",
    "sg:classifiers":[
        {
            "category":"Restaurant",
            "type":"Food & Drink"
        }
    ],
    "sg:phone":"+1 212 517 3118",
    "sg:postcode":"10028",
    "sg:province":"NY",
    "sg:tags":[
        "italian"
    ],
    "wof:name":"Luna Rossa",
    "wof:placetype":"venue"
},
  "geometry": {"coordinates":[-73.950411,40.776545],"type":"Point"}
}