{
  "type": "Feature",
  "properties": {
    "addr:full":"157 Cumberland Ave Plattsburgh NY 12901",
    "addr:housenumber":"157",
    "addr:postcode":"12901",
    "addr:street":"Cumberland Ave",
    "iso:country":"US",
    "sg:address":"157 Cumberland Ave",
    "sg:city":"Plattsburgh",
    "sg:classifiers":[
        {
            "category":"Professional",
            "subcategory":"Detective & Security Services",
            "type":"Services"
        }
    ],
    "sg:phone":"+1 518 563 4025",
    "sg:postcode":"12901",
    "sg:province":"NY",
    "sg:tags":[
        "car",
        "armored"
    ],
    "sg:website":"www.loomisfargo.com",
    "wof:name":"Loomis Fargo & Co",
    "wof:placetype":"venue"
},
  "geometry": {"coordinates":[-73.448723,44.708402],"type":"Point"}
}