{
  "type": "Feature",
  "properties": {
    "iso:country":"US",
    "sg:address":"42 Gables Dr",
    "sg:city":"Hicksville",
    "sg:classifiers":[
        {
            "category":"Building & Trades",
            "subcategory":"Construction",
            "type":"Services"
        }
    ],
    "sg:phone":"+1 516 681 5154",
    "sg:postcode":"11801",
    "sg:province":"NY",
    "sg:tags":[
        "contractor"
    ],
    "wof:name":"High End Home Improvements",
    "wof:placetype":"venue"
},
  "geometry": {"coordinates":[-73.509289,40.767421],"type":"Point"}
}