{
  "type": "Feature",
  "properties": {
    "iso:country":"US",
    "sg:address":"126 W 11 St",
    "sg:city":"New York",
    "sg:classifiers":[
        {
            "category":"Professional",
            "subcategory":"Computer Services",
            "type":"Services"
        }
    ],
    "sg:phone":"+1   ",
    "sg:postcode":"10011",
    "sg:province":"NY",
    "sg:tags":[
        "programming"
    ],
    "wof:name":"Televerse Inc",
    "wof:placetype":"venue"
},
  "geometry": {"coordinates":[-74.000801,40.736318],"type":"Point"}
}