{
  "type": "Feature",
  "properties": {
    "addr:full":"2501 Browncroft Blvd Rochester NY 14625",
    "addr:housenumber":"2501",
    "addr:postcode":"14625",
    "addr:street":"Browncroft Blvd",
    "iso:country":"US",
    "sg:address":"2501 Browncroft Blvd",
    "sg:city":"Rochester",
    "sg:classifiers":[
        {
            "category":"Restaurant",
            "type":"Food & Drink"
        }
    ],
    "sg:phone":"+1 585 248 2960",
    "sg:postcode":"14625",
    "sg:province":"NY",
    "wof:name":"Browncroft Family Restaurant",
    "wof:placetype":"venue"
},
  "geometry": {"coordinates":[-77.50583,43.153586],"type":"Point"}
}