{
  "type": "Feature",
  "properties": {
    "iso:country":"US",
    "sg:address":"1770 Mecklenburg Rd Apt 1",
    "sg:city":"Ithaca",
    "sg:classifiers":[
        {
            "category":"Home & Garden",
            "subcategory":"Building Materials",
            "type":"Retail Goods"
        },
        {
            "category":"Building & Trades",
            "subcategory":"Construction",
            "type":"Services"
        }
    ],
    "sg:phone":"+1 607 256 8349",
    "sg:postcode":"14850",
    "sg:province":"NY",
    "sg:tags":[
        "insulation",
        "product",
        "conservation",
        "energy",
        "contractor"
    ],
    "sg:website":"http://www.hybridinsulationsystems.com",
    "wof:name":"Hybrid Insulation Systems",
    "wof:placetype":"venue"
},
  "geometry": {"coordinates":[-76.593138,42.45215],"type":"Point"}
}