{
  "type": "Feature",
  "properties": {
    "addr:full":"725 7th Ave Watervliet NY 12189",
    "addr:housenumber":"725",
    "addr:postcode":"12189",
    "addr:street":"7Th Ave",
    "iso:country":"US",
    "sg:address":"725 7th Ave",
    "sg:city":"Watervliet",
    "sg:classifiers":[
        {
            "category":"Arts & Performance",
            "subcategory":"Theater",
            "type":"Entertainment"
        }
    ],
    "sg:phone":"+1 518 270 8375",
    "sg:postcode":"12189",
    "sg:province":"NY",
    "sg:tags":[
        "live",
        "music"
    ],
    "wof:name":"Diamond Entertainment Pro DJ",
    "wof:placetype":"venue"
},
  "geometry": {"coordinates":[-73.709547,42.716572],"type":"Point"}
}