{
  "type": "Feature",
  "properties": {
    "iso:country":"US",
    "sg:address":"10402 Metropolitan Ave",
    "sg:city":"Forest Hills",
    "sg:classifiers":[
        {
            "category":"Building & Trades",
            "subcategory":"Locksmith",
            "type":"Services"
        }
    ],
    "sg:phone":"+1 718 301 8266",
    "sg:postcode":"11375",
    "sg:province":"NY",
    "sg:tags":[
        "key"
    ],
    "wof:name":"20 Street Lock And Key Of Flushing",
    "wof:placetype":"venue"
},
  "geometry": {"coordinates":[-73.848986,40.710028],"type":"Point"}
}