{
  "type": "Feature",
  "properties": {
    "addr:full":"2074 Valentine Ave Bronx NY 10457",
    "addr:housenumber":"2074",
    "addr:postcode":"10457",
    "addr:street":"Valentine Ave",
    "iso:country":"US",
    "sg:address":"2074 Valentine Ave",
    "sg:city":"Bronx",
    "sg:classifiers":[
        {
            "category":"Organizations",
            "subcategory":"Religious Organization",
            "type":"Services"
        }
    ],
    "sg:phone":"+1 718 364 9894",
    "sg:postcode":"10457",
    "sg:province":"NY",
    "sg:tags":[
        "church"
    ],
    "wof:name":"Bronx Community Baptist",
    "wof:placetype":"venue"
},
  "geometry": {"coordinates":[-73.900245,40.851132],"type":"Point"}
}