{
  "type": "Feature",
  "properties": {
    "addr:full":"25 S Regent St Port Chester NY 10573",
    "addr:housenumber":"25",
    "addr:postcode":"10573",
    "addr:street":"S Regent St",
    "iso:country":"US",
    "sg:address":"25 S Regent St",
    "sg:city":"Port Chester",
    "sg:classifiers":[
        {
            "category":"Professional",
            "subcategory":"Management & Consulting",
            "type":"Services"
        }
    ],
    "sg:phone":"+1 914 937 8879",
    "sg:postcode":"10573",
    "sg:province":"NY",
    "sg:tags":[
        "consultant",
        "educational"
    ],
    "sg:website":"www.nprinc.com",
    "wof:name":"National Professional Rsrcs",
    "wof:placetype":"venue"
},
  "geometry": {"coordinates":[-73.674137,41.005286],"type":"Point"}
}