{
  "type": "Feature",
  "properties": {
    "iso:country":"US",
    "sg:address":"440 Scottsville Mumford Rd",
    "sg:city":"Scottsville",
    "sg:classifiers":[
        {
            "category":"Bars & Pubs",
            "subcategory":"Nightclub",
            "type":"Food & Drink"
        }
    ],
    "sg:phone":"+1 585 889 3732",
    "sg:postcode":"14546",
    "sg:province":"NY",
    "sg:tags":[
        "nightlife"
    ],
    "wof:name":"Foxy's",
    "wof:placetype":"venue"
},
  "geometry": {"coordinates":[-77.775432,43.013561],"type":"Point"}
}