{
  "type": "Feature",
  "properties": {
    "iso:country":"US",
    "sg:address":"7100 Yellowstone Boulevard",
    "sg:city":"Forest Hills",
    "sg:classifiers":[
        {
            "category":"Place Of Worship",
            "subcategory":"Synagogue",
            "type":"Public Place"
        }
    ],
    "sg:phone":"+1 718 268 7100",
    "sg:postcode":"11375",
    "sg:province":"NY",
    "wof:name":"Young Israel of Forst Hls",
    "wof:placetype":"venue"
},
  "geometry": {"coordinates":[-73.852872,40.722387],"type":"Point"}
}