{
  "type": "Feature",
  "properties": {
    "addr:full":"6926 60th Ave Bsmt Maspeth NY 11378",
    "addr:housenumber":"6926",
    "addr:postcode":"11378",
    "addr:street":"60Th Ave",
    "iso:country":"US",
    "sg:address":"6926 60th Ave Bsmt",
    "sg:city":"Maspeth",
    "sg:classifiers":[
        {
            "category":"Building & Trades",
            "subcategory":"Construction",
            "type":"Services"
        }
    ],
    "sg:phone":"+1 718 505 2359",
    "sg:postcode":"11378",
    "sg:province":"NY",
    "sg:tags":[
        "wallcoverings-installation",
        "wallpaper",
        "painting",
        "contractor"
    ],
    "wof:name":"Tsolias Painting Corp",
    "wof:placetype":"venue"
},
  "geometry": {"coordinates":[-73.89188,40.721829],"type":"Point"}
}