{
  "type": "Feature",
  "properties": {
    "addr:full":"1078 Coney Island Ave Brooklyn NY 11230",
    "addr:housenumber":"1078",
    "addr:postcode":"11230",
    "addr:street":"Coney Island Ave",
    "iso:country":"US",
    "sg:address":"1078 Coney Island Ave",
    "sg:city":"Brooklyn",
    "sg:classifiers":[
        {
            "category":"Shopping",
            "subcategory":"Crafts & Fabrics",
            "type":"Retail Goods"
        }
    ],
    "sg:phone":"+1   ",
    "sg:postcode":"11230",
    "sg:province":"NY",
    "sg:tags":[
        "sewing"
    ],
    "wof:name":"ATIF Fabrics & Appliances",
    "wof:placetype":"venue"
},
  "geometry": {"coordinates":[-73.966244,40.630036],"type":"Point"}
}