{
  "type": "Feature",
  "properties": {
    "addr:full":"172 W Islip Rd West Islip NY 11795",
    "addr:housenumber":"172",
    "addr:postcode":"11795",
    "addr:street":"W Islip Rd",
    "iso:country":"US",
    "sg:address":"172 W Islip Rd",
    "sg:city":"West Islip",
    "sg:classifiers":[
        {
            "category":"Personal",
            "subcategory":"Beauty Salon",
            "type":"Services"
        }
    ],
    "sg:phone":"+1 631 321 6245",
    "sg:postcode":"11795",
    "sg:province":"NY",
    "wof:name":"Perfect Colored Nails",
    "wof:placetype":"venue"
},
  "geometry": {"coordinates":[-73.316948,40.693421],"type":"Point"}
}