{
  "type": "Feature",
  "properties": {
    "addr:full":"700 Hartwell Ave East Syracuse NY 13057",
    "addr:housenumber":"700",
    "addr:postcode":"13057",
    "addr:street":"Hartwell Ave",
    "iso:country":"US",
    "sg:address":"700 Hartwell Ave",
    "sg:city":"East Syracuse",
    "sg:classifiers":[
        {
            "category":"Professional",
            "subcategory":"Advertising",
            "type":"Services"
        }
    ],
    "sg:phone":"+1 315 463 2099",
    "sg:postcode":"13057",
    "sg:province":"NY",
    "sg:tags":[
        "outdoor"
    ],
    "wof:name":"Park Outdoor Advertising of NY",
    "wof:placetype":"venue"
},
  "geometry": {"coordinates":[-76.06272800000001,43.070673],"type":"Point"}
}