{
  "type": "Feature",
  "properties": {
    "iso:country":"US",
    "sg:address":"10 Cuttermill Rd",
    "sg:city":"Great Neck",
    "sg:classifiers":[
        {
            "category":"Manufacturing",
            "subcategory":"Paper Products",
            "type":"Manufacturing & Wholesale Goods"
        }
    ],
    "sg:phone":"+1 516 482 3229",
    "sg:postcode":"11021",
    "sg:province":"NY",
    "sg:tags":[
        "box"
    ],
    "wof:name":"Big Plus Inc",
    "wof:placetype":"venue"
},
  "geometry": {"coordinates":[-73.728702,40.7867],"type":"Point"}
}