{
  "type": "Feature",
  "properties": {
    "addr:full":"650 Baychester Ave Bronx NY 10475",
    "addr:housenumber":"650",
    "addr:postcode":"10475",
    "addr:street":"Baychester Ave",
    "iso:country":"US",
    "sg:address":"650 Baychester Ave",
    "sg:city":"Bronx",
    "sg:classifiers":[
        {
            "category":"Education",
            "subcategory":"School",
            "type":"Public Place"
        }
    ],
    "sg:phone":"+1 718 904 5550",
    "sg:postcode":"10475",
    "sg:province":"NY",
    "wof:name":"PS 153",
    "wof:placetype":"venue"
},
  "geometry": {"coordinates":[-73.833698,40.87554],"type":"Point"}
}