{
  "type": "Feature",
  "properties": {
    "addr:full":"116 Marine St Farmingdale NY 11735",
    "addr:housenumber":"116",
    "addr:postcode":"11735",
    "addr:street":"Marine St",
    "iso:country":"US",
    "sg:address":"116 Marine St",
    "sg:city":"Farmingdale",
    "sg:classifiers":[
        {
            "category":"Manufacturing",
            "subcategory":"Tools & Machinery",
            "type":"Manufacturing & Wholesale Goods"
        }
    ],
    "sg:phone":"+1 631 249 5111",
    "sg:postcode":"11735",
    "sg:province":"NY",
    "sg:tags":[
        "machine",
        "shop"
    ],
    "wof:name":"Main Machine & Tool Co",
    "wof:placetype":"venue"
},
  "geometry": {"coordinates":[-73.417388,40.714791],"type":"Point"}
}