{
  "type": "Feature",
  "properties": {
    "addr:full":"655 W Jericho Tpke Smithtown NY 11787",
    "addr:housenumber":"655",
    "addr:postcode":"11787",
    "addr:street":"W Jericho Tpke",
    "iso:country":"US",
    "sg:address":"655 W Jericho Tpke",
    "sg:city":"Smithtown",
    "sg:classifiers":[
        {
            "category":"Autos & Motor Vehicles",
            "subcategory":"Fuel & Gas Station",
            "type":"Retail Goods"
        },
        {
            "category":"Food & Beverages",
            "subcategory":"Groceries & Convenience Stores",
            "type":"Retail Goods"
        }
    ],
    "sg:phone":"+1 631 360 0196",
    "sg:postcode":"11787",
    "sg:province":"NY",
    "sg:website":"www.7-eleven.com",
    "wof:name":"7-Eleven",
    "wof:placetype":"venue"
},
  "geometry": {"coordinates":[-73.22817999999999,40.849658],"type":"Point"}
}