{
  "type": "Feature",
  "properties": {
    "addr:full":"656 Cary Ave Staten Island NY 10310",
    "addr:housenumber":"656",
    "addr:postcode":"10310",
    "addr:street":"Cary Ave",
    "iso:country":"US",
    "sg:address":"656 Cary Ave",
    "sg:city":"Staten Island",
    "sg:classifiers":[
        {
            "category":"Organizations",
            "subcategory":"Religious Organization",
            "type":"Services"
        }
    ],
    "sg:phone":"+1 718 273 5245",
    "sg:postcode":"10310",
    "sg:province":"NY",
    "sg:tags":[
        "church"
    ],
    "sg:website":"www.houseontherocksi.org",
    "wof:name":"House On The Rock",
    "wof:placetype":"venue"
},
  "geometry": {"coordinates":[-74.12330900000001,40.631847],"type":"Point"}
}