{
  "type": "Feature",
  "properties": {
    "addr:full":"100B Forsyth St Manhattan NY 10002",
    "addr:housenumber":"100b",
    "addr:postcode":"10002",
    "addr:street":"Forsyth St",
    "iso:country":"US",
    "sg:address":"100B Forsyth St",
    "sg:city":"Manhattan",
    "sg:classifiers":[
        {
            "category":"Shopping",
            "subcategory":"Crafts & Fabrics",
            "type":"Retail Goods"
        }
    ],
    "sg:phone":"+1 206 365 4083",
    "sg:postcode":"10002",
    "sg:province":"NY",
    "sg:tags":[
        "art",
        "supply"
    ],
    "sg:website":"artprimo.com",
    "wof:name":"Art Primo",
    "wof:placetype":"venue"
},
  "geometry": {"coordinates":[-73.992875,40.718322],"type":"Point"}
}