{
  "type": "Feature",
  "properties": {
    "addr:full":"229 Merritts Rd Farmingdale NY 11735",
    "addr:housenumber":"229",
    "addr:postcode":"11735",
    "addr:street":"Merritts Rd",
    "iso:country":"US",
    "sg:address":"229 Merritts Rd",
    "sg:city":"Farmingdale",
    "sg:classifiers":[
        {
            "category":"Retail",
            "subcategory":"Auto Repair",
            "type":"Services"
        }
    ],
    "sg:phone":"+1 516 293 2256",
    "sg:postcode":"11735",
    "sg:province":"NY",
    "sg:tags":[
        "automobile",
        "lubrication"
    ],
    "wof:name":"Lube & Brake Doctors Inc",
    "wof:placetype":"venue"
},
  "geometry": {"coordinates":[-73.45867200000001,40.719076],"type":"Point"}
}