{
  "type": "Feature",
  "properties": {
    "iso:country":"US",
    "sg:address":"258 Foster Hill Rd",
    "sg:city":"Greene",
    "sg:classifiers":[
        {
            "category":"Building & Trades",
            "subcategory":"Construction",
            "type":"Services"
        }
    ],
    "sg:phone":"+1 607 656 5382",
    "sg:postcode":"13778",
    "sg:province":"NY",
    "sg:tags":[
        "carpentry",
        "contractor"
    ],
    "wof:name":"Eugene A Browning Cabinetry",
    "wof:placetype":"venue"
},
  "geometry": {"coordinates":[-75.848004,42.306121],"type":"Point"}
}