{
  "type": "Feature",
  "properties": {
    "iso:country":"US",
    "sg:address":"85 Norman Ave",
    "sg:city":"Brooklyn",
    "sg:classifiers":[
        {
            "category":"Real Estate",
            "subcategory":"Real Estate Services",
            "type":"Services"
        }
    ],
    "sg:phone":"+1 718 383 2000",
    "sg:postcode":"11222",
    "sg:province":"NY",
    "wof:name":"Peters Evan Real Estate",
    "wof:placetype":"venue"
},
  "geometry": {"coordinates":[-73.95223799999999,40.725521],"type":"Point"}
}