{
  "type": "Feature",
  "properties": {
    "iso:country":"US",
    "sg:address":"73 Spring St",
    "sg:city":"New York",
    "sg:classifiers":[
        {
            "category":"Professional",
            "subcategory":"Business Services",
            "type":"Services"
        }
    ],
    "sg:phone":"+1 212 343 2534",
    "sg:postcode":"10012",
    "sg:province":"NY",
    "sg:tags":[
        "recording",
        "production"
    ],
    "wof:name":"Third Ear Music",
    "wof:placetype":"venue"
},
  "geometry": {"coordinates":[-73.99748,40.72247],"type":"Point"}
}