{
  "type": "Feature",
  "properties": {
    "addr:full":"299 Bedford Ave Brooklyn NY 11211",
    "addr:housenumber":"299",
    "addr:postcode":"11211",
    "addr:street":"Bedford Ave",
    "iso:country":"US",
    "sg:address":"299 Bedford Ave",
    "sg:city":"Brooklyn",
    "sg:classifiers":[
        {
            "category":"Real Estate",
            "subcategory":"Real Estate Agent",
            "type":"Services"
        }
    ],
    "sg:phone":"+1 718 486 4400",
    "sg:postcode":"11211",
    "sg:province":"NY",
    "wof:name":"Prudential Douglas Elliman",
    "wof:placetype":"venue"
},
  "geometry": {"coordinates":[-73.961912,40.713447],"type":"Point"}
}