{
  "type": "Feature",
  "properties": {
    "addr:full":"13332 41st Rd Flushing NY 11355",
    "addr:housenumber":"13332",
    "addr:postcode":"11355",
    "addr:street":"41St Rd",
    "iso:country":"US",
    "sg:address":"13332 41st Rd",
    "sg:city":"Flushing",
    "sg:classifiers":[
        {
            "category":"Banks & Credit Unions",
            "subcategory":"Bank",
            "type":"Services"
        }
    ],
    "sg:phone":"+1 718 358 7403",
    "sg:postcode":"11355",
    "sg:province":"NY",
    "sg:tags":[
        "company",
        "trust"
    ],
    "wof:name":"S U Ba Khin Memorial Trust",
    "wof:placetype":"venue"
},
  "geometry": {"coordinates":[-73.829095,40.757459],"type":"Point"}
}