{
  "type": "Feature",
  "properties": {
    "addr:full":"36 Snediker Ave Brooklyn NY 11207",
    "addr:housenumber":"36",
    "addr:postcode":"11207",
    "addr:street":"Snediker Ave",
    "iso:country":"US",
    "sg:address":"36 Snediker Ave",
    "sg:city":"Brooklyn",
    "sg:classifiers":[
        {
            "category":"Professional",
            "subcategory":"Detective & Security Services",
            "type":"Services"
        }
    ],
    "sg:phone":"+1 718 385 0436",
    "sg:postcode":"11207",
    "sg:province":"NY",
    "sg:tags":[
        "guard",
        "patrol"
    ],
    "wof:name":"Cannady Securities Svc Inc",
    "wof:placetype":"venue"
},
  "geometry": {"coordinates":[-73.90228,40.67424],"type":"Point"}
}