{
  "type": "Feature",
  "properties": {
    "addr:full":"86 Blossom Heath Ave Lynbrook NY 11563",
    "addr:housenumber":"86",
    "addr:postcode":"11563",
    "addr:street":"Blossom Heath Ave",
    "iso:country":"US",
    "sg:address":"86 Blossom Heath Ave",
    "sg:city":"Lynbrook",
    "sg:classifiers":[
        {
            "category":"Home & Garden",
            "subcategory":"Home Furnishings",
            "type":"Retail Goods"
        }
    ],
    "sg:phone":"+1   ",
    "sg:postcode":"11563",
    "sg:province":"NY",
    "wof:name":"Vista Sales",
    "wof:placetype":"venue"
},
  "geometry": {"coordinates":[-73.676886,40.66199],"type":"Point"}
}