{
  "type": "Feature",
  "properties": {
    "addr:full":"5420 13th Ave Brooklyn NY 11219",
    "addr:housenumber":"5420",
    "addr:postcode":"11219",
    "addr:street":"13Th Ave",
    "iso:country":"US",
    "sg:address":"5420 13th Ave",
    "sg:city":"Brooklyn",
    "sg:classifiers":[
        {
            "category":"Banks & Credit Unions",
            "subcategory":"Bank",
            "type":"Services"
        }
    ],
    "sg:phone":"+1 718 627 3999",
    "sg:postcode":"11219",
    "sg:province":"NY",
    "sg:tags":[
        "national",
        "commercial"
    ],
    "wof:name":"Citibank",
    "wof:placetype":"venue"
},
  "geometry": {"coordinates":[-73.99564100000001,40.631757],"type":"Point"}
}