{
  "type": "Feature",
  "properties": {
    "addr:full":"18 Eldridge St between Canal St & Division St Manhattan NY 10002",
    "addr:housenumber":"18",
    "addr:postcode":"10002",
    "addr:street":"Eldridge St;Canal St & Division St",
    "iso:country":"US",
    "sg:address":"18 Eldridge St between Canal St & Division St",
    "sg:city":"Manhattan",
    "sg:classifiers":[
        {
            "category":"Juice Bar",
            "subcategory":"None",
            "type":"Food & Drink"
        },
        {
            "category":"Coffee & Tea",
            "type":"Food & Drink"
        },
        {
            "category":"Restaurant",
            "type":"Food & Drink"
        }
    ],
    "sg:postcode":"10002",
    "sg:province":"NY",
    "sg:tags":[
        "smoothy",
        "taiwanese"
    ],
    "sg:website":"www.tbaar.com",
    "wof:name":"T Baar IV",
    "wof:placetype":"venue"
},
  "geometry": {"coordinates":[-73.99338899999999,40.714833],"type":"Point"}
}