{
  "type": "Feature",
  "properties": {
    "iso:country":"US",
    "sg:address":"20 Maple Ave",
    "sg:city":"Sodus",
    "sg:classifiers":[
        {
            "category":"Health Services",
            "subcategory":"Doctor",
            "type":"Services"
        }
    ],
    "sg:phone":"+1 315 483 8913",
    "sg:postcode":"14551",
    "sg:province":"NY",
    "sg:tags":[
        "dentist"
    ],
    "wof:name":"James R Burk DDS",
    "wof:placetype":"venue"
},
  "geometry": {"coordinates":[-77.061397,43.236363],"type":"Point"}
}