{
  "type": "Feature",
  "properties": {
    "iso:country":"US",
    "sg:address":"206 Paradise Rd",
    "sg:city":"East Amherst",
    "sg:classifiers":[
        {
            "category":"Food & Beverages",
            "subcategory":"Specialty",
            "type":"Retail Goods"
        }
    ],
    "sg:phone":"+1   ",
    "sg:postcode":"14051",
    "sg:province":"NY",
    "wof:name":"Dove Healthy Resrcs",
    "wof:placetype":"venue"
},
  "geometry": {"coordinates":[-78.710883,43.00698],"type":"Point"}
}