{
  "type": "Feature",
  "properties": {
    "iso:country":"US",
    "sg:address":"270 W 39 St",
    "sg:city":"New York",
    "sg:classifiers":[
        {
            "category":"Shopping",
            "subcategory":"Clothing, Apparel, & Fashions",
            "type":"Retail Goods"
        }
    ],
    "sg:phone":"+1 212 944 2216",
    "sg:postcode":"10018",
    "sg:province":"NY",
    "sg:tags":[
        "garment"
    ],
    "wof:name":"KAS Apparel",
    "wof:placetype":"venue"
},
  "geometry": {"coordinates":[-73.98967500000001,40.754407],"type":"Point"}
}