{
  "type": "Feature",
  "properties": {
    "iso:country":"US",
    "sg:address":"30 Commercial Dr",
    "sg:city":"Castleton On Hudson",
    "sg:classifiers":[
        {
            "category":"Insurance",
            "subcategory":"Health Insurance",
            "type":"Services"
        }
    ],
    "sg:phone":"+1 518 732 7160",
    "sg:postcode":"12033",
    "sg:province":"NY",
    "sg:tags":[
        "market"
    ],
    "wof:name":"New Country Value Foods",
    "wof:placetype":"venue"
},
  "geometry": {"coordinates":[-73.675206,42.513331],"type":"Point"}
}