{
  "type": "Feature",
  "properties": {
    "iso:country":"US",
    "sg:address":"749 1st Ave",
    "sg:city":"Troy",
    "sg:classifiers":[
        {
            "category":"Building & Trades",
            "subcategory":"Electrical",
            "type":"Services"
        }
    ],
    "sg:phone":"+1 518 237 5564",
    "sg:postcode":"12182",
    "sg:province":"NY",
    "sg:tags":[
        "work",
        "electrical",
        "electric",
        "contractor"
    ],
    "wof:name":"Mike Connors Electrical Contr",
    "wof:placetype":"venue"
},
  "geometry": {"coordinates":[-73.67546,42.781304],"type":"Point"}
}