{
  "type": "Feature",
  "properties": {
    "addr:full":"5205 Broadway St Lancaster NY 14086",
    "addr:housenumber":"5205",
    "addr:postcode":"14086",
    "addr:street":"Broadway St",
    "iso:country":"US",
    "sg:address":"5205 Broadway St",
    "sg:city":"Lancaster",
    "sg:classifiers":[
        {
            "category":"Building & Trades",
            "subcategory":"Construction",
            "type":"Services"
        }
    ],
    "sg:phone":"+1 716 681 2486",
    "sg:postcode":"14086",
    "sg:province":"NY",
    "sg:tags":[
        "contractor"
    ],
    "wof:name":"Kcm Management LLC",
    "wof:placetype":"venue"
},
  "geometry": {"coordinates":[-78.682806,42.901219],"type":"Point"}
}