{
  "type": "Feature",
  "properties": {
    "iso:country":"US",
    "sg:address":"4319 14th Avenue",
    "sg:city":"Brooklyn",
    "sg:classifiers":[
        {
            "category":"Shopping",
            "subcategory":"Antiques",
            "type":"Retail Goods"
        }
    ],
    "sg:phone":"+1 718 633 6393",
    "sg:postcode":"11219",
    "sg:province":"NY",
    "wof:name":"Antiques & Decorations",
    "wof:placetype":"venue"
},
  "geometry": {"coordinates":[-73.986812,40.6365],"type":"Point"}
}