{
  "type": "Feature",
  "properties": {
    "iso:country":"US",
    "sg:address":"7658 Gifford Rd",
    "sg:city":"Rome",
    "sg:classifiers":[
        {
            "category":"Wholesale",
            "subcategory":"Electrical",
            "type":"Manufacturing & Wholesale Goods"
        }
    ],
    "sg:phone":"+1 315 336 1328",
    "sg:postcode":"13440",
    "sg:province":"NY",
    "sg:tags":[
        "instrument",
        "electronic"
    ],
    "wof:name":"Eastern Labs",
    "wof:placetype":"venue"
},
  "geometry": {"coordinates":[-75.488108,43.230154],"type":"Point"}
}