{
  "type": "Feature",
  "properties": {
    "iso:country":"US",
    "sg:address":"130 South Howell Ave",
    "sg:city":"Centereach",
    "sg:classifiers":[
        {
            "category":"Real Estate",
            "subcategory":"Real Estate Services",
            "type":"Services"
        }
    ],
    "sg:phone":"+1 631 846 7724",
    "sg:postcode":"11720",
    "sg:province":"NY",
    "sg:website":"abellahomestaging.com/",
    "wof:name":"Abella Home Staging & Redesign",
    "wof:placetype":"venue"
},
  "geometry": {"coordinates":[-73.069258,40.848033],"type":"Point"}
}