{
  "type": "Feature",
  "properties": {
    "iso:country":"US",
    "sg:address":"5 Electric St",
    "sg:city":"Patchogue",
    "sg:classifiers":[
        {
            "category":"Retail",
            "subcategory":"Repair Shop",
            "type":"Services"
        }
    ],
    "sg:phone":"+1 631 475 0101",
    "sg:postcode":"11772",
    "sg:province":"NY",
    "sg:tags":[
        "welding"
    ],
    "wof:name":"Frame Performance",
    "wof:placetype":"venue"
},
  "geometry": {"coordinates":[-73.02225799999999,40.761374],"type":"Point"}
}