{
  "type": "Feature",
  "properties": {
    "addr:full":"4331 Katonah Ave Bronx NY 10470",
    "addr:housenumber":"4331",
    "addr:postcode":"10470",
    "addr:street":"Katonah Ave",
    "iso:country":"US",
    "sg:address":"4331 Katonah Ave",
    "sg:city":"Bronx",
    "sg:classifiers":[
        {
            "category":"Building & Trades",
            "subcategory":"Construction",
            "type":"Services"
        }
    ],
    "sg:phone":"+1 718 231 7765",
    "sg:postcode":"10470",
    "sg:province":"NY",
    "sg:tags":[
        "resurfacing",
        "laying",
        "refinishing",
        "floor"
    ],
    "wof:name":"Dr Floors",
    "wof:placetype":"venue"
},
  "geometry": {"coordinates":[-73.867701,40.900312],"type":"Point"}
}