{
  "type": "Feature",
  "properties": {
    "iso:country":"US",
    "sg:address":"5003 Lake Rd",
    "sg:city":"Williamson",
    "sg:classifiers":[
        {
            "category":"Recreation",
            "subcategory":"Marina",
            "type":"Entertainment"
        }
    ],
    "sg:phone":"+1   ",
    "sg:postcode":"14589",
    "sg:province":"NY",
    "sg:tags":[
        "operation",
        "camp"
    ],
    "wof:name":"Paradise Lagoon",
    "wof:placetype":"venue"
},
  "geometry": {"coordinates":[-77.143376,43.283847],"type":"Point"}
}