{
  "type": "Feature",
  "properties": {
    "addr:full":"225 W 24th St Deer Park NY 11729",
    "addr:housenumber":"225",
    "addr:postcode":"11729",
    "addr:street":"W 24Th St",
    "iso:country":"US",
    "sg:address":"225 W 24th St",
    "sg:city":"Deer Park",
    "sg:classifiers":[
        {
            "category":"Personal",
            "subcategory":"Beauty Salon",
            "type":"Services"
        }
    ],
    "sg:phone":"+1   ",
    "sg:postcode":"11729",
    "sg:province":"NY",
    "sg:tags":[
        "shop"
    ],
    "wof:name":"Skin Perfect Inc",
    "wof:placetype":"venue"
},
  "geometry": {"coordinates":[-73.347652,40.749713],"type":"Point"}
}