{
  "type": "Feature",
  "properties": {
    "iso:country":"US",
    "sg:address":"107 Harrison Ave",
    "sg:city":"Bethpage",
    "sg:classifiers":[
        {
            "category":"Building & Trades",
            "subcategory":"Construction",
            "type":"Services"
        }
    ],
    "sg:phone":"+1 516 433 3857",
    "sg:postcode":"11714",
    "sg:province":"NY",
    "sg:tags":[
        "house"
    ],
    "wof:name":"John Sardo Construction",
    "wof:placetype":"venue"
},
  "geometry": {"coordinates":[-73.48782,40.740283],"type":"Point"}
}