{
  "type": "Feature",
  "properties": {
    "iso:country":"US",
    "sg:address":"108 W Buffalo St",
    "sg:city":"Ithaca",
    "sg:classifiers":[
        {
            "category":"Wholesale",
            "subcategory":"Durable Goods & Equipment",
            "type":"Manufacturing & Wholesale Goods"
        }
    ],
    "sg:phone":"+1 607 277 4641",
    "sg:postcode":"14850",
    "sg:province":"NY",
    "sg:tags":[
        "representative",
        "manufacturer"
    ],
    "wof:name":"Kevin Brew Sales",
    "wof:placetype":"venue"
},
  "geometry": {"coordinates":[-76.500731,42.441342],"type":"Point"}
}