{
  "type": "Feature",
  "properties": {
    "addr:full":"7905 Northern Blvd Jackson Heights NY 11372",
    "addr:housenumber":"7905",
    "addr:postcode":"11372",
    "addr:street":"Northern Blvd",
    "iso:country":"US",
    "sg:address":"7905 Northern Blvd",
    "sg:city":"Jackson Heights",
    "sg:classifiers":[
        {
            "category":"Cafe",
            "type":"Food & Drink"
        }
    ],
    "sg:menulink":"http://www.allmenus.com/ny/queens/114554-cafe-salamanca-restaurant/menu/",
    "sg:phone":"+1 718 458 2446",
    "sg:postcode":"11372",
    "sg:province":"NY",
    "sg:tags":[
        "spanish"
    ],
    "wof:name":"Cafe Salamanca Restaurant",
    "wof:placetype":"venue"
},
  "geometry": {"coordinates":[-73.88812,40.755319],"type":"Point"}
}