{
  "type": "Feature",
  "properties": {
    "addr:full":"3 Woodpath Dr Northport NY 11768",
    "addr:housenumber":"3",
    "addr:postcode":"11768",
    "addr:street":"Woodpath Dr",
    "iso:country":"US",
    "sg:address":"3 Woodpath Dr",
    "sg:city":"Northport",
    "sg:classifiers":[
        {
            "category":"Professional",
            "subcategory":"Management & Consulting",
            "type":"Services"
        }
    ],
    "sg:phone":"+1 631 754 9233",
    "sg:postcode":"11768",
    "sg:province":"NY",
    "sg:tags":[
        "consultant"
    ],
    "wof:name":"Deacom Data Consultants Inc",
    "wof:placetype":"venue"
},
  "geometry": {"coordinates":[-73.318883,40.908268],"type":"Point"}
}