{
  "type": "Feature",
  "properties": {
    "iso:country":"US",
    "sg:address":"226 5th Ave",
    "sg:city":"New York",
    "sg:classifiers":[
        {
            "category":"Wholesale",
            "subcategory":"Non-durable Goods",
            "type":"Manufacturing & Wholesale Goods"
        }
    ],
    "sg:phone":"+1 212 725 9100",
    "sg:postcode":"10001",
    "sg:province":"NY",
    "sg:tags":[
        "importer"
    ],
    "wof:name":"Lavie International",
    "wof:placetype":"venue"
},
  "geometry": {"coordinates":[-73.988006,40.743751],"type":"Point"}
}