{
  "type": "Feature",
  "properties": {
    "addr:full":"35 Montauk Hwy Copiague NY 11726",
    "addr:housenumber":"35",
    "addr:postcode":"11726",
    "addr:street":"Montauk Hwy",
    "iso:country":"US",
    "sg:address":"35 Montauk Hwy",
    "sg:city":"Copiague",
    "sg:classifiers":[
        {
            "category":"Autos & Motor Vehicles",
            "subcategory":"Automobile Sales",
            "type":"Retail Goods"
        }
    ],
    "sg:phone":"+1 718 725 1100",
    "sg:postcode":"11726",
    "sg:province":"NY",
    "sg:tags":[
        "car",
        "dealer"
    ],
    "wof:name":"Long Island Auto Network",
    "wof:placetype":"venue"
},
  "geometry": {"coordinates":[-73.403565,40.667759],"type":"Point"}
}