{
  "type": "Feature",
  "properties": {
    "addr:full":"5629 Main St Buffalo NY 14221",
    "addr:housenumber":"5629",
    "addr:postcode":"14221",
    "addr:street":"Main St",
    "iso:country":"US",
    "sg:address":"5629 Main St",
    "sg:city":"Buffalo",
    "sg:classifiers":[
        {
            "category":"Restaurant",
            "type":"Food & Drink"
        }
    ],
    "sg:menulink":"http://www.allmenus.com/ny/amherst/253603-creekview-restaurant/menu/",
    "sg:phone":"+1 716 632 9373",
    "sg:postcode":"14221",
    "sg:province":"NY",
    "sg:tags":[
        "sandwich",
        "salad",
        "seafood",
        "soup",
        "american",
        "steakhouse",
        "pasta"
    ],
    "wof:name":"Creekview Restaurant",
    "wof:placetype":"venue"
},
  "geometry": {"coordinates":[-78.743302,42.963109],"type":"Point"}
}