{
  "type": "Feature",
  "properties": {
    "addr:full":"912 Soundview Ave Bronx NY 10473",
    "addr:housenumber":"912",
    "addr:postcode":"10473",
    "addr:street":"Soundview Ave",
    "iso:country":"US",
    "sg:address":"912 Soundview Ave",
    "sg:city":"Bronx",
    "sg:classifiers":[
        {
            "category":"Retail",
            "subcategory":"Repair Shop",
            "type":"Services"
        }
    ],
    "sg:phone":"+1 718 301 7462",
    "sg:postcode":"10473",
    "sg:province":"NY",
    "sg:tags":[
        "lock",
        "locksmith"
    ],
    "wof:name":"Emergency 7 Day Locksmith",
    "wof:placetype":"venue"
},
  "geometry": {"coordinates":[-73.868173,40.823418],"type":"Point"}
}