{
  "type": "Feature",
  "properties": {
    "addr:full":"309 E 105th St New York NY 10029",
    "addr:housenumber":"309",
    "addr:postcode":"10029",
    "addr:street":"E 105Th St",
    "iso:country":"US",
    "sg:address":"309 E 105th St",
    "sg:city":"New York",
    "sg:classifiers":[
        {
            "category":"Freight",
            "type":"Transportation"
        }
    ],
    "sg:phone":"+1 212 828 1081",
    "sg:postcode":"10029",
    "sg:province":"NY",
    "sg:tags":[
        "mover"
    ],
    "wof:name":"All American Movers",
    "wof:placetype":"venue"
},
  "geometry": {"coordinates":[-73.940669,40.789095],"type":"Point"}
}