{
  "type": "Feature",
  "properties": {
    "addr:full":"9 Elizabeth St New York NY 10013",
    "addr:housenumber":"9",
    "addr:postcode":"10013",
    "addr:street":"Elizabeth St",
    "iso:country":"US",
    "sg:address":"9 Elizabeth St",
    "sg:city":"New York",
    "sg:classifiers":[
        {
            "category":"Shopping",
            "subcategory":"Books",
            "type":"Retail Goods"
        }
    ],
    "sg:phone":"+1 212 625 8499",
    "sg:postcode":"10013",
    "sg:province":"NY",
    "sg:tags":[
        "bookstore"
    ],
    "sg:website":"www.xinhua.bookuu.com",
    "wof:name":"Xinhua Bookstore of Manhattan",
    "wof:placetype":"venue"
},
  "geometry": {"coordinates":[-73.997698,40.715846],"type":"Point"}
}