{
  "type": "Feature",
  "properties": {
    "addr:full":"449 Rte 25A Mt Sinai NY 11766",
    "addr:housenumber":"449",
    "addr:postcode":"11766",
    "addr:street":"Rte 25A",
    "iso:country":"US",
    "sg:address":"449 Rte 25A",
    "sg:city":"Mt Sinai",
    "sg:classifiers":[
        {
            "category":"Retail",
            "subcategory":"Repair Shop",
            "type":"Services"
        }
    ],
    "sg:phone":"+1 631 576 0371",
    "sg:postcode":"11766",
    "sg:province":"NY",
    "sg:tags":[
        "lock",
        "locksmith"
    ],
    "wof:name":"24 Hour Emergency Locksmith",
    "wof:placetype":"venue"
},
  "geometry": {"coordinates":[-73.01894299999999,40.935612],"type":"Point"}
}