{
  "type": "Feature",
  "properties": {
    "iso:country":"US",
    "sg:address":"150 Broadway",
    "sg:city":"New York",
    "sg:classifiers":[
        {
            "category":"Banks & Credit Unions",
            "subcategory":"Financial Services",
            "type":"Services"
        }
    ],
    "sg:phone":"+1 212 608 5100",
    "sg:postcode":"10038",
    "sg:province":"NY",
    "sg:tags":[
        "trust",
        "investment",
        "real estate"
    ],
    "wof:name":"J E M B Realty Corp",
    "wof:placetype":"venue"
},
  "geometry": {"coordinates":[-74.00998800000001,40.709806],"type":"Point"}
}