{
  "type": "Feature",
  "properties": {
    "addr:full":"14 N Chestnut St New Paltz NY 12561",
    "addr:housenumber":"14",
    "addr:postcode":"12561",
    "addr:street":"N Chestnut St",
    "iso:country":"US",
    "sg:address":"14 N Chestnut St",
    "sg:city":"New Paltz",
    "sg:classifiers":[
        {
            "category":"Retail",
            "subcategory":"Veterinary Services",
            "type":"Services"
        }
    ],
    "sg:phone":"+1 845 255 1890",
    "sg:postcode":"12561",
    "sg:province":"NY",
    "sg:tags":[
        "veterinarian"
    ],
    "wof:name":"All Creatures Veterinary Hosp",
    "wof:placetype":"venue"
},
  "geometry": {"coordinates":[-74.086885,41.747523],"type":"Point"}
}