{
  "type": "Feature",
  "properties": {
    "iso:country":"US",
    "sg:address":"1612 Grand Central Ave",
    "sg:city":"Elmira",
    "sg:classifiers":[
        {
            "category":"Retail",
            "subcategory":"Auto Rental",
            "type":"Services"
        }
    ],
    "sg:phone":"+1 607 734 6187",
    "sg:postcode":"14903",
    "sg:province":"NY",
    "sg:tags":[
        "truck",
        "leasing"
    ],
    "wof:name":"Penske",
    "wof:placetype":"venue"
},
  "geometry": {"coordinates":[-76.81589700000001,42.12103],"type":"Point"}
}