{
  "type": "Feature",
  "properties": {
    "iso:country":"US",
    "sg:address":"275 E Merrick Rd",
    "sg:city":"Valley Stream",
    "sg:classifiers":[
        {
            "category":"Autos & Motor Vehicles",
            "subcategory":"Fuel & Gas Station",
            "type":"Retail Goods"
        }
    ],
    "sg:phone":"+1 516 872 3794",
    "sg:postcode":"11580",
    "sg:province":"NY",
    "wof:name":"S & H Patroleum Inc",
    "wof:placetype":"venue"
},
  "geometry": {"coordinates":[-73.68888200000001,40.662302],"type":"Point"}
}