{
  "type": "Feature",
  "properties": {
    "addr:full":"225 E 125th St New York NY 10035",
    "addr:housenumber":"225",
    "addr:postcode":"10035",
    "addr:street":"E 125Th St",
    "iso:country":"US",
    "sg:address":"225 E 125th St",
    "sg:city":"New York",
    "sg:classifiers":[
        {
            "category":"Shopping",
            "subcategory":"Catalog Store",
            "type":"Retail Goods"
        }
    ],
    "sg:phone":"+1   ",
    "sg:postcode":"10035",
    "sg:province":"NY",
    "sg:tags":[
        "house",
        "consulting",
        "business",
        "mail"
    ],
    "wof:name":"Inner Circle Computer Inc",
    "wof:placetype":"venue"
},
  "geometry": {"coordinates":[-73.93395099999999,40.803051],"type":"Point"}
}