{
  "type": "Feature",
  "properties": {
    "iso:country":"US",
    "sg:address":"8639 Huntington Beach",
    "sg:city":"Barker",
    "sg:classifiers":[
        {
            "category":"Organizations",
            "subcategory":"Religious Organization",
            "type":"Services"
        }
    ],
    "sg:phone":"+1 716 795 3791",
    "sg:postcode":"14012",
    "sg:province":"NY",
    "sg:tags":[
        "clergy"
    ],
    "wof:name":"Olav Danielson",
    "wof:placetype":"venue"
},
  "geometry": {"coordinates":[-78.557321,43.367747],"type":"Point"}
}