{
  "type": "Feature",
  "properties": {
    "addr:full":"629 Lorraine St Mamaroneck NY 10543",
    "addr:housenumber":"629",
    "addr:postcode":"10543",
    "addr:street":"Lorraine St",
    "iso:country":"US",
    "sg:address":"629 Lorraine St",
    "sg:city":"Mamaroneck",
    "sg:classifiers":[
        {
            "category":"Manufacturing",
            "subcategory":"Pet Food",
            "type":"Manufacturing & Wholesale Goods"
        }
    ],
    "sg:phone":"+1   ",
    "sg:postcode":"10543",
    "sg:province":"NY",
    "sg:tags":[
        "mfg"
    ],
    "wof:name":"Aim Pet Foods Inc",
    "wof:placetype":"venue"
},
  "geometry": {"coordinates":[-73.73105200000001,40.960932],"type":"Point"}
}