{
  "type": "Feature",
  "properties": {
    "iso:country":"US",
    "sg:address":"1 Kattelville Rd",
    "sg:city":"Binghamton",
    "sg:classifiers":[
        {
            "category":"Professional",
            "subcategory":"Accounting & Tax Preparation",
            "type":"Services"
        }
    ],
    "sg:phone":"+1 607 648 7716",
    "sg:postcode":"13901",
    "sg:province":"NY",
    "wof:name":"ADP",
    "wof:placetype":"venue"
},
  "geometry": {"coordinates":[-75.873226,42.172554],"type":"Point"}
}