{
  "type": "Feature",
  "properties": {
    "addr:full":"14369 Ridge Rd W Albion NY 14411",
    "addr:housenumber":"14369",
    "addr:postcode":"14411",
    "addr:street":"Ridge Rd W",
    "iso:country":"US",
    "sg:address":"14369 Ridge Rd W",
    "sg:city":"Albion",
    "sg:phone":"+1 585 589 9151",
    "sg:postcode":"14411",
    "sg:province":"NY",
    "wof:name":"Village Inn",
    "wof:placetype":"venue"
},
  "geometry": {"coordinates":[-78.191833,43.2868],"type":"Point"}
}