{
  "type": "Feature",
  "properties": {
    "iso:country":"US",
    "sg:address":"145 S Bayview Ave",
    "sg:city":"Amityville",
    "sg:classifiers":[
        {
            "category":"Professional",
            "subcategory":"Management & Consulting",
            "type":"Services"
        }
    ],
    "sg:phone":"+1 631 691 3780",
    "sg:postcode":"11701",
    "sg:province":"NY",
    "sg:tags":[
        "consultant",
        "business"
    ],
    "wof:name":"Rispoli Management Consulting",
    "wof:placetype":"venue"
},
  "geometry": {"coordinates":[-73.408709,40.663753],"type":"Point"}
}