{
  "type": "Feature",
  "properties": {
    "addr:full":"1170 Central Ave Dunkirk NY 14048",
    "addr:housenumber":"1170",
    "addr:postcode":"14048",
    "addr:street":"Central Ave",
    "iso:country":"US",
    "sg:address":"1170 Central Ave",
    "sg:city":"Dunkirk",
    "sg:classifiers":[
        {
            "category":"Shopping",
            "type":"Retail Goods"
        }
    ],
    "sg:phone":"+1 716 366 0222",
    "sg:postcode":"14048",
    "sg:province":"NY",
    "sg:tags":[
        "hearing",
        "equipment",
        "supply",
        "impaired"
    ],
    "sg:website":"www.miracle-ear.com",
    "wof:name":"Miracle-Ear",
    "wof:placetype":"venue"
},
  "geometry": {"coordinates":[-79.33380099999999,42.457792],"type":"Point"}
}