{
  "type": "Feature",
  "properties": {
    "addr:full":"13008 Main Rd Akron NY 14001",
    "addr:housenumber":"13008",
    "addr:postcode":"14001",
    "addr:street":"Main Rd",
    "iso:country":"US",
    "sg:address":"13008 Main Rd",
    "sg:city":"Akron",
    "sg:classifiers":[
        {
            "category":"Retail",
            "subcategory":"Auto Repair",
            "type":"Services"
        }
    ],
    "sg:phone":"+1 716 542 2007",
    "sg:postcode":"14001",
    "sg:province":"NY",
    "sg:tags":[
        "repairing",
        "automobile"
    ],
    "wof:name":"Doug's Service Ctr",
    "wof:placetype":"venue"
},
  "geometry": {"coordinates":[-78.508931,42.99745],"type":"Point"}
}