{
  "type": "Feature",
  "properties": {
    "iso:country":"US",
    "sg:address":"1551 Bergen St",
    "sg:city":"Brooklyn",
    "sg:classifiers":[
        {
            "category":"Manufacturing",
            "subcategory":"Food",
            "type":"Manufacturing & Wholesale Goods"
        },
        {
            "category":"Banks & Credit Unions",
            "subcategory":"Financial Services",
            "type":"Services"
        }
    ],
    "sg:phone":"+1 347 374 3660",
    "sg:postcode":"11213",
    "sg:province":"NY",
    "sg:tags":[
        "product"
    ],
    "sg:website":"http://www.dpnsuperstore.com",
    "wof:name":"DPN SuperStore,Inc.",
    "wof:placetype":"venue"
},
  "geometry": {"coordinates":[-73.932205,40.675124],"type":"Point"}
}