{
  "type": "Feature",
  "properties": {
    "addr:full":"Unit 1229 1711 Cudaback Avenue Niagara Falls NY 14303",
    "addr:housenumber":"unit 1229",
    "addr:postcode":"1711;14303",
    "addr:street":"Cudaback Avenue",
    "iso:country":"US",
    "sg:address":"Unit 1229 1711 Cudaback Avenue",
    "sg:city":"Niagara Falls",
    "sg:classifiers":[
        {
            "category":"Professional",
            "subcategory":"Computer Services",
            "type":"Services"
        }
    ],
    "sg:phone":"+1 647 220 2515",
    "sg:postcode":"14303",
    "sg:province":"NY",
    "sg:tags":[
        "company-info",
        "industry-research-reports",
        "list-of-companies",
        "lead-generation",
        "b2b-marketing"
    ],
    "sg:website":"http://www.bizcompare.com",
    "wof:name":"BizCompare",
    "wof:placetype":"venue"
},
  "geometry": {"coordinates":[-79.041336,43.086079],"type":"Point"}
}