{
  "type": "Feature",
  "properties": {
    "addr:full":"140 Charles St New York NY 10014",
    "addr:housenumber":"140",
    "addr:postcode":"10014",
    "addr:street":"Charles St",
    "iso:country":"US",
    "sg:address":"140 Charles St",
    "sg:city":"New York",
    "sg:classifiers":[
        {
            "category":"Restaurant",
            "type":"Food & Drink"
        }
    ],
    "sg:phone":"+1 212 989 7707",
    "sg:postcode":"10014",
    "sg:province":"NY",
    "wof:name":"Deliziosa Pizza",
    "wof:placetype":"venue"
},
  "geometry": {"coordinates":[-74.00780399999999,40.734155],"type":"Point"}
}