{
  "type": "Feature",
  "properties": {
    "iso:country":"US",
    "sg:address":"630 9th Ave",
    "sg:city":"New York",
    "sg:classifiers":[
        {
            "category":"Restaurant",
            "type":"Food & Drink"
        }
    ],
    "sg:menulink":"http://www.allmenus.com/ny/new-york/252896-marseille/menu/",
    "sg:phone":"+1 212 333 2323",
    "sg:postcode":"10036",
    "sg:province":"NY",
    "sg:tags":[
        "greek",
        "moroccan",
        "french",
        "italian"
    ],
    "wof:name":"Marseille",
    "wof:placetype":"venue"
},
  "geometry": {"coordinates":[-73.991364,40.760164],"type":"Point"}
}