{
  "type": "Feature",
  "properties": {
    "iso:country":"US",
    "sg:address":"235 W 76 St",
    "sg:city":"New York",
    "sg:classifiers":[
        {
            "category":"Shopping",
            "subcategory":"Books",
            "type":"Retail Goods"
        }
    ],
    "sg:phone":"+1   ",
    "sg:postcode":"10023",
    "sg:province":"NY",
    "wof:name":"Lava Mount Talking Books",
    "wof:placetype":"venue"
},
  "geometry": {"coordinates":[-73.98239700000001,40.782372],"type":"Point"}
}