{
  "type": "Feature",
  "properties": {
    "iso:country":"US",
    "sg:address":"2 Great Jones St",
    "sg:city":"New York",
    "sg:classifiers":[
        {
            "category":"Professional",
            "type":"Services"
        }
    ],
    "sg:phone":"+1 212 253 2005",
    "sg:postcode":"10012",
    "sg:province":"NY",
    "sg:tags":[
        "establishment"
    ],
    "wof:name":"Natasha Ulyanov LLC",
    "wof:placetype":"venue"
},
  "geometry": {"coordinates":[-73.99419,40.727564],"type":"Point"}
}