{
  "type": "Feature",
  "properties": {
    "iso:country":"US",
    "sg:address":"201 Fine St",
    "sg:city":"Ogdensburg",
    "sg:classifiers":[
        {
            "category":"Manufacturing",
            "subcategory":"Tools & Machinery",
            "type":"Manufacturing & Wholesale Goods"
        }
    ],
    "sg:phone":"+1 315 393 0820",
    "sg:postcode":"13669",
    "sg:province":"NY",
    "sg:tags":[
        "machine",
        "shop"
    ],
    "wof:name":"Gille's Auto Truck & Marine",
    "wof:placetype":"venue"
},
  "geometry": {"coordinates":[-75.486324,44.685806],"type":"Point"}
}