{
  "type": "Feature",
  "properties": {
    "addr:full":"183 S Robinson Ave Newburgh NY 12550",
    "addr:housenumber":"183",
    "addr:postcode":"12550",
    "addr:street":"S Robinson Ave",
    "iso:country":"US",
    "sg:address":"183 S Robinson Ave",
    "sg:city":"Newburgh",
    "sg:classifiers":[
        {
            "category":"Ice Cream",
            "type":"Food & Drink"
        }
    ],
    "sg:phone":"+1 845 561 2312",
    "sg:postcode":"12550",
    "sg:province":"NY",
    "sg:tags":[
        "frozen",
        "yogurt"
    ],
    "wof:name":"Dairy Isle",
    "wof:placetype":"venue"
},
  "geometry": {"coordinates":[-74.022102,41.492901],"type":"Point"}
}