{
  "type": "Feature",
  "properties": {
    "addr:full":"76 E 167th St Bronx NY 10452",
    "addr:housenumber":"76",
    "addr:postcode":"10452",
    "addr:street":"E 167Th St",
    "iso:country":"US",
    "sg:address":"76 E 167th St",
    "sg:city":"Bronx",
    "sg:classifiers":[
        {
            "category":"Restaurant",
            "type":"Food & Drink"
        }
    ],
    "sg:phone":"+1 718 681 5513",
    "sg:postcode":"10452",
    "sg:province":"NY",
    "sg:tags":[
        "parlor",
        "ice",
        "cream"
    ],
    "wof:name":"Carvel Ice Cream & Bakery",
    "wof:placetype":"venue"
},
  "geometry": {"coordinates":[-73.91974999999999,40.835162],"type":"Point"}
}