{
  "type": "Feature",
  "properties": {
    "addr:full":"251 E 14th St Elmira NY 14903",
    "addr:housenumber":"251",
    "addr:postcode":"14903",
    "addr:street":"E 14Th St",
    "iso:country":"US",
    "sg:address":"251 E 14th St",
    "sg:city":"Elmira",
    "sg:classifiers":[
        {
            "category":"Education",
            "subcategory":"Dance Studio",
            "type":"Public Place"
        }
    ],
    "sg:phone":"+1 607 737 9014",
    "sg:postcode":"14903",
    "sg:province":"NY",
    "sg:tags":[
        "instruction",
        "dancing"
    ],
    "wof:name":"Leslie School Of Dance Arts",
    "wof:placetype":"venue"
},
  "geometry": {"coordinates":[-76.82092900000001,42.129393],"type":"Point"}
}