{
  "type": "Feature",
  "properties": {
    "iso:country":"US",
    "sg:address":"35 N Franklin St",
    "sg:city":"Cattaraugus",
    "sg:classifiers":[
        {
            "category":"Organizations",
            "subcategory":"Religious Organization",
            "type":"Services"
        }
    ],
    "sg:phone":"+1 716 257 3448",
    "sg:postcode":"14719",
    "sg:province":"NY",
    "sg:tags":[
        "clergy"
    ],
    "wof:name":"Clifford Waugh Rev",
    "wof:placetype":"venue"
},
  "geometry": {"coordinates":[-78.861766,42.334973],"type":"Point"}
}