{
  "type": "Feature",
  "properties": {
    "iso:country":"US",
    "sg:address":"405 Vliet Blvd",
    "sg:city":"Cohoes",
    "sg:classifiers":[
        {
            "category":"Social Services",
            "type":"Services"
        }
    ],
    "sg:phone":"+1 518 237 4263",
    "sg:postcode":"12047",
    "sg:province":"NY",
    "sg:tags":[
        "counselor",
        "marriage",
        "family"
    ],
    "sg:website":"www.counselingcareandservices.org",
    "wof:name":"Counseling Care & Svc Inc",
    "wof:placetype":"venue"
},
  "geometry": {"coordinates":[-73.72679599999999,42.779232],"type":"Point"}
}