{
  "type": "Feature",
  "properties": {
    "addr:full":"2115 Avenue U Brooklyn NY 11229",
    "addr:housenumber":"2115",
    "addr:postcode":"11229",
    "addr:street":"Avenue U",
    "iso:country":"US",
    "sg:address":"2115 Avenue U",
    "sg:city":"Brooklyn",
    "sg:classifiers":[
        {
            "category":"Professional",
            "subcategory":"Lawyer & Legal Services",
            "type":"Services"
        }
    ],
    "sg:phone":"+1 718 891 1200",
    "sg:postcode":"11229",
    "sg:province":"NY",
    "sg:tags":[
        "divorce",
        "law",
        "family"
    ],
    "wof:name":"Groner & Alatsas Atty",
    "wof:placetype":"venue"
},
  "geometry": {"coordinates":[-73.949898,40.599701],"type":"Point"}
}