{
  "type": "Feature",
  "properties": {
    "addr:full":"322 Main St Huntington NY 11743",
    "addr:housenumber":"322",
    "addr:postcode":"11743",
    "addr:street":"Main St",
    "iso:country":"US",
    "sg:address":"322 Main St",
    "sg:city":"Huntington",
    "sg:classifiers":[
        {
            "category":"Manufacturing",
            "subcategory":"Printing",
            "type":"Manufacturing & Wholesale Goods"
        }
    ],
    "sg:phone":"+1   ",
    "sg:postcode":"11743",
    "sg:province":"NY",
    "sg:tags":[
        "newspaper",
        "publication"
    ],
    "wof:name":"Long Islndr Nrth/Sth Pblctns",
    "wof:placetype":"venue"
},
  "geometry": {"coordinates":[-73.42968,40.870746],"type":"Point"}
}