{
  "type": "Feature",
  "properties": {
    "addr:full":"6647 Kirkville Rd East Syracuse NY 13057",
    "addr:housenumber":"6647",
    "addr:postcode":"13057",
    "addr:street":"Kirkville Rd",
    "iso:country":"US",
    "sg:address":"6647 Kirkville Rd",
    "sg:city":"East Syracuse",
    "sg:classifiers":[
        {
            "category":"Retail",
            "subcategory":"Veterinary Services",
            "type":"Services"
        }
    ],
    "sg:phone":"+1 315 431 0113",
    "sg:postcode":"13057",
    "sg:province":"NY",
    "sg:tags":[
        "hospital",
        "animal"
    ],
    "wof:name":"Eastside Animal Hospital",
    "wof:placetype":"venue"
},
  "geometry": {"coordinates":[-76.06335,43.076641],"type":"Point"}
}