{
  "type": "Feature",
  "properties": {
    "addr:full":"737 Lydig Ave Bronx NY 10462",
    "addr:housenumber":"737",
    "addr:postcode":"10462",
    "addr:street":"Lydig Ave",
    "iso:country":"US",
    "sg:address":"737 Lydig Ave",
    "sg:city":"Bronx",
    "sg:classifiers":[
        {
            "category":"Shopping",
            "subcategory":"Optical Goods",
            "type":"Retail Goods"
        },
        {
            "category":"Manufacturing",
            "subcategory":"Tools & Machinery",
            "type":"Manufacturing & Wholesale Goods"
        }
    ],
    "sg:phone":"+1 718 829 2160",
    "sg:postcode":"10462",
    "sg:province":"NY",
    "sg:tags":[
        "mfg",
        "optician",
        "ophthalmic"
    ],
    "wof:name":"Lydig Optical Lab Inc",
    "wof:placetype":"venue"
},
  "geometry": {"coordinates":[-73.866158,40.854544],"type":"Point"}
}