{
  "type": "Feature",
  "properties": {
    "iso:country":"US",
    "sg:address":"1440 Veterans Hwy",
    "sg:city":"Central Islip",
    "sg:classifiers":[
        {
            "category":"Wholesale",
            "subcategory":"Hardware",
            "type":"Manufacturing & Wholesale Goods"
        }
    ],
    "sg:phone":"+1 631 582 9700",
    "sg:postcode":"11749",
    "sg:province":"NY",
    "sg:tags":[
        "control",
        "equipment",
        "air",
        "pollution"
    ],
    "wof:name":"Emtrol Corp",
    "wof:placetype":"venue"
},
  "geometry": {"coordinates":[-73.187977,40.811188],"type":"Point"}
}