{
  "type": "Feature",
  "properties": {
    "iso:country":"US",
    "sg:address":"2586 Coney Island Ave",
    "sg:city":"Brooklyn",
    "sg:classifiers":[
        {
            "category":"Retail",
            "subcategory":"Auto Repair",
            "type":"Services"
        }
    ],
    "sg:phone":"+1 718 998 9198",
    "sg:postcode":"11223",
    "sg:province":"NY",
    "sg:tags":[
        "wheel",
        "automotive",
        "alignment",
        "axle",
        "general"
    ],
    "wof:name":"Franklen Automotive Diagnostic",
    "wof:placetype":"venue"
},
  "geometry": {"coordinates":[-73.96078799999999,40.593014],"type":"Point"}
}