{
  "type": "Feature",
  "properties": {
    "addr:full":"8030 Roll Rd East Amherst NY 14051",
    "addr:housenumber":"8030",
    "addr:postcode":"14051",
    "addr:street":"Roll Rd",
    "iso:country":"US",
    "sg:address":"8030 Roll Rd",
    "sg:city":"East Amherst",
    "sg:classifiers":[
        {
            "category":"Retail",
            "subcategory":"Repair Shop",
            "type":"Services"
        }
    ],
    "sg:phone":"+1   ",
    "sg:postcode":"14051",
    "sg:province":"NY",
    "sg:tags":[
        "instrument",
        "musical"
    ],
    "wof:name":"J&E Instrument Svce",
    "wof:placetype":"venue"
},
  "geometry": {"coordinates":[-78.691515,43.000321],"type":"Point"}
}