{
  "type": "Feature",
  "properties": {
    "addr:full":"2158 Grand Ave North Baldwin NY 11510",
    "addr:housenumber":"2158",
    "addr:postcode":"11510",
    "addr:street":"Grand Ave North",
    "iso:country":"US",
    "sg:address":"2158 Grand Ave",
    "sg:city":"North Baldwin",
    "sg:phone":"+1 516 378 8151",
    "sg:postcode":"11510",
    "sg:province":"NY",
    "sg:tags":[
        "oil"
    ],
    "wof:name":"Baylor Fuel Oil Inc",
    "wof:placetype":"venue"
},
  "geometry": {"coordinates":[-73.608982,40.657181],"type":"Point"}
}