{
  "type": "Feature",
  "properties": {
    "iso:country":"US",
    "sg:address":"2012 Victory Blvd",
    "sg:city":"Staten Island",
    "sg:classifiers":[
        {
            "category":"Professional",
            "subcategory":"Lawyer & Legal Services",
            "type":"Services"
        }
    ],
    "sg:phone":"+1   ",
    "sg:postcode":"10314",
    "sg:province":"NY",
    "wof:name":"A Anderocci Walter E",
    "wof:placetype":"venue"
},
  "geometry": {"coordinates":[-74.131306,40.612519],"type":"Point"}
}