{
  "type": "Feature",
  "properties": {
    "addr:full":"66 Hackett Blvd Albany NY 12209",
    "addr:housenumber":"66",
    "addr:postcode":"12209",
    "addr:street":"Hackett Blvd",
    "iso:country":"US",
    "sg:address":"66 Hackett Blvd",
    "sg:city":"Albany",
    "sg:classifiers":[
        {
            "category":"Health Services",
            "subcategory":"Medical Lab",
            "type":"Services"
        }
    ],
    "sg:phone":"+1 518 262 6759",
    "sg:postcode":"12209",
    "sg:province":"NY",
    "sg:tags":[
        "laboratory"
    ],
    "wof:name":"Amc/Clinical Research Office",
    "wof:placetype":"venue"
},
  "geometry": {"coordinates":[-73.781576,42.644057],"type":"Point"}
}