{
  "type": "Feature",
  "properties": {
    "iso:country":"US",
    "sg:address":"3 Delaware Dr",
    "sg:city":"New Hyde Park",
    "sg:classifiers":[
        {
            "category":"Sports & Exercise",
            "subcategory":"Gym",
            "type":"Entertainment"
        }
    ],
    "sg:phone":"+1 516 352 1241",
    "sg:postcode":"11042",
    "sg:province":"NY",
    "sg:tags":[
        "trainer"
    ],
    "wof:name":"Neostem Inc",
    "wof:placetype":"venue"
},
  "geometry": {"coordinates":[-73.69395900000001,40.759592],"type":"Point"}
}