{
  "type": "Feature",
  "properties": {
    "addr:full":"1095 Prospect Ave Bronx NY 10459",
    "addr:housenumber":"1095",
    "addr:postcode":"10459",
    "addr:street":"Prospect Ave",
    "iso:country":"US",
    "sg:address":"1095 Prospect Ave",
    "sg:city":"Bronx",
    "sg:classifiers":[
        {
            "category":"Social Services",
            "subcategory":"Child Care",
            "type":"Services"
        }
    ],
    "sg:phone":"+1 718 617 4983",
    "sg:postcode":"10459",
    "sg:province":"NY",
    "wof:name":"Elaine Williams",
    "wof:placetype":"venue"
},
  "geometry": {"coordinates":[-73.898984,40.826188],"type":"Point"}
}