{
  "type": "Feature",
  "properties": {
    "iso:country":"US",
    "sg:address":"584 Park Pl",
    "sg:city":"Brooklyn",
    "sg:classifiers":[
        {
            "category":"Real Estate",
            "subcategory":"Real Estate Agent",
            "type":"Services"
        }
    ],
    "sg:phone":"+1 718 783 1290",
    "sg:postcode":"11238",
    "sg:province":"NY",
    "wof:name":"Keizer & Keizer",
    "wof:placetype":"venue"
},
  "geometry": {"coordinates":[-73.959114,40.674686],"type":"Point"}
}