{
  "type": "Feature",
  "properties": {
    "addr:full":"128 Ninham Rd Carmel NY 10512",
    "addr:housenumber":"128",
    "addr:postcode":"10512",
    "addr:street":"Ninham Rd",
    "iso:country":"US",
    "sg:address":"128 Ninham Rd",
    "sg:city":"Carmel",
    "sg:classifiers":[
        {
            "category":"Social Services",
            "subcategory":"Adult Care",
            "type":"Services"
        }
    ],
    "sg:phone":"+1 845 228 4576",
    "sg:postcode":"10512",
    "sg:province":"NY",
    "sg:tags":[
        "home",
        "group"
    ],
    "wof:name":"Putnam Associated Resource Ctr",
    "wof:placetype":"venue"
},
  "geometry": {"coordinates":[-73.75035200000001,41.468832],"type":"Point"}
}