{
  "type": "Feature",
  "properties": {
    "addr:full":"1431 Broadway New York NY 10018",
    "addr:housenumber":"1431",
    "addr:postcode":"10018",
    "addr:street":"Broadway",
    "iso:country":"US",
    "sg:address":"1431 Broadway",
    "sg:city":"New York",
    "sg:classifiers":[
        {
            "category":"Wholesale",
            "subcategory":"Apparel",
            "type":"Manufacturing & Wholesale Goods"
        }
    ],
    "sg:phone":"+1 646 472 1700",
    "sg:postcode":"10018",
    "sg:province":"NY",
    "sg:tags":[
        "import"
    ],
    "wof:name":"Whispering Smith Company  LLC",
    "wof:placetype":"venue"
},
  "geometry": {"coordinates":[-73.986639,40.755035],"type":"Point"}
}