{
  "type": "Feature",
  "properties": {
    "iso:country":"US",
    "sg:address":"210 Chestnut Rd",
    "sg:city":"Manhasset",
    "sg:classifiers":[
        {
            "category":"Building & Trades",
            "subcategory":"Construction",
            "type":"Services"
        }
    ],
    "sg:phone":"+1 516 365 1420",
    "sg:postcode":"11030",
    "sg:province":"NY",
    "sg:tags":[
        "contractor"
    ],
    "wof:name":"North Shore Structures Ltd",
    "wof:placetype":"venue"
},
  "geometry": {"coordinates":[-73.68740099999999,40.815601],"type":"Point"}
}