{
  "type": "Feature",
  "properties": {
    "addr:full":"79 Conklingtown Rd Chester NY 10918",
    "addr:housenumber":"79",
    "addr:postcode":"10918",
    "addr:street":"Conklingtown Rd",
    "iso:country":"US",
    "sg:address":"79 Conklingtown Rd",
    "sg:city":"Chester",
    "sg:classifiers":[
        {
            "category":"Building & Trades",
            "subcategory":"Plumbing",
            "type":"Services"
        }
    ],
    "sg:phone":"+1 845 469 9656",
    "sg:postcode":"10918",
    "sg:province":"NY",
    "sg:tags":[
        "contractor"
    ],
    "wof:name":"Chester Mechanical",
    "wof:placetype":"venue"
},
  "geometry": {"coordinates":[-74.298271,41.355326],"type":"Point"}
}