{
  "type": "Feature",
  "properties": {
    "addr:full":"8406 20th Ave Brooklyn NY 11214",
    "addr:housenumber":"8406",
    "addr:postcode":"11214",
    "addr:street":"20Th Ave",
    "iso:country":"US",
    "sg:address":"8406 20th Ave",
    "sg:city":"Brooklyn",
    "sg:classifiers":[
        {
            "category":"Food & Beverages",
            "subcategory":"Groceries & Convenience Stores",
            "type":"Retail Goods"
        }
    ],
    "sg:phone":"+1 718 266 6062",
    "sg:postcode":"11214",
    "sg:province":"NY",
    "sg:tags":[
        "grocer"
    ],
    "wof:name":"White Mountain Farm Grocery",
    "wof:placetype":"venue"
},
  "geometry": {"coordinates":[-73.99766099999999,40.605291],"type":"Point"}
}