{
  "type": "Feature",
  "properties": {
    "iso:country":"US",
    "sg:address":"5251 Comstock Rd",
    "sg:city":"Brewerton",
    "sg:classifiers":[
        {
            "category":"Building & Trades",
            "subcategory":"Construction",
            "type":"Services"
        }
    ],
    "sg:phone":"+1 315 676 7160",
    "sg:postcode":"13029",
    "sg:province":"NY",
    "sg:tags":[
        "roofing",
        "contractor"
    ],
    "wof:name":"Bob Fleming Roofing & Siding",
    "wof:placetype":"venue"
},
  "geometry": {"coordinates":[-76.15367500000001,43.240218],"type":"Point"}
}