{
  "type": "Feature",
  "properties": {
    "addr:full":"57 Joan Ave Centereach NY 11720",
    "addr:housenumber":"57",
    "addr:postcode":"11720",
    "addr:street":"Joan Ave",
    "iso:country":"US",
    "sg:address":"57 Joan Ave",
    "sg:city":"Centereach",
    "sg:classifiers":[
        {
            "category":"Wholesale",
            "subcategory":"Vending Machines",
            "type":"Manufacturing & Wholesale Goods"
        }
    ],
    "sg:phone":"+1 631 696 9224",
    "sg:postcode":"11720",
    "sg:province":"NY",
    "wof:name":"Advantage Vending Svc",
    "wof:placetype":"venue"
},
  "geometry": {"coordinates":[-73.060585,40.856208],"type":"Point"}
}