{
  "type": "Feature",
  "properties": {
    "addr:full":"130 Bay St Staten Island NY 10301",
    "addr:housenumber":"130",
    "addr:postcode":"10301",
    "addr:street":"Bay St",
    "iso:country":"US",
    "sg:address":"130 Bay St",
    "sg:city":"Staten Island",
    "sg:classifiers":[
        {
            "category":"Organizations",
            "subcategory":"Professional Association",
            "type":"Services"
        }
    ],
    "sg:phone":"+1 718 727 1900",
    "sg:postcode":"10301",
    "sg:province":"NY",
    "sg:tags":[
        "chambers",
        "commerce"
    ],
    "sg:website":"www.sichamber.com",
    "wof:name":"Chamber Of Commerce",
    "wof:placetype":"venue"
},
  "geometry": {"coordinates":[-74.075503,40.639654],"type":"Point"}
}