{
  "type": "Feature",
  "properties": {
    "addr:full":"10 Robinhood Rd Suffern NY 10901",
    "addr:housenumber":"10",
    "addr:postcode":"10901",
    "addr:street":"Robinhood Rd",
    "iso:country":"US",
    "sg:address":"10 Robinhood Rd",
    "sg:city":"Suffern",
    "sg:classifiers":[
        {
            "category":"Shopping",
            "type":"Retail Goods"
        }
    ],
    "sg:phone":"+1   ",
    "sg:postcode":"10901",
    "sg:province":"NY",
    "sg:tags":[
        "merchandise"
    ],
    "wof:name":"Marine Collectibles Ltd",
    "wof:placetype":"venue"
},
  "geometry": {"coordinates":[-74.122027,41.129044],"type":"Point"}
}