{
  "type": "Feature",
  "properties": {
    "iso:country":"US",
    "sg:address":"55A Division Avenue",
    "sg:city":"Brooklyn",
    "sg:classifiers":[
        {
            "category":"Food & Beverages",
            "subcategory":"Meat & Fish",
            "type":"Retail Goods"
        }
    ],
    "sg:phone":"+1 718 963 2902",
    "sg:postcode":"11211",
    "sg:province":"NY",
    "sg:tags":[
        "seafood",
        "market"
    ],
    "wof:name":"Cohn Fish Market",
    "wof:placetype":"venue"
},
  "geometry": {"coordinates":[-73.967029,40.707159],"type":"Point"}
}