{
  "type": "Feature",
  "properties": {
    "iso:country":"US",
    "sg:address":"900 Fulton St",
    "sg:city":"Brooklyn",
    "sg:classifiers":[
        {
            "category":"Health Services",
            "subcategory":"Clinic",
            "type":"Services"
        }
    ],
    "sg:phone":"+1 718 857 4360",
    "sg:postcode":"11238",
    "sg:province":"NY",
    "sg:tags":[
        "wellness",
        "program",
        "instruction",
        "fitness"
    ],
    "sg:website":"www.embora.com",
    "wof:name":"Embora Wellness & Movement Studio",
    "wof:placetype":"venue"
},
  "geometry": {"coordinates":[-73.96509500000001,40.683106],"type":"Point"}
}