{
  "type": "Feature",
  "properties": {
    "addr:full":"24825 Union Tpke Bellerose NY 11426",
    "addr:housenumber":"24825",
    "addr:postcode":"11426",
    "addr:street":"Union Tpke",
    "iso:country":"US",
    "sg:address":"24825 Union Tpke",
    "sg:city":"Bellerose",
    "sg:classifiers":[
        {
            "category":"Professional",
            "subcategory":"Business Services",
            "type":"Services"
        }
    ],
    "sg:phone":"+1 718 470 0290",
    "sg:postcode":"11426",
    "sg:province":"NY",
    "sg:tags":[
        "organizing",
        "services-household"
    ],
    "wof:name":"Hu Chin-Chee",
    "wof:placetype":"venue"
},
  "geometry": {"coordinates":[-73.718361,40.743576],"type":"Point"}
}