{
  "type": "Feature",
  "properties": {
    "iso:country":"US",
    "name:eng_x_preferred":[
        "Avenue U"
    ],
    "wof:name":"Avenue U",
    "wof:placetype":"venue"
},
  "geometry": {"coordinates":[-73.97335699999999,40.596063],"type":"Point"}
}