{
  "type": "Feature",
  "properties": {
    "addr:full":"23 Mall Walk Yonkers NY 10704",
    "addr:housenumber":"23",
    "addr:postcode":"10704",
    "addr:street":"Mall Walk",
    "iso:country":"US",
    "sg:address":"23 Mall Walk",
    "sg:city":"Yonkers",
    "sg:classifiers":[
        {
            "category":"Restaurant",
            "type":"Food & Drink"
        }
    ],
    "sg:phone":"+1 914 423 7550",
    "sg:postcode":"10704",
    "sg:province":"NY",
    "wof:name":"Pizza Mania",
    "wof:placetype":"venue"
},
  "geometry": {"coordinates":[-73.85538099999999,40.928219],"type":"Point"}
}