{
  "type": "Feature",
  "properties": {
    "iso:country":"US",
    "sg:address":"94 S Union St",
    "sg:city":"Spencerport",
    "sg:classifiers":[
        {
            "category":"Restaurant",
            "type":"Food & Drink"
        }
    ],
    "sg:phone":"+1   ",
    "sg:postcode":"14559",
    "sg:province":"NY",
    "sg:tags":[
        "eating"
    ],
    "wof:name":"Stueys Restaurant Inc",
    "wof:placetype":"venue"
},
  "geometry": {"coordinates":[-77.800477,43.192921],"type":"Point"}
}