{
  "type": "Feature",
  "properties": {
    "iso:country":"US",
    "sg:address":"5815 Catalpa Ave",
    "sg:city":"Ridgewood",
    "sg:classifiers":[
        {
            "category":"Education",
            "subcategory":"School",
            "type":"Public Place"
        }
    ],
    "sg:phone":"+1 718 381 5033",
    "sg:postcode":"11385",
    "sg:province":"NY",
    "sg:tags":[
        "high",
        "middle",
        "elementary"
    ],
    "wof:name":"St Matthias After School Program",
    "wof:placetype":"venue"
},
  "geometry": {"coordinates":[-73.90270200000001,40.701801],"type":"Point"}
}