{
  "type": "Feature",
  "properties": {
    "iso:country":"US",
    "sg:address":"8 Anderson St",
    "sg:city":"New Rochelle",
    "sg:classifiers":[
        {
            "category":"Shopping",
            "subcategory":"Jewelry",
            "type":"Retail Goods"
        }
    ],
    "sg:phone":"+1   ",
    "sg:postcode":"10801",
    "sg:province":"NY",
    "wof:name":"Vinnys Jewelry Inc",
    "wof:placetype":"venue"
},
  "geometry": {"coordinates":[-73.78139299999999,40.910695],"type":"Point"}
}