{
  "type": "Feature",
  "properties": {
    "addr:full":"347 Baltic Street Brooklyn NY 11201",
    "addr:housenumber":"347",
    "addr:postcode":"11201",
    "addr:street":"Baltic Street",
    "iso:country":"US",
    "sg:address":"347 Baltic Street",
    "sg:city":"Brooklyn",
    "sg:classifiers":[
        {
            "category":"Professional",
            "subcategory":"Engineering",
            "type":"Services"
        },
        {
            "category":"Education",
            "subcategory":"School",
            "type":"Public Place"
        }
    ],
    "sg:phone":"+1 718 522 0464",
    "sg:postcode":"11201",
    "sg:province":"NY",
    "sg:tags":[
        "chemical",
        "engineer"
    ],
    "wof:name":"Nuziale Nicholas F Ce",
    "wof:placetype":"venue"
},
  "geometry": {"coordinates":[-73.99037800000001,40.684398],"type":"Point"}
}