{
  "type": "Feature",
  "properties": {
    "iso:country":"US",
    "sg:address":"3385 Brighton Henrietta Town Line Rd",
    "sg:city":"Rochester",
    "sg:classifiers":[
        {
            "category":"Shopping",
            "subcategory":"Shoes",
            "type":"Retail Goods"
        }
    ],
    "sg:phone":"+1 585 473 5950",
    "sg:postcode":"14623",
    "sg:province":"NY",
    "sg:tags":[
        "shoes-orthopedic"
    ],
    "sg:website":"http://www.footperformance.com",
    "wof:name":"Foot Performance Center",
    "wof:placetype":"venue"
},
  "geometry": {"coordinates":[-77.585245,43.095754],"type":"Point"}
}