{
  "type": "Feature",
  "properties": {
    "iso:country":"US",
    "sg:address":"27 Manila Pl",
    "sg:city":"Staten Island",
    "sg:classifiers":[
        {
            "category":"Building & Trades",
            "subcategory":"Construction",
            "type":"Services"
        }
    ],
    "sg:phone":"+1 718 667 0513",
    "sg:postcode":"10306",
    "sg:province":"NY",
    "sg:tags":[
        "hanging",
        "contractor"
    ],
    "wof:name":"Willies Painting",
    "wof:placetype":"venue"
},
  "geometry": {"coordinates":[-74.107758,40.561946],"type":"Point"}
}