{
  "type": "Feature",
  "properties": {
    "iso:country":"US",
    "sg:address":"311 State Hwy 211",
    "sg:city":"Middletown",
    "sg:classifiers":[
        {
            "category":"Retail",
            "subcategory":"Repair Shop",
            "type":"Services"
        }
    ],
    "sg:phone":"+1 845 343 5514",
    "sg:postcode":"10940",
    "sg:province":"NY",
    "sg:tags":[
        "repairing",
        "lawn",
        "mower"
    ],
    "wof:name":"Lou's Repair Shop",
    "wof:placetype":"venue"
},
  "geometry": {"coordinates":[-74.441766,41.459968],"type":"Point"}
}