{
  "type": "Feature",
  "properties": {
    "iso:country":"US",
    "sg:address":"199 Parrish St",
    "sg:city":"Canandaigua",
    "sg:classifiers":[
        {
            "category":"Health Services",
            "subcategory":"Doctor",
            "type":"Services"
        }
    ],
    "sg:phone":"+1 585 393 9690",
    "sg:postcode":"14424",
    "sg:province":"NY",
    "sg:tags":[
        "physician",
        "surgeon"
    ],
    "wof:name":"Heart Associates-Finger Lakes",
    "wof:placetype":"venue"
},
  "geometry": {"coordinates":[-77.28674100000001,42.876061],"type":"Point"}
}