{
  "type": "Feature",
  "properties": {
    "iso:country":"US",
    "sg:address":"329 Palmer Ter",
    "sg:city":"Mount Vernon",
    "sg:classifiers":[
        {
            "category":"Building & Trades",
            "subcategory":"Construction",
            "type":"Services"
        }
    ],
    "sg:phone":"+1 914 381 4453",
    "sg:postcode":"10543",
    "sg:province":"NY",
    "sg:tags":[
        "house"
    ],
    "wof:name":"Fabrizi Home Repair",
    "wof:placetype":"venue"
},
  "geometry": {"coordinates":[-73.743514,40.946225],"type":"Point"}
}