{
  "type": "Feature",
  "properties": {
    "iso:country":"US",
    "sg:address":"1349 Broadway",
    "sg:city":"Watervliet",
    "sg:classifiers":[
        {
            "category":"Manufacturing",
            "subcategory":"Printing",
            "type":"Manufacturing & Wholesale Goods"
        }
    ],
    "sg:phone":"+1   ",
    "sg:postcode":"12189",
    "sg:province":"NY",
    "sg:tags":[
        "lithographic",
        "commercial"
    ],
    "wof:name":"Archdesign Printing",
    "wof:placetype":"venue"
},
  "geometry": {"coordinates":[-73.70064600000001,42.723656],"type":"Point"}
}