{
  "type": "Feature",
  "properties": {
    "iso:country":"US",
    "sg:address":"2338 Cornwall Dr",
    "sg:city":"Macedon",
    "sg:classifiers":[
        {
            "category":"Building & Trades",
            "subcategory":"Construction",
            "type":"Services"
        }
    ],
    "sg:phone":"+1 315 986 2171",
    "sg:postcode":"14502",
    "sg:province":"NY",
    "sg:tags":[
        "house"
    ],
    "wof:name":"Cummings Const",
    "wof:placetype":"venue"
},
  "geometry": {"coordinates":[-77.347931,43.090873],"type":"Point"}
}