{
  "type": "Feature",
  "properties": {
    "addr:full":"100 E Old Country Rd Ste 14 Mineola NY 11501",
    "addr:housenumber":"100",
    "addr:postcode":"11501",
    "addr:street":"E Old Country Rd Ste 14",
    "iso:country":"US",
    "sg:address":"100 E Old Country Rd Ste 14",
    "sg:city":"Mineola",
    "sg:classifiers":[
        {
            "category":"Professional",
            "subcategory":"Lawyer & Legal Services",
            "type":"Services"
        }
    ],
    "sg:phone":"+1 516 739 8801",
    "sg:postcode":"11501",
    "sg:province":"NY",
    "wof:name":"Edelman Herbert M Atty",
    "wof:placetype":"venue"
},
  "geometry": {"coordinates":[-73.63130200000001,40.740398],"type":"Point"}
}