{
  "type": "Feature",
  "properties": {
    "iso:country":"US",
    "sg:address":"162 W 42nd St",
    "sg:city":"New York",
    "sg:classifiers":[
        {
            "category":"Retail",
            "subcategory":"Auto Repair",
            "type":"Services"
        }
    ],
    "sg:phone":"+1 212 937 1285",
    "sg:postcode":"10036",
    "sg:province":"NY",
    "sg:tags":[
        "wrecker"
    ],
    "wof:name":"Adi Towing & Repair",
    "wof:placetype":"venue"
},
  "geometry": {"coordinates":[-73.98486,40.754861],"type":"Point"}
}