{
  "type": "Feature",
  "properties": {
    "iso:country":"US",
    "sg:address":"8652 E Main St",
    "sg:city":"Clymer",
    "sg:classifiers":[
        {
            "category":"Farming",
            "subcategory":"Farm",
            "type":"Manufacturing & Wholesale Goods"
        }
    ],
    "sg:phone":"+1 716 355 2219",
    "sg:postcode":"14724",
    "sg:province":"NY",
    "sg:tags":[
        "crop",
        "general"
    ],
    "wof:name":"Duane Dunnewold",
    "wof:placetype":"venue"
},
  "geometry": {"coordinates":[-79.623363,42.020898],"type":"Point"}
}