{
  "type": "Feature",
  "properties": {
    "addr:full":"11481 178th Pl Jamaica NY 11434",
    "addr:housenumber":"11481",
    "addr:postcode":"11434",
    "addr:street":"178Th Pl",
    "iso:country":"US",
    "sg:address":"11481 178th Pl",
    "sg:city":"Jamaica",
    "sg:classifiers":[
        {
            "category":"Sports & Exercise",
            "subcategory":"Tennis Court",
            "type":"Entertainment"
        }
    ],
    "sg:phone":"+1 718 658 6728",
    "sg:postcode":"11434",
    "sg:province":"NY",
    "wof:name":"Youth & Tennis Inc",
    "wof:placetype":"venue"
},
  "geometry": {"coordinates":[-73.77010300000001,40.6936],"type":"Point"}
}