{
  "type": "Feature",
  "properties": {
    "iso:country":"US",
    "sg:address":"208 E 31 St",
    "sg:city":"New York",
    "sg:classifiers":[
        {
            "category":"Building & Trades",
            "subcategory":"Construction",
            "type":"Services"
        }
    ],
    "sg:phone":"+1 212 696 1530",
    "sg:postcode":"10016",
    "sg:province":"NY",
    "sg:tags":[
        "general",
        "contractor"
    ],
    "wof:name":"Joseph Lestingi Builder Dev",
    "wof:placetype":"venue"
},
  "geometry": {"coordinates":[-73.977385,40.742868],"type":"Point"}
}