{
  "type": "Feature",
  "properties": {
    "addr:full":"2856 Webster Ave Bronx NY 10458",
    "addr:housenumber":"2856",
    "addr:postcode":"10458",
    "addr:street":"Webster Ave",
    "iso:country":"US",
    "sg:address":"2856 Webster Ave",
    "sg:city":"Bronx",
    "sg:classifiers":[
        {
            "category":"Retail",
            "subcategory":"Laundry & Dry Cleaning",
            "type":"Services"
        }
    ],
    "sg:phone":"+1 718 365 6620",
    "sg:postcode":"10458",
    "sg:province":"NY",
    "wof:name":"Clean City Webster Av",
    "wof:placetype":"venue"
},
  "geometry": {"coordinates":[-73.884985,40.866464],"type":"Point"}
}