{
  "type": "Feature",
  "properties": {
    "addr:full":"30 Vandam St New York NY 10013",
    "addr:housenumber":"30",
    "addr:postcode":"10013",
    "addr:street":"Vandam St",
    "iso:country":"US",
    "sg:address":"30 Vandam St",
    "sg:city":"New York",
    "sg:classifiers":[
        {
            "category":"Professional",
            "subcategory":"Art Services",
            "type":"Services"
        }
    ],
    "sg:phone":"+1   ",
    "sg:postcode":"10013",
    "sg:province":"NY",
    "sg:tags":[
        "promotion",
        "graphic",
        "design",
        "advertising",
        "market"
    ],
    "wof:name":"Cronin & Prusco",
    "wof:placetype":"venue"
},
  "geometry": {"coordinates":[-74.00458999999999,40.726224],"type":"Point"}
}