{
  "type": "Feature",
  "properties": {
    "addr:full":"900 W Fingerboard Rd Staten Island NY 10305",
    "addr:housenumber":"900",
    "addr:postcode":"10305",
    "addr:street":"W Fingerboard Rd",
    "iso:country":"US",
    "sg:address":"900 W Fingerboard Rd",
    "sg:city":"Staten Island",
    "sg:classifiers":[
        {
            "category":"Restaurant",
            "type":"Food & Drink"
        }
    ],
    "sg:phone":"+1   ",
    "sg:postcode":"10305",
    "sg:province":"NY",
    "sg:tags":[
        "bar",
        "caterer"
    ],
    "wof:name":"Pat Veltons Catering Service",
    "wof:placetype":"venue"
},
  "geometry": {"coordinates":[-74.08495000000001,40.601664],"type":"Point"}
}