{
  "type": "Feature",
  "properties": {
    "iso:country":"US",
    "sg:address":"173 Airport Rd",
    "sg:city":"Greene",
    "sg:classifiers":[
        {
            "category":"Airport",
            "type":"Transportation"
        }
    ],
    "sg:phone":"+1 607 656 9518",
    "sg:postcode":"13778",
    "sg:province":"NY",
    "sg:tags":[
        "aircraft",
        "maintenance"
    ],
    "wof:name":"C & F Aircraft Svc",
    "wof:placetype":"venue"
},
  "geometry": {"coordinates":[-75.79193600000001,42.305912],"type":"Point"}
}