{
  "type": "Feature",
  "properties": {
    "iso:country":"US",
    "sg:address":"5152 Burnside Dr",
    "sg:city":"Jamesville",
    "sg:classifiers":[
        {
            "category":"Professional",
            "subcategory":"Computer Services",
            "type":"Services"
        }
    ],
    "sg:phone":"+1 315 446 3646",
    "sg:postcode":"13078",
    "sg:province":"NY",
    "sg:tags":[
        "prepackaged",
        "software"
    ],
    "wof:name":"Advanced Cmpt Sftwr Solutions",
    "wof:placetype":"venue"
},
  "geometry": {"coordinates":[-76.095341,43.020347],"type":"Point"}
}