{
  "type": "Feature",
  "properties": {
    "iso:country":"US",
    "sg:address":"98 Parker School Rd",
    "sg:city":"Johnsonville",
    "sg:classifiers":[
        {
            "category":"Freight",
            "type":"Transportation"
        }
    ],
    "sg:phone":"+1   ",
    "sg:postcode":"12094",
    "sg:province":"NY",
    "sg:tags":[
        "general"
    ],
    "wof:name":"Pittstown Self Storage",
    "wof:placetype":"venue"
},
  "geometry": {"coordinates":[-73.48315599999999,42.824408],"type":"Point"}
}