{
  "type": "Feature",
  "properties": {
    "iso:country":"US",
    "sg:address":"51 Wincrest Dr",
    "sg:city":"Queensbury",
    "sg:classifiers":[
        {
            "category":"Building & Trades",
            "subcategory":"Construction",
            "type":"Services"
        }
    ],
    "sg:phone":"+1 518 792 4371",
    "sg:postcode":"12804",
    "sg:province":"NY",
    "sg:tags":[
        "development",
        "operation",
        "apartment",
        "land"
    ],
    "wof:name":"Woodbury Development Group",
    "wof:placetype":"venue"
},
  "geometry": {"coordinates":[-73.667267,43.345067],"type":"Point"}
}