{
  "type": "Feature",
  "properties": {
    "iso:country":"US",
    "sg:address":"1601 W 2nd St",
    "sg:city":"Brooklyn",
    "sg:classifiers":[
        {
            "category":"Building & Trades",
            "subcategory":"Electrical",
            "type":"Services"
        }
    ],
    "sg:phone":"+1 718 375 5499",
    "sg:postcode":"11223",
    "sg:province":"NY",
    "sg:tags":[
        "electrical",
        "contractor"
    ],
    "wof:name":"Code Security Alarm",
    "wof:placetype":"venue"
},
  "geometry": {"coordinates":[-73.975511,40.606351],"type":"Point"}
}