{
  "type": "Feature",
  "properties": {
    "addr:full":"3021 State Hwy 206 Bainbridge NY 13733",
    "addr:housenumber":"3021",
    "addr:postcode":"13733",
    "addr:street":"State Hwy 206",
    "iso:country":"US",
    "sg:address":"3021 State Hwy 206",
    "sg:city":"Bainbridge",
    "sg:classifiers":[
        {
            "category":"Food & Beverages",
            "subcategory":"Groceries & Convenience Stores",
            "type":"Retail Goods"
        }
    ],
    "sg:phone":"+1   ",
    "sg:postcode":"13733",
    "sg:province":"NY",
    "wof:name":"Dollar Smart",
    "wof:placetype":"venue"
},
  "geometry": {"coordinates":[-75.580935,42.316504],"type":"Point"}
}