{
  "type": "Feature",
  "properties": {
    "addr:full":"2 Hudson Dr Highland Falls NY 10928",
    "addr:housenumber":"2",
    "addr:postcode":"10928",
    "addr:street":"Hudson Dr",
    "iso:country":"US",
    "sg:address":"2 Hudson Dr",
    "sg:city":"Highland Falls",
    "sg:classifiers":[
        {
            "category":"Real Estate",
            "subcategory":"Real Estate Operator",
            "type":"Services"
        }
    ],
    "sg:phone":"+1 845 446 6641",
    "sg:postcode":"10928",
    "sg:province":"NY",
    "sg:tags":[
        "building",
        "nonresidential"
    ],
    "wof:name":"Chamber Street Realty Corp",
    "wof:placetype":"venue"
},
  "geometry": {"coordinates":[-73.96591600000001,41.359407],"type":"Point"}
}