{
  "type": "Feature",
  "properties": {
    "addr:full":"1468 State St Schenectady NY 12304",
    "addr:housenumber":"1468",
    "addr:postcode":"12304",
    "addr:street":"State St",
    "iso:country":"US",
    "sg:address":"1468 State St",
    "sg:city":"Schenectady",
    "sg:classifiers":[
        {
            "category":"Organizations",
            "subcategory":"Community Association",
            "type":"Services"
        }
    ],
    "sg:phone":"+1 518 374 0557",
    "sg:postcode":"12304",
    "sg:province":"NY",
    "sg:tags":[
        "fraternal"
    ],
    "wof:name":"Knights Of St John",
    "wof:placetype":"venue"
},
  "geometry": {"coordinates":[-73.91801100000001,42.792758],"type":"Point"}
}