{
  "type": "Feature",
  "properties": {
    "iso:country":"US",
    "sg:address":"24 Erie Cres",
    "sg:city":"Fairport",
    "sg:classifiers":[
        {
            "category":"Retail",
            "subcategory":"Laundry & Dry Cleaning",
            "type":"Services"
        }
    ],
    "sg:phone":"+1 585 232 6306",
    "sg:postcode":"14450",
    "sg:province":"NY",
    "sg:tags":[
        "drycleaning",
        "plant"
    ],
    "wof:name":"Drive In Dry Cleaners",
    "wof:placetype":"venue"
},
  "geometry": {"coordinates":[-77.45459700000001,43.091884],"type":"Point"}
}