{
  "type": "Feature",
  "properties": {
    "iso:country":"US",
    "sg:address":"33 Bill Horton Way",
    "sg:city":"Wappingers Falls",
    "sg:classifiers":[
        {
            "category":"Home & Garden",
            "subcategory":"Building Materials",
            "type":"Retail Goods"
        }
    ],
    "sg:phone":"+1 845 298 9560",
    "sg:postcode":"12590",
    "sg:province":"NY",
    "sg:tags":[
        "door"
    ],
    "sg:website":"www.dandddoors.com",
    "wof:name":"D & D Doors Inc",
    "wof:placetype":"venue"
},
  "geometry": {"coordinates":[-73.888527,41.620639],"type":"Point"}
}