{
  "type": "Feature",
  "properties": {
    "iso:country":"US",
    "sg:address":"4008 3rd Ave",
    "sg:city":"Brooklyn",
    "sg:classifiers":[
        {
            "category":"Food & Beverages",
            "subcategory":"Meat & Fish",
            "type":"Retail Goods"
        }
    ],
    "sg:phone":"+1 718 499 3998",
    "sg:postcode":"11232",
    "sg:province":"NY",
    "sg:tags":[
        "seafood"
    ],
    "wof:name":"Seafood International Corp",
    "wof:placetype":"venue"
},
  "geometry": {"coordinates":[-74.00904,40.652621],"type":"Point"}
}