{
  "type": "Feature",
  "properties": {
    "iso:country":"US",
    "sg:address":"656 Castle Hill Ave",
    "sg:city":"Bronx",
    "sg:classifiers":[
        {
            "category":"Food & Beverages",
            "subcategory":"Groceries & Convenience Stores",
            "type":"Retail Goods"
        }
    ],
    "sg:phone":"+1 718 824 3666",
    "sg:postcode":"10473",
    "sg:province":"NY",
    "sg:tags":[
        "grocer"
    ],
    "wof:name":"656 Castle Hill Corp",
    "wof:placetype":"venue"
},
  "geometry": {"coordinates":[-73.84806,40.819197],"type":"Point"}
}