{
  "type": "Feature",
  "properties": {
    "iso:country":"US",
    "sg:address":"250 E Hartsdale Ave",
    "sg:city":"Hartsdale",
    "sg:classifiers":[
        {
            "category":"Health Services",
            "subcategory":"Doctor",
            "type":"Services"
        }
    ],
    "sg:phone":"+1 914 725 5300",
    "sg:postcode":"10530",
    "sg:province":"NY",
    "sg:tags":[
        "physician",
        "surgeon"
    ],
    "wof:name":"Judit Gordon-Lendvay MD",
    "wof:placetype":"venue"
},
  "geometry": {"coordinates":[-73.796345,41.012698],"type":"Point"}
}