{
  "type": "Feature",
  "properties": {
    "iso:country":"US",
    "sg:address":"200 Christopher St",
    "sg:city":"Ronkonkoma",
    "sg:classifiers":[
        {
            "category":"Manufacturing",
            "subcategory":"Metals",
            "type":"Manufacturing & Wholesale Goods"
        }
    ],
    "sg:phone":"+1 631 467 1800",
    "sg:postcode":"11779",
    "sg:province":"NY",
    "sg:tags":[
        "manufacture",
        "automotive",
        "stampings",
        "stamping",
        "other"
    ],
    "wof:name":"P R B Metal Products Inc",
    "wof:placetype":"venue"
},
  "geometry": {"coordinates":[-73.137255,40.795635],"type":"Point"}
}