{
  "type": "Feature",
  "properties": {
    "addr:full":"508 Northville Tpke Riverhead NY 11901",
    "addr:housenumber":"508",
    "addr:postcode":"11901",
    "addr:street":"Northville Tpke",
    "iso:country":"US",
    "sg:address":"508 Northville Tpke",
    "sg:city":"Riverhead",
    "sg:classifiers":[
        {
            "category":"Building & Trades",
            "subcategory":"Locksmith",
            "type":"Services"
        }
    ],
    "sg:phone":"+1 631 740 3193",
    "sg:postcode":"11901",
    "sg:province":"NY",
    "sg:tags":[
        "key"
    ],
    "wof:name":"Anytime Lockout Service",
    "wof:placetype":"venue"
},
  "geometry": {"coordinates":[-72.66082400000001,40.9243],"type":"Point"}
}