{
  "type": "Feature",
  "properties": {
    "addr:full":"18 148th St Jamaica NY 11435",
    "addr:housenumber":"18",
    "addr:postcode":"11435",
    "addr:street":"148Th St",
    "iso:country":"US",
    "sg:address":"18 148th St",
    "sg:city":"Jamaica",
    "sg:classifiers":[
        {
            "category":"Retail",
            "subcategory":"Auto Repair",
            "type":"Services"
        }
    ],
    "sg:phone":"+1 718 291 7464",
    "sg:postcode":"11435",
    "sg:province":"NY",
    "sg:tags":[
        "towing"
    ],
    "wof:name":"Kerr Carr Towing",
    "wof:placetype":"venue"
},
  "geometry": {"coordinates":[-73.80968799999999,40.707377],"type":"Point"}
}