{
  "type": "Feature",
  "properties": {
    "iso:country":"US",
    "sg:address":"5770 Innsbruck Rd",
    "sg:city":"East Syracuse",
    "sg:classifiers":[
        {
            "category":"Retail",
            "subcategory":"Portrait Studio",
            "type":"Services"
        }
    ],
    "sg:phone":"+1 315 463 7836",
    "sg:postcode":"13057",
    "sg:province":"NY",
    "sg:tags":[
        "photographer"
    ],
    "wof:name":"I Do Wedding Photography",
    "wof:placetype":"venue"
},
  "geometry": {"coordinates":[-76.030987,43.050625],"type":"Point"}
}