{
  "type": "Feature",
  "properties": {
    "addr:full":"185 Kings Hwy Brooklyn NY 11223",
    "addr:housenumber":"185",
    "addr:postcode":"11223",
    "addr:street":"Kings Hwy",
    "iso:country":"US",
    "sg:address":"185 Kings Hwy",
    "sg:city":"Brooklyn",
    "sg:classifiers":[
        {
            "category":"Professional",
            "type":"Services"
        }
    ],
    "sg:phone":"+1 718 621 1171",
    "sg:postcode":"11223",
    "sg:province":"NY",
    "sg:tags":[
        "establishment"
    ],
    "wof:name":"Dieboldlnc",
    "wof:placetype":"venue"
},
  "geometry": {"coordinates":[-73.98435600000001,40.605731],"type":"Point"}
}