{
  "type": "Feature",
  "properties": {
    "iso:country":"US",
    "sg:address":"20012 44th Ave",
    "sg:city":"Bayside",
    "sg:classifiers":[
        {
            "category":"Health Services",
            "subcategory":"Doctor",
            "type":"Services"
        }
    ],
    "sg:phone":"+1 718 460 4030",
    "sg:postcode":"11361",
    "sg:province":"NY",
    "sg:tags":[
        "medicine",
        "physician",
        "surgeon",
        "internal",
        "surgeons"
    ],
    "wof:name":"The Multi Specialty Exam Group",
    "wof:placetype":"venue"
},
  "geometry": {"coordinates":[-73.782466,40.757484],"type":"Point"}
}