{
  "type": "Feature",
  "properties": {
    "iso:country":"US",
    "sg:address":"12 Dellwood Rd",
    "sg:city":"Binghamton",
    "sg:classifiers":[
        {
            "category":"Health Services",
            "subcategory":"Doctor",
            "type":"Services"
        }
    ],
    "sg:phone":"+1 607 724 4075",
    "sg:postcode":"13903",
    "sg:province":"NY",
    "sg:tags":[
        "physician",
        "surgeon"
    ],
    "wof:name":"Richard M Bedosky MD",
    "wof:placetype":"venue"
},
  "geometry": {"coordinates":[-75.94604,42.085499],"type":"Point"}
}