{
  "type": "Feature",
  "properties": {
    "addr:full":"6 Maiden Ln New York NY 10038",
    "addr:housenumber":"6",
    "addr:postcode":"10038",
    "addr:street":"Maiden Ln",
    "iso:country":"US",
    "sg:address":"6 Maiden Ln",
    "sg:city":"New York",
    "sg:classifiers":[
        {
            "category":"Professional",
            "type":"Services"
        }
    ],
    "sg:phone":"+1 212 964 6087",
    "sg:postcode":"10038",
    "sg:province":"NY",
    "sg:tags":[
        "establishment"
    ],
    "wof:name":"Facilities Partners",
    "wof:placetype":"venue"
},
  "geometry": {"coordinates":[-74.00934700000001,40.709391],"type":"Point"}
}