{
  "type": "Feature",
  "properties": {
    "iso:country":"US",
    "sg:address":"269 Crow Hill Rd",
    "sg:city":"Delanson",
    "sg:classifiers":[
        {
            "category":"Professional",
            "type":"Services"
        }
    ],
    "sg:phone":"+1 518 895 8785",
    "sg:postcode":"12053",
    "sg:province":"NY",
    "sg:tags":[
        "establishment"
    ],
    "wof:name":"Schultz Doughlas",
    "wof:placetype":"venue"
},
  "geometry": {"coordinates":[-74.149057,42.739944],"type":"Point"}
}