{
  "type": "Feature",
  "properties": {
    "iso:country":"US",
    "sg:address":"2415 Jerusalem Ave Ste 101",
    "sg:city":"North Bellmore",
    "sg:classifiers":[
        {
            "category":"Shopping",
            "subcategory":"Pharmacy",
            "type":"Retail Goods"
        }
    ],
    "sg:phone":"+1 516 409 0400",
    "sg:postcode":"11710",
    "sg:province":"NY",
    "sg:tags":[
        "drugstore"
    ],
    "wof:name":"Toler Chemicals Inc",
    "wof:placetype":"venue"
},
  "geometry": {"coordinates":[-73.54160299999999,40.6912],"type":"Point"}
}