{
  "type": "Feature",
  "properties": {
    "addr:full":"1467 48th St Brooklyn NY 11219",
    "addr:housenumber":"1467",
    "addr:postcode":"11219",
    "addr:street":"48Th St",
    "iso:country":"US",
    "sg:address":"1467 48th St",
    "sg:city":"Brooklyn",
    "sg:classifiers":[
        {
            "category":"Social Services",
            "type":"Services"
        }
    ],
    "sg:phone":"+1   ",
    "sg:postcode":"11219",
    "sg:province":"NY",
    "sg:tags":[
        "organization",
        "religious"
    ],
    "wof:name":"Etz Chaim Tora Ctr Jerusalem",
    "wof:placetype":"venue"
},
  "geometry": {"coordinates":[-73.98821,40.633881],"type":"Point"}
}