{
  "type": "Feature",
  "properties": {
    "addr:full":"130 12th St Brooklyn NY 11215",
    "addr:housenumber":"130",
    "addr:postcode":"11215",
    "addr:street":"12Th St",
    "iso:country":"US",
    "sg:address":"130 12th St",
    "sg:city":"Brooklyn",
    "sg:classifiers":[
        {
            "category":"Wholesale",
            "subcategory":"Apparel",
            "type":"Manufacturing & Wholesale Goods"
        }
    ],
    "sg:phone":"+1 718 369 8965",
    "sg:postcode":"11215",
    "sg:province":"NY",
    "sg:tags":[
        "lingerie",
        "hosiery"
    ],
    "wof:name":"Z International Corp",
    "wof:placetype":"venue"
},
  "geometry": {"coordinates":[-73.99373,40.670326],"type":"Point"}
}