{
  "type": "Feature",
  "properties": {
    "iso:country":"US",
    "sg:address":"60 E 56 St",
    "sg:city":"New York",
    "sg:classifiers":[
        {
            "category":"Professional",
            "subcategory":"Business Services",
            "type":"Services"
        }
    ],
    "sg:phone":"+1 212 758 3420",
    "sg:postcode":"10022",
    "sg:province":"NY",
    "sg:tags":[
        "photography",
        "commercial"
    ],
    "wof:name":"Photo Researchers Inc",
    "wof:placetype":"venue"
},
  "geometry": {"coordinates":[-73.9717,40.761105],"type":"Point"}
}