{
  "type": "Feature",
  "properties": {
    "addr:full":"189 Montague St Ste 800 Brooklyn NY 11201",
    "addr:housenumber":"189",
    "addr:postcode":"11201",
    "addr:street":"Montague St Ste 800",
    "iso:country":"US",
    "sg:address":"189 Montague St Ste 800",
    "sg:city":"Brooklyn",
    "sg:classifiers":[
        {
            "category":"Professional",
            "subcategory":"Lawyer & Legal Services",
            "type":"Services"
        }
    ],
    "sg:phone":"+1 718 855 5840",
    "sg:postcode":"11201",
    "sg:province":"NY",
    "wof:name":"Schulman Henry H Atty",
    "wof:placetype":"venue"
},
  "geometry": {"coordinates":[-73.992401,40.694302],"type":"Point"}
}