{
  "type": "Feature",
  "properties": {
    "addr:full":"5916 19th Ave Brooklyn NY 11204",
    "addr:housenumber":"5916",
    "addr:postcode":"11204",
    "addr:street":"19Th Ave",
    "iso:country":"US",
    "sg:address":"5916 19th Ave",
    "sg:city":"Brooklyn",
    "sg:classifiers":[
        {
            "category":"Professional",
            "type":"Services"
        }
    ],
    "sg:phone":"+1   ",
    "sg:postcode":"11204",
    "sg:province":"NY",
    "wof:name":"David Lempel",
    "wof:placetype":"venue"
},
  "geometry": {"coordinates":[-73.98506999999999,40.620854],"type":"Point"}
}