{
  "type": "Feature",
  "properties": {
    "addr:full":"75 Esopus Ave Ulster Park NY 12487",
    "addr:housenumber":"75",
    "addr:postcode":"12487",
    "addr:street":"Esopus Ave",
    "iso:country":"US",
    "sg:address":"75 Esopus Ave",
    "sg:city":"Ulster Park",
    "sg:classifiers":[
        {
            "category":"Retail",
            "subcategory":"Auto Repair",
            "type":"Services"
        }
    ],
    "sg:phone":"+1   ",
    "sg:postcode":"12487",
    "sg:province":"NY",
    "sg:tags":[
        "general"
    ],
    "wof:name":"Auto Enhancing",
    "wof:placetype":"venue"
},
  "geometry": {"coordinates":[-73.987194,41.852869],"type":"Point"}
}