{
  "type": "Feature",
  "properties": {
    "iso:country":"US",
    "sg:address":"55 Broadway",
    "sg:city":"Tivoli",
    "sg:classifiers":[
        {
            "category":"Shopping",
            "subcategory":"Used Merchandise",
            "type":"Retail Goods"
        }
    ],
    "sg:phone":"+1 845 757 3634",
    "sg:postcode":"12583",
    "sg:province":"NY",
    "sg:tags":[
        "antique"
    ],
    "wof:name":"Madalin Antiques",
    "wof:placetype":"venue"
},
  "geometry": {"coordinates":[-73.906392,42.05824],"type":"Point"}
}