{
  "type": "Feature",
  "properties": {
    "iso:country":"US",
    "sg:address":"134 Brentwood Ln",
    "sg:city":"Fairport",
    "sg:classifiers":[
        {
            "category":"Building & Trades",
            "subcategory":"Electrical",
            "type":"Services"
        }
    ],
    "sg:phone":"+1 585 377 4890",
    "sg:postcode":"14450",
    "sg:province":"NY",
    "sg:tags":[
        "electrical",
        "electric",
        "contractor"
    ],
    "wof:name":"Hanss Richard Electrical Contr",
    "wof:placetype":"venue"
},
  "geometry": {"coordinates":[-77.46225099999999,43.08842],"type":"Point"}
}