{
  "type": "Feature",
  "properties": {
    "addr:full":"55 Great Jones Street New York NY 10012",
    "addr:housenumber":"55",
    "addr:postcode":"10012",
    "addr:street":"Great Jones Street",
    "iso:country":"US",
    "sg:address":"55 Great Jones Street",
    "sg:city":"New York",
    "sg:classifiers":[
        {
            "category":"Real Estate",
            "subcategory":"Architect",
            "type":"Services"
        }
    ],
    "sg:phone":"+1 212 253 1549",
    "sg:postcode":"10012",
    "sg:province":"NY",
    "wof:name":"Rossant James Architects",
    "wof:placetype":"venue"
},
  "geometry": {"coordinates":[-73.992712,40.726826],"type":"Point"}
}