{
  "type": "Feature",
  "properties": {
    "addr:full":"623 Madison St Brooklyn NY 11221",
    "addr:housenumber":"623",
    "addr:postcode":"11221",
    "addr:street":"Madison St",
    "iso:country":"US",
    "sg:address":"623 Madison St",
    "sg:city":"Brooklyn",
    "sg:classifiers":[
        {
            "category":"Organizations",
            "subcategory":"Religious Organization",
            "type":"Services"
        }
    ],
    "sg:phone":"+1 718 453 3302",
    "sg:postcode":"11221",
    "sg:province":"NY",
    "sg:tags":[
        "church"
    ],
    "wof:name":"Unity Temple",
    "wof:placetype":"venue"
},
  "geometry": {"coordinates":[-73.93005100000001,40.687151],"type":"Point"}
}