{
  "type": "Feature",
  "properties": {
    "iso:country":"US",
    "sg:address":"2451 Niagara Falls Blvd",
    "sg:city":"Amherst",
    "sg:classifiers":[
        {
            "category":"Personal",
            "subcategory":"Beauty Salon",
            "type":"Services"
        }
    ],
    "sg:phone":"+1 716 691 6262",
    "sg:postcode":"14228",
    "sg:province":"NY",
    "wof:name":"Look Of Beauty Coiffures",
    "wof:placetype":"venue"
},
  "geometry": {"coordinates":[-78.82210499999999,43.023742],"type":"Point"}
}