{
  "type": "Feature",
  "properties": {
    "iso:country":"US",
    "sg:address":"32504 Town Line Rd",
    "sg:city":"Philadelphia",
    "sg:classifiers":[
        {
            "category":"Building & Trades",
            "subcategory":"Construction",
            "type":"Services"
        }
    ],
    "sg:phone":"+1 315 486 1499",
    "sg:postcode":"13673",
    "sg:province":"NY",
    "sg:tags":[
        "general",
        "contractor"
    ],
    "wof:name":"T W Enterprises",
    "wof:placetype":"venue"
},
  "geometry": {"coordinates":[-75.72138099999999,44.107904],"type":"Point"}
}