{
  "type": "Feature",
  "properties": {
    "addr:full":"215 E 71 St New York NY 10021",
    "addr:housenumber":"215;71",
    "addr:postcode":"10021",
    "addr:street":"E;St",
    "iso:country":"US",
    "sg:address":"215 E 71 St",
    "sg:city":"New York",
    "sg:classifiers":[
        {
            "category":"Organizations",
            "subcategory":"Non-profit Organization",
            "type":"Services"
        }
    ],
    "sg:phone":"+1 212 744 3572",
    "sg:postcode":"10021",
    "sg:province":"NY",
    "wof:name":"National Society/Colonial Dame",
    "wof:placetype":"venue"
},
  "geometry": {"coordinates":[-73.960795,40.769044],"type":"Point"}
}