{
  "type": "Feature",
  "properties": {
    "addr:full":"170 E End Ave New York NY 10128",
    "addr:housenumber":"170",
    "addr:postcode":"10128",
    "addr:street":"E End Ave",
    "iso:country":"US",
    "sg:address":"170 E End Ave",
    "sg:city":"New York",
    "sg:classifiers":[
        {
            "category":"Health Services",
            "subcategory":"Doctor",
            "type":"Services"
        }
    ],
    "sg:phone":"+1 212 870 9430",
    "sg:postcode":"10128",
    "sg:province":"NY",
    "sg:tags":[
        "orthopedist"
    ],
    "wof:name":"Guomo Frances MD",
    "wof:placetype":"venue"
},
  "geometry": {"coordinates":[-73.944079,40.776122],"type":"Point"}
}