{
  "type": "Feature",
  "properties": {
    "iso:country":"US",
    "sg:address":"2 Hobnail Ct",
    "sg:city":"New Windsor",
    "sg:classifiers":[
        {
            "category":"Home & Garden",
            "subcategory":"Hardware",
            "type":"Retail Goods"
        }
    ],
    "sg:phone":"+1   ",
    "sg:postcode":"12553",
    "sg:province":"NY",
    "wof:name":"Fgl Tools Inc",
    "wof:placetype":"venue"
},
  "geometry": {"coordinates":[-74.03752,41.46505],"type":"Point"}
}