{
  "type": "Feature",
  "properties": {
    "addr:full":"127 Cuttermill Rd Great Neck NY 11021",
    "addr:housenumber":"127",
    "addr:postcode":"11021",
    "addr:street":"Cuttermill Rd",
    "iso:country":"US",
    "sg:address":"127 Cuttermill Rd",
    "sg:city":"Great Neck",
    "sg:classifiers":[
        {
            "category":"Professional",
            "subcategory":"Research",
            "type":"Services"
        }
    ],
    "sg:phone":"+1 516 773 7788",
    "sg:postcode":"11021",
    "sg:province":"NY",
    "sg:tags":[
        "development",
        "laboratory"
    ],
    "sg:website":"www.rtlab.com",
    "wof:name":"Research Testing Labs",
    "wof:placetype":"venue"
},
  "geometry": {"coordinates":[-73.73396,40.782843],"type":"Point"}
}