{
  "type": "Feature",
  "properties": {
    "addr:full":"178 Shookville Rd Red Hook NY 12571",
    "addr:housenumber":"178",
    "addr:postcode":"12571",
    "addr:street":"Shookville Rd",
    "iso:country":"US",
    "sg:address":"178 Shookville Rd",
    "sg:city":"Red Hook",
    "sg:classifiers":[
        {
            "category":"Farming",
            "subcategory":"Dairy Farm",
            "type":"Manufacturing & Wholesale Goods"
        }
    ],
    "sg:phone":"+1 845 758 2521",
    "sg:postcode":"12571",
    "sg:province":"NY",
    "wof:name":"George Zitz",
    "wof:placetype":"venue"
},
  "geometry": {"coordinates":[-73.80698700000001,41.988357],"type":"Point"}
}