{
  "type": "Feature",
  "properties": {
    "addr:full":"105 W 127th Street New York NY 10027",
    "addr:housenumber":"105",
    "addr:postcode":"10027",
    "addr:street":"W 127Th Street",
    "iso:country":"US",
    "sg:address":"105 W 127th Street",
    "sg:city":"New York",
    "sg:classifiers":[
        {
            "category":"Social Services",
            "subcategory":"Child Care",
            "type":"Services"
        }
    ],
    "sg:phone":"+1 212 662 1260",
    "sg:postcode":"10027",
    "sg:province":"NY",
    "sg:tags":[
        "day"
    ],
    "wof:name":"Patricias Childcare Service",
    "wof:placetype":"venue"
},
  "geometry": {"coordinates":[-73.944703,40.80916],"type":"Point"}
}