{
  "type": "Feature",
  "properties": {
    "addr:full":"1441 Broadway New York NY 10018",
    "addr:housenumber":"1441",
    "addr:postcode":"10018",
    "addr:street":"Broadway",
    "iso:country":"US",
    "sg:address":"1441 Broadway",
    "sg:city":"New York",
    "sg:classifiers":[
        {
            "category":"Professional",
            "type":"Services"
        }
    ],
    "sg:phone":"+1 212 391 7840",
    "sg:postcode":"10018",
    "sg:province":"NY",
    "sg:tags":[
        "establishment"
    ],
    "wof:name":"Gretta Cachat Inc",
    "wof:placetype":"venue"
},
  "geometry": {"coordinates":[-73.986807,40.754654],"type":"Point"}
}