{
  "type": "Feature",
  "properties": {
    "addr:full":"201 Springville Ave Buffalo NY 14226",
    "addr:housenumber":"201",
    "addr:postcode":"14226",
    "addr:street":"Springville Ave",
    "iso:country":"US",
    "sg:address":"201 Springville Ave",
    "sg:city":"Buffalo",
    "sg:classifiers":[
        {
            "category":"Building & Trades",
            "subcategory":"Construction",
            "type":"Services"
        }
    ],
    "sg:phone":"+1 716 834 9713",
    "sg:postcode":"14226",
    "sg:province":"NY",
    "sg:tags":[
        "house"
    ],
    "wof:name":"Joseph Gendreau and Sons",
    "wof:placetype":"venue"
},
  "geometry": {"coordinates":[-78.815918,42.96684],"type":"Point"}
}