{
  "type": "Feature",
  "properties": {
    "iso:country":"US",
    "sg:address":"801 Brooks St",
    "sg:city":"New Windsor",
    "sg:classifiers":[
        {
            "category":"Government",
            "subcategory":"Office",
            "type":"Public Place"
        }
    ],
    "sg:phone":"+1 845 567 0593",
    "sg:postcode":"12553",
    "sg:province":"NY",
    "sg:tags":[
        "federal",
        "security"
    ],
    "wof:name":"Us Defense Investigative Svc",
    "wof:placetype":"venue"
},
  "geometry": {"coordinates":[-74.10516200000001,41.49923],"type":"Point"}
}