{
  "type": "Feature",
  "properties": {
    "iso:country":"US",
    "sg:address":"17 Sumner St",
    "sg:city":"Batavia",
    "sg:classifiers":[
        {
            "category":"Recreation",
            "type":"Entertainment"
        }
    ],
    "sg:phone":"+1 585 343 9703",
    "sg:postcode":"14020",
    "sg:province":"NY",
    "sg:tags":[
        "hall",
        "auditorium"
    ],
    "wof:name":"Sacred Heart Social Ctr",
    "wof:placetype":"venue"
},
  "geometry": {"coordinates":[-78.176298,42.988479],"type":"Point"}
}