{
  "type": "Feature",
  "properties": {
    "addr:full":"234 Herricks Rd Mineola NY 11501",
    "addr:housenumber":"234",
    "addr:postcode":"11501",
    "addr:street":"Herricks Rd",
    "iso:country":"US",
    "sg:address":"234 Herricks Rd",
    "sg:city":"Mineola",
    "sg:classifiers":[
        {
            "category":"Manufacturing",
            "subcategory":"Apparel",
            "type":"Manufacturing & Wholesale Goods"
        }
    ],
    "sg:phone":"+1 516 742 1058",
    "sg:postcode":"11501",
    "sg:province":"NY",
    "sg:tags":[
        "awning",
        "canopy",
        "product",
        "mfg"
    ],
    "wof:name":"Canvas Products Company Inc",
    "wof:placetype":"venue"
},
  "geometry": {"coordinates":[-73.656008,40.742585],"type":"Point"}
}