{
  "type": "Feature",
  "properties": {
    "iso:country":"US",
    "sg:address":"107 Brookview Dr",
    "sg:city":"Schenectady",
    "sg:classifiers":[
        {
            "category":"Shopping",
            "subcategory":"Gifts & Souvenirs",
            "type":"Retail Goods"
        }
    ],
    "sg:phone":"+1 518 357 4538",
    "sg:postcode":"12303",
    "sg:province":"NY",
    "sg:tags":[
        "shop"
    ],
    "wof:name":"Faber Inc",
    "wof:placetype":"venue"
},
  "geometry": {"coordinates":[-73.913327,42.739399],"type":"Point"}
}