{
  "type": "Feature",
  "properties": {
    "addr:full":"5846 State Hwy 224 Alpine NY 14805",
    "addr:housenumber":"5846",
    "addr:postcode":"14805",
    "addr:street":"State Hwy 224",
    "iso:country":"US",
    "sg:address":"5846 State Hwy 224",
    "sg:city":"Alpine",
    "sg:classifiers":[
        {
            "category":"Building & Trades",
            "subcategory":"Plumbing",
            "type":"Services"
        }
    ],
    "sg:phone":"+1 607 594 3427",
    "sg:postcode":"14805",
    "sg:province":"NY",
    "sg:tags":[
        "plumbing",
        "contractor"
    ],
    "wof:name":"O'Bannion's Heating & Plumbing",
    "wof:placetype":"venue"
},
  "geometry": {"coordinates":[-76.725658,42.311085],"type":"Point"}
}