{
  "type": "Feature",
  "properties": {
    "iso:country":"US",
    "sg:address":"229 S Main St",
    "sg:city":"Canandaigua",
    "sg:classifiers":[
        {
            "category":"Home & Garden",
            "subcategory":"Carpets & Floor Coverings",
            "type":"Retail Goods"
        }
    ],
    "sg:phone":"+1 585 394 3170",
    "sg:postcode":"14424",
    "sg:province":"NY",
    "sg:tags":[
        "material",
        "linoleum"
    ],
    "wof:name":"Canandaigua Carpets Inc",
    "wof:placetype":"venue"
},
  "geometry": {"coordinates":[-77.27895700000001,42.884348],"type":"Point"}
}