{
  "type": "Feature",
  "properties": {
    "iso:country":"US",
    "sg:address":"1745 Union Blvd Ste 1",
    "sg:city":"Bay Shore",
    "sg:classifiers":[
        {
            "category":"Health Services",
            "subcategory":"Doctor",
            "type":"Services"
        }
    ],
    "sg:phone":"+1 631 647 4273",
    "sg:postcode":"11706",
    "sg:province":"NY",
    "sg:tags":[
        "practice",
        "family"
    ],
    "sg:website":"www.familymedicalny.com",
    "wof:name":"Family Medical Care",
    "wof:placetype":"venue"
},
  "geometry": {"coordinates":[-73.24967700000001,40.725257],"type":"Point"}
}