{
  "type": "Feature",
  "properties": {
    "iso:country":"US",
    "sg:address":"10 Liberty Pl",
    "sg:city":"New York",
    "sg:classifiers":[
        {
            "category":"Restaurant",
            "type":"Food & Drink"
        }
    ],
    "sg:phone":"+1 212 732 8264",
    "sg:postcode":"10038",
    "sg:province":"NY",
    "sg:tags":[
        "chinese"
    ],
    "wof:name":"Win Won Restaurant",
    "wof:placetype":"venue"
},
  "geometry": {"coordinates":[-74.009317,40.7091],"type":"Point"}
}