{
  "type": "Feature",
  "properties": {
    "iso:country":"US",
    "sg:address":"520 Farragut Pkwy",
    "sg:city":"Hastings On Hdsn",
    "sg:classifiers":[
        {
            "category":"Building & Trades",
            "subcategory":"Landscaping Services",
            "type":"Services"
        }
    ],
    "sg:phone":"+1 914 478 7320",
    "sg:postcode":"10706",
    "sg:province":"NY",
    "sg:tags":[
        "landscape",
        "contractor"
    ],
    "wof:name":"Aesthetic Landscape Care Inc",
    "wof:placetype":"venue"
},
  "geometry": {"coordinates":[-73.870689,40.983687],"type":"Point"}
}