{
  "type": "Feature",
  "properties": {
    "addr:full":"1095 State Hwy 110 Farmingdale NY 11735",
    "addr:housenumber":"1095",
    "addr:postcode":"11735",
    "addr:street":"State Hwy 110",
    "iso:country":"US",
    "sg:address":"1095 State Hwy 110",
    "sg:city":"Farmingdale",
    "sg:classifiers":[
        {
            "category":"Manufacturing",
            "subcategory":"Printing",
            "type":"Manufacturing & Wholesale Goods"
        }
    ],
    "sg:phone":"+1   ",
    "sg:postcode":"11735",
    "sg:province":"NY",
    "sg:tags":[
        "gift",
        "item",
        "mail",
        "glassware",
        "clothing",
        "order"
    ],
    "wof:name":"Intercollegiate Design",
    "wof:placetype":"venue"
},
  "geometry": {"coordinates":[-73.423399,40.733637],"type":"Point"}
}