{
  "type": "Feature",
  "properties": {
    "iso:country":"US",
    "sg:address":"1230 Ave of the Americas",
    "sg:city":"New York",
    "sg:classifiers":[
        {
            "category":"Professional",
            "type":"Services"
        }
    ],
    "sg:phone":"+1 212 618 6317",
    "sg:postcode":"10020",
    "sg:province":"NY",
    "sg:tags":[
        "establishment"
    ],
    "wof:name":"N8 Studios Inc",
    "wof:placetype":"venue"
},
  "geometry": {"coordinates":[-73.981036,40.758843],"type":"Point"}
}