{
  "type": "Feature",
  "properties": {
    "addr:full":"55 Johnson Rd Lawrence NY 11559",
    "addr:housenumber":"55",
    "addr:postcode":"11559",
    "addr:street":"Johnson Rd",
    "iso:country":"US",
    "sg:address":"55 Johnson Rd",
    "sg:city":"Lawrence",
    "sg:classifiers":[
        {
            "category":"Freight",
            "type":"Transportation"
        }
    ],
    "sg:phone":"+1 516 620 6000",
    "sg:postcode":"11559",
    "sg:province":"NY",
    "wof:name":"Circle International",
    "wof:placetype":"venue"
},
  "geometry": {"coordinates":[-73.743112,40.628966],"type":"Point"}
}