{
  "type": "Feature",
  "properties": {
    "iso:country":"US",
    "sg:address":"28 Dorset Rd",
    "sg:city":"Spring Valley",
    "sg:classifiers":[
        {
            "category":"Professional",
            "subcategory":"Management & Consulting",
            "type":"Services"
        }
    ],
    "sg:phone":"+1 845 371 1975",
    "sg:postcode":"10977",
    "sg:province":"NY",
    "sg:tags":[
        "business"
    ],
    "wof:name":"PC Ware Business Solutions",
    "wof:placetype":"venue"
},
  "geometry": {"coordinates":[-74.056611,41.124644],"type":"Point"}
}