{
  "type": "Feature",
  "properties": {
    "addr:full":"106 E Post Rd White Plains NY 10601",
    "addr:housenumber":"106",
    "addr:postcode":"10601",
    "addr:street":"E Post Rd",
    "iso:country":"US",
    "sg:address":"106 E Post Rd",
    "sg:city":"White Plains",
    "sg:classifiers":[
        {
            "category":"Professional",
            "subcategory":"Printing & Photocopies",
            "type":"Services"
        }
    ],
    "sg:phone":"+1   ",
    "sg:postcode":"10601",
    "sg:province":"NY",
    "sg:tags":[
        "photocopying",
        "commercial"
    ],
    "wof:name":"Independent Printing Co",
    "wof:placetype":"venue"
},
  "geometry": {"coordinates":[-73.76687699999999,41.028241],"type":"Point"}
}