{
  "type": "Feature",
  "properties": {
    "addr:full":"630 S Danby Rd Spencer NY 14883",
    "addr:housenumber":"630",
    "addr:postcode":"14883",
    "addr:street":"S Danby Rd",
    "iso:country":"US",
    "sg:address":"630 S Danby Rd",
    "sg:city":"Spencer",
    "sg:classifiers":[
        {
            "category":"Manufacturing",
            "subcategory":"Lumber",
            "type":"Manufacturing & Wholesale Goods"
        }
    ],
    "sg:phone":"+1 607 589 6620",
    "sg:postcode":"14883",
    "sg:province":"NY",
    "sg:tags":[
        "farm",
        "live",
        "tree",
        "christmas"
    ],
    "wof:name":"Southview",
    "wof:placetype":"venue"
},
  "geometry": {"coordinates":[-76.434656,42.287549],"type":"Point"}
}