{
  "type": "Feature",
  "properties": {
    "addr:full":"294 Smith St Brooklyn NY 11231",
    "addr:housenumber":"294",
    "addr:postcode":"11231",
    "addr:street":"Smith St",
    "iso:country":"US",
    "sg:address":"294 Smith St",
    "sg:city":"Brooklyn",
    "sg:classifiers":[
        {
            "category":"Education",
            "subcategory":"College",
            "type":"Public Place"
        }
    ],
    "sg:phone":"+1 718 624 3475",
    "sg:postcode":"11231",
    "sg:province":"NY",
    "sg:tags":[
        "academic",
        "school"
    ],
    "wof:name":"Carroll Gardens Neighborhood",
    "wof:placetype":"venue"
},
  "geometry": {"coordinates":[-73.99375999999999,40.682098],"type":"Point"}
}