{
  "type": "Feature",
  "properties": {
    "addr:full":"579 E 6 St New York NY 10009",
    "addr:housenumber":"579;6",
    "addr:postcode":"10009",
    "addr:street":"E",
    "iso:country":"US",
    "sg:address":"579 E 6 St",
    "sg:city":"New York",
    "sg:classifiers":[
        {
            "category":"Restaurant",
            "type":"Food & Drink"
        }
    ],
    "sg:phone":"+1 212 633 2220",
    "sg:postcode":"10009",
    "sg:province":"NY",
    "wof:name":"Golden Eagle Pub",
    "wof:placetype":"venue"
},
  "geometry": {"coordinates":[-73.983,40.725339],"type":"Point"}
}