{
  "type": "Feature",
  "properties": {
    "addr:full":"9506 89th St Ozone Park NY 11416",
    "addr:housenumber":"9506",
    "addr:postcode":"11416",
    "addr:street":"89Th St",
    "iso:country":"US",
    "sg:address":"9506 89th St",
    "sg:city":"Ozone Park",
    "sg:classifiers":[
        {
            "category":"Personal",
            "subcategory":"Barber",
            "type":"Services"
        }
    ],
    "sg:phone":"+1 718 641 2317",
    "sg:postcode":"11416",
    "sg:province":"NY",
    "wof:name":"Just Stop Beauty Salon Inc",
    "wof:placetype":"venue"
},
  "geometry": {"coordinates":[-73.852655,40.685564],"type":"Point"}
}