{
  "type": "Feature",
  "properties": {
    "addr:full":"7 Turner Dr Spencerport NY 14559",
    "addr:housenumber":"7",
    "addr:postcode":"14559",
    "addr:street":"Turner Dr",
    "iso:country":"US",
    "sg:address":"7 Turner Dr",
    "sg:city":"Spencerport",
    "sg:classifiers":[
        {
            "category":"Manufacturing",
            "subcategory":"Motor Vehicles & Parts",
            "type":"Manufacturing & Wholesale Goods"
        }
    ],
    "sg:phone":"+1   ",
    "sg:postcode":"14559",
    "sg:province":"NY",
    "sg:tags":[
        "go",
        "frame",
        "mfg"
    ],
    "wof:name":"Coyote Products Inc",
    "wof:placetype":"venue"
},
  "geometry": {"coordinates":[-77.765764,43.186108],"type":"Point"}
}