{
  "type": "Feature",
  "properties": {
    "addr:full":"11 Valley Rd Stony Brook NY 11790",
    "addr:housenumber":"11",
    "addr:postcode":"11790",
    "addr:street":"Valley Rd",
    "iso:country":"US",
    "sg:address":"11 Valley Rd",
    "sg:city":"Stony Brook",
    "sg:classifiers":[
        {
            "category":"Health Services",
            "subcategory":"Optometrist",
            "type":"Services"
        }
    ],
    "sg:phone":"+1 631 751 1078",
    "sg:postcode":"11790",
    "sg:province":"NY",
    "wof:name":"Creel Norman PHD",
    "wof:placetype":"venue"
},
  "geometry": {"coordinates":[-73.137901,40.927601],"type":"Point"}
}