{
  "type": "Feature",
  "properties": {
    "iso:country":"US",
    "sg:address":"2894 Long Beach Rd",
    "sg:city":"Oceanside",
    "sg:classifiers":[
        {
            "category":"Personal",
            "subcategory":"Beauty Salon",
            "type":"Services"
        }
    ],
    "sg:phone":"+1   ",
    "sg:postcode":"11572",
    "sg:province":"NY",
    "sg:tags":[
        "shop"
    ],
    "wof:name":"Blecker Sari Cpe",
    "wof:placetype":"venue"
},
  "geometry": {"coordinates":[-73.640209,40.641633],"type":"Point"}
}