{
  "type": "Feature",
  "properties": {
    "iso:country":"US",
    "sg:address":"12 Main St",
    "sg:city":"Hamburg",
    "sg:classifiers":[
        {
            "category":"Communications",
            "subcategory":"Television Station",
            "type":"Services"
        }
    ],
    "sg:phone":"+1   ",
    "sg:postcode":"14075",
    "sg:province":"NY",
    "wof:name":"Northeast Outdoors",
    "wof:placetype":"venue"
},
  "geometry": {"coordinates":[-78.834126,42.716122],"type":"Point"}
}