{
  "type": "Feature",
  "properties": {
    "iso:country":"US",
    "sg:address":"7760 Salt Springs Rd",
    "sg:city":"Fayetteville",
    "sg:classifiers":[
        {
            "category":"Personal",
            "subcategory":"Beauty Salon",
            "type":"Services"
        }
    ],
    "sg:phone":"+1 315 637 9615",
    "sg:postcode":"13066",
    "sg:province":"NY",
    "sg:tags":[
        "manicuring"
    ],
    "wof:name":"In His Hands Nail Boutique",
    "wof:placetype":"venue"
},
  "geometry": {"coordinates":[-75.986164,43.026011],"type":"Point"}
}