{
  "type": "Feature",
  "properties": {
    "iso:country":"US",
    "sg:address":"195 Oval Dr",
    "sg:city":"Islandia",
    "sg:classifiers":[
        {
            "category":"Freight",
            "type":"Transportation"
        }
    ],
    "sg:phone":"+1 631 234 6700",
    "sg:postcode":"11749",
    "sg:province":"NY",
    "sg:tags":[
        "mover"
    ],
    "sg:website":"www.certifiedtransport.com",
    "wof:name":"Certified Van Service Inc",
    "wof:placetype":"venue"
},
  "geometry": {"coordinates":[-73.19380200000001,40.805099],"type":"Point"}
}