{
  "type": "Feature",
  "properties": {
    "addr:full":"1202 Avenue Z Brooklyn NY 11235",
    "addr:housenumber":"1202",
    "addr:postcode":"11235",
    "addr:street":"Avenue Z",
    "iso:country":"US",
    "sg:address":"1202 Avenue Z",
    "sg:city":"Brooklyn",
    "sg:classifiers":[
        {
            "category":"Food & Beverages",
            "subcategory":"Groceries & Convenience Stores",
            "type":"Retail Goods"
        }
    ],
    "sg:phone":"+1 718 368 3583",
    "sg:postcode":"11235",
    "sg:province":"NY",
    "wof:name":"Z Supermarket",
    "wof:placetype":"venue"
},
  "geometry": {"coordinates":[-73.957802,40.587502],"type":"Point"}
}