{
  "type": "Feature",
  "properties": {
    "addr:full":"150 W 65th St New York NY 10023",
    "addr:housenumber":"150",
    "addr:postcode":"10023",
    "addr:street":"W 65Th St",
    "iso:country":"US",
    "sg:address":"150 W 65th St",
    "sg:city":"New York",
    "sg:classifiers":[
        {
            "category":"Arts & Performance",
            "subcategory":"Arts Center",
            "type":"Entertainment"
        }
    ],
    "sg:phone":"+1 212 239 6200",
    "sg:postcode":"10023",
    "sg:province":"NY",
    "sg:tags":[
        "performing"
    ],
    "sg:website":"www.lct.org/aboutBeaumont.htm",
    "wof:name":"Vivian Beaumont Theater",
    "wof:placetype":"venue"
},
  "geometry": {"coordinates":[-73.983757,40.773644],"type":"Point"}
}