{
  "type": "Feature",
  "properties": {
    "addr:full":"940 Waverly Pl Baldwin NY 11510",
    "addr:housenumber":"940",
    "addr:postcode":"11510",
    "addr:street":"Waverly Pl",
    "iso:country":"US",
    "sg:address":"940 Waverly Pl",
    "sg:city":"Baldwin",
    "sg:classifiers":[
        {
            "category":"Building & Trades",
            "subcategory":"Pest Control",
            "type":"Services"
        }
    ],
    "sg:phone":"+1 516 825 6008",
    "sg:postcode":"11510",
    "sg:province":"NY",
    "wof:name":"Able Wildlife Solutions LLC",
    "wof:placetype":"venue"
},
  "geometry": {"coordinates":[-73.607934,40.64305],"type":"Point"}
}