{
  "type": "Feature",
  "properties": {
    "iso:country":"US",
    "sg:address":"190 Bedford Ave",
    "sg:city":"Brooklyn",
    "sg:classifiers":[
        {
            "category":"Shopping",
            "subcategory":"Mobile Phones",
            "type":"Retail Goods"
        }
    ],
    "sg:phone":"+1 718 782 0151",
    "sg:postcode":"11211",
    "sg:province":"NY",
    "sg:website":"www.championwireless.com",
    "wof:name":"Champion Wireless",
    "wof:placetype":"venue"
},
  "geometry": {"coordinates":[-73.95802,40.717566],"type":"Point"}
}