{
  "type": "Feature",
  "properties": {
    "iso:country":"US",
    "sg:address":"16 Computer Dr E",
    "sg:city":"Albany",
    "sg:classifiers":[
        {
            "category":"Professional",
            "subcategory":"Detective & Security Services",
            "type":"Services"
        }
    ],
    "sg:phone":"+1 518 458 2609",
    "sg:postcode":"12205",
    "sg:province":"NY",
    "wof:name":"R 5 Security",
    "wof:placetype":"venue"
},
  "geometry": {"coordinates":[-73.804548,42.714988],"type":"Point"}
}