{
  "type": "Feature",
  "properties": {
    "iso:country":"US",
    "sg:address":"442 North St",
    "sg:city":"Rochester",
    "sg:classifiers":[
        {
            "category":"Personal",
            "subcategory":"Beauty Salon",
            "type":"Services"
        }
    ],
    "sg:phone":"+1   ",
    "sg:postcode":"14605",
    "sg:province":"NY",
    "sg:tags":[
        "shop"
    ],
    "wof:name":"Definitions Hair Salon",
    "wof:placetype":"venue"
},
  "geometry": {"coordinates":[-77.60040100000001,43.165654],"type":"Point"}
}