{
  "type": "Feature",
  "properties": {
    "addr:full":"28 Montgomery Ave Staten Island NY 10301",
    "addr:housenumber":"28",
    "addr:postcode":"10301",
    "addr:street":"Montgomery Ave",
    "iso:country":"US",
    "sg:address":"28 Montgomery Ave",
    "sg:city":"Staten Island",
    "sg:classifiers":[
        {
            "category":"Organizations",
            "subcategory":"Religious Organization",
            "type":"Services"
        }
    ],
    "sg:phone":"+1 718 420 9563",
    "sg:postcode":"10301",
    "sg:province":"NY",
    "wof:name":"Family Rstrtion Mnistries Intl",
    "wof:placetype":"venue"
},
  "geometry": {"coordinates":[-74.07810600000001,40.638804],"type":"Point"}
}