{
  "type": "Feature",
  "properties": {
    "addr:full":"983 Payne Ave North Tonawanda NY 14120",
    "addr:housenumber":"983",
    "addr:postcode":"14120",
    "addr:street":"Payne Ave",
    "iso:country":"US",
    "sg:address":"983 Payne Ave",
    "sg:city":"North Tonawanda",
    "sg:classifiers":[
        {
            "category":"Restaurant",
            "type":"Food & Drink"
        }
    ],
    "sg:phone":"+1   ",
    "sg:postcode":"14120",
    "sg:province":"NY",
    "sg:tags":[
        "eating"
    ],
    "wof:name":"China Wok Restaurant",
    "wof:placetype":"venue"
},
  "geometry": {"coordinates":[-78.877301,43.049498],"type":"Point"}
}