{
  "type": "Feature",
  "properties": {
    "addr:full":"2403 90th Pl Flushing NY 11369",
    "addr:housenumber":"2403",
    "addr:postcode":"11369",
    "addr:street":"90Th Pl",
    "iso:country":"US",
    "sg:address":"2403 90th Pl",
    "sg:city":"Flushing",
    "sg:classifiers":[
        {
            "category":"Professional",
            "type":"Services"
        }
    ],
    "sg:phone":"+1 718 803 0390",
    "sg:postcode":"11369",
    "sg:province":"NY",
    "sg:tags":[
        "establishment"
    ],
    "wof:name":"Tomer Development Corp",
    "wof:placetype":"venue"
},
  "geometry": {"coordinates":[-73.878908,40.764897],"type":"Point"}
}