{
  "type": "Feature",
  "properties": {
    "iso:country":"US",
    "sg:address":"20 W Post Rd",
    "sg:city":"White Plains",
    "sg:classifiers":[
        {
            "category":"Food & Beverages",
            "subcategory":"Groceries & Convenience Stores",
            "type":"Retail Goods"
        }
    ],
    "sg:phone":"+1   ",
    "sg:postcode":"10606",
    "sg:province":"NY",
    "wof:name":"Shop Smart",
    "wof:placetype":"venue"
},
  "geometry": {"coordinates":[-73.771694,41.025309],"type":"Point"}
}