{
  "type": "Feature",
  "properties": {
    "addr:full":"1752 Bath Ave Brooklyn NY 11214",
    "addr:housenumber":"1752",
    "addr:postcode":"11214",
    "addr:street":"Bath Ave",
    "iso:country":"US",
    "sg:address":"1752 Bath Ave",
    "sg:city":"Brooklyn",
    "sg:classifiers":[
        {
            "category":"Restaurant",
            "type":"Food & Drink"
        }
    ],
    "sg:phone":"+1   ",
    "sg:postcode":"11214",
    "sg:province":"NY",
    "sg:tags":[
        "drinking"
    ],
    "wof:name":"Goal Post",
    "wof:placetype":"venue"
},
  "geometry": {"coordinates":[-74.006241,40.603847],"type":"Point"}
}