{
  "type": "Feature",
  "properties": {
    "iso:country":"US",
    "sg:address":"37 Bedford Rd",
    "sg:city":"Pleasantville",
    "sg:classifiers":[
        {
            "category":"Health Services",
            "subcategory":"Chiropractor",
            "type":"Services"
        }
    ],
    "sg:phone":"+1 914 769 0900",
    "sg:postcode":"10570",
    "sg:province":"NY",
    "wof:name":"Smatt Family Chiropractic",
    "wof:placetype":"venue"
},
  "geometry": {"coordinates":[-73.777249,41.147367],"type":"Point"}
}