{
  "type": "Feature",
  "properties": {
    "iso:country":"US",
    "sg:address":"2417 Vestal Pkwy E",
    "sg:city":"Vestal",
    "sg:classifiers":[
        {
            "category":"Shopping",
            "subcategory":"Stationery & Office Supplies",
            "type":"Retail Goods"
        }
    ],
    "sg:phone":"+1 607 729 9999",
    "sg:postcode":"13850",
    "sg:province":"NY",
    "sg:tags":[
        "furniture"
    ],
    "sg:website":"www.officemax.com",
    "wof:name":"Office Max",
    "wof:placetype":"venue"
},
  "geometry": {"coordinates":[-76.01040399999999,42.094709],"type":"Point"}
}