{
  "type": "Feature",
  "properties": {
    "iso:country":"US",
    "sg:address":"2195 3rd St",
    "sg:city":"East Meadow",
    "sg:classifiers":[
        {
            "category":"Banks & Credit Unions",
            "subcategory":"Investment Brokerage",
            "type":"Services"
        }
    ],
    "sg:phone":"+1 516 794 1771",
    "sg:postcode":"11554",
    "sg:province":"NY",
    "sg:tags":[
        "banker"
    ],
    "wof:name":"Wachovia Retirement Svc",
    "wof:placetype":"venue"
},
  "geometry": {"coordinates":[-73.55494299999999,40.72327],"type":"Point"}
}