{
  "type": "Feature",
  "properties": {
    "addr:full":"5 Wellwood Ave Farmingdale NY 11735",
    "addr:housenumber":"5",
    "addr:postcode":"11735",
    "addr:street":"Wellwood Ave",
    "iso:country":"US",
    "sg:address":"5 Wellwood Ave",
    "sg:city":"Farmingdale",
    "sg:classifiers":[
        {
            "category":"Professional",
            "subcategory":"Advertising",
            "type":"Services"
        }
    ],
    "sg:phone":"+1 631 439 5000",
    "sg:postcode":"11735",
    "sg:province":"NY",
    "sg:tags":[
        "counselor"
    ],
    "wof:name":"Wilen Media",
    "wof:placetype":"venue"
},
  "geometry": {"coordinates":[-73.40271300000001,40.757241],"type":"Point"}
}