{
  "type": "Feature",
  "properties": {
    "iso:country":"US",
    "sg:address":"127 W 26th St",
    "sg:city":"New York",
    "sg:classifiers":[
        {
            "category":"Shopping",
            "subcategory":"Clothing, Apparel, & Fashions",
            "type":"Retail Goods"
        }
    ],
    "sg:phone":"+1   ",
    "sg:postcode":"10001",
    "sg:province":"NY",
    "sg:tags":[
        "miscellaneous",
        "store",
        "accessory"
    ],
    "wof:name":"Mimi Turner LLC",
    "wof:placetype":"venue"
},
  "geometry": {"coordinates":[-73.99365299999999,40.745751],"type":"Point"}
}