{
  "type": "Feature",
  "properties": {
    "iso:country":"US",
    "sg:address":"340 Abeel St",
    "sg:city":"Kingston",
    "sg:classifiers":[
        {
            "category":"Organizations",
            "subcategory":"Religious Organization",
            "type":"Services"
        }
    ],
    "sg:phone":"+1 845 339 7676",
    "sg:postcode":"12401",
    "sg:province":"NY",
    "sg:tags":[
        "clergy"
    ],
    "wof:name":"Arlene Dawber",
    "wof:placetype":"venue"
},
  "geometry": {"coordinates":[-73.994283,41.912903],"type":"Point"}
}