{
  "type": "Feature",
  "properties": {
    "addr:full":"221 Hempstead Tpke West Hempstead NY 11552",
    "addr:housenumber":"221",
    "addr:postcode":"11552",
    "addr:street":"Hempstead Tpke West",
    "iso:country":"US",
    "sg:address":"221 Hempstead Tpke",
    "sg:city":"West Hempstead",
    "sg:classifiers":[
        {
            "category":"Restaurant",
            "type":"Food & Drink"
        }
    ],
    "sg:phone":"+1 516 565 4607",
    "sg:postcode":"11552",
    "sg:province":"NY",
    "wof:name":"Taj Mahal Restrnt",
    "wof:placetype":"venue"
},
  "geometry": {"coordinates":[-73.646103,40.704899],"type":"Point"}
}