{
  "type": "Feature",
  "properties": {
    "iso:country":"US",
    "sg:address":"10 Madison Ave",
    "sg:city":"Endicott",
    "sg:classifiers":[
        {
            "category":"Professional",
            "subcategory":"Lawyer & Legal Services",
            "type":"Services"
        }
    ],
    "sg:phone":"+1 607 748 1533",
    "sg:postcode":"13760",
    "sg:province":"NY",
    "sg:tags":[
        "wrongful",
        "attorney",
        "death"
    ],
    "wof:name":"Cannavino Thomas F",
    "wof:placetype":"venue"
},
  "geometry": {"coordinates":[-76.049516,42.104368],"type":"Point"}
}