{
  "type": "Feature",
  "properties": {
    "iso:country":"US",
    "sg:address":"645 Broadway",
    "sg:city":"New York",
    "sg:classifiers":[
        {
            "category":"Real Estate",
            "subcategory":"Architect",
            "type":"Services"
        }
    ],
    "sg:phone":"+1 212 475 3531",
    "sg:postcode":"10012",
    "sg:province":"NY",
    "sg:tags":[
        "architectural"
    ],
    "wof:name":"Spatial Discipline",
    "wof:placetype":"venue"
},
  "geometry": {"coordinates":[-73.99538099999999,40.727175],"type":"Point"}
}