{
  "type": "Feature",
  "properties": {
    "addr:full":"475 Riverside Dr Ste 1935 New York NY 10115",
    "addr:housenumber":"475;1935",
    "addr:postcode":"10115",
    "addr:street":"Riverside Dr Ste",
    "iso:country":"US",
    "sg:address":"475 Riverside Dr Ste 1935",
    "sg:city":"New York",
    "sg:classifiers":[
        {
            "category":"Organizations",
            "subcategory":"Religious Organization",
            "type":"Services"
        }
    ],
    "sg:phone":"+1 212 870 2952",
    "sg:postcode":"10115",
    "sg:province":"NY",
    "wof:name":"AME Zion Church",
    "wof:placetype":"venue"
},
  "geometry": {"coordinates":[-73.964699,40.8106],"type":"Point"}
}