{
  "type": "Feature",
  "properties": {
    "addr:full":"3746 3rd Ave Bronx NY 10456",
    "addr:housenumber":"3746",
    "addr:postcode":"10456",
    "addr:street":"3Rd Ave",
    "iso:country":"US",
    "sg:address":"3746 3rd Ave",
    "sg:city":"Bronx",
    "sg:classifiers":[
        {
            "category":"Restaurant",
            "type":"Food & Drink"
        }
    ],
    "sg:phone":"+1 718 681 7272",
    "sg:postcode":"10456",
    "sg:province":"NY",
    "sg:tags":[
        "pizza"
    ],
    "wof:name":"Papa John's Pizza",
    "wof:placetype":"venue"
},
  "geometry": {"coordinates":[-73.90213900000001,40.836719],"type":"Point"}
}