{
  "type": "Feature",
  "properties": {
    "addr:full":"439 Kings Hwy Brooklyn NY 11223",
    "addr:housenumber":"439",
    "addr:postcode":"11223",
    "addr:street":"Kings Hwy",
    "iso:country":"US",
    "sg:address":"439 Kings Hwy",
    "sg:city":"Brooklyn",
    "sg:classifiers":[
        {
            "category":"Home & Garden",
            "subcategory":"Hardware",
            "type":"Retail Goods"
        }
    ],
    "sg:phone":"+1 718 375 2873",
    "sg:postcode":"11223",
    "sg:province":"NY",
    "sg:tags":[
        "store"
    ],
    "wof:name":"Frankson Hardware",
    "wof:placetype":"venue"
},
  "geometry": {"coordinates":[-73.97363799999999,40.604599],"type":"Point"}
}