{
  "type": "Feature",
  "properties": {
    "addr:full":"823 State Fair Blvd Syracuse NY 13209",
    "addr:housenumber":"823",
    "addr:postcode":"13209",
    "addr:street":"State Fair Blvd",
    "iso:country":"US",
    "sg:address":"823 State Fair Blvd",
    "sg:city":"Syracuse",
    "sg:classifiers":[
        {
            "category":"Recreation",
            "type":"Entertainment"
        }
    ],
    "sg:phone":"+1 315 487 8238",
    "sg:postcode":"13209",
    "sg:province":"NY",
    "sg:tags":[
        "parks"
    ],
    "wof:name":"Geddes Parks & Recreation",
    "wof:placetype":"venue"
},
  "geometry": {"coordinates":[-76.24039399999999,43.090439],"type":"Point"}
}