{
  "type": "Feature",
  "properties": {
    "addr:full":"200 W 12 St New York NY 10011",
    "addr:housenumber":"200",
    "addr:postcode":"10011",
    "addr:street":"W 12 St",
    "iso:country":"US",
    "sg:address":"200 W 12 St",
    "sg:city":"New York",
    "sg:classifiers":[
        {
            "category":"Retail",
            "subcategory":"Auto Repair",
            "type":"Services"
        }
    ],
    "sg:phone":"+1 646 237 9451",
    "sg:postcode":"10011",
    "sg:province":"NY",
    "sg:tags":[
        "wrecker"
    ],
    "wof:name":"Affordable Towing 24 Hour",
    "wof:placetype":"venue"
},
  "geometry": {"coordinates":[-74.001768,40.737674],"type":"Point"}
}