{
  "type": "Feature",
  "properties": {
    "addr:full":"21 Delano St Pulaski NY 13142",
    "addr:housenumber":"21",
    "addr:postcode":"13142",
    "addr:street":"Delano St",
    "iso:country":"US",
    "sg:address":"21 Delano St",
    "sg:city":"Pulaski",
    "sg:classifiers":[
        {
            "category":"Local Transit",
            "type":"Transportation"
        }
    ],
    "sg:phone":"+1 315 298 6516",
    "sg:postcode":"13142",
    "sg:province":"NY",
    "sg:tags":[
        "ambulance"
    ],
    "wof:name":"Northern Oswego Cnty Ambulance",
    "wof:placetype":"venue"
},
  "geometry": {"coordinates":[-76.117161,43.568859],"type":"Point"}
}