{
  "type": "Feature",
  "properties": {
    "iso:country":"US",
    "sg:address":"135 W 17th St",
    "sg:city":"New York",
    "sg:classifiers":[
        {
            "category":"Professional",
            "subcategory":"Lawyer & Legal Services",
            "type":"Services"
        }
    ],
    "sg:phone":"+1 212 350 9992",
    "sg:postcode":"10011",
    "sg:province":"NY",
    "wof:name":"Kislak Barbara",
    "wof:placetype":"venue"
},
  "geometry": {"coordinates":[-73.996399,40.7397],"type":"Point"}
}