{
  "type": "Feature",
  "properties": {
    "addr:full":"617 W 168th St New York NY 10032",
    "addr:housenumber":"617",
    "addr:postcode":"10032",
    "addr:street":"W 168Th St",
    "iso:country":"US",
    "sg:address":"617 W 168th St",
    "sg:city":"New York",
    "sg:classifiers":[
        {
            "category":"Health Services",
            "subcategory":"Hospital",
            "type":"Services"
        }
    ],
    "sg:phone":"+1 212 305 5439",
    "sg:postcode":"10032",
    "sg:province":"NY",
    "wof:name":"New York Presbyterian Hosp",
    "wof:placetype":"venue"
},
  "geometry": {"coordinates":[-73.941965,40.842063],"type":"Point"}
}