{
  "type": "Feature",
  "properties": {
    "iso:country":"US",
    "sg:address":"480 Co Rd 40",
    "sg:city":"Worcester",
    "sg:classifiers":[
        {
            "category":"Travel",
            "subcategory":"Hotels & Motels",
            "type":"Entertainment"
        }
    ],
    "sg:phone":"+1 607 397 8164",
    "sg:postcode":"12197",
    "sg:province":"NY",
    "sg:tags":[
        "breakfast",
        "accommodation",
        "bed"
    ],
    "wof:name":"Charlotte Valley Inn",
    "wof:placetype":"venue"
},
  "geometry": {"coordinates":[-74.74768299999999,42.517419],"type":"Point"}
}