{
  "type": "Feature",
  "properties": {
    "addr:full":"Broadway and W Houston Soho New York NY 10079",
    "addr:postcode":"10079",
    "iso:country":"US",
    "sg:address":"Broadway and W Houston Soho",
    "sg:city":"New York",
    "sg:classifiers":[
        {
            "category":"Restaurant",
            "type":"Food & Drink"
        },
        {
            "category":"Food Court",
            "type":"Food & Drink"
        }
    ],
    "sg:postcode":"10079",
    "sg:province":"NY",
    "sg:tags":[
        "middle",
        "stand",
        "eastern"
    ],
    "wof:name":"Halal Cart",
    "wof:placetype":"venue"
},
  "geometry": {"coordinates":[-73.996831,40.725342],"type":"Point"}
}