{
  "type": "Feature",
  "properties": {
    "iso:country":"US",
    "sg:address":"270 Skip Ln",
    "sg:city":"Bay Shore",
    "sg:classifiers":[
        {
            "category":"Personal",
            "type":"Services"
        }
    ],
    "sg:phone":"+1 800 355 1696",
    "sg:postcode":"11706",
    "sg:province":"NY",
    "sg:tags":[
        "mover"
    ],
    "sg:website":"upack.com",
    "wof:name":"ABF U-Pack Moving",
    "wof:placetype":"venue"
},
  "geometry": {"coordinates":[-73.286,40.762009],"type":"Point"}
}