{
  "type": "Feature",
  "properties": {
    "iso:country":"US",
    "sg:address":"39 Broadway",
    "sg:city":"Rocky Point",
    "sg:classifiers":[
        {
            "category":"Restaurant",
            "type":"Food & Drink"
        }
    ],
    "sg:phone":"+1 631 744 1117",
    "sg:postcode":"11778",
    "sg:province":"NY",
    "wof:name":"Del Fiore Ristorante",
    "wof:placetype":"venue"
},
  "geometry": {"coordinates":[-72.923672,40.948849],"type":"Point"}
}