{
  "type": "Feature",
  "properties": {
    "addr:full":"87 Burma Rd Kinderhook NY 12106",
    "addr:housenumber":"87",
    "addr:postcode":"12106",
    "addr:street":"Burma Rd",
    "iso:country":"US",
    "sg:address":"87 Burma Rd",
    "sg:city":"Kinderhook",
    "sg:classifiers":[
        {
            "category":"Building & Trades",
            "subcategory":"Construction",
            "type":"Services"
        }
    ],
    "sg:phone":"+1 518 758 8702",
    "sg:postcode":"12106",
    "sg:province":"NY",
    "sg:tags":[
        "tile",
        "dealer"
    ],
    "wof:name":"Sterling Tile & Stone",
    "wof:placetype":"venue"
},
  "geometry": {"coordinates":[-73.671842,42.357436],"type":"Point"}
}