{
  "type": "Feature",
  "properties": {
    "addr:full":"53 S Pearl St Pearl River NY 10965",
    "addr:housenumber":"53",
    "addr:postcode":"10965",
    "addr:street":"S Pearl St",
    "iso:country":"US",
    "sg:address":"53 S Pearl St",
    "sg:city":"Pearl River",
    "sg:classifiers":[
        {
            "category":"Shopping",
            "type":"Retail Goods"
        }
    ],
    "sg:phone":"+1 845 735 0555",
    "sg:postcode":"10965",
    "sg:province":"NY",
    "sg:tags":[
        "trophy",
        "medal",
        "merchandise",
        "award"
    ],
    "sg:website":"www.crowntrophy.com",
    "wof:name":"Crown Trophy",
    "wof:placetype":"venue"
},
  "geometry": {"coordinates":[-74.024551,41.056709],"type":"Point"}
}