{
  "type": "Feature",
  "properties": {
    "addr:full":"1216 Cortelyou Rd Brooklyn NY 11218",
    "addr:housenumber":"1216",
    "addr:postcode":"11218",
    "addr:street":"Cortelyou Rd",
    "iso:country":"US",
    "sg:address":"1216 Cortelyou Rd",
    "sg:city":"Brooklyn",
    "sg:classifiers":[
        {
            "category":"Retail",
            "subcategory":"Laundry & Dry Cleaning",
            "type":"Services"
        }
    ],
    "sg:phone":"+1 718 287 3810",
    "sg:postcode":"11218",
    "sg:province":"NY",
    "sg:tags":[
        "drycleaning",
        "plant"
    ],
    "wof:name":"Irwin Cleaners",
    "wof:placetype":"venue"
},
  "geometry": {"coordinates":[-73.966499,40.640202],"type":"Point"}
}