{
  "type": "Feature",
  "properties": {
    "addr:full":"2280 Ryder St Brooklyn NY 11234",
    "addr:housenumber":"2280",
    "addr:postcode":"11234",
    "addr:street":"Ryder St",
    "iso:country":"US",
    "sg:address":"2280 Ryder St",
    "sg:city":"Brooklyn",
    "sg:classifiers":[
        {
            "category":"Local Transit",
            "type":"Transportation"
        }
    ],
    "sg:phone":"+1 718 377 4141",
    "sg:postcode":"11234",
    "sg:province":"NY",
    "sg:tags":[
        "car",
        "passenger"
    ],
    "wof:name":"Fantasy Limousines",
    "wof:placetype":"venue"
},
  "geometry": {"coordinates":[-73.924903,40.607529],"type":"Point"}
}