{
  "type": "Feature",
  "properties": {
    "addr:full":"117 Henry St Brooklyn NY 11201",
    "addr:housenumber":"117",
    "addr:postcode":"11201",
    "addr:street":"Henry St",
    "iso:country":"US",
    "sg:address":"117 Henry St",
    "sg:city":"Brooklyn",
    "sg:classifiers":[
        {
            "category":"Retail",
            "subcategory":"Laundry & Dry Cleaning",
            "type":"Services"
        }
    ],
    "sg:phone":"+1 718 624 7812",
    "sg:postcode":"11201",
    "sg:province":"NY",
    "wof:name":"Heights Hand Laundry",
    "wof:placetype":"venue"
},
  "geometry": {"coordinates":[-73.993639,40.696052],"type":"Point"}
}