{
  "type": "Feature",
  "properties": {
    "addr:full":"380 5th Ave New Rochelle NY 10801",
    "addr:housenumber":"380",
    "addr:postcode":"10801",
    "addr:street":"5Th Ave",
    "iso:country":"US",
    "sg:address":"380 5th Ave",
    "sg:city":"New Rochelle",
    "sg:classifiers":[
        {
            "category":"Building & Trades",
            "subcategory":"Construction",
            "type":"Services"
        }
    ],
    "sg:phone":"+1 914 632 9573",
    "sg:postcode":"10801",
    "sg:province":"NY",
    "sg:tags":[
        "roofing",
        "contractor"
    ],
    "wof:name":"Marcelino Roofing",
    "wof:placetype":"venue"
},
  "geometry": {"coordinates":[-73.77606900000001,40.928357],"type":"Point"}
}