{
  "type": "Feature",
  "properties": {
    "addr:full":"197 Avenue of the Americ New York NY 10013",
    "addr:housenumber":"197",
    "addr:postcode":"10013",
    "addr:street":"Avenue Of The",
    "iso:country":"US",
    "sg:address":"197 Avenue of the Americ",
    "sg:city":"New York",
    "sg:classifiers":[
        {
            "category":"Retail",
            "subcategory":"Laundry & Dry Cleaning",
            "type":"Services"
        }
    ],
    "sg:phone":"+1 212 255 7065",
    "sg:postcode":"10013",
    "sg:province":"NY",
    "wof:name":"Charlton Cleaners & Tailors",
    "wof:placetype":"venue"
},
  "geometry": {"coordinates":[-74.003686,40.72668],"type":"Point"}
}