{
  "type": "Feature",
  "properties": {
    "iso:country":"US",
    "sg:address":"5663 E Circle Dr",
    "sg:city":"Cicero",
    "sg:classifiers":[
        {
            "category":"Health Services",
            "subcategory":"Dentist",
            "type":"Services"
        }
    ],
    "sg:phone":"+1 315 458 0080",
    "sg:postcode":"13039",
    "sg:province":"NY",
    "sg:tags":[
        "dentists-cosmetic",
        "denture",
        "dental",
        "clinic",
        "dentistry",
        "dentists-prosthodontists"
    ],
    "sg:website":"http://www.allcare.com",
    "wof:name":"Allcare Dental & Dentures",
    "wof:placetype":"venue"
},
  "geometry": {"coordinates":[-76.121571,43.148169],"type":"Point"}
}