{
  "type": "Feature",
  "properties": {
    "addr:full":"60 Oswego St Baldwinsville NY 13027",
    "addr:housenumber":"60",
    "addr:postcode":"13027",
    "addr:street":"Oswego St",
    "iso:country":"US",
    "sg:address":"60 Oswego St",
    "sg:city":"Baldwinsville",
    "sg:classifiers":[
        {
            "category":"Professional",
            "subcategory":"Secretarial Services",
            "type":"Services"
        }
    ],
    "sg:phone":"+1 315 635 1145",
    "sg:postcode":"13027",
    "sg:province":"NY",
    "sg:tags":[
        "record",
        "medical",
        "coding",
        "hospital"
    ],
    "wof:name":"Medical Coding Services Inc",
    "wof:placetype":"venue"
},
  "geometry": {"coordinates":[-76.33266399999999,43.158652],"type":"Point"}
}