{
  "type": "Feature",
  "properties": {
    "addr:full":"914 Hoe Ave Bronx NY 10459",
    "addr:housenumber":"914",
    "addr:postcode":"10459",
    "addr:street":"Hoe Ave",
    "iso:country":"US",
    "sg:address":"914 Hoe Ave",
    "sg:city":"Bronx",
    "sg:classifiers":[
        {
            "category":"Restaurant",
            "type":"Food & Drink"
        }
    ],
    "sg:phone":"+1 718 617 6161",
    "sg:postcode":"10459",
    "sg:province":"NY",
    "wof:name":"Boricuas Pizzera",
    "wof:placetype":"venue"
},
  "geometry": {"coordinates":[-73.89032400000001,40.822835],"type":"Point"}
}