{
  "type": "Feature",
  "properties": {
    "iso:country":"US",
    "sg:address":"170 Mercer Street",
    "sg:city":"New York",
    "sg:classifiers":[
        {
            "category":"Recreation",
            "subcategory":"Dance Hall",
            "type":"Entertainment"
        }
    ],
    "sg:phone":"+1 212 343 3095",
    "sg:postcode":"10012",
    "sg:province":"NY",
    "sg:tags":[
        "club"
    ],
    "wof:name":"Gypsy",
    "wof:placetype":"venue"
},
  "geometry": {"coordinates":[-73.99822,40.725064],"type":"Point"}
}