{
  "type": "Feature",
  "properties": {
    "addr:full":"8016 Greenbush Rd Akron NY 14001",
    "addr:housenumber":"8016",
    "addr:postcode":"14001",
    "addr:street":"Greenbush Rd",
    "iso:country":"US",
    "sg:address":"8016 Greenbush Rd",
    "sg:city":"Akron",
    "sg:phone":"+1 716 542 3510",
    "sg:postcode":"14001",
    "sg:province":"NY",
    "sg:tags":[
        "farm",
        "wheat"
    ],
    "wof:name":"Raymond Schrock",
    "wof:placetype":"venue"
},
  "geometry": {"coordinates":[-78.52965399999999,43.060046],"type":"Point"}
}