{
  "type": "Feature",
  "properties": {
    "iso:country":"US",
    "sg:address":"80 Orville Dr",
    "sg:city":"Bohemia",
    "sg:classifiers":[
        {
            "category":"Home & Garden",
            "subcategory":"Furniture",
            "type":"Retail Goods"
        }
    ],
    "sg:phone":"+1 631 244 1567",
    "sg:postcode":"11716",
    "sg:province":"NY",
    "sg:tags":[
        "equipment-household",
        "kitchen",
        "cabinet"
    ],
    "sg:website":"http://www.bayhill.net",
    "wof:name":"Unlimited Designs",
    "wof:placetype":"venue"
},
  "geometry": {"coordinates":[-73.101726,40.774763],"type":"Point"}
}