{
  "type": "Feature",
  "properties": {
    "addr:full":"2535 3rd Ave Bronx NY 10451",
    "addr:housenumber":"2535",
    "addr:postcode":"10451",
    "addr:street":"3Rd Ave",
    "iso:country":"US",
    "sg:address":"2535 3rd Ave",
    "sg:city":"Bronx",
    "sg:classifiers":[
        {
            "category":"Organizations",
            "subcategory":"Community Association",
            "type":"Services"
        }
    ],
    "sg:phone":"+1 718 742 0466",
    "sg:postcode":"10451",
    "sg:province":"NY",
    "sg:tags":[
        "club"
    ],
    "wof:name":"African Marquis LA Plantation",
    "wof:placetype":"venue"
},
  "geometry": {"coordinates":[-73.92752299999999,40.810764],"type":"Point"}
}