{
  "type": "Feature",
  "properties": {
    "addr:full":"346 Wilson St West Hempstead NY 11552",
    "addr:housenumber":"346",
    "addr:postcode":"11552",
    "addr:street":"Wilson St",
    "iso:country":"US",
    "sg:address":"346 Wilson St",
    "sg:city":"West Hempstead",
    "sg:classifiers":[
        {
            "category":"Health Services",
            "subcategory":"Doctor",
            "type":"Services"
        }
    ],
    "sg:phone":"+1 516 486 7384",
    "sg:postcode":"11552",
    "sg:province":"NY",
    "wof:name":"Herschman Aviva Lehrfield",
    "wof:placetype":"venue"
},
  "geometry": {"coordinates":[-73.65270700000001,40.700248],"type":"Point"}
}