{
  "type": "Feature",
  "properties": {
    "addr:full":"3300 Lawson Blvd Oceanside NY 11572",
    "addr:housenumber":"3300",
    "addr:postcode":"11572",
    "addr:street":"Lawson Blvd",
    "iso:country":"US",
    "sg:address":"3300 Lawson Blvd",
    "sg:city":"Oceanside",
    "sg:classifiers":[
        {
            "category":"Manufacturing",
            "subcategory":"Tools & Machinery",
            "type":"Manufacturing & Wholesale Goods"
        }
    ],
    "sg:phone":"+1 516 255 0292",
    "sg:postcode":"11572",
    "sg:province":"NY",
    "sg:tags":[
        "machine",
        "shop"
    ],
    "wof:name":"E F Kaiser Co Inc",
    "wof:placetype":"venue"
},
  "geometry": {"coordinates":[-73.652669,40.629667],"type":"Point"}
}