{
  "type": "Feature",
  "properties": {
    "addr:full":"24306 Merrick Boulevard Rosedale NY 11422",
    "addr:housenumber":"24306",
    "addr:postcode":"11422",
    "addr:street":"Merrick Boulevard",
    "iso:country":"US",
    "sg:address":"24306 Merrick Boulevard",
    "sg:city":"Rosedale",
    "sg:classifiers":[
        {
            "category":"Restaurant",
            "type":"Food & Drink"
        }
    ],
    "sg:phone":"+1 718 525 3185",
    "sg:postcode":"11422",
    "sg:province":"NY",
    "sg:tags":[
        "pizza"
    ],
    "wof:name":"Labari's Pizzeria",
    "wof:placetype":"venue"
},
  "geometry": {"coordinates":[-73.73045500000001,40.673851],"type":"Point"}
}