{
  "type": "Feature",
  "properties": {
    "addr:full":"8 Stevens St Freeport NY 11520",
    "addr:housenumber":"8",
    "addr:postcode":"11520",
    "addr:street":"Stevens St",
    "iso:country":"US",
    "sg:address":"8 Stevens St",
    "sg:city":"Freeport",
    "sg:classifiers":[
        {
            "category":"Wholesale",
            "subcategory":"Machinery & Supplies",
            "type":"Manufacturing & Wholesale Goods"
        },
        {
            "category":"Wholesale",
            "subcategory":"Chemicals & Plastics",
            "type":"Manufacturing & Wholesale Goods"
        },
        {
            "category":"Building & Trades",
            "subcategory":"Construction",
            "type":"Services"
        }
    ],
    "sg:phone":"+1 516 623 4519",
    "sg:postcode":"11520",
    "sg:province":"NY",
    "sg:tags":[
        "equipment",
        "welder",
        "helium",
        "welding"
    ],
    "wof:name":"Ace Welding Supply Inc",
    "wof:placetype":"venue"
},
  "geometry": {"coordinates":[-73.58744799999999,40.668499],"type":"Point"}
}