{
  "type": "Feature",
  "properties": {
    "iso:country":"US",
    "sg:address":"Richmond Avenue & Summer",
    "sg:city":"Buffalo",
    "sg:classifiers":[
        {
            "category":"Sports & Exercise",
            "subcategory":"Sports Center",
            "type":"Entertainment"
        }
    ],
    "sg:phone":"+1 716 885 3290",
    "sg:postcode":"14201",
    "sg:province":"NY",
    "sg:tags":[
        "amateur",
        "team"
    ],
    "wof:name":"Richmond Summer Recreation Center For the Elderly",
    "wof:placetype":"venue"
},
  "geometry": {"coordinates":[-78.881888,42.904785],"type":"Point"}
}