{
  "type": "Feature",
  "properties": {
    "addr:full":"594 Courtland Ave Bronx NY 10451",
    "addr:housenumber":"594",
    "addr:postcode":"10451",
    "addr:street":"Courtland Ave",
    "iso:country":"US",
    "sg:address":"594 Courtland Ave",
    "sg:city":"Bronx",
    "sg:classifiers":[
        {
            "category":"Retail",
            "subcategory":"Repair Shop",
            "type":"Services"
        }
    ],
    "sg:phone":"+1 718 231 2838",
    "sg:postcode":"10451",
    "sg:province":"NY",
    "sg:tags":[
        "lock",
        "locksmith"
    ],
    "wof:name":"24 7 Affordable Locksmith",
    "wof:placetype":"venue"
},
  "geometry": {"coordinates":[-73.91896300000001,40.817549],"type":"Point"}
}