{
  "type": "Feature",
  "properties": {
    "addr:full":"38 Avenue O Brooklyn NY 11204",
    "addr:housenumber":"38",
    "addr:postcode":"11204",
    "addr:street":"Avenue O",
    "iso:country":"US",
    "sg:address":"38 Avenue O",
    "sg:city":"Brooklyn",
    "sg:classifiers":[
        {
            "category":"Communications",
            "subcategory":"Film & Video Production",
            "type":"Services"
        }
    ],
    "sg:phone":"+1 718 621 9655",
    "sg:postcode":"11204",
    "sg:province":"NY",
    "sg:tags":[
        "companies-film",
        "tv",
        "dvd",
        "services-commercial",
        "duplicating",
        "cd",
        "radio",
        "cassette"
    ],
    "wof:name":"Best Video Productions",
    "wof:placetype":"venue"
},
  "geometry": {"coordinates":[-73.983779,40.610219],"type":"Point"}
}