{
  "type": "Feature",
  "properties": {
    "iso:country":"US",
    "sg:address":"129 Union Ave",
    "sg:city":"New Rochelle",
    "sg:classifiers":[
        {
            "category":"Building & Trades",
            "subcategory":"Construction",
            "type":"Services"
        },
        {
            "category":"Retail",
            "subcategory":"Auto Repair",
            "type":"Services"
        }
    ],
    "sg:phone":"+1 914 633 5853",
    "sg:postcode":"10801",
    "sg:province":"NY",
    "sg:tags":[
        "glass",
        "window",
        "coating",
        "tinting",
        "contractor"
    ],
    "wof:name":"Sunshield Energy Control Systs",
    "wof:placetype":"venue"
},
  "geometry": {"coordinates":[-73.789357,40.910033],"type":"Point"}
}