{
  "type": "Feature",
  "properties": {
    "iso:country":"US",
    "sg:address":"2700 Queens Plaza S",
    "sg:city":"Long Island City",
    "sg:classifiers":[
        {
            "category":"Bars & Pubs",
            "subcategory":"Nightclub",
            "type":"Food & Drink"
        }
    ],
    "sg:phone":"+1 718 786 8390",
    "sg:postcode":"11101",
    "sg:province":"NY",
    "sg:tags":[
        "nightlife"
    ],
    "wof:name":"City Scapes",
    "wof:placetype":"venue"
},
  "geometry": {"coordinates":[-73.939829,40.750076],"type":"Point"}
}