{
  "type": "Feature",
  "properties": {
    "iso:country":"US",
    "sg:address":"3636 N Buffalo St",
    "sg:city":"Orchard Park",
    "sg:classifiers":[
        {
            "category":"Building & Trades",
            "subcategory":"Pest Control",
            "type":"Services"
        }
    ],
    "sg:phone":"+1 716 884 0011",
    "sg:postcode":"14127",
    "sg:province":"NY",
    "sg:tags":[
        "exterminating"
    ],
    "sg:website":"www.buffaloexterminating.com",
    "wof:name":"Buffalo Exterminating Co Inc",
    "wof:placetype":"venue"
},
  "geometry": {"coordinates":[-78.75077899999999,42.788584],"type":"Point"}
}