{
  "type": "Feature",
  "properties": {
    "iso:country":"US",
    "sg:address":"111 Front St",
    "sg:city":"Brooklyn",
    "sg:classifiers":[
        {
            "category":"Restaurant",
            "type":"Food & Drink"
        }
    ],
    "sg:menulink":"http://www.allmenus.com/ny/brooklyn/274058-hecho-en-dumbo/menu/",
    "sg:phone":"+1 718 855 5288",
    "sg:postcode":"11201",
    "sg:province":"NY",
    "sg:tags":[
        "mexican"
    ],
    "wof:name":"Hecho En Dumbo",
    "wof:placetype":"venue"
},
  "geometry": {"coordinates":[-73.988995,40.702653],"type":"Point"}
}