{
  "type": "Feature",
  "properties": {
    "iso:country":"US",
    "sg:address":"23 Blake Ave",
    "sg:city":"Lynbrook",
    "sg:classifiers":[
        {
            "category":"Building & Trades",
            "subcategory":"Equipment Rental",
            "type":"Services"
        }
    ],
    "sg:phone":"+1   ",
    "sg:postcode":"11563",
    "sg:province":"NY",
    "sg:tags":[
        "machine",
        "a",
        "vending"
    ],
    "wof:name":"Greenwood Vending Svce",
    "wof:placetype":"venue"
},
  "geometry": {"coordinates":[-73.67186700000001,40.658037],"type":"Point"}
}