{
  "type": "Feature",
  "properties": {
    "iso:country":"US",
    "sg:address":"779 Washington St",
    "sg:city":"Buffalo",
    "sg:classifiers":[
        {
            "category":"Shopping",
            "subcategory":"Computers & Home Electronics",
            "type":"Retail Goods"
        }
    ],
    "sg:phone":"+1 716 854 2063",
    "sg:postcode":"14203",
    "sg:province":"NY",
    "sg:tags":[
        "software"
    ],
    "wof:name":"Niagara Systems & Software Inc",
    "wof:placetype":"venue"
},
  "geometry": {"coordinates":[-78.870744,42.893263],"type":"Point"}
}