{
  "type": "Feature",
  "properties": {
    "iso:country":"US",
    "sg:address":"62 Thruway Ct",
    "sg:city":"Buffalo",
    "sg:classifiers":[
        {
            "category":"Building & Trades",
            "subcategory":"Plumbing",
            "type":"Services"
        }
    ],
    "sg:phone":"+1 716 893 8111",
    "sg:postcode":"14225",
    "sg:province":"NY",
    "sg:tags":[
        "contractor"
    ],
    "wof:name":"Sherer Heating & AC",
    "wof:placetype":"venue"
},
  "geometry": {"coordinates":[-78.76813,42.927482],"type":"Point"}
}