{
  "type": "Feature",
  "properties": {
    "addr:full":"118 Lander Ave Staten Island NY 10314",
    "addr:housenumber":"118",
    "addr:postcode":"10314",
    "addr:street":"Lander Ave",
    "iso:country":"US",
    "sg:address":"118 Lander Ave",
    "sg:city":"Staten Island",
    "sg:classifiers":[
        {
            "category":"Building & Trades",
            "subcategory":"Construction",
            "type":"Services"
        }
    ],
    "sg:phone":"+1 718 494 9042",
    "sg:postcode":"10314",
    "sg:province":"NY",
    "sg:tags":[
        "house",
        "nonresidential"
    ],
    "wof:name":"Highkord Inc",
    "wof:placetype":"venue"
},
  "geometry": {"coordinates":[-74.16307,40.613627],"type":"Point"}
}