{
  "type": "Feature",
  "properties": {
    "iso:country":"US",
    "sg:address":"1012 Westwood Rd",
    "sg:city":"Woodmere",
    "sg:classifiers":[
        {
            "category":"Health Services",
            "subcategory":"Doctor",
            "type":"Services"
        }
    ],
    "sg:phone":"+1 516 374 9050",
    "sg:postcode":"11598",
    "sg:province":"NY",
    "sg:tags":[
        "physician",
        "surgeon"
    ],
    "wof:name":"A Better Dermatology Center",
    "wof:placetype":"venue"
},
  "geometry": {"coordinates":[-73.712502,40.6399],"type":"Point"}
}