{
  "type": "Feature",
  "properties": {
    "addr:full":"2 Barrie Dr Spring Valley NY 10977",
    "addr:housenumber":"2",
    "addr:postcode":"10977",
    "addr:street":"Barrie Dr",
    "iso:country":"US",
    "sg:address":"2 Barrie Dr",
    "sg:city":"Spring Valley",
    "sg:classifiers":[
        {
            "category":"Manufacturing",
            "subcategory":"Rubber & Plastics",
            "type":"Manufacturing & Wholesale Goods"
        }
    ],
    "sg:phone":"+1 845 364 9500",
    "sg:postcode":"10977",
    "sg:province":"NY",
    "sg:tags":[
        "polyethylene",
        "material",
        "prod"
    ],
    "wof:name":"Innovative Packaging Corp",
    "wof:placetype":"venue"
},
  "geometry": {"coordinates":[-74.058104,41.144146],"type":"Point"}
}