{
  "type": "Feature",
  "properties": {
    "iso:country":"US",
    "sg:address":"725 Park Ave",
    "sg:city":"Rochester",
    "sg:classifiers":[
        {
            "category":"Restaurant",
            "type":"Food & Drink"
        },
        {
            "category":"Bars & Pubs",
            "type":"Food & Drink"
        }
    ],
    "sg:phone":"+1 585 244 3267",
    "sg:postcode":"14607",
    "sg:province":"NY",
    "sg:tags":[
        "drinking"
    ],
    "wof:name":"Park Bench Back Alley Bar Rest",
    "wof:placetype":"venue"
},
  "geometry": {"coordinates":[-77.576156,43.147611],"type":"Point"}
}