{
  "type": "Feature",
  "properties": {
    "iso:country":"US",
    "sg:address":"135 Croton Ave",
    "sg:city":"Ossining",
    "sg:classifiers":[
        {
            "category":"Real Estate",
            "subcategory":"Real Estate Operator",
            "type":"Services"
        }
    ],
    "sg:phone":"+1 914 941 0077",
    "sg:postcode":"10562",
    "sg:province":"NY",
    "sg:tags":[
        "apartment"
    ],
    "wof:name":"Home Properties",
    "wof:placetype":"venue"
},
  "geometry": {"coordinates":[-73.85252800000001,41.167265],"type":"Point"}
}