{
  "type": "Feature",
  "properties": {
    "iso:country":"US",
    "sg:address":"19 Grace Ct.",
    "sg:city":"Islip",
    "sg:classifiers":[
        {
            "category":"Building & Trades",
            "subcategory":"Construction",
            "type":"Services"
        }
    ],
    "sg:phone":"+1 631 968 5820",
    "sg:postcode":"11751",
    "sg:province":"NY",
    "sg:tags":[
        "contractor"
    ],
    "sg:website":"www.longislanddockbuilders.com",
    "wof:name":"All Shore Marine Construction",
    "wof:placetype":"venue"
},
  "geometry": {"coordinates":[-73.218473,40.720275],"type":"Point"}
}