{
  "type": "Feature",
  "properties": {
    "addr:full":"100 Atlantic Ave Brooklyn NY 11201",
    "addr:housenumber":"100",
    "addr:postcode":"11201",
    "addr:street":"Atlantic Ave",
    "iso:country":"US",
    "sg:address":"100 Atlantic Ave",
    "sg:city":"Brooklyn",
    "sg:classifiers":[
        {
            "category":"Real Estate",
            "subcategory":"Real Estate Operator",
            "type":"Services"
        }
    ],
    "sg:phone":"+1 718 522 4111",
    "sg:postcode":"11201",
    "sg:province":"NY",
    "sg:tags":[
        "apartment"
    ],
    "wof:name":"Atlantic Apartments LLC",
    "wof:placetype":"venue"
},
  "geometry": {"coordinates":[-73.997793,40.691188],"type":"Point"}
}