{
  "type": "Feature",
  "properties": {
    "addr:full":"3144 Heath Ave Bronx NY 10463",
    "addr:housenumber":"3144",
    "addr:postcode":"10463",
    "addr:street":"Heath Ave",
    "iso:country":"US",
    "sg:address":"3144 Heath Ave",
    "sg:city":"Bronx",
    "sg:classifiers":[
        {
            "category":"Food & Beverages",
            "subcategory":"Groceries & Convenience Stores",
            "type":"Retail Goods"
        }
    ],
    "sg:phone":"+1   ",
    "sg:postcode":"10463",
    "sg:province":"NY",
    "wof:name":"Cruz Grocery Store",
    "wof:placetype":"venue"
},
  "geometry": {"coordinates":[-73.899227,40.878613],"type":"Point"}
}