{
  "type": "Feature",
  "properties": {
    "addr:full":"153 Rockaway Pkwy Valley Stream NY 11580",
    "addr:housenumber":"153",
    "addr:postcode":"11580",
    "addr:street":"Rockaway Pkwy",
    "iso:country":"US",
    "sg:address":"153 Rockaway Pkwy",
    "sg:city":"Valley Stream",
    "sg:classifiers":[
        {
            "category":"Freight",
            "type":"Transportation"
        }
    ],
    "sg:phone":"+1 516 256 7775",
    "sg:postcode":"11580",
    "sg:province":"NY",
    "sg:tags":[
        "delivery"
    ],
    "wof:name":"Direct Delivery Svc",
    "wof:placetype":"venue"
},
  "geometry": {"coordinates":[-73.695567,40.669566],"type":"Point"}
}