{
  "type": "Feature",
  "properties": {
    "iso:country":"US",
    "sg:address":"360 Sweezy Ave",
    "sg:city":"Riverhead",
    "sg:classifiers":[
        {
            "category":"Retail",
            "subcategory":"Auto Repair",
            "type":"Services"
        }
    ],
    "sg:phone":"+1 631 727 6767",
    "sg:postcode":"11901",
    "sg:province":"NY",
    "sg:tags":[
        "repairing",
        "automobile",
        "automotive"
    ],
    "wof:name":"George's Auto Repair",
    "wof:placetype":"venue"
},
  "geometry": {"coordinates":[-72.67379800000001,40.9221],"type":"Point"}
}