{
  "type": "Feature",
  "properties": {
    "iso:country":"US",
    "sg:address":"136 Wooster St",
    "sg:city":"New York",
    "sg:classifiers":[
        {
            "category":"Shopping",
            "subcategory":"Shoes",
            "type":"Retail Goods"
        }
    ],
    "sg:phone":"+1 212 777 2005",
    "sg:postcode":"10012",
    "sg:province":"NY",
    "wof:name":"Adidas America Inc",
    "wof:placetype":"venue"
},
  "geometry": {"coordinates":[-73.999173,40.726319],"type":"Point"}
}