{
  "type": "Feature",
  "properties": {
    "iso:country":"US",
    "sg:address":"347 Broadway",
    "sg:city":"Newburgh",
    "sg:classifiers":[
        {
            "category":"Professional",
            "type":"Services"
        }
    ],
    "sg:phone":"+1 845 561 9553",
    "sg:postcode":"12550",
    "sg:province":"NY",
    "sg:tags":[
        "establishment"
    ],
    "wof:name":"Clark",
    "wof:placetype":"venue"
},
  "geometry": {"coordinates":[-74.025588,41.501],"type":"Point"}
}