{
  "type": "Feature",
  "properties": {
    "addr:full":"31 Pondfield Rd W Bronxville NY 10708",
    "addr:housenumber":"31",
    "addr:postcode":"10708",
    "addr:street":"Pondfield Rd W",
    "iso:country":"US",
    "sg:address":"31 Pondfield Rd W",
    "sg:city":"Bronxville",
    "sg:classifiers":[
        {
            "category":"Building & Trades",
            "subcategory":"Construction",
            "type":"Services"
        }
    ],
    "sg:phone":"+1 914 961 4252",
    "sg:postcode":"10708",
    "sg:province":"NY",
    "sg:tags":[
        "house"
    ],
    "wof:name":"JM Construction Renovations",
    "wof:placetype":"venue"
},
  "geometry": {"coordinates":[-73.83934600000001,40.943809],"type":"Point"}
}