{
  "type": "Feature",
  "properties": {
    "iso:country":"US",
    "sg:address":"2231 Brickyard Rd",
    "sg:city":"Canandaigua",
    "sg:classifiers":[
        {
            "category":"Sports & Exercise",
            "subcategory":"Golf",
            "type":"Entertainment"
        }
    ],
    "sg:phone":"+1 585 924 5346",
    "sg:postcode":"14424",
    "sg:province":"NY",
    "sg:tags":[
        "course"
    ],
    "wof:name":"Centerpointe Country Club",
    "wof:placetype":"venue"
},
  "geometry": {"coordinates":[-77.325782,42.921661],"type":"Point"}
}