{
  "type": "Feature",
  "properties": {
    "addr:full":"2199 Holland Ave Bronx NY 10462",
    "addr:housenumber":"2199",
    "addr:postcode":"10462",
    "addr:street":"Holland Ave",
    "iso:country":"US",
    "sg:address":"2199 Holland Ave",
    "sg:city":"Bronx",
    "sg:classifiers":[
        {
            "category":"Professional",
            "subcategory":"Advertising",
            "type":"Services"
        }
    ],
    "sg:phone":"+1 718 409 1196",
    "sg:postcode":"10462",
    "sg:province":"NY",
    "sg:tags":[
        "distributing",
        "sample"
    ],
    "wof:name":"Metro International Distribtrs",
    "wof:placetype":"venue"
},
  "geometry": {"coordinates":[-73.865753,40.854459],"type":"Point"}
}