{
  "type": "Feature",
  "properties": {
    "iso:country":"US",
    "sg:address":"77 Creek Rd",
    "sg:city":"Poughkeepsie",
    "sg:classifiers":[
        {
            "category":"Autos & Motor Vehicles",
            "subcategory":"Motorcycle Sales",
            "type":"Retail Goods"
        }
    ],
    "sg:phone":"+1   ",
    "sg:postcode":"12601",
    "sg:province":"NY",
    "sg:tags":[
        "automobile",
        "used"
    ],
    "wof:name":"Verdi V-Twin",
    "wof:placetype":"venue"
},
  "geometry": {"coordinates":[-73.906193,41.718153],"type":"Point"}
}