{
  "type": "Feature",
  "properties": {
    "iso:country":"US",
    "sg:address":"215 S 1st St",
    "sg:city":"Fulton",
    "sg:classifiers":[
        {
            "category":"Restaurant",
            "type":"Food & Drink"
        }
    ],
    "sg:menulink":"http://www.allmenus.com/ny/fulton/229176-jreck-subs/menu/",
    "sg:phone":"+1 315 598 8818",
    "sg:postcode":"13069",
    "sg:province":"NY",
    "sg:tags":[
        "wrap",
        "american",
        "sandwich"
    ],
    "wof:name":"Jreck Subs",
    "wof:placetype":"venue"
},
  "geometry": {"coordinates":[-76.41537099999999,43.319558],"type":"Point"}
}