{
  "type": "Feature",
  "properties": {
    "iso:country":"US",
    "sg:address":"34 Heritage Ct",
    "sg:city":"Lockport",
    "sg:classifiers":[
        {
            "category":"Manufacturing",
            "subcategory":"Printing",
            "type":"Manufacturing & Wholesale Goods"
        }
    ],
    "sg:phone":"+1   ",
    "sg:postcode":"14094",
    "sg:province":"NY",
    "sg:tags":[
        "print",
        "lithographic"
    ],
    "wof:name":"Micro Graphics",
    "wof:placetype":"venue"
},
  "geometry": {"coordinates":[-78.692582,43.169152],"type":"Point"}
}