{
  "type": "Feature",
  "properties": {
    "iso:country":"US",
    "sg:address":"52 Maple St",
    "sg:city":"Auburn",
    "sg:classifiers":[
        {
            "category":"Building & Trades",
            "subcategory":"Construction",
            "type":"Services"
        }
    ],
    "sg:phone":"+1 315 255 1075",
    "sg:postcode":"13021",
    "sg:province":"NY",
    "sg:tags":[
        "contractor"
    ],
    "wof:name":"Chimney Works",
    "wof:placetype":"venue"
},
  "geometry": {"coordinates":[-76.54829100000001,42.929317],"type":"Point"}
}