{
  "type": "Feature",
  "properties": {
    "addr:full":"48 Allen Blvd Farmingdale NY 11735",
    "addr:housenumber":"48",
    "addr:postcode":"11735",
    "addr:street":"Allen Blvd",
    "iso:country":"US",
    "sg:address":"48 Allen Blvd",
    "sg:city":"Farmingdale",
    "sg:classifiers":[
        {
            "category":"Manufacturing",
            "subcategory":"Tools & Machinery",
            "type":"Manufacturing & Wholesale Goods"
        }
    ],
    "sg:phone":"+1   ",
    "sg:postcode":"11735",
    "sg:province":"NY",
    "sg:tags":[
        "packaging",
        "mfg"
    ],
    "wof:name":"R P S Company",
    "wof:placetype":"venue"
},
  "geometry": {"coordinates":[-73.42360499999999,40.71563],"type":"Point"}
}