{
  "type": "Feature",
  "properties": {
    "iso:country":"US",
    "sg:address":"6 Courtney Dr",
    "sg:city":"New City",
    "sg:classifiers":[
        {
            "category":"Professional",
            "subcategory":"Management & Consulting",
            "type":"Services"
        }
    ],
    "sg:phone":"+1 845 634 7613",
    "sg:postcode":"10956",
    "sg:province":"NY",
    "sg:tags":[
        "communication",
        "consultant"
    ],
    "wof:name":"Automated Analyst Service",
    "wof:placetype":"venue"
},
  "geometry": {"coordinates":[-73.97810699999999,41.14296],"type":"Point"}
}