{
  "type": "Feature",
  "properties": {
    "addr:full":"350 Linwood St Brooklyn NY 11208",
    "addr:housenumber":"350",
    "addr:postcode":"11208",
    "addr:street":"Linwood St",
    "iso:country":"US",
    "sg:address":"350 Linwood St",
    "sg:city":"Brooklyn",
    "sg:classifiers":[
        {
            "category":"Recreation",
            "type":"Entertainment"
        }
    ],
    "sg:phone":"+1 718 277 5664",
    "sg:postcode":"11208",
    "sg:province":"NY",
    "sg:tags":[
        "tennis",
        "court"
    ],
    "wof:name":"N Y Junior Tennis League-Is 302",
    "wof:placetype":"venue"
},
  "geometry": {"coordinates":[-73.883698,40.677502],"type":"Point"}
}