{
  "type": "Feature",
  "properties": {
    "iso:country":"US",
    "sg:address":"161 Avenue of the Americas, Ste 904",
    "sg:city":"New York",
    "sg:classifiers":[
        {
            "category":"Professional",
            "subcategory":"Computer Services",
            "type":"Services"
        }
    ],
    "sg:postcode":"10019",
    "sg:province":"NY",
    "wof:name":"Oriel Wines",
    "wof:placetype":"venue"
},
  "geometry": {"coordinates":[-73.979513,40.761148],"type":"Point"}
}