{
  "type": "Feature",
  "properties": {
    "iso:country":"US",
    "sg:address":"467 Enterprise Rd",
    "sg:city":"Rhinebeck",
    "sg:classifiers":[
        {
            "category":"Building & Trades",
            "subcategory":"Plumbing",
            "type":"Services"
        }
    ],
    "sg:phone":"+1 845 876 5371",
    "sg:postcode":"12572",
    "sg:province":"NY",
    "sg:tags":[
        "contractor"
    ],
    "wof:name":"Larry Hauptman Plumbing & Htg",
    "wof:placetype":"venue"
},
  "geometry": {"coordinates":[-73.82696199999999,41.922553],"type":"Point"}
}