{
  "type": "Feature",
  "properties": {
    "addr:full":"247 W Fayette St Syracuse NY 13202",
    "addr:housenumber":"247",
    "addr:postcode":"13202",
    "addr:street":"W Fayette St",
    "iso:country":"US",
    "sg:address":"247 W Fayette St",
    "sg:city":"Syracuse",
    "sg:classifiers":[
        {
            "category":"Restaurant",
            "type":"Food & Drink"
        }
    ],
    "sg:menulink":"http://www.allmenus.com/ny/syracuse/251319-b-c-restaurant/menu/",
    "sg:phone":"+1 315 701 0636",
    "sg:postcode":"13202",
    "sg:province":"NY",
    "sg:tags":[
        "seafood",
        "american"
    ],
    "wof:name":"B C Restaurant",
    "wof:placetype":"venue"
},
  "geometry": {"coordinates":[-76.154487,43.048696],"type":"Point"}
}