{
  "type": "Feature",
  "properties": {
    "addr:full":"3115 Long Beach Rd Oceanside NY 11572",
    "addr:housenumber":"3115",
    "addr:postcode":"11572",
    "addr:street":"Long Beach Rd",
    "iso:country":"US",
    "sg:address":"3115 Long Beach Rd",
    "sg:city":"Oceanside",
    "sg:classifiers":[
        {
            "category":"Building & Trades",
            "subcategory":"Construction",
            "type":"Services"
        }
    ],
    "sg:phone":"+1 516 766 3732",
    "sg:postcode":"11572",
    "sg:province":"NY",
    "sg:tags":[
        "contractor"
    ],
    "wof:name":"Redco Constr Corp",
    "wof:placetype":"venue"
},
  "geometry": {"coordinates":[-73.640404,40.636101],"type":"Point"}
}