{
  "type": "Feature",
  "properties": {
    "iso:country":"US",
    "sg:address":"116 Skyline Dr",
    "sg:city":"Coram",
    "sg:classifiers":[
        {
            "category":"Shopping",
            "subcategory":"Gifts & Souvenirs",
            "type":"Retail Goods"
        }
    ],
    "sg:phone":"+1   ",
    "sg:postcode":"11727",
    "sg:province":"NY",
    "wof:name":"Baskets By Bobbi",
    "wof:placetype":"venue"
},
  "geometry": {"coordinates":[-73.014878,40.861984],"type":"Point"}
}