{
  "type": "Feature",
  "properties": {
    "iso:country":"US",
    "sg:address":"670 Co Rd 25",
    "sg:city":"South Edmeston",
    "sg:classifiers":[
        {
            "category":"Bars & Pubs",
            "type":"Food & Drink"
        }
    ],
    "sg:phone":"+1 607 847 9976",
    "sg:postcode":"13411",
    "sg:province":"NY",
    "wof:name":"Rick's Tavern",
    "wof:placetype":"venue"
},
  "geometry": {"coordinates":[-75.324138,42.684679],"type":"Point"}
}