{
  "type": "Feature",
  "properties": {
    "addr:full":"670 Co Rd 25 South Edmeston NY 13411",
    "addr:housenumber":"670;25",
    "addr:postcode":"13411",
    "addr:street":"Co Rd;South Edmeston",
    "iso:country":"US",
    "sg:address":"670 Co Rd 25",
    "sg:city":"South Edmeston",
    "sg:classifiers":[
        {
            "category":"Bars & Pubs",
            "type":"Food & Drink"
        }
    ],
    "sg:phone":"+1 607 847 9976",
    "sg:postcode":"13411",
    "sg:province":"NY",
    "wof:name":"Rick's Tavern",
    "wof:placetype":"venue"
},
  "geometry": {"coordinates":[-75.324138,42.684679],"type":"Point"}
}