{
  "type": "Feature",
  "properties": {
    "addr:full":"928 Long Island Ave Deer Park NY 11729",
    "addr:housenumber":"928",
    "addr:postcode":"11729",
    "addr:street":"Long Island Ave",
    "iso:country":"US",
    "sg:address":"928 Long Island Ave",
    "sg:city":"Deer Park",
    "sg:classifiers":[
        {
            "category":"Wholesale",
            "subcategory":"Construction Materials",
            "type":"Manufacturing & Wholesale Goods"
        }
    ],
    "sg:phone":"+1   ",
    "sg:postcode":"11729",
    "sg:province":"NY",
    "sg:tags":[
        "ready",
        "concrete"
    ],
    "wof:name":"Ace Transit Mix",
    "wof:placetype":"venue"
},
  "geometry": {"coordinates":[-73.31104499999999,40.766016],"type":"Point"}
}