{
  "type": "Feature",
  "properties": {
    "addr:full":"10 Edgewater Dr Mastic Beach NY 11951",
    "addr:housenumber":"10",
    "addr:postcode":"11951",
    "addr:street":"Edgewater Dr",
    "iso:country":"US",
    "sg:address":"10 Edgewater Dr",
    "sg:city":"Mastic Beach",
    "sg:classifiers":[
        {
            "category":"Professional",
            "subcategory":"Business Services",
            "type":"Services"
        },
        {
            "category":"Manufacturing",
            "subcategory":"Electronics",
            "type":"Manufacturing & Wholesale Goods"
        }
    ],
    "sg:phone":"+1 631 399 4646",
    "sg:postcode":"11951",
    "sg:province":"NY",
    "sg:tags":[
        "prerecorded",
        "mfg"
    ],
    "wof:name":"OHM Productions Inc",
    "wof:placetype":"venue"
},
  "geometry": {"coordinates":[-72.815665,40.7748],"type":"Point"}
}