{
  "type": "Feature",
  "properties": {
    "addr:full":"803 Washington Ave Brooklyn NY 11238",
    "addr:housenumber":"803",
    "addr:postcode":"11238",
    "addr:street":"Washington Ave",
    "iso:country":"US",
    "sg:address":"803 Washington Ave",
    "sg:city":"Brooklyn",
    "sg:classifiers":[
        {
            "category":"Restaurant",
            "type":"Food & Drink"
        }
    ],
    "sg:phone":"+1 718 398 3575",
    "sg:postcode":"11238",
    "sg:province":"NY",
    "sg:tags":[
        "caribbean"
    ],
    "wof:name":"The Islands",
    "wof:placetype":"venue"
},
  "geometry": {"coordinates":[-73.96266,40.672101],"type":"Point"}
}