{
  "type": "Feature",
  "properties": {
    "iso:country":"US",
    "sg:address":"243 S Main St",
    "sg:city":"Albion",
    "sg:classifiers":[
        {
            "category":"Social Services",
            "subcategory":"Child Care",
            "type":"Services"
        }
    ],
    "sg:phone":"+1 585 589 5384",
    "sg:postcode":"14411",
    "sg:province":"NY",
    "sg:tags":[
        "day"
    ],
    "wof:name":"ARC Orleans County Rnbow",
    "wof:placetype":"venue"
},
  "geometry": {"coordinates":[-78.19393599999999,43.238468],"type":"Point"}
}