{
  "type": "Feature",
  "properties": {
    "iso:country":"US",
    "sg:address":"334 7th Ave",
    "sg:city":"Troy",
    "sg:classifiers":[
        {
            "category":"Insurance",
            "subcategory":"Insurance Agent",
            "type":"Services"
        }
    ],
    "sg:phone":"+1 518 233 0993",
    "sg:postcode":"12182",
    "sg:province":"NY",
    "wof:name":"Ohio Casualty Insurance Co",
    "wof:placetype":"venue"
},
  "geometry": {"coordinates":[-73.67563,42.763555],"type":"Point"}
}