{
  "type": "Feature",
  "properties": {
    "addr:full":"887 5th Ave Brooklyn NY 11232",
    "addr:housenumber":"887",
    "addr:postcode":"11232",
    "addr:street":"5Th Ave",
    "iso:country":"US",
    "sg:address":"887 5th Ave",
    "sg:city":"Brooklyn",
    "sg:classifiers":[
        {
            "category":"Restaurant",
            "type":"Food & Drink"
        }
    ],
    "sg:phone":"+1 718 686 8488",
    "sg:postcode":"11232",
    "sg:province":"NY",
    "wof:name":"J F K Fried Chicken",
    "wof:placetype":"venue"
},
  "geometry": {"coordinates":[-74.003468,40.651247],"type":"Point"}
}