{
  "type": "Feature",
  "properties": {
    "addr:full":"182 Evergreen Rd Riverhead NY 11901",
    "addr:housenumber":"182",
    "addr:postcode":"11901",
    "addr:street":"Evergreen Rd",
    "iso:country":"US",
    "sg:address":"182 Evergreen Rd",
    "sg:city":"Riverhead",
    "sg:classifiers":[
        {
            "category":"Shopping",
            "subcategory":"Bicycles & Sporting Goods",
            "type":"Retail Goods"
        }
    ],
    "sg:phone":"+1   ",
    "sg:postcode":"11901",
    "sg:province":"NY",
    "wof:name":"W Leposa Golf Pro",
    "wof:placetype":"venue"
},
  "geometry": {"coordinates":[-72.637698,40.915919],"type":"Point"}
}