{
  "type": "Feature",
  "properties": {
    "addr:full":"200 Katonah Ave Katonah NY 10536",
    "addr:housenumber":"200",
    "addr:postcode":"10536",
    "addr:street":"Katonah Ave",
    "iso:country":"US",
    "sg:address":"200 Katonah Ave",
    "sg:city":"Katonah",
    "sg:classifiers":[
        {
            "category":"Professional",
            "subcategory":"Management & Consulting",
            "type":"Services"
        }
    ],
    "sg:phone":"+1 914 767 3200",
    "sg:postcode":"10536",
    "sg:province":"NY",
    "sg:tags":[
        "communications",
        "consultant"
    ],
    "wof:name":"Telecom Network Solutions",
    "wof:placetype":"venue"
},
  "geometry": {"coordinates":[-73.683892,41.256183],"type":"Point"}
}