{
  "type": "Feature",
  "properties": {
    "addr:full":"10202 Queens Boulevard Forest Hills NY 11375",
    "addr:housenumber":"10202",
    "addr:postcode":"11375",
    "addr:street":"Queens Boulevard",
    "iso:country":"US",
    "sg:address":"10202 Queens Boulevard",
    "sg:city":"Forest Hills",
    "sg:classifiers":[
        {
            "category":"Retail",
            "subcategory":"Auto Repair",
            "type":"Services"
        }
    ],
    "sg:phone":"+1 718 459 8200",
    "sg:postcode":"11375",
    "sg:province":"NY",
    "wof:name":"Cunningham Pontiac",
    "wof:placetype":"venue"
},
  "geometry": {"coordinates":[-73.851764,40.725892],"type":"Point"}
}