{
  "type": "Feature",
  "properties": {
    "addr:full":"348 Plymouth Ave Brightwaters NY 11718",
    "addr:housenumber":"348",
    "addr:postcode":"11718",
    "addr:street":"Plymouth Ave",
    "iso:country":"US",
    "sg:address":"348 Plymouth Ave",
    "sg:city":"Brightwaters",
    "sg:classifiers":[
        {
            "category":"Professional",
            "type":"Services"
        }
    ],
    "sg:phone":"+1 631 666 4949",
    "sg:postcode":"11718",
    "sg:province":"NY",
    "sg:tags":[
        "establishment"
    ],
    "wof:name":"Chumley's Byte",
    "wof:placetype":"venue"
},
  "geometry": {"coordinates":[-73.26683800000001,40.718912],"type":"Point"}
}