{
  "type": "Feature",
  "properties": {
    "iso:country":"US",
    "sg:address":"165 Charles St",
    "sg:city":"Painted Post",
    "sg:classifiers":[
        {
            "category":"Organizations",
            "subcategory":"Community Association",
            "type":"Services"
        }
    ],
    "sg:phone":"+1   ",
    "sg:postcode":"14870",
    "sg:province":"NY",
    "wof:name":"Pta New York Congress",
    "wof:placetype":"venue"
},
  "geometry": {"coordinates":[-77.095939,42.15974],"type":"Point"}
}