{
  "type": "Feature",
  "properties": {
    "iso:country":"US",
    "sg:address":"645 Madison Ave",
    "sg:city":"New York",
    "sg:classifiers":[
        {
            "category":"Professional",
            "subcategory":"Business Services",
            "type":"Services"
        }
    ],
    "sg:phone":"+1 212 888 8108",
    "sg:postcode":"10022",
    "sg:province":"NY",
    "wof:name":"Ellen Hanson Designs",
    "wof:placetype":"venue"
},
  "geometry": {"coordinates":[-73.971132,40.76374],"type":"Point"}
}