{
  "type": "Feature",
  "properties": {
    "iso:country":"US",
    "sg:address":"5 South St",
    "sg:city":"Warwick",
    "sg:classifiers":[
        {
            "category":"Professional",
            "subcategory":"Accounting & Tax Preparation",
            "type":"Services"
        }
    ],
    "sg:phone":"+1 845 987 4000",
    "sg:postcode":"10990",
    "sg:province":"NY",
    "sg:tags":[
        "billing"
    ],
    "wof:name":"Attorney's Billing/Collection",
    "wof:placetype":"venue"
},
  "geometry": {"coordinates":[-74.35844,41.257814],"type":"Point"}
}