{
  "type": "Feature",
  "properties": {
    "iso:country":"US",
    "sg:address":"111 W Main St",
    "sg:city":"Sidney",
    "sg:phone":"+1 607 563 4059",
    "sg:postcode":"13838",
    "sg:province":"NY",
    "sg:tags":[
        "bulk",
        "gas"
    ],
    "wof:name":"Praxair Inc",
    "wof:placetype":"venue"
},
  "geometry": {"coordinates":[-75.388553,42.302612],"type":"Point"}
}