{
  "type": "Feature",
  "properties": {
    "addr:full":"2365 William St Buffalo NY 14206",
    "addr:housenumber":"2365",
    "addr:postcode":"14206",
    "addr:street":"William St",
    "iso:country":"US",
    "sg:address":"2365 William St",
    "sg:city":"Buffalo",
    "sg:classifiers":[
        {
            "category":"Food & Beverages",
            "subcategory":"Groceries & Convenience Stores",
            "type":"Retail Goods"
        }
    ],
    "sg:phone":"+1 716 892 7176",
    "sg:postcode":"14206",
    "sg:province":"NY",
    "sg:tags":[
        "beer"
    ],
    "sg:website":"http://www.convenientfoodmart.com",
    "wof:name":"Convenient Food Mart",
    "wof:placetype":"venue"
},
  "geometry": {"coordinates":[-78.78299699999999,42.884399],"type":"Point"}
}