{
  "type": "Feature",
  "properties": {
    "addr:full":"2215 Rte 112 Medford NY 11763",
    "addr:housenumber":"2215",
    "addr:postcode":"11763",
    "addr:street":"Rte 112",
    "iso:country":"US",
    "sg:address":"2215 Rte 112",
    "sg:city":"Medford",
    "sg:classifiers":[
        {
            "category":"Professional",
            "type":"Services"
        }
    ],
    "sg:phone":"+1 631 687 3601",
    "sg:postcode":"11763",
    "sg:province":"NY",
    "sg:tags":[
        "record",
        "company"
    ],
    "wof:name":"Give Back Records",
    "wof:placetype":"venue"
},
  "geometry": {"coordinates":[-73.00049799999999,40.814371],"type":"Point"}
}