{
  "type": "Feature",
  "properties": {
    "addr:full":"206 E 116th St New York NY 10029",
    "addr:housenumber":"206",
    "addr:postcode":"10029",
    "addr:street":"E 116Th St",
    "iso:country":"US",
    "sg:address":"206 E 116th St",
    "sg:city":"New York",
    "sg:classifiers":[
        {
            "category":"Personal",
            "subcategory":"Beauty Salon",
            "type":"Services"
        }
    ],
    "sg:phone":"+1 212 289 9388",
    "sg:postcode":"10029",
    "sg:province":"NY",
    "wof:name":"Ceasar's Haircutters",
    "wof:placetype":"venue"
},
  "geometry": {"coordinates":[-73.93791400000001,40.796994],"type":"Point"}
}