{
  "type": "Feature",
  "properties": {
    "addr:full":"65 Dare Rd Selden NY 11784",
    "addr:housenumber":"65",
    "addr:postcode":"11784",
    "addr:street":"Dare Rd",
    "iso:country":"US",
    "sg:address":"65 Dare Rd",
    "sg:city":"Selden",
    "sg:classifiers":[
        {
            "category":"Building & Trades",
            "subcategory":"Construction",
            "type":"Services"
        }
    ],
    "sg:phone":"+1 631 463 2614",
    "sg:postcode":"11784",
    "sg:province":"NY",
    "sg:tags":[
        "contractor"
    ],
    "wof:name":"Ray's Contracting",
    "wof:placetype":"venue"
},
  "geometry": {"coordinates":[-73.03628999999999,40.868588],"type":"Point"}
}