{
  "type": "Feature",
  "properties": {
    "addr:full":"350 Rector Pl New York NY 10280",
    "addr:housenumber":"350",
    "addr:postcode":"10280",
    "addr:street":"Rector Pl",
    "iso:country":"US",
    "sg:address":"350 Rector Pl",
    "sg:city":"New York",
    "sg:classifiers":[
        {
            "category":"Retail",
            "subcategory":"Auto Repair",
            "type":"Services"
        }
    ],
    "sg:phone":"+1 646 237 1448",
    "sg:postcode":"10280",
    "sg:province":"NY",
    "sg:tags":[
        "repairing",
        "automobile"
    ],
    "wof:name":"American Auto Repair",
    "wof:placetype":"venue"
},
  "geometry": {"coordinates":[-74.016998,40.709099],"type":"Point"}
}