{
  "type": "Feature",
  "properties": {
    "addr:full":"1623 Flatbush Ave Brooklyn NY 11210",
    "addr:housenumber":"1623",
    "addr:postcode":"11210",
    "addr:street":"Flatbush Ave",
    "iso:country":"US",
    "sg:address":"1623 Flatbush Ave",
    "sg:city":"Brooklyn",
    "sg:classifiers":[
        {
            "category":"Restaurant",
            "type":"Food & Drink"
        }
    ],
    "sg:phone":"+1   ",
    "sg:postcode":"11210",
    "sg:province":"NY",
    "sg:tags":[
        "eating"
    ],
    "wof:name":"Sizzler",
    "wof:placetype":"venue"
},
  "geometry": {"coordinates":[-73.94480799999999,40.630127],"type":"Point"}
}