{
  "type": "Feature",
  "properties": {
    "addr:full":"41 Main St Port Washington NY 11050",
    "addr:housenumber":"41",
    "addr:postcode":"11050",
    "addr:street":"Main St",
    "iso:country":"US",
    "sg:address":"41 Main St",
    "sg:city":"Port Washington",
    "sg:classifiers":[
        {
            "category":"Shopping",
            "subcategory":"Gifts & Souvenirs",
            "type":"Retail Goods"
        }
    ],
    "sg:phone":"+1   ",
    "sg:postcode":"11050",
    "sg:province":"NY",
    "wof:name":"Peppermint Stick The",
    "wof:placetype":"venue"
},
  "geometry": {"coordinates":[-73.686488,40.830896],"type":"Point"}
}