{
  "type": "Feature",
  "properties": {
    "addr:full":"3350 Gomer St Yorktown Heights NY 10598",
    "addr:postcode":"3350;10598",
    "addr:street":"Gomer St",
    "iso:country":"US",
    "sg:address":"3350 Gomer St",
    "sg:city":"Yorktown Heights",
    "sg:classifiers":[
        {
            "category":"Home & Garden",
            "subcategory":"Building Materials",
            "type":"Retail Goods"
        }
    ],
    "sg:phone":"+1 914 455 2600",
    "sg:postcode":"10598",
    "sg:province":"NY",
    "sg:tags":[
        "door"
    ],
    "wof:name":"Eagle Lock & Door",
    "wof:placetype":"venue"
},
  "geometry": {"coordinates":[-73.791276,41.320632],"type":"Point"}
}