{
  "type": "Feature",
  "properties": {
    "addr:full":"8 Woodcock Ln Remsenburg NY 11960",
    "addr:housenumber":"8",
    "addr:postcode":"11960",
    "addr:street":"Woodcock Ln",
    "iso:country":"US",
    "sg:address":"8 Woodcock Ln",
    "sg:city":"Remsenburg",
    "sg:classifiers":[
        {
            "category":"Travel",
            "subcategory":"Travel Agent",
            "type":"Entertainment"
        }
    ],
    "sg:phone":"+1 631 325 8590",
    "sg:postcode":"11960",
    "sg:province":"NY",
    "sg:tags":[
        "agency",
        "bureau"
    ],
    "wof:name":"World Discovery Travel",
    "wof:placetype":"venue"
},
  "geometry": {"coordinates":[-72.692807,40.804672],"type":"Point"}
}