{
  "type": "Feature",
  "properties": {
    "addr:full":"92 W Chippewa St Buffalo NY 14202",
    "addr:housenumber":"92",
    "addr:postcode":"14202",
    "addr:street":"W Chippewa St",
    "iso:country":"US",
    "sg:address":"92 W Chippewa St",
    "sg:city":"Buffalo",
    "sg:classifiers":[
        {
            "category":"Restaurant",
            "type":"Food & Drink"
        }
    ],
    "sg:phone":"+1 716 854 6666",
    "sg:postcode":"14202",
    "sg:province":"NY",
    "sg:website":"www.jimssteakout.com",
    "wof:name":"Jim's Steak House",
    "wof:placetype":"venue"
},
  "geometry": {"coordinates":[-78.87629699999999,42.890701],"type":"Point"}
}