{
  "type": "Feature",
  "properties": {
    "iso:country":"US",
    "sg:address":"672 Nancy Pl",
    "sg:city":"Valley Stream",
    "sg:classifiers":[
        {
            "category":"Manufacturing",
            "subcategory":"Metals",
            "type":"Manufacturing & Wholesale Goods"
        }
    ],
    "sg:phone":"+1   ",
    "sg:postcode":"11581",
    "sg:province":"NY",
    "sg:tags":[
        "steel",
        "converter",
        "roll"
    ],
    "wof:name":"J & S Steel Corp",
    "wof:placetype":"venue"
},
  "geometry": {"coordinates":[-73.73098400000001,40.647082],"type":"Point"}
}