{
  "type": "Feature",
  "properties": {
    "iso:country":"US",
    "sg:address":"499 Park Ave",
    "sg:city":"New York",
    "sg:classifiers":[
        {
            "category":"Banks & Credit Unions",
            "subcategory":"Investment Brokerage",
            "type":"Services"
        },
        {
            "category":"Professional",
            "subcategory":"Management & Consulting",
            "type":"Services"
        }
    ],
    "sg:phone":"+1 212 688 4010",
    "sg:postcode":"10022",
    "sg:province":"NY",
    "sg:tags":[
        "consultant",
        "financing",
        "financial"
    ],
    "wof:name":"First Spring Corp",
    "wof:placetype":"venue"
},
  "geometry": {"coordinates":[-73.969337,40.763546],"type":"Point"}
}