{
  "type": "Feature",
  "properties": {
    "addr:full":"328 Nassau Blvd S Garden City NY 11530",
    "addr:housenumber":"328",
    "addr:postcode":"11530",
    "addr:street":"Nassau Blvd S",
    "iso:country":"US",
    "sg:address":"328 Nassau Blvd S",
    "sg:city":"Garden City",
    "sg:classifiers":[
        {
            "category":"Retail",
            "subcategory":"Laundry & Dry Cleaning",
            "type":"Services"
        }
    ],
    "sg:phone":"+1 516 486 2442",
    "sg:postcode":"11530",
    "sg:province":"NY",
    "sg:tags":[
        "cleaner"
    ],
    "sg:website":"www.adelphicleaners.com",
    "wof:name":"Adelphi Drive-In Cleaners",
    "wof:placetype":"venue"
},
  "geometry": {"coordinates":[-73.660797,40.715599],"type":"Point"}
}