{
  "type": "Feature",
  "properties": {
    "addr:full":"44 Clinton St Rensselaer NY 12144",
    "addr:housenumber":"44",
    "addr:postcode":"12144",
    "addr:street":"Clinton St",
    "iso:country":"US",
    "sg:address":"44 Clinton St",
    "sg:city":"Rensselaer",
    "sg:classifiers":[
        {
            "category":"Real Estate",
            "subcategory":"Real Estate Agent",
            "type":"Services"
        }
    ],
    "sg:phone":"+1 518 434 9999",
    "sg:postcode":"12144",
    "sg:province":"NY",
    "wof:name":"Empire State Realty-The Capitl",
    "wof:placetype":"venue"
},
  "geometry": {"coordinates":[-73.733172,42.619447],"type":"Point"}
}