{
  "type": "Feature",
  "properties": {
    "addr:full":"11 E 47th St New York NY 10017",
    "addr:housenumber":"11",
    "addr:postcode":"10017",
    "addr:street":"E 47Th St",
    "iso:country":"US",
    "sg:address":"11 E 47th St",
    "sg:city":"New York",
    "sg:classifiers":[
        {
            "category":"Professional",
            "subcategory":"Management & Consulting",
            "type":"Services"
        }
    ],
    "sg:phone":"+1 212 888 4700",
    "sg:postcode":"10017",
    "sg:province":"NY",
    "sg:tags":[
        "marketing",
        "age",
        "full",
        "advertising",
        "communications"
    ],
    "wof:name":"P K Network Communications",
    "wof:placetype":"venue"
},
  "geometry": {"coordinates":[-73.97743,40.756326],"type":"Point"}
}