{
  "type": "Feature",
  "properties": {
    "iso:country":"US",
    "sg:address":"47 N Main St",
    "sg:city":"Prattsburgh",
    "sg:classifiers":[
        {
            "category":"Organizations",
            "subcategory":"Religious Organization",
            "type":"Services"
        }
    ],
    "sg:phone":"+1 607 522 6101",
    "sg:postcode":"14873",
    "sg:province":"NY",
    "sg:tags":[
        "church"
    ],
    "wof:name":"St Patrick's Church",
    "wof:placetype":"venue"
},
  "geometry": {"coordinates":[-77.285929,42.532223],"type":"Point"}
}