{
  "type": "Feature",
  "properties": {
    "addr:full":"656 Kreag Rd Pittsford NY 14534",
    "addr:housenumber":"656",
    "addr:postcode":"14534",
    "addr:street":"Kreag Rd",
    "iso:country":"US",
    "sg:address":"656 Kreag Rd",
    "sg:city":"Pittsford",
    "sg:classifiers":[
        {
            "category":"Insurance",
            "subcategory":"Insurance Agent",
            "type":"Services"
        }
    ],
    "sg:phone":"+1 585 586 3322",
    "sg:postcode":"14534",
    "sg:province":"NY",
    "wof:name":"Northast Investors Title Insur",
    "wof:placetype":"venue"
},
  "geometry": {"coordinates":[-77.472689,43.061613],"type":"Point"}
}