{
  "type": "Feature",
  "properties": {
    "addr:full":"395 W John St Hicksville NY 11801",
    "addr:housenumber":"395",
    "addr:postcode":"11801",
    "addr:street":"W John St",
    "iso:country":"US",
    "sg:address":"395 W John St",
    "sg:city":"Hicksville",
    "sg:classifiers":[
        {
            "category":"Personal",
            "subcategory":"Beauty Salon",
            "type":"Services"
        }
    ],
    "sg:phone":"+1 516 932 7376",
    "sg:postcode":"11801",
    "sg:province":"NY",
    "wof:name":"Cutter's Salon",
    "wof:placetype":"venue"
},
  "geometry": {"coordinates":[-73.542342,40.766246],"type":"Point"}
}