{
  "type": "Feature",
  "properties": {
    "addr:full":"24 E 17th St New York NY 10003",
    "addr:housenumber":"24",
    "addr:postcode":"10003",
    "addr:street":"E 17Th St",
    "iso:country":"US",
    "sg:address":"24 E 17th St",
    "sg:city":"New York",
    "sg:classifiers":[
        {
            "category":"Building & Trades",
            "subcategory":"Locksmith",
            "type":"Services"
        }
    ],
    "sg:phone":"+1 917 237 7996",
    "sg:postcode":"10003",
    "sg:province":"NY",
    "sg:tags":[
        "key"
    ],
    "wof:name":"17st A 24 Hour A Locksmith Emergency",
    "wof:placetype":"venue"
},
  "geometry": {"coordinates":[-73.99050099999999,40.737],"type":"Point"}
}