{
  "type": "Feature",
  "properties": {
    "addr:full":"77 Park Ave New York NY 10016",
    "addr:housenumber":"77",
    "addr:postcode":"10016",
    "addr:street":"Park Ave",
    "iso:country":"US",
    "sg:address":"77 Park Ave",
    "sg:city":"New York",
    "sg:classifiers":[
        {
            "category":"Health Services",
            "subcategory":"Health Practitioner",
            "type":"Services"
        }
    ],
    "sg:phone":"+1 212 213 4449",
    "sg:postcode":"10016",
    "sg:province":"NY",
    "sg:tags":[
        "psychologist"
    ],
    "wof:name":"Alon Gratch PHD",
    "wof:placetype":"venue"
},
  "geometry": {"coordinates":[-73.97923299999999,40.749743],"type":"Point"}
}