{
  "type": "Feature",
  "properties": {
    "addr:full":"829 State Hwy 131 Massena NY 13662",
    "addr:housenumber":"829",
    "addr:postcode":"13662",
    "addr:street":"State Hwy 131",
    "iso:country":"US",
    "sg:address":"829 State Hwy 131",
    "sg:city":"Massena",
    "sg:classifiers":[
        {
            "category":"Restaurant",
            "type":"Food & Drink"
        }
    ],
    "sg:phone":"+1 315 769 6910",
    "sg:postcode":"13662",
    "sg:province":"NY",
    "sg:website":"www.villageinnrestaurants.com",
    "wof:name":"Village Inn",
    "wof:placetype":"venue"
},
  "geometry": {"coordinates":[-74.97846800000001,44.951172],"type":"Point"}
}