{
  "type": "Feature",
  "properties": {
    "addr:full":"300 Delaware Ave Ste 101 Buffalo NY 14202",
    "addr:housenumber":"300",
    "addr:postcode":"14202",
    "addr:street":"Delaware Ave Ste 101",
    "iso:country":"US",
    "sg:address":"300 Delaware Ave Ste 101",
    "sg:city":"Buffalo",
    "sg:classifiers":[
        {
            "category":"Organizations",
            "subcategory":"Non-profit Organization",
            "type":"Services"
        }
    ],
    "sg:phone":"+1 716 835 1323",
    "sg:postcode":"14202",
    "sg:province":"NY",
    "sg:tags":[
        "service/non-profit",
        "community"
    ],
    "wof:name":"National Kidney Foundation",
    "wof:placetype":"venue"
},
  "geometry": {"coordinates":[-78.876406,42.892539],"type":"Point"}
}