{
  "type": "Feature",
  "properties": {
    "iso:country":"US",
    "sg:address":"335 Yaphank Ave",
    "sg:city":"Yaphank",
    "sg:classifiers":[
        {
            "category":"Building & Trades",
            "subcategory":"Construction",
            "type":"Services"
        },
        {
            "category":"Government",
            "subcategory":"Office",
            "type":"Public Place"
        }
    ],
    "sg:phone":"+1 631 852 4287",
    "sg:postcode":"11980",
    "sg:province":"NY",
    "sg:tags":[
        "management",
        "grading",
        "contractor"
    ],
    "wof:name":"Suffolk County Dept Pub Works",
    "wof:placetype":"venue"
},
  "geometry": {"coordinates":[-72.91609699999999,40.819116],"type":"Point"}
}