{
  "type": "Feature",
  "properties": {
    "iso:country":"US",
    "sg:address":"277 Broadway",
    "sg:city":"New York",
    "sg:classifiers":[
        {
            "category":"Professional",
            "subcategory":"Accounting & Tax Preparation",
            "type":"Services"
        }
    ],
    "sg:phone":"+1 212 962 5999",
    "sg:postcode":"10007",
    "sg:province":"NY",
    "wof:name":"Feder & Gopin PC Certified PBL",
    "wof:placetype":"venue"
},
  "geometry": {"coordinates":[-74.00599800000001,40.714645],"type":"Point"}
}