{
  "type": "Feature",
  "properties": {
    "iso:country":"US",
    "sg:address":"3905 Greentree Dr",
    "sg:city":"Oceanside",
    "sg:classifiers":[
        {
            "category":"Professional",
            "subcategory":"Accounting & Tax Preparation",
            "type":"Services"
        }
    ],
    "sg:phone":"+1   ",
    "sg:postcode":"11572",
    "sg:province":"NY",
    "wof:name":"Howard B Pearlman PC",
    "wof:placetype":"venue"
},
  "geometry": {"coordinates":[-73.627146,40.617309],"type":"Point"}
}