{
  "type": "Feature",
  "properties": {
    "iso:country":"US",
    "sg:address":"697 Troy Schenectady Rd",
    "sg:city":"Latham",
    "sg:classifiers":[
        {
            "category":"Ice Cream",
            "type":"Food & Drink"
        }
    ],
    "sg:menulink":"http://www.allmenus.com/ny/colonie/98810-friendlys-restaurant/menu/",
    "sg:phone":"+1 518 785 0909",
    "sg:postcode":"12110",
    "sg:province":"NY",
    "sg:tags":[
        "burger",
        "american"
    ],
    "wof:name":"Friendly's Restaurant",
    "wof:placetype":"venue"
},
  "geometry": {"coordinates":[-73.77492100000001,42.755854],"type":"Point"}
}