{
  "type": "Feature",
  "properties": {
    "addr:full":"1727 Amsterdam Avenue New York NY 10031",
    "addr:housenumber":"1727",
    "addr:postcode":"10031",
    "addr:street":"Amsterdam Avenue",
    "iso:country":"US",
    "sg:address":"1727 Amsterdam Avenue",
    "sg:city":"New York",
    "sg:classifiers":[
        {
            "category":"Health Services",
            "subcategory":"Doctor",
            "type":"Services"
        }
    ],
    "sg:phone":"+1 212 862 0054",
    "sg:postcode":"10031",
    "sg:province":"NY",
    "wof:name":"Heritage Health Care",
    "wof:placetype":"venue"
},
  "geometry": {"coordinates":[-73.94752699999999,40.825561],"type":"Point"}
}