{
  "type": "Feature",
  "properties": {
    "addr:full":"9293 Bonta Bridge Rd Jordan NY 13080",
    "addr:housenumber":"9293",
    "addr:postcode":"13080",
    "addr:street":"Bonta Bridge Rd",
    "iso:country":"US",
    "sg:address":"9293 Bonta Bridge Rd",
    "sg:city":"Jordan",
    "sg:classifiers":[
        {
            "category":"Freight",
            "type":"Transportation"
        }
    ],
    "sg:phone":"+1 315 689 9752",
    "sg:postcode":"13080",
    "sg:province":"NY",
    "sg:tags":[
        "trucking"
    ],
    "wof:name":"We Care Environmental LLC",
    "wof:placetype":"venue"
},
  "geometry": {"coordinates":[-76.51230700000001,43.062435],"type":"Point"}
}