{
  "type": "Feature",
  "properties": {
    "addr:full":"13 Waverly Ave Brooklyn NY 11205",
    "addr:housenumber":"13",
    "addr:postcode":"11205",
    "addr:street":"Waverly Ave",
    "iso:country":"US",
    "sg:address":"13 Waverly Ave",
    "sg:city":"Brooklyn",
    "sg:classifiers":[
        {
            "category":"Home & Garden",
            "subcategory":"Furniture",
            "type":"Retail Goods"
        }
    ],
    "sg:phone":"+1 718 237 2545",
    "sg:postcode":"11205",
    "sg:province":"NY",
    "sg:tags":[
        "store"
    ],
    "wof:name":"Loeffler Furniture",
    "wof:placetype":"venue"
},
  "geometry": {"coordinates":[-73.968498,40.6973],"type":"Point"}
}