{
  "type": "Feature",
  "properties": {
    "addr:full":"521 Beach 20th St Far Rockaway NY 11691",
    "addr:housenumber":"521",
    "addr:postcode":"11691",
    "addr:street":"Beach 20Th St",
    "iso:country":"US",
    "sg:address":"521 Beach 20th St",
    "sg:city":"Far Rockaway",
    "sg:classifiers":[
        {
            "category":"Health Services",
            "subcategory":"Hospital",
            "type":"Services"
        }
    ],
    "sg:phone":"+1 718 869 8822",
    "sg:postcode":"11691",
    "sg:province":"NY",
    "wof:name":"St John's Episcopal Hospital",
    "wof:placetype":"venue"
},
  "geometry": {"coordinates":[-73.75417400000001,40.599722],"type":"Point"}
}