{
  "type": "Feature",
  "properties": {
    "iso:country":"US",
    "sg:address":"49 Mc Cue Ln",
    "sg:city":"Babylon",
    "sg:classifiers":[
        {
            "category":"Building & Trades",
            "subcategory":"Construction",
            "type":"Services"
        }
    ],
    "sg:phone":"+1 631 587 6963",
    "sg:postcode":"11702",
    "sg:province":"NY",
    "sg:tags":[
        "contractor"
    ],
    "wof:name":"B & B Tile",
    "wof:placetype":"venue"
},
  "geometry": {"coordinates":[-73.33785399999999,40.6884],"type":"Point"}
}