{
  "type": "Feature",
  "properties": {
    "iso:country":"US",
    "sg:address":"1930 Veterans Hwy",
    "sg:city":"Islandia",
    "sg:classifiers":[
        {
            "category":"Arena",
            "subcategory":"Sports Club",
            "type":"Entertainment"
        }
    ],
    "sg:phone":"+1 631 650 9053",
    "sg:postcode":"11749",
    "sg:province":"NY",
    "sg:tags":[
        "martial art"
    ],
    "wof:name":"Martial Arts",
    "wof:placetype":"venue"
},
  "geometry": {"coordinates":[-73.171526,40.796439],"type":"Point"}
}