{
  "type": "Feature",
  "properties": {
    "iso:country":"US",
    "sg:address":"67 Broad St",
    "sg:city":"New York",
    "sg:classifiers":[
        {
            "category":"Utilities",
            "subcategory":"Telephone",
            "type":"Services"
        }
    ],
    "sg:phone":"+1 212 797 9191",
    "sg:postcode":"10004",
    "sg:province":"NY",
    "sg:tags":[
        "company"
    ],
    "wof:name":"National Telecommunication Svc",
    "wof:placetype":"venue"
},
  "geometry": {"coordinates":[-74.01156899999999,40.704249],"type":"Point"}
}