{
  "type": "Feature",
  "properties": {
    "addr:full":"4214 3rd Avenue Brooklyn NY 11232",
    "addr:housenumber":"4214",
    "addr:postcode":"11232",
    "addr:street":"3Rd Avenue",
    "iso:country":"US",
    "sg:address":"4214 3rd Avenue",
    "sg:city":"Brooklyn",
    "sg:classifiers":[
        {
            "category":"Building & Trades",
            "subcategory":"Construction",
            "type":"Services"
        }
    ],
    "sg:phone":"+1 718 832 9400",
    "sg:postcode":"11232",
    "sg:province":"NY",
    "sg:tags":[
        "contractor"
    ],
    "wof:name":"Di Salvo Contracting Company",
    "wof:placetype":"venue"
},
  "geometry": {"coordinates":[-74.01061199999999,40.651926],"type":"Point"}
}