{
  "type": "Feature",
  "properties": {
    "addr:full":"370 Motor Pkwy Hauppauge NY 11788",
    "addr:housenumber":"370",
    "addr:postcode":"11788",
    "addr:street":"Motor Pkwy",
    "iso:country":"US",
    "sg:address":"370 Motor Pkwy",
    "sg:city":"Hauppauge",
    "sg:classifiers":[
        {
            "category":"Building & Trades",
            "subcategory":"Electrical",
            "type":"Services"
        }
    ],
    "sg:phone":"+1 631 951 6100",
    "sg:postcode":"11788",
    "sg:province":"NY",
    "sg:tags":[
        "electric",
        "contractor"
    ],
    "wof:name":"Internationl Brotherhood Elec",
    "wof:placetype":"venue"
},
  "geometry": {"coordinates":[-73.240981,40.807628],"type":"Point"}
}