{
  "type": "Feature",
  "properties": {
    "iso:country":"US",
    "sg:address":"240 Garth Rd",
    "sg:city":"Scarsdale",
    "sg:classifiers":[
        {
            "category":"Building & Trades",
            "subcategory":"Construction",
            "type":"Services"
        }
    ],
    "sg:phone":"+1 914 725 0006",
    "sg:postcode":"10583",
    "sg:province":"NY",
    "sg:tags":[
        "hanging",
        "contractor"
    ],
    "wof:name":"R W Painting",
    "wof:placetype":"venue"
},
  "geometry": {"coordinates":[-73.81206299999999,40.982321],"type":"Point"}
}