{
  "type": "Feature",
  "properties": {
    "iso:country":"US",
    "sg:address":"4742 Morgan Pkwy",
    "sg:city":"Hamburg",
    "sg:classifiers":[
        {
            "category":"Manufacturing",
            "subcategory":"Building Materials",
            "type":"Manufacturing & Wholesale Goods"
        }
    ],
    "sg:phone":"+1   ",
    "sg:postcode":"14075",
    "sg:province":"NY",
    "sg:tags":[
        "equipment",
        "industrial",
        "mfg"
    ],
    "wof:name":"Superior Overhead Door",
    "wof:placetype":"venue"
},
  "geometry": {"coordinates":[-78.878283,42.757164],"type":"Point"}
}