{
  "type": "Feature",
  "properties": {
    "iso:country":"US",
    "sg:address":"3 Gillen Ter",
    "sg:city":"Gloversville",
    "sg:classifiers":[
        {
            "category":"Building & Trades",
            "subcategory":"Construction",
            "type":"Services"
        }
    ],
    "sg:phone":"+1 518 773 4232",
    "sg:postcode":"12078",
    "sg:province":"NY",
    "sg:tags":[
        "roofing",
        "contractor"
    ],
    "wof:name":"T & J Bldg & Roofing Mntnc",
    "wof:placetype":"venue"
},
  "geometry": {"coordinates":[-74.333697,43.068546],"type":"Point"}
}