{
  "type": "Feature",
  "properties": {
    "addr:full":"255 Conklin Ave Binghamton NY 13903",
    "addr:housenumber":"255",
    "addr:postcode":"13903",
    "addr:street":"Conklin Ave",
    "iso:country":"US",
    "sg:address":"255 Conklin Ave",
    "sg:city":"Binghamton",
    "sg:classifiers":[
        {
            "category":"Autos & Motor Vehicles",
            "subcategory":"Automobile Sales",
            "type":"Retail Goods"
        }
    ],
    "sg:phone":"+1 607 722 2737",
    "sg:postcode":"13903",
    "sg:province":"NY",
    "sg:tags":[
        "car",
        "dealer"
    ],
    "wof:name":"1 Preferred Used Cars",
    "wof:placetype":"venue"
},
  "geometry": {"coordinates":[-75.89333600000001,42.095268],"type":"Point"}
}