{
  "type": "Feature",
  "properties": {
    "iso:country":"US",
    "sg:address":"67 Becker Rd",
    "sg:city":"Valley Falls",
    "sg:classifiers":[
        {
            "category":"Building & Trades",
            "subcategory":"Landscaping Services",
            "type":"Services"
        }
    ],
    "sg:phone":"+1 518 692 9074",
    "sg:postcode":"12834",
    "sg:province":"NY",
    "wof:name":"Herbert E Broestler",
    "wof:placetype":"venue"
},
  "geometry": {"coordinates":[-73.535676,42.991529],"type":"Point"}
}