{
  "type": "Feature",
  "properties": {
    "addr:full":"100 Bay Ridge Ave Brooklyn NY 11220",
    "addr:housenumber":"100",
    "addr:postcode":"11220",
    "addr:street":"Bay Ridge Ave",
    "iso:country":"US",
    "sg:address":"100 Bay Ridge Ave",
    "sg:city":"Brooklyn",
    "sg:classifiers":[
        {
            "category":"Real Estate",
            "subcategory":"Real Estate Agent",
            "type":"Services"
        }
    ],
    "sg:phone":"+1 718 836 3736",
    "sg:postcode":"11220",
    "sg:province":"NY",
    "sg:tags":[
        "management"
    ],
    "wof:name":"Hal Greene Management",
    "wof:placetype":"venue"
},
  "geometry": {"coordinates":[-74.03303699999999,40.637918],"type":"Point"}
}