{
  "type": "Feature",
  "properties": {
    "iso:country":"US",
    "sg:address":"402 85th St",
    "sg:city":"Brooklyn",
    "sg:classifiers":[
        {
            "category":"Health Services",
            "subcategory":"Doctor",
            "type":"Services"
        }
    ],
    "sg:phone":"+1 718 748 1624",
    "sg:postcode":"11209",
    "sg:province":"NY",
    "wof:name":"Joel Sokol DMD",
    "wof:placetype":"venue"
},
  "geometry": {"coordinates":[-74.025745,40.622111],"type":"Point"}
}