{
  "type": "Feature",
  "properties": {
    "iso:country":"US",
    "sg:address":"1619 Boston Rd",
    "sg:city":"Bronx",
    "sg:classifiers":[
        {
            "category":"Education",
            "subcategory":"School",
            "type":"Public Place"
        }
    ],
    "sg:phone":"+1 718 589 8200",
    "sg:postcode":"10460",
    "sg:province":"NY",
    "wof:name":"H Ridder Junior High School",
    "wof:placetype":"venue"
},
  "geometry": {"coordinates":[-73.891008,40.835862],"type":"Point"}
}