{
  "type": "Feature",
  "properties": {
    "addr:full":"781 Fall Creek Rd Freeville NY 13068",
    "addr:housenumber":"781",
    "addr:postcode":"13068",
    "addr:street":"Fall Creek Rd",
    "iso:country":"US",
    "sg:address":"781 Fall Creek Rd",
    "sg:city":"Freeville",
    "sg:classifiers":[
        {
            "category":"Restaurant",
            "type":"Food & Drink"
        }
    ],
    "sg:phone":"+1 607 838 0101",
    "sg:postcode":"13068",
    "sg:province":"NY",
    "wof:name":"Dandy Mini Mart",
    "wof:placetype":"venue"
},
  "geometry": {"coordinates":[-76.29413099999999,42.549129],"type":"Point"}
}