{
  "type": "Feature",
  "properties": {
    "iso:country":"US",
    "sg:address":"170 Myrtle Blvd",
    "sg:city":"Larchmont",
    "sg:classifiers":[
        {
            "category":"Professional",
            "subcategory":"Lawyer & Legal Services",
            "type":"Services"
        }
    ],
    "sg:phone":"+1   ",
    "sg:postcode":"10538",
    "sg:province":"NY",
    "wof:name":"Joshua D Siegel Attorney",
    "wof:placetype":"venue"
},
  "geometry": {"coordinates":[-73.762396,40.932439],"type":"Point"}
}