{
  "type": "Feature",
  "properties": {
    "addr:full":"228 Park Ave S New York NY 10003",
    "addr:housenumber":"228",
    "addr:postcode":"10003",
    "addr:street":"Park Ave S",
    "iso:country":"US",
    "sg:address":"228 Park Ave S",
    "sg:city":"New York",
    "sg:classifiers":[
        {
            "category":"Communications",
            "subcategory":"Newspaper",
            "type":"Services"
        },
        {
            "category":"Professional",
            "subcategory":"Art Services",
            "type":"Services"
        },
        {
            "category":"Communications",
            "type":"Services"
        }
    ],
    "sg:phone":"+1 212 518 1726",
    "sg:postcode":"10003",
    "sg:province":"NY",
    "sg:tags":[
        "web",
        "graphic",
        "design",
        "advertising"
    ],
    "sg:website":"bigtopdesigns.com",
    "wof:name":"Big Top Designs",
    "wof:placetype":"venue"
},
  "geometry": {"coordinates":[-73.98886400000001,40.737811],"type":"Point"}
}