{
  "type": "Feature",
  "properties": {
    "iso:country":"US",
    "sg:address":"821 Franklin Ave Ste 303",
    "sg:city":"Garden City",
    "sg:classifiers":[
        {
            "category":"Real Estate",
            "subcategory":"Real Estate Services",
            "type":"Services"
        }
    ],
    "sg:phone":"+1 516 746 1118",
    "sg:postcode":"11530",
    "sg:province":"NY",
    "sg:tags":[
        "home",
        "inspector"
    ],
    "wof:name":"Artisan Services Inc",
    "wof:placetype":"venue"
},
  "geometry": {"coordinates":[-73.634804,40.727402],"type":"Point"}
}