{
  "type": "Feature",
  "properties": {
    "iso:country":"US",
    "sg:address":"307 Bradford Pkwy",
    "sg:city":"Syracuse",
    "sg:classifiers":[
        {
            "category":"Shopping",
            "subcategory":"Computers & Home Electronics",
            "type":"Retail Goods"
        }
    ],
    "sg:phone":"+1 315 446 0614",
    "sg:postcode":"13224",
    "sg:province":"NY",
    "sg:tags":[
        "software"
    ],
    "wof:name":"Somerset Publishing Co Inc",
    "wof:placetype":"venue"
},
  "geometry": {"coordinates":[-76.102169,43.036619],"type":"Point"}
}