{
  "type": "Feature",
  "properties": {
    "iso:country":"US",
    "sg:address":"28 Meadow Ave",
    "sg:city":"Bronxville",
    "sg:classifiers":[
        {
            "category":"Organizations",
            "subcategory":"Religious Organization",
            "type":"Services"
        }
    ],
    "sg:phone":"+1   ",
    "sg:postcode":"10708",
    "sg:province":"NY",
    "wof:name":"Religious Education Center",
    "wof:placetype":"venue"
},
  "geometry": {"coordinates":[-73.834008,40.937694],"type":"Point"}
}