{
  "type": "Feature",
  "properties": {
    "addr:full":"3663 Rte 112 Coram NY 11727",
    "addr:housenumber":"3663",
    "addr:postcode":"11727",
    "addr:street":"Rte 112",
    "iso:country":"US",
    "sg:address":"3663 Rte 112",
    "sg:city":"Coram",
    "sg:classifiers":[
        {
            "category":"Professional",
            "subcategory":"Accounting & Tax Preparation",
            "type":"Services"
        }
    ],
    "sg:phone":"+1 631 451 2483",
    "sg:postcode":"11727",
    "sg:province":"NY",
    "sg:tags":[
        "return",
        "filing"
    ],
    "wof:name":"Jackson Hewitt Tax Svc",
    "wof:placetype":"venue"
},
  "geometry": {"coordinates":[-72.999,40.863513],"type":"Point"}
}