{
  "type": "Feature",
  "properties": {
    "iso:country":"US",
    "sg:address":"32 Willett Ave",
    "sg:city":"Sayville",
    "sg:classifiers":[
        {
            "category":"Building & Trades",
            "subcategory":"Construction",
            "type":"Services"
        }
    ],
    "sg:phone":"+1 631 563 2996",
    "sg:postcode":"11782",
    "sg:province":"NY",
    "sg:tags":[
        "house"
    ],
    "wof:name":"Jeff Otto Home Improvement",
    "wof:placetype":"venue"
},
  "geometry": {"coordinates":[-73.08941900000001,40.742604],"type":"Point"}
}