{
  "type": "Feature",
  "properties": {
    "addr:full":"364 Prospect Pl Apt 2B Brooklyn NY 11238",
    "addr:housenumber":"364",
    "addr:postcode":"11238",
    "addr:street":"Prospect Pl Apt",
    "iso:country":"US",
    "sg:address":"364 Prospect Pl Apt 2B",
    "sg:city":"Brooklyn",
    "sg:classifiers":[
        {
            "category":"Personal",
            "type":"Services"
        }
    ],
    "sg:phone":"+1 718 230 0672",
    "sg:postcode":"11238",
    "sg:province":"NY",
    "sg:tags":[
        "consultant",
        "planning",
        "wedding"
    ],
    "wof:name":"Emerald City N New York",
    "wof:placetype":"venue"
},
  "geometry": {"coordinates":[-73.964518,40.676738],"type":"Point"}
}