{
  "type": "Feature",
  "properties": {
    "iso:country":"US",
    "sg:address":"38 S Niagara St",
    "sg:city":"Lockport",
    "sg:classifiers":[
        {
            "category":"Taxi",
            "type":"Transportation"
        }
    ],
    "sg:phone":"+1   ",
    "sg:postcode":"14094",
    "sg:province":"NY",
    "sg:tags":[
        "taxicab"
    ],
    "wof:name":"Discount Cab Inc",
    "wof:placetype":"venue"
},
  "geometry": {"coordinates":[-78.71068099999999,43.169653],"type":"Point"}
}