{
  "type": "Feature",
  "properties": {
    "addr:full":"276 73rd St Brooklyn NY 11209",
    "addr:housenumber":"276",
    "addr:postcode":"11209",
    "addr:street":"73Rd St",
    "iso:country":"US",
    "sg:address":"276 73rd St",
    "sg:city":"Brooklyn",
    "sg:classifiers":[
        {
            "category":"Cinema",
            "subcategory":"Movie Rental",
            "type":"Entertainment"
        }
    ],
    "sg:phone":"+1 718 836 4708",
    "sg:postcode":"11209",
    "sg:province":"NY",
    "sg:tags":[
        "leasing",
        "video",
        "disc",
        "tape"
    ],
    "wof:name":"Shutt Video",
    "wof:placetype":"venue"
},
  "geometry": {"coordinates":[-74.028831,40.633259],"type":"Point"}
}