{
  "type": "Feature",
  "properties": {
    "iso:country":"US",
    "sg:address":"2624 Atlantic Avenue",
    "sg:city":"Brooklyn",
    "sg:classifiers":[
        {
            "category":"Autos & Motor Vehicles",
            "subcategory":"Auto Supplies",
            "type":"Retail Goods"
        }
    ],
    "sg:phone":"+1 718 498 1233",
    "sg:postcode":"11207",
    "sg:province":"NY",
    "sg:tags":[
        "tire"
    ],
    "wof:name":"Funsa Tire Shop",
    "wof:placetype":"venue"
},
  "geometry": {"coordinates":[-73.895099,40.67294],"type":"Point"}
}