{
  "type": "Feature",
  "properties": {
    "iso:country":"US",
    "sg:address":"169 Franklin St",
    "sg:city":"Franklin Square",
    "sg:classifiers":[
        {
            "category":"Wholesale",
            "subcategory":"Durable Goods & Equipment",
            "type":"Manufacturing & Wholesale Goods"
        }
    ],
    "sg:phone":"+1 516 616 4650",
    "sg:postcode":"11010",
    "sg:province":"NY",
    "sg:tags":[
        "representative",
        "manufacturer"
    ],
    "wof:name":"Metro-Rep",
    "wof:placetype":"venue"
},
  "geometry": {"coordinates":[-73.67420799999999,40.710442],"type":"Point"}
}