{
  "type": "Feature",
  "properties": {
    "addr:full":"4 Glendale Rd Greenwood Lake NY 10925",
    "addr:housenumber":"4",
    "addr:postcode":"10925",
    "addr:street":"Glendale Rd",
    "iso:country":"US",
    "sg:address":"4 Glendale Rd",
    "sg:city":"Greenwood Lake",
    "sg:classifiers":[
        {
            "category":"Building & Trades",
            "subcategory":"Landscaping Services",
            "type":"Services"
        }
    ],
    "sg:phone":"+1 845 477 2789",
    "sg:postcode":"10925",
    "sg:province":"NY",
    "sg:tags":[
        "house",
        "construction",
        "landscape"
    ],
    "wof:name":"Brice Construction & Ldscpg",
    "wof:placetype":"venue"
},
  "geometry": {"coordinates":[-74.282849,41.21962],"type":"Point"}
}