{
  "type": "Feature",
  "properties": {
    "iso:country":"US",
    "sg:address":"84-30 Roosevelt Ave #B",
    "sg:city":"Queens",
    "sg:classifiers":[
        {
            "category":"Personal",
            "type":"Services"
        },
        {
            "category":"Retail",
            "subcategory":"Laundry & Dry Cleaning",
            "type":"Services"
        }
    ],
    "sg:phone":"+1 718 779 4757",
    "sg:postcode":"11372",
    "sg:province":"NY",
    "sg:tags":[
        "sewing",
        "alteration"
    ],
    "wof:name":"Macbell Cleaners",
    "wof:placetype":"venue"
},
  "geometry": {"coordinates":[-73.88125100000001,40.747731],"type":"Point"}
}