{
  "type": "Feature",
  "properties": {
    "iso:country":"US",
    "sg:address":"578 Nepperhan Ave",
    "sg:city":"Yonkers",
    "sg:classifiers":[
        {
            "category":"Manufacturing",
            "subcategory":"Apparel",
            "type":"Manufacturing & Wholesale Goods"
        },
        {
            "category":"Home & Garden",
            "subcategory":"Home Furnishings",
            "type":"Retail Goods"
        }
    ],
    "sg:phone":"+1 914 964 0669",
    "sg:postcode":"10701",
    "sg:province":"NY",
    "sg:tags":[
        "curtain",
        "made",
        "drapery",
        "mfg"
    ],
    "wof:name":"Kate's Trade Shop Inc",
    "wof:placetype":"venue"
},
  "geometry": {"coordinates":[-73.885989,40.939622],"type":"Point"}
}