{
  "type": "Feature",
  "properties": {
    "iso:country":"US",
    "sg:address":"614 Fishers Run",
    "sg:city":"Victor",
    "sg:classifiers":[
        {
            "category":"Real Estate",
            "subcategory":"Real Estate Services",
            "type":"Services"
        },
        {
            "category":"Structure",
            "subcategory":"Office Building",
            "type":"Public Place"
        },
        {
            "category":"Real Estate",
            "subcategory":"Real Estate Agent",
            "type":"Services"
        }
    ],
    "sg:phone":"+1 585 924 7370",
    "sg:postcode":"14564",
    "sg:province":"NY",
    "sg:tags":[
        "management",
        "park"
    ],
    "wof:name":"M3 Properties",
    "wof:placetype":"venue"
},
  "geometry": {"coordinates":[-77.453003,43.009873],"type":"Point"}
}