{
  "type": "Feature",
  "properties": {
    "addr:full":"3532 Union St Flushing NY 11354",
    "addr:housenumber":"3532",
    "addr:postcode":"11354",
    "addr:street":"Union St",
    "iso:country":"US",
    "sg:address":"3532 Union St",
    "sg:city":"Flushing",
    "sg:classifiers":[
        {
            "category":"Shopping",
            "subcategory":"Comic Books",
            "type":"Retail Goods"
        }
    ],
    "sg:phone":"+1 347 438 1296",
    "sg:postcode":"11354",
    "sg:province":"NY",
    "wof:name":"Minxpo",
    "wof:placetype":"venue"
},
  "geometry": {"coordinates":[-73.828108,40.76496],"type":"Point"}
}