{
  "type": "Feature",
  "properties": {
    "iso:country":"US",
    "sg:address":"938 Rockaway Ave",
    "sg:city":"Valley Stream",
    "sg:classifiers":[
        {
            "category":"Wholesale",
            "subcategory":"Electrical",
            "type":"Manufacturing & Wholesale Goods"
        }
    ],
    "sg:phone":"+1 516 295 1123",
    "sg:postcode":"11581",
    "sg:province":"NY",
    "sg:tags":[
        "alarm",
        "burglar",
        "system"
    ],
    "wof:name":"ACE Protection Co",
    "wof:placetype":"venue"
},
  "geometry": {"coordinates":[-73.69569,40.653028],"type":"Point"}
}