{
  "type": "Feature",
  "properties": {
    "addr:full":"990 Hoosick Rd Troy NY 12180",
    "addr:housenumber":"990",
    "addr:postcode":"12180",
    "addr:street":"Hoosick Rd",
    "iso:country":"US",
    "sg:address":"990 Hoosick Rd",
    "sg:city":"Troy",
    "sg:classifiers":[
        {
            "category":"Organizations",
            "subcategory":"Religious Organization",
            "type":"Services"
        }
    ],
    "sg:phone":"+1 518 279 9705",
    "sg:postcode":"12180",
    "sg:province":"NY",
    "sg:tags":[
        "church"
    ],
    "wof:name":"Center Brunswick United Mthdst",
    "wof:placetype":"venue"
},
  "geometry": {"coordinates":[-73.61624999999999,42.757072],"type":"Point"}
}