{
  "type": "Feature",
  "properties": {
    "addr:full":"2220 36th Ave Astoria NY 11106",
    "addr:housenumber":"2220",
    "addr:postcode":"11106",
    "addr:street":"36Th Ave",
    "iso:country":"US",
    "sg:address":"2220 36th Ave",
    "sg:city":"Astoria",
    "sg:phone":"+1 718 472 4788",
    "sg:postcode":"11106",
    "sg:province":"NY",
    "wof:name":"Trade Fair Supermarket",
    "wof:placetype":"venue"
},
  "geometry": {"coordinates":[-73.944275,40.762775],"type":"Point"}
}