{
  "type": "Feature",
  "properties": {
    "iso:country":"US",
    "sg:address":"158 Higbie Ln",
    "sg:city":"West Islip",
    "sg:classifiers":[
        {
            "category":"Deli",
            "type":"Food & Drink"
        }
    ],
    "sg:menulink":"http://www.allmenus.com/ny/islip/215507-higbie-lane-country-deli/menu/",
    "sg:phone":"+1 631 669 9749",
    "sg:postcode":"11795",
    "sg:province":"NY",
    "sg:tags":[
        "american"
    ],
    "wof:name":"Higbie Lane Country Deli",
    "wof:placetype":"venue"
},
  "geometry": {"coordinates":[-73.30663699999999,40.705333],"type":"Point"}
}