{
  "type": "Feature",
  "properties": {
    "addr:full":"265 E Shore Rd Manhasset NY 11030",
    "addr:housenumber":"265",
    "addr:postcode":"11030",
    "addr:street":"E Shore Rd",
    "iso:country":"US",
    "sg:address":"265 E Shore Rd",
    "sg:city":"Manhasset",
    "sg:classifiers":[
        {
            "category":"Retail",
            "subcategory":"Auto Repair",
            "type":"Services"
        }
    ],
    "sg:phone":"+1   ",
    "sg:postcode":"11030",
    "sg:province":"NY",
    "sg:tags":[
        "automotive",
        "station",
        "au",
        "gasoline",
        "general"
    ],
    "wof:name":"Manhassett Auto Sales",
    "wof:placetype":"venue"
},
  "geometry": {"coordinates":[-73.708608,40.790279],"type":"Point"}
}