{
  "type": "Feature",
  "properties": {
    "addr:full":"251 E 188th St Bronx NY 10458",
    "addr:housenumber":"251",
    "addr:postcode":"10458",
    "addr:street":"E 188Th St",
    "iso:country":"US",
    "sg:address":"251 E 188th St",
    "sg:city":"Bronx",
    "sg:classifiers":[
        {
            "category":"Shopping",
            "subcategory":"Pharmacy",
            "type":"Retail Goods"
        }
    ],
    "sg:phone":"+1 718 733 6722",
    "sg:postcode":"10458",
    "sg:province":"NY",
    "wof:name":"Hopewell Pharmacy Inc",
    "wof:placetype":"venue"
},
  "geometry": {"coordinates":[-73.895376,40.860744],"type":"Point"}
}