{
  "type": "Feature",
  "properties": {
    "addr:full":"98 Varick St New York NY 10013",
    "addr:housenumber":"98",
    "addr:postcode":"10013",
    "addr:street":"Varick St",
    "iso:country":"US",
    "sg:address":"98 Varick St",
    "sg:city":"New York",
    "sg:classifiers":[
        {
            "category":"Building & Trades",
            "subcategory":"Plumbing",
            "type":"Services"
        }
    ],
    "sg:phone":"+1 212 937 1166",
    "sg:postcode":"10013",
    "sg:province":"NY",
    "sg:tags":[
        "contractor"
    ],
    "wof:name":"Ajar Plumbing",
    "wof:placetype":"venue"
},
  "geometry": {"coordinates":[-74.006203,40.723801],"type":"Point"}
}