{
  "type": "Feature",
  "properties": {
    "addr:full":"12396 McNeeley Rd Akron NY 14001",
    "addr:housenumber":"12396",
    "addr:postcode":"14001",
    "addr:street":"Mcneeley Rd",
    "iso:country":"US",
    "sg:address":"12396 McNeeley Rd",
    "sg:city":"Akron",
    "sg:classifiers":[
        {
            "category":"Building & Trades",
            "subcategory":"Construction",
            "type":"Services"
        }
    ],
    "sg:phone":"+1 585 542 9947",
    "sg:postcode":"14001",
    "sg:province":"NY",
    "sg:tags":[
        "demolition",
        "contractor"
    ],
    "wof:name":"Young's Auto Wrecking & House",
    "wof:placetype":"venue"
},
  "geometry": {"coordinates":[-78.52437500000001,43.02243],"type":"Point"}
}