{
  "type": "Feature",
  "properties": {
    "addr:full":"133-56 41st Ave Flushing NY 11355",
    "addr:housenumber":"133-56",
    "addr:postcode":"11355",
    "addr:street":"41St Ave",
    "iso:country":"US",
    "sg:address":"133-56 41st Ave",
    "sg:city":"Flushing",
    "sg:classifiers":[
        {
            "category":"Taxi",
            "type":"Transportation"
        }
    ],
    "sg:phone":"+1 718 539 7777",
    "sg:postcode":"11355",
    "sg:province":"NY",
    "wof:name":"G&E Express",
    "wof:placetype":"venue"
},
  "geometry": {"coordinates":[-73.831023,40.756454],"type":"Point"}
}