{
  "type": "Feature",
  "properties": {
    "iso:country":"US",
    "sg:address":"17 Gramercy Pl",
    "sg:city":"Thornwood",
    "sg:classifiers":[
        {
            "category":"Manufacturing",
            "subcategory":"Furniture",
            "type":"Manufacturing & Wholesale Goods"
        }
    ],
    "sg:phone":"+1   ",
    "sg:postcode":"10594",
    "sg:province":"NY",
    "sg:tags":[
        "upholstered",
        "on",
        "household",
        "wood",
        "frame"
    ],
    "wof:name":"Reupholstery By Anna",
    "wof:placetype":"venue"
},
  "geometry": {"coordinates":[-73.782714,41.127438],"type":"Point"}
}