{
  "type": "Feature",
  "properties": {
    "iso:country":"US",
    "sg:address":"1560 Best Rd",
    "sg:city":"Rensselaer",
    "sg:classifiers":[
        {
            "category":"Building & Trades",
            "subcategory":"Construction",
            "type":"Services"
        }
    ],
    "sg:phone":"+1 518 286 1580",
    "sg:postcode":"12144",
    "sg:province":"NY",
    "sg:tags":[
        "home",
        "builder"
    ],
    "wof:name":"Better Homes",
    "wof:placetype":"venue"
},
  "geometry": {"coordinates":[-73.682586,42.643664],"type":"Point"}
}