{
  "type": "Feature",
  "properties": {
    "addr:full":"21 Commercial Blvd Medford NY 11763",
    "addr:housenumber":"21",
    "addr:postcode":"11763",
    "addr:street":"Commercial Blvd",
    "iso:country":"US",
    "sg:address":"21 Commercial Blvd",
    "sg:city":"Medford",
    "sg:classifiers":[
        {
            "category":"Building & Trades",
            "subcategory":"Construction",
            "type":"Services"
        }
    ],
    "sg:phone":"+1 631 732 0800",
    "sg:postcode":"11763",
    "sg:province":"NY",
    "sg:tags":[
        "highway",
        "road"
    ],
    "wof:name":"Bi-County Construction Corp",
    "wof:placetype":"venue"
},
  "geometry": {"coordinates":[-72.994947,40.838914],"type":"Point"}
}