{
  "type": "Feature",
  "properties": {
    "addr:full":"209 Fred Ottaway Rd Cooperstown NY 13326",
    "addr:housenumber":"209",
    "addr:postcode":"13326",
    "addr:street":"Fred Ottaway Rd",
    "iso:country":"US",
    "sg:address":"209 Fred Ottaway Rd",
    "sg:city":"Cooperstown",
    "sg:classifiers":[
        {
            "category":"Building & Trades",
            "subcategory":"Plumbing",
            "type":"Services"
        }
    ],
    "sg:phone":"+1 607 286 7098",
    "sg:postcode":"13326",
    "sg:province":"NY",
    "sg:tags":[
        "plumbing",
        "contractor"
    ],
    "wof:name":"Hascup Plumbing",
    "wof:placetype":"venue"
},
  "geometry": {"coordinates":[-74.894454,42.638817],"type":"Point"}
}