{
  "type": "Feature",
  "properties": {
    "iso:country":"US",
    "sg:address":"16 Lonesome Rd",
    "sg:city":"Fairport",
    "sg:classifiers":[
        {
            "category":"Retail",
            "subcategory":"Auto Repair",
            "type":"Services"
        }
    ],
    "sg:phone":"+1 585 377 9835",
    "sg:postcode":"14450",
    "sg:province":"NY",
    "sg:tags":[
        "wrecker"
    ],
    "wof:name":"Master Towing Svc",
    "wof:placetype":"venue"
},
  "geometry": {"coordinates":[-77.452806,43.112161],"type":"Point"}
}