{
  "type": "Feature",
  "properties": {
    "iso:country":"US",
    "sg:address":"41 Adelphi St",
    "sg:city":"Brooklyn",
    "sg:classifiers":[
        {
            "category":"Organizations",
            "subcategory":"Religious Organization",
            "type":"Services"
        }
    ],
    "sg:phone":"+1 718 625 5115",
    "sg:postcode":"11205",
    "sg:province":"NY",
    "sg:tags":[
        "church"
    ],
    "wof:name":"Sacred Heart Church Inc",
    "wof:placetype":"venue"
},
  "geometry": {"coordinates":[-73.972589,40.697618],"type":"Point"}
}