{
  "type": "Feature",
  "properties": {
    "iso:country":"US",
    "sg:address":"406 Fitzsimmons Rd",
    "sg:city":"Red Hook",
    "sg:classifiers":[
        {
            "category":"Shopping",
            "subcategory":"Gifts & Souvenirs",
            "type":"Retail Goods"
        }
    ],
    "sg:phone":"+1 845 756 2511",
    "sg:postcode":"12571",
    "sg:province":"NY",
    "sg:tags":[
        "shop"
    ],
    "wof:name":"Annabelle's Gift Shop",
    "wof:placetype":"venue"
},
  "geometry": {"coordinates":[-73.782618,42.029613],"type":"Point"}
}