{
  "type": "Feature",
  "properties": {
    "addr:full":"1245 Park St Peekskill NY 10566",
    "addr:housenumber":"1245",
    "addr:postcode":"10566",
    "addr:street":"Park St",
    "iso:country":"US",
    "sg:address":"1245 Park St",
    "sg:city":"Peekskill",
    "sg:classifiers":[
        {
            "category":"Professional",
            "subcategory":"Advertising",
            "type":"Services"
        }
    ],
    "sg:phone":"+1 914 739 0900",
    "sg:postcode":"10566",
    "sg:province":"NY",
    "sg:tags":[
        "counselor"
    ],
    "wof:name":"Levine Associates",
    "wof:placetype":"venue"
},
  "geometry": {"coordinates":[-73.91406600000001,41.29079],"type":"Point"}
}