{
  "type": "Feature",
  "properties": {
    "addr:full":"128 Fort Washington Ave New York NY 10032",
    "addr:housenumber":"128",
    "addr:postcode":"10032",
    "addr:street":"Fort Washington Ave",
    "iso:country":"US",
    "sg:address":"128 Fort Washington Ave",
    "sg:city":"New York",
    "sg:classifiers":[
        {
            "category":"Sports & Exercise",
            "subcategory":"Gym",
            "type":"Entertainment"
        }
    ],
    "sg:phone":"+1 212 568 4907",
    "sg:postcode":"10032",
    "sg:province":"NY",
    "sg:tags":[
        "pilate"
    ],
    "sg:website":"www.pilatesintheheights.com",
    "wof:name":"Pilates In The Heights",
    "wof:placetype":"venue"
},
  "geometry": {"coordinates":[-73.94305199999999,40.839334],"type":"Point"}
}