{
  "type": "Feature",
  "properties": {
    "addr:full":"6911 48th Ave Woodside NY 11377",
    "addr:housenumber":"6911",
    "addr:postcode":"11377",
    "addr:street":"48Th Ave",
    "iso:country":"US",
    "sg:address":"6911 48th Ave",
    "sg:city":"Woodside",
    "sg:classifiers":[
        {
            "category":"Autos & Motor Vehicles",
            "subcategory":"Automobile Sales",
            "type":"Retail Goods"
        }
    ],
    "sg:phone":"+1 718 426 4910",
    "sg:postcode":"11377",
    "sg:province":"NY",
    "sg:tags":[
        "limo"
    ],
    "wof:name":"B G Limousine Incorporated",
    "wof:placetype":"venue"
},
  "geometry": {"coordinates":[-73.89479900000001,40.738468],"type":"Point"}
}