{
  "type": "Feature",
  "properties": {
    "iso:country":"US",
    "sg:address":"63 Hampden Ln",
    "sg:city":"Irvington",
    "sg:classifiers":[
        {
            "category":"Professional",
            "subcategory":"Lawyer & Legal Services",
            "type":"Services"
        }
    ],
    "sg:phone":"+1 914 591 8235",
    "sg:postcode":"10533",
    "sg:province":"NY",
    "sg:tags":[
        "attorney"
    ],
    "wof:name":"Eugene Dougherty",
    "wof:placetype":"venue"
},
  "geometry": {"coordinates":[-73.84880800000001,41.028195],"type":"Point"}
}