{
  "type": "Feature",
  "properties": {
    "iso:country":"US",
    "sg:address":"1560 Harlem Rd",
    "sg:city":"Buffalo",
    "sg:classifiers":[
        {
            "category":"Insurance",
            "subcategory":"Insurance Agent",
            "type":"Services"
        }
    ],
    "sg:phone":"+1 716 891 8514",
    "sg:postcode":"14206",
    "sg:province":"NY",
    "sg:tags":[
        "agency"
    ],
    "wof:name":"Genesee Agency",
    "wof:placetype":"venue"
},
  "geometry": {"coordinates":[-78.784639,42.884802],"type":"Point"}
}