{
  "type": "Feature",
  "properties": {
    "iso:country":"US",
    "sg:address":"254 Main St",
    "sg:city":"Schoharie",
    "sg:classifiers":[
        {
            "category":"Retail",
            "subcategory":"Laundry & Dry Cleaning",
            "type":"Services"
        }
    ],
    "sg:phone":"+1 518 295 7555",
    "sg:postcode":"12157",
    "sg:province":"NY",
    "sg:tags":[
        "cleaner",
        "rug",
        "carpet"
    ],
    "wof:name":"Carpet & Upholstery Cleaning W",
    "wof:placetype":"venue"
},
  "geometry": {"coordinates":[-74.31404999999999,42.662329],"type":"Point"}
}