{
  "type": "Feature",
  "properties": {
    "addr:full":"4 Ridgeview Ave White Plains NY 10606",
    "addr:housenumber":"4",
    "addr:postcode":"10606",
    "addr:street":"Ridgeview Ave",
    "iso:country":"US",
    "sg:address":"4 Ridgeview Ave",
    "sg:city":"White Plains",
    "sg:classifiers":[
        {
            "category":"Building & Trades",
            "subcategory":"Electrical",
            "type":"Services"
        }
    ],
    "sg:phone":"+1 914 328 7187",
    "sg:postcode":"10606",
    "sg:province":"NY",
    "sg:tags":[
        "electrical",
        "contractor"
    ],
    "wof:name":"Mary Kay Cosmetics",
    "wof:placetype":"venue"
},
  "geometry": {"coordinates":[-73.778683,41.023261],"type":"Point"}
}