{
  "type": "Feature",
  "properties": {
    "iso:country":"US",
    "sg:address":"1513 Main St",
    "sg:city":"Sylvan Beach",
    "sg:classifiers":[
        {
            "category":"Travel",
            "subcategory":"Hotels & Motels",
            "type":"Entertainment"
        }
    ],
    "sg:phone":"+1   ",
    "sg:postcode":"13157",
    "sg:province":"NY",
    "sg:tags":[
        "operation"
    ],
    "wof:name":"Beach Inn",
    "wof:placetype":"venue"
},
  "geometry": {"coordinates":[-75.728196,43.203826],"type":"Point"}
}