{
  "type": "Feature",
  "properties": {
    "iso:country":"US",
    "sg:address":"40 W 27th St",
    "sg:city":"New York",
    "sg:classifiers":[
        {
            "category":"Arena",
            "subcategory":"Sports Club",
            "type":"Entertainment"
        }
    ],
    "sg:phone":"+1 212 213 8805",
    "sg:postcode":"10001",
    "sg:province":"NY",
    "sg:tags":[
        "martial art"
    ],
    "wof:name":"Eagle Claw Kung-Fu Tai Chi Academy",
    "wof:placetype":"venue"
},
  "geometry": {"coordinates":[-73.989502,40.7449],"type":"Point"}
}