{
  "type": "Feature",
  "properties": {
    "addr:full":"200 Washington Ave Exd Albany NY 12203",
    "addr:housenumber":"200",
    "addr:postcode":"12203",
    "addr:street":"Washington Ave Exd",
    "iso:country":"US",
    "sg:address":"200 Washington Ave Exd",
    "sg:city":"Albany",
    "sg:classifiers":[
        {
            "category":"Organizations",
            "subcategory":"Religious Organization",
            "type":"Services"
        }
    ],
    "sg:phone":"+1 518 452 5884",
    "sg:postcode":"12203",
    "sg:province":"NY",
    "sg:tags":[
        "clergy"
    ],
    "wof:name":"John L Jones",
    "wof:placetype":"venue"
},
  "geometry": {"coordinates":[-73.866742,42.709698],"type":"Point"}
}