{
  "type": "Feature",
  "properties": {
    "addr:full":"600 Hillside Ave New Hyde Park NY 11040",
    "addr:housenumber":"600",
    "addr:postcode":"11040",
    "addr:street":"Hillside Ave",
    "iso:country":"US",
    "sg:address":"600 Hillside Ave",
    "sg:city":"New Hyde Park",
    "sg:classifiers":[
        {
            "category":"Wholesale",
            "subcategory":"Construction Materials",
            "type":"Manufacturing & Wholesale Goods"
        },
        {
            "category":"Building & Trades",
            "subcategory":"Construction",
            "type":"Services"
        }
    ],
    "sg:phone":"+1 718 343 0041",
    "sg:postcode":"11040",
    "sg:province":"NY",
    "sg:tags":[
        "fence",
        "contractor"
    ],
    "wof:name":"Amendola's Fence Co",
    "wof:placetype":"venue"
},
  "geometry": {"coordinates":[-73.694592,40.742643],"type":"Point"}
}