{
  "type": "Feature",
  "properties": {
    "iso:country":"US",
    "sg:address":"12 Mountain View Dr",
    "sg:city":"Cambridge",
    "sg:classifiers":[
        {
            "category":"Retail",
            "subcategory":"Repair Shop",
            "type":"Services"
        }
    ],
    "sg:phone":"+1 518 677 3243",
    "sg:postcode":"12816",
    "sg:province":"NY",
    "sg:tags":[
        "related"
    ],
    "wof:name":"Mr Fix It Repair Shop",
    "wof:placetype":"venue"
},
  "geometry": {"coordinates":[-73.37325199999999,43.021165],"type":"Point"}
}