{
  "type": "Feature",
  "properties": {
    "iso:country":"US",
    "sg:address":"1150 68th St",
    "sg:city":"Brooklyn",
    "sg:classifiers":[
        {
            "category":"Building & Trades",
            "subcategory":"Construction",
            "type":"Services"
        }
    ],
    "sg:phone":"+1 212 693 6634",
    "sg:postcode":"11219",
    "sg:province":"NY",
    "sg:tags":[
        "house"
    ],
    "wof:name":"Millennium Builder & Dev",
    "wof:placetype":"venue"
},
  "geometry": {"coordinates":[-74.006546,40.626087],"type":"Point"}
}