{
  "type": "Feature",
  "properties": {
    "addr:full":"1828 Chowan St Elmont NY 11003",
    "addr:housenumber":"1828",
    "addr:postcode":"11003",
    "addr:street":"Chowan St",
    "iso:country":"US",
    "sg:address":"1828 Chowan St",
    "sg:city":"Elmont",
    "sg:classifiers":[
        {
            "category":"Manufacturing",
            "subcategory":"Tools & Machinery",
            "type":"Manufacturing & Wholesale Goods"
        }
    ],
    "sg:phone":"+1 516 488 5773",
    "sg:postcode":"11003",
    "sg:province":"NY",
    "sg:tags":[
        "gage"
    ],
    "wof:name":"Sandy Webb's Bookkeeping Svc",
    "wof:placetype":"venue"
},
  "geometry": {"coordinates":[-73.709496,40.705278],"type":"Point"}
}