{
  "type": "Feature",
  "properties": {
    "addr:full":"22 E29th Street New York NY 10016",
    "addr:postcode":"10016",
    "addr:street":"E29Th Street",
    "iso:country":"US",
    "sg:address":"22 E29th Street",
    "sg:city":"New York",
    "sg:classifiers":[
        {
            "category":"Bars & Pubs",
            "subcategory":"Nightclub",
            "type":"Food & Drink"
        }
    ],
    "sg:postcode":"10016",
    "sg:province":"NY",
    "sg:tags":[
        "nightlife"
    ],
    "wof:name":"Jay Lounge",
    "wof:placetype":"venue"
},
  "geometry": {"coordinates":[-73.98529600000001,40.744668],"type":"Point"}
}