{
  "type": "Feature",
  "properties": {
    "iso:country":"US",
    "sg:address":"5223 Blodgett Rd",
    "sg:city":"Stanley",
    "sg:classifiers":[
        {
            "category":"Building & Trades",
            "subcategory":"Construction",
            "type":"Services"
        }
    ],
    "sg:phone":"+1 585 554 3652",
    "sg:postcode":"14561",
    "sg:province":"NY",
    "sg:tags":[
        "excavating",
        "contractor"
    ],
    "wof:name":"Owen Excavation",
    "wof:placetype":"venue"
},
  "geometry": {"coordinates":[-77.20928499999999,42.770504],"type":"Point"}
}