{
  "type": "Feature",
  "properties": {
    "iso:country":"US",
    "sg:address":"172 Cumberland St",
    "sg:city":"Mastic",
    "sg:classifiers":[
        {
            "category":"Home & Garden",
            "subcategory":"Carpets & Floor Coverings",
            "type":"Retail Goods"
        }
    ],
    "sg:phone":"+1   ",
    "sg:postcode":"11950",
    "sg:province":"NY",
    "wof:name":"Goldsborough Carpet",
    "wof:placetype":"venue"
},
  "geometry": {"coordinates":[-72.846405,40.794582],"type":"Point"}
}