{
  "type": "Feature",
  "properties": {
    "addr:full":"22 S Broad St Norwich NY 13815",
    "addr:housenumber":"22",
    "addr:postcode":"13815",
    "addr:street":"S Broad St",
    "iso:country":"US",
    "sg:address":"22 S Broad St",
    "sg:city":"Norwich",
    "sg:classifiers":[
        {
            "category":"Wholesale",
            "subcategory":"Machinery & Supplies",
            "type":"Manufacturing & Wholesale Goods"
        }
    ],
    "sg:phone":"+1 607 334 9595",
    "sg:postcode":"13815",
    "sg:province":"NY",
    "sg:tags":[
        "equipment",
        "industrial"
    ],
    "wof:name":"Bindersplus",
    "wof:placetype":"venue"
},
  "geometry": {"coordinates":[-75.523796,42.530343],"type":"Point"}
}