{
  "type": "Feature",
  "properties": {
    "iso:country":"US",
    "sg:address":"21 Sanford St Apt 16",
    "sg:city":"Warrensburg",
    "sg:classifiers":[
        {
            "category":"Real Estate",
            "subcategory":"Real Estate Operator",
            "type":"Services"
        }
    ],
    "sg:phone":"+1 518 623 2545",
    "sg:postcode":"12885",
    "sg:province":"NY",
    "sg:tags":[
        "apartment"
    ],
    "wof:name":"Warrensburg Commons",
    "wof:placetype":"venue"
},
  "geometry": {"coordinates":[-73.78009,43.494949],"type":"Point"}
}