{
  "type": "Feature",
  "properties": {
    "iso:country":"US",
    "sg:address":"352 Forestview Dr",
    "sg:city":"Williamsville",
    "sg:classifiers":[
        {
            "category":"Banks & Credit Unions",
            "subcategory":"Investment Brokerage",
            "type":"Services"
        }
    ],
    "sg:phone":"+1 716 688 6921",
    "sg:postcode":"14221",
    "sg:province":"NY",
    "wof:name":"David H Desmon Invstmnt Sec",
    "wof:placetype":"venue"
},
  "geometry": {"coordinates":[-78.746362,43.010065],"type":"Point"}
}