{
  "type": "Feature",
  "properties": {
    "addr:full":"37 Randall Rd Shoreham NY 11786",
    "addr:housenumber":"37",
    "addr:postcode":"randall;11786",
    "addr:street":"Rd",
    "iso:country":"US",
    "sg:address":"37 Randall Rd",
    "sg:city":"Shoreham",
    "sg:classifiers":[
        {
            "category":"Shopping",
            "subcategory":"Pets & Pet Supplies",
            "type":"Retail Goods"
        }
    ],
    "sg:phone":"+1 631 871 2239",
    "sg:postcode":"11786",
    "sg:province":"NY",
    "sg:tags":[
        "specialty"
    ],
    "wof:name":"Lucky Cat Tatoos",
    "wof:placetype":"venue"
},
  "geometry": {"coordinates":[-72.898883,40.943012],"type":"Point"}
}