{
  "type": "Feature",
  "properties": {
    "iso:country":"US",
    "sg:address":"219 Lyell Ave",
    "sg:city":"Spencerport",
    "sg:classifiers":[
        {
            "category":"Shopping",
            "subcategory":"Used Merchandise",
            "type":"Retail Goods"
        }
    ],
    "sg:phone":"+1   ",
    "sg:postcode":"14559",
    "sg:province":"NY",
    "wof:name":"Down Memory Lane Antiques & Co",
    "wof:placetype":"venue"
},
  "geometry": {"coordinates":[-77.79738399999999,43.189165],"type":"Point"}
}