{
  "type": "Feature",
  "properties": {
    "iso:country":"US",
    "sg:address":"55 Lindner Pl",
    "sg:city":"Malverne",
    "sg:classifiers":[
        {
            "category":"Social Services",
            "subcategory":"Child Care",
            "type":"Services"
        },
        {
            "category":"Education",
            "subcategory":"School",
            "type":"Public Place"
        }
    ],
    "sg:phone":"+1 516 887 7267",
    "sg:postcode":"11565",
    "sg:province":"NY",
    "sg:tags":[
        "elementary",
        "day"
    ],
    "wof:name":"Malverne After School Center",
    "wof:placetype":"venue"
},
  "geometry": {"coordinates":[-73.671631,40.676501],"type":"Point"}
}