{
  "type": "Feature",
  "properties": {
    "iso:country":"US",
    "sg:address":"728 Bradley St",
    "sg:city":"Watertown",
    "sg:classifiers":[
        {
            "category":"Organizations",
            "subcategory":"Community Association",
            "type":"Services"
        }
    ],
    "sg:phone":"+1 315 788 1270",
    "sg:postcode":"13601",
    "sg:province":"NY",
    "sg:tags":[
        "fraternal"
    ],
    "wof:name":"Elks Lodge",
    "wof:placetype":"venue"
},
  "geometry": {"coordinates":[-75.91609200000001,43.986391],"type":"Point"}
}