{
  "type": "Feature",
  "properties": {
    "addr:full":"3400 Southwestern Blvd Orchard Park NY 14127",
    "addr:housenumber":"3400",
    "addr:postcode":"14127",
    "addr:street":"Southwestern Blvd",
    "iso:country":"US",
    "sg:address":"3400 Southwestern Blvd",
    "sg:city":"Orchard Park",
    "sg:classifiers":[
        {
            "category":"Personal",
            "subcategory":"Beauty Salon",
            "type":"Services"
        }
    ],
    "sg:phone":"+1 716 674 2453",
    "sg:postcode":"14127",
    "sg:province":"NY",
    "wof:name":"Tips & Toes Nail Salon",
    "wof:placetype":"venue"
},
  "geometry": {"coordinates":[-78.754147,42.795139],"type":"Point"}
}