{
  "type": "Feature",
  "properties": {
    "iso:country":"US",
    "sg:address":"76 Commercial St",
    "sg:city":"Livonia",
    "sg:classifiers":[
        {
            "category":"Wholesale",
            "subcategory":"Home Furnishings",
            "type":"Manufacturing & Wholesale Goods"
        }
    ],
    "sg:phone":"+1 585 346 3240",
    "sg:postcode":"14487",
    "sg:province":"NY",
    "sg:tags":[
        "plumbing",
        "supplies-wholesale",
        "part",
        "fixture",
        "manufacturer"
    ],
    "wof:name":"Livonia Supply Center",
    "wof:placetype":"venue"
},
  "geometry": {"coordinates":[-77.671547,42.815941],"type":"Point"}
}