{
  "type": "Feature",
  "properties": {
    "addr:full":"6971 W Bergen Rd Bergen NY 14416",
    "addr:housenumber":"6971",
    "addr:postcode":"14416",
    "addr:street":"W Bergen Rd",
    "iso:country":"US",
    "sg:address":"6971 W Bergen Rd",
    "sg:city":"Bergen",
    "sg:classifiers":[
        {
            "category":"Education",
            "subcategory":"School",
            "type":"Public Place"
        }
    ],
    "sg:phone":"+1 585 494 2220",
    "sg:postcode":"14416",
    "sg:province":"NY",
    "wof:name":"Byron Bergen Elementary School",
    "wof:placetype":"venue"
},
  "geometry": {"coordinates":[-78.00497799999999,43.076442],"type":"Point"}
}