{
  "type": "Feature",
  "properties": {
    "iso:country":"US",
    "sg:address":"160 Hillair Cir",
    "sg:city":"White Plains",
    "sg:classifiers":[
        {
            "category":"Real Estate",
            "subcategory":"Architect",
            "type":"Services"
        }
    ],
    "sg:phone":"+1 914 761 1534",
    "sg:postcode":"10605",
    "sg:province":"NY",
    "wof:name":"Leonard Weinberg PC",
    "wof:placetype":"venue"
},
  "geometry": {"coordinates":[-73.75676300000001,40.996263],"type":"Point"}
}