{
  "type": "Feature",
  "properties": {
    "iso:country":"US",
    "sg:address":"7077 Lakeshore Rd",
    "sg:city":"Cicero",
    "sg:classifiers":[
        {
            "category":"Food & Beverages",
            "subcategory":"Specialty",
            "type":"Retail Goods"
        }
    ],
    "sg:phone":"+1   ",
    "sg:postcode":"13039",
    "sg:province":"NY",
    "wof:name":"Starlight International Ltd",
    "wof:placetype":"venue"
},
  "geometry": {"coordinates":[-76.035618,43.194813],"type":"Point"}
}