{
  "type": "Feature",
  "properties": {
    "iso:country":"US",
    "sg:address":"5 Flagpole Ln",
    "sg:city":"Setauket",
    "sg:classifiers":[
        {
            "category":"Banks & Credit Unions",
            "subcategory":"Investment Brokerage",
            "type":"Services"
        }
    ],
    "sg:phone":"+1 631 751 7026",
    "sg:postcode":"11733",
    "sg:province":"NY",
    "sg:tags":[
        "investing"
    ],
    "wof:name":"Ath Capital Management",
    "wof:placetype":"venue"
},
  "geometry": {"coordinates":[-73.430848,40.930599],"type":"Point"}
}