{
  "type": "Feature",
  "properties": {
    "addr:full":"8384 115th Street Richmond Hill NY 11418",
    "addr:housenumber":"8384",
    "addr:postcode":"11418",
    "addr:street":"115Th Street",
    "iso:country":"US",
    "sg:address":"8384 115th Street",
    "sg:city":"Richmond Hill",
    "sg:classifiers":[
        {
            "category":"Organizations",
            "subcategory":"Religious Organization",
            "type":"Services"
        }
    ],
    "sg:phone":"+1 718 805 0380",
    "sg:postcode":"11418",
    "sg:province":"NY",
    "wof:name":"Kabbalah Research Center",
    "wof:placetype":"venue"
},
  "geometry": {"coordinates":[-73.836809,40.703503],"type":"Point"}
}