{
  "type": "Feature",
  "properties": {
    "iso:country":"US",
    "sg:address":"51 Lake Desolation Rd",
    "sg:city":"Middle Grove",
    "sg:classifiers":[
        {
            "category":"Wholesale",
            "subcategory":"Construction Materials",
            "type":"Manufacturing & Wholesale Goods"
        }
    ],
    "sg:phone":"+1 518 584 0396",
    "sg:postcode":"12850",
    "sg:province":"NY",
    "sg:tags":[
        "dressed",
        "rough",
        "lumber",
        "finished"
    ],
    "wof:name":"Kilmer Lumber Inc",
    "wof:placetype":"venue"
},
  "geometry": {"coordinates":[-73.921356,43.091491],"type":"Point"}
}