{
  "type": "Feature",
  "properties": {
    "iso:country":"US",
    "sg:address":"1301 Oakpoint Ave",
    "sg:city":"Bronx",
    "sg:classifiers":[
        {
            "category":"Food & Beverages",
            "subcategory":"Fruits & Vegetables",
            "type":"Retail Goods"
        }
    ],
    "sg:phone":"+1 718 842 7690",
    "sg:postcode":"10474",
    "sg:province":"NY",
    "sg:tags":[
        "produce"
    ],
    "wof:name":"Fruit Harvest",
    "wof:placetype":"venue"
},
  "geometry": {"coordinates":[-73.884455,40.810472],"type":"Point"}
}