{
  "type": "Feature",
  "properties": {
    "iso:country":"US",
    "sg:address":"5210 W Genesee St",
    "sg:city":"Camillus",
    "sg:classifiers":[
        {
            "category":"Health Services",
            "subcategory":"Doctor",
            "type":"Services"
        }
    ],
    "sg:phone":"+1 315 487 9225",
    "sg:postcode":"13031",
    "sg:province":"NY",
    "sg:tags":[
        "dentist"
    ],
    "wof:name":"Camillus Dental Associates",
    "wof:placetype":"venue"
},
  "geometry": {"coordinates":[-76.265315,43.041399],"type":"Point"}
}