{
  "type": "Feature",
  "properties": {
    "iso:country":"US",
    "sg:address":"10 Denesha Pl",
    "sg:city":"Fulton",
    "sg:classifiers":[
        {
            "category":"Insurance",
            "subcategory":"Hazard Insurance",
            "type":"Services"
        }
    ],
    "sg:phone":"+1 315 593 8265",
    "sg:postcode":"13069",
    "sg:province":"NY",
    "wof:name":"William H Kane",
    "wof:placetype":"venue"
},
  "geometry": {"coordinates":[-76.42086500000001,43.310019],"type":"Point"}
}