{
  "type": "Feature",
  "properties": {
    "addr:full":"503 Wilbur Ave Kingston NY 12401",
    "addr:housenumber":"503",
    "addr:postcode":"12401",
    "addr:street":"Wilbur Ave",
    "iso:country":"US",
    "sg:address":"503 Wilbur Ave",
    "sg:city":"Kingston",
    "sg:classifiers":[
        {
            "category":"Manufacturing",
            "subcategory":"Metals",
            "type":"Manufacturing & Wholesale Goods"
        }
    ],
    "sg:phone":"+1 845 336 6147",
    "sg:postcode":"12401",
    "sg:province":"NY",
    "sg:tags":[
        "fabricator",
        "sheet"
    ],
    "wof:name":"Ahed Metal Fabrication",
    "wof:placetype":"venue"
},
  "geometry": {"coordinates":[-74.005855,41.910746],"type":"Point"}
}