{
  "type": "Feature",
  "properties": {
    "iso:country":"US",
    "sg:address":"7 Center Dr",
    "sg:city":"Corning",
    "sg:classifiers":[
        {
            "category":"Government",
            "subcategory":"Office",
            "type":"Public Place"
        }
    ],
    "sg:phone":"+1 607 962 8120",
    "sg:postcode":"14830",
    "sg:province":"NY",
    "sg:tags":[
        "city",
        "executive"
    ],
    "wof:name":"Corning City Mayor's Office",
    "wof:placetype":"venue"
},
  "geometry": {"coordinates":[-76.98629099999999,42.12703],"type":"Point"}
}