{
  "type": "Feature",
  "properties": {
    "addr:full":"143 Madison Ave New York NY 10016",
    "addr:housenumber":"143",
    "addr:postcode":"10016",
    "addr:street":"Madison Ave",
    "iso:country":"US",
    "sg:address":"143 Madison Ave",
    "sg:city":"New York",
    "sg:classifiers":[
        {
            "category":"Organizations",
            "subcategory":"Professional Association",
            "type":"Services"
        }
    ],
    "sg:phone":"+1 212 679 5100",
    "sg:postcode":"10016",
    "sg:province":"NY",
    "sg:tags":[
        "legal"
    ],
    "wof:name":"New York Chapter",
    "wof:placetype":"venue"
},
  "geometry": {"coordinates":[-73.984019,40.746099],"type":"Point"}
}