{
  "type": "Feature",
  "properties": {
    "addr:full":"1764 Nostrand Ave Brooklyn NY 11226",
    "addr:housenumber":"1764",
    "addr:postcode":"11226",
    "addr:street":"Nostrand Ave",
    "iso:country":"US",
    "sg:address":"1764 Nostrand Ave",
    "sg:city":"Brooklyn",
    "sg:classifiers":[
        {
            "category":"Shopping",
            "subcategory":"Discount & Variety Stores",
            "type":"Retail Goods"
        }
    ],
    "sg:phone":"+1 718 941 1731",
    "sg:postcode":"11226",
    "sg:province":"NY",
    "wof:name":"Junior Variety Store",
    "wof:placetype":"venue"
},
  "geometry": {"coordinates":[-73.94861899999999,40.641306],"type":"Point"}
}