{
  "type": "Feature",
  "properties": {
    "addr:full":"3509 James Street Syracuse NY 13206",
    "addr:housenumber":"3509",
    "addr:postcode":"13206",
    "addr:street":"James Street",
    "iso:country":"US",
    "sg:address":"3509 James Street",
    "sg:city":"Syracuse",
    "sg:classifiers":[
        {
            "category":"Restaurant",
            "type":"Food & Drink"
        }
    ],
    "sg:menulink":"http://www.allmenus.com/ny/syracuse/276626-original-italian-pizza/menu/",
    "sg:phone":"+1 315 437 3800",
    "sg:postcode":"13206",
    "sg:province":"NY",
    "sg:tags":[
        "american",
        "italian",
        "pizza"
    ],
    "wof:name":"Original Italian Pizza",
    "wof:placetype":"venue"
},
  "geometry": {"coordinates":[-76.09815500000001,43.06923],"type":"Point"}
}