{
  "type": "Feature",
  "properties": {
    "addr:full":"1130 N Broadway Massapequa NY 11758",
    "addr:housenumber":"1130",
    "addr:postcode":"11758",
    "addr:street":"N Broadway",
    "iso:country":"US",
    "sg:address":"1130 N Broadway",
    "sg:city":"Massapequa",
    "sg:classifiers":[
        {
            "category":"Professional",
            "subcategory":"Credit Reporting & Collection",
            "type":"Services"
        }
    ],
    "sg:phone":"+1 516 420 7440",
    "sg:postcode":"11758",
    "sg:province":"NY",
    "sg:tags":[
        "agency"
    ],
    "wof:name":"Commercial Collection Cnsltnts",
    "wof:placetype":"venue"
},
  "geometry": {"coordinates":[-73.46113,40.715617],"type":"Point"}
}