{
  "type": "Feature",
  "properties": {
    "addr:full":"665 88th St Brooklyn NY 11228",
    "addr:housenumber":"665",
    "addr:postcode":"11228",
    "addr:street":"88Th St",
    "iso:country":"US",
    "sg:address":"665 88th St",
    "sg:city":"Brooklyn",
    "sg:classifiers":[
        {
            "category":"Home & Garden",
            "subcategory":"Furniture",
            "type":"Retail Goods"
        }
    ],
    "sg:phone":"+1 718 680 7277",
    "sg:postcode":"11228",
    "sg:province":"NY",
    "wof:name":"Konan Furniture Design Studio",
    "wof:placetype":"venue"
},
  "geometry": {"coordinates":[-74.02162199999999,40.6175],"type":"Point"}
}