{
  "type": "Feature",
  "properties": {
    "iso:country":"US",
    "sg:address":"853 Broadway",
    "sg:city":"New York",
    "sg:classifiers":[
        {
            "category":"Building & Trades",
            "subcategory":"Construction",
            "type":"Services"
        }
    ],
    "sg:phone":"+1 212 529 5840",
    "sg:postcode":"10003",
    "sg:province":"NY",
    "sg:tags":[
        "interior",
        "design"
    ],
    "wof:name":"Network For Employment Opportunity",
    "wof:placetype":"venue"
},
  "geometry": {"coordinates":[-73.990846,40.734562],"type":"Point"}
}