{
  "type": "Feature",
  "properties": {
    "iso:country":"US",
    "sg:address":"605 W 48 St",
    "sg:city":"New York",
    "sg:classifiers":[
        {
            "category":"Real Estate",
            "subcategory":"Real Estate Agent",
            "type":"Services"
        }
    ],
    "sg:phone":"+1 212 921 0600",
    "sg:postcode":"10036",
    "sg:province":"NY",
    "wof:name":"A T C",
    "wof:placetype":"venue"
},
  "geometry": {"coordinates":[-73.997632,40.765585],"type":"Point"}
}