{
  "type": "Feature",
  "properties": {
    "iso:country":"US",
    "sg:address":"616 Jamaica Ave",
    "sg:city":"Brooklyn",
    "sg:classifiers":[
        {
            "category":"Social Services",
            "subcategory":"Child Care",
            "type":"Services"
        }
    ],
    "sg:phone":"+1 718 827 6978",
    "sg:postcode":"11208",
    "sg:province":"NY",
    "wof:name":"Parents United For Better",
    "wof:placetype":"venue"
},
  "geometry": {"coordinates":[-73.88220200000001,40.685359],"type":"Point"}
}