{
  "type": "Feature",
  "properties": {
    "addr:full":"8 Williams St Clinton NY 13323",
    "addr:housenumber":"8",
    "addr:postcode":"13323",
    "addr:street":"Williams St",
    "iso:country":"US",
    "sg:address":"8 Williams St",
    "sg:city":"Clinton",
    "sg:classifiers":[
        {
            "category":"Professional",
            "subcategory":"Business Services",
            "type":"Services"
        }
    ],
    "sg:phone":"+1 315 853 8953",
    "sg:postcode":"13323",
    "sg:province":"NY",
    "sg:tags":[
        "interior",
        "consultant",
        "design",
        "decorator"
    ],
    "wof:name":"Charlotte Grace Interiors",
    "wof:placetype":"venue"
},
  "geometry": {"coordinates":[-75.378713,43.044658],"type":"Point"}
}