{
  "type": "Feature",
  "properties": {
    "addr:full":"335 Gillespie Ave Syracuse NY 13219",
    "addr:housenumber":"335",
    "addr:postcode":"13219",
    "addr:street":"Gillespie Ave",
    "iso:country":"US",
    "sg:address":"335 Gillespie Ave",
    "sg:city":"Syracuse",
    "sg:classifiers":[
        {
            "category":"Wholesale",
            "subcategory":"Vending Machines",
            "type":"Manufacturing & Wholesale Goods"
        }
    ],
    "sg:phone":"+1   ",
    "sg:postcode":"13219",
    "sg:province":"NY",
    "sg:tags":[
        "operator"
    ],
    "wof:name":"Daley Enterprises",
    "wof:placetype":"venue"
},
  "geometry": {"coordinates":[-76.24472,43.05025],"type":"Point"}
}