{
  "type": "Feature",
  "properties": {
    "addr:full":"161 Maine Ave Staten Island NY 10314",
    "addr:housenumber":"161",
    "addr:postcode":"10314",
    "addr:street":"Maine Ave",
    "iso:country":"US",
    "sg:address":"161 Maine Ave",
    "sg:city":"Staten Island",
    "sg:classifiers":[
        {
            "category":"Personal",
            "subcategory":"Barber",
            "type":"Services"
        }
    ],
    "sg:phone":"+1 718 227 0528",
    "sg:postcode":"10314",
    "sg:province":"NY",
    "wof:name":"Dipaolo's Barber Shop",
    "wof:placetype":"venue"
},
  "geometry": {"coordinates":[-74.128941,40.620602],"type":"Point"}
}