{
  "type": "Feature",
  "properties": {
    "addr:full":"5 Brandreth St Ossining NY 10562",
    "addr:housenumber":"5",
    "addr:postcode":"10562",
    "addr:street":"Brandreth St",
    "iso:country":"US",
    "sg:address":"5 Brandreth St",
    "sg:city":"Ossining",
    "sg:classifiers":[
        {
            "category":"Building & Trades",
            "subcategory":"Landscaping Services",
            "type":"Services"
        }
    ],
    "sg:phone":"+1 914 923 9723",
    "sg:postcode":"10562",
    "sg:province":"NY",
    "sg:tags":[
        "landscape",
        "contractor"
    ],
    "wof:name":"Landscaping Jose",
    "wof:placetype":"venue"
},
  "geometry": {"coordinates":[-73.863871,41.162752],"type":"Point"}
}