{
  "type": "Feature",
  "properties": {
    "addr:full":"165 Clermont Ave Brooklyn NY 11205",
    "addr:housenumber":"165",
    "addr:postcode":"11205",
    "addr:street":"Clermont Ave",
    "iso:country":"US",
    "sg:address":"165 Clermont Ave",
    "sg:city":"Brooklyn",
    "sg:classifiers":[
        {
            "category":"Organizations",
            "subcategory":"Religious Organization",
            "type":"Services"
        }
    ],
    "sg:phone":"+1 718 624 6997",
    "sg:postcode":"11205",
    "sg:province":"NY",
    "sg:tags":[
        "church"
    ],
    "wof:name":"Temple Of Thoughts Music",
    "wof:placetype":"venue"
},
  "geometry": {"coordinates":[-73.97048700000001,40.691699],"type":"Point"}
}