{
  "type": "Feature",
  "properties": {
    "addr:full":"2470 Beaumont Ave Bronx NY 10458",
    "addr:housenumber":"2470",
    "addr:postcode":"10458",
    "addr:street":"Beaumont Ave",
    "iso:country":"US",
    "sg:address":"2470 Beaumont Ave",
    "sg:city":"Bronx",
    "sg:classifiers":[
        {
            "category":"Bars & Pubs",
            "type":"Food & Drink"
        }
    ],
    "sg:phone":"+1 718 367 1433",
    "sg:postcode":"10458",
    "sg:province":"NY",
    "sg:tags":[
        "lounge",
        "cocktail"
    ],
    "wof:name":"Rams Lounge",
    "wof:placetype":"venue"
},
  "geometry": {"coordinates":[-73.88366600000001,40.855181],"type":"Point"}
}