{
  "type": "Feature",
  "properties": {
    "addr:full":"10 Zent Ct Cheektowaga NY 14225",
    "addr:housenumber":"10",
    "addr:postcode":"14225",
    "addr:street":"Zent Ct",
    "iso:country":"US",
    "sg:address":"10 Zent Ct",
    "sg:city":"Cheektowaga",
    "sg:classifiers":[
        {
            "category":"Real Estate",
            "subcategory":"Real Estate Agent",
            "type":"Services"
        }
    ],
    "sg:phone":"+1 716 634 5242",
    "sg:postcode":"14225",
    "sg:province":"NY",
    "wof:name":"S K S Real Estate",
    "wof:placetype":"venue"
},
  "geometry": {"coordinates":[-78.751912,42.917307],"type":"Point"}
}