{
  "type": "Feature",
  "properties": {
    "addr:full":"37 Grant St Sloatsburg NY 10974",
    "addr:housenumber":"37",
    "addr:postcode":"10974",
    "addr:street":"Grant St",
    "iso:country":"US",
    "sg:address":"37 Grant St",
    "sg:city":"Sloatsburg",
    "sg:classifiers":[
        {
            "category":"Building & Trades",
            "subcategory":"Construction",
            "type":"Services"
        }
    ],
    "sg:phone":"+1 845 753 2852",
    "sg:postcode":"10974",
    "sg:province":"NY",
    "sg:tags":[
        "house"
    ],
    "wof:name":"Bob Radel Home Improvement",
    "wof:placetype":"venue"
},
  "geometry": {"coordinates":[-74.18825099999999,41.168201],"type":"Point"}
}