{
  "type": "Feature",
  "properties": {
    "iso:country":"US",
    "sg:address":"3830 Richmond Ave",
    "sg:city":"Staten Island",
    "sg:classifiers":[
        {
            "category":"Food & Beverages",
            "subcategory":"Groceries & Convenience Stores",
            "type":"Retail Goods"
        }
    ],
    "sg:phone":"+1   ",
    "sg:postcode":"10312",
    "sg:province":"NY",
    "sg:tags":[
        "independent"
    ],
    "wof:name":"Demonte Salumeria Pork Store",
    "wof:placetype":"venue"
},
  "geometry": {"coordinates":[-74.165736,40.545311],"type":"Point"}
}