{
  "type": "Feature",
  "properties": {
    "addr:full":"204 E Main St Jefferson Valley NY 10535",
    "addr:housenumber":"204",
    "addr:postcode":"10535",
    "addr:street":"E Main St",
    "iso:country":"US",
    "sg:address":"204 E Main St",
    "sg:city":"Jefferson Valley",
    "sg:classifiers":[
        {
            "category":"Insurance",
            "subcategory":"Insurance Agent",
            "type":"Services"
        }
    ],
    "sg:phone":"+1 914 245 8100",
    "sg:postcode":"10535",
    "sg:province":"NY",
    "wof:name":"Allstate Insurance Co",
    "wof:placetype":"venue"
},
  "geometry": {"coordinates":[-73.7872,41.337733],"type":"Point"}
}