{
  "type": "Feature",
  "properties": {
    "addr:full":"450 West 31st Street penthouse New York NY 10001",
    "addr:housenumber":"450",
    "addr:postcode":"10001",
    "addr:street":"West 31St Street",
    "iso:country":"US",
    "sg:address":"450 West 31st Street penthouse",
    "sg:city":"New York",
    "sg:classifiers":[
        {
            "category":"Retail",
            "subcategory":"Event Space",
            "type":"Services"
        }
    ],
    "sg:phone":"+1 212 871 0940",
    "sg:postcode":"10001",
    "sg:province":"NY",
    "sg:tags":[
        "venue"
    ],
    "sg:website":"loft11.com/studio_450.html",
    "wof:name":"Studio 450",
    "wof:placetype":"venue"
},
  "geometry": {"coordinates":[-73.99965400000001,40.752248],"type":"Point"}
}