{
  "type": "Feature",
  "properties": {
    "addr:full":"499 Park Ave New York NY 10022",
    "addr:housenumber":"499",
    "addr:postcode":"10022",
    "addr:street":"Park Ave",
    "iso:country":"US",
    "sg:address":"499 Park Ave",
    "sg:city":"New York",
    "sg:classifiers":[
        {
            "category":"Banks & Credit Unions",
            "subcategory":"Investment Brokerage",
            "type":"Services"
        }
    ],
    "sg:phone":"+1 212 652 3720",
    "sg:postcode":"10022",
    "sg:province":"NY",
    "sg:tags":[
        "investing"
    ],
    "wof:name":"Stevenson Partners",
    "wof:placetype":"venue"
},
  "geometry": {"coordinates":[-73.96959699999999,40.762901],"type":"Point"}
}