{
  "type": "Feature",
  "properties": {
    "addr:full":"136 Sobieski St Buffalo NY 14212",
    "addr:housenumber":"136",
    "addr:postcode":"14212",
    "addr:street":"Sobieski St",
    "iso:country":"US",
    "sg:address":"136 Sobieski St",
    "sg:city":"Buffalo",
    "sg:classifiers":[
        {
            "category":"Health Services",
            "subcategory":"Doctor",
            "type":"Services"
        }
    ],
    "sg:phone":"+1 716 897 9202",
    "sg:postcode":"14212",
    "sg:province":"NY",
    "sg:tags":[
        "medical"
    ],
    "wof:name":"Zulkharnain Medical Services",
    "wof:placetype":"venue"
},
  "geometry": {"coordinates":[-78.832753,42.898785],"type":"Point"}
}