{
  "type": "Feature",
  "properties": {
    "iso:country":"US",
    "sg:address":"149 S 3rd Ave",
    "sg:city":"Mechanicville",
    "sg:classifiers":[
        {
            "category":"Building & Trades",
            "subcategory":"Construction",
            "type":"Services"
        }
    ],
    "sg:phone":"+1 518 664 3622",
    "sg:postcode":"12118",
    "sg:province":"NY",
    "sg:tags":[
        "fence",
        "contractor"
    ],
    "wof:name":"Laurenzo Fence",
    "wof:placetype":"venue"
},
  "geometry": {"coordinates":[-73.692418,42.901683],"type":"Point"}
}