{
  "type": "Feature",
  "properties": {
    "addr:full":"11 Haswell Rd Watervliet NY 12189",
    "addr:housenumber":"11",
    "addr:postcode":"12189",
    "addr:street":"Haswell Rd",
    "iso:country":"US",
    "sg:address":"11 Haswell Rd",
    "sg:city":"Watervliet",
    "sg:classifiers":[
        {
            "category":"Organizations",
            "subcategory":"Non-profit Organization",
            "type":"Services"
        }
    ],
    "sg:phone":"+1 518 273 5143",
    "sg:postcode":"12189",
    "sg:province":"NY",
    "sg:tags":[
        "fund",
        "counselor",
        "raising"
    ],
    "wof:name":"St Coleman's Fund Raising",
    "wof:placetype":"venue"
},
  "geometry": {"coordinates":[-73.71935999999999,42.74713],"type":"Point"}
}