{
  "type": "Feature",
  "properties": {
    "addr:full":"17 Forest Dr Voorheesville NY 12186",
    "addr:housenumber":"17",
    "addr:postcode":"12186",
    "addr:street":"Forest Dr",
    "iso:country":"US",
    "sg:address":"17 Forest Dr",
    "sg:city":"Voorheesville",
    "sg:classifiers":[
        {
            "category":"Home & Garden",
            "subcategory":"Home Furnishings",
            "type":"Retail Goods"
        }
    ],
    "sg:phone":"+1   ",
    "sg:postcode":"12186",
    "sg:province":"NY",
    "wof:name":"Edi Linens N Things",
    "wof:placetype":"venue"
},
  "geometry": {"coordinates":[-73.915336,42.644882],"type":"Point"}
}