{
  "type": "Feature",
  "properties": {
    "addr:full":"172 Main St Massena NY 13662",
    "addr:housenumber":"172",
    "addr:postcode":"13662",
    "addr:street":"Main St",
    "iso:country":"US",
    "sg:address":"172 Main St",
    "sg:city":"Massena",
    "sg:classifiers":[
        {
            "category":"Shopping",
            "subcategory":"Music",
            "type":"Retail Goods"
        }
    ],
    "sg:phone":"+1 315 764 9045",
    "sg:postcode":"13662",
    "sg:province":"NY",
    "sg:tags":[
        "compact",
        "record",
        "disc",
        "tape"
    ],
    "wof:name":"Mc Grath Music",
    "wof:placetype":"venue"
},
  "geometry": {"coordinates":[-74.89170799999999,44.927193],"type":"Point"}
}