{
  "type": "Feature",
  "properties": {
    "addr:full":"125 Myers Corners Rd Wappingers Falls NY 12590",
    "addr:housenumber":"125",
    "addr:postcode":"12590",
    "addr:street":"Myers Corners Rd",
    "iso:country":"US",
    "sg:address":"125 Myers Corners Rd",
    "sg:city":"Wappingers Falls",
    "sg:classifiers":[
        {
            "category":"Home & Garden",
            "subcategory":"Garden Supply",
            "type":"Retail Goods"
        }
    ],
    "sg:phone":"+1 845 298 1825",
    "sg:postcode":"12590",
    "sg:province":"NY",
    "sg:tags":[
        "nursery",
        "gardening"
    ],
    "wof:name":"Red Barn Farm & Nursery",
    "wof:placetype":"venue"
},
  "geometry": {"coordinates":[-73.88829800000001,41.5951],"type":"Point"}
}