{
  "type": "Feature",
  "properties": {
    "addr:full":"44 Court Street Brooklyn NY 11201",
    "addr:housenumber":"44",
    "addr:postcode":"11201",
    "addr:street":"Court Street",
    "iso:country":"US",
    "sg:address":"44 Court Street",
    "sg:city":"Brooklyn",
    "sg:classifiers":[
        {
            "category":"Real Estate",
            "subcategory":"Architect",
            "type":"Services"
        }
    ],
    "sg:phone":"+1 718 237 2786",
    "sg:postcode":"11201",
    "sg:province":"NY",
    "wof:name":"Kiss & Cathcart Architects PC",
    "wof:placetype":"venue"
},
  "geometry": {"coordinates":[-73.99101400000001,40.692538],"type":"Point"}
}