{
  "type": "Feature",
  "properties": {
    "addr:full":"16602 Metcalf Ave Fresh Meadows NY 11365",
    "addr:housenumber":"16602",
    "addr:postcode":"11365",
    "addr:street":"Metcalf Ave",
    "iso:country":"US",
    "sg:address":"16602 Metcalf Ave",
    "sg:city":"Fresh Meadows",
    "sg:classifiers":[
        {
            "category":"Building & Trades",
            "subcategory":"Construction",
            "type":"Services"
        }
    ],
    "sg:phone":"+1 718 886 4648",
    "sg:postcode":"11365",
    "sg:province":"NY",
    "sg:tags":[
        "contractor"
    ],
    "wof:name":"Tupac Construction Corp",
    "wof:placetype":"venue"
},
  "geometry": {"coordinates":[-73.80194299999999,40.747155],"type":"Point"}
}