{
  "type": "Feature",
  "properties": {
    "iso:country":"US",
    "sg:address":"20 S Airmont Rd",
    "sg:city":"Suffern",
    "sg:classifiers":[
        {
            "category":"Local Transit",
            "type":"Transportation"
        }
    ],
    "sg:phone":"+1   ",
    "sg:postcode":"10901",
    "sg:province":"NY",
    "wof:name":"Tlc Ambulette Corp",
    "wof:placetype":"venue"
},
  "geometry": {"coordinates":[-74.11425699999999,41.112274],"type":"Point"}
}