{
  "type": "Feature",
  "properties": {
    "iso:country":"US",
    "sg:address":"70 W 38th St",
    "sg:city":"New York",
    "sg:classifiers":[
        {
            "category":"Professional",
            "type":"Services"
        }
    ],
    "sg:phone":"+1 212 695 1367",
    "sg:postcode":"10018",
    "sg:province":"NY",
    "sg:tags":[
        "establishment"
    ],
    "wof:name":"Ellen Robin Hats",
    "wof:placetype":"venue"
},
  "geometry": {"coordinates":[-73.984253,40.75129],"type":"Point"}
}