{
  "type": "Feature",
  "properties": {
    "addr:full":"748 Stone Church Rd Waterloo NY 13165",
    "addr:housenumber":"748",
    "addr:postcode":"13165",
    "addr:street":"Stone Church Rd",
    "iso:country":"US",
    "sg:address":"748 Stone Church Rd",
    "sg:city":"Waterloo",
    "sg:classifiers":[
        {
            "category":"Home & Garden",
            "subcategory":"Garden Supply",
            "type":"Retail Goods"
        },
        {
            "category":"Farming",
            "subcategory":"Crops",
            "type":"Manufacturing & Wholesale Goods"
        }
    ],
    "sg:phone":"+1 585 202 4583",
    "sg:postcode":"13165",
    "sg:province":"NY",
    "sg:tags":[
        "spraying",
        "dusting",
        "seeding",
        "agricultural"
    ],
    "wof:name":"Sweetpea Farm",
    "wof:placetype":"venue"
},
  "geometry": {"coordinates":[-76.8862,42.988671],"type":"Point"}
}