{
  "type": "Feature",
  "properties": {
    "iso:country":"US",
    "sg:address":"1 E Beach Dr",
    "sg:city":"Glen Cove",
    "sg:classifiers":[
        {
            "category":"Organizations",
            "subcategory":"Religious Organization",
            "type":"Services"
        }
    ],
    "sg:phone":"+1 516 671 0545",
    "sg:postcode":"11542",
    "sg:province":"NY",
    "wof:name":"St Josaphats Monastary",
    "wof:placetype":"venue"
},
  "geometry": {"coordinates":[-73.619619,40.897],"type":"Point"}
}