{
  "type": "Feature",
  "properties": {
    "addr:full":"2319 Frederick Douglass Blvd New York NY 10027",
    "addr:housenumber":"2319",
    "addr:postcode":"10027",
    "addr:street":"Frederick Douglass Blvd",
    "iso:country":"US",
    "sg:address":"2319 Frederick Douglass Blvd",
    "sg:city":"New York",
    "sg:classifiers":[
        {
            "category":"Shopping",
            "subcategory":"Books",
            "type":"Retail Goods"
        }
    ],
    "sg:phone":"+1 212 665 7400",
    "sg:postcode":"10027",
    "sg:province":"NY",
    "sg:tags":[
        "bookstore"
    ],
    "sg:website":"www.huemanbookstore.com/",
    "wof:name":"Hue-Man Bookstore & Cafe",
    "wof:placetype":"venue"
},
  "geometry": {"coordinates":[-73.951409,40.809829],"type":"Point"}
}