{
  "type": "Feature",
  "properties": {
    "addr:full":"12 Roxton Rd Plainview NY 11803",
    "addr:housenumber":"12",
    "addr:postcode":"11803",
    "addr:street":"Roxton Rd",
    "iso:country":"US",
    "sg:address":"12 Roxton Rd",
    "sg:city":"Plainview",
    "sg:classifiers":[
        {
            "category":"Building & Trades",
            "subcategory":"Construction",
            "type":"Services"
        }
    ],
    "sg:phone":"+1 516 931 4675",
    "sg:postcode":"11803",
    "sg:province":"NY",
    "sg:tags":[
        "tile",
        "dealer"
    ],
    "wof:name":"Fanelli Tile & Marble",
    "wof:placetype":"venue"
},
  "geometry": {"coordinates":[-73.491201,40.792676],"type":"Point"}
}