{
  "type": "Feature",
  "properties": {
    "addr:full":"558 Green Pl Woodmere NY 11598",
    "addr:housenumber":"558",
    "addr:postcode":"11598",
    "addr:street":"Green Pl",
    "iso:country":"US",
    "sg:address":"558 Green Pl",
    "sg:city":"Woodmere",
    "sg:classifiers":[
        {
            "category":"Professional",
            "subcategory":"Engineering",
            "type":"Services"
        }
    ],
    "sg:phone":"+1 516 295 1993",
    "sg:postcode":"11598",
    "sg:province":"NY",
    "sg:tags":[
        "engineer"
    ],
    "wof:name":"STSA Inc",
    "wof:placetype":"venue"
},
  "geometry": {"coordinates":[-73.722981,40.638149],"type":"Point"}
}