{
  "type": "Feature",
  "properties": {
    "addr:full":"3393 Union Rd Buffalo NY 14225",
    "addr:housenumber":"3393",
    "addr:postcode":"14225",
    "addr:street":"Union Rd",
    "iso:country":"US",
    "sg:address":"3393 Union Rd",
    "sg:city":"Buffalo",
    "sg:classifiers":[
        {
            "category":"Wholesale",
            "subcategory":"Auto Parts",
            "type":"Manufacturing & Wholesale Goods"
        }
    ],
    "sg:phone":"+1 716 686 0960",
    "sg:postcode":"14225",
    "sg:province":"NY",
    "wof:name":"Hutchins Carquest",
    "wof:placetype":"venue"
},
  "geometry": {"coordinates":[-78.754316,42.906366],"type":"Point"}
}