{
  "type": "Feature",
  "properties": {
    "iso:country":"US",
    "sg:address":"139 Walnut St",
    "sg:city":"Corning",
    "sg:classifiers":[
        {
            "category":"Retail",
            "subcategory":"Funeral Services",
            "type":"Services"
        }
    ],
    "sg:phone":"+1 607 936 9121",
    "sg:postcode":"14830",
    "sg:province":"NY",
    "sg:tags":[
        "parlor"
    ],
    "wof:name":"Beilby Funeral Home",
    "wof:placetype":"venue"
},
  "geometry": {"coordinates":[-77.057288,42.141436],"type":"Point"}
}