{
  "type": "Feature",
  "properties": {
    "addr:full":"189 Ave A New York NY 10009",
    "addr:housenumber":"189",
    "addr:postcode":"10009",
    "addr:street":"Ave A",
    "iso:country":"US",
    "sg:address":"189 Ave A",
    "sg:city":"New York",
    "sg:classifiers":[
        {
            "category":"Retail",
            "subcategory":"Repair Shop",
            "type":"Services"
        }
    ],
    "sg:phone":"+1 212 982 2930",
    "sg:postcode":"10009",
    "sg:province":"NY",
    "sg:tags":[
        "pump",
        "electric",
        "motor"
    ],
    "wof:name":"Daves Electric Motors & Pumps",
    "wof:placetype":"venue"
},
  "geometry": {"coordinates":[-73.98166500000001,40.728624],"type":"Point"}
}