{
  "type": "Feature",
  "properties": {
    "addr:full":"375 Windsor Hwy New Windsor NY 12553",
    "addr:housenumber":"375",
    "addr:postcode":"12553",
    "addr:street":"Windsor Hwy",
    "iso:country":"US",
    "sg:address":"375 Windsor Hwy",
    "sg:city":"New Windsor",
    "sg:classifiers":[
        {
            "category":"Personal",
            "subcategory":"Beauty Salon",
            "type":"Services"
        }
    ],
    "sg:phone":"+1   ",
    "sg:postcode":"12553",
    "sg:province":"NY",
    "sg:tags":[
        "shop"
    ],
    "wof:name":"Radiance Tanning & Nail Studio",
    "wof:placetype":"venue"
},
  "geometry": {"coordinates":[-74.055235,41.457821],"type":"Point"}
}