{
  "type": "Feature",
  "properties": {
    "iso:country":"US",
    "sg:address":"55 Washington St",
    "sg:city":"Poughkeepsie",
    "sg:classifiers":[
        {
            "category":"Autos & Motor Vehicles",
            "subcategory":"Fuel & Gas Station",
            "type":"Retail Goods"
        }
    ],
    "sg:phone":"+1   ",
    "sg:postcode":"12601",
    "sg:province":"NY",
    "sg:tags":[
        "station",
        "gasoline"
    ],
    "wof:name":"A and M Mobile",
    "wof:placetype":"venue"
},
  "geometry": {"coordinates":[-73.9289,41.707978],"type":"Point"}
}