{
  "type": "Feature",
  "properties": {
    "iso:country":"US",
    "sg:address":"146 W 29th St",
    "sg:city":"New York",
    "sg:classifiers":[
        {
            "category":"Wholesale",
            "subcategory":"Non-durable Goods",
            "type":"Manufacturing & Wholesale Goods"
        }
    ],
    "sg:phone":"+1 212 695 8887",
    "sg:postcode":"10001",
    "sg:province":"NY",
    "wof:name":"Belwin Trading Inc",
    "wof:placetype":"venue"
},
  "geometry": {"coordinates":[-73.991935,40.747228],"type":"Point"}
}