{
  "type": "Feature",
  "properties": {
    "addr:full":"2109 Broadway New York NY 10023",
    "addr:housenumber":"2109",
    "addr:postcode":"10023",
    "addr:street":"Broadway",
    "iso:country":"US",
    "sg:address":"2109 Broadway",
    "sg:city":"New York",
    "sg:classifiers":[
        {
            "category":"Real Estate",
            "subcategory":"Real Estate Services",
            "type":"Services"
        }
    ],
    "sg:phone":"+1 212 362 5822",
    "sg:postcode":"10023",
    "sg:province":"NY",
    "sg:tags":[
        "management",
        "property"
    ],
    "wof:name":"Janoff & Olshan Inc",
    "wof:placetype":"venue"
},
  "geometry": {"coordinates":[-73.982298,40.779854],"type":"Point"}
}