{
  "type": "Feature",
  "properties": {
    "iso:country":"US",
    "sg:address":"142 5th Ave",
    "sg:city":"Brooklyn",
    "sg:classifiers":[
        {
            "category":"Personal",
            "subcategory":"Massage",
            "type":"Services"
        },
        {
            "category":"Health Services",
            "subcategory":"Clinic",
            "type":"Services"
        }
    ],
    "sg:phone":"+1 718 623 8888",
    "sg:postcode":"11217",
    "sg:province":"NY",
    "sg:tags":[
        "medical"
    ],
    "sg:website":"www.renewrelaxspa.com",
    "wof:name":"Renew & Relax Spa",
    "wof:placetype":"venue"
},
  "geometry": {"coordinates":[-73.97932400000001,40.678556],"type":"Point"}
}