{
  "type": "Feature",
  "properties": {
    "addr:full":"281 Jewett Ave Staten Island NY 10302",
    "addr:housenumber":"281",
    "addr:postcode":"10302",
    "addr:street":"Jewett Ave",
    "iso:country":"US",
    "sg:address":"281 Jewett Ave",
    "sg:city":"Staten Island",
    "sg:classifiers":[
        {
            "category":"Manufacturing",
            "subcategory":"Printing",
            "type":"Manufacturing & Wholesale Goods"
        }
    ],
    "sg:phone":"+1   ",
    "sg:postcode":"10302",
    "sg:province":"NY",
    "sg:tags":[
        "publishing"
    ],
    "wof:name":"Niceville Publishing",
    "wof:placetype":"venue"
},
  "geometry": {"coordinates":[-74.13025,40.630231],"type":"Point"}
}