{
  "type": "Feature",
  "properties": {
    "addr:full":"81 Trenton Ave Long Beach NY 11561",
    "addr:housenumber":"81",
    "addr:postcode":"11561",
    "addr:street":"Trenton Ave",
    "iso:country":"US",
    "sg:address":"81 Trenton Ave",
    "sg:city":"Long Beach",
    "sg:classifiers":[
        {
            "category":"Building & Trades",
            "subcategory":"Construction",
            "type":"Services"
        }
    ],
    "sg:phone":"+1 516 432 4691",
    "sg:postcode":"11561",
    "sg:province":"NY",
    "sg:tags":[
        "hanging",
        "contractor"
    ],
    "wof:name":"Z Brothers Painting Plus",
    "wof:placetype":"venue"
},
  "geometry": {"coordinates":[-73.70215399999999,40.587206],"type":"Point"}
}