{
  "type": "Feature",
  "properties": {
    "iso:country":"US",
    "sg:address":"16 Hillside Dr",
    "sg:city":"Apalachin",
    "sg:classifiers":[
        {
            "category":"Shopping",
            "subcategory":"Gifts & Souvenirs",
            "type":"Retail Goods"
        }
    ],
    "sg:phone":"+1   ",
    "sg:postcode":"13732",
    "sg:province":"NY",
    "wof:name":"Crystal Rose Gifts & Collectib",
    "wof:placetype":"venue"
},
  "geometry": {"coordinates":[-76.119598,42.05647],"type":"Point"}
}