{
  "type": "Feature",
  "properties": {
    "addr:full":"589 5th Ave New York NY 10017",
    "addr:housenumber":"589",
    "addr:postcode":"10017",
    "addr:street":"5Th Ave",
    "iso:country":"US",
    "sg:address":"589 5th Ave",
    "sg:city":"New York",
    "sg:classifiers":[
        {
            "category":"Wholesale",
            "subcategory":"Machinery & Supplies",
            "type":"Manufacturing & Wholesale Goods"
        }
    ],
    "sg:phone":"+1 212 888 8313",
    "sg:postcode":"10017",
    "sg:province":"NY",
    "sg:tags":[
        "industrial"
    ],
    "wof:name":"Bendiam",
    "wof:placetype":"venue"
},
  "geometry": {"coordinates":[-73.979024,40.756032],"type":"Point"}
}