{
  "type": "Feature",
  "properties": {
    "addr:full":"46th St and Broadway New York NY 10036",
    "addr:postcode":"10036",
    "addr:street":"46Th St And Broadway",
    "iso:country":"US",
    "sg:address":"46th St and Broadway",
    "sg:city":"New York",
    "sg:classifiers":[
        {
            "category":"Restaurant",
            "type":"Food & Drink"
        }
    ],
    "sg:postcode":"10036",
    "sg:province":"NY",
    "sg:tags":[
        "flavor",
        "local"
    ],
    "sg:website":"www.nakedcowgirlny.com/",
    "wof:name":"Naked Cowgirl",
    "wof:placetype":"venue"
},
  "geometry": {"coordinates":[-73.98533999999999,40.75869],"type":"Point"}
}