{
  "type": "Feature",
  "properties": {
    "iso:country":"US",
    "sg:address":"53 Hearst St",
    "sg:city":"Yonkers",
    "sg:classifiers":[
        {
            "category":"Home & Garden",
            "subcategory":"Carpets & Floor Coverings",
            "type":"Retail Goods"
        }
    ],
    "sg:phone":"+1   ",
    "sg:postcode":"10703",
    "sg:province":"NY",
    "wof:name":"F & L Floorworks Inc",
    "wof:placetype":"venue"
},
  "geometry": {"coordinates":[-73.87096099999999,40.974514],"type":"Point"}
}