{
  "type": "Feature",
  "properties": {
    "iso:country":"US",
    "sg:address":"505 Boston Post Rd",
    "sg:city":"Port Chester",
    "sg:classifiers":[
        {
            "category":"Shopping",
            "subcategory":"Jewelry",
            "type":"Retail Goods"
        }
    ],
    "sg:phone":"+1 914 939 0350",
    "sg:postcode":"10573",
    "sg:province":"NY",
    "wof:name":"Tyson",
    "wof:placetype":"venue"
},
  "geometry": {"coordinates":[-73.675817,40.993165],"type":"Point"}
}