{
  "type": "Feature",
  "properties": {
    "addr:full":"188 21st St Brooklyn NY 11232",
    "addr:housenumber":"188",
    "addr:postcode":"11232",
    "addr:street":"21St St",
    "iso:country":"US",
    "sg:address":"188 21st St",
    "sg:city":"Brooklyn",
    "sg:classifiers":[
        {
            "category":"Wholesale",
            "subcategory":"Durable Goods & Equipment",
            "type":"Manufacturing & Wholesale Goods"
        }
    ],
    "sg:phone":"+1 718 768 8800",
    "sg:postcode":"11232",
    "sg:province":"NY",
    "sg:tags":[
        "importer"
    ],
    "sg:website":"www.hpi.com",
    "wof:name":"HPI Intl",
    "wof:placetype":"venue"
},
  "geometry": {"coordinates":[-73.993798,40.661554],"type":"Point"}
}