{
  "type": "Feature",
  "properties": {
    "iso:country":"US",
    "sg:address":"729 Eagle Ave",
    "sg:city":"Bronx",
    "sg:classifiers":[
        {
            "category":"Shopping",
            "subcategory":"Computers & Home Electronics",
            "type":"Retail Goods"
        }
    ],
    "sg:phone":"+1 718 696 3474",
    "sg:postcode":"10455",
    "sg:province":"NY",
    "sg:tags":[
        "installation",
        "theatre"
    ],
    "sg:website":"WWW.1080HD.COM",
    "wof:name":"Equipped Home Theater",
    "wof:placetype":"venue"
},
  "geometry": {"coordinates":[-73.910077,40.818933],"type":"Point"}
}