{
  "type": "Feature",
  "properties": {
    "addr:full":"1600 New Hwy Farmingdale NY 11735",
    "addr:housenumber":"1600",
    "addr:postcode":"11735",
    "addr:street":"New Hwy",
    "iso:country":"US",
    "sg:address":"1600 New Hwy",
    "sg:city":"Farmingdale",
    "sg:classifiers":[
        {
            "category":"Social Services",
            "type":"Services"
        }
    ],
    "sg:phone":"+1 631 225 2444",
    "sg:postcode":"11735",
    "sg:province":"NY",
    "sg:tags":[
        "organization",
        "welfare"
    ],
    "wof:name":"People With Aids Coalition",
    "wof:placetype":"venue"
},
  "geometry": {"coordinates":[-73.413172,40.739466],"type":"Point"}
}