{
  "type": "Feature",
  "properties": {
    "addr:full":"70 W 36th Street New York NY 10018",
    "addr:housenumber":"70",
    "addr:postcode":"10018",
    "addr:street":"W 36Th Street",
    "iso:country":"US",
    "sg:address":"70 W 36th Street",
    "sg:city":"New York",
    "sg:classifiers":[
        {
            "category":"Retail",
            "subcategory":"Portrait Studio",
            "type":"Services"
        },
        {
            "category":"Professional",
            "subcategory":"Art Services",
            "type":"Services"
        }
    ],
    "sg:phone":"+1 212 268 5680",
    "sg:postcode":"10018",
    "sg:province":"NY",
    "sg:tags":[
        "photographer",
        "photography",
        "store"
    ],
    "wof:name":"Firebird Production",
    "wof:placetype":"venue"
},
  "geometry": {"coordinates":[-73.98619600000001,40.750929],"type":"Point"}
}