{
  "type": "Feature",
  "properties": {
    "addr:full":"2541 Richmond Ter Staten Island NY 10303",
    "addr:housenumber":"2541",
    "addr:postcode":"10303",
    "addr:street":"Richmond Ter",
    "iso:country":"US",
    "sg:address":"2541 Richmond Ter",
    "sg:city":"Staten Island",
    "sg:classifiers":[
        {
            "category":"Retail",
            "subcategory":"Auto Repair",
            "type":"Services"
        }
    ],
    "sg:phone":"+1 718 447 8910",
    "sg:postcode":"10303",
    "sg:province":"NY",
    "sg:tags":[
        "truck"
    ],
    "wof:name":"Richmond Truck & Auto Repair",
    "wof:placetype":"venue"
},
  "geometry": {"coordinates":[-74.145326,40.637973],"type":"Point"}
}