{
  "type": "Feature",
  "properties": {
    "addr:full":"41 Wicks Rd Brentwood NY 11717",
    "addr:housenumber":"41",
    "addr:postcode":"11717",
    "addr:street":"Wicks Rd",
    "iso:country":"US",
    "sg:address":"41 Wicks Rd",
    "sg:city":"Brentwood",
    "sg:classifiers":[
        {
            "category":"Cinema",
            "subcategory":"Movie Rental",
            "type":"Entertainment"
        }
    ],
    "sg:phone":"+1 631 273 5707",
    "sg:postcode":"11717",
    "sg:province":"NY",
    "sg:tags":[
        "leasing",
        "video",
        "disc",
        "tape"
    ],
    "sg:website":"www.blockbuster.com",
    "wof:name":"Blockbuster Video",
    "wof:placetype":"venue"
},
  "geometry": {"coordinates":[-73.259759,40.777202],"type":"Point"}
}