{
  "type": "Feature",
  "properties": {
    "iso:country":"US",
    "sg:address":"23 Stevenson Rd",
    "sg:city":"Queensbury",
    "sg:classifiers":[
        {
            "category":"Building & Trades",
            "subcategory":"Landscaping Services",
            "type":"Services"
        }
    ],
    "sg:phone":"+1 518 798 3608",
    "sg:postcode":"12804",
    "sg:province":"NY",
    "wof:name":"Mikes Lawn Care",
    "wof:placetype":"venue"
},
  "geometry": {"coordinates":[-73.625979,43.424342],"type":"Point"}
}