{
  "type": "Feature",
  "properties": {
    "iso:country":"US",
    "sg:address":"1615 Pitkin Ave",
    "sg:city":"Brooklyn",
    "sg:classifiers":[
        {
            "category":"Shopping",
            "subcategory":"Shoes",
            "type":"Retail Goods"
        }
    ],
    "sg:phone":"+1 718 485 2301",
    "sg:postcode":"11212",
    "sg:province":"NY",
    "sg:tags":[
        "store"
    ],
    "wof:name":"Stars Shoes",
    "wof:placetype":"venue"
},
  "geometry": {"coordinates":[-73.913752,40.669378],"type":"Point"}
}