{
  "type": "Feature",
  "properties": {
    "addr:full":"52 W 12th St New York NY 10011",
    "addr:housenumber":"52",
    "addr:postcode":"10011",
    "addr:street":"W 12Th St",
    "iso:country":"US",
    "sg:address":"52 W 12th St",
    "sg:city":"New York",
    "sg:classifiers":[
        {
            "category":"Health Services",
            "subcategory":"Doctor",
            "type":"Services"
        }
    ],
    "sg:phone":"+1 212 989 9728",
    "sg:postcode":"10011",
    "sg:province":"NY",
    "wof:name":"Freudenthal Gideon Dr",
    "wof:placetype":"venue"
},
  "geometry": {"coordinates":[-73.996498,40.735401],"type":"Point"}
}