{
  "type": "Feature",
  "properties": {
    "addr:full":"1865 Stewart Ave New Hyde Park NY 11040",
    "addr:housenumber":"1865",
    "addr:postcode":"11040",
    "addr:street":"Stewart Ave",
    "iso:country":"US",
    "sg:address":"1865 Stewart Ave",
    "sg:city":"New Hyde Park",
    "sg:classifiers":[
        {
            "category":"Professional",
            "subcategory":"Advertising",
            "type":"Services"
        }
    ],
    "sg:phone":"+1 516 775 5704",
    "sg:postcode":"11040",
    "sg:province":"NY",
    "sg:tags":[
        "installation",
        "display"
    ],
    "wof:name":"Lucky Window Dressing",
    "wof:placetype":"venue"
},
  "geometry": {"coordinates":[-73.70049299999999,40.745749],"type":"Point"}
}