{
  "type": "Feature",
  "properties": {
    "addr:full":"1286 E Delavan Ave Buffalo NY 14215",
    "addr:housenumber":"1286",
    "addr:postcode":"14215",
    "addr:street":"E Delavan Ave",
    "iso:country":"US",
    "sg:address":"1286 E Delavan Ave",
    "sg:city":"Buffalo",
    "sg:classifiers":[
        {
            "category":"Personal",
            "subcategory":"Beauty Salon",
            "type":"Services"
        }
    ],
    "sg:phone":"+1 716 894 8737",
    "sg:postcode":"14215",
    "sg:province":"NY",
    "wof:name":"Studio U",
    "wof:placetype":"venue"
},
  "geometry": {"coordinates":[-78.808718,42.9227],"type":"Point"}
}