{
  "type": "Feature",
  "properties": {
    "iso:country":"US",
    "sg:address":"1445 Park Ave",
    "sg:city":"New York",
    "sg:classifiers":[
        {
            "category":"Personal",
            "type":"Services"
        }
    ],
    "sg:phone":"+1 646 237 1342",
    "sg:postcode":"10029",
    "sg:province":"NY",
    "sg:tags":[
        "towing"
    ],
    "wof:name":"Rapid Tow Service",
    "wof:placetype":"venue"
},
  "geometry": {"coordinates":[-73.9478,40.7929],"type":"Point"}
}