{
  "type": "Feature",
  "properties": {
    "addr:full":"26 Main St Potsdam NY 13676",
    "addr:housenumber":"26",
    "addr:postcode":"13676",
    "addr:street":"Main St",
    "iso:country":"US",
    "sg:address":"26 Main St",
    "sg:city":"Potsdam",
    "sg:classifiers":[
        {
            "category":"Place Of Worship",
            "subcategory":"Church",
            "type":"Public Place"
        },
        {
            "category":"Place Of Worship",
            "type":"Public Place"
        }
    ],
    "sg:phone":"+1 315 265 7474",
    "sg:postcode":"13676",
    "sg:province":"NY",
    "sg:tags":[
        "churches-methodist"
    ],
    "sg:website":"http://www.umc.org",
    "wof:name":"United Methodist Church",
    "wof:placetype":"venue"
},
  "geometry": {"coordinates":[-74.97708900000001,44.610241],"type":"Point"}
}