{
  "type": "Feature",
  "properties": {
    "addr:full":"112 Colonial Rd West Babylon NY 11704",
    "addr:housenumber":"112",
    "addr:postcode":"11704",
    "addr:street":"Colonial Rd",
    "iso:country":"US",
    "sg:address":"112 Colonial Rd",
    "sg:city":"West Babylon",
    "sg:classifiers":[
        {
            "category":"Professional",
            "subcategory":"Business Services",
            "type":"Services"
        }
    ],
    "sg:phone":"+1 631 422 9647",
    "sg:postcode":"11704",
    "sg:province":"NY",
    "wof:name":"Easy Credit",
    "wof:placetype":"venue"
},
  "geometry": {"coordinates":[-73.340476,40.71939],"type":"Point"}
}