{
  "type": "Feature",
  "properties": {
    "iso:country":"US",
    "sg:address":"13 Sandra Ave",
    "sg:city":"Plattsburgh",
    "sg:classifiers":[
        {
            "category":"Professional",
            "subcategory":"Management & Consulting",
            "type":"Services"
        }
    ],
    "sg:phone":"+1 518 562 1462",
    "sg:postcode":"12901",
    "sg:province":"NY",
    "sg:tags":[
        "consultant",
        "safety"
    ],
    "wof:name":"E & S Landrock Consulting",
    "wof:placetype":"venue"
},
  "geometry": {"coordinates":[-73.478008,44.689291],"type":"Point"}
}