{
  "type": "Feature",
  "properties": {
    "addr:full":"158 Chenango St Buffalo NY 14213",
    "addr:housenumber":"158",
    "addr:postcode":"14213",
    "addr:street":"Chenango St",
    "iso:country":"US",
    "sg:address":"158 Chenango St",
    "sg:city":"Buffalo",
    "sg:classifiers":[
        {
            "category":"Real Estate",
            "subcategory":"Developer",
            "type":"Services"
        }
    ],
    "sg:phone":"+1 716 884 8059",
    "sg:postcode":"14213",
    "sg:province":"NY",
    "wof:name":"Delta Development St John Bosc",
    "wof:placetype":"venue"
},
  "geometry": {"coordinates":[-78.885625,42.914774],"type":"Point"}
}