{
  "type": "Feature",
  "properties": {
    "addr:full":"2950 Express Dr S Islandia NY 11749",
    "addr:postcode":"2950;11749",
    "addr:street":"Express Dr S Islandia",
    "iso:country":"US",
    "sg:address":"2950 Express Dr S",
    "sg:city":"Islandia",
    "sg:classifiers":[
        {
            "category":"Sports & Exercise",
            "subcategory":"Gym",
            "type":"Entertainment"
        }
    ],
    "sg:phone":"+1 631 234 3098",
    "sg:postcode":"11749",
    "sg:province":"NY",
    "sg:tags":[
        "trainer"
    ],
    "wof:name":"United Healthcare",
    "wof:placetype":"venue"
},
  "geometry": {"coordinates":[-73.18981100000001,40.808432],"type":"Point"}
}