{
  "type": "Feature",
  "properties": {
    "addr:full":"225 W 35th St 2nd Fl New York NY 10001",
    "addr:housenumber":"225",
    "addr:postcode":"10001",
    "addr:street":"W 35Th St",
    "iso:country":"US",
    "sg:address":"225 W 35th St 2nd Fl",
    "sg:city":"New York",
    "sg:classifiers":[
        {
            "category":"Health Services",
            "subcategory":"Chiropractor",
            "type":"Services"
        }
    ],
    "sg:phone":"+1 212 239 4544",
    "sg:postcode":"10001",
    "sg:province":"NY",
    "sg:website":"www.ODonohueChiropractic.com",
    "wof:name":"O'Donohue Chiropractic",
    "wof:placetype":"venue"
},
  "geometry": {"coordinates":[-73.99102600000001,40.752287],"type":"Point"}
}