{
  "type": "Feature",
  "properties": {
    "addr:full":"119 Tyler Ct Syracuse NY 13202",
    "addr:housenumber":"119",
    "addr:postcode":"13202",
    "addr:street":"Tyler Ct",
    "iso:country":"US",
    "sg:address":"119 Tyler Ct",
    "sg:city":"Syracuse",
    "sg:classifiers":[
        {
            "category":"Building & Trades",
            "subcategory":"Construction",
            "type":"Services"
        }
    ],
    "sg:phone":"+1 315 422 9802",
    "sg:postcode":"13202",
    "sg:province":"NY",
    "sg:tags":[
        "insulation",
        "heat",
        "contractor"
    ],
    "wof:name":"William Coffin Inc",
    "wof:placetype":"venue"
},
  "geometry": {"coordinates":[-76.143038,43.04228],"type":"Point"}
}