{
  "type": "Feature",
  "properties": {
    "iso:country":"US",
    "sg:address":"411 Cambridge Ave",
    "sg:city":"Syracuse",
    "sg:classifiers":[
        {
            "category":"Home & Garden",
            "subcategory":"Building Materials",
            "type":"Retail Goods"
        },
        {
            "category":"Building & Trades",
            "subcategory":"Construction",
            "type":"Services"
        },
        {
            "category":"Manufacturing",
            "subcategory":"Building Materials",
            "type":"Manufacturing & Wholesale Goods"
        }
    ],
    "sg:phone":"+1 315 454 3291",
    "sg:postcode":"13208",
    "sg:province":"NY",
    "sg:tags":[
        "roofing",
        "industrial",
        "sheet",
        "work",
        "metal",
        "contractor",
        "downspouts",
        "gutter",
        "contractors-commercial"
    ],
    "sg:website":"http://diamondroofing.com",
    "wof:name":"Diamond Roofing CO Inc",
    "wof:placetype":"venue"
},
  "geometry": {"coordinates":[-76.14099299999999,43.091525],"type":"Point"}
}