{
  "type": "Feature",
  "properties": {
    "iso:country":"US",
    "sg:address":"638 Crows Nest Ln",
    "sg:city":"Macedon",
    "sg:classifiers":[
        {
            "category":"Retail",
            "subcategory":"Auto Repair",
            "type":"Services"
        }
    ],
    "sg:phone":"+1 315 986 2935",
    "sg:postcode":"14502",
    "sg:province":"NY",
    "sg:tags":[
        "body",
        "automobile",
        "painting",
        "repairing"
    ],
    "wof:name":"Concours Classic Motorcars",
    "wof:placetype":"venue"
},
  "geometry": {"coordinates":[-77.34787,43.12595],"type":"Point"}
}