{
  "type": "Feature",
  "properties": {
    "addr:full":"3828 Broadway New York NY 10032",
    "addr:housenumber":"3828",
    "addr:postcode":"10032",
    "addr:street":"Broadway",
    "iso:country":"US",
    "sg:address":"3828 Broadway",
    "sg:city":"New York",
    "sg:classifiers":[
        {
            "category":"Personal",
            "subcategory":"Barber",
            "type":"Services"
        }
    ],
    "sg:phone":"+1 212 923 9796",
    "sg:postcode":"10032",
    "sg:province":"NY",
    "sg:tags":[
        "shop"
    ],
    "wof:name":"Odalis Barber Shop",
    "wof:placetype":"venue"
},
  "geometry": {"coordinates":[-73.94362,40.835584],"type":"Point"}
}