{
  "type": "Feature",
  "properties": {
    "iso:country":"US",
    "sg:address":"10900 Erie Rd",
    "sg:city":"Irving",
    "sg:classifiers":[
        {
            "category":"Insurance",
            "subcategory":"Insurance Agent",
            "type":"Services"
        }
    ],
    "sg:phone":"+1 716 549 1171",
    "sg:postcode":"14081",
    "sg:province":"NY",
    "wof:name":"Fred Brinkman Agency",
    "wof:placetype":"venue"
},
  "geometry": {"coordinates":[-79.106171,42.580827],"type":"Point"}
}