{
  "type": "Feature",
  "properties": {
    "addr:full":"448 Bedford Rd Ste 1 Armonk NY 10504",
    "addr:housenumber":"448",
    "addr:postcode":"10504",
    "addr:street":"Bedford Rd Ste 1",
    "iso:country":"US",
    "sg:address":"448 Bedford Rd Ste 1",
    "sg:city":"Armonk",
    "sg:classifiers":[
        {
            "category":"Organizations",
            "subcategory":"Religious Organization",
            "type":"Services"
        }
    ],
    "sg:phone":"+1 914 273 1207",
    "sg:postcode":"10504",
    "sg:province":"NY",
    "wof:name":"Hillside Church",
    "wof:placetype":"venue"
},
  "geometry": {"coordinates":[-73.68409699999999,41.145599],"type":"Point"}
}