{
  "type": "Feature",
  "properties": {
    "addr:full":"219 Beach 100th St Far Rockaway NY 11694",
    "addr:housenumber":"219",
    "addr:postcode":"11694",
    "addr:street":"Beach 100Th St",
    "iso:country":"US",
    "sg:address":"219 Beach 100th St",
    "sg:city":"Far Rockaway",
    "sg:classifiers":[
        {
            "category":"Real Estate",
            "subcategory":"Architect",
            "type":"Services"
        }
    ],
    "sg:phone":"+1 718 318 2144",
    "sg:postcode":"11694",
    "sg:province":"NY",
    "wof:name":"American Architectural Entrncs",
    "wof:placetype":"venue"
},
  "geometry": {"coordinates":[-73.821628,40.584541],"type":"Point"}
}