{
  "type": "Feature",
  "properties": {
    "addr:full":"556 Bay St Rochester NY 14609",
    "addr:housenumber":"556",
    "addr:postcode":"14609",
    "addr:street":"Bay St",
    "iso:country":"US",
    "sg:address":"556 Bay St",
    "sg:city":"Rochester",
    "sg:classifiers":[
        {
            "category":"Retail",
            "subcategory":"Laundry & Dry Cleaning",
            "type":"Services"
        }
    ],
    "sg:phone":"+1 585 482 9533",
    "sg:postcode":"14609",
    "sg:province":"NY",
    "sg:tags":[
        "cleaners"
    ],
    "wof:name":"Royal Cleaners & Launderers",
    "wof:placetype":"venue"
},
  "geometry": {"coordinates":[-77.579312,43.171094],"type":"Point"}
}