{
  "type": "Feature",
  "properties": {
    "iso:country":"US",
    "sg:address":"204 Fulton Ave",
    "sg:city":"Rochester",
    "sg:classifiers":[
        {
            "category":"Building & Trades",
            "subcategory":"Electrical",
            "type":"Services"
        }
    ],
    "sg:phone":"+1 585 278 7121",
    "sg:postcode":"14613",
    "sg:province":"NY",
    "sg:tags":[
        "electrician"
    ],
    "wof:name":"Jh Electric",
    "wof:placetype":"venue"
},
  "geometry": {"coordinates":[-77.631912,43.175743],"type":"Point"}
}