{
  "type": "Feature",
  "properties": {
    "iso:country":"US",
    "sg:address":"18 Shorn Dr",
    "sg:city":"Blauvelt",
    "sg:classifiers":[
        {
            "category":"Professional",
            "subcategory":"Accounting & Tax Preparation",
            "type":"Services"
        }
    ],
    "sg:phone":"+1 845 359 4104",
    "sg:postcode":"10913",
    "sg:province":"NY",
    "wof:name":"Steven R Strauhs CPA PC",
    "wof:placetype":"venue"
},
  "geometry": {"coordinates":[-73.957476,41.069647],"type":"Point"}
}