{
  "type": "Feature",
  "properties": {
    "iso:country":"US",
    "sg:address":"8 N Manheim Blvd",
    "sg:city":"New Paltz",
    "sg:classifiers":[
        {
            "category":"Organizations",
            "subcategory":"Religious Organization",
            "type":"Services"
        }
    ],
    "sg:phone":"+1 845 255 5791",
    "sg:postcode":"12561",
    "sg:province":"NY",
    "sg:tags":[
        "church"
    ],
    "wof:name":"Friends-Religious Society",
    "wof:placetype":"venue"
},
  "geometry": {"coordinates":[-74.077293,41.747155],"type":"Point"}
}