{
  "type": "Feature",
  "properties": {
    "addr:full":"31 Burd St Nyack NY 10960",
    "addr:housenumber":"31",
    "addr:postcode":"10960",
    "addr:street":"Burd St",
    "iso:country":"US",
    "sg:address":"31 Burd St",
    "sg:city":"Nyack",
    "sg:classifiers":[
        {
            "category":"Shopping",
            "subcategory":"Used Merchandise",
            "type":"Retail Goods"
        }
    ],
    "sg:phone":"+1 845 353 8573",
    "sg:postcode":"10960",
    "sg:province":"NY",
    "sg:tags":[
        "antique"
    ],
    "wof:name":"USIS Training Ctr",
    "wof:placetype":"venue"
},
  "geometry": {"coordinates":[-73.916273,41.089832],"type":"Point"}
}