{
  "type": "Feature",
  "properties": {
    "addr:full":"19 La Rue Dr Huntington NY 11743",
    "addr:housenumber":"19",
    "addr:postcode":"11743",
    "addr:street":"La Rue Dr",
    "iso:country":"US",
    "sg:address":"19 La Rue Dr",
    "sg:city":"Huntington",
    "sg:classifiers":[
        {
            "category":"Professional",
            "subcategory":"Lawyer & Legal Services",
            "type":"Services"
        }
    ],
    "sg:phone":"+1 631 923 0975",
    "sg:postcode":"11743",
    "sg:province":"NY",
    "wof:name":"Susan Carman Esq",
    "wof:placetype":"venue"
},
  "geometry": {"coordinates":[-73.437642,40.88491],"type":"Point"}
}