{
  "type": "Feature",
  "properties": {
    "iso:country":"US",
    "sg:address":"41 N 7th St",
    "sg:city":"Hudson",
    "sg:classifiers":[
        {
            "category":"Food & Beverages",
            "subcategory":"Bakery",
            "type":"Retail Goods"
        }
    ],
    "sg:phone":"+1 518 828 8979",
    "sg:postcode":"12534",
    "sg:province":"NY",
    "sg:tags":[
        "bagel"
    ],
    "wof:name":"Bagel Time",
    "wof:placetype":"venue"
},
  "geometry": {"coordinates":[-73.78225999999999,42.248381],"type":"Point"}
}