{
  "type": "Feature",
  "properties": {
    "addr:full":"812 Proctor Ave Ogdensburg NY 13669",
    "addr:housenumber":"812",
    "addr:postcode":"13669",
    "addr:street":"Proctor Ave",
    "iso:country":"US",
    "sg:address":"812 Proctor Ave",
    "sg:city":"Ogdensburg",
    "sg:classifiers":[
        {
            "category":"Professional",
            "subcategory":"Engineering",
            "type":"Services"
        }
    ],
    "sg:phone":"+1   ",
    "sg:postcode":"13669",
    "sg:province":"NY",
    "wof:name":"H D R Technical Services",
    "wof:placetype":"venue"
},
  "geometry": {"coordinates":[-75.44975700000001,44.716428],"type":"Point"}
}