{
  "type": "Feature",
  "properties": {
    "addr:full":"4465 21st St Long Island City NY 11101",
    "addr:housenumber":"4465",
    "addr:postcode":"11101",
    "addr:street":"21St St",
    "iso:country":"US",
    "sg:address":"4465 21st St",
    "sg:city":"Long Island City",
    "sg:classifiers":[
        {
            "category":"Food & Beverages",
            "subcategory":"Groceries & Convenience Stores",
            "type":"Retail Goods"
        }
    ],
    "sg:phone":"+1 718 361 7471",
    "sg:postcode":"11101",
    "sg:province":"NY",
    "sg:website":"www.ctownsupermarkets.com",
    "wof:name":"J & M Food Inc",
    "wof:placetype":"venue"
},
  "geometry": {"coordinates":[-73.94740299999999,40.747601],"type":"Point"}
}