{
  "type": "Feature",
  "properties": {
    "iso:country":"US",
    "sg:address":"222 S Westchester Ave",
    "sg:city":"White Plains",
    "sg:classifiers":[
        {
            "category":"Shopping",
            "type":"Retail Goods"
        }
    ],
    "sg:phone":"+1 914 328 2231",
    "sg:postcode":"10604",
    "sg:province":"NY",
    "sg:tags":[
        "orthopedic",
        "appliance",
        "prosthetic",
        "supply"
    ],
    "sg:website":"www.hanger.com",
    "wof:name":"Hanger Prosthetics & Orthotics",
    "wof:placetype":"venue"
},
  "geometry": {"coordinates":[-73.749948,41.030477],"type":"Point"}
}