{
  "type": "Feature",
  "properties": {
    "iso:country":"US",
    "sg:address":"243 Warren St",
    "sg:city":"Hudson",
    "sg:classifiers":[
        {
            "category":"Shopping",
            "subcategory":"Gifts & Souvenirs",
            "type":"Retail Goods"
        }
    ],
    "sg:phone":"+1 518 671 6132",
    "sg:postcode":"12534",
    "sg:province":"NY",
    "sg:tags":[
        "shop"
    ],
    "wof:name":"Mary's Marbles",
    "wof:placetype":"venue"
},
  "geometry": {"coordinates":[-73.792699,42.253825],"type":"Point"}
}