{
  "type": "Feature",
  "properties": {
    "addr:full":"500 City Island Ave Bronx NY 10464",
    "addr:housenumber":"500",
    "addr:postcode":"10464",
    "addr:street":"City Island Ave",
    "iso:country":"US",
    "sg:address":"500 City Island Ave",
    "sg:city":"Bronx",
    "sg:phone":"+1 718 885 0700",
    "sg:postcode":"10464",
    "sg:province":"NY",
    "sg:website":"http://www.ohanahibachirestaurant.com/",
    "wof:name":"Ohana",
    "wof:placetype":"venue"
},
  "geometry": {"coordinates":[-73.789062,40.85199],"type":"Point"}
}