{
  "type": "Feature",
  "properties": {
    "iso:country":"US",
    "sg:address":"900 South Ave",
    "sg:city":"Staten Island",
    "sg:classifiers":[
        {
            "category":"Professional",
            "subcategory":"Employment Agencies",
            "type":"Services"
        }
    ],
    "sg:phone":"+1 718 568 3666",
    "sg:postcode":"10314",
    "sg:province":"NY",
    "wof:name":"Career Capital",
    "wof:placetype":"venue"
},
  "geometry": {"coordinates":[-74.174301,40.614101],"type":"Point"}
}