{
  "type": "Feature",
  "properties": {
    "iso:country":"US",
    "sg:address":"45 W 10 St",
    "sg:city":"New York",
    "sg:classifiers":[
        {
            "category":"Real Estate",
            "subcategory":"Real Estate Agent",
            "type":"Services"
        }
    ],
    "sg:phone":"+1 212 307 0500",
    "sg:postcode":"10011",
    "sg:province":"NY",
    "sg:tags":[
        "management"
    ],
    "wof:name":"Marathon Management Inc",
    "wof:placetype":"venue"
},
  "geometry": {"coordinates":[-73.99758,40.734244],"type":"Point"}
}