{
  "type": "Feature",
  "properties": {
    "addr:full":"27 Old Pine Ln Rochester NY 14615",
    "addr:housenumber":"27",
    "addr:postcode":"14615",
    "addr:street":"Old Pine Ln",
    "iso:country":"US",
    "sg:address":"27 Old Pine Ln",
    "sg:city":"Rochester",
    "sg:classifiers":[
        {
            "category":"Arts & Performance",
            "subcategory":"Theater",
            "type":"Entertainment"
        }
    ],
    "sg:phone":"+1 585 621 6561",
    "sg:postcode":"14615",
    "sg:province":"NY",
    "sg:tags":[
        "entertainer"
    ],
    "wof:name":"Organist Unlimited",
    "wof:placetype":"venue"
},
  "geometry": {"coordinates":[-77.672607,43.227514],"type":"Point"}
}