{
  "type": "Feature",
  "properties": {
    "addr:full":"359 E 138th St Bronx NY 10454",
    "addr:housenumber":"359",
    "addr:postcode":"10454",
    "addr:street":"E 138Th St",
    "iso:country":"US",
    "sg:address":"359 E 138th St",
    "sg:city":"Bronx",
    "sg:classifiers":[
        {
            "category":"Restaurant",
            "type":"Food & Drink"
        }
    ],
    "sg:postcode":"10454",
    "sg:province":"NY",
    "sg:tags":[
        "mexican"
    ],
    "wof:name":"Taco Mix",
    "wof:placetype":"venue"
},
  "geometry": {"coordinates":[-73.92386500000001,40.809818],"type":"Point"}
}