{
  "type": "Feature",
  "properties": {
    "addr:full":"1176 Portion Rd Holtsville NY 11742",
    "addr:housenumber":"1176",
    "addr:postcode":"11742",
    "addr:street":"Portion Rd",
    "iso:country":"US",
    "sg:address":"1176 Portion Rd",
    "sg:city":"Holtsville",
    "sg:classifiers":[
        {
            "category":"Professional",
            "subcategory":"Lawyer & Legal Services",
            "type":"Services"
        }
    ],
    "sg:phone":"+1 631 451 7900",
    "sg:postcode":"11742",
    "sg:province":"NY",
    "sg:tags":[
        "attorney"
    ],
    "wof:name":"Rosenberg & Gluck LLP",
    "wof:placetype":"venue"
},
  "geometry": {"coordinates":[-73.055262,40.835809],"type":"Point"}
}