{
  "type": "Feature",
  "properties": {
    "addr:full":"2465 Randy Ln Bellmore NY 11710",
    "addr:housenumber":"2465",
    "addr:postcode":"11710",
    "addr:street":"Randy Ln",
    "iso:country":"US",
    "sg:address":"2465 Randy Ln",
    "sg:city":"Bellmore",
    "sg:classifiers":[
        {
            "category":"Building & Trades",
            "subcategory":"Electrical",
            "type":"Services"
        }
    ],
    "sg:phone":"+1 516 409 0800",
    "sg:postcode":"11710",
    "sg:province":"NY",
    "sg:tags":[
        "electric",
        "contractor"
    ],
    "wof:name":"Fishma Electric & Son Inc",
    "wof:placetype":"venue"
},
  "geometry": {"coordinates":[-73.53098199999999,40.648731],"type":"Point"}
}