{
  "type": "Feature",
  "properties": {
    "addr:full":"1889 State St Schenectady NY 12304",
    "addr:housenumber":"1889",
    "addr:postcode":"12304",
    "addr:street":"State St",
    "iso:country":"US",
    "sg:address":"1889 State St",
    "sg:city":"Schenectady",
    "sg:classifiers":[
        {
            "category":"Bars & Pubs",
            "type":"Food & Drink"
        }
    ],
    "sg:phone":"+1   ",
    "sg:postcode":"12304",
    "sg:province":"NY",
    "sg:tags":[
        "drinking"
    ],
    "wof:name":"Gaylords Tap Room",
    "wof:placetype":"venue"
},
  "geometry": {"coordinates":[-73.900807,42.77753],"type":"Point"}
}