{
  "type": "Feature",
  "properties": {
    "addr:full":"436 Atlantic Ave Brooklyn NY 11217",
    "addr:housenumber":"436",
    "addr:postcode":"11217",
    "addr:street":"Atlantic Ave",
    "iso:country":"US",
    "sg:address":"436 Atlantic Ave",
    "sg:city":"Brooklyn",
    "sg:classifiers":[
        {
            "category":"Social Services",
            "type":"Services"
        }
    ],
    "sg:phone":"+1 718 834 1562",
    "sg:postcode":"11217",
    "sg:province":"NY",
    "sg:tags":[
        "furniture",
        "store",
        "welfare"
    ],
    "sg:website":"www.use.salvationarmy.org",
    "wof:name":"Salvation Army",
    "wof:placetype":"venue"
},
  "geometry": {"coordinates":[-73.98377600000001,40.68652],"type":"Point"}
}