{
  "type": "Feature",
  "properties": {
    "addr:full":"1277 US Hwy 20 Silver Creek NY 14136",
    "addr:housenumber":"1277",
    "addr:postcode":"14136",
    "addr:street":"Us Hwy 20",
    "iso:country":"US",
    "sg:address":"1277 US Hwy 20",
    "sg:city":"Silver Creek",
    "sg:classifiers":[
        {
            "category":"Freight",
            "type":"Transportation"
        }
    ],
    "sg:phone":"+1 716 934 7119",
    "sg:postcode":"14136",
    "sg:province":"NY",
    "sg:tags":[
        "trucking"
    ],
    "wof:name":"Precision Transport Inc",
    "wof:placetype":"venue"
},
  "geometry": {"coordinates":[-79.14393099999999,42.551559],"type":"Point"}
}