{
  "type": "Feature",
  "properties": {
    "iso:country":"US",
    "sg:address":"99-14 Northern Blvd",
    "sg:city":"Queens",
    "sg:classifiers":[
        {
            "category":"Shopping",
            "subcategory":"Bicycles & Sporting Goods",
            "type":"Retail Goods"
        }
    ],
    "sg:phone":"+1 917 775 9272",
    "sg:postcode":"11368",
    "sg:province":"NY",
    "sg:website":"www.facebook.com/pages/Northern-...",
    "wof:name":"Northern Martial Arts Supplies, Silk Screening & Embroidery",
    "wof:placetype":"venue"
},
  "geometry": {"coordinates":[-73.868838,40.757019],"type":"Point"}
}