{
  "type": "Feature",
  "properties": {
    "addr:full":"319 Broadway Fl 4 New York NY 10007",
    "addr:housenumber":"319;4",
    "addr:postcode":"10007",
    "addr:street":"Broadway",
    "iso:country":"US",
    "sg:address":"319 Broadway Fl 4",
    "sg:city":"New York",
    "sg:classifiers":[
        {
            "category":"Professional",
            "subcategory":"Lawyer & Legal Services",
            "type":"Services"
        }
    ],
    "sg:phone":"+1 212 962 2400",
    "sg:postcode":"10007",
    "sg:province":"NY",
    "wof:name":"Bellin Aytan Y Atty",
    "wof:placetype":"venue"
},
  "geometry": {"coordinates":[-74.004997,40.715801],"type":"Point"}
}