{
  "type": "Feature",
  "properties": {
    "addr:full":"263 E Main St Avon NY 14414",
    "addr:housenumber":"263",
    "addr:postcode":"14414",
    "addr:street":"E Main St",
    "iso:country":"US",
    "sg:address":"263 E Main St",
    "sg:city":"Avon",
    "sg:classifiers":[
        {
            "category":"Banks & Credit Unions",
            "subcategory":"Bank",
            "type":"Services"
        }
    ],
    "sg:phone":"+1 585 226 6630",
    "sg:postcode":"14414",
    "sg:province":"NY",
    "sg:tags":[
        "state",
        "commercial"
    ],
    "sg:website":"www.bankofcastile.com",
    "wof:name":"Bank Of Castile",
    "wof:placetype":"venue"
},
  "geometry": {"coordinates":[-77.73710199999999,42.910613],"type":"Point"}
}