{
  "type": "Feature",
  "properties": {
    "addr:full":"1739 Melville St Bronx NY 10460",
    "addr:housenumber":"1739",
    "addr:postcode":"10460",
    "addr:street":"Melville St",
    "iso:country":"US",
    "sg:address":"1739 Melville St",
    "sg:city":"Bronx",
    "sg:classifiers":[
        {
            "category":"Shopping",
            "type":"Retail Goods"
        }
    ],
    "sg:phone":"+1   ",
    "sg:postcode":"10460",
    "sg:province":"NY",
    "sg:tags":[
        "merchandise"
    ],
    "wof:name":"Moses E Upomba",
    "wof:placetype":"venue"
},
  "geometry": {"coordinates":[-73.87058399999999,40.842487],"type":"Point"}
}