{
  "type": "Feature",
  "properties": {
    "addr:full":"1171 Castle Hill Ave Bronx NY 10462",
    "addr:housenumber":"1171",
    "addr:postcode":"10462",
    "addr:street":"Castle Hill Ave",
    "iso:country":"US",
    "sg:address":"1171 Castle Hill Ave",
    "sg:city":"Bronx",
    "sg:classifiers":[
        {
            "category":"Retail",
            "subcategory":"Laundry & Dry Cleaning",
            "type":"Services"
        }
    ],
    "sg:phone":"+1   ",
    "sg:postcode":"10462",
    "sg:province":"NY",
    "sg:tags":[
        "drycleaning",
        "plant"
    ],
    "wof:name":"Kleener King 6",
    "wof:placetype":"venue"
},
  "geometry": {"coordinates":[-73.85108,40.831726],"type":"Point"}
}