{
  "type": "Feature",
  "properties": {
    "iso:country":"US",
    "sg:address":"244 Arden Ave",
    "sg:city":"Staten Island",
    "sg:classifiers":[
        {
            "category":"Shopping",
            "subcategory":"Discount & Variety Stores",
            "type":"Retail Goods"
        }
    ],
    "sg:phone":"+1 718 966 7931",
    "sg:postcode":"10312",
    "sg:province":"NY",
    "sg:tags":[
        "merchandise",
        "general"
    ],
    "wof:name":"King Kullen Store",
    "wof:placetype":"venue"
},
  "geometry": {"coordinates":[-74.19219099999999,40.553654],"type":"Point"}
}