{
  "type": "Feature",
  "properties": {
    "iso:country":"US",
    "sg:address":"3074 14th Street",
    "sg:city":"Astoria",
    "sg:classifiers":[
        {
            "category":"Food & Beverages",
            "subcategory":"Groceries & Convenience Stores",
            "type":"Retail Goods"
        }
    ],
    "sg:phone":"+1 718 728 6540",
    "sg:postcode":"11102",
    "sg:province":"NY",
    "wof:name":"Lantigua Grocery",
    "wof:placetype":"venue"
},
  "geometry": {"coordinates":[-73.93159,40.768981],"type":"Point"}
}