{
  "type": "Feature",
  "properties": {
    "addr:full":"8836 E Town Line Rd Interlaken NY 14847",
    "addr:housenumber":"8836",
    "addr:postcode":"14847",
    "addr:street":"E Town Line Rd",
    "iso:country":"US",
    "sg:address":"8836 E Town Line Rd",
    "sg:city":"Interlaken",
    "sg:classifiers":[
        {
            "category":"Building & Trades",
            "subcategory":"Construction",
            "type":"Services"
        }
    ],
    "sg:phone":"+1 607 532 9558",
    "sg:postcode":"14847",
    "sg:province":"NY",
    "sg:tags":[
        "general",
        "contractor"
    ],
    "wof:name":"Wech Construction",
    "wof:placetype":"venue"
},
  "geometry": {"coordinates":[-76.763817,42.600948],"type":"Point"}
}