{
  "type": "Feature",
  "properties": {
    "addr:full":"1280 Sunrise Hwy Copiague NY 11726",
    "addr:housenumber":"1280",
    "addr:postcode":"11726",
    "addr:street":"Sunrise Hwy",
    "iso:country":"US",
    "sg:address":"1280 Sunrise Hwy",
    "sg:city":"Copiague",
    "sg:classifiers":[
        {
            "category":"Autos & Motor Vehicles",
            "subcategory":"Auto Supplies",
            "type":"Retail Goods"
        }
    ],
    "sg:phone":"+1 631 842 8787",
    "sg:postcode":"11726",
    "sg:province":"NY",
    "wof:name":"Tire Depot",
    "wof:placetype":"venue"
},
  "geometry": {"coordinates":[-73.39793899999999,40.692389],"type":"Point"}
}