{
  "type": "Feature",
  "properties": {
    "iso:country":"US",
    "sg:address":"900 Hylan Blvd",
    "sg:city":"Staten Island",
    "sg:classifiers":[
        {
            "category":"Restaurant",
            "type":"Food & Drink"
        }
    ],
    "sg:phone":"+1   ",
    "sg:postcode":"10305",
    "sg:province":"NY",
    "sg:tags":[
        "pizzeria"
    ],
    "wof:name":"Bobarinos",
    "wof:placetype":"venue"
},
  "geometry": {"coordinates":[-74.07387199999999,40.597637],"type":"Point"}
}