{
  "type": "Feature",
  "properties": {
    "addr:full":"369 Lexington Avenue New York NY 10017",
    "addr:housenumber":"369",
    "addr:postcode":"10017",
    "addr:street":"Lexington Avenue",
    "iso:country":"US",
    "sg:address":"369 Lexington Avenue",
    "sg:city":"New York",
    "sg:classifiers":[
        {
            "category":"Shopping",
            "subcategory":"Department Store",
            "type":"Retail Goods"
        }
    ],
    "sg:phone":"+1 212 983 0338",
    "sg:postcode":"10017",
    "sg:province":"NY",
    "wof:name":"Lloyds Department Store",
    "wof:placetype":"venue"
},
  "geometry": {"coordinates":[-73.976518,40.750719],"type":"Point"}
}