{
  "type": "Feature",
  "properties": {
    "iso:country":"US",
    "sg:address":"59 Mann Blvd",
    "sg:city":"Clifton Park",
    "sg:classifiers":[
        {
            "category":"Wholesale",
            "subcategory":"Non-durable Goods",
            "type":"Manufacturing & Wholesale Goods"
        }
    ],
    "sg:phone":"+1 518 373 5861",
    "sg:postcode":"12065",
    "sg:province":"NY",
    "wof:name":"J McCrudden Inc",
    "wof:placetype":"venue"
},
  "geometry": {"coordinates":[-73.766734,42.882385],"type":"Point"}
}