{
  "type": "Feature",
  "properties": {
    "addr:full":"82 Glenwood Ave Queensbury NY 12804",
    "addr:housenumber":"82",
    "addr:postcode":"12804",
    "addr:street":"Glenwood Ave",
    "iso:country":"US",
    "sg:address":"82 Glenwood Ave",
    "sg:city":"Queensbury",
    "sg:classifiers":[
        {
            "category":"Professional",
            "subcategory":"Lawyer & Legal Services",
            "type":"Services"
        }
    ],
    "sg:phone":"+1 518 793 4900",
    "sg:postcode":"12804",
    "sg:province":"NY",
    "sg:tags":[
        "attorney"
    ],
    "wof:name":"Borgos & Del Signore PC",
    "wof:placetype":"venue"
},
  "geometry": {"coordinates":[-73.654866,43.333752],"type":"Point"}
}