{
  "type": "Feature",
  "properties": {
    "addr:full":"671 W Broadway Cedarhurst NY 11516",
    "addr:housenumber":"671",
    "addr:postcode":"11516",
    "addr:street":"W Broadway",
    "iso:country":"US",
    "sg:address":"671 W Broadway",
    "sg:city":"Cedarhurst",
    "sg:classifiers":[
        {
            "category":"Wholesale",
            "subcategory":"Hardware",
            "type":"Manufacturing & Wholesale Goods"
        }
    ],
    "sg:phone":"+1 516 374 0291",
    "sg:postcode":"11516",
    "sg:province":"NY",
    "sg:tags":[
        "refrigerating"
    ],
    "wof:name":"Tannen Contracting Co",
    "wof:placetype":"venue"
},
  "geometry": {"coordinates":[-73.722596,40.627398],"type":"Point"}
}