{
  "type": "Feature",
  "properties": {
    "addr:full":"1727 White Plains Rd Bronx NY 10462",
    "addr:housenumber":"1727",
    "addr:postcode":"10462",
    "addr:street":"White Plains Rd",
    "iso:country":"US",
    "sg:address":"1727 White Plains Rd",
    "sg:city":"Bronx",
    "sg:classifiers":[
        {
            "category":"Health Services",
            "subcategory":"Dentist",
            "type":"Services"
        }
    ],
    "sg:phone":"+1 347 657 1926",
    "sg:postcode":"10462",
    "sg:province":"NY",
    "wof:name":"Miriam Dental Llc",
    "wof:placetype":"venue"
},
  "geometry": {"coordinates":[-73.8659,40.844107],"type":"Point"}
}