{
  "type": "Feature",
  "properties": {
    "iso:country":"US",
    "sg:address":"8075 Plainville Rd",
    "sg:city":"Baldwinsville",
    "sg:classifiers":[
        {
            "category":"Home & Garden",
            "subcategory":"Home Furnishings",
            "type":"Retail Goods"
        }
    ],
    "sg:phone":"+1   ",
    "sg:postcode":"13027",
    "sg:province":"NY",
    "wof:name":"Country Butler",
    "wof:placetype":"venue"
},
  "geometry": {"coordinates":[-76.44761800000001,43.163644],"type":"Point"}
}