{
  "type": "Feature",
  "properties": {
    "iso:country":"US",
    "sg:address":"270 Windsor Hwy",
    "sg:city":"New Windsor",
    "sg:classifiers":[
        {
            "category":"Wholesale",
            "subcategory":"Durable Goods & Equipment",
            "type":"Manufacturing & Wholesale Goods"
        }
    ],
    "sg:phone":"+1 845 569 2400",
    "sg:postcode":"12553",
    "sg:province":"NY",
    "sg:tags":[
        "importer"
    ],
    "wof:name":"Eurotek Imports",
    "wof:placetype":"venue"
},
  "geometry": {"coordinates":[-74.050042,41.466042],"type":"Point"}
}