{
  "type": "Feature",
  "properties": {
    "iso:country":"US",
    "sg:address":"20 Arlington Ave",
    "sg:city":"Saint James",
    "sg:classifiers":[
        {
            "category":"Building & Trades",
            "subcategory":"Construction",
            "type":"Services"
        }
    ],
    "sg:phone":"+1 631 863 2041",
    "sg:postcode":"11780",
    "sg:province":"NY",
    "sg:tags":[
        "house"
    ],
    "wof:name":"Woodcrest General Contracting",
    "wof:placetype":"venue"
},
  "geometry": {"coordinates":[-73.162436,40.866319],"type":"Point"}
}