{
  "type": "Feature",
  "properties": {
    "iso:country":"US",
    "sg:address":"4258 Sweden Walker Rd",
    "sg:city":"Brockport",
    "sg:classifiers":[
        {
            "category":"Building & Trades",
            "subcategory":"Construction",
            "type":"Services"
        }
    ],
    "sg:phone":"+1 585 637 4691",
    "sg:postcode":"14420",
    "sg:province":"NY",
    "sg:tags":[
        "contractor"
    ],
    "wof:name":"Exterior Finishers",
    "wof:placetype":"venue"
},
  "geometry": {"coordinates":[-77.894881,43.211421],"type":"Point"}
}