{
  "type": "Feature",
  "properties": {
    "iso:country":"US",
    "sg:address":"2106 Fort Hill Rd",
    "sg:city":"Phelps",
    "sg:classifiers":[
        {
            "category":"Sports & Exercise",
            "subcategory":"Sports Center",
            "type":"Entertainment"
        }
    ],
    "sg:phone":"+1 315 548 6239",
    "sg:postcode":"14532",
    "sg:province":"NY",
    "wof:name":"Palmyra Hunt Club Inc",
    "wof:placetype":"venue"
},
  "geometry": {"coordinates":[-77.05000699999999,42.931228],"type":"Point"}
}