{
  "type": "Feature",
  "properties": {
    "iso:country":"US",
    "sg:address":"60 Middle Neck Rd",
    "sg:city":"Great Neck",
    "sg:classifiers":[
        {
            "category":"Restaurant",
            "type":"Food & Drink"
        }
    ],
    "sg:menulink":"http://www.allmenus.com/ny/great-neck/37174-ginos/menu/",
    "sg:phone":"+1 516 487 1122",
    "sg:postcode":"11021",
    "sg:province":"NY",
    "sg:tags":[
        "american",
        "pizza"
    ],
    "wof:name":"Gino's",
    "wof:placetype":"venue"
},
  "geometry": {"coordinates":[-73.72947600000001,40.788189],"type":"Point"}
}