{
  "type": "Feature",
  "properties": {
    "addr:full":"130 Prospect Ave Salamanca NY 14779",
    "addr:housenumber":"130",
    "addr:postcode":"14779",
    "addr:street":"Prospect Ave",
    "iso:country":"US",
    "sg:address":"130 Prospect Ave",
    "sg:city":"Salamanca",
    "sg:classifiers":[
        {
            "category":"Organizations",
            "subcategory":"Religious Organization",
            "type":"Services"
        }
    ],
    "sg:phone":"+1 716 945 0586",
    "sg:postcode":"14779",
    "sg:province":"NY",
    "sg:tags":[
        "church"
    ],
    "wof:name":"Valley Christian Assembly",
    "wof:placetype":"venue"
},
  "geometry": {"coordinates":[-78.69255099999999,42.159425],"type":"Point"}
}