{
  "type": "Feature",
  "properties": {
    "addr:full":"75 W Main St East Islip NY 11730",
    "addr:housenumber":"75",
    "addr:postcode":"11730",
    "addr:street":"W Main St",
    "iso:country":"US",
    "sg:address":"75 W Main St",
    "sg:city":"East Islip",
    "sg:classifiers":[
        {
            "category":"Sports & Exercise",
            "subcategory":"Bicycle Rental",
            "type":"Entertainment"
        }
    ],
    "sg:phone":"+1 631 581 5557",
    "sg:postcode":"11730",
    "sg:province":"NY",
    "sg:tags":[
        "bike"
    ],
    "wof:name":"Bike Depot",
    "wof:placetype":"venue"
},
  "geometry": {"coordinates":[-73.19409899999999,40.7304],"type":"Point"}
}