{
  "type": "Feature",
  "properties": {
    "iso:country":"US",
    "sg:address":"52 Fulton St",
    "sg:city":"Manhattan",
    "sg:classifiers":[
        {
            "category":"Fast Food",
            "type":"Food & Drink"
        }
    ],
    "sg:phone":"+1 212 528 2930",
    "sg:postcode":"10038",
    "sg:province":"NY",
    "sg:tags":[
        "burger"
    ],
    "sg:website":"www.mcdonalds.com",
    "wof:name":"McDonald's",
    "wof:placetype":"venue"
},
  "geometry": {"coordinates":[-74.00482700000001,40.708306],"type":"Point"}
}