{
  "type": "Feature",
  "properties": {
    "addr:full":"18 Horse Hill Rd Glen Head NY 11545",
    "addr:housenumber":"18",
    "addr:postcode":"11545",
    "addr:street":"Horse Hill Rd",
    "iso:country":"US",
    "sg:address":"18 Horse Hill Rd",
    "sg:city":"Glen Head",
    "sg:classifiers":[
        {
            "category":"Building & Trades",
            "subcategory":"Plumbing",
            "type":"Services"
        }
    ],
    "sg:phone":"+1 516 626 2970",
    "sg:postcode":"11545",
    "sg:province":"NY",
    "wof:name":"Warga Plumbing & Htg",
    "wof:placetype":"venue"
},
  "geometry": {"coordinates":[-73.582497,40.816399],"type":"Point"}
}