{
  "type": "Feature",
  "properties": {
    "addr:full":"113 Marangale Rd Manlius NY 13104",
    "addr:housenumber":"113",
    "addr:postcode":"13104",
    "addr:street":"Marangale Rd",
    "iso:country":"US",
    "sg:address":"113 Marangale Rd",
    "sg:city":"Manlius",
    "sg:classifiers":[
        {
            "category":"Wholesale",
            "subcategory":"Apparel",
            "type":"Manufacturing & Wholesale Goods"
        }
    ],
    "sg:phone":"+1 315 682 4936",
    "sg:postcode":"13104",
    "sg:province":"NY",
    "sg:tags":[
        "piece"
    ],
    "wof:name":"Noel Keith Textiles",
    "wof:placetype":"venue"
},
  "geometry": {"coordinates":[-75.995987,43.012838],"type":"Point"}
}