{
  "type": "Feature",
  "properties": {
    "addr:full":"31 E 27th St New York NY 10016",
    "addr:housenumber":"31",
    "addr:postcode":"10016",
    "addr:street":"E 27Th St",
    "iso:country":"US",
    "sg:address":"31 E 27th St",
    "sg:city":"New York",
    "sg:classifiers":[
        {
            "category":"Restaurant",
            "type":"Food & Drink"
        }
    ],
    "sg:menulink":"http://www.allmenus.com/ny/new-york/249220-kabab-king/menu/",
    "sg:phone":"+1 212 213 8930",
    "sg:postcode":"10016",
    "sg:province":"NY",
    "sg:tags":[
        "asian",
        "chinese"
    ],
    "wof:name":"Kabab King",
    "wof:placetype":"venue"
},
  "geometry": {"coordinates":[-73.985983,40.743321],"type":"Point"}
}