{
  "type": "Feature",
  "properties": {
    "iso:country":"US",
    "sg:address":"289 Hudson St",
    "sg:city":"New York",
    "sg:classifiers":[
        {
            "category":"Deli",
            "type":"Food & Drink"
        },
        {
            "category":"Restaurant",
            "type":"Food & Drink"
        }
    ],
    "sg:menulink":"http://www.allmenus.com/ny/new-york/7040-ellen-deli--grocery/menu/",
    "sg:phone":"+1 212 675 7792",
    "sg:postcode":"10013",
    "sg:province":"NY",
    "sg:tags":[
        "deli",
        "american"
    ],
    "wof:name":"Ellen Deli & Grocery",
    "wof:placetype":"venue"
},
  "geometry": {"coordinates":[-74.007846,40.725671],"type":"Point"}
}