{
  "type": "Feature",
  "properties": {
    "addr:full":"399 W Broadway New York NY 10012",
    "addr:housenumber":"399",
    "addr:postcode":"10012",
    "addr:street":"W Broadway",
    "iso:country":"US",
    "sg:address":"399 W Broadway",
    "sg:city":"New York",
    "sg:classifiers":[
        {
            "category":"Shopping",
            "subcategory":"Optician",
            "type":"Retail Goods"
        }
    ],
    "sg:phone":"+1 212 966 0099",
    "sg:postcode":"10012",
    "sg:province":"NY",
    "sg:tags":[
        "eyewear"
    ],
    "sg:website":"www.morgenthalfrederics.com/",
    "wof:name":"Morgenthal Frederics Opticians",
    "wof:placetype":"venue"
},
  "geometry": {"coordinates":[-74.00190000000001,40.724499],"type":"Point"}
}