{
  "type": "Feature",
  "properties": {
    "iso:country":"US",
    "sg:address":"4348 Loveland Dr",
    "sg:city":"Liverpool",
    "sg:classifiers":[
        {
            "category":"Building & Trades",
            "subcategory":"Construction",
            "type":"Services"
        }
    ],
    "sg:phone":"+1 315 622 5304",
    "sg:postcode":"13090",
    "sg:province":"NY",
    "sg:tags":[
        "contractor"
    ],
    "wof:name":"High Smith Contracting",
    "wof:placetype":"venue"
},
  "geometry": {"coordinates":[-76.214411,43.16566],"type":"Point"}
}