{
  "type": "Feature",
  "properties": {
    "addr:full":"2400 Ryer Ave Bronx NY 10458",
    "addr:housenumber":"2400",
    "addr:postcode":"10458",
    "addr:street":"Ryer Ave",
    "iso:country":"US",
    "sg:address":"2400 Ryer Ave",
    "sg:city":"Bronx",
    "sg:classifiers":[
        {
            "category":"Food & Beverages",
            "subcategory":"Groceries & Convenience Stores",
            "type":"Retail Goods"
        }
    ],
    "sg:phone":"+1 718 367 1800",
    "sg:postcode":"10458",
    "sg:province":"NY",
    "wof:name":"Pioneer Supermarkets",
    "wof:placetype":"venue"
},
  "geometry": {"coordinates":[-73.89792799999999,40.859272],"type":"Point"}
}