{
  "type": "Feature",
  "properties": {
    "addr:full":"107 Cortlandt St Sleepy Hollow NY 10591",
    "addr:housenumber":"107",
    "addr:postcode":"10591",
    "addr:street":"Cortlandt St",
    "iso:country":"US",
    "sg:address":"107 Cortlandt St",
    "sg:city":"Sleepy Hollow",
    "sg:classifiers":[
        {
            "category":"Organizations",
            "subcategory":"Community Association",
            "type":"Services"
        }
    ],
    "sg:phone":"+1 914 631 9866",
    "sg:postcode":"10591",
    "sg:province":"NY",
    "sg:tags":[
        "club"
    ],
    "wof:name":"Violet Rose Social Club Inc",
    "wof:placetype":"venue"
},
  "geometry": {"coordinates":[-73.863782,41.08133],"type":"Point"}
}