{
  "type": "Feature",
  "properties": {
    "iso:country":"US",
    "sg:address":"883 9th Ave",
    "sg:city":"New York",
    "sg:classifiers":[
        {
            "category":"Shopping",
            "subcategory":"Pharmacy",
            "type":"Retail Goods"
        }
    ],
    "sg:phone":"+1 212 245 8469",
    "sg:postcode":"10019",
    "sg:province":"NY",
    "sg:tags":[
        "drugstore"
    ],
    "wof:name":"Arrow Pharmacy Inc",
    "wof:placetype":"venue"
},
  "geometry": {"coordinates":[-73.985603,40.7682],"type":"Point"}
}