{
  "type": "Feature",
  "properties": {
    "iso:country":"US",
    "sg:address":"740 Elmwood Ave",
    "sg:city":"Buffalo",
    "sg:classifiers":[
        {
            "category":"Shopping",
            "subcategory":"Gifts & Souvenirs",
            "type":"Retail Goods"
        }
    ],
    "sg:phone":"+1 716 883 0607",
    "sg:postcode":"14222",
    "sg:province":"NY",
    "sg:tags":[
        "shop",
        "accessory"
    ],
    "wof:name":"Everything Elmwood",
    "wof:placetype":"venue"
},
  "geometry": {"coordinates":[-78.876999,42.917],"type":"Point"}
}