{
  "type": "Feature",
  "properties": {
    "iso:country":"US",
    "sg:address":"121 Old Rte 146",
    "sg:city":"Clifton Park",
    "sg:classifiers":[
        {
            "category":"Home & Garden",
            "subcategory":"Furniture",
            "type":"Retail Goods"
        }
    ],
    "sg:phone":"+1 518 371 6027",
    "sg:postcode":"12065",
    "sg:province":"NY",
    "sg:tags":[
        "mattress"
    ],
    "sg:website":"www.rockawaybedding.com",
    "wof:name":"Rockaway Bedding",
    "wof:placetype":"venue"
},
  "geometry": {"coordinates":[-73.776608,42.864062],"type":"Point"}
}