{
  "type": "Feature",
  "properties": {
    "iso:country":"US",
    "sg:address":"1757 Parkmeadow Dr",
    "sg:city":"Jamestown",
    "sg:classifiers":[
        {
            "category":"Professional",
            "type":"Services"
        }
    ],
    "sg:phone":"+1   ",
    "sg:postcode":"14701",
    "sg:province":"NY",
    "wof:name":"CC Enterprises",
    "wof:placetype":"venue"
},
  "geometry": {"coordinates":[-79.261523,42.074124],"type":"Point"}
}