{
  "type": "Feature",
  "properties": {
    "addr:full":"51 Benbro Dr Cheektowaga NY 14225",
    "addr:housenumber":"51",
    "addr:postcode":"14225",
    "addr:street":"Benbro Dr",
    "iso:country":"US",
    "sg:address":"51 Benbro Dr",
    "sg:city":"Cheektowaga",
    "sg:classifiers":[
        {
            "category":"Wholesale",
            "subcategory":"Durable Goods & Equipment",
            "type":"Manufacturing & Wholesale Goods"
        }
    ],
    "sg:phone":"+1 716 684 1200",
    "sg:postcode":"14225",
    "sg:province":"NY",
    "sg:tags":[
        "importer"
    ],
    "wof:name":"Dobkintile",
    "wof:placetype":"venue"
},
  "geometry": {"coordinates":[-78.73622,42.911729],"type":"Point"}
}