{
  "type": "Feature",
  "properties": {
    "addr:full":"215 Mulberry St New York NY 10012",
    "addr:housenumber":"215",
    "addr:postcode":"10012",
    "addr:street":"Mulberry St",
    "iso:country":"US",
    "sg:address":"215 Mulberry St",
    "sg:city":"New York",
    "sg:classifiers":[
        {
            "category":"Professional",
            "type":"Services"
        }
    ],
    "sg:phone":"+1 212 431 5584",
    "sg:postcode":"10012",
    "sg:province":"NY",
    "sg:tags":[
        "establishment"
    ],
    "wof:name":"Best Pashmina",
    "wof:placetype":"venue"
},
  "geometry": {"coordinates":[-73.995797,40.72332],"type":"Point"}
}