{
  "type": "Feature",
  "properties": {
    "addr:full":"40 Ogden Ave White Plains NY 10605",
    "addr:housenumber":"40",
    "addr:postcode":"10605",
    "addr:street":"Ogden Ave",
    "iso:country":"US",
    "sg:address":"40 Ogden Ave",
    "sg:city":"White Plains",
    "sg:classifiers":[
        {
            "category":"Professional",
            "subcategory":"Computer Services",
            "type":"Services"
        }
    ],
    "sg:phone":"+1   ",
    "sg:postcode":"10605",
    "sg:province":"NY",
    "sg:tags":[
        "development",
        "fire",
        "department",
        "for",
        "software"
    ],
    "wof:name":"Saturn Software Systems Inc",
    "wof:placetype":"venue"
},
  "geometry": {"coordinates":[-73.76611699999999,41.016586],"type":"Point"}
}