{
  "type": "Feature",
  "properties": {
    "iso:country":"US",
    "sg:address":"2402 22nd St",
    "sg:city":"Troy",
    "sg:classifiers":[
        {
            "category":"Health Services",
            "subcategory":"Doctor",
            "type":"Services"
        }
    ],
    "sg:phone":"+1 518 274 2030",
    "sg:postcode":"12180",
    "sg:province":"NY",
    "sg:tags":[
        "physician",
        "surgeon",
        "medical"
    ],
    "wof:name":"John A Brendese MD",
    "wof:placetype":"venue"
},
  "geometry": {"coordinates":[-73.667501,42.741051],"type":"Point"}
}