{
  "type": "Feature",
  "properties": {
    "iso:country":"US",
    "sg:address":"103 Sandy Hollow Rd",
    "sg:city":"Northport",
    "sg:classifiers":[
        {
            "category":"Professional",
            "subcategory":"Management & Consulting",
            "type":"Services"
        }
    ],
    "sg:phone":"+1   ",
    "sg:postcode":"11768",
    "sg:province":"NY",
    "wof:name":"Acadia Chemical Service",
    "wof:placetype":"venue"
},
  "geometry": {"coordinates":[-73.350649,40.882037],"type":"Point"}
}