{
  "type": "Feature",
  "properties": {
    "iso:country":"US",
    "sg:address":"9315 State Hwy 22",
    "sg:city":"Hillsdale",
    "sg:classifiers":[
        {
            "category":"Shopping",
            "subcategory":"Used Merchandise",
            "type":"Retail Goods"
        }
    ],
    "sg:phone":"+1   ",
    "sg:postcode":"12529",
    "sg:province":"NY",
    "wof:name":"Red Fox Antiques",
    "wof:placetype":"venue"
},
  "geometry": {"coordinates":[-73.52048499999999,42.181471],"type":"Point"}
}