{
  "type": "Feature",
  "properties": {
    "addr:full":"21 W Academy St Wappingers Falls NY 12590",
    "addr:housenumber":"21",
    "addr:postcode":"12590",
    "addr:street":"W Academy St",
    "iso:country":"US",
    "sg:address":"21 W Academy St",
    "sg:city":"Wappingers Falls",
    "sg:classifiers":[
        {
            "category":"Building & Trades",
            "subcategory":"Landscaping Services",
            "type":"Services"
        }
    ],
    "sg:phone":"+1 845 298 6281",
    "sg:postcode":"12590",
    "sg:province":"NY",
    "sg:tags":[
        "maintenance"
    ],
    "wof:name":"Perennial Ldscp Design & Maint",
    "wof:placetype":"venue"
},
  "geometry": {"coordinates":[-73.91933899999999,41.594834],"type":"Point"}
}