{
  "type": "Feature",
  "properties": {
    "addr:full":"11 Glenmore Ave Saratoga Springs NY 12866",
    "addr:housenumber":"11",
    "addr:postcode":"12866",
    "addr:street":"Glenmore Ave",
    "iso:country":"US",
    "sg:address":"11 Glenmore Ave",
    "sg:city":"Saratoga Springs",
    "sg:classifiers":[
        {
            "category":"Professional",
            "subcategory":"Computer Services",
            "type":"Services"
        }
    ],
    "sg:phone":"+1 518 587 4813",
    "sg:postcode":"12866",
    "sg:province":"NY",
    "sg:tags":[
        "repair"
    ],
    "wof:name":"Cei Computer Svc LLC",
    "wof:placetype":"venue"
},
  "geometry": {"coordinates":[-73.80776400000001,43.07456],"type":"Point"}
}