{
  "type": "Feature",
  "properties": {
    "iso:country":"US",
    "sg:address":"312 Uniondale Ave",
    "sg:city":"Uniondale",
    "sg:classifiers":[
        {
            "category":"Building & Trades",
            "subcategory":"Construction",
            "type":"Services"
        }
    ],
    "sg:phone":"+1 516 486 6322",
    "sg:postcode":"11553",
    "sg:province":"NY",
    "sg:tags":[
        "roofing",
        "siding",
        "general",
        "s",
        "home",
        "contractor"
    ],
    "wof:name":"County Housecrafts Co",
    "wof:placetype":"venue"
},
  "geometry": {"coordinates":[-73.592521,40.708441],"type":"Point"}
}