{
  "type": "Feature",
  "properties": {
    "addr:full":"107 Lee Ter East Syracuse NY 13057",
    "addr:housenumber":"107",
    "addr:postcode":"13057",
    "addr:street":"Lee Ter East",
    "iso:country":"US",
    "sg:address":"107 Lee Ter",
    "sg:city":"East Syracuse",
    "sg:classifiers":[
        {
            "category":"Food & Beverages",
            "subcategory":"Meat & Fish",
            "type":"Retail Goods"
        }
    ],
    "sg:phone":"+1   ",
    "sg:postcode":"13057",
    "sg:province":"NY",
    "wof:name":"Paisano Provisioners Inc",
    "wof:placetype":"venue"
},
  "geometry": {"coordinates":[-76.02013599999999,43.058542],"type":"Point"}
}