{
  "type": "Feature",
  "properties": {
    "iso:country":"US",
    "sg:address":"6120 Seneca St",
    "sg:city":"Elma",
    "sg:classifiers":[
        {
            "category":"Restaurant",
            "type":"Food & Drink"
        }
    ],
    "sg:phone":"+1 716 655 8600",
    "sg:postcode":"14059",
    "sg:province":"NY",
    "wof:name":"Elma Hollow Grille LLC",
    "wof:placetype":"venue"
},
  "geometry": {"coordinates":[-78.682526,42.822351],"type":"Point"}
}