{
  "type": "Feature",
  "properties": {
    "addr:full":"180 W 76th St New York NY 10023",
    "addr:housenumber":"180",
    "addr:postcode":"10023",
    "addr:street":"W 76Th St",
    "iso:country":"US",
    "sg:address":"180 W 76th St",
    "sg:city":"New York",
    "sg:classifiers":[
        {
            "category":"Retail",
            "subcategory":"Funeral Services",
            "type":"Services"
        }
    ],
    "sg:phone":"+1 212 362 6600",
    "sg:postcode":"10023",
    "sg:province":"NY",
    "sg:tags":[
        "cemetery"
    ],
    "sg:website":"www.riversidememorialchapel.com",
    "wof:name":"Riverside Memorial Chapel",
    "wof:placetype":"venue"
},
  "geometry": {"coordinates":[-73.97919899999999,40.780966],"type":"Point"}
}