{
  "type": "Feature",
  "properties": {
    "addr:full":"48 Central Park N New York NY 10026",
    "addr:housenumber":"48",
    "addr:postcode":"10026",
    "addr:street":"Central Park N",
    "iso:country":"US",
    "sg:address":"48 Central Park N",
    "sg:city":"New York",
    "sg:classifiers":[
        {
            "category":"Restaurant",
            "type":"Food & Drink"
        }
    ],
    "sg:phone":"+1 212 808 5511",
    "sg:postcode":"10026",
    "sg:province":"NY",
    "wof:name":"Dishes Central",
    "wof:placetype":"venue"
},
  "geometry": {"coordinates":[-73.951402,40.797742],"type":"Point"}
}