{
  "type": "Feature",
  "properties": {
    "addr:full":"48 New St New York NY 10004",
    "addr:housenumber":"48",
    "addr:postcode":"10004",
    "addr:street":"New St",
    "iso:country":"US",
    "sg:address":"48 New St",
    "sg:city":"New York",
    "sg:classifiers":[
        {
            "category":"Bakery",
            "type":"Food & Drink"
        },
        {
            "category":"Coffee & Tea",
            "type":"Food & Drink"
        },
        {
            "category":"Bagels",
            "type":"Food & Drink"
        },
        {
            "category":"Donuts",
            "type":"Food & Drink"
        }
    ],
    "sg:menulink":"http://www.allmenus.com/ny/new-york/138569-dunkin-donuts/menu/",
    "sg:phone":"+1 845 358 0666",
    "sg:postcode":"10004",
    "sg:province":"NY",
    "sg:tags":[
        "american",
        "pastry"
    ],
    "wof:name":"Dunkin' Donuts",
    "wof:placetype":"venue"
},
  "geometry": {"coordinates":[-74.012072,40.706148],"type":"Point"}
}