{
  "type": "Feature",
  "properties": {
    "addr:full":"10 Murray St Manhattan NY 10007",
    "addr:housenumber":"10",
    "addr:postcode":"10007",
    "addr:street":"Murray St",
    "iso:country":"US",
    "sg:address":"10 Murray St",
    "sg:city":"Manhattan",
    "sg:classifiers":[
        {
            "category":"Restaurant",
            "type":"Food & Drink"
        }
    ],
    "sg:phone":"+1 212 962 1813",
    "sg:postcode":"10007",
    "sg:province":"NY",
    "sg:website":"www.musclemakergrill.com",
    "wof:name":"Muscle Maker Grill",
    "wof:placetype":"venue"
},
  "geometry": {"coordinates":[-74.00802899999999,40.713425],"type":"Point"}
}