{
  "type": "Feature",
  "properties": {
    "addr:full":"6900 8th Ave Brooklyn NY 11228",
    "addr:housenumber":"6900",
    "addr:postcode":"11228",
    "addr:street":"8Th Ave",
    "iso:country":"US",
    "sg:address":"6900 8th Ave",
    "sg:city":"Brooklyn",
    "sg:classifiers":[
        {
            "category":"Real Estate",
            "subcategory":"Real Estate Agent",
            "type":"Services"
        }
    ],
    "sg:phone":"+1 718 238 9879",
    "sg:postcode":"11228",
    "sg:province":"NY",
    "sg:tags":[
        "management"
    ],
    "wof:name":"D & D Management Svc",
    "wof:placetype":"venue"
},
  "geometry": {"coordinates":[-74.01548699999999,40.629791],"type":"Point"}
}