{
  "type": "Feature",
  "properties": {
    "addr:full":"117 S State St Syracuse NY 13202",
    "addr:housenumber":"117",
    "addr:postcode":"13202",
    "addr:street":"S State St",
    "iso:country":"US",
    "sg:address":"117 S State St",
    "sg:city":"Syracuse",
    "sg:classifiers":[
        {
            "category":"Professional",
            "subcategory":"Lawyer & Legal Services",
            "type":"Services"
        }
    ],
    "sg:phone":"+1 315 475 3012",
    "sg:postcode":"13202",
    "sg:province":"NY",
    "sg:tags":[
        "attorney"
    ],
    "wof:name":"James B Fleckenstein",
    "wof:placetype":"venue"
},
  "geometry": {"coordinates":[-76.147316,43.049531],"type":"Point"}
}