{
  "type": "Feature",
  "properties": {
    "addr:full":"2285 University Ave Bronx NY 10468",
    "addr:housenumber":"2285",
    "addr:postcode":"10468",
    "addr:street":"University Ave",
    "iso:country":"US",
    "sg:address":"2285 University Ave",
    "sg:city":"Bronx",
    "sg:classifiers":[
        {
            "category":"Farming",
            "subcategory":"Orchard",
            "type":"Manufacturing & Wholesale Goods"
        }
    ],
    "sg:phone":"+1 718 584 3602",
    "sg:postcode":"10468",
    "sg:province":"NY",
    "wof:name":"Orchard Mews Assoc",
    "wof:placetype":"venue"
},
  "geometry": {"coordinates":[-73.90553300000001,40.862006],"type":"Point"}
}