{
  "type": "Feature",
  "properties": {
    "addr:full":"134 W Oneida St Oswego NY 13126",
    "addr:housenumber":"134",
    "addr:postcode":"13126",
    "addr:street":"W Oneida St",
    "iso:country":"US",
    "sg:address":"134 W Oneida St",
    "sg:city":"Oswego",
    "sg:classifiers":[
        {
            "category":"Organizations",
            "subcategory":"Community Association",
            "type":"Services"
        }
    ],
    "sg:phone":"+1 315 343 3516",
    "sg:postcode":"13126",
    "sg:province":"NY",
    "sg:tags":[
        "fraternal"
    ],
    "wof:name":"Loyal Order Of Moose",
    "wof:placetype":"venue"
},
  "geometry": {"coordinates":[-76.52049100000001,43.452627],"type":"Point"}
}