{
  "type": "Feature",
  "properties": {
    "addr:full":"4407 Broadway Manhattan NY 10040",
    "addr:housenumber":"4407",
    "addr:postcode":"10040",
    "addr:street":"Broadway",
    "iso:country":"US",
    "sg:address":"4407 Broadway",
    "sg:city":"Manhattan",
    "sg:classifiers":[
        {
            "category":"Food & Beverages",
            "subcategory":"Ethnic Foods",
            "type":"Retail Goods"
        }
    ],
    "sg:phone":"+1 212 928 3038",
    "sg:postcode":"10040",
    "sg:province":"NY",
    "wof:name":"Food Palace",
    "wof:placetype":"venue"
},
  "geometry": {"coordinates":[-73.933368,40.855247],"type":"Point"}
}