{
  "type": "Feature",
  "properties": {
    "addr:full":"331 Alberta Dr Buffalo NY 14226",
    "addr:housenumber":"331",
    "addr:postcode":"14226",
    "addr:street":"Alberta Dr",
    "iso:country":"US",
    "sg:address":"331 Alberta Dr",
    "sg:city":"Buffalo",
    "sg:classifiers":[
        {
            "category":"Social Services",
            "type":"Services"
        }
    ],
    "sg:phone":"+1   ",
    "sg:postcode":"14226",
    "sg:province":"NY",
    "wof:name":"Kent E Bath",
    "wof:placetype":"venue"
},
  "geometry": {"coordinates":[-78.817403,42.981766],"type":"Point"}
}