{
  "type": "Feature",
  "properties": {
    "iso:country":"US",
    "sg:address":"9 Gerhard Rd",
    "sg:city":"Plainview",
    "sg:classifiers":[
        {
            "category":"Professional",
            "subcategory":"Accounting & Tax Preparation",
            "type":"Services"
        }
    ],
    "sg:phone":"+1 516 681 0201",
    "sg:postcode":"11803",
    "sg:province":"NY",
    "wof:name":"Donel Assoc Ltd",
    "wof:placetype":"venue"
},
  "geometry": {"coordinates":[-73.47755600000001,40.772539],"type":"Point"}
}