{
  "type": "Feature",
  "properties": {
    "iso:country":"US",
    "sg:address":"34 15th St",
    "sg:city":"Brooklyn",
    "sg:classifiers":[
        {
            "category":"Professional",
            "subcategory":"Advertising",
            "type":"Services"
        }
    ],
    "sg:phone":"+1 212 965 1500",
    "sg:postcode":"11215",
    "sg:province":"NY",
    "sg:tags":[
        "distribution"
    ],
    "wof:name":"Rushh USA Inc",
    "wof:placetype":"venue"
},
  "geometry": {"coordinates":[-73.994793,40.668243],"type":"Point"}
}