{
  "type": "Feature",
  "properties": {
    "addr:full":"250 Saint Gregory Ct Williamsville NY 14221",
    "addr:housenumber":"250",
    "addr:postcode":"14221",
    "addr:street":"Saint Gregory Ct",
    "iso:country":"US",
    "sg:address":"250 Saint Gregory Ct",
    "sg:city":"Williamsville",
    "sg:classifiers":[
        {
            "category":"Education",
            "subcategory":"School",
            "type":"Public Place"
        }
    ],
    "sg:phone":"+1 716 688 5760",
    "sg:postcode":"14221",
    "sg:province":"NY",
    "wof:name":"Religious Education",
    "wof:placetype":"venue"
},
  "geometry": {"coordinates":[-78.72734800000001,42.99323],"type":"Point"}
}