{
  "type": "Feature",
  "properties": {
    "iso:country":"US",
    "sg:address":"75 Oregon St",
    "sg:city":"Long Beach",
    "sg:classifiers":[
        {
            "category":"Professional",
            "subcategory":"Computer Services",
            "type":"Services"
        }
    ],
    "sg:phone":"+1   ",
    "sg:postcode":"11561",
    "sg:province":"NY",
    "sg:tags":[
        "related"
    ],
    "wof:name":"Network Solutions",
    "wof:placetype":"venue"
},
  "geometry": {"coordinates":[-73.689804,40.587472],"type":"Point"}
}