{
  "type": "Feature",
  "properties": {
    "iso:country":"US",
    "sg:address":"59 Main St",
    "sg:city":"Fort Plain",
    "sg:classifiers":[
        {
            "category":"Restaurant",
            "type":"Food & Drink"
        }
    ],
    "sg:phone":"+1 518 993 3200",
    "sg:postcode":"13339",
    "sg:province":"NY",
    "wof:name":"Papa Joe's Pizzaria",
    "wof:placetype":"venue"
},
  "geometry": {"coordinates":[-74.622998,42.930689],"type":"Point"}
}