{
  "type": "Feature",
  "properties": {
    "iso:country":"US",
    "sg:address":"7417 Grand Ave",
    "sg:city":"Elmhurst",
    "sg:classifiers":[
        {
            "category":"Shopping",
            "subcategory":"Pets & Pet Supplies",
            "type":"Retail Goods"
        }
    ],
    "sg:phone":"+1 718 779 4992",
    "sg:postcode":"11373",
    "sg:province":"NY",
    "sg:tags":[
        "store"
    ],
    "sg:website":"www.petlanddiscounts.com",
    "wof:name":"Petland Discounts",
    "wof:placetype":"venue"
},
  "geometry": {"coordinates":[-73.887497,40.730301],"type":"Point"}
}