{
  "type": "Feature",
  "properties": {
    "addr:full":"486 Malcolm X Blvd New York NY 10037",
    "addr:housenumber":"486",
    "addr:postcode":"10037",
    "addr:street":"Malcolm X Blvd",
    "iso:country":"US",
    "sg:address":"486 Malcolm X Blvd",
    "sg:city":"New York",
    "sg:classifiers":[
        {
            "category":"Retail",
            "subcategory":"Auto Repair",
            "type":"Services"
        }
    ],
    "sg:phone":"+1 917 463 2798",
    "sg:postcode":"10037",
    "sg:province":"NY",
    "sg:tags":[
        "wrecker"
    ],
    "wof:name":"24 Hour A Day Towing",
    "wof:placetype":"venue"
},
  "geometry": {"coordinates":[-73.94091400000001,40.813846],"type":"Point"}
}