{
  "type": "Feature",
  "properties": {
    "addr:full":"40 Paerdegat 4th St Brooklyn NY 11236",
    "addr:housenumber":"40",
    "addr:postcode":"11236",
    "addr:street":"Paerdegat 4Th St",
    "iso:country":"US",
    "sg:address":"40 Paerdegat 4th St",
    "sg:city":"Brooklyn",
    "sg:classifiers":[
        {
            "category":"Organizations",
            "subcategory":"Religious Organization",
            "type":"Services"
        }
    ],
    "sg:phone":"+1 718 531 3539",
    "sg:postcode":"11236",
    "sg:province":"NY",
    "sg:tags":[
        "clergy"
    ],
    "wof:name":"Yitzhak Rabinowitz",
    "wof:placetype":"venue"
},
  "geometry": {"coordinates":[-73.910099,40.63123],"type":"Point"}
}