{
  "type": "Feature",
  "properties": {
    "addr:full":"10217 Glenwood Rd Brooklyn NY 11236",
    "addr:housenumber":"10217",
    "addr:postcode":"11236",
    "addr:street":"Glenwood Rd",
    "iso:country":"US",
    "sg:address":"10217 Glenwood Rd",
    "sg:city":"Brooklyn",
    "sg:classifiers":[
        {
            "category":"Organizations",
            "subcategory":"Religious Organization",
            "type":"Services"
        }
    ],
    "sg:phone":"+1 718 649 8623",
    "sg:postcode":"11236",
    "sg:province":"NY",
    "wof:name":"Canarsi Frnch Cngrgtion Jhvahs",
    "wof:placetype":"venue"
},
  "geometry": {"coordinates":[-73.897972,40.648044],"type":"Point"}
}