{
  "type": "Feature",
  "properties": {
    "iso:country":"US",
    "sg:address":"354 E Jericho Tpke",
    "sg:city":"Mineola",
    "sg:classifiers":[
        {
            "category":"Health Services",
            "subcategory":"Health Practitioner",
            "type":"Services"
        }
    ],
    "sg:phone":"+1   ",
    "sg:postcode":"11501",
    "sg:province":"NY",
    "wof:name":"Ira S Springer",
    "wof:placetype":"venue"
},
  "geometry": {"coordinates":[-73.62483,40.754732],"type":"Point"}
}