{
  "type": "Feature",
  "properties": {
    "iso:country":"US",
    "sg:address":"214 Turner Ave",
    "sg:city":"Syracuse",
    "sg:classifiers":[
        {
            "category":"Shopping",
            "subcategory":"Computers & Home Electronics",
            "type":"Retail Goods"
        }
    ],
    "sg:phone":"+1 315 468 9881",
    "sg:postcode":"13219",
    "sg:province":"NY",
    "sg:tags":[
        "equipment",
        "dealer"
    ],
    "wof:name":"J & S Computers",
    "wof:placetype":"venue"
},
  "geometry": {"coordinates":[-76.250444,43.048731],"type":"Point"}
}