{
  "type": "Feature",
  "properties": {
    "iso:country":"US",
    "sg:address":"130 W Sunrise Hwy",
    "sg:city":"Lindenhurst",
    "sg:classifiers":[
        {
            "category":"Shopping",
            "subcategory":"Gifts & Souvenirs",
            "type":"Retail Goods"
        }
    ],
    "sg:phone":"+1 631 842 5734",
    "sg:postcode":"11757",
    "sg:province":"NY",
    "sg:tags":[
        "cards",
        "greeting"
    ],
    "wof:name":"P M Cards & Gifts",
    "wof:placetype":"venue"
},
  "geometry": {"coordinates":[-73.39027400000001,40.69493],"type":"Point"}
}