{
  "type": "Feature",
  "properties": {
    "addr:full":"199 Merritts Rd Ste A Farmingdale NY 11735",
    "addr:housenumber":"199",
    "addr:postcode":"11735",
    "addr:street":"Merritts Rd Ste A Farmingdale",
    "iso:country":"US",
    "sg:address":"199 Merritts Rd Ste A",
    "sg:city":"Farmingdale",
    "sg:classifiers":[
        {
            "category":"Personal",
            "subcategory":"Beauty Salon",
            "type":"Services"
        }
    ],
    "sg:phone":"+1 516 756 7929",
    "sg:postcode":"11735",
    "sg:province":"NY",
    "sg:website":"http://www.meritcleaners.com",
    "wof:name":"Par-T Mania Inc",
    "wof:placetype":"venue"
},
  "geometry": {"coordinates":[-73.458511,40.723652],"type":"Point"}
}