{
  "type": "Feature",
  "properties": {
    "addr:full":"89 Forest Ave Glen Cove NY 11542",
    "addr:housenumber":"89",
    "addr:postcode":"11542",
    "addr:street":"Forest Ave",
    "iso:country":"US",
    "sg:address":"89 Forest Ave",
    "sg:city":"Glen Cove",
    "sg:classifiers":[
        {
            "category":"Deli",
            "type":"Food & Drink"
        },
        {
            "category":"Cafe",
            "type":"Food & Drink"
        }
    ],
    "sg:menulink":"http://www.allmenus.com/ny/glen-cove/239033-glen-cove-bagel-cafe/menu/",
    "sg:phone":"+1 516 671 3354",
    "sg:postcode":"11542",
    "sg:province":"NY",
    "sg:tags":[
        "american"
    ],
    "wof:name":"Glen Cove Bagel Cafe",
    "wof:placetype":"venue"
},
  "geometry": {"coordinates":[-73.622716,40.872839],"type":"Point"}
}