{
  "type": "Feature",
  "properties": {
    "addr:full":"1321 E 94th St Brooklyn NY 11236",
    "addr:housenumber":"1321",
    "addr:postcode":"11236",
    "addr:street":"E 94Th St",
    "iso:country":"US",
    "sg:address":"1321 E 94th St",
    "sg:city":"Brooklyn",
    "sg:classifiers":[
        {
            "category":"Social Services",
            "subcategory":"Adult Care",
            "type":"Services"
        }
    ],
    "sg:phone":"+1 718 257 5504",
    "sg:postcode":"11236",
    "sg:province":"NY",
    "sg:tags":[
        "home",
        "group"
    ],
    "wof:name":"Herbert G Birch Svc",
    "wof:placetype":"venue"
},
  "geometry": {"coordinates":[-73.900617,40.640388],"type":"Point"}
}