{
  "type": "Feature",
  "properties": {
    "addr:full":"1050 2nd Avenue New York NY 10022",
    "addr:housenumber":"1050",
    "addr:postcode":"10022",
    "addr:street":"2Nd Avenue",
    "iso:country":"US",
    "sg:address":"1050 2nd Avenue",
    "sg:city":"New York",
    "sg:classifiers":[
        {
            "category":"Arts & Performance",
            "subcategory":"Art Gallery",
            "type":"Entertainment"
        },
        {
            "category":"Shopping",
            "subcategory":"Antiques",
            "type":"Retail Goods"
        }
    ],
    "sg:phone":"+1 212 759 1153",
    "sg:postcode":"10022",
    "sg:province":"NY",
    "sg:website":"www.scholarsrock.com",
    "wof:name":"The Chinese Art Gallery",
    "wof:placetype":"venue"
},
  "geometry": {"coordinates":[-73.96607899999999,40.758172],"type":"Point"}
}