{
  "type": "Feature",
  "properties": {
    "addr:full":"180 W 20th Street Apt 8V New York NY 10011",
    "addr:housenumber":"180",
    "addr:postcode":"10011",
    "addr:street":"W 20Th Street Apt 8V",
    "iso:country":"US",
    "sg:address":"180 W 20th Street Apt 8V",
    "sg:city":"New York",
    "sg:classifiers":[
        {
            "category":"Real Estate",
            "subcategory":"Real Estate Services",
            "type":"Services"
        }
    ],
    "sg:phone":"+1 212 414 1464",
    "sg:postcode":"10011",
    "sg:province":"NY",
    "sg:tags":[
        "management",
        "property"
    ],
    "wof:name":"The Related Companies Rental",
    "wof:placetype":"venue"
},
  "geometry": {"coordinates":[-73.996486,40.742009],"type":"Point"}
}