{
  "type": "Feature",
  "properties": {
    "iso:country":"US",
    "sg:address":"501 5th Ave",
    "sg:city":"New York",
    "sg:classifiers":[
        {
            "category":"Professional",
            "subcategory":"Art Services",
            "type":"Services"
        }
    ],
    "sg:phone":"+1 212 684 0508",
    "sg:postcode":"10017",
    "sg:province":"NY",
    "sg:tags":[
        "on",
        "graphic",
        "for",
        "air",
        "animation",
        "design"
    ],
    "wof:name":"Mhx Design",
    "wof:placetype":"venue"
},
  "geometry": {"coordinates":[-73.98137199999999,40.752814],"type":"Point"}
}