{
  "type": "Feature",
  "properties": {
    "iso:country":"US",
    "sg:address":"69 Main St",
    "sg:city":"Saranac Lake",
    "sg:classifiers":[
        {
            "category":"Shopping",
            "subcategory":"Pharmacy",
            "type":"Retail Goods"
        }
    ],
    "sg:phone":"+1   ",
    "sg:postcode":"12983",
    "sg:province":"NY",
    "wof:name":"Meyers Drugs",
    "wof:placetype":"venue"
},
  "geometry": {"coordinates":[-74.131671,44.325804],"type":"Point"}
}