{
  "type": "Feature",
  "properties": {
    "addr:full":"18 Gray Ave Greenwich NY 12834",
    "addr:housenumber":"18",
    "addr:postcode":"12834",
    "addr:street":"Gray Ave",
    "iso:country":"US",
    "sg:address":"18 Gray Ave",
    "sg:city":"Greenwich",
    "sg:classifiers":[
        {
            "category":"Health Services",
            "subcategory":"Doctor",
            "type":"Services"
        }
    ],
    "sg:phone":"+1 518 692 9861",
    "sg:postcode":"12834",
    "sg:province":"NY",
    "sg:tags":[
        "physician",
        "surgeon"
    ],
    "wof:name":"William E Carroll DO",
    "wof:placetype":"venue"
},
  "geometry": {"coordinates":[-73.495606,43.09356],"type":"Point"}
}