{
  "type": "Feature",
  "properties": {
    "iso:country":"US",
    "sg:address":"34 Joyce Dr",
    "sg:city":"Spring Valley",
    "sg:classifiers":[
        {
            "category":"Building & Trades",
            "subcategory":"Construction",
            "type":"Services"
        }
    ],
    "sg:phone":"+1 845 356 1360",
    "sg:postcode":"10977",
    "sg:province":"NY",
    "sg:tags":[
        "floor",
        "laying",
        "contractor"
    ],
    "wof:name":"Archer Floors Ltd",
    "wof:placetype":"venue"
},
  "geometry": {"coordinates":[-74.06301000000001,41.079959],"type":"Point"}
}