{
  "type": "Feature",
  "properties": {
    "iso:country":"US",
    "sg:address":"950 Route 146",
    "sg:city":"Clifton Park",
    "sg:classifiers":[
        {
            "category":"Personal",
            "subcategory":"Hair Removal",
            "type":"Services"
        },
        {
            "category":"Personal",
            "subcategory":"Day Spa",
            "type":"Services"
        }
    ],
    "sg:phone":"+1 518 631 2158",
    "sg:postcode":"12065",
    "sg:province":"NY",
    "sg:website":"www.fountainlaser.com",
    "wof:name":"FOUNTAIN LASER & GENETIC ENHANCEMENT CENTER",
    "wof:placetype":"venue"
},
  "geometry": {"coordinates":[-73.805301,42.868064],"type":"Point"}
}