{
  "type": "Feature",
  "properties": {
    "addr:full":"408 Ave J Brooklyn NY 11230",
    "addr:housenumber":"408",
    "addr:postcode":"11230",
    "addr:street":"Ave J",
    "iso:country":"US",
    "sg:address":"408 Ave J",
    "sg:city":"Brooklyn",
    "sg:classifiers":[
        {
            "category":"Social Services",
            "subcategory":"Child Care",
            "type":"Services"
        }
    ],
    "sg:phone":"+1   ",
    "sg:postcode":"11230",
    "sg:province":"NY",
    "sg:tags":[
        "agency",
        "employment",
        "day"
    ],
    "wof:name":"New York Health Care",
    "wof:placetype":"venue"
},
  "geometry": {"coordinates":[-73.971869,40.62395],"type":"Point"}
}