{
  "type": "Feature",
  "properties": {
    "addr:full":"3990 Hylan Blvd Staten Island NY 10308",
    "addr:housenumber":"3990",
    "addr:postcode":"10308",
    "addr:street":"Hylan Blvd",
    "iso:country":"US",
    "sg:address":"3990 Hylan Blvd",
    "sg:city":"Staten Island",
    "sg:classifiers":[
        {
            "category":"Building & Trades",
            "subcategory":"Construction",
            "type":"Services"
        }
    ],
    "sg:phone":"+1 718 356 9311",
    "sg:postcode":"10308",
    "sg:province":"NY",
    "sg:tags":[
        "roofing",
        "contractor"
    ],
    "wof:name":"Bella Home Improvements-Staten",
    "wof:placetype":"venue"
},
  "geometry": {"coordinates":[-74.147103,40.541011],"type":"Point"}
}