{
  "type": "Feature",
  "properties": {
    "addr:full":"2173 86th St Brooklyn NY 11214",
    "addr:housenumber":"2173",
    "addr:postcode":"11214",
    "addr:street":"86Th St",
    "iso:country":"US",
    "sg:address":"2173 86th St",
    "sg:city":"Brooklyn",
    "sg:classifiers":[
        {
            "category":"Banks & Credit Unions",
            "subcategory":"Bank",
            "type":"Services"
        }
    ],
    "sg:phone":"+1 718 954 3700",
    "sg:postcode":"11214",
    "sg:province":"NY",
    "wof:name":"Commerce Bank",
    "wof:placetype":"venue"
},
  "geometry": {"coordinates":[-73.99397,40.602173],"type":"Point"}
}