{
  "type": "Feature",
  "properties": {
    "addr:full":"1 Medical Dr Port Jeffrsn Sta NY 11776",
    "addr:housenumber":"1",
    "addr:postcode":"11776",
    "addr:street":"Medical Dr",
    "iso:country":"US",
    "sg:address":"1 Medical Dr",
    "sg:city":"Port Jeffrsn Sta",
    "sg:classifiers":[
        {
            "category":"Health Services",
            "subcategory":"Doctor",
            "type":"Services"
        }
    ],
    "sg:phone":"+1 631 928 5850",
    "sg:postcode":"11776",
    "sg:province":"NY",
    "sg:tags":[
        "dentist"
    ],
    "wof:name":"Howard A Popper DDS",
    "wof:placetype":"venue"
},
  "geometry": {"coordinates":[-73.042642,40.929763],"type":"Point"}
}