{
  "type": "Feature",
  "properties": {
    "addr:full":"131 Jericho Tpke Ste 302 Jericho NY 11753",
    "addr:housenumber":"131",
    "addr:postcode":"11753",
    "addr:street":"Jericho Tpke Ste 302",
    "iso:country":"US",
    "sg:address":"131 Jericho Tpke Ste 302",
    "sg:city":"Jericho",
    "sg:classifiers":[
        {
            "category":"Professional",
            "subcategory":"Accounting & Tax Preparation",
            "type":"Services"
        }
    ],
    "sg:phone":"+1 516 333 3352",
    "sg:postcode":"11753",
    "sg:province":"NY",
    "sg:tags":[
        "accountant"
    ],
    "wof:name":"Altman Harvey CPA PC",
    "wof:placetype":"venue"
},
  "geometry": {"coordinates":[-73.550797,40.785599],"type":"Point"}
}