{
  "type": "Feature",
  "properties": {
    "iso:country":"US",
    "sg:address":"954 Eastern Pkwy",
    "sg:city":"Brooklyn",
    "sg:classifiers":[
        {
            "category":"Real Estate",
            "subcategory":"Real Estate Agent",
            "type":"Services"
        }
    ],
    "sg:phone":"+1 718 773 3572",
    "sg:postcode":"11213",
    "sg:province":"NY",
    "wof:name":"R C Realty",
    "wof:placetype":"venue"
},
  "geometry": {"coordinates":[-73.938715,40.669174],"type":"Point"}
}