{
  "type": "Feature",
  "properties": {
    "addr:full":"2014 Church Ave Brooklyn NY 11226",
    "addr:housenumber":"2014",
    "addr:postcode":"11226",
    "addr:street":"Church Ave",
    "iso:country":"US",
    "sg:address":"2014 Church Ave",
    "sg:city":"Brooklyn",
    "sg:classifiers":[
        {
            "category":"Social Services",
            "type":"Services"
        }
    ],
    "sg:phone":"+1   ",
    "sg:postcode":"11226",
    "sg:province":"NY",
    "wof:name":"Youth For Education & Sports",
    "wof:placetype":"venue"
},
  "geometry": {"coordinates":[-73.960077,40.650117],"type":"Point"}
}