{
  "type": "Feature",
  "properties": {
    "iso:country":"US",
    "sg:address":"971 Lexington Ave",
    "sg:city":"New York",
    "sg:classifiers":[
        {
            "category":"Shopping",
            "subcategory":"Hobbies, Toys, & Games",
            "type":"Retail Goods"
        }
    ],
    "sg:phone":"+1 212 717 0477",
    "sg:postcode":"11221",
    "sg:province":"NY",
    "sg:tags":[
        "shop",
        "hobby"
    ],
    "wof:name":"Knits Incredible",
    "wof:placetype":"venue"
},
  "geometry": {"coordinates":[-73.924436,40.690828],"type":"Point"}
}