{
  "type": "Feature",
  "properties": {
    "addr:full":"2269 Saw Mill River Rd Elmsford NY 10523",
    "addr:housenumber":"2269",
    "addr:postcode":"10523",
    "addr:street":"Saw Mill River Rd",
    "iso:country":"US",
    "sg:address":"2269 Saw Mill River Rd",
    "sg:city":"Elmsford",
    "sg:classifiers":[
        {
            "category":"Building & Trades",
            "subcategory":"Plumbing",
            "type":"Services"
        }
    ],
    "sg:phone":"+1 914 961 4235",
    "sg:postcode":"10523",
    "sg:province":"NY",
    "sg:tags":[
        "plumbing",
        "contractor"
    ],
    "wof:name":"J J Morris Bros",
    "wof:placetype":"venue"
},
  "geometry": {"coordinates":[-73.82258,41.047002],"type":"Point"}
}