{
  "type": "Feature",
  "properties": {
    "iso:country":"US",
    "sg:address":"38 Lake Rd",
    "sg:city":"Congers",
    "sg:classifiers":[
        {
            "category":"Restaurant",
            "type":"Food & Drink"
        }
    ],
    "sg:phone":"+1 845 267 0666",
    "sg:postcode":"10920",
    "sg:province":"NY",
    "sg:tags":[
        "pizza"
    ],
    "wof:name":"Primavera Pizza Inc",
    "wof:placetype":"venue"
},
  "geometry": {"coordinates":[-73.940544,41.150283],"type":"Point"}
}