{
  "type": "Feature",
  "properties": {
    "iso:country":"US",
    "sg:address":"7304 5th Ave",
    "sg:city":"Brooklyn",
    "sg:classifiers":[
        {
            "category":"Professional",
            "subcategory":"Business Services",
            "type":"Services"
        }
    ],
    "sg:phone":"+1 718 630 5655",
    "sg:postcode":"11209",
    "sg:province":"NY",
    "sg:tags":[
        "packaging",
        "labeling"
    ],
    "wof:name":"Ship Rite",
    "wof:placetype":"venue"
},
  "geometry": {"coordinates":[-74.02204500000001,40.630944],"type":"Point"}
}