{
  "type": "Feature",
  "properties": {
    "addr:full":"10 E 78th Street New York NY 10021",
    "addr:housenumber":"10",
    "addr:postcode":"10021",
    "addr:street":"E 78Th Street",
    "iso:country":"US",
    "sg:address":"10 E 78th Street",
    "sg:city":"New York",
    "sg:classifiers":[
        {
            "category":"Health Services",
            "subcategory":"Doctor",
            "type":"Services"
        }
    ],
    "sg:phone":"+1 212 721 2620",
    "sg:postcode":"10021",
    "sg:province":"NY",
    "wof:name":"Katzman Melanie PHD",
    "wof:placetype":"venue"
},
  "geometry": {"coordinates":[-73.963881,40.776136],"type":"Point"}
}