{
  "type": "Feature",
  "properties": {
    "addr:full":"2949 Monroe Ave Rochester NY 14618",
    "addr:housenumber":"2949",
    "addr:postcode":"14618",
    "addr:street":"Monroe Ave",
    "iso:country":"US",
    "sg:address":"2949 Monroe Ave",
    "sg:city":"Rochester",
    "sg:classifiers":[
        {
            "category":"Restaurant",
            "type":"Food & Drink"
        }
    ],
    "sg:menulink":"http://www.allmenus.com/ny/pittsford/215437-atlanta-bread-company/menu/",
    "sg:phone":"+1 585 461 1430",
    "sg:postcode":"14618",
    "sg:province":"NY",
    "sg:tags":[
        "american"
    ],
    "wof:name":"Atlanta Bread Company",
    "wof:placetype":"venue"
},
  "geometry": {"coordinates":[-77.546537,43.109569],"type":"Point"}
}