{
  "type": "Feature",
  "properties": {
    "addr:full":"330 Bowery New York NY 10012",
    "addr:housenumber":"330",
    "addr:postcode":"10012",
    "addr:street":"Bowery",
    "iso:country":"US",
    "sg:address":"330 Bowery",
    "sg:city":"New York",
    "sg:classifiers":[
        {
            "category":"Arts & Performance",
            "subcategory":"Arts Center",
            "type":"Entertainment"
        }
    ],
    "sg:phone":"+1 212 677 0060",
    "sg:postcode":"10012",
    "sg:province":"NY",
    "sg:tags":[
        "performing"
    ],
    "wof:name":"Jean Cocteau Repertory Theatre",
    "wof:placetype":"venue"
},
  "geometry": {"coordinates":[-73.992104,40.725601],"type":"Point"}
}