{
  "type": "Feature",
  "properties": {
    "addr:full":"139 1st Ave New York NY 10003",
    "addr:housenumber":"139",
    "addr:postcode":"10003",
    "addr:street":"1St Ave",
    "iso:country":"US",
    "sg:address":"139 1st Ave",
    "sg:city":"New York",
    "sg:classifiers":[
        {
            "category":"Autos & Motor Vehicles",
            "subcategory":"Automobile Sales",
            "type":"Retail Goods"
        }
    ],
    "sg:phone":"+1 212 505 6004",
    "sg:postcode":"10003",
    "sg:province":"NY",
    "sg:tags":[
        "limo"
    ],
    "sg:website":"www.telavivlimo.com/",
    "wof:name":"Tel-Aviv Car & Limousine Service",
    "wof:placetype":"venue"
},
  "geometry": {"coordinates":[-73.98537,40.728058],"type":"Point"}
}