{
  "type": "Feature",
  "properties": {
    "iso:country":"US",
    "sg:address":"8562 Niagara Falls Blvd",
    "sg:city":"Niagara Falls",
    "sg:classifiers":[
        {
            "category":"Restaurant",
            "type":"Food & Drink"
        }
    ],
    "sg:menulink":"http://www.allmenus.com/ny/niagara-falls/175259-arbys/menu/",
    "sg:phone":"+1 716 297 5090",
    "sg:postcode":"14304",
    "sg:province":"NY",
    "sg:tags":[
        "burger",
        "american"
    ],
    "wof:name":"Arby's",
    "wof:placetype":"venue"
},
  "geometry": {"coordinates":[-78.96592699999999,43.091529],"type":"Point"}
}