{
  "type": "Feature",
  "properties": {
    "addr:full":"136 E Genesee St Wellsville NY 14895",
    "addr:housenumber":"136",
    "addr:postcode":"14895",
    "addr:street":"E Genesee St",
    "iso:country":"US",
    "sg:address":"136 E Genesee St",
    "sg:city":"Wellsville",
    "sg:classifiers":[
        {
            "category":"Sports & Exercise",
            "subcategory":"Race Track",
            "type":"Entertainment"
        }
    ],
    "sg:phone":"+1 585 593 6984",
    "sg:postcode":"14895",
    "sg:province":"NY",
    "sg:tags":[
        "operation",
        "racing",
        "or"
    ],
    "wof:name":"D & P Motorsports Inc",
    "wof:placetype":"venue"
},
  "geometry": {"coordinates":[-77.94753300000001,42.12554],"type":"Point"}
}