{
  "type": "Feature",
  "properties": {
    "addr:full":"28 Linden Ct Clifton Park NY 12065",
    "addr:housenumber":"28",
    "addr:postcode":"12065",
    "addr:street":"Linden Ct",
    "iso:country":"US",
    "sg:address":"28 Linden Ct",
    "sg:city":"Clifton Park",
    "sg:classifiers":[
        {
            "category":"Home & Garden",
            "subcategory":"Hardware",
            "type":"Retail Goods"
        }
    ],
    "sg:phone":"+1   ",
    "sg:postcode":"12065",
    "sg:province":"NY",
    "wof:name":"Joseph Miclette",
    "wof:placetype":"venue"
},
  "geometry": {"coordinates":[-73.789316,42.845261],"type":"Point"}
}