{
  "type": "Feature",
  "properties": {
    "addr:full":"700 Cortelyou Road Brooklyn NY 11218",
    "addr:housenumber":"700",
    "addr:postcode":"11218",
    "addr:street":"Cortelyou Road",
    "iso:country":"US",
    "sg:address":"700 Cortelyou Road",
    "sg:city":"Brooklyn",
    "sg:classifiers":[
        {
            "category":"Education",
            "subcategory":"School",
            "type":"Public Place"
        }
    ],
    "sg:phone":"+1 718 941 5450",
    "sg:postcode":"11218",
    "sg:province":"NY",
    "sg:tags":[
        "high",
        "middle",
        "elementary"
    ],
    "wof:name":"N Y City of",
    "wof:placetype":"venue"
},
  "geometry": {"coordinates":[-73.97143199999999,40.6386],"type":"Point"}
}