{
  "type": "Feature",
  "properties": {
    "addr:full":"39 Scott St Huntington Station NY 11746",
    "addr:housenumber":"39",
    "addr:postcode":"11746",
    "addr:street":"Scott St",
    "iso:country":"US",
    "sg:address":"39 Scott St",
    "sg:city":"Huntington Station",
    "sg:classifiers":[
        {
            "category":"Health Services",
            "subcategory":"Optometrist",
            "type":"Services"
        }
    ],
    "sg:phone":"+1   ",
    "sg:postcode":"11746",
    "sg:province":"NY",
    "wof:name":"Jason Seligman Od PC",
    "wof:placetype":"venue"
},
  "geometry": {"coordinates":[-73.349807,40.775661],"type":"Point"}
}