{
  "type": "Feature",
  "properties": {
    "iso:country":"US",
    "sg:address":"175 5th Ave",
    "sg:city":"New York",
    "sg:classifiers":[
        {
            "category":"Professional",
            "subcategory":"Management & Consulting",
            "type":"Services"
        }
    ],
    "sg:phone":"+1 212 253 6474",
    "sg:postcode":"10010",
    "sg:province":"NY",
    "sg:tags":[
        "consultant",
        "business"
    ],
    "wof:name":"Martin R Lewis Assoc",
    "wof:placetype":"venue"
},
  "geometry": {"coordinates":[-73.98962899999999,40.741285],"type":"Point"}
}