{
  "type": "Feature",
  "properties": {
    "iso:country":"US",
    "sg:address":"2794 Co Rd 10",
    "sg:city":"Canandaigua",
    "sg:classifiers":[
        {
            "category":"Education",
            "subcategory":"Dance Studio",
            "type":"Public Place"
        }
    ],
    "sg:phone":"+1 585 394 6096",
    "sg:postcode":"14424",
    "sg:province":"NY",
    "wof:name":"Canandaigua Dance Studio",
    "wof:placetype":"venue"
},
  "geometry": {"coordinates":[-77.24578200000001,42.896469],"type":"Point"}
}