{
  "type": "Feature",
  "properties": {
    "addr:full":"2286 Richmond Rd Staten Island NY 10306",
    "addr:housenumber":"2286",
    "addr:postcode":"10306",
    "addr:street":"Richmond Rd",
    "iso:country":"US",
    "sg:address":"2286 Richmond Rd",
    "sg:city":"Staten Island",
    "sg:classifiers":[
        {
            "category":"Shopping",
            "subcategory":"Florist",
            "type":"Retail Goods"
        }
    ],
    "sg:phone":"+1   ",
    "sg:postcode":"10306",
    "sg:province":"NY",
    "sg:tags":[
        "plant",
        "flower",
        "gift",
        "accent",
        "fresh",
        "go",
        "home",
        "potted"
    ],
    "sg:website":"www.moravianflorist.com",
    "wof:name":"Moravian Florist",
    "wof:placetype":"venue"
},
  "geometry": {"coordinates":[-74.116389,40.578343],"type":"Point"}
}