{
  "type": "Feature",
  "properties": {
    "addr:full":"315 E Kingsbridge Rd Bronx NY 10458",
    "addr:housenumber":"315",
    "addr:postcode":"10458",
    "addr:street":"E Kingsbridge Rd",
    "iso:country":"US",
    "sg:address":"315 E Kingsbridge Rd",
    "sg:city":"Bronx",
    "sg:classifiers":[
        {
            "category":"Professional",
            "type":"Services"
        }
    ],
    "sg:phone":"+1 718 502 5000",
    "sg:postcode":"10458",
    "sg:province":"NY",
    "sg:tags":[
        "establishment"
    ],
    "wof:name":"Schneider & Kleinick",
    "wof:placetype":"venue"
},
  "geometry": {"coordinates":[-73.894035,40.862732],"type":"Point"}
}