{
  "type": "Feature",
  "properties": {
    "iso:country":"US",
    "sg:address":"4747 Nesconset Hwy",
    "sg:city":"Port Jefferson Station",
    "sg:classifiers":[
        {
            "category":"Home & Garden",
            "subcategory":"Furniture",
            "type":"Retail Goods"
        }
    ],
    "sg:phone":"+1 631 928 2952",
    "sg:postcode":"11776",
    "sg:province":"NY",
    "sg:tags":[
        "c",
        "material",
        "carpentry"
    ],
    "wof:name":"Top Drawer Custom Kitchens",
    "wof:placetype":"venue"
},
  "geometry": {"coordinates":[-73.053094,40.918406],"type":"Point"}
}