{
  "type": "Feature",
  "properties": {
    "iso:country":"US",
    "sg:address":"359 Riverview Rd",
    "sg:city":"Rexford",
    "sg:classifiers":[
        {
            "category":"Shopping",
            "subcategory":"Clothing, Apparel, & Fashions",
            "type":"Retail Goods"
        }
    ],
    "sg:phone":"+1 518 371 5484",
    "sg:postcode":"12148",
    "sg:province":"NY",
    "sg:tags":[
        "clothing",
        "glove",
        "store"
    ],
    "wof:name":"Deborah J Reardon",
    "wof:placetype":"venue"
},
  "geometry": {"coordinates":[-73.828875,42.797061],"type":"Point"}
}