{
  "type": "Feature",
  "properties": {
    "addr:full":"10 Lake Dr New Hyde Park NY 11040",
    "addr:housenumber":"10",
    "addr:postcode":"11040",
    "addr:street":"Lake Dr New",
    "iso:country":"US",
    "sg:address":"10 Lake Dr",
    "sg:city":"New Hyde Park",
    "sg:classifiers":[
        {
            "category":"Health Services",
            "subcategory":"Health Practitioner",
            "type":"Services"
        }
    ],
    "sg:phone":"+1   ",
    "sg:postcode":"11040",
    "sg:province":"NY",
    "wof:name":"Paula Modugno Okin",
    "wof:placetype":"venue"
},
  "geometry": {"coordinates":[-73.678239,40.759618],"type":"Point"}
}