{
  "type": "Feature",
  "properties": {
    "addr:full":"1815 Park Ave New York NY 10035",
    "addr:housenumber":"1815",
    "addr:postcode":"10035",
    "addr:street":"Park Ave",
    "iso:country":"US",
    "sg:address":"1815 Park Ave",
    "sg:city":"New York",
    "sg:classifiers":[
        {
            "category":"Personal",
            "subcategory":"Beauty Salon",
            "type":"Services"
        }
    ],
    "sg:phone":"+1 212 828 0100",
    "sg:postcode":"10035",
    "sg:province":"NY",
    "wof:name":"Maria's African Hair Braiding",
    "wof:placetype":"venue"
},
  "geometry": {"coordinates":[-73.939261,40.804496],"type":"Point"}
}