{
  "type": "Feature",
  "properties": {
    "addr:full":"7501 15th Ave Brooklyn NY 11228",
    "addr:housenumber":"7501",
    "addr:postcode":"11228",
    "addr:street":"15Th Ave",
    "iso:country":"US",
    "sg:address":"7501 15th Ave",
    "sg:city":"Brooklyn",
    "sg:classifiers":[
        {
            "category":"Real Estate",
            "subcategory":"Real Estate Operator",
            "type":"Services"
        }
    ],
    "sg:phone":"+1 718 232 9197",
    "sg:postcode":"11228",
    "sg:province":"NY",
    "sg:tags":[
        "building",
        "nonresidential"
    ],
    "wof:name":"Larm Properties LLC",
    "wof:placetype":"venue"
},
  "geometry": {"coordinates":[-74.003652,40.617041],"type":"Point"}
}