{
  "type": "Feature",
  "properties": {
    "addr:full":"1608 5th Ave Bay Shore NY 11706",
    "addr:housenumber":"1608",
    "addr:postcode":"11706",
    "addr:street":"5Th Ave",
    "iso:country":"US",
    "sg:address":"1608 5th Ave",
    "sg:city":"Bay Shore",
    "sg:classifiers":[
        {
            "category":"Retail",
            "subcategory":"Car Wash",
            "type":"Services"
        }
    ],
    "sg:phone":"+1 631 665 7597",
    "sg:postcode":"11706",
    "sg:province":"NY",
    "wof:name":"Fifth Ave Car Wash",
    "wof:placetype":"venue"
},
  "geometry": {"coordinates":[-73.262199,40.756901],"type":"Point"}
}