{
  "type": "Feature",
  "properties": {
    "addr:full":"12 Crescent Rd Port Washington NY 11050",
    "addr:housenumber":"12",
    "addr:postcode":"11050",
    "addr:street":"Crescent Rd",
    "iso:country":"US",
    "sg:address":"12 Crescent Rd",
    "sg:city":"Port Washington",
    "sg:classifiers":[
        {
            "category":"Wholesale",
            "subcategory":"Home Furnishings",
            "type":"Manufacturing & Wholesale Goods"
        }
    ],
    "sg:phone":"+1 516 767 3221",
    "sg:postcode":"11050",
    "sg:province":"NY",
    "sg:tags":[
        "housewares",
        "representative",
        "manufacturer"
    ],
    "wof:name":"Eileen Fischer Associates",
    "wof:placetype":"venue"
},
  "geometry": {"coordinates":[-73.680452,40.834526],"type":"Point"}
}