{
  "type": "Feature",
  "properties": {
    "iso:country":"US",
    "sg:address":"582 Middle Rd",
    "sg:city":"Bayport",
    "sg:classifiers":[
        {
            "category":"Personal",
            "subcategory":"Beauty Salon",
            "type":"Services"
        }
    ],
    "sg:phone":"+1   ",
    "sg:postcode":"11705",
    "sg:province":"NY",
    "sg:tags":[
        "shop"
    ],
    "wof:name":"Spotlight Beauty Salon",
    "wof:placetype":"venue"
},
  "geometry": {"coordinates":[-73.051413,40.738021],"type":"Point"}
}