{
  "type": "Feature",
  "properties": {
    "iso:country":"US",
    "sg:address":"36 Washington St",
    "sg:city":"Cattaraugus",
    "sg:classifiers":[
        {
            "category":"Organizations",
            "subcategory":"Religious Organization",
            "type":"Services"
        }
    ],
    "sg:phone":"+1   ",
    "sg:postcode":"14719",
    "sg:province":"NY",
    "wof:name":"Saint Marys Church Inc",
    "wof:placetype":"venue"
},
  "geometry": {"coordinates":[-78.867864,42.3299],"type":"Point"}
}