{
  "type": "Feature",
  "properties": {
    "addr:full":"105 Daywood Dr Baldwinsville NY 13027",
    "addr:housenumber":"105",
    "addr:postcode":"13027",
    "addr:street":"Daywood Dr",
    "iso:country":"US",
    "sg:address":"105 Daywood Dr",
    "sg:city":"Baldwinsville",
    "sg:classifiers":[
        {
            "category":"Manufacturing",
            "subcategory":"Apparel",
            "type":"Manufacturing & Wholesale Goods"
        }
    ],
    "sg:phone":"+1 315 635 3832",
    "sg:postcode":"13027",
    "sg:province":"NY",
    "sg:tags":[
        "sewing",
        "contractor"
    ],
    "wof:name":"Stacey's Stitching",
    "wof:placetype":"venue"
},
  "geometry": {"coordinates":[-76.30861,43.133718],"type":"Point"}
}