{
  "type": "Feature",
  "properties": {
    "addr:full":"3900 Veterans Memorial Hwy Bohemia NY 11716",
    "addr:housenumber":"3900",
    "addr:postcode":"11716",
    "addr:street":"Veterans Memorial Hwy",
    "iso:country":"US",
    "sg:address":"3900 Veterans Memorial Hwy",
    "sg:city":"Bohemia",
    "sg:classifiers":[
        {
            "category":"Education",
            "subcategory":"Vocational School",
            "type":"Public Place"
        }
    ],
    "sg:phone":"+1 631 981 1048",
    "sg:postcode":"11716",
    "sg:province":"NY",
    "sg:tags":[
        "training",
        "computer"
    ],
    "sg:website":"www.visionwarrior.com",
    "wof:name":"Hcs Training Ctr",
    "wof:placetype":"venue"
},
  "geometry": {"coordinates":[-73.10922600000001,40.784474],"type":"Point"}
}