{
  "type": "Feature",
  "properties": {
    "iso:country":"US",
    "sg:address":"1255 Amsterdam Avenue",
    "sg:city":"New York",
    "sg:classifiers":[
        {
            "category":"Education",
            "subcategory":"University",
            "type":"Public Place"
        }
    ],
    "sg:phone":"+1 914 251 6880",
    "sg:postcode":"10027",
    "sg:province":"NY",
    "sg:tags":[
        "college"
    ],
    "sg:website":"www.columbia.edu/cu/ssw",
    "wof:name":"Columbia University School Of Social Work",
    "wof:placetype":"venue"
},
  "geometry": {"coordinates":[-73.95794600000001,40.80994],"type":"Point"}
}