{
  "type": "Feature",
  "properties": {
    "iso:country":"US",
    "sg:address":"88 Harrison St",
    "sg:city":"West Harrison",
    "sg:classifiers":[
        {
            "category":"Shopping",
            "subcategory":"Crafts & Fabrics",
            "type":"Retail Goods"
        }
    ],
    "sg:phone":"+1 914 328 5706",
    "sg:postcode":"10604",
    "sg:province":"NY",
    "sg:tags":[
        "yarn"
    ],
    "wof:name":"Yarns N Notions",
    "wof:placetype":"venue"
},
  "geometry": {"coordinates":[-73.74830300000001,41.039234],"type":"Point"}
}