{
  "type": "Feature",
  "properties": {
    "addr:full":"72 Thompson St New York NY 10012",
    "addr:housenumber":"72",
    "addr:postcode":"10012",
    "addr:street":"Thompson St",
    "iso:country":"US",
    "sg:address":"72 Thompson St",
    "sg:city":"New York",
    "sg:classifiers":[
        {
            "category":"Professional",
            "type":"Services"
        },
        {
            "category":"Shopping",
            "subcategory":"Florist",
            "type":"Retail Goods"
        }
    ],
    "sg:phone":"+1 212 274 1887",
    "sg:postcode":"10012",
    "sg:province":"NY",
    "sg:tags":[
        "establishment"
    ],
    "wof:name":"Flora New York Inc",
    "wof:placetype":"venue"
},
  "geometry": {"coordinates":[-74.003112,40.723974],"type":"Point"}
}