{
  "type": "Feature",
  "properties": {
    "addr:full":"9952 US Hwy 219 West Valley NY 14171",
    "addr:housenumber":"9952",
    "addr:postcode":"14171",
    "addr:street":"Us Hwy 219 West",
    "iso:country":"US",
    "sg:address":"9952 US Hwy 219",
    "sg:city":"West Valley",
    "sg:classifiers":[
        {
            "category":"Shopping",
            "subcategory":"Musical Instruments",
            "type":"Retail Goods"
        }
    ],
    "sg:phone":"+1   ",
    "sg:postcode":"14171",
    "sg:province":"NY",
    "sg:tags":[
        "pipe",
        "repair",
        "organs",
        "mfg"
    ],
    "wof:name":"Heritage Pipe Organs Inc",
    "wof:placetype":"venue"
},
  "geometry": {"coordinates":[-78.60367599999999,42.380465],"type":"Point"}
}