{
  "type": "Feature",
  "properties": {
    "addr:full":"44 W 4 St New York NY 10012",
    "addr:housenumber":"44;4",
    "addr:postcode":"10012",
    "addr:street":"W;St",
    "iso:country":"US",
    "sg:address":"44 W 4 St",
    "sg:city":"New York",
    "sg:classifiers":[
        {
            "category":"Education",
            "subcategory":"College",
            "type":"Public Place"
        }
    ],
    "sg:phone":"+1 212 998 0630",
    "sg:postcode":"10012",
    "sg:province":"NY",
    "sg:tags":[
        "university"
    ],
    "wof:name":"Stern Graduate School Business",
    "wof:placetype":"venue"
},
  "geometry": {"coordinates":[-73.99541000000001,40.728829],"type":"Point"}
}