{
  "type": "Feature",
  "properties": {
    "iso:country":"US",
    "sg:address":"105 Reid St",
    "sg:city":"Fort Plain",
    "sg:classifiers":[
        {
            "category":"Travel",
            "subcategory":"Hotels & Motels",
            "type":"Entertainment"
        }
    ],
    "sg:phone":"+1 518 993 3339",
    "sg:postcode":"13339",
    "sg:province":"NY",
    "sg:tags":[
        "breakfast",
        "accommodation",
        "bed"
    ],
    "wof:name":"A White Rose Bed & Breakfast",
    "wof:placetype":"venue"
},
  "geometry": {"coordinates":[-74.63637900000001,42.928898],"type":"Point"}
}