{
  "type": "Feature",
  "properties": {
    "iso:country":"US",
    "sg:address":"990 South Ave",
    "sg:city":"Rochester",
    "sg:classifiers":[
        {
            "category":"Health Services",
            "subcategory":"Doctor",
            "type":"Services"
        }
    ],
    "sg:phone":"+1 585 244 2084",
    "sg:postcode":"14620",
    "sg:province":"NY",
    "sg:tags":[
        "gynecology",
        "physician",
        "surgeon",
        "surgeons",
        "obstetrics"
    ],
    "wof:name":"Olander Roger M MD PC",
    "wof:placetype":"venue"
},
  "geometry": {"coordinates":[-77.607716,43.135329],"type":"Point"}
}