{
  "type": "Feature",
  "properties": {
    "addr:full":"68 Baybright Dr W Shirley NY 11967",
    "addr:housenumber":"68",
    "addr:postcode":"11967",
    "addr:street":"Baybright Dr W",
    "iso:country":"US",
    "sg:address":"68 Baybright Dr W",
    "sg:city":"Shirley",
    "sg:classifiers":[
        {
            "category":"Building & Trades",
            "subcategory":"Electrical",
            "type":"Services"
        }
    ],
    "sg:phone":"+1 631 334 7982",
    "sg:postcode":"11967",
    "sg:province":"NY",
    "sg:tags":[
        "electrical",
        "contractor"
    ],
    "wof:name":"Fitzer J Electrical Contractor",
    "wof:placetype":"venue"
},
  "geometry": {"coordinates":[-72.873542,40.754261],"type":"Point"}
}