{
  "type": "Feature",
  "properties": {
    "iso:country":"US",
    "sg:address":"1240 W 1st St",
    "sg:city":"Elmira",
    "sg:classifiers":[
        {
            "category":"Building & Trades",
            "subcategory":"Electrical",
            "type":"Services"
        }
    ],
    "sg:phone":"+1 607 733 4305",
    "sg:postcode":"14905",
    "sg:province":"NY",
    "sg:tags":[
        "communications",
        "installation"
    ],
    "wof:name":"Lightspeed Tl/Data Ntworks Inc",
    "wof:placetype":"venue"
},
  "geometry": {"coordinates":[-76.841746,42.08136],"type":"Point"}
}