{
  "type": "Feature",
  "properties": {
    "iso:country":"US",
    "sg:address":"10 W 47 St",
    "sg:city":"New York",
    "sg:classifiers":[
        {
            "category":"Manufacturing",
            "subcategory":"Jewelry",
            "type":"Manufacturing & Wholesale Goods"
        }
    ],
    "sg:phone":"+1   ",
    "sg:postcode":"10036",
    "sg:province":"NY",
    "sg:tags":[
        "costume",
        "mfg"
    ],
    "wof:name":"Hope of Manhattan Corporation",
    "wof:placetype":"venue"
},
  "geometry": {"coordinates":[-73.981627,40.757842],"type":"Point"}
}