{
  "type": "Feature",
  "properties": {
    "iso:country":"US",
    "sg:address":"20 Railroad Ave",
    "sg:city":"Albany",
    "sg:classifiers":[
        {
            "category":"Taxi",
            "type":"Transportation"
        },
        {
            "category":"Freight",
            "type":"Transportation"
        },
        {
            "category":"Government",
            "subcategory":"Post Office",
            "type":"Public Place"
        }
    ],
    "sg:phone":"+1 518 495 5996",
    "sg:postcode":"12205",
    "sg:province":"NY",
    "sg:tags":[
        "delivery",
        "local",
        "courier",
        "trucking"
    ],
    "sg:website":"http://www.themanvan.us/",
    "wof:name":"A Man With A Van, LLC",
    "wof:placetype":"venue"
},
  "geometry": {"coordinates":[-73.811436,42.69183],"type":"Point"}
}