{
  "type": "Feature",
  "properties": {
    "addr:full":"28 Green Ave Patchogue NY 11772",
    "addr:housenumber":"28",
    "addr:postcode":"11772",
    "addr:street":"Green Ave",
    "iso:country":"US",
    "sg:address":"28 Green Ave",
    "sg:city":"Patchogue",
    "sg:classifiers":[
        {
            "category":"Home & Garden",
            "subcategory":"Building Materials",
            "type":"Retail Goods"
        }
    ],
    "sg:phone":"+1 631 207 2559",
    "sg:postcode":"11772",
    "sg:province":"NY",
    "sg:tags":[
        "screen",
        "window"
    ],
    "wof:name":"Ivy Bay Window Screening",
    "wof:placetype":"venue"
},
  "geometry": {"coordinates":[-73.02901799999999,40.78226],"type":"Point"}
}