{
  "type": "Feature",
  "properties": {
    "addr:full":"12 Lynwood Rd Scarsdale NY 10583",
    "addr:housenumber":"12",
    "addr:postcode":"10583",
    "addr:street":"Lynwood Rd",
    "iso:country":"US",
    "sg:address":"12 Lynwood Rd",
    "sg:city":"Scarsdale",
    "sg:classifiers":[
        {
            "category":"Personal",
            "subcategory":"Beauty Salon",
            "type":"Services"
        }
    ],
    "sg:phone":"+1   ",
    "sg:postcode":"10583",
    "sg:province":"NY",
    "sg:tags":[
        "shop"
    ],
    "wof:name":"Stanley Shampoo",
    "wof:placetype":"venue"
},
  "geometry": {"coordinates":[-73.81195200000001,40.987869],"type":"Point"}
}