{
  "type": "Feature",
  "properties": {
    "addr:full":"701 Post Rd Scarsdale NY 10583",
    "addr:housenumber":"701",
    "addr:postcode":"10583",
    "addr:street":"Post Rd",
    "iso:country":"US",
    "sg:address":"701 Post Rd",
    "sg:city":"Scarsdale",
    "sg:classifiers":[
        {
            "category":"Shopping",
            "subcategory":"Clothing, Apparel, & Fashions",
            "type":"Retail Goods"
        }
    ],
    "sg:phone":"+1 914 725 9855",
    "sg:postcode":"10583",
    "sg:province":"NY",
    "sg:tags":[
        "rental",
        "tuxedo",
        "men's",
        "sale",
        "wear",
        "clothing",
        "formal"
    ],
    "sg:website":"http://www.josbank.com",
    "wof:name":"JoS. A. Bank",
    "wof:placetype":"venue"
},
  "geometry": {"coordinates":[-73.802498,40.976814],"type":"Point"}
}