{
  "type": "Feature",
  "properties": {
    "iso:country":"US",
    "sg:address":"20 Cherry Ave",
    "sg:city":"New Rochelle",
    "sg:classifiers":[
        {
            "category":"Shopping",
            "subcategory":"Beauty & Cosmetics",
            "type":"Retail Goods"
        }
    ],
    "sg:phone":"+1   ",
    "sg:postcode":"10801",
    "sg:province":"NY",
    "sg:tags":[
        "merchandise"
    ],
    "wof:name":"Merle Pearlmutter",
    "wof:placetype":"venue"
},
  "geometry": {"coordinates":[-73.76694000000001,40.91833],"type":"Point"}
}