{
  "type": "Feature",
  "properties": {
    "addr:full":"5205 31st Place Long Island City NY 11101",
    "addr:housenumber":"5205",
    "addr:postcode":"11101",
    "addr:street":"31St Place",
    "iso:country":"US",
    "sg:address":"5205 31st Place",
    "sg:city":"Long Island City",
    "sg:classifiers":[
        {
            "category":"Retail",
            "subcategory":"Auto Repair",
            "type":"Services"
        }
    ],
    "sg:phone":"+1 718 937 3939",
    "sg:postcode":"11101",
    "sg:province":"NY",
    "wof:name":"Sportscar Painting",
    "wof:placetype":"venue"
},
  "geometry": {"coordinates":[-73.936967,40.73699],"type":"Point"}
}