{
  "type": "Feature",
  "properties": {
    "addr:full":"6094 67th Ave Ridgewood NY 11385",
    "addr:housenumber":"6094",
    "addr:postcode":"11385",
    "addr:street":"67Th Ave",
    "iso:country":"US",
    "sg:address":"6094 67th Ave",
    "sg:city":"Ridgewood",
    "sg:classifiers":[
        {
            "category":"Food & Beverages",
            "subcategory":"Meat & Fish",
            "type":"Retail Goods"
        }
    ],
    "sg:phone":"+1 718 456 8502",
    "sg:postcode":"11385",
    "sg:province":"NY",
    "sg:tags":[
        "seafood",
        "market"
    ],
    "wof:name":"Joe's Fish Market III",
    "wof:placetype":"venue"
},
  "geometry": {"coordinates":[-73.89659899999999,40.705601],"type":"Point"}
}