{
  "type": "Feature",
  "properties": {
    "iso:country":"US",
    "sg:address":"200 Portion Rd",
    "sg:city":"Lake Ronkonkoma",
    "sg:classifiers":[
        {
            "category":"Restaurant",
            "type":"Food & Drink"
        }
    ],
    "sg:menulink":"http://www.allmenus.com/ny/brookhaven/260806-long-island-grill/menu/",
    "sg:phone":"+1 631 981 7893",
    "sg:postcode":"11779",
    "sg:province":"NY",
    "wof:name":"Long Island Grill",
    "wof:placetype":"venue"
},
  "geometry": {"coordinates":[-73.105345,40.826672],"type":"Point"}
}