{
  "type": "Feature",
  "properties": {
    "iso:country":"US",
    "sg:address":"14 Albion Oval",
    "sg:city":"Mahopac",
    "sg:classifiers":[
        {
            "category":"Manufacturing",
            "subcategory":"Tools & Machinery",
            "type":"Manufacturing & Wholesale Goods"
        }
    ],
    "sg:phone":"+1   ",
    "sg:postcode":"10541",
    "sg:province":"NY",
    "sg:tags":[
        "equipment",
        "calculating",
        "mfg"
    ],
    "wof:name":"Uptown",
    "wof:placetype":"venue"
},
  "geometry": {"coordinates":[-73.715898,41.391669],"type":"Point"}
}