{
  "type": "Feature",
  "properties": {
    "iso:country":"US",
    "sg:address":"5846 Heritage Landing Dr",
    "sg:city":"East Syracuse",
    "sg:classifiers":[
        {
            "category":"Professional",
            "subcategory":"Art Services",
            "type":"Services"
        }
    ],
    "sg:phone":"+1 315 437 7561",
    "sg:postcode":"13057",
    "sg:province":"NY",
    "sg:tags":[
        "graphic",
        "designer"
    ],
    "sg:website":"www.aggraphics.com",
    "wof:name":"Automated Graphics Inc",
    "wof:placetype":"venue"
},
  "geometry": {"coordinates":[-76.048525,43.048207],"type":"Point"}
}