{
  "type": "Feature",
  "properties": {
    "iso:country":"US",
    "sg:address":"1030 46th St",
    "sg:city":"Brooklyn",
    "sg:classifiers":[
        {
            "category":"Retail",
            "subcategory":"Portrait Studio",
            "type":"Services"
        }
    ],
    "sg:phone":"+1   ",
    "sg:postcode":"11219",
    "sg:province":"NY",
    "sg:tags":[
        "photo"
    ],
    "wof:name":"Hr Photography Inc",
    "wof:placetype":"venue"
},
  "geometry": {"coordinates":[-73.996077,40.640166],"type":"Point"}
}