{
  "type": "Feature",
  "properties": {
    "addr:full":"258 W 15th Street New York NY 10011",
    "addr:housenumber":"258",
    "addr:postcode":"10011",
    "addr:street":"W 15Th Street",
    "iso:country":"US",
    "sg:address":"258 W 15th Street",
    "sg:city":"New York",
    "sg:classifiers":[
        {
            "category":"Restaurant",
            "type":"Food & Drink"
        }
    ],
    "sg:phone":"+1 212 255 3601",
    "sg:postcode":"10011",
    "sg:province":"NY",
    "sg:website":"www.penguincafe.com",
    "wof:name":"Penguin Cafe",
    "wof:placetype":"venue"
},
  "geometry": {"coordinates":[-74.001159,40.740012],"type":"Point"}
}