{
  "type": "Feature",
  "properties": {
    "iso:country":"US",
    "sg:address":"2470 Hamburg Tpke",
    "sg:city":"Buffalo",
    "sg:classifiers":[
        {
            "category":"Shopping",
            "subcategory":"Clothing, Apparel, & Fashions",
            "type":"Retail Goods"
        }
    ],
    "sg:phone":"+1 716 824 2424",
    "sg:postcode":"14218",
    "sg:province":"NY",
    "sg:tags":[
        "lingerie"
    ],
    "sg:website":"www.pussy-shaver.com",
    "wof:name":"2424 Hamburg Turnpike",
    "wof:placetype":"venue"
},
  "geometry": {"coordinates":[-78.846755,42.818003],"type":"Point"}
}