{
  "type": "Feature",
  "properties": {
    "addr:full":"30 W 21 St New York NY 10010",
    "addr:housenumber":"30",
    "addr:postcode":"10010",
    "addr:street":"W 21 St",
    "iso:country":"US",
    "sg:address":"30 W 21 St",
    "sg:city":"New York",
    "sg:classifiers":[
        {
            "category":"Professional",
            "type":"Services"
        }
    ],
    "sg:phone":"+1 917 661 0300",
    "sg:postcode":"10010",
    "sg:province":"NY",
    "sg:tags":[
        "establishment"
    ],
    "wof:name":"Idealab New York",
    "wof:placetype":"venue"
},
  "geometry": {"coordinates":[-73.99306300000001,40.741156],"type":"Point"}
}