{
  "type": "Feature",
  "properties": {
    "iso:country":"US",
    "sg:address":"315 W 55th Street Ofc",
    "sg:city":"New York",
    "sg:classifiers":[
        {
            "category":"Health Services",
            "subcategory":"Chiropractor",
            "type":"Services"
        }
    ],
    "sg:phone":"+1 212 459 0400",
    "sg:postcode":"10019",
    "sg:province":"NY",
    "wof:name":"Advanced Care Chiropractic",
    "wof:placetype":"venue"
},
  "geometry": {"coordinates":[-73.984191,40.765612],"type":"Point"}
}