{
  "type": "Feature",
  "properties": {
    "addr:full":"1228 Steuben Hill Rd Herkimer NY 13350",
    "addr:housenumber":"1228",
    "addr:postcode":"13350",
    "addr:street":"Steuben Hill Rd",
    "iso:country":"US",
    "sg:address":"1228 Steuben Hill Rd",
    "sg:city":"Herkimer",
    "sg:classifiers":[
        {
            "category":"Sports & Exercise",
            "subcategory":"Golf",
            "type":"Entertainment"
        }
    ],
    "sg:phone":"+1   ",
    "sg:postcode":"13350",
    "sg:province":"NY",
    "sg:tags":[
        "course",
        "public"
    ],
    "wof:name":"Holland Heights Golf Course",
    "wof:placetype":"venue"
},
  "geometry": {"coordinates":[-75.02621000000001,43.063053],"type":"Point"}
}