{
  "type": "Feature",
  "properties": {
    "iso:country":"US",
    "sg:address":"3060 State Hwy 50",
    "sg:city":"Saratoga Springs",
    "sg:classifiers":[
        {
            "category":"Shopping",
            "subcategory":"Jewelry",
            "type":"Retail Goods"
        }
    ],
    "sg:phone":"+1 518 583 7648",
    "sg:postcode":"12866",
    "sg:province":"NY",
    "sg:tags":[
        "jeweler"
    ],
    "wof:name":"Belden Jewelers",
    "wof:placetype":"venue"
},
  "geometry": {"coordinates":[-73.742617,43.103696],"type":"Point"}
}