{
  "type": "Feature",
  "properties": {
    "iso:country":"US",
    "sg:address":"101 Godfrey Ave",
    "sg:city":"Bayville",
    "sg:classifiers":[
        {
            "category":"Building & Trades",
            "subcategory":"Construction",
            "type":"Services"
        }
    ],
    "sg:phone":"+1 516 628 3397",
    "sg:postcode":"11709",
    "sg:province":"NY",
    "sg:tags":[
        "home",
        "improvement"
    ],
    "wof:name":"Woodcor Inc",
    "wof:placetype":"venue"
},
  "geometry": {"coordinates":[-73.560547,40.905701],"type":"Point"}
}