{
  "type": "Feature",
  "properties": {
    "iso:country":"US",
    "sg:address":"248 4th Ave",
    "sg:city":"Brooklyn",
    "sg:classifiers":[
        {
            "category":"Real Estate",
            "subcategory":"Real Estate Agent",
            "type":"Services"
        }
    ],
    "sg:phone":"+1 718 643 0192",
    "sg:postcode":"11215",
    "sg:province":"NY",
    "wof:name":"Prospect Washington Crop",
    "wof:placetype":"venue"
},
  "geometry": {"coordinates":[-73.983859,40.676393],"type":"Point"}
}