{
  "type": "Feature",
  "properties": {
    "iso:country":"US",
    "sg:address":"22 Westmoreland Ave",
    "sg:city":"White Plains",
    "sg:classifiers":[
        {
            "category":"Wholesale",
            "subcategory":"Auto Parts",
            "type":"Manufacturing & Wholesale Goods"
        }
    ],
    "sg:phone":"+1 914 949 3000",
    "sg:postcode":"10606",
    "sg:province":"NY",
    "sg:tags":[
        "supply"
    ],
    "wof:name":"White Plains Motors",
    "wof:placetype":"venue"
},
  "geometry": {"coordinates":[-73.775569,41.028424],"type":"Point"}
}