{
  "type": "Feature",
  "properties": {
    "iso:country":"US",
    "sg:address":"583 State Hwy 303",
    "sg:city":"Blauvelt",
    "sg:classifiers":[
        {
            "category":"Insurance",
            "subcategory":"Insurance Agent",
            "type":"Services"
        }
    ],
    "sg:phone":"+1 845 359 3200",
    "sg:postcode":"10913",
    "sg:province":"NY",
    "wof:name":"State Farm Insurance",
    "wof:placetype":"venue"
},
  "geometry": {"coordinates":[-73.94788699999999,41.085448],"type":"Point"}
}