{
  "type": "Feature",
  "properties": {
    "addr:full":"783 Franklin St Skaneateles NY 13152",
    "addr:housenumber":"783",
    "addr:postcode":"13152",
    "addr:street":"Franklin St",
    "iso:country":"US",
    "sg:address":"783 Franklin St",
    "sg:city":"Skaneateles",
    "sg:classifiers":[
        {
            "category":"Health Services",
            "subcategory":"Doctor",
            "type":"Services"
        }
    ],
    "sg:phone":"+1 315 685 8988",
    "sg:postcode":"13152",
    "sg:province":"NY",
    "sg:tags":[
        "medical"
    ],
    "wof:name":"Family Care Medical Group",
    "wof:placetype":"venue"
},
  "geometry": {"coordinates":[-76.448812,42.950706],"type":"Point"}
}