{
  "type": "Feature",
  "properties": {
    "addr:full":"146 Maple St Glens Falls NY 12801",
    "addr:housenumber":"146",
    "addr:postcode":"12801",
    "addr:street":"Maple St",
    "iso:country":"US",
    "sg:address":"146 Maple St",
    "sg:city":"Glens Falls",
    "sg:classifiers":[
        {
            "category":"Real Estate",
            "subcategory":"Real Estate Agent",
            "type":"Services"
        }
    ],
    "sg:phone":"+1 518 798 1531",
    "sg:postcode":"12801",
    "sg:province":"NY",
    "wof:name":"Royalview Realty",
    "wof:placetype":"venue"
},
  "geometry": {"coordinates":[-73.639456,43.31166],"type":"Point"}
}