{
  "type": "Feature",
  "properties": {
    "iso:country":"US",
    "sg:address":"250 Broadway",
    "sg:city":"New York",
    "sg:classifiers":[
        {
            "category":"Wholesale",
            "subcategory":"Machinery & Supplies",
            "type":"Manufacturing & Wholesale Goods"
        }
    ],
    "sg:phone":"+1 718 822 4060",
    "sg:postcode":"10007",
    "sg:province":"NY",
    "sg:tags":[
        "landscaping",
        "equipment"
    ],
    "wof:name":"Randall Ave Trailer",
    "wof:placetype":"venue"
},
  "geometry": {"coordinates":[-74.006753,40.713618],"type":"Point"}
}