{
  "type": "Feature",
  "properties": {
    "iso:country":"US",
    "sg:address":"10315 Wagner Dr",
    "sg:city":"Niagara Falls",
    "sg:classifiers":[
        {
            "category":"Government",
            "subcategory":"Office",
            "type":"Public Place"
        }
    ],
    "sg:phone":"+1 716 236 2262",
    "sg:postcode":"14304",
    "sg:province":"NY",
    "sg:tags":[
        "national",
        "security"
    ],
    "wof:name":"Niagra Falls Air Force RES 914",
    "wof:placetype":"venue"
},
  "geometry": {"coordinates":[-78.94068900000001,43.115752],"type":"Point"}
}