{
  "type": "Feature",
  "properties": {
    "addr:full":"268 Stuart Dr New Rochelle NY 10804",
    "addr:housenumber":"268",
    "addr:postcode":"10804",
    "addr:street":"Stuart Dr",
    "iso:country":"US",
    "sg:address":"268 Stuart Dr",
    "sg:city":"New Rochelle",
    "sg:classifiers":[
        {
            "category":"Health Services",
            "subcategory":"Doctor",
            "type":"Services"
        }
    ],
    "sg:phone":"+1 914 235 9020",
    "sg:postcode":"10804",
    "sg:province":"NY",
    "wof:name":"George M Glassman MD",
    "wof:placetype":"venue"
},
  "geometry": {"coordinates":[-73.784351,40.968199],"type":"Point"}
}