{
  "type": "Feature",
  "properties": {
    "addr:full":"222 Teall Ave Ste 100 Syracuse NY 13210",
    "addr:housenumber":"222",
    "addr:postcode":"13210",
    "addr:street":"Teall Ave Ste 100",
    "iso:country":"US",
    "sg:address":"222 Teall Ave Ste 100",
    "sg:city":"Syracuse",
    "sg:phone":"+1 315 471 4128",
    "sg:postcode":"13210",
    "sg:province":"NY",
    "wof:name":"Safety Solutions Inc",
    "wof:placetype":"venue"
},
  "geometry": {"coordinates":[-76.12173900000001,43.051106],"type":"Point"}
}