{
  "type": "Feature",
  "properties": {
    "addr:full":"5 E 98 St New York NY 10029",
    "addr:housenumber":"5;98",
    "addr:postcode":"10029",
    "addr:street":"E;St",
    "iso:country":"US",
    "sg:address":"5 E 98 St",
    "sg:city":"New York",
    "sg:classifiers":[
        {
            "category":"Health Services",
            "subcategory":"Doctor",
            "type":"Services"
        }
    ],
    "sg:phone":"+1 212 831 1473",
    "sg:postcode":"10029",
    "sg:province":"NY",
    "sg:tags":[
        "physician",
        "surgeon"
    ],
    "wof:name":"Daniel Moros MD",
    "wof:placetype":"venue"
},
  "geometry": {"coordinates":[-73.953275,40.788655],"type":"Point"}
}