{
  "type": "Feature",
  "properties": {
    "addr:full":"2776 W Main St Wappingers Falls NY 12590",
    "addr:housenumber":"2776",
    "addr:postcode":"12590",
    "addr:street":"W Main St",
    "iso:country":"US",
    "sg:address":"2776 W Main St",
    "sg:city":"Wappingers Falls",
    "sg:classifiers":[
        {
            "category":"Building & Trades",
            "subcategory":"Plumbing",
            "type":"Services"
        }
    ],
    "sg:phone":"+1 845 298 9300",
    "sg:postcode":"12590",
    "sg:province":"NY",
    "wof:name":"Juliano Heating & Plumbing",
    "wof:placetype":"venue"
},
  "geometry": {"coordinates":[-73.921097,41.605999],"type":"Point"}
}