{
  "type": "Feature",
  "properties": {
    "iso:country":"US",
    "sg:address":"1067 Rutland Rd",
    "sg:city":"Brooklyn",
    "sg:classifiers":[
        {
            "category":"Food & Beverages",
            "subcategory":"Groceries & Convenience Stores",
            "type":"Retail Goods"
        }
    ],
    "sg:phone":"+1 718 467 2301",
    "sg:postcode":"11212",
    "sg:province":"NY",
    "wof:name":"Sultan Grocery Deli Inc",
    "wof:placetype":"venue"
},
  "geometry": {"coordinates":[-73.924638,40.663974],"type":"Point"}
}