{
  "type": "Feature",
  "properties": {
    "addr:full":"301 W. 53rd St New York NY 10019",
    "addr:housenumber":"301",
    "addr:postcode":"10019",
    "addr:street":"W. 53Rd St",
    "iso:country":"US",
    "sg:address":"301 W. 53rd St",
    "sg:city":"New York",
    "sg:classifiers":[
        {
            "category":"Professional",
            "subcategory":"Computer Services",
            "type":"Services"
        }
    ],
    "sg:phone":"+1 617 488 9920",
    "sg:postcode":"10019",
    "sg:province":"NY",
    "sg:tags":[
        "social-network",
        "communication",
        "groups",
        "forum"
    ],
    "sg:website":"http://www.groupie.mobi",
    "wof:name":"Groupie",
    "wof:placetype":"venue"
},
  "geometry": {"coordinates":[-73.98757500000001,40.765364],"type":"Point"}
}