{
  "type": "Feature",
  "properties": {
    "addr:full":"1 W Pearl St Wellsville NY 14895",
    "addr:housenumber":"1",
    "addr:postcode":"14895",
    "addr:street":"W Pearl St",
    "iso:country":"US",
    "sg:address":"1 W Pearl St",
    "sg:city":"Wellsville",
    "sg:classifiers":[
        {
            "category":"Organizations",
            "subcategory":"Religious Organization",
            "type":"Services"
        }
    ],
    "sg:phone":"+1 585 593 2075",
    "sg:postcode":"14895",
    "sg:province":"NY",
    "sg:tags":[
        "church"
    ],
    "wof:name":"Christian Union Church",
    "wof:placetype":"venue"
},
  "geometry": {"coordinates":[-77.950042,42.121977],"type":"Point"}
}