{
  "type": "Feature",
  "properties": {
    "iso:country":"US",
    "sg:address":"249 Tarrytown Rd",
    "sg:city":"White Plains",
    "sg:classifiers":[
        {
            "category":"Home & Garden",
            "subcategory":"Home Furnishings",
            "type":"Retail Goods"
        }
    ],
    "sg:phone":"+1 914 948 8300",
    "sg:postcode":"10607",
    "sg:province":"NY",
    "sg:tags":[
        "bathroom",
        "fixture",
        "accessory"
    ],
    "wof:name":"Ferrari's Kitchens & Bath Home",
    "wof:placetype":"venue"
},
  "geometry": {"coordinates":[-73.788242,41.040544],"type":"Point"}
}