{
  "type": "Feature",
  "properties": {
    "iso:country":"US",
    "sg:address":"284 Schwartz Rd",
    "sg:city":"Lancaster",
    "sg:classifiers":[
        {
            "category":"Home & Garden",
            "subcategory":"Garden Supply",
            "type":"Retail Goods"
        },
        {
            "category":"Building & Trades",
            "subcategory":"Landscaping Services",
            "type":"Services"
        }
    ],
    "sg:phone":"+1 716 683 1136",
    "sg:postcode":"14086",
    "sg:province":"NY",
    "sg:tags":[
        "contractor",
        "landscape",
        "f"
    ],
    "wof:name":"T J Bednarski Nursery",
    "wof:placetype":"venue"
},
  "geometry": {"coordinates":[-78.607187,42.873831],"type":"Point"}
}