{
  "type": "Feature",
  "properties": {
    "addr:full":"197 Bowery Lbby 1 New York NY 10002",
    "addr:housenumber":"197;1",
    "addr:postcode":"10002",
    "addr:street":"Bowery Lbby",
    "iso:country":"US",
    "sg:address":"197 Bowery Lbby 1",
    "sg:city":"New York",
    "sg:classifiers":[
        {
            "category":"Travel",
            "subcategory":"Hotels & Motels",
            "type":"Entertainment"
        }
    ],
    "sg:phone":"+1 646 602 2060",
    "sg:postcode":"10002",
    "sg:province":"NY",
    "wof:name":"Common Ground Andrews",
    "wof:placetype":"venue"
},
  "geometry": {"coordinates":[-73.993531,40.72088],"type":"Point"}
}