{
  "type": "Feature",
  "properties": {
    "addr:full":"522 Smithtown By-Pass Smithtown NY 11787",
    "addr:housenumber":"522",
    "addr:postcode":"11787",
    "addr:street":"Smithtown By-Pass",
    "iso:country":"US",
    "sg:address":"522 Smithtown By-Pass",
    "sg:city":"Smithtown",
    "sg:classifiers":[
        {
            "category":"Autos & Motor Vehicles",
            "subcategory":"Fuel & Gas Station",
            "type":"Retail Goods"
        },
        {
            "category":"Food & Beverages",
            "subcategory":"Groceries & Convenience Stores",
            "type":"Retail Goods"
        }
    ],
    "sg:postcode":"11787",
    "sg:province":"NY",
    "sg:website":"www.hess.com",
    "wof:name":"Hess Express",
    "wof:placetype":"venue"
},
  "geometry": {"coordinates":[-73.173271,40.845717],"type":"Point"}
}