{
  "type": "Feature",
  "properties": {
    "addr:full":"14945 Northern Blvd Flushing NY 11354",
    "addr:housenumber":"14945",
    "addr:postcode":"11354",
    "addr:street":"Northern Blvd",
    "iso:country":"US",
    "sg:address":"14945 Northern Blvd",
    "sg:city":"Flushing",
    "sg:classifiers":[
        {
            "category":"Health Services",
            "subcategory":"Doctor",
            "type":"Services"
        }
    ],
    "sg:phone":"+1 718 353 8348",
    "sg:postcode":"11354",
    "sg:province":"NY",
    "wof:name":"EMPIRE MEDICAL OF ROCKAWAY BEACH",
    "wof:placetype":"venue"
},
  "geometry": {"coordinates":[-73.81595900000001,40.765489],"type":"Point"}
}