{
  "type": "Feature",
  "properties": {
    "addr:full":"616 Sherman Ave Thornwood NY 10594",
    "addr:housenumber":"616",
    "addr:postcode":"10594",
    "addr:street":"Sherman Ave",
    "iso:country":"US",
    "sg:address":"616 Sherman Ave",
    "sg:city":"Thornwood",
    "sg:classifiers":[
        {
            "category":"Building & Trades",
            "subcategory":"Electrical",
            "type":"Services"
        }
    ],
    "sg:phone":"+1 914 741 0311",
    "sg:postcode":"10594",
    "sg:province":"NY",
    "sg:tags":[
        "electrical",
        "contractor"
    ],
    "wof:name":"Gary A Debiase",
    "wof:placetype":"venue"
},
  "geometry": {"coordinates":[-73.786511,41.114805],"type":"Point"}
}