{
  "type": "Feature",
  "properties": {
    "iso:country":"US",
    "sg:address":"31 Holland Ave",
    "sg:city":"Albany",
    "sg:classifiers":[
        {
            "category":"Restaurant",
            "type":"Food & Drink"
        }
    ],
    "sg:menulink":"http://www.allmenus.com/ny/albany/189054-mcdonalds/menu/",
    "sg:postcode":"12209",
    "sg:province":"NY",
    "sg:tags":[
        "burger",
        "american"
    ],
    "wof:name":"McDonald's",
    "wof:placetype":"venue"
},
  "geometry": {"coordinates":[-73.771918,42.647323],"type":"Point"}
}