{
  "type": "Feature",
  "properties": {
    "addr:full":"1 Heady St Cortlandt Manor NY 10567",
    "addr:housenumber":"1",
    "addr:postcode":"10567",
    "addr:street":"Heady St Cortlandt",
    "iso:country":"US",
    "sg:address":"1 Heady St",
    "sg:city":"Cortlandt Manor",
    "sg:classifiers":[
        {
            "category":"Government",
            "subcategory":"Office",
            "type":"Public Place"
        }
    ],
    "sg:phone":"+1 914 739 4301",
    "sg:postcode":"10567",
    "sg:province":"NY",
    "sg:tags":[
        "village"
    ],
    "wof:name":"Cortlandt Rec Townhall Div",
    "wof:placetype":"venue"
},
  "geometry": {"coordinates":[-73.904939,41.31126],"type":"Point"}
}