{
  "type": "Feature",
  "properties": {
    "addr:full":"2112 Empire Blvd Webster NY 14580",
    "addr:housenumber":"2112",
    "addr:postcode":"14580",
    "addr:street":"Empire Blvd",
    "iso:country":"US",
    "sg:address":"2112 Empire Blvd",
    "sg:city":"Webster",
    "sg:classifiers":[
        {
            "category":"Real Estate",
            "subcategory":"Real Estate Agent",
            "type":"Services"
        }
    ],
    "sg:phone":"+1 585 787 2200",
    "sg:postcode":"14580",
    "sg:province":"NY",
    "wof:name":"Re/Max First",
    "wof:placetype":"venue"
},
  "geometry": {"coordinates":[-77.49946,43.198066],"type":"Point"}
}