{
  "type": "Feature",
  "properties": {
    "addr:full":"3 Sheridan Sq New York NY 10014",
    "addr:housenumber":"3",
    "addr:postcode":"10014",
    "addr:street":"Sheridan Sq",
    "iso:country":"US",
    "sg:address":"3 Sheridan Sq",
    "sg:city":"New York",
    "sg:classifiers":[
        {
            "category":"Parking",
            "type":"Transportation"
        }
    ],
    "sg:phone":"+1 212 242 9791",
    "sg:postcode":"10014",
    "sg:province":"NY",
    "sg:tags":[
        "garage"
    ],
    "wof:name":"Barrow Street Garage",
    "wof:placetype":"venue"
},
  "geometry": {"coordinates":[-74.002572,40.733371],"type":"Point"}
}