{
  "type": "Feature",
  "properties": {
    "iso:country":"US",
    "sg:address":"42 Cain Dr",
    "sg:city":"Plainview",
    "sg:classifiers":[
        {
            "category":"Manufacturing",
            "subcategory":"Tools & Machinery",
            "type":"Manufacturing & Wholesale Goods"
        }
    ],
    "sg:phone":"+1 631 447 0093",
    "sg:postcode":"11803",
    "sg:province":"NY",
    "sg:tags":[
        "equipment",
        "hospital",
        "supply"
    ],
    "wof:name":"Anthony Home Health Inc",
    "wof:placetype":"venue"
},
  "geometry": {"coordinates":[-73.450925,40.785237],"type":"Point"}
}