{
  "type": "Feature",
  "properties": {
    "iso:country":"US",
    "sg:address":"1403 State Hwy 96",
    "sg:city":"Waterloo",
    "sg:classifiers":[
        {
            "category":"Building & Trades",
            "subcategory":"Construction",
            "type":"Services"
        },
        {
            "category":"Utilities",
            "type":"Services"
        }
    ],
    "sg:phone":"+1 315 539 4221",
    "sg:postcode":"13165",
    "sg:province":"NY",
    "sg:tags":[
        "pavement",
        "paving",
        "maintenance",
        "contractor"
    ],
    "wof:name":"Stilwell's Super Sweeper Svc",
    "wof:placetype":"venue"
},
  "geometry": {"coordinates":[-76.871565,42.917179],"type":"Point"}
}