{
  "type": "Feature",
  "properties": {
    "iso:country":"US",
    "sg:address":"32 Alton Ave",
    "sg:city":"Greenlawn",
    "sg:classifiers":[
        {
            "category":"Building & Trades",
            "subcategory":"Construction",
            "type":"Services"
        }
    ],
    "sg:phone":"+1 631 754 2981",
    "sg:postcode":"11740",
    "sg:province":"NY",
    "sg:tags":[
        "contractor"
    ],
    "sg:website":"www.sterlingconstructioninc.com",
    "wof:name":"Sterling Construction Inc",
    "wof:placetype":"venue"
},
  "geometry": {"coordinates":[-73.366185,40.859133],"type":"Point"}
}