{
  "type": "Feature",
  "properties": {
    "addr:full":"2108 US Hwy 9 Round Lake NY 12151",
    "addr:housenumber":"2108",
    "addr:postcode":"12151",
    "addr:street":"Us Hwy 9",
    "iso:country":"US",
    "sg:address":"2108 US Hwy 9",
    "sg:city":"Round Lake",
    "sg:classifiers":[
        {
            "category":"Retail",
            "subcategory":"Animal Services",
            "type":"Services"
        }
    ],
    "sg:phone":"+1 518 899 5098",
    "sg:postcode":"12151",
    "sg:province":"NY",
    "sg:tags":[
        "pet",
        "grooming",
        "washing"
    ],
    "wof:name":"Liberty Canine Care Center",
    "wof:placetype":"venue"
},
  "geometry": {"coordinates":[-73.79233000000001,42.926102],"type":"Point"}
}