{
  "type": "Feature",
  "properties": {
    "iso:country":"US",
    "sg:address":"18 E Utica St",
    "sg:city":"Oswego",
    "sg:classifiers":[
        {
            "category":"Shopping",
            "subcategory":"Used Merchandise",
            "type":"Retail Goods"
        }
    ],
    "sg:phone":"+1 315 342 7552",
    "sg:postcode":"13126",
    "sg:province":"NY",
    "sg:tags":[
        "book",
        "rare",
        "dealer"
    ],
    "wof:name":"Time and Again Books & Tea",
    "wof:placetype":"venue"
},
  "geometry": {"coordinates":[-76.504666,43.453993],"type":"Point"}
}