{
  "type": "Feature",
  "properties": {
    "addr:full":"1635 Ohio Ave Bay Shore NY 11706",
    "addr:housenumber":"1635",
    "addr:postcode":"11706",
    "addr:street":"Ohio Ave",
    "iso:country":"US",
    "sg:address":"1635 Ohio Ave",
    "sg:city":"Bay Shore",
    "sg:classifiers":[
        {
            "category":"Manufacturing",
            "subcategory":"Furniture",
            "type":"Manufacturing & Wholesale Goods"
        }
    ],
    "sg:phone":"+1   ",
    "sg:postcode":"11706",
    "sg:province":"NY",
    "sg:tags":[
        "mfg"
    ],
    "wof:name":"Perez International",
    "wof:placetype":"venue"
},
  "geometry": {"coordinates":[-73.242345,40.7607],"type":"Point"}
}