{
  "type": "Feature",
  "properties": {
    "iso:country":"US",
    "sg:address":"231 Northern Lights Plz",
    "sg:city":"Syracuse",
    "sg:classifiers":[
        {
            "category":"Restaurant",
            "type":"Food & Drink"
        }
    ],
    "sg:phone":"+1 315 455 6477",
    "sg:postcode":"13212",
    "sg:province":"NY",
    "sg:tags":[
        "pizza"
    ],
    "wof:name":"Paladino's Pizza",
    "wof:placetype":"venue"
},
  "geometry": {"coordinates":[-76.143012,43.111606],"type":"Point"}
}