{
  "type": "Feature",
  "properties": {
    "addr:full":"4750 State Hwy 28 Cooperstown NY 13326",
    "addr:housenumber":"4750",
    "addr:postcode":"13326",
    "addr:street":"State Hwy 28",
    "iso:country":"US",
    "sg:address":"4750 State Hwy 28",
    "sg:city":"Cooperstown",
    "sg:classifiers":[
        {
            "category":"Recreation",
            "type":"Entertainment"
        }
    ],
    "sg:phone":"+1 607 547 8273",
    "sg:postcode":"13326",
    "sg:province":"NY",
    "sg:tags":[
        "course",
        "golf"
    ],
    "sg:website":"www.barnyardswing.com",
    "wof:name":"Barnyard Swing LLC",
    "wof:placetype":"venue"
},
  "geometry": {"coordinates":[-74.96442399999999,42.650113],"type":"Point"}
}