{
  "type": "Feature",
  "properties": {
    "iso:country":"US",
    "sg:address":"67 Paumanake Ave",
    "sg:city":"Babylon",
    "sg:classifiers":[
        {
            "category":"Local Transit",
            "type":"Transportation"
        }
    ],
    "sg:phone":"+1 631 422 2736",
    "sg:postcode":"11702",
    "sg:province":"NY",
    "sg:tags":[
        "limousine",
        "driver"
    ],
    "wof:name":"Concord Limousine Service Inc",
    "wof:placetype":"venue"
},
  "geometry": {"coordinates":[-73.318516,40.707288],"type":"Point"}
}