{
  "type": "Feature",
  "properties": {
    "iso:country":"US",
    "sg:address":"315 Bradley Ave",
    "sg:city":"Staten Island",
    "sg:classifiers":[
        {
            "category":"Personal",
            "subcategory":"Beauty Salon",
            "type":"Services"
        }
    ],
    "sg:phone":"+1 718 983 8151",
    "sg:postcode":"10314",
    "sg:province":"NY",
    "sg:tags":[
        "manicuring"
    ],
    "wof:name":"Liu Mei Jin",
    "wof:placetype":"venue"
},
  "geometry": {"coordinates":[-74.13135,40.602774],"type":"Point"}
}