{
  "type": "Feature",
  "properties": {
    "iso:country":"US",
    "sg:address":"1068 Park Ave",
    "sg:city":"Schenectady",
    "sg:classifiers":[
        {
            "category":"Organizations",
            "subcategory":"Religious Organization",
            "type":"Services"
        }
    ],
    "sg:phone":"+1 518 374 4464",
    "sg:postcode":"12308",
    "sg:province":"NY",
    "wof:name":"Union Presbyterian Church",
    "wof:placetype":"venue"
},
  "geometry": {"coordinates":[-73.925135,42.813357],"type":"Point"}
}