{
  "type": "Feature",
  "properties": {
    "iso:country":"US",
    "sg:address":"126 Eaglesfield Way",
    "sg:city":"Fairport",
    "sg:classifiers":[
        {
            "category":"Professional",
            "subcategory":"Advertising",
            "type":"Services"
        }
    ],
    "sg:phone":"+1 585 377 7840",
    "sg:postcode":"14450",
    "sg:province":"NY",
    "sg:tags":[
        "designer",
        "display",
        "producer"
    ],
    "wof:name":"Csd Exhibits/Displays LLC",
    "wof:placetype":"venue"
},
  "geometry": {"coordinates":[-77.450898,43.117715],"type":"Point"}
}