{
  "type": "Feature",
  "properties": {
    "iso:country":"US",
    "sg:address":"628 State Hwy 303",
    "sg:city":"Blauvelt",
    "sg:classifiers":[
        {
            "category":"Wholesale",
            "subcategory":"Durable Goods & Equipment",
            "type":"Manufacturing & Wholesale Goods"
        }
    ],
    "sg:phone":"+1 845 353 2121",
    "sg:postcode":"10913",
    "sg:province":"NY",
    "sg:tags":[
        "importer"
    ],
    "sg:website":"www.norex-enterprises.com",
    "wof:name":"Norex Enterprises Inc",
    "wof:placetype":"venue"
},
  "geometry": {"coordinates":[-73.948729,41.080955],"type":"Point"}
}