{
  "type": "Feature",
  "properties": {
    "addr:full":"1894 Lakeland Ave Ronkonkoma NY 11779",
    "addr:housenumber":"1894",
    "addr:postcode":"11779",
    "addr:street":"Lakeland Ave",
    "iso:country":"US",
    "sg:address":"1894 Lakeland Ave",
    "sg:city":"Ronkonkoma",
    "sg:classifiers":[
        {
            "category":"Home & Garden",
            "subcategory":"Garden Supply",
            "type":"Retail Goods"
        }
    ],
    "sg:phone":"+1 631 580 3140",
    "sg:postcode":"11779",
    "sg:province":"NY",
    "sg:tags":[
        "nursery",
        "gardening"
    ],
    "wof:name":"Bohemia Garden Center",
    "wof:placetype":"venue"
},
  "geometry": {"coordinates":[-73.119698,40.794399],"type":"Point"}
}