{
  "type": "Feature",
  "properties": {
    "iso:country":"US",
    "sg:address":"72 Whittier Dr",
    "sg:city":"Mastic Beach",
    "sg:classifiers":[
        {
            "category":"Building & Trades",
            "subcategory":"Construction",
            "type":"Services"
        }
    ],
    "sg:phone":"+1 631 399 1309",
    "sg:postcode":"11951",
    "sg:province":"NY",
    "sg:tags":[
        "waterproofing",
        "contractor"
    ],
    "wof:name":"G Visintin Waterproofing",
    "wof:placetype":"venue"
},
  "geometry": {"coordinates":[-72.83765200000001,40.766575],"type":"Point"}
}