{
  "type": "Feature",
  "properties": {
    "iso:country":"US",
    "sg:address":"24 Pine St",
    "sg:city":"East Aurora",
    "sg:classifiers":[
        {
            "category":"Personal",
            "type":"Services"
        }
    ],
    "sg:phone":"+1 716 655 1600",
    "sg:postcode":"14052",
    "sg:province":"NY",
    "sg:tags":[
        "therapist",
        "massage"
    ],
    "wof:name":"Borera & Masterson",
    "wof:placetype":"venue"
},
  "geometry": {"coordinates":[-78.607804,42.769197],"type":"Point"}
}