{
  "type": "Feature",
  "properties": {
    "addr:full":"1181 Webster Ave Bronx NY 10456",
    "addr:housenumber":"1181",
    "addr:postcode":"10456",
    "addr:street":"Webster Ave",
    "iso:country":"US",
    "sg:address":"1181 Webster Ave",
    "sg:city":"Bronx",
    "sg:classifiers":[
        {
            "category":"Shopping",
            "subcategory":"Discount & Variety Stores",
            "type":"Retail Goods"
        }
    ],
    "sg:phone":"+1 718 588 1661",
    "sg:postcode":"10456",
    "sg:province":"NY",
    "wof:name":"99 Cents Utica Inc",
    "wof:placetype":"venue"
},
  "geometry": {"coordinates":[-73.910003,40.831575],"type":"Point"}
}