{
  "type": "Feature",
  "properties": {
    "iso:country":"US",
    "sg:address":"175 Main St",
    "sg:city":"White Plains",
    "sg:classifiers":[
        {
            "category":"Health Services",
            "subcategory":"Clinic",
            "type":"Services"
        }
    ],
    "sg:phone":"+1 914 949 1300",
    "sg:postcode":"10601",
    "sg:province":"NY",
    "sg:tags":[
        "home",
        "care"
    ],
    "wof:name":"A & A Staffing Tmpry Personnel",
    "wof:placetype":"venue"
},
  "geometry": {"coordinates":[-73.76811499999999,41.032356],"type":"Point"}
}