{
  "type": "Feature",
  "properties": {
    "iso:country":"US",
    "sg:address":"100 W Maple Ave",
    "sg:city":"Monsey",
    "sg:classifiers":[
        {
            "category":"Organizations",
            "subcategory":"Religious Organization",
            "type":"Services"
        }
    ],
    "sg:phone":"+1 845 352 2501",
    "sg:postcode":"10952",
    "sg:province":"NY",
    "sg:tags":[
        "clergy"
    ],
    "wof:name":"Morton Minchenberg",
    "wof:placetype":"venue"
},
  "geometry": {"coordinates":[-74.077147,41.123086],"type":"Point"}
}