{
  "type": "Feature",
  "properties": {
    "addr:full":"39 W 34th St Manhattan NY 10001",
    "addr:housenumber":"39",
    "addr:postcode":"10001",
    "addr:street":"W 34Th St",
    "iso:country":"US",
    "sg:address":"39 W 34th St",
    "sg:city":"Manhattan",
    "sg:classifiers":[
        {
            "category":"Travel",
            "subcategory":"Travel Agent",
            "type":"Entertainment"
        },
        {
            "category":"Local Transit",
            "type":"Transportation"
        }
    ],
    "sg:phone":"+1 703 799 5170",
    "sg:postcode":"10001",
    "sg:province":"NY",
    "sg:tags":[
        "public"
    ],
    "sg:website":"www.sprinterbus.net",
    "wof:name":"Sprinter Bus",
    "wof:placetype":"venue"
},
  "geometry": {"coordinates":[-73.98690499999999,40.749445],"type":"Point"}
}