{
  "type": "Feature",
  "properties": {
    "iso:country":"US",
    "sg:address":"147 Racquette River Dr",
    "sg:city":"Tupper Lake",
    "sg:classifiers":[
        {
            "category":"Home & Garden",
            "subcategory":"Building Materials",
            "type":"Retail Goods"
        }
    ],
    "sg:phone":"+1 518 359 9331",
    "sg:postcode":"12986",
    "sg:province":"NY",
    "sg:tags":[
        "glass",
        "leaded"
    ],
    "wof:name":"Adirondack Glassmith",
    "wof:placetype":"venue"
},
  "geometry": {"coordinates":[-74.469926,44.204972],"type":"Point"}
}