{
  "type": "Feature",
  "properties": {
    "addr:full":"1450 Old Country Rd Riverhead NY 11901",
    "addr:housenumber":"1450",
    "addr:postcode":"11901",
    "addr:street":"Old Country Rd",
    "iso:country":"US",
    "sg:address":"1450 Old Country Rd",
    "sg:city":"Riverhead",
    "sg:classifiers":[
        {
            "category":"Food & Beverages",
            "subcategory":"Bakery",
            "type":"Retail Goods"
        }
    ],
    "sg:phone":"+1 631 208 0423",
    "sg:postcode":"11901",
    "sg:province":"NY",
    "sg:tags":[
        "doughnut"
    ],
    "sg:website":"www.krispykreme.com",
    "wof:name":"Krispy Kreme Doughnuts",
    "wof:placetype":"venue"
},
  "geometry": {"coordinates":[-72.683836,40.928796],"type":"Point"}
}