{
  "type": "Feature",
  "properties": {
    "addr:full":"1357 Teller Ave Bronx NY 10456",
    "addr:housenumber":"1357",
    "addr:postcode":"10456",
    "addr:street":"Teller Ave",
    "iso:country":"US",
    "sg:address":"1357 Teller Ave",
    "sg:city":"Bronx",
    "sg:classifiers":[
        {
            "category":"Banks & Credit Unions",
            "subcategory":"Bank",
            "type":"Services"
        }
    ],
    "sg:phone":"+1 718 588 4797",
    "sg:postcode":"10456",
    "sg:province":"NY",
    "sg:tags":[
        "loan",
        "real estate"
    ],
    "wof:name":"Future Funding & Construction",
    "wof:placetype":"venue"
},
  "geometry": {"coordinates":[-73.909826,40.835535],"type":"Point"}
}