{
  "type": "Feature",
  "properties": {
    "addr:full":"6175 Wagner Rd Springville NY 14141",
    "addr:housenumber":"6175",
    "addr:postcode":"14141",
    "addr:street":"Wagner Rd",
    "iso:country":"US",
    "sg:address":"6175 Wagner Rd",
    "sg:city":"Springville",
    "sg:classifiers":[
        {
            "category":"Farming",
            "subcategory":"Nursery",
            "type":"Manufacturing & Wholesale Goods"
        }
    ],
    "sg:phone":"+1 716 941 3122",
    "sg:postcode":"14141",
    "sg:province":"NY",
    "sg:tags":[
        "ornamental",
        "greenhouse"
    ],
    "wof:name":"Windy Acres Greenhouse & Nurse",
    "wof:placetype":"venue"
},
  "geometry": {"coordinates":[-78.75912099999999,42.586517],"type":"Point"}
}