{
  "type": "Feature",
  "properties": {
    "addr:full":"427 W 126th St New York NY 10027",
    "addr:housenumber":"427",
    "addr:postcode":"10027",
    "addr:street":"W 126Th St",
    "iso:country":"US",
    "sg:address":"427 W 126th St",
    "sg:city":"New York",
    "sg:classifiers":[
        {
            "category":"Retail",
            "subcategory":"Auto Repair",
            "type":"Services"
        }
    ],
    "sg:phone":"+1 212 222 8068",
    "sg:postcode":"10027",
    "sg:province":"NY",
    "sg:tags":[
        "repairing",
        "automobile"
    ],
    "wof:name":"Friendly's Auto Body Shop",
    "wof:placetype":"venue"
},
  "geometry": {"coordinates":[-73.954626,40.812824],"type":"Point"}
}