{
  "type": "Feature",
  "properties": {
    "addr:full":"130 Montauk Hwy Unit F East Moriches NY 11940",
    "addr:housenumber":"130",
    "addr:postcode":"11940",
    "addr:street":"Montauk Hwy Unit F East Moriches",
    "iso:country":"US",
    "sg:address":"130 Montauk Hwy Unit F",
    "sg:city":"East Moriches",
    "sg:classifiers":[
        {
            "category":"Health Services",
            "subcategory":"Chiropractor",
            "type":"Services"
        }
    ],
    "sg:phone":"+1 631 874 2797",
    "sg:postcode":"11940",
    "sg:province":"NY",
    "sg:website":"www.touchoflife.com",
    "wof:name":"Touch of Life Chiropractic East",
    "wof:placetype":"venue"
},
  "geometry": {"coordinates":[-72.750702,40.820599],"type":"Point"}
}