{
  "type": "Feature",
  "properties": {
    "addr:full":"29 N Franklin St Watkins Glen NY 14891",
    "addr:housenumber":"29",
    "addr:postcode":"14891",
    "addr:street":"N Franklin St",
    "iso:country":"US",
    "sg:address":"29 N Franklin St",
    "sg:city":"Watkins Glen",
    "sg:classifiers":[
        {
            "category":"Food & Beverages",
            "subcategory":"Liquor & Beverages",
            "type":"Retail Goods"
        }
    ],
    "sg:phone":"+1 607 535 2944",
    "sg:postcode":"14891",
    "sg:province":"NY",
    "sg:tags":[
        "wine"
    ],
    "sg:website":"www.newyorkstatewine.com",
    "wof:name":"NEWYORKSTATEWINE.COM",
    "wof:placetype":"venue"
},
  "geometry": {"coordinates":[-76.874825,42.38294],"type":"Point"}
}