{
  "type": "Feature",
  "properties": {
    "addr:full":"2717 State Hwy 51 Ilion NY 13357",
    "addr:housenumber":"2717",
    "addr:postcode":"13357",
    "addr:street":"State Hwy 51",
    "iso:country":"US",
    "sg:address":"2717 State Hwy 51",
    "sg:city":"Ilion",
    "sg:classifiers":[
        {
            "category":"Retail",
            "subcategory":"Veterinary Services",
            "type":"Services"
        }
    ],
    "sg:phone":"+1 315 894 9923",
    "sg:postcode":"13357",
    "sg:province":"NY",
    "sg:tags":[
        "veterinarian"
    ],
    "wof:name":"German Fltts Vtrinarian Clinic",
    "wof:placetype":"venue"
},
  "geometry": {"coordinates":[-75.04924699999999,42.999123],"type":"Point"}
}