{
  "type": "Feature",
  "properties": {
    "addr:full":"138 Frog Hollow Rd Poughquag NY 12570",
    "addr:housenumber":"138",
    "addr:postcode":"12570",
    "addr:street":"Frog Hollow Rd",
    "iso:country":"US",
    "sg:address":"138 Frog Hollow Rd",
    "sg:city":"Poughquag",
    "sg:classifiers":[
        {
            "category":"Organizations",
            "subcategory":"Membership Organization",
            "type":"Services"
        }
    ],
    "sg:phone":"+1 914 682 2224",
    "sg:postcode":"12570",
    "sg:province":"NY",
    "sg:tags":[
        "society",
        "humane"
    ],
    "wof:name":"Critter Control",
    "wof:placetype":"venue"
},
  "geometry": {"coordinates":[-73.700287,41.590627],"type":"Point"}
}