{
  "type": "Feature",
  "properties": {
    "addr:full":"213 Westchester Ave Port Chester NY 10573",
    "addr:housenumber":"213",
    "addr:postcode":"10573",
    "addr:street":"Westchester Ave",
    "iso:country":"US",
    "sg:address":"213 Westchester Ave",
    "sg:city":"Port Chester",
    "sg:classifiers":[
        {
            "category":"Restaurant",
            "type":"Food & Drink"
        }
    ],
    "sg:menulink":"http://www.allmenus.com/ny/rye/146632-panda-chinese-restaurant/menu/",
    "sg:phone":"+1 914 937 3979",
    "sg:postcode":"10573",
    "sg:province":"NY",
    "sg:tags":[
        "asian",
        "chinese"
    ],
    "wof:name":"Panda Chinese Restaurant",
    "wof:placetype":"venue"
},
  "geometry": {"coordinates":[-73.66677799999999,41.002286],"type":"Point"}
}