{
  "type": "Feature",
  "properties": {
    "iso:country":"US",
    "sg:address":"287 E Houston St",
    "sg:city":"New York",
    "sg:classifiers":[
        {
            "category":"Banks & Credit Unions",
            "subcategory":"Bank",
            "type":"Services"
        }
    ],
    "sg:phone":"+1 212 475 1103",
    "sg:postcode":"10002",
    "sg:province":"NY",
    "sg:tags":[
        "loan",
        "broker"
    ],
    "wof:name":"H & B Insurance",
    "wof:placetype":"venue"
},
  "geometry": {"coordinates":[-73.98424,40.721557],"type":"Point"}
}