{
  "type": "Feature",
  "properties": {
    "iso:country":"US",
    "sg:address":"133 Wall St",
    "sg:city":"Kingston",
    "sg:classifiers":[
        {
            "category":"Building & Trades",
            "subcategory":"Landscaping Services",
            "type":"Services"
        }
    ],
    "sg:phone":"+1 845 338 3399",
    "sg:postcode":"12401",
    "sg:province":"NY",
    "sg:tags":[
        "lawn",
        "landscape"
    ],
    "sg:website":"http://www.auroralandscapedesign.com",
    "wof:name":"Aurora Landscape Design & Cons",
    "wof:placetype":"venue"
},
  "geometry": {"coordinates":[-74.01621799999999,41.928158],"type":"Point"}
}