{
  "type": "Feature",
  "properties": {
    "addr:full":"315 State Hwy 211 Middletown NY 10940",
    "addr:housenumber":"315",
    "addr:postcode":"10940",
    "addr:street":"State Hwy 211",
    "iso:country":"US",
    "sg:address":"315 State Hwy 211",
    "sg:city":"Middletown",
    "sg:classifiers":[
        {
            "category":"Shopping",
            "subcategory":"Discount & Variety Stores",
            "type":"Retail Goods"
        }
    ],
    "sg:phone":"+1   ",
    "sg:postcode":"10940",
    "sg:province":"NY",
    "sg:tags":[
        "merchandise",
        "general"
    ],
    "wof:name":"St Robo Inc",
    "wof:placetype":"venue"
},
  "geometry": {"coordinates":[-74.44102599999999,41.459724],"type":"Point"}
}