{
  "type": "Feature",
  "properties": {
    "iso:country":"US",
    "sg:address":"1 Center Ter",
    "sg:city":"New Hartford",
    "sg:classifiers":[
        {
            "category":"Shopping",
            "subcategory":"Shoes",
            "type":"Retail Goods"
        }
    ],
    "sg:phone":"+1 315 724 2332",
    "sg:postcode":"13413",
    "sg:province":"NY",
    "wof:name":"Shoe Depot",
    "wof:placetype":"venue"
},
  "geometry": {"coordinates":[-75.286683,43.059566],"type":"Point"}
}