{
  "type": "Feature",
  "properties": {
    "iso:country":"US",
    "sg:address":"82 N Village Ave",
    "sg:city":"Rockville Centre",
    "sg:classifiers":[
        {
            "category":"Personal",
            "subcategory":"Nail Salon",
            "type":"Services"
        }
    ],
    "sg:phone":"+1 516 255 9123",
    "sg:postcode":"11570",
    "sg:province":"NY",
    "wof:name":"Cici Nail & Skin Care Corp",
    "wof:placetype":"venue"
},
  "geometry": {"coordinates":[-73.648158,40.6593],"type":"Point"}
}