{
  "type": "Feature",
  "properties": {
    "addr:full":"31 W 8 St New York NY 10011",
    "addr:housenumber":"31;8",
    "addr:postcode":"10011",
    "addr:street":"W",
    "iso:country":"US",
    "sg:address":"31 W 8 St",
    "sg:city":"New York",
    "sg:classifiers":[
        {
            "category":"Professional",
            "type":"Services"
        }
    ],
    "sg:phone":"+1 212 460 5000",
    "sg:postcode":"10011",
    "sg:province":"NY",
    "sg:tags":[
        "establishment"
    ],
    "wof:name":"Klein Group LLC",
    "wof:placetype":"venue"
},
  "geometry": {"coordinates":[-73.996971,40.732465],"type":"Point"}
}