{
  "type": "Feature",
  "properties": {
    "iso:country":"US",
    "sg:address":"14 Rolling Way",
    "sg:city":"New Rochelle",
    "sg:classifiers":[
        {
            "category":"Personal",
            "type":"Services"
        }
    ],
    "sg:phone":"+1 914 633 7654",
    "sg:postcode":"10804",
    "sg:province":"NY",
    "sg:tags":[
        "control",
        "weight"
    ],
    "wof:name":"Westchester Center",
    "wof:placetype":"venue"
},
  "geometry": {"coordinates":[-73.785492,40.956312],"type":"Point"}
}