{
  "type": "Feature",
  "properties": {
    "iso:country":"US",
    "sg:address":"Greene Medical Arts",
    "sg:city":"Catskill",
    "sg:classifiers":[
        {
            "category":"Health Services",
            "subcategory":"Doctor",
            "type":"Services"
        }
    ],
    "sg:phone":"+1 518 943 1442",
    "sg:postcode":"12414",
    "sg:province":"NY",
    "sg:tags":[
        "medicine",
        "practice",
        "internal",
        "family"
    ],
    "wof:name":"Mustapha Rahma MD",
    "wof:placetype":"venue"
},
  "geometry": {"coordinates":[-73.883904,42.2243],"type":"Point"}
}