{
  "type": "Feature",
  "properties": {
    "iso:country":"US",
    "sg:address":"225 Liberty St",
    "sg:city":"New York",
    "sg:classifiers":[
        {
            "category":"Shopping",
            "subcategory":"Hobbies, Toys, & Games",
            "type":"Retail Goods"
        }
    ],
    "sg:phone":"+1 212 786 3011",
    "sg:postcode":"10281",
    "sg:province":"NY",
    "sg:tags":[
        "toy",
        "store"
    ],
    "sg:website":"www.boomerangtoys.com",
    "wof:name":"Boomerang Toys",
    "wof:placetype":"venue"
},
  "geometry": {"coordinates":[-74.483431,40.711333],"type":"Point"}
}