{
  "type": "Feature",
  "properties": {
    "iso:country":"US",
    "sg:address":"3816 Dyre Ave",
    "sg:city":"Bronx",
    "sg:classifiers":[
        {
            "category":"Restaurant",
            "type":"Food & Drink"
        }
    ],
    "sg:phone":"+1 718 515 6411",
    "sg:postcode":"10466",
    "sg:province":"NY",
    "wof:name":"Kennedy Fried Chicken",
    "wof:placetype":"venue"
},
  "geometry": {"coordinates":[-73.831221,40.888967],"type":"Point"}
}