{
  "type": "Feature",
  "properties": {
    "addr:full":"88 Cherrywood Dr Buffalo NY 14221",
    "addr:housenumber":"88",
    "addr:postcode":"14221",
    "addr:street":"Cherrywood Dr",
    "iso:country":"US",
    "sg:address":"88 Cherrywood Dr",
    "sg:city":"Buffalo",
    "sg:classifiers":[
        {
            "category":"Real Estate",
            "subcategory":"Developer",
            "type":"Services"
        }
    ],
    "sg:phone":"+1 716 688 8257",
    "sg:postcode":"14221",
    "sg:province":"NY",
    "sg:tags":[
        "cemetery"
    ],
    "wof:name":"Skinnersville Cemetery As",
    "wof:placetype":"venue"
},
  "geometry": {"coordinates":[-78.748098,43.006104],"type":"Point"}
}