{
  "type": "Feature",
  "properties": {
    "iso:country":"US",
    "sg:address":"39 W Main St",
    "sg:city":"Avon",
    "sg:classifiers":[
        {
            "category":"Health Services",
            "subcategory":"Doctor",
            "type":"Services"
        }
    ],
    "sg:phone":"+1 585 226 2120",
    "sg:postcode":"14414",
    "sg:province":"NY",
    "wof:name":"Avon Family Dentistry",
    "wof:placetype":"venue"
},
  "geometry": {"coordinates":[-77.74745799999999,42.912827],"type":"Point"}
}