{
  "type": "Feature",
  "properties": {
    "addr:full":"183 Blackberry Rd Liverpool NY 13090",
    "addr:housenumber":"183",
    "addr:postcode":"13090",
    "addr:street":"Blackberry Rd",
    "iso:country":"US",
    "sg:address":"183 Blackberry Rd",
    "sg:city":"Liverpool",
    "sg:classifiers":[
        {
            "category":"Insurance",
            "subcategory":"Hazard Insurance",
            "type":"Services"
        }
    ],
    "sg:phone":"+1 315 622 3035",
    "sg:postcode":"13090",
    "sg:province":"NY",
    "wof:name":"Kraft & Scaravillo",
    "wof:placetype":"venue"
},
  "geometry": {"coordinates":[-76.225838,43.14053],"type":"Point"}
}