{
  "type": "Feature",
  "properties": {
    "addr:full":"814 Union St Brooklyn NY 11215",
    "addr:housenumber":"814",
    "addr:postcode":"11215",
    "addr:street":"Union St",
    "iso:country":"US",
    "sg:address":"814 Union St",
    "sg:city":"Brooklyn",
    "sg:classifiers":[
        {
            "category":"Food & Beverages",
            "subcategory":"Specialty",
            "type":"Retail Goods"
        }
    ],
    "sg:phone":"+1 718 230 3180",
    "sg:postcode":"11215",
    "sg:province":"NY",
    "wof:name":"Blue Apron Foods",
    "wof:placetype":"venue"
},
  "geometry": {"coordinates":[-73.975331,40.674412],"type":"Point"}
}