{
  "type": "Feature",
  "properties": {
    "iso:country":"US",
    "sg:address":"1584 Richmond Road",
    "sg:city":"Staten Island",
    "sg:classifiers":[
        {
            "category":"Autos & Motor Vehicles",
            "subcategory":"Auto Supplies",
            "type":"Retail Goods"
        },
        {
            "category":"Retail",
            "subcategory":"Auto Repair",
            "type":"Services"
        }
    ],
    "sg:phone":"+1 718 351 2600",
    "sg:postcode":"10304",
    "sg:province":"NY",
    "sg:tags":[
        "tire"
    ],
    "sg:website":"bfgoodrichtires.com",
    "wof:name":"Charley's Tire Warehouse",
    "wof:placetype":"venue"
},
  "geometry": {"coordinates":[-74.10108099999999,40.591321],"type":"Point"}
}