{
  "type": "Feature",
  "properties": {
    "addr:full":"44 E 67 St New York NY 10065",
    "addr:housenumber":"44;67",
    "addr:postcode":"10065",
    "addr:street":"E;St",
    "iso:country":"US",
    "sg:address":"44 E 67 St",
    "sg:city":"New York",
    "sg:classifiers":[
        {
            "category":"Health Services",
            "subcategory":"Doctor",
            "type":"Services"
        }
    ],
    "sg:phone":"+1 212 744 4668",
    "sg:postcode":"10065",
    "sg:province":"NY",
    "sg:tags":[
        "physician",
        "surgeon"
    ],
    "wof:name":"Gary S Hitzig MD",
    "wof:placetype":"venue"
},
  "geometry": {"coordinates":[-73.966437,40.767991],"type":"Point"}
}