{
  "type": "Feature",
  "properties": {
    "addr:full":"260 W Main St Bay Shore NY 11706",
    "addr:housenumber":"260",
    "addr:postcode":"11706",
    "addr:street":"W Main St",
    "iso:country":"US",
    "sg:address":"260 W Main St",
    "sg:city":"Bay Shore",
    "sg:classifiers":[
        {
            "category":"Health Services",
            "subcategory":"Clinic",
            "type":"Services"
        }
    ],
    "sg:phone":"+1 631 969 9792",
    "sg:postcode":"11706",
    "sg:province":"NY",
    "sg:tags":[
        "counseling",
        "mental"
    ],
    "wof:name":"Alexander Gregory Psychlgst",
    "wof:placetype":"venue"
},
  "geometry": {"coordinates":[-73.2565,40.716],"type":"Point"}
}