{
  "type": "Feature",
  "properties": {
    "addr:full":"724 New York Ave Huntington NY 11743",
    "addr:housenumber":"724",
    "addr:postcode":"11743",
    "addr:street":"New York Ave",
    "iso:country":"US",
    "sg:address":"724 New York Ave",
    "sg:city":"Huntington",
    "sg:classifiers":[
        {
            "category":"Manufacturing",
            "subcategory":"Building Materials",
            "type":"Manufacturing & Wholesale Goods"
        },
        {
            "category":"Home & Garden",
            "subcategory":"Home Furnishings",
            "type":"Retail Goods"
        }
    ],
    "sg:phone":"+1 631 427 4281",
    "sg:postcode":"11743",
    "sg:province":"NY",
    "sg:tags":[
        "woodworking",
        "fireplace"
    ],
    "wof:name":"Di Salvo Woodworking Inc",
    "wof:placetype":"venue"
},
  "geometry": {"coordinates":[-73.41977300000001,40.860049],"type":"Point"}
}