{
  "type": "Feature",
  "properties": {
    "addr:full":"1710 Veterans Memorial Hwy Islandia NY 11749",
    "addr:housenumber":"1710",
    "addr:postcode":"11749",
    "addr:street":"Veterans Memorial Hwy Islandia",
    "iso:country":"US",
    "sg:address":"1710 Veterans Memorial Hwy",
    "sg:city":"Islandia",
    "sg:classifiers":[
        {
            "category":"Utilities",
            "subcategory":"Mobile Phone",
            "type":"Services"
        }
    ],
    "sg:phone":"+1 631 348 3744",
    "sg:postcode":"11749",
    "sg:province":"NY",
    "sg:tags":[
        "telephone",
        "cellular"
    ],
    "wof:name":"Cingular Wireless",
    "wof:placetype":"venue"
},
  "geometry": {"coordinates":[-73.18431200000001,40.80808],"type":"Point"}
}