{
  "type": "Feature",
  "properties": {
    "iso:country":"US",
    "sg:address":"1350 Sunrise Hwy",
    "sg:city":"Bay Shore",
    "sg:classifiers":[
        {
            "category":"Autos & Motor Vehicles",
            "subcategory":"Automobile Sales",
            "type":"Retail Goods"
        }
    ],
    "sg:phone":"+1   ",
    "sg:postcode":"11706",
    "sg:province":"NY",
    "sg:tags":[
        "used"
    ],
    "wof:name":"Kay Chrys Plymouth Auto Sales",
    "wof:placetype":"venue"
},
  "geometry": {"coordinates":[-73.26237399999999,40.732613],"type":"Point"}
}