{
  "type": "Feature",
  "properties": {
    "addr:full":"2700 W Henrietta Rd Rochester NY 14623",
    "addr:housenumber":"2700",
    "addr:postcode":"14623",
    "addr:street":"W Henrietta Rd",
    "iso:country":"US",
    "sg:address":"2700 W Henrietta Rd",
    "sg:city":"Rochester",
    "sg:classifiers":[
        {
            "category":"Restaurant",
            "type":"Food & Drink"
        }
    ],
    "sg:menulink":"http://www.allmenus.com/ny/brighton/3835-michelinas/menu/",
    "sg:phone":"+1 585 424 3040",
    "sg:postcode":"14623",
    "sg:province":"NY",
    "sg:tags":[
        "italian"
    ],
    "wof:name":"Michelinas",
    "wof:placetype":"venue"
},
  "geometry": {"coordinates":[-77.630042,43.097865],"type":"Point"}
}