{
  "type": "Feature",
  "properties": {
    "addr:full":"2155 Paulding Ave Apt 3D Bronx NY 10462",
    "addr:housenumber":"2155",
    "addr:postcode":"10462",
    "addr:street":"Paulding Ave Apt 3D",
    "iso:country":"US",
    "sg:address":"2155 Paulding Ave Apt 3D",
    "sg:city":"Bronx",
    "sg:classifiers":[
        {
            "category":"Health Services",
            "subcategory":"Clinic",
            "type":"Services"
        }
    ],
    "sg:phone":"+1 718 892 1339",
    "sg:postcode":"10462",
    "sg:province":"NY",
    "sg:tags":[
        "medical"
    ],
    "wof:name":"Elgindy Hamdy",
    "wof:placetype":"venue"
},
  "geometry": {"coordinates":[-73.860277,40.855061],"type":"Point"}
}