{
  "type": "Feature",
  "properties": {
    "addr:full":"2500 Nostrand Avenue Brooklyn NY 11210",
    "addr:housenumber":"2500",
    "addr:postcode":"11210",
    "addr:street":"Nostrand Avenue",
    "iso:country":"US",
    "sg:address":"2500 Nostrand Avenue",
    "sg:city":"Brooklyn",
    "sg:classifiers":[
        {
            "category":"Education",
            "subcategory":"School",
            "type":"Public Place"
        }
    ],
    "sg:phone":"+1 718 253 3700",
    "sg:postcode":"11210",
    "sg:province":"NY",
    "sg:tags":[
        "high",
        "middle",
        "elementary"
    ],
    "wof:name":"N Y City of",
    "wof:placetype":"venue"
},
  "geometry": {"coordinates":[-73.946184,40.622304],"type":"Point"}
}