{
  "type": "Feature",
  "properties": {
    "addr:full":"619 New Loudon Rd Latham NY 12110",
    "addr:housenumber":"619",
    "addr:postcode":"12110",
    "addr:street":"New Loudon Rd",
    "iso:country":"US",
    "sg:address":"619 New Loudon Rd",
    "sg:city":"Latham",
    "sg:classifiers":[
        {
            "category":"Insurance",
            "subcategory":"Hazard Insurance",
            "type":"Services"
        },
        {
            "category":"Insurance",
            "subcategory":"Insurance Agent",
            "type":"Services"
        },
        {
            "category":"Insurance",
            "subcategory":"Life Insurance",
            "type":"Services"
        }
    ],
    "sg:phone":"+1 518 213 9408",
    "sg:postcode":"12110",
    "sg:province":"NY",
    "sg:tags":[
        "auto",
        "property",
        "casualty"
    ],
    "sg:website":"http://statefarm.mqgroup.com/url.asp?usr=521715",
    "wof:name":"Fazzone, Maryann - State Farm Insurance Agent",
    "wof:placetype":"venue"
},
  "geometry": {"coordinates":[-73.76141,42.730493],"type":"Point"}
}