{
  "type": "Feature",
  "properties": {
    "addr:full":"5718 Woodside Avenue Woodside NY 11377",
    "addr:housenumber":"5718",
    "addr:postcode":"11377",
    "addr:street":"Woodside Avenue",
    "iso:country":"US",
    "sg:address":"5718 Woodside Avenue",
    "sg:city":"Woodside",
    "sg:classifiers":[
        {
            "category":"Health Services",
            "subcategory":"Doctor",
            "type":"Services"
        }
    ],
    "sg:phone":"+1 718 205 0030",
    "sg:postcode":"11377",
    "sg:province":"NY",
    "wof:name":"Agustin Erie T Mdpc",
    "wof:placetype":"venue"
},
  "geometry": {"coordinates":[-73.907117,40.745828],"type":"Point"}
}