{
  "type": "Feature",
  "properties": {
    "iso:country":"US",
    "sg:address":"75 S Broadway",
    "sg:city":"White Plains",
    "sg:classifiers":[
        {
            "category":"Professional",
            "subcategory":"Lawyer & Legal Services",
            "type":"Services"
        }
    ],
    "sg:phone":"+1 914 304 4078",
    "sg:postcode":"10601",
    "sg:province":"NY",
    "sg:tags":[
        "attorney"
    ],
    "wof:name":"Susan B Henner",
    "wof:placetype":"venue"
},
  "geometry": {"coordinates":[-73.762432,41.029562],"type":"Point"}
}