{
  "type": "Feature",
  "properties": {
    "iso:country":"US",
    "sg:address":"719 2nd Ave",
    "sg:city":"Troy",
    "sg:classifiers":[
        {
            "category":"Restaurant",
            "type":"Food & Drink"
        }
    ],
    "sg:phone":"+1 518 237 6666",
    "sg:postcode":"12182",
    "sg:province":"NY",
    "wof:name":"Moon's",
    "wof:placetype":"venue"
},
  "geometry": {"coordinates":[-73.67473,42.779766],"type":"Point"}
}