{
  "type": "Feature",
  "properties": {
    "addr:full":"7 Van Auker St Rochester NY 14608",
    "addr:housenumber":"7",
    "addr:postcode":"14608",
    "addr:street":"Van Auker St",
    "iso:country":"US",
    "sg:address":"7 Van Auker St",
    "sg:city":"Rochester",
    "sg:classifiers":[
        {
            "category":"Real Estate",
            "subcategory":"Real Estate Operator",
            "type":"Services"
        }
    ],
    "sg:phone":"+1 585 235 6330",
    "sg:postcode":"14608",
    "sg:province":"NY",
    "sg:tags":[
        "apartment"
    ],
    "wof:name":"Park Titus Apartments",
    "wof:placetype":"venue"
},
  "geometry": {"coordinates":[-77.62200799999999,43.152452],"type":"Point"}
}