{
  "type": "Feature",
  "properties": {
    "addr:full":"132 Havemeyer St Brooklyn NY 11211",
    "addr:housenumber":"132",
    "addr:postcode":"11211",
    "addr:street":"Havemeyer St",
    "iso:country":"US",
    "sg:address":"132 Havemeyer St",
    "sg:city":"Brooklyn",
    "sg:classifiers":[
        {
            "category":"Food & Beverages",
            "subcategory":"Meat & Fish",
            "type":"Retail Goods"
        }
    ],
    "sg:phone":"+1 718 384 3966",
    "sg:postcode":"11211",
    "sg:province":"NY",
    "wof:name":"David Yolinsky",
    "wof:placetype":"venue"
},
  "geometry": {"coordinates":[-73.95753499999999,40.711608],"type":"Point"}
}