{
  "type": "Feature",
  "properties": {
    "iso:country":"US",
    "sg:address":"4714 48th Avenue",
    "sg:city":"Flushing",
    "sg:classifiers":[
        {
            "category":"Health Services",
            "subcategory":"Doctor",
            "type":"Services"
        }
    ],
    "sg:phone":"+1 718 786 9595",
    "sg:postcode":"11377",
    "sg:province":"NY",
    "wof:name":"47 Street Medical Ofcs",
    "wof:placetype":"venue"
},
  "geometry": {"coordinates":[-73.918246,40.739056],"type":"Point"}
}