{
  "type": "Feature",
  "properties": {
    "iso:country":"US",
    "sg:address":"3243 Sheridan Dr",
    "sg:city":"Buffalo",
    "sg:classifiers":[
        {
            "category":"Home & Garden",
            "subcategory":"Building Materials",
            "type":"Retail Goods"
        },
        {
            "category":"Building & Trades",
            "subcategory":"Construction",
            "type":"Services"
        }
    ],
    "sg:phone":"+1 716 833 7972",
    "sg:postcode":"14150",
    "sg:province":"NY",
    "sg:tags":[
        "plate",
        "window",
        "glass",
        "contractor"
    ],
    "wof:name":"Fast Auto Glass",
    "wof:placetype":"venue"
},
  "geometry": {"coordinates":[-78.812746,42.980128],"type":"Point"}
}