{
  "type": "Feature",
  "properties": {
    "addr:full":"695 Dutchess Tpke Poughkeepsie NY 12603",
    "addr:housenumber":"695",
    "addr:postcode":"12603",
    "addr:street":"Dutchess Tpke",
    "iso:country":"US",
    "sg:address":"695 Dutchess Tpke",
    "sg:city":"Poughkeepsie",
    "sg:classifiers":[
        {
            "category":"Health Services",
            "subcategory":"Clinic",
            "type":"Services"
        }
    ],
    "sg:phone":"+1 845 452 9926",
    "sg:postcode":"12603",
    "sg:province":"NY",
    "sg:tags":[
        "information",
        "examination",
        "insurance",
        "physical"
    ],
    "wof:name":"Portamedic 415",
    "wof:placetype":"venue"
},
  "geometry": {"coordinates":[-73.842167,41.72584],"type":"Point"}
}