{
  "type": "Feature",
  "properties": {
    "iso:country":"US",
    "sg:address":"264 Hampton Rd",
    "sg:city":"Southampton",
    "sg:classifiers":[
        {
            "category":"Restaurant",
            "type":"Food & Drink"
        }
    ],
    "sg:phone":"+1 631 283 0929",
    "sg:postcode":"11968",
    "sg:province":"NY",
    "sg:tags":[
        "delicatessen"
    ],
    "wof:name":"Ted's East End Market Inc",
    "wof:placetype":"venue"
},
  "geometry": {"coordinates":[-72.38233700000001,40.890187],"type":"Point"}
}