{
  "type": "Feature",
  "properties": {
    "addr:full":"610 Hamilton St Ogdensburg NY 13669",
    "addr:housenumber":"610",
    "addr:postcode":"13669",
    "addr:street":"Hamilton St",
    "iso:country":"US",
    "sg:address":"610 Hamilton St",
    "sg:city":"Ogdensburg",
    "sg:classifiers":[
        {
            "category":"Wholesale",
            "subcategory":"Electrical",
            "type":"Manufacturing & Wholesale Goods"
        }
    ],
    "sg:phone":"+1 315 322 5800",
    "sg:postcode":"13669",
    "sg:province":"NY",
    "sg:tags":[
        "alarm",
        "burglar",
        "system"
    ],
    "sg:website":"www.adrtelecom.com",
    "wof:name":"ADR Telecom",
    "wof:placetype":"venue"
},
  "geometry": {"coordinates":[-75.483428,44.697114],"type":"Point"}
}