{
  "type": "Feature",
  "properties": {
    "addr:full":"111 E 125th Street New York NY 10035",
    "addr:housenumber":"111",
    "addr:postcode":"10035",
    "addr:street":"E 125Th Street",
    "iso:country":"US",
    "sg:address":"111 E 125th Street",
    "sg:city":"New York",
    "sg:classifiers":[
        {
            "category":"Personal",
            "subcategory":"Nail Salon",
            "type":"Services"
        }
    ],
    "sg:phone":"+1 212 369 2148",
    "sg:postcode":"10035",
    "sg:province":"NY",
    "wof:name":"Envy Nail Salon",
    "wof:placetype":"venue"
},
  "geometry": {"coordinates":[-73.938603,40.804895],"type":"Point"}
}