{
  "type": "Feature",
  "properties": {
    "iso:country":"US",
    "sg:address":"197 Madison St",
    "sg:city":"Oneida",
    "sg:classifiers":[
        {
            "category":"Building & Trades",
            "subcategory":"Construction",
            "type":"Services"
        }
    ],
    "sg:phone":"+1 315 363 8707",
    "sg:postcode":"13421",
    "sg:province":"NY",
    "sg:tags":[
        "roofing",
        "contractor"
    ],
    "wof:name":"Mc Carthy Roofing Inc",
    "wof:placetype":"venue"
},
  "geometry": {"coordinates":[-75.46689499999999,42.933396],"type":"Point"}
}