{
  "type": "Feature",
  "properties": {
    "addr:full":"40 Erie St Goshen NY 10924",
    "addr:housenumber":"40",
    "addr:postcode":"10924",
    "addr:street":"Erie St",
    "iso:country":"US",
    "sg:address":"40 Erie St",
    "sg:city":"Goshen",
    "sg:classifiers":[
        {
            "category":"Professional",
            "subcategory":"Management & Consulting",
            "type":"Services"
        }
    ],
    "sg:phone":"+1 845 294 3352",
    "sg:postcode":"10924",
    "sg:province":"NY",
    "sg:tags":[
        "food"
    ],
    "wof:name":"Aramark Correctional Svc",
    "wof:placetype":"venue"
},
  "geometry": {"coordinates":[-74.32182899999999,41.406132],"type":"Point"}
}