{
  "type": "Feature",
  "properties": {
    "addr:full":"4 Greenwood Ln St James NY 11780",
    "addr:housenumber":"4",
    "addr:postcode":"11780",
    "addr:street":"Greenwood Ln",
    "iso:country":"US",
    "sg:address":"4 Greenwood Ln",
    "sg:city":"St James",
    "sg:classifiers":[
        {
            "category":"Insurance",
            "subcategory":"Insurance Agent",
            "type":"Services"
        }
    ],
    "sg:phone":"+1 631 584 2227",
    "sg:postcode":"11780",
    "sg:province":"NY",
    "wof:name":"Mc Ross Agency",
    "wof:placetype":"venue"
},
  "geometry": {"coordinates":[-73.140472,40.889308],"type":"Point"}
}