{
  "type": "Feature",
  "properties": {
    "addr:full":"2922 Broadway New York NY 10027",
    "addr:housenumber":"2922",
    "addr:postcode":"10027",
    "addr:street":"Broadway",
    "iso:country":"US",
    "sg:address":"2922 Broadway",
    "sg:city":"New York",
    "sg:classifiers":[
        {
            "category":"Shopping",
            "subcategory":"Books",
            "type":"Retail Goods"
        }
    ],
    "sg:phone":"+1 212 854 4131",
    "sg:postcode":"10027",
    "sg:province":"NY",
    "sg:tags":[
        "dealer"
    ],
    "wof:name":"Columbia Bookstore",
    "wof:placetype":"venue"
},
  "geometry": {"coordinates":[-73.962103,40.810298],"type":"Point"}
}