{
  "type": "Feature",
  "properties": {
    "addr:full":"30 Old Rte 9 Wappingers Falls NY 12590",
    "addr:housenumber":"30",
    "addr:postcode":"12590",
    "addr:street":"Old Rte 9",
    "iso:country":"US",
    "sg:address":"30 Old Rte 9",
    "sg:city":"Wappingers Falls",
    "sg:classifiers":[
        {
            "category":"Mining & Drilling",
            "type":"Manufacturing & Wholesale Goods"
        }
    ],
    "sg:phone":"+1 845 297 6089",
    "sg:postcode":"12590",
    "sg:province":"NY",
    "sg:tags":[
        "oil",
        "gas",
        "producer"
    ],
    "wof:name":"Wappingers Oil",
    "wof:placetype":"venue"
},
  "geometry": {"coordinates":[-73.910884,41.592069],"type":"Point"}
}