{
  "type": "Feature",
  "properties": {
    "iso:country":"US",
    "sg:address":"1659 E Noxon Rd",
    "sg:city":"Lagrangeville",
    "sg:classifiers":[
        {
            "category":"Education",
            "subcategory":"School",
            "type":"Public Place"
        }
    ],
    "sg:phone":"+1 845 223 8030",
    "sg:postcode":"12540",
    "sg:province":"NY",
    "wof:name":"Vail Farm Elementary School",
    "wof:placetype":"venue"
},
  "geometry": {"coordinates":[-73.740371,41.64996],"type":"Point"}
}