{
  "type": "Feature",
  "properties": {
    "iso:country":"US",
    "sg:address":"43 Briar Ln",
    "sg:city":"Jericho",
    "sg:classifiers":[
        {
            "category":"Professional",
            "subcategory":"Computer Services",
            "type":"Services"
        }
    ],
    "sg:phone":"+1   ",
    "sg:postcode":"11753",
    "sg:province":"NY",
    "sg:tags":[
        "related"
    ],
    "wof:name":"Briar Systems Inc",
    "wof:placetype":"venue"
},
  "geometry": {"coordinates":[-73.526625,40.790679],"type":"Point"}
}