{
  "type": "Feature",
  "properties": {
    "iso:country":"US",
    "sg:address":"40 Bridge St",
    "sg:city":"New York",
    "sg:classifiers":[
        {
            "category":"Retail",
            "subcategory":"Auto Repair",
            "type":"Services"
        }
    ],
    "sg:phone":"+1 646 237 1461",
    "sg:postcode":"10004",
    "sg:province":"NY",
    "wof:name":"Auto Care & Tow 24 Hours",
    "wof:placetype":"venue"
},
  "geometry": {"coordinates":[-74.01159699999999,40.703499],"type":"Point"}
}