{
  "type": "Feature",
  "properties": {
    "addr:full":"1837 Victory Blvd Staten Island NY 10314",
    "addr:housenumber":"1837",
    "addr:postcode":"10314",
    "addr:street":"Victory Blvd",
    "iso:country":"US",
    "sg:address":"1837 Victory Blvd",
    "sg:city":"Staten Island",
    "sg:classifiers":[
        {
            "category":"Banks & Credit Unions",
            "subcategory":"Bank",
            "type":"Services"
        }
    ],
    "sg:phone":"+1 718 447 8880",
    "sg:postcode":"10314",
    "sg:province":"NY",
    "wof:name":"Independence Community Bank",
    "wof:placetype":"venue"
},
  "geometry": {"coordinates":[-74.124636,40.612953],"type":"Point"}
}