{
  "type": "Feature",
  "properties": {
    "iso:country":"US",
    "sg:address":"3 Winners Cir",
    "sg:city":"Albany",
    "sg:classifiers":[
        {
            "category":"Professional",
            "subcategory":"Management & Consulting",
            "type":"Services"
        }
    ],
    "sg:phone":"+1 518 451 8000",
    "sg:postcode":"12205",
    "sg:province":"NY",
    "sg:tags":[
        "marketing",
        "program"
    ],
    "sg:website":"www.ctadvantage.com",
    "wof:name":"C T Corp",
    "wof:placetype":"venue"
},
  "geometry": {"coordinates":[-73.798787,42.718344],"type":"Point"}
}