{
  "type": "Feature",
  "properties": {
    "iso:country":"US",
    "sg:address":"27 Jackson St",
    "sg:city":"Little Falls",
    "sg:classifiers":[
        {
            "category":"Social Services",
            "type":"Services"
        }
    ],
    "sg:phone":"+1 315 823 1740",
    "sg:postcode":"13365",
    "sg:province":"NY",
    "sg:tags":[
        "community"
    ],
    "wof:name":"Little Falls Family YMCA",
    "wof:placetype":"venue"
},
  "geometry": {"coordinates":[-74.858586,43.04566],"type":"Point"}
}