{
  "type": "Feature",
  "properties": {
    "addr:full":"61 Cornell Dr Depew NY 14043",
    "addr:housenumber":"61",
    "addr:postcode":"14043",
    "addr:street":"Cornell Dr",
    "iso:country":"US",
    "sg:address":"61 Cornell Dr",
    "sg:city":"Depew",
    "sg:classifiers":[
        {
            "category":"Shopping",
            "subcategory":"Used Merchandise",
            "type":"Retail Goods"
        }
    ],
    "sg:phone":"+1   ",
    "sg:postcode":"14043",
    "sg:province":"NY",
    "wof:name":"Suzanne Rappleye Antiques",
    "wof:placetype":"venue"
},
  "geometry": {"coordinates":[-78.706621,42.917844],"type":"Point"}
}