{
  "type": "Feature",
  "properties": {
    "addr:full":"9000 Sheridan Dr Clarence NY 14031",
    "addr:housenumber":"9000",
    "addr:postcode":"14031",
    "addr:street":"Sheridan Dr",
    "iso:country":"US",
    "sg:address":"9000 Sheridan Dr",
    "sg:city":"Clarence",
    "sg:classifiers":[
        {
            "category":"Building & Trades",
            "subcategory":"Construction",
            "type":"Services"
        }
    ],
    "sg:phone":"+1 716 837 3084",
    "sg:postcode":"14031",
    "sg:province":"NY",
    "sg:tags":[
        "planning",
        "remodeling",
        "kitchen"
    ],
    "wof:name":"Beautiful Homes By Thomas",
    "wof:placetype":"venue"
},
  "geometry": {"coordinates":[-78.659476,42.974873],"type":"Point"}
}