{
  "type": "Feature",
  "properties": {
    "iso:country":"US",
    "sg:address":"2700 State Hwy 315",
    "sg:city":"Deansboro",
    "sg:classifiers":[
        {
            "category":"Government",
            "subcategory":"Office",
            "type":"Public Place"
        }
    ],
    "sg:phone":"+1 315 841 8051",
    "sg:postcode":"13328",
    "sg:province":"NY",
    "sg:tags":[
        "village"
    ],
    "wof:name":"Highway Garage",
    "wof:placetype":"venue"
},
  "geometry": {"coordinates":[-75.428274,42.994872],"type":"Point"}
}