{
  "type": "Feature",
  "properties": {
    "addr:full":"8801 Ditmas Ave Brooklyn NY 11236",
    "addr:housenumber":"8801",
    "addr:postcode":"11236",
    "addr:street":"Ditmas Ave",
    "iso:country":"US",
    "sg:address":"8801 Ditmas Ave",
    "sg:city":"Brooklyn",
    "sg:classifiers":[
        {
            "category":"Home & Garden",
            "subcategory":"Carpets & Floor Coverings",
            "type":"Retail Goods"
        }
    ],
    "sg:phone":"+1 212 644 1407",
    "sg:postcode":"11236",
    "sg:province":"NY",
    "sg:tags":[
        "dealer",
        "rug"
    ],
    "wof:name":"Christian Brothers Carpet",
    "wof:placetype":"venue"
},
  "geometry": {"coordinates":[-73.91549999999999,40.647605],"type":"Point"}
}