{
  "type": "Feature",
  "properties": {
    "addr:full":"7567 Oswego Rd Liverpool NY 13090",
    "addr:housenumber":"7567",
    "addr:postcode":"13090",
    "addr:street":"Oswego Rd",
    "iso:country":"US",
    "sg:address":"7567 Oswego Rd",
    "sg:city":"Liverpool",
    "sg:classifiers":[
        {
            "category":"Utilities",
            "subcategory":"Mobile Phone",
            "type":"Services"
        },
        {
            "category":"Coffee & Tea",
            "type":"Food & Drink"
        }
    ],
    "sg:phone":"+1 315 622 8932",
    "sg:postcode":"13090",
    "sg:province":"NY",
    "sg:tags":[
        "shop",
        "restaurant",
        "espresso",
        "hotspot",
        "wi-fi"
    ],
    "sg:website":"http://www.starbuckscoffee.com",
    "wof:name":"Starbucks Coffee",
    "wof:placetype":"venue"
},
  "geometry": {"coordinates":[-76.22525,43.13664],"type":"Point"}
}