{
  "type": "Feature",
  "properties": {
    "iso:country":"US",
    "sg:address":"255 Main St",
    "sg:city":"Goshen",
    "sg:classifiers":[
        {
            "category":"Government",
            "subcategory":"Court House",
            "type":"Public Place"
        }
    ],
    "sg:phone":"+1 845 291 3150",
    "sg:postcode":"10924",
    "sg:province":"NY",
    "sg:tags":[
        "county",
        "counsel"
    ],
    "wof:name":"Orange County Attorney",
    "wof:placetype":"venue"
},
  "geometry": {"coordinates":[-74.318783,41.404788],"type":"Point"}
}