{
  "type": "Feature",
  "properties": {
    "iso:country":"US",
    "sg:address":"214 Broadway",
    "sg:city":"Amityville",
    "sg:classifiers":[
        {
            "category":"Personal",
            "subcategory":"Beauty Salon",
            "type":"Services"
        }
    ],
    "sg:phone":"+1 631 691 1176",
    "sg:postcode":"11701",
    "sg:province":"NY",
    "wof:name":"Profiles Hair Studio",
    "wof:placetype":"venue"
},
  "geometry": {"coordinates":[-73.417131,40.680188],"type":"Point"}
}