{
  "type": "Feature",
  "properties": {
    "iso:country":"US",
    "sg:address":"1 Blauvelt Pl",
    "sg:city":"Scarsdale",
    "sg:classifiers":[
        {
            "category":"Manufacturing",
            "subcategory":"Aerospace",
            "type":"Manufacturing & Wholesale Goods"
        }
    ],
    "sg:phone":"+1   ",
    "sg:postcode":"10583",
    "sg:province":"NY",
    "sg:tags":[
        "aircraft",
        "mfg"
    ],
    "wof:name":"R M P Corporation",
    "wof:placetype":"venue"
},
  "geometry": {"coordinates":[-73.811114,40.992304],"type":"Point"}
}