{
  "type": "Feature",
  "properties": {
    "addr:full":"971 Irish Settlement Rd Freeville NY 13068",
    "addr:housenumber":"971",
    "addr:postcode":"13068",
    "addr:street":"Irish Settlement Rd",
    "iso:country":"US",
    "sg:address":"971 Irish Settlement Rd",
    "sg:city":"Freeville",
    "sg:classifiers":[
        {
            "category":"Building & Trades",
            "subcategory":"Construction",
            "type":"Services"
        }
    ],
    "sg:phone":"+1 607 844 8598",
    "sg:postcode":"13068",
    "sg:province":"NY",
    "sg:tags":[
        "excavation",
        "contractor"
    ],
    "wof:name":"Maybee Gary Lee",
    "wof:placetype":"venue"
},
  "geometry": {"coordinates":[-76.335718,42.428414],"type":"Point"}
}