{
  "type": "Feature",
  "properties": {
    "addr:full":"249 Grand St New York NY 10002",
    "addr:housenumber":"249",
    "addr:postcode":"10002",
    "addr:street":"Grand St",
    "iso:country":"US",
    "sg:address":"249 Grand St",
    "sg:city":"New York",
    "sg:classifiers":[
        {
            "category":"Food & Beverages",
            "subcategory":"Meat & Fish",
            "type":"Retail Goods"
        }
    ],
    "sg:phone":"+1 212 966 7878",
    "sg:postcode":"10002",
    "sg:province":"NY",
    "sg:tags":[
        "grocery",
        "seafood",
        "store"
    ],
    "wof:name":"Tan My My Co Inc",
    "wof:placetype":"venue"
},
  "geometry": {"coordinates":[-73.99417099999999,40.718034],"type":"Point"}
}