{
  "type": "Feature",
  "properties": {
    "iso:country":"US",
    "sg:address":"37 Quaker St",
    "sg:city":"Granville",
    "sg:classifiers":[
        {
            "category":"Autos & Motor Vehicles",
            "subcategory":"Auto Supplies",
            "type":"Retail Goods"
        }
    ],
    "sg:phone":"+1 518 642 1784",
    "sg:postcode":"12832",
    "sg:province":"NY",
    "sg:tags":[
        "automobile",
        "part"
    ],
    "wof:name":"Rutland Auto Supply Inc",
    "wof:placetype":"venue"
},
  "geometry": {"coordinates":[-73.265793,43.403439],"type":"Point"}
}