{
  "type": "Feature",
  "properties": {
    "addr:full":"145 Smithtown Blvd Ste 1 Nesconset NY 11767",
    "addr:housenumber":"145",
    "addr:postcode":"11767",
    "addr:street":"Smithtown Blvd Ste 1",
    "iso:country":"US",
    "sg:address":"145 Smithtown Blvd Ste 1",
    "sg:city":"Nesconset",
    "sg:phone":"+1 631 979 2583",
    "sg:postcode":"11767",
    "sg:province":"NY",
    "wof:name":"Boulevard Hot Bagels",
    "wof:placetype":"venue"
},
  "geometry": {"coordinates":[-73.159683,40.837551],"type":"Point"}
}