{
  "type": "Feature",
  "properties": {
    "addr:full":"16 Erie St Yorkville NY 13495",
    "addr:housenumber":"16",
    "addr:postcode":"13495",
    "addr:street":"Erie St",
    "iso:country":"US",
    "sg:address":"16 Erie St",
    "sg:city":"Yorkville",
    "sg:classifiers":[
        {
            "category":"Restaurant",
            "type":"Food & Drink"
        }
    ],
    "sg:phone":"+1   ",
    "sg:postcode":"13495",
    "sg:province":"NY",
    "sg:tags":[
        "bar"
    ],
    "wof:name":"Club Monarch",
    "wof:placetype":"venue"
},
  "geometry": {"coordinates":[-75.28109499999999,43.114207],"type":"Point"}
}