{
  "type": "Feature",
  "properties": {
    "iso:country":"US",
    "sg:address":"880 Broadway",
    "sg:city":"Albany",
    "sg:classifiers":[
        {
            "category":"Retail",
            "subcategory":"Repair Shop",
            "type":"Services"
        }
    ],
    "sg:phone":"+1 518 465 8878",
    "sg:postcode":"12207",
    "sg:province":"NY",
    "sg:tags":[
        "commercial",
        "heating",
        "air",
        "s",
        "refrigeration",
        "conditioning"
    ],
    "sg:website":"www.easternheatingcooling.com",
    "wof:name":"Eastern Heating & Cooling Inc",
    "wof:placetype":"venue"
},
  "geometry": {"coordinates":[-73.745552,42.660474],"type":"Point"}
}