{
  "type": "Feature",
  "properties": {
    "iso:country":"US",
    "sg:address":"51 N Park Dr",
    "sg:city":"Rochester",
    "sg:classifiers":[
        {
            "category":"Professional",
            "subcategory":"Management & Consulting",
            "type":"Services"
        }
    ],
    "sg:phone":"+1   ",
    "sg:postcode":"14612",
    "sg:province":"NY",
    "sg:tags":[
        "support",
        "retail",
        "business"
    ],
    "wof:name":"Brolain Collections  Inc",
    "wof:placetype":"venue"
},
  "geometry": {"coordinates":[-77.649309,43.25568],"type":"Point"}
}