{
  "type": "Feature",
  "properties": {
    "iso:country":"US",
    "sg:address":"11108 Roosevelt Ave",
    "sg:city":"Corona",
    "sg:classifiers":[
        {
            "category":"Bars & Pubs",
            "subcategory":"Sports Bar",
            "type":"Food & Drink"
        }
    ],
    "sg:phone":"+1 347 242 3213",
    "sg:postcode":"11368",
    "sg:province":"NY",
    "sg:tags":[
        "hall",
        "pool"
    ],
    "wof:name":"Loumax Billiards Inc",
    "wof:placetype":"venue"
},
  "geometry": {"coordinates":[-73.855614,40.751525],"type":"Point"}
}