{
  "type": "Feature",
  "properties": {
    "addr:full":"1026 6th Ave Ste 402 Manhattan NY 10018",
    "addr:housenumber":"1026",
    "addr:postcode":"10018",
    "addr:street":"6Th Ave Ste 402",
    "iso:country":"US",
    "sg:address":"1026 6th Ave Ste 402",
    "sg:city":"Manhattan",
    "sg:classifiers":[
        {
            "category":"Health Services",
            "subcategory":"Health Practitioner",
            "type":"Services"
        }
    ],
    "sg:phone":"+1 917 509 7318",
    "sg:postcode":"10018",
    "sg:province":"NY",
    "sg:tags":[
        "acupuncture"
    ],
    "sg:website":"www.ancientformacupuncture.com",
    "wof:name":"Ancient Form Acupuncture",
    "wof:placetype":"venue"
},
  "geometry": {"coordinates":[-73.985759,40.752572],"type":"Point"}
}