{
  "type": "Feature",
  "properties": {
    "iso:country":"US",
    "sg:address":"348 W End Ave",
    "sg:city":"New York",
    "sg:classifiers":[
        {
            "category":"Real Estate",
            "subcategory":"Real Estate Agent",
            "type":"Services"
        }
    ],
    "sg:phone":"+1 212 496 7387",
    "sg:postcode":"10024",
    "sg:province":"NY",
    "sg:tags":[
        "construction"
    ],
    "wof:name":"Orchard Mangement Inc",
    "wof:placetype":"venue"
},
  "geometry": {"coordinates":[-73.982192,40.782753],"type":"Point"}
}