{
  "type": "Feature",
  "properties": {
    "addr:full":"860 Pennsylvania Avenue Brooklyn NY 11207",
    "addr:housenumber":"860",
    "addr:postcode":"11207",
    "addr:street":"Pennsylvania Avenue",
    "iso:country":"US",
    "sg:address":"860 Pennsylvania Avenue",
    "sg:city":"Brooklyn",
    "sg:classifiers":[
        {
            "category":"Travel",
            "subcategory":"Hotels & Motels",
            "type":"Entertainment"
        }
    ],
    "sg:phone":"+1 718 649 4800",
    "sg:postcode":"11207",
    "sg:province":"NY",
    "wof:name":"Galaxy Hotel",
    "wof:placetype":"venue"
},
  "geometry": {"coordinates":[-73.88845999999999,40.655325],"type":"Point"}
}