{
  "type": "Feature",
  "properties": {
    "addr:full":"121 Morgan Ave Brooklyn NY 11237",
    "addr:housenumber":"121",
    "addr:postcode":"11237",
    "addr:street":"Morgan Ave",
    "iso:country":"US",
    "sg:address":"121 Morgan Ave",
    "sg:city":"Brooklyn",
    "sg:classifiers":[
        {
            "category":"Manufacturing",
            "subcategory":"Paper Products",
            "type":"Manufacturing & Wholesale Goods"
        }
    ],
    "sg:phone":"+1 718 381 7683",
    "sg:postcode":"11237",
    "sg:province":"NY",
    "sg:tags":[
        "bag"
    ],
    "wof:name":"C P Sunrise Trading",
    "wof:placetype":"venue"
},
  "geometry": {"coordinates":[-73.932545,40.708073],"type":"Point"}
}