{
  "type": "Feature",
  "properties": {
    "iso:country":"US",
    "sg:address":"26 Reserve Rd",
    "sg:city":"Buffalo",
    "sg:classifiers":[
        {
            "category":"Building & Trades",
            "subcategory":"Construction",
            "type":"Services"
        }
    ],
    "sg:phone":"+1 716 674 3646",
    "sg:postcode":"14224",
    "sg:province":"NY",
    "sg:tags":[
        "contractor"
    ],
    "wof:name":"Reserve Contracting",
    "wof:placetype":"venue"
},
  "geometry": {"coordinates":[-78.75941,42.811379],"type":"Point"}
}