{
  "type": "Feature",
  "properties": {
    "iso:country":"US",
    "sg:address":"120 E Jefferson St",
    "sg:city":"Syracuse",
    "sg:classifiers":[
        {
            "category":"Banks & Credit Unions",
            "subcategory":"Bank",
            "type":"Services"
        }
    ],
    "sg:phone":"+1 315 474 1939",
    "sg:postcode":"13202",
    "sg:province":"NY",
    "sg:tags":[
        "loan",
        "real estate"
    ],
    "sg:website":"www.homehq.org",
    "wof:name":"Home Headquarters Inc",
    "wof:placetype":"venue"
},
  "geometry": {"coordinates":[-76.150825,43.046952],"type":"Point"}
}