{
  "type": "Feature",
  "properties": {
    "addr:full":"20 Lewis Ave Brooklyn NY 11206",
    "addr:housenumber":"20",
    "addr:postcode":"11206",
    "addr:street":"Lewis Ave",
    "iso:country":"US",
    "sg:address":"20 Lewis Ave",
    "sg:city":"Brooklyn",
    "sg:classifiers":[
        {
            "category":"Government",
            "subcategory":"Office",
            "type":"Public Place"
        }
    ],
    "sg:phone":"+1 718 453 4343",
    "sg:postcode":"11206",
    "sg:province":"NY",
    "sg:tags":[
        "housing",
        "program"
    ],
    "wof:name":"Sumner Apartments",
    "wof:placetype":"venue"
},
  "geometry": {"coordinates":[-73.937878,40.696751],"type":"Point"}
}