{
  "type": "Feature",
  "properties": {
    "iso:country":"US",
    "sg:address":"388 Main St",
    "sg:city":"Schoharie",
    "sg:classifiers":[
        {
            "category":"Local Transit",
            "type":"Transportation"
        }
    ],
    "sg:phone":"+1 518 295 7425",
    "sg:postcode":"12157",
    "sg:province":"NY",
    "sg:tags":[
        "ambulance"
    ],
    "wof:name":"Scho Wright Ambulance",
    "wof:placetype":"venue"
},
  "geometry": {"coordinates":[-74.31508599999999,42.661185],"type":"Point"}
}