{
  "type": "Feature",
  "properties": {
    "addr:full":"35 Brady Ave New Rochelle NY 10805",
    "addr:housenumber":"35",
    "addr:postcode":"10805",
    "addr:street":"Brady Ave",
    "iso:country":"US",
    "sg:address":"35 Brady Ave",
    "sg:city":"New Rochelle",
    "sg:classifiers":[
        {
            "category":"Organizations",
            "subcategory":"Community Association",
            "type":"Services"
        }
    ],
    "sg:phone":"+1 914 235 0955",
    "sg:postcode":"10805",
    "sg:province":"NY",
    "wof:name":"International Veteran Box",
    "wof:placetype":"venue"
},
  "geometry": {"coordinates":[-73.79013500000001,40.895972],"type":"Point"}
}