{
  "type": "Feature",
  "properties": {
    "iso:country":"US",
    "sg:address":"4966 State Hwy 23",
    "sg:city":"Oneonta",
    "sg:classifiers":[
        {
            "category":"Shopping",
            "type":"Retail Goods"
        }
    ],
    "sg:phone":"+1 607 433 0829",
    "sg:postcode":"13820",
    "sg:province":"NY",
    "sg:tags":[
        "orthopedic",
        "appliance"
    ],
    "wof:name":"Aktive Orhotics",
    "wof:placetype":"venue"
},
  "geometry": {"coordinates":[-75.037004,42.448567],"type":"Point"}
}