{
  "type": "Feature",
  "properties": {
    "addr:full":"21 John Dr Farmingville NY 11738",
    "addr:housenumber":"21",
    "addr:postcode":"11738",
    "addr:street":"John Dr",
    "iso:country":"US",
    "sg:address":"21 John Dr",
    "sg:city":"Farmingville",
    "sg:classifiers":[
        {
            "category":"Real Estate",
            "subcategory":"Real Estate Services",
            "type":"Services"
        },
        {
            "category":"Banks & Credit Unions",
            "subcategory":"Financial Services",
            "type":"Services"
        }
    ],
    "sg:phone":"+1 631 451 7400",
    "sg:postcode":"11738",
    "sg:province":"NY",
    "sg:tags":[
        "loan",
        "processing"
    ],
    "wof:name":"Jim Mr Mortgage",
    "wof:placetype":"venue"
},
  "geometry": {"coordinates":[-73.033439,40.836218],"type":"Point"}
}