{
  "type": "Feature",
  "properties": {
    "addr:full":"238 Spring St Monroe NY 10950",
    "addr:housenumber":"238",
    "addr:postcode":"10950",
    "addr:street":"Spring St",
    "iso:country":"US",
    "sg:address":"238 Spring St",
    "sg:city":"Monroe",
    "sg:classifiers":[
        {
            "category":"Retail",
            "subcategory":"Auto Repair",
            "type":"Services"
        }
    ],
    "sg:phone":"+1 845 783 1871",
    "sg:postcode":"10950",
    "sg:province":"NY",
    "wof:name":"Monroe Automotive",
    "wof:placetype":"venue"
},
  "geometry": {"coordinates":[-74.17953300000001,41.32707],"type":"Point"}
}