{
  "type": "Feature",
  "properties": {
    "iso:country":"US",
    "sg:address":"7802 Bay Pkwy",
    "sg:city":"Brooklyn",
    "sg:classifiers":[
        {
            "category":"Professional",
            "subcategory":"Lawyer & Legal Services",
            "type":"Services"
        }
    ],
    "sg:phone":"+1   ",
    "sg:postcode":"11214",
    "sg:province":"NY",
    "wof:name":"Mira Wolf Russian",
    "wof:placetype":"venue"
},
  "geometry": {"coordinates":[-73.989763,40.605946],"type":"Point"}
}