{
  "type": "Feature",
  "properties": {
    "iso:country":"US",
    "sg:address":"11917 N Lake Rd",
    "sg:city":"Forestport",
    "sg:classifiers":[
        {
            "category":"Bars & Pubs",
            "type":"Food & Drink"
        },
        {
            "category":"Bars & Pubs",
            "subcategory":"Lounge",
            "type":"Food & Drink"
        }
    ],
    "sg:phone":"+1 315 392 6008",
    "sg:postcode":"13338",
    "sg:province":"NY",
    "sg:tags":[
        "cocktail"
    ],
    "wof:name":"Trackside Blazers Inc",
    "wof:placetype":"venue"
},
  "geometry": {"coordinates":[-75.097123,43.442133],"type":"Point"}
}