{
  "type": "Feature",
  "properties": {
    "addr:full":"2 W Park Ave Long Beach NY 11561",
    "addr:housenumber":"2",
    "addr:postcode":"11561",
    "addr:street":"W Park Ave",
    "iso:country":"US",
    "sg:address":"2 W Park Ave",
    "sg:city":"Long Beach",
    "sg:classifiers":[
        {
            "category":"Fast Food",
            "type":"Food & Drink"
        }
    ],
    "sg:phone":"+1 516 431 1999",
    "sg:postcode":"11561",
    "sg:province":"NY",
    "sg:tags":[
        "burger"
    ],
    "sg:website":"www.fiveguys.com",
    "wof:name":"Five Guys Famous Burgers and Fries",
    "wof:placetype":"venue"
},
  "geometry": {"coordinates":[-73.66415000000001,40.58836],"type":"Point"}
}