{
  "type": "Feature",
  "properties": {
    "iso:country":"US",
    "sg:address":"5 Charlick Pl",
    "sg:city":"Freeport",
    "sg:classifiers":[
        {
            "category":"Community Center",
            "subcategory":"Youth",
            "type":"Public Place"
        }
    ],
    "sg:phone":"+1 516 868 3066",
    "sg:postcode":"11520",
    "sg:province":"NY",
    "wof:name":"Bethel Freeport Youth Center",
    "wof:placetype":"venue"
},
  "geometry": {"coordinates":[-73.586618,40.670294],"type":"Point"}
}