{
  "type": "Feature",
  "properties": {
    "iso:country":"US",
    "sg:address":"75 Landing Meadow Rd",
    "sg:city":"Smithtown",
    "sg:classifiers":[
        {
            "category":"Organizations",
            "subcategory":"Non-profit Organization",
            "type":"Services"
        },
        {
            "category":"Education",
            "subcategory":"School",
            "type":"Public Place"
        }
    ],
    "sg:phone":"+1 631 360 4600",
    "sg:postcode":"11787",
    "sg:province":"NY",
    "sg:tags":[
        "disability"
    ],
    "wof:name":"Develpmental Disabilities Inst",
    "wof:placetype":"venue"
},
  "geometry": {"coordinates":[-73.201414,40.875244],"type":"Point"}
}