{
  "type": "Feature",
  "properties": {
    "iso:country":"US",
    "sg:address":"4 Stirling Cir",
    "sg:city":"Highland Mills",
    "sg:classifiers":[
        {
            "category":"Professional",
            "type":"Services"
        }
    ],
    "sg:phone":"+1   ",
    "sg:postcode":"10930",
    "sg:province":"NY",
    "wof:name":"E Voicelink Company",
    "wof:placetype":"venue"
},
  "geometry": {"coordinates":[-74.12239599999999,41.361668],"type":"Point"}
}