{
  "type": "Feature",
  "properties": {
    "iso:country":"US",
    "sg:address":"299 W John St",
    "sg:city":"Hicksville",
    "sg:classifiers":[
        {
            "category":"Health Services",
            "subcategory":"Clinic",
            "type":"Services"
        }
    ],
    "sg:phone":"+1 516 942 7652",
    "sg:postcode":"11801",
    "sg:province":"NY",
    "sg:tags":[
        "home",
        "care"
    ],
    "wof:name":"Alternate Care Inc",
    "wof:placetype":"venue"
},
  "geometry": {"coordinates":[-73.535967,40.767219],"type":"Point"}
}