{
  "type": "Feature",
  "properties": {
    "addr:full":"3980 Sheridan Dr Buffalo NY 14226",
    "addr:housenumber":"3980",
    "addr:postcode":"14226",
    "addr:street":"Sheridan Dr",
    "iso:country":"US",
    "sg:address":"3980 Sheridan Dr",
    "sg:city":"Buffalo",
    "sg:classifiers":[
        {
            "category":"Social Services",
            "subcategory":"Job Training",
            "type":"Services"
        }
    ],
    "sg:phone":"+1 716 839 1445",
    "sg:postcode":"14226",
    "sg:province":"NY",
    "sg:tags":[
        "career",
        "counseling",
        "vocational"
    ],
    "wof:name":"Advantage Resume Svc",
    "wof:placetype":"venue"
},
  "geometry": {"coordinates":[-78.786931,42.978767],"type":"Point"}
}