{
  "type": "Feature",
  "properties": {
    "addr:full":"1132 Route 9W Marlboro NY 12542",
    "addr:housenumber":"1132",
    "addr:postcode":"12542",
    "addr:street":"Route 9W",
    "iso:country":"US",
    "sg:address":"1132 Route 9W",
    "sg:city":"Marlboro",
    "sg:classifiers":[
        {
            "category":"Building & Trades",
            "subcategory":"Construction",
            "type":"Services"
        }
    ],
    "sg:phone":"+1 845 236 2814",
    "sg:postcode":"12542",
    "sg:province":"NY",
    "sg:tags":[
        "contractor"
    ],
    "wof:name":"Peter Mannese Contracting Inc",
    "wof:placetype":"venue"
},
  "geometry": {"coordinates":[-73.975945,41.595466],"type":"Point"}
}