{
  "type": "Feature",
  "properties": {
    "iso:country":"US",
    "sg:address":"5023 Main St",
    "sg:city":"South Fallsburg",
    "sg:classifiers":[
        {
            "category":"Building & Trades",
            "subcategory":"Construction",
            "type":"Services"
        }
    ],
    "sg:phone":"+1 845 434 2600",
    "sg:postcode":"12779",
    "sg:province":"NY",
    "sg:tags":[
        "home",
        "builder"
    ],
    "wof:name":"Catskill Vacation Home Builder",
    "wof:placetype":"venue"
},
  "geometry": {"coordinates":[-74.652913,41.686293],"type":"Point"}
}