{
  "type": "Feature",
  "properties": {
    "addr:full":"48 Donna Ct Staten Island NY 10314",
    "addr:housenumber":"48",
    "addr:postcode":"10314",
    "addr:street":"Donna Ct",
    "iso:country":"US",
    "sg:address":"48 Donna Ct",
    "sg:city":"Staten Island",
    "sg:classifiers":[
        {
            "category":"Professional",
            "type":"Services"
        }
    ],
    "sg:phone":"+1   ",
    "sg:postcode":"10314",
    "sg:province":"NY",
    "wof:name":"Saltech Inc",
    "wof:placetype":"venue"
},
  "geometry": {"coordinates":[-74.16228099999999,40.580712],"type":"Point"}
}