{
  "type": "Feature",
  "properties": {
    "iso:country":"US",
    "sg:address":"5701 2nd Ave",
    "sg:city":"Brooklyn",
    "sg:classifiers":[
        {
            "category":"Retail",
            "subcategory":"Auto Repair",
            "type":"Services"
        }
    ],
    "sg:phone":"+1 718 439 6064",
    "sg:postcode":"11220",
    "sg:province":"NY",
    "wof:name":"Manlor Corp",
    "wof:placetype":"venue"
},
  "geometry": {"coordinates":[-74.021004,40.645],"type":"Point"}
}