{
  "type": "Feature",
  "properties": {
    "addr:full":"1128 Rte 112 Port Jeffrsn Sta NY 11776",
    "addr:housenumber":"1128",
    "addr:postcode":"11776",
    "addr:street":"Rte 112 Port Jeffrsn Sta",
    "iso:country":"US",
    "sg:address":"1128 Rte 112",
    "sg:city":"Port Jeffrsn Sta",
    "sg:classifiers":[
        {
            "category":"Autos & Motor Vehicles",
            "subcategory":"Fuel & Gas Station",
            "type":"Retail Goods"
        }
    ],
    "sg:phone":"+1 631 473 4402",
    "sg:postcode":"11776",
    "sg:province":"NY",
    "sg:tags":[
        "oil"
    ],
    "wof:name":"Eagle Gas Corp",
    "wof:placetype":"venue"
},
  "geometry": {"coordinates":[-73.041708,40.920595],"type":"Point"}
}