{
  "type": "Feature",
  "properties": {
    "addr:full":"248 Middle Country Rd Coram NY 11727",
    "addr:housenumber":"248",
    "addr:postcode":"11727",
    "addr:street":"Middle Country Rd",
    "iso:country":"US",
    "sg:address":"248 Middle Country Rd",
    "sg:city":"Coram",
    "sg:classifiers":[
        {
            "category":"Health Services",
            "subcategory":"Doctor",
            "type":"Services"
        }
    ],
    "sg:phone":"+1 631 732 5121",
    "sg:postcode":"11727",
    "sg:province":"NY",
    "sg:tags":[
        "physician",
        "surgeon"
    ],
    "wof:name":"Mark Steinberg MD",
    "wof:placetype":"venue"
},
  "geometry": {"coordinates":[-72.995834,40.871067],"type":"Point"}
}