{
  "type": "Feature",
  "properties": {
    "addr:full":"502A 9th St Brooklyn NY 11215",
    "addr:housenumber":"502a",
    "addr:postcode":"11215",
    "addr:street":"9Th St",
    "iso:country":"US",
    "sg:address":"502A 9th St",
    "sg:city":"Brooklyn",
    "sg:classifiers":[
        {
            "category":"Health Services",
            "subcategory":"Doctor",
            "type":"Services"
        }
    ],
    "sg:phone":"+1 718 369 3660",
    "sg:postcode":"11215",
    "sg:province":"NY",
    "sg:tags":[
        "podiatrist"
    ],
    "wof:name":"Caprioni Enrico P DPM",
    "wof:placetype":"venue"
},
  "geometry": {"coordinates":[-73.9813,40.666599],"type":"Point"}
}