{
  "type": "Feature",
  "properties": {
    "addr:full":"185 Bryant St North Tonawanda NY 14120",
    "addr:housenumber":"185",
    "addr:postcode":"14120",
    "addr:street":"Bryant St",
    "iso:country":"US",
    "sg:address":"185 Bryant St",
    "sg:city":"North Tonawanda",
    "sg:classifiers":[
        {
            "category":"Organizations",
            "subcategory":"Religious Organization",
            "type":"Services"
        }
    ],
    "sg:phone":"+1 716 693 3602",
    "sg:postcode":"14120",
    "sg:province":"NY",
    "sg:tags":[
        "clergy"
    ],
    "wof:name":"Stuart H Smith",
    "wof:placetype":"venue"
},
  "geometry": {"coordinates":[-78.868025,43.02978],"type":"Point"}
}