{
  "type": "Feature",
  "properties": {
    "addr:full":"642 Myrtle Ave Brooklyn NY 11205",
    "addr:housenumber":"642",
    "addr:postcode":"11205",
    "addr:street":"Myrtle Ave",
    "iso:country":"US",
    "sg:address":"642 Myrtle Ave",
    "sg:city":"Brooklyn",
    "sg:classifiers":[
        {
            "category":"Shopping",
            "type":"Retail Goods"
        }
    ],
    "sg:phone":"+1 718 783 6298",
    "sg:postcode":"11205",
    "sg:province":"NY",
    "sg:tags":[
        "pet",
        "food",
        "supply"
    ],
    "wof:name":"Myrtle Pets",
    "wof:placetype":"venue"
},
  "geometry": {"coordinates":[-73.958716,40.694181],"type":"Point"}
}