{
  "type": "Feature",
  "properties": {
    "iso:country":"US",
    "sg:address":"4304 Medical Center Dr",
    "sg:city":"Fayetteville",
    "sg:classifiers":[
        {
            "category":"Health Services",
            "subcategory":"Doctor",
            "type":"Services"
        }
    ],
    "sg:phone":"+1 315 329 7350",
    "sg:postcode":"13066",
    "sg:province":"NY",
    "sg:tags":[
        "physician",
        "surgeon",
        "medical"
    ],
    "wof:name":"University Otolaryngology Asso",
    "wof:placetype":"venue"
},
  "geometry": {"coordinates":[-76.019069,43.039465],"type":"Point"}
}