{
  "type": "Feature",
  "properties": {
    "addr:full":"270 Garson Ave Rochester NY 14609",
    "addr:housenumber":"270",
    "addr:postcode":"14609",
    "addr:street":"Garson Ave",
    "iso:country":"US",
    "sg:address":"270 Garson Ave",
    "sg:city":"Rochester",
    "sg:classifiers":[
        {
            "category":"Professional",
            "type":"Services"
        }
    ],
    "sg:phone":"+1 585 234 7660",
    "sg:postcode":"14609",
    "sg:province":"NY",
    "sg:tags":[
        "shows",
        "exposition",
        "fair",
        "trade"
    ],
    "wof:name":"Puerto Rican Festival, Inc",
    "wof:placetype":"venue"
},
  "geometry": {"coordinates":[-77.580179,43.163596],"type":"Point"}
}