{
  "type": "Feature",
  "properties": {
    "addr:full":"1 Hutchinson Ln Waterford NY 12188",
    "addr:housenumber":"1",
    "addr:postcode":"12188",
    "addr:street":"Hutchinson Ln",
    "iso:country":"US",
    "sg:address":"1 Hutchinson Ln",
    "sg:city":"Waterford",
    "sg:classifiers":[
        {
            "category":"Wholesale",
            "subcategory":"Hardware",
            "type":"Manufacturing & Wholesale Goods"
        }
    ],
    "sg:phone":"+1 518 235 2291",
    "sg:postcode":"12188",
    "sg:province":"NY",
    "sg:tags":[
        "refrigerating"
    ],
    "wof:name":"Ahr Industries Inc",
    "wof:placetype":"venue"
},
  "geometry": {"coordinates":[-73.68639,42.789437],"type":"Point"}
}