{
  "type": "Feature",
  "properties": {
    "iso:country":"US",
    "sg:address":"1 Pepsi Way",
    "sg:city":"Somers",
    "sg:classifiers":[
        {
            "category":"Banks & Credit Unions",
            "subcategory":"Bank",
            "type":"Services"
        }
    ],
    "sg:phone":"+1 914 767 6010",
    "sg:postcode":"10589",
    "sg:province":"NY",
    "sg:website":"www.pbgjobs.com",
    "wof:name":"Pepsico Employees Federal CU",
    "wof:placetype":"venue"
},
  "geometry": {"coordinates":[-73.702232,41.274392],"type":"Point"}
}