{
  "type": "Feature",
  "properties": {
    "addr:full":"458 9 Ave New York NY 10018",
    "addr:housenumber":"458",
    "addr:postcode":"10018",
    "addr:street":"9 Ave",
    "iso:country":"US",
    "sg:address":"458 9 Ave",
    "sg:city":"New York",
    "sg:classifiers":[
        {
            "category":"Food & Beverages",
            "subcategory":"Specialty",
            "type":"Retail Goods"
        }
    ],
    "sg:phone":"+1 212 563 7750",
    "sg:postcode":"10018",
    "sg:province":"NY",
    "sg:tags":[
        "gourmet",
        "shop"
    ],
    "wof:name":"Mitchel London Foods",
    "wof:placetype":"venue"
},
  "geometry": {"coordinates":[-73.99535299999999,40.754688],"type":"Point"}
}