{
  "type": "Feature",
  "properties": {
    "iso:country":"US",
    "sg:address":"81 Buffalo Ave",
    "sg:city":"Medford",
    "sg:classifiers":[
        {
            "category":"Wholesale",
            "subcategory":"Office Equipment",
            "type":"Manufacturing & Wholesale Goods"
        }
    ],
    "sg:phone":"+1 631 758 0279",
    "sg:postcode":"11763",
    "sg:province":"NY",
    "sg:tags":[
        "machine",
        "duplicating",
        "copying"
    ],
    "wof:name":"Knight Business Systems LTD",
    "wof:placetype":"venue"
},
  "geometry": {"coordinates":[-72.988544,40.796309],"type":"Point"}
}