{
  "type": "Feature",
  "properties": {
    "addr:full":"1802 Avenue M Brooklyn NY 11230",
    "addr:housenumber":"1802",
    "addr:postcode":"11230",
    "addr:street":"Avenue M",
    "iso:country":"US",
    "sg:address":"1802 Avenue M",
    "sg:city":"Brooklyn",
    "sg:classifiers":[
        {
            "category":"Building & Trades",
            "subcategory":"Locksmith",
            "type":"Services"
        }
    ],
    "sg:phone":"+1 347 554 2783",
    "sg:postcode":"11230",
    "sg:province":"NY",
    "sg:tags":[
        "key"
    ],
    "wof:name":"AAA Roadside Service of Brooklyn",
    "wof:placetype":"venue"
},
  "geometry": {"coordinates":[-73.957088,40.61819],"type":"Point"}
}