{
  "type": "Feature",
  "properties": {
    "addr:full":"183 Troy Schenectady Rd Watervliet NY 12189",
    "addr:housenumber":"183",
    "addr:postcode":"12189",
    "addr:street":"Troy Schenectady Rd",
    "iso:country":"US",
    "sg:address":"183 Troy Schenectady Rd",
    "sg:city":"Watervliet",
    "sg:classifiers":[
        {
            "category":"Restaurant",
            "type":"Food & Drink"
        }
    ],
    "sg:menulink":"http://www.allmenus.com/ny/colonie/59869-santinos/menu/",
    "sg:phone":"+1 518 220 9900",
    "sg:postcode":"12189",
    "sg:province":"NY",
    "sg:tags":[
        "italian"
    ],
    "wof:name":"Santino's",
    "wof:placetype":"venue"
},
  "geometry": {"coordinates":[-73.730791,42.738248],"type":"Point"}
}