{
  "type": "Feature",
  "properties": {
    "addr:full":"4813 New Utrecht Avenue Brooklyn NY 11219",
    "addr:housenumber":"4813",
    "addr:postcode":"11219",
    "addr:street":"New Utrecht Avenue",
    "iso:country":"US",
    "sg:address":"4813 New Utrecht Avenue",
    "sg:city":"Brooklyn",
    "sg:classifiers":[
        {
            "category":"Restaurant",
            "type":"Food & Drink"
        }
    ],
    "sg:phone":"+1 718 972 3434",
    "sg:postcode":"11219",
    "sg:province":"NY",
    "wof:name":"Asia Restaurant",
    "wof:placetype":"venue"
},
  "geometry": {"coordinates":[-73.994541,40.637018],"type":"Point"}
}