{
  "type": "Feature",
  "properties": {
    "addr:full":"2167 Poe Ave East Meadow NY 11554",
    "addr:housenumber":"2167",
    "addr:postcode":"11554",
    "addr:street":"Poe Ave",
    "iso:country":"US",
    "sg:address":"2167 Poe Ave",
    "sg:city":"East Meadow",
    "sg:classifiers":[
        {
            "category":"Building & Trades",
            "subcategory":"Landscaping Services",
            "type":"Services"
        }
    ],
    "sg:phone":"+1 516 483 4702",
    "sg:postcode":"11554",
    "sg:province":"NY",
    "sg:tags":[
        "landscape"
    ],
    "wof:name":"Braga Landscaping Corp",
    "wof:placetype":"venue"
},
  "geometry": {"coordinates":[-73.55037400000001,40.705177],"type":"Point"}
}