{
  "type": "Feature",
  "properties": {
    "addr:full":"1800 Merrick Rd North Merrick NY 11566",
    "addr:housenumber":"1800",
    "addr:postcode":"11566",
    "addr:street":"Merrick Rd",
    "iso:country":"US",
    "sg:address":"1800 Merrick Rd",
    "sg:city":"North Merrick",
    "sg:classifiers":[
        {
            "category":"Food & Beverages",
            "subcategory":"Groceries & Convenience Stores",
            "type":"Retail Goods"
        }
    ],
    "sg:phone":"+1 516 378 6986",
    "sg:postcode":"11566",
    "sg:province":"NY",
    "sg:website":"www.7-eleven.com",
    "wof:name":"7-Eleven",
    "wof:placetype":"venue"
},
  "geometry": {"coordinates":[-73.556326,40.653463],"type":"Point"}
}