{
  "type": "Feature",
  "properties": {
    "iso:country":"US",
    "sg:address":"408 Kneeland Ave",
    "sg:city":"Yonkers",
    "sg:classifiers":[
        {
            "category":"Autos & Motor Vehicles",
            "subcategory":"Auto Supplies",
            "type":"Retail Goods"
        },
        {
            "category":"Wholesale",
            "subcategory":"Auto Parts",
            "type":"Manufacturing & Wholesale Goods"
        }
    ],
    "sg:phone":"+1 914 476 7853",
    "sg:postcode":"10704",
    "sg:province":"NY",
    "sg:tags":[
        "equipment",
        "truck",
        "accessory"
    ],
    "wof:name":"Westchester Foreign Truck Part",
    "wof:placetype":"venue"
},
  "geometry": {"coordinates":[-73.87263900000001,40.92252],"type":"Point"}
}