{
  "type": "Feature",
  "properties": {
    "iso:country":"US",
    "sg:address":"854 Beckman Dr",
    "sg:city":"Bellmore",
    "sg:classifiers":[
        {
            "category":"Professional",
            "subcategory":"Accounting & Tax Preparation",
            "type":"Services"
        }
    ],
    "sg:phone":"+1   ",
    "sg:postcode":"11710",
    "sg:province":"NY",
    "sg:tags":[
        "auditing",
        "bookkeeping"
    ],
    "wof:name":"Ralph V Esposito CPA",
    "wof:placetype":"venue"
},
  "geometry": {"coordinates":[-73.53495700000001,40.701202],"type":"Point"}
}