{
  "type": "Feature",
  "properties": {
    "addr:full":"7312 18th Ave Brooklyn NY 11204",
    "addr:housenumber":"7312",
    "addr:postcode":"11204",
    "addr:street":"18Th Ave",
    "iso:country":"US",
    "sg:address":"7312 18th Ave",
    "sg:city":"Brooklyn",
    "sg:classifiers":[
        {
            "category":"Retail",
            "subcategory":"Photofinishing",
            "type":"Services"
        }
    ],
    "sg:phone":"+1 718 232 6202",
    "sg:postcode":"11204",
    "sg:province":"NY",
    "sg:tags":[
        "photo",
        "finishing"
    ],
    "wof:name":"Jay Photo Lab",
    "wof:placetype":"venue"
},
  "geometry": {"coordinates":[-73.99537599999999,40.614111],"type":"Point"}
}