{
  "type": "Feature",
  "properties": {
    "iso:country":"US",
    "sg:address":"6832 3rd Ave",
    "sg:city":"Brooklyn",
    "sg:classifiers":[
        {
            "category":"Retail",
            "subcategory":"Laundry & Dry Cleaning",
            "type":"Services"
        }
    ],
    "sg:phone":"+1 718 921 2600",
    "sg:postcode":"11220",
    "sg:province":"NY",
    "sg:tags":[
        "garment",
        "agent"
    ],
    "wof:name":"Oui Oui French Cleaners",
    "wof:placetype":"venue"
},
  "geometry": {"coordinates":[-74.025803,40.636299],"type":"Point"}
}