{
  "type": "Feature",
  "properties": {
    "iso:country":"US",
    "sg:address":"95 W Broadway",
    "sg:city":"New York",
    "sg:classifiers":[
        {
            "category":"Banks & Credit Unions",
            "subcategory":"Bank",
            "type":"Services"
        }
    ],
    "sg:phone":"+1 212 608 0390",
    "sg:postcode":"10007",
    "sg:province":"NY",
    "sg:tags":[
        "cashing",
        "check"
    ],
    "wof:name":"Fast Cash USA",
    "wof:placetype":"venue"
},
  "geometry": {"coordinates":[-74.009681,40.714946],"type":"Point"}
}