{
  "type": "Feature",
  "properties": {
    "iso:country":"US",
    "sg:address":"100 Crossways Park Dr W",
    "sg:city":"Woodbury",
    "sg:classifiers":[
        {
            "category":"Professional",
            "subcategory":"Accounting & Tax Preparation",
            "type":"Services"
        }
    ],
    "sg:phone":"+1 516 364 7373",
    "sg:postcode":"11797",
    "sg:province":"NY",
    "sg:tags":[
        "accountant"
    ],
    "wof:name":"Landau & Co",
    "wof:placetype":"venue"
},
  "geometry": {"coordinates":[-73.488541,40.809397],"type":"Point"}
}