{
  "type": "Feature",
  "properties": {
    "iso:country":"US",
    "sg:address":"86 Middle Neck Rd",
    "sg:city":"Great Neck",
    "sg:classifiers":[
        {
            "category":"Wholesale",
            "subcategory":"Machinery & Supplies",
            "type":"Manufacturing & Wholesale Goods"
        }
    ],
    "sg:phone":"+1 516 487 1885",
    "sg:postcode":"11021",
    "sg:province":"NY",
    "sg:tags":[
        "salon",
        "beauty"
    ],
    "wof:name":"Dan's State Of The Art Beauty",
    "wof:placetype":"venue"
},
  "geometry": {"coordinates":[-73.729882,40.789135],"type":"Point"}
}