{
  "type": "Feature",
  "properties": {
    "addr:full":"3571 Long Beach Rd Oceanside NY 11572",
    "addr:housenumber":"3571",
    "addr:postcode":"11572",
    "addr:street":"Long Beach Rd",
    "iso:country":"US",
    "sg:address":"3571 Long Beach Rd",
    "sg:city":"Oceanside",
    "sg:classifiers":[
        {
            "category":"Shopping",
            "subcategory":"Shoes",
            "type":"Retail Goods"
        }
    ],
    "sg:phone":"+1 516 594 3461",
    "sg:postcode":"11572",
    "sg:province":"NY",
    "sg:tags":[
        "store"
    ],
    "sg:website":"www.easyspirit.com",
    "wof:name":"Easy Spirit Outlet",
    "wof:placetype":"venue"
},
  "geometry": {"coordinates":[-73.63943,40.624304],"type":"Point"}
}