{
  "type": "Feature",
  "properties": {
    "addr:full":"367 Avenue X Brooklyn NY 11223",
    "addr:housenumber":"367",
    "addr:postcode":"11223",
    "addr:street":"Avenue X",
    "iso:country":"US",
    "sg:address":"367 Avenue X",
    "sg:city":"Brooklyn",
    "sg:classifiers":[
        {
            "category":"Health Services",
            "subcategory":"Dentist",
            "type":"Services"
        }
    ],
    "sg:phone":"+1 718 942 4970",
    "sg:postcode":"11223",
    "sg:province":"NY",
    "wof:name":"American Smile Of Nyc",
    "wof:placetype":"venue"
},
  "geometry": {"coordinates":[-73.969311,40.590786],"type":"Point"}
}