{
  "type": "Feature",
  "properties": {
    "iso:country":"US",
    "sg:address":"1 Lakeview Dr",
    "sg:city":"Clifton Park",
    "sg:classifiers":[
        {
            "category":"Real Estate",
            "subcategory":"Real Estate Operator",
            "type":"Services"
        }
    ],
    "sg:phone":"+1 518 371 5307",
    "sg:postcode":"12065",
    "sg:province":"NY",
    "sg:tags":[
        "apartment"
    ],
    "wof:name":"Solomon Apartment Management",
    "wof:placetype":"venue"
},
  "geometry": {"coordinates":[-73.765541,42.852647],"type":"Point"}
}