{
  "type": "Feature",
  "properties": {
    "addr:full":"55 Hunter Ln Elmsford NY 10523",
    "addr:housenumber":"55",
    "addr:postcode":"10523",
    "addr:street":"Hunter Ln",
    "iso:country":"US",
    "sg:address":"55 Hunter Ln",
    "sg:city":"Elmsford",
    "sg:classifiers":[
        {
            "category":"Freight",
            "type":"Transportation"
        }
    ],
    "sg:phone":"+1   ",
    "sg:postcode":"10523",
    "sg:province":"NY",
    "sg:tags":[
        "forwarding",
        "household",
        "good",
        "storage",
        "foreign"
    ],
    "wof:name":"Interconex Inc",
    "wof:placetype":"venue"
},
  "geometry": {"coordinates":[-73.81343099999999,41.069601],"type":"Point"}
}