{
  "type": "Feature",
  "properties": {
    "addr:full":"684 Peekskill Hollow Rd Putnam Valley NY 10579",
    "addr:housenumber":"684",
    "addr:postcode":"10579",
    "addr:street":"Peekskill Hollow Rd",
    "iso:country":"US",
    "sg:address":"684 Peekskill Hollow Rd",
    "sg:city":"Putnam Valley",
    "sg:classifiers":[
        {
            "category":"Social Services",
            "type":"Services"
        }
    ],
    "sg:phone":"+1 845 526 0808",
    "sg:postcode":"10579",
    "sg:province":"NY",
    "sg:tags":[
        "community"
    ],
    "wof:name":"YMCA",
    "wof:placetype":"venue"
},
  "geometry": {"coordinates":[-73.808239,41.392459],"type":"Point"}
}