{
  "type": "Feature",
  "properties": {
    "iso:country":"US",
    "sg:address":"171 47th St",
    "sg:city":"Brooklyn",
    "sg:classifiers":[
        {
            "category":"Wholesale",
            "subcategory":"Photographic Equipment",
            "type":"Manufacturing & Wholesale Goods"
        }
    ],
    "sg:phone":"+1 718 832 3456",
    "sg:postcode":"11232",
    "sg:province":"NY",
    "sg:tags":[
        "supply"
    ],
    "wof:name":"Digital Distributors Inc",
    "wof:placetype":"venue"
},
  "geometry": {"coordinates":[-74.01650100000001,40.651924],"type":"Point"}
}