{
  "type": "Feature",
  "properties": {
    "iso:country":"US",
    "sg:address":"1039 Rte 112",
    "sg:city":"Port Jefferson Station",
    "sg:classifiers":[
        {
            "category":"Wholesale",
            "subcategory":"Drugs",
            "type":"Manufacturing & Wholesale Goods"
        },
        {
            "category":"Personal",
            "subcategory":"Beauty Salon",
            "type":"Services"
        }
    ],
    "sg:phone":"+1 631 476 6658",
    "sg:postcode":"11776",
    "sg:province":"NY",
    "sg:tags":[
        "shop",
        "cosmetic"
    ],
    "wof:name":"Salon 3",
    "wof:placetype":"venue"
},
  "geometry": {"coordinates":[-73.04603,40.92373],"type":"Point"}
}