{
  "type": "Feature",
  "properties": {
    "addr:full":"686 Courtland Ave Bronx NY 10451",
    "addr:housenumber":"686",
    "addr:postcode":"10451",
    "addr:street":"Courtland Ave",
    "iso:country":"US",
    "sg:address":"686 Courtland Ave",
    "sg:city":"Bronx",
    "sg:classifiers":[
        {
            "category":"Building & Trades",
            "subcategory":"Construction",
            "type":"Services"
        }
    ],
    "sg:phone":"+1 718 665 4843",
    "sg:postcode":"10451",
    "sg:province":"NY",
    "sg:tags":[
        "concrete",
        "contractor"
    ],
    "wof:name":"Maurice Sal Son Inc",
    "wof:placetype":"venue"
},
  "geometry": {"coordinates":[-73.91827499999999,40.819378],"type":"Point"}
}