{
  "type": "Feature",
  "properties": {
    "addr:full":"3050 White Plains Rd Bronx NY 10467",
    "addr:housenumber":"3050",
    "addr:postcode":"10467",
    "addr:street":"White Plains Rd",
    "iso:country":"US",
    "sg:address":"3050 White Plains Rd",
    "sg:city":"Bronx",
    "sg:classifiers":[
        {
            "category":"Professional",
            "type":"Services"
        }
    ],
    "sg:phone":"+1 718 655 5353",
    "sg:postcode":"10467",
    "sg:province":"NY",
    "sg:tags":[
        "establishment"
    ],
    "wof:name":"Mdc Center",
    "wof:placetype":"venue"
},
  "geometry": {"coordinates":[-73.86712300000001,40.870303],"type":"Point"}
}