{
  "type": "Feature",
  "properties": {
    "addr:full":"10 Willoughby St Brooklyn NY 11201",
    "addr:housenumber":"10",
    "addr:postcode":"11201",
    "addr:street":"Willoughby St",
    "iso:country":"US",
    "sg:address":"10 Willoughby St",
    "sg:city":"Brooklyn",
    "sg:classifiers":[
        {
            "category":"Shopping",
            "subcategory":"Shoes",
            "type":"Retail Goods"
        }
    ],
    "sg:phone":"+1 718 858 5178",
    "sg:postcode":"11201",
    "sg:province":"NY",
    "wof:name":"Shoe Master",
    "wof:placetype":"venue"
},
  "geometry": {"coordinates":[-73.988409,40.692213],"type":"Point"}
}