{
  "type": "Feature",
  "properties": {
    "addr:full":"236 US Hwy 9w Haverstraw NY 10927",
    "addr:housenumber":"236",
    "addr:postcode":"10927",
    "addr:street":"Us Hwy 9W",
    "iso:country":"US",
    "sg:address":"236 US Hwy 9w",
    "sg:city":"Haverstraw",
    "sg:classifiers":[
        {
            "category":"Real Estate",
            "subcategory":"Real Estate Agent",
            "type":"Services"
        }
    ],
    "sg:phone":"+1 845 429 5598",
    "sg:postcode":"10927",
    "sg:province":"NY",
    "wof:name":"Paul Mastromarino Real Estate",
    "wof:placetype":"venue"
},
  "geometry": {"coordinates":[-73.982518,41.199538],"type":"Point"}
}