{
  "type": "Feature",
  "properties": {
    "addr:full":"419 E 57th St New York NY 10022",
    "addr:housenumber":"419",
    "addr:postcode":"10022",
    "addr:street":"E 57Th St",
    "iso:country":"US",
    "sg:address":"419 E 57th St",
    "sg:city":"New York",
    "sg:classifiers":[
        {
            "category":"Shopping",
            "subcategory":"Used Merchandise",
            "type":"Retail Goods"
        }
    ],
    "sg:phone":"+1   ",
    "sg:postcode":"10022",
    "sg:province":"NY",
    "wof:name":"Ronald Stiegler",
    "wof:placetype":"venue"
},
  "geometry": {"coordinates":[-73.960947,40.757602],"type":"Point"}
}