{
  "type": "Feature",
  "properties": {
    "iso:country":"US",
    "sg:address":"1609 Crouse St",
    "sg:city":"Utica",
    "sg:classifiers":[
        {
            "category":"Building & Trades",
            "subcategory":"Landscaping Services",
            "type":"Services"
        }
    ],
    "sg:phone":"+1 315 732 6336",
    "sg:postcode":"13501",
    "sg:province":"NY",
    "wof:name":"Cross Country Tree Service",
    "wof:placetype":"venue"
},
  "geometry": {"coordinates":[-75.20666799999999,43.084077],"type":"Point"}
}