{
  "type": "Feature",
  "properties": {
    "addr:full":"535 Broad Hollow Rd Melville NY 11747",
    "addr:housenumber":"535",
    "addr:postcode":"11747",
    "addr:street":"Broad Hollow Rd",
    "iso:country":"US",
    "sg:address":"535 Broad Hollow Rd",
    "sg:city":"Melville",
    "sg:classifiers":[
        {
            "category":"Banks & Credit Unions",
            "subcategory":"Financial Services",
            "type":"Services"
        }
    ],
    "sg:phone":"+1 631 777 1977",
    "sg:postcode":"11747",
    "sg:province":"NY",
    "sg:tags":[
        "company",
        "holding"
    ],
    "wof:name":"Fortress Capital",
    "wof:placetype":"venue"
},
  "geometry": {"coordinates":[-73.42344,40.764941],"type":"Point"}
}