{
  "type": "Feature",
  "properties": {
    "iso:country":"US",
    "sg:address":"853 Dutchess Tpke",
    "sg:city":"Poughkeepsie",
    "sg:classifiers":[
        {
            "category":"Shopping",
            "subcategory":"Florist",
            "type":"Retail Goods"
        }
    ],
    "sg:phone":"+1 845 471 1112",
    "sg:postcode":"12603",
    "sg:province":"NY",
    "wof:name":"Thornton's Hillside Gardens",
    "wof:placetype":"venue"
},
  "geometry": {"coordinates":[-73.86980200000001,41.704619],"type":"Point"}
}