{
  "type": "Feature",
  "properties": {
    "addr:full":"2912 Brighton 12th St Brooklyn NY 11235",
    "addr:housenumber":"2912",
    "addr:postcode":"11235",
    "addr:street":"Brighton 12Th St",
    "iso:country":"US",
    "sg:address":"2912 Brighton 12th St",
    "sg:city":"Brooklyn",
    "sg:classifiers":[
        {
            "category":"Health Services",
            "subcategory":"Doctor",
            "type":"Services"
        }
    ],
    "sg:phone":"+1 718 332 0470",
    "sg:postcode":"11235",
    "sg:province":"NY",
    "wof:name":"Atkinson W MD",
    "wof:placetype":"venue"
},
  "geometry": {"coordinates":[-73.95610000000001,40.5807],"type":"Point"}
}