{
  "type": "Feature",
  "properties": {
    "iso:country":"US",
    "sg:address":"65 Hunt Dr",
    "sg:city":"Jericho",
    "sg:classifiers":[
        {
            "category":"Professional",
            "subcategory":"Lawyer & Legal Services",
            "type":"Services"
        }
    ],
    "sg:phone":"+1 516 931 6400",
    "sg:postcode":"11753",
    "sg:province":"NY",
    "wof:name":"Taras Bert Attorney",
    "wof:placetype":"venue"
},
  "geometry": {"coordinates":[-73.558601,40.784599],"type":"Point"}
}