{
  "type": "Feature",
  "properties": {
    "addr:full":"375 Simonson Ave Staten Island NY 10303",
    "addr:housenumber":"375",
    "addr:postcode":"10303",
    "addr:street":"Simonson Ave",
    "iso:country":"US",
    "sg:address":"375 Simonson Ave",
    "sg:city":"Staten Island",
    "sg:classifiers":[
        {
            "category":"Building & Trades",
            "subcategory":"Construction",
            "type":"Services"
        }
    ],
    "sg:phone":"+1 718 447 3363",
    "sg:postcode":"10303",
    "sg:province":"NY",
    "sg:tags":[
        "contractor"
    ],
    "wof:name":"Dura Tint Inc",
    "wof:placetype":"venue"
},
  "geometry": {"coordinates":[-74.153035,40.625809],"type":"Point"}
}