{
  "type": "Feature",
  "properties": {
    "addr:full":"8614 3rd Ave Brooklyn NY 11209",
    "addr:housenumber":"8614",
    "addr:postcode":"11209",
    "addr:street":"3Rd Ave",
    "iso:country":"US",
    "sg:address":"8614 3rd Ave",
    "sg:city":"Brooklyn",
    "sg:classifiers":[
        {
            "category":"Building & Trades",
            "subcategory":"Plumbing",
            "type":"Services"
        }
    ],
    "sg:phone":"+1 718 745 2975",
    "sg:postcode":"11209",
    "sg:province":"NY",
    "wof:name":"Forte Express Plumbing & Heating",
    "wof:placetype":"venue"
},
  "geometry": {"coordinates":[-74.126901,40.623408],"type":"Point"}
}