{
  "type": "Feature",
  "properties": {
    "iso:country":"US",
    "sg:address":"246 Avenue U",
    "sg:city":"Brooklyn",
    "sg:classifiers":[
        {
            "category":"Shopping",
            "subcategory":"Mobile Phones",
            "type":"Retail Goods"
        }
    ],
    "sg:phone":"+1 347 371 9319",
    "sg:postcode":"11223",
    "sg:province":"NY",
    "wof:name":"First Choice Wireless",
    "wof:placetype":"venue"
},
  "geometry": {"coordinates":[-73.97500599999999,40.596654],"type":"Point"}
}