{
  "type": "Feature",
  "properties": {
    "addr:full":"2934 Townline Rd Wilson NY 14111",
    "addr:housenumber":"2934",
    "addr:postcode":"14111",
    "addr:street":"Townline Rd",
    "iso:country":"US",
    "sg:address":"2934 Townline Rd",
    "sg:city":"Wilson",
    "sg:classifiers":[
        {
            "category":"Organizations",
            "subcategory":"Community Association",
            "type":"Services"
        }
    ],
    "sg:phone":"+1 716 751 6551",
    "sg:postcode":"14111",
    "sg:province":"NY",
    "sg:tags":[
        "club"
    ],
    "wof:name":"Wilson Conservation Club Inc",
    "wof:placetype":"venue"
},
  "geometry": {"coordinates":[-78.876957,42.608904],"type":"Point"}
}