{
  "type": "Feature",
  "properties": {
    "addr:full":"245 W 72nd St New York NY 10023",
    "addr:housenumber":"245",
    "addr:postcode":"10023",
    "addr:street":"W 72Nd St",
    "iso:country":"US",
    "sg:address":"245 W 72nd St",
    "sg:city":"New York",
    "sg:classifiers":[
        {
            "category":"Professional",
            "subcategory":"Art Services",
            "type":"Services"
        }
    ],
    "sg:phone":"+1 212 873 5588",
    "sg:postcode":"10023",
    "sg:province":"NY",
    "sg:tags":[
        "photographer"
    ],
    "wof:name":"Fred Marcus Photography & Videography",
    "wof:placetype":"venue"
},
  "geometry": {"coordinates":[-73.98316699999999,40.779573],"type":"Point"}
}