{
  "type": "Feature",
  "properties": {
    "iso:country":"US",
    "sg:address":"116 Pinehurst Ave, Ste J41",
    "sg:city":"New York",
    "sg:classifiers":[
        {
            "category":"Communications",
            "subcategory":"Newspaper",
            "type":"Services"
        }
    ],
    "sg:postcode":"10033",
    "sg:province":"NY",
    "sg:tags":[
        "print",
        "medium"
    ],
    "sg:website":"newyork.allaboutjazz.com",
    "wof:name":"All About Jazz",
    "wof:placetype":"venue"
},
  "geometry": {"coordinates":[-73.93870099999999,40.853082],"type":"Point"}
}