{
  "type": "Feature",
  "properties": {
    "addr:full":"54 Crossing Blvd Clifton Park NY 12065",
    "addr:housenumber":"54",
    "addr:postcode":"12065",
    "addr:street":"Crossing Blvd",
    "iso:country":"US",
    "sg:address":"54 Crossing Blvd",
    "sg:city":"Clifton Park",
    "sg:classifiers":[
        {
            "category":"Shopping",
            "type":"Retail Goods"
        }
    ],
    "sg:phone":"+1 518 371 3200",
    "sg:postcode":"12065",
    "sg:province":"NY",
    "sg:tags":[
        "merchandise",
        "cellular",
        "telephone"
    ],
    "wof:name":"Simply Wireless",
    "wof:placetype":"venue"
},
  "geometry": {"coordinates":[-73.77020899999999,42.859928],"type":"Point"}
}