{
  "type": "Feature",
  "properties": {
    "iso:country":"US",
    "sg:address":"690 Mace Ave",
    "sg:city":"Bronx",
    "sg:classifiers":[
        {
            "category":"Wholesale",
            "subcategory":"Machinery & Supplies",
            "type":"Manufacturing & Wholesale Goods"
        }
    ],
    "sg:phone":"+1 718 654 6633",
    "sg:postcode":"10467",
    "sg:province":"NY",
    "sg:tags":[
        "bearing"
    ],
    "wof:name":"IBC Bearing Co Inc",
    "wof:placetype":"venue"
},
  "geometry": {"coordinates":[-73.867912,40.863149],"type":"Point"}
}