{
  "type": "Feature",
  "properties": {
    "iso:country":"US",
    "sg:address":"42 2 Ave",
    "sg:city":"Bay Shore",
    "sg:classifiers":[
        {
            "category":"Retail",
            "subcategory":"Funeral Services",
            "type":"Services"
        }
    ],
    "sg:phone":"+1   ",
    "sg:postcode":"11706",
    "sg:province":"NY",
    "wof:name":"Bay Shore Funeral Home",
    "wof:placetype":"venue"
},
  "geometry": {"coordinates":[-73.24492499999999,40.723704],"type":"Point"}
}