{
  "type": "Feature",
  "properties": {
    "iso:country":"US",
    "sg:address":"5 Shaker Ct",
    "sg:city":"New Windsor",
    "sg:classifiers":[
        {
            "category":"Building & Trades",
            "subcategory":"Construction",
            "type":"Services"
        }
    ],
    "sg:phone":"+1 845 565 1434",
    "sg:postcode":"12553",
    "sg:province":"NY",
    "sg:tags":[
        "carpentry",
        "contractor"
    ],
    "wof:name":"Vince Arcaro Carpentry Inc",
    "wof:placetype":"venue"
},
  "geometry": {"coordinates":[-74.040671,41.459431],"type":"Point"}
}