{
  "type": "Feature",
  "properties": {
    "addr:full":"4343 161st St Flushing NY 11358",
    "addr:housenumber":"4343",
    "addr:postcode":"11358",
    "addr:street":"161St St",
    "iso:country":"US",
    "sg:address":"4343 161st St",
    "sg:city":"Flushing",
    "sg:classifiers":[
        {
            "category":"Professional",
            "subcategory":"Employment Agencies",
            "type":"Services"
        }
    ],
    "sg:phone":"+1 631 952 7210",
    "sg:postcode":"11358",
    "sg:province":"NY",
    "wof:name":"Magill Associates",
    "wof:placetype":"venue"
},
  "geometry": {"coordinates":[-73.805018,40.758303],"type":"Point"}
}