{
  "type": "Feature",
  "properties": {
    "addr:full":"4119 Co Rd 10 Cameron NY 14819",
    "addr:housenumber":"4119;10",
    "addr:postcode":"14819",
    "addr:street":"Co Rd",
    "iso:country":"US",
    "sg:address":"4119 Co Rd 10",
    "sg:city":"Cameron",
    "sg:classifiers":[
        {
            "category":"Government",
            "subcategory":"Post Office",
            "type":"Public Place"
        }
    ],
    "sg:phone":"+1   ",
    "sg:postcode":"14819",
    "sg:province":"NY",
    "sg:tags":[
        "postal",
        "us"
    ],
    "wof:name":"Cameron Post Office",
    "wof:placetype":"venue"
},
  "geometry": {"coordinates":[-77.398546,42.219003],"type":"Point"}
}