{
  "type": "Feature",
  "properties": {
    "iso:country":"US",
    "sg:address":"36 Holly Dr",
    "sg:city":"New Rochelle",
    "sg:classifiers":[
        {
            "category":"Building & Trades",
            "subcategory":"Construction",
            "type":"Services"
        }
    ],
    "sg:phone":"+1 914 636 1698",
    "sg:postcode":"10801",
    "sg:province":"NY",
    "sg:tags":[
        "hanging",
        "painter",
        "contractor"
    ],
    "wof:name":"De Carvalho Painting",
    "wof:placetype":"venue"
},
  "geometry": {"coordinates":[-73.79884800000001,40.919651],"type":"Point"}
}