{
  "type": "Feature",
  "properties": {
    "addr:full":"133 Park Ave Hicksville NY 11801",
    "addr:housenumber":"133",
    "addr:postcode":"11801",
    "addr:street":"Park Ave",
    "iso:country":"US",
    "sg:address":"133 Park Ave",
    "sg:city":"Hicksville",
    "sg:classifiers":[
        {
            "category":"Wholesale",
            "subcategory":"Auto Parts",
            "type":"Manufacturing & Wholesale Goods"
        }
    ],
    "sg:phone":"+1 516 868 0060",
    "sg:postcode":"11801",
    "sg:province":"NY",
    "sg:tags":[
        "automobile",
        "repair"
    ],
    "wof:name":"S & M Equipment Co Inc",
    "wof:placetype":"venue"
},
  "geometry": {"coordinates":[-73.5177,40.768902],"type":"Point"}
}