{
  "type": "Feature",
  "properties": {
    "iso:country":"US",
    "sg:address":"111 Rockland Ave",
    "sg:city":"Larchmont",
    "sg:classifiers":[
        {
            "category":"Insurance",
            "subcategory":"Insurance Agent",
            "type":"Services"
        }
    ],
    "sg:phone":"+1 914 833 1335",
    "sg:postcode":"10538",
    "sg:province":"NY",
    "wof:name":"Mudge Tapley",
    "wof:placetype":"venue"
},
  "geometry": {"coordinates":[-73.753844,40.948378],"type":"Point"}
}