{
  "type": "Feature",
  "properties": {
    "iso:country":"US",
    "sg:address":"1245 Erie Blvd W",
    "sg:city":"Rome",
    "sg:classifiers":[
        {
            "category":"Professional",
            "type":"Services"
        }
    ],
    "sg:phone":"+1 315 336 0852",
    "sg:postcode":"13440",
    "sg:province":"NY",
    "sg:tags":[
        "establishment"
    ],
    "wof:name":"Barrett Paving Materials",
    "wof:placetype":"venue"
},
  "geometry": {"coordinates":[-75.48509,43.223928],"type":"Point"}
}