{
  "type": "Feature",
  "properties": {
    "addr:full":"10 Avon Ave Farmingville NY 11738",
    "addr:housenumber":"10",
    "addr:postcode":"11738",
    "addr:street":"Avon Ave",
    "iso:country":"US",
    "sg:address":"10 Avon Ave",
    "sg:city":"Farmingville",
    "sg:classifiers":[
        {
            "category":"Professional",
            "type":"Services"
        }
    ],
    "sg:phone":"+1   ",
    "sg:postcode":"11738",
    "sg:province":"NY",
    "wof:name":"Zara Instruments Inc",
    "wof:placetype":"venue"
},
  "geometry": {"coordinates":[-73.06598700000001,40.830168],"type":"Point"}
}