{
  "type": "Feature",
  "properties": {
    "iso:country":"US",
    "sg:address":"953 49th St",
    "sg:city":"Brooklyn",
    "sg:classifiers":[
        {
            "category":"Personal",
            "type":"Services"
        }
    ],
    "sg:phone":"+1   ",
    "sg:postcode":"11219",
    "sg:province":"NY",
    "wof:name":"Mitchell Roslin",
    "wof:placetype":"venue"
},
  "geometry": {"coordinates":[-73.999562,40.63978],"type":"Point"}
}