{
  "type": "Feature",
  "properties": {
    "iso:country":"US",
    "sg:address":"74 West Ave",
    "sg:city":"Saratoga Springs",
    "sg:classifiers":[
        {
            "category":"Restaurant",
            "type":"Food & Drink"
        }
    ],
    "sg:phone":"+1 518 584 4532",
    "sg:postcode":"12866",
    "sg:province":"NY",
    "sg:tags":[
        "eating"
    ],
    "wof:name":"Shirley's Restaurant",
    "wof:placetype":"venue"
},
  "geometry": {"coordinates":[-73.804047,43.080905],"type":"Point"}
}