{
  "type": "Feature",
  "properties": {
    "iso:country":"US",
    "sg:address":"122 Forsyth St",
    "sg:city":"New York",
    "sg:classifiers":[
        {
            "category":"Building & Trades",
            "subcategory":"Plumbing",
            "type":"Services"
        }
    ],
    "sg:phone":"+1 212 966 9738",
    "sg:postcode":"10002",
    "sg:province":"NY",
    "sg:tags":[
        "special",
        "contractor"
    ],
    "wof:name":"Flytiger Plumbing & Heating",
    "wof:placetype":"venue"
},
  "geometry": {"coordinates":[-73.99225199999999,40.719307],"type":"Point"}
}