{
  "type": "Feature",
  "properties": {
    "addr:full":"404 Park Ave S New York NY 10016",
    "addr:housenumber":"404",
    "addr:postcode":"10016",
    "addr:street":"Park Ave S",
    "iso:country":"US",
    "sg:address":"404 Park Ave S",
    "sg:city":"New York",
    "sg:classifiers":[
        {
            "category":"Professional",
            "subcategory":"Lawyer & Legal Services",
            "type":"Services"
        }
    ],
    "sg:phone":"+1 212 213 3549",
    "sg:postcode":"10016",
    "sg:province":"NY",
    "wof:name":"Russell Richard L",
    "wof:placetype":"venue"
},
  "geometry": {"coordinates":[-73.984295,40.743431],"type":"Point"}
}