{
  "type": "Feature",
  "properties": {
    "iso:country":"US",
    "sg:address":"15 Elser Ter",
    "sg:city":"Rochester",
    "sg:classifiers":[
        {
            "category":"Retail",
            "subcategory":"Portrait Studio",
            "type":"Services"
        }
    ],
    "sg:phone":"+1 585 235 2860",
    "sg:postcode":"14611",
    "sg:province":"NY",
    "sg:tags":[
        "photographer"
    ],
    "wof:name":"Michael Zappia Photography",
    "wof:placetype":"venue"
},
  "geometry": {"coordinates":[-77.647452,43.154504],"type":"Point"}
}