{
  "type": "Feature",
  "properties": {
    "addr:full":"25 Indian Head Rd Kings Park NY 11754",
    "addr:housenumber":"25",
    "addr:postcode":"11754",
    "addr:street":"Indian Head Rd",
    "iso:country":"US",
    "sg:address":"25 Indian Head Rd",
    "sg:city":"Kings Park",
    "sg:classifiers":[
        {
            "category":"Manufacturing",
            "subcategory":"Toys & Sporting Goods",
            "type":"Manufacturing & Wholesale Goods"
        }
    ],
    "sg:phone":"+1   ",
    "sg:postcode":"11754",
    "sg:province":"NY",
    "sg:tags":[
        "mfg"
    ],
    "wof:name":"Iklectric Kollectibles",
    "wof:placetype":"venue"
},
  "geometry": {"coordinates":[-73.253562,40.883136],"type":"Point"}
}