{
  "type": "Feature",
  "properties": {
    "addr:full":"520 Broad Hollow Rd Melville NY 11747",
    "addr:housenumber":"520",
    "addr:postcode":"11747",
    "addr:street":"Broad Hollow Rd",
    "iso:country":"US",
    "sg:address":"520 Broad Hollow Rd",
    "sg:city":"Melville",
    "sg:classifiers":[
        {
            "category":"Banks & Credit Unions",
            "subcategory":"Bank",
            "type":"Services"
        }
    ],
    "sg:phone":"+1 516 937 7100",
    "sg:postcode":"11747",
    "sg:province":"NY",
    "sg:tags":[
        "loan",
        "real estate"
    ],
    "sg:website":"www.great-oak.com",
    "wof:name":"Great Oak Abstract Corp",
    "wof:placetype":"venue"
},
  "geometry": {"coordinates":[-73.423395,40.763378],"type":"Point"}
}