{
  "type": "Feature",
  "properties": {
    "iso:country":"US",
    "sg:address":"23 Candee Ave",
    "sg:city":"Sayville",
    "sg:classifiers":[
        {
            "category":"Manufacturing",
            "subcategory":"Printing",
            "type":"Manufacturing & Wholesale Goods"
        }
    ],
    "sg:phone":"+1 631 567 3011",
    "sg:postcode":"11782",
    "sg:province":"NY",
    "sg:tags":[
        "printer"
    ],
    "wof:name":"Printsmith",
    "wof:placetype":"venue"
},
  "geometry": {"coordinates":[-73.08141500000001,40.731352],"type":"Point"}
}