{
  "type": "Feature",
  "properties": {
    "iso:country":"US",
    "sg:address":"1172 E 92nd St",
    "sg:city":"Brooklyn",
    "sg:classifiers":[
        {
            "category":"Education",
            "subcategory":"Dance Studio",
            "type":"Public Place"
        }
    ],
    "sg:phone":"+1 718 272 1813",
    "sg:postcode":"11236",
    "sg:province":"NY",
    "sg:tags":[
        "instruction",
        "dancing"
    ],
    "wof:name":"April's Dance-N-Feet",
    "wof:placetype":"venue"
},
  "geometry": {"coordinates":[-73.903514,40.640071],"type":"Point"}
}