{
  "type": "Feature",
  "properties": {
    "iso:country":"US",
    "sg:address":"109 Century Dr",
    "sg:city":"Syracuse",
    "sg:classifiers":[
        {
            "category":"Professional",
            "subcategory":"Computer Services",
            "type":"Services"
        }
    ],
    "sg:phone":"+1 315 488 6245",
    "sg:postcode":"13209",
    "sg:province":"NY",
    "sg:tags":[
        "design",
        "system"
    ],
    "wof:name":"Josephine Devoe",
    "wof:placetype":"venue"
},
  "geometry": {"coordinates":[-76.215022,43.051844],"type":"Point"}
}