{
  "type": "Feature",
  "properties": {
    "iso:country":"US",
    "sg:address":"23 Mechanic St",
    "sg:city":"Springville",
    "sg:classifiers":[
        {
            "category":"Professional",
            "subcategory":"Computer Services",
            "type":"Services"
        }
    ],
    "sg:phone":"+1 716 592 2397",
    "sg:postcode":"14141",
    "sg:province":"NY",
    "sg:tags":[
        "consultant",
        "designer"
    ],
    "sg:website":"www.softwareinventors.com",
    "wof:name":"Software Inventors LTD",
    "wof:placetype":"venue"
},
  "geometry": {"coordinates":[-78.665812,42.509468],"type":"Point"}
}