{
  "type": "Feature",
  "properties": {
    "addr:full":"2809 Ocean Ave Brooklyn NY 11229",
    "addr:housenumber":"2809",
    "addr:postcode":"11229",
    "addr:street":"Ocean Ave",
    "iso:country":"US",
    "sg:address":"2809 Ocean Ave",
    "sg:city":"Brooklyn",
    "sg:classifiers":[
        {
            "category":"Restaurant",
            "type":"Food & Drink"
        }
    ],
    "sg:phone":"+1 718 769 6028",
    "sg:postcode":"11229",
    "sg:province":"NY",
    "sg:tags":[
        "japanese"
    ],
    "wof:name":"Ginza Japanese Restaurant Inc",
    "wof:placetype":"venue"
},
  "geometry": {"coordinates":[-73.950104,40.593201],"type":"Point"}
}