{
  "type": "Feature",
  "properties": {
    "iso:country":"US",
    "sg:address":"490 Plandome Rd",
    "sg:city":"Manhasset",
    "sg:classifiers":[
        {
            "category":"Shopping",
            "type":"Retail Goods"
        }
    ],
    "sg:phone":"+1 516 869 3378",
    "sg:postcode":"11030",
    "sg:province":"NY",
    "sg:tags":[
        "pet",
        "shop",
        "store"
    ],
    "wof:name":"Pets Boutique",
    "wof:placetype":"venue"
},
  "geometry": {"coordinates":[-73.700996,40.799801],"type":"Point"}
}