{
  "type": "Feature",
  "properties": {
    "addr:full":"1595 Military Rd Niagara Falls NY 14304",
    "addr:housenumber":"1595",
    "addr:postcode":"14304",
    "addr:street":"Military Rd",
    "iso:country":"US",
    "sg:address":"1595 Military Rd",
    "sg:city":"Niagara Falls",
    "sg:classifiers":[
        {
            "category":"Insurance",
            "subcategory":"Insurance Agent",
            "type":"Services"
        }
    ],
    "sg:phone":"+1 716 298 5651",
    "sg:postcode":"14304",
    "sg:province":"NY",
    "wof:name":"AAA Travel",
    "wof:placetype":"venue"
},
  "geometry": {"coordinates":[-78.971265,43.093585],"type":"Point"}
}