{
  "type": "Feature",
  "properties": {
    "iso:country":"US",
    "sg:address":"625 W 55th Street",
    "sg:city":"New York",
    "sg:classifiers":[
        {
            "category":"Education",
            "subcategory":"Music School",
            "type":"Public Place"
        },
        {
            "category":"Shopping",
            "subcategory":"Computers & Home Electronics",
            "type":"Retail Goods"
        }
    ],
    "sg:phone":"+1 212 868 4120",
    "sg:postcode":"10019",
    "sg:province":"NY",
    "sg:tags":[
        "instrument",
        "teacher",
        "musical"
    ],
    "wof:name":"Carroll Musical Instrument Rentals",
    "wof:placetype":"venue"
},
  "geometry": {"coordinates":[-73.993844,40.769636],"type":"Point"}
}