{
  "type": "Feature",
  "properties": {
    "iso:country":"US",
    "sg:address":"46 Wall St, Ste 450",
    "sg:city":"New York",
    "sg:classifiers":[
        {
            "category":"Banks & Credit Unions",
            "subcategory":"Financial Services",
            "type":"Services"
        }
    ],
    "sg:phone":"+1 216 132 3864",
    "sg:postcode":"10005",
    "sg:province":"NY",
    "wof:name":"Parker Forrester",
    "wof:placetype":"venue"
},
  "geometry": {"coordinates":[-74.009356,40.70631],"type":"Point"}
}