{
  "type": "Feature",
  "properties": {
    "addr:full":"120 Lee Ave Brooklyn NY 11211",
    "addr:housenumber":"120",
    "addr:postcode":"11211",
    "addr:street":"Lee Ave",
    "iso:country":"US",
    "sg:address":"120 Lee Ave",
    "sg:city":"Brooklyn",
    "sg:classifiers":[
        {
            "category":"Food & Beverages",
            "subcategory":"Groceries & Convenience Stores",
            "type":"Retail Goods"
        }
    ],
    "sg:phone":"+1 718 875 3547",
    "sg:postcode":"11211",
    "sg:province":"NY",
    "wof:name":"F & H Kosher Supermarket",
    "wof:placetype":"venue"
},
  "geometry": {"coordinates":[-73.95819899999999,40.704102],"type":"Point"}
}