{
  "type": "Feature",
  "properties": {
    "iso:country":"US",
    "sg:address":"60 Eddy St",
    "sg:city":"Greenwich",
    "sg:classifiers":[
        {
            "category":"Home & Garden",
            "subcategory":"Carpets & Floor Coverings",
            "type":"Retail Goods"
        }
    ],
    "sg:phone":"+1   ",
    "sg:postcode":"12834",
    "sg:province":"NY",
    "wof:name":"Grogans Floor Covering",
    "wof:placetype":"venue"
},
  "geometry": {"coordinates":[-73.493244,43.083962],"type":"Point"}
}