{
  "type": "Feature",
  "properties": {
    "iso:country":"US",
    "sg:address":"16 Tanglewood Ln",
    "sg:city":"Poughkeepsie",
    "sg:classifiers":[
        {
            "category":"Shopping",
            "subcategory":"Hobbies, Toys, & Games",
            "type":"Retail Goods"
        }
    ],
    "sg:phone":"+1   ",
    "sg:postcode":"12603",
    "sg:province":"NY",
    "wof:name":"Make It Special",
    "wof:placetype":"venue"
},
  "geometry": {"coordinates":[-73.84063500000001,41.662351],"type":"Point"}
}