{
  "type": "Feature",
  "properties": {
    "iso:country":"US",
    "sg:address":"197 State Hwy 67",
    "sg:city":"Amsterdam",
    "sg:classifiers":[
        {
            "category":"Farming",
            "subcategory":"Farm",
            "type":"Manufacturing & Wholesale Goods"
        }
    ],
    "sg:phone":"+1 518 843 6424",
    "sg:postcode":"12010",
    "sg:province":"NY",
    "sg:tags":[
        "crop",
        "general"
    ],
    "wof:name":"Wheelwright Farm",
    "wof:placetype":"venue"
},
  "geometry": {"coordinates":[-74.177626,42.937237],"type":"Point"}
}