{
  "type": "Feature",
  "properties": {
    "iso:country":"US",
    "sg:address":"276 W 1st St",
    "sg:city":"Oswego",
    "sg:classifiers":[
        {
            "category":"Food & Beverages",
            "subcategory":"Groceries & Convenience Stores",
            "type":"Retail Goods"
        }
    ],
    "sg:phone":"+1 315 342 2887",
    "sg:postcode":"13126",
    "sg:province":"NY",
    "sg:tags":[
        "grocer",
        "super",
        "supermarket"
    ],
    "wof:name":"Paul's Big M",
    "wof:placetype":"venue"
},
  "geometry": {"coordinates":[-76.50920000000001,43.452917],"type":"Point"}
}