{
  "type": "Feature",
  "properties": {
    "iso:country":"US",
    "sg:address":"189 W 231st St",
    "sg:city":"Bronx",
    "sg:classifiers":[
        {
            "category":"Shopping",
            "subcategory":"Jewelry",
            "type":"Retail Goods"
        }
    ],
    "sg:phone":"+1 718 796 2775",
    "sg:postcode":"10463",
    "sg:province":"NY",
    "sg:tags":[
        "jeweler"
    ],
    "wof:name":"Sterling World",
    "wof:placetype":"venue"
},
  "geometry": {"coordinates":[-73.904467,40.878845],"type":"Point"}
}