{
  "type": "Feature",
  "properties": {
    "addr:full":"34 Candlewood Gdns Baldwinsville NY 13027",
    "addr:housenumber":"34",
    "addr:postcode":"13027",
    "addr:street":"Candlewood Gdns",
    "iso:country":"US",
    "sg:address":"34 Candlewood Gdns",
    "sg:city":"Baldwinsville",
    "sg:classifiers":[
        {
            "category":"Real Estate",
            "subcategory":"Real Estate Services",
            "type":"Services"
        },
        {
            "category":"Real Estate",
            "subcategory":"Real Estate Operator",
            "type":"Services"
        }
    ],
    "sg:phone":"+1 315 638 0151",
    "sg:postcode":"13027",
    "sg:province":"NY",
    "sg:tags":[
        "vacancy",
        "apartment",
        "rental",
        "finder",
        "listing"
    ],
    "sg:website":"http://www.candlewoodgardens.com",
    "wof:name":"Candlewood Gardens",
    "wof:placetype":"venue"
},
  "geometry": {"coordinates":[-76.32365299999999,43.164101],"type":"Point"}
}