{
  "type": "Feature",
  "properties": {
    "iso:country":"US",
    "sg:address":"655 Yonkers Ave",
    "sg:city":"Yonkers",
    "sg:classifiers":[
        {
            "category":"Health Services",
            "subcategory":"Doctor",
            "type":"Services"
        }
    ],
    "sg:phone":"+1 914 375 5600",
    "sg:postcode":"10704",
    "sg:province":"NY",
    "sg:tags":[
        "dentist"
    ],
    "wof:name":"Frank P Petronella DDS",
    "wof:placetype":"venue"
},
  "geometry": {"coordinates":[-73.868037,40.925402],"type":"Point"}
}