{
  "type": "Feature",
  "properties": {
    "addr:full":"800 Park Ave New York NY 10021",
    "addr:housenumber":"800",
    "addr:postcode":"10021",
    "addr:street":"Park Ave",
    "iso:country":"US",
    "sg:address":"800 Park Ave",
    "sg:city":"New York",
    "sg:classifiers":[
        {
            "category":"Professional",
            "subcategory":"Business Services",
            "type":"Services"
        }
    ],
    "sg:phone":"+1   ",
    "sg:postcode":"10021",
    "sg:province":"NY",
    "wof:name":"Central Business Centers Inc",
    "wof:placetype":"venue"
},
  "geometry": {"coordinates":[-73.962546,40.772949],"type":"Point"}
}