{
  "type": "Feature",
  "properties": {
    "addr:full":"686 W 43rd St New York NY 10036",
    "addr:housenumber":"686",
    "addr:postcode":"10036",
    "addr:street":"W 43Rd St",
    "iso:country":"US",
    "sg:address":"686 W 43rd St",
    "sg:city":"New York",
    "sg:classifiers":[
        {
            "category":"Restaurant",
            "type":"Food & Drink"
        }
    ],
    "sg:phone":"+1   ",
    "sg:postcode":"10036",
    "sg:province":"NY",
    "sg:tags":[
        "eating"
    ],
    "wof:name":"Starbucks",
    "wof:placetype":"venue"
},
  "geometry": {"coordinates":[-73.99870900000001,40.761571],"type":"Point"}
}