{
  "type": "Feature",
  "properties": {
    "addr:full":"321 N Doxtator St Rome NY 13440",
    "addr:housenumber":"321",
    "addr:postcode":"13440",
    "addr:street":"N Doxtator St",
    "iso:country":"US",
    "sg:address":"321 N Doxtator St",
    "sg:city":"Rome",
    "sg:classifiers":[
        {
            "category":"Food & Beverages",
            "subcategory":"Candy",
            "type":"Retail Goods"
        },
        {
            "category":"Manufacturing",
            "subcategory":"Food",
            "type":"Manufacturing & Wholesale Goods"
        },
        {
            "category":"Food & Beverages",
            "subcategory":"Chocolate",
            "type":"Retail Goods"
        }
    ],
    "sg:phone":"+1 315 337 4530",
    "sg:postcode":"13440",
    "sg:province":"NY",
    "sg:tags":[
        "cocoa",
        "confectionery-wholesale",
        "confectionery",
        "manufacturer"
    ],
    "wof:name":"Candy Land",
    "wof:placetype":"venue"
},
  "geometry": {"coordinates":[-75.472128,43.221785],"type":"Point"}
}