{
  "type": "Feature",
  "properties": {
    "addr:full":"105 Belvedere Dr Yonkers NY 10705",
    "addr:housenumber":"105",
    "addr:postcode":"10705",
    "addr:street":"Belvedere Dr",
    "iso:country":"US",
    "sg:address":"105 Belvedere Dr",
    "sg:city":"Yonkers",
    "sg:classifiers":[
        {
            "category":"Professional",
            "subcategory":"Computer Services",
            "type":"Services"
        }
    ],
    "sg:phone":"+1   ",
    "sg:postcode":"10705",
    "sg:province":"NY",
    "sg:tags":[
        "prepackaged",
        "software"
    ],
    "wof:name":"Cohn",
    "wof:placetype":"venue"
},
  "geometry": {"coordinates":[-73.90656199999999,40.918769],"type":"Point"}
}