{
  "type": "Feature",
  "properties": {
    "iso:country":"US",
    "sg:address":"25 Browns Race",
    "sg:city":"Rochester",
    "sg:classifiers":[
        {
            "category":"Professional",
            "type":"Services"
        }
    ],
    "sg:phone":"+1 585 232 9120",
    "sg:postcode":"14614",
    "sg:province":"NY",
    "sg:tags":[
        "establishment"
    ],
    "wof:name":"Chamberlain Family Offices",
    "wof:placetype":"venue"
},
  "geometry": {"coordinates":[-77.61579500000001,43.160485],"type":"Point"}
}