{
  "type": "Feature",
  "properties": {
    "addr:full":"50 Triangle Center Yorktown Heights NY 10598",
    "addr:housenumber":"50",
    "addr:postcode":"10598",
    "addr:street":"Triangle;Yorktown Heights",
    "iso:country":"US",
    "sg:address":"50 Triangle Center",
    "sg:city":"Yorktown Heights",
    "sg:classifiers":[
        {
            "category":"Home & Garden",
            "subcategory":"Household Appliances",
            "type":"Retail Goods"
        }
    ],
    "sg:phone":"+1 914 962 0202",
    "sg:postcode":"10598",
    "sg:province":"NY",
    "wof:name":"Price Discounters",
    "wof:placetype":"venue"
},
  "geometry": {"coordinates":[-73.808335,41.295488],"type":"Point"}
}