{
  "type": "Feature",
  "properties": {
    "iso:country":"US",
    "sg:address":"8 Banta St",
    "sg:city":"Phelps",
    "sg:classifiers":[
        {
            "category":"Real Estate",
            "subcategory":"Surveying",
            "type":"Services"
        }
    ],
    "sg:phone":"+1 315 548 4045",
    "sg:postcode":"14532",
    "sg:province":"NY",
    "sg:tags":[
        "surveyor"
    ],
    "wof:name":"Clark Surveyors",
    "wof:placetype":"venue"
},
  "geometry": {"coordinates":[-77.06176000000001,42.958923],"type":"Point"}
}