{
  "type": "Feature",
  "properties": {
    "addr:full":"800 W 254th St Bronx NY 10471",
    "addr:housenumber":"800",
    "addr:postcode":"10471",
    "addr:street":"W 254Th St",
    "iso:country":"US",
    "sg:address":"800 W 254th St",
    "sg:city":"Bronx",
    "sg:classifiers":[
        {
            "category":"Recreation",
            "type":"Entertainment"
        }
    ],
    "sg:phone":"+1 718 543 0792",
    "sg:postcode":"10471",
    "sg:province":"NY",
    "sg:tags":[
        "marina",
        "club",
        "membership",
        "private"
    ],
    "sg:website":"http://www.riverdaleyachtclub.com",
    "wof:name":"Riverdale Yacht Club Inc",
    "wof:placetype":"venue"
},
  "geometry": {"coordinates":[-73.913696,40.90379],"type":"Point"}
}