{
  "type": "Feature",
  "properties": {
    "addr:full":"340 N Village Ave Rockville Centre NY 11570",
    "addr:housenumber":"340",
    "addr:postcode":"11570",
    "addr:street":"N Village Ave",
    "iso:country":"US",
    "sg:address":"340 N Village Ave",
    "sg:city":"Rockville Centre",
    "sg:classifiers":[
        {
            "category":"Education",
            "subcategory":"School",
            "type":"Public Place"
        }
    ],
    "sg:phone":"+1 516 594 8262",
    "sg:postcode":"11570",
    "sg:province":"NY",
    "wof:name":"E Approach",
    "wof:placetype":"venue"
},
  "geometry": {"coordinates":[-73.64668899999999,40.667849],"type":"Point"}
}