{
  "type": "Feature",
  "properties": {
    "addr:full":"2253 3rd Avenue New York NY 10035",
    "addr:housenumber":"2253",
    "addr:postcode":"10035",
    "addr:street":"3Rd Avenue",
    "iso:country":"US",
    "sg:address":"2253 3rd Avenue",
    "sg:city":"New York",
    "sg:classifiers":[
        {
            "category":"Shopping",
            "subcategory":"Mobile Phones",
            "type":"Retail Goods"
        }
    ],
    "sg:phone":"+1 212 996 1600",
    "sg:postcode":"10035",
    "sg:province":"NY",
    "wof:name":"East Harlem Wireless",
    "wof:placetype":"venue"
},
  "geometry": {"coordinates":[-73.936846,40.802174],"type":"Point"}
}