{
  "type": "Feature",
  "properties": {
    "iso:country":"US",
    "sg:address":"9700 Mill St",
    "sg:city":"Camden",
    "sg:classifiers":[
        {
            "category":"Shopping",
            "subcategory":"Catalog Store",
            "type":"Retail Goods"
        }
    ],
    "sg:phone":"+1 315 245 2690",
    "sg:postcode":"13316",
    "sg:province":"NY",
    "sg:tags":[
        "stamp",
        "sales",
        "by",
        "philatelic",
        "internet",
        "mail",
        "order"
    ],
    "sg:website":"www.mysticstamp.com",
    "wof:name":"Mystic Stamp Co Inc",
    "wof:placetype":"venue"
},
  "geometry": {"coordinates":[-75.75923299999999,43.346624],"type":"Point"}
}