{
  "type": "Feature",
  "properties": {
    "addr:full":"1158 46th St Brooklyn NY 11219",
    "addr:housenumber":"1158",
    "addr:postcode":"11219",
    "addr:street":"46Th St",
    "iso:country":"US",
    "sg:address":"1158 46th St",
    "sg:city":"Brooklyn",
    "sg:classifiers":[
        {
            "category":"Organizations",
            "subcategory":"Religious Organization",
            "type":"Services"
        }
    ],
    "sg:phone":"+1 718 853 6446",
    "sg:postcode":"11219",
    "sg:province":"NY",
    "sg:tags":[
        "clergy"
    ],
    "wof:name":"Jacob Gobioff",
    "wof:placetype":"venue"
},
  "geometry": {"coordinates":[-73.99332200000001,40.638535],"type":"Point"}
}