{
  "type": "Feature",
  "properties": {
    "addr:full":"646 Prospect Ave Bronx NY 10455",
    "addr:housenumber":"646",
    "addr:postcode":"10455",
    "addr:street":"Prospect Ave",
    "iso:country":"US",
    "sg:address":"646 Prospect Ave",
    "sg:city":"Bronx",
    "sg:classifiers":[
        {
            "category":"Shopping",
            "subcategory":"Discount & Variety Stores",
            "type":"Retail Goods"
        }
    ],
    "sg:phone":"+1 718 742 6855",
    "sg:postcode":"10455",
    "sg:province":"NY",
    "wof:name":"D & D 99 Cents & Up",
    "wof:placetype":"venue"
},
  "geometry": {"coordinates":[-73.903015,40.816011],"type":"Point"}
}