{
  "type": "Feature",
  "properties": {
    "addr:full":"25 Nickelsey Rd Shokan NY 12481",
    "addr:housenumber":"25",
    "addr:postcode":"12481",
    "addr:street":"Nickelsey Rd",
    "iso:country":"US",
    "sg:address":"25 Nickelsey Rd",
    "sg:city":"Shokan",
    "sg:classifiers":[
        {
            "category":"Professional",
            "subcategory":"Business Services",
            "type":"Services"
        }
    ],
    "sg:phone":"+1   ",
    "sg:postcode":"12481",
    "sg:province":"NY",
    "wof:name":"D & G Design",
    "wof:placetype":"venue"
},
  "geometry": {"coordinates":[-74.237193,41.997072],"type":"Point"}
}