{
  "type": "Feature",
  "properties": {
    "iso:country":"US",
    "sg:address":"55 Lafayette Ave",
    "sg:city":"White Plains",
    "sg:classifiers":[
        {
            "category":"Professional",
            "type":"Services"
        }
    ],
    "sg:phone":"+1 914 948 3231",
    "sg:postcode":"10603",
    "sg:province":"NY",
    "sg:tags":[
        "establishment"
    ],
    "wof:name":"Bentfield Power & Control Syst",
    "wof:placetype":"venue"
},
  "geometry": {"coordinates":[-73.771873,41.064796],"type":"Point"}
}