{
  "type": "Feature",
  "properties": {
    "iso:country":"US",
    "sg:address":"155 Droms Rd",
    "sg:city":"Schenectady",
    "sg:classifiers":[
        {
            "category":"Building & Trades",
            "subcategory":"Construction",
            "type":"Services"
        }
    ],
    "sg:phone":"+1 518 399 6030",
    "sg:postcode":"12302",
    "sg:province":"NY",
    "sg:tags":[
        "manufactured",
        "housing-communities"
    ],
    "wof:name":"Indian Meadows Park",
    "wof:placetype":"venue"
},
  "geometry": {"coordinates":[-73.941147,42.889462],"type":"Point"}
}