{
  "type": "Feature",
  "properties": {
    "iso:country":"US",
    "sg:address":"10948 Cooper St",
    "sg:city":"Cato",
    "sg:classifiers":[
        {
            "category":"Building & Trades",
            "subcategory":"Construction",
            "type":"Services"
        }
    ],
    "sg:phone":"+1 315 626 6482",
    "sg:postcode":"13033",
    "sg:province":"NY",
    "sg:tags":[
        "house"
    ],
    "wof:name":"Hemple Dan Construction",
    "wof:placetype":"venue"
},
  "geometry": {"coordinates":[-76.623515,43.1653],"type":"Point"}
}