{
  "type": "Feature",
  "properties": {
    "iso:country":"US",
    "sg:address":"1290 Amsterdam Ave",
    "sg:city":"New York",
    "sg:classifiers":[
        {
            "category":"Shopping",
            "subcategory":"Pharmacy",
            "type":"Retail Goods"
        }
    ],
    "sg:phone":"+1 212 665 8498",
    "sg:postcode":"10027",
    "sg:province":"NY",
    "sg:tags":[
        "drugstore"
    ],
    "wof:name":"Duanereade",
    "wof:placetype":"venue"
},
  "geometry": {"coordinates":[-73.95740600000001,40.812096],"type":"Point"}
}