{
  "type": "Feature",
  "properties": {
    "iso:country":"US",
    "sg:address":"131 Saw Mill River Rd",
    "sg:city":"Yonkers",
    "sg:classifiers":[
        {
            "category":"Freight",
            "type":"Transportation"
        }
    ],
    "sg:phone":"+1   ",
    "sg:postcode":"10701",
    "sg:province":"NY",
    "sg:tags":[
        "company",
        "storage"
    ],
    "wof:name":"Vestpro Corporation",
    "wof:placetype":"venue"
},
  "geometry": {"coordinates":[-73.880613,40.944316],"type":"Point"}
}