{
  "type": "Feature",
  "properties": {
    "addr:full":"713 4th Ave Brooklyn NY 11232",
    "addr:housenumber":"713",
    "addr:postcode":"11232",
    "addr:street":"4Th Ave",
    "iso:country":"US",
    "sg:address":"713 4th Ave",
    "sg:city":"Brooklyn",
    "sg:classifiers":[
        {
            "category":"Food & Beverages",
            "subcategory":"Supermarket",
            "type":"Retail Goods"
        },
        {
            "category":"Food & Beverages",
            "subcategory":"Groceries & Convenience Stores",
            "type":"Retail Goods"
        }
    ],
    "sg:phone":"+1 718 965 9560",
    "sg:postcode":"11232",
    "sg:province":"NY",
    "sg:tags":[
        "super"
    ],
    "wof:name":"Margarita Grocery",
    "wof:placetype":"venue"
},
  "geometry": {"coordinates":[-73.996644,40.661461],"type":"Point"}
}