{
  "type": "Feature",
  "properties": {
    "addr:full":"1088 Castleton Ave Staten Island NY 10310",
    "addr:housenumber":"1088",
    "addr:postcode":"10310",
    "addr:street":"Castleton Ave",
    "iso:country":"US",
    "sg:address":"1088 Castleton Ave",
    "sg:city":"Staten Island",
    "sg:classifiers":[
        {
            "category":"Personal",
            "subcategory":"Nail Salon",
            "type":"Services"
        }
    ],
    "sg:phone":"+1 718 442 2385",
    "sg:postcode":"10310",
    "sg:province":"NY",
    "wof:name":"Ji Lucky Nails Inc",
    "wof:placetype":"venue"
},
  "geometry": {"coordinates":[-74.11881700000001,40.634277],"type":"Point"}
}