{
  "type": "Feature",
  "properties": {
    "addr:full":"10 Gleason Dr East Quogue NY 11942",
    "addr:housenumber":"10",
    "addr:postcode":"11942",
    "addr:street":"Gleason Dr East",
    "iso:country":"US",
    "sg:address":"10 Gleason Dr",
    "sg:city":"East Quogue",
    "sg:classifiers":[
        {
            "category":"Wholesale",
            "subcategory":"Non-durable Goods",
            "type":"Manufacturing & Wholesale Goods"
        }
    ],
    "sg:phone":"+1 631 653 4189",
    "sg:postcode":"11942",
    "sg:province":"NY",
    "wof:name":"East Quogue Distributors Inc",
    "wof:placetype":"venue"
},
  "geometry": {"coordinates":[-72.582342,40.850271],"type":"Point"}
}