{
  "type": "Feature",
  "properties": {
    "iso:country":"US",
    "sg:address":"4195 Boston Rd",
    "sg:city":"Bronx",
    "sg:classifiers":[
        {
            "category":"Building & Trades",
            "subcategory":"Construction",
            "type":"Services"
        }
    ],
    "sg:phone":"+1 718 231 1463",
    "sg:postcode":"10466",
    "sg:province":"NY",
    "sg:tags":[
        "contractor"
    ],
    "wof:name":"Desmond Iron Works",
    "wof:placetype":"venue"
},
  "geometry": {"coordinates":[-73.824969,40.886969],"type":"Point"}
}