{
  "type": "Feature",
  "properties": {
    "addr:full":"225 W 57th Street New York NY 10019",
    "addr:housenumber":"225",
    "addr:postcode":"10019",
    "addr:street":"W 57Th Street",
    "iso:country":"US",
    "sg:address":"225 W 57th Street",
    "sg:city":"New York",
    "sg:classifiers":[
        {
            "category":"Shopping",
            "subcategory":"Mobile Phones",
            "type":"Retail Goods"
        }
    ],
    "sg:phone":"+1 212 660 6790",
    "sg:postcode":"10019",
    "sg:province":"NY",
    "wof:name":"Dentsu Communications",
    "wof:placetype":"venue"
},
  "geometry": {"coordinates":[-73.981566,40.766183],"type":"Point"}
}