{
  "type": "Feature",
  "properties": {
    "iso:country":"US",
    "sg:address":"431 Merrick Rd",
    "sg:city":"Lynbrook",
    "sg:classifiers":[
        {
            "category":"Restaurant",
            "type":"Food & Drink"
        }
    ],
    "sg:phone":"+1 516 599 7087",
    "sg:postcode":"11563",
    "sg:province":"NY",
    "wof:name":"New Hong Kong Restaurant",
    "wof:placetype":"venue"
},
  "geometry": {"coordinates":[-73.676697,40.658401],"type":"Point"}
}