{
  "type": "Feature",
  "properties": {
    "addr:full":"3863 E Tremont Ave Bronx NY 10465",
    "addr:housenumber":"3863",
    "addr:postcode":"10465",
    "addr:street":"E Tremont Ave",
    "iso:country":"US",
    "sg:address":"3863 E Tremont Ave",
    "sg:city":"Bronx",
    "sg:classifiers":[
        {
            "category":"Health Services",
            "subcategory":"Doctor",
            "type":"Services"
        }
    ],
    "sg:phone":"+1 718 829 4620",
    "sg:postcode":"10465",
    "sg:province":"NY",
    "sg:tags":[
        "physician",
        "medical",
        "surgeon"
    ],
    "wof:name":"Alvin B Hill MD PC",
    "wof:placetype":"venue"
},
  "geometry": {"coordinates":[-73.81951599999999,40.823176],"type":"Point"}
}