{
  "type": "Feature",
  "properties": {
    "addr:full":"90 Meadowbrook Rd Syosset NY 11791",
    "addr:housenumber":"90",
    "addr:postcode":"11791",
    "addr:street":"Meadowbrook Rd",
    "iso:country":"US",
    "sg:address":"90 Meadowbrook Rd",
    "sg:city":"Syosset",
    "sg:classifiers":[
        {
            "category":"Building & Trades",
            "subcategory":"Construction",
            "type":"Services"
        }
    ],
    "sg:phone":"+1 516 364 3574",
    "sg:postcode":"11791",
    "sg:province":"NY",
    "sg:tags":[
        "house",
        "improvement",
        "home"
    ],
    "wof:name":"Pusateri Home Improvements Inc",
    "wof:placetype":"venue"
},
  "geometry": {"coordinates":[-73.505971,40.834831],"type":"Point"}
}