{
  "type": "Feature",
  "properties": {
    "iso:country":"US",
    "sg:address":"6020 59th Pl",
    "sg:city":"Maspeth",
    "sg:classifiers":[
        {
            "category":"Building & Trades",
            "subcategory":"Construction",
            "type":"Services"
        }
    ],
    "sg:phone":"+1 718 418 0606",
    "sg:postcode":"11378",
    "sg:province":"NY",
    "sg:tags":[
        "contractor"
    ],
    "wof:name":"Century Window Fashion",
    "wof:placetype":"venue"
},
  "geometry": {"coordinates":[-73.907292,40.715703],"type":"Point"}
}