{
  "type": "Feature",
  "properties": {
    "addr:full":"100 Roberts Ave Ste 10 Syracuse NY 13207",
    "addr:housenumber":"100",
    "addr:postcode":"13207",
    "addr:street":"Roberts Ave Ste 10",
    "iso:country":"US",
    "sg:address":"100 Roberts Ave Ste 10",
    "sg:city":"Syracuse",
    "sg:classifiers":[
        {
            "category":"Health Services",
            "subcategory":"Nursing And Care Facility",
            "type":"Services"
        },
        {
            "category":"Health Services",
            "subcategory":"Health Practitioner",
            "type":"Services"
        }
    ],
    "sg:phone":"+1 315 475 1747",
    "sg:postcode":"13207",
    "sg:province":"NY",
    "sg:tags":[
        "home",
        "eldercare-home"
    ],
    "sg:website":"http://www.sarahhouse.org",
    "wof:name":"Hospital Hospitality",
    "wof:placetype":"venue"
},
  "geometry": {"coordinates":[-76.172089,43.032928],"type":"Point"}
}