{
  "type": "Feature",
  "properties": {
    "addr:full":"89-06 135th Jamaica NY 11430",
    "addr:housenumber":"89-06",
    "addr:postcode":"11430",
    "addr:street":"135Th",
    "iso:country":"US",
    "sg:address":"89-06 135th",
    "sg:city":"Jamaica",
    "sg:classifiers":[
        {
            "category":"Health Services",
            "subcategory":"Doctor",
            "type":"Services"
        }
    ],
    "sg:phone":"+1 718 206 6742",
    "sg:postcode":"11430",
    "sg:province":"NY",
    "sg:tags":[
        "medicine",
        "internal",
        "cardiologist"
    ],
    "wof:name":"Nandakumar Thambirajah",
    "wof:placetype":"venue"
},
  "geometry": {"coordinates":[-73.823238,40.715113],"type":"Point"}
}