{
  "type": "Feature",
  "properties": {
    "addr:full":"3580 160th Street Flushing NY 11358",
    "addr:housenumber":"3580",
    "addr:postcode":"11358",
    "addr:street":"160Th Street",
    "iso:country":"US",
    "sg:address":"3580 160th Street",
    "sg:city":"Flushing",
    "sg:classifiers":[
        {
            "category":"Wholesale",
            "subcategory":"Computers",
            "type":"Manufacturing & Wholesale Goods"
        }
    ],
    "sg:phone":"+1 718 762 3327",
    "sg:postcode":"11358",
    "sg:province":"NY",
    "wof:name":"Vlp",
    "wof:placetype":"venue"
},
  "geometry": {"coordinates":[-73.805632,40.763169],"type":"Point"}
}