{
  "type": "Feature",
  "properties": {
    "iso:country":"US",
    "sg:address":"7420 4th Ave",
    "sg:city":"Brooklyn",
    "sg:classifiers":[
        {
            "category":"Social Services",
            "subcategory":"Child Care",
            "type":"Services"
        }
    ],
    "sg:phone":"+1 718 745 6908",
    "sg:postcode":"11209",
    "sg:province":"NY",
    "sg:tags":[
        "day"
    ],
    "wof:name":"Carousel Corner Preschl Inc",
    "wof:placetype":"venue"
},
  "geometry": {"coordinates":[-74.025099,40.630977],"type":"Point"}
}