{
  "type": "Feature",
  "properties": {
    "iso:country":"US",
    "sg:address":"5 Charlotte Ave",
    "sg:city":"Hicksville",
    "sg:classifiers":[
        {
            "category":"Freight",
            "type":"Transportation"
        }
    ],
    "sg:phone":"+1 516 997 7100",
    "sg:postcode":"11801",
    "sg:province":"NY",
    "sg:tags":[
        "commercial",
        "storage"
    ],
    "wof:name":"TRANSIT USA Inc",
    "wof:placetype":"venue"
},
  "geometry": {"coordinates":[-73.547363,40.759296],"type":"Point"}
}