{
  "type": "Feature",
  "properties": {
    "iso:country":"US",
    "sg:address":"4716 White Plains Rd",
    "sg:city":"Bronx",
    "sg:classifiers":[
        {
            "category":"Wholesale",
            "subcategory":"Machinery & Supplies",
            "type":"Manufacturing & Wholesale Goods"
        }
    ],
    "sg:phone":"+1 718 325 1117",
    "sg:postcode":"10470",
    "sg:province":"NY",
    "sg:tags":[
        "equipment",
        "manicure"
    ],
    "wof:name":"Gold Nail",
    "wof:placetype":"venue"
},
  "geometry": {"coordinates":[-73.850054,40.903609],"type":"Point"}
}