{
  "type": "Feature",
  "properties": {
    "iso:country":"US",
    "sg:address":"25 Bloomingdale Rd",
    "sg:city":"Staten Island",
    "sg:classifiers":[
        {
            "category":"Real Estate",
            "subcategory":"Real Estate Agent",
            "type":"Services"
        }
    ],
    "sg:phone":"+1 718 227 1600",
    "sg:postcode":"10309",
    "sg:province":"NY",
    "wof:name":"Own A Home Realty Inc",
    "wof:placetype":"venue"
},
  "geometry": {"coordinates":[-74.215552,40.524725],"type":"Point"}
}