{
  "type": "Feature",
  "properties": {
    "iso:country":"US",
    "sg:address":"82 Margaret St",
    "sg:city":"Plattsburgh",
    "sg:classifiers":[
        {
            "category":"Professional",
            "subcategory":"Computer Services",
            "type":"Services"
        }
    ],
    "sg:phone":"+1 514 392 9111",
    "sg:postcode":"12901",
    "sg:province":"NY",
    "sg:tags":[
        "related"
    ],
    "wof:name":"Mendax Microsystems Inc",
    "wof:placetype":"venue"
},
  "geometry": {"coordinates":[-73.45289200000001,44.697196],"type":"Point"}
}