{
  "type": "Feature",
  "properties": {
    "addr:full":"54 Harder Dr Woodstock NY 12498",
    "addr:housenumber":"54",
    "addr:postcode":"12498",
    "addr:street":"Harder Dr",
    "iso:country":"US",
    "sg:address":"54 Harder Dr",
    "sg:city":"Woodstock",
    "sg:classifiers":[
        {
            "category":"Building & Trades",
            "subcategory":"Construction",
            "type":"Services"
        }
    ],
    "sg:phone":"+1 845 679 6031",
    "sg:postcode":"12498",
    "sg:province":"NY",
    "sg:tags":[
        "house"
    ],
    "wof:name":"Wholesome Homes Inc",
    "wof:placetype":"venue"
},
  "geometry": {"coordinates":[-74.14932899999999,42.037738],"type":"Point"}
}