{
  "type": "Feature",
  "properties": {
    "addr:full":"37 Reid St Amsterdam NY 12010",
    "addr:housenumber":"37",
    "addr:postcode":"12010",
    "addr:street":"Reid St",
    "iso:country":"US",
    "sg:address":"37 Reid St",
    "sg:city":"Amsterdam",
    "sg:classifiers":[
        {
            "category":"Personal",
            "subcategory":"Shoe Repair & Shine",
            "type":"Services"
        }
    ],
    "sg:phone":"+1   ",
    "sg:postcode":"12010",
    "sg:province":"NY",
    "sg:tags":[
        "parlor",
        "shoes"
    ],
    "wof:name":"Depalma Shoe & Luggage Service",
    "wof:placetype":"venue"
},
  "geometry": {"coordinates":[-74.181016,42.936012],"type":"Point"}
}