{
  "type": "Feature",
  "properties": {
    "addr:full":"430 Jefferson Street Brooklyn NY 11237",
    "addr:housenumber":"430",
    "addr:postcode":"11237",
    "addr:street":"Jefferson Street",
    "iso:country":"US",
    "sg:address":"430 Jefferson Street",
    "sg:city":"Brooklyn",
    "sg:classifiers":[
        {
            "category":"Building & Trades",
            "subcategory":"Plumbing",
            "type":"Services"
        }
    ],
    "sg:phone":"+1 718 386 1800",
    "sg:postcode":"11237",
    "sg:province":"NY",
    "wof:name":"Fulton Plumbing & Heating Corporation",
    "wof:placetype":"venue"
},
  "geometry": {"coordinates":[-73.922955,40.707466],"type":"Point"}
}