{
  "type": "Feature",
  "properties": {
    "addr:full":"96 Allen Blvd Farmingdale NY 11735",
    "addr:housenumber":"96",
    "addr:postcode":"11735",
    "addr:street":"Allen Blvd",
    "iso:country":"US",
    "sg:address":"96 Allen Blvd",
    "sg:city":"Farmingdale",
    "sg:classifiers":[
        {
            "category":"Professional",
            "subcategory":"Testing Lab",
            "type":"Services"
        }
    ],
    "sg:phone":"+1 631 293 8944",
    "sg:postcode":"11735",
    "sg:province":"NY",
    "sg:tags":[
        "laboratory"
    ],
    "sg:website":"www.govmark.com",
    "wof:name":"Govmark Organization Inc",
    "wof:placetype":"venue"
},
  "geometry": {"coordinates":[-73.419578,40.715851],"type":"Point"}
}