{
  "type": "Feature",
  "properties": {
    "iso:country":"US",
    "sg:address":"12 Central Ave",
    "sg:city":"New City",
    "sg:classifiers":[
        {
            "category":"Professional",
            "subcategory":"Computer Services",
            "type":"Services"
        }
    ],
    "sg:phone":"+1   ",
    "sg:postcode":"10956",
    "sg:province":"NY",
    "wof:name":"M & M Consulting L L C",
    "wof:placetype":"venue"
},
  "geometry": {"coordinates":[-74.00692100000001,41.123454],"type":"Point"}
}