{
  "type": "Feature",
  "properties": {
    "addr:full":"1203 Virginia Avenue Bronx NY 10472",
    "addr:housenumber":"1203",
    "addr:postcode":"10472",
    "addr:street":"Virginia Avenue",
    "iso:country":"US",
    "sg:address":"1203 Virginia Avenue",
    "sg:city":"Bronx",
    "sg:classifiers":[
        {
            "category":"Organizations",
            "subcategory":"Religious Organization",
            "type":"Services"
        }
    ],
    "sg:phone":"+1 718 828 4194",
    "sg:postcode":"10472",
    "sg:province":"NY",
    "wof:name":"Parkchester Jame Masjid",
    "wof:placetype":"venue"
},
  "geometry": {"coordinates":[-73.86076,40.830725],"type":"Point"}
}