{
  "type": "Feature",
  "properties": {
    "iso:country":"US",
    "sg:address":"1422 Flatbush Avenue",
    "sg:city":"Brooklyn",
    "sg:classifiers":[
        {
            "category":"Food & Beverages",
            "subcategory":"Groceries & Convenience Stores",
            "type":"Retail Goods"
        }
    ],
    "sg:phone":"+1 718 434 4718",
    "sg:postcode":"11210",
    "sg:province":"NY",
    "wof:name":"Rjm Mini Market",
    "wof:placetype":"venue"
},
  "geometry": {"coordinates":[-73.951103,40.635921],"type":"Point"}
}