{
  "type": "Feature",
  "properties": {
    "addr:full":"64 Beaver St New York NY 10004",
    "addr:housenumber":"64",
    "addr:postcode":"10004",
    "addr:street":"Beaver St",
    "iso:country":"US",
    "sg:address":"64 Beaver St",
    "sg:city":"New York",
    "sg:classifiers":[
        {
            "category":"Freight",
            "type":"Transportation"
        }
    ],
    "sg:phone":"+1 212 514 7472",
    "sg:postcode":"10004",
    "sg:province":"NY",
    "sg:tags":[
        "shipping"
    ],
    "sg:website":"www.theupsstore.com",
    "wof:name":"The UPS Store",
    "wof:placetype":"venue"
},
  "geometry": {"coordinates":[-74.009327,40.705213],"type":"Point"}
}