{
  "type": "Feature",
  "properties": {
    "addr:full":"903 Hardscrabble Rd Cassville NY 13318",
    "addr:housenumber":"903",
    "addr:postcode":"13318",
    "addr:street":"Hardscrabble Rd",
    "iso:country":"US",
    "sg:address":"903 Hardscrabble Rd",
    "sg:city":"Cassville",
    "sg:classifiers":[
        {
            "category":"Building & Trades",
            "subcategory":"Construction",
            "type":"Services"
        }
    ],
    "sg:phone":"+1 315 822 4261",
    "sg:postcode":"13318",
    "sg:province":"NY",
    "sg:tags":[
        "house"
    ],
    "wof:name":"Goodenough General Contracting",
    "wof:placetype":"venue"
},
  "geometry": {"coordinates":[-75.25689300000001,42.907622],"type":"Point"}
}