{
  "type": "Feature",
  "properties": {
    "iso:country":"US",
    "sg:address":"58 E Pkwy",
    "sg:city":"Scarsdale",
    "sg:classifiers":[
        {
            "category":"Food & Beverages",
            "subcategory":"Groceries & Convenience Stores",
            "type":"Retail Goods"
        }
    ],
    "sg:phone":"+1   ",
    "sg:postcode":"10583",
    "sg:province":"NY",
    "sg:tags":[
        "supermarket"
    ],
    "wof:name":"C-Town Supermarket",
    "wof:placetype":"venue"
},
  "geometry": {"coordinates":[-73.808061,40.98988],"type":"Point"}
}