{
  "type": "Feature",
  "properties": {
    "iso:country":"US",
    "sg:address":"10048 Wolcott Hill Rd",
    "sg:city":"Camden",
    "sg:classifiers":[
        {
            "category":"Organizations",
            "subcategory":"Religious Organization",
            "type":"Services"
        }
    ],
    "sg:phone":"+1 315 245 1515",
    "sg:postcode":"13316",
    "sg:province":"NY",
    "sg:tags":[
        "clergy"
    ],
    "sg:website":"www.pilgrimholiness-church.com",
    "wof:name":"Pilgrim Holiness Church",
    "wof:placetype":"venue"
},
  "geometry": {"coordinates":[-75.73074,43.345835],"type":"Point"}
}