{
  "type": "Feature",
  "properties": {
    "addr:full":"203 S Meadow St Ithaca NY 14850",
    "addr:housenumber":"203",
    "addr:postcode":"14850",
    "addr:street":"S Meadow St",
    "iso:country":"US",
    "sg:address":"203 S Meadow St",
    "sg:city":"Ithaca",
    "sg:classifiers":[
        {
            "category":"Restaurant",
            "type":"Food & Drink"
        }
    ],
    "sg:phone":"+1   ",
    "sg:postcode":"14850",
    "sg:province":"NY",
    "sg:tags":[
        "chicken",
        "fast"
    ],
    "wof:name":"KFC",
    "wof:placetype":"venue"
},
  "geometry": {"coordinates":[-76.508225,42.438329],"type":"Point"}
}