{
  "type": "Feature",
  "properties": {
    "addr:full":"9524 Carousel Center Syracuse NY 13290",
    "addr:housenumber":"9524",
    "addr:postcode":"13290",
    "addr:street":"Carousel Center",
    "iso:country":"US",
    "sg:address":"9524 Carousel Center",
    "sg:city":"Syracuse",
    "sg:classifiers":[
        {
            "category":"Retail",
            "subcategory":"Portrait Studio",
            "type":"Services"
        }
    ],
    "sg:phone":"+1 315 422 8134",
    "sg:postcode":"13290",
    "sg:province":"NY",
    "sg:tags":[
        "photographer",
        "photo"
    ],
    "sg:website":"www.picturepeople.com",
    "wof:name":"Picture People Inc",
    "wof:placetype":"venue"
},
  "geometry": {"coordinates":[-76.170756,43.066959],"type":"Point"}
}