{
  "type": "Feature",
  "properties": {
    "addr:full":"134 Park St Malone NY 12953",
    "addr:housenumber":"134",
    "addr:postcode":"12953",
    "addr:street":"Park St",
    "iso:country":"US",
    "sg:address":"134 Park St",
    "sg:city":"Malone",
    "sg:classifiers":[
        {
            "category":"Health Services",
            "subcategory":"Doctor",
            "type":"Services"
        }
    ],
    "sg:phone":"+1 518 483 2341",
    "sg:postcode":"12953",
    "sg:province":"NY",
    "sg:tags":[
        "medical"
    ],
    "wof:name":"Jonathan M Lowell D P C",
    "wof:placetype":"venue"
},
  "geometry": {"coordinates":[-74.291838,44.856155],"type":"Point"}
}