{
  "type": "Feature",
  "properties": {
    "addr:full":"80 Melrose Ave Lynbrook NY 11563",
    "addr:housenumber":"80",
    "addr:postcode":"11563",
    "addr:street":"Melrose Ave",
    "iso:country":"US",
    "sg:address":"80 Melrose Ave",
    "sg:city":"Lynbrook",
    "sg:classifiers":[
        {
            "category":"Manufacturing",
            "subcategory":"Textiles",
            "type":"Manufacturing & Wholesale Goods"
        }
    ],
    "sg:phone":"+1 516 596 2015",
    "sg:postcode":"11563",
    "sg:province":"NY",
    "wof:name":"International Textiles & Swng",
    "wof:placetype":"venue"
},
  "geometry": {"coordinates":[-73.663313,40.652731],"type":"Point"}
}