{
  "type": "Feature",
  "properties": {
    "addr:full":"471 Goodrich Ave North Babylon NY 11703",
    "addr:housenumber":"471",
    "addr:postcode":"11703",
    "addr:street":"Goodrich Ave North",
    "iso:country":"US",
    "sg:address":"471 Goodrich Ave",
    "sg:city":"North Babylon",
    "sg:classifiers":[
        {
            "category":"Professional",
            "type":"Services"
        }
    ],
    "sg:phone":"+1   ",
    "sg:postcode":"11703",
    "sg:province":"NY",
    "wof:name":"Pheasant Run Sportsman CL",
    "wof:placetype":"venue"
},
  "geometry": {"coordinates":[-73.326019,40.739983],"type":"Point"}
}