{
  "type": "Feature",
  "properties": {
    "iso:country":"US",
    "sg:address":"30 Glenn St",
    "sg:city":"White Plains",
    "sg:classifiers":[
        {
            "category":"Professional",
            "subcategory":"Lawyer & Legal Services",
            "type":"Services"
        }
    ],
    "sg:phone":"+1 914 684 6000",
    "sg:postcode":"10603",
    "sg:province":"NY",
    "wof:name":"Lapietra & Krieger",
    "wof:placetype":"venue"
},
  "geometry": {"coordinates":[-73.77051899999999,41.050663],"type":"Point"}
}