{
  "type": "Feature",
  "properties": {
    "iso:country":"US",
    "sg:address":"115A Wohseepee Dr",
    "sg:city":"Bay Shore",
    "sg:classifiers":[
        {
            "category":"Autos & Motor Vehicles",
            "subcategory":"Fuel & Gas Station",
            "type":"Retail Goods"
        }
    ],
    "sg:phone":"+1 631 665 4158",
    "sg:postcode":"11706",
    "sg:province":"NY",
    "sg:website":"www.hess.com",
    "wof:name":"Hess Corporation",
    "wof:placetype":"venue"
},
  "geometry": {"coordinates":[-73.273516,40.721535],"type":"Point"}
}