{
  "type": "Feature",
  "properties": {
    "addr:full":"159 Main St Nyack NY 10960",
    "addr:housenumber":"159",
    "addr:postcode":"10960",
    "addr:street":"Main St",
    "iso:country":"US",
    "sg:address":"159 Main St",
    "sg:city":"Nyack",
    "sg:classifiers":[
        {
            "category":"Personal",
            "subcategory":"Beauty Salon",
            "type":"Services"
        }
    ],
    "sg:phone":"+1 845 348 1871",
    "sg:postcode":"10960",
    "sg:province":"NY",
    "sg:tags":[
        "shop"
    ],
    "wof:name":"Creative Hair Styles",
    "wof:placetype":"venue"
},
  "geometry": {"coordinates":[-73.922009,41.091523],"type":"Point"}
}