{
  "type": "Feature",
  "properties": {
    "addr:full":"179 Nelson Rd Scarsdale NY 10583",
    "addr:housenumber":"179",
    "addr:postcode":"10583",
    "addr:street":"Nelson Rd",
    "iso:country":"US",
    "sg:address":"179 Nelson Rd",
    "sg:city":"Scarsdale",
    "sg:classifiers":[
        {
            "category":"Building & Trades",
            "subcategory":"Electrical",
            "type":"Services"
        }
    ],
    "sg:phone":"+1 914 472 3050",
    "sg:postcode":"10583",
    "sg:province":"NY",
    "sg:tags":[
        "electric",
        "contractor"
    ],
    "wof:name":"Fiorello Electric Inc",
    "wof:placetype":"venue"
},
  "geometry": {"coordinates":[-73.797397,40.978801],"type":"Point"}
}