{
  "type": "Feature",
  "properties": {
    "iso:country":"US",
    "sg:address":"96 S Depot St",
    "sg:city":"Owego",
    "sg:classifiers":[
        {
            "category":"Home & Garden",
            "subcategory":"Household Appliances",
            "type":"Retail Goods"
        }
    ],
    "sg:phone":"+1   ",
    "sg:postcode":"13827",
    "sg:province":"NY",
    "wof:name":"James Legursky",
    "wof:placetype":"venue"
},
  "geometry": {"coordinates":[-76.262253,42.107792],"type":"Point"}
}