{
  "type": "Feature",
  "properties": {
    "addr:full":"170 Old Country Rd Mineola NY 11501",
    "addr:housenumber":"170",
    "addr:postcode":"11501",
    "addr:street":"Old Country Rd",
    "iso:country":"US",
    "sg:address":"170 Old Country Rd",
    "sg:city":"Mineola",
    "sg:classifiers":[
        {
            "category":"Professional",
            "subcategory":"Lawyer & Legal Services",
            "type":"Services"
        }
    ],
    "sg:phone":"+1   ",
    "sg:postcode":"11501",
    "sg:province":"NY",
    "wof:name":"Lloyd J Nadel",
    "wof:placetype":"venue"
},
  "geometry": {"coordinates":[-73.62688,40.741282],"type":"Point"}
}