{
  "type": "Feature",
  "properties": {
    "addr:full":"3 Ridgeway Dr Great Neck NY 11024",
    "addr:housenumber":"3",
    "addr:postcode":"11024",
    "addr:street":"Ridgeway Dr",
    "iso:country":"US",
    "sg:address":"3 Ridgeway Dr",
    "sg:city":"Great Neck",
    "sg:classifiers":[
        {
            "category":"Professional",
            "subcategory":"Lawyer & Legal Services",
            "type":"Services"
        }
    ],
    "sg:phone":"+1 516 466 3045",
    "sg:postcode":"11024",
    "sg:province":"NY",
    "sg:tags":[
        "attorney"
    ],
    "wof:name":"Jerome I Katz",
    "wof:placetype":"venue"
},
  "geometry": {"coordinates":[-73.74118799999999,40.811526],"type":"Point"}
}