{
  "type": "Feature",
  "properties": {
    "iso:country":"US",
    "sg:address":"104 E 125th St",
    "sg:city":"New York",
    "sg:classifiers":[
        {
            "category":"Shopping",
            "subcategory":"Discount & Variety Stores",
            "type":"Retail Goods"
        }
    ],
    "sg:phone":"+1 212 987 4500",
    "sg:postcode":"10035",
    "sg:province":"NY",
    "wof:name":"Ly Ba 99 Cents Plus Inc",
    "wof:placetype":"venue"
},
  "geometry": {"coordinates":[-73.937583,40.80438],"type":"Point"}
}