{
  "type": "Feature",
  "properties": {
    "iso:country":"US",
    "sg:address":"49 Mohawk Ave",
    "sg:city":"Schenectady",
    "sg:classifiers":[
        {
            "category":"Restaurant",
            "type":"Food & Drink"
        }
    ],
    "sg:menulink":"http://www.allmenus.com/ny/glenville/31445-scotia-diner/menu/",
    "sg:phone":"+1 518 382 7796",
    "sg:postcode":"12302",
    "sg:province":"NY",
    "sg:tags":[
        "american",
        "diner"
    ],
    "wof:name":"Scotia Diner",
    "wof:placetype":"venue"
},
  "geometry": {"coordinates":[-73.96146299999999,42.824717],"type":"Point"}
}