{
  "type": "Feature",
  "properties": {
    "iso:country":"US",
    "sg:address":"216 E Jericho Tpke",
    "sg:city":"Mineola",
    "sg:classifiers":[
        {
            "category":"Professional",
            "type":"Services"
        }
    ],
    "sg:phone":"+1 516 747 4354",
    "sg:postcode":"11501",
    "sg:province":"NY",
    "sg:tags":[
        "caterer"
    ],
    "wof:name":"Vita Catering",
    "wof:placetype":"venue"
},
  "geometry": {"coordinates":[-73.62840300000001,40.753201],"type":"Point"}
}