{
  "type": "Feature",
  "properties": {
    "addr:full":"96 Merrick Rd Lynbrook NY 11563",
    "addr:housenumber":"96",
    "addr:postcode":"11563",
    "addr:street":"Merrick Rd",
    "iso:country":"US",
    "sg:address":"96 Merrick Rd",
    "sg:city":"Lynbrook",
    "sg:classifiers":[
        {
            "category":"Professional",
            "subcategory":"Management & Consulting",
            "type":"Services"
        }
    ],
    "sg:phone":"+1 516 596 0900",
    "sg:postcode":"11563",
    "sg:province":"NY",
    "sg:tags":[
        "consultant"
    ],
    "wof:name":"M R J Management Corp",
    "wof:placetype":"venue"
},
  "geometry": {"coordinates":[-73.66088000000001,40.658426],"type":"Point"}
}