{
  "type": "Feature",
  "properties": {
    "addr:full":"29 Maple Ave Schenectady NY 12302",
    "addr:housenumber":"29",
    "addr:postcode":"12302",
    "addr:street":"Maple Ave",
    "iso:country":"US",
    "sg:address":"29 Maple Ave",
    "sg:city":"Schenectady",
    "sg:classifiers":[
        {
            "category":"Freight",
            "type":"Transportation"
        }
    ],
    "sg:phone":"+1 518 372 9952",
    "sg:postcode":"12302",
    "sg:province":"NY",
    "sg:tags":[
        "storage",
        "commercial",
        "special",
        "contractor"
    ],
    "wof:name":"Scotia Lock Up",
    "wof:placetype":"venue"
},
  "geometry": {"coordinates":[-73.92739899999999,42.842201],"type":"Point"}
}