{
  "type": "Feature",
  "properties": {
    "addr:full":"191 Grand St New York NY 10013",
    "addr:housenumber":"191",
    "addr:postcode":"10013",
    "addr:street":"Grand St",
    "iso:country":"US",
    "sg:address":"191 Grand St",
    "sg:city":"New York",
    "sg:classifiers":[
        {
            "category":"Restaurant",
            "type":"Food & Drink"
        }
    ],
    "sg:phone":"+1 212 966 0555",
    "sg:postcode":"10013",
    "sg:province":"NY",
    "sg:tags":[
        "italian"
    ],
    "wof:name":"Novella Ristorante",
    "wof:placetype":"venue"
},
  "geometry": {"coordinates":[-73.997221,40.718988],"type":"Point"}
}