{
  "type": "Feature",
  "properties": {
    "iso:country":"US",
    "sg:address":"55 Chappell St",
    "sg:city":"Brockport",
    "sg:classifiers":[
        {
            "category":"Wholesale",
            "subcategory":"Durable Goods & Equipment",
            "type":"Manufacturing & Wholesale Goods"
        }
    ],
    "sg:phone":"+1 585 637 7936",
    "sg:postcode":"14420",
    "sg:province":"NY",
    "sg:tags":[
        "representative",
        "manufacturer"
    ],
    "wof:name":"Fox & Cook Assoc",
    "wof:placetype":"venue"
},
  "geometry": {"coordinates":[-77.943212,43.208318],"type":"Point"}
}