{
  "type": "Feature",
  "properties": {
    "addr:full":"120 Delancey St New York NY 10002",
    "addr:housenumber":"120",
    "addr:postcode":"10002",
    "addr:street":"Delancey St",
    "iso:country":"US",
    "sg:address":"120 Delancey St",
    "sg:city":"New York",
    "sg:classifiers":[
        {
            "category":"Shopping",
            "subcategory":"Clothing, Apparel, & Fashions",
            "type":"Retail Goods"
        }
    ],
    "sg:phone":"+1   ",
    "sg:postcode":"10002",
    "sg:province":"NY",
    "wof:name":"Top Secret Outlet",
    "wof:placetype":"venue"
},
  "geometry": {"coordinates":[-73.98756299999999,40.718434],"type":"Point"}
}