{
  "type": "Feature",
  "properties": {
    "iso:country":"US",
    "sg:address":"139 Flatbush Ave",
    "sg:city":"Brooklyn",
    "sg:classifiers":[
        {
            "category":"Home & Garden",
            "subcategory":"Furniture",
            "type":"Retail Goods"
        }
    ],
    "sg:phone":"+1 718 398 1726",
    "sg:postcode":"11217",
    "sg:province":"NY",
    "sg:tags":[
        "mattress"
    ],
    "sg:website":"www.rockawaybedding.com",
    "wof:name":"Rockaway Bedding",
    "wof:placetype":"venue"
},
  "geometry": {"coordinates":[-73.97762299999999,40.684524],"type":"Point"}
}