{
  "type": "Feature",
  "properties": {
    "addr:full":"5301 Vernon Blvd Long Island City NY 11101",
    "addr:housenumber":"5301",
    "addr:postcode":"11101",
    "addr:street":"Vernon Blvd",
    "iso:country":"US",
    "sg:address":"5301 Vernon Blvd",
    "sg:city":"Long Island City",
    "sg:classifiers":[
        {
            "category":"Building & Trades",
            "subcategory":"Electrical",
            "type":"Services"
        }
    ],
    "sg:phone":"+1 718 361 0574",
    "sg:postcode":"11101",
    "sg:province":"NY",
    "sg:tags":[
        "electrician"
    ],
    "wof:name":"Shelter Electric",
    "wof:placetype":"venue"
},
  "geometry": {"coordinates":[-73.954697,40.740299],"type":"Point"}
}