{
  "type": "Feature",
  "properties": {
    "addr:full":"9815 Roosevelt Ave Corona NY 11368",
    "addr:housenumber":"9815",
    "addr:postcode":"11368",
    "addr:street":"Roosevelt Ave",
    "iso:country":"US",
    "sg:address":"9815 Roosevelt Ave",
    "sg:city":"Corona",
    "sg:classifiers":[
        {
            "category":"Insurance",
            "subcategory":"Insurance Agent",
            "type":"Services"
        },
        {
            "category":"Insurance",
            "subcategory":"Hazard Insurance",
            "type":"Services"
        }
    ],
    "sg:phone":"+1 718 639 7729",
    "sg:postcode":"11368",
    "sg:province":"NY",
    "sg:tags":[
        "auto",
        "recreational",
        "motorcycle",
        "vehicle",
        "marine",
        "boat"
    ],
    "wof:name":"Pozo-Cohen Agency, Inc.",
    "wof:placetype":"venue"
},
  "geometry": {"coordinates":[-73.83847,40.757074],"type":"Point"}
}