{
  "type": "Feature",
  "properties": {
    "iso:country":"US",
    "sg:address":"30 Main St",
    "sg:city":"Petersburg",
    "sg:classifiers":[
        {
            "category":"Wholesale",
            "subcategory":"Medical Equipment & Supplies",
            "type":"Manufacturing & Wholesale Goods"
        },
        {
            "category":"Shopping",
            "subcategory":"Pharmacy",
            "type":"Retail Goods"
        }
    ],
    "sg:phone":"+1 518 658 3357",
    "sg:postcode":"12138",
    "sg:province":"NY",
    "sg:tags":[
        "home",
        "health",
        "care"
    ],
    "wof:name":"Empire X Ray",
    "wof:placetype":"venue"
},
  "geometry": {"coordinates":[-73.339203,42.74963],"type":"Point"}
}