{
  "type": "Feature",
  "properties": {
    "addr:full":"285 Lexington Ave New York NY 11415",
    "addr:housenumber":"285",
    "addr:postcode":"11415",
    "addr:street":"Lexington Ave",
    "iso:country":"US",
    "sg:address":"285 Lexington Ave",
    "sg:city":"New York",
    "sg:classifiers":[
        {
            "category":"Health Services",
            "subcategory":"Doctor",
            "type":"Services"
        },
        {
            "category":"Health Services",
            "subcategory":"Health Practitioner",
            "type":"Services"
        }
    ],
    "sg:phone":"+1 718 847 7278",
    "sg:postcode":"11415",
    "sg:province":"NY",
    "sg:tags":[
        "acupuncture"
    ],
    "sg:website":"www.hands-onhealth.org",
    "wof:name":"Hands-On Health Wholistic Center",
    "wof:placetype":"venue"
},
  "geometry": {"coordinates":[-73.978116,40.748026],"type":"Point"}
}