{
  "type": "Feature",
  "properties": {
    "iso:country":"US",
    "sg:address":"41 W 47 St",
    "sg:city":"New York",
    "sg:classifiers":[
        {
            "category":"Shopping",
            "subcategory":"Jewelry",
            "type":"Retail Goods"
        }
    ],
    "sg:phone":"+1 212 869 0838",
    "sg:postcode":"10036",
    "sg:province":"NY",
    "sg:tags":[
        "jeweler"
    ],
    "wof:name":"Mike & Sons Jewelry",
    "wof:placetype":"venue"
},
  "geometry": {"coordinates":[-73.98075900000001,40.757529],"type":"Point"}
}