{
  "type": "Feature",
  "properties": {
    "iso:country":"US",
    "sg:address":"19 Lakeside Dr",
    "sg:city":"Rye",
    "sg:classifiers":[
        {
            "category":"Manufacturing",
            "subcategory":"Chemicals & Compounds",
            "type":"Manufacturing & Wholesale Goods"
        }
    ],
    "sg:phone":"+1   ",
    "sg:postcode":"10580",
    "sg:province":"NY",
    "sg:tags":[
        "mfg",
        "perfume"
    ],
    "wof:name":"Virtue Group Inc",
    "wof:placetype":"venue"
},
  "geometry": {"coordinates":[-73.685987,40.997363],"type":"Point"}
}