{
  "type": "Feature",
  "properties": {
    "iso:country":"US",
    "sg:address":"85 N Central Ave",
    "sg:city":"Valley Stream",
    "sg:classifiers":[
        {
            "category":"Retail",
            "subcategory":"Auto Repair",
            "type":"Services"
        }
    ],
    "sg:phone":"+1 516 791 1198",
    "sg:postcode":"11580",
    "sg:province":"NY",
    "sg:tags":[
        "wrecker"
    ],
    "wof:name":"Sabo Towing Svc",
    "wof:placetype":"venue"
},
  "geometry": {"coordinates":[-73.70837299999999,40.670438],"type":"Point"}
}