{
  "type": "Feature",
  "properties": {
    "addr:full":"155 E 34th St Frnt 1 New York NY 10016",
    "addr:housenumber":"155;1",
    "addr:postcode":"10016",
    "addr:street":"E 34Th St Frnt",
    "iso:country":"US",
    "sg:address":"155 E 34th St Frnt 1",
    "sg:city":"New York",
    "sg:classifiers":[
        {
            "category":"Shopping",
            "subcategory":"Pharmacy",
            "type":"Retail Goods"
        }
    ],
    "sg:phone":"+1 212 683 3051",
    "sg:postcode":"10016",
    "sg:province":"NY",
    "sg:tags":[
        "drugstore"
    ],
    "wof:name":"Duanereade",
    "wof:placetype":"venue"
},
  "geometry": {"coordinates":[-73.979111,40.746306],"type":"Point"}
}