{
  "type": "Feature",
  "properties": {
    "addr:full":"175 Bedford Avenue Brooklyn NY 11211",
    "addr:housenumber":"175",
    "addr:postcode":"11211",
    "addr:street":"Bedford Avenue",
    "iso:country":"US",
    "sg:address":"175 Bedford Avenue",
    "sg:city":"Brooklyn",
    "sg:classifiers":[
        {
            "category":"Banks & Credit Unions",
            "subcategory":"Bank",
            "type":"Services"
        }
    ],
    "sg:phone":"+1 718 486 3599",
    "sg:postcode":"11211",
    "sg:province":"NY",
    "wof:name":"Cross County Federal Savings Bank",
    "wof:placetype":"venue"
},
  "geometry": {"coordinates":[-73.95737,40.717979],"type":"Point"}
}