{
  "type": "Feature",
  "properties": {
    "iso:country":"US",
    "sg:address":"54 S Shore Rd",
    "sg:city":"Cuba",
    "sg:classifiers":[
        {
            "category":"Wholesale",
            "subcategory":"Furniture",
            "type":"Manufacturing & Wholesale Goods"
        }
    ],
    "sg:phone":"+1 585 968 1834",
    "sg:postcode":"14727",
    "sg:province":"NY",
    "sg:tags":[
        "contract"
    ],
    "wof:name":"Plants and Company Inc",
    "wof:placetype":"venue"
},
  "geometry": {"coordinates":[-78.29821099999999,42.24493],"type":"Point"}
}