{
  "type": "Feature",
  "properties": {
    "addr:full":"6655 Booth Street Suite 1 Rego Park NY 11374",
    "addr:housenumber":"6655",
    "addr:postcode":"11374",
    "addr:street":"Booth Street Suite 1",
    "iso:country":"US",
    "sg:address":"6655 Booth Street Suite 1",
    "sg:city":"Rego Park",
    "sg:classifiers":[
        {
            "category":"Health Services",
            "subcategory":"Dentist",
            "type":"Services"
        }
    ],
    "sg:phone":"+1 718 896 9118",
    "sg:postcode":"11374",
    "sg:province":"NY",
    "wof:name":"Rosenfield Robert DDS",
    "wof:placetype":"venue"
},
  "geometry": {"coordinates":[-73.86085,40.728579],"type":"Point"}
}