{
  "type": "Feature",
  "properties": {
    "iso:country":"US",
    "sg:address":"821 Forest Ave",
    "sg:city":"Fulton",
    "sg:classifiers":[
        {
            "category":"Professional",
            "subcategory":"Management & Consulting",
            "type":"Services"
        }
    ],
    "sg:phone":"+1 315 598 9662",
    "sg:postcode":"13069",
    "sg:province":"NY",
    "sg:tags":[
        "business"
    ],
    "wof:name":"Educational Resources Inc",
    "wof:placetype":"venue"
},
  "geometry": {"coordinates":[-76.400104,43.304771],"type":"Point"}
}