{
  "type": "Feature",
  "properties": {
    "addr:full":"1468 Route 9 Wappingers Falls NY 12590",
    "addr:housenumber":"1468",
    "addr:postcode":"12590",
    "addr:street":"Route 9",
    "iso:country":"US",
    "sg:address":"1468 Route 9",
    "sg:city":"Wappingers Falls",
    "sg:classifiers":[
        {
            "category":"Personal",
            "type":"Services"
        }
    ],
    "sg:phone":"+1 845 298 0042",
    "sg:postcode":"12590",
    "sg:province":"NY",
    "sg:tags":[
        "towing"
    ],
    "wof:name":"Marty's Automotive",
    "wof:placetype":"venue"
},
  "geometry": {"coordinates":[-73.90930299999999,41.573436],"type":"Point"}
}