{
  "type": "Feature",
  "properties": {
    "iso:country":"US",
    "sg:address":"2023 Jericho Tpke",
    "sg:city":"Elwood",
    "sg:classifiers":[
        {
            "category":"Professional",
            "subcategory":"Computer Services",
            "type":"Services"
        }
    ],
    "sg:phone":"+1 631 462 5442",
    "sg:postcode":"11731",
    "sg:province":"NY",
    "sg:tags":[
        "repair"
    ],
    "wof:name":"PC Link Systems, Inc.",
    "wof:placetype":"venue"
},
  "geometry": {"coordinates":[-73.32732900000001,40.838735],"type":"Point"}
}