{
  "type": "Feature",
  "properties": {
    "iso:country":"US",
    "sg:address":"862 E 136th St",
    "sg:city":"Bronx",
    "sg:classifiers":[
        {
            "category":"Building & Trades",
            "subcategory":"Plumbing",
            "type":"Services"
        }
    ],
    "sg:phone":"+1 718 292 1107",
    "sg:postcode":"10454",
    "sg:province":"NY",
    "sg:tags":[
        "clean",
        "cleaning",
        "boilers-repair",
        "boiler"
    ],
    "wof:name":"Jrs Boiler",
    "wof:placetype":"venue"
},
  "geometry": {"coordinates":[-73.909845,40.80173],"type":"Point"}
}