{
  "type": "Feature",
  "properties": {
    "addr:full":"4912 Vernon Blvd Long Island City NY 11101",
    "addr:housenumber":"4912",
    "addr:postcode":"11101",
    "addr:street":"Vernon Blvd",
    "iso:country":"US",
    "sg:address":"4912 Vernon Blvd",
    "sg:city":"Long Island City",
    "sg:classifiers":[
        {
            "category":"Building & Trades",
            "subcategory":"Locksmith",
            "type":"Services"
        }
    ],
    "sg:phone":"+1 718 807 4294",
    "sg:postcode":"11101",
    "sg:province":"NY",
    "sg:tags":[
        "key"
    ],
    "wof:name":"Full Service Locksmith",
    "wof:placetype":"venue"
},
  "geometry": {"coordinates":[-73.953903,40.743301],"type":"Point"}
}