{
  "type": "Feature",
  "properties": {
    "iso:country":"US",
    "sg:address":"108 Browns Rd",
    "sg:city":"Nesconset",
    "sg:classifiers":[
        {
            "category":"Retail",
            "subcategory":"Auto Repair",
            "type":"Services"
        }
    ],
    "sg:phone":"+1 631 360 8326",
    "sg:postcode":"11767",
    "sg:province":"NY",
    "wof:name":"Zorn Automotive Bob",
    "wof:placetype":"venue"
},
  "geometry": {"coordinates":[-73.149002,40.856701],"type":"Point"}
}