{
  "type": "Feature",
  "properties": {
    "iso:country":"US",
    "sg:address":"19 Shinnecock Ave",
    "sg:city":"East Quogue",
    "sg:classifiers":[
        {
            "category":"Professional",
            "subcategory":"Business Services",
            "type":"Services"
        }
    ],
    "sg:phone":"+1 631 723 0062",
    "sg:postcode":"11942",
    "sg:province":"NY",
    "sg:tags":[
        "pool",
        "swimming"
    ],
    "wof:name":"Southampton Pool Svc",
    "wof:placetype":"venue"
},
  "geometry": {"coordinates":[-72.564137,40.859847],"type":"Point"}
}