{
  "type": "Feature",
  "properties": {
    "addr:full":"153 Woodcleft Ave Freeport NY 11520",
    "addr:housenumber":"153",
    "addr:postcode":"11520",
    "addr:street":"Woodcleft Ave",
    "iso:country":"US",
    "sg:address":"153 Woodcleft Ave",
    "sg:city":"Freeport",
    "sg:classifiers":[
        {
            "category":"Shopping",
            "subcategory":"Gifts & Souvenirs",
            "type":"Retail Goods"
        }
    ],
    "sg:phone":"+1 516 546 0410",
    "sg:postcode":"11520",
    "sg:province":"NY",
    "sg:tags":[
        "shop"
    ],
    "wof:name":"Water Lilly's",
    "wof:placetype":"venue"
},
  "geometry": {"coordinates":[-73.582418,40.636787],"type":"Point"}
}