{
  "type": "Feature",
  "properties": {
    "iso:country":"US",
    "sg:address":"1135 Bronx River Ave",
    "sg:city":"Bronx",
    "sg:classifiers":[
        {
            "category":"Professional",
            "subcategory":"Business Services",
            "type":"Services"
        }
    ],
    "sg:phone":"+1 718 402 9700",
    "sg:postcode":"10472",
    "sg:province":"NY",
    "sg:tags":[
        "decoration",
        "christmas"
    ],
    "sg:website":"www.americanchristmasdecor.com",
    "wof:name":"American Christmas Decorations",
    "wof:placetype":"venue"
},
  "geometry": {"coordinates":[-73.883292,40.827324],"type":"Point"}
}