{
  "type": "Feature",
  "properties": {
    "addr:full":"76 Union St Montgomery NY 12549",
    "addr:housenumber":"76",
    "addr:postcode":"12549",
    "addr:street":"Union St",
    "iso:country":"US",
    "sg:address":"76 Union St",
    "sg:city":"Montgomery",
    "sg:classifiers":[
        {
            "category":"Real Estate",
            "subcategory":"Real Estate Agent",
            "type":"Services"
        }
    ],
    "sg:phone":"+1 845 457 5813",
    "sg:postcode":"12549",
    "sg:province":"NY",
    "wof:name":"Horton Land Co",
    "wof:placetype":"venue"
},
  "geometry": {"coordinates":[-74.239572,41.524185],"type":"Point"}
}