{
  "type": "Feature",
  "properties": {
    "addr:full":"2225 Whispering Pines Ln Waterloo NY 13165",
    "addr:housenumber":"2225",
    "addr:postcode":"13165",
    "addr:street":"Whispering Pines Ln",
    "iso:country":"US",
    "sg:address":"2225 Whispering Pines Ln",
    "sg:city":"Waterloo",
    "sg:classifiers":[
        {
            "category":"Manufacturing",
            "subcategory":"Buildings",
            "type":"Manufacturing & Wholesale Goods"
        }
    ],
    "sg:phone":"+1 315 789 3849",
    "sg:postcode":"13165",
    "sg:province":"NY",
    "sg:tags":[
        "log",
        "mfg",
        "prefabricated",
        "wood",
        "home",
        "cabin"
    ],
    "sg:website":"www.kuhnsbros.com",
    "wof:name":"Kuhns Brothers Log Homes Inc",
    "wof:placetype":"venue"
},
  "geometry": {"coordinates":[-76.943657,42.918206],"type":"Point"}
}