{
  "type": "Feature",
  "properties": {
    "addr:full":"227 E 30th Street New York NY 10016",
    "addr:housenumber":"227",
    "addr:postcode":"10016",
    "addr:street":"E 30Th Street",
    "iso:country":"US",
    "sg:address":"227 E 30th Street",
    "sg:city":"New York",
    "sg:classifiers":[
        {
            "category":"Professional",
            "subcategory":"Computer Services",
            "type":"Services"
        }
    ],
    "sg:phone":"+1 212 213 5552",
    "sg:postcode":"10016",
    "sg:province":"NY",
    "sg:tags":[
        "repair"
    ],
    "wof:name":"Oncall 25-8",
    "wof:placetype":"venue"
},
  "geometry": {"coordinates":[-73.977763,40.742408],"type":"Point"}
}