{
  "type": "Feature",
  "properties": {
    "iso:country":"US",
    "sg:address":"4850 State Hwy 30",
    "sg:city":"Amsterdam",
    "sg:classifiers":[
        {
            "category":"Utilities",
            "subcategory":"Cable",
            "type":"Services"
        }
    ],
    "sg:phone":"+1 518 842 3733",
    "sg:postcode":"12010",
    "sg:province":"NY",
    "sg:tags":[
        "television"
    ],
    "wof:name":"Public Access Channel 11",
    "wof:placetype":"venue"
},
  "geometry": {"coordinates":[-74.187735,42.971977],"type":"Point"}
}