{
  "type": "Feature",
  "properties": {
    "addr:full":"525 Falconer St Jamestown NY 14701",
    "addr:housenumber":"525",
    "addr:postcode":"14701",
    "addr:street":"Falconer St",
    "iso:country":"US",
    "sg:address":"525 Falconer St",
    "sg:city":"Jamestown",
    "sg:classifiers":[
        {
            "category":"Professional",
            "subcategory":"Management & Consulting",
            "type":"Services"
        }
    ],
    "sg:phone":"+1 716 665 5754",
    "sg:postcode":"14701",
    "sg:province":"NY",
    "sg:tags":[
        "consultant",
        "business"
    ],
    "wof:name":"Small Business Development Ctr",
    "wof:placetype":"venue"
},
  "geometry": {"coordinates":[-79.21713699999999,42.113954],"type":"Point"}
}