{
  "type": "Feature",
  "properties": {
    "addr:full":"410 Saracino Dr Maybrook NY 12543",
    "addr:housenumber":"410",
    "addr:postcode":"12543",
    "addr:street":"Saracino Dr",
    "iso:country":"US",
    "sg:address":"410 Saracino Dr",
    "sg:city":"Maybrook",
    "sg:classifiers":[
        {
            "category":"Social Services",
            "type":"Services"
        }
    ],
    "sg:phone":"+1 845 427 5869",
    "sg:postcode":"12543",
    "sg:province":"NY",
    "sg:tags":[
        "referral"
    ],
    "wof:name":"WEIS Referral Svc",
    "wof:placetype":"venue"
},
  "geometry": {"coordinates":[-74.213765,41.497685],"type":"Point"}
}