{
  "type": "Feature",
  "properties": {
    "addr:full":"413 Knickerbocker Ave Brooklyn NY 11237",
    "addr:housenumber":"413",
    "addr:postcode":"11237",
    "addr:street":"Knickerbocker Ave",
    "iso:country":"US",
    "sg:address":"413 Knickerbocker Ave",
    "sg:city":"Brooklyn",
    "sg:classifiers":[
        {
            "category":"Shopping",
            "subcategory":"Discount & Variety Stores",
            "type":"Retail Goods"
        }
    ],
    "sg:phone":"+1   ",
    "sg:postcode":"11237",
    "sg:province":"NY",
    "wof:name":"Hyun Store",
    "wof:placetype":"venue"
},
  "geometry": {"coordinates":[-73.91943499999999,40.699529],"type":"Point"}
}