{
  "type": "Feature",
  "properties": {
    "addr:full":"6120 18th Ave Brooklyn NY 11204",
    "addr:housenumber":"6120",
    "addr:postcode":"11204",
    "addr:street":"18Th Ave",
    "iso:country":"US",
    "sg:address":"6120 18th Ave",
    "sg:city":"Brooklyn",
    "sg:classifiers":[
        {
            "category":"Real Estate",
            "subcategory":"Real Estate Operator",
            "type":"Services"
        }
    ],
    "sg:phone":"+1 718 259 8045",
    "sg:postcode":"11204",
    "sg:province":"NY",
    "sg:tags":[
        "building",
        "ope",
        "apartment",
        "nonresidential"
    ],
    "wof:name":"Shalosh Associates",
    "wof:placetype":"venue"
},
  "geometry": {"coordinates":[-73.98839,40.621033],"type":"Point"}
}