{
  "type": "Feature",
  "properties": {
    "addr:full":"53 Stanton St New York NY 10002",
    "addr:housenumber":"53",
    "addr:postcode":"10002",
    "addr:street":"Stanton St",
    "iso:country":"US",
    "sg:address":"53 Stanton St",
    "sg:city":"New York",
    "sg:classifiers":[
        {
            "category":"Banks & Credit Unions",
            "subcategory":"Bank",
            "type":"Services"
        }
    ],
    "sg:phone":"+1 212 780 9398",
    "sg:postcode":"10002",
    "sg:province":"NY",
    "sg:tags":[
        "short",
        "institution",
        "business"
    ],
    "wof:name":"A To Z Merchants Services",
    "wof:placetype":"venue"
},
  "geometry": {"coordinates":[-73.990509,40.722024],"type":"Point"}
}