{
  "type": "Feature",
  "properties": {
    "addr:full":"291 Long Beach Rd Oceanside NY 11572",
    "addr:housenumber":"291",
    "addr:postcode":"11572",
    "addr:street":"Long Beach Rd",
    "iso:country":"US",
    "sg:address":"291 Long Beach Rd",
    "sg:city":"Oceanside",
    "sg:classifiers":[
        {
            "category":"Restaurant",
            "type":"Food & Drink"
        }
    ],
    "sg:phone":"+1   ",
    "sg:postcode":"11572",
    "sg:province":"NY",
    "sg:tags":[
        "eating"
    ],
    "wof:name":"Ginza Japanese Restaurant",
    "wof:placetype":"venue"
},
  "geometry": {"coordinates":[-73.639982,40.641005],"type":"Point"}
}