{
  "type": "Feature",
  "properties": {
    "iso:country":"US",
    "sg:address":"9048 Union St",
    "sg:city":"Scottsville",
    "sg:classifiers":[
        {
            "category":"Food & Beverages",
            "subcategory":"Bakery",
            "type":"Retail Goods"
        }
    ],
    "sg:phone":"+1 585 889 4576",
    "sg:postcode":"14546",
    "sg:province":"NY",
    "sg:tags":[
        "grocery"
    ],
    "wof:name":"A Bakery Creation",
    "wof:placetype":"venue"
},
  "geometry": {"coordinates":[-77.796898,43.036999],"type":"Point"}
}