{
  "type": "Feature",
  "properties": {
    "iso:country":"US",
    "sg:address":"1558 Hempstead Tpke",
    "sg:city":"Elmont",
    "sg:classifiers":[
        {
            "category":"Personal",
            "subcategory":"Beauty Salon",
            "type":"Services"
        }
    ],
    "sg:phone":"+1 516 327 3048",
    "sg:postcode":"11003",
    "sg:province":"NY",
    "wof:name":"Blue Flame II Salon",
    "wof:placetype":"venue"
},
  "geometry": {"coordinates":[-73.697267,40.707019],"type":"Point"}
}