{
  "type": "Feature",
  "properties": {
    "iso:country":"US",
    "sg:address":"2800 E Henrietta Rd",
    "sg:city":"Rochester",
    "sg:classifiers":[
        {
            "category":"Shopping",
            "type":"Retail Goods"
        }
    ],
    "sg:phone":"+1 585 533 0022",
    "sg:postcode":"14467",
    "sg:province":"NY",
    "sg:tags":[
        "equipment",
        "telephone",
        "supply"
    ],
    "wof:name":"T R Svc Inc",
    "wof:placetype":"venue"
},
  "geometry": {"coordinates":[-77.607743,43.068707],"type":"Point"}
}