{
  "type": "Feature",
  "properties": {
    "addr:full":"33 W 60th St New York NY 10023",
    "addr:housenumber":"33",
    "addr:postcode":"10023",
    "addr:street":"W 60Th St",
    "iso:country":"US",
    "sg:address":"33 W 60th St",
    "sg:city":"New York",
    "sg:classifiers":[
        {
            "category":"Arts & Performance",
            "subcategory":"Theater",
            "type":"Entertainment"
        },
        {
            "category":"Manufacturing",
            "subcategory":"Printing",
            "type":"Manufacturing & Wholesale Goods"
        }
    ],
    "sg:phone":"+1 212 262 5161",
    "sg:postcode":"10023",
    "sg:province":"NY",
    "sg:tags":[
        "publisher",
        "for",
        "national",
        "orchestra",
        "symphony",
        "music",
        "organization"
    ],
    "wof:name":"American Symphony Orchestra",
    "wof:placetype":"venue"
},
  "geometry": {"coordinates":[-73.983728,40.769601],"type":"Point"}
}