{
  "type": "Feature",
  "properties": {
    "iso:country":"US",
    "sg:address":"1107 New Loudon Rd",
    "sg:city":"Cohoes",
    "sg:classifiers":[
        {
            "category":"Manufacturing",
            "subcategory":"Tools & Machinery",
            "type":"Manufacturing & Wholesale Goods"
        }
    ],
    "sg:phone":"+1 518 785 6692",
    "sg:postcode":"12047",
    "sg:province":"NY",
    "sg:tags":[
        "pump"
    ],
    "sg:website":"www.emerickassociates.com",
    "wof:name":"Emerick Associates Inc",
    "wof:placetype":"venue"
},
  "geometry": {"coordinates":[-73.74097399999999,42.786053],"type":"Point"}
}