{
  "type": "Feature",
  "properties": {
    "iso:country":"US",
    "sg:address":"60 N Harrison Ave",
    "sg:city":"Congers",
    "sg:classifiers":[
        {
            "category":"Building & Trades",
            "subcategory":"Cleaning & Sanitation",
            "type":"Services"
        }
    ],
    "sg:phone":"+1 845 268 5660",
    "sg:postcode":"10920",
    "sg:province":"NY",
    "sg:tags":[
        "floor",
        "fire",
        "damage",
        "water",
        "waxing",
        "restoration",
        "polishing"
    ],
    "sg:website":"http://www.amhrestoration.com",
    "wof:name":"AMH Restoration",
    "wof:placetype":"venue"
},
  "geometry": {"coordinates":[-73.94233699999999,41.154519],"type":"Point"}
}