{
  "type": "Feature",
  "properties": {
    "iso:country":"US",
    "sg:address":"6640 Old Lake Shore Rd",
    "sg:city":"Derby",
    "sg:classifiers":[
        {
            "category":"Real Estate",
            "subcategory":"Real Estate Operator",
            "type":"Services"
        }
    ],
    "sg:phone":"+1 716 947 4446",
    "sg:postcode":"14047",
    "sg:province":"NY",
    "sg:tags":[
        "building",
        "nonresidential"
    ],
    "wof:name":"Hj Properties",
    "wof:placetype":"venue"
},
  "geometry": {"coordinates":[-78.98214299999999,42.706865],"type":"Point"}
}