{
  "type": "Feature",
  "properties": {
    "iso:country":"US",
    "sg:address":"30 Troon Rd",
    "sg:city":"East Aurora",
    "sg:classifiers":[
        {
            "category":"Real Estate",
            "subcategory":"Real Estate Operator",
            "type":"Services"
        }
    ],
    "sg:phone":"+1 716 655 4299",
    "sg:postcode":"14052",
    "sg:province":"NY",
    "sg:tags":[
        "building",
        "nonresidential"
    ],
    "wof:name":"Lewmar Properties LLC",
    "wof:placetype":"venue"
},
  "geometry": {"coordinates":[-78.665615,42.784871],"type":"Point"}
}