{
  "type": "Feature",
  "properties": {
    "addr:full":"2916 36th Ave Long Island City NY 11106",
    "addr:housenumber":"2916",
    "addr:postcode":"11106",
    "addr:street":"36Th Ave",
    "iso:country":"US",
    "sg:address":"2916 36th Ave",
    "sg:city":"Long Island City",
    "sg:classifiers":[
        {
            "category":"Food & Beverages",
            "subcategory":"Meat & Fish",
            "type":"Retail Goods"
        }
    ],
    "sg:phone":"+1 800 784 1313",
    "sg:postcode":"11106",
    "sg:province":"NY",
    "sg:tags":[
        "shop"
    ],
    "wof:name":"Mike's Meat Mkt & Grcy",
    "wof:placetype":"venue"
},
  "geometry": {"coordinates":[-73.931298,40.757153],"type":"Point"}
}