{
  "type": "Feature",
  "properties": {
    "addr:full":"102 Main St Tuckahoe NY 10707",
    "addr:housenumber":"102",
    "addr:postcode":"10707",
    "addr:street":"Main St",
    "iso:country":"US",
    "sg:address":"102 Main St",
    "sg:city":"Tuckahoe",
    "sg:classifiers":[
        {
            "category":"Personal",
            "subcategory":"Beauty Salon",
            "type":"Services"
        }
    ],
    "sg:phone":"+1 914 337 4057",
    "sg:postcode":"10707",
    "sg:province":"NY",
    "wof:name":"Salon Delian",
    "wof:placetype":"venue"
},
  "geometry": {"coordinates":[-73.825462,40.949471],"type":"Point"}
}