{
  "type": "Feature",
  "properties": {
    "iso:country":"US",
    "sg:address":"4103 Clinton St",
    "sg:city":"Buffalo",
    "sg:classifiers":[
        {
            "category":"Professional",
            "subcategory":"Art Services",
            "type":"Services"
        }
    ],
    "sg:phone":"+1 716 826 1855",
    "sg:postcode":"14224",
    "sg:province":"NY",
    "sg:tags":[
        "graphic",
        "designer"
    ],
    "wof:name":"Digi-Books Montage Studio",
    "wof:placetype":"venue"
},
  "geometry": {"coordinates":[-78.730268,42.857051],"type":"Point"}
}