{
  "type": "Feature",
  "properties": {
    "addr:full":"829 Trinity Ave Bronx NY 10456",
    "addr:housenumber":"829",
    "addr:postcode":"10456",
    "addr:street":"Trinity Ave",
    "iso:country":"US",
    "sg:address":"829 Trinity Ave",
    "sg:city":"Bronx",
    "sg:classifiers":[
        {
            "category":"Building & Trades",
            "subcategory":"Equipment Rental",
            "type":"Services"
        }
    ],
    "sg:phone":"+1 212 965 1046",
    "sg:postcode":"10456",
    "sg:province":"NY",
    "sg:tags":[
        "player",
        "recorder",
        "video"
    ],
    "wof:name":"Ramdon Access Film Video Svc",
    "wof:placetype":"venue"
},
  "geometry": {"coordinates":[-73.907194,40.819981],"type":"Point"}
}