{
  "type": "Feature",
  "properties": {
    "addr:full":"1221 Jerome Ave Bronx NY 10452",
    "addr:housenumber":"1221",
    "addr:postcode":"10452",
    "addr:street":"Jerome Ave",
    "iso:country":"US",
    "sg:address":"1221 Jerome Ave",
    "sg:city":"Bronx",
    "sg:classifiers":[
        {
            "category":"Arts & Performance",
            "subcategory":"Theater",
            "type":"Entertainment"
        }
    ],
    "sg:phone":"+1 718 590 0800",
    "sg:postcode":"10452",
    "sg:province":"NY",
    "sg:tags":[
        "entertainer"
    ],
    "wof:name":"ELG House Of Joy",
    "wof:placetype":"venue"
},
  "geometry": {"coordinates":[-73.92348699999999,40.835258],"type":"Point"}
}