{
  "type": "Feature",
  "properties": {
    "iso:country":"US",
    "sg:address":"2249 85th St",
    "sg:city":"Brooklyn",
    "sg:classifiers":[
        {
            "category":"Restaurant",
            "type":"Food & Drink"
        }
    ],
    "sg:phone":"+1   ",
    "sg:postcode":"11214",
    "sg:province":"NY",
    "sg:tags":[
        "eating"
    ],
    "wof:name":"Red Zone Global Inc",
    "wof:placetype":"venue"
},
  "geometry": {"coordinates":[-73.991754,40.601904],"type":"Point"}
}