{
  "type": "Feature",
  "properties": {
    "addr:full":"674 State Hwy 304 New City NY 10956",
    "addr:housenumber":"674",
    "addr:postcode":"10956",
    "addr:street":"State Hwy 304",
    "iso:country":"US",
    "sg:address":"674 State Hwy 304",
    "sg:city":"New City",
    "sg:classifiers":[
        {
            "category":"Building & Trades",
            "subcategory":"Construction",
            "type":"Services"
        }
    ],
    "sg:phone":"+1 845 638 3554",
    "sg:postcode":"10956",
    "sg:province":"NY",
    "sg:tags":[
        "coping",
        "plastering",
        "tiling",
        "pool",
        "swimming"
    ],
    "wof:name":"Blanchard Pool Svc",
    "wof:placetype":"venue"
},
  "geometry": {"coordinates":[-73.992492,41.123256],"type":"Point"}
}