{
  "type": "Feature",
  "properties": {
    "addr:full":"129 Fulton St New York NY 10038",
    "addr:housenumber":"129",
    "addr:postcode":"10038",
    "addr:street":"Fulton St",
    "iso:country":"US",
    "sg:address":"129 Fulton St",
    "sg:city":"New York",
    "sg:classifiers":[
        {
            "category":"Social Services",
            "type":"Services"
        }
    ],
    "sg:phone":"+1   ",
    "sg:postcode":"10038",
    "sg:province":"NY",
    "wof:name":"Coalition For The Homeless",
    "wof:placetype":"venue"
},
  "geometry": {"coordinates":[-74.007329,40.710034],"type":"Point"}
}