{
  "type": "Feature",
  "properties": {
    "addr:full":"424 Broadway New York NY 10013",
    "addr:housenumber":"424",
    "addr:postcode":"10013",
    "addr:street":"Broadway",
    "iso:country":"US",
    "sg:address":"424 Broadway",
    "sg:city":"New York",
    "sg:classifiers":[
        {
            "category":"Banks & Credit Unions",
            "subcategory":"Financial Services",
            "type":"Services"
        }
    ],
    "sg:phone":"+1 646 613 9350",
    "sg:postcode":"10013",
    "sg:province":"NY",
    "sg:tags":[
        "international",
        "trade"
    ],
    "wof:name":"Gold Lin Trading",
    "wof:placetype":"venue"
},
  "geometry": {"coordinates":[-74.00151099999999,40.719666],"type":"Point"}
}