{
  "type": "Feature",
  "properties": {
    "addr:full":"228 Richmond Ave Staten Island NY 10302",
    "addr:housenumber":"228",
    "addr:postcode":"10302",
    "addr:street":"Richmond Ave",
    "iso:country":"US",
    "sg:address":"228 Richmond Ave",
    "sg:city":"Staten Island",
    "sg:classifiers":[
        {
            "category":"Shopping",
            "subcategory":"Clothing, Apparel, & Fashions",
            "type":"Retail Goods"
        }
    ],
    "sg:phone":"+1   ",
    "sg:postcode":"10302",
    "sg:province":"NY",
    "wof:name":"Lane Bryant",
    "wof:placetype":"venue"
},
  "geometry": {"coordinates":[-74.135199,40.635542],"type":"Point"}
}