{
  "type": "Feature",
  "properties": {
    "iso:country":"US",
    "sg:address":"5500 Main St",
    "sg:city":"Williamsville",
    "sg:classifiers":[
        {
            "category":"Professional",
            "subcategory":"Business Services",
            "type":"Services"
        }
    ],
    "sg:phone":"+1 585 436 4460",
    "sg:postcode":"14221",
    "sg:province":"NY",
    "sg:tags":[
        "inspection"
    ],
    "sg:website":"www.nybfu.org",
    "wof:name":"New York Brd-Fire Underwriters",
    "wof:placetype":"venue"
},
  "geometry": {"coordinates":[-78.747851,42.962356],"type":"Point"}
}