{
  "type": "Feature",
  "properties": {
    "iso:country":"US",
    "sg:address":"340 N Central Ave",
    "sg:city":"Valley Stream",
    "sg:classifiers":[
        {
            "category":"Retail",
            "subcategory":"Auto Repair",
            "type":"Services"
        }
    ],
    "sg:phone":"+1 516 872 8729",
    "sg:postcode":"11580",
    "sg:province":"NY",
    "wof:name":"Joyal Svce Center",
    "wof:placetype":"venue"
},
  "geometry": {"coordinates":[-73.709198,40.6763],"type":"Point"}
}