{
  "type": "Feature",
  "properties": {
    "addr:full":"607 Midland Ave Staten Island NY 10306",
    "addr:housenumber":"607",
    "addr:postcode":"10306",
    "addr:street":"Midland Ave",
    "iso:country":"US",
    "sg:address":"607 Midland Ave",
    "sg:city":"Staten Island",
    "sg:classifiers":[
        {
            "category":"Wholesale",
            "subcategory":"Durable Goods & Equipment",
            "type":"Manufacturing & Wholesale Goods"
        }
    ],
    "sg:phone":"+1 718 987 7878",
    "sg:postcode":"10306",
    "sg:province":"NY",
    "sg:tags":[
        "repair",
        "electrical"
    ],
    "wof:name":"Sound Attitude Corp",
    "wof:placetype":"venue"
},
  "geometry": {"coordinates":[-74.09117500000001,40.571265],"type":"Point"}
}