{
  "type": "Feature",
  "properties": {
    "iso:country":"US",
    "sg:address":"6905 5th Ave",
    "sg:city":"Brooklyn",
    "sg:classifiers":[
        {
            "category":"Retail",
            "subcategory":"Self-service Laundry",
            "type":"Services"
        }
    ],
    "sg:phone":"+1   ",
    "sg:postcode":"11209",
    "sg:province":"NY",
    "sg:tags":[
        "coin"
    ],
    "wof:name":"E&M Laundermat",
    "wof:placetype":"venue"
},
  "geometry": {"coordinates":[-74.02129100000001,40.632593],"type":"Point"}
}