{
  "type": "Feature",
  "properties": {
    "iso:country":"US",
    "sg:address":"212 Forsyth St",
    "sg:city":"New York",
    "sg:classifiers":[
        {
            "category":"Building & Trades",
            "subcategory":"Construction",
            "type":"Services"
        }
    ],
    "sg:phone":"+1 212 473 0457",
    "sg:postcode":"10002",
    "sg:province":"NY",
    "sg:tags":[
        "house",
        "nonresidential"
    ],
    "wof:name":"Herman Hewitt Construction",
    "wof:placetype":"venue"
},
  "geometry": {"coordinates":[-73.990568,40.722465],"type":"Point"}
}