{
  "type": "Feature",
  "properties": {
    "addr:full":"266 24th St Brooklyn NY 11232",
    "addr:housenumber":"266",
    "addr:postcode":"11232",
    "addr:street":"24Th St",
    "iso:country":"US",
    "sg:address":"266 24th St",
    "sg:city":"Brooklyn",
    "sg:classifiers":[
        {
            "category":"Shopping",
            "subcategory":"Mobile Phones",
            "type":"Retail Goods"
        }
    ],
    "sg:phone":"+1 718 788 8829",
    "sg:postcode":"11232",
    "sg:province":"NY",
    "wof:name":"Gavin Network",
    "wof:placetype":"venue"
},
  "geometry": {"coordinates":[-73.996959,40.660471],"type":"Point"}
}