{
  "type": "Feature",
  "properties": {
    "iso:country":"US",
    "sg:address":"16115 Crossbay Boulevard",
    "sg:city":"Howard Beach",
    "sg:classifiers":[
        {
            "category":"Autos & Motor Vehicles",
            "subcategory":"Fuel & Gas Station",
            "type":"Retail Goods"
        }
    ],
    "sg:phone":"+1 718 641 0206",
    "sg:postcode":"11414",
    "sg:province":"NY",
    "wof:name":"Ashoka Gasoline Company",
    "wof:placetype":"venue"
},
  "geometry": {"coordinates":[-73.838734,40.654998],"type":"Point"}
}