{
  "type": "Feature",
  "properties": {
    "iso:country":"US",
    "sg:address":"37 Drake Ave",
    "sg:city":"Bellport",
    "sg:classifiers":[
        {
            "category":"Restaurant",
            "type":"Food & Drink"
        }
    ],
    "sg:phone":"+1 631 286 9131",
    "sg:postcode":"11713",
    "sg:province":"NY",
    "sg:tags":[
        "machine",
        "vending",
        "eating",
        "operator"
    ],
    "wof:name":"Christas Snacks",
    "wof:placetype":"venue"
},
  "geometry": {"coordinates":[-72.954457,40.796854],"type":"Point"}
}