{
  "type": "Feature",
  "properties": {
    "iso:country":"US",
    "sg:address":"183 Madison Ave Suite 1200",
    "sg:city":"New York",
    "sg:classifiers":[
        {
            "category":"Shopping",
            "subcategory":"Clothing, Apparel, & Fashions",
            "type":"Retail Goods"
        }
    ],
    "sg:phone":"+1 212 685 6444",
    "sg:postcode":"10016",
    "sg:province":"NY",
    "sg:tags":[
        "clothing",
        "women's"
    ],
    "wof:name":"Loomworks Apparel",
    "wof:placetype":"venue"
},
  "geometry": {"coordinates":[-73.982941,40.74775],"type":"Point"}
}