{
  "type": "Feature",
  "properties": {
    "iso:country":"US",
    "sg:address":"10918 Sutphin Blvd",
    "sg:city":"Jamaica",
    "sg:classifiers":[
        {
            "category":"Food & Beverages",
            "subcategory":"Groceries & Convenience Stores",
            "type":"Retail Goods"
        }
    ],
    "sg:phone":"+1 718 526 0043",
    "sg:postcode":"11435",
    "sg:province":"NY",
    "wof:name":"Empire Processer Service Inc",
    "wof:placetype":"venue"
},
  "geometry": {"coordinates":[-73.797971,40.69125],"type":"Point"}
}