{
  "type": "Feature",
  "properties": {
    "addr:full":"112 Commack Rd Commack NY 11725",
    "addr:housenumber":"112",
    "addr:postcode":"11725",
    "addr:street":"Commack Rd",
    "iso:country":"US",
    "sg:address":"112 Commack Rd",
    "sg:city":"Commack",
    "sg:classifiers":[
        {
            "category":"Real Estate",
            "subcategory":"Real Estate Agent",
            "type":"Services"
        }
    ],
    "sg:phone":"+1 631 499 4500",
    "sg:postcode":"11725",
    "sg:province":"NY",
    "wof:name":"Larsen Realty Group LLC",
    "wof:placetype":"venue"
},
  "geometry": {"coordinates":[-73.292901,40.842901],"type":"Point"}
}