{
  "type": "Feature",
  "properties": {
    "addr:full":"346 Avenue P Brooklyn NY 11204",
    "addr:housenumber":"346",
    "addr:postcode":"11204",
    "addr:street":"Avenue P",
    "iso:country":"US",
    "sg:address":"346 Avenue P",
    "sg:city":"Brooklyn",
    "sg:classifiers":[
        {
            "category":"Education",
            "subcategory":"School",
            "type":"Public Place"
        }
    ],
    "sg:phone":"+1 718 375 9506",
    "sg:postcode":"11204",
    "sg:province":"NY",
    "sg:tags":[
        "high",
        "middle",
        "elementary"
    ],
    "wof:name":"New York City Community School District 21 Region 7",
    "wof:placetype":"venue"
},
  "geometry": {"coordinates":[-73.97456,40.60852],"type":"Point"}
}