{
  "type": "Feature",
  "properties": {
    "iso:country":"US",
    "sg:address":"1818 Kennedy Rd",
    "sg:city":"Webster",
    "sg:classifiers":[
        {
            "category":"Professional",
            "type":"Services"
        },
        {
            "category":"Professional",
            "subcategory":"Art Services",
            "type":"Services"
        }
    ],
    "sg:phone":"+1 585 872 0453",
    "sg:postcode":"14580",
    "sg:province":"NY",
    "sg:tags":[
        "calligrapher"
    ],
    "wof:name":"Kathy Saunders Calligraphy",
    "wof:placetype":"venue"
},
  "geometry": {"coordinates":[-77.374737,43.173151],"type":"Point"}
}