{
  "type": "Feature",
  "properties": {
    "addr:full":"3787 Marshfield Rd Lawtons NY 14091",
    "addr:housenumber":"3787",
    "addr:postcode":"14091",
    "addr:street":"Marshfield Rd",
    "iso:country":"US",
    "sg:address":"3787 Marshfield Rd",
    "sg:city":"Lawtons",
    "sg:classifiers":[
        {
            "category":"Farming",
            "subcategory":"Dairy Farm",
            "type":"Manufacturing & Wholesale Goods"
        }
    ],
    "sg:phone":"+1 716 337 3165",
    "sg:postcode":"14091",
    "sg:province":"NY",
    "wof:name":"Philfred Farm",
    "wof:placetype":"venue"
},
  "geometry": {"coordinates":[-78.842646,42.542852],"type":"Point"}
}