{
  "type": "Feature",
  "properties": {
    "addr:full":"2800 3rd Ave Bronx NY 10455",
    "addr:housenumber":"2800",
    "addr:postcode":"10455",
    "addr:street":"3Rd Ave",
    "iso:country":"US",
    "sg:address":"2800 3rd Ave",
    "sg:city":"Bronx",
    "sg:classifiers":[
        {
            "category":"Home & Garden",
            "subcategory":"Hardware",
            "type":"Retail Goods"
        }
    ],
    "sg:phone":"+1 718 665 0215",
    "sg:postcode":"10455",
    "sg:province":"NY",
    "wof:name":"Morales Hardware",
    "wof:placetype":"venue"
},
  "geometry": {"coordinates":[-73.918755,40.815336],"type":"Point"}
}