{
  "type": "Feature",
  "properties": {
    "addr:full":"1142 E 156th St Bronx NY 10474",
    "addr:housenumber":"1142",
    "addr:postcode":"10474",
    "addr:street":"E 156Th St",
    "iso:country":"US",
    "sg:address":"1142 E 156th St",
    "sg:city":"Bronx",
    "sg:classifiers":[
        {
            "category":"Building & Trades",
            "subcategory":"Plumbing",
            "type":"Services"
        }
    ],
    "sg:phone":"+1 718 842 9000",
    "sg:postcode":"10474",
    "sg:province":"NY",
    "sg:tags":[
        "equipment",
        "installation",
        "heating"
    ],
    "wof:name":"L & C Burner Service Inc",
    "wof:placetype":"venue"
},
  "geometry": {"coordinates":[-73.89245699999999,40.812297],"type":"Point"}
}