{
  "type": "Feature",
  "properties": {
    "iso:country":"US",
    "sg:address":"412 E 176th St",
    "sg:city":"Bronx",
    "sg:classifiers":[
        {
            "category":"Retail",
            "subcategory":"Auto Repair",
            "type":"Services"
        }
    ],
    "sg:phone":"+1 718 960 0722",
    "sg:postcode":"10457",
    "sg:province":"NY",
    "sg:tags":[
        "repairing",
        "automobile"
    ],
    "wof:name":"Juan Auto Repair Shop",
    "wof:placetype":"venue"
},
  "geometry": {"coordinates":[-73.900554,40.846541],"type":"Point"}
}