{
  "type": "Feature",
  "properties": {
    "addr:full":"445 Gramatan Ave Mount Vernon NY 10552",
    "addr:housenumber":"445",
    "addr:postcode":"10552",
    "addr:street":"Gramatan Ave",
    "iso:country":"US",
    "sg:address":"445 Gramatan Ave",
    "sg:city":"Mount Vernon",
    "sg:classifiers":[
        {
            "category":"Real Estate",
            "subcategory":"Real Estate Operator",
            "type":"Services"
        }
    ],
    "sg:phone":"+1 914 664 2565",
    "sg:postcode":"10552",
    "sg:province":"NY",
    "sg:tags":[
        "building",
        "apartment"
    ],
    "wof:name":"Westchester Gardens Owners",
    "wof:placetype":"venue"
},
  "geometry": {"coordinates":[-73.837014,40.922675],"type":"Point"}
}