{
  "type": "Feature",
  "properties": {
    "addr:full":"505 W 171st St New York NY 10032",
    "addr:housenumber":"505",
    "addr:postcode":"10032",
    "addr:street":"W 171St St",
    "iso:country":"US",
    "sg:address":"505 W 171st St",
    "sg:city":"New York",
    "sg:classifiers":[
        {
            "category":"Social Services",
            "type":"Services"
        }
    ],
    "sg:phone":"+1 212 927 1667",
    "sg:postcode":"10032",
    "sg:province":"NY",
    "sg:tags":[
        "youth",
        "organization",
        "center"
    ],
    "wof:name":"Fresh Youth Initiative",
    "wof:placetype":"venue"
},
  "geometry": {"coordinates":[-73.93689999999999,40.842329],"type":"Point"}
}