{
  "type": "Feature",
  "properties": {
    "iso:country":"US",
    "sg:address":"790 New York Ave",
    "sg:city":"Huntington",
    "sg:classifiers":[
        {
            "category":"Insurance",
            "subcategory":"Insurance Agent",
            "type":"Services"
        }
    ],
    "sg:phone":"+1 631 424 2400",
    "sg:postcode":"11743",
    "sg:province":"NY",
    "sg:tags":[
        "processing"
    ],
    "sg:website":"www.infinityadmin.com",
    "wof:name":"Mutual Assn Administrators",
    "wof:placetype":"venue"
},
  "geometry": {"coordinates":[-73.42074,40.860755],"type":"Point"}
}