{
  "type": "Feature",
  "properties": {
    "addr:full":"4124 54th St Woodside NY 11377",
    "addr:housenumber":"4124",
    "addr:postcode":"11377",
    "addr:street":"54Th St",
    "iso:country":"US",
    "sg:address":"4124 54th St",
    "sg:city":"Woodside",
    "sg:classifiers":[
        {
            "category":"Shopping",
            "subcategory":"Party Supplies",
            "type":"Retail Goods"
        }
    ],
    "sg:phone":"+1 718 458 2958",
    "sg:postcode":"11377",
    "sg:province":"NY",
    "wof:name":"Felicia's Party",
    "wof:placetype":"venue"
},
  "geometry": {"coordinates":[-73.910599,40.745399],"type":"Point"}
}