{
  "type": "Feature",
  "properties": {
    "iso:country":"US",
    "sg:address":"5536 Imperia Ln",
    "sg:city":"Clay",
    "sg:classifiers":[
        {
            "category":"Building & Trades",
            "subcategory":"Pest Control",
            "type":"Services"
        }
    ],
    "sg:phone":"+1 315 699 7122",
    "sg:postcode":"13041",
    "sg:province":"NY",
    "wof:name":"D J Evans & Son Exterminating",
    "wof:placetype":"venue"
},
  "geometry": {"coordinates":[-76.133079,43.153224],"type":"Point"}
}