{
  "type": "Feature",
  "properties": {
    "iso:country":"US",
    "sg:address":"770 State Hwy 52",
    "sg:city":"Beacon",
    "sg:classifiers":[
        {
            "category":"Sports & Exercise",
            "subcategory":"Bowling",
            "type":"Entertainment"
        }
    ],
    "sg:phone":"+1 845 838 0644",
    "sg:postcode":"12508",
    "sg:province":"NY",
    "sg:tags":[
        "center"
    ],
    "wof:name":"Southern Dutchess Bowl Inc",
    "wof:placetype":"venue"
},
  "geometry": {"coordinates":[-73.937558,41.522287],"type":"Point"}
}