{
  "type": "Feature",
  "properties": {
    "addr:full":"46 Buchanan Ln Spring Valley NY 10977",
    "addr:housenumber":"46",
    "addr:postcode":"10977",
    "addr:street":"Buchanan Ln",
    "iso:country":"US",
    "sg:address":"46 Buchanan Ln",
    "sg:city":"Spring Valley",
    "sg:classifiers":[
        {
            "category":"Building & Trades",
            "subcategory":"Construction",
            "type":"Services"
        }
    ],
    "sg:phone":"+1 845 362 5999",
    "sg:postcode":"10977",
    "sg:province":"NY",
    "sg:tags":[
        "window",
        "decorating"
    ],
    "wof:name":"Fashion Window Decorating Inc",
    "wof:placetype":"venue"
},
  "geometry": {"coordinates":[-74.033126,41.13871],"type":"Point"}
}