{
  "type": "Feature",
  "properties": {
    "iso:country":"US",
    "sg:address":"226 84th St",
    "sg:city":"Niagara Falls",
    "sg:classifiers":[
        {
            "category":"Education",
            "subcategory":"Special Training",
            "type":"Public Place"
        }
    ],
    "sg:phone":"+1 716 283 7943",
    "sg:postcode":"14304",
    "sg:province":"NY",
    "sg:tags":[
        "instruction",
        "music"
    ],
    "wof:name":"Laurie Jircitano's Music Std",
    "wof:placetype":"venue"
},
  "geometry": {"coordinates":[-78.96805999999999,43.077281],"type":"Point"}
}