{
  "type": "Feature",
  "properties": {
    "addr:full":"4120 38th St Long Island City NY 11101",
    "addr:housenumber":"4120",
    "addr:postcode":"11101",
    "addr:street":"38Th St",
    "iso:country":"US",
    "sg:address":"4120 38th St",
    "sg:city":"Long Island City",
    "sg:classifiers":[
        {
            "category":"Building & Trades",
            "subcategory":"Electrical",
            "type":"Services"
        }
    ],
    "sg:phone":"+1 718 392 0885",
    "sg:postcode":"11101",
    "sg:province":"NY",
    "sg:tags":[
        "electrician"
    ],
    "wof:name":"Polyphase Electric Inc",
    "wof:placetype":"venue"
},
  "geometry": {"coordinates":[-73.926598,40.746799],"type":"Point"}
}