{
  "type": "Feature",
  "properties": {
    "addr:full":"3 E Deer Park Rd Dix Hills NY 11746",
    "addr:housenumber":"3",
    "addr:postcode":"11746",
    "addr:street":"E Deer Park Rd",
    "iso:country":"US",
    "sg:address":"3 E Deer Park Rd",
    "sg:city":"Dix Hills",
    "sg:classifiers":[
        {
            "category":"Home & Garden",
            "subcategory":"Carpets & Floor Coverings",
            "type":"Retail Goods"
        }
    ],
    "sg:phone":"+1 631 462 5650",
    "sg:postcode":"11746",
    "sg:province":"NY",
    "sg:tags":[
        "flooring"
    ],
    "sg:website":"www.a-zfloorsanding.com",
    "wof:name":"A-Z Floor Sanding",
    "wof:placetype":"venue"
},
  "geometry": {"coordinates":[-73.33523599999999,40.835203],"type":"Point"}
}