{
  "type": "Feature",
  "properties": {
    "iso:country":"US",
    "sg:address":"29 2nd Ave",
    "sg:city":"North Tonawanda",
    "sg:classifiers":[
        {
            "category":"Banks & Credit Unions",
            "subcategory":"Investment Brokerage",
            "type":"Services"
        }
    ],
    "sg:phone":"+1 716 694 7439",
    "sg:postcode":"14120",
    "sg:province":"NY",
    "sg:tags":[
        "security"
    ],
    "wof:name":"Parchuk",
    "wof:placetype":"venue"
},
  "geometry": {"coordinates":[-78.879514,43.037273],"type":"Point"}
}