{
  "type": "Feature",
  "properties": {
    "iso:country":"US",
    "sg:address":"934 Birchwood Ln",
    "sg:city":"Schenectady",
    "sg:classifiers":[
        {
            "category":"Home & Garden",
            "subcategory":"Carpets & Floor Coverings",
            "type":"Retail Goods"
        }
    ],
    "sg:phone":"+1 518 355 2848",
    "sg:postcode":"12309",
    "sg:province":"NY",
    "sg:tags":[
        "material"
    ],
    "wof:name":"Tygert Enterprises Inc",
    "wof:placetype":"venue"
},
  "geometry": {"coordinates":[-73.838869,42.773071],"type":"Point"}
}