{
  "type": "Feature",
  "properties": {
    "addr:full":"2293 McDonald Ave Brooklyn NY 11223",
    "addr:housenumber":"2293",
    "addr:postcode":"11223",
    "addr:street":"Mcdonald Ave",
    "iso:country":"US",
    "sg:address":"2293 McDonald Ave",
    "sg:city":"Brooklyn",
    "sg:classifiers":[
        {
            "category":"Shopping",
            "type":"Retail Goods"
        }
    ],
    "sg:phone":"+1   ",
    "sg:postcode":"11223",
    "sg:province":"NY",
    "sg:tags":[
        "merchandise"
    ],
    "wof:name":"Popular Security",
    "wof:placetype":"venue"
},
  "geometry": {"coordinates":[-73.973384,40.595407],"type":"Point"}
}