{
  "type": "Feature",
  "properties": {
    "iso:country":"US",
    "sg:address":"1030 Merrick Rd",
    "sg:city":"Baldwin",
    "sg:classifiers":[
        {
            "category":"Real Estate",
            "subcategory":"Real Estate Agent",
            "type":"Services"
        }
    ],
    "sg:phone":"+1 516 223 3111",
    "sg:postcode":"11510",
    "sg:province":"NY",
    "wof:name":"Mahler Realty",
    "wof:placetype":"venue"
},
  "geometry": {"coordinates":[-73.602937,40.650995],"type":"Point"}
}