{
  "type": "Feature",
  "properties": {
    "addr:full":"1750 E 15th St Brooklyn NY 11229",
    "addr:housenumber":"1750",
    "addr:postcode":"11229",
    "addr:street":"E 15Th St",
    "iso:country":"US",
    "sg:address":"1750 E 15th St",
    "sg:city":"Brooklyn",
    "sg:classifiers":[
        {
            "category":"Professional",
            "subcategory":"Advertising",
            "type":"Services"
        }
    ],
    "sg:phone":"+1 718 336 4980",
    "sg:postcode":"11229",
    "sg:province":"NY",
    "sg:tags":[
        "agency"
    ],
    "wof:name":"Pin Point Advertising",
    "wof:placetype":"venue"
},
  "geometry": {"coordinates":[-73.958046,40.607517],"type":"Point"}
}