{
  "type": "Feature",
  "properties": {
    "iso:country":"US",
    "sg:address":"687 8th Ave Frnt 1",
    "sg:city":"New York",
    "sg:classifiers":[
        {
            "category":"Cinema",
            "subcategory":"Movie Rental",
            "type":"Entertainment"
        }
    ],
    "sg:phone":"+1 212 445 1731",
    "sg:postcode":"10036",
    "sg:province":"NY",
    "sg:tags":[
        "game",
        "video"
    ],
    "wof:name":"Gotham City Video",
    "wof:placetype":"venue"
},
  "geometry": {"coordinates":[-74.115595,40.573513],"type":"Point"}
}