{
  "type": "Feature",
  "properties": {
    "iso:country":"US",
    "sg:address":"11200 Maple Ridge Rd",
    "sg:city":"Medina",
    "sg:classifiers":[
        {
            "category":"Food & Beverages",
            "subcategory":"Groceries & Convenience Stores",
            "type":"Retail Goods"
        }
    ],
    "sg:phone":"+1 585 798 1629",
    "sg:postcode":"14103",
    "sg:province":"NY",
    "sg:tags":[
        "grocer",
        "supermarket"
    ],
    "wof:name":"Tops Friendly Markets 248",
    "wof:placetype":"venue"
},
  "geometry": {"coordinates":[-78.40246500000001,43.206697],"type":"Point"}
}