{
  "type": "Feature",
  "properties": {
    "addr:full":"755 Trimmer Rd Spencerport NY 14559",
    "addr:housenumber":"755",
    "addr:postcode":"14559",
    "addr:street":"Trimmer Rd",
    "iso:country":"US",
    "sg:address":"755 Trimmer Rd",
    "sg:city":"Spencerport",
    "sg:classifiers":[
        {
            "category":"Building & Trades",
            "subcategory":"Landscaping Services",
            "type":"Services"
        }
    ],
    "sg:phone":"+1 585 352 7302",
    "sg:postcode":"14559",
    "sg:province":"NY",
    "sg:tags":[
        "lawn",
        "maintenance",
        "grounds"
    ],
    "wof:name":"Best Cut Lawn Care",
    "wof:placetype":"venue"
},
  "geometry": {"coordinates":[-77.82325899999999,43.191145],"type":"Point"}
}