{
  "type": "Feature",
  "properties": {
    "iso:country":"US",
    "sg:address":"236 North St",
    "sg:city":"Greenport",
    "sg:classifiers":[
        {
            "category":"Real Estate",
            "subcategory":"Real Estate Agent",
            "type":"Services"
        }
    ],
    "sg:phone":"+1 631 682 2386",
    "sg:postcode":"11944",
    "sg:province":"NY",
    "sg:tags":[
        "management"
    ],
    "wof:name":"Property Management Affiliates",
    "wof:placetype":"venue"
},
  "geometry": {"coordinates":[-72.36432600000001,41.105958],"type":"Point"}
}