{
  "type": "Feature",
  "properties": {
    "addr:full":"41 Oak Brook Dr Ithaca NY 14850",
    "addr:housenumber":"41",
    "addr:postcode":"14850",
    "addr:street":"Oak Brook Dr",
    "iso:country":"US",
    "sg:address":"41 Oak Brook Dr",
    "sg:city":"Ithaca",
    "sg:classifiers":[
        {
            "category":"Building & Trades",
            "subcategory":"Landscaping Services",
            "type":"Services"
        }
    ],
    "sg:phone":"+1 607 277 5296",
    "sg:postcode":"14850",
    "sg:province":"NY",
    "wof:name":"Bellisario Nickolas",
    "wof:placetype":"venue"
},
  "geometry": {"coordinates":[-76.42265999999999,42.460351],"type":"Point"}
}