{
  "type": "Feature",
  "properties": {
    "iso:country":"US",
    "sg:address":"114 Church St",
    "sg:city":"Freeport",
    "sg:classifiers":[
        {
            "category":"Shopping",
            "subcategory":"Hobbies, Toys, & Games",
            "type":"Retail Goods"
        }
    ],
    "sg:phone":"+1 516 379 0020",
    "sg:postcode":"11520",
    "sg:province":"NY",
    "wof:name":"Many Mini Toys Inc",
    "wof:placetype":"venue"
},
  "geometry": {"coordinates":[-73.58156200000001,40.65359],"type":"Point"}
}