{
  "type": "Feature",
  "properties": {
    "iso:country":"US",
    "sg:address":"5 Front St",
    "sg:city":"Waterford",
    "sg:classifiers":[
        {
            "category":"Shopping",
            "subcategory":"Gifts & Souvenirs",
            "type":"Retail Goods"
        }
    ],
    "sg:phone":"+1   ",
    "sg:postcode":"12188",
    "sg:province":"NY",
    "wof:name":"Nicks Nacks",
    "wof:placetype":"venue"
},
  "geometry": {"coordinates":[-73.676912,42.786341],"type":"Point"}
}