{
  "type": "Feature",
  "properties": {
    "addr:full":"901 Holly Dr Fulton NY 13069",
    "addr:housenumber":"901",
    "addr:postcode":"13069",
    "addr:street":"Holly Dr",
    "iso:country":"US",
    "sg:address":"901 Holly Dr",
    "sg:city":"Fulton",
    "sg:classifiers":[
        {
            "category":"Building & Trades",
            "subcategory":"Construction",
            "type":"Services"
        }
    ],
    "sg:phone":"+1 315 523 0386",
    "sg:postcode":"13069",
    "sg:province":"NY",
    "sg:tags":[
        "general",
        "contractor"
    ],
    "wof:name":"Vail Construction",
    "wof:placetype":"venue"
},
  "geometry": {"coordinates":[-76.40073099999999,43.326246],"type":"Point"}
}