{
  "type": "Feature",
  "properties": {
    "iso:country":"US",
    "sg:address":"3712 Milton Ave",
    "sg:city":"Camillus",
    "sg:classifiers":[
        {
            "category":"Personal",
            "subcategory":"Beauty Salon",
            "type":"Services"
        }
    ],
    "sg:phone":"+1 315 488 3284",
    "sg:postcode":"13031",
    "sg:province":"NY",
    "wof:name":"Salon Development Corp",
    "wof:placetype":"venue"
},
  "geometry": {"coordinates":[-76.265061,43.052464],"type":"Point"}
}