{
  "type": "Feature",
  "properties": {
    "iso:country":"US",
    "sg:address":"2007 E 29th St",
    "sg:city":"Brooklyn",
    "sg:classifiers":[
        {
            "category":"Wholesale",
            "subcategory":"Non-durable Goods",
            "type":"Manufacturing & Wholesale Goods"
        }
    ],
    "sg:phone":"+1 718 368 2926",
    "sg:postcode":"11229",
    "sg:province":"NY",
    "wof:name":"Tai Pang Trading Inc",
    "wof:placetype":"venue"
},
  "geometry": {"coordinates":[-73.942835,40.600467],"type":"Point"}
}