{
  "type": "Feature",
  "properties": {
    "addr:full":"148 Duane St New York NY 10013",
    "addr:housenumber":"148",
    "addr:postcode":"10013",
    "addr:street":"Duane St",
    "iso:country":"US",
    "sg:address":"148 Duane St",
    "sg:city":"New York",
    "sg:classifiers":[
        {
            "category":"Real Estate",
            "subcategory":"Real Estate Agent",
            "type":"Services"
        }
    ],
    "sg:phone":"+1 212 608 8889",
    "sg:postcode":"10013",
    "sg:province":"NY",
    "wof:name":"Loftworks Realty",
    "wof:placetype":"venue"
},
  "geometry": {"coordinates":[-74.007608,40.716032],"type":"Point"}
}