{
  "type": "Feature",
  "properties": {
    "iso:country":"US",
    "sg:address":"305 Locust Ave",
    "sg:city":"Bronx",
    "sg:classifiers":[
        {
            "category":"Restaurant",
            "type":"Food & Drink"
        }
    ],
    "sg:phone":"+1 718 292 0669",
    "sg:postcode":"10454",
    "sg:province":"NY",
    "wof:name":"Vithas Coffee Shop Inc",
    "wof:placetype":"venue"
},
  "geometry": {"coordinates":[-73.905627,40.803852],"type":"Point"}
}