{
  "type": "Feature",
  "properties": {
    "addr:full":"362 Webster Ave Brooklyn NY 11230",
    "addr:housenumber":"362",
    "addr:postcode":"11230",
    "addr:street":"Webster Ave",
    "iso:country":"US",
    "sg:address":"362 Webster Ave",
    "sg:city":"Brooklyn",
    "sg:classifiers":[
        {
            "category":"Shopping",
            "subcategory":"Gifts & Souvenirs",
            "type":"Retail Goods"
        }
    ],
    "sg:phone":"+1   ",
    "sg:postcode":"11230",
    "sg:province":"NY",
    "sg:tags":[
        "via",
        "internet"
    ],
    "wof:name":"Toy Bucket",
    "wof:placetype":"venue"
},
  "geometry": {"coordinates":[-73.968119,40.63393],"type":"Point"}
}