{
  "type": "Feature",
  "properties": {
    "addr:full":"132 W 89th Street New York NY 10024",
    "addr:housenumber":"132",
    "addr:postcode":"10024",
    "addr:street":"W 89Th Street",
    "iso:country":"US",
    "sg:address":"132 W 89th Street",
    "sg:city":"New York",
    "sg:classifiers":[
        {
            "category":"Education",
            "subcategory":"School",
            "type":"Public Place"
        }
    ],
    "sg:phone":"+1 212 678 2829",
    "sg:postcode":"10024",
    "sg:province":"NY",
    "sg:tags":[
        "high",
        "middle",
        "elementary"
    ],
    "wof:name":"N Y City of",
    "wof:placetype":"venue"
},
  "geometry": {"coordinates":[-73.971296,40.788772],"type":"Point"}
}