{
  "type": "Feature",
  "properties": {
    "iso:country":"US",
    "sg:address":"20 Ann St",
    "sg:city":"Lockport",
    "sg:classifiers":[
        {
            "category":"Personal",
            "type":"Services"
        },
        {
            "category":"Sports & Exercise",
            "subcategory":"Gym",
            "type":"Entertainment"
        }
    ],
    "sg:phone":"+1 716 439 4094",
    "sg:postcode":"14094",
    "sg:province":"NY",
    "sg:tags":[
        "fitness",
        "program",
        "physical",
        "facility"
    ],
    "wof:name":"Ultimate Physique Inc",
    "wof:placetype":"venue"
},
  "geometry": {"coordinates":[-78.684702,43.174237],"type":"Point"}
}