{
  "type": "Feature",
  "properties": {
    "addr:full":"401 Main St Utica NY 13501",
    "addr:housenumber":"401",
    "addr:postcode":"13501",
    "addr:street":"Main St",
    "iso:country":"US",
    "sg:address":"401 Main St",
    "sg:city":"Utica",
    "sg:classifiers":[
        {
            "category":"Restaurant",
            "type":"Food & Drink"
        }
    ],
    "sg:phone":"+1   ",
    "sg:postcode":"13501",
    "sg:province":"NY",
    "wof:name":"Lupinos Trackside Restaurant",
    "wof:placetype":"venue"
},
  "geometry": {"coordinates":[-75.22103799999999,43.103028],"type":"Point"}
}