{
  "type": "Feature",
  "properties": {
    "addr:full":"143 W 15 St New York NY 10011",
    "addr:housenumber":"143",
    "addr:postcode":"10011",
    "addr:street":"W 15 St",
    "iso:country":"US",
    "sg:address":"143 W 15 St",
    "sg:city":"New York",
    "sg:classifiers":[
        {
            "category":"Wholesale",
            "subcategory":"Apparel",
            "type":"Manufacturing & Wholesale Goods"
        }
    ],
    "sg:phone":"+1 212 684 3670",
    "sg:postcode":"10011",
    "sg:province":"NY",
    "sg:tags":[
        "underwear"
    ],
    "wof:name":"Luxerdame Co",
    "wof:placetype":"venue"
},
  "geometry": {"coordinates":[-73.997997,40.738698],"type":"Point"}
}