{
  "type": "Feature",
  "properties": {
    "addr:full":"1177 Flushing Ave Brooklyn NY 11237",
    "addr:housenumber":"1177",
    "addr:postcode":"11237",
    "addr:street":"Flushing Ave",
    "iso:country":"US",
    "sg:address":"1177 Flushing Ave",
    "sg:city":"Brooklyn",
    "sg:classifiers":[
        {
            "category":"Wholesale",
            "subcategory":"Meat",
            "type":"Manufacturing & Wholesale Goods"
        }
    ],
    "sg:phone":"+1 718 628 0678",
    "sg:postcode":"11237",
    "sg:province":"NY",
    "sg:tags":[
        "poultry",
        "canned",
        "seafood"
    ],
    "wof:name":"China Provision",
    "wof:placetype":"venue"
},
  "geometry": {"coordinates":[-73.925658,40.706044],"type":"Point"}
}