{
  "type": "Feature",
  "properties": {
    "iso:country":"US",
    "sg:address":"1337 Main St E",
    "sg:city":"Rochester",
    "sg:classifiers":[
        {
            "category":"Social Services",
            "subcategory":"Adult Care",
            "type":"Services"
        }
    ],
    "sg:phone":"+1 585 654 4455",
    "sg:postcode":"14609",
    "sg:province":"NY",
    "sg:tags":[
        "residential"
    ],
    "wof:name":"Hillside Behavioral Health Sys",
    "wof:placetype":"venue"
},
  "geometry": {"coordinates":[-77.576103,43.161079],"type":"Point"}
}