{
  "type": "Feature",
  "properties": {
    "addr:full":"33 Oswego St Baldwinsville NY 13027",
    "addr:housenumber":"33",
    "addr:postcode":"13027",
    "addr:street":"Oswego St",
    "iso:country":"US",
    "sg:address":"33 Oswego St",
    "sg:city":"Baldwinsville",
    "sg:classifiers":[
        {
            "category":"Personal",
            "subcategory":"Beauty Salon",
            "type":"Services"
        }
    ],
    "sg:phone":"+1 315 638 2898",
    "sg:postcode":"13027",
    "sg:province":"NY",
    "wof:name":"The Mirage Salon",
    "wof:placetype":"venue"
},
  "geometry": {"coordinates":[-76.33268700000001,43.158669],"type":"Point"}
}