{
  "type": "Feature",
  "properties": {
    "iso:country":"US",
    "sg:address":"34 Broadway",
    "sg:city":"Cohoes",
    "sg:classifiers":[
        {
            "category":"Building & Trades",
            "subcategory":"Construction",
            "type":"Services"
        }
    ],
    "sg:phone":"+1 518 235 4443",
    "sg:postcode":"12047",
    "sg:province":"NY",
    "sg:tags":[
        "house"
    ],
    "wof:name":"Farrigan Construction",
    "wof:placetype":"venue"
},
  "geometry": {"coordinates":[-73.708276,42.772786],"type":"Point"}
}