{
  "type": "Feature",
  "properties": {
    "addr:full":"3815 Dyre Ave Bronx NY 10466",
    "addr:housenumber":"3815",
    "addr:postcode":"10466",
    "addr:street":"Dyre Ave",
    "iso:country":"US",
    "sg:address":"3815 Dyre Ave",
    "sg:city":"Bronx",
    "sg:classifiers":[
        {
            "category":"Food & Beverages",
            "subcategory":"Groceries & Convenience Stores",
            "type":"Retail Goods"
        }
    ],
    "sg:phone":"+1   ",
    "sg:postcode":"10466",
    "sg:province":"NY",
    "wof:name":"Dyre Bakery",
    "wof:placetype":"venue"
},
  "geometry": {"coordinates":[-73.831371,40.888995],"type":"Point"}
}