{
  "type": "Feature",
  "properties": {
    "addr:full":"1240 State Hwy 264 Phoenix NY 13135",
    "addr:housenumber":"1240",
    "addr:postcode":"13135",
    "addr:street":"State Hwy 264",
    "iso:country":"US",
    "sg:address":"1240 State Hwy 264",
    "sg:city":"Phoenix",
    "sg:classifiers":[
        {
            "category":"Shopping",
            "subcategory":"Hobbies, Toys, & Games",
            "type":"Retail Goods"
        }
    ],
    "sg:phone":"+1 315 593 6766",
    "sg:postcode":"13135",
    "sg:province":"NY",
    "sg:tags":[
        "equipment",
        "ceramic",
        "supply"
    ],
    "wof:name":"Dar's Ceramics & Crafts",
    "wof:placetype":"venue"
},
  "geometry": {"coordinates":[-76.290216,43.317302],"type":"Point"}
}