{
  "type": "Feature",
  "properties": {
    "addr:full":"247 E Spencer Rd Spencer NY 14883",
    "addr:housenumber":"247",
    "addr:postcode":"14883",
    "addr:street":"E Spencer Rd",
    "iso:country":"US",
    "sg:address":"247 E Spencer Rd",
    "sg:city":"Spencer",
    "sg:classifiers":[
        {
            "category":"Farming",
            "subcategory":"Livestock Farm",
            "type":"Manufacturing & Wholesale Goods"
        }
    ],
    "sg:phone":"+1 607 589 4234",
    "sg:postcode":"14883",
    "sg:province":"NY",
    "sg:tags":[
        "beef",
        "feedlot",
        "cattle"
    ],
    "wof:name":"Kenneth Frisbie",
    "wof:placetype":"venue"
},
  "geometry": {"coordinates":[-76.448069,42.212637],"type":"Point"}
}