{
  "type": "Feature",
  "properties": {
    "addr:full":"1044 W Jericho Tpke Smithtown NY 11787",
    "addr:housenumber":"1044",
    "addr:postcode":"11787",
    "addr:street":"W Jericho Tpke",
    "iso:country":"US",
    "sg:address":"1044 W Jericho Tpke",
    "sg:city":"Smithtown",
    "sg:classifiers":[
        {
            "category":"Bars & Pubs",
            "type":"Food & Drink"
        }
    ],
    "sg:phone":"+1 631 499 9029",
    "sg:postcode":"11787",
    "sg:province":"NY",
    "wof:name":"Stees",
    "wof:placetype":"venue"
},
  "geometry": {"coordinates":[-73.252415,40.847326],"type":"Point"}
}