{
  "type": "Feature",
  "properties": {
    "addr:full":"614 9th Avenue New York NY 10036",
    "addr:housenumber":"614",
    "addr:postcode":"10036",
    "addr:street":"9Th Avenue",
    "iso:country":"US",
    "sg:address":"614 9th Avenue",
    "sg:city":"New York",
    "sg:classifiers":[
        {
            "category":"Building & Trades",
            "subcategory":"Locksmith",
            "type":"Services"
        }
    ],
    "sg:phone":"+1 917 595 3169",
    "sg:postcode":"10036",
    "sg:province":"NY",
    "sg:tags":[
        "key"
    ],
    "wof:name":"Tow Any-Time",
    "wof:placetype":"venue"
},
  "geometry": {"coordinates":[-73.991821,40.7593],"type":"Point"}
}