{
  "type": "Feature",
  "properties": {
    "iso:country":"US",
    "sg:address":"3730 103rd Street",
    "sg:city":"Corona",
    "sg:classifiers":[
        {
            "category":"Health Services",
            "subcategory":"Dentist",
            "type":"Services"
        }
    ],
    "sg:phone":"+1 718 426 0820",
    "sg:postcode":"11368",
    "sg:province":"NY",
    "wof:name":"Peralta Juan DDS",
    "wof:placetype":"venue"
},
  "geometry": {"coordinates":[-73.864248,40.752854],"type":"Point"}
}