{
  "type": "Feature",
  "properties": {
    "addr:full":"450 West Ave Rochester NY 14611",
    "addr:housenumber":"450",
    "addr:postcode":"14611",
    "addr:street":"West Ave",
    "iso:country":"US",
    "sg:address":"450 West Ave",
    "sg:city":"Rochester",
    "sg:classifiers":[
        {
            "category":"Food & Beverages",
            "subcategory":"Groceries & Convenience Stores",
            "type":"Retail Goods"
        }
    ],
    "sg:phone":"+1 585 512 4104",
    "sg:postcode":"14611",
    "sg:province":"NY",
    "sg:tags":[
        "grocer"
    ],
    "wof:name":"Tops Friendly Market",
    "wof:placetype":"venue"
},
  "geometry": {"coordinates":[-77.650657,43.150041],"type":"Point"}
}