{
  "type": "Feature",
  "properties": {
    "iso:country":"US",
    "sg:address":"12 Burt Dr",
    "sg:city":"Deer Park",
    "sg:classifiers":[
        {
            "category":"Manufacturing",
            "subcategory":"Electronics",
            "type":"Manufacturing & Wholesale Goods"
        }
    ],
    "sg:phone":"+1   ",
    "sg:postcode":"11729",
    "sg:province":"NY",
    "sg:tags":[
        "co",
        "mfg"
    ],
    "wof:name":"McG Surge Protection",
    "wof:placetype":"venue"
},
  "geometry": {"coordinates":[-73.305634,40.761409],"type":"Point"}
}