{
  "type": "Feature",
  "properties": {
    "iso:country":"US",
    "sg:address":"4786 Gretchen Cir",
    "sg:city":"Syracuse",
    "sg:classifiers":[
        {
            "category":"Building & Trades",
            "subcategory":"Construction",
            "type":"Services"
        }
    ],
    "sg:phone":"+1 315 447 1992",
    "sg:postcode":"13215",
    "sg:province":"NY",
    "sg:tags":[
        "general",
        "contractor"
    ],
    "wof:name":"Brandon Construction",
    "wof:placetype":"venue"
},
  "geometry": {"coordinates":[-76.184691,42.995175],"type":"Point"}
}