{
  "type": "Feature",
  "properties": {
    "addr:full":"50 Doxsee Dr Freeport NY 11520",
    "addr:housenumber":"50",
    "addr:postcode":"11520",
    "addr:street":"Doxsee Dr",
    "iso:country":"US",
    "sg:address":"50 Doxsee Dr",
    "sg:city":"Freeport",
    "sg:classifiers":[
        {
            "category":"Professional",
            "subcategory":"Engineering",
            "type":"Services"
        }
    ],
    "sg:phone":"+1 516 223 1575",
    "sg:postcode":"11520",
    "sg:province":"NY",
    "sg:tags":[
        "business"
    ],
    "wof:name":"Cadview Technologies Corp",
    "wof:placetype":"venue"
},
  "geometry": {"coordinates":[-73.568774,40.646055],"type":"Point"}
}