{
  "type": "Feature",
  "properties": {
    "addr:full":"78 Todt Hill Rd Staten Island NY 10314",
    "addr:housenumber":"78",
    "addr:postcode":"10314",
    "addr:street":"Todt Hill Rd",
    "iso:country":"US",
    "sg:address":"78 Todt Hill Rd",
    "sg:city":"Staten Island",
    "sg:classifiers":[
        {
            "category":"Health Services",
            "subcategory":"Clinic",
            "type":"Services"
        }
    ],
    "sg:phone":"+1 718 447 6560",
    "sg:postcode":"10314",
    "sg:province":"NY",
    "sg:tags":[
        "medical",
        "group"
    ],
    "wof:name":"Reon Avenue Medical Assoc Inc",
    "wof:placetype":"venue"
},
  "geometry": {"coordinates":[-74.11895800000001,40.61199],"type":"Point"}
}