{
  "type": "Feature",
  "properties": {
    "iso:country":"US",
    "sg:address":"269 Cream St",
    "sg:city":"Poughkeepsie",
    "sg:classifiers":[
        {
            "category":"Building & Trades",
            "subcategory":"Plumbing",
            "type":"Services"
        }
    ],
    "sg:phone":"+1 845 452 4275",
    "sg:postcode":"12601",
    "sg:province":"NY",
    "sg:tags":[
        "septic",
        "contractor"
    ],
    "wof:name":"Losee Constr Co",
    "wof:placetype":"venue"
},
  "geometry": {"coordinates":[-73.877612,41.747582],"type":"Point"}
}