{
  "type": "Feature",
  "properties": {
    "addr:full":"155 E 76 St New York NY 10021",
    "addr:housenumber":"155;76",
    "addr:postcode":"10021",
    "addr:street":"E;St",
    "iso:country":"US",
    "sg:address":"155 E 76 St",
    "sg:city":"New York",
    "sg:classifiers":[
        {
            "category":"Health Services",
            "subcategory":"Doctor",
            "type":"Services"
        }
    ],
    "sg:phone":"+1 212 369 3200",
    "sg:postcode":"10021",
    "sg:province":"NY",
    "sg:tags":[
        "physician",
        "surgeon"
    ],
    "wof:name":"Peter A Godsick MD",
    "wof:placetype":"venue"
},
  "geometry": {"coordinates":[-73.958905,40.772522],"type":"Point"}
}