{
  "type": "Feature",
  "properties": {
    "addr:full":"101 N Central Ave Hartsdale NY 10530",
    "addr:housenumber":"101",
    "addr:postcode":"10530",
    "addr:street":"N Central Ave",
    "iso:country":"US",
    "sg:address":"101 N Central Ave",
    "sg:city":"Hartsdale",
    "sg:classifiers":[
        {
            "category":"Organizations",
            "subcategory":"Religious Organization",
            "type":"Services"
        }
    ],
    "sg:phone":"+1 914 946 7931",
    "sg:postcode":"10530",
    "sg:province":"NY",
    "sg:tags":[
        "church"
    ],
    "wof:name":"St Andrew's Episcopal Church",
    "wof:placetype":"venue"
},
  "geometry": {"coordinates":[-73.797146,41.019936],"type":"Point"}
}