{
  "type": "Feature",
  "properties": {
    "addr:full":"349 E 49th St New York NY 10017",
    "addr:housenumber":"349",
    "addr:postcode":"10017",
    "addr:street":"E 49Th St",
    "iso:country":"US",
    "sg:address":"349 E 49th St",
    "sg:city":"New York",
    "sg:classifiers":[
        {
            "category":"Food & Beverages",
            "subcategory":"Specialty",
            "type":"Retail Goods"
        }
    ],
    "sg:phone":"+1   ",
    "sg:postcode":"10017",
    "sg:province":"NY",
    "wof:name":"Robin J Roman",
    "wof:placetype":"venue"
},
  "geometry": {"coordinates":[-73.967456,40.753802],"type":"Point"}
}