{
  "type": "Feature",
  "properties": {
    "iso:country":"US",
    "sg:address":"405 S Oyster Bay Rd",
    "sg:city":"Plainview",
    "sg:classifiers":[
        {
            "category":"Shopping",
            "subcategory":"Clothing, Apparel, & Fashions",
            "type":"Retail Goods"
        },
        {
            "category":"Shopping",
            "subcategory":"Baby Store",
            "type":"Retail Goods"
        },
        {
            "category":"Shopping",
            "subcategory":"Department Store",
            "type":"Retail Goods"
        }
    ],
    "sg:phone":"+1 516 433 6077",
    "sg:postcode":"11803",
    "sg:province":"NY",
    "sg:tags":[
        "infant",
        "vintage",
        "men's",
        "period",
        "accessory",
        "children's",
        "wear",
        "apparel",
        "girls'",
        "women's",
        "clothing",
        "boys'",
        "clothing-collectible"
    ],
    "sg:website":"http://www.gap.com",
    "wof:name":"Gap",
    "wof:placetype":"venue"
},
  "geometry": {"coordinates":[-73.502858,40.781732],"type":"Point"}
}