{
  "type": "Feature",
  "properties": {
    "iso:country":"US",
    "sg:address":"50 Fisher Hill Rd",
    "sg:city":"Pine City",
    "sg:classifiers":[
        {
            "category":"Restaurant",
            "type":"Food & Drink"
        }
    ],
    "sg:phone":"+1 518 942 3065",
    "sg:postcode":"14871",
    "sg:province":"NY",
    "wof:name":"Country Inn",
    "wof:placetype":"venue"
},
  "geometry": {"coordinates":[-76.94700899999999,42.081907],"type":"Point"}
}