{
  "type": "Feature",
  "properties": {
    "addr:full":"125 State St Ste 100A Rochester NY 14614",
    "addr:housenumber":"125",
    "addr:postcode":"14614",
    "addr:street":"State St Ste 100A",
    "iso:country":"US",
    "sg:address":"125 State St Ste 100A",
    "sg:city":"Rochester",
    "sg:phone":"+1 585 697 0353",
    "sg:postcode":"14614",
    "sg:province":"NY",
    "wof:name":"Rogers Enterprises",
    "wof:placetype":"venue"
},
  "geometry": {"coordinates":[-77.614463,43.157666],"type":"Point"}
}