{
  "type": "Feature",
  "properties": {
    "addr:full":"531 Nostrand Ave Brooklyn NY 11216",
    "addr:housenumber":"531",
    "addr:postcode":"11216",
    "addr:street":"Nostrand Ave",
    "iso:country":"US",
    "sg:address":"531 Nostrand Ave",
    "sg:city":"Brooklyn",
    "sg:classifiers":[
        {
            "category":"Personal",
            "subcategory":"Beauty Salon",
            "type":"Services"
        }
    ],
    "sg:phone":"+1 718 789 5555",
    "sg:postcode":"11216",
    "sg:province":"NY",
    "wof:name":"Vic & Vic Unisex Barber Salon",
    "wof:placetype":"venue"
},
  "geometry": {"coordinates":[-73.94955299999999,40.679234],"type":"Point"}
}