{
  "type": "Feature",
  "properties": {
    "addr:full":"1789 84th St Brooklyn NY 11214",
    "addr:housenumber":"1789",
    "addr:postcode":"11214",
    "addr:street":"84Th St",
    "iso:country":"US",
    "sg:address":"1789 84th St",
    "sg:city":"Brooklyn",
    "sg:classifiers":[
        {
            "category":"Building & Trades",
            "subcategory":"Construction",
            "type":"Services"
        }
    ],
    "sg:phone":"+1 718 232 2959",
    "sg:postcode":"11214",
    "sg:province":"NY",
    "sg:tags":[
        "home",
        "general",
        "family",
        "contractor"
    ],
    "wof:name":"Badolato Contracting Corp",
    "wof:placetype":"venue"
},
  "geometry": {"coordinates":[-74.001437,40.609089],"type":"Point"}
}