{
  "type": "Feature",
  "properties": {
    "iso:country":"US",
    "sg:address":"6911 E Genesee St",
    "sg:city":"Fayetteville",
    "sg:classifiers":[
        {
            "category":"Personal",
            "subcategory":"Beauty Salon",
            "type":"Services"
        }
    ],
    "sg:phone":"+1   ",
    "sg:postcode":"13066",
    "sg:province":"NY",
    "sg:tags":[
        "shop"
    ],
    "wof:name":"Salon Salon",
    "wof:placetype":"venue"
},
  "geometry": {"coordinates":[-76.043272,43.028213],"type":"Point"}
}