{
  "type": "Feature",
  "properties": {
    "addr:full":"407 Sherman St Watertown NY 13601",
    "addr:housenumber":"407",
    "addr:postcode":"13601",
    "addr:street":"Sherman St",
    "iso:country":"US",
    "sg:address":"407 Sherman St",
    "sg:city":"Watertown",
    "sg:classifiers":[
        {
            "category":"Retail",
            "subcategory":"Repair Shop",
            "type":"Services"
        }
    ],
    "sg:phone":"+1 705 428 3573",
    "sg:postcode":"13601",
    "sg:province":"NY",
    "sg:tags":[
        "equipment",
        "sales"
    ],
    "wof:name":"A&K Equipment",
    "wof:placetype":"venue"
},
  "geometry": {"coordinates":[-75.91545499999999,43.971236],"type":"Point"}
}