{
  "type": "Feature",
  "properties": {
    "iso:country":"US",
    "sg:address":"407 Airport Rd",
    "sg:city":"Endicott",
    "sg:classifiers":[
        {
            "category":"Autos & Motor Vehicles",
            "subcategory":"Automobile Sales",
            "type":"Retail Goods"
        }
    ],
    "sg:phone":"+1 607 785 8710",
    "sg:postcode":"13760",
    "sg:province":"NY",
    "sg:tags":[
        "car",
        "dealer"
    ],
    "wof:name":"Absolute Emergency Vehicles",
    "wof:placetype":"venue"
},
  "geometry": {"coordinates":[-76.093553,42.086405],"type":"Point"}
}