{
  "type": "Feature",
  "properties": {
    "addr:full":"269 Main St Beacon NY 12508",
    "addr:housenumber":"269",
    "addr:postcode":"12508",
    "addr:street":"Main St",
    "iso:country":"US",
    "sg:address":"269 Main St",
    "sg:city":"Beacon",
    "sg:classifiers":[
        {
            "category":"Manufacturing",
            "subcategory":"Food",
            "type":"Manufacturing & Wholesale Goods"
        }
    ],
    "sg:phone":"+1 845 831 8240",
    "sg:postcode":"12508",
    "sg:province":"NY",
    "sg:tags":[
        "store",
        "candy",
        "mfg"
    ],
    "sg:website":"www.alpssweetshop.com",
    "wof:name":"Alps Sweet Shop",
    "wof:placetype":"venue"
},
  "geometry": {"coordinates":[-73.971802,41.506199],"type":"Point"}
}