{
  "type": "Feature",
  "properties": {
    "iso:country":"US",
    "sg:address":"700 Town Hall Dr",
    "sg:city":"Hudson",
    "sg:classifiers":[
        {
            "category":"Retail",
            "subcategory":"Funeral Services",
            "type":"Services"
        }
    ],
    "sg:phone":"+1   ",
    "sg:postcode":"12534",
    "sg:province":"NY",
    "wof:name":"M Grimaldi Funeral Home",
    "wof:placetype":"venue"
},
  "geometry": {"coordinates":[-73.760857,42.254399],"type":"Point"}
}