{
  "type": "Feature",
  "properties": {
    "addr:full":"44 Prince Street New York NY 10012",
    "addr:housenumber":"44",
    "addr:postcode":"10012",
    "addr:street":"Prince Street",
    "iso:country":"US",
    "sg:address":"44 Prince Street",
    "sg:city":"New York",
    "sg:classifiers":[
        {
            "category":"Restaurant",
            "type":"Food & Drink"
        }
    ],
    "sg:phone":"+1 212 343 8169",
    "sg:postcode":"10012",
    "sg:province":"NY",
    "wof:name":"Mekong Restaurant Corporation",
    "wof:placetype":"venue"
},
  "geometry": {"coordinates":[-73.995362,40.723345],"type":"Point"}
}