{
  "type": "Feature",
  "properties": {
    "addr:full":"2099 New York Ave Brooklyn NY 11210",
    "addr:housenumber":"2099",
    "addr:postcode":"11210",
    "addr:street":"New York Ave",
    "iso:country":"US",
    "sg:address":"2099 New York Ave",
    "sg:city":"Brooklyn",
    "sg:classifiers":[
        {
            "category":"Shopping",
            "subcategory":"Jewelry",
            "type":"Retail Goods"
        }
    ],
    "sg:phone":"+1 718 758 0970",
    "sg:postcode":"11210",
    "sg:province":"NY",
    "sg:tags":[
        "jeweler"
    ],
    "wof:name":"Pearl Collection",
    "wof:placetype":"venue"
},
  "geometry": {"coordinates":[-73.942744,40.620997],"type":"Point"}
}