{
  "type": "Feature",
  "properties": {
    "addr:full":"20661 45th Dr Bayside NY 11361",
    "addr:housenumber":"20661",
    "addr:postcode":"11361",
    "addr:street":"45Th Dr",
    "iso:country":"US",
    "sg:address":"20661 45th Dr",
    "sg:city":"Bayside",
    "sg:classifiers":[
        {
            "category":"Transit Center",
            "subcategory":"Freight",
            "type":"Transportation"
        }
    ],
    "sg:phone":"+1 718 423 9196",
    "sg:postcode":"11361",
    "sg:province":"NY",
    "sg:tags":[
        "container",
        "broker"
    ],
    "sg:website":"http://www.covicweb.net",
    "wof:name":"Covic International",
    "wof:placetype":"venue"
},
  "geometry": {"coordinates":[-73.775779,40.757048],"type":"Point"}
}