{
  "type": "Feature",
  "properties": {
    "addr:full":"1309 Lemoyne Ave Syracuse NY 13208",
    "addr:housenumber":"1309",
    "addr:postcode":"13208",
    "addr:street":"Lemoyne Ave",
    "iso:country":"US",
    "sg:address":"1309 Lemoyne Ave",
    "sg:city":"Syracuse",
    "sg:classifiers":[
        {
            "category":"Building & Trades",
            "subcategory":"Electrical",
            "type":"Services"
        }
    ],
    "sg:phone":"+1 315 455 5412",
    "sg:postcode":"13208",
    "sg:province":"NY",
    "sg:tags":[
        "electrical",
        "contractor"
    ],
    "wof:name":"Kelly Electric",
    "wof:placetype":"venue"
},
  "geometry": {"coordinates":[-76.15289199999999,43.080554],"type":"Point"}
}