{
  "type": "Feature",
  "properties": {
    "addr:full":"1211 Ave of the Americas New York NY 10036",
    "addr:housenumber":"1211",
    "addr:postcode":"10036",
    "addr:street":"Ave Of The Americas",
    "iso:country":"US",
    "sg:address":"1211 Ave of the Americas",
    "sg:city":"New York",
    "sg:classifiers":[
        {
            "category":"Professional",
            "subcategory":"Accounting & Tax Preparation",
            "type":"Services"
        }
    ],
    "sg:phone":"+1 212 284 1000",
    "sg:postcode":"10036",
    "sg:province":"NY",
    "sg:tags":[
        "accountant"
    ],
    "wof:name":"Margolin Winer & Evens",
    "wof:placetype":"venue"
},
  "geometry": {"coordinates":[-73.981621,40.758291],"type":"Point"}
}