{
  "type": "Feature",
  "properties": {
    "iso:country":"US",
    "sg:address":"1378 Coney Island Ave",
    "sg:city":"Brooklyn",
    "sg:classifiers":[
        {
            "category":"Shopping",
            "subcategory":"Clothing, Apparel, & Fashions",
            "type":"Retail Goods"
        }
    ],
    "sg:phone":"+1   ",
    "sg:postcode":"11230",
    "sg:province":"NY",
    "sg:tags":[
        "jewelry",
        "accessory"
    ],
    "wof:name":"Plan Ahead",
    "wof:placetype":"venue"
},
  "geometry": {"coordinates":[-73.965138,40.624374],"type":"Point"}
}