{
  "type": "Feature",
  "properties": {
    "iso:country":"US",
    "sg:address":"19 W 36 St",
    "sg:city":"New York",
    "sg:classifiers":[
        {
            "category":"Manufacturing",
            "subcategory":"Jewelry",
            "type":"Manufacturing & Wholesale Goods"
        }
    ],
    "sg:phone":"+1 212 997 1677",
    "sg:postcode":"10018",
    "sg:province":"NY",
    "wof:name":"Mig Manufacturing Inc",
    "wof:placetype":"venue"
},
  "geometry": {"coordinates":[-73.986363,40.750898],"type":"Point"}
}