{
  "type": "Feature",
  "properties": {
    "addr:full":"14 Penn Plaza 225 W 34th St Ste 700 New York NY 10122",
    "addr:housenumber":"14;225;700",
    "addr:postcode":"10122",
    "addr:street":"Penn;W 34Th St Ste",
    "iso:country":"US",
    "sg:address":"14 Penn Plaza 225 W 34th St Ste 700",
    "sg:city":"New York",
    "sg:classifiers":[
        {
            "category":"Travel",
            "subcategory":"Travel Agent",
            "type":"Entertainment"
        }
    ],
    "sg:phone":"+1 917 678 9172",
    "sg:postcode":"10122",
    "sg:province":"NY",
    "sg:website":"www.samedaypassport-visa.com/",
    "wof:name":"Sameday Passport & Visa Expedite Services",
    "wof:placetype":"venue"
},
  "geometry": {"coordinates":[-73.991736,40.751814],"type":"Point"}
}