{
  "type": "Feature",
  "properties": {
    "iso:country":"US",
    "sg:address":"5210 Church Ave",
    "sg:city":"Brooklyn",
    "sg:classifiers":[
        {
            "category":"Real Estate",
            "subcategory":"Real Estate Services",
            "type":"Services"
        }
    ],
    "sg:phone":"+1 718 346 0404",
    "sg:postcode":"11203",
    "sg:province":"NY",
    "wof:name":"Johnson George A Rl Est",
    "wof:placetype":"venue"
},
  "geometry": {"coordinates":[-73.928398,40.652199],"type":"Point"}
}