{
  "type": "Feature",
  "properties": {
    "addr:full":"1707 3rd Ave New York NY 10128",
    "addr:housenumber":"1707",
    "addr:postcode":"10128",
    "addr:street":"3Rd Ave",
    "iso:country":"US",
    "sg:address":"1707 3rd Ave",
    "sg:city":"New York",
    "sg:classifiers":[
        {
            "category":"Cinema",
            "subcategory":"Movie Rental",
            "type":"Entertainment"
        }
    ],
    "sg:phone":"+1 212 360 6862",
    "sg:postcode":"10128",
    "sg:province":"NY",
    "sg:tags":[
        "game",
        "video"
    ],
    "wof:name":"Blockbuster",
    "wof:placetype":"venue"
},
  "geometry": {"coordinates":[-73.94904699999999,40.785277],"type":"Point"}
}