{
  "type": "Feature",
  "properties": {
    "iso:country":"US",
    "sg:address":"174 W 76 St",
    "sg:city":"New York",
    "sg:classifiers":[
        {
            "category":"Health Services",
            "subcategory":"Doctor",
            "type":"Services"
        }
    ],
    "sg:phone":"+1   ",
    "sg:postcode":"10023",
    "sg:province":"NY",
    "sg:tags":[
        "medical"
    ],
    "wof:name":"Annette Kirszrot",
    "wof:placetype":"venue"
},
  "geometry": {"coordinates":[-73.97815799999999,40.780225],"type":"Point"}
}