{
  "type": "Feature",
  "properties": {
    "addr:full":"11 Scenic Cir Horseheads NY 14845",
    "addr:housenumber":"11",
    "addr:postcode":"14845",
    "addr:street":"Scenic Cir",
    "iso:country":"US",
    "sg:address":"11 Scenic Cir",
    "sg:city":"Horseheads",
    "sg:classifiers":[
        {
            "category":"Professional",
            "type":"Services"
        }
    ],
    "sg:phone":"+1   ",
    "sg:postcode":"14845",
    "sg:province":"NY",
    "wof:name":"Elaine Peckham",
    "wof:placetype":"venue"
},
  "geometry": {"coordinates":[-76.82250000000001,42.195812],"type":"Point"}
}