{
  "type": "Feature",
  "properties": {
    "addr:full":"157 W 79th St New York NY 10024",
    "addr:housenumber":"157",
    "addr:postcode":"10024",
    "addr:street":"W 79Th St",
    "iso:country":"US",
    "sg:address":"157 W 79th St",
    "sg:city":"New York",
    "sg:classifiers":[
        {
            "category":"Building & Trades",
            "subcategory":"Locksmith",
            "type":"Services"
        }
    ],
    "sg:phone":"+1 212 812 2660",
    "sg:postcode":"10024",
    "sg:province":"NY",
    "sg:tags":[
        "key"
    ],
    "wof:name":"AA Emergency Locksmith",
    "wof:placetype":"venue"
},
  "geometry": {"coordinates":[-73.97779800000001,40.783001],"type":"Point"}
}