{
  "type": "Feature",
  "properties": {
    "addr:full":"309 North Ave New Rochelle NY 10801",
    "addr:housenumber":"309",
    "addr:postcode":"10801",
    "addr:street":"North Ave",
    "iso:country":"US",
    "sg:address":"309 North Ave",
    "sg:city":"New Rochelle",
    "sg:classifiers":[
        {
            "category":"Real Estate",
            "subcategory":"Real Estate Agent",
            "type":"Services"
        }
    ],
    "sg:phone":"+1 914 235 7770",
    "sg:postcode":"10801",
    "sg:province":"NY",
    "wof:name":"Platzner Intnl Group",
    "wof:placetype":"venue"
},
  "geometry": {"coordinates":[-73.78376900000001,40.913309],"type":"Point"}
}