{
  "type": "Feature",
  "properties": {
    "addr:full":"43 Herkimer Pl Brooklyn NY 11216",
    "addr:housenumber":"43",
    "addr:postcode":"11216",
    "addr:street":"Herkimer Pl",
    "iso:country":"US",
    "sg:address":"43 Herkimer Pl",
    "sg:city":"Brooklyn",
    "sg:classifiers":[
        {
            "category":"Retail",
            "subcategory":"Auto Repair",
            "type":"Services"
        }
    ],
    "sg:phone":"+1 718 399 1686",
    "sg:postcode":"11216",
    "sg:province":"NY",
    "sg:tags":[
        "repairing",
        "automobile"
    ],
    "wof:name":"Jawanna & Donna Autos Inc",
    "wof:placetype":"venue"
},
  "geometry": {"coordinates":[-73.95077999999999,40.679107],"type":"Point"}
}