{
  "type": "Feature",
  "properties": {
    "iso:country":"US",
    "sg:address":"446 Travis Ave",
    "sg:city":"Staten Island",
    "sg:classifiers":[
        {
            "category":"Professional",
            "subcategory":"Management & Consulting",
            "type":"Services"
        }
    ],
    "sg:phone":"+1 718 698 3636",
    "sg:postcode":"10314",
    "sg:province":"NY",
    "sg:tags":[
        "consultant",
        "educational"
    ],
    "wof:name":"Educational Support Systems",
    "wof:placetype":"venue"
},
  "geometry": {"coordinates":[-74.15435600000001,40.588556],"type":"Point"}
}