{
  "type": "Feature",
  "properties": {
    "iso:country":"US",
    "sg:address":"26 Lincoln Ter",
    "sg:city":"Yonkers",
    "sg:classifiers":[
        {
            "category":"Manufacturing",
            "subcategory":"Metals",
            "type":"Manufacturing & Wholesale Goods"
        }
    ],
    "sg:phone":"+1 914 963 2472",
    "sg:postcode":"10701",
    "sg:province":"NY",
    "sg:tags":[
        "metal-wholesale",
        "specialty",
        "manufacturer"
    ],
    "wof:name":"Metalmorphosis",
    "wof:placetype":"venue"
},
  "geometry": {"coordinates":[-73.89536699999999,40.948056],"type":"Point"}
}