{
  "type": "Feature",
  "properties": {
    "addr:full":"6006 New Hartford St Wolcott NY 14590",
    "addr:housenumber":"6006",
    "addr:postcode":"14590",
    "addr:street":"New Hartford St",
    "iso:country":"US",
    "sg:address":"6006 New Hartford St",
    "sg:city":"Wolcott",
    "sg:classifiers":[
        {
            "category":"Shopping",
            "subcategory":"Department Store",
            "type":"Retail Goods"
        }
    ],
    "sg:phone":"+1 315 594 1368",
    "sg:postcode":"14590",
    "sg:province":"NY",
    "wof:name":"Family Dollar Store",
    "wof:placetype":"venue"
},
  "geometry": {"coordinates":[-76.814953,43.21961],"type":"Point"}
}