{
  "type": "Feature",
  "properties": {
    "addr:full":"224 W 35th St New York NY 10001",
    "addr:housenumber":"224",
    "addr:postcode":"10001",
    "addr:street":"W 35Th St",
    "iso:country":"US",
    "sg:address":"224 W 35th St",
    "sg:city":"New York",
    "sg:classifiers":[
        {
            "category":"Professional",
            "subcategory":"Printing & Photocopies",
            "type":"Services"
        }
    ],
    "sg:phone":"+1 212 560 9529",
    "sg:postcode":"10001",
    "sg:province":"NY",
    "sg:website":"www.popularprinting.com",
    "wof:name":"Popular Printing",
    "wof:placetype":"venue"
},
  "geometry": {"coordinates":[-73.99128,40.751881],"type":"Point"}
}