{
  "type": "Feature",
  "properties": {
    "addr:full":"49 W 46 St New York NY 10036",
    "addr:housenumber":"49",
    "addr:postcode":"10036",
    "addr:street":"W 46 St",
    "iso:country":"US",
    "sg:address":"49 W 46 St",
    "sg:city":"New York",
    "sg:classifiers":[
        {
            "category":"Wholesale",
            "subcategory":"Jewelry",
            "type":"Manufacturing & Wholesale Goods"
        }
    ],
    "sg:phone":"+1 212 869 8448",
    "sg:postcode":"10036",
    "sg:province":"NY",
    "sg:tags":[
        "watch"
    ],
    "wof:name":"Aqua Master Ltd",
    "wof:placetype":"venue"
},
  "geometry": {"coordinates":[-73.98102,40.756789],"type":"Point"}
}