{
  "type": "Feature",
  "properties": {
    "addr:full":"515 Targee St Staten Island NY 10304",
    "addr:housenumber":"515",
    "addr:postcode":"10304",
    "addr:street":"Targee St",
    "iso:country":"US",
    "sg:address":"515 Targee St",
    "sg:city":"Staten Island",
    "sg:classifiers":[
        {
            "category":"Food & Beverages",
            "subcategory":"Groceries & Convenience Stores",
            "type":"Retail Goods"
        }
    ],
    "sg:phone":"+1 718 442 6728",
    "sg:postcode":"10304",
    "sg:province":"NY",
    "wof:name":"Targee Farm",
    "wof:placetype":"venue"
},
  "geometry": {"coordinates":[-74.084575,40.614619],"type":"Point"}
}