{
  "type": "Feature",
  "properties": {
    "addr:full":"7979 Victor-Pittsford Rd Victor NY 14564",
    "addr:housenumber":"7979",
    "addr:postcode":"14564",
    "addr:street":"Victor-Pittsford Rd",
    "iso:country":"US",
    "sg:address":"7979 Victor-Pittsford Rd",
    "sg:city":"Victor",
    "sg:classifiers":[
        {
            "category":"Professional",
            "subcategory":"Accounting & Tax Preparation",
            "type":"Services"
        }
    ],
    "sg:phone":"+1 585 223 3607",
    "sg:postcode":"14564",
    "sg:province":"NY",
    "sg:tags":[
        "return",
        "filing"
    ],
    "sg:website":"www.hrblock.com",
    "wof:name":"H & R Block Tax Svc",
    "wof:placetype":"venue"
},
  "geometry": {"coordinates":[-77.440434,43.03059],"type":"Point"}
}