{
  "type": "Feature",
  "properties": {
    "iso:country":"US",
    "sg:address":"8 W Cavalry Dr",
    "sg:city":"New City",
    "sg:classifiers":[
        {
            "category":"Real Estate",
            "subcategory":"Real Estate Agent",
            "type":"Services"
        }
    ],
    "sg:phone":"+1 610 695 9516",
    "sg:postcode":"10956",
    "sg:province":"NY",
    "wof:name":"Hageney Agency The",
    "wof:placetype":"venue"
},
  "geometry": {"coordinates":[-73.986254,41.15368],"type":"Point"}
}