{
  "type": "Feature",
  "properties": {
    "iso:country":"US",
    "sg:address":"391 Case Rd",
    "sg:city":"Bainbridge",
    "sg:classifiers":[
        {
            "category":"Manufacturing",
            "subcategory":"Lumber",
            "type":"Manufacturing & Wholesale Goods"
        }
    ],
    "sg:phone":"+1 607 967 3335",
    "sg:postcode":"13733",
    "sg:province":"NY",
    "sg:tags":[
        "logging"
    ],
    "wof:name":"D & H Logging",
    "wof:placetype":"venue"
},
  "geometry": {"coordinates":[-75.506803,42.321297],"type":"Point"}
}