{
  "type": "Feature",
  "properties": {
    "iso:country":"US",
    "sg:address":"250 State Hwy 59",
    "sg:city":"Nanuet",
    "sg:classifiers":[
        {
            "category":"Shopping",
            "subcategory":"Jewelry",
            "type":"Retail Goods"
        }
    ],
    "sg:phone":"+1 845 624 4020",
    "sg:postcode":"10954",
    "sg:province":"NY",
    "sg:tags":[
        "jeweler"
    ],
    "wof:name":"Zareh Jewelry",
    "wof:placetype":"venue"
},
  "geometry": {"coordinates":[-74.00295699999999,41.094063],"type":"Point"}
}