{
  "type": "Feature",
  "properties": {
    "addr:full":"1064 James St Syracuse NY 13203",
    "addr:housenumber":"1064",
    "addr:postcode":"13203",
    "addr:street":"James St",
    "iso:country":"US",
    "sg:address":"1064 James St",
    "sg:city":"Syracuse",
    "sg:classifiers":[
        {
            "category":"Communications",
            "subcategory":"Radio Station",
            "type":"Services"
        }
    ],
    "sg:phone":"+1   ",
    "sg:postcode":"13203",
    "sg:province":"NY",
    "sg:tags":[
        "broadcast"
    ],
    "wof:name":"Citadel Communications",
    "wof:placetype":"venue"
},
  "geometry": {"coordinates":[-76.13338400000001,43.0593],"type":"Point"}
}