{
  "type": "Feature",
  "properties": {
    "iso:country":"US",
    "sg:address":"6221 Goodrich Rd",
    "sg:city":"Clarence Center",
    "sg:classifiers":[
        {
            "category":"Government",
            "subcategory":"Office",
            "type":"Public Place"
        }
    ],
    "sg:phone":"+1 716 741 8952",
    "sg:postcode":"14032",
    "sg:province":"NY",
    "sg:tags":[
        "village"
    ],
    "wof:name":"Clarence Town Engineer",
    "wof:placetype":"venue"
},
  "geometry": {"coordinates":[-78.637018,43.017848],"type":"Point"}
}