{
  "type": "Feature",
  "properties": {
    "iso:country":"US",
    "sg:address":"55 Water St",
    "sg:city":"New York",
    "sg:classifiers":[
        {
            "category":"Banks & Credit Unions",
            "subcategory":"Investment Brokerage",
            "type":"Services"
        },
        {
            "category":"Banks & Credit Unions",
            "subcategory":"Financial Services",
            "type":"Services"
        }
    ],
    "sg:phone":"+1 212 855 1000",
    "sg:postcode":"10004",
    "sg:province":"NY",
    "sg:tags":[
        "b",
        "business",
        "money",
        "funds",
        "security",
        "market"
    ],
    "sg:website":"www.dtcc.com",
    "wof:name":"Depository Trust Clearing Corp",
    "wof:placetype":"venue"
},
  "geometry": {"coordinates":[-74.009326,40.703716],"type":"Point"}
}