{
  "type": "Feature",
  "properties": {
    "iso:country":"US",
    "sg:address":"2 W 47 St",
    "sg:city":"New York",
    "sg:classifiers":[
        {
            "category":"Manufacturing",
            "subcategory":"Jewelry",
            "type":"Manufacturing & Wholesale Goods"
        }
    ],
    "sg:phone":"+1 212 869 1070",
    "sg:postcode":"10036",
    "sg:province":"NY",
    "sg:tags":[
        "parts",
        "casting"
    ],
    "sg:website":"www.gwcasting.com",
    "wof:name":"G & W Castings Inc",
    "wof:placetype":"venue"
},
  "geometry": {"coordinates":[-73.98179399999999,40.758021],"type":"Point"}
}