{
  "type": "Feature",
  "properties": {
    "addr:full":"645 Nott St Schenectady NY 12308",
    "addr:housenumber":"645",
    "addr:postcode":"12308",
    "addr:street":"Nott St",
    "iso:country":"US",
    "sg:address":"645 Nott St",
    "sg:city":"Schenectady",
    "sg:classifiers":[
        {
            "category":"Banks & Credit Unions",
            "subcategory":"Bank",
            "type":"Services"
        }
    ],
    "sg:phone":"+1 518 370 7735",
    "sg:postcode":"12308",
    "sg:province":"NY",
    "sg:tags":[
        "state",
        "commercial"
    ],
    "wof:name":"Fleet",
    "wof:placetype":"venue"
},
  "geometry": {"coordinates":[-73.927415,42.820089],"type":"Point"}
}