{
  "type": "Feature",
  "properties": {
    "iso:country":"US",
    "sg:address":"4 W Red Oak Ln",
    "sg:city":"White Plains",
    "sg:classifiers":[
        {
            "category":"Professional",
            "subcategory":"Business Services",
            "type":"Services"
        },
        {
            "category":"Professional",
            "subcategory":"Accounting & Tax Preparation",
            "type":"Services"
        }
    ],
    "sg:phone":"+1 914 644 6161",
    "sg:postcode":"10604",
    "sg:province":"NY",
    "sg:tags":[
        "accountant"
    ],
    "wof:name":"Pollan Mauner & Wess",
    "wof:placetype":"venue"
},
  "geometry": {"coordinates":[-73.723361,41.016279],"type":"Point"}
}