{
  "type": "Feature",
  "properties": {
    "addr:full":"480 Mamaroneck Ave White Plains NY 10605",
    "addr:housenumber":"480",
    "addr:postcode":"10605",
    "addr:street":"Mamaroneck Ave",
    "iso:country":"US",
    "sg:address":"480 Mamaroneck Ave",
    "sg:city":"White Plains",
    "sg:classifiers":[
        {
            "category":"Shopping",
            "subcategory":"Gifts & Souvenirs",
            "type":"Retail Goods"
        }
    ],
    "sg:phone":"+1   ",
    "sg:postcode":"10605",
    "sg:province":"NY",
    "sg:tags":[
        "printing",
        "commercial"
    ],
    "wof:name":"Saxon Cards and Gifts",
    "wof:placetype":"venue"
},
  "geometry": {"coordinates":[-73.759719,41.022643],"type":"Point"}
}