{
  "type": "Feature",
  "properties": {
    "addr:full":"1 Buffington St Watervliet NY 12189",
    "addr:housenumber":"1",
    "addr:postcode":"12189",
    "addr:street":"Buffington St",
    "iso:country":"US",
    "sg:address":"1 Buffington St",
    "sg:city":"Watervliet",
    "sg:classifiers":[
        {
            "category":"Restaurant",
            "type":"Food & Drink"
        }
    ],
    "sg:phone":"+1 518 266 3617",
    "sg:postcode":"12189",
    "sg:province":"NY",
    "wof:name":"Mwr/Post Restaurant",
    "wof:placetype":"venue"
},
  "geometry": {"coordinates":[-73.70755,42.719219],"type":"Point"}
}