{
  "type": "Feature",
  "properties": {
    "iso:country":"US",
    "sg:address":"145 Nassau St",
    "sg:city":"New York",
    "sg:classifiers":[
        {
            "category":"Professional",
            "subcategory":"Art Services",
            "type":"Services"
        }
    ],
    "sg:phone":"+1 917 716 2322",
    "sg:postcode":"10038",
    "sg:province":"NY",
    "sg:tags":[
        "photographer"
    ],
    "sg:website":"www.thomasroemischer.com",
    "wof:name":"Thomas Roemischer Photography",
    "wof:placetype":"venue"
},
  "geometry": {"coordinates":[-74.006258,40.71143],"type":"Point"}
}