{
  "type": "Feature",
  "properties": {
    "iso:country":"US",
    "sg:address":"851 Merrick Rd",
    "sg:city":"Baldwin",
    "sg:classifiers":[
        {
            "category":"Shopping",
            "subcategory":"Pharmacy",
            "type":"Retail Goods"
        }
    ],
    "sg:phone":"+1   ",
    "sg:postcode":"11510",
    "sg:province":"NY",
    "wof:name":"Nassau Chemists Inc",
    "wof:placetype":"venue"
},
  "geometry": {"coordinates":[-73.612213,40.650825],"type":"Point"}
}