{
  "type": "Feature",
  "properties": {
    "addr:full":"2861 Steinway Street Astoria NY 11103",
    "addr:housenumber":"2861",
    "addr:postcode":"11103",
    "addr:street":"Steinway Street",
    "iso:country":"US",
    "sg:address":"2861 Steinway Street",
    "sg:city":"Astoria",
    "sg:classifiers":[
        {
            "category":"Personal",
            "subcategory":"Nail Salon",
            "type":"Services"
        }
    ],
    "sg:phone":"+1 718 274 6145",
    "sg:postcode":"11103",
    "sg:province":"NY",
    "wof:name":"Pink Nail",
    "wof:placetype":"venue"
},
  "geometry": {"coordinates":[-73.914704,40.76403],"type":"Point"}
}