{
  "type": "Feature",
  "properties": {
    "iso:country":"US",
    "sg:address":"145 Stanton Street",
    "sg:city":"New York",
    "sg:classifiers":[
        {
            "category":"Education",
            "subcategory":"School",
            "type":"Public Place"
        }
    ],
    "sg:phone":"+1 212 505 6338",
    "sg:postcode":"10002",
    "sg:province":"NY",
    "sg:tags":[
        "high",
        "middle",
        "elementary"
    ],
    "wof:name":"Grand Street Beacon Cc At Jhs 22",
    "wof:placetype":"venue"
},
  "geometry": {"coordinates":[-73.986152,40.720737],"type":"Point"}
}