{
  "type": "Feature",
  "properties": {
    "iso:country":"US",
    "sg:address":"64 Applegrove Dr",
    "sg:city":"Rochester",
    "sg:classifiers":[
        {
            "category":"Building & Trades",
            "subcategory":"Construction",
            "type":"Services"
        }
    ],
    "sg:phone":"+1 585 720 9652",
    "sg:postcode":"14612",
    "sg:province":"NY",
    "sg:tags":[
        "window",
        "replacement",
        "door",
        "contractor"
    ],
    "wof:name":"Just Windows",
    "wof:placetype":"venue"
},
  "geometry": {"coordinates":[-77.718525,43.251687],"type":"Point"}
}