{
  "type": "Feature",
  "properties": {
    "addr:full":"362 Main St Setauket NY 11733",
    "addr:housenumber":"362",
    "addr:postcode":"11733",
    "addr:street":"Main St",
    "iso:country":"US",
    "sg:address":"362 Main St",
    "sg:city":"Setauket",
    "sg:classifiers":[
        {
            "category":"Professional",
            "subcategory":"Computer Services",
            "type":"Services"
        }
    ],
    "sg:phone":"+1 631 689 0122",
    "sg:postcode":"11733",
    "sg:province":"NY",
    "sg:tags":[
        "website",
        "design",
        "network",
        "system"
    ],
    "wof:name":"Sharon Kormendi",
    "wof:placetype":"venue"
},
  "geometry": {"coordinates":[-73.093811,40.94466],"type":"Point"}
}