{
  "type": "Feature",
  "properties": {
    "iso:country":"US",
    "sg:address":"30 Central Park Plz",
    "sg:city":"Buffalo",
    "sg:classifiers":[
        {
            "category":"Health Services",
            "subcategory":"Doctor",
            "type":"Services"
        }
    ],
    "sg:phone":"+1 716 834 3272",
    "sg:postcode":"14214",
    "sg:province":"NY",
    "sg:tags":[
        "medical"
    ],
    "wof:name":"Community Services Dept",
    "wof:placetype":"venue"
},
  "geometry": {"coordinates":[-78.833039,42.938372],"type":"Point"}
}