{
  "type": "Feature",
  "properties": {
    "addr:full":"79 E Lincoln Ave Valley Stream NY 11580",
    "addr:housenumber":"79",
    "addr:postcode":"11580",
    "addr:street":"E Lincoln Ave",
    "iso:country":"US",
    "sg:address":"79 E Lincoln Ave",
    "sg:city":"Valley Stream",
    "sg:classifiers":[
        {
            "category":"Communications",
            "subcategory":"Film & Video Production",
            "type":"Services"
        }
    ],
    "sg:phone":"+1 516 561 0313",
    "sg:postcode":"11580",
    "sg:province":"NY",
    "sg:tags":[
        "consultant",
        "audio"
    ],
    "wof:name":"B C Constructin Svc Inc",
    "wof:placetype":"venue"
},
  "geometry": {"coordinates":[-73.694016,40.663056],"type":"Point"}
}