{
  "type": "Feature",
  "properties": {
    "addr:full":"191 Main St Dansville NY 14437",
    "addr:housenumber":"191",
    "addr:postcode":"14437",
    "addr:street":"Main St",
    "iso:country":"US",
    "sg:address":"191 Main St",
    "sg:city":"Dansville",
    "sg:classifiers":[
        {
            "category":"Banks & Credit Unions",
            "subcategory":"Bank",
            "type":"Services"
        }
    ],
    "sg:phone":"+1 585 335 2480",
    "sg:postcode":"14437",
    "sg:province":"NY",
    "sg:tags":[
        "mortgage"
    ],
    "wof:name":"Enterprise Mortgage Solutions",
    "wof:placetype":"venue"
},
  "geometry": {"coordinates":[-77.69713299999999,42.56216],"type":"Point"}
}