{
  "type": "Feature",
  "properties": {
    "iso:country":"US",
    "sg:address":"1444 Massachusetts Ave",
    "sg:city":"Troy",
    "sg:classifiers":[
        {
            "category":"Health Services",
            "subcategory":"Doctor",
            "type":"Services"
        }
    ],
    "sg:phone":"+1 518 271 9155",
    "sg:postcode":"12180",
    "sg:province":"NY",
    "sg:tags":[
        "physician",
        "stomach",
        "pediatrics-gastroenterology",
        "gastroenterology",
        "surgeons",
        "surgeon",
        "intestines"
    ],
    "wof:name":"Kumar Arbind MD",
    "wof:placetype":"venue"
},
  "geometry": {"coordinates":[-73.67403899999999,42.742833],"type":"Point"}
}