{
  "type": "Feature",
  "properties": {
    "addr:full":"201 Ferncliff Ave Liverpool NY 13088",
    "addr:housenumber":"201",
    "addr:postcode":"13088",
    "addr:street":"Ferncliff Ave",
    "iso:country":"US",
    "sg:address":"201 Ferncliff Ave",
    "sg:city":"Liverpool",
    "sg:classifiers":[
        {
            "category":"Real Estate",
            "subcategory":"Real Estate Services",
            "type":"Services"
        }
    ],
    "sg:phone":"+1 315 451 3074",
    "sg:postcode":"13088",
    "sg:province":"NY",
    "sg:tags":[
        "management"
    ],
    "wof:name":"Tipp Hill Associates",
    "wof:placetype":"venue"
},
  "geometry": {"coordinates":[-76.179802,43.090111],"type":"Point"}
}