{
  "type": "Feature",
  "properties": {
    "iso:country":"US",
    "sg:address":"441 W 53 St",
    "sg:city":"New York",
    "sg:classifiers":[
        {
            "category":"Professional",
            "subcategory":"Business Services",
            "type":"Services"
        }
    ],
    "sg:phone":"+1 212 765 7500",
    "sg:postcode":"10019",
    "sg:province":"NY",
    "sg:tags":[
        "recording",
        "production",
        "studio"
    ],
    "wof:name":"Avatar Studios",
    "wof:placetype":"venue"
},
  "geometry": {"coordinates":[-73.98950600000001,40.766137],"type":"Point"}
}