{
  "type": "Feature",
  "properties": {
    "addr:full":"5218 New Utrecht Ave Brooklyn NY 11219",
    "addr:housenumber":"5218",
    "addr:postcode":"11219",
    "addr:street":"New Utrecht Ave",
    "iso:country":"US",
    "sg:address":"5218 New Utrecht Ave",
    "sg:city":"Brooklyn",
    "sg:classifiers":[
        {
            "category":"Wholesale",
            "subcategory":"Poultry",
            "type":"Manufacturing & Wholesale Goods"
        }
    ],
    "sg:phone":"+1 718 871 3680",
    "sg:postcode":"11219",
    "sg:province":"NY",
    "wof:name":"Sandor & Anne Berger",
    "wof:placetype":"venue"
},
  "geometry": {"coordinates":[-73.995239,40.63339],"type":"Point"}
}