{
  "type": "Feature",
  "properties": {
    "addr:full":"684 Richmond Rd Staten Island NY 10304",
    "addr:housenumber":"684",
    "addr:postcode":"10304",
    "addr:street":"Richmond Rd",
    "iso:country":"US",
    "sg:address":"684 Richmond Rd",
    "sg:city":"Staten Island",
    "sg:classifiers":[
        {
            "category":"Building & Trades",
            "subcategory":"Electrical",
            "type":"Services"
        }
    ],
    "sg:phone":"+1 718 727 3149",
    "sg:postcode":"10304",
    "sg:province":"NY",
    "sg:tags":[
        "electrician",
        "electric",
        "contractor"
    ],
    "wof:name":"A J Caruso Electric Inc",
    "wof:placetype":"venue"
},
  "geometry": {"coordinates":[-74.089699,40.609901],"type":"Point"}
}