{
  "type": "Feature",
  "properties": {
    "addr:full":"89 Washington Ave Albany NY 12205",
    "addr:housenumber":"89",
    "addr:postcode":"12205",
    "addr:street":"Washington Ave",
    "iso:country":"US",
    "sg:address":"89 Washington Ave",
    "sg:city":"Albany",
    "sg:classifiers":[
        {
            "category":"Government",
            "subcategory":"Office",
            "type":"Public Place"
        }
    ],
    "sg:phone":"+1 518 474 3852",
    "sg:postcode":"12205",
    "sg:province":"NY",
    "sg:tags":[
        "state",
        "program"
    ],
    "sg:website":"www.nysed.gov",
    "wof:name":"Education Dept",
    "wof:placetype":"venue"
},
  "geometry": {"coordinates":[-73.818459,42.700668],"type":"Point"}
}