{
  "type": "Feature",
  "properties": {
    "addr:full":"5 E Main St Canisteo NY 14823",
    "addr:housenumber":"5",
    "addr:postcode":"14823",
    "addr:street":"E Main St",
    "iso:country":"US",
    "sg:address":"5 E Main St",
    "sg:city":"Canisteo",
    "sg:classifiers":[
        {
            "category":"Home & Garden",
            "subcategory":"Household Appliances",
            "type":"Retail Goods"
        },
        {
            "category":"Building & Trades",
            "subcategory":"Construction",
            "type":"Services"
        }
    ],
    "sg:phone":"+1 607 698 4444",
    "sg:postcode":"14823",
    "sg:province":"NY",
    "sg:tags":[
        "systems-repairing",
        "dishwashing",
        "system",
        "specialty",
        "machine",
        "equipment",
        "heating",
        "contractor",
        "air conditioning"
    ],
    "wof:name":"Mike Palmer Heating & Air Conditioning",
    "wof:placetype":"venue"
},
  "geometry": {"coordinates":[-77.604057,42.269646],"type":"Point"}
}