{
  "type": "Feature",
  "properties": {
    "iso:country":"US",
    "sg:address":"25 W Main St",
    "sg:city":"Cambridge",
    "sg:classifiers":[
        {
            "category":"Banks & Credit Unions",
            "subcategory":"Bank",
            "type":"Services"
        }
    ],
    "sg:phone":"+1 518 677 2642",
    "sg:postcode":"12816",
    "sg:province":"NY",
    "sg:tags":[
        "national",
        "commercial"
    ],
    "wof:name":"Glens Falls Nat Bnk & Tr Co",
    "wof:placetype":"venue"
},
  "geometry": {"coordinates":[-73.386034,43.028131],"type":"Point"}
}