{
  "type": "Feature",
  "properties": {
    "addr:full":"361 E 86th Street New York NY 10028",
    "addr:housenumber":"361",
    "addr:postcode":"10028",
    "addr:street":"E 86Th Street",
    "iso:country":"US",
    "sg:address":"361 E 86th Street",
    "sg:city":"New York",
    "sg:classifiers":[
        {
            "category":"Shopping",
            "subcategory":"Florist",
            "type":"Retail Goods"
        }
    ],
    "sg:phone":"+1 212 289 5323",
    "sg:postcode":"10028",
    "sg:province":"NY",
    "wof:name":"Hybrid Flowers Ltd",
    "wof:placetype":"venue"
},
  "geometry": {"coordinates":[-73.949575,40.77708],"type":"Point"}
}