{
  "type": "Feature",
  "properties": {
    "iso:country":"US",
    "sg:address":"348 Northern Blvd",
    "sg:city":"Albany",
    "sg:classifiers":[
        {
            "category":"Restaurant",
            "type":"Food & Drink"
        }
    ],
    "sg:phone":"+1   ",
    "sg:postcode":"12204",
    "sg:province":"NY",
    "sg:tags":[
        "eating"
    ],
    "wof:name":"Davids Fine Foods",
    "wof:placetype":"venue"
},
  "geometry": {"coordinates":[-73.753288,42.670925],"type":"Point"}
}