{
  "type": "Feature",
  "properties": {
    "addr:full":"2703 23rd Ave Astoria NY 11105",
    "addr:housenumber":"2703",
    "addr:postcode":"11105",
    "addr:street":"23Rd Ave",
    "iso:country":"US",
    "sg:address":"2703 23rd Ave",
    "sg:city":"Astoria",
    "sg:classifiers":[
        {
            "category":"Restaurant",
            "type":"Food & Drink"
        }
    ],
    "sg:postcode":"11105",
    "sg:province":"NY",
    "wof:name":"Sandro's Latin Food Restaurant",
    "wof:placetype":"venue"
},
  "geometry": {"coordinates":[-73.91509499999999,40.77596],"type":"Point"}
}