{
  "type": "Feature",
  "properties": {
    "addr:full":"143 W 29th St Lbby New York NY 10001",
    "addr:housenumber":"143",
    "addr:postcode":"10001",
    "addr:street":"W 29Th St",
    "iso:country":"US",
    "sg:address":"143 W 29th St Lbby",
    "sg:city":"New York",
    "sg:classifiers":[
        {
            "category":"Wholesale",
            "subcategory":"Home Furnishings",
            "type":"Manufacturing & Wholesale Goods"
        }
    ],
    "sg:phone":"+1 212 564 0034",
    "sg:postcode":"10001",
    "sg:province":"NY",
    "sg:tags":[
        "blind",
        "shade"
    ],
    "wof:name":"K J Textiles International",
    "wof:placetype":"venue"
},
  "geometry": {"coordinates":[-73.991302,40.7472],"type":"Point"}
}