{
  "type": "Feature",
  "properties": {
    "iso:country":"US",
    "sg:address":"1841 Broadway",
    "sg:city":"New York",
    "sg:classifiers":[
        {
            "category":"Professional",
            "type":"Services"
        }
    ],
    "sg:phone":"+1 212 397 6791",
    "sg:postcode":"10023",
    "sg:province":"NY",
    "sg:tags":[
        "establishment"
    ],
    "wof:name":"Harold Gordon Assoc",
    "wof:placetype":"venue"
},
  "geometry": {"coordinates":[-73.98218799999999,40.769528],"type":"Point"}
}