{
  "type": "Feature",
  "properties": {
    "iso:country":"US",
    "sg:address":"1031 Lexington Ave",
    "sg:city":"New York",
    "sg:classifiers":[
        {
            "category":"Retail",
            "subcategory":"Laundry & Dry Cleaning",
            "type":"Services"
        }
    ],
    "sg:phone":"+1 212 734 8360",
    "sg:postcode":"10021",
    "sg:province":"NY",
    "sg:tags":[
        "cleaner"
    ],
    "wof:name":"Chang's Cleaners",
    "wof:placetype":"venue"
},
  "geometry": {"coordinates":[-73.961502,40.771599],"type":"Point"}
}