{
  "type": "Feature",
  "properties": {
    "addr:full":"224 25th St Brooklyn NY 11232",
    "addr:housenumber":"224",
    "addr:postcode":"11232",
    "addr:street":"25Th St",
    "iso:country":"US",
    "sg:address":"224 25th St",
    "sg:city":"Brooklyn",
    "sg:classifiers":[
        {
            "category":"Retail",
            "subcategory":"Auto Repair",
            "type":"Services"
        }
    ],
    "sg:phone":"+1   ",
    "sg:postcode":"11232",
    "sg:province":"NY",
    "sg:tags":[
        "body"
    ],
    "wof:name":"Tonys Auto Body Works",
    "wof:placetype":"venue"
},
  "geometry": {"coordinates":[-73.995918,40.659143],"type":"Point"}
}