{
  "type": "Feature",
  "properties": {
    "iso:country":"US",
    "sg:address":"595 State Hwy 25A",
    "sg:city":"Rocky Point",
    "sg:classifiers":[
        {
            "category":"Professional",
            "type":"Services"
        }
    ],
    "sg:phone":"+1 631 744 8578",
    "sg:postcode":"11778",
    "sg:province":"NY",
    "sg:tags":[
        "establishment"
    ],
    "wof:name":"Periphonics Corp",
    "wof:placetype":"venue"
},
  "geometry": {"coordinates":[-72.930493,40.946615],"type":"Point"}
}