{
  "type": "Feature",
  "properties": {
    "iso:country":"US",
    "sg:address":"853 Broadway",
    "sg:city":"New York",
    "sg:classifiers":[
        {
            "category":"Government",
            "subcategory":"Office",
            "type":"Public Place"
        }
    ],
    "sg:phone":"+1 212 674 5153",
    "sg:postcode":"10003",
    "sg:province":"NY",
    "sg:tags":[
        "legislative",
        "body"
    ],
    "wof:name":"Assembly Member Deborah Glick",
    "wof:placetype":"venue"
},
  "geometry": {"coordinates":[-73.99095699999999,40.734086],"type":"Point"}
}