{
  "type": "Feature",
  "properties": {
    "iso:country":"US",
    "sg:address":"132 N Wellwood Ave",
    "sg:city":"Lindenhurst",
    "sg:classifiers":[
        {
            "category":"Shopping",
            "type":"Retail Goods"
        }
    ],
    "sg:phone":"+1 631 225 1720",
    "sg:postcode":"11757",
    "sg:province":"NY",
    "sg:tags":[
        "plumbing",
        "heating",
        "supply"
    ],
    "wof:name":"C & S Plumbing & Htg Sups Inc",
    "wof:placetype":"venue"
},
  "geometry": {"coordinates":[-73.373749,40.687062],"type":"Point"}
}