{
  "type": "Feature",
  "properties": {
    "addr:full":"163 W Ferry St Buffalo NY 14213",
    "addr:housenumber":"163",
    "addr:postcode":"14213",
    "addr:street":"W Ferry St",
    "iso:country":"US",
    "sg:address":"163 W Ferry St",
    "sg:city":"Buffalo",
    "sg:classifiers":[
        {
            "category":"Food & Beverages",
            "subcategory":"Groceries & Convenience Stores",
            "type":"Retail Goods"
        }
    ],
    "sg:phone":"+1   ",
    "sg:postcode":"14213",
    "sg:province":"NY",
    "wof:name":"Daily Grocery",
    "wof:placetype":"venue"
},
  "geometry": {"coordinates":[-78.894747,42.915096],"type":"Point"}
}