{
  "type": "Feature",
  "properties": {
    "addr:full":"174 Vassar Rd Poughkeepsie NY 12603",
    "addr:housenumber":"174",
    "addr:postcode":"12603",
    "addr:street":"Vassar Rd",
    "iso:country":"US",
    "sg:address":"174 Vassar Rd",
    "sg:city":"Poughkeepsie",
    "sg:classifiers":[
        {
            "category":"Education",
            "subcategory":"School",
            "type":"Public Place"
        }
    ],
    "sg:phone":"+1 845 463 7860",
    "sg:postcode":"12603",
    "sg:province":"NY",
    "wof:name":"Vassar Road Elementary School",
    "wof:placetype":"venue"
},
  "geometry": {"coordinates":[-73.88921499999999,41.635448],"type":"Point"}
}