{
  "type": "Feature",
  "properties": {
    "iso:country":"US",
    "sg:address":"519 Revere Rd",
    "sg:city":"Larchmont",
    "sg:classifiers":[
        {
            "category":"Restaurant",
            "type":"Food & Drink"
        }
    ],
    "sg:phone":"+1   ",
    "sg:postcode":"10538",
    "sg:province":"NY",
    "sg:tags":[
        "concession",
        "stand",
        "operates"
    ],
    "wof:name":"Westchester Food Service Inc",
    "wof:placetype":"venue"
},
  "geometry": {"coordinates":[-73.749262,40.943981],"type":"Point"}
}