{
  "type": "Feature",
  "properties": {
    "iso:country":"US",
    "sg:address":"1428 Ridley Rd",
    "sg:city":"Phelps",
    "sg:classifiers":[
        {
            "category":"Utilities",
            "subcategory":"Mobile Phone",
            "type":"Services"
        }
    ],
    "sg:phone":"+1   ",
    "sg:postcode":"14532",
    "sg:province":"NY",
    "sg:tags":[
        "communication",
        "radiotelephone"
    ],
    "wof:name":"Paging Services of Phelps",
    "wof:placetype":"venue"
},
  "geometry": {"coordinates":[-77.025042,42.963306],"type":"Point"}
}