{
  "type": "Feature",
  "properties": {
    "addr:full":"45 Holiday Park Dr Centereach NY 11720",
    "addr:housenumber":"45",
    "addr:postcode":"11720",
    "addr:street":"Holiday Park Dr",
    "iso:country":"US",
    "sg:address":"45 Holiday Park Dr",
    "sg:city":"Centereach",
    "sg:classifiers":[
        {
            "category":"Professional",
            "subcategory":"Management & Consulting",
            "type":"Services"
        }
    ],
    "sg:phone":"+1   ",
    "sg:postcode":"11720",
    "sg:province":"NY",
    "sg:tags":[
        "retail",
        "direct",
        "sales"
    ],
    "wof:name":"Avon",
    "wof:placetype":"venue"
},
  "geometry": {"coordinates":[-73.06252600000001,40.885545],"type":"Point"}
}