{
  "type": "Feature",
  "properties": {
    "addr:full":"159 Pine Ave Palenville NY 12463",
    "addr:housenumber":"159",
    "addr:postcode":"12463",
    "addr:street":"Pine Ave",
    "iso:country":"US",
    "sg:address":"159 Pine Ave",
    "sg:city":"Palenville",
    "sg:classifiers":[
        {
            "category":"Professional",
            "subcategory":"Computer Services",
            "type":"Services"
        }
    ],
    "sg:phone":"+1   ",
    "sg:postcode":"12463",
    "sg:province":"NY",
    "sg:tags":[
        "programing",
        "custom"
    ],
    "wof:name":"VA Systems Ltd",
    "wof:placetype":"venue"
},
  "geometry": {"coordinates":[-74.015643,42.170562],"type":"Point"}
}