{
  "type": "Feature",
  "properties": {
    "iso:country":"US",
    "sg:address":"103 Avenue F",
    "sg:city":"Brooklyn",
    "sg:classifiers":[
        {
            "category":"Food & Beverages",
            "subcategory":"Groceries & Convenience Stores",
            "type":"Retail Goods"
        }
    ],
    "sg:phone":"+1 718 633 5063",
    "sg:postcode":"11218",
    "sg:province":"NY",
    "wof:name":"International Food Market Inc",
    "wof:placetype":"venue"
},
  "geometry": {"coordinates":[-73.977519,40.633297],"type":"Point"}
}