{
  "type": "Feature",
  "properties": {
    "iso:country":"US",
    "sg:address":"1110 Route 52",
    "sg:city":"Carmel",
    "sg:classifiers":[
        {
            "category":"Personal",
            "subcategory":"Nail Salon",
            "type":"Services"
        }
    ],
    "sg:phone":"+1 845 225 2559",
    "sg:postcode":"10512",
    "sg:province":"NY",
    "wof:name":"Glamour Nails And Spa",
    "wof:placetype":"venue"
},
  "geometry": {"coordinates":[-73.680134,41.492739],"type":"Point"}
}