{
  "type": "Feature",
  "properties": {
    "iso:country":"US",
    "sg:address":"100 Broadway",
    "sg:city":"Massapequa",
    "sg:classifiers":[
        {
            "category":"Home & Garden",
            "subcategory":"Building Materials",
            "type":"Retail Goods"
        },
        {
            "category":"Manufacturing",
            "subcategory":"Building Materials",
            "type":"Manufacturing & Wholesale Goods"
        }
    ],
    "sg:phone":"+1 516 541 8844",
    "sg:postcode":"11758",
    "sg:province":"NY",
    "sg:tags":[
        "installs",
        "kitchen",
        "cabinet"
    ],
    "wof:name":"Styline Designs Inc",
    "wof:placetype":"venue"
},
  "geometry": {"coordinates":[-73.473034,40.674096],"type":"Point"}
}