{
  "type": "Feature",
  "properties": {
    "iso:country":"US",
    "sg:address":"297 Broadway",
    "sg:city":"Lynbrook",
    "sg:classifiers":[
        {
            "category":"Restaurant",
            "type":"Food & Drink"
        }
    ],
    "sg:phone":"+1   ",
    "sg:postcode":"11563",
    "sg:province":"NY",
    "sg:tags":[
        "eating"
    ],
    "wof:name":"Long Hing Kitchen",
    "wof:placetype":"venue"
},
  "geometry": {"coordinates":[-73.679104,40.65273],"type":"Point"}
}