{
  "type": "Feature",
  "properties": {
    "addr:full":"73 Old Route 22 Armonk NY 10504",
    "addr:housenumber":"73",
    "addr:postcode":"10504",
    "addr:street":"Old Route 22",
    "iso:country":"US",
    "sg:address":"73 Old Route 22",
    "sg:city":"Armonk",
    "sg:classifiers":[
        {
            "category":"Social Services",
            "subcategory":"Child Care",
            "type":"Services"
        },
        {
            "category":"Education",
            "subcategory":"School",
            "type":"Public Place"
        }
    ],
    "sg:phone":"+1 914 273 3360",
    "sg:postcode":"10504",
    "sg:province":"NY",
    "sg:tags":[
        "day"
    ],
    "wof:name":"Tutor Time Child Care/Learning Centers",
    "wof:placetype":"venue"
},
  "geometry": {"coordinates":[-73.7183,41.119301],"type":"Point"}
}