{
  "type": "Feature",
  "properties": {
    "iso:country":"US",
    "sg:address":"88 Ackerman Rd",
    "sg:city":"Warwick",
    "sg:classifiers":[
        {
            "category":"Health Services",
            "subcategory":"Doctor",
            "type":"Services"
        }
    ],
    "sg:phone":"+1 845 987 9945",
    "sg:postcode":"10990",
    "sg:province":"NY",
    "sg:tags":[
        "physician",
        "surgeon"
    ],
    "wof:name":"Radiation Shielding Systems",
    "wof:placetype":"venue"
},
  "geometry": {"coordinates":[-74.347898,41.282176],"type":"Point"}
}