{
  "type": "Feature",
  "properties": {
    "addr:full":"19 Jersey Ave Suffern NY 10901",
    "addr:housenumber":"19",
    "addr:postcode":"10901",
    "addr:street":"Jersey Ave",
    "iso:country":"US",
    "sg:address":"19 Jersey Ave",
    "sg:city":"Suffern",
    "sg:classifiers":[
        {
            "category":"Retail",
            "subcategory":"Animal Services",
            "type":"Services"
        }
    ],
    "sg:phone":"+1 845 368 0868",
    "sg:postcode":"10901",
    "sg:province":"NY",
    "sg:tags":[
        "pet",
        "fence-sales",
        "contractor"
    ],
    "sg:website":"http://www.dpdogtraining.com",
    "wof:name":"D'Andrea Professional Dog Training",
    "wof:placetype":"venue"
},
  "geometry": {"coordinates":[-74.153891,41.109571],"type":"Point"}
}