{
  "type": "Feature",
  "properties": {
    "iso:country":"US",
    "sg:address":"494 8th Ave",
    "sg:city":"New York",
    "sg:classifiers":[
        {
            "category":"Professional",
            "type":"Services"
        }
    ],
    "sg:phone":"+1 212 695 7538",
    "sg:postcode":"10001",
    "sg:province":"NY",
    "sg:tags":[
        "caterer"
    ],
    "wof:name":"Premier Home Health Care Svces Inc",
    "wof:placetype":"venue"
},
  "geometry": {"coordinates":[-73.992104,40.752399],"type":"Point"}
}