{
  "type": "Feature",
  "properties": {
    "iso:country":"US",
    "sg:address":"302 Forest Ave",
    "sg:city":"Locust Valley",
    "sg:classifiers":[
        {
            "category":"Home & Garden",
            "subcategory":"Building Materials",
            "type":"Retail Goods"
        }
    ],
    "sg:phone":"+1 516 674 3400",
    "sg:postcode":"11560",
    "sg:province":"NY",
    "sg:tags":[
        "door"
    ],
    "wof:name":"ANP Garage Door Corp",
    "wof:placetype":"venue"
},
  "geometry": {"coordinates":[-73.608513,40.874745],"type":"Point"}
}