{
  "type": "Feature",
  "properties": {
    "iso:country":"US",
    "sg:address":"726 Kelly St",
    "sg:city":"Bronx",
    "sg:classifiers":[
        {
            "category":"Health Services",
            "subcategory":"Hospital",
            "type":"Services"
        }
    ],
    "sg:phone":"+1 718 893 9893",
    "sg:postcode":"10455",
    "sg:province":"NY",
    "sg:tags":[
        "mental"
    ],
    "wof:name":"Hogar Inc",
    "wof:placetype":"venue"
},
  "geometry": {"coordinates":[-73.89994799999999,40.816306],"type":"Point"}
}