{
  "type": "Feature",
  "properties": {
    "iso:country":"US",
    "sg:address":"160 Delaware Ave Ste 3",
    "sg:city":"Delmar",
    "sg:classifiers":[
        {
            "category":"Restaurant",
            "type":"Food & Drink"
        }
    ],
    "sg:phone":"+1 518 439 3230",
    "sg:postcode":"12054",
    "sg:province":"NY",
    "sg:tags":[
        "lunch",
        "brunch",
        "breakfast"
    ],
    "wof:name":"Mancusos Luncheonette",
    "wof:placetype":"venue"
},
  "geometry": {"coordinates":[-73.811768,42.628929],"type":"Point"}
}