{
  "type": "Feature",
  "properties": {
    "addr:full":"213 Cannon St Syracuse NY 13205",
    "addr:housenumber":"213",
    "addr:postcode":"13205",
    "addr:street":"Cannon St",
    "iso:country":"US",
    "sg:address":"213 Cannon St",
    "sg:city":"Syracuse",
    "sg:classifiers":[
        {
            "category":"Social Services",
            "subcategory":"Child Care",
            "type":"Services"
        }
    ],
    "sg:phone":"+1 315 471 4750",
    "sg:postcode":"13205",
    "sg:province":"NY",
    "sg:tags":[
        "day"
    ],
    "wof:name":"Lydia's Lullaby Day Care",
    "wof:placetype":"venue"
},
  "geometry": {"coordinates":[-76.146762,43.023224],"type":"Point"}
}