{
  "type": "Feature",
  "properties": {
    "iso:country":"US",
    "sg:address":"456 Nostrand Ave",
    "sg:city":"Brooklyn",
    "sg:classifiers":[
        {
            "category":"Restaurant",
            "type":"Food & Drink"
        }
    ],
    "sg:phone":"+1 718 398 1766",
    "sg:postcode":"11216",
    "sg:province":"NY",
    "sg:tags":[
        "eating"
    ],
    "wof:name":"Sister's Place",
    "wof:placetype":"venue"
},
  "geometry": {"coordinates":[-73.950203,40.6833],"type":"Point"}
}