{
  "type": "Feature",
  "properties": {
    "addr:full":"Route 110 - New York Avenue Corner of New York Ave. -Route 110 - and Broadway Huntington NY 11743",
    "addr:postcode":"11743",
    "addr:street":"Route 110 New York Avenue Corner Of New;Ave. Route 110 And Broadway",
    "iso:country":"US",
    "sg:address":"Route 110 - New York Avenue Corner of New York Ave. -Route 110 - and Broadway",
    "sg:city":"Huntington",
    "sg:classifiers":[
        {
            "category":"Local Transit",
            "type":"Transportation"
        }
    ],
    "sg:phone":"+1 631 231 5477",
    "sg:postcode":"11743",
    "sg:province":"NY",
    "sg:tags":[
        "public"
    ],
    "sg:website":"www.mta.info/index.html",
    "wof:name":"LIRR - Huntington Station",
    "wof:placetype":"venue"
},
  "geometry": {"coordinates":[-73.418165,40.859222],"type":"Point"}
}