{
  "type": "Feature",
  "properties": {
    "addr:full":"17 E 9 St New York NY 10003",
    "addr:housenumber":"17;9",
    "addr:postcode":"10003",
    "addr:street":"E",
    "iso:country":"US",
    "sg:address":"17 E 9 St",
    "sg:city":"New York",
    "sg:classifiers":[
        {
            "category":"Health Services",
            "subcategory":"Doctor",
            "type":"Services"
        }
    ],
    "sg:phone":"+1 212 473 3354",
    "sg:postcode":"10003",
    "sg:province":"NY",
    "sg:tags":[
        "dentist"
    ],
    "wof:name":"Edward Frost DDS",
    "wof:placetype":"venue"
},
  "geometry": {"coordinates":[-73.995015,40.73265],"type":"Point"}
}