{
  "type": "Feature",
  "properties": {
    "addr:full":"Knickerbocker Station 128 E Broadway Manhattan NY 10002",
    "addr:housenumber":"128",
    "addr:postcode":"10002",
    "addr:street":"E Broadway",
    "iso:country":"US",
    "sg:address":"Knickerbocker Station 128 E Broadway",
    "sg:city":"Manhattan",
    "sg:classifiers":[
        {
            "category":"Government",
            "subcategory":"Post Office",
            "type":"Public Place"
        }
    ],
    "sg:phone":"+1 212 608 3598",
    "sg:postcode":"10002",
    "sg:province":"NY",
    "sg:website":"www.usps.com",
    "wof:name":"US Post Office",
    "wof:placetype":"venue"
},
  "geometry": {"coordinates":[-73.991862,40.714196],"type":"Point"}
}