{
  "type": "Feature",
  "properties": {
    "addr:full":"782 Marconi Ave Ronkonkoma NY 11779",
    "addr:housenumber":"782",
    "addr:postcode":"11779",
    "addr:street":"Marconi Ave",
    "iso:country":"US",
    "sg:address":"782 Marconi Ave",
    "sg:city":"Ronkonkoma",
    "sg:classifiers":[
        {
            "category":"Wholesale",
            "subcategory":"Machinery & Supplies",
            "type":"Manufacturing & Wholesale Goods"
        }
    ],
    "sg:phone":"+1 631 588 8484",
    "sg:postcode":"11779",
    "sg:province":"NY",
    "sg:tags":[
        "equipment",
        "transportation",
        "motorcycle"
    ],
    "wof:name":"Velorex USA Inc",
    "wof:placetype":"venue"
},
  "geometry": {"coordinates":[-73.120283,40.7956],"type":"Point"}
}