{
  "type": "Feature",
  "properties": {
    "iso:country":"US",
    "sg:address":"2500 Saddlebrook Dr",
    "sg:city":"Vestal",
    "sg:classifiers":[
        {
            "category":"Real Estate",
            "subcategory":"Real Estate Operator",
            "type":"Services"
        }
    ],
    "sg:phone":"+1 607 729 7670",
    "sg:postcode":"13850",
    "sg:province":"NY",
    "sg:tags":[
        "building",
        "apartment"
    ],
    "wof:name":"Justin A & Sylvia J Marchuska",
    "wof:placetype":"venue"
},
  "geometry": {"coordinates":[-76.00993,42.08582],"type":"Point"}
}