{
  "type": "Feature",
  "properties": {
    "addr:full":"1 Carol Ct Endwell NY 13760",
    "addr:housenumber":"1",
    "addr:postcode":"13760",
    "addr:street":"Carol Ct",
    "iso:country":"US",
    "sg:address":"1 Carol Ct",
    "sg:city":"Endwell",
    "sg:classifiers":[
        {
            "category":"Building & Trades",
            "subcategory":"Construction",
            "type":"Services"
        }
    ],
    "sg:phone":"+1 607 427 1680",
    "sg:postcode":"13760",
    "sg:province":"NY",
    "sg:tags":[
        "front",
        "store"
    ],
    "wof:name":"Wright On Designs",
    "wof:placetype":"venue"
},
  "geometry": {"coordinates":[-76.024034,42.13142],"type":"Point"}
}