{
  "type": "Feature",
  "properties": {
    "addr:full":"561 Portage Rd Niagara Falls NY 14301",
    "addr:housenumber":"561",
    "addr:postcode":"14301",
    "addr:street":"Portage Rd",
    "iso:country":"US",
    "sg:address":"561 Portage Rd",
    "sg:city":"Niagara Falls",
    "sg:classifiers":[
        {
            "category":"Education",
            "subcategory":"Special Training",
            "type":"Public Place"
        }
    ],
    "sg:phone":"+1 716 282 3605",
    "sg:postcode":"14301",
    "sg:province":"NY",
    "wof:name":"Indian Education",
    "wof:placetype":"venue"
},
  "geometry": {"coordinates":[-79.046515,43.092027],"type":"Point"}
}