{
  "type": "Feature",
  "properties": {
    "iso:country":"US",
    "sg:address":"446 Cold Spring Rd",
    "sg:city":"Stanfordville",
    "sg:classifiers":[
        {
            "category":"Retail",
            "subcategory":"Auto Repair",
            "type":"Services"
        }
    ],
    "sg:phone":"+1   ",
    "sg:postcode":"12581",
    "sg:province":"NY",
    "sg:tags":[
        "general"
    ],
    "wof:name":"Herrmann S Automotive Clinic I",
    "wof:placetype":"venue"
},
  "geometry": {"coordinates":[-73.74570300000001,41.954599],"type":"Point"}
}