{
  "type": "Feature",
  "properties": {
    "addr:full":"210 Merritts Rd Farmingdale NY 11735",
    "addr:housenumber":"210",
    "addr:postcode":"11735",
    "addr:street":"Merritts Rd",
    "iso:country":"US",
    "sg:address":"210 Merritts Rd",
    "sg:city":"Farmingdale",
    "sg:classifiers":[
        {
            "category":"Social Services",
            "subcategory":"Child Care",
            "type":"Services"
        }
    ],
    "sg:phone":"+1 516 694 6530",
    "sg:postcode":"11735",
    "sg:province":"NY",
    "sg:tags":[
        "kindergarten",
        "academic",
        "school"
    ],
    "wof:name":"Dilly Dally Nursery School",
    "wof:placetype":"venue"
},
  "geometry": {"coordinates":[-73.458338,40.71996],"type":"Point"}
}