{
  "type": "Feature",
  "properties": {
    "addr:full":"10 W 15th Street New York NY 10011",
    "addr:housenumber":"10",
    "addr:postcode":"10011",
    "addr:street":"W 15Th Street",
    "iso:country":"US",
    "sg:address":"10 W 15th Street",
    "sg:city":"New York",
    "sg:classifiers":[
        {
            "category":"Personal",
            "type":"Services"
        }
    ],
    "sg:phone":"+1 888 438 7455",
    "sg:postcode":"10011",
    "sg:province":"NY",
    "sg:tags":[
        "party",
        "planning",
        "event"
    ],
    "sg:website":"www.sillybillymagic.com",
    "wof:name":"Silly Billy-the Funny Magical Clown",
    "wof:placetype":"venue"
},
  "geometry": {"coordinates":[-73.99327,40.73674],"type":"Point"}
}