{
  "type": "Feature",
  "properties": {
    "addr:full":"46 Main St Warwick NY 10990",
    "addr:housenumber":"46",
    "addr:postcode":"10990",
    "addr:street":"Main St",
    "iso:country":"US",
    "sg:address":"46 Main St",
    "sg:city":"Warwick",
    "sg:classifiers":[
        {
            "category":"Shopping",
            "subcategory":"Gifts & Souvenirs",
            "type":"Retail Goods"
        }
    ],
    "sg:phone":"+1 845 988 1865",
    "sg:postcode":"10990",
    "sg:province":"NY",
    "sg:tags":[
        "shop"
    ],
    "wof:name":"Flowers At Home By Woodland",
    "wof:placetype":"venue"
},
  "geometry": {"coordinates":[-74.35945100000001,41.256992],"type":"Point"}
}