{
  "type": "Feature",
  "properties": {
    "addr:full":"3962 US Hwy 11 Cortland NY 13045",
    "addr:housenumber":"3962",
    "addr:postcode":"13045",
    "addr:street":"Us Hwy 11",
    "iso:country":"US",
    "sg:address":"3962 US Hwy 11",
    "sg:city":"Cortland",
    "sg:classifiers":[
        {
            "category":"Taxi",
            "type":"Transportation"
        }
    ],
    "sg:phone":"+1 607 756 9122",
    "sg:postcode":"13045",
    "sg:province":"NY",
    "sg:tags":[
        "taxicab"
    ],
    "wof:name":"Express Taxi",
    "wof:placetype":"venue"
},
  "geometry": {"coordinates":[-76.156988,42.59822],"type":"Point"}
}