{
  "type": "Feature",
  "properties": {
    "iso:country":"US",
    "sg:address":"249 E 54th St",
    "sg:city":"Brooklyn",
    "sg:classifiers":[
        {
            "category":"Food & Beverages",
            "subcategory":"Candy",
            "type":"Retail Goods"
        }
    ],
    "sg:phone":"+1 718 498 0144",
    "sg:postcode":"11203",
    "sg:province":"NY",
    "sg:tags":[
        "confectionery"
    ],
    "wof:name":"Tony's Candy Store",
    "wof:placetype":"venue"
},
  "geometry": {"coordinates":[-73.926721,40.654044],"type":"Point"}
}