{
  "type": "Feature",
  "properties": {
    "addr:full":"45 Market St Cold Spring NY 10516",
    "addr:housenumber":"45",
    "addr:postcode":"10516",
    "addr:street":"Market St",
    "iso:country":"US",
    "sg:address":"45 Market St",
    "sg:city":"Cold Spring",
    "sg:classifiers":[
        {
            "category":"Organizations",
            "subcategory":"Religious Organization",
            "type":"Services"
        }
    ],
    "sg:phone":"+1 845 265 5537",
    "sg:postcode":"10516",
    "sg:province":"NY",
    "wof:name":"Chapel Of Our Lady Restoration",
    "wof:placetype":"venue"
},
  "geometry": {"coordinates":[-73.9563,41.413419],"type":"Point"}
}