{
  "type": "Feature",
  "properties": {
    "iso:country":"US",
    "sg:address":"60 Red Jacket Pkwy",
    "sg:city":"Buffalo",
    "sg:classifiers":[
        {
            "category":"Social Services",
            "subcategory":"Child Care",
            "type":"Services"
        }
    ],
    "sg:phone":"+1 716 822 6339",
    "sg:postcode":"14220",
    "sg:province":"NY",
    "sg:tags":[
        "day"
    ],
    "wof:name":"Mini Meez Daycare",
    "wof:placetype":"venue"
},
  "geometry": {"coordinates":[-78.812532,42.845098],"type":"Point"}
}