{
  "type": "Feature",
  "properties": {
    "addr:full":"3822 Quentin Rd Brooklyn NY 11234",
    "addr:housenumber":"3822",
    "addr:postcode":"11234",
    "addr:street":"Quentin Rd",
    "iso:country":"US",
    "sg:address":"3822 Quentin Rd",
    "sg:city":"Brooklyn",
    "sg:classifiers":[
        {
            "category":"Building & Trades",
            "subcategory":"Equipment Rental",
            "type":"Services"
        }
    ],
    "sg:phone":"+1   ",
    "sg:postcode":"11234",
    "sg:province":"NY",
    "wof:name":"Alpine Vending Inc",
    "wof:placetype":"venue"
},
  "geometry": {"coordinates":[-73.93470499999999,40.615887],"type":"Point"}
}