{
  "type": "Feature",
  "properties": {
    "addr:full":"6603 Bay Pkwy Brooklyn NY 11204",
    "addr:housenumber":"6603",
    "addr:postcode":"11204",
    "addr:street":"Bay Pkwy",
    "iso:country":"US",
    "sg:address":"6603 Bay Pkwy",
    "sg:city":"Brooklyn",
    "sg:classifiers":[
        {
            "category":"Shopping",
            "subcategory":"Optical Goods",
            "type":"Retail Goods"
        }
    ],
    "sg:phone":"+1   ",
    "sg:postcode":"11204",
    "sg:province":"NY",
    "wof:name":"Kings Eyewear Inc",
    "wof:placetype":"venue"
},
  "geometry": {"coordinates":[-73.981917,40.613361],"type":"Point"}
}