{
  "type": "Feature",
  "properties": {
    "iso:country":"US",
    "sg:address":"120 Ellsworth Ave",
    "sg:city":"Mineola",
    "sg:classifiers":[
        {
            "category":"Wholesale",
            "subcategory":"Meat",
            "type":"Manufacturing & Wholesale Goods"
        }
    ],
    "sg:phone":"+1 516 294 3318",
    "sg:postcode":"11501",
    "sg:province":"NY",
    "wof:name":"Gilor Provisions",
    "wof:placetype":"venue"
},
  "geometry": {"coordinates":[-73.64138,40.751773],"type":"Point"}
}