{
  "type": "Feature",
  "properties": {
    "addr:full":"331 Chestnut St Oneonta NY 13820",
    "addr:housenumber":"331",
    "addr:postcode":"13820",
    "addr:street":"Chestnut St",
    "iso:country":"US",
    "sg:address":"331 Chestnut St",
    "sg:city":"Oneonta",
    "sg:classifiers":[
        {
            "category":"Autos & Motor Vehicles",
            "subcategory":"Automobile Sales",
            "type":"Retail Goods"
        }
    ],
    "sg:phone":"+1   ",
    "sg:postcode":"13820",
    "sg:province":"NY",
    "sg:tags":[
        "new",
        "used"
    ],
    "wof:name":"Five Star Subaru",
    "wof:placetype":"venue"
},
  "geometry": {"coordinates":[-75.086949,42.453097],"type":"Point"}
}