{
  "type": "Feature",
  "properties": {
    "iso:country":"US",
    "sg:address":"53 Bishop St",
    "sg:city":"Staten Island",
    "sg:classifiers":[
        {
            "category":"Building & Trades",
            "subcategory":"Construction",
            "type":"Services"
        }
    ],
    "sg:phone":"+1 718 979 0330",
    "sg:postcode":"10306",
    "sg:province":"NY",
    "sg:tags":[
        "concrete",
        "contractor"
    ],
    "wof:name":"Masseria Concrete & Brick Work",
    "wof:placetype":"venue"
},
  "geometry": {"coordinates":[-74.12427599999999,40.57204],"type":"Point"}
}