{
  "type": "Feature",
  "properties": {
    "iso:country":"US",
    "sg:address":"60 Maple Ave",
    "sg:city":"Victor",
    "sg:classifiers":[
        {
            "category":"Cinema",
            "subcategory":"Movie Rental",
            "type":"Entertainment"
        }
    ],
    "sg:phone":"+1 585 924 3990",
    "sg:postcode":"14564",
    "sg:province":"NY",
    "sg:tags":[
        "leasing",
        "video",
        "disc",
        "tape"
    ],
    "wof:name":"Maple Avenue Video Inc",
    "wof:placetype":"venue"
},
  "geometry": {"coordinates":[-77.409599,42.982304],"type":"Point"}
}