{
  "type": "Feature",
  "properties": {
    "addr:full":"80 Maiden Ln New York NY 10038",
    "addr:housenumber":"80",
    "addr:postcode":"10038",
    "addr:street":"Maiden Ln",
    "iso:country":"US",
    "sg:address":"80 Maiden Ln",
    "sg:city":"New York",
    "sg:classifiers":[
        {
            "category":"Organizations",
            "subcategory":"Non-profit Organization",
            "type":"Services"
        },
        {
            "category":"Retail",
            "subcategory":"Auto Repair",
            "type":"Services"
        }
    ],
    "sg:phone":"+1 212 742 2843",
    "sg:postcode":"10038",
    "sg:province":"NY",
    "sg:tags":[
        "info",
        "repairing",
        "automobile",
        "drug",
        "abuse",
        "treatment",
        "addiction"
    ],
    "sg:website":"www.lesc.org",
    "wof:name":"Lower East Side Svc Ctr",
    "wof:placetype":"venue"
},
  "geometry": {"coordinates":[-74.00687000000001,40.706705],"type":"Point"}
}