{
  "type": "Feature",
  "properties": {
    "iso:country":"US",
    "sg:address":"4423 Pompey Center Rd",
    "sg:city":"Manlius",
    "sg:classifiers":[
        {
            "category":"Building & Trades",
            "subcategory":"Construction",
            "type":"Services"
        }
    ],
    "sg:phone":"+1 315 682 9221",
    "sg:postcode":"13104",
    "sg:province":"NY",
    "sg:tags":[
        "house"
    ],
    "wof:name":"Debottis Construction",
    "wof:placetype":"venue"
},
  "geometry": {"coordinates":[-75.959861,42.984141],"type":"Point"}
}