{
  "type": "Feature",
  "properties": {
    "iso:country":"US",
    "sg:address":"4239 White Plains Rd",
    "sg:city":"Bronx",
    "sg:classifiers":[
        {
            "category":"Personal",
            "subcategory":"Beauty Salon",
            "type":"Services"
        }
    ],
    "sg:phone":"+1 718 798 7271",
    "sg:postcode":"10466",
    "sg:province":"NY",
    "wof:name":"Uptown Best Braids",
    "wof:placetype":"venue"
},
  "geometry": {"coordinates":[-73.856832,40.894518],"type":"Point"}
}