{
  "type": "Feature",
  "properties": {
    "addr:full":"122 Commack Rd Commack NY 11725",
    "addr:housenumber":"122",
    "addr:postcode":"11725",
    "addr:street":"Commack Rd",
    "iso:country":"US",
    "sg:address":"122 Commack Rd",
    "sg:city":"Commack",
    "sg:classifiers":[
        {
            "category":"Restaurant",
            "type":"Food & Drink"
        }
    ],
    "sg:menulink":"http://www.allmenus.com/ny/huntington/54068-foo-luck/menu/",
    "sg:phone":"+1 631 499 1512",
    "sg:postcode":"11725",
    "sg:province":"NY",
    "sg:tags":[
        "asian",
        "chinese"
    ],
    "wof:name":"Foo Luck",
    "wof:placetype":"venue"
},
  "geometry": {"coordinates":[-73.293648,40.839781],"type":"Point"}
}