{
  "type": "Feature",
  "properties": {
    "addr:full":"10 Peck Slip New York NY 10038",
    "addr:housenumber":"10",
    "addr:postcode":"10038",
    "addr:street":"Peck Slip",
    "iso:country":"US",
    "sg:address":"10 Peck Slip",
    "sg:city":"New York",
    "sg:classifiers":[
        {
            "category":"Parking",
            "type":"Transportation"
        }
    ],
    "sg:phone":"+1 212 385 9746",
    "sg:postcode":"10038",
    "sg:province":"NY",
    "sg:tags":[
        "garage"
    ],
    "wof:name":"Edison Park Fast",
    "wof:placetype":"venue"
},
  "geometry": {"coordinates":[-74.00210800000001,40.708358],"type":"Point"}
}