{
  "type": "Feature",
  "properties": {
    "iso:country":"US",
    "sg:address":"190 Vernon Ave",
    "sg:city":"Brooklyn",
    "sg:classifiers":[
        {
            "category":"Park",
            "type":"Public Place"
        }
    ],
    "sg:postcode":"11206",
    "sg:province":"NY",
    "wof:name":"T & T Vernon Block Association Community Garden",
    "wof:placetype":"venue"
},
  "geometry": {"coordinates":[-73.94429,40.695185],"type":"Point"}
}