{
  "type": "Feature",
  "properties": {
    "iso:country":"US",
    "sg:address":"763 E New York Ave",
    "sg:city":"Brooklyn",
    "sg:classifiers":[
        {
            "category":"Retail",
            "subcategory":"Auto Repair",
            "type":"Services"
        }
    ],
    "sg:phone":"+1 347 756 3838",
    "sg:postcode":"11203",
    "sg:province":"NY",
    "wof:name":"Mount Garizim Auto Collision",
    "wof:placetype":"venue"
},
  "geometry": {"coordinates":[-73.937421,40.662521],"type":"Point"}
}