{
  "type": "Feature",
  "properties": {
    "addr:full":"155 E Main St Smithtown NY 11787",
    "addr:housenumber":"155",
    "addr:postcode":"11787",
    "addr:street":"E Main St",
    "iso:country":"US",
    "sg:address":"155 E Main St",
    "sg:city":"Smithtown",
    "sg:classifiers":[
        {
            "category":"Travel",
            "subcategory":"Hotels & Motels",
            "type":"Entertainment"
        }
    ],
    "sg:phone":"+1 631 424 7755",
    "sg:postcode":"11787",
    "sg:province":"NY",
    "sg:website":"www.hotelinteractive.com",
    "wof:name":"Hotel Interactive",
    "wof:placetype":"venue"
},
  "geometry": {"coordinates":[-73.189697,40.856098],"type":"Point"}
}