{
  "type": "Feature",
  "properties": {
    "addr:full":"2318 31st St Ste 320 Long Island City NY 11105",
    "addr:housenumber":"2318",
    "addr:postcode":"11105",
    "addr:street":"31St St Ste 320",
    "iso:country":"US",
    "sg:address":"2318 31st St Ste 320",
    "sg:city":"Long Island City",
    "sg:classifiers":[
        {
            "category":"Health Services",
            "subcategory":"Doctor",
            "type":"Services"
        }
    ],
    "sg:phone":"+1 718 728 9822",
    "sg:postcode":"11105",
    "sg:province":"NY",
    "sg:tags":[
        "dermatologist"
    ],
    "wof:name":"Alexander Nicolaides, MD",
    "wof:placetype":"venue"
},
  "geometry": {"coordinates":[-73.913408,40.773932],"type":"Point"}
}