{
  "type": "Feature",
  "properties": {
    "addr:full":"2489 Route 32 Highland Mills NY 10930",
    "addr:housenumber":"2489",
    "addr:postcode":"10930",
    "addr:street":"Route 32;Mills",
    "iso:country":"US",
    "sg:address":"2489 Route 32",
    "sg:city":"Highland Mills",
    "sg:classifiers":[
        {
            "category":"Health Services",
            "subcategory":"Clinic",
            "type":"Services"
        }
    ],
    "sg:phone":"+1 845 928 7979",
    "sg:postcode":"10930",
    "sg:province":"NY",
    "sg:tags":[
        "counseling",
        "mental"
    ],
    "wof:name":"Adolescent & Family Counseling Center",
    "wof:placetype":"venue"
},
  "geometry": {"coordinates":[-74.120903,41.3503],"type":"Point"}
}