{
  "type": "Feature",
  "properties": {
    "addr:full":"191 Douglass Street Brooklyn NY 11217",
    "addr:housenumber":"191",
    "addr:postcode":"11217",
    "addr:street":"Douglass Street",
    "iso:country":"US",
    "sg:address":"191 Douglass Street",
    "sg:city":"Brooklyn",
    "sg:classifiers":[
        {
            "category":"Building & Trades",
            "subcategory":"Construction",
            "type":"Services"
        }
    ],
    "sg:phone":"+1 718 222 3220",
    "sg:postcode":"11217",
    "sg:province":"NY",
    "sg:tags":[
        "contractor"
    ],
    "wof:name":"Burda Construction Corporation",
    "wof:placetype":"venue"
},
  "geometry": {"coordinates":[-73.98732800000001,40.681502],"type":"Point"}
}