{
  "type": "Feature",
  "properties": {
    "iso:country":"US",
    "sg:address":"521 Co Rte 17A",
    "sg:city":"Williamstown",
    "sg:classifiers":[
        {
            "category":"Farming",
            "subcategory":"Livestock Farm",
            "type":"Manufacturing & Wholesale Goods"
        }
    ],
    "sg:phone":"+1 315 964 0069",
    "sg:postcode":"13493",
    "sg:province":"NY",
    "sg:tags":[
        "beef",
        "feedlot",
        "cattle"
    ],
    "wof:name":"Barry Leemann",
    "wof:placetype":"venue"
},
  "geometry": {"coordinates":[-75.91515,43.361768],"type":"Point"}
}