{
  "type": "Feature",
  "properties": {
    "addr:full":"43 Bismark Ave Valley Stream NY 11581",
    "addr:housenumber":"43",
    "addr:postcode":"11581",
    "addr:street":"Bismark Ave",
    "iso:country":"US",
    "sg:address":"43 Bismark Ave",
    "sg:city":"Valley Stream",
    "sg:classifiers":[
        {
            "category":"Wholesale",
            "subcategory":"Non-durable Goods",
            "type":"Manufacturing & Wholesale Goods"
        }
    ],
    "sg:phone":"+1 516 825 5738",
    "sg:postcode":"11581",
    "sg:province":"NY",
    "wof:name":"Eksioglu Distributor",
    "wof:placetype":"venue"
},
  "geometry": {"coordinates":[-73.6931,40.652652],"type":"Point"}
}