{
  "type": "Feature",
  "properties": {
    "iso:country":"US",
    "sg:address":"1801 Ford St",
    "sg:city":"Ogdensburg",
    "sg:classifiers":[
        {
            "category":"Bus Charters",
            "type":"Transportation"
        }
    ],
    "sg:phone":"+1   ",
    "sg:postcode":"13669",
    "sg:province":"NY",
    "wof:name":"Roethels Coach Lines Inc",
    "wof:placetype":"venue"
},
  "geometry": {"coordinates":[-75.472921,44.70624],"type":"Point"}
}