{
  "type": "Feature",
  "properties": {
    "addr:full":"309 State St Watertown NY 13601",
    "addr:housenumber":"309",
    "addr:postcode":"13601",
    "addr:street":"State St",
    "iso:country":"US",
    "sg:address":"309 State St",
    "sg:city":"Watertown",
    "sg:classifiers":[
        {
            "category":"Building & Trades",
            "subcategory":"Construction",
            "type":"Services"
        }
    ],
    "sg:phone":"+1 315 782 8888",
    "sg:postcode":"13601",
    "sg:province":"NY",
    "sg:tags":[
        "insulation",
        "heat",
        "contractor"
    ],
    "wof:name":"Havens Group",
    "wof:placetype":"venue"
},
  "geometry": {"coordinates":[-75.90496,43.973549],"type":"Point"}
}