{
  "type": "Feature",
  "properties": {
    "iso:country":"US",
    "sg:address":"5 Golf Ln",
    "sg:city":"Huntington",
    "sg:classifiers":[
        {
            "category":"Professional",
            "subcategory":"Advertising",
            "type":"Services"
        }
    ],
    "sg:phone":"+1 631 271 3005",
    "sg:postcode":"11743",
    "sg:province":"NY",
    "sg:tags":[
        "counselor"
    ],
    "wof:name":"Creative Media Graphics Inc",
    "wof:placetype":"venue"
},
  "geometry": {"coordinates":[-73.40073700000001,40.890103],"type":"Point"}
}