{
  "type": "Feature",
  "properties": {
    "addr:full":"98 N Chestnut St New Paltz NY 12561",
    "addr:housenumber":"98",
    "addr:postcode":"12561",
    "addr:street":"N Chestnut St",
    "iso:country":"US",
    "sg:address":"98 N Chestnut St",
    "sg:city":"New Paltz",
    "sg:classifiers":[
        {
            "category":"Food & Beverages",
            "subcategory":"Groceries & Convenience Stores",
            "type":"Retail Goods"
        }
    ],
    "sg:phone":"+1 845 255 4382",
    "sg:postcode":"12561",
    "sg:province":"NY",
    "sg:website":"www.stewartsicecream.com",
    "wof:name":"Stewart's Shop",
    "wof:placetype":"venue"
},
  "geometry": {"coordinates":[-74.083906,41.754342],"type":"Point"}
}