{
  "type": "Feature",
  "properties": {
    "addr:full":"19 S Franklin St Cortland NY 13045",
    "addr:housenumber":"19",
    "addr:postcode":"13045",
    "addr:street":"S Franklin St",
    "iso:country":"US",
    "sg:address":"19 S Franklin St",
    "sg:city":"Cortland",
    "sg:classifiers":[
        {
            "category":"Government",
            "subcategory":"Office",
            "type":"Public Place"
        }
    ],
    "sg:phone":"+1 607 753 1957",
    "sg:postcode":"13045",
    "sg:province":"NY",
    "sg:tags":[
        "civil",
        "defense",
        "agency"
    ],
    "wof:name":"Cortland City Pub Safety Comm",
    "wof:placetype":"venue"
},
  "geometry": {"coordinates":[-76.16454299999999,42.596953],"type":"Point"}
}