{
  "type": "Feature",
  "properties": {
    "addr:full":"200 Park Ave S Ste 1611 New York NY 10003",
    "addr:housenumber":"200",
    "addr:postcode":"1611;10003",
    "addr:street":"Park Ave S Ste",
    "iso:country":"US",
    "sg:address":"200 Park Ave S Ste 1611",
    "sg:city":"New York",
    "sg:classifiers":[
        {
            "category":"Professional",
            "subcategory":"Lawyer & Legal Services",
            "type":"Services"
        }
    ],
    "sg:phone":"+1 212 661 3131",
    "sg:postcode":"10003",
    "sg:province":"NY",
    "wof:name":"Grayson Grayson",
    "wof:placetype":"venue"
},
  "geometry": {"coordinates":[-73.98919600000001,40.73665],"type":"Point"}
}