{
  "type": "Feature",
  "properties": {
    "iso:country":"US",
    "sg:address":"50 Ferris St",
    "sg:city":"Corning",
    "sg:classifiers":[
        {
            "category":"Utilities",
            "subcategory":"Cable",
            "type":"Services"
        }
    ],
    "sg:phone":"+1   ",
    "sg:postcode":"14830",
    "sg:province":"NY",
    "sg:tags":[
        "television"
    ],
    "wof:name":"Time Warner",
    "wof:placetype":"venue"
},
  "geometry": {"coordinates":[-77.05984100000001,42.150825],"type":"Point"}
}