{
  "type": "Feature",
  "properties": {
    "iso:country":"US",
    "sg:address":"717 Waterloo Geneva Rd",
    "sg:city":"Waterloo",
    "sg:classifiers":[
        {
            "category":"Professional",
            "subcategory":"Art Services",
            "type":"Services"
        }
    ],
    "sg:phone":"+1 315 539 9004",
    "sg:postcode":"13165",
    "sg:province":"NY",
    "sg:tags":[
        "graphic",
        "designer"
    ],
    "wof:name":"In House Graphic Design",
    "wof:placetype":"venue"
},
  "geometry": {"coordinates":[-76.909217,42.895649],"type":"Point"}
}