{
  "type": "Feature",
  "properties": {
    "addr:full":"1566 1st Ave New York NY 10028",
    "addr:housenumber":"1566",
    "addr:postcode":"10028",
    "addr:street":"1St Ave",
    "iso:country":"US",
    "sg:address":"1566 1st Ave",
    "sg:city":"New York",
    "sg:classifiers":[
        {
            "category":"Retail",
            "subcategory":"Laundry & Dry Cleaning",
            "type":"Services"
        }
    ],
    "sg:phone":"+1 212 535 3461",
    "sg:postcode":"10028",
    "sg:province":"NY",
    "wof:name":"Fantastic Cleaners",
    "wof:placetype":"venue"
},
  "geometry": {"coordinates":[-73.95120199999999,40.774101],"type":"Point"}
}