{
  "type": "Feature",
  "properties": {
    "addr:full":"47 Wallkill Ave Wallkill NY 12589",
    "addr:housenumber":"47",
    "addr:postcode":"12589",
    "addr:street":"Wallkill Ave",
    "iso:country":"US",
    "sg:address":"47 Wallkill Ave",
    "sg:city":"Wallkill",
    "sg:classifiers":[
        {
            "category":"Building & Trades",
            "subcategory":"Construction",
            "type":"Services"
        },
        {
            "category":"Home & Garden",
            "subcategory":"Carpets & Floor Coverings",
            "type":"Retail Goods"
        }
    ],
    "sg:phone":"+1 845 895 4641",
    "sg:postcode":"12589",
    "sg:province":"NY",
    "sg:tags":[
        "material",
        "tile-contractors",
        "rug",
        "flooring",
        "contractor"
    ],
    "sg:website":"http://www.cmsfloors.com",
    "wof:name":"CMS Floors",
    "wof:placetype":"venue"
},
  "geometry": {"coordinates":[-74.184605,41.606161],"type":"Point"}
}