{
  "type": "Feature",
  "properties": {
    "addr:full":"5602 New Utrecht Ave Brooklyn NY 11219",
    "addr:housenumber":"5602",
    "addr:postcode":"11219",
    "addr:street":"New Utrecht Ave",
    "iso:country":"US",
    "sg:address":"5602 New Utrecht Ave",
    "sg:city":"Brooklyn",
    "sg:classifiers":[
        {
            "category":"Restaurant",
            "type":"Food & Drink"
        }
    ],
    "sg:phone":"+1 718 435 6200",
    "sg:postcode":"11219",
    "sg:province":"NY",
    "sg:tags":[
        "diner"
    ],
    "sg:website":"www.glattdiner.com",
    "wof:name":"Glatt Diner",
    "wof:placetype":"venue"
},
  "geometry": {"coordinates":[-73.995817,40.630814],"type":"Point"}
}