{
  "type": "Feature",
  "properties": {
    "addr:full":"74 Pine Rd Elizaville NY 12523",
    "addr:housenumber":"74",
    "addr:postcode":"12523",
    "addr:street":"Pine Rd",
    "iso:country":"US",
    "sg:address":"74 Pine Rd",
    "sg:city":"Elizaville",
    "sg:classifiers":[
        {
            "category":"Building & Trades",
            "subcategory":"Cleaning & Sanitation",
            "type":"Services"
        }
    ],
    "sg:phone":"+1   ",
    "sg:postcode":"12523",
    "sg:province":"NY",
    "sg:tags":[
        "maintenance"
    ],
    "wof:name":"Bee Ezz",
    "wof:placetype":"venue"
},
  "geometry": {"coordinates":[-73.801124,42.061891],"type":"Point"}
}