{
  "type": "Feature",
  "properties": {
    "iso:country":"US",
    "sg:address":"331 Main St",
    "sg:city":"Lake Placid",
    "sg:classifiers":[
        {
            "category":"Shopping",
            "subcategory":"Bicycles & Sporting Goods",
            "type":"Retail Goods"
        }
    ],
    "sg:phone":"+1 518 523 3764",
    "sg:postcode":"12946",
    "sg:province":"NY",
    "sg:website":"www.highpeakscyclery.com",
    "wof:name":"High Peaks Cyclery",
    "wof:placetype":"venue"
},
  "geometry": {"coordinates":[-73.981584,44.280927],"type":"Point"}
}