{
  "type": "Feature",
  "properties": {
    "iso:country":"US",
    "sg:address":"11 Adair Dr",
    "sg:city":"Rochester",
    "sg:classifiers":[
        {
            "category":"Building & Trades",
            "subcategory":"Construction",
            "type":"Services"
        }
    ],
    "sg:phone":"+1 585 247 3906",
    "sg:postcode":"14606",
    "sg:province":"NY",
    "sg:tags":[
        "residential",
        "nonresidential"
    ],
    "wof:name":"Eckles Enterprise Ltd",
    "wof:placetype":"venue"
},
  "geometry": {"coordinates":[-77.712891,43.175024],"type":"Point"}
}