{
  "type": "Feature",
  "properties": {
    "addr:full":"922 Canandaigua Rd Macedon NY 14502",
    "addr:housenumber":"922",
    "addr:postcode":"14502",
    "addr:street":"Canandaigua Rd",
    "iso:country":"US",
    "sg:address":"922 Canandaigua Rd",
    "sg:city":"Macedon",
    "sg:classifiers":[
        {
            "category":"Insurance",
            "subcategory":"Insurance Agent",
            "type":"Services"
        }
    ],
    "sg:phone":"+1 315 986 1376",
    "sg:postcode":"14502",
    "sg:province":"NY",
    "wof:name":"Safeco Insurance",
    "wof:placetype":"venue"
},
  "geometry": {"coordinates":[-77.31081,43.044109],"type":"Point"}
}