{
  "type": "Feature",
  "properties": {
    "addr:full":"9 Oak Hill Dr Schenectady NY 12302",
    "addr:housenumber":"9",
    "addr:postcode":"12302",
    "addr:street":"Oak Hill Dr",
    "iso:country":"US",
    "sg:address":"9 Oak Hill Dr",
    "sg:city":"Schenectady",
    "sg:classifiers":[
        {
            "category":"Building & Trades",
            "subcategory":"Construction",
            "type":"Services"
        }
    ],
    "sg:phone":"+1 518 399 4032",
    "sg:postcode":"12302",
    "sg:province":"NY",
    "sg:tags":[
        "house"
    ],
    "wof:name":"Ronald M Siefert",
    "wof:placetype":"venue"
},
  "geometry": {"coordinates":[-73.9375,42.864387],"type":"Point"}
}