{
  "type": "Feature",
  "properties": {
    "addr:full":"430 W 14th Street New York NY 10014",
    "addr:housenumber":"430",
    "addr:postcode":"10014",
    "addr:street":"W 14Th Street",
    "iso:country":"US",
    "sg:address":"430 W 14th Street",
    "sg:city":"New York",
    "sg:classifiers":[
        {
            "category":"Building & Trades",
            "subcategory":"Construction",
            "type":"Services"
        }
    ],
    "sg:phone":"+1 212 485 5400",
    "sg:postcode":"10014",
    "sg:province":"NY",
    "sg:tags":[
        "contractor"
    ],
    "wof:name":"Crm Management",
    "wof:placetype":"venue"
},
  "geometry": {"coordinates":[-74.00666,40.741469],"type":"Point"}
}