{
  "type": "Feature",
  "properties": {
    "addr:full":"650 Hylan Dr Rochester NY 14623",
    "addr:housenumber":"650",
    "addr:postcode":"14623",
    "addr:street":"Hylan Dr",
    "iso:country":"US",
    "sg:address":"650 Hylan Dr",
    "sg:city":"Rochester",
    "sg:classifiers":[
        {
            "category":"Food & Beverages",
            "subcategory":"Groceries & Convenience Stores",
            "type":"Retail Goods"
        }
    ],
    "sg:phone":"+1 585 424 7255",
    "sg:postcode":"14623",
    "sg:province":"NY",
    "sg:tags":[
        "grocer"
    ],
    "sg:website":"www.wegmans.com",
    "wof:name":"Wegmans Food Markets",
    "wof:placetype":"venue"
},
  "geometry": {"coordinates":[-77.629561,43.082129],"type":"Point"}
}