{
  "type": "Feature",
  "properties": {
    "iso:country":"US",
    "sg:address":"505 Northern Blvd",
    "sg:city":"Great Neck",
    "sg:classifiers":[
        {
            "category":"Wholesale",
            "subcategory":"Sporting Goods",
            "type":"Manufacturing & Wholesale Goods"
        },
        {
            "category":"Building & Trades",
            "subcategory":"Construction",
            "type":"Services"
        }
    ],
    "sg:phone":"+1 516 482 3671",
    "sg:postcode":"11021",
    "sg:province":"NY",
    "sg:tags":[
        "trad",
        "designer",
        "business",
        "dealer",
        "pool",
        "swimming"
    ],
    "wof:name":"A Aqua Pro Pool & Spa Co LTD",
    "wof:placetype":"venue"
},
  "geometry": {"coordinates":[-73.723373,40.77889],"type":"Point"}
}