{
  "type": "Feature",
  "properties": {
    "addr:full":"48 Broadway St Haverstraw NY 10927",
    "addr:housenumber":"48",
    "addr:postcode":"10927",
    "addr:street":"Broadway St",
    "iso:country":"US",
    "sg:address":"48 Broadway St",
    "sg:city":"Haverstraw",
    "sg:classifiers":[
        {
            "category":"Wholesale",
            "subcategory":"Non-durable Goods",
            "type":"Manufacturing & Wholesale Goods"
        }
    ],
    "sg:phone":"+1 845 786 1000",
    "sg:postcode":"10927",
    "sg:province":"NY",
    "wof:name":"Rochet Travel",
    "wof:placetype":"venue"
},
  "geometry": {"coordinates":[-73.964609,41.198154],"type":"Point"}
}