{
  "type": "Feature",
  "properties": {
    "addr:full":"3007 Eastchester Rd Bronx NY 10469",
    "addr:housenumber":"3007",
    "addr:postcode":"10469",
    "addr:street":"Eastchester Rd",
    "iso:country":"US",
    "sg:address":"3007 Eastchester Rd",
    "sg:city":"Bronx",
    "sg:classifiers":[
        {
            "category":"Professional",
            "subcategory":"Lawyer & Legal Services",
            "type":"Services"
        }
    ],
    "sg:phone":"+1 718 379 3500",
    "sg:postcode":"10469",
    "sg:province":"NY",
    "sg:tags":[
        "attorney"
    ],
    "wof:name":"Madu Edozie & Madu",
    "wof:placetype":"venue"
},
  "geometry": {"coordinates":[-73.843177,40.870127],"type":"Point"}
}