{
  "type": "Feature",
  "properties": {
    "addr:full":"153 Mohawk Ave Schenectady NY 12302",
    "addr:housenumber":"153",
    "addr:postcode":"12302",
    "addr:street":"Mohawk Ave",
    "iso:country":"US",
    "sg:address":"153 Mohawk Ave",
    "sg:city":"Schenectady",
    "sg:classifiers":[
        {
            "category":"Bars & Pubs",
            "type":"Food & Drink"
        }
    ],
    "sg:menulink":"http://www.allmenus.com/ny/glenville/31447-oleary-pub--grill/menu/",
    "sg:phone":"+1 518 382 8909",
    "sg:postcode":"12302",
    "sg:province":"NY",
    "sg:tags":[
        "american"
    ],
    "wof:name":"O'Leary' Pub & Grill",
    "wof:placetype":"venue"
},
  "geometry": {"coordinates":[-73.964361,42.826345],"type":"Point"}
}