{
  "type": "Feature",
  "properties": {
    "iso:country":"US",
    "sg:address":"70 Kisco Ave",
    "sg:city":"Mt Kisco",
    "sg:classifiers":[
        {
            "category":"Professional",
            "subcategory":"Lawyer & Legal Services",
            "type":"Services"
        }
    ],
    "sg:phone":"+1 914 666 5004",
    "sg:postcode":"10549",
    "sg:province":"NY",
    "sg:tags":[
        "attorney"
    ],
    "wof:name":"Baltay & Stone",
    "wof:placetype":"venue"
},
  "geometry": {"coordinates":[-73.725773,41.215489],"type":"Point"}
}