{
  "type": "Feature",
  "properties": {
    "addr:full":"743 Allerton Ave Bronx NY 10467",
    "addr:housenumber":"743",
    "addr:postcode":"10467",
    "addr:street":"Allerton Ave",
    "iso:country":"US",
    "sg:address":"743 Allerton Ave",
    "sg:city":"Bronx",
    "sg:classifiers":[
        {
            "category":"Food & Beverages",
            "subcategory":"Groceries & Convenience Stores",
            "type":"Retail Goods"
        }
    ],
    "sg:phone":"+1   ",
    "sg:postcode":"10467",
    "sg:province":"NY",
    "wof:name":"Ro Grocery",
    "wof:placetype":"venue"
},
  "geometry": {"coordinates":[-73.865937,40.865529],"type":"Point"}
}