{
  "type": "Feature",
  "properties": {
    "addr:full":"9900 Mallory Rd Sauquoit NY 13456",
    "addr:housenumber":"9900",
    "addr:postcode":"13456",
    "addr:street":"Mallory Rd",
    "iso:country":"US",
    "sg:address":"9900 Mallory Rd",
    "sg:city":"Sauquoit",
    "sg:classifiers":[
        {
            "category":"Shopping",
            "subcategory":"Computers & Home Electronics",
            "type":"Retail Goods"
        }
    ],
    "sg:phone":"+1   ",
    "sg:postcode":"13456",
    "sg:province":"NY",
    "wof:name":"Certified Digital Svcs",
    "wof:placetype":"venue"
},
  "geometry": {"coordinates":[-75.23578000000001,43.038818],"type":"Point"}
}