{
  "type": "Feature",
  "properties": {
    "addr:full":"30 E Main St Bay Shore NY 11706",
    "addr:housenumber":"30",
    "addr:postcode":"11706",
    "addr:street":"E Main St",
    "iso:country":"US",
    "sg:address":"30 E Main St",
    "sg:city":"Bay Shore",
    "sg:classifiers":[
        {
            "category":"Shopping",
            "subcategory":"Pharmacy",
            "type":"Retail Goods"
        }
    ],
    "sg:phone":"+1 631 665 3000",
    "sg:postcode":"11706",
    "sg:province":"NY",
    "sg:tags":[
        "drugstore"
    ],
    "wof:name":"Shore Drug",
    "wof:placetype":"venue"
},
  "geometry": {"coordinates":[-73.24720000000001,40.721901],"type":"Point"}
}