{
  "type": "Feature",
  "properties": {
    "iso:country":"US",
    "sg:address":"150 Roosevelt Rd",
    "sg:city":"Monticello",
    "sg:classifiers":[
        {
            "category":"Travel",
            "subcategory":"Campground",
            "type":"Entertainment"
        }
    ],
    "sg:phone":"+1 845 794 7400",
    "sg:postcode":"12701",
    "sg:province":"NY",
    "sg:tags":[
        "camp"
    ],
    "wof:name":"Camp Romimu",
    "wof:placetype":"venue"
},
  "geometry": {"coordinates":[-74.72619400000001,41.625064],"type":"Point"}
}