{
  "type": "Feature",
  "properties": {
    "addr:full":"162 Throop Avenue Brooklyn NY 11206",
    "addr:housenumber":"162",
    "addr:postcode":"11206",
    "addr:street":"Throop Avenue",
    "iso:country":"US",
    "sg:address":"162 Throop Avenue",
    "sg:city":"Brooklyn",
    "sg:classifiers":[
        {
            "category":"Restaurant",
            "type":"Food & Drink"
        }
    ],
    "sg:postcode":"11206",
    "sg:province":"NY",
    "sg:tags":[
        "mexican"
    ],
    "wof:name":"Juquilita's",
    "wof:placetype":"venue"
},
  "geometry": {"coordinates":[-73.944503,40.699517],"type":"Point"}
}