{
  "type": "Feature",
  "properties": {
    "iso:country":"US",
    "sg:address":"77 Eastern Blvd",
    "sg:city":"Canandaigua",
    "sg:classifiers":[
        {
            "category":"Home & Garden",
            "subcategory":"Building Materials",
            "type":"Retail Goods"
        }
    ],
    "sg:phone":"+1 585 394 4549",
    "sg:postcode":"14424",
    "sg:province":"NY",
    "sg:tags":[
        "paint"
    ],
    "wof:name":"Sherwin-Williams Paints",
    "wof:placetype":"venue"
},
  "geometry": {"coordinates":[-77.266509,42.877874],"type":"Point"}
}