{
  "type": "Feature",
  "properties": {
    "addr:full":"58 Canfield Rd Pittsford NY 14534",
    "addr:housenumber":"58",
    "addr:postcode":"14534",
    "addr:street":"Canfield Rd",
    "iso:country":"US",
    "sg:address":"58 Canfield Rd",
    "sg:city":"Pittsford",
    "sg:classifiers":[
        {
            "category":"Real Estate",
            "subcategory":"Real Estate Agent",
            "type":"Services"
        }
    ],
    "sg:phone":"+1 585 546 8180",
    "sg:postcode":"14534",
    "sg:province":"NY",
    "sg:tags":[
        "appraiser"
    ],
    "wof:name":"Morgan-Stanwix Appraisal Inc",
    "wof:placetype":"venue"
},
  "geometry": {"coordinates":[-77.538663,43.03393],"type":"Point"}
}