{
  "type": "Feature",
  "properties": {
    "addr:full":"247 Rockaway Ave Valley Stream NY 11580",
    "addr:housenumber":"247",
    "addr:postcode":"11580",
    "addr:street":"Rockaway Ave",
    "iso:country":"US",
    "sg:address":"247 Rockaway Ave",
    "sg:city":"Valley Stream",
    "sg:classifiers":[
        {
            "category":"Health Services",
            "subcategory":"Dentist",
            "type":"Services"
        }
    ],
    "sg:phone":"+1 516 825 2320",
    "sg:postcode":"11580",
    "sg:province":"NY",
    "wof:name":"Henner Richard H Dr",
    "wof:placetype":"venue"
},
  "geometry": {"coordinates":[-73.698196,40.6647],"type":"Point"}
}