{
  "type": "Feature",
  "properties": {
    "addr:full":"18 Deb Ellen Dr Rochester NY 14624",
    "addr:housenumber":"18",
    "addr:postcode":"14624",
    "addr:street":"Deb Ellen Dr",
    "iso:country":"US",
    "sg:address":"18 Deb Ellen Dr",
    "sg:city":"Rochester",
    "sg:classifiers":[
        {
            "category":"Wholesale",
            "subcategory":"Machinery & Supplies",
            "type":"Manufacturing & Wholesale Goods"
        }
    ],
    "sg:phone":"+1 585 889 2733",
    "sg:postcode":"14624",
    "sg:province":"NY",
    "sg:tags":[
        "equipment",
        "industrial"
    ],
    "wof:name":"Pressure Washers Plus",
    "wof:placetype":"venue"
},
  "geometry": {"coordinates":[-77.75874899999999,43.104042],"type":"Point"}
}