{
  "type": "Feature",
  "properties": {
    "addr:full":"48 Market St New York NY 10002",
    "addr:housenumber":"48",
    "addr:postcode":"10002",
    "addr:street":"Market St",
    "iso:country":"US",
    "sg:address":"48 Market St",
    "sg:city":"New York",
    "sg:classifiers":[
        {
            "category":"Health Services",
            "subcategory":"Doctor",
            "type":"Services"
        }
    ],
    "sg:phone":"+1 212 647 6490",
    "sg:postcode":"10002",
    "sg:province":"NY",
    "sg:tags":[
        "obstetrician",
        "gynecologist"
    ],
    "wof:name":"PO Ching Fong MD",
    "wof:placetype":"venue"
},
  "geometry": {"coordinates":[-73.99418,40.711858],"type":"Point"}
}