{
  "type": "Feature",
  "properties": {
    "iso:country":"US",
    "sg:address":"55 W Main St",
    "sg:city":"Riverhead",
    "sg:classifiers":[
        {
            "category":"Deli",
            "type":"Food & Drink"
        },
        {
            "category":"Restaurant",
            "type":"Food & Drink"
        },
        {
            "category":"Food & Beverages",
            "subcategory":"Groceries & Convenience Stores",
            "type":"Retail Goods"
        }
    ],
    "sg:phone":"+1 631 727 5482",
    "sg:postcode":"11901",
    "sg:province":"NY",
    "sg:tags":[
        "delicatessen"
    ],
    "wof:name":"Riverhead Deli Corp",
    "wof:placetype":"venue"
},
  "geometry": {"coordinates":[-72.663196,40.916772],"type":"Point"}
}