{
  "type": "Feature",
  "properties": {
    "iso:country":"US",
    "sg:address":"20 Hofstra Dr",
    "sg:city":"Farmingville",
    "sg:classifiers":[
        {
            "category":"Wholesale",
            "subcategory":"Drugs",
            "type":"Manufacturing & Wholesale Goods"
        }
    ],
    "sg:phone":"+1 631 732 8042",
    "sg:postcode":"11738",
    "sg:province":"NY",
    "sg:tags":[
        "battery",
        "aids",
        "health",
        "beauty"
    ],
    "wof:name":"Syed Distributors",
    "wof:placetype":"venue"
},
  "geometry": {"coordinates":[-73.047679,40.841232],"type":"Point"}
}