{
  "type": "Feature",
  "properties": {
    "addr:full":"4 E 77th St Fl 1 New York NY 10021",
    "addr:housenumber":"4;1",
    "addr:postcode":"10021",
    "addr:street":"E 77Th St",
    "iso:country":"US",
    "sg:address":"4 E 77th St Fl 1",
    "sg:city":"New York",
    "sg:classifiers":[
        {
            "category":"Health Services",
            "subcategory":"Doctor",
            "type":"Services"
        }
    ],
    "sg:phone":"+1 212 288 1200",
    "sg:postcode":"10021",
    "sg:province":"NY",
    "wof:name":"Sudarsky David R MD",
    "wof:placetype":"venue"
},
  "geometry": {"coordinates":[-73.9646,40.7756],"type":"Point"}
}