{
  "type": "Feature",
  "properties": {
    "iso:country":"US",
    "sg:address":"4502 8th Ave",
    "sg:city":"Brooklyn",
    "sg:classifiers":[
        {
            "category":"Personal",
            "subcategory":"Beauty Salon",
            "type":"Services"
        }
    ],
    "sg:phone":"+1   ",
    "sg:postcode":"11220",
    "sg:province":"NY",
    "sg:tags":[
        "shop"
    ],
    "wof:name":"Sunset Hairstylist",
    "wof:placetype":"venue"
},
  "geometry": {"coordinates":[-74.00143,40.643414],"type":"Point"}
}