{
  "type": "Feature",
  "properties": {
    "addr:full":"420 Gregory St Rochester NY 14620",
    "addr:housenumber":"420",
    "addr:postcode":"14620",
    "addr:street":"Gregory St",
    "iso:country":"US",
    "sg:address":"420 Gregory St",
    "sg:city":"Rochester",
    "sg:classifiers":[
        {
            "category":"Personal",
            "subcategory":"Beauty Salon",
            "type":"Services"
        }
    ],
    "sg:phone":"+1 585 473 5060",
    "sg:postcode":"14620",
    "sg:province":"NY",
    "sg:tags":[
        "shop"
    ],
    "wof:name":"H F-X Hair Studio",
    "wof:placetype":"venue"
},
  "geometry": {"coordinates":[-77.60061399999999,43.143399],"type":"Point"}
}