{
  "type": "Feature",
  "properties": {
    "iso:country":"US",
    "sg:address":"1907 State Hwy 214",
    "sg:city":"Lanesville",
    "sg:classifiers":[
        {
            "category":"Building & Trades",
            "subcategory":"Construction",
            "type":"Services"
        }
    ],
    "sg:phone":"+1 845 688 5482",
    "sg:postcode":"12450",
    "sg:province":"NY",
    "sg:tags":[
        "carpentry",
        "contractor"
    ],
    "wof:name":"Jk Building",
    "wof:placetype":"venue"
},
  "geometry": {"coordinates":[-74.25693200000001,42.131186],"type":"Point"}
}