{
  "type": "Feature",
  "properties": {
    "addr:full":"1234 State Hwy 17K Montgomery NY 12549",
    "addr:housenumber":"1234",
    "addr:postcode":"12549",
    "addr:street":"State Hwy",
    "iso:country":"US",
    "sg:address":"1234 State Hwy 17K",
    "sg:city":"Montgomery",
    "sg:classifiers":[
        {
            "category":"Retail",
            "subcategory":"Auto Repair",
            "type":"Services"
        }
    ],
    "sg:phone":"+1 845 569 9434",
    "sg:postcode":"12549",
    "sg:province":"NY",
    "sg:tags":[
        "automotive",
        "wrecker"
    ],
    "wof:name":"Classic Towing & Recovery Inc",
    "wof:placetype":"venue"
},
  "geometry": {"coordinates":[-74.223786,41.525863],"type":"Point"}
}