{
  "type": "Feature",
  "properties": {
    "iso:country":"US",
    "sg:address":"5100 Lockport Rd",
    "sg:city":"Niagara Falls",
    "sg:classifiers":[
        {
            "category":"Building & Trades",
            "subcategory":"Construction",
            "type":"Services"
        }
    ],
    "sg:phone":"+1 716 282 2664",
    "sg:postcode":"14305",
    "sg:province":"NY",
    "sg:tags":[
        "contractor"
    ],
    "wof:name":"Rainers Drywall",
    "wof:placetype":"venue"
},
  "geometry": {"coordinates":[-79.006496,43.118979],"type":"Point"}
}