{
  "type": "Feature",
  "properties": {
    "iso:country":"US",
    "sg:address":"38 Gateway",
    "sg:city":"Rockville Centre",
    "sg:classifiers":[
        {
            "category":"Real Estate",
            "subcategory":"Real Estate Agent",
            "type":"Services"
        }
    ],
    "sg:phone":"+1 516 766 1570",
    "sg:postcode":"11570",
    "sg:province":"NY",
    "wof:name":"Popko A J",
    "wof:placetype":"venue"
},
  "geometry": {"coordinates":[-73.62334,40.65911],"type":"Point"}
}