{
  "type": "Feature",
  "properties": {
    "addr:full":"1613 63rd St Brooklyn NY 11204",
    "addr:housenumber":"1613",
    "addr:postcode":"11204",
    "addr:street":"63Rd St",
    "iso:country":"US",
    "sg:address":"1613 63rd St",
    "sg:city":"Brooklyn",
    "sg:classifiers":[
        {
            "category":"Building & Trades",
            "subcategory":"Electrical",
            "type":"Services"
        }
    ],
    "sg:phone":"+1 718 236 6280",
    "sg:postcode":"11204",
    "sg:province":"NY",
    "sg:tags":[
        "electrical",
        "contractor"
    ],
    "wof:name":"Terry Reilly",
    "wof:placetype":"venue"
},
  "geometry": {"coordinates":[-73.991437,40.621912],"type":"Point"}
}