{
  "type": "Feature",
  "properties": {
    "iso:country":"US",
    "sg:address":"218 N George St",
    "sg:city":"Rome",
    "sg:classifiers":[
        {
            "category":"Personal",
            "subcategory":"Beauty Salon",
            "type":"Services"
        }
    ],
    "sg:phone":"+1 315 334 9800",
    "sg:postcode":"13440",
    "sg:province":"NY",
    "wof:name":"Hair With Flair",
    "wof:placetype":"venue"
},
  "geometry": {"coordinates":[-75.459563,43.215067],"type":"Point"}
}