{
  "type": "Feature",
  "properties": {
    "addr:full":"262 Bleecker Street New York NY 10014",
    "addr:housenumber":"262",
    "addr:postcode":"10014",
    "addr:street":"Bleecker Street",
    "iso:country":"US",
    "sg:address":"262 Bleecker Street",
    "sg:city":"New York",
    "sg:classifiers":[
        {
            "category":"Restaurant",
            "type":"Food & Drink"
        }
    ],
    "sg:phone":"+1 212 645 2993",
    "sg:postcode":"10014",
    "sg:province":"NY",
    "sg:tags":[
        "italian"
    ],
    "sg:website":"www.pesce-pasta.com",
    "wof:name":"Pesce Pasta Trattoria",
    "wof:placetype":"venue"
},
  "geometry": {"coordinates":[-74.003182,40.731152],"type":"Point"}
}