{
  "type": "Feature",
  "properties": {
    "addr:full":"1593 Hamlin Parma Tl Rd Hilton NY 14468",
    "addr:housenumber":"1593",
    "addr:postcode":"14468",
    "addr:street":"Hamlin Parma Tl Rd",
    "iso:country":"US",
    "sg:address":"1593 Hamlin Parma Tl Rd",
    "sg:city":"Hilton",
    "sg:classifiers":[
        {
            "category":"Farming",
            "subcategory":"Orchard",
            "type":"Manufacturing & Wholesale Goods"
        }
    ],
    "sg:phone":"+1 585 671 1955",
    "sg:postcode":"14468",
    "sg:province":"NY",
    "sg:tags":[
        "fruit",
        "tree"
    ],
    "wof:name":"Mayers Cider Mill",
    "wof:placetype":"venue"
},
  "geometry": {"coordinates":[-77.832611,43.287387],"type":"Point"}
}