{
  "type": "Feature",
  "properties": {
    "addr:full":"146 Chestnut Hill Ln S Buffalo NY 14221",
    "addr:housenumber":"146",
    "addr:postcode":"14221",
    "addr:street":"Chestnut Hill Ln",
    "iso:country":"US",
    "sg:address":"146 Chestnut Hill Ln S",
    "sg:city":"Buffalo",
    "sg:classifiers":[
        {
            "category":"Health Services",
            "subcategory":"Doctor",
            "type":"Services"
        }
    ],
    "sg:phone":"+1 716 688 1202",
    "sg:postcode":"14221",
    "sg:province":"NY",
    "sg:tags":[
        "medical"
    ],
    "wof:name":"David F Weppner",
    "wof:placetype":"venue"
},
  "geometry": {"coordinates":[-78.734478,42.998084],"type":"Point"}
}