{
  "type": "Feature",
  "properties": {
    "iso:country":"US",
    "sg:address":"507 W Main St",
    "sg:city":"Patchogue",
    "sg:classifiers":[
        {
            "category":"Restaurant",
            "type":"Food & Drink"
        }
    ],
    "sg:menulink":"http://www.allmenus.com/ny/brookhaven/209493-meson-ole!/menu/",
    "sg:phone":"+1 631 475 1557",
    "sg:postcode":"11772",
    "sg:province":"NY",
    "sg:tags":[
        "mexican"
    ],
    "wof:name":"Meson Ole!",
    "wof:placetype":"venue"
},
  "geometry": {"coordinates":[-73.03117399999999,40.76006],"type":"Point"}
}