{
  "type": "Feature",
  "properties": {
    "iso:country":"US",
    "sg:address":"1029 Middle Stella Ireland Rd",
    "sg:city":"Binghamton",
    "sg:classifiers":[
        {
            "category":"Shopping",
            "subcategory":"Florist",
            "type":"Retail Goods"
        }
    ],
    "sg:phone":"+1 607 729 7612",
    "sg:postcode":"13905",
    "sg:province":"NY",
    "wof:name":"Stella Ireland Gardens",
    "wof:placetype":"venue"
},
  "geometry": {"coordinates":[-75.94222499999999,42.143932],"type":"Point"}
}