{
  "type": "Feature",
  "properties": {
    "iso:country":"US",
    "sg:address":"821 Broadway",
    "sg:city":"New York",
    "sg:classifiers":[
        {
            "category":"Manufacturing",
            "subcategory":"Paper Products",
            "type":"Manufacturing & Wholesale Goods"
        }
    ],
    "sg:phone":"+1 212 477 8580",
    "sg:postcode":"10003",
    "sg:province":"NY",
    "sg:tags":[
        "wall",
        "plastic",
        "covering"
    ],
    "wof:name":"KIRK-Brummel Assoc Inc",
    "wof:placetype":"venue"
},
  "geometry": {"coordinates":[-73.990945,40.733978],"type":"Point"}
}