{
  "type": "Feature",
  "properties": {
    "addr:full":"2188 E 5th St Brooklyn NY 11223",
    "addr:housenumber":"2188",
    "addr:postcode":"11223",
    "addr:street":"E 5Th St",
    "iso:country":"US",
    "sg:address":"2188 E 5th St",
    "sg:city":"Brooklyn",
    "sg:classifiers":[
        {
            "category":"Wholesale",
            "subcategory":"Apparel",
            "type":"Manufacturing & Wholesale Goods"
        }
    ],
    "sg:phone":"+1 718 787 1397",
    "sg:postcode":"11223",
    "sg:province":"NY",
    "sg:tags":[
        "imported",
        "clothing"
    ],
    "wof:name":"Haber Intl Import Export Ltd",
    "wof:placetype":"venue"
},
  "geometry": {"coordinates":[-73.966615,40.596195],"type":"Point"}
}