{
  "type": "Feature",
  "properties": {
    "addr:full":"75 Wall St Manhattan NY 10005",
    "addr:housenumber":"75",
    "addr:postcode":"10005",
    "addr:street":"Wall St",
    "iso:country":"US",
    "sg:address":"75 Wall St",
    "sg:city":"Manhattan",
    "sg:classifiers":[
        {
            "category":"Sports & Exercise",
            "subcategory":"Playing Field",
            "type":"Entertainment"
        }
    ],
    "sg:phone":"+1 212 706 0809",
    "sg:postcode":"10005",
    "sg:province":"NY",
    "sg:tags":[
        "instruction",
        "fitness"
    ],
    "sg:website":"www.sculpt-newyork.com",
    "wof:name":"Sculpt New York",
    "wof:placetype":"venue"
},
  "geometry": {"coordinates":[-74.007767,40.705287],"type":"Point"}
}