{
  "type": "Feature",
  "properties": {
    "iso:country":"US",
    "sg:address":"5735 Sunrise Hwy",
    "sg:city":"Holbrook",
    "sg:classifiers":[
        {
            "category":"Shopping",
            "subcategory":"Optical Goods",
            "type":"Retail Goods"
        }
    ],
    "sg:phone":"+1 631 244 8844",
    "sg:postcode":"11741",
    "sg:province":"NY",
    "sg:website":"www.lenscrafters.com",
    "wof:name":"Lens Crafters",
    "wof:placetype":"venue"
},
  "geometry": {"coordinates":[-73.069008,40.768255],"type":"Point"}
}