{
  "type": "Feature",
  "properties": {
    "iso:country":"US",
    "sg:address":"2066 Batchelder St",
    "sg:city":"Brooklyn",
    "sg:classifiers":[
        {
            "category":"Building & Trades",
            "subcategory":"Pest Control",
            "type":"Services"
        }
    ],
    "sg:phone":"+1   ",
    "sg:postcode":"11229",
    "sg:province":"NY",
    "wof:name":"Shield Pest Control",
    "wof:placetype":"venue"
},
  "geometry": {"coordinates":[-73.939333,40.602249],"type":"Point"}
}