{
  "type": "Feature",
  "properties": {
    "iso:country":"US",
    "sg:address":"40 Oser Ave",
    "sg:city":"Hauppauge",
    "sg:classifiers":[
        {
            "category":"Professional",
            "subcategory":"Art Services",
            "type":"Services"
        }
    ],
    "sg:phone":"+1 631 434 1095",
    "sg:postcode":"11788",
    "sg:province":"NY",
    "sg:tags":[
        "photographer",
        "photography",
        "commercial"
    ],
    "wof:name":"David Reeves Studio Inc",
    "wof:placetype":"venue"
},
  "geometry": {"coordinates":[-73.236817,40.815793],"type":"Point"}
}