{
  "type": "Feature",
  "properties": {
    "addr:full":"Beach 155 & Boardwal Rockaway Park NY 11694",
    "addr:housenumber":"155",
    "addr:postcode":"11694",
    "iso:country":"US",
    "sg:address":"Beach 155 & Boardwal",
    "sg:city":"Rockaway Park",
    "sg:classifiers":[
        {
            "category":"Sports & Exercise",
            "subcategory":"Golf",
            "type":"Entertainment"
        }
    ],
    "sg:phone":"+1 718 474 1623",
    "sg:postcode":"11694",
    "sg:province":"NY",
    "wof:name":"Breezy Point Exec Golf Course",
    "wof:placetype":"venue"
},
  "geometry": {"coordinates":[-73.840698,40.5788],"type":"Point"}
}