{
  "type": "Feature",
  "properties": {
    "addr:full":"5 S Main St Homer NY 13077",
    "addr:housenumber":"5",
    "addr:postcode":"13077",
    "addr:street":"S Main St",
    "iso:country":"US",
    "sg:address":"5 S Main St",
    "sg:city":"Homer",
    "sg:classifiers":[
        {
            "category":"Food & Beverages",
            "subcategory":"Bakery",
            "type":"Retail Goods"
        }
    ],
    "sg:phone":"+1 607 749 9999",
    "sg:postcode":"13077",
    "sg:province":"NY",
    "sg:tags":[
        "baker"
    ],
    "sg:website":"www.linaniscookies.com",
    "wof:name":"Linani's Cookie Factory",
    "wof:placetype":"venue"
},
  "geometry": {"coordinates":[-76.17851899999999,42.636941],"type":"Point"}
}