{
  "type": "Feature",
  "properties": {
    "addr:full":"692 Hart St Brooklyn NY 11237",
    "addr:housenumber":"692",
    "addr:postcode":"11237",
    "addr:street":"Hart St",
    "iso:country":"US",
    "sg:address":"692 Hart St",
    "sg:city":"Brooklyn",
    "sg:classifiers":[
        {
            "category":"Shopping",
            "subcategory":"Pets & Pet Supplies",
            "type":"Retail Goods"
        }
    ],
    "sg:phone":"+1 718 864 5595",
    "sg:postcode":"11237",
    "sg:province":"NY",
    "sg:tags":[
        "walker",
        "dog"
    ],
    "sg:website":"www.gooddogwalking.com",
    "wof:name":"Good Dog Walking",
    "wof:placetype":"venue"
},
  "geometry": {"coordinates":[-73.925214,40.699038],"type":"Point"}
}