{
  "type": "Feature",
  "properties": {
    "addr:full":"22 E Main St Gowanda NY 14070",
    "addr:housenumber":"22",
    "addr:postcode":"14070",
    "addr:street":"E Main St",
    "iso:country":"US",
    "sg:address":"22 E Main St",
    "sg:city":"Gowanda",
    "sg:classifiers":[
        {
            "category":"Restaurant",
            "type":"Food & Drink"
        }
    ],
    "sg:phone":"+1   ",
    "sg:postcode":"14070",
    "sg:province":"NY",
    "sg:tags":[
        "eating"
    ],
    "wof:name":"Hazelnut Cafe & Bakery",
    "wof:placetype":"venue"
},
  "geometry": {"coordinates":[-78.93408599999999,42.463898],"type":"Point"}
}