{
  "type": "Feature",
  "properties": {
    "addr:full":"14 E 1 St New York NY 10003",
    "addr:housenumber":"14;1",
    "addr:postcode":"10003",
    "addr:street":"E",
    "iso:country":"US",
    "sg:address":"14 E 1 St",
    "sg:city":"New York",
    "sg:classifiers":[
        {
            "category":"Shopping",
            "subcategory":"Florist",
            "type":"Retail Goods"
        }
    ],
    "sg:phone":"+1   ",
    "sg:postcode":"10003",
    "sg:province":"NY",
    "wof:name":"Gus Flowers Horafas",
    "wof:placetype":"venue"
},
  "geometry": {"coordinates":[-73.990861,40.724383],"type":"Point"}
}