{
  "type": "Feature",
  "properties": {
    "iso:country":"US",
    "sg:address":"2 E Merrick Rd",
    "sg:city":"Valley Stream",
    "sg:classifiers":[
        {
            "category":"Professional",
            "subcategory":"Business Services",
            "type":"Services"
        }
    ],
    "sg:phone":"+1 516 256 7702",
    "sg:postcode":"11580",
    "sg:province":"NY",
    "sg:tags":[
        "interior",
        "consultant",
        "design",
        "decorator"
    ],
    "wof:name":"C & F Interiors LTD",
    "wof:placetype":"venue"
},
  "geometry": {"coordinates":[-73.696467,40.664324],"type":"Point"}
}