{
  "type": "Feature",
  "properties": {
    "addr:full":"70 Lebrun St Port Jeffrsn Sta NY 11776",
    "addr:housenumber":"70",
    "addr:postcode":"11776",
    "addr:street":"Lebrun St",
    "iso:country":"US",
    "sg:address":"70 Lebrun St",
    "sg:city":"Port Jeffrsn Sta",
    "sg:classifiers":[
        {
            "category":"Manufacturing",
            "subcategory":"Signs",
            "type":"Manufacturing & Wholesale Goods"
        }
    ],
    "sg:phone":"+1 631 928 1033",
    "sg:postcode":"11776",
    "sg:province":"NY",
    "wof:name":"Sal Signs",
    "wof:placetype":"venue"
},
  "geometry": {"coordinates":[-73.067256,40.899629],"type":"Point"}
}