{
  "type": "Feature",
  "properties": {
    "iso:country":"US",
    "sg:address":"2102 Mecklenburg Rd",
    "sg:city":"Ithaca",
    "sg:classifiers":[
        {
            "category":"Utilities",
            "subcategory":"Fuel Oil & Lpg",
            "type":"Services"
        }
    ],
    "sg:phone":"+1   ",
    "sg:postcode":"14850",
    "sg:province":"NY",
    "wof:name":"Dans Fuel Service Inc",
    "wof:placetype":"venue"
},
  "geometry": {"coordinates":[-76.631264,42.451043],"type":"Point"}
}