{
  "type": "Feature",
  "properties": {
    "iso:country":"US",
    "sg:address":"6359 Smith Rd",
    "sg:city":"Hamburg",
    "sg:classifiers":[
        {
            "category":"Building & Trades",
            "subcategory":"Landscaping Services",
            "type":"Services"
        }
    ],
    "sg:phone":"+1 716 312 0013",
    "sg:postcode":"14075",
    "sg:province":"NY",
    "wof:name":"Klb Yard Services",
    "wof:placetype":"venue"
},
  "geometry": {"coordinates":[-78.869778,42.714287],"type":"Point"}
}