{
  "type": "Feature",
  "properties": {
    "iso:country":"US",
    "sg:address":"8121 Rapallo Way",
    "sg:city":"Clay",
    "sg:classifiers":[
        {
            "category":"Home & Garden",
            "subcategory":"Household Appliances",
            "type":"Retail Goods"
        },
        {
            "category":"Building & Trades",
            "subcategory":"Construction",
            "type":"Services"
        },
        {
            "category":"Building & Trades",
            "subcategory":"Electrical",
            "type":"Services"
        }
    ],
    "sg:phone":"+1 315 699 0902",
    "sg:postcode":"13041",
    "sg:province":"NY",
    "sg:tags":[
        "industrial",
        "electrician",
        "electric",
        "pump",
        "specialty",
        "system",
        "heat",
        "heating",
        "contractors-commercial",
        "contractor",
        "air conditioning"
    ],
    "wof:name":"Syracuse Energy Systems",
    "wof:placetype":"venue"
},
  "geometry": {"coordinates":[-76.151444,43.162986],"type":"Point"}
}