{
  "type": "Feature",
  "properties": {
    "iso:country":"US",
    "sg:address":"126 Lafayette Ave",
    "sg:city":"White Plains",
    "sg:classifiers":[
        {
            "category":"Retail",
            "subcategory":"Auto Repair",
            "type":"Services"
        }
    ],
    "sg:phone":"+1 914 949 7889",
    "sg:postcode":"10603",
    "sg:province":"NY",
    "sg:tags":[
        "body",
        "towing",
        "painting"
    ],
    "wof:name":"New York Recovery",
    "wof:placetype":"venue"
},
  "geometry": {"coordinates":[-73.772485,41.062477],"type":"Point"}
}