{
  "type": "Feature",
  "properties": {
    "addr:full":"697 Snells Bush Rd Little Falls NY 13365",
    "addr:housenumber":"697",
    "addr:postcode":"13365",
    "addr:street":"Snells Bush Rd",
    "iso:country":"US",
    "sg:address":"697 Snells Bush Rd",
    "sg:city":"Little Falls",
    "sg:classifiers":[
        {
            "category":"Wholesale",
            "subcategory":"Machinery & Supplies",
            "type":"Manufacturing & Wholesale Goods"
        }
    ],
    "sg:phone":"+1 315 823 1982",
    "sg:postcode":"13365",
    "sg:province":"NY",
    "sg:tags":[
        "equipment",
        "industrial"
    ],
    "wof:name":"Charles D Stahl Logging",
    "wof:placetype":"venue"
},
  "geometry": {"coordinates":[-74.76674800000001,43.023269],"type":"Point"}
}