{
  "type": "Feature",
  "properties": {
    "addr:full":"460 W 34th St New York NY 10001",
    "addr:housenumber":"460",
    "addr:postcode":"10001",
    "addr:street":"W 34Th St",
    "iso:country":"US",
    "sg:address":"460 W 34th St",
    "sg:city":"New York",
    "sg:classifiers":[
        {
            "category":"Retail",
            "subcategory":"Repair Shop",
            "type":"Services"
        }
    ],
    "sg:phone":"+1 212 268 9988",
    "sg:postcode":"10001",
    "sg:province":"NY",
    "sg:tags":[
        "modernization",
        "elevator",
        "maintenance"
    ],
    "wof:name":"CE",
    "wof:placetype":"venue"
},
  "geometry": {"coordinates":[-73.999143,40.754585],"type":"Point"}
}