{
  "type": "Feature",
  "properties": {
    "iso:country":"US",
    "sg:address":"4131 Queens Blvd",
    "sg:city":"Sunnyside",
    "sg:classifiers":[
        {
            "category":"Restaurant",
            "type":"Food & Drink"
        }
    ],
    "sg:phone":"+1 718 729 0505",
    "sg:postcode":"11104",
    "sg:province":"NY",
    "wof:name":"Anatolian Turkish Cuisine & Pizzeria",
    "wof:placetype":"venue"
},
  "geometry": {"coordinates":[-73.923005,40.743819],"type":"Point"}
}