{
  "type": "Feature",
  "properties": {
    "iso:country":"US",
    "sg:address":"124 Degarmo Rd",
    "sg:city":"Schuylerville",
    "sg:classifiers":[
        {
            "category":"Retail",
            "subcategory":"Repair Shop",
            "type":"Services"
        }
    ],
    "sg:phone":"+1   ",
    "sg:postcode":"12871",
    "sg:province":"NY",
    "sg:tags":[
        "equipment",
        "agricultural"
    ],
    "wof:name":"Saratoga AG Sls & Svc",
    "wof:placetype":"venue"
},
  "geometry": {"coordinates":[-73.619207,43.101443],"type":"Point"}
}