{
  "type": "Feature",
  "properties": {
    "addr:full":"165 Ave C New York NY 10009",
    "addr:housenumber":"165",
    "addr:postcode":"10009",
    "addr:street":"Ave C",
    "iso:country":"US",
    "sg:address":"165 Ave C",
    "sg:city":"New York",
    "sg:classifiers":[
        {
            "category":"Personal",
            "subcategory":"Barber",
            "type":"Services"
        }
    ],
    "sg:phone":"+1   ",
    "sg:postcode":"10009",
    "sg:province":"NY",
    "sg:tags":[
        "shop"
    ],
    "wof:name":"Marcos Figueredo",
    "wof:placetype":"venue"
},
  "geometry": {"coordinates":[-73.977204,40.726418],"type":"Point"}
}