{
  "type": "Feature",
  "properties": {
    "addr:full":"344 Sharrotts Rd Staten Island NY 10309",
    "addr:housenumber":"344",
    "addr:postcode":"10309",
    "addr:street":"Sharrotts Rd",
    "iso:country":"US",
    "sg:address":"344 Sharrotts Rd",
    "sg:city":"Staten Island",
    "sg:classifiers":[
        {
            "category":"Building & Trades",
            "subcategory":"Construction",
            "type":"Services"
        }
    ],
    "sg:phone":"+1 718 987 4400",
    "sg:postcode":"10309",
    "sg:province":"NY",
    "sg:tags":[
        "paving",
        "contractor"
    ],
    "wof:name":"Constructive Concepts Inc",
    "wof:placetype":"venue"
},
  "geometry": {"coordinates":[-74.22962099999999,40.537039],"type":"Point"}
}