{
  "type": "Feature",
  "properties": {
    "addr:full":"25-17 36th St Queens NY 11103",
    "addr:housenumber":"25-17",
    "addr:postcode":"11103",
    "addr:street":"36Th St",
    "iso:country":"US",
    "sg:address":"25-17 36th St",
    "sg:city":"Queens",
    "sg:classifiers":[
        {
            "category":"Social Services",
            "subcategory":"Child Care",
            "type":"Services"
        },
        {
            "category":"Education",
            "subcategory":"Preschool",
            "type":"Public Place"
        }
    ],
    "sg:phone":"+1 718 278 7808",
    "sg:postcode":"11103",
    "sg:province":"NY",
    "sg:tags":[
        "day"
    ],
    "sg:website":"www.happydayschildcare.net/",
    "wof:name":"Happy Days Child Care",
    "wof:placetype":"venue"
},
  "geometry": {"coordinates":[-73.91399,40.76876],"type":"Point"}
}