{
  "type": "Feature",
  "properties": {
    "addr:full":"49 Main St Tonawanda NY 14150",
    "addr:housenumber":"49",
    "addr:postcode":"14150",
    "addr:street":"Main St",
    "iso:country":"US",
    "sg:address":"49 Main St",
    "sg:city":"Tonawanda",
    "sg:classifiers":[
        {
            "category":"Professional",
            "type":"Services"
        }
    ],
    "sg:phone":"+1 716 693 7235",
    "sg:postcode":"14150",
    "sg:province":"NY",
    "sg:tags":[
        "establishment"
    ],
    "wof:name":"Mulberry Tree",
    "wof:placetype":"venue"
},
  "geometry": {"coordinates":[-78.878321,43.019107],"type":"Point"}
}