{
  "type": "Feature",
  "properties": {
    "addr:full":"222 Summit Ave Buffalo NY 14214",
    "addr:housenumber":"222",
    "addr:postcode":"14214",
    "addr:street":"Summit Ave",
    "iso:country":"US",
    "sg:address":"222 Summit Ave",
    "sg:city":"Buffalo",
    "sg:classifiers":[
        {
            "category":"Real Estate",
            "subcategory":"Architect",
            "type":"Services"
        }
    ],
    "sg:phone":"+1   ",
    "sg:postcode":"14214",
    "sg:province":"NY",
    "sg:tags":[
        "architectural"
    ],
    "wof:name":"Deborah L Pease Architect",
    "wof:placetype":"venue"
},
  "geometry": {"coordinates":[-78.84755,42.939299],"type":"Point"}
}