{
  "type": "Feature",
  "properties": {
    "addr:full":"1100 Rockaway Ave Brooklyn NY 11236",
    "addr:housenumber":"1100",
    "addr:postcode":"11236",
    "addr:street":"Rockaway Ave",
    "iso:country":"US",
    "sg:address":"1100 Rockaway Ave",
    "sg:city":"Brooklyn",
    "sg:classifiers":[
        {
            "category":"Wholesale",
            "subcategory":"Auto Parts",
            "type":"Manufacturing & Wholesale Goods"
        }
    ],
    "sg:phone":"+1 718 495 4949",
    "sg:postcode":"11236",
    "sg:province":"NY",
    "sg:tags":[
        "automobile",
        "rebuilt"
    ],
    "wof:name":"Satellite Auto Parts Inc",
    "wof:placetype":"venue"
},
  "geometry": {"coordinates":[-73.906434,40.652687],"type":"Point"}
}