{
  "type": "Feature",
  "properties": {
    "addr:full":"20 Main St Massena NY 13662",
    "addr:housenumber":"20",
    "addr:postcode":"13662",
    "addr:street":"Main St",
    "iso:country":"US",
    "sg:address":"20 Main St",
    "sg:city":"Massena",
    "sg:classifiers":[
        {
            "category":"Bars & Pubs",
            "type":"Food & Drink"
        }
    ],
    "sg:phone":"+1 315 769 9873",
    "sg:postcode":"13662",
    "sg:province":"NY",
    "wof:name":"Phil's Tavern",
    "wof:placetype":"venue"
},
  "geometry": {"coordinates":[-74.893106,44.931924],"type":"Point"}
}