{
  "type": "Feature",
  "properties": {
    "iso:country":"US",
    "sg:address":"71 North Ave",
    "sg:city":"Webster",
    "sg:classifiers":[
        {
            "category":"Professional",
            "subcategory":"Computer Services",
            "type":"Services"
        },
        {
            "category":"Shopping",
            "subcategory":"Computers & Home Electronics",
            "type":"Retail Goods"
        }
    ],
    "sg:phone":"+1 585 872 7760",
    "sg:postcode":"14580",
    "sg:province":"NY",
    "sg:tags":[
        "design",
        "system",
        "software"
    ],
    "wof:name":"Network Services Group LLC",
    "wof:placetype":"venue"
},
  "geometry": {"coordinates":[-77.430217,43.212818],"type":"Point"}
}