{
  "type": "Feature",
  "properties": {
    "iso:country":"US",
    "sg:address":"220 W 93 St",
    "sg:city":"New York",
    "sg:classifiers":[
        {
            "category":"Education",
            "subcategory":"Dance Studio",
            "type":"Public Place"
        }
    ],
    "sg:phone":"+1   ",
    "sg:postcode":"10025",
    "sg:province":"NY",
    "wof:name":"Infinity Dance Theatre",
    "wof:placetype":"venue"
},
  "geometry": {"coordinates":[-73.972782,40.79241],"type":"Point"}
}