{
  "type": "Feature",
  "properties": {
    "iso:country":"US",
    "sg:address":"1432 Lexington Ave",
    "sg:city":"New York",
    "sg:classifiers":[
        {
            "category":"Professional",
            "subcategory":"Business Services",
            "type":"Services"
        }
    ],
    "sg:phone":"+1 212 426 3801",
    "sg:postcode":"10128",
    "sg:province":"NY",
    "sg:tags":[
        "interior",
        "consultant",
        "design",
        "decorator"
    ],
    "wof:name":"M Anderson Design Inc",
    "wof:placetype":"venue"
},
  "geometry": {"coordinates":[-73.952122,40.784287],"type":"Point"}
}