{
  "type": "Feature",
  "properties": {
    "iso:country":"US",
    "sg:address":"105 Sunset Dr",
    "sg:city":"Rochester",
    "sg:classifiers":[
        {
            "category":"Professional",
            "type":"Services"
        }
    ],
    "sg:phone":"+1 585 242 8927",
    "sg:postcode":"14618",
    "sg:province":"NY",
    "sg:tags":[
        "establishment"
    ],
    "wof:name":"Davis Steven D Csw Bcd Casac",
    "wof:placetype":"venue"
},
  "geometry": {"coordinates":[-77.55396500000001,43.122051],"type":"Point"}
}