{
  "type": "Feature",
  "properties": {
    "addr:full":"212 8th Ave New York NY 10011",
    "addr:housenumber":"212",
    "addr:postcode":"10011",
    "addr:street":"8Th Ave",
    "iso:country":"US",
    "sg:address":"212 8th Ave",
    "sg:city":"New York",
    "sg:classifiers":[
        {
            "category":"Bars & Pubs",
            "subcategory":"Gay Bar",
            "type":"Food & Drink"
        }
    ],
    "sg:phone":"+1 212 242 9332",
    "sg:postcode":"10011",
    "sg:province":"NY",
    "wof:name":"Rawhide",
    "wof:placetype":"venue"
},
  "geometry": {"coordinates":[-73.999397,40.743801],"type":"Point"}
}