{
  "type": "Feature",
  "properties": {
    "iso:country":"US",
    "sg:address":"1663 E 17th St",
    "sg:city":"Brooklyn",
    "sg:classifiers":[
        {
            "category":"Professional",
            "subcategory":"Advertising",
            "type":"Services"
        }
    ],
    "sg:phone":"+1 718 998 0200",
    "sg:postcode":"11229",
    "sg:province":"NY",
    "sg:tags":[
        "counselor"
    ],
    "wof:name":"Comprehensive Resources",
    "wof:placetype":"venue"
},
  "geometry": {"coordinates":[-73.95625099999999,40.608672],"type":"Point"}
}