{
  "type": "Feature",
  "properties": {
    "iso:country":"US",
    "sg:address":"204 Wellington Rd",
    "sg:city":"Mineola",
    "sg:classifiers":[
        {
            "category":"Professional",
            "type":"Services"
        }
    ],
    "sg:phone":"+1 516 747 1115",
    "sg:postcode":"11501",
    "sg:province":"NY",
    "sg:tags":[
        "establishment"
    ],
    "wof:name":"Grpahics Bleed",
    "wof:placetype":"venue"
},
  "geometry": {"coordinates":[-73.645304,40.744021],"type":"Point"}
}