{
  "type": "Feature",
  "properties": {
    "addr:full":"2449 Bragg St Brooklyn NY 11235",
    "addr:housenumber":"2449",
    "addr:postcode":"11235",
    "addr:street":"Bragg St",
    "iso:country":"US",
    "sg:address":"2449 Bragg St",
    "sg:city":"Brooklyn",
    "sg:classifiers":[
        {
            "category":"Shopping",
            "type":"Retail Goods"
        }
    ],
    "sg:phone":"+1 718 769 4774",
    "sg:postcode":"11235",
    "sg:province":"NY",
    "sg:tags":[
        "stamp",
        "collector",
        "for"
    ],
    "wof:name":"DRJB Enterprises",
    "wof:placetype":"venue"
},
  "geometry": {"coordinates":[-73.934612,40.59336],"type":"Point"}
}