{
  "type": "Feature",
  "properties": {
    "iso:country":"US",
    "sg:address":"1025 E 163rd St",
    "sg:city":"Bronx",
    "sg:classifiers":[
        {
            "category":"Restaurant",
            "type":"Food & Drink"
        }
    ],
    "sg:phone":"+1 718 378 0252",
    "sg:postcode":"10459",
    "sg:province":"NY",
    "wof:name":"Asia Luna Restaurant",
    "wof:placetype":"venue"
},
  "geometry": {"coordinates":[-73.89235499999999,40.821051],"type":"Point"}
}