{
  "type": "Feature",
  "properties": {
    "iso:country":"US",
    "sg:address":"2399 Sweet Home Rd",
    "sg:city":"Buffalo",
    "sg:classifiers":[
        {
            "category":"Professional",
            "subcategory":"Accounting & Tax Preparation",
            "type":"Services"
        }
    ],
    "sg:phone":"+1 716 564 3730",
    "sg:postcode":"14228",
    "sg:province":"NY",
    "sg:tags":[
        "accountant",
        "public",
        "certified"
    ],
    "sg:website":"www.larkingibbs.com",
    "wof:name":"Larkin & Gibbs",
    "wof:placetype":"venue"
},
  "geometry": {"coordinates":[-78.799031,43.024654],"type":"Point"}
}