{
  "type": "Feature",
  "properties": {
    "addr:full":"43 Conklin St Farmingdale NY 11735",
    "addr:housenumber":"43",
    "addr:postcode":"11735",
    "addr:street":"Conklin St",
    "iso:country":"US",
    "sg:address":"43 Conklin St",
    "sg:city":"Farmingdale",
    "sg:classifiers":[
        {
            "category":"Professional",
            "type":"Services"
        }
    ],
    "sg:phone":"+1 631 390 7777",
    "sg:postcode":"11735",
    "sg:province":"NY",
    "sg:tags":[
        "establishment"
    ],
    "wof:name":"Ark Capital Corp",
    "wof:placetype":"venue"
},
  "geometry": {"coordinates":[-73.460184,40.730594],"type":"Point"}
}