{
  "type": "Feature",
  "properties": {
    "iso:country":"US",
    "sg:address":"82 Seaview Ave",
    "sg:city":"Staten Island",
    "sg:classifiers":[
        {
            "category":"Food & Beverages",
            "subcategory":"Groceries & Convenience Stores",
            "type":"Retail Goods"
        }
    ],
    "sg:phone":"+1   ",
    "sg:postcode":"10304",
    "sg:province":"NY",
    "wof:name":"Angelos Superette Inc",
    "wof:placetype":"venue"
},
  "geometry": {"coordinates":[-74.099716,40.590525],"type":"Point"}
}