{
  "type": "Feature",
  "properties": {
    "iso:country":"US",
    "sg:address":"679 Washington St",
    "sg:city":"New York",
    "sg:classifiers":[
        {
            "category":"Retail",
            "subcategory":"Laundry & Dry Cleaning",
            "type":"Services"
        }
    ],
    "sg:phone":"+1 212 627 3646",
    "sg:postcode":"10014",
    "sg:province":"NY",
    "sg:tags":[
        "drycleaning",
        "plant"
    ],
    "wof:name":"Memphis Cleaners Inc",
    "wof:placetype":"venue"
},
  "geometry": {"coordinates":[-74.008698,40.7337],"type":"Point"}
}