{
  "type": "Feature",
  "properties": {
    "iso:country":"US",
    "sg:address":"177 N Main St",
    "sg:city":"Warsaw",
    "sg:classifiers":[
        {
            "category":"Cinema",
            "subcategory":"Movie Theater",
            "type":"Entertainment"
        }
    ],
    "sg:phone":"+1 585 786 3030",
    "sg:postcode":"14569",
    "sg:province":"NY",
    "wof:name":"Wyoming County Bicentenial",
    "wof:placetype":"venue"
},
  "geometry": {"coordinates":[-78.13265,42.745265],"type":"Point"}
}