{
  "type": "Feature",
  "properties": {
    "iso:country":"US",
    "sg:address":"64 Lorraine Rd",
    "sg:city":"Island Park",
    "sg:classifiers":[
        {
            "category":"Building & Trades",
            "subcategory":"Construction",
            "type":"Services"
        }
    ],
    "sg:phone":"+1 516 763 3285",
    "sg:postcode":"11558",
    "sg:province":"NY",
    "sg:tags":[
        "contractor"
    ],
    "wof:name":"William OConnor",
    "wof:placetype":"venue"
},
  "geometry": {"coordinates":[-73.650532,40.610501],"type":"Point"}
}