{
  "type": "Feature",
  "properties": {
    "addr:full":"3550 W Genesee St Syracuse NY 13219",
    "addr:housenumber":"3550",
    "addr:postcode":"13219",
    "addr:street":"W Genesee St",
    "iso:country":"US",
    "sg:address":"3550 W Genesee St",
    "sg:city":"Syracuse",
    "sg:classifiers":[
        {
            "category":"Bars & Pubs",
            "subcategory":"Lounge",
            "type":"Food & Drink"
        },
        {
            "category":"Food & Beverages",
            "subcategory":"Liquor & Beverages",
            "type":"Retail Goods"
        }
    ],
    "sg:phone":"+1 315 488 7411",
    "sg:postcode":"13219",
    "sg:province":"NY",
    "sg:tags":[
        "cocktail",
        "store"
    ],
    "wof:name":"Hallinan's Liquor Store",
    "wof:placetype":"venue"
},
  "geometry": {"coordinates":[-76.235044,43.047784],"type":"Point"}
}