{
  "type": "Feature",
  "properties": {
    "iso:country":"US",
    "sg:address":"182 Varick St",
    "sg:city":"New York",
    "sg:classifiers":[
        {
            "category":"Restaurant",
            "type":"Food & Drink"
        }
    ],
    "sg:phone":"+1   ",
    "sg:postcode":"10014",
    "sg:province":"NY",
    "sg:tags":[
        "eating"
    ],
    "wof:name":"Little Italy Pizza",
    "wof:placetype":"venue"
},
  "geometry": {"coordinates":[-74.005404,40.727457],"type":"Point"}
}