{
  "type": "Feature",
  "properties": {
    "iso:country":"US",
    "sg:address":"602 Ave T",
    "sg:city":"Brooklyn",
    "sg:classifiers":[
        {
            "category":"Organizations",
            "subcategory":"Religious Organization",
            "type":"Services"
        }
    ],
    "sg:phone":"+1 718 376 3615",
    "sg:postcode":"11223",
    "sg:province":"NY",
    "sg:tags":[
        "clergy"
    ],
    "wof:name":"Chalom Elbaz",
    "wof:placetype":"venue"
},
  "geometry": {"coordinates":[-73.96454,40.600165],"type":"Point"}
}