{
  "type": "Feature",
  "properties": {
    "addr:full":"8 Fulton St White Plains NY 10606",
    "addr:housenumber":"8",
    "addr:postcode":"10606",
    "addr:street":"Fulton St",
    "iso:country":"US",
    "sg:address":"8 Fulton St",
    "sg:city":"White Plains",
    "sg:classifiers":[
        {
            "category":"Building & Trades",
            "subcategory":"Electrical",
            "type":"Services"
        }
    ],
    "sg:phone":"+1 914 428 5200",
    "sg:postcode":"10606",
    "sg:province":"NY",
    "sg:tags":[
        "electrical",
        "contractor"
    ],
    "wof:name":"Mount Pleasant Electric",
    "wof:placetype":"venue"
},
  "geometry": {"coordinates":[-73.784713,41.035122],"type":"Point"}
}