{
  "type": "Feature",
  "properties": {
    "iso:country":"US",
    "sg:address":"189 Burr Rd",
    "sg:city":"East Northport",
    "sg:classifiers":[
        {
            "category":"Organizations",
            "subcategory":"Religious Organization",
            "type":"Services"
        }
    ],
    "sg:phone":"+1 631 499 4655",
    "sg:postcode":"11731",
    "sg:province":"NY",
    "sg:website":"www.gotoclc.org",
    "wof:name":"Christ Lutheran Church",
    "wof:placetype":"venue"
},
  "geometry": {"coordinates":[-73.31293100000001,40.849112],"type":"Point"}
}