{
  "type": "Feature",
  "properties": {
    "addr:full":"511 Airport Executive Park Nanuet NY 10954",
    "addr:housenumber":"511",
    "addr:postcode":"10954",
    "addr:street":"Airport Executive Park",
    "iso:country":"US",
    "sg:address":"511 Airport Executive Park",
    "sg:city":"Nanuet",
    "sg:classifiers":[
        {
            "category":"Wholesale",
            "subcategory":"Drugs",
            "type":"Manufacturing & Wholesale Goods"
        },
        {
            "category":"Personal",
            "subcategory":"Beauty Salon",
            "type":"Services"
        }
    ],
    "sg:phone":"+1 845 578 1500",
    "sg:postcode":"10954",
    "sg:province":"NY",
    "sg:tags":[
        "product",
        "skin",
        "cosmetic",
        "care",
        "treatment"
    ],
    "wof:name":"Nelly D Vuyst USA Inc",
    "wof:placetype":"venue"
},
  "geometry": {"coordinates":[-74.02816799999999,41.108324],"type":"Point"}
}