{
  "type": "Feature",
  "properties": {
    "iso:country":"US",
    "sg:address":"11 Mill St",
    "sg:city":"New York Mills",
    "sg:classifiers":[
        {
            "category":"Building & Trades",
            "subcategory":"Construction",
            "type":"Services"
        }
    ],
    "sg:phone":"+1 315 736 8397",
    "sg:postcode":"13417",
    "sg:province":"NY",
    "sg:tags":[
        "masonry",
        "sealing",
        "caulking",
        "contractor"
    ],
    "sg:website":"www.lupiniconstruction.com",
    "wof:name":"Lupini Construction Inc",
    "wof:placetype":"venue"
},
  "geometry": {"coordinates":[-75.29380999999999,43.10485],"type":"Point"}
}