{
  "type": "Feature",
  "properties": {
    "addr:full":"5 E 22nd St Frnt New York NY 10010",
    "addr:housenumber":"5",
    "addr:postcode":"10010",
    "addr:street":"E 22Nd St",
    "iso:country":"US",
    "sg:address":"5 E 22nd St Frnt",
    "sg:city":"New York",
    "sg:classifiers":[
        {
            "category":"Retail",
            "subcategory":"Laundry & Dry Cleaning",
            "type":"Services"
        }
    ],
    "sg:phone":"+1 212 533 3546",
    "sg:postcode":"10010",
    "sg:province":"NY",
    "wof:name":"Green Valet",
    "wof:placetype":"venue"
},
  "geometry": {"coordinates":[-73.989304,40.740601],"type":"Point"}
}