{
  "type": "Feature",
  "properties": {
    "addr:full":"110 Genesee St Auburn NY 13021",
    "addr:housenumber":"110",
    "addr:postcode":"13021",
    "addr:street":"Genesee St",
    "iso:country":"US",
    "sg:address":"110 Genesee St",
    "sg:city":"Auburn",
    "sg:classifiers":[
        {
            "category":"Professional",
            "subcategory":"Lawyer & Legal Services",
            "type":"Services"
        }
    ],
    "sg:phone":"+1 315 253 0326",
    "sg:postcode":"13021",
    "sg:province":"NY",
    "sg:tags":[
        "attorney"
    ],
    "wof:name":"Boyle & Anderson",
    "wof:placetype":"venue"
},
  "geometry": {"coordinates":[-76.568144,42.930603],"type":"Point"}
}