{
  "type": "Feature",
  "properties": {
    "addr:full":"4215 Crescent Street Suite 304 Long Island City NY 11101",
    "addr:housenumber":"4215",
    "addr:postcode":"11101",
    "addr:street":"Crescent Street Suite 304",
    "iso:country":"US",
    "sg:address":"4215 Crescent Street Suite 304",
    "sg:city":"Long Island City",
    "sg:classifiers":[
        {
            "category":"Professional",
            "subcategory":"Lawyer & Legal Services",
            "type":"Services"
        }
    ],
    "sg:phone":"+1 718 784 5080",
    "sg:postcode":"11101",
    "sg:province":"NY",
    "wof:name":"Mision Hispana",
    "wof:placetype":"venue"
},
  "geometry": {"coordinates":[-73.94092000000001,40.750147],"type":"Point"}
}