{
  "type": "Feature",
  "properties": {
    "addr:full":"33 35th St Brooklyn NY 11232",
    "addr:housenumber":"33",
    "addr:postcode":"11232",
    "addr:street":"35Th St",
    "iso:country":"US",
    "sg:address":"33 35th St",
    "sg:city":"Brooklyn",
    "sg:classifiers":[
        {
            "category":"Professional",
            "type":"Services"
        }
    ],
    "sg:phone":"+1 718 840 2811",
    "sg:postcode":"11232",
    "sg:province":"NY",
    "sg:tags":[
        "establishment"
    ],
    "wof:name":"CBA",
    "wof:placetype":"venue"
},
  "geometry": {"coordinates":[-74.005906,40.656124],"type":"Point"}
}