{
  "type": "Feature",
  "properties": {
    "iso:country":"US",
    "sg:address":"4 Martine Ave",
    "sg:city":"White Plains",
    "sg:classifiers":[
        {
            "category":"Real Estate",
            "subcategory":"Real Estate Operator",
            "type":"Services"
        }
    ],
    "sg:phone":"+1 914 328 4630",
    "sg:postcode":"10606",
    "sg:province":"NY",
    "sg:tags":[
        "apartment"
    ],
    "wof:name":"Wimbleton Apartments",
    "wof:placetype":"venue"
},
  "geometry": {"coordinates":[-73.77219100000001,41.030414],"type":"Point"}
}