{
  "type": "Feature",
  "properties": {
    "addr:full":"410 Bunn Hill Rd Vestal NY 13850",
    "addr:housenumber":"410",
    "addr:postcode":"13850",
    "addr:street":"Bunn Hill Rd",
    "iso:country":"US",
    "sg:address":"410 Bunn Hill Rd",
    "sg:city":"Vestal",
    "sg:classifiers":[
        {
            "category":"Manufacturing",
            "subcategory":"Tools & Machinery",
            "type":"Manufacturing & Wholesale Goods"
        }
    ],
    "sg:phone":"+1   ",
    "sg:postcode":"13850",
    "sg:province":"NY",
    "sg:tags":[
        "construction",
        "mfg"
    ],
    "wof:name":"Wood Wiz",
    "wof:placetype":"venue"
},
  "geometry": {"coordinates":[-75.993551,42.063016],"type":"Point"}
}