{
  "type": "Feature",
  "properties": {
    "addr:full":"2132 1st Ave Manhattan NY 10029",
    "addr:housenumber":"2132",
    "addr:postcode":"10029",
    "addr:street":"1St Ave",
    "iso:country":"US",
    "sg:address":"2132 1st Ave",
    "sg:city":"Manhattan",
    "sg:classifiers":[
        {
            "category":"Building & Trades",
            "subcategory":"Pest Control",
            "type":"Services"
        }
    ],
    "sg:phone":"+1 347 422 5292",
    "sg:postcode":"10029",
    "sg:province":"NY",
    "sg:website":"www.perrysexterminators.com",
    "wof:name":"Perrys Exterminators",
    "wof:placetype":"venue"
},
  "geometry": {"coordinates":[-73.93820100000001,40.792127],"type":"Point"}
}