{
  "type": "Feature",
  "properties": {
    "iso:country":"US",
    "sg:address":"1095 Avenue of the Americas",
    "sg:city":"New York",
    "sg:classifiers":[
        {
            "category":"Professional",
            "subcategory":"Lawyer & Legal Services",
            "type":"Services"
        }
    ],
    "sg:phone":"+1 212 395 0029",
    "sg:postcode":"10036",
    "sg:province":"NY",
    "wof:name":"Abramson Carol R Lwyr",
    "wof:placetype":"venue"
},
  "geometry": {"coordinates":[-73.98457999999999,40.755021],"type":"Point"}
}