{
  "type": "Feature",
  "properties": {
    "addr:full":"78 Schuyler Baldwin Dr Fairport NY 14450",
    "addr:housenumber":"78",
    "addr:postcode":"14450",
    "addr:street":"Schuyler Baldwin Dr",
    "iso:country":"US",
    "sg:address":"78 Schuyler Baldwin Dr",
    "sg:city":"Fairport",
    "sg:classifiers":[
        {
            "category":"Professional",
            "subcategory":"Computer Services",
            "type":"Services"
        }
    ],
    "sg:phone":"+1 585 334 0663",
    "sg:postcode":"14450",
    "sg:province":"NY",
    "wof:name":"Rescuecom",
    "wof:placetype":"venue"
},
  "geometry": {"coordinates":[-77.391013,43.092013],"type":"Point"}
}