{
  "type": "Feature",
  "properties": {
    "addr:full":"3056 Buhre Ave Bronx NY 10461",
    "addr:housenumber":"3056",
    "addr:postcode":"10461",
    "addr:street":"Buhre Ave",
    "iso:country":"US",
    "sg:address":"3056 Buhre Ave",
    "sg:city":"Bronx",
    "sg:classifiers":[
        {
            "category":"Communications",
            "subcategory":"Newspaper",
            "type":"Services"
        }
    ],
    "sg:phone":"+1 718 684 1785",
    "sg:postcode":"10461",
    "sg:province":"NY",
    "sg:tags":[
        "magazine"
    ],
    "wof:name":"Shs News Inc",
    "wof:placetype":"venue"
},
  "geometry": {"coordinates":[-73.830505,40.847513],"type":"Point"}
}