{
  "type": "Feature",
  "properties": {
    "iso:country":"US",
    "sg:address":"7 Scouting Blvd",
    "sg:city":"Medford",
    "sg:classifiers":[
        {
            "category":"Organizations",
            "subcategory":"Community Association",
            "type":"Services"
        }
    ],
    "sg:phone":"+1 631 924 7000",
    "sg:postcode":"11763",
    "sg:province":"NY",
    "sg:tags":[
        "executive"
    ],
    "sg:website":"www.scouting.org",
    "wof:name":"Boy Scouts Of America",
    "wof:placetype":"venue"
},
  "geometry": {"coordinates":[-72.960921,40.815105],"type":"Point"}
}