{
  "type": "Feature",
  "properties": {
    "iso:country":"US",
    "sg:address":"601 Dise Rd",
    "sg:city":"Little Falls",
    "sg:classifiers":[
        {
            "category":"Wholesale",
            "subcategory":"Auto Parts",
            "type":"Manufacturing & Wholesale Goods"
        }
    ],
    "sg:phone":"+1 315 823 1603",
    "sg:postcode":"13365",
    "sg:province":"NY",
    "wof:name":"Automotive Imagineering",
    "wof:placetype":"venue"
},
  "geometry": {"coordinates":[-74.85569099999999,43.064209],"type":"Point"}
}