{
  "type": "Feature",
  "properties": {
    "addr:full":"33 Branchbrook Dr Henrietta NY 14467",
    "addr:housenumber":"33",
    "addr:postcode":"14467",
    "addr:street":"Branchbrook Dr",
    "iso:country":"US",
    "sg:address":"33 Branchbrook Dr",
    "sg:city":"Henrietta",
    "sg:classifiers":[
        {
            "category":"Professional",
            "subcategory":"Art Services",
            "type":"Services"
        }
    ],
    "sg:phone":"+1   ",
    "sg:postcode":"14467",
    "sg:province":"NY",
    "sg:tags":[
        "photography",
        "commercial"
    ],
    "wof:name":"G & L Photographic",
    "wof:placetype":"venue"
},
  "geometry": {"coordinates":[-77.623538,43.033062],"type":"Point"}
}