{
  "type": "Feature",
  "properties": {
    "addr:full":"4882 N Jefferson St Pulaski NY 13142",
    "addr:housenumber":"4882",
    "addr:postcode":"13142",
    "addr:street":"N Jefferson St",
    "iso:country":"US",
    "sg:address":"4882 N Jefferson St",
    "sg:city":"Pulaski",
    "sg:classifiers":[
        {
            "category":"Health Services",
            "subcategory":"Doctor",
            "type":"Services"
        }
    ],
    "sg:phone":"+1 315 298 2768",
    "sg:postcode":"13142",
    "sg:province":"NY",
    "sg:tags":[
        "physician",
        "medical",
        "surgeon"
    ],
    "wof:name":"Jay F Sullivan MD PC",
    "wof:placetype":"venue"
},
  "geometry": {"coordinates":[-76.12684900000001,43.567783],"type":"Point"}
}