{
  "type": "Feature",
  "properties": {
    "iso:country":"US",
    "sg:address":"608 Leray St",
    "sg:city":"Watertown",
    "sg:classifiers":[
        {
            "category":"Retail",
            "subcategory":"Laundry & Dry Cleaning",
            "type":"Services"
        }
    ],
    "sg:phone":"+1 315 782 3736",
    "sg:postcode":"13601",
    "sg:province":"NY",
    "sg:tags":[
        "cleaners",
        "rug",
        "carpet"
    ],
    "wof:name":"Dry Tech Carpet Cleaning",
    "wof:placetype":"venue"
},
  "geometry": {"coordinates":[-75.911417,43.984598],"type":"Point"}
}