{
  "type": "Feature",
  "properties": {
    "iso:country":"US",
    "sg:address":"4616 5th Ave",
    "sg:city":"Brooklyn",
    "sg:classifiers":[
        {
            "category":"Restaurant",
            "type":"Food & Drink"
        }
    ],
    "sg:phone":"+1 718 439 1661",
    "sg:postcode":"11220",
    "sg:province":"NY",
    "wof:name":"Tacos California",
    "wof:placetype":"venue"
},
  "geometry": {"coordinates":[-74.008593,40.647171],"type":"Point"}
}