{
  "type": "Feature",
  "properties": {
    "iso:country":"US",
    "sg:address":"12 Terrich Ct",
    "sg:city":"Ossining",
    "sg:classifiers":[
        {
            "category":"Organizations",
            "subcategory":"Community Association",
            "type":"Services"
        }
    ],
    "sg:phone":"+1   ",
    "sg:postcode":"10562",
    "sg:province":"NY",
    "wof:name":"Alliance To Close Indian Point",
    "wof:placetype":"venue"
},
  "geometry": {"coordinates":[-73.84502000000001,41.168731],"type":"Point"}
}