{
  "type": "Feature",
  "properties": {
    "addr:full":"310 E Gun Hill Rd Bronx NY 10467",
    "addr:housenumber":"310",
    "addr:postcode":"10467",
    "addr:street":"E Gun Hill Rd",
    "iso:country":"US",
    "sg:address":"310 E Gun Hill Rd",
    "sg:city":"Bronx",
    "sg:classifiers":[
        {
            "category":"Retail",
            "subcategory":"Self-service Laundry",
            "type":"Services"
        }
    ],
    "sg:phone":"+1 718 515 7548",
    "sg:postcode":"10467",
    "sg:province":"NY",
    "wof:name":"Miracle Working Ctr Inc",
    "wof:placetype":"venue"
},
  "geometry": {"coordinates":[-73.873767,40.87886],"type":"Point"}
}