{
  "type": "Feature",
  "properties": {
    "addr:full":"178 Stormville Mountain Rd Stormville NY 12582",
    "addr:housenumber":"178",
    "addr:postcode":"12582",
    "addr:street":"Stormville Mountain Rd",
    "iso:country":"US",
    "sg:address":"178 Stormville Mountain Rd",
    "sg:city":"Stormville",
    "sg:classifiers":[
        {
            "category":"Sports & Exercise",
            "subcategory":"Golf",
            "type":"Entertainment"
        }
    ],
    "sg:phone":"+1 845 223 1600",
    "sg:postcode":"12582",
    "sg:province":"NY",
    "sg:tags":[
        "course"
    ],
    "wof:name":"Branton Woods Golf Club",
    "wof:placetype":"venue"
},
  "geometry": {"coordinates":[-73.733396,41.554672],"type":"Point"}
}