{
  "type": "Feature",
  "properties": {
    "iso:country":"US",
    "sg:address":"247 Hollywood Ave",
    "sg:city":"Tuckahoe",
    "sg:classifiers":[
        {
            "category":"Real Estate",
            "subcategory":"Real Estate Services",
            "type":"Services"
        },
        {
            "category":"Real Estate",
            "subcategory":"Real Estate Agent",
            "type":"Services"
        }
    ],
    "sg:phone":"+1 914 779 5315",
    "sg:postcode":"10707",
    "sg:province":"NY",
    "sg:tags":[
        "buyer",
        "broker"
    ],
    "wof:name":"Judy Realty Corp",
    "wof:placetype":"venue"
},
  "geometry": {"coordinates":[-73.821842,40.967008],"type":"Point"}
}