{
  "type": "Feature",
  "properties": {
    "addr:full":"600 Johnson Ave Bohemia NY 11716",
    "addr:housenumber":"600",
    "addr:postcode":"11716",
    "addr:street":"Johnson Ave",
    "iso:country":"US",
    "sg:address":"600 Johnson Ave",
    "sg:city":"Bohemia",
    "sg:classifiers":[
        {
            "category":"Professional",
            "type":"Services"
        }
    ],
    "sg:phone":"+1 631 563 8188",
    "sg:postcode":"11716",
    "sg:province":"NY",
    "sg:tags":[
        "establishment"
    ],
    "wof:name":"Khan Buta",
    "wof:placetype":"venue"
},
  "geometry": {"coordinates":[-73.097087,40.780578],"type":"Point"}
}