{
  "type": "Feature",
  "properties": {
    "iso:country":"US",
    "sg:address":"10 E 46th St",
    "sg:city":"New York",
    "sg:classifiers":[
        {
            "category":"Government",
            "subcategory":"Office",
            "type":"Public Place"
        }
    ],
    "sg:phone":"+1 212 370 0004",
    "sg:postcode":"10017",
    "sg:province":"NY",
    "sg:tags":[
        "federal",
        "international",
        "affairs"
    ],
    "wof:name":"Colombian Consulate General",
    "wof:placetype":"venue"
},
  "geometry": {"coordinates":[-73.977828,40.755497],"type":"Point"}
}