{
  "type": "Feature",
  "properties": {
    "iso:country":"US",
    "sg:address":"571 E 83rd St",
    "sg:city":"Brooklyn",
    "sg:classifiers":[
        {
            "category":"Professional",
            "subcategory":"Engineering",
            "type":"Services"
        },
        {
            "category":"Building & Trades",
            "subcategory":"Construction",
            "type":"Services"
        }
    ],
    "sg:phone":"+1 718 927 1163",
    "sg:postcode":"11236",
    "sg:province":"NY",
    "sg:tags":[
        "system",
        "specialty",
        "heating",
        "contractor",
        "refrigeration",
        "air conditioning",
        "engineer"
    ],
    "wof:name":"Ja's Protocol Rfrgn Svcs",
    "wof:placetype":"venue"
},
  "geometry": {"coordinates":[-73.91515699999999,40.640596],"type":"Point"}
}