{
  "type": "Feature",
  "properties": {
    "addr:full":"224 N Comrie Ave Johnstown NY 12095",
    "addr:housenumber":"224",
    "addr:postcode":"12095",
    "addr:street":"N Comrie Ave",
    "iso:country":"US",
    "sg:address":"224 N Comrie Ave",
    "sg:city":"Johnstown",
    "sg:classifiers":[
        {
            "category":"Shopping",
            "subcategory":"Department Store",
            "type":"Retail Goods"
        }
    ],
    "sg:phone":"+1 518 762 0252",
    "sg:postcode":"12095",
    "sg:province":"NY",
    "wof:name":"Peebles",
    "wof:placetype":"venue"
},
  "geometry": {"coordinates":[-74.361048,43.015126],"type":"Point"}
}