{
  "type": "Feature",
  "properties": {
    "addr:full":"14 Union Rd Spring Valley NY 10977",
    "addr:housenumber":"14",
    "addr:postcode":"10977",
    "addr:street":"Union Rd",
    "iso:country":"US",
    "sg:address":"14 Union Rd",
    "sg:city":"Spring Valley",
    "sg:classifiers":[
        {
            "category":"Social Services",
            "type":"Services"
        }
    ],
    "sg:phone":"+1 845 352 8671",
    "sg:postcode":"10977",
    "sg:province":"NY",
    "sg:tags":[
        "organization",
        "welfare"
    ],
    "wof:name":"Spring Valley Housing Auth",
    "wof:placetype":"venue"
},
  "geometry": {"coordinates":[-74.045953,41.117303],"type":"Point"}
}