{
  "type": "Feature",
  "properties": {
    "iso:country":"US",
    "sg:address":"395 Wimbledon Rd",
    "sg:city":"Rochester",
    "sg:classifiers":[
        {
            "category":"Shopping",
            "subcategory":"Hobbies, Toys, & Games",
            "type":"Retail Goods"
        }
    ],
    "sg:phone":"+1   ",
    "sg:postcode":"14617",
    "sg:province":"NY",
    "sg:tags":[
        "board"
    ],
    "wof:name":"Adventures & Hobbies",
    "wof:placetype":"venue"
},
  "geometry": {"coordinates":[-77.60591100000001,43.204722],"type":"Point"}
}