{
  "type": "Feature",
  "properties": {
    "iso:country":"US",
    "sg:address":"14 Water St",
    "sg:city":"Oneonta",
    "sg:classifiers":[
        {
            "category":"Bars & Pubs",
            "type":"Food & Drink"
        }
    ],
    "sg:phone":"+1 607 432 9566",
    "sg:postcode":"13820",
    "sg:province":"NY",
    "sg:tags":[
        "tavern"
    ],
    "wof:name":"Black Oak Tavern",
    "wof:placetype":"venue"
},
  "geometry": {"coordinates":[-75.062647,42.452766],"type":"Point"}
}