{
  "type": "Feature",
  "properties": {
    "iso:country":"US",
    "sg:address":"3361 Baychester Ave",
    "sg:city":"Bronx",
    "sg:classifiers":[
        {
            "category":"Utilities",
            "subcategory":"Mobile Phone",
            "type":"Services"
        }
    ],
    "sg:phone":"+1   ",
    "sg:postcode":"10469",
    "sg:province":"NY",
    "sg:tags":[
        "communication",
        "radiotelephone"
    ],
    "wof:name":"Baychester Wireless",
    "wof:placetype":"venue"
},
  "geometry": {"coordinates":[-73.83874299999999,40.881266],"type":"Point"}
}