{
  "type": "Feature",
  "properties": {
    "addr:full":"336 Middletown Rd Waterford NY 12188",
    "addr:housenumber":"336",
    "addr:postcode":"12188",
    "addr:street":"Middletown Rd",
    "iso:country":"US",
    "sg:address":"336 Middletown Rd",
    "sg:city":"Waterford",
    "sg:classifiers":[
        {
            "category":"Government",
            "subcategory":"Post Office",
            "type":"Public Place"
        }
    ],
    "sg:phone":"+1 518 373 1230",
    "sg:postcode":"12188",
    "sg:province":"NY",
    "sg:tags":[
        "delivery",
        "courier"
    ],
    "wof:name":"Ron Cocca's Courier Express",
    "wof:placetype":"venue"
},
  "geometry": {"coordinates":[-73.71743499999999,42.829076],"type":"Point"}
}