{
  "type": "Feature",
  "properties": {
    "iso:country":"US",
    "sg:address":"304 Cogswell Ave",
    "sg:city":"Syracuse",
    "sg:classifiers":[
        {
            "category":"Retail",
            "subcategory":"Repair Shop",
            "type":"Services"
        }
    ],
    "sg:phone":"+1   ",
    "sg:postcode":"13209",
    "sg:province":"NY",
    "sg:tags":[
        "household",
        "appliance"
    ],
    "wof:name":"Cavedines Sales & Service",
    "wof:placetype":"venue"
},
  "geometry": {"coordinates":[-76.21863500000001,43.059731],"type":"Point"}
}