{
  "type": "Feature",
  "properties": {
    "iso:country":"US",
    "sg:address":"665 Bleecker St",
    "sg:city":"Utica",
    "sg:classifiers":[
        {
            "category":"Social Services",
            "type":"Services"
        }
    ],
    "sg:phone":"+1   ",
    "sg:postcode":"13501",
    "sg:province":"NY",
    "wof:name":"New Life Community Services",
    "wof:placetype":"venue"
},
  "geometry": {"coordinates":[-75.219273,43.098984],"type":"Point"}
}