{
  "type": "Feature",
  "properties": {
    "addr:full":"333 Cedarwood Ter Rochester NY 14609",
    "addr:housenumber":"333",
    "addr:postcode":"14609",
    "addr:street":"Cedarwood Ter",
    "iso:country":"US",
    "sg:address":"333 Cedarwood Ter",
    "sg:city":"Rochester",
    "sg:classifiers":[
        {
            "category":"Communications",
            "type":"Services"
        }
    ],
    "sg:phone":"+1 585 334 2369",
    "sg:postcode":"14609",
    "sg:province":"NY",
    "wof:name":"CNG Communications",
    "wof:placetype":"venue"
},
  "geometry": {"coordinates":[-77.56612,43.162806],"type":"Point"}
}