{
  "type": "Feature",
  "properties": {
    "iso:country":"US",
    "sg:address":"20 Elm St",
    "sg:city":"Hornell",
    "sg:classifiers":[
        {
            "category":"Health Services",
            "subcategory":"Doctor",
            "type":"Services"
        }
    ],
    "sg:phone":"+1 607 324 0490",
    "sg:postcode":"14843",
    "sg:province":"NY",
    "sg:tags":[
        "medical"
    ],
    "wof:name":"Primary Med Care Otptent Clnic",
    "wof:placetype":"venue"
},
  "geometry": {"coordinates":[-77.659569,42.324781],"type":"Point"}
}