{
  "type": "Feature",
  "properties": {
    "addr:full":"102 Lafayette St Palatine Bridge NY 13428",
    "addr:housenumber":"102",
    "addr:postcode":"13428",
    "addr:street":"Lafayette St",
    "iso:country":"US",
    "sg:address":"102 Lafayette St",
    "sg:city":"Palatine Bridge",
    "sg:classifiers":[
        {
            "category":"Real Estate",
            "subcategory":"Real Estate Operator",
            "type":"Services"
        }
    ],
    "sg:phone":"+1 518 673 8244",
    "sg:postcode":"13428",
    "sg:province":"NY",
    "sg:tags":[
        "building",
        "apartment"
    ],
    "wof:name":"Valley View Apartments",
    "wof:placetype":"venue"
},
  "geometry": {"coordinates":[-74.56912199999999,42.922737],"type":"Point"}
}