{
  "type": "Feature",
  "properties": {
    "addr:full":"330 King Ave Bronx NY 10464",
    "addr:housenumber":"330",
    "addr:postcode":"10464",
    "addr:street":"King Ave",
    "iso:country":"US",
    "sg:address":"330 King Ave",
    "sg:city":"Bronx",
    "sg:classifiers":[
        {
            "category":"Building & Trades",
            "subcategory":"Construction",
            "type":"Services"
        }
    ],
    "sg:phone":"+1 718 885 1255",
    "sg:postcode":"10464",
    "sg:province":"NY",
    "sg:tags":[
        "wallcoverings-installation",
        "wallpaper",
        "painting",
        "contractor"
    ],
    "wof:name":"Kortleven Painting",
    "wof:placetype":"venue"
},
  "geometry": {"coordinates":[-73.784627,40.848634],"type":"Point"}
}