{
  "type": "Feature",
  "properties": {
    "addr:full":"200 E 72 St New York NY 10021",
    "addr:housenumber":"200;72",
    "addr:postcode":"10021",
    "addr:street":"E;St",
    "iso:country":"US",
    "sg:address":"200 E 72 St",
    "sg:city":"New York",
    "sg:classifiers":[
        {
            "category":"Professional",
            "subcategory":"Management & Consulting",
            "type":"Services"
        }
    ],
    "sg:phone":"+1   ",
    "sg:postcode":"10021",
    "sg:province":"NY",
    "sg:tags":[
        "resource",
        "human"
    ],
    "wof:name":"Enable Enterprises Inc",
    "wof:placetype":"venue"
},
  "geometry": {"coordinates":[-73.958527,40.768809],"type":"Point"}
}