{
  "type": "Feature",
  "properties": {
    "addr:full":"224 Beach 147th St Rockaway Park NY 11694",
    "addr:housenumber":"224",
    "addr:postcode":"11694",
    "addr:street":"Beach 147Th St",
    "iso:country":"US",
    "sg:address":"224 Beach 147th St",
    "sg:city":"Rockaway Park",
    "sg:classifiers":[
        {
            "category":"Professional",
            "subcategory":"Lawyer & Legal Services",
            "type":"Services"
        }
    ],
    "sg:phone":"+1 718 318 8805",
    "sg:postcode":"11694",
    "sg:province":"NY",
    "wof:name":"Leon Brickman Atty At Law",
    "wof:placetype":"venue"
},
  "geometry": {"coordinates":[-73.86241099999999,40.570435],"type":"Point"}
}