{
  "type": "Feature",
  "properties": {
    "addr:full":"60 E 42nd St Rm 2527 New York NY 10165",
    "addr:housenumber":"60;2527",
    "addr:postcode":"10165",
    "addr:street":"E 42Nd St",
    "iso:country":"US",
    "sg:address":"60 E 42nd St Rm 2527",
    "sg:city":"New York",
    "sg:classifiers":[
        {
            "category":"Professional",
            "subcategory":"Lawyer & Legal Services",
            "type":"Services"
        }
    ],
    "sg:phone":"+1 212 697 0024",
    "sg:postcode":"10165",
    "sg:province":"NY",
    "wof:name":"Fastenberg & Birnant",
    "wof:placetype":"venue"
},
  "geometry": {"coordinates":[-73.97930100000001,40.752102],"type":"Point"}
}