{
  "type": "Feature",
  "properties": {
    "addr:full":"110 E 55th Street New York NY 10022",
    "addr:housenumber":"110",
    "addr:postcode":"10022",
    "addr:street":"E 55Th Street",
    "iso:country":"US",
    "sg:address":"110 E 55th Street",
    "sg:city":"New York",
    "sg:classifiers":[
        {
            "category":"Shopping",
            "subcategory":"Shoes",
            "type":"Retail Goods"
        }
    ],
    "sg:phone":"+1 212 755 7372",
    "sg:postcode":"10022",
    "sg:province":"NY",
    "sg:tags":[
        "store"
    ],
    "wof:name":"Belgian Shoes",
    "wof:placetype":"venue"
},
  "geometry": {"coordinates":[-73.97108900000001,40.760024],"type":"Point"}
}