{
  "type": "Feature",
  "properties": {
    "iso:country":"US",
    "sg:address":"91 N Main St",
    "sg:city":"Liberty",
    "sg:classifiers":[
        {
            "category":"Bars & Pubs",
            "type":"Food & Drink"
        }
    ],
    "sg:phone":"+1   ",
    "sg:postcode":"12754",
    "sg:province":"NY",
    "sg:tags":[
        "drinking"
    ],
    "wof:name":"Just For You",
    "wof:placetype":"venue"
},
  "geometry": {"coordinates":[-74.74646300000001,41.800509],"type":"Point"}
}