{
  "type": "Feature",
  "properties": {
    "addr:full":"235 E 167th St Bronx NY 10456",
    "addr:housenumber":"235",
    "addr:postcode":"10456",
    "addr:street":"E 167Th St",
    "iso:country":"US",
    "sg:address":"235 E 167th St",
    "sg:city":"Bronx",
    "sg:classifiers":[
        {
            "category":"Shopping",
            "subcategory":"Pharmacy",
            "type":"Retail Goods"
        }
    ],
    "sg:phone":"+1 718 538 4754",
    "sg:postcode":"10456",
    "sg:province":"NY",
    "sg:tags":[
        "drugstore"
    ],
    "wof:name":"Stat Rx",
    "wof:placetype":"venue"
},
  "geometry": {"coordinates":[-73.91527600000001,40.833832],"type":"Point"}
}