{
  "type": "Feature",
  "properties": {
    "addr:full":"240 Main St Northport NY 11768",
    "addr:housenumber":"240",
    "addr:postcode":"11768",
    "addr:street":"Main St",
    "iso:country":"US",
    "sg:address":"240 Main St",
    "sg:city":"Northport",
    "sg:classifiers":[
        {
            "category":"Government",
            "subcategory":"Post Office",
            "type":"Public Place"
        }
    ],
    "sg:phone":"+1   ",
    "sg:postcode":"11768",
    "sg:province":"NY",
    "sg:tags":[
        "postal",
        "executive",
        "us"
    ],
    "wof:name":"US Post Office",
    "wof:placetype":"venue"
},
  "geometry": {"coordinates":[-73.347027,40.900831],"type":"Point"}
}