{
  "type": "Feature",
  "properties": {
    "iso:country":"US",
    "sg:address":"59 E River St",
    "sg:city":"Ogdensburg",
    "sg:classifiers":[
        {
            "category":"Professional",
            "subcategory":"Computer Services",
            "type":"Services"
        }
    ],
    "sg:phone":"+1 315 393 1202",
    "sg:postcode":"13669",
    "sg:province":"NY",
    "sg:tags":[
        "design",
        "system"
    ],
    "wof:name":"Linux On Line",
    "wof:placetype":"venue"
},
  "geometry": {"coordinates":[-75.494304,44.694539],"type":"Point"}
}