{
  "type": "Feature",
  "properties": {
    "addr:full":"20 Nelson Ave Staten Island NY 10308",
    "addr:housenumber":"20",
    "addr:postcode":"10308",
    "addr:street":"Nelson Ave",
    "iso:country":"US",
    "sg:address":"20 Nelson Ave",
    "sg:city":"Staten Island",
    "sg:classifiers":[
        {
            "category":"Personal",
            "subcategory":"Beauty Salon",
            "type":"Services"
        }
    ],
    "sg:phone":"+1 718 984 3230",
    "sg:postcode":"10308",
    "sg:province":"NY",
    "wof:name":"Hair & Body Plaza",
    "wof:placetype":"venue"
},
  "geometry": {"coordinates":[-74.15073099999999,40.549252],"type":"Point"}
}