{
  "type": "Feature",
  "properties": {
    "iso:country":"US",
    "sg:address":"62 Jerusalem Ave",
    "sg:city":"Hicksville",
    "sg:classifiers":[
        {
            "category":"Personal",
            "subcategory":"Barber",
            "type":"Services"
        }
    ],
    "sg:phone":"+1 516 931 8223",
    "sg:postcode":"11801",
    "sg:province":"NY",
    "wof:name":"Manya Barber Shop",
    "wof:placetype":"venue"
},
  "geometry": {"coordinates":[-73.5252,40.7663],"type":"Point"}
}