{
  "type": "Feature",
  "properties": {
    "addr:full":"1610 Brentwood Rd Bay Shore NY 11706",
    "addr:housenumber":"1610",
    "addr:postcode":"11706",
    "addr:street":"Brentwood Rd",
    "iso:country":"US",
    "sg:address":"1610 Brentwood Rd",
    "sg:city":"Bay Shore",
    "sg:classifiers":[
        {
            "category":"Shopping",
            "type":"Retail Goods"
        }
    ],
    "sg:phone":"+1 631 273 7669",
    "sg:postcode":"11706",
    "sg:province":"NY",
    "sg:tags":[
        "pet",
        "food",
        "supply"
    ],
    "wof:name":"Drew's Dog Training",
    "wof:placetype":"venue"
},
  "geometry": {"coordinates":[-73.245935,40.761354],"type":"Point"}
}