{
  "type": "Feature",
  "properties": {
    "iso:country":"US",
    "sg:address":"1935 Allison Dr",
    "sg:city":"North Bellmore",
    "sg:classifiers":[
        {
            "category":"Professional",
            "subcategory":"Accounting & Tax Preparation",
            "type":"Services"
        }
    ],
    "sg:phone":"+1 516 409 5561",
    "sg:postcode":"11710",
    "sg:province":"NY",
    "sg:tags":[
        "accountant"
    ],
    "wof:name":"Ettinger Seymour M CPA",
    "wof:placetype":"venue"
},
  "geometry": {"coordinates":[-73.530602,40.675999],"type":"Point"}
}