{
  "type": "Feature",
  "properties": {
    "addr:full":"101 Clinton St Brooklyn NY 11201",
    "addr:housenumber":"101",
    "addr:postcode":"11201",
    "addr:street":"Clinton St",
    "iso:country":"US",
    "sg:address":"101 Clinton St",
    "sg:city":"Brooklyn",
    "sg:classifiers":[
        {
            "category":"Food & Beverages",
            "subcategory":"Groceries & Convenience Stores",
            "type":"Retail Goods"
        }
    ],
    "sg:phone":"+1 718 875 8220",
    "sg:postcode":"11201",
    "sg:province":"NY",
    "sg:tags":[
        "grocer"
    ],
    "wof:name":"101 Clinton Market",
    "wof:placetype":"venue"
},
  "geometry": {"coordinates":[-73.992699,40.693401],"type":"Point"}
}