{
  "type": "Feature",
  "properties": {
    "addr:full":"6205 Buffalo Ave Niagara Falls NY 14304",
    "addr:housenumber":"6205",
    "addr:postcode":"14304",
    "addr:street":"Buffalo Ave",
    "iso:country":"US",
    "sg:address":"6205 Buffalo Ave",
    "sg:city":"Niagara Falls",
    "sg:classifiers":[
        {
            "category":"Freight",
            "type":"Transportation"
        }
    ],
    "sg:phone":"+1 716 283 4200",
    "sg:postcode":"14304",
    "sg:province":"NY",
    "wof:name":"Gavin Transportation & Sight",
    "wof:placetype":"venue"
},
  "geometry": {"coordinates":[-78.99321500000001,43.076174],"type":"Point"}
}