{
  "type": "Feature",
  "properties": {
    "iso:country":"US",
    "sg:address":"437 N Indiana Ave",
    "sg:city":"Lindenhurst",
    "sg:classifiers":[
        {
            "category":"Wholesale",
            "subcategory":"Metals & Minerals",
            "type":"Manufacturing & Wholesale Goods"
        }
    ],
    "sg:phone":"+1 631 884 6908",
    "sg:postcode":"11757",
    "sg:province":"NY",
    "sg:tags":[
        "center"
    ],
    "wof:name":"Barany Monumental Works",
    "wof:placetype":"venue"
},
  "geometry": {"coordinates":[-73.369038,40.697988],"type":"Point"}
}