{
  "type": "Feature",
  "properties": {
    "iso:country":"US",
    "sg:address":"310 Titusville Rd",
    "sg:city":"Poughkeepsie",
    "sg:classifiers":[
        {
            "category":"Restaurant",
            "type":"Food & Drink"
        }
    ],
    "sg:phone":"+1 845 483 0070",
    "sg:postcode":"12603",
    "sg:province":"NY",
    "wof:name":"Habana 50 Cafe",
    "wof:placetype":"venue"
},
  "geometry": {"coordinates":[-73.848473,41.659639],"type":"Point"}
}