{
  "type": "Feature",
  "properties": {
    "addr:full":"2894 Len Dr Bellmore NY 11710",
    "addr:housenumber":"2894",
    "addr:postcode":"11710",
    "addr:street":"Len Dr",
    "iso:country":"US",
    "sg:address":"2894 Len Dr",
    "sg:city":"Bellmore",
    "sg:classifiers":[
        {
            "category":"Retail",
            "subcategory":"Laundry & Dry Cleaning",
            "type":"Services"
        }
    ],
    "sg:phone":"+1 516 221 0931",
    "sg:postcode":"11710",
    "sg:province":"NY",
    "sg:tags":[
        "cleaners",
        "rug",
        "carpet"
    ],
    "sg:website":"www.fabracleen.com",
    "wof:name":"Rapp Furniture & Carpet Clng",
    "wof:placetype":"venue"
},
  "geometry": {"coordinates":[-73.52238199999999,40.65114],"type":"Point"}
}