{
  "type": "Feature",
  "properties": {
    "addr:full":"1591 Old Rte 22 Brewster NY 10509",
    "addr:housenumber":"1591",
    "addr:postcode":"10509",
    "addr:street":"Old Rte 22",
    "iso:country":"US",
    "sg:address":"1591 Old Rte 22",
    "sg:city":"Brewster",
    "sg:classifiers":[
        {
            "category":"Health Services",
            "subcategory":"Health Practitioner",
            "type":"Services"
        }
    ],
    "sg:phone":"+1 845 940 1050",
    "sg:postcode":"10509",
    "sg:province":"NY",
    "sg:tags":[
        "therapist",
        "physical"
    ],
    "wof:name":"Wholistic Physical Therapy",
    "wof:placetype":"venue"
},
  "geometry": {"coordinates":[-73.58202,41.461121],"type":"Point"}
}