{
  "type": "Feature",
  "properties": {
    "iso:country":"US",
    "sg:address":"178 Teakwood Ter",
    "sg:city":"Buffalo",
    "sg:classifiers":[
        {
            "category":"Retail",
            "subcategory":"Laundry & Dry Cleaning",
            "type":"Services"
        }
    ],
    "sg:phone":"+1 716 634 5145",
    "sg:postcode":"14221",
    "sg:province":"NY",
    "sg:tags":[
        "cleaners",
        "rug",
        "carpet"
    ],
    "wof:name":"Carpet Beauty Care",
    "wof:placetype":"venue"
},
  "geometry": {"coordinates":[-78.704886,42.981881],"type":"Point"}
}