{
  "type": "Feature",
  "properties": {
    "addr:full":"5355 Main St Buffalo NY 14221",
    "addr:housenumber":"5355",
    "addr:postcode":"14221",
    "addr:street":"Main St",
    "iso:country":"US",
    "sg:address":"5355 Main St",
    "sg:city":"Buffalo",
    "sg:classifiers":[
        {
            "category":"Real Estate",
            "subcategory":"Surveying",
            "type":"Services"
        }
    ],
    "sg:phone":"+1 716 631 1515",
    "sg:postcode":"14221",
    "sg:province":"NY",
    "sg:tags":[
        "surveyor"
    ],
    "wof:name":"Fenter Surveying",
    "wof:placetype":"venue"
},
  "geometry": {"coordinates":[-78.752081,42.961554],"type":"Point"}
}