{
  "type": "Feature",
  "properties": {
    "iso:country":"US",
    "sg:address":"7 Squire Ct",
    "sg:city":"Getzville",
    "sg:classifiers":[
        {
            "category":"Professional",
            "type":"Services"
        }
    ],
    "sg:phone":"+1   ",
    "sg:postcode":"14068",
    "sg:province":"NY",
    "wof:name":"Michael J Karam",
    "wof:placetype":"venue"
},
  "geometry": {"coordinates":[-78.765699,43.012784],"type":"Point"}
}