{
  "type": "Feature",
  "properties": {
    "iso:country":"US",
    "name:eng_x_preferred":[
        "Bedford - Nostrand Avs"
    ],
    "wof:name":"Bedford - Nostrand Avs",
    "wof:placetype":"venue"
},
  "geometry": {"coordinates":[-73.95352200000001,40.689627],"type":"Point"}
}