{
  "type": "Feature",
  "properties": {
    "addr:full":"225 W 34th Street New York NY 10001",
    "addr:housenumber":"225",
    "addr:postcode":"10001",
    "addr:street":"W 34Th Street",
    "iso:country":"US",
    "sg:address":"225 W 34th Street",
    "sg:city":"New York",
    "sg:classifiers":[
        {
            "category":"Professional",
            "subcategory":"Lawyer & Legal Services",
            "type":"Services"
        }
    ],
    "sg:phone":"+1 212 564 3555",
    "sg:postcode":"10001",
    "sg:province":"NY",
    "wof:name":"Kunkis Martha H",
    "wof:placetype":"venue"
},
  "geometry": {"coordinates":[-73.99109,40.751067],"type":"Point"}
}