{
  "type": "Feature",
  "properties": {
    "iso:country":"US",
    "sg:address":"572 Gramatan Ave",
    "sg:city":"Mount Vernon",
    "sg:classifiers":[
        {
            "category":"Food & Beverages",
            "subcategory":"Liquor & Beverages",
            "type":"Retail Goods"
        }
    ],
    "sg:phone":"+1   ",
    "sg:postcode":"10552",
    "sg:province":"NY",
    "sg:tags":[
        "alcoholic"
    ],
    "wof:name":"Gramatan Park Liquors Inc",
    "wof:placetype":"venue"
},
  "geometry": {"coordinates":[-73.83568099999999,40.926272],"type":"Point"}
}