{
  "type": "Feature",
  "properties": {
    "iso:country":"US",
    "sg:address":"418 Marcy St",
    "sg:city":"West Babylon",
    "sg:classifiers":[
        {
            "category":"Wholesale",
            "subcategory":"Electrical",
            "type":"Manufacturing & Wholesale Goods"
        },
        {
            "category":"Professional",
            "subcategory":"Computer Services",
            "type":"Services"
        }
    ],
    "sg:phone":"+1 631 661 2763",
    "sg:postcode":"11704",
    "sg:province":"NY",
    "sg:tags":[
        "communications",
        "design",
        "system",
        "equipment"
    ],
    "wof:name":"Kal Technologies Inc",
    "wof:placetype":"venue"
},
  "geometry": {"coordinates":[-73.342141,40.727901],"type":"Point"}
}