{
  "type": "Feature",
  "properties": {
    "addr:full":"22521 Duffy Rd Watertown NY 13601",
    "addr:housenumber":"22521",
    "addr:postcode":"13601",
    "addr:street":"Duffy Rd",
    "iso:country":"US",
    "sg:address":"22521 Duffy Rd",
    "sg:city":"Watertown",
    "sg:classifiers":[
        {
            "category":"Taxi",
            "type":"Transportation"
        }
    ],
    "sg:phone":"+1 315 779 2199",
    "sg:postcode":"13601",
    "sg:province":"NY",
    "sg:tags":[
        "taxicab"
    ],
    "wof:name":"Watertown Taxi",
    "wof:placetype":"venue"
},
  "geometry": {"coordinates":[-75.83894600000001,43.993406],"type":"Point"}
}