{
  "type": "Feature",
  "properties": {
    "iso:country":"US",
    "sg:address":"18 Gingerbread Ln",
    "sg:city":"Albany",
    "sg:classifiers":[
        {
            "category":"Building & Trades",
            "subcategory":"Electrical",
            "type":"Services"
        }
    ],
    "sg:phone":"+1 518 463 4445",
    "sg:postcode":"12208",
    "sg:province":"NY",
    "sg:tags":[
        "electrical",
        "contractor"
    ],
    "wof:name":"Henzel Electric Company Inc",
    "wof:placetype":"venue"
},
  "geometry": {"coordinates":[-73.809737,42.652868],"type":"Point"}
}