{
  "type": "Feature",
  "properties": {
    "addr:full":"173 Avenue A New York NY 10009",
    "addr:housenumber":"173",
    "addr:postcode":"10009",
    "addr:street":"Avenue A",
    "iso:country":"US",
    "sg:address":"173 Avenue A",
    "sg:city":"New York",
    "sg:classifiers":[
        {
            "category":"Restaurant",
            "type":"Food & Drink"
        }
    ],
    "sg:menulink":"http://www.allmenus.com/ny/new-york/7039-italian-bistro/menu/",
    "sg:phone":"+1 212 677 0443",
    "sg:postcode":"10009",
    "sg:province":"NY",
    "sg:tags":[
        "italian"
    ],
    "wof:name":"Italian Bistro",
    "wof:placetype":"venue"
},
  "geometry": {"coordinates":[-73.982142,40.72848],"type":"Point"}
}