{
  "type": "Feature",
  "properties": {
    "addr:full":"888 Forest Ave Staten Island NY 10310",
    "addr:housenumber":"888",
    "addr:postcode":"10310",
    "addr:street":"Forest Ave",
    "iso:country":"US",
    "sg:address":"888 Forest Ave",
    "sg:city":"Staten Island",
    "sg:classifiers":[
        {
            "category":"Building & Trades",
            "subcategory":"Electrical",
            "type":"Services"
        }
    ],
    "sg:phone":"+1 718 442 0770",
    "sg:postcode":"10310",
    "sg:province":"NY",
    "sg:tags":[
        "electrician"
    ],
    "wof:name":"Garbarino Eugene Elctrcn",
    "wof:placetype":"venue"
},
  "geometry": {"coordinates":[-74.121101,40.627998],"type":"Point"}
}