{
  "type": "Feature",
  "properties": {
    "addr:full":"2368 E 27th St Brooklyn NY 11229",
    "addr:housenumber":"2368",
    "addr:postcode":"11229",
    "addr:street":"E 27Th St",
    "iso:country":"US",
    "sg:address":"2368 E 27th St",
    "sg:city":"Brooklyn",
    "sg:classifiers":[
        {
            "category":"Manufacturing",
            "subcategory":"Tools & Machinery",
            "type":"Manufacturing & Wholesale Goods"
        }
    ],
    "sg:phone":"+1   ",
    "sg:postcode":"11229",
    "sg:province":"NY",
    "sg:tags":[
        "instrument",
        "surgical",
        "medical",
        "apparatus",
        "mfg"
    ],
    "wof:name":"W P Scientific Products Inc",
    "wof:placetype":"venue"
},
  "geometry": {"coordinates":[-73.943769,40.594946],"type":"Point"}
}