{
  "type": "Feature",
  "properties": {
    "iso:country":"US",
    "sg:address":"8647 Summit Rd",
    "sg:city":"Sauquoit",
    "sg:classifiers":[
        {
            "category":"Retail",
            "subcategory":"Auto Repair",
            "type":"Services"
        }
    ],
    "sg:phone":"+1 315 839 5051",
    "sg:postcode":"13456",
    "sg:province":"NY",
    "sg:tags":[
        "body",
        "automobile",
        "painting"
    ],
    "wof:name":"Kalies Collision",
    "wof:placetype":"venue"
},
  "geometry": {"coordinates":[-75.315877,42.961797],"type":"Point"}
}