{
  "type": "Feature",
  "properties": {
    "addr:full":"241 Monterey Ave Pelham NY 10803",
    "addr:housenumber":"241",
    "addr:postcode":"10803",
    "addr:street":"Monterey Ave",
    "iso:country":"US",
    "sg:address":"241 Monterey Ave",
    "sg:city":"Pelham",
    "sg:classifiers":[
        {
            "category":"Professional",
            "subcategory":"Lawyer & Legal Services",
            "type":"Services"
        }
    ],
    "sg:phone":"+1 914 232 9570",
    "sg:postcode":"10803",
    "sg:province":"NY",
    "sg:tags":[
        "attorney"
    ],
    "wof:name":"Richard P Donovan Attorney",
    "wof:placetype":"venue"
},
  "geometry": {"coordinates":[-73.80462199999999,40.904588],"type":"Point"}
}