{
  "type": "Feature",
  "properties": {
    "iso:country":"US",
    "sg:address":"263 W 38th St",
    "sg:city":"New York",
    "sg:classifiers":[
        {
            "category":"Shopping",
            "subcategory":"Crafts & Fabrics",
            "type":"Retail Goods"
        }
    ],
    "sg:phone":"+1 212 840 3120",
    "sg:postcode":"10018",
    "sg:province":"NY",
    "sg:tags":[
        "shop"
    ],
    "wof:name":"N Y Theatrical Supply Inc",
    "wof:placetype":"venue"
},
  "geometry": {"coordinates":[-73.990233,40.754019],"type":"Point"}
}