{
  "type": "Feature",
  "properties": {
    "iso:country":"US",
    "sg:address":"63 Sullivan St",
    "sg:city":"New York",
    "sg:classifiers":[
        {
            "category":"Professional",
            "subcategory":"Computer Services",
            "type":"Services"
        }
    ],
    "sg:phone":"+1 917 821 7023",
    "sg:postcode":"10012",
    "sg:province":"NY",
    "sg:tags":[
        "internet"
    ],
    "wof:name":"Flanagan Co",
    "wof:placetype":"venue"
},
  "geometry": {"coordinates":[-74.003491,40.724931],"type":"Point"}
}