{
  "type": "Feature",
  "properties": {
    "addr:full":"4 Midwood Pl Freeport NY 11520",
    "addr:housenumber":"4",
    "addr:postcode":"11520",
    "addr:street":"Midwood Pl",
    "iso:country":"US",
    "sg:address":"4 Midwood Pl",
    "sg:city":"Freeport",
    "sg:classifiers":[
        {
            "category":"Communications",
            "type":"Services"
        }
    ],
    "sg:phone":"+1 516 623 7733",
    "sg:postcode":"11520",
    "sg:province":"NY",
    "wof:name":"Soulsource Communications",
    "wof:placetype":"venue"
},
  "geometry": {"coordinates":[-73.593693,40.672764],"type":"Point"}
}