{
  "type": "Feature",
  "properties": {
    "addr:full":"10120 Queens Blvd Forest Hills NY 11375",
    "addr:housenumber":"10120",
    "addr:postcode":"11375",
    "addr:street":"Queens Blvd",
    "iso:country":"US",
    "sg:address":"10120 Queens Blvd",
    "sg:city":"Forest Hills",
    "sg:classifiers":[
        {
            "category":"Retail",
            "subcategory":"Auto Rental",
            "type":"Services"
        }
    ],
    "sg:phone":"+1 718 997 8700",
    "sg:postcode":"11375",
    "sg:province":"NY",
    "sg:tags":[
        "car"
    ],
    "wof:name":"Auto House",
    "wof:placetype":"venue"
},
  "geometry": {"coordinates":[-73.852648,40.726204],"type":"Point"}
}