{
  "type": "Feature",
  "properties": {
    "iso:country":"US",
    "sg:address":"5 Heritage Ln",
    "sg:city":"Somers",
    "sg:classifiers":[
        {
            "category":"Personal",
            "subcategory":"Beauty Salon",
            "type":"Services"
        }
    ],
    "sg:phone":"+1 914 669 5682",
    "sg:postcode":"10580",
    "sg:province":"NY",
    "sg:tags":[
        "manicuring"
    ],
    "wof:name":"Annie's Nails",
    "wof:placetype":"venue"
},
  "geometry": {"coordinates":[-73.675866,40.970059],"type":"Point"}
}