{
  "type": "Feature",
  "properties": {
    "iso:country":"US",
    "sg:address":"683 Washington Rd",
    "sg:city":"West Point",
    "sg:classifiers":[
        {
            "category":"Personal",
            "subcategory":"Beauty Salon",
            "type":"Services"
        }
    ],
    "sg:phone":"+1 845 446 5774",
    "sg:postcode":"10996",
    "sg:province":"NY",
    "sg:tags":[
        "shop"
    ],
    "wof:name":"Post Exch Beauty Shop",
    "wof:placetype":"venue"
},
  "geometry": {"coordinates":[-73.98206,41.399035],"type":"Point"}
}