{
  "type": "Feature",
  "properties": {
    "iso:country":"US",
    "sg:address":"701 Canton St",
    "sg:city":"Ogdensburg",
    "sg:classifiers":[
        {
            "category":"Shopping",
            "type":"Retail Goods"
        },
        {
            "category":"Shopping",
            "subcategory":"Computers & Home Electronics",
            "type":"Retail Goods"
        }
    ],
    "sg:phone":"+1 315 393 4646",
    "sg:postcode":"13669",
    "sg:province":"NY",
    "sg:tags":[
        "telephone",
        "cellular"
    ],
    "wof:name":"Radio Shack",
    "wof:placetype":"venue"
},
  "geometry": {"coordinates":[-75.479421,44.690217],"type":"Point"}
}