{
  "type": "Feature",
  "properties": {
    "iso:country":"US",
    "sg:address":"1067 Rte 25A",
    "sg:city":"Stony Brook",
    "sg:classifiers":[
        {
            "category":"Personal",
            "subcategory":"Beauty Salon",
            "type":"Services"
        }
    ],
    "sg:phone":"+1   ",
    "sg:postcode":"11790",
    "sg:province":"NY",
    "sg:tags":[
        "shop"
    ],
    "wof:name":"Calcutters Hair Salon",
    "wof:placetype":"venue"
},
  "geometry": {"coordinates":[-73.12916199999999,40.919833],"type":"Point"}
}