{
  "type": "Feature",
  "properties": {
    "addr:full":"130 Walton St Syracuse NY 13202",
    "addr:housenumber":"130",
    "addr:postcode":"13202",
    "addr:street":"Walton St",
    "iso:country":"US",
    "sg:address":"130 Walton St",
    "sg:city":"Syracuse",
    "sg:classifiers":[
        {
            "category":"Professional",
            "subcategory":"Lawyer & Legal Services",
            "type":"Services"
        }
    ],
    "sg:phone":"+1 315 474 4628",
    "sg:postcode":"13202",
    "sg:province":"NY",
    "sg:tags":[
        "attorney",
        "criminal",
        "appellate",
        "business",
        "personal",
        "practice",
        "planning",
        "real estate",
        "injury",
        "insurance",
        "law"
    ],
    "wof:name":"Wasmund Mark W",
    "wof:placetype":"venue"
},
  "geometry": {"coordinates":[-76.15416399999999,43.048006],"type":"Point"}
}