{
  "type": "Feature",
  "properties": {
    "addr:full":"3811 Broadway Astoria NY 11103",
    "addr:housenumber":"3811",
    "addr:postcode":"11103",
    "addr:street":"Broadway",
    "iso:country":"US",
    "sg:address":"3811 Broadway",
    "sg:city":"Astoria",
    "sg:classifiers":[
        {
            "category":"Professional",
            "subcategory":"Lawyer & Legal Services",
            "type":"Services"
        }
    ],
    "sg:phone":"+1 718 728 3442",
    "sg:postcode":"11103",
    "sg:province":"NY",
    "wof:name":"Giano Steve Atty",
    "wof:placetype":"venue"
},
  "geometry": {"coordinates":[-73.920097,40.759602],"type":"Point"}
}