{
  "type": "Feature",
  "properties": {
    "addr:full":"1301 Kings Hwy Brooklyn NY 11229",
    "addr:housenumber":"1301",
    "addr:postcode":"11229",
    "addr:street":"Kings Hwy",
    "iso:country":"US",
    "sg:address":"1301 Kings Hwy",
    "sg:city":"Brooklyn",
    "sg:classifiers":[
        {
            "category":"Real Estate",
            "subcategory":"Real Estate Services",
            "type":"Services"
        }
    ],
    "sg:phone":"+1 718 375 9100",
    "sg:postcode":"11229",
    "sg:province":"NY",
    "wof:name":"Rankell Associates Real Estate",
    "wof:placetype":"venue"
},
  "geometry": {"coordinates":[-73.959999,40.608101],"type":"Point"}
}