{
  "type": "Feature",
  "properties": {
    "addr:full":"1417 E 14th St Brooklyn NY 11230",
    "addr:housenumber":"1417",
    "addr:postcode":"11230",
    "addr:street":"E 14Th St",
    "iso:country":"US",
    "sg:address":"1417 E 14th St",
    "sg:city":"Brooklyn",
    "sg:classifiers":[
        {
            "category":"Retail",
            "subcategory":"Repair Shop",
            "type":"Services"
        }
    ],
    "sg:phone":"+1   ",
    "sg:postcode":"11230",
    "sg:province":"NY",
    "wof:name":"Sssz Holdings",
    "wof:placetype":"venue"
},
  "geometry": {"coordinates":[-73.959993,40.6133],"type":"Point"}
}