{
  "type": "Feature",
  "properties": {
    "addr:full":"304 Swaggertown Rd Schenectady NY 12302",
    "addr:housenumber":"304",
    "addr:postcode":"12302",
    "addr:street":"Swaggertown Rd",
    "iso:country":"US",
    "sg:address":"304 Swaggertown Rd",
    "sg:city":"Schenectady",
    "sg:classifiers":[
        {
            "category":"Organizations",
            "subcategory":"Religious Organization",
            "type":"Services"
        }
    ],
    "sg:phone":"+1 518 399 0039",
    "sg:postcode":"12302",
    "sg:province":"NY",
    "wof:name":"Believers Fellowship Center",
    "wof:placetype":"venue"
},
  "geometry": {"coordinates":[-73.950203,42.867298],"type":"Point"}
}