{
  "type": "Feature",
  "properties": {
    "iso:country":"US",
    "sg:address":"9415 Main St",
    "sg:city":"Clarence",
    "sg:classifiers":[
        {
            "category":"Restaurant",
            "type":"Food & Drink"
        }
    ],
    "sg:menulink":"http://www.allmenus.com/ny/tonawanda/245735-orazios-restaurant/menu/",
    "sg:phone":"+1 716 759 8888",
    "sg:postcode":"14031",
    "sg:province":"NY",
    "sg:tags":[
        "american",
        "diner"
    ],
    "wof:name":"Orazio's Restaurant",
    "wof:placetype":"venue"
},
  "geometry": {"coordinates":[-78.639537,42.9713],"type":"Point"}
}