{
  "type": "Feature",
  "properties": {
    "iso:country":"US",
    "sg:address":"2 S Village Ave",
    "sg:city":"Rockville Centre",
    "sg:classifiers":[
        {
            "category":"Restaurant",
            "type":"Food & Drink"
        }
    ],
    "sg:phone":"+1 516 766 7260",
    "sg:postcode":"11570",
    "sg:province":"NY",
    "sg:tags":[
        "deli",
        "grocery",
        "eating"
    ],
    "wof:name":"South Village Deli",
    "wof:placetype":"venue"
},
  "geometry": {"coordinates":[-73.64830000000001,40.655701],"type":"Point"}
}