{
  "type": "Feature",
  "properties": {
    "addr:full":"1133 Broadway New York NY 10010",
    "addr:housenumber":"1133",
    "addr:postcode":"10010",
    "addr:street":"Broadway",
    "iso:country":"US",
    "sg:address":"1133 Broadway",
    "sg:city":"New York",
    "sg:classifiers":[
        {
            "category":"Communications",
            "type":"Services"
        }
    ],
    "sg:phone":"+1 917 582 4177",
    "sg:postcode":"10010",
    "sg:province":"NY",
    "sg:tags":[
        "web",
        "design"
    ],
    "sg:website":"www.newyorkfullycustomwebsitedes...",
    "wof:name":"Fully Custom Web Design",
    "wof:placetype":"venue"
},
  "geometry": {"coordinates":[-73.98901499999999,40.743836],"type":"Point"}
}