{
  "type": "Feature",
  "properties": {
    "addr:full":"110 Croton Ave Ossining NY 10562",
    "addr:housenumber":"110",
    "addr:postcode":"10562",
    "addr:street":"Croton Ave",
    "iso:country":"US",
    "sg:address":"110 Croton Ave",
    "sg:city":"Ossining",
    "sg:classifiers":[
        {
            "category":"Retail",
            "subcategory":"Repair Shop",
            "type":"Services"
        }
    ],
    "sg:phone":"+1 914 762 4704",
    "sg:postcode":"10562",
    "sg:province":"NY",
    "sg:tags":[
        "lock",
        "locksmith"
    ],
    "wof:name":"Beasley's Lock Shop",
    "wof:placetype":"venue"
},
  "geometry": {"coordinates":[-73.854979,41.16623],"type":"Point"}
}