{
  "type": "Feature",
  "properties": {
    "addr:full":"58 Welcher Ave Peekskill NY 10566",
    "addr:housenumber":"58",
    "addr:postcode":"10566",
    "addr:street":"Welcher Ave",
    "iso:country":"US",
    "sg:address":"58 Welcher Ave",
    "sg:city":"Peekskill",
    "sg:classifiers":[
        {
            "category":"Restaurant",
            "type":"Food & Drink"
        }
    ],
    "sg:phone":"+1 845 788 4180",
    "sg:postcode":"10566",
    "sg:province":"NY",
    "wof:name":"Mio Papa",
    "wof:placetype":"venue"
},
  "geometry": {"coordinates":[-73.93073699999999,41.271012],"type":"Point"}
}