{
  "type": "Feature",
  "properties": {
    "iso:country":"US",
    "sg:address":"28 Bloomingdale Ave",
    "sg:city":"Saranac Lake",
    "sg:classifiers":[
        {
            "category":"Building & Trades",
            "subcategory":"Construction",
            "type":"Services"
        }
    ],
    "sg:phone":"+1 518 891 2150",
    "sg:postcode":"12983",
    "sg:province":"NY",
    "sg:tags":[
        "contractor"
    ],
    "wof:name":"Total Care By American",
    "wof:placetype":"venue"
},
  "geometry": {"coordinates":[-74.13088500000001,44.329712],"type":"Point"}
}