{
  "type": "Feature",
  "properties": {
    "iso:country":"US",
    "sg:address":"330 Alabama Ave",
    "sg:city":"Brooklyn",
    "sg:classifiers":[
        {
            "category":"Building & Trades",
            "subcategory":"Construction",
            "type":"Services"
        }
    ],
    "sg:phone":"+1 347 240 8592",
    "sg:postcode":"11207",
    "sg:province":"NY",
    "sg:tags":[
        "contractor"
    ],
    "wof:name":"Olympic Contracting",
    "wof:placetype":"venue"
},
  "geometry": {"coordinates":[-73.897993,40.668119],"type":"Point"}
}