{
  "type": "Feature",
  "properties": {
    "iso:country":"US",
    "sg:address":"689 Burden Ave",
    "sg:city":"Troy",
    "sg:classifiers":[
        {
            "category":"Autos & Motor Vehicles",
            "subcategory":"Automobile Sales",
            "type":"Retail Goods"
        }
    ],
    "sg:phone":"+1 518 274 3094",
    "sg:postcode":"12180",
    "sg:province":"NY",
    "sg:tags":[
        "car",
        "dealer"
    ],
    "wof:name":"JJS Auto Sales",
    "wof:placetype":"venue"
},
  "geometry": {"coordinates":[-73.697626,42.707536],"type":"Point"}
}