{
  "type": "Feature",
  "properties": {
    "iso:country":"US",
    "sg:address":"9883 W Main Rd",
    "sg:city":"Ripley",
    "sg:classifiers":[
        {
            "category":"Building & Trades",
            "subcategory":"Construction",
            "type":"Services"
        }
    ],
    "sg:phone":"+1 716 736 4934",
    "sg:postcode":"14775",
    "sg:province":"NY",
    "sg:tags":[
        "layer",
        "carpet"
    ],
    "wof:name":"Henry's Flooring Installation",
    "wof:placetype":"venue"
},
  "geometry": {"coordinates":[-79.737871,42.255351],"type":"Point"}
}