{
  "type": "Feature",
  "properties": {
    "addr:full":"445 Hamilton Ave White Plains NY 10601",
    "addr:housenumber":"445",
    "addr:postcode":"10601",
    "addr:street":"Hamilton Ave",
    "iso:country":"US",
    "sg:address":"445 Hamilton Ave",
    "sg:city":"White Plains",
    "sg:classifiers":[
        {
            "category":"Professional",
            "subcategory":"Art Services",
            "type":"Services"
        }
    ],
    "sg:phone":"+1 914 686 7780",
    "sg:postcode":"10601",
    "sg:province":"NY",
    "sg:tags":[
        "graphic",
        "designer"
    ],
    "sg:website":"www.designworksny.com",
    "wof:name":"Designworks Ny",
    "wof:placetype":"venue"
},
  "geometry": {"coordinates":[-73.76499099999999,41.035018],"type":"Point"}
}