{
  "type": "Feature",
  "properties": {
    "addr:full":"157 5th Ave Brooklyn NY 11217",
    "addr:housenumber":"157",
    "addr:postcode":"11217",
    "addr:street":"5Th Ave",
    "iso:country":"US",
    "sg:address":"157 5th Ave",
    "sg:city":"Brooklyn",
    "sg:classifiers":[
        {
            "category":"Sports & Exercise",
            "subcategory":"Gym",
            "type":"Entertainment"
        }
    ],
    "sg:phone":"+1 718 398 2100",
    "sg:postcode":"11217",
    "sg:province":"NY",
    "sg:tags":[
        "spa",
        "health",
        "day"
    ],
    "sg:website":"www.dmaiurbanspa.com",
    "wof:name":"d'mai Urban Spa",
    "wof:placetype":"venue"
},
  "geometry": {"coordinates":[-73.97930100000001,40.678001],"type":"Point"}
}