{
  "type": "Feature",
  "properties": {
    "iso:country":"US",
    "sg:address":"122 E 25th St",
    "sg:city":"New York",
    "sg:classifiers":[
        {
            "category":"Shopping",
            "subcategory":"Florist",
            "type":"Retail Goods"
        }
    ],
    "sg:phone":"+1 212 477 1037",
    "sg:postcode":"10010",
    "sg:province":"NY",
    "wof:name":"Flower You",
    "wof:placetype":"venue"
},
  "geometry": {"coordinates":[-73.9845,40.740894],"type":"Point"}
}