{
  "type": "Feature",
  "properties": {
    "addr:full":"6702 Myrtle Avenue Glendale NY 11385",
    "addr:housenumber":"6702",
    "addr:postcode":"11385",
    "addr:street":"Myrtle Avenue",
    "iso:country":"US",
    "sg:address":"6702 Myrtle Avenue",
    "sg:city":"Glendale",
    "sg:classifiers":[
        {
            "category":"Shopping",
            "subcategory":"Pharmacy",
            "type":"Retail Goods"
        }
    ],
    "sg:phone":"+1 718 821 3330",
    "sg:postcode":"11385",
    "sg:province":"NY",
    "sg:tags":[
        "drugstore"
    ],
    "wof:name":"Family Pharmacy",
    "wof:placetype":"venue"
},
  "geometry": {"coordinates":[-73.885891,40.701402],"type":"Point"}
}