{
  "type": "Feature",
  "properties": {
    "addr:full":"1941 Deer Park Ave Deer Park NY 11729",
    "addr:housenumber":"1941",
    "addr:postcode":"11729",
    "addr:street":"Deer Park Ave",
    "iso:country":"US",
    "sg:address":"1941 Deer Park Ave",
    "sg:city":"Deer Park",
    "sg:classifiers":[
        {
            "category":"Personal",
            "subcategory":"Tanning Parlor",
            "type":"Services"
        }
    ],
    "sg:phone":"+1 631 242 4656",
    "sg:postcode":"11729",
    "sg:province":"NY",
    "sg:tags":[
        "salon"
    ],
    "wof:name":"Hollywood Tans",
    "wof:placetype":"venue"
},
  "geometry": {"coordinates":[-73.32982800000001,40.762835],"type":"Point"}
}