{
  "type": "Feature",
  "properties": {
    "iso:country":"US",
    "sg:address":"250 Vesey St",
    "sg:city":"New York",
    "sg:classifiers":[
        {
            "category":"Professional",
            "type":"Services"
        }
    ],
    "sg:phone":"+1 212 786 0768",
    "sg:postcode":"10281",
    "sg:province":"NY",
    "sg:tags":[
        "establishment"
    ],
    "wof:name":"Midland Walwyn",
    "wof:placetype":"venue"
},
  "geometry": {"coordinates":[-74.01375299999999,40.71369],"type":"Point"}
}