{
  "type": "Feature",
  "properties": {
    "addr:full":"572 S 6th St Lindenhurst NY 11757",
    "addr:housenumber":"572",
    "addr:postcode":"11757",
    "addr:street":"S 6Th St",
    "iso:country":"US",
    "sg:address":"572 S 6th St",
    "sg:city":"Lindenhurst",
    "sg:classifiers":[
        {
            "category":"Marine",
            "type":"Transportation"
        }
    ],
    "sg:phone":"+1 631 226 2944",
    "sg:postcode":"11757",
    "sg:province":"NY",
    "sg:tags":[
        "transporting",
        "boat"
    ],
    "wof:name":"Bob's Boat Transfer",
    "wof:placetype":"venue"
},
  "geometry": {"coordinates":[-73.37480600000001,40.676192],"type":"Point"}
}