{
  "type": "Feature",
  "properties": {
    "addr:full":"17240 133rd Ave Apt 9C Jamaica NY 11434",
    "addr:housenumber":"17240;9c",
    "addr:postcode":"11434",
    "addr:street":"133Rd Ave Apt",
    "iso:country":"US",
    "sg:address":"17240 133rd Ave Apt 9C",
    "sg:city":"Jamaica",
    "sg:classifiers":[
        {
            "category":"Communications",
            "subcategory":"Film & Video Production",
            "type":"Services"
        }
    ],
    "sg:phone":"+1 718 641 0650",
    "sg:postcode":"11434",
    "sg:province":"NY",
    "wof:name":"Eflife Corp",
    "wof:placetype":"venue"
},
  "geometry": {"coordinates":[-73.768923,40.675579],"type":"Point"}
}