{
  "type": "Feature",
  "properties": {
    "iso:country":"US",
    "sg:address":"1108 Rutland Rd",
    "sg:city":"Brooklyn",
    "sg:classifiers":[
        {
            "category":"Restaurant",
            "type":"Food & Drink"
        }
    ],
    "sg:phone":"+1 718 774 8165",
    "sg:postcode":"11212",
    "sg:province":"NY",
    "wof:name":"Cheng Restaurant",
    "wof:placetype":"venue"
},
  "geometry": {"coordinates":[-73.92327,40.664513],"type":"Point"}
}