{
  "type": "Feature",
  "properties": {
    "addr:full":"179 New York Ave Huntington NY 11743",
    "addr:housenumber":"179",
    "addr:postcode":"11743",
    "addr:street":"New York Ave",
    "iso:country":"US",
    "sg:address":"179 New York Ave",
    "sg:city":"Huntington",
    "sg:classifiers":[
        {
            "category":"Professional",
            "subcategory":"Accounting & Tax Preparation",
            "type":"Services"
        }
    ],
    "sg:phone":"+1 631 673 1999",
    "sg:postcode":"11743",
    "sg:province":"NY",
    "sg:tags":[
        "bookkeeping",
        "general"
    ],
    "wof:name":"GES Financial & Tax Svc",
    "wof:placetype":"venue"
},
  "geometry": {"coordinates":[-73.41946900000001,40.883166],"type":"Point"}
}