{
  "type": "Feature",
  "properties": {
    "iso:country":"US",
    "sg:address":"324 Lafayette St Fl 6",
    "sg:city":"New York",
    "sg:classifiers":[
        {
            "category":"Building & Trades",
            "subcategory":"Construction",
            "type":"Services"
        }
    ],
    "sg:phone":"+1 212 625 3808",
    "sg:postcode":"10012",
    "sg:province":"NY",
    "sg:tags":[
        "interior",
        "design"
    ],
    "wof:name":"Roman And Williams",
    "wof:placetype":"venue"
},
  "geometry": {"coordinates":[-73.994896,40.725866],"type":"Point"}
}