{
  "type": "Feature",
  "properties": {
    "addr:full":"283 Bleecker St New York NY 10014",
    "addr:housenumber":"283",
    "addr:postcode":"10014",
    "addr:street":"Bleecker St",
    "iso:country":"US",
    "sg:address":"283 Bleecker St",
    "sg:city":"New York",
    "sg:classifiers":[
        {
            "category":"Shopping",
            "subcategory":"Hobbies, Toys, & Games",
            "type":"Retail Goods"
        }
    ],
    "sg:phone":"+1   ",
    "sg:postcode":"10014",
    "sg:province":"NY",
    "wof:name":"Second Childhood",
    "wof:placetype":"venue"
},
  "geometry": {"coordinates":[-74.003299,40.731743],"type":"Point"}
}