{
  "type": "Feature",
  "properties": {
    "iso:country":"US",
    "sg:address":"1331 State St",
    "sg:city":"Schenectady",
    "sg:classifiers":[
        {
            "category":"Education",
            "subcategory":"Library",
            "type":"Public Place"
        }
    ],
    "sg:phone":"+1 518 386 2242",
    "sg:postcode":"12304",
    "sg:province":"NY",
    "wof:name":"Duane Branch Library",
    "wof:placetype":"venue"
},
  "geometry": {"coordinates":[-73.92239499999999,42.796737],"type":"Point"}
}