{
  "type": "Feature",
  "properties": {
    "addr:full":"2501 Grand Concourse Bronx NY 10468",
    "addr:housenumber":"2501",
    "addr:postcode":"10468",
    "addr:street":"Grand Concourse",
    "iso:country":"US",
    "sg:address":"2501 Grand Concourse",
    "sg:city":"Bronx",
    "sg:classifiers":[
        {
            "category":"Shopping",
            "subcategory":"Clothing, Apparel, & Fashions",
            "type":"Retail Goods"
        }
    ],
    "sg:phone":"+1 718 563 5591",
    "sg:postcode":"10468",
    "sg:province":"NY",
    "sg:tags":[
        "children's",
        "clothing"
    ],
    "wof:name":"The Childrens Place",
    "wof:placetype":"venue"
},
  "geometry": {"coordinates":[-73.897408,40.862601],"type":"Point"}
}