{
  "type": "Feature",
  "properties": {
    "iso:country":"US",
    "sg:address":"5 East Rd",
    "sg:city":"Wallkill",
    "sg:classifiers":[
        {
            "category":"Autos & Motor Vehicles",
            "subcategory":"Automobile Sales",
            "type":"Retail Goods"
        },
        {
            "category":"Retail",
            "subcategory":"Auto Repair",
            "type":"Services"
        }
    ],
    "sg:phone":"+1 845 564 3420",
    "sg:postcode":"12589",
    "sg:province":"NY",
    "sg:tags":[
        "body",
        "car",
        "used",
        "wrecker",
        "shop"
    ],
    "wof:name":"Otto's Garage & Body Shop Inc",
    "wof:placetype":"venue"
},
  "geometry": {"coordinates":[-74.068563,41.591869],"type":"Point"}
}