{
  "type": "Feature",
  "properties": {
    "addr:full":"360 Hamilton Ave White Plains NY 10601",
    "addr:housenumber":"360",
    "addr:postcode":"10601",
    "addr:street":"Hamilton Ave",
    "iso:country":"US",
    "sg:address":"360 Hamilton Ave",
    "sg:city":"White Plains",
    "sg:classifiers":[
        {
            "category":"Utilities",
            "subcategory":"Telephone",
            "type":"Services"
        }
    ],
    "sg:phone":"+1 914 428 0434",
    "sg:postcode":"10601",
    "sg:province":"NY",
    "sg:tags":[
        "company"
    ],
    "wof:name":"A T & T",
    "wof:placetype":"venue"
},
  "geometry": {"coordinates":[-73.76689,41.034372],"type":"Point"}
}