{
  "type": "Feature",
  "properties": {
    "addr:full":"203 W 23rd Street New York NY 10011",
    "addr:housenumber":"203",
    "addr:postcode":"10011",
    "addr:street":"W 23Rd Street",
    "iso:country":"US",
    "sg:address":"203 W 23rd Street",
    "sg:city":"New York",
    "sg:classifiers":[
        {
            "category":"Arts & Performance",
            "subcategory":"Music",
            "type":"Entertainment"
        }
    ],
    "sg:phone":"+1 212 691 7731",
    "sg:postcode":"10011",
    "sg:province":"NY",
    "sg:tags":[
        "dj"
    ],
    "wof:name":"Lo-Fi Entertainment",
    "wof:placetype":"venue"
},
  "geometry": {"coordinates":[-73.995741,40.744038],"type":"Point"}
}