{
  "type": "Feature",
  "properties": {
    "addr:full":"7401 17th Ave Brooklyn NY 11204",
    "addr:housenumber":"7401",
    "addr:postcode":"11204",
    "addr:street":"17Th Ave",
    "iso:country":"US",
    "sg:address":"7401 17th Ave",
    "sg:city":"Brooklyn",
    "sg:classifiers":[
        {
            "category":"Professional",
            "subcategory":"Detective & Security Services",
            "type":"Services"
        }
    ],
    "sg:phone":"+1 718 331 7300",
    "sg:postcode":"11204",
    "sg:province":"NY",
    "sg:tags":[
        "guard",
        "patrol"
    ],
    "wof:name":"Sanitors Security Svc",
    "wof:placetype":"venue"
},
  "geometry": {"coordinates":[-73.998374,40.614832],"type":"Point"}
}