{
  "type": "Feature",
  "properties": {
    "iso:country":"US",
    "sg:address":"35033 Eddy Rd",
    "sg:city":"Theresa",
    "sg:classifiers":[
        {
            "category":"Real Estate",
            "subcategory":"Real Estate Operator",
            "type":"Services"
        }
    ],
    "sg:phone":"+1 315 628 5984",
    "sg:postcode":"13691",
    "sg:province":"NY",
    "sg:tags":[
        "mobile",
        "home",
        "community"
    ],
    "wof:name":"Indian River Estates",
    "wof:placetype":"venue"
},
  "geometry": {"coordinates":[-75.786435,44.174087],"type":"Point"}
}