{
  "type": "Feature",
  "properties": {
    "iso:country":"US",
    "sg:address":"42 Old Karner Rd",
    "sg:city":"Albany",
    "sg:classifiers":[
        {
            "category":"Government",
            "subcategory":"Court House",
            "type":"Public Place"
        }
    ],
    "sg:phone":"+1 518 869 4271",
    "sg:postcode":"12205",
    "sg:province":"NY",
    "wof:name":"Court Administration Centl Svc",
    "wof:placetype":"venue"
},
  "geometry": {"coordinates":[-73.85244400000001,42.727539],"type":"Point"}
}