{
  "type": "Feature",
  "properties": {
    "addr:full":"2485 University Ave Bronx NY 10468",
    "addr:housenumber":"2485",
    "addr:postcode":"10468",
    "addr:street":"University Ave",
    "iso:country":"US",
    "sg:address":"2485 University Ave",
    "sg:city":"Bronx",
    "sg:classifiers":[
        {
            "category":"Restaurant",
            "type":"Food & Drink"
        }
    ],
    "sg:phone":"+1 718 365 1500",
    "sg:postcode":"10468",
    "sg:province":"NY",
    "sg:tags":[
        "chicken",
        "pizza"
    ],
    "sg:website":"http://www.crownfriedchicken.com",
    "wof:name":"Bittu Fried Chicken & Pizza Inc",
    "wof:placetype":"venue"
},
  "geometry": {"coordinates":[-73.903531,40.864996],"type":"Point"}
}