{
  "type": "Feature",
  "properties": {
    "iso:country":"US",
    "sg:address":"3010 Westchester Ave # 305",
    "sg:city":"Purchase",
    "sg:classifiers":[
        {
            "category":"Professional",
            "subcategory":"Accounting & Tax Preparation",
            "type":"Services"
        },
        {
            "category":"Professional",
            "subcategory":"Management & Consulting",
            "type":"Services"
        }
    ],
    "sg:phone":"+1 914 251 0783",
    "sg:postcode":"10577",
    "sg:province":"NY",
    "sg:tags":[
        "planning",
        "consultant",
        "bookkeeping",
        "facility",
        "space"
    ],
    "wof:name":"Back Ofc Support Svces",
    "wof:placetype":"venue"
},
  "geometry": {"coordinates":[-73.694271,41.008431],"type":"Point"}
}