{
  "type": "Feature",
  "properties": {
    "iso:country":"US",
    "sg:address":"169 W Sunrise Hwy",
    "sg:city":"Freeport",
    "sg:classifiers":[
        {
            "category":"Autos & Motor Vehicles",
            "subcategory":"Automobile Sales",
            "type":"Retail Goods"
        }
    ],
    "sg:phone":"+1 516 378 1130",
    "sg:postcode":"11520",
    "sg:province":"NY",
    "sg:tags":[
        "new",
        "car"
    ],
    "sg:website":"http://www.contecadillac.com",
    "wof:name":"Conte Paul Cadillac Inc",
    "wof:placetype":"venue"
},
  "geometry": {"coordinates":[-73.589449,40.656289],"type":"Point"}
}