{
  "type": "Feature",
  "properties": {
    "addr:full":"3120 Niagara Falls Blvd Buffalo NY 14228",
    "addr:housenumber":"3120",
    "addr:postcode":"14228",
    "addr:street":"Niagara Falls Blvd",
    "iso:country":"US",
    "sg:address":"3120 Niagara Falls Blvd",
    "sg:city":"Buffalo",
    "sg:classifiers":[
        {
            "category":"Restaurant",
            "type":"Food & Drink"
        }
    ],
    "sg:menulink":"http://www.allmenus.com/ny/amherst/189056-mcdonalds/menu/",
    "sg:postcode":"14228",
    "sg:province":"NY",
    "sg:tags":[
        "burger",
        "american"
    ],
    "wof:name":"McDonald's",
    "wof:placetype":"venue"
},
  "geometry": {"coordinates":[-78.824138,43.039404],"type":"Point"}
}