{
  "type": "Feature",
  "properties": {
    "iso:country":"US",
    "sg:address":"310 Hallock Ave",
    "sg:city":"Port Jeffrsn Sta",
    "sg:classifiers":[
        {
            "category":"Professional",
            "subcategory":"Business Services",
            "type":"Services"
        }
    ],
    "sg:phone":"+1 631 642 8463",
    "sg:postcode":"11776",
    "sg:province":"NY",
    "wof:name":"Time Legal Svc",
    "wof:placetype":"venue"
},
  "geometry": {"coordinates":[-73.048619,40.931952],"type":"Point"}
}