{
  "type": "Feature",
  "properties": {
    "addr:full":"1 Cross Island Plz # 308 Rosedale NY 11422",
    "addr:housenumber":"1",
    "addr:postcode":"11422",
    "addr:street":"Cross Island Plz # 308",
    "iso:country":"US",
    "sg:address":"1 Cross Island Plz # 308",
    "sg:city":"Rosedale",
    "sg:classifiers":[
        {
            "category":"Transit Center",
            "subcategory":"Freight",
            "type":"Transportation"
        },
        {
            "category":"Professional",
            "subcategory":"Employment Agencies",
            "type":"Services"
        },
        {
            "category":"Professional",
            "subcategory":"Business Services",
            "type":"Services"
        }
    ],
    "sg:phone":"+1 718 481 8888",
    "sg:postcode":"11422",
    "sg:province":"NY",
    "sg:tags":[
        "cargo",
        "package",
        "consultant",
        "express",
        "broker",
        "air",
        "custom"
    ],
    "sg:website":"http://www.ftn.fedex.com",
    "wof:name":"Fedex Trade Networks Transport & Brokerage, Inc.",
    "wof:placetype":"venue"
},
  "geometry": {"coordinates":[-73.73175000000001,40.673859],"type":"Point"}
}