{
  "type": "Feature",
  "properties": {
    "addr:full":"592 E 61st St Manhattan NY 10065",
    "addr:housenumber":"592",
    "addr:postcode":"10065",
    "addr:street":"E 61St St",
    "iso:country":"US",
    "sg:address":"592 E 61st St",
    "sg:city":"Manhattan",
    "sg:classifiers":[
        {
            "category":"Personal",
            "type":"Services"
        }
    ],
    "sg:phone":"+1 866 616 1664",
    "sg:postcode":"10065",
    "sg:province":"NY",
    "sg:tags":[
        "towing"
    ],
    "sg:website":"www.59stbridgetowing.com/",
    "wof:name":"59th St Bridge Towing",
    "wof:placetype":"venue"
},
  "geometry": {"coordinates":[-73.95816600000001,40.75964],"type":"Point"}
}