{
  "type": "Feature",
  "properties": {
    "addr:full":"379 Little East Neck Rd N West Babylon NY 11704",
    "addr:housenumber":"379",
    "addr:postcode":"11704",
    "addr:street":"Little East Neck Rd N",
    "iso:country":"US",
    "sg:address":"379 Little East Neck Rd N",
    "sg:city":"West Babylon",
    "sg:classifiers":[
        {
            "category":"Shopping",
            "subcategory":"Stationery & Office Supplies",
            "type":"Retail Goods"
        }
    ],
    "sg:phone":"+1 631 587 7937",
    "sg:postcode":"11704",
    "sg:province":"NY",
    "sg:tags":[
        "stationer"
    ],
    "wof:name":"Galleria Stationery",
    "wof:placetype":"venue"
},
  "geometry": {"coordinates":[-73.343557,40.703519],"type":"Point"}
}