{
  "type": "Feature",
  "properties": {
    "addr:full":"189 9th Ave New York NY 10011",
    "addr:housenumber":"189",
    "addr:postcode":"10011",
    "addr:street":"9Th Ave",
    "iso:country":"US",
    "sg:address":"189 9th Ave",
    "sg:city":"New York",
    "sg:classifiers":[
        {
            "category":"Restaurant",
            "type":"Food & Drink"
        }
    ],
    "sg:phone":"+1 212 242 1900",
    "sg:postcode":"10011",
    "sg:province":"NY",
    "sg:tags":[
        "pakistani",
        "indian"
    ],
    "sg:website":"www.bombaytalkie.com",
    "wof:name":"Bombay Talkie",
    "wof:placetype":"venue"
},
  "geometry": {"coordinates":[-74.00225399999999,40.745562],"type":"Point"}
}