{
  "type": "Feature",
  "properties": {
    "iso:country":"US",
    "sg:address":"8 Carriage Dr",
    "sg:city":"Orchard Park",
    "sg:classifiers":[
        {
            "category":"Real Estate",
            "subcategory":"Real Estate Operator",
            "type":"Services"
        }
    ],
    "sg:phone":"+1 716 662 3517",
    "sg:postcode":"14127",
    "sg:province":"NY",
    "sg:tags":[
        "apartment"
    ],
    "wof:name":"Quaker Meadow Apartments",
    "wof:placetype":"venue"
},
  "geometry": {"coordinates":[-78.766609,42.77717],"type":"Point"}
}