{
  "type": "Feature",
  "properties": {
    "iso:country":"US",
    "sg:address":"11576 217th St",
    "sg:city":"Cambria Heights",
    "sg:classifiers":[
        {
            "category":"Professional",
            "subcategory":"Computer Services",
            "type":"Services"
        }
    ],
    "sg:phone":"+1 718 297 2107",
    "sg:postcode":"11411",
    "sg:province":"NY",
    "sg:tags":[
        "consulting",
        "it"
    ],
    "wof:name":"XYZ Business",
    "wof:placetype":"venue"
},
  "geometry": {"coordinates":[-73.74160999999999,40.698487],"type":"Point"}
}