{
  "type": "Feature",
  "properties": {
    "iso:country":"US",
    "sg:address":"1390 Clover St",
    "sg:city":"Rochester",
    "sg:classifiers":[
        {
            "category":"Health Services",
            "subcategory":"Doctor",
            "type":"Services"
        }
    ],
    "sg:phone":"+1   ",
    "sg:postcode":"14610",
    "sg:province":"NY",
    "sg:tags":[
        "dentist"
    ],
    "wof:name":"Neal Levitt",
    "wof:placetype":"venue"
},
  "geometry": {"coordinates":[-77.544135,43.13177],"type":"Point"}
}