{
  "type": "Feature",
  "properties": {
    "addr:full":"831 State Hwy 67 Ballston Spa NY 12020",
    "addr:housenumber":"831",
    "addr:postcode":"12020",
    "addr:street":"State Hwy 67",
    "iso:country":"US",
    "sg:address":"831 State Hwy 67",
    "sg:city":"Ballston Spa",
    "sg:classifiers":[
        {
            "category":"Shopping",
            "subcategory":"Clothing, Apparel, & Fashions",
            "type":"Retail Goods"
        }
    ],
    "sg:phone":"+1   ",
    "sg:postcode":"12020",
    "sg:province":"NY",
    "sg:tags":[
        "wear"
    ],
    "wof:name":"Cindys Corner",
    "wof:placetype":"venue"
},
  "geometry": {"coordinates":[-73.837744,42.972417],"type":"Point"}
}