{
  "type": "Feature",
  "properties": {
    "iso:country":"US",
    "sg:address":"100 Suffolk Rd",
    "sg:city":"Syracuse",
    "sg:classifiers":[
        {
            "category":"Restaurant",
            "type":"Food & Drink"
        }
    ],
    "sg:phone":"+1   ",
    "sg:postcode":"13219",
    "sg:province":"NY",
    "sg:tags":[
        "eating"
    ],
    "wof:name":"Katko Catering",
    "wof:placetype":"venue"
},
  "geometry": {"coordinates":[-76.255139,43.049772],"type":"Point"}
}