{
  "type": "Feature",
  "properties": {
    "iso:country":"US",
    "sg:address":"2002 Ridge Rd",
    "sg:city":"Ontario",
    "sg:classifiers":[
        {
            "category":"Restaurant",
            "type":"Food & Drink"
        }
    ],
    "sg:phone":"+1 315 524 2300",
    "sg:postcode":"14519",
    "sg:province":"NY",
    "sg:tags":[
        "pizza"
    ],
    "sg:website":"www.camsnypizza.com",
    "wof:name":"Cam's New York Pizzeria Inc",
    "wof:placetype":"venue"
},
  "geometry": {"coordinates":[-77.2843,43.221042],"type":"Point"}
}