{
  "type": "Feature",
  "properties": {
    "addr:full":"59 Kensico Dr Mount Kisco NY 10549",
    "addr:housenumber":"59",
    "addr:postcode":"10549",
    "addr:street":"Kensico Dr",
    "iso:country":"US",
    "sg:address":"59 Kensico Dr",
    "sg:city":"Mount Kisco",
    "sg:classifiers":[
        {
            "category":"Sports & Exercise",
            "subcategory":"Gym",
            "type":"Entertainment"
        }
    ],
    "sg:phone":"+1 914 244 0075",
    "sg:postcode":"10549",
    "sg:province":"NY",
    "sg:tags":[
        "trainer"
    ],
    "wof:name":"Probody",
    "wof:placetype":"venue"
},
  "geometry": {"coordinates":[-73.723073,41.219776],"type":"Point"}
}