{
  "type": "Feature",
  "properties": {
    "addr:full":"7414 Palmcrest Rd Syracuse NY 13212",
    "addr:housenumber":"7414",
    "addr:postcode":"13212",
    "addr:street":"Palmcrest Rd",
    "iso:country":"US",
    "sg:address":"7414 Palmcrest Rd",
    "sg:city":"Syracuse",
    "sg:classifiers":[
        {
            "category":"Building & Trades",
            "subcategory":"Construction",
            "type":"Services"
        }
    ],
    "sg:phone":"+1 315 623 9902",
    "sg:postcode":"13212",
    "sg:province":"NY",
    "sg:tags":[
        "carpenter"
    ],
    "wof:name":"Targa Enterprise",
    "wof:placetype":"venue"
},
  "geometry": {"coordinates":[-76.10232499999999,43.126335],"type":"Point"}
}