{
  "type": "Feature",
  "properties": {
    "addr:full":"797 Pennsylvania Ave Brooklyn NY 11207",
    "addr:housenumber":"797",
    "addr:postcode":"11207",
    "addr:street":"Pennsylvania Ave",
    "iso:country":"US",
    "sg:address":"797 Pennsylvania Ave",
    "sg:city":"Brooklyn",
    "sg:classifiers":[
        {
            "category":"Retail",
            "subcategory":"Car Wash",
            "type":"Services"
        }
    ],
    "sg:phone":"+1 718 649 0400",
    "sg:postcode":"11207",
    "sg:province":"NY",
    "sg:tags":[
        "polishing",
        "washing"
    ],
    "wof:name":"Buddy's Carwash",
    "wof:placetype":"venue"
},
  "geometry": {"coordinates":[-73.889523,40.657317],"type":"Point"}
}