{
  "type": "Feature",
  "properties": {
    "addr:full":"7 Diane Dr Otego NY 13825",
    "addr:housenumber":"7",
    "addr:postcode":"13825",
    "addr:street":"Diane Dr",
    "iso:country":"US",
    "sg:address":"7 Diane Dr",
    "sg:city":"Otego",
    "sg:classifiers":[
        {
            "category":"Building & Trades",
            "subcategory":"Construction",
            "type":"Services"
        }
    ],
    "sg:phone":"+1 607 988 7898",
    "sg:postcode":"13825",
    "sg:province":"NY",
    "sg:tags":[
        "carpentry",
        "contractor"
    ],
    "wof:name":"Shultis Carpentry",
    "wof:placetype":"venue"
},
  "geometry": {"coordinates":[-75.193815,42.384538],"type":"Point"}
}