{
  "type": "Feature",
  "properties": {
    "addr:full":"7910 3rd Ave Brooklyn NY 11209",
    "addr:housenumber":"7910",
    "addr:postcode":"11209",
    "addr:street":"3Rd Ave",
    "iso:country":"US",
    "sg:address":"7910 3rd Ave",
    "sg:city":"Brooklyn",
    "sg:classifiers":[
        {
            "category":"Real Estate",
            "subcategory":"Real Estate Agent",
            "type":"Services"
        }
    ],
    "sg:phone":"+1 718 748 2400",
    "sg:postcode":"11209",
    "sg:province":"NY",
    "sg:website":"www.lechaimrealty.com",
    "wof:name":"Le Chaim Realty",
    "wof:placetype":"venue"
},
  "geometry": {"coordinates":[-74.029297,40.628201],"type":"Point"}
}