{
  "type": "Feature",
  "properties": {
    "addr:full":"105 Rte 9a Ossining NY 10562",
    "addr:housenumber":"105",
    "addr:postcode":"10562",
    "addr:street":"Rte 9A",
    "iso:country":"US",
    "sg:address":"105 Rte 9a",
    "sg:city":"Ossining",
    "sg:classifiers":[
        {
            "category":"Building & Trades",
            "subcategory":"Landscaping Services",
            "type":"Services"
        }
    ],
    "sg:phone":"+1 914 923 3454",
    "sg:postcode":"10562",
    "sg:province":"NY",
    "sg:tags":[
        "landscape"
    ],
    "wof:name":"Chongs Oriental Landscaping",
    "wof:placetype":"venue"
},
  "geometry": {"coordinates":[-73.840174,41.173808],"type":"Point"}
}