{
  "type": "Feature",
  "properties": {
    "addr:full":"1671 Macombs Road Bronx NY 10453",
    "addr:housenumber":"1671",
    "addr:postcode":"10453",
    "addr:street":"Macombs Road",
    "iso:country":"US",
    "sg:address":"1671 Macombs Road",
    "sg:city":"Bronx",
    "sg:classifiers":[
        {
            "category":"Food & Beverages",
            "subcategory":"Groceries & Convenience Stores",
            "type":"Retail Goods"
        }
    ],
    "sg:phone":"+1 718 299 3224",
    "sg:postcode":"10453",
    "sg:province":"NY",
    "wof:name":"1671 Macombs Deli & Grocery",
    "wof:placetype":"venue"
},
  "geometry": {"coordinates":[-73.916321,40.848124],"type":"Point"}
}