{
  "type": "Feature",
  "properties": {
    "addr:full":"532 Bedford Road Bedford Hills NY 10507",
    "addr:housenumber":"532",
    "addr:postcode":"10507",
    "addr:street":"Bedford Road",
    "iso:country":"US",
    "sg:address":"532 Bedford Road",
    "sg:city":"Bedford Hills",
    "sg:classifiers":[
        {
            "category":"Insurance",
            "subcategory":"Hazard Insurance",
            "type":"Services"
        }
    ],
    "sg:phone":"+1 914 241 2990",
    "sg:postcode":"10507",
    "sg:province":"NY",
    "sg:website":"www.sampoliti.com/",
    "wof:name":"Samantha Politi, State Farm Insurance",
    "wof:placetype":"venue"
},
  "geometry": {"coordinates":[-73.709222,41.229358],"type":"Point"}
}