{
  "type": "Feature",
  "properties": {
    "addr:full":"740 Flatbush Ave Brooklyn NY 11226",
    "addr:housenumber":"740",
    "addr:postcode":"11226",
    "addr:street":"Flatbush Ave",
    "iso:country":"US",
    "sg:address":"740 Flatbush Ave",
    "sg:city":"Brooklyn",
    "sg:classifiers":[
        {
            "category":"Shopping",
            "subcategory":"Department Store",
            "type":"Retail Goods"
        }
    ],
    "sg:phone":"+1 718 282 3222",
    "sg:postcode":"11226",
    "sg:province":"NY",
    "sg:tags":[
        "shop"
    ],
    "wof:name":"Seven Brothers Corp",
    "wof:placetype":"venue"
},
  "geometry": {"coordinates":[-73.959451,40.653575],"type":"Point"}
}