{
  "type": "Feature",
  "properties": {
    "addr:full":"108 E Smith St Herkimer NY 13350",
    "addr:housenumber":"108",
    "addr:postcode":"13350",
    "addr:street":"E Smith St",
    "iso:country":"US",
    "sg:address":"108 E Smith St",
    "sg:city":"Herkimer",
    "sg:classifiers":[
        {
            "category":"Shopping",
            "subcategory":"Florist",
            "type":"Retail Goods"
        }
    ],
    "sg:phone":"+1   ",
    "sg:postcode":"13350",
    "sg:province":"NY",
    "wof:name":"J N S Flowers & Ballons",
    "wof:placetype":"venue"
},
  "geometry": {"coordinates":[-74.982781,43.02347],"type":"Point"}
}