{
  "type": "Feature",
  "properties": {
    "addr:full":"500 Helendale Rd Ste 155 Rochester NY 14609",
    "addr:housenumber":"500",
    "addr:postcode":"14609",
    "addr:street":"Helendale Rd Ste 155",
    "iso:country":"US",
    "sg:address":"500 Helendale Rd Ste 155",
    "sg:city":"Rochester",
    "sg:classifiers":[
        {
            "category":"Health Services",
            "subcategory":"Doctor",
            "type":"Services"
        }
    ],
    "sg:phone":"+1 585 748 3772",
    "sg:postcode":"14609",
    "sg:province":"NY",
    "sg:tags":[
        "psychiatry",
        "physician",
        "surgeon",
        "surgeons"
    ],
    "wof:name":"Robin J Sturm",
    "wof:placetype":"venue"
},
  "geometry": {"coordinates":[-77.54512,43.180168],"type":"Point"}
}