{
  "type": "Feature",
  "properties": {
    "addr:full":"4261 Broadway New York NY 10033",
    "addr:housenumber":"4261",
    "addr:postcode":"10033",
    "addr:street":"Broadway",
    "iso:country":"US",
    "sg:address":"4261 Broadway",
    "sg:city":"New York",
    "sg:classifiers":[
        {
            "category":"Insurance",
            "subcategory":"Health Insurance",
            "type":"Services"
        }
    ],
    "sg:phone":"+1 212 927 9064",
    "sg:postcode":"10033",
    "sg:province":"NY",
    "sg:tags":[
        "market"
    ],
    "wof:name":"GNC",
    "wof:placetype":"venue"
},
  "geometry": {"coordinates":[-73.935873,40.850228],"type":"Point"}
}