{
  "type": "Feature",
  "properties": {
    "addr:full":"256 State Hwy 100 Somers NY 10589",
    "addr:housenumber":"256",
    "addr:postcode":"10589",
    "addr:street":"State Hwy 100",
    "iso:country":"US",
    "sg:address":"256 State Hwy 100",
    "sg:city":"Somers",
    "sg:classifiers":[
        {
            "category":"Personal",
            "subcategory":"Beauty Salon",
            "type":"Services"
        }
    ],
    "sg:phone":"+1 914 232 7070",
    "sg:postcode":"10589",
    "sg:province":"NY",
    "wof:name":"Hair By Lisa & Co",
    "wof:placetype":"venue"
},
  "geometry": {"coordinates":[-73.699766,41.3018],"type":"Point"}
}