{
  "type": "Feature",
  "properties": {
    "addr:full":"269 Skillen St Buffalo NY 14207",
    "addr:housenumber":"269",
    "addr:postcode":"14207",
    "addr:street":"Skillen St",
    "iso:country":"US",
    "sg:address":"269 Skillen St",
    "sg:city":"Buffalo",
    "sg:classifiers":[
        {
            "category":"Organizations",
            "subcategory":"Religious Organization",
            "type":"Services"
        },
        {
            "category":"Education",
            "subcategory":"School",
            "type":"Public Place"
        }
    ],
    "sg:phone":"+1 716 876 1787",
    "sg:postcode":"14207",
    "sg:province":"NY",
    "sg:tags":[
        "elementary",
        "church"
    ],
    "wof:name":"Nazareth Lutheran Church Schl",
    "wof:placetype":"venue"
},
  "geometry": {"coordinates":[-78.896856,42.96014],"type":"Point"}
}