{
  "type": "Feature",
  "properties": {
    "addr:full":"828 Carman Ave Westbury NY 11590",
    "addr:housenumber":"828",
    "addr:postcode":"11590",
    "addr:street":"Carman Ave",
    "iso:country":"US",
    "sg:address":"828 Carman Ave",
    "sg:city":"Westbury",
    "sg:classifiers":[
        {
            "category":"Retail",
            "subcategory":"Self-service Laundry",
            "type":"Services"
        }
    ],
    "sg:phone":"+1   ",
    "sg:postcode":"11590",
    "sg:province":"NY",
    "sg:tags":[
        "coin"
    ],
    "wof:name":"Everyday Laundry",
    "wof:placetype":"venue"
},
  "geometry": {"coordinates":[-73.552419,40.748264],"type":"Point"}
}