{
  "type": "Feature",
  "properties": {
    "iso:country":"US",
    "sg:address":"406 Connecticut St",
    "sg:city":"Buffalo",
    "sg:classifiers":[
        {
            "category":"Building & Trades",
            "subcategory":"Pest Control",
            "type":"Services"
        }
    ],
    "sg:phone":"+1 716 886 1371",
    "sg:postcode":"14213",
    "sg:province":"NY",
    "wof:name":"Control Ashland Pest",
    "wof:placetype":"venue"
},
  "geometry": {"coordinates":[-78.88629899999999,42.906502],"type":"Point"}
}