{
  "type": "Feature",
  "properties": {
    "iso:country":"US",
    "sg:address":"621 W Hoffman Ave",
    "sg:city":"Lindenhurst",
    "sg:classifiers":[
        {
            "category":"Restaurant",
            "type":"Food & Drink"
        }
    ],
    "sg:phone":"+1 631 225 0653",
    "sg:postcode":"11757",
    "sg:province":"NY",
    "sg:tags":[
        "shop",
        "coffee"
    ],
    "wof:name":"Nick's Coffee Shop",
    "wof:placetype":"venue"
},
  "geometry": {"coordinates":[-73.386949,40.682753],"type":"Point"}
}