{
  "type": "Feature",
  "properties": {
    "addr:full":"2096 College Ave Elmira Heights NY 14903",
    "addr:housenumber":"2096",
    "addr:postcode":"14903",
    "addr:street":"College Ave Elmira",
    "iso:country":"US",
    "sg:address":"2096 College Ave",
    "sg:city":"Elmira Heights",
    "sg:classifiers":[
        {
            "category":"Personal",
            "subcategory":"Beauty Salon",
            "type":"Services"
        }
    ],
    "sg:phone":"+1 607 732 1907",
    "sg:postcode":"14903",
    "sg:province":"NY",
    "wof:name":"Angela's Hair Salon",
    "wof:placetype":"venue"
},
  "geometry": {"coordinates":[-76.82387300000001,42.121485],"type":"Point"}
}