{
  "type": "Feature",
  "properties": {
    "iso:country":"US",
    "sg:address":"3 Barter Ln",
    "sg:city":"Hicksville",
    "sg:classifiers":[
        {
            "category":"Real Estate",
            "subcategory":"Real Estate Agent",
            "type":"Services"
        }
    ],
    "sg:phone":"+1 516 681 4582",
    "sg:postcode":"11801",
    "sg:province":"NY",
    "wof:name":"Sonam Realty Inc",
    "wof:placetype":"venue"
},
  "geometry": {"coordinates":[-73.534267,40.745278],"type":"Point"}
}