{
  "type": "Feature",
  "properties": {
    "addr:full":"1805 Harbor View Rd Sylvan Beach NY 13157",
    "addr:housenumber":"1805",
    "addr:postcode":"13157",
    "addr:street":"Harbor View Rd",
    "iso:country":"US",
    "sg:address":"1805 Harbor View Rd",
    "sg:city":"Sylvan Beach",
    "sg:classifiers":[
        {
            "category":"Professional",
            "subcategory":"Management & Consulting",
            "type":"Services"
        }
    ],
    "sg:phone":"+1 315 762 4324",
    "sg:postcode":"13157",
    "sg:province":"NY",
    "sg:tags":[
        "executive",
        "public",
        "relations"
    ],
    "wof:name":"Sylvan Beach Village Street De",
    "wof:placetype":"venue"
},
  "geometry": {"coordinates":[-75.719498,43.206956],"type":"Point"}
}