{
  "type": "Feature",
  "properties": {
    "iso:country":"US",
    "sg:address":"34 Bedell St",
    "sg:city":"Freeport",
    "sg:classifiers":[
        {
            "category":"Home & Garden",
            "subcategory":"Garden Supply",
            "type":"Retail Goods"
        }
    ],
    "sg:phone":"+1 516 377 8311",
    "sg:postcode":"11520",
    "sg:province":"NY",
    "sg:tags":[
        "sprinkler"
    ],
    "wof:name":"J & A Irrigation Specialists",
    "wof:placetype":"venue"
},
  "geometry": {"coordinates":[-73.578624,40.652386],"type":"Point"}
}