{
  "type": "Feature",
  "properties": {
    "iso:country":"US",
    "sg:address":"6 Durant Rd",
    "sg:city":"New City",
    "sg:classifiers":[
        {
            "category":"Home & Garden",
            "subcategory":"Carpets & Floor Coverings",
            "type":"Retail Goods"
        }
    ],
    "sg:phone":"+1   ",
    "sg:postcode":"10956",
    "sg:province":"NY",
    "wof:name":"Roca Carpet",
    "wof:placetype":"venue"
},
  "geometry": {"coordinates":[-73.98928600000001,41.135185],"type":"Point"}
}