{
  "type": "Feature",
  "properties": {
    "addr:full":"180 Lexington Ave New York NY 10016",
    "addr:housenumber":"180",
    "addr:postcode":"10016",
    "addr:street":"Lexington Ave",
    "iso:country":"US",
    "sg:address":"180 Lexington Ave",
    "sg:city":"New York",
    "sg:classifiers":[
        {
            "category":"Professional",
            "subcategory":"Employment Agencies",
            "type":"Services"
        }
    ],
    "sg:phone":"+1 212 551 1115",
    "sg:postcode":"10016",
    "sg:province":"NY",
    "sg:tags":[
        "recruiter",
        "executive"
    ],
    "wof:name":"Tennyson Advisors Inc",
    "wof:placetype":"venue"
},
  "geometry": {"coordinates":[-73.980659,40.745115],"type":"Point"}
}