{
  "type": "Feature",
  "properties": {
    "iso:country":"US",
    "sg:address":"42 Saratoga Ave",
    "sg:city":"Waterford",
    "sg:classifiers":[
        {
            "category":"Home & Garden",
            "subcategory":"Hardware",
            "type":"Retail Goods"
        }
    ],
    "sg:phone":"+1 518 233 1073",
    "sg:postcode":"12188",
    "sg:province":"NY",
    "wof:name":"Phillips Hardware",
    "wof:placetype":"venue"
},
  "geometry": {"coordinates":[-73.694953,42.784738],"type":"Point"}
}