{
  "type": "Feature",
  "properties": {
    "iso:country":"US",
    "sg:address":"120 Riverdale Dr",
    "sg:city":"Syracuse",
    "sg:classifiers":[
        {
            "category":"Professional",
            "subcategory":"Lawyer & Legal Services",
            "type":"Services"
        }
    ],
    "sg:phone":"+1 315 469 3831",
    "sg:postcode":"13207",
    "sg:province":"NY",
    "sg:tags":[
        "paralegal"
    ],
    "wof:name":"P.P.S. Paralegal/Personal Services Inc.",
    "wof:placetype":"venue"
},
  "geometry": {"coordinates":[-76.155051,43.001534],"type":"Point"}
}