{
  "type": "Feature",
  "properties": {
    "addr:full":"321 E 75 St New York NY 10021",
    "addr:housenumber":"321;75",
    "addr:postcode":"10021",
    "addr:street":"E;St",
    "iso:country":"US",
    "sg:address":"321 E 75 St",
    "sg:city":"New York",
    "sg:classifiers":[
        {
            "category":"Shopping",
            "subcategory":"Clothing, Apparel, & Fashions",
            "type":"Retail Goods"
        }
    ],
    "sg:phone":"+1 212 717 2559",
    "sg:postcode":"10021",
    "sg:province":"NY",
    "sg:tags":[
        "baby",
        "accessory"
    ],
    "wof:name":"Laura Beth's Baby Collection",
    "wof:placetype":"venue"
},
  "geometry": {"coordinates":[-73.954903,40.770024],"type":"Point"}
}