{
  "type": "Feature",
  "properties": {
    "iso:country":"US",
    "sg:address":"309 W Morris St",
    "sg:city":"Bath",
    "sg:classifiers":[
        {
            "category":"Food & Beverages",
            "subcategory":"Groceries & Convenience Stores",
            "type":"Retail Goods"
        }
    ],
    "sg:phone":"+1 607 776 1282",
    "sg:postcode":"14810",
    "sg:province":"NY",
    "sg:tags":[
        "grocer"
    ],
    "sg:website":"www.topsmarkets.com",
    "wof:name":"Tops Friendly Markets 539",
    "wof:placetype":"venue"
},
  "geometry": {"coordinates":[-77.331706,42.337092],"type":"Point"}
}