{
  "type": "Feature",
  "properties": {
    "addr:full":"63-30 Roosevelt Ave Woodside NY 11377",
    "addr:housenumber":"63-30",
    "addr:postcode":"11377",
    "addr:street":"Roosevelt Ave",
    "iso:country":"US",
    "sg:address":"63-30 Roosevelt Ave",
    "sg:city":"Woodside",
    "sg:classifiers":[
        {
            "category":"Personal",
            "subcategory":"Beauty Salon",
            "type":"Services"
        }
    ],
    "sg:phone":"+1 718 898 0333",
    "sg:postcode":"11377",
    "sg:province":"NY",
    "sg:tags":[
        "hair"
    ],
    "sg:website":"www.hairprocharming.com",
    "wof:name":"Hair Pro Charming",
    "wof:placetype":"venue"
},
  "geometry": {"coordinates":[-73.900774,40.745863],"type":"Point"}
}