{
  "type": "Feature",
  "properties": {
    "iso:country":"US",
    "sg:address":"482 Kings Hwy",
    "sg:city":"Valley Cottage",
    "sg:classifiers":[
        {
            "category":"Personal",
            "subcategory":"Tanning Parlor",
            "type":"Services"
        }
    ],
    "sg:phone":"+1 845 268 0218",
    "sg:postcode":"10989",
    "sg:province":"NY",
    "sg:tags":[
        "salon"
    ],
    "wof:name":"Celebrity Tans",
    "wof:placetype":"venue"
},
  "geometry": {"coordinates":[-73.9496,41.119149],"type":"Point"}
}