{
  "type": "Feature",
  "properties": {
    "iso:country":"US",
    "sg:address":"127 E Broadway",
    "sg:city":"Fulton",
    "sg:classifiers":[
        {
            "category":"Organizations",
            "subcategory":"Community Association",
            "type":"Services"
        }
    ],
    "sg:phone":"+1 315 598 3121",
    "sg:postcode":"13069",
    "sg:province":"NY",
    "sg:tags":[
        "club"
    ],
    "wof:name":"Recreational Club Inc",
    "wof:placetype":"venue"
},
  "geometry": {"coordinates":[-76.412747,43.318202],"type":"Point"}
}