{
  "type": "Feature",
  "properties": {
    "addr:full":"8811 101st Ave Ozone Park NY 11416",
    "addr:housenumber":"8811",
    "addr:postcode":"11416",
    "addr:street":"101St Ave",
    "iso:country":"US",
    "sg:address":"8811 101st Ave",
    "sg:city":"Ozone Park",
    "sg:classifiers":[
        {
            "category":"Deli",
            "type":"Food & Drink"
        }
    ],
    "sg:phone":"+1 718 323 4545",
    "sg:postcode":"11416",
    "sg:province":"NY",
    "wof:name":"Andy's Grocery",
    "wof:placetype":"venue"
},
  "geometry": {"coordinates":[-73.851601,40.6828],"type":"Point"}
}