{
  "type": "Feature",
  "properties": {
    "addr:full":"24 State Hwy 96 Owego NY 13827",
    "addr:housenumber":"24",
    "addr:postcode":"13827",
    "addr:street":"State Hwy 96",
    "iso:country":"US",
    "sg:address":"24 State Hwy 96",
    "sg:city":"Owego",
    "sg:classifiers":[
        {
            "category":"Real Estate",
            "subcategory":"Surveying",
            "type":"Services"
        }
    ],
    "sg:phone":"+1 607 687 8953",
    "sg:postcode":"13827",
    "sg:province":"NY",
    "sg:tags":[
        "surveyor"
    ],
    "wof:name":"Williams & Edsall Land",
    "wof:placetype":"venue"
},
  "geometry": {"coordinates":[-76.263046,42.104597],"type":"Point"}
}