{
  "type": "Feature",
  "properties": {
    "iso:country":"US",
    "sg:address":"1124 Wilmot Rd",
    "sg:city":"Scarsdale",
    "sg:classifiers":[
        {
            "category":"Personal",
            "subcategory":"Beauty Salon",
            "type":"Services"
        }
    ],
    "sg:phone":"+1   ",
    "sg:postcode":"10583",
    "sg:province":"NY",
    "sg:tags":[
        "shop",
        "clothing"
    ],
    "wof:name":"Leahs Beauty Center",
    "wof:placetype":"venue"
},
  "geometry": {"coordinates":[-73.776943,40.983881],"type":"Point"}
}