{
  "type": "Feature",
  "properties": {
    "addr:full":"79 Bayview Ave Port Washington NY 11050",
    "addr:housenumber":"79",
    "addr:postcode":"11050",
    "addr:street":"Bayview Ave",
    "iso:country":"US",
    "sg:address":"79 Bayview Ave",
    "sg:city":"Port Washington",
    "sg:classifiers":[
        {
            "category":"Wholesale",
            "subcategory":"Electrical",
            "type":"Manufacturing & Wholesale Goods"
        }
    ],
    "sg:phone":"+1 516 944 0061",
    "sg:postcode":"11050",
    "sg:province":"NY",
    "sg:tags":[
        "generator"
    ],
    "sg:website":"www.northshorehomepower.com",
    "wof:name":"North Shore Homepower Inc",
    "wof:placetype":"venue"
},
  "geometry": {"coordinates":[-73.69042399999999,40.827971],"type":"Point"}
}