{
  "type": "Feature",
  "properties": {
    "iso:country":"US",
    "sg:address":"60 Madison Ave",
    "sg:city":"New York",
    "sg:classifiers":[
        {
            "category":"Real Estate",
            "subcategory":"Real Estate Agent",
            "type":"Services"
        }
    ],
    "sg:phone":"+1 212 779 8111",
    "sg:postcode":"10010",
    "sg:province":"NY",
    "sg:tags":[
        "manages",
        "industrial"
    ],
    "wof:name":"APC Capital Partners",
    "wof:placetype":"venue"
},
  "geometry": {"coordinates":[-73.986597,40.742771],"type":"Point"}
}