{
  "type": "Feature",
  "properties": {
    "iso:country":"US",
    "sg:address":"214 E Lincoln Ave",
    "sg:city":"Mount Vernon",
    "sg:classifiers":[
        {
            "category":"Education",
            "subcategory":"School",
            "type":"Public Place"
        }
    ],
    "sg:phone":"+1   ",
    "sg:postcode":"10552",
    "sg:province":"NY",
    "sg:tags":[
        "organization",
        "religious"
    ],
    "wof:name":"St Ursula School",
    "wof:placetype":"venue"
},
  "geometry": {"coordinates":[-73.832121,40.917928],"type":"Point"}
}