{
  "type": "Feature",
  "properties": {
    "iso:country":"US",
    "sg:address":"532 Neptune Ave",
    "sg:city":"Brooklyn",
    "sg:classifiers":[
        {
            "category":"Health Services",
            "subcategory":"Doctor",
            "type":"Services"
        }
    ],
    "sg:phone":"+1 718 449 8860",
    "sg:postcode":"11224",
    "sg:province":"NY",
    "wof:name":"Plaza Medical Assoc",
    "wof:placetype":"venue"
},
  "geometry": {"coordinates":[-73.974701,40.579899],"type":"Point"}
}