{
  "type": "Feature",
  "properties": {
    "iso:country":"US",
    "sg:address":"1183 Hertel Ave",
    "sg:city":"Buffalo",
    "sg:classifiers":[
        {
            "category":"Retail",
            "subcategory":"Laundry & Dry Cleaning",
            "type":"Services"
        }
    ],
    "sg:phone":"+1   ",
    "sg:postcode":"14216",
    "sg:province":"NY",
    "sg:tags":[
        "drycleaning",
        "plant"
    ],
    "wof:name":"Custom Cleaners",
    "wof:placetype":"venue"
},
  "geometry": {"coordinates":[-78.86456699999999,42.947761],"type":"Point"}
}