{
  "type": "Feature",
  "properties": {
    "addr:full":"96 Bieselin Rd Bellport NY 11713",
    "addr:housenumber":"96",
    "addr:postcode":"11713",
    "addr:street":"Bieselin Rd",
    "iso:country":"US",
    "sg:address":"96 Bieselin Rd",
    "sg:city":"Bellport",
    "sg:classifiers":[
        {
            "category":"Organizations",
            "subcategory":"Community Association",
            "type":"Services"
        }
    ],
    "sg:phone":"+1 631 286 9009",
    "sg:postcode":"11713",
    "sg:province":"NY",
    "wof:name":"Interntional Order Rainbow Grl",
    "wof:placetype":"venue"
},
  "geometry": {"coordinates":[-72.950256,40.764573],"type":"Point"}
}