{
  "type": "Feature",
  "properties": {
    "addr:full":"143 7th Ave S New York NY 10014",
    "addr:housenumber":"143",
    "addr:postcode":"10014",
    "addr:street":"7Th Ave S",
    "iso:country":"US",
    "sg:address":"143 7th Ave S",
    "sg:city":"New York",
    "sg:classifiers":[
        {
            "category":"Shopping",
            "subcategory":"Clothing, Apparel, & Fashions",
            "type":"Retail Goods"
        }
    ],
    "sg:phone":"+1 212 633 6867",
    "sg:postcode":"10014",
    "sg:province":"NY",
    "sg:tags":[
        "men's",
        "clothing"
    ],
    "sg:website":"www.johnbartlettny.com",
    "wof:name":"John Bartlett Men's Wear",
    "wof:placetype":"venue"
},
  "geometry": {"coordinates":[-73.974209,40.676277],"type":"Point"}
}