{
  "type": "Feature",
  "properties": {
    "addr:full":"66 Meadowbrook Rd Orchard Park NY 14127",
    "addr:housenumber":"66",
    "addr:postcode":"14127",
    "addr:street":"Meadowbrook Rd",
    "iso:country":"US",
    "sg:address":"66 Meadowbrook Rd",
    "sg:city":"Orchard Park",
    "sg:classifiers":[
        {
            "category":"Health Services",
            "subcategory":"Medical Lab",
            "type":"Services"
        }
    ],
    "sg:phone":"+1   ",
    "sg:postcode":"14127",
    "sg:province":"NY",
    "sg:tags":[
        "laboratory",
        "dental"
    ],
    "wof:name":"Wagner Dental Lab",
    "wof:placetype":"venue"
},
  "geometry": {"coordinates":[-78.73589200000001,42.76121],"type":"Point"}
}