{
  "type": "Feature",
  "properties": {
    "addr:full":"12 Madison Ave Endicott NY 13760",
    "addr:housenumber":"12",
    "addr:postcode":"13760",
    "addr:street":"Madison Ave",
    "iso:country":"US",
    "sg:address":"12 Madison Ave",
    "sg:city":"Endicott",
    "sg:classifiers":[
        {
            "category":"Banks & Credit Unions",
            "subcategory":"Bank",
            "type":"Services"
        }
    ],
    "sg:phone":"+1 607 754 9872",
    "sg:postcode":"13760",
    "sg:province":"NY",
    "wof:name":"Citizens Bank",
    "wof:placetype":"venue"
},
  "geometry": {"coordinates":[-76.04944399999999,42.10264],"type":"Point"}
}