{
  "type": "Feature",
  "properties": {
    "addr:full":"87 E 233rd St Bronx NY 10470",
    "addr:housenumber":"87",
    "addr:postcode":"10470",
    "addr:street":"E 233Rd St",
    "iso:country":"US",
    "sg:address":"87 E 233rd St",
    "sg:city":"Bronx",
    "sg:classifiers":[
        {
            "category":"Building & Trades",
            "subcategory":"Construction",
            "type":"Services"
        }
    ],
    "sg:phone":"+1 718 324 7694",
    "sg:postcode":"10470",
    "sg:province":"NY",
    "sg:tags":[
        "company"
    ],
    "wof:name":"Mocar Construction",
    "wof:placetype":"venue"
},
  "geometry": {"coordinates":[-73.873823,40.895916],"type":"Point"}
}