{
  "type": "Feature",
  "properties": {
    "addr:full":"33 Mc Gowan Ln Central Islip NY 11722",
    "addr:housenumber":"33",
    "addr:postcode":"11722",
    "addr:street":"Mc Gowan Ln",
    "iso:country":"US",
    "sg:address":"33 Mc Gowan Ln",
    "sg:city":"Central Islip",
    "sg:classifiers":[
        {
            "category":"Retail",
            "subcategory":"Laundry & Dry Cleaning",
            "type":"Services"
        }
    ],
    "sg:phone":"+1   ",
    "sg:postcode":"11722",
    "sg:province":"NY",
    "sg:tags":[
        "linen",
        "supply"
    ],
    "wof:name":"Old James Clothing",
    "wof:placetype":"venue"
},
  "geometry": {"coordinates":[-73.21145,40.797132],"type":"Point"}
}