{
  "type": "Feature",
  "properties": {
    "addr:full":"356 Wadsworth Ave New York NY 10040",
    "addr:housenumber":"356",
    "addr:postcode":"10040",
    "addr:street":"Wadsworth Ave",
    "iso:country":"US",
    "sg:address":"356 Wadsworth Ave",
    "sg:city":"New York",
    "sg:classifiers":[
        {
            "category":"Freight",
            "type":"Transportation"
        }
    ],
    "sg:phone":"+1 212 568 5088",
    "sg:postcode":"10040",
    "sg:province":"NY",
    "sg:tags":[
        "courier"
    ],
    "wof:name":"L C Couriers Inc",
    "wof:placetype":"venue"
},
  "geometry": {"coordinates":[-73.93065900000001,40.85576],"type":"Point"}
}