{
  "type": "Feature",
  "properties": {
    "addr:full":"595 Grand Ave Saratoga Springs NY 12866",
    "addr:housenumber":"595",
    "addr:postcode":"12866",
    "addr:street":"Grand Ave",
    "iso:country":"US",
    "sg:address":"595 Grand Ave",
    "sg:city":"Saratoga Springs",
    "sg:classifiers":[
        {
            "category":"Manufacturing",
            "subcategory":"Signs",
            "type":"Manufacturing & Wholesale Goods"
        }
    ],
    "sg:phone":"+1 518 584 1111",
    "sg:postcode":"12866",
    "sg:province":"NY",
    "sg:tags":[
        "mfg"
    ],
    "wof:name":"Saratoga Sign Pros Inc",
    "wof:placetype":"venue"
},
  "geometry": {"coordinates":[-73.834057,43.072548],"type":"Point"}
}