{
  "type": "Feature",
  "properties": {
    "iso:country":"US",
    "sg:address":"273 Dumont Avenue",
    "sg:city":"Brooklyn",
    "sg:classifiers":[
        {
            "category":"Restaurant",
            "type":"Food & Drink"
        }
    ],
    "sg:phone":"+1 718 498 1022",
    "sg:postcode":"11212",
    "sg:province":"NY",
    "wof:name":"Luen Hop Kitchen",
    "wof:placetype":"venue"
},
  "geometry": {"coordinates":[-73.909306,40.664096],"type":"Point"}
}