{
  "type": "Feature",
  "properties": {
    "iso:country":"US",
    "sg:address":"3301 Country Club Rd",
    "sg:city":"Endwell",
    "sg:classifiers":[
        {
            "category":"Health Services",
            "subcategory":"Doctor",
            "type":"Services"
        }
    ],
    "sg:phone":"+1 607 757 9242",
    "sg:postcode":"13760",
    "sg:province":"NY",
    "sg:tags":[
        "dentist"
    ],
    "wof:name":"Bronsky Orthodontic Group",
    "wof:placetype":"venue"
},
  "geometry": {"coordinates":[-76.02213399999999,42.116074],"type":"Point"}
}