{
  "type": "Feature",
  "properties": {
    "addr:full":"992 E 15th St Brooklyn NY 11230",
    "addr:housenumber":"992",
    "addr:postcode":"11230",
    "addr:street":"E 15Th St",
    "iso:country":"US",
    "sg:address":"992 E 15th St",
    "sg:city":"Brooklyn",
    "sg:classifiers":[
        {
            "category":"Restaurant",
            "type":"Food & Drink"
        }
    ],
    "sg:phone":"+1 347 713 8077",
    "sg:postcode":"11230",
    "sg:province":"NY",
    "sg:tags":[
        "kosher"
    ],
    "wof:name":"Kosher Creperie",
    "wof:placetype":"venue"
},
  "geometry": {"coordinates":[-73.96159400000001,40.625301],"type":"Point"}
}