{
  "type": "Feature",
  "properties": {
    "iso:country":"US",
    "sg:address":"4000 McMahon Rd",
    "sg:city":"Marathon",
    "sg:classifiers":[
        {
            "category":"Farming",
            "subcategory":"Farm",
            "type":"Manufacturing & Wholesale Goods"
        }
    ],
    "sg:phone":"+1 607 849 6628",
    "sg:postcode":"13803",
    "sg:province":"NY",
    "wof:name":"Alpacas Marathon",
    "wof:placetype":"venue"
},
  "geometry": {"coordinates":[-76.01152500000001,42.47821],"type":"Point"}
}