{
  "type": "Feature",
  "properties": {
    "addr:full":"50 E Barclay St Hicksville NY 11801",
    "addr:housenumber":"50",
    "addr:postcode":"11801",
    "addr:street":"E Barclay St",
    "iso:country":"US",
    "sg:address":"50 E Barclay St",
    "sg:city":"Hicksville",
    "sg:classifiers":[
        {
            "category":"Autos & Motor Vehicles",
            "subcategory":"Automobile Sales",
            "type":"Retail Goods"
        }
    ],
    "sg:phone":"+1   ",
    "sg:postcode":"11801",
    "sg:province":"NY",
    "sg:tags":[
        "used"
    ],
    "wof:name":"Hicksville Auto Sales Ltd",
    "wof:placetype":"venue"
},
  "geometry": {"coordinates":[-73.52400900000001,40.769093],"type":"Point"}
}