{
  "type": "Feature",
  "properties": {
    "iso:country":"US",
    "sg:address":"4905 Merrick Rd",
    "sg:city":"Massapequa Park",
    "sg:classifiers":[
        {
            "category":"Personal",
            "subcategory":"Shoe Repair & Shine",
            "type":"Services"
        }
    ],
    "sg:phone":"+1   ",
    "sg:postcode":"11762",
    "sg:province":"NY",
    "sg:tags":[
        "parlor",
        "good"
    ],
    "wof:name":"Bar Harbour Shoe Repair",
    "wof:placetype":"venue"
},
  "geometry": {"coordinates":[-73.453946,40.666534],"type":"Point"}
}