{
  "type": "Feature",
  "properties": {
    "addr:full":"45 Greene Ave Sayville NY 11782",
    "addr:housenumber":"45",
    "addr:postcode":"11782",
    "addr:street":"Greene Ave",
    "iso:country":"US",
    "sg:address":"45 Greene Ave",
    "sg:city":"Sayville",
    "sg:classifiers":[
        {
            "category":"Social Services",
            "subcategory":"Child Care",
            "type":"Services"
        }
    ],
    "sg:phone":"+1   ",
    "sg:postcode":"11782",
    "sg:province":"NY",
    "sg:tags":[
        "day"
    ],
    "wof:name":"Sayville Lutheran Playschool",
    "wof:placetype":"venue"
},
  "geometry": {"coordinates":[-73.08595200000001,40.739074],"type":"Point"}
}