{
  "type": "Feature",
  "properties": {
    "iso:country":"US",
    "sg:address":"135 Green Meadow Dr",
    "sg:city":"Deer Park",
    "sg:classifiers":[
        {
            "category":"Retail",
            "subcategory":"Auto Repair",
            "type":"Services"
        }
    ],
    "sg:phone":"+1 631 667 3700",
    "sg:postcode":"11729",
    "sg:province":"NY",
    "sg:tags":[
        "exchanging",
        "engine"
    ],
    "wof:name":"A & J Auto Wreckers Inc",
    "wof:placetype":"venue"
},
  "geometry": {"coordinates":[-73.30569199999999,40.757462],"type":"Point"}
}