{
  "type": "Feature",
  "properties": {
    "addr:full":"350 Fairview Ave Hudson NY 12534",
    "addr:housenumber":"350",
    "addr:postcode":"12534",
    "addr:street":"Fairview Ave",
    "iso:country":"US",
    "sg:address":"350 Fairview Ave",
    "sg:city":"Hudson",
    "sg:classifiers":[
        {
            "category":"Restaurant",
            "type":"Food & Drink"
        }
    ],
    "sg:menulink":"http://www.allmenus.com/ny/greenport/200641-long-john-silvers/menu/",
    "sg:phone":"+1 518 828 3193",
    "sg:postcode":"12534",
    "sg:province":"NY",
    "sg:tags":[
        "seafood",
        "american"
    ],
    "wof:name":"Long John Silver's",
    "wof:placetype":"venue"
},
  "geometry": {"coordinates":[-73.75925100000001,42.27331],"type":"Point"}
}