{
  "type": "Feature",
  "properties": {
    "addr:full":"41 Loughlin Rd Binghamton NY 13904",
    "addr:housenumber":"41",
    "addr:postcode":"13904",
    "addr:street":"Loughlin Rd",
    "iso:country":"US",
    "sg:address":"41 Loughlin Rd",
    "sg:city":"Binghamton",
    "sg:classifiers":[
        {
            "category":"Real Estate",
            "subcategory":"Real Estate Operator",
            "type":"Services"
        }
    ],
    "sg:phone":"+1 607 775 1805",
    "sg:postcode":"13904",
    "sg:province":"NY",
    "sg:tags":[
        "mobile",
        "home",
        "community"
    ],
    "wof:name":"Kirkwood Mobile Home Park",
    "wof:placetype":"venue"
},
  "geometry": {"coordinates":[-75.846075,42.105427],"type":"Point"}
}