{
  "type": "Feature",
  "properties": {
    "addr:full":"514 Pine St Mamaroneck NY 10543",
    "addr:housenumber":"514",
    "addr:postcode":"10543",
    "addr:street":"Pine St",
    "iso:country":"US",
    "sg:address":"514 Pine St",
    "sg:city":"Mamaroneck",
    "sg:classifiers":[
        {
            "category":"Building & Trades",
            "subcategory":"Landscaping Services",
            "type":"Services"
        }
    ],
    "sg:phone":"+1 914 381 7327",
    "sg:postcode":"10543",
    "sg:province":"NY",
    "sg:tags":[
        "masonry",
        "landscape",
        "contractor"
    ],
    "wof:name":"Panetta Zntti Ldscp Msnry Work",
    "wof:placetype":"venue"
},
  "geometry": {"coordinates":[-73.72893500000001,40.952471],"type":"Point"}
}