{
  "type": "Feature",
  "properties": {
    "iso:country":"US",
    "sg:address":"14216 56th Rd",
    "sg:city":"Flushing",
    "sg:classifiers":[
        {
            "category":"Home & Garden",
            "subcategory":"Building Materials",
            "type":"Retail Goods"
        },
        {
            "category":"Manufacturing",
            "subcategory":"Building Materials",
            "type":"Manufacturing & Wholesale Goods"
        }
    ],
    "sg:phone":"+1 718 539 3864",
    "sg:postcode":"11355",
    "sg:province":"NY",
    "sg:tags":[
        "window",
        "doors-wholesale",
        "manufacturer"
    ],
    "wof:name":"Rlc Realty",
    "wof:placetype":"venue"
},
  "geometry": {"coordinates":[-73.823195,40.746603],"type":"Point"}
}