{
  "type": "Feature",
  "properties": {
    "iso:country":"US",
    "sg:address":"2641 Grand Concourse",
    "sg:city":"Bronx",
    "sg:classifiers":[
        {
            "category":"Manufacturing",
            "subcategory":"Retail Goods",
            "type":"Manufacturing & Wholesale Goods"
        }
    ],
    "sg:phone":"+1 718 295 2191",
    "sg:postcode":"10468",
    "sg:province":"NY",
    "sg:tags":[
        "manufacturer"
    ],
    "wof:name":"Temco Service Industries Inc",
    "wof:placetype":"venue"
},
  "geometry": {"coordinates":[-73.89457899999999,40.865865],"type":"Point"}
}