{
  "type": "Feature",
  "properties": {
    "iso:country":"US",
    "sg:address":"1299 Kings Rd",
    "sg:city":"Schenectady",
    "sg:classifiers":[
        {
            "category":"Building & Trades",
            "subcategory":"Construction",
            "type":"Services"
        }
    ],
    "sg:phone":"+1 518 346 7804",
    "sg:postcode":"12303",
    "sg:province":"NY",
    "sg:tags":[
        "excavation",
        "excavating",
        "contractor"
    ],
    "wof:name":"Wozniuk Nicholas Excavator",
    "wof:placetype":"venue"
},
  "geometry": {"coordinates":[-73.890511,42.740342],"type":"Point"}
}