{
  "type": "Feature",
  "properties": {
    "iso:country":"US",
    "sg:address":"367 Main St",
    "sg:city":"East Aurora",
    "sg:classifiers":[
        {
            "category":"Organizations",
            "subcategory":"Religious Organization",
            "type":"Services"
        }
    ],
    "sg:phone":"+1 716 652 6300",
    "sg:postcode":"14052",
    "sg:province":"NY",
    "wof:name":"First Church Christ Sceintist",
    "wof:placetype":"venue"
},
  "geometry": {"coordinates":[-78.621998,42.76803],"type":"Point"}
}