{
  "type": "Feature",
  "properties": {
    "addr:full":"6 Mall Walk Yonkers NY 10704",
    "addr:housenumber":"6",
    "addr:postcode":"10704",
    "addr:street":"Mall Walk",
    "iso:country":"US",
    "sg:address":"6 Mall Walk",
    "sg:city":"Yonkers",
    "sg:classifiers":[
        {
            "category":"Government",
            "subcategory":"Office",
            "type":"Public Place"
        }
    ],
    "sg:phone":"+1 914 968 0042",
    "sg:postcode":"10704",
    "sg:province":"NY",
    "sg:tags":[
        "navy",
        "recruiting"
    ],
    "wof:name":"Navy Recruiting Office",
    "wof:placetype":"venue"
},
  "geometry": {"coordinates":[-73.855205,40.928032],"type":"Point"}
}