{
  "type": "Feature",
  "properties": {
    "addr:full":"13333 Brookville Boulevard Rosedale NY 11422",
    "addr:housenumber":"13333",
    "addr:postcode":"11422",
    "addr:street":"Brookville Boulevard",
    "iso:country":"US",
    "sg:address":"13333 Brookville Boulevard",
    "sg:city":"Rosedale",
    "sg:classifiers":[
        {
            "category":"Professional",
            "subcategory":"Accounting & Tax Preparation",
            "type":"Services"
        }
    ],
    "sg:phone":"+1 718 723 9440",
    "sg:postcode":"11422",
    "sg:province":"NY",
    "sg:tags":[
        "accountant"
    ],
    "wof:name":"Hantour Mahmoud K CPA",
    "wof:placetype":"venue"
},
  "geometry": {"coordinates":[-73.732788,40.674258],"type":"Point"}
}