{
  "type": "Feature",
  "properties": {
    "addr:full":"282 Franklin St Buffalo NY 14202",
    "addr:housenumber":"282",
    "addr:postcode":"14202",
    "addr:street":"Franklin St",
    "iso:country":"US",
    "sg:address":"282 Franklin St",
    "sg:city":"Buffalo",
    "sg:classifiers":[
        {
            "category":"Restaurant",
            "type":"Food & Drink"
        }
    ],
    "sg:menulink":"http://www.allmenus.com/ny/buffalo/245716-buffalo-chophouse/menu/",
    "sg:phone":"+1 716 842 6900",
    "sg:postcode":"14202",
    "sg:province":"NY",
    "sg:tags":[
        "american",
        "steakhouse"
    ],
    "wof:name":"Buffalo Chophouse",
    "wof:placetype":"venue"
},
  "geometry": {"coordinates":[-78.874701,42.891955],"type":"Point"}
}