{
  "type": "Feature",
  "properties": {
    "iso:country":"US",
    "sg:address":"1462 Erie Blvd",
    "sg:city":"Schenectady",
    "sg:classifiers":[
        {
            "category":"Professional",
            "subcategory":"Accounting & Tax Preparation",
            "type":"Services"
        }
    ],
    "sg:phone":"+1 518 374 0680",
    "sg:postcode":"12305",
    "sg:province":"NY",
    "sg:tags":[
        "return",
        "filing"
    ],
    "wof:name":"Joseph J Montone & Co",
    "wof:placetype":"venue"
},
  "geometry": {"coordinates":[-73.93743499999999,42.819955],"type":"Point"}
}