{
  "type": "Feature",
  "properties": {
    "iso:country":"US",
    "sg:address":"167 Depot Rd",
    "sg:city":"Huntington Station",
    "sg:classifiers":[
        {
            "category":"Wholesale",
            "subcategory":"Construction Materials",
            "type":"Manufacturing & Wholesale Goods"
        }
    ],
    "sg:phone":"+1 631 271 4004",
    "sg:postcode":"11746",
    "sg:province":"NY",
    "sg:tags":[
        "stone",
        "paving"
    ],
    "wof:name":"Canus Distributing Corporation",
    "wof:placetype":"venue"
},
  "geometry": {"coordinates":[-73.406942,40.845822],"type":"Point"}
}