{
  "type": "Feature",
  "properties": {
    "addr:full":"745 Fort Salonga Rd Northport NY 11768",
    "addr:housenumber":"745",
    "addr:postcode":"11768",
    "addr:street":"Fort Salonga Rd",
    "iso:country":"US",
    "sg:address":"745 Fort Salonga Rd",
    "sg:city":"Northport",
    "sg:classifiers":[
        {
            "category":"Cinema",
            "subcategory":"Movie Rental",
            "type":"Entertainment"
        }
    ],
    "sg:phone":"+1 631 912 9051",
    "sg:postcode":"11768",
    "sg:province":"NY",
    "sg:tags":[
        "video",
        "tape"
    ],
    "wof:name":"Blockbuster",
    "wof:placetype":"venue"
},
  "geometry": {"coordinates":[-73.33504600000001,40.896354],"type":"Point"}
}