{
  "type": "Feature",
  "properties": {
    "addr:full":"174 5th Ave Manhattan NY 10010",
    "addr:housenumber":"174",
    "addr:postcode":"10010",
    "addr:street":"5Th Ave",
    "iso:country":"US",
    "sg:address":"174 5th Ave",
    "sg:city":"Manhattan",
    "sg:classifiers":[
        {
            "category":"Real Estate",
            "subcategory":"Real Estate Agent",
            "type":"Services"
        }
    ],
    "sg:phone":"+1 646 306 0448",
    "sg:postcode":"10010",
    "sg:province":"NY",
    "sg:website":"avirealtynyc.com",
    "wof:name":"Avi Realty",
    "wof:placetype":"venue"
},
  "geometry": {"coordinates":[-73.990257,40.74119],"type":"Point"}
}