{
  "type": "Feature",
  "properties": {
    "iso:country":"US",
    "sg:address":"1612 Westchester Ave",
    "sg:city":"Bronx",
    "sg:classifiers":[
        {
            "category":"Shopping",
            "subcategory":"Pharmacy",
            "type":"Retail Goods"
        }
    ],
    "sg:phone":"+1   ",
    "sg:postcode":"10472",
    "sg:province":"NY",
    "wof:name":"Liptis Laboratories Inc",
    "wof:placetype":"venue"
},
  "geometry": {"coordinates":[-73.875004,40.82926],"type":"Point"}
}