{
  "type": "Feature",
  "properties": {
    "iso:country":"US",
    "sg:address":"783 Route 9 # 22",
    "sg:city":"Fishkill",
    "sg:phone":"+1 845 896 5151",
    "sg:postcode":"12524",
    "sg:province":"NY",
    "wof:name":"Stein, Lawrence C, Dds - Family Dental Group",
    "wof:placetype":"venue"
},
  "geometry": {"coordinates":[-73.90168799999999,41.540645],"type":"Point"}
}