{
  "type": "Feature",
  "properties": {
    "iso:country":"US",
    "sg:address":"7399 Oxbow Rd",
    "sg:city":"Canastota",
    "sg:classifiers":[
        {
            "category":"Personal",
            "subcategory":"Beauty Salon",
            "type":"Services"
        }
    ],
    "sg:phone":"+1   ",
    "sg:postcode":"13032",
    "sg:province":"NY",
    "sg:tags":[
        "shop"
    ],
    "wof:name":"Crew Cuts",
    "wof:placetype":"venue"
},
  "geometry": {"coordinates":[-75.749927,43.060412],"type":"Point"}
}