{
  "type": "Feature",
  "properties": {
    "addr:full":"7 Diane Ct East Northport NY 11731",
    "addr:housenumber":"7",
    "addr:postcode":"11731",
    "addr:street":"Diane Ct",
    "iso:country":"US",
    "sg:address":"7 Diane Ct",
    "sg:city":"East Northport",
    "sg:classifiers":[
        {
            "category":"Social Services",
            "type":"Services"
        }
    ],
    "sg:phone":"+1 631 261 7901",
    "sg:postcode":"11731",
    "sg:province":"NY",
    "sg:tags":[
        "organization",
        "welfare"
    ],
    "wof:name":"Youth Directions & Alternative",
    "wof:placetype":"venue"
},
  "geometry": {"coordinates":[-73.32216,40.876793],"type":"Point"}
}