{
  "type": "Feature",
  "properties": {
    "addr:full":"7921 Lauther Rd Blossvale NY 13308",
    "addr:housenumber":"7921",
    "addr:postcode":"13308",
    "addr:street":"Lauther Rd",
    "iso:country":"US",
    "sg:address":"7921 Lauther Rd",
    "sg:city":"Blossvale",
    "sg:classifiers":[
        {
            "category":"Building & Trades",
            "subcategory":"Construction",
            "type":"Services"
        }
    ],
    "sg:phone":"+1 315 336 6524",
    "sg:postcode":"13308",
    "sg:province":"NY",
    "sg:tags":[
        "house"
    ],
    "wof:name":"Waterman Sky & Marie",
    "wof:placetype":"venue"
},
  "geometry": {"coordinates":[-75.596705,43.251405],"type":"Point"}
}