{
  "type": "Feature",
  "properties": {
    "addr:full":"180 E 64 St New York NY 10065",
    "addr:housenumber":"180;64",
    "addr:postcode":"10065",
    "addr:street":"E;St",
    "iso:country":"US",
    "sg:address":"180 E 64 St",
    "sg:city":"New York",
    "sg:classifiers":[
        {
            "category":"Arts & Performance",
            "subcategory":"Theater",
            "type":"Entertainment"
        }
    ],
    "sg:phone":"+1 212 755 1940",
    "sg:postcode":"10065",
    "sg:province":"NY",
    "sg:tags":[
        "bureau"
    ],
    "sg:website":"www.barryherman.com",
    "wof:name":"Barry Herman Entertainment",
    "wof:placetype":"venue"
},
  "geometry": {"coordinates":[-73.965052,40.765016],"type":"Point"}
}