{
  "type": "Feature",
  "properties": {
    "addr:full":"146 W 57th St New York NY 10019",
    "addr:housenumber":"146",
    "addr:postcode":"10019",
    "addr:street":"W 57Th St",
    "iso:country":"US",
    "sg:address":"146 W 57th St",
    "sg:city":"New York",
    "sg:classifiers":[
        {
            "category":"Retail",
            "subcategory":"Laundry & Dry Cleaning",
            "type":"Services"
        }
    ],
    "sg:phone":"+1 212 489 7430",
    "sg:postcode":"10019",
    "sg:province":"NY",
    "wof:name":"Aphrodite French Laundry & Cleaners",
    "wof:placetype":"venue"
},
  "geometry": {"coordinates":[-73.978897,40.765202],"type":"Point"}
}