{
  "type": "Feature",
  "properties": {
    "addr:full":"5611 Broadway Bronx NY 10463",
    "addr:housenumber":"5611",
    "addr:postcode":"10463",
    "addr:street":"Broadway",
    "iso:country":"US",
    "sg:address":"5611 Broadway",
    "sg:city":"Bronx",
    "sg:classifiers":[
        {
            "category":"Personal",
            "subcategory":"Beauty Salon",
            "type":"Services"
        }
    ],
    "sg:phone":"+1 718 548 9894",
    "sg:postcode":"10463",
    "sg:province":"NY",
    "wof:name":"Victor's Beauty Salon",
    "wof:placetype":"venue"
},
  "geometry": {"coordinates":[-73.904607,40.879248],"type":"Point"}
}