{
  "type": "Feature",
  "properties": {
    "addr:full":"2753 E 21st St Brooklyn NY 11235",
    "addr:housenumber":"2753",
    "addr:postcode":"11235",
    "addr:street":"E 21St St",
    "iso:country":"US",
    "sg:address":"2753 E 21st St",
    "sg:city":"Brooklyn",
    "sg:classifiers":[
        {
            "category":"Freight",
            "type":"Transportation"
        }
    ],
    "sg:phone":"+1   ",
    "sg:postcode":"11235",
    "sg:province":"NY",
    "sg:tags":[
        "local",
        "storage",
        "trucking"
    ],
    "wof:name":"AAAA Aurora Van Lines Inc",
    "wof:placetype":"venue"
},
  "geometry": {"coordinates":[-73.94758400000001,40.58518],"type":"Point"}
}