{
  "type": "Feature",
  "properties": {
    "iso:country":"US",
    "sg:address":"117 E 24th Street",
    "sg:city":"New York",
    "sg:classifiers":[
        {
            "category":"Education",
            "subcategory":"University",
            "type":"Public Place"
        }
    ],
    "sg:phone":"+1 212 982 5370",
    "sg:postcode":"10010",
    "sg:province":"NY",
    "sg:tags":[
        "college"
    ],
    "sg:website":"www.appstate.edu",
    "wof:name":"Appalachian State University",
    "wof:placetype":"venue"
},
  "geometry": {"coordinates":[-73.985145,40.740446],"type":"Point"}
}