{
  "type": "Feature",
  "properties": {
    "addr:full":"250 South St Peekskill NY 10566",
    "addr:housenumber":"250",
    "addr:postcode":"10566",
    "addr:street":"South St",
    "iso:country":"US",
    "sg:address":"250 South St",
    "sg:city":"Peekskill",
    "sg:classifiers":[
        {
            "category":"Organizations",
            "subcategory":"Religious Organization",
            "type":"Services"
        }
    ],
    "sg:phone":"+1 914 737 3373",
    "sg:postcode":"10566",
    "sg:province":"NY",
    "sg:tags":[
        "monastery",
        "convent"
    ],
    "wof:name":"Franciscan Sisters-Peekskill",
    "wof:placetype":"venue"
},
  "geometry": {"coordinates":[-73.928916,41.284548],"type":"Point"}
}