{
  "type": "Feature",
  "properties": {
    "addr:full":"80 W Kingsbridge Rd Bronx NY 10468",
    "addr:housenumber":"80",
    "addr:postcode":"10468",
    "addr:street":"W Kingsbridge Rd",
    "iso:country":"US",
    "sg:address":"80 W Kingsbridge Rd",
    "sg:city":"Bronx",
    "sg:classifiers":[
        {
            "category":"Restaurant",
            "type":"Food & Drink"
        }
    ],
    "sg:phone":"+1 718 220 0012",
    "sg:postcode":"10468",
    "sg:province":"NY",
    "wof:name":"Brisas",
    "wof:placetype":"venue"
},
  "geometry": {"coordinates":[-73.900829,40.868093],"type":"Point"}
}