{
  "type": "Feature",
  "properties": {
    "addr:full":"145 Triphammer Ter Ithaca NY 14850",
    "addr:housenumber":"145",
    "addr:postcode":"14850",
    "addr:street":"Triphammer Ter",
    "iso:country":"US",
    "sg:address":"145 Triphammer Ter",
    "sg:city":"Ithaca",
    "sg:classifiers":[
        {
            "category":"Professional",
            "subcategory":"Advertising",
            "type":"Services"
        }
    ],
    "sg:phone":"+1 607 273 9264",
    "sg:postcode":"14850",
    "sg:province":"NY",
    "sg:tags":[
        "promotion",
        "sale"
    ],
    "wof:name":"Mark D Hulsebosch",
    "wof:placetype":"venue"
},
  "geometry": {"coordinates":[-76.48387,42.524333],"type":"Point"}
}