{
  "type": "Feature",
  "properties": {
    "iso:country":"US",
    "sg:address":"1255 Alken Ave",
    "sg:city":"Seaford",
    "sg:classifiers":[
        {
            "category":"Social Services",
            "type":"Services"
        }
    ],
    "sg:phone":"+1 631 691 5100",
    "sg:postcode":"11783",
    "sg:province":"NY",
    "wof:name":"Hope For Youth Inc",
    "wof:placetype":"venue"
},
  "geometry": {"coordinates":[-73.488063,40.701063],"type":"Point"}
}