{
  "type": "Feature",
  "properties": {
    "addr:full":"550 Long Beach Blvd Long Beach NY 11561",
    "addr:housenumber":"550",
    "addr:postcode":"11561",
    "addr:street":"Long Beach Blvd",
    "iso:country":"US",
    "sg:address":"550 Long Beach Blvd",
    "sg:city":"Long Beach",
    "sg:classifiers":[
        {
            "category":"Banks & Credit Unions",
            "subcategory":"Bank",
            "type":"Services"
        }
    ],
    "sg:phone":"+1 516 889 1119",
    "sg:postcode":"11561",
    "sg:province":"NY",
    "sg:tags":[
        "state",
        "commercial"
    ],
    "wof:name":"Commerce Bank NA",
    "wof:placetype":"venue"
},
  "geometry": {"coordinates":[-73.657364,40.591595],"type":"Point"}
}