{
  "type": "Feature",
  "properties": {
    "iso:country":"US",
    "sg:address":"28 Hillside Ln",
    "sg:city":"Valley Cottage",
    "sg:classifiers":[
        {
            "category":"Banks & Credit Unions",
            "subcategory":"Bank",
            "type":"Services"
        }
    ],
    "sg:phone":"+1 845 398 6277",
    "sg:postcode":"10989",
    "sg:province":"NY",
    "sg:tags":[
        "mortgage"
    ],
    "wof:name":"Michael Starbaggi",
    "wof:placetype":"venue"
},
  "geometry": {"coordinates":[-73.943072,41.113359],"type":"Point"}
}