{
  "type": "Feature",
  "properties": {
    "addr:full":"2414 Gerritsen Ave Brooklyn NY 11229",
    "addr:housenumber":"2414",
    "addr:postcode":"11229",
    "addr:street":"Gerritsen Ave",
    "iso:country":"US",
    "sg:address":"2414 Gerritsen Ave",
    "sg:city":"Brooklyn",
    "sg:classifiers":[
        {
            "category":"Organizations",
            "subcategory":"Community Association",
            "type":"Services"
        }
    ],
    "sg:phone":"+1   ",
    "sg:postcode":"11229",
    "sg:province":"NY",
    "wof:name":"Veterans of Foreign War",
    "wof:placetype":"venue"
},
  "geometry": {"coordinates":[-73.930189,40.597331],"type":"Point"}
}