{
  "type": "Feature",
  "properties": {
    "addr:full":"5518 Gravel Run Rd Dundee NY 14837",
    "addr:housenumber":"5518",
    "addr:postcode":"14837",
    "addr:street":"Gravel Run Rd",
    "iso:country":"US",
    "sg:address":"5518 Gravel Run Rd",
    "sg:city":"Dundee",
    "sg:classifiers":[
        {
            "category":"Wholesale",
            "subcategory":"Farm Supplies",
            "type":"Manufacturing & Wholesale Goods"
        }
    ],
    "sg:phone":"+1 607 243 8448",
    "sg:postcode":"14837",
    "sg:province":"NY",
    "wof:name":"Bloom Farm Supply",
    "wof:placetype":"venue"
},
  "geometry": {"coordinates":[-77.02311899999999,42.49989],"type":"Point"}
}