{
  "type": "Feature",
  "properties": {
    "iso:country":"US",
    "sg:address":"311 Old Indianhead Rd",
    "sg:city":"Kings Park",
    "sg:classifiers":[
        {
            "category":"Retail",
            "subcategory":"Auto Repair",
            "type":"Services"
        }
    ],
    "sg:phone":"+1   ",
    "sg:postcode":"11754",
    "sg:province":"NY",
    "sg:tags":[
        "body"
    ],
    "wof:name":"Dent Fixr Inc",
    "wof:placetype":"venue"
},
  "geometry": {"coordinates":[-73.254974,40.871699],"type":"Point"}
}