{
  "type": "Feature",
  "properties": {
    "addr:full":"4 Village Dr Medford NY 11763",
    "addr:housenumber":"4",
    "addr:postcode":"11763",
    "addr:street":"Village Dr",
    "iso:country":"US",
    "sg:address":"4 Village Dr",
    "sg:city":"Medford",
    "sg:classifiers":[
        {
            "category":"Building & Trades",
            "subcategory":"Plumbing",
            "type":"Services"
        }
    ],
    "sg:phone":"+1 631 807 2009",
    "sg:postcode":"11763",
    "sg:province":"NY",
    "sg:tags":[
        "plumber",
        "industrial",
        "contractors-commercial"
    ],
    "wof:name":"Conrad Plumbing And Heating Inc.",
    "wof:placetype":"venue"
},
  "geometry": {"coordinates":[-72.987422,40.811798],"type":"Point"}
}