{
  "type": "Feature",
  "properties": {
    "iso:country":"US",
    "sg:address":"931 Shoemaker Rd",
    "sg:city":"Webster",
    "sg:classifiers":[
        {
            "category":"Restaurant",
            "type":"Food & Drink"
        }
    ],
    "sg:phone":"+1   ",
    "sg:postcode":"14580",
    "sg:province":"NY",
    "sg:tags":[
        "american"
    ],
    "wof:name":"Senator Restaurant",
    "wof:placetype":"venue"
},
  "geometry": {"coordinates":[-77.465093,43.237162],"type":"Point"}
}