{
  "type": "Feature",
  "properties": {
    "iso:country":"US",
    "sg:address":"399 Neighborhood Road",
    "sg:city":"Mastic Beach",
    "sg:classifiers":[
        {
            "category":"Food & Beverages",
            "subcategory":"Candy",
            "type":"Retail Goods"
        }
    ],
    "sg:phone":"+1 631 804 5623",
    "sg:postcode":"11951",
    "sg:province":"NY",
    "sg:tags":[
        "dessert"
    ],
    "wof:name":"Mommylou's Cheesecake",
    "wof:placetype":"venue"
},
  "geometry": {"coordinates":[-72.856064,40.762647],"type":"Point"}
}