{
  "type": "Feature",
  "properties": {
    "addr:full":"134 E Manlius St East Syracuse NY 13057",
    "addr:housenumber":"134",
    "addr:postcode":"13057",
    "addr:street":"E Manlius St",
    "iso:country":"US",
    "sg:address":"134 E Manlius St",
    "sg:city":"East Syracuse",
    "sg:classifiers":[
        {
            "category":"Health Services",
            "subcategory":"Doctor",
            "type":"Services"
        }
    ],
    "sg:phone":"+1 315 463 9649",
    "sg:postcode":"13057",
    "sg:province":"NY",
    "sg:tags":[
        "dentist"
    ],
    "wof:name":"Bernard M Florento DDS",
    "wof:placetype":"venue"
},
  "geometry": {"coordinates":[-76.069213,43.063826],"type":"Point"}
}