{
  "type": "Feature",
  "properties": {
    "addr:full":"48 W 58th St New York NY 10019",
    "addr:housenumber":"48",
    "addr:postcode":"10019",
    "addr:street":"W 58Th St",
    "iso:country":"US",
    "sg:address":"48 W 58th St",
    "sg:city":"New York",
    "sg:classifiers":[
        {
            "category":"Personal",
            "subcategory":"Beauty Salon",
            "type":"Services"
        }
    ],
    "sg:phone":"+1 212 753 6131",
    "sg:postcode":"10019",
    "sg:province":"NY",
    "wof:name":"Salon At The Wyndam",
    "wof:placetype":"venue"
},
  "geometry": {"coordinates":[-73.97578900000001,40.764428],"type":"Point"}
}