{
  "type": "Feature",
  "properties": {
    "addr:full":"678 Central Park Ave Yonkers NY 10704",
    "addr:housenumber":"678",
    "addr:postcode":"10704",
    "addr:street":"Central Park Ave",
    "iso:country":"US",
    "sg:address":"678 Central Park Ave",
    "sg:city":"Yonkers",
    "sg:classifiers":[
        {
            "category":"Shopping",
            "subcategory":"Florist",
            "type":"Retail Goods"
        }
    ],
    "sg:phone":"+1 914 376 1334",
    "sg:postcode":"10704",
    "sg:province":"NY",
    "wof:name":"Central Park Florist",
    "wof:placetype":"venue"
},
  "geometry": {"coordinates":[-73.85941099999999,40.923407],"type":"Point"}
}