{
  "type": "Feature",
  "properties": {
    "iso:country":"US",
    "sg:address":"40 River Rd",
    "sg:city":"New York",
    "sg:classifiers":[
        {
            "category":"Building & Trades",
            "subcategory":"Construction",
            "type":"Services"
        }
    ],
    "sg:phone":"+1 212 645 1555",
    "sg:postcode":"10044",
    "sg:province":"NY",
    "sg:tags":[
        "floor",
        "laying",
        "contractor"
    ],
    "wof:name":"Best Chair Rentals",
    "wof:placetype":"venue"
},
  "geometry": {"coordinates":[-73.94621100000001,40.765893],"type":"Point"}
}