{
  "type": "Feature",
  "properties": {
    "addr:full":"88 Main St Whitehall NY 12887",
    "addr:housenumber":"88",
    "addr:postcode":"12887",
    "addr:street":"Main St",
    "iso:country":"US",
    "sg:address":"88 Main St",
    "sg:city":"Whitehall",
    "sg:classifiers":[
        {
            "category":"Manufacturing",
            "subcategory":"Food",
            "type":"Manufacturing & Wholesale Goods"
        },
        {
            "category":"Restaurant",
            "type":"Food & Drink"
        },
        {
            "category":"Ice Cream",
            "type":"Food & Drink"
        }
    ],
    "sg:phone":"+1 315 531 5311",
    "sg:postcode":"12887",
    "sg:province":"NY",
    "sg:tags":[
        "frozen",
        "dessert",
        "desserts-manufacturers",
        "distributor"
    ],
    "wof:name":"Mr Twistee's",
    "wof:placetype":"venue"
},
  "geometry": {"coordinates":[-73.401753,43.556066],"type":"Point"}
}