{
  "type": "Feature",
  "properties": {
    "addr:full":"751 Brand Hollow Rd Peru NY 12972",
    "addr:housenumber":"751",
    "addr:postcode":"12972",
    "addr:street":"Brand Hollow Rd",
    "iso:country":"US",
    "sg:address":"751 Brand Hollow Rd",
    "sg:city":"Peru",
    "sg:classifiers":[
        {
            "category":"Farming",
            "subcategory":"Orchard",
            "type":"Manufacturing & Wholesale Goods"
        }
    ],
    "sg:phone":"+1 518 643 2268",
    "sg:postcode":"12972",
    "sg:province":"NY",
    "sg:tags":[
        "fruit",
        "tree"
    ],
    "wof:name":"Applejack Orchard",
    "wof:placetype":"venue"
},
  "geometry": {"coordinates":[-73.562687,44.598855],"type":"Point"}
}