{
  "type": "Feature",
  "properties": {
    "iso:country":"US",
    "sg:address":"253 Beach 116th St",
    "sg:city":"Rockaway Park",
    "sg:classifiers":[
        {
            "category":"Health Services",
            "subcategory":"Optometrist",
            "type":"Services"
        },
        {
            "category":"Shopping",
            "subcategory":"Optician",
            "type":"Retail Goods"
        }
    ],
    "sg:phone":"+1 718 634 0005",
    "sg:postcode":"11694",
    "sg:province":"NY",
    "sg:tags":[
        "eyewear"
    ],
    "sg:website":"www.mirkinvisioncare.com",
    "wof:name":"Mirkin Vision Care",
    "wof:placetype":"venue"
},
  "geometry": {"coordinates":[-73.8377,40.5802],"type":"Point"}
}