{
  "type": "Feature",
  "properties": {
    "addr:full":"739 Coney Island Ave Brooklyn NY 11218",
    "addr:housenumber":"739",
    "addr:postcode":"11218",
    "addr:street":"Coney Island Ave",
    "iso:country":"US",
    "sg:address":"739 Coney Island Ave",
    "sg:city":"Brooklyn",
    "sg:classifiers":[
        {
            "category":"Restaurant",
            "type":"Food & Drink"
        }
    ],
    "sg:phone":"+1 718 462 5000",
    "sg:postcode":"11218",
    "sg:province":"NY",
    "sg:tags":[
        "middle",
        "eastern"
    ],
    "wof:name":"Gyro King",
    "wof:placetype":"venue"
},
  "geometry": {"coordinates":[-73.96884799999999,40.639509],"type":"Point"}
}