{
  "type": "Feature",
  "properties": {
    "iso:country":"US",
    "sg:address":"88 Benbro Dr",
    "sg:city":"Cheektowaga",
    "sg:classifiers":[
        {
            "category":"Shopping",
            "subcategory":"Clothing, Apparel, & Fashions",
            "type":"Retail Goods"
        }
    ],
    "sg:phone":"+1 716 681 1238",
    "sg:postcode":"14225",
    "sg:province":"NY",
    "sg:tags":[
        "uniform"
    ],
    "wof:name":"North Eastern Uniforms & Equip",
    "wof:placetype":"venue"
},
  "geometry": {"coordinates":[-78.73636999999999,42.911077],"type":"Point"}
}