{
  "type": "Feature",
  "properties": {
    "addr:full":"531 Forest Ave Staten Island NY 10310",
    "addr:housenumber":"531",
    "addr:postcode":"10310",
    "addr:street":"Forest Ave",
    "iso:country":"US",
    "sg:address":"531 Forest Ave",
    "sg:city":"Staten Island",
    "sg:classifiers":[
        {
            "category":"Communications",
            "subcategory":"Film & Video Production",
            "type":"Services"
        }
    ],
    "sg:phone":"+1   ",
    "sg:postcode":"10310",
    "sg:province":"NY",
    "sg:tags":[
        "motion",
        "picture"
    ],
    "wof:name":"Ironhorse 2000 Inc",
    "wof:placetype":"venue"
},
  "geometry": {"coordinates":[-74.107995,40.630359],"type":"Point"}
}