{
  "type": "Feature",
  "properties": {
    "addr:full":"330 Hillside Ave Williston Park NY 11596",
    "addr:housenumber":"330",
    "addr:postcode":"11596",
    "addr:street":"Hillside Ave",
    "iso:country":"US",
    "sg:address":"330 Hillside Ave",
    "sg:city":"Williston Park",
    "sg:classifiers":[
        {
            "category":"Shopping",
            "subcategory":"Pharmacy",
            "type":"Retail Goods"
        }
    ],
    "sg:phone":"+1 516 746 0646",
    "sg:postcode":"11596",
    "sg:province":"NY",
    "sg:tags":[
        "drugstore"
    ],
    "wof:name":"Lafayette Pharmcy",
    "wof:placetype":"venue"
},
  "geometry": {"coordinates":[-73.65149700000001,40.754398],"type":"Point"}
}