{
  "type": "Feature",
  "properties": {
    "addr:full":"120 Edgewood Ave Smithtown NY 11787",
    "addr:housenumber":"120",
    "addr:postcode":"11787",
    "addr:street":"Edgewood Ave",
    "iso:country":"US",
    "sg:address":"120 Edgewood Ave",
    "sg:city":"Smithtown",
    "sg:classifiers":[
        {
            "category":"Organizations",
            "subcategory":"Professional Association",
            "type":"Services"
        },
        {
            "category":"Organizations",
            "subcategory":"Community Association",
            "type":"Services"
        }
    ],
    "sg:phone":"+1 631 360 8681",
    "sg:postcode":"11787",
    "sg:province":"NY",
    "wof:name":"Elks Bpoe Lodge No 2036",
    "wof:placetype":"venue"
},
  "geometry": {"coordinates":[-73.198722,40.860842],"type":"Point"}
}