{
  "type": "Feature",
  "properties": {
    "iso:country":"US",
    "sg:address":"116 Saxon Ave",
    "sg:city":"Bay Shore",
    "sg:classifiers":[
        {
            "category":"Autos & Motor Vehicles",
            "subcategory":"Auto Supplies",
            "type":"Retail Goods"
        }
    ],
    "sg:phone":"+1 631 581 8473",
    "sg:postcode":"11706",
    "sg:province":"NY",
    "sg:tags":[
        "tire"
    ],
    "wof:name":"Tires Direct Inc",
    "wof:placetype":"venue"
},
  "geometry": {"coordinates":[-73.22875999999999,40.736903],"type":"Point"}
}