{
  "type": "Feature",
  "properties": {
    "iso:country":"US",
    "sg:address":"2660 E 14th St",
    "sg:city":"Brooklyn",
    "sg:classifiers":[
        {
            "category":"Retail",
            "subcategory":"Auto Repair",
            "type":"Services"
        }
    ],
    "sg:phone":"+1   ",
    "sg:postcode":"11235",
    "sg:province":"NY",
    "sg:tags":[
        "automotive"
    ],
    "wof:name":"Golden Rhino Inc",
    "wof:placetype":"venue"
},
  "geometry": {"coordinates":[-73.95532799999999,40.587839],"type":"Point"}
}