{
  "type": "Feature",
  "properties": {
    "iso:country":"US",
    "sg:address":"289 Schenck St",
    "sg:city":"North Tonawanda",
    "sg:classifiers":[
        {
            "category":"Shopping",
            "type":"Retail Goods"
        },
        {
            "category":"Wholesale",
            "subcategory":"Electrical",
            "type":"Manufacturing & Wholesale Goods"
        }
    ],
    "sg:phone":"+1 716 694 6400",
    "sg:postcode":"14120",
    "sg:province":"NY",
    "sg:tags":[
        "cb",
        "radio",
        "telephone",
        "cellular"
    ],
    "wof:name":"Foss Warehouse Distr Ctr",
    "wof:placetype":"venue"
},
  "geometry": {"coordinates":[-78.8702,43.031749],"type":"Point"}
}