{
  "type": "Feature",
  "properties": {
    "iso:country":"US",
    "sg:address":"1738 Coney Island Ave",
    "sg:city":"Brooklyn",
    "sg:classifiers":[
        {
            "category":"Wholesale",
            "subcategory":"Medical Equipment & Supplies",
            "type":"Manufacturing & Wholesale Goods"
        }
    ],
    "sg:phone":"+1 718 336 6756",
    "sg:postcode":"11230",
    "sg:province":"NY",
    "sg:tags":[
        "physician",
        "surgeon"
    ],
    "wof:name":"Adams Medical Supplies",
    "wof:placetype":"venue"
},
  "geometry": {"coordinates":[-73.96285899999999,40.61255],"type":"Point"}
}