{
  "type": "Feature",
  "properties": {
    "addr:full":"1365 39th St Brooklyn NY 11218",
    "addr:housenumber":"1365",
    "addr:postcode":"11218",
    "addr:street":"39Th St",
    "iso:country":"US",
    "sg:address":"1365 39th St",
    "sg:city":"Brooklyn",
    "sg:classifiers":[
        {
            "category":"Professional",
            "type":"Services"
        }
    ],
    "sg:phone":"+1 718 853 6343",
    "sg:postcode":"11218",
    "sg:province":"NY",
    "sg:tags":[
        "establishment"
    ],
    "wof:name":"Alphatron Inc",
    "wof:placetype":"venue"
},
  "geometry": {"coordinates":[-73.985133,40.640223],"type":"Point"}
}