{
  "type": "Feature",
  "properties": {
    "addr:full":"209 W 80th St New York NY 10024",
    "addr:housenumber":"209",
    "addr:postcode":"10024",
    "addr:street":"W 80Th St",
    "iso:country":"US",
    "sg:address":"209 W 80th St",
    "sg:city":"New York",
    "sg:classifiers":[
        {
            "category":"Personal",
            "type":"Services"
        }
    ],
    "sg:phone":"+1 212 268 3900",
    "sg:postcode":"10024",
    "sg:province":"NY",
    "sg:tags":[
        "party",
        "planning",
        "event"
    ],
    "wof:name":"Balloon Man",
    "wof:placetype":"venue"
},
  "geometry": {"coordinates":[-73.978104,40.784],"type":"Point"}
}