{
  "type": "Feature",
  "properties": {
    "addr:full":"201 Anchorage Dr Islip NY 11795",
    "addr:housenumber":"201",
    "addr:postcode":"11795",
    "addr:street":"Anchorage Dr",
    "iso:country":"US",
    "sg:address":"201 Anchorage Dr",
    "sg:city":"Islip",
    "sg:classifiers":[
        {
            "category":"Professional",
            "type":"Services"
        }
    ],
    "sg:phone":"+1 631 893 8411",
    "sg:postcode":"11795",
    "sg:province":"NY",
    "sg:tags":[
        "establishment"
    ],
    "wof:name":"Red Clover Group Inc",
    "wof:placetype":"venue"
},
  "geometry": {"coordinates":[-73.286833,40.689461],"type":"Point"}
}