{
  "type": "Feature",
  "properties": {
    "iso:country":"US",
    "sg:address":"657 64th St",
    "sg:city":"Brooklyn",
    "sg:classifiers":[
        {
            "category":"Retail",
            "subcategory":"Auto Rental",
            "type":"Services"
        }
    ],
    "sg:phone":"+1 718 836 0900",
    "sg:postcode":"11220",
    "sg:province":"NY",
    "sg:tags":[
        "renting",
        "car",
        "automobile"
    ],
    "sg:website":"www.enterprise.com",
    "wof:name":"Enterprise Rent-A-Car",
    "wof:placetype":"venue"
},
  "geometry": {"coordinates":[-74.014504,40.635116],"type":"Point"}
}