{
  "type": "Feature",
  "properties": {
    "iso:country":"US",
    "sg:address":"114 Pearl St",
    "sg:city":"Mount Vernon",
    "sg:classifiers":[
        {
            "category":"Retail",
            "subcategory":"Auto Repair",
            "type":"Services"
        }
    ],
    "sg:phone":"+1 914 668 0305",
    "sg:postcode":"10550",
    "sg:province":"NY",
    "sg:tags":[
        "repairing",
        "automobile",
        "general"
    ],
    "wof:name":"Euromeccanica Inc",
    "wof:placetype":"venue"
},
  "geometry": {"coordinates":[-73.852358,40.907111],"type":"Point"}
}