{
  "type": "Feature",
  "properties": {
    "iso:country":"US",
    "sg:address":"3 Water Ln",
    "sg:city":"Manhasset",
    "sg:classifiers":[
        {
            "category":"Health Services",
            "subcategory":"Doctor",
            "type":"Services"
        }
    ],
    "sg:phone":"+1 516 627 6830",
    "sg:postcode":"11030",
    "sg:province":"NY",
    "sg:tags":[
        "medicine",
        "physician",
        "practice",
        "surgeons",
        "family"
    ],
    "wof:name":"The Theodore Goldsmith Family Limited Pa",
    "wof:placetype":"venue"
},
  "geometry": {"coordinates":[-73.703661,40.814029],"type":"Point"}
}