{
  "type": "Feature",
  "properties": {
    "iso:country":"US",
    "sg:address":"298 Montauk Hwy",
    "sg:city":"Bay Shore",
    "sg:classifiers":[
        {
            "category":"Restaurant",
            "type":"Food & Drink"
        }
    ],
    "sg:phone":"+1   ",
    "sg:postcode":"11706",
    "sg:province":"NY",
    "sg:tags":[
        "eating"
    ],
    "wof:name":"Friendlys",
    "wof:placetype":"venue"
},
  "geometry": {"coordinates":[-73.257026,40.715295],"type":"Point"}
}