{
  "type": "Feature",
  "properties": {
    "addr:full":"734 Walt Whitman Rd Melville NY 11747",
    "addr:housenumber":"734",
    "addr:postcode":"11747",
    "addr:street":"Walt Whitman Rd",
    "iso:country":"US",
    "sg:address":"734 Walt Whitman Rd",
    "sg:city":"Melville",
    "sg:classifiers":[
        {
            "category":"Wholesale",
            "subcategory":"Hardware",
            "type":"Manufacturing & Wholesale Goods"
        },
        {
            "category":"Building & Trades",
            "subcategory":"Plumbing",
            "type":"Services"
        }
    ],
    "sg:phone":"+1 631 271 6307",
    "sg:postcode":"11747",
    "sg:province":"NY",
    "sg:tags":[
        "plumbing",
        "c",
        "contractor"
    ],
    "wof:name":"Robert's Plumbing Inc",
    "wof:placetype":"venue"
},
  "geometry": {"coordinates":[-73.411553,40.803149],"type":"Point"}
}