{
  "type": "Feature",
  "properties": {
    "iso:country":"US",
    "sg:address":"4 S Washington Ave",
    "sg:city":"Oxford",
    "sg:classifiers":[
        {
            "category":"Insurance",
            "subcategory":"Insurance Agent",
            "type":"Services"
        },
        {
            "category":"Insurance",
            "subcategory":"Hazard Insurance",
            "type":"Services"
        },
        {
            "category":"Insurance",
            "subcategory":"Title Insurance",
            "type":"Services"
        }
    ],
    "sg:phone":"+1 607 843 8860",
    "sg:postcode":"13830",
    "sg:province":"NY",
    "sg:tags":[
        "business",
        "auto",
        "commercial",
        "homeowner",
        "property",
        "casualty"
    ],
    "sg:website":"http://www.mercuryinsurance.com",
    "wof:name":"Mercury Insurance - Drickard Insurance",
    "wof:placetype":"venue"
},
  "geometry": {"coordinates":[-75.59885199999999,42.442003],"type":"Point"}
}