{
  "type": "Feature",
  "properties": {
    "iso:country":"US",
    "sg:address":"2007 D St",
    "sg:city":"New Windsor",
    "sg:classifiers":[
        {
            "category":"Education",
            "subcategory":"Special Training",
            "type":"Public Place"
        }
    ],
    "sg:phone":"+1 845 567 3337",
    "sg:postcode":"12553",
    "sg:province":"NY",
    "sg:tags":[
        "instruction",
        "driving"
    ],
    "wof:name":"Now Jr Inc",
    "wof:placetype":"venue"
},
  "geometry": {"coordinates":[-74.099413,41.491391],"type":"Point"}
}