{
  "type": "Feature",
  "properties": {
    "addr:full":"783 Wangum Rd Victor NY 14564",
    "addr:housenumber":"783",
    "addr:postcode":"14564",
    "addr:street":"Wangum Rd",
    "iso:country":"US",
    "sg:address":"783 Wangum Rd",
    "sg:city":"Victor",
    "sg:classifiers":[
        {
            "category":"Manufacturing",
            "subcategory":"Metals",
            "type":"Manufacturing & Wholesale Goods"
        }
    ],
    "sg:phone":"+1 585 742 1790",
    "sg:postcode":"14564",
    "sg:province":"NY",
    "sg:tags":[
        "tool"
    ],
    "wof:name":"Victor Specialty Tools Inc",
    "wof:placetype":"venue"
},
  "geometry": {"coordinates":[-77.469515,43.000955],"type":"Point"}
}