{
  "type": "Feature",
  "properties": {
    "addr:full":"342 E 22nd St Manhattan NY 10010",
    "addr:housenumber":"342",
    "addr:postcode":"10010",
    "addr:street":"E 22Nd St",
    "iso:country":"US",
    "sg:address":"342 E 22nd St",
    "sg:city":"Manhattan",
    "sg:classifiers":[
        {
            "category":"Food & Beverages",
            "subcategory":"Meat & Fish",
            "type":"Retail Goods"
        }
    ],
    "sg:phone":"+1 212 358 7677",
    "sg:postcode":"10010",
    "sg:province":"NY",
    "sg:tags":[
        "seafood",
        "market"
    ],
    "sg:website":"www.rosendofishmarket.com/",
    "wof:name":"Rosendo Fish Market",
    "wof:placetype":"venue"
},
  "geometry": {"coordinates":[-73.979439,40.736313],"type":"Point"}
}