{
  "type": "Feature",
  "properties": {
    "iso:country":"US",
    "sg:address":"151 Richmond Hill Rd",
    "sg:city":"New Canaan",
    "sg:classifiers":[
        {
            "category":"Professional",
            "subcategory":"Business Services",
            "type":"Services"
        }
    ],
    "sg:phone":"+1   ",
    "sg:postcode":"06840",
    "sg:province":"NY",
    "wof:name":"Sb Designs",
    "wof:placetype":"venue"
},
  "geometry": {"coordinates":[-73.499094,41.142351],"type":"Point"}
}