{
  "type": "Feature",
  "properties": {
    "iso:country":"US",
    "sg:address":"55 Rte 111",
    "sg:city":"Smithtown",
    "sg:classifiers":[
        {
            "category":"Food & Beverages",
            "subcategory":"Candy",
            "type":"Retail Goods"
        }
    ],
    "sg:phone":"+1   ",
    "sg:postcode":"11787",
    "sg:province":"NY",
    "wof:name":"Sweet Dreams Candy Shoppe",
    "wof:placetype":"venue"
},
  "geometry": {"coordinates":[-73.18781799999999,40.850145],"type":"Point"}
}