{
  "type": "Feature",
  "properties": {
    "iso:country":"US",
    "sg:address":"120 New York Ave",
    "sg:city":"Westbury",
    "sg:classifiers":[
        {
            "category":"Wholesale",
            "subcategory":"Apparel",
            "type":"Manufacturing & Wholesale Goods"
        }
    ],
    "sg:phone":"+1 212 679 0210",
    "sg:postcode":"11590",
    "sg:province":"NY",
    "wof:name":"Imported Craft",
    "wof:placetype":"venue"
},
  "geometry": {"coordinates":[-73.560473,40.757149],"type":"Point"}
}