{
  "type": "Feature",
  "properties": {
    "addr:full":"3255 E Genesee Street Rd Auburn NY 13021",
    "addr:housenumber":"3255",
    "addr:postcode":"13021",
    "addr:street":"E Genesee Street Rd",
    "iso:country":"US",
    "sg:address":"3255 E Genesee Street Rd",
    "sg:city":"Auburn",
    "sg:classifiers":[
        {
            "category":"Professional",
            "subcategory":"Management & Consulting",
            "type":"Services"
        },
        {
            "category":"Professional",
            "subcategory":"Engineering",
            "type":"Services"
        }
    ],
    "sg:phone":"+1 315 255 0212",
    "sg:postcode":"13021",
    "sg:province":"NY",
    "sg:tags":[
        "consultant",
        "engineer"
    ],
    "wof:name":"Cny Business Advisors",
    "wof:placetype":"venue"
},
  "geometry": {"coordinates":[-76.525274,42.936356],"type":"Point"}
}