{
  "type": "Feature",
  "properties": {
    "iso:country":"US",
    "sg:address":"628 E Main St Ste C",
    "sg:city":"Palmyra",
    "sg:classifiers":[
        {
            "category":"Professional",
            "subcategory":"Business Services",
            "type":"Services"
        },
        {
            "category":"Government",
            "subcategory":"Post Office",
            "type":"Public Place"
        }
    ],
    "sg:phone":"+1 315 597 6655",
    "sg:postcode":"14522",
    "sg:province":"NY",
    "sg:tags":[
        "delivery",
        "messenger",
        "courier"
    ],
    "wof:name":"Timesaver Courier Journal",
    "wof:placetype":"venue"
},
  "geometry": {"coordinates":[-77.217781,43.061127],"type":"Point"}
}