{
  "type": "Feature",
  "properties": {
    "addr:full":"81 1st St Brooklyn NY 11231",
    "addr:housenumber":"81",
    "addr:postcode":"11231",
    "addr:street":"1St St",
    "iso:country":"US",
    "sg:address":"81 1st St",
    "sg:city":"Brooklyn",
    "sg:classifiers":[
        {
            "category":"Social Services",
            "type":"Services"
        }
    ],
    "sg:phone":"+1 718 522 1143",
    "sg:postcode":"11231",
    "sg:province":"NY",
    "wof:name":"Ascrmd Lubin Center",
    "wof:placetype":"venue"
},
  "geometry": {"coordinates":[-73.98985399999999,40.677788],"type":"Point"}
}