{
  "type": "Feature",
  "properties": {
    "addr:full":"13631 41st Ave Flushing NY 11355",
    "addr:housenumber":"13631",
    "addr:postcode":"11355",
    "addr:street":"41St Ave",
    "iso:country":"US",
    "sg:address":"13631 41st Ave",
    "sg:city":"Flushing",
    "sg:classifiers":[
        {
            "category":"Shopping",
            "subcategory":"Crafts & Fabrics",
            "type":"Retail Goods"
        }
    ],
    "sg:phone":"+1 718 886 2660",
    "sg:postcode":"11355",
    "sg:province":"NY",
    "sg:tags":[
        "art"
    ],
    "wof:name":"New York Culture Exchange",
    "wof:placetype":"venue"
},
  "geometry": {"coordinates":[-73.828965,40.758844],"type":"Point"}
}