{
  "type": "Feature",
  "properties": {
    "iso:country":"US",
    "sg:address":"20408 Hillside Ave",
    "sg:city":"Hollis",
    "sg:classifiers":[
        {
            "category":"Restaurant",
            "type":"Food & Drink"
        }
    ],
    "sg:menulink":"http://www.allmenus.com/ny/queens/60839-golden-krust/menu/",
    "sg:phone":"+1 718 464 6602",
    "sg:postcode":"11423",
    "sg:province":"NY",
    "sg:tags":[
        "caribbean"
    ],
    "wof:name":"Golden Krust",
    "wof:placetype":"venue"
},
  "geometry": {"coordinates":[-73.761028,40.720319],"type":"Point"}
}