{
  "type": "Feature",
  "properties": {
    "addr:full":"603 W 45th St New York NY 10024",
    "addr:housenumber":"603",
    "addr:postcode":"10024",
    "addr:street":"W 45Th St",
    "iso:country":"US",
    "sg:address":"603 W 45th St",
    "sg:city":"New York",
    "sg:classifiers":[
        {
            "category":"Restaurant",
            "type":"Food & Drink"
        }
    ],
    "sg:phone":"+1 212 245 0002",
    "sg:postcode":"10024",
    "sg:province":"NY",
    "sg:tags":[
        "steakhouse"
    ],
    "wof:name":"Robert's Steakhouse",
    "wof:placetype":"venue"
},
  "geometry": {"coordinates":[-73.99695699999999,40.762777],"type":"Point"}
}