{
  "type": "Feature",
  "properties": {
    "iso:country":"US",
    "sg:address":"315 King St",
    "sg:city":"Port Chester",
    "sg:classifiers":[
        {
            "category":"Building & Trades",
            "subcategory":"Construction",
            "type":"Services"
        }
    ],
    "sg:phone":"+1 914 934 5932",
    "sg:postcode":"10573",
    "sg:province":"NY",
    "sg:tags":[
        "tennis",
        "court"
    ],
    "wof:name":"National Platform Tennis Inc",
    "wof:placetype":"venue"
},
  "geometry": {"coordinates":[-73.664598,41.008088],"type":"Point"}
}