{
  "type": "Feature",
  "properties": {
    "addr:full":"336 Harris Hill Rd Williamsville NY 14221",
    "addr:housenumber":"336",
    "addr:postcode":"14221",
    "addr:street":"Harris Hill Rd",
    "iso:country":"US",
    "sg:address":"336 Harris Hill Rd",
    "sg:city":"Williamsville",
    "sg:classifiers":[
        {
            "category":"Wholesale",
            "subcategory":"Metals & Minerals",
            "type":"Manufacturing & Wholesale Goods"
        }
    ],
    "sg:phone":"+1 716 565 3746",
    "sg:postcode":"14221",
    "sg:province":"NY",
    "sg:tags":[
        "steel",
        "warehouse"
    ],
    "wof:name":"Castle Metals",
    "wof:placetype":"venue"
},
  "geometry": {"coordinates":[-78.677173,42.949647],"type":"Point"}
}