{
  "type": "Feature",
  "properties": {
    "iso:country":"US",
    "sg:address":"292 E Montauk Hwy",
    "sg:city":"Lindenhurst",
    "sg:classifiers":[
        {
            "category":"Retail",
            "subcategory":"Self-service Laundry",
            "type":"Services"
        }
    ],
    "sg:phone":"+1 631 226 4623",
    "sg:postcode":"11757",
    "sg:province":"NY",
    "wof:name":"Superior Wash",
    "wof:placetype":"venue"
},
  "geometry": {"coordinates":[-73.356154,40.682882],"type":"Point"}
}