{
  "type": "Feature",
  "properties": {
    "addr:full":"600 Mother Gaston Blvd Brooklyn NY 11212",
    "addr:housenumber":"600",
    "addr:postcode":"11212",
    "addr:street":"Mother Gaston Blvd",
    "iso:country":"US",
    "sg:address":"600 Mother Gaston Blvd",
    "sg:city":"Brooklyn",
    "sg:classifiers":[
        {
            "category":"Organizations",
            "subcategory":"Religious Organization",
            "type":"Services"
        }
    ],
    "sg:phone":"+1   ",
    "sg:postcode":"11212",
    "sg:province":"NY",
    "wof:name":"Brownsville Commuity Church",
    "wof:placetype":"venue"
},
  "geometry": {"coordinates":[-73.90534100000001,40.663573],"type":"Point"}
}