{
  "type": "Feature",
  "properties": {
    "iso:country":"US",
    "sg:address":"2 E 2nd St",
    "sg:city":"Jamestown",
    "sg:classifiers":[
        {
            "category":"Professional",
            "subcategory":"Lawyer & Legal Services",
            "type":"Services"
        }
    ],
    "sg:phone":"+1 716 483 1760",
    "sg:postcode":"14701",
    "sg:province":"NY",
    "sg:tags":[
        "attorney"
    ],
    "sg:website":"www.jeffreyfreedman.com",
    "wof:name":"Jeffrey Freedman Attorneys",
    "wof:placetype":"venue"
},
  "geometry": {"coordinates":[-79.24050099999999,42.095574],"type":"Point"}
}