{
  "type": "Feature",
  "properties": {
    "iso:country":"US",
    "sg:address":"112 Wheatland Center Rd",
    "sg:city":"Caledonia",
    "sg:classifiers":[
        {
            "category":"Farming",
            "subcategory":"Farm",
            "type":"Manufacturing & Wholesale Goods"
        }
    ],
    "sg:phone":"+1 585 538 4915",
    "sg:postcode":"14423",
    "sg:province":"NY",
    "sg:tags":[
        "cash",
        "crop"
    ],
    "wof:name":"Stein Paul E & Sons LLC",
    "wof:placetype":"venue"
},
  "geometry": {"coordinates":[-77.830461,42.977863],"type":"Point"}
}