{
  "type": "Feature",
  "properties": {
    "iso:country":"US",
    "sg:address":"10 Hayrake Ln",
    "sg:city":"Chappaqua",
    "sg:classifiers":[
        {
            "category":"Professional",
            "subcategory":"Management & Consulting",
            "type":"Services"
        }
    ],
    "sg:phone":"+1 914 238 3737",
    "sg:postcode":"10514",
    "sg:province":"NY",
    "sg:tags":[
        "party",
        "planning"
    ],
    "sg:website":"www.hiphiphooray.com",
    "wof:name":"Bubble Gum Party Entertainment",
    "wof:placetype":"venue"
},
  "geometry": {"coordinates":[-73.767943,41.185574],"type":"Point"}
}