{
  "type": "Feature",
  "properties": {
    "iso:country":"US",
    "sg:address":"386 Utica Ave",
    "sg:city":"Brooklyn",
    "sg:classifiers":[
        {
            "category":"Manufacturing",
            "subcategory":"Printing",
            "type":"Manufacturing & Wholesale Goods"
        }
    ],
    "sg:phone":"+1 718 774 8882",
    "sg:postcode":"11213",
    "sg:province":"NY",
    "sg:tags":[
        "social",
        "commercial",
        "reproduction",
        "offset"
    ],
    "wof:name":"7 Star Printing Co",
    "wof:placetype":"venue"
},
  "geometry": {"coordinates":[-73.931605,40.664466],"type":"Point"}
}