{
  "type": "Feature",
  "properties": {
    "iso:country":"US",
    "sg:address":"115 Broadway",
    "sg:city":"New York",
    "sg:classifiers":[
        {
            "category":"Professional",
            "subcategory":"Lawyer & Legal Services",
            "type":"Services"
        }
    ],
    "sg:phone":"+1 212 577 2800",
    "sg:postcode":"10006",
    "sg:province":"NY",
    "wof:name":"Allan Sexter & David Warmflash",
    "wof:placetype":"venue"
},
  "geometry": {"coordinates":[-74.010846,40.708797],"type":"Point"}
}