{
  "type": "Feature",
  "properties": {
    "addr:full":"4201 8 Ave Brooklyn NY 11232",
    "addr:housenumber":"4201",
    "addr:postcode":"11232",
    "addr:street":"8 Ave",
    "iso:country":"US",
    "sg:address":"4201 8 Ave",
    "sg:city":"Brooklyn",
    "sg:classifiers":[
        {
            "category":"Restaurant",
            "type":"Food & Drink"
        }
    ],
    "sg:phone":"+1 718 436 6002",
    "sg:postcode":"11232",
    "sg:province":"NY",
    "sg:tags":[
        "chinese"
    ],
    "wof:name":"New Kim Wei Kitchen",
    "wof:placetype":"venue"
},
  "geometry": {"coordinates":[-73.998876,40.645337],"type":"Point"}
}