{
  "type": "Feature",
  "properties": {
    "addr:full":"280 Vandenburgh Point Rd Gloversville NY 12078",
    "addr:housenumber":"280",
    "addr:postcode":"12078",
    "addr:street":"Vandenburgh Point Rd",
    "iso:country":"US",
    "sg:address":"280 Vandenburgh Point Rd",
    "sg:city":"Gloversville",
    "sg:classifiers":[
        {
            "category":"Manufacturing",
            "subcategory":"Buildings",
            "type":"Manufacturing & Wholesale Goods"
        },
        {
            "category":"Building & Trades",
            "subcategory":"Construction",
            "type":"Services"
        }
    ],
    "sg:phone":"+1 518 469 4971",
    "sg:postcode":"12078",
    "sg:province":"NY",
    "sg:tags":[
        "home",
        "builder",
        "contractor"
    ],
    "wof:name":"Preferred Salisburg Builders, Inc.",
    "wof:placetype":"venue"
},
  "geometry": {"coordinates":[-74.24370999999999,43.082588],"type":"Point"}
}