{
  "type": "Feature",
  "properties": {
    "iso:country":"US",
    "sg:address":"30 Jericho Tpke",
    "sg:city":"Jericho",
    "sg:classifiers":[
        {
            "category":"Wholesale",
            "subcategory":"Electrical",
            "type":"Manufacturing & Wholesale Goods"
        }
    ],
    "sg:phone":"+1 516 876 2003",
    "sg:postcode":"11753",
    "sg:province":"NY",
    "sg:tags":[
        "electronic"
    ],
    "wof:name":"Enterprise Solutions Group",
    "wof:placetype":"venue"
},
  "geometry": {"coordinates":[-73.55577700000001,40.781733],"type":"Point"}
}