{
  "type": "Feature",
  "properties": {
    "iso:country":"US",
    "sg:address":"5020 Munro Rd",
    "sg:city":"Camillus",
    "sg:classifiers":[
        {
            "category":"Building & Trades",
            "subcategory":"Construction",
            "type":"Services"
        }
    ],
    "sg:phone":"+1 315 673 1868",
    "sg:postcode":"13031",
    "sg:province":"NY",
    "sg:tags":[
        "home",
        "family",
        "patio",
        "rooms"
    ],
    "wof:name":"S & R Custom Homes Inc",
    "wof:placetype":"venue"
},
  "geometry": {"coordinates":[-76.30484800000001,43.019129],"type":"Point"}
}