{
  "type": "Feature",
  "properties": {
    "iso:country":"US",
    "sg:address":"204 Garfield Pl",
    "sg:city":"Brooklyn",
    "sg:classifiers":[
        {
            "category":"Restaurant",
            "type":"Food & Drink"
        }
    ],
    "sg:phone":"+1 718 369 2681",
    "sg:postcode":"11215",
    "sg:province":"NY",
    "sg:tags":[
        "mexican"
    ],
    "wof:name":"Rancho Alegre",
    "wof:placetype":"venue"
},
  "geometry": {"coordinates":[-73.977097,40.672298],"type":"Point"}
}