{
  "type": "Feature",
  "properties": {
    "iso:country":"US",
    "sg:address":"99 Oak St",
    "sg:city":"Harrison",
    "sg:classifiers":[
        {
            "category":"Building & Trades",
            "subcategory":"Landscaping Services",
            "type":"Services"
        }
    ],
    "sg:phone":"+1 914 835 0605",
    "sg:postcode":"10528",
    "sg:province":"NY",
    "sg:tags":[
        "landscape"
    ],
    "wof:name":"Ferraro Joe Ldscpg Lawn Mntnce",
    "wof:placetype":"venue"
},
  "geometry": {"coordinates":[-73.715743,40.964157],"type":"Point"}
}