{
  "type": "Feature",
  "properties": {
    "addr:full":"39-01 Queens Blvd Sunnyside NY 11104",
    "addr:housenumber":"39-01",
    "addr:postcode":"11104",
    "addr:street":"Queens Blvd",
    "iso:country":"US",
    "sg:address":"39-01 Queens Blvd",
    "sg:city":"Sunnyside",
    "sg:classifiers":[
        {
            "category":"Sports & Exercise",
            "subcategory":"Gym",
            "type":"Entertainment"
        },
        {
            "category":"Arena",
            "subcategory":"Sports Club",
            "type":"Entertainment"
        }
    ],
    "sg:phone":"+1 718 361 2254",
    "sg:postcode":"11104",
    "sg:province":"NY",
    "sg:website":"www.mysportsclubs.com/clubsched/...",
    "wof:name":"New York Sports Club",
    "wof:placetype":"venue"
},
  "geometry": {"coordinates":[-73.92608300000001,40.744175],"type":"Point"}
}