{
  "type": "Feature",
  "properties": {
    "addr:full":"1346 Broadway Brooklyn NY 11221",
    "addr:housenumber":"1346",
    "addr:postcode":"11221",
    "addr:street":"Broadway",
    "iso:country":"US",
    "sg:address":"1346 Broadway",
    "sg:city":"Brooklyn",
    "sg:classifiers":[
        {
            "category":"Restaurant",
            "type":"Food & Drink"
        }
    ],
    "sg:phone":"+1 718 919 9500",
    "sg:postcode":"11221",
    "sg:province":"NY",
    "wof:name":"El Nuevo Yayo Restaurant 2",
    "wof:placetype":"venue"
},
  "geometry": {"coordinates":[-73.922072,40.68949],"type":"Point"}
}