{
  "type": "Feature",
  "properties": {
    "addr:full":"3913 Oneida St New Hartford NY 13413",
    "addr:housenumber":"3913",
    "addr:postcode":"13413",
    "addr:street":"Oneida St",
    "iso:country":"US",
    "sg:address":"3913 Oneida St",
    "sg:city":"New Hartford",
    "sg:classifiers":[
        {
            "category":"Restaurant",
            "type":"Food & Drink"
        }
    ],
    "sg:phone":"+1   ",
    "sg:postcode":"13413",
    "sg:province":"NY",
    "sg:tags":[
        "eating"
    ],
    "wof:name":"China House",
    "wof:placetype":"venue"
},
  "geometry": {"coordinates":[-75.271154,43.054668],"type":"Point"}
}