{
  "type": "Feature",
  "properties": {
    "addr:full":"1701 79th St Brooklyn NY 11214",
    "addr:housenumber":"1701",
    "addr:postcode":"11214",
    "addr:street":"79Th St",
    "iso:country":"US",
    "sg:address":"1701 79th St",
    "sg:city":"Brooklyn",
    "sg:classifiers":[
        {
            "category":"Professional",
            "subcategory":"Accounting & Tax Preparation",
            "type":"Services"
        }
    ],
    "sg:phone":"+1 718 837 8656",
    "sg:postcode":"11214",
    "sg:province":"NY",
    "sg:tags":[
        "accountant"
    ],
    "wof:name":"Vincent Reale Accountant",
    "wof:placetype":"venue"
},
  "geometry": {"coordinates":[-73.998313,40.611084],"type":"Point"}
}