{
  "type": "Feature",
  "properties": {
    "iso:country":"US",
    "sg:address":"5435 Trinity Ave",
    "sg:city":"Lowville",
    "sg:classifiers":[
        {
            "category":"Building & Trades",
            "subcategory":"Electrical",
            "type":"Services"
        }
    ],
    "sg:phone":"+1 315 376 3937",
    "sg:postcode":"13367",
    "sg:province":"NY",
    "sg:tags":[
        "electric",
        "contractor"
    ],
    "wof:name":"S & L Electric",
    "wof:placetype":"venue"
},
  "geometry": {"coordinates":[-75.492982,43.788502],"type":"Point"}
}