{
  "type": "Feature",
  "properties": {
    "addr:full":"63 Lockwood Ave Yonkers NY 10701",
    "addr:housenumber":"63",
    "addr:postcode":"10701",
    "addr:street":"Lockwood Ave",
    "iso:country":"US",
    "sg:address":"63 Lockwood Ave",
    "sg:city":"Yonkers",
    "sg:classifiers":[
        {
            "category":"Retail",
            "subcategory":"Repair Shop",
            "type":"Services"
        }
    ],
    "sg:phone":"+1 914 218 2218",
    "sg:postcode":"10701",
    "sg:province":"NY",
    "sg:tags":[
        "lock",
        "locksmith"
    ],
    "wof:name":"USA Locksmith",
    "wof:placetype":"venue"
},
  "geometry": {"coordinates":[-73.873105,40.947959],"type":"Point"}
}