{
  "type": "Feature",
  "properties": {
    "addr:full":"1314 Ave L Brooklyn NY 11230",
    "addr:postcode":"11230",
    "addr:street":"1314 Ave L",
    "iso:country":"US",
    "sg:address":"1314 Ave L",
    "sg:city":"Brooklyn",
    "sg:classifiers":[
        {
            "category":"Organizations",
            "subcategory":"Religious Organization",
            "type":"Services"
        }
    ],
    "sg:phone":"+1 718 338 1980",
    "sg:postcode":"11230",
    "sg:province":"NY",
    "sg:tags":[
        "clergy"
    ],
    "wof:name":"Philip M Barasch",
    "wof:placetype":"venue"
},
  "geometry": {"coordinates":[-73.96150400000001,40.620209],"type":"Point"}
}