{
  "type": "Feature",
  "properties": {
    "iso:country":"US",
    "sg:address":"3109 Sedgwick Ave",
    "sg:city":"Bronx",
    "sg:classifiers":[
        {
            "category":"Professional",
            "subcategory":"Lawyer & Legal Services",
            "type":"Services"
        }
    ],
    "sg:phone":"+1 718 220 1400",
    "sg:postcode":"10463",
    "sg:province":"NY",
    "sg:tags":[
        "attorney"
    ],
    "wof:name":"Villaverde Legal Svc",
    "wof:placetype":"venue"
},
  "geometry": {"coordinates":[-73.898166,40.878442],"type":"Point"}
}