{
  "type": "Feature",
  "properties": {
    "iso:country":"US",
    "sg:address":"978 Cole Hill Rd",
    "sg:city":"East Berne",
    "sg:classifiers":[
        {
            "category":"Local Transit",
            "type":"Transportation"
        }
    ],
    "sg:phone":"+1 518 872 9111",
    "sg:postcode":"12023",
    "sg:province":"NY",
    "sg:tags":[
        "passenger",
        "ambulance"
    ],
    "wof:name":"Helderberg Ambulance Squad",
    "wof:placetype":"venue"
},
  "geometry": {"coordinates":[-74.08936300000001,42.614161],"type":"Point"}
}