{
  "type": "Feature",
  "properties": {
    "addr:full":"114 Clinton St Brooklyn NY 11201",
    "addr:housenumber":"114",
    "addr:postcode":"11201",
    "addr:street":"Clinton St",
    "iso:country":"US",
    "sg:address":"114 Clinton St",
    "sg:city":"Brooklyn",
    "sg:classifiers":[
        {
            "category":"Professional",
            "subcategory":"Accounting & Tax Preparation",
            "type":"Services"
        }
    ],
    "sg:phone":"+1 718 624 2828",
    "sg:postcode":"11201",
    "sg:province":"NY",
    "sg:tags":[
        "accountant"
    ],
    "wof:name":"Peter J Simone",
    "wof:placetype":"venue"
},
  "geometry": {"coordinates":[-73.99300599999999,40.693338],"type":"Point"}
}