{
  "type": "Feature",
  "properties": {
    "addr:full":"1234 Hicksville Rd Seaford NY 11758",
    "addr:housenumber":"1234",
    "addr:postcode":"11758",
    "addr:street":"Hicksville Rd",
    "iso:country":"US",
    "sg:address":"1234 Hicksville Rd",
    "sg:city":"Seaford",
    "sg:classifiers":[
        {
            "category":"Personal",
            "subcategory":"Beauty Salon",
            "type":"Services"
        }
    ],
    "sg:phone":"+1 516 798 9744",
    "sg:postcode":"11758",
    "sg:province":"NY",
    "wof:name":"Profiles Hair Designers",
    "wof:placetype":"venue"
},
  "geometry": {"coordinates":[-73.48291,40.707213],"type":"Point"}
}