{
  "type": "Feature",
  "properties": {
    "addr:full":"901 Broadway New York NY 10003",
    "addr:housenumber":"901",
    "addr:postcode":"10003",
    "addr:street":"Broadway",
    "iso:country":"US",
    "sg:address":"901 Broadway",
    "sg:city":"New York",
    "sg:classifiers":[
        {
            "category":"Retail",
            "subcategory":"Repair Shop",
            "type":"Services"
        }
    ],
    "sg:phone":"+1 646 237 1302",
    "sg:postcode":"10003",
    "sg:province":"NY",
    "sg:tags":[
        "lock",
        "locksmith"
    ],
    "wof:name":"Emergency Locksmith Anytimes",
    "wof:placetype":"venue"
},
  "geometry": {"coordinates":[-73.989952,40.738488],"type":"Point"}
}