{
  "type": "Feature",
  "properties": {
    "addr:full":"1115 31st Drive Astoria NY 11106",
    "addr:housenumber":"1115",
    "addr:postcode":"11106",
    "addr:street":"31St Drive",
    "iso:country":"US",
    "sg:address":"1115 31st Drive",
    "sg:city":"Astoria",
    "sg:classifiers":[
        {
            "category":"Building & Trades",
            "subcategory":"Construction",
            "type":"Services"
        }
    ],
    "sg:phone":"+1 718 274 2231",
    "sg:postcode":"11106",
    "sg:province":"NY",
    "sg:tags":[
        "contractor"
    ],
    "wof:name":"Dave Kitchen Cabinets",
    "wof:placetype":"venue"
},
  "geometry": {"coordinates":[-73.93471099999999,40.768203],"type":"Point"}
}