{
  "type": "Feature",
  "properties": {
    "addr:full":"10 Sheridan Dr Tonawanda NY 14150",
    "addr:housenumber":"10",
    "addr:postcode":"14150",
    "addr:street":"Sheridan Dr",
    "iso:country":"US",
    "sg:address":"10 Sheridan Dr",
    "sg:city":"Tonawanda",
    "sg:classifiers":[
        {
            "category":"Professional",
            "subcategory":"Employment Agencies",
            "type":"Services"
        }
    ],
    "sg:phone":"+1 716 940 5239",
    "sg:postcode":"14150",
    "sg:province":"NY",
    "sg:tags":[
        "help",
        "supply"
    ],
    "wof:name":"Houses Loading Service Inc",
    "wof:placetype":"venue"
},
  "geometry": {"coordinates":[-78.911884,42.973694],"type":"Point"}
}