{
  "type": "Feature",
  "properties": {
    "addr:full":"4450 Lake Ave Rochester NY 14612",
    "addr:housenumber":"4450",
    "addr:postcode":"14612",
    "addr:street":"Lake Ave",
    "iso:country":"US",
    "sg:address":"4450 Lake Ave",
    "sg:city":"Rochester",
    "sg:classifiers":[
        {
            "category":"Restaurant",
            "type":"Food & Drink"
        }
    ],
    "sg:menulink":"http://www.allmenus.com/ny/rochester/145062-subway/menu/",
    "sg:phone":"+1 585 663 8580",
    "sg:postcode":"14612",
    "sg:province":"NY",
    "sg:tags":[
        "american",
        "sandwich"
    ],
    "wof:name":"Subway",
    "wof:placetype":"venue"
},
  "geometry": {"coordinates":[-77.612709,43.251828],"type":"Point"}
}