{
  "type": "Feature",
  "properties": {
    "addr:full":"115 Lawrence St Brooklyn NY 11201",
    "addr:housenumber":"115",
    "addr:postcode":"11201",
    "addr:street":"Lawrence St",
    "iso:country":"US",
    "sg:address":"115 Lawrence St",
    "sg:city":"Brooklyn",
    "sg:classifiers":[
        {
            "category":"Professional",
            "subcategory":"Accounting & Tax Preparation",
            "type":"Services"
        }
    ],
    "sg:phone":"+1 718 522 7260",
    "sg:postcode":"11201",
    "sg:province":"NY",
    "sg:tags":[
        "return",
        "filing"
    ],
    "wof:name":"Compu-Finance",
    "wof:placetype":"venue"
},
  "geometry": {"coordinates":[-73.986178,40.692672],"type":"Point"}
}