{
  "type": "Feature",
  "properties": {
    "addr:full":"200 Terminal Drive Plainview  NY 11803",
    "addr:housenumber":"200",
    "addr:postcode":"11803",
    "addr:street":"Terminal Drive",
    "iso:country":"US",
    "sg:address":"200 Terminal Drive",
    "sg:city":"Plainview ",
    "sg:classifiers":[
        {
            "category":"Professional",
            "subcategory":"Computer Services",
            "type":"Services"
        }
    ],
    "sg:phone":"+1 800 256 6102",
    "sg:postcode":"11803",
    "sg:province":"NY",
    "sg:tags":[
        "vitamins",
        "health-products"
    ],
    "sg:website":"http://www.purityproducts.com/",
    "wof:name":"Purity Products",
    "wof:placetype":"venue"
},
  "geometry": {"coordinates":[-73.46948999999999,40.792337],"type":"Point"}
}