{
  "type": "Feature",
  "properties": {
    "iso:country":"US",
    "sg:address":"22 Van Derveer St",
    "sg:city":"Amsterdam",
    "sg:classifiers":[
        {
            "category":"Professional",
            "subcategory":"Lawyer & Legal Services",
            "type":"Services"
        }
    ],
    "sg:phone":"+1 518 842 1812",
    "sg:postcode":"12010",
    "sg:province":"NY",
    "sg:tags":[
        "attorney"
    ],
    "wof:name":"Eliot King",
    "wof:placetype":"venue"
},
  "geometry": {"coordinates":[-74.182705,42.942644],"type":"Point"}
}