{
  "type": "Feature",
  "properties": {
    "iso:country":"US",
    "sg:address":"184 N Main St",
    "sg:city":"Liberty",
    "sg:classifiers":[
        {
            "category":"Health Services",
            "subcategory":"Doctor",
            "type":"Services"
        }
    ],
    "sg:phone":"+1   ",
    "sg:postcode":"12754",
    "sg:province":"NY",
    "wof:name":"Stephen Klafter DDS",
    "wof:placetype":"venue"
},
  "geometry": {"coordinates":[-74.747449,41.803383],"type":"Point"}
}