{
  "type": "Feature",
  "properties": {
    "addr:full":"1551 Jefferson Ave Buffalo NY 14208",
    "addr:housenumber":"1551",
    "addr:postcode":"14208",
    "addr:street":"Jefferson Ave",
    "iso:country":"US",
    "sg:address":"1551 Jefferson Ave",
    "sg:city":"Buffalo",
    "sg:classifiers":[
        {
            "category":"Organizations",
            "subcategory":"Religious Organization",
            "type":"Services"
        }
    ],
    "sg:phone":"+1   ",
    "sg:postcode":"14208",
    "sg:province":"NY",
    "wof:name":"Unity Church Of God & Christ",
    "wof:placetype":"venue"
},
  "geometry": {"coordinates":[-78.853921,42.917625],"type":"Point"}
}