{
  "type": "Feature",
  "properties": {
    "addr:full":"406 Ave U Brooklyn NY 11223",
    "addr:housenumber":"406",
    "addr:postcode":"11223",
    "addr:street":"Ave U",
    "iso:country":"US",
    "sg:address":"406 Ave U",
    "sg:city":"Brooklyn",
    "sg:classifiers":[
        {
            "category":"Wholesale",
            "subcategory":"Medical Equipment & Supplies",
            "type":"Manufacturing & Wholesale Goods"
        }
    ],
    "sg:phone":"+1 718 333 2227",
    "sg:postcode":"11223",
    "sg:province":"NY",
    "sg:tags":[
        "physician",
        "surgeon"
    ],
    "wof:name":"First Response Med Supls Inc",
    "wof:placetype":"venue"
},
  "geometry": {"coordinates":[-73.969076,40.59735],"type":"Point"}
}