{
  "type": "Feature",
  "properties": {
    "addr:full":"117 State St Westbury NY 11590",
    "addr:housenumber":"117",
    "addr:postcode":"11590",
    "addr:street":"State St",
    "iso:country":"US",
    "sg:address":"117 State St",
    "sg:city":"Westbury",
    "sg:classifiers":[
        {
            "category":"Manufacturing",
            "subcategory":"Retail Goods",
            "type":"Manufacturing & Wholesale Goods"
        }
    ],
    "sg:phone":"+1   ",
    "sg:postcode":"11590",
    "sg:province":"NY",
    "sg:tags":[
        "pencil",
        "lead",
        "mfg"
    ],
    "wof:name":"Pencoa",
    "wof:placetype":"venue"
},
  "geometry": {"coordinates":[-73.559083,40.759031],"type":"Point"}
}