{
  "type": "Feature",
  "properties": {
    "addr:full":"2800 White Plains Rd Bronx NY 10467",
    "addr:housenumber":"2800",
    "addr:postcode":"10467",
    "addr:street":"White Plains Rd",
    "iso:country":"US",
    "sg:address":"2800 White Plains Rd",
    "sg:city":"Bronx",
    "sg:classifiers":[
        {
            "category":"Retail",
            "subcategory":"Auto Rental",
            "type":"Services"
        }
    ],
    "sg:phone":"+1 718 515 6262",
    "sg:postcode":"10467",
    "sg:province":"NY",
    "sg:tags":[
        "renting",
        "truck",
        "leasing"
    ],
    "sg:website":"www.uhaul.com",
    "wof:name":"U-Haul Co",
    "wof:placetype":"venue"
},
  "geometry": {"coordinates":[-73.86725800000001,40.865995],"type":"Point"}
}