{
  "type": "Feature",
  "properties": {
    "iso:country":"US",
    "sg:address":"55 N Ocean Ave",
    "sg:city":"Freeport",
    "sg:classifiers":[
        {
            "category":"Health Services",
            "subcategory":"Clinic",
            "type":"Services"
        }
    ],
    "sg:phone":"+1 516 223 9570",
    "sg:postcode":"11520",
    "sg:province":"NY",
    "sg:tags":[
        "residence",
        "program",
        "community"
    ],
    "wof:name":"Project Real",
    "wof:placetype":"venue"
},
  "geometry": {"coordinates":[-73.58735799999999,40.658268],"type":"Point"}
}