{
  "type": "Feature",
  "properties": {
    "addr:full":"21 David St Staten Island NY 10308",
    "addr:housenumber":"21",
    "addr:postcode":"10308",
    "addr:street":"David St",
    "iso:country":"US",
    "sg:address":"21 David St",
    "sg:city":"Staten Island",
    "sg:classifiers":[
        {
            "category":"Building & Trades",
            "subcategory":"Construction",
            "type":"Services"
        }
    ],
    "sg:phone":"+1 718 227 1200",
    "sg:postcode":"10308",
    "sg:province":"NY",
    "sg:tags":[
        "painter"
    ],
    "wof:name":"J P Interiors",
    "wof:placetype":"venue"
},
  "geometry": {"coordinates":[-74.148916,40.543272],"type":"Point"}
}