{
  "type": "Feature",
  "properties": {
    "iso:country":"US",
    "sg:address":"430 Balltown Rd",
    "sg:city":"Schenectady",
    "sg:classifiers":[
        {
            "category":"Shopping",
            "subcategory":"Shoes",
            "type":"Retail Goods"
        }
    ],
    "sg:phone":"+1 518 377 9185",
    "sg:postcode":"12304",
    "sg:province":"NY",
    "wof:name":"Payless Shoe Source",
    "wof:placetype":"venue"
},
  "geometry": {"coordinates":[-73.89343599999999,42.774025],"type":"Point"}
}