{
  "type": "Feature",
  "properties": {
    "iso:country":"US",
    "sg:address":"521 State Route 17M",
    "sg:city":"Monroe",
    "sg:classifiers":[
        {
            "category":"Retail",
            "subcategory":"Pet Boarding",
            "type":"Services"
        }
    ],
    "sg:phone":"+1 845 782 0412",
    "sg:postcode":"10950",
    "sg:province":"NY",
    "sg:tags":[
        "boarding/pet",
        "sitting"
    ],
    "wof:name":"Bilt-Well Fence Company",
    "wof:placetype":"venue"
},
  "geometry": {"coordinates":[-74.179001,41.320099],"type":"Point"}
}