{
  "type": "Feature",
  "properties": {
    "addr:full":"4528 Parsons Blvd Flushing NY 11355",
    "addr:housenumber":"4528",
    "addr:postcode":"11355",
    "addr:street":"Parsons Blvd",
    "iso:country":"US",
    "sg:address":"4528 Parsons Blvd",
    "sg:city":"Flushing",
    "sg:classifiers":[
        {
            "category":"Health Services",
            "subcategory":"Doctor",
            "type":"Services"
        }
    ],
    "sg:phone":"+1 718 961 5677",
    "sg:postcode":"11355",
    "sg:province":"NY",
    "wof:name":"Asadourian Armand MD",
    "wof:placetype":"venue"
},
  "geometry": {"coordinates":[-73.814903,40.7551],"type":"Point"}
}