{
  "type": "Feature",
  "properties": {
    "addr:full":"101 Park Ave Lowr G New York NY 10178",
    "addr:housenumber":"101",
    "addr:postcode":"10178",
    "addr:street":"Park Ave Lowr G",
    "iso:country":"US",
    "sg:address":"101 Park Ave Lowr G",
    "sg:city":"New York",
    "sg:classifiers":[
        {
            "category":"Deli",
            "type":"Food & Drink"
        },
        {
            "category":"Food & Beverages",
            "subcategory":"Bakery",
            "type":"Retail Goods"
        }
    ],
    "sg:phone":"+1 212 682 9009",
    "sg:postcode":"10178",
    "sg:province":"NY",
    "sg:tags":[
        "sandwich"
    ],
    "wof:name":"Cafe 101",
    "wof:placetype":"venue"
},
  "geometry": {"coordinates":[-73.978337,40.750705],"type":"Point"}
}