{
  "type": "Feature",
  "properties": {
    "iso:country":"US",
    "sg:address":"2067 9th Ave",
    "sg:city":"Ronkonkoma",
    "sg:classifiers":[
        {
            "category":"Manufacturing",
            "subcategory":"Textiles",
            "type":"Manufacturing & Wholesale Goods"
        },
        {
            "category":"Manufacturing",
            "subcategory":"Glass & Minerals",
            "type":"Manufacturing & Wholesale Goods"
        }
    ],
    "sg:phone":"+1 631 467 3369",
    "sg:postcode":"11779",
    "sg:province":"NY",
    "sg:tags":[
        "fabricator",
        "mill",
        "fiber",
        "fabric"
    ],
    "wof:name":"Empire State Manufacturer LLC",
    "wof:placetype":"venue"
},
  "geometry": {"coordinates":[-73.14199000000001,40.794521],"type":"Point"}
}