{
  "type": "Feature",
  "properties": {
    "iso:country":"US",
    "sg:address":"2732 Transit Rd",
    "sg:city":"Buffalo",
    "sg:classifiers":[
        {
            "category":"Health Services",
            "subcategory":"Clinic",
            "type":"Services"
        }
    ],
    "sg:phone":"+1 716 712 2700",
    "sg:postcode":"14224",
    "sg:province":"NY",
    "wof:name":"Prism Health Networks",
    "wof:placetype":"venue"
},
  "geometry": {"coordinates":[-78.696831,42.842186],"type":"Point"}
}