{
  "type": "Feature",
  "properties": {
    "addr:full":"254 Robinson St Binghamton NY 13904",
    "addr:housenumber":"254",
    "addr:postcode":"13904",
    "addr:street":"Robinson St",
    "iso:country":"US",
    "sg:address":"254 Robinson St",
    "sg:city":"Binghamton",
    "sg:classifiers":[
        {
            "category":"Organizations",
            "subcategory":"Religious Organization",
            "type":"Services"
        }
    ],
    "sg:phone":"+1 607 724 6886",
    "sg:postcode":"13904",
    "sg:province":"NY",
    "sg:tags":[
        "church"
    ],
    "wof:name":"Fairview United Methodist Chr",
    "wof:placetype":"venue"
},
  "geometry": {"coordinates":[-75.88168400000001,42.107973],"type":"Point"}
}