{
  "type": "Feature",
  "properties": {
    "iso:country":"US",
    "sg:address":"6 Quarropas St",
    "sg:city":"White Plains",
    "sg:classifiers":[
        {
            "category":"Restaurant",
            "type":"Food & Drink"
        }
    ],
    "sg:phone":"+1   ",
    "sg:postcode":"10601",
    "sg:province":"NY",
    "sg:tags":[
        "eating"
    ],
    "wof:name":"Piacere",
    "wof:placetype":"venue"
},
  "geometry": {"coordinates":[-73.766751,41.029887],"type":"Point"}
}