{
  "type": "Feature",
  "properties": {
    "addr:full":"154 Jamestown Ter Rochester NY 14615",
    "addr:housenumber":"154",
    "addr:postcode":"14615",
    "addr:street":"Jamestown Ter",
    "iso:country":"US",
    "sg:address":"154 Jamestown Ter",
    "sg:city":"Rochester",
    "sg:classifiers":[
        {
            "category":"Building & Trades",
            "subcategory":"Construction",
            "type":"Services"
        }
    ],
    "sg:phone":"+1 585 621 7925",
    "sg:postcode":"14615",
    "sg:province":"NY",
    "sg:tags":[
        "contractor"
    ],
    "wof:name":"M&T Gutter Co",
    "wof:placetype":"venue"
},
  "geometry": {"coordinates":[-77.666878,43.227663],"type":"Point"}
}