{
  "type": "Feature",
  "properties": {
    "iso:country":"US",
    "sg:address":"119 E Main St",
    "sg:city":"Norwich",
    "sg:classifiers":[
        {
            "category":"Organizations",
            "subcategory":"Non-profit Organization",
            "type":"Services"
        }
    ],
    "sg:phone":"+1 607 334 3577",
    "sg:postcode":"13815",
    "sg:province":"NY",
    "sg:tags":[
        "human"
    ],
    "wof:name":"Broome Developmental Svc",
    "wof:placetype":"venue"
},
  "geometry": {"coordinates":[-75.514084,42.532057],"type":"Point"}
}