{
  "type": "Feature",
  "properties": {
    "iso:country":"US",
    "sg:address":"10 Fort George Hill",
    "sg:city":"New York",
    "sg:classifiers":[
        {
            "category":"Manufacturing",
            "subcategory":"Food",
            "type":"Manufacturing & Wholesale Goods"
        },
        {
            "category":"Wholesale",
            "subcategory":"Groceries",
            "type":"Manufacturing & Wholesale Goods"
        }
    ],
    "sg:phone":"+1 212 569 5613",
    "sg:postcode":"10040",
    "sg:province":"NY",
    "sg:tags":[
        "honey",
        "preserves",
        "jam",
        "jelly",
        "mfg"
    ],
    "wof:name":"Atlas Preserves Co Inc",
    "wof:placetype":"venue"
},
  "geometry": {"coordinates":[-73.92757400000001,40.857713],"type":"Point"}
}