{
  "type": "Feature",
  "properties": {
    "addr:full":"106 Wilkinson Rd Macedon NY 14502",
    "addr:housenumber":"106",
    "addr:postcode":"14502",
    "addr:street":"Wilkinson Rd",
    "iso:country":"US",
    "sg:address":"106 Wilkinson Rd",
    "sg:city":"Macedon",
    "sg:classifiers":[
        {
            "category":"Retail",
            "subcategory":"Animal Services",
            "type":"Services"
        }
    ],
    "sg:phone":"+1 315 986 5975",
    "sg:postcode":"14502",
    "sg:province":"NY",
    "wof:name":"Thunder Hill Stable",
    "wof:placetype":"venue"
},
  "geometry": {"coordinates":[-77.371033,43.043422],"type":"Point"}
}