{
  "type": "Feature",
  "properties": {
    "iso:country":"US",
    "sg:address":"580 Broadway",
    "sg:city":"New York",
    "sg:classifiers":[
        {
            "category":"Real Estate",
            "subcategory":"Real Estate Agent",
            "type":"Services"
        }
    ],
    "sg:phone":"+1 212 226 9000",
    "sg:postcode":"10012",
    "sg:province":"NY",
    "sg:website":"www.itzhakiproperties.com",
    "wof:name":"Itzhaki Properties",
    "wof:placetype":"venue"
},
  "geometry": {"coordinates":[-73.996965,40.724993],"type":"Point"}
}