{
  "type": "Feature",
  "properties": {
    "addr:full":"520 Oakwood Ave East Aurora NY 14052",
    "addr:housenumber":"520",
    "addr:postcode":"14052",
    "addr:street":"Oakwood Ave",
    "iso:country":"US",
    "sg:address":"520 Oakwood Ave",
    "sg:city":"East Aurora",
    "sg:classifiers":[
        {
            "category":"Organizations",
            "subcategory":"Religious Organization",
            "type":"Services"
        }
    ],
    "sg:phone":"+1 716 652 6400",
    "sg:postcode":"14052",
    "sg:province":"NY",
    "sg:tags":[
        "church"
    ],
    "wof:name":"Immaculate Conception RC",
    "wof:placetype":"venue"
},
  "geometry": {"coordinates":[-78.615167,42.76573],"type":"Point"}
}