{
  "type": "Feature",
  "properties": {
    "iso:country":"US",
    "sg:address":"172 Madison Ave",
    "sg:city":"New York",
    "sg:classifiers":[
        {
            "category":"Wholesale",
            "subcategory":"Scrap",
            "type":"Manufacturing & Wholesale Goods"
        }
    ],
    "sg:phone":"+1 212 685 5755",
    "sg:postcode":"10016",
    "sg:province":"NY",
    "sg:tags":[
        "metal",
        "export"
    ],
    "wof:name":"JLJ International (ny) Inc",
    "wof:placetype":"venue"
},
  "geometry": {"coordinates":[-73.982957,40.747765],"type":"Point"}
}