{
  "type": "Feature",
  "properties": {
    "iso:country":"US",
    "sg:address":"125 Merrick Rd",
    "sg:city":"Merrick",
    "sg:classifiers":[
        {
            "category":"Retail",
            "subcategory":"Auto Repair",
            "type":"Services"
        }
    ],
    "sg:phone":"+1 516 378 9469",
    "sg:postcode":"11566",
    "sg:province":"NY",
    "sg:tags":[
        "general"
    ],
    "wof:name":"Merrick Motors",
    "wof:placetype":"venue"
},
  "geometry": {"coordinates":[-73.554788,40.653861],"type":"Point"}
}