{
  "type": "Feature",
  "properties": {
    "addr:full":"257 Burts Rd Kirkwood NY 13795",
    "addr:housenumber":"257",
    "addr:postcode":"13795",
    "addr:street":"Burts Rd",
    "iso:country":"US",
    "sg:address":"257 Burts Rd",
    "sg:city":"Kirkwood",
    "sg:classifiers":[
        {
            "category":"Wholesale",
            "subcategory":"Construction Materials",
            "type":"Manufacturing & Wholesale Goods"
        }
    ],
    "sg:phone":"+1 607 775 3599",
    "sg:postcode":"13795",
    "sg:province":"NY",
    "wof:name":"Hamptons Cabinet Shop",
    "wof:placetype":"venue"
},
  "geometry": {"coordinates":[-75.767449,42.037217],"type":"Point"}
}