{
  "type": "Feature",
  "properties": {
    "iso:country":"US",
    "sg:address":"21 Hampshire Rd",
    "sg:city":"Great Neck",
    "sg:classifiers":[
        {
            "category":"Real Estate",
            "subcategory":"Real Estate Agent",
            "type":"Services"
        }
    ],
    "sg:phone":"+1 516 487 4754",
    "sg:postcode":"11023",
    "sg:province":"NY",
    "wof:name":"Relwex",
    "wof:placetype":"venue"
},
  "geometry": {"coordinates":[-73.728756,40.797537],"type":"Point"}
}