{
  "type": "Feature",
  "properties": {
    "addr:full":"33 Catherine St New York NY 10038",
    "addr:housenumber":"33",
    "addr:postcode":"10038",
    "addr:street":"Catherine St",
    "iso:country":"US",
    "sg:address":"33 Catherine St",
    "sg:city":"New York",
    "sg:classifiers":[
        {
            "category":"Building & Trades",
            "subcategory":"Construction",
            "type":"Services"
        }
    ],
    "sg:phone":"+1 212 233 8979",
    "sg:postcode":"10038",
    "sg:province":"NY",
    "sg:tags":[
        "contractor"
    ],
    "wof:name":"L C Construction Inc",
    "wof:placetype":"venue"
},
  "geometry": {"coordinates":[-73.99683400000001,40.712493],"type":"Point"}
}