{
  "type": "Feature",
  "properties": {
    "iso:country":"US",
    "sg:address":"332 New York Ave",
    "sg:city":"Huntington",
    "sg:classifiers":[
        {
            "category":"Shopping",
            "subcategory":"Jewelry",
            "type":"Retail Goods"
        }
    ],
    "sg:phone":"+1 631 427 8193",
    "sg:postcode":"11743",
    "sg:province":"NY",
    "wof:name":"Time Source Inc",
    "wof:placetype":"venue"
},
  "geometry": {"coordinates":[-73.426399,40.872002],"type":"Point"}
}