{
  "type": "Feature",
  "properties": {
    "iso:country":"US",
    "sg:address":"8800 Alexander Rd",
    "sg:city":"Batavia",
    "sg:classifiers":[
        {
            "category":"Building & Trades",
            "subcategory":"Construction",
            "type":"Services"
        }
    ],
    "sg:phone":"+1 585 343 3497",
    "sg:postcode":"14020",
    "sg:province":"NY",
    "sg:tags":[
        "residential"
    ],
    "wof:name":"Jeff Sanfaldlo",
    "wof:placetype":"venue"
},
  "geometry": {"coordinates":[-78.198949,42.986572],"type":"Point"}
}