{
  "type": "Feature",
  "properties": {
    "addr:full":"268 Main St Buffalo NY 14202",
    "addr:housenumber":"268",
    "addr:postcode":"14202",
    "addr:street":"Main St",
    "iso:country":"US",
    "sg:address":"268 Main St",
    "sg:city":"Buffalo",
    "sg:classifiers":[
        {
            "category":"Manufacturing",
            "subcategory":"Printing",
            "type":"Manufacturing & Wholesale Goods"
        }
    ],
    "sg:phone":"+1 716 852 2664",
    "sg:postcode":"14202",
    "sg:province":"NY",
    "sg:tags":[
        "printer"
    ],
    "sg:website":"www.greatlakesprint.com",
    "wof:name":"Great Lakes Graphics & Ptg",
    "wof:placetype":"venue"
},
  "geometry": {"coordinates":[-78.875958,42.880845],"type":"Point"}
}