{
  "type": "Feature",
  "properties": {
    "addr:full":"52 S Main St Castletn On Hdsn NY 12022",
    "addr:housenumber":"52",
    "addr:postcode":"12022",
    "addr:street":"S Main St",
    "iso:country":"US",
    "sg:address":"52 S Main St",
    "sg:city":"Castletn On Hdsn",
    "sg:classifiers":[
        {
            "category":"Travel",
            "subcategory":"Hotels & Motels",
            "type":"Entertainment"
        }
    ],
    "sg:phone":"+1 518 732 4016",
    "sg:postcode":"12022",
    "sg:province":"NY",
    "sg:tags":[
        "management"
    ],
    "wof:name":"Hilton Management",
    "wof:placetype":"venue"
},
  "geometry": {"coordinates":[-73.372462,42.692076],"type":"Point"}
}