{
  "type": "Feature",
  "properties": {
    "iso:country":"US",
    "sg:address":"2291 Penfield Rd",
    "sg:city":"Penfield",
    "sg:classifiers":[
        {
            "category":"Autos & Motor Vehicles",
            "subcategory":"Automobile Sales",
            "type":"Retail Goods"
        }
    ],
    "sg:phone":"+1 585 381 4368",
    "sg:postcode":"14526",
    "sg:province":"NY",
    "sg:tags":[
        "classic"
    ],
    "wof:name":"Riter Automotive",
    "wof:placetype":"venue"
},
  "geometry": {"coordinates":[-77.431596,43.130593],"type":"Point"}
}