{
  "type": "Feature",
  "properties": {
    "iso:country":"US",
    "sg:address":"6670 Martin St",
    "sg:city":"Rome",
    "sg:classifiers":[
        {
            "category":"Wholesale",
            "subcategory":"Machinery & Supplies",
            "type":"Manufacturing & Wholesale Goods"
        }
    ],
    "sg:phone":"+1 315 339 3378",
    "sg:postcode":"13440",
    "sg:province":"NY",
    "sg:tags":[
        "equipment",
        "welding"
    ],
    "wof:name":"Haun Welding Supply",
    "wof:placetype":"venue"
},
  "geometry": {"coordinates":[-75.453135,43.199442],"type":"Point"}
}