{
  "type": "Feature",
  "properties": {
    "iso:country":"US",
    "sg:address":"44 Jordan Rd",
    "sg:city":"Buffalo",
    "sg:classifiers":[
        {
            "category":"Shopping",
            "subcategory":"Gifts & Souvenirs",
            "type":"Retail Goods"
        }
    ],
    "sg:phone":"+1   ",
    "sg:postcode":"14221",
    "sg:province":"NY",
    "wof:name":"Cosis Closet",
    "wof:placetype":"venue"
},
  "geometry": {"coordinates":[-78.755121,42.982075],"type":"Point"}
}