{
  "type": "Feature",
  "properties": {
    "addr:full":"166 Mill St Canandaigua NY 14424",
    "addr:housenumber":"166",
    "addr:postcode":"14424",
    "addr:street":"Mill St",
    "iso:country":"US",
    "sg:address":"166 Mill St",
    "sg:city":"Canandaigua",
    "sg:classifiers":[
        {
            "category":"Professional",
            "subcategory":"Business Services",
            "type":"Services"
        }
    ],
    "sg:phone":"+1 585 394 7110",
    "sg:postcode":"14424",
    "sg:province":"NY",
    "sg:tags":[
        "event"
    ],
    "wof:name":"Bardeen Enterprises",
    "wof:placetype":"venue"
},
  "geometry": {"coordinates":[-77.27870299999999,42.885609],"type":"Point"}
}