{
  "type": "Feature",
  "properties": {
    "iso:country":"US",
    "sg:address":"6343 S Whitham Dr",
    "sg:city":"Niagara Falls",
    "sg:classifiers":[
        {
            "category":"Home & Garden",
            "subcategory":"Household Appliances",
            "type":"Retail Goods"
        }
    ],
    "sg:phone":"+1 716 297 7885",
    "sg:postcode":"14304",
    "sg:province":"NY",
    "sg:tags":[
        "refrigerator",
        "freezer"
    ],
    "wof:name":"Robert's Refrigeration",
    "wof:placetype":"venue"
},
  "geometry": {"coordinates":[-78.99122800000001,43.113771],"type":"Point"}
}