{
  "type": "Feature",
  "properties": {
    "iso:country":"US",
    "sg:address":"369 E Union St",
    "sg:city":"Lockport",
    "sg:classifiers":[
        {
            "category":"Recreation",
            "subcategory":"Amusement Park",
            "type":"Entertainment"
        }
    ],
    "sg:phone":"+1 716 439 5857",
    "sg:postcode":"14094",
    "sg:province":"NY",
    "sg:tags":[
        "camp",
        "ground"
    ],
    "wof:name":"Kelli Hale",
    "wof:placetype":"venue"
},
  "geometry": {"coordinates":[-78.67620599999999,43.176812],"type":"Point"}
}