{
  "type": "Feature",
  "properties": {
    "addr:full":"128 Mount Airy Rd New Windsor NY 12553",
    "addr:housenumber":"128",
    "addr:postcode":"12553",
    "addr:street":"Mount Airy Rd",
    "iso:country":"US",
    "sg:address":"128 Mount Airy Rd",
    "sg:city":"New Windsor",
    "sg:classifiers":[
        {
            "category":"Freight",
            "type":"Transportation"
        }
    ],
    "sg:phone":"+1 845 567 3420",
    "sg:postcode":"12553",
    "sg:province":"NY",
    "sg:tags":[
        "trucking"
    ],
    "wof:name":"TFL Transport",
    "wof:placetype":"venue"
},
  "geometry": {"coordinates":[-74.096647,41.481257],"type":"Point"}
}