{
  "type": "Feature",
  "properties": {
    "iso:country":"US",
    "sg:address":"2157 Penfield Rd",
    "sg:city":"Penfield",
    "sg:classifiers":[
        {
            "category":"Fast Food",
            "type":"Food & Drink"
        },
        {
            "category":"Restaurant",
            "type":"Food & Drink"
        }
    ],
    "sg:phone":"+1 585 388 9420",
    "sg:postcode":"14526",
    "sg:province":"NY",
    "sg:tags":[
        "style",
        "hamburger",
        "family",
        "dog",
        "hot",
        "take",
        "american"
    ],
    "wof:name":"Lindburgers",
    "wof:placetype":"venue"
},
  "geometry": {"coordinates":[-77.444258,43.130749],"type":"Point"}
}