{
  "type": "Feature",
  "properties": {
    "addr:full":"1501 Clinton St Buffalo NY 14206",
    "addr:housenumber":"1501",
    "addr:postcode":"14206",
    "addr:street":"Clinton St",
    "iso:country":"US",
    "sg:address":"1501 Clinton St",
    "sg:city":"Buffalo",
    "sg:classifiers":[
        {
            "category":"Restaurant",
            "type":"Food & Drink"
        }
    ],
    "sg:phone":"+1 716 822 8518",
    "sg:postcode":"14206",
    "sg:province":"NY",
    "wof:name":"Ang's Lunch Car",
    "wof:placetype":"venue"
},
  "geometry": {"coordinates":[-78.82199900000001,42.8727],"type":"Point"}
}