{
  "type": "Feature",
  "properties": {
    "iso:country":"US",
    "sg:address":"2262 Jerome Ave",
    "sg:city":"Bronx",
    "sg:classifiers":[
        {
            "category":"Professional",
            "type":"Services"
        }
    ],
    "sg:phone":"+1 718 933 4440",
    "sg:postcode":"10453",
    "sg:province":"NY",
    "sg:tags":[
        "establishment"
    ],
    "wof:name":"BHD Corp",
    "wof:placetype":"venue"
},
  "geometry": {"coordinates":[-73.904313,40.85748],"type":"Point"}
}