{
  "type": "Feature",
  "properties": {
    "iso:country":"US",
    "sg:address":"275 Ave X",
    "sg:city":"Brooklyn",
    "sg:classifiers":[
        {
            "category":"Building & Trades",
            "subcategory":"Electrical",
            "type":"Services"
        }
    ],
    "sg:phone":"+1 718 787 0300",
    "sg:postcode":"11223",
    "sg:province":"NY",
    "sg:tags":[
        "electrical",
        "contractor"
    ],
    "wof:name":"Cmy Electrical Corp",
    "wof:placetype":"venue"
},
  "geometry": {"coordinates":[-73.972274,40.590387],"type":"Point"}
}