{
  "type": "Feature",
  "properties": {
    "addr:full":"39 Eldridge St New York NY 10002",
    "addr:housenumber":"39",
    "addr:postcode":"10002",
    "addr:street":"Eldridge St",
    "iso:country":"US",
    "sg:address":"39 Eldridge St",
    "sg:city":"New York",
    "sg:classifiers":[
        {
            "category":"Social Services",
            "subcategory":"Child Care",
            "type":"Services"
        }
    ],
    "sg:phone":"+1 212 925 0998",
    "sg:postcode":"10002",
    "sg:province":"NY",
    "sg:tags":[
        "day"
    ],
    "wof:name":"Red Apple Education Center",
    "wof:placetype":"venue"
},
  "geometry": {"coordinates":[-73.99300100000001,40.716224],"type":"Point"}
}