{
  "type": "Feature",
  "properties": {
    "iso:country":"US",
    "sg:address":"5814 8th Ave",
    "sg:city":"Brooklyn",
    "sg:classifiers":[
        {
            "category":"Home & Garden",
            "subcategory":"Household Appliances",
            "type":"Retail Goods"
        }
    ],
    "sg:phone":"+1 718 492 6668",
    "sg:postcode":"11220",
    "sg:province":"NY",
    "sg:tags":[
        "computer"
    ],
    "wof:name":"Xpc Technology Inc",
    "wof:placetype":"venue"
},
  "geometry": {"coordinates":[-74.008797,40.636398],"type":"Point"}
}