{
  "type": "Feature",
  "properties": {
    "addr:full":"45 W 47 St New York NY 10036",
    "addr:housenumber":"45",
    "addr:postcode":"10036",
    "addr:street":"W 47 St",
    "iso:country":"US",
    "sg:address":"45 W 47 St",
    "sg:city":"New York",
    "sg:classifiers":[
        {
            "category":"Professional",
            "subcategory":"Business Services",
            "type":"Services"
        }
    ],
    "sg:phone":"+1 212 382 0087",
    "sg:postcode":"10036",
    "sg:province":"NY",
    "wof:name":"G Christensen",
    "wof:placetype":"venue"
},
  "geometry": {"coordinates":[-73.980659,40.757473],"type":"Point"}
}