{
  "type": "Feature",
  "properties": {
    "iso:country":"US",
    "sg:address":"405 Greenfield Ave",
    "sg:city":"Ballston Spa",
    "sg:classifiers":[
        {
            "category":"Building & Trades",
            "subcategory":"Equipment Rental",
            "type":"Services"
        }
    ],
    "sg:phone":"+1 518 885 5470",
    "sg:postcode":"12020",
    "sg:province":"NY",
    "sg:tags":[
        "aircraft",
        "leasing",
        "charter"
    ],
    "sg:website":"www.nafsinc.com",
    "wof:name":"North American Flight Svc",
    "wof:placetype":"venue"
},
  "geometry": {"coordinates":[-73.861293,43.044136],"type":"Point"}
}