{
  "type": "Feature",
  "properties": {
    "addr:full":"75 Sarine Rd Wurtsboro NY 12790",
    "addr:housenumber":"75",
    "addr:postcode":"12790",
    "addr:street":"Sarine Rd",
    "iso:country":"US",
    "sg:address":"75 Sarine Rd",
    "sg:city":"Wurtsboro",
    "sg:classifiers":[
        {
            "category":"Shopping",
            "subcategory":"Clothing, Apparel, & Fashions",
            "type":"Retail Goods"
        }
    ],
    "sg:phone":"+1 845 888 2468",
    "sg:postcode":"12790",
    "sg:province":"NY",
    "wof:name":"Helen Morrell Elegant Ladies",
    "wof:placetype":"venue"
},
  "geometry": {"coordinates":[-74.542942,41.601941],"type":"Point"}
}