{
  "type": "Feature",
  "properties": {
    "addr:full":"425 Neptune Ave Brooklyn NY 11224",
    "addr:housenumber":"425",
    "addr:postcode":"11224",
    "addr:street":"Neptune Ave",
    "iso:country":"US",
    "sg:address":"425 Neptune Ave",
    "sg:city":"Brooklyn",
    "sg:classifiers":[
        {
            "category":"Retail",
            "subcategory":"Repair Shop",
            "type":"Services"
        }
    ],
    "sg:phone":"+1 718 887 2380",
    "sg:postcode":"11224",
    "sg:province":"NY",
    "sg:tags":[
        "lock",
        "locksmith"
    ],
    "wof:name":"24 Hour Emergency Locksmith",
    "wof:placetype":"venue"
},
  "geometry": {"coordinates":[-73.968216,40.580395],"type":"Point"}
}