{
  "type": "Feature",
  "properties": {
    "iso:country":"US",
    "sg:address":"2732 W Entry Rd",
    "sg:city":"Baldwinsville",
    "sg:classifiers":[
        {
            "category":"Building & Trades",
            "subcategory":"Electrical",
            "type":"Services"
        }
    ],
    "sg:phone":"+1 315 638 7338",
    "sg:postcode":"13027",
    "sg:province":"NY",
    "sg:tags":[
        "electric",
        "contractor"
    ],
    "wof:name":"Penny Electric Inc",
    "wof:placetype":"venue"
},
  "geometry": {"coordinates":[-76.307535,43.179204],"type":"Point"}
}