{
  "type": "Feature",
  "properties": {
    "iso:country":"US",
    "sg:address":"925 Coney Island Ave",
    "sg:city":"Brooklyn",
    "sg:classifiers":[
        {
            "category":"Travel",
            "subcategory":"Travel Agent",
            "type":"Entertainment"
        }
    ],
    "sg:phone":"+1 718 940 4800",
    "sg:postcode":"11230",
    "sg:province":"NY",
    "sg:tags":[
        "agency",
        "bureau"
    ],
    "wof:name":"A Wireless City & Electronics",
    "wof:placetype":"venue"
},
  "geometry": {"coordinates":[-73.967433,40.634947],"type":"Point"}
}