{
  "type": "Feature",
  "properties": {
    "addr:full":"15 W Bayberry Rd Glenmont NY 12077",
    "addr:housenumber":"15",
    "addr:postcode":"12077",
    "addr:street":"W Bayberry Rd",
    "iso:country":"US",
    "sg:address":"15 W Bayberry Rd",
    "sg:city":"Glenmont",
    "sg:classifiers":[
        {
            "category":"Professional",
            "type":"Services"
        }
    ],
    "sg:phone":"+1 518 439 8052",
    "sg:postcode":"12077",
    "sg:province":"NY",
    "sg:tags":[
        "establishment"
    ],
    "wof:name":"Capital BPM Inc",
    "wof:placetype":"venue"
},
  "geometry": {"coordinates":[-73.809259,42.603668],"type":"Point"}
}