{
  "type": "Feature",
  "properties": {
    "addr:full":"171 West St Brooklyn NY 11222",
    "addr:housenumber":"171",
    "addr:postcode":"11222",
    "addr:street":"West St",
    "iso:country":"US",
    "sg:address":"171 West St",
    "sg:city":"Brooklyn",
    "sg:classifiers":[
        {
            "category":"Freight",
            "type":"Transportation"
        }
    ],
    "sg:phone":"+1   ",
    "sg:postcode":"11222",
    "sg:province":"NY",
    "sg:tags":[
        "terminal",
        "warehouse",
        "marine",
        "public"
    ],
    "wof:name":"Lumber Exchange Terminal Inc",
    "wof:placetype":"venue"
},
  "geometry": {"coordinates":[-73.959846,40.732818],"type":"Point"}
}