{
  "type": "Feature",
  "properties": {
    "iso:country":"US",
    "sg:address":"230 E Main St",
    "sg:city":"East Islip",
    "sg:classifiers":[
        {
            "category":"Shopping",
            "subcategory":"Bicycles & Sporting Goods",
            "type":"Retail Goods"
        }
    ],
    "sg:phone":"+1   ",
    "sg:postcode":"11730",
    "sg:province":"NY",
    "sg:website":"www.soccersticks.net",
    "wof:name":"Soccer Sticks",
    "wof:placetype":"venue"
},
  "geometry": {"coordinates":[-73.18091699999999,40.733267],"type":"Point"}
}