{
  "type": "Feature",
  "properties": {
    "iso:country":"US",
    "sg:address":"689 Main St",
    "sg:city":"Westbury",
    "sg:classifiers":[
        {
            "category":"Travel",
            "subcategory":"Travel Agent",
            "type":"Entertainment"
        }
    ],
    "sg:phone":"+1 516 334 6700",
    "sg:postcode":"11590",
    "sg:province":"NY",
    "sg:tags":[
        "tours",
        "promoter"
    ],
    "wof:name":"Pet-Mal Inc",
    "wof:placetype":"venue"
},
  "geometry": {"coordinates":[-73.55801,40.757369],"type":"Point"}
}