{
  "type": "Feature",
  "properties": {
    "addr:full":"30 Commercial Ct Plainview NY 11803",
    "addr:housenumber":"30",
    "addr:postcode":"11803",
    "addr:street":"Commercial Ct",
    "iso:country":"US",
    "sg:address":"30 Commercial Ct",
    "sg:city":"Plainview",
    "sg:classifiers":[
        {
            "category":"Professional",
            "subcategory":"Management & Consulting",
            "type":"Services"
        }
    ],
    "sg:phone":"+1 516 349 0100",
    "sg:postcode":"11803",
    "sg:province":"NY",
    "sg:tags":[
        "support",
        "direct",
        "market"
    ],
    "sg:website":"www.linkdir.com",
    "wof:name":"Link Direct Inc",
    "wof:placetype":"venue"
},
  "geometry": {"coordinates":[-73.467336,40.788831],"type":"Point"}
}