{
  "type": "Feature",
  "properties": {
    "addr:full":"4824 4th Ave Brooklyn NY 11220",
    "addr:housenumber":"4824",
    "addr:postcode":"11220",
    "addr:street":"4Th Ave",
    "iso:country":"US",
    "sg:address":"4824 4th Ave",
    "sg:city":"Brooklyn",
    "sg:classifiers":[
        {
            "category":"Retail",
            "subcategory":"Laundry & Dry Cleaning",
            "type":"Services"
        }
    ],
    "sg:phone":"+1 718 439 1929",
    "sg:postcode":"11220",
    "sg:province":"NY",
    "sg:tags":[
        "cleaner"
    ],
    "wof:name":"Franick Cleaners",
    "wof:placetype":"venue"
},
  "geometry": {"coordinates":[-74.012001,40.647301],"type":"Point"}
}