{
  "type": "Feature",
  "properties": {
    "iso:country":"US",
    "sg:address":"9979 Francis Rd",
    "sg:city":"Batavia",
    "sg:classifiers":[
        {
            "category":"Autos & Motor Vehicles",
            "subcategory":"Recreational Vehicle Sales",
            "type":"Retail Goods"
        }
    ],
    "sg:phone":"+1   ",
    "sg:postcode":"14020",
    "sg:province":"NY",
    "wof:name":"L E I T I R V Sales & Service",
    "wof:placetype":"venue"
},
  "geometry": {"coordinates":[-78.162066,42.931339],"type":"Point"}
}