{
  "type": "Feature",
  "properties": {
    "iso:country":"US",
    "sg:address":"1353 50th St",
    "sg:city":"Brooklyn",
    "sg:classifiers":[
        {
            "category":"Education",
            "subcategory":"School",
            "type":"Public Place"
        }
    ],
    "sg:phone":"+1 718 435 2266",
    "sg:postcode":"11219",
    "sg:province":"NY",
    "wof:name":"Bais Esther School",
    "wof:placetype":"venue"
},
  "geometry": {"coordinates":[-73.991449,40.633868],"type":"Point"}
}