{
  "type": "Feature",
  "properties": {
    "addr:full":"1840 Hylan Boulevard Staten Island NY 10305",
    "addr:housenumber":"1840",
    "addr:postcode":"10305",
    "addr:street":"Hylan Boulevard",
    "iso:country":"US",
    "sg:address":"1840 Hylan Boulevard",
    "sg:city":"Staten Island",
    "sg:classifiers":[
        {
            "category":"Professional",
            "subcategory":"Detective & Security Services",
            "type":"Services"
        }
    ],
    "sg:phone":"+1 718 924 2662",
    "sg:postcode":"10305",
    "sg:province":"NY",
    "sg:tags":[
        "system"
    ],
    "wof:name":"Garage Door Repair Staten Island",
    "wof:placetype":"venue"
},
  "geometry": {"coordinates":[-74.094491,40.584352],"type":"Point"}
}