{
  "type": "Feature",
  "properties": {
    "iso:country":"US",
    "sg:address":"752 New Lots Ave",
    "sg:city":"Brooklyn",
    "sg:classifiers":[
        {
            "category":"Banks & Credit Unions",
            "subcategory":"Bank",
            "type":"Services"
        }
    ],
    "sg:phone":"+1 718 649 6780",
    "sg:postcode":"11207",
    "sg:province":"NY",
    "sg:tags":[
        "cashing",
        "check"
    ],
    "wof:name":"David's Money Ctr Of New York",
    "wof:placetype":"venue"
},
  "geometry": {"coordinates":[-73.88276999999999,40.666227],"type":"Point"}
}