{
  "type": "Feature",
  "properties": {
    "addr:full":"5282 Lake Shore Rd Hamburg NY 14075",
    "addr:housenumber":"5282",
    "addr:postcode":"14075",
    "addr:street":"Lake Shore Rd",
    "iso:country":"US",
    "sg:address":"5282 Lake Shore Rd",
    "sg:city":"Hamburg",
    "sg:classifiers":[
        {
            "category":"Professional",
            "type":"Services"
        }
    ],
    "sg:phone":"+1 716 627 9624",
    "sg:postcode":"14075",
    "sg:province":"NY",
    "sg:tags":[
        "editorial"
    ],
    "wof:name":"Wordwright Editorial Svc",
    "wof:placetype":"venue"
},
  "geometry": {"coordinates":[-78.909503,42.742043],"type":"Point"}
}