{
  "type": "Feature",
  "properties": {
    "iso:country":"US",
    "sg:address":"71 Hill St",
    "sg:city":"Southampton",
    "sg:classifiers":[
        {
            "category":"Personal",
            "type":"Services"
        }
    ],
    "sg:phone":"+1 631 287 3183",
    "sg:postcode":"11968",
    "sg:province":"NY",
    "sg:tags":[
        "consultant",
        "program",
        "health",
        "fitness"
    ],
    "wof:name":"Human Potential Health Studio",
    "wof:placetype":"venue"
},
  "geometry": {"coordinates":[-72.39552999999999,40.883883],"type":"Point"}
}