{
  "type": "Feature",
  "properties": {
    "addr:full":"76 Washington Ave Island Park NY 11558",
    "addr:housenumber":"76",
    "addr:postcode":"11558",
    "addr:street":"Washington Ave;Park",
    "iso:country":"US",
    "sg:address":"76 Washington Ave",
    "sg:city":"Island Park",
    "sg:classifiers":[
        {
            "category":"Building & Trades",
            "subcategory":"Construction",
            "type":"Services"
        }
    ],
    "sg:phone":"+1 516 432 3944",
    "sg:postcode":"11558",
    "sg:province":"NY",
    "sg:tags":[
        "excavation",
        "contractor"
    ],
    "wof:name":"Quinto Contracting",
    "wof:placetype":"venue"
},
  "geometry": {"coordinates":[-73.66300200000001,40.600101],"type":"Point"}
}