{
  "type": "Feature",
  "properties": {
    "addr:full":"110 Lockwood Ave New Rochelle NY 10801",
    "addr:housenumber":"110",
    "addr:postcode":"10801",
    "addr:street":"Lockwood Ave",
    "iso:country":"US",
    "sg:address":"110 Lockwood Ave",
    "sg:city":"New Rochelle",
    "sg:classifiers":[
        {
            "category":"Health Services",
            "subcategory":"Doctor",
            "type":"Services"
        }
    ],
    "sg:phone":"+1   ",
    "sg:postcode":"10801",
    "sg:province":"NY",
    "wof:name":"Dino M Defilippis",
    "wof:placetype":"venue"
},
  "geometry": {"coordinates":[-73.78970700000001,40.913492],"type":"Point"}
}