{
  "type": "Feature",
  "properties": {
    "addr:full":"415 Woodland Rd Syracuse NY 13219",
    "addr:housenumber":"415",
    "addr:postcode":"13219",
    "addr:street":"Woodland Rd",
    "iso:country":"US",
    "sg:address":"415 Woodland Rd",
    "sg:city":"Syracuse",
    "sg:classifiers":[
        {
            "category":"Wholesale",
            "subcategory":"Electrical",
            "type":"Manufacturing & Wholesale Goods"
        },
        {
            "category":"Professional",
            "subcategory":"Advertising",
            "type":"Services"
        }
    ],
    "sg:phone":"+1 315 487 2320",
    "sg:postcode":"13219",
    "sg:province":"NY",
    "sg:tags":[
        "equipment",
        "distribution"
    ],
    "sg:website":"www.cedcareers.com",
    "wof:name":"Consolidated Electrical Distrs",
    "wof:placetype":"venue"
},
  "geometry": {"coordinates":[-76.223488,43.034041],"type":"Point"}
}