{
  "type": "Feature",
  "properties": {
    "iso:country":"US",
    "sg:address":"4283 Canty Hill Rd",
    "sg:city":"Tully",
    "sg:classifiers":[
        {
            "category":"Government",
            "subcategory":"Office",
            "type":"Public Place"
        }
    ],
    "sg:phone":"+1 315 696 8753",
    "sg:postcode":"13159",
    "sg:province":"NY",
    "sg:tags":[
        "executive"
    ],
    "wof:name":"Otisco Highway Department",
    "wof:placetype":"venue"
},
  "geometry": {"coordinates":[-76.20138300000001,42.86643],"type":"Point"}
}