{
  "type": "Feature",
  "properties": {
    "addr:full":"364 Seneca Rd Hornell NY 14843",
    "addr:housenumber":"364",
    "addr:postcode":"14843",
    "addr:street":"Seneca Rd",
    "iso:country":"US",
    "sg:address":"364 Seneca Rd",
    "sg:city":"Hornell",
    "sg:classifiers":[
        {
            "category":"Health Services",
            "subcategory":"Doctor",
            "type":"Services"
        }
    ],
    "sg:phone":"+1 607 324 0051",
    "sg:postcode":"14843",
    "sg:province":"NY",
    "sg:tags":[
        "medical"
    ],
    "wof:name":"Peterson Wm D MD",
    "wof:placetype":"venue"
},
  "geometry": {"coordinates":[-77.660549,42.343532],"type":"Point"}
}