{
  "type": "Feature",
  "properties": {
    "addr:full":"212 Smith Hill Rd Lisle NY 13797",
    "addr:housenumber":"212",
    "addr:postcode":"13797",
    "addr:street":"Smith Hill Rd",
    "iso:country":"US",
    "sg:address":"212 Smith Hill Rd",
    "sg:city":"Lisle",
    "sg:phone":"+1 607 849 6102",
    "sg:postcode":"13797",
    "sg:province":"NY",
    "sg:tags":[
        "farm",
        "field",
        "corn",
        "crop"
    ],
    "wof:name":"Pendell Septice Service",
    "wof:placetype":"venue"
},
  "geometry": {"coordinates":[-76.037651,42.34883],"type":"Point"}
}