{
  "type": "Feature",
  "properties": {
    "iso:country":"US",
    "sg:address":"824 Walt Whitman Rd",
    "sg:city":"Melville",
    "sg:classifiers":[
        {
            "category":"Personal",
            "subcategory":"Beauty Salon",
            "type":"Services"
        }
    ],
    "sg:phone":"+1 631 351 1460",
    "sg:postcode":"11747",
    "sg:province":"NY",
    "sg:tags":[
        "spa",
        "day"
    ],
    "wof:name":"Juvance Le Spa Skin Vitality",
    "wof:placetype":"venue"
},
  "geometry": {"coordinates":[-73.41379499999999,40.796062],"type":"Point"}
}