{
  "type": "Feature",
  "properties": {
    "iso:country":"US",
    "sg:address":"13 Grove St",
    "sg:city":"Poughkeepsie",
    "sg:classifiers":[
        {
            "category":"Organizations",
            "subcategory":"Religious Organization",
            "type":"Services"
        }
    ],
    "sg:phone":"+1 845 454 5735",
    "sg:postcode":"12601",
    "sg:province":"NY",
    "sg:tags":[
        "clergy"
    ],
    "wof:name":"A Forro",
    "wof:placetype":"venue"
},
  "geometry": {"coordinates":[-73.936049,41.698893],"type":"Point"}
}