{
  "type": "Feature",
  "properties": {
    "addr:full":"354 Gibbs Pond Rd Nesconset NY 11767",
    "addr:housenumber":"354",
    "addr:postcode":"11767",
    "addr:street":"Gibbs Pond Rd",
    "iso:country":"US",
    "sg:address":"354 Gibbs Pond Rd",
    "sg:city":"Nesconset",
    "sg:classifiers":[
        {
            "category":"Professional",
            "subcategory":"Management & Consulting",
            "type":"Services"
        }
    ],
    "sg:phone":"+1 631 981 3521",
    "sg:postcode":"11767",
    "sg:province":"NY",
    "sg:tags":[
        "roofing",
        "consultant"
    ],
    "wof:name":"All Weather Roofing",
    "wof:placetype":"venue"
},
  "geometry": {"coordinates":[-73.13731,40.841679],"type":"Point"}
}