{
  "type": "Feature",
  "properties": {
    "addr:full":"2840 Freshour Rd Canandaigua NY 14424",
    "addr:housenumber":"2840",
    "addr:postcode":"14424",
    "addr:street":"Freshour Rd",
    "iso:country":"US",
    "sg:address":"2840 Freshour Rd",
    "sg:city":"Canandaigua",
    "sg:classifiers":[
        {
            "category":"Real Estate",
            "subcategory":"Surveying",
            "type":"Services"
        }
    ],
    "sg:phone":"+1 585 394 5861",
    "sg:postcode":"14424",
    "sg:province":"NY",
    "sg:tags":[
        "surveyor"
    ],
    "wof:name":"Earl Gear-Surveying",
    "wof:placetype":"venue"
},
  "geometry": {"coordinates":[-77.209253,42.893812],"type":"Point"}
}