{
  "type": "Feature",
  "properties": {
    "addr:full":"2215 Burdett Ave Troy NY 12180",
    "addr:housenumber":"2215",
    "addr:postcode":"12180",
    "addr:street":"Burdett Ave",
    "iso:country":"US",
    "sg:address":"2215 Burdett Ave",
    "sg:city":"Troy",
    "sg:classifiers":[
        {
            "category":"Social Services",
            "type":"Services"
        }
    ],
    "sg:phone":"+1 518 271 3592",
    "sg:postcode":"12180",
    "sg:province":"NY",
    "sg:tags":[
        "information",
        "center",
        "diabetes"
    ],
    "sg:website":"www.nehgwise.com",
    "wof:name":"Northeast Health Diabetes Ctr",
    "wof:placetype":"venue"
},
  "geometry": {"coordinates":[-73.670785,42.735696],"type":"Point"}
}