{
  "type": "Feature",
  "properties": {
    "iso:country":"US",
    "sg:address":"265 Post Ave Ste 290",
    "sg:city":"Westbury",
    "sg:classifiers":[
        {
            "category":"Professional",
            "subcategory":"Lawyer & Legal Services",
            "type":"Services"
        }
    ],
    "sg:phone":"+1 516 333 1972",
    "sg:postcode":"11590",
    "sg:province":"NY",
    "wof:name":"Ortiz Laura Esq",
    "wof:placetype":"venue"
},
  "geometry": {"coordinates":[-73.58808000000001,40.758515],"type":"Point"}
}