{
  "type": "Feature",
  "properties": {
    "addr:full":"101 E 54th St Brooklyn NY 11203",
    "addr:housenumber":"101",
    "addr:postcode":"11203",
    "addr:street":"E 54Th St",
    "iso:country":"US",
    "sg:address":"101 E 54th St",
    "sg:city":"Brooklyn",
    "sg:classifiers":[
        {
            "category":"Recreation",
            "subcategory":"Amusement Park",
            "type":"Entertainment"
        }
    ],
    "sg:phone":"+1 718 345 1414",
    "sg:postcode":"11203",
    "sg:province":"NY",
    "wof:name":"Melody Amusement Corp",
    "wof:placetype":"venue"
},
  "geometry": {"coordinates":[-73.926804,40.6567],"type":"Point"}
}