{
  "type": "Feature",
  "properties": {
    "addr:full":"13168 226th St Springfield Gardens NY 11413",
    "addr:housenumber":"13168",
    "addr:postcode":"11413",
    "addr:street":"226Th St",
    "iso:country":"US",
    "sg:address":"13168 226th St",
    "sg:city":"Springfield Gardens",
    "sg:classifiers":[
        {
            "category":"Education",
            "subcategory":"School",
            "type":"Public Place"
        }
    ],
    "sg:phone":"+1 718 528 3753",
    "sg:postcode":"11413",
    "sg:province":"NY",
    "wof:name":"SCO Family of Services",
    "wof:placetype":"venue"
},
  "geometry": {"coordinates":[-73.74257,40.680044],"type":"Point"}
}