{
  "type": "Feature",
  "properties": {
    "addr:full":"19 Waverly Place New York NY 10003",
    "addr:housenumber":"19",
    "addr:postcode":"10003",
    "addr:street":"Waverly Place",
    "iso:country":"US",
    "sg:address":"19 Waverly Place",
    "sg:city":"New York",
    "sg:classifiers":[
        {
            "category":"Restaurant",
            "type":"Food & Drink"
        }
    ],
    "sg:phone":"+1 212 674 0608",
    "sg:postcode":"10003",
    "sg:province":"NY",
    "wof:name":"Campus Diner",
    "wof:placetype":"venue"
},
  "geometry": {"coordinates":[-73.99459,40.730108],"type":"Point"}
}