{
  "type": "Feature",
  "properties": {
    "iso:country":"US",
    "sg:address":"7292 Lakeshore Rd",
    "sg:city":"Cicero",
    "sg:classifiers":[
        {
            "category":"Communications",
            "type":"Services"
        }
    ],
    "sg:phone":"+1 315 699 3304",
    "sg:postcode":"13039",
    "sg:province":"NY",
    "sg:tags":[
        "carrier"
    ],
    "wof:name":"Moore Creative Communications",
    "wof:placetype":"venue"
},
  "geometry": {"coordinates":[-76.02399800000001,43.188891],"type":"Point"}
}