{
  "type": "Feature",
  "properties": {
    "iso:country":"US",
    "sg:address":"62 W 45th St",
    "sg:city":"New York",
    "sg:classifiers":[
        {
            "category":"Shopping",
            "type":"Retail Goods"
        }
    ],
    "sg:phone":"+1 212 719 1918",
    "sg:postcode":"10036",
    "sg:province":"NY",
    "sg:website":"www.manhattanjudaica.com",
    "wof:name":"Manhattan Judaica",
    "wof:placetype":"venue"
},
  "geometry": {"coordinates":[-73.981466,40.756239],"type":"Point"}
}