{
  "type": "Feature",
  "properties": {
    "addr:full":"9816 River Rd Marcy NY 13403",
    "addr:housenumber":"9816",
    "addr:postcode":"13403",
    "addr:street":"River Rd",
    "iso:country":"US",
    "sg:address":"9816 River Rd",
    "sg:city":"Marcy",
    "sg:classifiers":[
        {
            "category":"Freight",
            "type":"Transportation"
        }
    ],
    "sg:phone":"+1 315 735 7666",
    "sg:postcode":"13403",
    "sg:province":"NY",
    "sg:tags":[
        "commercial",
        "storage"
    ],
    "wof:name":"Store America",
    "wof:placetype":"venue"
},
  "geometry": {"coordinates":[-75.237375,43.126204],"type":"Point"}
}