{
  "type": "Feature",
  "properties": {
    "addr:full":"1924 53rd St Brooklyn NY 11204",
    "addr:housenumber":"1924",
    "addr:postcode":"11204",
    "addr:street":"53Rd St",
    "iso:country":"US",
    "sg:address":"1924 53rd St",
    "sg:city":"Brooklyn",
    "sg:classifiers":[
        {
            "category":"Professional",
            "subcategory":"Management & Consulting",
            "type":"Services"
        }
    ],
    "sg:phone":"+1 718 232 4161",
    "sg:postcode":"11204",
    "sg:province":"NY",
    "sg:tags":[
        "brokerage",
        "insurance"
    ],
    "wof:name":"Right Insurance Service",
    "wof:placetype":"venue"
},
  "geometry": {"coordinates":[-73.97923900000001,40.62359],"type":"Point"}
}