{
  "type": "Feature",
  "properties": {
    "iso:country":"US",
    "sg:address":"8300 N Main St",
    "sg:city":"Eden",
    "sg:classifiers":[
        {
            "category":"Wholesale",
            "subcategory":"Motor Vehicles",
            "type":"Manufacturing & Wholesale Goods"
        }
    ],
    "sg:phone":"+1 716 992 9928",
    "sg:postcode":"14057",
    "sg:province":"NY",
    "sg:tags":[
        "automobile",
        "truck",
        "broker"
    ],
    "wof:name":"Specialty Motor Care Ctr",
    "wof:placetype":"venue"
},
  "geometry": {"coordinates":[-78.89142099999999,42.662151],"type":"Point"}
}