{
  "type": "Feature",
  "properties": {
    "iso:country":"US",
    "sg:address":"3 Ashton Dr",
    "sg:city":"Greenwich",
    "sg:classifiers":[
        {
            "category":"Building & Trades",
            "subcategory":"Construction",
            "type":"Services"
        }
    ],
    "sg:phone":"+1 203 622 0446",
    "sg:postcode":"06831",
    "sg:province":"NY",
    "sg:tags":[
        "contractor"
    ],
    "wof:name":"Dimitra Designs",
    "wof:placetype":"venue"
},
  "geometry": {"coordinates":[-73.64891,41.042576],"type":"Point"}
}