{
  "type": "Feature",
  "properties": {
    "iso:country":"US",
    "sg:address":"59 Riverside Ave",
    "sg:city":"Haverstraw",
    "sg:classifiers":[
        {
            "category":"Professional",
            "type":"Services"
        }
    ],
    "sg:phone":"+1 845 429 6061",
    "sg:postcode":"10927",
    "sg:province":"NY",
    "sg:tags":[
        "establishment"
    ],
    "wof:name":"Tilcon New York Inc",
    "wof:placetype":"venue"
},
  "geometry": {"coordinates":[-73.942232,41.177081],"type":"Point"}
}