{
  "type": "Feature",
  "properties": {
    "addr:full":"3532 Union St Flushing NY 11354",
    "addr:housenumber":"3532",
    "addr:postcode":"11354",
    "addr:street":"Union St",
    "iso:country":"US",
    "sg:address":"3532 Union St",
    "sg:city":"Flushing",
    "sg:classifiers":[
        {
            "category":"Local Transit",
            "type":"Transportation"
        }
    ],
    "sg:phone":"+1 718 333 2222",
    "sg:postcode":"11354",
    "sg:province":"NY",
    "sg:tags":[
        "shuttle"
    ],
    "wof:name":"Moogunghwa Ny Corp",
    "wof:placetype":"venue"
},
  "geometry": {"coordinates":[-73.82658000000001,40.77198],"type":"Point"}
}