{
  "type": "Feature",
  "properties": {
    "iso:country":"US",
    "sg:address":"300 E Main St",
    "sg:city":"Falconer",
    "sg:classifiers":[
        {
            "category":"Real Estate",
            "subcategory":"Real Estate Operator",
            "type":"Services"
        }
    ],
    "sg:phone":"+1 716 665 2088",
    "sg:postcode":"14733",
    "sg:province":"NY",
    "sg:tags":[
        "building",
        "apartment"
    ],
    "wof:name":"Shirley Manor",
    "wof:placetype":"venue"
},
  "geometry": {"coordinates":[-79.19313699999999,42.12309],"type":"Point"}
}