{
  "type": "Feature",
  "properties": {
    "addr:full":"137 E 13th St New York NY 10003",
    "addr:housenumber":"137",
    "addr:postcode":"10003",
    "addr:street":"E 13Th St",
    "iso:country":"US",
    "sg:address":"137 E 13th St",
    "sg:city":"New York",
    "sg:classifiers":[
        {
            "category":"Cinema",
            "subcategory":"Movie Rental",
            "type":"Entertainment"
        }
    ],
    "sg:phone":"+1 212 674 0200",
    "sg:postcode":"10003",
    "sg:province":"NY",
    "sg:tags":[
        "game",
        "video"
    ],
    "wof:name":"Plan N Trade Video Games",
    "wof:placetype":"venue"
},
  "geometry": {"coordinates":[-73.98898199999999,40.733302],"type":"Point"}
}