{
  "type": "Feature",
  "properties": {
    "addr:full":"205 Pearl St New York NY 10038",
    "addr:housenumber":"205",
    "addr:postcode":"10038",
    "addr:street":"Pearl St",
    "iso:country":"US",
    "sg:address":"205 Pearl St",
    "sg:city":"New York",
    "sg:classifiers":[
        {
            "category":"Restaurant",
            "type":"Food & Drink"
        }
    ],
    "sg:phone":"+1   ",
    "sg:postcode":"10038",
    "sg:province":"NY",
    "sg:tags":[
        "eating"
    ],
    "wof:name":"Sophie S Restaurant LLC",
    "wof:placetype":"venue"
},
  "geometry": {"coordinates":[-74.00663299999999,40.706905],"type":"Point"}
}