{
  "type": "Feature",
  "properties": {
    "addr:full":"656 Willoughby Ave Brooklyn NY 11206",
    "addr:housenumber":"656",
    "addr:postcode":"11206",
    "addr:street":"Willoughby Ave",
    "iso:country":"US",
    "sg:address":"656 Willoughby Ave",
    "sg:city":"Brooklyn",
    "sg:classifiers":[
        {
            "category":"Social Services",
            "subcategory":"Child Care",
            "type":"Services"
        }
    ],
    "sg:phone":"+1 718 443 2900",
    "sg:postcode":"11206",
    "sg:province":"NY",
    "sg:tags":[
        "day"
    ],
    "wof:name":"Day Aguadilla Care Center",
    "wof:placetype":"venue"
},
  "geometry": {"coordinates":[-73.940411,40.69488],"type":"Point"}
}