{
  "type": "Feature",
  "properties": {
    "addr:full":"4201 30th Ave Astoria NY 11103",
    "addr:housenumber":"4201",
    "addr:postcode":"11103",
    "addr:street":"30Th Ave",
    "iso:country":"US",
    "sg:address":"4201 30th Ave",
    "sg:city":"Astoria",
    "sg:classifiers":[
        {
            "category":"Real Estate",
            "subcategory":"Real Estate Agent",
            "type":"Services"
        }
    ],
    "sg:phone":"+1 718 777 7857",
    "sg:postcode":"11103",
    "sg:province":"NY",
    "sg:website":"www.citystoprealty.com",
    "wof:name":"City Stop Realty",
    "wof:placetype":"venue"
},
  "geometry": {"coordinates":[-73.91338,40.763134],"type":"Point"}
}