{
  "type": "Feature",
  "properties": {
    "addr:full":"71 E Main St East Islip NY 11730",
    "addr:housenumber":"71",
    "addr:postcode":"11730",
    "addr:street":"E Main St",
    "iso:country":"US",
    "sg:address":"71 E Main St",
    "sg:city":"East Islip",
    "sg:classifiers":[
        {
            "category":"Wholesale",
            "subcategory":"Medical Equipment & Supplies",
            "type":"Manufacturing & Wholesale Goods"
        }
    ],
    "sg:phone":"+1 631 581 4088",
    "sg:postcode":"11730",
    "sg:province":"NY",
    "sg:tags":[
        "dental"
    ],
    "wof:name":"Advantage Dental Equip Repair",
    "wof:placetype":"venue"
},
  "geometry": {"coordinates":[-73.188057,40.731739],"type":"Point"}
}