{
  "type": "Feature",
  "properties": {
    "addr:full":"4 Fritz Blvd Albany NY 12205",
    "addr:housenumber":"4",
    "addr:postcode":"12205",
    "addr:street":"Fritz Blvd",
    "iso:country":"US",
    "sg:address":"4 Fritz Blvd",
    "sg:city":"Albany",
    "sg:classifiers":[
        {
            "category":"Wholesale",
            "subcategory":"Medical Equipment & Supplies",
            "type":"Manufacturing & Wholesale Goods"
        }
    ],
    "sg:phone":"+1 518 456 6192",
    "sg:postcode":"12205",
    "sg:province":"NY",
    "sg:tags":[
        "hospital"
    ],
    "wof:name":"Prime Care Medical Supplies",
    "wof:placetype":"venue"
},
  "geometry": {"coordinates":[-73.840326,42.714716],"type":"Point"}
}