{
  "type": "Feature",
  "properties": {
    "iso:country":"US",
    "sg:address":"945 Jefferson Rd",
    "sg:city":"Rochester",
    "sg:classifiers":[
        {
            "category":"Restaurant",
            "type":"Food & Drink"
        }
    ],
    "sg:phone":"+1 585 475 9464",
    "sg:postcode":"14623",
    "sg:province":"NY",
    "sg:website":"www.hooters.com",
    "wof:name":"Hooters",
    "wof:placetype":"venue"
},
  "geometry": {"coordinates":[-77.609649,43.087144],"type":"Point"}
}