{
  "type": "Feature",
  "properties": {
    "addr:full":"8 Barnard Rd Armonk NY 10504",
    "addr:housenumber":"8",
    "addr:postcode":"10504",
    "addr:street":"Barnard Rd",
    "iso:country":"US",
    "sg:address":"8 Barnard Rd",
    "sg:city":"Armonk",
    "sg:classifiers":[
        {
            "category":"Health Services",
            "subcategory":"Doctor",
            "type":"Services"
        }
    ],
    "sg:phone":"+1 914 273 2121",
    "sg:postcode":"10504",
    "sg:province":"NY",
    "sg:tags":[
        "physician",
        "surgeon"
    ],
    "wof:name":"Kenneth B Liegner MD",
    "wof:placetype":"venue"
},
  "geometry": {"coordinates":[-73.697603,41.119465],"type":"Point"}
}