{
  "type": "Feature",
  "properties": {
    "iso:country":"US",
    "sg:address":"34 Pearl St",
    "sg:city":"Westfield",
    "sg:classifiers":[
        {
            "category":"Organizations",
            "subcategory":"Community Association",
            "type":"Services"
        }
    ],
    "sg:phone":"+1 716 326 2613",
    "sg:postcode":"14787",
    "sg:province":"NY",
    "wof:name":"William P Jackway",
    "wof:placetype":"venue"
},
  "geometry": {"coordinates":[-79.57680000000001,42.327147],"type":"Point"}
}