{
  "type": "Feature",
  "properties": {
    "addr:full":"1686 County Route 38 Norfolk NY 13667",
    "addr:housenumber":"1686",
    "addr:postcode":"13667",
    "addr:street":"County Route 38 Norfolk",
    "iso:country":"US",
    "sg:address":"1686 County Route 38",
    "sg:city":"Norfolk",
    "sg:classifiers":[
        {
            "category":"Farming",
            "subcategory":"Farm & Veterinary Services",
            "type":"Manufacturing & Wholesale Goods"
        }
    ],
    "sg:phone":"+1 315 769 7209",
    "sg:postcode":"13667",
    "sg:province":"NY",
    "sg:tags":[
        "breeder",
        "livestock"
    ],
    "wof:name":"Han Vonallmen",
    "wof:placetype":"venue"
},
  "geometry": {"coordinates":[-74.902559,44.836958],"type":"Point"}
}