{
  "type": "Feature",
  "properties": {
    "iso:country":"US",
    "sg:address":"3 Barker Ave",
    "sg:city":"White Plains",
    "sg:classifiers":[
        {
            "category":"Professional",
            "subcategory":"Accounting & Tax Preparation",
            "type":"Services"
        }
    ],
    "sg:phone":"+1 914 289 0679",
    "sg:postcode":"10601",
    "sg:province":"NY",
    "sg:tags":[
        "accountant"
    ],
    "wof:name":"Peter To CPA",
    "wof:placetype":"venue"
},
  "geometry": {"coordinates":[-73.770779,41.034542],"type":"Point"}
}