{
  "type": "Feature",
  "properties": {
    "iso:country":"US",
    "sg:address":"9334 Shaw Rd",
    "sg:city":"Nunda",
    "sg:classifiers":[
        {
            "category":"Retail",
            "subcategory":"Auto Repair",
            "type":"Services"
        }
    ],
    "sg:phone":"+1   ",
    "sg:postcode":"14517",
    "sg:province":"NY",
    "sg:tags":[
        "general"
    ],
    "wof:name":"Pts Auto Repair",
    "wof:placetype":"venue"
},
  "geometry": {"coordinates":[-77.840898,42.571674],"type":"Point"}
}