{
  "type": "Feature",
  "properties": {
    "iso:country":"US",
    "sg:address":"1873 Western Ave",
    "sg:city":"Albany",
    "sg:classifiers":[
        {
            "category":"Health Services",
            "subcategory":"Doctor",
            "type":"Services"
        },
        {
            "category":"Health Services",
            "subcategory":"Clinic",
            "type":"Services"
        }
    ],
    "sg:phone":"+1 518 690 4420",
    "sg:postcode":"12203",
    "sg:province":"NY",
    "sg:tags":[
        "physician",
        "industrial",
        "medical",
        "surgeons",
        "medicine",
        "surgeon",
        "occupational"
    ],
    "wof:name":"Occupational & Environmental H",
    "wof:placetype":"venue"
},
  "geometry": {"coordinates":[-73.87426000000001,42.692539],"type":"Point"}
}