{
  "type": "Feature",
  "properties": {
    "addr:full":"2545 Sheridan Dr Ste 3 Tonawanda NY 14150",
    "addr:housenumber":"2545",
    "addr:postcode":"14150",
    "addr:street":"Sheridan Dr Ste 3",
    "iso:country":"US",
    "sg:address":"2545 Sheridan Dr Ste 3",
    "sg:city":"Tonawanda",
    "sg:classifiers":[
        {
            "category":"Health Services",
            "subcategory":"Doctor",
            "type":"Services"
        }
    ],
    "sg:phone":"+1 716 838 1100",
    "sg:postcode":"14150",
    "sg:province":"NY",
    "sg:tags":[
        "medicine",
        "physician",
        "practice",
        "surgeons",
        "family"
    ],
    "wof:name":"Sheridan Medical Center Inc",
    "wof:placetype":"venue"
},
  "geometry": {"coordinates":[-78.839814,42.980784],"type":"Point"}
}