{
  "type": "Feature",
  "properties": {
    "iso:country":"US",
    "sg:address":"300 Railroad Ave",
    "sg:city":"Peekskill",
    "sg:classifiers":[
        {
            "category":"Restaurant",
            "type":"Food & Drink"
        }
    ],
    "sg:phone":"+1 914 734 2100",
    "sg:postcode":"10566",
    "sg:province":"NY",
    "wof:name":"P J Kelly's",
    "wof:placetype":"venue"
},
  "geometry": {"coordinates":[-73.93002799999999,41.285869],"type":"Point"}
}