{
  "type": "Feature",
  "properties": {
    "iso:country":"US",
    "sg:address":"67 Maiden Ln",
    "sg:city":"Kingston",
    "sg:classifiers":[
        {
            "category":"Professional",
            "subcategory":"Engineering",
            "type":"Services"
        }
    ],
    "sg:phone":"+1 845 338 7622",
    "sg:postcode":"12401",
    "sg:province":"NY",
    "sg:tags":[
        "engineer"
    ],
    "wof:name":"Brinnier & Larios PC",
    "wof:placetype":"venue"
},
  "geometry": {"coordinates":[-74.015407,41.931612],"type":"Point"}
}