{
  "type": "Feature",
  "properties": {
    "addr:full":"123 Oakbriar Dr Rochester NY 14616",
    "addr:housenumber":"123",
    "addr:postcode":"14616",
    "addr:street":"Oakbriar Dr",
    "iso:country":"US",
    "sg:address":"123 Oakbriar Dr",
    "sg:city":"Rochester",
    "sg:classifiers":[
        {
            "category":"Organizations",
            "subcategory":"Religious Organization",
            "type":"Services"
        }
    ],
    "sg:phone":"+1 585 663 5973",
    "sg:postcode":"14616",
    "sg:province":"NY",
    "sg:tags":[
        "clergy"
    ],
    "wof:name":"Stephen K Matson",
    "wof:placetype":"venue"
},
  "geometry": {"coordinates":[-77.652287,43.24605],"type":"Point"}
}