{
  "type": "Feature",
  "properties": {
    "addr:full":"830 Old Country Rd Westbury NY 11590",
    "addr:housenumber":"830",
    "addr:postcode":"11590",
    "addr:street":"Old Country Rd",
    "iso:country":"US",
    "sg:address":"830 Old Country Rd",
    "sg:city":"Westbury",
    "sg:classifiers":[
        {
            "category":"Recreation",
            "type":"Entertainment"
        }
    ],
    "sg:phone":"+1 516 338 8681",
    "sg:postcode":"11590",
    "sg:province":"NY",
    "sg:tags":[
        "astrologer"
    ],
    "wof:name":"Miss Leona",
    "wof:placetype":"venue"
},
  "geometry": {"coordinates":[-73.56615499999999,40.752687],"type":"Point"}
}