{
  "type": "Feature",
  "properties": {
    "addr:full":"3 College Rd Monsey NY 10952",
    "addr:housenumber":"3",
    "addr:postcode":"10952",
    "addr:street":"College Rd",
    "iso:country":"US",
    "sg:address":"3 College Rd",
    "sg:city":"Monsey",
    "sg:classifiers":[
        {
            "category":"Health Services",
            "subcategory":"Doctor",
            "type":"Services"
        }
    ],
    "sg:phone":"+1 845 357 5088",
    "sg:postcode":"10952",
    "sg:province":"NY",
    "wof:name":"Hugh Calder DDS",
    "wof:placetype":"venue"
},
  "geometry": {"coordinates":[-74.08953,41.112705],"type":"Point"}
}