{
  "type": "Feature",
  "properties": {
    "addr:full":"160 W 118th St New York NY 10026",
    "addr:housenumber":"160",
    "addr:postcode":"10026",
    "addr:street":"W 118Th St",
    "iso:country":"US",
    "sg:address":"160 W 118th St",
    "sg:city":"New York",
    "sg:classifiers":[
        {
            "category":"Building & Trades",
            "subcategory":"Cleaning & Sanitation",
            "type":"Services"
        }
    ],
    "sg:phone":"+1 212 222 2978",
    "sg:postcode":"10026",
    "sg:province":"NY",
    "sg:tags":[
        "maintenance"
    ],
    "wof:name":"1 60 W 118th Street Corp",
    "wof:placetype":"venue"
},
  "geometry": {"coordinates":[-73.95029,40.803728],"type":"Point"}
}