{
  "type": "Feature",
  "properties": {
    "addr:full":"303 Herman Dr Syracuse NY 13212",
    "addr:housenumber":"303",
    "addr:postcode":"13212",
    "addr:street":"Herman Dr",
    "iso:country":"US",
    "sg:address":"303 Herman Dr",
    "sg:city":"Syracuse",
    "sg:classifiers":[
        {
            "category":"Shopping",
            "subcategory":"Gifts & Souvenirs",
            "type":"Retail Goods"
        }
    ],
    "sg:phone":"+1   ",
    "sg:postcode":"13212",
    "sg:province":"NY",
    "wof:name":"Gift Solutions By Kim Co",
    "wof:placetype":"venue"
},
  "geometry": {"coordinates":[-76.14368899999999,43.130633],"type":"Point"}
}