{
  "type": "Feature",
  "properties": {
    "iso:country":"US",
    "sg:address":"1688 Victory Blvd",
    "sg:city":"Staten Island",
    "sg:classifiers":[
        {
            "category":"Retail",
            "subcategory":"Portrait Studio",
            "type":"Services"
        },
        {
            "category":"Professional",
            "subcategory":"Art Services",
            "type":"Services"
        }
    ],
    "sg:phone":"+1 718 273 7999",
    "sg:postcode":"10314",
    "sg:province":"NY",
    "sg:tags":[
        "photography",
        "commercial"
    ],
    "wof:name":"V Amesse Photography",
    "wof:placetype":"venue"
},
  "geometry": {"coordinates":[-74.12009500000001,40.613203],"type":"Point"}
}