{
  "type": "Feature",
  "properties": {
    "iso:country":"US",
    "sg:address":"7034 W Henrietta Rd",
    "sg:city":"Rush",
    "sg:classifiers":[
        {
            "category":"Manufacturing",
            "subcategory":"Toys & Sporting Goods",
            "type":"Manufacturing & Wholesale Goods"
        }
    ],
    "sg:phone":"+1   ",
    "sg:postcode":"14543",
    "sg:province":"NY",
    "sg:tags":[
        "mfg"
    ],
    "wof:name":"Kink",
    "wof:placetype":"venue"
},
  "geometry": {"coordinates":[-77.666726,43.006526],"type":"Point"}
}