{
  "type": "Feature",
  "properties": {
    "addr:full":"723 Genesee St Oneida NY 13421",
    "addr:housenumber":"723",
    "addr:postcode":"13421",
    "addr:street":"Genesee St",
    "iso:country":"US",
    "sg:address":"723 Genesee St",
    "sg:city":"Oneida",
    "sg:classifiers":[
        {
            "category":"Personal",
            "subcategory":"Beauty Salon",
            "type":"Services"
        }
    ],
    "sg:phone":"+1 315 363 4247",
    "sg:postcode":"13421",
    "sg:province":"NY",
    "wof:name":"Brigitte Hair & Tanning Salon",
    "wof:placetype":"venue"
},
  "geometry": {"coordinates":[-75.689976,43.07624],"type":"Point"}
}