{
  "type": "Feature",
  "properties": {
    "iso:country":"US",
    "sg:address":"141 E 33 St",
    "sg:city":"New York",
    "sg:classifiers":[
        {
            "category":"Shopping",
            "type":"Retail Goods"
        }
    ],
    "sg:phone":"+1 212 679 6626",
    "sg:postcode":"10016",
    "sg:province":"NY",
    "sg:tags":[
        "equipment",
        "telephone",
        "supply"
    ],
    "wof:name":"Adco System",
    "wof:placetype":"venue"
},
  "geometry": {"coordinates":[-73.978607,40.745058],"type":"Point"}
}