{
  "type": "Feature",
  "properties": {
    "addr:full":"240 Park Hill Ave Staten Island NY 10304",
    "addr:housenumber":"240",
    "addr:postcode":"10304",
    "addr:street":"Park Hill Ave",
    "iso:country":"US",
    "sg:address":"240 Park Hill Ave",
    "sg:city":"Staten Island",
    "sg:classifiers":[
        {
            "category":"Wholesale",
            "subcategory":"Apparel",
            "type":"Manufacturing & Wholesale Goods"
        }
    ],
    "sg:phone":"+1 718 556 9164",
    "sg:postcode":"10304",
    "sg:province":"NY",
    "sg:tags":[
        "footwear"
    ],
    "wof:name":"Diallo Hip Hop Wear",
    "wof:placetype":"venue"
},
  "geometry": {"coordinates":[-74.08217399999999,40.614508],"type":"Point"}
}