{
  "type": "Feature",
  "properties": {
    "addr:full":"601 W Ferry St Buffalo NY 14222",
    "addr:housenumber":"601",
    "addr:postcode":"14222",
    "addr:street":"W Ferry St",
    "iso:country":"US",
    "sg:address":"601 W Ferry St",
    "sg:city":"Buffalo",
    "sg:classifiers":[
        {
            "category":"Professional",
            "subcategory":"Management & Consulting",
            "type":"Services"
        }
    ],
    "sg:phone":"+1   ",
    "sg:postcode":"14222",
    "sg:province":"NY",
    "wof:name":"Caucus Partnership",
    "wof:placetype":"venue"
},
  "geometry": {"coordinates":[-78.87704600000001,42.915465],"type":"Point"}
}