{
  "type": "Feature",
  "properties": {
    "addr:full":"2109 Southern Boulevard Bronx NY 10460",
    "addr:housenumber":"2109",
    "addr:postcode":"10460",
    "addr:street":"Southern Boulevard",
    "iso:country":"US",
    "sg:address":"2109 Southern Boulevard",
    "sg:city":"Bronx",
    "sg:classifiers":[
        {
            "category":"Food & Beverages",
            "subcategory":"Groceries & Convenience Stores",
            "type":"Retail Goods"
        }
    ],
    "sg:phone":"+1 718 562 7896",
    "sg:postcode":"10460",
    "sg:province":"NY",
    "wof:name":"Deli Grocery Corporation",
    "wof:placetype":"venue"
},
  "geometry": {"coordinates":[-73.88435699999999,40.846312],"type":"Point"}
}