{
  "type": "Feature",
  "properties": {
    "addr:full":"63 E Main St Malone NY 12953",
    "addr:housenumber":"63",
    "addr:postcode":"12953",
    "addr:street":"E Main St",
    "iso:country":"US",
    "sg:address":"63 E Main St",
    "sg:city":"Malone",
    "sg:classifiers":[
        {
            "category":"Building & Trades",
            "subcategory":"Electrical",
            "type":"Services"
        }
    ],
    "sg:phone":"+1 518 483 3181",
    "sg:postcode":"12953",
    "sg:province":"NY",
    "sg:tags":[
        "electrical",
        "contractor"
    ],
    "wof:name":"Adirondack Alarms",
    "wof:placetype":"venue"
},
  "geometry": {"coordinates":[-74.29156399999999,44.84882],"type":"Point"}
}