{
  "type": "Feature",
  "properties": {
    "addr:full":"6625 Niagara Falls Blvd Niagara Falls NY 14304",
    "addr:housenumber":"6625",
    "addr:postcode":"14304",
    "addr:street":"Niagara Falls Blvd",
    "iso:country":"US",
    "sg:address":"6625 Niagara Falls Blvd",
    "sg:city":"Niagara Falls",
    "sg:classifiers":[
        {
            "category":"Professional",
            "subcategory":"Business Services",
            "type":"Services"
        }
    ],
    "sg:phone":"+1 716 283 2010",
    "sg:postcode":"14304",
    "sg:province":"NY",
    "sg:tags":[
        "reservation",
        "motel",
        "hotel"
    ],
    "sg:website":"www.redcarpetinnhotel.com",
    "wof:name":"Red Carpet Inn",
    "wof:placetype":"venue"
},
  "geometry": {"coordinates":[-78.98813800000001,43.089318],"type":"Point"}
}