{
  "type": "Feature",
  "properties": {
    "addr:full":"8 Hanover Sq Horseheads NY 14845",
    "addr:housenumber":"8",
    "addr:postcode":"14845",
    "addr:street":"Hanover Sq",
    "iso:country":"US",
    "sg:address":"8 Hanover Sq",
    "sg:city":"Horseheads",
    "sg:classifiers":[
        {
            "category":"Retail",
            "subcategory":"Animal Services",
            "type":"Services"
        }
    ],
    "sg:phone":"+1 607 739 5515",
    "sg:postcode":"14845",
    "sg:province":"NY",
    "sg:tags":[
        "pet",
        "grooming",
        "washing"
    ],
    "wof:name":"Amy's Pet Salon",
    "wof:placetype":"venue"
},
  "geometry": {"coordinates":[-76.821072,42.167947],"type":"Point"}
}