{
  "type": "Feature",
  "properties": {
    "addr:full":"1001 N Franklin St Watkins Glen NY 14891",
    "addr:housenumber":"1001",
    "addr:postcode":"14891",
    "addr:street":"N Franklin St",
    "iso:country":"US",
    "sg:address":"1001 N Franklin St",
    "sg:city":"Watkins Glen",
    "sg:classifiers":[
        {
            "category":"Restaurant",
            "type":"Food & Drink"
        },
        {
            "category":"Shopping",
            "subcategory":"Gifts & Souvenirs",
            "type":"Retail Goods"
        }
    ],
    "sg:phone":"+1 607 535 6050",
    "sg:postcode":"14891",
    "sg:province":"NY",
    "sg:tags":[
        "shop",
        "eating"
    ],
    "wof:name":"J Con Parks Inc",
    "wof:placetype":"venue"
},
  "geometry": {"coordinates":[-76.871045,42.375909],"type":"Point"}
}