{
  "type": "Feature",
  "properties": {
    "iso:country":"US",
    "sg:address":"4012 Boston Rd",
    "sg:city":"Bronx",
    "sg:classifiers":[
        {
            "category":"Restaurant",
            "type":"Food & Drink"
        }
    ],
    "sg:phone":"+1 718 320 9505",
    "sg:postcode":"10475",
    "sg:province":"NY",
    "wof:name":"Mingles",
    "wof:placetype":"venue"
},
  "geometry": {"coordinates":[-73.831867,40.884518],"type":"Point"}
}