{
  "type": "Feature",
  "properties": {
    "iso:country":"US",
    "sg:address":"4360 Walden Ave",
    "sg:city":"Lancaster",
    "sg:classifiers":[
        {
            "category":"Building & Trades",
            "subcategory":"Electrical",
            "type":"Services"
        }
    ],
    "sg:phone":"+1 716 681 7858",
    "sg:postcode":"14086",
    "sg:province":"NY",
    "wof:name":"White Mountain Cable Constr",
    "wof:placetype":"venue"
},
  "geometry": {"coordinates":[-78.617518,42.924422],"type":"Point"}
}