{
  "type": "Feature",
  "properties": {
    "iso:country":"US",
    "sg:address":"4709 Crossroads Park Dr",
    "sg:city":"Liverpool",
    "sg:classifiers":[
        {
            "category":"Government",
            "subcategory":"Office",
            "type":"Public Place"
        }
    ],
    "sg:phone":"+1 315 457 2881",
    "sg:postcode":"13088",
    "sg:province":"NY",
    "sg:tags":[
        "agricultural",
        "regulation",
        "marketing"
    ],
    "wof:name":"USDA Market Administrator",
    "wof:placetype":"venue"
},
  "geometry": {"coordinates":[-76.189183,43.121431],"type":"Point"}
}