{
  "type": "Feature",
  "properties": {
    "addr:full":"4 Fordham Hill Oval 17B Bronx NY 10468",
    "addr:housenumber":"4;17b",
    "addr:postcode":"10468",
    "addr:street":"Fordham Hill Oval",
    "iso:country":"US",
    "sg:address":"4 Fordham Hill Oval 17B",
    "sg:city":"Bronx",
    "sg:classifiers":[
        {
            "category":"Shopping",
            "subcategory":"Music",
            "type":"Retail Goods"
        }
    ],
    "sg:phone":"+1 917 238 8195",
    "sg:postcode":"10468",
    "sg:province":"NY",
    "sg:tags":[
        "store"
    ],
    "wof:name":"Rebel Soul Records",
    "wof:placetype":"venue"
},
  "geometry": {"coordinates":[-73.90822199999999,40.864126],"type":"Point"}
}