{
  "type": "Feature",
  "properties": {
    "iso:country":"US",
    "sg:address":"2771 Merrick Rd",
    "sg:city":"Bellmore",
    "sg:classifiers":[
        {
            "category":"Shopping",
            "subcategory":"Clothing, Apparel, & Fashions",
            "type":"Retail Goods"
        }
    ],
    "sg:phone":"+1 516 409 4653",
    "sg:postcode":"11710",
    "sg:province":"NY",
    "sg:tags":[
        "item",
        "boutique"
    ],
    "wof:name":"Body Boutique",
    "wof:placetype":"venue"
},
  "geometry": {"coordinates":[-73.52252799999999,40.664361],"type":"Point"}
}