{
  "type": "Feature",
  "properties": {
    "iso:country":"US",
    "sg:address":"207 Commerce Dr",
    "sg:city":"Buffalo",
    "sg:classifiers":[
        {
            "category":"Insurance",
            "subcategory":"Insurance Agent",
            "type":"Services"
        }
    ],
    "sg:phone":"+1 716 689 1925",
    "sg:postcode":"14228",
    "sg:province":"NY",
    "sg:tags":[
        "hospital",
        "billing"
    ],
    "wof:name":"Southtowns Radiology Assoc LLC",
    "wof:placetype":"venue"
},
  "geometry": {"coordinates":[-78.813171,43.027273],"type":"Point"}
}