{
  "type": "Feature",
  "properties": {
    "addr:full":"1220 1st Ave New York NY 10065",
    "addr:housenumber":"1220",
    "addr:postcode":"10065",
    "addr:street":"1St Ave",
    "iso:country":"US",
    "sg:address":"1220 1st Ave",
    "sg:city":"New York",
    "sg:classifiers":[
        {
            "category":"Restaurant",
            "type":"Food & Drink"
        }
    ],
    "sg:phone":"+1 800 273 1171",
    "sg:postcode":"10065",
    "sg:province":"NY",
    "sg:tags":[
        "pizza"
    ],
    "wof:name":"Rosa Marie Pizza",
    "wof:placetype":"venue"
},
  "geometry": {"coordinates":[-73.958623,40.763909],"type":"Point"}
}