{
  "type": "Feature",
  "properties": {
    "iso:country":"US",
    "sg:address":"34 Farm Rd",
    "sg:city":"Briarcliff Manor",
    "sg:classifiers":[
        {
            "category":"Professional",
            "subcategory":"Art Services",
            "type":"Services"
        }
    ],
    "sg:phone":"+1   ",
    "sg:postcode":"10510",
    "sg:province":"NY",
    "sg:tags":[
        "commercial",
        "design"
    ],
    "wof:name":"Dominic Arbitrio Design I",
    "wof:placetype":"venue"
},
  "geometry": {"coordinates":[-73.85019699999999,41.158789],"type":"Point"}
}