{
  "type": "Feature",
  "properties": {
    "addr:full":"1020 E 48th Street Brooklyn NY 11203",
    "addr:housenumber":"1020",
    "addr:postcode":"11203",
    "addr:street":"E 48Th Street",
    "iso:country":"US",
    "sg:address":"1020 E 48th Street",
    "sg:city":"Brooklyn",
    "sg:classifiers":[
        {
            "category":"Shopping",
            "subcategory":"Clothing, Apparel, & Fashions",
            "type":"Retail Goods"
        }
    ],
    "sg:phone":"+1 718 282 0105",
    "sg:postcode":"11203",
    "sg:province":"NY",
    "sg:tags":[
        "lingerie"
    ],
    "wof:name":"Maf Intimate",
    "wof:placetype":"venue"
},
  "geometry": {"coordinates":[-73.930779,40.636999],"type":"Point"}
}