{
  "type": "Feature",
  "properties": {
    "addr:full":"41 Green Acres Rd Valley Stream NY 11581",
    "addr:housenumber":"41",
    "addr:postcode":"11581",
    "addr:street":"Green Acres Rd",
    "iso:country":"US",
    "sg:address":"41 Green Acres Rd",
    "sg:city":"Valley Stream",
    "sg:classifiers":[
        {
            "category":"Shopping",
            "subcategory":"Clothing, Apparel, & Fashions",
            "type":"Retail Goods"
        }
    ],
    "sg:phone":"+1 516 593 6848",
    "sg:postcode":"11581",
    "sg:province":"NY",
    "sg:tags":[
        "furnishing"
    ],
    "wof:name":"M G Men's Style",
    "wof:placetype":"venue"
},
  "geometry": {"coordinates":[-73.71678199999999,40.6606],"type":"Point"}
}