{
  "type": "Feature",
  "properties": {
    "addr:full":"30 North St Monticello NY 12701",
    "addr:housenumber":"30",
    "addr:postcode":"12701",
    "addr:street":"North St",
    "iso:country":"US",
    "sg:address":"30 North St",
    "sg:city":"Monticello",
    "sg:classifiers":[
        {
            "category":"Insurance",
            "subcategory":"Insurance Agent",
            "type":"Services"
        }
    ],
    "sg:phone":"+1 845 794 5600",
    "sg:postcode":"12701",
    "sg:province":"NY",
    "wof:name":"Ralph Giordano and Associates",
    "wof:placetype":"venue"
},
  "geometry": {"coordinates":[-74.687157,41.656336],"type":"Point"}
}