{
  "type": "Feature",
  "properties": {
    "iso:country":"US",
    "sg:address":"404 Park Avenue S",
    "sg:city":"New York",
    "sg:classifiers":[
        {
            "category":"Retail",
            "subcategory":"Portrait Studio",
            "type":"Services"
        },
        {
            "category":"Professional",
            "subcategory":"Art Services",
            "type":"Services"
        }
    ],
    "sg:phone":"+1 212 871 1800",
    "sg:postcode":"10016",
    "sg:province":"NY",
    "sg:tags":[
        "photographer",
        "photography",
        "store"
    ],
    "wof:name":"Spectra Photo Digital",
    "wof:placetype":"venue"
},
  "geometry": {"coordinates":[-73.984163,40.74336],"type":"Point"}
}