{
  "type": "Feature",
  "properties": {
    "addr:full":"547 Hudson St New York NY 10014",
    "addr:housenumber":"547",
    "addr:postcode":"10014",
    "addr:street":"Hudson St",
    "iso:country":"US",
    "sg:address":"547 Hudson St",
    "sg:city":"New York",
    "sg:classifiers":[
        {
            "category":"Personal",
            "subcategory":"Beauty Salon",
            "type":"Services"
        }
    ],
    "sg:phone":"+1   ",
    "sg:postcode":"10014",
    "sg:province":"NY",
    "sg:tags":[
        "shop"
    ],
    "wof:name":"Gemini Personal Care Salon",
    "wof:placetype":"venue"
},
  "geometry": {"coordinates":[-74.00621599999999,40.734546],"type":"Point"}
}