{
  "type": "Feature",
  "properties": {
    "iso:country":"US",
    "sg:address":"330 Douglas Rd",
    "sg:city":"Chappaqua",
    "sg:classifiers":[
        {
            "category":"Health Services",
            "subcategory":"Doctor",
            "type":"Services"
        }
    ],
    "sg:phone":"+1 914 238 1352",
    "sg:postcode":"10514",
    "sg:province":"NY",
    "sg:tags":[
        "medical"
    ],
    "wof:name":"Dr Elliott Seligman",
    "wof:placetype":"venue"
},
  "geometry": {"coordinates":[-73.790509,41.164541],"type":"Point"}
}