{
  "type": "Feature",
  "properties": {
    "addr:full":"212 Huron St Brooklyn NY 11222",
    "addr:housenumber":"212",
    "addr:postcode":"11222",
    "addr:street":"Huron St",
    "iso:country":"US",
    "sg:address":"212 Huron St",
    "sg:city":"Brooklyn",
    "sg:classifiers":[
        {
            "category":"Real Estate",
            "subcategory":"Real Estate Agent",
            "type":"Services"
        }
    ],
    "sg:phone":"+1 718 389 1490",
    "sg:postcode":"11222",
    "sg:province":"NY",
    "wof:name":"151 Huron Realty Corp",
    "wof:placetype":"venue"
},
  "geometry": {"coordinates":[-73.953577,40.733021],"type":"Point"}
}