{
  "type": "Feature",
  "properties": {
    "addr:full":"71 Genesee St Auburn NY 13021",
    "addr:housenumber":"71",
    "addr:postcode":"13021",
    "addr:street":"Genesee St",
    "iso:country":"US",
    "sg:address":"71 Genesee St",
    "sg:city":"Auburn",
    "sg:classifiers":[
        {
            "category":"Retail",
            "subcategory":"Repair Shop",
            "type":"Services"
        }
    ],
    "sg:phone":"+1 315 252 9506",
    "sg:postcode":"13021",
    "sg:province":"NY",
    "sg:tags":[
        "watch"
    ],
    "wof:name":"W C Crosman & Son Inc",
    "wof:placetype":"venue"
},
  "geometry": {"coordinates":[-76.56627400000001,42.931772],"type":"Point"}
}