{
  "type": "Feature",
  "properties": {
    "iso:country":"US",
    "sg:address":"289 Halstead Ave",
    "sg:city":"Harrison",
    "sg:classifiers":[
        {
            "category":"Banks & Credit Unions",
            "subcategory":"Bank",
            "type":"Services"
        }
    ],
    "sg:phone":"+1 914 835 8552",
    "sg:postcode":"10528",
    "sg:province":"NY",
    "wof:name":"Washington Mutual",
    "wof:placetype":"venue"
},
  "geometry": {"coordinates":[-73.711911,40.969044],"type":"Point"}
}