{
  "type": "Feature",
  "properties": {
    "addr:full":"South Side of Grand Street at Bowrey Chinatown New York NY 10013",
    "addr:postcode":"10013",
    "iso:country":"US",
    "sg:address":"South Side of Grand Street at Bowrey Chinatown",
    "sg:city":"New York",
    "sg:classifiers":[
        {
            "category":"Food & Beverages",
            "subcategory":"Candy",
            "type":"Retail Goods"
        }
    ],
    "sg:postcode":"10013",
    "sg:province":"NY",
    "sg:tags":[
        "store"
    ],
    "wof:name":"Dragon Beard Candy Guy",
    "wof:placetype":"venue"
},
  "geometry": {"coordinates":[-73.99481,40.71846],"type":"Point"}
}