{
  "type": "Feature",
  "properties": {
    "addr:full":"1579 5th Ave Bay Shore NY 11706",
    "addr:housenumber":"1579",
    "addr:postcode":"11706",
    "addr:street":"5Th Ave",
    "iso:country":"US",
    "sg:address":"1579 5th Ave",
    "sg:city":"Bay Shore",
    "sg:classifiers":[
        {
            "category":"Autos & Motor Vehicles",
            "subcategory":"Auto Supplies",
            "type":"Retail Goods"
        }
    ],
    "sg:phone":"+1 631 665 9214",
    "sg:postcode":"11706",
    "sg:province":"NY",
    "sg:tags":[
        "tire"
    ],
    "wof:name":"Chapin Tires",
    "wof:placetype":"venue"
},
  "geometry": {"coordinates":[-73.26242000000001,40.755022],"type":"Point"}
}