{
  "type": "Feature",
  "properties": {
    "iso:country":"US",
    "sg:address":"80 Cook St",
    "sg:city":"Rochester",
    "sg:classifiers":[
        {
            "category":"Freight",
            "type":"Transportation"
        }
    ],
    "sg:phone":"+1 585 325 6328",
    "sg:postcode":"14620",
    "sg:province":"NY",
    "sg:tags":[
        "operator",
        "local",
        "mover",
        "storage",
        "trucking"
    ],
    "sg:website":"www.kensneatmoving.com",
    "wof:name":"Ken's Neat Moving & Storage",
    "wof:placetype":"venue"
},
  "geometry": {"coordinates":[-77.614786,43.125274],"type":"Point"}
}