{
  "type": "Feature",
  "properties": {
    "iso:country":"US",
    "sg:address":"384 Neighborhood Rd",
    "sg:city":"Mastic Beach",
    "sg:classifiers":[
        {
            "category":"Airline",
            "type":"Transportation"
        }
    ],
    "sg:phone":"+1 631 477 2227",
    "sg:postcode":"11951",
    "sg:province":"NY",
    "sg:tags":[
        "shuttle",
        "airport"
    ],
    "wof:name":"Four Ones Enterprises Llc",
    "wof:placetype":"venue"
},
  "geometry": {"coordinates":[-72.857495,40.762215],"type":"Point"}
}