{
  "type": "Feature",
  "properties": {
    "iso:country":"US",
    "sg:address":"29 Earlwood Dr",
    "sg:city":"Poughkeepsie",
    "sg:classifiers":[
        {
            "category":"Professional",
            "subcategory":"Management & Consulting",
            "type":"Services"
        }
    ],
    "sg:phone":"+1   ",
    "sg:postcode":"12603",
    "sg:province":"NY",
    "sg:tags":[
        "business"
    ],
    "wof:name":"Elias Thomas Inc",
    "wof:placetype":"venue"
},
  "geometry": {"coordinates":[-73.889628,41.67398],"type":"Point"}
}