{
  "type": "Feature",
  "properties": {
    "iso:country":"US",
    "sg:address":"1281 Metropolitan Ave",
    "sg:city":"Brooklyn",
    "sg:classifiers":[
        {
            "category":"Building & Trades",
            "subcategory":"Equipment Rental",
            "type":"Services"
        }
    ],
    "sg:phone":"+1 212 423 0023",
    "sg:postcode":"11237",
    "sg:province":"NY",
    "sg:tags":[
        "scaffolding"
    ],
    "wof:name":"B & H Scaffold & Equipment",
    "wof:placetype":"venue"
},
  "geometry": {"coordinates":[-73.924578,40.714044],"type":"Point"}
}