{
  "type": "Feature",
  "properties": {
    "addr:full":"121 W Nyack Rd Nanuet NY 10954",
    "addr:housenumber":"121",
    "addr:postcode":"10954",
    "addr:street":"W Nyack Rd",
    "iso:country":"US",
    "sg:address":"121 W Nyack Rd",
    "sg:city":"Nanuet",
    "sg:classifiers":[
        {
            "category":"Professional",
            "subcategory":"Printing & Photocopies",
            "type":"Services"
        }
    ],
    "sg:phone":"+1 845 623 2277",
    "sg:postcode":"10954",
    "sg:province":"NY",
    "sg:tags":[
        "services-commercial",
        "duplicating",
        "copying"
    ],
    "sg:website":"http://www.mmpnanuet.com/",
    "wof:name":"Minuteman Press",
    "wof:placetype":"venue"
},
  "geometry": {"coordinates":[-74.001147,41.097758],"type":"Point"}
}