{
  "type": "Feature",
  "properties": {
    "addr:full":"256 Grand St 2nd Fl Brooklyn NY 11211",
    "addr:housenumber":"256",
    "addr:postcode":"11211",
    "addr:street":"Grand St",
    "iso:country":"US",
    "sg:address":"256 Grand St 2nd Fl",
    "sg:city":"Brooklyn",
    "sg:classifiers":[
        {
            "category":"Professional",
            "subcategory":"Advertising",
            "type":"Services"
        }
    ],
    "sg:phone":"+1 213 675 0465",
    "sg:postcode":"11211",
    "sg:province":"NY",
    "sg:tags":[
        "videographers"
    ],
    "sg:website":"hellosuper8.com/",
    "wof:name":"Hello Super 8",
    "wof:placetype":"venue"
},
  "geometry": {"coordinates":[-73.95876,40.713377],"type":"Point"}
}