{
  "type": "Feature",
  "properties": {
    "iso:country":"US",
    "sg:address":"1877 Webster Ave",
    "sg:city":"Bronx",
    "sg:classifiers":[
        {
            "category":"Restaurant",
            "type":"Food & Drink"
        }
    ],
    "sg:phone":"+1 718 466 5200",
    "sg:postcode":"10457",
    "sg:province":"NY",
    "wof:name":"Palenque Palace Corp",
    "wof:placetype":"venue"
},
  "geometry": {"coordinates":[-73.90117499999999,40.847374],"type":"Point"}
}