{
  "type": "Feature",
  "properties": {
    "addr:full":"IS 131 Dr. Sun Yat-Sen School 100 Hester St Manhattan NY 10002",
    "addr:housenumber":"100",
    "addr:postcode":"10002",
    "addr:street":"Hester St",
    "iso:country":"US",
    "sg:address":"IS 131 Dr. Sun Yat-Sen School 100 Hester St",
    "sg:city":"Manhattan",
    "sg:classifiers":[
        {
            "category":"Education",
            "subcategory":"Special Training",
            "type":"Public Place"
        },
        {
            "category":"Community Center",
            "subcategory":"Social",
            "type":"Public Place"
        }
    ],
    "sg:phone":"+1 917 767 7194",
    "sg:postcode":"10002",
    "sg:province":"NY",
    "sg:tags":[
        "club",
        "school",
        "language"
    ],
    "sg:website":"www.alesn.org",
    "wof:name":"Asian Language Exchange and Social Network",
    "wof:placetype":"venue"
},
  "geometry": {"coordinates":[-73.993714,40.716542],"type":"Point"}
}