{
  "type": "Feature",
  "properties": {
    "iso:country":"US",
    "sg:address":"111 Birch Ln",
    "sg:city":"Valley Stream",
    "sg:classifiers":[
        {
            "category":"Building & Trades",
            "subcategory":"Landscaping Services",
            "type":"Services"
        }
    ],
    "sg:phone":"+1 516 295 1420",
    "sg:postcode":"11581",
    "sg:province":"NY",
    "sg:tags":[
        "landscape"
    ],
    "wof:name":"Foliage Factory",
    "wof:placetype":"venue"
},
  "geometry": {"coordinates":[-73.706746,40.65261],"type":"Point"}
}