{
  "type": "Feature",
  "properties": {
    "addr:full":"777 S Oyster Bay Rd Bethpage NY 11714",
    "addr:housenumber":"777",
    "addr:postcode":"11714",
    "addr:street":"S Oyster Bay Rd",
    "iso:country":"US",
    "sg:address":"777 S Oyster Bay Rd",
    "sg:city":"Bethpage",
    "sg:classifiers":[
        {
            "category":"Autos & Motor Vehicles",
            "subcategory":"Automobile Sales",
            "type":"Retail Goods"
        }
    ],
    "sg:phone":"+1 516 822 0003",
    "sg:postcode":"11714",
    "sg:province":"NY",
    "sg:tags":[
        "car",
        "part",
        "supply"
    ],
    "wof:name":"Automobilex Jeep Chrysler Suba",
    "wof:placetype":"venue"
},
  "geometry": {"coordinates":[-73.500407,40.763728],"type":"Point"}
}