{
  "type": "Feature",
  "properties": {
    "addr:full":"276 Boston Rd Ontario NY 14519",
    "addr:housenumber":"276",
    "addr:postcode":"14519",
    "addr:street":"Boston Rd",
    "iso:country":"US",
    "sg:address":"276 Boston Rd",
    "sg:city":"Ontario",
    "sg:phone":"+1 315 524 9107",
    "sg:postcode":"14519",
    "sg:province":"NY",
    "sg:tags":[
        "farm"
    ],
    "wof:name":"Donald Herman",
    "wof:placetype":"venue"
},
  "geometry": {"coordinates":[-77.36792800000001,43.255394],"type":"Point"}
}