{
  "type": "Feature",
  "properties": {
    "addr:full":"425 Broad Hollow Rd Melville NY 11747",
    "addr:housenumber":"425",
    "addr:postcode":"11747",
    "addr:street":"Broad Hollow Rd",
    "iso:country":"US",
    "sg:address":"425 Broad Hollow Rd",
    "sg:city":"Melville",
    "sg:classifiers":[
        {
            "category":"Professional",
            "subcategory":"Management & Consulting",
            "type":"Services"
        }
    ],
    "sg:phone":"+1 631 622 2380",
    "sg:postcode":"11747",
    "sg:province":"NY",
    "sg:tags":[
        "marketing",
        "program"
    ],
    "wof:name":"Homedata",
    "wof:placetype":"venue"
},
  "geometry": {"coordinates":[-73.42345400000001,40.765064],"type":"Point"}
}