{
  "type": "Feature",
  "properties": {
    "addr:full":"23 Old Mt Peter Rd Warwick NY 10990",
    "addr:housenumber":"23",
    "addr:postcode":"10990",
    "addr:street":"Old Mt Peter Rd",
    "iso:country":"US",
    "sg:address":"23 Old Mt Peter Rd",
    "sg:city":"Warwick",
    "sg:classifiers":[
        {
            "category":"Building & Trades",
            "subcategory":"Landscaping Services",
            "type":"Services"
        }
    ],
    "sg:phone":"+1 845 986 7951",
    "sg:postcode":"10990",
    "sg:province":"NY",
    "wof:name":"Creative Enterprises",
    "wof:placetype":"venue"
},
  "geometry": {"coordinates":[-74.30552400000001,41.248566],"type":"Point"}
}