{
  "type": "Feature",
  "properties": {
    "addr:full":"575 Broadway Newburgh NY 12550",
    "addr:housenumber":"575",
    "addr:postcode":"12550",
    "addr:street":"Broadway",
    "iso:country":"US",
    "sg:address":"575 Broadway",
    "sg:city":"Newburgh",
    "sg:classifiers":[
        {
            "category":"Wholesale",
            "subcategory":"Motor Vehicles",
            "type":"Manufacturing & Wholesale Goods"
        }
    ],
    "sg:phone":"+1 845 561 1134",
    "sg:postcode":"12550",
    "sg:province":"NY",
    "wof:name":"Xpress Auto Brokers",
    "wof:placetype":"venue"
},
  "geometry": {"coordinates":[-74.03463499999999,41.50155],"type":"Point"}
}