{
  "type": "Feature",
  "properties": {
    "addr:full":"10537 64th Avenue Forest Hills NY 11375",
    "addr:housenumber":"10537",
    "addr:postcode":"11375",
    "addr:street":"64Th Avenue",
    "iso:country":"US",
    "sg:address":"10537 64th Avenue",
    "sg:city":"Forest Hills",
    "sg:classifiers":[
        {
            "category":"Health Services",
            "subcategory":"Doctor",
            "type":"Services"
        },
        {
            "category":"Health Services",
            "subcategory":"Dentist",
            "type":"Services"
        }
    ],
    "sg:phone":"+1 718 459 0111",
    "sg:postcode":"11375",
    "sg:province":"NY",
    "wof:name":"Olenko Eugene MD",
    "wof:placetype":"venue"
},
  "geometry": {"coordinates":[-73.84506,40.724095],"type":"Point"}
}