{
  "type": "Feature",
  "properties": {
    "iso:country":"US",
    "sg:address":"609 Buffalo Rd",
    "sg:city":"Rochester",
    "sg:classifiers":[
        {
            "category":"Wholesale",
            "subcategory":"Metals & Minerals",
            "type":"Manufacturing & Wholesale Goods"
        }
    ],
    "sg:phone":"+1 585 235 6990",
    "sg:postcode":"14611",
    "sg:province":"NY",
    "sg:tags":[
        "pipe"
    ],
    "sg:website":"www.mjpipe.com",
    "wof:name":"M J Pipe & Supply Inc",
    "wof:placetype":"venue"
},
  "geometry": {"coordinates":[-77.671037,43.149879],"type":"Point"}
}