{
  "type": "Feature",
  "properties": {
    "addr:full":"232 Walnut St Buffalo NY 14204",
    "addr:housenumber":"232",
    "addr:postcode":"14204",
    "addr:street":"Walnut St",
    "iso:country":"US",
    "sg:address":"232 Walnut St",
    "sg:city":"Buffalo",
    "sg:classifiers":[
        {
            "category":"Shopping",
            "subcategory":"Gifts & Souvenirs",
            "type":"Retail Goods"
        }
    ],
    "sg:phone":"+1   ",
    "sg:postcode":"14204",
    "sg:province":"NY",
    "wof:name":"Gifts & Things",
    "wof:placetype":"venue"
},
  "geometry": {"coordinates":[-78.860049,42.885249],"type":"Point"}
}