{
  "type": "Feature",
  "properties": {
    "addr:full":"180 Madison Ave Ste 1200 New York NY 10016",
    "addr:housenumber":"180",
    "addr:postcode":"10016",
    "addr:street":"Madison Ave Ste 1200",
    "iso:country":"US",
    "sg:address":"180 Madison Ave Ste 1200",
    "sg:city":"New York",
    "sg:classifiers":[
        {
            "category":"Food & Beverages",
            "subcategory":"Liquor & Beverages",
            "type":"Retail Goods"
        }
    ],
    "sg:phone":"+1 646 424 9703",
    "sg:postcode":"10016",
    "sg:province":"NY",
    "sg:tags":[
        "beer",
        "spirit",
        "wine"
    ],
    "wof:name":"Weinert & Radisic International Corp",
    "wof:placetype":"venue"
},
  "geometry": {"coordinates":[-73.98290299999999,40.747898],"type":"Point"}
}