{
  "type": "Feature",
  "properties": {
    "iso:country":"US",
    "sg:address":"120 W State St",
    "sg:city":"Ithaca",
    "sg:classifiers":[
        {
            "category":"Social Services",
            "subcategory":"Adult Care",
            "type":"Services"
        }
    ],
    "sg:phone":"+1 607 275 0067",
    "sg:postcode":"14850",
    "sg:province":"NY",
    "wof:name":"Bridges For Youth & Families",
    "wof:placetype":"venue"
},
  "geometry": {"coordinates":[-76.49937,42.439613],"type":"Point"}
}