{
  "type": "Feature",
  "properties": {
    "addr:full":"200 Hillside Ave New Hyde Park NY 11040",
    "addr:housenumber":"200",
    "addr:postcode":"11040",
    "addr:street":"Hillside Ave",
    "iso:country":"US",
    "sg:address":"200 Hillside Ave",
    "sg:city":"New Hyde Park",
    "sg:classifiers":[
        {
            "category":"Restaurant",
            "type":"Food & Drink"
        }
    ],
    "sg:phone":"+1 516 326 0481",
    "sg:postcode":"11040",
    "sg:province":"NY",
    "wof:name":"Pizza Hut",
    "wof:placetype":"venue"
},
  "geometry": {"coordinates":[-73.698926,40.740001],"type":"Point"}
}