{
  "type": "Feature",
  "properties": {
    "addr:full":"1 Avenue & Sixteen New York NY 10003",
    "addr:housenumber":"1",
    "addr:postcode":"10003",
    "addr:street":"Avenue & Sixteen",
    "iso:country":"US",
    "sg:address":"1 Avenue & Sixteen",
    "sg:city":"New York",
    "sg:classifiers":[
        {
            "category":"Health Services",
            "subcategory":"Doctor",
            "type":"Services"
        }
    ],
    "sg:phone":"+1 212 420 4132",
    "sg:postcode":"10003",
    "sg:province":"NY",
    "wof:name":"Simeon David MD",
    "wof:placetype":"venue"
},
  "geometry": {"coordinates":[-73.98157999999999,40.732646],"type":"Point"}
}