{
  "type": "Feature",
  "properties": {
    "addr:full":"349 Atlantic Ave Brooklyn NY 11217",
    "addr:housenumber":"349",
    "addr:postcode":"11217",
    "addr:street":"Atlantic Ave",
    "iso:country":"US",
    "sg:address":"349 Atlantic Ave",
    "sg:city":"Brooklyn",
    "sg:classifiers":[
        {
            "category":"Shopping",
            "type":"Retail Goods"
        }
    ],
    "sg:phone":"+1 718 797 5608",
    "sg:postcode":"11217",
    "sg:province":"NY",
    "sg:tags":[
        "material",
        "artist",
        "supply"
    ],
    "wof:name":"Art Artery Inc",
    "wof:placetype":"venue"
},
  "geometry": {"coordinates":[-73.98485700000001,40.687029],"type":"Point"}
}