{
  "type": "Feature",
  "properties": {
    "iso:country":"US",
    "sg:address":"7 Depot Plz",
    "sg:city":"Tarrytown",
    "sg:classifiers":[
        {
            "category":"Government",
            "subcategory":"Office",
            "type":"Public Place"
        }
    ],
    "sg:phone":"+1 914 332 0197",
    "sg:postcode":"10591",
    "sg:province":"NY",
    "sg:tags":[
        "county",
        "program"
    ],
    "wof:name":"Westchester Cnty Environmental",
    "wof:placetype":"venue"
},
  "geometry": {"coordinates":[-73.863218,41.076061],"type":"Point"}
}