{
  "type": "Feature",
  "properties": {
    "iso:country":"US",
    "sg:address":"2418 Belmont Ave",
    "sg:city":"Bronx",
    "sg:classifiers":[
        {
            "category":"Manufacturing",
            "subcategory":"Food",
            "type":"Manufacturing & Wholesale Goods"
        }
    ],
    "sg:phone":"+1   ",
    "sg:postcode":"10458",
    "sg:province":"NY",
    "sg:tags":[
        "mfg",
        "bread"
    ],
    "wof:name":"Prince Bakery Inc",
    "wof:placetype":"venue"
},
  "geometry": {"coordinates":[-73.885583,40.855385],"type":"Point"}
}