{
  "type": "Feature",
  "properties": {
    "addr:full":"17 Dederick St Kingston NY 12401",
    "addr:housenumber":"17",
    "addr:postcode":"12401",
    "addr:street":"Dederick St",
    "iso:country":"US",
    "sg:address":"17 Dederick St",
    "sg:city":"Kingston",
    "sg:classifiers":[
        {
            "category":"Manufacturing",
            "subcategory":"Printing",
            "type":"Manufacturing & Wholesale Goods"
        }
    ],
    "sg:phone":"+1 845 339 4455",
    "sg:postcode":"12401",
    "sg:province":"NY",
    "sg:tags":[
        "screen"
    ],
    "wof:name":"Sunshine Tees",
    "wof:placetype":"venue"
},
  "geometry": {"coordinates":[-74.000303,41.928409],"type":"Point"}
}