{
  "type": "Feature",
  "properties": {
    "addr:full":"29 Wispering Pine Bloomingburg NY 12721",
    "addr:housenumber":"29",
    "addr:postcode":"12721",
    "addr:street":"Wispering Pine",
    "iso:country":"US",
    "sg:address":"29 Wispering Pine",
    "sg:city":"Bloomingburg",
    "sg:classifiers":[
        {
            "category":"Professional",
            "subcategory":"Advertising",
            "type":"Services"
        }
    ],
    "sg:phone":"+1 845 733 1999",
    "sg:postcode":"12721",
    "sg:province":"NY",
    "sg:tags":[
        "counselor"
    ],
    "wof:name":"Texter Marketing Support Inc",
    "wof:placetype":"venue"
},
  "geometry": {"coordinates":[-74.424796,41.568171],"type":"Point"}
}