{
  "type": "Feature",
  "properties": {
    "addr:full":"210 Express St Plainview NY 11803",
    "addr:postcode":"11803",
    "addr:street":"St",
    "iso:country":"US",
    "sg:address":"210 Express St",
    "sg:city":"Plainview",
    "sg:classifiers":[
        {
            "category":"Manufacturing",
            "subcategory":"Electronics",
            "type":"Manufacturing & Wholesale Goods"
        }
    ],
    "sg:phone":"+1   ",
    "sg:postcode":"11803",
    "sg:province":"NY",
    "sg:tags":[
        "connector",
        "electronic"
    ],
    "wof:name":"EBY Group The",
    "wof:placetype":"venue"
},
  "geometry": {"coordinates":[-73.46350700000001,40.787836],"type":"Point"}
}