{
  "type": "Feature",
  "properties": {
    "iso:country":"US",
    "sg:address":"656 Suffolk Ave",
    "sg:city":"Brentwood",
    "sg:classifiers":[
        {
            "category":"Real Estate",
            "subcategory":"Real Estate Agent",
            "type":"Services"
        }
    ],
    "sg:phone":"+1 631 232 6063",
    "sg:postcode":"11717",
    "sg:province":"NY",
    "wof:name":"Jacmel Realty",
    "wof:placetype":"venue"
},
  "geometry": {"coordinates":[-73.250702,40.780102],"type":"Point"}
}