{
  "type": "Feature",
  "properties": {
    "iso:country":"US",
    "sg:address":"113 Downer St",
    "sg:city":"Baldwinsville",
    "sg:classifiers":[
        {
            "category":"Shopping",
            "subcategory":"Pharmacy",
            "type":"Retail Goods"
        }
    ],
    "sg:phone":"+1 315 635 8821",
    "sg:postcode":"13027",
    "sg:province":"NY",
    "wof:name":"Eckerd",
    "wof:placetype":"venue"
},
  "geometry": {"coordinates":[-76.34496300000001,43.151759],"type":"Point"}
}