{
  "type": "Feature",
  "properties": {
    "addr:full":"5899 E Taft Rd Syracuse NY 13212",
    "addr:housenumber":"5899",
    "addr:postcode":"13212",
    "addr:street":"E Taft Rd",
    "iso:country":"US",
    "sg:address":"5899 E Taft Rd",
    "sg:city":"Syracuse",
    "sg:classifiers":[
        {
            "category":"Restaurant",
            "type":"Food & Drink"
        }
    ],
    "sg:phone":"+1 315 884 4425",
    "sg:postcode":"13212",
    "sg:province":"NY",
    "sg:tags":[
        "caterer"
    ],
    "wof:name":"Bella Domani",
    "wof:placetype":"venue"
},
  "geometry": {"coordinates":[-76.11720099999999,43.12495],"type":"Point"}
}