{
  "type": "Feature",
  "properties": {
    "iso:country":"US",
    "sg:address":"5955 US Hwy 20",
    "sg:city":"La Fayette",
    "sg:classifiers":[
        {
            "category":"Education",
            "subcategory":"School",
            "type":"Public Place"
        }
    ],
    "sg:phone":"+1 315 677 3143",
    "sg:postcode":"13084",
    "sg:province":"NY",
    "sg:website":"www.lafayetteschools.org",
    "wof:name":"LA Fayette Central Schools",
    "wof:placetype":"venue"
},
  "geometry": {"coordinates":[-76.108356,42.892658],"type":"Point"}
}