{
  "type": "Feature",
  "properties": {
    "addr:full":"124 Hester St New York NY 10002",
    "addr:housenumber":"124",
    "addr:postcode":"10002",
    "addr:street":"Hester St",
    "iso:country":"US",
    "sg:address":"124 Hester St",
    "sg:city":"New York",
    "sg:classifiers":[
        {
            "category":"Personal",
            "subcategory":"Beauty Salon",
            "type":"Services"
        }
    ],
    "sg:phone":"+1 212 343 3088",
    "sg:postcode":"10002",
    "sg:province":"NY",
    "wof:name":"A S Beauty",
    "wof:placetype":"venue"
},
  "geometry": {"coordinates":[-73.995288,40.71714],"type":"Point"}
}