{
  "type": "Feature",
  "properties": {
    "addr:full":"2 Front St Bay Shore NY 11706",
    "addr:housenumber":"2",
    "addr:postcode":"11706",
    "addr:street":"Front St",
    "iso:country":"US",
    "sg:address":"2 Front St",
    "sg:city":"Bay Shore",
    "sg:classifiers":[
        {
            "category":"Building & Trades",
            "subcategory":"Cleaning & Sanitation",
            "type":"Services"
        }
    ],
    "sg:phone":"+1 631 666 2464",
    "sg:postcode":"11706",
    "sg:province":"NY",
    "sg:tags":[
        "window"
    ],
    "wof:name":"Brite View Window & Gutter",
    "wof:placetype":"venue"
},
  "geometry": {"coordinates":[-73.257352,40.73711],"type":"Point"}
}