{
  "type": "Feature",
  "properties": {
    "iso:country":"US",
    "sg:address":"203 S Main St",
    "sg:city":"North Syracuse",
    "sg:classifiers":[
        {
            "category":"Personal",
            "subcategory":"Beauty Salon",
            "type":"Services"
        }
    ],
    "sg:phone":"+1 315 214 0288",
    "sg:postcode":"13212",
    "sg:province":"NY",
    "wof:name":"Encore Salon & Day Spa",
    "wof:placetype":"venue"
},
  "geometry": {"coordinates":[-76.130526,43.133661],"type":"Point"}
}