{
  "type": "Feature",
  "properties": {
    "iso:country":"US",
    "sg:address":"55 W 116th St",
    "sg:city":"New York",
    "sg:classifiers":[
        {
            "category":"Professional",
            "subcategory":"Computer Services",
            "type":"Services"
        }
    ],
    "sg:phone":"+1   ",
    "sg:postcode":"10026",
    "sg:province":"NY",
    "sg:tags":[
        "related"
    ],
    "wof:name":"Electricmac Inc",
    "wof:placetype":"venue"
},
  "geometry": {"coordinates":[-73.948301,40.80134],"type":"Point"}
}