{
  "type": "Feature",
  "properties": {
    "addr:full":"16 Staniak Rd Mechanicville NY 12118",
    "addr:housenumber":"16",
    "addr:postcode":"12118",
    "addr:street":"Staniak Rd",
    "iso:country":"US",
    "sg:address":"16 Staniak Rd",
    "sg:city":"Mechanicville",
    "sg:classifiers":[
        {
            "category":"Building & Trades",
            "subcategory":"Construction",
            "type":"Services"
        }
    ],
    "sg:phone":"+1 518 664 2409",
    "sg:postcode":"12118",
    "sg:province":"NY",
    "sg:tags":[
        "concrete",
        "contractor"
    ],
    "wof:name":"McClimans Asphalt Paving",
    "wof:placetype":"venue"
},
  "geometry": {"coordinates":[-73.73018999999999,42.905018],"type":"Point"}
}