{
  "type": "Feature",
  "properties": {
    "iso:country":"US",
    "sg:address":"551 5th Ave",
    "sg:city":"New York",
    "sg:classifiers":[
        {
            "category":"Professional",
            "subcategory":"Lawyer & Legal Services",
            "type":"Services"
        }
    ],
    "sg:phone":"+1 212 586 4700",
    "sg:postcode":"10176",
    "sg:province":"NY",
    "wof:name":"Lasky Floria V Atty",
    "wof:placetype":"venue"
},
  "geometry": {"coordinates":[-73.979797,40.755299],"type":"Point"}
}