{
  "type": "Feature",
  "properties": {
    "addr:full":"8119 7th Ave Brooklyn NY 11228",
    "addr:housenumber":"8119",
    "addr:postcode":"11228",
    "addr:street":"7Th Ave",
    "iso:country":"US",
    "sg:address":"8119 7th Ave",
    "sg:city":"Brooklyn",
    "sg:classifiers":[
        {
            "category":"Professional",
            "subcategory":"Lawyer & Legal Services",
            "type":"Services"
        }
    ],
    "sg:phone":"+1 718 836 3800",
    "sg:postcode":"11228",
    "sg:province":"NY",
    "wof:name":"Bacotti Louis J Atty",
    "wof:placetype":"venue"
},
  "geometry": {"coordinates":[-74.019699,40.6217],"type":"Point"}
}