{
  "type": "Feature",
  "properties": {
    "iso:country":"US",
    "sg:address":"872 Fams Ct",
    "sg:city":"East Meadow",
    "sg:classifiers":[
        {
            "category":"Building & Trades",
            "subcategory":"Construction",
            "type":"Services"
        }
    ],
    "sg:phone":"+1 516 292 8570",
    "sg:postcode":"11554",
    "sg:province":"NY",
    "sg:tags":[
        "house"
    ],
    "wof:name":"Gje Construction Inc",
    "wof:placetype":"venue"
},
  "geometry": {"coordinates":[-73.549802,40.702549],"type":"Point"}
}