{
  "type": "Feature",
  "properties": {
    "iso:country":"US",
    "sg:address":"1328 Broadway",
    "sg:city":"New York",
    "sg:classifiers":[
        {
            "category":"Wholesale",
            "subcategory":"Apparel",
            "type":"Manufacturing & Wholesale Goods"
        }
    ],
    "sg:phone":"+1 212 714 0444",
    "sg:postcode":"10001",
    "sg:province":"NY",
    "sg:tags":[
        "textile",
        "converter"
    ],
    "wof:name":"Vzr Sales Corp",
    "wof:placetype":"venue"
},
  "geometry": {"coordinates":[-73.987816,40.749902],"type":"Point"}
}