{
  "type": "Feature",
  "properties": {
    "addr:full":"824 Evergreen Dr West Hempstead NY 11552",
    "addr:housenumber":"824",
    "addr:postcode":"11552",
    "addr:street":"Evergreen Dr West",
    "iso:country":"US",
    "sg:address":"824 Evergreen Dr",
    "sg:city":"West Hempstead",
    "sg:classifiers":[
        {
            "category":"Professional",
            "subcategory":"Employment Agencies",
            "type":"Services"
        }
    ],
    "sg:phone":"+1 516 385 3339",
    "sg:postcode":"11552",
    "sg:province":"NY",
    "wof:name":"Nycpa Jbs",
    "wof:placetype":"venue"
},
  "geometry": {"coordinates":[-73.66736299999999,40.685169],"type":"Point"}
}