{
  "type": "Feature",
  "properties": {
    "addr:full":"195 Kingsland Avenue Brooklyn NY 11222",
    "addr:housenumber":"195",
    "addr:postcode":"11222",
    "addr:street":"Kingsland Avenue",
    "iso:country":"US",
    "sg:address":"195 Kingsland Avenue",
    "sg:city":"Brooklyn",
    "sg:classifiers":[
        {
            "category":"Building & Trades",
            "subcategory":"Construction",
            "type":"Services"
        }
    ],
    "sg:phone":"+1 718 383 5661",
    "sg:postcode":"11222",
    "sg:province":"NY",
    "sg:tags":[
        "contractor"
    ],
    "wof:name":"G E M American Construction Corporation",
    "wof:placetype":"venue"
},
  "geometry": {"coordinates":[-73.94139,40.723184],"type":"Point"}
}