{
  "type": "Feature",
  "properties": {
    "addr:full":"7885 State Rd Colden NY 14033",
    "addr:housenumber":"7885",
    "addr:postcode":"14033",
    "addr:street":"State Rd",
    "iso:country":"US",
    "sg:address":"7885 State Rd",
    "sg:city":"Colden",
    "sg:classifiers":[
        {
            "category":"Organizations",
            "subcategory":"Religious Organization",
            "type":"Services"
        }
    ],
    "sg:phone":"+1 716 592 0785",
    "sg:postcode":"14033",
    "sg:province":"NY",
    "wof:name":"Jehovah's Witnesses",
    "wof:placetype":"venue"
},
  "geometry": {"coordinates":[-78.682728,42.671183],"type":"Point"}
}