{
  "type": "Feature",
  "properties": {
    "addr:full":"72 Mohawk St Cohoes NY 12047",
    "addr:housenumber":"72",
    "addr:postcode":"12047",
    "addr:street":"Mohawk St",
    "iso:country":"US",
    "sg:address":"72 Mohawk St",
    "sg:city":"Cohoes",
    "sg:classifiers":[
        {
            "category":"Banks & Credit Unions",
            "subcategory":"Bank",
            "type":"Services"
        }
    ],
    "sg:phone":"+1 518 237 2370",
    "sg:postcode":"12047",
    "sg:province":"NY",
    "wof:name":"First Niagara Bank",
    "wof:placetype":"venue"
},
  "geometry": {"coordinates":[-73.70016099999999,42.774963],"type":"Point"}
}