{
  "type": "Feature",
  "properties": {
    "addr:full":"512 Horseblock Rd Farmingville NY 11738",
    "addr:housenumber":"512",
    "addr:postcode":"11738",
    "addr:street":"Horseblock Rd",
    "iso:country":"US",
    "sg:address":"512 Horseblock Rd",
    "sg:city":"Farmingville",
    "sg:classifiers":[
        {
            "category":"Professional",
            "subcategory":"Lawyer & Legal Services",
            "type":"Services"
        }
    ],
    "sg:phone":"+1 631 846 9844",
    "sg:postcode":"11738",
    "sg:province":"NY",
    "wof:name":"John Walsh Signs",
    "wof:placetype":"venue"
},
  "geometry": {"coordinates":[-73.178147,40.834183],"type":"Point"}
}