{
  "type": "Feature",
  "properties": {
    "addr:full":"374 Mooney Pond Rd Ste E Farmingville NY 11738",
    "addr:housenumber":"374",
    "addr:postcode":"11738",
    "addr:street":"Mooney Pond Rd Ste E Farmingville",
    "iso:country":"US",
    "sg:address":"374 Mooney Pond Rd Ste E",
    "sg:city":"Farmingville",
    "sg:classifiers":[
        {
            "category":"Personal",
            "subcategory":"Beauty Salon",
            "type":"Services"
        }
    ],
    "sg:phone":"+1 631 732 9843",
    "sg:postcode":"11738",
    "sg:province":"NY",
    "sg:tags":[
        "hair",
        "stylist"
    ],
    "wof:name":"Studio Ii Hair Designers",
    "wof:placetype":"venue"
},
  "geometry": {"coordinates":[-73.041786,40.852049],"type":"Point"}
}