{
  "type": "Feature",
  "properties": {
    "addr:full":"45 W 47 St New York NY 10036",
    "addr:housenumber":"45",
    "addr:postcode":"10036",
    "addr:street":"W 47 St",
    "iso:country":"US",
    "sg:address":"45 W 47 St",
    "sg:city":"New York",
    "sg:classifiers":[
        {
            "category":"Shopping",
            "subcategory":"Jewelry",
            "type":"Retail Goods"
        }
    ],
    "sg:phone":"+1 212 302 1259",
    "sg:postcode":"10036",
    "sg:province":"NY",
    "sg:tags":[
        "jeweler"
    ],
    "wof:name":"Murat's Engraver",
    "wof:placetype":"venue"
},
  "geometry": {"coordinates":[-73.980659,40.757473],"type":"Point"}
}