{
  "type": "Feature",
  "properties": {
    "iso:country":"US",
    "sg:address":"12611 Seneca Rd",
    "sg:city":"Irving",
    "sg:classifiers":[
        {
            "category":"Building & Trades",
            "subcategory":"Construction",
            "type":"Services"
        }
    ],
    "sg:phone":"+1 716 934 3976",
    "sg:postcode":"14081",
    "sg:province":"NY",
    "sg:tags":[
        "roofing",
        "contractor"
    ],
    "wof:name":"Superior Roofing",
    "wof:placetype":"venue"
},
  "geometry": {"coordinates":[-79.12621900000001,42.55598],"type":"Point"}
}