{
  "type": "Feature",
  "properties": {
    "addr:full":"4611 White Plains Rd Bronx NY 10470",
    "addr:housenumber":"4611",
    "addr:postcode":"10470",
    "addr:street":"White Plains Rd",
    "iso:country":"US",
    "sg:address":"4611 White Plains Rd",
    "sg:city":"Bronx",
    "sg:classifiers":[
        {
            "category":"Travel",
            "subcategory":"Travel Agent",
            "type":"Entertainment"
        }
    ],
    "sg:phone":"+1 718 994 4026",
    "sg:postcode":"10470",
    "sg:province":"NY",
    "sg:tags":[
        "agency",
        "bureau"
    ],
    "wof:name":"Campbell Travel Agency",
    "wof:placetype":"venue"
},
  "geometry": {"coordinates":[-73.85052899999999,40.903327],"type":"Point"}
}