{
  "type": "Feature",
  "properties": {
    "iso:country":"US",
    "sg:address":"55 N Howells Point Rd",
    "sg:city":"Bellport",
    "sg:classifiers":[
        {
            "category":"Building & Trades",
            "subcategory":"Electrical",
            "type":"Services"
        }
    ],
    "sg:phone":"+1 631 286 6623",
    "sg:postcode":"11713",
    "sg:province":"NY",
    "sg:tags":[
        "electric",
        "industrial",
        "contractors-commercial",
        "contractor"
    ],
    "wof:name":"Evergreen Electric",
    "wof:placetype":"venue"
},
  "geometry": {"coordinates":[-72.94513600000001,40.760533],"type":"Point"}
}