{
  "type": "Feature",
  "properties": {
    "addr:full":"105 Oak St Corinth NY 12822",
    "addr:housenumber":"105",
    "addr:postcode":"12822",
    "addr:street":"Oak St",
    "iso:country":"US",
    "sg:address":"105 Oak St",
    "sg:city":"Corinth",
    "sg:classifiers":[
        {
            "category":"Education",
            "subcategory":"School",
            "type":"Public Place"
        }
    ],
    "sg:phone":"+1 518 654 2960",
    "sg:postcode":"12822",
    "sg:province":"NY",
    "wof:name":"Corinth Central Elementary Sch",
    "wof:placetype":"venue"
},
  "geometry": {"coordinates":[-73.827112,43.24227],"type":"Point"}
}