{
  "type": "Feature",
  "properties": {
    "iso:country":"US",
    "sg:address":"301 3rd Ave",
    "sg:city":"Brooklyn",
    "sg:classifiers":[
        {
            "category":"Wholesale",
            "subcategory":"Electrical",
            "type":"Manufacturing & Wholesale Goods"
        }
    ],
    "sg:phone":"+1 718 646 6561",
    "sg:postcode":"11215",
    "sg:province":"NY",
    "sg:tags":[
        "fire",
        "equipment",
        "protection"
    ],
    "wof:name":"Bell Fire Extinguisher Co Inc",
    "wof:placetype":"venue"
},
  "geometry": {"coordinates":[-73.98674800000001,40.676528],"type":"Point"}
}