{
  "type": "Feature",
  "properties": {
    "iso:country":"US",
    "sg:address":"636 2nd Ave",
    "sg:city":"Troy",
    "sg:classifiers":[
        {
            "category":"Building & Trades",
            "subcategory":"Electrical",
            "type":"Services"
        }
    ],
    "sg:phone":"+1 518 237 1893",
    "sg:postcode":"12182",
    "sg:province":"NY",
    "sg:tags":[
        "electrical",
        "contractor"
    ],
    "wof:name":"T & J Electrical Corp",
    "wof:placetype":"venue"
},
  "geometry": {"coordinates":[-73.67557100000001,42.778103],"type":"Point"}
}