{
  "type": "Feature",
  "properties": {
    "iso:country":"US",
    "sg:address":"875 3rd Ave Lowr 12",
    "sg:city":"New York",
    "sg:classifiers":[
        {
            "category":"Restaurant",
            "type":"Food & Drink"
        }
    ],
    "sg:phone":"+1 212 355 5303",
    "sg:postcode":"10022",
    "sg:province":"NY",
    "sg:tags":[
        "sushi",
        "bar"
    ],
    "wof:name":"875 Sushi Corp",
    "wof:placetype":"venue"
},
  "geometry": {"coordinates":[-73.969234,40.757608],"type":"Point"}
}