{
  "type": "Feature",
  "properties": {
    "iso:country":"US",
    "sg:address":"116 Westchester Ave",
    "sg:city":"Port Chester",
    "sg:classifiers":[
        {
            "category":"Food & Beverages",
            "subcategory":"Groceries & Convenience Stores",
            "type":"Retail Goods"
        }
    ],
    "sg:phone":"+1 914 937 6220",
    "sg:postcode":"10573",
    "sg:province":"NY",
    "sg:tags":[
        "grocer"
    ],
    "wof:name":"Port Chester Farm",
    "wof:placetype":"venue"
},
  "geometry": {"coordinates":[-73.665153,41.000897],"type":"Point"}
}