{
  "type": "Feature",
  "properties": {
    "addr:full":"90 N Main Ave Albany NY 12206",
    "addr:housenumber":"90",
    "addr:postcode":"12206",
    "addr:street":"N Main Ave",
    "iso:country":"US",
    "sg:address":"90 N Main Ave",
    "sg:city":"Albany",
    "sg:classifiers":[
        {
            "category":"Government",
            "subcategory":"Office",
            "type":"Public Place"
        }
    ],
    "sg:phone":"+1 518 438 3546",
    "sg:postcode":"12206",
    "sg:province":"NY",
    "sg:tags":[
        "federal",
        "security"
    ],
    "wof:name":"US Army Reserve Ctr",
    "wof:placetype":"venue"
},
  "geometry": {"coordinates":[-73.78431999999999,42.6689],"type":"Point"}
}