{
  "type": "Feature",
  "properties": {
    "addr:full":"147 Belmont Blvd Elmont NY 11003",
    "addr:housenumber":"147",
    "addr:postcode":"11003",
    "addr:street":"Belmont Blvd",
    "iso:country":"US",
    "sg:address":"147 Belmont Blvd",
    "sg:city":"Elmont",
    "sg:classifiers":[
        {
            "category":"Professional",
            "subcategory":"Detective & Security Services",
            "type":"Services"
        }
    ],
    "sg:phone":"+1   ",
    "sg:postcode":"11003",
    "sg:province":"NY",
    "sg:tags":[
        "car"
    ],
    "wof:name":"Golden Glow Investigative",
    "wof:placetype":"venue"
},
  "geometry": {"coordinates":[-73.701812,40.702482],"type":"Point"}
}