{
  "type": "Feature",
  "properties": {
    "iso:country":"US",
    "sg:address":"65 Cherry Plain Sq",
    "sg:city":"Cherry Plain",
    "sg:classifiers":[
        {
            "category":"Government",
            "subcategory":"Post Office",
            "type":"Public Place"
        }
    ],
    "sg:phone":"+1 518 658 2503",
    "sg:postcode":"12040",
    "sg:province":"NY",
    "wof:name":"US Post Office",
    "wof:placetype":"venue"
},
  "geometry": {"coordinates":[-73.360111,42.627097],"type":"Point"}
}