{
  "type": "Feature",
  "properties": {
    "addr:full":"162 Hicksville Rd Bethpage NY 11714",
    "addr:housenumber":"162",
    "addr:postcode":"11714",
    "addr:street":"Hicksville Rd",
    "iso:country":"US",
    "sg:address":"162 Hicksville Rd",
    "sg:city":"Bethpage",
    "sg:classifiers":[
        {
            "category":"Deli",
            "type":"Food & Drink"
        }
    ],
    "sg:menulink":"http://www.allmenus.com/ny/plainedge/243886-super-suppers/menu/",
    "sg:phone":"+1 516 520 0503",
    "sg:postcode":"11714",
    "sg:province":"NY",
    "sg:tags":[
        "american"
    ],
    "wof:name":"Super Suppers",
    "wof:placetype":"venue"
},
  "geometry": {"coordinates":[-73.49008499999999,40.727681],"type":"Point"}
}