{
  "type": "Feature",
  "properties": {
    "addr:full":"1022 Pulaski Hwy Goshen NY 10924",
    "addr:housenumber":"1022",
    "addr:postcode":"10924",
    "addr:street":"Pulaski Hwy",
    "iso:country":"US",
    "sg:address":"1022 Pulaski Hwy",
    "sg:city":"Goshen",
    "sg:classifiers":[
        {
            "category":"Manufacturing",
            "subcategory":"Food",
            "type":"Manufacturing & Wholesale Goods"
        },
        {
            "category":"Food & Beverages",
            "subcategory":"Groceries & Convenience Stores",
            "type":"Retail Goods"
        }
    ],
    "sg:phone":"+1 845 651 4490",
    "sg:postcode":"10924",
    "sg:province":"NY",
    "sg:tags":[
        "frozen"
    ],
    "wof:name":"Panda Food Products Inc",
    "wof:placetype":"venue"
},
  "geometry": {"coordinates":[-74.386208,41.35183],"type":"Point"}
}