{
  "type": "Feature",
  "properties": {
    "iso:country":"US",
    "sg:address":"913 Saw Mill River Rd",
    "sg:city":"Ardsley",
    "sg:classifiers":[
        {
            "category":"Personal",
            "subcategory":"Beauty Salon",
            "type":"Services"
        }
    ],
    "sg:phone":"+1 914 693 8080",
    "sg:postcode":"10502",
    "sg:province":"NY",
    "wof:name":"Kim's Beauty Salon",
    "wof:placetype":"venue"
},
  "geometry": {"coordinates":[-73.84382600000001,41.019319],"type":"Point"}
}