{
  "type": "Feature",
  "properties": {
    "iso:country":"US",
    "sg:address":"1515 Route 22 Ste D2",
    "sg:city":"Brewster",
    "sg:classifiers":[
        {
            "category":"Coffee & Tea",
            "type":"Food & Drink"
        },
        {
            "category":"Restaurant",
            "type":"Food & Drink"
        },
        {
            "category":"Bakery",
            "type":"Food & Drink"
        },
        {
            "category":"Bagels",
            "subcategory":"None",
            "type":"Food & Drink"
        }
    ],
    "sg:phone":"+1 845 278 6002",
    "sg:postcode":"10509",
    "sg:province":"NY",
    "sg:tags":[
        "espresso"
    ],
    "wof:name":"Tom Tom Bagel Cafe",
    "wof:placetype":"venue"
},
  "geometry": {"coordinates":[-73.577264,41.422306],"type":"Point"}
}