{
  "type": "Feature",
  "properties": {
    "iso:country":"US",
    "sg:address":"49 Amherst Ct",
    "sg:city":"Rockville Centre",
    "sg:classifiers":[
        {
            "category":"Travel",
            "subcategory":"Travel Agent",
            "type":"Entertainment"
        }
    ],
    "sg:phone":"+1   ",
    "sg:postcode":"11570",
    "sg:province":"NY",
    "sg:tags":[
        "agency"
    ],
    "wof:name":"Donlon Travel Service Inc",
    "wof:placetype":"venue"
},
  "geometry": {"coordinates":[-73.634773,40.671493],"type":"Point"}
}