{
  "type": "Feature",
  "properties": {
    "addr:full":"110 8th St Troy NY 12180",
    "addr:housenumber":"110",
    "addr:postcode":"12180",
    "addr:street":"8Th St",
    "iso:country":"US",
    "sg:address":"110 8th St",
    "sg:city":"Troy",
    "sg:classifiers":[
        {
            "category":"Manufacturing",
            "subcategory":"Printing",
            "type":"Manufacturing & Wholesale Goods"
        }
    ],
    "sg:phone":"+1   ",
    "sg:postcode":"12180",
    "sg:province":"NY",
    "sg:tags":[
        "publishing"
    ],
    "wof:name":"R P I Envmtl Mgt & Politics",
    "wof:placetype":"venue"
},
  "geometry": {"coordinates":[-73.68392900000001,42.731107],"type":"Point"}
}