{
  "type": "Feature",
  "properties": {
    "addr:full":"1420 6 Ave New York NY 10019",
    "addr:housenumber":"1420",
    "addr:postcode":"10019",
    "addr:street":"6 Ave",
    "iso:country":"US",
    "sg:address":"1420 6 Ave",
    "sg:city":"New York",
    "sg:classifiers":[
        {
            "category":"Shopping",
            "subcategory":"Luggage & Leather Goods",
            "type":"Retail Goods"
        }
    ],
    "sg:phone":"+1 212 224 0142",
    "sg:postcode":"10019",
    "sg:province":"NY",
    "wof:name":"Agape Sarang Inc",
    "wof:placetype":"venue"
},
  "geometry": {"coordinates":[-73.979513,40.761148],"type":"Point"}
}