{
  "type": "Feature",
  "properties": {
    "iso:country":"US",
    "sg:address":"201 West 21st St 15D",
    "sg:city":"New York",
    "sg:classifiers":[
        {
            "category":"Personal",
            "subcategory":"Hair Removal",
            "type":"Services"
        }
    ],
    "sg:phone":"+1 212 633 1503",
    "sg:postcode":"10011",
    "sg:province":"NY",
    "sg:website":"www.affordablepermanentelectroly...",
    "wof:name":"Affordable Permanent Electrolysis",
    "wof:placetype":"venue"
},
  "geometry": {"coordinates":[-73.996802,40.743],"type":"Point"}
}