{
  "type": "Feature",
  "properties": {
    "iso:country":"US",
    "sg:address":"24 Ohio St",
    "sg:city":"Oswego",
    "sg:classifiers":[
        {
            "category":"Professional",
            "type":"Services"
        }
    ],
    "sg:phone":"+1 315 343 6414",
    "sg:postcode":"13126",
    "sg:province":"NY",
    "sg:tags":[
        "establishment"
    ],
    "wof:name":"KDE Inc",
    "wof:placetype":"venue"
},
  "geometry": {"coordinates":[-76.507369,43.447412],"type":"Point"}
}