{
  "type": "Feature",
  "properties": {
    "addr:full":"1657 Hannington Ave Wantagh NY 11793",
    "addr:housenumber":"1657",
    "addr:postcode":"11793",
    "addr:street":"Hannington Ave",
    "iso:country":"US",
    "sg:address":"1657 Hannington Ave",
    "sg:city":"Wantagh",
    "sg:classifiers":[
        {
            "category":"Shopping",
            "subcategory":"Florist",
            "type":"Retail Goods"
        }
    ],
    "sg:phone":"+1   ",
    "sg:postcode":"11793",
    "sg:province":"NY",
    "wof:name":"Argyle Flower and Garden Ltd",
    "wof:placetype":"venue"
},
  "geometry": {"coordinates":[-73.51966400000001,40.68099],"type":"Point"}
}