{
  "type": "Feature",
  "properties": {
    "iso:country":"US",
    "sg:address":"7 Delavergne Ave",
    "sg:city":"Wappingers Falls",
    "sg:classifiers":[
        {
            "category":"Retail",
            "subcategory":"Auto Repair",
            "type":"Services"
        }
    ],
    "sg:phone":"+1 845 298 6118",
    "sg:postcode":"12590",
    "sg:province":"NY",
    "sg:tags":[
        "repairing",
        "automobile"
    ],
    "wof:name":"Community Car Care",
    "wof:placetype":"venue"
},
  "geometry": {"coordinates":[-73.922848,41.608235],"type":"Point"}
}