{
  "type": "Feature",
  "properties": {
    "addr:full":"307 Kimberly Dr E Syracuse NY 13219",
    "addr:housenumber":"307",
    "addr:postcode":"13219",
    "addr:street":"Kimberly Dr E",
    "iso:country":"US",
    "sg:address":"307 Kimberly Dr E",
    "sg:city":"Syracuse",
    "sg:classifiers":[
        {
            "category":"Bars & Pubs",
            "type":"Food & Drink"
        }
    ],
    "sg:phone":"+1   ",
    "sg:postcode":"13219",
    "sg:province":"NY",
    "sg:tags":[
        "drinking"
    ],
    "wof:name":"Velvet Undergrand",
    "wof:placetype":"venue"
},
  "geometry": {"coordinates":[-76.229232,43.045632],"type":"Point"}
}