{
  "type": "Feature",
  "properties": {
    "iso:country":"US",
    "sg:address":"334 Phyllis Dr",
    "sg:city":"Patchogue",
    "sg:classifiers":[
        {
            "category":"Professional",
            "subcategory":"Detective & Security Services",
            "type":"Services"
        }
    ],
    "sg:phone":"+1 631 207 2582",
    "sg:postcode":"11772",
    "sg:province":"NY",
    "sg:tags":[
        "investigator"
    ],
    "wof:name":"Access Private Investigations",
    "wof:placetype":"venue"
},
  "geometry": {"coordinates":[-72.997896,40.784915],"type":"Point"}
}