{
  "type": "Feature",
  "properties": {
    "addr:full":"1398 Victory Blvd Staten Island NY 10301",
    "addr:housenumber":"1398",
    "addr:postcode":"10301",
    "addr:street":"Victory Blvd",
    "iso:country":"US",
    "sg:address":"1398 Victory Blvd",
    "sg:city":"Staten Island",
    "sg:classifiers":[
        {
            "category":"Health Services",
            "subcategory":"Podiatrist",
            "type":"Services"
        }
    ],
    "sg:phone":"+1 718 981 4515",
    "sg:postcode":"10301",
    "sg:province":"NY",
    "wof:name":"Clove Lakes Foot Care",
    "wof:placetype":"venue"
},
  "geometry": {"coordinates":[-74.110995,40.614156],"type":"Point"}
}