{
  "type": "Feature",
  "properties": {
    "addr:full":"2753 US Hwy 20 Cazenovia NY 13035",
    "addr:housenumber":"2753",
    "addr:postcode":"13035",
    "addr:street":"Us Hwy 20",
    "iso:country":"US",
    "sg:address":"2753 US Hwy 20",
    "sg:city":"Cazenovia",
    "sg:classifiers":[
        {
            "category":"Social Services",
            "type":"Services"
        }
    ],
    "sg:phone":"+1   ",
    "sg:postcode":"13035",
    "sg:province":"NY",
    "wof:name":"Cazenovia Senior Services",
    "wof:placetype":"venue"
},
  "geometry": {"coordinates":[-75.81339,42.919671],"type":"Point"}
}