{
  "type": "Feature",
  "properties": {
    "addr:full":"3207 Fulton St Brooklyn NY 11208",
    "addr:housenumber":"3207",
    "addr:postcode":"11208",
    "addr:street":"Fulton St",
    "iso:country":"US",
    "sg:address":"3207 Fulton St",
    "sg:city":"Brooklyn",
    "sg:classifiers":[
        {
            "category":"Taxi",
            "type":"Transportation"
        }
    ],
    "sg:phone":"+1 718 277 3353",
    "sg:postcode":"11208",
    "sg:province":"NY",
    "sg:tags":[
        "taxicab"
    ],
    "wof:name":"Atlantic Car Svc",
    "wof:placetype":"venue"
},
  "geometry": {"coordinates":[-73.877674,40.682086],"type":"Point"}
}