{
  "type": "Feature",
  "properties": {
    "addr:full":"25 Walker Way Albany NY 12205",
    "addr:housenumber":"25",
    "addr:postcode":"12205",
    "addr:street":"Walker Way",
    "iso:country":"US",
    "sg:address":"25 Walker Way",
    "sg:city":"Albany",
    "sg:classifiers":[
        {
            "category":"Shopping",
            "subcategory":"Bicycles & Sporting Goods",
            "type":"Retail Goods"
        }
    ],
    "sg:phone":"+1   ",
    "sg:postcode":"12205",
    "sg:province":"NY",
    "sg:tags":[
        "repair",
        "golf"
    ],
    "wof:name":"Clubery The",
    "wof:placetype":"venue"
},
  "geometry": {"coordinates":[-73.83773600000001,42.718044],"type":"Point"}
}