{
  "type": "Feature",
  "properties": {
    "iso:country":"US",
    "sg:address":"14 Andover Dr",
    "sg:city":"Syosset",
    "sg:classifiers":[
        {
            "category":"Building & Trades",
            "subcategory":"Cleaning & Sanitation",
            "type":"Services"
        }
    ],
    "sg:phone":"+1   ",
    "sg:postcode":"11791",
    "sg:province":"NY",
    "sg:tags":[
        "janitorial"
    ],
    "wof:name":"All Facilities Maint Corp",
    "wof:placetype":"venue"
},
  "geometry": {"coordinates":[-73.49412100000001,40.795725],"type":"Point"}
}