{
  "type": "Feature",
  "properties": {
    "addr:full":"5524 13th Ave Brooklyn NY 11219",
    "addr:housenumber":"5524",
    "addr:postcode":"11219",
    "addr:street":"13Th Ave",
    "iso:country":"US",
    "sg:address":"5524 13th Ave",
    "sg:city":"Brooklyn",
    "sg:classifiers":[
        {
            "category":"Real Estate",
            "subcategory":"Real Estate Agent",
            "type":"Services"
        }
    ],
    "sg:phone":"+1 718 972 4799",
    "sg:postcode":"11219",
    "sg:province":"NY",
    "wof:name":"Ben Zucker Real Estate",
    "wof:placetype":"venue"
},
  "geometry": {"coordinates":[-73.99614699999999,40.631289],"type":"Point"}
}