{
  "type": "Feature",
  "properties": {
    "addr:full":"1407 Broadway New York NY 10018",
    "addr:housenumber":"1407",
    "addr:postcode":"10018",
    "addr:street":"Broadway",
    "iso:country":"US",
    "sg:address":"1407 Broadway",
    "sg:city":"New York",
    "sg:classifiers":[
        {
            "category":"Wholesale",
            "subcategory":"Apparel",
            "type":"Manufacturing & Wholesale Goods"
        }
    ],
    "sg:phone":"+1 212 382 1888",
    "sg:postcode":"10018",
    "sg:province":"NY",
    "sg:tags":[
        "clothing"
    ],
    "wof:name":"Fob NY Inc",
    "wof:placetype":"venue"
},
  "geometry": {"coordinates":[-73.987309,40.752999],"type":"Point"}
}