{
  "type": "Feature",
  "properties": {
    "iso:country":"US",
    "sg:address":"140 Central Ave",
    "sg:city":"Lawrence",
    "sg:classifiers":[
        {
            "category":"Social Services",
            "subcategory":"Child Care",
            "type":"Services"
        },
        {
            "category":"Education",
            "subcategory":"Preschool",
            "type":"Public Place"
        },
        {
            "category":"Education",
            "subcategory":"School",
            "type":"Public Place"
        }
    ],
    "sg:phone":"+1 516 239 0305",
    "sg:postcode":"11559",
    "sg:province":"NY",
    "sg:tags":[
        "elementary",
        "day"
    ],
    "wof:name":"Jewish Community Council",
    "wof:placetype":"venue"
},
  "geometry": {"coordinates":[-73.739773,40.612405],"type":"Point"}
}