{
  "type": "Feature",
  "properties": {
    "addr:full":"105 Edgecombe Ave New York NY 10030",
    "addr:housenumber":"105",
    "addr:postcode":"10030",
    "addr:street":"Edgecombe Ave",
    "iso:country":"US",
    "sg:address":"105 Edgecombe Ave",
    "sg:city":"New York",
    "sg:classifiers":[
        {
            "category":"Professional",
            "subcategory":"Management & Consulting",
            "type":"Services"
        }
    ],
    "sg:phone":"+1 917 640 6156",
    "sg:postcode":"10030",
    "sg:province":"NY",
    "sg:tags":[
        "consultant"
    ],
    "wof:name":"A J Consulting & Productions",
    "wof:placetype":"venue"
},
  "geometry": {"coordinates":[-73.94561299999999,40.820254],"type":"Point"}
}