{
  "type": "Feature",
  "properties": {
    "addr:full":"122 E 42nd St Rm 606 New York NY 10168",
    "addr:housenumber":"122;606",
    "addr:postcode":"10168",
    "addr:street":"E 42Nd St Rm",
    "iso:country":"US",
    "sg:address":"122 E 42nd St Rm 606",
    "sg:city":"New York",
    "sg:classifiers":[
        {
            "category":"Professional",
            "subcategory":"Lawyer & Legal Services",
            "type":"Services"
        }
    ],
    "sg:phone":"+1 212 972 7505",
    "sg:postcode":"10168",
    "sg:province":"NY",
    "wof:name":"Andrews Bradley Esq",
    "wof:placetype":"venue"
},
  "geometry": {"coordinates":[-73.97598600000001,40.751544],"type":"Point"}
}