{
  "type": "Feature",
  "properties": {
    "addr:full":"7547 Metropolitan Ave Middle Village NY 11379",
    "addr:housenumber":"7547",
    "addr:postcode":"11379",
    "addr:street":"Metropolitan Ave",
    "iso:country":"US",
    "sg:address":"7547 Metropolitan Ave",
    "sg:city":"Middle Village",
    "sg:classifiers":[
        {
            "category":"Arts & Performance",
            "subcategory":"Arts Center",
            "type":"Entertainment"
        },
        {
            "category":"Education",
            "subcategory":"Special Training",
            "type":"Public Place"
        },
        {
            "category":"Retail",
            "subcategory":"Event Space",
            "type":"Services"
        },
        {
            "category":"Professional",
            "type":"Services"
        }
    ],
    "sg:phone":"+1 718 326 2121",
    "sg:postcode":"11379",
    "sg:province":"NY",
    "sg:tags":[
        "school",
        "performing",
        "venue",
        "specialty",
        "caterer"
    ],
    "wof:name":"Dance Club International",
    "wof:placetype":"venue"
},
  "geometry": {"coordinates":[-73.875888,40.713321],"type":"Point"}
}