{
  "type": "Feature",
  "properties": {
    "addr:full":"16 Highfield Dr Dix Hills NY 11746",
    "addr:housenumber":"16",
    "addr:postcode":"11746",
    "addr:street":"Highfield Dr",
    "iso:country":"US",
    "sg:address":"16 Highfield Dr",
    "sg:city":"Dix Hills",
    "sg:classifiers":[
        {
            "category":"Building & Trades",
            "subcategory":"Landscaping Services",
            "type":"Services"
        }
    ],
    "sg:phone":"+1 631 421 0044",
    "sg:postcode":"11746",
    "sg:province":"NY",
    "sg:tags":[
        "lawn",
        "maintenance",
        "grounds"
    ],
    "wof:name":"Grassland LLC",
    "wof:placetype":"venue"
},
  "geometry": {"coordinates":[-73.365471,40.800927],"type":"Point"}
}