{
  "type": "Feature",
  "properties": {
    "addr:full":"39 Grove St New York NY 10014",
    "addr:housenumber":"39",
    "addr:postcode":"10014",
    "addr:street":"Grove St",
    "iso:country":"US",
    "sg:address":"39 Grove St",
    "sg:city":"New York",
    "sg:classifiers":[
        {
            "category":"Bars & Pubs",
            "type":"Food & Drink"
        },
        {
            "category":"Restaurant",
            "type":"Food & Drink"
        }
    ],
    "sg:phone":"+1 212 206 7691",
    "sg:postcode":"10014",
    "sg:province":"NY",
    "sg:tags":[
        "german"
    ],
    "sg:website":"www.lederhosennyc.com/",
    "wof:name":"Lederhosen",
    "wof:placetype":"venue"
},
  "geometry": {"coordinates":[-74.00448299999999,40.732852],"type":"Point"}
}