{
  "type": "Feature",
  "properties": {
    "addr:full":"287 South Ave Poughkeepsie NY 12601",
    "addr:housenumber":"287",
    "addr:postcode":"12601",
    "addr:street":"South Ave",
    "iso:country":"US",
    "sg:address":"287 South Ave",
    "sg:city":"Poughkeepsie",
    "sg:classifiers":[
        {
            "category":"Autos & Motor Vehicles",
            "subcategory":"Auto Supplies",
            "type":"Retail Goods"
        }
    ],
    "sg:phone":"+1 845 471 9880",
    "sg:postcode":"12601",
    "sg:province":"NY",
    "sg:tags":[
        "automobile",
        "stereo",
        "radio"
    ],
    "wof:name":"Sound On Wheels",
    "wof:placetype":"venue"
},
  "geometry": {"coordinates":[-73.92989,41.683233],"type":"Point"}
}