{
  "type": "Feature",
  "properties": {
    "iso:country":"US",
    "sg:address":"5082 Foster Rd",
    "sg:city":"Canandaigua",
    "sg:classifiers":[
        {
            "category":"Food & Beverages",
            "subcategory":"Candy",
            "type":"Retail Goods"
        }
    ],
    "sg:phone":"+1   ",
    "sg:postcode":"14424",
    "sg:province":"NY",
    "wof:name":"K&B Fudge Co",
    "wof:placetype":"venue"
},
  "geometry": {"coordinates":[-77.294974,42.816768],"type":"Point"}
}