{
  "type": "Feature",
  "properties": {
    "iso:country":"US",
    "sg:address":"115 E Stevens Ave Ste 22",
    "sg:city":"Valhalla",
    "sg:classifiers":[
        {
            "category":"Professional",
            "subcategory":"Employment Agencies",
            "type":"Services"
        }
    ],
    "sg:phone":"+1 914 747 4297",
    "sg:postcode":"10595",
    "sg:province":"NY",
    "sg:tags":[
        "temporary"
    ],
    "sg:website":"http://www.eliassen.com",
    "wof:name":"Eliassen Group",
    "wof:placetype":"venue"
},
  "geometry": {"coordinates":[-73.77320899999999,41.097592],"type":"Point"}
}