{
  "type": "Feature",
  "properties": {
    "addr:full":"625 Atlantic Avenue Brooklyn NY 11217",
    "addr:housenumber":"625",
    "addr:postcode":"11217",
    "addr:street":"Atlantic Avenue",
    "iso:country":"US",
    "sg:address":"625 Atlantic Avenue",
    "sg:city":"Brooklyn",
    "sg:classifiers":[
        {
            "category":"Professional",
            "subcategory":"Lawyer & Legal Services",
            "type":"Services"
        }
    ],
    "sg:phone":"+1 718 855 4529",
    "sg:postcode":"11217",
    "sg:province":"NY",
    "wof:name":"Cohen J Jessie Atty",
    "wof:placetype":"venue"
},
  "geometry": {"coordinates":[-73.97582300000001,40.683504],"type":"Point"}
}