{
  "type": "Feature",
  "properties": {
    "addr:full":"1335 E Bay Ave Bronx NY 10474",
    "addr:housenumber":"1335",
    "addr:postcode":"10474",
    "addr:street":"E Bay Ave",
    "iso:country":"US",
    "sg:address":"1335 E Bay Ave",
    "sg:city":"Bronx",
    "sg:classifiers":[
        {
            "category":"Manufacturing",
            "subcategory":"Paper Products",
            "type":"Manufacturing & Wholesale Goods"
        }
    ],
    "sg:phone":"+1   ",
    "sg:postcode":"10474",
    "sg:province":"NY",
    "sg:tags":[
        "closure",
        "spool",
        "tube",
        "plastic",
        "mfg"
    ],
    "sg:website":"www.mailingtubes-ipt.com",
    "wof:name":"Industrial Paper Tube Inc",
    "wof:placetype":"venue"
},
  "geometry": {"coordinates":[-73.88404199999999,40.808855],"type":"Point"}
}