{
  "type": "Feature",
  "properties": {
    "addr:full":"7964 State Hwy 53 Bath NY 14810",
    "addr:housenumber":"7964",
    "addr:postcode":"14810",
    "addr:street":"State Hwy 53",
    "iso:country":"US",
    "sg:address":"7964 State Hwy 53",
    "sg:city":"Bath",
    "sg:classifiers":[
        {
            "category":"Professional",
            "subcategory":"Business Services",
            "type":"Services"
        }
    ],
    "sg:phone":"+1 607 776 7133",
    "sg:postcode":"14810",
    "sg:province":"NY",
    "sg:tags":[
        "painter",
        "sign"
    ],
    "wof:name":"Signs Plus",
    "wof:placetype":"venue"
},
  "geometry": {"coordinates":[-77.34979300000001,42.390823],"type":"Point"}
}