{
  "type": "Feature",
  "properties": {
    "addr:full":"300 Manhattan Ave New York NY 10026",
    "addr:housenumber":"300",
    "addr:postcode":"10026",
    "addr:street":"Manhattan Ave",
    "iso:country":"US",
    "sg:address":"300 Manhattan Ave",
    "sg:city":"New York",
    "sg:classifiers":[
        {
            "category":"Organizations",
            "subcategory":"Non-profit Organization",
            "type":"Services"
        }
    ],
    "sg:phone":"+1 212 678 5801",
    "sg:postcode":"10026",
    "sg:province":"NY",
    "sg:tags":[
        "info",
        "addiction",
        "abuse",
        "treatment",
        "drug"
    ],
    "wof:name":"Hale House Ctr Inc",
    "wof:placetype":"venue"
},
  "geometry": {"coordinates":[-73.958349,40.802754],"type":"Point"}
}