{
  "type": "Feature",
  "properties": {
    "addr:full":"3717 Bronxwood Ave Bronx NY 10469",
    "addr:housenumber":"3717",
    "addr:postcode":"10469",
    "addr:street":"Bronxwood Ave",
    "iso:country":"US",
    "sg:address":"3717 Bronxwood Ave",
    "sg:city":"Bronx",
    "sg:classifiers":[
        {
            "category":"Personal",
            "subcategory":"Barber",
            "type":"Services"
        }
    ],
    "sg:phone":"+1 718 519 1428",
    "sg:postcode":"10469",
    "sg:province":"NY",
    "wof:name":"Bailey's Barber & Beauty Shop",
    "wof:placetype":"venue"
},
  "geometry": {"coordinates":[-73.85811699999999,40.879855],"type":"Point"}
}