{
  "type": "Feature",
  "properties": {
    "iso:country":"US",
    "sg:address":"2528 Cruger Ave",
    "sg:city":"Bronx",
    "sg:classifiers":[
        {
            "category":"Communications",
            "subcategory":"Television Station",
            "type":"Services"
        }
    ],
    "sg:phone":"+1 718 325 5081",
    "sg:postcode":"10467",
    "sg:province":"NY",
    "sg:tags":[
        "network"
    ],
    "wof:name":"Link Shire Communication",
    "wof:placetype":"venue"
},
  "geometry": {"coordinates":[-73.86640300000001,40.86351],"type":"Point"}
}