{
  "type": "Feature",
  "properties": {
    "addr:full":"615 Montauk Hwy East Quogue NY 11942",
    "addr:housenumber":"615",
    "addr:postcode":"11942",
    "addr:street":"Montauk Hwy East",
    "iso:country":"US",
    "sg:address":"615 Montauk Hwy",
    "sg:city":"East Quogue",
    "sg:classifiers":[
        {
            "category":"Food & Beverages",
            "subcategory":"Groceries & Convenience Stores",
            "type":"Retail Goods"
        },
        {
            "category":"Restaurant",
            "type":"Food & Drink"
        }
    ],
    "sg:phone":"+1 631 653 3354",
    "sg:postcode":"11942",
    "sg:province":"NY",
    "sg:tags":[
        "delicatessen"
    ],
    "wof:name":"Michael's Deli",
    "wof:placetype":"venue"
},
  "geometry": {"coordinates":[-72.582368,40.83925],"type":"Point"}
}