{
  "type": "Feature",
  "properties": {
    "addr:full":"9 Stonehouse Rd Scarsdale NY 10583",
    "addr:housenumber":"9",
    "addr:postcode":"10583",
    "addr:street":"Stonehouse Rd",
    "iso:country":"US",
    "sg:address":"9 Stonehouse Rd",
    "sg:city":"Scarsdale",
    "sg:classifiers":[
        {
            "category":"Professional",
            "subcategory":"Management & Consulting",
            "type":"Services"
        },
        {
            "category":"Professional",
            "subcategory":"Business Services",
            "type":"Services"
        }
    ],
    "sg:phone":"+1 914 725 3095",
    "sg:postcode":"10583",
    "sg:province":"NY",
    "sg:tags":[
        "consultant",
        "coach"
    ],
    "wof:name":"International Pharmaceutical Consultants, Inc.",
    "wof:placetype":"venue"
},
  "geometry": {"coordinates":[-73.804282,40.992861],"type":"Point"}
}