{
  "type": "Feature",
  "properties": {
    "iso:country":"US",
    "sg:address":"445 E 140th St",
    "sg:city":"Bronx",
    "sg:classifiers":[
        {
            "category":"Organizations",
            "subcategory":"Professional Association",
            "type":"Services"
        }
    ],
    "sg:phone":"+1 718 742 2522",
    "sg:postcode":"10454",
    "sg:province":"NY",
    "sg:tags":[
        "business"
    ],
    "wof:name":"Cherry Tree Association Inc",
    "wof:placetype":"venue"
},
  "geometry": {"coordinates":[-73.91946,40.809582],"type":"Point"}
}