{
  "type": "Feature",
  "properties": {
    "iso:country":"US",
    "sg:address":"811 Black River Blvd N",
    "sg:city":"Rome",
    "sg:classifiers":[
        {
            "category":"Shopping",
            "subcategory":"Bicycles & Sporting Goods",
            "type":"Retail Goods"
        }
    ],
    "sg:phone":"+1 315 337 3879",
    "sg:postcode":"13440",
    "sg:province":"NY",
    "sg:tags":[
        "equipment",
        "skiing"
    ],
    "wof:name":"Bob's Snowboard Dungeon",
    "wof:placetype":"venue"
},
  "geometry": {"coordinates":[-75.44605199999999,43.221443],"type":"Point"}
}