{
  "type": "Feature",
  "properties": {
    "iso:country":"US",
    "sg:address":"117 Sullivan St",
    "sg:city":"New York",
    "sg:classifiers":[
        {
            "category":"Professional",
            "subcategory":"Computer Services",
            "type":"Services"
        }
    ],
    "sg:phone":"+1 212 925 1482",
    "sg:postcode":"10012",
    "sg:province":"NY",
    "sg:tags":[
        "website",
        "design"
    ],
    "sg:website":"www.marketorial.com",
    "wof:name":"Marketorial Web Design/Mktg",
    "wof:placetype":"venue"
},
  "geometry": {"coordinates":[-74.002805,40.725627],"type":"Point"}
}