{
  "type": "Feature",
  "properties": {
    "iso:country":"US",
    "sg:address":"25 Chestnut Ln",
    "sg:city":"Levittown",
    "sg:classifiers":[
        {
            "category":"Building & Trades",
            "subcategory":"Landscaping Services",
            "type":"Services"
        }
    ],
    "sg:phone":"+1 516 796 0240",
    "sg:postcode":"11756",
    "sg:province":"NY",
    "sg:tags":[
        "landscape"
    ],
    "wof:name":"BP Landscaping",
    "wof:placetype":"venue"
},
  "geometry": {"coordinates":[-73.51154,40.723433],"type":"Point"}
}