{
  "type": "Feature",
  "properties": {
    "iso:country":"US",
    "sg:address":"888 Pond View Rd",
    "sg:city":"Riverhead",
    "sg:classifiers":[
        {
            "category":"Wholesale",
            "subcategory":"Books, Periodicals, & Newspapers",
            "type":"Manufacturing & Wholesale Goods"
        }
    ],
    "sg:phone":"+1 631 208 8260",
    "sg:postcode":"11901",
    "sg:province":"NY",
    "sg:tags":[
        "publisher",
        "book"
    ],
    "wof:name":"Malibu Press Inc",
    "wof:placetype":"venue"
},
  "geometry": {"coordinates":[-72.66771300000001,40.927145],"type":"Point"}
}