{
  "type": "Feature",
  "properties": {
    "addr:full":"106 Main St Kingston NY 12401",
    "addr:housenumber":"106",
    "addr:postcode":"12401",
    "addr:street":"Main St",
    "iso:country":"US",
    "sg:address":"106 Main St",
    "sg:city":"Kingston",
    "sg:classifiers":[
        {
            "category":"Real Estate",
            "subcategory":"Real Estate Agent",
            "type":"Services"
        }
    ],
    "sg:phone":"+1 845 331 5035",
    "sg:postcode":"12401",
    "sg:province":"NY",
    "wof:name":"P G Simmons Realty LTD",
    "wof:placetype":"venue"
},
  "geometry": {"coordinates":[-74.021297,41.931514],"type":"Point"}
}