{
  "type": "Feature",
  "properties": {
    "iso:country":"US",
    "sg:address":"230 W Old Country Rd",
    "sg:city":"Hicksville",
    "sg:classifiers":[
        {
            "category":"Shopping",
            "subcategory":"Tobacco",
            "type":"Retail Goods"
        }
    ],
    "sg:phone":"+1 516 933 0898",
    "sg:postcode":"11801",
    "sg:province":"NY",
    "sg:tags":[
        "cigarette",
        "cigar"
    ],
    "wof:name":"Hicksville Humidor",
    "wof:placetype":"venue"
},
  "geometry": {"coordinates":[-73.530439,40.761088],"type":"Point"}
}