{
  "type": "Feature",
  "properties": {
    "addr:full":"2730 N Forest Rd Getzville NY 14068",
    "addr:housenumber":"2730",
    "addr:postcode":"14068",
    "addr:street":"N Forest Rd",
    "iso:country":"US",
    "sg:address":"2730 N Forest Rd",
    "sg:city":"Getzville",
    "sg:classifiers":[
        {
            "category":"Real Estate",
            "subcategory":"Real Estate Services",
            "type":"Services"
        }
    ],
    "sg:phone":"+1 866 968 2142",
    "sg:postcode":"14068",
    "sg:province":"NY",
    "sg:tags":[
        "apartment",
        "rental",
        "finder"
    ],
    "wof:name":"Turtle Creek Senior Apartments",
    "wof:placetype":"venue"
},
  "geometry": {"coordinates":[-78.786109,43.015566],"type":"Point"}
}