{
  "type": "Feature",
  "properties": {
    "addr:full":"31 W 10th St Apt 1 New York NY 10011",
    "addr:housenumber":"31;1",
    "addr:postcode":"10011",
    "addr:street":"W 10Th St Apt",
    "iso:country":"US",
    "sg:address":"31 W 10th St Apt 1",
    "sg:city":"New York",
    "sg:classifiers":[
        {
            "category":"Health Services",
            "subcategory":"Doctor",
            "type":"Services"
        }
    ],
    "sg:phone":"+1 212 777 7030",
    "sg:postcode":"10011",
    "sg:province":"NY",
    "wof:name":"Ott David",
    "wof:placetype":"venue"
},
  "geometry": {"coordinates":[-73.996376,40.733974],"type":"Point"}
}