{
  "type": "Feature",
  "properties": {
    "addr:full":"63 Mc Loughlin St Glen Cove NY 11542",
    "addr:housenumber":"63",
    "addr:postcode":"11542",
    "addr:street":"Mc Loughlin St",
    "iso:country":"US",
    "sg:address":"63 Mc Loughlin St",
    "sg:city":"Glen Cove",
    "sg:classifiers":[
        {
            "category":"Shopping",
            "type":"Retail Goods"
        }
    ],
    "sg:phone":"+1 516 671 9797",
    "sg:postcode":"11542",
    "sg:province":"NY",
    "sg:tags":[
        "chemical"
    ],
    "wof:name":"Hartford Chemical",
    "wof:placetype":"venue"
},
  "geometry": {"coordinates":[-73.645478,40.863904],"type":"Point"}
}