{
  "type": "Feature",
  "properties": {
    "iso:country":"US",
    "sg:address":"1 Lincoln Center Plz",
    "sg:city":"New York",
    "sg:classifiers":[
        {
            "category":"Arts & Performance",
            "subcategory":"Theater",
            "type":"Entertainment"
        }
    ],
    "sg:phone":"+1 212 877 5381",
    "sg:postcode":"10023",
    "sg:province":"NY",
    "sg:tags":[
        "bureau"
    ],
    "wof:name":"Morin Entertainment",
    "wof:placetype":"venue"
},
  "geometry": {"coordinates":[-73.981295,40.771029],"type":"Point"}
}