{
  "type": "Feature",
  "properties": {
    "iso:country":"US",
    "sg:address":"18 Manchester Cir",
    "sg:city":"Poughkeepsie",
    "sg:classifiers":[
        {
            "category":"Autos & Motor Vehicles",
            "subcategory":"Recreational Vehicle Sales",
            "type":"Retail Goods"
        }
    ],
    "sg:phone":"+1   ",
    "sg:postcode":"12603",
    "sg:province":"NY",
    "sg:tags":[
        "customize",
        "car",
        "snow",
        "race",
        "truck",
        "trailer"
    ],
    "wof:name":"King Truck Equipment",
    "wof:placetype":"venue"
},
  "geometry": {"coordinates":[-73.882497,41.690596],"type":"Point"}
}