{
  "type": "Feature",
  "properties": {
    "iso:country":"US",
    "sg:address":"224 N Ballston Ave",
    "sg:city":"Scotia",
    "sg:classifiers":[
        {
            "category":"Organizations",
            "subcategory":"Religious Organization",
            "type":"Services"
        }
    ],
    "sg:phone":"+1 518 370 4751",
    "sg:postcode":"12302",
    "sg:province":"NY",
    "sg:tags":[
        "church"
    ],
    "wof:name":"First Reformed Church Scotia",
    "wof:placetype":"venue"
},
  "geometry": {"coordinates":[-73.959628,42.829891],"type":"Point"}
}