{
  "type": "Feature",
  "properties": {
    "addr:full":"90 Muddy Kill Ln Montgomery NY 12549",
    "addr:housenumber":"90",
    "addr:postcode":"12549",
    "addr:street":"Muddy Kill Ln",
    "iso:country":"US",
    "sg:address":"90 Muddy Kill Ln",
    "sg:city":"Montgomery",
    "sg:classifiers":[
        {
            "category":"Building & Trades",
            "subcategory":"Construction",
            "type":"Services"
        }
    ],
    "sg:phone":"+1 845 457 3632",
    "sg:postcode":"12549",
    "sg:province":"NY",
    "sg:tags":[
        "general",
        "contractor"
    ],
    "wof:name":"Roger Wild General Contractor",
    "wof:placetype":"venue"
},
  "geometry": {"coordinates":[-74.260913,41.545174],"type":"Point"}
}