{
  "type": "Feature",
  "properties": {
    "addr:full":"271 Covert St Westbury NY 11590",
    "addr:housenumber":"271",
    "addr:postcode":"11590",
    "addr:street":"Covert St",
    "iso:country":"US",
    "sg:address":"271 Covert St",
    "sg:city":"Westbury",
    "sg:classifiers":[
        {
            "category":"Organizations",
            "subcategory":"Religious Organization",
            "type":"Services"
        }
    ],
    "sg:phone":"+1 516 997 9820",
    "sg:postcode":"11590",
    "sg:province":"NY",
    "sg:website":"www.mountcalvarybaptist.com",
    "wof:name":"Mount Calvary Baptist Church Inc",
    "wof:placetype":"venue"
},
  "geometry": {"coordinates":[-73.5765,40.7598],"type":"Point"}
}