{
  "type": "Feature",
  "properties": {
    "addr:full":"21 W 19th St New York NY 10011",
    "addr:housenumber":"21",
    "addr:postcode":"10011",
    "addr:street":"W 19Th St",
    "iso:country":"US",
    "sg:address":"21 W 19th St",
    "sg:city":"New York",
    "sg:classifiers":[
        {
            "category":"Real Estate",
            "subcategory":"Real Estate Services",
            "type":"Services"
        }
    ],
    "sg:phone":"+1 212 206 1720",
    "sg:postcode":"10011",
    "sg:province":"NY",
    "sg:website":"www.bondnewyork.com",
    "wof:name":"Bond New York",
    "wof:placetype":"venue"
},
  "geometry": {"coordinates":[-73.992028,40.739359],"type":"Point"}
}