{
  "type": "Feature",
  "properties": {
    "iso:country":"US",
    "sg:address":"40 W Main St",
    "sg:city":"Malone",
    "sg:classifiers":[
        {
            "category":"Insurance",
            "subcategory":"Insurance Agent",
            "type":"Services"
        }
    ],
    "sg:phone":"+1 518 483 0686",
    "sg:postcode":"12953",
    "sg:province":"NY",
    "wof:name":"K J Karleskent Inc",
    "wof:placetype":"venue"
},
  "geometry": {"coordinates":[-74.29558299999999,44.8488],"type":"Point"}
}