{
  "type": "Feature",
  "properties": {
    "addr:full":"15 Riverview Blvd Hudson NY 12534",
    "addr:housenumber":"15",
    "addr:postcode":"12534",
    "addr:street":"Riverview Blvd",
    "iso:country":"US",
    "sg:address":"15 Riverview Blvd",
    "sg:city":"Hudson",
    "sg:classifiers":[
        {
            "category":"Real Estate",
            "subcategory":"Architect",
            "type":"Services"
        }
    ],
    "sg:phone":"+1 518 828 3828",
    "sg:postcode":"12534",
    "sg:province":"NY",
    "wof:name":"Kremer Affiliates",
    "wof:placetype":"venue"
},
  "geometry": {"coordinates":[-73.772526,42.263909],"type":"Point"}
}