{
  "type": "Feature",
  "properties": {
    "iso:country":"US",
    "sg:address":"440 3rd Ave",
    "sg:city":"Watervliet",
    "sg:classifiers":[
        {
            "category":"Professional",
            "subcategory":"Management & Consulting",
            "type":"Services"
        }
    ],
    "sg:phone":"+1 518 271 2007",
    "sg:postcode":"12189",
    "sg:province":"NY",
    "sg:tags":[
        "consultant",
        "energy",
        "conservation"
    ],
    "wof:name":"Applied Proactive Technologies",
    "wof:placetype":"venue"
},
  "geometry": {"coordinates":[-73.708803,42.711064],"type":"Point"}
}