{
  "type": "Feature",
  "properties": {
    "iso:country":"US",
    "sg:address":"54 Tinker St",
    "sg:city":"Woodstock",
    "sg:classifiers":[
        {
            "category":"Shopping",
            "subcategory":"Used Merchandise",
            "type":"Retail Goods"
        }
    ],
    "sg:phone":"+1 845 679 5311",
    "sg:postcode":"12498",
    "sg:province":"NY",
    "sg:tags":[
        "carpet",
        "dealer",
        "rug"
    ],
    "wof:name":"Anatolia-Tribal Rugs & Weaving",
    "wof:placetype":"venue"
},
  "geometry": {"coordinates":[-74.11894100000001,42.04117],"type":"Point"}
}