{
  "type": "Feature",
  "properties": {
    "addr:full":"70 W Red Oak Ln White Plains NY 10604",
    "addr:housenumber":"70",
    "addr:postcode":"10604",
    "addr:street":"W Red Oak Ln",
    "iso:country":"US",
    "sg:address":"70 W Red Oak Ln",
    "sg:city":"White Plains",
    "sg:classifiers":[
        {
            "category":"Insurance",
            "subcategory":"Insurance Agent",
            "type":"Services"
        }
    ],
    "sg:phone":"+1 914 697 4754",
    "sg:postcode":"10604",
    "sg:province":"NY",
    "wof:name":"Jamison Company Insurance",
    "wof:placetype":"venue"
},
  "geometry": {"coordinates":[-73.72116,41.015498],"type":"Point"}
}