{
  "type": "Feature",
  "properties": {
    "addr:full":"2704 University Ave Bronx NY 10468",
    "addr:housenumber":"2704",
    "addr:postcode":"10468",
    "addr:street":"University Ave",
    "iso:country":"US",
    "sg:address":"2704 University Ave",
    "sg:city":"Bronx",
    "sg:classifiers":[
        {
            "category":"Education",
            "subcategory":"University",
            "type":"Public Place"
        }
    ],
    "sg:phone":"+1 718 581 0399",
    "sg:postcode":"10468",
    "sg:province":"NY",
    "sg:tags":[
        "college"
    ],
    "wof:name":"University Ave Reality Corp",
    "wof:placetype":"venue"
},
  "geometry": {"coordinates":[-73.900398,40.869099],"type":"Point"}
}