{
  "type": "Feature",
  "properties": {
    "iso:country":"US",
    "sg:address":"2 Barton Ave",
    "sg:city":"Utica",
    "sg:classifiers":[
        {
            "category":"Organizations",
            "subcategory":"Religious Organization",
            "type":"Services"
        }
    ],
    "sg:phone":"+1 315 724 7467",
    "sg:postcode":"13502",
    "sg:province":"NY",
    "wof:name":"St Joseph Church",
    "wof:placetype":"venue"
},
  "geometry": {"coordinates":[-75.26920699999999,43.082671],"type":"Point"}
}