{
  "type": "Feature",
  "properties": {
    "addr:full":"203 Audubon Ave New York NY 10033",
    "addr:housenumber":"203",
    "addr:postcode":"10033",
    "addr:street":"Audubon Ave",
    "iso:country":"US",
    "sg:address":"203 Audubon Ave",
    "sg:city":"New York",
    "sg:classifiers":[
        {
            "category":"Bars & Pubs",
            "subcategory":"Nightclub",
            "type":"Food & Drink"
        }
    ],
    "sg:phone":"+1 347 767 8089",
    "sg:postcode":"10033",
    "sg:province":"NY",
    "sg:tags":[
        "nightlife"
    ],
    "sg:website":"www.vibelounge175.com",
    "wof:name":"Vibe Lounge",
    "wof:placetype":"venue"
},
  "geometry": {"coordinates":[-73.934952,40.845137],"type":"Point"}
}