{
  "type": "Feature",
  "properties": {
    "addr:full":"575 White Plains Rd Eastchester NY 10709",
    "addr:housenumber":"575",
    "addr:postcode":"10709",
    "addr:street":"White Plains Rd",
    "iso:country":"US",
    "sg:address":"575 White Plains Rd",
    "sg:city":"Eastchester",
    "sg:classifiers":[
        {
            "category":"Professional",
            "subcategory":"Lawyer & Legal Services",
            "type":"Services"
        }
    ],
    "sg:phone":"+1 914 961 6003",
    "sg:postcode":"10709",
    "sg:province":"NY",
    "wof:name":"Anne Penachio",
    "wof:placetype":"venue"
},
  "geometry": {"coordinates":[-73.81025699999999,40.96322],"type":"Point"}
}