{
  "type": "Feature",
  "properties": {
    "iso:country":"US",
    "sg:address":"98 Washington St",
    "sg:city":"Liberty",
    "sg:classifiers":[
        {
            "category":"Building & Trades",
            "subcategory":"Construction",
            "type":"Services"
        }
    ],
    "sg:phone":"+1 845 866 4384",
    "sg:postcode":"12754",
    "sg:province":"NY",
    "sg:tags":[
        "painter"
    ],
    "wof:name":"East Coast Painting Corp",
    "wof:placetype":"venue"
},
  "geometry": {"coordinates":[-74.754987,41.795803],"type":"Point"}
}