{
  "type": "Feature",
  "properties": {
    "addr:full":"16 Lower Byrdcliffe Rd Woodstock NY 12498",
    "addr:housenumber":"16",
    "addr:postcode":"12498",
    "addr:street":"Lower Byrdcliffe Rd",
    "iso:country":"US",
    "sg:address":"16 Lower Byrdcliffe Rd",
    "sg:city":"Woodstock",
    "sg:classifiers":[
        {
            "category":"Professional",
            "subcategory":"Lawyer & Legal Services",
            "type":"Services"
        }
    ],
    "sg:phone":"+1 845 679 4500",
    "sg:postcode":"12498",
    "sg:province":"NY",
    "wof:name":"Don T Carmody",
    "wof:placetype":"venue"
},
  "geometry": {"coordinates":[-74.123384,42.047264],"type":"Point"}
}