{
  "type": "Feature",
  "properties": {
    "addr:full":"2740 Broadway New York NY 10025",
    "addr:housenumber":"2740",
    "addr:postcode":"10025",
    "addr:street":"Broadway",
    "iso:country":"US",
    "sg:address":"2740 Broadway",
    "sg:city":"New York",
    "sg:classifiers":[
        {
            "category":"Food & Beverages",
            "subcategory":"Bakery",
            "type":"Retail Goods"
        },
        {
            "category":"Bakery",
            "type":"Food & Drink"
        }
    ],
    "sg:menulink":"http://www.allmenus.com/ny/new-york/253484-silver-moon-bakery/menu/",
    "sg:phone":"+1 212 866 4717",
    "sg:postcode":"10025",
    "sg:province":"NY",
    "sg:tags":[
        "american",
        "bakery",
        "pastry"
    ],
    "wof:name":"Silver Moon Bakery",
    "wof:placetype":"venue"
},
  "geometry": {"coordinates":[-73.967877,40.800511],"type":"Point"}
}