{
  "type": "Feature",
  "properties": {
    "iso:country":"US",
    "sg:address":"653 Cumberland Way",
    "sg:city":"Webster",
    "sg:classifiers":[
        {
            "category":"Building & Trades",
            "subcategory":"Construction",
            "type":"Services"
        }
    ],
    "sg:phone":"+1 585 872 7270",
    "sg:postcode":"14580",
    "sg:province":"NY",
    "sg:tags":[
        "hanging",
        "contractor"
    ],
    "wof:name":"Mark Peacock Painting",
    "wof:placetype":"venue"
},
  "geometry": {"coordinates":[-77.45626900000001,43.232288],"type":"Point"}
}