{
  "type": "Feature",
  "properties": {
    "iso:country":"US",
    "sg:address":"5600 1st Ave",
    "sg:city":"Brooklyn",
    "sg:classifiers":[
        {
            "category":"Shopping",
            "subcategory":"Discount & Variety Stores",
            "type":"Retail Goods"
        }
    ],
    "sg:phone":"+1 718 238 8766",
    "sg:postcode":"11220",
    "sg:province":"NY",
    "sg:tags":[
        "post",
        "trading"
    ],
    "wof:name":"Chow Trading Co Inc",
    "wof:placetype":"venue"
},
  "geometry": {"coordinates":[-74.02320400000001,40.646502],"type":"Point"}
}