{
  "type": "Feature",
  "properties": {
    "addr:full":"4779 State Hwy 5 Herkimer NY 13350",
    "addr:housenumber":"4779",
    "addr:postcode":"13350",
    "addr:street":"State Hwy 5",
    "iso:country":"US",
    "sg:address":"4779 State Hwy 5",
    "sg:city":"Herkimer",
    "sg:classifiers":[
        {
            "category":"Home & Garden",
            "subcategory":"Building Materials",
            "type":"Retail Goods"
        }
    ],
    "sg:phone":"+1 315 866 6467",
    "sg:postcode":"13350",
    "sg:province":"NY",
    "sg:tags":[
        "glass",
        "window",
        "plate"
    ],
    "wof:name":"NEP Glass Co",
    "wof:placetype":"venue"
},
  "geometry": {"coordinates":[-75.002279,43.020198],"type":"Point"}
}