{
  "type": "Feature",
  "properties": {
    "iso:country":"US",
    "sg:address":"6 Winspear Ave",
    "sg:city":"Buffalo",
    "sg:classifiers":[
        {
            "category":"Shopping",
            "subcategory":"Optician",
            "type":"Retail Goods"
        }
    ],
    "sg:phone":"+1 716 832 0704",
    "sg:postcode":"14214",
    "sg:province":"NY",
    "sg:tags":[
        "eyewear"
    ],
    "wof:name":"Main Optical Co",
    "wof:placetype":"venue"
},
  "geometry": {"coordinates":[-78.82559999999999,42.951302],"type":"Point"}
}