{
  "type": "Feature",
  "properties": {
    "iso:country":"US",
    "sg:address":"211 Alplaus Ave",
    "sg:city":"Alplaus",
    "sg:classifiers":[
        {
            "category":"Freight",
            "type":"Transportation"
        },
        {
            "category":"Utilities",
            "subcategory":"Refuse",
            "type":"Services"
        }
    ],
    "sg:phone":"+1 518 399 7583",
    "sg:postcode":"12008",
    "sg:province":"NY",
    "sg:tags":[
        "garbage",
        "storage",
        "collection",
        "trucking",
        "without",
        "local"
    ],
    "wof:name":"Good Riddance Trucking Inc",
    "wof:placetype":"venue"
},
  "geometry": {"coordinates":[-73.90612400000001,42.856042],"type":"Point"}
}