{
  "type": "Feature",
  "properties": {
    "iso:country":"US",
    "sg:address":"20 Johnson St",
    "sg:city":"Frewsburg",
    "sg:classifiers":[
        {
            "category":"Shopping",
            "type":"Retail Goods"
        }
    ],
    "sg:phone":"+1   ",
    "sg:postcode":"14738",
    "sg:province":"NY",
    "sg:tags":[
        "merchandise"
    ],
    "wof:name":"Discount Monuments",
    "wof:placetype":"venue"
},
  "geometry": {"coordinates":[-79.16332199999999,42.06066],"type":"Point"}
}