{
  "type": "Feature",
  "properties": {
    "addr:full":"7 S Canal St Greene NY 13778",
    "addr:housenumber":"7",
    "addr:postcode":"13778",
    "addr:street":"S Canal St",
    "iso:country":"US",
    "sg:address":"7 S Canal St",
    "sg:city":"Greene",
    "sg:classifiers":[
        {
            "category":"Personal",
            "subcategory":"Beauty Salon",
            "type":"Services"
        }
    ],
    "sg:phone":"+1 607 656 8844",
    "sg:postcode":"13778",
    "sg:province":"NY",
    "wof:name":"Shear Magic",
    "wof:placetype":"venue"
},
  "geometry": {"coordinates":[-75.772217,42.32917],"type":"Point"}
}