{
  "type": "Feature",
  "properties": {
    "addr:full":"874 Rockaway Ave Brooklyn NY 11212",
    "addr:housenumber":"874",
    "addr:postcode":"11212",
    "addr:street":"Rockaway Ave",
    "iso:country":"US",
    "sg:address":"874 Rockaway Ave",
    "sg:city":"Brooklyn",
    "sg:classifiers":[
        {
            "category":"Retail",
            "subcategory":"Auto Rental",
            "type":"Services"
        }
    ],
    "sg:phone":"+1 718 498 1100",
    "sg:postcode":"11212",
    "sg:province":"NY",
    "sg:tags":[
        "renting",
        "truck",
        "leasing"
    ],
    "wof:name":"U-Haul Co",
    "wof:placetype":"venue"
},
  "geometry": {"coordinates":[-73.908044,40.659135],"type":"Point"}
}