{
  "type": "Feature",
  "properties": {
    "addr:full":"161 Morris Ave Merrick NY 11566",
    "addr:housenumber":"161",
    "addr:postcode":"11566",
    "addr:street":"Morris Ave",
    "iso:country":"US",
    "sg:address":"161 Morris Ave",
    "sg:city":"Merrick",
    "sg:classifiers":[
        {
            "category":"Restaurant",
            "type":"Food & Drink"
        }
    ],
    "sg:menulink":"http://www.allmenus.com/ny/bellmore-merrick/54788-thai-station/menu/",
    "sg:phone":"+1 516 868 1168",
    "sg:postcode":"11566",
    "sg:province":"NY",
    "sg:tags":[
        "thai",
        "asian"
    ],
    "wof:name":"Thai Station",
    "wof:placetype":"venue"
},
  "geometry": {"coordinates":[-73.571145,40.67988],"type":"Point"}
}