{
  "type": "Feature",
  "properties": {
    "iso:country":"US",
    "sg:address":"1051 Development Ct",
    "sg:city":"Kingston",
    "sg:classifiers":[
        {
            "category":"Government",
            "subcategory":"Office",
            "type":"Public Place"
        }
    ],
    "sg:phone":"+1 845 334 5200",
    "sg:postcode":"12401",
    "sg:province":"NY",
    "sg:tags":[
        "county",
        "resource"
    ],
    "wof:name":"Ulster County Food Stamps",
    "wof:placetype":"venue"
},
  "geometry": {"coordinates":[-73.99755999999999,41.945282],"type":"Point"}
}