{
  "type": "Feature",
  "properties": {
    "addr:full":"217 E 28th Street New York NY 10016",
    "addr:housenumber":"217",
    "addr:postcode":"10016",
    "addr:street":"E 28Th Street",
    "iso:country":"US",
    "sg:address":"217 E 28th Street",
    "sg:city":"New York",
    "sg:classifiers":[
        {
            "category":"Organizations",
            "subcategory":"Religious Organization",
            "type":"Services"
        }
    ],
    "sg:phone":"+1 212 689 3622",
    "sg:postcode":"10016",
    "sg:province":"NY",
    "wof:name":"Self Realization Fellowship",
    "wof:placetype":"venue"
},
  "geometry": {"coordinates":[-73.98002099999999,40.741739],"type":"Point"}
}