{
  "type": "Feature",
  "properties": {
    "iso:country":"US",
    "sg:address":"95 E Main St",
    "sg:city":"Patchogue",
    "sg:classifiers":[
        {
            "category":"Organizations",
            "subcategory":"Religious Organization",
            "type":"Services"
        }
    ],
    "sg:phone":"+1 631 475 1235",
    "sg:postcode":"11772",
    "sg:province":"NY",
    "sg:tags":[
        "church"
    ],
    "sg:website":"www.congrepatchogue.org",
    "wof:name":"Congregational Church",
    "wof:placetype":"venue"
},
  "geometry": {"coordinates":[-73.014805,40.765757],"type":"Point"}
}