{
  "type": "Feature",
  "properties": {
    "addr:full":"65 S 11th St Brooklyn NY 11211",
    "addr:housenumber":"65",
    "addr:postcode":"11211",
    "addr:street":"S 11Th St",
    "iso:country":"US",
    "sg:address":"65 S 11th St",
    "sg:city":"Brooklyn",
    "sg:classifiers":[
        {
            "category":"Building & Trades",
            "subcategory":"Construction",
            "type":"Services"
        }
    ],
    "sg:phone":"+1 718 599 4109",
    "sg:postcode":"11211",
    "sg:province":"NY",
    "sg:tags":[
        "woodworker"
    ],
    "wof:name":"Jerry Middleton",
    "wof:placetype":"venue"
},
  "geometry": {"coordinates":[-73.966773,40.70767],"type":"Point"}
}