{
  "type": "Feature",
  "properties": {
    "addr:full":"32 Cherry St Saratoga Springs NY 12866",
    "addr:housenumber":"32",
    "addr:postcode":"12866",
    "addr:street":"Cherry St",
    "iso:country":"US",
    "sg:address":"32 Cherry St",
    "sg:city":"Saratoga Springs",
    "sg:classifiers":[
        {
            "category":"Retail",
            "subcategory":"Repair Shop",
            "type":"Services"
        }
    ],
    "sg:phone":"+1 518 584 2991",
    "sg:postcode":"12866",
    "sg:province":"NY",
    "sg:tags":[
        "lock",
        "locksmith"
    ],
    "wof:name":"Tom's Locksmith Shop",
    "wof:placetype":"venue"
},
  "geometry": {"coordinates":[-73.79154,43.081729],"type":"Point"}
}