{
  "type": "Feature",
  "properties": {
    "iso:country":"US",
    "sg:address":"86 S Long St",
    "sg:city":"Williamsville",
    "sg:classifiers":[
        {
            "category":"Museum",
            "type":"Entertainment"
        }
    ],
    "sg:phone":"+1 716 633 7002",
    "sg:postcode":"14221",
    "sg:province":"NY",
    "wof:name":"Western New York RY Society",
    "wof:placetype":"venue"
},
  "geometry": {"coordinates":[-78.753246,42.95893],"type":"Point"}
}