{
  "type": "Feature",
  "properties": {
    "addr:full":"364 Grandview Blvd Yonkers NY 10710",
    "addr:housenumber":"364",
    "addr:postcode":"10710",
    "addr:street":"Grandview Blvd",
    "iso:country":"US",
    "sg:address":"364 Grandview Blvd",
    "sg:city":"Yonkers",
    "sg:classifiers":[
        {
            "category":"Real Estate",
            "subcategory":"Real Estate Agent",
            "type":"Services"
        }
    ],
    "sg:phone":"+1 914 961 3471",
    "sg:postcode":"10710",
    "sg:province":"NY",
    "sg:tags":[
        "inspection"
    ],
    "wof:name":"Grandview Contracting",
    "wof:placetype":"venue"
},
  "geometry": {"coordinates":[-73.83085199999999,40.970045],"type":"Point"}
}