{
  "type": "Feature",
  "properties": {
    "addr:full":"311 Utica Ave Apt 2A Brooklyn NY 11213",
    "addr:housenumber":"311;2a",
    "addr:postcode":"11213",
    "addr:street":"Utica Ave Apt",
    "iso:country":"US",
    "sg:address":"311 Utica Ave Apt 2A",
    "sg:city":"Brooklyn",
    "sg:classifiers":[
        {
            "category":"Shopping",
            "subcategory":"Books",
            "type":"Retail Goods"
        }
    ],
    "sg:phone":"+1 718 773 2101",
    "sg:postcode":"11213",
    "sg:province":"NY",
    "sg:tags":[
        "bookstore",
        "store"
    ],
    "sg:website":"http://www.goodwill.org",
    "wof:name":"Goodwill Gospel Store",
    "wof:placetype":"venue"
},
  "geometry": {"coordinates":[-73.931068,40.667326],"type":"Point"}
}