{
  "type": "Feature",
  "properties": {
    "addr:full":"183 Bay Ridge Ave Brooklyn NY 11220",
    "addr:housenumber":"183",
    "addr:postcode":"11220",
    "addr:street":"Bay Ridge Ave",
    "iso:country":"US",
    "sg:address":"183 Bay Ridge Ave",
    "sg:city":"Brooklyn",
    "sg:classifiers":[
        {
            "category":"Manufacturing",
            "subcategory":"Printing",
            "type":"Manufacturing & Wholesale Goods"
        }
    ],
    "sg:phone":"+1 718 921 3342",
    "sg:postcode":"11220",
    "sg:province":"NY",
    "sg:tags":[
        "lithographic",
        "printer",
        "commercial"
    ],
    "wof:name":"Senior Citizen Publishing Inc",
    "wof:placetype":"venue"
},
  "geometry": {"coordinates":[-74.030193,40.637255],"type":"Point"}
}