{
  "type": "Feature",
  "properties": {
    "iso:country":"US",
    "sg:address":"17 Greenbush Rd",
    "sg:city":"Orangeburg",
    "sg:classifiers":[
        {
            "category":"Professional",
            "type":"Services"
        }
    ],
    "sg:phone":"+1 845 267 5405",
    "sg:postcode":"10962",
    "sg:province":"NY",
    "sg:tags":[
        "establishment"
    ],
    "wof:name":"Power Tower",
    "wof:placetype":"venue"
},
  "geometry": {"coordinates":[-73.947239,41.04396],"type":"Point"}
}