{
  "type": "Feature",
  "properties": {
    "iso:country":"US",
    "sg:address":"24 Main St",
    "sg:city":"Hyde Park",
    "sg:classifiers":[
        {
            "category":"Health Services",
            "subcategory":"Doctor",
            "type":"Services"
        }
    ],
    "sg:phone":"+1   ",
    "sg:postcode":"12538",
    "sg:province":"NY",
    "wof:name":"Fitzpatrick J Robert",
    "wof:placetype":"venue"
},
  "geometry": {"coordinates":[-73.935698,41.790288],"type":"Point"}
}