{
  "type": "Feature",
  "properties": {
    "iso:country":"US",
    "sg:address":"655 3rd Avenue",
    "sg:city":"New York",
    "sg:classifiers":[
        {
            "category":"Professional",
            "subcategory":"Lawyer & Legal Services",
            "type":"Services"
        }
    ],
    "sg:phone":"+1 212 490 2020",
    "sg:postcode":"10017",
    "sg:province":"NY",
    "wof:name":"Krooks Bernard ESQ",
    "wof:placetype":"venue"
},
  "geometry": {"coordinates":[-73.974397,40.750773],"type":"Point"}
}