{
  "type": "Feature",
  "properties": {
    "addr:full":"6705 S Salina St Nedrow NY 13120",
    "addr:housenumber":"6705",
    "addr:postcode":"13120",
    "addr:street":"S Salina St",
    "iso:country":"US",
    "sg:address":"6705 S Salina St",
    "sg:city":"Nedrow",
    "sg:classifiers":[
        {
            "category":"Home & Garden",
            "subcategory":"Garden Supply",
            "type":"Retail Goods"
        }
    ],
    "sg:phone":"+1   ",
    "sg:postcode":"13120",
    "sg:province":"NY",
    "wof:name":"Natural Selections",
    "wof:placetype":"venue"
},
  "geometry": {"coordinates":[-76.141384,42.97542],"type":"Point"}
}