{
  "type": "Feature",
  "properties": {
    "addr:full":"217 Wood Ave Buffalo NY 14211",
    "addr:housenumber":"217",
    "addr:postcode":"14211",
    "addr:street":"Wood Ave",
    "iso:country":"US",
    "sg:address":"217 Wood Ave",
    "sg:city":"Buffalo",
    "sg:classifiers":[
        {
            "category":"Shopping",
            "subcategory":"Clothing, Apparel, & Fashions",
            "type":"Retail Goods"
        }
    ],
    "sg:phone":"+1   ",
    "sg:postcode":"14211",
    "sg:province":"NY",
    "sg:tags":[
        "family"
    ],
    "wof:name":"Abstract Da Hood Alliance",
    "wof:placetype":"venue"
},
  "geometry": {"coordinates":[-78.809361,42.906926],"type":"Point"}
}