{
  "type": "Feature",
  "properties": {
    "addr:full":"965 Longwood Ave Bronx NY 10459",
    "addr:housenumber":"965",
    "addr:postcode":"10459",
    "addr:street":"Longwood Ave",
    "iso:country":"US",
    "sg:address":"965 Longwood Ave",
    "sg:city":"Bronx",
    "sg:classifiers":[
        {
            "category":"Building & Trades",
            "subcategory":"Landscaping Services",
            "type":"Services"
        }
    ],
    "sg:phone":"+1 718 328 4800",
    "sg:postcode":"10459",
    "sg:province":"NY",
    "sg:tags":[
        "landscape"
    ],
    "wof:name":"Cornell Corp N S B",
    "wof:placetype":"venue"
},
  "geometry": {"coordinates":[-73.897944,40.817467],"type":"Point"}
}