{
  "type": "Feature",
  "properties": {
    "addr:full":"1668-B 78th St Brooklyn NY 11214",
    "addr:housenumber":"1668-b",
    "addr:postcode":"11214",
    "addr:street":"78Th St",
    "iso:country":"US",
    "sg:address":"1668-B 78th St",
    "sg:city":"Brooklyn",
    "sg:classifiers":[
        {
            "category":"Real Estate",
            "subcategory":"Real Estate Operator",
            "type":"Services"
        }
    ],
    "sg:phone":"+1 718 232 2550",
    "sg:postcode":"11214",
    "sg:province":"NY",
    "sg:tags":[
        "apartment"
    ],
    "sg:website":"www.rhrealtyinc.com",
    "wof:name":"R&H Realty",
    "wof:placetype":"venue"
},
  "geometry": {"coordinates":[-74.00187200000001,40.614116],"type":"Point"}
}