{
  "type": "Feature",
  "properties": {
    "iso:country":"US",
    "sg:address":"47 Hillside Ave",
    "sg:city":"Manhasset",
    "sg:classifiers":[
        {
            "category":"Professional",
            "subcategory":"Management & Consulting",
            "type":"Services"
        }
    ],
    "sg:phone":"+1 516 869 0166",
    "sg:postcode":"11030",
    "sg:province":"NY",
    "sg:tags":[
        "town",
        "city",
        "regional",
        "planner"
    ],
    "wof:name":"Urbanetics",
    "wof:placetype":"venue"
},
  "geometry": {"coordinates":[-73.701374,40.796818],"type":"Point"}
}