{
  "type": "Feature",
  "properties": {
    "addr:full":"407 S Walnut St Elmira NY 14904",
    "addr:housenumber":"407",
    "addr:postcode":"14904",
    "addr:street":"S Walnut St",
    "iso:country":"US",
    "sg:address":"407 S Walnut St",
    "sg:city":"Elmira",
    "sg:classifiers":[
        {
            "category":"Manufacturing",
            "subcategory":"Tools & Machinery",
            "type":"Manufacturing & Wholesale Goods"
        },
        {
            "category":"Shopping",
            "subcategory":"Computers & Home Electronics",
            "type":"Retail Goods"
        }
    ],
    "sg:phone":"+1 607 735 0466",
    "sg:postcode":"14904",
    "sg:province":"NY",
    "sg:tags":[
        "equipment",
        "dealer"
    ],
    "sg:website":"www.pcs407.com",
    "wof:name":"P C Solutions",
    "wof:placetype":"venue"
},
  "geometry": {"coordinates":[-76.81249099999999,42.07657],"type":"Point"}
}