{
  "type": "Feature",
  "properties": {
    "addr:full":"156 5th Ave New York NY 10010",
    "addr:housenumber":"156",
    "addr:postcode":"10010",
    "addr:street":"5Th Ave",
    "iso:country":"US",
    "sg:address":"156 5th Ave",
    "sg:city":"New York",
    "sg:classifiers":[
        {
            "category":"Building & Trades",
            "subcategory":"Locksmith",
            "type":"Services"
        }
    ],
    "sg:phone":"+1 212 231 6064",
    "sg:postcode":"10010",
    "sg:province":"NY",
    "sg:tags":[
        "key"
    ],
    "wof:name":"A Best Twenty Four Hr Locksmtih",
    "wof:placetype":"venue"
},
  "geometry": {"coordinates":[-73.990888,40.740053],"type":"Point"}
}