{
  "type": "Feature",
  "properties": {
    "addr:full":"400 Madison Ave New York NY 10017",
    "addr:housenumber":"400",
    "addr:postcode":"10017",
    "addr:street":"Madison Ave",
    "iso:country":"US",
    "sg:address":"400 Madison Ave",
    "sg:city":"New York",
    "sg:classifiers":[
        {
            "category":"Health Services",
            "subcategory":"Doctor",
            "type":"Services"
        }
    ],
    "sg:phone":"+1 212 644 1228",
    "sg:postcode":"10017",
    "sg:province":"NY",
    "sg:tags":[
        "dentist"
    ],
    "wof:name":"Cosmetic & Reconstructive",
    "wof:placetype":"venue"
},
  "geometry": {"coordinates":[-73.976698,40.756407],"type":"Point"}
}