{
  "type": "Feature",
  "properties": {
    "iso:country":"US",
    "sg:address":"1154 Mohawk Rd",
    "sg:city":"Schenectady",
    "sg:classifiers":[
        {
            "category":"Manufacturing",
            "subcategory":"Tools & Machinery",
            "type":"Manufacturing & Wholesale Goods"
        }
    ],
    "sg:phone":"+1   ",
    "sg:postcode":"12309",
    "sg:province":"NY",
    "sg:tags":[
        "inverter"
    ],
    "wof:name":"Inverters Unlimited Inc",
    "wof:placetype":"venue"
},
  "geometry": {"coordinates":[-73.84618399999999,42.785326],"type":"Point"}
}