{
  "type": "Feature",
  "properties": {
    "iso:country":"US",
    "sg:address":"9011 Elmhurst Avenue",
    "sg:city":"Jackson Heights",
    "sg:classifiers":[
        {
            "category":"Restaurant",
            "type":"Food & Drink"
        }
    ],
    "sg:phone":"+1 718 651 7452",
    "sg:postcode":"11372",
    "sg:province":"NY",
    "sg:tags":[
        "pizza"
    ],
    "wof:name":"Pizza La Cancha",
    "wof:placetype":"venue"
},
  "geometry": {"coordinates":[-73.876259,40.748707],"type":"Point"}
}