{
  "type": "Feature",
  "properties": {
    "iso:country":"US",
    "sg:address":"610 Main St",
    "sg:city":"Niagara Falls",
    "sg:classifiers":[
        {
            "category":"Professional",
            "type":"Services"
        }
    ],
    "sg:phone":"+1 716 282 1324",
    "sg:postcode":"14301",
    "sg:province":"NY",
    "sg:tags":[
        "establishment"
    ],
    "wof:name":"Niagara Falls Sightseeing",
    "wof:placetype":"venue"
},
  "geometry": {"coordinates":[-79.05785899999999,43.093041],"type":"Point"}
}