{
  "type": "Feature",
  "properties": {
    "addr:full":"26 Sharpe Ave Staten Island NY 10302",
    "addr:housenumber":"26",
    "addr:postcode":"10302",
    "addr:street":"Sharpe Ave",
    "iso:country":"US",
    "sg:address":"26 Sharpe Ave",
    "sg:city":"Staten Island",
    "sg:classifiers":[
        {
            "category":"Sports & Exercise",
            "subcategory":"Sports Center",
            "type":"Entertainment"
        }
    ],
    "sg:phone":"+1 718 720 8718",
    "sg:postcode":"10302",
    "sg:province":"NY",
    "sg:tags":[
        "amateur",
        "team"
    ],
    "wof:name":"Police Athletic League",
    "wof:placetype":"venue"
},
  "geometry": {"coordinates":[-74.13687299999999,40.639624],"type":"Point"}
}