{
  "type": "Feature",
  "properties": {
    "addr:full":"1638 Military Rd Niagara Falls NY 14304",
    "addr:housenumber":"1638",
    "addr:postcode":"14304",
    "addr:street":"Military Rd",
    "iso:country":"US",
    "sg:address":"1638 Military Rd",
    "sg:city":"Niagara Falls",
    "sg:classifiers":[
        {
            "category":"Shopping",
            "subcategory":"Shoes",
            "type":"Retail Goods"
        }
    ],
    "sg:phone":"+1   ",
    "sg:postcode":"14304",
    "sg:province":"NY",
    "sg:tags":[
        "shoe",
        "store"
    ],
    "wof:name":"Factory Brand Shoes",
    "wof:placetype":"venue"
},
  "geometry": {"coordinates":[-78.971186,43.093457],"type":"Point"}
}