{
  "type": "Feature",
  "properties": {
    "addr:full":"10623 154th St Jamaica NY 11433",
    "addr:housenumber":"10623",
    "addr:postcode":"11433",
    "addr:street":"154Th St",
    "iso:country":"US",
    "sg:address":"10623 154th St",
    "sg:city":"Jamaica",
    "sg:classifiers":[
        {
            "category":"Organizations",
            "subcategory":"Religious Organization",
            "type":"Services"
        }
    ],
    "sg:phone":"+1 718 291 8419",
    "sg:postcode":"11433",
    "sg:province":"NY",
    "wof:name":"Bethel Mission Church",
    "wof:placetype":"venue"
},
  "geometry": {"coordinates":[-73.79938,40.695724],"type":"Point"}
}