{
  "type": "Feature",
  "properties": {
    "addr:full":"31 Beekman Ave Sleepy Hollow NY 10591",
    "addr:housenumber":"31",
    "addr:postcode":"10591",
    "addr:street":"Beekman Ave",
    "iso:country":"US",
    "sg:address":"31 Beekman Ave",
    "sg:city":"Sleepy Hollow",
    "sg:classifiers":[
        {
            "category":"Restaurant",
            "type":"Food & Drink"
        }
    ],
    "sg:phone":"+1 914 631 9802",
    "sg:postcode":"10591",
    "sg:province":"NY",
    "sg:website":"www.outofbounds.com",
    "wof:name":"Out of Bounds",
    "wof:placetype":"venue"
},
  "geometry": {"coordinates":[-73.860001,41.0849],"type":"Point"}
}