{
  "type": "Feature",
  "properties": {
    "addr:full":"97 Industrial Park Dr Binghamton NY 13904",
    "addr:housenumber":"97",
    "addr:postcode":"13904",
    "addr:street":"Industrial Park Dr",
    "iso:country":"US",
    "sg:address":"97 Industrial Park Dr",
    "sg:city":"Binghamton",
    "sg:classifiers":[
        {
            "category":"Freight",
            "type":"Transportation"
        }
    ],
    "sg:phone":"+1 607 722 2121",
    "sg:postcode":"13904",
    "sg:province":"NY",
    "wof:name":"Air Plus Limited",
    "wof:placetype":"venue"
},
  "geometry": {"coordinates":[-75.829713,42.097672],"type":"Point"}
}