{
  "type": "Feature",
  "properties": {
    "addr:full":"946 Kings Hwy Brooklyn NY 11223",
    "addr:housenumber":"946",
    "addr:postcode":"11223",
    "addr:street":"Kings Hwy",
    "iso:country":"US",
    "sg:address":"946 Kings Hwy",
    "sg:city":"Brooklyn",
    "sg:classifiers":[
        {
            "category":"Food & Beverages",
            "subcategory":"Bakery",
            "type":"Retail Goods"
        }
    ],
    "sg:phone":"+1 718 627 4700",
    "sg:postcode":"11223",
    "sg:province":"NY",
    "sg:tags":[
        "sandwich"
    ],
    "wof:name":"Quiznos",
    "wof:placetype":"venue"
},
  "geometry": {"coordinates":[-73.962762,40.60694],"type":"Point"}
}