{
  "type": "Feature",
  "properties": {
    "addr:full":"494 Reiman St Buffalo NY 14212",
    "addr:housenumber":"494",
    "addr:postcode":"14212",
    "addr:street":"Reiman St",
    "iso:country":"US",
    "sg:address":"494 Reiman St",
    "sg:city":"Buffalo",
    "sg:classifiers":[
        {
            "category":"Food & Beverages",
            "subcategory":"Groceries & Convenience Stores",
            "type":"Retail Goods"
        }
    ],
    "sg:phone":"+1   ",
    "sg:postcode":"14212",
    "sg:province":"NY",
    "wof:name":"David A CAMillo& Rosette",
    "wof:placetype":"venue"
},
  "geometry": {"coordinates":[-78.790505,42.895582],"type":"Point"}
}