{
  "type": "Feature",
  "properties": {
    "iso:country":"US",
    "sg:address":"1650 Sycamore Ave",
    "sg:city":"Bohemia",
    "sg:classifiers":[
        {
            "category":"Shopping",
            "type":"Retail Goods"
        },
        {
            "category":"Wholesale",
            "subcategory":"Non-durable Goods",
            "type":"Manufacturing & Wholesale Goods"
        }
    ],
    "sg:phone":"+1 631 244 2736",
    "sg:postcode":"11716",
    "sg:province":"NY",
    "sg:tags":[
        "art",
        "gallery",
        "dealer"
    ],
    "wof:name":"C & L Fine Arts Inc",
    "wof:placetype":"venue"
},
  "geometry": {"coordinates":[-73.12446,40.786985],"type":"Point"}
}