{
  "type": "Feature",
  "properties": {
    "addr:full":"1105 Morrison Ave Bronx NY 10472",
    "addr:housenumber":"1105",
    "addr:postcode":"10472",
    "addr:street":"Morrison Ave",
    "iso:country":"US",
    "sg:address":"1105 Morrison Ave",
    "sg:city":"Bronx",
    "sg:classifiers":[
        {
            "category":"Food & Beverages",
            "subcategory":"Groceries & Convenience Stores",
            "type":"Retail Goods"
        }
    ],
    "sg:phone":"+1 718 842 3212",
    "sg:postcode":"10472",
    "sg:province":"NY",
    "wof:name":"Morrison Mini Market",
    "wof:placetype":"venue"
},
  "geometry": {"coordinates":[-73.87400100000001,40.826801],"type":"Point"}
}