{
  "type": "Feature",
  "properties": {
    "addr:full":"6 Executive Plz Yonkers NY 10701",
    "addr:housenumber":"6",
    "addr:postcode":"10701",
    "addr:street":"Executive Plz",
    "iso:country":"US",
    "sg:address":"6 Executive Plz",
    "sg:city":"Yonkers",
    "sg:classifiers":[
        {
            "category":"Utilities",
            "subcategory":"Cable",
            "type":"Services"
        }
    ],
    "sg:phone":"+1   ",
    "sg:postcode":"10701",
    "sg:province":"NY",
    "sg:tags":[
        "television"
    ],
    "wof:name":"Cablevision",
    "wof:placetype":"venue"
},
  "geometry": {"coordinates":[-73.881421,40.970673],"type":"Point"}
}