{
  "type": "Feature",
  "properties": {
    "iso:country":"US",
    "sg:address":"10 Inland Ct",
    "sg:city":"Carmel",
    "sg:classifiers":[
        {
            "category":"Building & Trades",
            "subcategory":"Construction",
            "type":"Services"
        }
    ],
    "sg:phone":"+1 845 225 7967",
    "sg:postcode":"10512",
    "sg:province":"NY",
    "sg:tags":[
        "house"
    ],
    "wof:name":"Maglio Home Improvements Inc",
    "wof:placetype":"venue"
},
  "geometry": {"coordinates":[-73.66299600000001,41.445603],"type":"Point"}
}