{
  "type": "Feature",
  "properties": {
    "addr:full":"342 Main St Center Moriches NY 11934",
    "addr:housenumber":"342",
    "addr:postcode":"11934",
    "addr:street":"Main St",
    "iso:country":"US",
    "sg:address":"342 Main St",
    "sg:city":"Center Moriches",
    "sg:classifiers":[
        {
            "category":"Shopping",
            "subcategory":"Florist",
            "type":"Retail Goods"
        }
    ],
    "sg:phone":"+1 631 874 1030",
    "sg:postcode":"11934",
    "sg:province":"NY",
    "wof:name":"Moriches Main St Flowers",
    "wof:placetype":"venue"
},
  "geometry": {"coordinates":[-72.79202600000001,40.800222],"type":"Point"}
}