{
  "type": "Feature",
  "properties": {
    "iso:country":"US",
    "sg:address":"1 Glendale Ave",
    "sg:city":"Armonk",
    "sg:classifiers":[
        {
            "category":"Restaurant",
            "type":"Food & Drink"
        }
    ],
    "sg:phone":"+1 914 273 8211",
    "sg:postcode":"10504",
    "sg:province":"NY",
    "sg:tags":[
        "seafood"
    ],
    "wof:name":"Ship To Shore Fisheries",
    "wof:placetype":"venue"
},
  "geometry": {"coordinates":[-73.7089,41.129799],"type":"Point"}
}