{
  "type": "Feature",
  "properties": {
    "addr:full":"617 Sackett St Brooklyn NY 11217",
    "addr:housenumber":"617",
    "addr:postcode":"11217",
    "addr:street":"Sackett St",
    "iso:country":"US",
    "sg:address":"617 Sackett St",
    "sg:city":"Brooklyn",
    "sg:phone":"+1 718 797 3434",
    "sg:postcode":"11217",
    "sg:province":"NY",
    "sg:tags":[
        "leather",
        "finish",
        "findings"
    ],
    "wof:name":"National Leather & Shoe Fndngs",
    "wof:placetype":"venue"
},
  "geometry": {"coordinates":[-73.983368,40.678522],"type":"Point"}
}