{
  "type": "Feature",
  "properties": {
    "iso:country":"US",
    "sg:address":"6 Wall St",
    "sg:city":"Homer",
    "sg:classifiers":[
        {
            "category":"Personal",
            "subcategory":"Beauty Salon",
            "type":"Services"
        }
    ],
    "sg:phone":"+1 607 749 6816",
    "sg:postcode":"13077",
    "sg:province":"NY",
    "wof:name":"Suzanne's Salon",
    "wof:placetype":"venue"
},
  "geometry": {"coordinates":[-76.178426,42.63725],"type":"Point"}
}