{
  "type": "Feature",
  "properties": {
    "addr:full":"97 Hillside Ave New York NY 10040",
    "addr:housenumber":"97",
    "addr:postcode":"10040",
    "addr:street":"Hillside Ave",
    "iso:country":"US",
    "sg:address":"97 Hillside Ave",
    "sg:city":"New York",
    "sg:classifiers":[
        {
            "category":"Building & Trades",
            "subcategory":"Cleaning & Sanitation",
            "type":"Services"
        }
    ],
    "sg:phone":"+1 212 663 6500",
    "sg:postcode":"10040",
    "sg:province":"NY",
    "sg:tags":[
        "janitor"
    ],
    "wof:name":"Giovanni Cohen Office Cleaning",
    "wof:placetype":"venue"
},
  "geometry": {"coordinates":[-73.927156,40.85948],"type":"Point"}
}