{
  "type": "Feature",
  "properties": {
    "addr:full":"540 Jericho Tpke Mineola NY 11501",
    "addr:housenumber":"540",
    "addr:postcode":"11501",
    "addr:street":"Jericho Tpke",
    "iso:country":"US",
    "sg:address":"540 Jericho Tpke",
    "sg:city":"Mineola",
    "sg:classifiers":[
        {
            "category":"Banks & Credit Unions",
            "subcategory":"Bank",
            "type":"Services"
        }
    ],
    "sg:phone":"+1 516 741 4261",
    "sg:postcode":"11501",
    "sg:province":"NY",
    "wof:name":"TD Bank",
    "wof:placetype":"venue"
},
  "geometry": {"coordinates":[-73.65691200000001,40.74422],"type":"Point"}
}