{
  "type": "Feature",
  "properties": {
    "iso:country":"US",
    "sg:address":"1330 Carroll St",
    "sg:city":"Cortland",
    "sg:classifiers":[
        {
            "category":"Autos & Motor Vehicles",
            "subcategory":"Automobile Sales",
            "type":"Retail Goods"
        },
        {
            "category":"Retail",
            "subcategory":"Auto Repair",
            "type":"Services"
        }
    ],
    "sg:phone":"+1 607 756 2351",
    "sg:postcode":"13045",
    "sg:province":"NY",
    "sg:tags":[
        "car",
        "used",
        "dealer",
        "general"
    ],
    "wof:name":"Fairgrounds Auto Sales In",
    "wof:placetype":"venue"
},
  "geometry": {"coordinates":[-76.186314,42.613958],"type":"Point"}
}