{
  "type": "Feature",
  "properties": {
    "addr:full":"26 Willow Pl Brooklyn NY 11201",
    "addr:housenumber":"26",
    "addr:postcode":"11201",
    "addr:street":"Willow Pl",
    "iso:country":"US",
    "sg:address":"26 Willow Pl",
    "sg:city":"Brooklyn",
    "sg:classifiers":[
        {
            "category":"Organizations",
            "subcategory":"Non-profit Organization",
            "type":"Services"
        }
    ],
    "sg:phone":"+1 718 237 2752",
    "sg:postcode":"11201",
    "sg:province":"NY",
    "sg:tags":[
        "service/non-profit",
        "community"
    ],
    "sg:website":"www.heightsplayers.org",
    "wof:name":"Heights Players Inc",
    "wof:placetype":"venue"
},
  "geometry": {"coordinates":[-73.998299,40.6926],"type":"Point"}
}