{
  "type": "Feature",
  "properties": {
    "addr:full":"5405 12th Ave Brooklyn NY 11219",
    "addr:housenumber":"5405",
    "addr:postcode":"11219",
    "addr:street":"12Th Ave",
    "iso:country":"US",
    "sg:address":"5405 12th Ave",
    "sg:city":"Brooklyn",
    "sg:classifiers":[
        {
            "category":"Organizations",
            "subcategory":"Religious Organization",
            "type":"Services"
        }
    ],
    "sg:phone":"+1 718 851 1222",
    "sg:postcode":"11219",
    "sg:province":"NY",
    "sg:tags":[
        "clergy"
    ],
    "wof:name":"Jacob Klein",
    "wof:placetype":"venue"
},
  "geometry": {"coordinates":[-73.997736,40.632972],"type":"Point"}
}