{
  "type": "Feature",
  "properties": {
    "addr:full":"1300 Veterans Hwy Ste 140 Hauppauge NY 11788",
    "addr:housenumber":"1300",
    "addr:postcode":"11788",
    "addr:street":"Veterans Hwy Ste 140",
    "iso:country":"US",
    "sg:address":"1300 Veterans Hwy Ste 140",
    "sg:city":"Hauppauge",
    "sg:classifiers":[
        {
            "category":"Professional",
            "subcategory":"Management & Consulting",
            "type":"Services"
        },
        {
            "category":"Banks & Credit Unions",
            "subcategory":"Investment Brokerage",
            "type":"Services"
        },
        {
            "category":"Health Services",
            "subcategory":"Nursing And Care Facility",
            "type":"Services"
        },
        {
            "category":"Banks & Credit Unions",
            "subcategory":"Financial Services",
            "type":"Services"
        },
        {
            "category":"Social Services",
            "subcategory":"Adult Care",
            "type":"Services"
        }
    ],
    "sg:phone":"+1 631 218 3174",
    "sg:postcode":"11788",
    "sg:province":"NY",
    "sg:tags":[
        "living",
        "financing",
        "consultant",
        "assisted",
        "rest",
        "elder",
        "planning",
        "home",
        "security"
    ],
    "wof:name":"Creative Retirement Planning, Inc",
    "wof:placetype":"venue"
},
  "geometry": {"coordinates":[-73.190675,40.813452],"type":"Point"}
}