{
  "type": "Feature",
  "properties": {
    "addr:full":"11 Douglas St Batavia NY 14020",
    "addr:housenumber":"11",
    "addr:postcode":"14020",
    "addr:street":"Douglas St",
    "iso:country":"US",
    "sg:address":"11 Douglas St",
    "sg:city":"Batavia",
    "sg:classifiers":[
        {
            "category":"Shopping",
            "subcategory":"Florist",
            "type":"Retail Goods"
        }
    ],
    "sg:phone":"+1   ",
    "sg:postcode":"14020",
    "sg:province":"NY",
    "wof:name":"Photos Flowers Gifts",
    "wof:placetype":"venue"
},
  "geometry": {"coordinates":[-78.181804,43.008247],"type":"Point"}
}