{
  "type": "Feature",
  "properties": {
    "iso:country":"US",
    "sg:address":"29 Washington Sq W",
    "sg:city":"New York",
    "sg:classifiers":[
        {
            "category":"Shopping",
            "subcategory":"Used Merchandise",
            "type":"Retail Goods"
        }
    ],
    "sg:phone":"+1   ",
    "sg:postcode":"10011",
    "sg:province":"NY",
    "sg:tags":[
        "antique"
    ],
    "wof:name":"Jones Road Antiques",
    "wof:placetype":"venue"
},
  "geometry": {"coordinates":[-73.998957,40.731814],"type":"Point"}
}