{
  "type": "Feature",
  "properties": {
    "iso:country":"US",
    "sg:address":"769 Elmont Rd",
    "sg:city":"Elmont",
    "sg:classifiers":[
        {
            "category":"Building & Trades",
            "subcategory":"Cleaning & Sanitation",
            "type":"Services"
        }
    ],
    "sg:phone":"+1 718 387 3367",
    "sg:postcode":"11003",
    "sg:province":"NY",
    "sg:tags":[
        "home"
    ],
    "sg:website":"www.sato-construction.com",
    "wof:name":"Sato Construction",
    "wof:placetype":"venue"
},
  "geometry": {"coordinates":[-73.71959699999999,40.691898],"type":"Point"}
}