{
  "type": "Feature",
  "properties": {
    "iso:country":"US",
    "sg:address":"19 Asbury Dr",
    "sg:city":"Smithtown",
    "sg:classifiers":[
        {
            "category":"Real Estate",
            "subcategory":"Real Estate Agent",
            "type":"Services"
        }
    ],
    "sg:phone":"+1 631 360 1377",
    "sg:postcode":"11787",
    "sg:province":"NY",
    "wof:name":"Dli Assocs",
    "wof:placetype":"venue"
},
  "geometry": {"coordinates":[-73.24087,40.849621],"type":"Point"}
}