{
  "type": "Feature",
  "properties": {
    "addr:full":"1840 58th St Brooklyn NY 11204",
    "addr:housenumber":"1840",
    "addr:postcode":"11204",
    "addr:street":"58Th St",
    "iso:country":"US",
    "sg:address":"1840 58th St",
    "sg:city":"Brooklyn",
    "sg:classifiers":[
        {
            "category":"Organizations",
            "subcategory":"Religious Organization",
            "type":"Services"
        }
    ],
    "sg:phone":"+1 718 259 2063",
    "sg:postcode":"11204",
    "sg:province":"NY",
    "sg:tags":[
        "clergy"
    ],
    "wof:name":"Barry Webster",
    "wof:placetype":"venue"
},
  "geometry": {"coordinates":[-73.985302,40.62276],"type":"Point"}
}