{
  "type": "Feature",
  "properties": {
    "addr:full":"10 E 53rd Street New York NY 10022",
    "addr:housenumber":"10",
    "addr:postcode":"10022",
    "addr:street":"E 53Rd Street",
    "iso:country":"US",
    "sg:address":"10 E 53rd Street",
    "sg:city":"New York",
    "sg:classifiers":[
        {
            "category":"Banks & Credit Unions",
            "subcategory":"Investment Brokerage",
            "type":"Services"
        }
    ],
    "sg:phone":"+1 212 319 7676",
    "sg:postcode":"10022",
    "sg:province":"NY",
    "sg:tags":[
        "investing"
    ],
    "wof:name":"Crescendo Advisors II",
    "wof:placetype":"venue"
},
  "geometry": {"coordinates":[-73.975234,40.760145],"type":"Point"}
}