{
  "type": "Feature",
  "properties": {
    "iso:country":"US",
    "sg:address":"450 Fashion Ave",
    "sg:city":"New York",
    "sg:classifiers":[
        {
            "category":"Health Services",
            "subcategory":"Dentist",
            "type":"Services"
        }
    ],
    "sg:phone":"+1 212 563 3693",
    "sg:postcode":"10123",
    "sg:province":"NY",
    "wof:name":"Rubin Edward",
    "wof:placetype":"venue"
},
  "geometry": {"coordinates":[-73.990402,40.7509],"type":"Point"}
}