{
  "type": "Feature",
  "properties": {
    "addr:full":"560 Broadway New York NY 10012",
    "addr:housenumber":"560",
    "addr:postcode":"10012",
    "addr:street":"Broadway",
    "iso:country":"US",
    "sg:address":"560 Broadway",
    "sg:city":"New York",
    "sg:classifiers":[
        {
            "category":"Restaurant",
            "type":"Food & Drink"
        }
    ],
    "sg:menulink":"http://www.allmenus.com/ny/new-york/252706-dean--deluca-catering/menu/",
    "sg:phone":"+1 212 226 6800",
    "sg:postcode":"10012",
    "sg:province":"NY",
    "sg:tags":[
        "american"
    ],
    "wof:name":"Dean & Deluca Catering",
    "wof:placetype":"venue"
},
  "geometry": {"coordinates":[-73.997466,40.723854],"type":"Point"}
}