{
  "type": "Feature",
  "properties": {
    "iso:country":"US",
    "sg:address":"180 E Post Rd",
    "sg:city":"White Plains",
    "sg:classifiers":[
        {
            "category":"Social Services",
            "type":"Services"
        }
    ],
    "sg:phone":"+1   ",
    "sg:postcode":"10601",
    "sg:province":"NY",
    "wof:name":"Center Lane of W J C S",
    "wof:placetype":"venue"
},
  "geometry": {"coordinates":[-73.76503700000001,41.029344],"type":"Point"}
}