{
  "type": "Feature",
  "properties": {
    "iso:country":"US",
    "sg:address":"35 Delancey Ct",
    "sg:city":"Pittsford",
    "sg:classifiers":[
        {
            "category":"Wholesale",
            "subcategory":"Medical Equipment & Supplies",
            "type":"Manufacturing & Wholesale Goods"
        }
    ],
    "sg:phone":"+1 585 615 7707",
    "sg:postcode":"14534",
    "sg:province":"NY",
    "sg:tags":[
        "laboratory"
    ],
    "wof:name":"Aquaero Systems",
    "wof:placetype":"venue"
},
  "geometry": {"coordinates":[-77.562342,43.063877],"type":"Point"}
}