{
  "type": "Feature",
  "properties": {
    "addr:full":"107 E 33 St New York NY 10016",
    "addr:housenumber":"107;33",
    "addr:postcode":"10016",
    "addr:street":"E;St",
    "iso:country":"US",
    "sg:address":"107 E 33 St",
    "sg:city":"New York",
    "sg:classifiers":[
        {
            "category":"Professional",
            "subcategory":"Research",
            "type":"Services"
        }
    ],
    "sg:phone":"+1 212 889 6074",
    "sg:postcode":"10016",
    "sg:province":"NY",
    "sg:tags":[
        "market",
        "analysis"
    ],
    "wof:name":"EVAXX",
    "wof:placetype":"venue"
},
  "geometry": {"coordinates":[-73.980367,40.745907],"type":"Point"}
}