{
  "type": "Feature",
  "properties": {
    "addr:full":"165 Canal St Fort Plain NY 13339",
    "addr:housenumber":"165",
    "addr:postcode":"13339",
    "addr:street":"Canal St",
    "iso:country":"US",
    "sg:address":"165 Canal St",
    "sg:city":"Fort Plain",
    "sg:classifiers":[
        {
            "category":"Organizations",
            "subcategory":"Religious Organization",
            "type":"Services"
        }
    ],
    "sg:phone":"+1 518 993 4302",
    "sg:postcode":"13339",
    "sg:province":"NY",
    "sg:tags":[
        "church"
    ],
    "wof:name":"Reformed Church",
    "wof:placetype":"venue"
},
  "geometry": {"coordinates":[-74.62435000000001,42.932995],"type":"Point"}
}