{
  "type": "Feature",
  "properties": {
    "addr:full":"183 State Route 23B Hudson NY 12534",
    "addr:housenumber":"183",
    "addr:postcode":"12534",
    "addr:street":"State Route 23B",
    "iso:country":"US",
    "sg:address":"183 State Route 23B",
    "sg:city":"Hudson",
    "sg:classifiers":[
        {
            "category":"Organizations",
            "subcategory":"Religious Organization",
            "type":"Services"
        }
    ],
    "sg:phone":"+1 518 828 9891",
    "sg:postcode":"12534",
    "sg:province":"NY",
    "wof:name":"Grace Assembly Appostolic",
    "wof:placetype":"venue"
},
  "geometry": {"coordinates":[-73.772745,42.246933],"type":"Point"}
}