{
  "type": "Feature",
  "properties": {
    "iso:country":"US",
    "sg:address":"446 Thurber St",
    "sg:city":"Syracuse",
    "sg:classifiers":[
        {
            "category":"Manufacturing",
            "subcategory":"Wood Products",
            "type":"Manufacturing & Wholesale Goods"
        }
    ],
    "sg:phone":"+1   ",
    "sg:postcode":"13210",
    "sg:province":"NY",
    "sg:tags":[
        "mfg"
    ],
    "wof:name":"Accent Framing",
    "wof:placetype":"venue"
},
  "geometry": {"coordinates":[-76.129141,43.019033],"type":"Point"}
}