{
  "type": "Feature",
  "properties": {
    "addr:full":"400 Community Dr Manhasset NY 11030",
    "addr:housenumber":"400",
    "addr:postcode":"11030",
    "addr:street":"Community Dr",
    "iso:country":"US",
    "sg:address":"400 Community Dr",
    "sg:city":"Manhasset",
    "sg:classifiers":[
        {
            "category":"Health Services",
            "subcategory":"Hospital",
            "type":"Services"
        }
    ],
    "sg:phone":"+1 516 562 3053",
    "sg:postcode":"11030",
    "sg:province":"NY",
    "wof:name":"New York Presbyterian Hospital",
    "wof:placetype":"venue"
},
  "geometry": {"coordinates":[-73.70327899999999,40.773415],"type":"Point"}
}