{
  "type": "Feature",
  "properties": {
    "addr:full":"703 Seneca Ave Ridgewood NY 11385",
    "addr:housenumber":"703",
    "addr:postcode":"11385",
    "addr:street":"Seneca Ave",
    "iso:country":"US",
    "sg:address":"703 Seneca Ave",
    "sg:city":"Ridgewood",
    "sg:classifiers":[
        {
            "category":"Real Estate",
            "subcategory":"Real Estate Agent",
            "type":"Services"
        }
    ],
    "sg:phone":"+1 718 386 6555",
    "sg:postcode":"11385",
    "sg:province":"NY",
    "wof:name":"Lucia Realty",
    "wof:placetype":"venue"
},
  "geometry": {"coordinates":[-73.907618,40.702772],"type":"Point"}
}