{
  "type": "Feature",
  "properties": {
    "iso:country":"US",
    "sg:address":"18722 Quencer Rd",
    "sg:city":"Saint Albans",
    "sg:classifiers":[
        {
            "category":"Autos & Motor Vehicles",
            "subcategory":"Automobile Sales",
            "type":"Retail Goods"
        }
    ],
    "sg:phone":"+1 718 949 4323",
    "sg:postcode":"11412",
    "sg:province":"NY",
    "sg:tags":[
        "limo"
    ],
    "sg:website":"www.navigatortransportation.com",
    "wof:name":"Navigator Transportation Service Corp",
    "wof:placetype":"venue"
},
  "geometry": {"coordinates":[-73.767197,40.695801],"type":"Point"}
}