{
  "type": "Feature",
  "properties": {
    "iso:country":"US",
    "sg:address":"293 Deauville Blvd",
    "sg:city":"Copiague",
    "sg:classifiers":[
        {
            "category":"Personal",
            "type":"Services"
        }
    ],
    "sg:phone":"+1 631 691 4844",
    "sg:postcode":"11726",
    "sg:province":"NY",
    "sg:tags":[
        "assistant"
    ],
    "wof:name":"Joseph Cardino",
    "wof:placetype":"venue"
},
  "geometry": {"coordinates":[-73.404419,40.677345],"type":"Point"}
}