{
  "type": "Feature",
  "properties": {
    "addr:full":"6181 Strickland Ave Brooklyn NY 11234",
    "addr:housenumber":"6181",
    "addr:postcode":"11234",
    "addr:street":"Strickland Ave",
    "iso:country":"US",
    "sg:address":"6181 Strickland Ave",
    "sg:city":"Brooklyn",
    "sg:classifiers":[
        {
            "category":"Restaurant",
            "type":"Food & Drink"
        }
    ],
    "sg:phone":"+1 718 676 5891",
    "sg:postcode":"11234",
    "sg:province":"NY",
    "wof:name":"Gourmet Grill",
    "wof:placetype":"venue"
},
  "geometry": {"coordinates":[-73.91405399999999,40.609043],"type":"Point"}
}