{
  "type": "Feature",
  "properties": {
    "addr:full":"1078 Nostrand Ave Brooklyn NY 11225",
    "addr:housenumber":"1078",
    "addr:postcode":"11225",
    "addr:street":"Nostrand Ave",
    "iso:country":"US",
    "sg:address":"1078 Nostrand Ave",
    "sg:city":"Brooklyn",
    "sg:classifiers":[
        {
            "category":"Restaurant",
            "type":"Food & Drink"
        }
    ],
    "sg:phone":"+1 718 856 3888",
    "sg:postcode":"11225",
    "sg:province":"NY",
    "sg:tags":[
        "delivery"
    ],
    "wof:name":"Taste Of China",
    "wof:placetype":"venue"
},
  "geometry": {"coordinates":[-73.950857,40.662276],"type":"Point"}
}