{
  "type": "Feature",
  "properties": {
    "addr:full":"442 Beach Rd Buffalo NY 14225",
    "addr:housenumber":"442",
    "addr:postcode":"14225",
    "addr:street":"Beach Rd",
    "iso:country":"US",
    "sg:address":"442 Beach Rd",
    "sg:city":"Buffalo",
    "sg:classifiers":[
        {
            "category":"Personal",
            "subcategory":"Beauty Salon",
            "type":"Services"
        }
    ],
    "sg:phone":"+1   ",
    "sg:postcode":"14225",
    "sg:province":"NY",
    "sg:tags":[
        "shop"
    ],
    "wof:name":"Cut Hut",
    "wof:placetype":"venue"
},
  "geometry": {"coordinates":[-78.76232299999999,42.931273],"type":"Point"}
}