{
  "type": "Feature",
  "properties": {
    "iso:country":"US",
    "sg:address":"222 7 Ave",
    "sg:city":"New York",
    "sg:classifiers":[
        {
            "category":"Retail",
            "subcategory":"Auto Repair",
            "type":"Services"
        }
    ],
    "sg:phone":"+1 212 624 1316",
    "sg:postcode":"10011",
    "sg:province":"NY",
    "sg:tags":[
        "wrecker"
    ],
    "wof:name":"Anytime Towing Svc",
    "wof:placetype":"venue"
},
  "geometry": {"coordinates":[-74.000693,40.736974],"type":"Point"}
}