{
  "type": "Feature",
  "properties": {
    "addr:full":"3059 Eastchester Rd Bronx NY 10469",
    "addr:housenumber":"3059",
    "addr:postcode":"10469",
    "addr:street":"Eastchester Rd",
    "iso:country":"US",
    "sg:address":"3059 Eastchester Rd",
    "sg:city":"Bronx",
    "sg:classifiers":[
        {
            "category":"Real Estate",
            "subcategory":"Real Estate Agent",
            "type":"Services"
        }
    ],
    "sg:phone":"+1 718 379 2121",
    "sg:postcode":"10469",
    "sg:province":"NY",
    "wof:name":"Prudential Aashwani Realty",
    "wof:placetype":"venue"
},
  "geometry": {"coordinates":[-73.843535,40.870958],"type":"Point"}
}