{
  "type": "Feature",
  "properties": {
    "addr:full":"302 Morningstar Rd Staten Island NY 10303",
    "addr:housenumber":"302",
    "addr:postcode":"10303",
    "addr:street":"Morningstar Rd",
    "iso:country":"US",
    "sg:address":"302 Morningstar Rd",
    "sg:city":"Staten Island",
    "sg:classifiers":[
        {
            "category":"Food & Beverages",
            "subcategory":"Groceries & Convenience Stores",
            "type":"Retail Goods"
        }
    ],
    "sg:phone":"+1 718 727 7769",
    "sg:postcode":"10303",
    "sg:province":"NY",
    "wof:name":"Guerrero Minimarket",
    "wof:placetype":"venue"
},
  "geometry": {"coordinates":[-74.147378,40.630121],"type":"Point"}
}