{
  "type": "Feature",
  "properties": {
    "addr:full":"1477 Leland Ave Bronx NY 10460",
    "addr:housenumber":"1477",
    "addr:postcode":"10460",
    "addr:street":"Leland Ave",
    "iso:country":"US",
    "sg:address":"1477 Leland Ave",
    "sg:city":"Bronx",
    "sg:classifiers":[
        {
            "category":"Health Services",
            "subcategory":"Doctor",
            "type":"Services"
        }
    ],
    "sg:phone":"+1 718 904 1411",
    "sg:postcode":"10460",
    "sg:province":"NY",
    "wof:name":"Archer Health Care",
    "wof:placetype":"venue"
},
  "geometry": {"coordinates":[-73.86449399999999,40.837527],"type":"Point"}
}