{
  "type": "Feature",
  "properties": {
    "addr:full":"403 Jericho Tpke New Hyde Park NY 11040",
    "addr:housenumber":"403",
    "addr:postcode":"11040",
    "addr:street":"Jericho Tpke;Hyde Park",
    "iso:country":"US",
    "sg:address":"403 Jericho Tpke",
    "sg:city":"New Hyde Park",
    "sg:classifiers":[
        {
            "category":"Arts & Performance",
            "subcategory":"Theater",
            "type":"Entertainment"
        }
    ],
    "sg:phone":"+1 516 887 8777",
    "sg:postcode":"11040",
    "sg:province":"NY",
    "sg:tags":[
        "live",
        "music"
    ],
    "wof:name":"Satisfaction Guaranteed Entrtn",
    "wof:placetype":"venue"
},
  "geometry": {"coordinates":[-73.69005300000001,40.731601],"type":"Point"}
}