{
  "type": "Feature",
  "properties": {
    "addr:full":"30 Erie Canal Dr Rochester NY 14626",
    "addr:housenumber":"30",
    "addr:postcode":"14626",
    "addr:street":"Erie Canal Dr",
    "iso:country":"US",
    "sg:address":"30 Erie Canal Dr",
    "sg:city":"Rochester",
    "sg:classifiers":[
        {
            "category":"Professional",
            "subcategory":"Computer Services",
            "type":"Services"
        }
    ],
    "sg:phone":"+1 585 328 3602",
    "sg:postcode":"14626",
    "sg:province":"NY",
    "sg:tags":[
        "internet"
    ],
    "sg:website":"www.enterprisedesign.cc",
    "wof:name":"Enterprise Design",
    "wof:placetype":"venue"
},
  "geometry": {"coordinates":[-77.70395600000001,43.185019],"type":"Point"}
}