{
  "type": "Feature",
  "properties": {
    "addr:full":"161 Center St Ellenville NY 12428",
    "addr:housenumber":"161",
    "addr:postcode":"12428",
    "addr:street":"Center St",
    "iso:country":"US",
    "sg:address":"161 Center St",
    "sg:city":"Ellenville",
    "sg:classifiers":[
        {
            "category":"Organizations",
            "subcategory":"Religious Organization",
            "type":"Services"
        }
    ],
    "sg:phone":"+1 845 647 5998",
    "sg:postcode":"12428",
    "sg:province":"NY",
    "sg:tags":[
        "church"
    ],
    "wof:name":"Ellenville SDA Church",
    "wof:placetype":"venue"
},
  "geometry": {"coordinates":[-74.386931,41.711989],"type":"Point"}
}