{
  "type": "Feature",
  "properties": {
    "addr:full":"209 Lake Flower Ave Saranac Lake NY 12983",
    "addr:housenumber":"209",
    "addr:postcode":"12983",
    "addr:street":"Lake Flower Ave",
    "iso:country":"US",
    "sg:address":"209 Lake Flower Ave",
    "sg:city":"Saranac Lake",
    "sg:classifiers":[
        {
            "category":"Banks & Credit Unions",
            "subcategory":"Bank",
            "type":"Services"
        }
    ],
    "sg:phone":"+1 518 891 2050",
    "sg:postcode":"12983",
    "sg:province":"NY",
    "wof:name":"NBT Bank",
    "wof:placetype":"venue"
},
  "geometry": {"coordinates":[-74.115527,44.310994],"type":"Point"}
}