{
  "type": "Feature",
  "properties": {
    "addr:full":"500 E 87th St New York NY 10128",
    "addr:housenumber":"500",
    "addr:postcode":"10128",
    "addr:street":"E 87Th St",
    "iso:country":"US",
    "sg:address":"500 E 87th St",
    "sg:city":"New York",
    "sg:classifiers":[
        {
            "category":"Health Services",
            "subcategory":"Dentist",
            "type":"Services"
        }
    ],
    "sg:phone":"+1 212 288 5350",
    "sg:postcode":"10128",
    "sg:province":"NY",
    "wof:name":"Elite Smiles",
    "wof:placetype":"venue"
},
  "geometry": {"coordinates":[-73.94668900000001,40.776473],"type":"Point"}
}