{
  "type": "Feature",
  "properties": {
    "addr:full":"3 Cebra Ave Staten Island NY 10301",
    "addr:housenumber":"3",
    "addr:postcode":"10301",
    "addr:street":"Cebra Ave",
    "iso:country":"US",
    "sg:address":"3 Cebra Ave",
    "sg:city":"Staten Island",
    "sg:classifiers":[
        {
            "category":"Restaurant",
            "type":"Food & Drink"
        }
    ],
    "sg:phone":"+1 718 355 6065",
    "sg:postcode":"10301",
    "sg:province":"NY",
    "wof:name":"Lakshmi's Restaurant",
    "wof:placetype":"venue"
},
  "geometry": {"coordinates":[-74.08578199999999,40.634078],"type":"Point"}
}