{
  "type": "Feature",
  "properties": {
    "iso:country":"US",
    "sg:address":"3304 Park Ave",
    "sg:city":"Oceanside",
    "sg:classifiers":[
        {
            "category":"Manufacturing",
            "subcategory":"Printing",
            "type":"Manufacturing & Wholesale Goods"
        }
    ],
    "sg:phone":"+1 516 255 2006",
    "sg:postcode":"11572",
    "sg:province":"NY",
    "sg:tags":[
        "multimedia"
    ],
    "wof:name":"I P Media Inc",
    "wof:placetype":"venue"
},
  "geometry": {"coordinates":[-73.63056400000001,40.630946],"type":"Point"}
}