{
  "type": "Feature",
  "properties": {
    "addr:full":"6407 108th St Forest Hills NY 11375",
    "addr:housenumber":"6407",
    "addr:postcode":"11375",
    "addr:street":"108Th St",
    "iso:country":"US",
    "sg:address":"6407 108th St",
    "sg:city":"Forest Hills",
    "sg:classifiers":[
        {
            "category":"Shopping",
            "subcategory":"Shoes",
            "type":"Retail Goods"
        }
    ],
    "sg:phone":"+1 718 997 8151",
    "sg:postcode":"11375",
    "sg:province":"NY",
    "sg:tags":[
        "store"
    ],
    "wof:name":"Salamander Shoe Store",
    "wof:placetype":"venue"
},
  "geometry": {"coordinates":[-73.849267,40.732817],"type":"Point"}
}