{
  "type": "Feature",
  "properties": {
    "addr:full":"521 Sunrise Hwy West Islip NY 11795",
    "addr:housenumber":"521",
    "addr:postcode":"11795",
    "addr:street":"Sunrise Hwy West",
    "iso:country":"US",
    "sg:address":"521 Sunrise Hwy",
    "sg:city":"West Islip",
    "sg:classifiers":[
        {
            "category":"Retail",
            "subcategory":"Veterinary Services",
            "type":"Services"
        },
        {
            "category":"Retail",
            "subcategory":"Pet Boarding",
            "type":"Services"
        }
    ],
    "sg:phone":"+1 631 956 4448",
    "sg:postcode":"11795",
    "sg:province":"NY",
    "sg:tags":[
        "veterinarian",
        "boarding/pet",
        "sitting"
    ],
    "sg:website":"www.sunrisevet.com",
    "wof:name":"Sunrise Veterinary Group",
    "wof:placetype":"venue"
},
  "geometry": {"coordinates":[-73.292345,40.7246],"type":"Point"}
}