{
  "type": "Feature",
  "properties": {
    "addr:full":"3668 Delaware Ave Buffalo NY 14217",
    "addr:housenumber":"3668",
    "addr:postcode":"14217",
    "addr:street":"Delaware Ave",
    "iso:country":"US",
    "sg:address":"3668 Delaware Ave",
    "sg:city":"Buffalo",
    "sg:classifiers":[
        {
            "category":"Restaurant",
            "type":"Food & Drink"
        }
    ],
    "sg:phone":"+1   ",
    "sg:postcode":"14217",
    "sg:province":"NY",
    "sg:tags":[
        "eating"
    ],
    "wof:name":"Peking Garden Chinese Rest",
    "wof:placetype":"venue"
},
  "geometry": {"coordinates":[-78.872929,42.984469],"type":"Point"}
}