{
  "type": "Feature",
  "properties": {
    "addr:full":"19 Mill St Rhinebeck NY 12572",
    "addr:housenumber":"19",
    "addr:postcode":"12572",
    "addr:street":"Mill St",
    "iso:country":"US",
    "sg:address":"19 Mill St",
    "sg:city":"Rhinebeck",
    "sg:classifiers":[
        {
            "category":"Organizations",
            "subcategory":"Professional Association",
            "type":"Services"
        }
    ],
    "sg:phone":"+1 845 876 4778",
    "sg:postcode":"12572",
    "sg:province":"NY",
    "sg:tags":[
        "chambers",
        "commerce"
    ],
    "wof:name":"Chamber Of Commerce",
    "wof:placetype":"venue"
},
  "geometry": {"coordinates":[-73.912457,41.926411],"type":"Point"}
}