{
  "type": "Feature",
  "properties": {
    "addr:full":"153 Hudson St New York NY 10013",
    "addr:housenumber":"153",
    "addr:postcode":"10013",
    "addr:street":"Hudson St",
    "iso:country":"US",
    "sg:address":"153 Hudson St",
    "sg:city":"New York",
    "sg:classifiers":[
        {
            "category":"Museum",
            "type":"Entertainment"
        }
    ],
    "sg:phone":"+1 917 237 1158",
    "sg:postcode":"10013",
    "sg:province":"NY",
    "sg:tags":[
        "platform",
        "american",
        "latin",
        "creation",
        "for"
    ],
    "wof:name":"Latincollectorcom Inc",
    "wof:placetype":"venue"
},
  "geometry": {"coordinates":[-74.008321,40.721868],"type":"Point"}
}