{
  "type": "Feature",
  "properties": {
    "iso:country":"US",
    "sg:address":"64 Devoe Ave",
    "sg:city":"Yonkers",
    "sg:classifiers":[
        {
            "category":"Retail",
            "subcategory":"Repair Shop",
            "type":"Services"
        }
    ],
    "sg:phone":"+1 914 476 8477",
    "sg:postcode":"10705",
    "sg:province":"NY",
    "sg:tags":[
        "equipment",
        "conditioning",
        "air"
    ],
    "wof:name":"Rondel TV Svc",
    "wof:placetype":"venue"
},
  "geometry": {"coordinates":[-73.877753,40.911781],"type":"Point"}
}