{
  "type": "Feature",
  "properties": {
    "iso:country":"US",
    "sg:address":"366 Townview Dr",
    "sg:city":"Wappingers Falls",
    "sg:classifiers":[
        {
            "category":"Professional",
            "type":"Services"
        }
    ],
    "sg:phone":"+1 845 838 0610",
    "sg:postcode":"12590",
    "sg:province":"NY",
    "sg:tags":[
        "establishment"
    ],
    "wof:name":"Bridge St Worldwide",
    "wof:placetype":"venue"
},
  "geometry": {"coordinates":[-73.970257,41.530888],"type":"Point"}
}