{
  "type": "Feature",
  "properties": {
    "addr:full":"4578 US Hwy 13 Pulaski NY 13142",
    "addr:housenumber":"4578",
    "addr:postcode":"13142",
    "addr:street":"Us Hwy 13",
    "iso:country":"US",
    "sg:address":"4578 US Hwy 13",
    "sg:city":"Pulaski",
    "sg:classifiers":[
        {
            "category":"Professional",
            "type":"Services"
        }
    ],
    "sg:phone":"+1 315 298 4391",
    "sg:postcode":"13142",
    "sg:province":"NY",
    "sg:tags":[
        "establishment"
    ],
    "wof:name":"Myrna WORX",
    "wof:placetype":"venue"
},
  "geometry": {"coordinates":[-76.145172,43.56013],"type":"Point"}
}