{
  "type": "Feature",
  "properties": {
    "iso:country":"US",
    "sg:address":"2710 Ridgeway Ave",
    "sg:city":"Rochester",
    "sg:classifiers":[
        {
            "category":"Building & Trades",
            "subcategory":"Construction",
            "type":"Services"
        }
    ],
    "sg:phone":"+1 585 865 5966",
    "sg:postcode":"14626",
    "sg:province":"NY",
    "sg:tags":[
        "handyman"
    ],
    "wof:name":"Mike's Handyman Svc",
    "wof:placetype":"venue"
},
  "geometry": {"coordinates":[-77.703851,43.186901],"type":"Point"}
}