{
  "type": "Feature",
  "properties": {
    "iso:country":"US",
    "sg:address":"10 Mitchell Place",
    "sg:city":"New York",
    "sg:classifiers":[
        {
            "category":"Real Estate",
            "subcategory":"Real Estate Operator",
            "type":"Services"
        }
    ],
    "sg:phone":"+1 212 355 1981",
    "sg:postcode":"10017",
    "sg:province":"NY",
    "sg:tags":[
        "apartment"
    ],
    "wof:name":"Apartments & Apartment Houses",
    "wof:placetype":"venue"
},
  "geometry": {"coordinates":[-73.96657500000001,40.752996],"type":"Point"}
}