{
  "type": "Feature",
  "properties": {
    "iso:country":"US",
    "sg:address":"583 Courtland Ave",
    "sg:city":"Bronx",
    "sg:classifiers":[
        {
            "category":"Food & Beverages",
            "subcategory":"Groceries & Convenience Stores",
            "type":"Retail Goods"
        }
    ],
    "sg:phone":"+1 718 585 7190",
    "sg:postcode":"10451",
    "sg:province":"NY",
    "sg:tags":[
        "grocer"
    ],
    "wof:name":"Deli Grocery",
    "wof:placetype":"venue"
},
  "geometry": {"coordinates":[-73.919027,40.817825],"type":"Point"}
}