{
  "type": "Feature",
  "properties": {
    "addr:full":"151 E Burnside Ave Bronx NY 10453",
    "addr:housenumber":"151",
    "addr:postcode":"10453",
    "addr:street":"E Burnside Ave",
    "iso:country":"US",
    "sg:address":"151 E Burnside Ave",
    "sg:city":"Bronx",
    "sg:classifiers":[
        {
            "category":"Shopping",
            "subcategory":"Clothing, Apparel, & Fashions",
            "type":"Retail Goods"
        }
    ],
    "sg:phone":"+1 718 733 7476",
    "sg:postcode":"10453",
    "sg:province":"NY",
    "sg:tags":[
        "jean"
    ],
    "wof:name":"Jeans Plus Co",
    "wof:placetype":"venue"
},
  "geometry": {"coordinates":[-73.90367999999999,40.852388],"type":"Point"}
}