{
  "type": "Feature",
  "properties": {
    "addr:full":"1155 Jericho Tpke Commack NY 11725",
    "addr:housenumber":"1155",
    "addr:postcode":"11725",
    "addr:street":"Jericho Tpke",
    "iso:country":"US",
    "sg:address":"1155 Jericho Tpke",
    "sg:city":"Commack",
    "sg:classifiers":[
        {
            "category":"Deli",
            "type":"Food & Drink"
        }
    ],
    "sg:menulink":"http://www.allmenus.com/ny/smithtown/247820-scotts-five-star-meat-center/menu/",
    "sg:phone":"+1 631 543 4350",
    "sg:postcode":"11725",
    "sg:province":"NY",
    "sg:tags":[
        "american"
    ],
    "wof:name":"Scott's Five Star Meat Center",
    "wof:placetype":"venue"
},
  "geometry": {"coordinates":[-73.265097,40.846536],"type":"Point"}
}