{
  "type": "Feature",
  "properties": {
    "addr:full":"1221 Fteley Ave Bronx NY 10472",
    "addr:housenumber":"1221",
    "addr:postcode":"10472",
    "addr:street":"Fteley Ave",
    "iso:country":"US",
    "sg:address":"1221 Fteley Ave",
    "sg:city":"Bronx",
    "sg:classifiers":[
        {
            "category":"Wholesale",
            "subcategory":"Scrap",
            "type":"Manufacturing & Wholesale Goods"
        }
    ],
    "sg:phone":"+1 718 328 2409",
    "sg:postcode":"10472",
    "sg:province":"NY",
    "sg:tags":[
        "recycling",
        "center"
    ],
    "wof:name":"Tomra Metro",
    "wof:placetype":"venue"
},
  "geometry": {"coordinates":[-73.871726,40.829489],"type":"Point"}
}