{
  "type": "Feature",
  "properties": {
    "addr:full":"78 Norman Ave Amityville NY 11701",
    "addr:housenumber":"78",
    "addr:postcode":"11701",
    "addr:street":"Norman Ave",
    "iso:country":"US",
    "sg:address":"78 Norman Ave",
    "sg:city":"Amityville",
    "sg:classifiers":[
        {
            "category":"Health Services",
            "subcategory":"Health Practitioner",
            "type":"Services"
        }
    ],
    "sg:phone":"+1   ",
    "sg:postcode":"11701",
    "sg:province":"NY",
    "sg:tags":[
        "therapist",
        "physical"
    ],
    "wof:name":"Stott Hollie Ba Lmt Cat",
    "wof:placetype":"venue"
},
  "geometry": {"coordinates":[-73.419225,40.657276],"type":"Point"}
}