{
  "type": "Feature",
  "properties": {
    "addr:full":"4 Smith St Sidney NY 13838",
    "addr:housenumber":"4",
    "addr:postcode":"13838",
    "addr:street":"Smith St",
    "iso:country":"US",
    "sg:address":"4 Smith St",
    "sg:city":"Sidney",
    "sg:classifiers":[
        {
            "category":"Shopping",
            "subcategory":"Florist",
            "type":"Retail Goods"
        }
    ],
    "sg:phone":"+1   ",
    "sg:postcode":"13838",
    "sg:province":"NY",
    "wof:name":"Darlenes Flower World",
    "wof:placetype":"venue"
},
  "geometry": {"coordinates":[-75.390142,42.315181],"type":"Point"}
}