{
  "type": "Feature",
  "properties": {
    "addr:full":"110 Smith St Brooklyn NY 11201",
    "addr:housenumber":"110",
    "addr:postcode":"11201",
    "addr:street":"Smith St",
    "iso:country":"US",
    "sg:address":"110 Smith St",
    "sg:city":"Brooklyn",
    "sg:classifiers":[
        {
            "category":"Communications",
            "type":"Services"
        }
    ],
    "sg:phone":"+1 718 246 5618",
    "sg:postcode":"11201",
    "sg:province":"NY",
    "sg:tags":[
        "consultant",
        "engineer"
    ],
    "wof:name":"Kingdom Communication",
    "wof:placetype":"venue"
},
  "geometry": {"coordinates":[-73.989609,40.687981],"type":"Point"}
}