{
  "type": "Feature",
  "properties": {
    "iso:country":"US",
    "sg:address":"1519 S Salina St",
    "sg:city":"Syracuse",
    "sg:classifiers":[
        {
            "category":"Insurance",
            "subcategory":"Insurance Agent",
            "type":"Services"
        }
    ],
    "sg:phone":"+1 315 476 5374",
    "sg:postcode":"13205",
    "sg:province":"NY",
    "wof:name":"Midtown Insurance",
    "wof:placetype":"venue"
},
  "geometry": {"coordinates":[-76.14771399999999,43.030898],"type":"Point"}
}