{
  "type": "Feature",
  "properties": {
    "addr:full":"464 Park Avenue S Manhattan NY 10016",
    "addr:housenumber":"464",
    "addr:postcode":"10016",
    "addr:street":"Park Avenue S",
    "iso:country":"US",
    "sg:address":"464 Park Avenue S",
    "sg:city":"Manhattan",
    "sg:classifiers":[
        {
            "category":"Restaurant",
            "type":"Food & Drink"
        }
    ],
    "sg:postcode":"10016",
    "sg:province":"NY",
    "sg:website":"www.chipotle.com",
    "wof:name":"Chipotle",
    "wof:placetype":"venue"
},
  "geometry": {"coordinates":[-73.98287000000001,40.745278],"type":"Point"}
}