{
  "type": "Feature",
  "properties": {
    "iso:country":"US",
    "sg:address":"12 W 23rd St",
    "sg:city":"New York",
    "sg:classifiers":[
        {
            "category":"Professional",
            "subcategory":"Art Services",
            "type":"Services"
        }
    ],
    "sg:phone":"+1 212 645 5800",
    "sg:postcode":"10010",
    "sg:province":"NY",
    "sg:tags":[
        "production",
        "commercial",
        "film"
    ],
    "wof:name":"Cohn & Company Inc",
    "wof:placetype":"venue"
},
  "geometry": {"coordinates":[-73.988731,40.741159],"type":"Point"}
}