{
  "type": "Feature",
  "properties": {
    "addr:full":"307 Gifford St Syracuse NY 13204",
    "addr:housenumber":"307",
    "addr:postcode":"13204",
    "addr:street":"Gifford St",
    "iso:country":"US",
    "sg:address":"307 Gifford St",
    "sg:city":"Syracuse",
    "sg:classifiers":[
        {
            "category":"Food & Beverages",
            "subcategory":"Groceries & Convenience Stores",
            "type":"Retail Goods"
        }
    ],
    "sg:phone":"+1 315 475 3441",
    "sg:postcode":"13204",
    "sg:province":"NY",
    "sg:tags":[
        "grocer"
    ],
    "wof:name":"Nojaim Brothers Super Market",
    "wof:placetype":"venue"
},
  "geometry": {"coordinates":[-76.158191,43.043451],"type":"Point"}
}