{
  "type": "Feature",
  "properties": {
    "addr:full":"4000 Boston Rd Bronx NY 10475",
    "addr:housenumber":"4000",
    "addr:postcode":"10475",
    "addr:street":"Boston Rd",
    "iso:country":"US",
    "sg:address":"4000 Boston Rd",
    "sg:city":"Bronx",
    "sg:classifiers":[
        {
            "category":"Home & Garden",
            "subcategory":"Furniture",
            "type":"Retail Goods"
        }
    ],
    "sg:phone":"+1 718 320 8400",
    "sg:postcode":"10475",
    "sg:province":"NY",
    "wof:name":"Basha Furniture",
    "wof:placetype":"venue"
},
  "geometry": {"coordinates":[-73.831693,40.884554],"type":"Point"}
}