{
  "type": "Feature",
  "properties": {
    "addr:full":"1644 Oneida St Utica NY 13501",
    "addr:housenumber":"1644",
    "addr:postcode":"13501",
    "addr:street":"Oneida St",
    "iso:country":"US",
    "sg:address":"1644 Oneida St",
    "sg:city":"Utica",
    "sg:classifiers":[
        {
            "category":"Restaurant",
            "type":"Food & Drink"
        }
    ],
    "sg:phone":"+1 315 733 2011",
    "sg:postcode":"13501",
    "sg:province":"NY",
    "sg:tags":[
        "cafe"
    ],
    "wof:name":"Diamonds",
    "wof:placetype":"venue"
},
  "geometry": {"coordinates":[-75.24966000000001,43.087492],"type":"Point"}
}