{
  "type": "Feature",
  "properties": {
    "iso:country":"US",
    "sg:address":"107 E State St",
    "sg:city":"Ithaca",
    "sg:classifiers":[
        {
            "category":"Manufacturing",
            "subcategory":"Tools & Machinery",
            "type":"Manufacturing & Wholesale Goods"
        }
    ],
    "sg:phone":"+1 607 277 3317",
    "sg:postcode":"14850",
    "sg:province":"NY",
    "sg:tags":[
        "computer",
        "storage",
        "devices"
    ],
    "wof:name":"Glyph Store",
    "wof:placetype":"venue"
},
  "geometry": {"coordinates":[-76.496903,42.43953],"type":"Point"}
}