{
  "type": "Feature",
  "properties": {
    "iso:country":"US",
    "sg:address":"162 State Hwy 17K",
    "sg:city":"Newburgh",
    "sg:classifiers":[
        {
            "category":"Retail",
            "subcategory":"Auto Rental",
            "type":"Services"
        }
    ],
    "sg:phone":"+1 845 778 7201",
    "sg:postcode":"12550",
    "sg:province":"NY",
    "sg:tags":[
        "renting",
        "truck",
        "leasing"
    ],
    "wof:name":"Hertz Penske Truck Rental",
    "wof:placetype":"venue"
},
  "geometry": {"coordinates":[-74.09505299999999,41.510878],"type":"Point"}
}