{
  "type": "Feature",
  "properties": {
    "addr:full":"2918 Westchester Ave Bronx NY 10461",
    "addr:housenumber":"2918",
    "addr:postcode":"10461",
    "addr:street":"Westchester Ave",
    "iso:country":"US",
    "sg:address":"2918 Westchester Ave",
    "sg:city":"Bronx",
    "sg:classifiers":[
        {
            "category":"Building & Trades",
            "subcategory":"Pest Control",
            "type":"Services"
        }
    ],
    "sg:phone":"+1 718 931 0453",
    "sg:postcode":"10461",
    "sg:province":"NY",
    "wof:name":"El Toro Exterminator",
    "wof:placetype":"venue"
},
  "geometry": {"coordinates":[-73.833062,40.846185],"type":"Point"}
}