{
  "type": "Feature",
  "properties": {
    "addr:full":"136 Wyckoff Ave Brooklyn NY 11237",
    "addr:housenumber":"136",
    "addr:postcode":"11237",
    "addr:street":"Wyckoff Ave",
    "iso:country":"US",
    "sg:address":"136 Wyckoff Ave",
    "sg:city":"Brooklyn",
    "sg:classifiers":[
        {
            "category":"Insurance",
            "subcategory":"Hazard Insurance",
            "type":"Services"
        }
    ],
    "sg:phone":"+1 718 386 6800",
    "sg:postcode":"11237",
    "sg:province":"NY",
    "sg:website":"online2.statefarm.com/b2c/sf/age...",
    "wof:name":"Olivia Triana - State Farm",
    "wof:placetype":"venue"
},
  "geometry": {"coordinates":[-73.917602,40.703],"type":"Point"}
}