{
  "type": "Feature",
  "properties": {
    "addr:full":"35 E 38th Street New York NY 10016",
    "addr:housenumber":"35",
    "addr:postcode":"10016",
    "addr:street":"E 38Th Street",
    "iso:country":"US",
    "sg:address":"35 E 38th Street",
    "sg:city":"New York",
    "sg:classifiers":[
        {
            "category":"Health Services",
            "subcategory":"Dentist",
            "type":"Services"
        }
    ],
    "sg:phone":"+1 212 682 2060",
    "sg:postcode":"10016",
    "sg:province":"NY",
    "sg:website":"www.drshmuely.com",
    "wof:name":"Gaster Bert D DDS",
    "wof:placetype":"venue"
},
  "geometry": {"coordinates":[-73.980469,40.750027],"type":"Point"}
}