{
  "type": "Feature",
  "properties": {
    "addr:full":"17636 Sunbury Rd Jamaica NY 11434",
    "addr:housenumber":"17636",
    "addr:postcode":"11434",
    "addr:street":"Sunbury Rd",
    "iso:country":"US",
    "sg:address":"17636 Sunbury Rd",
    "sg:city":"Jamaica",
    "sg:classifiers":[
        {
            "category":"Organizations",
            "subcategory":"Community Association",
            "type":"Services"
        }
    ],
    "sg:phone":"+1 718 527 0014",
    "sg:postcode":"11434",
    "sg:province":"NY",
    "wof:name":"Rainbow Association Inc",
    "wof:placetype":"venue"
},
  "geometry": {"coordinates":[-73.76856600000001,40.683142],"type":"Point"}
}