{
  "type": "Feature",
  "properties": {
    "iso:country":"US",
    "sg:address":"2704 Parsons Boulevard",
    "sg:city":"Flushing",
    "sg:classifiers":[
        {
            "category":"Health Services",
            "subcategory":"Doctor",
            "type":"Services"
        }
    ],
    "sg:phone":"+1 718 321 9090",
    "sg:postcode":"11354",
    "sg:province":"NY",
    "wof:name":"Lee Stephen MD",
    "wof:placetype":"venue"
},
  "geometry": {"coordinates":[-73.824724,40.773738],"type":"Point"}
}