{
  "type": "Feature",
  "properties": {
    "addr:full":"4050 Park Ave Bronx NY 10457",
    "addr:housenumber":"4050",
    "addr:postcode":"10457",
    "addr:street":"Park Ave",
    "iso:country":"US",
    "sg:address":"4050 Park Ave",
    "sg:city":"Bronx",
    "sg:classifiers":[
        {
            "category":"Retail",
            "subcategory":"Auto Repair",
            "type":"Services"
        }
    ],
    "sg:phone":"+1 718 731 6666",
    "sg:postcode":"10457",
    "sg:province":"NY",
    "sg:tags":[
        "wrecker"
    ],
    "wof:name":"Ant's Towing",
    "wof:placetype":"venue"
},
  "geometry": {"coordinates":[-73.90111400000001,40.843841],"type":"Point"}
}