{
  "type": "Feature",
  "properties": {
    "addr:full":"142 Lexington Ave Oyster Bay NY 11771",
    "addr:housenumber":"142",
    "addr:postcode":"11771",
    "addr:street":"Lexington Ave",
    "iso:country":"US",
    "sg:address":"142 Lexington Ave",
    "sg:city":"Oyster Bay",
    "sg:classifiers":[
        {
            "category":"Health Services",
            "subcategory":"Health Practitioner",
            "type":"Services"
        }
    ],
    "sg:phone":"+1 516 628 1090",
    "sg:postcode":"11771",
    "sg:province":"NY",
    "sg:tags":[
        "pathologist",
        "speech"
    ],
    "sg:website":"www.nyspeechconsultants.com",
    "wof:name":"New York Speech Consultants",
    "wof:placetype":"venue"
},
  "geometry": {"coordinates":[-73.53424099999999,40.868016],"type":"Point"}
}