{
  "type": "Feature",
  "properties": {
    "addr:full":"510 5th Ave Brooklyn NY 11215",
    "addr:housenumber":"510",
    "addr:postcode":"11215",
    "addr:street":"5Th Ave",
    "iso:country":"US",
    "sg:address":"510 5th Ave",
    "sg:city":"Brooklyn",
    "sg:classifiers":[
        {
            "category":"Shopping",
            "type":"Retail Goods"
        }
    ],
    "sg:phone":"+1 718 369 1786",
    "sg:postcode":"11215",
    "sg:province":"NY",
    "sg:tags":[
        "pet",
        "shop",
        "store"
    ],
    "sg:website":"www.petlanddiscounts.com/",
    "wof:name":"Petland Discounts",
    "wof:placetype":"venue"
},
  "geometry": {"coordinates":[-73.988297,40.667],"type":"Point"}
}