{
  "type": "Feature",
  "properties": {
    "iso:country":"US",
    "sg:address":"1020 Northern Blvd",
    "sg:city":"Roslyn",
    "sg:classifiers":[
        {
            "category":"Autos & Motor Vehicles",
            "subcategory":"Fuel & Gas Station",
            "type":"Retail Goods"
        }
    ],
    "sg:phone":"+1 516 621 7035",
    "sg:postcode":"11576",
    "sg:province":"NY",
    "sg:tags":[
        "oil"
    ],
    "wof:name":"BP",
    "wof:placetype":"venue"
},
  "geometry": {"coordinates":[-73.664839,40.797971],"type":"Point"}
}