{
  "type": "Feature",
  "properties": {
    "iso:country":"US",
    "sg:address":"282 Phelps Ln",
    "sg:city":"North Babylon",
    "sg:classifiers":[
        {
            "category":"Manufacturing",
            "subcategory":"Toys & Sporting Goods",
            "type":"Manufacturing & Wholesale Goods"
        }
    ],
    "sg:phone":"+1   ",
    "sg:postcode":"11703",
    "sg:province":"NY",
    "sg:tags":[
        "mfg"
    ],
    "wof:name":"Michelle Mulhall",
    "wof:placetype":"venue"
},
  "geometry": {"coordinates":[-73.33319899999999,40.727072],"type":"Point"}
}