{
  "type": "Feature",
  "properties": {
    "iso:country":"US",
    "sg:address":"6 Roxbury St",
    "sg:city":"Farmingdale",
    "sg:classifiers":[
        {
            "category":"Real Estate",
            "subcategory":"Real Estate Agent",
            "type":"Services"
        }
    ],
    "sg:phone":"+1 516 847 0514",
    "sg:postcode":"11735",
    "sg:province":"NY",
    "wof:name":"Elegant Realty Group Inc",
    "wof:placetype":"venue"
},
  "geometry": {"coordinates":[-73.45866599999999,40.734711],"type":"Point"}
}