{
  "type": "Feature",
  "properties": {
    "iso:country":"US",
    "sg:address":"46 W 28 St",
    "sg:city":"New York",
    "sg:classifiers":[
        {
            "category":"Wholesale",
            "subcategory":"Sporting Goods",
            "type":"Manufacturing & Wholesale Goods"
        }
    ],
    "sg:phone":"+1 212 679 8207",
    "sg:postcode":"10001",
    "sg:province":"NY",
    "wof:name":"Glk Trading",
    "wof:placetype":"venue"
},
  "geometry": {"coordinates":[-73.99010199999999,40.745722],"type":"Point"}
}