{
  "type": "Feature",
  "properties": {
    "iso:country":"US",
    "sg:address":"1225 Park Ln",
    "sg:city":"Yorktown Heights",
    "sg:classifiers":[
        {
            "category":"Real Estate",
            "subcategory":"Real Estate Agent",
            "type":"Services"
        }
    ],
    "sg:phone":"+1 914 245 0729",
    "sg:postcode":"10598",
    "sg:province":"NY",
    "wof:name":"Dove Realty Corp",
    "wof:placetype":"venue"
},
  "geometry": {"coordinates":[-73.824715,41.286039],"type":"Point"}
}