{
  "type": "Feature",
  "properties": {
    "iso:country":"US",
    "sg:address":"2722 W Main St",
    "sg:city":"Wappingers Falls",
    "sg:classifiers":[
        {
            "category":"Personal",
            "subcategory":"Barber",
            "type":"Services"
        },
        {
            "category":"Personal",
            "subcategory":"Nail Salon",
            "type":"Services"
        }
    ],
    "sg:phone":"+1 845 296 0230",
    "sg:postcode":"12590",
    "sg:province":"NY",
    "wof:name":"Arianna's Salon",
    "wof:placetype":"venue"
},
  "geometry": {"coordinates":[-73.921204,41.603001],"type":"Point"}
}