{
  "type": "Feature",
  "properties": {
    "addr:full":"80 Clinton St Hempstead NY 11550",
    "addr:housenumber":"80",
    "addr:postcode":"11550",
    "addr:street":"Clinton St",
    "iso:country":"US",
    "sg:address":"80 Clinton St",
    "sg:city":"Hempstead",
    "sg:classifiers":[
        {
            "category":"Travel",
            "subcategory":"Hotels & Motels",
            "type":"Entertainment"
        }
    ],
    "sg:phone":"+1 516 486 4100",
    "sg:postcode":"11550",
    "sg:province":"NY",
    "sg:tags":[
        "lodging"
    ],
    "wof:name":"Quality Hotel",
    "wof:placetype":"venue"
},
  "geometry": {"coordinates":[-73.619043,40.707925],"type":"Point"}
}