{
  "type": "Feature",
  "properties": {
    "addr:full":"514 4th Avenue Brooklyn NY 11226",
    "addr:housenumber":"514",
    "addr:postcode":"11226",
    "addr:street":"4Th Avenue",
    "iso:country":"US",
    "sg:address":"514 4th Avenue",
    "sg:city":"Brooklyn",
    "sg:classifiers":[
        {
            "category":"Deli",
            "type":"Food & Drink"
        },
        {
            "category":"Food & Beverages",
            "subcategory":"Groceries & Convenience Stores",
            "type":"Retail Goods"
        }
    ],
    "sg:phone":"+1 718 768 6310",
    "sg:postcode":"11226",
    "sg:province":"NY",
    "wof:name":"Tony's Superior Market",
    "wof:placetype":"venue"
},
  "geometry": {"coordinates":[-73.990818,40.667943],"type":"Point"}
}