{
  "type": "Feature",
  "properties": {
    "iso:country":"US",
    "sg:address":"373 Lexington Ave",
    "sg:city":"New York",
    "sg:classifiers":[
        {
            "category":"Retail",
            "subcategory":"Repair Shop",
            "type":"Services"
        }
    ],
    "sg:phone":"+1 646 509 2861",
    "sg:postcode":"10017",
    "sg:province":"NY",
    "sg:tags":[
        "lock",
        "locksmith"
    ],
    "wof:name":"24 Hr Emerg A Locksmith",
    "wof:placetype":"venue"
},
  "geometry": {"coordinates":[-73.976986,40.750157],"type":"Point"}
}