{
  "type": "Feature",
  "properties": {
    "addr:full":"7561 Sugarwood Ln Syracuse NY 13212",
    "addr:housenumber":"7561",
    "addr:postcode":"13212",
    "addr:street":"Sugarwood Ln",
    "iso:country":"US",
    "sg:address":"7561 Sugarwood Ln",
    "sg:city":"Syracuse",
    "sg:classifiers":[
        {
            "category":"Organizations",
            "subcategory":"Membership Organization",
            "type":"Services"
        }
    ],
    "sg:phone":"+1   ",
    "sg:postcode":"13212",
    "sg:province":"NY",
    "wof:name":"Lourdes N Amercn Volunteers",
    "wof:placetype":"venue"
},
  "geometry": {"coordinates":[-76.16842800000001,43.131506],"type":"Point"}
}