{
  "type": "Feature",
  "properties": {
    "addr:full":"626 Middle Country Rd Selden NY 11784",
    "addr:housenumber":"626",
    "addr:postcode":"11784",
    "addr:street":"Middle Country Rd",
    "iso:country":"US",
    "sg:address":"626 Middle Country Rd",
    "sg:city":"Selden",
    "sg:classifiers":[
        {
            "category":"Restaurant",
            "type":"Food & Drink"
        }
    ],
    "sg:phone":"+1   ",
    "sg:postcode":"11784",
    "sg:province":"NY",
    "sg:tags":[
        "eating"
    ],
    "wof:name":"Pudgies Famous Chicken",
    "wof:placetype":"venue"
},
  "geometry": {"coordinates":[-73.03386399999999,40.866636],"type":"Point"}
}