{
  "type": "Feature",
  "properties": {
    "iso:country":"US",
    "sg:address":"115 E 23 St",
    "sg:city":"New York",
    "sg:classifiers":[
        {
            "category":"Manufacturing",
            "subcategory":"Tools & Machinery",
            "type":"Manufacturing & Wholesale Goods"
        }
    ],
    "sg:phone":"+1   ",
    "sg:postcode":"10010",
    "sg:province":"NY",
    "sg:tags":[
        "mfg",
        "ophthalmic"
    ],
    "wof:name":"Eyeweb Inc",
    "wof:placetype":"venue"
},
  "geometry": {"coordinates":[-73.985248,40.739869],"type":"Point"}
}