{
  "type": "Feature",
  "properties": {
    "addr:full":"6 Bond St Great Neck NY 11021",
    "addr:housenumber":"6",
    "addr:postcode":"11021",
    "addr:street":"Bond St",
    "iso:country":"US",
    "sg:address":"6 Bond St",
    "sg:city":"Great Neck",
    "sg:classifiers":[
        {
            "category":"Restaurant",
            "type":"Food & Drink"
        },
        {
            "category":"Ice Cream",
            "type":"Food & Drink"
        }
    ],
    "sg:menulink":"http://www.allmenus.com/ny/great-neck/232660-haagen-dazs/menu/",
    "sg:phone":"+1 516 487 4448",
    "sg:postcode":"11021",
    "sg:province":"NY",
    "sg:tags":[
        "american",
        "ice",
        "cream"
    ],
    "wof:name":"Haagen Dazs",
    "wof:placetype":"venue"
},
  "geometry": {"coordinates":[-73.727341,40.787882],"type":"Point"}
}