{
  "type": "Feature",
  "properties": {
    "iso:country":"US",
    "sg:address":"4622 14th Avenue",
    "sg:city":"Brooklyn",
    "sg:classifiers":[
        {
            "category":"Education",
            "subcategory":"Preschool",
            "type":"Public Place"
        },
        {
            "category":"Education",
            "subcategory":"School",
            "type":"Public Place"
        }
    ],
    "sg:phone":"+1 718 871 0859",
    "sg:postcode":"11219",
    "sg:province":"NY",
    "sg:tags":[
        "elementary"
    ],
    "wof:name":"Tomer Dvorah Dskwere Pre School",
    "wof:placetype":"venue"
},
  "geometry": {"coordinates":[-73.98838000000001,40.635353],"type":"Point"}
}