{
  "type": "Feature",
  "properties": {
    "iso:country":"US",
    "sg:address":"2 Rector St",
    "sg:city":"New York",
    "sg:classifiers":[
        {
            "category":"Shopping",
            "subcategory":"Computers & Home Electronics",
            "type":"Retail Goods"
        }
    ],
    "sg:phone":"+1 212 406 0760",
    "sg:postcode":"10006",
    "sg:province":"NY",
    "wof:name":"National Interfaith Cable",
    "wof:placetype":"venue"
},
  "geometry": {"coordinates":[-74.186431,40.70756],"type":"Point"}
}