{
  "type": "Feature",
  "properties": {
    "iso:country":"US",
    "sg:address":"236 Kane St",
    "sg:city":"Brooklyn",
    "sg:classifiers":[
        {
            "category":"Organizations",
            "subcategory":"Religious Organization",
            "type":"Services"
        }
    ],
    "sg:phone":"+1 718 875 1550",
    "sg:postcode":"11231",
    "sg:province":"NY",
    "sg:tags":[
        "synagogue"
    ],
    "sg:website":"www.kanestreet.org",
    "wof:name":"Kane Street Synagogue",
    "wof:placetype":"venue"
},
  "geometry": {"coordinates":[-73.99524,40.685727],"type":"Point"}
}