{
  "type": "Feature",
  "properties": {
    "addr:full":"7 Kings Dr Old Westbury NY 11568",
    "addr:housenumber":"7",
    "addr:postcode":"11568",
    "addr:street":"Kings Dr Old",
    "iso:country":"US",
    "sg:address":"7 Kings Dr",
    "sg:city":"Old Westbury",
    "sg:classifiers":[
        {
            "category":"Health Services",
            "subcategory":"Optometrist",
            "type":"Services"
        }
    ],
    "sg:phone":"+1 516 626 1228",
    "sg:postcode":"11568",
    "sg:province":"NY",
    "wof:name":"Garber Jerome Martin OD",
    "wof:placetype":"venue"
},
  "geometry": {"coordinates":[-73.61460099999999,40.788601],"type":"Point"}
}