{
  "type": "Feature",
  "properties": {
    "addr:full":"53 Chenango St Binghamton NY 13901",
    "addr:housenumber":"53",
    "addr:postcode":"13901",
    "addr:street":"Chenango St",
    "iso:country":"US",
    "sg:address":"53 Chenango St",
    "sg:city":"Binghamton",
    "sg:classifiers":[
        {
            "category":"Insurance",
            "subcategory":"Insurance Agent",
            "type":"Services"
        }
    ],
    "sg:phone":"+1 607 723 6488",
    "sg:postcode":"13901",
    "sg:province":"NY",
    "sg:website":"www.excellusbcbs.com",
    "wof:name":"Blue Cross & Blue Shield",
    "wof:placetype":"venue"
},
  "geometry": {"coordinates":[-75.91023300000001,42.10057],"type":"Point"}
}