{
  "type": "Feature",
  "properties": {
    "addr:full":"365 Strawtown Rd New City NY 10956",
    "addr:housenumber":"365",
    "addr:postcode":"10956",
    "addr:street":"Strawtown Rd",
    "iso:country":"US",
    "sg:address":"365 Strawtown Rd",
    "sg:city":"New City",
    "sg:classifiers":[
        {
            "category":"Organizations",
            "subcategory":"Religious Organization",
            "type":"Services"
        }
    ],
    "sg:phone":"+1   ",
    "sg:postcode":"10956",
    "sg:province":"NY",
    "wof:name":"St John Episcopal Church",
    "wof:placetype":"venue"
},
  "geometry": {"coordinates":[-73.969449,41.126211],"type":"Point"}
}