{
  "type": "Feature",
  "properties": {
    "addr:full":"53 Prospect Rd Centerport NY 11721",
    "addr:housenumber":"53",
    "addr:postcode":"11721",
    "addr:street":"Prospect Rd",
    "iso:country":"US",
    "sg:address":"53 Prospect Rd",
    "sg:city":"Centerport",
    "sg:classifiers":[
        {
            "category":"Organizations",
            "subcategory":"Religious Organization",
            "type":"Services"
        }
    ],
    "sg:phone":"+1 631 757 8184",
    "sg:postcode":"11721",
    "sg:province":"NY",
    "sg:tags":[
        "church"
    ],
    "sg:website":"www.olqmparish.org",
    "wof:name":"Our Lady Queen-Martyrs Church",
    "wof:placetype":"venue"
},
  "geometry": {"coordinates":[-73.36933399999999,40.890712],"type":"Point"}
}