{
  "type": "Feature",
  "properties": {
    "iso:country":"US",
    "sg:address":"1000 Turk Hill Rd",
    "sg:city":"Fairport",
    "sg:classifiers":[
        {
            "category":"Professional",
            "subcategory":"Art Services",
            "type":"Services"
        }
    ],
    "sg:phone":"+1 585 703 3374",
    "sg:postcode":"14450",
    "sg:province":"NY",
    "sg:tags":[
        "photographer"
    ],
    "wof:name":"Burnham Studios & Photography",
    "wof:placetype":"venue"
},
  "geometry": {"coordinates":[-77.43214500000001,43.096073],"type":"Point"}
}