{
  "type": "Feature",
  "properties": {
    "iso:country":"US",
    "sg:address":"205 W Henley St",
    "sg:city":"Olean",
    "sg:classifiers":[
        {
            "category":"Education",
            "subcategory":"School",
            "type":"Public Place"
        }
    ],
    "sg:phone":"+1 716 373 1855",
    "sg:postcode":"14760",
    "sg:province":"NY",
    "wof:name":"St Mary's Religious Education",
    "wof:placetype":"venue"
},
  "geometry": {"coordinates":[-78.431439,42.075456],"type":"Point"}
}