{
  "type": "Feature",
  "properties": {
    "addr:full":"535 E 5 St New York NY 10009",
    "addr:housenumber":"535;5",
    "addr:postcode":"10009",
    "addr:street":"E;St",
    "iso:country":"US",
    "sg:address":"535 E 5 St",
    "sg:city":"New York",
    "sg:classifiers":[
        {
            "category":"Wholesale",
            "subcategory":"Groceries",
            "type":"Manufacturing & Wholesale Goods"
        }
    ],
    "sg:phone":"+1 212 475 8048",
    "sg:postcode":"10009",
    "sg:province":"NY",
    "sg:tags":[
        "general"
    ],
    "wof:name":"61 First Ave Food Corp",
    "wof:placetype":"venue"
},
  "geometry": {"coordinates":[-73.982373,40.724128],"type":"Point"}
}