{
  "type": "Feature",
  "properties": {
    "addr:full":"320 E 43rd St New York NY 10017",
    "addr:housenumber":"320",
    "addr:postcode":"10017",
    "addr:street":"E 43Rd St",
    "iso:country":"US",
    "sg:address":"320 E 43rd St",
    "sg:city":"New York",
    "sg:classifiers":[
        {
            "category":"Education",
            "subcategory":"Library",
            "type":"Public Place"
        },
        {
            "category":"Banks & Credit Unions",
            "subcategory":"Financial Services",
            "type":"Services"
        }
    ],
    "sg:phone":"+1 212 983 6234",
    "sg:postcode":"10017",
    "sg:province":"NY",
    "sg:tags":[
        "management",
        "business",
        "association",
        "interest",
        "nonprofit",
        "trust",
        "special"
    ],
    "sg:website":"www.fordfound.org",
    "wof:name":"Ford Foundation",
    "wof:placetype":"venue"
},
  "geometry": {"coordinates":[-73.97054,40.749992],"type":"Point"}
}