{
  "type": "Feature",
  "properties": {
    "addr:full":"319 Vliet Blvd Cohoes NY 12047",
    "addr:housenumber":"319",
    "addr:postcode":"12047",
    "addr:street":"Vliet Blvd",
    "iso:country":"US",
    "sg:address":"319 Vliet Blvd",
    "sg:city":"Cohoes",
    "sg:classifiers":[
        {
            "category":"Government",
            "subcategory":"Office",
            "type":"Public Place"
        }
    ],
    "sg:phone":"+1 518 237 4320",
    "sg:postcode":"12047",
    "sg:province":"NY",
    "sg:tags":[
        "village"
    ],
    "wof:name":"Cohoes Filtration Plant",
    "wof:placetype":"venue"
},
  "geometry": {"coordinates":[-73.72298000000001,42.779184],"type":"Point"}
}