{
  "type": "Feature",
  "properties": {
    "iso:country":"US",
    "sg:address":"4 Heath Ct",
    "sg:city":"Schenectady",
    "sg:classifiers":[
        {
            "category":"Professional",
            "subcategory":"Advertising",
            "type":"Services"
        }
    ],
    "sg:phone":"+1 518 452 5400",
    "sg:postcode":"12309",
    "sg:province":"NY",
    "sg:tags":[
        "agency"
    ],
    "wof:name":"Marino Advertising & Media Svc",
    "wof:placetype":"venue"
},
  "geometry": {"coordinates":[-73.845889,42.750509],"type":"Point"}
}