{
  "type": "Feature",
  "properties": {
    "addr:full":"1005 W Fayette St Syracuse NY 13202",
    "addr:housenumber":"1005",
    "addr:postcode":"13202",
    "addr:street":"W Fayette St",
    "iso:country":"US",
    "sg:address":"1005 W Fayette St",
    "sg:city":"Syracuse",
    "sg:classifiers":[
        {
            "category":"Professional",
            "subcategory":"Testing Lab",
            "type":"Services"
        }
    ],
    "sg:phone":"+1 315 425 1151",
    "sg:postcode":"13202",
    "sg:province":"NY",
    "sg:tags":[
        "calibration"
    ],
    "sg:website":"www.woodsvalleyskiteam.org",
    "wof:name":"Cal Source",
    "wof:placetype":"venue"
},
  "geometry": {"coordinates":[-76.169304,43.046206],"type":"Point"}
}