{
  "type": "Feature",
  "properties": {
    "addr:full":"1520 Ridge Rd W Rochester NY 14420",
    "addr:housenumber":"1520",
    "addr:postcode":"14420",
    "addr:street":"Ridge Rd W",
    "iso:country":"US",
    "sg:address":"1520 Ridge Rd W",
    "sg:city":"Rochester",
    "sg:classifiers":[
        {
            "category":"Personal",
            "type":"Services"
        }
    ],
    "sg:phone":"+1 585 581 0270",
    "sg:postcode":"14420",
    "sg:province":"NY",
    "sg:tags":[
        "wear",
        "formal"
    ],
    "sg:website":"www.tuxedopark.com",
    "wof:name":"Tuxedo Park",
    "wof:placetype":"venue"
},
  "geometry": {"coordinates":[-77.666995,43.205328],"type":"Point"}
}