{
  "type": "Feature",
  "properties": {
    "iso:country":"US",
    "sg:address":"947 Old Country Rd",
    "sg:city":"Westbury",
    "sg:classifiers":[
        {
            "category":"Banks & Credit Unions",
            "subcategory":"Bank",
            "type":"Services"
        }
    ],
    "sg:phone":"+1 516 997 6400",
    "sg:postcode":"11590",
    "sg:province":"NY",
    "wof:name":"North Fork Bank",
    "wof:placetype":"venue"
},
  "geometry": {"coordinates":[-73.56092099999999,40.754269],"type":"Point"}
}