{
  "type": "Feature",
  "properties": {
    "iso:country":"US",
    "sg:address":"158 W 27th Street",
    "sg:city":"New York",
    "sg:classifiers":[
        {
            "category":"Retail",
            "subcategory":"Portrait Studio",
            "type":"Services"
        },
        {
            "category":"Professional",
            "subcategory":"Art Services",
            "type":"Services"
        }
    ],
    "sg:phone":"+1 212 229 0069",
    "sg:postcode":"10001",
    "sg:province":"NY",
    "sg:tags":[
        "photographer",
        "photography",
        "store"
    ],
    "sg:website":"www.jahse.com",
    "wof:name":"Jahse Photography",
    "wof:placetype":"venue"
},
  "geometry": {"coordinates":[-73.99279199999999,40.746132],"type":"Point"}
}