{
  "type": "Feature",
  "properties": {
    "iso:country":"US",
    "sg:address":"359 2nd Ave",
    "sg:city":"New York",
    "sg:classifiers":[
        {
            "category":"Health Services",
            "subcategory":"Doctor",
            "type":"Services"
        }
    ],
    "sg:phone":"+1 212 475 2535",
    "sg:postcode":"10010",
    "sg:province":"NY",
    "wof:name":"Laufer Ira J",
    "wof:placetype":"venue"
},
  "geometry": {"coordinates":[-73.98215500000001,40.736578],"type":"Point"}
}