{
  "type": "Feature",
  "properties": {
    "iso:country":"US",
    "sg:address":"585 Fire Island Ave",
    "sg:city":"Babylon",
    "sg:classifiers":[
        {
            "category":"Shopping",
            "subcategory":"Computers & Home Electronics",
            "type":"Retail Goods"
        }
    ],
    "sg:phone":"+1 631 321 4481",
    "sg:postcode":"11702",
    "sg:province":"NY",
    "sg:tags":[
        "audio"
    ],
    "wof:name":"J B Audio Video Corp",
    "wof:placetype":"venue"
},
  "geometry": {"coordinates":[-73.316709,40.685665],"type":"Point"}
}