{
  "type": "Feature",
  "properties": {
    "iso:country":"US",
    "sg:address":"18 Pocatello Rd",
    "sg:city":"Middletown",
    "sg:classifiers":[
        {
            "category":"Home & Garden",
            "subcategory":"Home Furnishings",
            "type":"Retail Goods"
        }
    ],
    "sg:phone":"+1 845 344 3063",
    "sg:postcode":"10940",
    "sg:province":"NY",
    "sg:tags":[
        "fixture",
        "lighting"
    ],
    "wof:name":"La Forge Karen",
    "wof:placetype":"venue"
},
  "geometry": {"coordinates":[-74.453301,41.441661],"type":"Point"}
}