{
  "type": "Feature",
  "properties": {
    "addr:full":"4515 Ave D Brooklyn NY 11203",
    "addr:housenumber":"4515",
    "addr:postcode":"11203",
    "addr:street":"Ave D",
    "iso:country":"US",
    "sg:address":"4515 Ave D",
    "sg:city":"Brooklyn",
    "sg:classifiers":[
        {
            "category":"Government",
            "subcategory":"Office",
            "type":"Public Place"
        }
    ],
    "sg:phone":"+1 718 629 6401",
    "sg:postcode":"11203",
    "sg:province":"NY",
    "wof:name":"Senator Kevin S Parker",
    "wof:placetype":"venue"
},
  "geometry": {"coordinates":[-73.933341,40.641962],"type":"Point"}
}