{
  "type": "Feature",
  "properties": {
    "iso:country":"US",
    "sg:address":"812 Revere Ave",
    "sg:city":"Bronx",
    "sg:classifiers":[
        {
            "category":"Building & Trades",
            "subcategory":"Construction",
            "type":"Services"
        }
    ],
    "sg:phone":"+1 718 863 3657",
    "sg:postcode":"10465",
    "sg:province":"NY",
    "sg:tags":[
        "contractor"
    ],
    "wof:name":"Roland Morlocck",
    "wof:placetype":"venue"
},
  "geometry": {"coordinates":[-73.826004,40.829034],"type":"Point"}
}