{
  "type": "Feature",
  "properties": {
    "iso:country":"US",
    "sg:address":"440 E 63rd Street",
    "sg:city":"New York",
    "sg:classifiers":[
        {
            "category":"Health Services",
            "subcategory":"Doctor",
            "type":"Services"
        }
    ],
    "sg:phone":"+1 212 752 3464",
    "sg:postcode":"10021",
    "sg:province":"NY",
    "wof:name":"Magid Norman",
    "wof:placetype":"venue"
},
  "geometry": {"coordinates":[-73.958991,40.761483],"type":"Point"}
}