{
  "type": "Feature",
  "properties": {
    "addr:full":"82 Christopher St New York NY 10014",
    "addr:housenumber":"82",
    "addr:postcode":"10014",
    "addr:street":"Christopher St",
    "iso:country":"US",
    "sg:address":"82 Christopher St",
    "sg:city":"New York",
    "sg:classifiers":[
        {
            "category":"Real Estate",
            "subcategory":"Real Estate Agent",
            "type":"Services"
        }
    ],
    "sg:phone":"+1 212 337 3173",
    "sg:postcode":"10014",
    "sg:province":"NY",
    "sg:tags":[
        "management"
    ],
    "wof:name":"BSC Property Management",
    "wof:placetype":"venue"
},
  "geometry": {"coordinates":[-74.00348,40.733475],"type":"Point"}
}