{
  "type": "Feature",
  "properties": {
    "iso:country":"US",
    "sg:address":"615 Merrick Ave",
    "sg:city":"Westbury",
    "sg:classifiers":[
        {
            "category":"Banks & Credit Unions",
            "subcategory":"Bank",
            "type":"Services"
        }
    ],
    "sg:phone":"+1 516 683 4100",
    "sg:postcode":"11590",
    "sg:province":"NY",
    "wof:name":"Columbia Federal Savings Bank",
    "wof:placetype":"venue"
},
  "geometry": {"coordinates":[-73.584,40.738899],"type":"Point"}
}