{
  "type": "Feature",
  "properties": {
    "addr:full":"27 Oregon Dr Huntington Station NY 11746",
    "addr:housenumber":"27",
    "addr:postcode":"11746",
    "addr:street":"Oregon Dr",
    "iso:country":"US",
    "sg:address":"27 Oregon Dr",
    "sg:city":"Huntington Station",
    "sg:classifiers":[
        {
            "category":"Real Estate",
            "subcategory":"Architect",
            "type":"Services"
        }
    ],
    "sg:phone":"+1   ",
    "sg:postcode":"11746",
    "sg:province":"NY",
    "sg:tags":[
        "architectural"
    ],
    "wof:name":"Frondozo Architecture LLC",
    "wof:placetype":"venue"
},
  "geometry": {"coordinates":[-73.39407199999999,40.843502],"type":"Point"}
}