{
  "type": "Feature",
  "properties": {
    "iso:country":"US",
    "sg:address":"462 Hopi Ct",
    "sg:city":"Suffern",
    "sg:classifiers":[
        {
            "category":"Wholesale",
            "subcategory":"Durable Goods & Equipment",
            "type":"Manufacturing & Wholesale Goods"
        }
    ],
    "sg:phone":"+1 845 357 1440",
    "sg:postcode":"10901",
    "sg:province":"NY",
    "sg:tags":[
        "dry",
        "goods-wholesale"
    ],
    "wof:name":"Natures Supplmnt Br",
    "wof:placetype":"venue"
},
  "geometry": {"coordinates":[-74.13239900000001,41.123259],"type":"Point"}
}