{
  "type": "Feature",
  "properties": {
    "addr:full":"570 Fulton St Brooklyn NY 11217",
    "addr:housenumber":"570",
    "addr:postcode":"11217",
    "addr:street":"Fulton St",
    "iso:country":"US",
    "sg:address":"570 Fulton St",
    "sg:city":"Brooklyn",
    "sg:classifiers":[
        {
            "category":"Professional",
            "subcategory":"Testing Lab",
            "type":"Services"
        },
        {
            "category":"Health Services",
            "subcategory":"Medical Lab",
            "type":"Services"
        }
    ],
    "sg:phone":"+1 718 403 9126",
    "sg:postcode":"11217",
    "sg:province":"NY",
    "sg:tags":[
        "analytical",
        "laboratory"
    ],
    "wof:name":"Bio Reference",
    "wof:placetype":"venue"
},
  "geometry": {"coordinates":[-73.979512,40.688321],"type":"Point"}
}