{
  "type": "Feature",
  "properties": {
    "addr:full":"504 Old Rte 32 Highland Mills NY 10953",
    "addr:housenumber":"504",
    "addr:postcode":"10953",
    "addr:street":"Old Rte 32;Mills",
    "iso:country":"US",
    "sg:address":"504 Old Rte 32",
    "sg:city":"Highland Mills",
    "sg:classifiers":[
        {
            "category":"Bars & Pubs",
            "type":"Food & Drink"
        }
    ],
    "sg:phone":"+1 845 928 9802",
    "sg:postcode":"10953",
    "sg:province":"NY",
    "wof:name":"Murray's Irish House",
    "wof:placetype":"venue"
},
  "geometry": {"coordinates":[-74.07980000000001,41.397414],"type":"Point"}
}