{
  "type": "Feature",
  "properties": {
    "iso:country":"US",
    "sg:address":"415 N Lake St",
    "sg:city":"Oneida",
    "sg:classifiers":[
        {
            "category":"Health Services",
            "subcategory":"Doctor",
            "type":"Services"
        }
    ],
    "sg:phone":"+1   ",
    "sg:postcode":"13421",
    "sg:province":"NY",
    "wof:name":"Linda Boehm",
    "wof:placetype":"venue"
},
  "geometry": {"coordinates":[-75.653187,43.105282],"type":"Point"}
}