{
  "type": "Feature",
  "properties": {
    "iso:country":"US",
    "sg:address":"103 Ralph Ave",
    "sg:city":"Brooklyn",
    "sg:classifiers":[
        {
            "category":"Personal",
            "subcategory":"Beauty Salon",
            "type":"Services"
        }
    ],
    "sg:phone":"+1 718 452 9591",
    "sg:postcode":"11221",
    "sg:province":"NY",
    "wof:name":"Newkirk's Beauty Salon",
    "wof:placetype":"venue"
},
  "geometry": {"coordinates":[-73.92340799999999,40.686925],"type":"Point"}
}