{
  "type": "Feature",
  "properties": {
    "addr:full":"110 W 40 St New York NY 10018",
    "addr:housenumber":"110",
    "addr:postcode":"10018",
    "addr:street":"W 40 St",
    "iso:country":"US",
    "sg:address":"110 W 40 St",
    "sg:city":"New York",
    "sg:classifiers":[
        {
            "category":"Shopping",
            "subcategory":"Crafts & Fabrics",
            "type":"Retail Goods"
        }
    ],
    "sg:phone":"+1 646 366 1950",
    "sg:postcode":"10018",
    "sg:province":"NY",
    "sg:tags":[
        "shop"
    ],
    "wof:name":"Michael Mason & Co",
    "wof:placetype":"venue"
},
  "geometry": {"coordinates":[-73.98649500000001,40.754028],"type":"Point"}
}