{
  "type": "Feature",
  "properties": {
    "addr:full":"2000 Monroe Ave Rochester NY 14618",
    "addr:housenumber":"2000",
    "addr:postcode":"14618",
    "addr:street":"Monroe Ave",
    "iso:country":"US",
    "sg:address":"2000 Monroe Ave",
    "sg:city":"Rochester",
    "sg:classifiers":[
        {
            "category":"Banks & Credit Unions",
            "subcategory":"Bank",
            "type":"Services"
        }
    ],
    "sg:phone":"+1 585 442 0847",
    "sg:postcode":"14618",
    "sg:province":"NY",
    "sg:tags":[
        "national",
        "commercial"
    ],
    "wof:name":"Charter One Bank NA",
    "wof:placetype":"venue"
},
  "geometry": {"coordinates":[-77.564026,43.126309],"type":"Point"}
}