{
  "type": "Feature",
  "properties": {
    "addr:full":"44 Oswego St Baldwinsville NY 13027",
    "addr:housenumber":"44",
    "addr:postcode":"13027",
    "addr:street":"Oswego St",
    "iso:country":"US",
    "sg:address":"44 Oswego St",
    "sg:city":"Baldwinsville",
    "sg:classifiers":[
        {
            "category":"Professional",
            "subcategory":"Lawyer & Legal Services",
            "type":"Services"
        }
    ],
    "sg:phone":"+1 315 635 3222",
    "sg:postcode":"13027",
    "sg:province":"NY",
    "sg:tags":[
        "attorney"
    ],
    "wof:name":"Farrell Martin & Barnell",
    "wof:placetype":"venue"
},
  "geometry": {"coordinates":[-76.332786,43.159448],"type":"Point"}
}