{
  "type": "Feature",
  "properties": {
    "iso:country":"US",
    "sg:address":"1280 Titus Ave",
    "sg:city":"Rochester",
    "sg:classifiers":[
        {
            "category":"Government",
            "subcategory":"Office",
            "type":"Public Place"
        }
    ],
    "sg:phone":"+1 585 336 6050",
    "sg:postcode":"14617",
    "sg:province":"NY",
    "sg:tags":[
        "department",
        "taxation"
    ],
    "wof:name":"Finance Dir/ Tax Office",
    "wof:placetype":"venue"
},
  "geometry": {"coordinates":[-77.58218599999999,43.211212],"type":"Point"}
}