{
  "type": "Feature",
  "properties": {
    "iso:country":"US",
    "sg:address":"163 Clinton St",
    "sg:city":"Brooklyn",
    "sg:classifiers":[
        {
            "category":"Health Services",
            "subcategory":"Doctor",
            "type":"Services"
        },
        {
            "category":"Health Services",
            "subcategory":"Clinic",
            "type":"Services"
        },
        {
            "category":"Personal",
            "type":"Services"
        }
    ],
    "sg:phone":"+1 718 625 6526",
    "sg:postcode":"11201",
    "sg:province":"NY",
    "sg:tags":[
        "counseling",
        "psychologist",
        "mental"
    ],
    "sg:website":"http://www.shelleyjuranphd.com",
    "wof:name":"Juran Shelley Ph.D.",
    "wof:placetype":"venue"
},
  "geometry": {"coordinates":[-73.993982,40.691037],"type":"Point"}
}