{
  "type": "Feature",
  "properties": {
    "addr:full":"225 Broad Hollow Rd Melville NY 11747",
    "addr:housenumber":"225",
    "addr:postcode":"11747",
    "addr:street":"Broad Hollow Rd",
    "iso:country":"US",
    "sg:address":"225 Broad Hollow Rd",
    "sg:city":"Melville",
    "sg:classifiers":[
        {
            "category":"Banks & Credit Unions",
            "subcategory":"Bank",
            "type":"Services"
        }
    ],
    "sg:phone":"+1 631 396 2180",
    "sg:postcode":"11747",
    "sg:province":"NY",
    "sg:tags":[
        "mortgage"
    ],
    "wof:name":"CAPSTAR FUNDING",
    "wof:placetype":"venue"
},
  "geometry": {"coordinates":[-73.42325,40.762874],"type":"Point"}
}