{
  "type": "Feature",
  "properties": {
    "addr:full":"783 Route 9 Fishkill NY 12524",
    "addr:housenumber":"783",
    "addr:postcode":"12524",
    "addr:street":"Route 9",
    "iso:country":"US",
    "sg:address":"783 Route 9",
    "sg:city":"Fishkill",
    "sg:classifiers":[
        {
            "category":"Health Services",
            "subcategory":"Dentist",
            "type":"Services"
        }
    ],
    "sg:phone":"+1 845 896 1041",
    "sg:postcode":"12524",
    "sg:province":"NY",
    "sg:website":"www.familydentalgrp.com",
    "wof:name":"Family Dental Group",
    "wof:placetype":"venue"
},
  "geometry": {"coordinates":[-73.901921,41.540773],"type":"Point"}
}