{
  "type": "Feature",
  "properties": {
    "addr:full":"150 Elm St Yonkers NY 10701",
    "addr:housenumber":"150",
    "addr:postcode":"10701",
    "addr:street":"Elm St",
    "iso:country":"US",
    "sg:address":"150 Elm St",
    "sg:city":"Yonkers",
    "sg:classifiers":[
        {
            "category":"Wholesale",
            "subcategory":"Groceries",
            "type":"Manufacturing & Wholesale Goods"
        }
    ],
    "sg:phone":"+1 914 423 0273",
    "sg:postcode":"10701",
    "sg:province":"NY",
    "sg:tags":[
        "grocer"
    ],
    "wof:name":"Orlando's Mini Market",
    "wof:placetype":"venue"
},
  "geometry": {"coordinates":[-73.890598,40.933527],"type":"Point"}
}