{
  "type": "Feature",
  "properties": {
    "addr:full":"77 Lower Reservoir Rd Goshen NY 10924",
    "addr:housenumber":"77",
    "addr:postcode":"10924",
    "addr:street":"Lower Reservoir Rd",
    "iso:country":"US",
    "sg:address":"77 Lower Reservoir Rd",
    "sg:city":"Goshen",
    "sg:classifiers":[
        {
            "category":"Freight",
            "type":"Transportation"
        }
    ],
    "sg:phone":"+1   ",
    "sg:postcode":"10924",
    "sg:province":"NY",
    "sg:tags":[
        "operator",
        "local",
        "trucking"
    ],
    "wof:name":"Petrakis Trucking",
    "wof:placetype":"venue"
},
  "geometry": {"coordinates":[-74.329987,41.385153],"type":"Point"}
}