{
  "type": "Feature",
  "properties": {
    "addr:full":"565 Bicycle Path Port Jeffrsn Sta NY 11776",
    "addr:housenumber":"565",
    "addr:postcode":"11776",
    "addr:street":"Bicycle Path",
    "iso:country":"US",
    "sg:address":"565 Bicycle Path",
    "sg:city":"Port Jeffrsn Sta",
    "sg:classifiers":[
        {
            "category":"Retail",
            "subcategory":"Repair Shop",
            "type":"Services"
        }
    ],
    "sg:phone":"+1 631 791 0015",
    "sg:postcode":"11776",
    "sg:province":"NY",
    "sg:tags":[
        "lock",
        "locksmith"
    ],
    "wof:name":"1 Hour Emergency Locksmith",
    "wof:placetype":"venue"
},
  "geometry": {"coordinates":[-73.037463,40.906877],"type":"Point"}
}