{
  "type": "Feature",
  "properties": {
    "addr:full":"711 Old Saw Mill River Rd Tarrytown NY 10591",
    "addr:housenumber":"711",
    "addr:postcode":"10591",
    "addr:street":"Old Saw Mill River Rd",
    "iso:country":"US",
    "sg:address":"711 Old Saw Mill River Rd",
    "sg:city":"Tarrytown",
    "sg:classifiers":[
        {
            "category":"Manufacturing",
            "subcategory":"Electronics",
            "type":"Manufacturing & Wholesale Goods"
        }
    ],
    "sg:phone":"+1   ",
    "sg:postcode":"10591",
    "sg:province":"NY",
    "sg:tags":[
        "electronic",
        "center"
    ],
    "wof:name":"Novartis Corporation",
    "wof:placetype":"venue"
},
  "geometry": {"coordinates":[-73.844812,41.079855],"type":"Point"}
}