{
  "type": "Feature",
  "properties": {
    "addr:full":"202 E Main St Batavia NY 14020",
    "addr:housenumber":"202",
    "addr:postcode":"14020",
    "addr:street":"E Main St",
    "iso:country":"US",
    "sg:address":"202 E Main St",
    "sg:city":"Batavia",
    "sg:classifiers":[
        {
            "category":"Shopping",
            "subcategory":"Florist",
            "type":"Retail Goods"
        }
    ],
    "sg:phone":"+1 585 343 3922",
    "sg:postcode":"14020",
    "sg:province":"NY",
    "wof:name":"Enchanted Florist The",
    "wof:placetype":"venue"
},
  "geometry": {"coordinates":[-78.181785,42.99727],"type":"Point"}
}