{
  "type": "Feature",
  "properties": {
    "iso:country":"US",
    "sg:address":"688 Best Rd",
    "sg:city":"West Sand Lake",
    "sg:classifiers":[
        {
            "category":"Building & Trades",
            "subcategory":"Construction",
            "type":"Services"
        }
    ],
    "sg:phone":"+1 518 283 2755",
    "sg:postcode":"12196",
    "sg:province":"NY",
    "sg:tags":[
        "contractor"
    ],
    "wof:name":"All Phase Dem & Excav Co",
    "wof:placetype":"venue"
},
  "geometry": {"coordinates":[-73.617445,42.608129],"type":"Point"}
}