{
  "type": "Feature",
  "properties": {
    "addr:full":"3874 Jerusalem Ave Seaford NY 11783",
    "addr:housenumber":"3874",
    "addr:postcode":"11783",
    "addr:street":"Jerusalem Ave",
    "iso:country":"US",
    "sg:address":"3874 Jerusalem Ave",
    "sg:city":"Seaford",
    "sg:classifiers":[
        {
            "category":"Banks & Credit Unions",
            "subcategory":"Financial Services",
            "type":"Services"
        }
    ],
    "sg:phone":"+1 516 221 0451",
    "sg:postcode":"11783",
    "sg:province":"NY",
    "sg:tags":[
        "company",
        "holding"
    ],
    "wof:name":"Piro Holding Corp",
    "wof:placetype":"venue"
},
  "geometry": {"coordinates":[-73.488328,40.690908],"type":"Point"}
}