{
  "type": "Feature",
  "properties": {
    "iso:country":"US",
    "sg:address":"59 Coolidge St",
    "sg:city":"Blauvelt",
    "sg:classifiers":[
        {
            "category":"Government",
            "subcategory":"Office",
            "type":"Public Place"
        }
    ],
    "sg:phone":"+1 845 359 0830",
    "sg:postcode":"10913",
    "sg:province":"NY",
    "sg:tags":[
        "national",
        "security"
    ],
    "wof:name":"Civil Air Patrol Inc",
    "wof:placetype":"venue"
},
  "geometry": {"coordinates":[-73.983113,41.061745],"type":"Point"}
}