{
  "type": "Feature",
  "properties": {
    "iso:country":"US",
    "sg:address":"197 Meserole St",
    "sg:city":"Brooklyn",
    "sg:classifiers":[
        {
            "category":"Restaurant",
            "type":"Food & Drink"
        }
    ],
    "sg:phone":"+1 718 381 4343",
    "sg:postcode":"11206",
    "sg:province":"NY",
    "sg:tags":[
        "american",
        "latin",
        "eating"
    ],
    "wof:name":"Barzola Restaurant",
    "wof:placetype":"venue"
},
  "geometry": {"coordinates":[-73.941101,40.708302],"type":"Point"}
}