{
  "type": "Feature",
  "properties": {
    "addr:full":"97 Prospect St Binghamton NY 13905",
    "addr:housenumber":"97",
    "addr:postcode":"13905",
    "addr:street":"Prospect St",
    "iso:country":"US",
    "sg:address":"97 Prospect St",
    "sg:city":"Binghamton",
    "sg:classifiers":[
        {
            "category":"Organizations",
            "subcategory":"Religious Organization",
            "type":"Services"
        }
    ],
    "sg:phone":"+1 607 723 3702",
    "sg:postcode":"13905",
    "sg:province":"NY",
    "sg:tags":[
        "clergy"
    ],
    "wof:name":"Henry J Ausby",
    "wof:placetype":"venue"
},
  "geometry": {"coordinates":[-75.91800000000001,42.111686],"type":"Point"}
}