{
  "type": "Feature",
  "properties": {
    "iso:country":"US",
    "sg:address":"1234 Broadway",
    "sg:city":"New York",
    "sg:classifiers":[
        {
            "category":"Professional",
            "type":"Services"
        }
    ],
    "sg:phone":"+1 212 216 9403",
    "sg:postcode":"10001",
    "sg:province":"NY",
    "sg:tags":[
        "establishment"
    ],
    "wof:name":"Hallco Inc",
    "wof:placetype":"venue"
},
  "geometry": {"coordinates":[-73.988317,40.746944],"type":"Point"}
}