{
  "type": "Feature",
  "properties": {
    "addr:full":"3466 Boston Rd Bronx NY 10469",
    "addr:housenumber":"3466",
    "addr:postcode":"10469",
    "addr:street":"Boston Rd",
    "iso:country":"US",
    "sg:address":"3466 Boston Rd",
    "sg:city":"Bronx",
    "sg:classifiers":[
        {
            "category":"Home & Garden",
            "subcategory":"Building Materials",
            "type":"Retail Goods"
        }
    ],
    "sg:phone":"+1 718 515 5722",
    "sg:postcode":"10469",
    "sg:province":"NY",
    "sg:tags":[
        "paint"
    ],
    "wof:name":"K & R Paint & Hardware",
    "wof:placetype":"venue"
},
  "geometry": {"coordinates":[-73.847487,40.87657],"type":"Point"}
}