{
  "type": "Feature",
  "properties": {
    "iso:country":"US",
    "sg:address":"735 Renaissance Dr # 205",
    "sg:city":"Buffalo",
    "sg:classifiers":[
        {
            "category":"Professional",
            "subcategory":"Management & Consulting",
            "type":"Services"
        }
    ],
    "sg:phone":"+1 716 929 5324",
    "sg:postcode":"14221",
    "sg:province":"NY",
    "sg:tags":[
        "consultant"
    ],
    "wof:name":"Fred S Nadel & Associates",
    "wof:placetype":"venue"
},
  "geometry": {"coordinates":[-78.69846699999999,42.996024],"type":"Point"}
}