{
  "type": "Feature",
  "properties": {
    "iso:country":"US",
    "sg:address":"1154 State Hwy 52",
    "sg:city":"Loch Sheldrake",
    "sg:classifiers":[
        {
            "category":"Restaurant",
            "type":"Food & Drink"
        }
    ],
    "sg:phone":"+1 845 436 8424",
    "sg:postcode":"12726",
    "sg:province":"NY",
    "wof:name":"China Direct Trading",
    "wof:placetype":"venue"
},
  "geometry": {"coordinates":[-74.980913,41.659739],"type":"Point"}
}