{
  "type": "Feature",
  "properties": {
    "addr:full":"23 Cedar St Dobbs Ferry NY 10522",
    "addr:housenumber":"23",
    "addr:postcode":"10522",
    "addr:street":"Cedar St",
    "iso:country":"US",
    "sg:address":"23 Cedar St",
    "sg:city":"Dobbs Ferry",
    "sg:classifiers":[
        {
            "category":"Restaurant",
            "type":"Food & Drink"
        }
    ],
    "sg:menulink":"http://www.allmenus.com/ny/greenburgh/141251-mykonos/menu/",
    "sg:phone":"+1 914 674 0706",
    "sg:postcode":"10522",
    "sg:province":"NY",
    "sg:tags":[
        "greek"
    ],
    "wof:name":"Mykonos",
    "wof:placetype":"venue"
},
  "geometry": {"coordinates":[-73.872078,41.015351],"type":"Point"}
}