{
  "type": "Feature",
  "properties": {
    "iso:country":"US",
    "sg:address":"1397 Broadway",
    "sg:city":"Watervliet",
    "sg:classifiers":[
        {
            "category":"Professional",
            "subcategory":"Accounting & Tax Preparation",
            "type":"Services"
        },
        {
            "category":"Recreation",
            "subcategory":"Amusement Park",
            "type":"Entertainment"
        }
    ],
    "sg:phone":"+1 518 272 5776",
    "sg:postcode":"12189",
    "sg:province":"NY",
    "sg:tags":[
        "device",
        "jukebox"
    ],
    "sg:website":"http://www.albanyamusement.com",
    "wof:name":"Albany Amusement Co. Inc.",
    "wof:placetype":"venue"
},
  "geometry": {"coordinates":[-73.70036,42.724283],"type":"Point"}
}