{
  "type": "Feature",
  "properties": {
    "addr:full":"655 E 187th St Bronx NY 10458",
    "addr:housenumber":"655",
    "addr:postcode":"10458",
    "addr:street":"E 187Th St",
    "iso:country":"US",
    "sg:address":"655 E 187th St",
    "sg:city":"Bronx",
    "sg:classifiers":[
        {
            "category":"Food & Beverages",
            "subcategory":"Specialty",
            "type":"Retail Goods"
        }
    ],
    "sg:phone":"+1 718 365 6500",
    "sg:postcode":"10458",
    "sg:province":"NY",
    "sg:tags":[
        "gourmet",
        "shop"
    ],
    "wof:name":"Gregorio Gourmet Foods Inc",
    "wof:placetype":"venue"
},
  "geometry": {"coordinates":[-73.885509,40.854644],"type":"Point"}
}