{
  "type": "Feature",
  "properties": {
    "addr:full":"318 Malcolm X Blvd Brooklyn NY 11233",
    "addr:housenumber":"318",
    "addr:postcode":"11233",
    "addr:street":"Malcolm X Blvd",
    "iso:country":"US",
    "sg:address":"318 Malcolm X Blvd",
    "sg:city":"Brooklyn",
    "sg:classifiers":[
        {
            "category":"Shopping",
            "subcategory":"Used Merchandise",
            "type":"Retail Goods"
        }
    ],
    "sg:phone":"+1   ",
    "sg:postcode":"11233",
    "sg:province":"NY",
    "wof:name":"Odd Things",
    "wof:placetype":"venue"
},
  "geometry": {"coordinates":[-73.92900899999999,40.682703],"type":"Point"}
}