{
  "type": "Feature",
  "properties": {
    "iso:country":"US",
    "sg:address":"593 Maple Ave",
    "sg:city":"Clymer",
    "sg:classifiers":[
        {
            "category":"Home & Garden",
            "subcategory":"Furniture",
            "type":"Retail Goods"
        }
    ],
    "sg:phone":"+1 716 355 6440",
    "sg:postcode":"14724",
    "sg:province":"NY",
    "sg:tags":[
        "top",
        "counter"
    ],
    "wof:name":"Countertop Solutions Inc",
    "wof:placetype":"venue"
},
  "geometry": {"coordinates":[-79.631258,42.020994],"type":"Point"}
}