{
  "type": "Feature",
  "properties": {
    "iso:country":"US",
    "sg:address":"84 S Davis St",
    "sg:city":"Orchard Park",
    "sg:classifiers":[
        {
            "category":"Professional",
            "subcategory":"Lawyer & Legal Services",
            "type":"Services"
        }
    ],
    "sg:phone":"+1 716 662 9749",
    "sg:postcode":"14127",
    "sg:province":"NY",
    "sg:tags":[
        "attorney"
    ],
    "wof:name":"Smith Family Offices",
    "wof:placetype":"venue"
},
  "geometry": {"coordinates":[-78.75256899999999,42.764375],"type":"Point"}
}