{
  "type": "Feature",
  "properties": {
    "addr:full":"40 Hudson Pl Monroe NY 10950",
    "addr:housenumber":"40",
    "addr:postcode":"10950",
    "addr:street":"Hudson Pl",
    "iso:country":"US",
    "sg:address":"40 Hudson Pl",
    "sg:city":"Monroe",
    "sg:classifiers":[
        {
            "category":"Building & Trades",
            "subcategory":"Construction",
            "type":"Services"
        }
    ],
    "sg:phone":"+1 845 782 3877",
    "sg:postcode":"10950",
    "sg:province":"NY",
    "sg:tags":[
        "contractor"
    ],
    "wof:name":"Anastasia Construction Services Inc",
    "wof:placetype":"venue"
},
  "geometry": {"coordinates":[-74.17330200000001,41.312901],"type":"Point"}
}