{
  "type": "Feature",
  "properties": {
    "addr:full":"1748 State Hwy 52 Walden NY 12586",
    "addr:housenumber":"1748",
    "addr:postcode":"12586",
    "addr:street":"State Hwy 52",
    "iso:country":"US",
    "sg:address":"1748 State Hwy 52",
    "sg:city":"Walden",
    "sg:classifiers":[
        {
            "category":"Farming",
            "subcategory":"Dairy Farm",
            "type":"Manufacturing & Wholesale Goods"
        }
    ],
    "sg:phone":"+1 845 778 3631",
    "sg:postcode":"12586",
    "sg:province":"NY",
    "wof:name":"Carl Balbach",
    "wof:placetype":"venue"
},
  "geometry": {"coordinates":[-74.24506100000001,41.590585],"type":"Point"}
}