{
  "type": "Feature",
  "properties": {
    "addr:full":"84 Broadway St Whitehall NY 12887",
    "addr:housenumber":"84",
    "addr:postcode":"12887",
    "addr:street":"Broadway St",
    "iso:country":"US",
    "sg:address":"84 Broadway St",
    "sg:city":"Whitehall",
    "sg:classifiers":[
        {
            "category":"Education",
            "subcategory":"School",
            "type":"Public Place"
        }
    ],
    "sg:phone":"+1 518 499 1251",
    "sg:postcode":"12887",
    "sg:province":"NY",
    "wof:name":"H & R Block Tax Svc",
    "wof:placetype":"venue"
},
  "geometry": {"coordinates":[-73.40360699999999,43.553872],"type":"Point"}
}