{
  "type": "Feature",
  "properties": {
    "addr:full":"441 Electronics Pkwy Liverpool NY 13088",
    "addr:housenumber":"441",
    "addr:postcode":"13088",
    "addr:street":"Electronics Pkwy",
    "iso:country":"US",
    "sg:address":"441 Electronics Pkwy",
    "sg:city":"Liverpool",
    "sg:classifiers":[
        {
            "category":"Restaurant",
            "type":"Food & Drink"
        }
    ],
    "sg:phone":"+1 800 345 8082",
    "sg:postcode":"13088",
    "sg:province":"NY",
    "sg:tags":[
        "hotel"
    ],
    "sg:website":"http://ad.doubleclick.net/clk;223371278;47096201;d?http://www.holidayinn.com/redirect?path=hd&brandCode=hi&hotelCode=syrlp&_PMID=99601036&cm_mmc=mdpr-_-yellowpages-_-hi-_-syrlp",
    "wof:name":"Holiday Inn Syracuse-Liverpool-Exit 37",
    "wof:placetype":"venue"
},
  "geometry": {"coordinates":[-76.188316,43.100874],"type":"Point"}
}