{
  "type": "Feature",
  "properties": {
    "addr:full":"9 E 17th St New York NY 10003",
    "addr:housenumber":"9",
    "addr:postcode":"10003",
    "addr:street":"E 17Th St",
    "iso:country":"US",
    "sg:address":"9 E 17th St",
    "sg:city":"New York",
    "sg:classifiers":[
        {
            "category":"Restaurant",
            "type":"Food & Drink"
        }
    ],
    "sg:menulink":"http://www.allmenus.com/ny/new-york/7917-sushi-edo/menu/",
    "sg:phone":"+1 212 989 2938",
    "sg:postcode":"10003",
    "sg:province":"NY",
    "sg:tags":[
        "sushi",
        "japanese",
        "asian"
    ],
    "wof:name":"Edo Japanese Restaurant",
    "wof:placetype":"venue"
},
  "geometry": {"coordinates":[-73.991299,40.73775],"type":"Point"}
}