{
  "type": "Feature",
  "properties": {
    "iso:country":"US",
    "sg:address":"6420 State Hwy 31",
    "sg:city":"Fairport",
    "sg:classifiers":[
        {
            "category":"Shopping",
            "subcategory":"Florist",
            "type":"Retail Goods"
        }
    ],
    "sg:phone":"+1 315 699 7513",
    "sg:postcode":"14450",
    "sg:province":"NY",
    "wof:name":"Guignard Florist",
    "wof:placetype":"venue"
},
  "geometry": {"coordinates":[-77.456194,43.072981],"type":"Point"}
}