{
  "type": "Feature",
  "properties": {
    "addr:full":"65 Smithtown Blvd Smithtown NY 11787",
    "addr:housenumber":"65",
    "addr:postcode":"11787",
    "addr:street":"Smithtown Blvd",
    "iso:country":"US",
    "sg:address":"65 Smithtown Blvd",
    "sg:city":"Smithtown",
    "sg:classifiers":[
        {
            "category":"Retail",
            "subcategory":"Laundry & Dry Cleaning",
            "type":"Services"
        }
    ],
    "sg:phone":"+1 631 265 9887",
    "sg:postcode":"11787",
    "sg:province":"NY",
    "sg:tags":[
        "cleaners"
    ],
    "wof:name":"Michele French Cleaners",
    "wof:placetype":"venue"
},
  "geometry": {"coordinates":[-73.166172,40.8399],"type":"Point"}
}