{
  "type": "Feature",
  "properties": {
    "addr:full":"150 Varick St 2nd Floor New York NY 10013",
    "addr:housenumber":"150;2nd floor",
    "addr:postcode":"10013",
    "addr:street":"Varick St",
    "iso:country":"US",
    "sg:address":"150 Varick St 2nd Floor",
    "sg:city":"New York",
    "sg:classifiers":[
        {
            "category":"Communications",
            "type":"Services"
        }
    ],
    "sg:phone":"+1 212 606 0700",
    "sg:postcode":"10013",
    "sg:province":"NY",
    "sg:tags":[
        "recording",
        "rehearsal",
        "studio"
    ],
    "sg:website":"www.panavision.com",
    "wof:name":"Panavision New York",
    "wof:placetype":"venue"
},
  "geometry": {"coordinates":[-74.00532,40.726008],"type":"Point"}
}