{
  "type": "Feature",
  "properties": {
    "addr:full":"1305 50th St Brooklyn NY 11219",
    "addr:housenumber":"1305",
    "addr:postcode":"11219",
    "addr:street":"50Th St",
    "iso:country":"US",
    "sg:address":"1305 50th St",
    "sg:city":"Brooklyn",
    "sg:classifiers":[
        {
            "category":"Food & Beverages",
            "subcategory":"Candy",
            "type":"Retail Goods"
        },
        {
            "category":"Food & Beverages",
            "subcategory":"Chocolate",
            "type":"Retail Goods"
        }
    ],
    "sg:phone":"+1 718 853 5158",
    "sg:postcode":"11219",
    "sg:province":"NY",
    "sg:tags":[
        "shop",
        "chocolatiers",
        "store"
    ],
    "sg:website":"www.ohnuts.com",
    "wof:name":"Oh Nuts",
    "wof:placetype":"venue"
},
  "geometry": {"coordinates":[-73.992401,40.634399],"type":"Point"}
}