{
  "type": "Feature",
  "properties": {
    "iso:country":"US",
    "sg:address":"60 W 39th St",
    "sg:city":"New York",
    "sg:classifiers":[
        {
            "category":"Professional",
            "type":"Services"
        }
    ],
    "sg:phone":"+1 212 391 2500",
    "sg:postcode":"10018",
    "sg:province":"NY",
    "sg:tags":[
        "caterer"
    ],
    "sg:website":"www.sixocatering.com",
    "wof:name":"Sixo Catering",
    "wof:placetype":"venue"
},
  "geometry": {"coordinates":[-73.984223,40.752265],"type":"Point"}
}