{
  "type": "Feature",
  "properties": {
    "addr:full":"6 Patterson St Port Jervis NY 12771",
    "addr:housenumber":"6",
    "addr:postcode":"12771",
    "addr:street":"Patterson St",
    "iso:country":"US",
    "sg:address":"6 Patterson St",
    "sg:city":"Port Jervis",
    "sg:classifiers":[
        {
            "category":"Wholesale",
            "subcategory":"Non-durable Goods",
            "type":"Manufacturing & Wholesale Goods"
        }
    ],
    "sg:phone":"+1 845 856 4700",
    "sg:postcode":"12771",
    "sg:province":"NY",
    "wof:name":"Jem Products",
    "wof:placetype":"venue"
},
  "geometry": {"coordinates":[-74.68301099999999,41.361219],"type":"Point"}
}