{
  "type": "Feature",
  "properties": {
    "iso:country":"US",
    "sg:address":"2670 Ford St",
    "sg:city":"Brooklyn",
    "sg:classifiers":[
        {
            "category":"Autos & Motor Vehicles",
            "subcategory":"Boat Sales",
            "type":"Retail Goods"
        }
    ],
    "sg:phone":"+1 718 934 5551",
    "sg:postcode":"11235",
    "sg:province":"NY",
    "sg:tags":[
        "equipment",
        "manufacturer",
        "supplies-wholesale",
        "supply"
    ],
    "wof:name":"Bay Side Boat Canvas Co",
    "wof:placetype":"venue"
},
  "geometry": {"coordinates":[-73.935789,40.588541],"type":"Point"}
}