{
  "type": "Feature",
  "properties": {
    "iso:country":"US",
    "sg:address":"65 Williamsburg Ln",
    "sg:city":"Lancaster",
    "sg:classifiers":[
        {
            "category":"Shopping",
            "subcategory":"Bicycles & Sporting Goods",
            "type":"Retail Goods"
        }
    ],
    "sg:phone":"+1   ",
    "sg:postcode":"14086",
    "sg:province":"NY",
    "wof:name":"Advantage Sporting Goods",
    "wof:placetype":"venue"
},
  "geometry": {"coordinates":[-78.679586,42.882107],"type":"Point"}
}