{
  "type": "Feature",
  "properties": {
    "addr:full":"1390 Avenue of the Americ New York NY 10019",
    "addr:housenumber":"1390",
    "addr:postcode":"10019",
    "addr:street":"Avenue Of The",
    "iso:country":"US",
    "sg:address":"1390 Avenue of the Americ",
    "sg:city":"New York",
    "sg:classifiers":[
        {
            "category":"Shopping",
            "subcategory":"Tobacco",
            "type":"Retail Goods"
        }
    ],
    "sg:phone":"+1 212 757 3167",
    "sg:postcode":"10019",
    "sg:province":"NY",
    "sg:tags":[
        "shop"
    ],
    "sg:website":"www.delaconcha.com/",
    "wof:name":"De La Concha Tobacconist",
    "wof:placetype":"venue"
},
  "geometry": {"coordinates":[-73.977216,40.764069],"type":"Point"}
}