{
  "type": "Feature",
  "properties": {
    "addr:full":"72 Gleneida Ave Carmel NY 10512",
    "addr:housenumber":"72",
    "addr:postcode":"10512",
    "addr:street":"Gleneida Ave",
    "iso:country":"US",
    "sg:address":"72 Gleneida Ave",
    "sg:city":"Carmel",
    "sg:classifiers":[
        {
            "category":"Building & Trades",
            "subcategory":"Construction",
            "type":"Services"
        }
    ],
    "sg:phone":"+1 845 225 5244",
    "sg:postcode":"10512",
    "sg:province":"NY",
    "sg:tags":[
        "general",
        "contractor"
    ],
    "wof:name":"Starview International Constr",
    "wof:placetype":"venue"
},
  "geometry": {"coordinates":[-73.67914,41.428087],"type":"Point"}
}