{
  "type": "Feature",
  "properties": {
    "addr:full":"598 Main St Ste 1 Buffalo NY 14202",
    "addr:housenumber":"598",
    "addr:postcode":"14202",
    "addr:street":"Main St Ste 1",
    "iso:country":"US",
    "sg:address":"598 Main St Ste 1",
    "sg:city":"Buffalo",
    "sg:classifiers":[
        {
            "category":"Banks & Credit Unions",
            "subcategory":"Bank",
            "type":"Services"
        }
    ],
    "sg:phone":"+1 716 852 5660",
    "sg:postcode":"14202",
    "sg:province":"NY",
    "wof:name":"SEFCU",
    "wof:placetype":"venue"
},
  "geometry": {"coordinates":[-78.873051,42.890295],"type":"Point"}
}