{
  "type": "Feature",
  "properties": {
    "addr:full":"451 Morris Park Ave Bronx NY 10460",
    "addr:housenumber":"451",
    "addr:postcode":"10460",
    "addr:street":"Morris Park Ave",
    "iso:country":"US",
    "sg:address":"451 Morris Park Ave",
    "sg:city":"Bronx",
    "sg:classifiers":[
        {
            "category":"Restaurant",
            "type":"Food & Drink"
        }
    ],
    "sg:phone":"+1 718 319 8320",
    "sg:postcode":"10460",
    "sg:province":"NY",
    "sg:tags":[
        "mexican"
    ],
    "wof:name":"Guacamole'X",
    "wof:placetype":"venue"
},
  "geometry": {"coordinates":[-73.873029,40.840582],"type":"Point"}
}