{
  "type": "Feature",
  "properties": {
    "iso:country":"US",
    "sg:address":"3544 Dutch Hollow Rd",
    "sg:city":"Jamestown",
    "sg:classifiers":[
        {
            "category":"Retail",
            "subcategory":"Repair Shop",
            "type":"Services"
        }
    ],
    "sg:phone":"+1 716 640 1606",
    "sg:postcode":"14701",
    "sg:province":"NY",
    "sg:tags":[
        "welding"
    ],
    "wof:name":"Welding Works",
    "wof:placetype":"venue"
},
  "geometry": {"coordinates":[-79.317998,42.145159],"type":"Point"}
}