{
  "type": "Feature",
  "properties": {
    "addr:full":"3910 64th St Woodside NY 11377",
    "addr:housenumber":"3910",
    "addr:postcode":"11377",
    "addr:street":"64Th St",
    "iso:country":"US",
    "sg:address":"3910 64th St",
    "sg:city":"Woodside",
    "sg:classifiers":[
        {
            "category":"Personal",
            "subcategory":"Nail Salon",
            "type":"Services"
        }
    ],
    "sg:phone":"+1 718 639 5833",
    "sg:postcode":"11377",
    "sg:province":"NY",
    "wof:name":"J & J Nail Inc",
    "wof:placetype":"venue"
},
  "geometry": {"coordinates":[-73.90010100000001,40.7463],"type":"Point"}
}