{
  "type": "Feature",
  "properties": {
    "iso:country":"US",
    "sg:address":"231 W 39 St",
    "sg:city":"New York",
    "sg:classifiers":[
        {
            "category":"Wholesale",
            "subcategory":"Apparel",
            "type":"Manufacturing & Wholesale Goods"
        }
    ],
    "sg:phone":"+1 212 398 3020",
    "sg:postcode":"10018",
    "sg:province":"NY",
    "sg:tags":[
        "clothing"
    ],
    "wof:name":"Novum Fashion International",
    "wof:placetype":"venue"
},
  "geometry": {"coordinates":[-73.990481,40.755028],"type":"Point"}
}