{
  "type": "Feature",
  "properties": {
    "addr:full":"JFK International Airport New York NY 10079",
    "addr:housenumber":"jfk",
    "addr:postcode":"10079",
    "iso:country":"US",
    "sg:address":"JFK International Airport",
    "sg:city":"New York",
    "sg:classifiers":[
        {
            "category":"Airline",
            "type":"Transportation"
        }
    ],
    "sg:postcode":"10079",
    "sg:province":"NY",
    "sg:website":"www.thaiair.com",
    "wof:name":"Thai Airlines",
    "wof:placetype":"venue"
},
  "geometry": {"coordinates":[-73.787282,40.646667],"type":"Point"}
}