{
  "type": "Feature",
  "properties": {
    "addr:full":"473 Morgan Ave Brooklyn NY 11222",
    "addr:housenumber":"473",
    "addr:postcode":"11222",
    "addr:street":"Morgan Ave",
    "iso:country":"US",
    "sg:address":"473 Morgan Ave",
    "sg:city":"Brooklyn",
    "sg:classifiers":[
        {
            "category":"Banks & Credit Unions",
            "subcategory":"Bank",
            "type":"Services"
        }
    ],
    "sg:phone":"+1 718 782 3492",
    "sg:postcode":"11222",
    "sg:province":"NY",
    "sg:tags":[
        "cashing",
        "agency",
        "check"
    ],
    "wof:name":"Morgan Check Cashing Co",
    "wof:placetype":"venue"
},
  "geometry": {"coordinates":[-73.938098,40.720503],"type":"Point"}
}