{
  "type": "Feature",
  "properties": {
    "addr:full":"181 Aqueduct Rd White Plains NY 10606",
    "addr:housenumber":"181",
    "addr:postcode":"10606",
    "addr:street":"Aqueduct Rd",
    "iso:country":"US",
    "sg:address":"181 Aqueduct Rd",
    "sg:city":"White Plains",
    "sg:classifiers":[
        {
            "category":"Taxi",
            "type":"Transportation"
        }
    ],
    "sg:phone":"+1 914 686 1968",
    "sg:postcode":"10606",
    "sg:province":"NY",
    "sg:tags":[
        "taxicab"
    ],
    "wof:name":"Madison Cab Corp",
    "wof:placetype":"venue"
},
  "geometry": {"coordinates":[-73.78164700000001,41.037586],"type":"Point"}
}