{
  "type": "Feature",
  "properties": {
    "addr:full":"94 Wood Ave Amityville NY 11701",
    "addr:housenumber":"94",
    "addr:postcode":"11701",
    "addr:street":"Wood Ave",
    "iso:country":"US",
    "sg:address":"94 Wood Ave",
    "sg:city":"Amityville",
    "sg:classifiers":[
        {
            "category":"Social Services",
            "type":"Services"
        }
    ],
    "sg:phone":"+1 631 264 8252",
    "sg:postcode":"11701",
    "sg:province":"NY",
    "sg:tags":[
        "youth",
        "organization",
        "center"
    ],
    "wof:name":"Amityville Little League",
    "wof:placetype":"venue"
},
  "geometry": {"coordinates":[-73.408546,40.672043],"type":"Point"}
}