{
  "type": "Feature",
  "properties": {
    "addr:full":"580 Broadway New York NY 10012",
    "addr:housenumber":"580",
    "addr:postcode":"10012",
    "addr:street":"Broadway",
    "iso:country":"US",
    "sg:address":"580 Broadway",
    "sg:city":"New York",
    "sg:classifiers":[
        {
            "category":"Real Estate",
            "subcategory":"Architect",
            "type":"Services"
        }
    ],
    "sg:phone":"+1 212 625 8476",
    "sg:postcode":"10012",
    "sg:province":"NY",
    "sg:website":"www.absarchitectsnyc.com",
    "wof:name":"ABS Architects",
    "wof:placetype":"venue"
},
  "geometry": {"coordinates":[-73.996965,40.724993],"type":"Point"}
}