{
  "type": "Feature",
  "properties": {
    "iso:country":"US",
    "sg:address":"116 5th Ave",
    "sg:city":"Pelham",
    "sg:classifiers":[
        {
            "category":"Health Services",
            "subcategory":"Doctor",
            "type":"Services"
        }
    ],
    "sg:phone":"+1 914 738 5744",
    "sg:postcode":"10803",
    "sg:province":"NY",
    "sg:tags":[
        "medical",
        "clinic"
    ],
    "wof:name":"Pelham Medical Clinic",
    "wof:placetype":"venue"
},
  "geometry": {"coordinates":[-73.80834,40.913745],"type":"Point"}
}