{
  "type": "Feature",
  "properties": {
    "addr:full":"1565 Columbia Tpke Castleton On Hudson NY 12033",
    "addr:housenumber":"1565",
    "addr:postcode":"12033",
    "addr:street":"Columbia Tpke",
    "iso:country":"US",
    "sg:address":"1565 Columbia Tpke",
    "sg:city":"Castleton On Hudson",
    "sg:classifiers":[
        {
            "category":"Travel",
            "subcategory":"Hotels & Motels",
            "type":"Entertainment"
        }
    ],
    "sg:phone":"+1 518 477 9906",
    "sg:postcode":"12033",
    "sg:province":"NY",
    "wof:name":"Hostfield Inn",
    "wof:placetype":"venue"
},
  "geometry": {"coordinates":[-73.688811,42.574798],"type":"Point"}
}