{
  "type": "Feature",
  "properties": {
    "iso:country":"US",
    "sg:address":"498 Watervliet Shaker Rd",
    "sg:city":"Latham",
    "sg:classifiers":[
        {
            "category":"Organizations",
            "subcategory":"Religious Organization",
            "type":"Services"
        }
    ],
    "sg:phone":"+1 518 785 1605",
    "sg:postcode":"12110",
    "sg:province":"NY",
    "sg:tags":[
        "church"
    ],
    "wof:name":"Our Lady-The Assumption Church",
    "wof:placetype":"venue"
},
  "geometry": {"coordinates":[-73.754077,42.733922],"type":"Point"}
}