{
  "type": "Feature",
  "properties": {
    "iso:country":"US",
    "sg:address":"6228 Dale Rd",
    "sg:city":"Newfane",
    "sg:classifiers":[
        {
            "category":"Social Services",
            "subcategory":"Adult Care",
            "type":"Services"
        }
    ],
    "sg:phone":"+1 716 778 6015",
    "sg:postcode":"14108",
    "sg:province":"NY",
    "sg:tags":[
        "home",
        "group"
    ],
    "wof:name":"Western New York DD So",
    "wof:placetype":"venue"
},
  "geometry": {"coordinates":[-78.693749,43.270167],"type":"Point"}
}