{
  "type": "Feature",
  "properties": {
    "addr:full":"507 W 111th St New York NY 10025",
    "addr:housenumber":"507",
    "addr:postcode":"10025",
    "addr:street":"W 111Th St",
    "iso:country":"US",
    "sg:address":"507 W 111th St",
    "sg:city":"New York",
    "sg:classifiers":[
        {
            "category":"Organizations",
            "subcategory":"Religious Organization",
            "type":"Services"
        }
    ],
    "sg:phone":"+1 212 666 1308",
    "sg:postcode":"10025",
    "sg:province":"NY",
    "sg:tags":[
        "clergy"
    ],
    "wof:name":"D Givens",
    "wof:placetype":"venue"
},
  "geometry": {"coordinates":[-73.963733,40.803835],"type":"Point"}
}