{
  "type": "Feature",
  "properties": {
    "iso:country":"US",
    "sg:address":"35 Crescent St",
    "sg:city":"Brooklyn",
    "sg:classifiers":[
        {
            "category":"Building & Trades",
            "subcategory":"Construction",
            "type":"Services"
        }
    ],
    "sg:phone":"+1 718 647 4924",
    "sg:postcode":"11208",
    "sg:province":"NY",
    "sg:tags":[
        "residential",
        "general",
        "dwelling",
        "contractor"
    ],
    "wof:name":"Losardo General Contractors",
    "wof:placetype":"venue"
},
  "geometry": {"coordinates":[-73.873874,40.68922],"type":"Point"}
}