{
  "type": "Feature",
  "properties": {
    "iso:country":"US",
    "sg:address":"44 Front St",
    "sg:city":"Owego",
    "sg:classifiers":[
        {
            "category":"Travel",
            "subcategory":"Hotels & Motels",
            "type":"Entertainment"
        }
    ],
    "sg:phone":"+1 607 687 0510",
    "sg:postcode":"13827",
    "sg:province":"NY",
    "sg:tags":[
        "breakfast",
        "accommodation",
        "bed"
    ],
    "sg:website":"www.pumpelly.com",
    "wof:name":"Pumpelly House Bed & Breakfast",
    "wof:placetype":"venue"
},
  "geometry": {"coordinates":[-76.26522199999999,42.100009],"type":"Point"}
}