{
  "type": "Feature",
  "properties": {
    "addr:full":"920 E 233rd St Bronx NY 10466",
    "addr:housenumber":"920",
    "addr:postcode":"10466",
    "addr:street":"E 233Rd St",
    "iso:country":"US",
    "sg:address":"920 E 233rd St",
    "sg:city":"Bronx",
    "sg:classifiers":[
        {
            "category":"Wholesale",
            "subcategory":"Machinery & Supplies",
            "type":"Manufacturing & Wholesale Goods"
        }
    ],
    "sg:phone":"+1 718 515 4800",
    "sg:postcode":"10466",
    "sg:province":"NY",
    "sg:tags":[
        "pleating"
    ],
    "wof:name":"Willbege Plumbing Supply Inc",
    "wof:placetype":"venue"
},
  "geometry": {"coordinates":[-73.85103599999999,40.891354],"type":"Point"}
}