{
  "type": "Feature",
  "properties": {
    "addr:full":"715 Main St Buffalo NY 14203",
    "addr:housenumber":"715",
    "addr:postcode":"14203",
    "addr:street":"Main St",
    "iso:country":"US",
    "sg:address":"715 Main St",
    "sg:city":"Buffalo",
    "sg:classifiers":[
        {
            "category":"Education",
            "subcategory":"School",
            "type":"Public Place"
        }
    ],
    "sg:phone":"+1 716 845 5060",
    "sg:postcode":"14203",
    "sg:province":"NY",
    "wof:name":"Verrico & Associates",
    "wof:placetype":"venue"
},
  "geometry": {"coordinates":[-78.871644,42.89332],"type":"Point"}
}