{
  "type": "Feature",
  "properties": {
    "addr:full":"687 Nostrand Ave Brooklyn NY 11216",
    "addr:housenumber":"687",
    "addr:postcode":"11216",
    "addr:street":"Nostrand Ave",
    "iso:country":"US",
    "sg:address":"687 Nostrand Ave",
    "sg:city":"Brooklyn",
    "sg:classifiers":[
        {
            "category":"Retail",
            "subcategory":"Laundry & Dry Cleaning",
            "type":"Services"
        }
    ],
    "sg:phone":"+1 718 221 1835",
    "sg:postcode":"11216",
    "sg:province":"NY",
    "sg:tags":[
        "cleaner"
    ],
    "wof:name":"Dutch Dry Cleaners",
    "wof:placetype":"venue"
},
  "geometry": {"coordinates":[-73.949997,40.673698],"type":"Point"}
}