{
  "type": "Feature",
  "properties": {
    "addr:full":"8 Medical Arts Ln Saratoga Springs NY 12866",
    "addr:housenumber":"8",
    "addr:postcode":"12866",
    "addr:street":"Medical Arts Ln",
    "iso:country":"US",
    "sg:address":"8 Medical Arts Ln",
    "sg:city":"Saratoga Springs",
    "sg:classifiers":[
        {
            "category":"Health Services",
            "subcategory":"Doctor",
            "type":"Services"
        }
    ],
    "sg:phone":"+1 518 584 6240",
    "sg:postcode":"12866",
    "sg:province":"NY",
    "sg:tags":[
        "dentist"
    ],
    "wof:name":"Wayne S Harrison DDS",
    "wof:placetype":"venue"
},
  "geometry": {"coordinates":[-73.795647,43.086425],"type":"Point"}
}