{
  "type": "Feature",
  "properties": {
    "addr:full":"4415 College Point Blvd Flushing NY 11355",
    "addr:housenumber":"4415",
    "addr:postcode":"11355",
    "addr:street":"College Point Blvd",
    "iso:country":"US",
    "sg:address":"4415 College Point Blvd",
    "sg:city":"Flushing",
    "sg:classifiers":[
        {
            "category":"Restaurant",
            "type":"Food & Drink"
        }
    ],
    "sg:phone":"+1 718 463 5787",
    "sg:postcode":"11355",
    "sg:province":"NY",
    "sg:tags":[
        "diner"
    ],
    "wof:name":"Kanes Diner",
    "wof:placetype":"venue"
},
  "geometry": {"coordinates":[-73.832652,40.753274],"type":"Point"}
}