{
  "type": "Feature",
  "properties": {
    "iso:country":"US",
    "sg:address":"668 Wemple Rd",
    "sg:city":"Glenmont",
    "sg:classifiers":[
        {
            "category":"Professional",
            "subcategory":"Lawyer & Legal Services",
            "type":"Services"
        }
    ],
    "sg:phone":"+1 518 462 9350",
    "sg:postcode":"12077",
    "sg:province":"NY",
    "wof:name":"Eastern New York District Counsel",
    "wof:placetype":"venue"
},
  "geometry": {"coordinates":[-73.77359800000001,42.5741],"type":"Point"}
}