{
  "type": "Feature",
  "properties": {
    "addr:full":"2535 Consaul Rd Schenectady NY 12304",
    "addr:postcode":"2535;12304",
    "addr:street":"Consaul Rd",
    "iso:country":"US",
    "sg:address":"2535 Consaul Rd",
    "sg:city":"Schenectady",
    "sg:classifiers":[
        {
            "category":"Organizations",
            "subcategory":"Religious Organization",
            "type":"Services"
        }
    ],
    "sg:phone":"+1   ",
    "sg:postcode":"12304",
    "sg:province":"NY",
    "wof:name":"Church of Nazarene Inc",
    "wof:placetype":"venue"
},
  "geometry": {"coordinates":[-73.903339,42.787057],"type":"Point"}
}