{
  "type": "Feature",
  "properties": {
    "iso:country":"US",
    "sg:address":"146 N Exchange St",
    "sg:city":"Geneva",
    "sg:classifiers":[
        {
            "category":"Retail",
            "subcategory":"Auto Repair",
            "type":"Services"
        }
    ],
    "sg:phone":"+1 315 789 4331",
    "sg:postcode":"14456",
    "sg:province":"NY",
    "sg:tags":[
        "automobile",
        "top",
        "upholstery"
    ],
    "wof:name":"Rancho Upholstery",
    "wof:placetype":"venue"
},
  "geometry": {"coordinates":[-76.978081,42.883513],"type":"Point"}
}