{
  "type": "Feature",
  "properties": {
    "addr:full":"93 Mcmanus Rd S Patterson NY 12563",
    "addr:housenumber":"93",
    "addr:postcode":"12563",
    "addr:street":"Mcmanus Rd",
    "iso:country":"US",
    "sg:address":"93 Mcmanus Rd S",
    "sg:city":"Patterson",
    "sg:classifiers":[
        {
            "category":"Real Estate",
            "subcategory":"Real Estate Agent",
            "type":"Services"
        }
    ],
    "sg:phone":"+1 845 878 7907",
    "sg:postcode":"12563",
    "sg:province":"NY",
    "wof:name":"21 Century Ecommerce.Com, Inc.",
    "wof:placetype":"venue"
},
  "geometry": {"coordinates":[-73.626605,41.466031],"type":"Point"}
}