{
  "type": "Feature",
  "properties": {
    "iso:country":"US",
    "sg:address":"243 88th St",
    "sg:city":"Brooklyn",
    "sg:classifiers":[
        {
            "category":"Social Services",
            "subcategory":"Child Care",
            "type":"Services"
        }
    ],
    "sg:phone":"+1 718 745 4509",
    "sg:postcode":"11209",
    "sg:province":"NY",
    "sg:tags":[
        "day"
    ],
    "wof:name":"Tiny Tot Playhouse",
    "wof:placetype":"venue"
},
  "geometry": {"coordinates":[-74.033897,40.6227],"type":"Point"}
}