{
  "type": "Feature",
  "properties": {
    "addr:full":"410 Dare Rd Selden NY 11784",
    "addr:housenumber":"410",
    "addr:postcode":"11784",
    "addr:street":"Dare Rd",
    "iso:country":"US",
    "sg:address":"410 Dare Rd",
    "sg:city":"Selden",
    "sg:classifiers":[
        {
            "category":"Manufacturing",
            "subcategory":"Printing",
            "type":"Manufacturing & Wholesale Goods"
        }
    ],
    "sg:phone":"+1   ",
    "sg:postcode":"11784",
    "sg:province":"NY",
    "sg:tags":[
        "screen",
        "printer"
    ],
    "wof:name":"Gran Prints Inc",
    "wof:placetype":"venue"
},
  "geometry": {"coordinates":[-73.043482,40.893654],"type":"Point"}
}