{
  "type": "Feature",
  "properties": {
    "iso:country":"US",
    "sg:address":"269 Court St",
    "sg:city":"Brooklyn",
    "sg:classifiers":[
        {
            "category":"Taxi",
            "type":"Transportation"
        }
    ],
    "sg:phone":"+1 718 643 1113",
    "sg:postcode":"11231",
    "sg:province":"NY",
    "sg:tags":[
        "car",
        "limo"
    ],
    "wof:name":"Cobble Hill Car Service",
    "wof:placetype":"venue"
},
  "geometry": {"coordinates":[-73.994598,40.6847],"type":"Point"}
}