{
  "type": "Feature",
  "properties": {
    "iso:country":"US",
    "sg:address":"932 Jericho Tpke",
    "sg:city":"Saint James",
    "sg:classifiers":[
        {
            "category":"Building & Trades",
            "subcategory":"Construction",
            "type":"Services"
        }
    ],
    "sg:phone":"+1 631 897 1116",
    "sg:postcode":"11780",
    "sg:province":"NY",
    "sg:tags":[
        "house",
        "contractor"
    ],
    "wof:name":"Four Seasons N Shore Sun Rooms",
    "wof:placetype":"venue"
},
  "geometry": {"coordinates":[-73.141789,40.861396],"type":"Point"}
}