{
  "type": "Feature",
  "properties": {
    "addr:full":"1 Elizabeth St New York NY 10013",
    "addr:housenumber":"1",
    "addr:postcode":"10013",
    "addr:street":"Elizabeth St",
    "iso:country":"US",
    "sg:address":"1 Elizabeth St",
    "sg:city":"New York",
    "sg:classifiers":[
        {
            "category":"Restaurant",
            "type":"Food & Drink"
        }
    ],
    "sg:menulink":"http://www.allmenus.com/ny/new-york/4715-new-big-wang-restaurant/menu/",
    "sg:phone":"+1 212 219 3686",
    "sg:postcode":"10013",
    "sg:province":"NY",
    "sg:tags":[
        "asian",
        "chinese"
    ],
    "wof:name":"New Big Wang Restaurant",
    "wof:placetype":"venue"
},
  "geometry": {"coordinates":[-73.99768899999999,40.71539],"type":"Point"}
}