{
  "type": "Feature",
  "properties": {
    "iso:country":"US",
    "sg:address":"210 S Westchester Ave",
    "sg:city":"White Plains",
    "sg:classifiers":[
        {
            "category":"Health Services",
            "subcategory":"Health Practitioner",
            "type":"Services"
        }
    ],
    "sg:phone":"+1   ",
    "sg:postcode":"10604",
    "sg:province":"NY",
    "wof:name":"Charles Eubanks Pt",
    "wof:placetype":"venue"
},
  "geometry": {"coordinates":[-73.74991199999999,41.030386],"type":"Point"}
}