{
  "type": "Feature",
  "properties": {
    "addr:full":"338 78th St Brooklyn NY 11209",
    "addr:housenumber":"338",
    "addr:postcode":"11209",
    "addr:street":"78Th St",
    "iso:country":"US",
    "sg:address":"338 78th St",
    "sg:city":"Brooklyn",
    "sg:classifiers":[
        {
            "category":"Health Services",
            "subcategory":"Dentist",
            "type":"Services"
        }
    ],
    "sg:phone":"+1 718 745 2728",
    "sg:postcode":"11209",
    "sg:province":"NY",
    "wof:name":"Mehta Pradeep",
    "wof:placetype":"venue"
},
  "geometry": {"coordinates":[-74.027199,40.628799],"type":"Point"}
}