{
  "type": "Feature",
  "properties": {
    "addr:full":"43 W 46 St New York NY 10036",
    "addr:housenumber":"43",
    "addr:postcode":"10036",
    "addr:street":"W 46 St",
    "iso:country":"US",
    "sg:address":"43 W 46 St",
    "sg:city":"New York",
    "sg:classifiers":[
        {
            "category":"Professional",
            "type":"Services"
        }
    ],
    "sg:phone":"+1 212 921 2503",
    "sg:postcode":"10036",
    "sg:province":"NY",
    "sg:tags":[
        "establishment"
    ],
    "wof:name":"ABM Diamond Corp",
    "wof:placetype":"venue"
},
  "geometry": {"coordinates":[-73.98117000000001,40.756872],"type":"Point"}
}