{
  "type": "Feature",
  "properties": {
    "addr:full":"6650 Myrtle Avenue Glendale NY 11385",
    "addr:housenumber":"6650",
    "addr:postcode":"11385",
    "addr:street":"Myrtle Avenue",
    "iso:country":"US",
    "sg:address":"6650 Myrtle Avenue",
    "sg:city":"Glendale",
    "sg:classifiers":[
        {
            "category":"Banks & Credit Unions",
            "subcategory":"Bank",
            "type":"Services"
        }
    ],
    "sg:phone":"+1 718 366 6422",
    "sg:postcode":"11385",
    "sg:province":"NY",
    "wof:name":"Italo-American Federal Credit Union",
    "wof:placetype":"venue"
},
  "geometry": {"coordinates":[-73.886617,40.70134],"type":"Point"}
}