{
  "type": "Feature",
  "properties": {
    "addr:full":"241 Bedford Ave Brooklyn NY 11211",
    "addr:housenumber":"241",
    "addr:postcode":"11211",
    "addr:street":"Bedford Ave",
    "iso:country":"US",
    "sg:address":"241 Bedford Ave",
    "sg:city":"Brooklyn",
    "sg:classifiers":[
        {
            "category":"Professional",
            "type":"Services"
        }
    ],
    "sg:phone":"+1   ",
    "sg:postcode":"11211",
    "sg:province":"NY",
    "wof:name":"Taradash Studio",
    "wof:placetype":"venue"
},
  "geometry": {"coordinates":[-73.959783,40.715904],"type":"Point"}
}