{
  "type": "Feature",
  "properties": {
    "addr:full":"462 Evans St Williamsville NY 14221",
    "addr:housenumber":"462",
    "addr:postcode":"14221",
    "addr:street":"Evans St",
    "iso:country":"US",
    "sg:address":"462 Evans St",
    "sg:city":"Williamsville",
    "sg:classifiers":[
        {
            "category":"Personal",
            "subcategory":"Beauty Salon",
            "type":"Services"
        }
    ],
    "sg:phone":"+1 716 633 7546",
    "sg:postcode":"14221",
    "sg:province":"NY",
    "wof:name":"Beauty Quest Skin Care & Medi",
    "wof:placetype":"venue"
},
  "geometry": {"coordinates":[-78.739588,42.977416],"type":"Point"}
}