{
  "type": "Feature",
  "properties": {
    "addr:full":"204 Smithtown Blvd Nesconset NY 11767",
    "addr:housenumber":"204",
    "addr:postcode":"11767",
    "addr:street":"Smithtown Blvd",
    "iso:country":"US",
    "sg:address":"204 Smithtown Blvd",
    "sg:city":"Nesconset",
    "sg:classifiers":[
        {
            "category":"Wholesale",
            "subcategory":"Electrical",
            "type":"Manufacturing & Wholesale Goods"
        }
    ],
    "sg:phone":"+1 631 366 4848",
    "sg:postcode":"11767",
    "sg:province":"NY",
    "sg:tags":[
        "communications",
        "retail",
        "equipment"
    ],
    "wof:name":"Dynamic Communications",
    "wof:placetype":"venue"
},
  "geometry": {"coordinates":[-73.15201399999999,40.83536],"type":"Point"}
}