{
  "type": "Feature",
  "properties": {
    "iso:country":"US",
    "sg:address":"75 Troy Rd",
    "sg:city":"East Greenbush",
    "sg:classifiers":[
        {
            "category":"Professional",
            "subcategory":"Accounting & Tax Preparation",
            "type":"Services"
        }
    ],
    "sg:phone":"+1 518 477 1102",
    "sg:postcode":"12061",
    "sg:province":"NY",
    "sg:tags":[
        "accountant"
    ],
    "sg:website":"www.wojeskico.com",
    "wof:name":"Wojeski & Co",
    "wof:placetype":"venue"
},
  "geometry": {"coordinates":[-73.70293700000001,42.613969],"type":"Point"}
}