{
  "type": "Feature",
  "properties": {
    "addr:full":"221 E 122nd St New York NY 10035",
    "addr:housenumber":"221",
    "addr:postcode":"10035",
    "addr:street":"E 122Nd St",
    "iso:country":"US",
    "sg:address":"221 E 122nd St",
    "sg:city":"New York",
    "sg:classifiers":[
        {
            "category":"Social Services",
            "subcategory":"Child Care",
            "type":"Services"
        }
    ],
    "sg:phone":"+1 212 427 6800",
    "sg:postcode":"10035",
    "sg:province":"NY",
    "sg:tags":[
        "day"
    ],
    "wof:name":"Community Life Center Inc",
    "wof:placetype":"venue"
},
  "geometry": {"coordinates":[-73.936798,40.801601],"type":"Point"}
}