{
  "type": "Feature",
  "properties": {
    "addr:full":"76 9th Ave New York NY 10011",
    "addr:housenumber":"76",
    "addr:postcode":"10011",
    "addr:street":"9Th Ave",
    "iso:country":"US",
    "sg:address":"76 9th Ave",
    "sg:city":"New York",
    "sg:classifiers":[
        {
            "category":"Shopping",
            "subcategory":"Clothing, Apparel, & Fashions",
            "type":"Retail Goods"
        }
    ],
    "sg:phone":"+1 212 645 8686",
    "sg:postcode":"10011",
    "sg:province":"NY",
    "sg:tags":[
        "accessory",
        "clothing",
        "women's"
    ],
    "wof:name":"Phi Design Studios",
    "wof:placetype":"venue"
},
  "geometry": {"coordinates":[-74.00457900000001,40.741851],"type":"Point"}
}