{
  "type": "Feature",
  "properties": {
    "iso:country":"US",
    "sg:address":"3250 3rd Ave",
    "sg:city":"Bronx",
    "sg:classifiers":[
        {
            "category":"Health Services",
            "subcategory":"Doctor",
            "type":"Services"
        }
    ],
    "sg:phone":"+1 718 842 6960",
    "sg:postcode":"10456",
    "sg:province":"NY",
    "sg:tags":[
        "dentist"
    ],
    "wof:name":"Vijay Shah DDS",
    "wof:placetype":"venue"
},
  "geometry": {"coordinates":[-73.908444,40.824441],"type":"Point"}
}