{
  "type": "Feature",
  "properties": {
    "iso:country":"US",
    "sg:address":"27 Grove St",
    "sg:city":"New Canaan",
    "sg:classifiers":[
        {
            "category":"Building & Trades",
            "subcategory":"Construction",
            "type":"Services"
        }
    ],
    "sg:phone":"+1 203 966 0726",
    "sg:postcode":"06840",
    "sg:province":"NY",
    "sg:tags":[
        "general",
        "contractor"
    ],
    "sg:website":"www.hobbsinc.com",
    "wof:name":"Hobbs Inc",
    "wof:placetype":"venue"
},
  "geometry": {"coordinates":[-73.499045,41.144908],"type":"Point"}
}