{
  "type": "Feature",
  "properties": {
    "iso:country":"US",
    "sg:address":"241 Pennsylvania Ave",
    "sg:city":"Freeport",
    "sg:classifiers":[
        {
            "category":"Health Services",
            "subcategory":"Doctor",
            "type":"Services"
        }
    ],
    "sg:phone":"+1 516 379 6121",
    "sg:postcode":"11520",
    "sg:province":"NY",
    "sg:tags":[
        "physician",
        "surgeon"
    ],
    "wof:name":"Lester N Ploss Md",
    "wof:placetype":"venue"
},
  "geometry": {"coordinates":[-73.596215,40.664582],"type":"Point"}
}