{
  "type": "Feature",
  "properties": {
    "iso:country":"US",
    "sg:address":"121 Delaware St",
    "sg:city":"Walton",
    "sg:classifiers":[
        {
            "category":"Professional",
            "subcategory":"Lawyer & Legal Services",
            "type":"Services"
        }
    ],
    "sg:phone":"+1 607 865 5050",
    "sg:postcode":"13856",
    "sg:province":"NY",
    "sg:tags":[
        "attorney"
    ],
    "wof:name":"Richard J Thomson",
    "wof:placetype":"venue"
},
  "geometry": {"coordinates":[-75.129603,42.167876],"type":"Point"}
}