{
  "type": "Feature",
  "properties": {
    "iso:country":"US",
    "sg:address":"727 S Crouse Ave",
    "sg:city":"Syracuse",
    "sg:classifiers":[
        {
            "category":"Taxi",
            "type":"Transportation"
        }
    ],
    "sg:phone":"+1 315 478 8000",
    "sg:postcode":"13210",
    "sg:province":"NY",
    "sg:tags":[
        "taxicab"
    ],
    "wof:name":"AAA Carousel Taxi",
    "wof:placetype":"venue"
},
  "geometry": {"coordinates":[-76.136568,43.041879],"type":"Point"}
}