{
  "type": "Feature",
  "properties": {
    "addr:full":"258 W 44th St New York NY 10036",
    "addr:housenumber":"258",
    "addr:postcode":"10036",
    "addr:street":"W 44Th St",
    "iso:country":"US",
    "sg:address":"258 W 44th St",
    "sg:city":"New York",
    "sg:classifiers":[
        {
            "category":"Restaurant",
            "type":"Food & Drink"
        }
    ],
    "sg:menulink":"http://www.allmenus.com/ny/new-york/2936-angus-mcindoe/menu/",
    "sg:phone":"+1 212 221 9222",
    "sg:postcode":"10036",
    "sg:province":"NY",
    "sg:tags":[
        "american"
    ],
    "wof:name":"Angus McIndoe",
    "wof:placetype":"venue"
},
  "geometry": {"coordinates":[-73.988354,40.758324],"type":"Point"}
}