{
  "type": "Feature",
  "properties": {
    "iso:country":"US",
    "sg:address":"29 Locust Ave",
    "sg:city":"Rye",
    "sg:classifiers":[
        {
            "category":"Professional",
            "subcategory":"Computer Services",
            "type":"Services"
        }
    ],
    "sg:phone":"+1 914 967 6932",
    "sg:postcode":"10580",
    "sg:province":"NY",
    "sg:tags":[
        "consultant",
        "designer"
    ],
    "wof:name":"Hi Tech Public Relations",
    "wof:placetype":"venue"
},
  "geometry": {"coordinates":[-73.68704,40.982593],"type":"Point"}
}