{
  "type": "Feature",
  "properties": {
    "iso:country":"US",
    "sg:address":"2045 Rte 112",
    "sg:city":"Coram",
    "sg:classifiers":[
        {
            "category":"Government",
            "subcategory":"Office",
            "type":"Public Place"
        }
    ],
    "sg:phone":"+1 631 736 0783",
    "sg:postcode":"11727",
    "sg:province":"NY",
    "sg:tags":[
        "federal"
    ],
    "wof:name":"US Geological Survey Wrd",
    "wof:placetype":"venue"
},
  "geometry": {"coordinates":[-73.010476,40.880618],"type":"Point"}
}