{
  "type": "Feature",
  "properties": {
    "iso:country":"US",
    "sg:address":"84 Green St",
    "sg:city":"Huntington",
    "sg:classifiers":[
        {
            "category":"Health Services",
            "subcategory":"Dentist",
            "type":"Services"
        }
    ],
    "sg:phone":"+1 631 427 2277",
    "sg:postcode":"11743",
    "sg:province":"NY",
    "wof:name":"Soviero Francis J DDS Ofc",
    "wof:placetype":"venue"
},
  "geometry": {"coordinates":[-73.42800099999999,40.8675],"type":"Point"}
}