{
  "type": "Feature",
  "properties": {
    "iso:country":"US",
    "sg:address":"4368 Grace Ave",
    "sg:city":"Bronx",
    "sg:classifiers":[
        {
            "category":"Communications",
            "type":"Services"
        }
    ],
    "sg:phone":"+1 718 324 7979",
    "sg:postcode":"10466",
    "sg:province":"NY",
    "wof:name":"Greenland Communications",
    "wof:placetype":"venue"
},
  "geometry": {"coordinates":[-73.847269,40.897103],"type":"Point"}
}