{
  "type": "Feature",
  "properties": {
    "addr:full":"310 Main St Holbrook NY 11741",
    "addr:housenumber":"310",
    "addr:postcode":"11741",
    "addr:street":"Main St",
    "iso:country":"US",
    "sg:address":"310 Main St",
    "sg:city":"Holbrook",
    "sg:classifiers":[
        {
            "category":"Professional",
            "type":"Services"
        },
        {
            "category":"Deli",
            "type":"Food & Drink"
        }
    ],
    "sg:phone":"+1 631 467 3737",
    "sg:postcode":"11741",
    "sg:province":"NY",
    "sg:tags":[
        "caterer"
    ],
    "wof:name":"Salad Spoon Deli & Caterers",
    "wof:placetype":"venue"
},
  "geometry": {"coordinates":[-73.074699,40.825901],"type":"Point"}
}