{
  "type": "Feature",
  "properties": {
    "addr:full":"126 E Niagara St Tonawanda NY 14150",
    "addr:housenumber":"126",
    "addr:postcode":"14150",
    "addr:street":"E Niagara St",
    "iso:country":"US",
    "sg:address":"126 E Niagara St",
    "sg:city":"Tonawanda",
    "sg:classifiers":[
        {
            "category":"Building & Trades",
            "subcategory":"Electrical",
            "type":"Services"
        }
    ],
    "sg:phone":"+1 716 692 2832",
    "sg:postcode":"14150",
    "sg:province":"NY",
    "sg:tags":[
        "electrical",
        "electric",
        "contractor"
    ],
    "wof:name":"Advanced Electrical Services",
    "wof:placetype":"venue"
},
  "geometry": {"coordinates":[-78.87109,43.022144],"type":"Point"}
}