{
  "type": "Feature",
  "properties": {
    "addr:full":"20 Chestnut St Centereach NY 11720",
    "addr:housenumber":"20",
    "addr:postcode":"11720",
    "addr:street":"Chestnut St",
    "iso:country":"US",
    "sg:address":"20 Chestnut St",
    "sg:city":"Centereach",
    "sg:classifiers":[
        {
            "category":"Education",
            "subcategory":"School",
            "type":"Public Place"
        }
    ],
    "sg:phone":"+1 631 588 6408",
    "sg:postcode":"11720",
    "sg:province":"NY",
    "sg:tags":[
        "religious"
    ],
    "wof:name":"Assumption School Of Religion",
    "wof:placetype":"venue"
},
  "geometry": {"coordinates":[-73.101613,40.860928],"type":"Point"}
}