{
  "type": "Feature",
  "properties": {
    "iso:country":"US",
    "sg:address":"54 Newton St",
    "sg:city":"Staten Island",
    "sg:classifiers":[
        {
            "category":"Building & Trades",
            "subcategory":"Construction",
            "type":"Services"
        }
    ],
    "sg:phone":"+1 718 317 6453",
    "sg:postcode":"10312",
    "sg:province":"NY",
    "sg:tags":[
        "house"
    ],
    "wof:name":"Caliper Construction Corp",
    "wof:placetype":"venue"
},
  "geometry": {"coordinates":[-74.173895,40.527565],"type":"Point"}
}