{
  "type": "Feature",
  "properties": {
    "addr:full":"3 Ruscitti Rd New Windsor NY 12553",
    "addr:housenumber":"3",
    "addr:postcode":"12553",
    "addr:street":"Ruscitti Rd",
    "iso:country":"US",
    "sg:address":"3 Ruscitti Rd",
    "sg:city":"New Windsor",
    "sg:classifiers":[
        {
            "category":"Wholesale",
            "subcategory":"Electrical",
            "type":"Manufacturing & Wholesale Goods"
        }
    ],
    "sg:phone":"+1 800 223 4534",
    "sg:postcode":"12553",
    "sg:province":"NY",
    "sg:tags":[
        "a",
        "datum",
        "communications",
        "distributor",
        "home",
        "security"
    ],
    "wof:name":"Tristate Telecom Inc",
    "wof:placetype":"venue"
},
  "geometry": {"coordinates":[-74.032387,41.484167],"type":"Point"}
}