{
  "type": "Feature",
  "properties": {
    "addr:full":"360 6 Ave New York NY 10011",
    "addr:housenumber":"360",
    "addr:postcode":"10011",
    "addr:street":"6 Ave",
    "iso:country":"US",
    "sg:address":"360 6 Ave",
    "sg:city":"New York",
    "sg:classifiers":[
        {
            "category":"Manufacturing",
            "subcategory":"Furniture",
            "type":"Manufacturing & Wholesale Goods"
        }
    ],
    "sg:phone":"+1   ",
    "sg:postcode":"10011",
    "sg:province":"NY",
    "sg:tags":[
        "mfg"
    ],
    "wof:name":"Gothic Cabinet Craft Inc",
    "wof:placetype":"venue"
},
  "geometry": {"coordinates":[-74.001413,40.731065],"type":"Point"}
}