{
  "type": "Feature",
  "properties": {
    "addr:full":"1380 Coney Island Ave Brooklyn NY 11230",
    "addr:housenumber":"1380",
    "addr:postcode":"11230",
    "addr:street":"Coney Island Ave",
    "iso:country":"US",
    "sg:address":"1380 Coney Island Ave",
    "sg:city":"Brooklyn",
    "sg:classifiers":[
        {
            "category":"Shopping",
            "subcategory":"Clothing, Apparel, & Fashions",
            "type":"Retail Goods"
        }
    ],
    "sg:phone":"+1   ",
    "sg:postcode":"11230",
    "sg:province":"NY",
    "sg:tags":[
        "ready"
    ],
    "wof:name":"Estelles",
    "wof:placetype":"venue"
},
  "geometry": {"coordinates":[-73.965146,40.624429],"type":"Point"}
}