{
  "type": "Feature",
  "properties": {
    "iso:country":"US",
    "sg:address":"49 Schildbach Rd",
    "sg:city":"Pound Ridge",
    "sg:classifiers":[
        {
            "category":"Wholesale",
            "subcategory":"Seafood",
            "type":"Manufacturing & Wholesale Goods"
        }
    ],
    "sg:phone":"+1 914 234 0302",
    "sg:postcode":"10576",
    "sg:province":"NY",
    "wof:name":"Alba Seafood Inc",
    "wof:placetype":"venue"
},
  "geometry": {"coordinates":[-73.61375,41.238366],"type":"Point"}
}