{
  "type": "Feature",
  "properties": {
    "iso:country":"US",
    "sg:address":"501 S Pearl St",
    "sg:city":"Albany",
    "sg:classifiers":[
        {
            "category":"Building & Trades",
            "subcategory":"Construction",
            "type":"Services"
        }
    ],
    "sg:phone":"+1 518 434 8110",
    "sg:postcode":"12202",
    "sg:province":"NY",
    "sg:tags":[
        "flooring",
        "contractor"
    ],
    "wof:name":"J J Curran & Son Inc",
    "wof:placetype":"venue"
},
  "geometry": {"coordinates":[-73.762021,42.635413],"type":"Point"}
}