{
  "type": "Feature",
  "properties": {
    "iso:country":"US",
    "sg:address":"74 Catherine St",
    "sg:city":"Poughkeepsie",
    "sg:classifiers":[
        {
            "category":"Professional",
            "type":"Services"
        }
    ],
    "sg:phone":"+1 845 485 2450",
    "sg:postcode":"12601",
    "sg:province":"NY",
    "sg:tags":[
        "establishment"
    ],
    "wof:name":"Street Scraper Shop",
    "wof:placetype":"venue"
},
  "geometry": {"coordinates":[-73.92365599999999,41.705801],"type":"Point"}
}