{
  "type": "Feature",
  "properties": {
    "iso:country":"US",
    "sg:address":"1729 Broad Hollow Rd",
    "sg:city":"Farmingdale",
    "sg:classifiers":[
        {
            "category":"Home & Garden",
            "subcategory":"Furniture",
            "type":"Retail Goods"
        }
    ],
    "sg:phone":"+1 631 249 7811",
    "sg:postcode":"11735",
    "sg:province":"NY",
    "wof:name":"Nostalgia Oak Warehouse",
    "wof:placetype":"venue"
},
  "geometry": {"coordinates":[-73.42286300000001,40.740424],"type":"Point"}
}