{
  "type": "Feature",
  "properties": {
    "iso:country":"US",
    "sg:address":"29 California Dr",
    "sg:city":"Buffalo",
    "sg:classifiers":[
        {
            "category":"Professional",
            "subcategory":"Computer Services",
            "type":"Services"
        }
    ],
    "sg:phone":"+1 716 837 4731",
    "sg:postcode":"14221",
    "sg:province":"NY",
    "sg:tags":[
        "graphic"
    ],
    "sg:website":"http://www.yourdot-comsolution.com",
    "wof:name":"Your Dot Com Solution",
    "wof:placetype":"venue"
},
  "geometry": {"coordinates":[-78.750867,42.960751],"type":"Point"}
}