{
  "type": "Feature",
  "properties": {
    "addr:full":"541 E 183rd St Bronx NY 10458",
    "addr:housenumber":"541",
    "addr:postcode":"10458",
    "addr:street":"E 183Rd St",
    "iso:country":"US",
    "sg:address":"541 E 183rd St",
    "sg:city":"Bronx",
    "sg:classifiers":[
        {
            "category":"Shopping",
            "type":"Retail Goods"
        }
    ],
    "sg:phone":"+1 718 933 1200",
    "sg:postcode":"10458",
    "sg:province":"NY",
    "sg:tags":[
        "cosmetic",
        "perfume"
    ],
    "wof:name":"East Side Beauty Supply",
    "wof:placetype":"venue"
},
  "geometry": {"coordinates":[-73.891198,40.854424],"type":"Point"}
}