{
  "type": "Feature",
  "properties": {
    "addr:full":"110 Hudson St New York NY 10013",
    "addr:housenumber":"110",
    "addr:postcode":"10013",
    "addr:street":"Hudson St",
    "iso:country":"US",
    "sg:address":"110 Hudson St",
    "sg:city":"New York",
    "sg:classifiers":[
        {
            "category":"Banks & Credit Unions",
            "subcategory":"Bank",
            "type":"Services"
        }
    ],
    "sg:phone":"+1 212 219 2008",
    "sg:postcode":"10013",
    "sg:province":"NY",
    "wof:name":"Independence Community Bank",
    "wof:placetype":"venue"
},
  "geometry": {"coordinates":[-74.00854200000001,40.719696],"type":"Point"}
}