{
  "type": "Feature",
  "properties": {
    "iso:country":"US",
    "sg:address":"24 Queens Blvd",
    "sg:city":"Forest Hills",
    "sg:classifiers":[
        {
            "category":"Retail",
            "subcategory":"Auto Rental",
            "type":"Services"
        }
    ],
    "sg:phone":"+1 718 793 0900",
    "sg:postcode":"11375",
    "sg:province":"NY",
    "sg:tags":[
        "passenger",
        "car"
    ],
    "wof:name":"Enterprise Rent-A-Car",
    "wof:placetype":"venue"
},
  "geometry": {"coordinates":[-73.84625699999999,40.722453],"type":"Point"}
}