{
  "type": "Feature",
  "properties": {
    "addr:full":"444 Community Dr Manhasset NY 11030",
    "addr:housenumber":"444",
    "addr:postcode":"11030",
    "addr:street":"Community Dr",
    "iso:country":"US",
    "sg:address":"444 Community Dr",
    "sg:city":"Manhasset",
    "sg:classifiers":[
        {
            "category":"Health Services",
            "subcategory":"Doctor",
            "type":"Services"
        }
    ],
    "sg:phone":"+1 516 627 4466",
    "sg:postcode":"11030",
    "sg:province":"NY",
    "sg:tags":[
        "physician",
        "medical",
        "surgeon"
    ],
    "wof:name":"Mickey Chiu MD PC",
    "wof:placetype":"venue"
},
  "geometry": {"coordinates":[-73.70327899999999,40.773415],"type":"Point"}
}