{
  "type": "Feature",
  "properties": {
    "addr:full":"20 Picone Blvd Farmingdale NY 11735",
    "addr:housenumber":"20",
    "addr:postcode":"11735",
    "addr:street":"Picone Blvd",
    "iso:country":"US",
    "sg:address":"20 Picone Blvd",
    "sg:city":"Farmingdale",
    "sg:classifiers":[
        {
            "category":"Wholesale",
            "subcategory":"Home Furnishings",
            "type":"Manufacturing & Wholesale Goods"
        }
    ],
    "sg:phone":"+1 631 249 2626",
    "sg:postcode":"11735",
    "sg:province":"NY",
    "sg:tags":[
        "installs",
        "tile",
        "carpet",
        "floor"
    ],
    "wof:name":"R & D Crpt & Tile Installation",
    "wof:placetype":"venue"
},
  "geometry": {"coordinates":[-73.42193,40.742532],"type":"Point"}
}