{
  "type": "Feature",
  "properties": {
    "iso:country":"US",
    "sg:address":"123 E Seneca St",
    "sg:city":"Manlius",
    "sg:classifiers":[
        {
            "category":"Shopping",
            "subcategory":"Hobbies, Toys, & Games",
            "type":"Retail Goods"
        }
    ],
    "sg:phone":"+1 315 682 0033",
    "sg:postcode":"13104",
    "sg:province":"NY",
    "sg:tags":[
        "product",
        "ceramic"
    ],
    "wof:name":"Village Pottery",
    "wof:placetype":"venue"
},
  "geometry": {"coordinates":[-75.977974,43.001594],"type":"Point"}
}