{
  "type": "Feature",
  "properties": {
    "addr:full":"2418 Johnson Rd Horseheads NY 14845",
    "addr:housenumber":"2418",
    "addr:postcode":"14845",
    "addr:street":"Johnson Rd",
    "iso:country":"US",
    "sg:address":"2418 Johnson Rd",
    "sg:city":"Horseheads",
    "sg:classifiers":[
        {
            "category":"Building & Trades",
            "subcategory":"Construction",
            "type":"Services"
        }
    ],
    "sg:phone":"+1 607 795 1234",
    "sg:postcode":"14845",
    "sg:province":"NY",
    "sg:tags":[
        "general",
        "contractor"
    ],
    "wof:name":"Roy Builders Inc",
    "wof:placetype":"venue"
},
  "geometry": {"coordinates":[-76.809793,42.205378],"type":"Point"}
}