{
  "type": "Feature",
  "properties": {
    "addr:full":"10 Manetto Hill Rd Plainview NY 11803",
    "addr:housenumber":"10",
    "addr:postcode":"11803",
    "addr:street":"Manetto Hill Rd",
    "iso:country":"US",
    "sg:address":"10 Manetto Hill Rd",
    "sg:city":"Plainview",
    "sg:classifiers":[
        {
            "category":"Government",
            "subcategory":"Office",
            "type":"Public Place"
        }
    ],
    "sg:phone":"+1 516 931 6469",
    "sg:postcode":"11803",
    "sg:province":"NY",
    "sg:tags":[
        "water",
        "municipality"
    ],
    "wof:name":"Town of Oyster Bay",
    "wof:placetype":"venue"
},
  "geometry": {"coordinates":[-73.467147,40.776923],"type":"Point"}
}