{
  "type": "Feature",
  "properties": {
    "iso:country":"US",
    "sg:address":"61 Broadway",
    "sg:city":"Brooklyn",
    "sg:classifiers":[
        {
            "category":"Professional",
            "subcategory":"Lawyer & Legal Services",
            "type":"Services"
        }
    ],
    "sg:phone":"+1 718 237 3400",
    "sg:postcode":"11211",
    "sg:province":"NY",
    "wof:name":"Barrett Jane Atty",
    "wof:placetype":"venue"
},
  "geometry": {"coordinates":[-73.96645700000001,40.710707],"type":"Point"}
}