{
  "type": "Feature",
  "properties": {
    "addr:full":"96 14th Street Brooklyn NY 11215",
    "addr:housenumber":"96",
    "addr:postcode":"11215",
    "addr:street":"14Th Street",
    "iso:country":"US",
    "sg:address":"96 14th Street",
    "sg:city":"Brooklyn",
    "sg:classifiers":[
        {
            "category":"Building & Trades",
            "subcategory":"Construction",
            "type":"Services"
        }
    ],
    "sg:phone":"+1 718 768 3600",
    "sg:postcode":"11215",
    "sg:province":"NY",
    "sg:tags":[
        "contractor"
    ],
    "wof:name":"Preserv",
    "wof:placetype":"venue"
},
  "geometry": {"coordinates":[-73.993921,40.668514],"type":"Point"}
}