{
  "type": "Feature",
  "properties": {
    "iso:country":"US",
    "sg:address":"15 Lindbergh St",
    "sg:city":"Locust Valley",
    "sg:classifiers":[
        {
            "category":"Home & Garden",
            "subcategory":"Household Appliances",
            "type":"Retail Goods"
        }
    ],
    "sg:phone":"+1   ",
    "sg:postcode":"11560",
    "sg:province":"NY",
    "sg:tags":[
        "repair",
        "electrical"
    ],
    "wof:name":"Ryder Aplnc Parts & Svce",
    "wof:placetype":"venue"
},
  "geometry": {"coordinates":[-73.59341999999999,40.880993],"type":"Point"}
}