{
  "type": "Feature",
  "properties": {
    "addr:full":"1520 Flatbush Ave Brooklyn NY 11210",
    "addr:housenumber":"1520",
    "addr:postcode":"11210",
    "addr:street":"Flatbush Ave",
    "iso:country":"US",
    "sg:address":"1520 Flatbush Ave",
    "sg:city":"Brooklyn",
    "sg:classifiers":[
        {
            "category":"Shopping",
            "subcategory":"Discount & Variety Stores",
            "type":"Retail Goods"
        }
    ],
    "sg:phone":"+1 718 421 9200",
    "sg:postcode":"11210",
    "sg:province":"NY",
    "sg:tags":[
        "luggage"
    ],
    "wof:name":"Gem Variety Stores",
    "wof:placetype":"venue"
},
  "geometry": {"coordinates":[-73.948601,40.633499],"type":"Point"}
}