{
  "type": "Feature",
  "properties": {
    "addr:full":"745 Columbia St Hudson NY 12534",
    "addr:housenumber":"745",
    "addr:postcode":"12534",
    "addr:street":"Columbia St",
    "iso:country":"US",
    "sg:address":"745 Columbia St",
    "sg:city":"Hudson",
    "sg:classifiers":[
        {
            "category":"Retail",
            "subcategory":"Repair Shop",
            "type":"Services"
        }
    ],
    "sg:phone":"+1   ",
    "sg:postcode":"12534",
    "sg:province":"NY",
    "sg:tags":[
        "equipment"
    ],
    "wof:name":"Hudson Valley Office Equipment",
    "wof:placetype":"venue"
},
  "geometry": {"coordinates":[-73.781201,42.247417],"type":"Point"}
}