{
  "type": "Feature",
  "properties": {
    "iso:country":"US",
    "sg:address":"19 Clinton St",
    "sg:city":"Westfield",
    "sg:classifiers":[
        {
            "category":"Organizations",
            "subcategory":"Community Association",
            "type":"Services"
        }
    ],
    "sg:phone":"+1 716 326 2032",
    "sg:postcode":"14787",
    "sg:province":"NY",
    "sg:tags":[
        "membership"
    ],
    "wof:name":"Moose Fmly Ctr 118 - Wstfield",
    "wof:placetype":"venue"
},
  "geometry": {"coordinates":[-79.57795299999999,42.323505],"type":"Point"}
}