{
  "type": "Feature",
  "properties": {
    "iso:country":"US",
    "sg:address":"100 Ring Rd W",
    "sg:city":"Garden City",
    "sg:classifiers":[
        {
            "category":"Real Estate",
            "subcategory":"Real Estate Agent",
            "type":"Services"
        },
        {
            "category":"Building & Trades",
            "subcategory":"Construction",
            "type":"Services"
        }
    ],
    "sg:phone":"+1 516 248 4920",
    "sg:postcode":"11530",
    "sg:province":"NY",
    "sg:tags":[
        "management",
        "nonresidential"
    ],
    "wof:name":"Anchorage Woods Inc",
    "wof:placetype":"venue"
},
  "geometry": {"coordinates":[-73.61473599999999,40.734232],"type":"Point"}
}