{
  "type": "Feature",
  "properties": {
    "iso:country":"US",
    "sg:address":"253 Regent Dr",
    "sg:city":"Lido Beach",
    "sg:classifiers":[
        {
            "category":"Organizations",
            "subcategory":"Religious Organization",
            "type":"Services"
        }
    ],
    "sg:phone":"+1 516 431 7480",
    "sg:postcode":"11561",
    "sg:province":"NY",
    "sg:tags":[
        "clergy"
    ],
    "wof:name":"Solomon Mendelson",
    "wof:placetype":"venue"
},
  "geometry": {"coordinates":[-73.635604,40.592222],"type":"Point"}
}