{
  "type": "Feature",
  "properties": {
    "addr:full":"139 W Main St Springville NY 14141",
    "addr:housenumber":"139",
    "addr:postcode":"14141",
    "addr:street":"W Main St",
    "iso:country":"US",
    "sg:address":"139 W Main St",
    "sg:city":"Springville",
    "sg:classifiers":[
        {
            "category":"Organizations",
            "subcategory":"Religious Organization",
            "type":"Services"
        }
    ],
    "sg:phone":"+1 716 592 4321",
    "sg:postcode":"14141",
    "sg:province":"NY",
    "sg:tags":[
        "clergy"
    ],
    "wof:name":"Robert W Peck",
    "wof:placetype":"venue"
},
  "geometry": {"coordinates":[-78.67427600000001,42.508937],"type":"Point"}
}