{
  "type": "Feature",
  "properties": {
    "addr:full":"122 E 17th St New York NY 10003",
    "addr:housenumber":"122",
    "addr:postcode":"10003",
    "addr:street":"E 17Th St",
    "iso:country":"US",
    "sg:address":"122 E 17th St",
    "sg:city":"New York",
    "sg:classifiers":[
        {
            "category":"Restaurant",
            "type":"Food & Drink"
        }
    ],
    "sg:phone":"+1 212 475 0969",
    "sg:postcode":"10003",
    "sg:province":"NY",
    "sg:tags":[
        "sushi",
        "bar",
        "japanese"
    ],
    "wof:name":"Yama",
    "wof:placetype":"venue"
},
  "geometry": {"coordinates":[-73.98746,40.73589],"type":"Point"}
}