{
  "type": "Feature",
  "properties": {
    "iso:country":"US",
    "sg:address":"506 Washington St",
    "sg:city":"Ogdensburg",
    "sg:classifiers":[
        {
            "category":"Restaurant",
            "type":"Food & Drink"
        }
    ],
    "sg:phone":"+1 315 394 6216",
    "sg:postcode":"13669",
    "sg:province":"NY",
    "sg:tags":[
        "pizza"
    ],
    "wof:name":"G & D Pizza",
    "wof:placetype":"venue"
},
  "geometry": {"coordinates":[-75.49106999999999,44.699807],"type":"Point"}
}