{
  "type": "Feature",
  "properties": {
    "iso:country":"US",
    "sg:address":"272 Spruce St",
    "sg:city":"North Tonawanda",
    "sg:classifiers":[
        {
            "category":"Shopping",
            "subcategory":"Optical Goods",
            "type":"Retail Goods"
        }
    ],
    "sg:phone":"+1   ",
    "sg:postcode":"14120",
    "sg:province":"NY",
    "sg:tags":[
        "merchandise"
    ],
    "wof:name":"Farino Opticians",
    "wof:placetype":"venue"
},
  "geometry": {"coordinates":[-78.857608,43.029191],"type":"Point"}
}