{
  "type": "Feature",
  "properties": {
    "iso:country":"US",
    "sg:address":"874 Morris Park Ave",
    "sg:city":"Bronx",
    "sg:classifiers":[
        {
            "category":"Professional",
            "subcategory":"Accounting & Tax Preparation",
            "type":"Services"
        }
    ],
    "sg:phone":"+1   ",
    "sg:postcode":"10462",
    "sg:province":"NY",
    "sg:tags":[
        "return"
    ],
    "wof:name":"P&L",
    "wof:placetype":"venue"
},
  "geometry": {"coordinates":[-73.859663,40.846502],"type":"Point"}
}