{
  "type": "Feature",
  "properties": {
    "iso:country":"US",
    "sg:address":"85 Jersey Ave",
    "sg:city":"Port Jervis",
    "sg:classifiers":[
        {
            "category":"Shopping",
            "subcategory":"Used Merchandise",
            "type":"Retail Goods"
        }
    ],
    "sg:phone":"+1 845 856 6122",
    "sg:postcode":"12771",
    "sg:province":"NY",
    "sg:tags":[
        "furniture"
    ],
    "wof:name":"Hodge Podge",
    "wof:placetype":"venue"
},
  "geometry": {"coordinates":[-74.689606,41.370265],"type":"Point"}
}