{
  "type": "Feature",
  "properties": {
    "addr:full":"11 Suffern Pl Suffern NY 10901",
    "addr:housenumber":"11",
    "addr:postcode":"10901",
    "addr:street":"Suffern Pl",
    "iso:country":"US",
    "sg:address":"11 Suffern Pl",
    "sg:city":"Suffern",
    "sg:classifiers":[
        {
            "category":"Wholesale",
            "subcategory":"Medical Equipment & Supplies",
            "type":"Manufacturing & Wholesale Goods"
        }
    ],
    "sg:phone":"+1 845 369 7535",
    "sg:postcode":"10901",
    "sg:province":"NY",
    "sg:tags":[
        "furniture"
    ],
    "sg:website":"www.bluechipmedical.com",
    "wof:name":"Blue Chip Medical Products",
    "wof:placetype":"venue"
},
  "geometry": {"coordinates":[-74.15023100000001,41.11567],"type":"Point"}
}