{
  "type": "Feature",
  "properties": {
    "addr:full":"16 Grand Ave Farmingdale NY 11735",
    "addr:housenumber":"16",
    "addr:postcode":"11735",
    "addr:street":"Grand Ave",
    "iso:country":"US",
    "sg:address":"16 Grand Ave",
    "sg:city":"Farmingdale",
    "sg:classifiers":[
        {
            "category":"Wholesale",
            "subcategory":"Construction Materials",
            "type":"Manufacturing & Wholesale Goods"
        }
    ],
    "sg:phone":"+1 631 755 2420",
    "sg:postcode":"11735",
    "sg:province":"NY",
    "wof:name":"Brer-Four Transportation Corp",
    "wof:placetype":"venue"
},
  "geometry": {"coordinates":[-73.418588,40.713355],"type":"Point"}
}