{
  "type": "Feature",
  "properties": {
    "addr:full":"45 Sams Path Rocky Point NY 11778",
    "addr:housenumber":"45",
    "addr:postcode":"11778",
    "addr:street":"Sams Path",
    "iso:country":"US",
    "sg:address":"45 Sams Path",
    "sg:city":"Rocky Point",
    "sg:classifiers":[
        {
            "category":"Building & Trades",
            "subcategory":"Landscaping Services",
            "type":"Services"
        }
    ],
    "sg:phone":"+1 631 744 3389",
    "sg:postcode":"11778",
    "sg:province":"NY",
    "sg:tags":[
        "landscape"
    ],
    "wof:name":"Js Landscaping",
    "wof:placetype":"venue"
},
  "geometry": {"coordinates":[-72.939987,40.961475],"type":"Point"}
}