{
  "type": "Feature",
  "properties": {
    "addr:full":"236 Main St Poughkeepsie NY 12601",
    "addr:housenumber":"236",
    "addr:postcode":"12601",
    "addr:street":"Main St",
    "iso:country":"US",
    "sg:address":"236 Main St",
    "sg:city":"Poughkeepsie",
    "sg:classifiers":[
        {
            "category":"Government",
            "subcategory":"Court House",
            "type":"Public Place"
        }
    ],
    "sg:phone":"+1 845 486 2300",
    "sg:postcode":"12601",
    "sg:province":"NY",
    "sg:tags":[
        "county",
        "counsel"
    ],
    "sg:website":"www.dutchessworks.com",
    "wof:name":"Dutchess County District Atty",
    "wof:placetype":"venue"
},
  "geometry": {"coordinates":[-73.929687,41.704342],"type":"Point"}
}