{
  "type": "Feature",
  "properties": {
    "iso:country":"US",
    "sg:address":"1 School St",
    "sg:city":"Batavia",
    "sg:classifiers":[
        {
            "category":"Home & Garden",
            "subcategory":"Garden Supply",
            "type":"Retail Goods"
        }
    ],
    "sg:phone":"+1   ",
    "sg:postcode":"14020",
    "sg:province":"NY",
    "sg:tags":[
        "repair",
        "lawnmowers",
        "tractor",
        "bowling"
    ],
    "wof:name":"Mortellaros Sales and Service",
    "wof:placetype":"venue"
},
  "geometry": {"coordinates":[-78.183578,42.996005],"type":"Point"}
}