{
  "type": "Feature",
  "properties": {
    "iso:country":"US",
    "sg:address":"598 New York Ave",
    "sg:city":"Brooklyn",
    "sg:classifiers":[
        {
            "category":"Community Center",
            "type":"Public Place"
        }
    ],
    "sg:phone":"+1 347 663 9403",
    "sg:postcode":"11203",
    "sg:province":"NY",
    "sg:tags":[
        "medical"
    ],
    "wof:name":"Medical Center",
    "wof:placetype":"venue"
},
  "geometry": {"coordinates":[-73.947801,40.659894],"type":"Point"}
}