{
  "type": "Feature",
  "properties": {
    "iso:country":"US",
    "sg:address":"44 Earl Rd",
    "sg:city":"Melville",
    "sg:classifiers":[
        {
            "category":"Health Services",
            "subcategory":"Chiropractor",
            "type":"Services"
        }
    ],
    "sg:phone":"+1 631 421 4177",
    "sg:postcode":"11747",
    "sg:province":"NY",
    "sg:tags":[
        "chiropractic"
    ],
    "wof:name":"Jessica Erario",
    "wof:placetype":"venue"
},
  "geometry": {"coordinates":[-73.39349900000001,40.810175],"type":"Point"}
}