{
  "type": "Feature",
  "properties": {
    "addr:full":"514 E Henrietta Rd Rochester NY 14623",
    "addr:housenumber":"514",
    "addr:postcode":"14623",
    "addr:street":"E Henrietta Rd",
    "iso:country":"US",
    "sg:address":"514 E Henrietta Rd",
    "sg:city":"Rochester",
    "sg:classifiers":[
        {
            "category":"Restaurant",
            "type":"Food & Drink"
        }
    ],
    "sg:menulink":"http://www.allmenus.com/ny/rochester/19569-jtbs/menu/",
    "sg:phone":"+1 585 334 8433",
    "sg:postcode":"14623",
    "sg:province":"NY",
    "sg:tags":[
        "american",
        "pizza"
    ],
    "wof:name":"JTB's",
    "wof:placetype":"venue"
},
  "geometry": {"coordinates":[-77.616106,43.111002],"type":"Point"}
}