{
  "type": "Feature",
  "properties": {
    "addr:full":"55 W 39th St Fl 14 New York NY 10018",
    "addr:housenumber":"55;14",
    "addr:postcode":"10018",
    "addr:street":"W 39Th St Fl",
    "iso:country":"US",
    "sg:address":"55 W 39th St Fl 14",
    "sg:city":"New York",
    "sg:classifiers":[
        {
            "category":"Shopping",
            "subcategory":"Crafts & Fabrics",
            "type":"Retail Goods"
        }
    ],
    "sg:phone":"+1 212 840 1570",
    "sg:postcode":"10018",
    "sg:province":"NY",
    "sg:tags":[
        "store"
    ],
    "wof:name":"Calamo Silk Inc",
    "wof:placetype":"venue"
},
  "geometry": {"coordinates":[-73.98400100000001,40.7523],"type":"Point"}
}