{
  "type": "Feature",
  "properties": {
    "addr:full":"680 Fort Washington Ave New York NY 10040",
    "addr:housenumber":"680",
    "addr:postcode":"10040",
    "addr:street":"Fort Washington Ave",
    "iso:country":"US",
    "sg:address":"680 Fort Washington Ave",
    "sg:city":"New York",
    "sg:classifiers":[
        {
            "category":"Arts & Performance",
            "subcategory":"Theater",
            "type":"Entertainment"
        }
    ],
    "sg:phone":"+1   ",
    "sg:postcode":"10040",
    "sg:province":"NY",
    "sg:tags":[
        "theatrical"
    ],
    "wof:name":"Bulldog Theatre",
    "wof:placetype":"venue"
},
  "geometry": {"coordinates":[-73.936421,40.855255],"type":"Point"}
}