{
  "type": "Feature",
  "properties": {
    "addr:full":"3585 Seneca St Buffalo NY 14224",
    "addr:housenumber":"3585",
    "addr:postcode":"14224",
    "addr:street":"Seneca St",
    "iso:country":"US",
    "sg:address":"3585 Seneca St",
    "sg:city":"Buffalo",
    "sg:classifiers":[
        {
            "category":"Social Services",
            "subcategory":"Child Care",
            "type":"Services"
        }
    ],
    "sg:phone":"+1 716 675 4553",
    "sg:postcode":"14224",
    "sg:province":"NY",
    "sg:tags":[
        "day"
    ],
    "wof:name":"Edukids Inc",
    "wof:placetype":"venue"
},
  "geometry": {"coordinates":[-78.772181,42.829542],"type":"Point"}
}