{
  "type": "Feature",
  "properties": {
    "addr:full":"300 Private Rd East Patchogue NY 11772",
    "addr:housenumber":"300",
    "addr:postcode":"11772",
    "addr:street":"Private Rd",
    "iso:country":"US",
    "sg:address":"300 Private Rd",
    "sg:city":"East Patchogue",
    "sg:classifiers":[
        {
            "category":"Professional",
            "subcategory":"Advertising",
            "type":"Services"
        }
    ],
    "sg:phone":"+1 631 475 7500",
    "sg:postcode":"11772",
    "sg:province":"NY",
    "sg:tags":[
        "mailing",
        "shipping"
    ],
    "wof:name":"Direct Mail Works Inc",
    "wof:placetype":"venue"
},
  "geometry": {"coordinates":[-72.97940699999999,40.753063],"type":"Point"}
}