{
  "type": "Feature",
  "properties": {
    "iso:country":"US",
    "sg:address":"7 Charles St",
    "sg:city":"New York",
    "sg:classifiers":[
        {
            "category":"Professional",
            "subcategory":"Accounting & Tax Preparation",
            "type":"Services"
        }
    ],
    "sg:phone":"+1   ",
    "sg:postcode":"10014",
    "sg:province":"NY",
    "wof:name":"West Village Accountants",
    "wof:placetype":"venue"
},
  "geometry": {"coordinates":[-74.001311,40.735255],"type":"Point"}
}