{
  "type": "Feature",
  "properties": {
    "addr:full":"438 Old Courthouse Rd New Hyde Park NY 11040",
    "addr:housenumber":"438",
    "addr:postcode":"11040",
    "addr:street":"Old Courthouse Rd",
    "iso:country":"US",
    "sg:address":"438 Old Courthouse Rd",
    "sg:city":"New Hyde Park",
    "sg:classifiers":[
        {
            "category":"Building & Trades",
            "subcategory":"Construction",
            "type":"Services"
        }
    ],
    "sg:phone":"+1 516 627 1810",
    "sg:postcode":"11040",
    "sg:province":"NY",
    "sg:tags":[
        "painter"
    ],
    "wof:name":"Aliberti Joseph T",
    "wof:placetype":"venue"
},
  "geometry": {"coordinates":[-73.684799,40.761902],"type":"Point"}
}