{
  "type": "Feature",
  "properties": {
    "addr:full":"7409 37th Ave Jackson Heights NY 11372",
    "addr:housenumber":"7409",
    "addr:postcode":"11372",
    "addr:street":"37Th Ave",
    "iso:country":"US",
    "sg:address":"7409 37th Ave",
    "sg:city":"Jackson Heights",
    "sg:classifiers":[
        {
            "category":"Professional",
            "subcategory":"Lawyer & Legal Services",
            "type":"Services"
        }
    ],
    "sg:phone":"+1 718 533 8620",
    "sg:postcode":"11372",
    "sg:province":"NY",
    "wof:name":"Chawla M S Atty",
    "wof:placetype":"venue"
},
  "geometry": {"coordinates":[-73.891701,40.749001],"type":"Point"}
}