{
  "type": "Feature",
  "properties": {
    "iso:country":"US",
    "sg:address":"112 Dorchester Rd",
    "sg:city":"Lake Ronkonkoma",
    "sg:classifiers":[
        {
            "category":"Building & Trades",
            "subcategory":"Electrical",
            "type":"Services"
        }
    ],
    "sg:phone":"+1 631 585 6126",
    "sg:postcode":"11779",
    "sg:province":"NY",
    "sg:tags":[
        "electric",
        "contractor"
    ],
    "wof:name":"BME Svc Inc",
    "wof:placetype":"venue"
},
  "geometry": {"coordinates":[-73.101732,40.847645],"type":"Point"}
}