{
  "type": "Feature",
  "properties": {
    "addr:full":"12 Whitwell Pl Brooklyn NY 11215",
    "addr:housenumber":"12",
    "addr:postcode":"11215",
    "addr:street":"Whitwell Pl",
    "iso:country":"US",
    "sg:address":"12 Whitwell Pl",
    "sg:city":"Brooklyn",
    "sg:classifiers":[
        {
            "category":"Professional",
            "subcategory":"Research",
            "type":"Services"
        }
    ],
    "sg:phone":"+1 718 237 8823",
    "sg:postcode":"11215",
    "sg:province":"NY",
    "sg:tags":[
        "nonphysical",
        "commercial"
    ],
    "wof:name":"Shieh & Radka",
    "wof:placetype":"venue"
},
  "geometry": {"coordinates":[-73.98611,40.676239],"type":"Point"}
}