{
  "type": "Feature",
  "properties": {
    "iso:country":"US",
    "sg:address":"1980 Riff Rd",
    "sg:city":"Corning",
    "sg:classifiers":[
        {
            "category":"Wholesale",
            "subcategory":"Construction Materials",
            "type":"Manufacturing & Wholesale Goods"
        }
    ],
    "sg:phone":"+1 607 936 0610",
    "sg:postcode":"14830",
    "sg:province":"NY",
    "sg:tags":[
        "fence"
    ],
    "wof:name":"Lee S Kosow Metal Artist",
    "wof:placetype":"venue"
},
  "geometry": {"coordinates":[-77.038922,42.093566],"type":"Point"}
}