{
  "type": "Feature",
  "properties": {
    "addr:full":"5801 Sunrise Hwy Holbrook NY 11741",
    "addr:housenumber":"5801",
    "addr:postcode":"11741",
    "addr:street":"Sunrise Hwy",
    "iso:country":"US",
    "sg:address":"5801 Sunrise Hwy",
    "sg:city":"Holbrook",
    "sg:classifiers":[
        {
            "category":"Restaurant",
            "type":"Food & Drink"
        }
    ],
    "sg:phone":"+1   ",
    "sg:postcode":"11741",
    "sg:province":"NY",
    "sg:tags":[
        "parlor",
        "pizza"
    ],
    "wof:name":"Aegean Pizza Restaurant",
    "wof:placetype":"venue"
},
  "geometry": {"coordinates":[-73.061604,40.769076],"type":"Point"}
}