{
  "type": "Feature",
  "properties": {
    "iso:country":"US",
    "sg:address":"382 Metropolitan Ave",
    "sg:city":"Brooklyn",
    "sg:classifiers":[
        {
            "category":"Restaurant",
            "type":"Food & Drink"
        },
        {
            "category":"Bakery",
            "type":"Food & Drink"
        }
    ],
    "sg:postcode":"11211",
    "sg:province":"NY",
    "sg:tags":[
        "fusion",
        "asian"
    ],
    "sg:website":"www.momofuku.com/milk-bar/",
    "wof:name":"Momofuku Milk Bar",
    "wof:placetype":"venue"
},
  "geometry": {"coordinates":[-73.955399,40.713596],"type":"Point"}
}