{
  "type": "Feature",
  "properties": {
    "addr:full":"816 Forest Ave Staten Island NY 10310",
    "addr:housenumber":"816",
    "addr:postcode":"10310",
    "addr:street":"Forest Ave",
    "iso:country":"US",
    "sg:address":"816 Forest Ave",
    "sg:city":"Staten Island",
    "sg:classifiers":[
        {
            "category":"Shopping",
            "subcategory":"Bicycles & Sporting Goods",
            "type":"Retail Goods"
        }
    ],
    "sg:phone":"+1 718 447 7511",
    "sg:postcode":"10310",
    "sg:province":"NY",
    "sg:tags":[
        "equipment",
        "arts",
        "supply",
        "martial"
    ],
    "wof:name":"Nieves Karate Club",
    "wof:placetype":"venue"
},
  "geometry": {"coordinates":[-74.11867100000001,40.628668],"type":"Point"}
}