{
  "type": "Feature",
  "properties": {
    "iso:country":"US",
    "sg:address":"2520 8th Ave",
    "sg:city":"New York",
    "sg:classifiers":[
        {
            "category":"Personal",
            "subcategory":"Beauty Salon",
            "type":"Services"
        }
    ],
    "sg:phone":"+1 212 234 6664",
    "sg:postcode":"10030",
    "sg:province":"NY",
    "wof:name":"Mali Hair Braiding",
    "wof:placetype":"venue"
},
  "geometry": {"coordinates":[-73.946651,40.816156],"type":"Point"}
}