{
  "type": "Feature",
  "properties": {
    "iso:country":"US",
    "sg:address":"103 Squashville Rd",
    "sg:city":"Greenfield Center",
    "sg:classifiers":[
        {
            "category":"Health Services",
            "subcategory":"Doctor",
            "type":"Services"
        }
    ],
    "sg:phone":"+1   ",
    "sg:postcode":"12833",
    "sg:province":"NY",
    "sg:tags":[
        "medical"
    ],
    "wof:name":"Elliot-Bearce Assocs Cswtc",
    "wof:placetype":"venue"
},
  "geometry": {"coordinates":[-73.87787299999999,43.128908],"type":"Point"}
}