{
  "type": "Feature",
  "properties": {
    "iso:country":"US",
    "sg:address":"51 Astor Pl",
    "sg:city":"New York",
    "sg:classifiers":[
        {
            "category":"Education",
            "subcategory":"University",
            "type":"Public Place"
        }
    ],
    "sg:phone":"+1 212 353 4100",
    "sg:postcode":"10003",
    "sg:province":"NY",
    "sg:tags":[
        "college"
    ],
    "wof:name":"Cooper Union For the Advancement of Science & Art",
    "wof:placetype":"venue"
},
  "geometry": {"coordinates":[-73.98987099999999,40.729562],"type":"Point"}
}