{
  "type": "Feature",
  "properties": {
    "iso:country":"US",
    "sg:address":"745 Heim Rd",
    "sg:city":"Getzville",
    "sg:classifiers":[
        {
            "category":"Education",
            "subcategory":"School",
            "type":"Public Place"
        }
    ],
    "sg:phone":"+1 716 689 6050",
    "sg:postcode":"14068",
    "sg:province":"NY",
    "wof:name":"Universal Academy",
    "wof:placetype":"venue"
},
  "geometry": {"coordinates":[-78.743554,43.021498],"type":"Point"}
}