{
  "type": "Feature",
  "properties": {
    "addr:full":"220 E 25 St New York NY 10010",
    "addr:housenumber":"220;25",
    "addr:postcode":"10010",
    "addr:street":"E;St",
    "iso:country":"US",
    "sg:address":"220 E 25 St",
    "sg:city":"New York",
    "sg:classifiers":[
        {
            "category":"Professional",
            "type":"Services"
        }
    ],
    "sg:phone":"+1 212 696 9123",
    "sg:postcode":"10010",
    "sg:province":"NY",
    "sg:tags":[
        "establishment"
    ],
    "wof:name":"Ata Enterprises",
    "wof:placetype":"venue"
},
  "geometry": {"coordinates":[-73.98035,40.739296],"type":"Point"}
}