{
  "type": "Feature",
  "properties": {
    "addr:full":"3649 31st Street Astoria NY 11106",
    "addr:housenumber":"3649",
    "addr:postcode":"11106",
    "addr:street":"31St Street",
    "iso:country":"US",
    "sg:address":"3649 31st Street",
    "sg:city":"Astoria",
    "sg:classifiers":[
        {
            "category":"Retail",
            "subcategory":"Auto Rental",
            "type":"Services"
        }
    ],
    "sg:phone":"+1 718 472 5200",
    "sg:postcode":"11106",
    "sg:province":"NY",
    "sg:tags":[
        "car"
    ],
    "wof:name":"Enterprise Rent-A-Car",
    "wof:placetype":"venue"
},
  "geometry": {"coordinates":[-73.930781,40.755103],"type":"Point"}
}