{
  "type": "Feature",
  "properties": {
    "addr:full":"240 Lucille Ave Elmont NY 11003",
    "addr:housenumber":"240",
    "addr:postcode":"11003",
    "addr:street":"Lucille Ave",
    "iso:country":"US",
    "sg:address":"240 Lucille Ave",
    "sg:city":"Elmont",
    "sg:classifiers":[
        {
            "category":"Building & Trades",
            "subcategory":"Construction",
            "type":"Services"
        }
    ],
    "sg:phone":"+1 516 616 0127",
    "sg:postcode":"11003",
    "sg:province":"NY",
    "sg:tags":[
        "swimming",
        "pool",
        "contractor"
    ],
    "wof:name":"J & P Swimming Pools",
    "wof:placetype":"venue"
},
  "geometry": {"coordinates":[-73.685169,40.701183],"type":"Point"}
}