{
  "type": "Feature",
  "properties": {
    "addr:full":"3415 Broadway Astoria NY 11106",
    "addr:housenumber":"3415",
    "addr:postcode":"11106",
    "addr:street":"Broadway",
    "iso:country":"US",
    "sg:address":"3415 Broadway",
    "sg:city":"Astoria",
    "sg:classifiers":[
        {
            "category":"Restaurant",
            "type":"Food & Drink"
        }
    ],
    "sg:phone":"+1 718 728 7522",
    "sg:postcode":"11106",
    "sg:province":"NY",
    "sg:tags":[
        "italian",
        "pizza"
    ],
    "sg:website":"bartolinosastoria.com",
    "wof:name":"Bartolino's Restaurant",
    "wof:placetype":"venue"
},
  "geometry": {"coordinates":[-73.922203,40.760601],"type":"Point"}
}