{
  "type": "Feature",
  "properties": {
    "iso:country":"US",
    "sg:address":"807 W Beech St",
    "sg:city":"Long Beach",
    "sg:classifiers":[
        {
            "category":"Retail",
            "subcategory":"Self-service Laundry",
            "type":"Services"
        }
    ],
    "sg:phone":"+1   ",
    "sg:postcode":"11561",
    "sg:province":"NY",
    "sg:tags":[
        "coin",
        "laundromat"
    ],
    "wof:name":"East End Laundromat",
    "wof:placetype":"venue"
},
  "geometry": {"coordinates":[-73.68803200000001,40.586023],"type":"Point"}
}