{
  "type": "Feature",
  "properties": {
    "iso:country":"US",
    "sg:address":"196 Bergen St",
    "sg:city":"Brooklyn",
    "sg:classifiers":[
        {
            "category":"Restaurant",
            "type":"Food & Drink"
        }
    ],
    "sg:phone":"+1   ",
    "sg:postcode":"11217",
    "sg:province":"NY",
    "sg:tags":[
        "grocery",
        "eating"
    ],
    "wof:name":"Elberih Deli",
    "wof:placetype":"venue"
},
  "geometry": {"coordinates":[-73.983953,40.684182],"type":"Point"}
}