{
  "type": "Feature",
  "properties": {
    "addr:full":"640 Hawkins Ave Ronkonkoma NY 11779",
    "addr:housenumber":"640",
    "addr:postcode":"11779",
    "addr:street":"Hawkins Ave",
    "iso:country":"US",
    "sg:address":"640 Hawkins Ave",
    "sg:city":"Ronkonkoma",
    "sg:classifiers":[
        {
            "category":"Health Services",
            "subcategory":"Doctor",
            "type":"Services"
        }
    ],
    "sg:phone":"+1 631 737 0100",
    "sg:postcode":"11779",
    "sg:province":"NY",
    "wof:name":"East Nassau Medical Group",
    "wof:placetype":"venue"
},
  "geometry": {"coordinates":[-73.108704,40.833199],"type":"Point"}
}