{
  "type": "Feature",
  "properties": {
    "addr:full":"13 W 36th St New York NY 10018",
    "addr:housenumber":"13",
    "addr:postcode":"10018",
    "addr:street":"W 36Th St",
    "iso:country":"US",
    "sg:address":"13 W 36th St",
    "sg:city":"New York",
    "sg:classifiers":[
        {
            "category":"Museum",
            "type":"Entertainment"
        }
    ],
    "sg:phone":"+1 212 736 3336",
    "sg:postcode":"10018",
    "sg:province":"NY",
    "wof:name":"Manhattan Art",
    "wof:placetype":"venue"
},
  "geometry": {"coordinates":[-73.9841,40.75],"type":"Point"}
}