{
  "type": "Feature",
  "properties": {
    "addr:full":"2775 Broadway St Buffalo NY 14227",
    "addr:housenumber":"2775",
    "addr:postcode":"14227",
    "addr:street":"Broadway St",
    "iso:country":"US",
    "sg:address":"2775 Broadway St",
    "sg:city":"Buffalo",
    "sg:classifiers":[
        {
            "category":"Professional",
            "subcategory":"Business Services",
            "type":"Services"
        }
    ],
    "sg:phone":"+1 716 894 4360",
    "sg:postcode":"14227",
    "sg:province":"NY",
    "sg:tags":[
        "cylinder",
        "processing",
        "gas",
        "plant"
    ],
    "wof:name":"Nellcor Puritan Bennett",
    "wof:placetype":"venue"
},
  "geometry": {"coordinates":[-78.772127,42.90175],"type":"Point"}
}