{
  "type": "Feature",
  "properties": {
    "iso:country":"US",
    "sg:address":"865 W Jericho Tpke",
    "sg:city":"Smithtown",
    "sg:classifiers":[
        {
            "category":"Building & Trades",
            "subcategory":"Equipment Rental",
            "type":"Services"
        }
    ],
    "sg:phone":"+1 631 864 6464",
    "sg:postcode":"11787",
    "sg:province":"NY",
    "sg:tags":[
        "contractor"
    ],
    "sg:website":"www.truckloadersny.com",
    "wof:name":"Truckloaders",
    "wof:placetype":"venue"
},
  "geometry": {"coordinates":[-73.24907399999999,40.848165],"type":"Point"}
}