{
  "type": "Feature",
  "properties": {
    "iso:country":"US",
    "sg:address":"35 Main St",
    "sg:city":"Hornell",
    "sg:classifiers":[
        {
            "category":"Restaurant",
            "type":"Food & Drink"
        }
    ],
    "sg:phone":"+1 607 324 5750",
    "sg:postcode":"14843",
    "sg:province":"NY",
    "sg:tags":[
        "chinese"
    ],
    "wof:name":"Super Wok",
    "wof:placetype":"venue"
},
  "geometry": {"coordinates":[-77.66316999999999,42.328192],"type":"Point"}
}