{
  "type": "Feature",
  "properties": {
    "addr:full":"689 Morris Park Ave Bronx NY 10462",
    "addr:housenumber":"689",
    "addr:postcode":"10462",
    "addr:street":"Morris Park Ave",
    "iso:country":"US",
    "sg:address":"689 Morris Park Ave",
    "sg:city":"Bronx",
    "sg:classifiers":[
        {
            "category":"Banks & Credit Unions",
            "subcategory":"Bank",
            "type":"Services"
        }
    ],
    "sg:phone":"+1 718 239 0833",
    "sg:postcode":"10462",
    "sg:province":"NY",
    "sg:tags":[
        "cashing",
        "check"
    ],
    "wof:name":"Cortlandt Checking Corp",
    "wof:placetype":"venue"
},
  "geometry": {"coordinates":[-73.866474,40.845203],"type":"Point"}
}