{
  "type": "Feature",
  "properties": {
    "addr:full":"734 Broadway New York NY 10003",
    "addr:housenumber":"734",
    "addr:postcode":"10003",
    "addr:street":"Broadway",
    "iso:country":"US",
    "sg:address":"734 Broadway",
    "sg:city":"New York",
    "sg:classifiers":[
        {
            "category":"Retail",
            "subcategory":"Auto Repair",
            "type":"Services"
        }
    ],
    "sg:phone":"+1 212 792 0711",
    "sg:postcode":"10003",
    "sg:province":"NY",
    "sg:tags":[
        "wrecker"
    ],
    "wof:name":"7 Days 24 Hour Towing",
    "wof:placetype":"venue"
},
  "geometry": {"coordinates":[-73.992831,40.729955],"type":"Point"}
}