{
  "type": "Feature",
  "properties": {
    "addr:full":"49 Castor Pl Staten Island NY 10312",
    "addr:housenumber":"49",
    "addr:postcode":"10312",
    "addr:street":"Castor Pl",
    "iso:country":"US",
    "sg:address":"49 Castor Pl",
    "sg:city":"Staten Island",
    "sg:classifiers":[
        {
            "category":"Shopping",
            "subcategory":"Clothing, Apparel, & Fashions",
            "type":"Retail Goods"
        }
    ],
    "sg:phone":"+1 516 794 1816",
    "sg:postcode":"10312",
    "sg:province":"NY",
    "sg:tags":[
        "shop",
        "bridal"
    ],
    "wof:name":"Bridal Affair To Remember",
    "wof:placetype":"venue"
},
  "geometry": {"coordinates":[-74.197607,40.545673],"type":"Point"}
}