{
  "type": "Feature",
  "properties": {
    "addr:full":"13 Catherine St Nyack NY 10960",
    "addr:housenumber":"13",
    "addr:postcode":"10960",
    "addr:street":"Catherine St",
    "iso:country":"US",
    "sg:address":"13 Catherine St",
    "sg:city":"Nyack",
    "sg:classifiers":[
        {
            "category":"Shopping",
            "subcategory":"Jewelry",
            "type":"Retail Goods"
        }
    ],
    "sg:phone":"+1 845 348 7748",
    "sg:postcode":"10960",
    "sg:province":"NY",
    "sg:tags":[
        "jeweler"
    ],
    "wof:name":"Timeless Treasures Group",
    "wof:placetype":"venue"
},
  "geometry": {"coordinates":[-73.92388200000001,41.092237],"type":"Point"}
}