{
  "type": "Feature",
  "properties": {
    "iso:country":"US",
    "sg:address":"87 Ellis St",
    "sg:city":"Staten Island",
    "sg:classifiers":[
        {
            "category":"Building & Trades",
            "subcategory":"Construction",
            "type":"Services"
        }
    ],
    "sg:phone":"+1 718 605 0910",
    "sg:postcode":"10307",
    "sg:province":"NY",
    "sg:tags":[
        "contractor"
    ],
    "sg:website":"www.amtotal.com",
    "wof:name":"A & M TOTAL",
    "wof:placetype":"venue"
},
  "geometry": {"coordinates":[-74.24253,40.516758],"type":"Point"}
}