{
  "type": "Feature",
  "properties": {
    "addr:full":"2328 Browncroft Blvd Rochester NY 14625",
    "addr:housenumber":"2328",
    "addr:postcode":"14625",
    "addr:street":"Browncroft Blvd",
    "iso:country":"US",
    "sg:address":"2328 Browncroft Blvd",
    "sg:city":"Rochester",
    "sg:classifiers":[
        {
            "category":"Restaurant",
            "type":"Food & Drink"
        }
    ],
    "sg:phone":"+1 585 473 1330",
    "sg:postcode":"14625",
    "sg:province":"NY",
    "sg:website":"www.creativecaterers.com",
    "wof:name":"Creative Caterers",
    "wof:placetype":"venue"
},
  "geometry": {"coordinates":[-77.52230299999999,43.155683],"type":"Point"}
}