{
  "type": "Feature",
  "properties": {
    "addr:full":"63 Wall St New York NY 10005",
    "addr:housenumber":"63",
    "addr:postcode":"10005",
    "addr:street":"Wall St",
    "iso:country":"US",
    "sg:address":"63 Wall St",
    "sg:city":"New York",
    "sg:classifiers":[
        {
            "category":"Professional",
            "subcategory":"Business Services",
            "type":"Services"
        },
        {
            "category":"Professional",
            "subcategory":"Employment Agencies",
            "type":"Services"
        }
    ],
    "sg:phone":"+1 212 248 1113",
    "sg:postcode":"10005",
    "sg:province":"NY",
    "sg:tags":[
        "information",
        "executive",
        "placement",
        "referral"
    ],
    "wof:name":"Colton Information Technology",
    "wof:placetype":"venue"
},
  "geometry": {"coordinates":[-74.008138,40.705588],"type":"Point"}
}