{
  "type": "Feature",
  "properties": {
    "addr:full":"1821 Penfield Rd Penfield NY 14526",
    "addr:housenumber":"1821",
    "addr:postcode":"14526",
    "addr:street":"Penfield Rd",
    "iso:country":"US",
    "sg:address":"1821 Penfield Rd",
    "sg:city":"Penfield",
    "sg:classifiers":[
        {
            "category":"Shopping",
            "subcategory":"Clothing, Apparel, & Fashions",
            "type":"Retail Goods"
        }
    ],
    "sg:phone":"+1   ",
    "sg:postcode":"14526",
    "sg:province":"NY",
    "sg:website":"www.tuxedopark.com",
    "wof:name":"Tuxedo Park",
    "wof:placetype":"venue"
},
  "geometry": {"coordinates":[-77.480082,43.128985],"type":"Point"}
}