{
  "type": "Feature",
  "properties": {
    "iso:country":"US",
    "sg:address":"3 Salem Ct",
    "sg:city":"Suffern",
    "sg:classifiers":[
        {
            "category":"Real Estate",
            "subcategory":"Real Estate Agent",
            "type":"Services"
        }
    ],
    "sg:phone":"+1 845 357 3348",
    "sg:postcode":"10901",
    "sg:province":"NY",
    "wof:name":"Nadasdi Corp",
    "wof:placetype":"venue"
},
  "geometry": {"coordinates":[-74.133374,41.102516],"type":"Point"}
}