{
  "type": "Feature",
  "properties": {
    "addr:full":"1489 Broadway Rensselaer NY 12144",
    "addr:housenumber":"1489",
    "addr:postcode":"12144",
    "addr:street":"Broadway",
    "iso:country":"US",
    "sg:address":"1489 Broadway",
    "sg:city":"Rensselaer",
    "sg:classifiers":[
        {
            "category":"Wholesale",
            "subcategory":"Computers",
            "type":"Manufacturing & Wholesale Goods"
        },
        {
            "category":"Shopping",
            "subcategory":"Used Merchandise",
            "type":"Retail Goods"
        },
        {
            "category":"Retail",
            "subcategory":"Repair Shop",
            "type":"Services"
        },
        {
            "category":"Professional",
            "subcategory":"Computer Services",
            "type":"Services"
        }
    ],
    "sg:phone":"+1 518 434 8193",
    "sg:postcode":"12144",
    "sg:province":"NY",
    "sg:tags":[
        "repair-business",
        "equipment-service",
        "data",
        "recovery",
        "equipment"
    ],
    "sg:website":"http://www.npbcomputers.com",
    "wof:name":"NPB Computers",
    "wof:placetype":"venue"
},
  "geometry": {"coordinates":[-73.73528,42.654834],"type":"Point"}
}