{
  "type": "Feature",
  "properties": {
    "iso:country":"US",
    "sg:address":"10 Technology Dr",
    "sg:city":"East Setauket",
    "sg:classifiers":[
        {
            "category":"Retail",
            "subcategory":"Laundry & Dry Cleaning",
            "type":"Services"
        }
    ],
    "sg:phone":"+1 631 689 0204",
    "sg:postcode":"11733",
    "sg:province":"NY",
    "sg:tags":[
        "cleaners",
        "rug",
        "carpet"
    ],
    "wof:name":"Mr Wizard Carpet Cleaning",
    "wof:placetype":"venue"
},
  "geometry": {"coordinates":[-73.086333,40.89853],"type":"Point"}
}