{
  "type": "Feature",
  "properties": {
    "addr:full":"447 Craig Ave Staten Island NY 10307",
    "addr:housenumber":"447",
    "addr:postcode":"10307",
    "addr:street":"Craig Ave",
    "iso:country":"US",
    "sg:address":"447 Craig Ave",
    "sg:city":"Staten Island",
    "sg:classifiers":[
        {
            "category":"Professional",
            "subcategory":"Accounting & Tax Preparation",
            "type":"Services"
        }
    ],
    "sg:phone":"+1   ",
    "sg:postcode":"10307",
    "sg:province":"NY",
    "wof:name":"Philip T Matthews",
    "wof:placetype":"venue"
},
  "geometry": {"coordinates":[-74.249121,40.510272],"type":"Point"}
}