{
  "type": "Feature",
  "properties": {
    "iso:country":"US",
    "sg:address":"2 Washington St",
    "sg:city":"Newburgh",
    "sg:classifiers":[
        {
            "category":"Restaurant",
            "type":"Food & Drink"
        }
    ],
    "sg:phone":"+1 845 561 2637",
    "sg:postcode":"12550",
    "sg:province":"NY",
    "wof:name":"Gully's Restaurant",
    "wof:placetype":"venue"
},
  "geometry": {"coordinates":[-74.00591300000001,41.498009],"type":"Point"}
}