{
  "type": "Feature",
  "properties": {
    "addr:full":"267 Sycamore St Buffalo NY 14204",
    "addr:housenumber":"267",
    "addr:postcode":"14204",
    "addr:street":"Sycamore St",
    "iso:country":"US",
    "sg:address":"267 Sycamore St",
    "sg:city":"Buffalo",
    "sg:classifiers":[
        {
            "category":"Organizations",
            "subcategory":"Religious Organization",
            "type":"Services"
        }
    ],
    "sg:phone":"+1 716 854 4651",
    "sg:postcode":"14204",
    "sg:province":"NY",
    "sg:tags":[
        "church"
    ],
    "wof:name":"Temple Of Divine Science",
    "wof:placetype":"venue"
},
  "geometry": {"coordinates":[-78.86003100000001,42.890966],"type":"Point"}
}