{
  "type": "Feature",
  "properties": {
    "iso:country":"US",
    "sg:address":"109 Lattingtown Rd",
    "sg:city":"Glen Cove",
    "sg:classifiers":[
        {
            "category":"Cafe",
            "type":"Food & Drink"
        }
    ],
    "sg:menulink":"http://www.allmenus.com/ny/glen-cove/275271-soundview-cafe/menu/",
    "sg:phone":"+1 516 676 9781",
    "sg:postcode":"11542",
    "sg:province":"NY",
    "sg:tags":[
        "american"
    ],
    "wof:name":"Soundview Cafe",
    "wof:placetype":"venue"
},
  "geometry": {"coordinates":[-73.623823,40.889792],"type":"Point"}
}