{
  "type": "Feature",
  "properties": {
    "addr:full":"159 W 53 St New York NY 10019",
    "addr:housenumber":"159",
    "addr:postcode":"10019",
    "addr:street":"W 53 St",
    "iso:country":"US",
    "sg:address":"159 W 53 St",
    "sg:city":"New York",
    "sg:classifiers":[
        {
            "category":"Utilities",
            "subcategory":"Telephone",
            "type":"Services"
        }
    ],
    "sg:phone":"+1   ",
    "sg:postcode":"10019",
    "sg:province":"NY",
    "sg:tags":[
        "derivative",
        "market",
        "for",
        "equity"
    ],
    "wof:name":"Strumarc",
    "wof:placetype":"venue"
},
  "geometry": {"coordinates":[-73.981244,40.762691],"type":"Point"}
}