{
  "type": "Feature",
  "properties": {
    "addr:full":"126 S Port Rd Albany NY 12202",
    "addr:housenumber":"126",
    "addr:postcode":"12202",
    "addr:street":"S Port Rd",
    "iso:country":"US",
    "sg:address":"126 S Port Rd",
    "sg:city":"Albany",
    "sg:classifiers":[
        {
            "category":"Manufacturing",
            "subcategory":"Metals",
            "type":"Manufacturing & Wholesale Goods"
        }
    ],
    "sg:phone":"+1 518 465 6221",
    "sg:postcode":"12202",
    "sg:province":"NY",
    "sg:tags":[
        "steel",
        "consulting",
        "management",
        "mfg",
        "metalwork",
        "structural"
    ],
    "sg:website":"www.barker.com",
    "wof:name":"Barker Steel Co",
    "wof:placetype":"venue"
},
  "geometry": {"coordinates":[-73.764481,42.621108],"type":"Point"}
}