{
  "type": "Feature",
  "properties": {
    "addr:full":"177 W 73 St New York NY 10023",
    "addr:housenumber":"177",
    "addr:postcode":"10023",
    "addr:street":"W 73 St",
    "iso:country":"US",
    "sg:address":"177 W 73 St",
    "sg:city":"New York",
    "sg:classifiers":[
        {
            "category":"Parking",
            "type":"Transportation"
        }
    ],
    "sg:phone":"+1 212 288 1798",
    "sg:postcode":"10023",
    "sg:province":"NY",
    "sg:tags":[
        "automobile"
    ],
    "wof:name":"Townhouse Garage",
    "wof:placetype":"venue"
},
  "geometry": {"coordinates":[-73.97942999999999,40.778429],"type":"Point"}
}