{
  "type": "Feature",
  "properties": {
    "iso:country":"US",
    "sg:address":"212 Turkey Hill Rd",
    "sg:city":"Ithaca",
    "sg:classifiers":[
        {
            "category":"Real Estate",
            "subcategory":"Real Estate Agent",
            "type":"Services"
        }
    ],
    "sg:phone":"+1 607 277 3010",
    "sg:postcode":"14850",
    "sg:province":"NY",
    "wof:name":"Reed Alton Real Estate",
    "wof:placetype":"venue"
},
  "geometry": {"coordinates":[-76.42918899999999,42.445034],"type":"Point"}
}