{
  "type": "Feature",
  "properties": {
    "addr:full":"56 Fulton St New York NY 10038",
    "addr:housenumber":"56",
    "addr:postcode":"10038",
    "addr:street":"Fulton St",
    "iso:country":"US",
    "sg:address":"56 Fulton St",
    "sg:city":"New York",
    "sg:classifiers":[
        {
            "category":"Retail",
            "subcategory":"Auto Rental",
            "type":"Services"
        }
    ],
    "sg:phone":"+1 212 227 5050",
    "sg:postcode":"10038",
    "sg:province":"NY",
    "sg:tags":[
        "renting",
        "automobile",
        "passenger",
        "car"
    ],
    "wof:name":"Enterprise Rent A Car",
    "wof:placetype":"venue"
},
  "geometry": {"coordinates":[-74.005072,40.708656],"type":"Point"}
}