{
  "type": "Feature",
  "properties": {
    "addr:full":"3630 Walden Ave Lancaster NY 14086",
    "addr:housenumber":"3630",
    "addr:postcode":"14086",
    "addr:street":"Walden Ave",
    "iso:country":"US",
    "sg:address":"3630 Walden Ave",
    "sg:city":"Lancaster",
    "sg:classifiers":[
        {
            "category":"Organizations",
            "subcategory":"Labor Organization",
            "type":"Services"
        }
    ],
    "sg:phone":"+1   ",
    "sg:postcode":"14086",
    "sg:province":"NY",
    "wof:name":"Buffalo Typographical Un No 9",
    "wof:placetype":"venue"
},
  "geometry": {"coordinates":[-78.670957,42.915997],"type":"Point"}
}