{
  "type": "Feature",
  "properties": {
    "addr:full":"596 Ramona Ave Staten Island NY 10309",
    "addr:housenumber":"596",
    "addr:postcode":"10309",
    "addr:street":"Ramona Ave",
    "iso:country":"US",
    "sg:address":"596 Ramona Ave",
    "sg:city":"Staten Island",
    "sg:classifiers":[
        {
            "category":"Shopping",
            "type":"Retail Goods"
        }
    ],
    "sg:phone":"+1 718 227 0521",
    "sg:postcode":"10309",
    "sg:province":"NY",
    "sg:tags":[
        "cosmetic",
        "perfume"
    ],
    "wof:name":"L Image Perfumes & Cosmetics",
    "wof:placetype":"venue"
},
  "geometry": {"coordinates":[-74.207668,40.53574],"type":"Point"}
}