{
  "type": "Feature",
  "properties": {
    "addr:full":"570 Expressway Dr S Medford NY 11763",
    "addr:housenumber":"570",
    "addr:postcode":"11763",
    "addr:street":"Expressway Dr S",
    "iso:country":"US",
    "sg:address":"570 Expressway Dr S",
    "sg:city":"Medford",
    "sg:classifiers":[
        {
            "category":"Banks & Credit Unions",
            "subcategory":"Bank",
            "type":"Services"
        }
    ],
    "sg:phone":"+1 631 475 7600",
    "sg:postcode":"11763",
    "sg:province":"NY",
    "sg:tags":[
        "loan",
        "real estate"
    ],
    "wof:name":"Prime Star Mortgage Corp",
    "wof:placetype":"venue"
},
  "geometry": {"coordinates":[-72.98515399999999,40.822328],"type":"Point"}
}