{
  "type": "Feature",
  "properties": {
    "iso:country":"US",
    "sg:address":"6313 Avenue N",
    "sg:city":"Brooklyn",
    "sg:classifiers":[
        {
            "category":"Retail",
            "subcategory":"Laundry & Dry Cleaning",
            "type":"Services"
        }
    ],
    "sg:phone":"+1 718 763 2090",
    "sg:postcode":"11234",
    "sg:province":"NY",
    "sg:tags":[
        "cleaner"
    ],
    "wof:name":"Anthony's Cleaners & Tailors",
    "wof:placetype":"venue"
},
  "geometry": {"coordinates":[-73.91627,40.619728],"type":"Point"}
}