{
  "type": "Feature",
  "properties": {
    "iso:country":"US",
    "sg:address":"803 S 7th St",
    "sg:city":"Lindenhurst",
    "sg:classifiers":[
        {
            "category":"Building & Trades",
            "subcategory":"Construction",
            "type":"Services"
        }
    ],
    "sg:phone":"+1 631 957 2331",
    "sg:postcode":"11757",
    "sg:province":"NY",
    "sg:tags":[
        "contractor"
    ],
    "wof:name":"CDM Contracting of LI Inc",
    "wof:placetype":"venue"
},
  "geometry": {"coordinates":[-73.370217,40.667525],"type":"Point"}
}