{
  "type": "Feature",
  "properties": {
    "addr:full":"200 Co Rd 23 New City NY 10956",
    "addr:housenumber":"200;23",
    "addr:postcode":"10956",
    "addr:street":"Co Rd",
    "iso:country":"US",
    "sg:address":"200 Co Rd 23",
    "sg:city":"New City",
    "sg:classifiers":[
        {
            "category":"Health Services",
            "subcategory":"Doctor",
            "type":"Services"
        }
    ],
    "sg:phone":"+1 845 356 4484",
    "sg:postcode":"10956",
    "sg:province":"NY",
    "sg:tags":[
        "dentist"
    ],
    "wof:name":"Mark S Hirsch DDS",
    "wof:placetype":"venue"
},
  "geometry": {"coordinates":[-73.96142999999999,41.170244],"type":"Point"}
}