{
  "type": "Feature",
  "properties": {
    "addr:full":"119 Pennsylvania Ave Brooklyn NY 11207",
    "addr:housenumber":"119",
    "addr:postcode":"11207",
    "addr:street":"Pennsylvania Ave",
    "iso:country":"US",
    "sg:address":"119 Pennsylvania Ave",
    "sg:city":"Brooklyn",
    "sg:classifiers":[
        {
            "category":"Shopping",
            "subcategory":"Pharmacy",
            "type":"Retail Goods"
        }
    ],
    "sg:phone":"+1 718 495 9015",
    "sg:postcode":"11207",
    "sg:province":"NY",
    "wof:name":"Health One Pharmacy",
    "wof:placetype":"venue"
},
  "geometry": {"coordinates":[-73.896587,40.675193],"type":"Point"}
}