{
  "type": "Feature",
  "properties": {
    "addr:full":"88 Hudson Ave Irvington NY 10533",
    "addr:housenumber":"88",
    "addr:postcode":"ny 10533",
    "addr:street":"Hudson Ave",
    "iso:country":"US",
    "sg:address":"88 Hudson Ave",
    "sg:city":"Irvington",
    "sg:classifiers":[
        {
            "category":"Recreation",
            "type":"Entertainment"
        }
    ],
    "sg:phone":"+1   ",
    "sg:postcode":"10533",
    "sg:province":"NY",
    "wof:name":"Kwon Inc",
    "wof:placetype":"venue"
},
  "geometry": {"coordinates":[-73.854333,41.045605],"type":"Point"}
}