{
  "type": "Feature",
  "properties": {
    "addr:full":"13118 Broadway St Alden NY 14004",
    "addr:housenumber":"13118",
    "addr:postcode":"14004",
    "addr:street":"Broadway St",
    "iso:country":"US",
    "sg:address":"13118 Broadway St",
    "sg:city":"Alden",
    "sg:classifiers":[
        {
            "category":"Recreation",
            "type":"Entertainment"
        }
    ],
    "sg:phone":"+1 716 937 3772",
    "sg:postcode":"14004",
    "sg:province":"NY",
    "sg:tags":[
        "martial",
        "arts",
        "instruction"
    ],
    "wof:name":"Robert Koch's Intl Black Belt",
    "wof:placetype":"venue"
},
  "geometry": {"coordinates":[-78.499574,42.898819],"type":"Point"}
}