{
  "type": "Feature",
  "properties": {
    "addr:full":"1375 Boies Rd East Aurora NY 14052",
    "addr:housenumber":"1375",
    "addr:postcode":"14052",
    "addr:street":"Boies Rd",
    "iso:country":"US",
    "sg:address":"1375 Boies Rd",
    "sg:city":"East Aurora",
    "sg:classifiers":[
        {
            "category":"Building & Trades",
            "subcategory":"Construction",
            "type":"Services"
        }
    ],
    "sg:phone":"+1 716 652 3686",
    "sg:postcode":"14052",
    "sg:province":"NY",
    "sg:tags":[
        "siding",
        "contractor"
    ],
    "wof:name":"Siding Systems",
    "wof:placetype":"venue"
},
  "geometry": {"coordinates":[-78.637781,42.725169],"type":"Point"}
}