{
  "type": "Feature",
  "properties": {
    "iso:country":"US",
    "sg:address":"22 Forest Ave",
    "sg:city":"Locust Valley",
    "sg:classifiers":[
        {
            "category":"Health Services",
            "subcategory":"Clinic",
            "type":"Services"
        }
    ],
    "sg:phone":"+1 516 609 9642",
    "sg:postcode":"11560",
    "sg:province":"NY",
    "sg:tags":[
        "holistic",
        "practitioner"
    ],
    "wof:name":"Robert A Kornfeld Holistic",
    "wof:placetype":"venue"
},
  "geometry": {"coordinates":[-73.59788500000001,40.875815],"type":"Point"}
}