{
  "type": "Feature",
  "properties": {
    "addr:full":"212 Myron Rd Syracuse NY 13219",
    "addr:housenumber":"212",
    "addr:postcode":"13219",
    "addr:street":"Myron Rd",
    "iso:country":"US",
    "sg:address":"212 Myron Rd",
    "sg:city":"Syracuse",
    "sg:classifiers":[
        {
            "category":"Shopping",
            "subcategory":"Florist",
            "type":"Retail Goods"
        },
        {
            "category":"Shopping",
            "subcategory":"Gifts & Souvenirs",
            "type":"Retail Goods"
        }
    ],
    "sg:phone":"+1 315 468 0100",
    "sg:postcode":"13219",
    "sg:province":"NY",
    "sg:tags":[
        "balloon",
        "artist"
    ],
    "wof:name":"Say It With Helium",
    "wof:placetype":"venue"
},
  "geometry": {"coordinates":[-76.236206,43.0507],"type":"Point"}
}