{
  "type": "Feature",
  "properties": {
    "iso:country":"US",
    "sg:address":"172 Conklin Ave",
    "sg:city":"Binghamton",
    "sg:classifiers":[
        {
            "category":"Building & Trades",
            "subcategory":"Plumbing",
            "type":"Services"
        }
    ],
    "sg:phone":"+1 607 771 8473",
    "sg:postcode":"13903",
    "sg:province":"NY",
    "sg:tags":[
        "contractor"
    ],
    "wof:name":"Eagle Heating & Cooling",
    "wof:placetype":"venue"
},
  "geometry": {"coordinates":[-75.89844100000001,42.09412],"type":"Point"}
}