{
  "type": "Feature",
  "properties": {
    "addr:full":"3013 Steinway St Astoria NY 11103",
    "addr:housenumber":"3013",
    "addr:postcode":"11103",
    "addr:street":"Steinway St",
    "iso:country":"US",
    "sg:address":"3013 Steinway St",
    "sg:city":"Astoria",
    "sg:classifiers":[
        {
            "category":"Shopping",
            "subcategory":"Shoes",
            "type":"Retail Goods"
        }
    ],
    "sg:phone":"+1 718 777 7788",
    "sg:postcode":"11103",
    "sg:province":"NY",
    "sg:tags":[
        "store"
    ],
    "wof:name":"NYC Shoes Inc",
    "wof:placetype":"venue"
},
  "geometry": {"coordinates":[-73.915108,40.763489],"type":"Point"}
}