{
  "type": "Feature",
  "properties": {
    "iso:country":"US",
    "sg:address":"860 Hooper Rd",
    "sg:city":"Endicott",
    "sg:classifiers":[
        {
            "category":"Food & Beverages",
            "subcategory":"Groceries & Convenience Stores",
            "type":"Retail Goods"
        }
    ],
    "sg:phone":"+1   ",
    "sg:postcode":"13760",
    "sg:province":"NY",
    "wof:name":"Endwell Giant Market 7",
    "wof:placetype":"venue"
},
  "geometry": {"coordinates":[-76.02689700000001,42.127431],"type":"Point"}
}