{
  "type": "Feature",
  "properties": {
    "iso:country":"US",
    "sg:address":"1835 Ridge Road Jct",
    "sg:city":"Webster",
    "sg:classifiers":[
        {
            "category":"Building & Trades",
            "subcategory":"Plumbing",
            "type":"Services"
        },
        {
            "category":"Utilities",
            "subcategory":"Sewage",
            "type":"Services"
        },
        {
            "category":"Building & Trades",
            "subcategory":"Cleaning & Sanitation",
            "type":"Services"
        }
    ],
    "sg:phone":"+1 585 265 0277",
    "sg:postcode":"14580",
    "sg:province":"NY",
    "sg:tags":[
        "cleaner",
        "plumber",
        "industrial",
        "tank",
        "septic",
        "repairer",
        "systems-cleaning",
        "system",
        "sewer",
        "contractors-commercial",
        "plumbing-drain"
    ],
    "sg:website":"http://www.chamberlainseptictankserviceinc.com",
    "wof:name":"Chamberlain Septic Service",
    "wof:placetype":"venue"
},
  "geometry": {"coordinates":[-77.384614,43.222077],"type":"Point"}
}