{
  "type": "Feature",
  "properties": {
    "addr:full":"520 W Metro Park Rochester NY 14623",
    "addr:housenumber":"520",
    "addr:postcode":"14623",
    "addr:street":"W Metro Park",
    "iso:country":"US",
    "sg:address":"520 W Metro Park",
    "sg:city":"Rochester",
    "sg:classifiers":[
        {
            "category":"Professional",
            "subcategory":"Business Services",
            "type":"Services"
        }
    ],
    "sg:phone":"+1 585 272 1440",
    "sg:postcode":"14623",
    "sg:province":"NY",
    "sg:tags":[
        "record",
        "document"
    ],
    "sg:website":"www.ironmoutain.com",
    "wof:name":"Iron Mountain",
    "wof:placetype":"venue"
},
  "geometry": {"coordinates":[-77.62538600000001,43.098614],"type":"Point"}
}