{
  "type": "Feature",
  "properties": {
    "addr:full":"796 Ulster Ave Kingston NY 12449",
    "addr:housenumber":"796",
    "addr:postcode":"12449",
    "addr:street":"Ulster Ave",
    "iso:country":"US",
    "sg:address":"796 Ulster Ave",
    "sg:city":"Kingston",
    "sg:classifiers":[
        {
            "category":"Shopping",
            "subcategory":"Clothing, Apparel, & Fashions",
            "type":"Retail Goods"
        }
    ],
    "sg:phone":"+1   ",
    "sg:postcode":"12449",
    "sg:province":"NY",
    "sg:tags":[
        "shop",
        "tuxedo",
        "bridal",
        "rental"
    ],
    "wof:name":"Prom & Wedding Bridal Salon",
    "wof:placetype":"venue"
},
  "geometry": {"coordinates":[-73.994174,41.952191],"type":"Point"}
}