{
  "type": "Feature",
  "properties": {
    "addr:full":"5 Di Tomas Ct Copiague NY 11726",
    "addr:housenumber":"5",
    "addr:postcode":"11726",
    "addr:street":"Di Tomas Ct",
    "iso:country":"US",
    "sg:address":"5 Di Tomas Ct",
    "sg:city":"Copiague",
    "sg:classifiers":[
        {
            "category":"Building & Trades",
            "subcategory":"Construction",
            "type":"Services"
        }
    ],
    "sg:phone":"+1 631 884 3656",
    "sg:postcode":"11726",
    "sg:province":"NY",
    "sg:tags":[
        "street",
        "general",
        "highway",
        "contractor"
    ],
    "wof:name":"Femi 9 Contracting Corp",
    "wof:placetype":"venue"
},
  "geometry": {"coordinates":[-73.406869,40.685368],"type":"Point"}
}