{
  "type": "Feature",
  "properties": {
    "iso:country":"US",
    "sg:address":"1756 E 12th St",
    "sg:city":"Brooklyn",
    "sg:classifiers":[
        {
            "category":"Building & Trades",
            "subcategory":"Construction",
            "type":"Services"
        }
    ],
    "sg:phone":"+1 718 336 4338",
    "sg:postcode":"11229",
    "sg:province":"NY",
    "sg:tags":[
        "house"
    ],
    "wof:name":"Yarap Construction Company",
    "wof:placetype":"venue"
},
  "geometry": {"coordinates":[-73.960871,40.606524],"type":"Point"}
}