{
  "type": "Feature",
  "properties": {
    "iso:country":"US",
    "sg:address":"128 Washington Ave",
    "sg:city":"Hastings On Hudson",
    "sg:classifiers":[
        {
            "category":"Communications",
            "subcategory":"Film & Video Production",
            "type":"Services"
        }
    ],
    "sg:phone":"+1 914 478 3890",
    "sg:postcode":"10706",
    "sg:province":"NY",
    "sg:tags":[
        "motion"
    ],
    "wof:name":"Dawkins Productions Inc",
    "wof:placetype":"venue"
},
  "geometry": {"coordinates":[-73.87881400000001,40.992091],"type":"Point"}
}