{
  "type": "Feature",
  "properties": {
    "addr:full":"517 George Urban Blvd Buffalo NY 14225",
    "addr:housenumber":"517",
    "addr:postcode":"14225",
    "addr:street":"George Urban Blvd",
    "iso:country":"US",
    "sg:address":"517 George Urban Blvd",
    "sg:city":"Buffalo",
    "sg:classifiers":[
        {
            "category":"Professional",
            "subcategory":"Accounting & Tax Preparation",
            "type":"Services"
        }
    ],
    "sg:phone":"+1 716 894 1102",
    "sg:postcode":"14225",
    "sg:province":"NY",
    "sg:tags":[
        "bookkeeping",
        "general"
    ],
    "wof:name":"Roger W Reynolds Accounting",
    "wof:placetype":"venue"
},
  "geometry": {"coordinates":[-78.770962,42.918769],"type":"Point"}
}