{
  "type": "Feature",
  "properties": {
    "addr:full":"1262 Castle Hill Ave Bronx NY 10462",
    "addr:housenumber":"1262",
    "addr:postcode":"10462",
    "addr:street":"Castle Hill Ave",
    "iso:country":"US",
    "sg:address":"1262 Castle Hill Ave",
    "sg:city":"Bronx",
    "sg:classifiers":[
        {
            "category":"Travel",
            "subcategory":"Travel Agent",
            "type":"Entertainment"
        }
    ],
    "sg:phone":"+1 718 829 8300",
    "sg:postcode":"10462",
    "sg:province":"NY",
    "sg:tags":[
        "agency",
        "bureau"
    ],
    "wof:name":"Cophresi Travel Agency Inc",
    "wof:placetype":"venue"
},
  "geometry": {"coordinates":[-73.851569,40.83407],"type":"Point"}
}