{
  "type": "Feature",
  "properties": {
    "addr:full":"754 5th Ave 7th Fl New York NY 10019",
    "addr:housenumber":"754",
    "addr:postcode":"10019",
    "addr:street":"5Th Ave",
    "iso:country":"US",
    "sg:address":"754 5th Ave 7th Fl",
    "sg:city":"New York",
    "sg:classifiers":[
        {
            "category":"Restaurant",
            "type":"Food & Drink"
        }
    ],
    "sg:phone":"+1 212 872 8977",
    "sg:postcode":"10019",
    "sg:province":"NY",
    "sg:tags":[
        "new",
        "american"
    ],
    "sg:website":"www.bergdorfgoodman.com/store/in...",
    "wof:name":"Bergdorf Goodman Restaurant",
    "wof:placetype":"venue"
},
  "geometry": {"coordinates":[-73.97354,40.763562],"type":"Point"}
}