{
  "type": "Feature",
  "properties": {
    "addr:full":"11 Main St Port Washington NY 11050",
    "addr:housenumber":"11",
    "addr:postcode":"11050",
    "addr:street":"Main St",
    "iso:country":"US",
    "sg:address":"11 Main St",
    "sg:city":"Port Washington",
    "sg:classifiers":[
        {
            "category":"Shopping",
            "subcategory":"Clothing, Apparel, & Fashions",
            "type":"Retail Goods"
        }
    ],
    "sg:phone":"+1   ",
    "sg:postcode":"11050",
    "sg:province":"NY",
    "sg:tags":[
        "ready"
    ],
    "wof:name":"Entree Designer Boutique",
    "wof:placetype":"venue"
},
  "geometry": {"coordinates":[-73.68549899999999,40.830955],"type":"Point"}
}