{
  "type": "Feature",
  "properties": {
    "addr:full":"8125 Foster Ave Brooklyn NY 11236",
    "addr:housenumber":"8125",
    "addr:postcode":"11236",
    "addr:street":"Foster Ave",
    "iso:country":"US",
    "sg:address":"8125 Foster Ave",
    "sg:city":"Brooklyn",
    "sg:classifiers":[
        {
            "category":"Wholesale",
            "subcategory":"Groceries",
            "type":"Manufacturing & Wholesale Goods"
        }
    ],
    "sg:phone":"+1 718 763 5440",
    "sg:postcode":"11236",
    "sg:province":"NY",
    "sg:tags":[
        "food",
        "product"
    ],
    "wof:name":"Gani Products Inc",
    "wof:placetype":"venue"
},
  "geometry": {"coordinates":[-73.918454,40.640931],"type":"Point"}
}