{
  "type": "Feature",
  "properties": {
    "addr:full":"824 W Fingerboard Rd Staten Island NY 10305",
    "addr:housenumber":"824",
    "addr:postcode":"10305",
    "addr:street":"W Fingerboard Rd",
    "iso:country":"US",
    "sg:address":"824 W Fingerboard Rd",
    "sg:city":"Staten Island",
    "sg:classifiers":[
        {
            "category":"Shopping",
            "subcategory":"Catalog Store",
            "type":"Retail Goods"
        }
    ],
    "sg:phone":"+1   ",
    "sg:postcode":"10305",
    "sg:province":"NY",
    "sg:tags":[
        "house",
        "mail"
    ],
    "wof:name":"Home of Electronics LLC",
    "wof:placetype":"venue"
},
  "geometry": {"coordinates":[-74.08241200000001,40.601871],"type":"Point"}
}