{
  "type": "Feature",
  "properties": {
    "addr:full":"19 Mildenhall Ridge Fairport NY 14450",
    "addr:housenumber":"19",
    "addr:postcode":"14450",
    "addr:street":"Mildenhall Ridge",
    "iso:country":"US",
    "sg:address":"19 Mildenhall Ridge",
    "sg:city":"Fairport",
    "sg:classifiers":[
        {
            "category":"Manufacturing",
            "subcategory":"Pottery",
            "type":"Manufacturing & Wholesale Goods"
        }
    ],
    "sg:phone":"+1   ",
    "sg:postcode":"14450",
    "sg:province":"NY",
    "sg:tags":[
        "product",
        "mfg"
    ],
    "wof:name":"Etniko US",
    "wof:placetype":"venue"
},
  "geometry": {"coordinates":[-77.399316,43.066272],"type":"Point"}
}