{
  "type": "Feature",
  "properties": {
    "addr:full":"1320 Broadway Hewlett NY 11557",
    "addr:housenumber":"1320",
    "addr:postcode":"11557",
    "addr:street":"Broadway",
    "iso:country":"US",
    "sg:address":"1320 Broadway",
    "sg:city":"Hewlett",
    "sg:classifiers":[
        {
            "category":"Deli",
            "type":"Food & Drink"
        },
        {
            "category":"Restaurant",
            "type":"Food & Drink"
        }
    ],
    "sg:phone":"+1 516 837 0818",
    "sg:postcode":"11557",
    "sg:province":"NY",
    "sg:tags":[
        "delicatessen"
    ],
    "wof:name":"Ay Caramba",
    "wof:placetype":"venue"
},
  "geometry": {"coordinates":[-73.700827,40.638974],"type":"Point"}
}