{
  "type": "Feature",
  "properties": {
    "iso:country":"US",
    "sg:address":"1726 Brentwood Rd",
    "sg:city":"Brentwood",
    "sg:classifiers":[
        {
            "category":"Shopping",
            "type":"Retail Goods"
        }
    ],
    "sg:phone":"+1   ",
    "sg:postcode":"11717",
    "sg:province":"NY",
    "sg:tags":[
        "merchandise"
    ],
    "wof:name":"Aladdin Accessories",
    "wof:placetype":"venue"
},
  "geometry": {"coordinates":[-73.24627099999999,40.772832],"type":"Point"}
}