{
  "type": "Feature",
  "properties": {
    "addr:full":"1805 215th St Bayside NY 11360",
    "addr:housenumber":"1805",
    "addr:postcode":"11360",
    "addr:street":"215Th St",
    "iso:country":"US",
    "sg:address":"1805 215th St",
    "sg:city":"Bayside",
    "sg:classifiers":[
        {
            "category":"Utilities",
            "subcategory":"Water",
            "type":"Services"
        }
    ],
    "sg:phone":"+1 718 819 0900",
    "sg:postcode":"11360",
    "sg:province":"NY",
    "sg:tags":[
        "bulk",
        "companies-bottled"
    ],
    "wof:name":"Towers At Waters Edge The Sales Office",
    "wof:placetype":"venue"
},
  "geometry": {"coordinates":[-73.776466,40.783958],"type":"Point"}
}