{
  "type": "Feature",
  "properties": {
    "iso:country":"US",
    "sg:address":"285 Commack Rd Ste 9",
    "sg:city":"Commack",
    "sg:classifiers":[
        {
            "category":"Sports & Exercise",
            "subcategory":"Gym",
            "type":"Entertainment"
        }
    ],
    "sg:phone":"+1 631 858 2900",
    "sg:postcode":"11725",
    "sg:province":"NY",
    "sg:website":"www.intelligentfitness.net",
    "wof:name":"Intelligent Fitness Inc",
    "wof:placetype":"venue"
},
  "geometry": {"coordinates":[-73.29303899999999,40.842381],"type":"Point"}
}