{
  "type": "Feature",
  "properties": {
    "addr:full":"777 Culver Rd Rochester NY 14609",
    "addr:housenumber":"777",
    "addr:postcode":"14609",
    "addr:street":"Culver Rd",
    "iso:country":"US",
    "sg:address":"777 Culver Rd",
    "sg:city":"Rochester",
    "sg:classifiers":[
        {
            "category":"Restaurant",
            "type":"Food & Drink"
        }
    ],
    "sg:menulink":"http://www.allmenus.com/ny/rochester/256248-lorraines-food-factory/menu/",
    "sg:phone":"+1 585 442 6574",
    "sg:postcode":"14609",
    "sg:province":"NY",
    "sg:tags":[
        "pasta",
        "wrap",
        "american",
        "sandwich",
        "salad"
    ],
    "wof:name":"Lorraine's Food Factory",
    "wof:placetype":"venue"
},
  "geometry": {"coordinates":[-77.566569,43.159152],"type":"Point"}
}