{
  "type": "Feature",
  "properties": {
    "addr:full":"1217 Erie Blvd W Rome NY 13440",
    "addr:housenumber":"1217",
    "addr:postcode":"13440",
    "addr:street":"Erie Blvd W",
    "iso:country":"US",
    "sg:address":"1217 Erie Blvd W",
    "sg:city":"Rome",
    "sg:classifiers":[
        {
            "category":"Retail",
            "subcategory":"Auto Rental",
            "type":"Services"
        }
    ],
    "sg:phone":"+1 315 336 0194",
    "sg:postcode":"13440",
    "sg:province":"NY",
    "sg:tags":[
        "truck"
    ],
    "wof:name":"Ryder",
    "wof:placetype":"venue"
},
  "geometry": {"coordinates":[-75.485674,43.224336],"type":"Point"}
}