{
  "type": "Feature",
  "properties": {
    "iso:country":"US",
    "sg:address":"60 State Route 17M",
    "sg:city":"Harriman",
    "sg:classifiers":[
        {
            "category":"Sports & Exercise",
            "subcategory":"Gym",
            "type":"Entertainment"
        }
    ],
    "sg:phone":"+1 845 782 4653",
    "sg:postcode":"10926",
    "sg:province":"NY",
    "sg:tags":[
        "trainer"
    ],
    "wof:name":"Gold's Gym",
    "wof:placetype":"venue"
},
  "geometry": {"coordinates":[-74.150846,41.30649],"type":"Point"}
}