{
  "type": "Feature",
  "properties": {
    "iso:country":"US",
    "sg:address":"5109 W Genesee St # 201",
    "sg:city":"Camillus",
    "sg:classifiers":[
        {
            "category":"Health Services",
            "subcategory":"Clinic",
            "type":"Services"
        },
        {
            "category":"Health Services",
            "subcategory":"Podiatrist",
            "type":"Services"
        }
    ],
    "sg:phone":"+1 315 487 1571",
    "sg:postcode":"13031",
    "sg:province":"NY",
    "sg:tags":[
        "physician",
        "surgeons"
    ],
    "sg:website":"http://www.cnyfootdoc.com",
    "wof:name":"Rameas Samuel B",
    "wof:placetype":"venue"
},
  "geometry": {"coordinates":[-76.262789,43.041529],"type":"Point"}
}