{
  "type": "Feature",
  "properties": {
    "iso:country":"US",
    "sg:address":"942 State Hwy 13",
    "sg:city":"Cortland",
    "sg:classifiers":[
        {
            "category":"Home & Garden",
            "subcategory":"Hardware",
            "type":"Retail Goods"
        }
    ],
    "sg:phone":"+1 607 756 7903",
    "sg:postcode":"13045",
    "sg:province":"NY",
    "wof:name":"Arnold's Ace Hardware",
    "wof:placetype":"venue"
},
  "geometry": {"coordinates":[-76.214821,42.576505],"type":"Point"}
}