{
  "type": "Feature",
  "properties": {
    "addr:full":"1131 Allerton Avenue Bronx NY 10469",
    "addr:housenumber":"1131",
    "addr:postcode":"10469",
    "addr:street":"Allerton Avenue",
    "iso:country":"US",
    "sg:address":"1131 Allerton Avenue",
    "sg:city":"Bronx",
    "sg:classifiers":[
        {
            "category":"Building & Trades",
            "subcategory":"Construction",
            "type":"Services"
        }
    ],
    "sg:phone":"+1 718 652 9600",
    "sg:postcode":"10469",
    "sg:province":"NY",
    "sg:tags":[
        "contractor"
    ],
    "wof:name":"Intercity Electric",
    "wof:placetype":"venue"
},
  "geometry": {"coordinates":[-73.85445,40.865527],"type":"Point"}
}