{
  "type": "Feature",
  "properties": {
    "iso:country":"US",
    "sg:address":"904 Miller Rd W",
    "sg:city":"Westdale",
    "sg:classifiers":[
        {
            "category":"Professional",
            "subcategory":"Art Services",
            "type":"Services"
        }
    ],
    "sg:phone":"+1 315 964 2757",
    "sg:postcode":"13483",
    "sg:province":"NY",
    "sg:tags":[
        "photographer"
    ],
    "wof:name":"Vick's Sky Prints",
    "wof:placetype":"venue"
},
  "geometry": {"coordinates":[-75.84210299999999,43.412044],"type":"Point"}
}