{
  "type": "Feature",
  "properties": {
    "iso:country":"US",
    "sg:address":"348 Elverton Ave",
    "sg:city":"Staten Island",
    "sg:classifiers":[
        {
            "category":"Building & Trades",
            "subcategory":"Landscaping Services",
            "type":"Services"
        }
    ],
    "sg:phone":"+1 718 966 2461",
    "sg:postcode":"10308",
    "sg:province":"NY",
    "sg:tags":[
        "landscape"
    ],
    "wof:name":"A & J Landscaping Of Si Inc",
    "wof:placetype":"venue"
},
  "geometry": {"coordinates":[-74.155402,40.557414],"type":"Point"}
}