{
  "type": "Feature",
  "properties": {
    "iso:country":"US",
    "sg:address":"1678 Empire Blvd",
    "sg:city":"Webster",
    "sg:classifiers":[
        {
            "category":"Health Services",
            "subcategory":"Clinic",
            "type":"Services"
        }
    ],
    "sg:phone":"+1 585 671 1920",
    "sg:postcode":"14580",
    "sg:province":"NY",
    "sg:tags":[
        "home"
    ],
    "wof:name":"We Care Home Nursing Svc",
    "wof:placetype":"venue"
},
  "geometry": {"coordinates":[-77.507521,43.182787],"type":"Point"}
}