{
  "type": "Feature",
  "properties": {
    "iso:country":"US",
    "sg:address":"4 S William St",
    "sg:city":"Johnstown",
    "sg:classifiers":[
        {
            "category":"Personal",
            "subcategory":"Beauty Salon",
            "type":"Services"
        }
    ],
    "sg:phone":"+1 518 762 7389",
    "sg:postcode":"12095",
    "sg:province":"NY",
    "wof:name":"Hair Affair",
    "wof:placetype":"venue"
},
  "geometry": {"coordinates":[-74.37412399999999,43.006319],"type":"Point"}
}