{
  "type": "Feature",
  "properties": {
    "addr:full":"3065 Roberts Ave Apt 1H Bronx NY 10461",
    "addr:housenumber":"3065",
    "addr:postcode":"10461",
    "addr:street":"Roberts Ave Apt 1H",
    "iso:country":"US",
    "sg:address":"3065 Roberts Ave Apt 1H",
    "sg:city":"Bronx",
    "sg:classifiers":[
        {
            "category":"Home & Garden",
            "subcategory":"Building Materials",
            "type":"Retail Goods"
        }
    ],
    "sg:phone":"+1 718 409 4527",
    "sg:postcode":"10461",
    "sg:province":"NY",
    "sg:tags":[
        "bathroom",
        "cabinet",
        "fixtures",
        "accessory"
    ],
    "wof:name":"You Scent Me",
    "wof:placetype":"venue"
},
  "geometry": {"coordinates":[-73.829407,40.845959],"type":"Point"}
}