{
  "type": "Feature",
  "properties": {
    "iso:country":"US",
    "sg:address":"9360 Johnson Rd",
    "sg:city":"Middleport",
    "sg:classifiers":[
        {
            "category":"Building & Trades",
            "subcategory":"Construction",
            "type":"Services"
        }
    ],
    "sg:phone":"+1 716 735 6135",
    "sg:postcode":"14105",
    "sg:province":"NY",
    "sg:tags":[
        "restoration",
        "cleaning",
        "patio",
        "deck"
    ],
    "wof:name":"Kingdom Kleaning",
    "wof:placetype":"venue"
},
  "geometry": {"coordinates":[-78.514042,43.145814],"type":"Point"}
}