{
  "type": "Feature",
  "properties": {
    "addr:full":"957 Ashford St Brooklyn NY 11207",
    "addr:housenumber":"957",
    "addr:postcode":"11207",
    "addr:street":"Ashford St",
    "iso:country":"US",
    "sg:address":"957 Ashford St",
    "sg:city":"Brooklyn",
    "sg:classifiers":[
        {
            "category":"Professional",
            "subcategory":"Employment Agencies",
            "type":"Services"
        }
    ],
    "sg:phone":"+1 718 257 9646",
    "sg:postcode":"11207",
    "sg:province":"NY",
    "sg:tags":[
        "training",
        "temporary"
    ],
    "wof:name":"Employees Merit Inc",
    "wof:placetype":"venue"
},
  "geometry": {"coordinates":[-73.87809799999999,40.659199],"type":"Point"}
}