{
  "type": "Feature",
  "properties": {
    "iso:country":"US",
    "sg:address":"623 New Loudon Rd",
    "sg:city":"Latham",
    "sg:classifiers":[
        {
            "category":"Health Services",
            "subcategory":"Health Practitioner",
            "type":"Services"
        }
    ],
    "sg:phone":"+1 518 783 1051",
    "sg:postcode":"12110",
    "sg:province":"NY",
    "sg:tags":[
        "psychologist"
    ],
    "wof:name":"Affiliated Psychological Svc",
    "wof:placetype":"venue"
},
  "geometry": {"coordinates":[-73.76024700000001,42.728377],"type":"Point"}
}