{
  "type": "Feature",
  "properties": {
    "addr:full":"74 Grand St New York NY 10013",
    "addr:housenumber":"74",
    "addr:postcode":"10013",
    "addr:street":"Grand St",
    "iso:country":"US",
    "sg:address":"74 Grand St",
    "sg:city":"New York",
    "sg:classifiers":[
        {
            "category":"Shopping",
            "type":"Retail Goods"
        }
    ],
    "sg:phone":"+1 212 925 3501",
    "sg:postcode":"10013",
    "sg:province":"NY",
    "sg:tags":[
        "art",
        "gallery",
        "dealer"
    ],
    "wof:name":"Charles Cowles Gallery Inc",
    "wof:placetype":"venue"
},
  "geometry": {"coordinates":[-74.00224,40.721731],"type":"Point"}
}