{
  "type": "Feature",
  "properties": {
    "addr:full":"129 Genesee St Auburn NY 13021",
    "addr:housenumber":"129",
    "addr:postcode":"13021",
    "addr:street":"Genesee St",
    "iso:country":"US",
    "sg:address":"129 Genesee St",
    "sg:city":"Auburn",
    "sg:classifiers":[
        {
            "category":"Restaurant",
            "type":"Food & Drink"
        }
    ],
    "sg:phone":"+1 315 252 6884",
    "sg:postcode":"13021",
    "sg:province":"NY",
    "sg:tags":[
        "eating"
    ],
    "wof:name":"Parkers' Grille & Tap House",
    "wof:placetype":"venue"
},
  "geometry": {"coordinates":[-76.56873899999999,42.930535],"type":"Point"}
}