{
  "type": "Feature",
  "properties": {
    "iso:country":"US",
    "sg:address":"14 N Seneca St",
    "sg:city":"West Seneca",
    "sg:classifiers":[
        {
            "category":"Personal",
            "subcategory":"Barber",
            "type":"Services"
        }
    ],
    "sg:phone":"+1 716 675 5585",
    "sg:postcode":"14224",
    "sg:province":"NY",
    "wof:name":"Headlines Perfect Hair Design",
    "wof:placetype":"venue"
},
  "geometry": {"coordinates":[-78.788748,42.848016],"type":"Point"}
}