{
  "type": "Feature",
  "properties": {
    "iso:country":"US",
    "sg:address":"2737 3rd Ave",
    "sg:city":"Bronx",
    "sg:classifiers":[
        {
            "category":"Health Services",
            "subcategory":"Clinic",
            "type":"Services"
        }
    ],
    "sg:phone":"+1 718 401 3007",
    "sg:postcode":"10451",
    "sg:province":"NY",
    "wof:name":"Bronx Care",
    "wof:placetype":"venue"
},
  "geometry": {"coordinates":[-73.92061200000001,40.814564],"type":"Point"}
}