{
  "type": "Feature",
  "properties": {
    "iso:country":"US",
    "sg:address":"1510 Orchard Park Rd",
    "sg:city":"Buffalo",
    "sg:classifiers":[
        {
            "category":"Retail",
            "subcategory":"Auto Repair",
            "type":"Services"
        }
    ],
    "sg:phone":"+1 716 674 1150",
    "sg:postcode":"14224",
    "sg:province":"NY",
    "sg:tags":[
        "body"
    ],
    "wof:name":"Bittermans Automotive Center",
    "wof:placetype":"venue"
},
  "geometry": {"coordinates":[-78.759218,42.808103],"type":"Point"}
}