{
  "type": "Feature",
  "properties": {
    "addr:full":"937 Jefferson Rd Rochester NY 14623",
    "addr:housenumber":"937",
    "addr:postcode":"14623",
    "addr:street":"Jefferson Rd",
    "iso:country":"US",
    "sg:address":"937 Jefferson Rd",
    "sg:city":"Rochester",
    "sg:classifiers":[
        {
            "category":"Shopping",
            "subcategory":"Beauty & Cosmetics",
            "type":"Retail Goods"
        }
    ],
    "sg:phone":"+1   ",
    "sg:postcode":"14623",
    "sg:province":"NY",
    "sg:tags":[
        "art",
        "supply"
    ],
    "wof:name":"Hyatts All Things Created",
    "wof:placetype":"venue"
},
  "geometry": {"coordinates":[-77.609386,43.087146],"type":"Point"}
}