{
  "type": "Feature",
  "properties": {
    "addr:full":"7852 Freeman Rd Sherman NY 14781",
    "addr:housenumber":"7852",
    "addr:postcode":"14781",
    "addr:street":"Freeman Rd",
    "iso:country":"US",
    "sg:address":"7852 Freeman Rd",
    "sg:city":"Sherman",
    "sg:classifiers":[
        {
            "category":"Building & Trades",
            "subcategory":"Construction",
            "type":"Services"
        }
    ],
    "sg:phone":"+1 716 761 6671",
    "sg:postcode":"14781",
    "sg:province":"NY",
    "sg:tags":[
        "house",
        "general",
        "contractor"
    ],
    "wof:name":"Country Side Construction",
    "wof:placetype":"venue"
},
  "geometry": {"coordinates":[-79.565309,42.149631],"type":"Point"}
}