{
  "type": "Feature",
  "properties": {
    "addr:full":"1055 Liberty Avenue Brooklyn NY 11208",
    "addr:housenumber":"1055",
    "addr:postcode":"11208",
    "addr:street":"Liberty Avenue",
    "iso:country":"US",
    "sg:address":"1055 Liberty Avenue",
    "sg:city":"Brooklyn",
    "sg:classifiers":[
        {
            "category":"Shopping",
            "subcategory":"Shoes",
            "type":"Retail Goods"
        }
    ],
    "sg:phone":"+1 718 235 3401",
    "sg:postcode":"11208",
    "sg:province":"NY",
    "sg:tags":[
        "store"
    ],
    "wof:name":"The Athletes Foot",
    "wof:placetype":"venue"
},
  "geometry": {"coordinates":[-73.870248,40.678355],"type":"Point"}
}