{
  "type": "Feature",
  "properties": {
    "addr:full":"25 Hillside Ave Jamaica NY 11432",
    "addr:housenumber":"25",
    "addr:postcode":"11432",
    "addr:street":"Hillside Ave",
    "iso:country":"US",
    "sg:address":"25 Hillside Ave",
    "sg:city":"Jamaica",
    "sg:classifiers":[
        {
            "category":"Shopping",
            "subcategory":"Florist",
            "type":"Retail Goods"
        }
    ],
    "sg:phone":"+1   ",
    "sg:postcode":"11432",
    "sg:province":"NY",
    "wof:name":"Michaels Flower Shop",
    "wof:placetype":"venue"
},
  "geometry": {"coordinates":[-73.794516,40.710104],"type":"Point"}
}