{
  "type": "Feature",
  "properties": {
    "addr:full":"1562 New York Ave Huntington Sta NY 11746",
    "addr:housenumber":"1562",
    "addr:postcode":"11746",
    "addr:street":"New York Ave",
    "iso:country":"US",
    "sg:address":"1562 New York Ave",
    "sg:city":"Huntington Sta",
    "sg:classifiers":[
        {
            "category":"Insurance",
            "subcategory":"Insurance Agent",
            "type":"Services"
        }
    ],
    "sg:phone":"+1 631 367 0300",
    "sg:postcode":"11746",
    "sg:province":"NY",
    "wof:name":"Allstate Insurance Co",
    "wof:placetype":"venue"
},
  "geometry": {"coordinates":[-73.411725,40.845114],"type":"Point"}
}