{
  "type": "Feature",
  "properties": {
    "addr:full":"10 Mitchell Ave Plainview NY 11803",
    "addr:housenumber":"10",
    "addr:postcode":"11803",
    "addr:street":"Mitchell Ave",
    "iso:country":"US",
    "sg:address":"10 Mitchell Ave",
    "sg:city":"Plainview",
    "sg:classifiers":[
        {
            "category":"Education",
            "subcategory":"School",
            "type":"Public Place"
        }
    ],
    "sg:phone":"+1 516 752 6620",
    "sg:postcode":"11803",
    "sg:province":"NY",
    "sg:tags":[
        "high",
        "k-",
        "private"
    ],
    "wof:name":"Farmingdale Senior High School",
    "wof:placetype":"venue"
},
  "geometry": {"coordinates":[-73.47640199999999,40.787731],"type":"Point"}
}