{
  "type": "Feature",
  "properties": {
    "iso:country":"US",
    "sg:address":"175 Highland Ave",
    "sg:city":"Staten Island",
    "sg:classifiers":[
        {
            "category":"Building & Trades",
            "subcategory":"Cleaning & Sanitation",
            "type":"Services"
        }
    ],
    "sg:phone":"+1 718 442 3768",
    "sg:postcode":"10301",
    "sg:province":"NY",
    "sg:tags":[
        "home"
    ],
    "sg:website":"www.sanigrout.com",
    "wof:name":"SaniGrout Inc.",
    "wof:placetype":"venue"
},
  "geometry": {"coordinates":[-74.097371,40.615659],"type":"Point"}
}