{
  "type": "Feature",
  "properties": {
    "addr:full":"2100 Hughes Ave Bronx NY 10457",
    "addr:housenumber":"2100",
    "addr:postcode":"10457",
    "addr:street":"Hughes Ave",
    "iso:country":"US",
    "sg:address":"2100 Hughes Ave",
    "sg:city":"Bronx",
    "sg:classifiers":[
        {
            "category":"Retail",
            "subcategory":"Repair Shop",
            "type":"Services"
        }
    ],
    "sg:phone":"+1 718 563 4843",
    "sg:postcode":"10457",
    "sg:province":"NY",
    "sg:tags":[
        "lock",
        "locksmith"
    ],
    "wof:name":"24/7 Affordable Locksmith",
    "wof:placetype":"venue"
},
  "geometry": {"coordinates":[-73.8899,40.849869],"type":"Point"}
}