{
  "type": "Feature",
  "properties": {
    "iso:country":"US",
    "sg:address":"100 Old Maryvale Dr",
    "sg:city":"Buffalo",
    "sg:classifiers":[
        {
            "category":"Organizations",
            "subcategory":"Religious Organization",
            "type":"Services"
        },
        {
            "category":"Organizations",
            "subcategory":"Professional Association",
            "type":"Services"
        }
    ],
    "sg:phone":"+1 716 833 6617",
    "sg:postcode":"14225",
    "sg:province":"NY",
    "wof:name":"Catholic Pamphlet Society-Us",
    "wof:placetype":"venue"
},
  "geometry": {"coordinates":[-78.76941600000001,42.934695],"type":"Point"}
}