{
  "type": "Feature",
  "properties": {
    "iso:country":"US",
    "sg:address":"254 Genesee St",
    "sg:city":"Utica",
    "sg:classifiers":[
        {
            "category":"Organizations",
            "subcategory":"Community Association",
            "type":"Services"
        }
    ],
    "sg:phone":"+1 315 797 0170",
    "sg:postcode":"13502",
    "sg:province":"NY",
    "sg:tags":[
        "club",
        "social"
    ],
    "wof:name":"Fort Schuyler Club House",
    "wof:placetype":"venue"
},
  "geometry": {"coordinates":[-75.234306,43.100083],"type":"Point"}
}