{
  "type": "Feature",
  "properties": {
    "addr:full":"25-13 30th Ave Astoria NY 11102",
    "addr:housenumber":"25-13",
    "addr:postcode":"11102",
    "addr:street":"30Th Ave",
    "iso:country":"US",
    "sg:address":"25-13 30th Ave",
    "sg:city":"Astoria",
    "sg:classifiers":[
        {
            "category":"Restaurant",
            "type":"Food & Drink"
        }
    ],
    "sg:phone":"+1 718 777 7879",
    "sg:postcode":"11102",
    "sg:province":"NY",
    "sg:tags":[
        "turkish"
    ],
    "sg:website":"lapapaonline.com/",
    "wof:name":"La Papa",
    "wof:placetype":"venue"
},
  "geometry": {"coordinates":[-73.924437,40.768571],"type":"Point"}
}