{
  "type": "Feature",
  "properties": {
    "addr:full":"74 E 79th Street New York NY 10021",
    "addr:housenumber":"74",
    "addr:postcode":"10021",
    "addr:street":"E 79Th Street",
    "iso:country":"US",
    "sg:address":"74 E 79th Street",
    "sg:city":"New York",
    "sg:classifiers":[
        {
            "category":"Arts & Performance",
            "subcategory":"Art Gallery",
            "type":"Entertainment"
        },
        {
            "category":"Shopping",
            "subcategory":"Antiques",
            "type":"Retail Goods"
        }
    ],
    "sg:phone":"+1 212 439 6600",
    "sg:postcode":"10021",
    "sg:province":"NY",
    "sg:website":"www.mmefineart.com",
    "wof:name":"Mme Fine Art",
    "wof:placetype":"venue"
},
  "geometry": {"coordinates":[-73.96151500000001,40.776003],"type":"Point"}
}