{
  "type": "Feature",
  "properties": {
    "addr:full":"39 W 34 5 Ave New York NY 10001",
    "addr:housenumber":"39",
    "addr:postcode":"10001",
    "addr:street":"W 34 5 Ave",
    "iso:country":"US",
    "sg:address":"39 W 34 5 Ave",
    "sg:city":"New York",
    "sg:classifiers":[
        {
            "category":"Shopping",
            "subcategory":"Clothing, Apparel, & Fashions",
            "type":"Retail Goods"
        }
    ],
    "sg:phone":"+1 212 868 6551",
    "sg:postcode":"10001",
    "sg:province":"NY",
    "sg:tags":[
        "men's",
        "clothing",
        "women's"
    ],
    "wof:name":"Zara USA",
    "wof:placetype":"venue"
},
  "geometry": {"coordinates":[-73.99549500000001,40.733486],"type":"Point"}
}