{
  "type": "Feature",
  "properties": {
    "iso:country":"US",
    "sg:address":"111 Earle Ave",
    "sg:city":"Lynbrook",
    "sg:classifiers":[
        {
            "category":"Building & Trades",
            "subcategory":"Construction",
            "type":"Services"
        }
    ],
    "sg:phone":"+1 516 887 1379",
    "sg:postcode":"11563",
    "sg:province":"NY",
    "sg:tags":[
        "general",
        "contractor"
    ],
    "wof:name":"Nassau Carpentry",
    "wof:placetype":"venue"
},
  "geometry": {"coordinates":[-73.667816,40.654562],"type":"Point"}
}