{
  "type": "Feature",
  "properties": {
    "iso:country":"US",
    "sg:address":"1691 Mount Hope Ave",
    "sg:city":"Rochester",
    "sg:classifiers":[
        {
            "category":"Restaurant",
            "type":"Food & Drink"
        }
    ],
    "sg:menulink":"http://www.allmenus.com/ny/rochester/23663-country-sweet-chicken/menu/",
    "sg:phone":"+1 585 244 3200",
    "sg:postcode":"14620",
    "sg:province":"NY",
    "sg:tags":[
        "barbecue",
        "chicken",
        "american"
    ],
    "wof:name":"Country Sweet Chicken",
    "wof:placetype":"venue"
},
  "geometry": {"coordinates":[-77.62115300000001,43.11722],"type":"Point"}
}