{
  "type": "Feature",
  "properties": {
    "iso:country":"US",
    "sg:address":"308 W 46 St",
    "sg:city":"New York",
    "sg:classifiers":[
        {
            "category":"Social Services",
            "type":"Services"
        }
    ],
    "sg:phone":"+1 212 974 7480",
    "sg:postcode":"10036",
    "sg:province":"NY",
    "wof:name":"Times Square Consortium",
    "wof:placetype":"venue"
},
  "geometry": {"coordinates":[-73.99062499999999,40.760825],"type":"Point"}
}