{
  "type": "Feature",
  "properties": {
    "addr:full":"508 Beach 135th St Far Rockaway NY 11694",
    "addr:housenumber":"508",
    "addr:postcode":"11694",
    "addr:street":"Beach 135Th St",
    "iso:country":"US",
    "sg:address":"508 Beach 135th St",
    "sg:city":"Far Rockaway",
    "sg:classifiers":[
        {
            "category":"Real Estate",
            "subcategory":"Real Estate Agent",
            "type":"Services"
        }
    ],
    "sg:phone":"+1 718 474 1174",
    "sg:postcode":"11694",
    "sg:province":"NY",
    "wof:name":"Rosenthal Real Estate Brokers",
    "wof:placetype":"venue"
},
  "geometry": {"coordinates":[-73.85587599999999,40.579485],"type":"Point"}
}