{
  "type": "Feature",
  "properties": {
    "addr:full":"220 E 53rd St New York NY 10022",
    "addr:housenumber":"220",
    "addr:postcode":"10022",
    "addr:street":"E 53Rd St",
    "iso:country":"US",
    "sg:address":"220 E 53rd St",
    "sg:city":"New York",
    "sg:classifiers":[
        {
            "category":"Restaurant",
            "type":"Food & Drink"
        }
    ],
    "sg:menulink":"http://www.allmenus.com/ny/new-york/2958-east-53/menu/",
    "sg:phone":"+1 212 888 6075",
    "sg:postcode":"10022",
    "sg:province":"NY",
    "sg:tags":[
        "japanese",
        "asian"
    ],
    "wof:name":"East 53",
    "wof:placetype":"venue"
},
  "geometry": {"coordinates":[-73.96864100000001,40.757171],"type":"Point"}
}