{
  "type": "Feature",
  "properties": {
    "iso:country":"US",
    "sg:address":"35 Maple Rd",
    "sg:city":"Williamsville",
    "sg:classifiers":[
        {
            "category":"Professional",
            "subcategory":"Lawyer & Legal Services",
            "type":"Services"
        }
    ],
    "sg:phone":"+1 716 565 1200",
    "sg:postcode":"14221",
    "sg:province":"NY",
    "sg:tags":[
        "attorney"
    ],
    "wof:name":"Lipsitz Green Fahringer Roll",
    "wof:placetype":"venue"
},
  "geometry": {"coordinates":[-78.787893,42.991288],"type":"Point"}
}