{
  "type": "Feature",
  "properties": {
    "addr:full":"48 Prince St New York NY 10012",
    "addr:housenumber":"48",
    "addr:postcode":"10012",
    "addr:street":"Prince St",
    "iso:country":"US",
    "sg:address":"48 Prince St",
    "sg:city":"New York",
    "sg:classifiers":[
        {
            "category":"Shopping",
            "subcategory":"Computers & Home Electronics",
            "type":"Retail Goods"
        }
    ],
    "sg:phone":"+1   ",
    "sg:postcode":"10012",
    "sg:province":"NY",
    "wof:name":"Sig",
    "wof:placetype":"venue"
},
  "geometry": {"coordinates":[-73.996476,40.723686],"type":"Point"}
}