{
  "type": "Feature",
  "properties": {
    "addr:full":"25 E 7th Street New York NY 10003",
    "addr:housenumber":"25",
    "addr:postcode":"10003",
    "addr:street":"E 7Th Street",
    "iso:country":"US",
    "sg:address":"25 E 7th Street",
    "sg:city":"New York",
    "sg:classifiers":[
        {
            "category":"Building & Trades",
            "subcategory":"Construction",
            "type":"Services"
        }
    ],
    "sg:phone":"+1 212 777 4321",
    "sg:postcode":"10003",
    "sg:province":"NY",
    "sg:tags":[
        "contractor"
    ],
    "wof:name":"Schweiger Contracting",
    "wof:placetype":"venue"
},
  "geometry": {"coordinates":[-73.98923499999999,40.728454],"type":"Point"}
}