{
  "type": "Feature",
  "properties": {
    "iso:country":"US",
    "sg:address":"5 Lewis Rd",
    "sg:city":"Saratoga Springs",
    "sg:classifiers":[
        {
            "category":"Retail",
            "subcategory":"Auto Repair",
            "type":"Services"
        }
    ],
    "sg:phone":"+1 518 581 7900",
    "sg:postcode":"12866",
    "sg:province":"NY",
    "sg:tags":[
        "repairing",
        "automobile"
    ],
    "sg:website":"www.hoffmancarwash.com",
    "wof:name":"Jiffy Lube",
    "wof:placetype":"venue"
},
  "geometry": {"coordinates":[-73.750739,43.118844],"type":"Point"}
}