{
  "type": "Feature",
  "properties": {
    "addr:full":"8 Thompson St Patchogue NY 11772",
    "addr:housenumber":"8",
    "addr:postcode":"11772",
    "addr:street":"Thompson St",
    "iso:country":"US",
    "sg:address":"8 Thompson St",
    "sg:city":"Patchogue",
    "sg:classifiers":[
        {
            "category":"Building & Trades",
            "subcategory":"Landscaping Services",
            "type":"Services"
        }
    ],
    "sg:phone":"+1 631 447 5362",
    "sg:postcode":"11772",
    "sg:province":"NY",
    "wof:name":"Quarlteres Tree Service",
    "wof:placetype":"venue"
},
  "geometry": {"coordinates":[-72.974203,40.756455],"type":"Point"}
}