{
  "type": "Feature",
  "properties": {
    "iso:country":"US",
    "sg:address":"80 Willett St",
    "sg:city":"Albany",
    "sg:classifiers":[
        {
            "category":"Social Services",
            "type":"Services"
        }
    ],
    "sg:phone":"+1 518 449 2897",
    "sg:postcode":"12210",
    "sg:province":"NY",
    "sg:tags":[
        "counselor",
        "marriage",
        "family"
    ],
    "wof:name":"Diane Saunders",
    "wof:placetype":"venue"
},
  "geometry": {"coordinates":[-73.768747,42.653146],"type":"Point"}
}