{
  "type": "Feature",
  "properties": {
    "addr:full":"188 Scott Ave Yonkers NY 10704",
    "addr:housenumber":"188",
    "addr:postcode":"10704",
    "addr:street":"Scott Ave",
    "iso:country":"US",
    "sg:address":"188 Scott Ave",
    "sg:city":"Yonkers",
    "sg:classifiers":[
        {
            "category":"Building & Trades",
            "subcategory":"Construction",
            "type":"Services"
        }
    ],
    "sg:phone":"+1 914 776 2434",
    "sg:postcode":"10704",
    "sg:province":"NY",
    "sg:tags":[
        "house"
    ],
    "wof:name":"Nat Construction Corp",
    "wof:placetype":"venue"
},
  "geometry": {"coordinates":[-73.861538,40.904333],"type":"Point"}
}