{
  "type": "Feature",
  "properties": {
    "addr:full":"89 Overlook Dr Mastic Beach NY 11951",
    "addr:housenumber":"89",
    "addr:postcode":"11951",
    "addr:street":"Overlook Dr",
    "iso:country":"US",
    "sg:address":"89 Overlook Dr",
    "sg:city":"Mastic Beach",
    "sg:classifiers":[
        {
            "category":"Organizations",
            "subcategory":"Religious Organization",
            "type":"Services"
        }
    ],
    "sg:phone":"+1 631 281 2835",
    "sg:postcode":"11951",
    "sg:province":"NY",
    "wof:name":"St Jude's Confraternity of Christian Doctrine",
    "wof:placetype":"venue"
},
  "geometry": {"coordinates":[-72.84880099999999,40.761002],"type":"Point"}
}