{
  "type": "Feature",
  "properties": {
    "iso:country":"US",
    "sg:address":"6 E 1st St",
    "sg:city":"Mt Vernon",
    "sg:classifiers":[
        {
            "category":"Shopping",
            "subcategory":"Bicycles & Sporting Goods",
            "type":"Retail Goods"
        }
    ],
    "sg:phone":"+1 914 667 7417",
    "sg:postcode":"10550",
    "sg:province":"NY",
    "wof:name":"Bronx River Bicycle Works",
    "wof:placetype":"venue"
},
  "geometry": {"coordinates":[-73.836214,40.91191],"type":"Point"}
}