{
  "type": "Feature",
  "properties": {
    "addr:full":"130 Commerce Way East Aurora NY 14052",
    "addr:housenumber":"130",
    "addr:postcode":"14052",
    "addr:street":"Commerce Way",
    "iso:country":"US",
    "sg:address":"130 Commerce Way",
    "sg:city":"East Aurora",
    "sg:classifiers":[
        {
            "category":"Manufacturing",
            "subcategory":"Paper Products",
            "type":"Manufacturing & Wholesale Goods"
        }
    ],
    "sg:phone":"+1   ",
    "sg:postcode":"14052",
    "sg:province":"NY",
    "sg:tags":[
        "box",
        "folding",
        "mfg",
        "paperboard",
        "equipment",
        "lighting"
    ],
    "wof:name":"Astronics Corporation",
    "wof:placetype":"venue"
},
  "geometry": {"coordinates":[-78.63872600000001,42.761571],"type":"Point"}
}