{
  "type": "Feature",
  "properties": {
    "addr:full":"9840 Welch District Rd Remsen NY 13438",
    "addr:housenumber":"9840",
    "addr:postcode":"13438",
    "addr:street":"Welch District Rd",
    "iso:country":"US",
    "sg:address":"9840 Welch District Rd",
    "sg:city":"Remsen",
    "sg:classifiers":[
        {
            "category":"Farming",
            "subcategory":"Livestock Farm",
            "type":"Manufacturing & Wholesale Goods"
        }
    ],
    "sg:phone":"+1 315 831 8863",
    "sg:postcode":"13438",
    "sg:province":"NY",
    "sg:tags":[
        "beef",
        "feedlot",
        "cattle"
    ],
    "wof:name":"Wesley Tompkins",
    "wof:placetype":"venue"
},
  "geometry": {"coordinates":[-75.157188,43.330936],"type":"Point"}
}