{
  "type": "Feature",
  "properties": {
    "addr:full":"199 Chambers St New York NY 10007",
    "addr:housenumber":"199",
    "addr:postcode":"10007",
    "addr:street":"Chambers St",
    "iso:country":"US",
    "sg:address":"199 Chambers St",
    "sg:city":"New York",
    "sg:classifiers":[
        {
            "category":"Shopping",
            "subcategory":"Books",
            "type":"Retail Goods"
        }
    ],
    "sg:phone":"+1 212 267 3474",
    "sg:postcode":"10007",
    "sg:province":"NY",
    "sg:tags":[
        "dealer"
    ],
    "wof:name":"Barnes & Noble Bookstore 731",
    "wof:placetype":"venue"
},
  "geometry": {"coordinates":[-74.012135,40.716862],"type":"Point"}
}