{
  "type": "Feature",
  "properties": {
    "addr:full":"114 Carpenter Ave Tuckahoe NY 10707",
    "addr:housenumber":"114",
    "addr:postcode":"10707",
    "addr:street":"Carpenter Ave",
    "iso:country":"US",
    "sg:address":"114 Carpenter Ave",
    "sg:city":"Tuckahoe",
    "sg:classifiers":[
        {
            "category":"Food & Beverages",
            "subcategory":"Chocolate",
            "type":"Retail Goods"
        }
    ],
    "sg:phone":"+1 914 320 9615",
    "sg:postcode":"10707",
    "sg:province":"NY",
    "sg:tags":[
        "processor",
        "canners"
    ],
    "wof:name":"Global Food Source & Co. Inc.",
    "wof:placetype":"venue"
},
  "geometry": {"coordinates":[-73.828626,40.959049],"type":"Point"}
}