{
  "type": "Feature",
  "properties": {
    "addr:full":"43 N Plank Rd Newburgh NY 12550",
    "addr:housenumber":"43",
    "addr:postcode":"12550",
    "addr:street":"N Plank Rd",
    "iso:country":"US",
    "sg:address":"43 N Plank Rd",
    "sg:city":"Newburgh",
    "sg:classifiers":[
        {
            "category":"Banks & Credit Unions",
            "subcategory":"Bank",
            "type":"Services"
        }
    ],
    "sg:phone":"+1 845 565 2403",
    "sg:postcode":"12550",
    "sg:province":"NY",
    "wof:name":"Wachovia",
    "wof:placetype":"venue"
},
  "geometry": {"coordinates":[-74.030197,41.523499],"type":"Point"}
}