{
  "type": "Feature",
  "properties": {
    "addr:full":"168 Golf Ln Medford NY 11763",
    "addr:housenumber":"168",
    "addr:postcode":"11763",
    "addr:street":"Golf Ln",
    "iso:country":"US",
    "sg:address":"168 Golf Ln",
    "sg:city":"Medford",
    "sg:classifiers":[
        {
            "category":"Communications",
            "subcategory":"Film & Video Production",
            "type":"Services"
        }
    ],
    "sg:phone":"+1 631 929 5661",
    "sg:postcode":"11763",
    "sg:province":"NY",
    "sg:tags":[
        "taping"
    ],
    "wof:name":"Community Video & Film",
    "wof:placetype":"venue"
},
  "geometry": {"coordinates":[-73.001954,40.841353],"type":"Point"}
}