{
  "type": "Feature",
  "properties": {
    "addr:full":"266 W. 47th Street New York NY 10019",
    "addr:housenumber":"266",
    "addr:postcode":"10019",
    "addr:street":"W. 47Th Street",
    "iso:country":"US",
    "sg:address":"266 W. 47th Street",
    "sg:city":"New York",
    "sg:classifiers":[
        {
            "category":"Bars & Pubs",
            "subcategory":"Nightclub",
            "type":"Food & Drink"
        }
    ],
    "sg:phone":"+1 212 221 3960",
    "sg:postcode":"10019",
    "sg:province":"NY",
    "sg:tags":[
        "nightlife"
    ],
    "sg:website":"www.theencorenyc.com",
    "wof:name":"The Encore",
    "wof:placetype":"venue"
},
  "geometry": {"coordinates":[-73.986603,40.759899],"type":"Point"}
}