{
  "type": "Feature",
  "properties": {
    "iso:country":"US",
    "sg:address":"227 Ruggles Rd",
    "sg:city":"Saratoga Springs",
    "sg:classifiers":[
        {
            "category":"Social Services",
            "type":"Services"
        }
    ],
    "sg:phone":"+1   ",
    "sg:postcode":"12866",
    "sg:province":"NY",
    "wof:name":"Saratoga Co Assoc Rtrd Citizen",
    "wof:placetype":"venue"
},
  "geometry": {"coordinates":[-73.687033,43.121869],"type":"Point"}
}