{
  "type": "Feature",
  "properties": {
    "addr:full":"40 Cayuga Rd Canandaigua NY 14424",
    "addr:housenumber":"40",
    "addr:postcode":"14424",
    "addr:street":"Cayuga Rd",
    "iso:country":"US",
    "sg:address":"40 Cayuga Rd",
    "sg:city":"Canandaigua",
    "sg:classifiers":[
        {
            "category":"Health Services",
            "subcategory":"Chiropractor",
            "type":"Services"
        }
    ],
    "sg:phone":"+1 585 396 2150",
    "sg:postcode":"14424",
    "sg:province":"NY",
    "wof:name":"Sullivan Chiropractic",
    "wof:placetype":"venue"
},
  "geometry": {"coordinates":[-77.284995,42.907478],"type":"Point"}
}