{
  "type": "Feature",
  "properties": {
    "addr:full":"1579 Valencia Rd Schenectady NY 12309",
    "addr:housenumber":"1579",
    "addr:postcode":"12309",
    "addr:street":"Valencia Rd",
    "iso:country":"US",
    "sg:address":"1579 Valencia Rd",
    "sg:city":"Schenectady",
    "sg:classifiers":[
        {
            "category":"Real Estate",
            "subcategory":"Real Estate Agent",
            "type":"Services"
        }
    ],
    "sg:phone":"+1 518 377 2082",
    "sg:postcode":"12309",
    "sg:province":"NY",
    "wof:name":"Home Detective Home Insptn Svc",
    "wof:placetype":"venue"
},
  "geometry": {"coordinates":[-73.89540700000001,42.818339],"type":"Point"}
}