{
  "type": "Feature",
  "properties": {
    "iso:country":"US",
    "sg:address":"440 W 53 St",
    "sg:city":"New York",
    "sg:classifiers":[
        {
            "category":"Professional",
            "subcategory":"Research",
            "type":"Services"
        }
    ],
    "sg:phone":"+1 212 977 4439",
    "sg:postcode":"10019",
    "sg:province":"NY",
    "sg:tags":[
        "foundation",
        "philanthropic"
    ],
    "wof:name":"Everybody Wins Foundation",
    "wof:placetype":"venue"
},
  "geometry": {"coordinates":[-73.98957799999999,40.766006],"type":"Point"}
}