{
  "type": "Feature",
  "properties": {
    "addr:full":"6217 Kenlaren Cir Syracuse NY 13212",
    "addr:housenumber":"6217",
    "addr:postcode":"13212",
    "addr:street":"Kenlaren Cir",
    "iso:country":"US",
    "sg:address":"6217 Kenlaren Cir",
    "sg:city":"Syracuse",
    "sg:classifiers":[
        {
            "category":"Professional",
            "subcategory":"Lawyer & Legal Services",
            "type":"Services"
        }
    ],
    "sg:phone":"+1 315 458 9126",
    "sg:postcode":"13212",
    "sg:province":"NY",
    "sg:tags":[
        "plan"
    ],
    "wof:name":"Suzan Martuscello",
    "wof:placetype":"venue"
},
  "geometry": {"coordinates":[-76.092692,43.139622],"type":"Point"}
}