{
  "type": "Feature",
  "properties": {
    "addr:full":"301 Fayette St Manlius NY 13104",
    "addr:housenumber":"301",
    "addr:postcode":"13104",
    "addr:street":"Fayette St",
    "iso:country":"US",
    "sg:address":"301 Fayette St",
    "sg:city":"Manlius",
    "sg:classifiers":[
        {
            "category":"Restaurant",
            "type":"Food & Drink"
        }
    ],
    "sg:phone":"+1 315 682 9955",
    "sg:postcode":"13104",
    "sg:province":"NY",
    "wof:name":"What's Your Beef",
    "wof:placetype":"venue"
},
  "geometry": {"coordinates":[-75.982703,43.004388],"type":"Point"}
}