{
  "type": "Feature",
  "properties": {
    "iso:country":"US",
    "sg:address":"2755 Lakeshore Rd",
    "sg:city":"Chazy",
    "sg:classifiers":[
        {
            "category":"Farming",
            "subcategory":"Dairy Farm",
            "type":"Manufacturing & Wholesale Goods"
        }
    ],
    "sg:phone":"+1 518 298 5611",
    "sg:postcode":"12921",
    "sg:province":"NY",
    "wof:name":"Bobby Menard",
    "wof:placetype":"venue"
},
  "geometry": {"coordinates":[-73.407507,44.939398],"type":"Point"}
}