{
  "type": "Feature",
  "properties": {
    "iso:country":"US",
    "sg:address":"20 Everett Ave",
    "sg:city":"Staten Island",
    "sg:classifiers":[
        {
            "category":"Education",
            "subcategory":"Special Training",
            "type":"Public Place"
        }
    ],
    "sg:phone":"+1   ",
    "sg:postcode":"10309",
    "sg:province":"NY",
    "sg:tags":[
        "book"
    ],
    "wof:name":"Readingladycom Inc",
    "wof:placetype":"venue"
},
  "geometry": {"coordinates":[-74.205234,40.518571],"type":"Point"}
}