{
  "type": "Feature",
  "properties": {
    "addr:full":"3706 Broadway Astoria NY 11103",
    "addr:housenumber":"3706",
    "addr:postcode":"11103",
    "addr:street":"Broadway",
    "iso:country":"US",
    "sg:address":"3706 Broadway",
    "sg:city":"Astoria",
    "sg:classifiers":[
        {
            "category":"Personal",
            "subcategory":"Barber",
            "type":"Services"
        }
    ],
    "sg:phone":"+1 718 626 7454",
    "sg:postcode":"11103",
    "sg:province":"NY",
    "wof:name":"Ideal Barber Shop",
    "wof:placetype":"venue"
},
  "geometry": {"coordinates":[-73.920601,40.759602],"type":"Point"}
}