{
  "type": "Feature",
  "properties": {
    "addr:full":"4848 State Hwy 365 Oneida NY 13421",
    "addr:housenumber":"4848",
    "addr:postcode":"13421",
    "addr:street":"State Hwy 365",
    "iso:country":"US",
    "sg:address":"4848 State Hwy 365",
    "sg:city":"Oneida",
    "sg:classifiers":[
        {
            "category":"Retail",
            "subcategory":"Auto Repair",
            "type":"Services"
        }
    ],
    "sg:phone":"+1   ",
    "sg:postcode":"13421",
    "sg:province":"NY",
    "sg:tags":[
        "shop",
        "automotive",
        "used",
        "trail",
        "general"
    ],
    "wof:name":"Kinneys Kar Kare Service",
    "wof:placetype":"venue"
},
  "geometry": {"coordinates":[-75.621025,43.09683],"type":"Point"}
}