{
  "type": "Feature",
  "properties": {
    "iso:country":"US",
    "sg:address":"1370 Broadway",
    "sg:city":"New York",
    "sg:classifiers":[
        {
            "category":"Wholesale",
            "subcategory":"Apparel",
            "type":"Manufacturing & Wholesale Goods"
        }
    ],
    "sg:phone":"+1 212 563 1663",
    "sg:postcode":"10018",
    "sg:province":"NY",
    "sg:tags":[
        "trade"
    ],
    "wof:name":"Coupe DEtat",
    "wof:placetype":"venue"
},
  "geometry": {"coordinates":[-73.987644,40.751419],"type":"Point"}
}