{
  "type": "Feature",
  "properties": {
    "addr:full":"199 Mott St New York NY 10012",
    "addr:housenumber":"199",
    "addr:postcode":"10012",
    "addr:street":"Mott St",
    "iso:country":"US",
    "sg:address":"199 Mott St",
    "sg:city":"New York",
    "sg:classifiers":[
        {
            "category":"Restaurant",
            "type":"Food & Drink"
        }
    ],
    "sg:phone":"+1   ",
    "sg:postcode":"10012",
    "sg:province":"NY",
    "sg:tags":[
        "drinking",
        "eating"
    ],
    "wof:name":"Original Vincents The",
    "wof:placetype":"venue"
},
  "geometry": {"coordinates":[-73.995661,40.721226],"type":"Point"}
}