{
  "type": "Feature",
  "properties": {
    "iso:country":"US",
    "sg:address":"136 W Main St",
    "sg:city":"Bay Shore",
    "sg:classifiers":[
        {
            "category":"Banks & Credit Unions",
            "subcategory":"Bank",
            "type":"Services"
        }
    ],
    "sg:phone":"+1 631 206 2222",
    "sg:postcode":"11706",
    "sg:province":"NY",
    "sg:tags":[
        "broker",
        "mortgage"
    ],
    "wof:name":"Northeast Equities Funding",
    "wof:placetype":"venue"
},
  "geometry": {"coordinates":[-73.25100500000001,40.719522],"type":"Point"}
}