{
  "type": "Feature",
  "properties": {
    "addr:full":"145 Duane St New York NY 10013",
    "addr:housenumber":"145",
    "addr:postcode":"10013",
    "addr:street":"Duane St",
    "iso:country":"US",
    "sg:address":"145 Duane St",
    "sg:city":"New York",
    "sg:classifiers":[
        {
            "category":"Professional",
            "type":"Services"
        }
    ],
    "sg:phone":"+1 212 566 0559",
    "sg:postcode":"10013",
    "sg:province":"NY",
    "sg:tags":[
        "establishment"
    ],
    "wof:name":"Duvoor Corp",
    "wof:placetype":"venue"
},
  "geometry": {"coordinates":[-74.00754499999999,40.716169],"type":"Point"}
}