{
  "type": "Feature",
  "properties": {
    "addr:full":"4309 E Genesee St Syracuse NY 13214",
    "addr:housenumber":"4309",
    "addr:postcode":"13214",
    "addr:street":"E Genesee St",
    "iso:country":"US",
    "sg:address":"4309 E Genesee St",
    "sg:city":"Syracuse",
    "sg:classifiers":[
        {
            "category":"Building & Trades",
            "subcategory":"Construction",
            "type":"Services"
        }
    ],
    "sg:phone":"+1 315 449 4649",
    "sg:postcode":"13214",
    "sg:province":"NY",
    "sg:tags":[
        "contractor"
    ],
    "wof:name":"Syracuse Office",
    "wof:placetype":"venue"
},
  "geometry": {"coordinates":[-76.06867099999999,43.035551],"type":"Point"}
}