{
  "type": "Feature",
  "properties": {
    "iso:country":"US",
    "sg:address":"195 Wall St",
    "sg:city":"Kingston",
    "sg:classifiers":[
        {
            "category":"Professional",
            "subcategory":"Lawyer & Legal Services",
            "type":"Services"
        }
    ],
    "sg:phone":"+1 845 331 1500",
    "sg:postcode":"12401",
    "sg:province":"NY",
    "sg:tags":[
        "attorney"
    ],
    "wof:name":"Melvin T Higgins",
    "wof:placetype":"venue"
},
  "geometry": {"coordinates":[-74.01810999999999,41.930239],"type":"Point"}
}