{
  "type": "Feature",
  "properties": {
    "addr:full":"1290 North Ave New Rochelle NY 10804",
    "addr:housenumber":"1290",
    "addr:postcode":"10804",
    "addr:street":"North Ave",
    "iso:country":"US",
    "sg:address":"1290 North Ave",
    "sg:city":"New Rochelle",
    "sg:classifiers":[
        {
            "category":"Shopping",
            "subcategory":"Clothing, Apparel, & Fashions",
            "type":"Retail Goods"
        }
    ],
    "sg:phone":"+1   ",
    "sg:postcode":"10804",
    "sg:province":"NY",
    "sg:tags":[
        "store"
    ],
    "wof:name":"Annie Sez 340",
    "wof:placetype":"venue"
},
  "geometry": {"coordinates":[-73.795417,40.945369],"type":"Point"}
}