{
  "type": "Feature",
  "properties": {
    "addr:full":"9 Commercial St Hicksville NY 11801",
    "addr:housenumber":"9",
    "addr:postcode":"11801",
    "addr:street":"Commercial St",
    "iso:country":"US",
    "sg:address":"9 Commercial St",
    "sg:city":"Hicksville",
    "sg:classifiers":[
        {
            "category":"Building & Trades",
            "subcategory":"Construction",
            "type":"Services"
        },
        {
            "category":"Real Estate",
            "subcategory":"Real Estate Operator",
            "type":"Services"
        }
    ],
    "sg:phone":"+1 516 935 8383",
    "sg:postcode":"11801",
    "sg:province":"NY",
    "sg:tags":[
        "company",
        "industrial",
        "holding",
        "contractor"
    ],
    "wof:name":"Fore Improvement Corp",
    "wof:placetype":"venue"
},
  "geometry": {"coordinates":[-73.508869,40.76052],"type":"Point"}
}