{
  "type": "Feature",
  "properties": {
    "addr:full":"71 Victor Dr East Northport NY 11731",
    "addr:housenumber":"71",
    "addr:postcode":"11731",
    "addr:street":"Victor Dr",
    "iso:country":"US",
    "sg:address":"71 Victor Dr",
    "sg:city":"East Northport",
    "sg:classifiers":[
        {
            "category":"Building & Trades",
            "subcategory":"Cleaning & Sanitation",
            "type":"Services"
        }
    ],
    "sg:phone":"+1 631 858 1784",
    "sg:postcode":"11731",
    "sg:province":"NY",
    "sg:tags":[
        "janitor"
    ],
    "wof:name":"Ingrid's Cleaning Svc Inc",
    "wof:placetype":"venue"
},
  "geometry": {"coordinates":[-73.31885200000001,40.833178],"type":"Point"}
}