{
  "type": "Feature",
  "properties": {
    "iso:country":"US",
    "sg:address":"1 College Ave",
    "sg:city":"Geneseo",
    "sg:classifiers":[
        {
            "category":"Organizations",
            "subcategory":"Labor Organization",
            "type":"Services"
        }
    ],
    "sg:phone":"+1 585 245 5380",
    "sg:postcode":"14420",
    "sg:province":"NY",
    "wof:name":"United University Professions",
    "wof:placetype":"venue"
},
  "geometry": {"coordinates":[-77.93136199999999,43.231317],"type":"Point"}
}