{
  "type": "Feature",
  "properties": {
    "addr:full":"249 9th St Brooklyn NY 11215",
    "addr:housenumber":"249",
    "addr:postcode":"11215",
    "addr:street":"9Th St",
    "iso:country":"US",
    "sg:address":"249 9th St",
    "sg:city":"Brooklyn",
    "sg:classifiers":[
        {
            "category":"Organizations",
            "subcategory":"Religious Organization",
            "type":"Services"
        }
    ],
    "sg:phone":"+1 718 965 4025",
    "sg:postcode":"11215",
    "sg:province":"NY",
    "sg:tags":[
        "church"
    ],
    "wof:name":"Carmelite Priory",
    "wof:placetype":"venue"
},
  "geometry": {"coordinates":[-73.98651599999999,40.669398],"type":"Point"}
}