{
  "type": "Feature",
  "properties": {
    "addr:full":"2901 39th Avenue Long Island City NY 11101",
    "addr:housenumber":"2901",
    "addr:postcode":"11101",
    "addr:street":"39Th Avenue",
    "iso:country":"US",
    "sg:address":"2901 39th Avenue",
    "sg:city":"Long Island City",
    "sg:classifiers":[
        {
            "category":"Restaurant",
            "type":"Food & Drink"
        }
    ],
    "sg:phone":"+1 718 349 6368",
    "sg:postcode":"11101",
    "sg:province":"NY",
    "wof:name":"Lic Deli & Grocery",
    "wof:placetype":"venue"
},
  "geometry": {"coordinates":[-73.93428299999999,40.753559],"type":"Point"}
}