{
  "type": "Feature",
  "properties": {
    "addr:full":"10 Kimball Pl Mount Vernon NY 10550",
    "addr:housenumber":"10",
    "addr:postcode":"10550",
    "addr:street":"Kimball Pl",
    "iso:country":"US",
    "sg:address":"10 Kimball Pl",
    "sg:city":"Mount Vernon",
    "sg:classifiers":[
        {
            "category":"Professional",
            "subcategory":"Advertising",
            "type":"Services"
        }
    ],
    "sg:phone":"+1 914 664 7600",
    "sg:postcode":"10550",
    "sg:province":"NY",
    "sg:tags":[
        "mail",
        "direct"
    ],
    "wof:name":"Speedy Mail Inc",
    "wof:placetype":"venue"
},
  "geometry": {"coordinates":[-73.820322,40.898788],"type":"Point"}
}