{
  "type": "Feature",
  "properties": {
    "iso:country":"US",
    "sg:address":"59 N Plank Rd",
    "sg:city":"Newburgh",
    "sg:classifiers":[
        {
            "category":"Shopping",
            "subcategory":"Department Store",
            "type":"Retail Goods"
        }
    ],
    "sg:phone":"+1 845 568 0023",
    "sg:postcode":"12550",
    "sg:province":"NY",
    "sg:website":"www.biglots.com",
    "wof:name":"Big Lots",
    "wof:placetype":"venue"
},
  "geometry": {"coordinates":[-74.032501,41.5247],"type":"Point"}
}