{
  "type": "Feature",
  "properties": {
    "addr:full":"141 Mitchell Hollow Rd Windham NY 12496",
    "addr:housenumber":"141",
    "addr:postcode":"12496",
    "addr:street":"Mitchell Hollow Rd",
    "iso:country":"US",
    "sg:address":"141 Mitchell Hollow Rd",
    "sg:city":"Windham",
    "sg:classifiers":[
        {
            "category":"Building & Trades",
            "subcategory":"Landscaping Services",
            "type":"Services"
        }
    ],
    "sg:phone":"+1 518 734 6873",
    "sg:postcode":"12496",
    "sg:province":"NY",
    "sg:tags":[
        "excavation",
        "landscape",
        "contractor"
    ],
    "wof:name":"Gr Landscaping & Excavation",
    "wof:placetype":"venue"
},
  "geometry": {"coordinates":[-74.2473,42.313021],"type":"Point"}
}