{
  "type": "Feature",
  "properties": {
    "addr:full":"123 1st Avenue New York NY 10003",
    "addr:housenumber":"123",
    "addr:postcode":"10003",
    "addr:street":"1St Avenue",
    "iso:country":"US",
    "sg:address":"123 1st Avenue",
    "sg:city":"New York",
    "sg:classifiers":[
        {
            "category":"Restaurant",
            "type":"Food & Drink"
        }
    ],
    "sg:phone":"+1 212 387 9945",
    "sg:postcode":"10003",
    "sg:province":"NY",
    "wof:name":"Warsaw Restaurant Corporation",
    "wof:placetype":"venue"
},
  "geometry": {"coordinates":[-73.985602,40.727397],"type":"Point"}
}