{
  "type": "Feature",
  "properties": {
    "addr:full":"314 Reservoir Hill Rd Candor NY 13743",
    "addr:housenumber":"314",
    "addr:postcode":"13743",
    "addr:street":"Reservoir Hill Rd",
    "iso:country":"US",
    "sg:address":"314 Reservoir Hill Rd",
    "sg:city":"Candor",
    "sg:classifiers":[
        {
            "category":"Building & Trades",
            "subcategory":"Equipment Rental",
            "type":"Services"
        }
    ],
    "sg:phone":"+1 607 659 5195",
    "sg:postcode":"13743",
    "sg:province":"NY",
    "sg:tags":[
        "yard",
        "leasing",
        "store"
    ],
    "wof:name":"Precision Tent Rentals",
    "wof:placetype":"venue"
},
  "geometry": {"coordinates":[-76.33472999999999,42.233814],"type":"Point"}
}