{
  "type": "Feature",
  "properties": {
    "addr:full":"3604 Townhouse Dr Coram NY 11727",
    "addr:housenumber":"3604",
    "addr:postcode":"11727",
    "addr:street":"Townhouse Dr",
    "iso:country":"US",
    "sg:address":"3604 Townhouse Dr",
    "sg:city":"Coram",
    "sg:classifiers":[
        {
            "category":"Professional",
            "subcategory":"Engineering",
            "type":"Services"
        }
    ],
    "sg:phone":"+1   ",
    "sg:postcode":"11727",
    "sg:province":"NY",
    "sg:tags":[
        "consulting"
    ],
    "wof:name":"Amseta Corp",
    "wof:placetype":"venue"
},
  "geometry": {"coordinates":[-73.01087099999999,40.874288],"type":"Point"}
}