{
  "type": "Feature",
  "properties": {
    "iso:country":"US",
    "sg:address":"47 Juniper Cir",
    "sg:city":"Brewster",
    "sg:classifiers":[
        {
            "category":"Manufacturing",
            "subcategory":"Musical Instruments",
            "type":"Manufacturing & Wholesale Goods"
        }
    ],
    "sg:phone":"+1   ",
    "sg:postcode":"10509",
    "sg:province":"NY",
    "sg:tags":[
        "mfg"
    ],
    "wof:name":"Goodman Guitars",
    "wof:placetype":"venue"
},
  "geometry": {"coordinates":[-73.602215,41.415158],"type":"Point"}
}