{
  "type": "Feature",
  "properties": {
    "iso:country":"US",
    "sg:address":"43 Echo Ave",
    "sg:city":"Miller Place",
    "sg:classifiers":[
        {
            "category":"Social Services",
            "subcategory":"Child Care",
            "type":"Services"
        },
        {
            "category":"Education",
            "subcategory":"Preschool",
            "type":"Public Place"
        },
        {
            "category":"Education",
            "subcategory":"School",
            "type":"Public Place"
        }
    ],
    "sg:phone":"+1 631 331 5351",
    "sg:postcode":"11764",
    "sg:province":"NY",
    "sg:tags":[
        "elementary",
        "day"
    ],
    "wof:name":"KIDS QUEST OF MILLER PLACE",
    "wof:placetype":"venue"
},
  "geometry": {"coordinates":[-73.356397,40.943062],"type":"Point"}
}