{
  "type": "Feature",
  "properties": {
    "iso:country":"US",
    "sg:address":"61 E Main St",
    "sg:city":"Wolcott",
    "sg:phone":"+1 315 594 2785",
    "sg:postcode":"14590",
    "sg:province":"NY",
    "sg:website":"http://www.lakeontario.net/palace",
    "wof:name":"Palace Theatre",
    "wof:placetype":"venue"
},
  "geometry": {"coordinates":[-76.822281,43.22296],"type":"Point"}
}