{
  "type": "Feature",
  "properties": {
    "addr:full":"764 Main St Poughkeepsie NY 12603",
    "addr:housenumber":"764",
    "addr:postcode":"12603",
    "addr:street":"Main St",
    "iso:country":"US",
    "sg:address":"764 Main St",
    "sg:city":"Poughkeepsie",
    "sg:classifiers":[
        {
            "category":"Autos & Motor Vehicles",
            "subcategory":"Automobile Sales",
            "type":"Retail Goods"
        }
    ],
    "sg:phone":"+1 845 454 8330",
    "sg:postcode":"12603",
    "sg:province":"NY",
    "sg:tags":[
        "dealers-used",
        "car",
        "used",
        "cars-wholesale",
        "new"
    ],
    "wof:name":"Town & Country Motors",
    "wof:placetype":"venue"
},
  "geometry": {"coordinates":[-73.90316,41.696381],"type":"Point"}
}