{
  "type": "Feature",
  "properties": {
    "iso:country":"US",
    "sg:address":"114 W 87 St",
    "sg:city":"New York",
    "sg:classifiers":[
        {
            "category":"Communications",
            "subcategory":"Film & Video Production",
            "type":"Services"
        }
    ],
    "sg:phone":"+1 917 705 8570",
    "sg:postcode":"10024",
    "sg:province":"NY",
    "sg:tags":[
        "motion",
        "picture",
        "studio",
        "producer"
    ],
    "wof:name":"LA Luna Sicilia Productions",
    "wof:placetype":"venue"
},
  "geometry": {"coordinates":[-73.974251,40.788123],"type":"Point"}
}