{
  "type": "Feature",
  "properties": {
    "addr:full":"22 Dekalb Ave Brooklyn NY 11201",
    "addr:housenumber":"22",
    "addr:postcode":"11201",
    "addr:street":"Dekalb Ave",
    "iso:country":"US",
    "sg:address":"22 Dekalb Ave",
    "sg:city":"Brooklyn",
    "sg:classifiers":[
        {
            "category":"Shopping",
            "subcategory":"Florist",
            "type":"Retail Goods"
        }
    ],
    "sg:phone":"+1 718 596 9119",
    "sg:postcode":"11201",
    "sg:province":"NY",
    "sg:tags":[
        "nursery",
        "gardening"
    ],
    "wof:name":"Ace Indoor Garden Center Inc",
    "wof:placetype":"venue"
},
  "geometry": {"coordinates":[-73.982201,40.689899],"type":"Point"}
}