{
  "type": "Feature",
  "properties": {
    "iso:country":"US",
    "sg:address":"2737 Cruger Ave",
    "sg:city":"Bronx",
    "sg:classifiers":[
        {
            "category":"Organizations",
            "subcategory":"Professional Association",
            "type":"Services"
        }
    ],
    "sg:phone":"+1 718 655 4616",
    "sg:postcode":"10467",
    "sg:province":"NY",
    "sg:tags":[
        "sale"
    ],
    "wof:name":"Diamond Fuel Oil",
    "wof:placetype":"venue"
},
  "geometry": {"coordinates":[-73.866347,40.865894],"type":"Point"}
}