{
  "type": "Feature",
  "properties": {
    "addr:full":"3577 Harlem Rd Buffalo NY 14225",
    "addr:housenumber":"3577",
    "addr:postcode":"14225",
    "addr:street":"Harlem Rd",
    "iso:country":"US",
    "sg:address":"3577 Harlem Rd",
    "sg:city":"Buffalo",
    "sg:classifiers":[
        {
            "category":"Recreation",
            "type":"Entertainment"
        }
    ],
    "sg:phone":"+1 716 836 6366",
    "sg:postcode":"14225",
    "sg:province":"NY",
    "sg:tags":[
        "entertainers-family",
        "business"
    ],
    "wof:name":"Neon Entertainment",
    "wof:placetype":"venue"
},
  "geometry": {"coordinates":[-78.784126,42.941299],"type":"Point"}
}