{
  "type": "Feature",
  "properties": {
    "iso:country":"US",
    "sg:address":"185 Randolph St",
    "sg:city":"Brooklyn",
    "sg:classifiers":[
        {
            "category":"Freight",
            "type":"Transportation"
        }
    ],
    "sg:phone":"+1 718 456 9703",
    "sg:postcode":"11237",
    "sg:province":"NY",
    "sg:tags":[
        "mover"
    ],
    "sg:website":"www.tobergroup.com",
    "wof:name":"TDY Freight Svc LTD",
    "wof:placetype":"venue"
},
  "geometry": {"coordinates":[-73.925208,40.709778],"type":"Point"}
}