{
  "type": "Feature",
  "properties": {
    "addr:full":"21 Dongan Avenue Staten Island NY 10314",
    "addr:housenumber":"21",
    "addr:postcode":"10314",
    "addr:street":"Dongan Avenue",
    "iso:country":"US",
    "sg:address":"21 Dongan Avenue",
    "sg:city":"Staten Island",
    "sg:classifiers":[
        {
            "category":"Education",
            "subcategory":"Preschool",
            "type":"Public Place"
        }
    ],
    "sg:phone":"+1 718 477 2936",
    "sg:postcode":"10314",
    "sg:province":"NY",
    "wof:name":"Jonah's Ark Pre-School/Day Care",
    "wof:placetype":"venue"
},
  "geometry": {"coordinates":[-74.121183,40.614772],"type":"Point"}
}