{
  "type": "Feature",
  "properties": {
    "addr:full":"2260 Washington Ave Bronx NY 10457",
    "addr:housenumber":"2260",
    "addr:postcode":"10457",
    "addr:street":"Washington Ave",
    "iso:country":"US",
    "sg:address":"2260 Washington Ave",
    "sg:city":"Bronx",
    "sg:classifiers":[
        {
            "category":"Travel",
            "subcategory":"Travel Agent",
            "type":"Entertainment"
        }
    ],
    "sg:phone":"+1   ",
    "sg:postcode":"10457",
    "sg:province":"NY",
    "sg:tags":[
        "agency"
    ],
    "wof:name":"Rafa Wena Enterprises",
    "wof:placetype":"venue"
},
  "geometry": {"coordinates":[-73.89351000000001,40.854524],"type":"Point"}
}