{
  "type": "Feature",
  "properties": {
    "addr:full":"1 Speedway Dr 240 Weedsport NY 13166",
    "addr:housenumber":"1",
    "addr:postcode":"240;13166",
    "addr:street":"Speedway Dr",
    "iso:country":"US",
    "sg:address":"1 Speedway Dr 240",
    "sg:city":"Weedsport",
    "sg:classifiers":[
        {
            "category":"Museum",
            "type":"Entertainment"
        }
    ],
    "sg:phone":"+1 315 834 6667",
    "sg:postcode":"13166",
    "sg:province":"NY",
    "wof:name":"Dirt Classic Car Museum",
    "wof:placetype":"venue"
},
  "geometry": {"coordinates":[-76.546959,43.056],"type":"Point"}
}