{
  "type": "Feature",
  "properties": {
    "iso:country":"US",
    "sg:address":"3 Frontage Rd",
    "sg:city":"Gloversville",
    "sg:classifiers":[
        {
            "category":"Government",
            "subcategory":"Office",
            "type":"Public Place"
        }
    ],
    "sg:phone":"+1 518 773 4532",
    "sg:postcode":"12078",
    "sg:province":"NY",
    "sg:tags":[
        "city",
        "taxation"
    ],
    "sg:website":"www.cityofgloversville.com",
    "wof:name":"Gloversville Finance Dept",
    "wof:placetype":"venue"
},
  "geometry": {"coordinates":[-74.348888,43.050783],"type":"Point"}
}