{
  "type": "Feature",
  "properties": {
    "iso:country":"US",
    "sg:address":"88 Cuttermill Rd",
    "sg:city":"Great Neck",
    "sg:classifiers":[
        {
            "category":"Real Estate",
            "subcategory":"Real Estate Operator",
            "type":"Services"
        }
    ],
    "sg:phone":"+1 516 466 7302",
    "sg:postcode":"11021",
    "sg:province":"NY",
    "sg:tags":[
        "building",
        "apartment"
    ],
    "wof:name":"Pavillion",
    "wof:placetype":"venue"
},
  "geometry": {"coordinates":[-73.727766,40.787268],"type":"Point"}
}