{
  "type": "Feature",
  "properties": {
    "iso:country":"US",
    "sg:address":"200 5th Ave",
    "sg:city":"New York",
    "sg:classifiers":[
        {
            "category":"Shopping",
            "subcategory":"Gifts & Souvenirs",
            "type":"Retail Goods"
        }
    ],
    "sg:phone":"+1 212 627 9286",
    "sg:postcode":"10010",
    "sg:province":"NY",
    "sg:tags":[
        "material",
        "wrapping"
    ],
    "sg:website":"www.cleowrap.com",
    "wof:name":"Cleo Inc",
    "wof:placetype":"venue"
},
  "geometry": {"coordinates":[-73.989532,40.741642],"type":"Point"}
}