{
  "type": "Feature",
  "properties": {
    "addr:full":"11 Hampshire Ln Mendon NY 14506",
    "addr:housenumber":"11",
    "addr:postcode":"14506",
    "addr:street":"Hampshire Ln",
    "iso:country":"US",
    "sg:address":"11 Hampshire Ln",
    "sg:city":"Mendon",
    "sg:classifiers":[
        {
            "category":"Professional",
            "subcategory":"Management & Consulting",
            "type":"Services"
        }
    ],
    "sg:phone":"+1 585 624 5410",
    "sg:postcode":"14506",
    "sg:province":"NY",
    "sg:tags":[
        "consultant",
        "business"
    ],
    "wof:name":"Victor Merkel Realty",
    "wof:placetype":"venue"
},
  "geometry": {"coordinates":[-77.51147,43.000392],"type":"Point"}
}