{
  "type": "Feature",
  "properties": {
    "iso:country":"US",
    "sg:address":"422 McDonald Ave",
    "sg:city":"Brooklyn",
    "sg:classifiers":[
        {
            "category":"Arts & Performance",
            "subcategory":"Arts Center",
            "type":"Entertainment"
        }
    ],
    "sg:postcode":"11218",
    "sg:province":"NY",
    "sg:website":"www.vincentpaulmusic.com",
    "wof:name":"Vincent Paul Music and Entertainment",
    "wof:placetype":"venue"
},
  "geometry": {"coordinates":[-73.97964,40.643905],"type":"Point"}
}