{
  "type": "Feature",
  "properties": {
    "iso:country":"US",
    "sg:address":"271 McCormack Rd N",
    "sg:city":"Slingerlands",
    "sg:classifiers":[
        {
            "category":"Manufacturing",
            "subcategory":"Pottery",
            "type":"Manufacturing & Wholesale Goods"
        }
    ],
    "sg:phone":"+1   ",
    "sg:postcode":"12159",
    "sg:province":"NY",
    "sg:tags":[
        "potter"
    ],
    "wof:name":"Ullas Pottery",
    "wof:placetype":"venue"
},
  "geometry": {"coordinates":[-73.843113,42.640338],"type":"Point"}
}