{
  "type": "Feature",
  "properties": {
    "iso:country":"US",
    "sg:address":"1635 Great Neck Rd",
    "sg:city":"Copiague",
    "sg:classifiers":[
        {
            "category":"Home & Garden",
            "subcategory":"Furniture",
            "type":"Retail Goods"
        }
    ],
    "sg:phone":"+1 631 841 6111",
    "sg:postcode":"11726",
    "sg:province":"NY",
    "wof:name":"Danilo's Furniture",
    "wof:placetype":"venue"
},
  "geometry": {"coordinates":[-73.399339,40.679753],"type":"Point"}
}