{
  "type": "Feature",
  "properties": {
    "iso:country":"US",
    "sg:address":"90 Broad St",
    "sg:city":"New York",
    "sg:phone":"+1   ",
    "sg:postcode":"10004",
    "sg:province":"NY",
    "sg:tags":[
        "broadcasting",
        "facsimile"
    ],
    "wof:name":"Summit Partners Inc",
    "wof:placetype":"venue"
},
  "geometry": {"coordinates":[-74.011594,40.703578],"type":"Point"}
}