{
  "type": "Feature",
  "properties": {
    "addr:full":"148 Convent Rd Nanuet NY 10954",
    "addr:housenumber":"148",
    "addr:postcode":"10954",
    "addr:street":"Convent Rd",
    "iso:country":"US",
    "sg:address":"148 Convent Rd",
    "sg:city":"Nanuet",
    "sg:classifiers":[
        {
            "category":"Professional",
            "type":"Services"
        }
    ],
    "sg:phone":"+1 845 624 4477",
    "sg:postcode":"10954",
    "sg:province":"NY",
    "sg:tags":[
        "establishment"
    ],
    "wof:name":"Seton Village Housing Corp",
    "wof:placetype":"venue"
},
  "geometry": {"coordinates":[-74.032808,41.087999],"type":"Point"}
}