{
  "type": "Feature",
  "properties": {
    "addr:full":"41 Ivy Hill Rd Brewster NY 10509",
    "addr:housenumber":"41",
    "addr:postcode":"10509",
    "addr:street":"Ivy Hill Rd",
    "iso:country":"US",
    "sg:address":"41 Ivy Hill Rd",
    "sg:city":"Brewster",
    "sg:classifiers":[
        {
            "category":"Retail",
            "subcategory":"Car Wash",
            "type":"Services"
        }
    ],
    "sg:phone":"+1   ",
    "sg:postcode":"10509",
    "sg:province":"NY",
    "sg:tags":[
        "carwash"
    ],
    "wof:name":"Buggy Bath & Groom",
    "wof:placetype":"venue"
},
  "geometry": {"coordinates":[-73.651321,41.409282],"type":"Point"}
}