{
  "type": "Feature",
  "properties": {
    "iso:country":"US",
    "sg:address":"26 Greenridge Dr",
    "sg:city":"Clifton Park",
    "sg:classifiers":[
        {
            "category":"Wholesale",
            "subcategory":"Non-durable Goods",
            "type":"Manufacturing & Wholesale Goods"
        }
    ],
    "sg:phone":"+1 518 373 1862",
    "sg:postcode":"12065",
    "sg:province":"NY",
    "wof:name":"Double D Distributor",
    "wof:placetype":"venue"
},
  "geometry": {"coordinates":[-73.793059,42.81626],"type":"Point"}
}