{
  "type": "Feature",
  "properties": {
    "iso:country":"US",
    "sg:address":"4218 Bell Blvd",
    "sg:city":"Bayside",
    "sg:classifiers":[
        {
            "category":"Real Estate",
            "subcategory":"Real Estate Services",
            "type":"Services"
        },
        {
            "category":"Real Estate",
            "subcategory":"Real Estate Agent",
            "type":"Services"
        }
    ],
    "sg:phone":"+1 718 225 0620",
    "sg:postcode":"11361",
    "sg:province":"NY",
    "sg:tags":[
        "buyer",
        "broker"
    ],
    "sg:website":"http://www.pillingrealestate.com",
    "wof:name":"Pilling, Frances Lee",
    "wof:placetype":"venue"
},
  "geometry": {"coordinates":[-73.770523,40.762705],"type":"Point"}
}