{
  "type": "Feature",
  "properties": {
    "addr:full":"1785 215th St Bayside NY 11360",
    "addr:housenumber":"1785",
    "addr:postcode":"11360",
    "addr:street":"215Th St",
    "iso:country":"US",
    "sg:address":"1785 215th St",
    "sg:city":"Bayside",
    "sg:classifiers":[
        {
            "category":"Landmark",
            "subcategory":"Monument",
            "type":"Public Place"
        }
    ],
    "sg:phone":"+1 718 225 1095",
    "sg:postcode":"11360",
    "sg:province":"NY",
    "wof:name":"Design Memorials",
    "wof:placetype":"venue"
},
  "geometry": {"coordinates":[-73.776635,40.784192],"type":"Point"}
}