{
  "type": "Feature",
  "properties": {
    "iso:country":"US",
    "sg:address":"188 6th Ave",
    "sg:city":"Brooklyn",
    "sg:classifiers":[
        {
            "category":"Professional",
            "subcategory":"Business Services",
            "type":"Services"
        }
    ],
    "sg:phone":"+1 718 622 7893",
    "sg:postcode":"11217",
    "sg:province":"NY",
    "sg:tags":[
        "information",
        "referral"
    ],
    "wof:name":"Information Access Co",
    "wof:placetype":"venue"
},
  "geometry": {"coordinates":[-73.977954,40.675613],"type":"Point"}
}