{
  "type": "Feature",
  "properties": {
    "addr:full":"98 State Hwy 303 Tappan NY 10983",
    "addr:housenumber":"98",
    "addr:postcode":"10983",
    "addr:street":"State Hwy 303",
    "iso:country":"US",
    "sg:address":"98 State Hwy 303",
    "sg:city":"Tappan",
    "sg:classifiers":[
        {
            "category":"Retail",
            "subcategory":"Funeral Services",
            "type":"Services"
        }
    ],
    "sg:phone":"+1 845 359 0890",
    "sg:postcode":"10983",
    "sg:province":"NY",
    "sg:tags":[
        "director"
    ],
    "wof:name":"Moritz Funeral Home Inc",
    "wof:placetype":"venue"
},
  "geometry": {"coordinates":[-73.945151,41.016368],"type":"Point"}
}