{
  "type": "Feature",
  "properties": {
    "iso:country":"US",
    "sg:address":"77 Harloff Rd",
    "sg:city":"Honeoye Falls",
    "sg:classifiers":[
        {
            "category":"Wholesale",
            "subcategory":"Durable Goods & Equipment",
            "type":"Manufacturing & Wholesale Goods"
        }
    ],
    "sg:phone":"+1 585 582 2240",
    "sg:postcode":"14472",
    "sg:province":"NY",
    "wof:name":"Marchese Marsey & Barden In C",
    "wof:placetype":"venue"
},
  "geometry": {"coordinates":[-77.486204,42.979766],"type":"Point"}
}