{
  "type": "Feature",
  "properties": {
    "iso:country":"US",
    "sg:address":"1308 Broadway",
    "sg:city":"Brooklyn",
    "sg:classifiers":[
        {
            "category":"Shopping",
            "subcategory":"Jewelry",
            "type":"Retail Goods"
        },
        {
            "category":"Banks & Credit Unions",
            "subcategory":"Bank",
            "type":"Services"
        },
        {
            "category":"Manufacturing",
            "subcategory":"Jewelry",
            "type":"Manufacturing & Wholesale Goods"
        }
    ],
    "sg:phone":"+1 718 574 4304",
    "sg:postcode":"11221",
    "sg:province":"NY",
    "sg:tags":[
        "platinum",
        "gold",
        "hand",
        "second",
        "buyer",
        "silver"
    ],
    "wof:name":"Alexis Buy & Sell",
    "wof:placetype":"venue"
},
  "geometry": {"coordinates":[-73.923958,40.690584],"type":"Point"}
}