{
  "type": "Feature",
  "properties": {
    "addr:full":"468 Empire Blvd Brooklyn NY 11225",
    "addr:housenumber":"468",
    "addr:postcode":"11225",
    "addr:street":"Empire Blvd",
    "iso:country":"US",
    "sg:address":"468 Empire Blvd",
    "sg:city":"Brooklyn",
    "sg:classifiers":[
        {
            "category":"Organizations",
            "subcategory":"Religious Organization",
            "type":"Services"
        }
    ],
    "sg:phone":"+1 718 756 0943",
    "sg:postcode":"11225",
    "sg:province":"NY",
    "sg:tags":[
        "clergy"
    ],
    "wof:name":"Israel Pshemish",
    "wof:placetype":"venue"
},
  "geometry": {"coordinates":[-73.946608,40.66407],"type":"Point"}
}