{
  "type": "Feature",
  "properties": {
    "iso:country":"US",
    "sg:address":"35 Prospect St",
    "sg:city":"Southampton",
    "sg:classifiers":[
        {
            "category":"Retail",
            "subcategory":"Funeral Services",
            "type":"Services"
        }
    ],
    "sg:phone":"+1 631 283 2676",
    "sg:postcode":"11968",
    "sg:province":"NY",
    "sg:tags":[
        "casket"
    ],
    "wof:name":"Westerhoff Family Ltd Partners",
    "wof:placetype":"venue"
},
  "geometry": {"coordinates":[-72.392111,40.892921],"type":"Point"}
}