{
  "type": "Feature",
  "properties": {
    "addr:full":"15 W 28th St 3rd Fl New York NY 10001",
    "addr:housenumber":"15;3rd fl",
    "addr:postcode":"10001",
    "addr:street":"W 28Th St",
    "iso:country":"US",
    "sg:address":"15 W 28th St 3rd Fl",
    "sg:city":"New York",
    "sg:classifiers":[
        {
            "category":"Arts & Performance",
            "subcategory":"Arts Center",
            "type":"Entertainment"
        },
        {
            "category":"Education",
            "subcategory":"Special Training",
            "type":"Public Place"
        }
    ],
    "sg:phone":"+1 212 252 1619",
    "sg:postcode":"10001",
    "sg:province":"NY",
    "sg:tags":[
        "school",
        "performing",
        "specialty"
    ],
    "wof:name":"TADA! Youth Theater",
    "wof:placetype":"venue"
},
  "geometry": {"coordinates":[-73.98821599999999,40.745196],"type":"Point"}
}