{
  "type": "Feature",
  "properties": {
    "addr:full":"278 Piermont Ave Nyack NY 10960",
    "addr:housenumber":"278",
    "addr:postcode":"10960",
    "addr:street":"Piermont Ave",
    "iso:country":"US",
    "sg:address":"278 Piermont Ave",
    "sg:city":"Nyack",
    "sg:classifiers":[
        {
            "category":"Professional",
            "type":"Services"
        }
    ],
    "sg:phone":"+1 845 358 2399",
    "sg:postcode":"10960",
    "sg:province":"NY",
    "sg:tags":[
        "art",
        "fine",
        "artist"
    ],
    "wof:name":"Hudson River Editions, Inc",
    "wof:placetype":"venue"
},
  "geometry": {"coordinates":[-73.91950199999999,41.078861],"type":"Point"}
}