{
  "type": "Feature",
  "properties": {
    "addr:full":"2951 Broadway New York NY 10025",
    "addr:housenumber":"2951",
    "addr:postcode":"10025",
    "addr:street":"Broadway",
    "iso:country":"US",
    "sg:address":"2951 Broadway",
    "sg:city":"New York",
    "sg:classifiers":[
        {
            "category":"Organizations",
            "subcategory":"Religious Organization",
            "type":"Services"
        }
    ],
    "sg:phone":"+1 212 662 9591",
    "sg:postcode":"10025",
    "sg:province":"NY",
    "sg:tags":[
        "church"
    ],
    "wof:name":"Lord Of The Fleas",
    "wof:placetype":"venue"
},
  "geometry": {"coordinates":[-73.96519499999999,40.806237],"type":"Point"}
}