{
  "type": "Feature",
  "properties": {
    "addr:full":"681 Co Rd 125 Gloversville NY 12078",
    "addr:housenumber":"681;125",
    "addr:postcode":"12078",
    "addr:street":"Co Rd",
    "iso:country":"US",
    "sg:address":"681 Co Rd 125",
    "sg:city":"Gloversville",
    "sg:classifiers":[
        {
            "category":"Shopping",
            "subcategory":"Bicycles & Sporting Goods",
            "type":"Retail Goods"
        }
    ],
    "sg:phone":"+1   ",
    "sg:postcode":"12078",
    "sg:province":"NY",
    "wof:name":"Oak Ridge Golf Clubs",
    "wof:placetype":"venue"
},
  "geometry": {"coordinates":[-74.34255,43.191322],"type":"Point"}
}