{
  "type": "Feature",
  "properties": {
    "addr:full":"2384 Jerome Ave Bronx NY 10468",
    "addr:housenumber":"2384",
    "addr:postcode":"10468",
    "addr:street":"Jerome Ave",
    "iso:country":"US",
    "sg:address":"2384 Jerome Ave",
    "sg:city":"Bronx",
    "sg:classifiers":[
        {
            "category":"Personal",
            "subcategory":"Beauty Salon",
            "type":"Services"
        }
    ],
    "sg:phone":"+1 718 367 1385",
    "sg:postcode":"10468",
    "sg:province":"NY",
    "sg:tags":[
        "hair"
    ],
    "wof:name":"Sandra Mercado Beauty Salon",
    "wof:placetype":"venue"
},
  "geometry": {"coordinates":[-73.9021,40.861],"type":"Point"}
}