{
  "type": "Feature",
  "properties": {
    "addr:full":"1066 Craigville Rd Chester NY 10918",
    "addr:housenumber":"1066",
    "addr:postcode":"10918",
    "addr:street":"Craigville Rd",
    "iso:country":"US",
    "sg:address":"1066 Craigville Rd",
    "sg:city":"Chester",
    "sg:classifiers":[
        {
            "category":"Wholesale",
            "subcategory":"Machinery & Supplies",
            "type":"Manufacturing & Wholesale Goods"
        }
    ],
    "sg:phone":"+1 845 783 7010",
    "sg:postcode":"10918",
    "sg:province":"NY",
    "sg:tags":[
        "equipment",
        "industrial",
        "repair"
    ],
    "wof:name":"Lift Trucks Plus",
    "wof:placetype":"venue"
},
  "geometry": {"coordinates":[-74.220506,41.364073],"type":"Point"}
}