{
  "type": "Feature",
  "properties": {
    "addr:full":"9508 Church Ave Brooklyn NY 11212",
    "addr:housenumber":"9508",
    "addr:postcode":"11212",
    "addr:street":"Church Ave",
    "iso:country":"US",
    "sg:address":"9508 Church Ave",
    "sg:city":"Brooklyn",
    "sg:classifiers":[
        {
            "category":"Shopping",
            "subcategory":"Discount & Variety Stores",
            "type":"Retail Goods"
        }
    ],
    "sg:phone":"+1 718 346 9030",
    "sg:postcode":"11212",
    "sg:province":"NY",
    "wof:name":"Barney's Variety Ctr Inc",
    "wof:placetype":"venue"
},
  "geometry": {"coordinates":[-73.91545600000001,40.655596],"type":"Point"}
}