{
  "type": "Feature",
  "properties": {
    "addr:full":"325 E 194th St Bronx NY 10458",
    "addr:housenumber":"325",
    "addr:postcode":"10458",
    "addr:street":"E 194Th St",
    "iso:country":"US",
    "sg:address":"325 E 194th St",
    "sg:city":"Bronx",
    "sg:classifiers":[
        {
            "category":"Education",
            "subcategory":"Kindergarten",
            "type":"Public Place"
        }
    ],
    "sg:phone":"+1 718 733 7400",
    "sg:postcode":"10458",
    "sg:province":"NY",
    "sg:tags":[
        "school",
        "driving"
    ],
    "wof:name":"Lucy's Multiservice",
    "wof:placetype":"venue"
},
  "geometry": {"coordinates":[-73.891481,40.864416],"type":"Point"}
}