{
  "type": "Feature",
  "properties": {
    "iso:country":"US",
    "sg:address":"30-90 14th St",
    "sg:city":"Queens",
    "sg:classifiers":[
        {
            "category":"Shopping",
            "subcategory":"Bicycles & Sporting Goods",
            "type":"Retail Goods"
        }
    ],
    "sg:phone":"+1 718 606 8220",
    "sg:postcode":"11102",
    "sg:province":"NY",
    "sg:website":"www.fivestrideskateshop.com",
    "wof:name":"Five Stride Skate Shop",
    "wof:placetype":"venue"
},
  "geometry": {"coordinates":[-73.931922,40.768804],"type":"Point"}
}