{
  "type": "Feature",
  "properties": {
    "addr:full":"70 Mount Eden Ave Bronx NY 10452",
    "addr:housenumber":"70",
    "addr:postcode":"10452",
    "addr:street":"Mount Eden Ave",
    "iso:country":"US",
    "sg:address":"70 Mount Eden Ave",
    "sg:city":"Bronx",
    "sg:classifiers":[
        {
            "category":"Retail",
            "subcategory":"Self-service Laundry",
            "type":"Services"
        }
    ],
    "sg:phone":"+1 718 901 4734",
    "sg:postcode":"10452",
    "sg:province":"NY",
    "wof:name":"Laundermagic",
    "wof:placetype":"venue"
},
  "geometry": {"coordinates":[-73.91340700000001,40.843762],"type":"Point"}
}