{
  "type": "Feature",
  "properties": {
    "addr:full":"49 Madison St Brooklyn NY 11238",
    "addr:housenumber":"49",
    "addr:postcode":"11238",
    "addr:street":"Madison St",
    "iso:country":"US",
    "sg:address":"49 Madison St",
    "sg:city":"Brooklyn",
    "sg:classifiers":[
        {
            "category":"Social Services",
            "type":"Services"
        }
    ],
    "sg:phone":"+1 718 230 0006",
    "sg:postcode":"11238",
    "sg:province":"NY",
    "sg:tags":[
        "organization",
        "welfare"
    ],
    "wof:name":"Independent Living",
    "wof:placetype":"venue"
},
  "geometry": {"coordinates":[-73.95777200000001,40.68391],"type":"Point"}
}