{
  "type": "Feature",
  "properties": {
    "addr:full":"181 South 3rd St Brooklyn NY 11211",
    "addr:housenumber":"181",
    "addr:postcode":"11211",
    "addr:street":"South 3Rd St",
    "iso:country":"US",
    "sg:address":"181 South 3rd St",
    "sg:city":"Brooklyn",
    "sg:classifiers":[
        {
            "category":"Food & Beverages",
            "subcategory":"Groceries & Convenience Stores",
            "type":"Retail Goods"
        }
    ],
    "sg:postcode":"11211",
    "sg:province":"NY",
    "wof:name":"Carniceria La Espanola",
    "wof:placetype":"venue"
},
  "geometry": {"coordinates":[-73.96004600000001,40.711625],"type":"Point"}
}