{
  "type": "Feature",
  "properties": {
    "iso:country":"US",
    "sg:address":"610 Sackman St",
    "sg:city":"Brooklyn",
    "sg:classifiers":[
        {
            "category":"Place Of Worship",
            "subcategory":"Church",
            "type":"Public Place"
        },
        {
            "category":"Place Of Worship",
            "type":"Public Place"
        }
    ],
    "sg:phone":"+1 718 498 6392",
    "sg:postcode":"11212",
    "sg:province":"NY",
    "sg:tags":[
        "churches-pentecostal-independent",
        "churches-pentecostal"
    ],
    "wof:name":"Shield Of Faith",
    "wof:placetype":"venue"
},
  "geometry": {"coordinates":[-73.90308,40.662609],"type":"Point"}
}