{
  "type": "Feature",
  "properties": {
    "iso:country":"US",
    "sg:address":"1091 Jamison Rd",
    "sg:city":"Elma",
    "sg:classifiers":[
        {
            "category":"Mining & Drilling",
            "type":"Manufacturing & Wholesale Goods"
        },
        {
            "category":"Professional",
            "subcategory":"Management & Consulting",
            "type":"Services"
        },
        {
            "category":"Professional",
            "subcategory":"Engineering",
            "type":"Services"
        }
    ],
    "sg:phone":"+1 716 655 1717",
    "sg:postcode":"14059",
    "sg:province":"NY",
    "sg:tags":[
        "consultant",
        "ecological",
        "engineer",
        "geologist",
        "environmental"
    ],
    "wof:name":"Earth Dimensions Inc",
    "wof:placetype":"venue"
},
  "geometry": {"coordinates":[-78.619478,42.805021],"type":"Point"}
}