{
  "type": "Feature",
  "properties": {
    "iso:country":"US",
    "sg:address":"39 E 83rd Street",
    "sg:city":"New York",
    "sg:classifiers":[
        {
            "category":"Organizations",
            "subcategory":"Religious Organization",
            "type":"Services"
        }
    ],
    "sg:phone":"+1 212 794 1036",
    "sg:postcode":"10028",
    "sg:province":"NY",
    "wof:name":"Jesuit Seminary & Missn Bur",
    "wof:placetype":"venue"
},
  "geometry": {"coordinates":[-73.960173,40.778866],"type":"Point"}
}