{
  "type": "Feature",
  "properties": {
    "iso:country":"US",
    "sg:address":"482 Ridgewood Ave",
    "sg:city":"Brooklyn",
    "sg:classifiers":[
        {
            "category":"Organizations",
            "subcategory":"Non-profit Organization",
            "type":"Services"
        }
    ],
    "sg:phone":"+1 718 277 1547",
    "sg:postcode":"11208",
    "sg:province":"NY",
    "sg:tags":[
        "fund",
        "counselor",
        "raising"
    ],
    "wof:name":"Ethiopian World Federation Inc",
    "wof:placetype":"venue"
},
  "geometry": {"coordinates":[-73.87111400000001,40.685705],"type":"Point"}
}