{
  "type": "Feature",
  "properties": {
    "addr:full":"Fort Tryon Park New York NY 10040",
    "addr:postcode":"10040",
    "addr:street":"Park",
    "iso:country":"US",
    "sg:address":"Fort Tryon Park",
    "sg:city":"New York",
    "sg:classifiers":[
        {
            "category":"Museum",
            "type":"Entertainment"
        }
    ],
    "sg:phone":"+1 212 923 3700",
    "sg:postcode":"10040",
    "sg:province":"NY",
    "wof:name":"N Y City of",
    "wof:placetype":"venue"
},
  "geometry": {"coordinates":[-73.92890199999999,40.857399],"type":"Point"}
}