{
  "type": "Feature",
  "properties": {
    "iso:country":"US",
    "sg:address":"114 Old Country Rd Ste 244",
    "sg:city":"Mineola",
    "sg:classifiers":[
        {
            "category":"Professional",
            "subcategory":"Lawyer & Legal Services",
            "type":"Services"
        }
    ],
    "sg:phone":"+1 516 294 9200",
    "sg:postcode":"11501",
    "sg:province":"NY",
    "wof:name":"Pearl Anthony A",
    "wof:placetype":"venue"
},
  "geometry": {"coordinates":[-73.634727,40.739868],"type":"Point"}
}