{
  "type": "Feature",
  "properties": {
    "addr:full":"5194 Wilcox Rd Whitesboro NY 13492",
    "addr:housenumber":"5194",
    "addr:postcode":"13492",
    "addr:street":"Wilcox Rd",
    "iso:country":"US",
    "sg:address":"5194 Wilcox Rd",
    "sg:city":"Whitesboro",
    "sg:classifiers":[
        {
            "category":"Professional",
            "subcategory":"Computer Services",
            "type":"Services"
        }
    ],
    "sg:phone":"+1 315 525 4153",
    "sg:postcode":"13492",
    "sg:province":"NY",
    "sg:tags":[
        "website",
        "design"
    ],
    "wof:name":"Your Internet Technologist",
    "wof:placetype":"venue"
},
  "geometry": {"coordinates":[-75.31416,43.11376],"type":"Point"}
}