{
  "type": "Feature",
  "properties": {
    "addr:full":"1417 Jefferson Ave Brooklyn NY 11237",
    "addr:housenumber":"1417",
    "addr:postcode":"11237",
    "addr:street":"Jefferson Ave",
    "iso:country":"US",
    "sg:address":"1417 Jefferson Ave",
    "sg:city":"Brooklyn",
    "sg:classifiers":[
        {
            "category":"Real Estate",
            "subcategory":"Real Estate Agent",
            "type":"Services"
        }
    ],
    "sg:phone":"+1 347 247 9543",
    "sg:postcode":"11237",
    "sg:province":"NY",
    "wof:name":"Lalong Enterprises Inc",
    "wof:placetype":"venue"
},
  "geometry": {"coordinates":[-73.909646,40.694832],"type":"Point"}
}