{
  "type": "Feature",
  "properties": {
    "iso:country":"US",
    "sg:address":"9305 3rd Ave",
    "sg:city":"Brooklyn",
    "sg:classifiers":[
        {
            "category":"Restaurant",
            "type":"Food & Drink"
        }
    ],
    "sg:phone":"+1 718 491 2599",
    "sg:postcode":"11209",
    "sg:province":"NY",
    "wof:name":"Positano",
    "wof:placetype":"venue"
},
  "geometry": {"coordinates":[-74.03331300000001,40.617945],"type":"Point"}
}