{
  "type": "Feature",
  "properties": {
    "iso:country":"US",
    "sg:address":"910 Middle Country Rd",
    "sg:city":"Middle Island",
    "sg:classifiers":[
        {
            "category":"Autos & Motor Vehicles",
            "subcategory":"Automobile Sales",
            "type":"Retail Goods"
        }
    ],
    "sg:phone":"+1 631 924 8100",
    "sg:postcode":"11953",
    "sg:province":"NY",
    "sg:tags":[
        "passenger",
        "general",
        "repair"
    ],
    "wof:name":"Competition Toyota",
    "wof:placetype":"venue"
},
  "geometry": {"coordinates":[-72.93749699999999,40.884192],"type":"Point"}
}