{
  "type": "Feature",
  "properties": {
    "addr:full":"1552 Coney Island Avenue Brooklyn NY 11230",
    "addr:housenumber":"1552",
    "addr:postcode":"11230",
    "addr:street":"Coney Island Avenue",
    "iso:country":"US",
    "sg:address":"1552 Coney Island Avenue",
    "sg:city":"Brooklyn",
    "sg:classifiers":[
        {
            "category":"Health Services",
            "subcategory":"Doctor",
            "type":"Services"
        }
    ],
    "sg:phone":"+1 718 258 0315",
    "sg:postcode":"11230",
    "sg:province":"NY",
    "wof:name":"Optique Elegance",
    "wof:placetype":"venue"
},
  "geometry": {"coordinates":[-73.96401400000001,40.617611],"type":"Point"}
}