{
  "type": "Feature",
  "properties": {
    "addr:full":"908 Tiffany St Bronx NY 10459",
    "addr:housenumber":"908",
    "addr:postcode":"10459",
    "addr:street":"Tiffany St",
    "iso:country":"US",
    "sg:address":"908 Tiffany St",
    "sg:city":"Bronx",
    "sg:classifiers":[
        {
            "category":"Professional",
            "type":"Services"
        }
    ],
    "sg:phone":"+1 718 542 7545",
    "sg:postcode":"10459",
    "sg:province":"NY",
    "sg:tags":[
        "establishment"
    ],
    "wof:name":"Ares Berrios Blanca",
    "wof:placetype":"venue"
},
  "geometry": {"coordinates":[-73.894848,40.819392],"type":"Point"}
}