{
  "type": "Feature",
  "properties": {
    "addr:full":"651 W Hoffman Ave Lindenhurst NY 11757",
    "addr:housenumber":"651",
    "addr:postcode":"11757",
    "addr:street":"W Hoffman Ave",
    "iso:country":"US",
    "sg:address":"651 W Hoffman Ave",
    "sg:city":"Lindenhurst",
    "sg:classifiers":[
        {
            "category":"Manufacturing",
            "subcategory":"Toys & Sporting Goods",
            "type":"Manufacturing & Wholesale Goods"
        }
    ],
    "sg:phone":"+1   ",
    "sg:postcode":"11757",
    "sg:province":"NY",
    "sg:tags":[
        "manufacture",
        "train"
    ],
    "sg:website":"www.pridelinesltd.com",
    "wof:name":"Pride Lines LTD",
    "wof:placetype":"venue"
},
  "geometry": {"coordinates":[-73.388148,40.682365],"type":"Point"}
}