{
  "type": "Feature",
  "properties": {
    "addr:full":"2258 3rd Ave New York NY 10035",
    "addr:housenumber":"2258",
    "addr:postcode":"10035",
    "addr:street":"3Rd Ave",
    "iso:country":"US",
    "sg:address":"2258 3rd Ave",
    "sg:city":"New York",
    "sg:classifiers":[
        {
            "category":"Arts & Performance",
            "subcategory":"Comedy Club",
            "type":"Entertainment"
        }
    ],
    "sg:phone":"+1 212 987 5910",
    "sg:postcode":"10035",
    "sg:province":"NY",
    "wof:name":"Groove With Me Inc",
    "wof:placetype":"venue"
},
  "geometry": {"coordinates":[-73.936971,40.802379],"type":"Point"}
}