{
  "type": "Feature",
  "properties": {
    "addr:full":"52 Broadview Dr Oswego NY 13126",
    "addr:housenumber":"52",
    "addr:postcode":"13126",
    "addr:street":"Broadview Dr",
    "iso:country":"US",
    "sg:address":"52 Broadview Dr",
    "sg:city":"Oswego",
    "sg:classifiers":[
        {
            "category":"Social Services",
            "type":"Services"
        }
    ],
    "sg:phone":"+1   ",
    "sg:postcode":"13126",
    "sg:province":"NY",
    "sg:tags":[
        "child",
        "day",
        "care"
    ],
    "wof:name":"Little People Day Care",
    "wof:placetype":"venue"
},
  "geometry": {"coordinates":[-76.576442,43.421308],"type":"Point"}
}