{
  "type": "Feature",
  "properties": {
    "iso:country":"US",
    "sg:address":"522 Browns Rd",
    "sg:city":"Nesconset",
    "sg:classifiers":[
        {
            "category":"Shopping",
            "subcategory":"Used Merchandise",
            "type":"Retail Goods"
        }
    ],
    "sg:phone":"+1 631 588 4016",
    "sg:postcode":"11767",
    "sg:province":"NY",
    "sg:tags":[
        "furniture"
    ],
    "wof:name":"Marie's Memory Lane",
    "wof:placetype":"venue"
},
  "geometry": {"coordinates":[-73.12274600000001,40.836718],"type":"Point"}
}