{
  "type": "Feature",
  "properties": {
    "iso:country":"US",
    "sg:address":"9 Jones Ave",
    "sg:city":"Feura Bush",
    "sg:classifiers":[
        {
            "category":"Building & Trades",
            "subcategory":"Plumbing",
            "type":"Services"
        }
    ],
    "sg:phone":"+1 518 475 0204",
    "sg:postcode":"12067",
    "sg:province":"NY",
    "sg:tags":[
        "contractor"
    ],
    "wof:name":"JRS Mechanical",
    "wof:placetype":"venue"
},
  "geometry": {"coordinates":[-73.88783100000001,42.581406],"type":"Point"}
}