{
  "type": "Feature",
  "properties": {
    "addr:full":"276 Canal St New York NY 10013",
    "addr:housenumber":"276",
    "addr:postcode":"10013",
    "addr:street":"Canal St",
    "iso:country":"US",
    "sg:address":"276 Canal St",
    "sg:city":"New York",
    "sg:classifiers":[
        {
            "category":"Organizations",
            "subcategory":"Non-profit Organization",
            "type":"Services"
        }
    ],
    "sg:phone":"+1 212 226 4739",
    "sg:postcode":"10013",
    "sg:province":"NY",
    "wof:name":"Milarepa Fund",
    "wof:placetype":"venue"
},
  "geometry": {"coordinates":[-74.001819,40.719234],"type":"Point"}
}