{
  "type": "Feature",
  "properties": {
    "addr:full":"344 E 85th St New York NY 10028",
    "addr:housenumber":"344",
    "addr:postcode":"10028",
    "addr:street":"E 85Th St",
    "iso:country":"US",
    "sg:address":"344 E 85th St",
    "sg:city":"New York",
    "sg:classifiers":[
        {
            "category":"Building & Trades",
            "subcategory":"Locksmith",
            "type":"Services"
        }
    ],
    "sg:phone":"+1 212 242 4733",
    "sg:postcode":"10028",
    "sg:province":"NY",
    "sg:tags":[
        "key"
    ],
    "wof:name":"A Locksmith & Security",
    "wof:placetype":"venue"
},
  "geometry": {"coordinates":[-73.95120199999999,40.776699],"type":"Point"}
}