{
  "type": "Feature",
  "properties": {
    "iso:country":"US",
    "sg:address":"55 Lake Shore Rd",
    "sg:city":"Ronkonkoma",
    "sg:classifiers":[
        {
            "category":"Organizations",
            "subcategory":"Community Association",
            "type":"Services"
        }
    ],
    "sg:phone":"+1   ",
    "sg:postcode":"11779",
    "sg:province":"NY",
    "wof:name":"V F W Post 9486",
    "wof:placetype":"venue"
},
  "geometry": {"coordinates":[-73.12888700000001,40.831672],"type":"Point"}
}