{
  "type": "Feature",
  "properties": {
    "addr:full":"1800 Victor St Bronx NY 10462",
    "addr:housenumber":"1800",
    "addr:postcode":"10462",
    "addr:street":"Victor St",
    "iso:country":"US",
    "sg:address":"1800 Victor St",
    "sg:city":"Bronx",
    "sg:classifiers":[
        {
            "category":"Banks & Credit Unions",
            "subcategory":"Financial Services",
            "type":"Services"
        },
        {
            "category":"Professional",
            "subcategory":"Credit Reporting & Collection",
            "type":"Services"
        }
    ],
    "sg:phone":"+1 718 918 9075",
    "sg:postcode":"10462",
    "sg:province":"NY",
    "sg:tags":[
        "debt",
        "adjuster",
        "agency"
    ],
    "wof:name":"Fl Brown & Assoc",
    "wof:placetype":"venue"
},
  "geometry": {"coordinates":[-73.86689,40.84507],"type":"Point"}
}