{
  "type": "Feature",
  "properties": {
    "addr:full":"89 Allen St Buffalo NY 14202",
    "addr:housenumber":"89",
    "addr:postcode":"14202",
    "addr:street":"Allen St",
    "iso:country":"US",
    "sg:address":"89 Allen St",
    "sg:city":"Buffalo",
    "sg:classifiers":[
        {
            "category":"Shopping",
            "subcategory":"Clothing, Apparel, & Fashions",
            "type":"Retail Goods"
        }
    ],
    "sg:phone":"+1 716 883 0871",
    "sg:postcode":"14202",
    "sg:province":"NY",
    "wof:name":"Allen Street Dress Shop",
    "wof:placetype":"venue"
},
  "geometry": {"coordinates":[-78.873769,42.899501],"type":"Point"}
}