{
  "type": "Feature",
  "properties": {
    "iso:country":"US",
    "sg:address":"80 Smith St",
    "sg:city":"Farmingdale",
    "sg:classifiers":[
        {
            "category":"Shopping",
            "subcategory":"Clothing, Apparel, & Fashions",
            "type":"Retail Goods"
        }
    ],
    "sg:phone":"+1 631 847 0530",
    "sg:postcode":"11735",
    "sg:province":"NY",
    "wof:name":"Sharon Blouse & Sportswear",
    "wof:placetype":"venue"
},
  "geometry": {"coordinates":[-73.417017,40.754457],"type":"Point"}
}