{
  "type": "Feature",
  "properties": {
    "addr:full":"54 Willis Ave Mineola NY 11501",
    "addr:housenumber":"54",
    "addr:postcode":"11501",
    "addr:street":"Willis Ave",
    "iso:country":"US",
    "sg:address":"54 Willis Ave",
    "sg:city":"Mineola",
    "sg:classifiers":[
        {
            "category":"Professional",
            "subcategory":"Lawyer & Legal Services",
            "type":"Services"
        }
    ],
    "sg:phone":"+1   ",
    "sg:postcode":"11501",
    "sg:province":"NY",
    "wof:name":"Stephen P Shea",
    "wof:placetype":"venue"
},
  "geometry": {"coordinates":[-73.636302,40.740716],"type":"Point"}
}