{
  "type": "Feature",
  "properties": {
    "addr:full":"30 Columbia Hts Brooklyn NY 11201",
    "addr:housenumber":"30",
    "addr:postcode":"11201",
    "addr:street":"Columbia Hts",
    "iso:country":"US",
    "sg:address":"30 Columbia Hts",
    "sg:city":"Brooklyn",
    "sg:classifiers":[
        {
            "category":"Wholesale",
            "subcategory":"Machinery & Supplies",
            "type":"Manufacturing & Wholesale Goods"
        }
    ],
    "sg:phone":"+1 718 560 4530",
    "sg:postcode":"11201",
    "sg:province":"NY",
    "wof:name":"Turpin Elevator Equip Svc Corp",
    "wof:placetype":"venue"
},
  "geometry": {"coordinates":[-73.995064,40.701179],"type":"Point"}
}