{
  "type": "Feature",
  "properties": {
    "iso:country":"US",
    "sg:address":"679 Whiskey Rd",
    "sg:city":"Ridge",
    "sg:classifiers":[
        {
            "category":"Shopping",
            "type":"Retail Goods"
        }
    ],
    "sg:phone":"+1 631 821 4313",
    "sg:postcode":"11961",
    "sg:province":"NY",
    "sg:tags":[
        "hearing",
        "equipment",
        "supply",
        "impaired"
    ],
    "wof:name":"Beltone Hearing Aid Ctr",
    "wof:placetype":"venue"
},
  "geometry": {"coordinates":[-72.903136,40.911679],"type":"Point"}
}