{
  "type": "Feature",
  "properties": {
    "iso:country":"US",
    "sg:address":"408 Saw Mill River Rd",
    "sg:city":"Yonkers",
    "sg:classifiers":[
        {
            "category":"Wholesale",
            "subcategory":"Auto Parts",
            "type":"Manufacturing & Wholesale Goods"
        }
    ],
    "sg:phone":"+1 914 375 3774",
    "sg:postcode":"10701",
    "sg:province":"NY",
    "sg:tags":[
        "automobile",
        "rebuilt"
    ],
    "wof:name":"D & G Motor Sales Inc",
    "wof:placetype":"venue"
},
  "geometry": {"coordinates":[-73.876142,40.95082],"type":"Point"}
}