{
  "type": "Feature",
  "properties": {
    "addr:full":"5 Skycrest Dr Troy NY 12180",
    "addr:housenumber":"5",
    "addr:postcode":"12180",
    "addr:street":"Skycrest Dr",
    "iso:country":"US",
    "sg:address":"5 Skycrest Dr",
    "sg:city":"Troy",
    "sg:classifiers":[
        {
            "category":"Building & Trades",
            "subcategory":"Construction",
            "type":"Services"
        }
    ],
    "sg:phone":"+1 518 279 3382",
    "sg:postcode":"12180",
    "sg:province":"NY",
    "sg:tags":[
        "excavation",
        "contractor"
    ],
    "wof:name":"Duncan Poured Foundations Inc",
    "wof:placetype":"venue"
},
  "geometry": {"coordinates":[-73.632885,42.77805],"type":"Point"}
}