{
  "type": "Feature",
  "properties": {
    "addr:full":"170 City Hall Rd Accord NY 12404",
    "addr:housenumber":"170",
    "addr:postcode":"12404",
    "addr:street":"City Hall Rd",
    "iso:country":"US",
    "sg:address":"170 City Hall Rd",
    "sg:city":"Accord",
    "sg:classifiers":[
        {
            "category":"Retail",
            "subcategory":"Auto Repair",
            "type":"Services"
        }
    ],
    "sg:phone":"+1 845 626 3357",
    "sg:postcode":"12404",
    "sg:province":"NY",
    "sg:tags":[
        "body",
        "automobile",
        "painting"
    ],
    "wof:name":"Ken Ballard's Body Shop",
    "wof:placetype":"venue"
},
  "geometry": {"coordinates":[-74.30578800000001,41.809953],"type":"Point"}
}