{
  "type": "Feature",
  "properties": {
    "addr:full":"1828 South Ave Syracuse NY 13207",
    "addr:housenumber":"1828",
    "addr:postcode":"13207",
    "addr:street":"South Ave",
    "iso:country":"US",
    "sg:address":"1828 South Ave",
    "sg:city":"Syracuse",
    "sg:classifiers":[
        {
            "category":"Education",
            "subcategory":"College",
            "type":"Public Place"
        }
    ],
    "sg:phone":"+1 315 475 5142",
    "sg:postcode":"13207",
    "sg:province":"NY",
    "sg:tags":[
        "school",
        "funeral"
    ],
    "wof:name":"Simmons Institute of Fnrl Svc",
    "wof:placetype":"venue"
},
  "geometry": {"coordinates":[-76.160591,43.019537],"type":"Point"}
}