{
  "type": "Feature",
  "properties": {
    "addr:full":"320 3rd Ave Bayport NY 11705",
    "addr:housenumber":"320",
    "addr:postcode":"11705",
    "addr:street":"3Rd Ave",
    "iso:country":"US",
    "sg:address":"320 3rd Ave",
    "sg:city":"Bayport",
    "sg:classifiers":[
        {
            "category":"Personal",
            "subcategory":"Beauty Salon",
            "type":"Services"
        }
    ],
    "sg:phone":"+1 631 472 9304",
    "sg:postcode":"11705",
    "sg:province":"NY",
    "wof:name":"De Javu Hair Designs",
    "wof:placetype":"venue"
},
  "geometry": {"coordinates":[-73.053673,40.74744],"type":"Point"}
}