{
  "type": "Feature",
  "properties": {
    "iso:country":"US",
    "sg:address":"155 Orawaupum St",
    "sg:city":"White Plains",
    "sg:classifiers":[
        {
            "category":"Organizations",
            "subcategory":"Religious Organization",
            "type":"Services"
        }
    ],
    "sg:phone":"+1 914 946 1024",
    "sg:postcode":"10606",
    "sg:province":"NY",
    "sg:tags":[
        "church"
    ],
    "wof:name":"White Plains E Cngrgtn-Jehovah",
    "wof:placetype":"venue"
},
  "geometry": {"coordinates":[-73.772723,41.025669],"type":"Point"}
}