{
  "type": "Feature",
  "properties": {
    "iso:country":"US",
    "sg:address":"22 Hudson St",
    "sg:city":"Warrensburg",
    "sg:classifiers":[
        {
            "category":"Professional",
            "type":"Services"
        }
    ],
    "sg:phone":"+1 518 761 1044",
    "sg:postcode":"12885",
    "sg:province":"NY",
    "sg:tags":[
        "establishment"
    ],
    "wof:name":"Paul KAZA Assoc Inc",
    "wof:placetype":"venue"
},
  "geometry": {"coordinates":[-73.77897299999999,43.497],"type":"Point"}
}