{
  "type": "Feature",
  "properties": {
    "iso:country":"US",
    "sg:address":"1362 Nostrand Ave",
    "sg:city":"Brooklyn",
    "sg:classifiers":[
        {
            "category":"Retail",
            "subcategory":"Auto Repair",
            "type":"Services"
        }
    ],
    "sg:phone":"+1 718 856 1900",
    "sg:postcode":"11226",
    "sg:province":"NY",
    "sg:tags":[
        "wrecker"
    ],
    "wof:name":"A A Alpha Towing",
    "wof:placetype":"venue"
},
  "geometry": {"coordinates":[-73.949865,40.652902],"type":"Point"}
}