{
  "type": "Feature",
  "properties": {
    "addr:full":"51 Kensett Rd Manhasset NY 11030",
    "addr:housenumber":"51",
    "addr:postcode":"11030",
    "addr:street":"Kensett Rd",
    "iso:country":"US",
    "sg:address":"51 Kensett Rd",
    "sg:city":"Manhasset",
    "sg:classifiers":[
        {
            "category":"Insurance",
            "subcategory":"Insurance Agent",
            "type":"Services"
        }
    ],
    "sg:phone":"+1 516 365 7915",
    "sg:postcode":"11030",
    "sg:province":"NY",
    "wof:name":"Total Dollar Management Effort",
    "wof:placetype":"venue"
},
  "geometry": {"coordinates":[-73.67892999999999,40.802132],"type":"Point"}
}