{
  "type": "Feature",
  "properties": {
    "addr:full":"555 Park Ave New York NY 10021",
    "addr:housenumber":"555",
    "addr:postcode":"10021",
    "addr:street":"Park Ave",
    "iso:country":"US",
    "sg:address":"555 Park Ave",
    "sg:city":"New York",
    "sg:classifiers":[
        {
            "category":"Real Estate",
            "subcategory":"Real Estate Operator",
            "type":"Services"
        }
    ],
    "sg:phone":"+1 212 838 6628",
    "sg:postcode":"10021",
    "sg:province":"NY",
    "sg:tags":[
        "apartment"
    ],
    "wof:name":"Five Hundred & Fifty Five Pk Av Apts",
    "wof:placetype":"venue"
},
  "geometry": {"coordinates":[-73.9683,40.764702],"type":"Point"}
}