{
  "type": "Feature",
  "properties": {
    "addr:full":"29 W 12 St New York NY 10011",
    "addr:housenumber":"29",
    "addr:postcode":"10011",
    "addr:street":"W 12 St",
    "iso:country":"US",
    "sg:address":"29 W 12 St",
    "sg:city":"New York",
    "sg:classifiers":[
        {
            "category":"Real Estate",
            "subcategory":"Real Estate Agent",
            "type":"Services"
        }
    ],
    "sg:phone":"+1 646 638 3585",
    "sg:postcode":"10011",
    "sg:province":"NY",
    "wof:name":"29 West 12 Realty LLC",
    "wof:placetype":"venue"
},
  "geometry": {"coordinates":[-73.99707100000001,40.735709],"type":"Point"}
}