{
  "type": "Feature",
  "properties": {
    "addr:full":"246 Frozen Ridge Rd Newburgh NY 12550",
    "addr:housenumber":"246",
    "addr:postcode":"12550",
    "addr:street":"Frozen Ridge Rd",
    "iso:country":"US",
    "sg:address":"246 Frozen Ridge Rd",
    "sg:city":"Newburgh",
    "sg:classifiers":[
        {
            "category":"Manufacturing",
            "subcategory":"Metals",
            "type":"Manufacturing & Wholesale Goods"
        }
    ],
    "sg:phone":"+1 845 562 6263",
    "sg:postcode":"12550",
    "sg:province":"NY",
    "sg:tags":[
        "fabricator",
        "metalwork",
        "sheet",
        "mfg"
    ],
    "wof:name":"Craftsmen Metal & Roofing",
    "wof:placetype":"venue"
},
  "geometry": {"coordinates":[-74.02827000000001,41.577506],"type":"Point"}
}