{
  "type": "Feature",
  "properties": {
    "iso:country":"US",
    "sg:address":"41 Northumberland Dr",
    "sg:city":"Shoreham",
    "sg:classifiers":[
        {
            "category":"Health Services",
            "subcategory":"Podiatrist",
            "type":"Services"
        }
    ],
    "sg:phone":"+1 631 821 6002",
    "sg:postcode":"11786",
    "sg:province":"NY",
    "sg:tags":[
        "equipment",
        "supply"
    ],
    "wof:name":"Select Medical",
    "wof:placetype":"venue"
},
  "geometry": {"coordinates":[-72.902298,40.942329],"type":"Point"}
}