{
  "type": "Feature",
  "properties": {
    "addr:full":"218 Stone St Watertown NY 13601",
    "addr:housenumber":"218",
    "addr:postcode":"13601",
    "addr:street":"Stone St",
    "iso:country":"US",
    "sg:address":"218 Stone St",
    "sg:city":"Watertown",
    "sg:classifiers":[
        {
            "category":"Health Services",
            "subcategory":"Doctor",
            "type":"Services"
        }
    ],
    "sg:phone":"+1 315 788 0062",
    "sg:postcode":"13601",
    "sg:province":"NY",
    "sg:tags":[
        "physician",
        "surgeon"
    ],
    "wof:name":"Industrial Medicine Assoc",
    "wof:placetype":"venue"
},
  "geometry": {"coordinates":[-75.91581100000001,43.974553],"type":"Point"}
}