{
  "type": "Feature",
  "properties": {
    "iso:country":"US",
    "sg:address":"16 Brewer Rd",
    "sg:city":"Monsey",
    "sg:classifiers":[
        {
            "category":"Professional",
            "type":"Services"
        }
    ],
    "sg:phone":"+1 845 371 4203",
    "sg:postcode":"10952",
    "sg:province":"NY",
    "sg:tags":[
        "establishment"
    ],
    "wof:name":"Continental Trading Of USA",
    "wof:placetype":"venue"
},
  "geometry": {"coordinates":[-74.06267800000001,41.103535],"type":"Point"}
}