{
  "type": "Feature",
  "properties": {
    "addr:full":"388 Westchester Ave Port Chester NY 10573",
    "addr:housenumber":"388",
    "addr:postcode":"10573",
    "addr:street":"Westchester Ave",
    "iso:country":"US",
    "sg:address":"388 Westchester Ave",
    "sg:city":"Port Chester",
    "sg:classifiers":[
        {
            "category":"Health Services",
            "subcategory":"Podiatrist",
            "type":"Services"
        }
    ],
    "sg:phone":"+1 914 939 4101",
    "sg:postcode":"10573",
    "sg:province":"NY",
    "wof:name":"Accent On Feet",
    "wof:placetype":"venue"
},
  "geometry": {"coordinates":[-73.673547,41.004992],"type":"Point"}
}