{
  "type": "Feature",
  "properties": {
    "iso:country":"US",
    "sg:address":"321 E 54 St",
    "sg:city":"New York",
    "sg:classifiers":[
        {
            "category":"Professional",
            "type":"Services"
        }
    ],
    "sg:phone":"+1 917 292 0881",
    "sg:postcode":"10022",
    "sg:province":"NY",
    "sg:tags":[
        "establishment"
    ],
    "wof:name":"Nano Fund Inc",
    "wof:placetype":"venue"
},
  "geometry": {"coordinates":[-73.96465600000001,40.75665],"type":"Point"}
}