{
  "type": "Feature",
  "properties": {
    "iso:country":"US",
    "sg:address":"523 W 125th St",
    "sg:city":"New York",
    "sg:classifiers":[
        {
            "category":"Wholesale",
            "subcategory":"Electrical",
            "type":"Manufacturing & Wholesale Goods"
        }
    ],
    "sg:phone":"+1 212 662 6990",
    "sg:postcode":"10027",
    "sg:province":"NY",
    "sg:tags":[
        "stove",
        "gas"
    ],
    "wof:name":"Kaplan Bros Blue Flame Corp",
    "wof:placetype":"venue"
},
  "geometry": {"coordinates":[-73.956463,40.813542],"type":"Point"}
}