{
  "type": "Feature",
  "properties": {
    "addr:full":"968 Suffolk Ave Brentwood NY 11717",
    "addr:housenumber":"968",
    "addr:postcode":"11717",
    "addr:street":"Suffolk Ave",
    "iso:country":"US",
    "sg:address":"968 Suffolk Ave",
    "sg:city":"Brentwood",
    "sg:classifiers":[
        {
            "category":"Real Estate",
            "subcategory":"Real Estate Services",
            "type":"Services"
        },
        {
            "category":"Real Estate",
            "subcategory":"Real Estate Agent",
            "type":"Services"
        }
    ],
    "sg:phone":"+1 631 435 0900",
    "sg:postcode":"11717",
    "sg:province":"NY",
    "sg:tags":[
        "buyer",
        "management",
        "broker"
    ],
    "wof:name":"Shirlan Realty",
    "wof:placetype":"venue"
},
  "geometry": {"coordinates":[-73.235204,40.78369],"type":"Point"}
}