{
  "type": "Feature",
  "properties": {
    "addr:full":"2854 W 19th St Brooklyn NY 11224",
    "addr:housenumber":"2854",
    "addr:postcode":"11224",
    "addr:street":"W 19Th St",
    "iso:country":"US",
    "sg:address":"2854 W 19th St",
    "sg:city":"Brooklyn",
    "sg:classifiers":[
        {
            "category":"Retail",
            "subcategory":"Laundry & Dry Cleaning",
            "type":"Services"
        }
    ],
    "sg:phone":"+1 718 256 4744",
    "sg:postcode":"11224",
    "sg:province":"NY",
    "wof:name":"New Utrecht Laundry Mat",
    "wof:placetype":"venue"
},
  "geometry": {"coordinates":[-73.986092,40.577774],"type":"Point"}
}