{
  "type": "Feature",
  "properties": {
    "addr:full":"1677 New York Ave Huntington Station NY 11746",
    "addr:housenumber":"1677",
    "addr:postcode":"11746",
    "addr:street":"New York Ave Huntington",
    "iso:country":"US",
    "sg:address":"1677 New York Ave",
    "sg:city":"Huntington Station",
    "sg:classifiers":[
        {
            "category":"Professional",
            "subcategory":"Lawyer & Legal Services",
            "type":"Services"
        }
    ],
    "sg:phone":"+1 631 421 4820",
    "sg:postcode":"11746",
    "sg:province":"NY",
    "wof:name":"Campos Victoria",
    "wof:placetype":"venue"
},
  "geometry": {"coordinates":[-73.411697,40.836601],"type":"Point"}
}