{
  "type": "Feature",
  "properties": {
    "addr:full":"75 Varick Street New York NY 10013",
    "addr:housenumber":"75",
    "addr:postcode":"10013",
    "addr:street":"Varick Street",
    "iso:country":"US",
    "sg:address":"75 Varick Street",
    "sg:city":"New York",
    "sg:classifiers":[
        {
            "category":"Communications",
            "subcategory":"Newspaper",
            "type":"Services"
        }
    ],
    "sg:phone":"+1 646 563 7000",
    "sg:postcode":"10013",
    "sg:province":"NY",
    "sg:tags":[
        "magazine"
    ],
    "wof:name":"Nature America",
    "wof:placetype":"venue"
},
  "geometry": {"coordinates":[-74.00632899999999,40.722627],"type":"Point"}
}