{
  "type": "Feature",
  "properties": {
    "addr:full":"150 W 30th St Frnt 4 New York NY 10001",
    "addr:housenumber":"150;4",
    "addr:postcode":"10001",
    "addr:street":"W 30Th St Frnt",
    "iso:country":"US",
    "sg:address":"150 W 30th St Frnt 4",
    "sg:city":"New York",
    "sg:classifiers":[
        {
            "category":"Shopping",
            "subcategory":"Jewelry",
            "type":"Retail Goods"
        }
    ],
    "sg:phone":"+1 212 868 0043",
    "sg:postcode":"10001",
    "sg:province":"NY",
    "wof:name":"Yours & Mine Jewelers Inc",
    "wof:placetype":"venue"
},
  "geometry": {"coordinates":[-73.99112599999999,40.747759],"type":"Point"}
}