{
  "type": "Feature",
  "properties": {
    "iso:country":"US",
    "sg:address":"3400 Ridge Rd W",
    "sg:city":"Rochester",
    "sg:classifiers":[
        {
            "category":"Professional",
            "subcategory":"Business Services",
            "type":"Services"
        }
    ],
    "sg:phone":"+1   ",
    "sg:postcode":"14420",
    "sg:province":"NY",
    "wof:name":"Safe-T-Net",
    "wof:placetype":"venue"
},
  "geometry": {"coordinates":[-77.72049800000001,43.21252],"type":"Point"}
}