{
  "type": "Feature",
  "properties": {
    "iso:country":"US",
    "sg:address":"32 W 38th Street",
    "sg:city":"New York",
    "sg:classifiers":[
        {
            "category":"Restaurant",
            "type":"Food & Drink"
        }
    ],
    "sg:phone":"+1 212 221 3334",
    "sg:postcode":"10018",
    "sg:province":"NY",
    "sg:tags":[
        "diner"
    ],
    "wof:name":"Wolf's Bay Deli & Catering",
    "wof:placetype":"venue"
},
  "geometry": {"coordinates":[-73.983716,40.751343],"type":"Point"}
}