{
  "type": "Feature",
  "properties": {
    "iso:country":"US",
    "sg:address":"1015 Park Blvd",
    "sg:city":"Massapequa Park",
    "sg:classifiers":[
        {
            "category":"Bars & Pubs",
            "type":"Food & Drink"
        }
    ],
    "sg:phone":"+1   ",
    "sg:postcode":"11762",
    "sg:province":"NY",
    "sg:tags":[
        "drinking"
    ],
    "wof:name":"Ljh Inc",
    "wof:placetype":"venue"
},
  "geometry": {"coordinates":[-73.45582400000001,40.678425],"type":"Point"}
}