{
  "type": "Feature",
  "properties": {
    "addr:full":"45 Pine St New Canaan NY 06840",
    "addr:housenumber":"45",
    "addr:postcode":"06840",
    "addr:street":"Pine St",
    "iso:country":"US",
    "sg:address":"45 Pine St",
    "sg:city":"New Canaan",
    "sg:classifiers":[
        {
            "category":"Health Services",
            "subcategory":"Doctor",
            "type":"Services"
        }
    ],
    "sg:phone":"+1 203 966 3042",
    "sg:postcode":"06840",
    "sg:province":"NY",
    "sg:tags":[
        "dentist"
    ],
    "wof:name":"Austin W Feeney DDS",
    "wof:placetype":"venue"
},
  "geometry": {"coordinates":[-73.49691300000001,41.144942],"type":"Point"}
}