{
  "type": "Feature",
  "properties": {
    "iso:country":"US",
    "sg:address":"21 Old Mill Ct",
    "sg:city":"Rockville Centre",
    "sg:classifiers":[
        {
            "category":"Personal",
            "subcategory":"Beauty Salon",
            "type":"Services"
        }
    ],
    "sg:phone":"+1   ",
    "sg:postcode":"11570",
    "sg:province":"NY",
    "wof:name":"D GS Grooming",
    "wof:placetype":"venue"
},
  "geometry": {"coordinates":[-73.65091700000001,40.663571],"type":"Point"}
}