{
  "type": "Feature",
  "properties": {
    "iso:country":"US",
    "sg:address":"76 E Main St Ste 1",
    "sg:city":"Huntington",
    "sg:classifiers":[
        {
            "category":"Health Services",
            "subcategory":"Doctor",
            "type":"Services"
        },
        {
            "category":"Education",
            "subcategory":"School",
            "type":"Public Place"
        }
    ],
    "sg:phone":"+1 631 423 2100",
    "sg:postcode":"11743",
    "sg:province":"NY",
    "sg:tags":[
        "high",
        "middle",
        "elementary"
    ],
    "wof:name":"Engstrand Beatrice C MD",
    "wof:placetype":"venue"
},
  "geometry": {"coordinates":[-73.40920300000001,40.878502],"type":"Point"}
}