{
  "type": "Feature",
  "properties": {
    "addr:full":"44 N Main St Delevan NY 14042",
    "addr:housenumber":"44",
    "addr:postcode":"14042",
    "addr:street":"N Main St",
    "iso:country":"US",
    "sg:address":"44 N Main St",
    "sg:city":"Delevan",
    "sg:classifiers":[
        {
            "category":"Social Services",
            "type":"Services"
        }
    ],
    "sg:phone":"+1 716 492 1805",
    "sg:postcode":"14042",
    "sg:province":"NY",
    "sg:tags":[
        "organization",
        "welfare"
    ],
    "wof:name":"Suburban Adult Svc",
    "wof:placetype":"venue"
},
  "geometry": {"coordinates":[-78.48035,42.490633],"type":"Point"}
}