{
  "type": "Feature",
  "properties": {
    "addr:full":"1933 Williamsbridge Rd Bronx NY 10461",
    "addr:housenumber":"1933",
    "addr:postcode":"10461",
    "addr:street":"Williamsbridge Rd",
    "iso:country":"US",
    "sg:address":"1933 Williamsbridge Rd",
    "sg:city":"Bronx",
    "sg:classifiers":[
        {
            "category":"Health Services",
            "subcategory":"Doctor",
            "type":"Services"
        }
    ],
    "sg:phone":"+1 718 823 4719",
    "sg:postcode":"10461",
    "sg:province":"NY",
    "wof:name":"Michael Perretta DDS PC",
    "wof:placetype":"venue"
},
  "geometry": {"coordinates":[-73.85409900000001,40.85353],"type":"Point"}
}