{
  "type": "Feature",
  "properties": {
    "addr:full":"5 Hub Dr Melville NY 11747",
    "addr:housenumber":"5",
    "addr:postcode":"11747",
    "addr:street":"Hub Dr",
    "iso:country":"US",
    "sg:address":"5 Hub Dr",
    "sg:city":"Melville",
    "sg:classifiers":[
        {
            "category":"Food & Beverages",
            "subcategory":"Groceries & Convenience Stores",
            "type":"Retail Goods"
        },
        {
            "category":"Wholesale",
            "subcategory":"Drugs",
            "type":"Manufacturing & Wholesale Goods"
        }
    ],
    "sg:phone":"+1 631 845 9780",
    "sg:postcode":"11747",
    "sg:province":"NY",
    "sg:tags":[
        "grocer",
        "sundries",
        "beauty",
        "supply"
    ],
    "wof:name":"Bi-Lo Distributors Ltd",
    "wof:placetype":"venue"
},
  "geometry": {"coordinates":[-73.438166,40.761089],"type":"Point"}
}