{
  "type": "Feature",
  "properties": {
    "addr:full":"535 W 51st St Ofc New York NY 10019",
    "addr:housenumber":"535",
    "addr:postcode":"10019",
    "addr:street":"W 51St St",
    "iso:country":"US",
    "sg:address":"535 W 51st St Ofc",
    "sg:city":"New York",
    "sg:classifiers":[
        {
            "category":"Real Estate",
            "subcategory":"Real Estate Operator",
            "type":"Services"
        }
    ],
    "sg:phone":"+1 212 586 1888",
    "sg:postcode":"10019",
    "sg:province":"NY",
    "sg:tags":[
        "apartment"
    ],
    "wof:name":"Clinton Manor Assocs",
    "wof:placetype":"venue"
},
  "geometry": {"coordinates":[-73.99279799999999,40.7659],"type":"Point"}
}