{
  "type": "Feature",
  "properties": {
    "addr:full":"138 5th Ave New York NY 10011",
    "addr:housenumber":"138",
    "addr:postcode":"10011",
    "addr:street":"5Th Ave",
    "iso:country":"US",
    "sg:address":"138 5th Ave",
    "sg:city":"New York",
    "sg:classifiers":[
        {
            "category":"Shopping",
            "subcategory":"Musical Instruments",
            "type":"Retail Goods"
        }
    ],
    "sg:phone":"+1 212 352 0211",
    "sg:postcode":"10011",
    "sg:province":"NY",
    "sg:tags":[
        "music",
        "dealer"
    ],
    "sg:website":"www.humanworldwide.com",
    "wof:name":"Human Music & Sound Design",
    "wof:placetype":"venue"
},
  "geometry": {"coordinates":[-73.991654,40.738735],"type":"Point"}
}