{
  "type": "Feature",
  "properties": {
    "addr:full":"111 Church Ave Brooklyn NY 11218",
    "addr:housenumber":"111",
    "addr:postcode":"11218",
    "addr:street":"Church Ave",
    "iso:country":"US",
    "sg:address":"111 Church Ave",
    "sg:city":"Brooklyn",
    "sg:classifiers":[
        {
            "category":"Food & Beverages",
            "subcategory":"Groceries & Convenience Stores",
            "type":"Retail Goods"
        }
    ],
    "sg:phone":"+1 718 436 6300",
    "sg:postcode":"11218",
    "sg:province":"NY",
    "sg:tags":[
        "market"
    ],
    "wof:name":"Thamer Deli & Grocery",
    "wof:placetype":"venue"
},
  "geometry": {"coordinates":[-73.97944099999999,40.642796],"type":"Point"}
}