{
  "type": "Feature",
  "properties": {
    "addr:full":"74 Ruxton Ave Staten Island NY 10312",
    "addr:housenumber":"74",
    "addr:postcode":"10312",
    "addr:street":"Ruxton Ave",
    "iso:country":"US",
    "sg:address":"74 Ruxton Ave",
    "sg:city":"Staten Island",
    "sg:classifiers":[
        {
            "category":"Wholesale",
            "subcategory":"Non-durable Goods",
            "type":"Manufacturing & Wholesale Goods"
        }
    ],
    "sg:phone":"+1 718 605 0280",
    "sg:postcode":"10312",
    "sg:province":"NY",
    "wof:name":"Glamorous Escort Inc",
    "wof:placetype":"venue"
},
  "geometry": {"coordinates":[-74.190645,40.550169],"type":"Point"}
}