{
  "type": "Feature",
  "properties": {
    "addr:full":"295 Lafayette St New York NY 10012",
    "addr:housenumber":"295",
    "addr:postcode":"10012",
    "addr:street":"Lafayette St",
    "iso:country":"US",
    "sg:address":"295 Lafayette St",
    "sg:city":"New York",
    "sg:classifiers":[
        {
            "category":"Building & Trades",
            "subcategory":"Construction",
            "type":"Services"
        },
        {
            "category":"Real Estate",
            "subcategory":"Architect",
            "type":"Services"
        }
    ],
    "sg:phone":"+1 212 226 9696",
    "sg:postcode":"10012",
    "sg:province":"NY",
    "sg:tags":[
        "interior",
        "design"
    ],
    "wof:name":"Hayden Richard S",
    "wof:placetype":"venue"
},
  "geometry": {"coordinates":[-73.995598,40.724701],"type":"Point"}
}