{
  "type": "Feature",
  "properties": {
    "addr:full":"3105 Quentin Rd Brooklyn NY 11234",
    "addr:housenumber":"3105",
    "addr:postcode":"11234",
    "addr:street":"Quentin Rd",
    "iso:country":"US",
    "sg:address":"3105 Quentin Rd",
    "sg:city":"Brooklyn",
    "sg:classifiers":[
        {
            "category":"Professional",
            "subcategory":"Accounting & Tax Preparation",
            "type":"Services"
        }
    ],
    "sg:phone":"+1 718 336 2400",
    "sg:postcode":"11234",
    "sg:province":"NY",
    "sg:tags":[
        "bookkeeping",
        "general"
    ],
    "wof:name":"Royal Alliance Assoc Inc",
    "wof:placetype":"venue"
},
  "geometry": {"coordinates":[-73.93975399999999,40.612819],"type":"Point"}
}