{
  "type": "Feature",
  "properties": {
    "iso:country":"US",
    "sg:address":"13 Sagamore Ave",
    "sg:city":"Suffern",
    "sg:classifiers":[
        {
            "category":"Freight",
            "type":"Transportation"
        }
    ],
    "sg:phone":"+1   ",
    "sg:postcode":"10901",
    "sg:province":"NY",
    "sg:tags":[
        "operator",
        "local",
        "trucking"
    ],
    "wof:name":"All Jay Trucking Inc",
    "wof:placetype":"venue"
},
  "geometry": {"coordinates":[-74.132209,41.100045],"type":"Point"}
}