{
  "type": "Feature",
  "properties": {
    "iso:country":"US",
    "sg:address":"State Route 207",
    "sg:city":"Maybrook",
    "sg:classifiers":[
        {
            "category":"Education",
            "subcategory":"Preschool",
            "type":"Public Place"
        },
        {
            "category":"Education",
            "subcategory":"School",
            "type":"Public Place"
        }
    ],
    "sg:phone":"+1 845 427 2711",
    "sg:postcode":"12543",
    "sg:province":"NY",
    "sg:tags":[
        "elementary"
    ],
    "wof:name":"Hamptonburgh Area Nursery School",
    "wof:placetype":"venue"
},
  "geometry": {"coordinates":[-74.213303,41.4953],"type":"Point"}
}