{
  "type": "Feature",
  "properties": {
    "addr:full":"548 Troy Rd Ithaca NY 14850",
    "addr:housenumber":"548",
    "addr:postcode":"14850",
    "addr:street":"Troy Rd",
    "iso:country":"US",
    "sg:address":"548 Troy Rd",
    "sg:city":"Ithaca",
    "sg:classifiers":[
        {
            "category":"Retail",
            "subcategory":"Self-service Laundry",
            "type":"Services"
        }
    ],
    "sg:phone":"+1   ",
    "sg:postcode":"14850",
    "sg:province":"NY",
    "sg:tags":[
        "coin"
    ],
    "wof:name":"Ithaca Laundramat",
    "wof:placetype":"venue"
},
  "geometry": {"coordinates":[-76.471081,42.377084],"type":"Point"}
}