{
  "type": "Feature",
  "properties": {
    "addr:full":"34 W 62 St New York NY 10023",
    "addr:housenumber":"34",
    "addr:postcode":"10023",
    "addr:street":"W 62 St",
    "iso:country":"US",
    "sg:address":"34 W 62 St",
    "sg:city":"New York",
    "sg:classifiers":[
        {
            "category":"Health Services",
            "subcategory":"Medical Lab",
            "type":"Services"
        }
    ],
    "sg:phone":"+1 212 838 8302",
    "sg:postcode":"10023",
    "sg:province":"NY",
    "sg:tags":[
        "laboratory"
    ],
    "wof:name":"APW Dental Svc",
    "wof:placetype":"venue"
},
  "geometry": {"coordinates":[-73.983419,40.771022],"type":"Point"}
}