{
  "type": "Feature",
  "properties": {
    "addr:full":"500 Milan Hill Rd Red Hook NY 12571",
    "addr:housenumber":"500",
    "addr:postcode":"12571",
    "addr:street":"Milan Hill Rd",
    "iso:country":"US",
    "sg:address":"500 Milan Hill Rd",
    "sg:city":"Red Hook",
    "sg:classifiers":[
        {
            "category":"Professional",
            "type":"Services"
        }
    ],
    "sg:phone":"+1   ",
    "sg:postcode":"12571",
    "sg:province":"NY",
    "wof:name":"Ibid Editorial",
    "wof:placetype":"venue"
},
  "geometry": {"coordinates":[-73.783991,41.998585],"type":"Point"}
}