{
  "type": "Feature",
  "properties": {
    "addr:full":"249 State Hwy 211 Middletown NY 10940",
    "addr:housenumber":"249",
    "addr:postcode":"10940",
    "addr:street":"State Hwy 211",
    "iso:country":"US",
    "sg:address":"249 State Hwy 211",
    "sg:city":"Middletown",
    "sg:classifiers":[
        {
            "category":"Retail",
            "subcategory":"Car Wash",
            "type":"Services"
        }
    ],
    "sg:phone":"+1 845 342 3300",
    "sg:postcode":"10940",
    "sg:province":"NY",
    "sg:tags":[
        "polishing",
        "washing"
    ],
    "wof:name":"Middletown Professional Car",
    "wof:placetype":"venue"
},
  "geometry": {"coordinates":[-74.438582,41.457567],"type":"Point"}
}