{
  "type": "Feature",
  "properties": {
    "addr:full":"46 N Portage St Westfield NY 14787",
    "addr:housenumber":"46",
    "addr:postcode":"14787",
    "addr:street":"N Portage St",
    "iso:country":"US",
    "sg:address":"46 N Portage St",
    "sg:city":"Westfield",
    "sg:classifiers":[
        {
            "category":"Personal",
            "subcategory":"Beauty Salon",
            "type":"Services"
        }
    ],
    "sg:phone":"+1 716 326 2279",
    "sg:postcode":"14787",
    "sg:province":"NY",
    "sg:tags":[
        "hair",
        "stylist"
    ],
    "wof:name":"Hair By Lucia",
    "wof:placetype":"venue"
},
  "geometry": {"coordinates":[-79.579217,42.323116],"type":"Point"}
}