{
  "type": "Feature",
  "properties": {
    "addr:full":"1818 Atlantic Ave Brooklyn NY 11233",
    "addr:housenumber":"1818",
    "addr:postcode":"11233",
    "addr:street":"Atlantic Ave",
    "iso:country":"US",
    "sg:address":"1818 Atlantic Ave",
    "sg:city":"Brooklyn",
    "sg:classifiers":[
        {
            "category":"Professional",
            "type":"Services"
        }
    ],
    "sg:phone":"+1 718 431 5873",
    "sg:postcode":"11233",
    "sg:province":"NY",
    "sg:tags":[
        "sculptor"
    ],
    "wof:name":"Architectural Sculpture",
    "wof:placetype":"venue"
},
  "geometry": {"coordinates":[-73.928777,40.677294],"type":"Point"}
}