{
  "type": "Feature",
  "properties": {
    "iso:country":"US",
    "sg:address":"56 Brown St",
    "sg:city":"Baldwinsville",
    "sg:classifiers":[
        {
            "category":"Organizations",
            "subcategory":"Religious Organization",
            "type":"Services"
        }
    ],
    "sg:phone":"+1 315 635 5523",
    "sg:postcode":"13027",
    "sg:province":"NY",
    "sg:tags":[
        "clergy"
    ],
    "wof:name":"Kouterick Rhonda Rev",
    "wof:placetype":"venue"
},
  "geometry": {"coordinates":[-76.34652800000001,43.165604],"type":"Point"}
}