{
  "type": "Feature",
  "properties": {
    "addr:full":"1045 N Horsepound Rd Carmel NY 10512",
    "addr:housenumber":"1045",
    "addr:postcode":"10512",
    "addr:street":"N Horsepound Rd",
    "iso:country":"US",
    "sg:address":"1045 N Horsepound Rd",
    "sg:city":"Carmel",
    "sg:classifiers":[
        {
            "category":"Education",
            "subcategory":"Kindergarten",
            "type":"Public Place"
        }
    ],
    "sg:phone":"+1 845 225 7222",
    "sg:postcode":"10512",
    "sg:province":"NY",
    "sg:tags":[
        "school",
        "driving"
    ],
    "wof:name":"Geri's Driving School",
    "wof:placetype":"venue"
},
  "geometry": {"coordinates":[-73.685801,41.50058],"type":"Point"}
}