{
  "type": "Feature",
  "properties": {
    "addr:full":"168 Wayside Ln Apalachin NY 13732",
    "addr:housenumber":"168",
    "addr:postcode":"13732",
    "addr:street":"Wayside Ln",
    "iso:country":"US",
    "sg:address":"168 Wayside Ln",
    "sg:city":"Apalachin",
    "sg:classifiers":[
        {
            "category":"Building & Trades",
            "subcategory":"Plumbing",
            "type":"Services"
        }
    ],
    "sg:phone":"+1 607 625 2547",
    "sg:postcode":"13732",
    "sg:province":"NY",
    "sg:tags":[
        "heating",
        "contractor"
    ],
    "wof:name":"Dave Pierce Heating",
    "wof:placetype":"venue"
},
  "geometry": {"coordinates":[-76.150004,42.0614],"type":"Point"}
}