{
  "type": "Feature",
  "properties": {
    "addr:full":"1170 Bronx River Ave Bronx NY 10472",
    "addr:housenumber":"1170",
    "addr:postcode":"10472",
    "addr:street":"Bronx River Ave",
    "iso:country":"US",
    "sg:address":"1170 Bronx River Ave",
    "sg:city":"Bronx",
    "sg:classifiers":[
        {
            "category":"Wholesale",
            "subcategory":"Auto Parts",
            "type":"Manufacturing & Wholesale Goods"
        }
    ],
    "sg:phone":"+1 718 842 3440",
    "sg:postcode":"10472",
    "sg:province":"NY",
    "sg:tags":[
        "supply"
    ],
    "wof:name":"B S & F Auto Parts Inc",
    "wof:placetype":"venue"
},
  "geometry": {"coordinates":[-73.883414,40.826251],"type":"Point"}
}