{
  "type": "Feature",
  "properties": {
    "addr:full":"1956 Bronxdale Ave Bronx NY 10462",
    "addr:housenumber":"1956",
    "addr:postcode":"10462",
    "addr:street":"Bronxdale Ave",
    "iso:country":"US",
    "sg:address":"1956 Bronxdale Ave",
    "sg:city":"Bronx",
    "sg:classifiers":[
        {
            "category":"Building & Trades",
            "subcategory":"Construction",
            "type":"Services"
        }
    ],
    "sg:phone":"+1 718 829 7900",
    "sg:postcode":"10462",
    "sg:province":"NY",
    "sg:tags":[
        "installation",
        "wood",
        "design",
        "flooring"
    ],
    "wof:name":"Classic Wood Flooring & Design",
    "wof:placetype":"venue"
},
  "geometry": {"coordinates":[-73.86278799999999,40.849238],"type":"Point"}
}