{
  "type": "Feature",
  "properties": {
    "addr:full":"113 Beekman Ave Tarrytown NY 10591",
    "addr:housenumber":"113",
    "addr:postcode":"10591",
    "addr:street":"Beekman Ave",
    "iso:country":"US",
    "sg:address":"113 Beekman Ave",
    "sg:city":"Tarrytown",
    "sg:classifiers":[
        {
            "category":"Shopping",
            "subcategory":"Jewelry",
            "type":"Retail Goods"
        }
    ],
    "sg:phone":"+1   ",
    "sg:postcode":"10591",
    "sg:province":"NY",
    "wof:name":"Bryans Jewelry",
    "wof:placetype":"venue"
},
  "geometry": {"coordinates":[-73.863167,41.084052],"type":"Point"}
}