{
  "type": "Feature",
  "properties": {
    "iso:country":"US",
    "sg:address":"114 Bruckner Blvd",
    "sg:city":"Bronx",
    "sg:classifiers":[
        {
            "category":"Bakery",
            "type":"Food & Drink"
        },
        {
            "category":"Coffee & Tea",
            "type":"Food & Drink"
        },
        {
            "category":"Bagels",
            "type":"Food & Drink"
        },
        {
            "category":"Donuts",
            "type":"Food & Drink"
        }
    ],
    "sg:menulink":"http://www.allmenus.com/ny/bronx/138210-dunkin-donuts/menu/",
    "sg:phone":"+1 718 421 3650",
    "sg:postcode":"10454",
    "sg:province":"NY",
    "sg:tags":[
        "american",
        "pastry"
    ],
    "wof:name":"Dunkin' Donuts",
    "wof:placetype":"venue"
},
  "geometry": {"coordinates":[-73.922285,40.804649],"type":"Point"}
}