{
  "type": "Feature",
  "properties": {
    "addr:full":"249 State Hwy 59 Nanuet NY 10954",
    "addr:housenumber":"249",
    "addr:postcode":"10954",
    "addr:street":"State Hwy 59",
    "iso:country":"US",
    "sg:address":"249 State Hwy 59",
    "sg:city":"Nanuet",
    "sg:classifiers":[
        {
            "category":"Social Services",
            "subcategory":"Child Care",
            "type":"Services"
        }
    ],
    "sg:phone":"+1 845 624 0811",
    "sg:postcode":"10954",
    "sg:province":"NY",
    "sg:tags":[
        "kindergarten",
        "academic",
        "school"
    ],
    "wof:name":"My Gym Children's Fitness Ctr",
    "wof:placetype":"venue"
},
  "geometry": {"coordinates":[-74.003417,41.093833],"type":"Point"}
}