{
  "type": "Feature",
  "properties": {
    "iso:country":"US",
    "sg:address":"4 E 39th Street",
    "sg:city":"New York",
    "sg:classifiers":[
        {
            "category":"Banks & Credit Unions",
            "subcategory":"Bank",
            "type":"Services"
        }
    ],
    "sg:phone":"+1 212 802 1000",
    "sg:postcode":"10016",
    "sg:province":"NY",
    "wof:name":"Berkshire Bank",
    "wof:placetype":"venue"
},
  "geometry": {"coordinates":[-73.98139,40.751338],"type":"Point"}
}