{
  "type": "Feature",
  "properties": {
    "iso:country":"US",
    "sg:address":"341 Mineola Blvd",
    "sg:city":"Mineola",
    "sg:classifiers":[
        {
            "category":"Health Services",
            "subcategory":"Chiropractor",
            "type":"Services"
        }
    ],
    "sg:phone":"+1 516 742 0088",
    "sg:postcode":"11501",
    "sg:province":"NY",
    "wof:name":"Forte Ann M DC",
    "wof:placetype":"venue"
},
  "geometry": {"coordinates":[-73.64510300000001,40.75],"type":"Point"}
}