{
  "type": "Feature",
  "properties": {
    "iso:country":"US",
    "sg:address":"933 Lawrence Ct",
    "sg:city":"Bellmore",
    "sg:classifiers":[
        {
            "category":"Communications",
            "subcategory":"Film & Video Production",
            "type":"Services"
        }
    ],
    "sg:phone":"+1   ",
    "sg:postcode":"11710",
    "sg:province":"NY",
    "sg:tags":[
        "motion"
    ],
    "wof:name":"Savoyid Productions Inc",
    "wof:placetype":"venue"
},
  "geometry": {"coordinates":[-73.556465,40.697869],"type":"Point"}
}