{
  "type": "Feature",
  "properties": {
    "iso:country":"US",
    "sg:address":"200 Green Lawn Rd",
    "sg:city":"Vestal",
    "sg:classifiers":[
        {
            "category":"Building & Trades",
            "subcategory":"Landscaping Services",
            "type":"Services"
        }
    ],
    "sg:phone":"+1 607 754 2203",
    "sg:postcode":"13850",
    "sg:province":"NY",
    "sg:tags":[
        "landscape",
        "contractor"
    ],
    "wof:name":"Foresome Inc",
    "wof:placetype":"venue"
},
  "geometry": {"coordinates":[-76.08820900000001,42.077463],"type":"Point"}
}