{
  "type": "Feature",
  "properties": {
    "addr:full":"223 W 19 St New York NY 10011",
    "addr:housenumber":"223",
    "addr:postcode":"10011",
    "addr:street":"W 19 St",
    "iso:country":"US",
    "sg:address":"223 W 19 St",
    "sg:city":"New York",
    "sg:classifiers":[
        {
            "category":"Retail",
            "subcategory":"Repair Shop",
            "type":"Services"
        }
    ],
    "sg:phone":"+1 212 924 4334",
    "sg:postcode":"10011",
    "sg:province":"NY",
    "sg:tags":[
        "ironwork"
    ],
    "wof:name":"Koenig Iron Works Inc",
    "wof:placetype":"venue"
},
  "geometry": {"coordinates":[-73.99997399999999,40.742758],"type":"Point"}
}