{
  "type": "Feature",
  "properties": {
    "addr:full":"2758 Elmwood Ave Buffalo NY 14217",
    "addr:housenumber":"2758",
    "addr:postcode":"14217",
    "addr:street":"Elmwood Ave",
    "iso:country":"US",
    "sg:address":"2758 Elmwood Ave",
    "sg:city":"Buffalo",
    "sg:classifiers":[
        {
            "category":"Restaurant",
            "type":"Food & Drink"
        }
    ],
    "sg:phone":"+1 716 877 6802",
    "sg:postcode":"14217",
    "sg:province":"NY",
    "sg:tags":[
        "eating"
    ],
    "wof:name":"Ling Ling Chinese Restaurant",
    "wof:placetype":"venue"
},
  "geometry": {"coordinates":[-78.87870700000001,42.972571],"type":"Point"}
}