{
  "type": "Feature",
  "properties": {
    "addr:full":"164 Bank St New York NY 10014",
    "addr:housenumber":"164",
    "addr:postcode":"10014",
    "addr:street":"Bank St",
    "iso:country":"US",
    "sg:address":"164 Bank St",
    "sg:city":"New York",
    "sg:classifiers":[
        {
            "category":"Professional",
            "type":"Services"
        }
    ],
    "sg:phone":"+1 212 255 6095",
    "sg:postcode":"10014",
    "sg:province":"NY",
    "wof:name":"Lalvani Haresh",
    "wof:placetype":"venue"
},
  "geometry": {"coordinates":[-74.008983,40.736067],"type":"Point"}
}