{
  "type": "Feature",
  "properties": {
    "addr:full":"1515 Hendrickson Ave Merrick NY 11566",
    "addr:housenumber":"1515",
    "addr:postcode":"11566",
    "addr:street":"Hendrickson Ave",
    "iso:country":"US",
    "sg:address":"1515 Hendrickson Ave",
    "sg:city":"Merrick",
    "sg:classifiers":[
        {
            "category":"Building & Trades",
            "subcategory":"Electrical",
            "type":"Services"
        }
    ],
    "sg:phone":"+1 516 599 1949",
    "sg:postcode":"11566",
    "sg:province":"NY",
    "sg:tags":[
        "electrician"
    ],
    "wof:name":"Sapienza Electric",
    "wof:placetype":"venue"
},
  "geometry": {"coordinates":[-73.551421,40.682495],"type":"Point"}
}