{
  "type": "Feature",
  "properties": {
    "iso:country":"US",
    "sg:address":"6020 Buffalo Ave",
    "sg:city":"Niagara Falls",
    "sg:classifiers":[
        {
            "category":"Wholesale",
            "subcategory":"Non-durable Goods",
            "type":"Manufacturing & Wholesale Goods"
        }
    ],
    "sg:phone":"+1 716 283 5284",
    "sg:postcode":"14304",
    "sg:province":"NY",
    "wof:name":"Onys Distributor",
    "wof:placetype":"venue"
},
  "geometry": {"coordinates":[-78.994096,43.076424],"type":"Point"}
}