{
  "type": "Feature",
  "properties": {
    "addr:full":"94 Rivington St New York NY 10002",
    "addr:housenumber":"94",
    "addr:postcode":"10002",
    "addr:street":"Rivington St",
    "iso:country":"US",
    "sg:address":"94 Rivington St",
    "sg:city":"New York",
    "sg:classifiers":[
        {
            "category":"Real Estate",
            "subcategory":"Real Estate Operator",
            "type":"Services"
        }
    ],
    "sg:phone":"+1 212 476 7231",
    "sg:postcode":"10002",
    "sg:province":"NY",
    "sg:tags":[
        "building",
        "commercial",
        "operates"
    ],
    "wof:name":"C/O Kay & S",
    "wof:placetype":"venue"
},
  "geometry": {"coordinates":[-73.98871,40.7203],"type":"Point"}
}