{
  "type": "Feature",
  "properties": {
    "addr:full":"303 Page Ave Staten Island NY 10307",
    "addr:housenumber":"303",
    "addr:postcode":"10307",
    "addr:street":"Page Ave",
    "iso:country":"US",
    "sg:address":"303 Page Ave",
    "sg:city":"Staten Island",
    "sg:classifiers":[
        {
            "category":"Personal",
            "subcategory":"Beauty Salon",
            "type":"Services"
        }
    ],
    "sg:phone":"+1   ",
    "sg:postcode":"10307",
    "sg:province":"NY",
    "sg:tags":[
        "shop"
    ],
    "wof:name":"Chen Zhuo",
    "wof:placetype":"venue"
},
  "geometry": {"coordinates":[-74.234303,40.517904],"type":"Point"}
}