{
  "type": "Feature",
  "properties": {
    "iso:country":"US",
    "sg:address":"216 Genesee St",
    "sg:city":"Chittenango",
    "sg:classifiers":[
        {
            "category":"Government",
            "subcategory":"Police Station",
            "type":"Public Place"
        },
        {
            "category":"Professional",
            "subcategory":"Lawyer & Legal Services",
            "type":"Services"
        }
    ],
    "sg:phone":"+1 315 510 3328",
    "sg:postcode":"13037",
    "sg:province":"NY",
    "sg:tags":[
        "attorney",
        "planning",
        "traffic",
        "real estate",
        "law"
    ],
    "sg:website":"http://www.colellalawoffice.com",
    "wof:name":"Colella Law Office",
    "wof:placetype":"venue"
},
  "geometry": {"coordinates":[-75.866598,43.044957],"type":"Point"}
}