{
  "type": "Feature",
  "properties": {
    "iso:country":"US",
    "sg:address":"441 Route 6",
    "sg:city":"Mahopac",
    "sg:classifiers":[
        {
            "category":"Bars & Pubs",
            "subcategory":"Hookah Bar",
            "type":"Food & Drink"
        }
    ],
    "sg:postcode":"10541",
    "sg:province":"NY",
    "wof:name":"The Bat Cave",
    "wof:placetype":"venue"
},
  "geometry": {"coordinates":[-73.744958,41.363415],"type":"Point"}
}