{
  "type": "Feature",
  "properties": {
    "addr:full":"206 Lynhurst Ave Syracuse NY 13212",
    "addr:housenumber":"206",
    "addr:postcode":"13212",
    "addr:street":"Lynhurst Ave",
    "iso:country":"US",
    "sg:address":"206 Lynhurst Ave",
    "sg:city":"Syracuse",
    "sg:classifiers":[
        {
            "category":"Retail",
            "subcategory":"Portrait Studio",
            "type":"Services"
        }
    ],
    "sg:phone":"+1 315 452 1456",
    "sg:postcode":"13212",
    "sg:province":"NY",
    "sg:tags":[
        "photography"
    ],
    "wof:name":"D T Studios",
    "wof:placetype":"venue"
},
  "geometry": {"coordinates":[-76.133056,43.138999],"type":"Point"}
}