{
  "type": "Feature",
  "properties": {
    "addr:full":"2716 Baird Rd Fairport NY 14450",
    "addr:housenumber":"2716",
    "addr:postcode":"14450",
    "addr:street":"Baird Rd",
    "iso:country":"US",
    "sg:address":"2716 Baird Rd",
    "sg:city":"Fairport",
    "sg:classifiers":[
        {
            "category":"Building & Trades",
            "subcategory":"Landscaping Services",
            "type":"Services"
        }
    ],
    "sg:phone":"+1 585 249 5127",
    "sg:postcode":"14450",
    "sg:province":"NY",
    "sg:tags":[
        "lawn",
        "maintenance",
        "grounds"
    ],
    "wof:name":"Lawn Management Inc",
    "wof:placetype":"venue"
},
  "geometry": {"coordinates":[-77.46508300000001,43.105502],"type":"Point"}
}