{
  "type": "Feature",
  "properties": {
    "addr:full":"3929 Lockport Olcott Rd Lockport NY 14094",
    "addr:housenumber":"3929",
    "addr:postcode":"14094",
    "addr:street":"Olcott Rd",
    "iso:country":"US",
    "sg:address":"3929 Lockport Olcott Rd",
    "sg:city":"Lockport",
    "sg:classifiers":[
        {
            "category":"Restaurant",
            "type":"Food & Drink"
        }
    ],
    "sg:phone":"+1 716 560 6738",
    "sg:postcode":"14094",
    "sg:province":"NY",
    "wof:name":"Mc Donald's",
    "wof:placetype":"venue"
},
  "geometry": {"coordinates":[-78.67738,43.224831],"type":"Point"}
}