{
  "type": "Feature",
  "properties": {
    "iso:country":"US",
    "sg:address":"21 Davidson Ave",
    "sg:city":"Buffalo",
    "sg:classifiers":[
        {
            "category":"Education",
            "subcategory":"College",
            "type":"Public Place"
        }
    ],
    "sg:phone":"+1 716 838 0810",
    "sg:postcode":"14215",
    "sg:province":"NY",
    "wof:name":"Houghton College",
    "wof:placetype":"venue"
},
  "geometry": {"coordinates":[-78.81048699999999,42.937251],"type":"Point"}
}