{
  "type": "Feature",
  "properties": {
    "addr:full":"401 Mill Rd Hewlett NY 11557",
    "addr:housenumber":"401",
    "addr:postcode":"11557",
    "addr:street":"Mill Rd",
    "iso:country":"US",
    "sg:address":"401 Mill Rd",
    "sg:city":"Hewlett",
    "sg:classifiers":[
        {
            "category":"Retail",
            "subcategory":"Laundry & Dry Cleaning",
            "type":"Services"
        }
    ],
    "sg:phone":"+1 516 374 5700",
    "sg:postcode":"11557",
    "sg:province":"NY",
    "wof:name":"Mill Rd Drive In Cleaners",
    "wof:placetype":"venue"
},
  "geometry": {"coordinates":[-73.703598,40.642399],"type":"Point"}
}