{
  "type": "Feature",
  "properties": {
    "addr:full":"2 Nelson Ave Peekskill NY 10566",
    "addr:housenumber":"2",
    "addr:postcode":"10566",
    "addr:street":"Nelson Ave",
    "iso:country":"US",
    "sg:address":"2 Nelson Ave",
    "sg:city":"Peekskill",
    "sg:classifiers":[
        {
            "category":"Professional",
            "subcategory":"Lawyer & Legal Services",
            "type":"Services"
        }
    ],
    "sg:phone":"+1 914 862 5170",
    "sg:postcode":"10566",
    "sg:province":"NY",
    "wof:name":"District Attorney",
    "wof:placetype":"venue"
},
  "geometry": {"coordinates":[-73.92218200000001,41.291478],"type":"Point"}
}