{
  "type": "Feature",
  "properties": {
    "iso:country":"US",
    "sg:address":"625 Tuckahoe Rd",
    "sg:city":"Yonkers",
    "sg:classifiers":[
        {
            "category":"Personal",
            "subcategory":"Nail Salon",
            "type":"Services"
        }
    ],
    "sg:phone":"+1 914 337 7388",
    "sg:postcode":"10710",
    "sg:province":"NY",
    "wof:name":"Penny's Nail Salon",
    "wof:placetype":"venue"
},
  "geometry": {"coordinates":[-73.844926,40.953702],"type":"Point"}
}