{
  "type": "Feature",
  "properties": {
    "iso:country":"US",
    "sg:address":"117 Lake St",
    "sg:city":"West Harrison",
    "sg:classifiers":[
        {
            "category":"Personal",
            "subcategory":"Tanning Parlor",
            "type":"Services"
        }
    ],
    "sg:phone":"+1 914 686 7220",
    "sg:postcode":"10604",
    "sg:province":"NY",
    "sg:tags":[
        "salon"
    ],
    "wof:name":"Luminous Tanning Inc",
    "wof:placetype":"venue"
},
  "geometry": {"coordinates":[-73.752762,41.04256],"type":"Point"}
}