{
  "type": "Feature",
  "properties": {
    "addr:full":"2097 Amsterdam Ave Schenectady NY 12303",
    "addr:housenumber":"2097",
    "addr:postcode":"12303",
    "addr:street":"Amsterdam Ave",
    "iso:country":"US",
    "sg:address":"2097 Amsterdam Ave",
    "sg:city":"Schenectady",
    "sg:classifiers":[
        {
            "category":"Retail",
            "subcategory":"Animal Services",
            "type":"Services"
        }
    ],
    "sg:phone":"+1 518 355 2695",
    "sg:postcode":"12303",
    "sg:province":"NY",
    "sg:tags":[
        "training",
        "dog"
    ],
    "wof:name":"Devil Dog Training",
    "wof:placetype":"venue"
},
  "geometry": {"coordinates":[-73.948025,42.776946],"type":"Point"}
}