{
  "type": "Feature",
  "properties": {
    "iso:country":"US",
    "sg:address":"460 Kennedy Rd",
    "sg:city":"Buffalo",
    "sg:classifiers":[
        {
            "category":"Retail",
            "subcategory":"Repair Shop",
            "type":"Services"
        },
        {
            "category":"Professional",
            "subcategory":"Business Services",
            "type":"Services"
        }
    ],
    "sg:phone":"+1 716 893 1600",
    "sg:postcode":"14227",
    "sg:province":"NY",
    "sg:tags":[
        "water",
        "equipment",
        "softening"
    ],
    "wof:name":"Sheridan Soft Water Service Co",
    "wof:placetype":"venue"
},
  "geometry": {"coordinates":[-78.776093,42.899093],"type":"Point"}
}