{
  "type": "Feature",
  "properties": {
    "iso:country":"US",
    "sg:address":"1111 Broad Hollow Rd",
    "sg:city":"Farmingdale",
    "sg:classifiers":[
        {
            "category":"Home & Garden",
            "subcategory":"Hardware",
            "type":"Retail Goods"
        }
    ],
    "sg:phone":"+1   ",
    "sg:postcode":"11735",
    "sg:province":"NY",
    "wof:name":"Ace Hardware",
    "wof:placetype":"venue"
},
  "geometry": {"coordinates":[-73.423412,40.733366],"type":"Point"}
}