{
  "type": "Feature",
  "properties": {
    "addr:full":"4828 Lake Rd Brockport NY 14420",
    "addr:housenumber":"4828",
    "addr:postcode":"14420",
    "addr:street":"Lake Rd",
    "iso:country":"US",
    "sg:address":"4828 Lake Rd",
    "sg:city":"Brockport",
    "sg:classifiers":[
        {
            "category":"Shopping",
            "subcategory":"Department Store",
            "type":"Retail Goods"
        }
    ],
    "sg:phone":"+1   ",
    "sg:postcode":"14420",
    "sg:province":"NY",
    "wof:name":"Wal-Mart",
    "wof:placetype":"venue"
},
  "geometry": {"coordinates":[-77.94371599999999,43.197625],"type":"Point"}
}