{
  "type": "Feature",
  "properties": {
    "iso:country":"US",
    "sg:address":"200 Montauk Hwy",
    "sg:city":"Westhampton Beach",
    "sg:classifiers":[
        {
            "category":"Building & Trades",
            "subcategory":"Construction",
            "type":"Services"
        }
    ],
    "sg:phone":"+1 631 898 0592",
    "sg:postcode":"11978",
    "sg:province":"NY",
    "sg:tags":[
        "special",
        "business",
        "contractor"
    ],
    "wof:name":"Millwater Pools Inc",
    "wof:placetype":"venue"
},
  "geometry": {"coordinates":[-72.641276,40.821422],"type":"Point"}
}