{
  "type": "Feature",
  "properties": {
    "iso:country":"US",
    "sg:address":"2908 Nostrand Ave",
    "sg:city":"Brooklyn",
    "sg:classifiers":[
        {
            "category":"Retail",
            "subcategory":"Auto Repair",
            "type":"Services"
        }
    ],
    "sg:phone":"+1 718 258 4343",
    "sg:postcode":"11229",
    "sg:province":"NY",
    "sg:tags":[
        "automobile",
        "diagnostic",
        "automotive",
        "general"
    ],
    "wof:name":"Victory Auto Care II Inc",
    "wof:placetype":"venue"
},
  "geometry": {"coordinates":[-73.944548,40.614543],"type":"Point"}
}