{
  "type": "Feature",
  "properties": {
    "addr:full":"3552 W Genesee St Syracuse NY 13219",
    "addr:housenumber":"3552",
    "addr:postcode":"13219",
    "addr:street":"W Genesee St",
    "iso:country":"US",
    "sg:address":"3552 W Genesee St",
    "sg:city":"Syracuse",
    "sg:classifiers":[
        {
            "category":"Personal",
            "type":"Services"
        }
    ],
    "sg:phone":"+1 315 487 9229",
    "sg:postcode":"13219",
    "sg:province":"NY",
    "sg:tags":[
        "wear",
        "formal"
    ],
    "sg:website":"www.tuxedojunction.com",
    "wof:name":"Tuxedo Junction",
    "wof:placetype":"venue"
},
  "geometry": {"coordinates":[-76.23312199999999,43.048228],"type":"Point"}
}