{
  "type": "Feature",
  "properties": {
    "addr:full":"717 Richmond Rd Staten Island NY 10304",
    "addr:housenumber":"717",
    "addr:postcode":"10304",
    "addr:street":"Richmond Rd",
    "iso:country":"US",
    "sg:address":"717 Richmond Rd",
    "sg:city":"Staten Island",
    "sg:classifiers":[
        {
            "category":"Retail",
            "subcategory":"Auto Repair",
            "type":"Services"
        }
    ],
    "sg:phone":"+1 718 727 4330",
    "sg:postcode":"10304",
    "sg:province":"NY",
    "wof:name":"George P Auto Repair Inc",
    "wof:placetype":"venue"
},
  "geometry": {"coordinates":[-74.089798,40.609901],"type":"Point"}
}