{
  "type": "Feature",
  "properties": {
    "addr:full":"24614 Jamaica Ave Jamaica NY 11001",
    "addr:housenumber":"24614",
    "addr:postcode":"11001",
    "addr:street":"Jamaica Ave",
    "iso:country":"US",
    "sg:address":"24614 Jamaica Ave",
    "sg:city":"Jamaica",
    "sg:classifiers":[
        {
            "category":"Building & Trades",
            "subcategory":"Construction",
            "type":"Services"
        }
    ],
    "sg:phone":"+1 718 232 6469",
    "sg:postcode":"11001",
    "sg:province":"NY",
    "sg:tags":[
        "sewer",
        "contractor"
    ],
    "wof:name":"Brooklyn County Sewer Rooter",
    "wof:placetype":"venue"
},
  "geometry": {"coordinates":[-73.72038499999999,40.725474],"type":"Point"}
}