{
  "type": "Feature",
  "properties": {
    "addr:full":"267 Stafford Ave Staten Island NY 10312",
    "addr:housenumber":"267",
    "addr:postcode":"10312",
    "addr:street":"Stafford Ave",
    "iso:country":"US",
    "sg:address":"267 Stafford Ave",
    "sg:city":"Staten Island",
    "sg:classifiers":[
        {
            "category":"Building & Trades",
            "subcategory":"Construction",
            "type":"Services"
        }
    ],
    "sg:phone":"+1 718 967 4000",
    "sg:postcode":"10312",
    "sg:province":"NY",
    "sg:tags":[
        "concrete",
        "contractor"
    ],
    "wof:name":"Interstate Concrete & Paving C",
    "wof:placetype":"venue"
},
  "geometry": {"coordinates":[-74.188067,40.54578],"type":"Point"}
}