{
  "type": "Feature",
  "properties": {
    "iso:country":"US",
    "sg:address":"86 E Merrick Rd",
    "sg:city":"Freeport",
    "sg:classifiers":[
        {
            "category":"Manufacturing",
            "subcategory":"Rubber & Plastics",
            "type":"Manufacturing & Wholesale Goods"
        }
    ],
    "sg:phone":"+1   ",
    "sg:postcode":"11520",
    "sg:province":"NY",
    "sg:tags":[
        "injection",
        "molding"
    ],
    "wof:name":"Midbury Industries Inc",
    "wof:placetype":"venue"
},
  "geometry": {"coordinates":[-73.57561699999999,40.654612],"type":"Point"}
}