{
  "type": "Feature",
  "properties": {
    "iso:country":"US",
    "sg:address":"5923 7th Ave",
    "sg:city":"Brooklyn",
    "sg:classifiers":[
        {
            "category":"Food & Beverages",
            "subcategory":"Groceries & Convenience Stores",
            "type":"Retail Goods"
        }
    ],
    "sg:phone":"+1 718 492 9190",
    "sg:postcode":"11220",
    "sg:province":"NY",
    "sg:tags":[
        "grocer"
    ],
    "wof:name":"5923 7th Avenue Corp",
    "wof:placetype":"venue"
},
  "geometry": {"coordinates":[-74.01159800000001,40.636907],"type":"Point"}
}