{
  "type": "Feature",
  "properties": {
    "addr:full":"4821 Avenue N Brooklyn NY 11234",
    "addr:housenumber":"4821",
    "addr:postcode":"11234",
    "addr:street":"Avenue N",
    "iso:country":"US",
    "sg:address":"4821 Avenue N",
    "sg:city":"Brooklyn",
    "sg:classifiers":[
        {
            "category":"Building & Trades",
            "subcategory":"Construction",
            "type":"Services"
        }
    ],
    "sg:phone":"+1 718 677 1390",
    "sg:postcode":"11234",
    "sg:province":"NY",
    "sg:tags":[
        "resurfacing",
        "refinishing",
        "floor"
    ],
    "wof:name":"Kings Plaza Floor Scraping",
    "wof:placetype":"venue"
},
  "geometry": {"coordinates":[-73.928034,40.618951],"type":"Point"}
}