{
  "type": "Feature",
  "properties": {
    "addr:full":"409 S 5th St Brooklyn NY 11211",
    "addr:housenumber":"409",
    "addr:postcode":"11211",
    "addr:street":"S 5Th St",
    "iso:country":"US",
    "sg:address":"409 S 5th St",
    "sg:city":"Brooklyn",
    "sg:classifiers":[
        {
            "category":"Home & Garden",
            "subcategory":"Building Materials",
            "type":"Retail Goods"
        }
    ],
    "sg:phone":"+1 718 388 1990",
    "sg:postcode":"11211",
    "sg:province":"NY",
    "sg:tags":[
        "paint"
    ],
    "wof:name":"Sam Wasser",
    "wof:placetype":"venue"
},
  "geometry": {"coordinates":[-73.95360599999999,40.707744],"type":"Point"}
}