{
  "type": "Feature",
  "properties": {
    "addr:full":"149 Sullivan St New York NY 10012",
    "addr:housenumber":"149",
    "addr:postcode":"10012",
    "addr:street":"Sullivan St",
    "iso:country":"US",
    "sg:address":"149 Sullivan St",
    "sg:city":"New York",
    "sg:classifiers":[
        {
            "category":"Restaurant",
            "type":"Food & Drink"
        }
    ],
    "sg:phone":"+1 212 677 4555",
    "sg:postcode":"10012",
    "sg:province":"NY",
    "sg:tags":[
        "italian"
    ],
    "sg:website":"www.peperossotogo.com",
    "wof:name":"Pepe Rosso To Go",
    "wof:placetype":"venue"
},
  "geometry": {"coordinates":[-74.001509,40.727088],"type":"Point"}
}