{
  "type": "Feature",
  "properties": {
    "addr:full":"130 N Main St New City NY 10956",
    "addr:housenumber":"130",
    "addr:postcode":"10956",
    "addr:street":"N Main St",
    "iso:country":"US",
    "sg:address":"130 N Main St",
    "sg:city":"New City",
    "sg:classifiers":[
        {
            "category":"Professional",
            "subcategory":"Lawyer & Legal Services",
            "type":"Services"
        }
    ],
    "sg:phone":"+1 845 638 1400",
    "sg:postcode":"10956",
    "sg:province":"NY",
    "sg:tags":[
        "attorney"
    ],
    "wof:name":"Freedman Wagner Tabakman Weiss",
    "wof:placetype":"venue"
},
  "geometry": {"coordinates":[-73.98898,41.151162],"type":"Point"}
}