{
  "type": "Feature",
  "properties": {
    "iso:country":"US",
    "sg:address":"51 Main St",
    "sg:city":"Lockport",
    "sg:classifiers":[
        {
            "category":"Shopping",
            "subcategory":"Jewelry",
            "type":"Retail Goods"
        }
    ],
    "sg:phone":"+1 716 433 6456",
    "sg:postcode":"14094",
    "sg:province":"NY",
    "sg:tags":[
        "jeweler"
    ],
    "wof:name":"Mills Jewelers",
    "wof:placetype":"venue"
},
  "geometry": {"coordinates":[-78.690381,43.170428],"type":"Point"}
}