{
  "type": "Feature",
  "properties": {
    "iso:country":"US",
    "sg:address":"3329 Fulton St",
    "sg:city":"Brooklyn",
    "sg:classifiers":[
        {
            "category":"Food & Beverages",
            "subcategory":"Meat & Fish",
            "type":"Retail Goods"
        }
    ],
    "sg:phone":"+1   ",
    "sg:postcode":"11208",
    "sg:province":"NY",
    "wof:name":"Lapalma Meat Markert 2",
    "wof:placetype":"venue"
},
  "geometry": {"coordinates":[-73.87250899999999,40.683609],"type":"Point"}
}