{
  "type": "Feature",
  "properties": {
    "addr:full":"56 Main St Tonawanda NY 14150",
    "addr:housenumber":"56",
    "addr:postcode":"14150",
    "addr:street":"Main St",
    "iso:country":"US",
    "sg:address":"56 Main St",
    "sg:city":"Tonawanda",
    "sg:classifiers":[
        {
            "category":"Personal",
            "subcategory":"Beauty Salon",
            "type":"Services"
        }
    ],
    "sg:phone":"+1 716 695 1858",
    "sg:postcode":"14150",
    "sg:province":"NY",
    "wof:name":"Shear Magic By Linda",
    "wof:placetype":"venue"
},
  "geometry": {"coordinates":[-78.878435,43.019375],"type":"Point"}
}