{
  "type": "Feature",
  "properties": {
    "addr:full":"355 Central Ave Albany NY 12206",
    "addr:housenumber":"355",
    "addr:postcode":"12206",
    "addr:street":"Central Ave",
    "iso:country":"US",
    "sg:address":"355 Central Ave",
    "sg:city":"Albany",
    "sg:classifiers":[
        {
            "category":"Autos & Motor Vehicles",
            "subcategory":"Automobile Sales",
            "type":"Retail Goods"
        }
    ],
    "sg:phone":"+1 518 462 2233",
    "sg:postcode":"12206",
    "sg:province":"NY",
    "sg:tags":[
        "car",
        "dealer"
    ],
    "wof:name":"Sweet Auto Sales",
    "wof:placetype":"venue"
},
  "geometry": {"coordinates":[-73.77474599999999,42.666742],"type":"Point"}
}