{
  "type": "Feature",
  "properties": {
    "iso:country":"US",
    "sg:address":"6001 Niagara Falls Blvd",
    "sg:city":"Niagara Falls",
    "sg:classifiers":[
        {
            "category":"Retail",
            "subcategory":"Auto Repair",
            "type":"Services"
        }
    ],
    "sg:phone":"+1 716 283 2789",
    "sg:postcode":"14304",
    "sg:province":"NY",
    "sg:tags":[
        "shop",
        "specializing",
        "shock",
        "spring"
    ],
    "wof:name":"International Spring Co",
    "wof:placetype":"venue"
},
  "geometry": {"coordinates":[-78.99482399999999,43.09013],"type":"Point"}
}