{
  "type": "Feature",
  "properties": {
    "addr:full":"1716 56th St Brooklyn NY 11204",
    "addr:housenumber":"1716",
    "addr:postcode":"11204",
    "addr:street":"56Th St",
    "iso:country":"US",
    "sg:address":"1716 56th St",
    "sg:city":"Brooklyn",
    "sg:classifiers":[
        {
            "category":"Real Estate",
            "subcategory":"Real Estate Operator",
            "type":"Services"
        }
    ],
    "sg:phone":"+1 718 259 4092",
    "sg:postcode":"11204",
    "sg:province":"NY",
    "sg:tags":[
        "mobile",
        "home",
        "site"
    ],
    "wof:name":"Holiday Hills Estates Corp",
    "wof:placetype":"venue"
},
  "geometry": {"coordinates":[-73.98527900000001,40.624479],"type":"Point"}
}