{
  "type": "Feature",
  "properties": {
    "addr:full":"110 Franklin St Malone NY 12953",
    "addr:housenumber":"110",
    "addr:postcode":"12953",
    "addr:street":"Franklin St",
    "iso:country":"US",
    "sg:address":"110 Franklin St",
    "sg:city":"Malone",
    "sg:classifiers":[
        {
            "category":"Banks & Credit Unions",
            "subcategory":"Investment Brokerage",
            "type":"Services"
        }
    ],
    "sg:phone":"+1 518 483 7825",
    "sg:postcode":"12953",
    "sg:province":"NY",
    "sg:tags":[
        "advisory",
        "planning",
        "financial",
        "consultant"
    ],
    "sg:website":"http://www.ameriprise.com",
    "wof:name":"Ameriprise Financial",
    "wof:placetype":"venue"
},
  "geometry": {"coordinates":[-74.303614,44.843369],"type":"Point"}
}