{
  "type": "Feature",
  "properties": {
    "addr:full":"34 Park St Canton NY 13617",
    "addr:housenumber":"34",
    "addr:postcode":"13617",
    "addr:street":"Park St",
    "iso:country":"US",
    "sg:address":"34 Park St",
    "sg:city":"Canton",
    "sg:classifiers":[
        {
            "category":"Real Estate",
            "subcategory":"Real Estate Agent",
            "type":"Services"
        }
    ],
    "sg:phone":"+1 315 386 4521",
    "sg:postcode":"13617",
    "sg:province":"NY",
    "sg:tags":[
        "loan",
        "management",
        "consul",
        "broker"
    ],
    "wof:name":"Pat Collins Real Estate",
    "wof:placetype":"venue"
},
  "geometry": {"coordinates":[-75.16783,44.593549],"type":"Point"}
}