{
  "type": "Feature",
  "properties": {
    "addr:full":"6720 Pittsford Palmyra Rd Fairport NY 14450",
    "addr:housenumber":"6720",
    "addr:postcode":"14450",
    "addr:street":"Pittsford Palmyra Rd",
    "iso:country":"US",
    "sg:address":"6720 Pittsford Palmyra Rd",
    "sg:city":"Fairport",
    "sg:classifiers":[
        {
            "category":"Restaurant",
            "type":"Food & Drink"
        }
    ],
    "sg:phone":"+1 585 223 4240",
    "sg:postcode":"14450",
    "sg:province":"NY",
    "sg:tags":[
        "shop",
        "coffee"
    ],
    "sg:website":"www.starbucks.com",
    "wof:name":"Starbucks",
    "wof:placetype":"venue"
},
  "geometry": {"coordinates":[-77.439438,43.06903],"type":"Point"}
}