{
  "type": "Feature",
  "properties": {
    "iso:country":"US",
    "sg:address":"45 April Ln",
    "sg:city":"Nanuet",
    "sg:classifiers":[
        {
            "category":"Food & Beverages",
            "subcategory":"Specialty",
            "type":"Retail Goods"
        }
    ],
    "sg:phone":"+1   ",
    "sg:postcode":"10954",
    "sg:province":"NY",
    "sg:tags":[
        "store",
        "variety"
    ],
    "wof:name":"Youngs Discount Town",
    "wof:placetype":"venue"
},
  "geometry": {"coordinates":[-74.005352,41.082865],"type":"Point"}
}