{
  "type": "Feature",
  "properties": {
    "addr:full":"88 Nassau Blvd Garden City NY 11530",
    "addr:housenumber":"88",
    "addr:postcode":"11530",
    "addr:street":"Nassau Blvd",
    "iso:country":"US",
    "sg:address":"88 Nassau Blvd",
    "sg:city":"Garden City",
    "sg:classifiers":[
        {
            "category":"Autos & Motor Vehicles",
            "subcategory":"Fuel & Gas Station",
            "type":"Retail Goods"
        }
    ],
    "sg:phone":"+1   ",
    "sg:postcode":"11530",
    "sg:province":"NY",
    "sg:tags":[
        "station",
        "gasoline"
    ],
    "wof:name":"Shell",
    "wof:placetype":"venue"
},
  "geometry": {"coordinates":[-73.66082299999999,40.723736],"type":"Point"}
}