{
  "type": "Feature",
  "properties": {
    "addr:full":"566 S 4th St Fulton NY 13069",
    "addr:housenumber":"566",
    "addr:postcode":"13069",
    "addr:street":"S 4Th St",
    "iso:country":"US",
    "sg:address":"566 S 4th St",
    "sg:city":"Fulton",
    "sg:classifiers":[
        {
            "category":"Real Estate",
            "subcategory":"Real Estate Agent",
            "type":"Services"
        }
    ],
    "sg:phone":"+1 315 598 1165",
    "sg:postcode":"13069",
    "sg:province":"NY",
    "wof:name":"Leah's Signature",
    "wof:placetype":"venue"
},
  "geometry": {"coordinates":[-76.403586,43.312467],"type":"Point"}
}