{
  "type": "Feature",
  "properties": {
    "iso:country":"US",
    "sg:address":"228 Bridge St",
    "sg:city":"East Syracuse",
    "sg:classifiers":[
        {
            "category":"Retail",
            "subcategory":"Animal Services",
            "type":"Services"
        }
    ],
    "sg:phone":"+1 315 437 7110",
    "sg:postcode":"13057",
    "sg:province":"NY",
    "sg:tags":[
        "pet",
        "boarding",
        "sitting"
    ],
    "wof:name":"K-9 KAMP Dog Daycare",
    "wof:placetype":"venue"
},
  "geometry": {"coordinates":[-76.06687599999999,43.060454],"type":"Point"}
}