{
  "type": "Feature",
  "properties": {
    "addr:full":"209 Hillside Ave Williston Park NY 11596",
    "addr:housenumber":"209",
    "addr:postcode":"11596",
    "addr:street":"Hillside Ave",
    "iso:country":"US",
    "sg:address":"209 Hillside Ave",
    "sg:city":"Williston Park",
    "sg:classifiers":[
        {
            "category":"Building & Trades",
            "subcategory":"Plumbing",
            "type":"Services"
        }
    ],
    "sg:phone":"+1 516 746 0045",
    "sg:postcode":"11596",
    "sg:province":"NY",
    "sg:tags":[
        "plumbing",
        "contractor"
    ],
    "wof:name":"Gramman Plumbing & Heating",
    "wof:placetype":"venue"
},
  "geometry": {"coordinates":[-73.647595,40.755346],"type":"Point"}
}