{
  "type": "Feature",
  "properties": {
    "addr:full":"5 John Ct Yaphank NY 11980",
    "addr:housenumber":"5",
    "addr:postcode":"11980",
    "addr:street":"John Ct",
    "iso:country":"US",
    "sg:address":"5 John Ct",
    "sg:city":"Yaphank",
    "sg:classifiers":[
        {
            "category":"Building & Trades",
            "subcategory":"Landscaping Services",
            "type":"Services"
        }
    ],
    "sg:phone":"+1 631 345 9076",
    "sg:postcode":"11980",
    "sg:province":"NY",
    "sg:tags":[
        "landscape",
        "contractor"
    ],
    "wof:name":"Nature's Best Landscaping",
    "wof:placetype":"venue"
},
  "geometry": {"coordinates":[-72.90409,40.808785],"type":"Point"}
}