{
  "type": "Feature",
  "properties": {
    "iso:country":"US",
    "sg:address":"8 N Neck Ln",
    "sg:city":"Quogue",
    "sg:classifiers":[
        {
            "category":"Professional",
            "type":"Services"
        }
    ],
    "sg:phone":"+1 631 653 0028",
    "sg:postcode":"11954",
    "sg:province":"NY",
    "sg:tags":[
        "establishment"
    ],
    "wof:name":"Penniman's Point LTD Prtnrshp",
    "wof:placetype":"venue"
},
  "geometry": {"coordinates":[-71.956067,41.056855],"type":"Point"}
}