{
  "type": "Feature",
  "properties": {
    "iso:country":"US",
    "sg:address":"20 Cross Rd",
    "sg:city":"Cross River",
    "sg:classifiers":[
        {
            "category":"Building & Trades",
            "subcategory":"Construction",
            "type":"Services"
        }
    ],
    "sg:phone":"+1 914 234 3492",
    "sg:postcode":"10567",
    "sg:province":"NY",
    "sg:tags":[
        "hanging",
        "contractor"
    ],
    "wof:name":"Bradsell Painting Inc",
    "wof:placetype":"venue"
},
  "geometry": {"coordinates":[-73.87499099999999,41.275447],"type":"Point"}
}