{
  "type": "Feature",
  "properties": {
    "addr:full":"257 W 39 St New York NY 10018",
    "addr:housenumber":"257",
    "addr:postcode":"10018",
    "addr:street":"W 39 St",
    "iso:country":"US",
    "sg:address":"257 W 39 St",
    "sg:city":"New York",
    "sg:classifiers":[
        {
            "category":"Professional",
            "type":"Services"
        }
    ],
    "sg:phone":"+1 212 398 4598",
    "sg:postcode":"10018",
    "sg:province":"NY",
    "sg:tags":[
        "establishment"
    ],
    "wof:name":"Fitwork Production Inc",
    "wof:placetype":"venue"
},
  "geometry": {"coordinates":[-73.98990999999999,40.75471],"type":"Point"}
}