{
  "type": "Feature",
  "properties": {
    "addr:full":"402 Union Ave Brooklyn NY 11211",
    "addr:housenumber":"402",
    "addr:postcode":"11211",
    "addr:street":"Union Ave",
    "iso:country":"US",
    "sg:address":"402 Union Ave",
    "sg:city":"Brooklyn",
    "sg:classifiers":[
        {
            "category":"Professional",
            "subcategory":"Accounting & Tax Preparation",
            "type":"Services"
        }
    ],
    "sg:phone":"+1 718 387 2837",
    "sg:postcode":"11211",
    "sg:province":"NY",
    "sg:tags":[
        "bookkeeping",
        "general"
    ],
    "wof:name":"Paul Massotti",
    "wof:placetype":"venue"
},
  "geometry": {"coordinates":[-73.951465,40.713105],"type":"Point"}
}