{
  "type": "Feature",
  "properties": {
    "addr:full":"75 Caldwell Pl Lackawanna NY 14218",
    "addr:housenumber":"75",
    "addr:postcode":"14218",
    "addr:street":"Caldwell Pl",
    "iso:country":"US",
    "sg:address":"75 Caldwell Pl",
    "sg:city":"Lackawanna",
    "sg:classifiers":[
        {
            "category":"Organizations",
            "subcategory":"Religious Organization",
            "type":"Services"
        }
    ],
    "sg:phone":"+1 716 825 8955",
    "sg:postcode":"14218",
    "sg:province":"NY",
    "sg:tags":[
        "church"
    ],
    "wof:name":"St Barbara's Parish Ctr",
    "wof:placetype":"venue"
},
  "geometry": {"coordinates":[-78.829838,42.82492],"type":"Point"}
}