{
  "type": "Feature",
  "properties": {
    "iso:country":"US",
    "sg:address":"8707 5th Ave",
    "sg:city":"Brooklyn",
    "sg:classifiers":[
        {
            "category":"Food & Beverages",
            "subcategory":"Groceries & Convenience Stores",
            "type":"Retail Goods"
        }
    ],
    "sg:phone":"+1 718 680 2394",
    "sg:postcode":"11209",
    "sg:province":"NY",
    "sg:tags":[
        "grocer"
    ],
    "wof:name":"Exotic Food",
    "wof:placetype":"venue"
},
  "geometry": {"coordinates":[-74.027136,40.620314],"type":"Point"}
}