{
  "type": "Feature",
  "properties": {
    "iso:country":"US",
    "sg:address":"31 Merrick Ave",
    "sg:city":"Merrick",
    "sg:classifiers":[
        {
            "category":"Health Services",
            "subcategory":"Health Practitioner",
            "type":"Services"
        }
    ],
    "sg:phone":"+1   ",
    "sg:postcode":"11566",
    "sg:province":"NY",
    "wof:name":"Merrill Weiner",
    "wof:placetype":"venue"
},
  "geometry": {"coordinates":[-73.552542,40.664625],"type":"Point"}
}