{
  "type": "Feature",
  "properties": {
    "addr:full":"2720 Hylan Blvd Staten Island NY 10306",
    "addr:housenumber":"2720",
    "addr:postcode":"10306",
    "addr:street":"Hylan Blvd",
    "iso:country":"US",
    "sg:address":"2720 Hylan Blvd",
    "sg:city":"Staten Island",
    "sg:classifiers":[
        {
            "category":"Building & Trades",
            "subcategory":"Locksmith",
            "type":"Services"
        }
    ],
    "sg:phone":"+1 917 423 8510",
    "sg:postcode":"10306",
    "sg:province":"NY",
    "sg:tags":[
        "key"
    ],
    "wof:name":"0 One A1 Lock Smith",
    "wof:placetype":"venue"
},
  "geometry": {"coordinates":[-74.113956,40.565975],"type":"Point"}
}