{
  "type": "Feature",
  "properties": {
    "iso:country":"US",
    "sg:address":"83 Canal St",
    "sg:city":"New York",
    "sg:classifiers":[
        {
            "category":"Manufacturing",
            "subcategory":"Jewelry",
            "type":"Manufacturing & Wholesale Goods"
        }
    ],
    "sg:phone":"+1 212 226 3716",
    "sg:postcode":"10002",
    "sg:province":"NY",
    "wof:name":"Nutovic Inc",
    "wof:placetype":"venue"
},
  "geometry": {"coordinates":[-73.99290000000001,40.715235],"type":"Point"}
}