{
  "type": "Feature",
  "properties": {
    "addr:full":"900 Old Liverpool Rd Liverpool NY 13088",
    "addr:housenumber":"900",
    "addr:postcode":"13088",
    "addr:street":"Old Liverpool Rd",
    "iso:country":"US",
    "sg:address":"900 Old Liverpool Rd",
    "sg:city":"Liverpool",
    "sg:classifiers":[
        {
            "category":"Professional",
            "type":"Services"
        }
    ],
    "sg:phone":"+1 315 461 9900",
    "sg:postcode":"13088",
    "sg:province":"NY",
    "sg:tags":[
        "establishment"
    ],
    "wof:name":"Reading's Fun Of CNY",
    "wof:placetype":"venue"
},
  "geometry": {"coordinates":[-76.198717,43.099622],"type":"Point"}
}