{
  "type": "Feature",
  "properties": {
    "addr:full":"73 Gramatan Ave Mount Vernon NY 10550",
    "addr:housenumber":"73",
    "addr:postcode":"10550",
    "addr:street":"Gramatan Ave",
    "iso:country":"US",
    "sg:address":"73 Gramatan Ave",
    "sg:city":"Mount Vernon",
    "sg:classifiers":[
        {
            "category":"Restaurant",
            "type":"Food & Drink"
        }
    ],
    "sg:menulink":"http://www.allmenus.com/ny/mount-vernon/82734-dominos-pizza/menu/",
    "sg:phone":"+1 914 668 3030",
    "sg:postcode":"10550",
    "sg:province":"NY",
    "sg:tags":[
        "american",
        "wing",
        "pizza"
    ],
    "wof:name":"Domino's Pizza",
    "wof:placetype":"venue"
},
  "geometry": {"coordinates":[-73.837324,40.913823],"type":"Point"}
}