{
  "type": "Feature",
  "properties": {
    "iso:country":"US",
    "sg:address":"694 Forest Ave",
    "sg:city":"Staten Island",
    "sg:classifiers":[
        {
            "category":"Real Estate",
            "subcategory":"Architect",
            "type":"Services"
        }
    ],
    "sg:phone":"+1 718 720 3478",
    "sg:postcode":"10310",
    "sg:province":"NY",
    "wof:name":"Victorio Ronald D Archt",
    "wof:placetype":"venue"
},
  "geometry": {"coordinates":[-74.11129800000001,40.629799],"type":"Point"}
}