{
  "type": "Feature",
  "properties": {
    "addr:full":"3 Swim Club Rd Stony Point NY 10980",
    "addr:postcode":"10980",
    "addr:street":"Rd",
    "iso:country":"US",
    "sg:address":"3 Swim Club Rd",
    "sg:city":"Stony Point",
    "sg:classifiers":[
        {
            "category":"Restaurant",
            "type":"Food & Drink"
        }
    ],
    "sg:phone":"+1   ",
    "sg:postcode":"10980",
    "sg:province":"NY",
    "sg:tags":[
        "personal",
        "eating"
    ],
    "sg:website":"www.marvellocountryclub.com",
    "wof:name":"Marvello Country Club",
    "wof:placetype":"venue"
},
  "geometry": {"coordinates":[-74.024919,41.24089],"type":"Point"}
}