{
  "type": "Feature",
  "properties": {
    "iso:country":"US",
    "sg:address":"15 Gable Rd",
    "sg:city":"New City",
    "sg:classifiers":[
        {
            "category":"Professional",
            "subcategory":"Management & Consulting",
            "type":"Services"
        }
    ],
    "sg:phone":"+1   ",
    "sg:postcode":"10956",
    "sg:province":"NY",
    "sg:tags":[
        "retail",
        "direct",
        "sales"
    ],
    "wof:name":"Marc Ostrie & Associates Inc",
    "wof:placetype":"venue"
},
  "geometry": {"coordinates":[-73.984509,41.132897],"type":"Point"}
}