{
  "type": "Feature",
  "properties": {
    "iso:country":"US",
    "sg:address":"80 Highland Rd",
    "sg:city":"Glen Cove",
    "sg:classifiers":[
        {
            "category":"Shopping",
            "subcategory":"Stationery & Office Supplies",
            "type":"Retail Goods"
        }
    ],
    "sg:phone":"+1   ",
    "sg:postcode":"11542",
    "sg:province":"NY",
    "wof:name":"Paper Inc",
    "wof:placetype":"venue"
},
  "geometry": {"coordinates":[-73.623628,40.865981],"type":"Point"}
}