{
  "type": "Feature",
  "properties": {
    "addr:full":"915 Central Park Ave Scarsdale NY 10583",
    "addr:housenumber":"915",
    "addr:postcode":"10583",
    "addr:street":"Central Park Ave",
    "iso:country":"US",
    "sg:address":"915 Central Park Ave",
    "sg:city":"Scarsdale",
    "sg:classifiers":[
        {
            "category":"Professional",
            "type":"Services"
        }
    ],
    "sg:phone":"+1 914 722 6296",
    "sg:postcode":"10583",
    "sg:province":"NY",
    "sg:tags":[
        "establishment"
    ],
    "wof:name":"New York Connecticut Dev Corp",
    "wof:placetype":"venue"
},
  "geometry": {"coordinates":[-73.818622,40.995742],"type":"Point"}
}