{
  "type": "Feature",
  "properties": {
    "addr:full":"286 Katonah Ave Katonah NY 10536",
    "addr:housenumber":"286",
    "addr:postcode":"10536",
    "addr:street":"Katonah Ave",
    "iso:country":"US",
    "sg:address":"286 Katonah Ave",
    "sg:city":"Katonah",
    "sg:classifiers":[
        {
            "category":"Restaurant",
            "type":"Food & Drink"
        },
        {
            "category":"Food & Beverages",
            "subcategory":"Ethnic Foods",
            "type":"Retail Goods"
        }
    ],
    "sg:phone":"+1 914 232 3900",
    "sg:postcode":"10536",
    "sg:province":"NY",
    "sg:tags":[
        "asian",
        "pan",
        "vietnamese"
    ],
    "wof:name":"Tengda Asian Bistro",
    "wof:placetype":"venue"
},
  "geometry": {"coordinates":[-73.68406400000001,41.254926],"type":"Point"}
}