{
  "type": "Feature",
  "properties": {
    "addr:full":"1959 60th St Brooklyn NY 11204",
    "addr:housenumber":"1959",
    "addr:postcode":"11204",
    "addr:street":"60Th St",
    "iso:country":"US",
    "sg:address":"1959 60th St",
    "sg:city":"Brooklyn",
    "sg:classifiers":[
        {
            "category":"Professional",
            "subcategory":"Business Services",
            "type":"Services"
        }
    ],
    "sg:phone":"+1 718 256 3100",
    "sg:postcode":"11204",
    "sg:province":"NY",
    "sg:tags":[
        "event"
    ],
    "wof:name":"Current Events",
    "wof:placetype":"venue"
},
  "geometry": {"coordinates":[-73.98382599999999,40.620227],"type":"Point"}
}