{
  "type": "Feature",
  "properties": {
    "iso:country":"US",
    "sg:address":"125 Gage Rd",
    "sg:city":"Newport",
    "sg:classifiers":[
        {
            "category":"Shopping",
            "subcategory":"Computers & Home Electronics",
            "type":"Retail Goods"
        }
    ],
    "sg:phone":"+1 315 845 8141",
    "sg:postcode":"13416",
    "sg:province":"NY",
    "sg:tags":[
        "equipment",
        "satellite",
        "system"
    ],
    "wof:name":"Stark Satellite Sales",
    "wof:placetype":"venue"
},
  "geometry": {"coordinates":[-74.994953,43.201817],"type":"Point"}
}