{
  "type": "Feature",
  "properties": {
    "addr:full":"455 E 14 St New York NY 10009",
    "addr:housenumber":"455;14",
    "addr:postcode":"10009",
    "addr:street":"E",
    "iso:country":"US",
    "sg:address":"455 E 14 St",
    "sg:city":"New York",
    "sg:classifiers":[
        {
            "category":"Professional",
            "type":"Services"
        }
    ],
    "sg:phone":"+1 212 475 6576",
    "sg:postcode":"10009",
    "sg:province":"NY",
    "sg:tags":[
        "establishment"
    ],
    "wof:name":"De Waart HAAM",
    "wof:placetype":"venue"
},
  "geometry": {"coordinates":[-73.98123200000001,40.731016],"type":"Point"}
}