{
  "type": "Feature",
  "properties": {
    "iso:country":"US",
    "sg:address":"125 Maiden Ln",
    "sg:city":"New York",
    "sg:classifiers":[
        {
            "category":"Wholesale",
            "subcategory":"Furniture",
            "type":"Manufacturing & Wholesale Goods"
        }
    ],
    "sg:phone":"+1 212 269 6800",
    "sg:postcode":"10038",
    "sg:province":"NY",
    "wof:name":"Sbfi Inc",
    "wof:placetype":"venue"
},
  "geometry": {"coordinates":[-74.00631300000001,40.706544],"type":"Point"}
}