{
  "type": "Feature",
  "properties": {
    "iso:country":"US",
    "sg:address":"4335 Dean School Rd",
    "sg:city":"Kennedy",
    "sg:classifiers":[
        {
            "category":"Sports & Exercise",
            "subcategory":"Golf",
            "type":"Entertainment"
        }
    ],
    "sg:phone":"+1 716 287 2138",
    "sg:postcode":"14733",
    "sg:province":"NY",
    "sg:tags":[
        "course"
    ],
    "wof:name":"Breezewood Golf Links",
    "wof:placetype":"venue"
},
  "geometry": {"coordinates":[-79.162601,42.194018],"type":"Point"}
}