{
  "type": "Feature",
  "properties": {
    "iso:country":"US",
    "sg:address":"111 N Pearl St",
    "sg:city":"Albany",
    "sg:classifiers":[
        {
            "category":"Arts & Performance",
            "subcategory":"Theater",
            "type":"Entertainment"
        }
    ],
    "sg:phone":"+1 518 462 4531",
    "sg:postcode":"12207",
    "sg:province":"NY",
    "sg:website":"www.capitalrep.org",
    "wof:name":"Capital Repertory Co",
    "wof:placetype":"venue"
},
  "geometry": {"coordinates":[-73.75022,42.653379],"type":"Point"}
}