{
  "type": "Feature",
  "properties": {
    "iso:country":"US",
    "sg:address":"73 Saginaw Dr",
    "sg:city":"Rochester",
    "sg:classifiers":[
        {
            "category":"Building & Trades",
            "subcategory":"Construction",
            "type":"Services"
        }
    ],
    "sg:phone":"+1 585 424 6840",
    "sg:postcode":"14623",
    "sg:province":"NY",
    "sg:tags":[
        "roofing",
        "contractor"
    ],
    "wof:name":"A W Farrell & Sons",
    "wof:placetype":"venue"
},
  "geometry": {"coordinates":[-77.58938499999999,43.087021],"type":"Point"}
}