{
  "type": "Feature",
  "properties": {
    "addr:full":"20 Woodlawn Ave Greenwich NY 12834",
    "addr:housenumber":"20",
    "addr:postcode":"12834",
    "addr:street":"Woodlawn Ave",
    "iso:country":"US",
    "sg:address":"20 Woodlawn Ave",
    "sg:city":"Greenwich",
    "sg:classifiers":[
        {
            "category":"Real Estate",
            "subcategory":"Real Estate Operator",
            "type":"Services"
        }
    ],
    "sg:phone":"+1 518 692 9532",
    "sg:postcode":"12834",
    "sg:province":"NY",
    "sg:tags":[
        "building",
        "apartment"
    ],
    "wof:name":"Cynthia Meadow",
    "wof:placetype":"venue"
},
  "geometry": {"coordinates":[-73.498485,43.095736],"type":"Point"}
}