{
  "type": "Feature",
  "properties": {
    "iso:country":"US",
    "sg:address":"45 Rockland Ctr",
    "sg:city":"Nanuet",
    "sg:classifiers":[
        {
            "category":"Restaurant",
            "type":"Food & Drink"
        }
    ],
    "sg:phone":"+1 845 623 5494",
    "sg:postcode":"10954",
    "sg:province":"NY",
    "wof:name":"Chon Bon Chicken",
    "wof:placetype":"venue"
},
  "geometry": {"coordinates":[-74.01639299999999,41.084497],"type":"Point"}
}