{
  "type": "Feature",
  "properties": {
    "addr:full":"83 Main St Nyack NY 10960",
    "addr:housenumber":"83",
    "addr:postcode":"10960",
    "addr:street":"Main St",
    "iso:country":"US",
    "sg:address":"83 Main St",
    "sg:city":"Nyack",
    "sg:classifiers":[
        {
            "category":"Health Services",
            "subcategory":"Health Practitioner",
            "type":"Services"
        }
    ],
    "sg:phone":"+1 845 729 1855",
    "sg:postcode":"10960",
    "sg:province":"NY",
    "sg:tags":[
        "psychotherapist"
    ],
    "wof:name":"Robin J Wallace",
    "wof:placetype":"venue"
},
  "geometry": {"coordinates":[-73.91930600000001,41.091055],"type":"Point"}
}