{
  "type": "Feature",
  "properties": {
    "iso:country":"US",
    "sg:address":"885 Co Rte 29",
    "sg:city":"Oswego",
    "sg:classifiers":[
        {
            "category":"Bars & Pubs",
            "type":"Food & Drink"
        }
    ],
    "sg:phone":"+1 315 342 2950",
    "sg:postcode":"13126",
    "sg:province":"NY",
    "wof:name":"Route 29 Entertainment Inc",
    "wof:placetype":"venue"
},
  "geometry": {"coordinates":[-76.38496600000001,43.481535],"type":"Point"}
}