{
  "type": "Feature",
  "properties": {
    "addr:full":"669 Shingle St Morrisonville NY 12962",
    "addr:housenumber":"669",
    "addr:postcode":"12962",
    "addr:street":"Shingle St",
    "iso:country":"US",
    "sg:address":"669 Shingle St",
    "sg:city":"Morrisonville",
    "sg:classifiers":[
        {
            "category":"Building & Trades",
            "subcategory":"Cleaning & Sanitation",
            "type":"Services"
        }
    ],
    "sg:phone":"+1 518 643 9978",
    "sg:postcode":"12962",
    "sg:province":"NY",
    "sg:tags":[
        "supply",
        "septic",
        "tanks-treatment"
    ],
    "wof:name":"Shingle Street Sand And Septic",
    "wof:placetype":"venue"
},
  "geometry": {"coordinates":[-73.602079,44.66458],"type":"Point"}
}