{
  "type": "Feature",
  "properties": {
    "iso:country":"US",
    "sg:address":"490 State Hwy 304",
    "sg:city":"New City",
    "sg:classifiers":[
        {
            "category":"Health Services",
            "subcategory":"Doctor",
            "type":"Services"
        }
    ],
    "sg:phone":"+1 845 634 9400",
    "sg:postcode":"10956",
    "sg:province":"NY",
    "sg:tags":[
        "medical"
    ],
    "wof:name":"Bernard Laitman",
    "wof:placetype":"venue"
},
  "geometry": {"coordinates":[-73.991455,41.130023],"type":"Point"}
}