{
  "type": "Feature",
  "properties": {
    "iso:country":"US",
    "sg:address":"4330 Amboy Rd",
    "sg:city":"Staten Island",
    "sg:classifiers":[
        {
            "category":"Personal",
            "subcategory":"Beauty Salon",
            "type":"Services"
        }
    ],
    "sg:phone":"+1 718 967 1184",
    "sg:postcode":"10312",
    "sg:province":"NY",
    "wof:name":"Posh Hair & Nail Emporium",
    "wof:placetype":"venue"
},
  "geometry": {"coordinates":[-74.162921,40.544049],"type":"Point"}
}