{
  "type": "Feature",
  "properties": {
    "addr:full":"156 5th Ave New York NY 10010",
    "addr:housenumber":"156",
    "addr:postcode":"10010",
    "addr:street":"5Th Ave",
    "iso:country":"US",
    "sg:address":"156 5th Ave",
    "sg:city":"New York",
    "sg:classifiers":[
        {
            "category":"Professional",
            "subcategory":"Business Services",
            "type":"Services"
        }
    ],
    "sg:phone":"+1 646 485 8792",
    "sg:postcode":"10010",
    "sg:province":"NY",
    "sg:tags":[
        "apparel",
        "designer"
    ],
    "wof:name":"Mrs Mudd LLC",
    "wof:placetype":"venue"
},
  "geometry": {"coordinates":[-73.990692,40.740101],"type":"Point"}
}