{
  "type": "Feature",
  "properties": {
    "iso:country":"US",
    "sg:address":"555 Maple Ave",
    "sg:city":"Saratoga Springs",
    "sg:classifiers":[
        {
            "category":"Real Estate",
            "subcategory":"Real Estate Agent",
            "type":"Services"
        }
    ],
    "sg:phone":"+1 518 583 9888",
    "sg:postcode":"12866",
    "sg:province":"NY",
    "wof:name":"Warren Prime Properties",
    "wof:placetype":"venue"
},
  "geometry": {"coordinates":[-73.771422,43.109464],"type":"Point"}
}