{
  "type": "Feature",
  "properties": {
    "addr:full":"20 Trade Rd Plattsburgh NY 12901",
    "addr:housenumber":"20",
    "addr:postcode":"12901",
    "addr:street":"Trade Rd",
    "iso:country":"US",
    "sg:address":"20 Trade Rd",
    "sg:city":"Plattsburgh",
    "sg:classifiers":[
        {
            "category":"Communications",
            "subcategory":"Television Station",
            "type":"Services"
        },
        {
            "category":"Communications",
            "type":"Services"
        },
        {
            "category":"Shopping",
            "subcategory":"Computers & Home Electronics",
            "type":"Retail Goods"
        }
    ],
    "sg:phone":"+1 518 562 9790",
    "sg:postcode":"12901",
    "sg:province":"NY",
    "sg:tags":[
        "sound",
        "satellite",
        "cable",
        "system",
        "equipment",
        "radio",
        "store"
    ],
    "wof:name":"Prime Service Center",
    "wof:placetype":"venue"
},
  "geometry": {"coordinates":[-73.469427,44.718837],"type":"Point"}
}