{
  "type": "Feature",
  "properties": {
    "addr:full":"1415 Pelhamdale Ave Pelham NY 10803",
    "addr:housenumber":"1415",
    "addr:postcode":"10803",
    "addr:street":"Pelhamdale Ave",
    "iso:country":"US",
    "sg:address":"1415 Pelhamdale Ave",
    "sg:city":"Pelham",
    "sg:classifiers":[
        {
            "category":"Social Services",
            "type":"Services"
        }
    ],
    "sg:phone":"+1   ",
    "sg:postcode":"10803",
    "sg:province":"NY",
    "wof:name":"Counseling Center",
    "wof:placetype":"venue"
},
  "geometry": {"coordinates":[-73.791464,40.887003],"type":"Point"}
}