{
  "type": "Feature",
  "properties": {
    "iso:country":"US",
    "sg:address":"5312 Jillian Ln",
    "sg:city":"Brewerton",
    "sg:classifiers":[
        {
            "category":"Professional",
            "subcategory":"Management & Consulting",
            "type":"Services"
        }
    ],
    "sg:phone":"+1 315 676 5616",
    "sg:postcode":"13029",
    "sg:province":"NY",
    "wof:name":"Intervention Pain Mgmt Assoc",
    "wof:placetype":"venue"
},
  "geometry": {"coordinates":[-76.150424,43.225244],"type":"Point"}
}