{
  "type": "Feature",
  "properties": {
    "addr:full":"347 Linden St Brooklyn NY 11237",
    "addr:housenumber":"347",
    "addr:postcode":"11237",
    "addr:street":"Linden St",
    "iso:country":"US",
    "sg:address":"347 Linden St",
    "sg:city":"Brooklyn",
    "sg:classifiers":[
        {
            "category":"Personal",
            "subcategory":"Beauty Salon",
            "type":"Services"
        }
    ],
    "sg:phone":"+1 718 497 3050",
    "sg:postcode":"11237",
    "sg:province":"NY",
    "wof:name":"Glow Beauty Salon",
    "wof:placetype":"venue"
},
  "geometry": {"coordinates":[-73.91277100000001,40.70021],"type":"Point"}
}