{
  "type": "Feature",
  "properties": {
    "iso:country":"US",
    "sg:address":"216 Hamilton St",
    "sg:city":"Penn Yan",
    "sg:classifiers":[
        {
            "category":"Restaurant",
            "type":"Food & Drink"
        }
    ],
    "sg:phone":"+1 315 536 9613",
    "sg:postcode":"14527",
    "sg:province":"NY",
    "sg:tags":[
        "out"
    ],
    "wof:name":"Adirondack Deli",
    "wof:placetype":"venue"
},
  "geometry": {"coordinates":[-77.050072,42.668607],"type":"Point"}
}