{
  "type": "Feature",
  "properties": {
    "addr:full":"464 W Lake Rd Oswego NY 13126",
    "addr:housenumber":"464",
    "addr:postcode":"13126",
    "addr:street":"W Lake Rd",
    "iso:country":"US",
    "sg:address":"464 W Lake Rd",
    "sg:city":"Oswego",
    "sg:classifiers":[
        {
            "category":"Wholesale",
            "subcategory":"Groceries",
            "type":"Manufacturing & Wholesale Goods"
        }
    ],
    "sg:phone":"+1 315 342 7631",
    "sg:postcode":"13126",
    "sg:province":"NY",
    "sg:tags":[
        "general"
    ],
    "wof:name":"Principal Assoc",
    "wof:placetype":"venue"
},
  "geometry": {"coordinates":[-76.616653,43.415434],"type":"Point"}
}