{
  "type": "Feature",
  "properties": {
    "addr:full":"20 Turner Dr New Rochelle NY 10804",
    "addr:housenumber":"20",
    "addr:postcode":"10804",
    "addr:street":"Turner Dr",
    "iso:country":"US",
    "sg:address":"20 Turner Dr",
    "sg:city":"New Rochelle",
    "sg:classifiers":[
        {
            "category":"Wholesale",
            "subcategory":"Home Furnishings",
            "type":"Manufacturing & Wholesale Goods"
        }
    ],
    "sg:phone":"+1 212 868 2560",
    "sg:postcode":"10804",
    "sg:province":"NY",
    "wof:name":"Ellen Textile Corp",
    "wof:placetype":"venue"
},
  "geometry": {"coordinates":[-73.791804,40.971639],"type":"Point"}
}