{
  "type": "Feature",
  "properties": {
    "addr:full":"298 Dahlgreen Pl Brooklyn NY 11228",
    "addr:housenumber":"298",
    "addr:postcode":"11228",
    "addr:street":"Dahlgreen Pl",
    "iso:country":"US",
    "sg:address":"298 Dahlgreen Pl",
    "sg:city":"Brooklyn",
    "sg:classifiers":[
        {
            "category":"Building & Trades",
            "subcategory":"Construction",
            "type":"Services"
        }
    ],
    "sg:phone":"+1 718 646 2501",
    "sg:postcode":"11228",
    "sg:province":"NY",
    "sg:tags":[
        "general",
        "contractor"
    ],
    "wof:name":"Porter General Contracting",
    "wof:placetype":"venue"
},
  "geometry": {"coordinates":[-74.027402,40.613071],"type":"Point"}
}