{
  "type": "Feature",
  "properties": {
    "addr:full":"3902 Amboy Rd Staten Island NY 10308",
    "addr:housenumber":"3902",
    "addr:postcode":"10308",
    "addr:street":"Amboy Rd",
    "iso:country":"US",
    "sg:address":"3902 Amboy Rd",
    "sg:city":"Staten Island",
    "sg:classifiers":[
        {
            "category":"Arena",
            "subcategory":"Sports Club",
            "type":"Entertainment"
        }
    ],
    "sg:phone":"+1 718 619 0150",
    "sg:postcode":"10308",
    "sg:province":"NY",
    "sg:tags":[
        "martial art"
    ],
    "sg:website":"www.sijjd.com/",
    "wof:name":"Staten Island Judo & Jujitsu Dojo",
    "wof:placetype":"venue"
},
  "geometry": {"coordinates":[-74.14858700000001,40.55141],"type":"Point"}
}