{
  "type": "Feature",
  "properties": {
    "iso:country":"US",
    "sg:address":"1790 Walt Whitman Rd",
    "sg:city":"Melville",
    "sg:classifiers":[
        {
            "category":"Restaurant",
            "type":"Food & Drink"
        }
    ],
    "sg:phone":"+1   ",
    "sg:postcode":"11747",
    "sg:province":"NY",
    "sg:tags":[
        "eating"
    ],
    "wof:name":"Deli Worx Inc",
    "wof:placetype":"venue"
},
  "geometry": {"coordinates":[-73.427789,40.77018],"type":"Point"}
}