{
  "type": "Feature",
  "properties": {
    "addr:full":"228 Earl Ave Syracuse NY 13211",
    "addr:housenumber":"228",
    "addr:postcode":"13211",
    "addr:street":"Earl Ave",
    "iso:country":"US",
    "sg:address":"228 Earl Ave",
    "sg:city":"Syracuse",
    "sg:classifiers":[
        {
            "category":"Real Estate",
            "subcategory":"Real Estate Agent",
            "type":"Services"
        }
    ],
    "sg:phone":"+1 315 454 0423",
    "sg:postcode":"13211",
    "sg:province":"NY",
    "wof:name":"Banker Contracting Services",
    "wof:placetype":"venue"
},
  "geometry": {"coordinates":[-76.13858500000001,43.101583],"type":"Point"}
}