{
  "type": "Feature",
  "properties": {
    "iso:country":"US",
    "sg:address":"224 W Old Country Rd",
    "sg:city":"Hicksville",
    "sg:classifiers":[
        {
            "category":"Shopping",
            "subcategory":"Beauty & Cosmetics",
            "type":"Retail Goods"
        }
    ],
    "sg:phone":"+1 516 931 1976",
    "sg:postcode":"11801",
    "sg:province":"NY",
    "sg:tags":[
        "supply"
    ],
    "wof:name":"Venus Beauty Supply",
    "wof:placetype":"venue"
},
  "geometry": {"coordinates":[-73.52939499999999,40.761533],"type":"Point"}
}