{
  "type": "Feature",
  "properties": {
    "addr:full":"3021 Quentin Rd Brooklyn NY 11234",
    "addr:housenumber":"3021",
    "addr:postcode":"11234",
    "addr:street":"Quentin Rd",
    "iso:country":"US",
    "sg:address":"3021 Quentin Rd",
    "sg:city":"Brooklyn",
    "sg:classifiers":[
        {
            "category":"Health Services",
            "subcategory":"Chiropractor",
            "type":"Services"
        }
    ],
    "sg:phone":"+1 718 627 1127",
    "sg:postcode":"11234",
    "sg:province":"NY",
    "wof:name":"Esposito Vincent DC",
    "wof:placetype":"venue"
},
  "geometry": {"coordinates":[-73.940804,40.612202],"type":"Point"}
}