{
  "type": "Feature",
  "properties": {
    "iso:country":"US",
    "sg:address":"124 3rd St",
    "sg:city":"Niagara Falls",
    "sg:classifiers":[
        {
            "category":"Organizations",
            "subcategory":"Religious Organization",
            "type":"Services"
        }
    ],
    "sg:phone":"+1 716 284 0833",
    "sg:postcode":"14303",
    "sg:province":"NY",
    "sg:tags":[
        "monastery",
        "convent"
    ],
    "wof:name":"Daughters Of Charity-Saint Vin",
    "wof:placetype":"venue"
},
  "geometry": {"coordinates":[-79.05925000000001,43.083412],"type":"Point"}
}