{
  "type": "Feature",
  "properties": {
    "addr:full":"1435 Upper Front St # 1 Binghamton NY 13901",
    "addr:housenumber":"1435",
    "addr:postcode":"13901",
    "addr:street":"Upper Front St # 1",
    "iso:country":"US",
    "sg:address":"1435 Upper Front St # 1",
    "sg:city":"Binghamton",
    "sg:classifiers":[
        {
            "category":"Manufacturing",
            "subcategory":"Leather Goods",
            "type":"Manufacturing & Wholesale Goods"
        }
    ],
    "sg:phone":"+1 607 724 4630",
    "sg:postcode":"13901",
    "sg:province":"NY",
    "wof:name":"Leather Line",
    "wof:placetype":"venue"
},
  "geometry": {"coordinates":[-75.888901,42.167],"type":"Point"}
}