{
  "type": "Feature",
  "properties": {
    "addr:full":"20 Bassett Ave Brooklyn NY 11234",
    "addr:housenumber":"20",
    "addr:postcode":"11234",
    "addr:street":"Bassett Ave",
    "iso:country":"US",
    "sg:address":"20 Bassett Ave",
    "sg:city":"Brooklyn",
    "sg:classifiers":[
        {
            "category":"Professional",
            "subcategory":"Computer Services",
            "type":"Services"
        }
    ],
    "sg:phone":"+1 718 251 0176",
    "sg:postcode":"11234",
    "sg:province":"NY",
    "sg:tags":[
        "programing",
        "custom"
    ],
    "wof:name":"Metasources Inc",
    "wof:placetype":"venue"
},
  "geometry": {"coordinates":[-73.906246,40.609461],"type":"Point"}
}