{
  "type": "Feature",
  "properties": {
    "iso:country":"US",
    "sg:address":"106 Ridgehaven Dr",
    "sg:city":"Vestal",
    "sg:classifiers":[
        {
            "category":"Autos & Motor Vehicles",
            "subcategory":"Motorcycle Sales",
            "type":"Retail Goods"
        }
    ],
    "sg:phone":"+1   ",
    "sg:postcode":"13850",
    "sg:province":"NY",
    "sg:tags":[
        "dealer"
    ],
    "wof:name":"J & J Cycles Inc",
    "wof:placetype":"venue"
},
  "geometry": {"coordinates":[-76.02112700000001,42.092256],"type":"Point"}
}