{
  "type": "Feature",
  "properties": {
    "iso:country":"US",
    "sg:address":"90 State St",
    "sg:city":"Albany",
    "sg:classifiers":[
        {
            "category":"Shopping",
            "subcategory":"Tobacco",
            "type":"Retail Goods"
        }
    ],
    "sg:phone":"+1 518 463 9838",
    "sg:postcode":"12207",
    "sg:province":"NY",
    "sg:tags":[
        "cigarette",
        "cigar",
        "dealer"
    ],
    "wof:name":"Smokers Paradise Store",
    "wof:placetype":"venue"
},
  "geometry": {"coordinates":[-73.752821,42.649749],"type":"Point"}
}