{
  "type": "Feature",
  "properties": {
    "addr:full":"1214 Ave M Brooklyn NY 11230",
    "addr:housenumber":"1214",
    "addr:postcode":"11230",
    "addr:street":"Ave M",
    "iso:country":"US",
    "sg:address":"1214 Ave M",
    "sg:city":"Brooklyn",
    "sg:classifiers":[
        {
            "category":"Food & Beverages",
            "subcategory":"Bakery",
            "type":"Retail Goods"
        }
    ],
    "sg:phone":"+1 718 376 6116",
    "sg:postcode":"11230",
    "sg:province":"NY",
    "sg:tags":[
        "baker"
    ],
    "wof:name":"Weiss Bakery II",
    "wof:placetype":"venue"
},
  "geometry": {"coordinates":[-73.961973,40.617711],"type":"Point"}
}