{
  "type": "Feature",
  "properties": {
    "addr:full":"122 W 53rd St New York NY 10019",
    "addr:housenumber":"122",
    "addr:postcode":"10019",
    "addr:street":"W 53Rd St",
    "iso:country":"US",
    "sg:address":"122 W 53rd St",
    "sg:city":"New York",
    "sg:classifiers":[
        {
            "category":"Building & Trades",
            "subcategory":"Locksmith",
            "type":"Services"
        }
    ],
    "sg:phone":"+1 212 937 2911",
    "sg:postcode":"10019",
    "sg:province":"NY",
    "sg:tags":[
        "key"
    ],
    "wof:name":"Americano Locksmith",
    "wof:placetype":"venue"
},
  "geometry": {"coordinates":[-73.978996,40.761902],"type":"Point"}
}