{
  "type": "Feature",
  "properties": {
    "iso:country":"US",
    "sg:address":"589 5th Ave",
    "sg:city":"New York",
    "sg:classifiers":[
        {
            "category":"Building & Trades",
            "subcategory":"Construction",
            "type":"Services"
        },
        {
            "category":"Wholesale",
            "subcategory":"Jewelry",
            "type":"Manufacturing & Wholesale Goods"
        }
    ],
    "sg:phone":"+1 212 223 4142",
    "sg:postcode":"10017",
    "sg:province":"NY",
    "sg:tags":[
        "stone",
        "designer"
    ],
    "wof:name":"Donna Vock Designs Inc",
    "wof:placetype":"venue"
},
  "geometry": {"coordinates":[-73.979024,40.756032],"type":"Point"}
}