{
  "type": "Feature",
  "properties": {
    "iso:country":"US",
    "sg:address":"120 E 32 St",
    "sg:city":"New York",
    "sg:classifiers":[
        {
            "category":"Professional",
            "type":"Services"
        }
    ],
    "sg:phone":"+1 212 883 0680",
    "sg:postcode":"10016",
    "sg:province":"NY",
    "wof:name":"Grand Central Neighborhood Svc",
    "wof:placetype":"venue"
},
  "geometry": {"coordinates":[-73.98146199999999,40.745475],"type":"Point"}
}