{
  "type": "Feature",
  "properties": {
    "addr:full":"6013 7th Ave Brooklyn NY 11220",
    "addr:housenumber":"6013",
    "addr:postcode":"11220",
    "addr:street":"7Th Ave",
    "iso:country":"US",
    "sg:address":"6013 7th Ave",
    "sg:city":"Brooklyn",
    "sg:classifiers":[
        {
            "category":"Home & Garden",
            "subcategory":"Building Materials",
            "type":"Retail Goods"
        }
    ],
    "sg:phone":"+1 718 567 2328",
    "sg:postcode":"11220",
    "sg:province":"NY",
    "sg:tags":[
        "lumber"
    ],
    "wof:name":"Super Sun Lumber Inc",
    "wof:placetype":"venue"
},
  "geometry": {"coordinates":[-74.012248,40.636268],"type":"Point"}
}