{
  "type": "Feature",
  "properties": {
    "iso:country":"US",
    "sg:address":"7113 5th Ave",
    "sg:city":"Brooklyn",
    "sg:classifiers":[
        {
            "category":"Personal",
            "type":"Services"
        }
    ],
    "sg:phone":"+1 718 833 7000",
    "sg:postcode":"11209",
    "sg:province":"NY",
    "sg:tags":[
        "consultant",
        "planning",
        "wedding"
    ],
    "wof:name":"Lsw Wedding Planning Inc",
    "wof:placetype":"venue"
},
  "geometry": {"coordinates":[-74.021407,40.63246],"type":"Point"}
}