{
  "type": "Feature",
  "properties": {
    "addr:full":"41 Elizabeth St Fl 1 New York NY 10013",
    "addr:housenumber":"41;1",
    "addr:postcode":"10013",
    "addr:street":"Elizabeth St",
    "iso:country":"US",
    "sg:address":"41 Elizabeth St Fl 1",
    "sg:city":"New York",
    "sg:classifiers":[
        {
            "category":"Health Services",
            "subcategory":"Health Practitioner",
            "type":"Services"
        }
    ],
    "sg:phone":"+1 212 966 3829",
    "sg:postcode":"10013",
    "sg:province":"NY",
    "sg:tags":[
        "nutritionist"
    ],
    "wof:name":"Cheung Clara",
    "wof:placetype":"venue"
},
  "geometry": {"coordinates":[-73.996968,40.717027],"type":"Point"}
}