{
  "type": "Feature",
  "properties": {
    "addr:full":"9818 103rd Ave Ozone Park NY 11417",
    "addr:housenumber":"9818",
    "addr:postcode":"11417",
    "addr:street":"103Rd Ave",
    "iso:country":"US",
    "sg:address":"9818 103rd Ave",
    "sg:city":"Ozone Park",
    "sg:classifiers":[
        {
            "category":"Arena",
            "subcategory":"Sports Club",
            "type":"Entertainment"
        }
    ],
    "sg:phone":"+1 718 805 8200",
    "sg:postcode":"11417",
    "sg:province":"NY",
    "sg:tags":[
        "martial art"
    ],
    "sg:website":"www.traditionalkarateamerica.com",
    "wof:name":"Traditional Karate America",
    "wof:placetype":"venue"
},
  "geometry": {"coordinates":[-73.841662,40.683208],"type":"Point"}
}