{
  "type": "Feature",
  "properties": {
    "addr:full":"1190 Evergreen Ave Bronx NY 10472",
    "addr:housenumber":"1190",
    "addr:postcode":"10472",
    "addr:street":"Evergreen Ave",
    "iso:country":"US",
    "sg:address":"1190 Evergreen Ave",
    "sg:city":"Bronx",
    "sg:classifiers":[
        {
            "category":"Building & Trades",
            "subcategory":"Construction",
            "type":"Services"
        }
    ],
    "sg:phone":"+1 718 328 0210",
    "sg:postcode":"10472",
    "sg:province":"NY",
    "sg:tags":[
        "contractor"
    ],
    "wof:name":"A & R Contract",
    "wof:placetype":"venue"
},
  "geometry": {"coordinates":[-73.88054200000001,40.826009],"type":"Point"}
}