{
  "type": "Feature",
  "properties": {
    "addr:full":"8801 Shore Rd Brooklyn NY 11209",
    "addr:housenumber":"8801",
    "addr:postcode":"11209",
    "addr:street":"Shore Rd",
    "iso:country":"US",
    "sg:address":"8801 Shore Rd",
    "sg:city":"Brooklyn",
    "sg:classifiers":[
        {
            "category":"Health Services",
            "subcategory":"Doctor",
            "type":"Services"
        }
    ],
    "sg:phone":"+1 718 745 8885",
    "sg:postcode":"11209",
    "sg:province":"NY",
    "sg:tags":[
        "physician",
        "surgeon"
    ],
    "wof:name":"Richard D Epstein MD",
    "wof:placetype":"venue"
},
  "geometry": {"coordinates":[-74.040291,40.622546],"type":"Point"}
}