{
  "type": "Feature",
  "properties": {
    "iso:country":"US",
    "sg:address":"539 E 12 St",
    "sg:city":"New York",
    "sg:classifiers":[
        {
            "category":"Home & Garden",
            "subcategory":"Furniture",
            "type":"Retail Goods"
        }
    ],
    "sg:phone":"+1 212 505 5344",
    "sg:postcode":"10009",
    "sg:province":"NY",
    "wof:name":"B 4",
    "wof:placetype":"venue"
},
  "geometry": {"coordinates":[-73.979645,40.728551],"type":"Point"}
}