{
  "type": "Feature",
  "properties": {
    "addr:full":"3207 Horseblock Rd Medford NY 11763",
    "addr:housenumber":"3207",
    "addr:postcode":"11763",
    "addr:street":"Horseblock Rd",
    "iso:country":"US",
    "sg:address":"3207 Horseblock Rd",
    "sg:city":"Medford",
    "sg:classifiers":[
        {
            "category":"Professional",
            "type":"Services"
        }
    ],
    "sg:phone":"+1 631 286 2347",
    "sg:postcode":"11763",
    "sg:province":"NY",
    "sg:tags":[
        "establishment"
    ],
    "wof:name":"Tritec Co",
    "wof:placetype":"venue"
},
  "geometry": {"coordinates":[-72.986598,40.826267],"type":"Point"}
}