{
  "type": "Feature",
  "properties": {
    "addr:full":"643 Park Avenue New York NY 10021",
    "addr:housenumber":"643",
    "addr:postcode":"10021",
    "addr:street":"Park Avenue",
    "iso:country":"US",
    "sg:address":"643 Park Avenue",
    "sg:city":"New York",
    "sg:classifiers":[
        {
            "category":"Museum",
            "type":"Entertainment"
        }
    ],
    "sg:phone":"+1 212 988 2416",
    "sg:postcode":"10021",
    "sg:province":"NY",
    "wof:name":"107th Infantry",
    "wof:placetype":"venue"
},
  "geometry": {"coordinates":[-73.966368,40.767638],"type":"Point"}
}