{
  "type": "Feature",
  "properties": {
    "addr:full":"21 Lydia Ln Garden City NY 11530",
    "addr:housenumber":"21",
    "addr:postcode":"11530",
    "addr:street":"Lydia Ln",
    "iso:country":"US",
    "sg:address":"21 Lydia Ln",
    "sg:city":"Garden City",
    "sg:classifiers":[
        {
            "category":"Shopping",
            "subcategory":"Computers & Home Electronics",
            "type":"Retail Goods"
        }
    ],
    "sg:phone":"+1 516 565 3351",
    "sg:postcode":"11530",
    "sg:province":"NY",
    "sg:tags":[
        "sell",
        "equipment",
        "audio",
        "video",
        "install"
    ],
    "wof:name":"Eti",
    "wof:placetype":"venue"
},
  "geometry": {"coordinates":[-73.65261700000001,40.71458],"type":"Point"}
}