{
  "type": "Feature",
  "properties": {
    "addr:full":"248 Race Rd Greene NY 13778",
    "addr:housenumber":"248",
    "addr:postcode":"13778",
    "addr:street":"Race Rd",
    "iso:country":"US",
    "sg:address":"248 Race Rd",
    "sg:city":"Greene",
    "sg:classifiers":[
        {
            "category":"Autos & Motor Vehicles",
            "subcategory":"Automobile Sales",
            "type":"Retail Goods"
        }
    ],
    "sg:phone":"+1   ",
    "sg:postcode":"13778",
    "sg:province":"NY",
    "sg:tags":[
        "hardware",
        "repair"
    ],
    "wof:name":"Hallenbeck Sales Co",
    "wof:placetype":"venue"
},
  "geometry": {"coordinates":[-75.754339,42.379512],"type":"Point"}
}