{
  "type": "Feature",
  "properties": {
    "iso:country":"US",
    "sg:address":"1531 Watson Ave",
    "sg:city":"Bronx",
    "sg:classifiers":[
        {
            "category":"Personal",
            "subcategory":"Beauty Salon",
            "type":"Services"
        }
    ],
    "sg:phone":"+1 718 860 5930",
    "sg:postcode":"10472",
    "sg:province":"NY",
    "wof:name":"Hair Braiding",
    "wof:placetype":"venue"
},
  "geometry": {"coordinates":[-73.878055,40.826157],"type":"Point"}
}