{
  "type": "Feature",
  "properties": {
    "addr:full":"684 Park Avenue New York NY 10021",
    "addr:housenumber":"684",
    "addr:postcode":"10021",
    "addr:street":"Park Avenue",
    "iso:country":"US",
    "sg:address":"684 Park Avenue",
    "sg:city":"New York",
    "sg:classifiers":[
        {
            "category":"Education",
            "subcategory":"Special Training",
            "type":"Public Place"
        }
    ],
    "sg:phone":"+1 212 628 0420",
    "sg:postcode":"10021",
    "sg:province":"NY",
    "sg:tags":[
        "school",
        "language"
    ],
    "wof:name":"Queen Sophia Spanish Institu",
    "wof:placetype":"venue"
},
  "geometry": {"coordinates":[-73.96570199999999,40.768717],"type":"Point"}
}