{
  "type": "Feature",
  "properties": {
    "addr:full":"194 Joralemon St Brooklyn NY 11201",
    "addr:housenumber":"194",
    "addr:postcode":"11201",
    "addr:street":"Joralemon St",
    "iso:country":"US",
    "sg:address":"194 Joralemon St",
    "sg:city":"Brooklyn",
    "sg:classifiers":[
        {
            "category":"Utilities",
            "subcategory":"Mobile Phone",
            "type":"Services"
        }
    ],
    "sg:phone":"+1 718 403 5340",
    "sg:postcode":"11201",
    "sg:province":"NY",
    "sg:tags":[
        "telephone",
        "cellular"
    ],
    "sg:website":"www.t-mobile.com",
    "wof:name":"T-Mobile USA",
    "wof:placetype":"venue"
},
  "geometry": {"coordinates":[-73.992228,40.692703],"type":"Point"}
}