{
  "type": "Feature",
  "properties": {
    "addr:full":"19 Squadron Blvd New City NY 10956",
    "addr:housenumber":"19",
    "addr:postcode":"10956",
    "addr:street":"Squadron Blvd",
    "iso:country":"US",
    "sg:address":"19 Squadron Blvd",
    "sg:city":"New City",
    "sg:classifiers":[
        {
            "category":"Wholesale",
            "subcategory":"Chemicals & Plastics",
            "type":"Manufacturing & Wholesale Goods"
        }
    ],
    "sg:phone":"+1 845 634 2400",
    "sg:postcode":"10956",
    "sg:province":"NY",
    "sg:website":"www.amereq.com",
    "wof:name":"Amereq Inc",
    "wof:placetype":"venue"
},
  "geometry": {"coordinates":[-73.982884,41.15734],"type":"Point"}
}