{
  "type": "Feature",
  "properties": {
    "addr:full":"557 Atlantic Ave Oceanside NY 11572",
    "addr:housenumber":"557",
    "addr:postcode":"11572",
    "addr:street":"Atlantic Ave",
    "iso:country":"US",
    "sg:address":"557 Atlantic Ave",
    "sg:city":"Oceanside",
    "sg:classifiers":[
        {
            "category":"Restaurant",
            "type":"Food & Drink"
        }
    ],
    "sg:menulink":"http://www.allmenus.com/ny/oceanside/210560-kfc---kentucky-fried-chicken/menu/",
    "sg:phone":"+1 516 678 8307",
    "sg:postcode":"11572",
    "sg:province":"NY",
    "sg:tags":[
        "american",
        "chicken"
    ],
    "wof:name":"KFC - Kentucky Fried Chicken",
    "wof:placetype":"venue"
},
  "geometry": {"coordinates":[-73.65683300000001,40.640813],"type":"Point"}
}