{
  "type": "Feature",
  "properties": {
    "addr:full":"16 South Broadway Woodside NY 11377",
    "addr:housenumber":"16",
    "addr:postcode":"11377",
    "addr:street":"South Broadway",
    "iso:country":"US",
    "sg:address":"16 South Broadway",
    "sg:city":"Woodside",
    "sg:classifiers":[
        {
            "category":"Restaurant",
            "type":"Food & Drink"
        }
    ],
    "sg:phone":"+1 201 444 7887",
    "sg:postcode":"11377",
    "sg:province":"NY",
    "sg:tags":[
        "italian"
    ],
    "sg:website":"www.nataliescafe.com/",
    "wof:name":"Natalie's Cafe",
    "wof:placetype":"venue"
},
  "geometry": {"coordinates":[-73.905929,40.752846],"type":"Point"}
}