{
  "type": "Feature",
  "properties": {
    "addr:full":"1985 Webster Ave Bronx NY 10457",
    "addr:housenumber":"1985",
    "addr:postcode":"10457",
    "addr:street":"Webster Ave",
    "iso:country":"US",
    "sg:address":"1985 Webster Ave",
    "sg:city":"Bronx",
    "sg:classifiers":[
        {
            "category":"Building & Trades",
            "subcategory":"Construction",
            "type":"Services"
        }
    ],
    "sg:phone":"+1 718 294 7801",
    "sg:postcode":"10457",
    "sg:province":"NY",
    "sg:tags":[
        "hanging",
        "contractor"
    ],
    "wof:name":"Muhamdou Fsiru Mest Afrcan Art",
    "wof:placetype":"venue"
},
  "geometry": {"coordinates":[-73.899866,40.84957],"type":"Point"}
}