{
  "type": "Feature",
  "properties": {
    "addr:full":"350 Broadway Kingston NY 12401",
    "addr:housenumber":"350",
    "addr:postcode":"12401",
    "addr:street":"Broadway",
    "iso:country":"US",
    "sg:address":"350 Broadway",
    "sg:city":"Kingston",
    "sg:classifiers":[
        {
            "category":"Health Services",
            "subcategory":"Hospital",
            "type":"Services"
        }
    ],
    "sg:phone":"+1 845 338 0833",
    "sg:postcode":"12401",
    "sg:province":"NY",
    "wof:name":"Kingston Hospital Happy Apple",
    "wof:placetype":"venue"
},
  "geometry": {"coordinates":[-73.993274,41.925937],"type":"Point"}
}