{
  "type": "Feature",
  "properties": {
    "iso:country":"US",
    "sg:address":"5687 Main St",
    "sg:city":"Williamsville",
    "sg:classifiers":[
        {
            "category":"Banks & Credit Unions",
            "subcategory":"Bank",
            "type":"Services"
        }
    ],
    "sg:phone":"+1 716 626 9995",
    "sg:postcode":"14221",
    "sg:province":"NY",
    "sg:tags":[
        "financing"
    ],
    "wof:name":"Financial Solutions LLC",
    "wof:placetype":"venue"
},
  "geometry": {"coordinates":[-78.740404,42.963469],"type":"Point"}
}