{
  "type": "Feature",
  "properties": {
    "iso:country":"US",
    "sg:address":"229 Washington St",
    "sg:city":"Saratoga Springs",
    "sg:classifiers":[
        {
            "category":"Health Services",
            "subcategory":"Health Practitioner",
            "type":"Services"
        }
    ],
    "sg:phone":"+1 518 580 1300",
    "sg:postcode":"12866",
    "sg:province":"NY",
    "sg:tags":[
        "psychologist"
    ],
    "wof:name":"Cynthia A Guile",
    "wof:placetype":"venue"
},
  "geometry": {"coordinates":[-73.79815499999999,43.080048],"type":"Point"}
}