{
  "type": "Feature",
  "properties": {
    "addr:full":"806 Madison Ave New York NY 10021",
    "addr:housenumber":"806",
    "addr:postcode":"10021",
    "addr:street":"Madison Ave",
    "iso:country":"US",
    "sg:address":"806 Madison Ave",
    "sg:city":"New York",
    "sg:classifiers":[
        {
            "category":"Shopping",
            "subcategory":"Shoes",
            "type":"Retail Goods"
        }
    ],
    "sg:phone":"+1 212 650 0455",
    "sg:postcode":"10021",
    "sg:province":"NY",
    "sg:tags":[
        "store"
    ],
    "sg:website":"www.giuseppe-zanotti-design.com",
    "wof:name":"Giuseppe Zanotti Design",
    "wof:placetype":"venue"
},
  "geometry": {"coordinates":[-73.967102,40.769299],"type":"Point"}
}