{
  "type": "Feature",
  "properties": {
    "addr:full":"3011 Paulding Ave Bronx NY 10469",
    "addr:housenumber":"3011",
    "addr:postcode":"10469",
    "addr:street":"Paulding Ave",
    "iso:country":"US",
    "sg:address":"3011 Paulding Ave",
    "sg:city":"Bronx",
    "sg:classifiers":[
        {
            "category":"Personal",
            "subcategory":"Beauty Salon",
            "type":"Services"
        }
    ],
    "sg:phone":"+1 718 654 1136",
    "sg:postcode":"10469",
    "sg:province":"NY",
    "sg:tags":[
        "consultant",
        "health"
    ],
    "wof:name":"Anita Crosby",
    "wof:placetype":"venue"
},
  "geometry": {"coordinates":[-73.858565,40.871197],"type":"Point"}
}