{
  "type": "Feature",
  "properties": {
    "addr:full":"2480 Beltagh Ave Bellmore NY 11710",
    "addr:postcode":"2480;11710",
    "addr:street":"Beltagh Ave",
    "iso:country":"US",
    "sg:address":"2480 Beltagh Ave",
    "sg:city":"Bellmore",
    "sg:classifiers":[
        {
            "category":"Local Transit",
            "type":"Transportation"
        }
    ],
    "sg:phone":"+1   ",
    "sg:postcode":"11710",
    "sg:province":"NY",
    "sg:tags":[
        "passenger"
    ],
    "wof:name":"Atlas Limousine Svce",
    "wof:placetype":"venue"
},
  "geometry": {"coordinates":[-73.537508,40.676027],"type":"Point"}
}