{
  "type": "Feature",
  "properties": {
    "addr:full":"162 W 56th St New York NY 10019",
    "addr:housenumber":"162",
    "addr:postcode":"10019",
    "addr:street":"W 56Th St",
    "iso:country":"US",
    "sg:address":"162 W 56th St",
    "sg:city":"New York",
    "sg:classifiers":[
        {
            "category":"Health Services",
            "subcategory":"Chiropractor",
            "type":"Services"
        }
    ],
    "sg:phone":"+1 212 247 3310",
    "sg:postcode":"10019",
    "sg:province":"NY",
    "sg:website":"www.carnegiechiropractic.com/",
    "wof:name":"Gordon Jason R",
    "wof:placetype":"venue"
},
  "geometry": {"coordinates":[-73.97989699999999,40.7645],"type":"Point"}
}