{
  "type": "Feature",
  "properties": {
    "addr:full":"125 Sunrise Hwy Lindenhurst NY 11757",
    "addr:housenumber":"125",
    "addr:postcode":"11757",
    "addr:street":"Sunrise Hwy",
    "iso:country":"US",
    "sg:address":"125 Sunrise Hwy",
    "sg:city":"Lindenhurst",
    "sg:classifiers":[
        {
            "category":"Professional",
            "subcategory":"Detective & Security Services",
            "type":"Services"
        }
    ],
    "sg:phone":"+1 631 884 4130",
    "sg:postcode":"11757",
    "sg:province":"NY",
    "sg:tags":[
        "investigator"
    ],
    "wof:name":"Investigative Professional Inc",
    "wof:placetype":"venue"
},
  "geometry": {"coordinates":[-73.37681600000001,40.702176],"type":"Point"}
}