{
  "type": "Feature",
  "properties": {
    "addr:full":"90 S 2nd Street Brooklyn NY 11211",
    "addr:housenumber":"90",
    "addr:postcode":"11211",
    "addr:street":"S 2Nd Street",
    "iso:country":"US",
    "sg:address":"90 S 2nd Street",
    "sg:city":"Brooklyn",
    "sg:classifiers":[
        {
            "category":"Restaurant",
            "type":"Food & Drink"
        },
        {
            "category":"Professional",
            "subcategory":"Lawyer & Legal Services",
            "type":"Services"
        }
    ],
    "sg:phone":"+1 718 387 0600",
    "sg:postcode":"11211",
    "sg:province":"NY",
    "sg:tags":[
        "seafood"
    ],
    "wof:name":"Imperial Sea Food Corporation",
    "wof:placetype":"venue"
},
  "geometry": {"coordinates":[-73.964544,40.714011],"type":"Point"}
}