{
  "type": "Feature",
  "properties": {
    "addr:full":"1985 University Ave Bronx NY 10453",
    "addr:housenumber":"1985",
    "addr:postcode":"10453",
    "addr:street":"University Ave",
    "iso:country":"US",
    "sg:address":"1985 University Ave",
    "sg:city":"Bronx",
    "sg:classifiers":[
        {
            "category":"Real Estate",
            "subcategory":"Real Estate Operator",
            "type":"Services"
        }
    ],
    "sg:phone":"+1 718 583 8283",
    "sg:postcode":"10453",
    "sg:province":"NY",
    "sg:tags":[
        "mall",
        "shopping",
        "center"
    ],
    "wof:name":"One Stop African Market",
    "wof:placetype":"venue"
},
  "geometry": {"coordinates":[-73.91413799999999,40.851314],"type":"Point"}
}