{
  "type": "Feature",
  "properties": {
    "addr:full":"35 Dickinson Ave East Northport NY 11731",
    "addr:housenumber":"35",
    "addr:postcode":"11731",
    "addr:street":"Dickinson Ave",
    "iso:country":"US",
    "sg:address":"35 Dickinson Ave",
    "sg:city":"East Northport",
    "sg:classifiers":[
        {
            "category":"Home & Garden",
            "subcategory":"Household Appliances",
            "type":"Retail Goods"
        }
    ],
    "sg:phone":"+1 631 757 5995",
    "sg:postcode":"11731",
    "sg:province":"NY",
    "wof:name":"Chuck's Refrigeration & Appl",
    "wof:placetype":"venue"
},
  "geometry": {"coordinates":[-73.33085,40.887495],"type":"Point"}
}