{
  "type": "Feature",
  "properties": {
    "addr:full":"16 Main St Hilton NY 14468",
    "addr:housenumber":"16",
    "addr:postcode":"14468",
    "addr:street":"Main St",
    "iso:country":"US",
    "sg:address":"16 Main St",
    "sg:city":"Hilton",
    "sg:classifiers":[
        {
            "category":"Health Services",
            "subcategory":"Chiropractor",
            "type":"Services"
        }
    ],
    "sg:phone":"+1   ",
    "sg:postcode":"14468",
    "sg:province":"NY",
    "wof:name":"Hilton Chiropractic",
    "wof:placetype":"venue"
},
  "geometry": {"coordinates":[-77.792669,43.288168],"type":"Point"}
}