{
  "type": "Feature",
  "properties": {
    "iso:country":"US",
    "sg:address":"897 Upper Front St",
    "sg:city":"Binghamton",
    "sg:classifiers":[
        {
            "category":"Government",
            "subcategory":"Police Station",
            "type":"Public Place"
        }
    ],
    "sg:phone":"+1 607 778 8726",
    "sg:postcode":"13905",
    "sg:province":"NY",
    "sg:tags":[
        "sheriff"
    ],
    "wof:name":"Sheriff Dept-Crime Prevention",
    "wof:placetype":"venue"
},
  "geometry": {"coordinates":[-75.905638,42.132743],"type":"Point"}
}