{
  "type": "Feature",
  "properties": {
    "addr:full":"4 Brighton Pl Huntington NY 11743",
    "addr:housenumber":"4",
    "addr:postcode":"11743",
    "addr:street":"Brighton Pl",
    "iso:country":"US",
    "sg:address":"4 Brighton Pl",
    "sg:city":"Huntington",
    "sg:classifiers":[
        {
            "category":"Sports & Exercise",
            "subcategory":"Gym",
            "type":"Entertainment"
        }
    ],
    "sg:phone":"+1   ",
    "sg:postcode":"11743",
    "sg:province":"NY",
    "sg:tags":[
        "fitness",
        "physical",
        "facility"
    ],
    "wof:name":"Best Bodies",
    "wof:placetype":"venue"
},
  "geometry": {"coordinates":[-73.409758,40.863998],"type":"Point"}
}