{
  "type": "Feature",
  "properties": {
    "iso:country":"US",
    "sg:address":"1551 Randolph Rd",
    "sg:city":"Schenectady",
    "sg:classifiers":[
        {
            "category":"Building & Trades",
            "subcategory":"Landscaping Services",
            "type":"Services"
        }
    ],
    "sg:phone":"+1 518 393 1404",
    "sg:postcode":"12308",
    "sg:province":"NY",
    "sg:tags":[
        "landscape"
    ],
    "wof:name":"John F Macbeth",
    "wof:placetype":"venue"
},
  "geometry": {"coordinates":[-73.91981699999999,42.821784],"type":"Point"}
}