{
  "type": "Feature",
  "properties": {
    "iso:country":"US",
    "sg:address":"77 Greenkill Ave",
    "sg:city":"Kingston",
    "sg:classifiers":[
        {
            "category":"Building & Trades",
            "subcategory":"Construction",
            "type":"Services"
        }
    ],
    "sg:phone":"+1 845 339 1600",
    "sg:postcode":"12401",
    "sg:province":"NY",
    "sg:tags":[
        "general",
        "contractor"
    ],
    "wof:name":"Rahm Construction Corp",
    "wof:placetype":"venue"
},
  "geometry": {"coordinates":[-74.005415,41.927251],"type":"Point"}
}