{
  "type": "Feature",
  "properties": {
    "addr:full":"11 Lone Oak Cir Penfield NY 14526",
    "addr:housenumber":"11",
    "addr:postcode":"14526",
    "addr:street":"Lone Oak Cir",
    "iso:country":"US",
    "sg:address":"11 Lone Oak Cir",
    "sg:city":"Penfield",
    "sg:classifiers":[
        {
            "category":"Building & Trades",
            "subcategory":"Landscaping Services",
            "type":"Services"
        }
    ],
    "sg:phone":"+1 585 248 8816",
    "sg:postcode":"14526",
    "sg:province":"NY",
    "sg:tags":[
        "landscape",
        "contractor"
    ],
    "wof:name":"Blades Lawn Svc",
    "wof:placetype":"venue"
},
  "geometry": {"coordinates":[-77.47328899999999,43.158684],"type":"Point"}
}