{
  "type": "Feature",
  "properties": {
    "addr:full":"10819 72nd Ave Forest Hills NY 11375",
    "addr:housenumber":"10819",
    "addr:postcode":"11375",
    "addr:street":"72Nd Ave",
    "iso:country":"US",
    "sg:address":"10819 72nd Ave",
    "sg:city":"Forest Hills",
    "sg:classifiers":[
        {
            "category":"Health Services",
            "subcategory":"Chiropractor",
            "type":"Services"
        }
    ],
    "sg:phone":"+1 888 324 5700",
    "sg:postcode":"11375",
    "sg:province":"NY",
    "wof:name":"Konner Greg chrprctr",
    "wof:placetype":"venue"
},
  "geometry": {"coordinates":[-73.842641,40.719597],"type":"Point"}
}