{
  "type": "Feature",
  "properties": {
    "iso:country":"US",
    "sg:address":"2271 State Hwy 13",
    "sg:city":"Cortland",
    "sg:classifiers":[
        {
            "category":"Farming",
            "subcategory":"Dairy Farm",
            "type":"Manufacturing & Wholesale Goods"
        }
    ],
    "sg:phone":"+1 607 756 6564",
    "sg:postcode":"13045",
    "sg:province":"NY",
    "wof:name":"Forbes Farms",
    "wof:placetype":"venue"
},
  "geometry": {"coordinates":[-76.140134,42.639267],"type":"Point"}
}