{
  "type": "Feature",
  "properties": {
    "addr:full":"479 Sunrise Mall Massapequa NY 11758",
    "addr:housenumber":"479",
    "addr:postcode":"11758",
    "addr:street":"Sunrise Mall",
    "iso:country":"US",
    "sg:address":"479 Sunrise Mall",
    "sg:city":"Massapequa",
    "sg:classifiers":[
        {
            "category":"Shopping",
            "subcategory":"Gifts & Souvenirs",
            "type":"Retail Goods"
        }
    ],
    "sg:phone":"+1 516 541 4055",
    "sg:postcode":"11758",
    "sg:province":"NY",
    "sg:tags":[
        "shop"
    ],
    "wof:name":"Disney Store",
    "wof:placetype":"venue"
},
  "geometry": {"coordinates":[-73.436239,40.682423],"type":"Point"}
}