{
  "type": "Feature",
  "properties": {
    "iso:country":"US",
    "sg:address":"377 Huguenot St",
    "sg:city":"New Rochelle",
    "sg:classifiers":[
        {
            "category":"Building & Trades",
            "subcategory":"Construction",
            "type":"Services"
        }
    ],
    "sg:phone":"+1 914 636 0848",
    "sg:postcode":"10801",
    "sg:province":"NY",
    "sg:tags":[
        "house"
    ],
    "wof:name":"De Vivo Paolo Inc",
    "wof:placetype":"venue"
},
  "geometry": {"coordinates":[-73.78659500000001,40.906086],"type":"Point"}
}