{
  "type": "Feature",
  "properties": {
    "addr:full":"8830 51st Avenue Elmhurst NY 11373",
    "addr:housenumber":"8830",
    "addr:postcode":"11373",
    "addr:street":"51St Avenue",
    "iso:country":"US",
    "sg:address":"8830 51st Avenue",
    "sg:city":"Elmhurst",
    "sg:classifiers":[
        {
            "category":"Building & Trades",
            "subcategory":"Construction",
            "type":"Services"
        }
    ],
    "sg:phone":"+1 718 271 0170",
    "sg:postcode":"11373",
    "sg:province":"NY",
    "sg:tags":[
        "contractor"
    ],
    "wof:name":"Armco Mngmnt & Gen Contrctng Company",
    "wof:placetype":"venue"
},
  "geometry": {"coordinates":[-73.875454,40.739151],"type":"Point"}
}