{
  "type": "Feature",
  "properties": {
    "addr:full":"1715 Saint Johns Pl Brooklyn NY 11233",
    "addr:housenumber":"1715",
    "addr:postcode":"11233",
    "addr:street":"Saint Johns Pl",
    "iso:country":"US",
    "sg:address":"1715 Saint Johns Pl",
    "sg:city":"Brooklyn",
    "sg:classifiers":[
        {
            "category":"Personal",
            "subcategory":"Barber",
            "type":"Services"
        }
    ],
    "sg:phone":"+1 718 513 4363",
    "sg:postcode":"11233",
    "sg:province":"NY",
    "wof:name":"Elite Barbarshop",
    "wof:placetype":"venue"
},
  "geometry": {"coordinates":[-73.91999800000001,40.670101],"type":"Point"}
}