{
  "type": "Feature",
  "properties": {
    "iso:country":"US",
    "sg:address":"110 Rensselaer Ave",
    "sg:city":"Cohoes",
    "sg:classifiers":[
        {
            "category":"Retail",
            "subcategory":"Repair Shop",
            "type":"Services"
        }
    ],
    "sg:phone":"+1 518 237 6416",
    "sg:postcode":"12047",
    "sg:province":"NY",
    "sg:tags":[
        "sharpening"
    ],
    "wof:name":"Hudson River Grinding",
    "wof:placetype":"venue"
},
  "geometry": {"coordinates":[-73.69006899999999,42.771724],"type":"Point"}
}