{
  "type": "Feature",
  "properties": {
    "iso:country":"US",
    "sg:address":"433 Amsterdam Ave",
    "sg:city":"New York",
    "sg:classifiers":[
        {
            "category":"Restaurant",
            "type":"Food & Drink"
        }
    ],
    "sg:menulink":"http://www.allmenus.com/ny/new-york/2422-haru-amsterdam-ave/menu/",
    "sg:phone":"+1 212 579 5655",
    "sg:postcode":"10024",
    "sg:province":"NY",
    "sg:tags":[
        "japanese",
        "american",
        "sushi",
        "seafood",
        "asian"
    ],
    "wof:name":"Haru Amsterdam Ave.",
    "wof:placetype":"venue"
},
  "geometry": {"coordinates":[-73.97751,40.784267],"type":"Point"}
}