{
  "type": "Feature",
  "properties": {
    "addr:full":"329 Wilmore Pl Syracuse NY 13208",
    "addr:housenumber":"329",
    "addr:postcode":"13208",
    "addr:street":"Wilmore Pl",
    "iso:country":"US",
    "sg:address":"329 Wilmore Pl",
    "sg:city":"Syracuse",
    "sg:classifiers":[
        {
            "category":"Place Of Worship",
            "type":"Public Place"
        }
    ],
    "sg:phone":"+1 315 454 4223",
    "sg:postcode":"13208",
    "sg:province":"NY",
    "sg:tags":[
        "church"
    ],
    "wof:name":"Grant Donald",
    "wof:placetype":"venue"
},
  "geometry": {"coordinates":[-76.13550600000001,43.083006],"type":"Point"}
}