{
  "type": "Feature",
  "properties": {
    "iso:country":"US",
    "sg:address":"877 Madison Ave",
    "sg:city":"Albany",
    "sg:classifiers":[
        {
            "category":"Organizations",
            "subcategory":"Non-profit Organization",
            "type":"Services"
        }
    ],
    "sg:phone":"+1 518 482 8856",
    "sg:postcode":"12208",
    "sg:province":"NY",
    "sg:website":"www.jfsneny.org",
    "wof:name":"Jewish Family Svc",
    "wof:placetype":"venue"
},
  "geometry": {"coordinates":[-73.78323399999999,42.661245],"type":"Point"}
}