{
  "type": "Feature",
  "properties": {
    "addr:full":"272 Geneva St Farmingdale NY 11706",
    "addr:housenumber":"272",
    "addr:postcode":"11706",
    "addr:street":"Geneva St",
    "iso:country":"US",
    "sg:address":"272 Geneva St",
    "sg:city":"Farmingdale",
    "sg:classifiers":[
        {
            "category":"Building & Trades",
            "subcategory":"Construction",
            "type":"Services"
        }
    ],
    "sg:phone":"+1 631 831 3070",
    "sg:postcode":"11706",
    "sg:province":"NY",
    "sg:tags":[
        "residential"
    ],
    "wof:name":"Global Hardwood Importers LLC",
    "wof:placetype":"venue"
},
  "geometry": {"coordinates":[-73.229263,40.747899],"type":"Point"}
}