{
  "type": "Feature",
  "properties": {
    "iso:country":"US",
    "sg:address":"1466 49th Street",
    "sg:city":"Brooklyn",
    "sg:classifiers":[
        {
            "category":"Health Services",
            "subcategory":"Doctor",
            "type":"Services"
        }
    ],
    "sg:phone":"+1 718 435 7200",
    "sg:postcode":"11219",
    "sg:province":"NY",
    "wof:name":"Sherman-Abrams Laboratory",
    "wof:placetype":"venue"
},
  "geometry": {"coordinates":[-73.988575,40.632816],"type":"Point"}
}