{
  "type": "Feature",
  "properties": {
    "addr:full":"1305 State Hwy 143 Coeymans Hollow NY 12046",
    "addr:housenumber":"1305",
    "addr:postcode":"12046",
    "addr:street":"State Hwy 143 Coeymans Hollow",
    "iso:country":"US",
    "sg:address":"1305 State Hwy 143",
    "sg:city":"Coeymans Hollow",
    "sg:classifiers":[
        {
            "category":"Government",
            "subcategory":"Office",
            "type":"Public Place"
        }
    ],
    "sg:phone":"+1 518 756 2251",
    "sg:postcode":"12046",
    "sg:province":"NY",
    "sg:tags":[
        "executive",
        "construction"
    ],
    "wof:name":"Coeymans Highway Dept",
    "wof:placetype":"venue"
},
  "geometry": {"coordinates":[-73.905998,42.475491],"type":"Point"}
}