{
  "type": "Feature",
  "properties": {
    "addr:full":"31 Hatfield Ln Goshen NY 10924",
    "addr:housenumber":"31",
    "addr:postcode":"10924",
    "addr:street":"Hatfield Ln",
    "iso:country":"US",
    "sg:address":"31 Hatfield Ln",
    "sg:city":"Goshen",
    "sg:classifiers":[
        {
            "category":"Manufacturing",
            "subcategory":"Tools & Machinery",
            "type":"Manufacturing & Wholesale Goods"
        }
    ],
    "sg:phone":"+1 845 294 3200",
    "sg:postcode":"10924",
    "sg:province":"NY",
    "sg:tags":[
        "machine",
        "manufacturer"
    ],
    "sg:website":"http://www.blaser.com",
    "wof:name":"Swisslube Div",
    "wof:placetype":"venue"
},
  "geometry": {"coordinates":[-74.341401,41.39543],"type":"Point"}
}