{
  "type": "Feature",
  "properties": {
    "iso:country":"US",
    "sg:address":"30 Macghee Rd",
    "sg:city":"Poughkeepsie",
    "sg:classifiers":[
        {
            "category":"Professional",
            "subcategory":"Lawyer & Legal Services",
            "type":"Services"
        }
    ],
    "sg:phone":"+1 845 462 6133",
    "sg:postcode":"12603",
    "sg:province":"NY",
    "sg:tags":[
        "attorney"
    ],
    "wof:name":"Stephen Buchalter",
    "wof:placetype":"venue"
},
  "geometry": {"coordinates":[-73.865415,41.644338],"type":"Point"}
}