{
  "type": "Feature",
  "properties": {
    "addr:full":"70 Goshen Trl Goshen NY 10924",
    "addr:housenumber":"70",
    "addr:postcode":"10924",
    "addr:street":"Goshen Trl",
    "iso:country":"US",
    "sg:address":"70 Goshen Trl",
    "sg:city":"Goshen",
    "sg:classifiers":[
        {
            "category":"Health Services",
            "subcategory":"Doctor",
            "type":"Services"
        }
    ],
    "sg:phone":"+1 845 294 7700",
    "sg:postcode":"10924",
    "sg:province":"NY",
    "sg:tags":[
        "medical"
    ],
    "wof:name":"Hudson Heart Associates PC",
    "wof:placetype":"venue"
},
  "geometry": {"coordinates":[-74.334565,41.3648],"type":"Point"}
}