{
  "type": "Feature",
  "properties": {
    "addr:full":"240 N French Rd Buffalo NY 14228",
    "addr:housenumber":"240",
    "addr:postcode":"14228",
    "addr:street":"N French Rd",
    "iso:country":"US",
    "sg:address":"240 N French Rd",
    "sg:city":"Buffalo",
    "sg:classifiers":[
        {
            "category":"Building & Trades",
            "subcategory":"Cleaning & Sanitation",
            "type":"Services"
        }
    ],
    "sg:phone":"+1 716 691 4302",
    "sg:postcode":"14228",
    "sg:province":"NY",
    "sg:tags":[
        "maintenance"
    ],
    "wof:name":"Fr Services",
    "wof:placetype":"venue"
},
  "geometry": {"coordinates":[-78.821299,43.034411],"type":"Point"}
}