{
  "type": "Feature",
  "properties": {
    "addr:full":"139 Lyell Ave Unit B Rochester NY 14608",
    "addr:housenumber":"139",
    "addr:postcode":"14608",
    "addr:street":"Lyell Ave Unit B",
    "iso:country":"US",
    "sg:address":"139 Lyell Ave Unit B",
    "sg:city":"Rochester",
    "sg:classifiers":[
        {
            "category":"Autos & Motor Vehicles",
            "subcategory":"Automobile Sales",
            "type":"Retail Goods"
        },
        {
            "category":"Personal",
            "type":"Services"
        }
    ],
    "sg:phone":"+1 585 546 8210",
    "sg:postcode":"14608",
    "sg:province":"NY",
    "sg:tags":[
        "dealers-used",
        "car",
        "cars-wholesale",
        "used",
        "towing"
    ],
    "wof:name":"Advance Auto",
    "wof:placetype":"venue"
},
  "geometry": {"coordinates":[-77.627724,43.164631],"type":"Point"}
}