{
  "type": "Feature",
  "properties": {
    "addr:full":"503 Grasslands Rd Ste 105 Valhalla NY 10595",
    "addr:housenumber":"503",
    "addr:postcode":"10595",
    "addr:street":"Grasslands Rd Ste 105",
    "iso:country":"US",
    "sg:address":"503 Grasslands Rd Ste 105",
    "sg:city":"Valhalla",
    "sg:classifiers":[
        {
            "category":"Health Services",
            "subcategory":"Health Practitioner",
            "type":"Services"
        }
    ],
    "sg:phone":"+1 914 345 9133",
    "sg:postcode":"10595",
    "sg:province":"NY",
    "sg:tags":[
        "occupational",
        "therapist"
    ],
    "wof:name":"Hands On Rehab",
    "wof:placetype":"venue"
},
  "geometry": {"coordinates":[-73.79992300000001,41.072725],"type":"Point"}
}