{
  "type": "Feature",
  "properties": {
    "iso:country":"US",
    "sg:address":"3 Main St",
    "sg:city":"Cherry Valley",
    "sg:classifiers":[
        {
            "category":"Organizations",
            "subcategory":"Religious Organization",
            "type":"Services"
        }
    ],
    "sg:phone":"+1 607 264 3306",
    "sg:postcode":"13320",
    "sg:province":"NY",
    "wof:name":"Cherry Valley Assembly of God",
    "wof:placetype":"venue"
},
  "geometry": {"coordinates":[-74.754171,42.797035],"type":"Point"}
}