{
  "type": "Feature",
  "properties": {
    "addr:full":"346 Doane Ave Staten Island NY 10308",
    "addr:housenumber":"346",
    "addr:postcode":"10308",
    "addr:street":"Doane Ave",
    "iso:country":"US",
    "sg:address":"346 Doane Ave",
    "sg:city":"Staten Island",
    "sg:classifiers":[
        {
            "category":"Wholesale",
            "subcategory":"Apparel",
            "type":"Manufacturing & Wholesale Goods"
        }
    ],
    "sg:phone":"+1 718 816 1347",
    "sg:postcode":"10308",
    "sg:province":"NY",
    "sg:tags":[
        "lingerie"
    ],
    "wof:name":"NY Intimates Inc",
    "wof:placetype":"venue"
},
  "geometry": {"coordinates":[-74.156356,40.55739],"type":"Point"}
}