{
  "type": "Feature",
  "properties": {
    "addr:full":"1 Jefferson Ave Rockville Centre NY 11570",
    "addr:housenumber":"1",
    "addr:postcode":"11570",
    "addr:street":"Jefferson Ave",
    "iso:country":"US",
    "sg:address":"1 Jefferson Ave",
    "sg:city":"Rockville Centre",
    "sg:classifiers":[
        {
            "category":"Real Estate",
            "subcategory":"Real Estate Services",
            "type":"Services"
        }
    ],
    "sg:phone":"+1 800 273 7803",
    "sg:postcode":"11570",
    "sg:province":"NY",
    "wof:name":"Ormond Park Realty Corp",
    "wof:placetype":"venue"
},
  "geometry": {"coordinates":[-73.63217,40.658252],"type":"Point"}
}