{
  "type": "Feature",
  "properties": {
    "iso:country":"US",
    "sg:address":"2402 Hughes Ave",
    "sg:city":"Bronx",
    "sg:classifiers":[
        {
            "category":"Social Services",
            "type":"Services"
        }
    ],
    "sg:phone":"+1 718 364 4788",
    "sg:postcode":"10458",
    "sg:province":"NY",
    "sg:tags":[
        "organization",
        "welfare"
    ],
    "wof:name":"COBO Inc",
    "wof:placetype":"venue"
},
  "geometry": {"coordinates":[-73.886077,40.856016],"type":"Point"}
}