{
  "type": "Feature",
  "properties": {
    "iso:country":"US",
    "sg:address":"208 Main St",
    "sg:city":"Hurleyville",
    "sg:classifiers":[
        {
            "category":"Professional",
            "type":"Services"
        }
    ],
    "sg:phone":"+1 845 436 0261",
    "sg:postcode":"12747",
    "sg:province":"NY",
    "sg:tags":[
        "establishment"
    ],
    "wof:name":"Vivs Place LLC",
    "wof:placetype":"venue"
},
  "geometry": {"coordinates":[-74.67421899999999,41.736035],"type":"Point"}
}