{
  "type": "Feature",
  "properties": {
    "iso:country":"US",
    "sg:address":"90 Eycleshymer Rd",
    "sg:city":"Johnsonville",
    "sg:classifiers":[
        {
            "category":"Manufacturing",
            "subcategory":"Metals",
            "type":"Manufacturing & Wholesale Goods"
        }
    ],
    "sg:phone":"+1 518 663 8032",
    "sg:postcode":"12094",
    "sg:province":"NY",
    "sg:tags":[
        "work",
        "blast",
        "furnace",
        "specialty"
    ],
    "wof:name":"Chardon Machine & Tool, Inc.",
    "wof:placetype":"venue"
},
  "geometry": {"coordinates":[-73.478674,42.836499],"type":"Point"}
}