{
  "type": "Feature",
  "properties": {
    "addr:full":"4768 Broadway Manhattan NY 10034",
    "addr:housenumber":"4768",
    "addr:postcode":"10034",
    "addr:street":"Broadway",
    "iso:country":"US",
    "sg:address":"4768 Broadway",
    "sg:city":"Manhattan",
    "sg:classifiers":[
        {
            "category":"Building & Trades",
            "subcategory":"Locksmith",
            "type":"Services"
        }
    ],
    "sg:phone":"+1 718 887 9026",
    "sg:postcode":"10034",
    "sg:province":"NY",
    "sg:tags":[
        "key"
    ],
    "sg:website":"www.bronxlocksmith.org/",
    "wof:name":"Bronx Locksmith Pros",
    "wof:placetype":"venue"
},
  "geometry": {"coordinates":[-73.92636400000001,40.86546],"type":"Point"}
}