{
  "type": "Feature",
  "properties": {
    "addr:full":"905 Lorimer St Brooklyn NY 11222",
    "addr:housenumber":"905",
    "addr:postcode":"11222",
    "addr:street":"Lorimer St",
    "iso:country":"US",
    "sg:address":"905 Lorimer St",
    "sg:city":"Brooklyn",
    "sg:classifiers":[
        {
            "category":"Restaurant",
            "type":"Food & Drink"
        }
    ],
    "sg:phone":"+1   ",
    "sg:postcode":"11222",
    "sg:province":"NY",
    "sg:tags":[
        "eating"
    ],
    "wof:name":"Manonsignors",
    "wof:placetype":"venue"
},
  "geometry": {"coordinates":[-73.95262700000001,40.725032],"type":"Point"}
}