{
  "type": "Feature",
  "properties": {
    "addr:full":"479 Old Hopewell Rd Hopewell Jct NY 12533",
    "addr:housenumber":"479",
    "addr:postcode":"12533",
    "addr:street":"Old Hopewell Rd",
    "iso:country":"US",
    "sg:address":"479 Old Hopewell Rd",
    "sg:city":"Hopewell Jct",
    "sg:classifiers":[
        {
            "category":"Shopping",
            "subcategory":"Hobbies, Toys, & Games",
            "type":"Retail Goods"
        }
    ],
    "sg:phone":"+1 845 896 5386",
    "sg:postcode":"12533",
    "sg:province":"NY",
    "sg:tags":[
        "product",
        "ceramic"
    ],
    "wof:name":"Pat's Place",
    "wof:placetype":"venue"
},
  "geometry": {"coordinates":[-73.85070399999999,41.573236],"type":"Point"}
}