{
  "type": "Feature",
  "properties": {
    "addr:full":"22 W 19 St New York NY 10011",
    "addr:housenumber":"22",
    "addr:postcode":"10011",
    "addr:street":"W 19 St",
    "iso:country":"US",
    "sg:address":"22 W 19 St",
    "sg:city":"New York",
    "sg:classifiers":[
        {
            "category":"Manufacturing",
            "subcategory":"Printing",
            "type":"Manufacturing & Wholesale Goods"
        }
    ],
    "sg:phone":"+1   ",
    "sg:postcode":"10011",
    "sg:province":"NY",
    "sg:tags":[
        "book"
    ],
    "wof:name":"Carnot USA Books",
    "wof:placetype":"venue"
},
  "geometry": {"coordinates":[-73.99412100000001,40.740094],"type":"Point"}
}