{
  "type": "Feature",
  "properties": {
    "iso:country":"US",
    "sg:address":"26 Saratoga Rd",
    "sg:city":"Schenectady",
    "sg:classifiers":[
        {
            "category":"Retail",
            "subcategory":"Laundry & Dry Cleaning",
            "type":"Services"
        }
    ],
    "sg:phone":"+1 518 399 7809",
    "sg:postcode":"12302",
    "sg:province":"NY",
    "sg:website":"www.kemcleaners.com",
    "wof:name":"Kem Cleaners Inc",
    "wof:placetype":"venue"
},
  "geometry": {"coordinates":[-73.94193799999999,42.851521],"type":"Point"}
}