{
  "type": "Feature",
  "properties": {
    "iso:country":"US",
    "sg:address":"8606 Jamaica Ave",
    "sg:city":"Woodhaven",
    "sg:classifiers":[
        {
            "category":"Food & Beverages",
            "subcategory":"Groceries & Convenience Stores",
            "type":"Retail Goods"
        }
    ],
    "sg:phone":"+1 718 849 2203",
    "sg:postcode":"11421",
    "sg:province":"NY",
    "wof:name":"Harry's Discount Grocery",
    "wof:placetype":"venue"
},
  "geometry": {"coordinates":[-73.858002,40.692501],"type":"Point"}
}