{
  "type": "Feature",
  "properties": {
    "addr:full":"21 Main St Chester NY 10918",
    "addr:housenumber":"21",
    "addr:postcode":"10918",
    "addr:street":"Main St",
    "iso:country":"US",
    "sg:address":"21 Main St",
    "sg:city":"Chester",
    "sg:classifiers":[
        {
            "category":"Food & Beverages",
            "subcategory":"Meat & Fish",
            "type":"Retail Goods"
        }
    ],
    "sg:phone":"+1 845 469 4131",
    "sg:postcode":"10918",
    "sg:province":"NY",
    "wof:name":"Chester Meat Market",
    "wof:placetype":"venue"
},
  "geometry": {"coordinates":[-74.27175200000001,41.362299],"type":"Point"}
}