{
  "type": "Feature",
  "properties": {
    "addr:full":"888 Old Country Rd Plainview NY 11803",
    "addr:housenumber":"888",
    "addr:postcode":"11803",
    "addr:street":"Old Country Rd",
    "iso:country":"US",
    "sg:address":"888 Old Country Rd",
    "sg:city":"Plainview",
    "sg:classifiers":[
        {
            "category":"Health Services",
            "subcategory":"Medical Lab",
            "type":"Services"
        }
    ],
    "sg:phone":"+1 516 681 6451",
    "sg:postcode":"11803",
    "sg:province":"NY",
    "sg:tags":[
        "laboratory"
    ],
    "wof:name":"Ultrasound Lab",
    "wof:placetype":"venue"
},
  "geometry": {"coordinates":[-73.481602,40.773781],"type":"Point"}
}