{
  "type": "Feature",
  "properties": {
    "iso:country":"US",
    "sg:address":"997 Parma Center Rd",
    "sg:city":"Hilton",
    "sg:classifiers":[
        {
            "category":"Railroad",
            "type":"Transportation"
        }
    ],
    "sg:phone":"+1 585 392 3202",
    "sg:postcode":"14468",
    "sg:province":"NY",
    "sg:tags":[
        "equipment",
        "supply"
    ],
    "wof:name":"Empire Rail Signaling Inc",
    "wof:placetype":"venue"
},
  "geometry": {"coordinates":[-77.845547,43.257998],"type":"Point"}
}