{
  "type": "Feature",
  "properties": {
    "iso:country":"US",
    "sg:address":"11 Dongan Pl",
    "sg:city":"New York",
    "sg:classifiers":[
        {
            "category":"Food & Beverages",
            "subcategory":"Groceries & Convenience Stores",
            "type":"Retail Goods"
        }
    ],
    "sg:phone":"+1   ",
    "sg:postcode":"10040",
    "sg:province":"NY",
    "wof:name":"Ciprian Food Corp",
    "wof:placetype":"venue"
},
  "geometry": {"coordinates":[-73.928551,40.863362],"type":"Point"}
}