{
  "type": "Feature",
  "properties": {
    "addr:full":"1895 Flatbush Ave Brooklyn NY 11210",
    "addr:housenumber":"1895",
    "addr:postcode":"11210",
    "addr:street":"Flatbush Ave",
    "iso:country":"US",
    "sg:address":"1895 Flatbush Ave",
    "sg:city":"Brooklyn",
    "sg:classifiers":[
        {
            "category":"Retail",
            "subcategory":"Funeral Services",
            "type":"Services"
        }
    ],
    "sg:phone":"+1 718 377 3292",
    "sg:postcode":"11210",
    "sg:province":"NY",
    "sg:tags":[
        "cemetery"
    ],
    "wof:name":"I J Morris Inc",
    "wof:placetype":"venue"
},
  "geometry": {"coordinates":[-73.938103,40.6236],"type":"Point"}
}