{
  "type": "Feature",
  "properties": {
    "iso:country":"US",
    "sg:address":"1739 Seagirt Blvd",
    "sg:city":"Far Rockaway",
    "sg:classifiers":[
        {
            "category":"Banks & Credit Unions",
            "subcategory":"Bank",
            "type":"Services"
        }
    ],
    "sg:phone":"+1 718 935 9919",
    "sg:postcode":"11691",
    "sg:province":"NY",
    "wof:name":"Greenpoint Bank",
    "wof:placetype":"venue"
},
  "geometry": {"coordinates":[-73.751999,40.594898],"type":"Point"}
}