{
  "type": "Feature",
  "properties": {
    "addr:full":"239 Plandome Rd Manhasset NY 11030",
    "addr:housenumber":"239",
    "addr:postcode":"11030",
    "addr:street":"Plandome Rd",
    "iso:country":"US",
    "sg:address":"239 Plandome Rd",
    "sg:city":"Manhasset",
    "sg:classifiers":[
        {
            "category":"Retail",
            "subcategory":"Auto Repair",
            "type":"Services"
        }
    ],
    "sg:phone":"+1 516 365 4606",
    "sg:postcode":"11030",
    "sg:province":"NY",
    "sg:tags":[
        "repairing",
        "automobile"
    ],
    "wof:name":"Norens Friendly Auto Svce II Inc",
    "wof:placetype":"venue"
},
  "geometry": {"coordinates":[-73.699501,40.796501],"type":"Point"}
}