{
  "type": "Feature",
  "properties": {
    "iso:country":"US",
    "sg:address":"30 3rd St",
    "sg:city":"Waterford",
    "sg:classifiers":[
        {
            "category":"Taxi",
            "type":"Transportation"
        }
    ],
    "sg:phone":"+1   ",
    "sg:postcode":"12188",
    "sg:province":"NY",
    "sg:tags":[
        "taxicab"
    ],
    "wof:name":"Onald Service Inc",
    "wof:placetype":"venue"
},
  "geometry": {"coordinates":[-73.67855,42.789791],"type":"Point"}
}