{
  "type": "Feature",
  "properties": {
    "addr:full":"3307 Erie Blvd E De Witt NY 13214",
    "addr:housenumber":"3307",
    "addr:postcode":"13214",
    "addr:street":"Erie Blvd E De Witt",
    "iso:country":"US",
    "sg:address":"3307 Erie Blvd E",
    "sg:city":"De Witt",
    "sg:classifiers":[
        {
            "category":"Shopping",
            "subcategory":"Clothing, Apparel, & Fashions",
            "type":"Retail Goods"
        }
    ],
    "sg:phone":"+1 315 446 8330",
    "sg:postcode":"13214",
    "sg:province":"NY",
    "sg:tags":[
        "tailor"
    ],
    "wof:name":"Yunus Custom Tailoring",
    "wof:placetype":"venue"
},
  "geometry": {"coordinates":[-76.070269,43.048163],"type":"Point"}
}