{
  "type": "Feature",
  "properties": {
    "iso:country":"US",
    "sg:address":"41 Grand St",
    "sg:city":"Croton On Hudson",
    "sg:classifiers":[
        {
            "category":"Retail",
            "subcategory":"Funeral Services",
            "type":"Services"
        }
    ],
    "sg:phone":"+1 914 271 4882",
    "sg:postcode":"10520",
    "sg:province":"NY",
    "sg:tags":[
        "director"
    ],
    "wof:name":"Edward F Carter Funeral Home",
    "wof:placetype":"venue"
},
  "geometry": {"coordinates":[-73.889447,41.203925],"type":"Point"}
}