{
  "type": "Feature",
  "properties": {
    "addr:full":"55 Bush Ln Ithaca NY 14850",
    "addr:housenumber":"55",
    "addr:postcode":"14850",
    "addr:street":"Bush Ln",
    "iso:country":"US",
    "sg:address":"55 Bush Ln",
    "sg:city":"Ithaca",
    "sg:classifiers":[
        {
            "category":"Social Services",
            "type":"Services"
        }
    ],
    "sg:phone":"+1 607 257 0906",
    "sg:postcode":"14850",
    "sg:province":"NY",
    "sg:tags":[
        "hospital",
        "counselor",
        "marriage",
        "specialty",
        "family"
    ],
    "wof:name":"Stuart E Bergman",
    "wof:placetype":"venue"
},
  "geometry": {"coordinates":[-76.483836,42.494828],"type":"Point"}
}