{
  "type": "Feature",
  "properties": {
    "addr:full":"11 Ralph Place Staten Island NY 10304",
    "addr:housenumber":"11",
    "addr:postcode":"10304",
    "addr:street":"Ralph Place",
    "iso:country":"US",
    "sg:address":"11 Ralph Place",
    "sg:city":"Staten Island",
    "sg:classifiers":[
        {
            "category":"Health Services",
            "subcategory":"Dentist",
            "type":"Services"
        }
    ],
    "sg:phone":"+1 718 727 4141",
    "sg:postcode":"10304",
    "sg:province":"NY",
    "wof:name":"D & D Periodontics PC",
    "wof:placetype":"venue"
},
  "geometry": {"coordinates":[-74.092174,40.605237],"type":"Point"}
}