{
  "type": "Feature",
  "properties": {
    "iso:country":"US",
    "sg:address":"4814 Avenue N",
    "sg:city":"Brooklyn",
    "sg:classifiers":[
        {
            "category":"Personal",
            "subcategory":"Beauty Salon",
            "type":"Services"
        }
    ],
    "sg:phone":"+1 718 338 9840",
    "sg:postcode":"11234",
    "sg:province":"NY",
    "sg:tags":[
        "nail",
        "manicuring"
    ],
    "wof:name":"Nail House",
    "wof:placetype":"venue"
},
  "geometry": {"coordinates":[-73.928403,40.618743],"type":"Point"}
}