{
  "type": "Feature",
  "properties": {
    "addr:full":"1058 Broadway Woodmere NY 11598",
    "addr:housenumber":"1058",
    "addr:postcode":"11598",
    "addr:street":"Broadway",
    "iso:country":"US",
    "sg:address":"1058 Broadway",
    "sg:city":"Woodmere",
    "sg:classifiers":[
        {
            "category":"Restaurant",
            "type":"Food & Drink"
        }
    ],
    "sg:menulink":"http://www.allmenus.com/ny/five-towns/240643-tokyo-sushi-japanese-restaurant/menu/",
    "sg:phone":"+1 516 569 1016",
    "sg:postcode":"11598",
    "sg:province":"NY",
    "sg:tags":[
        "japanese",
        "asian"
    ],
    "wof:name":"Tokyo Sushi Japanese Restaurant",
    "wof:placetype":"venue"
},
  "geometry": {"coordinates":[-73.706856,40.632049],"type":"Point"}
}