{
  "type": "Feature",
  "properties": {
    "addr:full":"2805 W Henrietta Rd Rochester NY 14623",
    "addr:housenumber":"2805",
    "addr:postcode":"14623",
    "addr:street":"W Henrietta Rd",
    "iso:country":"US",
    "sg:address":"2805 W Henrietta Rd",
    "sg:city":"Rochester",
    "sg:classifiers":[
        {
            "category":"Restaurant",
            "type":"Food & Drink"
        }
    ],
    "sg:menulink":"http://www.allmenus.com/ny/brighton/23513-seoul-garden-restaurant/menu/",
    "sg:phone":"+1 585 424 2220",
    "sg:postcode":"14623",
    "sg:province":"NY",
    "sg:tags":[
        "korean",
        "asian"
    ],
    "wof:name":"Seoul Garden Restaurant",
    "wof:placetype":"venue"
},
  "geometry": {"coordinates":[-77.632735,43.095665],"type":"Point"}
}