{
  "type": "Feature",
  "properties": {
    "addr:full":"360 Rockaway Tpke Cedarhurst NY 11516",
    "addr:housenumber":"360",
    "addr:postcode":"11516",
    "addr:street":"Rockaway Tpke",
    "iso:country":"US",
    "sg:address":"360 Rockaway Tpke",
    "sg:city":"Cedarhurst",
    "sg:classifiers":[
        {
            "category":"Retail",
            "subcategory":"Auto Repair",
            "type":"Services"
        }
    ],
    "sg:phone":"+1 516 239 9993",
    "sg:postcode":"11516",
    "sg:province":"NY",
    "wof:name":"K Stevenson Auto Cntr Inc",
    "wof:placetype":"venue"
},
  "geometry": {"coordinates":[-73.73429899999999,40.622898],"type":"Point"}
}