{
  "type": "Feature",
  "properties": {
    "iso:country":"US",
    "sg:address":"85 Mc Clellan St",
    "sg:city":"Bronx",
    "sg:classifiers":[
        {
            "category":"Food & Beverages",
            "subcategory":"Bakery",
            "type":"Retail Goods"
        }
    ],
    "sg:phone":"+1   ",
    "sg:postcode":"10452",
    "sg:province":"NY",
    "wof:name":"Comida Mexicana",
    "wof:placetype":"venue"
},
  "geometry": {"coordinates":[-73.92042600000001,40.833653],"type":"Point"}
}