{
  "type": "Feature",
  "properties": {
    "addr:full":"26 Murdock St Gouverneur NY 13642",
    "addr:housenumber":"26",
    "addr:postcode":"13642",
    "addr:street":"Murdock St",
    "iso:country":"US",
    "sg:address":"26 Murdock St",
    "sg:city":"Gouverneur",
    "sg:classifiers":[
        {
            "category":"Government",
            "subcategory":"Police Station",
            "type":"Public Place"
        }
    ],
    "sg:phone":"+1 315 287 2311",
    "sg:postcode":"13642",
    "sg:province":"NY",
    "sg:tags":[
        "state"
    ],
    "wof:name":"State Police Dept",
    "wof:placetype":"venue"
},
  "geometry": {"coordinates":[-75.48031,44.326424],"type":"Point"}
}