{
  "type": "Feature",
  "properties": {
    "addr:full":"555 Prospect Pl Brooklyn NY 11238",
    "addr:housenumber":"555",
    "addr:postcode":"11238",
    "addr:street":"Prospect Pl",
    "iso:country":"US",
    "sg:address":"555 Prospect Pl",
    "sg:city":"Brooklyn",
    "sg:classifiers":[
        {
            "category":"Health Services",
            "subcategory":"Doctor",
            "type":"Services"
        }
    ],
    "sg:phone":"+1 718 398 4883",
    "sg:postcode":"11238",
    "sg:province":"NY",
    "wof:name":"Rafela Sameer MD",
    "wof:placetype":"venue"
},
  "geometry": {"coordinates":[-73.958298,40.675598],"type":"Point"}
}