{
  "type": "Feature",
  "properties": {
    "addr:full":"218 Hoosick St Troy NY 12180",
    "addr:housenumber":"218",
    "addr:postcode":"12180",
    "addr:street":"Hoosick St",
    "iso:country":"US",
    "sg:address":"218 Hoosick St",
    "sg:city":"Troy",
    "sg:classifiers":[
        {
            "category":"Restaurant",
            "type":"Food & Drink"
        }
    ],
    "sg:phone":"+1 518 271 6422",
    "sg:postcode":"12180",
    "sg:province":"NY",
    "sg:tags":[
        "pizza"
    ],
    "sg:website":"http://www.dominospizza.com",
    "wof:name":"Domino's Pizza",
    "wof:placetype":"venue"
},
  "geometry": {"coordinates":[-73.67321699999999,42.738731],"type":"Point"}
}