{
  "type": "Feature",
  "properties": {
    "iso:country":"US",
    "sg:address":"1273 Clinton St",
    "sg:city":"Buffalo",
    "sg:classifiers":[
        {
            "category":"Retail",
            "subcategory":"Repair Shop",
            "type":"Services"
        }
    ],
    "sg:phone":"+1 716 823 0227",
    "sg:postcode":"14206",
    "sg:province":"NY",
    "sg:tags":[
        "welding"
    ],
    "wof:name":"Clinton Welding & Fabricating",
    "wof:placetype":"venue"
},
  "geometry": {"coordinates":[-78.827332,42.87488],"type":"Point"}
}