{
  "type": "Feature",
  "properties": {
    "addr:full":"700 Beach Rd Buffalo NY 14225",
    "addr:housenumber":"700",
    "addr:postcode":"14225",
    "addr:street":"Beach Rd",
    "iso:country":"US",
    "sg:address":"700 Beach Rd",
    "sg:city":"Buffalo",
    "sg:classifiers":[
        {
            "category":"Professional",
            "type":"Services"
        }
    ],
    "sg:phone":"+1 716 565 2188",
    "sg:postcode":"14225",
    "sg:province":"NY",
    "sg:tags":[
        "establishment"
    ],
    "wof:name":"Nancy A Gaglione Designs",
    "wof:placetype":"venue"
},
  "geometry": {"coordinates":[-78.761877,42.942206],"type":"Point"}
}