{
  "type": "Feature",
  "properties": {
    "iso:country":"US",
    "sg:address":"115 Beekman Ave",
    "sg:city":"Sleepy Hollow",
    "sg:classifiers":[
        {
            "category":"Retail",
            "subcategory":"Self-service Laundry",
            "type":"Services"
        }
    ],
    "sg:phone":"+1 914 631 3051",
    "sg:postcode":"10591",
    "sg:province":"NY",
    "wof:name":"Beekman Laundromat",
    "wof:placetype":"venue"
},
  "geometry": {"coordinates":[-73.863247,41.084017],"type":"Point"}
}