{
  "type": "Feature",
  "properties": {
    "iso:country":"US",
    "sg:address":"28 Oceanview Ave",
    "sg:city":"Manorville",
    "sg:classifiers":[
        {
            "category":"Freight",
            "type":"Transportation"
        }
    ],
    "sg:phone":"+1 631 325 2350",
    "sg:postcode":"11937",
    "sg:province":"NY",
    "sg:tags":[
        "local",
        "without",
        "storage",
        "trucking"
    ],
    "wof:name":"Dcr Trucking & Associates",
    "wof:placetype":"venue"
},
  "geometry": {"coordinates":[-72.159779,41.011008],"type":"Point"}
}