{
  "type": "Feature",
  "properties": {
    "addr:full":"1735 West Farms Rd New York NY 10460",
    "addr:housenumber":"1735",
    "addr:postcode":"10460",
    "addr:street":"West Farms Rd",
    "iso:country":"US",
    "sg:address":"1735 West Farms Rd",
    "sg:city":"New York",
    "sg:classifiers":[
        {
            "category":"Building & Trades",
            "subcategory":"Cleaning & Sanitation",
            "type":"Services"
        }
    ],
    "sg:phone":"+1 866 920 3227",
    "sg:postcode":"10460",
    "sg:province":"NY",
    "sg:tags":[
        "home",
        "carpet"
    ],
    "sg:website":"ecoastrestoration.com",
    "wof:name":"East Coast Cleaning & Restoration",
    "wof:placetype":"venue"
},
  "geometry": {"coordinates":[-73.88252799999999,40.835066],"type":"Point"}
}