{
  "type": "Feature",
  "properties": {
    "iso:country":"US",
    "sg:address":"20 Pine St",
    "sg:city":"Walden",
    "sg:classifiers":[
        {
            "category":"Organizations",
            "subcategory":"Religious Organization",
            "type":"Services"
        }
    ],
    "sg:phone":"+1 845 778 7374",
    "sg:postcode":"12586",
    "sg:province":"NY",
    "sg:tags":[
        "church"
    ],
    "wof:name":"Congregation Beth Hillel",
    "wof:placetype":"venue"
},
  "geometry": {"coordinates":[-74.192395,41.560626],"type":"Point"}
}