{
  "type": "Feature",
  "properties": {
    "iso:country":"US",
    "sg:address":"450 Eastward Ct",
    "sg:city":"Mattituck",
    "sg:classifiers":[
        {
            "category":"Government",
            "subcategory":"Office",
            "type":"Public Place"
        }
    ],
    "sg:phone":"+1 631 298 1800",
    "sg:postcode":"11952",
    "sg:province":"NY",
    "sg:tags":[
        "city"
    ],
    "wof:name":"Southold Town PBA",
    "wof:placetype":"venue"
},
  "geometry": {"coordinates":[-72.511685,40.997682],"type":"Point"}
}