{
  "type": "Feature",
  "properties": {
    "iso:country":"US",
    "sg:address":"14 Plymouth Rd",
    "sg:city":"Larchmont",
    "sg:classifiers":[
        {
            "category":"Communications",
            "type":"Services"
        }
    ],
    "sg:phone":"+1   ",
    "sg:postcode":"10538",
    "sg:province":"NY",
    "sg:tags":[
        "communication"
    ],
    "wof:name":"AG Communication",
    "wof:placetype":"venue"
},
  "geometry": {"coordinates":[-73.74938299999999,40.936044],"type":"Point"}
}