{
  "type": "Feature",
  "properties": {
    "addr:full":"273 Irving Ave Brooklyn NY 11237",
    "addr:housenumber":"273",
    "addr:postcode":"11237",
    "addr:street":"Irving Ave",
    "iso:country":"US",
    "sg:address":"273 Irving Ave",
    "sg:city":"Brooklyn",
    "sg:classifiers":[
        {
            "category":"Professional",
            "subcategory":"Computer Services",
            "type":"Services"
        }
    ],
    "sg:phone":"+1 718 628 1917",
    "sg:postcode":"11237",
    "sg:province":"NY",
    "sg:tags":[
        "repair"
    ],
    "wof:name":"Agency Matters Confidential",
    "wof:placetype":"venue"
},
  "geometry": {"coordinates":[-73.915918,40.700053],"type":"Point"}
}