{
  "type": "Feature",
  "properties": {
    "addr:full":"1256 Central Ave Albany NY 12205",
    "addr:housenumber":"1256",
    "addr:postcode":"12205",
    "addr:street":"Central Ave",
    "iso:country":"US",
    "sg:address":"1256 Central Ave",
    "sg:city":"Albany",
    "sg:classifiers":[
        {
            "category":"Banks & Credit Unions",
            "subcategory":"Bank",
            "type":"Services"
        }
    ],
    "sg:phone":"+1 518 438 2006",
    "sg:postcode":"12205",
    "sg:province":"NY",
    "wof:name":"T D Bank North",
    "wof:placetype":"venue"
},
  "geometry": {"coordinates":[-73.81078599999999,42.698266],"type":"Point"}
}