{
  "type": "Feature",
  "properties": {
    "addr:full":"9502 Flatlands Ave Brooklyn NY 11236",
    "addr:housenumber":"9502",
    "addr:postcode":"11236",
    "addr:street":"Flatlands Ave",
    "iso:country":"US",
    "sg:address":"9502 Flatlands Ave",
    "sg:city":"Brooklyn",
    "sg:classifiers":[
        {
            "category":"Building & Trades",
            "subcategory":"Construction",
            "type":"Services"
        }
    ],
    "sg:phone":"+1 718 649 3839",
    "sg:postcode":"11236",
    "sg:province":"NY",
    "sg:tags":[
        "builder",
        "patio",
        "deck"
    ],
    "wof:name":"Adorable Backyards",
    "wof:placetype":"venue"
},
  "geometry": {"coordinates":[-73.902311,40.642589],"type":"Point"}
}