{
  "type": "Feature",
  "properties": {
    "iso:country":"US",
    "sg:address":"443 Center St",
    "sg:city":"Salamanca",
    "sg:classifiers":[
        {
            "category":"Organizations",
            "subcategory":"Religious Organization",
            "type":"Services"
        }
    ],
    "sg:phone":"+1 716 945 4739",
    "sg:postcode":"14779",
    "sg:province":"NY",
    "sg:tags":[
        "church"
    ],
    "wof:name":"Centerstreet Baptist Church",
    "wof:placetype":"venue"
},
  "geometry": {"coordinates":[-78.74594,42.169913],"type":"Point"}
}