{
  "type": "Feature",
  "properties": {
    "iso:country":"US",
    "sg:address":"15 Simmons Plz",
    "sg:city":"Saugerties",
    "sg:classifiers":[
        {
            "category":"Restaurant",
            "type":"Food & Drink"
        }
    ],
    "sg:phone":"+1 845 246 0243",
    "sg:postcode":"12477",
    "sg:province":"NY",
    "wof:name":"Coasters Bar & Grille",
    "wof:placetype":"venue"
},
  "geometry": {"coordinates":[-73.955578,42.056765],"type":"Point"}
}