{
  "type": "Feature",
  "properties": {
    "addr:full":"175 Park Ave Cohoes NY 12047",
    "addr:housenumber":"175",
    "addr:postcode":"12047",
    "addr:street":"Park Ave",
    "iso:country":"US",
    "sg:address":"175 Park Ave",
    "sg:city":"Cohoes",
    "sg:classifiers":[
        {
            "category":"Organizations",
            "subcategory":"Religious Organization",
            "type":"Services"
        }
    ],
    "sg:phone":"+1   ",
    "sg:postcode":"12047",
    "sg:province":"NY",
    "wof:name":"St Ritas Sacred Heart Parish",
    "wof:placetype":"venue"
},
  "geometry": {"coordinates":[-73.689042,42.769846],"type":"Point"}
}