{
  "type": "Feature",
  "properties": {
    "iso:country":"US",
    "sg:address":"46 Genesee St",
    "sg:city":"New Hartford",
    "sg:classifiers":[
        {
            "category":"Real Estate",
            "subcategory":"Real Estate Agent",
            "type":"Services"
        }
    ],
    "sg:phone":"+1 315 732 3456",
    "sg:postcode":"13413",
    "sg:province":"NY",
    "sg:tags":[
        "consulting",
        "management"
    ],
    "wof:name":"Joyce Realty",
    "wof:placetype":"venue"
},
  "geometry": {"coordinates":[-75.288016,43.073335],"type":"Point"}
}