{
  "type": "Feature",
  "properties": {
    "addr:full":"1224 Prospect Ave Brooklyn NY 11218",
    "addr:housenumber":"1224",
    "addr:postcode":"11218",
    "addr:street":"Prospect Ave",
    "iso:country":"US",
    "sg:address":"1224 Prospect Ave",
    "sg:city":"Brooklyn",
    "sg:classifiers":[
        {
            "category":"Building & Trades",
            "subcategory":"Plumbing",
            "type":"Services"
        }
    ],
    "sg:phone":"+1 718 531 0395",
    "sg:postcode":"11218",
    "sg:province":"NY",
    "sg:tags":[
        "conditioning",
        "air",
        "system",
        "contractor"
    ],
    "wof:name":"Colonial Air Conditioning Co",
    "wof:placetype":"venue"
},
  "geometry": {"coordinates":[-73.976231,40.653247],"type":"Point"}
}