{
  "type": "Feature",
  "properties": {
    "iso:country":"US",
    "sg:address":"4455 Broadway",
    "sg:city":"New York",
    "sg:classifiers":[
        {
            "category":"Professional",
            "subcategory":"Lawyer & Legal Services",
            "type":"Services"
        }
    ],
    "sg:phone":"+1 212 544 2000",
    "sg:postcode":"10040",
    "sg:province":"NY",
    "sg:tags":[
        "plan"
    ],
    "sg:website":"www.americancapitalfinance.com",
    "wof:name":"American Capital & Para Legal",
    "wof:placetype":"venue"
},
  "geometry": {"coordinates":[-73.93261200000001,40.856578],"type":"Point"}
}