{
  "type": "Feature",
  "properties": {
    "addr:full":"8709 Turin Rd Rome NY 13440",
    "addr:housenumber":"8709",
    "addr:postcode":"13440",
    "addr:street":"Turin Rd",
    "iso:country":"US",
    "sg:address":"8709 Turin Rd",
    "sg:city":"Rome",
    "sg:classifiers":[
        {
            "category":"Food & Beverages",
            "subcategory":"Groceries & Convenience Stores",
            "type":"Retail Goods"
        }
    ],
    "sg:phone":"+1 315 339 1851",
    "sg:postcode":"13440",
    "sg:province":"NY",
    "sg:website":"http://www.niceneasy.com",
    "wof:name":"Nice N Easy Grocery Shoppes, Inc.",
    "wof:placetype":"venue"
},
  "geometry": {"coordinates":[-75.47060999999999,43.282724],"type":"Point"}
}