{
  "type": "Feature",
  "properties": {
    "addr:full":"1721 Elmwood Ave Buffalo NY 14207",
    "addr:housenumber":"1721",
    "addr:postcode":"14207",
    "addr:street":"Elmwood Ave",
    "iso:country":"US",
    "sg:address":"1721 Elmwood Ave",
    "sg:city":"Buffalo",
    "sg:classifiers":[
        {
            "category":"Building & Trades",
            "subcategory":"Construction",
            "type":"Services"
        }
    ],
    "sg:phone":"+1 716 873 5720",
    "sg:postcode":"14207",
    "sg:province":"NY",
    "sg:tags":[
        "contractor",
        "industrial",
        "machinery",
        "mfg"
    ],
    "wof:name":"Hagner Industries Inc",
    "wof:placetype":"venue"
},
  "geometry": {"coordinates":[-78.87849300000001,42.940747],"type":"Point"}
}