{
  "type": "Feature",
  "properties": {
    "addr:full":"30 W Jefryn Blvd Deer Park NY 11729",
    "addr:housenumber":"30",
    "addr:postcode":"11729",
    "addr:street":"W Jefryn Blvd",
    "iso:country":"US",
    "sg:address":"30 W Jefryn Blvd",
    "sg:city":"Deer Park",
    "sg:classifiers":[
        {
            "category":"Professional",
            "subcategory":"Management & Consulting",
            "type":"Services"
        }
    ],
    "sg:phone":"+1 631 586 0844",
    "sg:postcode":"11729",
    "sg:province":"NY",
    "sg:tags":[
        "design",
        "command",
        "installation",
        "center",
        "console"
    ],
    "wof:name":"Crc Group LLC",
    "wof:placetype":"venue"
},
  "geometry": {"coordinates":[-73.301411,40.757992],"type":"Point"}
}