{
  "type": "Feature",
  "properties": {
    "addr:full":"878 Long Pond Rd Greece NY 14612",
    "addr:housenumber":"878",
    "addr:postcode":"14612",
    "addr:street":"Long Pond Rd",
    "iso:country":"US",
    "sg:address":"878 Long Pond Rd",
    "sg:city":"Greece",
    "sg:classifiers":[
        {
            "category":"Shopping",
            "subcategory":"Pharmacy",
            "type":"Retail Goods"
        }
    ],
    "sg:phone":"+1 585 723 3051",
    "sg:postcode":"14612",
    "sg:province":"NY",
    "wof:name":"CVS Pharmacy",
    "wof:placetype":"venue"
},
  "geometry": {"coordinates":[-77.696529,43.24278],"type":"Point"}
}