{
  "type": "Feature",
  "properties": {
    "iso:country":"US",
    "sg:address":"59 Covert Ave",
    "sg:city":"Floral Park",
    "sg:classifiers":[
        {
            "category":"Shopping",
            "subcategory":"Florist",
            "type":"Retail Goods"
        }
    ],
    "sg:phone":"+1   ",
    "sg:postcode":"11001",
    "sg:province":"NY",
    "wof:name":"Esthers Florist",
    "wof:placetype":"venue"
},
  "geometry": {"coordinates":[-73.689269,40.7134],"type":"Point"}
}