{
  "type": "Feature",
  "properties": {
    "addr:full":"119 N Park Ave Ste 206 Rockville Centre NY 11570",
    "addr:housenumber":"119",
    "addr:postcode":"11570",
    "addr:street":"N Park Ave Ste 206",
    "iso:country":"US",
    "sg:address":"119 N Park Ave Ste 206",
    "sg:city":"Rockville Centre",
    "sg:classifiers":[
        {
            "category":"Health Services",
            "subcategory":"Doctor",
            "type":"Services"
        },
        {
            "category":"Health Services",
            "subcategory":"Clinic",
            "type":"Services"
        }
    ],
    "sg:phone":"+1 516 678 6368",
    "sg:postcode":"11570",
    "sg:province":"NY",
    "sg:tags":[
        "counseling",
        "mental"
    ],
    "wof:name":"Springstubb Gary PHD",
    "wof:placetype":"venue"
},
  "geometry": {"coordinates":[-73.644897,40.6604],"type":"Point"}
}