{
  "type": "Feature",
  "properties": {
    "addr:full":"303 Main St Little Valley NY 14755",
    "addr:housenumber":"303",
    "addr:postcode":"14755",
    "addr:street":"Main St",
    "iso:country":"US",
    "sg:address":"303 Main St",
    "sg:city":"Little Valley",
    "sg:classifiers":[
        {
            "category":"Shopping",
            "subcategory":"Computers & Home Electronics",
            "type":"Retail Goods"
        }
    ],
    "sg:phone":"+1 716 938 6343",
    "sg:postcode":"14755",
    "sg:province":"NY",
    "sg:tags":[
        "merchandise"
    ],
    "wof:name":"Aurora Electronics",
    "wof:placetype":"venue"
},
  "geometry": {"coordinates":[-78.796334,42.250683],"type":"Point"}
}