{
  "type": "Feature",
  "properties": {
    "iso:country":"US",
    "sg:address":"275 North Street",
    "sg:city":"Newburgh",
    "sg:classifiers":[
        {
            "category":"Real Estate",
            "subcategory":"Architect",
            "type":"Services"
        }
    ],
    "sg:phone":"+1 845 561 7500",
    "sg:postcode":"12550",
    "sg:province":"NY",
    "sg:website":"www.hennessyarchitects.com",
    "wof:name":"A Hennessy Architects, PC",
    "wof:placetype":"venue"
},
  "geometry": {"coordinates":[-74.024413,41.514661],"type":"Point"}
}