{
  "type": "Feature",
  "properties": {
    "addr:full":"1982 Crotona Pkwy Bronx NY 10460",
    "addr:housenumber":"1982",
    "addr:postcode":"10460",
    "addr:street":"Crotona Pkwy",
    "iso:country":"US",
    "sg:address":"1982 Crotona Pkwy",
    "sg:city":"Bronx",
    "sg:classifiers":[
        {
            "category":"Shopping",
            "subcategory":"Computers & Home Electronics",
            "type":"Retail Goods"
        }
    ],
    "sg:phone":"+1 718 842 5900",
    "sg:postcode":"10460",
    "sg:province":"NY",
    "sg:tags":[
        "parts",
        "supply"
    ],
    "wof:name":"Royal Automation Supplies Corp",
    "wof:placetype":"venue"
},
  "geometry": {"coordinates":[-73.88509999999999,40.843001],"type":"Point"}
}