{
  "type": "Feature",
  "properties": {
    "iso:country":"US",
    "sg:address":"100 Morris Ave",
    "sg:city":"Glen Cove",
    "sg:classifiers":[
        {
            "category":"Professional",
            "subcategory":"Management & Consulting",
            "type":"Services"
        }
    ],
    "sg:phone":"+1   ",
    "sg:postcode":"11542",
    "sg:province":"NY",
    "sg:tags":[
        "chemical",
        "refuse",
        "system",
        "mfg"
    ],
    "wof:name":"Island Recycling & Envmtl",
    "wof:placetype":"venue"
},
  "geometry": {"coordinates":[-73.63516199999999,40.860351],"type":"Point"}
}