{
  "type": "Feature",
  "properties": {
    "addr:full":"160 Riverside Blvd New York NY 10069",
    "addr:housenumber":"160",
    "addr:postcode":"10069",
    "addr:street":"Riverside Blvd",
    "iso:country":"US",
    "sg:address":"160 Riverside Blvd",
    "sg:city":"New York",
    "sg:classifiers":[
        {
            "category":"Retail",
            "subcategory":"Laundry & Dry Cleaning",
            "type":"Services"
        }
    ],
    "sg:phone":"+1 212 799 1753",
    "sg:postcode":"10069",
    "sg:province":"NY",
    "wof:name":"Nu Valet Cleaners",
    "wof:placetype":"venue"
},
  "geometry": {"coordinates":[-73.987099,40.771599],"type":"Point"}
}