{
  "type": "Feature",
  "properties": {
    "addr:full":"Mt. Kisco Square Shopping Ctr 360 N Bedford Rd Mt Kisco NY 10549",
    "addr:housenumber":"360",
    "addr:postcode":"10549",
    "addr:street":"Kisco Square Shopping Ctr;N Bedford Rd",
    "iso:country":"US",
    "sg:address":"Mt. Kisco Square Shopping Ctr 360 N Bedford Rd",
    "sg:city":"Mt Kisco",
    "sg:classifiers":[
        {
            "category":"Restaurant",
            "type":"Food & Drink"
        }
    ],
    "sg:phone":"+1 914 244 8588",
    "sg:postcode":"10549",
    "sg:province":"NY",
    "sg:tags":[
        "thai"
    ],
    "wof:name":"Mana Thai Cuisine",
    "wof:placetype":"venue"
},
  "geometry": {"coordinates":[-73.71664699999999,41.217688],"type":"Point"}
}