{
  "type": "Feature",
  "properties": {
    "addr:full":"106 Main St New Canaan NY 06840",
    "addr:housenumber":"106",
    "addr:postcode":"06840",
    "addr:street":"Main St",
    "iso:country":"US",
    "sg:address":"106 Main St",
    "sg:city":"New Canaan",
    "sg:classifiers":[
        {
            "category":"Health Services",
            "subcategory":"Doctor",
            "type":"Services"
        }
    ],
    "sg:phone":"+1   ",
    "sg:postcode":"06840",
    "sg:province":"NY",
    "sg:tags":[
        "medical"
    ],
    "wof:name":"Adlt Pdtrc Drmtlgy of Grn",
    "wof:placetype":"venue"
},
  "geometry": {"coordinates":[-73.492216,41.147255],"type":"Point"}
}