{
  "type": "Feature",
  "properties": {
    "addr:full":"200 Lakewood Dr Port Jervis NY 12771",
    "addr:housenumber":"200",
    "addr:postcode":"12771",
    "addr:street":"Lakewood Dr",
    "iso:country":"US",
    "sg:address":"200 Lakewood Dr",
    "sg:city":"Port Jervis",
    "sg:classifiers":[
        {
            "category":"Home & Garden",
            "subcategory":"Building Materials",
            "type":"Retail Goods"
        }
    ],
    "sg:phone":"+1   ",
    "sg:postcode":"12771",
    "sg:province":"NY",
    "wof:name":"Lakewood Estate Mfg Home Cmnty",
    "wof:placetype":"venue"
},
  "geometry": {"coordinates":[-74.659184,41.405227],"type":"Point"}
}