{
  "type": "Feature",
  "properties": {
    "iso:country":"US",
    "sg:address":"7217 3rd Avenue",
    "sg:city":"Brooklyn",
    "sg:classifiers":[
        {
            "category":"Restaurant",
            "type":"Food & Drink"
        }
    ],
    "sg:phone":"+1 718 921 0660",
    "sg:postcode":"11209",
    "sg:province":"NY",
    "wof:name":"Dmitry Maryanovsky",
    "wof:placetype":"venue"
},
  "geometry": {"coordinates":[-74.026976,40.633397],"type":"Point"}
}