{
  "type": "Feature",
  "properties": {
    "iso:country":"US",
    "sg:address":"3361 Milton Ave",
    "sg:city":"Syracuse",
    "sg:classifiers":[
        {
            "category":"Autos & Motor Vehicles",
            "subcategory":"Automobile Sales",
            "type":"Retail Goods"
        }
    ],
    "sg:phone":"+1 315 468 1411",
    "sg:postcode":"13219",
    "sg:province":"NY",
    "sg:tags":[
        "dealers-used",
        "car",
        "used",
        "cars-wholesale"
    ],
    "wof:name":"South Eastern Motors",
    "wof:placetype":"venue"
},
  "geometry": {"coordinates":[-76.23979199999999,43.051539],"type":"Point"}
}