{
  "type": "Feature",
  "properties": {
    "addr:full":"313 E 43rd St New York NY 10017",
    "addr:housenumber":"313",
    "addr:postcode":"10017",
    "addr:street":"E 43Rd St",
    "iso:country":"US",
    "sg:address":"313 E 43rd St",
    "sg:city":"New York",
    "sg:classifiers":[
        {
            "category":"Government",
            "subcategory":"Office",
            "type":"Public Place"
        }
    ],
    "sg:phone":"+1 212 682 0232",
    "sg:postcode":"10017",
    "sg:province":"NY",
    "sg:tags":[
        "affairs",
        "product",
        "federal",
        "malaysian",
        "us",
        "to",
        "promote"
    ],
    "wof:name":"Malaysian Trade Commission",
    "wof:placetype":"venue"
},
  "geometry": {"coordinates":[-73.970311,40.750036],"type":"Point"}
}