{
  "type": "Feature",
  "properties": {
    "iso:country":"US",
    "sg:address":"16 Jefferson Blvd",
    "sg:city":"Staten Island",
    "sg:classifiers":[
        {
            "category":"Personal",
            "subcategory":"Beauty Salon",
            "type":"Services"
        }
    ],
    "sg:phone":"+1   ",
    "sg:postcode":"10312",
    "sg:province":"NY",
    "sg:tags":[
        "shop"
    ],
    "wof:name":"Hair Den",
    "wof:placetype":"venue"
},
  "geometry": {"coordinates":[-74.178015,40.541173],"type":"Point"}
}