{
  "type": "Feature",
  "properties": {
    "iso:country":"US",
    "sg:address":"1 Penn Plz",
    "sg:city":"New York",
    "sg:classifiers":[
        {
            "category":"Professional",
            "subcategory":"Lawyer & Legal Services",
            "type":"Services"
        }
    ],
    "sg:phone":"+1 212 695 8100",
    "sg:postcode":"10119",
    "sg:province":"NY",
    "wof:name":"Boyajian Aaron D ESQ",
    "wof:placetype":"venue"
},
  "geometry": {"coordinates":[-73.992104,40.751598],"type":"Point"}
}