{
  "type": "Feature",
  "properties": {
    "addr:full":"4 Berry Ct Congers NY 10920",
    "addr:housenumber":"4",
    "addr:postcode":"10920",
    "addr:street":"Berry Ct",
    "iso:country":"US",
    "sg:address":"4 Berry Ct",
    "sg:city":"Congers",
    "sg:classifiers":[
        {
            "category":"Building & Trades",
            "subcategory":"Landscaping Services",
            "type":"Services"
        }
    ],
    "sg:phone":"+1 845 268 6037",
    "sg:postcode":"10920",
    "sg:province":"NY",
    "sg:tags":[
        "landscape"
    ],
    "wof:name":"Schmidt Brothers Landscaping",
    "wof:placetype":"venue"
},
  "geometry": {"coordinates":[-73.94464499999999,41.164276],"type":"Point"}
}