{
  "type": "Feature",
  "properties": {
    "addr:full":"111 Prospect Place Brooklyn NY 11217",
    "addr:housenumber":"111",
    "addr:postcode":"11217",
    "addr:street":"Prospect Place",
    "iso:country":"US",
    "sg:address":"111 Prospect Place",
    "sg:city":"Brooklyn",
    "sg:classifiers":[
        {
            "category":"Shopping",
            "subcategory":"Crafts & Fabrics",
            "type":"Retail Goods"
        }
    ],
    "sg:phone":"+1 718 636 5835",
    "sg:postcode":"11217",
    "sg:province":"NY",
    "sg:tags":[
        "art",
        "supply"
    ],
    "wof:name":"Artisan Art",
    "wof:placetype":"venue"
},
  "geometry": {"coordinates":[-73.97351500000001,40.678663],"type":"Point"}
}