{
  "type": "Feature",
  "properties": {
    "addr:full":"4 Baisley Cir Pomona NY 10970",
    "addr:housenumber":"4",
    "addr:postcode":"10970",
    "addr:street":"Baisley Cir",
    "iso:country":"US",
    "sg:address":"4 Baisley Cir",
    "sg:city":"Pomona",
    "sg:classifiers":[
        {
            "category":"Building & Trades",
            "subcategory":"Cleaning & Sanitation",
            "type":"Services"
        }
    ],
    "sg:phone":"+1 845 634 6300",
    "sg:postcode":"10970",
    "sg:province":"NY",
    "sg:tags":[
        "fireplace",
        "chimney"
    ],
    "wof:name":"High Tech Chimney",
    "wof:placetype":"venue"
},
  "geometry": {"coordinates":[-74.024288,41.195962],"type":"Point"}
}