{
  "type": "Feature",
  "properties": {
    "addr:full":"700 Bradley Hill Rd Blauvelt NY 10913",
    "addr:housenumber":"700",
    "addr:postcode":"10913",
    "addr:street":"Bradley Hill Rd",
    "iso:country":"US",
    "sg:address":"700 Bradley Hill Rd",
    "sg:city":"Blauvelt",
    "sg:classifiers":[
        {
            "category":"Professional",
            "subcategory":"Management & Consulting",
            "type":"Services"
        }
    ],
    "sg:phone":"+1 845 353 8548",
    "sg:postcode":"10913",
    "sg:province":"NY",
    "sg:tags":[
        "consultant",
        "resource",
        "human"
    ],
    "wof:name":"Human Resources Staffing",
    "wof:placetype":"venue"
},
  "geometry": {"coordinates":[-73.94932799999999,41.076043],"type":"Point"}
}