{
  "type": "Feature",
  "properties": {
    "addr:full":"18 Sound Rd Greenport NY 11944",
    "addr:housenumber":"18",
    "addr:postcode":"11944",
    "addr:street":"Sound Rd",
    "iso:country":"US",
    "sg:address":"18 Sound Rd",
    "sg:city":"Greenport",
    "sg:classifiers":[
        {
            "category":"Professional",
            "subcategory":"Accounting & Tax Preparation",
            "type":"Services"
        }
    ],
    "sg:phone":"+1   ",
    "sg:postcode":"11944",
    "sg:province":"NY",
    "wof:name":"North Fork Bookkeeping Cons",
    "wof:placetype":"venue"
},
  "geometry": {"coordinates":[-72.368437,41.114937],"type":"Point"}
}