{
  "type": "Feature",
  "properties": {
    "addr:full":"170 E 116th St New York NY 10029",
    "addr:housenumber":"170",
    "addr:postcode":"10029",
    "addr:street":"E 116Th St",
    "iso:country":"US",
    "sg:address":"170 E 116th St",
    "sg:city":"New York",
    "sg:classifiers":[
        {
            "category":"Government",
            "subcategory":"Office",
            "type":"Public Place"
        }
    ],
    "sg:phone":"+1 212 860 6704",
    "sg:postcode":"10029",
    "sg:province":"NY",
    "sg:tags":[
        "policy"
    ],
    "wof:name":"Pozo International Promotions",
    "wof:placetype":"venue"
},
  "geometry": {"coordinates":[-73.940562,40.798164],"type":"Point"}
}