{
  "type": "Feature",
  "properties": {
    "addr:full":"73 E 7 St New York NY 10003",
    "addr:housenumber":"73;7",
    "addr:postcode":"10003",
    "addr:street":"E",
    "iso:country":"US",
    "sg:address":"73 E 7 St",
    "sg:city":"New York",
    "sg:classifiers":[
        {
            "category":"Shopping",
            "subcategory":"Beauty & Cosmetics",
            "type":"Retail Goods"
        }
    ],
    "sg:phone":"+1   ",
    "sg:postcode":"10003",
    "sg:province":"NY",
    "sg:tags":[
        "merchandise"
    ],
    "wof:name":"Most Wanted",
    "wof:placetype":"venue"
},
  "geometry": {"coordinates":[-73.98682599999999,40.727671],"type":"Point"}
}