{
  "type": "Feature",
  "properties": {
    "iso:country":"US",
    "sg:address":"18 New St",
    "sg:city":"Hewlett",
    "sg:classifiers":[
        {
            "category":"Building & Trades",
            "subcategory":"Plumbing",
            "type":"Services"
        }
    ],
    "sg:phone":"+1 516 295 2140",
    "sg:postcode":"11557",
    "sg:province":"NY",
    "sg:tags":[
        "contractor"
    ],
    "wof:name":"Metropolitan Plumbing & Heating",
    "wof:placetype":"venue"
},
  "geometry": {"coordinates":[-73.702698,40.637299],"type":"Point"}
}