{
  "type": "Feature",
  "properties": {
    "addr:full":"402 W 47th St New York NY 10036",
    "addr:housenumber":"402",
    "addr:postcode":"10036",
    "addr:street":"W 47Th St",
    "iso:country":"US",
    "sg:address":"402 W 47th St",
    "sg:city":"New York",
    "sg:classifiers":[
        {
            "category":"Restaurant",
            "type":"Food & Drink"
        }
    ],
    "sg:menulink":"http://www.allmenus.com/ny/new-york/252769-pam-real-thai/menu/",
    "sg:phone":"+1 212 315 4441",
    "sg:postcode":"10036",
    "sg:province":"NY",
    "sg:tags":[
        "thai",
        "asian"
    ],
    "wof:name":"Pam Real Thai",
    "wof:placetype":"venue"
},
  "geometry": {"coordinates":[-73.99078799999999,40.761646],"type":"Point"}
}