{
  "type": "Feature",
  "properties": {
    "iso:country":"US",
    "sg:address":"510 Main St",
    "sg:city":"Medina",
    "sg:classifiers":[
        {
            "category":"Real Estate",
            "subcategory":"Real Estate Agent",
            "type":"Services"
        }
    ],
    "sg:phone":"+1 585 798 1949",
    "sg:postcode":"14103",
    "sg:province":"NY",
    "sg:website":"www.realtyusa.com",
    "wof:name":"Realty USA",
    "wof:placetype":"venue"
},
  "geometry": {"coordinates":[-78.38697999999999,43.2195],"type":"Point"}
}