{
  "type": "Feature",
  "properties": {
    "addr:full":"309 Breakspear Rd Syracuse NY 13219",
    "addr:housenumber":"309",
    "addr:postcode":"13219",
    "addr:street":"Breakspear Rd",
    "iso:country":"US",
    "sg:address":"309 Breakspear Rd",
    "sg:city":"Syracuse",
    "sg:classifiers":[
        {
            "category":"Organizations",
            "subcategory":"Religious Organization",
            "type":"Services"
        }
    ],
    "sg:phone":"+1 315 468 0076",
    "sg:postcode":"13219",
    "sg:province":"NY",
    "sg:tags":[
        "clergy"
    ],
    "wof:name":"Thomas H Hedges",
    "wof:placetype":"venue"
},
  "geometry": {"coordinates":[-76.21447000000001,43.041036],"type":"Point"}
}