{
  "type": "Feature",
  "properties": {
    "addr:full":"1380 E 17th St Brooklyn NY 11230",
    "addr:housenumber":"1380",
    "addr:postcode":"11230",
    "addr:street":"E 17Th St",
    "iso:country":"US",
    "sg:address":"1380 E 17th St",
    "sg:city":"Brooklyn",
    "sg:classifiers":[
        {
            "category":"Manufacturing",
            "subcategory":"Printing",
            "type":"Manufacturing & Wholesale Goods"
        }
    ],
    "sg:phone":"+1   ",
    "sg:postcode":"11230",
    "sg:province":"NY",
    "sg:tags":[
        "publishing"
    ],
    "wof:name":"Lrc Publications Incorporated",
    "wof:placetype":"venue"
},
  "geometry": {"coordinates":[-73.95792899999999,40.616934],"type":"Point"}
}