{
  "type": "Feature",
  "properties": {
    "addr:full":"630 Old Country Rd Garden City NY 11530",
    "addr:housenumber":"630",
    "addr:postcode":"11530",
    "addr:street":"Old Country Rd",
    "iso:country":"US",
    "sg:address":"630 Old Country Rd",
    "sg:city":"Garden City",
    "sg:classifiers":[
        {
            "category":"Shopping",
            "subcategory":"Gifts & Souvenirs",
            "type":"Retail Goods"
        }
    ],
    "sg:phone":"+1 516 248 0642",
    "sg:postcode":"11530",
    "sg:province":"NY",
    "sg:tags":[
        "flower"
    ],
    "wof:name":"Gadgets & Gizmos",
    "wof:placetype":"venue"
},
  "geometry": {"coordinates":[-73.614296,40.742997],"type":"Point"}
}