{
  "type": "Feature",
  "properties": {
    "addr:full":"2064 N Country Rd Wading River NY 11792",
    "addr:housenumber":"2064",
    "addr:postcode":"11792",
    "addr:street":"N Country Rd",
    "iso:country":"US",
    "sg:address":"2064 N Country Rd",
    "sg:city":"Wading River",
    "sg:classifiers":[
        {
            "category":"Building & Trades",
            "subcategory":"Construction",
            "type":"Services"
        }
    ],
    "sg:phone":"+1 631 929 6619",
    "sg:postcode":"11792",
    "sg:province":"NY",
    "sg:tags":[
        "general",
        "contractor"
    ],
    "wof:name":"William Bryant Construction Co",
    "wof:placetype":"venue"
},
  "geometry": {"coordinates":[-72.847774,40.954345],"type":"Point"}
}