{
  "type": "Feature",
  "properties": {
    "iso:country":"US",
    "sg:address":"6815 Byron Holley Rd",
    "sg:city":"Byron",
    "sg:classifiers":[
        {
            "category":"Community Center",
            "type":"Public Place"
        }
    ],
    "sg:phone":"+1 585 548 7155",
    "sg:postcode":"14422",
    "sg:province":"NY",
    "sg:tags":[
        "medical"
    ],
    "wof:name":"United Memorial Medical Center",
    "wof:placetype":"venue"
},
  "geometry": {"coordinates":[-78.06477,43.082365],"type":"Point"}
}