{
  "type": "Feature",
  "properties": {
    "addr:full":"93 Spring Brook Rd Pulaski NY 13142",
    "addr:housenumber":"93",
    "addr:postcode":"13142",
    "addr:street":"Spring Brook Rd",
    "iso:country":"US",
    "sg:address":"93 Spring Brook Rd",
    "sg:city":"Pulaski",
    "sg:classifiers":[
        {
            "category":"Recreation",
            "type":"Entertainment"
        }
    ],
    "sg:phone":"+1   ",
    "sg:postcode":"13142",
    "sg:province":"NY",
    "wof:name":"Full Stringrs Salmn Rv Guide S",
    "wof:placetype":"venue"
},
  "geometry": {"coordinates":[-76.090064,43.571462],"type":"Point"}
}