{
  "type": "Feature",
  "properties": {
    "addr:full":"485 East Rd Marlboro NY 12542",
    "addr:housenumber":"485",
    "addr:postcode":"rd;12542",
    "addr:street":"East",
    "iso:country":"US",
    "sg:address":"485 East Rd",
    "sg:city":"Marlboro",
    "sg:classifiers":[
        {
            "category":"Utilities",
            "subcategory":"Fuel Oil & Lpg",
            "type":"Services"
        }
    ],
    "sg:phone":"+1 845 566 0105",
    "sg:postcode":"12542",
    "sg:province":"NY",
    "sg:tags":[
        "oils-fuel"
    ],
    "wof:name":"A1 Fuel Oil Inc",
    "wof:placetype":"venue"
},
  "geometry": {"coordinates":[-74.03792,41.584611],"type":"Point"}
}