{
  "type": "Feature",
  "properties": {
    "addr:full":"502 9th Ave New York NY 10018",
    "addr:housenumber":"502",
    "addr:postcode":"10018",
    "addr:street":"9Th Ave",
    "iso:country":"US",
    "sg:address":"502 9th Ave",
    "sg:city":"New York",
    "sg:classifiers":[
        {
            "category":"Coffee & Tea",
            "type":"Food & Drink"
        }
    ],
    "sg:phone":"+1 212 792 6998",
    "sg:postcode":"10018",
    "sg:province":"NY",
    "wof:name":"Buongiorno Espresso Bar",
    "wof:placetype":"venue"
},
  "geometry": {"coordinates":[-73.994057,40.75587],"type":"Point"}
}