{
  "type": "Feature",
  "properties": {
    "addr:full":"321 Hazeltine Ave Jamestown NY 14701",
    "addr:housenumber":"321",
    "addr:postcode":"14701",
    "addr:street":"Hazeltine Ave",
    "iso:country":"US",
    "sg:address":"321 Hazeltine Ave",
    "sg:city":"Jamestown",
    "sg:classifiers":[
        {
            "category":"Government",
            "subcategory":"Office",
            "type":"Public Place"
        }
    ],
    "sg:phone":"+1 716 487 9055",
    "sg:postcode":"14701",
    "sg:province":"NY",
    "sg:tags":[
        "federal",
        "program"
    ],
    "wof:name":"US Health & Human Svc",
    "wof:placetype":"venue"
},
  "geometry": {"coordinates":[-79.254459,42.082839],"type":"Point"}
}