{
  "type": "Feature",
  "properties": {
    "addr:full":"41 Lake St White Plains NY 10603",
    "addr:housenumber":"41",
    "addr:postcode":"10603",
    "addr:street":"Lake St",
    "iso:country":"US",
    "sg:address":"41 Lake St",
    "sg:city":"White Plains",
    "sg:classifiers":[
        {
            "category":"Retail",
            "subcategory":"Laundry & Dry Cleaning",
            "type":"Services"
        }
    ],
    "sg:phone":"+1 914 428 4444",
    "sg:postcode":"10603",
    "sg:province":"NY",
    "sg:tags":[
        "drycleaning",
        "plant",
        "cleaners"
    ],
    "wof:name":"Young Fashion Care Cleaners",
    "wof:placetype":"venue"
},
  "geometry": {"coordinates":[-73.760301,41.037808],"type":"Point"}
}