{
  "type": "Feature",
  "properties": {
    "addr:full":"253 Utica Ave Brooklyn NY 11213",
    "addr:housenumber":"253",
    "addr:postcode":"11213",
    "addr:street":"Utica Ave",
    "iso:country":"US",
    "sg:address":"253 Utica Ave",
    "sg:city":"Brooklyn",
    "sg:classifiers":[
        {
            "category":"Health Services",
            "subcategory":"Health Practitioner",
            "type":"Services"
        }
    ],
    "sg:phone":"+1 718 221 2561",
    "sg:postcode":"11213",
    "sg:province":"NY",
    "sg:tags":[
        "nurse",
        "registry"
    ],
    "wof:name":"Atm Professional Registry",
    "wof:placetype":"venue"
},
  "geometry": {"coordinates":[-73.930908,40.670408],"type":"Point"}
}