{
  "type": "Feature",
  "properties": {
    "addr:full":"19 1st Ave Ulster Park NY 12401",
    "addr:housenumber":"19",
    "addr:postcode":"12401",
    "addr:street":"1St Ave",
    "iso:country":"US",
    "sg:address":"19 1st Ave",
    "sg:city":"Ulster Park",
    "sg:classifiers":[
        {
            "category":"Building & Trades",
            "subcategory":"Construction",
            "type":"Services"
        }
    ],
    "sg:phone":"+1 845 336 4419",
    "sg:postcode":"12401",
    "sg:province":"NY",
    "sg:tags":[
        "product",
        "asphalt"
    ],
    "wof:name":"Callanan Asphalt Plant",
    "wof:placetype":"venue"
},
  "geometry": {"coordinates":[-73.98392200000001,41.927212],"type":"Point"}
}