{
  "type": "Feature",
  "properties": {
    "iso:country":"US",
    "sg:address":"7529 State Hwy 12",
    "sg:city":"Lowville",
    "sg:classifiers":[
        {
            "category":"Shopping",
            "type":"Retail Goods"
        }
    ],
    "sg:phone":"+1   ",
    "sg:postcode":"13367",
    "sg:province":"NY",
    "sg:tags":[
        "monument"
    ],
    "wof:name":"Lewis County Monuments",
    "wof:placetype":"venue"
},
  "geometry": {"coordinates":[-75.49077200000001,43.784392],"type":"Point"}
}