{
  "type": "Feature",
  "properties": {
    "addr:full":"7907 New Utrecht Ave Brooklyn NY 11214",
    "addr:housenumber":"7907",
    "addr:postcode":"11214",
    "addr:street":"New Utrecht Ave",
    "iso:country":"US",
    "sg:address":"7907 New Utrecht Ave",
    "sg:city":"Brooklyn",
    "sg:classifiers":[
        {
            "category":"Social Services",
            "subcategory":"Adult Care",
            "type":"Services"
        }
    ],
    "sg:phone":"+1 718 621 7960",
    "sg:postcode":"11214",
    "sg:province":"NY",
    "sg:tags":[
        "organization",
        "senior",
        "citizen"
    ],
    "wof:name":"Home Crest Community Svc",
    "wof:placetype":"venue"
},
  "geometry": {"coordinates":[-74.000991,40.611848],"type":"Point"}
}