{
  "type": "Feature",
  "properties": {
    "iso:country":"US",
    "sg:address":"1940 Clover St",
    "sg:city":"Rochester",
    "sg:classifiers":[
        {
            "category":"Manufacturing",
            "subcategory":"Signs",
            "type":"Manufacturing & Wholesale Goods"
        }
    ],
    "sg:phone":"+1   ",
    "sg:postcode":"14618",
    "sg:province":"NY",
    "sg:tags":[
        "specialty",
        "mfg"
    ],
    "wof:name":"Signs of Light",
    "wof:placetype":"venue"
},
  "geometry": {"coordinates":[-77.548056,43.11879],"type":"Point"}
}