{
  "type": "Feature",
  "properties": {
    "addr:full":"140 W 32 St New York NY 10001",
    "addr:housenumber":"140",
    "addr:postcode":"10001",
    "addr:street":"W 32 St",
    "iso:country":"US",
    "sg:address":"140 W 32 St",
    "sg:city":"New York",
    "sg:classifiers":[
        {
            "category":"Retail",
            "subcategory":"Portrait Studio",
            "type":"Services"
        }
    ],
    "sg:phone":"+1 212 967 6964",
    "sg:postcode":"10001",
    "sg:province":"NY",
    "sg:tags":[
        "photographer"
    ],
    "sg:website":"www.davidbeyda.com",
    "wof:name":"David Beyda Studio",
    "wof:placetype":"venue"
},
  "geometry": {"coordinates":[-73.990718,40.749152],"type":"Point"}
}