{
  "type": "Feature",
  "properties": {
    "iso:country":"US",
    "sg:address":"7802 Metropolitan Ave",
    "sg:city":"Middle Village",
    "sg:classifiers":[
        {
            "category":"Banks & Credit Unions",
            "subcategory":"Bank",
            "type":"Services"
        }
    ],
    "sg:phone":"+1 718 894 1038",
    "sg:postcode":"11379",
    "sg:province":"NY",
    "sg:website":"www.chase.com",
    "wof:name":"Chase",
    "wof:placetype":"venue"
},
  "geometry": {"coordinates":[-73.875254,40.713003],"type":"Point"}
}