{
  "type": "Feature",
  "properties": {
    "iso:country":"US",
    "sg:address":"1845 Jacob Rd",
    "sg:city":"Cortlandt Manor",
    "sg:classifiers":[
        {
            "category":"Autos & Motor Vehicles",
            "subcategory":"Automobile Sales",
            "type":"Retail Goods"
        }
    ],
    "sg:phone":"+1 914 965 0600",
    "sg:postcode":"10567",
    "sg:province":"NY",
    "sg:tags":[
        "car",
        "dealer"
    ],
    "wof:name":"Vision Auto Sales",
    "wof:placetype":"venue"
},
  "geometry": {"coordinates":[-73.851069,41.278716],"type":"Point"}
}