{
  "type": "Feature",
  "properties": {
    "addr:full":"87 Mill Pond Ln Bay Shore NY 11706",
    "addr:housenumber":"87",
    "addr:postcode":"11706",
    "addr:street":"Mill Pond Ln",
    "iso:country":"US",
    "sg:address":"87 Mill Pond Ln",
    "sg:city":"Bay Shore",
    "sg:classifiers":[
        {
            "category":"Organizations",
            "subcategory":"Religious Organization",
            "type":"Services"
        }
    ],
    "sg:phone":"+1 631 968 1363",
    "sg:postcode":"11706",
    "sg:province":"NY",
    "sg:tags":[
        "clergy"
    ],
    "wof:name":"Bertha O Stevenson",
    "wof:placetype":"venue"
},
  "geometry": {"coordinates":[-73.244738,40.727267],"type":"Point"}
}