{
  "type": "Feature",
  "properties": {
    "addr:full":"2410 White Plains Rd Bronx NY 10467",
    "addr:housenumber":"2410",
    "addr:postcode":"10467",
    "addr:street":"White Plains Rd",
    "iso:country":"US",
    "sg:address":"2410 White Plains Rd",
    "sg:city":"Bronx",
    "sg:classifiers":[
        {
            "category":"Building & Trades",
            "subcategory":"Construction",
            "type":"Services"
        }
    ],
    "sg:phone":"+1 347 920 5688",
    "sg:postcode":"10467",
    "sg:province":"NY",
    "sg:tags":[
        "contractor"
    ],
    "sg:website":"www.kamconstruction.com",
    "wof:name":"Kam Construction",
    "wof:placetype":"venue"
},
  "geometry": {"coordinates":[-73.867334,40.861537],"type":"Point"}
}