{
  "type": "Feature",
  "properties": {
    "addr:full":"14 Bay Shore Ave Bay Shore NY 11706",
    "addr:housenumber":"14",
    "addr:postcode":"11706",
    "addr:street":"Bay Shore Ave",
    "iso:country":"US",
    "sg:address":"14 Bay Shore Ave",
    "sg:city":"Bay Shore",
    "sg:classifiers":[
        {
            "category":"Utilities",
            "subcategory":"Natural Gas",
            "type":"Services"
        }
    ],
    "sg:phone":"+1 631 666 6484",
    "sg:postcode":"11706",
    "sg:province":"NY",
    "sg:tags":[
        "company"
    ],
    "wof:name":"Gas Dynamics Inc",
    "wof:placetype":"venue"
},
  "geometry": {"coordinates":[-73.24706,40.724171],"type":"Point"}
}