{
  "type": "Feature",
  "properties": {
    "addr:full":"65 Saint Felix St Brooklyn NY 11217",
    "addr:housenumber":"65",
    "addr:postcode":"11217",
    "addr:street":"Saint Felix St",
    "iso:country":"US",
    "sg:address":"65 Saint Felix St",
    "sg:city":"Brooklyn",
    "sg:classifiers":[
        {
            "category":"Real Estate",
            "subcategory":"Architect",
            "type":"Services"
        }
    ],
    "sg:phone":"+1 718 596 2379",
    "sg:postcode":"11217",
    "sg:province":"NY",
    "wof:name":"Della Paolera",
    "wof:placetype":"venue"
},
  "geometry": {"coordinates":[-73.977501,40.687801],"type":"Point"}
}