{
  "type": "Feature",
  "properties": {
    "addr:full":"7 Tivoli St Albany NY 12207",
    "addr:housenumber":"7",
    "addr:postcode":"12207",
    "addr:street":"Tivoli St",
    "iso:country":"US",
    "sg:address":"7 Tivoli St",
    "sg:city":"Albany",
    "sg:classifiers":[
        {
            "category":"Freight",
            "type":"Transportation"
        }
    ],
    "sg:phone":"+1 518 463 5525",
    "sg:postcode":"12207",
    "sg:province":"NY",
    "sg:tags":[
        "mover"
    ],
    "sg:website":"www.arnoff.com",
    "wof:name":"North American Van Lines",
    "wof:placetype":"venue"
},
  "geometry": {"coordinates":[-73.745673,42.664763],"type":"Point"}
}