{
  "type": "Feature",
  "properties": {
    "iso:country":"US",
    "sg:address":"4521 Lewis Rd",
    "sg:city":"Walworth",
    "sg:classifiers":[
        {
            "category":"Professional",
            "subcategory":"Lawyer & Legal Services",
            "type":"Services"
        }
    ],
    "sg:phone":"+1 315 524 6862",
    "sg:postcode":"14568",
    "sg:province":"NY",
    "sg:tags":[
        "attorney"
    ],
    "wof:name":"Mark F Viencek",
    "wof:placetype":"venue"
},
  "geometry": {"coordinates":[-77.30826500000001,43.174965],"type":"Point"}
}