{
  "type": "Feature",
  "properties": {
    "iso:country":"US",
    "sg:address":"741 Peconic St",
    "sg:city":"Ronkonkoma",
    "sg:classifiers":[
        {
            "category":"Building & Trades",
            "subcategory":"Landscaping Services",
            "type":"Services"
        }
    ],
    "sg:phone":"+1 631 981 8733",
    "sg:postcode":"11779",
    "sg:province":"NY",
    "sg:tags":[
        "tree"
    ],
    "wof:name":"Complete Tree Service",
    "wof:placetype":"venue"
},
  "geometry": {"coordinates":[-73.12386600000001,40.800856],"type":"Point"}
}