{
  "type": "Feature",
  "properties": {
    "addr:full":"6312 Northern Blvd East Norwich NY 11732",
    "addr:housenumber":"6312",
    "addr:postcode":"11732",
    "addr:street":"Northern Blvd East",
    "iso:country":"US",
    "sg:address":"6312 Northern Blvd",
    "sg:city":"East Norwich",
    "sg:classifiers":[
        {
            "category":"Retail",
            "subcategory":"Laundry & Dry Cleaning",
            "type":"Services"
        }
    ],
    "sg:phone":"+1 516 624 6055",
    "sg:postcode":"11732",
    "sg:province":"NY",
    "sg:tags":[
        "cleaners",
        "plant",
        "drycleaning"
    ],
    "wof:name":"Marcello's Cleaners Inc",
    "wof:placetype":"venue"
},
  "geometry": {"coordinates":[-73.532267,40.842276],"type":"Point"}
}