{
  "type": "Feature",
  "properties": {
    "iso:country":"US",
    "sg:address":"415 Meacham Ave",
    "sg:city":"Elmont",
    "sg:classifiers":[
        {
            "category":"Building & Trades",
            "subcategory":"Construction",
            "type":"Services"
        }
    ],
    "sg:phone":"+1 516 488 3883",
    "sg:postcode":"11003",
    "sg:province":"NY",
    "sg:tags":[
        "contractor"
    ],
    "wof:name":"L J C Dismantling Corp",
    "wof:placetype":"venue"
},
  "geometry": {"coordinates":[-73.690697,40.698399],"type":"Point"}
}