{
  "type": "Feature",
  "properties": {
    "addr:full":"458 Rodney St Brooklyn NY 11211",
    "addr:housenumber":"458",
    "addr:postcode":"11211",
    "addr:street":"Rodney St",
    "iso:country":"US",
    "sg:address":"458 Rodney St",
    "sg:city":"Brooklyn",
    "sg:phone":"+1 718 388 9637",
    "sg:postcode":"11211",
    "sg:province":"NY",
    "sg:tags":[
        "equipment",
        "supply"
    ],
    "wof:name":"American Circle Inc",
    "wof:placetype":"venue"
},
  "geometry": {"coordinates":[-73.95322899999999,40.713942],"type":"Point"}
}