{
  "type": "Feature",
  "properties": {
    "iso:country":"US",
    "sg:address":"321 E Albany St",
    "sg:city":"Herkimer",
    "sg:classifiers":[
        {
            "category":"Banks & Credit Unions",
            "subcategory":"Investment Brokerage",
            "type":"Services"
        },
        {
            "category":"Shopping",
            "subcategory":"Computers & Home Electronics",
            "type":"Retail Goods"
        }
    ],
    "sg:phone":"+1 315 866 6290",
    "sg:postcode":"13350",
    "sg:province":"NY",
    "sg:tags":[
        "dvd",
        "video",
        "tape",
        "sale",
        "dvds-rental"
    ],
    "wof:name":"Blockbuster",
    "wof:placetype":"venue"
},
  "geometry": {"coordinates":[-74.97829900000001,43.028777],"type":"Point"}
}