{
  "type": "Feature",
  "properties": {
    "addr:full":"1076 Washington Ave Bronx NY 10456",
    "addr:housenumber":"1076",
    "addr:postcode":"10456",
    "addr:street":"Washington Ave",
    "iso:country":"US",
    "sg:address":"1076 Washington Ave",
    "sg:city":"Bronx",
    "sg:classifiers":[
        {
            "category":"Organizations",
            "subcategory":"Religious Organization",
            "type":"Services"
        }
    ],
    "sg:phone":"+1 718 585 6983",
    "sg:postcode":"10456",
    "sg:province":"NY",
    "sg:tags":[
        "church"
    ],
    "wof:name":"Trinity United Methodist Ch",
    "wof:placetype":"venue"
},
  "geometry": {"coordinates":[-73.908939,40.827229],"type":"Point"}
}