{
  "type": "Feature",
  "properties": {
    "iso:country":"US",
    "sg:address":"935 Hayes St",
    "sg:city":"Baldwin",
    "sg:classifiers":[
        {
            "category":"Professional",
            "subcategory":"Secretarial Services",
            "type":"Services"
        }
    ],
    "sg:phone":"+1 516 546 8338",
    "sg:postcode":"11510",
    "sg:province":"NY",
    "sg:tags":[
        "manuscript"
    ],
    "wof:name":"Baldwin Literary Svc",
    "wof:placetype":"venue"
},
  "geometry": {"coordinates":[-73.60501499999999,40.633231],"type":"Point"}
}