{
  "type": "Feature",
  "properties": {
    "iso:country":"US",
    "sg:address":"807 Holt Rd",
    "sg:city":"Webster",
    "sg:classifiers":[
        {
            "category":"Retail",
            "subcategory":"Auto Repair",
            "type":"Services"
        }
    ],
    "sg:phone":"+1 585 872 4649",
    "sg:postcode":"14580",
    "sg:province":"NY",
    "sg:tags":[
        "repairing",
        "automobile"
    ],
    "wof:name":"Jos C Marlowe Svc",
    "wof:placetype":"venue"
},
  "geometry": {"coordinates":[-77.446549,43.218094],"type":"Point"}
}