{
  "type": "Feature",
  "properties": {
    "addr:full":"2750 Stillwell Ave Brooklyn NY 11224",
    "addr:housenumber":"2750",
    "addr:postcode":"11224",
    "addr:street":"Stillwell Ave",
    "iso:country":"US",
    "sg:address":"2750 Stillwell Ave",
    "sg:city":"Brooklyn",
    "sg:classifiers":[
        {
            "category":"Retail",
            "subcategory":"Auto Repair",
            "type":"Services"
        }
    ],
    "sg:phone":"+1 718 714 5059",
    "sg:postcode":"11224",
    "sg:province":"NY",
    "sg:tags":[
        "body",
        "shop"
    ],
    "wof:name":"Brighton Enterprises Inc",
    "wof:placetype":"venue"
},
  "geometry": {"coordinates":[-73.982201,40.579899],"type":"Point"}
}