{
  "type": "Feature",
  "properties": {
    "iso:country":"US",
    "sg:address":"520 8th Ave",
    "sg:city":"New York",
    "sg:classifiers":[
        {
            "category":"Arts & Performance",
            "subcategory":"Arts Center",
            "type":"Entertainment"
        }
    ],
    "sg:phone":"+1 212 971 4862",
    "sg:postcode":"10018",
    "sg:province":"NY",
    "sg:tags":[
        "performing"
    ],
    "sg:website":"www.ma-yitheatre.org",
    "wof:name":"Ma-Yi Theater Company",
    "wof:placetype":"venue"
},
  "geometry": {"coordinates":[-73.99184700000001,40.753557],"type":"Point"}
}