{
  "type": "Feature",
  "properties": {
    "iso:country":"US",
    "sg:address":"102 Lincoln Park Dr",
    "sg:city":"Syracuse",
    "sg:classifiers":[
        {
            "category":"Government",
            "subcategory":"Office",
            "type":"Public Place"
        }
    ],
    "sg:phone":"+1 315 475 7406",
    "sg:postcode":"13203",
    "sg:province":"NY",
    "sg:tags":[
        "state",
        "resource"
    ],
    "wof:name":"Children & Family Svc Office",
    "wof:placetype":"venue"
},
  "geometry": {"coordinates":[-76.130573,43.057803],"type":"Point"}
}