{
  "type": "Feature",
  "properties": {
    "addr:full":"200 W 40 St New York NY 10018",
    "addr:housenumber":"200",
    "addr:postcode":"10018",
    "addr:street":"W 40 St",
    "iso:country":"US",
    "sg:address":"200 W 40 St",
    "sg:city":"New York",
    "sg:classifiers":[
        {
            "category":"Shopping",
            "type":"Retail Goods"
        }
    ],
    "sg:phone":"+1   ",
    "sg:postcode":"10018",
    "sg:province":"NY",
    "sg:tags":[
        "cell",
        "phone"
    ],
    "wof:name":"H & H Cellular",
    "wof:placetype":"venue"
},
  "geometry": {"coordinates":[-73.990726,40.75595],"type":"Point"}
}