{
  "type": "Feature",
  "properties": {
    "addr:full":"675 Ave of the Americas New York NY 10010",
    "addr:housenumber":"675",
    "addr:postcode":"10010",
    "addr:street":"Ave Of The Americas",
    "iso:country":"US",
    "sg:address":"675 Ave of the Americas",
    "sg:city":"New York",
    "sg:classifiers":[
        {
            "category":"Shopping",
            "subcategory":"Clothing, Apparel, & Fashions",
            "type":"Retail Goods"
        }
    ],
    "sg:phone":"+1 212 206 4200",
    "sg:postcode":"10010",
    "sg:province":"NY",
    "wof:name":"Forth & Towne",
    "wof:placetype":"venue"
},
  "geometry": {"coordinates":[-73.993292,40.742233],"type":"Point"}
}