{
  "type": "Feature",
  "properties": {
    "addr:full":"142 Schwenk Dr Kingston NY 12401",
    "addr:housenumber":"142",
    "addr:postcode":"12401",
    "addr:street":"Schwenk Dr",
    "iso:country":"US",
    "sg:address":"142 Schwenk Dr",
    "sg:city":"Kingston",
    "sg:classifiers":[
        {
            "category":"Organizations",
            "subcategory":"Community Association",
            "type":"Services"
        }
    ],
    "sg:phone":"+1 845 340 7465",
    "sg:postcode":"12401",
    "sg:province":"NY",
    "sg:tags":[
        "club"
    ],
    "wof:name":"Pink Elephant Club",
    "wof:placetype":"venue"
},
  "geometry": {"coordinates":[-74.02301,41.936721],"type":"Point"}
}