{
  "type": "Feature",
  "properties": {
    "addr:full":"4539 216th St Bayside NY 11361",
    "addr:housenumber":"4539",
    "addr:postcode":"11361",
    "addr:street":"216Th St",
    "iso:country":"US",
    "sg:address":"4539 216th St",
    "sg:city":"Bayside",
    "sg:classifiers":[
        {
            "category":"Retail",
            "subcategory":"Auto Rental",
            "type":"Services"
        }
    ],
    "sg:phone":"+1 718 423 1213",
    "sg:postcode":"11361",
    "sg:province":"NY",
    "sg:tags":[
        "limousine"
    ],
    "wof:name":"Thoroughbred Luxury Limo Service",
    "wof:placetype":"venue"
},
  "geometry": {"coordinates":[-73.76561599999999,40.760506],"type":"Point"}
}