{
  "type": "Feature",
  "properties": {
    "addr:full":"6101 23rd Ave Brooklyn NY 11204",
    "addr:housenumber":"6101",
    "addr:postcode":"11204",
    "addr:street":"23Rd Ave",
    "iso:country":"US",
    "sg:address":"6101 23rd Ave",
    "sg:city":"Brooklyn",
    "sg:classifiers":[
        {
            "category":"Professional",
            "subcategory":"Accounting & Tax Preparation",
            "type":"Services"
        }
    ],
    "sg:phone":"+1 212 752 1500",
    "sg:postcode":"11204",
    "sg:province":"NY",
    "sg:tags":[
        "designer",
        "for",
        "work",
        "fashion",
        "administrative",
        "italian"
    ],
    "wof:name":"Fashion Systems USA Ltd",
    "wof:placetype":"venue"
},
  "geometry": {"coordinates":[-73.977408,40.614218],"type":"Point"}
}