{
  "type": "Feature",
  "properties": {
    "iso:country":"US",
    "sg:address":"133 Main St",
    "sg:city":"Corinth",
    "sg:classifiers":[
        {
            "category":"Restaurant",
            "type":"Food & Drink"
        }
    ],
    "sg:phone":"+1 518 654 6800",
    "sg:postcode":"12822",
    "sg:province":"NY",
    "sg:tags":[
        "eating"
    ],
    "wof:name":"Jack's Place",
    "wof:placetype":"venue"
},
  "geometry": {"coordinates":[-73.833535,43.247261],"type":"Point"}
}