{
  "type": "Feature",
  "properties": {
    "addr:full":"89 Garden St Westbury NY 11590",
    "addr:housenumber":"89",
    "addr:postcode":"11590",
    "addr:street":"Garden St",
    "iso:country":"US",
    "sg:address":"89 Garden St",
    "sg:city":"Westbury",
    "sg:classifiers":[
        {
            "category":"Shopping",
            "type":"Retail Goods"
        }
    ],
    "sg:phone":"+1   ",
    "sg:postcode":"11590",
    "sg:province":"NY",
    "sg:tags":[
        "equipment",
        "medical"
    ],
    "wof:name":"Progressive Surgical Products",
    "wof:placetype":"venue"
},
  "geometry": {"coordinates":[-73.56676299999999,40.756777],"type":"Point"}
}