{
  "type": "Feature",
  "properties": {
    "iso:country":"US",
    "sg:address":"136 Main Ave",
    "sg:city":"Wyandanch",
    "sg:classifiers":[
        {
            "category":"Building & Trades",
            "subcategory":"Landscaping Services",
            "type":"Services"
        }
    ],
    "sg:phone":"+1 631 643 1213",
    "sg:postcode":"11798",
    "sg:province":"NY",
    "wof:name":"Wheatley Hollow Ldscpg Design",
    "wof:placetype":"venue"
},
  "geometry": {"coordinates":[-73.368365,40.757998],"type":"Point"}
}