{
  "type": "Feature",
  "properties": {
    "addr:full":"545 8 Ave New York NY 10018",
    "addr:housenumber":"545",
    "addr:postcode":"10018",
    "addr:street":"8 Ave",
    "iso:country":"US",
    "sg:address":"545 8 Ave",
    "sg:city":"New York",
    "sg:classifiers":[
        {
            "category":"Food & Beverages",
            "subcategory":"Bakery",
            "type":"Retail Goods"
        }
    ],
    "sg:phone":"+1 212 946 5000",
    "sg:postcode":"10018",
    "sg:province":"NY",
    "sg:tags":[
        "baker"
    ],
    "wof:name":"Icing On The Cake",
    "wof:placetype":"venue"
},
  "geometry": {"coordinates":[-73.99252799999999,40.753474],"type":"Point"}
}