{
  "type": "Feature",
  "properties": {
    "addr:full":"215 Main St Binghamton NY 13905",
    "addr:housenumber":"215",
    "addr:postcode":"13905",
    "addr:street":"Main St",
    "iso:country":"US",
    "sg:address":"215 Main St",
    "sg:city":"Binghamton",
    "sg:classifiers":[
        {
            "category":"Banks & Credit Unions",
            "subcategory":"Bank",
            "type":"Services"
        }
    ],
    "sg:phone":"+1 607 766 9450",
    "sg:postcode":"13905",
    "sg:province":"NY",
    "sg:tags":[
        "cashing",
        "check"
    ],
    "wof:name":"Universal Check Cashing",
    "wof:placetype":"venue"
},
  "geometry": {"coordinates":[-75.935125,42.105931],"type":"Point"}
}