{
  "type": "Feature",
  "properties": {
    "iso:country":"US",
    "sg:address":"6359 S Stockton-Cassadaga Rd",
    "sg:city":"Sinclairville",
    "sg:classifiers":[
        {
            "category":"Retail",
            "subcategory":"Repair Shop",
            "type":"Services"
        },
        {
            "category":"Building & Trades",
            "subcategory":"Plumbing",
            "type":"Services"
        }
    ],
    "sg:phone":"+1 716 962 4647",
    "sg:postcode":"14782",
    "sg:province":"NY",
    "sg:tags":[
        "repairing",
        "contractor",
        "electrical",
        "system",
        "heating"
    ],
    "wof:name":"Bill's Heating & Washer Repair",
    "wof:placetype":"venue"
},
  "geometry": {"coordinates":[-79.315681,42.274768],"type":"Point"}
}