{
  "type": "Feature",
  "properties": {
    "iso:country":"US",
    "sg:address":"301 Myron Rd",
    "sg:city":"Syracuse",
    "sg:classifiers":[
        {
            "category":"Professional",
            "subcategory":"Computer Services",
            "type":"Services"
        }
    ],
    "sg:phone":"+1 315 488 8572",
    "sg:postcode":"13219",
    "sg:province":"NY",
    "sg:tags":[
        "programing",
        "custom"
    ],
    "wof:name":"Counterpoint Systems Inc",
    "wof:placetype":"venue"
},
  "geometry": {"coordinates":[-76.23312199999999,43.051311],"type":"Point"}
}