{
  "type": "Feature",
  "properties": {
    "iso:country":"US",
    "sg:address":"3 Colonial Dr",
    "sg:city":"Wappingers Falls",
    "sg:classifiers":[
        {
            "category":"Banks & Credit Unions",
            "subcategory":"Bank",
            "type":"Services"
        }
    ],
    "sg:phone":"+1 845 298 0149",
    "sg:postcode":"12590",
    "sg:province":"NY",
    "sg:tags":[
        "federal",
        "agency"
    ],
    "wof:name":"Suppova Int L",
    "wof:placetype":"venue"
},
  "geometry": {"coordinates":[-73.911945,41.599987],"type":"Point"}
}