{
  "type": "Feature",
  "properties": {
    "addr:full":"1417 Grand Concourse Bronx NY 10452",
    "addr:housenumber":"1417",
    "addr:postcode":"10452",
    "addr:street":"Grand Concourse",
    "iso:country":"US",
    "sg:address":"1417 Grand Concourse",
    "sg:city":"Bronx",
    "sg:classifiers":[
        {
            "category":"Professional",
            "subcategory":"Management & Consulting",
            "type":"Services"
        },
        {
            "category":"Real Estate",
            "subcategory":"Real Estate Agent",
            "type":"Services"
        }
    ],
    "sg:phone":"+1 718 293 1788",
    "sg:postcode":"10452",
    "sg:province":"NY",
    "sg:tags":[
        "fuel",
        "property"
    ],
    "wof:name":"Chp Management Corp",
    "wof:placetype":"venue"
},
  "geometry": {"coordinates":[-73.913696,40.839199],"type":"Point"}
}