{
  "type": "Feature",
  "properties": {
    "iso:country":"US",
    "sg:address":"5174 S Livonia Rd",
    "sg:city":"Livonia",
    "sg:classifiers":[
        {
            "category":"Building & Trades",
            "subcategory":"Construction",
            "type":"Services"
        }
    ],
    "sg:phone":"+1 585 346 6708",
    "sg:postcode":"14487",
    "sg:province":"NY",
    "sg:tags":[
        "carpentry",
        "contractor"
    ],
    "wof:name":"Frank L Noll",
    "wof:placetype":"venue"
},
  "geometry": {"coordinates":[-77.671209,42.767831],"type":"Point"}
}