{
  "type": "Feature",
  "properties": {
    "addr:full":"437 Rte 25A St James NY 11780",
    "addr:housenumber":"437",
    "addr:postcode":"11780",
    "addr:street":"Rte 25A St",
    "iso:country":"US",
    "sg:address":"437 Rte 25A",
    "sg:city":"St James",
    "sg:classifiers":[
        {
            "category":"Shopping",
            "subcategory":"Clothing, Apparel, & Fashions",
            "type":"Retail Goods"
        }
    ],
    "sg:phone":"+1 631 584 0070",
    "sg:postcode":"11780",
    "sg:province":"NY",
    "sg:tags":[
        "dancing",
        "supply"
    ],
    "wof:name":"Emily's Other Place Inc",
    "wof:placetype":"venue"
},
  "geometry": {"coordinates":[-73.16942299999999,40.87836],"type":"Point"}
}