{
  "type": "Feature",
  "properties": {
    "addr:full":"2108 Northern Blvd Manhasset NY 11030",
    "addr:housenumber":"2108",
    "addr:postcode":"11030",
    "addr:street":"Northern Blvd",
    "iso:country":"US",
    "sg:address":"2108 Northern Blvd",
    "sg:city":"Manhasset",
    "sg:classifiers":[
        {
            "category":"Shopping",
            "subcategory":"Jewelry",
            "type":"Retail Goods"
        }
    ],
    "sg:phone":"+1 516 869 0009",
    "sg:postcode":"11030",
    "sg:province":"NY",
    "sg:tags":[
        "equipment",
        "silverware"
    ],
    "wof:name":"Christofle Pavillion",
    "wof:placetype":"venue"
},
  "geometry": {"coordinates":[-73.66940099999999,40.796966],"type":"Point"}
}