{
  "type": "Feature",
  "properties": {
    "addr:full":"15 Michael Pl Nesconset NY 11767",
    "addr:housenumber":"15",
    "addr:postcode":"11767",
    "addr:street":"Michael Pl",
    "iso:country":"US",
    "sg:address":"15 Michael Pl",
    "sg:city":"Nesconset",
    "sg:classifiers":[
        {
            "category":"Professional",
            "subcategory":"Management & Consulting",
            "type":"Services"
        }
    ],
    "sg:phone":"+1 631 366 4643",
    "sg:postcode":"11767",
    "sg:province":"NY",
    "wof:name":"Michael Place Management Inc",
    "wof:placetype":"venue"
},
  "geometry": {"coordinates":[-73.148903,40.855031],"type":"Point"}
}