{
  "type": "Feature",
  "properties": {
    "iso:country":"US",
    "sg:address":"18 N Main St",
    "sg:city":"Pittsford",
    "sg:classifiers":[
        {
            "category":"Health Services",
            "subcategory":"Health Practitioner",
            "type":"Services"
        }
    ],
    "sg:phone":"+1   ",
    "sg:postcode":"14534",
    "sg:province":"NY",
    "wof:name":"Joel Latner",
    "wof:placetype":"venue"
},
  "geometry": {"coordinates":[-77.51482,43.091477],"type":"Point"}
}