{
  "type": "Feature",
  "properties": {
    "addr:full":"69-29 Queens Blvd Woodside NY 11377",
    "addr:housenumber":"69-29",
    "addr:postcode":"11377",
    "addr:street":"Queens Blvd",
    "iso:country":"US",
    "sg:address":"69-29 Queens Blvd",
    "sg:city":"Woodside",
    "sg:classifiers":[
        {
            "category":"Restaurant",
            "type":"Food & Drink"
        }
    ],
    "sg:phone":"+1 718 898 3538",
    "sg:postcode":"11377",
    "sg:province":"NY",
    "sg:tags":[
        "mexican"
    ],
    "wof:name":"Camilo's Coffee Shop",
    "wof:placetype":"venue"
},
  "geometry": {"coordinates":[-73.895511,40.740379],"type":"Point"}
}