{
  "type": "Feature",
  "properties": {
    "iso:country":"US",
    "sg:address":"30 Liftbridge Ln E",
    "sg:city":"Fairport",
    "sg:classifiers":[
        {
            "category":"Professional",
            "subcategory":"Computer Services",
            "type":"Services"
        }
    ],
    "sg:phone":"+1 585 377 7000",
    "sg:postcode":"14450",
    "sg:province":"NY",
    "sg:tags":[
        "design",
        "integrated",
        "system"
    ],
    "wof:name":"Solunet Storage",
    "wof:placetype":"venue"
},
  "geometry": {"coordinates":[-77.440963,43.102132],"type":"Point"}
}