{
  "type": "Feature",
  "properties": {
    "iso:country":"US",
    "sg:address":"1400 Old Country Rd Ste 102",
    "sg:city":"Westbury",
    "sg:classifiers":[
        {
            "category":"Professional",
            "subcategory":"Lawyer & Legal Services",
            "type":"Services"
        }
    ],
    "sg:phone":"+1 516 333 2006",
    "sg:postcode":"11590",
    "sg:province":"NY",
    "wof:name":"Law Offices Of Charles Ferzola",
    "wof:placetype":"venue"
},
  "geometry": {"coordinates":[-73.59607800000001,40.746384],"type":"Point"}
}