{
  "type": "Feature",
  "properties": {
    "addr:full":"1103 1st Avenue New York NY 10021",
    "addr:housenumber":"1103",
    "addr:postcode":"10021",
    "addr:street":"1St Avenue",
    "iso:country":"US",
    "sg:address":"1103 1st Avenue",
    "sg:city":"New York",
    "sg:classifiers":[
        {
            "category":"Restaurant",
            "type":"Food & Drink"
        }
    ],
    "sg:phone":"+1 212 308 8828",
    "sg:postcode":"10021",
    "sg:province":"NY",
    "wof:name":"Nagasaki Sushi",
    "wof:placetype":"venue"
},
  "geometry": {"coordinates":[-73.961339,40.760501],"type":"Point"}
}