{
  "type": "Feature",
  "properties": {
    "iso:country":"US",
    "sg:address":"876 Arno Dr",
    "sg:city":"Castletn On Hdsn",
    "sg:classifiers":[
        {
            "category":"Home & Garden",
            "subcategory":"Building Materials",
            "type":"Retail Goods"
        }
    ],
    "sg:phone":"+1 518 732 7479",
    "sg:postcode":"12033",
    "sg:province":"NY",
    "sg:tags":[
        "glass",
        "window",
        "plate"
    ],
    "wof:name":"All In Glass Studios",
    "wof:placetype":"venue"
},
  "geometry": {"coordinates":[-73.707481,42.496035],"type":"Point"}
}