{
  "type": "Feature",
  "properties": {
    "addr:full":"140 Cornell St Ithaca NY 14850",
    "addr:housenumber":"140",
    "addr:postcode":"14850",
    "addr:street":"Cornell St",
    "iso:country":"US",
    "sg:address":"140 Cornell St",
    "sg:city":"Ithaca",
    "sg:classifiers":[
        {
            "category":"Professional",
            "subcategory":"Management & Consulting",
            "type":"Services"
        }
    ],
    "sg:phone":"+1 607 255 6222",
    "sg:postcode":"14850",
    "sg:province":"NY",
    "sg:tags":[
        "support",
        "facility"
    ],
    "wof:name":"East Asia Program",
    "wof:placetype":"venue"
},
  "geometry": {"coordinates":[-76.477655,42.438472],"type":"Point"}
}