{
  "type": "Feature",
  "properties": {
    "addr:full":"135 Summerfield St Scarsdale NY 10583",
    "addr:housenumber":"135",
    "addr:postcode":"10583",
    "addr:street":"Summerfield St",
    "iso:country":"US",
    "sg:address":"135 Summerfield St",
    "sg:city":"Scarsdale",
    "sg:classifiers":[
        {
            "category":"Food & Beverages",
            "subcategory":"Liquor & Beverages",
            "type":"Retail Goods"
        },
        {
            "category":"Wholesale",
            "subcategory":"Beer",
            "type":"Manufacturing & Wholesale Goods"
        }
    ],
    "sg:phone":"+1 914 725 3131",
    "sg:postcode":"10583",
    "sg:province":"NY",
    "sg:tags":[
        "ale"
    ],
    "wof:name":"Sal's Beverage Depot",
    "wof:placetype":"venue"
},
  "geometry": {"coordinates":[-73.80574,40.9778],"type":"Point"}
}