{
  "type": "Feature",
  "properties": {
    "addr:full":"135 Lookout Cir Syracuse NY 13209",
    "addr:housenumber":"135",
    "addr:postcode":"13209",
    "addr:street":"Lookout Cir",
    "iso:country":"US",
    "sg:address":"135 Lookout Cir",
    "sg:city":"Syracuse",
    "sg:classifiers":[
        {
            "category":"Shopping",
            "type":"Retail Goods"
        }
    ],
    "sg:phone":"+1 315 488 6876",
    "sg:postcode":"13209",
    "sg:province":"NY",
    "sg:tags":[
        "hearing",
        "equipment",
        "supply",
        "impaired"
    ],
    "wof:name":"New York Hearing Ctr",
    "wof:placetype":"venue"
},
  "geometry": {"coordinates":[-76.243133,43.058361],"type":"Point"}
}