{
  "type": "Feature",
  "properties": {
    "iso:country":"US",
    "sg:address":"6605 Myrtle Ave",
    "sg:city":"Glendale",
    "sg:classifiers":[
        {
            "category":"Health Services",
            "subcategory":"Health Practitioner",
            "type":"Services"
        }
    ],
    "sg:phone":"+1 347 335 0479",
    "sg:postcode":"11385",
    "sg:province":"NY",
    "sg:tags":[
        "therapy",
        "physical"
    ],
    "wof:name":"Top Care Physical Therapy Pc",
    "wof:placetype":"venue"
},
  "geometry": {"coordinates":[-73.888137,40.701476],"type":"Point"}
}