{
  "type": "Feature",
  "properties": {
    "addr:full":"19 W 44th St New York NY 10036",
    "addr:housenumber":"19",
    "addr:postcode":"10036",
    "addr:street":"W 44Th St",
    "iso:country":"US",
    "sg:address":"19 W 44th St",
    "sg:city":"New York",
    "sg:classifiers":[
        {
            "category":"Professional",
            "subcategory":"Management & Consulting",
            "type":"Services"
        }
    ],
    "sg:phone":"+1 212 354 4530",
    "sg:postcode":"10036",
    "sg:province":"NY",
    "sg:tags":[
        "consultant",
        "benefit",
        "business"
    ],
    "sg:website":"www.benconsys.com",
    "wof:name":"Benefit Concepts Systems Inc",
    "wof:placetype":"venue"
},
  "geometry": {"coordinates":[-73.982681,40.755955],"type":"Point"}
}