{
  "type": "Feature",
  "properties": {
    "addr:full":"73 Tulip Rd Mahopac NY 10541",
    "addr:housenumber":"73",
    "addr:postcode":"10541",
    "addr:street":"Tulip Rd",
    "iso:country":"US",
    "sg:address":"73 Tulip Rd",
    "sg:city":"Mahopac",
    "sg:classifiers":[
        {
            "category":"Farming",
            "subcategory":"Farm",
            "type":"Manufacturing & Wholesale Goods"
        }
    ],
    "sg:phone":"+1 845 628 1497",
    "sg:postcode":"10541",
    "sg:province":"NY",
    "wof:name":"Sunshine Farm",
    "wof:placetype":"venue"
},
  "geometry": {"coordinates":[-73.738241,41.365284],"type":"Point"}
}