{
  "type": "Feature",
  "properties": {
    "iso:country":"US",
    "sg:address":"7 Cheddar Ln",
    "sg:city":"New Windsor",
    "sg:classifiers":[
        {
            "category":"Building & Trades",
            "subcategory":"Landscaping Services",
            "type":"Services"
        }
    ],
    "sg:phone":"+1 845 562 9378",
    "sg:postcode":"12553",
    "sg:province":"NY",
    "sg:tags":[
        "landscape"
    ],
    "wof:name":"Cambridge Development Group",
    "wof:placetype":"venue"
},
  "geometry": {"coordinates":[-74.031476,41.459935],"type":"Point"}
}