{
  "type": "Feature",
  "properties": {
    "addr:full":"515 Madison Ave Rm 201 New York NY 10022",
    "addr:housenumber":"515;201",
    "addr:postcode":"10022",
    "addr:street":"Madison Ave Rm",
    "iso:country":"US",
    "sg:address":"515 Madison Ave Rm 201",
    "sg:city":"New York",
    "sg:classifiers":[
        {
            "category":"Shopping",
            "subcategory":"Antiques",
            "type":"Retail Goods"
        }
    ],
    "sg:phone":"+1 212 207 3800",
    "sg:postcode":"10022",
    "sg:province":"NY",
    "wof:name":"Rare Art Inc",
    "wof:placetype":"venue"
},
  "geometry": {"coordinates":[-73.93112600000001,40.814559],"type":"Point"}
}