{
  "type": "Feature",
  "properties": {
    "addr:full":"4552 Bell Blvd Bayside NY 11361",
    "addr:housenumber":"4552",
    "addr:postcode":"11361",
    "addr:street":"Bell Blvd",
    "iso:country":"US",
    "sg:address":"4552 Bell Blvd",
    "sg:city":"Bayside",
    "sg:classifiers":[
        {
            "category":"Real Estate",
            "subcategory":"Real Estate Services",
            "type":"Services"
        },
        {
            "category":"Real Estate",
            "subcategory":"Real Estate Agent",
            "type":"Services"
        }
    ],
    "sg:phone":"+1 718 428 0900",
    "sg:postcode":"11361",
    "sg:province":"NY",
    "sg:tags":[
        "management"
    ],
    "wof:name":"Maymoon Realty Inc",
    "wof:placetype":"venue"
},
  "geometry": {"coordinates":[-73.770523,40.762705],"type":"Point"}
}