{
  "type": "Feature",
  "properties": {
    "iso:country":"US",
    "sg:address":"15 Windmill Ln",
    "sg:city":"Southampton",
    "sg:classifiers":[
        {
            "category":"Banks & Credit Unions",
            "subcategory":"Investment Brokerage",
            "type":"Services"
        }
    ],
    "sg:phone":"+1 631 287 3040",
    "sg:postcode":"11968",
    "sg:province":"NY",
    "sg:tags":[
        "advisory"
    ],
    "wof:name":"McLaren Capitol Advisors Co",
    "wof:placetype":"venue"
},
  "geometry": {"coordinates":[-72.392979,40.885103],"type":"Point"}
}