{
  "type": "Feature",
  "properties": {
    "iso:country":"US",
    "sg:address":"67 Oak St",
    "sg:city":"Binghamton",
    "sg:classifiers":[
        {
            "category":"Health Services",
            "subcategory":"Health Practitioner",
            "type":"Services"
        }
    ],
    "sg:phone":"+1 607 772 9710",
    "sg:postcode":"13905",
    "sg:province":"NY",
    "sg:tags":[
        "psychologist"
    ],
    "wof:name":"Oak Street Psychological Svc",
    "wof:placetype":"venue"
},
  "geometry": {"coordinates":[-75.92076,42.096414],"type":"Point"}
}