{
  "type": "Feature",
  "properties": {
    "addr:full":"920 Wantagh Ave Wantagh NY 11793",
    "addr:housenumber":"920",
    "addr:postcode":"11793",
    "addr:street":"Wantagh Ave",
    "iso:country":"US",
    "sg:address":"920 Wantagh Ave",
    "sg:city":"Wantagh",
    "sg:classifiers":[
        {
            "category":"Retail",
            "subcategory":"Laundry & Dry Cleaning",
            "type":"Services"
        }
    ],
    "sg:phone":"+1 516 735 1389",
    "sg:postcode":"11793",
    "sg:province":"NY",
    "sg:tags":[
        "cleaners"
    ],
    "wof:name":"Wantagh Avenue Cleaners",
    "wof:placetype":"venue"
},
  "geometry": {"coordinates":[-73.50547299999999,40.702175],"type":"Point"}
}