{
  "type": "Feature",
  "properties": {
    "addr:full":"1767 Central Ave Albany NY 12205",
    "addr:housenumber":"1767",
    "addr:postcode":"12205",
    "addr:street":"Central Ave",
    "iso:country":"US",
    "sg:address":"1767 Central Ave",
    "sg:city":"Albany",
    "sg:classifiers":[
        {
            "category":"Restaurant",
            "type":"Food & Drink"
        }
    ],
    "sg:menulink":"http://www.allmenus.com/ny/colonie/148032-subway/menu/",
    "sg:phone":"+1 518 456 8968",
    "sg:postcode":"12205",
    "sg:province":"NY",
    "sg:tags":[
        "american",
        "sandwich"
    ],
    "wof:name":"Subway",
    "wof:placetype":"venue"
},
  "geometry": {"coordinates":[-73.84369100000001,42.727911],"type":"Point"}
}