{
  "type": "Feature",
  "properties": {
    "iso:country":"US",
    "sg:address":"75 E 93 St",
    "sg:city":"New York",
    "sg:classifiers":[
        {
            "category":"Shopping",
            "subcategory":"Books",
            "type":"Retail Goods"
        }
    ],
    "sg:phone":"+1   ",
    "sg:postcode":"10128",
    "sg:province":"NY",
    "sg:tags":[
        "organization",
        "religious"
    ],
    "wof:name":"Synod Bookstore",
    "wof:placetype":"venue"
},
  "geometry": {"coordinates":[-73.954533,40.785022],"type":"Point"}
}