{
  "type": "Feature",
  "properties": {
    "addr:full":"31 N Bridge St Staten Island NY 10309",
    "addr:housenumber":"31",
    "addr:postcode":"10309",
    "addr:street":"N Bridge St",
    "iso:country":"US",
    "sg:address":"31 N Bridge St",
    "sg:city":"Staten Island",
    "sg:classifiers":[
        {
            "category":"Wholesale",
            "subcategory":"Construction Materials",
            "type":"Manufacturing & Wholesale Goods"
        },
        {
            "category":"Building & Trades",
            "subcategory":"Construction",
            "type":"Services"
        }
    ],
    "sg:phone":"+1 718 317 8500",
    "sg:postcode":"10309",
    "sg:province":"NY",
    "sg:tags":[
        "product",
        "supply",
        "ceramic",
        "plumbing",
        "tile",
        "retail"
    ],
    "sg:website":"www.richmondtile.com",
    "wof:name":"Richmond Ceramic Tile",
    "wof:placetype":"venue"
},
  "geometry": {"coordinates":[-74.235116,40.525787],"type":"Point"}
}