{
  "type": "Feature",
  "properties": {
    "iso:country":"US",
    "sg:address":"411 Park Ave",
    "sg:city":"Rochester",
    "sg:classifiers":[
        {
            "category":"Shopping",
            "type":"Retail Goods"
        }
    ],
    "sg:phone":"+1 585 227 6543",
    "sg:postcode":"14607",
    "sg:province":"NY",
    "sg:tags":[
        "assistive",
        "aid",
        "device",
        "merchandise",
        "hearing"
    ],
    "wof:name":"Hart Hearing Center",
    "wof:placetype":"venue"
},
  "geometry": {"coordinates":[-77.584732,43.149387],"type":"Point"}
}