{
  "type": "Feature",
  "properties": {
    "addr:full":"462 Union Ave Brooklyn NY 11211",
    "addr:housenumber":"462",
    "addr:postcode":"11211",
    "addr:street":"Union Ave",
    "iso:country":"US",
    "sg:address":"462 Union Ave",
    "sg:city":"Brooklyn",
    "sg:classifiers":[
        {
            "category":"Bars & Pubs",
            "type":"Food & Drink"
        }
    ],
    "sg:phone":"+1 718 599 4999",
    "sg:postcode":"11211",
    "sg:province":"NY",
    "wof:name":"Macri Park",
    "wof:placetype":"venue"
},
  "geometry": {"coordinates":[-73.951669,40.714221],"type":"Point"}
}