{
  "type": "Feature",
  "properties": {
    "iso:country":"US",
    "sg:address":"485 Iroquois Ct",
    "sg:city":"Suffern",
    "sg:classifiers":[
        {
            "category":"Manufacturing",
            "subcategory":"Textiles",
            "type":"Manufacturing & Wholesale Goods"
        }
    ],
    "sg:phone":"+1   ",
    "sg:postcode":"10901",
    "sg:province":"NY",
    "sg:tags":[
        "mfg",
        "identification",
        "label"
    ],
    "wof:name":"Labelman International Corp",
    "wof:placetype":"venue"
},
  "geometry": {"coordinates":[-74.131376,41.122314],"type":"Point"}
}