{
  "type": "Feature",
  "properties": {
    "iso:country":"US",
    "sg:address":"6609 80th Street",
    "sg:city":"Middle Village",
    "sg:classifiers":[
        {
            "category":"Building & Trades",
            "subcategory":"Locksmith",
            "type":"Services"
        }
    ],
    "sg:phone":"+1 718 898 3242",
    "sg:postcode":"11379",
    "sg:province":"NY",
    "sg:tags":[
        "key"
    ],
    "wof:name":"Always Available 24 Hour Middle Village 7 Day Emergency Locksmit",
    "wof:placetype":"venue"
},
  "geometry": {"coordinates":[-73.879099,40.716603],"type":"Point"}
}