{
  "type": "Feature",
  "properties": {
    "addr:full":"2737 Erie Blvd E Syracuse NY 13224",
    "addr:housenumber":"2737",
    "addr:postcode":"13224",
    "addr:street":"Erie Blvd E",
    "iso:country":"US",
    "sg:address":"2737 Erie Blvd E",
    "sg:city":"Syracuse",
    "sg:classifiers":[
        {
            "category":"Food & Beverages",
            "subcategory":"Groceries & Convenience Stores",
            "type":"Retail Goods"
        }
    ],
    "sg:phone":"+1 315 446 7801",
    "sg:postcode":"13224",
    "sg:province":"NY",
    "sg:website":"http://www.hangaram.com",
    "wof:name":"Han Garam Inc",
    "wof:placetype":"venue"
},
  "geometry": {"coordinates":[-76.095288,43.054852],"type":"Point"}
}