{
  "type": "Feature",
  "properties": {
    "addr:full":"143 W 1st St Oswego NY 13126",
    "addr:housenumber":"143",
    "addr:postcode":"13126",
    "addr:street":"W 1St St",
    "iso:country":"US",
    "sg:address":"143 W 1st St",
    "sg:city":"Oswego",
    "sg:classifiers":[
        {
            "category":"Autos & Motor Vehicles",
            "subcategory":"Auto Supplies",
            "type":"Retail Goods"
        }
    ],
    "sg:phone":"+1 315 343 6370",
    "sg:postcode":"13126",
    "sg:province":"NY",
    "sg:tags":[
        "automobile",
        "parts"
    ],
    "wof:name":"Stoney's Auto Parts Co",
    "wof:placetype":"venue"
},
  "geometry": {"coordinates":[-76.512131,43.457969],"type":"Point"}
}