{
  "type": "Feature",
  "properties": {
    "iso:country":"US",
    "sg:address":"36 Cedar St",
    "sg:city":"Dobbs Ferry",
    "sg:classifiers":[
        {
            "category":"Personal",
            "subcategory":"Beauty Salon",
            "type":"Services"
        }
    ],
    "sg:phone":"+1   ",
    "sg:postcode":"10522",
    "sg:province":"NY",
    "sg:tags":[
        "shop"
    ],
    "wof:name":"Aria On Hudson",
    "wof:placetype":"venue"
},
  "geometry": {"coordinates":[-73.870915,41.014987],"type":"Point"}
}