{
  "type": "Feature",
  "properties": {
    "addr:full":"1125 Rte 112 Port Jefferson Station NY 11776",
    "addr:housenumber":"1125",
    "addr:postcode":"11776",
    "addr:street":"Rte 112",
    "iso:country":"US",
    "sg:address":"1125 Rte 112",
    "sg:city":"Port Jefferson Station",
    "sg:classifiers":[
        {
            "category":"Recreation",
            "type":"Entertainment"
        }
    ],
    "sg:phone":"+1 631 331 3220",
    "sg:postcode":"11776",
    "sg:province":"NY",
    "sg:tags":[
        "martial",
        "arts",
        "instruction"
    ],
    "wof:name":"Chikara Martial Arts Acad Inc",
    "wof:placetype":"venue"
},
  "geometry": {"coordinates":[-73.0454,40.922821],"type":"Point"}
}