{
  "type": "Feature",
  "properties": {
    "addr:full":"6266 Muskrat Bay Rd Brewerton NY 13029",
    "addr:housenumber":"6266",
    "addr:postcode":"13029",
    "addr:street":"Muskrat Bay Rd",
    "iso:country":"US",
    "sg:address":"6266 Muskrat Bay Rd",
    "sg:city":"Brewerton",
    "sg:classifiers":[
        {
            "category":"Building & Trades",
            "subcategory":"Construction",
            "type":"Services"
        }
    ],
    "sg:phone":"+1 315 863 8784",
    "sg:postcode":"13029",
    "sg:province":"NY",
    "sg:tags":[
        "resurfacing",
        "refinishing",
        "floor"
    ],
    "wof:name":"Cerio's Hardwood Floors",
    "wof:placetype":"venue"
},
  "geometry": {"coordinates":[-76.098153,43.224147],"type":"Point"}
}