{
  "type": "Feature",
  "properties": {
    "iso:country":"US",
    "sg:address":"124 E 40th St",
    "sg:city":"New York",
    "sg:classifiers":[
        {
            "category":"Personal",
            "subcategory":"Beauty Salon",
            "type":"Services"
        }
    ],
    "sg:phone":"+1 212 532 0692",
    "sg:postcode":"10016",
    "sg:province":"NY",
    "sg:tags":[
        "barber"
    ],
    "sg:website":"concordhair.com/",
    "wof:name":"Concord Hair Design Studio",
    "wof:placetype":"venue"
},
  "geometry": {"coordinates":[-73.977317,40.750139],"type":"Point"}
}