{
  "type": "Feature",
  "properties": {
    "addr:full":"7404 5th Ave Brooklyn NY 11209",
    "addr:housenumber":"7404",
    "addr:postcode":"11209",
    "addr:street":"5Th Ave",
    "iso:country":"US",
    "sg:address":"7404 5th Ave",
    "sg:city":"Brooklyn",
    "sg:classifiers":[
        {
            "category":"Restaurant",
            "type":"Food & Drink"
        }
    ],
    "sg:phone":"+1 718 748 1858",
    "sg:postcode":"11209",
    "sg:province":"NY",
    "wof:name":"Ridge Bay Diner",
    "wof:placetype":"venue"
},
  "geometry": {"coordinates":[-74.022499,40.630199],"type":"Point"}
}