{
  "type": "Feature",
  "properties": {
    "addr:full":"1206 Stratford Ave Bronx NY 10472",
    "addr:housenumber":"1206",
    "addr:postcode":"10472",
    "addr:street":"Stratford Ave",
    "iso:country":"US",
    "sg:address":"1206 Stratford Ave",
    "sg:city":"Bronx",
    "sg:classifiers":[
        {
            "category":"Retail",
            "subcategory":"Laundry & Dry Cleaning",
            "type":"Services"
        }
    ],
    "sg:phone":"+1 718 842 8558",
    "sg:postcode":"10472",
    "sg:province":"NY",
    "sg:tags":[
        "cleaners"
    ],
    "wof:name":"Two Cousins Cleaners",
    "wof:placetype":"venue"
},
  "geometry": {"coordinates":[-73.87596600000001,40.831504],"type":"Point"}
}