{
  "type": "Feature",
  "properties": {
    "iso:country":"US",
    "sg:address":"14 W Park Pl",
    "sg:city":"Norwich",
    "sg:classifiers":[
        {
            "category":"Home & Garden",
            "subcategory":"Building Materials",
            "type":"Retail Goods"
        }
    ],
    "sg:phone":"+1 607 334 5188",
    "sg:postcode":"13815",
    "sg:province":"NY",
    "sg:tags":[
        "glass",
        "window",
        "plate"
    ],
    "wof:name":"Triumph Auto Glass",
    "wof:placetype":"venue"
},
  "geometry": {"coordinates":[-75.52396299999999,42.53187],"type":"Point"}
}