{
  "type": "Feature",
  "properties": {
    "addr:full":"31 John Austin Rd North Creek NY 12853",
    "addr:housenumber":"31",
    "addr:postcode":"12853",
    "addr:street":"John Austin Rd",
    "iso:country":"US",
    "sg:address":"31 John Austin Rd",
    "sg:city":"North Creek",
    "sg:classifiers":[
        {
            "category":"Building & Trades",
            "subcategory":"Construction",
            "type":"Services"
        }
    ],
    "sg:phone":"+1 518 251 2060",
    "sg:postcode":"12853",
    "sg:province":"NY",
    "sg:tags":[
        "contractor"
    ],
    "wof:name":"Fraisers General Contracting",
    "wof:placetype":"venue"
},
  "geometry": {"coordinates":[-73.922197,43.711735],"type":"Point"}
}