{
  "type": "Feature",
  "properties": {
    "iso:country":"US",
    "sg:address":"40 Wall St",
    "sg:city":"New York",
    "sg:classifiers":[
        {
            "category":"Insurance",
            "subcategory":"Hazard Insurance",
            "type":"Services"
        }
    ],
    "sg:phone":"+1 212 440 3600",
    "sg:postcode":"10005",
    "sg:province":"NY",
    "sg:tags":[
        "carrier"
    ],
    "wof:name":"CNA Insurance",
    "wof:placetype":"venue"
},
  "geometry": {"coordinates":[-74.010122,40.70699],"type":"Point"}
}