{
  "type": "Feature",
  "properties": {
    "iso:country":"US",
    "sg:address":"1218 Kings Rd",
    "sg:city":"Schenectady",
    "sg:classifiers":[
        {
            "category":"Wholesale",
            "subcategory":"Electrical",
            "type":"Manufacturing & Wholesale Goods"
        }
    ],
    "sg:phone":"+1 518 370 1433",
    "sg:postcode":"12303",
    "sg:province":"NY",
    "sg:tags":[
        "equipment"
    ],
    "wof:name":"Complete Catv Communications",
    "wof:placetype":"venue"
},
  "geometry": {"coordinates":[-73.885632,42.735272],"type":"Point"}
}