{
  "type": "Feature",
  "properties": {
    "addr:full":"19 Hyatt Street Staten Island NY 10301",
    "addr:housenumber":"19",
    "addr:postcode":"10301",
    "addr:street":"Hyatt Street",
    "iso:country":"US",
    "sg:address":"19 Hyatt Street",
    "sg:city":"Staten Island",
    "sg:classifiers":[
        {
            "category":"Arts & Performance",
            "subcategory":"Arts Center",
            "type":"Entertainment"
        }
    ],
    "sg:phone":"+1 718 442 2900",
    "sg:postcode":"10301",
    "sg:province":"NY",
    "sg:tags":[
        "performing"
    ],
    "wof:name":"The St George Theater",
    "wof:placetype":"venue"
},
  "geometry": {"coordinates":[-74.077348,40.641703],"type":"Point"}
}