{
  "type": "Feature",
  "properties": {
    "iso:country":"US",
    "sg:address":"132 49th St",
    "sg:city":"Brooklyn",
    "sg:classifiers":[
        {
            "category":"Organizations",
            "subcategory":"Religious Organization",
            "type":"Services"
        }
    ],
    "sg:phone":"+1 718 435 7256",
    "sg:postcode":"11232",
    "sg:province":"NY",
    "sg:tags":[
        "clergy"
    ],
    "wof:name":"Nachman Rosenberg",
    "wof:placetype":"venue"
},
  "geometry": {"coordinates":[-74.016936,40.650029],"type":"Point"}
}