{
  "type": "Feature",
  "properties": {
    "addr:full":"141 W 35th Street New York NY 10001",
    "addr:housenumber":"141",
    "addr:postcode":"10001",
    "addr:street":"W 35Th Street",
    "iso:country":"US",
    "sg:address":"141 W 35th Street",
    "sg:city":"New York",
    "sg:classifiers":[
        {
            "category":"Personal",
            "subcategory":"Nail Salon",
            "type":"Services"
        }
    ],
    "sg:phone":"+1 212 564 6971",
    "sg:postcode":"10001",
    "sg:province":"NY",
    "wof:name":"Green Tea Nail and Spa",
    "wof:placetype":"venue"
},
  "geometry": {"coordinates":[-73.98877400000001,40.75098],"type":"Point"}
}