{
  "type": "Feature",
  "properties": {
    "iso:country":"US",
    "sg:address":"3155 Main St",
    "sg:city":"Yorkshire",
    "sg:classifiers":[
        {
            "category":"Personal",
            "subcategory":"Beauty Salon",
            "type":"Services"
        }
    ],
    "sg:phone":"+1 716 492 1141",
    "sg:postcode":"14173",
    "sg:province":"NY",
    "sg:tags":[
        "shop"
    ],
    "wof:name":"Ye Old Country Salon",
    "wof:placetype":"venue"
},
  "geometry": {"coordinates":[-78.47402099999999,42.530096],"type":"Point"}
}