{
  "type": "Feature",
  "properties": {
    "addr:full":"Sw Corner, 49th St & Park Ave Manhattan NY 10017",
    "addr:postcode":"10017",
    "addr:street":"Sw;49Th St & Park Ave",
    "iso:country":"US",
    "sg:address":"Sw Corner, 49th St & Park Ave",
    "sg:city":"Manhattan",
    "sg:classifiers":[
        {
            "category":"Coffee & Tea",
            "type":"Food & Drink"
        },
        {
            "category":"Food Court",
            "type":"Food & Drink"
        }
    ],
    "sg:postcode":"10017",
    "sg:province":"NY",
    "sg:tags":[
        "stand"
    ],
    "wof:name":"Tony's Coffee Cart",
    "wof:placetype":"venue"
},
  "geometry": {"coordinates":[-73.97436399999999,40.756529],"type":"Point"}
}