{
  "type": "Feature",
  "properties": {
    "addr:full":"7 Thurlow Ter Albany NY 12203",
    "addr:housenumber":"7",
    "addr:postcode":"12203",
    "addr:street":"Thurlow Ter",
    "iso:country":"US",
    "sg:address":"7 Thurlow Ter",
    "sg:city":"Albany",
    "sg:classifiers":[
        {
            "category":"Professional",
            "subcategory":"Lawyer & Legal Services",
            "type":"Services"
        }
    ],
    "sg:phone":"+1 518 465 2426",
    "sg:postcode":"12203",
    "sg:province":"NY",
    "sg:tags":[
        "attorney"
    ],
    "wof:name":"Sommers & Sommers LLP",
    "wof:placetype":"venue"
},
  "geometry": {"coordinates":[-73.77281499999999,42.65975],"type":"Point"}
}