{
  "type": "Feature",
  "properties": {
    "iso:country":"US",
    "sg:address":"16 Horse Hollow Rd",
    "sg:city":"Locust Valley",
    "sg:classifiers":[
        {
            "category":"Professional",
            "subcategory":"Management & Consulting",
            "type":"Services"
        }
    ],
    "sg:phone":"+1   ",
    "sg:postcode":"11560",
    "sg:province":"NY",
    "sg:tags":[
        "business"
    ],
    "wof:name":"Samet M Francis Interiors",
    "wof:placetype":"venue"
},
  "geometry": {"coordinates":[-73.59407299999999,40.885095],"type":"Point"}
}