{
  "type": "Feature",
  "properties": {
    "addr:full":"36 20th St Brooklyn NY 11232",
    "addr:housenumber":"36",
    "addr:postcode":"11232",
    "addr:street":"20Th St",
    "iso:country":"US",
    "sg:address":"36 20th St",
    "sg:city":"Brooklyn",
    "sg:classifiers":[
        {
            "category":"Social Services",
            "subcategory":"Child Care",
            "type":"Services"
        }
    ],
    "sg:phone":"+1 718 369 3399",
    "sg:postcode":"11232",
    "sg:province":"NY",
    "sg:tags":[
        "day"
    ],
    "wof:name":"A Plus Child Supply Inc",
    "wof:placetype":"venue"
},
  "geometry": {"coordinates":[-73.997704,40.664799],"type":"Point"}
}