{
  "type": "Feature",
  "properties": {
    "iso:country":"US",
    "sg:address":"2 15th St",
    "sg:city":"Watervliet",
    "sg:classifiers":[
        {
            "category":"Government",
            "subcategory":"Office",
            "type":"Public Place"
        }
    ],
    "sg:phone":"+1 518 270 3800",
    "sg:postcode":"12189",
    "sg:province":"NY",
    "sg:tags":[
        "executive"
    ],
    "wof:name":"City of Watervliet",
    "wof:placetype":"venue"
},
  "geometry": {"coordinates":[-73.701038,42.725891],"type":"Point"}
}