{
  "type": "Feature",
  "properties": {
    "addr:full":"91 Ellison Ave Westbury NY 11590",
    "addr:housenumber":"91",
    "addr:postcode":"11590",
    "addr:street":"Ellison Ave",
    "iso:country":"US",
    "sg:address":"91 Ellison Ave",
    "sg:city":"Westbury",
    "sg:classifiers":[
        {
            "category":"Government",
            "subcategory":"Office",
            "type":"Public Place"
        }
    ],
    "sg:phone":"+1 516 333 7854",
    "sg:postcode":"11590",
    "sg:province":"NY",
    "wof:name":"Han Lee Ki",
    "wof:placetype":"venue"
},
  "geometry": {"coordinates":[-73.594585,40.750126],"type":"Point"}
}