{
  "type": "Feature",
  "properties": {
    "addr:full":"38 W 32nd St Ste 1403 New York NY 10001",
    "addr:housenumber":"38",
    "addr:postcode":"10001",
    "addr:street":"W 32Nd St Ste 1403",
    "iso:country":"US",
    "sg:address":"38 W 32nd St Ste 1403",
    "sg:city":"New York",
    "sg:classifiers":[
        {
            "category":"Health Services",
            "subcategory":"Health Practitioner",
            "type":"Services"
        }
    ],
    "sg:phone":"+1 212 290 0290",
    "sg:postcode":"10001",
    "sg:province":"NY",
    "sg:tags":[
        "therapy",
        "physical"
    ],
    "sg:website":"connectthedotstherapy.com",
    "wof:name":"Coonect the Dots, Occupational Therapy Pllc",
    "wof:placetype":"venue"
},
  "geometry": {"coordinates":[-73.98806999999999,40.748229],"type":"Point"}
}