{
  "type": "Feature",
  "properties": {
    "iso:country":"US",
    "sg:address":"15 Meadow Ln",
    "sg:city":"Chappaqua",
    "sg:classifiers":[
        {
            "category":"Organizations",
            "subcategory":"Religious Organization",
            "type":"Services"
        }
    ],
    "sg:phone":"+1 914 238 3875",
    "sg:postcode":"10514",
    "sg:province":"NY",
    "sg:tags":[
        "clergy"
    ],
    "wof:name":"Timothy Ives",
    "wof:placetype":"venue"
},
  "geometry": {"coordinates":[-73.780193,41.165785],"type":"Point"}
}