{
  "type": "Feature",
  "properties": {
    "addr:full":"1294 E 19th St Brooklyn NY 11230",
    "addr:housenumber":"1294",
    "addr:postcode":"11230",
    "addr:street":"E 19Th St",
    "iso:country":"US",
    "sg:address":"1294 E 19th St",
    "sg:city":"Brooklyn",
    "sg:classifiers":[
        {
            "category":"Food & Beverages",
            "subcategory":"Groceries & Convenience Stores",
            "type":"Retail Goods"
        }
    ],
    "sg:phone":"+1 718 252 6186",
    "sg:postcode":"11230",
    "sg:province":"NY",
    "wof:name":"Phinex International Food Inc",
    "wof:placetype":"venue"
},
  "geometry": {"coordinates":[-73.95639799999999,40.618999],"type":"Point"}
}