{
  "type": "Feature",
  "properties": {
    "iso:country":"US",
    "sg:address":"300 New Hyde Park Rd",
    "sg:city":"New Hyde Park",
    "sg:classifiers":[
        {
            "category":"Health Services",
            "subcategory":"Doctor",
            "type":"Services"
        }
    ],
    "sg:phone":"+1 516 488 1888",
    "sg:postcode":"11040",
    "sg:province":"NY",
    "wof:name":"Mallin Jeffrey E MD",
    "wof:placetype":"venue"
},
  "geometry": {"coordinates":[-73.683025,40.741829],"type":"Point"}
}