{
  "type": "Feature",
  "properties": {
    "addr:full":"81 Pondfield Rd Bronxville NY 10708",
    "addr:housenumber":"81",
    "addr:postcode":"10708",
    "addr:street":"Pondfield Rd",
    "iso:country":"US",
    "sg:address":"81 Pondfield Rd",
    "sg:city":"Bronxville",
    "sg:classifiers":[
        {
            "category":"Professional",
            "subcategory":"Business Services",
            "type":"Services"
        }
    ],
    "sg:phone":"+1 914 779 0140",
    "sg:postcode":"10708",
    "sg:province":"NY",
    "wof:name":"UPS Stores The",
    "wof:placetype":"venue"
},
  "geometry": {"coordinates":[-73.833313,40.940543],"type":"Point"}
}