{
  "type": "Feature",
  "properties": {
    "addr:full":"10 Curley St Long Beach NY 11561",
    "addr:housenumber":"10",
    "addr:postcode":"11561",
    "addr:street":"Curley St",
    "iso:country":"US",
    "sg:address":"10 Curley St",
    "sg:city":"Long Beach",
    "sg:classifiers":[
        {
            "category":"Professional",
            "subcategory":"Detective & Security Services",
            "type":"Services"
        }
    ],
    "sg:phone":"+1 516 432 1291",
    "sg:postcode":"11561",
    "sg:province":"NY",
    "sg:tags":[
        "car"
    ],
    "wof:name":"Exposition Management",
    "wof:placetype":"venue"
},
  "geometry": {"coordinates":[-73.638605,40.591949],"type":"Point"}
}