{
  "type": "Feature",
  "properties": {
    "iso:country":"US",
    "sg:address":"1841 Broadway",
    "sg:city":"New York",
    "sg:classifiers":[
        {
            "category":"Restaurant",
            "type":"Food & Drink"
        }
    ],
    "sg:phone":"+1 212 757 7560",
    "sg:postcode":"10023",
    "sg:province":"NY",
    "wof:name":"New York Sun Works",
    "wof:placetype":"venue"
},
  "geometry": {"coordinates":[-73.98218799999999,40.769528],"type":"Point"}
}