{
  "type": "Feature",
  "properties": {
    "addr:full":"233 Caesar Blvd Buffalo NY 14221",
    "addr:housenumber":"233",
    "addr:postcode":"14221",
    "addr:street":"Caesar Blvd",
    "iso:country":"US",
    "sg:address":"233 Caesar Blvd",
    "sg:city":"Buffalo",
    "sg:classifiers":[
        {
            "category":"Building & Trades",
            "subcategory":"Construction",
            "type":"Services"
        }
    ],
    "sg:phone":"+1 716 634 3762",
    "sg:postcode":"14221",
    "sg:province":"NY",
    "sg:tags":[
        "concrete",
        "contractor"
    ],
    "wof:name":"Expert Concrete Construction",
    "wof:placetype":"venue"
},
  "geometry": {"coordinates":[-78.701824,42.972237],"type":"Point"}
}