{
  "type": "Feature",
  "properties": {
    "iso:country":"US",
    "sg:address":"2 Cogan Ave",
    "sg:city":"Plattsburgh",
    "sg:classifiers":[
        {
            "category":"Professional",
            "subcategory":"Computer Services",
            "type":"Services"
        }
    ],
    "sg:phone":"+1 518 563 8872",
    "sg:postcode":"12901",
    "sg:province":"NY",
    "sg:tags":[
        "consultant",
        "designer"
    ],
    "wof:name":"KBS",
    "wof:placetype":"venue"
},
  "geometry": {"coordinates":[-73.479905,44.697274],"type":"Point"}
}