{
  "type": "Feature",
  "properties": {
    "addr:full":"350 W 49 St New York NY 10019",
    "addr:housenumber":"350",
    "addr:postcode":"10019",
    "addr:street":"W 49 St",
    "iso:country":"US",
    "sg:address":"350 W 49 St",
    "sg:city":"New York",
    "sg:classifiers":[
        {
            "category":"Professional",
            "type":"Services"
        }
    ],
    "sg:phone":"+1 212 586 4773",
    "sg:postcode":"10019",
    "sg:province":"NY",
    "sg:tags":[
        "establishment"
    ],
    "wof:name":"Fountain House Inc",
    "wof:placetype":"venue"
},
  "geometry": {"coordinates":[-73.98833999999999,40.762182],"type":"Point"}
}