{
  "type": "Feature",
  "properties": {
    "iso:country":"US",
    "sg:address":"544 E 171st St",
    "sg:city":"Bronx",
    "sg:classifiers":[
        {
            "category":"Manufacturing",
            "subcategory":"Furniture",
            "type":"Manufacturing & Wholesale Goods"
        }
    ],
    "sg:phone":"+1   ",
    "sg:postcode":"10457",
    "sg:province":"NY",
    "sg:tags":[
        "mfg"
    ],
    "wof:name":"Display Factory Inc",
    "wof:placetype":"venue"
},
  "geometry": {"coordinates":[-73.900567,40.836591],"type":"Point"}
}