{
  "type": "Feature",
  "properties": {
    "iso:country":"US",
    "sg:address":"39 Grand Blvd",
    "sg:city":"Scarsdale",
    "sg:classifiers":[
        {
            "category":"Health Services",
            "subcategory":"Doctor",
            "type":"Services"
        }
    ],
    "sg:phone":"+1 914 723 9325",
    "sg:postcode":"10583",
    "sg:province":"NY",
    "sg:tags":[
        "physician",
        "surgeon",
        "medical"
    ],
    "wof:name":"E Bruckmann MD",
    "wof:placetype":"venue"
},
  "geometry": {"coordinates":[-73.808984,40.983329],"type":"Point"}
}