{
  "type": "Feature",
  "properties": {
    "addr:full":"2408 Elton Rd Bloomfield NY 14469",
    "addr:housenumber":"2408",
    "addr:postcode":"14469",
    "addr:street":"Elton Rd",
    "iso:country":"US",
    "sg:address":"2408 Elton Rd",
    "sg:city":"Bloomfield",
    "sg:classifiers":[
        {
            "category":"Building & Trades",
            "subcategory":"Landscaping Services",
            "type":"Services"
        }
    ],
    "sg:phone":"+1 585 657 4373",
    "sg:postcode":"14469",
    "sg:province":"NY",
    "sg:tags":[
        "landscape"
    ],
    "wof:name":"Bedrock Landscaping",
    "wof:placetype":"venue"
},
  "geometry": {"coordinates":[-77.495569,42.912614],"type":"Point"}
}