{
  "type": "Feature",
  "properties": {
    "addr:full":"1063 Grant St Buffalo NY 14207",
    "addr:housenumber":"1063",
    "addr:postcode":"14207",
    "addr:street":"Grant St",
    "iso:country":"US",
    "sg:address":"1063 Grant St",
    "sg:city":"Buffalo",
    "sg:classifiers":[
        {
            "category":"Recreation",
            "type":"Entertainment"
        }
    ],
    "sg:phone":"+1 716 447 1271",
    "sg:postcode":"14207",
    "sg:province":"NY",
    "sg:tags":[
        "hall",
        "auditorium"
    ],
    "wof:name":"Showplace Theatre",
    "wof:placetype":"venue"
},
  "geometry": {"coordinates":[-78.890579,42.938993],"type":"Point"}
}