{
  "type": "Feature",
  "properties": {
    "addr:full":"4116 Wilder Ave Bronx NY 10466",
    "addr:housenumber":"4116",
    "addr:postcode":"10466",
    "addr:street":"Wilder Ave",
    "iso:country":"US",
    "sg:address":"4116 Wilder Ave",
    "sg:city":"Bronx",
    "sg:classifiers":[
        {
            "category":"Organizations",
            "subcategory":"Religious Organization",
            "type":"Services"
        }
    ],
    "sg:phone":"+1 212 289 7083",
    "sg:postcode":"10466",
    "sg:province":"NY",
    "sg:tags":[
        "church"
    ],
    "wof:name":"Holy Tabernacle Church",
    "wof:placetype":"venue"
},
  "geometry": {"coordinates":[-73.84269,40.895416],"type":"Point"}
}