{
  "type": "Feature",
  "properties": {
    "addr:full":"64 Bleecker St New York NY 10012",
    "addr:housenumber":"64",
    "addr:postcode":"10012",
    "addr:street":"Bleecker St",
    "iso:country":"US",
    "sg:address":"64 Bleecker St",
    "sg:city":"New York",
    "sg:classifiers":[
        {
            "category":"Retail",
            "subcategory":"Portrait Studio",
            "type":"Services"
        }
    ],
    "sg:phone":"+1 212 254 4345",
    "sg:postcode":"10012",
    "sg:province":"NY",
    "sg:tags":[
        "photography",
        "store"
    ],
    "sg:website":"www.bleekerdigital.com",
    "wof:name":"Bleeker Digital Solutions",
    "wof:placetype":"venue"
},
  "geometry": {"coordinates":[-73.99527999999999,40.726225],"type":"Point"}
}