{
  "type": "Feature",
  "properties": {
    "iso:country":"US",
    "sg:address":"1045 Westchester Ave",
    "sg:city":"Bronx",
    "sg:classifiers":[
        {
            "category":"Shopping",
            "subcategory":"Pharmacy",
            "type":"Retail Goods"
        }
    ],
    "sg:phone":"+1   ",
    "sg:postcode":"10459",
    "sg:province":"NY",
    "wof:name":"United Pharmacy Inc",
    "wof:placetype":"venue"
},
  "geometry": {"coordinates":[-73.892157,40.824594],"type":"Point"}
}