{
  "type": "Feature",
  "properties": {
    "addr:full":"10 W 34th St New York NY 10016",
    "addr:housenumber":"10",
    "addr:postcode":"10016",
    "addr:street":"W 34Th St",
    "iso:country":"US",
    "sg:address":"10 W 34th St",
    "sg:city":"New York",
    "sg:classifiers":[
        {
            "category":"Personal",
            "subcategory":"Beauty Salon",
            "type":"Services"
        }
    ],
    "sg:phone":"+1 212 659 5300",
    "sg:postcode":"10016",
    "sg:province":"NY",
    "sg:tags":[
        "spa"
    ],
    "sg:website":"www.borghese.com",
    "wof:name":"Borghese",
    "wof:placetype":"venue"
},
  "geometry": {"coordinates":[-73.983808,40.748105],"type":"Point"}
}