{
  "type": "Feature",
  "properties": {
    "iso:country":"US",
    "sg:address":"875 Saw Mill River Rd",
    "sg:city":"Ardsley",
    "sg:classifiers":[
        {
            "category":"Sports & Exercise",
            "subcategory":"Gym",
            "type":"Entertainment"
        }
    ],
    "sg:phone":"+1 800 615 7352",
    "sg:postcode":"10502",
    "sg:province":"NY",
    "sg:tags":[
        "club",
        "gymnasium",
        "program",
        "health",
        "fitness",
        "studio",
        "physical"
    ],
    "sg:website":"http://newyork.citysearch.com/profile/external/37265274/ardsley_ny/curves.html?publisher=yellowpages&reference_id=1&placement=ypwebsitemip",
    "wof:name":"Curves",
    "wof:placetype":"venue"
},
  "geometry": {"coordinates":[-73.843998,41.018271],"type":"Point"}
}