{
  "type": "Feature",
  "properties": {
    "iso:country":"US",
    "sg:address":"1936 Madison Ave",
    "sg:city":"New York",
    "sg:classifiers":[
        {
            "category":"Food & Beverages",
            "subcategory":"Specialty",
            "type":"Retail Goods"
        }
    ],
    "sg:phone":"+1   ",
    "sg:postcode":"10035",
    "sg:province":"NY",
    "wof:name":"Positive Vibrations Inc",
    "wof:placetype":"venue"
},
  "geometry": {"coordinates":[-73.94096399999999,40.805342],"type":"Point"}
}