{
  "type": "Feature",
  "properties": {
    "addr:full":"1300 Hylan Blvd Staten Island NY 10305",
    "addr:housenumber":"1300",
    "addr:postcode":"10305",
    "addr:street":"Hylan Blvd",
    "iso:country":"US",
    "sg:address":"1300 Hylan Blvd",
    "sg:city":"Staten Island",
    "sg:classifiers":[
        {
            "category":"Shopping",
            "subcategory":"Optician",
            "type":"Retail Goods"
        }
    ],
    "sg:phone":"+1 718 987 2020",
    "sg:postcode":"10305",
    "sg:province":"NY",
    "sg:tags":[
        "eyewear"
    ],
    "sg:website":"www.sparepairvisioncenter.com",
    "wof:name":"Spare Pair Vision Center",
    "wof:placetype":"venue"
},
  "geometry": {"coordinates":[-74.085097,40.596886],"type":"Point"}
}