{
  "type": "Feature",
  "properties": {
    "addr:full":"223 Kearsing Pkwy Monsey NY 10952",
    "addr:housenumber":"223",
    "addr:postcode":"10952",
    "addr:street":"Kearsing Pkwy",
    "iso:country":"US",
    "sg:address":"223 Kearsing Pkwy",
    "sg:city":"Monsey",
    "sg:classifiers":[
        {
            "category":"Wholesale",
            "subcategory":"Machinery & Supplies",
            "type":"Manufacturing & Wholesale Goods"
        }
    ],
    "sg:phone":"+1 917 674 7842",
    "sg:postcode":"10952",
    "sg:province":"NY",
    "sg:tags":[
        "industrial",
        "commercial",
        "computer"
    ],
    "wof:name":"United Digital Inc",
    "wof:placetype":"venue"
},
  "geometry": {"coordinates":[-74.06571599999999,41.127306],"type":"Point"}
}