{
  "type": "Feature",
  "properties": {
    "addr:full":"1110 N Salina St Syracuse NY 13208",
    "addr:housenumber":"1110",
    "addr:postcode":"13208",
    "addr:street":"N Salina St",
    "iso:country":"US",
    "sg:address":"1110 N Salina St",
    "sg:city":"Syracuse",
    "sg:classifiers":[
        {
            "category":"Restaurant",
            "type":"Food & Drink"
        }
    ],
    "sg:phone":"+1 315 471 9082",
    "sg:postcode":"13208",
    "sg:province":"NY",
    "sg:tags":[
        "bar"
    ],
    "wof:name":"Aunt Josies Restaurant Inc",
    "wof:placetype":"venue"
},
  "geometry": {"coordinates":[-76.157704,43.065988],"type":"Point"}
}