{
  "type": "Feature",
  "properties": {
    "addr:full":"306 Main St Port Jefferson NY 11777",
    "addr:housenumber":"306",
    "addr:postcode":"11777",
    "addr:street":"Main St",
    "iso:country":"US",
    "sg:address":"306 Main St",
    "sg:city":"Port Jefferson",
    "sg:classifiers":[
        {
            "category":"Professional",
            "subcategory":"Computer Services",
            "type":"Services"
        }
    ],
    "sg:phone":"+1   ",
    "sg:postcode":"11777",
    "sg:province":"NY",
    "sg:tags":[
        "related"
    ],
    "wof:name":"Pjm Computer Consulting Svcs",
    "wof:placetype":"venue"
},
  "geometry": {"coordinates":[-73.067914,40.94493],"type":"Point"}
}