{
  "type": "Feature",
  "properties": {
    "addr:full":"103 Lincoln Ave Groton NY 13073",
    "addr:housenumber":"103",
    "addr:postcode":"13073",
    "addr:street":"Lincoln Ave",
    "iso:country":"US",
    "sg:address":"103 Lincoln Ave",
    "sg:city":"Groton",
    "sg:classifiers":[
        {
            "category":"Real Estate",
            "subcategory":"Real Estate Agent",
            "type":"Services"
        }
    ],
    "sg:phone":"+1 607 898 3744",
    "sg:postcode":"13073",
    "sg:province":"NY",
    "wof:name":"NEA Realty",
    "wof:placetype":"venue"
},
  "geometry": {"coordinates":[-76.36329000000001,42.586552],"type":"Point"}
}