{
  "type": "Feature",
  "properties": {
    "iso:country":"US",
    "sg:address":"5550 Main St",
    "sg:city":"Buffalo",
    "sg:classifiers":[
        {
            "category":"Sports & Exercise",
            "subcategory":"Gym",
            "type":"Entertainment"
        }
    ],
    "sg:phone":"+1 716 626 3399",
    "sg:postcode":"14221",
    "sg:province":"NY",
    "sg:tags":[
        "facility",
        "club",
        "gymnasium",
        "health",
        "fitness",
        "studio",
        "physical"
    ],
    "wof:name":"Body One Studios Inc",
    "wof:placetype":"venue"
},
  "geometry": {"coordinates":[-78.746318,42.962643],"type":"Point"}
}