{
  "type": "Feature",
  "properties": {
    "addr:full":"12 Sleepy Hollow Rd Shelter Island NY 11964",
    "addr:housenumber":"12",
    "addr:postcode":"11964",
    "addr:street":"Sleepy Hollow Rd",
    "iso:country":"US",
    "sg:address":"12 Sleepy Hollow Rd",
    "sg:city":"Shelter Island",
    "sg:classifiers":[
        {
            "category":"Professional",
            "type":"Services"
        }
    ],
    "sg:phone":"+1 631 749 7867",
    "sg:postcode":"11964",
    "sg:province":"NY",
    "sg:tags":[
        "establishment"
    ],
    "wof:name":"Shelter Island Run Inc",
    "wof:placetype":"venue"
},
  "geometry": {"coordinates":[-72.349261,41.072759],"type":"Point"}
}