{
  "type": "Feature",
  "properties": {
    "addr:full":"1121 Lincoln Ave Holbrook NY 11741",
    "addr:housenumber":"1121",
    "addr:postcode":"11741",
    "addr:street":"Lincoln Ave",
    "iso:country":"US",
    "sg:address":"1121 Lincoln Ave",
    "sg:city":"Holbrook",
    "sg:classifiers":[
        {
            "category":"Shopping",
            "subcategory":"Bicycles & Sporting Goods",
            "type":"Retail Goods"
        }
    ],
    "sg:phone":"+1 631 589 1739",
    "sg:postcode":"11741",
    "sg:province":"NY",
    "sg:tags":[
        "gun",
        "gunsmith"
    ],
    "sg:website":"www.suffolkammo.com",
    "wof:name":"Suffolk Ammunition Co",
    "wof:placetype":"venue"
},
  "geometry": {"coordinates":[-73.083844,40.779147],"type":"Point"}
}