{
  "type": "Feature",
  "properties": {
    "iso:country":"US",
    "sg:address":"17 Lent Dr",
    "sg:city":"Plainview",
    "sg:classifiers":[
        {
            "category":"Building & Trades",
            "subcategory":"Cleaning & Sanitation",
            "type":"Services"
        }
    ],
    "sg:phone":"+1 516 938 6738",
    "sg:postcode":"11803",
    "sg:province":"NY",
    "sg:tags":[
        "fireplace",
        "chimney",
        "maintenance"
    ],
    "wof:name":"E & M Maintenance Inc",
    "wof:placetype":"venue"
},
  "geometry": {"coordinates":[-73.469094,40.762748],"type":"Point"}
}