{
  "type": "Feature",
  "properties": {
    "iso:country":"US",
    "sg:address":"233 W 54 St",
    "sg:city":"New York",
    "sg:classifiers":[
        {
            "category":"Professional",
            "subcategory":"Advertising",
            "type":"Services"
        }
    ],
    "sg:phone":"+1 212 977 2679",
    "sg:postcode":"10019",
    "sg:province":"NY",
    "sg:tags":[
        "mailing",
        "shipping"
    ],
    "sg:website":"www.kinkos.com",
    "wof:name":"Fed Ex Kinko's Ofc & Print Ctr",
    "wof:placetype":"venue"
},
  "geometry": {"coordinates":[-73.984205,40.764835],"type":"Point"}
}