{
  "type": "Feature",
  "properties": {
    "iso:country":"US",
    "sg:address":"15 Concord Ave",
    "sg:city":"Larchmont",
    "sg:classifiers":[
        {
            "category":"Communications",
            "type":"Services"
        }
    ],
    "sg:phone":"+1   ",
    "sg:postcode":"10538",
    "sg:province":"NY",
    "sg:tags":[
        "communication"
    ],
    "wof:name":"Ejb Communications",
    "wof:placetype":"venue"
},
  "geometry": {"coordinates":[-73.75401599999999,40.935026],"type":"Point"}
}