{
  "type": "Feature",
  "properties": {
    "addr:full":"424 E 147th St Bronx NY 10455",
    "addr:housenumber":"424",
    "addr:postcode":"10455",
    "addr:street":"E 147Th St",
    "iso:country":"US",
    "sg:address":"424 E 147th St",
    "sg:city":"Bronx",
    "sg:classifiers":[
        {
            "category":"Education",
            "subcategory":"University",
            "type":"Public Place"
        }
    ],
    "sg:phone":"+1 718 742 6088",
    "sg:postcode":"10455",
    "sg:province":"NY",
    "sg:tags":[
        "college"
    ],
    "wof:name":"Boricua College",
    "wof:placetype":"venue"
},
  "geometry": {"coordinates":[-73.917945,40.814266],"type":"Point"}
}