{
  "type": "Feature",
  "properties": {
    "addr:full":"20 Warren St New York NY 10007",
    "addr:housenumber":"20",
    "addr:postcode":"10007",
    "addr:street":"Warren St",
    "iso:country":"US",
    "sg:address":"20 Warren St",
    "sg:city":"New York",
    "sg:classifiers":[
        {
            "category":"Restaurant",
            "type":"Food & Drink"
        }
    ],
    "sg:menulink":"http://www.allmenus.com/ny/new-york/249937-twenty-20/menu/",
    "sg:phone":"+1 212 962 9759",
    "sg:postcode":"10007",
    "sg:province":"NY",
    "sg:tags":[
        "american"
    ],
    "wof:name":"Twenty 20",
    "wof:placetype":"venue"
},
  "geometry": {"coordinates":[-74.007615,40.714247],"type":"Point"}
}