{
  "type": "Feature",
  "properties": {
    "iso:country":"US",
    "sg:address":"55 Sealy Dr",
    "sg:city":"Lawrence",
    "sg:classifiers":[
        {
            "category":"Health Services",
            "subcategory":"Doctor",
            "type":"Services"
        }
    ],
    "sg:phone":"+1 516 569 9510",
    "sg:postcode":"11559",
    "sg:province":"NY",
    "wof:name":"Simon Iris Np",
    "wof:placetype":"venue"
},
  "geometry": {"coordinates":[-73.72145,40.61476],"type":"Point"}
}