{
  "type": "Feature",
  "properties": {
    "iso:country":"US",
    "sg:address":"270 Genesee St",
    "sg:city":"Utica",
    "sg:classifiers":[
        {
            "category":"Organizations",
            "subcategory":"Labor Organization",
            "type":"Services"
        }
    ],
    "sg:phone":"+1   ",
    "sg:postcode":"13502",
    "sg:province":"NY",
    "sg:tags":[
        "charitable",
        "de",
        "offering",
        "human"
    ],
    "wof:name":"Central New York Labor Agency",
    "wof:placetype":"venue"
},
  "geometry": {"coordinates":[-75.236501,43.098999],"type":"Point"}
}