{
  "type": "Feature",
  "properties": {
    "addr:full":"53 Mckinley Ave Endicott NY 13760",
    "addr:housenumber":"53",
    "addr:postcode":"13760",
    "addr:street":"Mckinley Ave",
    "iso:country":"US",
    "sg:address":"53 Mckinley Ave",
    "sg:city":"Endicott",
    "sg:classifiers":[
        {
            "category":"Place Of Worship",
            "subcategory":"Church",
            "type":"Public Place"
        },
        {
            "category":"Place Of Worship",
            "type":"Public Place"
        },
        {
            "category":"Social Services",
            "subcategory":"Child Care",
            "type":"Services"
        }
    ],
    "sg:phone":"+1 607 748 7434",
    "sg:postcode":"13760",
    "sg:province":"NY",
    "sg:tags":[
        "nursery",
        "churches-methodist",
        "day"
    ],
    "wof:name":"First Untd Methodst Nurs Schl",
    "wof:placetype":"venue"
},
  "geometry": {"coordinates":[-76.04459,42.103393],"type":"Point"}
}