{
  "type": "Feature",
  "properties": {
    "addr:full":"1760 Grand Ave Merrick NY 11566",
    "addr:housenumber":"1760",
    "addr:postcode":"11566",
    "addr:street":"Grand Ave",
    "iso:country":"US",
    "sg:address":"1760 Grand Ave",
    "sg:city":"Merrick",
    "sg:classifiers":[
        {
            "category":"Wholesale",
            "subcategory":"Durable Goods & Equipment",
            "type":"Manufacturing & Wholesale Goods"
        }
    ],
    "sg:phone":"+1 516 379 1203",
    "sg:postcode":"11566",
    "sg:province":"NY",
    "sg:tags":[
        "importer",
        "parts",
        "scientific"
    ],
    "sg:website":"www.tecoptics.com",
    "wof:name":"Tec Optics Inc",
    "wof:placetype":"venue"
},
  "geometry": {"coordinates":[-73.56247500000001,40.665534],"type":"Point"}
}