{
  "type": "Feature",
  "properties": {
    "iso:country":"US",
    "sg:address":"1028 Washington Ave",
    "sg:city":"Albany",
    "sg:classifiers":[
        {
            "category":"Manufacturing",
            "subcategory":"Metals",
            "type":"Manufacturing & Wholesale Goods"
        }
    ],
    "sg:phone":"+1 518 453 8819",
    "sg:postcode":"12203",
    "sg:province":"NY",
    "sg:tags":[
        "hanging"
    ],
    "wof:name":"Feidens Painting",
    "wof:placetype":"venue"
},
  "geometry": {"coordinates":[-73.796161,42.675747],"type":"Point"}
}