{
  "type": "Feature",
  "properties": {
    "iso:country":"US",
    "sg:address":"980 Franklin Ave",
    "sg:city":"Garden City",
    "sg:classifiers":[
        {
            "category":"Restaurant",
            "type":"Food & Drink"
        }
    ],
    "sg:phone":"+1 516 294 6565",
    "sg:postcode":"11530",
    "sg:province":"NY",
    "sg:tags":[
        "pizza"
    ],
    "sg:website":"www.kpsearch.com/df/grimaldis/al...",
    "wof:name":"Grimaldi's Pizzeria",
    "wof:placetype":"venue"
},
  "geometry": {"coordinates":[-73.635555,40.729359],"type":"Point"}
}