{
  "type": "Feature",
  "properties": {
    "addr:full":"270 W 36th Street New York NY 10018",
    "addr:housenumber":"270",
    "addr:postcode":"10018",
    "addr:street":"W 36Th Street",
    "iso:country":"US",
    "sg:address":"270 W 36th Street",
    "sg:city":"New York",
    "sg:classifiers":[
        {
            "category":"Food & Beverages",
            "subcategory":"Liquor & Beverages",
            "type":"Retail Goods"
        }
    ],
    "sg:phone":"+1 212 244 5276",
    "sg:postcode":"10018",
    "sg:province":"NY",
    "sg:tags":[
        "beer",
        "spirit",
        "wine"
    ],
    "wof:name":"Harry's Liquors",
    "wof:placetype":"venue"
},
  "geometry": {"coordinates":[-73.991846,40.753132],"type":"Point"}
}