{
  "type": "Feature",
  "properties": {
    "iso:country":"US",
    "sg:address":"7357 Eastgate Cir",
    "sg:city":"Liverpool",
    "sg:classifiers":[
        {
            "category":"Wholesale",
            "subcategory":"Non-durable Goods",
            "type":"Manufacturing & Wholesale Goods"
        }
    ],
    "sg:phone":"+1 315 263 0842",
    "sg:postcode":"13090",
    "sg:province":"NY",
    "sg:tags":[
        "advertising"
    ],
    "wof:name":"Just Great Sports",
    "wof:placetype":"venue"
},
  "geometry": {"coordinates":[-76.23947800000001,43.125837],"type":"Point"}
}