{
  "type": "Feature",
  "properties": {
    "addr:full":"40 Wall St New York NY 10005",
    "addr:housenumber":"40",
    "addr:postcode":"10005",
    "addr:street":"Wall St",
    "iso:country":"US",
    "sg:address":"40 Wall St",
    "sg:city":"New York",
    "sg:classifiers":[
        {
            "category":"Professional",
            "subcategory":"Management & Consulting",
            "type":"Services"
        }
    ],
    "sg:phone":"+1 212 430 4000",
    "sg:postcode":"10005",
    "sg:province":"NY",
    "sg:tags":[
        "business"
    ],
    "wof:name":"Eco Smart Healthy Prpts LLC",
    "wof:placetype":"venue"
},
  "geometry": {"coordinates":[-74.010122,40.70699],"type":"Point"}
}