{
  "type": "Feature",
  "properties": {
    "addr:full":"374 Windsor Hwy Vails Gate NY 12553",
    "addr:housenumber":"374",
    "addr:postcode":"12553",
    "addr:street":"Windsor Hwy;Gate",
    "iso:country":"US",
    "sg:address":"374 Windsor Hwy",
    "sg:city":"Vails Gate",
    "sg:classifiers":[
        {
            "category":"Social Services",
            "subcategory":"Child Care",
            "type":"Services"
        }
    ],
    "sg:phone":"+1 631 348 1970",
    "sg:postcode":"12553",
    "sg:province":"NY",
    "sg:tags":[
        "day"
    ],
    "wof:name":"Tutor Time of Vails Gate",
    "wof:placetype":"venue"
},
  "geometry": {"coordinates":[-74.055306,41.458025],"type":"Point"}
}