{
  "type": "Feature",
  "properties": {
    "addr:full":"972 58th St Brooklyn NY 11219",
    "addr:housenumber":"972",
    "addr:postcode":"11219",
    "addr:street":"58Th St",
    "iso:country":"US",
    "sg:address":"972 58th St",
    "sg:city":"Brooklyn",
    "sg:classifiers":[
        {
            "category":"Utilities",
            "subcategory":"Electric",
            "type":"Services"
        }
    ],
    "sg:phone":"+1 718 686 2710",
    "sg:postcode":"11219",
    "sg:province":"NY",
    "sg:tags":[
        "company"
    ],
    "wof:name":"Allaround Electric",
    "wof:placetype":"venue"
},
  "geometry": {"coordinates":[-74.00535499999999,40.634956],"type":"Point"}
}