{
  "type": "Feature",
  "properties": {
    "addr:full":"847 E 230th St Bronx NY 10466",
    "addr:housenumber":"847",
    "addr:postcode":"10466",
    "addr:street":"E 230Th St",
    "iso:country":"US",
    "sg:address":"847 E 230th St",
    "sg:city":"Bronx",
    "sg:classifiers":[
        {
            "category":"Real Estate",
            "subcategory":"Real Estate Agent",
            "type":"Services"
        }
    ],
    "sg:phone":"+1 718 231 1605",
    "sg:postcode":"10466",
    "sg:province":"NY",
    "sg:tags":[
        "management"
    ],
    "wof:name":"845 E 229 St Real Estate Mgmt",
    "wof:placetype":"venue"
},
  "geometry": {"coordinates":[-73.853756,40.890005],"type":"Point"}
}