{
  "type": "Feature",
  "properties": {
    "addr:full":"415 W 47 St New York NY 10036",
    "addr:housenumber":"415",
    "addr:postcode":"10036",
    "addr:street":"W 47 St",
    "iso:country":"US",
    "sg:address":"415 W 47 St",
    "sg:city":"New York",
    "sg:classifiers":[
        {
            "category":"Building & Trades",
            "subcategory":"Electrical",
            "type":"Services"
        }
    ],
    "sg:phone":"+1 212 582 4410",
    "sg:postcode":"10036",
    "sg:province":"NY",
    "sg:tags":[
        "electrical",
        "contractor"
    ],
    "wof:name":"Al-Wes Electric Services Inc",
    "wof:placetype":"venue"
},
  "geometry": {"coordinates":[-73.992812,40.7627],"type":"Point"}
}