{
  "type": "Feature",
  "properties": {
    "addr:full":"4691 Makyes Rd Syracuse NY 13215",
    "addr:housenumber":"4691",
    "addr:postcode":"13215",
    "addr:street":"Makyes Rd",
    "iso:country":"US",
    "sg:address":"4691 Makyes Rd",
    "sg:city":"Syracuse",
    "sg:classifiers":[
        {
            "category":"Recreation",
            "type":"Entertainment"
        }
    ],
    "sg:phone":"+1   ",
    "sg:postcode":"13215",
    "sg:province":"NY",
    "sg:tags":[
        "club",
        "country",
        "golf",
        "private",
        "course"
    ],
    "wof:name":"Lafayette Country Club",
    "wof:placetype":"venue"
},
  "geometry": {"coordinates":[-76.186053,42.995424],"type":"Point"}
}