{
  "type": "Feature",
  "properties": {
    "iso:country":"US",
    "sg:address":"409 Warren St",
    "sg:city":"Hudson",
    "sg:classifiers":[
        {
            "category":"Shopping",
            "subcategory":"Clothing, Apparel, & Fashions",
            "type":"Retail Goods"
        }
    ],
    "sg:phone":"+1 518 828 6804",
    "sg:postcode":"12534",
    "sg:province":"NY",
    "wof:name":"Ong",
    "wof:placetype":"venue"
},
  "geometry": {"coordinates":[-73.78864400000001,42.250964],"type":"Point"}
}