{
  "type": "Feature",
  "properties": {
    "addr:full":"7 Autumn Dr East Northport NY 11731",
    "addr:housenumber":"7",
    "addr:postcode":"11731",
    "addr:street":"Autumn Dr",
    "iso:country":"US",
    "sg:address":"7 Autumn Dr",
    "sg:city":"East Northport",
    "sg:classifiers":[
        {
            "category":"Professional",
            "subcategory":"Secretarial Services",
            "type":"Services"
        }
    ],
    "sg:phone":"+1   ",
    "sg:postcode":"11731",
    "sg:province":"NY",
    "sg:tags":[
        "resume",
        "writing"
    ],
    "wof:name":"Actresume Inc",
    "wof:placetype":"venue"
},
  "geometry": {"coordinates":[-73.302346,40.877413],"type":"Point"}
}