{
  "type": "Feature",
  "properties": {
    "iso:country":"US",
    "sg:address":"220 3rd St",
    "sg:city":"Brooklyn",
    "sg:classifiers":[
        {
            "category":"Wholesale",
            "subcategory":"Auto Parts",
            "type":"Manufacturing & Wholesale Goods"
        }
    ],
    "sg:phone":"+1 718 858 6262",
    "sg:postcode":"11215",
    "sg:province":"NY",
    "wof:name":"Radiator Express",
    "wof:placetype":"venue"
},
  "geometry": {"coordinates":[-73.989452,40.67591],"type":"Point"}
}