{
  "type": "Feature",
  "properties": {
    "addr:full":"206 Nanuet Mall S Nanuet NY 10954",
    "addr:housenumber":"206",
    "addr:postcode":"10954",
    "addr:street":"Nanuet Mall S",
    "iso:country":"US",
    "sg:address":"206 Nanuet Mall S",
    "sg:city":"Nanuet",
    "sg:classifiers":[
        {
            "category":"Food & Beverages",
            "subcategory":"Bakery",
            "type":"Retail Goods"
        }
    ],
    "sg:phone":"+1 845 627 5404",
    "sg:postcode":"10954",
    "sg:province":"NY",
    "sg:tags":[
        "pretzel"
    ],
    "wof:name":"Auntie Anne's Hand Rolled Soft",
    "wof:placetype":"venue"
},
  "geometry": {"coordinates":[-74.015333,41.09339],"type":"Point"}
}