{
  "type": "Feature",
  "properties": {
    "addr:full":"545 Fulton Ave Hempstead NY 11550",
    "addr:housenumber":"545",
    "addr:postcode":"11550",
    "addr:street":"Fulton Ave",
    "iso:country":"US",
    "sg:address":"545 Fulton Ave",
    "sg:city":"Hempstead",
    "sg:classifiers":[
        {
            "category":"Shopping",
            "subcategory":"Clothing, Apparel, & Fashions",
            "type":"Retail Goods"
        }
    ],
    "sg:phone":"+1 516 564 8238",
    "sg:postcode":"11550",
    "sg:province":"NY",
    "wof:name":"H & M Express Corp",
    "wof:placetype":"venue"
},
  "geometry": {"coordinates":[-73.611463,40.711317],"type":"Point"}
}