{
  "type": "Feature",
  "properties": {
    "iso:country":"US",
    "sg:address":"58 Market St",
    "sg:city":"Brockport",
    "sg:classifiers":[
        {
            "category":"Professional",
            "subcategory":"Accounting & Tax Preparation",
            "type":"Services"
        }
    ],
    "sg:phone":"+1 585 637 3860",
    "sg:postcode":"14420",
    "sg:province":"NY",
    "sg:tags":[
        "accountant"
    ],
    "wof:name":"Carmen E Fowler",
    "wof:placetype":"venue"
},
  "geometry": {"coordinates":[-77.93612400000001,43.215131],"type":"Point"}
}