{
  "type": "Feature",
  "properties": {
    "iso:country":"US",
    "sg:address":"70 Jay Scutti Blvd",
    "sg:city":"Rochester",
    "sg:classifiers":[
        {
            "category":"Recreation",
            "subcategory":"Amusement Park",
            "type":"Entertainment"
        }
    ],
    "sg:phone":"+1 585 272 7888",
    "sg:postcode":"14623",
    "sg:province":"NY",
    "wof:name":"Clubhouse Fun Ctr",
    "wof:placetype":"venue"
},
  "geometry": {"coordinates":[-77.634632,43.091155],"type":"Point"}
}