{
  "type": "Feature",
  "properties": {
    "addr:full":"1580 Grand Ave Baldwin NY 11510",
    "addr:housenumber":"1580",
    "addr:postcode":"11510",
    "addr:street":"Grand Ave",
    "iso:country":"US",
    "sg:address":"1580 Grand Ave",
    "sg:city":"Baldwin",
    "sg:classifiers":[
        {
            "category":"Retail",
            "subcategory":"Auto Repair",
            "type":"Services"
        }
    ],
    "sg:phone":"+1   ",
    "sg:postcode":"11510",
    "sg:province":"NY",
    "sg:tags":[
        "general"
    ],
    "wof:name":"Veterans Motor Service",
    "wof:placetype":"venue"
},
  "geometry": {"coordinates":[-73.61089,40.671774],"type":"Point"}
}