{
  "type": "Feature",
  "properties": {
    "iso:country":"US",
    "sg:address":"209 Brook St",
    "sg:city":"Scarsdale",
    "sg:classifiers":[
        {
            "category":"Retail",
            "subcategory":"Laundry & Dry Cleaning",
            "type":"Services"
        }
    ],
    "sg:phone":"+1 914 725 6804",
    "sg:postcode":"10583",
    "sg:province":"NY",
    "sg:tags":[
        "cleaners"
    ],
    "wof:name":"Fox Meadow",
    "wof:placetype":"venue"
},
  "geometry": {"coordinates":[-73.80286,40.976262],"type":"Point"}
}