{
  "type": "Feature",
  "properties": {
    "addr:full":"213 Albany Post Rd Montrose NY 10548",
    "addr:housenumber":"213",
    "addr:postcode":"10548",
    "addr:street":"Albany Post Rd",
    "iso:country":"US",
    "sg:address":"213 Albany Post Rd",
    "sg:city":"Montrose",
    "sg:classifiers":[
        {
            "category":"Personal",
            "type":"Services"
        }
    ],
    "sg:phone":"+1 914 788 9790",
    "sg:postcode":"10548",
    "sg:province":"NY",
    "sg:tags":[
        "electrolysis"
    ],
    "wof:name":"Pretty Face",
    "wof:placetype":"venue"
},
  "geometry": {"coordinates":[-73.923512,41.240413],"type":"Point"}
}