{
  "type": "Feature",
  "properties": {
    "addr:full":"14 20th St Brooklyn NY 11232",
    "addr:housenumber":"14",
    "addr:postcode":"11232",
    "addr:street":"20Th St",
    "iso:country":"US",
    "sg:address":"14 20th St",
    "sg:city":"Brooklyn",
    "sg:classifiers":[
        {
            "category":"Home & Garden",
            "subcategory":"Furniture",
            "type":"Retail Goods"
        },
        {
            "category":"Wholesale",
            "subcategory":"Furniture",
            "type":"Manufacturing & Wholesale Goods"
        }
    ],
    "sg:phone":"+1 718 832 6541",
    "sg:postcode":"11232",
    "sg:province":"NY",
    "wof:name":"Brandon of Brooklyn Inc",
    "wof:placetype":"venue"
},
  "geometry": {"coordinates":[-73.99731800000001,40.664624],"type":"Point"}
}