{
  "type": "Feature",
  "properties": {
    "addr:full":"30 Harrison St Binghamton NY 13905",
    "addr:housenumber":"30",
    "addr:postcode":"13905",
    "addr:street":"Harrison St",
    "iso:country":"US",
    "sg:address":"30 Harrison St",
    "sg:city":"Binghamton",
    "sg:classifiers":[
        {
            "category":"Health Services",
            "subcategory":"Clinic",
            "type":"Services"
        }
    ],
    "sg:phone":"+1 607 763 6784",
    "sg:postcode":"13905",
    "sg:province":"NY",
    "sg:tags":[
        "loss",
        "center",
        "weight"
    ],
    "wof:name":"Optifast",
    "wof:placetype":"venue"
},
  "geometry": {"coordinates":[-75.944896,42.103054],"type":"Point"}
}