{
  "type": "Feature",
  "properties": {
    "iso:country":"US",
    "sg:address":"49 W Sunrise Hwy",
    "sg:city":"Lindenhurst",
    "sg:classifiers":[
        {
            "category":"Food & Beverages",
            "subcategory":"Groceries & Convenience Stores",
            "type":"Retail Goods"
        }
    ],
    "sg:phone":"+1   ",
    "sg:postcode":"11757",
    "sg:province":"NY",
    "wof:name":"Great American Food Stores",
    "wof:placetype":"venue"
},
  "geometry": {"coordinates":[-73.38561300000001,40.696865],"type":"Point"}
}