{
  "type": "Feature",
  "properties": {
    "iso:country":"US",
    "sg:address":"505 Root Rd",
    "sg:city":"Brockport",
    "sg:classifiers":[
        {
            "category":"Autos & Motor Vehicles",
            "subcategory":"Automobile Sales",
            "type":"Retail Goods"
        }
    ],
    "sg:phone":"+1   ",
    "sg:postcode":"14420",
    "sg:province":"NY",
    "sg:tags":[
        "used"
    ],
    "wof:name":"J R Auto Service",
    "wof:placetype":"venue"
},
  "geometry": {"coordinates":[-77.915122,43.143941],"type":"Point"}
}