{
  "type": "Feature",
  "properties": {
    "addr:full":"153 E 43rd St New York NY 10017",
    "addr:housenumber":"153",
    "addr:postcode":"10017",
    "addr:street":"E 43Rd St",
    "iso:country":"US",
    "sg:address":"153 E 43rd St",
    "sg:city":"New York",
    "sg:classifiers":[
        {
            "category":"Personal",
            "subcategory":"Beauty Salon",
            "type":"Services"
        }
    ],
    "sg:phone":"+1 212 856 0143",
    "sg:postcode":"10017",
    "sg:province":"NY",
    "sg:tags":[
        "nail",
        "shop"
    ],
    "wof:name":"Amy Yee Nail Inc",
    "wof:placetype":"venue"
},
  "geometry": {"coordinates":[-73.9748,40.751801],"type":"Point"}
}