{
  "type": "Feature",
  "properties": {
    "iso:country":"US",
    "sg:address":"2266 Lake Shore Rd",
    "sg:city":"Essex",
    "sg:classifiers":[
        {
            "category":"Restaurant",
            "type":"Food & Drink"
        }
    ],
    "sg:phone":"+1 518 963 7700",
    "sg:postcode":"12936",
    "sg:province":"NY",
    "sg:website":"www.essexshipyard.com",
    "wof:name":"Essex Shipyard & Rudder Club",
    "wof:placetype":"venue"
},
  "geometry": {"coordinates":[-73.350657,44.306592],"type":"Point"}
}