{
  "type": "Feature",
  "properties": {
    "addr:full":"2290 Main St E Rochester NY 14609",
    "addr:housenumber":"2290",
    "addr:postcode":"14609",
    "addr:street":"Main St E",
    "iso:country":"US",
    "sg:address":"2290 Main St E",
    "sg:city":"Rochester",
    "sg:classifiers":[
        {
            "category":"Wholesale",
            "subcategory":"Machinery & Supplies",
            "type":"Manufacturing & Wholesale Goods"
        }
    ],
    "sg:phone":"+1 585 424 4223",
    "sg:postcode":"14609",
    "sg:province":"NY",
    "sg:tags":[
        "equipment",
        "industrial"
    ],
    "wof:name":"Honeywell",
    "wof:placetype":"venue"
},
  "geometry": {"coordinates":[-77.54965300000001,43.159524],"type":"Point"}
}