{
  "type": "Feature",
  "properties": {
    "iso:country":"US",
    "sg:address":"1107 Quentin Rd",
    "sg:city":"Brooklyn",
    "sg:classifiers":[
        {
            "category":"Personal",
            "subcategory":"Beauty Salon",
            "type":"Services"
        }
    ],
    "sg:phone":"+1 718 375 3737",
    "sg:postcode":"11229",
    "sg:province":"NY",
    "sg:tags":[
        "manicuring"
    ],
    "wof:name":"Treschic Inc",
    "wof:placetype":"venue"
},
  "geometry": {"coordinates":[-73.961015,40.60802],"type":"Point"}
}