{
  "type": "Feature",
  "properties": {
    "iso:country":"US",
    "sg:address":"26 Vause St",
    "sg:city":"Northport",
    "sg:classifiers":[
        {
            "category":"Building & Trades",
            "subcategory":"Construction",
            "type":"Services"
        }
    ],
    "sg:phone":"+1 631 361 9223",
    "sg:postcode":"11768",
    "sg:province":"NY",
    "sg:tags":[
        "general"
    ],
    "wof:name":"Diesel Construction LLC",
    "wof:placetype":"venue"
},
  "geometry": {"coordinates":[-73.323504,40.902171],"type":"Point"}
}