{
  "type": "Feature",
  "properties": {
    "iso:country":"US",
    "sg:address":"420 E Main St",
    "sg:city":"Riverhead",
    "sg:classifiers":[
        {
            "category":"Social Services",
            "type":"Services"
        }
    ],
    "sg:phone":"+1 631 369 1718",
    "sg:postcode":"11901",
    "sg:province":"NY",
    "sg:tags":[
        "counselor",
        "marriage",
        "family"
    ],
    "wof:name":"Christian N Caputo",
    "wof:placetype":"venue"
},
  "geometry": {"coordinates":[-72.65654499999999,40.918761],"type":"Point"}
}