{
  "type": "Feature",
  "properties": {
    "iso:country":"US",
    "sg:address":"1741 2nd Ave",
    "sg:city":"New York",
    "sg:classifiers":[
        {
            "category":"Restaurant",
            "type":"Food & Drink"
        }
    ],
    "sg:phone":"+1 212 722 1923",
    "sg:postcode":"10128",
    "sg:province":"NY",
    "sg:tags":[
        "italian"
    ],
    "wof:name":"Trattoria Novanta",
    "wof:placetype":"venue"
},
  "geometry": {"coordinates":[-73.949806,40.780499],"type":"Point"}
}