{
  "type": "Feature",
  "properties": {
    "iso:country":"US",
    "sg:address":"10 Braemar Rd",
    "sg:city":"East Setauket",
    "sg:classifiers":[
        {
            "category":"Professional",
            "type":"Services"
        }
    ],
    "sg:phone":"+1   ",
    "sg:postcode":"11733",
    "sg:province":"NY",
    "wof:name":"About Smiles Inc",
    "wof:placetype":"venue"
},
  "geometry": {"coordinates":[-73.09629700000001,40.945723],"type":"Point"}
}