{
  "type": "Feature",
  "properties": {
    "iso:country":"US",
    "sg:address":"34 Public Sq",
    "sg:city":"Holley",
    "sg:classifiers":[
        {
            "category":"Insurance",
            "subcategory":"Insurance Agent",
            "type":"Services"
        }
    ],
    "sg:phone":"+1 585 638 6313",
    "sg:postcode":"14470",
    "sg:province":"NY",
    "wof:name":"James S Sullivan Agency Inc",
    "wof:placetype":"venue"
},
  "geometry": {"coordinates":[-78.02495,43.22482],"type":"Point"}
}