{
  "type": "Feature",
  "properties": {
    "addr:full":"995 Fox St Bronx NY 10459",
    "addr:housenumber":"995",
    "addr:postcode":"10459",
    "addr:street":"Fox St",
    "iso:country":"US",
    "sg:address":"995 Fox St",
    "sg:city":"Bronx",
    "sg:classifiers":[
        {
            "category":"Retail",
            "subcategory":"Repair Shop",
            "type":"Services"
        }
    ],
    "sg:phone":"+1 718 535 9334",
    "sg:postcode":"10459",
    "sg:province":"NY",
    "sg:tags":[
        "lock",
        "locksmith"
    ],
    "wof:name":"24 Hour Emergency Locksmith",
    "wof:placetype":"venue"
},
  "geometry": {"coordinates":[-73.89396499999999,40.82216],"type":"Point"}
}