{
  "type": "Feature",
  "properties": {
    "addr:full":"475 Park Ave Lindenhurst NY 11757",
    "addr:housenumber":"475",
    "addr:postcode":"11757",
    "addr:street":"Park Ave",
    "iso:country":"US",
    "sg:address":"475 Park Ave",
    "sg:city":"Lindenhurst",
    "sg:classifiers":[
        {
            "category":"Travel",
            "subcategory":"Travel Agent",
            "type":"Entertainment"
        }
    ],
    "sg:phone":"+1   ",
    "sg:postcode":"11757",
    "sg:province":"NY",
    "wof:name":"Empress Travel",
    "wof:placetype":"venue"
},
  "geometry": {"coordinates":[-73.353206,40.688329],"type":"Point"}
}