{
  "type": "Feature",
  "properties": {
    "addr:full":"9614 Rte 474 Clymer NY 14724",
    "addr:housenumber":"9614",
    "addr:postcode":"14724",
    "addr:street":"Rte 474 Clymer",
    "iso:country":"US",
    "sg:address":"9614 Rte 474",
    "sg:city":"Clymer",
    "sg:classifiers":[
        {
            "category":"Farming",
            "subcategory":"Dairy Farm",
            "type":"Manufacturing & Wholesale Goods"
        }
    ],
    "sg:phone":"+1 716 355 2575",
    "sg:postcode":"14724",
    "sg:province":"NY",
    "wof:name":"Dunnewold Farm L L C",
    "wof:placetype":"venue"
},
  "geometry": {"coordinates":[-79.68959700000001,42.024788],"type":"Point"}
}