{
  "type": "Feature",
  "properties": {
    "addr:full":"The Sage Theater 711 Seventh Avenue New York NY 10023",
    "addr:housenumber":"711",
    "addr:postcode":"10023",
    "addr:street":"Seventh Avenue",
    "iso:country":"US",
    "sg:address":"The Sage Theater 711 Seventh Avenue",
    "sg:city":"New York",
    "sg:classifiers":[
        {
            "category":"Arts & Performance",
            "subcategory":"Arts Center",
            "type":"Entertainment"
        }
    ],
    "sg:phone":"+1 212 279 4200",
    "sg:postcode":"10023",
    "sg:province":"NY",
    "sg:tags":[
        "performing"
    ],
    "sg:website":"www.motherloadshow.com",
    "wof:name":"Mother Load",
    "wof:placetype":"venue"
},
  "geometry": {"coordinates":[-73.95386000000001,40.80124],"type":"Point"}
}