{
  "type": "Feature",
  "properties": {
    "addr:full":"491 7th Avenue Brooklyn NY 11215",
    "addr:housenumber":"491",
    "addr:postcode":"11215",
    "addr:street":"7Th Avenue",
    "iso:country":"US",
    "sg:address":"491 7th Avenue",
    "sg:city":"Brooklyn",
    "sg:classifiers":[
        {
            "category":"Retail",
            "subcategory":"Laundry & Dry Cleaning",
            "type":"Services"
        }
    ],
    "sg:postcode":"11215",
    "sg:province":"NY",
    "wof:name":"7th Avenue Laundromat",
    "wof:placetype":"venue"
},
  "geometry": {"coordinates":[-73.985922,40.66167],"type":"Point"}
}