{
  "type": "Feature",
  "properties": {
    "iso:country":"US",
    "sg:address":"3572 Co Rte 45",
    "sg:city":"Oswego",
    "sg:classifiers":[
        {
            "category":"Retail",
            "subcategory":"Auto Repair",
            "type":"Services"
        }
    ],
    "sg:phone":"+1 315 342 2204",
    "sg:postcode":"13126",
    "sg:province":"NY",
    "sg:tags":[
        "wheel",
        "axle",
        "alignment"
    ],
    "wof:name":"Alignment Specialists",
    "wof:placetype":"venue"
},
  "geometry": {"coordinates":[-76.438475,43.404227],"type":"Point"}
}