{
  "type": "Feature",
  "properties": {
    "addr:full":"501 Lexington Ave New York NY 10017",
    "addr:housenumber":"501",
    "addr:postcode":"10017",
    "addr:street":"Lexington Ave",
    "iso:country":"US",
    "sg:address":"501 Lexington Ave",
    "sg:city":"New York",
    "sg:classifiers":[
        {
            "category":"Travel",
            "subcategory":"Hotels & Motels",
            "type":"Entertainment"
        }
    ],
    "sg:phone":"+1 212 755 1400",
    "sg:postcode":"10017",
    "sg:province":"NY",
    "sg:website":"www.rogersmith.com",
    "wof:name":"Roger Smith Hotel",
    "wof:placetype":"venue"
},
  "geometry": {"coordinates":[-73.97370100000001,40.754601],"type":"Point"}
}