{
  "type": "Feature",
  "properties": {
    "addr:full":"41 S Bedford Rd Mount Kisco NY 10549",
    "addr:housenumber":"41",
    "addr:postcode":"10549",
    "addr:street":"S Bedford Rd",
    "iso:country":"US",
    "sg:address":"41 S Bedford Rd",
    "sg:city":"Mount Kisco",
    "sg:classifiers":[
        {
            "category":"Health Services",
            "subcategory":"Doctor",
            "type":"Services"
        }
    ],
    "sg:phone":"+1   ",
    "sg:postcode":"10549",
    "sg:province":"NY",
    "sg:tags":[
        "medical"
    ],
    "wof:name":"Martin Saltzman MD",
    "wof:placetype":"venue"
},
  "geometry": {"coordinates":[-73.722189,41.196705],"type":"Point"}
}