{
  "type": "Feature",
  "properties": {
    "addr:full":"221 Nassau St Westbury NY 11590",
    "addr:housenumber":"221",
    "addr:postcode":"11590",
    "addr:street":"Nassau St",
    "iso:country":"US",
    "sg:address":"221 Nassau St",
    "sg:city":"Westbury",
    "sg:classifiers":[
        {
            "category":"Manufacturing",
            "subcategory":"Metals",
            "type":"Manufacturing & Wholesale Goods"
        }
    ],
    "sg:phone":"+1 516 333 5030",
    "sg:postcode":"11590",
    "sg:province":"NY",
    "sg:tags":[
        "fabricator",
        "sheet"
    ],
    "wof:name":"Air-Vent Awning Mfg Co",
    "wof:placetype":"venue"
},
  "geometry": {"coordinates":[-73.580912,40.756707],"type":"Point"}
}