{
  "type": "Feature",
  "properties": {
    "iso:country":"US",
    "sg:address":"3951 Riverhead Morichs Rd",
    "sg:city":"Riverhead",
    "sg:classifiers":[
        {
            "category":"Sports & Exercise",
            "subcategory":"Bowling",
            "type":"Entertainment"
        }
    ],
    "sg:phone":"+1 631 727 6622",
    "sg:postcode":"11901",
    "sg:province":"NY",
    "wof:name":"Wildwood Lake Bowl Inc",
    "wof:placetype":"venue"
},
  "geometry": {"coordinates":[-72.666702,40.908199],"type":"Point"}
}