{
  "type": "Feature",
  "properties": {
    "iso:country":"US",
    "sg:address":"1357 Ulster Ave",
    "sg:city":"Kingston",
    "sg:classifiers":[
        {
            "category":"Professional",
            "subcategory":"Accounting & Tax Preparation",
            "type":"Services"
        }
    ],
    "sg:phone":"+1 845 336 7709",
    "sg:postcode":"12401",
    "sg:province":"NY",
    "sg:tags":[
        "return",
        "filing"
    ],
    "wof:name":"Brenner Income Tax",
    "wof:placetype":"venue"
},
  "geometry": {"coordinates":[-73.988952,41.971673],"type":"Point"}
}