{
  "type": "Feature",
  "properties": {
    "addr:full":"279 Bushwick Ave Brooklyn NY 11206",
    "addr:housenumber":"279",
    "addr:postcode":"11206",
    "addr:street":"Bushwick Ave",
    "iso:country":"US",
    "sg:address":"279 Bushwick Ave",
    "sg:city":"Brooklyn",
    "sg:classifiers":[
        {
            "category":"Restaurant",
            "type":"Food & Drink"
        }
    ],
    "sg:phone":"+1 718 381 2889",
    "sg:postcode":"11206",
    "sg:province":"NY",
    "sg:tags":[
        "thai"
    ],
    "wof:name":"Note Thai",
    "wof:placetype":"venue"
},
  "geometry": {"coordinates":[-73.939655,40.706534],"type":"Point"}
}