{
  "type": "Feature",
  "properties": {
    "addr:full":"56 Echo Ave Miller Place NY 11764",
    "addr:housenumber":"56",
    "addr:postcode":"11764",
    "addr:street":"Echo Ave",
    "iso:country":"US",
    "sg:address":"56 Echo Ave",
    "sg:city":"Miller Place",
    "sg:classifiers":[
        {
            "category":"Shopping",
            "subcategory":"Pharmacy",
            "type":"Retail Goods"
        }
    ],
    "sg:phone":"+1 631 642 8175",
    "sg:postcode":"11764",
    "sg:province":"NY",
    "wof:name":"Echo Pharmacy LLC",
    "wof:placetype":"venue"
},
  "geometry": {"coordinates":[-73.00009900000001,40.943369],"type":"Point"}
}