{
  "type": "Feature",
  "properties": {
    "addr:full":"66 Rte 25A Shoreham NY 11786",
    "addr:housenumber":"66",
    "addr:postcode":"11786",
    "addr:street":"Rte 25A",
    "iso:country":"US",
    "sg:address":"66 Rte 25A",
    "sg:city":"Shoreham",
    "sg:classifiers":[
        {
            "category":"Professional",
            "type":"Services"
        }
    ],
    "sg:phone":"+1 631 744 7555",
    "sg:postcode":"11786",
    "sg:province":"NY",
    "sg:tags":[
        "establishment"
    ],
    "wof:name":"Blue Ribbon Contrng & Design",
    "wof:placetype":"venue"
},
  "geometry": {"coordinates":[-72.896106,40.946479],"type":"Point"}
}