{
  "type": "Feature",
  "properties": {
    "addr:full":"500 N Main St Canandaigua NY 14424",
    "addr:housenumber":"500",
    "addr:postcode":"14424",
    "addr:street":"N Main St",
    "iso:country":"US",
    "sg:address":"500 N Main St",
    "sg:city":"Canandaigua",
    "sg:classifiers":[
        {
            "category":"Health Services",
            "subcategory":"Doctor",
            "type":"Services"
        }
    ],
    "sg:phone":"+1   ",
    "sg:postcode":"14424",
    "sg:province":"NY",
    "wof:name":"Dr Phillip G Cary DDS",
    "wof:placetype":"venue"
},
  "geometry": {"coordinates":[-77.29214899999999,42.902527],"type":"Point"}
}