{
  "type": "Feature",
  "properties": {
    "iso:country":"US",
    "sg:address":"17 Herdman Ct",
    "sg:city":"Middle Island",
    "sg:classifiers":[
        {
            "category":"Autos & Motor Vehicles",
            "subcategory":"Automobile Sales",
            "type":"Retail Goods"
        }
    ],
    "sg:phone":"+1 631 345 3985",
    "sg:postcode":"11953",
    "sg:province":"NY",
    "sg:tags":[
        "car",
        "dealer"
    ],
    "wof:name":"Discount Motors",
    "wof:placetype":"venue"
},
  "geometry": {"coordinates":[-72.92148400000001,40.881805],"type":"Point"}
}