{
  "type": "Feature",
  "properties": {
    "addr:full":"530 Humphrey Rd Scottsville NY 14546",
    "addr:housenumber":"530",
    "addr:postcode":"14546",
    "addr:street":"Humphrey Rd",
    "iso:country":"US",
    "sg:address":"530 Humphrey Rd",
    "sg:city":"Scottsville",
    "sg:classifiers":[
        {
            "category":"Manufacturing",
            "subcategory":"Printing",
            "type":"Manufacturing & Wholesale Goods"
        }
    ],
    "sg:phone":"+1   ",
    "sg:postcode":"14546",
    "sg:province":"NY",
    "sg:tags":[
        "publishing"
    ],
    "wof:name":"Harmon Homes",
    "wof:placetype":"venue"
},
  "geometry": {"coordinates":[-77.757229,43.067709],"type":"Point"}
}