{
  "type": "Feature",
  "properties": {
    "addr:full":"311 Winding Rd Old Bethpage NY 11804",
    "addr:housenumber":"311",
    "addr:postcode":"11804",
    "addr:street":"Winding Rd",
    "iso:country":"US",
    "sg:address":"311 Winding Rd",
    "sg:city":"Old Bethpage",
    "sg:classifiers":[
        {
            "category":"Freight",
            "type":"Transportation"
        }
    ],
    "sg:phone":"+1   ",
    "sg:postcode":"11804",
    "sg:province":"NY",
    "sg:tags":[
        "trucker",
        "local",
        "rubbish",
        "removal"
    ],
    "wof:name":"Ace Garbage & Rubbish Removal",
    "wof:placetype":"venue"
},
  "geometry": {"coordinates":[-73.448587,40.763082],"type":"Point"}
}