{
  "type": "Feature",
  "properties": {
    "addr:full":"124 W Fordham Rd Bronx NY 10468",
    "addr:housenumber":"124",
    "addr:postcode":"10468",
    "addr:street":"W Fordham Rd",
    "iso:country":"US",
    "sg:address":"124 W Fordham Rd",
    "sg:city":"Bronx",
    "sg:classifiers":[
        {
            "category":"Health Services",
            "subcategory":"Doctor",
            "type":"Services"
        }
    ],
    "sg:phone":"+1 718 367 8500",
    "sg:postcode":"10468",
    "sg:province":"NY",
    "sg:tags":[
        "medical",
        "clinic"
    ],
    "wof:name":"West Fordham Road Med Clinic",
    "wof:placetype":"venue"
},
  "geometry": {"coordinates":[-73.907229,40.862728],"type":"Point"}
}