{
  "type": "Feature",
  "properties": {
    "addr:full":"30 W 22 St New York NY 10010",
    "addr:housenumber":"30",
    "addr:postcode":"10010",
    "addr:street":"W 22 St",
    "iso:country":"US",
    "sg:address":"30 W 22 St",
    "sg:city":"New York",
    "sg:classifiers":[
        {
            "category":"Professional",
            "subcategory":"Employment Agencies",
            "type":"Services"
        }
    ],
    "sg:phone":"+1 212 226 2432",
    "sg:postcode":"10010",
    "sg:province":"NY",
    "sg:tags":[
        "industry",
        "fashion",
        "staffing",
        "for"
    ],
    "wof:name":"Project Solvers Inc",
    "wof:placetype":"venue"
},
  "geometry": {"coordinates":[-73.992616,40.741773],"type":"Point"}
}