{
  "type": "Feature",
  "properties": {
    "iso:country":"US",
    "sg:address":"46 104th St",
    "sg:city":"Corona",
    "sg:classifiers":[
        {
            "category":"Food & Beverages",
            "subcategory":"Groceries & Convenience Stores",
            "type":"Retail Goods"
        }
    ],
    "sg:phone":"+1   ",
    "sg:postcode":"11368",
    "sg:province":"NY",
    "sg:tags":[
        "alcoholic"
    ],
    "wof:name":"Leos Lattcini",
    "wof:placetype":"venue"
},
  "geometry": {"coordinates":[-73.86317099999999,40.752685],"type":"Point"}
}