{
  "type": "Feature",
  "properties": {
    "iso:country":"US",
    "sg:address":"1862 Lexington Ave",
    "sg:city":"New York",
    "sg:classifiers":[
        {
            "category":"Restaurant",
            "type":"Food & Drink"
        }
    ],
    "sg:phone":"+1 800 953 7488",
    "sg:postcode":"10029",
    "sg:province":"NY",
    "sg:tags":[
        "pizza"
    ],
    "wof:name":"Harlems Rays Pizza",
    "wof:placetype":"venue"
},
  "geometry": {"coordinates":[-73.942093,40.798246],"type":"Point"}
}