{
  "type": "Feature",
  "properties": {
    "addr:full":"1650 Union Center Maine Hwy Endicott NY 13760",
    "addr:housenumber":"1650",
    "addr:postcode":"13760",
    "addr:street":"Union Center Maine Hwy",
    "iso:country":"US",
    "sg:address":"1650 Union Center Maine Hwy",
    "sg:city":"Endicott",
    "sg:classifiers":[
        {
            "category":"Personal",
            "subcategory":"Beauty Salon",
            "type":"Services"
        }
    ],
    "sg:phone":"+1 607 785 7906",
    "sg:postcode":"13760",
    "sg:province":"NY",
    "wof:name":"Radiance Family Hair Salon",
    "wof:placetype":"venue"
},
  "geometry": {"coordinates":[-76.065619,42.135971],"type":"Point"}
}