{
  "type": "Feature",
  "properties": {
    "addr:full":"113 W 60th Street New York NY 10023",
    "addr:housenumber":"113",
    "addr:postcode":"10023",
    "addr:street":"W 60Th Street",
    "iso:country":"US",
    "sg:address":"113 W 60th Street",
    "sg:city":"New York",
    "sg:classifiers":[
        {
            "category":"Education",
            "subcategory":"University",
            "type":"Public Place"
        }
    ],
    "sg:phone":"+1 914 332 6000",
    "sg:postcode":"10023",
    "sg:province":"NY",
    "sg:tags":[
        "college"
    ],
    "wof:name":"Fordham University Graduate Center",
    "wof:placetype":"venue"
},
  "geometry": {"coordinates":[-73.984663,40.769974],"type":"Point"}
}