{
  "type": "Feature",
  "properties": {
    "iso:country":"US",
    "sg:address":"119 Cooper St",
    "sg:city":"Babylon",
    "sg:classifiers":[
        {
            "category":"Education",
            "subcategory":"Special Training",
            "type":"Public Place"
        }
    ],
    "sg:phone":"+1 631 893 4540",
    "sg:postcode":"11702",
    "sg:province":"NY",
    "sg:tags":[
        "program",
        "student",
        "exchange"
    ],
    "wof:name":"International Student Exchange",
    "wof:placetype":"venue"
},
  "geometry": {"coordinates":[-73.319541,40.701644],"type":"Point"}
}