{
  "type": "Feature",
  "properties": {
    "addr:full":"13325 Guy R Brewer Blvd Jamaica NY 11434",
    "addr:housenumber":"13325",
    "addr:postcode":"11434",
    "addr:street":"Guy R Brewer Blvd",
    "iso:country":"US",
    "sg:address":"13325 Guy R Brewer Blvd",
    "sg:city":"Jamaica",
    "sg:classifiers":[
        {
            "category":"Sports & Exercise",
            "subcategory":"Sports Center",
            "type":"Entertainment"
        }
    ],
    "sg:phone":"+1 718 723 4190",
    "sg:postcode":"11434",
    "sg:province":"NY",
    "sg:tags":[
        "amateur",
        "team"
    ],
    "wof:name":"Rise",
    "wof:placetype":"venue"
},
  "geometry": {"coordinates":[-73.77619900000001,40.6744],"type":"Point"}
}