{
  "type": "Feature",
  "properties": {
    "addr:full":"12911 95th Ave South Richmond Hill NY 11419",
    "addr:housenumber":"12911",
    "addr:postcode":"11419",
    "addr:street":"95Th Ave South",
    "iso:country":"US",
    "sg:address":"12911 95th Ave",
    "sg:city":"South Richmond Hill",
    "sg:classifiers":[
        {
            "category":"Personal",
            "type":"Services"
        }
    ],
    "sg:phone":"+1 718 639 6650",
    "sg:postcode":"11419",
    "sg:province":"NY",
    "sg:tags":[
        "sewing",
        "alteration"
    ],
    "wof:name":"Bis Millaa Tailoring",
    "wof:placetype":"venue"
},
  "geometry": {"coordinates":[-73.81909899999999,40.694801],"type":"Point"}
}