{
  "type": "Feature",
  "properties": {
    "addr:full":"4 Newkirk Plz Brooklyn NY 11226",
    "addr:housenumber":"4",
    "addr:postcode":"11226",
    "addr:street":"Newkirk Plz",
    "iso:country":"US",
    "sg:address":"4 Newkirk Plz",
    "sg:city":"Brooklyn",
    "sg:classifiers":[
        {
            "category":"Food & Beverages",
            "subcategory":"Fruits & Vegetables",
            "type":"Retail Goods"
        }
    ],
    "sg:phone":"+1 718 434 3355",
    "sg:postcode":"11226",
    "sg:province":"NY",
    "sg:tags":[
        "produce"
    ],
    "wof:name":"Plaza Fruit & Vegetable Inc",
    "wof:placetype":"venue"
},
  "geometry": {"coordinates":[-73.96266900000001,40.634539],"type":"Point"}
}