{
  "type": "Feature",
  "properties": {
    "iso:country":"US",
    "sg:address":"100 Main St",
    "sg:city":"Windsor",
    "sg:classifiers":[
        {
            "category":"Personal",
            "subcategory":"Beauty Salon",
            "type":"Services"
        }
    ],
    "sg:phone":"+1 607 655 2220",
    "sg:postcode":"13865",
    "sg:province":"NY",
    "wof:name":"Beauty Chateau",
    "wof:placetype":"venue"
},
  "geometry": {"coordinates":[-75.63966499999999,42.078908],"type":"Point"}
}