{
  "type": "Feature",
  "properties": {
    "iso:country":"US",
    "sg:address":"430 Bedford Rd",
    "sg:city":"Pleasantville",
    "sg:classifiers":[
        {
            "category":"Building & Trades",
            "subcategory":"Electrical",
            "type":"Services"
        }
    ],
    "sg:phone":"+1 914 769 6395",
    "sg:postcode":"10570",
    "sg:province":"NY",
    "sg:tags":[
        "electrical",
        "contractor"
    ],
    "wof:name":"Charles Borg",
    "wof:placetype":"venue"
},
  "geometry": {"coordinates":[-73.79056199999999,41.134048],"type":"Point"}
}