{
  "type": "Feature",
  "properties": {
    "addr:full":"191 Newtown Rd Plainview NY 11803",
    "addr:housenumber":"191",
    "addr:postcode":"11803",
    "addr:street":"Newtown Rd",
    "iso:country":"US",
    "sg:address":"191 Newtown Rd",
    "sg:city":"Plainview",
    "sg:classifiers":[
        {
            "category":"Wholesale",
            "subcategory":"Machinery & Supplies",
            "type":"Manufacturing & Wholesale Goods"
        }
    ],
    "sg:phone":"+1 516 753 1200",
    "sg:postcode":"11803",
    "sg:province":"NY",
    "sg:tags":[
        "abrasive"
    ],
    "wof:name":"CBE/Conrad Blasius Equip Co",
    "wof:placetype":"venue"
},
  "geometry": {"coordinates":[-73.451545,40.784922],"type":"Point"}
}