{
  "type": "Feature",
  "properties": {
    "iso:country":"US",
    "sg:address":"19 Shonnard Ave",
    "sg:city":"Freeport",
    "sg:classifiers":[
        {
            "category":"Education",
            "subcategory":"Dance Studio",
            "type":"Public Place"
        }
    ],
    "sg:phone":"+1 516 538 8107",
    "sg:postcode":"11520",
    "sg:province":"NY",
    "sg:tags":[
        "instruction",
        "dancing"
    ],
    "wof:name":"Progressive Movement Dance",
    "wof:placetype":"venue"
},
  "geometry": {"coordinates":[-73.576272,40.66036],"type":"Point"}
}