{
  "type": "Feature",
  "properties": {
    "addr:full":"270 W Sunrise Hwy Valley Stream NY 11581",
    "addr:housenumber":"270",
    "addr:postcode":"11581",
    "addr:street":"W Sunrise Hwy",
    "iso:country":"US",
    "sg:address":"270 W Sunrise Hwy",
    "sg:city":"Valley Stream",
    "sg:classifiers":[
        {
            "category":"Retail",
            "subcategory":"Auto Rental",
            "type":"Services"
        },
        {
            "category":"Retail",
            "subcategory":"Auto Repair",
            "type":"Services"
        }
    ],
    "sg:phone":"+1 516 791 6075",
    "sg:postcode":"11581",
    "sg:province":"NY",
    "sg:tags":[
        "car"
    ],
    "wof:name":"Ace Auto Clinic",
    "wof:placetype":"venue"
},
  "geometry": {"coordinates":[-73.71036599999999,40.662135],"type":"Point"}
}