{
  "type": "Feature",
  "properties": {
    "iso:country":"US",
    "sg:address":"1619 Boston Rd",
    "sg:city":"Bronx",
    "sg:classifiers":[
        {
            "category":"Education",
            "subcategory":"School",
            "type":"Public Place"
        }
    ],
    "sg:phone":"+1 718 991 2209",
    "sg:postcode":"10460",
    "sg:province":"NY",
    "sg:tags":[
        "high"
    ],
    "sg:website":"http://www.autohs.com",
    "wof:name":"Foreign Language/Global Study",
    "wof:placetype":"venue"
},
  "geometry": {"coordinates":[-73.890698,40.835844],"type":"Point"}
}