{
  "type": "Feature",
  "properties": {
    "addr:full":"490 Rowley Rd Depew NY 14043",
    "addr:housenumber":"490",
    "addr:postcode":"14043",
    "addr:street":"Rowley Rd",
    "iso:country":"US",
    "sg:address":"490 Rowley Rd",
    "sg:city":"Depew",
    "sg:classifiers":[
        {
            "category":"Professional",
            "subcategory":"Testing Lab",
            "type":"Services"
        }
    ],
    "sg:phone":"+1 716 651 0030",
    "sg:postcode":"14043",
    "sg:province":"NY",
    "sg:tags":[
        "laboratory"
    ],
    "sg:website":"www.emsl.com",
    "wof:name":"EMSL Analytical Inc",
    "wof:placetype":"venue"
},
  "geometry": {"coordinates":[-78.71775700000001,42.896318],"type":"Point"}
}