{
  "type": "Feature",
  "properties": {
    "iso:country":"US",
    "sg:address":"4109 Walden Ave",
    "sg:city":"Lancaster",
    "sg:classifiers":[
        {
            "category":"Autos & Motor Vehicles",
            "subcategory":"Auto Supplies",
            "type":"Retail Goods"
        },
        {
            "category":"Wholesale",
            "subcategory":"Auto Parts",
            "type":"Manufacturing & Wholesale Goods"
        }
    ],
    "sg:phone":"+1 716 681 8446",
    "sg:postcode":"14086",
    "sg:province":"NY",
    "sg:tags":[
        "tire"
    ],
    "wof:name":"Hurtubise Tires Inc",
    "wof:placetype":"venue"
},
  "geometry": {"coordinates":[-78.62775000000001,42.922635],"type":"Point"}
}