{
  "type": "Feature",
  "properties": {
    "addr:full":"1511 Route 22 Ste C8 Brewster NY 10509",
    "addr:housenumber":"1511",
    "addr:postcode":"10509",
    "addr:street":"Route 22 Ste C8",
    "iso:country":"US",
    "sg:address":"1511 Route 22 Ste C8",
    "sg:city":"Brewster",
    "sg:classifiers":[
        {
            "category":"Personal",
            "subcategory":"Nail Salon",
            "type":"Services"
        }
    ],
    "sg:phone":"+1 845 278 0222",
    "sg:postcode":"10509",
    "sg:province":"NY",
    "wof:name":"Fashion Nails",
    "wof:placetype":"venue"
},
  "geometry": {"coordinates":[-73.576421,41.420263],"type":"Point"}
}