{
  "type": "Feature",
  "properties": {
    "addr:full":"9920 4th Avenue Suite 207 Brooklyn NY 11209",
    "addr:housenumber":"9920",
    "addr:postcode":"11209",
    "addr:street":"4Th Avenue Suite 207",
    "iso:country":"US",
    "sg:address":"9920 4th Avenue Suite 207",
    "sg:city":"Brooklyn",
    "sg:classifiers":[
        {
            "category":"Health Services",
            "subcategory":"Doctor",
            "type":"Services"
        }
    ],
    "sg:phone":"+1 718 238 1518",
    "sg:postcode":"11209",
    "sg:province":"NY",
    "wof:name":"Accettola Albert B MD Jr",
    "wof:placetype":"venue"
},
  "geometry": {"coordinates":[-74.033275,40.613299],"type":"Point"}
}