{
  "type": "Feature",
  "properties": {
    "iso:country":"US",
    "sg:address":"51 State Pl",
    "sg:city":"Huntington",
    "sg:classifiers":[
        {
            "category":"Building & Trades",
            "subcategory":"Electrical",
            "type":"Services"
        }
    ],
    "sg:phone":"+1 631 351 5444",
    "sg:postcode":"11743",
    "sg:province":"NY",
    "sg:tags":[
        "communications",
        "telephone"
    ],
    "wof:name":"Reyal Communications Inc",
    "wof:placetype":"venue"
},
  "geometry": {"coordinates":[-73.365824,40.830535],"type":"Point"}
}