{
  "type": "Feature",
  "properties": {
    "addr:full":"11 Summit St Salamanca NY 14779",
    "addr:housenumber":"11",
    "addr:postcode":"14779",
    "addr:street":"Summit St",
    "iso:country":"US",
    "sg:address":"11 Summit St",
    "sg:city":"Salamanca",
    "sg:classifiers":[
        {
            "category":"Food & Beverages",
            "subcategory":"Groceries & Convenience Stores",
            "type":"Retail Goods"
        }
    ],
    "sg:phone":"+1 716 945 2630",
    "sg:postcode":"14779",
    "sg:province":"NY",
    "sg:tags":[
        "grocer"
    ],
    "wof:name":"Mongillo's Inc",
    "wof:placetype":"venue"
},
  "geometry": {"coordinates":[-78.714697,42.154636],"type":"Point"}
}