{
  "type": "Feature",
  "properties": {
    "addr:full":"17 John St Bsmt New York NY 10038",
    "addr:housenumber":"17",
    "addr:postcode":"10038",
    "addr:street":"John St",
    "iso:country":"US",
    "sg:address":"17 John St Bsmt",
    "sg:city":"New York",
    "sg:classifiers":[
        {
            "category":"Travel",
            "subcategory":"Hotels & Motels",
            "type":"Entertainment"
        }
    ],
    "sg:phone":"+1 212 233 0419",
    "sg:postcode":"10038",
    "sg:province":"NY",
    "wof:name":"Execustay by Marriott",
    "wof:placetype":"venue"
},
  "geometry": {"coordinates":[-74.008904,40.7099],"type":"Point"}
}