{
  "type": "Feature",
  "properties": {
    "iso:country":"US",
    "sg:address":"534 Ridge Rd W",
    "sg:city":"Rochester",
    "sg:classifiers":[
        {
            "category":"Real Estate",
            "subcategory":"Real Estate Operator",
            "type":"Services"
        }
    ],
    "sg:phone":"+1 585 663 5810",
    "sg:postcode":"14420",
    "sg:province":"NY",
    "sg:tags":[
        "holding"
    ],
    "wof:name":"McGinities",
    "wof:placetype":"venue"
},
  "geometry": {"coordinates":[-77.641487,43.201513],"type":"Point"}
}