{
  "type": "Feature",
  "properties": {
    "iso:country":"US",
    "sg:address":"16 Stephenville St",
    "sg:city":"Massena",
    "sg:classifiers":[
        {
            "category":"Organizations",
            "subcategory":"Religious Organization",
            "type":"Services"
        }
    ],
    "sg:phone":"+1 315 769 5867",
    "sg:postcode":"13662",
    "sg:province":"NY",
    "sg:tags":[
        "church"
    ],
    "wof:name":"Church Of Christ",
    "wof:placetype":"venue"
},
  "geometry": {"coordinates":[-74.875687,44.925467],"type":"Point"}
}