{
  "type": "Feature",
  "properties": {
    "iso:country":"US",
    "sg:address":"146 S Liberty Dr",
    "sg:city":"Stony Point",
    "sg:classifiers":[
        {
            "category":"Personal",
            "subcategory":"Beauty Salon",
            "type":"Services"
        }
    ],
    "sg:phone":"+1 845 786 2602",
    "sg:postcode":"10980",
    "sg:province":"NY",
    "wof:name":"Gina's Head To Toes",
    "wof:placetype":"venue"
},
  "geometry": {"coordinates":[-73.985124,41.221699],"type":"Point"}
}