{
  "type": "Feature",
  "properties": {
    "addr:full":"4 Metrotech Ctr Brooklyn NY 11201",
    "addr:housenumber":"4",
    "addr:postcode":"11201",
    "addr:street":"Metrotech Ctr",
    "iso:country":"US",
    "sg:address":"4 Metrotech Ctr",
    "sg:city":"Brooklyn",
    "sg:classifiers":[
        {
            "category":"Shopping",
            "subcategory":"Pharmacy",
            "type":"Retail Goods"
        }
    ],
    "sg:phone":"+1 800 887 8938",
    "sg:postcode":"11201",
    "sg:province":"NY",
    "sg:tags":[
        "drugstore"
    ],
    "sg:website":"www.metro-drugs.com",
    "wof:name":"Metro Drug Inc",
    "wof:placetype":"venue"
},
  "geometry": {"coordinates":[-73.987193,40.693572],"type":"Point"}
}