{
  "type": "Feature",
  "properties": {
    "addr:full":"7184 Lake Rd Appleton NY 14008",
    "addr:housenumber":"7184",
    "addr:postcode":"14008",
    "addr:street":"Lake Rd",
    "iso:country":"US",
    "sg:address":"7184 Lake Rd",
    "sg:city":"Appleton",
    "sg:classifiers":[
        {
            "category":"Farming",
            "subcategory":"Nursery",
            "type":"Manufacturing & Wholesale Goods"
        },
        {
            "category":"Home & Garden",
            "subcategory":"Garden Supply",
            "type":"Retail Goods"
        }
    ],
    "sg:phone":"+1 716 778 8710",
    "sg:postcode":"14008",
    "sg:province":"NY",
    "sg:tags":[
        "ornamental",
        "nurseryman"
    ],
    "wof:name":"Green Lane Nurseries Inc",
    "wof:placetype":"venue"
},
  "geometry": {"coordinates":[-78.630222,43.348889],"type":"Point"}
}