{
  "type": "Feature",
  "properties": {
    "addr:full":"212 Neptune Ave Brooklyn NY 11235",
    "addr:housenumber":"212",
    "addr:postcode":"11235",
    "addr:street":"Neptune Ave",
    "iso:country":"US",
    "sg:address":"212 Neptune Ave",
    "sg:city":"Brooklyn",
    "sg:classifiers":[
        {
            "category":"Health Services",
            "subcategory":"Medical Lab",
            "type":"Services"
        }
    ],
    "sg:phone":"+1 718 769 6212",
    "sg:postcode":"11235",
    "sg:province":"NY",
    "sg:tags":[
        "dental",
        "ceramics"
    ],
    "wof:name":"Fine Craft Dental Studio",
    "wof:placetype":"venue"
},
  "geometry": {"coordinates":[-73.96186400000001,40.581478],"type":"Point"}
}