{
  "type": "Feature",
  "properties": {
    "iso:country":"US",
    "sg:address":"28 W 27 St",
    "sg:city":"New York",
    "sg:classifiers":[
        {
            "category":"Wholesale",
            "subcategory":"Apparel",
            "type":"Manufacturing & Wholesale Goods"
        },
        {
            "category":"Shopping",
            "subcategory":"Optical Goods",
            "type":"Retail Goods"
        }
    ],
    "sg:phone":"+1 212 686 6869",
    "sg:postcode":"10001",
    "sg:province":"NY",
    "sg:tags":[
        "sun",
        "goggles",
        "sunglasses",
        "glove"
    ],
    "sg:website":"www.davidandyoung.com",
    "wof:name":"David & Young Co Inc",
    "wof:placetype":"venue"
},
  "geometry": {"coordinates":[-73.990574,40.745115],"type":"Point"}
}