{
  "type": "Feature",
  "properties": {
    "iso:country":"US",
    "sg:address":"47 Country Corner Ln",
    "sg:city":"Fairport",
    "sg:classifiers":[
        {
            "category":"Building & Trades",
            "subcategory":"Construction",
            "type":"Services"
        }
    ],
    "sg:phone":"+1 585 223 6815",
    "sg:postcode":"14450",
    "sg:province":"NY",
    "sg:tags":[
        "house"
    ],
    "wof:name":"Kennys Contracting",
    "wof:placetype":"venue"
},
  "geometry": {"coordinates":[-77.446719,43.083825],"type":"Point"}
}