{
  "type": "Feature",
  "properties": {
    "iso:country":"US",
    "sg:address":"48 S 2nd Ave",
    "sg:city":"Broadalbin",
    "sg:classifiers":[
        {
            "category":"Autos & Motor Vehicles",
            "subcategory":"Fuel & Gas Station",
            "type":"Retail Goods"
        },
        {
            "category":"Retail",
            "subcategory":"Auto Repair",
            "type":"Services"
        }
    ],
    "sg:phone":"+1 518 883 5911",
    "sg:postcode":"12025",
    "sg:province":"NY",
    "sg:tags":[
        "repairing",
        "automobile",
        "station",
        "gasoline"
    ],
    "wof:name":"Avery's Service Station",
    "wof:placetype":"venue"
},
  "geometry": {"coordinates":[-74.199207,43.053058],"type":"Point"}
}