{
  "type": "Feature",
  "properties": {
    "iso:country":"US",
    "sg:address":"135 W 50th St",
    "sg:city":"New York",
    "sg:classifiers":[
        {
            "category":"Food & Beverages",
            "subcategory":"Bakery",
            "type":"Retail Goods"
        }
    ],
    "sg:phone":"+1 212 489 6458",
    "sg:postcode":"10020",
    "sg:province":"NY",
    "sg:tags":[
        "sandwich"
    ],
    "wof:name":"Pret A Manger",
    "wof:placetype":"venue"
},
  "geometry": {"coordinates":[-73.98159800000001,40.7603],"type":"Point"}
}