{
  "type": "Feature",
  "properties": {
    "addr:full":"3349 Seymour Ave Bronx NY 10469",
    "addr:housenumber":"3349",
    "addr:postcode":"10469",
    "addr:street":"Seymour Ave",
    "iso:country":"US",
    "sg:address":"3349 Seymour Ave",
    "sg:city":"Bronx",
    "sg:classifiers":[
        {
            "category":"Real Estate",
            "subcategory":"Real Estate Agent",
            "type":"Services"
        }
    ],
    "sg:phone":"+1 718 652 3302",
    "sg:postcode":"10469",
    "sg:province":"NY",
    "wof:name":"Uptight Realty Co",
    "wof:placetype":"venue"
},
  "geometry": {"coordinates":[-73.84864,40.875022],"type":"Point"}
}