{
  "type": "Feature",
  "properties": {
    "addr:full":"173 Passaic Ave Lockport NY 14094",
    "addr:housenumber":"173",
    "addr:postcode":"14094",
    "addr:street":"Passaic Ave",
    "iso:country":"US",
    "sg:address":"173 Passaic Ave",
    "sg:city":"Lockport",
    "sg:classifiers":[
        {
            "category":"Building & Trades",
            "subcategory":"Construction",
            "type":"Services"
        }
    ],
    "sg:phone":"+1 716 434 0099",
    "sg:postcode":"14094",
    "sg:province":"NY",
    "sg:tags":[
        "excavation",
        "contractor"
    ],
    "wof:name":"Triway Contracting",
    "wof:placetype":"venue"
},
  "geometry": {"coordinates":[-78.707176,43.176103],"type":"Point"}
}