{
  "type": "Feature",
  "properties": {
    "iso:country":"US",
    "sg:address":"825 Payne Ave",
    "sg:city":"North Tonawanda",
    "sg:classifiers":[
        {
            "category":"Professional",
            "subcategory":"Lawyer & Legal Services",
            "type":"Services"
        }
    ],
    "sg:phone":"+1 716 692 6300",
    "sg:postcode":"14120",
    "sg:province":"NY",
    "sg:tags":[
        "attorney"
    ],
    "wof:name":"Siegel Kelleher & Kahn",
    "wof:placetype":"venue"
},
  "geometry": {"coordinates":[-78.875895,43.046415],"type":"Point"}
}