{
  "type": "Feature",
  "properties": {
    "iso:country":"US",
    "sg:address":"633 State Hwy 17M",
    "sg:city":"Middletown",
    "sg:classifiers":[
        {
            "category":"Restaurant",
            "type":"Food & Drink"
        }
    ],
    "sg:phone":"+1   ",
    "sg:postcode":"10940",
    "sg:province":"NY",
    "sg:tags":[
        "drinking",
        "eating"
    ],
    "wof:name":"Johns Harvest Inn Inc",
    "wof:placetype":"venue"
},
  "geometry": {"coordinates":[-74.41653100000001,41.473471],"type":"Point"}
}