{
  "type": "Feature",
  "properties": {
    "iso:country":"US",
    "sg:address":"51 Bergen Ln",
    "sg:city":"Blue Point",
    "sg:classifiers":[
        {
            "category":"Professional",
            "subcategory":"Management & Consulting",
            "type":"Services"
        }
    ],
    "sg:phone":"+1 631 363 2823",
    "sg:postcode":"11715",
    "sg:province":"NY",
    "wof:name":"Asset Mgmt",
    "wof:placetype":"venue"
},
  "geometry": {"coordinates":[-73.031173,40.744307],"type":"Point"}
}