{
  "type": "Feature",
  "properties": {
    "iso:country":"US",
    "sg:address":"103 E 198th St",
    "sg:city":"Bronx",
    "sg:classifiers":[
        {
            "category":"Shopping",
            "subcategory":"Computers & Home Electronics",
            "type":"Retail Goods"
        }
    ],
    "sg:phone":"+1 718 329 1030",
    "sg:postcode":"10468",
    "sg:province":"NY",
    "sg:tags":[
        "equipment",
        "electronic",
        "supply"
    ],
    "wof:name":"Computec & Electronics Co",
    "wof:placetype":"venue"
},
  "geometry": {"coordinates":[-73.890958,40.870241],"type":"Point"}
}