{
  "type": "Feature",
  "properties": {
    "addr:full":"41 Shadow Wood Way Ballston Lake NY 12019",
    "addr:housenumber":"41",
    "addr:postcode":"12019",
    "addr:street":"Shadow Wood Way",
    "iso:country":"US",
    "sg:address":"41 Shadow Wood Way",
    "sg:city":"Ballston Lake",
    "sg:classifiers":[
        {
            "category":"Professional",
            "subcategory":"Detective & Security Services",
            "type":"Services"
        }
    ],
    "sg:phone":"+1   ",
    "sg:postcode":"12019",
    "sg:province":"NY",
    "sg:tags":[
        "car"
    ],
    "wof:name":"Shadow Service Investigations",
    "wof:placetype":"venue"
},
  "geometry": {"coordinates":[-73.81433199999999,42.922691],"type":"Point"}
}