{
  "type": "Feature",
  "properties": {
    "iso:country":"US",
    "sg:address":"2111 E 15th Street",
    "sg:city":"Brooklyn",
    "sg:classifiers":[
        {
            "category":"Health Services",
            "subcategory":"Health Practitioner",
            "type":"Services"
        }
    ],
    "sg:phone":"+1 718 336 9872",
    "sg:postcode":"11229",
    "sg:province":"NY",
    "sg:tags":[
        "therapy",
        "physical"
    ],
    "wof:name":"Jennan Comprehensive Medical",
    "wof:placetype":"venue"
},
  "geometry": {"coordinates":[-73.956262,40.598853],"type":"Point"}
}