{
  "type": "Feature",
  "properties": {
    "iso:country":"US",
    "sg:address":"204 Park St",
    "sg:city":"Sherrill",
    "sg:classifiers":[
        {
            "category":"Shopping",
            "subcategory":"Catalog Store",
            "type":"Retail Goods"
        }
    ],
    "sg:phone":"+1   ",
    "sg:postcode":"13461",
    "sg:province":"NY",
    "sg:tags":[
        "house",
        "mail"
    ],
    "wof:name":"Pear Co",
    "wof:placetype":"venue"
},
  "geometry": {"coordinates":[-75.598333,43.070591],"type":"Point"}
}