{
  "type": "Feature",
  "properties": {
    "iso:country":"US",
    "sg:address":"227 Arlington Ave",
    "sg:city":"Staten Island",
    "sg:classifiers":[
        {
            "category":"Manufacturing",
            "subcategory":"Building Materials",
            "type":"Manufacturing & Wholesale Goods"
        },
        {
            "category":"Building & Trades",
            "subcategory":"Construction",
            "type":"Services"
        }
    ],
    "sg:phone":"+1 718 442 4960",
    "sg:postcode":"10303",
    "sg:province":"NY",
    "sg:tags":[
        "mfr",
        "wood",
        "product",
        "woodworker"
    ],
    "wof:name":"Bennington Woodworking Inc",
    "wof:placetype":"venue"
},
  "geometry": {"coordinates":[-74.167481,40.634946],"type":"Point"}
}