{
  "type": "Feature",
  "properties": {
    "iso:country":"US",
    "sg:address":"88 Sawyer Ave",
    "sg:city":"Lancaster",
    "sg:classifiers":[
        {
            "category":"Building & Trades",
            "subcategory":"Construction",
            "type":"Services"
        }
    ],
    "sg:phone":"+1 716 684 5104",
    "sg:postcode":"14086",
    "sg:province":"NY",
    "sg:tags":[
        "house"
    ],
    "wof:name":"Ehrenreich Construction",
    "wof:placetype":"venue"
},
  "geometry": {"coordinates":[-78.677852,42.909328],"type":"Point"}
}