{
  "type": "Feature",
  "properties": {
    "iso:country":"US",
    "sg:address":"199 East Main Street",
    "sg:city":"Smithtown",
    "sg:classifiers":[
        {
            "category":"Shopping",
            "type":"Retail Goods"
        }
    ],
    "sg:phone":"+1 631 265 4424",
    "sg:postcode":"11787",
    "sg:province":"NY",
    "sg:website":"www.deltachemicals.com",
    "wof:name":"Delta Chemicals",
    "wof:placetype":"venue"
},
  "geometry": {"coordinates":[-73.18561699999999,40.85651],"type":"Point"}
}