{
  "type": "Feature",
  "properties": {
    "addr:full":"100 Grand St New York NY 10013",
    "addr:housenumber":"100",
    "addr:postcode":"10013",
    "addr:street":"Grand St",
    "iso:country":"US",
    "sg:address":"100 Grand St",
    "sg:city":"New York",
    "sg:classifiers":[
        {
            "category":"Communications",
            "subcategory":"Film & Video Production",
            "type":"Services"
        }
    ],
    "sg:phone":"+1 212 647 1877",
    "sg:postcode":"10013",
    "sg:province":"NY",
    "sg:tags":[
        "event",
        "special"
    ],
    "sg:website":"www.dalzellproductions.com",
    "wof:name":"Dalzell Productions LTD",
    "wof:placetype":"venue"
},
  "geometry": {"coordinates":[-74.001819,40.721579],"type":"Point"}
}