{
  "type": "Feature",
  "properties": {
    "iso:country":"US",
    "sg:address":"10 Bates Dr",
    "sg:city":"Port Jefferson Station",
    "sg:classifiers":[
        {
            "category":"Shopping",
            "subcategory":"Bicycles & Sporting Goods",
            "type":"Retail Goods"
        }
    ],
    "sg:phone":"+1   ",
    "sg:postcode":"11776",
    "sg:province":"NY",
    "wof:name":"Pj Wet Sport Inc",
    "wof:placetype":"venue"
},
  "geometry": {"coordinates":[-73.02826,40.915332],"type":"Point"}
}