{
  "type": "Feature",
  "properties": {
    "iso:country":"US",
    "sg:address":"121 Hudson Ave",
    "sg:city":"Haverstraw",
    "sg:classifiers":[
        {
            "category":"Social Services",
            "subcategory":"Adult Care",
            "type":"Services"
        },
        {
            "category":"Professional",
            "type":"Services"
        }
    ],
    "sg:phone":"+1 845 429 1328",
    "sg:postcode":"10927",
    "sg:province":"NY",
    "sg:tags":[
        "residential",
        "establishment"
    ],
    "wof:name":"Westchester Residences Yai RCA",
    "wof:placetype":"venue"
},
  "geometry": {"coordinates":[-73.96507699999999,41.192932],"type":"Point"}
}