{
  "type": "Feature",
  "properties": {
    "addr:full":"1179 Hertel Ave Buffalo NY 14216",
    "addr:housenumber":"1179",
    "addr:postcode":"14216",
    "addr:street":"Hertel Ave",
    "iso:country":"US",
    "sg:address":"1179 Hertel Ave",
    "sg:city":"Buffalo",
    "sg:classifiers":[
        {
            "category":"Food & Beverages",
            "subcategory":"Specialty",
            "type":"Retail Goods"
        }
    ],
    "sg:phone":"+1 716 873 4540",
    "sg:postcode":"14216",
    "sg:province":"NY",
    "sg:tags":[
        "gourmet",
        "shop"
    ],
    "wof:name":"Giancarlo's Pasta & Sauces",
    "wof:placetype":"venue"
},
  "geometry": {"coordinates":[-78.865937,42.947764],"type":"Point"}
}