{
  "type": "Feature",
  "properties": {
    "addr:full":"211 41st St Brooklyn NY 11232",
    "addr:housenumber":"211",
    "addr:postcode":"11232",
    "addr:street":"41St St",
    "iso:country":"US",
    "sg:address":"211 41st St",
    "sg:city":"Brooklyn",
    "sg:classifiers":[
        {
            "category":"Wholesale",
            "subcategory":"Durable Goods & Equipment",
            "type":"Manufacturing & Wholesale Goods"
        }
    ],
    "sg:phone":"+1 718 768 6030",
    "sg:postcode":"11232",
    "sg:province":"NY",
    "sg:tags":[
        "exporter"
    ],
    "wof:name":"Top Quality Export Merchandise",
    "wof:placetype":"venue"
},
  "geometry": {"coordinates":[-74.009508,40.652944],"type":"Point"}
}