{
  "type": "Feature",
  "properties": {
    "addr:full":"120 W 28 St New York NY 10001",
    "addr:housenumber":"120",
    "addr:postcode":"10001",
    "addr:street":"W 28 St",
    "iso:country":"US",
    "sg:address":"120 W 28 St",
    "sg:city":"New York",
    "sg:classifiers":[
        {
            "category":"Wholesale",
            "subcategory":"Plants",
            "type":"Manufacturing & Wholesale Goods"
        }
    ],
    "sg:phone":"+1 212 924 6969",
    "sg:postcode":"10001",
    "sg:province":"NY",
    "sg:tags":[
        "supply"
    ],
    "sg:website":"www.caribbeancuts.com",
    "wof:name":"Caribbean Cuts Corp",
    "wof:placetype":"venue"
},
  "geometry": {"coordinates":[-73.99295600000001,40.746925],"type":"Point"}
}