{
  "type": "Feature",
  "properties": {
    "addr:full":"20 Broadway Massapequa NY 11758",
    "addr:housenumber":"20",
    "addr:postcode":"11758",
    "addr:street":"Broadway",
    "iso:country":"US",
    "sg:address":"20 Broadway",
    "sg:city":"Massapequa",
    "sg:classifiers":[
        {
            "category":"Retail",
            "subcategory":"Laundry & Dry Cleaning",
            "type":"Services"
        }
    ],
    "sg:phone":"+1 516 797 5390",
    "sg:postcode":"11758",
    "sg:province":"NY",
    "sg:tags":[
        "drycleaning",
        "plant"
    ],
    "wof:name":"One Price Dry Cleaners",
    "wof:placetype":"venue"
},
  "geometry": {"coordinates":[-73.470446,40.678279],"type":"Point"}
}