{
  "type": "Feature",
  "properties": {
    "iso:country":"US",
    "sg:address":"32 Paxton Ave",
    "sg:city":"Bronxville",
    "sg:classifiers":[
        {
            "category":"Retail",
            "subcategory":"Auto Repair",
            "type":"Services"
        }
    ],
    "sg:phone":"+1 914 337 0000",
    "sg:postcode":"10708",
    "sg:province":"NY",
    "sg:tags":[
        "shop",
        "automotive",
        "general"
    ],
    "wof:name":"Gt Motors Ltd",
    "wof:placetype":"venue"
},
  "geometry": {"coordinates":[-73.83803899999999,40.941306],"type":"Point"}
}