{
  "type": "Feature",
  "properties": {
    "iso:country":"US",
    "sg:address":"61 Lakeview Dr",
    "sg:city":"Kings Park",
    "sg:classifiers":[
        {
            "category":"Building & Trades",
            "subcategory":"Construction",
            "type":"Services"
        }
    ],
    "sg:phone":"+1 631 271 2916",
    "sg:postcode":"11754",
    "sg:province":"NY",
    "wof:name":"Construction Zone",
    "wof:placetype":"venue"
},
  "geometry": {"coordinates":[-73.21821,40.896675],"type":"Point"}
}