{
  "type": "Feature",
  "properties": {
    "iso:country":"US",
    "sg:address":"1025 Cork Rd",
    "sg:city":"Victor",
    "sg:classifiers":[
        {
            "category":"Building & Trades",
            "subcategory":"Construction",
            "type":"Services"
        }
    ],
    "sg:phone":"+1 585 924 3961",
    "sg:postcode":"14564",
    "sg:province":"NY",
    "sg:tags":[
        "house"
    ],
    "wof:name":"Colcon Co Inc",
    "wof:placetype":"venue"
},
  "geometry": {"coordinates":[-77.439144,42.990113],"type":"Point"}
}