{
  "type": "Feature",
  "properties": {
    "addr:full":"598 Round Pond Rd Smithville Flats NY 13841",
    "addr:housenumber":"598",
    "addr:postcode":"13841",
    "addr:street":"Round Pond Rd",
    "iso:country":"US",
    "sg:address":"598 Round Pond Rd",
    "sg:city":"Smithville Flats",
    "sg:classifiers":[
        {
            "category":"Wholesale",
            "subcategory":"Electrical",
            "type":"Manufacturing & Wholesale Goods"
        }
    ],
    "sg:phone":"+1 607 656 4600",
    "sg:postcode":"13841",
    "sg:province":"NY",
    "sg:tags":[
        "generator"
    ],
    "sg:website":"www.independentpower.com",
    "wof:name":"Independent Power Systems",
    "wof:placetype":"venue"
},
  "geometry": {"coordinates":[-75.845401,42.398512],"type":"Point"}
}