{
  "type": "Feature",
  "properties": {
    "iso:country":"US",
    "sg:address":"24114 140th Avenue",
    "sg:city":"Rosedale",
    "sg:classifiers":[
        {
            "category":"Health Services",
            "subcategory":"Chiropractor",
            "type":"Services"
        },
        {
            "category":"Health Services",
            "subcategory":"Dentist",
            "type":"Services"
        }
    ],
    "sg:phone":"+1 718 481 7900",
    "sg:postcode":"11422",
    "sg:province":"NY",
    "wof:name":"Denny Scott DDS",
    "wof:placetype":"venue"
},
  "geometry": {"coordinates":[-73.736507,40.66473],"type":"Point"}
}