{
  "type": "Feature",
  "properties": {
    "addr:full":"57 N Main St Albion NY 14411",
    "addr:housenumber":"57",
    "addr:postcode":"14411",
    "addr:street":"N Main St",
    "iso:country":"US",
    "sg:address":"57 N Main St",
    "sg:city":"Albion",
    "sg:classifiers":[
        {
            "category":"Personal",
            "subcategory":"Beauty Salon",
            "type":"Services"
        }
    ],
    "sg:phone":"+1 585 589 6635",
    "sg:postcode":"14411",
    "sg:province":"NY",
    "wof:name":"Hair Fantasy",
    "wof:placetype":"venue"
},
  "geometry": {"coordinates":[-78.193652,43.246945],"type":"Point"}
}