{
  "type": "Feature",
  "properties": {
    "addr:full":"41 Madison Ave New York NY 10010",
    "addr:housenumber":"41",
    "addr:postcode":"10010",
    "addr:street":"Madison Ave",
    "iso:country":"US",
    "sg:address":"41 Madison Ave",
    "sg:city":"New York",
    "sg:classifiers":[
        {
            "category":"Professional",
            "type":"Services"
        }
    ],
    "sg:phone":"+1 212 532 5809",
    "sg:postcode":"10010",
    "sg:province":"NY",
    "sg:tags":[
        "establishment"
    ],
    "wof:name":"Moser Co",
    "wof:placetype":"venue"
},
  "geometry": {"coordinates":[-73.986836,40.742184],"type":"Point"}
}