{
  "type": "Feature",
  "properties": {
    "iso:country":"US",
    "sg:address":"5938 Old Orchard Dr",
    "sg:city":"Hamburg",
    "sg:classifiers":[
        {
            "category":"Personal",
            "subcategory":"Beauty Salon",
            "type":"Services"
        }
    ],
    "sg:phone":"+1 716 648 7915",
    "sg:postcode":"14075",
    "sg:province":"NY",
    "wof:name":"Frames By Tony",
    "wof:placetype":"venue"
},
  "geometry": {"coordinates":[-78.770707,42.673299],"type":"Point"}
}