{
  "type": "Feature",
  "properties": {
    "addr:full":"1426 Lexington Ave New York NY 10128",
    "addr:housenumber":"1426",
    "addr:postcode":"10128",
    "addr:street":"Lexington Ave",
    "iso:country":"US",
    "sg:address":"1426 Lexington Ave",
    "sg:city":"New York",
    "sg:classifiers":[
        {
            "category":"Building & Trades",
            "subcategory":"Locksmith",
            "type":"Services"
        }
    ],
    "sg:phone":"+1 646 918 8702",
    "sg:postcode":"10128",
    "sg:province":"NY",
    "sg:tags":[
        "key"
    ],
    "wof:name":"A Twenty Four Hour Emergency Lexington Avenue Locksm",
    "wof:placetype":"venue"
},
  "geometry": {"coordinates":[-73.952438,40.784053],"type":"Point"}
}