{
  "type": "Feature",
  "properties": {
    "iso:country":"US",
    "sg:address":"78 W 47 St",
    "sg:city":"New York",
    "sg:classifiers":[
        {
            "category":"Professional",
            "type":"Services"
        }
    ],
    "sg:phone":"+1 212 764 3186",
    "sg:postcode":"10036",
    "sg:province":"NY",
    "sg:tags":[
        "establishment"
    ],
    "wof:name":"47th Street Corp",
    "wof:placetype":"venue"
},
  "geometry": {"coordinates":[-73.979894,40.756873],"type":"Point"}
}