{
  "type": "Feature",
  "properties": {
    "addr:full":"47 Andrea Ln Scarsdale NY 10583",
    "addr:housenumber":"47",
    "addr:postcode":"10583",
    "addr:street":"Andrea Ln",
    "iso:country":"US",
    "sg:address":"47 Andrea Ln",
    "sg:city":"Scarsdale",
    "sg:classifiers":[
        {
            "category":"Real Estate",
            "subcategory":"Real Estate Agent",
            "type":"Services"
        }
    ],
    "sg:phone":"+1 914 472 4850",
    "sg:postcode":"10583",
    "sg:province":"NY",
    "wof:name":"Ekg VII Ltd Partnership",
    "wof:placetype":"venue"
},
  "geometry": {"coordinates":[-73.830617,40.993902],"type":"Point"}
}