{
  "type": "Feature",
  "properties": {
    "addr:full":"543 Empire Blvd Brooklyn NY 11225",
    "addr:housenumber":"543",
    "addr:postcode":"11225",
    "addr:street":"Empire Blvd",
    "iso:country":"US",
    "sg:address":"543 Empire Blvd",
    "sg:city":"Brooklyn",
    "sg:classifiers":[
        {
            "category":"Retail",
            "subcategory":"Auto Rental",
            "type":"Services"
        }
    ],
    "sg:phone":"+1 718 771 2299",
    "sg:postcode":"11225",
    "sg:province":"NY",
    "sg:tags":[
        "car",
        "puller"
    ],
    "wof:name":"Bedstar Car Svc",
    "wof:placetype":"venue"
},
  "geometry": {"coordinates":[-73.94458899999999,40.66424],"type":"Point"}
}