{
  "type": "Feature",
  "properties": {
    "addr:full":"331 Route 25A Mount Sinai NY 11766",
    "addr:housenumber":"331",
    "addr:postcode":"11766",
    "addr:street":"Route 25A",
    "iso:country":"US",
    "sg:address":"331 Route 25A",
    "sg:city":"Mount Sinai",
    "sg:classifiers":[
        {
            "category":"Retail",
            "subcategory":"Veterinary Services",
            "type":"Services"
        }
    ],
    "sg:phone":"+1 631 476 1304",
    "sg:postcode":"11766",
    "sg:province":"NY",
    "sg:tags":[
        "veterinarian"
    ],
    "wof:name":"Mt Sinai Animal Hospital",
    "wof:placetype":"venue"
},
  "geometry": {"coordinates":[-73.025497,40.933998],"type":"Point"}
}