{
  "type": "Feature",
  "properties": {
    "addr:full":"333 Kingston Ave Brooklyn NY 11213",
    "addr:housenumber":"333",
    "addr:postcode":"11213",
    "addr:street":"Kingston Ave",
    "iso:country":"US",
    "sg:address":"333 Kingston Ave",
    "sg:city":"Brooklyn",
    "sg:classifiers":[
        {
            "category":"Food & Beverages",
            "subcategory":"Bakery",
            "type":"Retail Goods"
        }
    ],
    "sg:phone":"+1   ",
    "sg:postcode":"11213",
    "sg:province":"NY",
    "wof:name":"Crown Heights Bagel",
    "wof:placetype":"venue"
},
  "geometry": {"coordinates":[-73.942234,40.668372],"type":"Point"}
}