{
  "type": "Feature",
  "properties": {
    "iso:country":"US",
    "sg:address":"5100 Broadway",
    "sg:city":"Depew",
    "sg:classifiers":[
        {
            "category":"Retail",
            "subcategory":"Repair Shop",
            "type":"Services"
        }
    ],
    "sg:phone":"+1 716 651 0200",
    "sg:postcode":"14043",
    "sg:province":"NY",
    "sg:tags":[
        "lift",
        "truck"
    ],
    "wof:name":"Buffalo Lift Trucks Inc",
    "wof:placetype":"venue"
},
  "geometry": {"coordinates":[-78.685175,42.901377],"type":"Point"}
}