{
  "type": "Feature",
  "properties": {
    "addr:full":"3495 Winton Pl Rochester NY 14623",
    "addr:housenumber":"3495",
    "addr:postcode":"14623",
    "addr:street":"Winton Pl",
    "iso:country":"US",
    "sg:address":"3495 Winton Pl",
    "sg:city":"Rochester",
    "sg:classifiers":[
        {
            "category":"Professional",
            "subcategory":"Business Services",
            "type":"Services"
        }
    ],
    "sg:phone":"+1 585 292 7290",
    "sg:postcode":"14623",
    "sg:province":"NY",
    "sg:tags":[
        "organizing",
        "services-household"
    ],
    "wof:name":"Filices Enterprises",
    "wof:placetype":"venue"
},
  "geometry": {"coordinates":[-77.576492,43.096069],"type":"Point"}
}