{
  "type": "Feature",
  "properties": {
    "addr:full":"18 Eisenhower Ave Spring Valley NY 10977",
    "addr:housenumber":"18",
    "addr:postcode":"10977",
    "addr:street":"Eisenhower Ave",
    "iso:country":"US",
    "sg:address":"18 Eisenhower Ave",
    "sg:city":"Spring Valley",
    "sg:classifiers":[
        {
            "category":"Wholesale",
            "subcategory":"Durable Goods & Equipment",
            "type":"Manufacturing & Wholesale Goods"
        }
    ],
    "sg:phone":"+1 845 362 4243",
    "sg:postcode":"10977",
    "sg:province":"NY",
    "sg:tags":[
        "importer"
    ],
    "wof:name":"United Enterprise Corp",
    "wof:placetype":"venue"
},
  "geometry": {"coordinates":[-74.027272,41.137078],"type":"Point"}
}