{
  "type": "Feature",
  "properties": {
    "addr:full":"433 Evergreen Ct Central Valley NY 10917",
    "addr:housenumber":"433",
    "addr:postcode":"10917",
    "addr:street":"Evergreen Ct",
    "iso:country":"US",
    "sg:address":"433 Evergreen Ct",
    "sg:city":"Central Valley",
    "sg:classifiers":[
        {
            "category":"Shopping",
            "subcategory":"Discount & Variety Stores",
            "type":"Retail Goods"
        }
    ],
    "sg:phone":"+1 845 928 0676",
    "sg:postcode":"10917",
    "sg:province":"NY",
    "sg:tags":[
        "outlet"
    ],
    "wof:name":"Woodbury Common Premium Outlets",
    "wof:placetype":"venue"
},
  "geometry": {"coordinates":[-74.127081,41.317137],"type":"Point"}
}