{
  "type": "Feature",
  "properties": {
    "addr:full":"57 W Shore Rd Roslyn NY 11576",
    "addr:housenumber":"57",
    "addr:postcode":"11576",
    "addr:street":"W Shore Rd",
    "iso:country":"US",
    "sg:address":"57 W Shore Rd",
    "sg:city":"Roslyn",
    "sg:classifiers":[
        {
            "category":"Banks & Credit Unions",
            "subcategory":"Financial Services",
            "type":"Services"
        }
    ],
    "sg:phone":"+1 516 621 4290",
    "sg:postcode":"11576",
    "sg:province":"NY",
    "sg:tags":[
        "investor"
    ],
    "wof:name":"Rose Hall Capital Corp",
    "wof:placetype":"venue"
},
  "geometry": {"coordinates":[-73.654084,40.804111],"type":"Point"}
}