{
  "type": "Feature",
  "properties": {
    "addr:full":"3825 Broadway New York NY 10032",
    "addr:housenumber":"3825",
    "addr:postcode":"10032",
    "addr:street":"Broadway",
    "iso:country":"US",
    "sg:address":"3825 Broadway",
    "sg:city":"New York",
    "sg:classifiers":[
        {
            "category":"Banks & Credit Unions",
            "subcategory":"Bank",
            "type":"Services"
        }
    ],
    "sg:phone":"+1 212 543 6300",
    "sg:postcode":"10032",
    "sg:province":"NY",
    "sg:tags":[
        "money",
        "order"
    ],
    "wof:name":"Dominican Communications",
    "wof:placetype":"venue"
},
  "geometry": {"coordinates":[-73.943656,40.83583],"type":"Point"}
}