{
  "type": "Feature",
  "properties": {
    "addr:full":"100 Atlantic Ave Lynbrook NY 11563",
    "addr:housenumber":"100",
    "addr:postcode":"11563",
    "addr:street":"Atlantic Ave",
    "iso:country":"US",
    "sg:address":"100 Atlantic Ave",
    "sg:city":"Lynbrook",
    "sg:classifiers":[
        {
            "category":"Wholesale",
            "subcategory":"Chemicals & Plastics",
            "type":"Manufacturing & Wholesale Goods"
        }
    ],
    "sg:phone":"+1 516 256 0008",
    "sg:postcode":"11563",
    "sg:province":"NY",
    "sg:tags":[
        "home",
        "respiratory"
    ],
    "wof:name":"R R T Group",
    "wof:placetype":"venue"
},
  "geometry": {"coordinates":[-73.67066199999999,40.652567],"type":"Point"}
}