{
  "type": "Feature",
  "properties": {
    "addr:full":"330 E State St Ithaca NY 14850",
    "addr:housenumber":"330",
    "addr:postcode":"14850",
    "addr:street":"E State St",
    "iso:country":"US",
    "sg:address":"330 E State St",
    "sg:city":"Ithaca",
    "sg:classifiers":[
        {
            "category":"Education",
            "subcategory":"Junior College",
            "type":"Public Place"
        }
    ],
    "sg:phone":"+1 607 272 1474",
    "sg:postcode":"14850",
    "sg:province":"NY",
    "sg:tags":[
        "technical",
        "institute"
    ],
    "sg:website":"www.csma-ithaca.org",
    "wof:name":"Community School-Music",
    "wof:placetype":"venue"
},
  "geometry": {"coordinates":[-76.49432899999999,42.439575],"type":"Point"}
}