{
  "type": "Feature",
  "properties": {
    "iso:country":"US",
    "sg:address":"20 Harrison St",
    "sg:city":"Garnerville",
    "sg:classifiers":[
        {
            "category":"Building & Trades",
            "subcategory":"Construction",
            "type":"Services"
        }
    ],
    "sg:phone":"+1 845 786 2809",
    "sg:postcode":"10923",
    "sg:province":"NY",
    "sg:tags":[
        "general",
        "contractor"
    ],
    "wof:name":"DNI Contracting Inc",
    "wof:placetype":"venue"
},
  "geometry": {"coordinates":[-73.997782,41.203432],"type":"Point"}
}