{
  "type": "Feature",
  "properties": {
    "addr:full":"128 E 84th St New York NY 10028",
    "addr:housenumber":"128",
    "addr:postcode":"10028",
    "addr:street":"E 84Th St",
    "iso:country":"US",
    "sg:address":"128 E 84th St",
    "sg:city":"New York",
    "sg:classifiers":[
        {
            "category":"Retail",
            "subcategory":"Repair Shop",
            "type":"Services"
        }
    ],
    "sg:phone":"+1 917 558 9578",
    "sg:postcode":"10028",
    "sg:province":"NY",
    "sg:tags":[
        "lock",
        "locksmith"
    ],
    "wof:name":"24 Hour 7 Day Emerg Locksmith",
    "wof:placetype":"venue"
},
  "geometry": {"coordinates":[-73.95740000000001,40.778568],"type":"Point"}
}