{
  "type": "Feature",
  "properties": {
    "addr:full":"39 Mc Intyre St Fort Edward NY 12828",
    "addr:housenumber":"39",
    "addr:postcode":"12828",
    "addr:street":"Mc Intyre St",
    "iso:country":"US",
    "sg:address":"39 Mc Intyre St",
    "sg:city":"Fort Edward",
    "sg:classifiers":[
        {
            "category":"Recreation",
            "type":"Entertainment"
        }
    ],
    "sg:phone":"+1 518 747 3005",
    "sg:postcode":"12828",
    "sg:province":"NY",
    "sg:tags":[
        "center"
    ],
    "wof:name":"Fort Edward Village Recreation",
    "wof:placetype":"venue"
},
  "geometry": {"coordinates":[-73.579785,43.271881],"type":"Point"}
}