{
  "type": "Feature",
  "properties": {
    "iso:country":"US",
    "sg:address":"24 High St",
    "sg:city":"Pulaski",
    "sg:classifiers":[
        {
            "category":"Building & Trades",
            "subcategory":"Construction",
            "type":"Services"
        }
    ],
    "sg:phone":"+1 315 298 6286",
    "sg:postcode":"13142",
    "sg:province":"NY",
    "sg:tags":[
        "general",
        "contractor"
    ],
    "wof:name":"Homes Construction & Plowing",
    "wof:placetype":"venue"
},
  "geometry": {"coordinates":[-76.12663499999999,43.563484],"type":"Point"}
}