{
  "type": "Feature",
  "properties": {
    "addr:full":"2600 3rd Ave Bronx NY 10454",
    "addr:housenumber":"2600",
    "addr:postcode":"10454",
    "addr:street":"3Rd Ave",
    "iso:country":"US",
    "sg:address":"2600 3rd Ave",
    "sg:city":"Bronx",
    "sg:classifiers":[
        {
            "category":"Retail",
            "subcategory":"Repair Shop",
            "type":"Services"
        }
    ],
    "sg:phone":"+1 718 685 5727",
    "sg:postcode":"10454",
    "sg:province":"NY",
    "sg:tags":[
        "lock",
        "locksmith"
    ],
    "wof:name":"Emergency Locksmith",
    "wof:placetype":"venue"
},
  "geometry": {"coordinates":[-73.92644199999999,40.811507],"type":"Point"}
}