{
  "type": "Feature",
  "properties": {
    "addr:full":"9202 Farragut Rd Brooklyn NY 11236",
    "addr:housenumber":"9202",
    "addr:postcode":"11236",
    "addr:street":"Farragut Rd",
    "iso:country":"US",
    "sg:address":"9202 Farragut Rd",
    "sg:city":"Brooklyn",
    "sg:classifiers":[
        {
            "category":"Wholesale",
            "subcategory":"Hardware",
            "type":"Manufacturing & Wholesale Goods"
        }
    ],
    "sg:phone":"+1 718 257 2586",
    "sg:postcode":"11236",
    "sg:province":"NY",
    "sg:tags":[
        "control",
        "oil",
        "burner",
        "unit",
        "supply"
    ],
    "wof:name":"Superior Relay Rebuilders Inc",
    "wof:placetype":"venue"
},
  "geometry": {"coordinates":[-73.907556,40.644225],"type":"Point"}
}