{
  "type": "Feature",
  "properties": {
    "iso:country":"US",
    "sg:address":"17 Salem Ln",
    "sg:city":"South Salem",
    "sg:classifiers":[
        {
            "category":"Building & Trades",
            "subcategory":"Construction",
            "type":"Services"
        }
    ],
    "sg:phone":"+1 914 763 3070",
    "sg:postcode":"10590",
    "sg:province":"NY",
    "sg:tags":[
        "commercial"
    ],
    "wof:name":"Mario A Buzzeo Construction Co",
    "wof:placetype":"venue"
},
  "geometry": {"coordinates":[-73.549475,41.277925],"type":"Point"}
}