{
  "type": "Feature",
  "properties": {
    "addr:full":"714 Foster Ave Brooklyn NY 11230",
    "addr:housenumber":"714",
    "addr:postcode":"11230",
    "addr:street":"Foster Ave",
    "iso:country":"US",
    "sg:address":"714 Foster Ave",
    "sg:city":"Brooklyn",
    "sg:classifiers":[
        {
            "category":"Building & Trades",
            "subcategory":"Construction",
            "type":"Services"
        }
    ],
    "sg:phone":"+1 718 434 7360",
    "sg:postcode":"11230",
    "sg:province":"NY",
    "sg:tags":[
        "contractor"
    ],
    "wof:name":"F & S Contracting",
    "wof:placetype":"venue"
},
  "geometry": {"coordinates":[-73.96979899999999,40.630536],"type":"Point"}
}