{
  "type": "Feature",
  "properties": {
    "addr:full":"278 City Island Ave Bronx NY 10464",
    "addr:housenumber":"278",
    "addr:postcode":"10464",
    "addr:street":"City Island Ave",
    "iso:country":"US",
    "sg:address":"278 City Island Ave",
    "sg:city":"Bronx",
    "sg:classifiers":[
        {
            "category":"Shopping",
            "subcategory":"Used Merchandise",
            "type":"Retail Goods"
        }
    ],
    "sg:phone":"+1 718 885 2172",
    "sg:postcode":"10464",
    "sg:province":"NY",
    "sg:tags":[
        "antique"
    ],
    "wof:name":"Main Street Antiques",
    "wof:placetype":"venue"
},
  "geometry": {"coordinates":[-73.78595199999999,40.845832],"type":"Point"}
}