{
  "type": "Feature",
  "properties": {
    "addr:full":"361 State Hwy 59 Nanuet NY 10954",
    "addr:housenumber":"361",
    "addr:postcode":"10954",
    "addr:street":"State Hwy 59",
    "iso:country":"US",
    "sg:address":"361 State Hwy 59",
    "sg:city":"Nanuet",
    "sg:classifiers":[
        {
            "category":"Freight",
            "type":"Transportation"
        }
    ],
    "sg:phone":"+1 845 624 7777",
    "sg:postcode":"10954",
    "sg:province":"NY",
    "sg:tags":[
        "commercial",
        "storage"
    ],
    "sg:website":"www.extraspace.com",
    "wof:name":"Extra Space Storage",
    "wof:placetype":"venue"
},
  "geometry": {"coordinates":[-74.02734,41.101923],"type":"Point"}
}