{
  "type": "Feature",
  "properties": {
    "iso:country":"US",
    "sg:address":"7 Broadview Rd",
    "sg:city":"Poughkeepsie",
    "sg:classifiers":[
        {
            "category":"Building & Trades",
            "subcategory":"Construction",
            "type":"Services"
        }
    ],
    "sg:phone":"+1 845 229 5596",
    "sg:postcode":"12603",
    "sg:province":"NY",
    "sg:tags":[
        "carpenter"
    ],
    "wof:name":"Bw Carpentry Plus Inc",
    "wof:placetype":"venue"
},
  "geometry": {"coordinates":[-73.90229600000001,41.622533],"type":"Point"}
}