{
  "type": "Feature",
  "properties": {
    "addr:full":"129 Sterling Pl Watertown NY 13601",
    "addr:housenumber":"129",
    "addr:postcode":"13601",
    "addr:street":"Sterling Pl",
    "iso:country":"US",
    "sg:address":"129 Sterling Pl",
    "sg:city":"Watertown",
    "sg:classifiers":[
        {
            "category":"Education",
            "subcategory":"School",
            "type":"Public Place"
        }
    ],
    "sg:phone":"+1 315 786 3988",
    "sg:postcode":"13601",
    "sg:province":"NY",
    "wof:name":"St Patrick's School",
    "wof:placetype":"venue"
},
  "geometry": {"coordinates":[-75.904079,43.972229],"type":"Point"}
}