{
  "type": "Feature",
  "properties": {
    "iso:country":"US",
    "sg:address":"36 Sea Gate Ave",
    "sg:city":"Westhampton",
    "sg:classifiers":[
        {
            "category":"Building & Trades",
            "subcategory":"Construction",
            "type":"Services"
        }
    ],
    "sg:phone":"+1 631 288 5944",
    "sg:postcode":"11977",
    "sg:province":"NY",
    "sg:tags":[
        "carpentry",
        "contractor"
    ],
    "wof:name":"Seabreeze Carpentry & Painting",
    "wof:placetype":"venue"
},
  "geometry": {"coordinates":[-72.672056,40.822561],"type":"Point"}
}