{
  "type": "Feature",
  "properties": {
    "addr:full":"215 W 125th Street New York NY 10027",
    "addr:housenumber":"215",
    "addr:postcode":"10027",
    "addr:street":"W 125Th Street",
    "iso:country":"US",
    "sg:address":"215 W 125th Street",
    "sg:city":"New York",
    "sg:classifiers":[
        {
            "category":"Health Services",
            "subcategory":"Hospital",
            "type":"Services"
        }
    ],
    "sg:phone":"+1 212 932 6500",
    "sg:postcode":"10027",
    "sg:province":"NY",
    "wof:name":"Renaissance Health Care Network",
    "wof:placetype":"venue"
},
  "geometry": {"coordinates":[-73.948792,40.809189],"type":"Point"}
}