{
  "type": "Feature",
  "properties": {
    "iso:country":"US",
    "sg:address":"241 Norris Dr",
    "sg:city":"Rochester",
    "sg:classifiers":[
        {
            "category":"Insurance",
            "subcategory":"Hazard Insurance",
            "type":"Services"
        },
        {
            "category":"Professional",
            "subcategory":"Computer Services",
            "type":"Services"
        }
    ],
    "sg:phone":"+1 585 423 9450",
    "sg:postcode":"14610",
    "sg:province":"NY",
    "sg:tags":[
        "sharing",
        "profit",
        "custom",
        "plan",
        "programing",
        "pension"
    ],
    "sg:website":"www.24hrhr.com",
    "wof:name":"H R Communications Inc",
    "wof:placetype":"venue"
},
  "geometry": {"coordinates":[-77.56324499999999,43.144146],"type":"Point"}
}