{
  "type": "Feature",
  "properties": {
    "addr:full":"165 W 66 St New York NY 10023",
    "addr:housenumber":"165",
    "addr:postcode":"10023",
    "addr:street":"W 66 St",
    "iso:country":"US",
    "sg:address":"165 W 66 St",
    "sg:city":"New York",
    "sg:classifiers":[
        {
            "category":"Health Services",
            "subcategory":"Health Practitioner",
            "type":"Services"
        }
    ],
    "sg:phone":"+1 212 799 9559",
    "sg:postcode":"10023",
    "sg:province":"NY",
    "sg:tags":[
        "pathologist",
        "speech"
    ],
    "wof:name":"Kling Voice & Speech Language",
    "wof:placetype":"venue"
},
  "geometry": {"coordinates":[-73.983316,40.774276],"type":"Point"}
}