{
  "type": "Feature",
  "properties": {
    "iso:country":"US",
    "sg:address":"7914 Bay Parkway",
    "sg:city":"Brooklyn",
    "sg:classifiers":[
        {
            "category":"Education",
            "subcategory":"School",
            "type":"Public Place"
        }
    ],
    "sg:phone":"+1 718 256 6603",
    "sg:postcode":"11214",
    "sg:province":"NY",
    "sg:tags":[
        "high",
        "middle",
        "elementary"
    ],
    "wof:name":"Bet Yaakov of Ateret Torah",
    "wof:placetype":"venue"
},
  "geometry": {"coordinates":[-73.990211,40.605582],"type":"Point"}
}