{
  "type": "Feature",
  "properties": {
    "iso:country":"US",
    "sg:address":"3320 Hillside Ave",
    "sg:city":"New Hyde Park",
    "sg:classifiers":[
        {
            "category":"Shopping",
            "subcategory":"Discount & Variety Stores",
            "type":"Retail Goods"
        }
    ],
    "sg:phone":"+1   ",
    "sg:postcode":"11040",
    "sg:province":"NY",
    "sg:tags":[
        "department"
    ],
    "wof:name":"Maces Closeout City",
    "wof:placetype":"venue"
},
  "geometry": {"coordinates":[-73.65966400000001,40.7529],"type":"Point"}
}