{
  "type": "Feature",
  "properties": {
    "addr:full":"4227 Merrick Rd Massapequa NY 11758",
    "addr:housenumber":"4227",
    "addr:postcode":"11758",
    "addr:street":"Merrick Rd",
    "iso:country":"US",
    "sg:address":"4227 Merrick Rd",
    "sg:city":"Massapequa",
    "sg:classifiers":[
        {
            "category":"Professional",
            "type":"Services"
        },
        {
            "category":"Deli",
            "type":"Food & Drink"
        },
        {
            "category":"Restaurant",
            "type":"Food & Drink"
        }
    ],
    "sg:phone":"+1 516 541 3400",
    "sg:postcode":"11758",
    "sg:province":"NY",
    "sg:tags":[
        "delicatessen",
        "caterer"
    ],
    "wof:name":"G M Deli",
    "wof:placetype":"venue"
},
  "geometry": {"coordinates":[-73.47595800000001,40.666759],"type":"Point"}
}