{
  "type": "Feature",
  "properties": {
    "addr:full":"Essex Street Market 120 Essex St, #17 New York NY 10002",
    "addr:housenumber":"120;17",
    "addr:postcode":"10002",
    "addr:street":"Essex Street;Essex St #",
    "iso:country":"US",
    "sg:address":"Essex Street Market 120 Essex St, #17",
    "sg:city":"New York",
    "sg:classifiers":[
        {
            "category":"Food & Beverages",
            "subcategory":"Cheese",
            "type":"Retail Goods"
        }
    ],
    "sg:phone":"+1 212 228 8204",
    "sg:postcode":"10002",
    "sg:province":"NY",
    "sg:tags":[
        "shop"
    ],
    "sg:website":"www.saxelbycheese.com",
    "wof:name":"Saxelby Cheesemongers",
    "wof:placetype":"venue"
},
  "geometry": {"coordinates":[-73.990089,40.715258],"type":"Point"}
}