{
  "type": "Feature",
  "properties": {
    "iso:country":"US",
    "sg:address":"4444 Hogmire Rd",
    "sg:city":"Avon",
    "sg:classifiers":[
        {
            "category":"Recreation",
            "type":"Entertainment"
        }
    ],
    "sg:phone":"+1 585 226 6287",
    "sg:postcode":"14414",
    "sg:province":"NY",
    "sg:tags":[
        "stable"
    ],
    "wof:name":"Mothersfield",
    "wof:placetype":"venue"
},
  "geometry": {"coordinates":[-77.776284,42.875097],"type":"Point"}
}