{
  "type": "Feature",
  "properties": {
    "addr:full":"32 Middle Neck Rd Great Neck NY 11021",
    "addr:housenumber":"32",
    "addr:postcode":"11021",
    "addr:street":"Middle Neck Rd",
    "iso:country":"US",
    "sg:address":"32 Middle Neck Rd",
    "sg:city":"Great Neck",
    "sg:classifiers":[
        {
            "category":"Shopping",
            "subcategory":"Gifts & Souvenirs",
            "type":"Retail Goods"
        }
    ],
    "sg:phone":"+1 516 466 3119",
    "sg:postcode":"11021",
    "sg:province":"NY",
    "sg:tags":[
        "shop"
    ],
    "wof:name":"Marel Silver Co Inc",
    "wof:placetype":"venue"
},
  "geometry": {"coordinates":[-73.72846800000001,40.787522],"type":"Point"}
}