{
  "type": "Feature",
  "properties": {
    "addr:full":"9737 Carousel Center Syracuse NY 13290",
    "addr:housenumber":"9737",
    "addr:postcode":"13290",
    "addr:street":"Carousel Center",
    "iso:country":"US",
    "sg:address":"9737 Carousel Center",
    "sg:city":"Syracuse",
    "sg:classifiers":[
        {
            "category":"Food & Beverages",
            "subcategory":"Specialty",
            "type":"Retail Goods"
        }
    ],
    "sg:phone":"+1   ",
    "sg:postcode":"13290",
    "sg:province":"NY",
    "sg:tags":[
        "a",
        "coffee",
        "tea",
        "retailer",
        "related",
        "mug",
        "appliance"
    ],
    "wof:name":"Barnies Coffee & Tea Co",
    "wof:placetype":"venue"
},
  "geometry": {"coordinates":[-76.170569,43.067034],"type":"Point"}
}