{
  "type": "Feature",
  "properties": {
    "addr:full":"157 W 122nd St New York NY 10027",
    "addr:housenumber":"157",
    "addr:postcode":"10027",
    "addr:street":"W 122Nd St",
    "iso:country":"US",
    "sg:address":"157 W 122nd St",
    "sg:city":"New York",
    "sg:classifiers":[
        {
            "category":"Organizations",
            "subcategory":"Membership Organization",
            "type":"Services"
        }
    ],
    "sg:phone":"+1 212 666 4163",
    "sg:postcode":"10027",
    "sg:province":"NY",
    "sg:website":"www.hcz.org",
    "wof:name":"Harlem Childrens Zone",
    "wof:placetype":"venue"
},
  "geometry": {"coordinates":[-73.948474,40.806419],"type":"Point"}
}