{
  "type": "Feature",
  "properties": {
    "iso:country":"US",
    "sg:address":"164-09 69th Ave",
    "sg:city":"Fresh Meadows",
    "sg:classifiers":[
        {
            "category":"Restaurant",
            "type":"Food & Drink"
        }
    ],
    "sg:phone":"+1 718 380 8878",
    "sg:postcode":"11365",
    "sg:province":"NY",
    "sg:tags":[
        "japanese"
    ],
    "wof:name":"Futigi",
    "wof:placetype":"venue"
},
  "geometry": {"coordinates":[-73.804834,40.733093],"type":"Point"}
}