{
  "type": "Feature",
  "properties": {
    "iso:country":"US",
    "sg:address":"1 Woodsorrell Ln",
    "sg:city":"East Northport",
    "sg:classifiers":[
        {
            "category":"Organizations",
            "subcategory":"Religious Organization",
            "type":"Services"
        }
    ],
    "sg:phone":"+1 631 266 5049",
    "sg:postcode":"11731",
    "sg:province":"NY",
    "sg:tags":[
        "clergy"
    ],
    "wof:name":"C Cameron",
    "wof:placetype":"venue"
},
  "geometry": {"coordinates":[-73.29678699999999,40.862657],"type":"Point"}
}