{
  "type": "Feature",
  "properties": {
    "addr:full":"12 Cowpath Glen Head NY 11545",
    "addr:housenumber":"12",
    "addr:postcode":"11545",
    "addr:street":"Cowpath Glen Head",
    "iso:country":"US",
    "sg:address":"12 Cowpath",
    "sg:city":"Glen Head",
    "sg:classifiers":[
        {
            "category":"Travel",
            "subcategory":"Travel Agent",
            "type":"Entertainment"
        }
    ],
    "sg:phone":"+1   ",
    "sg:postcode":"11545",
    "sg:province":"NY",
    "sg:tags":[
        "agency"
    ],
    "wof:name":"Bridge Holidays",
    "wof:placetype":"venue"
},
  "geometry": {"coordinates":[-73.564159,40.805697],"type":"Point"}
}