{
  "type": "Feature",
  "properties": {
    "addr:full":"6424 4th Ave Brooklyn NY 11220",
    "addr:housenumber":"6424",
    "addr:postcode":"11220",
    "addr:street":"4Th Ave",
    "iso:country":"US",
    "sg:address":"6424 4th Ave",
    "sg:city":"Brooklyn",
    "sg:classifiers":[
        {
            "category":"Food & Beverages",
            "subcategory":"Groceries & Convenience Stores",
            "type":"Retail Goods"
        }
    ],
    "sg:phone":"+1 718 492 0824",
    "sg:postcode":"11220",
    "sg:province":"NY",
    "sg:tags":[
        "grocer"
    ],
    "wof:name":"New Towers Deli & Grocery",
    "wof:placetype":"venue"
},
  "geometry": {"coordinates":[-74.0214,40.638199],"type":"Point"}
}