{
  "type": "Feature",
  "properties": {
    "addr:full":"22703 Merrick Blvd Springfield Gardens NY 11413",
    "addr:housenumber":"22703",
    "addr:postcode":"11413",
    "addr:street":"Merrick Blvd",
    "iso:country":"US",
    "sg:address":"22703 Merrick Blvd",
    "sg:city":"Springfield Gardens",
    "sg:classifiers":[
        {
            "category":"Food & Beverages",
            "subcategory":"Meat & Fish",
            "type":"Retail Goods"
        }
    ],
    "sg:phone":"+1 718 341 2477",
    "sg:postcode":"11413",
    "sg:province":"NY",
    "sg:tags":[
        "seafood",
        "market"
    ],
    "wof:name":"Monte's Seafood",
    "wof:placetype":"venue"
},
  "geometry": {"coordinates":[-73.74296200000001,40.677163],"type":"Point"}
}