{
  "type": "Feature",
  "properties": {
    "iso:country":"US",
    "sg:address":"7177 Lane Rd",
    "sg:city":"Victor",
    "sg:classifiers":[
        {
            "category":"Building & Trades",
            "subcategory":"Construction",
            "type":"Services"
        }
    ],
    "sg:phone":"+1 585 924 9382",
    "sg:postcode":"14564",
    "sg:province":"NY",
    "sg:tags":[
        "excavation",
        "contractor"
    ],
    "wof:name":"Tc Pipeline",
    "wof:placetype":"venue"
},
  "geometry": {"coordinates":[-77.42202399999999,42.997882],"type":"Point"}
}