{
  "type": "Feature",
  "properties": {
    "iso:country":"US",
    "sg:address":"1145 Co Rd 8",
    "sg:city":"Farmington",
    "sg:classifiers":[
        {
            "category":"Food & Beverages",
            "subcategory":"Candy",
            "type":"Retail Goods"
        }
    ],
    "sg:phone":"+1   ",
    "sg:postcode":"14425",
    "sg:province":"NY",
    "wof:name":"Chocolate Creations Plus",
    "wof:placetype":"venue"
},
  "geometry": {"coordinates":[-77.324898,42.978738],"type":"Point"}
}