{
  "type": "Feature",
  "properties": {
    "addr:full":"1566 Bedford Ave Brooklyn NY 11225",
    "addr:housenumber":"1566",
    "addr:postcode":"11225",
    "addr:street":"Bedford Ave",
    "iso:country":"US",
    "sg:address":"1566 Bedford Ave",
    "sg:city":"Brooklyn",
    "sg:classifiers":[
        {
            "category":"Wholesale",
            "subcategory":"Auto Parts",
            "type":"Manufacturing & Wholesale Goods"
        }
    ],
    "sg:phone":"+1 718 771 0998",
    "sg:postcode":"11225",
    "sg:province":"NY",
    "sg:tags":[
        "body",
        "automobile",
        "shop"
    ],
    "wof:name":"Shane Auto Repair",
    "wof:placetype":"venue"
},
  "geometry": {"coordinates":[-73.955907,40.66836],"type":"Point"}
}