{
  "type": "Feature",
  "properties": {
    "iso:country":"US",
    "sg:address":"174 Creek Rd",
    "sg:city":"Mc Donough",
    "sg:classifiers":[
        {
            "category":"Manufacturing",
            "subcategory":"Retail Goods",
            "type":"Manufacturing & Wholesale Goods"
        }
    ],
    "sg:phone":"+1   ",
    "sg:postcode":"13801",
    "sg:province":"NY",
    "sg:tags":[
        "product",
        "mfg"
    ],
    "wof:name":"Wing Nuts",
    "wof:placetype":"venue"
},
  "geometry": {"coordinates":[-75.762659,42.463972],"type":"Point"}
}