{
  "type": "Feature",
  "properties": {
    "iso:country":"US",
    "sg:address":"4174 State Hwy 3",
    "sg:city":"Star Lake",
    "sg:classifiers":[
        {
            "category":"Wholesale",
            "subcategory":"Scrap",
            "type":"Manufacturing & Wholesale Goods"
        }
    ],
    "sg:phone":"+1 315 848 2330",
    "sg:postcode":"13690",
    "sg:province":"NY",
    "sg:tags":[
        "recycling",
        "center"
    ],
    "wof:name":"Clifton Fine Redemption Ctr",
    "wof:placetype":"venue"
},
  "geometry": {"coordinates":[-75.042732,44.162704],"type":"Point"}
}