{
  "type": "Feature",
  "properties": {
    "addr:full":"726 Flatbush Ave Brooklyn NY 11226",
    "addr:housenumber":"726",
    "addr:postcode":"11226",
    "addr:street":"Flatbush Ave",
    "iso:country":"US",
    "sg:address":"726 Flatbush Ave",
    "sg:city":"Brooklyn",
    "sg:classifiers":[
        {
            "category":"Shopping",
            "subcategory":"Discount & Variety Stores",
            "type":"Retail Goods"
        }
    ],
    "sg:phone":"+1 718 469 9626",
    "sg:postcode":"11226",
    "sg:province":"NY",
    "wof:name":"Gem Stores",
    "wof:placetype":"venue"
},
  "geometry": {"coordinates":[-73.959788,40.65494],"type":"Point"}
}