{
  "type": "Feature",
  "properties": {
    "addr:full":"132 Bellmore Ave Point Lookout NY 11569",
    "addr:housenumber":"132",
    "addr:postcode":"11569",
    "addr:street":"Bellmore Ave",
    "iso:country":"US",
    "sg:address":"132 Bellmore Ave",
    "sg:city":"Point Lookout",
    "sg:classifiers":[
        {
            "category":"Professional",
            "subcategory":"Lawyer & Legal Services",
            "type":"Services"
        }
    ],
    "sg:phone":"+1 516 431 1120",
    "sg:postcode":"11569",
    "sg:province":"NY",
    "sg:tags":[
        "attorney"
    ],
    "wof:name":"Mc Glew & Tuttle",
    "wof:placetype":"venue"
},
  "geometry": {"coordinates":[-73.581965,40.588799],"type":"Point"}
}