{
  "type": "Feature",
  "properties": {
    "iso:country":"US",
    "sg:address":"388 Montauk Hwy",
    "sg:city":"Eastport",
    "sg:classifiers":[
        {
            "category":"Retail",
            "subcategory":"Auto Repair",
            "type":"Services"
        }
    ],
    "sg:phone":"+1 631 325 0279",
    "sg:postcode":"11941",
    "sg:province":"NY",
    "wof:name":"Getty Gas Station",
    "wof:placetype":"venue"
},
  "geometry": {"coordinates":[-72.722286,40.825457],"type":"Point"}
}