{
  "type": "Feature",
  "properties": {
    "addr:full":"598 Morris Ave Bronx NY 10451",
    "addr:housenumber":"598",
    "addr:postcode":"10451",
    "addr:street":"Morris Ave",
    "iso:country":"US",
    "sg:address":"598 Morris Ave",
    "sg:city":"Bronx",
    "sg:classifiers":[
        {
            "category":"Deli",
            "type":"Food & Drink"
        },
        {
            "category":"Food & Beverages",
            "subcategory":"Bakery",
            "type":"Retail Goods"
        }
    ],
    "sg:phone":"+1 347 270 3551",
    "sg:postcode":"10451",
    "sg:province":"NY",
    "sg:tags":[
        "sandwich"
    ],
    "wof:name":"Juaquin Deli",
    "wof:placetype":"venue"
},
  "geometry": {"coordinates":[-73.922062,40.818496],"type":"Point"}
}