{
  "type": "Feature",
  "properties": {
    "iso:country":"US",
    "sg:address":"9 Northview Ln",
    "sg:city":"Hopewell Jct",
    "sg:classifiers":[
        {
            "category":"Retail",
            "subcategory":"Repair Shop",
            "type":"Services"
        }
    ],
    "sg:phone":"+1 845 226 5871",
    "sg:postcode":"12533",
    "sg:province":"NY",
    "sg:tags":[
        "television",
        "radio"
    ],
    "wof:name":"Audio Video Electronics",
    "wof:placetype":"venue"
},
  "geometry": {"coordinates":[-73.801644,41.574425],"type":"Point"}
}