{
  "type": "Feature",
  "properties": {
    "iso:country":"US",
    "sg:address":"303 Denise Rd",
    "sg:city":"Rochester",
    "sg:classifiers":[
        {
            "category":"Food & Beverages",
            "subcategory":"Meat & Fish",
            "type":"Retail Goods"
        }
    ],
    "sg:phone":"+1   ",
    "sg:postcode":"14612",
    "sg:province":"NY",
    "wof:name":"Ocean Foods Inc",
    "wof:placetype":"venue"
},
  "geometry": {"coordinates":[-77.62539700000001,43.241638],"type":"Point"}
}