{
  "type": "Feature",
  "properties": {
    "addr:full":"1 Wilson Dr Middletown NY 10941",
    "addr:housenumber":"1",
    "addr:postcode":"10941",
    "addr:street":"Wilson Dr",
    "iso:country":"US",
    "sg:address":"1 Wilson Dr",
    "sg:city":"Middletown",
    "sg:classifiers":[
        {
            "category":"Real Estate",
            "subcategory":"Architect",
            "type":"Services"
        }
    ],
    "sg:phone":"+1 845 624 4581",
    "sg:postcode":"10941",
    "sg:province":"NY",
    "sg:tags":[
        "estimate",
        "construction"
    ],
    "wof:name":"All Skills Construction",
    "wof:placetype":"venue"
},
  "geometry": {"coordinates":[-74.366663,41.463555],"type":"Point"}
}