{
  "type": "Feature",
  "properties": {
    "iso:country":"US",
    "sg:address":"1727 Amsterdam Ave",
    "sg:city":"New York",
    "sg:classifiers":[
        {
            "category":"Utilities",
            "subcategory":"Refuse",
            "type":"Services"
        }
    ],
    "sg:phone":"+1 212 368 4765",
    "sg:postcode":"10031",
    "sg:province":"NY",
    "sg:tags":[
        "waste",
        "removal"
    ],
    "wof:name":"Bendiner & Schlesinger Inc",
    "wof:placetype":"venue"
},
  "geometry": {"coordinates":[-73.94718899999999,40.825616],"type":"Point"}
}