{
  "type": "Feature",
  "properties": {
    "iso:country":"US",
    "sg:address":"2040 Forest Ave",
    "sg:city":"Staten Island",
    "sg:classifiers":[
        {
            "category":"Food & Beverages",
            "subcategory":"Groceries & Convenience Stores",
            "type":"Retail Goods"
        }
    ],
    "sg:phone":"+1   ",
    "sg:postcode":"10303",
    "sg:province":"NY",
    "wof:name":"Waldbaums Supermarket",
    "wof:placetype":"venue"
},
  "geometry": {"coordinates":[-74.157241,40.626028],"type":"Point"}
}