{
  "type": "Feature",
  "properties": {
    "iso:country":"US",
    "sg:address":"5 Krey Blvd",
    "sg:city":"Rensselaer",
    "sg:classifiers":[
        {
            "category":"Wholesale",
            "subcategory":"Sporting Goods",
            "type":"Manufacturing & Wholesale Goods"
        },
        {
            "category":"Shopping",
            "subcategory":"Bicycles & Sporting Goods",
            "type":"Retail Goods"
        }
    ],
    "sg:phone":"+1 518 283 0126",
    "sg:postcode":"12144",
    "sg:province":"NY",
    "sg:tags":[
        "equipment",
        "recreational",
        "playground"
    ],
    "wof:name":"Bill Simione & Assoc Inc",
    "wof:placetype":"venue"
},
  "geometry": {"coordinates":[-73.709399,42.647138],"type":"Point"}
}