{
  "type": "Feature",
  "properties": {
    "addr:full":"6230 S Stockton-Cassadaga Rd Sinclairville NY 14782",
    "addr:housenumber":"6230",
    "addr:postcode":"14782",
    "addr:street":"S Stockton-Cassadaga Rd",
    "iso:country":"US",
    "sg:address":"6230 S Stockton-Cassadaga Rd",
    "sg:city":"Sinclairville",
    "sg:classifiers":[
        {
            "category":"Autos & Motor Vehicles",
            "subcategory":"Automobile Sales",
            "type":"Retail Goods"
        }
    ],
    "sg:phone":"+1   ",
    "sg:postcode":"14782",
    "sg:province":"NY",
    "sg:tags":[
        "used"
    ],
    "wof:name":"Julie Auto Sales",
    "wof:placetype":"venue"
},
  "geometry": {"coordinates":[-79.315583,42.262966],"type":"Point"}
}