{
  "type": "Feature",
  "properties": {
    "addr:full":"31 Main St Arkport NY 14807",
    "addr:housenumber":"31",
    "addr:postcode":"14807",
    "addr:street":"Main St",
    "iso:country":"US",
    "sg:address":"31 Main St",
    "sg:city":"Arkport",
    "sg:classifiers":[
        {
            "category":"Utilities",
            "subcategory":"Water",
            "type":"Services"
        }
    ],
    "sg:phone":"+1 607 295 7543",
    "sg:postcode":"14807",
    "sg:province":"NY",
    "sg:tags":[
        "systems-equipment",
        "industrial",
        "treatment",
        "supplies-commercial"
    ],
    "wof:name":"Certified Water Testing",
    "wof:placetype":"venue"
},
  "geometry": {"coordinates":[-77.695831,42.39259],"type":"Point"}
}