{
  "type": "Feature",
  "properties": {
    "addr:full":"1915 Ave M Brooklyn NY 11230",
    "addr:postcode":"11230",
    "addr:street":"1915 Ave M",
    "iso:country":"US",
    "sg:address":"1915 Ave M",
    "sg:city":"Brooklyn",
    "sg:classifiers":[
        {
            "category":"Shopping",
            "subcategory":"Computers & Home Electronics",
            "type":"Retail Goods"
        }
    ],
    "sg:phone":"+1 212 619 6363",
    "sg:postcode":"11230",
    "sg:province":"NY",
    "sg:tags":[
        "equipment",
        "dealer"
    ],
    "sg:website":"www.rentapcnow.com",
    "wof:name":"A Computer Rental Co",
    "wof:placetype":"venue"
},
  "geometry": {"coordinates":[-73.95517700000001,40.618614],"type":"Point"}
}