{
  "type": "Feature",
  "properties": {
    "addr:full":"1362 Flatbush Ave Brooklyn NY 11210",
    "addr:housenumber":"1362",
    "addr:postcode":"11210",
    "addr:street":"Flatbush Ave",
    "iso:country":"US",
    "sg:address":"1362 Flatbush Ave",
    "sg:city":"Brooklyn",
    "sg:classifiers":[
        {
            "category":"Retail",
            "subcategory":"Repair Shop",
            "type":"Services"
        }
    ],
    "sg:phone":"+1 718 421 5898",
    "sg:postcode":"11210",
    "sg:province":"NY",
    "sg:tags":[
        "appliance"
    ],
    "wof:name":"Glen's Appliance Svc",
    "wof:placetype":"venue"
},
  "geometry": {"coordinates":[-73.952444,40.637352],"type":"Point"}
}