{
  "type": "Feature",
  "properties": {
    "addr:full":"3077 3rd Ave Bronx NY 10451",
    "addr:housenumber":"3077",
    "addr:postcode":"10451",
    "addr:street":"3Rd Ave",
    "iso:country":"US",
    "sg:address":"3077 3rd Ave",
    "sg:city":"Bronx",
    "sg:classifiers":[
        {
            "category":"Retail",
            "subcategory":"Repair Shop",
            "type":"Services"
        }
    ],
    "sg:phone":"+1 718 764 5305",
    "sg:postcode":"10451",
    "sg:province":"NY",
    "sg:tags":[
        "lock",
        "locksmith"
    ],
    "wof:name":"7 Day Anyplace A Locksmith",
    "wof:placetype":"venue"
},
  "geometry": {"coordinates":[-73.912301,40.821385],"type":"Point"}
}