{
  "type": "Feature",
  "properties": {
    "iso:country":"US",
    "sg:address":"205 W 29th St",
    "sg:city":"New York",
    "sg:classifiers":[
        {
            "category":"Building & Trades",
            "subcategory":"Construction",
            "type":"Services"
        }
    ],
    "sg:phone":"+1 212 239 9080",
    "sg:postcode":"10001",
    "sg:province":"NY",
    "sg:tags":[
        "contractor"
    ],
    "wof:name":"Target NY Construction Inc",
    "wof:placetype":"venue"
},
  "geometry": {"coordinates":[-73.99297300000001,40.748034],"type":"Point"}
}