{
  "type": "Feature",
  "properties": {
    "addr:full":"10 South Ave Bloomfield NY 14469",
    "addr:housenumber":"10",
    "addr:postcode":"14469",
    "addr:street":"South Ave",
    "iso:country":"US",
    "sg:address":"10 South Ave",
    "sg:city":"Bloomfield",
    "sg:classifiers":[
        {
            "category":"Organizations",
            "subcategory":"Religious Organization",
            "type":"Services"
        }
    ],
    "sg:phone":"+1   ",
    "sg:postcode":"14469",
    "sg:province":"NY",
    "wof:name":"First Congregtnl Untd Chrch of",
    "wof:placetype":"venue"
},
  "geometry": {"coordinates":[-77.43438999999999,42.895931],"type":"Point"}
}