{
  "type": "Feature",
  "properties": {
    "iso:country":"US",
    "sg:address":"100 E 183rd St",
    "sg:city":"Bronx",
    "sg:classifiers":[
        {
            "category":"Food & Beverages",
            "subcategory":"Fruits & Vegetables",
            "type":"Retail Goods"
        }
    ],
    "sg:phone":"+1   ",
    "sg:postcode":"10453",
    "sg:province":"NY",
    "wof:name":"Valle Deli Market",
    "wof:placetype":"venue"
},
  "geometry": {"coordinates":[-73.90093899999999,40.857759],"type":"Point"}
}