{
  "type": "Feature",
  "properties": {
    "iso:country":"US",
    "sg:address":"69 Florida St",
    "sg:city":"Farmingdale",
    "sg:classifiers":[
        {
            "category":"Wholesale",
            "subcategory":"Machinery & Supplies",
            "type":"Manufacturing & Wholesale Goods"
        }
    ],
    "sg:phone":"+1 631 752 7606",
    "sg:postcode":"11735",
    "sg:province":"NY",
    "sg:tags":[
        "plumbing",
        "marine"
    ],
    "sg:website":"www.northeastsanitation.com",
    "wof:name":"Northeast Marine Sanitation",
    "wof:placetype":"venue"
},
  "geometry": {"coordinates":[-73.42107900000001,40.713781],"type":"Point"}
}