{
  "type": "Feature",
  "properties": {
    "addr:full":"4702 5th St Long Island City NY 11101",
    "addr:housenumber":"4702",
    "addr:postcode":"11101",
    "addr:street":"5Th St",
    "iso:country":"US",
    "sg:address":"4702 5th St",
    "sg:city":"Long Island City",
    "sg:classifiers":[
        {
            "category":"Shopping",
            "subcategory":"Pharmacy",
            "type":"Retail Goods"
        }
    ],
    "sg:phone":"+1 718 472 3600",
    "sg:postcode":"11101",
    "sg:province":"NY",
    "sg:tags":[
        "drugstore"
    ],
    "sg:website":"www.duanereade.com",
    "wof:name":"Duane Reade",
    "wof:placetype":"venue"
},
  "geometry": {"coordinates":[-73.955535,40.745873],"type":"Point"}
}