{
  "type": "Feature",
  "properties": {
    "iso:country":"US",
    "sg:address":"378 S Oyster Bay Rd",
    "sg:city":"Hicksville",
    "sg:classifiers":[
        {
            "category":"Banks & Credit Unions",
            "subcategory":"Investment Brokerage",
            "type":"Services"
        }
    ],
    "sg:phone":"+1 516 931 1090",
    "sg:postcode":"11801",
    "sg:province":"NY",
    "sg:tags":[
        "brokerage",
        "security"
    ],
    "wof:name":"Benjamin Securities Inc",
    "wof:placetype":"venue"
},
  "geometry": {"coordinates":[-73.50331,40.784646],"type":"Point"}
}