{
  "type": "Feature",
  "properties": {
    "addr:full":"570 Pine Aire Dr Bay Shore NY 11706",
    "addr:housenumber":"570",
    "addr:postcode":"11706",
    "addr:street":"Pine Aire Dr",
    "iso:country":"US",
    "sg:address":"570 Pine Aire Dr",
    "sg:city":"Bay Shore",
    "sg:classifiers":[
        {
            "category":"Autos & Motor Vehicles",
            "subcategory":"Auto Supplies",
            "type":"Retail Goods"
        }
    ],
    "sg:phone":"+1 631 242 8864",
    "sg:postcode":"11706",
    "sg:province":"NY",
    "sg:tags":[
        "tire"
    ],
    "wof:name":"Roadside Wholesale Tires",
    "wof:placetype":"venue"
},
  "geometry": {"coordinates":[-73.284042,40.771224],"type":"Point"}
}