{
  "type": "Feature",
  "properties": {
    "addr:full":"168 Campbell Ave Yorkville NY 13495",
    "addr:housenumber":"168",
    "addr:postcode":"13495",
    "addr:street":"Campbell Ave",
    "iso:country":"US",
    "sg:address":"168 Campbell Ave",
    "sg:city":"Yorkville",
    "sg:classifiers":[
        {
            "category":"Building & Trades",
            "subcategory":"Construction",
            "type":"Services"
        }
    ],
    "sg:phone":"+1 315 724 2313",
    "sg:postcode":"13495",
    "sg:province":"NY",
    "sg:tags":[
        "marking",
        "maintenance",
        "parking"
    ],
    "wof:name":"Yorkville Village Highway Dept",
    "wof:placetype":"venue"
},
  "geometry": {"coordinates":[-75.268973,43.109011],"type":"Point"}
}