{
  "type": "Feature",
  "properties": {
    "iso:country":"US",
    "sg:address":"14359 243rd St",
    "sg:city":"Rosedale",
    "sg:classifiers":[
        {
            "category":"Food & Beverages",
            "subcategory":"Groceries & Convenience Stores",
            "type":"Retail Goods"
        }
    ],
    "sg:phone":"+1 718 481 6481",
    "sg:postcode":"11422",
    "sg:province":"NY",
    "wof:name":"Bak Soonki",
    "wof:placetype":"venue"
},
  "geometry": {"coordinates":[-73.7388,40.660801],"type":"Point"}
}