{
  "type": "Feature",
  "properties": {
    "iso:country":"US",
    "sg:address":"509 McLean Rd",
    "sg:city":"Cortland",
    "sg:classifiers":[
        {
            "category":"Building & Trades",
            "subcategory":"Construction",
            "type":"Services"
        }
    ],
    "sg:phone":"+1 607 756 2266",
    "sg:postcode":"13045",
    "sg:province":"NY",
    "sg:tags":[
        "house"
    ],
    "wof:name":"AP Builders LLC",
    "wof:placetype":"venue"
},
  "geometry": {"coordinates":[-76.233163,42.578274],"type":"Point"}
}