{
  "type": "Feature",
  "properties": {
    "addr:full":"10218 159th Rd Howard Beach NY 11414",
    "addr:housenumber":"10218",
    "addr:postcode":"11414",
    "addr:street":"159Th Rd",
    "iso:country":"US",
    "sg:address":"10218 159th Rd",
    "sg:city":"Howard Beach",
    "sg:classifiers":[
        {
            "category":"Arts & Performance",
            "subcategory":"Arts Center",
            "type":"Entertainment"
        }
    ],
    "sg:phone":"+1 718 296 2929",
    "sg:postcode":"11414",
    "sg:province":"NY",
    "sg:tags":[
        "performing"
    ],
    "wof:name":"Spotlight Dance Factory",
    "wof:placetype":"venue"
},
  "geometry": {"coordinates":[-73.830771,40.659643],"type":"Point"}
}