{
  "type": "Feature",
  "properties": {
    "iso:country":"US",
    "sg:address":"545 Kings Hwy",
    "sg:city":"Brooklyn",
    "sg:classifiers":[
        {
            "category":"Shopping",
            "subcategory":"Jewelry",
            "type":"Retail Goods"
        }
    ],
    "sg:phone":"+1 718 336 1980",
    "sg:postcode":"11223",
    "sg:province":"NY",
    "sg:tags":[
        "jeweler"
    ],
    "wof:name":"Chamoula Jewelers",
    "wof:placetype":"venue"
},
  "geometry": {"coordinates":[-73.96935999999999,40.604631],"type":"Point"}
}