{
  "type": "Feature",
  "properties": {
    "addr:full":"1344 Middle Country Rd Centereach NY 11720",
    "addr:housenumber":"1344",
    "addr:postcode":"11720",
    "addr:street":"Middle Country Rd",
    "iso:country":"US",
    "sg:address":"1344 Middle Country Rd",
    "sg:city":"Centereach",
    "sg:classifiers":[
        {
            "category":"Health Services",
            "subcategory":"Doctor",
            "type":"Services"
        }
    ],
    "sg:phone":"+1 631 698 4932",
    "sg:postcode":"11720",
    "sg:province":"NY",
    "wof:name":"Thomas Joseph MD",
    "wof:placetype":"venue"
},
  "geometry": {"coordinates":[-73.105003,40.858601],"type":"Point"}
}