{
  "type": "Feature",
  "properties": {
    "addr:full":"33 Willis Ave Mineola NY 11501",
    "addr:housenumber":"33",
    "addr:postcode":"11501",
    "addr:street":"Willis Ave",
    "iso:country":"US",
    "sg:address":"33 Willis Ave",
    "sg:city":"Mineola",
    "sg:classifiers":[
        {
            "category":"Professional",
            "subcategory":"Lawyer & Legal Services",
            "type":"Services"
        }
    ],
    "sg:phone":"+1 516 877 7300",
    "sg:postcode":"11501",
    "sg:province":"NY",
    "sg:tags":[
        "attorney"
    ],
    "wof:name":"Seaey Vogel & Oziel",
    "wof:placetype":"venue"
},
  "geometry": {"coordinates":[-73.63625500000001,40.740373],"type":"Point"}
}