{
  "type": "Feature",
  "properties": {
    "addr:full":"5000 15th Ave Brooklyn NY 11219",
    "addr:housenumber":"5000",
    "addr:postcode":"11219",
    "addr:street":"15Th Ave",
    "iso:country":"US",
    "sg:address":"5000 15th Ave",
    "sg:city":"Brooklyn",
    "sg:classifiers":[
        {
            "category":"Organizations",
            "subcategory":"Religious Organization",
            "type":"Services"
        }
    ],
    "sg:phone":"+1 718 853 7419",
    "sg:postcode":"11219",
    "sg:province":"NY",
    "sg:tags":[
        "clergy"
    ],
    "wof:name":"E Kupperman",
    "wof:placetype":"venue"
},
  "geometry": {"coordinates":[-73.988879,40.631246],"type":"Point"}
}