{
  "type": "Feature",
  "properties": {
    "addr:full":"194 Brown Pl Bronx NY 10454",
    "addr:housenumber":"194",
    "addr:postcode":"10454",
    "addr:street":"Brown Pl",
    "iso:country":"US",
    "sg:address":"194 Brown Pl",
    "sg:city":"Bronx",
    "sg:classifiers":[
        {
            "category":"Social Services",
            "type":"Services"
        }
    ],
    "sg:phone":"+1 718 742 4170",
    "sg:postcode":"10454",
    "sg:province":"NY",
    "sg:tags":[
        "organization",
        "welfare"
    ],
    "wof:name":"Leeward Hall",
    "wof:placetype":"venue"
},
  "geometry": {"coordinates":[-73.92052200000001,40.80711],"type":"Point"}
}