{
  "type": "Feature",
  "properties": {
    "addr:full":"1976 Davidson Ave Bronx NY 10453",
    "addr:housenumber":"1976",
    "addr:postcode":"10453",
    "addr:street":"Davidson Ave",
    "iso:country":"US",
    "sg:address":"1976 Davidson Ave",
    "sg:city":"Bronx",
    "sg:classifiers":[
        {
            "category":"Food & Beverages",
            "subcategory":"Bakery",
            "type":"Retail Goods"
        }
    ],
    "sg:phone":"+1 718 583 2503",
    "sg:postcode":"10453",
    "sg:province":"NY",
    "sg:tags":[
        "baker"
    ],
    "wof:name":"LA Sultana Bakery",
    "wof:placetype":"venue"
},
  "geometry": {"coordinates":[-73.908551,40.853613],"type":"Point"}
}