{
  "type": "Feature",
  "properties": {
    "iso:country":"US",
    "sg:address":"8196 Dexter Pkwy",
    "sg:city":"Baldwinsville",
    "sg:classifiers":[
        {
            "category":"Shopping",
            "subcategory":"Catalog Store",
            "type":"Retail Goods"
        }
    ],
    "sg:phone":"+1   ",
    "sg:postcode":"13027",
    "sg:province":"NY",
    "sg:tags":[
        "mail",
        "house"
    ],
    "wof:name":"Baldwinsville Brand Source",
    "wof:placetype":"venue"
},
  "geometry": {"coordinates":[-76.35017999999999,43.167126],"type":"Point"}
}