{
  "type": "Feature",
  "properties": {
    "addr:full":"301 E 87th St New York NY 10128",
    "addr:housenumber":"301",
    "addr:postcode":"10128",
    "addr:street":"E 87Th St",
    "iso:country":"US",
    "sg:address":"301 E 87th St",
    "sg:city":"New York",
    "sg:classifiers":[
        {
            "category":"Real Estate",
            "subcategory":"Real Estate Operator",
            "type":"Services"
        }
    ],
    "sg:phone":"+1 212 860 0958",
    "sg:postcode":"10128",
    "sg:province":"NY",
    "sg:tags":[
        "apartment"
    ],
    "wof:name":"Corniche the",
    "wof:placetype":"venue"
},
  "geometry": {"coordinates":[-73.95120199999999,40.778599],"type":"Point"}
}