{
  "type": "Feature",
  "properties": {
    "iso:country":"US",
    "sg:address":"209 S Fehr Way",
    "sg:city":"Bay Shore",
    "sg:classifiers":[
        {
            "category":"Manufacturing",
            "subcategory":"Metals",
            "type":"Manufacturing & Wholesale Goods"
        },
        {
            "category":"Building & Trades",
            "subcategory":"Construction",
            "type":"Services"
        }
    ],
    "sg:phone":"+1 631 242 6293",
    "sg:postcode":"11706",
    "sg:province":"NY",
    "sg:tags":[
        "fabricator",
        "sheet",
        "contractor"
    ],
    "wof:name":"Cool Sheet Metal Inc",
    "wof:placetype":"venue"
},
  "geometry": {"coordinates":[-73.285011,40.765005],"type":"Point"}
}