{
  "type": "Feature",
  "properties": {
    "addr:full":"1856 Pleasantville Rd Ossining NY 10562",
    "addr:housenumber":"1856",
    "addr:postcode":"10562",
    "addr:street":"Pleasantville Rd",
    "iso:country":"US",
    "sg:address":"1856 Pleasantville Rd",
    "sg:city":"Ossining",
    "sg:classifiers":[
        {
            "category":"Shopping",
            "subcategory":"Mobile Phones",
            "type":"Retail Goods"
        }
    ],
    "sg:phone":"+1 914 762 2188",
    "sg:postcode":"10562",
    "sg:province":"NY",
    "sg:website":"www.radioshack.com",
    "wof:name":"Radioshack",
    "wof:placetype":"venue"
},
  "geometry": {"coordinates":[-73.851997,41.171001],"type":"Point"}
}