{
  "type": "Feature",
  "properties": {
    "iso:country":"US",
    "sg:address":"46 Southridge Dr",
    "sg:city":"Glen Cove",
    "sg:classifiers":[
        {
            "category":"Retail",
            "subcategory":"Repair Shop",
            "type":"Services"
        }
    ],
    "sg:phone":"+1   ",
    "sg:postcode":"11542",
    "sg:province":"NY",
    "sg:tags":[
        "instrument",
        "musical"
    ],
    "wof:name":"Richard Cheshire",
    "wof:placetype":"venue"
},
  "geometry": {"coordinates":[-73.602226,40.856635],"type":"Point"}
}