{
  "type": "Feature",
  "properties": {
    "iso:country":"US",
    "sg:address":"19 Mitchell Dr",
    "sg:city":"Great Neck",
    "sg:classifiers":[
        {
            "category":"Real Estate",
            "subcategory":"Real Estate Operator",
            "type":"Services"
        }
    ],
    "sg:phone":"+1 516 487 7674",
    "sg:postcode":"11024",
    "sg:province":"NY",
    "sg:tags":[
        "building",
        "nonresidential"
    ],
    "wof:name":"Damast Realty Holding Corp",
    "wof:placetype":"venue"
},
  "geometry": {"coordinates":[-73.733844,40.82439],"type":"Point"}
}