{
  "type": "Feature",
  "properties": {
    "iso:country":"US",
    "sg:address":"484 77th Street",
    "sg:city":"Brooklyn",
    "sg:classifiers":[
        {
            "category":"Restaurant",
            "type":"Food & Drink"
        },
        {
            "category":"Food & Beverages",
            "subcategory":"Ethnic Foods",
            "type":"Retail Goods"
        }
    ],
    "sg:phone":"+1 718 921 2400",
    "sg:postcode":"11209",
    "sg:province":"NY",
    "sg:tags":[
        "french",
        "moroccan",
        "grocers-ethnic"
    ],
    "sg:website":"www.lamaisonducouscous.com/",
    "wof:name":"La Maison Du Couscous",
    "wof:placetype":"venue"
},
  "geometry": {"coordinates":[-74.02354099999999,40.628119],"type":"Point"}
}