{
  "type": "Feature",
  "properties": {
    "addr:full":"10650 Sutphin Blvd Jamaica NY 11435",
    "addr:housenumber":"10650",
    "addr:postcode":"11435",
    "addr:street":"Sutphin Blvd",
    "iso:country":"US",
    "sg:address":"10650 Sutphin Blvd",
    "sg:city":"Jamaica",
    "sg:classifiers":[
        {
            "category":"Restaurant",
            "type":"Food & Drink"
        }
    ],
    "sg:phone":"+1 718 206 0040",
    "sg:postcode":"11435",
    "sg:province":"NY",
    "sg:tags":[
        "pizza"
    ],
    "wof:name":"Sutphin Pizza",
    "wof:placetype":"venue"
},
  "geometry": {"coordinates":[-73.802013,40.694306],"type":"Point"}
}