{
  "type": "Feature",
  "properties": {
    "iso:country":"US",
    "sg:address":"51 Neptune Ave",
    "sg:city":"Brooklyn",
    "sg:classifiers":[
        {
            "category":"Food & Beverages",
            "subcategory":"Groceries & Convenience Stores",
            "type":"Retail Goods"
        }
    ],
    "sg:phone":"+1 718 648 7080",
    "sg:postcode":"11235",
    "sg:province":"NY",
    "sg:tags":[
        "print",
        "medium"
    ],
    "wof:name":"Shop & Smile",
    "wof:placetype":"venue"
},
  "geometry": {"coordinates":[-73.95590199999999,40.582802],"type":"Point"}
}