{
  "type": "Feature",
  "properties": {
    "addr:full":"308 Old Farm Rd Riverhead NY 11901",
    "addr:housenumber":"308",
    "addr:postcode":"11901",
    "addr:street":"Old Farm Rd",
    "iso:country":"US",
    "sg:address":"308 Old Farm Rd",
    "sg:city":"Riverhead",
    "sg:classifiers":[
        {
            "category":"Building & Trades",
            "subcategory":"Construction",
            "type":"Services"
        }
    ],
    "sg:phone":"+1 631 369 5747",
    "sg:postcode":"11901",
    "sg:province":"NY",
    "sg:tags":[
        "contractor"
    ],
    "wof:name":"K-Man Construction",
    "wof:placetype":"venue"
},
  "geometry": {"coordinates":[-72.67041399999999,40.948355],"type":"Point"}
}