{
  "type": "Feature",
  "properties": {
    "addr:full":"225 W 35 St New York NY 10001",
    "addr:housenumber":"225",
    "addr:postcode":"10001",
    "addr:street":"W 35 St",
    "iso:country":"US",
    "sg:address":"225 W 35 St",
    "sg:city":"New York",
    "sg:classifiers":[
        {
            "category":"Banks & Credit Unions",
            "subcategory":"Bank",
            "type":"Services"
        }
    ],
    "sg:phone":"+1 212 244 2600",
    "sg:postcode":"10001",
    "sg:province":"NY",
    "sg:tags":[
        "term",
        "short",
        "factoring",
        "business",
        "institution"
    ],
    "wof:name":"Hilldun Corporation",
    "wof:placetype":"venue"
},
  "geometry": {"coordinates":[-73.992414,40.752627],"type":"Point"}
}