{
  "type": "Feature",
  "properties": {
    "addr:full":"20 Claremont Dr Voorheesville NY 12186",
    "addr:housenumber":"20",
    "addr:postcode":"12186",
    "addr:street":"Claremont Dr",
    "iso:country":"US",
    "sg:address":"20 Claremont Dr",
    "sg:city":"Voorheesville",
    "sg:classifiers":[
        {
            "category":"Museum",
            "type":"Entertainment"
        }
    ],
    "sg:phone":"+1   ",
    "sg:postcode":"12186",
    "sg:province":"NY",
    "sg:tags":[
        "art",
        "gallery"
    ],
    "wof:name":"Pelletier Galleries Inc",
    "wof:placetype":"venue"
},
  "geometry": {"coordinates":[-73.948517,42.650809],"type":"Point"}
}