{
  "type": "Feature",
  "properties": {
    "iso:country":"US",
    "sg:address":"3841 Sheldon Rd",
    "sg:city":"Orchard Park",
    "sg:classifiers":[
        {
            "category":"Professional",
            "subcategory":"Testing Lab",
            "type":"Services"
        }
    ],
    "sg:phone":"+1 716 649 7960",
    "sg:postcode":"14127",
    "sg:province":"NY",
    "sg:tags":[
        "laboratory"
    ],
    "wof:name":"Mc Andrew Lab Inc",
    "wof:placetype":"venue"
},
  "geometry": {"coordinates":[-78.79586999999999,42.777747],"type":"Point"}
}