{
  "type": "Feature",
  "properties": {
    "addr:full":"126 Schneider Ln Hauppauge NY 11788",
    "addr:housenumber":"126",
    "addr:postcode":"11788",
    "addr:street":"Schneider Ln",
    "iso:country":"US",
    "sg:address":"126 Schneider Ln",
    "sg:city":"Hauppauge",
    "sg:classifiers":[
        {
            "category":"Home & Garden",
            "subcategory":"Carpets & Floor Coverings",
            "type":"Retail Goods"
        }
    ],
    "sg:phone":"+1   ",
    "sg:postcode":"11788",
    "sg:province":"NY",
    "wof:name":"Wooleys Carpet Workroom",
    "wof:placetype":"venue"
},
  "geometry": {"coordinates":[-73.21102999999999,40.810294],"type":"Point"}
}