{
  "type": "Feature",
  "properties": {
    "addr:full":"493 Western Hwy Blauvelt NY 10913",
    "addr:housenumber":"493",
    "addr:postcode":"10913",
    "addr:street":"Western Hwy",
    "iso:country":"US",
    "sg:address":"493 Western Hwy",
    "sg:city":"Blauvelt",
    "sg:classifiers":[
        {
            "category":"Wholesale",
            "subcategory":"Books, Periodicals, & Newspapers",
            "type":"Manufacturing & Wholesale Goods"
        }
    ],
    "sg:phone":"+1 845 680 0353",
    "sg:postcode":"10913",
    "sg:province":"NY",
    "sg:tags":[
        "dealer"
    ],
    "wof:name":"Bookstore At Dominican College",
    "wof:placetype":"venue"
},
  "geometry": {"coordinates":[-73.96182399999999,41.082336],"type":"Point"}
}