{
  "type": "Feature",
  "properties": {
    "iso:country":"US",
    "sg:address":"24 Pheasant Hill Ln",
    "sg:city":"Glen Head",
    "sg:classifiers":[
        {
            "category":"Real Estate",
            "subcategory":"Architect",
            "type":"Services"
        }
    ],
    "sg:phone":"+1   ",
    "sg:postcode":"11545",
    "sg:province":"NY",
    "sg:tags":[
        "architectural"
    ],
    "wof:name":"Cara Mar",
    "wof:placetype":"venue"
},
  "geometry": {"coordinates":[-73.604905,40.83413],"type":"Point"}
}