{
  "type": "Feature",
  "properties": {
    "iso:country":"US",
    "sg:address":"3980 Jerusalem Ave",
    "sg:city":"Seaford",
    "sg:classifiers":[
        {
            "category":"Personal",
            "subcategory":"Beauty Salon",
            "type":"Services"
        }
    ],
    "sg:phone":"+1 516 409 4000",
    "sg:postcode":"11783",
    "sg:province":"NY",
    "sg:tags":[
        "shop"
    ],
    "wof:name":"Fantastic Nails Inc",
    "wof:placetype":"venue"
},
  "geometry": {"coordinates":[-73.48638,40.691076],"type":"Point"}
}