{
  "type": "Feature",
  "properties": {
    "addr:full":"230 W 125th St New York NY 10027",
    "addr:housenumber":"230",
    "addr:postcode":"10027",
    "addr:street":"W 125Th St",
    "iso:country":"US",
    "sg:address":"230 W 125th St",
    "sg:city":"New York",
    "sg:classifiers":[
        {
            "category":"Wholesale",
            "subcategory":"Apparel",
            "type":"Manufacturing & Wholesale Goods"
        }
    ],
    "sg:phone":"+1 212 662 4422",
    "sg:postcode":"10027",
    "sg:province":"NY",
    "sg:tags":[
        "sportswear"
    ],
    "wof:name":"High Energy Boutique Inc",
    "wof:placetype":"venue"
},
  "geometry": {"coordinates":[-73.95054399999999,40.80974],"type":"Point"}
}