{
  "type": "Feature",
  "properties": {
    "addr:website":"http://www.abraconyc.com/",
    "wof:name":"Abra\u00e7o",
    "wof:placetype":"venue"
},
  "geometry": {"coordinates":[-73.98608299999999,40.727017],"type":"Point"}
}