{
  "type": "Feature",
  "properties": {
    "iso:country":"US",
    "sg:address":"2008 Church Ave",
    "sg:city":"Brooklyn",
    "sg:classifiers":[
        {
            "category":"Retail",
            "subcategory":"Repair Shop",
            "type":"Services"
        }
    ],
    "sg:phone":"+1 718 301 7202",
    "sg:postcode":"11226",
    "sg:province":"NY",
    "sg:tags":[
        "lock",
        "locksmith"
    ],
    "wof:name":"24 Hr Emerg A Locksmith",
    "wof:placetype":"venue"
},
  "geometry": {"coordinates":[-73.96002900000001,40.650125],"type":"Point"}
}