{
  "type": "Feature",
  "properties": {
    "iso:country":"US",
    "sg:address":"79 Delaware Rd",
    "sg:city":"Buffalo",
    "sg:classifiers":[
        {
            "category":"Retail",
            "subcategory":"Portrait Studio",
            "type":"Services"
        }
    ],
    "sg:phone":"+1   ",
    "sg:postcode":"14217",
    "sg:province":"NY",
    "sg:tags":[
        "photo"
    ],
    "sg:website":"www.kenwoodphotography.com",
    "wof:name":"Kenwood Photography Studio",
    "wof:placetype":"venue"
},
  "geometry": {"coordinates":[-78.869113,42.963947],"type":"Point"}
}