{
  "type": "Feature",
  "properties": {
    "iso:country":"US",
    "sg:address":"17 Payne Cir",
    "sg:city":"Hewlett",
    "sg:classifiers":[
        {
            "category":"Shopping",
            "subcategory":"Stationery & Office Supplies",
            "type":"Retail Goods"
        }
    ],
    "sg:phone":"+1 516 569 0547",
    "sg:postcode":"11557",
    "sg:province":"NY",
    "sg:tags":[
        "equipment"
    ],
    "wof:name":"Doneger Abraham",
    "wof:placetype":"venue"
},
  "geometry": {"coordinates":[-73.677498,40.638],"type":"Point"}
}