{
  "type": "Feature",
  "properties": {
    "addr:full":"33 Main St East Rockaway NY 11518",
    "addr:housenumber":"33",
    "addr:postcode":"11518",
    "addr:street":"Main St East",
    "iso:country":"US",
    "sg:address":"33 Main St",
    "sg:city":"East Rockaway",
    "sg:classifiers":[
        {
            "category":"Bars & Pubs",
            "type":"Food & Drink"
        }
    ],
    "sg:phone":"+1 516 599 9515",
    "sg:postcode":"11518",
    "sg:province":"NY",
    "wof:name":"East Rockaway Village Tavern",
    "wof:placetype":"venue"
},
  "geometry": {"coordinates":[-73.661205,40.639706],"type":"Point"}
}