{
  "type": "Feature",
  "properties": {
    "addr:full":"27 Hampton Rd Southampton NY 11968",
    "addr:housenumber":"27",
    "addr:postcode":"11968",
    "addr:street":"Hampton Rd",
    "iso:country":"US",
    "sg:address":"27 Hampton Rd",
    "sg:city":"Southampton",
    "sg:classifiers":[
        {
            "category":"Shopping",
            "subcategory":"Florist",
            "type":"Retail Goods"
        }
    ],
    "sg:phone":"+1 631 283 8200",
    "sg:postcode":"11968",
    "sg:province":"NY",
    "wof:name":"Artistry In Flowers",
    "wof:placetype":"venue"
},
  "geometry": {"coordinates":[-72.38901199999999,40.887311],"type":"Point"}
}