{
  "type": "Feature",
  "properties": {
    "iso:country":"US",
    "sg:address":"1425 37th St",
    "sg:city":"Brooklyn",
    "sg:classifiers":[
        {
            "category":"Building & Trades",
            "subcategory":"Construction",
            "type":"Services"
        }
    ],
    "sg:phone":"+1 718 851 2705",
    "sg:postcode":"11218",
    "sg:province":"NY",
    "sg:tags":[
        "contractor"
    ],
    "wof:name":"Creative KJ Contracting Inc",
    "wof:placetype":"venue"
},
  "geometry": {"coordinates":[-73.98227799999999,40.640204],"type":"Point"}
}