{
  "type": "Feature",
  "properties": {
    "addr:full":"70 North Dr Copiague NY 11726",
    "addr:housenumber":"70",
    "addr:postcode":"11726",
    "addr:street":"North Dr",
    "iso:country":"US",
    "sg:address":"70 North Dr",
    "sg:city":"Copiague",
    "sg:classifiers":[
        {
            "category":"Organizations",
            "subcategory":"Religious Organization",
            "type":"Services"
        }
    ],
    "sg:phone":"+1 631 842 9421",
    "sg:postcode":"11726",
    "sg:province":"NY",
    "sg:tags":[
        "spiritualist"
    ],
    "wof:name":"Melissa Miakoda",
    "wof:placetype":"venue"
},
  "geometry": {"coordinates":[-73.39156199999999,40.66574],"type":"Point"}
}