{
  "type": "Feature",
  "properties": {
    "iso:country":"US",
    "sg:address":"95 Catherine St",
    "sg:city":"Beacon",
    "sg:classifiers":[
        {
            "category":"Sports & Exercise",
            "subcategory":"Gym",
            "type":"Entertainment"
        }
    ],
    "sg:phone":"+1 845 838 0134",
    "sg:postcode":"12508",
    "sg:province":"NY",
    "sg:tags":[
        "trainer"
    ],
    "wof:name":"Mid Hudson Family Health Institute",
    "wof:placetype":"venue"
},
  "geometry": {"coordinates":[-73.968002,41.5023],"type":"Point"}
}