{
  "type": "Feature",
  "properties": {
    "addr:full":"34968 Co Rd 194 Antwerp NY 13608",
    "addr:housenumber":"34968",
    "addr:postcode":"13608",
    "addr:street":"Co Rd 194",
    "iso:country":"US",
    "sg:address":"34968 Co Rd 194",
    "sg:city":"Antwerp",
    "sg:classifiers":[
        {
            "category":"Farming",
            "subcategory":"Dairy Farm",
            "type":"Manufacturing & Wholesale Goods"
        }
    ],
    "sg:phone":"+1 315 659 8524",
    "sg:postcode":"13608",
    "sg:province":"NY",
    "wof:name":"Rodger Dimon",
    "wof:placetype":"venue"
},
  "geometry": {"coordinates":[-75.677824,44.206915],"type":"Point"}
}