{
  "type": "Feature",
  "properties": {
    "addr:full":"12 E 33 St New York NY 10016",
    "addr:housenumber":"12;33",
    "addr:postcode":"10016",
    "addr:street":"E;St",
    "iso:country":"US",
    "sg:address":"12 E 33 St",
    "sg:city":"New York",
    "sg:classifiers":[
        {
            "category":"Wholesale",
            "subcategory":"Computers",
            "type":"Manufacturing & Wholesale Goods"
        }
    ],
    "sg:phone":"+1 212 545 7575",
    "sg:postcode":"10016",
    "sg:province":"NY",
    "wof:name":"Connecting Point Multi Media",
    "wof:placetype":"venue"
},
  "geometry": {"coordinates":[-73.983985,40.747313],"type":"Point"}
}