{
  "type": "Feature",
  "properties": {
    "iso:country":"US",
    "sg:address":"165 Rockaway Pkwy",
    "sg:city":"Brooklyn",
    "sg:classifiers":[
        {
            "category":"Shopping",
            "subcategory":"Music",
            "type":"Retail Goods"
        }
    ],
    "sg:phone":"+1   ",
    "sg:postcode":"11212",
    "sg:province":"NY",
    "wof:name":"My Time Records",
    "wof:placetype":"venue"
},
  "geometry": {"coordinates":[-73.92012699999999,40.661123],"type":"Point"}
}