{
  "type": "Feature",
  "properties": {
    "addr:full":"66 Tubby St Kingston NY 12401",
    "addr:housenumber":"66",
    "addr:postcode":"12401",
    "addr:street":"Tubby St",
    "iso:country":"US",
    "sg:address":"66 Tubby St",
    "sg:city":"Kingston",
    "sg:classifiers":[
        {
            "category":"Wholesale",
            "subcategory":"Construction Materials",
            "type":"Manufacturing & Wholesale Goods"
        }
    ],
    "sg:phone":"+1 845 338 2916",
    "sg:postcode":"12401",
    "sg:province":"NY",
    "sg:tags":[
        "fence"
    ],
    "wof:name":"Mertine Fencing",
    "wof:placetype":"venue"
},
  "geometry": {"coordinates":[-73.990103,41.930864],"type":"Point"}
}