{
  "type": "Feature",
  "properties": {
    "addr:full":"88 Canal St Lyons NY 14489",
    "addr:housenumber":"88",
    "addr:postcode":"14489",
    "addr:street":"Canal St",
    "iso:country":"US",
    "sg:address":"88 Canal St",
    "sg:city":"Lyons",
    "sg:classifiers":[
        {
            "category":"Restaurant",
            "type":"Food & Drink"
        }
    ],
    "sg:phone":"+1 315 946 3100",
    "sg:postcode":"14489",
    "sg:province":"NY",
    "wof:name":"Lyons Family Restaurant",
    "wof:placetype":"venue"
},
  "geometry": {"coordinates":[-76.987927,43.064492],"type":"Point"}
}