{
  "type": "Feature",
  "properties": {
    "addr:full":"628 Broadway Manhattan NY 10012",
    "addr:housenumber":"628",
    "addr:postcode":"10012",
    "addr:street":"Broadway",
    "iso:country":"US",
    "sg:address":"628 Broadway",
    "sg:city":"Manhattan",
    "sg:classifiers":[
        {
            "category":"Retail",
            "subcategory":"Event Space",
            "type":"Services"
        }
    ],
    "sg:phone":"+1 646 770 0628",
    "sg:postcode":"10012",
    "sg:province":"NY",
    "sg:tags":[
        "venue"
    ],
    "sg:website":"www.noho628.com/",
    "wof:name":"NoHo 628",
    "wof:placetype":"venue"
},
  "geometry": {"coordinates":[-73.996385,40.725665],"type":"Point"}
}