{
  "type": "Feature",
  "properties": {
    "iso:country":"US",
    "sg:address":"28 Hylan Blvd",
    "sg:city":"Staten Island",
    "sg:classifiers":[
        {
            "category":"Deli",
            "type":"Food & Drink"
        }
    ],
    "sg:phone":"+1 718 984 5758",
    "sg:postcode":"10305",
    "sg:province":"NY",
    "wof:name":"Shields Geo K Dlctsn",
    "wof:placetype":"venue"
},
  "geometry": {"coordinates":[-74.066299,40.613998],"type":"Point"}
}