{
  "type": "Feature",
  "properties": {
    "addr:full":"151 W 25th St New York NY 10001",
    "addr:housenumber":"151",
    "addr:postcode":"10001",
    "addr:street":"W 25Th St",
    "iso:country":"US",
    "sg:address":"151 W 25th St",
    "sg:city":"New York",
    "sg:classifiers":[
        {
            "category":"Communications",
            "type":"Services"
        }
    ],
    "sg:phone":"+1 212 243 3230",
    "sg:postcode":"10001",
    "sg:province":"NY",
    "sg:tags":[
        "recording",
        "rehearsal",
        "studio"
    ],
    "wof:name":"Fast Forward Studios",
    "wof:placetype":"venue"
},
  "geometry": {"coordinates":[-73.99340100000001,40.744801],"type":"Point"}
}