{
  "type": "Feature",
  "properties": {
    "addr:full":"1435 39th Street Brooklyn NY 11218",
    "addr:housenumber":"1435",
    "addr:postcode":"11218",
    "addr:street":"39Th Street",
    "iso:country":"US",
    "sg:address":"1435 39th Street",
    "sg:city":"Brooklyn",
    "sg:classifiers":[
        {
            "category":"Retail",
            "subcategory":"Auto Repair",
            "type":"Services"
        }
    ],
    "sg:phone":"+1 718 633 0080",
    "sg:postcode":"11218",
    "sg:province":"NY",
    "wof:name":"B & T Auto Sales & Repair Shop",
    "wof:placetype":"venue"
},
  "geometry": {"coordinates":[-73.983619,40.639146],"type":"Point"}
}