{
  "type": "Feature",
  "properties": {
    "addr:full":"85 8th Ave Sea Cliff NY 11579",
    "addr:housenumber":"85",
    "addr:postcode":"11579",
    "addr:street":"8Th Ave",
    "iso:country":"US",
    "sg:address":"85 8th Ave",
    "sg:city":"Sea Cliff",
    "sg:classifiers":[
        {
            "category":"Freight",
            "type":"Transportation"
        }
    ],
    "sg:phone":"+1 516 759 4430",
    "sg:postcode":"11579",
    "sg:province":"NY",
    "sg:tags":[
        "commercial",
        "storage"
    ],
    "wof:name":"Red Ball Transit",
    "wof:placetype":"venue"
},
  "geometry": {"coordinates":[-73.639383,40.850929],"type":"Point"}
}