{
  "type": "Feature",
  "properties": {
    "addr:full":"1235 Youngs Ave Southold NY 11971",
    "addr:housenumber":"1235",
    "addr:postcode":"11971",
    "addr:street":"Youngs Ave",
    "iso:country":"US",
    "sg:address":"1235 Youngs Ave",
    "sg:city":"Southold",
    "sg:classifiers":[
        {
            "category":"Sports & Exercise",
            "subcategory":"Gym",
            "type":"Entertainment"
        }
    ],
    "sg:phone":"+1 631 765 9100",
    "sg:postcode":"11971",
    "sg:province":"NY",
    "sg:tags":[
        "spa",
        "health"
    ],
    "wof:name":"Face & Body Spa",
    "wof:placetype":"venue"
},
  "geometry": {"coordinates":[-72.426481,41.065014],"type":"Point"}
}