{
  "type": "Feature",
  "properties": {
    "addr:full":"1958 Victory Blvd Staten Island NY 10314",
    "addr:housenumber":"1958",
    "addr:postcode":"10314",
    "addr:street":"Victory Blvd",
    "iso:country":"US",
    "sg:address":"1958 Victory Blvd",
    "sg:city":"Staten Island",
    "sg:classifiers":[
        {
            "category":"Personal",
            "subcategory":"Beauty Salon",
            "type":"Services"
        }
    ],
    "sg:phone":"+1 718 981 7229",
    "sg:postcode":"10314",
    "sg:province":"NY",
    "sg:tags":[
        "shop"
    ],
    "wof:name":"Ciao Unisex Salon",
    "wof:placetype":"venue"
},
  "geometry": {"coordinates":[-74.128603,40.612563],"type":"Point"}
}