{
  "type": "Feature",
  "properties": {
    "addr:full":"176 Grand St New York NY 10013",
    "addr:housenumber":"176",
    "addr:postcode":"10013",
    "addr:street":"Grand St",
    "iso:country":"US",
    "sg:address":"176 Grand St",
    "sg:city":"New York",
    "sg:classifiers":[
        {
            "category":"Arts & Performance",
            "subcategory":"Theater",
            "type":"Entertainment"
        }
    ],
    "sg:phone":"+1 212 941 8517",
    "sg:postcode":"10013",
    "sg:province":"NY",
    "sg:tags":[
        "production",
        "radio"
    ],
    "wof:name":"Sound Portraits Productions",
    "wof:placetype":"venue"
},
  "geometry": {"coordinates":[-73.997367,40.719435],"type":"Point"}
}