{
  "type": "Feature",
  "properties": {
    "iso:country":"US",
    "sg:address":"6253 Brownsville Rd",
    "sg:city":"Farmington",
    "sg:classifiers":[
        {
            "category":"Building & Trades",
            "subcategory":"Construction",
            "type":"Services"
        }
    ],
    "sg:phone":"+1 585 924 2688",
    "sg:postcode":"14425",
    "sg:province":"NY",
    "sg:tags":[
        "residential",
        "nonresidential"
    ],
    "wof:name":"Flora and Benson Builders",
    "wof:placetype":"venue"
},
  "geometry": {"coordinates":[-77.366906,43.011953],"type":"Point"}
}