{
  "type": "Feature",
  "properties": {
    "addr:full":"1911 George Ct Merrick NY 11566",
    "addr:housenumber":"1911",
    "addr:postcode":"11566",
    "addr:street":"George Ct",
    "iso:country":"US",
    "sg:address":"1911 George Ct",
    "sg:city":"Merrick",
    "sg:classifiers":[
        {
            "category":"Building & Trades",
            "subcategory":"Plumbing",
            "type":"Services"
        }
    ],
    "sg:phone":"+1 516 623 6939",
    "sg:postcode":"11566",
    "sg:province":"NY",
    "sg:tags":[
        "plumbing",
        "contractor"
    ],
    "wof:name":"Bob Phillips Plumbing & Htg",
    "wof:placetype":"venue"
},
  "geometry": {"coordinates":[-73.550354,40.650076],"type":"Point"}
}