{
  "type": "Feature",
  "properties": {
    "addr:full":"2257 Church Avenue Brooklyn NY 11226",
    "addr:housenumber":"2257",
    "addr:postcode":"11226",
    "addr:street":"Church Avenue",
    "iso:country":"US",
    "sg:address":"2257 Church Avenue",
    "sg:city":"Brooklyn",
    "sg:classifiers":[
        {
            "category":"Social Services",
            "subcategory":"Child Care",
            "type":"Services"
        },
        {
            "category":"Education",
            "subcategory":"Preschool",
            "type":"Public Place"
        },
        {
            "category":"Education",
            "subcategory":"School",
            "type":"Public Place"
        }
    ],
    "sg:phone":"+1 718 693 1400",
    "sg:postcode":"11226",
    "sg:province":"NY",
    "sg:tags":[
        "elementary",
        "day"
    ],
    "wof:name":"All American",
    "wof:placetype":"venue"
},
  "geometry": {"coordinates":[-73.957898,40.650545],"type":"Point"}
}