{
  "type": "Feature",
  "properties": {
    "iso:country":"US",
    "sg:address":"132 W Montauk Hwy",
    "sg:city":"Hampton Bays",
    "sg:classifiers":[
        {
            "category":"Personal",
            "subcategory":"Beauty Salon",
            "type":"Services"
        }
    ],
    "sg:phone":"+1 631 728 7776",
    "sg:postcode":"11946",
    "sg:province":"NY",
    "sg:tags":[
        "manicuring"
    ],
    "wof:name":"Cali Nails",
    "wof:placetype":"venue"
},
  "geometry": {"coordinates":[-72.532214,40.876657],"type":"Point"}
}