{
  "type": "Feature",
  "properties": {
    "addr:full":"2545 Hempstead Tpke East Meadow NY 11554",
    "addr:housenumber":"2545",
    "addr:postcode":"11554",
    "addr:street":"Hempstead Tpke",
    "iso:country":"US",
    "sg:address":"2545 Hempstead Tpke",
    "sg:city":"East Meadow",
    "sg:classifiers":[
        {
            "category":"Professional",
            "subcategory":"Accounting & Tax Preparation",
            "type":"Services"
        }
    ],
    "sg:phone":"+1 516 579 2880",
    "sg:postcode":"11554",
    "sg:province":"NY",
    "sg:tags":[
        "accountant"
    ],
    "wof:name":"Neuman Steven CPA",
    "wof:placetype":"venue"
},
  "geometry": {"coordinates":[-73.542297,40.724499],"type":"Point"}
}