{
  "type": "Feature",
  "properties": {
    "addr:full":"604 New York Ave Brooklyn NY 11203",
    "addr:housenumber":"604",
    "addr:postcode":"11203",
    "addr:street":"New York Ave",
    "iso:country":"US",
    "sg:address":"604 New York Ave",
    "sg:city":"Brooklyn",
    "sg:classifiers":[
        {
            "category":"Wholesale",
            "subcategory":"Machinery & Supplies",
            "type":"Manufacturing & Wholesale Goods"
        }
    ],
    "sg:phone":"+1 718 756 5880",
    "sg:postcode":"11203",
    "sg:province":"NY",
    "sg:tags":[
        "equipment",
        "cosmetic",
        "beauty"
    ],
    "wof:name":"Durene Sales",
    "wof:placetype":"venue"
},
  "geometry": {"coordinates":[-73.9478,40.659901],"type":"Point"}
}