{
  "type": "Feature",
  "properties": {
    "addr:full":"615 Soundview Ave Bronx NY 10473",
    "addr:housenumber":"615",
    "addr:postcode":"10473",
    "addr:street":"Soundview Ave",
    "iso:country":"US",
    "sg:address":"615 Soundview Ave",
    "sg:city":"Bronx",
    "sg:classifiers":[
        {
            "category":"Retail",
            "subcategory":"Funeral Services",
            "type":"Services"
        }
    ],
    "sg:phone":"+1 718 589 0877",
    "sg:postcode":"10473",
    "sg:province":"NY",
    "sg:tags":[
        "cemetery"
    ],
    "wof:name":"Ortiz R G Funeral Home Soundview Inc",
    "wof:placetype":"venue"
},
  "geometry": {"coordinates":[-73.862801,40.818001],"type":"Point"}
}