{
  "type": "Feature",
  "properties": {
    "iso:country":"US",
    "sg:address":"210 Mill Rd",
    "sg:city":"Holbrook",
    "sg:classifiers":[
        {
            "category":"Retail",
            "subcategory":"Veterinary Services",
            "type":"Services"
        }
    ],
    "sg:phone":"+1 631 585 4396",
    "sg:postcode":"11741",
    "sg:province":"NY",
    "sg:tags":[
        "veterinarian"
    ],
    "wof:name":"McIntosh Rustin DVM",
    "wof:placetype":"venue"
},
  "geometry": {"coordinates":[-73.08699799999999,40.8223],"type":"Point"}
}