{
  "type": "Feature",
  "properties": {
    "addr:full":"995 Gates Ave Brooklyn NY 11221",
    "addr:housenumber":"995",
    "addr:postcode":"11221",
    "addr:street":"Gates Ave",
    "iso:country":"US",
    "sg:address":"995 Gates Ave",
    "sg:city":"Brooklyn",
    "sg:classifiers":[
        {
            "category":"Restaurant",
            "type":"Food & Drink"
        }
    ],
    "sg:phone":"+1 718 455 2141",
    "sg:postcode":"11221",
    "sg:province":"NY",
    "sg:tags":[
        "caterer"
    ],
    "wof:name":"Peterson's Catering",
    "wof:placetype":"venue"
},
  "geometry": {"coordinates":[-73.925196,40.689167],"type":"Point"}
}