{
  "type": "Feature",
  "properties": {
    "addr:full":"3574 Broadway New York NY 10031",
    "addr:housenumber":"3574",
    "addr:postcode":"10031",
    "addr:street":"Broadway",
    "iso:country":"US",
    "sg:address":"3574 Broadway",
    "sg:city":"New York",
    "sg:classifiers":[
        {
            "category":"Personal",
            "subcategory":"Beauty Salon",
            "type":"Services"
        }
    ],
    "sg:phone":"+1 212 926 1903",
    "sg:postcode":"10031",
    "sg:province":"NY",
    "sg:tags":[
        "shop"
    ],
    "wof:name":"Carmens Beauty Salon",
    "wof:placetype":"venue"
},
  "geometry": {"coordinates":[-73.94970600000001,40.827206],"type":"Point"}
}