{
  "type": "Feature",
  "properties": {
    "addr:full":"1420 Main St Buffalo NY 14209",
    "addr:housenumber":"1420",
    "addr:postcode":"14209",
    "addr:street":"Main St",
    "iso:country":"US",
    "sg:address":"1420 Main St",
    "sg:city":"Buffalo",
    "sg:classifiers":[
        {
            "category":"Communications",
            "subcategory":"Radio Station",
            "type":"Services"
        }
    ],
    "sg:phone":"+1 716 783 7522",
    "sg:postcode":"14209",
    "sg:province":"NY",
    "wof:name":"WHLD-AM 1270 Totally Gospel",
    "wof:placetype":"venue"
},
  "geometry": {"coordinates":[-78.865707,42.912416],"type":"Point"}
}