{
  "type": "Feature",
  "properties": {
    "addr:full":"12 Pine Rd Valhalla NY 10595",
    "addr:housenumber":"12",
    "addr:postcode":"10595",
    "addr:street":"Pine Rd",
    "iso:country":"US",
    "sg:address":"12 Pine Rd",
    "sg:city":"Valhalla",
    "sg:classifiers":[
        {
            "category":"Organizations",
            "subcategory":"Religious Organization",
            "type":"Services"
        }
    ],
    "sg:phone":"+1 914 428 7292",
    "sg:postcode":"10595",
    "sg:province":"NY",
    "sg:tags":[
        "clergy"
    ],
    "wof:name":"Norman A Andre",
    "wof:placetype":"venue"
},
  "geometry": {"coordinates":[-73.763057,41.09714],"type":"Point"}
}