{
  "type": "Feature",
  "properties": {
    "iso:country":"US",
    "sg:address":"214 Court St",
    "sg:city":"Brooklyn",
    "sg:classifiers":[
        {
            "category":"Restaurant",
            "type":"Food & Drink"
        },
        {
            "category":"Food & Beverages",
            "subcategory":"Bakery",
            "type":"Retail Goods"
        }
    ],
    "sg:phone":"+1 718 624 2361",
    "sg:postcode":"11201",
    "sg:province":"NY",
    "sg:tags":[
        "sandwich",
        "pizza"
    ],
    "sg:website":"www.laylajones.com",
    "wof:name":"Layla Jones",
    "wof:placetype":"venue"
},
  "geometry": {"coordinates":[-73.99383,40.686664],"type":"Point"}
}