{
  "type": "Feature",
  "properties": {
    "addr:full":"2636 Nostrand Ave Brooklyn NY 11210",
    "addr:housenumber":"2636",
    "addr:postcode":"11210",
    "addr:street":"Nostrand Ave",
    "iso:country":"US",
    "sg:address":"2636 Nostrand Ave",
    "sg:city":"Brooklyn",
    "sg:classifiers":[
        {
            "category":"Banks & Credit Unions",
            "subcategory":"Financial Services",
            "type":"Services"
        }
    ],
    "sg:phone":"+1 718 377 2053",
    "sg:postcode":"11210",
    "sg:province":"NY",
    "sg:tags":[
        "broker",
        "mortgage"
    ],
    "wof:name":"Meridian Residental Group",
    "wof:placetype":"venue"
},
  "geometry": {"coordinates":[-73.94609800000001,40.622002],"type":"Point"}
}