{
  "type": "Feature",
  "properties": {
    "addr:full":"672 E 180th Street Bronx NY 10457",
    "addr:housenumber":"672",
    "addr:postcode":"10457",
    "addr:street":"E 180Th Street",
    "iso:country":"US",
    "sg:address":"672 E 180th Street",
    "sg:city":"Bronx",
    "sg:classifiers":[
        {
            "category":"Retail",
            "subcategory":"Auto Repair",
            "type":"Services"
        }
    ],
    "sg:phone":"+1 718 364 7200",
    "sg:postcode":"10457",
    "sg:province":"NY",
    "wof:name":"Frank's Auto Electric Svc",
    "wof:placetype":"venue"
},
  "geometry": {"coordinates":[-73.88945099999999,40.848436],"type":"Point"}
}