{
  "type": "Feature",
  "properties": {
    "iso:country":"US",
    "sg:address":"264 Ontario St",
    "sg:city":"Buffalo",
    "sg:classifiers":[
        {
            "category":"Health Services",
            "subcategory":"Chiropractor",
            "type":"Services"
        }
    ],
    "sg:phone":"+1 716 873 3013",
    "sg:postcode":"14207",
    "sg:province":"NY",
    "wof:name":"Horvath Julius P DC PC",
    "wof:placetype":"venue"
},
  "geometry": {"coordinates":[-78.901901,42.951599],"type":"Point"}
}