{
  "type": "Feature",
  "properties": {
    "addr:full":"344 W 49 St New York NY 10019",
    "addr:housenumber":"344",
    "addr:postcode":"10019",
    "addr:street":"W 49 St",
    "iso:country":"US",
    "sg:address":"344 W 49 St",
    "sg:city":"New York",
    "sg:classifiers":[
        {
            "category":"Arts & Performance",
            "subcategory":"Theater",
            "type":"Entertainment"
        }
    ],
    "sg:phone":"+1 212 586 7425",
    "sg:postcode":"10019",
    "sg:province":"NY",
    "sg:tags":[
        "entertainer",
        "business"
    ],
    "sg:website":"www.familydisco.com",
    "wof:name":"Family Disco",
    "wof:placetype":"venue"
},
  "geometry": {"coordinates":[-73.988472,40.762255],"type":"Point"}
}