{
  "type": "Feature",
  "properties": {
    "iso:country":"US",
    "sg:address":"231 S Middletown Rd",
    "sg:city":"Nanuet",
    "sg:classifiers":[
        {
            "category":"Communications",
            "subcategory":"Film & Video Production",
            "type":"Services"
        }
    ],
    "sg:phone":"+1 845 623 6149",
    "sg:postcode":"10954",
    "sg:province":"NY",
    "sg:tags":[
        "editing",
        "tape"
    ],
    "wof:name":"Top Of The Line Entertainment",
    "wof:placetype":"venue"
},
  "geometry": {"coordinates":[-74.015666,41.085419],"type":"Point"}
}