{
  "type": "Feature",
  "properties": {
    "addr:full":"142 Mineola Blvd Mineola NY 11501",
    "addr:housenumber":"142",
    "addr:postcode":"11501",
    "addr:street":"Mineola Blvd",
    "iso:country":"US",
    "sg:address":"142 Mineola Blvd",
    "sg:city":"Mineola",
    "sg:classifiers":[
        {
            "category":"Personal",
            "type":"Services"
        }
    ],
    "sg:phone":"+1 516 739 3891",
    "sg:postcode":"11501",
    "sg:province":"NY",
    "sg:tags":[
        "dating"
    ],
    "wof:name":"Together",
    "wof:placetype":"venue"
},
  "geometry": {"coordinates":[-73.640669,40.74262],"type":"Point"}
}