{
  "type": "Feature",
  "properties": {
    "addr:full":"109-33 71st Rd Forest Hills NY 11375",
    "addr:housenumber":"109-33",
    "addr:postcode":"11375",
    "addr:street":"71St Rd",
    "iso:country":"US",
    "sg:address":"109-33 71st Rd",
    "sg:city":"Forest Hills",
    "sg:classifiers":[
        {
            "category":"Health Services",
            "subcategory":"Doctor",
            "type":"Services"
        }
    ],
    "sg:phone":"+1 718 690 9533",
    "sg:postcode":"11375",
    "sg:province":"NY",
    "sg:website":"www.charlesckleinbergmd.com/",
    "wof:name":"Charles C Kleinberg MD",
    "wof:placetype":"venue"
},
  "geometry": {"coordinates":[-73.841939,40.721661],"type":"Point"}
}