{
  "type": "Feature",
  "properties": {
    "addr:full":"1515 Youngs Ave Southold NY 11971",
    "addr:housenumber":"1515",
    "addr:postcode":"11971",
    "addr:street":"Youngs Ave",
    "iso:country":"US",
    "sg:address":"1515 Youngs Ave",
    "sg:city":"Southold",
    "sg:classifiers":[
        {
            "category":"Professional",
            "type":"Services"
        }
    ],
    "sg:phone":"+1 631 765 4760",
    "sg:postcode":"11971",
    "sg:province":"NY",
    "sg:tags":[
        "water",
        "analysis"
    ],
    "wof:name":"Peconic Waters Corp",
    "wof:placetype":"venue"
},
  "geometry": {"coordinates":[-72.426816,41.065625],"type":"Point"}
}