{
  "type": "Feature",
  "properties": {
    "iso:country":"US",
    "sg:address":"7 Ripley Rd",
    "sg:city":"Camden",
    "sg:classifiers":[
        {
            "category":"Retail",
            "subcategory":"Repair Shop",
            "type":"Services"
        }
    ],
    "sg:phone":"+1 315 245 3332",
    "sg:postcode":"13316",
    "sg:province":"NY",
    "sg:tags":[
        "appliance"
    ],
    "wof:name":"One Day At A Time",
    "wof:placetype":"venue"
},
  "geometry": {"coordinates":[-75.740904,43.330667],"type":"Point"}
}