{
  "type": "Feature",
  "properties": {
    "addr:full":"57 College Pl Yonkers NY 10704",
    "addr:housenumber":"57",
    "addr:postcode":"10704",
    "addr:street":"College Pl",
    "iso:country":"US",
    "sg:address":"57 College Pl",
    "sg:city":"Yonkers",
    "sg:classifiers":[
        {
            "category":"Building & Trades",
            "subcategory":"Plumbing",
            "type":"Services"
        }
    ],
    "sg:phone":"+1 914 423 2729",
    "sg:postcode":"10704",
    "sg:province":"NY",
    "sg:tags":[
        "contractor"
    ],
    "wof:name":"Irrigation By Michael",
    "wof:placetype":"venue"
},
  "geometry": {"coordinates":[-73.85951,40.935139],"type":"Point"}
}