{
  "type": "Feature",
  "properties": {
    "addr:full":"36 Carlough Rd Bohemia NY 11716",
    "addr:housenumber":"36",
    "addr:postcode":"11716",
    "addr:street":"Carlough Rd",
    "iso:country":"US",
    "sg:address":"36 Carlough Rd",
    "sg:city":"Bohemia",
    "sg:classifiers":[
        {
            "category":"Wholesale",
            "subcategory":"Motor Vehicles",
            "type":"Manufacturing & Wholesale Goods"
        }
    ],
    "sg:phone":"+1 631 567 7500",
    "sg:postcode":"11716",
    "sg:province":"NY",
    "sg:tags":[
        "automobile",
        "truck",
        "broker"
    ],
    "wof:name":"Coach Industries Group",
    "wof:placetype":"venue"
},
  "geometry": {"coordinates":[-73.09244700000001,40.773822],"type":"Point"}
}