{
  "type": "Feature",
  "properties": {
    "addr:full":"325 West St Canandaigua NY 14424",
    "addr:housenumber":"325",
    "addr:postcode":"14424",
    "addr:street":"West St",
    "iso:country":"US",
    "sg:address":"325 West St",
    "sg:city":"Canandaigua",
    "sg:classifiers":[
        {
            "category":"Health Services",
            "subcategory":"Doctor",
            "type":"Services"
        }
    ],
    "sg:phone":"+1 585 394 2020",
    "sg:postcode":"14424",
    "sg:province":"NY",
    "sg:tags":[
        "eye",
        "center",
        "care"
    ],
    "wof:name":"Eye Care Center",
    "wof:placetype":"venue"
},
  "geometry": {"coordinates":[-77.29270099999999,42.875722],"type":"Point"}
}