{
  "type": "Feature",
  "properties": {
    "addr:full":"325 Kyserike Rd High Falls NY 12440",
    "addr:housenumber":"325",
    "addr:postcode":"12440",
    "addr:street":"Kyserike Rd",
    "iso:country":"US",
    "sg:address":"325 Kyserike Rd",
    "sg:city":"High Falls",
    "sg:classifiers":[
        {
            "category":"Building & Trades",
            "subcategory":"Construction",
            "type":"Services"
        }
    ],
    "sg:phone":"+1 845 687 0030",
    "sg:postcode":"12440",
    "sg:province":"NY",
    "sg:tags":[
        "excavating",
        "contractor"
    ],
    "wof:name":"Robert Lapp Excavating",
    "wof:placetype":"venue"
},
  "geometry": {"coordinates":[-74.18615800000001,41.812028],"type":"Point"}
}