{
  "type": "Feature",
  "properties": {
    "iso:country":"US",
    "sg:address":"1661 Boone Ave",
    "sg:city":"Bronx",
    "sg:classifiers":[
        {
            "category":"Retail",
            "subcategory":"Auto Repair",
            "type":"Services"
        }
    ],
    "sg:phone":"+1 718 991 4041",
    "sg:postcode":"10460",
    "sg:province":"NY",
    "wof:name":"Diaz Pablo",
    "wof:placetype":"venue"
},
  "geometry": {"coordinates":[-73.884399,40.834499],"type":"Point"}
}