{
  "type": "Feature",
  "properties": {
    "iso:country":"US",
    "sg:address":"233 W 54 St",
    "sg:city":"New York",
    "sg:classifiers":[
        {
            "category":"Shopping",
            "subcategory":"Computers & Home Electronics",
            "type":"Retail Goods"
        }
    ],
    "sg:phone":"+1 212 333 3033",
    "sg:postcode":"10019",
    "sg:province":"NY",
    "sg:tags":[
        "publishing"
    ],
    "sg:website":"www.gutprint.com",
    "wof:name":"Gutenberg Printing",
    "wof:placetype":"venue"
},
  "geometry": {"coordinates":[-73.984205,40.764835],"type":"Point"}
}