{
  "type": "Feature",
  "properties": {
    "addr:full":"4881 Tellier Rd Newark NY 14513",
    "addr:housenumber":"4881",
    "addr:postcode":"14513",
    "addr:street":"Tellier Rd",
    "iso:country":"US",
    "sg:address":"4881 Tellier Rd",
    "sg:city":"Newark",
    "sg:classifiers":[
        {
            "category":"Organizations",
            "subcategory":"Religious Organization",
            "type":"Services"
        }
    ],
    "sg:phone":"+1   ",
    "sg:postcode":"14513",
    "sg:province":"NY",
    "wof:name":"Seventh Day Adventist Church",
    "wof:placetype":"venue"
},
  "geometry": {"coordinates":[-77.148545,43.084591],"type":"Point"}
}