{
  "type": "Feature",
  "properties": {
    "addr:full":"326 S Ocean Ave Patchogue NY 11772",
    "addr:housenumber":"326",
    "addr:postcode":"11772",
    "addr:street":"S Ocean Ave",
    "iso:country":"US",
    "sg:address":"326 S Ocean Ave",
    "sg:city":"Patchogue",
    "sg:classifiers":[
        {
            "category":"Autos & Motor Vehicles",
            "subcategory":"Boat Sales",
            "type":"Retail Goods"
        }
    ],
    "sg:phone":"+1 631 654 0406",
    "sg:postcode":"11772",
    "sg:province":"NY",
    "sg:tags":[
        "equipment",
        "marine",
        "supply"
    ],
    "wof:name":"Whitworth Marine Svc",
    "wof:placetype":"venue"
},
  "geometry": {"coordinates":[-73.01183399999999,40.758285],"type":"Point"}
}