{
  "type": "Feature",
  "properties": {
    "addr:full":"27 Cloverdale Dr Oakdale NY 11769",
    "addr:housenumber":"27",
    "addr:postcode":"11769",
    "addr:street":"Cloverdale Dr",
    "iso:country":"US",
    "sg:address":"27 Cloverdale Dr",
    "sg:city":"Oakdale",
    "sg:classifiers":[
        {
            "category":"Building & Trades",
            "subcategory":"Landscaping Services",
            "type":"Services"
        }
    ],
    "sg:phone":"+1 631 567 7064",
    "sg:postcode":"11769",
    "sg:province":"NY",
    "sg:tags":[
        "landscape",
        "contractor"
    ],
    "wof:name":"Art Of Nature Landscaping",
    "wof:placetype":"venue"
},
  "geometry": {"coordinates":[-73.116529,40.749307],"type":"Point"}
}