{
  "type": "Feature",
  "properties": {
    "iso:country":"US",
    "sg:address":"308 N Comrie Ave",
    "sg:city":"Johnstown",
    "sg:classifiers":[
        {
            "category":"Travel",
            "subcategory":"Hotels & Motels",
            "type":"Entertainment"
        },
        {
            "category":"Retail",
            "subcategory":"Event Space",
            "type":"Services"
        },
        {
            "category":"Travel",
            "subcategory":"Resort",
            "type":"Entertainment"
        }
    ],
    "sg:phone":"+1 800 345 8082",
    "sg:postcode":"12095",
    "sg:province":"NY",
    "sg:tags":[
        "facility",
        "banquet",
        "reception",
        "lodging",
        "corporate",
        "hall"
    ],
    "sg:website":"http://ad.doubleclick.net/clk;223371278;47096201;d?http://www.holidayinn.com/redirect?path=hd&brandCode=hi&hotelCode=jntny&_PMID=99601036&cm_mmc=mdpr-_-yellowpages-_-hi-_-jntny",
    "wof:name":"Holiday Inn Johnstown-Gloversville",
    "wof:placetype":"venue"
},
  "geometry": {"coordinates":[-74.361891,43.020755],"type":"Point"}
}