{
  "type": "Feature",
  "properties": {
    "addr:full":"2643 Genesee St Utica NY 13501",
    "addr:housenumber":"2643",
    "addr:postcode":"13501",
    "addr:street":"Genesee St",
    "iso:country":"US",
    "sg:address":"2643 Genesee St",
    "sg:city":"Utica",
    "sg:classifiers":[
        {
            "category":"Insurance",
            "subcategory":"Insurance Agent",
            "type":"Services"
        },
        {
            "category":"Insurance",
            "subcategory":"Hazard Insurance",
            "type":"Services"
        },
        {
            "category":"Insurance",
            "subcategory":"Title Insurance",
            "type":"Services"
        },
        {
            "category":"Insurance",
            "subcategory":"Life Insurance",
            "type":"Services"
        }
    ],
    "sg:phone":"+1 315 793 0070",
    "sg:postcode":"13501",
    "sg:province":"NY",
    "sg:tags":[
        "business",
        "auto",
        "commercial",
        "homeowner",
        "motorcycle",
        "renter"
    ],
    "wof:name":"Allstate Insurance Company - Frank Boden",
    "wof:placetype":"venue"
},
  "geometry": {"coordinates":[-75.280039,43.077189],"type":"Point"}
}