{
  "type": "Feature",
  "properties": {
    "addr:full":"121 Wellington Ct Staten Island NY 10314",
    "addr:housenumber":"121",
    "addr:postcode":"10314",
    "addr:street":"Wellington Ct",
    "iso:country":"US",
    "sg:address":"121 Wellington Ct",
    "sg:city":"Staten Island",
    "sg:classifiers":[
        {
            "category":"Building & Trades",
            "subcategory":"Construction",
            "type":"Services"
        }
    ],
    "sg:phone":"+1 718 761 0123",
    "sg:postcode":"10314",
    "sg:province":"NY",
    "sg:tags":[
        "house"
    ],
    "wof:name":"SL Building Corp",
    "wof:placetype":"venue"
},
  "geometry": {"coordinates":[-74.15823399999999,40.579695],"type":"Point"}
}