{
  "type": "Feature",
  "properties": {
    "addr:full":"670 Broadway Rm 300 New York NY 10012",
    "addr:housenumber":"670;300",
    "addr:postcode":"10012",
    "addr:street":"Broadway Rm",
    "iso:country":"US",
    "sg:address":"670 Broadway Rm 300",
    "sg:city":"New York",
    "sg:classifiers":[
        {
            "category":"Communications",
            "type":"Services"
        }
    ],
    "sg:phone":"+1 212 217 1605",
    "sg:postcode":"10012",
    "sg:province":"NY",
    "sg:tags":[
        "web",
        "design"
    ],
    "wof:name":"9Mmedia",
    "wof:placetype":"venue"
},
  "geometry": {"coordinates":[-73.99536000000001,40.727121],"type":"Point"}
}