{
  "type": "Feature",
  "properties": {
    "addr:full":"1058 Morris Park Ave Bronx NY 10461",
    "addr:housenumber":"1058",
    "addr:postcode":"10461",
    "addr:street":"Morris Park Ave",
    "iso:country":"US",
    "sg:address":"1058 Morris Park Ave",
    "sg:city":"Bronx",
    "sg:classifiers":[
        {
            "category":"Personal",
            "subcategory":"Barber",
            "type":"Services"
        }
    ],
    "sg:phone":"+1 718 822 8790",
    "sg:postcode":"10461",
    "sg:province":"NY",
    "wof:name":"Carmen & John's Hair Stylist For Men",
    "wof:placetype":"venue"
},
  "geometry": {"coordinates":[-73.854202,40.8489],"type":"Point"}
}