{
  "type": "Feature",
  "properties": {
    "iso:country":"US",
    "sg:address":"23 Scouting Blvd Unit C",
    "sg:city":"Medford",
    "sg:classifiers":[
        {
            "category":"Manufacturing",
            "subcategory":"Tools & Machinery",
            "type":"Manufacturing & Wholesale Goods"
        },
        {
            "category":"Retail",
            "subcategory":"Repair Shop",
            "type":"Services"
        },
        {
            "category":"Retail",
            "subcategory":"Auto Repair",
            "type":"Services"
        }
    ],
    "sg:phone":"+1 631 924 7063",
    "sg:postcode":"11763",
    "sg:province":"NY",
    "sg:tags":[
        "machine",
        "automobile",
        "machinery-rebuild"
    ],
    "wof:name":"E F J Industry Inc",
    "wof:placetype":"venue"
},
  "geometry": {"coordinates":[-72.9598,40.811045],"type":"Point"}
}