{
  "type": "Feature",
  "properties": {
    "addr:full":"700 Burnside Ave Inwood NY 11096",
    "addr:housenumber":"700",
    "addr:postcode":"11096",
    "addr:street":"Burnside Ave",
    "iso:country":"US",
    "sg:address":"700 Burnside Ave",
    "sg:city":"Inwood",
    "sg:classifiers":[
        {
            "category":"Manufacturing",
            "subcategory":"Tools & Machinery",
            "type":"Manufacturing & Wholesale Goods"
        }
    ],
    "sg:phone":"+1   ",
    "sg:postcode":"11096",
    "sg:province":"NY",
    "sg:tags":[
        "machine",
        "industrial",
        "accessory",
        "mfg"
    ],
    "wof:name":"Hollinde Machine & Tool Inc",
    "wof:placetype":"venue"
},
  "geometry": {"coordinates":[-73.739105,40.62318],"type":"Point"}
}