{
  "type": "Feature",
  "properties": {
    "addr:full":"3 Neptune Rd Poughkeepsie NY 12601",
    "addr:housenumber":"3",
    "addr:postcode":"12601",
    "addr:street":"Neptune Rd",
    "iso:country":"US",
    "sg:address":"3 Neptune Rd",
    "sg:city":"Poughkeepsie",
    "sg:classifiers":[
        {
            "category":"Building & Trades",
            "subcategory":"Landscaping Services",
            "type":"Services"
        }
    ],
    "sg:phone":"+1 914 238 5333",
    "sg:postcode":"12601",
    "sg:province":"NY",
    "sg:tags":[
        "landscape",
        "contractor"
    ],
    "wof:name":"Red Leaf Landscaping",
    "wof:placetype":"venue"
},
  "geometry": {"coordinates":[-73.92522200000001,41.643025],"type":"Point"}
}