{
  "type": "Feature",
  "properties": {
    "iso:country":"US",
    "sg:address":"246 W 35 St",
    "sg:city":"New York",
    "sg:classifiers":[
        {
            "category":"Wholesale",
            "subcategory":"Apparel",
            "type":"Manufacturing & Wholesale Goods"
        }
    ],
    "sg:phone":"+1 212 643 9691",
    "sg:postcode":"10001",
    "sg:province":"NY",
    "sg:tags":[
        "clothing"
    ],
    "wof:name":"Munchies Of Hong Kong",
    "wof:placetype":"venue"
},
  "geometry": {"coordinates":[-73.992003,40.752227],"type":"Point"}
}