{
  "type": "Feature",
  "properties": {
    "iso:country":"US",
    "sg:address":"21 Pine Aire Dr",
    "sg:city":"Bay Shore",
    "sg:classifiers":[
        {
            "category":"Organizations",
            "subcategory":"Community Association",
            "type":"Services"
        }
    ],
    "sg:phone":"+1   ",
    "sg:postcode":"11706",
    "sg:province":"NY",
    "sg:tags":[
        "refuse",
        "system"
    ],
    "wof:name":"Environmental Products",
    "wof:placetype":"venue"
},
  "geometry": {"coordinates":[-73.261889,40.776149],"type":"Point"}
}