{
  "type": "Feature",
  "properties": {
    "iso:country":"US",
    "sg:address":"961 E 174th St",
    "sg:city":"Bronx",
    "sg:classifiers":[
        {
            "category":"Health Services",
            "subcategory":"Health Practitioner",
            "type":"Services"
        }
    ],
    "sg:phone":"+1 347 271 3777",
    "sg:postcode":"10460",
    "sg:province":"NY",
    "sg:tags":[
        "therapy",
        "physical"
    ],
    "wof:name":"Ss Medical Care Pc",
    "wof:placetype":"venue"
},
  "geometry": {"coordinates":[-73.88590000000001,40.836909],"type":"Point"}
}