{
  "type": "Feature",
  "properties": {
    "iso:country":"US",
    "sg:address":"8 Propose Rd",
    "sg:city":"Shirley",
    "sg:classifiers":[
        {
            "category":"Building & Trades",
            "subcategory":"Construction",
            "type":"Services"
        }
    ],
    "sg:phone":"+1 631 399 8229",
    "sg:postcode":"11967",
    "sg:province":"NY",
    "sg:tags":[
        "carpentry",
        "contractor"
    ],
    "wof:name":"Frenchman Carpentry",
    "wof:placetype":"venue"
},
  "geometry": {"coordinates":[-72.876768,40.786125],"type":"Point"}
}