{
  "type": "Feature",
  "properties": {
    "addr:full":"601 Wolf St Syracuse NY 13208",
    "addr:housenumber":"601",
    "addr:postcode":"13208",
    "addr:street":"Wolf St",
    "iso:country":"US",
    "sg:address":"601 Wolf St",
    "sg:city":"Syracuse",
    "sg:classifiers":[
        {
            "category":"Shopping",
            "subcategory":"Jewelry",
            "type":"Retail Goods"
        }
    ],
    "sg:phone":"+1 315 475 0622",
    "sg:postcode":"13208",
    "sg:province":"NY",
    "sg:tags":[
        "jeweler"
    ],
    "wof:name":"Dundeal",
    "wof:placetype":"venue"
},
  "geometry": {"coordinates":[-76.160866,43.07571],"type":"Point"}
}