{
  "type": "Feature",
  "properties": {
    "addr:full":"182 E 95 St New York NY 10128",
    "addr:housenumber":"182;95",
    "addr:postcode":"10128",
    "addr:street":"E;St",
    "iso:country":"US",
    "sg:address":"182 E 95 St",
    "sg:city":"New York",
    "sg:classifiers":[
        {
            "category":"Parking",
            "type":"Transportation"
        }
    ],
    "sg:phone":"+1   ",
    "sg:postcode":"10128",
    "sg:province":"NY",
    "sg:tags":[
        "automobile"
    ],
    "wof:name":"Gallant Parking Corp",
    "wof:placetype":"venue"
},
  "geometry": {"coordinates":[-73.950588,40.784855],"type":"Point"}
}