{
  "type": "Feature",
  "properties": {
    "iso:country":"US",
    "sg:address":"242 Merrick Rd",
    "sg:city":"Rockville Centre",
    "sg:classifiers":[
        {
            "category":"Health Services",
            "subcategory":"Doctor",
            "type":"Services"
        }
    ],
    "sg:phone":"+1 516 764 7070",
    "sg:postcode":"11570",
    "sg:province":"NY",
    "sg:tags":[
        "specializing",
        "physician",
        "surgeon",
        "medical"
    ],
    "wof:name":"Island Renal Physicians PC",
    "wof:placetype":"venue"
},
  "geometry": {"coordinates":[-73.64603099999999,40.656195],"type":"Point"}
}