{
  "type": "Feature",
  "properties": {
    "addr:full":"9 Ohara Rd Tonawanda NY 14150",
    "addr:housenumber":"9",
    "addr:postcode":"14150",
    "addr:street":"Ohara Rd",
    "iso:country":"US",
    "sg:address":"9 Ohara Rd",
    "sg:city":"Tonawanda",
    "sg:classifiers":[
        {
            "category":"Organizations",
            "subcategory":"Religious Organization",
            "type":"Services"
        }
    ],
    "sg:phone":"+1 716 693 1600",
    "sg:postcode":"14150",
    "sg:province":"NY",
    "sg:tags":[
        "clergy"
    ],
    "wof:name":"Dominic K Jung",
    "wof:placetype":"venue"
},
  "geometry": {"coordinates":[-78.86389200000001,42.999051],"type":"Point"}
}