{
  "type": "Feature",
  "properties": {
    "addr:full":"797 State Hwy 9l Queensbury NY 12804",
    "addr:housenumber":"797",
    "addr:postcode":"12804",
    "addr:street":"State Hwy",
    "iso:country":"US",
    "sg:address":"797 State Hwy 9l",
    "sg:city":"Queensbury",
    "sg:classifiers":[
        {
            "category":"Utilities",
            "subcategory":"Mobile Phone",
            "type":"Services"
        }
    ],
    "sg:phone":"+1 518 743 8260",
    "sg:postcode":"12804",
    "sg:province":"NY",
    "sg:tags":[
        "telephone",
        "cellular"
    ],
    "wof:name":"A Wireless Solutions",
    "wof:placetype":"venue"
},
  "geometry": {"coordinates":[-73.619669,43.356923],"type":"Point"}
}