{
  "type": "Feature",
  "properties": {
    "iso:country":"US",
    "sg:address":"163 Sullivan St",
    "sg:city":"Elmira",
    "sg:classifiers":[
        {
            "category":"Social Services",
            "type":"Services"
        }
    ],
    "sg:phone":"+1 607 734 6135",
    "sg:postcode":"14901",
    "sg:province":"NY",
    "wof:name":"Fingerlakes Developmental Dis",
    "wof:placetype":"venue"
},
  "geometry": {"coordinates":[-76.792939,42.091919],"type":"Point"}
}