{
  "type": "Feature",
  "properties": {
    "addr:full":"501 E Genesee St Fayetteville NY 13066",
    "addr:housenumber":"501",
    "addr:postcode":"13066",
    "addr:street":"E Genesee St",
    "iso:country":"US",
    "sg:address":"501 E Genesee St",
    "sg:city":"Fayetteville",
    "sg:classifiers":[
        {
            "category":"Ice Cream",
            "type":"Food & Drink"
        }
    ],
    "sg:menulink":"http://www.allmenus.com/ny/manlius/98786-friendlys/menu/",
    "sg:phone":"+1 315 637 9518",
    "sg:postcode":"13066",
    "sg:province":"NY",
    "sg:tags":[
        "burger",
        "american"
    ],
    "wof:name":"Friendly's",
    "wof:placetype":"venue"
},
  "geometry": {"coordinates":[-76.004446,43.029978],"type":"Point"}
}