{
  "type": "Feature",
  "properties": {
    "iso:country":"US",
    "sg:address":"2184 Pond Rd",
    "sg:city":"Ronkonkoma",
    "sg:classifiers":[
        {
            "category":"Local Transit",
            "type":"Transportation"
        }
    ],
    "sg:phone":"+1 631 588 7100",
    "sg:postcode":"11779",
    "sg:province":"NY",
    "sg:tags":[
        "ambulance"
    ],
    "wof:name":"Medical Express Inc",
    "wof:placetype":"venue"
},
  "geometry": {"coordinates":[-73.118629,40.798789],"type":"Point"}
}