{
  "type": "Feature",
  "properties": {
    "iso:country":"US",
    "sg:address":"86 Water St",
    "sg:city":"Fort Covington",
    "sg:classifiers":[
        {
            "category":"Railroad",
            "type":"Transportation"
        }
    ],
    "sg:phone":"+1 518 358 2446",
    "sg:postcode":"12932",
    "sg:province":"NY",
    "wof:name":"Conrail",
    "wof:placetype":"venue"
},
  "geometry": {"coordinates":[-73.590913,44.216648],"type":"Point"}
}