{
  "type": "Feature",
  "properties": {
    "addr:full":"27 State Hwy 59 Nyack NY 10960",
    "addr:housenumber":"27",
    "addr:postcode":"10960",
    "addr:street":"State Hwy 59",
    "iso:country":"US",
    "sg:address":"27 State Hwy 59",
    "sg:city":"Nyack",
    "sg:classifiers":[
        {
            "category":"Retail",
            "subcategory":"Auto Repair",
            "type":"Services"
        }
    ],
    "sg:phone":"+1 845 353 0500",
    "sg:postcode":"10960",
    "sg:province":"NY",
    "sg:tags":[
        "machine",
        "automotive",
        "shop",
        "performance"
    ],
    "wof:name":"Olsen Engines Inc",
    "wof:placetype":"venue"
},
  "geometry": {"coordinates":[-73.93097299999999,41.093007],"type":"Point"}
}