{
  "type": "Feature",
  "properties": {
    "addr:full":"12 W 20th St New York NY 10011",
    "addr:housenumber":"12",
    "addr:postcode":"10011",
    "addr:street":"W 20Th St",
    "iso:country":"US",
    "sg:address":"12 W 20th St",
    "sg:city":"New York",
    "sg:classifiers":[
        {
            "category":"Freight",
            "type":"Transportation"
        }
    ],
    "sg:phone":"+1 212 645 4364",
    "sg:postcode":"10011",
    "sg:province":"NY",
    "sg:tags":[
        "trucking"
    ],
    "wof:name":"Brown's Trucking & Messenger",
    "wof:placetype":"venue"
},
  "geometry": {"coordinates":[-73.99394700000001,40.740824],"type":"Point"}
}