{
  "type": "Feature",
  "properties": {
    "iso:country":"US",
    "sg:address":"800 Troy Schenectady Rd",
    "sg:city":"Latham",
    "sg:classifiers":[
        {
            "category":"Organizations",
            "subcategory":"Labor Organization",
            "type":"Services"
        }
    ],
    "sg:phone":"+1 518 785 4672",
    "sg:postcode":"12110",
    "sg:province":"NY",
    "wof:name":"Cdalf",
    "wof:placetype":"venue"
},
  "geometry": {"coordinates":[-73.78553599999999,42.759473],"type":"Point"}
}