{
  "type": "Feature",
  "properties": {
    "addr:full":"185 West End Ave Ste 1B New York NY 10023",
    "addr:housenumber":"185",
    "addr:postcode":"10023",
    "addr:street":"West End Ave Ste 1B",
    "iso:country":"US",
    "sg:address":"185 West End Ave Ste 1B",
    "sg:city":"New York",
    "sg:classifiers":[
        {
            "category":"Health Services",
            "subcategory":"Doctor",
            "type":"Services"
        }
    ],
    "sg:phone":"+1 212 877 3062",
    "sg:postcode":"10023",
    "sg:province":"NY",
    "sg:website":"www.americanfootcare.com",
    "wof:name":"Theodore Antonetz, DPM",
    "wof:placetype":"venue"
},
  "geometry": {"coordinates":[-73.986755,40.777522],"type":"Point"}
}