{
  "type": "Feature",
  "properties": {
    "iso:country":"US",
    "sg:address":"108 Erie Blvd",
    "sg:city":"Schenectady",
    "sg:classifiers":[
        {
            "category":"Communications",
            "subcategory":"Radio Station",
            "type":"Services"
        }
    ],
    "sg:phone":"+1   ",
    "sg:postcode":"12305",
    "sg:province":"NY",
    "sg:tags":[
        "broadcast"
    ],
    "wof:name":"W B K K Radio",
    "wof:placetype":"venue"
},
  "geometry": {"coordinates":[-73.945729,42.813149],"type":"Point"}
}