{
  "type": "Feature",
  "properties": {
    "iso:country":"US",
    "sg:address":"5117 Kings Hwy",
    "sg:city":"Brooklyn",
    "sg:classifiers":[
        {
            "category":"Shopping",
            "subcategory":"Clothing, Apparel, & Fashions",
            "type":"Retail Goods"
        }
    ],
    "sg:phone":"+1   ",
    "sg:postcode":"11234",
    "sg:province":"NY",
    "sg:tags":[
        "woman",
        "accessory"
    ],
    "wof:name":"Accessory Place 8",
    "wof:placetype":"venue"
},
  "geometry": {"coordinates":[-73.926805,40.635931],"type":"Point"}
}