{
  "type": "Feature",
  "properties": {
    "addr:full":"2207 Jericho Tpke Commack NY 11725",
    "addr:housenumber":"2207",
    "addr:postcode":"11725",
    "addr:street":"Jericho Tpke",
    "iso:country":"US",
    "sg:address":"2207 Jericho Tpke",
    "sg:city":"Commack",
    "sg:classifiers":[
        {
            "category":"Home & Garden",
            "subcategory":"Building Materials",
            "type":"Retail Goods"
        }
    ],
    "sg:phone":"+1 631 499 6300",
    "sg:postcode":"11725",
    "sg:province":"NY",
    "sg:tags":[
        "glass",
        "window",
        "plate"
    ],
    "wof:name":"Amendola Auto Glass Inc",
    "wof:placetype":"venue"
},
  "geometry": {"coordinates":[-73.27250100000001,40.845213],"type":"Point"}
}