{
  "type": "Feature",
  "properties": {
    "iso:country":"US",
    "sg:address":"3938 S Street Rd",
    "sg:city":"Marcellus",
    "sg:classifiers":[
        {
            "category":"Professional",
            "subcategory":"Management & Consulting",
            "type":"Services"
        }
    ],
    "sg:phone":"+1 315 673 9126",
    "sg:postcode":"13108",
    "sg:province":"NY",
    "sg:tags":[
        "consultant",
        "educational"
    ],
    "wof:name":"The Donor Family Network",
    "wof:placetype":"venue"
},
  "geometry": {"coordinates":[-76.333898,42.961013],"type":"Point"}
}