{
  "type": "Feature",
  "properties": {
    "iso:country":"US",
    "sg:address":"3049 N Gravel Rd",
    "sg:city":"Medina",
    "sg:classifiers":[
        {
            "category":"Building & Trades",
            "subcategory":"Construction",
            "type":"Services"
        }
    ],
    "sg:phone":"+1 585 798 3680",
    "sg:postcode":"14103",
    "sg:province":"NY",
    "sg:tags":[
        "marking",
        "maintenance",
        "parking"
    ],
    "wof:name":"Ridgeway Highway Dept",
    "wof:placetype":"venue"
},
  "geometry": {"coordinates":[-78.394671,43.262984],"type":"Point"}
}