{
  "type": "Feature",
  "properties": {
    "iso:country":"US",
    "sg:address":"162 Madison Ave",
    "sg:city":"New York",
    "sg:classifiers":[
        {
            "category":"Deli",
            "type":"Food & Drink"
        }
    ],
    "sg:menulink":"http://www.allmenus.com/ny/new-york/249222-twin-deli/menu/",
    "sg:phone":"+1 212 447 4455",
    "sg:postcode":"10016",
    "sg:province":"NY",
    "sg:tags":[
        "american"
    ],
    "wof:name":"Twin Deli",
    "wof:placetype":"venue"
},
  "geometry": {"coordinates":[-73.983926,40.746944],"type":"Point"}
}