{
  "type": "Feature",
  "properties": {
    "addr:full":"13867 Francis Lewis Blvd Rosedale NY 11422",
    "addr:housenumber":"13867",
    "addr:postcode":"11422",
    "addr:street":"Francis Lewis Blvd",
    "iso:country":"US",
    "sg:address":"13867 Francis Lewis Blvd",
    "sg:city":"Rosedale",
    "sg:classifiers":[
        {
            "category":"Retail",
            "subcategory":"Laundry & Dry Cleaning",
            "type":"Services"
        }
    ],
    "sg:phone":"+1 718 978 5145",
    "sg:postcode":"11422",
    "sg:province":"NY",
    "wof:name":"Rosedale Village Cleaners",
    "wof:placetype":"venue"
},
  "geometry": {"coordinates":[-73.73699999999999,40.667301],"type":"Point"}
}