{
  "type": "Feature",
  "properties": {
    "addr:full":"103 Richmond Hill Rd New Canaan NY 06840",
    "addr:housenumber":"103",
    "addr:postcode":"06840",
    "addr:street":"Richmond Hill Rd",
    "iso:country":"US",
    "sg:address":"103 Richmond Hill Rd",
    "sg:city":"New Canaan",
    "sg:classifiers":[
        {
            "category":"Shopping",
            "subcategory":"Gifts & Souvenirs",
            "type":"Retail Goods"
        }
    ],
    "sg:phone":"+1 203 966 3094",
    "sg:postcode":"06840",
    "sg:province":"NY",
    "sg:tags":[
        "basket",
        "parcel"
    ],
    "wof:name":"Between Friends",
    "wof:placetype":"venue"
},
  "geometry": {"coordinates":[-73.500961,41.141554],"type":"Point"}
}