{
  "type": "Feature",
  "properties": {
    "iso:country":"US",
    "sg:address":"151 Mitchell Rd",
    "sg:city":"Bridgehampton",
    "sg:classifiers":[
        {
            "category":"Travel",
            "subcategory":"Campground",
            "type":"Entertainment"
        }
    ],
    "sg:phone":"+1 631 537 5188",
    "sg:postcode":"11978",
    "sg:province":"NY",
    "sg:tags":[
        "camp"
    ],
    "wof:name":"Hayground Camp",
    "wof:placetype":"venue"
},
  "geometry": {"coordinates":[-72.644149,40.807511],"type":"Point"}
}