{
  "type": "Feature",
  "properties": {
    "addr:full":"341 Heberton Ave Staten Island NY 10302",
    "addr:housenumber":"341",
    "addr:postcode":"10302",
    "addr:street":"Heberton Ave",
    "iso:country":"US",
    "sg:address":"341 Heberton Ave",
    "sg:city":"Staten Island",
    "sg:classifiers":[
        {
            "category":"Food & Beverages",
            "subcategory":"Groceries & Convenience Stores",
            "type":"Retail Goods"
        }
    ],
    "sg:phone":"+1 718 442 7906",
    "sg:postcode":"10302",
    "sg:province":"NY",
    "sg:tags":[
        "deli",
        "delicatessen"
    ],
    "wof:name":"Heberton Deli",
    "wof:placetype":"venue"
},
  "geometry": {"coordinates":[-74.134201,40.632702],"type":"Point"}
}