{
  "type": "Feature",
  "properties": {
    "addr:full":"711 E 140th St Bronx NY 10454",
    "addr:housenumber":"711",
    "addr:postcode":"10454",
    "addr:street":"E 140Th St",
    "iso:country":"US",
    "sg:address":"711 E 140th St",
    "sg:city":"Bronx",
    "sg:classifiers":[
        {
            "category":"Retail",
            "subcategory":"Auto Repair",
            "type":"Services"
        }
    ],
    "sg:phone":"+1 646 432 7443",
    "sg:postcode":"10454",
    "sg:province":"NY",
    "sg:tags":[
        "wrecker"
    ],
    "wof:name":"24 Hour Towing",
    "wof:placetype":"venue"
},
  "geometry": {"coordinates":[-73.913144,40.806921],"type":"Point"}
}