{
  "type": "Feature",
  "properties": {
    "iso:country":"US",
    "sg:address":"289 Southwood Cir",
    "sg:city":"Syosset",
    "sg:classifiers":[
        {
            "category":"Professional",
            "subcategory":"Computer Services",
            "type":"Services"
        }
    ],
    "sg:phone":"+1 516 496 4608",
    "sg:postcode":"11791",
    "sg:province":"NY",
    "sg:tags":[
        "design",
        "system"
    ],
    "wof:name":"Honest John TV",
    "wof:placetype":"venue"
},
  "geometry": {"coordinates":[-73.50309300000001,40.801344],"type":"Point"}
}