{
  "type": "Feature",
  "properties": {
    "iso:country":"US",
    "sg:address":"1473 Front St",
    "sg:city":"East Meadow",
    "sg:classifiers":[
        {
            "category":"Building & Trades",
            "subcategory":"Construction",
            "type":"Services"
        }
    ],
    "sg:phone":"+1 516 292 0517",
    "sg:postcode":"11554",
    "sg:province":"NY",
    "sg:tags":[
        "contractor"
    ],
    "wof:name":"Seasons At East Meadow Construction The",
    "wof:placetype":"venue"
},
  "geometry": {"coordinates":[-73.576975,40.713264],"type":"Point"}
}