{
  "type": "Feature",
  "properties": {
    "addr:full":"2134 30th Avenue Astoria NY 11102",
    "addr:housenumber":"2134",
    "addr:postcode":"11102",
    "addr:street":"30Th Avenue",
    "iso:country":"US",
    "sg:address":"2134 30th Avenue",
    "sg:city":"Astoria",
    "sg:classifiers":[
        {
            "category":"Health Services",
            "subcategory":"Dentist",
            "type":"Services"
        }
    ],
    "sg:phone":"+1 718 274 2749",
    "sg:postcode":"11102",
    "sg:province":"NY",
    "wof:name":"Bokser Alexander DDS",
    "wof:placetype":"venue"
},
  "geometry": {"coordinates":[-73.927288,40.769517],"type":"Point"}
}