{
  "type": "Feature",
  "properties": {
    "iso:country":"US",
    "sg:address":"26 Williamsburg Rd",
    "sg:city":"Pittsford",
    "sg:classifiers":[
        {
            "category":"Insurance",
            "subcategory":"Insurance Agent",
            "type":"Services"
        }
    ],
    "sg:phone":"+1 585 359 9717",
    "sg:postcode":"14534",
    "sg:province":"NY",
    "wof:name":"S&E Assoc",
    "wof:placetype":"venue"
},
  "geometry": {"coordinates":[-77.586146,43.067518],"type":"Point"}
}