{
  "type": "Feature",
  "properties": {
    "iso:country":"US",
    "sg:address":"136 Montague St",
    "sg:city":"Brooklyn",
    "sg:phone":"+1 866 678 5305",
    "sg:postcode":"11201",
    "sg:province":"NY",
    "sg:website":"http://brooklyn.citysearch.com/profile/external/603899212/brooklyn_ny/the_heights_salon_of_brooklyn.html?publisher=yellowpages&reference_id=1&placement=ypwebsitemip",
    "wof:name":"The Heights Salon of Brooklyn",
    "wof:placetype":"venue"
},
  "geometry": {"coordinates":[-73.993898,40.694672],"type":"Point"}
}