{
  "type": "Feature",
  "properties": {
    "iso:country":"US",
    "sg:address":"74 Pearl St",
    "sg:city":"New York",
    "sg:classifiers":[
        {
            "category":"Shopping",
            "subcategory":"Florist",
            "type":"Retail Goods"
        },
        {
            "category":"Shopping",
            "subcategory":"Gifts & Souvenirs",
            "type":"Retail Goods"
        }
    ],
    "sg:phone":"+1 212 269 0090",
    "sg:postcode":"10004",
    "sg:province":"NY",
    "sg:tags":[
        "basket",
        "parcel"
    ],
    "wof:name":"Flowers On The Exchange Too",
    "wof:placetype":"venue"
},
  "geometry": {"coordinates":[-74.009455,40.704447],"type":"Point"}
}