{
  "type": "Feature",
  "properties": {
    "addr:full":"6336 Robinson Rd Exd Lockport NY 14094",
    "addr:housenumber":"6336",
    "addr:postcode":"14094",
    "addr:street":"Robinson Rd Exd",
    "iso:country":"US",
    "sg:address":"6336 Robinson Rd Exd",
    "sg:city":"Lockport",
    "sg:classifiers":[
        {
            "category":"Travel",
            "subcategory":"Travel Agent",
            "type":"Entertainment"
        }
    ],
    "sg:phone":"+1   ",
    "sg:postcode":"14094",
    "sg:province":"NY",
    "sg:tags":[
        "agency"
    ],
    "wof:name":"Cammaratas Travel Agency",
    "wof:placetype":"venue"
},
  "geometry": {"coordinates":[-78.686549,43.131984],"type":"Point"}
}