{
  "type": "Feature",
  "properties": {
    "iso:country":"US",
    "sg:address":"69 S 4th Ave",
    "sg:city":"Mount Vernon",
    "sg:classifiers":[
        {
            "category":"Shopping",
            "subcategory":"Clothing, Apparel, & Fashions",
            "type":"Retail Goods"
        }
    ],
    "sg:phone":"+1 914 667 4034",
    "sg:postcode":"10550",
    "sg:province":"NY",
    "sg:tags":[
        "wig",
        "toupee",
        "hairpiece"
    ],
    "wof:name":"Wig Land",
    "wof:placetype":"venue"
},
  "geometry": {"coordinates":[-73.83656499999999,40.910946],"type":"Point"}
}