{
  "type": "Feature",
  "properties": {
    "addr:full":"445 Park Avenue New York NY 10022",
    "addr:housenumber":"445",
    "addr:postcode":"10022",
    "addr:street":"Park Avenue",
    "iso:country":"US",
    "sg:address":"445 Park Avenue",
    "sg:city":"New York",
    "sg:classifiers":[
        {
            "category":"Professional",
            "subcategory":"Lawyer & Legal Services",
            "type":"Services"
        }
    ],
    "sg:phone":"+1 212 229 1516",
    "sg:postcode":"10022",
    "sg:province":"NY",
    "wof:name":"Newman Donna ESQ",
    "wof:placetype":"venue"
},
  "geometry": {"coordinates":[-73.970623,40.761547],"type":"Point"}
}