{
  "type": "Feature",
  "properties": {
    "addr:full":"60-15 Woodside Ave Queens NY 11377",
    "addr:housenumber":"60-15",
    "addr:postcode":"11377",
    "addr:street":"Woodside Ave",
    "iso:country":"US",
    "sg:address":"60-15 Woodside Ave",
    "sg:city":"Queens",
    "sg:classifiers":[
        {
            "category":"Restaurant",
            "type":"Food & Drink"
        }
    ],
    "sg:phone":"+1 718 205 1975",
    "sg:postcode":"11377",
    "sg:province":"NY",
    "sg:tags":[
        "thai"
    ],
    "sg:website":"www.sukithaishabu.com",
    "wof:name":"Suki Thai Shabu",
    "wof:placetype":"venue"
},
  "geometry": {"coordinates":[-73.904004,40.745013],"type":"Point"}
}