{
  "type": "Feature",
  "properties": {
    "iso:country":"US",
    "sg:address":"256 Franklin St",
    "sg:city":"Brooklyn",
    "sg:classifiers":[
        {
            "category":"Organizations",
            "subcategory":"Religious Organization",
            "type":"Services"
        }
    ],
    "sg:phone":"+1 718 383 1126",
    "sg:postcode":"11222",
    "sg:province":"NY",
    "sg:tags":[
        "church"
    ],
    "wof:name":"Iglesia Pentecostal El Tabor",
    "wof:placetype":"venue"
},
  "geometry": {"coordinates":[-73.958292,40.734134],"type":"Point"}
}