{
  "type": "Feature",
  "properties": {
    "addr:full":"481 E 180th St Bronx NY 10457",
    "addr:housenumber":"481",
    "addr:postcode":"10457",
    "addr:street":"E 180Th St",
    "iso:country":"US",
    "sg:address":"481 E 180th St",
    "sg:city":"Bronx",
    "sg:classifiers":[
        {
            "category":"Wholesale",
            "subcategory":"Groceries",
            "type":"Manufacturing & Wholesale Goods"
        }
    ],
    "sg:phone":"+1 718 733 5082",
    "sg:postcode":"10457",
    "sg:province":"NY",
    "sg:tags":[
        "grocer"
    ],
    "wof:name":"481 Grocery Store Inc",
    "wof:placetype":"venue"
},
  "geometry": {"coordinates":[-73.896722,40.851851],"type":"Point"}
}