{
  "type": "Feature",
  "properties": {
    "iso:country":"US",
    "sg:address":"17 Springbrook Rd",
    "sg:city":"Nanuet",
    "sg:classifiers":[
        {
            "category":"Building & Trades",
            "subcategory":"Construction",
            "type":"Services"
        }
    ],
    "sg:phone":"+1 845 371 7518",
    "sg:postcode":"10954",
    "sg:province":"NY",
    "sg:tags":[
        "house"
    ],
    "wof:name":"NJ Marshall Construction Inc",
    "wof:placetype":"venue"
},
  "geometry": {"coordinates":[-74.033083,41.117055],"type":"Point"}
}