{
  "type": "Feature",
  "properties": {
    "iso:country":"US",
    "sg:address":"19 Frost Creek Dr",
    "sg:city":"Locust Valley",
    "sg:classifiers":[
        {
            "category":"Building & Trades",
            "subcategory":"Construction",
            "type":"Services"
        }
    ],
    "sg:phone":"+1 516 676 6501",
    "sg:postcode":"11560",
    "sg:province":"NY",
    "sg:tags":[
        "dry wall",
        "contractor"
    ],
    "wof:name":"R K Drywall Corp",
    "wof:placetype":"venue"
},
  "geometry": {"coordinates":[-73.60062000000001,40.893384],"type":"Point"}
}