{
  "type": "Feature",
  "properties": {
    "iso:country":"US",
    "sg:address":"50 E 42nd St Fl 14",
    "sg:city":"New York",
    "sg:classifiers":[
        {
            "category":"Communications",
            "subcategory":"Newspaper",
            "type":"Services"
        }
    ],
    "sg:phone":"+1 646 837 0200",
    "sg:postcode":"10017",
    "sg:province":"NY",
    "sg:tags":[
        "print",
        "medium"
    ],
    "wof:name":"Giant Magazine LLC",
    "wof:placetype":"venue"
},
  "geometry": {"coordinates":[-73.97894100000001,40.752516],"type":"Point"}
}