{
  "type": "Feature",
  "properties": {
    "addr:full":"140 Cabrini Boulevard New York NY 10033",
    "addr:housenumber":"140",
    "addr:postcode":"10033",
    "addr:street":"Cabrini Boulevard",
    "iso:country":"US",
    "sg:address":"140 Cabrini Boulevard",
    "sg:city":"New York",
    "sg:classifiers":[
        {
            "category":"Building & Trades",
            "subcategory":"Locksmith",
            "type":"Services"
        }
    ],
    "sg:phone":"+1 347 576 2850",
    "sg:postcode":"10033",
    "sg:province":"NY",
    "sg:tags":[
        "key"
    ],
    "wof:name":"Locksmith Tire Svc Locksmith Flat Fix Locksmith 24",
    "wof:placetype":"venue"
},
  "geometry": {"coordinates":[-73.93972100000001,40.852785],"type":"Point"}
}