{
  "type": "Feature",
  "properties": {
    "iso:country":"US",
    "sg:address":"129 W Main St",
    "sg:city":"Goshen",
    "sg:classifiers":[
        {
            "category":"Travel",
            "subcategory":"Travel Agent",
            "type":"Entertainment"
        }
    ],
    "sg:phone":"+1   ",
    "sg:postcode":"10924",
    "sg:province":"NY",
    "sg:tags":[
        "agency"
    ],
    "wof:name":"J A B Travel & Cruise Center",
    "wof:placetype":"venue"
},
  "geometry": {"coordinates":[-74.32654100000001,41.401644],"type":"Point"}
}