{
  "type": "Feature",
  "properties": {
    "iso:country":"US",
    "sg:address":"15 S Main St",
    "sg:city":"Spring Valley",
    "sg:classifiers":[
        {
            "category":"Professional",
            "subcategory":"Accounting & Tax Preparation",
            "type":"Services"
        }
    ],
    "sg:phone":"+1 845 371 3259",
    "sg:postcode":"10977",
    "sg:province":"NY",
    "sg:tags":[
        "return",
        "filing"
    ],
    "wof:name":"H & R Block",
    "wof:placetype":"venue"
},
  "geometry": {"coordinates":[-74.044912,41.111847],"type":"Point"}
}