{
  "type": "Feature",
  "properties": {
    "addr:full":"351 Old Kensico Rd White Plains NY 10603",
    "addr:housenumber":"351",
    "addr:postcode":"10603",
    "addr:street":"Old Kensico Rd",
    "iso:country":"US",
    "sg:address":"351 Old Kensico Rd",
    "sg:city":"White Plains",
    "sg:classifiers":[
        {
            "category":"Shopping",
            "subcategory":"Optician",
            "type":"Retail Goods"
        }
    ],
    "sg:phone":"+1 914 684 6090",
    "sg:postcode":"10603",
    "sg:province":"NY",
    "sg:tags":[
        "eyewear"
    ],
    "wof:name":"Specialty Optix",
    "wof:placetype":"venue"
},
  "geometry": {"coordinates":[-73.777241,41.4377],"type":"Point"}
}