{
  "type": "Feature",
  "properties": {
    "addr:full":"380 Merrick Ave East Meadow NY 11554",
    "addr:housenumber":"380",
    "addr:postcode":"11554",
    "addr:street":"Merrick Ave",
    "iso:country":"US",
    "sg:address":"380 Merrick Ave",
    "sg:city":"East Meadow",
    "sg:classifiers":[
        {
            "category":"Health Services",
            "subcategory":"Doctor",
            "type":"Services"
        }
    ],
    "sg:phone":"+1 516 542 0203",
    "sg:postcode":"11554",
    "sg:province":"NY",
    "wof:name":"Hamid And Aslam Medical Group",
    "wof:placetype":"venue"
},
  "geometry": {"coordinates":[-73.572669,40.712401],"type":"Point"}
}