{
  "type": "Feature",
  "properties": {
    "iso:country":"US",
    "sg:address":"132 Main St",
    "sg:city":"Leicester",
    "sg:classifiers":[
        {
            "category":"Government",
            "subcategory":"Court House",
            "type":"Public Place"
        }
    ],
    "sg:phone":"+1 585 382 9419",
    "sg:postcode":"14481",
    "sg:province":"NY",
    "sg:tags":[
        "city"
    ],
    "wof:name":"Leicester Town Court",
    "wof:placetype":"venue"
},
  "geometry": {"coordinates":[-77.89913900000001,42.771989],"type":"Point"}
}