{
  "type": "Feature",
  "properties": {
    "iso:country":"US",
    "sg:address":"117 N Main St",
    "sg:city":"Mount Morris",
    "sg:classifiers":[
        {
            "category":"Government",
            "subcategory":"Police Station",
            "type":"Public Place"
        }
    ],
    "sg:phone":"+1 585 658 2155",
    "sg:postcode":"14510",
    "sg:province":"NY",
    "sg:tags":[
        "enforcement",
        "law"
    ],
    "wof:name":"Mount Morris Police",
    "wof:placetype":"venue"
},
  "geometry": {"coordinates":[-77.879822,42.735158],"type":"Point"}
}