{
  "type": "Feature",
  "properties": {
    "iso:country":"US",
    "sg:address":"31 W 11 St",
    "sg:city":"New York",
    "sg:classifiers":[
        {
            "category":"Health Services",
            "subcategory":"Health Practitioner",
            "type":"Services"
        }
    ],
    "sg:phone":"+1   ",
    "sg:postcode":"10011",
    "sg:province":"NY",
    "wof:name":"Steven Reisner",
    "wof:placetype":"venue"
},
  "geometry": {"coordinates":[-73.99749,40.735041],"type":"Point"}
}