{
  "type": "Feature",
  "properties": {
    "iso:country":"US",
    "sg:address":"661 South Ave",
    "sg:city":"Syracuse",
    "sg:classifiers":[
        {
            "category":"Food & Beverages",
            "subcategory":"Liquor & Beverages",
            "type":"Retail Goods"
        }
    ],
    "sg:phone":"+1   ",
    "sg:postcode":"13207",
    "sg:province":"NY",
    "sg:tags":[
        "alcoholic"
    ],
    "wof:name":"Cherry Valley Liquor Store",
    "wof:placetype":"venue"
},
  "geometry": {"coordinates":[-76.158726,43.032845],"type":"Point"}
}