{
  "type": "Feature",
  "properties": {
    "addr:full":"54 Jeanne Dr Newburgh NY 12550",
    "addr:housenumber":"54",
    "addr:postcode":"12550",
    "addr:street":"Jeanne Dr",
    "iso:country":"US",
    "sg:address":"54 Jeanne Dr",
    "sg:city":"Newburgh",
    "sg:classifiers":[
        {
            "category":"Shopping",
            "subcategory":"Gifts & Souvenirs",
            "type":"Retail Goods"
        }
    ],
    "sg:phone":"+1 845 566 1907",
    "sg:postcode":"12550",
    "sg:province":"NY",
    "sg:tags":[
        "party",
        "supply"
    ],
    "wof:name":"Amscan Inc",
    "wof:placetype":"venue"
},
  "geometry": {"coordinates":[-74.052741,41.542399],"type":"Point"}
}