{
  "type": "Feature",
  "properties": {
    "addr:full":"164 Hilltop Dr Brentwood NY 11717",
    "addr:housenumber":"164",
    "addr:postcode":"11717",
    "addr:street":"Hilltop Dr",
    "iso:country":"US",
    "sg:address":"164 Hilltop Dr",
    "sg:city":"Brentwood",
    "sg:classifiers":[
        {
            "category":"Banks & Credit Unions",
            "subcategory":"Bank",
            "type":"Services"
        }
    ],
    "sg:phone":"+1 631 231 8056",
    "sg:postcode":"11717",
    "sg:province":"NY",
    "sg:tags":[
        "loan",
        "real estate"
    ],
    "wof:name":"Majorie's",
    "wof:placetype":"venue"
},
  "geometry": {"coordinates":[-73.23294199999999,40.771628],"type":"Point"}
}