{
  "type": "Feature",
  "properties": {
    "addr:full":"East 66th Street Brooklyn NY 11234",
    "addr:postcode":"11234",
    "addr:street":"East 66Th Street",
    "iso:country":"US",
    "sg:address":"East 66th Street",
    "sg:city":"Brooklyn",
    "sg:classifiers":[
        {
            "category":"Wholesale",
            "subcategory":"Stationery",
            "type":"Manufacturing & Wholesale Goods"
        }
    ],
    "sg:phone":"+1 917 697 0423",
    "sg:postcode":"11234",
    "sg:province":"NY",
    "sg:tags":[
        "card"
    ],
    "sg:website":"www.apaperie.com",
    "wof:name":"A'Paperie",
    "wof:placetype":"venue"
},
  "geometry": {"coordinates":[-73.90917899999999,40.615723],"type":"Point"}
}