{
  "type": "Feature",
  "properties": {
    "addr:full":"101 S Hudson St Mechanicville NY 12118",
    "addr:housenumber":"101",
    "addr:postcode":"12118",
    "addr:street":"S Hudson St",
    "iso:country":"US",
    "sg:address":"101 S Hudson St",
    "sg:city":"Mechanicville",
    "sg:classifiers":[
        {
            "category":"Building & Trades",
            "subcategory":"Construction",
            "type":"Services"
        }
    ],
    "sg:phone":"+1 518 664 7866",
    "sg:postcode":"12118",
    "sg:province":"NY",
    "sg:tags":[
        "contractor"
    ],
    "wof:name":"Admiral The",
    "wof:placetype":"venue"
},
  "geometry": {"coordinates":[-73.68168300000001,42.902004],"type":"Point"}
}