{
  "type": "Feature",
  "properties": {
    "addr:full":"3864 Co Rd 46 Canandaigua NY 14424",
    "addr:housenumber":"3864;46",
    "addr:postcode":"14424",
    "addr:street":"Co Rd",
    "iso:country":"US",
    "sg:address":"3864 Co Rd 46",
    "sg:city":"Canandaigua",
    "sg:classifiers":[
        {
            "category":"Real Estate",
            "subcategory":"Surveying",
            "type":"Services"
        }
    ],
    "sg:phone":"+1 585 396 1382",
    "sg:postcode":"14424",
    "sg:province":"NY",
    "sg:tags":[
        "surveyor"
    ],
    "wof:name":"Schafer Survey",
    "wof:placetype":"venue"
},
  "geometry": {"coordinates":[-77.209136,42.886203],"type":"Point"}
}