{
  "type": "Feature",
  "properties": {
    "addr:full":"4310 National Street Corona NY 11368",
    "addr:housenumber":"4310",
    "addr:postcode":"11368",
    "addr:street":"National Street",
    "iso:country":"US",
    "sg:address":"4310 National Street",
    "sg:city":"Corona",
    "sg:classifiers":[
        {
            "category":"Place Of Worship",
            "subcategory":"Synagogue",
            "type":"Public Place"
        },
        {
            "category":"Place Of Worship",
            "subcategory":"Temple",
            "type":"Public Place"
        }
    ],
    "sg:phone":"+1 718 639 2456",
    "sg:postcode":"11368",
    "sg:province":"NY",
    "sg:tags":[
        "buddhist"
    ],
    "wof:name":"Fu Yen True Budda Temple",
    "wof:placetype":"venue"
},
  "geometry": {"coordinates":[-73.86408299999999,40.746383],"type":"Point"}
}