{
  "type": "Feature",
  "properties": {
    "addr:full":"25857 US Hwy 11 Evans Mills NY 13637",
    "addr:postcode":"25857;13637",
    "addr:street":"Us Hwy 11 Evans Mills",
    "iso:country":"US",
    "sg:address":"25857 US Hwy 11",
    "sg:city":"Evans Mills",
    "sg:classifiers":[
        {
            "category":"Restaurant",
            "type":"Food & Drink"
        }
    ],
    "sg:phone":"+1 315 629 4055",
    "sg:postcode":"13637",
    "sg:province":"NY",
    "wof:name":"Subway Sandwiches & Salads",
    "wof:placetype":"venue"
},
  "geometry": {"coordinates":[-75.835212,44.050574],"type":"Point"}
}