{
  "type": "Feature",
  "properties": {
    "iso:country":"US",
    "sg:address":"201 46th St",
    "sg:city":"Brooklyn",
    "sg:classifiers":[
        {
            "category":"Manufacturing",
            "subcategory":"Textiles",
            "type":"Manufacturing & Wholesale Goods"
        }
    ],
    "sg:phone":"+1   ",
    "sg:postcode":"11220",
    "sg:province":"NY",
    "sg:tags":[
        "sweater",
        "contract",
        "mfg"
    ],
    "wof:name":"Star Bright Knitting Mills",
    "wof:placetype":"venue"
},
  "geometry": {"coordinates":[-74.012299,40.649947],"type":"Point"}
}