{
  "type": "Feature",
  "properties": {
    "addr:full":"730 5th Ave 17th Fl New York NY 10019",
    "addr:housenumber":"730",
    "addr:postcode":"10019",
    "addr:street":"5Th Ave 17Th Fl",
    "iso:country":"US",
    "sg:address":"730 5th Ave 17th Fl",
    "sg:city":"New York",
    "sg:classifiers":[
        {
            "category":"Shopping",
            "subcategory":"Clothing, Apparel, & Fashions",
            "type":"Retail Goods"
        }
    ],
    "sg:phone":"+1 212 246 2244",
    "sg:postcode":"10019",
    "sg:province":"NY",
    "sg:tags":[
        "men's",
        "clothing"
    ],
    "sg:website":"www.zegna.com",
    "wof:name":"Ermenegildo Zegna Co.",
    "wof:placetype":"venue"
},
  "geometry": {"coordinates":[-73.97411099999999,40.762763],"type":"Point"}
}