{
  "type": "Feature",
  "properties": {
    "iso:country":"US",
    "sg:address":"7359 Coward Rd",
    "sg:city":"Byron",
    "sg:classifiers":[
        {
            "category":"Personal",
            "type":"Services"
        }
    ],
    "sg:phone":"+1   ",
    "sg:postcode":"14422",
    "sg:province":"NY",
    "wof:name":"Daniel Gonyea",
    "wof:placetype":"venue"
},
  "geometry": {"coordinates":[-78.030495,43.05899],"type":"Point"}
}