{
  "type": "Feature",
  "properties": {
    "iso:country":"US",
    "sg:address":"1 Carlyle Ave",
    "sg:city":"Troy",
    "sg:classifiers":[
        {
            "category":"Shopping",
            "subcategory":"Crafts & Fabrics",
            "type":"Retail Goods"
        }
    ],
    "sg:phone":"+1 518 274 1931",
    "sg:postcode":"12180",
    "sg:province":"NY",
    "sg:tags":[
        "yarn"
    ],
    "wof:name":"East Side Weaver",
    "wof:placetype":"venue"
},
  "geometry": {"coordinates":[-73.65733299999999,42.72989],"type":"Point"}
}