{
  "type": "Feature",
  "properties": {
    "iso:country":"US",
    "sg:address":"102 Bedford Ave",
    "sg:city":"Bellmore",
    "sg:classifiers":[
        {
            "category":"Manufacturing",
            "subcategory":"Tools & Machinery",
            "type":"Manufacturing & Wholesale Goods"
        }
    ],
    "sg:phone":"+1 516 781 2669",
    "sg:postcode":"11710",
    "sg:province":"NY",
    "sg:tags":[
        "equipment",
        "hospital",
        "supply"
    ],
    "wof:name":"Managed Health Care Svc",
    "wof:placetype":"venue"
},
  "geometry": {"coordinates":[-73.526989,40.668061],"type":"Point"}
}