{
  "type": "Feature",
  "properties": {
    "addr:full":"3530 Webster Ave Bronx NY 10467",
    "addr:housenumber":"3530",
    "addr:postcode":"10467",
    "addr:street":"Webster Ave",
    "iso:country":"US",
    "sg:address":"3530 Webster Ave",
    "sg:city":"Bronx",
    "sg:classifiers":[
        {
            "category":"Retail",
            "subcategory":"Auto Repair",
            "type":"Services"
        }
    ],
    "sg:phone":"+1 718 515 9144",
    "sg:postcode":"10467",
    "sg:province":"NY",
    "sg:tags":[
        "general"
    ],
    "wof:name":"Great Bronx Auto Repair",
    "wof:placetype":"venue"
},
  "geometry": {"coordinates":[-73.871168,40.879227],"type":"Point"}
}