{
  "type": "Feature",
  "properties": {
    "addr:full":"6067 State Hwy 46 Durhamville NY 13054",
    "addr:housenumber":"6067",
    "addr:postcode":"13054",
    "addr:street":"State Hwy 46",
    "iso:country":"US",
    "sg:address":"6067 State Hwy 46",
    "sg:city":"Durhamville",
    "sg:classifiers":[
        {
            "category":"Building & Trades",
            "subcategory":"Landscaping Services",
            "type":"Services"
        }
    ],
    "sg:phone":"+1 315 363 1329",
    "sg:postcode":"13054",
    "sg:province":"NY",
    "wof:name":"Precision Tree Care",
    "wof:placetype":"venue"
},
  "geometry": {"coordinates":[-75.67112299999999,43.156589],"type":"Point"}
}