{
  "type": "Feature",
  "properties": {
    "addr:full":"76 Southaven Ave Medford NY 11763",
    "addr:housenumber":"76",
    "addr:postcode":"11763",
    "addr:street":"Southaven Ave",
    "iso:country":"US",
    "sg:address":"76 Southaven Ave",
    "sg:city":"Medford",
    "sg:classifiers":[
        {
            "category":"Health Services",
            "subcategory":"Doctor",
            "type":"Services"
        }
    ],
    "sg:phone":"+1 631 475 0332",
    "sg:postcode":"11763",
    "sg:province":"NY",
    "sg:tags":[
        "physician",
        "surgeon"
    ],
    "wof:name":"Huml & Vani",
    "wof:placetype":"venue"
},
  "geometry": {"coordinates":[-73.003224,40.801348],"type":"Point"}
}