{
  "type": "Feature",
  "properties": {
    "iso:country":"US",
    "sg:address":"111 Carleton Ave Ste",
    "sg:city":"Islip",
    "sg:classifiers":[
        {
            "category":"Health Services",
            "subcategory":"Doctor",
            "type":"Services"
        }
    ],
    "sg:phone":"+1 516 581 8822",
    "sg:postcode":"11751",
    "sg:province":"NY",
    "sg:tags":[
        "podiatrist"
    ],
    "wof:name":"Cutler Peter DPM",
    "wof:placetype":"venue"
},
  "geometry": {"coordinates":[-73.212997,40.735802],"type":"Point"}
}