{
  "type": "Feature",
  "properties": {
    "addr:full":"84 Forest Ave Locust Valley NY 11560",
    "addr:housenumber":"84",
    "addr:postcode":"11560",
    "addr:street":"Forest Ave",
    "iso:country":"US",
    "sg:address":"84 Forest Ave",
    "sg:city":"Locust Valley",
    "sg:classifiers":[
        {
            "category":"Banks & Credit Unions",
            "subcategory":"Investment Brokerage",
            "type":"Services"
        }
    ],
    "sg:phone":"+1 516 759 6278",
    "sg:postcode":"11560",
    "sg:province":"NY",
    "sg:tags":[
        "security"
    ],
    "wof:name":"Morgan Stanley",
    "wof:placetype":"venue"
},
  "geometry": {"coordinates":[-73.598724,40.875746],"type":"Point"}
}