{
  "type": "Feature",
  "properties": {
    "iso:country":"US",
    "sg:address":"405 Park Ave Ste 502",
    "sg:city":"New York",
    "sg:classifiers":[
        {
            "category":"Professional",
            "subcategory":"Lawyer & Legal Services",
            "type":"Services"
        }
    ],
    "sg:phone":"+1 212 754 7000",
    "sg:postcode":"10022",
    "sg:province":"NY",
    "wof:name":"Danziger & Danziger Atty",
    "wof:placetype":"venue"
},
  "geometry": {"coordinates":[-73.971653,40.75973],"type":"Point"}
}