{
  "type": "Feature",
  "properties": {
    "iso:country":"US",
    "sg:address":"38 Broadway",
    "sg:city":"Greenlawn",
    "sg:classifiers":[
        {
            "category":"Professional",
            "subcategory":"Secretarial Services",
            "type":"Services"
        }
    ],
    "sg:phone":"+1 631 754 0355",
    "sg:postcode":"11740",
    "sg:province":"NY",
    "sg:tags":[
        "reporting",
        "court"
    ],
    "wof:name":"Island Business Svc Ctr",
    "wof:placetype":"venue"
},
  "geometry": {"coordinates":[-73.36568,40.871339],"type":"Point"}
}