{
  "type": "Feature",
  "properties": {
    "addr:full":"104 Taberg St Camden NY 13316",
    "addr:housenumber":"104",
    "addr:postcode":"13316",
    "addr:street":"Taberg St",
    "iso:country":"US",
    "sg:address":"104 Taberg St",
    "sg:city":"Camden",
    "sg:classifiers":[
        {
            "category":"Health Services",
            "subcategory":"Podiatrist",
            "type":"Services"
        }
    ],
    "sg:phone":"+1 315 245 0232",
    "sg:postcode":"13316",
    "sg:province":"NY",
    "wof:name":"Absolute Foot Care",
    "wof:placetype":"venue"
},
  "geometry": {"coordinates":[-75.736301,43.336095],"type":"Point"}
}