{
  "type": "Feature",
  "properties": {
    "addr:full":"86 Nancy St West Babylon NY 11704",
    "addr:housenumber":"86",
    "addr:postcode":"11704",
    "addr:street":"Nancy St",
    "iso:country":"US",
    "sg:address":"86 Nancy St",
    "sg:city":"West Babylon",
    "sg:classifiers":[
        {
            "category":"Manufacturing",
            "subcategory":"Tools & Machinery",
            "type":"Manufacturing & Wholesale Goods"
        }
    ],
    "sg:phone":"+1 631 643 1111",
    "sg:postcode":"11704",
    "sg:province":"NY",
    "sg:tags":[
        "machine",
        "shop"
    ],
    "wof:name":"RGH Assoc Inc",
    "wof:placetype":"venue"
},
  "geometry": {"coordinates":[-73.37596600000001,40.738312],"type":"Point"}
}