{
  "type": "Feature",
  "properties": {
    "iso:country":"US",
    "sg:address":"8 Hofstra Dr",
    "sg:city":"Farmingville",
    "sg:classifiers":[
        {
            "category":"Building & Trades",
            "subcategory":"Construction",
            "type":"Services"
        }
    ],
    "sg:phone":"+1 631 736 0983",
    "sg:postcode":"11738",
    "sg:province":"NY",
    "sg:tags":[
        "concrete",
        "contractor"
    ],
    "wof:name":"Springstone Concrete Inc",
    "wof:placetype":"venue"
},
  "geometry": {"coordinates":[-73.048226,40.838831],"type":"Point"}
}