{
  "type": "Feature",
  "properties": {
    "iso:country":"US",
    "sg:address":"315 W 39 St",
    "sg:city":"New York",
    "sg:classifiers":[
        {
            "category":"Professional",
            "type":"Services"
        }
    ],
    "sg:phone":"+1 212 564 8248",
    "sg:postcode":"10018",
    "sg:province":"NY",
    "sg:tags":[
        "establishment"
    ],
    "wof:name":"Logan Productions",
    "wof:placetype":"venue"
},
  "geometry": {"coordinates":[-73.993675,40.756422],"type":"Point"}
}