{
  "type": "Feature",
  "properties": {
    "iso:country":"US",
    "sg:address":"143 Ruskin Rd",
    "sg:city":"Buffalo",
    "sg:classifiers":[
        {
            "category":"Professional",
            "subcategory":"Detective & Security Services",
            "type":"Services"
        }
    ],
    "sg:phone":"+1 716 838 9771",
    "sg:postcode":"14226",
    "sg:province":"NY",
    "sg:tags":[
        "consulting",
        "investigation",
        "private"
    ],
    "wof:name":"Amherst Prof Investigation",
    "wof:placetype":"venue"
},
  "geometry": {"coordinates":[-78.79517,42.961992],"type":"Point"}
}