{
  "type": "Feature",
  "properties": {
    "addr:full":"1350 Fairport Rd Fairport NY 14450",
    "addr:housenumber":"1350",
    "addr:postcode":"14450",
    "addr:street":"Fairport Rd",
    "iso:country":"US",
    "sg:address":"1350 Fairport Rd",
    "sg:city":"Fairport",
    "sg:classifiers":[
        {
            "category":"Building & Trades",
            "subcategory":"Construction",
            "type":"Services"
        }
    ],
    "sg:phone":"+1 585 421 0880",
    "sg:postcode":"14450",
    "sg:province":"NY",
    "sg:tags":[
        "roofing",
        "contractor"
    ],
    "sg:website":"www.ontarioexteriors.com",
    "wof:name":"Ontario Exteriors Inc",
    "wof:placetype":"venue"
},
  "geometry": {"coordinates":[-77.46108099999999,43.101429],"type":"Point"}
}