{
  "type": "Feature",
  "properties": {
    "addr:full":"4025 82nd St Elmhurst NY 11373",
    "addr:housenumber":"4025",
    "addr:postcode":"11373",
    "addr:street":"82Nd St",
    "iso:country":"US",
    "sg:address":"4025 82nd St",
    "sg:city":"Elmhurst",
    "sg:classifiers":[
        {
            "category":"Restaurant",
            "type":"Food & Drink"
        }
    ],
    "sg:phone":"+1 718 205 6860",
    "sg:postcode":"11373",
    "sg:province":"NY",
    "sg:tags":[
        "pizza"
    ],
    "wof:name":"Kumar Pizzeria Llc",
    "wof:placetype":"venue"
},
  "geometry": {"coordinates":[-73.88363200000001,40.746983],"type":"Point"}
}