{
  "type": "Feature",
  "properties": {
    "iso:country":"US",
    "sg:address":"111 W Nicholai St",
    "sg:city":"Hicksville",
    "sg:classifiers":[
        {
            "category":"Health Services",
            "subcategory":"Chiropractor",
            "type":"Services"
        }
    ],
    "sg:phone":"+1   ",
    "sg:postcode":"11801",
    "sg:province":"NY",
    "wof:name":"Alyn Barbara",
    "wof:placetype":"venue"
},
  "geometry": {"coordinates":[-73.52649099999999,40.764454],"type":"Point"}
}