{
  "type": "Feature",
  "properties": {
    "addr:full":"219 Dale Rd Rome NY 13440",
    "addr:housenumber":"219",
    "addr:postcode":"13440",
    "addr:street":"Dale Rd",
    "iso:country":"US",
    "sg:address":"219 Dale Rd",
    "sg:city":"Rome",
    "sg:classifiers":[
        {
            "category":"Building & Trades",
            "subcategory":"Landscaping Services",
            "type":"Services"
        }
    ],
    "sg:phone":"+1 315 339 6336",
    "sg:postcode":"13440",
    "sg:province":"NY",
    "sg:tags":[
        "landscape"
    ],
    "wof:name":"Four Seasons Landscaping",
    "wof:placetype":"venue"
},
  "geometry": {"coordinates":[-75.45425899999999,43.256458],"type":"Point"}
}