{
  "type": "Feature",
  "properties": {
    "addr:full":"43 Washington Ave Endicott NY 13760",
    "addr:housenumber":"43",
    "addr:postcode":"13760",
    "addr:street":"Washington Ave",
    "iso:country":"US",
    "sg:address":"43 Washington Ave",
    "sg:city":"Endicott",
    "sg:classifiers":[
        {
            "category":"Banks & Credit Unions",
            "subcategory":"Bank",
            "type":"Services"
        }
    ],
    "sg:phone":"+1 607 779 3595",
    "sg:postcode":"13760",
    "sg:province":"NY",
    "sg:website":"www.partnerstrustbank.com",
    "wof:name":"Investment Centers Of America",
    "wof:placetype":"venue"
},
  "geometry": {"coordinates":[-76.04817799999999,42.103452],"type":"Point"}
}