{
  "type": "Feature",
  "properties": {
    "addr:full":"44 High St Hastings On Hudson NY 10706",
    "addr:housenumber":"44",
    "addr:postcode":"10706",
    "addr:street":"High St",
    "iso:country":"US",
    "sg:address":"44 High St",
    "sg:city":"Hastings On Hudson",
    "sg:classifiers":[
        {
            "category":"Building & Trades",
            "subcategory":"Construction",
            "type":"Services"
        }
    ],
    "sg:phone":"+1 914 478 0006",
    "sg:postcode":"10706",
    "sg:province":"NY",
    "sg:tags":[
        "carpentry",
        "carpenter",
        "contractor"
    ],
    "wof:name":"Ronald Paquette & Sons Inc",
    "wof:placetype":"venue"
},
  "geometry": {"coordinates":[-73.873214,40.984514],"type":"Point"}
}