{
  "type": "Feature",
  "properties": {
    "addr:full":"20 Health St Dansville NY 14437",
    "addr:housenumber":"20",
    "addr:postcode":"14437",
    "addr:street":"Health St",
    "iso:country":"US",
    "sg:address":"20 Health St",
    "sg:city":"Dansville",
    "sg:classifiers":[
        {
            "category":"Social Services",
            "subcategory":"Child Care",
            "type":"Services"
        }
    ],
    "sg:phone":"+1 585 335 7962",
    "sg:postcode":"14437",
    "sg:province":"NY",
    "sg:tags":[
        "nursery",
        "day"
    ],
    "wof:name":"Dansville Children Center Inc",
    "wof:placetype":"venue"
},
  "geometry": {"coordinates":[-77.68825,42.564032],"type":"Point"}
}