{
  "type": "Feature",
  "properties": {
    "addr:full":"1 Columbus Pl New York NY 10079",
    "addr:housenumber":"1",
    "addr:postcode":"10079",
    "addr:street":"Columbus Pl",
    "iso:country":"US",
    "sg:address":"1 Columbus Pl",
    "sg:city":"New York",
    "sg:classifiers":[
        {
            "category":"Personal",
            "subcategory":"Massage",
            "type":"Services"
        },
        {
            "category":"Personal",
            "subcategory":"Hair Removal",
            "type":"Services"
        },
        {
            "category":"Personal",
            "subcategory":"Day Spa",
            "type":"Services"
        }
    ],
    "sg:phone":"+1 866 651 3529",
    "sg:postcode":"10079",
    "sg:province":"NY",
    "sg:website":"www.bodywork411.com/massage-New%...",
    "wof:name":"New York Massage Bodywork411",
    "wof:placetype":"venue"
},
  "geometry": {"coordinates":[-73.98474299999999,40.769242],"type":"Point"}
}