{
  "type": "Feature",
  "properties": {
    "addr:full":"10708 Rockaway Boulevard Ozone Park NY 11417",
    "addr:housenumber":"10708",
    "addr:postcode":"11417",
    "addr:street":"Rockaway Boulevard",
    "iso:country":"US",
    "sg:address":"10708 Rockaway Boulevard",
    "sg:city":"Ozone Park",
    "sg:classifiers":[
        {
            "category":"Education",
            "subcategory":"Kindergarten",
            "type":"Public Place"
        }
    ],
    "sg:phone":"+1 718 322 3434",
    "sg:postcode":"11417",
    "sg:province":"NY",
    "sg:tags":[
        "school",
        "driving"
    ],
    "wof:name":"All Roads Driving School",
    "wof:placetype":"venue"
},
  "geometry": {"coordinates":[-73.83178599999999,40.678135],"type":"Point"}
}