{
  "type": "Feature",
  "properties": {
    "addr:full":"777 7 Ave New York NY 10019",
    "addr:housenumber":"777",
    "addr:postcode":"10019",
    "addr:street":"7 Ave",
    "iso:country":"US",
    "sg:address":"777 7 Ave",
    "sg:city":"New York",
    "sg:classifiers":[
        {
            "category":"Retail",
            "subcategory":"Auto Repair",
            "type":"Services"
        }
    ],
    "sg:phone":"+1 917 289 3779",
    "sg:postcode":"10019",
    "sg:province":"NY",
    "sg:tags":[
        "wrecker"
    ],
    "wof:name":"24 All Day Emergency Towing",
    "wof:placetype":"venue"
},
  "geometry": {"coordinates":[-73.98372999999999,40.760456],"type":"Point"}
}