{
  "type": "Feature",
  "properties": {
    "iso:country":"US",
    "sg:address":"866 E Tremont Ave",
    "sg:city":"Bronx",
    "sg:classifiers":[
        {
            "category":"Food & Beverages",
            "subcategory":"Groceries & Convenience Stores",
            "type":"Retail Goods"
        }
    ],
    "sg:phone":"+1 718 860 6299",
    "sg:postcode":"10460",
    "sg:province":"NY",
    "wof:name":"Kids Bargain Inc",
    "wof:placetype":"venue"
},
  "geometry": {"coordinates":[-73.886178,40.842961],"type":"Point"}
}