{
  "type": "Feature",
  "properties": {
    "iso:country":"US",
    "sg:address":"876 Willis Ave",
    "sg:city":"Albertson",
    "sg:classifiers":[
        {
            "category":"Health Services",
            "subcategory":"Medical Lab",
            "type":"Services"
        }
    ],
    "sg:phone":"+1 516 747 6464",
    "sg:postcode":"11507",
    "sg:province":"NY",
    "sg:tags":[
        "laboratory"
    ],
    "wof:name":"Quest Diagnotics",
    "wof:placetype":"venue"
},
  "geometry": {"coordinates":[-73.64896,40.772093],"type":"Point"}
}