{
  "type": "Feature",
  "properties": {
    "addr:full":"1585 Broadway New York NY 10036",
    "addr:housenumber":"1585",
    "addr:postcode":"10036",
    "addr:street":"Broadway",
    "iso:country":"US",
    "sg:address":"1585 Broadway",
    "sg:city":"New York",
    "sg:classifiers":[
        {
            "category":"Professional",
            "subcategory":"Lawyer & Legal Services",
            "type":"Services"
        }
    ],
    "sg:phone":"+1 212 969 3138",
    "sg:postcode":"10036",
    "sg:province":"NY",
    "wof:name":"Coles Anthony C Lwyr",
    "wof:placetype":"venue"
},
  "geometry": {"coordinates":[-73.985001,40.759602],"type":"Point"}
}