{
  "type": "Feature",
  "properties": {
    "iso:country":"US",
    "sg:address":"115 Lilac Park Dr",
    "sg:city":"Mannsville",
    "sg:classifiers":[
        {
            "category":"Real Estate",
            "subcategory":"Real Estate Agent",
            "type":"Services"
        }
    ],
    "sg:phone":"+1 315 465 4650",
    "sg:postcode":"13661",
    "sg:province":"NY",
    "wof:name":"More Real Estate LLC",
    "wof:placetype":"venue"
},
  "geometry": {"coordinates":[-76.06604299999999,43.711915],"type":"Point"}
}