{
  "type": "Feature",
  "properties": {
    "addr:full":"41 Quaker St Granville NY 12832",
    "addr:housenumber":"41",
    "addr:postcode":"12832",
    "addr:street":"Quaker St",
    "iso:country":"US",
    "sg:address":"41 Quaker St",
    "sg:city":"Granville",
    "sg:classifiers":[
        {
            "category":"Home & Garden",
            "subcategory":"Hardware",
            "type":"Retail Goods"
        }
    ],
    "sg:phone":"+1   ",
    "sg:postcode":"12832",
    "sg:province":"NY",
    "wof:name":"True Value",
    "wof:placetype":"venue"
},
  "geometry": {"coordinates":[-73.265885,43.403154],"type":"Point"}
}