{
  "type": "Feature",
  "properties": {
    "iso:country":"US",
    "sg:address":"20 W 37th St",
    "sg:city":"New York",
    "sg:classifiers":[
        {
            "category":"Manufacturing",
            "subcategory":"Retail Goods",
            "type":"Manufacturing & Wholesale Goods"
        }
    ],
    "sg:phone":"+1 212 947 3770",
    "sg:postcode":"10018",
    "sg:province":"NY",
    "sg:tags":[
        "manufacturer"
    ],
    "wof:name":"Ciner Manufacturing",
    "wof:placetype":"venue"
},
  "geometry": {"coordinates":[-73.98597599999999,40.75138],"type":"Point"}
}