{
  "type": "Feature",
  "properties": {
    "addr:full":"8095 Sheridan Dr Buffalo NY 14221",
    "addr:housenumber":"8095",
    "addr:postcode":"14221",
    "addr:street":"Sheridan Dr",
    "iso:country":"US",
    "sg:address":"8095 Sheridan Dr",
    "sg:city":"Buffalo",
    "sg:classifiers":[
        {
            "category":"Health Services",
            "subcategory":"Doctor",
            "type":"Services"
        }
    ],
    "sg:phone":"+1 716 633 1076",
    "sg:postcode":"14221",
    "sg:province":"NY",
    "sg:tags":[
        "physician",
        "medical",
        "surgeon"
    ],
    "wof:name":"Aesthetic Plastic Surgery Ctr",
    "wof:placetype":"venue"
},
  "geometry": {"coordinates":[-78.69613,42.978119],"type":"Point"}
}