{
  "type": "Feature",
  "properties": {
    "addr:full":"131 Sherman Rd Ellenville NY 12428",
    "addr:housenumber":"131",
    "addr:postcode":"12428",
    "addr:street":"Sherman Rd",
    "iso:country":"US",
    "sg:address":"131 Sherman Rd",
    "sg:city":"Ellenville",
    "sg:classifiers":[
        {
            "category":"Building & Trades",
            "subcategory":"Landscaping Services",
            "type":"Services"
        }
    ],
    "sg:phone":"+1 845 985 0584",
    "sg:postcode":"12428",
    "sg:province":"NY",
    "sg:tags":[
        "tree"
    ],
    "wof:name":"Touch & Go Tree Svc",
    "wof:placetype":"venue"
},
  "geometry": {"coordinates":[-74.48101,41.77488],"type":"Point"}
}