{
  "type": "Feature",
  "properties": {
    "iso:country":"US",
    "sg:address":"7 Willowdale Ave",
    "sg:city":"Port Washington",
    "sg:classifiers":[
        {
            "category":"Social Services",
            "subcategory":"Child Care",
            "type":"Services"
        }
    ],
    "sg:phone":"+1 516 767 6703",
    "sg:postcode":"11050",
    "sg:province":"NY",
    "sg:tags":[
        "day"
    ],
    "wof:name":"Imagine Early Learning Cntr",
    "wof:placetype":"venue"
},
  "geometry": {"coordinates":[-73.68849899999999,40.8251],"type":"Point"}
}