{
  "type": "Feature",
  "properties": {
    "iso:country":"US",
    "sg:address":"901 E 6 St",
    "sg:city":"New York",
    "sg:classifiers":[
        {
            "category":"Health Services",
            "subcategory":"Optometrist",
            "type":"Services"
        }
    ],
    "sg:phone":"+1 212 967 4177",
    "sg:postcode":"10009",
    "sg:province":"NY",
    "sg:website":"www.lenscrafters.com",
    "wof:name":"Herald Sqr Optometric Assc PC",
    "wof:placetype":"venue"
},
  "geometry": {"coordinates":[-73.975959,40.722223],"type":"Point"}
}