{
  "type": "Feature",
  "properties": {
    "iso:country":"US",
    "sg:address":"392 Eastview Mall",
    "sg:city":"Victor",
    "sg:classifiers":[
        {
            "category":"Personal",
            "subcategory":"Beauty Salon",
            "type":"Services"
        },
        {
            "category":"Personal",
            "subcategory":"Barber",
            "type":"Services"
        }
    ],
    "sg:phone":"+1 585 223 8040",
    "sg:postcode":"14564",
    "sg:province":"NY",
    "sg:tags":[
        "hair",
        "stylist"
    ],
    "sg:website":"http://www.mastercuts.com",
    "wof:name":"MasterCuts",
    "wof:placetype":"venue"
},
  "geometry": {"coordinates":[-77.449671,43.029288],"type":"Point"}
}