{
  "type": "Feature",
  "properties": {
    "iso:country":"US",
    "sg:address":"8408 N Main St",
    "sg:city":"Eden",
    "sg:classifiers":[
        {
            "category":"Sports & Exercise",
            "subcategory":"Gym",
            "type":"Entertainment"
        }
    ],
    "sg:phone":"+1 716 992 2909",
    "sg:postcode":"14057",
    "sg:province":"NY",
    "sg:tags":[
        "club",
        "health",
        "studio",
        "gymnasium"
    ],
    "wof:name":"Curves",
    "wof:placetype":"venue"
},
  "geometry": {"coordinates":[-78.89421900000001,42.657784],"type":"Point"}
}