{
  "type": "Feature",
  "properties": {
    "addr:full":"PO Box 1058 Manhasset NY 11030",
    "addr:housenumber":"po;1058",
    "addr:postcode":"11030",
    "addr:street":"Box",
    "iso:country":"US",
    "sg:address":"PO Box 1058",
    "sg:city":"Manhasset",
    "sg:classifiers":[
        {
            "category":"Building & Trades",
            "subcategory":"Electrical",
            "type":"Services"
        }
    ],
    "sg:phone":"+1 516 869 8410",
    "sg:postcode":"11030",
    "sg:province":"NY",
    "sg:tags":[
        "electrician"
    ],
    "wof:name":"Jenco Electric Inc",
    "wof:placetype":"venue"
},
  "geometry": {"coordinates":[-73.690102,40.795799],"type":"Point"}
}