{
  "type": "Feature",
  "properties": {
    "addr:full":"6804 20th Ave Brooklyn NY 11204",
    "addr:housenumber":"6804",
    "addr:postcode":"11204",
    "addr:street":"20Th Ave",
    "iso:country":"US",
    "sg:address":"6804 20th Ave",
    "sg:city":"Brooklyn",
    "sg:classifiers":[
        {
            "category":"Personal",
            "subcategory":"Skin Care",
            "type":"Services"
        },
        {
            "category":"Personal",
            "subcategory":"Nail Salon",
            "type":"Services"
        }
    ],
    "sg:phone":"+1 718 256 3581",
    "sg:postcode":"11204",
    "sg:province":"NY",
    "wof:name":"Yin's Beauty & Spa",
    "wof:placetype":"venue"
},
  "geometry": {"coordinates":[-73.987819,40.614855],"type":"Point"}
}