{
  "type": "Feature",
  "properties": {
    "addr:full":"1117 Michigan Ave Niagara Falls NY 14305",
    "addr:housenumber":"1117",
    "addr:postcode":"14305",
    "addr:street":"Michigan Ave",
    "iso:country":"US",
    "sg:address":"1117 Michigan Ave",
    "sg:city":"Niagara Falls",
    "sg:classifiers":[
        {
            "category":"Social Services",
            "type":"Services"
        }
    ],
    "sg:phone":"+1 716 282 7588",
    "sg:postcode":"14305",
    "sg:province":"NY",
    "sg:tags":[
        "organization",
        "welfare"
    ],
    "wof:name":"Center For Joy",
    "wof:placetype":"venue"
},
  "geometry": {"coordinates":[-79.04697299999999,43.104543],"type":"Point"}
}