{
  "type": "Feature",
  "properties": {
    "addr:full":"831 Bartholdi St Bronx NY 10467",
    "addr:housenumber":"831",
    "addr:postcode":"10467",
    "addr:street":"Bartholdi St",
    "iso:country":"US",
    "sg:address":"831 Bartholdi St",
    "sg:city":"Bronx",
    "sg:classifiers":[
        {
            "category":"Professional",
            "type":"Services"
        }
    ],
    "sg:phone":"+1 718 654 4057",
    "sg:postcode":"10467",
    "sg:province":"NY",
    "sg:tags":[
        "establishment"
    ],
    "wof:name":"Stevenson Towers",
    "wof:placetype":"venue"
},
  "geometry": {"coordinates":[-73.861654,40.873799],"type":"Point"}
}