{
  "type": "Feature",
  "properties": {
    "addr:full":"7 Green Rd Monroe NY 10950",
    "addr:housenumber":"7",
    "addr:postcode":"10950",
    "addr:street":"Green Rd",
    "iso:country":"US",
    "sg:address":"7 Green Rd",
    "sg:city":"Monroe",
    "sg:classifiers":[
        {
            "category":"Building & Trades",
            "subcategory":"Landscaping Services",
            "type":"Services"
        }
    ],
    "sg:phone":"+1 845 783 2290",
    "sg:postcode":"10950",
    "sg:province":"NY",
    "wof:name":"Landscaping Plus Property Mgt",
    "wof:placetype":"venue"
},
  "geometry": {"coordinates":[-74.18174399999999,41.365436],"type":"Point"}
}