{
  "type": "Feature",
  "properties": {
    "iso:country":"US",
    "sg:address":"270 Lafayette St Ste 1002",
    "sg:city":"New York",
    "sg:classifiers":[
        {
            "category":"Real Estate",
            "subcategory":"Architect",
            "type":"Services"
        }
    ],
    "sg:phone":"+1 212 625 3125",
    "sg:postcode":"10012",
    "sg:province":"NY",
    "wof:name":"Reddymade Design",
    "wof:placetype":"venue"
},
  "geometry": {"coordinates":[-73.996595,40.723771],"type":"Point"}
}