{
  "type": "Feature",
  "properties": {
    "iso:country":"US",
    "sg:address":"7007 Myrtle Ave",
    "sg:city":"Glendale",
    "sg:classifiers":[
        {
            "category":"Bakery",
            "type":"Food & Drink"
        },
        {
            "category":"Coffee & Tea",
            "type":"Food & Drink"
        },
        {
            "category":"Bagels",
            "type":"Food & Drink"
        },
        {
            "category":"Donuts",
            "type":"Food & Drink"
        }
    ],
    "sg:menulink":"http://www.allmenus.com/ny/queens/138662-dunkin-donuts/menu/",
    "sg:phone":"+1 518 370 2840",
    "sg:postcode":"11385",
    "sg:province":"NY",
    "sg:tags":[
        "american",
        "pastry"
    ],
    "wof:name":"Dunkin' Donuts",
    "wof:placetype":"venue"
},
  "geometry": {"coordinates":[-73.880961,40.701938],"type":"Point"}
}