{
  "type": "Feature",
  "properties": {
    "addr:full":"42 Amherst Ln Wappingers Falls NY 12590",
    "addr:housenumber":"42",
    "addr:postcode":"12590",
    "addr:street":"Amherst Ln",
    "iso:country":"US",
    "sg:address":"42 Amherst Ln",
    "sg:city":"Wappingers Falls",
    "sg:classifiers":[
        {
            "category":"Freight",
            "type":"Transportation"
        }
    ],
    "sg:phone":"+1   ",
    "sg:postcode":"12590",
    "sg:province":"NY",
    "sg:tags":[
        "operator",
        "local",
        "trucking"
    ],
    "wof:name":"Scotts Delivery Service",
    "wof:placetype":"venue"
},
  "geometry": {"coordinates":[-73.936615,41.576528],"type":"Point"}
}