{
  "type": "Feature",
  "properties": {
    "iso:country":"US",
    "sg:address":"79 E Jericho Tpke",
    "sg:city":"Mineola",
    "sg:classifiers":[
        {
            "category":"Building & Trades",
            "subcategory":"Cleaning & Sanitation",
            "type":"Services"
        },
        {
            "category":"Home & Garden",
            "subcategory":"Carpets & Floor Coverings",
            "type":"Retail Goods"
        }
    ],
    "sg:phone":"+1 646 763 8806",
    "sg:postcode":"11501",
    "sg:province":"NY",
    "sg:tags":[
        "carpeting"
    ],
    "sg:website":"www.cleaningcitycarpets.com",
    "wof:name":"Cleaning City Carpets",
    "wof:placetype":"venue"
},
  "geometry": {"coordinates":[-73.63164999999999,40.7523],"type":"Point"}
}