{
  "type": "Feature",
  "properties": {
    "iso:country":"US",
    "sg:address":"1164 Ridge Rd E",
    "sg:city":"Rochester",
    "sg:classifiers":[
        {
            "category":"Personal",
            "subcategory":"Beauty Salon",
            "type":"Services"
        }
    ],
    "sg:phone":"+1 585 342 3220",
    "sg:postcode":"14621",
    "sg:province":"NY",
    "wof:name":"Mr & Miz Hair Bazaar",
    "wof:placetype":"venue"
},
  "geometry": {"coordinates":[-77.58781500000001,43.197333],"type":"Point"}
}