{
  "type": "Feature",
  "properties": {
    "addr:full":"1257 Bedford Ave Brooklyn NY 11216",
    "addr:housenumber":"1257",
    "addr:postcode":"11216",
    "addr:street":"Bedford Ave",
    "iso:country":"US",
    "sg:address":"1257 Bedford Ave",
    "sg:city":"Brooklyn",
    "sg:classifiers":[
        {
            "category":"Shopping",
            "subcategory":"Beauty & Cosmetics",
            "type":"Retail Goods"
        }
    ],
    "sg:phone":"+1   ",
    "sg:postcode":"11216",
    "sg:province":"NY",
    "sg:tags":[
        "item",
        "oil",
        "various",
        "gift"
    ],
    "wof:name":"Musk and Gift Inc",
    "wof:placetype":"venue"
},
  "geometry": {"coordinates":[-73.953146,40.679936],"type":"Point"}
}