{
  "type": "Feature",
  "properties": {
    "addr:full":"54 W 39 St New York NY 10018",
    "addr:housenumber":"54",
    "addr:postcode":"10018",
    "addr:street":"W 39 St",
    "iso:country":"US",
    "sg:address":"54 W 39 St",
    "sg:city":"New York",
    "sg:classifiers":[
        {
            "category":"Professional",
            "subcategory":"Engineering",
            "type":"Services"
        }
    ],
    "sg:phone":"+1 212 221 6803",
    "sg:postcode":"10018",
    "sg:province":"NY",
    "wof:name":"Kunstadt Herbert Associates PC",
    "wof:placetype":"venue"
},
  "geometry": {"coordinates":[-73.984206,40.752134],"type":"Point"}
}