{
  "type": "Feature",
  "properties": {
    "addr:full":"754 Deer Park Ave North Babylon NY 11703",
    "addr:housenumber":"754",
    "addr:postcode":"11703",
    "addr:street":"Deer Park Ave North",
    "iso:country":"US",
    "sg:address":"754 Deer Park Ave",
    "sg:city":"North Babylon",
    "sg:classifiers":[
        {
            "category":"Health Services",
            "subcategory":"Doctor",
            "type":"Services"
        }
    ],
    "sg:phone":"+1 631 661 1200",
    "sg:postcode":"11703",
    "sg:province":"NY",
    "sg:tags":[
        "physician",
        "surgeon",
        "medical"
    ],
    "wof:name":"Jason Hitner MD",
    "wof:placetype":"venue"
},
  "geometry": {"coordinates":[-73.32241399999999,40.719695],"type":"Point"}
}