{
  "type": "Feature",
  "properties": {
    "iso:country":"US",
    "sg:address":"2185 Clinton Ave S",
    "sg:city":"Rochester",
    "sg:classifiers":[
        {
            "category":"Restaurant",
            "type":"Food & Drink"
        }
    ],
    "sg:menulink":"http://www.allmenus.com/ny/brighton/253662-red-osier-catering/menu/",
    "sg:phone":"+1 585 467 5090",
    "sg:postcode":"14618",
    "sg:province":"NY",
    "sg:tags":[
        "sandwich",
        "salad",
        "seafood",
        "soup",
        "american",
        "chicken"
    ],
    "wof:name":"Red Osier Catering",
    "wof:placetype":"venue"
},
  "geometry": {"coordinates":[-77.596695,43.116162],"type":"Point"}
}