{
  "type": "Feature",
  "properties": {
    "iso:country":"US",
    "sg:address":"7718 14th Avenue",
    "sg:city":"Brooklyn",
    "sg:classifiers":[
        {
            "category":"Building & Trades",
            "subcategory":"Pest Control",
            "type":"Services"
        }
    ],
    "sg:phone":"+1 718 331 7633",
    "sg:postcode":"11228",
    "sg:province":"NY",
    "wof:name":"On Target Exterminating Svc",
    "wof:placetype":"venue"
},
  "geometry": {"coordinates":[-74.006939,40.61752],"type":"Point"}
}