{
  "type": "Feature",
  "properties": {
    "addr:full":"20 Vandam St Fl 4 New York NY 10013",
    "addr:housenumber":"20;4",
    "addr:postcode":"10013",
    "addr:street":"Vandam St",
    "iso:country":"US",
    "sg:address":"20 Vandam St Fl 4",
    "sg:city":"New York",
    "sg:classifiers":[
        {
            "category":"Wholesale",
            "subcategory":"Stationery",
            "type":"Manufacturing & Wholesale Goods"
        }
    ],
    "sg:phone":"+1 212 243 9661",
    "sg:postcode":"10013",
    "sg:province":"NY",
    "sg:tags":[
        "card"
    ],
    "wof:name":"Rockshots Inc",
    "wof:placetype":"venue"
},
  "geometry": {"coordinates":[-74.0047,40.726299],"type":"Point"}
}