{
  "type": "Feature",
  "properties": {
    "iso:country":"US",
    "sg:address":"31 W Merrick Rd",
    "sg:city":"Freeport",
    "sg:classifiers":[
        {
            "category":"Shopping",
            "subcategory":"Bicycles & Sporting Goods",
            "type":"Retail Goods"
        }
    ],
    "sg:phone":"+1   ",
    "sg:postcode":"11520",
    "sg:province":"NY",
    "wof:name":"Freeport Bicycle Store",
    "wof:placetype":"venue"
},
  "geometry": {"coordinates":[-73.58362099999999,40.653645],"type":"Point"}
}