{
  "type": "Feature",
  "properties": {
    "addr:full":"7 Willis Ct Hicksville NY 11801",
    "addr:housenumber":"7",
    "addr:postcode":"11801",
    "addr:street":"Willis Ct",
    "iso:country":"US",
    "sg:address":"7 Willis Ct",
    "sg:city":"Hicksville",
    "sg:classifiers":[
        {
            "category":"Building & Trades",
            "subcategory":"Construction",
            "type":"Services"
        }
    ],
    "sg:phone":"+1 516 681 5127",
    "sg:postcode":"11801",
    "sg:province":"NY",
    "sg:tags":[
        "specializing",
        "steel",
        "contractor",
        "painting",
        "structural"
    ],
    "wof:name":"Voyage Contracting Corp",
    "wof:placetype":"venue"
},
  "geometry": {"coordinates":[-73.505156,40.745737],"type":"Point"}
}