{
  "type": "Feature",
  "properties": {
    "addr:full":"82 Warwick Brook Rd Tuxedo Park NY 10987",
    "addr:housenumber":"82",
    "addr:postcode":"10987",
    "addr:street":"Warwick Brook Rd",
    "iso:country":"US",
    "sg:address":"82 Warwick Brook Rd",
    "sg:city":"Tuxedo Park",
    "sg:classifiers":[
        {
            "category":"Building & Trades",
            "subcategory":"Plumbing",
            "type":"Services"
        }
    ],
    "sg:phone":"+1 845 425 5632",
    "sg:postcode":"10987",
    "sg:province":"NY",
    "sg:tags":[
        "contractor"
    ],
    "wof:name":"Timothy L Ross Plumbing & Heat",
    "wof:placetype":"venue"
},
  "geometry": {"coordinates":[-74.197766,41.222301],"type":"Point"}
}