{
  "type": "Feature",
  "properties": {
    "addr:full":"739 Clinton Ave S Rochester NY 14620",
    "addr:housenumber":"739",
    "addr:postcode":"14620",
    "addr:street":"Clinton Ave S",
    "iso:country":"US",
    "sg:address":"739 Clinton Ave S",
    "sg:city":"Rochester",
    "sg:classifiers":[
        {
            "category":"Wholesale",
            "subcategory":"Hardware",
            "type":"Manufacturing & Wholesale Goods"
        }
    ],
    "sg:phone":"+1 585 244 8840",
    "sg:postcode":"14620",
    "sg:province":"NY",
    "sg:tags":[
        "equipment",
        "heating",
        "system"
    ],
    "sg:website":"www.wardsupply.com",
    "wof:name":"Ward Supply Co Inc",
    "wof:placetype":"venue"
},
  "geometry": {"coordinates":[-77.598506,43.142188],"type":"Point"}
}