{
  "type": "Feature",
  "properties": {
    "iso:country":"US",
    "sg:address":"17 Executive Park Dr",
    "sg:city":"Albany",
    "sg:classifiers":[
        {
            "category":"Banks & Credit Unions",
            "subcategory":"Investment Brokerage",
            "type":"Services"
        }
    ],
    "sg:phone":"+1 518 383 6018",
    "sg:postcode":"12203",
    "sg:province":"NY",
    "sg:tags":[
        "advisory",
        "financial"
    ],
    "wof:name":"ORD Financial Svc Inc",
    "wof:placetype":"venue"
},
  "geometry": {"coordinates":[-73.840102,42.685621],"type":"Point"}
}