{
  "type": "Feature",
  "properties": {
    "addr:full":"556 39th St Brooklyn NY 11232",
    "addr:housenumber":"556",
    "addr:postcode":"11232",
    "addr:street":"39Th St",
    "iso:country":"US",
    "sg:address":"556 39th St",
    "sg:city":"Brooklyn",
    "sg:classifiers":[
        {
            "category":"Building & Trades",
            "subcategory":"Construction",
            "type":"Services"
        }
    ],
    "sg:phone":"+1 718 851 4200",
    "sg:postcode":"11232",
    "sg:province":"NY",
    "sg:tags":[
        "designer",
        "marine",
        "contractor"
    ],
    "sg:website":"www.acmeproductsonline.com",
    "wof:name":"Acme Products & Engr Inc",
    "wof:placetype":"venue"
},
  "geometry": {"coordinates":[-74.00270999999999,40.650639],"type":"Point"}
}