{
  "type": "Feature",
  "properties": {
    "addr:full":"62 Erasmus St Brooklyn NY 11226",
    "addr:housenumber":"62",
    "addr:postcode":"11226",
    "addr:street":"Erasmus St",
    "iso:country":"US",
    "sg:address":"62 Erasmus St",
    "sg:city":"Brooklyn",
    "sg:classifiers":[
        {
            "category":"Social Services",
            "subcategory":"Child Care",
            "type":"Services"
        }
    ],
    "sg:phone":"+1   ",
    "sg:postcode":"11226",
    "sg:province":"NY",
    "sg:tags":[
        "day"
    ],
    "wof:name":"Parris Child Care Service",
    "wof:placetype":"venue"
},
  "geometry": {"coordinates":[-73.953271,40.649548],"type":"Point"}
}