{
  "type": "Feature",
  "properties": {
    "addr:full":"351 N High St Mount Vernon NY 10550",
    "addr:housenumber":"351",
    "addr:postcode":"10550",
    "addr:street":"N High St",
    "iso:country":"US",
    "sg:address":"351 N High St",
    "sg:city":"Mount Vernon",
    "sg:classifiers":[
        {
            "category":"Building & Trades",
            "subcategory":"Landscaping Services",
            "type":"Services"
        }
    ],
    "sg:phone":"+1 914 668 5486",
    "sg:postcode":"10550",
    "sg:province":"NY",
    "sg:tags":[
        "landscape"
    ],
    "wof:name":"Manny Custodio",
    "wof:placetype":"venue"
},
  "geometry": {"coordinates":[-73.84217700000001,40.917705],"type":"Point"}
}