{
  "type": "Feature",
  "properties": {
    "addr:full":"6753 Old Lyons Rd Newark NY 14513",
    "addr:housenumber":"6753",
    "addr:postcode":"14513",
    "addr:street":"Old Lyons Rd",
    "iso:country":"US",
    "sg:address":"6753 Old Lyons Rd",
    "sg:city":"Newark",
    "sg:classifiers":[
        {
            "category":"Building & Trades",
            "subcategory":"Plumbing",
            "type":"Services"
        }
    ],
    "sg:phone":"+1 315 331 8764",
    "sg:postcode":"14513",
    "sg:province":"NY",
    "sg:tags":[
        "plumbing",
        "heating",
        "contractor"
    ],
    "wof:name":"A Plus Plumbing & Heating",
    "wof:placetype":"venue"
},
  "geometry": {"coordinates":[-77.05850700000001,43.059391],"type":"Point"}
}