{
  "type": "Feature",
  "properties": {
    "addr:full":"1546 Minford Place Bronx NY 10460",
    "addr:housenumber":"1546",
    "addr:postcode":"10460",
    "addr:street":"Minford Place",
    "iso:country":"US",
    "sg:address":"1546 Minford Place",
    "sg:city":"Bronx",
    "sg:classifiers":[
        {
            "category":"Personal",
            "type":"Services"
        }
    ],
    "sg:phone":"+1 718 589 5260",
    "sg:postcode":"10460",
    "sg:province":"NY",
    "sg:tags":[
        "mover"
    ],
    "wof:name":"Dun-Rite Movers",
    "wof:placetype":"venue"
},
  "geometry": {"coordinates":[-73.88962600000001,40.835831],"type":"Point"}
}