{
  "type": "Feature",
  "properties": {
    "addr:full":"303 Park Ave S New York NY 10010",
    "addr:housenumber":"303",
    "addr:postcode":"10010",
    "addr:street":"Park Ave S",
    "iso:country":"US",
    "sg:address":"303 Park Ave S",
    "sg:city":"New York",
    "sg:classifiers":[
        {
            "category":"Professional",
            "subcategory":"Management & Consulting",
            "type":"Services"
        }
    ],
    "sg:phone":"+1   ",
    "sg:postcode":"10010",
    "sg:province":"NY",
    "sg:tags":[
        "consultant",
        "business"
    ],
    "wof:name":"Design Management Company",
    "wof:placetype":"venue"
},
  "geometry": {"coordinates":[-73.98585,40.74075],"type":"Point"}
}