{
  "type": "Feature",
  "properties": {
    "addr:full":"218 Bedford Ave Brooklyn NY 11211",
    "addr:housenumber":"218",
    "addr:postcode":"11211",
    "addr:street":"Bedford Ave",
    "iso:country":"US",
    "sg:address":"218 Bedford Ave",
    "sg:city":"Brooklyn",
    "sg:classifiers":[
        {
            "category":"Shopping",
            "subcategory":"Clothing, Apparel, & Fashions",
            "type":"Retail Goods"
        }
    ],
    "sg:phone":"+1 718 302 3007",
    "sg:postcode":"11211",
    "sg:province":"NY",
    "wof:name":"Otte",
    "wof:placetype":"venue"
},
  "geometry": {"coordinates":[-73.95950999999999,40.716172],"type":"Point"}
}