{
  "type": "Feature",
  "properties": {
    "iso:country":"US",
    "sg:address":"2469 Braley Rd",
    "sg:city":"Ransomville",
    "sg:classifiers":[
        {
            "category":"Farming",
            "subcategory":"Dairy Farm",
            "type":"Manufacturing & Wholesale Goods"
        }
    ],
    "sg:phone":"+1 716 791 4407",
    "sg:postcode":"14131",
    "sg:province":"NY",
    "wof:name":"Douglas Canfield",
    "wof:placetype":"venue"
},
  "geometry": {"coordinates":[-78.911936,43.258463],"type":"Point"}
}