{
  "type": "Feature",
  "properties": {
    "addr:full":"1713 Nostrand Ave Brooklyn NY 11226",
    "addr:housenumber":"1713",
    "addr:postcode":"11226",
    "addr:street":"Nostrand Ave",
    "iso:country":"US",
    "sg:address":"1713 Nostrand Ave",
    "sg:city":"Brooklyn",
    "sg:classifiers":[
        {
            "category":"Real Estate",
            "subcategory":"Real Estate Agent",
            "type":"Services"
        }
    ],
    "sg:phone":"+1 718 469 1130",
    "sg:postcode":"11226",
    "sg:province":"NY",
    "sg:tags":[
        "appraiser"
    ],
    "sg:website":"www.channelrealty.com",
    "wof:name":"Channel Realty Co",
    "wof:placetype":"venue"
},
  "geometry": {"coordinates":[-73.94870400000001,40.643476],"type":"Point"}
}