{
  "type": "Feature",
  "properties": {
    "iso:country":"US",
    "sg:address":"1644 Park Ave",
    "sg:city":"New York",
    "sg:classifiers":[
        {
            "category":"Organizations",
            "subcategory":"Religious Organization",
            "type":"Services"
        }
    ],
    "sg:phone":"+1 845 566 4203",
    "sg:postcode":"10035",
    "sg:province":"NY",
    "sg:tags":[
        "church"
    ],
    "wof:name":"Villa Cristiana",
    "wof:placetype":"venue"
},
  "geometry": {"coordinates":[-73.942902,40.799851],"type":"Point"}
}