{
  "type": "Feature",
  "properties": {
    "addr:full":"238 W 78th St Fl 2 New York NY 10024",
    "addr:housenumber":"238;2",
    "addr:postcode":"10024",
    "addr:street":"W 78Th St",
    "iso:country":"US",
    "sg:address":"238 W 78th St Fl 2",
    "sg:city":"New York",
    "sg:classifiers":[
        {
            "category":"Sports & Exercise",
            "subcategory":"Gym",
            "type":"Entertainment"
        }
    ],
    "sg:phone":"+1 212 362 4604",
    "sg:postcode":"10024",
    "sg:province":"NY",
    "sg:tags":[
        "pilate"
    ],
    "sg:website":"www.absolutelypilates.net",
    "wof:name":"Absolutely Pilates",
    "wof:placetype":"venue"
},
  "geometry": {"coordinates":[-73.980323,40.7831],"type":"Point"}
}