{
  "type": "Feature",
  "properties": {
    "iso:country":"US",
    "sg:address":"2037 US Hwy 9",
    "sg:city":"Round Lake",
    "sg:classifiers":[
        {
            "category":"Utilities",
            "subcategory":"Refuse",
            "type":"Services"
        }
    ],
    "sg:phone":"+1   ",
    "sg:postcode":"12151",
    "sg:province":"NY",
    "sg:tags":[
        "consulting",
        "system",
        "business"
    ],
    "wof:name":"Chemcept Inc",
    "wof:placetype":"venue"
},
  "geometry": {"coordinates":[-73.78415099999999,42.91326],"type":"Point"}
}