{
  "type": "Feature",
  "properties": {
    "addr:full":"139 Havemeyer St Brooklyn NY 11211",
    "addr:housenumber":"139",
    "addr:postcode":"11211",
    "addr:street":"Havemeyer St",
    "iso:country":"US",
    "sg:address":"139 Havemeyer St",
    "sg:city":"Brooklyn",
    "sg:classifiers":[
        {
            "category":"Retail",
            "subcategory":"Portrait Studio",
            "type":"Services"
        }
    ],
    "sg:phone":"+1 718 388 9493",
    "sg:postcode":"11211",
    "sg:province":"NY",
    "sg:tags":[
        "photographer"
    ],
    "wof:name":"Cesar's Photo Studio",
    "wof:placetype":"venue"
},
  "geometry": {"coordinates":[-73.95736599999999,40.711786],"type":"Point"}
}