{
  "type": "Feature",
  "properties": {
    "addr:full":"961 Flatbush Ave Brooklyn NY 11226",
    "addr:housenumber":"961",
    "addr:postcode":"11226",
    "addr:street":"Flatbush Ave",
    "iso:country":"US",
    "sg:address":"961 Flatbush Ave",
    "sg:city":"Brooklyn",
    "sg:classifiers":[
        {
            "category":"Wholesale",
            "subcategory":"Apparel",
            "type":"Manufacturing & Wholesale Goods"
        },
        {
            "category":"Shopping",
            "subcategory":"Clothing, Apparel, & Fashions",
            "type":"Retail Goods"
        }
    ],
    "sg:phone":"+1 718 940 0258",
    "sg:postcode":"11226",
    "sg:province":"NY",
    "sg:tags":[
        "millinery"
    ],
    "wof:name":"Monica's New York",
    "wof:placetype":"venue"
},
  "geometry": {"coordinates":[-73.958122,40.648221],"type":"Point"}
}