{
  "type": "Feature",
  "properties": {
    "iso:country":"US",
    "sg:address":"393 Avenue X",
    "sg:city":"Brooklyn",
    "sg:classifiers":[
        {
            "category":"Retail",
            "subcategory":"Laundry & Dry Cleaning",
            "type":"Services"
        }
    ],
    "sg:phone":"+1 718 376 5540",
    "sg:postcode":"11223",
    "sg:province":"NY",
    "wof:name":"Friendly Cleaners",
    "wof:placetype":"venue"
},
  "geometry": {"coordinates":[-73.96790300000001,40.590698],"type":"Point"}
}