{
  "type": "Feature",
  "properties": {
    "addr:full":"3527 Long Beach Rd Oceanside NY 11572",
    "addr:housenumber":"3527",
    "addr:postcode":"11572",
    "addr:street":"Long Beach Rd",
    "iso:country":"US",
    "sg:address":"3527 Long Beach Rd",
    "sg:city":"Oceanside",
    "sg:classifiers":[
        {
            "category":"Shopping",
            "subcategory":"Clothing, Apparel, & Fashions",
            "type":"Retail Goods"
        }
    ],
    "sg:phone":"+1 516 255 9532",
    "sg:postcode":"11572",
    "sg:province":"NY",
    "sg:tags":[
        "lingerie"
    ],
    "sg:website":"www.victoriassecret.com",
    "wof:name":"Victoria's Secret",
    "wof:placetype":"venue"
},
  "geometry": {"coordinates":[-73.639397,40.624599],"type":"Point"}
}