{
  "type": "Feature",
  "properties": {
    "addr:full":"5715 Roosevelt Avenue Woodside NY 11377",
    "addr:housenumber":"5715",
    "addr:postcode":"11377",
    "addr:street":"Roosevelt Avenue",
    "iso:country":"US",
    "sg:address":"5715 Roosevelt Avenue",
    "sg:city":"Woodside",
    "sg:classifiers":[
        {
            "category":"Wholesale",
            "subcategory":"Computers",
            "type":"Manufacturing & Wholesale Goods"
        }
    ],
    "sg:phone":"+1 718 371 6600",
    "sg:postcode":"11377",
    "sg:province":"NY",
    "wof:name":"Ezone Computer Center",
    "wof:placetype":"venue"
},
  "geometry": {"coordinates":[-73.90713100000001,40.745457],"type":"Point"}
}