{
  "type": "Feature",
  "properties": {
    "addr:full":"124 Co Rd 19 Norwich NY 13830",
    "addr:housenumber":"124;19",
    "addr:postcode":"13830",
    "addr:street":"Co Rd",
    "iso:country":"US",
    "sg:address":"124 Co Rd 19",
    "sg:city":"Norwich",
    "sg:classifiers":[
        {
            "category":"Government",
            "subcategory":"Fire Station",
            "type":"Public Place"
        }
    ],
    "sg:phone":"+1 607 336 7215",
    "sg:postcode":"13830",
    "sg:province":"NY",
    "sg:tags":[
        "department",
        "protection"
    ],
    "wof:name":"Preston Fire District",
    "wof:placetype":"venue"
},
  "geometry": {"coordinates":[-75.619373,42.548543],"type":"Point"}
}