{
  "type": "Feature",
  "properties": {
    "addr:full":"127 W 24th St 5th Fl New York NY 10079",
    "addr:housenumber":"127",
    "addr:postcode":"10079",
    "addr:street":"W 24Th St",
    "iso:country":"US",
    "sg:address":"127 W 24th St 5th Fl",
    "sg:city":"New York",
    "sg:classifiers":[
        {
            "category":"Autos & Motor Vehicles",
            "subcategory":"Automobile Sales",
            "type":"Retail Goods"
        }
    ],
    "sg:phone":"+1 866 494 7227",
    "sg:postcode":"10079",
    "sg:province":"NY",
    "sg:tags":[
        "automotive"
    ],
    "sg:website":"zipcar.com",
    "wof:name":"Zipcar",
    "wof:placetype":"venue"
},
  "geometry": {"coordinates":[-73.99308600000001,40.743876],"type":"Point"}
}