{
  "type": "Feature",
  "properties": {
    "addr:full":"8 Crow Hill Dr Fairport NY 14450",
    "addr:housenumber":"8",
    "addr:postcode":"14450",
    "addr:street":"Crow Hill Dr",
    "iso:country":"US",
    "sg:address":"8 Crow Hill Dr",
    "sg:city":"Fairport",
    "sg:classifiers":[
        {
            "category":"Health Services",
            "subcategory":"Clinic",
            "type":"Services"
        }
    ],
    "sg:phone":"+1   ",
    "sg:postcode":"14450",
    "sg:province":"NY",
    "wof:name":"GE Healthcare Financial Svcs",
    "wof:placetype":"venue"
},
  "geometry": {"coordinates":[-77.44464499999999,43.063507],"type":"Point"}
}