{
  "type": "Feature",
  "properties": {
    "addr:full":"8373 Boston State Rd Boston NY 14025",
    "addr:housenumber":"8373",
    "addr:postcode":"14025",
    "addr:street":"Boston State Rd",
    "iso:country":"US",
    "sg:address":"8373 Boston State Rd",
    "sg:city":"Boston",
    "sg:classifiers":[
        {
            "category":"Coffee & Tea",
            "type":"Food & Drink"
        },
        {
            "category":"Restaurant",
            "type":"Food & Drink"
        }
    ],
    "sg:phone":"+1 716 941 3250",
    "sg:postcode":"14025",
    "sg:province":"NY",
    "sg:tags":[
        "lunch",
        "brunch",
        "cafeteria",
        "espresso",
        "breakfast"
    ],
    "wof:name":"The Girls Caf",
    "wof:placetype":"venue"
},
  "geometry": {"coordinates":[-78.74637300000001,42.655654],"type":"Point"}
}