{
  "type": "Feature",
  "properties": {
    "addr:full":"341 5th Ave Brooklyn NY 11215",
    "addr:housenumber":"341",
    "addr:postcode":"11215",
    "addr:street":"5Th Ave",
    "iso:country":"US",
    "sg:address":"341 5th Ave",
    "sg:city":"Brooklyn",
    "sg:classifiers":[
        {
            "category":"Restaurant",
            "type":"Food & Drink"
        }
    ],
    "sg:phone":"+1 718 369 2222",
    "sg:postcode":"11215",
    "sg:province":"NY",
    "wof:name":"El Sitio Borinquen",
    "wof:placetype":"venue"
},
  "geometry": {"coordinates":[-73.98365699999999,40.671932],"type":"Point"}
}