{
  "type": "Feature",
  "properties": {
    "addr:full":"15315 Cross Island Parkway Whitestone NY 11357",
    "addr:housenumber":"15315",
    "addr:postcode":"11357",
    "addr:street":"Cross Island Parkway",
    "iso:country":"US",
    "sg:address":"15315 Cross Island Parkway",
    "sg:city":"Whitestone",
    "sg:classifiers":[
        {
            "category":"Banks & Credit Unions",
            "subcategory":"Bank",
            "type":"Services"
        }
    ],
    "sg:phone":"+1 718 935 9935",
    "sg:postcode":"11357",
    "sg:province":"NY",
    "wof:name":"Chase Manhattan Bank",
    "wof:placetype":"venue"
},
  "geometry": {"coordinates":[-73.807806,40.786979],"type":"Point"}
}