{
  "type": "Feature",
  "properties": {
    "iso:country":"US",
    "sg:address":"14522 14th Ave",
    "sg:city":"Whitestone",
    "sg:classifiers":[
        {
            "category":"Retail",
            "subcategory":"Laundry & Dry Cleaning",
            "type":"Services"
        }
    ],
    "sg:phone":"+1 718 747 7698",
    "sg:postcode":"11357",
    "sg:province":"NY",
    "wof:name":"In Sook Kim",
    "wof:placetype":"venue"
},
  "geometry": {"coordinates":[-73.82147500000001,40.786899],"type":"Point"}
}