{
  "type": "Feature",
  "properties": {
    "iso:country":"US",
    "sg:address":"1455 Weaver St",
    "sg:city":"Scarsdale",
    "sg:classifiers":[
        {
            "category":"Retail",
            "subcategory":"Auto Repair",
            "type":"Services"
        }
    ],
    "sg:phone":"+1 914 472 6628",
    "sg:postcode":"10583",
    "sg:province":"NY",
    "sg:tags":[
        "wrecker"
    ],
    "wof:name":"Mid Westchester Towing",
    "wof:placetype":"venue"
},
  "geometry": {"coordinates":[-73.77545499999999,40.97667],"type":"Point"}
}