{
  "type": "Feature",
  "properties": {
    "addr:full":"27 Smith St Glen Cove NY 11542",
    "addr:housenumber":"27",
    "addr:postcode":"11542",
    "addr:street":"Smith St",
    "iso:country":"US",
    "sg:address":"27 Smith St",
    "sg:city":"Glen Cove",
    "sg:classifiers":[
        {
            "category":"Building & Trades",
            "subcategory":"Landscaping Services",
            "type":"Services"
        }
    ],
    "sg:phone":"+1 516 671 4633",
    "sg:postcode":"11542",
    "sg:province":"NY",
    "wof:name":"Periwood Inc",
    "wof:placetype":"venue"
},
  "geometry": {"coordinates":[-73.608507,40.85634],"type":"Point"}
}