{
  "type": "Feature",
  "properties": {
    "iso:country":"US",
    "sg:address":"6277 W Carter Rd",
    "sg:city":"Rome",
    "sg:classifiers":[
        {
            "category":"Wholesale",
            "subcategory":"Electrical",
            "type":"Manufacturing & Wholesale Goods"
        }
    ],
    "sg:phone":"+1 315 337 6825",
    "sg:postcode":"13490",
    "sg:province":"NY",
    "sg:tags":[
        "mfg"
    ],
    "wof:name":"HI Tech Documentation",
    "wof:placetype":"venue"
},
  "geometry": {"coordinates":[-75.46879300000001,43.159864],"type":"Point"}
}