{
  "type": "Feature",
  "properties": {
    "addr:full":"1175 Leggett Ave Bronx NY 10474",
    "addr:housenumber":"1175",
    "addr:postcode":"10474",
    "addr:street":"Leggett Ave",
    "iso:country":"US",
    "sg:address":"1175 Leggett Ave",
    "sg:city":"Bronx",
    "sg:classifiers":[
        {
            "category":"Banks & Credit Unions",
            "subcategory":"Bank",
            "type":"Services"
        }
    ],
    "sg:phone":"+1 718 378 7000",
    "sg:postcode":"10474",
    "sg:province":"NY",
    "sg:tags":[
        "cashing",
        "check"
    ],
    "wof:name":"Hunts Point Check Cashing",
    "wof:placetype":"venue"
},
  "geometry": {"coordinates":[-73.894885,40.81183],"type":"Point"}
}