{
  "type": "Feature",
  "properties": {
    "addr:full":"1616 Sheepshead Bay Rd Brooklyn NY 11235",
    "addr:housenumber":"1616",
    "addr:postcode":"11235",
    "addr:street":"Sheepshead Bay Rd",
    "iso:country":"US",
    "sg:address":"1616 Sheepshead Bay Rd",
    "sg:city":"Brooklyn",
    "sg:classifiers":[
        {
            "category":"Real Estate",
            "subcategory":"Real Estate Agent",
            "type":"Services"
        }
    ],
    "sg:phone":"+1 718 646 1752",
    "sg:postcode":"11235",
    "sg:province":"NY",
    "sg:tags":[
        "management"
    ],
    "wof:name":"Felicita",
    "wof:placetype":"venue"
},
  "geometry": {"coordinates":[-73.95188899999999,40.585936],"type":"Point"}
}