{
  "type": "Feature",
  "properties": {
    "iso:country":"US",
    "sg:address":"110 Wells Farm Rd",
    "sg:city":"Goshen",
    "sg:classifiers":[
        {
            "category":"Professional",
            "subcategory":"Management & Consulting",
            "type":"Services"
        }
    ],
    "sg:phone":"+1 845 294 3352",
    "sg:postcode":"10924",
    "sg:province":"NY",
    "wof:name":"Aramark",
    "wof:placetype":"venue"
},
  "geometry": {"coordinates":[-74.35578099999999,41.40558],"type":"Point"}
}