{
  "type": "Feature",
  "properties": {
    "addr:full":"435 Yorktown Rd Croton On Hudson NY 10520",
    "addr:housenumber":"435",
    "addr:postcode":"10520",
    "addr:street":"Yorktown Rd",
    "iso:country":"US",
    "sg:address":"435 Yorktown Rd",
    "sg:city":"Croton On Hudson",
    "sg:classifiers":[
        {
            "category":"Manufacturing",
            "subcategory":"Chemicals & Compounds",
            "type":"Manufacturing & Wholesale Goods"
        }
    ],
    "sg:phone":"+1   ",
    "sg:postcode":"10520",
    "sg:province":"NY",
    "sg:tags":[
        "distributor",
        "manufacturer",
        "mineral",
        "vitamin"
    ],
    "wof:name":"Healthyn Fit International",
    "wof:placetype":"venue"
},
  "geometry": {"coordinates":[-73.850668,41.23782],"type":"Point"}
}