{
  "type": "Feature",
  "properties": {
    "addr:full":"105 Old Farm Rd Riverhead NY 11901",
    "addr:housenumber":"105",
    "addr:postcode":"11901",
    "addr:street":"Old Farm Rd",
    "iso:country":"US",
    "sg:address":"105 Old Farm Rd",
    "sg:city":"Riverhead",
    "sg:classifiers":[
        {
            "category":"Travel",
            "subcategory":"Campground",
            "type":"Entertainment"
        }
    ],
    "sg:phone":"+1 631 852 3232",
    "sg:postcode":"11901",
    "sg:province":"NY",
    "sg:tags":[
        "executive",
        "trailer"
    ],
    "wof:name":"Parks Recreation Conservation",
    "wof:placetype":"venue"
},
  "geometry": {"coordinates":[-72.665212,40.942323],"type":"Point"}
}