{
  "type": "Feature",
  "properties": {
    "addr:full":"2 Lyon Pl White Plains NY 10601",
    "addr:housenumber":"2",
    "addr:postcode":"10601",
    "addr:street":"Lyon Pl",
    "iso:country":"US",
    "sg:address":"2 Lyon Pl",
    "sg:city":"White Plains",
    "sg:classifiers":[
        {
            "category":"Professional",
            "subcategory":"Lawyer & Legal Services",
            "type":"Services"
        }
    ],
    "sg:phone":"+1 914 684 0014",
    "sg:postcode":"10601",
    "sg:province":"NY",
    "sg:tags":[
        "attorney"
    ],
    "wof:name":"Worby PC",
    "wof:placetype":"venue"
},
  "geometry": {"coordinates":[-73.762282,41.029209],"type":"Point"}
}