{
  "type": "Feature",
  "properties": {
    "addr:full":"4774 Salina St Pulaski NY 13142",
    "addr:housenumber":"4774",
    "addr:postcode":"13142",
    "addr:street":"Salina St",
    "iso:country":"US",
    "sg:address":"4774 Salina St",
    "sg:city":"Pulaski",
    "sg:classifiers":[
        {
            "category":"Real Estate",
            "subcategory":"Real Estate Agent",
            "type":"Services"
        }
    ],
    "sg:phone":"+1 315 298 2012",
    "sg:postcode":"13142",
    "sg:province":"NY",
    "wof:name":"Harvey Realty",
    "wof:placetype":"venue"
},
  "geometry": {"coordinates":[-76.12646599999999,43.562523],"type":"Point"}
}