{
  "type": "Feature",
  "properties": {
    "iso:country":"US",
    "sg:address":"181 Wilson Park Dr",
    "sg:city":"Tarrytown",
    "sg:classifiers":[
        {
            "category":"Shopping",
            "type":"Retail Goods"
        }
    ],
    "sg:phone":"+1   ",
    "sg:postcode":"10591",
    "sg:province":"NY",
    "sg:tags":[
        "merchandise"
    ],
    "wof:name":"Numismatic Rarities Ltd",
    "wof:placetype":"venue"
},
  "geometry": {"coordinates":[-73.848551,41.086273],"type":"Point"}
}