{
  "type": "Feature",
  "properties": {
    "iso:country":"US",
    "sg:address":"1548 Mohawk St",
    "sg:city":"Utica",
    "sg:classifiers":[
        {
            "category":"Shopping",
            "subcategory":"Clothing, Apparel, & Fashions",
            "type":"Retail Goods"
        }
    ],
    "sg:phone":"+1   ",
    "sg:postcode":"13501",
    "sg:province":"NY",
    "wof:name":"Donna Maries Bridal Shoppe",
    "wof:placetype":"venue"
},
  "geometry": {"coordinates":[-75.228809,43.081912],"type":"Point"}
}