{
  "type": "Feature",
  "properties": {
    "iso:country":"US",
    "sg:address":"1507 Round Pond Rd",
    "sg:city":"Lake Ronkonkoma",
    "sg:classifiers":[
        {
            "category":"Real Estate",
            "subcategory":"Real Estate Operator",
            "type":"Services"
        }
    ],
    "sg:phone":"+1 631 981 5212",
    "sg:postcode":"11779",
    "sg:province":"NY",
    "sg:tags":[
        "apartment"
    ],
    "wof:name":"Brookwood On The Lake",
    "wof:placetype":"venue"
},
  "geometry": {"coordinates":[-73.09808,40.832648],"type":"Point"}
}