{
  "type": "Feature",
  "properties": {
    "addr:full":"187 Rodney St Brooklyn NY 11211",
    "addr:housenumber":"187",
    "addr:postcode":"11211",
    "addr:street":"Rodney St",
    "iso:country":"US",
    "sg:address":"187 Rodney St",
    "sg:city":"Brooklyn",
    "sg:classifiers":[
        {
            "category":"Shopping",
            "type":"Retail Goods"
        }
    ],
    "sg:phone":"+1 718 963 1205",
    "sg:postcode":"11211",
    "sg:province":"NY",
    "sg:tags":[
        "religious"
    ],
    "wof:name":"Adorn Sterling",
    "wof:placetype":"venue"
},
  "geometry": {"coordinates":[-73.959284,40.705508],"type":"Point"}
}