{
  "type": "Feature",
  "properties": {
    "addr:full":"135 E 96th St New York NY 10128",
    "addr:housenumber":"135",
    "addr:postcode":"10128",
    "addr:street":"E 96Th St",
    "iso:country":"US",
    "sg:address":"135 E 96th St",
    "sg:city":"New York",
    "sg:classifiers":[
        {
            "category":"Education",
            "subcategory":"Special Training",
            "type":"Public Place"
        }
    ],
    "sg:phone":"+1 212 427 7770",
    "sg:postcode":"10128",
    "sg:province":"NY",
    "sg:tags":[
        "school",
        "language"
    ],
    "sg:website":"www.collinaitaliana.com",
    "wof:name":"Collina Italiana Llc",
    "wof:placetype":"venue"
},
  "geometry": {"coordinates":[-73.95120199999999,40.786141],"type":"Point"}
}