{
  "type": "Feature",
  "properties": {
    "iso:country":"US",
    "sg:address":"1431 E 9th St",
    "sg:city":"Brooklyn",
    "sg:classifiers":[
        {
            "category":"Professional",
            "subcategory":"Management & Consulting",
            "type":"Services"
        }
    ],
    "sg:phone":"+1 718 633 4733",
    "sg:postcode":"11230",
    "sg:province":"NY",
    "sg:tags":[
        "business"
    ],
    "wof:name":"Degrees Plus",
    "wof:placetype":"venue"
},
  "geometry": {"coordinates":[-73.96482399999999,40.613156],"type":"Point"}
}