{
  "type": "Feature",
  "properties": {
    "addr:full":"1128 Lexington Ave Rochester NY 14606",
    "addr:housenumber":"1128",
    "addr:postcode":"14606",
    "addr:street":"Lexington Ave",
    "iso:country":"US",
    "sg:address":"1128 Lexington Ave",
    "sg:city":"Rochester",
    "sg:classifiers":[
        {
            "category":"Manufacturing",
            "subcategory":"Rubber & Plastics",
            "type":"Manufacturing & Wholesale Goods"
        }
    ],
    "sg:phone":"+1 585 458 6727",
    "sg:postcode":"14606",
    "sg:province":"NY",
    "sg:tags":[
        "product"
    ],
    "wof:name":"Norandex Inc",
    "wof:placetype":"venue"
},
  "geometry": {"coordinates":[-77.660657,43.179276],"type":"Point"}
}