{
  "type": "Feature",
  "properties": {
    "iso:country":"US",
    "sg:address":"140 Riverside Dr",
    "sg:city":"Riverhead",
    "sg:classifiers":[
        {
            "category":"Building & Trades",
            "subcategory":"Construction",
            "type":"Services"
        }
    ],
    "sg:phone":"+1 631 369 2953",
    "sg:postcode":"11901",
    "sg:province":"NY",
    "sg:tags":[
        "house"
    ],
    "wof:name":"K Nethercott Const",
    "wof:placetype":"venue"
},
  "geometry": {"coordinates":[-72.652497,40.92041],"type":"Point"}
}