{
  "type": "Feature",
  "properties": {
    "iso:country":"US",
    "sg:address":"468 Eaker Rd",
    "sg:city":"Fort Plain",
    "sg:classifiers":[
        {
            "category":"Manufacturing",
            "subcategory":"Leather Goods",
            "type":"Manufacturing & Wholesale Goods"
        }
    ],
    "sg:phone":"+1   ",
    "sg:postcode":"13339",
    "sg:province":"NY",
    "sg:tags":[
        "mfg"
    ],
    "wof:name":"Jens Splits",
    "wof:placetype":"venue"
},
  "geometry": {"coordinates":[-74.510375,42.983786],"type":"Point"}
}