{
  "type": "Feature",
  "properties": {
    "addr:full":"148 W Park Ave Long Beach NY 11561",
    "addr:housenumber":"148",
    "addr:postcode":"11561",
    "addr:street":"W Park Ave",
    "iso:country":"US",
    "sg:address":"148 W Park Ave",
    "sg:city":"Long Beach",
    "sg:classifiers":[
        {
            "category":"Food & Beverages",
            "subcategory":"Groceries & Convenience Stores",
            "type":"Retail Goods"
        }
    ],
    "sg:phone":"+1 516 889 0081",
    "sg:postcode":"11561",
    "sg:province":"NY",
    "wof:name":"Fresh Fruit Bowl",
    "wof:placetype":"venue"
},
  "geometry": {"coordinates":[-73.668296,40.588207],"type":"Point"}
}