{
  "type": "Feature",
  "properties": {
    "addr:full":"610 5th Ave New York NY 10020",
    "addr:housenumber":"610",
    "addr:postcode":"10020",
    "addr:street":"5Th Ave",
    "iso:country":"US",
    "sg:address":"610 5th Ave",
    "sg:city":"New York",
    "sg:classifiers":[
        {
            "category":"Professional",
            "subcategory":"Management & Consulting",
            "type":"Services"
        }
    ],
    "sg:phone":"+1 212 218 7880",
    "sg:postcode":"10020",
    "sg:province":"NY",
    "sg:tags":[
        "consultant",
        "financial"
    ],
    "wof:name":"Ravitch Rice & Co LLC",
    "wof:placetype":"venue"
},
  "geometry": {"coordinates":[-73.97720099999999,40.758538],"type":"Point"}
}