{
  "type": "Feature",
  "properties": {
    "addr:full":"40 Bowery New York NY 10013",
    "addr:housenumber":"40",
    "addr:postcode":"10013",
    "addr:street":"Bowery",
    "iso:country":"US",
    "sg:address":"40 Bowery",
    "sg:city":"New York",
    "sg:classifiers":[
        {
            "category":"Restaurant",
            "type":"Food & Drink"
        }
    ],
    "sg:phone":"+1 212 608 0806",
    "sg:postcode":"10013",
    "sg:province":"NY",
    "sg:tags":[
        "chinese"
    ],
    "wof:name":"Kens Asian Taste",
    "wof:placetype":"venue"
},
  "geometry": {"coordinates":[-73.99691,40.715571],"type":"Point"}
}