{
  "type": "Feature",
  "properties": {
    "addr:full":"3802 Ditmars Blvd Queens NY 11105",
    "addr:housenumber":"3802",
    "addr:postcode":"11105",
    "addr:street":"Ditmars Blvd",
    "iso:country":"US",
    "sg:address":"3802 Ditmars Blvd",
    "sg:city":"Queens",
    "sg:classifiers":[
        {
            "category":"Shopping",
            "subcategory":"Florist",
            "type":"Retail Goods"
        }
    ],
    "sg:phone":"+1 718 278 1067",
    "sg:postcode":"11105",
    "sg:province":"NY",
    "sg:website":"www.licflorist.com/",
    "wof:name":"LIC Florist",
    "wof:placetype":"venue"
},
  "geometry": {"coordinates":[-73.906758,40.773224],"type":"Point"}
}