{
  "type": "Feature",
  "properties": {
    "addr:full":"15 Bogel Rd Bayport NY 11705",
    "addr:housenumber":"15",
    "addr:postcode":"11705",
    "addr:street":"Bogel Rd",
    "iso:country":"US",
    "sg:address":"15 Bogel Rd",
    "sg:city":"Bayport",
    "sg:classifiers":[
        {
            "category":"Manufacturing",
            "subcategory":"Tools & Machinery",
            "type":"Manufacturing & Wholesale Goods"
        }
    ],
    "sg:phone":"+1   ",
    "sg:postcode":"11705",
    "sg:province":"NY",
    "sg:tags":[
        "construction",
        "mfg"
    ],
    "wof:name":"Lightship Systems",
    "wof:placetype":"venue"
},
  "geometry": {"coordinates":[-73.066795,40.740104],"type":"Point"}
}