{
  "type": "Feature",
  "properties": {
    "iso:country":"US",
    "sg:address":"39 Buttonwood Dr",
    "sg:city":"Huntington Station",
    "sg:classifiers":[
        {
            "category":"Professional",
            "subcategory":"Management & Consulting",
            "type":"Services"
        }
    ],
    "sg:phone":"+1 631 499 2211",
    "sg:postcode":"11746",
    "sg:province":"NY",
    "wof:name":"Trident Recreation Enterprises",
    "wof:placetype":"venue"
},
  "geometry": {"coordinates":[-73.32757700000001,40.825657],"type":"Point"}
}