{
  "type": "Feature",
  "properties": {
    "addr:full":"180 Jefferson Ave Mamaroneck NY 10543",
    "addr:housenumber":"180",
    "addr:postcode":"10543",
    "addr:street":"Jefferson Ave",
    "iso:country":"US",
    "sg:address":"180 Jefferson Ave",
    "sg:city":"Mamaroneck",
    "sg:classifiers":[
        {
            "category":"Wholesale",
            "subcategory":"Meat",
            "type":"Manufacturing & Wholesale Goods"
        }
    ],
    "sg:phone":"+1   ",
    "sg:postcode":"10543",
    "sg:province":"NY",
    "sg:tags":[
        "sausage",
        "mfg"
    ],
    "wof:name":"Picones Sausage",
    "wof:placetype":"venue"
},
  "geometry": {"coordinates":[-73.73715300000001,40.955978],"type":"Point"}
}