{
  "type": "Feature",
  "properties": {
    "addr:full":"1220 Wantagh Ave Wantagh NY 11793",
    "addr:housenumber":"1220",
    "addr:postcode":"11793",
    "addr:street":"Wantagh Ave",
    "iso:country":"US",
    "sg:address":"1220 Wantagh Ave",
    "sg:city":"Wantagh",
    "sg:classifiers":[
        {
            "category":"Manufacturing",
            "subcategory":"Printing",
            "type":"Manufacturing & Wholesale Goods"
        }
    ],
    "sg:phone":"+1 516 409 1400",
    "sg:postcode":"11793",
    "sg:province":"NY",
    "sg:tags":[
        "publisher"
    ],
    "wof:name":"Mortgage Press LTD",
    "wof:placetype":"venue"
},
  "geometry": {"coordinates":[-73.507972,40.692488],"type":"Point"}
}