{
  "type": "Feature",
  "properties": {
    "addr:full":"27 Thelma St Roslyn Heights NY 11577",
    "addr:housenumber":"27",
    "addr:postcode":"11577",
    "addr:street":"Thelma St",
    "iso:country":"US",
    "sg:address":"27 Thelma St",
    "sg:city":"Roslyn Heights",
    "sg:classifiers":[
        {
            "category":"Retail",
            "subcategory":"Repair Shop",
            "type":"Services"
        }
    ],
    "sg:phone":"+1 516 621 8775",
    "sg:postcode":"11577",
    "sg:province":"NY",
    "sg:tags":[
        "lock",
        "locksmith"
    ],
    "wof:name":"A Plus Locksmith",
    "wof:placetype":"venue"
},
  "geometry": {"coordinates":[-73.639473,40.786595],"type":"Point"}
}