{
  "type": "Feature",
  "properties": {
    "addr:full":"201 Helen St Holbrook NY 11741",
    "addr:housenumber":"201",
    "addr:postcode":"11741",
    "addr:street":"Helen St",
    "iso:country":"US",
    "sg:address":"201 Helen St",
    "sg:city":"Holbrook",
    "sg:classifiers":[
        {
            "category":"Personal",
            "subcategory":"Beauty Salon",
            "type":"Services"
        }
    ],
    "sg:phone":"+1 631 585 1715",
    "sg:postcode":"11741",
    "sg:province":"NY",
    "wof:name":"Spa Haus",
    "wof:placetype":"venue"
},
  "geometry": {"coordinates":[-73.08068799999999,40.78642],"type":"Point"}
}