{
  "type": "Feature",
  "properties": {
    "addr:full":"7724 Victor-Pittsford Rd Victor NY 14564",
    "addr:housenumber":"7724",
    "addr:postcode":"14564",
    "addr:street":"Victor-Pittsford Rd",
    "iso:country":"US",
    "sg:address":"7724 Victor-Pittsford Rd",
    "sg:city":"Victor",
    "sg:classifiers":[
        {
            "category":"Restaurant",
            "type":"Food & Drink"
        }
    ],
    "sg:menulink":"http://www.allmenus.com/ny/victor/68294-uno-chicago-grill/menu/",
    "sg:phone":"+1 585 223 6100",
    "sg:postcode":"14564",
    "sg:province":"NY",
    "sg:tags":[
        "american",
        "italian",
        "pizza"
    ],
    "wof:name":"Uno Chicago Grill",
    "wof:placetype":"venue"
},
  "geometry": {"coordinates":[-77.438726,43.024356],"type":"Point"}
}