{
  "type": "Feature",
  "properties": {
    "addr:full":"544 Northern Blvd Great Neck NY 11021",
    "addr:housenumber":"544",
    "addr:postcode":"11021",
    "addr:street":"Northern Blvd",
    "iso:country":"US",
    "sg:address":"544 Northern Blvd",
    "sg:city":"Great Neck",
    "sg:classifiers":[
        {
            "category":"Local Transit",
            "type":"Transportation"
        }
    ],
    "sg:phone":"+1   ",
    "sg:postcode":"11021",
    "sg:province":"NY",
    "sg:tags":[
        "limousine",
        "rental"
    ],
    "wof:name":"Excalbur Extrvgnza Limosne Ltd",
    "wof:placetype":"venue"
},
  "geometry": {"coordinates":[-73.72012599999999,40.780487],"type":"Point"}
}