{
  "type": "Feature",
  "properties": {
    "iso:country":"US",
    "sg:address":"5291 Starr Rd",
    "sg:city":"Campbell",
    "sg:classifiers":[
        {
            "category":"Health Services",
            "subcategory":"Clinic",
            "type":"Services"
        }
    ],
    "sg:phone":"+1 607 527 8793",
    "sg:postcode":"14821",
    "sg:province":"NY",
    "wof:name":"Insight Health Corp",
    "wof:placetype":"venue"
},
  "geometry": {"coordinates":[-77.26918499999999,42.230129],"type":"Point"}
}