{
  "type": "Feature",
  "properties": {
    "addr:full":"720 Livonia Ave Brooklyn NY 11207",
    "addr:housenumber":"720",
    "addr:postcode":"11207",
    "addr:street":"Livonia Ave",
    "iso:country":"US",
    "sg:address":"720 Livonia Ave",
    "sg:city":"Brooklyn",
    "sg:classifiers":[
        {
            "category":"Education",
            "subcategory":"School",
            "type":"Public Place"
        }
    ],
    "sg:phone":"+1 718 498 1190",
    "sg:postcode":"11207",
    "sg:province":"NY",
    "wof:name":"Public School 53",
    "wof:placetype":"venue"
},
  "geometry": {"coordinates":[-73.89121299999999,40.665175],"type":"Point"}
}