{
  "type": "Feature",
  "properties": {
    "iso:country":"US",
    "sg:address":"67 Kisco Ave",
    "sg:city":"Mt Kisco",
    "sg:classifiers":[
        {
            "category":"Personal",
            "type":"Services"
        }
    ],
    "sg:phone":"+1 914 244 0009",
    "sg:postcode":"10549",
    "sg:province":"NY",
    "sg:tags":[
        "therapist",
        "massage"
    ],
    "wof:name":"G Flint & M Ploener",
    "wof:placetype":"venue"
},
  "geometry": {"coordinates":[-73.72560900000001,41.215545],"type":"Point"}
}