{
  "type": "Feature",
  "properties": {
    "iso:country":"US",
    "sg:address":"3014 Riverdale Ave",
    "sg:city":"Bronx",
    "sg:classifiers":[
        {
            "category":"Retail",
            "subcategory":"Auto Repair",
            "type":"Services"
        }
    ],
    "sg:phone":"+1 718 601 3371",
    "sg:postcode":"10463",
    "sg:province":"NY",
    "sg:tags":[
        "repairing",
        "automobile"
    ],
    "wof:name":"South Riverdale Svc",
    "wof:placetype":"venue"
},
  "geometry": {"coordinates":[-73.91019,40.880594],"type":"Point"}
}