{
  "type": "Feature",
  "properties": {
    "iso:country":"US",
    "sg:address":"309 Malden Ave",
    "sg:city":"Palenville",
    "sg:classifiers":[
        {
            "category":"Professional",
            "subcategory":"Detective & Security Services",
            "type":"Services"
        }
    ],
    "sg:phone":"+1 845 246 5501",
    "sg:postcode":"12463",
    "sg:province":"NY",
    "sg:tags":[
        "information",
        "bureau"
    ],
    "wof:name":"Brian M Robinson",
    "wof:placetype":"venue"
},
  "geometry": {"coordinates":[-74.025533,42.173072],"type":"Point"}
}