{
  "type": "Feature",
  "properties": {
    "iso:country":"US",
    "sg:address":"32 W 82 St",
    "sg:city":"New York",
    "sg:classifiers":[
        {
            "category":"Professional",
            "subcategory":"Computer Services",
            "type":"Services"
        }
    ],
    "sg:phone":"+1 212 874 4829",
    "sg:postcode":"10024",
    "sg:province":"NY",
    "sg:tags":[
        "processing",
        "datum"
    ],
    "wof:name":"Counter Point Systems Inc",
    "wof:placetype":"venue"
},
  "geometry": {"coordinates":[-73.97342399999999,40.783462],"type":"Point"}
}