{
  "type": "Feature",
  "properties": {
    "iso:country":"US",
    "sg:address":"404 W Yates St",
    "sg:city":"East Syracuse",
    "sg:classifiers":[
        {
            "category":"Building & Trades",
            "subcategory":"Plumbing",
            "type":"Services"
        }
    ],
    "sg:phone":"+1 315 463 1116",
    "sg:postcode":"13057",
    "sg:province":"NY",
    "sg:tags":[
        "contractor"
    ],
    "wof:name":"B&M",
    "wof:placetype":"venue"
},
  "geometry": {"coordinates":[-76.079137,43.066575],"type":"Point"}
}