{
  "type": "Feature",
  "properties": {
    "iso:country":"US",
    "sg:address":"565 Broadway",
    "sg:city":"Amityville",
    "sg:classifiers":[
        {
            "category":"Personal",
            "subcategory":"Beauty Salon",
            "type":"Services"
        }
    ],
    "sg:phone":"+1   ",
    "sg:postcode":"11701",
    "sg:province":"NY",
    "sg:tags":[
        "shop"
    ],
    "wof:name":"Lins Nail Salon",
    "wof:placetype":"venue"
},
  "geometry": {"coordinates":[-73.421789,40.69147],"type":"Point"}
}