{
  "type": "Feature",
  "properties": {
    "addr:full":"26 Colony Dr Monroe NY 10950",
    "addr:housenumber":"26",
    "addr:postcode":"10950",
    "addr:street":"Colony Dr",
    "iso:country":"US",
    "sg:address":"26 Colony Dr",
    "sg:city":"Monroe",
    "sg:classifiers":[
        {
            "category":"Shopping",
            "subcategory":"Gifts & Souvenirs",
            "type":"Retail Goods"
        }
    ],
    "sg:phone":"+1 845 782 6911",
    "sg:postcode":"10950",
    "sg:province":"NY",
    "sg:tags":[
        "announcement",
        "invitation"
    ],
    "wof:name":"Creative Quill LTD",
    "wof:placetype":"venue"
},
  "geometry": {"coordinates":[-74.197063,41.312373],"type":"Point"}
}