{
  "type": "Feature",
  "properties": {
    "addr:full":"1010 Wayne St Olean NY 14760",
    "addr:housenumber":"1010",
    "addr:postcode":"14760",
    "addr:street":"Wayne St",
    "iso:country":"US",
    "sg:address":"1010 Wayne St",
    "sg:city":"Olean",
    "sg:classifiers":[
        {
            "category":"Food & Beverages",
            "subcategory":"Groceries & Convenience Stores",
            "type":"Retail Goods"
        }
    ],
    "sg:phone":"+1 716 372 4989",
    "sg:postcode":"14760",
    "sg:province":"NY",
    "sg:tags":[
        "product"
    ],
    "wof:name":"Olean Food Pantry",
    "wof:placetype":"venue"
},
  "geometry": {"coordinates":[-78.442221,42.085201],"type":"Point"}
}