{
  "type": "Feature",
  "properties": {
    "addr:full":"52 W Main St Fillmore NY 14735",
    "addr:housenumber":"52",
    "addr:postcode":"14735",
    "addr:street":"W Main St",
    "iso:country":"US",
    "sg:address":"52 W Main St",
    "sg:city":"Fillmore",
    "sg:classifiers":[
        {
            "category":"Banks & Credit Unions",
            "subcategory":"Bank",
            "type":"Services"
        }
    ],
    "sg:phone":"+1 585 567 4103",
    "sg:postcode":"14735",
    "sg:province":"NY",
    "sg:website":"http://www.acsfcu.com",
    "wof:name":"Allegany County Schools Federal Credit Union",
    "wof:placetype":"venue"
},
  "geometry": {"coordinates":[-78.110344,42.465434],"type":"Point"}
}