{
  "type": "Feature",
  "properties": {
    "iso:country":"US",
    "sg:address":"2 E 103rd St",
    "sg:city":"New York",
    "sg:classifiers":[
        {
            "category":"Health Services",
            "subcategory":"Doctor",
            "type":"Services"
        }
    ],
    "sg:phone":"+1 212 722 4300",
    "sg:postcode":"10029",
    "sg:province":"NY",
    "sg:tags":[
        "physician",
        "surgeon"
    ],
    "wof:name":"Ny Section American Urological",
    "wof:placetype":"venue"
},
  "geometry": {"coordinates":[-73.95091600000001,40.791675],"type":"Point"}
}