{
  "type": "Feature",
  "properties": {
    "addr:full":"412 Old Post Rd Bedford NY 10506",
    "addr:housenumber":"412",
    "addr:postcode":"10506",
    "addr:street":"Old Post Rd",
    "iso:country":"US",
    "sg:address":"412 Old Post Rd",
    "sg:city":"Bedford",
    "sg:classifiers":[
        {
            "category":"Building & Trades",
            "subcategory":"Construction",
            "type":"Services"
        }
    ],
    "sg:phone":"+1 914 234 0965",
    "sg:postcode":"10506",
    "sg:province":"NY",
    "sg:tags":[
        "masonry",
        "contractor"
    ],
    "wof:name":"Nick Cambareri Masonry",
    "wof:placetype":"venue"
},
  "geometry": {"coordinates":[-73.654962,41.195809],"type":"Point"}
}