{
  "type": "Feature",
  "properties": {
    "addr:full":"1007 State Fair Blvd Syracuse NY 13209",
    "addr:housenumber":"1007",
    "addr:postcode":"13209",
    "addr:street":"State Fair Blvd",
    "iso:country":"US",
    "sg:address":"1007 State Fair Blvd",
    "sg:city":"Syracuse",
    "sg:classifiers":[
        {
            "category":"Food & Beverages",
            "subcategory":"Groceries & Convenience Stores",
            "type":"Retail Goods"
        }
    ],
    "sg:phone":"+1 315 488 0350",
    "sg:postcode":"13209",
    "sg:province":"NY",
    "wof:name":"Lakeside Grocery",
    "wof:placetype":"venue"
},
  "geometry": {"coordinates":[-76.247963,43.099463],"type":"Point"}
}