{
  "type": "Feature",
  "properties": {
    "addr:full":"35 Leonard St Glens Falls NY 12801",
    "addr:housenumber":"35",
    "addr:postcode":"12801",
    "addr:street":"Leonard St",
    "iso:country":"US",
    "sg:address":"35 Leonard St",
    "sg:city":"Glens Falls",
    "sg:classifiers":[
        {
            "category":"Retail",
            "subcategory":"Repair Shop",
            "type":"Services"
        }
    ],
    "sg:phone":"+1   ",
    "sg:postcode":"12801",
    "sg:province":"NY",
    "wof:name":"J & S Invisible Repairs",
    "wof:placetype":"venue"
},
  "geometry": {"coordinates":[-73.635786,43.317363],"type":"Point"}
}