{
  "type": "Feature",
  "properties": {
    "iso:country":"US",
    "sg:address":"150 US Hwy 9",
    "sg:city":"Rhinebeck",
    "sg:classifiers":[
        {
            "category":"Government",
            "subcategory":"Police Station",
            "type":"Public Place"
        }
    ],
    "sg:phone":"+1 845 876 4033",
    "sg:postcode":"12572",
    "sg:province":"NY",
    "sg:tags":[
        "state"
    ],
    "wof:name":"State Police Dept",
    "wof:placetype":"venue"
},
  "geometry": {"coordinates":[-73.88381699999999,41.969629],"type":"Point"}
}