{
  "type": "Feature",
  "properties": {
    "iso:country":"US",
    "sg:address":"4360 Commerce Dr",
    "sg:city":"Batavia",
    "sg:classifiers":[
        {
            "category":"Travel",
            "subcategory":"Hotels & Motels",
            "type":"Entertainment"
        }
    ],
    "sg:phone":"+1 585 815 0475",
    "sg:postcode":"14020",
    "sg:province":"NY",
    "sg:tags":[
        "corporate",
        "lodging"
    ],
    "sg:website":"http://www.batavia.hamptoninn.com",
    "wof:name":"Hampton Inn",
    "wof:placetype":"venue"
},
  "geometry": {"coordinates":[-78.19446600000001,43.019883],"type":"Point"}
}