{
  "type": "Feature",
  "properties": {
    "addr:full":"240 W 35th Street Suite 504 New York NY 10001",
    "addr:housenumber":"240;504",
    "addr:postcode":"10001",
    "addr:street":"W 35Th Street Suite",
    "iso:country":"US",
    "sg:address":"240 W 35th Street Suite 504",
    "sg:city":"New York",
    "sg:classifiers":[
        {
            "category":"Real Estate",
            "subcategory":"Real Estate Services",
            "type":"Services"
        }
    ],
    "sg:phone":"+1 212 685 5152",
    "sg:postcode":"10001",
    "sg:province":"NY",
    "wof:name":"Heim Real Estate",
    "wof:placetype":"venue"
},
  "geometry": {"coordinates":[-73.991309,40.75213],"type":"Point"}
}