{
  "type": "Feature",
  "properties": {
    "iso:country":"US",
    "sg:address":"80 University Pl Fl 3",
    "sg:city":"New York",
    "sg:classifiers":[
        {
            "category":"Health Services",
            "subcategory":"Doctor",
            "type":"Services"
        }
    ],
    "sg:phone":"+1 212 989 9380",
    "sg:postcode":"10003",
    "sg:province":"NY",
    "wof:name":"Dollar Mark MD",
    "wof:placetype":"venue"
},
  "geometry": {"coordinates":[-73.993493,40.733521],"type":"Point"}
}