{
  "type": "Feature",
  "properties": {
    "addr:full":"581 Warburton Ave Hastings On Hdsn NY 10706",
    "addr:housenumber":"581",
    "addr:postcode":"10706",
    "addr:street":"Warburton Ave",
    "iso:country":"US",
    "sg:address":"581 Warburton Ave",
    "sg:city":"Hastings On Hdsn",
    "sg:classifiers":[
        {
            "category":"Real Estate",
            "subcategory":"Architect",
            "type":"Services"
        }
    ],
    "sg:phone":"+1 914 478 2442",
    "sg:postcode":"10706",
    "sg:province":"NY",
    "wof:name":"Four Dimensional Designs Inc",
    "wof:placetype":"venue"
},
  "geometry": {"coordinates":[-73.88214000000001,40.995924],"type":"Point"}
}