{
  "type": "Feature",
  "properties": {
    "iso:country":"US",
    "sg:address":"319 Lathrop Rd",
    "sg:city":"Syracuse",
    "sg:classifiers":[
        {
            "category":"Building & Trades",
            "subcategory":"Construction",
            "type":"Services"
        }
    ],
    "sg:phone":"+1 315 488 4187",
    "sg:postcode":"13219",
    "sg:province":"NY",
    "sg:tags":[
        "home",
        "improvement"
    ],
    "wof:name":"Metell's House & Yard Svc",
    "wof:placetype":"venue"
},
  "geometry": {"coordinates":[-76.205322,43.040459],"type":"Point"}
}