{
  "type": "Feature",
  "properties": {
    "iso:country":"US",
    "sg:address":"2002 Cropsey Avenue",
    "sg:city":"Brooklyn",
    "sg:classifiers":[
        {
            "category":"Food & Beverages",
            "subcategory":"Liquor & Beverages",
            "type":"Retail Goods"
        }
    ],
    "sg:phone":"+1 718 372 8152",
    "sg:postcode":"11214",
    "sg:province":"NY",
    "sg:tags":[
        "beer",
        "spirit",
        "wine"
    ],
    "wof:name":"Manna Liquors",
    "wof:placetype":"venue"
},
  "geometry": {"coordinates":[-74.002808,40.600047],"type":"Point"}
}