{
  "type": "Feature",
  "properties": {
    "iso:country":"US",
    "sg:address":"1146 Woodsboro Farms",
    "sg:city":"Webster",
    "sg:classifiers":[
        {
            "category":"Building & Trades",
            "subcategory":"Construction",
            "type":"Services"
        }
    ],
    "sg:phone":"+1 585 872 9030",
    "sg:postcode":"14580",
    "sg:province":"NY",
    "sg:tags":[
        "painter"
    ],
    "wof:name":"Penfield Painting Inc",
    "wof:placetype":"venue"
},
  "geometry": {"coordinates":[-77.441434,43.245388],"type":"Point"}
}