{
  "type": "Feature",
  "properties": {
    "addr:full":"2045 Story Avenue Bronx NY 10473",
    "addr:housenumber":"2045",
    "addr:postcode":"10473",
    "addr:street":"Story Avenue",
    "iso:country":"US",
    "sg:address":"2045 Story Avenue",
    "sg:city":"Bronx",
    "sg:classifiers":[
        {
            "category":"Social Services",
            "subcategory":"Child Care",
            "type":"Services"
        }
    ],
    "sg:phone":"+1 718 239 4618",
    "sg:postcode":"10473",
    "sg:province":"NY",
    "sg:tags":[
        "day"
    ],
    "wof:name":"Primary Foundation Educational Center",
    "wof:placetype":"venue"
},
  "geometry": {"coordinates":[-73.85427300000001,40.824831],"type":"Point"}
}