{
  "type": "Feature",
  "properties": {
    "iso:country":"US",
    "sg:address":"27 1st St",
    "sg:city":"Syosset",
    "sg:classifiers":[
        {
            "category":"Professional",
            "subcategory":"Management & Consulting",
            "type":"Services"
        }
    ],
    "sg:phone":"+1 516 921 3311",
    "sg:postcode":"11791",
    "sg:province":"NY",
    "sg:tags":[
        "nonphysical",
        "r",
        "commercial"
    ],
    "wof:name":"Jay L Roth & Associates Inc",
    "wof:placetype":"venue"
},
  "geometry": {"coordinates":[-73.506328,40.827331],"type":"Point"}
}