{
  "type": "Feature",
  "properties": {
    "addr:full":"310 State St Montgomery NY 12534",
    "addr:housenumber":"310",
    "addr:postcode":"12534",
    "addr:street":"State St",
    "iso:country":"US",
    "sg:address":"310 State St",
    "sg:city":"Montgomery",
    "sg:classifiers":[
        {
            "category":"Building & Trades",
            "subcategory":"Pest Control",
            "type":"Services"
        }
    ],
    "sg:phone":"+1 845 457 3520",
    "sg:postcode":"12534",
    "sg:province":"NY",
    "wof:name":"Thomas Pest Control Svc Inc",
    "wof:placetype":"venue"
},
  "geometry": {"coordinates":[-73.789114,42.253894],"type":"Point"}
}