{
  "type": "Feature",
  "properties": {
    "iso:country":"US",
    "sg:address":"331 Tompkins Avenue",
    "sg:city":"Brooklyn",
    "sg:classifiers":[
        {
            "category":"Food & Beverages",
            "subcategory":"Groceries & Convenience Stores",
            "type":"Retail Goods"
        }
    ],
    "sg:phone":"+1 718 455 2511",
    "sg:postcode":"11216",
    "sg:province":"NY",
    "wof:name":"Tompkins Food Market",
    "wof:placetype":"venue"
},
  "geometry": {"coordinates":[-73.944427,40.686631],"type":"Point"}
}