{
  "type": "Feature",
  "properties": {
    "iso:country":"US",
    "sg:address":"23 Portsmouth Ter",
    "sg:city":"Rochester",
    "sg:classifiers":[
        {
            "category":"Wholesale",
            "subcategory":"Office Equipment",
            "type":"Manufacturing & Wholesale Goods"
        }
    ],
    "sg:phone":"+1 585 244 6995",
    "sg:postcode":"14607",
    "sg:province":"NY",
    "wof:name":"P O S Systems Mgt Rochstr",
    "wof:placetype":"venue"
},
  "geometry": {"coordinates":[-77.581985,43.15269],"type":"Point"}
}