{
  "type": "Feature",
  "properties": {
    "addr:full":"4491 Amboy Rd Staten Island NY 10312",
    "addr:housenumber":"4491",
    "addr:postcode":"10312",
    "addr:street":"Amboy Rd",
    "iso:country":"US",
    "sg:address":"4491 Amboy Rd",
    "sg:city":"Staten Island",
    "sg:classifiers":[
        {
            "category":"Professional",
            "subcategory":"Detective & Security Services",
            "type":"Services"
        }
    ],
    "sg:phone":"+1 718 317 9100",
    "sg:postcode":"10312",
    "sg:province":"NY",
    "sg:tags":[
        "investigator"
    ],
    "wof:name":"Security One Investigation",
    "wof:placetype":"venue"
},
  "geometry": {"coordinates":[-74.164237,40.543391],"type":"Point"}
}