{
  "type": "Feature",
  "properties": {
    "iso:country":"US",
    "sg:address":"190 Old Country Rd",
    "sg:city":"Melville",
    "sg:classifiers":[
        {
            "category":"Professional",
            "type":"Services"
        }
    ],
    "sg:phone":"+1 631 645 3248",
    "sg:postcode":"11747",
    "sg:province":"NY",
    "wof:name":"Coachfranca",
    "wof:placetype":"venue"
},
  "geometry": {"coordinates":[-73.41372699999999,40.794472],"type":"Point"}
}