{
  "type": "Feature",
  "properties": {
    "addr:full":"79 Wheatley Rd Old Westbury NY 11568",
    "addr:housenumber":"79",
    "addr:postcode":"11568",
    "addr:street":"Wheatley Rd",
    "iso:country":"US",
    "sg:address":"79 Wheatley Rd",
    "sg:city":"Old Westbury",
    "sg:classifiers":[
        {
            "category":"Real Estate",
            "subcategory":"Real Estate Operator",
            "type":"Services"
        }
    ],
    "sg:phone":"+1 516 626 3487",
    "sg:postcode":"11568",
    "sg:province":"NY",
    "sg:tags":[
        "owner"
    ],
    "wof:name":"Johnson Ave Realty Co",
    "wof:placetype":"venue"
},
  "geometry": {"coordinates":[-73.599603,40.788677],"type":"Point"}
}