{
  "type": "Feature",
  "properties": {
    "iso:country":"US",
    "sg:address":"437 Middle Grove Rd",
    "sg:city":"Middle Grove",
    "sg:classifiers":[
        {
            "category":"Building & Trades",
            "subcategory":"Construction",
            "type":"Services"
        }
    ],
    "sg:phone":"+1 518 587 2305",
    "sg:postcode":"12850",
    "sg:province":"NY",
    "sg:tags":[
        "wireless"
    ],
    "wof:name":"Mannwireles  Ltd",
    "wof:placetype":"venue"
},
  "geometry": {"coordinates":[-73.92048200000001,43.087224],"type":"Point"}
}