{
  "type": "Feature",
  "properties": {
    "addr:full":"130 E 67th Street New York NY 10021",
    "addr:housenumber":"130",
    "addr:postcode":"10021",
    "addr:street":"E 67Th Street",
    "iso:country":"US",
    "sg:address":"130 E 67th Street",
    "sg:city":"New York",
    "sg:classifiers":[
        {
            "category":"Health Services",
            "subcategory":"Doctor",
            "type":"Services"
        }
    ],
    "sg:phone":"+1 212 879 6824",
    "sg:postcode":"10021",
    "sg:province":"NY",
    "wof:name":"Lauer Simeon",
    "wof:placetype":"venue"
},
  "geometry": {"coordinates":[-73.964518,40.767227],"type":"Point"}
}