{
  "type": "Feature",
  "properties": {
    "addr:full":"569 Lexington Ave New York NY 10022",
    "addr:housenumber":"569",
    "addr:postcode":"10022",
    "addr:street":"Lexington Ave",
    "iso:country":"US",
    "sg:address":"569 Lexington Ave",
    "sg:city":"New York",
    "sg:classifiers":[
        {
            "category":"Personal",
            "subcategory":"Barber",
            "type":"Services"
        }
    ],
    "sg:phone":"+1   ",
    "sg:postcode":"10022",
    "sg:province":"NY",
    "sg:tags":[
        "shop",
        "beauty"
    ],
    "wof:name":"Giannattasio Pat",
    "wof:placetype":"venue"
},
  "geometry": {"coordinates":[-73.972099,40.756618],"type":"Point"}
}