{
  "type": "Feature",
  "properties": {
    "addr:full":"725 5th Ave Fl 20 New York NY 10022",
    "addr:housenumber":"725;20",
    "addr:postcode":"10022",
    "addr:street":"5Th Ave Fl",
    "iso:country":"US",
    "sg:address":"725 5th Ave Fl 20",
    "sg:city":"New York",
    "sg:classifiers":[
        {
            "category":"Banks & Credit Unions",
            "subcategory":"Bank",
            "type":"Services"
        }
    ],
    "sg:phone":"+1 212 223 4367",
    "sg:postcode":"10022",
    "sg:province":"NY",
    "wof:name":"Industrial And Commercial Bank Of China",
    "wof:placetype":"venue"
},
  "geometry": {"coordinates":[-73.97421900000001,40.762571],"type":"Point"}
}