{
  "type": "Feature",
  "properties": {
    "iso:country":"US",
    "sg:address":"54 N Main St",
    "sg:city":"Brockport",
    "sg:classifiers":[
        {
            "category":"Personal",
            "subcategory":"Beauty Salon",
            "type":"Services"
        }
    ],
    "sg:phone":"+1 585 637 3800",
    "sg:postcode":"14420",
    "sg:province":"NY",
    "sg:tags":[
        "shop"
    ],
    "wof:name":"Shear Images",
    "wof:placetype":"venue"
},
  "geometry": {"coordinates":[-77.93709200000001,43.219829],"type":"Point"}
}