{
  "type": "Feature",
  "properties": {
    "addr:full":"37 S Main St Cohocton NY 14826",
    "addr:housenumber":"37",
    "addr:postcode":"14826",
    "addr:street":"S Main St",
    "iso:country":"US",
    "sg:address":"37 S Main St",
    "sg:city":"Cohocton",
    "sg:classifiers":[
        {
            "category":"Government",
            "subcategory":"Office",
            "type":"Public Place"
        }
    ],
    "sg:phone":"+1 585 384 5939",
    "sg:postcode":"14826",
    "sg:province":"NY",
    "wof:name":"Intermediate Care Facility",
    "wof:placetype":"venue"
},
  "geometry": {"coordinates":[-77.494778,42.495491],"type":"Point"}
}