{
  "type": "Feature",
  "properties": {
    "addr:full":"1345 Ave of the Americas New York NY 10105",
    "addr:postcode":"10105",
    "addr:street":"1345 Ave Of The Americas",
    "iso:country":"US",
    "sg:address":"1345 Ave of the Americas",
    "sg:city":"New York",
    "sg:classifiers":[
        {
            "category":"Professional",
            "subcategory":"Lawyer & Legal Services",
            "type":"Services"
        }
    ],
    "sg:phone":"+1 212 603 6300",
    "sg:postcode":"10105",
    "sg:province":"NY",
    "wof:name":"D'erocle John",
    "wof:placetype":"venue"
},
  "geometry": {"coordinates":[-73.97840100000001,40.762299],"type":"Point"}
}