{
  "type": "Feature",
  "properties": {
    "addr:full":"655 E Meadow Ave East Meadow NY 11554",
    "addr:housenumber":"655",
    "addr:postcode":"11554",
    "addr:street":"E Meadow Ave",
    "iso:country":"US",
    "sg:address":"655 E Meadow Ave",
    "sg:city":"East Meadow",
    "sg:classifiers":[
        {
            "category":"Professional",
            "subcategory":"Accounting & Tax Preparation",
            "type":"Services"
        }
    ],
    "sg:phone":"+1 516 409 5400",
    "sg:postcode":"11554",
    "sg:province":"NY",
    "sg:tags":[
        "accountant",
        "referral"
    ],
    "wof:name":"Hummel & Butler CPA Inc",
    "wof:placetype":"venue"
},
  "geometry": {"coordinates":[-73.552798,40.709155],"type":"Point"}
}