{
  "type": "Feature",
  "properties": {
    "iso:country":"US",
    "sg:address":"21 Spring St",
    "sg:city":"New York",
    "sg:classifiers":[
        {
            "category":"Health Services",
            "subcategory":"Doctor",
            "type":"Services"
        }
    ],
    "sg:phone":"+1   ",
    "sg:postcode":"10012",
    "sg:province":"NY",
    "sg:tags":[
        "medical"
    ],
    "wof:name":"Allan Sicignano Dr",
    "wof:placetype":"venue"
},
  "geometry": {"coordinates":[-73.99509999999999,40.721507],"type":"Point"}
}