{
  "type": "Feature",
  "properties": {
    "addr:full":"176 E 161st St Bronx NY 10451",
    "addr:housenumber":"176",
    "addr:postcode":"10451",
    "addr:street":"E 161St St",
    "iso:country":"US",
    "sg:address":"176 E 161st St",
    "sg:city":"Bronx",
    "sg:classifiers":[
        {
            "category":"Education",
            "subcategory":"Special Training",
            "type":"Public Place"
        }
    ],
    "sg:phone":"+1 718 585 2080",
    "sg:postcode":"10451",
    "sg:province":"NY",
    "sg:tags":[
        "program"
    ],
    "wof:name":"Security Enforcement Training",
    "wof:placetype":"venue"
},
  "geometry": {"coordinates":[-73.92162500000001,40.826506],"type":"Point"}
}