{
  "type": "Feature",
  "properties": {
    "iso:country":"US",
    "sg:address":"8 Woods End",
    "sg:city":"Pittsford",
    "sg:classifiers":[
        {
            "category":"Real Estate",
            "subcategory":"Real Estate Agent",
            "type":"Services"
        }
    ],
    "sg:phone":"+1 585 248 0181",
    "sg:postcode":"14534",
    "sg:province":"NY",
    "wof:name":"Skb Enterprises",
    "wof:placetype":"venue"
},
  "geometry": {"coordinates":[-77.507183,43.07834],"type":"Point"}
}