{
  "type": "Feature",
  "properties": {
    "addr:full":"675 Walton Ave Bronx NY 10451",
    "addr:housenumber":"675",
    "addr:postcode":"10451",
    "addr:street":"Walton Ave",
    "iso:country":"US",
    "sg:address":"675 Walton Ave",
    "sg:city":"Bronx",
    "sg:classifiers":[
        {
            "category":"Personal",
            "subcategory":"Beauty Salon",
            "type":"Services"
        }
    ],
    "sg:phone":"+1 718 665 1236",
    "sg:postcode":"10451",
    "sg:province":"NY",
    "wof:name":"Stern Beauty",
    "wof:placetype":"venue"
},
  "geometry": {"coordinates":[-73.925505,40.825062],"type":"Point"}
}