{
  "type": "Feature",
  "properties": {
    "addr:full":"147 Parkdale Dr North Babylon NY 11703",
    "addr:housenumber":"147",
    "addr:postcode":"11703",
    "addr:street":"Parkdale Dr North",
    "iso:country":"US",
    "sg:address":"147 Parkdale Dr",
    "sg:city":"North Babylon",
    "sg:classifiers":[
        {
            "category":"Professional",
            "type":"Services"
        }
    ],
    "sg:phone":"+1 631 254 4309",
    "sg:postcode":"11703",
    "sg:province":"NY",
    "sg:tags":[
        "writer"
    ],
    "wof:name":"Jedi For Hire",
    "wof:placetype":"venue"
},
  "geometry": {"coordinates":[-73.31135999999999,40.735637],"type":"Point"}
}