{
  "type": "Feature",
  "properties": {
    "addr:full":"117 Montauk Hwy Westhampton NY 11977",
    "addr:housenumber":"117",
    "addr:postcode":"11977",
    "addr:street":"Montauk Hwy",
    "iso:country":"US",
    "sg:address":"117 Montauk Hwy",
    "sg:city":"Westhampton",
    "sg:classifiers":[
        {
            "category":"Insurance",
            "subcategory":"Insurance Agent",
            "type":"Services"
        }
    ],
    "sg:phone":"+1 631 288 1486",
    "sg:postcode":"11977",
    "sg:province":"NY",
    "wof:name":"William G Hentschel Inc",
    "wof:placetype":"venue"
},
  "geometry": {"coordinates":[-72.675271,40.816404],"type":"Point"}
}