{
  "type": "Feature",
  "properties": {
    "addr:full":"1615 58th St Brooklyn NY 11204",
    "addr:housenumber":"1615",
    "addr:postcode":"11204",
    "addr:street":"58Th St",
    "iso:country":"US",
    "sg:address":"1615 58th St",
    "sg:city":"Brooklyn",
    "sg:classifiers":[
        {
            "category":"Professional",
            "subcategory":"Accounting & Tax Preparation",
            "type":"Services"
        }
    ],
    "sg:phone":"+1 718 633 8800",
    "sg:postcode":"11204",
    "sg:province":"NY",
    "sg:tags":[
        "accountant"
    ],
    "wof:name":"Karl Schwarzmer",
    "wof:placetype":"venue"
},
  "geometry": {"coordinates":[-73.989897,40.625611],"type":"Point"}
}