{
  "type": "Feature",
  "properties": {
    "iso:country":"US",
    "sg:address":"15 Shady Oaks Trl",
    "sg:city":"Spencerport",
    "sg:classifiers":[
        {
            "category":"Building & Trades",
            "subcategory":"Construction",
            "type":"Services"
        }
    ],
    "sg:phone":"+1 585 349 4335",
    "sg:postcode":"14559",
    "sg:province":"NY",
    "sg:tags":[
        "contractor"
    ],
    "wof:name":"Naviclean Building Svc Inc",
    "wof:placetype":"venue"
},
  "geometry": {"coordinates":[-77.757192,43.20092],"type":"Point"}
}