{
  "type": "Feature",
  "properties": {
    "addr:full":"161 W. 54th St #1404 New York NY 10019",
    "addr:housenumber":"161",
    "addr:postcode":"10019",
    "addr:street":"W. 54Th St # 1404",
    "iso:country":"US",
    "sg:address":"161 W. 54th St #1404",
    "sg:city":"New York",
    "sg:classifiers":[
        {
            "category":"Health Services",
            "subcategory":"Doctor",
            "type":"Services"
        },
        {
            "category":"Farming",
            "subcategory":"Crops",
            "type":"Manufacturing & Wholesale Goods"
        },
        {
            "category":"Health Services",
            "subcategory":"Health Practitioner",
            "type":"Services"
        }
    ],
    "sg:phone":"+1 212 581 0001",
    "sg:postcode":"10019",
    "sg:province":"NY",
    "sg:tags":[
        "nutritionist",
        "fertility",
        "gynecologist",
        "obstetrician"
    ],
    "sg:website":"www.laughingsagewellness.com",
    "wof:name":"Laughing Sage Wellness",
    "wof:placetype":"venue"
},
  "geometry": {"coordinates":[-73.980771,40.763319],"type":"Point"}
}