{
  "type": "Feature",
  "properties": {
    "iso:country":"US",
    "sg:address":"8267 E Main Rd",
    "sg:city":"Le Roy",
    "sg:classifiers":[
        {
            "category":"Airline",
            "type":"Transportation"
        }
    ],
    "sg:phone":"+1 585 768 4560",
    "sg:postcode":"14482",
    "sg:province":"NY",
    "sg:tags":[
        "airport"
    ],
    "wof:name":"Leroy Aviation Services Incorporation",
    "wof:placetype":"venue"
},
  "geometry": {"coordinates":[-77.93924199999999,42.981296],"type":"Point"}
}