{
  "type": "Feature",
  "properties": {
    "iso:country":"US",
    "sg:address":"114 Glenmont Dr",
    "sg:city":"Rochester",
    "sg:classifiers":[
        {
            "category":"Professional",
            "subcategory":"Printing & Photocopies",
            "type":"Services"
        }
    ],
    "sg:phone":"+1 585 544 2289",
    "sg:postcode":"14617",
    "sg:province":"NY",
    "sg:tags":[
        "photographers-commercial"
    ],
    "wof:name":"Laragy Photography",
    "wof:placetype":"venue"
},
  "geometry": {"coordinates":[-77.595421,43.238819],"type":"Point"}
}