{
  "type": "Feature",
  "properties": {
    "iso:country":"US",
    "sg:address":"15 Fairway Dr",
    "sg:city":"Batavia",
    "sg:classifiers":[
        {
            "category":"Building & Trades",
            "subcategory":"Construction",
            "type":"Services"
        }
    ],
    "sg:phone":"+1 585 344 3561",
    "sg:postcode":"14020",
    "sg:province":"NY",
    "sg:tags":[
        "contractor"
    ],
    "wof:name":"Superionor Drywall and Pntg",
    "wof:placetype":"venue"
},
  "geometry": {"coordinates":[-78.21727300000001,43.003482],"type":"Point"}
}