{
  "type": "Feature",
  "properties": {
    "iso:country":"US",
    "sg:address":"10 13th St",
    "sg:city":"Bohemia",
    "sg:classifiers":[
        {
            "category":"Building & Trades",
            "subcategory":"Landscaping Services",
            "type":"Services"
        }
    ],
    "sg:phone":"+1 631 567 1409",
    "sg:postcode":"11716",
    "sg:province":"NY",
    "wof:name":"Woodland Tree Service",
    "wof:placetype":"venue"
},
  "geometry": {"coordinates":[-73.102667,40.761107],"type":"Point"}
}