{
  "type": "Feature",
  "properties": {
    "iso:country":"US",
    "sg:address":"24904 Hillside Ave",
    "sg:city":"Bellerose",
    "sg:classifiers":[
        {
            "category":"Home & Garden",
            "subcategory":"Building Materials",
            "type":"Retail Goods"
        },
        {
            "category":"Professional",
            "subcategory":"Business Services",
            "type":"Services"
        }
    ],
    "sg:phone":"+1 718 831 6647",
    "sg:postcode":"11426",
    "sg:province":"NY",
    "sg:tags":[
        "marble-natural-wholesale",
        "marble-natural",
        "manufacturer"
    ],
    "wof:name":"Moh's & Sons Marble Tile",
    "wof:placetype":"venue"
},
  "geometry": {"coordinates":[-73.722633,40.734261],"type":"Point"}
}