{
  "type": "Feature",
  "properties": {
    "addr:full":"506 Ave L Brooklyn NY 11230",
    "addr:housenumber":"506",
    "addr:postcode":"11230",
    "addr:street":"Ave L",
    "iso:country":"US",
    "sg:address":"506 Ave L",
    "sg:city":"Brooklyn",
    "sg:classifiers":[
        {
            "category":"Organizations",
            "subcategory":"Religious Organization",
            "type":"Services"
        }
    ],
    "sg:phone":"+1 718 252 7747",
    "sg:postcode":"11230",
    "sg:province":"NY",
    "sg:tags":[
        "clergy"
    ],
    "wof:name":"Israel Grossman",
    "wof:placetype":"venue"
},
  "geometry": {"coordinates":[-73.969618,40.619316],"type":"Point"}
}