{
  "type": "Feature",
  "properties": {
    "addr:full":"26 Nevins St Brooklyn NY 11217",
    "addr:housenumber":"26",
    "addr:postcode":"11217",
    "addr:street":"Nevins St",
    "iso:country":"US",
    "sg:address":"26 Nevins St",
    "sg:city":"Brooklyn",
    "sg:classifiers":[
        {
            "category":"Restaurant",
            "type":"Food & Drink"
        }
    ],
    "sg:menulink":"http://www.allmenus.com/ny/brooklyn/156795-kennedy-fried-chicken--pizza/menu/",
    "sg:phone":"+1 718 875 5399",
    "sg:postcode":"11217",
    "sg:province":"NY",
    "sg:tags":[
        "american",
        "pizza"
    ],
    "wof:name":"Kennedy Fried Chicken & Pizza",
    "wof:placetype":"venue"
},
  "geometry": {"coordinates":[-73.981345,40.688024],"type":"Point"}
}