{
  "type": "Feature",
  "properties": {
    "addr:full":"1707 Route 6 Carmel NY 10512",
    "addr:housenumber":"1707",
    "addr:postcode":"10512",
    "addr:street":"Route 6",
    "iso:country":"US",
    "sg:address":"1707 Route 6",
    "sg:city":"Carmel",
    "sg:classifiers":[
        {
            "category":"Personal",
            "type":"Services"
        }
    ],
    "sg:phone":"+1 845 621 1200",
    "sg:postcode":"10512",
    "sg:province":"NY",
    "sg:tags":[
        "party",
        "planning",
        "event"
    ],
    "sg:website":"www.rentaparty.com",
    "wof:name":"Cartwright Party Rentals",
    "wof:placetype":"venue"
},
  "geometry": {"coordinates":[-73.678802,41.421299],"type":"Point"}
}