{
  "type": "Feature",
  "properties": {
    "iso:country":"US",
    "sg:address":"12 Beatty Ave",
    "sg:city":"Clinton",
    "sg:classifiers":[
        {
            "category":"Utilities",
            "type":"Services"
        }
    ],
    "sg:phone":"+1   ",
    "sg:postcode":"13323",
    "sg:province":"NY",
    "sg:tags":[
        "sweeping",
        "snowplowing",
        "lot",
        "parking"
    ],
    "wof:name":"Rotondos Inc",
    "wof:placetype":"venue"
},
  "geometry": {"coordinates":[-75.37009399999999,43.051587],"type":"Point"}
}