{
  "type": "Feature",
  "properties": {
    "addr:full":"511 5th Avenue Fl 2 New York NY 10017",
    "addr:housenumber":"511;2",
    "addr:postcode":"10017",
    "addr:street":"5Th Avenue Fl",
    "iso:country":"US",
    "sg:address":"511 5th Avenue Fl 2",
    "sg:city":"New York",
    "sg:classifiers":[
        {
            "category":"Professional",
            "subcategory":"Employment Agencies",
            "type":"Services"
        }
    ],
    "sg:phone":"+1 212 353 9005",
    "sg:postcode":"10017",
    "sg:province":"NY",
    "wof:name":"De Novo Legal",
    "wof:placetype":"venue"
},
  "geometry": {"coordinates":[-73.980458,40.75398],"type":"Point"}
}