{
  "type": "Feature",
  "properties": {
    "addr:full":"114 Manhattan Ave Brooklyn NY 11206",
    "addr:housenumber":"114",
    "addr:postcode":"11206",
    "addr:street":"Manhattan Ave",
    "iso:country":"US",
    "sg:address":"114 Manhattan Ave",
    "sg:city":"Brooklyn",
    "sg:classifiers":[
        {
            "category":"Wholesale",
            "subcategory":"Apparel",
            "type":"Manufacturing & Wholesale Goods"
        }
    ],
    "sg:phone":"+1 718 599 7277",
    "sg:postcode":"11206",
    "sg:province":"NY",
    "sg:tags":[
        "lady",
        "clothing",
        "sportswear"
    ],
    "wof:name":"M & D Sportswear Corp",
    "wof:placetype":"venue"
},
  "geometry": {"coordinates":[-73.944687,40.705739],"type":"Point"}
}