{
  "type": "Feature",
  "properties": {
    "addr:full":"1504 Old Country Rd  Westbury NY 11590",
    "addr:housenumber":"1504",
    "addr:postcode":"11590",
    "addr:street":"Old Country Rd",
    "iso:country":"US",
    "sg:address":"1504 Old Country Rd ",
    "sg:city":"Westbury",
    "sg:classifiers":[
        {
            "category":"Coffee & Tea",
            "type":"Food & Drink"
        },
        {
            "category":"Cafe",
            "type":"Food & Drink"
        }
    ],
    "sg:menulink":"http://www.allmenus.com/ny/garden-city/223730-chock-cafe/menu/",
    "sg:phone":"+1 516 357 9591",
    "sg:postcode":"11590",
    "sg:province":"NY",
    "sg:tags":[
        "wrap",
        "american",
        "sandwich"
    ],
    "wof:name":"Chock Cafe",
    "wof:placetype":"venue"
},
  "geometry": {"coordinates":[-73.59548100000001,40.746444],"type":"Point"}
}