{
  "type": "Feature",
  "properties": {
    "addr:full":"1981 Fillmore Ave Buffalo NY 14214",
    "addr:housenumber":"1981",
    "addr:postcode":"14214",
    "addr:street":"Fillmore Ave",
    "iso:country":"US",
    "sg:address":"1981 Fillmore Ave",
    "sg:city":"Buffalo",
    "sg:classifiers":[
        {
            "category":"Autos & Motor Vehicles",
            "subcategory":"Fuel & Gas Station",
            "type":"Retail Goods"
        }
    ],
    "sg:phone":"+1   ",
    "sg:postcode":"14214",
    "sg:province":"NY",
    "sg:tags":[
        "station",
        "gasoline"
    ],
    "wof:name":"A Plus Mini Market",
    "wof:placetype":"venue"
},
  "geometry": {"coordinates":[-78.83922,42.928253],"type":"Point"}
}