{
  "type": "Feature",
  "properties": {
    "addr:full":"4301 21st Street Long Island City NY 11101",
    "addr:housenumber":"4301",
    "addr:postcode":"11101",
    "addr:street":"21St Street",
    "iso:country":"US",
    "sg:address":"4301 21st Street",
    "sg:city":"Long Island City",
    "sg:classifiers":[
        {
            "category":"Retail",
            "subcategory":"Repair Shop",
            "type":"Services"
        }
    ],
    "sg:phone":"+1 718 361 0946",
    "sg:postcode":"11101",
    "sg:province":"NY",
    "sg:tags":[
        "reupholstery",
        "furniture"
    ],
    "wof:name":"J Quintana Upholstery Corporation",
    "wof:placetype":"venue"
},
  "geometry": {"coordinates":[-73.94572599999999,40.750376],"type":"Point"}
}