{
  "type": "Feature",
  "properties": {
    "addr:full":"20 E Sunrise Hwy Valley Stream NY 11581",
    "addr:housenumber":"20",
    "addr:postcode":"11581",
    "addr:street":"E Sunrise Hwy",
    "iso:country":"US",
    "sg:address":"20 E Sunrise Hwy",
    "sg:city":"Valley Stream",
    "sg:classifiers":[
        {
            "category":"Shopping",
            "subcategory":"Mobile Phones",
            "type":"Retail Goods"
        }
    ],
    "sg:phone":"+1 516 887 0700",
    "sg:postcode":"11581",
    "sg:province":"NY",
    "wof:name":"Global Payment Technologies Executive Office",
    "wof:placetype":"venue"
},
  "geometry": {"coordinates":[-73.699799,40.659401],"type":"Point"}
}