{
  "type": "Feature",
  "properties": {
    "iso:country":"US",
    "sg:address":"79 Rosalia St",
    "sg:city":"Buffalo",
    "sg:classifiers":[
        {
            "category":"Professional",
            "subcategory":"Detective & Security Services",
            "type":"Services"
        }
    ],
    "sg:phone":"+1 716 873 1100",
    "sg:postcode":"14216",
    "sg:province":"NY",
    "sg:tags":[
        "car",
        "armored"
    ],
    "wof:name":"Brink's Inc",
    "wof:placetype":"venue"
},
  "geometry": {"coordinates":[-78.873143,42.947266],"type":"Point"}
}