{
  "type": "Feature",
  "properties": {
    "addr:full":"117 Meserole Ave Brooklyn NY 11222",
    "addr:housenumber":"117",
    "addr:postcode":"11222",
    "addr:street":"Meserole Ave",
    "iso:country":"US",
    "sg:address":"117 Meserole Ave",
    "sg:city":"Brooklyn",
    "sg:classifiers":[
        {
            "category":"Shopping",
            "subcategory":"Music",
            "type":"Retail Goods"
        }
    ],
    "sg:phone":"+1 718 349 3323",
    "sg:postcode":"11222",
    "sg:province":"NY",
    "sg:tags":[
        "compact",
        "record",
        "disc",
        "tape"
    ],
    "wof:name":"T Wireless",
    "wof:placetype":"venue"
},
  "geometry": {"coordinates":[-73.95196,40.727405],"type":"Point"}
}