{
  "type": "Feature",
  "properties": {
    "iso:country":"US",
    "sg:address":"108 Sand Pine Ln",
    "sg:city":"Albany",
    "sg:classifiers":[
        {
            "category":"Travel",
            "subcategory":"Travel Agent",
            "type":"Entertainment"
        }
    ],
    "sg:phone":"+1 518 453 3692",
    "sg:postcode":"12203",
    "sg:province":"NY",
    "sg:tags":[
        "agency",
        "bureau"
    ],
    "wof:name":"Vision Quest Tours & Travel",
    "wof:placetype":"venue"
},
  "geometry": {"coordinates":[-73.840457,42.67366],"type":"Point"}
}