{
  "type": "Feature",
  "properties": {
    "addr:full":"343 W Broadway New York NY 10013",
    "addr:housenumber":"343",
    "addr:postcode":"10013",
    "addr:street":"W Broadway",
    "iso:country":"US",
    "sg:address":"343 W Broadway",
    "sg:city":"New York",
    "sg:classifiers":[
        {
            "category":"Restaurant",
            "type":"Food & Drink"
        }
    ],
    "sg:menulink":"http://www.allmenus.com/ny/new-york/269687-novecento-new-york/menu/",
    "sg:phone":"+1 212 925 4706",
    "sg:postcode":"10013",
    "sg:province":"NY",
    "sg:tags":[
        "argentinean"
    ],
    "wof:name":"Novecento New York",
    "wof:placetype":"venue"
},
  "geometry": {"coordinates":[-74.00351999999999,40.722655],"type":"Point"}
}