{
  "type": "Feature",
  "properties": {
    "iso:country":"US",
    "sg:address":"1 S Main St",
    "sg:city":"Pittsford",
    "sg:classifiers":[
        {
            "category":"Retail",
            "subcategory":"Portrait Studio",
            "type":"Services"
        }
    ],
    "sg:phone":"+1 585 248 9100",
    "sg:postcode":"14534",
    "sg:province":"NY",
    "sg:tags":[
        "photographer"
    ],
    "wof:name":"Pamela Roberts Photography",
    "wof:placetype":"venue"
},
  "geometry": {"coordinates":[-77.51576300000001,43.090094],"type":"Point"}
}