{
  "type": "Feature",
  "properties": {
    "iso:country":"US",
    "sg:address":"3107 State Hwy 11B",
    "sg:city":"Nicholville",
    "sg:classifiers":[
        {
            "category":"Retail",
            "subcategory":"Repair Shop",
            "type":"Services"
        }
    ],
    "sg:phone":"+1 315 328 5579",
    "sg:postcode":"12965",
    "sg:province":"NY",
    "sg:tags":[
        "ironwork"
    ],
    "wof:name":"Artistry In Iron",
    "wof:placetype":"venue"
},
  "geometry": {"coordinates":[-74.676407,44.692503],"type":"Point"}
}