{
  "type": "Feature",
  "properties": {
    "addr:full":"296 9th Ave New York NY 10001",
    "addr:housenumber":"296",
    "addr:postcode":"10001",
    "addr:street":"9Th Ave",
    "iso:country":"US",
    "sg:address":"296 9th Ave",
    "sg:city":"New York",
    "sg:classifiers":[
        {
            "category":"Organizations",
            "subcategory":"Non-profit Organization",
            "type":"Services"
        }
    ],
    "sg:phone":"+1 212 924 0167",
    "sg:postcode":"10001",
    "sg:province":"NY",
    "sg:tags":[
        "service/non-profit",
        "community"
    ],
    "sg:website":"www.holyapostlessoupkitchen.org/",
    "wof:name":"Holy Apostles Soup Kitchen",
    "wof:placetype":"venue"
},
  "geometry": {"coordinates":[-73.999014,40.749395],"type":"Point"}
}