{
  "type": "Feature",
  "properties": {
    "addr:full":"493 3rd Ave New York NY 10016",
    "addr:housenumber":"493",
    "addr:postcode":"10016",
    "addr:street":"3Rd Ave",
    "iso:country":"US",
    "sg:address":"493 3rd Ave",
    "sg:city":"New York",
    "sg:classifiers":[
        {
            "category":"Bars & Pubs",
            "subcategory":"Sports Bar",
            "type":"Food & Drink"
        },
        {
            "category":"Restaurant",
            "type":"Food & Drink"
        }
    ],
    "sg:phone":"+1 212 683 2645",
    "sg:postcode":"10016",
    "sg:province":"NY",
    "sg:tags":[
        "traditional",
        "american"
    ],
    "sg:website":"www.mercurybareast.com",
    "wof:name":"Mercury Bar",
    "wof:placetype":"venue"
},
  "geometry": {"coordinates":[-73.97815300000001,40.745164],"type":"Point"}
}