{
  "type": "Feature",
  "properties": {
    "addr:full":"4184 N Buffalo Rd Orchard Park NY 14127",
    "addr:housenumber":"4184",
    "addr:postcode":"14127",
    "addr:street":"N Buffalo Rd",
    "iso:country":"US",
    "sg:address":"4184 N Buffalo Rd",
    "sg:city":"Orchard Park",
    "sg:classifiers":[
        {
            "category":"Shopping",
            "subcategory":"Bicycles & Sporting Goods",
            "type":"Retail Goods"
        }
    ],
    "sg:phone":"+1   ",
    "sg:postcode":"14127",
    "sg:province":"NY",
    "wof:name":"Good Earth Goods",
    "wof:placetype":"venue"
},
  "geometry": {"coordinates":[-78.74464999999999,42.770639],"type":"Point"}
}