{
  "type": "Feature",
  "properties": {
    "addr:full":"13780A W Lake Rd Hammondsport NY 14840",
    "addr:housenumber":"13780a",
    "addr:postcode":"14840",
    "addr:street":"W Lake Rd",
    "iso:country":"US",
    "sg:address":"13780A W Lake Rd",
    "sg:city":"Hammondsport",
    "sg:classifiers":[
        {
            "category":"Restaurant",
            "type":"Food & Drink"
        }
    ],
    "sg:phone":"+1 607 868 3636",
    "sg:postcode":"14840",
    "sg:province":"NY",
    "sg:tags":[
        "style",
        "american",
        "family"
    ],
    "wof:name":"Lakeside Restaurant",
    "wof:placetype":"venue"
},
  "geometry": {"coordinates":[-77.156569,42.509152],"type":"Point"}
}