{
  "type": "Feature",
  "properties": {
    "addr:full":"126 Front St Vestal NY 13850",
    "addr:housenumber":"126",
    "addr:postcode":"13850",
    "addr:street":"Front St",
    "iso:country":"US",
    "sg:address":"126 Front St",
    "sg:city":"Vestal",
    "sg:classifiers":[
        {
            "category":"Food & Beverages",
            "subcategory":"Specialty",
            "type":"Retail Goods"
        }
    ],
    "sg:phone":"+1 607 786 1238",
    "sg:postcode":"13850",
    "sg:province":"NY",
    "sg:tags":[
        "tea",
        "coffee"
    ],
    "wof:name":"Classic Latte",
    "wof:placetype":"venue"
},
  "geometry": {"coordinates":[-76.06049299999999,42.083283],"type":"Point"}
}