{
  "type": "Feature",
  "properties": {
    "addr:full":"1620 E 172nd St Bronx NY 10472",
    "addr:housenumber":"1620",
    "addr:postcode":"10472",
    "addr:street":"E 172Nd St",
    "iso:country":"US",
    "sg:address":"1620 E 172nd St",
    "sg:city":"Bronx",
    "sg:classifiers":[
        {
            "category":"Manufacturing",
            "subcategory":"Petroleum Products",
            "type":"Manufacturing & Wholesale Goods"
        }
    ],
    "sg:phone":"+1   ",
    "sg:postcode":"10472",
    "sg:province":"NY",
    "sg:tags":[
        "lubricating",
        "mfg"
    ],
    "wof:name":"Gallery 172",
    "wof:placetype":"venue"
},
  "geometry": {"coordinates":[-73.87432200000001,40.831793],"type":"Point"}
}