{
  "type": "Feature",
  "properties": {
    "iso:country":"US",
    "sg:address":"65 Glen Ellyn Way",
    "sg:city":"Rochester",
    "sg:classifiers":[
        {
            "category":"Shopping",
            "subcategory":"Stationery & Office Supplies",
            "type":"Retail Goods"
        }
    ],
    "sg:phone":"+1   ",
    "sg:postcode":"14618",
    "sg:province":"NY",
    "wof:name":"Stationery Etc",
    "wof:placetype":"venue"
},
  "geometry": {"coordinates":[-77.564954,43.135231],"type":"Point"}
}