{
  "type": "Feature",
  "properties": {
    "addr:full":"3 Catholic Way Castletn On Hdsn NY 12033",
    "addr:housenumber":"3",
    "addr:postcode":"12033",
    "addr:street":"Catholic Way",
    "iso:country":"US",
    "sg:address":"3 Catholic Way",
    "sg:city":"Castletn On Hdsn",
    "sg:classifiers":[
        {
            "category":"Organizations",
            "subcategory":"Religious Organization",
            "type":"Services"
        }
    ],
    "sg:phone":"+1 518 732 2155",
    "sg:postcode":"12033",
    "sg:province":"NY",
    "sg:tags":[
        "church"
    ],
    "wof:name":"Sacred Heart Catholic Church",
    "wof:placetype":"venue"
},
  "geometry": {"coordinates":[-73.75372299999999,42.526736],"type":"Point"}
}