{
  "type": "Feature",
  "properties": {
    "addr:full":"1418 Harding Park Bronx NY 10473",
    "addr:housenumber":"1418",
    "addr:postcode":"10473",
    "addr:street":"Harding Park",
    "iso:country":"US",
    "sg:address":"1418 Harding Park",
    "sg:city":"Bronx",
    "sg:classifiers":[
        {
            "category":"Building & Trades",
            "subcategory":"Construction",
            "type":"Services"
        }
    ],
    "sg:phone":"+1 718 620 0777",
    "sg:postcode":"10473",
    "sg:province":"NY",
    "sg:tags":[
        "contractor"
    ],
    "wof:name":"A & J Quality Renovations",
    "wof:placetype":"venue"
},
  "geometry": {"coordinates":[-73.85226299999999,40.810029],"type":"Point"}
}