{
  "type": "Feature",
  "properties": {
    "iso:country":"US",
    "sg:address":"25 School Ln",
    "sg:city":"Scarsdale",
    "sg:classifiers":[
        {
            "category":"Education",
            "subcategory":"Special Training",
            "type":"Public Place"
        }
    ],
    "sg:phone":"+1 914 723 1169",
    "sg:postcode":"10583",
    "sg:province":"NY",
    "sg:tags":[
        "child",
        "day",
        "care"
    ],
    "sg:website":"www.hbms.org",
    "wof:name":"Hoff-Barthelson Music School",
    "wof:placetype":"venue"
},
  "geometry": {"coordinates":[-73.803731,40.988297],"type":"Point"}
}