{
  "type": "Feature",
  "properties": {
    "addr:full":"3689 California Rd Orchard Park NY 14127",
    "addr:housenumber":"3689",
    "addr:postcode":"14127",
    "addr:street":"California Rd",
    "iso:country":"US",
    "sg:address":"3689 California Rd",
    "sg:city":"Orchard Park",
    "sg:classifiers":[
        {
            "category":"Building & Trades",
            "subcategory":"Construction",
            "type":"Services"
        }
    ],
    "sg:phone":"+1 716 667 7065",
    "sg:postcode":"14127",
    "sg:province":"NY",
    "sg:tags":[
        "contractor"
    ],
    "wof:name":"Burke LLC",
    "wof:placetype":"venue"
},
  "geometry": {"coordinates":[-78.787471,42.788431],"type":"Point"}
}