{
  "type": "Feature",
  "properties": {
    "iso:country":"US",
    "sg:address":"3 Opal St",
    "sg:city":"Holbrook",
    "sg:classifiers":[
        {
            "category":"Health Services",
            "subcategory":"Doctor",
            "type":"Services"
        }
    ],
    "sg:phone":"+1 631 567 4554",
    "sg:postcode":"11741",
    "sg:province":"NY",
    "sg:tags":[
        "obstetrician",
        "gynecologist"
    ],
    "wof:name":"Kramer Barry MD",
    "wof:placetype":"venue"
},
  "geometry": {"coordinates":[-73.0681,40.786598],"type":"Point"}
}