{
  "type": "Feature",
  "properties": {
    "iso:country":"US",
    "sg:address":"414 Main St",
    "sg:city":"Catskill",
    "sg:classifiers":[
        {
            "category":"Communications",
            "subcategory":"Newspaper",
            "type":"Services"
        }
    ],
    "sg:phone":"+1 518 943 2100",
    "sg:postcode":"12414",
    "sg:province":"NY",
    "sg:tags":[
        "print",
        "medium"
    ],
    "wof:name":"Catskill Daily Mail the",
    "wof:placetype":"venue"
},
  "geometry": {"coordinates":[-73.8657,42.2202],"type":"Point"}
}