{
  "type": "Feature",
  "properties": {
    "iso:country":"US",
    "sg:address":"8 Holly Ct",
    "sg:city":"North Babylon",
    "sg:classifiers":[
        {
            "category":"Shopping",
            "subcategory":"Jewelry",
            "type":"Retail Goods"
        }
    ],
    "sg:phone":"+1   ",
    "sg:postcode":"11703",
    "sg:province":"NY",
    "wof:name":"James Sutera",
    "wof:placetype":"venue"
},
  "geometry": {"coordinates":[-73.33139,40.745913],"type":"Point"}
}