{
  "type": "Feature",
  "properties": {
    "iso:country":"US",
    "sg:address":"22 Church St",
    "sg:city":"Gouverneur",
    "sg:classifiers":[
        {
            "category":"Social Services",
            "type":"Services"
        }
    ],
    "sg:phone":"+1 315 287 1650",
    "sg:postcode":"13642",
    "sg:province":"NY",
    "sg:tags":[
        "organization",
        "welfare"
    ],
    "wof:name":"Head Start",
    "wof:placetype":"venue"
},
  "geometry": {"coordinates":[-75.466932,44.335233],"type":"Point"}
}