{
  "type": "Feature",
  "properties": {
    "iso:country":"US",
    "sg:address":"8214 Turin Rd",
    "sg:city":"Rome",
    "sg:classifiers":[
        {
            "category":"Retail",
            "subcategory":"Auto Repair",
            "type":"Services"
        }
    ],
    "sg:phone":"+1   ",
    "sg:postcode":"13440",
    "sg:province":"NY",
    "sg:tags":[
        "car",
        "used"
    ],
    "wof:name":"Sales & Service",
    "wof:placetype":"venue"
},
  "geometry": {"coordinates":[-75.462586,43.260687],"type":"Point"}
}