{
  "type": "Feature",
  "properties": {
    "iso:country":"US",
    "sg:address":"200 Schermerhorn St",
    "sg:city":"Brooklyn",
    "sg:classifiers":[
        {
            "category":"Coffee & Tea",
            "type":"Food & Drink"
        }
    ],
    "sg:phone":"+1 718 222 8868",
    "sg:postcode":"11217",
    "sg:province":"NY",
    "sg:website":"renaissancejavacafe.com/",
    "wof:name":"Renaissance Java Cafe",
    "wof:placetype":"venue"
},
  "geometry": {"coordinates":[-73.985174,40.688627],"type":"Point"}
}