{
  "type": "Feature",
  "properties": {
    "iso:country":"US",
    "sg:address":"3125 Carman Rd",
    "sg:city":"Schenectady",
    "sg:classifiers":[
        {
            "category":"Home & Garden",
            "subcategory":"Household Appliances",
            "type":"Retail Goods"
        },
        {
            "category":"Shopping",
            "subcategory":"Computers & Home Electronics",
            "type":"Retail Goods"
        }
    ],
    "sg:phone":"+1 518 355 1020",
    "sg:postcode":"12303",
    "sg:province":"NY",
    "sg:tags":[
        "major",
        "radio",
        "television",
        "store"
    ],
    "sg:website":"http://www.townetv.com",
    "wof:name":"Towne TV Audio & Appliances",
    "wof:placetype":"venue"
},
  "geometry": {"coordinates":[-73.94130699999999,42.761339],"type":"Point"}
}