{
  "type": "Feature",
  "properties": {
    "iso:country":"US",
    "sg:address":"1167 2nd Avenue",
    "sg:city":"New York",
    "sg:classifiers":[
        {
            "category":"Food & Beverages",
            "subcategory":"Candy",
            "type":"Retail Goods"
        }
    ],
    "sg:phone":"+1 212 308 0618",
    "sg:postcode":"10021",
    "sg:province":"NY",
    "sg:tags":[
        "store"
    ],
    "wof:name":"Sweet & Sour 1167 Corporation",
    "wof:placetype":"venue"
},
  "geometry": {"coordinates":[-73.963227,40.762113],"type":"Point"}
}