{
  "type": "Feature",
  "properties": {
    "iso:country":"US",
    "sg:address":"32 Congress St",
    "sg:city":"Saratoga Springs",
    "sg:classifiers":[
        {
            "category":"Shopping",
            "subcategory":"Florist",
            "type":"Retail Goods"
        }
    ],
    "sg:phone":"+1 518 584 3770",
    "sg:postcode":"12866",
    "sg:province":"NY",
    "wof:name":"Schrade's Posie Peddler",
    "wof:placetype":"venue"
},
  "geometry": {"coordinates":[-73.787736,43.078557],"type":"Point"}
}