{
  "type": "Feature",
  "properties": {
    "addr:full":"1650 Eastern Pkwy Schenectady NY 12309",
    "addr:housenumber":"1650",
    "addr:postcode":"12309",
    "addr:street":"Eastern Pkwy",
    "iso:country":"US",
    "sg:address":"1650 Eastern Pkwy",
    "sg:city":"Schenectady",
    "sg:classifiers":[
        {
            "category":"Building & Trades",
            "subcategory":"Equipment Rental",
            "type":"Services"
        }
    ],
    "sg:phone":"+1   ",
    "sg:postcode":"12309",
    "sg:province":"NY",
    "sg:tags":[
        "leasing"
    ],
    "wof:name":"Aarons F89",
    "wof:placetype":"venue"
},
  "geometry": {"coordinates":[-73.91247199999999,42.806747],"type":"Point"}
}