{
  "type": "Feature",
  "properties": {
    "iso:country":"US",
    "sg:address":"487 Butternut Brook Rd",
    "sg:city":"Portville",
    "sg:classifiers":[
        {
            "category":"Food & Beverages",
            "subcategory":"Bakery",
            "type":"Retail Goods"
        }
    ],
    "sg:phone":"+1   ",
    "sg:postcode":"14770",
    "sg:province":"NY",
    "wof:name":"Butternut",
    "wof:placetype":"venue"
},
  "geometry": {"coordinates":[-78.308269,42.020246],"type":"Point"}
}