{
  "type": "Feature",
  "properties": {
    "addr:full":"161 Canal St New York NY 10013",
    "addr:housenumber":"161",
    "addr:postcode":"10013",
    "addr:street":"Canal St",
    "iso:country":"US",
    "sg:address":"161 Canal St",
    "sg:city":"New York",
    "sg:classifiers":[
        {
            "category":"Shopping",
            "subcategory":"Jewelry",
            "type":"Retail Goods"
        }
    ],
    "sg:phone":"+1 212 966 2332",
    "sg:postcode":"10013",
    "sg:province":"NY",
    "sg:tags":[
        "jeweler"
    ],
    "wof:name":"Golden Gifts",
    "wof:placetype":"venue"
},
  "geometry": {"coordinates":[-73.996645,40.716455],"type":"Point"}
}