{
  "type": "Feature",
  "properties": {
    "addr:full":"221 W 37th St New York NY 10018",
    "addr:housenumber":"221",
    "addr:postcode":"10018",
    "addr:street":"W 37Th St",
    "iso:country":"US",
    "sg:address":"221 W 37th St",
    "sg:city":"New York",
    "sg:classifiers":[
        {
            "category":"Wholesale",
            "subcategory":"Fruits & Vegetables",
            "type":"Manufacturing & Wholesale Goods"
        }
    ],
    "sg:phone":"+1 212 921 0305",
    "sg:postcode":"10018",
    "sg:province":"NY",
    "sg:tags":[
        "veggie"
    ],
    "wof:name":"Banana Lemon",
    "wof:placetype":"venue"
},
  "geometry": {"coordinates":[-73.990178,40.75354],"type":"Point"}
}