{
  "type": "Feature",
  "properties": {
    "addr:full":"222 River St Warrensburg NY 12885",
    "addr:housenumber":"222",
    "addr:postcode":"12885",
    "addr:street":"River St",
    "iso:country":"US",
    "sg:address":"222 River St",
    "sg:city":"Warrensburg",
    "sg:classifiers":[
        {
            "category":"Bars & Pubs",
            "type":"Food & Drink"
        }
    ],
    "sg:phone":"+1   ",
    "sg:postcode":"12885",
    "sg:province":"NY",
    "sg:tags":[
        "drinking"
    ],
    "wof:name":"Seafood & Spirits",
    "wof:placetype":"venue"
},
  "geometry": {"coordinates":[-73.785691,43.4851],"type":"Point"}
}