{
  "type": "Feature",
  "properties": {
    "iso:country":"US",
    "sg:address":"5503 Ridge Rd W",
    "sg:city":"Spencerport",
    "sg:classifiers":[
        {
            "category":"Autos & Motor Vehicles",
            "subcategory":"Automobile Sales",
            "type":"Retail Goods"
        }
    ],
    "sg:phone":"+1 585 349 0170",
    "sg:postcode":"14420",
    "sg:province":"NY",
    "sg:tags":[
        "car",
        "dealer"
    ],
    "wof:name":"Ridge Auto Sales",
    "wof:placetype":"venue"
},
  "geometry": {"coordinates":[-77.836941,43.221736],"type":"Point"}
}