{
  "type": "Feature",
  "properties": {
    "addr:full":"5016 13th Avenue Brooklyn NY 11219",
    "addr:housenumber":"5016",
    "addr:postcode":"11219",
    "addr:street":"13Th Avenue",
    "iso:country":"US",
    "sg:address":"5016 13th Avenue",
    "sg:city":"Brooklyn",
    "sg:classifiers":[
        {
            "category":"Shopping",
            "subcategory":"Crafts & Fabrics",
            "type":"Retail Goods"
        }
    ],
    "sg:phone":"+1 718 437 5154",
    "sg:postcode":"11219",
    "sg:province":"NY",
    "sg:tags":[
        "store"
    ],
    "wof:name":"Sew Splendid Trimmings & Notions",
    "wof:placetype":"venue"
},
  "geometry": {"coordinates":[-73.993222,40.634136],"type":"Point"}
}