{
  "type": "Feature",
  "properties": {
    "addr:full":"520 Madison Ave New York NY 10022",
    "addr:housenumber":"520",
    "addr:postcode":"10022",
    "addr:street":"Madison Ave",
    "iso:country":"US",
    "sg:address":"520 Madison Ave",
    "sg:city":"New York",
    "sg:classifiers":[
        {
            "category":"Banks & Credit Unions",
            "subcategory":"Bank",
            "type":"Services"
        }
    ],
    "sg:phone":"+1 212 381 4900",
    "sg:postcode":"10022",
    "sg:province":"NY",
    "sg:tags":[
        "firm",
        "loan",
        "private",
        "equity"
    ],
    "wof:name":"Carlyle Group",
    "wof:placetype":"venue"
},
  "geometry": {"coordinates":[-73.974767,40.760106],"type":"Point"}
}