{
  "type": "Feature",
  "properties": {
    "iso:country":"US",
    "sg:address":"4715 Richardson Ave",
    "sg:city":"Bronx",
    "sg:classifiers":[
        {
            "category":"Freight",
            "type":"Transportation"
        }
    ],
    "sg:phone":"+1 718 325 4481",
    "sg:postcode":"10470",
    "sg:province":"NY",
    "sg:tags":[
        "trucking"
    ],
    "wof:name":"Saf Trucking Inc",
    "wof:placetype":"venue"
},
  "geometry": {"coordinates":[-73.85015,40.90563],"type":"Point"}
}