{
  "type": "Feature",
  "properties": {
    "addr:full":"304 Straub Rd Rochester NY 14626",
    "addr:housenumber":"304",
    "addr:postcode":"14626",
    "addr:street":"Straub Rd",
    "iso:country":"US",
    "sg:address":"304 Straub Rd",
    "sg:city":"Rochester",
    "sg:classifiers":[
        {
            "category":"Shopping",
            "subcategory":"Gifts & Souvenirs",
            "type":"Retail Goods"
        }
    ],
    "sg:phone":"+1   ",
    "sg:postcode":"14626",
    "sg:province":"NY",
    "wof:name":"Major League Sports Cards",
    "wof:placetype":"venue"
},
  "geometry": {"coordinates":[-77.73054999999999,43.198096],"type":"Point"}
}