{
  "type": "Feature",
  "properties": {
    "addr:full":"667 Jericho Tpke Huntington Sta NY 11746",
    "addr:housenumber":"667",
    "addr:postcode":"11746",
    "addr:street":"Jericho Tpke",
    "iso:country":"US",
    "sg:address":"667 Jericho Tpke",
    "sg:city":"Huntington Sta",
    "sg:classifiers":[
        {
            "category":"Shopping",
            "subcategory":"Bicycles & Sporting Goods",
            "type":"Retail Goods"
        }
    ],
    "sg:phone":"+1 631 425 9500",
    "sg:postcode":"11746",
    "sg:province":"NY",
    "sg:tags":[
        "equipment",
        "exercise"
    ],
    "wof:name":"Fitness Showrooms Of LI",
    "wof:placetype":"venue"
},
  "geometry": {"coordinates":[-73.38677800000001,40.834105],"type":"Point"}
}