{
  "type": "Feature",
  "properties": {
    "addr:full":"410 Lakeville Rd Ste 105 New Hyde Park NY 11042",
    "addr:housenumber":"410;105",
    "addr:postcode":"11042",
    "addr:street":"Lakeville Rd Ste;Hyde Park",
    "iso:country":"US",
    "sg:address":"410 Lakeville Rd Ste 105",
    "sg:city":"New Hyde Park",
    "sg:classifiers":[
        {
            "category":"Health Services",
            "subcategory":"Doctor",
            "type":"Services"
        }
    ],
    "sg:phone":"+1 516 465 5470",
    "sg:postcode":"11042",
    "sg:province":"NY",
    "wof:name":"North Shore LIJ Dermatology",
    "wof:placetype":"venue"
},
  "geometry": {"coordinates":[-73.68801999999999,40.734966],"type":"Point"}
}