{
  "type": "Feature",
  "properties": {
    "iso:country":"US",
    "sg:address":"18 Dunmore Rd",
    "sg:city":"New City",
    "sg:classifiers":[
        {
            "category":"Professional",
            "subcategory":"Management & Consulting",
            "type":"Services"
        },
        {
            "category":"Shopping",
            "subcategory":"Gifts & Souvenirs",
            "type":"Retail Goods"
        }
    ],
    "sg:phone":"+1 845 638 3880",
    "sg:postcode":"10956",
    "sg:province":"NY",
    "sg:tags":[
        "sales",
        "announcement",
        "direct",
        "invitation"
    ],
    "wof:name":"Leslie's Party Boutique",
    "wof:placetype":"venue"
},
  "geometry": {"coordinates":[-73.995514,41.178551],"type":"Point"}
}