{
  "type": "Feature",
  "properties": {
    "iso:country":"US",
    "sg:address":"30 Johnson St",
    "sg:city":"Buffalo",
    "sg:classifiers":[
        {
            "category":"Government",
            "subcategory":"Office",
            "type":"Public Place"
        }
    ],
    "sg:phone":"+1 716 827 6767",
    "sg:postcode":"14218",
    "sg:province":"NY",
    "sg:tags":[
        "educational",
        "program",
        "administrative"
    ],
    "wof:name":"School Department",
    "wof:placetype":"venue"
},
  "geometry": {"coordinates":[-78.82620199999999,42.813082],"type":"Point"}
}