{
  "type": "Feature",
  "properties": {
    "iso:country":"US",
    "sg:address":"970 N Broadway",
    "sg:city":"Yonkers",
    "sg:classifiers":[
        {
            "category":"Health Services",
            "subcategory":"Doctor",
            "type":"Services"
        }
    ],
    "sg:phone":"+1 914 375 2229",
    "sg:postcode":"10701",
    "sg:province":"NY",
    "sg:tags":[
        "physician",
        "surgeon"
    ],
    "wof:name":"Riverside Pediatrics",
    "wof:placetype":"venue"
},
  "geometry": {"coordinates":[-73.88426699999999,40.97007],"type":"Point"}
}