{
  "type": "Feature",
  "properties": {
    "iso:country":"US",
    "sg:address":"29 W 47th St",
    "sg:city":"New York",
    "sg:classifiers":[
        {
            "category":"Shopping",
            "subcategory":"Jewelry",
            "type":"Retail Goods"
        }
    ],
    "sg:phone":"+1 212 302 4428",
    "sg:postcode":"10036",
    "sg:province":"NY",
    "wof:name":"Milan Casting Corporation",
    "wof:placetype":"venue"
},
  "geometry": {"coordinates":[-73.980124,40.75756],"type":"Point"}
}