{
  "type": "Feature",
  "properties": {
    "iso:country":"US",
    "sg:address":"2044 Westchester Ave",
    "sg:city":"Bronx",
    "sg:classifiers":[
        {
            "category":"Home & Garden",
            "subcategory":"Hardware",
            "type":"Retail Goods"
        }
    ],
    "sg:phone":"+1 718 829 6665",
    "sg:postcode":"10462",
    "sg:province":"NY",
    "sg:tags":[
        "store"
    ],
    "sg:website":"http://www.truevalue.com",
    "wof:name":"Georges True Value Hardware",
    "wof:placetype":"venue"
},
  "geometry": {"coordinates":[-73.856347,40.833708],"type":"Point"}
}