{
  "type": "Feature",
  "properties": {
    "addr:full":"3961 Laconia Ave Bronx NY 10466",
    "addr:housenumber":"3961",
    "addr:postcode":"10466",
    "addr:street":"Laconia Ave",
    "iso:country":"US",
    "sg:address":"3961 Laconia Ave",
    "sg:city":"Bronx",
    "sg:classifiers":[
        {
            "category":"Personal",
            "subcategory":"Beauty Salon",
            "type":"Services"
        }
    ],
    "sg:phone":"+1 718 231 4584",
    "sg:postcode":"10466",
    "sg:province":"NY",
    "wof:name":"Olga's Beauty Salon",
    "wof:placetype":"venue"
},
  "geometry": {"coordinates":[-73.84953299999999,40.883901],"type":"Point"}
}