{
  "type": "Feature",
  "properties": {
    "iso:country":"US",
    "sg:address":"300 State St",
    "sg:city":"Binghamton",
    "sg:classifiers":[
        {
            "category":"Manufacturing",
            "subcategory":"Printing",
            "type":"Manufacturing & Wholesale Goods"
        }
    ],
    "sg:phone":"+1 607 724 3001",
    "sg:postcode":"13901",
    "sg:province":"NY",
    "sg:tags":[
        "publisher"
    ],
    "wof:name":"Gould Publications",
    "wof:placetype":"venue"
},
  "geometry": {"coordinates":[-75.910917,42.103071],"type":"Point"}
}