{
  "type": "Feature",
  "properties": {
    "iso:country":"US",
    "sg:address":"431 Centre Island Rd",
    "sg:city":"Central Islip",
    "sg:classifiers":[
        {
            "category":"Recreation",
            "type":"Entertainment"
        }
    ],
    "sg:phone":"+1   ",
    "sg:postcode":"11771",
    "sg:province":"NY",
    "sg:tags":[
        "training",
        "sport"
    ],
    "wof:name":"New York Baseball Academy",
    "wof:placetype":"venue"
},
  "geometry": {"coordinates":[-73.520332,40.89993],"type":"Point"}
}