{
  "type": "Feature",
  "properties": {
    "iso:country":"US",
    "sg:address":"3 New York Plaza",
    "sg:city":"New York",
    "sg:classifiers":[
        {
            "category":"Professional",
            "subcategory":"Lawyer & Legal Services",
            "type":"Services"
        }
    ],
    "sg:phone":"+1 212 267 2300",
    "sg:postcode":"10004",
    "sg:province":"NY",
    "wof:name":"Kalmus Micheal Attys",
    "wof:placetype":"venue"
},
  "geometry": {"coordinates":[-74.01111400000001,40.703586],"type":"Point"}
}