{
  "type": "Feature",
  "properties": {
    "addr:full":"462 Fashion Ave New York NY 10018",
    "addr:housenumber":"462",
    "addr:postcode":"10018",
    "addr:street":"Fashion Ave",
    "iso:country":"US",
    "sg:address":"462 Fashion Ave",
    "sg:city":"New York",
    "sg:classifiers":[
        {
            "category":"Coffee & Tea",
            "type":"Food & Drink"
        }
    ],
    "sg:menulink":"http://www.allmenus.com/ny/new-york/113406-starbucks-coffee/menu/",
    "sg:phone":"+1 212 279 6432",
    "sg:postcode":"10018",
    "sg:province":"NY",
    "sg:tags":[
        "american"
    ],
    "wof:name":"Starbucks Coffee",
    "wof:placetype":"venue"
},
  "geometry": {"coordinates":[-73.990075,40.751699],"type":"Point"}
}