{
  "type": "Feature",
  "properties": {
    "iso:country":"US",
    "sg:address":"499 Ocean Ave",
    "sg:city":"Brooklyn",
    "sg:classifiers":[
        {
            "category":"Building & Trades",
            "subcategory":"Construction",
            "type":"Services"
        }
    ],
    "sg:phone":"+1 718 826 9241",
    "sg:postcode":"11226",
    "sg:province":"NY",
    "sg:tags":[
        "contractor"
    ],
    "wof:name":"Ocean Construction",
    "wof:placetype":"venue"
},
  "geometry": {"coordinates":[-73.961113,40.650598],"type":"Point"}
}