{
  "type": "Feature",
  "properties": {
    "addr:full":"670 Sunrise Hwy Baldwin NY 11510",
    "addr:housenumber":"670",
    "addr:postcode":"11510",
    "addr:street":"Sunrise Hwy",
    "iso:country":"US",
    "sg:address":"670 Sunrise Hwy",
    "sg:city":"Baldwin",
    "sg:classifiers":[
        {
            "category":"Education",
            "subcategory":"Junior College",
            "type":"Public Place"
        }
    ],
    "sg:phone":"+1 516 546 5466",
    "sg:postcode":"11510",
    "sg:province":"NY",
    "sg:tags":[
        "technical",
        "institute"
    ],
    "wof:name":"H & R Block Tax Svc",
    "wof:placetype":"venue"
},
  "geometry": {"coordinates":[-73.613947,40.656425],"type":"Point"}
}