{
  "type": "Feature",
  "properties": {
    "addr:full":"27 Skillman St Brooklyn NY 11205",
    "addr:housenumber":"27",
    "addr:postcode":"11205",
    "addr:street":"Skillman St",
    "iso:country":"US",
    "sg:address":"27 Skillman St",
    "sg:city":"Brooklyn",
    "sg:classifiers":[
        {
            "category":"Professional",
            "type":"Services"
        }
    ],
    "sg:phone":"+1 718 834 1900",
    "sg:postcode":"11205",
    "sg:province":"NY",
    "sg:tags":[
        "establishment"
    ],
    "wof:name":"Abraham Lichtenstein",
    "wof:placetype":"venue"
},
  "geometry": {"coordinates":[-73.957594,40.697616],"type":"Point"}
}