{
  "type": "Feature",
  "properties": {
    "addr:full":"581 Ontario Dr Ontario NY 14519",
    "addr:housenumber":"581",
    "addr:postcode":"14519",
    "addr:street":"Ontario Dr",
    "iso:country":"US",
    "sg:address":"581 Ontario Dr",
    "sg:city":"Ontario",
    "sg:classifiers":[
        {
            "category":"Insurance",
            "subcategory":"Hazard Insurance",
            "type":"Services"
        }
    ],
    "sg:phone":"+1 585 987 8326",
    "sg:postcode":"14519",
    "sg:province":"NY",
    "sg:tags":[
        "commercial",
        "business"
    ],
    "wof:name":"Forman Cogan & Cline",
    "wof:placetype":"venue"
},
  "geometry": {"coordinates":[-77.351724,43.27733],"type":"Point"}
}