{
  "type": "Feature",
  "properties": {
    "iso:country":"US",
    "sg:address":"3999 Hylan Blvd",
    "sg:city":"Staten Island",
    "sg:classifiers":[
        {
            "category":"Home & Garden",
            "subcategory":"Household Appliances",
            "type":"Retail Goods"
        }
    ],
    "sg:phone":"+1 718 948 8787",
    "sg:postcode":"10308",
    "sg:province":"NY",
    "sg:tags":[
        "repair"
    ],
    "wof:name":"Community Maytag Home Appliance Center",
    "wof:placetype":"venue"
},
  "geometry": {"coordinates":[-74.147003,40.541],"type":"Point"}
}