{
  "type": "Feature",
  "properties": {
    "addr:full":"4801 Fort Hamilton Pkwy Brooklyn NY 11219",
    "addr:housenumber":"4801",
    "addr:postcode":"11219",
    "addr:street":"Fort Hamilton Pkwy",
    "iso:country":"US",
    "sg:address":"4801 Fort Hamilton Pkwy",
    "sg:city":"Brooklyn",
    "sg:classifiers":[
        {
            "category":"Health Services",
            "subcategory":"Doctor",
            "type":"Services"
        }
    ],
    "sg:phone":"+1 718 972 9712",
    "sg:postcode":"11219",
    "sg:province":"NY",
    "sg:tags":[
        "medical"
    ],
    "wof:name":"Thelusmond Louis Herve MD",
    "wof:placetype":"venue"
},
  "geometry": {"coordinates":[-73.99690200000001,40.638699],"type":"Point"}
}