{
  "type": "Feature",
  "properties": {
    "addr:full":"1100 Westchester Ave Bronx NY 10459",
    "addr:housenumber":"1100",
    "addr:postcode":"10459",
    "addr:street":"Westchester Ave",
    "iso:country":"US",
    "sg:address":"1100 Westchester Ave",
    "sg:city":"Bronx",
    "sg:classifiers":[
        {
            "category":"Retail",
            "subcategory":"Repair Shop",
            "type":"Services"
        }
    ],
    "sg:phone":"+1 718 685 5866",
    "sg:postcode":"10459",
    "sg:province":"NY",
    "sg:tags":[
        "lock",
        "locksmith"
    ],
    "wof:name":"24 Hour Locksmith",
    "wof:placetype":"venue"
},
  "geometry": {"coordinates":[-73.88970999999999,40.8258],"type":"Point"}
}