{
  "type": "Feature",
  "properties": {
    "addr:full":"607 S Main St Horseheads NY 14845",
    "addr:housenumber":"607",
    "addr:postcode":"14845",
    "addr:street":"S Main St",
    "iso:country":"US",
    "sg:address":"607 S Main St",
    "sg:city":"Horseheads",
    "sg:classifiers":[
        {
            "category":"Autos & Motor Vehicles",
            "subcategory":"Auto Supplies",
            "type":"Retail Goods"
        }
    ],
    "sg:phone":"+1 607 739 5663",
    "sg:postcode":"14845",
    "sg:province":"NY",
    "sg:tags":[
        "automobile",
        "parts"
    ],
    "wof:name":"NAPA Auto Parts",
    "wof:placetype":"venue"
},
  "geometry": {"coordinates":[-76.820521,42.167439],"type":"Point"}
}