{
  "type": "Feature",
  "properties": {
    "addr:full":"339 E 116th St New York NY 10029",
    "addr:housenumber":"339",
    "addr:postcode":"10029",
    "addr:street":"E 116Th St",
    "iso:country":"US",
    "sg:address":"339 E 116th St",
    "sg:city":"New York",
    "sg:classifiers":[
        {
            "category":"Arts & Performance",
            "subcategory":"Theater",
            "type":"Entertainment"
        }
    ],
    "sg:phone":"+1 212 426 0863",
    "sg:postcode":"10029",
    "sg:province":"NY",
    "sg:tags":[
        "group"
    ],
    "wof:name":"Black Box Entertainment Co",
    "wof:placetype":"venue"
},
  "geometry": {"coordinates":[-73.936066,40.796456],"type":"Point"}
}