{
  "type": "Feature",
  "properties": {
    "iso:country":"US",
    "sg:address":"28 Smith Clove Rd",
    "sg:city":"Central Valley",
    "sg:classifiers":[
        {
            "category":"Government",
            "subcategory":"Post Office",
            "type":"Public Place"
        }
    ],
    "sg:phone":"+1 845 928 6016",
    "sg:postcode":"10917",
    "sg:province":"NY",
    "wof:name":"United States Postal Service",
    "wof:placetype":"venue"
},
  "geometry": {"coordinates":[-74.119698,41.333],"type":"Point"}
}