{
  "type": "Feature",
  "properties": {
    "addr:full":"1751 Lexington Ave New York NY 10029",
    "addr:housenumber":"1751",
    "addr:postcode":"10029",
    "addr:street":"Lexington Ave",
    "iso:country":"US",
    "sg:address":"1751 Lexington Ave",
    "sg:city":"New York",
    "sg:classifiers":[
        {
            "category":"Retail",
            "subcategory":"Laundry & Dry Cleaning",
            "type":"Services"
        }
    ],
    "sg:phone":"+1 212 426 8334",
    "sg:postcode":"10029",
    "sg:province":"NY",
    "wof:name":"A One Laundry",
    "wof:placetype":"venue"
},
  "geometry": {"coordinates":[-73.945052,40.793687],"type":"Point"}
}