{
  "type": "Feature",
  "properties": {
    "addr:full":"3 Remington Ave Canton NY 13667",
    "addr:housenumber":"3",
    "addr:postcode":"13667",
    "addr:street":"Remington Ave",
    "iso:country":"US",
    "sg:address":"3 Remington Ave",
    "sg:city":"Canton",
    "sg:classifiers":[
        {
            "category":"Education",
            "subcategory":"School",
            "type":"Public Place"
        }
    ],
    "sg:phone":"+1 315 386 1616",
    "sg:postcode":"13667",
    "sg:province":"NY",
    "wof:name":"St Lawrence-LEWIS Boces",
    "wof:placetype":"venue"
},
  "geometry": {"coordinates":[-74.995519,44.806964],"type":"Point"}
}