{
  "type": "Feature",
  "properties": {
    "iso:country":"US",
    "sg:address":"400 E 72 St",
    "sg:city":"New York",
    "sg:classifiers":[
        {
            "category":"Real Estate",
            "subcategory":"Real Estate Agent",
            "type":"Services"
        }
    ],
    "sg:phone":"+1 212 628 2600",
    "sg:postcode":"10021",
    "sg:province":"NY",
    "sg:tags":[
        "broker"
    ],
    "wof:name":"Charles Birdoff & Co",
    "wof:placetype":"venue"
},
  "geometry": {"coordinates":[-73.953749,40.766853],"type":"Point"}
}