{
  "type": "Feature",
  "properties": {
    "addr:full":"18233 Spook Hill Rd Adams NY 13605",
    "addr:postcode":"18233;13605",
    "addr:street":"Spook Hill Rd",
    "iso:country":"US",
    "sg:address":"18233 Spook Hill Rd",
    "sg:city":"Adams",
    "sg:classifiers":[
        {
            "category":"Shopping",
            "subcategory":"Beauty & Cosmetics",
            "type":"Retail Goods"
        }
    ],
    "sg:phone":"+1   ",
    "sg:postcode":"13605",
    "sg:province":"NY",
    "sg:tags":[
        "merchandise"
    ],
    "wof:name":"Mary Kay Cosmetics",
    "wof:placetype":"venue"
},
  "geometry": {"coordinates":[-76.01594799999999,43.836054],"type":"Point"}
}