{
  "type": "Feature",
  "properties": {
    "addr:full":"90 Atlantic Ave Hempstead NY 11550",
    "addr:housenumber":"90",
    "addr:postcode":"11550",
    "addr:street":"Atlantic Ave",
    "iso:country":"US",
    "sg:address":"90 Atlantic Ave",
    "sg:city":"Hempstead",
    "sg:classifiers":[
        {
            "category":"Recreation",
            "type":"Entertainment"
        }
    ],
    "sg:phone":"+1 516 489 3400",
    "sg:postcode":"11550",
    "sg:province":"NY",
    "sg:tags":[
        "parks"
    ],
    "wof:name":"Mirschel Park",
    "wof:placetype":"venue"
},
  "geometry": {"coordinates":[-73.631846,40.713007],"type":"Point"}
}