{
  "type": "Feature",
  "properties": {
    "addr:full":"5952 Rte 25A Wading River NY 11792",
    "addr:housenumber":"5952",
    "addr:postcode":"11792",
    "addr:street":"Rte 25A",
    "iso:country":"US",
    "sg:address":"5952 Rte 25A",
    "sg:city":"Wading River",
    "sg:classifiers":[
        {
            "category":"Social Services",
            "subcategory":"Child Care",
            "type":"Services"
        }
    ],
    "sg:phone":"+1 631 929 4800",
    "sg:postcode":"11792",
    "sg:province":"NY",
    "sg:website":"www.kiddieacademy.com",
    "wof:name":"Kiddie Academy Child Care Lrng",
    "wof:placetype":"venue"
},
  "geometry": {"coordinates":[-72.825181,40.945344],"type":"Point"}
}