{
  "type": "Feature",
  "properties": {
    "iso:country":"US",
    "sg:address":"959 Flatbush Ave",
    "sg:city":"Brooklyn",
    "sg:classifiers":[
        {
            "category":"Shopping",
            "subcategory":"Shoes",
            "type":"Retail Goods"
        }
    ],
    "sg:phone":"+1 718 282 7022",
    "sg:postcode":"11226",
    "sg:province":"NY",
    "sg:tags":[
        "store"
    ],
    "wof:name":"Pretty Shoes",
    "wof:placetype":"venue"
},
  "geometry": {"coordinates":[-73.957995,40.648173],"type":"Point"}
}