{
  "type": "Feature",
  "properties": {
    "iso:country":"US",
    "sg:address":"315 W 53 St",
    "sg:city":"New York",
    "sg:classifiers":[
        {
            "category":"Arts & Performance",
            "subcategory":"Theater",
            "type":"Entertainment"
        }
    ],
    "sg:phone":"+1 212 246 0929",
    "sg:postcode":"10019",
    "sg:province":"NY",
    "sg:tags":[
        "music",
        "agent"
    ],
    "wof:name":"Edgar Grana",
    "wof:placetype":"venue"
},
  "geometry": {"coordinates":[-73.98723099999999,40.765259],"type":"Point"}
}