{
  "type": "Feature",
  "properties": {
    "addr:full":"1487 Saratoga Rd Ballston Spa NY 12020",
    "addr:housenumber":"1487",
    "addr:postcode":"12020",
    "addr:street":"Saratoga Rd",
    "iso:country":"US",
    "sg:address":"1487 Saratoga Rd",
    "sg:city":"Ballston Spa",
    "sg:classifiers":[
        {
            "category":"Building & Trades",
            "subcategory":"Landscaping Services",
            "type":"Services"
        }
    ],
    "sg:phone":"+1 518 885 8655",
    "sg:postcode":"12020",
    "sg:province":"NY",
    "wof:name":"Timber & Stone LLC",
    "wof:placetype":"venue"
},
  "geometry": {"coordinates":[-73.856165,42.983843],"type":"Point"}
}