{
  "type": "Feature",
  "properties": {
    "addr:full":"333 Washington Ave Kingston NY 12401",
    "addr:housenumber":"333",
    "addr:postcode":"12401",
    "addr:street":"Washington Ave",
    "iso:country":"US",
    "sg:address":"333 Washington Ave",
    "sg:city":"Kingston",
    "sg:classifiers":[
        {
            "category":"Food & Beverages",
            "subcategory":"Groceries & Convenience Stores",
            "type":"Retail Goods"
        },
        {
            "category":"Autos & Motor Vehicles",
            "subcategory":"Fuel & Gas Station",
            "type":"Retail Goods"
        }
    ],
    "sg:phone":"+1 845 331 9013",
    "sg:postcode":"12401",
    "sg:province":"NY",
    "sg:tags":[
        "oil"
    ],
    "wof:name":"Getty Food Mart",
    "wof:placetype":"venue"
},
  "geometry": {"coordinates":[-74.02216799999999,41.931152],"type":"Point"}
}