{
  "type": "Feature",
  "properties": {
    "addr:full":"171 Willow St Yonkers NY 10701",
    "addr:housenumber":"171",
    "addr:postcode":"10701",
    "addr:street":"Willow St",
    "iso:country":"US",
    "sg:address":"171 Willow St",
    "sg:city":"Yonkers",
    "sg:classifiers":[
        {
            "category":"Food & Beverages",
            "subcategory":"Bakery",
            "type":"Retail Goods"
        }
    ],
    "sg:phone":"+1 914 968 5568",
    "sg:postcode":"10701",
    "sg:province":"NY",
    "sg:tags":[
        "baker"
    ],
    "wof:name":"Brito & Son Bakery",
    "wof:placetype":"venue"
},
  "geometry": {"coordinates":[-73.891735,40.931092],"type":"Point"}
}