{
  "type": "Feature",
  "properties": {
    "iso:country":"US",
    "sg:address":"9 Sergio Ct",
    "sg:city":"Spring Valley",
    "sg:classifiers":[
        {
            "category":"Building & Trades",
            "subcategory":"Construction",
            "type":"Services"
        }
    ],
    "sg:phone":"+1 845 352 7500",
    "sg:postcode":"10977",
    "sg:province":"NY",
    "sg:tags":[
        "contractor"
    ],
    "wof:name":"Sergio Masonry Inc",
    "wof:placetype":"venue"
},
  "geometry": {"coordinates":[-74.041905,41.090165],"type":"Point"}
}