{
  "type": "Feature",
  "properties": {
    "iso:country":"US",
    "sg:address":"1264 Amsterdam Ave",
    "sg:city":"New York",
    "sg:classifiers":[
        {
            "category":"Health Services",
            "subcategory":"Doctor",
            "type":"Services"
        }
    ],
    "sg:phone":"+1 212 864 7882",
    "sg:postcode":"10027",
    "sg:province":"NY",
    "wof:name":"Vitale Leonard MD",
    "wof:placetype":"venue"
},
  "geometry": {"coordinates":[-73.958099,40.810902],"type":"Point"}
}