{
  "type": "Feature",
  "properties": {
    "addr:full":"106 3rd Ave Mineola NY 11501",
    "addr:housenumber":"106",
    "addr:postcode":"11501",
    "addr:street":"3Rd Ave",
    "iso:country":"US",
    "sg:address":"106 3rd Ave",
    "sg:city":"Mineola",
    "sg:classifiers":[
        {
            "category":"Professional",
            "subcategory":"Management & Consulting",
            "type":"Services"
        }
    ],
    "sg:phone":"+1 516 873 6096",
    "sg:postcode":"11501",
    "sg:province":"NY",
    "sg:tags":[
        "consultant"
    ],
    "wof:name":"Nassau Consulting Svc",
    "wof:placetype":"venue"
},
  "geometry": {"coordinates":[-73.641694,40.741733],"type":"Point"}
}