{
  "type": "Feature",
  "properties": {
    "iso:country":"US",
    "sg:address":"37 Lagrasse St",
    "sg:city":"Waddington",
    "sg:classifiers":[
        {
            "category":"Wholesale",
            "subcategory":"Machinery & Supplies",
            "type":"Manufacturing & Wholesale Goods"
        }
    ],
    "sg:phone":"+1 315 388 4920",
    "sg:postcode":"13694",
    "sg:province":"NY",
    "sg:tags":[
        "equipment"
    ],
    "wof:name":"North Country Survey Stakes",
    "wof:placetype":"venue"
},
  "geometry": {"coordinates":[-75.201052,44.86055],"type":"Point"}
}