{
  "type": "Feature",
  "properties": {
    "addr:full":"5212 Avenue N Brooklyn NY 11234",
    "addr:housenumber":"5212",
    "addr:postcode":"11234",
    "addr:street":"Avenue N",
    "iso:country":"US",
    "sg:address":"5212 Avenue N",
    "sg:city":"Brooklyn",
    "sg:classifiers":[
        {
            "category":"Food & Beverages",
            "subcategory":"Cheese",
            "type":"Retail Goods"
        }
    ],
    "sg:phone":"+1 347 492 3800",
    "sg:postcode":"11234",
    "sg:province":"NY",
    "sg:tags":[
        "shop"
    ],
    "wof:name":"Cheese & Tomatos",
    "wof:placetype":"venue"
},
  "geometry": {"coordinates":[-73.924818,40.61894],"type":"Point"}
}