{
  "type": "Feature",
  "properties": {
    "addr:full":"70 Allen St Saugerties NY 12477",
    "addr:housenumber":"70",
    "addr:postcode":"12477",
    "addr:street":"Allen St",
    "iso:country":"US",
    "sg:address":"70 Allen St",
    "sg:city":"Saugerties",
    "sg:classifiers":[
        {
            "category":"Fast Food",
            "type":"Food & Drink"
        },
        {
            "category":"Restaurant",
            "type":"Food & Drink"
        }
    ],
    "sg:phone":"+1 845 246 9589",
    "sg:postcode":"12477",
    "sg:province":"NY",
    "sg:tags":[
        "take"
    ],
    "wof:name":"Wendy Walker",
    "wof:placetype":"venue"
},
  "geometry": {"coordinates":[-73.95134899999999,42.072928],"type":"Point"}
}