{
  "type": "Feature",
  "properties": {
    "addr:full":"8145 Lefferts Blvd Kew Gardens NY 11415",
    "addr:housenumber":"8145",
    "addr:postcode":"11415",
    "addr:street":"Lefferts Blvd",
    "iso:country":"US",
    "sg:address":"8145 Lefferts Blvd",
    "sg:city":"Kew Gardens",
    "sg:classifiers":[
        {
            "category":"Deli",
            "type":"Food & Drink"
        }
    ],
    "sg:phone":"+1 718 849 1366",
    "sg:postcode":"11415",
    "sg:province":"NY",
    "wof:name":"Homestead Gourmet Shop",
    "wof:placetype":"venue"
},
  "geometry": {"coordinates":[-73.830597,40.708302],"type":"Point"}
}