{
  "type": "Feature",
  "properties": {
    "iso:country":"US",
    "sg:address":"711 Lee St",
    "sg:city":"Rome",
    "sg:classifiers":[
        {
            "category":"Building & Trades",
            "subcategory":"Landscaping Services",
            "type":"Services"
        }
    ],
    "sg:phone":"+1 315 336 8689",
    "sg:postcode":"13440",
    "sg:province":"NY",
    "sg:tags":[
        "contractor",
        "nursery",
        "landscape",
        "retail"
    ],
    "wof:name":"Maplecroft Nurseries Inc",
    "wof:placetype":"venue"
},
  "geometry": {"coordinates":[-75.46586600000001,43.227742],"type":"Point"}
}