{
  "type": "Feature",
  "properties": {
    "addr:full":"128 Mott St Ste 603 New York NY 10013",
    "addr:housenumber":"128;603",
    "addr:postcode":"10013",
    "addr:street":"Mott St Ste",
    "iso:country":"US",
    "sg:address":"128 Mott St Ste 603",
    "sg:city":"New York",
    "sg:classifiers":[
        {
            "category":"Health Services",
            "subcategory":"Doctor",
            "type":"Services"
        }
    ],
    "sg:phone":"+1 212 966 7583",
    "sg:postcode":"10013",
    "sg:province":"NY",
    "wof:name":"Naing Andrew",
    "wof:placetype":"venue"
},
  "geometry": {"coordinates":[-73.996697,40.718241],"type":"Point"}
}