{
  "type": "Feature",
  "properties": {
    "iso:country":"US",
    "sg:address":"984 Intervale Ave",
    "sg:city":"Bronx",
    "sg:classifiers":[
        {
            "category":"Organizations",
            "subcategory":"Religious Organization",
            "type":"Services"
        }
    ],
    "sg:phone":"+1 718 328 4511",
    "sg:postcode":"10459",
    "sg:province":"NY",
    "wof:name":"Aljaned Islamic Center",
    "wof:placetype":"venue"
},
  "geometry": {"coordinates":[-73.896677,40.822648],"type":"Point"}
}