{
  "type": "Feature",
  "properties": {
    "iso:country":"US",
    "sg:address":"815 Tenth Ave.",
    "sg:city":"New York",
    "sg:classifiers":[
        {
            "category":"Restaurant",
            "type":"Food & Drink"
        }
    ],
    "sg:menulink":"http://www.allmenus.com/ny/new-york/107164-soup-man/menu/",
    "sg:phone":"+1 646 215 7781",
    "sg:postcode":"10019",
    "sg:province":"NY",
    "sg:tags":[
        "soup",
        "american",
        "salad"
    ],
    "wof:name":"Soup Man",
    "wof:placetype":"venue"
},
  "geometry": {"coordinates":[-73.98987099999999,40.76733],"type":"Point"}
}