{
  "type": "Feature",
  "properties": {
    "addr:full":"371 77th St Brooklyn NY 11209",
    "addr:housenumber":"371",
    "addr:postcode":"11209",
    "addr:street":"77Th St",
    "iso:country":"US",
    "sg:address":"371 77th St",
    "sg:city":"Brooklyn",
    "sg:classifiers":[
        {
            "category":"Organizations",
            "subcategory":"Religious Organization",
            "type":"Services"
        }
    ],
    "sg:phone":"+1 718 745 5282",
    "sg:postcode":"11209",
    "sg:province":"NY",
    "sg:tags":[
        "church"
    ],
    "sg:website":"www.ukcny.com",
    "wof:name":"United Korean Church-New York",
    "wof:placetype":"venue"
},
  "geometry": {"coordinates":[-74.027112,40.62991],"type":"Point"}
}