{
  "type": "Feature",
  "properties": {
    "iso:country":"US",
    "sg:address":"5 Main St",
    "sg:city":"Sparrow Bush",
    "sg:classifiers":[
        {
            "category":"Food & Beverages",
            "subcategory":"Groceries & Convenience Stores",
            "type":"Retail Goods"
        }
    ],
    "sg:phone":"+1   ",
    "sg:postcode":"12780",
    "sg:province":"NY",
    "sg:tags":[
        "station",
        "gasoline"
    ],
    "wof:name":"Weyant Convenient Store",
    "wof:placetype":"venue"
},
  "geometry": {"coordinates":[-74.721548,41.39861],"type":"Point"}
}