{
  "type": "Feature",
  "properties": {
    "iso:country":"US",
    "sg:address":"110 E Chestnut St",
    "sg:city":"Rome",
    "sg:classifiers":[
        {
            "category":"Shopping",
            "subcategory":"Optical Goods",
            "type":"Retail Goods"
        }
    ],
    "sg:phone":"+1   ",
    "sg:postcode":"13440",
    "sg:province":"NY",
    "wof:name":"Rome Eye Clinic",
    "wof:placetype":"venue"
},
  "geometry": {"coordinates":[-75.439742,43.230395],"type":"Point"}
}