{
  "type": "Feature",
  "properties": {
    "addr:full":"589 E New York Ave Brooklyn NY 11225",
    "addr:housenumber":"589",
    "addr:postcode":"11225",
    "addr:street":"E New York Ave",
    "iso:country":"US",
    "sg:address":"589 E New York Ave",
    "sg:city":"Brooklyn",
    "sg:classifiers":[
        {
            "category":"Food & Beverages",
            "subcategory":"Groceries & Convenience Stores",
            "type":"Retail Goods"
        }
    ],
    "sg:phone":"+1 718 778 2500",
    "sg:postcode":"11225",
    "sg:province":"NY",
    "wof:name":"The Shuk",
    "wof:placetype":"venue"
},
  "geometry": {"coordinates":[-73.94323,40.662032],"type":"Point"}
}