{
  "type": "Feature",
  "properties": {
    "addr:full":"15 Holiday Pond Rd Jericho NY 11753",
    "addr:housenumber":"15",
    "addr:postcode":"11753",
    "addr:street":"Holiday Pond Rd",
    "iso:country":"US",
    "sg:address":"15 Holiday Pond Rd",
    "sg:city":"Jericho",
    "sg:classifiers":[
        {
            "category":"Real Estate",
            "subcategory":"Real Estate Services",
            "type":"Services"
        },
        {
            "category":"Real Estate",
            "subcategory":"Real Estate Agent",
            "type":"Services"
        }
    ],
    "sg:phone":"+1 516 937 0550",
    "sg:postcode":"11753",
    "sg:province":"NY",
    "sg:tags":[
        "buyer",
        "broker"
    ],
    "wof:name":"Hamlet Estates At Jericho",
    "wof:placetype":"venue"
},
  "geometry": {"coordinates":[-73.54476,40.789953],"type":"Point"}
}