{
  "type": "Feature",
  "properties": {
    "iso:country":"US",
    "sg:address":"2256 Bronx Park E",
    "sg:city":"Bronx",
    "sg:classifiers":[
        {
            "category":"Place Of Worship",
            "type":"Public Place"
        }
    ],
    "sg:phone":"+1 718 882 2080",
    "sg:postcode":"10467",
    "sg:province":"NY",
    "sg:tags":[
        "church"
    ],
    "wof:name":"Avram J Twersky",
    "wof:placetype":"venue"
},
  "geometry": {"coordinates":[-73.870901,40.858789],"type":"Point"}
}