{
  "type": "Feature",
  "properties": {
    "addr:full":"44 Raymond Ave Poughkeepsie NY 12603",
    "addr:housenumber":"44",
    "addr:postcode":"12603",
    "addr:street":"Raymond Ave",
    "iso:country":"US",
    "sg:address":"44 Raymond Ave",
    "sg:city":"Poughkeepsie",
    "sg:classifiers":[
        {
            "category":"Restaurant",
            "type":"Food & Drink"
        }
    ],
    "sg:phone":"+1 845 483 7584",
    "sg:postcode":"12603",
    "sg:province":"NY",
    "sg:tags":[
        "shop",
        "coffee"
    ],
    "wof:name":"Cubby Hole Coffee House",
    "wof:placetype":"venue"
},
  "geometry": {"coordinates":[-73.90095599999999,41.693634],"type":"Point"}
}