{
  "type": "Feature",
  "properties": {
    "addr:full":"53 Broad St Plattsburgh NY 12901",
    "addr:housenumber":"53",
    "addr:postcode":"12901",
    "addr:street":"Broad St",
    "iso:country":"US",
    "sg:address":"53 Broad St",
    "sg:city":"Plattsburgh",
    "sg:classifiers":[
        {
            "category":"Utilities",
            "subcategory":"Telephone",
            "type":"Services"
        }
    ],
    "sg:phone":"+1 518 561 9555",
    "sg:postcode":"12901",
    "sg:province":"NY",
    "sg:tags":[
        "company"
    ],
    "wof:name":"Burlington Telephone Co",
    "wof:placetype":"venue"
},
  "geometry": {"coordinates":[-73.46120000000001,44.69458],"type":"Point"}
}