{
  "type": "Feature",
  "properties": {
    "addr:full":"2590 Ridge Rd W Rochester NY 14420",
    "addr:housenumber":"2590",
    "addr:postcode":"14420",
    "addr:street":"Ridge Rd W",
    "iso:country":"US",
    "sg:address":"2590 Ridge Rd W",
    "sg:city":"Rochester",
    "sg:classifiers":[
        {
            "category":"Sports & Exercise",
            "subcategory":"Gym",
            "type":"Entertainment"
        }
    ],
    "sg:phone":"+1 585 368 0380",
    "sg:postcode":"14420",
    "sg:province":"NY",
    "sg:tags":[
        "club",
        "health",
        "studio",
        "gymnasium"
    ],
    "wof:name":"Curves",
    "wof:placetype":"venue"
},
  "geometry": {"coordinates":[-77.698554,43.210311],"type":"Point"}
}