{
  "type": "Feature",
  "properties": {
    "iso:country":"US",
    "sg:address":"138 Ludlow St",
    "sg:city":"New York",
    "sg:classifiers":[
        {
            "category":"Organizations",
            "subcategory":"Labor Organization",
            "type":"Services"
        }
    ],
    "sg:phone":"+1 212 477 0280",
    "sg:postcode":"10002",
    "sg:province":"NY",
    "sg:tags":[
        "bar"
    ],
    "wof:name":"Local 138",
    "wof:placetype":"venue"
},
  "geometry": {"coordinates":[-73.988195,40.720357],"type":"Point"}
}