{
  "type": "Feature",
  "properties": {
    "addr:full":"1855 Broadway New York NY 10023",
    "addr:housenumber":"1855",
    "addr:postcode":"10023",
    "addr:street":"Broadway",
    "iso:country":"US",
    "sg:address":"1855 Broadway",
    "sg:city":"New York",
    "sg:classifiers":[
        {
            "category":"Education",
            "subcategory":"College",
            "type":"Public Place"
        }
    ],
    "sg:phone":"+1   ",
    "sg:postcode":"10023",
    "sg:province":"NY",
    "wof:name":"Efap New York Inc",
    "wof:placetype":"venue"
},
  "geometry": {"coordinates":[-73.98217699999999,40.769033],"type":"Point"}
}