{
  "type": "Feature",
  "properties": {
    "iso:country":"US",
    "sg:address":"244 5th Ave 2nd Fl",
    "sg:city":"Manhattan",
    "sg:classifiers":[
        {
            "category":"Professional",
            "subcategory":"Advertising",
            "type":"Services"
        },
        {
            "category":"Communications",
            "subcategory":"Newspaper",
            "type":"Services"
        }
    ],
    "sg:phone":"+1 718 593 4892",
    "sg:postcode":"10001",
    "sg:province":"NY",
    "sg:tags":[
        "marketing"
    ],
    "sg:website":"www.pinkstone.es/Pinkstone%20Eng...",
    "wof:name":"Pink Stone Advertisment Group",
    "wof:placetype":"venue"
},
  "geometry": {"coordinates":[-73.987368,40.744648],"type":"Point"}
}