{
  "type": "Feature",
  "properties": {
    "addr:full":"1390 Castleton Ave Staten Island NY 10302",
    "addr:housenumber":"1390",
    "addr:postcode":"10302",
    "addr:street":"Castleton Ave",
    "iso:country":"US",
    "sg:address":"1390 Castleton Ave",
    "sg:city":"Staten Island",
    "sg:classifiers":[
        {
            "category":"Organizations",
            "subcategory":"Labor Organization",
            "type":"Services"
        }
    ],
    "sg:phone":"+1 718 442 7611",
    "sg:postcode":"10302",
    "sg:province":"NY",
    "sg:website":"www.atu.org",
    "wof:name":"Amalgamated Transit Union",
    "wof:placetype":"venue"
},
  "geometry": {"coordinates":[-74.129064,40.633592],"type":"Point"}
}