{
  "type": "Feature",
  "properties": {
    "addr:full":"7018 Fort Hamilton Pkwy Brooklyn NY 11228",
    "addr:housenumber":"7018",
    "addr:postcode":"11228",
    "addr:street":"Fort Hamilton Pkwy",
    "iso:country":"US",
    "sg:address":"7018 Fort Hamilton Pkwy",
    "sg:city":"Brooklyn",
    "sg:classifiers":[
        {
            "category":"Banks & Credit Unions",
            "subcategory":"Financial Services",
            "type":"Services"
        }
    ],
    "sg:phone":"+1 718 921 0200",
    "sg:postcode":"11228",
    "sg:province":"NY",
    "sg:tags":[
        "broker",
        "mortgage"
    ],
    "sg:website":"www.fortfunding.com",
    "wof:name":"Fort Funding Corp",
    "wof:placetype":"venue"
},
  "geometry": {"coordinates":[-74.01346700000001,40.628038],"type":"Point"}
}