{
  "type": "Feature",
  "properties": {
    "addr:full":"2851 W Henrietta Rd Rochester NY 14623",
    "addr:housenumber":"2851",
    "addr:postcode":"14623",
    "addr:street":"W Henrietta Rd",
    "iso:country":"US",
    "sg:address":"2851 W Henrietta Rd",
    "sg:city":"Rochester",
    "sg:classifiers":[
        {
            "category":"Restaurant",
            "type":"Food & Drink"
        }
    ],
    "sg:menulink":"http://www.allmenus.com/ny/brighton/3804-davincis-restaurant/menu/",
    "sg:phone":"+1 585 291 1960",
    "sg:postcode":"14623",
    "sg:province":"NY",
    "sg:tags":[
        "italian"
    ],
    "wof:name":"Davinci's Restaurant",
    "wof:placetype":"venue"
},
  "geometry": {"coordinates":[-77.63376100000001,43.094658],"type":"Point"}
}