{
  "type": "Feature",
  "properties": {
    "addr:full":"10 Harlem River Dr New York NY 10039",
    "addr:housenumber":"10",
    "addr:postcode":"10039",
    "addr:street":"Harlem River Dr",
    "iso:country":"US",
    "sg:address":"10 Harlem River Dr",
    "sg:city":"New York",
    "sg:classifiers":[
        {
            "category":"Professional",
            "type":"Services"
        }
    ],
    "sg:phone":"+1   ",
    "sg:postcode":"10039",
    "sg:province":"NY",
    "wof:name":"159 10 Harlem River Drive Clrs",
    "wof:placetype":"venue"
},
  "geometry": {"coordinates":[-73.935219,40.83543],"type":"Point"}
}