{
  "type": "Feature",
  "properties": {
    "addr:full":"25 W 33rd Street New York NY 10001",
    "addr:housenumber":"25",
    "addr:postcode":"10001",
    "addr:street":"W 33Rd Street",
    "iso:country":"US",
    "sg:address":"25 W 33rd Street",
    "sg:city":"New York",
    "sg:classifiers":[
        {
            "category":"Personal",
            "subcategory":"Shoe Repair & Shine",
            "type":"Services"
        }
    ],
    "sg:phone":"+1 212 736 7170",
    "sg:postcode":"10001",
    "sg:province":"NY",
    "wof:name":"Louis Shoes Rebuilder",
    "wof:placetype":"venue"
},
  "geometry": {"coordinates":[-73.996213,40.750051],"type":"Point"}
}