{
  "type": "Feature",
  "properties": {
    "iso:country":"US",
    "sg:address":"199 E 93 St",
    "sg:city":"New York",
    "sg:classifiers":[
        {
            "category":"Retail",
            "subcategory":"Auto Repair",
            "type":"Services"
        }
    ],
    "sg:phone":"+1 212 937 1249",
    "sg:postcode":"10128",
    "sg:province":"NY",
    "sg:tags":[
        "wrecker"
    ],
    "wof:name":"Asam Towing & Recovery",
    "wof:placetype":"venue"
},
  "geometry": {"coordinates":[-73.95234000000001,40.783937],"type":"Point"}
}