{
  "type": "Feature",
  "properties": {
    "iso:country":"US",
    "sg:address":"199 Jericho Tpke Ste 203",
    "sg:city":"Floral Park",
    "sg:classifiers":[
        {
            "category":"Professional",
            "subcategory":"Lawyer & Legal Services",
            "type":"Services"
        }
    ],
    "sg:phone":"+1 516 352 2400",
    "sg:postcode":"11001",
    "sg:province":"NY",
    "wof:name":"Langer Steven H Atty",
    "wof:placetype":"venue"
},
  "geometry": {"coordinates":[-73.703078,40.729296],"type":"Point"}
}