{
  "type": "Feature",
  "properties": {
    "iso:country":"US",
    "sg:address":"10 Bay Blvd",
    "sg:city":"Inwood",
    "sg:classifiers":[
        {
            "category":"Home & Garden",
            "subcategory":"Garden Supply",
            "type":"Retail Goods"
        }
    ],
    "sg:phone":"+1 516 371 3700",
    "sg:postcode":"11096",
    "sg:province":"NY",
    "sg:tags":[
        "nursery",
        "gardening"
    ],
    "wof:name":"Bay Blvd Nursery Inc",
    "wof:placetype":"venue"
},
  "geometry": {"coordinates":[-73.7407,40.628502],"type":"Point"}
}