{
  "type": "Feature",
  "properties": {
    "addr:full":"421 Clifton Corporate Pkwy Clifton Park NY 12065",
    "addr:housenumber":"421",
    "addr:postcode":"12065",
    "addr:street":"Clifton Corporate Pkwy",
    "iso:country":"US",
    "sg:address":"421 Clifton Corporate Pkwy",
    "sg:city":"Clifton Park",
    "sg:classifiers":[
        {
            "category":"Professional",
            "subcategory":"Research",
            "type":"Services"
        }
    ],
    "sg:phone":"+1 518 383 1661",
    "sg:postcode":"12065",
    "sg:province":"NY",
    "sg:tags":[
        "marketing"
    ],
    "wof:name":"Data Collection Agency",
    "wof:placetype":"venue"
},
  "geometry": {"coordinates":[-73.78906600000001,42.864462],"type":"Point"}
}