{
  "type": "Feature",
  "properties": {
    "iso:country":"US",
    "sg:address":"31 Wagner Rd",
    "sg:city":"Medford",
    "sg:classifiers":[
        {
            "category":"Utilities",
            "subcategory":"Fuel Oil & Lpg",
            "type":"Services"
        }
    ],
    "sg:phone":"+1   ",
    "sg:postcode":"11763",
    "sg:province":"NY",
    "sg:tags":[
        "dealer"
    ],
    "wof:name":"Charles Ashby",
    "wof:placetype":"venue"
},
  "geometry": {"coordinates":[-72.949911,40.853472],"type":"Point"}
}