{
  "type": "Feature",
  "properties": {
    "addr:full":"1315 Champlin Ave Utica NY 13502",
    "addr:housenumber":"1315",
    "addr:postcode":"13502",
    "addr:street":"Champlin Ave",
    "iso:country":"US",
    "sg:address":"1315 Champlin Ave",
    "sg:city":"Utica",
    "sg:classifiers":[
        {
            "category":"Organizations",
            "subcategory":"Community Association",
            "type":"Services"
        }
    ],
    "sg:phone":"+1 315 733 2377",
    "sg:postcode":"13502",
    "sg:province":"NY",
    "sg:tags":[
        "fraternal"
    ],
    "wof:name":"Elks Lodge",
    "wof:placetype":"venue"
},
  "geometry": {"coordinates":[-75.27015900000001,43.105952],"type":"Point"}
}