{
  "type": "Feature",
  "properties": {
    "iso:country":"US",
    "sg:address":"55 Knowles St",
    "sg:city":"Yonkers",
    "sg:classifiers":[
        {
            "category":"Real Estate",
            "subcategory":"Real Estate Agent",
            "type":"Services"
        }
    ],
    "sg:phone":"+1 914 476 3035",
    "sg:postcode":"10705",
    "sg:province":"NY",
    "wof:name":"Olivieri Properties Inc",
    "wof:placetype":"venue"
},
  "geometry": {"coordinates":[-73.904129,40.924586],"type":"Point"}
}