{
  "type": "Feature",
  "properties": {
    "addr:full":"31 E 32 St New York NY 10016",
    "addr:housenumber":"31;32",
    "addr:postcode":"10016",
    "addr:street":"E;St",
    "iso:country":"US",
    "sg:address":"31 E 32 St",
    "sg:city":"New York",
    "sg:classifiers":[
        {
            "category":"Communications",
            "type":"Services"
        }
    ],
    "sg:phone":"+1 212 684 1106",
    "sg:postcode":"10016",
    "sg:province":"NY",
    "wof:name":"Madison & Lloyd Communications",
    "wof:placetype":"venue"
},
  "geometry": {"coordinates":[-73.98231,40.745899],"type":"Point"}
}