{
  "type": "Feature",
  "properties": {
    "addr:full":"1758 E 52nd St Brooklyn NY 11234",
    "addr:housenumber":"1758",
    "addr:postcode":"11234",
    "addr:street":"E 52Nd St",
    "iso:country":"US",
    "sg:address":"1758 E 52nd St",
    "sg:city":"Brooklyn",
    "sg:classifiers":[
        {
            "category":"Building & Trades",
            "subcategory":"Plumbing",
            "type":"Services"
        }
    ],
    "sg:phone":"+1 718 677 0925",
    "sg:postcode":"11234",
    "sg:province":"NY",
    "sg:tags":[
        "plumbing",
        "contractor"
    ],
    "wof:name":"Bulldog Mechanical Corp",
    "wof:placetype":"venue"
},
  "geometry": {"coordinates":[-73.924559,40.614802],"type":"Point"}
}