{
  "type": "Feature",
  "properties": {
    "addr:full":"363 Van Duzer St Staten Island NY 10304",
    "addr:housenumber":"363",
    "addr:postcode":"10304",
    "addr:street":"Van Duzer St",
    "iso:country":"US",
    "sg:address":"363 Van Duzer St",
    "sg:city":"Staten Island",
    "sg:classifiers":[
        {
            "category":"Arts & Performance",
            "subcategory":"Theater",
            "type":"Entertainment"
        }
    ],
    "sg:phone":"+1 718 980 1920",
    "sg:postcode":"10304",
    "sg:province":"NY",
    "sg:tags":[
        "live",
        "music"
    ],
    "wof:name":"Johnny Be Good Production",
    "wof:placetype":"venue"
},
  "geometry": {"coordinates":[-74.07938799999999,40.62929],"type":"Point"}
}