{
  "type": "Feature",
  "properties": {
    "addr:full":"303 Park Ave New York NY 10022",
    "addr:housenumber":"303",
    "addr:postcode":"10022",
    "addr:street":"Park Ave",
    "iso:country":"US",
    "sg:address":"303 Park Ave",
    "sg:city":"New York",
    "sg:classifiers":[
        {
            "category":"Restaurant",
            "type":"Food & Drink"
        }
    ],
    "sg:menulink":"http://www.allmenus.com/ny/new-york/52146-new-york-burger-co/menu/",
    "sg:phone":"+1 212 254 2727",
    "sg:postcode":"10022",
    "sg:province":"NY",
    "sg:tags":[
        "american"
    ],
    "wof:name":"New York Burger Co.",
    "wof:placetype":"venue"
},
  "geometry": {"coordinates":[-73.97408,40.75682],"type":"Point"}
}