{
  "type": "Feature",
  "properties": {
    "iso:country":"US",
    "sg:address":"18 John Street",
    "sg:city":"New York",
    "sg:classifiers":[
        {
            "category":"Shopping",
            "subcategory":"Shoes",
            "type":"Retail Goods"
        }
    ],
    "sg:phone":"+1 212 577 9298",
    "sg:postcode":"10038",
    "sg:province":"NY",
    "sg:tags":[
        "store"
    ],
    "sg:website":"www.aerosoles.com",
    "wof:name":"Aerosoles Shoe Store",
    "wof:placetype":"venue"
},
  "geometry": {"coordinates":[-74.00841800000001,40.709372],"type":"Point"}
}