{
  "type": "Feature",
  "properties": {
    "addr:full":"2 Grove St Delmar NY 12054",
    "addr:housenumber":"2",
    "addr:postcode":"12054",
    "addr:street":"Grove St",
    "iso:country":"US",
    "sg:address":"2 Grove St",
    "sg:city":"Delmar",
    "sg:phone":"+1 518 439 0172",
    "sg:postcode":"12054",
    "sg:province":"NY",
    "wof:name":"Four Corners Luncheonette",
    "wof:placetype":"venue"
},
  "geometry": {"coordinates":[-73.832047,42.62249],"type":"Point"}
}