{
  "type": "Feature",
  "properties": {
    "addr:full":"45 Frost St Westbury NY 11590",
    "addr:housenumber":"45",
    "addr:postcode":"11590",
    "addr:street":"Frost St",
    "iso:country":"US",
    "sg:address":"45 Frost St",
    "sg:city":"Westbury",
    "sg:classifiers":[
        {
            "category":"Building & Trades",
            "subcategory":"Construction",
            "type":"Services"
        }
    ],
    "sg:phone":"+1 516 997 3097",
    "sg:postcode":"11590",
    "sg:province":"NY",
    "sg:tags":[
        "tile",
        "dealer"
    ],
    "wof:name":"Swan Tile & Cabinets",
    "wof:placetype":"venue"
},
  "geometry": {"coordinates":[-73.55241700000001,40.756517],"type":"Point"}
}