{
  "type": "Feature",
  "properties": {
    "addr:full":"4401 Tibbett Ave Bronx NY 10471",
    "addr:housenumber":"4401",
    "addr:postcode":"10471",
    "addr:street":"Tibbett Ave",
    "iso:country":"US",
    "sg:address":"4401 Tibbett Ave",
    "sg:city":"Bronx",
    "sg:classifiers":[
        {
            "category":"Organizations",
            "subcategory":"Religious Organization",
            "type":"Services"
        }
    ],
    "sg:phone":"+1 718 549 0530",
    "sg:postcode":"10471",
    "sg:province":"NY",
    "sg:tags":[
        "clergy"
    ],
    "wof:name":"Anthony Rubsys",
    "wof:placetype":"venue"
},
  "geometry": {"coordinates":[-73.899897,40.893054],"type":"Point"}
}