{
  "type": "Feature",
  "properties": {
    "addr:full":"18 Eagle Chase Woodbury NY 11797",
    "addr:housenumber":"18",
    "addr:postcode":"11797",
    "addr:street":"Eagle Chase",
    "iso:country":"US",
    "sg:address":"18 Eagle Chase",
    "sg:city":"Woodbury",
    "sg:classifiers":[
        {
            "category":"Building & Trades",
            "subcategory":"Construction",
            "type":"Services"
        }
    ],
    "sg:phone":"+1 516 349 7431",
    "sg:postcode":"11797",
    "sg:province":"NY",
    "sg:tags":[
        "house"
    ],
    "wof:name":"MCS Estate Builders Inc",
    "wof:placetype":"venue"
},
  "geometry": {"coordinates":[-73.475173,40.799766],"type":"Point"}
}