{
  "type": "Feature",
  "properties": {
    "addr:full":"3 Brookside Ave Newburgh NY 12550",
    "addr:housenumber":"3",
    "addr:postcode":"12550",
    "addr:street":"Brookside Ave",
    "iso:country":"US",
    "sg:address":"3 Brookside Ave",
    "sg:city":"Newburgh",
    "sg:classifiers":[
        {
            "category":"Banks & Credit Unions",
            "subcategory":"Investment Brokerage",
            "type":"Services"
        }
    ],
    "sg:phone":"+1 845 565 7378",
    "sg:postcode":"12550",
    "sg:province":"NY",
    "sg:tags":[
        "dealer"
    ],
    "wof:name":"Independent Financial Cons",
    "wof:placetype":"venue"
},
  "geometry": {"coordinates":[-74.05098599999999,41.514198],"type":"Point"}
}