{
  "type": "Feature",
  "properties": {
    "addr:full":"8697 18th Ave Brooklyn NY 11214",
    "addr:housenumber":"8697",
    "addr:postcode":"11214",
    "addr:street":"18Th Ave",
    "iso:country":"US",
    "sg:address":"8697 18th Ave",
    "sg:city":"Brooklyn",
    "sg:classifiers":[
        {
            "category":"Retail",
            "subcategory":"Auto Repair",
            "type":"Services"
        }
    ],
    "sg:phone":"+1 718 331 2489",
    "sg:postcode":"11214",
    "sg:province":"NY",
    "sg:tags":[
        "repairing",
        "automobile"
    ],
    "wof:name":"Joe's Auto Clinic",
    "wof:placetype":"venue"
},
  "geometry": {"coordinates":[-74.004758,40.605177],"type":"Point"}
}