{
  "type": "Feature",
  "properties": {
    "addr:full":"15016 Tahoe St Ozone Park NY 11417",
    "addr:housenumber":"15016",
    "addr:postcode":"11417",
    "addr:street":"Tahoe St",
    "iso:country":"US",
    "sg:address":"15016 Tahoe St",
    "sg:city":"Ozone Park",
    "sg:classifiers":[
        {
            "category":"Home & Garden",
            "subcategory":"Building Materials",
            "type":"Retail Goods"
        }
    ],
    "sg:phone":"+1 718 845 7250",
    "sg:postcode":"11417",
    "sg:province":"NY",
    "sg:tags":[
        "equipment",
        "fixture",
        "lighting"
    ],
    "wof:name":"Ozone Lighting Distributors Inc",
    "wof:placetype":"venue"
},
  "geometry": {"coordinates":[-73.837898,40.6688],"type":"Point"}
}