{
  "type": "Feature",
  "properties": {
    "addr:full":"1760 Flatbush Ave Brooklyn NY 11210",
    "addr:housenumber":"1760",
    "addr:postcode":"11210",
    "addr:street":"Flatbush Ave",
    "iso:country":"US",
    "sg:address":"1760 Flatbush Ave",
    "sg:city":"Brooklyn",
    "sg:classifiers":[
        {
            "category":"Autos & Motor Vehicles",
            "subcategory":"Fuel & Gas Station",
            "type":"Retail Goods"
        }
    ],
    "sg:phone":"+1 718 692 4638",
    "sg:postcode":"11210",
    "sg:province":"NY",
    "sg:tags":[
        "oil"
    ],
    "wof:name":"City Gas",
    "wof:placetype":"venue"
},
  "geometry": {"coordinates":[-73.94139800000001,40.626849],"type":"Point"}
}