{
  "type": "Feature",
  "properties": {
    "addr:full":"357 Ave X Brooklyn NY 11223",
    "addr:housenumber":"357",
    "addr:postcode":"11223",
    "addr:street":"Ave X",
    "iso:country":"US",
    "sg:address":"357 Ave X",
    "sg:city":"Brooklyn",
    "sg:classifiers":[
        {
            "category":"Organizations",
            "subcategory":"Religious Organization",
            "type":"Services"
        }
    ],
    "sg:phone":"+1 718 769 6644",
    "sg:postcode":"11223",
    "sg:province":"NY",
    "sg:tags":[
        "church"
    ],
    "wof:name":"St Peters Co",
    "wof:placetype":"venue"
},
  "geometry": {"coordinates":[-73.969611,40.590675],"type":"Point"}
}