{
  "type": "Feature",
  "properties": {
    "addr:full":"61 Railroad Ave West Haverstraw NY 10993",
    "addr:housenumber":"61",
    "addr:postcode":"10993",
    "addr:street":"Railroad Ave West",
    "iso:country":"US",
    "sg:address":"61 Railroad Ave",
    "sg:city":"West Haverstraw",
    "sg:classifiers":[
        {
            "category":"Professional",
            "subcategory":"Computer Services",
            "type":"Services"
        }
    ],
    "sg:phone":"+1 845 786 7700",
    "sg:postcode":"10993",
    "sg:province":"NY",
    "sg:tags":[
        "website",
        "design"
    ],
    "wof:name":"Ariacom Technologies",
    "wof:placetype":"venue"
},
  "geometry": {"coordinates":[-73.983133,41.209414],"type":"Point"}
}