{
  "type": "Feature",
  "properties": {
    "iso:country":"US",
    "sg:address":"305 W 78th St",
    "sg:city":"New York",
    "sg:classifiers":[
        {
            "category":"Building & Trades",
            "subcategory":"Locksmith",
            "type":"Services"
        }
    ],
    "sg:phone":"+1 646 224 0624",
    "sg:postcode":"10024",
    "sg:province":"NY",
    "sg:tags":[
        "key"
    ],
    "wof:name":"24 Hour A Number 1 Emergency Locksmith",
    "wof:placetype":"venue"
},
  "geometry": {"coordinates":[-73.9823,40.783798],"type":"Point"}
}