{
  "type": "Feature",
  "properties": {
    "iso:country":"US",
    "sg:address":"510 Maloney Rd",
    "sg:city":"Poughkeepsie",
    "sg:classifiers":[
        {
            "category":"Real Estate",
            "subcategory":"Real Estate Agent",
            "type":"Services"
        }
    ],
    "sg:phone":"+1 845 463 1747",
    "sg:postcode":"12603",
    "sg:province":"NY",
    "sg:tags":[
        "building",
        "operator",
        "apartment"
    ],
    "wof:name":"Steven Manor Apartments",
    "wof:placetype":"venue"
},
  "geometry": {"coordinates":[-73.871578,41.641047],"type":"Point"}
}