{
  "type": "Feature",
  "properties": {
    "addr:full":"1603 2 Ave New York NY 10028",
    "addr:housenumber":"1603",
    "addr:postcode":"10028",
    "addr:street":"2 Ave",
    "iso:country":"US",
    "sg:address":"1603 2 Ave",
    "sg:city":"New York",
    "sg:classifiers":[
        {
            "category":"Retail",
            "subcategory":"Repair Shop",
            "type":"Services"
        }
    ],
    "sg:phone":"+1 212 518 2323",
    "sg:postcode":"10028",
    "sg:province":"NY",
    "sg:tags":[
        "lock",
        "locksmith"
    ],
    "wof:name":"24 Hrs Emergency Locksmith",
    "wof:placetype":"venue"
},
  "geometry": {"coordinates":[-73.954092,40.774656],"type":"Point"}
}