{
  "type": "Feature",
  "properties": {
    "iso:country":"US",
    "sg:address":"3431 E Tremont Ave",
    "sg:city":"Bronx",
    "sg:classifiers":[
        {
            "category":"Personal",
            "subcategory":"Beauty Salon",
            "type":"Services"
        }
    ],
    "sg:phone":"+1   ",
    "sg:postcode":"10465",
    "sg:province":"NY",
    "sg:tags":[
        "shop"
    ],
    "wof:name":"Ever Nail",
    "wof:placetype":"venue"
},
  "geometry": {"coordinates":[-73.827856,40.83277],"type":"Point"}
}