{
  "type": "Feature",
  "properties": {
    "iso:country":"US",
    "sg:address":"4 N Erie St",
    "sg:city":"Mayville",
    "sg:classifiers":[
        {
            "category":"Restaurant",
            "type":"Food & Drink"
        }
    ],
    "sg:phone":"+1 716 753 7601",
    "sg:postcode":"14757",
    "sg:province":"NY",
    "wof:name":"Mel's Bakery & Cafe",
    "wof:placetype":"venue"
},
  "geometry": {"coordinates":[-79.506788,42.255371],"type":"Point"}
}