{
  "type": "Feature",
  "properties": {
    "iso:country":"US",
    "sg:address":"163 US Hwy 9w",
    "sg:city":"Congers",
    "sg:classifiers":[
        {
            "category":"Building & Trades",
            "subcategory":"Construction",
            "type":"Services"
        }
    ],
    "sg:phone":"+1 845 268 2613",
    "sg:postcode":"10920",
    "sg:province":"NY",
    "sg:tags":[
        "installs",
        "pool",
        "swimming"
    ],
    "wof:name":"Swim & Sports Warehouse Outlet",
    "wof:placetype":"venue"
},
  "geometry": {"coordinates":[-73.928077,41.157972],"type":"Point"}
}