{
  "type": "Feature",
  "properties": {
    "addr:full":"3018 Colden Ave Bronx NY 10469",
    "addr:housenumber":"3018",
    "addr:postcode":"10469",
    "addr:street":"Colden Ave",
    "iso:country":"US",
    "sg:address":"3018 Colden Ave",
    "sg:city":"Bronx",
    "sg:classifiers":[
        {
            "category":"Health Services",
            "subcategory":"Doctor",
            "type":"Services"
        }
    ],
    "sg:phone":"+1 718 652 6206",
    "sg:postcode":"10469",
    "sg:province":"NY",
    "wof:name":"Hall Arthur",
    "wof:placetype":"venue"
},
  "geometry": {"coordinates":[-73.859284,40.869714],"type":"Point"}
}