{
  "type": "Feature",
  "properties": {
    "iso:country":"US",
    "sg:address":"10 Valleyview St",
    "sg:city":"Oneonta",
    "sg:classifiers":[
        {
            "category":"Professional",
            "subcategory":"Art Services",
            "type":"Services"
        }
    ],
    "sg:phone":"+1 607 431 9776",
    "sg:postcode":"13820",
    "sg:province":"NY",
    "sg:tags":[
        "interior",
        "designer",
        "decorator"
    ],
    "wof:name":"Jason Woertendyke",
    "wof:placetype":"venue"
},
  "geometry": {"coordinates":[-75.048849,42.45701],"type":"Point"}
}