{
  "type": "Feature",
  "properties": {
    "iso:country":"US",
    "sg:address":"165 N Village Ave",
    "sg:city":"Rockville Centre",
    "sg:classifiers":[
        {
            "category":"Health Services",
            "subcategory":"Doctor",
            "type":"Services"
        }
    ],
    "sg:phone":"+1 516 678 6816",
    "sg:postcode":"11570",
    "sg:province":"NY",
    "sg:tags":[
        "physician",
        "surgeon",
        "medical"
    ],
    "wof:name":"Pakstis Edward J MD",
    "wof:placetype":"venue"
},
  "geometry": {"coordinates":[-73.648399,40.6623],"type":"Point"}
}