{
  "type": "Feature",
  "properties": {
    "iso:country":"US",
    "sg:address":"777 Elmgrove Rd",
    "sg:city":"Rochester",
    "sg:classifiers":[
        {
            "category":"Manufacturing",
            "subcategory":"Tools & Machinery",
            "type":"Manufacturing & Wholesale Goods"
        }
    ],
    "sg:phone":"+1   ",
    "sg:postcode":"14606",
    "sg:province":"NY",
    "sg:tags":[
        "machine",
        "induction",
        "mfg"
    ],
    "wof:name":"Induction Atmospheres LLC",
    "wof:placetype":"venue"
},
  "geometry": {"coordinates":[-77.732435,43.160027],"type":"Point"}
}