{
  "type": "Feature",
  "properties": {
    "addr:full":"170 Cabot St West Babylon NY 11704",
    "addr:housenumber":"170",
    "addr:postcode":"11704",
    "addr:street":"Cabot St",
    "iso:country":"US",
    "sg:address":"170 Cabot St",
    "sg:city":"West Babylon",
    "sg:classifiers":[
        {
            "category":"Mining & Drilling",
            "type":"Manufacturing & Wholesale Goods"
        }
    ],
    "sg:phone":"+1 631 694 2822",
    "sg:postcode":"11704",
    "sg:province":"NY",
    "sg:tags":[
        "sand",
        "gravel",
        "pit"
    ],
    "wof:name":"110 Sand Company",
    "wof:placetype":"venue"
},
  "geometry": {"coordinates":[-73.393525,40.733695],"type":"Point"}
}