{
  "type": "Feature",
  "properties": {
    "iso:country":"US",
    "sg:address":"20 N Spruce St",
    "sg:city":"Batavia",
    "sg:classifiers":[
        {
            "category":"Home & Garden",
            "subcategory":"Household Appliances",
            "type":"Retail Goods"
        }
    ],
    "sg:phone":"+1 585 343 3355",
    "sg:postcode":"14020",
    "sg:province":"NY",
    "wof:name":"Ron Gervase",
    "wof:placetype":"venue"
},
  "geometry": {"coordinates":[-78.16869,42.997223],"type":"Point"}
}