{
  "type": "Feature",
  "properties": {
    "addr:full":"1309 Fulton St Brooklyn NY 11216",
    "addr:housenumber":"1309",
    "addr:postcode":"11216",
    "addr:street":"Fulton St",
    "iso:country":"US",
    "sg:address":"1309 Fulton St",
    "sg:city":"Brooklyn",
    "sg:classifiers":[
        {
            "category":"Bagels",
            "type":"Food & Drink"
        },
        {
            "category":"Coffee & Tea",
            "type":"Food & Drink"
        },
        {
            "category":"Food & Beverages",
            "subcategory":"Bakery",
            "type":"Retail Goods"
        },
        {
            "category":"Bakery",
            "type":"Food & Drink"
        },
        {
            "category":"Donuts",
            "type":"Food & Drink"
        }
    ],
    "sg:menulink":"http://www.allmenus.com/ny/brooklyn/138243-dunkin-donuts/menu/",
    "sg:phone":"+1 718 235 1511",
    "sg:postcode":"11216",
    "sg:province":"NY",
    "sg:tags":[
        "coffee",
        "tea",
        "american",
        "bagel",
        "bakery",
        "pastry"
    ],
    "wof:name":"Dunkin' Donuts",
    "wof:placetype":"venue"
},
  "geometry": {"coordinates":[-73.948909,40.680355],"type":"Point"}
}