{
  "type": "Feature",
  "properties": {
    "addr:full":"2460 Flatbush Ave Brooklyn NY 11234",
    "addr:housenumber":"2460",
    "addr:postcode":"11234",
    "addr:street":"Flatbush Ave",
    "iso:country":"US",
    "sg:address":"2460 Flatbush Ave",
    "sg:city":"Brooklyn",
    "sg:classifiers":[
        {
            "category":"Health Services",
            "subcategory":"Doctor",
            "type":"Services"
        }
    ],
    "sg:phone":"+1 718 692 0020",
    "sg:postcode":"11234",
    "sg:province":"NY",
    "sg:tags":[
        "physician",
        "surgeon"
    ],
    "wof:name":"Advanced Urology Assoc",
    "wof:placetype":"venue"
},
  "geometry": {"coordinates":[-73.92436499999999,40.611461],"type":"Point"}
}