{
  "type": "Feature",
  "properties": {
    "iso:country":"US",
    "sg:address":"622 Pullman Ave",
    "sg:city":"Rochester",
    "sg:classifiers":[
        {
            "category":"Manufacturing",
            "subcategory":"Tools & Machinery",
            "type":"Manufacturing & Wholesale Goods"
        }
    ],
    "sg:phone":"+1   ",
    "sg:postcode":"14615",
    "sg:province":"NY",
    "sg:tags":[
        "machine",
        "shop"
    ],
    "wof:name":"H T Specialty Inc",
    "wof:placetype":"venue"
},
  "geometry": {"coordinates":[-77.648419,43.196482],"type":"Point"}
}