{
  "type": "Feature",
  "properties": {
    "iso:country":"US",
    "sg:address":"31 Tioga Street",
    "sg:city":"Staten Island",
    "sg:classifiers":[
        {
            "category":"Health Services",
            "subcategory":"Doctor",
            "type":"Services"
        }
    ],
    "sg:phone":"+1 718 981 5040",
    "sg:postcode":"10301",
    "sg:province":"NY",
    "sg:tags":[
        "dermatologist"
    ],
    "wof:name":"Dominick Ligresti MD",
    "wof:placetype":"venue"
},
  "geometry": {"coordinates":[-74.100478,40.611874],"type":"Point"}
}