{
  "type": "Feature",
  "properties": {
    "iso:country":"US",
    "sg:address":"3562 Lake Shore Dr",
    "sg:city":"Lake George",
    "sg:classifiers":[
        {
            "category":"Arts & Performance",
            "subcategory":"Theater",
            "type":"Entertainment"
        }
    ],
    "sg:phone":"+1 518 623 3760",
    "sg:postcode":"12845",
    "sg:province":"NY",
    "sg:tags":[
        "theatrical",
        "production"
    ],
    "wof:name":"C & E Associates",
    "wof:placetype":"venue"
},
  "geometry": {"coordinates":[-73.68767,43.472094],"type":"Point"}
}