{
  "type": "Feature",
  "properties": {
    "iso:country":"US",
    "sg:address":"7530 Transit Rd",
    "sg:city":"Buffalo",
    "sg:classifiers":[
        {
            "category":"Restaurant",
            "type":"Food & Drink"
        }
    ],
    "sg:menulink":"http://www.allmenus.com/ny/amherst/245749-la-tolteca-mexican-restaurante/menu/",
    "sg:phone":"+1 716 565 0105",
    "sg:postcode":"14221",
    "sg:province":"NY",
    "sg:tags":[
        "mexican"
    ],
    "wof:name":"La Tolteca Mexican Restaurante",
    "wof:placetype":"venue"
},
  "geometry": {"coordinates":[-78.696935,42.973126],"type":"Point"}
}