{
  "type": "Feature",
  "properties": {
    "addr:full":"105 Abeel St Kingston NY 12401",
    "addr:housenumber":"105",
    "addr:postcode":"12401",
    "addr:street":"Abeel St",
    "iso:country":"US",
    "sg:address":"105 Abeel St",
    "sg:city":"Kingston",
    "sg:classifiers":[
        {
            "category":"Shopping",
            "subcategory":"Computers & Home Electronics",
            "type":"Retail Goods"
        }
    ],
    "sg:phone":"+1   ",
    "sg:postcode":"12401",
    "sg:province":"NY",
    "wof:name":"Mac Diagnostics",
    "wof:placetype":"venue"
},
  "geometry": {"coordinates":[-73.985998,41.917364],"type":"Point"}
}