{
  "type": "Feature",
  "properties": {
    "addr:full":"114 Greenwich St New York NY 10006",
    "addr:housenumber":"114",
    "addr:postcode":"10006",
    "addr:street":"Greenwich St",
    "iso:country":"US",
    "sg:address":"114 Greenwich St",
    "sg:city":"New York",
    "sg:classifiers":[
        {
            "category":"Restaurant",
            "type":"Food & Drink"
        }
    ],
    "sg:phone":"+1 212 267 6800",
    "sg:postcode":"10006",
    "sg:province":"NY",
    "sg:tags":[
        "mexican"
    ],
    "wof:name":"Tijuana Toms",
    "wof:placetype":"venue"
},
  "geometry": {"coordinates":[-74.34318,40.708801],"type":"Point"}
}