{
  "type": "Feature",
  "properties": {
    "addr:full":"1160 Broadway New York NY 10001",
    "addr:housenumber":"1160",
    "addr:postcode":"10001",
    "addr:street":"Broadway",
    "iso:country":"US",
    "sg:address":"1160 Broadway",
    "sg:city":"New York",
    "sg:classifiers":[
        {
            "category":"Health Services",
            "subcategory":"Hospital",
            "type":"Services"
        }
    ],
    "sg:phone":"+1 212 481 1256",
    "sg:postcode":"10001",
    "sg:province":"NY",
    "wof:name":"New York Hospital Medical Center Of Queens",
    "wof:placetype":"venue"
},
  "geometry": {"coordinates":[-73.988641,40.744815],"type":"Point"}
}