{
  "type": "Feature",
  "properties": {
    "iso:country":"US",
    "sg:address":"420 Railroad Way",
    "sg:city":"Mamaroneck",
    "sg:classifiers":[
        {
            "category":"Manufacturing",
            "subcategory":"Tools & Machinery",
            "type":"Manufacturing & Wholesale Goods"
        }
    ],
    "sg:phone":"+1 914 698 5988",
    "sg:postcode":"10543",
    "sg:province":"NY",
    "sg:tags":[
        "ind",
        "lighting"
    ],
    "wof:name":"D'Ac Lighting",
    "wof:placetype":"venue"
},
  "geometry": {"coordinates":[-73.744224,40.947387],"type":"Point"}
}