{
  "type": "Feature",
  "properties": {
    "iso:country":"US",
    "sg:address":"75 Ames St",
    "sg:city":"Massena",
    "sg:classifiers":[
        {
            "category":"Personal",
            "subcategory":"Beauty Salon",
            "type":"Services"
        }
    ],
    "sg:phone":"+1 315 769 2211",
    "sg:postcode":"13662",
    "sg:province":"NY",
    "wof:name":"Lotte's Beauty Boutique",
    "wof:placetype":"venue"
},
  "geometry": {"coordinates":[-74.89162399999999,44.941829],"type":"Point"}
}