{
  "type": "Feature",
  "properties": {
    "addr:full":"1010 Michigan Ave Niagara Falls NY 14305",
    "addr:housenumber":"1010",
    "addr:postcode":"14305",
    "addr:street":"Michigan Ave",
    "iso:country":"US",
    "sg:address":"1010 Michigan Ave",
    "sg:city":"Niagara Falls",
    "sg:classifiers":[
        {
            "category":"Organizations",
            "subcategory":"Religious Organization",
            "type":"Services"
        }
    ],
    "sg:phone":"+1   ",
    "sg:postcode":"14305",
    "sg:province":"NY",
    "sg:tags":[
        "church"
    ],
    "wof:name":"Zion Lutheran Church",
    "wof:placetype":"venue"
},
  "geometry": {"coordinates":[-79.049385,43.104702],"type":"Point"}
}