{
  "type": "Feature",
  "properties": {
    "iso:country":"US",
    "sg:address":"114 Barlow Drive S",
    "sg:city":"Brooklyn",
    "sg:classifiers":[
        {
            "category":"Health Services",
            "subcategory":"Dentist",
            "type":"Services"
        }
    ],
    "sg:phone":"+1 718 241 7347",
    "sg:postcode":"11234",
    "sg:province":"NY",
    "wof:name":"Jonas Paul DDS",
    "wof:placetype":"venue"
},
  "geometry": {"coordinates":[-73.905216,40.608845],"type":"Point"}
}