{
  "type": "Feature",
  "properties": {
    "iso:country":"US",
    "sg:address":"86 S Portland Ave",
    "sg:city":"Brooklyn",
    "sg:classifiers":[
        {
            "category":"Restaurant",
            "type":"Food & Drink"
        }
    ],
    "sg:phone":"+1 718 643 0000",
    "sg:postcode":"11217",
    "sg:province":"NY",
    "sg:tags":[
        "mexican"
    ],
    "sg:website":"www.pequenarestaurant.com",
    "wof:name":"Pequena",
    "wof:placetype":"venue"
},
  "geometry": {"coordinates":[-73.974593,40.68707],"type":"Point"}
}