{
  "type": "Feature",
  "properties": {
    "iso:country":"US",
    "sg:address":"2200 Smithtown Ave",
    "sg:city":"Ronkonkoma",
    "sg:classifiers":[
        {
            "category":"Wholesale",
            "subcategory":"Electrical",
            "type":"Manufacturing & Wholesale Goods"
        }
    ],
    "sg:phone":"+1 631 981 2400",
    "sg:postcode":"11779",
    "sg:province":"NY",
    "sg:tags":[
        "semiconductor",
        "device"
    ],
    "wof:name":"N H I",
    "wof:placetype":"venue"
},
  "geometry": {"coordinates":[-73.11064399999999,40.800322],"type":"Point"}
}