{
  "type": "Feature",
  "properties": {
    "addr:full":"252 Plymouth Ave N Rochester NY 14608",
    "addr:housenumber":"252",
    "addr:postcode":"14608",
    "addr:street":"Plymouth Ave N",
    "iso:country":"US",
    "sg:address":"252 Plymouth Ave N",
    "sg:city":"Rochester",
    "sg:classifiers":[
        {
            "category":"Professional",
            "subcategory":"Lawyer & Legal Services",
            "type":"Services"
        }
    ],
    "sg:phone":"+1   ",
    "sg:postcode":"14608",
    "sg:province":"NY",
    "wof:name":"Scott Garretson",
    "wof:placetype":"venue"
},
  "geometry": {"coordinates":[-77.618156,43.158264],"type":"Point"}
}