{
  "type": "Feature",
  "properties": {
    "iso:country":"US",
    "sg:address":"768 Goodman St N",
    "sg:city":"Rochester",
    "sg:classifiers":[
        {
            "category":"Autos & Motor Vehicles",
            "subcategory":"Automobile Sales",
            "type":"Retail Goods"
        }
    ],
    "sg:phone":"+1   ",
    "sg:postcode":"14609",
    "sg:province":"NY",
    "sg:tags":[
        "used"
    ],
    "wof:name":"Southern Motors",
    "wof:placetype":"venue"
},
  "geometry": {"coordinates":[-77.580015,43.168676],"type":"Point"}
}