{
  "type": "Feature",
  "properties": {
    "iso:country":"US",
    "sg:address":"31 Thurman St",
    "sg:city":"Yonkers",
    "sg:classifiers":[
        {
            "category":"Building & Trades",
            "subcategory":"Plumbing",
            "type":"Services"
        }
    ],
    "sg:phone":"+1 914 965 4306",
    "sg:postcode":"10701",
    "sg:province":"NY",
    "sg:tags":[
        "contractor"
    ],
    "wof:name":"AM Temp Refrigeration & Air",
    "wof:placetype":"venue"
},
  "geometry": {"coordinates":[-73.88957499999999,40.929807],"type":"Point"}
}