{
  "type": "Feature",
  "properties": {
    "addr:full":"207 Dow Ave Mineola NY 11501",
    "addr:housenumber":"207",
    "addr:postcode":"11501",
    "addr:street":"Dow Ave",
    "iso:country":"US",
    "sg:address":"207 Dow Ave",
    "sg:city":"Mineola",
    "sg:classifiers":[
        {
            "category":"Building & Trades",
            "subcategory":"Landscaping Services",
            "type":"Services"
        }
    ],
    "sg:phone":"+1 516 248 4613",
    "sg:postcode":"11501",
    "sg:province":"NY",
    "sg:tags":[
        "lawn",
        "garden"
    ],
    "wof:name":"Joe & Manny Landscaping Inc",
    "wof:placetype":"venue"
},
  "geometry": {"coordinates":[-73.62663000000001,40.748464],"type":"Point"}
}