{
  "type": "Feature",
  "properties": {
    "addr:full":"184 Clinton St Binghamton NY 13905",
    "addr:housenumber":"184",
    "addr:postcode":"13905",
    "addr:street":"Clinton St",
    "iso:country":"US",
    "sg:address":"184 Clinton St",
    "sg:city":"Binghamton",
    "sg:classifiers":[
        {
            "category":"Food & Beverages",
            "subcategory":"Groceries & Convenience Stores",
            "type":"Retail Goods"
        }
    ],
    "sg:phone":"+1 607 724 4905",
    "sg:postcode":"13905",
    "sg:province":"NY",
    "sg:tags":[
        "grocer"
    ],
    "wof:name":"Nannery's Grocery Store",
    "wof:placetype":"venue"
},
  "geometry": {"coordinates":[-75.926744,42.105992],"type":"Point"}
}