{
  "type": "Feature",
  "properties": {
    "addr:full":"65 Bridge St Beaver Dams NY 14830",
    "addr:housenumber":"65",
    "addr:postcode":"14830",
    "addr:street":"Bridge St",
    "iso:country":"US",
    "sg:address":"65 Bridge St",
    "sg:city":"Beaver Dams",
    "sg:classifiers":[
        {
            "category":"Insurance",
            "subcategory":"Life Insurance",
            "type":"Services"
        }
    ],
    "sg:phone":"+1 607 936 4149",
    "sg:postcode":"14830",
    "sg:province":"NY",
    "wof:name":"Allstate",
    "wof:placetype":"venue"
},
  "geometry": {"coordinates":[-77.060833,42.151089],"type":"Point"}
}