{
  "type": "Feature",
  "properties": {
    "iso:country":"US",
    "sg:address":"240 W 35 St",
    "sg:city":"New York",
    "sg:classifiers":[
        {
            "category":"Professional",
            "subcategory":"Business Services",
            "type":"Services"
        },
        {
            "category":"Travel",
            "subcategory":"Campground",
            "type":"Entertainment"
        }
    ],
    "sg:phone":"+1 212 971 9562",
    "sg:postcode":"10001",
    "sg:province":"NY",
    "sg:tags":[
        "camp"
    ],
    "wof:name":"Fiver Foundation Inc",
    "wof:placetype":"venue"
},
  "geometry": {"coordinates":[-73.992135,40.752301],"type":"Point"}
}