{
  "type": "Feature",
  "properties": {
    "addr:full":"555 Union St Hudson NY 12534",
    "addr:housenumber":"555",
    "addr:postcode":"12534",
    "addr:street":"Union St",
    "iso:country":"US",
    "sg:address":"555 Union St",
    "sg:city":"Hudson",
    "sg:classifiers":[
        {
            "category":"Health Services",
            "subcategory":"Doctor",
            "type":"Services"
        }
    ],
    "sg:phone":"+1 518 828 1688",
    "sg:postcode":"12534",
    "sg:province":"NY",
    "sg:tags":[
        "physician",
        "surgeon"
    ],
    "wof:name":"Iqbal Karim MD PC",
    "wof:placetype":"venue"
},
  "geometry": {"coordinates":[-73.786614,42.248022],"type":"Point"}
}