{
  "type": "Feature",
  "properties": {
    "addr:full":"7930 Rae Blvd Victor NY 14564",
    "addr:housenumber":"7930",
    "addr:postcode":"14564",
    "addr:street":"Rae Blvd",
    "iso:country":"US",
    "sg:address":"7930 Rae Blvd",
    "sg:city":"Victor",
    "sg:classifiers":[
        {
            "category":"Home & Garden",
            "subcategory":"Furniture",
            "type":"Retail Goods"
        }
    ],
    "sg:phone":"+1 585 924 3820",
    "sg:postcode":"14564",
    "sg:province":"NY",
    "wof:name":"Viking International Furniture",
    "wof:placetype":"venue"
},
  "geometry": {"coordinates":[-77.471159,43.000082],"type":"Point"}
}