{
  "type": "Feature",
  "properties": {
    "addr:full":"9 W 130th Street New York NY 10037",
    "addr:housenumber":"9",
    "addr:postcode":"10037",
    "addr:street":"W 130Th Street",
    "iso:country":"US",
    "sg:address":"9 W 130th Street",
    "sg:city":"New York",
    "sg:classifiers":[
        {
            "category":"Education",
            "subcategory":"Special Training",
            "type":"Public Place"
        },
        {
            "category":"Education",
            "subcategory":"School",
            "type":"Public Place"
        }
    ],
    "sg:phone":"+1 212 690 8094",
    "sg:postcode":"10037",
    "sg:province":"NY",
    "sg:tags":[
        "high",
        "middle",
        "specialty",
        "elementary"
    ],
    "wof:name":"Fellowship of Learningschool",
    "wof:placetype":"venue"
},
  "geometry": {"coordinates":[-73.940313,40.809617],"type":"Point"}
}