{
  "type": "Feature",
  "properties": {
    "addr:full":"1 Old Orchard Rd Armonk NY 10504",
    "addr:housenumber":"1",
    "addr:postcode":"10504",
    "addr:street":"Old Orchard Rd",
    "iso:country":"US",
    "sg:address":"1 Old Orchard Rd",
    "sg:city":"Armonk",
    "sg:classifiers":[
        {
            "category":"Manufacturing",
            "subcategory":"Tools & Machinery",
            "type":"Manufacturing & Wholesale Goods"
        }
    ],
    "sg:phone":"+1 914 499 1900",
    "sg:postcode":"10504",
    "sg:province":"NY",
    "sg:tags":[
        "computer"
    ],
    "sg:website":"www.ibm.com",
    "wof:name":"IBM Corp",
    "wof:placetype":"venue"
},
  "geometry": {"coordinates":[-73.70932999999999,41.119974],"type":"Point"}
}