{
  "type": "Feature",
  "properties": {
    "iso:country":"US",
    "sg:address":"5595 Ridge Rd W",
    "sg:city":"Spencerport",
    "sg:classifiers":[
        {
            "category":"Autos & Motor Vehicles",
            "subcategory":"Automobile Sales",
            "type":"Retail Goods"
        }
    ],
    "sg:phone":"+1 585 352 1000",
    "sg:postcode":"14559",
    "sg:province":"NY",
    "sg:tags":[
        "car",
        "used",
        "dealer"
    ],
    "wof:name":"Ridgeview Motors Inc",
    "wof:placetype":"venue"
},
  "geometry": {"coordinates":[-77.82987799999999,43.221042],"type":"Point"}
}