{
  "type": "Feature",
  "properties": {
    "iso:country":"US",
    "sg:address":"945 S 1st St",
    "sg:city":"Fulton",
    "sg:classifiers":[
        {
            "category":"Retail",
            "subcategory":"Auto Repair",
            "type":"Services"
        }
    ],
    "sg:phone":"+1 315 593 7854",
    "sg:postcode":"13069",
    "sg:province":"NY",
    "sg:tags":[
        "body",
        "painting",
        "repairing",
        "automobile"
    ],
    "wof:name":"Custom Collision",
    "wof:placetype":"venue"
},
  "geometry": {"coordinates":[-76.39610500000001,43.306811],"type":"Point"}
}