{
  "type": "Feature",
  "properties": {
    "addr:full":"661 Plains Rd Wallkill NY 12589",
    "addr:housenumber":"661",
    "addr:postcode":"12589",
    "addr:street":"Plains Rd",
    "iso:country":"US",
    "sg:address":"661 Plains Rd",
    "sg:city":"Wallkill",
    "sg:classifiers":[
        {
            "category":"Professional",
            "subcategory":"Business Services",
            "type":"Services"
        }
    ],
    "sg:phone":"+1   ",
    "sg:postcode":"12589",
    "sg:province":"NY",
    "wof:name":"Garrison Auction Realty",
    "wof:placetype":"venue"
},
  "geometry": {"coordinates":[-74.141824,41.606677],"type":"Point"}
}