{
  "type": "Feature",
  "properties": {
    "iso:country":"US",
    "sg:address":"290 Lenox Ave",
    "sg:city":"New York",
    "sg:classifiers":[
        {
            "category":"Professional",
            "subcategory":"Management & Consulting",
            "type":"Services"
        }
    ],
    "sg:phone":"+1 212 410 0030",
    "sg:postcode":"10027",
    "sg:province":"NY",
    "sg:tags":[
        "development",
        "economic"
    ],
    "wof:name":"Upper Manhattan Impowerment",
    "wof:placetype":"venue"
},
  "geometry": {"coordinates":[-73.94562500000001,40.807362],"type":"Point"}
}