{
  "type": "Feature",
  "properties": {
    "iso:country":"US",
    "sg:address":"39 Elm St",
    "sg:city":"Warrensburg",
    "sg:classifiers":[
        {
            "category":"Health Services",
            "subcategory":"Health Practitioner",
            "type":"Services"
        }
    ],
    "sg:phone":"+1 518 623 2094",
    "sg:postcode":"12885",
    "sg:province":"NY",
    "sg:tags":[
        "therapist",
        "physical"
    ],
    "sg:website":"www.hhhn.org",
    "wof:name":"Hudson Headwaters Health Ntwrk",
    "wof:placetype":"venue"
},
  "geometry": {"coordinates":[-73.776062,43.496476],"type":"Point"}
}