{
  "type": "Feature",
  "properties": {
    "addr:full":"151 Maujer St Brooklyn NY 11206",
    "addr:housenumber":"151",
    "addr:postcode":"11206",
    "addr:street":"Maujer St",
    "iso:country":"US",
    "sg:address":"151 Maujer St",
    "sg:city":"Brooklyn",
    "sg:classifiers":[
        {
            "category":"Organizations",
            "subcategory":"Membership Organization",
            "type":"Services"
        }
    ],
    "sg:phone":"+1 718 387 6536",
    "sg:postcode":"11206",
    "sg:province":"NY",
    "wof:name":"Ny City Nghbrhd Wic Prog",
    "wof:placetype":"venue"
},
  "geometry": {"coordinates":[-73.944474,40.71089],"type":"Point"}
}