{
  "type": "Feature",
  "properties": {
    "iso:country":"US",
    "sg:address":"12220 Merrill St",
    "sg:city":"Jamaica",
    "sg:classifiers":[
        {
            "category":"Organizations",
            "subcategory":"Religious Organization",
            "type":"Services"
        }
    ],
    "sg:phone":"+1 718 276 2799",
    "sg:postcode":"11434",
    "sg:province":"NY",
    "sg:tags":[
        "church"
    ],
    "wof:name":"Christ Church Intl",
    "wof:placetype":"venue"
},
  "geometry": {"coordinates":[-73.769946,40.683043],"type":"Point"}
}