{
  "type": "Feature",
  "properties": {
    "iso:country":"US",
    "sg:address":"666 State Hwy 211",
    "sg:city":"Middletown",
    "sg:classifiers":[
        {
            "category":"Restaurant",
            "type":"Food & Drink"
        }
    ],
    "sg:phone":"+1 845 695 8700",
    "sg:postcode":"10941",
    "sg:province":"NY",
    "wof:name":"Marco's Pizza",
    "wof:placetype":"venue"
},
  "geometry": {"coordinates":[-74.36197,41.465295],"type":"Point"}
}