{
  "type": "Feature",
  "properties": {
    "iso:country":"US",
    "sg:address":"55 Upton Dr",
    "sg:city":"Sound Beach",
    "sg:classifiers":[
        {
            "category":"Professional",
            "subcategory":"Management & Consulting",
            "type":"Services"
        }
    ],
    "sg:phone":"+1 631 821 7813",
    "sg:postcode":"11789",
    "sg:province":"NY",
    "sg:tags":[
        "consultant",
        "educational"
    ],
    "wof:name":"Melissa P Rash Enterprises",
    "wof:placetype":"venue"
},
  "geometry": {"coordinates":[-72.98269000000001,40.958093],"type":"Point"}
}