{
  "type": "Feature",
  "properties": {
    "addr:full":"623 E 4th St Brooklyn NY 11218",
    "addr:housenumber":"623",
    "addr:postcode":"11218",
    "addr:street":"E 4Th St",
    "iso:country":"US",
    "sg:address":"623 E 4th St",
    "sg:city":"Brooklyn",
    "sg:classifiers":[
        {
            "category":"Wholesale",
            "subcategory":"Non-durable Goods",
            "type":"Manufacturing & Wholesale Goods"
        }
    ],
    "sg:phone":"+1 718 853 1620",
    "sg:postcode":"11218",
    "sg:province":"NY",
    "wof:name":"Timber Loc House Construction",
    "wof:placetype":"venue"
},
  "geometry": {"coordinates":[-73.97515300000001,40.637231],"type":"Point"}
}