{
  "type": "Feature",
  "properties": {
    "addr:full":"1116 Champlain St Ogdensburg NY 13669",
    "addr:housenumber":"1116",
    "addr:postcode":"13669",
    "addr:street":"Champlain St",
    "iso:country":"US",
    "sg:address":"1116 Champlain St",
    "sg:city":"Ogdensburg",
    "sg:classifiers":[
        {
            "category":"Home & Garden",
            "subcategory":"Household Appliances",
            "type":"Retail Goods"
        }
    ],
    "sg:phone":"+1 315 394 0884",
    "sg:postcode":"13669",
    "sg:province":"NY",
    "wof:name":"Hayes Appliance Ctr",
    "wof:placetype":"venue"
},
  "geometry": {"coordinates":[-75.46233599999999,44.70021],"type":"Point"}
}