{
  "type": "Feature",
  "properties": {
    "addr:full":"36 Taaffe Pl Brooklyn NY 11205",
    "addr:housenumber":"36",
    "addr:postcode":"11205",
    "addr:street":"Taaffe Pl",
    "iso:country":"US",
    "sg:address":"36 Taaffe Pl",
    "sg:city":"Brooklyn",
    "sg:classifiers":[
        {
            "category":"Shopping",
            "subcategory":"Computers & Home Electronics",
            "type":"Retail Goods"
        }
    ],
    "sg:phone":"+1 718 963 9757",
    "sg:postcode":"11205",
    "sg:province":"NY",
    "sg:tags":[
        "equipment",
        "dealer"
    ],
    "wof:name":"Prime Trading LLC",
    "wof:placetype":"venue"
},
  "geometry": {"coordinates":[-73.961071,40.698167],"type":"Point"}
}