{
  "type": "Feature",
  "properties": {
    "iso:country":"US",
    "sg:address":"400 Halstead Ave",
    "sg:city":"Harrison",
    "sg:classifiers":[
        {
            "category":"Home & Garden",
            "subcategory":"Furniture",
            "type":"Retail Goods"
        }
    ],
    "sg:phone":"+1 914 835 4450",
    "sg:postcode":"10528",
    "sg:province":"NY",
    "wof:name":"Freight Liquidators",
    "wof:placetype":"venue"
},
  "geometry": {"coordinates":[-73.709267,40.969662],"type":"Point"}
}