{
  "type": "Feature",
  "properties": {
    "iso:country":"US",
    "sg:address":"8995 Pardee Hollow Rd",
    "sg:city":"Wayland",
    "sg:classifiers":[
        {
            "category":"Building & Trades",
            "subcategory":"Plumbing",
            "type":"Services"
        }
    ],
    "sg:phone":"+1 585 534 9029",
    "sg:postcode":"14572",
    "sg:province":"NY",
    "sg:tags":[
        "conditioning",
        "air",
        "system",
        "contractor"
    ],
    "wof:name":"Gleason Heating & Air Cond",
    "wof:placetype":"venue"
},
  "geometry": {"coordinates":[-77.497911,42.577877],"type":"Point"}
}