{
  "type": "Feature",
  "properties": {
    "addr:full":"360 W 21st Street Apt 3F New York NY 10011",
    "addr:housenumber":"360",
    "addr:postcode":"10011",
    "addr:street":"W 21St Street Apt 3F",
    "iso:country":"US",
    "sg:address":"360 W 21st Street Apt 3F",
    "sg:city":"New York",
    "sg:classifiers":[
        {
            "category":"Professional",
            "subcategory":"Lawyer & Legal Services",
            "type":"Services"
        }
    ],
    "sg:phone":"+1 212 243 2681",
    "sg:postcode":"10011",
    "sg:province":"NY",
    "wof:name":"Abrams Carol A Atty",
    "wof:placetype":"venue"
},
  "geometry": {"coordinates":[-74.001289,40.744732],"type":"Point"}
}