{
  "type": "Feature",
  "properties": {
    "addr:full":"3855 Broadway New York NY 10032",
    "addr:housenumber":"3855",
    "addr:postcode":"10032",
    "addr:street":"Broadway",
    "iso:country":"US",
    "sg:address":"3855 Broadway",
    "sg:city":"New York",
    "sg:classifiers":[
        {
            "category":"Utilities",
            "subcategory":"Mobile Phone",
            "type":"Services"
        }
    ],
    "sg:phone":"+1 212 740 6155",
    "sg:postcode":"10032",
    "sg:province":"NY",
    "sg:tags":[
        "equipment",
        "paging",
        "signaling",
        "system"
    ],
    "wof:name":"Active Communications",
    "wof:placetype":"venue"
},
  "geometry": {"coordinates":[-73.943389,40.836108],"type":"Point"}
}