{
  "type": "Feature",
  "properties": {
    "iso:country":"US",
    "sg:address":"16 Mount Vernon Ave",
    "sg:city":"Mt Vernon",
    "sg:classifiers":[
        {
            "category":"Restaurant",
            "type":"Food & Drink"
        }
    ],
    "sg:phone":"+1 914 668 5000",
    "sg:postcode":"10550",
    "sg:province":"NY",
    "wof:name":"Famous Little Italy Pizza",
    "wof:placetype":"venue"
},
  "geometry": {"coordinates":[-73.844075,40.910557],"type":"Point"}
}