{
  "type": "Feature",
  "properties": {
    "iso:country":"US",
    "sg:address":"1524 Cain Rd",
    "sg:city":"Angola",
    "sg:phone":"+1 716 337 2578",
    "sg:postcode":"14006",
    "sg:province":"NY",
    "sg:tags":[
        "vegetable",
        "farm",
        "fruit"
    ],
    "wof:name":"Vacco Farms Inc",
    "wof:placetype":"venue"
},
  "geometry": {"coordinates":[-78.987928,42.609432],"type":"Point"}
}