{
  "type": "Feature",
  "properties": {
    "iso:country":"US",
    "sg:address":"5388 Rte 25A",
    "sg:city":"Calverton",
    "sg:classifiers":[
        {
            "category":"Home & Garden",
            "subcategory":"Household Appliances",
            "type":"Retail Goods"
        }
    ],
    "sg:phone":"+1 631 474 7116",
    "sg:postcode":"11933",
    "sg:province":"NY",
    "wof:name":"Home Care Appliance Svc",
    "wof:placetype":"venue"
},
  "geometry": {"coordinates":[-72.814784,40.942786],"type":"Point"}
}