{
  "type": "Feature",
  "properties": {
    "addr:full":"5317 Clarendon Rd Brooklyn NY 11203",
    "addr:housenumber":"5317",
    "addr:postcode":"11203",
    "addr:street":"Clarendon Rd",
    "iso:country":"US",
    "sg:address":"5317 Clarendon Rd",
    "sg:city":"Brooklyn",
    "sg:classifiers":[
        {
            "category":"Real Estate",
            "subcategory":"Real Estate Agent",
            "type":"Services"
        }
    ],
    "sg:phone":"+1 718 451 1000",
    "sg:postcode":"11203",
    "sg:province":"NY",
    "wof:name":"Helpful Realty LLC",
    "wof:placetype":"venue"
},
  "geometry": {"coordinates":[-73.925847,40.644738],"type":"Point"}
}