{
  "type": "Feature",
  "properties": {
    "addr:full":"363 W Seneca Tpke Syracuse NY 13207",
    "addr:housenumber":"363",
    "addr:postcode":"13207",
    "addr:street":"W Seneca Tpke",
    "iso:country":"US",
    "sg:address":"363 W Seneca Tpke",
    "sg:city":"Syracuse",
    "sg:classifiers":[
        {
            "category":"Bars & Pubs",
            "type":"Food & Drink"
        }
    ],
    "sg:phone":"+1 315 492 9926",
    "sg:postcode":"13207",
    "sg:province":"NY",
    "wof:name":"Remedy Tavern",
    "wof:placetype":"venue"
},
  "geometry": {"coordinates":[-76.152743,43.001902],"type":"Point"}
}