{
  "type": "Feature",
  "properties": {
    "addr:full":"357 Windsor Hwy Ste 100 New Windsor NY 12553",
    "addr:housenumber":"357;100",
    "addr:postcode":"12553",
    "addr:street":"Windsor Hwy Ste",
    "iso:country":"US",
    "sg:address":"357 Windsor Hwy Ste 100",
    "sg:city":"New Windsor",
    "sg:classifiers":[
        {
            "category":"Personal",
            "subcategory":"Barber",
            "type":"Services"
        }
    ],
    "sg:phone":"+1 845 787 5629",
    "sg:postcode":"12553",
    "sg:province":"NY",
    "wof:name":"Gustavos Barber Shop",
    "wof:placetype":"venue"
},
  "geometry": {"coordinates":[-74.33488699999999,41.4605],"type":"Point"}
}