{
  "type": "Feature",
  "properties": {
    "iso:country":"US",
    "sg:address":"23 Old Dock Rd",
    "sg:city":"Yaphank",
    "sg:classifiers":[
        {
            "category":"Wholesale",
            "subcategory":"Machinery & Supplies",
            "type":"Manufacturing & Wholesale Goods"
        }
    ],
    "sg:phone":"+1 631 924 1315",
    "sg:postcode":"11980",
    "sg:province":"NY",
    "sg:tags":[
        "control",
        "for",
        "process",
        "system",
        "water",
        "primarily"
    ],
    "wof:name":"Eagle Control Corp",
    "wof:placetype":"venue"
},
  "geometry": {"coordinates":[-72.94394200000001,40.809289],"type":"Point"}
}