{
  "type": "Feature",
  "properties": {
    "addr:full":"323 1 Ave New York NY 10003",
    "addr:housenumber":"323",
    "addr:postcode":"10003",
    "addr:street":"1 Ave",
    "iso:country":"US",
    "sg:address":"323 1 Ave",
    "sg:city":"New York",
    "sg:classifiers":[
        {
            "category":"Professional",
            "subcategory":"Accounting & Tax Preparation",
            "type":"Services"
        }
    ],
    "sg:phone":"+1 212 358 0801",
    "sg:postcode":"10003",
    "sg:province":"NY",
    "sg:tags":[
        "return",
        "filing"
    ],
    "wof:name":"H & R Block Tax Svc",
    "wof:placetype":"venue"
},
  "geometry": {"coordinates":[-73.987968,40.723942],"type":"Point"}
}