{
  "type": "Feature",
  "properties": {
    "addr:full":"39 Laurel St Patchogue NY 11772",
    "addr:housenumber":"39",
    "addr:postcode":"11772",
    "addr:street":"Laurel St",
    "iso:country":"US",
    "sg:address":"39 Laurel St",
    "sg:city":"Patchogue",
    "sg:classifiers":[
        {
            "category":"Building & Trades",
            "subcategory":"Electrical",
            "type":"Services"
        }
    ],
    "sg:phone":"+1 631 207 0771",
    "sg:postcode":"11772",
    "sg:province":"NY",
    "sg:tags":[
        "electrical",
        "contractor"
    ],
    "wof:name":"Rant Electrical Contracting",
    "wof:placetype":"venue"
},
  "geometry": {"coordinates":[-73.01176599999999,40.755454],"type":"Point"}
}