{
  "type": "Feature",
  "properties": {
    "iso:country":"US",
    "sg:address":"390 Spencerport Rd",
    "sg:city":"Rochester",
    "sg:classifiers":[
        {
            "category":"Autos & Motor Vehicles",
            "subcategory":"Auto Supplies",
            "type":"Retail Goods"
        }
    ],
    "sg:phone":"+1 585 426 0770",
    "sg:postcode":"14606",
    "sg:province":"NY",
    "sg:tags":[
        "automobile",
        "parts"
    ],
    "sg:website":"www.autozone.com",
    "wof:name":"Autozone",
    "wof:placetype":"venue"
},
  "geometry": {"coordinates":[-77.701369,43.169518],"type":"Point"}
}