{
  "type": "Feature",
  "properties": {
    "addr:full":"353 Hempstead Ave Malverne NY 11565",
    "addr:housenumber":"353",
    "addr:postcode":"11565",
    "addr:street":"Hempstead Ave",
    "iso:country":"US",
    "sg:address":"353 Hempstead Ave",
    "sg:city":"Malverne",
    "sg:classifiers":[
        {
            "category":"Professional",
            "subcategory":"Lawyer & Legal Services",
            "type":"Services"
        }
    ],
    "sg:phone":"+1 516 599 6420",
    "sg:postcode":"11565",
    "sg:province":"NY",
    "sg:tags":[
        "personal",
        "injury"
    ],
    "wof:name":"Kruman Martin J Atty",
    "wof:placetype":"venue"
},
  "geometry": {"coordinates":[-73.66660299999999,40.678699],"type":"Point"}
}