{
  "type": "Feature",
  "properties": {
    "iso:country":"US",
    "sg:address":"17 Holland St",
    "sg:city":"Alexandria Bay",
    "sg:classifiers":[
        {
            "category":"Travel",
            "subcategory":"Hotels & Motels",
            "type":"Entertainment"
        }
    ],
    "sg:phone":"+1   ",
    "sg:postcode":"13607",
    "sg:province":"NY",
    "sg:tags":[
        "bar"
    ],
    "sg:website":"www.riveredgeresorthotel.com",
    "wof:name":"Riveredge Resort Hotel",
    "wof:placetype":"venue"
},
  "geometry": {"coordinates":[-75.914939,44.338593],"type":"Point"}
}