{
  "type": "Feature",
  "properties": {
    "iso:country":"US",
    "sg:address":"155 Cambridge Dr E",
    "sg:city":"Copiague",
    "sg:classifiers":[
        {
            "category":"Organizations",
            "subcategory":"Membership Organization",
            "type":"Services"
        }
    ],
    "sg:phone":"+1   ",
    "sg:postcode":"11726",
    "sg:province":"NY",
    "wof:name":"U C P Council",
    "wof:placetype":"venue"
},
  "geometry": {"coordinates":[-73.393199,40.680101],"type":"Point"}
}