{
  "type": "Feature",
  "properties": {
    "iso:country":"US",
    "sg:address":"51 Andrew St",
    "sg:city":"Manhasset",
    "sg:classifiers":[
        {
            "category":"Shopping",
            "subcategory":"Computers & Home Electronics",
            "type":"Retail Goods"
        }
    ],
    "sg:phone":"+1 516 365 1800",
    "sg:postcode":"11030",
    "sg:province":"NY",
    "sg:tags":[
        "software"
    ],
    "wof:name":"Bretic Enterprises Inc",
    "wof:placetype":"venue"
},
  "geometry": {"coordinates":[-73.69711,40.795702],"type":"Point"}
}