{
  "type": "Feature",
  "properties": {
    "iso:country":"US",
    "sg:address":"94 E Burnside Ave",
    "sg:city":"Bronx",
    "sg:classifiers":[
        {
            "category":"Banks & Credit Unions",
            "subcategory":"Bank",
            "type":"Services"
        }
    ],
    "sg:phone":"+1 718 627 3999",
    "sg:postcode":"10453",
    "sg:province":"NY",
    "sg:website":"www.citibank.com",
    "wof:name":"Citibank N A",
    "wof:placetype":"venue"
},
  "geometry": {"coordinates":[-73.90571300000001,40.853173],"type":"Point"}
}