{
  "type": "Feature",
  "properties": {
    "iso:country":"US",
    "sg:address":"421 Oakdale St",
    "sg:city":"Staten Island",
    "sg:classifiers":[
        {
            "category":"Restaurant",
            "type":"Food & Drink"
        }
    ],
    "sg:phone":"+1   ",
    "sg:postcode":"10312",
    "sg:province":"NY",
    "sg:tags":[
        "eating"
    ],
    "wof:name":"Ciao Bambini Italian Language",
    "wof:placetype":"venue"
},
  "geometry": {"coordinates":[-74.16473000000001,40.540681],"type":"Point"}
}