{
  "type": "Feature",
  "properties": {
    "iso:country":"US",
    "sg:address":"210 Greenpoint Ave",
    "sg:city":"Brooklyn",
    "sg:classifiers":[
        {
            "category":"Autos & Motor Vehicles",
            "subcategory":"Fuel & Gas Station",
            "type":"Retail Goods"
        }
    ],
    "sg:postcode":"11222",
    "sg:province":"NY",
    "sg:tags":[
        "gasoline"
    ],
    "wof:name":"Hess",
    "wof:placetype":"venue"
},
  "geometry": {"coordinates":[-73.951719,40.730164],"type":"Point"}
}