{
  "type": "Feature",
  "properties": {
    "addr:full":"10 Center Ave Larchmont NY 10538",
    "addr:housenumber":"10",
    "addr:postcode":"10538",
    "addr:street":"Center Ave",
    "iso:country":"US",
    "sg:address":"10 Center Ave",
    "sg:city":"Larchmont",
    "sg:classifiers":[
        {
            "category":"Health Services",
            "subcategory":"Doctor",
            "type":"Services"
        }
    ],
    "sg:phone":"+1 914 833 3098",
    "sg:postcode":"10538",
    "sg:province":"NY",
    "sg:tags":[
        "medical"
    ],
    "wof:name":"Cyril J Kaplan Dr",
    "wof:placetype":"venue"
},
  "geometry": {"coordinates":[-73.75989300000001,40.929869],"type":"Point"}
}