{
  "type": "Feature",
  "properties": {
    "addr:full":"97 Stuffle St Cropseyville NY 12052",
    "addr:housenumber":"97",
    "addr:postcode":"12052",
    "addr:street":"Stuffle St",
    "iso:country":"US",
    "sg:address":"97 Stuffle St",
    "sg:city":"Cropseyville",
    "sg:classifiers":[
        {
            "category":"Banks & Credit Unions",
            "subcategory":"Financial Services",
            "type":"Services"
        }
    ],
    "sg:phone":"+1 518 279 3905",
    "sg:postcode":"12052",
    "sg:province":"NY",
    "sg:tags":[
        "company",
        "holding"
    ],
    "wof:name":"Synergy Holding Corp",
    "wof:placetype":"venue"
},
  "geometry": {"coordinates":[-73.514472,42.770418],"type":"Point"}
}