{
  "type": "Feature",
  "properties": {
    "addr:full":"223 S Plank Rd Newburgh NY 12550",
    "addr:housenumber":"223",
    "addr:postcode":"12550",
    "addr:street":"S Plank Rd",
    "iso:country":"US",
    "sg:address":"223 S Plank Rd",
    "sg:city":"Newburgh",
    "sg:classifiers":[
        {
            "category":"Building & Trades",
            "subcategory":"Construction",
            "type":"Services"
        }
    ],
    "sg:phone":"+1 845 566 3000",
    "sg:postcode":"12550",
    "sg:province":"NY",
    "sg:tags":[
        "contractor"
    ],
    "wof:name":"A N Rich Inc",
    "wof:placetype":"venue"
},
  "geometry": {"coordinates":[-74.072841,41.528984],"type":"Point"}
}