{
  "type": "Feature",
  "properties": {
    "iso:country":"US",
    "sg:address":"4 Raymond Ave",
    "sg:city":"Cortland",
    "sg:classifiers":[
        {
            "category":"Professional",
            "subcategory":"Management & Consulting",
            "type":"Services"
        }
    ],
    "sg:phone":"+1 607 261 2660",
    "sg:postcode":"13045",
    "sg:province":"NY",
    "wof:name":"Storey J LLC",
    "wof:placetype":"venue"
},
  "geometry": {"coordinates":[-76.192277,42.587676],"type":"Point"}
}