{
  "type": "Feature",
  "properties": {
    "iso:country":"US",
    "sg:address":"557 W Kerley Corners Rd",
    "sg:city":"Tivoli",
    "sg:classifiers":[
        {
            "category":"Education",
            "subcategory":"Preschool",
            "type":"Public Place"
        },
        {
            "category":"Education",
            "subcategory":"School",
            "type":"Public Place"
        }
    ],
    "sg:phone":"+1 845 758 3434",
    "sg:postcode":"12583",
    "sg:province":"NY",
    "sg:tags":[
        "elementary"
    ],
    "wof:name":"MONTESSORI AT THE OLD SCHOOL HOUSE",
    "wof:placetype":"venue"
},
  "geometry": {"coordinates":[-73.851617,42.202936],"type":"Point"}
}