{
  "type": "Feature",
  "properties": {
    "addr:full":"95 Laurel Hill Rd Northport NY 11768",
    "addr:housenumber":"95",
    "addr:postcode":"11768",
    "addr:street":"Laurel Hill Rd",
    "iso:country":"US",
    "sg:address":"95 Laurel Hill Rd",
    "sg:city":"Northport",
    "sg:classifiers":[
        {
            "category":"Wholesale",
            "subcategory":"Computers",
            "type":"Manufacturing & Wholesale Goods"
        }
    ],
    "sg:phone":"+1 631 261 0103",
    "sg:postcode":"11768",
    "sg:province":"NY",
    "wof:name":"Krupski John P Assoc Inc",
    "wof:placetype":"venue"
},
  "geometry": {"coordinates":[-73.348204,40.88034],"type":"Point"}
}