{
  "type": "Feature",
  "properties": {
    "addr:full":"24 Nugent St Southampton NY 11968",
    "addr:housenumber":"24",
    "addr:postcode":"11968",
    "addr:street":"Nugent St",
    "iso:country":"US",
    "sg:address":"24 Nugent St",
    "sg:city":"Southampton",
    "sg:classifiers":[
        {
            "category":"Shopping",
            "subcategory":"Gifts & Souvenirs",
            "type":"Retail Goods"
        }
    ],
    "sg:phone":"+1 631 283 0474",
    "sg:postcode":"11968",
    "sg:province":"NY",
    "sg:tags":[
        "novelty"
    ],
    "wof:name":"Smyzer's Novelty Shop",
    "wof:placetype":"venue"
},
  "geometry": {"coordinates":[-72.39012700000001,40.886798],"type":"Point"}
}