{
  "type": "Feature",
  "properties": {
    "iso:country":"US",
    "sg:address":"10 E 53 St",
    "sg:city":"New York",
    "sg:classifiers":[
        {
            "category":"Shopping",
            "subcategory":"Books",
            "type":"Retail Goods"
        }
    ],
    "sg:phone":"+1 212 207 7057",
    "sg:postcode":"10022",
    "sg:province":"NY",
    "sg:tags":[
        "dealer"
    ],
    "wof:name":"Basic Books Inc",
    "wof:placetype":"venue"
},
  "geometry": {"coordinates":[-73.97470199999999,40.759921],"type":"Point"}
}