{
  "type": "Feature",
  "properties": {
    "addr:full":"5610 Broadway Bronx NY 10463",
    "addr:housenumber":"5610",
    "addr:postcode":"10463",
    "addr:street":"Broadway",
    "iso:country":"US",
    "sg:address":"5610 Broadway",
    "sg:city":"Bronx",
    "sg:classifiers":[
        {
            "category":"Banks & Credit Unions",
            "subcategory":"Investment Brokerage",
            "type":"Services"
        }
    ],
    "sg:phone":"+1 718 796 3343",
    "sg:postcode":"10463",
    "sg:province":"NY",
    "sg:tags":[
        "advisory",
        "financial"
    ],
    "wof:name":"Leopoldo Polanco",
    "wof:placetype":"venue"
},
  "geometry": {"coordinates":[-73.90521699999999,40.878313],"type":"Point"}
}