{
  "type": "Feature",
  "properties": {
    "iso:country":"US",
    "sg:address":"48 Van Wyck Dr",
    "sg:city":"Poughkeepsie",
    "sg:classifiers":[
        {
            "category":"Building & Trades",
            "subcategory":"Construction",
            "type":"Services"
        }
    ],
    "sg:phone":"+1 845 473 2750",
    "sg:postcode":"12601",
    "sg:province":"NY",
    "sg:tags":[
        "contractor",
        "painting",
        "hanging"
    ],
    "wof:name":"Charter Arthur",
    "wof:placetype":"venue"
},
  "geometry": {"coordinates":[-73.90795199999999,41.728059],"type":"Point"}
}