{
  "type": "Feature",
  "properties": {
    "addr:full":"266 Bedford Park Blvd Bronx NY 10458",
    "addr:housenumber":"266",
    "addr:postcode":"10458",
    "addr:street":"Bedford Park Blvd",
    "iso:country":"US",
    "sg:address":"266 Bedford Park Blvd",
    "sg:city":"Bronx",
    "sg:classifiers":[
        {
            "category":"Real Estate",
            "subcategory":"Real Estate Agent",
            "type":"Services"
        }
    ],
    "sg:phone":"+1 914 273 5695",
    "sg:postcode":"10458",
    "sg:province":"NY",
    "sg:tags":[
        "management"
    ],
    "wof:name":"PMV Realty",
    "wof:placetype":"venue"
},
  "geometry": {"coordinates":[-73.88565800000001,40.870228],"type":"Point"}
}