{
  "type": "Feature",
  "properties": {
    "addr:full":"33 34th St Ste 6 Brooklyn NY 11232",
    "addr:housenumber":"33",
    "addr:postcode":"11232",
    "addr:street":"34Th St Ste 6",
    "iso:country":"US",
    "sg:address":"33 34th St Ste 6",
    "sg:city":"Brooklyn",
    "sg:classifiers":[
        {
            "category":"Shopping",
            "subcategory":"Clothing, Apparel, & Fashions",
            "type":"Retail Goods"
        },
        {
            "category":"Manufacturing",
            "subcategory":"Apparel",
            "type":"Manufacturing & Wholesale Goods"
        }
    ],
    "sg:phone":"+1 718 832 2688",
    "sg:postcode":"11232",
    "sg:province":"NY",
    "sg:tags":[
        "apparel-wholesale",
        "manufacturer",
        "clothing-men's-wholesale",
        "women's"
    ],
    "wof:name":"Tri Factor Inc",
    "wof:placetype":"venue"
},
  "geometry": {"coordinates":[-74.007009,40.657681],"type":"Point"}
}