{
  "type": "Feature",
  "properties": {
    "addr:full":"53 Riverside Dr Saranac Lake NY 12983",
    "addr:housenumber":"53",
    "addr:postcode":"12983",
    "addr:street":"Riverside Dr",
    "iso:country":"US",
    "sg:address":"53 Riverside Dr",
    "sg:city":"Saranac Lake",
    "sg:classifiers":[
        {
            "category":"Banks & Credit Unions",
            "subcategory":"Investment Brokerage",
            "type":"Services"
        }
    ],
    "sg:phone":"+1 518 891 3290",
    "sg:postcode":"12983",
    "sg:province":"NY",
    "sg:tags":[
        "consultant",
        "planning",
        "financial"
    ],
    "wof:name":"Jef Financial Planning LLC",
    "wof:placetype":"venue"
},
  "geometry": {"coordinates":[-74.128028,44.321499],"type":"Point"}
}