{
  "type": "Feature",
  "properties": {
    "addr:full":"218 W 147th St New York NY 10039",
    "addr:housenumber":"218",
    "addr:postcode":"10039",
    "addr:street":"W 147Th St",
    "iso:country":"US",
    "sg:address":"218 W 147th St",
    "sg:city":"New York",
    "sg:classifiers":[
        {
            "category":"Social Services",
            "subcategory":"Child Care",
            "type":"Services"
        }
    ],
    "sg:phone":"+1 212 368 4710",
    "sg:postcode":"10039",
    "sg:province":"NY",
    "sg:tags":[
        "kindergarten",
        "academic",
        "school"
    ],
    "wof:name":"Chama Child Development Ctr",
    "wof:placetype":"venue"
},
  "geometry": {"coordinates":[-73.940612,40.823846],"type":"Point"}
}