{
  "type": "Feature",
  "properties": {
    "iso:country":"US",
    "sg:address":"1060 Northern Blvd",
    "sg:city":"Roslyn",
    "sg:classifiers":[
        {
            "category":"Shopping",
            "subcategory":"Used Merchandise",
            "type":"Retail Goods"
        }
    ],
    "sg:phone":"+1   ",
    "sg:postcode":"11576",
    "sg:province":"NY",
    "sg:tags":[
        "furniture"
    ],
    "wof:name":"Country-Tique Inc",
    "wof:placetype":"venue"
},
  "geometry": {"coordinates":[-73.66902399999999,40.797156],"type":"Point"}
}