{
  "type": "Feature",
  "properties": {
    "iso:country":"US",
    "sg:address":"107 Fairview Ave",
    "sg:city":"Syracuse",
    "sg:classifiers":[
        {
            "category":"Building & Trades",
            "subcategory":"Construction",
            "type":"Services"
        }
    ],
    "sg:phone":"+1 315 474 0417",
    "sg:postcode":"13203",
    "sg:province":"NY",
    "sg:tags":[
        "commercial",
        "contractor",
        "exterior",
        "interior",
        "painting",
        "painter"
    ],
    "wof:name":"Triple P Painting Inc",
    "wof:placetype":"venue"
},
  "geometry": {"coordinates":[-76.12698,43.055318],"type":"Point"}
}