{
  "type": "Feature",
  "properties": {
    "addr:full":"150 Van Ostrand Rd Groton NY 13073",
    "addr:housenumber":"150",
    "addr:postcode":"13073",
    "addr:street":"Van Ostrand Rd",
    "iso:country":"US",
    "sg:address":"150 Van Ostrand Rd",
    "sg:city":"Groton",
    "sg:classifiers":[
        {
            "category":"Farming",
            "subcategory":"Farm",
            "type":"Manufacturing & Wholesale Goods"
        }
    ],
    "sg:phone":"+1 607 533 7145",
    "sg:postcode":"13073",
    "sg:province":"NY",
    "sg:tags":[
        "crop",
        "general"
    ],
    "wof:name":"Bucks Farm",
    "wof:placetype":"venue"
},
  "geometry": {"coordinates":[-76.468403,42.546141],"type":"Point"}
}