{
  "type": "Feature",
  "properties": {
    "iso:country":"US",
    "sg:address":"60 Cuttermill Rd",
    "sg:city":"Great Neck",
    "sg:classifiers":[
        {
            "category":"Professional",
            "subcategory":"Computer Services",
            "type":"Services"
        }
    ],
    "sg:phone":"+1 516 303 1100",
    "sg:postcode":"11021",
    "sg:province":"NY",
    "sg:website":"www.bottomline.com",
    "wof:name":"Bottomline Technologies",
    "wof:placetype":"venue"
},
  "geometry": {"coordinates":[-73.730885,40.786103],"type":"Point"}
}