{
  "type": "Feature",
  "properties": {
    "iso:country":"US",
    "sg:address":"75 Brook St",
    "sg:city":"Scarsdale",
    "sg:classifiers":[
        {
            "category":"Retail",
            "subcategory":"Auto Rental",
            "type":"Services"
        }
    ],
    "sg:phone":"+1 914 472 8204",
    "sg:postcode":"10583",
    "sg:province":"NY",
    "sg:tags":[
        "renting",
        "automobile"
    ],
    "wof:name":"Rent A Car Ireland",
    "wof:placetype":"venue"
},
  "geometry": {"coordinates":[-73.80828200000001,40.979343],"type":"Point"}
}