{
  "type": "Feature",
  "properties": {
    "iso:country":"US",
    "sg:address":"272 Main St",
    "sg:city":"White Plains",
    "sg:classifiers":[
        {
            "category":"Retail",
            "subcategory":"Laundry & Dry Cleaning",
            "type":"Services"
        }
    ],
    "sg:phone":"+1 914 949 6161",
    "sg:postcode":"10601",
    "sg:province":"NY",
    "wof:name":"Nu Trend Cleaner",
    "wof:placetype":"venue"
},
  "geometry": {"coordinates":[-73.763464,41.36441],"type":"Point"}
}