{
  "type": "Feature",
  "properties": {
    "addr:full":"40 Main St Oneonta NY 13820",
    "addr:housenumber":"40",
    "addr:postcode":"13820",
    "addr:street":"Main St",
    "iso:country":"US",
    "sg:address":"40 Main St",
    "sg:city":"Oneonta",
    "sg:classifiers":[
        {
            "category":"Wholesale",
            "subcategory":"Home Furnishings",
            "type":"Manufacturing & Wholesale Goods"
        }
    ],
    "sg:phone":"+1 607 432 6588",
    "sg:postcode":"13820",
    "sg:province":"NY",
    "wof:name":"Kemper Pottery",
    "wof:placetype":"venue"
},
  "geometry": {"coordinates":[-75.06382499999999,42.448447],"type":"Point"}
}