{
  "type": "Feature",
  "properties": {
    "iso:country":"US",
    "sg:address":"30 Church St",
    "sg:city":"Chatham",
    "sg:classifiers":[
        {
            "category":"Manufacturing",
            "subcategory":"Rubber & Plastics",
            "type":"Manufacturing & Wholesale Goods"
        }
    ],
    "sg:phone":"+1   ",
    "sg:postcode":"12037",
    "sg:province":"NY",
    "sg:tags":[
        "product",
        "mfg"
    ],
    "wof:name":"Chatham Plastic Ventures Inc",
    "wof:placetype":"venue"
},
  "geometry": {"coordinates":[-73.60245999999999,42.356905],"type":"Point"}
}