{
  "type": "Feature",
  "properties": {
    "iso:country":"US",
    "sg:address":"133 Vernon Ave",
    "sg:city":"Mt Vernon",
    "sg:classifiers":[
        {
            "category":"Bars & Pubs",
            "type":"Food & Drink"
        }
    ],
    "sg:phone":"+1 914 663 6877",
    "sg:postcode":"10553",
    "sg:province":"NY",
    "wof:name":"Shamballa",
    "wof:placetype":"venue"
},
  "geometry": {"coordinates":[-73.815522,40.906526],"type":"Point"}
}