{
  "type": "Feature",
  "properties": {
    "addr:full":"1 E 27 St New York NY 10016",
    "addr:housenumber":"1;27",
    "addr:postcode":"10016",
    "addr:street":"E",
    "iso:country":"US",
    "sg:address":"1 E 27 St",
    "sg:city":"New York",
    "sg:classifiers":[
        {
            "category":"Health Services",
            "subcategory":"Doctor",
            "type":"Services"
        }
    ],
    "sg:phone":"+1 212 562 5524",
    "sg:postcode":"10016",
    "sg:province":"NY",
    "sg:tags":[
        "physician",
        "surgeon"
    ],
    "wof:name":"Bellevue Pediatrics",
    "wof:placetype":"venue"
},
  "geometry": {"coordinates":[-73.986147,40.743389],"type":"Point"}
}