{
  "type": "Feature",
  "properties": {
    "addr:full":"511 Amsterdam Ave New York NY 10024",
    "addr:housenumber":"511",
    "addr:postcode":"10024",
    "addr:street":"Amsterdam Ave",
    "iso:country":"US",
    "sg:address":"511 Amsterdam Ave",
    "sg:city":"New York",
    "sg:classifiers":[
        {
            "category":"Restaurant",
            "type":"Food & Drink"
        }
    ],
    "sg:menulink":"http://www.allmenus.com/ny/new-york/251721-the-neptune-room/menu/",
    "sg:phone":"+1 212 496 4100",
    "sg:postcode":"10024",
    "sg:province":"NY",
    "sg:tags":[
        "seafood",
        "mediterranean",
        "american"
    ],
    "wof:name":"The Neptune Room",
    "wof:placetype":"venue"
},
  "geometry": {"coordinates":[-73.975381,40.786603],"type":"Point"}
}