{
  "type": "Feature",
  "properties": {
    "iso:country":"US",
    "sg:address":"4 Lupi Ct",
    "sg:city":"Mahopac",
    "sg:classifiers":[
        {
            "category":"Wholesale",
            "subcategory":"Machinery & Supplies",
            "type":"Manufacturing & Wholesale Goods"
        }
    ],
    "sg:phone":"+1 845 621 4111",
    "sg:postcode":"10541",
    "sg:province":"NY",
    "sg:tags":[
        "slicing",
        "machine"
    ],
    "wof:name":"Ambrosi Cutlery LTD",
    "wof:placetype":"venue"
},
  "geometry": {"coordinates":[-73.748289,41.355601],"type":"Point"}
}