{
  "type": "Feature",
  "properties": {
    "iso:country":"US",
    "sg:address":"388 Grand Concourse",
    "sg:city":"Bronx",
    "sg:classifiers":[
        {
            "category":"Real Estate",
            "subcategory":"Real Estate Agent",
            "type":"Services"
        }
    ],
    "sg:phone":"+1 718 665 1023",
    "sg:postcode":"10451",
    "sg:province":"NY",
    "wof:name":"388-90 Grand Concourse Tenant",
    "wof:placetype":"venue"
},
  "geometry": {"coordinates":[-73.928181,40.816395],"type":"Point"}
}