{
  "type": "Feature",
  "properties": {
    "addr:full":"2422 State Hwy 12B Hamilton NY 13346",
    "addr:housenumber":"2422",
    "addr:postcode":"13346",
    "addr:street":"State Hwy 12B",
    "iso:country":"US",
    "sg:address":"2422 State Hwy 12B",
    "sg:city":"Hamilton",
    "sg:classifiers":[
        {
            "category":"Building & Trades",
            "subcategory":"Construction",
            "type":"Services"
        }
    ],
    "sg:phone":"+1 315 824 2128",
    "sg:postcode":"13346",
    "sg:province":"NY",
    "sg:tags":[
        "specializing",
        "co",
        "metal",
        "contractor",
        "framing",
        "drywall"
    ],
    "wof:name":"Ron Wright Inc",
    "wof:placetype":"venue"
},
  "geometry": {"coordinates":[-75.551565,42.836466],"type":"Point"}
}