{
  "type": "Feature",
  "properties": {
    "addr:full":"3325 Chili Ave Rochester NY 14624",
    "addr:housenumber":"3325",
    "addr:postcode":"14624",
    "addr:street":"Chili Ave",
    "iso:country":"US",
    "sg:address":"3325 Chili Ave",
    "sg:city":"Rochester",
    "sg:classifiers":[
        {
            "category":"Utilities",
            "subcategory":"Fuel Oil & Lpg",
            "type":"Services"
        }
    ],
    "sg:phone":"+1   ",
    "sg:postcode":"14624",
    "sg:province":"NY",
    "sg:tags":[
        "liquefied",
        "gas",
        "petroleum"
    ],
    "wof:name":"Suburban Propane",
    "wof:placetype":"venue"
},
  "geometry": {"coordinates":[-77.756925,43.102026],"type":"Point"}
}