{
  "type": "Feature",
  "properties": {
    "iso:country":"US",
    "sg:address":"175 W 73 St",
    "sg:city":"New York",
    "sg:classifiers":[
        {
            "category":"Health Services",
            "subcategory":"Podiatrist",
            "type":"Services"
        }
    ],
    "sg:phone":"+1 212 787 1286",
    "sg:postcode":"10023",
    "sg:province":"NY",
    "wof:name":"Joseph Eichen DPM",
    "wof:placetype":"venue"
},
  "geometry": {"coordinates":[-73.979474,40.778454],"type":"Point"}
}