{
  "type": "Feature",
  "properties": {
    "iso:country":"US",
    "sg:address":"75 Urban Ave",
    "sg:city":"Westbury",
    "sg:classifiers":[
        {
            "category":"Retail",
            "subcategory":"Auto Repair",
            "type":"Services"
        }
    ],
    "sg:phone":"+1 516 334 6765",
    "sg:postcode":"11590",
    "sg:province":"NY",
    "sg:tags":[
        "body",
        "shop"
    ],
    "wof:name":"Bodyline Collision Inc",
    "wof:placetype":"venue"
},
  "geometry": {"coordinates":[-73.563103,40.755798],"type":"Point"}
}