{
  "type": "Feature",
  "properties": {
    "iso:country":"US",
    "sg:address":"29 Liberty St",
    "sg:city":"Batavia",
    "sg:classifiers":[
        {
            "category":"Social Services",
            "type":"Services"
        }
    ],
    "sg:phone":"+1 585 344 0134",
    "sg:postcode":"14020",
    "sg:province":"NY",
    "sg:tags":[
        "organization",
        "welfare"
    ],
    "wof:name":"Hillside Children's Ctr",
    "wof:placetype":"venue"
},
  "geometry": {"coordinates":[-78.179874,42.99459],"type":"Point"}
}