{
  "type": "Feature",
  "properties": {
    "iso:country":"US",
    "sg:address":"15 Stonehenge Rd",
    "sg:city":"Great Neck",
    "sg:classifiers":[
        {
            "category":"Professional",
            "subcategory":"Lawyer & Legal Services",
            "type":"Services"
        }
    ],
    "sg:phone":"+1 516 487 2495",
    "sg:postcode":"11023",
    "sg:province":"NY",
    "sg:tags":[
        "attorney"
    ],
    "wof:name":"Harvey A Eysman",
    "wof:placetype":"venue"
},
  "geometry": {"coordinates":[-73.740707,40.797762],"type":"Point"}
}