{
  "type": "Feature",
  "properties": {
    "addr:full":"1 Hunting Ridge Rd Chappaqua NY 10514",
    "addr:housenumber":"1",
    "addr:postcode":"10514",
    "addr:street":"Hunting Ridge Rd",
    "iso:country":"US",
    "sg:address":"1 Hunting Ridge Rd",
    "sg:city":"Chappaqua",
    "sg:classifiers":[
        {
            "category":"Retail",
            "subcategory":"Laundry & Dry Cleaning",
            "type":"Services"
        }
    ],
    "sg:phone":"+1   ",
    "sg:postcode":"10514",
    "sg:province":"NY",
    "wof:name":"Community Chem Dry",
    "wof:placetype":"venue"
},
  "geometry": {"coordinates":[-73.765491,41.18013],"type":"Point"}
}