{
  "type": "Feature",
  "properties": {
    "addr:full":"480 Bainbridge St Brooklyn NY 11233",
    "addr:housenumber":"480",
    "addr:postcode":"11233",
    "addr:street":"Bainbridge St",
    "iso:country":"US",
    "sg:address":"480 Bainbridge St",
    "sg:city":"Brooklyn",
    "sg:classifiers":[
        {
            "category":"Organizations",
            "subcategory":"Religious Organization",
            "type":"Services"
        }
    ],
    "sg:phone":"+1 718 452 0949",
    "sg:postcode":"11233",
    "sg:province":"NY",
    "sg:tags":[
        "baptist",
        "church"
    ],
    "wof:name":"St Johns Baptist Church Inc",
    "wof:placetype":"venue"
},
  "geometry": {"coordinates":[-73.917299,40.682465],"type":"Point"}
}