{
  "type": "Feature",
  "properties": {
    "addr:full":"5 W 19th St New York NY 10011",
    "addr:housenumber":"5",
    "addr:postcode":"10011",
    "addr:street":"W 19Th St",
    "iso:country":"US",
    "sg:address":"5 W 19th St",
    "sg:city":"New York",
    "sg:classifiers":[
        {
            "category":"Food & Beverages",
            "subcategory":"Liquor & Beverages",
            "type":"Retail Goods"
        }
    ],
    "sg:phone":"+1 212 929 2323",
    "sg:postcode":"10011",
    "sg:province":"NY",
    "sg:tags":[
        "beer",
        "spirit",
        "wine"
    ],
    "sg:website":"www.bottlerocketwine.com",
    "wof:name":"Bottlerocket Wine & Spirit",
    "wof:placetype":"venue"
},
  "geometry": {"coordinates":[-73.991632,40.739297],"type":"Point"}
}