{
  "type": "Feature",
  "properties": {
    "iso:country":"US",
    "sg:address":"5292 Parkside Dr",
    "sg:city":"Canandaigua",
    "sg:classifiers":[
        {
            "category":"Personal",
            "type":"Services"
        }
    ],
    "sg:phone":"+1 585 398 3042",
    "sg:postcode":"14424",
    "sg:province":"NY",
    "sg:tags":[
        "therapist",
        "massage"
    ],
    "wof:name":"Parkside Greens",
    "wof:placetype":"venue"
},
  "geometry": {"coordinates":[-77.293094,42.912775],"type":"Point"}
}