{
  "type": "Feature",
  "properties": {
    "addr:full":"5586 Broadway Bronx NY 10463",
    "addr:housenumber":"5586",
    "addr:postcode":"10463",
    "addr:street":"Broadway",
    "iso:country":"US",
    "sg:address":"5586 Broadway",
    "sg:city":"Bronx",
    "sg:classifiers":[
        {
            "category":"Personal",
            "subcategory":"Beauty Salon",
            "type":"Services"
        }
    ],
    "sg:phone":"+1 718 601 8378",
    "sg:postcode":"10463",
    "sg:province":"NY",
    "sg:tags":[
        "shop"
    ],
    "wof:name":"Mirrors & Images Of Riverdale",
    "wof:placetype":"venue"
},
  "geometry": {"coordinates":[-73.904787,40.878924],"type":"Point"}
}