{
  "type": "Feature",
  "properties": {
    "addr:full":"1023 Route 52 Carmel NY 10512",
    "addr:housenumber":"1023",
    "addr:postcode":"10512",
    "addr:street":"Route 52",
    "iso:country":"US",
    "sg:address":"1023 Route 52",
    "sg:city":"Carmel",
    "sg:classifiers":[
        {
            "category":"Professional",
            "type":"Services"
        }
    ],
    "sg:phone":"+1 845 225 9853",
    "sg:postcode":"10512",
    "sg:province":"NY",
    "sg:tags":[
        "caterer"
    ],
    "wof:name":"Mr Gug's Countryside Inc",
    "wof:placetype":"venue"
},
  "geometry": {"coordinates":[-73.68101900000001,41.494176],"type":"Point"}
}