{
  "type": "Feature",
  "properties": {
    "addr:full":"37 State St Otisville NY 10963",
    "addr:housenumber":"37",
    "addr:postcode":"10963",
    "addr:street":"State St",
    "iso:country":"US",
    "sg:address":"37 State St",
    "sg:city":"Otisville",
    "sg:classifiers":[
        {
            "category":"Real Estate",
            "subcategory":"Real Estate Services",
            "type":"Services"
        },
        {
            "category":"Building & Trades",
            "subcategory":"Cleaning & Sanitation",
            "type":"Services"
        }
    ],
    "sg:phone":"+1 845 741 1352",
    "sg:postcode":"10963",
    "sg:province":"NY",
    "sg:tags":[
        "maintenance",
        "cleaners-interior"
    ],
    "wof:name":"Hands On Property Mtc",
    "wof:placetype":"venue"
},
  "geometry": {"coordinates":[-74.53524,41.47551],"type":"Point"}
}