{
  "type": "Feature",
  "properties": {
    "iso:country":"US",
    "sg:address":"1631 Whiting Rd",
    "sg:city":"Memphis",
    "sg:classifiers":[
        {
            "category":"Building & Trades",
            "subcategory":"Landscaping Services",
            "type":"Services"
        }
    ],
    "sg:phone":"+1 315 689 1470",
    "sg:postcode":"13112",
    "sg:province":"NY",
    "sg:tags":[
        "landscape",
        "contractor"
    ],
    "sg:website":"www.groundeffectsny.com",
    "wof:name":"Ground Effects",
    "wof:placetype":"venue"
},
  "geometry": {"coordinates":[-76.392062,43.07513],"type":"Point"}
}