{
  "type": "Feature",
  "properties": {
    "addr:full":"800 E Gun Hill Rd Bronx NY 10467",
    "addr:housenumber":"800",
    "addr:postcode":"10467",
    "addr:street":"E Gun Hill Rd",
    "iso:country":"US",
    "sg:address":"800 E Gun Hill Rd",
    "sg:city":"Bronx",
    "sg:classifiers":[
        {
            "category":"Education",
            "subcategory":"School",
            "type":"Public Place"
        }
    ],
    "sg:phone":"+1 718 519 7700",
    "sg:postcode":"10467",
    "sg:province":"NY",
    "sg:tags":[
        "high"
    ],
    "wof:name":"Evander Childs High School",
    "wof:placetype":"venue"
},
  "geometry": {"coordinates":[-73.862129,40.875999],"type":"Point"}
}