{
  "type": "Feature",
  "properties": {
    "iso:country":"US",
    "sg:address":"140 Pine Aire Dr",
    "sg:city":"Bay Shore",
    "sg:classifiers":[
        {
            "category":"Food & Beverages",
            "subcategory":"Meat & Fish",
            "type":"Retail Goods"
        }
    ],
    "sg:phone":"+1   ",
    "sg:postcode":"11706",
    "sg:province":"NY",
    "wof:name":"Pine Air Fish Market",
    "wof:placetype":"venue"
},
  "geometry": {"coordinates":[-73.272598,40.773541],"type":"Point"}
}