{
  "type": "Feature",
  "properties": {
    "iso:country":"US",
    "sg:address":"800 Veterans Memorial Hwy",
    "sg:city":"Hauppauge",
    "sg:classifiers":[
        {
            "category":"Health Services",
            "subcategory":"Health Practitioner",
            "type":"Services"
        }
    ],
    "sg:phone":"+1 631 724 5464",
    "sg:postcode":"11788",
    "sg:province":"NY",
    "sg:tags":[
        "psychologist"
    ],
    "wof:name":"Susan Bogard PHD",
    "wof:placetype":"venue"
},
  "geometry": {"coordinates":[-73.19988600000001,40.819033],"type":"Point"}
}