{
  "type": "Feature",
  "properties": {
    "iso:country":"US",
    "sg:address":"2163 Jackson Pl",
    "sg:city":"North Bellmore",
    "sg:classifiers":[
        {
            "category":"Professional",
            "subcategory":"Management & Consulting",
            "type":"Services"
        }
    ],
    "sg:phone":"+1 516 679 8241",
    "sg:postcode":"11710",
    "sg:province":"NY",
    "sg:tags":[
        "magazine",
        "agent"
    ],
    "wof:name":"Subscription Service-America",
    "wof:placetype":"venue"
},
  "geometry": {"coordinates":[-73.547344,40.702625],"type":"Point"}
}