{
  "type": "Feature",
  "properties": {
    "addr:full":"224 Long Island Ave Holtsville NY 11742",
    "addr:housenumber":"224",
    "addr:postcode":"11742",
    "addr:street":"Long Island Ave",
    "iso:country":"US",
    "sg:address":"224 Long Island Ave",
    "sg:city":"Holtsville",
    "sg:phone":"+1 631 475 1412",
    "sg:postcode":"11742",
    "sg:province":"NY",
    "sg:tags":[
        "oil"
    ],
    "wof:name":"Colonial Fuel",
    "wof:placetype":"venue"
},
  "geometry": {"coordinates":[-73.037161,40.815552],"type":"Point"}
}