{
  "type": "Feature",
  "properties": {
    "addr:full":"35 Laviclin Ln Cuddebackville NY 12729",
    "addr:housenumber":"35",
    "addr:postcode":"12729",
    "addr:street":"Laviclin Ln",
    "iso:country":"US",
    "sg:address":"35 Laviclin Ln",
    "sg:city":"Cuddebackville",
    "sg:classifiers":[
        {
            "category":"Manufacturing",
            "subcategory":"Buildings",
            "type":"Manufacturing & Wholesale Goods"
        },
        {
            "category":"Building & Trades",
            "subcategory":"Construction",
            "type":"Services"
        }
    ],
    "sg:phone":"+1 845 754 7653",
    "sg:postcode":"12729",
    "sg:province":"NY",
    "sg:tags":[
        "home",
        "builder",
        "contractor"
    ],
    "wof:name":"Homes By Yara",
    "wof:placetype":"venue"
},
  "geometry": {"coordinates":[-74.593636,41.453709],"type":"Point"}
}