{
  "type": "Feature",
  "properties": {
    "iso:country":"US",
    "sg:address":"122 Mayfair Ave",
    "sg:city":"West Hempstead",
    "sg:classifiers":[
        {
            "category":"Professional",
            "subcategory":"Engineering",
            "type":"Services"
        }
    ],
    "sg:phone":"+1 516 564 7839",
    "sg:postcode":"11552",
    "sg:province":"NY",
    "wof:name":"Waldvogel Metallurigical Inc",
    "wof:placetype":"venue"
},
  "geometry": {"coordinates":[-73.64618299999999,40.70793],"type":"Point"}
}