{
  "type": "Feature",
  "properties": {
    "addr:full":"600 Manor Rd Staten Island NY 10314",
    "addr:housenumber":"600",
    "addr:postcode":"10314",
    "addr:street":"Manor Rd",
    "iso:country":"US",
    "sg:address":"600 Manor Rd",
    "sg:city":"Staten Island",
    "sg:classifiers":[
        {
            "category":"Wholesale",
            "subcategory":"Durable Goods & Equipment",
            "type":"Manufacturing & Wholesale Goods"
        }
    ],
    "sg:phone":"+1 718 494 0731",
    "sg:postcode":"10314",
    "sg:province":"NY",
    "sg:tags":[
        "used",
        "business"
    ],
    "wof:name":"Victorian Brothers",
    "wof:placetype":"venue"
},
  "geometry": {"coordinates":[-74.12236300000001,40.612575],"type":"Point"}
}