{
  "type": "Feature",
  "properties": {
    "addr:full":"100 Mohawk St Cohoes NY 12047",
    "addr:housenumber":"100",
    "addr:postcode":"12047",
    "addr:street":"Mohawk St",
    "iso:country":"US",
    "sg:address":"100 Mohawk St",
    "sg:city":"Cohoes",
    "sg:classifiers":[
        {
            "category":"Retail",
            "subcategory":"Auto Rental",
            "type":"Services"
        }
    ],
    "sg:phone":"+1 518 235 6399",
    "sg:postcode":"12047",
    "sg:province":"NY",
    "sg:tags":[
        "renting",
        "truck",
        "leasing"
    ],
    "wof:name":"U-Haul Co",
    "wof:placetype":"venue"
},
  "geometry": {"coordinates":[-73.700079,42.773786],"type":"Point"}
}