{
  "type": "Feature",
  "properties": {
    "addr:full":"1064 Broadway Brooklyn NY 11221",
    "addr:housenumber":"1064",
    "addr:postcode":"11221",
    "addr:street":"Broadway",
    "iso:country":"US",
    "sg:address":"1064 Broadway",
    "sg:city":"Brooklyn",
    "sg:classifiers":[
        {
            "category":"Food & Beverages",
            "subcategory":"Groceries & Convenience Stores",
            "type":"Retail Goods"
        }
    ],
    "sg:phone":"+1 718 919 1851",
    "sg:postcode":"11221",
    "sg:province":"NY",
    "wof:name":"La Famosa H G Grocery",
    "wof:placetype":"venue"
},
  "geometry": {"coordinates":[-73.93163,40.694808],"type":"Point"}
}