{
  "type": "Feature",
  "properties": {
    "iso:country":"US",
    "sg:address":"1130 E 9th St",
    "sg:city":"Brooklyn",
    "sg:classifiers":[
        {
            "category":"Organizations",
            "subcategory":"Religious Organization",
            "type":"Services"
        }
    ],
    "sg:phone":"+1   ",
    "sg:postcode":"11230",
    "sg:province":"NY",
    "wof:name":"Ark",
    "wof:placetype":"venue"
},
  "geometry": {"coordinates":[-73.966369,40.620493],"type":"Point"}
}