{
  "type": "Feature",
  "properties": {
    "iso:country":"US",
    "sg:address":"115 Rose Rd",
    "sg:city":"West Nyack",
    "sg:classifiers":[
        {
            "category":"Building & Trades",
            "subcategory":"Electrical",
            "type":"Services"
        }
    ],
    "sg:phone":"+1 845 627 6939",
    "sg:postcode":"10994",
    "sg:province":"NY",
    "sg:tags":[
        "electric",
        "contractor"
    ],
    "wof:name":"Phil Visa Contracting Co",
    "wof:placetype":"venue"
},
  "geometry": {"coordinates":[-73.993775,41.090471],"type":"Point"}
}