{
  "type": "Feature",
  "properties": {
    "iso:country":"US",
    "sg:address":"548 Cherry Ln",
    "sg:city":"Floral Park",
    "sg:classifiers":[
        {
            "category":"Retail",
            "subcategory":"Auto Repair",
            "type":"Services"
        }
    ],
    "sg:phone":"+1 516 437 7436",
    "sg:postcode":"11001",
    "sg:province":"NY",
    "sg:tags":[
        "body",
        "automobile",
        "painting"
    ],
    "wof:name":"AVI Parts Intl",
    "wof:placetype":"venue"
},
  "geometry": {"coordinates":[-73.699046,40.737299],"type":"Point"}
}