{
  "type": "Feature",
  "properties": {
    "iso:country":"US",
    "sg:address":"75 Main St Ste 1",
    "sg:city":"Northport",
    "sg:classifiers":[
        {
            "category":"Shopping",
            "subcategory":"Jewelry",
            "type":"Retail Goods"
        }
    ],
    "sg:phone":"+1 631 262 0880",
    "sg:postcode":"11768",
    "sg:province":"NY",
    "sg:tags":[
        "precious",
        "semi-precious",
        "stone"
    ],
    "wof:name":"Jewelry Collection",
    "wof:placetype":"venue"
},
  "geometry": {"coordinates":[-73.35066999999999,40.900305],"type":"Point"}
}