{
  "type": "Feature",
  "properties": {
    "addr:full":"1664 E 14th Street Brooklyn NY 11229",
    "addr:housenumber":"1664",
    "addr:postcode":"11229",
    "addr:street":"E 14Th Street",
    "iso:country":"US",
    "sg:address":"1664 E 14th Street",
    "sg:city":"Brooklyn",
    "sg:classifiers":[
        {
            "category":"Health Services",
            "subcategory":"Doctor",
            "type":"Services"
        }
    ],
    "sg:phone":"+1 718 787 0400",
    "sg:postcode":"11229",
    "sg:province":"NY",
    "wof:name":"Bandari Don MD",
    "wof:placetype":"venue"
},
  "geometry": {"coordinates":[-73.959311,40.608978],"type":"Point"}
}