{
  "type": "Feature",
  "properties": {
    "iso:country":"US",
    "sg:address":"1545 Ocean Ave",
    "sg:city":"Bohemia",
    "sg:classifiers":[
        {
            "category":"Manufacturing",
            "subcategory":"Buildings",
            "type":"Manufacturing & Wholesale Goods"
        }
    ],
    "sg:phone":"+1   ",
    "sg:postcode":"11716",
    "sg:province":"NY",
    "sg:tags":[
        "manufacture",
        "wall",
        "panel"
    ],
    "wof:name":"Eastern Exterior Wall Systems",
    "wof:placetype":"venue"
},
  "geometry": {"coordinates":[-73.12061199999999,40.783534],"type":"Point"}
}