{
  "type": "Feature",
  "properties": {
    "iso:country":"US",
    "sg:address":"600 Kreag Rd",
    "sg:city":"Pittsford",
    "sg:classifiers":[
        {
            "category":"Education",
            "subcategory":"Special Training",
            "type":"Public Place"
        }
    ],
    "sg:phone":"+1 585 234 2825",
    "sg:postcode":"14534",
    "sg:province":"NY",
    "sg:tags":[
        "instruction",
        "music"
    ],
    "wof:name":"Allegro School Of Music",
    "wof:placetype":"venue"
},
  "geometry": {"coordinates":[-77.472123,43.061826],"type":"Point"}
}