{
  "type": "Feature",
  "properties": {
    "addr:full":"7119 State Hwy 104 Oswego NY 13126",
    "addr:housenumber":"7119",
    "addr:postcode":"13126",
    "addr:street":"State Hwy 104",
    "iso:country":"US",
    "sg:address":"7119 State Hwy 104",
    "sg:city":"Oswego",
    "sg:classifiers":[
        {
            "category":"Organizations",
            "subcategory":"Religious Organization",
            "type":"Services"
        }
    ],
    "sg:phone":"+1 315 342 5417",
    "sg:postcode":"13126",
    "sg:province":"NY",
    "sg:tags":[
        "clergy"
    ],
    "wof:name":"James C Tschudy",
    "wof:placetype":"venue"
},
  "geometry": {"coordinates":[-76.55390199999999,43.440343],"type":"Point"}
}