{
  "type": "Feature",
  "properties": {
    "addr:full":"903 Co Rte 1 Oswego NY 13126",
    "addr:housenumber":"903",
    "addr:postcode":"13126",
    "addr:street":"Co Rte 1",
    "iso:country":"US",
    "sg:address":"903 Co Rte 1",
    "sg:city":"Oswego",
    "sg:classifiers":[
        {
            "category":"Autos & Motor Vehicles",
            "subcategory":"Auto Supplies",
            "type":"Retail Goods"
        }
    ],
    "sg:phone":"+1   ",
    "sg:postcode":"13126",
    "sg:province":"NY",
    "wof:name":"North Road Auto Parts",
    "wof:placetype":"venue"
},
  "geometry": {"coordinates":[-76.353307,43.496901],"type":"Point"}
}