{
  "type": "Feature",
  "properties": {
    "addr:full":"3374 Cody Rd Cazenovia NY 13035",
    "addr:housenumber":"3374",
    "addr:postcode":"13035",
    "addr:street":"Cody Rd",
    "iso:country":"US",
    "sg:address":"3374 Cody Rd",
    "sg:city":"Cazenovia",
    "sg:classifiers":[
        {
            "category":"Insurance",
            "subcategory":"Insurance Agent",
            "type":"Services"
        }
    ],
    "sg:phone":"+1 315 655 3683",
    "sg:postcode":"13035",
    "sg:province":"NY",
    "sg:tags":[
        "consultant"
    ],
    "wof:name":"Swaim Agency",
    "wof:placetype":"venue"
},
  "geometry": {"coordinates":[-75.78314399999999,42.951926],"type":"Point"}
}