{
  "type": "Feature",
  "properties": {
    "addr:full":"1973 84th St Brooklyn NY 11214",
    "addr:housenumber":"1973",
    "addr:postcode":"11214",
    "addr:street":"84Th St",
    "iso:country":"US",
    "sg:address":"1973 84th St",
    "sg:city":"Brooklyn",
    "sg:classifiers":[
        {
            "category":"Organizations",
            "subcategory":"Religious Organization",
            "type":"Services"
        }
    ],
    "sg:phone":"+1 718 372 7739",
    "sg:postcode":"11214",
    "sg:province":"NY",
    "sg:tags":[
        "clergy"
    ],
    "wof:name":"Emerich Feigelstock",
    "wof:placetype":"venue"
},
  "geometry": {"coordinates":[-73.998227,40.606802],"type":"Point"}
}