{
  "type": "Feature",
  "properties": {
    "addr:full":"1580 Jerome Ave Bronx NY 10452",
    "addr:housenumber":"1580",
    "addr:postcode":"10452",
    "addr:street":"Jerome Ave",
    "iso:country":"US",
    "sg:address":"1580 Jerome Ave",
    "sg:city":"Bronx",
    "sg:classifiers":[
        {
            "category":"Professional",
            "type":"Services"
        }
    ],
    "sg:phone":"+1   ",
    "sg:postcode":"10452",
    "sg:province":"NY",
    "wof:name":"New Galaxy Sign Inc",
    "wof:placetype":"venue"
},
  "geometry": {"coordinates":[-73.914411,40.8448],"type":"Point"}
}