{
  "type": "Feature",
  "properties": {
    "addr:full":"340 E 72nd Street New York NY 10021",
    "addr:housenumber":"340",
    "addr:postcode":"10021",
    "addr:street":"E 72Nd Street",
    "iso:country":"US",
    "sg:address":"340 E 72nd Street",
    "sg:city":"New York",
    "sg:classifiers":[
        {
            "category":"Health Services",
            "subcategory":"Dentist",
            "type":"Services"
        }
    ],
    "sg:phone":"+1 877 449 3708",
    "sg:postcode":"10021",
    "sg:province":"NY",
    "sg:website":"www.dentalartsny.net/?UBL=TRUE",
    "wof:name":"Racanelli Richard A DMD",
    "wof:placetype":"venue"
},
  "geometry": {"coordinates":[-73.957386,40.768392],"type":"Point"}
}