{
  "type": "Feature",
  "properties": {
    "addr:full":"4501 Church Avenue Brooklyn NY 11203",
    "addr:housenumber":"4501",
    "addr:postcode":"11203",
    "addr:street":"Church Avenue",
    "iso:country":"US",
    "sg:address":"4501 Church Avenue",
    "sg:city":"Brooklyn",
    "sg:classifiers":[
        {
            "category":"Personal",
            "subcategory":"Barber",
            "type":"Services"
        }
    ],
    "sg:phone":"+1 718 282 9634",
    "sg:postcode":"11203",
    "sg:province":"NY",
    "wof:name":"Stylz Barber Shop",
    "wof:placetype":"venue"
},
  "geometry": {"coordinates":[-73.935202,40.651511],"type":"Point"}
}