{
  "type": "Feature",
  "properties": {
    "addr:full":"2 Van Buren Blvd Altamont NY 12009",
    "addr:housenumber":"2",
    "addr:postcode":"12009",
    "addr:street":"Van Buren Blvd",
    "iso:country":"US",
    "sg:address":"2 Van Buren Blvd",
    "sg:city":"Altamont",
    "sg:classifiers":[
        {
            "category":"Freight",
            "type":"Transportation"
        }
    ],
    "sg:phone":"+1 518 861 5879",
    "sg:postcode":"12009",
    "sg:province":"NY",
    "sg:tags":[
        "delivery"
    ],
    "wof:name":"Fedex Home Delivery",
    "wof:placetype":"venue"
},
  "geometry": {"coordinates":[-73.95812599999999,42.701865],"type":"Point"}
}