{
  "type": "Feature",
  "properties": {
    "addr:full":"35 Glenn St Massena NY 13662",
    "addr:housenumber":"35",
    "addr:postcode":"13662",
    "addr:street":"Glenn St",
    "iso:country":"US",
    "sg:address":"35 Glenn St",
    "sg:city":"Massena",
    "sg:classifiers":[
        {
            "category":"Education",
            "subcategory":"School",
            "type":"Public Place"
        }
    ],
    "sg:phone":"+1 315 769 5895",
    "sg:postcode":"13662",
    "sg:province":"NY",
    "wof:name":"GED Preparation Boces",
    "wof:placetype":"venue"
},
  "geometry": {"coordinates":[-74.891385,44.930407],"type":"Point"}
}