{
  "type": "Feature",
  "properties": {
    "iso:country":"US",
    "sg:address":"11 New King St",
    "sg:city":"White Plains",
    "sg:classifiers":[
        {
            "category":"Wholesale",
            "subcategory":"Machinery & Supplies",
            "type":"Manufacturing & Wholesale Goods"
        }
    ],
    "sg:phone":"+1 914 681 3000",
    "sg:postcode":"10604",
    "sg:province":"NY",
    "sg:tags":[
        "equipment",
        "parts",
        "aerospace"
    ],
    "sg:website":"www.aerotechworld.com",
    "wof:name":"Aerotech World Trade Corp",
    "wof:placetype":"venue"
},
  "geometry": {"coordinates":[-73.714156,41.082552],"type":"Point"}
}