{
  "type": "Feature",
  "properties": {
    "addr:full":"419 Warburton Ave Hastings On Hdsn NY 10706",
    "addr:housenumber":"419",
    "addr:postcode":"10706",
    "addr:street":"Warburton Ave",
    "iso:country":"US",
    "sg:address":"419 Warburton Ave",
    "sg:city":"Hastings On Hdsn",
    "sg:classifiers":[
        {
            "category":"Wholesale",
            "subcategory":"Groceries",
            "type":"Manufacturing & Wholesale Goods"
        }
    ],
    "sg:phone":"+1 914 478 9642",
    "sg:postcode":"10706",
    "sg:province":"NY",
    "sg:tags":[
        "confectionery",
        "candy"
    ],
    "wof:name":"Westchester Foods",
    "wof:placetype":"venue"
},
  "geometry": {"coordinates":[-73.88329899999999,40.991223],"type":"Point"}
}