{
  "type": "Feature",
  "properties": {
    "iso:country":"US",
    "sg:address":"861 Sunrise Mall",
    "sg:city":"Massapequa",
    "sg:classifiers":[
        {
            "category":"Shopping",
            "subcategory":"Clothing, Apparel, & Fashions",
            "type":"Retail Goods"
        }
    ],
    "sg:phone":"+1 516 799 3323",
    "sg:postcode":"11758",
    "sg:province":"NY",
    "sg:tags":[
        "furnishing"
    ],
    "wof:name":"Just For Men",
    "wof:placetype":"venue"
},
  "geometry": {"coordinates":[-73.434168,40.685507],"type":"Point"}
}