{
  "type": "Feature",
  "properties": {
    "iso:country":"US",
    "sg:address":"989 Main St Ste 1",
    "sg:city":"Fishkill",
    "sg:classifiers":[
        {
            "category":"Professional",
            "subcategory":"Management & Consulting",
            "type":"Services"
        },
        {
            "category":"Banks & Credit Unions",
            "subcategory":"Investment Brokerage",
            "type":"Services"
        },
        {
            "category":"Insurance",
            "subcategory":"Hazard Insurance",
            "type":"Services"
        },
        {
            "category":"Banks & Credit Unions",
            "subcategory":"Financial Services",
            "type":"Services"
        }
    ],
    "sg:phone":"+1 845 896 6727",
    "sg:postcode":"12524",
    "sg:province":"NY",
    "sg:tags":[
        "financing",
        "business",
        "resume",
        "consultant",
        "commercial",
        "agent",
        "planning"
    ],
    "sg:website":"http://www.emerywebb.com",
    "wof:name":"Emery & Webb Inc",
    "wof:placetype":"venue"
},
  "geometry": {"coordinates":[-73.90677599999999,41.53207],"type":"Point"}
}