{
  "type": "Feature",
  "properties": {
    "iso:country":"US",
    "sg:address":"4477 W Fairmount Ave",
    "sg:city":"Lakewood",
    "sg:classifiers":[
        {
            "category":"Farming",
            "subcategory":"Nursery",
            "type":"Manufacturing & Wholesale Goods"
        }
    ],
    "sg:phone":"+1 716 763 8685",
    "sg:postcode":"14750",
    "sg:province":"NY",
    "sg:tags":[
        "ornamental"
    ],
    "wof:name":"Chautauqua Perennial Gardens",
    "wof:placetype":"venue"
},
  "geometry": {"coordinates":[-79.35271400000001,42.09913],"type":"Point"}
}