{
  "type": "Feature",
  "properties": {
    "addr:full":"356 New York Ave Huntington NY 11743",
    "addr:housenumber":"356",
    "addr:postcode":"11743",
    "addr:street":"New York Ave",
    "iso:country":"US",
    "sg:address":"356 New York Ave",
    "sg:city":"Huntington",
    "sg:classifiers":[
        {
            "category":"Retail",
            "subcategory":"Portrait Studio",
            "type":"Services"
        }
    ],
    "sg:phone":"+1 631 547 0243",
    "sg:postcode":"11743",
    "sg:province":"NY",
    "sg:tags":[
        "photography"
    ],
    "wof:name":"Bob Mitchell Photography",
    "wof:placetype":"venue"
},
  "geometry": {"coordinates":[-73.42598599999999,40.869208],"type":"Point"}
}