{
  "type": "Feature",
  "properties": {
    "iso:country":"US",
    "sg:address":"56 Miller Rd",
    "sg:city":"Stanfordville",
    "sg:classifiers":[
        {
            "category":"Farming",
            "subcategory":"Farm",
            "type":"Manufacturing & Wholesale Goods"
        }
    ],
    "sg:phone":"+1 845 868 2217",
    "sg:postcode":"12549",
    "sg:province":"NY",
    "wof:name":"Miller Pond Farm",
    "wof:placetype":"venue"
},
  "geometry": {"coordinates":[-74.289945,41.490929],"type":"Point"}
}