{
  "type": "Feature",
  "properties": {
    "addr:full":"112 W Islip Rd West Islip NY 11795",
    "addr:housenumber":"112",
    "addr:postcode":"11795",
    "addr:street":"W Islip Rd",
    "iso:country":"US",
    "sg:address":"112 W Islip Rd",
    "sg:city":"West Islip",
    "sg:classifiers":[
        {
            "category":"Organizations",
            "subcategory":"Community Association",
            "type":"Services"
        }
    ],
    "sg:phone":"+1 631 667 3952",
    "sg:postcode":"11795",
    "sg:province":"NY",
    "sg:tags":[
        "environmental",
        "org"
    ],
    "wof:name":"Wings Over LI Wildlife Rehab C",
    "wof:placetype":"venue"
},
  "geometry": {"coordinates":[-73.31643800000001,40.691232],"type":"Point"}
}