{
  "type": "Feature",
  "properties": {
    "iso:country":"US",
    "sg:address":"4500 Witmer Industrial Ests",
    "sg:city":"Niagara Falls",
    "sg:classifiers":[
        {
            "category":"Manufacturing",
            "subcategory":"Printing",
            "type":"Manufacturing & Wholesale Goods"
        }
    ],
    "sg:phone":"+1   ",
    "sg:postcode":"14305",
    "sg:province":"NY",
    "sg:tags":[
        "newsletter",
        "publishing"
    ],
    "wof:name":"Patient News Publishing Ltd",
    "wof:placetype":"venue"
},
  "geometry": {"coordinates":[-79.012106,43.126297],"type":"Point"}
}