{
  "type": "Feature",
  "properties": {
    "addr:full":"111 Broadway Lbby New York NY 10006",
    "addr:housenumber":"111",
    "addr:postcode":"10006",
    "addr:street":"Broadway",
    "iso:country":"US",
    "sg:address":"111 Broadway Lbby",
    "sg:city":"New York",
    "sg:classifiers":[
        {
            "category":"Professional",
            "subcategory":"Lawyer & Legal Services",
            "type":"Services"
        }
    ],
    "sg:phone":"+1 212 404 6988",
    "sg:postcode":"10006",
    "sg:province":"NY",
    "wof:name":"Richard L Yellen & Associates",
    "wof:placetype":"venue"
},
  "geometry": {"coordinates":[-74.011171,40.708395],"type":"Point"}
}