{
  "type": "Feature",
  "properties": {
    "addr:full":"51 Cliffside Park Jamesville NY 13078",
    "addr:housenumber":"51",
    "addr:postcode":"13078",
    "addr:street":"Park",
    "iso:country":"US",
    "sg:address":"51 Cliffside Park",
    "sg:city":"Jamesville",
    "sg:classifiers":[
        {
            "category":"Retail",
            "subcategory":"Laundry & Dry Cleaning",
            "type":"Services"
        }
    ],
    "sg:phone":"+1   ",
    "sg:postcode":"13078",
    "sg:province":"NY",
    "sg:tags":[
        "drycleaning",
        "plant"
    ],
    "wof:name":"Mean Cleaners",
    "wof:placetype":"venue"
},
  "geometry": {"coordinates":[-76.10032099999999,43.002395],"type":"Point"}
}