{
  "type": "Feature",
  "properties": {
    "iso:country":"US",
    "sg:address":"40 Ellicott St",
    "sg:city":"Batavia",
    "sg:classifiers":[
        {
            "category":"Professional",
            "type":"Services"
        }
    ],
    "sg:phone":"+1 585 344 1625",
    "sg:postcode":"14020",
    "sg:province":"NY",
    "wof:name":"Del Plato Svc",
    "wof:placetype":"venue"
},
  "geometry": {"coordinates":[-78.185829,42.996646],"type":"Point"}
}