{
  "type": "Feature",
  "properties": {
    "addr:full":"523 Central Ave Cedarhurst NY 11516",
    "addr:housenumber":"523",
    "addr:postcode":"11516",
    "addr:street":"Central Ave",
    "iso:country":"US",
    "sg:address":"523 Central Ave",
    "sg:city":"Cedarhurst",
    "sg:classifiers":[
        {
            "category":"Shopping",
            "subcategory":"Shoes",
            "type":"Retail Goods"
        }
    ],
    "sg:phone":"+1 516 295 4350",
    "sg:postcode":"11516",
    "sg:province":"NY",
    "wof:name":"Stride Rite Shoes",
    "wof:placetype":"venue"
},
  "geometry": {"coordinates":[-73.721478,40.623215],"type":"Point"}
}