{
  "type": "Feature",
  "properties": {
    "addr:full":"1938 3 Ave New York NY 10029",
    "addr:housenumber":"1938",
    "addr:postcode":"10029",
    "addr:street":"3 Ave",
    "iso:country":"US",
    "sg:address":"1938 3 Ave",
    "sg:city":"New York",
    "sg:classifiers":[
        {
            "category":"Shopping",
            "subcategory":"Jewelry",
            "type":"Retail Goods"
        }
    ],
    "sg:phone":"+1 212 876 3393",
    "sg:postcode":"10029",
    "sg:province":"NY",
    "sg:tags":[
        "jeweler"
    ],
    "wof:name":"Caesar's Jewelry",
    "wof:placetype":"venue"
},
  "geometry": {"coordinates":[-73.94882699999999,40.785881],"type":"Point"}
}