{
  "type": "Feature",
  "properties": {
    "iso:country":"US",
    "sg:address":"552 North Rd",
    "sg:city":"Binghamton",
    "sg:classifiers":[
        {
            "category":"Retail",
            "subcategory":"Laundry & Dry Cleaning",
            "type":"Services"
        }
    ],
    "sg:phone":"+1 607 775 1055",
    "sg:postcode":"13904",
    "sg:province":"NY",
    "sg:tags":[
        "house"
    ],
    "wof:name":"Custom Cleaning",
    "wof:placetype":"venue"
},
  "geometry": {"coordinates":[-75.74851200000001,42.133188],"type":"Point"}
}