{
  "type": "Feature",
  "properties": {
    "iso:country":"US",
    "sg:address":"1050 Gravel Rd",
    "sg:city":"Webster",
    "sg:classifiers":[
        {
            "category":"Professional",
            "subcategory":"Lawyer & Legal Services",
            "type":"Services"
        }
    ],
    "sg:phone":"+1 585 671 3660",
    "sg:postcode":"14580",
    "sg:province":"NY",
    "sg:tags":[
        "attorney"
    ],
    "wof:name":"William H Farr",
    "wof:placetype":"venue"
},
  "geometry": {"coordinates":[-77.496788,43.203995],"type":"Point"}
}