{
  "type": "Feature",
  "properties": {
    "iso:country":"US",
    "sg:address":"3322 Bainbridge Ave",
    "sg:city":"Bronx",
    "sg:classifiers":[
        {
            "category":"Health Services",
            "subcategory":"Doctor",
            "type":"Services"
        }
    ],
    "sg:phone":"+1 718 882 0090",
    "sg:postcode":"10467",
    "sg:province":"NY",
    "sg:tags":[
        "clinic"
    ],
    "wof:name":"Klapper & Dluca Pulmonary",
    "wof:placetype":"venue"
},
  "geometry": {"coordinates":[-73.879017,40.879168],"type":"Point"}
}