{
  "type": "Feature",
  "properties": {
    "addr:full":"16 Gramercy Park S New York NY 10003",
    "addr:housenumber":"16",
    "addr:postcode":"10003",
    "addr:street":"Gramercy Park S",
    "iso:country":"US",
    "sg:address":"16 Gramercy Park S",
    "sg:city":"New York",
    "sg:classifiers":[
        {
            "category":"Education",
            "subcategory":"Library",
            "type":"Public Place"
        }
    ],
    "sg:phone":"+1 212 228 1861",
    "sg:postcode":"10003",
    "sg:province":"NY",
    "wof:name":"Hampden Booth Theatre Library",
    "wof:placetype":"venue"
},
  "geometry": {"coordinates":[-73.98623499999999,40.737618],"type":"Point"}
}