{
  "type": "Feature",
  "properties": {
    "addr:full":"1412 Mermaid Ave Brooklyn NY 11224",
    "addr:housenumber":"1412",
    "addr:postcode":"11224",
    "addr:street":"Mermaid Ave",
    "iso:country":"US",
    "sg:address":"1412 Mermaid Ave",
    "sg:city":"Brooklyn",
    "sg:classifiers":[
        {
            "category":"Retail",
            "subcategory":"Laundry & Dry Cleaning",
            "type":"Services"
        }
    ],
    "sg:phone":"+1 718 373 6469",
    "sg:postcode":"11224",
    "sg:province":"NY",
    "sg:tags":[
        "cleaner"
    ],
    "wof:name":"Jiffy Cleaners",
    "wof:placetype":"venue"
},
  "geometry": {"coordinates":[-73.982201,40.5769],"type":"Point"}
}