{
  "type": "Feature",
  "properties": {
    "addr:full":"10519 Judson Rd Hammondsport NY 14840",
    "addr:housenumber":"10519",
    "addr:postcode":"14840",
    "addr:street":"Judson Rd",
    "iso:country":"US",
    "sg:address":"10519 Judson Rd",
    "sg:city":"Hammondsport",
    "sg:classifiers":[
        {
            "category":"Farming",
            "subcategory":"Dairy Farm",
            "type":"Manufacturing & Wholesale Goods"
        }
    ],
    "sg:phone":"+1 607 868 3116",
    "sg:postcode":"14840",
    "sg:province":"NY",
    "wof:name":"Medrek John",
    "wof:placetype":"venue"
},
  "geometry": {"coordinates":[-77.182946,42.508562],"type":"Point"}
}