{
  "type": "Feature",
  "properties": {
    "iso:country":"US",
    "sg:address":"22 Lakeview Dr",
    "sg:city":"Warwick",
    "sg:classifiers":[
        {
            "category":"Professional",
            "subcategory":"Lawyer & Legal Services",
            "type":"Services"
        }
    ],
    "sg:phone":"+1 845 987 1480",
    "sg:postcode":"10990",
    "sg:province":"NY",
    "wof:name":"Snigur Virginia R Esq",
    "wof:placetype":"venue"
},
  "geometry": {"coordinates":[-74.313033,41.285293],"type":"Point"}
}