{
  "type": "Feature",
  "properties": {
    "iso:country":"US",
    "sg:address":"483 Idlewood Blvd",
    "sg:city":"Baldwinsville",
    "sg:classifiers":[
        {
            "category":"Retail",
            "subcategory":"Repair Shop",
            "type":"Services"
        }
    ],
    "sg:phone":"+1 315 638 4170",
    "sg:postcode":"13027",
    "sg:province":"NY",
    "wof:name":"Al Ds Fine",
    "wof:placetype":"venue"
},
  "geometry": {"coordinates":[-76.30922700000001,43.133032],"type":"Point"}
}