{
  "type": "Feature",
  "properties": {
    "iso:country":"US",
    "sg:address":"213 Lake Ave",
    "sg:city":"St James",
    "sg:classifiers":[
        {
            "category":"Retail",
            "subcategory":"Laundry & Dry Cleaning",
            "type":"Services"
        }
    ],
    "sg:phone":"+1 631 862 1048",
    "sg:postcode":"11780",
    "sg:province":"NY",
    "sg:tags":[
        "cleaners"
    ],
    "wof:name":"KWIK Discount Dry Cleaners",
    "wof:placetype":"venue"
},
  "geometry": {"coordinates":[-73.15614100000001,40.875206],"type":"Point"}
}