{
  "type": "Feature",
  "properties": {
    "iso:country":"US",
    "sg:address":"243 Main St",
    "sg:city":"Huntington",
    "sg:classifiers":[
        {
            "category":"Home & Garden",
            "subcategory":"Furniture",
            "type":"Retail Goods"
        }
    ],
    "sg:phone":"+1 631 427 1045",
    "sg:postcode":"11743",
    "sg:province":"NY",
    "sg:tags":[
        "store"
    ],
    "sg:website":"www.classicgalleries-ny.com",
    "wof:name":"Classic Galleries",
    "wof:placetype":"venue"
},
  "geometry": {"coordinates":[-73.42269899999999,40.872898],"type":"Point"}
}