{
  "type": "Feature",
  "properties": {
    "addr:full":"579 E Boston Post Rd Mamaroneck NY 10543",
    "addr:housenumber":"579",
    "addr:postcode":"10543",
    "addr:street":"E Boston Post Rd",
    "iso:country":"US",
    "sg:address":"579 E Boston Post Rd",
    "sg:city":"Mamaroneck",
    "sg:classifiers":[
        {
            "category":"Real Estate",
            "subcategory":"Real Estate Services",
            "type":"Services"
        },
        {
            "category":"Real Estate",
            "subcategory":"Real Estate Agent",
            "type":"Services"
        }
    ],
    "sg:phone":"+1 914 835 6800",
    "sg:postcode":"10543",
    "sg:province":"NY",
    "sg:tags":[
        "management"
    ],
    "wof:name":"Westchester County Realty Corp",
    "wof:placetype":"venue"
},
  "geometry": {"coordinates":[-73.728915,40.951164],"type":"Point"}
}