{
  "type": "Feature",
  "properties": {
    "iso:country":"US",
    "sg:address":"877 N Corona Ave",
    "sg:city":"Valley Stream",
    "sg:classifiers":[
        {
            "category":"Professional",
            "subcategory":"Lawyer & Legal Services",
            "type":"Services"
        }
    ],
    "sg:phone":"+1 516 872 8900",
    "sg:postcode":"11580",
    "sg:province":"NY",
    "sg:tags":[
        "attorney"
    ],
    "wof:name":"Joseph J Ra Lawyer",
    "wof:placetype":"venue"
},
  "geometry": {"coordinates":[-73.68858400000001,40.68292],"type":"Point"}
}