{
  "type": "Feature",
  "properties": {
    "iso:country":"US",
    "sg:address":"1170 Shannon Ave",
    "sg:city":"Elmira",
    "sg:classifiers":[
        {
            "category":"Manufacturing",
            "subcategory":"Metals",
            "type":"Manufacturing & Wholesale Goods"
        }
    ],
    "sg:phone":"+1   ",
    "sg:postcode":"14904",
    "sg:province":"NY",
    "sg:tags":[
        "plate",
        "work",
        "fabricated",
        "mfg"
    ],
    "wof:name":"LL Disposal",
    "wof:placetype":"venue"
},
  "geometry": {"coordinates":[-76.79349000000001,42.062376],"type":"Point"}
}