{
  "type": "Feature",
  "properties": {
    "iso:country":"US",
    "sg:address":"205 Lowell Ave",
    "sg:city":"Central Islip",
    "sg:classifiers":[
        {
            "category":"Autos & Motor Vehicles",
            "subcategory":"Fuel & Gas Station",
            "type":"Retail Goods"
        },
        {
            "category":"Retail",
            "subcategory":"Auto Repair",
            "type":"Services"
        }
    ],
    "sg:phone":"+1 631 348 4018",
    "sg:postcode":"11722",
    "sg:province":"NY",
    "wof:name":"Kaba Auto Repairs Inc",
    "wof:placetype":"venue"
},
  "geometry": {"coordinates":[-73.18589799999999,40.784],"type":"Point"}
}