{
  "type": "Feature",
  "properties": {
    "iso:country":"US",
    "sg:address":"399 E 14th St",
    "sg:city":"Elmira",
    "sg:classifiers":[
        {
            "category":"Real Estate",
            "subcategory":"Real Estate Operator",
            "type":"Services"
        }
    ],
    "sg:phone":"+1 607 734 0584",
    "sg:postcode":"14903",
    "sg:province":"NY",
    "sg:tags":[
        "building",
        "apartment"
    ],
    "wof:name":"Villa Serene Apartments",
    "wof:placetype":"venue"
},
  "geometry": {"coordinates":[-76.816271,42.130134],"type":"Point"}
}