{
  "type": "Feature",
  "properties": {
    "iso:country":"US",
    "sg:address":"7 Cresthill Dr",
    "sg:city":"Nyack",
    "sg:classifiers":[
        {
            "category":"Building & Trades",
            "subcategory":"Construction",
            "type":"Services"
        }
    ],
    "sg:phone":"+1 845 727 7250",
    "sg:postcode":"10960",
    "sg:province":"NY",
    "sg:tags":[
        "general",
        "contractor"
    ],
    "wof:name":"STK Construction",
    "wof:placetype":"venue"
},
  "geometry": {"coordinates":[-73.942899,41.090192],"type":"Point"}
}