{
  "type": "Feature",
  "properties": {
    "iso:country":"US",
    "sg:address":"708 E 228th St",
    "sg:city":"Bronx",
    "sg:classifiers":[
        {
            "category":"Personal",
            "subcategory":"Beauty Salon",
            "type":"Services"
        }
    ],
    "sg:phone":"+1 718 655 2307",
    "sg:postcode":"10466",
    "sg:province":"NY",
    "wof:name":"Laddlane Unisex Salon",
    "wof:placetype":"venue"
},
  "geometry": {"coordinates":[-73.856621,40.889014],"type":"Point"}
}