{
  "type": "Feature",
  "properties": {
    "addr:full":"14201 37th Ave Flushing NY 11354",
    "addr:housenumber":"14201",
    "addr:postcode":"11354",
    "addr:street":"37Th Ave",
    "iso:country":"US",
    "sg:address":"14201 37th Ave",
    "sg:city":"Flushing",
    "sg:classifiers":[
        {
            "category":"Health Services",
            "subcategory":"Doctor",
            "type":"Services"
        }
    ],
    "sg:phone":"+1 718 539 1300",
    "sg:postcode":"11354",
    "sg:province":"NY",
    "sg:tags":[
        "podiatrist"
    ],
    "wof:name":"Warren Jeff Poditrst",
    "wof:placetype":"venue"
},
  "geometry": {"coordinates":[-73.827499,40.762402],"type":"Point"}
}