{
  "type": "Feature",
  "properties": {
    "addr:full":"450 Park Ave South  9th Floor New York  NY 10016",
    "addr:housenumber":"450",
    "addr:postcode":"10016",
    "addr:street":"Park Ave South 9Th Floor",
    "iso:country":"US",
    "sg:address":"450 Park Ave South  9th Floor",
    "sg:city":"New York ",
    "sg:classifiers":[
        {
            "category":"Professional",
            "subcategory":"Computer Services",
            "type":"Services"
        }
    ],
    "sg:phone":"+1 646 237 3400",
    "sg:postcode":"10016",
    "sg:province":"NY",
    "sg:tags":[
        "sales",
        "career",
        "matching",
        "jobs"
    ],
    "sg:website":"http://urgentcareer.com",
    "wof:name":"Urgent Career",
    "wof:placetype":"venue"
},
  "geometry": {"coordinates":[-73.982944,40.744941],"type":"Point"}
}