{
  "type": "Feature",
  "properties": {
    "iso:country":"US",
    "sg:address":"100 Amidon Dr",
    "sg:city":"Syracuse",
    "sg:classifiers":[
        {
            "category":"Education",
            "subcategory":"School",
            "type":"Public Place"
        }
    ],
    "sg:phone":"+1 315 435 4411",
    "sg:postcode":"13205",
    "sg:province":"NY",
    "wof:name":"Clary Math Science Magnet Sch",
    "wof:placetype":"venue"
},
  "geometry": {"coordinates":[-76.144057,42.996707],"type":"Point"}
}