{
  "type": "Feature",
  "properties": {
    "iso:country":"US",
    "sg:address":"850 Bailey Rd",
    "sg:city":"West Henrietta",
    "sg:classifiers":[
        {
            "category":"Government",
            "subcategory":"Fire Station",
            "type":"Public Place"
        }
    ],
    "sg:phone":"+1 585 334 1234",
    "sg:postcode":"14586",
    "sg:province":"NY",
    "sg:tags":[
        "department"
    ],
    "sg:website":"www.henriettafire.com",
    "wof:name":"Henrietta Fire District",
    "wof:placetype":"venue"
},
  "geometry": {"coordinates":[-77.650043,43.072528],"type":"Point"}
}