{
  "type": "Feature",
  "properties": {
    "addr:full":"324 5th Ave Brooklyn NY 11215",
    "addr:housenumber":"324",
    "addr:postcode":"11215",
    "addr:street":"5Th Ave",
    "iso:country":"US",
    "sg:address":"324 5th Ave",
    "sg:city":"Brooklyn",
    "sg:classifiers":[
        {
            "category":"Coffee & Tea",
            "type":"Food & Drink"
        },
        {
            "category":"Restaurant",
            "type":"Food & Drink"
        }
    ],
    "sg:phone":"+1 718 369 0082",
    "sg:postcode":"11215",
    "sg:province":"NY",
    "sg:tags":[
        "grill",
        "bar",
        "espresso",
        "soul",
        "american",
        "asian",
        "pan"
    ],
    "sg:website":"http://www.usmenuguide.com/stoneparkcafe.htm",
    "wof:name":"Stone Park Cafe",
    "wof:placetype":"venue"
},
  "geometry": {"coordinates":[-73.983299,40.672791],"type":"Point"}
}