{
  "type": "Feature",
  "properties": {
    "addr:full":"258 Chestnut St Port Jeffrsn Sta NY 11776",
    "addr:housenumber":"258",
    "addr:postcode":"11776",
    "addr:street":"Chestnut St",
    "iso:country":"US",
    "sg:address":"258 Chestnut St",
    "sg:city":"Port Jeffrsn Sta",
    "sg:classifiers":[
        {
            "category":"Wholesale",
            "subcategory":"Electrical",
            "type":"Manufacturing & Wholesale Goods"
        }
    ],
    "sg:phone":"+1 631 476 1255",
    "sg:postcode":"11776",
    "sg:province":"NY",
    "sg:tags":[
        "alarm",
        "burglar",
        "system"
    ],
    "wof:name":"Long Island Sound & Security",
    "wof:placetype":"venue"
},
  "geometry": {"coordinates":[-73.014696,40.908001],"type":"Point"}
}