{
  "type": "Feature",
  "properties": {
    "iso:country":"US",
    "sg:address":"485 Main St",
    "sg:city":"Phoenix",
    "sg:classifiers":[
        {
            "category":"Food & Beverages",
            "subcategory":"Groceries & Convenience Stores",
            "type":"Retail Goods"
        }
    ],
    "sg:phone":"+1 315 695 7005",
    "sg:postcode":"13135",
    "sg:province":"NY",
    "wof:name":"Nice N Easy",
    "wof:placetype":"venue"
},
  "geometry": {"coordinates":[-76.301546,43.232303],"type":"Point"}
}