{
  "type": "Feature",
  "properties": {
    "iso:country":"US",
    "sg:address":"216 Central Park",
    "sg:city":"Rochester",
    "sg:classifiers":[
        {
            "category":"Wholesale",
            "subcategory":"Auto Parts",
            "type":"Manufacturing & Wholesale Goods"
        }
    ],
    "sg:phone":"+1 585 232 3718",
    "sg:postcode":"14605",
    "sg:province":"NY",
    "sg:tags":[
        "automobile",
        "rebuilt"
    ],
    "wof:name":"Phil's Auto Parts Inc",
    "wof:placetype":"venue"
},
  "geometry": {"coordinates":[-77.589547,43.168632],"type":"Point"}
}