{
  "type": "Feature",
  "properties": {
    "addr:full":"225 Johnson St East Syracuse NY 13057",
    "addr:housenumber":"225",
    "addr:postcode":"13057",
    "addr:street":"Johnson St",
    "iso:country":"US",
    "sg:address":"225 Johnson St",
    "sg:city":"East Syracuse",
    "sg:phone":"+1 315 463 6961",
    "sg:postcode":"13057",
    "sg:province":"NY",
    "sg:tags":[
        "lubricant",
        "oil",
        "motor"
    ],
    "wof:name":"Dryden Oil",
    "wof:placetype":"venue"
},
  "geometry": {"coordinates":[-76.07018100000001,43.059329],"type":"Point"}
}