{
  "type": "Feature",
  "properties": {
    "iso:country":"US",
    "sg:address":"4546 Ridge Rd W",
    "sg:city":"Rochester",
    "sg:classifiers":[
        {
            "category":"Retail",
            "subcategory":"Repair Shop",
            "type":"Services"
        }
    ],
    "sg:phone":"+1 585 352 3400",
    "sg:postcode":"14420",
    "sg:province":"NY",
    "sg:tags":[
        "scooter",
        "motorcycle",
        "motor"
    ],
    "wof:name":"Falco's ITM",
    "wof:placetype":"venue"
},
  "geometry": {"coordinates":[-77.74804899999999,43.216873],"type":"Point"}
}