{
  "type": "Feature",
  "properties": {
    "iso:country":"US",
    "sg:address":"454 Suffolk Ave",
    "sg:city":"Brentwood",
    "sg:classifiers":[
        {
            "category":"Professional",
            "subcategory":"Accounting & Tax Preparation",
            "type":"Services"
        }
    ],
    "sg:phone":"+1 631 236 5702",
    "sg:postcode":"11717",
    "sg:province":"NY",
    "sg:tags":[
        "return",
        "filing"
    ],
    "wof:name":"Jackson Hewitt",
    "wof:placetype":"venue"
},
  "geometry": {"coordinates":[-73.25788900000001,40.778442],"type":"Point"}
}