{
  "type": "Feature",
  "properties": {
    "addr:full":"2546 White Plains Rd Bronx NY 10467",
    "addr:housenumber":"2546",
    "addr:postcode":"10467",
    "addr:street":"White Plains Rd",
    "iso:country":"US",
    "sg:address":"2546 White Plains Rd",
    "sg:city":"Bronx",
    "sg:classifiers":[
        {
            "category":"Food & Beverages",
            "subcategory":"Groceries & Convenience Stores",
            "type":"Retail Goods"
        }
    ],
    "sg:phone":"+1 347 346 6274",
    "sg:postcode":"10467",
    "sg:province":"NY",
    "wof:name":"White Plains Gourmet Deli & Grocery",
    "wof:placetype":"venue"
},
  "geometry": {"coordinates":[-73.867261,40.86373],"type":"Point"}
}