{
  "type": "Feature",
  "properties": {
    "addr:full":"476 Merrick Rd Oceanside NY 11572",
    "addr:housenumber":"476",
    "addr:postcode":"11572",
    "addr:street":"Merrick Rd",
    "iso:country":"US",
    "sg:address":"476 Merrick Rd",
    "sg:city":"Oceanside",
    "sg:phone":"+1 516 255 2032",
    "sg:postcode":"11572",
    "sg:province":"NY",
    "sg:tags":[
        "product",
        "petroleum"
    ],
    "wof:name":"E & B Petroleum",
    "wof:placetype":"venue"
},
  "geometry": {"coordinates":[-73.623642,40.653362],"type":"Point"}
}