{
  "type": "Feature",
  "properties": {
    "addr:full":"576 9 Ave New York NY 10036",
    "addr:housenumber":"576",
    "addr:postcode":"10036",
    "addr:street":"9 Ave",
    "iso:country":"US",
    "sg:address":"576 9 Ave",
    "sg:city":"New York",
    "sg:classifiers":[
        {
            "category":"Professional",
            "subcategory":"Business Services",
            "type":"Services"
        }
    ],
    "sg:phone":"+1 212 246 6100",
    "sg:postcode":"10036",
    "sg:province":"NY",
    "sg:tags":[
        "recording",
        "photography",
        "studio"
    ],
    "wof:name":"Streetlight Music Inc",
    "wof:placetype":"venue"
},
  "geometry": {"coordinates":[-73.992633,40.75843],"type":"Point"}
}