{
  "type": "Feature",
  "properties": {
    "iso:country":"US",
    "sg:address":"41 Lafayette Ave",
    "sg:city":"Suffern",
    "sg:classifiers":[
        {
            "category":"Restaurant",
            "type":"Food & Drink"
        }
    ],
    "sg:phone":"+1   ",
    "sg:postcode":"10901",
    "sg:province":"NY",
    "sg:tags":[
        "eating"
    ],
    "wof:name":"Suffern Deli & Diner",
    "wof:placetype":"venue"
},
  "geometry": {"coordinates":[-74.154186,41.116275],"type":"Point"}
}