{
  "type": "Feature",
  "properties": {
    "addr:full":"125 Mill St Troy NY 12180",
    "addr:housenumber":"125",
    "addr:postcode":"12180",
    "addr:street":"Mill St",
    "iso:country":"US",
    "sg:address":"125 Mill St",
    "sg:city":"Troy",
    "sg:classifiers":[
        {
            "category":"Autos & Motor Vehicles",
            "subcategory":"Fuel & Gas Station",
            "type":"Retail Goods"
        }
    ],
    "sg:phone":"+1 518 272 9595",
    "sg:postcode":"12180",
    "sg:province":"NY",
    "sg:tags":[
        "station",
        "gasoline",
        "oil"
    ],
    "wof:name":"King Fuels",
    "wof:placetype":"venue"
},
  "geometry": {"coordinates":[-73.68945600000001,42.704491],"type":"Point"}
}