{
  "type": "Feature",
  "properties": {
    "iso:country":"US",
    "sg:address":"60 N Prospect Ave",
    "sg:city":"Lynbrook",
    "sg:classifiers":[
        {
            "category":"Building & Trades",
            "subcategory":"Plumbing",
            "type":"Services"
        }
    ],
    "sg:phone":"+1 516 887 4000",
    "sg:postcode":"11563",
    "sg:province":"NY",
    "wof:name":"Robert Mechanical Corp",
    "wof:placetype":"venue"
},
  "geometry": {"coordinates":[-73.686798,40.6623],"type":"Point"}
}