{
  "type": "Feature",
  "properties": {
    "iso:country":"US",
    "sg:address":"66 Hale Ave",
    "sg:city":"White Plains",
    "sg:classifiers":[
        {
            "category":"Professional",
            "subcategory":"Computer Services",
            "type":"Services"
        }
    ],
    "sg:phone":"+1 914 328 1800",
    "sg:postcode":"10601",
    "sg:province":"NY",
    "sg:tags":[
        "leasing"
    ],
    "wof:name":"Superior Audio Visuals",
    "wof:placetype":"venue"
},
  "geometry": {"coordinates":[-73.760992,41.030398],"type":"Point"}
}