{
  "type": "Feature",
  "properties": {
    "addr:full":"1604 Gravesend Neck Rd Brooklyn NY 11229",
    "addr:housenumber":"1604",
    "addr:postcode":"11229",
    "addr:street":"Gravesend Neck Rd",
    "iso:country":"US",
    "sg:address":"1604 Gravesend Neck Rd",
    "sg:city":"Brooklyn",
    "sg:classifiers":[
        {
            "category":"Manufacturing",
            "subcategory":"Leather Goods",
            "type":"Manufacturing & Wholesale Goods"
        }
    ],
    "sg:phone":"+1 718 648 3383",
    "sg:postcode":"11229",
    "sg:province":"NY",
    "wof:name":"Abyb Wine Corp",
    "wof:placetype":"venue"
},
  "geometry": {"coordinates":[-73.95462499999999,40.594912],"type":"Point"}
}