{
  "type": "Feature",
  "properties": {
    "addr:full":"2 W 47th St Fl 6 New York NY 10036",
    "addr:housenumber":"2;6",
    "addr:postcode":"10036",
    "addr:street":"W 47Th St",
    "iso:country":"US",
    "sg:address":"2 W 47th St Fl 6",
    "sg:city":"New York",
    "sg:classifiers":[
        {
            "category":"Shopping",
            "subcategory":"Jewelry",
            "type":"Retail Goods"
        }
    ],
    "sg:phone":"+1 866 960 8134",
    "sg:postcode":"10036",
    "sg:province":"NY",
    "wof:name":"Alexander Primak Jewelry",
    "wof:placetype":"venue"
},
  "geometry": {"coordinates":[-73.979343,40.756737],"type":"Point"}
}