{
  "type": "Feature",
  "properties": {
    "iso:country":"US",
    "sg:address":"54 Beekman Ave",
    "sg:city":"Sleepy Hollow",
    "sg:classifiers":[
        {
            "category":"Home & Garden",
            "subcategory":"Furniture",
            "type":"Retail Goods"
        }
    ],
    "sg:phone":"+1 914 366 0759",
    "sg:postcode":"10591",
    "sg:province":"NY",
    "sg:tags":[
        "store"
    ],
    "wof:name":"Westchester Furniture & Bedding",
    "wof:placetype":"venue"
},
  "geometry": {"coordinates":[-73.860603,41.084999],"type":"Point"}
}