{
  "type": "Feature",
  "properties": {
    "addr:full":"274 Southport St Ronkonkoma NY 11779",
    "addr:housenumber":"274",
    "addr:postcode":"11779",
    "addr:street":"Southport St",
    "iso:country":"US",
    "sg:address":"274 Southport St",
    "sg:city":"Ronkonkoma",
    "sg:classifiers":[
        {
            "category":"Recreation",
            "type":"Entertainment"
        }
    ],
    "sg:phone":"+1 631 737 8027",
    "sg:postcode":"11779",
    "sg:province":"NY",
    "sg:tags":[
        "hall",
        "auditorium"
    ],
    "wof:name":"Occasions",
    "wof:placetype":"venue"
},
  "geometry": {"coordinates":[-73.149908,40.798059],"type":"Point"}
}