{
  "type": "Feature",
  "properties": {
    "addr:full":"2940 Telephone Rd Caledonia NY 14423",
    "addr:housenumber":"2940",
    "addr:postcode":"14423",
    "addr:street":"Telephone Rd",
    "iso:country":"US",
    "sg:address":"2940 Telephone Rd",
    "sg:city":"Caledonia",
    "sg:phone":"+1 585 538 4110",
    "sg:postcode":"14423",
    "sg:province":"NY",
    "sg:tags":[
        "gas"
    ],
    "wof:name":"Bickford Holland Propane Inc",
    "wof:placetype":"venue"
},
  "geometry": {"coordinates":[-77.858683,42.914931],"type":"Point"}
}