{
  "type": "Feature",
  "properties": {
    "addr:full":"2051 Military Rd Niagara Falls NY 14304",
    "addr:housenumber":"2051",
    "addr:postcode":"14304",
    "addr:street":"Military Rd",
    "iso:country":"US",
    "sg:address":"2051 Military Rd",
    "sg:city":"Niagara Falls",
    "sg:classifiers":[
        {
            "category":"Insurance",
            "subcategory":"Insurance Agent",
            "type":"Services"
        }
    ],
    "sg:phone":"+1 716 297 0660",
    "sg:postcode":"14304",
    "sg:province":"NY",
    "wof:name":"Robert E Lee Insurance",
    "wof:placetype":"venue"
},
  "geometry": {"coordinates":[-78.975227,43.097355],"type":"Point"}
}