{
  "type": "Feature",
  "properties": {
    "iso:country":"US",
    "sg:address":"64 E Market St",
    "sg:city":"Rhinebeck",
    "sg:classifiers":[
        {
            "category":"Shopping",
            "subcategory":"Pharmacy",
            "type":"Retail Goods"
        }
    ],
    "sg:phone":"+1 845 876 3222",
    "sg:postcode":"12572",
    "sg:province":"NY",
    "sg:tags":[
        "medicines-patent",
        "proprietary"
    ],
    "wof:name":"Proimmune Company",
    "wof:placetype":"venue"
},
  "geometry": {"coordinates":[-73.910314,41.927013],"type":"Point"}
}