{
  "type": "Feature",
  "properties": {
    "addr:full":"9 Fisher Ave White Plains NY 10601",
    "addr:housenumber":"9",
    "addr:postcode":"10601",
    "addr:street":"Fisher Ave",
    "iso:country":"US",
    "sg:address":"9 Fisher Ave",
    "sg:city":"White Plains",
    "sg:classifiers":[
        {
            "category":"Government",
            "subcategory":"Office",
            "type":"Public Place"
        }
    ],
    "sg:phone":"+1 914 946 6330",
    "sg:postcode":"10601",
    "sg:province":"NY",
    "sg:tags":[
        "village"
    ],
    "wof:name":"White Plains Public Housing",
    "wof:placetype":"venue"
},
  "geometry": {"coordinates":[-73.772976,41.027786],"type":"Point"}
}