{
  "type": "Feature",
  "properties": {
    "iso:country":"US",
    "sg:address":"1979 Marcus Ave",
    "sg:city":"New Hyde Park",
    "sg:classifiers":[
        {
            "category":"Professional",
            "subcategory":"Employment Agencies",
            "type":"Services"
        }
    ],
    "sg:phone":"+1 516 622 1660",
    "sg:postcode":"11042",
    "sg:province":"NY",
    "wof:name":"Premier Staffing",
    "wof:placetype":"venue"
},
  "geometry": {"coordinates":[-73.691498,40.757099],"type":"Point"}
}