{
  "type": "Feature",
  "properties": {
    "addr:full":"246 Main St Staten Island NY 10307",
    "addr:housenumber":"246",
    "addr:postcode":"10307",
    "addr:street":"Main St",
    "iso:country":"US",
    "sg:address":"246 Main St",
    "sg:city":"Staten Island",
    "sg:classifiers":[
        {
            "category":"Autos & Motor Vehicles",
            "subcategory":"Auto Supplies",
            "type":"Retail Goods"
        },
        {
            "category":"Wholesale",
            "subcategory":"Auto Parts",
            "type":"Manufacturing & Wholesale Goods"
        }
    ],
    "sg:phone":"+1 718 948 5048",
    "sg:postcode":"10307",
    "sg:province":"NY",
    "sg:tags":[
        "automobile"
    ],
    "wof:name":"Parts House The",
    "wof:placetype":"venue"
},
  "geometry": {"coordinates":[-74.247412,40.509652],"type":"Point"}
}