{
  "type": "Feature",
  "properties": {
    "addr:full":"245 W 104th St New York NY 10025",
    "addr:housenumber":"245",
    "addr:postcode":"10025",
    "addr:street":"W 104Th St",
    "iso:country":"US",
    "sg:address":"245 W 104th St",
    "sg:city":"New York",
    "sg:classifiers":[
        {
            "category":"Restaurant",
            "type":"Food & Drink"
        }
    ],
    "sg:phone":"+1 212 316 5000",
    "sg:postcode":"10025",
    "sg:province":"NY",
    "wof:name":"Cafe Du Soleil",
    "wof:placetype":"venue"
},
  "geometry": {"coordinates":[-73.969505,40.800329],"type":"Point"}
}