{
  "type": "Feature",
  "properties": {
    "addr:full":"1811 Bath Ave Brooklyn NY 11214",
    "addr:housenumber":"1811",
    "addr:postcode":"11214",
    "addr:street":"Bath Ave",
    "iso:country":"US",
    "sg:address":"1811 Bath Ave",
    "sg:city":"Brooklyn",
    "sg:classifiers":[
        {
            "category":"Place Of Worship",
            "subcategory":"Church",
            "type":"Public Place"
        },
        {
            "category":"Place Of Worship",
            "type":"Public Place"
        }
    ],
    "sg:phone":"+1 718 837 7354",
    "sg:postcode":"11214",
    "sg:province":"NY",
    "sg:tags":[
        "churches-baptist-general",
        "churches-baptist"
    ],
    "wof:name":"Mt Zion Baptist Church",
    "wof:placetype":"venue"
},
  "geometry": {"coordinates":[-74.005737,40.603653],"type":"Point"}
}