{
  "type": "Feature",
  "properties": {
    "iso:country":"US",
    "sg:address":"49 Morton St",
    "sg:city":"Malone",
    "sg:classifiers":[
        {
            "category":"Organizations",
            "subcategory":"Religious Organization",
            "type":"Services"
        }
    ],
    "sg:phone":"+1 518 483 2880",
    "sg:postcode":"12953",
    "sg:province":"NY",
    "wof:name":"St Josephs Ursuline Sister",
    "wof:placetype":"venue"
},
  "geometry": {"coordinates":[-74.287497,44.851278],"type":"Point"}
}