{
  "type": "Feature",
  "properties": {
    "iso:country":"US",
    "sg:address":"272 Bayview Ave",
    "sg:city":"Massapequa",
    "sg:classifiers":[
        {
            "category":"Building & Trades",
            "subcategory":"Plumbing",
            "type":"Services"
        }
    ],
    "sg:phone":"+1 516 795 7691",
    "sg:postcode":"11758",
    "sg:province":"NY",
    "sg:tags":[
        "contractor"
    ],
    "wof:name":"D & G Plumbing",
    "wof:placetype":"venue"
},
  "geometry": {"coordinates":[-73.46463799999999,40.652743],"type":"Point"}
}