{
  "type": "Feature",
  "properties": {
    "addr:full":"5550 Netherland Ave Bronx NY 10471",
    "addr:housenumber":"5550",
    "addr:postcode":"10471",
    "addr:street":"Netherland Ave",
    "iso:country":"US",
    "sg:address":"5550 Netherland Ave",
    "sg:city":"Bronx",
    "sg:classifiers":[
        {
            "category":"Retail",
            "subcategory":"Repair Shop",
            "type":"Services"
        }
    ],
    "sg:phone":"+1 718 685 5948",
    "sg:postcode":"10471",
    "sg:province":"NY",
    "sg:tags":[
        "lock",
        "locksmith"
    ],
    "wof:name":"AAA Able Locksmith",
    "wof:placetype":"venue"
},
  "geometry": {"coordinates":[-73.90637700000001,40.903772],"type":"Point"}
}