{
  "type": "Feature",
  "properties": {
    "addr:full":"200 5th Avenue New York NY 10010",
    "addr:housenumber":"200",
    "addr:postcode":"10010",
    "addr:street":"5Th Avenue",
    "iso:country":"US",
    "sg:address":"200 5th Avenue",
    "sg:city":"New York",
    "sg:classifiers":[
        {
            "category":"Shopping",
            "subcategory":"Hobbies, Toys, & Games",
            "type":"Retail Goods"
        }
    ],
    "sg:phone":"+1 212 924 9716",
    "sg:postcode":"10010",
    "sg:province":"NY",
    "sg:tags":[
        "toy",
        "store"
    ],
    "wof:name":"Spin Master",
    "wof:placetype":"venue"
},
  "geometry": {"coordinates":[-73.988653,40.742827],"type":"Point"}
}