{
  "type": "Feature",
  "properties": {
    "addr:full":"2660 N Forest Rd Getzville NY 14068",
    "addr:housenumber":"2660",
    "addr:postcode":"14068",
    "addr:street":"N Forest Rd",
    "iso:country":"US",
    "sg:address":"2660 N Forest Rd",
    "sg:city":"Getzville",
    "sg:classifiers":[
        {
            "category":"Professional",
            "subcategory":"Accounting & Tax Preparation",
            "type":"Services"
        }
    ],
    "sg:phone":"+1   ",
    "sg:postcode":"14068",
    "sg:province":"NY",
    "wof:name":"Albert I Coe",
    "wof:placetype":"venue"
},
  "geometry": {"coordinates":[-78.784307,43.013616],"type":"Point"}
}