{
  "type": "Feature",
  "properties": {
    "iso:country":"US",
    "sg:address":"21 Murray St",
    "sg:city":"Whitestone",
    "sg:classifiers":[
        {
            "category":"Insurance",
            "subcategory":"Insurance Agent",
            "type":"Services"
        }
    ],
    "sg:phone":"+1 718 762 3995",
    "sg:postcode":"11357",
    "sg:province":"NY",
    "sg:tags":[
        "investigation"
    ],
    "wof:name":"Edward J Kirk",
    "wof:placetype":"venue"
},
  "geometry": {"coordinates":[-73.81278399999999,40.775605],"type":"Point"}
}