{
  "type": "Feature",
  "properties": {
    "iso:country":"US",
    "sg:address":"975 Gravel Rd",
    "sg:city":"Webster",
    "sg:classifiers":[
        {
            "category":"Home & Garden",
            "subcategory":"Home Furnishings",
            "type":"Retail Goods"
        }
    ],
    "sg:phone":"+1 585 671 9173",
    "sg:postcode":"14580",
    "sg:province":"NY",
    "sg:tags":[
        "draperies",
        "vertical",
        "blinds-venetian",
        "window",
        "treatment",
        "curtain"
    ],
    "sg:website":"http://www.budgetblinds.com",
    "wof:name":"Budget Blinds",
    "wof:placetype":"venue"
},
  "geometry": {"coordinates":[-77.493965,43.208895],"type":"Point"}
}