{
  "type": "Feature",
  "properties": {
    "addr:full":"7387 State Hwy 96 Victor NY 14564",
    "addr:housenumber":"7387",
    "addr:postcode":"14564",
    "addr:street":"State Hwy 96",
    "iso:country":"US",
    "sg:address":"7387 State Hwy 96",
    "sg:city":"Victor",
    "sg:classifiers":[
        {
            "category":"Restaurant",
            "type":"Food & Drink"
        }
    ],
    "sg:phone":"+1   ",
    "sg:postcode":"14564",
    "sg:province":"NY",
    "sg:tags":[
        "eating"
    ],
    "wof:name":"Leonardos Pizza",
    "wof:placetype":"venue"
},
  "geometry": {"coordinates":[-77.443843,43.0124],"type":"Point"}
}