{
  "type": "Feature",
  "properties": {
    "addr:full":"402 Meyers Rd Liverpool NY 13088",
    "addr:housenumber":"402",
    "addr:postcode":"13088",
    "addr:street":"Meyers Rd",
    "iso:country":"US",
    "sg:address":"402 Meyers Rd",
    "sg:city":"Liverpool",
    "sg:classifiers":[
        {
            "category":"Professional",
            "subcategory":"Business Services",
            "type":"Services"
        }
    ],
    "sg:phone":"+1 315 451 8817",
    "sg:postcode":"13088",
    "sg:province":"NY",
    "sg:tags":[
        "interior",
        "consultant",
        "design",
        "decorator"
    ],
    "wof:name":"Brandi Interior Designers",
    "wof:placetype":"venue"
},
  "geometry": {"coordinates":[-76.223561,43.111598],"type":"Point"}
}