{
  "type": "Feature",
  "properties": {
    "addr:full":"7 N Broadway Yonkers NY 10701",
    "addr:housenumber":"7",
    "addr:postcode":"10701",
    "addr:street":"N Broadway",
    "iso:country":"US",
    "sg:address":"7 N Broadway",
    "sg:city":"Yonkers",
    "sg:classifiers":[
        {
            "category":"Personal",
            "subcategory":"Beauty Salon",
            "type":"Services"
        },
        {
            "category":"Personal",
            "subcategory":"Nail Salon",
            "type":"Services"
        }
    ],
    "sg:phone":"+1 914 476 1891",
    "sg:postcode":"10701",
    "sg:province":"NY",
    "wof:name":"Gold Nail",
    "wof:placetype":"venue"
},
  "geometry": {"coordinates":[-73.897892,40.934014],"type":"Point"}
}