{
  "type": "Feature",
  "properties": {
    "addr:full":"3135 Ridge Rd Williamson NY 14589",
    "addr:housenumber":"3135",
    "addr:postcode":"14589",
    "addr:street":"Ridge Rd",
    "iso:country":"US",
    "sg:address":"3135 Ridge Rd",
    "sg:city":"Williamson",
    "sg:classifiers":[
        {
            "category":"Food & Beverages",
            "subcategory":"Fruits & Vegetables",
            "type":"Retail Goods"
        }
    ],
    "sg:phone":"+1 315 589 4175",
    "sg:postcode":"14589",
    "sg:province":"NY",
    "sg:tags":[
        "farm",
        "market"
    ],
    "wof:name":"Mason Farms",
    "wof:placetype":"venue"
},
  "geometry": {"coordinates":[-77.232174,43.222709],"type":"Point"}
}