{
  "type": "Feature",
  "properties": {
    "addr:full":"130 Franklin Street New York NY 10013",
    "addr:housenumber":"130",
    "addr:postcode":"10013",
    "addr:street":"Franklin Street",
    "iso:country":"US",
    "sg:address":"130 Franklin Street",
    "sg:city":"New York",
    "sg:classifiers":[
        {
            "category":"Personal",
            "subcategory":"Day Spa",
            "type":"Services"
        }
    ],
    "sg:phone":"+1 212 966 3656",
    "sg:postcode":"10013",
    "sg:province":"NY",
    "wof:name":"Millefleurs Spa Mondial",
    "wof:placetype":"venue"
},
  "geometry": {"coordinates":[-74.00657099999999,40.718833],"type":"Point"}
}