{
  "type": "Feature",
  "properties": {
    "addr:full":"274 Central Ave Bethpage NY 11714",
    "addr:housenumber":"274",
    "addr:postcode":"11714",
    "addr:street":"Central Ave",
    "iso:country":"US",
    "sg:address":"274 Central Ave",
    "sg:city":"Bethpage",
    "sg:classifiers":[
        {
            "category":"Wholesale",
            "subcategory":"Electrical",
            "type":"Manufacturing & Wholesale Goods"
        }
    ],
    "sg:phone":"+1 516 933 2828",
    "sg:postcode":"11714",
    "sg:province":"NY",
    "sg:tags":[
        "lighting",
        "fixture"
    ],
    "wof:name":"GPM Lighting Supply",
    "wof:placetype":"venue"
},
  "geometry": {"coordinates":[-73.481238,40.738443],"type":"Point"}
}