{
  "type": "Feature",
  "properties": {
    "addr:full":"246 Route 52 Carmel NY 10512",
    "addr:housenumber":"246",
    "addr:postcode":"10512",
    "addr:street":"Route 52",
    "iso:country":"US",
    "sg:address":"246 Route 52",
    "sg:city":"Carmel",
    "sg:classifiers":[
        {
            "category":"Building & Trades",
            "subcategory":"Construction",
            "type":"Services"
        },
        {
            "category":"Home & Garden",
            "subcategory":"Carpets & Floor Coverings",
            "type":"Retail Goods"
        }
    ],
    "sg:phone":"+1 800 394 3064",
    "sg:postcode":"10512",
    "sg:province":"NY",
    "sg:tags":[
        "material",
        "tile-contractors",
        "rug",
        "flooring",
        "contractor"
    ],
    "sg:website":"http://www.filitrac.com/Click.aspx?tid=BDEDC5D5EF8BAE3541B5938870DA3DDECE60F60FEE115906&FiliAff=15016&sid=99202&utm_source=YellowPages&utm_medium=ppc&utm_campaign=national&utm_term=10512",
    "wof:name":"Kennys Carpet One Floor & Home",
    "wof:placetype":"venue"
},
  "geometry": {"coordinates":[-73.680994,41.440245],"type":"Point"}
}