{
  "type": "Feature",
  "properties": {
    "addr:full":"4 Warehouse Ln Elmsford NY 10523",
    "addr:housenumber":"4",
    "addr:postcode":"10523",
    "addr:street":"Warehouse Ln",
    "iso:country":"US",
    "sg:address":"4 Warehouse Ln",
    "sg:city":"Elmsford",
    "sg:classifiers":[
        {
            "category":"Home & Garden",
            "subcategory":"Garden Supply",
            "type":"Retail Goods"
        }
    ],
    "sg:phone":"+1 914 345 1350",
    "sg:postcode":"10523",
    "sg:province":"NY",
    "sg:tags":[
        "sprinkler"
    ],
    "sg:website":"www.aqua-turf.com",
    "wof:name":"Aqua Turf Irrigation Systems",
    "wof:placetype":"venue"
},
  "geometry": {"coordinates":[-73.814593,41.064032],"type":"Point"}
}