{
  "type": "Feature",
  "properties": {
    "addr:full":"136 W Corning Ave Syracuse NY 13205",
    "addr:housenumber":"136",
    "addr:postcode":"13205",
    "addr:street":"W Corning Ave",
    "iso:country":"US",
    "sg:address":"136 W Corning Ave",
    "sg:city":"Syracuse",
    "sg:classifiers":[
        {
            "category":"Building & Trades",
            "subcategory":"Construction",
            "type":"Services"
        }
    ],
    "sg:phone":"+1 315 471 3904",
    "sg:postcode":"13205",
    "sg:province":"NY",
    "sg:tags":[
        "remodeling",
        "renovation",
        "contractor"
    ],
    "wof:name":"Chris Tull Construction",
    "wof:placetype":"venue"
},
  "geometry": {"coordinates":[-76.14488799999999,43.018637],"type":"Point"}
}