{
  "type": "Feature",
  "properties": {
    "iso:country":"US",
    "sg:address":"900 Palmer Rd",
    "sg:city":"Bronxville",
    "sg:classifiers":[
        {
            "category":"Real Estate",
            "subcategory":"Real Estate Operator",
            "type":"Services"
        }
    ],
    "sg:phone":"+1 914 337 0309",
    "sg:postcode":"10708",
    "sg:province":"NY",
    "sg:tags":[
        "apartment"
    ],
    "wof:name":"Winchester Apartments",
    "wof:placetype":"venue"
},
  "geometry": {"coordinates":[-73.842879,40.940715],"type":"Point"}
}