{
  "type": "Feature",
  "properties": {
    "addr:full":"130 Woodworth Ave Yonkers NY 10701",
    "addr:housenumber":"130",
    "addr:postcode":"10701",
    "addr:street":"Woodworth Ave",
    "iso:country":"US",
    "sg:address":"130 Woodworth Ave",
    "sg:city":"Yonkers",
    "sg:classifiers":[
        {
            "category":"Manufacturing",
            "subcategory":"Paper Products",
            "type":"Manufacturing & Wholesale Goods"
        },
        {
            "category":"Wholesale",
            "subcategory":"Groceries",
            "type":"Manufacturing & Wholesale Goods"
        }
    ],
    "sg:phone":"+1 914 969 4500",
    "sg:postcode":"10701",
    "sg:province":"NY",
    "sg:tags":[
        "fr",
        "dairy"
    ],
    "wof:name":"Yonkers Institutional Food Co",
    "wof:placetype":"venue"
},
  "geometry": {"coordinates":[-73.898347,40.942832],"type":"Point"}
}