{
  "type": "Feature",
  "properties": {
    "addr:full":"7908 Ontario Ave Cicero NY 13039",
    "addr:housenumber":"7908",
    "addr:postcode":"13039",
    "addr:street":"Ontario Ave",
    "iso:country":"US",
    "sg:address":"7908 Ontario Ave",
    "sg:city":"Cicero",
    "sg:classifiers":[
        {
            "category":"Manufacturing",
            "subcategory":"Tools & Machinery",
            "type":"Manufacturing & Wholesale Goods"
        }
    ],
    "sg:phone":"+1   ",
    "sg:postcode":"13039",
    "sg:province":"NY",
    "sg:tags":[
        "industrial",
        "mfg"
    ],
    "wof:name":"Liberty Machine & Tool",
    "wof:placetype":"venue"
},
  "geometry": {"coordinates":[-76.058837,43.197746],"type":"Point"}
}