{
  "type": "Feature",
  "properties": {
    "addr:full":"5223 Co Rd 8 Avoca NY 14809",
    "addr:housenumber":"8",
    "addr:postcode":"5223;14809",
    "addr:street":"Co Rd",
    "iso:country":"US",
    "sg:address":"5223 Co Rd 8",
    "sg:city":"Avoca",
    "sg:classifiers":[
        {
            "category":"Wholesale",
            "subcategory":"Machinery & Supplies",
            "type":"Manufacturing & Wholesale Goods"
        }
    ],
    "sg:phone":"+1 607 566 2617",
    "sg:postcode":"14809",
    "sg:province":"NY",
    "sg:website":"www.mjdtools.com",
    "wof:name":"Live Free Or Die Antique Tool",
    "wof:placetype":"venue"
},
  "geometry": {"coordinates":[-77.400588,42.428731],"type":"Point"}
}