{
  "type": "Feature",
  "properties": {
    "iso:country":"US",
    "sg:address":"34 Stonehaven Dr",
    "sg:city":"Ithaca",
    "sg:classifiers":[
        {
            "category":"Professional",
            "subcategory":"Secretarial Services",
            "type":"Services"
        }
    ],
    "sg:phone":"+1 607 257 3737",
    "sg:postcode":"14850",
    "sg:province":"NY",
    "sg:tags":[
        "proofreading"
    ],
    "wof:name":"Bowman's Press LLC",
    "wof:placetype":"venue"
},
  "geometry": {"coordinates":[-76.470906,42.516429],"type":"Point"}
}