{
  "type": "Feature",
  "properties": {
    "addr:full":"31 Randy Dr Akron NY 14001",
    "addr:housenumber":"31",
    "addr:postcode":"14001",
    "addr:street":"Randy Dr",
    "iso:country":"US",
    "sg:address":"31 Randy Dr",
    "sg:city":"Akron",
    "sg:classifiers":[
        {
            "category":"Organizations",
            "subcategory":"Religious Organization",
            "type":"Services"
        }
    ],
    "sg:phone":"+1 716 542 4914",
    "sg:postcode":"14001",
    "sg:province":"NY",
    "sg:tags":[
        "clergy"
    ],
    "wof:name":"Donald E Willman",
    "wof:placetype":"venue"
},
  "geometry": {"coordinates":[-78.49023,43.026567],"type":"Point"}
}