{
  "type": "Feature",
  "properties": {
    "iso:country":"US",
    "sg:address":"16 E Broadway Fl 1",
    "sg:city":"New York",
    "sg:classifiers":[
        {
            "category":"Banks & Credit Unions",
            "subcategory":"Bank",
            "type":"Services"
        }
    ],
    "sg:phone":"+1 646 613 8705",
    "sg:postcode":"10002",
    "sg:province":"NY",
    "wof:name":"Great Eastern Bank",
    "wof:placetype":"venue"
},
  "geometry": {"coordinates":[-73.996939,40.713372],"type":"Point"}
}