{
  "type": "Feature",
  "properties": {
    "iso:country":"US",
    "sg:address":"1082 Coney Island Ave",
    "sg:city":"Brooklyn",
    "sg:classifiers":[
        {
            "category":"Shopping",
            "subcategory":"Tobacco",
            "type":"Retail Goods"
        }
    ],
    "sg:phone":"+1 718 766 5377",
    "sg:postcode":"11230",
    "sg:province":"NY",
    "sg:tags":[
        "cigarette",
        "cigar",
        "dealer"
    ],
    "wof:name":"Smoker's Social",
    "wof:placetype":"venue"
},
  "geometry": {"coordinates":[-73.966263,40.630137],"type":"Point"}
}