{
  "type": "Feature",
  "properties": {
    "addr:full":"400 Montauk Hwy Oakdale NY 11769",
    "addr:housenumber":"400",
    "addr:postcode":"11769",
    "addr:street":"Montauk Hwy",
    "iso:country":"US",
    "sg:address":"400 Montauk Hwy",
    "sg:city":"Oakdale",
    "sg:classifiers":[
        {
            "category":"Sports & Exercise",
            "subcategory":"Sports Center",
            "type":"Entertainment"
        }
    ],
    "sg:phone":"+1 631 589 8363",
    "sg:postcode":"11769",
    "sg:province":"NY",
    "sg:tags":[
        "amateur",
        "team"
    ],
    "wof:name":"West Oak Recreation Inc",
    "wof:placetype":"venue"
},
  "geometry": {"coordinates":[-73.112801,40.725498],"type":"Point"}
}