{
  "type": "Feature",
  "properties": {
    "addr:full":"8 Royal Hunt Ln Pittsford NY 14534",
    "addr:housenumber":"8",
    "addr:postcode":"14534",
    "addr:street":"Royal Hunt Ln",
    "iso:country":"US",
    "sg:address":"8 Royal Hunt Ln",
    "sg:city":"Pittsford",
    "sg:classifiers":[
        {
            "category":"Health Services",
            "subcategory":"Doctor",
            "type":"Services"
        }
    ],
    "sg:phone":"+1 585 624 4605",
    "sg:postcode":"14534",
    "sg:province":"NY",
    "sg:tags":[
        "medical"
    ],
    "wof:name":"Harry M Cole MD",
    "wof:placetype":"venue"
},
  "geometry": {"coordinates":[-77.489628,43.024577],"type":"Point"}
}