{
  "type": "Feature",
  "properties": {
    "addr:full":"11013 101st Avenue South Richmond Hill NY 11419",
    "addr:housenumber":"11013",
    "addr:postcode":"11419",
    "addr:street":"101St Avenue South",
    "iso:country":"US",
    "sg:address":"11013 101st Avenue",
    "sg:city":"South Richmond Hill",
    "sg:classifiers":[
        {
            "category":"Food & Beverages",
            "subcategory":"Liquor & Beverages",
            "type":"Retail Goods"
        }
    ],
    "sg:phone":"+1 718 847 9423",
    "sg:postcode":"11419",
    "sg:province":"NY",
    "sg:tags":[
        "beer",
        "spirit",
        "wine"
    ],
    "wof:name":"New India Wine & Liquors",
    "wof:placetype":"venue"
},
  "geometry": {"coordinates":[-73.833203,40.688021],"type":"Point"}
}