{
  "type": "Feature",
  "properties": {
    "addr:full":"400 Atlantic Ave Brooklyn NY 11217",
    "addr:housenumber":"400",
    "addr:postcode":"11217",
    "addr:street":"Atlantic Ave",
    "iso:country":"US",
    "sg:address":"400 Atlantic Ave",
    "sg:city":"Brooklyn",
    "sg:classifiers":[
        {
            "category":"Shopping",
            "subcategory":"Used Merchandise",
            "type":"Retail Goods"
        }
    ],
    "sg:phone":"+1   ",
    "sg:postcode":"11217",
    "sg:province":"NY",
    "wof:name":"Old Good Things",
    "wof:placetype":"venue"
},
  "geometry": {"coordinates":[-73.986448,40.687675],"type":"Point"}
}