{
  "type": "Feature",
  "properties": {
    "iso:country":"US",
    "sg:address":"69 Bayard St",
    "sg:city":"New York",
    "sg:classifiers":[
        {
            "category":"Food & Beverages",
            "subcategory":"Specialty",
            "type":"Retail Goods"
        }
    ],
    "sg:phone":"+1   ",
    "sg:postcode":"10013",
    "sg:province":"NY",
    "wof:name":"Herb Store",
    "wof:placetype":"venue"
},
  "geometry": {"coordinates":[-73.998133,40.715381],"type":"Point"}
}