{
  "type": "Feature",
  "properties": {
    "addr:full":"164-166 7th Ave Brooklyn NY 11215",
    "addr:housenumber":"164-166",
    "addr:postcode":"11215",
    "addr:street":"7Th Ave",
    "iso:country":"US",
    "sg:address":"164-166 7th Ave",
    "sg:city":"Brooklyn",
    "sg:classifiers":[
        {
            "category":"Coffee & Tea",
            "type":"Food & Drink"
        }
    ],
    "sg:phone":"+1 718 369 1213",
    "sg:postcode":"11215",
    "sg:province":"NY",
    "sg:website":"www.starbucks.com",
    "wof:name":"Starbucks",
    "wof:placetype":"venue"
},
  "geometry": {"coordinates":[-73.997879,40.650249],"type":"Point"}
}