{
  "type": "Feature",
  "properties": {
    "iso:country":"US",
    "sg:address":"10 Brinkerhoff St",
    "sg:city":"Plattsburgh",
    "sg:classifiers":[
        {
            "category":"Health Services",
            "subcategory":"Chiropractor",
            "type":"Services"
        }
    ],
    "sg:phone":"+1 518 562 9355",
    "sg:postcode":"12901",
    "sg:province":"NY",
    "wof:name":"Living Well Chiropractic",
    "wof:placetype":"venue"
},
  "geometry": {"coordinates":[-73.45337600000001,44.697161],"type":"Point"}
}