{
  "type": "Feature",
  "properties": {
    "iso:country":"US",
    "sg:address":"10 Norrie Ct",
    "sg:city":"Germantown",
    "sg:classifiers":[
        {
            "category":"Restaurant",
            "type":"Food & Drink"
        }
    ],
    "sg:phone":"+1 518 537 7667",
    "sg:postcode":"12526",
    "sg:province":"NY",
    "wof:name":"Beyond The Box Web Productions",
    "wof:placetype":"venue"
},
  "geometry": {"coordinates":[-73.815262,42.075399],"type":"Point"}
}