{
  "type": "Feature",
  "properties": {
    "addr:full":"14605 232nd St Springfield Gardens NY 11413",
    "addr:housenumber":"14605",
    "addr:postcode":"11413",
    "addr:street":"232Nd St",
    "iso:country":"US",
    "sg:address":"14605 232nd St",
    "sg:city":"Springfield Gardens",
    "sg:classifiers":[
        {
            "category":"Building & Trades",
            "subcategory":"Construction",
            "type":"Services"
        }
    ],
    "sg:phone":"+1 718 723 2032",
    "sg:postcode":"11413",
    "sg:province":"NY",
    "sg:tags":[
        "contractor"
    ],
    "wof:name":"New York City Billionares Construction Corp",
    "wof:placetype":"venue"
},
  "geometry": {"coordinates":[-73.74820699999999,40.658591],"type":"Point"}
}