{
  "type": "Feature",
  "properties": {
    "addr:full":"108 New South Rd Hicksville NY 11801",
    "addr:housenumber":"108",
    "addr:postcode":"11801",
    "addr:street":"New South Rd",
    "iso:country":"US",
    "sg:address":"108 New South Rd",
    "sg:city":"Hicksville",
    "sg:classifiers":[
        {
            "category":"Wholesale",
            "subcategory":"Farm Supplies",
            "type":"Manufacturing & Wholesale Goods"
        }
    ],
    "sg:phone":"+1 516 822 2870",
    "sg:postcode":"11801",
    "sg:province":"NY",
    "sg:tags":[
        "fertilizer"
    ],
    "wof:name":"Lesco Service Ctr",
    "wof:placetype":"venue"
},
  "geometry": {"coordinates":[-73.50606000000001,40.757754],"type":"Point"}
}