{
  "type": "Feature",
  "properties": {
    "addr:full":"167 Bunker Hill Rd Cossayuna NY 12823",
    "addr:housenumber":"167",
    "addr:postcode":"12823",
    "addr:street":"Bunker Hill Rd",
    "iso:country":"US",
    "sg:address":"167 Bunker Hill Rd",
    "sg:city":"Cossayuna",
    "sg:classifiers":[
        {
            "category":"Farming",
            "subcategory":"Dairy Farm",
            "type":"Manufacturing & Wholesale Goods"
        }
    ],
    "sg:phone":"+1 518 692 2652",
    "sg:postcode":"12823",
    "sg:province":"NY",
    "sg:tags":[
        "field",
        "corn",
        "crop"
    ],
    "wof:name":"Bunker Hill Farms",
    "wof:placetype":"venue"
},
  "geometry": {"coordinates":[-73.41982899999999,43.187902],"type":"Point"}
}