{
  "type": "Feature",
  "properties": {
    "iso:country":"US",
    "sg:address":"1467 1st Avenue",
    "sg:city":"New York",
    "sg:classifiers":[
        {
            "category":"Shopping",
            "subcategory":"Pharmacy",
            "type":"Retail Goods"
        }
    ],
    "sg:phone":"+1 212 585 2108",
    "sg:postcode":"10021",
    "sg:province":"NY",
    "sg:tags":[
        "drugstore"
    ],
    "wof:name":"Duane Reade",
    "wof:placetype":"venue"
},
  "geometry": {"coordinates":[-73.95393799999999,40.770829],"type":"Point"}
}