{
  "type": "Feature",
  "properties": {
    "addr:full":"764 State Fair Blvd Syracuse NY 13209",
    "addr:housenumber":"764",
    "addr:postcode":"13209",
    "addr:street":"State Fair Blvd",
    "iso:country":"US",
    "sg:address":"764 State Fair Blvd",
    "sg:city":"Syracuse",
    "sg:classifiers":[
        {
            "category":"Wholesale",
            "subcategory":"Groceries",
            "type":"Manufacturing & Wholesale Goods"
        }
    ],
    "sg:phone":"+1 315 488 5321",
    "sg:postcode":"13209",
    "sg:province":"NY",
    "sg:tags":[
        "food",
        "broker"
    ],
    "wof:name":"Lomac & May Assoc",
    "wof:placetype":"venue"
},
  "geometry": {"coordinates":[-76.237368,43.086767],"type":"Point"}
}