{
  "type": "Feature",
  "properties": {
    "addr:full":"1633 Broadway New York NY 10019",
    "addr:housenumber":"1633",
    "addr:postcode":"10019",
    "addr:street":"Broadway",
    "iso:country":"US",
    "sg:address":"1633 Broadway",
    "sg:city":"New York",
    "sg:classifiers":[
        {
            "category":"Professional",
            "subcategory":"Lawyer & Legal Services",
            "type":"Services"
        }
    ],
    "sg:phone":"+1 212 541 5080",
    "sg:postcode":"10019",
    "sg:province":"NY",
    "wof:name":"Kasowitz Benson Torres & Freidman Llp",
    "wof:placetype":"venue"
},
  "geometry": {"coordinates":[-73.984015,40.76151],"type":"Point"}
}