{
  "type": "Feature",
  "properties": {
    "addr:full":"1 W 125th St New York NY 10027",
    "addr:housenumber":"1",
    "addr:postcode":"10027",
    "addr:street":"W 125Th St",
    "iso:country":"US",
    "sg:address":"1 W 125th St",
    "sg:city":"New York",
    "sg:classifiers":[
        {
            "category":"Professional",
            "subcategory":"Employment Agencies",
            "type":"Services"
        }
    ],
    "sg:phone":"+1 212 534 2076",
    "sg:postcode":"10027",
    "sg:province":"NY",
    "wof:name":"Professional Placement Services Inc",
    "wof:placetype":"venue"
},
  "geometry": {"coordinates":[-73.94229900000001,40.806301],"type":"Point"}
}