{
  "type": "Feature",
  "properties": {
    "addr:full":"39 Washington St Buffalo NY 14218",
    "addr:housenumber":"39",
    "addr:postcode":"14218",
    "addr:street":"Washington St",
    "iso:country":"US",
    "sg:address":"39 Washington St",
    "sg:city":"Buffalo",
    "sg:classifiers":[
        {
            "category":"Building & Trades",
            "subcategory":"Construction",
            "type":"Services"
        }
    ],
    "sg:phone":"+1 716 827 7084",
    "sg:postcode":"14218",
    "sg:province":"NY",
    "sg:tags":[
        "handyman"
    ],
    "wof:name":"ARJ Handyman Svc",
    "wof:placetype":"venue"
},
  "geometry": {"coordinates":[-78.844319,42.822857],"type":"Point"}
}