{
  "type": "Feature",
  "properties": {
    "addr:full":"28 Country Club Dr Shelter Island NY 11964",
    "addr:housenumber":"28",
    "addr:postcode":"11964",
    "addr:street":"Country Club Dr",
    "iso:country":"US",
    "sg:address":"28 Country Club Dr",
    "sg:city":"Shelter Island",
    "sg:classifiers":[
        {
            "category":"Wholesale",
            "subcategory":"Hardware",
            "type":"Manufacturing & Wholesale Goods"
        }
    ],
    "sg:phone":"+1 631 477 8531",
    "sg:postcode":"11964",
    "sg:province":"NY",
    "wof:name":"Radiant Heater Corporation",
    "wof:placetype":"venue"
},
  "geometry": {"coordinates":[-72.33120099999999,41.097995],"type":"Point"}
}