{
  "type": "Feature",
  "properties": {
    "addr:full":"Pier 60 Pier 60 New York NY 10011",
    "addr:housenumber":"pier 60",
    "addr:postcode":"10011",
    "iso:country":"US",
    "sg:address":"Pier 60 Pier 60",
    "sg:city":"New York",
    "sg:classifiers":[
        {
            "category":"Fast Food",
            "type":"Food & Drink"
        }
    ],
    "sg:phone":"+1 212 989 8400",
    "sg:postcode":"10011",
    "sg:province":"NY",
    "wof:name":"Jason's Riverside Grill",
    "wof:placetype":"venue"
},
  "geometry": {"coordinates":[-74.002264,40.761628],"type":"Point"}
}