{
  "type": "Feature",
  "properties": {
    "iso:country":"US",
    "sg:address":"64 Lafayette Ave",
    "sg:city":"Brooklyn",
    "sg:classifiers":[
        {
            "category":"Restaurant",
            "type":"Food & Drink"
        }
    ],
    "sg:menulink":"http://www.allmenus.com/ny/brooklyn/274019-little-piggy-market/menu/",
    "sg:phone":"+1 718 797 1011",
    "sg:postcode":"11217",
    "sg:province":"NY",
    "sg:tags":[
        "new",
        "american"
    ],
    "wof:name":"Little Piggy Market",
    "wof:placetype":"venue"
},
  "geometry": {"coordinates":[-73.97534899999999,40.686983],"type":"Point"}
}