{
  "type": "Feature",
  "properties": {
    "iso:country":"US",
    "sg:address":"1 West Ave",
    "sg:city":"Le Roy",
    "sg:classifiers":[
        {
            "category":"Health Services",
            "subcategory":"Nursing And Care Facility",
            "type":"Services"
        }
    ],
    "sg:phone":"+1 585 768 2740",
    "sg:postcode":"14482",
    "sg:province":"NY",
    "wof:name":"Greens Of Leroy",
    "wof:placetype":"venue"
},
  "geometry": {"coordinates":[-78.002472,42.98121],"type":"Point"}
}