{
  "type": "Feature",
  "properties": {
    "addr:full":"530 E 29th St Brooklyn NY 11210",
    "addr:housenumber":"530",
    "addr:postcode":"11210",
    "addr:street":"E 29Th St",
    "iso:country":"US",
    "sg:address":"530 E 29th St",
    "sg:city":"Brooklyn",
    "sg:classifiers":[
        {
            "category":"Retail",
            "subcategory":"Auto Repair",
            "type":"Services"
        }
    ],
    "sg:phone":"+1 212 792 6116",
    "sg:postcode":"11210",
    "sg:province":"NY",
    "sg:tags":[
        "wrecker"
    ],
    "wof:name":"Tow Co",
    "wof:placetype":"venue"
},
  "geometry": {"coordinates":[-73.949116,40.636919],"type":"Point"}
}