{
  "type": "Feature",
  "properties": {
    "addr:full":"14 Ridge Dr E Roslyn NY 11576",
    "addr:housenumber":"14",
    "addr:postcode":"11576",
    "addr:street":"Ridge Dr E",
    "iso:country":"US",
    "sg:address":"14 Ridge Dr E",
    "sg:city":"Roslyn",
    "sg:classifiers":[
        {
            "category":"Shopping",
            "subcategory":"Photographic Equipment",
            "type":"Retail Goods"
        }
    ],
    "sg:phone":"+1   ",
    "sg:postcode":"11576",
    "sg:province":"NY",
    "sg:tags":[
        "supply"
    ],
    "wof:name":"Hartford Camera",
    "wof:placetype":"venue"
},
  "geometry": {"coordinates":[-73.659953,40.80109],"type":"Point"}
}