{
  "type": "Feature",
  "properties": {
    "iso:country":"US",
    "sg:address":"171 Eads St",
    "sg:city":"West Babylon",
    "sg:classifiers":[
        {
            "category":"Manufacturing",
            "subcategory":"Retail Goods",
            "type":"Manufacturing & Wholesale Goods"
        }
    ],
    "sg:phone":"+1 631 644 0005",
    "sg:postcode":"11704",
    "sg:province":"NY",
    "sg:tags":[
        "manufacturer"
    ],
    "wof:name":"Bootsector Industries Inc",
    "wof:placetype":"venue"
},
  "geometry": {"coordinates":[-73.390873,40.735613],"type":"Point"}
}