{
  "type": "Feature",
  "properties": {
    "iso:country":"US",
    "sg:address":"352 Fairport Rd",
    "sg:city":"East Rochester",
    "sg:classifiers":[
        {
            "category":"Building & Trades",
            "subcategory":"Construction",
            "type":"Services"
        }
    ],
    "sg:phone":"+1 585 381 3060",
    "sg:postcode":"14445",
    "sg:province":"NY",
    "sg:tags":[
        "painter"
    ],
    "wof:name":"TAK Painting & Wall Covering",
    "wof:placetype":"venue"
},
  "geometry": {"coordinates":[-77.488736,43.104976],"type":"Point"}
}