{
  "type": "Feature",
  "properties": {
    "iso:country":"US",
    "sg:address":"50 Roman Rd",
    "sg:city":"Southampton",
    "sg:classifiers":[
        {
            "category":"Wholesale",
            "subcategory":"Non-durable Goods",
            "type":"Manufacturing & Wholesale Goods"
        }
    ],
    "sg:phone":"+1 631 287 1842",
    "sg:postcode":"11968",
    "sg:province":"NY",
    "wof:name":"Micro Trade Network",
    "wof:placetype":"venue"
},
  "geometry": {"coordinates":[-72.402861,40.90326],"type":"Point"}
}