{
  "type": "Feature",
  "properties": {
    "addr:full":"24 W 47 St New York NY 10036",
    "addr:housenumber":"24",
    "addr:postcode":"10036",
    "addr:street":"W 47 St",
    "iso:country":"US",
    "sg:address":"24 W 47 St",
    "sg:city":"New York",
    "sg:classifiers":[
        {
            "category":"Building & Trades",
            "subcategory":"Plumbing",
            "type":"Services"
        }
    ],
    "sg:phone":"+1 212 406 2256",
    "sg:postcode":"10036",
    "sg:province":"NY",
    "sg:tags":[
        "conditioning",
        "air",
        "system",
        "contractor"
    ],
    "wof:name":"Ace Air Conditioning",
    "wof:placetype":"venue"
},
  "geometry": {"coordinates":[-73.98126999999999,40.757642],"type":"Point"}
}