{
  "type": "Feature",
  "properties": {
    "iso:country":"US",
    "sg:address":"571 N Main St",
    "sg:city":"Brewster",
    "sg:classifiers":[
        {
            "category":"Manufacturing",
            "subcategory":"Food",
            "type":"Manufacturing & Wholesale Goods"
        }
    ],
    "sg:phone":"+1   ",
    "sg:postcode":"10509",
    "sg:province":"NY",
    "sg:tags":[
        "liquor",
        "mfg"
    ],
    "wof:name":"Vivendi Universal Holding I",
    "wof:placetype":"venue"
},
  "geometry": {"coordinates":[-73.61827099999999,41.402736],"type":"Point"}
}