{
  "type": "Feature",
  "properties": {
    "addr:full":"83 Grand St Elmont NY 11003",
    "addr:housenumber":"83",
    "addr:postcode":"11003",
    "addr:street":"Grand St",
    "iso:country":"US",
    "sg:address":"83 Grand St",
    "sg:city":"Elmont",
    "sg:classifiers":[
        {
            "category":"Manufacturing",
            "subcategory":"Metals",
            "type":"Manufacturing & Wholesale Goods"
        }
    ],
    "sg:phone":"+1   ",
    "sg:postcode":"11003",
    "sg:province":"NY",
    "sg:tags":[
        "sanitary",
        "ware",
        "metalwork",
        "structural",
        "mfg"
    ],
    "wof:name":"Design Impressions Corp",
    "wof:placetype":"venue"
},
  "geometry": {"coordinates":[-73.686711,40.70964],"type":"Point"}
}