{
  "type": "Feature",
  "properties": {
    "addr:full":"164 State Hwy 385 Catskill NY 12414",
    "addr:housenumber":"164",
    "addr:postcode":"12414",
    "addr:street":"State Hwy 385",
    "iso:country":"US",
    "sg:address":"164 State Hwy 385",
    "sg:city":"Catskill",
    "sg:classifiers":[
        {
            "category":"Retail",
            "subcategory":"Auto Repair",
            "type":"Services"
        }
    ],
    "sg:phone":"+1 518 943 5219",
    "sg:postcode":"12414",
    "sg:province":"NY",
    "sg:tags":[
        "truck"
    ],
    "wof:name":"J & J Truck Repairs",
    "wof:placetype":"venue"
},
  "geometry": {"coordinates":[-73.861941,42.223586],"type":"Point"}
}