{
  "type": "Feature",
  "properties": {
    "iso:country":"US",
    "sg:address":"220 Nassau Blvd",
    "sg:city":"Garden City",
    "sg:classifiers":[
        {
            "category":"Health Services",
            "subcategory":"Chiropractor",
            "type":"Services"
        }
    ],
    "sg:phone":"+1 516 481 8797",
    "sg:postcode":"11530",
    "sg:province":"NY",
    "wof:name":"Goebel Donna M Chiropractor",
    "wof:placetype":"venue"
},
  "geometry": {"coordinates":[-73.660698,40.730598],"type":"Point"}
}