{
  "type": "Feature",
  "properties": {
    "iso:country":"US",
    "sg:address":"52 Central Ave",
    "sg:city":"Tarrytown",
    "sg:classifiers":[
        {
            "category":"Retail",
            "subcategory":"Repair Shop",
            "type":"Services"
        }
    ],
    "sg:phone":"+1   ",
    "sg:postcode":"10591",
    "sg:province":"NY",
    "sg:tags":[
        "motor",
        "cycle"
    ],
    "wof:name":"Top Dead Center",
    "wof:placetype":"venue"
},
  "geometry": {"coordinates":[-73.861259,41.078203],"type":"Point"}
}