{
  "type": "Feature",
  "properties": {
    "iso:country":"US",
    "sg:address":"1201 Front St",
    "sg:city":"Uniondale",
    "sg:classifiers":[
        {
            "category":"Retail",
            "subcategory":"Auto Repair",
            "type":"Services"
        }
    ],
    "sg:phone":"+1 516 385 6642",
    "sg:postcode":"11553",
    "sg:province":"NY",
    "sg:tags":[
        "repairing",
        "automobile"
    ],
    "wof:name":"Jp Performance",
    "wof:placetype":"venue"
},
  "geometry": {"coordinates":[-73.585503,40.710499],"type":"Point"}
}