{
  "type": "Feature",
  "properties": {
    "iso:country":"US",
    "sg:address":"2347 Main St",
    "sg:city":"Collins",
    "sg:classifiers":[
        {
            "category":"Organizations",
            "subcategory":"Religious Organization",
            "type":"Services"
        }
    ],
    "sg:phone":"+1 716 532 3230",
    "sg:postcode":"14034",
    "sg:province":"NY",
    "wof:name":"Ministry Mats",
    "wof:placetype":"venue"
},
  "geometry": {"coordinates":[-78.91888400000001,42.496574],"type":"Point"}
}