{
  "type": "Feature",
  "properties": {
    "addr:full":"710 E 229th St Bronx NY 10466",
    "addr:housenumber":"710",
    "addr:postcode":"10466",
    "addr:street":"E 229Th St",
    "iso:country":"US",
    "sg:address":"710 E 229th St",
    "sg:city":"Bronx",
    "sg:classifiers":[
        {
            "category":"Autos & Motor Vehicles",
            "subcategory":"Automobile Sales",
            "type":"Retail Goods"
        }
    ],
    "sg:phone":"+1   ",
    "sg:postcode":"10466",
    "sg:province":"NY",
    "sg:tags":[
        "dealer"
    ],
    "wof:name":"Top Quality Cars",
    "wof:placetype":"venue"
},
  "geometry": {"coordinates":[-73.85628,40.889738],"type":"Point"}
}