{
  "type": "Feature",
  "properties": {
    "iso:country":"US",
    "sg:address":"1933 Kensington Ave",
    "sg:city":"Buffalo",
    "sg:classifiers":[
        {
            "category":"Retail",
            "subcategory":"Funeral Services",
            "type":"Services"
        }
    ],
    "sg:phone":"+1 716 833 1695",
    "sg:postcode":"14215",
    "sg:province":"NY",
    "sg:tags":[
        "cemetery"
    ],
    "wof:name":"Sauer-Lynette-Amigone Funeral Home",
    "wof:placetype":"venue"
},
  "geometry": {"coordinates":[-78.78649900000001,42.9491],"type":"Point"}
}