{
  "type": "Feature",
  "properties": {
    "iso:country":"US",
    "sg:address":"132 Cherry St",
    "sg:city":"Ithaca",
    "sg:classifiers":[
        {
            "category":"Building & Trades",
            "subcategory":"Construction",
            "type":"Services"
        }
    ],
    "sg:phone":"+1 607 272 0536",
    "sg:postcode":"14850",
    "sg:province":"NY",
    "sg:tags":[
        "welder"
    ],
    "wof:name":"Gts-Welco",
    "wof:placetype":"venue"
},
  "geometry": {"coordinates":[-76.515714,42.4372],"type":"Point"}
}