{
  "type": "Feature",
  "properties": {
    "addr:full":"22 John St Monticello NY 12771",
    "addr:housenumber":"22",
    "addr:postcode":"12771",
    "addr:street":"John St",
    "iso:country":"US",
    "sg:address":"22 John St",
    "sg:city":"Monticello",
    "sg:classifiers":[
        {
            "category":"Education",
            "subcategory":"School",
            "type":"Public Place"
        }
    ],
    "sg:phone":"+1 845 794 6020",
    "sg:postcode":"12771",
    "sg:province":"NY",
    "wof:name":"Monticello Middle School",
    "wof:placetype":"venue"
},
  "geometry": {"coordinates":[-74.68746899999999,41.375585],"type":"Point"}
}