{
  "type": "Feature",
  "properties": {
    "addr:full":"331 Soundview Ave Bronx NY 10473",
    "addr:housenumber":"331",
    "addr:postcode":"10473",
    "addr:street":"Soundview Ave",
    "iso:country":"US",
    "sg:address":"331 Soundview Ave",
    "sg:city":"Bronx",
    "sg:classifiers":[
        {
            "category":"Wholesale",
            "subcategory":"Machinery & Supplies",
            "type":"Manufacturing & Wholesale Goods"
        }
    ],
    "sg:phone":"+1 718 893 5030",
    "sg:postcode":"10473",
    "sg:province":"NY",
    "sg:tags":[
        "machine",
        "sewing"
    ],
    "wof:name":"American Sewing Machine Enam",
    "wof:placetype":"venue"
},
  "geometry": {"coordinates":[-73.85673800000001,40.811907],"type":"Point"}
}