{
  "type": "Feature",
  "properties": {
    "iso:country":"US",
    "sg:address":"1317 Hilton Parma Rd",
    "sg:city":"Hilton",
    "sg:classifiers":[
        {
            "category":"Professional",
            "subcategory":"Accounting & Tax Preparation",
            "type":"Services"
        }
    ],
    "sg:phone":"+1   ",
    "sg:postcode":"14468",
    "sg:province":"NY",
    "wof:name":"Frl Assoc",
    "wof:placetype":"venue"
},
  "geometry": {"coordinates":[-77.79142400000001,43.247235],"type":"Point"}
}