{
  "type": "Feature",
  "properties": {
    "addr:full":"75 Ross Street Brooklyn NY 11211",
    "addr:housenumber":"75",
    "addr:postcode":"11211",
    "addr:street":"Ross Street",
    "iso:country":"US",
    "sg:address":"75 Ross Street",
    "sg:city":"Brooklyn",
    "sg:classifiers":[
        {
            "category":"Professional",
            "type":"Services"
        }
    ],
    "sg:phone":"+1 718 302 3700",
    "sg:postcode":"11211",
    "sg:province":"NY",
    "sg:tags":[
        "caterer"
    ],
    "wof:name":"Ateres Avrohom",
    "wof:placetype":"venue"
},
  "geometry": {"coordinates":[-73.963815,40.703611],"type":"Point"}
}