{
  "type": "Feature",
  "properties": {
    "addr:full":"8081 Jericho Tpke Woodbury NY 11797",
    "addr:housenumber":"8081",
    "addr:postcode":"11797",
    "addr:street":"Jericho Tpke",
    "iso:country":"US",
    "sg:address":"8081 Jericho Tpke",
    "sg:city":"Woodbury",
    "sg:classifiers":[
        {
            "category":"Banks & Credit Unions",
            "subcategory":"Bank",
            "type":"Services"
        }
    ],
    "sg:phone":"+1 516 367 9100",
    "sg:postcode":"11797",
    "sg:province":"NY",
    "wof:name":"Roslyn Savings Bank",
    "wof:placetype":"venue"
},
  "geometry": {"coordinates":[-73.47720700000001,40.814384],"type":"Point"}
}