{
  "type": "Feature",
  "properties": {
    "iso:country":"US",
    "sg:address":"15 New Hwy",
    "sg:city":"Commack",
    "sg:classifiers":[
        {
            "category":"Education",
            "subcategory":"School",
            "type":"Public Place"
        }
    ],
    "sg:phone":"+1 631 858 3680",
    "sg:postcode":"11725",
    "sg:province":"NY",
    "wof:name":"Commack School District",
    "wof:placetype":"venue"
},
  "geometry": {"coordinates":[-73.289247,40.828151],"type":"Point"}
}