{
  "type": "Feature",
  "properties": {
    "addr:full":"5820 Bay Parkway Brooklyn NY 11204",
    "addr:housenumber":"5820",
    "addr:postcode":"11204",
    "addr:street":"Bay Parkway",
    "iso:country":"US",
    "sg:address":"5820 Bay Parkway",
    "sg:city":"Brooklyn",
    "sg:classifiers":[
        {
            "category":"Retail",
            "subcategory":"Auto Repair",
            "type":"Services"
        }
    ],
    "sg:phone":"+1 718 331 4444",
    "sg:postcode":"11204",
    "sg:province":"NY",
    "wof:name":"J C's Auto Enterprise",
    "wof:placetype":"venue"
},
  "geometry": {"coordinates":[-73.97638999999999,40.619057],"type":"Point"}
}