{
  "type": "Feature",
  "properties": {
    "addr:full":"3 Water St Elizabethtown NY 12932",
    "addr:housenumber":"3",
    "addr:postcode":"12932",
    "addr:street":"Water St",
    "iso:country":"US",
    "sg:address":"3 Water St",
    "sg:city":"Elizabethtown",
    "sg:classifiers":[
        {
            "category":"Restaurant",
            "type":"Food & Drink"
        }
    ],
    "sg:phone":"+1 518 873 9288",
    "sg:postcode":"12932",
    "sg:province":"NY",
    "sg:tags":[
        "eating"
    ],
    "wof:name":"Bub's Pizza & Deli",
    "wof:placetype":"venue"
},
  "geometry": {"coordinates":[-73.59116400000001,44.216789],"type":"Point"}
}