{
  "type": "Feature",
  "properties": {
    "addr:full":"101 Main St Corinth NY 12822",
    "addr:housenumber":"101",
    "addr:postcode":"12822",
    "addr:street":"Main St",
    "iso:country":"US",
    "sg:address":"101 Main St",
    "sg:city":"Corinth",
    "sg:classifiers":[
        {
            "category":"Food & Beverages",
            "subcategory":"Groceries & Convenience Stores",
            "type":"Retail Goods"
        }
    ],
    "sg:phone":"+1   ",
    "sg:postcode":"12822",
    "sg:province":"NY",
    "wof:name":"Stewarts",
    "wof:placetype":"venue"
},
  "geometry": {"coordinates":[-73.83372199999999,43.247499],"type":"Point"}
}