{
  "type": "Feature",
  "properties": {
    "iso:country":"US",
    "sg:address":"76 King St",
    "sg:city":"Chappaqua",
    "sg:classifiers":[
        {
            "category":"Restaurant",
            "type":"Food & Drink"
        }
    ],
    "sg:phone":"+1 914 238 5950",
    "sg:postcode":"10514",
    "sg:province":"NY",
    "sg:tags":[
        "italian"
    ],
    "sg:website":"www.grappololocanda.com",
    "wof:name":"Grappolo",
    "wof:placetype":"venue"
},
  "geometry": {"coordinates":[-73.772126,41.159152],"type":"Point"}
}