{
  "type": "Feature",
  "properties": {
    "addr:full":"8 Beacon Hills Dr N Penfield NY 14526",
    "addr:housenumber":"8",
    "addr:postcode":"14526",
    "addr:street":"Beacon Hills Dr N",
    "iso:country":"US",
    "sg:address":"8 Beacon Hills Dr N",
    "sg:city":"Penfield",
    "sg:classifiers":[
        {
            "category":"Building & Trades",
            "subcategory":"Construction",
            "type":"Services"
        }
    ],
    "sg:phone":"+1 585 671 1561",
    "sg:postcode":"14526",
    "sg:province":"NY",
    "sg:tags":[
        "floor",
        "laying",
        "contractor"
    ],
    "wof:name":"Superior Flooring",
    "wof:placetype":"venue"
},
  "geometry": {"coordinates":[-77.483692,43.174596],"type":"Point"}
}