{
  "type": "Feature",
  "properties": {
    "addr:full":"1219 E 73rd St Brooklyn NY 11234",
    "addr:housenumber":"1219",
    "addr:postcode":"11234",
    "addr:street":"E 73Rd St",
    "iso:country":"US",
    "sg:address":"1219 E 73rd St",
    "sg:city":"Brooklyn",
    "sg:classifiers":[
        {
            "category":"Taxi",
            "type":"Transportation"
        }
    ],
    "sg:phone":"+1   ",
    "sg:postcode":"11234",
    "sg:province":"NY",
    "sg:tags":[
        "taxicab"
    ],
    "wof:name":"J and Y",
    "wof:placetype":"venue"
},
  "geometry": {"coordinates":[-73.91131799999999,40.625869],"type":"Point"}
}