{
  "type": "Feature",
  "properties": {
    "addr:full":"150 Old Mill Rd Rochester NY 14618",
    "addr:housenumber":"150",
    "addr:postcode":"14618",
    "addr:street":"Old Mill Rd",
    "iso:country":"US",
    "sg:address":"150 Old Mill Rd",
    "sg:city":"Rochester",
    "sg:classifiers":[
        {
            "category":"Shopping",
            "subcategory":"Computers & Home Electronics",
            "type":"Retail Goods"
        }
    ],
    "sg:phone":"+1 585 424 5235",
    "sg:postcode":"14618",
    "sg:province":"NY",
    "sg:tags":[
        "equipment",
        "electronic",
        "supply"
    ],
    "wof:name":"Radio Shack",
    "wof:placetype":"venue"
},
  "geometry": {"coordinates":[-77.546678,43.119443],"type":"Point"}
}