{
  "type": "Feature",
  "properties": {
    "iso:country":"US",
    "sg:address":"1728 Front St",
    "sg:city":"Keeseville",
    "sg:classifiers":[
        {
            "category":"Professional",
            "subcategory":"Lawyer & Legal Services",
            "type":"Services"
        }
    ],
    "sg:phone":"+1 518 834 7900",
    "sg:postcode":"12944",
    "sg:province":"NY",
    "sg:tags":[
        "attorney"
    ],
    "wof:name":"Bradford H Brinton",
    "wof:placetype":"venue"
},
  "geometry": {"coordinates":[-73.480109,44.504715],"type":"Point"}
}