{
  "type": "Feature",
  "properties": {
    "addr:full":"97 Huguenot St New Paltz NY 12561",
    "addr:housenumber":"97",
    "addr:postcode":"12561",
    "addr:street":"Huguenot St",
    "iso:country":"US",
    "sg:address":"97 Huguenot St",
    "sg:city":"New Paltz",
    "sg:classifiers":[
        {
            "category":"Organizations",
            "subcategory":"Religious Organization",
            "type":"Services"
        }
    ],
    "sg:phone":"+1 845 255 0490",
    "sg:postcode":"12561",
    "sg:province":"NY",
    "sg:tags":[
        "clergy"
    ],
    "wof:name":"Howard Major",
    "wof:placetype":"venue"
},
  "geometry": {"coordinates":[-74.086658,41.75369],"type":"Point"}
}