{
  "type": "Feature",
  "properties": {
    "iso:country":"US",
    "sg:address":"208 State St",
    "sg:city":"Binghamton",
    "sg:classifiers":[
        {
            "category":"Autos & Motor Vehicles",
            "subcategory":"Automobile Sales",
            "type":"Retail Goods"
        }
    ],
    "sg:phone":"+1   ",
    "sg:postcode":"13901",
    "sg:province":"NY",
    "sg:tags":[
        "used"
    ],
    "wof:name":"Central Motors",
    "wof:placetype":"venue"
},
  "geometry": {"coordinates":[-75.911551,42.10123],"type":"Point"}
}