{
  "type": "Feature",
  "properties": {
    "addr:full":"100 Lafayette St Ste 304 New York NY 10013",
    "addr:housenumber":"100;304",
    "addr:postcode":"10013",
    "addr:street":"Lafayette St Ste",
    "iso:country":"US",
    "sg:address":"100 Lafayette St Ste 304",
    "sg:city":"New York",
    "sg:classifiers":[
        {
            "category":"Professional",
            "subcategory":"Lawyer & Legal Services",
            "type":"Services"
        }
    ],
    "sg:phone":"+1 212 431 8073",
    "sg:postcode":"10013",
    "sg:province":"NY",
    "wof:name":"Axelrod and Gottlieb",
    "wof:placetype":"venue"
},
  "geometry": {"coordinates":[-74.00116800000001,40.717765],"type":"Point"}
}