{
  "type": "Feature",
  "properties": {
    "iso:country":"US",
    "sg:address":"205 W 39 St",
    "sg:city":"New York",
    "sg:classifiers":[
        {
            "category":"Professional",
            "type":"Services"
        }
    ],
    "sg:phone":"+1 212 278 8175",
    "sg:postcode":"10018",
    "sg:province":"NY",
    "sg:tags":[
        "establishment"
    ],
    "wof:name":"Julianna Collezione Hma",
    "wof:placetype":"venue"
},
  "geometry": {"coordinates":[-73.99105299999999,40.755347],"type":"Point"}
}