{
  "type": "Feature",
  "properties": {
    "iso:country":"US",
    "sg:address":"993 Lexington Ave",
    "sg:city":"New York",
    "sg:classifiers":[
        {
            "category":"Shopping",
            "subcategory":"Books",
            "type":"Retail Goods"
        }
    ],
    "sg:phone":"+1 212 570 9565",
    "sg:postcode":"10021",
    "sg:province":"NY",
    "sg:tags":[
        "bookstore"
    ],
    "sg:website":"www.archiviabooks.com",
    "wof:name":"Archivia Books",
    "wof:placetype":"venue"
},
  "geometry": {"coordinates":[-73.962141,40.770069],"type":"Point"}
}