{
  "type": "Feature",
  "properties": {
    "addr:full":"7149 Yellowstone Blvd Forest Hills NY 11375",
    "addr:housenumber":"7149",
    "addr:postcode":"11375",
    "addr:street":"Yellowstone Blvd",
    "iso:country":"US",
    "sg:address":"7149 Yellowstone Blvd",
    "sg:city":"Forest Hills",
    "sg:classifiers":[
        {
            "category":"Personal",
            "subcategory":"Barber",
            "type":"Services"
        }
    ],
    "sg:phone":"+1 718 268 4675",
    "sg:postcode":"11375",
    "sg:province":"NY",
    "sg:website":"www.primesalon.com",
    "wof:name":"Prime Salon",
    "wof:placetype":"venue"
},
  "geometry": {"coordinates":[-73.854837,40.721283],"type":"Point"}
}