{
  "type": "Feature",
  "properties": {
    "addr:full":"133 E 58th St New York NY 10022",
    "addr:housenumber":"133",
    "addr:postcode":"10022",
    "addr:street":"E 58Th St",
    "iso:country":"US",
    "sg:address":"133 E 58th St",
    "sg:city":"New York",
    "sg:classifiers":[
        {
            "category":"Communications",
            "subcategory":"Film & Video Production",
            "type":"Services"
        }
    ],
    "sg:phone":"+1 212 755 6690",
    "sg:postcode":"10022",
    "sg:province":"NY",
    "sg:tags":[
        "motion"
    ],
    "wof:name":"Foxboro Entertainment Co",
    "wof:placetype":"venue"
},
  "geometry": {"coordinates":[-73.970258,40.762288],"type":"Point"}
}