{
  "type": "Feature",
  "properties": {
    "addr:full":"316 Main St Cornwall NY 12518",
    "addr:housenumber":"316",
    "addr:postcode":"12518",
    "addr:street":"Main St",
    "iso:country":"US",
    "sg:address":"316 Main St",
    "sg:city":"Cornwall",
    "sg:classifiers":[
        {
            "category":"Retail",
            "subcategory":"Repair Shop",
            "type":"Services"
        }
    ],
    "sg:phone":"+1 845 534 9677",
    "sg:postcode":"12518",
    "sg:province":"NY",
    "sg:tags":[
        "clocks",
        "parts"
    ],
    "wof:name":"Cornwall Clock Shop",
    "wof:placetype":"venue"
},
  "geometry": {"coordinates":[-74.034881,41.434993],"type":"Point"}
}