{
  "type": "Feature",
  "properties": {
    "iso:country":"US",
    "sg:address":"1 Kiefer Ct",
    "sg:city":"Stony Point",
    "sg:classifiers":[
        {
            "category":"Wholesale",
            "subcategory":"Hardware",
            "type":"Manufacturing & Wholesale Goods"
        }
    ],
    "sg:phone":"+1 845 429 5554",
    "sg:postcode":"10980",
    "sg:province":"NY",
    "sg:tags":[
        "plumbing",
        "c"
    ],
    "wof:name":"Patriot Burners",
    "wof:placetype":"venue"
},
  "geometry": {"coordinates":[-74.000044,41.239176],"type":"Point"}
}