{
  "type": "Feature",
  "properties": {
    "iso:country":"US",
    "sg:address":"139 Flatbush Ave",
    "sg:city":"Brooklyn",
    "sg:classifiers":[
        {
            "category":"Shopping",
            "subcategory":"Clothing, Apparel, & Fashions",
            "type":"Retail Goods"
        }
    ],
    "sg:postcode":"11217",
    "sg:province":"NY",
    "sg:tags":[
        "maternity",
        "wear"
    ],
    "wof:name":"Motherhood Maternity",
    "wof:placetype":"venue"
},
  "geometry": {"coordinates":[-73.977721,40.684429],"type":"Point"}
}