{
  "type": "Feature",
  "properties": {
    "iso:country":"US",
    "sg:address":"9733 Savage Rd",
    "sg:city":"Holland",
    "sg:classifiers":[
        {
            "category":"Professional",
            "subcategory":"Computer Services",
            "type":"Services"
        }
    ],
    "sg:phone":"+1   ",
    "sg:postcode":"14080",
    "sg:province":"NY",
    "sg:tags":[
        "communications",
        "datum",
        "telephone"
    ],
    "wof:name":"Blazingsky Technologies",
    "wof:placetype":"venue"
},
  "geometry": {"coordinates":[-78.53053,42.613944],"type":"Point"}
}