{
  "type": "Feature",
  "properties": {
    "addr:full":"5 Coates Ave N Ronkonkoma NY 11779",
    "addr:housenumber":"5",
    "addr:postcode":"11779",
    "addr:street":"Coates Ave N",
    "iso:country":"US",
    "sg:address":"5 Coates Ave N",
    "sg:city":"Ronkonkoma",
    "sg:classifiers":[
        {
            "category":"Building & Trades",
            "subcategory":"Plumbing",
            "type":"Services"
        }
    ],
    "sg:phone":"+1 631 467 1570",
    "sg:postcode":"11779",
    "sg:province":"NY",
    "sg:tags":[
        "conditioning",
        "air",
        "system",
        "contractor"
    ],
    "wof:name":"Comfort Zone Inc",
    "wof:placetype":"venue"
},
  "geometry": {"coordinates":[-73.084318,40.830019],"type":"Point"}
}