{
  "type": "Feature",
  "properties": {
    "addr:full":"12 Silver Hollow Rd Chichester NY 12416",
    "addr:housenumber":"12",
    "addr:postcode":"12416",
    "addr:street":"Silver Hollow Rd",
    "iso:country":"US",
    "sg:address":"12 Silver Hollow Rd",
    "sg:city":"Chichester",
    "sg:classifiers":[
        {
            "category":"Building & Trades",
            "subcategory":"Plumbing",
            "type":"Services"
        }
    ],
    "sg:phone":"+1 845 688 7139",
    "sg:postcode":"12416",
    "sg:province":"NY",
    "sg:tags":[
        "contractor"
    ],
    "wof:name":"F R Plumbing & Heating",
    "wof:placetype":"venue"
},
  "geometry": {"coordinates":[-74.299503,42.101089],"type":"Point"}
}