{
  "type": "Feature",
  "properties": {
    "iso:country":"US",
    "sg:address":"2405 Westchester Ave Frnt",
    "sg:city":"Bronx",
    "sg:classifiers":[
        {
            "category":"Retail",
            "subcategory":"Laundry & Dry Cleaning",
            "type":"Services"
        }
    ],
    "sg:phone":"+1 718 597 0005",
    "sg:postcode":"10461",
    "sg:province":"NY",
    "wof:name":"Classical Cleaners of New York",
    "wof:placetype":"venue"
},
  "geometry": {"coordinates":[-73.84610000000001,40.837299],"type":"Point"}
}