{
  "type": "Feature",
  "properties": {
    "addr:full":"2957 Harlem Rd Cheektowaga NY 14225",
    "addr:housenumber":"2957",
    "addr:postcode":"14225",
    "addr:street":"Harlem Rd",
    "iso:country":"US",
    "sg:address":"2957 Harlem Rd",
    "sg:city":"Cheektowaga",
    "sg:classifiers":[
        {
            "category":"Organizations",
            "subcategory":"Religious Organization",
            "type":"Services"
        }
    ],
    "sg:phone":"+1 716 892 1670",
    "sg:postcode":"14225",
    "sg:province":"NY",
    "sg:tags":[
        "church"
    ],
    "wof:name":"Mt Calvary Cemetery",
    "wof:placetype":"venue"
},
  "geometry": {"coordinates":[-78.784144,42.924964],"type":"Point"}
}