{
  "type": "Feature",
  "properties": {
    "addr:full":"150 Sunnyside Blvd Plainview NY 11803",
    "addr:housenumber":"150",
    "addr:postcode":"11803",
    "addr:street":"Sunnyside Blvd",
    "iso:country":"US",
    "sg:address":"150 Sunnyside Blvd",
    "sg:city":"Plainview",
    "sg:classifiers":[
        {
            "category":"Social Services",
            "subcategory":"Adult Care",
            "type":"Services"
        }
    ],
    "sg:phone":"+1 516 576 3330",
    "sg:postcode":"11803",
    "sg:province":"NY",
    "sg:tags":[
        "home",
        "residential"
    ],
    "sg:website":"www.chelseaseniorliving.com",
    "wof:name":"Somerset Gardens",
    "wof:placetype":"venue"
},
  "geometry": {"coordinates":[-73.469022,40.794752],"type":"Point"}
}