{
  "type": "Feature",
  "properties": {
    "iso:country":"US",
    "sg:address":"1 E Main St",
    "sg:city":"Oyster Bay",
    "sg:classifiers":[
        {
            "category":"Restaurant",
            "type":"Food & Drink"
        }
    ],
    "sg:phone":"+1 516 922 4690",
    "sg:postcode":"11771",
    "sg:province":"NY",
    "wof:name":"Wild Honey",
    "wof:placetype":"venue"
},
  "geometry": {"coordinates":[-73.529178,40.872312],"type":"Point"}
}