{
  "type": "Feature",
  "properties": {
    "addr:full":"300 Pearl St Ste 275 Buffalo NY 14202",
    "addr:housenumber":"300",
    "addr:postcode":"14202",
    "addr:street":"Pearl St Ste 275",
    "iso:country":"US",
    "sg:address":"300 Pearl St Ste 275",
    "sg:city":"Buffalo",
    "sg:classifiers":[
        {
            "category":"Real Estate",
            "subcategory":"Architect",
            "type":"Services"
        }
    ],
    "sg:phone":"+1 716 842 3165",
    "sg:postcode":"14202",
    "sg:province":"NY",
    "wof:name":"Carmina & Wood PC Architecture & Engineering",
    "wof:placetype":"venue"
},
  "geometry": {"coordinates":[-78.875,42.8876],"type":"Point"}
}