{
  "type": "Feature",
  "properties": {
    "iso:country":"US",
    "sg:address":"23 Fall Meadow Dr",
    "sg:city":"Pittsford",
    "sg:classifiers":[
        {
            "category":"Wholesale",
            "subcategory":"Durable Goods & Equipment",
            "type":"Manufacturing & Wholesale Goods"
        }
    ],
    "sg:phone":"+1 585 586 9000",
    "sg:postcode":"14534",
    "sg:province":"NY",
    "sg:tags":[
        "representative",
        "manufacturer"
    ],
    "wof:name":"Manufactures Representatives",
    "wof:placetype":"venue"
},
  "geometry": {"coordinates":[-77.493143,43.040428],"type":"Point"}
}