{
  "type": "Feature",
  "properties": {
    "addr:full":"9 Monroe St Ellicottville NY 14731",
    "addr:housenumber":"9",
    "addr:postcode":"14731",
    "addr:street":"Monroe St",
    "iso:country":"US",
    "sg:address":"9 Monroe St",
    "sg:city":"Ellicottville",
    "sg:classifiers":[
        {
            "category":"Real Estate",
            "subcategory":"Real Estate Agent",
            "type":"Services"
        }
    ],
    "sg:phone":"+1 716 699 6990",
    "sg:postcode":"14731",
    "sg:province":"NY",
    "sg:tags":[
        "management"
    ],
    "wof:name":"Ellicottville Concierge",
    "wof:placetype":"venue"
},
  "geometry": {"coordinates":[-78.671639,42.275993],"type":"Point"}
}