{
  "type": "Feature",
  "properties": {
    "addr:full":"1748 Brooklyn Ave Brooklyn NY 11210",
    "addr:housenumber":"1748",
    "addr:postcode":"11210",
    "addr:street":"Brooklyn Ave",
    "iso:country":"US",
    "sg:address":"1748 Brooklyn Ave",
    "sg:city":"Brooklyn",
    "sg:classifiers":[
        {
            "category":"Freight",
            "type":"Transportation"
        }
    ],
    "sg:phone":"+1 718 677 3850",
    "sg:postcode":"11210",
    "sg:province":"NY",
    "sg:tags":[
        "shipping",
        "agent",
        "arrangement"
    ],
    "wof:name":"Caribbean Express",
    "wof:placetype":"venue"
},
  "geometry": {"coordinates":[-73.94154899999999,40.630165],"type":"Point"}
}