{
  "type": "Feature",
  "properties": {
    "iso:country":"US",
    "sg:address":"2217 Monroe Ave",
    "sg:city":"Rochester",
    "sg:classifiers":[
        {
            "category":"Personal",
            "subcategory":"Beauty Salon",
            "type":"Services"
        }
    ],
    "sg:phone":"+1 585 244 1131",
    "sg:postcode":"14618",
    "sg:province":"NY",
    "wof:name":"Tress Hair Salon",
    "wof:placetype":"venue"
},
  "geometry": {"coordinates":[-77.56057800000001,43.122827],"type":"Point"}
}