{
  "type": "Feature",
  "properties": {
    "iso:country":"US",
    "sg:address":"5 Riverview Ave",
    "sg:city":"New Windsor",
    "sg:classifiers":[
        {
            "category":"Real Estate",
            "subcategory":"Surveying",
            "type":"Services"
        }
    ],
    "sg:phone":"+1 845 562 4873",
    "sg:postcode":"12553",
    "sg:province":"NY",
    "sg:tags":[
        "surveyor"
    ],
    "wof:name":"Patrick T Kennedy",
    "wof:placetype":"venue"
},
  "geometry": {"coordinates":[-74.01839699999999,41.477553],"type":"Point"}
}