{
  "type": "Feature",
  "properties": {
    "iso:country":"US",
    "sg:address":"5524 5th Ave",
    "sg:city":"Brooklyn",
    "sg:classifiers":[
        {
            "category":"Professional",
            "type":"Services"
        }
    ],
    "sg:phone":"+1 718 439 3334",
    "sg:postcode":"11220",
    "sg:province":"NY",
    "sg:tags":[
        "establishment"
    ],
    "wof:name":"Sneaker Expo",
    "wof:placetype":"venue"
},
  "geometry": {"coordinates":[-74.01376500000001,40.641929],"type":"Point"}
}