{
  "type": "Feature",
  "properties": {
    "iso:country":"US",
    "sg:address":"107 Concord Pl",
    "sg:city":"Fayetteville",
    "sg:classifiers":[
        {
            "category":"Professional",
            "subcategory":"Engineering",
            "type":"Services"
        }
    ],
    "sg:phone":"+1 315 637 9841",
    "sg:postcode":"13066",
    "sg:province":"NY",
    "sg:tags":[
        "engineer"
    ],
    "sg:website":"www.iesolutions.com",
    "wof:name":"Interactive Engineering",
    "wof:placetype":"venue"
},
  "geometry": {"coordinates":[-75.996132,43.025698],"type":"Point"}
}