{
  "type": "Feature",
  "properties": {
    "addr:full":"140 Meadow Ln Davenport NY 13750",
    "addr:housenumber":"140",
    "addr:postcode":"13750",
    "addr:street":"Meadow Ln",
    "iso:country":"US",
    "sg:address":"140 Meadow Ln",
    "sg:city":"Davenport",
    "sg:classifiers":[
        {
            "category":"Shopping",
            "subcategory":"Jewelry",
            "type":"Retail Goods"
        }
    ],
    "sg:phone":"+1 607 278 6819",
    "sg:postcode":"13750",
    "sg:province":"NY",
    "sg:tags":[
        "precious",
        "semi-precious",
        "stone"
    ],
    "wof:name":"Jewels By Park Lane",
    "wof:placetype":"venue"
},
  "geometry": {"coordinates":[-74.782652,42.462635],"type":"Point"}
}