{
  "type": "Feature",
  "properties": {
    "addr:full":"15 E Main St Brocton NY 14716",
    "addr:housenumber":"15",
    "addr:postcode":"14716",
    "addr:street":"E Main St",
    "iso:country":"US",
    "sg:address":"15 E Main St",
    "sg:city":"Brocton",
    "sg:classifiers":[
        {
            "category":"Shopping",
            "subcategory":"Gifts & Souvenirs",
            "type":"Retail Goods"
        }
    ],
    "sg:phone":"+1   ",
    "sg:postcode":"14716",
    "sg:province":"NY",
    "wof:name":"Triple Crown Sports Cards",
    "wof:placetype":"venue"
},
  "geometry": {"coordinates":[-79.438782,42.3893],"type":"Point"}
}