{
  "type": "Feature",
  "properties": {
    "addr:full":"615 Union Ave Westbury NY 11590",
    "addr:housenumber":"615",
    "addr:postcode":"11590",
    "addr:street":"Union Ave",
    "iso:country":"US",
    "sg:address":"615 Union Ave",
    "sg:city":"Westbury",
    "sg:classifiers":[
        {
            "category":"Autos & Motor Vehicles",
            "subcategory":"Fuel & Gas Station",
            "type":"Retail Goods"
        }
    ],
    "sg:phone":"+1 516 876 8263",
    "sg:postcode":"11590",
    "sg:province":"NY",
    "wof:name":"Amoco Service Station",
    "wof:placetype":"venue"
},
  "geometry": {"coordinates":[-73.577499,40.759499],"type":"Point"}
}