{
  "type": "Feature",
  "properties": {
    "iso:country":"US",
    "sg:address":"601 W Broadway",
    "sg:city":"Fulton",
    "sg:classifiers":[
        {
            "category":"Restaurant",
            "type":"Food & Drink"
        }
    ],
    "sg:phone":"+1 315 593 1595",
    "sg:postcode":"13069",
    "sg:province":"NY",
    "wof:name":"Dial For Wings",
    "wof:placetype":"venue"
},
  "geometry": {"coordinates":[-76.424284,43.314174],"type":"Point"}
}