{
  "type": "Feature",
  "properties": {
    "iso:country":"US",
    "sg:address":"740 Erie Blvd E",
    "sg:city":"Syracuse",
    "sg:classifiers":[
        {
            "category":"Retail",
            "subcategory":"Auto Rental",
            "type":"Services"
        }
    ],
    "sg:phone":"+1 315 424 0633",
    "sg:postcode":"13210",
    "sg:province":"NY",
    "sg:tags":[
        "truck",
        "trailer",
        "utility"
    ],
    "wof:name":"U-Haul",
    "wof:placetype":"venue"
},
  "geometry": {"coordinates":[-76.141412,43.050644],"type":"Point"}
}