{
  "type": "Feature",
  "properties": {
    "iso:country":"US",
    "sg:address":"56 Washington Pkwy",
    "sg:city":"Hicksville",
    "sg:classifiers":[
        {
            "category":"Home & Garden",
            "subcategory":"Building Materials",
            "type":"Retail Goods"
        },
        {
            "category":"Building & Trades",
            "subcategory":"Construction",
            "type":"Services"
        }
    ],
    "sg:phone":"+1 516 933 7426",
    "sg:postcode":"11801",
    "sg:province":"NY",
    "sg:tags":[
        "cabinet",
        "contractor",
        "maker",
        "carpentry"
    ],
    "wof:name":"Giuseppe Cabinets Inc",
    "wof:placetype":"venue"
},
  "geometry": {"coordinates":[-73.503204,40.750382],"type":"Point"}
}