{
  "type": "Feature",
  "properties": {
    "iso:country":"US",
    "sg:address":"247 Middaugh Rd",
    "sg:city":"Brooktondale",
    "sg:classifiers":[
        {
            "category":"Wholesale",
            "subcategory":"Electrical",
            "type":"Manufacturing & Wholesale Goods"
        }
    ],
    "sg:phone":"+1 607 256 3640",
    "sg:postcode":"14817",
    "sg:province":"NY",
    "sg:tags":[
        "lighting",
        "fixture"
    ],
    "sg:website":"www.donovanlighting.com",
    "wof:name":"Donovan Lighting",
    "wof:placetype":"venue"
},
  "geometry": {"coordinates":[-76.414449,42.372725],"type":"Point"}
}