{
  "type": "Feature",
  "properties": {
    "addr:full":"1514 Outlet Rd Penn Yan NY 14527",
    "addr:housenumber":"1514",
    "addr:postcode":"14527",
    "addr:street":"Outlet Rd",
    "iso:country":"US",
    "sg:address":"1514 Outlet Rd",
    "sg:city":"Penn Yan",
    "sg:classifiers":[
        {
            "category":"Food & Beverages",
            "subcategory":"Dairy",
            "type":"Retail Goods"
        }
    ],
    "sg:phone":"+1 315 536 3340",
    "sg:postcode":"14527",
    "sg:province":"NY",
    "sg:tags":[
        "product"
    ],
    "wof:name":"Lepp's Goat Enterprises",
    "wof:placetype":"venue"
},
  "geometry": {"coordinates":[-77.00637,42.660619],"type":"Point"}
}