{
  "type": "Feature",
  "properties": {
    "addr:full":"176 Main St Islip NY 11751",
    "addr:housenumber":"176",
    "addr:postcode":"11751",
    "addr:street":"Main St",
    "iso:country":"US",
    "sg:address":"176 Main St",
    "sg:city":"Islip",
    "sg:classifiers":[
        {
            "category":"Restaurant",
            "type":"Food & Drink"
        }
    ],
    "sg:phone":"+1 631 581 9888",
    "sg:postcode":"11751",
    "sg:province":"NY",
    "wof:name":"Viking Restaurant",
    "wof:placetype":"venue"
},
  "geometry": {"coordinates":[-73.221001,40.727798],"type":"Point"}
}