{
  "type": "Feature",
  "properties": {
    "addr:full":"1409 W Genesee St Syracuse NY 13204",
    "addr:housenumber":"1409",
    "addr:postcode":"13204",
    "addr:street":"W Genesee St",
    "iso:country":"US",
    "sg:address":"1409 W Genesee St",
    "sg:city":"Syracuse",
    "sg:classifiers":[
        {
            "category":"Personal",
            "subcategory":"Beauty Salon",
            "type":"Services"
        }
    ],
    "sg:phone":"+1 315 425 8969",
    "sg:postcode":"13204",
    "sg:province":"NY",
    "wof:name":"Hair Razors",
    "wof:placetype":"venue"
},
  "geometry": {"coordinates":[-76.180654,43.052306],"type":"Point"}
}