{
  "type": "Feature",
  "properties": {
    "iso:country":"US",
    "sg:address":"4 Randolph St",
    "sg:city":"Yonkers",
    "sg:classifiers":[
        {
            "category":"Personal",
            "subcategory":"Barber",
            "type":"Services"
        }
    ],
    "sg:phone":"+1 914 965 0165",
    "sg:postcode":"10705",
    "sg:province":"NY",
    "wof:name":"Spot",
    "wof:placetype":"venue"
},
  "geometry": {"coordinates":[-73.895709,40.917932],"type":"Point"}
}