{
  "type": "Feature",
  "properties": {
    "addr:full":"77 Cornell St Kingston NY 12401",
    "addr:housenumber":"77",
    "addr:postcode":"12401",
    "addr:street":"Cornell St",
    "iso:country":"US",
    "sg:address":"77 Cornell St",
    "sg:city":"Kingston",
    "sg:classifiers":[
        {
            "category":"Manufacturing",
            "subcategory":"Electronics",
            "type":"Manufacturing & Wholesale Goods"
        }
    ],
    "sg:phone":"+1 845 334 8108",
    "sg:postcode":"12401",
    "sg:province":"NY",
    "sg:tags":[
        "printed",
        "circuit",
        "etched"
    ],
    "wof:name":"Qdp Electronics Assembly",
    "wof:placetype":"venue"
},
  "geometry": {"coordinates":[-74.000913,41.931706],"type":"Point"}
}