{
  "type": "Feature",
  "properties": {
    "iso:country":"US",
    "sg:address":"63 Cannon St",
    "sg:city":"Poughkeepsie",
    "sg:classifiers":[
        {
            "category":"Personal",
            "subcategory":"Beauty Salon",
            "type":"Services"
        }
    ],
    "sg:phone":"+1 845 471 0369",
    "sg:postcode":"12601",
    "sg:province":"NY",
    "wof:name":"Unique Hair Boutique",
    "wof:placetype":"venue"
},
  "geometry": {"coordinates":[-73.92728700000001,41.702191],"type":"Point"}
}