{
  "type": "Feature",
  "properties": {
    "addr:full":"55 W 57 St New York NY 10019",
    "addr:housenumber":"55",
    "addr:postcode":"10019",
    "addr:street":"W 57 St",
    "iso:country":"US",
    "sg:address":"55 W 57 St",
    "sg:city":"New York",
    "sg:classifiers":[
        {
            "category":"Shopping",
            "subcategory":"Computers & Home Electronics",
            "type":"Retail Goods"
        }
    ],
    "sg:phone":"+1 718 934 9303",
    "sg:postcode":"10019",
    "sg:province":"NY",
    "sg:tags":[
        "equipment",
        "dealer"
    ],
    "wof:name":"Dibs Computer Forensics Inc",
    "wof:placetype":"venue"
},
  "geometry": {"coordinates":[-73.975812,40.763641],"type":"Point"}
}