{
  "type": "Feature",
  "properties": {
    "iso:country":"US",
    "sg:address":"390 Clay Pitts Rd",
    "sg:city":"East Northport",
    "sg:classifiers":[
        {
            "category":"Professional",
            "subcategory":"Business Services",
            "type":"Services"
        }
    ],
    "sg:phone":"+1   ",
    "sg:postcode":"11731",
    "sg:province":"NY",
    "wof:name":"Rochlen Enterprises Inc",
    "wof:placetype":"venue"
},
  "geometry": {"coordinates":[-73.3022,40.867871],"type":"Point"}
}