{
  "type": "Feature",
  "properties": {
    "addr:full":"459 Lyell Ave Rochester NY 14606",
    "addr:housenumber":"459",
    "addr:postcode":"14606",
    "addr:street":"Lyell Ave",
    "iso:country":"US",
    "sg:address":"459 Lyell Ave",
    "sg:city":"Rochester",
    "sg:classifiers":[
        {
            "category":"Home & Garden",
            "subcategory":"Furniture",
            "type":"Retail Goods"
        }
    ],
    "sg:phone":"+1 585 719 9880",
    "sg:postcode":"14606",
    "sg:province":"NY",
    "sg:tags":[
        "bedding"
    ],
    "wof:name":"Markson's Sleep Ctr Inc",
    "wof:placetype":"venue"
},
  "geometry": {"coordinates":[-77.63936,43.164561],"type":"Point"}
}