{
  "type": "Feature",
  "properties": {
    "iso:country":"US",
    "sg:address":"322 7th Ave",
    "sg:city":"Pelham",
    "sg:classifiers":[
        {
            "category":"Building & Trades",
            "subcategory":"Electrical",
            "type":"Services"
        }
    ],
    "sg:phone":"+1 914 738 9544",
    "sg:postcode":"10803",
    "sg:province":"NY",
    "sg:tags":[
        "electrical",
        "contractor"
    ],
    "wof:name":"Aj Electric of Westcheste",
    "wof:placetype":"venue"
},
  "geometry": {"coordinates":[-73.804186,40.917748],"type":"Point"}
}