{
  "type": "Feature",
  "properties": {
    "iso:country":"US",
    "sg:address":"79 Yonkers Ave",
    "sg:city":"Yonkers",
    "sg:classifiers":[
        {
            "category":"Travel",
            "subcategory":"Travel Agent",
            "type":"Entertainment"
        }
    ],
    "sg:phone":"+1   ",
    "sg:postcode":"10701",
    "sg:province":"NY",
    "sg:tags":[
        "operator",
        "tour"
    ],
    "wof:name":"Moderne Travel Service",
    "wof:placetype":"venue"
},
  "geometry": {"coordinates":[-73.88679999999999,40.935347],"type":"Point"}
}