{
  "type": "Feature",
  "properties": {
    "iso:country":"US",
    "sg:address":"250 Old E Neck Rd",
    "sg:city":"Melville",
    "sg:classifiers":[
        {
            "category":"Education",
            "subcategory":"School",
            "type":"Public Place"
        }
    ],
    "sg:phone":"+1 516 420 1710",
    "sg:postcode":"11747",
    "sg:province":"NY",
    "wof:name":"Half Hollow Hills School Dist",
    "wof:placetype":"venue"
},
  "geometry": {"coordinates":[-73.403907,40.77387],"type":"Point"}
}