{
  "type": "Feature",
  "properties": {
    "iso:country":"US",
    "sg:address":"200 5th Ave",
    "sg:city":"New York",
    "sg:classifiers":[
        {
            "category":"Professional",
            "subcategory":"Management & Consulting",
            "type":"Services"
        }
    ],
    "sg:phone":"+1 212 647 8500",
    "sg:postcode":"10010",
    "sg:province":"NY",
    "sg:tags":[
        "marketing",
        "consultant"
    ],
    "sg:website":"www.byrnecom.com",
    "wof:name":"Byrne Communications Inc",
    "wof:placetype":"venue"
},
  "geometry": {"coordinates":[-73.989532,40.741642],"type":"Point"}
}