{
  "type": "Feature",
  "properties": {
    "addr:full":"508 E 120th Street New York NY 10035",
    "addr:housenumber":"508",
    "addr:postcode":"10035",
    "addr:street":"E 120Th Street",
    "iso:country":"US",
    "sg:address":"508 E 120th Street",
    "sg:city":"New York",
    "sg:classifiers":[
        {
            "category":"Education",
            "subcategory":"School",
            "type":"Public Place"
        }
    ],
    "sg:phone":"+1 212 860 5809",
    "sg:postcode":"10035",
    "sg:province":"NY",
    "sg:tags":[
        "high",
        "middle",
        "elementary"
    ],
    "wof:name":"N Y City of",
    "wof:placetype":"venue"
},
  "geometry": {"coordinates":[-73.930824,40.797311],"type":"Point"}
}