{
  "type": "Feature",
  "properties": {
    "iso:country":"US",
    "sg:address":"106 E Bayard St",
    "sg:city":"Seneca Falls",
    "sg:classifiers":[
        {
            "category":"Wholesale",
            "subcategory":"Non-durable Goods",
            "type":"Manufacturing & Wholesale Goods"
        }
    ],
    "sg:phone":"+1 315 568 5479",
    "sg:postcode":"13148",
    "sg:province":"NY",
    "wof:name":"Birdsong of Fingerlake",
    "wof:placetype":"venue"
},
  "geometry": {"coordinates":[-76.787125,42.910063],"type":"Point"}
}