{
  "type": "Feature",
  "properties": {
    "iso:country":"US",
    "sg:address":"178 Prince St",
    "sg:city":"New York",
    "sg:classifiers":[
        {
            "category":"Shopping",
            "subcategory":"Clothing, Apparel, & Fashions",
            "type":"Retail Goods"
        }
    ],
    "sg:phone":"+1   ",
    "sg:postcode":"10012",
    "sg:province":"NY",
    "wof:name":"Gordon Clothes",
    "wof:placetype":"venue"
},
  "geometry": {"coordinates":[-74.002106,40.726245],"type":"Point"}
}