{
  "type": "Feature",
  "properties": {
    "iso:country":"US",
    "sg:address":"116 Higby Rd",
    "sg:city":"Utica",
    "sg:classifiers":[
        {
            "category":"Building & Trades",
            "subcategory":"Construction",
            "type":"Services"
        }
    ],
    "sg:phone":"+1 315 724 3430",
    "sg:postcode":"13501",
    "sg:province":"NY",
    "sg:tags":[
        "painter"
    ],
    "wof:name":"Sexton Painting Co LLC",
    "wof:placetype":"venue"
},
  "geometry": {"coordinates":[-75.274458,43.070882],"type":"Point"}
}