{
  "type": "Feature",
  "properties": {
    "addr:full":"14 Stillman Rd Glen Cove NY 11542",
    "addr:housenumber":"14",
    "addr:postcode":"11542",
    "addr:street":"Stillman Rd",
    "iso:country":"US",
    "sg:address":"14 Stillman Rd",
    "sg:city":"Glen Cove",
    "sg:classifiers":[
        {
            "category":"Professional",
            "subcategory":"Advertising",
            "type":"Services"
        }
    ],
    "sg:phone":"+1 516 656 0958",
    "sg:postcode":"11542",
    "sg:province":"NY",
    "sg:tags":[
        "medium",
        "buying"
    ],
    "wof:name":"Mundy Katowitz Media Inc",
    "wof:placetype":"venue"
},
  "geometry": {"coordinates":[-73.603891,40.858572],"type":"Point"}
}