{
  "type": "Feature",
  "properties": {
    "addr:full":"2928 Ave P Brooklyn NY 11229",
    "addr:housenumber":"2928",
    "addr:postcode":"11229",
    "addr:street":"Ave P",
    "iso:country":"US",
    "sg:address":"2928 Ave P",
    "sg:city":"Brooklyn",
    "sg:classifiers":[
        {
            "category":"Retail",
            "subcategory":"Laundry & Dry Cleaning",
            "type":"Services"
        }
    ],
    "sg:phone":"+1 718 382 8619",
    "sg:postcode":"11229",
    "sg:province":"NY",
    "wof:name":"Double Bubble Laundromat",
    "wof:placetype":"venue"
},
  "geometry": {"coordinates":[-73.943786,40.612829],"type":"Point"}
}