{
  "type": "Feature",
  "properties": {
    "iso:country":"US",
    "sg:address":"37 W 65th St",
    "sg:city":"New York",
    "sg:classifiers":[
        {
            "category":"Sports & Exercise",
            "subcategory":"Gym",
            "type":"Entertainment"
        }
    ],
    "sg:phone":"+1 212 769 9642",
    "sg:postcode":"10023",
    "sg:province":"NY",
    "sg:tags":[
        "yoga"
    ],
    "wof:name":"Karma Yoga Pilates",
    "wof:placetype":"venue"
},
  "geometry": {"coordinates":[-73.98127100000001,40.772648],"type":"Point"}
}