{
  "type": "Feature",
  "properties": {
    "iso:country":"US",
    "sg:address":"47 Main St",
    "sg:city":"Hoosick Falls",
    "sg:classifiers":[
        {
            "category":"Banks & Credit Unions",
            "subcategory":"Bank",
            "type":"Services"
        }
    ],
    "sg:phone":"+1 518 686 5352",
    "sg:postcode":"12090",
    "sg:province":"NY",
    "wof:name":"Trustco Bank",
    "wof:placetype":"venue"
},
  "geometry": {"coordinates":[-73.35065899999999,42.900447],"type":"Point"}
}