{
  "type": "Feature",
  "properties": {
    "iso:country":"US",
    "sg:address":"412 Canal St",
    "sg:city":"Rome",
    "sg:classifiers":[
        {
            "category":"Manufacturing",
            "subcategory":"Metals",
            "type":"Manufacturing & Wholesale Goods"
        }
    ],
    "sg:phone":"+1   ",
    "sg:postcode":"13440",
    "sg:province":"NY",
    "sg:tags":[
        "steel",
        "fabricator",
        "structural"
    ],
    "wof:name":"Raulli & Sons",
    "wof:placetype":"venue"
},
  "geometry": {"coordinates":[-75.45678599999999,43.204578],"type":"Point"}
}