{
  "type": "Feature",
  "properties": {
    "addr:full":"71 Albany Ave Kingston NY 12401",
    "addr:housenumber":"71",
    "addr:postcode":"12401",
    "addr:street":"Albany Ave",
    "iso:country":"US",
    "sg:address":"71 Albany Ave",
    "sg:city":"Kingston",
    "sg:classifiers":[
        {
            "category":"Insurance",
            "subcategory":"Title Insurance",
            "type":"Services"
        }
    ],
    "sg:phone":"+1 845 331 8612",
    "sg:postcode":"12401",
    "sg:province":"NY",
    "wof:name":"Title Service Company",
    "wof:placetype":"venue"
},
  "geometry": {"coordinates":[-74.012444,41.932549],"type":"Point"}
}