{
  "type": "Feature",
  "properties": {
    "iso:country":"US",
    "sg:address":"547 Larkfield Rd",
    "sg:city":"East Northport",
    "sg:classifiers":[
        {
            "category":"Organizations",
            "subcategory":"Religious Organization",
            "type":"Services"
        }
    ],
    "sg:phone":"+1 631 368 5880",
    "sg:postcode":"11731",
    "sg:province":"NY",
    "sg:tags":[
        "church"
    ],
    "wof:name":"Young Israel Of East Northport",
    "wof:placetype":"venue"
},
  "geometry": {"coordinates":[-73.318646,40.856808],"type":"Point"}
}