{
  "type": "Feature",
  "properties": {
    "addr:full":"120 W 106th St New York NY 10025",
    "addr:housenumber":"120",
    "addr:postcode":"10025",
    "addr:street":"W 106Th St",
    "iso:country":"US",
    "sg:address":"120 W 106th St",
    "sg:city":"New York",
    "sg:classifiers":[
        {
            "category":"Retail",
            "subcategory":"Repair Shop",
            "type":"Services"
        }
    ],
    "sg:phone":"+1 646 224 9284",
    "sg:postcode":"10025",
    "sg:province":"NY",
    "sg:tags":[
        "lock",
        "locksmith"
    ],
    "wof:name":"Locksmith",
    "wof:placetype":"venue"
},
  "geometry": {"coordinates":[-73.96530799999999,40.800126],"type":"Point"}
}