{
  "type": "Feature",
  "properties": {
    "addr:full":"712 Jericho Tpke Huntington Station NY 11746",
    "addr:housenumber":"712",
    "addr:postcode":"11746",
    "addr:street":"Jericho Tpke Huntington",
    "iso:country":"US",
    "sg:address":"712 Jericho Tpke",
    "sg:city":"Huntington Station",
    "sg:classifiers":[
        {
            "category":"Professional",
            "subcategory":"Accounting & Tax Preparation",
            "type":"Services"
        }
    ],
    "sg:phone":"+1 631 385 3137",
    "sg:postcode":"11746",
    "sg:province":"NY",
    "sg:tags":[
        "return",
        "filing"
    ],
    "wof:name":"Gold Tax Professionals",
    "wof:placetype":"venue"
},
  "geometry": {"coordinates":[-73.382149,40.834439],"type":"Point"}
}