{
  "type": "Feature",
  "properties": {
    "addr:full":"136 E 39 St New York NY 10016",
    "addr:housenumber":"136;39",
    "addr:postcode":"10016",
    "addr:street":"E;St",
    "iso:country":"US",
    "sg:address":"136 E 39 St",
    "sg:city":"New York",
    "sg:classifiers":[
        {
            "category":"Professional",
            "subcategory":"Management & Consulting",
            "type":"Services"
        }
    ],
    "sg:phone":"+1 212 679 1505",
    "sg:postcode":"10016",
    "sg:province":"NY",
    "wof:name":"Records Management Institute",
    "wof:placetype":"venue"
},
  "geometry": {"coordinates":[-73.975945,40.748838],"type":"Point"}
}