{
  "type": "Feature",
  "properties": {
    "iso:country":"US",
    "sg:address":"26 Old Grange Rd",
    "sg:city":"Hopewell Junction",
    "sg:classifiers":[
        {
            "category":"Professional",
            "subcategory":"Accounting & Tax Preparation",
            "type":"Services"
        }
    ],
    "sg:phone":"+1   ",
    "sg:postcode":"12533",
    "sg:province":"NY",
    "wof:name":"Rossi & Sons",
    "wof:placetype":"venue"
},
  "geometry": {"coordinates":[-73.86069500000001,41.542691],"type":"Point"}
}