{
  "type": "Feature",
  "properties": {
    "addr:full":"99 Bay St Bronx NY 10464",
    "addr:housenumber":"99",
    "addr:postcode":"10464",
    "addr:street":"Bay St",
    "iso:country":"US",
    "sg:address":"99 Bay St",
    "sg:city":"Bronx",
    "sg:classifiers":[
        {
            "category":"Organizations",
            "subcategory":"Community Association",
            "type":"Services"
        }
    ],
    "sg:phone":"+1   ",
    "sg:postcode":"10464",
    "sg:province":"NY",
    "wof:name":"Gaia Institute",
    "wof:placetype":"venue"
},
  "geometry": {"coordinates":[-73.78757299999999,40.847727],"type":"Point"}
}