{
  "type": "Feature",
  "properties": {
    "iso:country":"US",
    "sg:address":"490 Dekalb St.",
    "sg:city":"Brooklyn",
    "sg:classifiers":[
        {
            "category":"Restaurant",
            "type":"Food & Drink"
        }
    ],
    "sg:phone":"+1 718 789 3300",
    "sg:postcode":"11205",
    "sg:province":"NY",
    "sg:tags":[
        "mexican"
    ],
    "sg:website":"puntacanacoffeeshopbrooklyn.com",
    "wof:name":"Punta Cana Coffee Shop",
    "wof:placetype":"venue"
},
  "geometry": {"coordinates":[-73.95698899999999,40.690709],"type":"Point"}
}