{
  "type": "Feature",
  "properties": {
    "addr:full":"105 Windwood Rd Syracuse NY 13212",
    "addr:housenumber":"105",
    "addr:postcode":"13212",
    "addr:street":"Windwood Rd",
    "iso:country":"US",
    "sg:address":"105 Windwood Rd",
    "sg:city":"Syracuse",
    "sg:classifiers":[
        {
            "category":"Real Estate",
            "subcategory":"Developer",
            "type":"Services"
        }
    ],
    "sg:phone":"+1 315 458 6867",
    "sg:postcode":"13212",
    "sg:province":"NY",
    "wof:name":"Hafner Developers Inc",
    "wof:placetype":"venue"
},
  "geometry": {"coordinates":[-76.159052,43.131565],"type":"Point"}
}