{
  "type": "Feature",
  "properties": {
    "iso:country":"US",
    "sg:address":"1016 Post Avenue",
    "sg:city":"Staten Island",
    "sg:classifiers":[
        {
            "category":"Banks & Credit Unions",
            "subcategory":"Financial Services",
            "type":"Services"
        }
    ],
    "sg:phone":"+1 718 815 6000",
    "sg:postcode":"10302",
    "sg:province":"NY",
    "sg:tags":[
        "broker",
        "mortgage"
    ],
    "wof:name":"Hds Funding",
    "wof:placetype":"venue"
},
  "geometry": {"coordinates":[-74.134668,40.633283],"type":"Point"}
}