{
  "type": "Feature",
  "properties": {
    "addr:full":"565 Woodward Ave Flushing NY 11385",
    "addr:housenumber":"565",
    "addr:postcode":"11385",
    "addr:street":"Woodward Ave",
    "iso:country":"US",
    "sg:address":"565 Woodward Ave",
    "sg:city":"Flushing",
    "sg:classifiers":[
        {
            "category":"Professional",
            "type":"Services"
        }
    ],
    "sg:phone":"+1 718 326 4341",
    "sg:postcode":"11385",
    "sg:province":"NY",
    "sg:tags":[
        "establishment"
    ],
    "wof:name":"House-Refuge Comm Outreach",
    "wof:placetype":"venue"
},
  "geometry": {"coordinates":[-73.908891,40.706935],"type":"Point"}
}