{
  "type": "Feature",
  "properties": {
    "addr:full":"101 W Main St Canajoharie NY 13317",
    "addr:housenumber":"101",
    "addr:postcode":"13317",
    "addr:street":"W Main St",
    "iso:country":"US",
    "sg:address":"101 W Main St",
    "sg:city":"Canajoharie",
    "sg:classifiers":[
        {
            "category":"Health Services",
            "subcategory":"Doctor",
            "type":"Services"
        }
    ],
    "sg:phone":"+1 518 673 2573",
    "sg:postcode":"13317",
    "sg:province":"NY",
    "sg:tags":[
        "laboratory",
        "medical"
    ],
    "wof:name":"Family Health Center The",
    "wof:placetype":"venue"
},
  "geometry": {"coordinates":[-74.573111,42.906107],"type":"Point"}
}