{
  "type": "Feature",
  "properties": {
    "addr:full":"218 E 89 St New York NY 10128",
    "addr:housenumber":"218;89",
    "addr:postcode":"10128",
    "addr:street":"E",
    "iso:country":"US",
    "sg:address":"218 E 89 St",
    "sg:city":"New York",
    "sg:classifiers":[
        {
            "category":"Retail",
            "subcategory":"Self-service Laundry",
            "type":"Services"
        }
    ],
    "sg:phone":"+1 212 410 4408",
    "sg:postcode":"10128",
    "sg:province":"NY",
    "wof:name":"K K Laundromat & Cleaners",
    "wof:placetype":"venue"
},
  "geometry": {"coordinates":[-73.950684,40.779918],"type":"Point"}
}