{
  "type": "Feature",
  "properties": {
    "iso:country":"US",
    "sg:address":"83 N Central Ave",
    "sg:city":"Mechanicville",
    "sg:classifiers":[
        {
            "category":"Building & Trades",
            "subcategory":"Electrical",
            "type":"Services"
        }
    ],
    "sg:phone":"+1 518 664 7316",
    "sg:postcode":"12118",
    "sg:province":"NY",
    "sg:tags":[
        "contractor",
        "electrical",
        "supply"
    ],
    "wof:name":"C & P Electrical Whl & Ret",
    "wof:placetype":"venue"
},
  "geometry": {"coordinates":[-73.687989,42.905944],"type":"Point"}
}