{
  "type": "Feature",
  "properties": {
    "addr:full":"159 Lexington Ave Brooklyn NY 11216",
    "addr:housenumber":"159",
    "addr:postcode":"11216",
    "addr:street":"Lexington Ave",
    "iso:country":"US",
    "sg:address":"159 Lexington Ave",
    "sg:city":"Brooklyn",
    "sg:classifiers":[
        {
            "category":"Retail",
            "subcategory":"Repair Shop",
            "type":"Services"
        }
    ],
    "sg:phone":"+1 718 398 6244",
    "sg:postcode":"11216",
    "sg:province":"NY",
    "sg:tags":[
        "ironwork"
    ],
    "wof:name":"Kong Wu",
    "wof:placetype":"venue"
},
  "geometry": {"coordinates":[-73.955203,40.687242],"type":"Point"}
}