{
  "type": "Feature",
  "properties": {
    "addr:full":"32 Rogers Ave Brooklyn NY 11216",
    "addr:housenumber":"32",
    "addr:postcode":"11216",
    "addr:street":"Rogers Ave",
    "iso:country":"US",
    "sg:address":"32 Rogers Ave",
    "sg:city":"Brooklyn",
    "sg:classifiers":[
        {
            "category":"Building & Trades",
            "subcategory":"Construction",
            "type":"Services"
        }
    ],
    "sg:phone":"+1 718 857 2966",
    "sg:postcode":"11216",
    "sg:province":"NY",
    "sg:tags":[
        "house"
    ],
    "wof:name":"Tyrone Clarke Company",
    "wof:placetype":"venue"
},
  "geometry": {"coordinates":[-73.952798,40.676007],"type":"Point"}
}