{
  "type": "Feature",
  "properties": {
    "iso:country":"US",
    "sg:address":"4 Daisy Ct",
    "sg:city":"Nanuet",
    "sg:classifiers":[
        {
            "category":"Retail",
            "subcategory":"Portrait Studio",
            "type":"Services"
        }
    ],
    "sg:phone":"+1 845 624 7245",
    "sg:postcode":"10954",
    "sg:province":"NY",
    "sg:tags":[
        "photography"
    ],
    "sg:website":"www.jscollo.com",
    "wof:name":"Joseph Scollo Photography",
    "wof:placetype":"venue"
},
  "geometry": {"coordinates":[-73.995814,41.081562],"type":"Point"}
}