{
  "type": "Feature",
  "properties": {
    "addr:full":"156 Mount Vernon Ave Mt Vernon NY 10550",
    "addr:housenumber":"156",
    "addr:postcode":"10550",
    "addr:street":"Mount Vernon Ave",
    "iso:country":"US",
    "sg:address":"156 Mount Vernon Ave",
    "sg:city":"Mt Vernon",
    "sg:classifiers":[
        {
            "category":"Education",
            "subcategory":"Dance Studio",
            "type":"Public Place"
        }
    ],
    "sg:phone":"+1 914 667 6677",
    "sg:postcode":"10550",
    "sg:province":"NY",
    "sg:tags":[
        "instruction",
        "dancing"
    ],
    "wof:name":"Miss Dorothy's Creative Dance",
    "wof:placetype":"venue"
},
  "geometry": {"coordinates":[-73.849914,40.913391],"type":"Point"}
}