{
  "type": "Feature",
  "properties": {
    "iso:country":"US",
    "sg:address":"224 Main St",
    "sg:city":"Cold Spring",
    "sg:classifiers":[
        {
            "category":"Social Services",
            "subcategory":"Child Care",
            "type":"Services"
        }
    ],
    "sg:phone":"+1 845 265 3317",
    "sg:postcode":"10516",
    "sg:province":"NY",
    "sg:tags":[
        "kindergarten",
        "academic",
        "school",
        "center",
        "preschool"
    ],
    "wof:name":"Bounous Montessori School",
    "wof:placetype":"venue"
},
  "geometry": {"coordinates":[-73.95071299999999,41.422674],"type":"Point"}
}