{
  "type": "Feature",
  "properties": {
    "addr:full":"360 Madison Ave New York NY 10017",
    "addr:housenumber":"360",
    "addr:postcode":"10017",
    "addr:street":"Madison Ave",
    "iso:country":"US",
    "sg:address":"360 Madison Ave",
    "sg:city":"New York",
    "sg:classifiers":[
        {
            "category":"Professional",
            "subcategory":"Business Services",
            "type":"Services"
        },
        {
            "category":"Professional",
            "subcategory":"Management & Consulting",
            "type":"Services"
        }
    ],
    "sg:phone":"+1 212 661 1760",
    "sg:postcode":"10017",
    "sg:province":"NY",
    "sg:tags":[
        "fuel",
        "financial"
    ],
    "wof:name":"Archeus Capital Management LLC",
    "wof:placetype":"venue"
},
  "geometry": {"coordinates":[-73.977526,40.755312],"type":"Point"}
}