{
  "type": "Feature",
  "properties": {
    "addr:full":"7313 McCormick Rd Boonville NY 13309",
    "addr:housenumber":"7313",
    "addr:postcode":"13309",
    "addr:street":"Mccormick Rd",
    "iso:country":"US",
    "sg:address":"7313 McCormick Rd",
    "sg:city":"Boonville",
    "sg:classifiers":[
        {
            "category":"Farming",
            "subcategory":"Dairy Farm",
            "type":"Manufacturing & Wholesale Goods"
        }
    ],
    "sg:phone":"+1 315 827 4439",
    "sg:postcode":"13309",
    "sg:province":"NY",
    "wof:name":"Michael Sokoloff",
    "wof:placetype":"venue"
},
  "geometry": {"coordinates":[-75.413588,43.371636],"type":"Point"}
}