{
  "type": "Feature",
  "properties": {
    "iso:country":"US",
    "sg:address":"55 5th Ave",
    "sg:city":"New York",
    "sg:classifiers":[
        {
            "category":"Professional",
            "subcategory":"Business Services",
            "type":"Services"
        }
    ],
    "sg:phone":"+1 212 206 5635",
    "sg:postcode":"10003",
    "sg:province":"NY",
    "sg:tags":[
        "literary",
        "agent"
    ],
    "wof:name":"Carol Mann Agency",
    "wof:placetype":"venue"
},
  "geometry": {"coordinates":[-73.994141,40.735116],"type":"Point"}
}