{
  "type": "Feature",
  "properties": {
    "addr:full":"7160 State Hwy 54 Bath NY 14810",
    "addr:housenumber":"7160",
    "addr:postcode":"14810",
    "addr:street":"State Hwy 54",
    "iso:country":"US",
    "sg:address":"7160 State Hwy 54",
    "sg:city":"Bath",
    "sg:classifiers":[
        {
            "category":"Social Services",
            "type":"Services"
        }
    ],
    "sg:phone":"+1 607 776 7082",
    "sg:postcode":"14810",
    "sg:province":"NY",
    "sg:tags":[
        "organization",
        "welfare"
    ],
    "wof:name":"Steuben ARC",
    "wof:placetype":"venue"
},
  "geometry": {"coordinates":[-77.306962,42.349735],"type":"Point"}
}