{
  "type": "Feature",
  "properties": {
    "addr:full":"318 E Fairmount Ave Lakewood NY 14750",
    "addr:housenumber":"318",
    "addr:postcode":"14750",
    "addr:street":"E Fairmount Ave",
    "iso:country":"US",
    "sg:address":"318 E Fairmount Ave",
    "sg:city":"Lakewood",
    "sg:classifiers":[
        {
            "category":"Real Estate",
            "subcategory":"Real Estate Operator",
            "type":"Services"
        }
    ],
    "sg:phone":"+1 716 763 1823",
    "sg:postcode":"14750",
    "sg:province":"NY",
    "sg:tags":[
        "mall",
        "shopping",
        "center"
    ],
    "sg:website":"www.simon.com",
    "wof:name":"Chautauqua Mall",
    "wof:placetype":"venue"
},
  "geometry": {"coordinates":[-79.30226999999999,42.099101],"type":"Point"}
}