{
  "type": "Feature",
  "properties": {
    "iso:country":"US",
    "sg:address":"60 Cuttermill Rd",
    "sg:city":"Great Neck",
    "sg:classifiers":[
        {
            "category":"Professional",
            "subcategory":"Management & Consulting",
            "type":"Services"
        }
    ],
    "sg:phone":"+1 516 829 6050",
    "sg:postcode":"11021",
    "sg:province":"NY",
    "sg:tags":[
        "insurance"
    ],
    "wof:name":"Alpha Risk Management",
    "wof:placetype":"venue"
},
  "geometry": {"coordinates":[-73.730885,40.786103],"type":"Point"}
}