{
  "type": "Feature",
  "properties": {
    "addr:full":"127 Wolf Rd Albany NY 12205",
    "addr:housenumber":"127",
    "addr:postcode":"12205",
    "addr:street":"Wolf Rd",
    "iso:country":"US",
    "sg:address":"127 Wolf Rd",
    "sg:city":"Albany",
    "sg:classifiers":[
        {
            "category":"Retail",
            "subcategory":"Auto Rental",
            "type":"Services"
        }
    ],
    "sg:phone":"+1 518 782 7654",
    "sg:postcode":"12205",
    "sg:province":"NY",
    "sg:tags":[
        "renting",
        "automobile"
    ],
    "wof:name":"Thrifty Car Rental",
    "wof:placetype":"venue"
},
  "geometry": {"coordinates":[-73.805801,42.718993],"type":"Point"}
}