{
  "type": "Feature",
  "properties": {
    "iso:country":"US",
    "sg:address":"16 Dakin Ave",
    "sg:city":"Mount Kisco",
    "sg:classifiers":[
        {
            "category":"Social Services",
            "type":"Services"
        }
    ],
    "sg:phone":"+1   ",
    "sg:postcode":"10549",
    "sg:province":"NY",
    "wof:name":"Phyllis Spiegel",
    "wof:placetype":"venue"
},
  "geometry": {"coordinates":[-73.728084,41.203714],"type":"Point"}
}