{
  "type": "Feature",
  "properties": {
    "iso:country":"US",
    "sg:address":"139 N Main St",
    "sg:city":"Port Chester",
    "sg:classifiers":[
        {
            "category":"Restaurant",
            "type":"Food & Drink"
        }
    ],
    "sg:phone":"+1 914 690 9720",
    "sg:postcode":"10573",
    "sg:province":"NY",
    "wof:name":"LA Hacienda Bar & Grill",
    "wof:placetype":"venue"
},
  "geometry": {"coordinates":[-73.661035,41.003153],"type":"Point"}
}