{
  "type": "Feature",
  "properties": {
    "iso:country":"US",
    "sg:address":"1 Walden Galleria",
    "sg:city":"Buffalo",
    "sg:classifiers":[
        {
            "category":"Restaurant",
            "type":"Food & Drink"
        }
    ],
    "sg:menulink":"http://www.allmenus.com/ny/cheektowaga/148266-subway/menu/",
    "sg:phone":"+1 716 685 0541",
    "sg:postcode":"14225",
    "sg:province":"NY",
    "sg:tags":[
        "american",
        "sandwich"
    ],
    "wof:name":"Subway",
    "wof:placetype":"venue"
},
  "geometry": {"coordinates":[-78.759337,42.908129],"type":"Point"}
}