{
  "type": "Feature",
  "properties": {
    "addr:full":"19 W 45 St New York NY 10036",
    "addr:housenumber":"19",
    "addr:postcode":"10036",
    "addr:street":"W 45 St",
    "iso:country":"US",
    "sg:address":"19 W 45 St",
    "sg:city":"New York",
    "sg:classifiers":[
        {
            "category":"Shopping",
            "subcategory":"Jewelry",
            "type":"Retail Goods"
        }
    ],
    "sg:phone":"+1 212 719 0242",
    "sg:postcode":"10036",
    "sg:province":"NY",
    "sg:tags":[
        "designer"
    ],
    "wof:name":"Jewels By Procopios",
    "wof:placetype":"venue"
},
  "geometry": {"coordinates":[-73.982225,40.756585],"type":"Point"}
}