{
  "type": "Feature",
  "properties": {
    "iso:country":"US",
    "sg:address":"191 Malcolm X Blvd",
    "sg:city":"Brooklyn",
    "sg:classifiers":[
        {
            "category":"Building & Trades",
            "subcategory":"Plumbing",
            "type":"Services"
        }
    ],
    "sg:phone":"+1 718 919 1680",
    "sg:postcode":"11221",
    "sg:province":"NY",
    "wof:name":"Alai Plumbing & Heating",
    "wof:placetype":"venue"
},
  "geometry": {"coordinates":[-73.929597,40.686578],"type":"Point"}
}