{
  "type": "Feature",
  "properties": {
    "iso:country":"US",
    "sg:address":"750 Grand St",
    "sg:city":"Brooklyn",
    "sg:classifiers":[
        {
            "category":"Sports & Exercise",
            "subcategory":"Gym",
            "type":"Entertainment"
        }
    ],
    "sg:phone":"+1 718 387 4711",
    "sg:postcode":"11211",
    "sg:province":"NY",
    "sg:website":"absolutepowergym.com",
    "wof:name":"Absolute Power Fitness",
    "wof:placetype":"venue"
},
  "geometry": {"coordinates":[-73.94292799999999,40.711664],"type":"Point"}
}