{
  "type": "Feature",
  "properties": {
    "addr:full":"881 9th Ave New York NY 10019",
    "addr:housenumber":"881",
    "addr:postcode":"10019",
    "addr:street":"9Th Ave",
    "iso:country":"US",
    "sg:address":"881 9th Ave",
    "sg:city":"New York",
    "sg:classifiers":[
        {
            "category":"Food & Beverages",
            "subcategory":"Groceries & Convenience Stores",
            "type":"Retail Goods"
        }
    ],
    "sg:phone":"+1 212 307 1909",
    "sg:postcode":"10019",
    "sg:province":"NY",
    "wof:name":"Manhattan Tobacco & Grocery Corp",
    "wof:placetype":"venue"
},
  "geometry": {"coordinates":[-73.985703,40.768101],"type":"Point"}
}