{
  "type": "Feature",
  "properties": {
    "addr:full":"414 8th Avenue New York NY 10001",
    "addr:housenumber":"414",
    "addr:postcode":"10001",
    "addr:street":"8Th Avenue",
    "iso:country":"US",
    "sg:address":"414 8th Avenue",
    "sg:city":"New York",
    "sg:classifiers":[
        {
            "category":"Food & Beverages",
            "subcategory":"Liquor & Beverages",
            "type":"Retail Goods"
        }
    ],
    "sg:phone":"+1 212 290 0710",
    "sg:postcode":"10001",
    "sg:province":"NY",
    "sg:tags":[
        "beer",
        "spirit",
        "wine"
    ],
    "wof:name":"Nrs Wine & Liquor",
    "wof:placetype":"venue"
},
  "geometry": {"coordinates":[-73.99504,40.749774],"type":"Point"}
}