{
  "type": "Feature",
  "properties": {
    "addr:full":"200 Burrs Ln Huntington Station NY 11746",
    "addr:housenumber":"200",
    "addr:postcode":"11746",
    "addr:street":"Burrs Ln Huntington",
    "iso:country":"US",
    "sg:address":"200 Burrs Ln",
    "sg:city":"Huntington Station",
    "sg:classifiers":[
        {
            "category":"Health Services",
            "subcategory":"Doctor",
            "type":"Services"
        }
    ],
    "sg:phone":"+1 516 889 4527",
    "sg:postcode":"11746",
    "sg:province":"NY",
    "sg:tags":[
        "medical"
    ],
    "wof:name":"Harlan B Spindler Dr",
    "wof:placetype":"venue"
},
  "geometry": {"coordinates":[-73.35539799999999,40.771744],"type":"Point"}
}