{
  "type": "Feature",
  "properties": {
    "addr:full":"10555 State Hwy 242 Randolph NY 14772",
    "addr:housenumber":"10555",
    "addr:postcode":"14772",
    "addr:street":"State Hwy 242",
    "iso:country":"US",
    "sg:address":"10555 State Hwy 242",
    "sg:city":"Randolph",
    "sg:classifiers":[
        {
            "category":"Building & Trades",
            "subcategory":"Construction",
            "type":"Services"
        }
    ],
    "sg:phone":"+1 716 358 9821",
    "sg:postcode":"14772",
    "sg:province":"NY",
    "sg:tags":[
        "house"
    ],
    "wof:name":"Great American Builders",
    "wof:placetype":"venue"
},
  "geometry": {"coordinates":[-78.91586,42.186857],"type":"Point"}
}