{
  "type": "Feature",
  "properties": {
    "iso:country":"US",
    "sg:address":"687 Morris Park Ave",
    "sg:city":"Bronx",
    "sg:classifiers":[
        {
            "category":"Restaurant",
            "type":"Food & Drink"
        }
    ],
    "sg:phone":"+1 718 518 1242",
    "sg:postcode":"10462",
    "sg:province":"NY",
    "sg:tags":[
        "chinese"
    ],
    "wof:name":"Joy Garden Chinese Restaurant",
    "wof:placetype":"venue"
},
  "geometry": {"coordinates":[-73.86640199999999,40.845299],"type":"Point"}
}