{
  "type": "Feature",
  "properties": {
    "iso:country":"US",
    "sg:address":"28 East 28th Street 9th Floor",
    "sg:city":"New York",
    "sg:classifiers":[
        {
            "category":"Professional",
            "subcategory":"Computer Services",
            "type":"Services"
        }
    ],
    "sg:phone":"+1 212 541 2838",
    "sg:postcode":"10016",
    "sg:province":"NY",
    "sg:tags":[
        "investor",
        "financial-organization",
        "entertainment",
        "social-gaming",
        "video-gaming",
        "casual-gaming",
        "venture-capital",
        "strategic-investor",
        "bertelsmann",
        "bdmi"
    ],
    "sg:website":"http://www.fremantlemedia.com",
    "wof:name":"FremantleMedia Ventures",
    "wof:placetype":"venue"
},
  "geometry": {"coordinates":[-73.984211,40.743313],"type":"Point"}
}