{
  "type": "Feature",
  "properties": {
    "addr:full":"Grand St & Lorimer St Brooklyn NY 11211",
    "addr:postcode":"11211",
    "addr:street":"Grand St & Lorimer St",
    "iso:country":"US",
    "sg:address":"Grand St & Lorimer St",
    "sg:city":"Brooklyn",
    "sg:classifiers":[
        {
            "category":"Restaurant",
            "type":"Food & Drink"
        }
    ],
    "sg:phone":"+1 718 384 2122",
    "sg:postcode":"11211",
    "sg:province":"NY",
    "sg:tags":[
        "greek",
        "mediterranean"
    ],
    "wof:name":"Manna",
    "wof:placetype":"venue"
},
  "geometry": {"coordinates":[-73.948898,40.711165],"type":"Point"}
}