{
  "type": "Feature",
  "properties": {
    "iso:country":"US",
    "sg:address":"75 Northern Pines Rd",
    "sg:city":"Gansevoort",
    "sg:classifiers":[
        {
            "category":"Government",
            "subcategory":"Office",
            "type":"Public Place"
        }
    ],
    "sg:phone":"+1 518 581 3145",
    "sg:postcode":"12831",
    "sg:province":"NY",
    "sg:tags":[
        "health"
    ],
    "wof:name":"Office For Develop Challenged",
    "wof:placetype":"venue"
},
  "geometry": {"coordinates":[-73.742448,43.169474],"type":"Point"}
}