{
  "type": "Feature",
  "properties": {
    "iso:country":"US",
    "sg:address":"5520 15th Ave",
    "sg:city":"Brooklyn",
    "sg:classifiers":[
        {
            "category":"Organizations",
            "subcategory":"Religious Organization",
            "type":"Services"
        }
    ],
    "sg:phone":"+1 718 851 8958",
    "sg:postcode":"11219",
    "sg:province":"NY",
    "sg:tags":[
        "clergy"
    ],
    "wof:name":"Gershon Glatzer",
    "wof:placetype":"venue"
},
  "geometry": {"coordinates":[-73.99176300000001,40.628607],"type":"Point"}
}