{
  "type": "Feature",
  "properties": {
    "addr:full":"1 Penn Plaza New York NY 10001",
    "addr:housenumber":"1",
    "addr:postcode":"10001",
    "addr:street":"Penn Plaza",
    "iso:country":"US",
    "sg:address":"1 Penn Plaza",
    "sg:city":"New York",
    "sg:classifiers":[
        {
            "category":"Personal",
            "type":"Services"
        }
    ],
    "sg:phone":"+1 917 974 4729",
    "sg:postcode":"10001",
    "sg:province":"NY",
    "sg:tags":[
        "planning",
        "wedding"
    ],
    "sg:website":"www.brillianteventplanning.com",
    "wof:name":"Brilliant Event Planning",
    "wof:placetype":"venue"
},
  "geometry": {"coordinates":[-73.99166200000001,40.749559],"type":"Point"}
}