{
  "type": "Feature",
  "properties": {
    "addr:full":"16174 Carr Rd Kendall NY 14476",
    "addr:housenumber":"16174",
    "addr:postcode":"14476",
    "addr:street":"Carr Rd",
    "iso:country":"US",
    "sg:address":"16174 Carr Rd",
    "sg:city":"Kendall",
    "sg:classifiers":[
        {
            "category":"Building & Trades",
            "subcategory":"Landscaping Services",
            "type":"Services"
        }
    ],
    "sg:phone":"+1 585 659 8357",
    "sg:postcode":"14476",
    "sg:province":"NY",
    "wof:name":"Quality Lawn Mowing",
    "wof:placetype":"venue"
},
  "geometry": {"coordinates":[-78.057605,43.336001],"type":"Point"}
}