{
  "type": "Feature",
  "properties": {
    "iso:country":"US",
    "sg:address":"41 Thompson St",
    "sg:city":"Newburgh",
    "sg:classifiers":[
        {
            "category":"Building & Trades",
            "subcategory":"Landscaping Services",
            "type":"Services"
        }
    ],
    "sg:phone":"+1 845 562 4878",
    "sg:postcode":"12550",
    "sg:province":"NY",
    "sg:tags":[
        "lawn",
        "maintenance",
        "grounds"
    ],
    "wof:name":"Nelson Lawnmowing/Landscaping",
    "wof:placetype":"venue"
},
  "geometry": {"coordinates":[-74.04491899999999,41.505934],"type":"Point"}
}