{
  "type": "Feature",
  "properties": {
    "addr:full":"1367 Broadway Brooklyn NY 11221",
    "addr:housenumber":"1367",
    "addr:postcode":"11221",
    "addr:street":"Broadway",
    "iso:country":"US",
    "sg:address":"1367 Broadway",
    "sg:city":"Brooklyn",
    "sg:classifiers":[
        {
            "category":"Shopping",
            "subcategory":"Pharmacy",
            "type":"Retail Goods"
        }
    ],
    "sg:phone":"+1 718 453 6866",
    "sg:postcode":"11221",
    "sg:province":"NY",
    "sg:tags":[
        "drugstore"
    ],
    "wof:name":"Sam's Drugs",
    "wof:placetype":"venue"
},
  "geometry": {"coordinates":[-73.922203,40.689701],"type":"Point"}
}