{
  "type": "Feature",
  "properties": {
    "addr:full":"1770 Stillwell Avenue Bronx NY 10469",
    "addr:housenumber":"1770",
    "addr:postcode":"10469",
    "addr:street":"Stillwell Avenue",
    "iso:country":"US",
    "sg:address":"1770 Stillwell Avenue",
    "sg:city":"Bronx",
    "sg:classifiers":[
        {
            "category":"Social Services",
            "subcategory":"Child Care",
            "type":"Services"
        }
    ],
    "sg:phone":"+1 718 652 9790",
    "sg:postcode":"10469",
    "sg:province":"NY",
    "sg:tags":[
        "day"
    ],
    "wof:name":"United Cerebral Palsy of N Y C",
    "wof:placetype":"venue"
},
  "geometry": {"coordinates":[-73.83491600000001,40.858106],"type":"Point"}
}