{
  "type": "Feature",
  "properties": {
    "iso:country":"US",
    "sg:address":"40 Hudson Dr",
    "sg:city":"Hyde Park",
    "sg:classifiers":[
        {
            "category":"Building & Trades",
            "subcategory":"Plumbing",
            "type":"Services"
        }
    ],
    "sg:phone":"+1 845 229 2041",
    "sg:postcode":"12538",
    "sg:province":"NY",
    "sg:tags":[
        "contractor"
    ],
    "wof:name":"Watson Temperature Control",
    "wof:placetype":"venue"
},
  "geometry": {"coordinates":[-73.93077,41.792318],"type":"Point"}
}