{
  "type": "Feature",
  "properties": {
    "addr:full":"15 E 6th St Jamestown NY 14701",
    "addr:housenumber":"15",
    "addr:postcode":"14701",
    "addr:street":"E 6Th St",
    "iso:country":"US",
    "sg:address":"15 E 6th St",
    "sg:city":"Jamestown",
    "sg:classifiers":[
        {
            "category":"Insurance",
            "subcategory":"Insurance Agent",
            "type":"Services"
        }
    ],
    "sg:phone":"+1 716 664 2910",
    "sg:postcode":"14701",
    "sg:province":"NY",
    "wof:name":"Greenlee-Winchester Agency Inc",
    "wof:placetype":"venue"
},
  "geometry": {"coordinates":[-79.240893,42.099227],"type":"Point"}
}