{
  "type": "Feature",
  "properties": {
    "addr:full":"936 Kings Hwy Brooklyn NY 11223",
    "addr:housenumber":"936",
    "addr:postcode":"11223",
    "addr:street":"Kings Hwy",
    "iso:country":"US",
    "sg:address":"936 Kings Hwy",
    "sg:city":"Brooklyn",
    "sg:classifiers":[
        {
            "category":"Banks & Credit Unions",
            "subcategory":"Investment Brokerage",
            "type":"Services"
        }
    ],
    "sg:phone":"+1 718 787 0817",
    "sg:postcode":"11223",
    "sg:province":"NY",
    "sg:tags":[
        "stock",
        "bond"
    ],
    "wof:name":"A Heffco Technologies",
    "wof:placetype":"venue"
},
  "geometry": {"coordinates":[-73.961866,40.607263],"type":"Point"}
}