{
  "type": "Feature",
  "properties": {
    "iso:country":"US",
    "sg:address":"88 Sunnyside Blvd",
    "sg:city":"Plainview",
    "sg:classifiers":[
        {
            "category":"Real Estate",
            "subcategory":"Real Estate Agent",
            "type":"Services"
        }
    ],
    "sg:phone":"+1 516 349 9200",
    "sg:postcode":"11803",
    "sg:province":"NY",
    "wof:name":"Cedar Ridge Properties",
    "wof:placetype":"venue"
},
  "geometry": {"coordinates":[-73.47031200000001,40.794173],"type":"Point"}
}