{
  "type": "Feature",
  "properties": {
    "iso:country":"US",
    "sg:address":"20 Assembly Dr Ste 108",
    "sg:city":"Mendon",
    "sg:classifiers":[
        {
            "category":"Health Services",
            "subcategory":"Clinic",
            "type":"Services"
        },
        {
            "category":"Health Services",
            "subcategory":"Health Practitioner",
            "type":"Services"
        }
    ],
    "sg:phone":"+1 585 748 5558",
    "sg:postcode":"14506",
    "sg:province":"NY",
    "sg:tags":[
        "therapist",
        "therapy",
        "physical"
    ],
    "wof:name":"Titus Loni Lmt",
    "wof:placetype":"venue"
},
  "geometry": {"coordinates":[-77.508972,42.999381],"type":"Point"}
}