{
  "type": "Feature",
  "properties": {
    "iso:country":"US",
    "sg:address":"747 E Main St",
    "sg:city":"Riverhead",
    "sg:classifiers":[
        {
            "category":"Real Estate",
            "subcategory":"Real Estate Services",
            "type":"Services"
        }
    ],
    "sg:phone":"+1 631 727 3713",
    "sg:postcode":"11901",
    "sg:province":"NY",
    "sg:tags":[
        "management",
        "property"
    ],
    "sg:website":"www.coldwellbankerbagshaw.com",
    "wof:name":"Bagshaw Realty - Coldwell Banker",
    "wof:placetype":"venue"
},
  "geometry": {"coordinates":[-72.652477,40.921757],"type":"Point"}
}