{
  "type": "Feature",
  "properties": {
    "iso:country":"US",
    "sg:address":"181 Rice Rd",
    "sg:city":"De Kalb Junction",
    "sg:classifiers":[
        {
            "category":"Home & Garden",
            "subcategory":"Building Materials",
            "type":"Retail Goods"
        },
        {
            "category":"Manufacturing",
            "subcategory":"Lumber",
            "type":"Manufacturing & Wholesale Goods"
        }
    ],
    "sg:phone":"+1 315 347 5400",
    "sg:postcode":"13630",
    "sg:province":"NY",
    "sg:tags":[
        "forester"
    ],
    "wof:name":"J & D Forestry Products",
    "wof:placetype":"venue"
},
  "geometry": {"coordinates":[-75.244625,44.507255],"type":"Point"}
}