{
  "type": "Feature",
  "properties": {
    "addr:full":"2 Hawley St Binghamton NY 13901",
    "addr:housenumber":"2",
    "addr:postcode":"13901",
    "addr:street":"Hawley St",
    "iso:country":"US",
    "sg:address":"2 Hawley St",
    "sg:city":"Binghamton",
    "sg:classifiers":[
        {
            "category":"Professional",
            "subcategory":"Lawyer & Legal Services",
            "type":"Services"
        }
    ],
    "sg:phone":"+1 607 722 4934",
    "sg:postcode":"13901",
    "sg:province":"NY",
    "sg:tags":[
        "attorney"
    ],
    "wof:name":"Thomas Miller",
    "wof:placetype":"venue"
},
  "geometry": {"coordinates":[-75.914593,42.098718],"type":"Point"}
}