{
  "type": "Feature",
  "properties": {
    "iso:country":"US",
    "sg:address":"786 E 163rd St",
    "sg:city":"Bronx",
    "sg:classifiers":[
        {
            "category":"Organizations",
            "subcategory":"Religious Organization",
            "type":"Services"
        }
    ],
    "sg:phone":"+1 718 665 4686",
    "sg:postcode":"10456",
    "sg:province":"NY",
    "sg:tags":[
        "church"
    ],
    "wof:name":"Mt Hope Missionary Baptist Chr",
    "wof:placetype":"venue"
},
  "geometry": {"coordinates":[-73.902248,40.822443],"type":"Point"}
}