{
  "type": "Feature",
  "properties": {
    "addr:full":"1062 Central Ave South Hempstead NY 11550",
    "addr:housenumber":"1062",
    "addr:postcode":"11550",
    "addr:street":"Central Ave South",
    "iso:country":"US",
    "sg:address":"1062 Central Ave",
    "sg:city":"South Hempstead",
    "sg:classifiers":[
        {
            "category":"Building & Trades",
            "subcategory":"Construction",
            "type":"Services"
        }
    ],
    "sg:phone":"+1 516 379 4043",
    "sg:postcode":"11550",
    "sg:province":"NY",
    "sg:tags":[
        "contractor"
    ],
    "sg:website":"www.fjfremodelersinc.com",
    "wof:name":"FJF Remodelers Inc",
    "wof:placetype":"venue"
},
  "geometry": {"coordinates":[-73.617454,40.685231],"type":"Point"}
}