{
  "type": "Feature",
  "properties": {
    "addr:full":"3248 W River Rd Olean NY 14760",
    "addr:housenumber":"3248",
    "addr:postcode":"14760",
    "addr:street":"W River Rd",
    "iso:country":"US",
    "sg:address":"3248 W River Rd",
    "sg:city":"Olean",
    "sg:classifiers":[
        {
            "category":"Retail",
            "subcategory":"Auto Repair",
            "type":"Services"
        }
    ],
    "sg:phone":"+1 716 372 5276",
    "sg:postcode":"14760",
    "sg:province":"NY",
    "sg:tags":[
        "automobile",
        "inspection"
    ],
    "wof:name":"4 Seasons Auto Repair",
    "wof:placetype":"venue"
},
  "geometry": {"coordinates":[-78.492876,42.073676],"type":"Point"}
}