{
  "type": "Feature",
  "properties": {
    "iso:country":"US",
    "sg:address":"6013 4th Ave",
    "sg:city":"Brooklyn",
    "sg:classifiers":[
        {
            "category":"Shopping",
            "subcategory":"Stationery & Office Supplies",
            "type":"Retail Goods"
        }
    ],
    "sg:phone":"+1 718 492 7695",
    "sg:postcode":"11220",
    "sg:province":"NY",
    "sg:tags":[
        "stationer"
    ],
    "wof:name":"Mr Tangs Stationery",
    "wof:placetype":"venue"
},
  "geometry": {"coordinates":[-74.01890899999999,40.640288],"type":"Point"}
}