{
  "type": "Feature",
  "properties": {
    "addr:full":"7535 31st Ave Ste 201 East Elmhurst NY 11370",
    "addr:housenumber":"7535",
    "addr:postcode":"11370",
    "addr:street":"31St Ave Ste 201",
    "iso:country":"US",
    "sg:address":"7535 31st Ave Ste 201",
    "sg:city":"East Elmhurst",
    "sg:classifiers":[
        {
            "category":"Banks & Credit Unions",
            "subcategory":"Financial Services",
            "type":"Services"
        }
    ],
    "sg:phone":"+1 718 507 9270",
    "sg:postcode":"11370",
    "sg:province":"NY",
    "sg:tags":[
        "broker",
        "mortgage"
    ],
    "wof:name":"Central Mortgage Corp",
    "wof:placetype":"venue"
},
  "geometry": {"coordinates":[-73.892224,40.758717],"type":"Point"}
}