{
  "type": "Feature",
  "properties": {
    "addr:full":"7523 Broadway Elmhurst NY 11373",
    "addr:housenumber":"7523",
    "addr:postcode":"11373",
    "addr:street":"Broadway",
    "iso:country":"US",
    "sg:address":"7523 Broadway",
    "sg:city":"Elmhurst",
    "sg:classifiers":[
        {
            "category":"Food & Beverages",
            "subcategory":"Groceries & Convenience Stores",
            "type":"Retail Goods"
        }
    ],
    "sg:phone":"+1 718 446 9697",
    "sg:postcode":"11373",
    "sg:province":"NY",
    "wof:name":"Kavi Convenience",
    "wof:placetype":"venue"
},
  "geometry": {"coordinates":[-73.889529,40.745997],"type":"Point"}
}