{
  "type": "Feature",
  "properties": {
    "addr:full":"120 Herriot St Yonkers NY 10701",
    "addr:housenumber":"120",
    "addr:postcode":"10701",
    "addr:street":"Herriot St",
    "iso:country":"US",
    "sg:address":"120 Herriot St",
    "sg:city":"Yonkers",
    "sg:classifiers":[
        {
            "category":"Food & Beverages",
            "subcategory":"Groceries & Convenience Stores",
            "type":"Retail Goods"
        }
    ],
    "sg:phone":"+1 914 964 6986",
    "sg:postcode":"10701",
    "sg:province":"NY",
    "sg:tags":[
        "grocer"
    ],
    "wof:name":"A & E Groceries",
    "wof:placetype":"venue"
},
  "geometry": {"coordinates":[-73.902402,40.928301],"type":"Point"}
}