{
  "type": "Feature",
  "properties": {
    "addr:full":"307 Richs Dugway Rd Rochester NY 14625",
    "addr:housenumber":"307",
    "addr:postcode":"14625",
    "addr:street":"Richs Dugway Rd",
    "iso:country":"US",
    "sg:address":"307 Richs Dugway Rd",
    "sg:city":"Rochester",
    "sg:classifiers":[
        {
            "category":"Wholesale",
            "subcategory":"Drugs",
            "type":"Manufacturing & Wholesale Goods"
        }
    ],
    "sg:phone":"+1 585 482 0284",
    "sg:postcode":"14625",
    "sg:province":"NY",
    "wof:name":"Blue Crescent Botanica",
    "wof:placetype":"venue"
},
  "geometry": {"coordinates":[-77.524525,43.147482],"type":"Point"}
}