{
  "type": "Feature",
  "properties": {
    "addr:full":"699 E 187th St Bronx NY 10458",
    "addr:housenumber":"699",
    "addr:postcode":"10458",
    "addr:street":"E 187Th St",
    "iso:country":"US",
    "sg:address":"699 E 187th St",
    "sg:city":"Bronx",
    "sg:classifiers":[
        {
            "category":"Fast Food",
            "type":"Food & Drink"
        }
    ],
    "sg:phone":"+1 718 562 9464",
    "sg:postcode":"10458",
    "sg:province":"NY",
    "sg:website":"www.planetwings.com",
    "wof:name":"Planet Wings",
    "wof:placetype":"venue"
},
  "geometry": {"coordinates":[-73.884591,40.85434],"type":"Point"}
}