{
  "type": "Feature",
  "properties": {
    "addr:full":"354 S Broadway Yonkers NY 10705",
    "addr:housenumber":"354",
    "addr:postcode":"10705",
    "addr:street":"S Broadway",
    "iso:country":"US",
    "sg:address":"354 S Broadway",
    "sg:city":"Yonkers",
    "sg:classifiers":[
        {
            "category":"Shopping",
            "subcategory":"Department Store",
            "type":"Retail Goods"
        },
        {
            "category":"Shopping",
            "subcategory":"Discount & Variety Stores",
            "type":"Retail Goods"
        }
    ],
    "sg:phone":"+1 914 968 2946",
    "sg:postcode":"10705",
    "sg:province":"NY",
    "sg:website":"http://www.familydollar.com",
    "wof:name":"Family Dollar Stores",
    "wof:placetype":"venue"
},
  "geometry": {"coordinates":[-73.895996,40.921374],"type":"Point"}
}