{
  "type": "Feature",
  "properties": {
    "addr:full":"417 New Karner Rd Albany NY 12205",
    "addr:housenumber":"417",
    "addr:postcode":"12205",
    "addr:street":"New Karner Rd",
    "iso:country":"US",
    "sg:address":"417 New Karner Rd",
    "sg:city":"Albany",
    "sg:classifiers":[
        {
            "category":"Shopping",
            "type":"Retail Goods"
        }
    ],
    "sg:phone":"+1 518 456 3081",
    "sg:postcode":"12205",
    "sg:province":"NY",
    "sg:tags":[
        "hearing",
        "equipment",
        "supply",
        "impaired"
    ],
    "wof:name":"General Hearing Aids Inc",
    "wof:placetype":"venue"
},
  "geometry": {"coordinates":[-73.84358899999999,42.738146],"type":"Point"}
}