{
  "type": "Feature",
  "properties": {
    "iso:country":"US",
    "sg:address":"1 Park Ave",
    "sg:city":"Valhalla",
    "sg:classifiers":[
        {
            "category":"Manufacturing",
            "subcategory":"Tools & Machinery",
            "type":"Manufacturing & Wholesale Goods"
        }
    ],
    "sg:phone":"+1 914 686 3600",
    "sg:postcode":"10595",
    "sg:province":"NY",
    "sg:tags":[
        "physician",
        "surgeon"
    ],
    "wof:name":"Spellman High Voltage",
    "wof:placetype":"venue"
},
  "geometry": {"coordinates":[-73.782414,41.086413],"type":"Point"}
}