{
  "type": "Feature",
  "properties": {
    "iso:country":"US",
    "sg:address":"161 McMaster St",
    "sg:city":"Owego",
    "sg:classifiers":[
        {
            "category":"Building & Trades",
            "subcategory":"Construction",
            "type":"Services"
        }
    ],
    "sg:phone":"+1 607 687 5810",
    "sg:postcode":"13827",
    "sg:province":"NY",
    "sg:tags":[
        "general",
        "contractor"
    ],
    "wof:name":"S & W General Contractor",
    "wof:placetype":"venue"
},
  "geometry": {"coordinates":[-76.267385,42.105085],"type":"Point"}
}