{
  "type": "Feature",
  "properties": {
    "iso:country":"US",
    "sg:address":"27 Auburn Rd",
    "sg:city":"Lansing",
    "sg:classifiers":[
        {
            "category":"Education",
            "subcategory":"Library",
            "type":"Public Place"
        }
    ],
    "sg:phone":"+1 607 533 4939",
    "sg:postcode":"14882",
    "sg:province":"NY",
    "wof:name":"Lansing Community Library Ctr",
    "wof:placetype":"venue"
},
  "geometry": {"coordinates":[-76.50112900000001,42.538048],"type":"Point"}
}