{
  "type": "Feature",
  "properties": {
    "iso:country":"US",
    "sg:address":"126 Cayuga St",
    "sg:city":"Fulton",
    "sg:classifiers":[
        {
            "category":"Restaurant",
            "type":"Food & Drink"
        }
    ],
    "sg:phone":"+1 315 343 2272",
    "sg:postcode":"13069",
    "sg:province":"NY",
    "wof:name":"Russell's Ribs Carolina BBQ",
    "wof:placetype":"venue"
},
  "geometry": {"coordinates":[-76.416557,43.324136],"type":"Point"}
}