{
  "type": "Feature",
  "properties": {
    "iso:country":"US",
    "sg:address":"915 Butternut St",
    "sg:city":"Syracuse",
    "sg:classifiers":[
        {
            "category":"Personal",
            "subcategory":"Beauty Salon",
            "type":"Services"
        }
    ],
    "sg:phone":"+1   ",
    "sg:postcode":"13208",
    "sg:province":"NY",
    "sg:tags":[
        "shop"
    ],
    "wof:name":"Blessings Beauty & Barber Sln",
    "wof:placetype":"venue"
},
  "geometry": {"coordinates":[-76.14360600000001,43.063486],"type":"Point"}
}