{
  "type": "Feature",
  "properties": {
    "iso:country":"US",
    "sg:address":"3965 Sedgwick Ave",
    "sg:city":"Bronx",
    "sg:classifiers":[
        {
            "category":"Health Services",
            "subcategory":"Clinic",
            "type":"Services"
        }
    ],
    "sg:phone":"+1 718 548 1569",
    "sg:postcode":"10463",
    "sg:province":"NY",
    "sg:tags":[
        "medical",
        "group"
    ],
    "wof:name":"A Z Medical Ctr",
    "wof:placetype":"venue"
},
  "geometry": {"coordinates":[-73.887896,40.88285],"type":"Point"}
}