{
  "type": "Feature",
  "properties": {
    "addr:full":"1760 Mount Hope Ave Rochester NY 14620",
    "addr:housenumber":"1760",
    "addr:postcode":"14620",
    "addr:street":"Mount Hope Ave",
    "iso:country":"US",
    "sg:address":"1760 Mount Hope Ave",
    "sg:city":"Rochester",
    "sg:classifiers":[
        {
            "category":"Shopping",
            "subcategory":"Department Store",
            "type":"Retail Goods"
        }
    ],
    "sg:phone":"+1 585 256 1761",
    "sg:postcode":"14620",
    "sg:province":"NY",
    "sg:tags":[
        "shop"
    ],
    "wof:name":"U S Greek",
    "wof:placetype":"venue"
},
  "geometry": {"coordinates":[-77.62244800000001,43.11465],"type":"Point"}
}