{
  "type": "Feature",
  "properties": {
    "iso:country":"US",
    "sg:address":"41 Senator Levy Dr",
    "sg:city":"Suffern",
    "sg:classifiers":[
        {
            "category":"Professional",
            "subcategory":"Business Services",
            "type":"Services"
        }
    ],
    "sg:phone":"+1   ",
    "sg:postcode":"10901",
    "sg:province":"NY",
    "wof:name":"Mark Burke Sales Inc",
    "wof:placetype":"venue"
},
  "geometry": {"coordinates":[-74.11272099999999,41.127221],"type":"Point"}
}