{
  "type": "Feature",
  "properties": {
    "addr:full":"81 Elizabeth St New York NY 10013",
    "addr:housenumber":"81",
    "addr:postcode":"10013",
    "addr:street":"Elizabeth St",
    "iso:country":"US",
    "sg:address":"81 Elizabeth St",
    "sg:city":"New York",
    "sg:classifiers":[
        {
            "category":"Shopping",
            "subcategory":"Mobile Phones",
            "type":"Retail Goods"
        }
    ],
    "sg:phone":"+1 212 966 0081",
    "sg:postcode":"10013",
    "sg:province":"NY",
    "wof:name":"Vericon Inc",
    "wof:placetype":"venue"
},
  "geometry": {"coordinates":[-73.996272,40.718021],"type":"Point"}
}