{
  "type": "Feature",
  "properties": {
    "addr:full":"700 Ashford Ave Ardsley NY 10502",
    "addr:housenumber":"700",
    "addr:postcode":"10502",
    "addr:street":"Ashford Ave",
    "iso:country":"US",
    "sg:address":"700 Ashford Ave",
    "sg:city":"Ardsley",
    "sg:classifiers":[
        {
            "category":"Education",
            "subcategory":"School",
            "type":"Public Place"
        }
    ],
    "sg:phone":"+1 914 674 2025",
    "sg:postcode":"10502",
    "sg:province":"NY",
    "sg:website":"www.intervillage.org",
    "wof:name":"Inter-Village Continuing Ed",
    "wof:placetype":"venue"
},
  "geometry": {"coordinates":[-73.836688,41.005014],"type":"Point"}
}