{
  "type": "Feature",
  "properties": {
    "iso:country":"US",
    "sg:address":"1082 Olmstead Ave",
    "sg:city":"Bronx",
    "sg:classifiers":[
        {
            "category":"Food & Beverages",
            "subcategory":"Groceries & Convenience Stores",
            "type":"Retail Goods"
        }
    ],
    "sg:phone":"+1 718 319 0309",
    "sg:postcode":"10472",
    "sg:province":"NY",
    "sg:tags":[
        "grocer"
    ],
    "wof:name":"Rosario Grocery",
    "wof:placetype":"venue"
},
  "geometry": {"coordinates":[-73.85340100000001,40.829201],"type":"Point"}
}