{
  "type": "Feature",
  "properties": {
    "iso:country":"US",
    "sg:address":"1875 Utica Ave",
    "sg:city":"Brooklyn",
    "sg:classifiers":[
        {
            "category":"Restaurant",
            "type":"Food & Drink"
        }
    ],
    "sg:phone":"+1   ",
    "sg:postcode":"11234",
    "sg:province":"NY",
    "wof:name":"Topaze Restaurant",
    "wof:placetype":"venue"
},
  "geometry": {"coordinates":[-73.92771399999999,40.627831],"type":"Point"}
}