{
  "type": "Feature",
  "properties": {
    "addr:full":"55 E 22 St New York NY 10010",
    "addr:housenumber":"55;22",
    "addr:postcode":"10010",
    "addr:street":"E;St",
    "iso:country":"US",
    "sg:address":"55 E 22 St",
    "sg:city":"New York",
    "sg:classifiers":[
        {
            "category":"Professional",
            "subcategory":"Management & Consulting",
            "type":"Services"
        }
    ],
    "sg:phone":"+1 212 777 6655",
    "sg:postcode":"10010",
    "sg:province":"NY",
    "sg:tags":[
        "marketing",
        "communications"
    ],
    "wof:name":"Maloney Group Ltd",
    "wof:placetype":"venue"
},
  "geometry": {"coordinates":[-73.987883,40.740182],"type":"Point"}
}