{
  "type": "Feature",
  "properties": {
    "addr:full":"30 Steuben Rd Garrison NY 10524",
    "addr:housenumber":"30",
    "addr:postcode":"10524",
    "addr:street":"Steuben Rd",
    "iso:country":"US",
    "sg:address":"30 Steuben Rd",
    "sg:city":"Garrison",
    "sg:classifiers":[
        {
            "category":"Building & Trades",
            "subcategory":"Construction",
            "type":"Services"
        }
    ],
    "sg:phone":"+1 845 736 0940",
    "sg:postcode":"10524",
    "sg:province":"NY",
    "sg:tags":[
        "painting",
        "painter",
        "contractor"
    ],
    "wof:name":"Jerry Quinn & Son Painting Con",
    "wof:placetype":"venue"
},
  "geometry": {"coordinates":[-73.907292,41.334896],"type":"Point"}
}