{
  "type": "Feature",
  "properties": {
    "iso:country":"US",
    "sg:address":"181 Ramsey Ave",
    "sg:city":"Yonkers",
    "sg:classifiers":[
        {
            "category":"Building & Trades",
            "subcategory":"Landscaping Services",
            "type":"Services"
        }
    ],
    "sg:phone":"+1 914 423 4732",
    "sg:postcode":"10701",
    "sg:province":"NY",
    "wof:name":"Gentile Gardening",
    "wof:placetype":"venue"
},
  "geometry": {"coordinates":[-73.863939,40.945856],"type":"Point"}
}