{
  "type": "Feature",
  "properties": {
    "iso:country":"US",
    "sg:address":"94 Norman Ave",
    "sg:city":"Brooklyn",
    "sg:classifiers":[
        {
            "category":"Professional",
            "subcategory":"Business Services",
            "type":"Services"
        }
    ],
    "sg:phone":"+1 718 383 7750",
    "sg:postcode":"11222",
    "sg:province":"NY",
    "sg:tags":[
        "license"
    ],
    "wof:name":"Plus Enterprise",
    "wof:placetype":"venue"
},
  "geometry": {"coordinates":[-73.951125,40.72553],"type":"Point"}
}