{
  "type": "Feature",
  "properties": {
    "iso:country":"US",
    "sg:address":"136 Kahn Rd",
    "sg:city":"Fort Plain",
    "sg:classifiers":[
        {
            "category":"Farming",
            "subcategory":"Dairy Farm",
            "type":"Manufacturing & Wholesale Goods"
        }
    ],
    "sg:phone":"+1 518 993 2244",
    "sg:postcode":"13339",
    "sg:province":"NY",
    "wof:name":"Winddrift Farm",
    "wof:placetype":"venue"
},
  "geometry": {"coordinates":[-74.525432,42.985148],"type":"Point"}
}