{
  "type": "Feature",
  "properties": {
    "addr:full":"2 Lincoln Sq New York NY 10023",
    "addr:housenumber":"2",
    "addr:postcode":"10023",
    "addr:street":"Lincoln Sq",
    "iso:country":"US",
    "sg:address":"2 Lincoln Sq",
    "sg:city":"New York",
    "sg:classifiers":[
        {
            "category":"Real Estate",
            "subcategory":"Real Estate Services",
            "type":"Services"
        },
        {
            "category":"Real Estate",
            "subcategory":"Real Estate Operator",
            "type":"Services"
        }
    ],
    "sg:phone":"+1 212 580 0870",
    "sg:postcode":"10023",
    "sg:province":"NY",
    "sg:tags":[
        "apartment",
        "property",
        "management"
    ],
    "wof:name":"Two Lincoln Square",
    "wof:placetype":"venue"
},
  "geometry": {"coordinates":[-73.98139,40.773207],"type":"Point"}
}