{
  "type": "Feature",
  "properties": {
    "addr:full":"1008 Atlantic Ave Brooklyn NY 11238",
    "addr:housenumber":"1008",
    "addr:postcode":"11238",
    "addr:street":"Atlantic Ave",
    "iso:country":"US",
    "sg:address":"1008 Atlantic Ave",
    "sg:city":"Brooklyn",
    "sg:classifiers":[
        {
            "category":"Home & Garden",
            "subcategory":"Building Materials",
            "type":"Retail Goods"
        }
    ],
    "sg:phone":"+1 718 783 3902",
    "sg:postcode":"11238",
    "sg:province":"NY",
    "wof:name":"Jamaica Building Material",
    "wof:placetype":"venue"
},
  "geometry": {"coordinates":[-73.95899199999999,40.679944],"type":"Point"}
}