{
  "type": "Feature",
  "properties": {
    "iso:country":"US",
    "sg:address":"395 Central Ave",
    "sg:city":"Rochester",
    "sg:classifiers":[
        {
            "category":"Wholesale",
            "subcategory":"Scrap",
            "type":"Manufacturing & Wholesale Goods"
        }
    ],
    "sg:phone":"+1 585 546 6620",
    "sg:postcode":"14605",
    "sg:province":"NY",
    "sg:tags":[
        "recycling",
        "center"
    ],
    "sg:website":"www.rochestercomputer.com",
    "wof:name":"Rochester Computer Recycling",
    "wof:placetype":"venue"
},
  "geometry": {"coordinates":[-77.606458,43.162729],"type":"Point"}
}