{
  "type": "Feature",
  "properties": {
    "addr:full":"15 1st St Long Island City NY 11102",
    "addr:housenumber":"15",
    "addr:postcode":"11102",
    "addr:street":"1St St",
    "iso:country":"US",
    "sg:address":"15 1st St",
    "sg:city":"Long Island City",
    "sg:classifiers":[
        {
            "category":"Wholesale",
            "subcategory":"Electrical",
            "type":"Manufacturing & Wholesale Goods"
        }
    ],
    "sg:phone":"+1 718 729 2373",
    "sg:postcode":"11102",
    "sg:province":"NY",
    "sg:tags":[
        "equipment",
        "electric",
        "supply"
    ],
    "wof:name":"Grant Electrical Supply",
    "wof:placetype":"venue"
},
  "geometry": {"coordinates":[-73.936001,40.775778],"type":"Point"}
}