{
  "type": "Feature",
  "properties": {
    "iso:country":"US",
    "sg:address":"132 N Carll Ave",
    "sg:city":"Babylon",
    "sg:classifiers":[
        {
            "category":"Personal",
            "subcategory":"Beauty Salon",
            "type":"Services"
        }
    ],
    "sg:phone":"+1   ",
    "sg:postcode":"11702",
    "sg:province":"NY",
    "sg:tags":[
        "shop"
    ],
    "wof:name":"Diva Nail Salon",
    "wof:placetype":"venue"
},
  "geometry": {"coordinates":[-73.325947,40.700604],"type":"Point"}
}