{
  "type": "Feature",
  "properties": {
    "addr:full":"234 MacDougal Street Brooklyn NY 11233",
    "addr:housenumber":"234",
    "addr:postcode":"11233",
    "addr:street":"Macdougal Street",
    "iso:country":"US",
    "sg:address":"234 MacDougal Street",
    "sg:city":"Brooklyn",
    "sg:classifiers":[
        {
            "category":"Social Services",
            "subcategory":"Child Care",
            "type":"Services"
        }
    ],
    "sg:phone":"+1 718 453 4256",
    "sg:postcode":"11233",
    "sg:province":"NY",
    "sg:tags":[
        "day"
    ],
    "wof:name":"Precious Gift Day-Care Center",
    "wof:placetype":"venue"
},
  "geometry": {"coordinates":[-73.91111600000001,40.680135],"type":"Point"}
}