{
  "type": "Feature",
  "properties": {
    "addr:full":"10 Davids Dr Hauppauge NY 11788",
    "addr:housenumber":"10",
    "addr:postcode":"11788",
    "addr:street":"Davids Dr",
    "iso:country":"US",
    "sg:address":"10 Davids Dr",
    "sg:city":"Hauppauge",
    "sg:classifiers":[
        {
            "category":"Manufacturing",
            "subcategory":"Food",
            "type":"Manufacturing & Wholesale Goods"
        }
    ],
    "sg:phone":"+1   ",
    "sg:postcode":"11788",
    "sg:province":"NY",
    "sg:tags":[
        "manufacture",
        "flavor",
        "extract"
    ],
    "wof:name":"Borthwicks Flavors U S A",
    "wof:placetype":"venue"
},
  "geometry": {"coordinates":[-73.262891,40.818886],"type":"Point"}
}