{
  "type": "Feature",
  "properties": {
    "iso:country":"US",
    "sg:address":"7 Old Dock Rd",
    "sg:city":"Yaphank",
    "sg:classifiers":[
        {
            "category":"Wholesale",
            "subcategory":"Electrical",
            "type":"Manufacturing & Wholesale Goods"
        }
    ],
    "sg:phone":"+1 631 205 1061",
    "sg:postcode":"11980",
    "sg:province":"NY",
    "sg:tags":[
        "battery"
    ],
    "wof:name":"Lyntronics",
    "wof:placetype":"venue"
},
  "geometry": {"coordinates":[-72.94384599999999,40.810439],"type":"Point"}
}