{
  "type": "Feature",
  "properties": {
    "iso:country":"US",
    "sg:address":"2800 Middle Country Rd",
    "sg:city":"Lake Grove",
    "sg:classifiers":[
        {
            "category":"Professional",
            "subcategory":"Management & Consulting",
            "type":"Services"
        }
    ],
    "sg:phone":"+1 631 471 0900",
    "sg:postcode":"11755",
    "sg:province":"NY",
    "sg:tags":[
        "marketing",
        "program"
    ],
    "wof:name":"Urban Marketing Inc",
    "wof:placetype":"venue"
},
  "geometry": {"coordinates":[-73.110347,40.859461],"type":"Point"}
}