{
  "type": "Feature",
  "properties": {
    "addr:full":"315 E 69th St Ofc New York NY 10021",
    "addr:housenumber":"315",
    "addr:postcode":"10021",
    "addr:street":"E 69Th St",
    "iso:country":"US",
    "sg:address":"315 E 69th St Ofc",
    "sg:city":"New York",
    "sg:classifiers":[
        {
            "category":"Health Services",
            "subcategory":"Doctor",
            "type":"Services"
        }
    ],
    "sg:phone":"+1 212 535 7474",
    "sg:postcode":"10021",
    "sg:province":"NY",
    "wof:name":"Spitzer J M MD",
    "wof:placetype":"venue"
},
  "geometry": {"coordinates":[-73.958702,40.768398],"type":"Point"}
}