{
  "type": "Feature",
  "properties": {
    "addr:full":"730 Co Rd 10 Corinth NY 12822",
    "addr:housenumber":"730;10",
    "addr:postcode":"12822",
    "addr:street":"Co Rd",
    "iso:country":"US",
    "sg:address":"730 Co Rd 10",
    "sg:city":"Corinth",
    "sg:classifiers":[
        {
            "category":"Shopping",
            "type":"Retail Goods"
        }
    ],
    "sg:phone":"+1   ",
    "sg:postcode":"12822",
    "sg:province":"NY",
    "sg:tags":[
        "merchandise"
    ],
    "wof:name":"Brooks Bay Country Store Inc",
    "wof:placetype":"venue"
},
  "geometry": {"coordinates":[-73.945589,43.268901],"type":"Point"}
}