{
  "type": "Feature",
  "properties": {
    "addr:full":"10 Plattekill Ave New Paltz NY 12561",
    "addr:housenumber":"10",
    "addr:postcode":"12561",
    "addr:street":"Plattekill Ave",
    "iso:country":"US",
    "sg:address":"10 Plattekill Ave",
    "sg:city":"New Paltz",
    "sg:classifiers":[
        {
            "category":"Restaurant",
            "type":"Food & Drink"
        },
        {
            "category":"Tea Room",
            "type":"Food & Drink"
        }
    ],
    "sg:menulink":"http://www.allmenus.com/ny/new-paltz/282267-village-tea-room/menu/",
    "sg:phone":"+1 845 255 3434",
    "sg:postcode":"12561",
    "sg:province":"NY",
    "sg:tags":[
        "american"
    ],
    "wof:name":"Village Tea Room",
    "wof:placetype":"venue"
},
  "geometry": {"coordinates":[-74.084444,41.747257],"type":"Point"}
}