{
  "type": "Feature",
  "properties": {
    "addr:full":"31 Washington Sq W Ste 1R New York NY 10011",
    "addr:housenumber":"31",
    "addr:postcode":"10011",
    "addr:street":"Washington Sq W Ste 1R",
    "iso:country":"US",
    "sg:address":"31 Washington Sq W Ste 1R",
    "sg:city":"New York",
    "sg:classifiers":[
        {
            "category":"Health Services",
            "subcategory":"Dentist",
            "type":"Services"
        }
    ],
    "sg:phone":"+1 212 240 9444",
    "sg:postcode":"10011",
    "sg:province":"NY",
    "sg:tags":[
        "periodontist",
        "cosmetic"
    ],
    "sg:website":"davidbrismandmd.com",
    "wof:name":"David Brisman, DMD, PC",
    "wof:placetype":"venue"
},
  "geometry": {"coordinates":[-73.999183,40.731952],"type":"Point"}
}