{
  "type": "Feature",
  "properties": {
    "iso:country":"US",
    "sg:address":"12 Dunsbach Rd",
    "sg:city":"Clifton Park",
    "sg:classifiers":[
        {
            "category":"Home & Garden",
            "subcategory":"Home Furnishings",
            "type":"Retail Goods"
        }
    ],
    "sg:phone":"+1   ",
    "sg:postcode":"12065",
    "sg:province":"NY",
    "wof:name":"West Creasant Pottery",
    "wof:placetype":"venue"
},
  "geometry": {"coordinates":[-73.757698,42.810617],"type":"Point"}
}