{
  "type": "Feature",
  "properties": {
    "addr:full":"135 Montgomery Ave Scarsdale NY 10583",
    "addr:housenumber":"135",
    "addr:postcode":"10583",
    "addr:street":"Montgomery Ave",
    "iso:country":"US",
    "sg:address":"135 Montgomery Ave",
    "sg:city":"Scarsdale",
    "sg:classifiers":[
        {
            "category":"Insurance",
            "subcategory":"Hazard Insurance",
            "type":"Services"
        }
    ],
    "sg:phone":"+1 914 722 9180",
    "sg:postcode":"10583",
    "sg:province":"NY",
    "sg:tags":[
        "commercial",
        "business"
    ],
    "wof:name":"Raben Capital Growth",
    "wof:placetype":"venue"
},
  "geometry": {"coordinates":[-73.805223,40.978305],"type":"Point"}
}