{
  "type": "Feature",
  "properties": {
    "iso:country":"US",
    "sg:address":"1770 Mecklenburg Rd",
    "sg:city":"Ithaca",
    "sg:classifiers":[
        {
            "category":"Building & Trades",
            "subcategory":"Construction",
            "type":"Services"
        }
    ],
    "sg:phone":"+1 607 539 3350",
    "sg:postcode":"14850",
    "sg:province":"NY",
    "sg:tags":[
        "dry wall",
        "contractor"
    ],
    "wof:name":"Robert Card",
    "wof:placetype":"venue"
},
  "geometry": {"coordinates":[-76.594925,42.452153],"type":"Point"}
}