{
  "type": "Feature",
  "properties": {
    "iso:country":"US",
    "sg:address":"35 Dix Hills Rd",
    "sg:city":"Huntington",
    "sg:classifiers":[
        {
            "category":"Organizations",
            "subcategory":"Membership Organization",
            "type":"Services"
        }
    ],
    "sg:phone":"+1 631 549 7314",
    "sg:postcode":"11743",
    "sg:province":"NY",
    "sg:tags":[
        "animal"
    ],
    "wof:name":"International Somali Cat Club",
    "wof:placetype":"venue"
},
  "geometry": {"coordinates":[-73.374634,40.843389],"type":"Point"}
}