{
  "type": "Feature",
  "properties": {
    "addr:full":"301 W 89 St New York NY 10024",
    "addr:housenumber":"301",
    "addr:postcode":"10024",
    "addr:street":"W 89 St",
    "iso:country":"US",
    "sg:address":"301 W 89 St",
    "sg:city":"New York",
    "sg:classifiers":[
        {
            "category":"Retail",
            "subcategory":"Repair Shop",
            "type":"Services"
        }
    ],
    "sg:phone":"+1 646 224 0839",
    "sg:postcode":"10024",
    "sg:province":"NY",
    "sg:tags":[
        "lock",
        "locksmith"
    ],
    "wof:name":"Locksmith Number 1 24 Hour",
    "wof:placetype":"venue"
},
  "geometry": {"coordinates":[-73.97866999999999,40.791751],"type":"Point"}
}