{
  "type": "Feature",
  "properties": {
    "addr:full":"162 W 83rd St New York NY 10024",
    "addr:housenumber":"162",
    "addr:postcode":"10024",
    "addr:street":"W 83Rd St",
    "iso:country":"US",
    "sg:address":"162 W 83rd St",
    "sg:city":"New York",
    "sg:classifiers":[
        {
            "category":"Sports & Exercise",
            "subcategory":"Gym",
            "type":"Entertainment"
        }
    ],
    "sg:phone":"+1 212 875 1902",
    "sg:postcode":"10024",
    "sg:province":"NY",
    "sg:tags":[
        "trainer",
        "pilate",
        "yoga"
    ],
    "sg:website":"www.crunch.com",
    "wof:name":"Crunch",
    "wof:placetype":"venue"
},
  "geometry": {"coordinates":[-73.975809,40.785465],"type":"Point"}
}