{
  "type": "Feature",
  "properties": {
    "addr:full":"342 Bedford Ave Brooklyn NY 11211",
    "addr:housenumber":"342",
    "addr:postcode":"11211",
    "addr:street":"Bedford Ave",
    "iso:country":"US",
    "sg:address":"342 Bedford Ave",
    "sg:city":"Brooklyn",
    "sg:classifiers":[
        {
            "category":"Personal",
            "subcategory":"Hair Removal",
            "type":"Services"
        },
        {
            "category":"Personal",
            "subcategory":"Skin Care",
            "type":"Services"
        },
        {
            "category":"Personal",
            "subcategory":"Nail Salon",
            "type":"Services"
        }
    ],
    "sg:phone":"+1 718 388 8200",
    "sg:postcode":"11211",
    "sg:province":"NY",
    "sg:website":"www.audreybeautysalon.com",
    "wof:name":"Audrey Beauty Salon",
    "wof:placetype":"venue"
},
  "geometry": {"coordinates":[-73.96256099999999,40.71272],"type":"Point"}
}