{
  "type": "Feature",
  "properties": {
    "addr:full":"333 Hudson St Cornwall On Hudson NY 12520",
    "addr:housenumber":"333",
    "addr:postcode":"12520",
    "addr:street":"Hudson St",
    "iso:country":"US",
    "sg:address":"333 Hudson St",
    "sg:city":"Cornwall On Hudson",
    "sg:classifiers":[
        {
            "category":"Professional",
            "subcategory":"Lawyer & Legal Services",
            "type":"Services"
        }
    ],
    "sg:phone":"+1 845 534 3334",
    "sg:postcode":"12520",
    "sg:province":"NY",
    "wof:name":"Sovak Stefanie Attny",
    "wof:placetype":"venue"
},
  "geometry": {"coordinates":[-74.21843,41.44392],"type":"Point"}
}