{
  "type": "Feature",
  "properties": {
    "iso:country":"US",
    "sg:address":"4797 Kasson Rd",
    "sg:city":"Syracuse",
    "sg:classifiers":[
        {
            "category":"Professional",
            "type":"Services"
        }
    ],
    "sg:phone":"+1   ",
    "sg:postcode":"13215",
    "sg:province":"NY",
    "wof:name":"Candle Bouquet",
    "wof:placetype":"venue"
},
  "geometry": {"coordinates":[-76.260502,42.987852],"type":"Point"}
}