{
  "type": "Feature",
  "properties": {
    "addr:full":"206 Ramapo Rd Garnerville NY 10923",
    "addr:housenumber":"206",
    "addr:postcode":"10923",
    "addr:street":"Ramapo Rd",
    "iso:country":"US",
    "sg:address":"206 Ramapo Rd",
    "sg:city":"Garnerville",
    "sg:classifiers":[
        {
            "category":"Building & Trades",
            "subcategory":"Cleaning & Sanitation",
            "type":"Services"
        }
    ],
    "sg:phone":"+1 845 786 0313",
    "sg:postcode":"10923",
    "sg:province":"NY",
    "sg:tags":[
        "janitor"
    ],
    "wof:name":"Aviola Cleaning Svc",
    "wof:placetype":"venue"
},
  "geometry": {"coordinates":[-73.98650499999999,41.200311],"type":"Point"}
}