{
  "type": "Feature",
  "properties": {
    "iso:country":"US",
    "sg:address":"925 River Rd",
    "sg:city":"Binghamton",
    "sg:classifiers":[
        {
            "category":"Wholesale",
            "subcategory":"Auto Parts",
            "type":"Manufacturing & Wholesale Goods"
        }
    ],
    "sg:phone":"+1 607 648 4676",
    "sg:postcode":"13901",
    "sg:province":"NY",
    "sg:tags":[
        "automotive",
        "retail"
    ],
    "wof:name":"OShea Auto Parts Inc",
    "wof:placetype":"venue"
},
  "geometry": {"coordinates":[-75.85236,42.165951],"type":"Point"}
}