{
  "type": "Feature",
  "properties": {
    "iso:country":"US",
    "sg:address":"178 Fairlawn Rd",
    "sg:city":"Buffalo",
    "sg:classifiers":[
        {
            "category":"Professional",
            "subcategory":"Computer Services",
            "type":"Services"
        }
    ],
    "sg:phone":"+1 716 864 2939",
    "sg:postcode":"14226",
    "sg:province":"NY",
    "sg:tags":[
        "related"
    ],
    "wof:name":"Business Intelligence Services",
    "wof:placetype":"venue"
},
  "geometry": {"coordinates":[-78.79610099999999,42.964983],"type":"Point"}
}