{
  "type": "Feature",
  "properties": {
    "addr:full":"53 Old Rte 22 Armonk NY 10504",
    "addr:housenumber":"53",
    "addr:postcode":"10504",
    "addr:street":"Old Rte 22",
    "iso:country":"US",
    "sg:address":"53 Old Rte 22",
    "sg:city":"Armonk",
    "sg:classifiers":[
        {
            "category":"Professional",
            "subcategory":"Management & Consulting",
            "type":"Services"
        }
    ],
    "sg:phone":"+1 914 273 2275",
    "sg:postcode":"10504",
    "sg:province":"NY",
    "sg:tags":[
        "marketing",
        "program"
    ],
    "sg:website":"www.goldnfishmarketing.com",
    "wof:name":"Gold N Fish Marketing Group",
    "wof:placetype":"venue"
},
  "geometry": {"coordinates":[-73.71760399999999,41.119764],"type":"Point"}
}