{
  "type": "Feature",
  "properties": {
    "iso:country":"US",
    "sg:address":"400 Mason Rd",
    "sg:city":"Fairport",
    "sg:classifiers":[
        {
            "category":"Freight",
            "type":"Transportation"
        }
    ],
    "sg:phone":"+1   ",
    "sg:postcode":"14450",
    "sg:province":"NY",
    "sg:tags":[
        "trucking"
    ],
    "wof:name":"Worldwide Transportation Inc",
    "wof:placetype":"venue"
},
  "geometry": {"coordinates":[-77.40707,43.065595],"type":"Point"}
}