{
  "type": "Feature",
  "properties": {
    "addr:full":"395 Merrick Rd Amityville NY 11701",
    "addr:housenumber":"395",
    "addr:postcode":"11701",
    "addr:street":"Merrick Rd",
    "iso:country":"US",
    "sg:address":"395 Merrick Rd",
    "sg:city":"Amityville",
    "sg:classifiers":[
        {
            "category":"Wholesale",
            "subcategory":"Jewelry",
            "type":"Manufacturing & Wholesale Goods"
        }
    ],
    "sg:phone":"+1 631 264 0626",
    "sg:postcode":"11701",
    "sg:province":"NY",
    "sg:tags":[
        "buyer"
    ],
    "wof:name":"Snug Harbor Jewelers",
    "wof:placetype":"venue"
},
  "geometry": {"coordinates":[-73.412706,40.669903],"type":"Point"}
}