{
  "type": "Feature",
  "properties": {
    "addr:full":"100 W Utica St Oswego NY 13126",
    "addr:housenumber":"100",
    "addr:postcode":"13126",
    "addr:street":"W Utica St",
    "iso:country":"US",
    "sg:address":"100 W Utica St",
    "sg:city":"Oswego",
    "sg:classifiers":[
        {
            "category":"Insurance",
            "subcategory":"Insurance Agent",
            "type":"Services"
        }
    ],
    "sg:phone":"+1 315 343 5268",
    "sg:postcode":"13126",
    "sg:province":"NY",
    "wof:name":"Northwestern Mutual Financial",
    "wof:placetype":"venue"
},
  "geometry": {"coordinates":[-76.51672600000001,43.450396],"type":"Point"}
}