{
  "type": "Feature",
  "properties": {
    "addr:full":"205 Ave U Brooklyn NY 11223",
    "addr:housenumber":"205",
    "addr:postcode":"11223",
    "addr:street":"Ave U",
    "iso:country":"US",
    "sg:address":"205 Ave U",
    "sg:city":"Brooklyn",
    "sg:classifiers":[
        {
            "category":"Health Services",
            "subcategory":"Doctor",
            "type":"Services"
        }
    ],
    "sg:phone":"+1 718 372 0900",
    "sg:postcode":"11223",
    "sg:province":"NY",
    "sg:tags":[
        "dentist"
    ],
    "wof:name":"Tamia Dental Care",
    "wof:placetype":"venue"
},
  "geometry": {"coordinates":[-73.975588,40.596719],"type":"Point"}
}