{
  "type": "Feature",
  "properties": {
    "addr:full":"1544 Mount Hope Ave Rochester NY 14620",
    "addr:housenumber":"1544",
    "addr:postcode":"14620",
    "addr:street":"Mount Hope Ave",
    "iso:country":"US",
    "sg:address":"1544 Mount Hope Ave",
    "sg:city":"Rochester",
    "sg:classifiers":[
        {
            "category":"Education",
            "subcategory":"Special Training",
            "type":"Public Place"
        }
    ],
    "sg:phone":"+1 585 461 9320",
    "sg:postcode":"14620",
    "sg:province":"NY",
    "wof:name":"Kaplan Inc",
    "wof:placetype":"venue"
},
  "geometry": {"coordinates":[-77.6199,43.11957],"type":"Point"}
}