{
  "type": "Feature",
  "properties": {
    "addr:full":"63 Nelson St Auburn NY 13021",
    "addr:housenumber":"63",
    "addr:postcode":"13021",
    "addr:street":"Nelson St",
    "iso:country":"US",
    "sg:address":"63 Nelson St",
    "sg:city":"Auburn",
    "sg:classifiers":[
        {
            "category":"Restaurant",
            "type":"Food & Drink"
        }
    ],
    "sg:phone":"+1 315 655 8912",
    "sg:postcode":"13021",
    "sg:province":"NY",
    "sg:tags":[
        "parlor",
        "ice",
        "cream"
    ],
    "wof:name":"Kimberly's Ice Cream Factory",
    "wof:placetype":"venue"
},
  "geometry": {"coordinates":[-76.562634,42.938898],"type":"Point"}
}