{
  "type": "Feature",
  "properties": {
    "addr:full":"986 Winthrop St Brooklyn NY 11212",
    "addr:housenumber":"986",
    "addr:postcode":"11212",
    "addr:street":"Winthrop St",
    "iso:country":"US",
    "sg:address":"986 Winthrop St",
    "sg:city":"Brooklyn",
    "sg:classifiers":[
        {
            "category":"Restaurant",
            "type":"Food & Drink"
        }
    ],
    "sg:phone":"+1 718 566 8571",
    "sg:postcode":"11212",
    "sg:province":"NY",
    "wof:name":"Butches Restaurant Inc",
    "wof:placetype":"venue"
},
  "geometry": {"coordinates":[-73.926799,40.659452],"type":"Point"}
}