{
  "type": "Feature",
  "properties": {
    "iso:country":"US",
    "sg:address":"5840 Creekview Dr",
    "sg:city":"Clarence Center",
    "sg:classifiers":[
        {
            "category":"Wholesale",
            "subcategory":"Machinery & Supplies",
            "type":"Manufacturing & Wholesale Goods"
        },
        {
            "category":"Building & Trades",
            "subcategory":"Construction",
            "type":"Services"
        }
    ],
    "sg:phone":"+1 716 741 3873",
    "sg:postcode":"14032",
    "sg:province":"NY",
    "sg:tags":[
        "machine",
        "rigging",
        "crane",
        "derrick"
    ],
    "wof:name":"Mc Pherson Steel Corp",
    "wof:placetype":"venue"
},
  "geometry": {"coordinates":[-78.62945000000001,43.00618],"type":"Point"}
}