{
  "type": "Feature",
  "properties": {
    "addr:full":"157 W 70th St New York NY 10023",
    "addr:housenumber":"157",
    "addr:postcode":"10023",
    "addr:street":"W 70Th St",
    "iso:country":"US",
    "sg:address":"157 W 70th St",
    "sg:city":"New York",
    "sg:classifiers":[
        {
            "category":"Personal",
            "type":"Services"
        }
    ],
    "sg:phone":"+1 212 547 6482",
    "sg:postcode":"10023",
    "sg:province":"NY",
    "sg:tags":[
        "towing"
    ],
    "wof:name":"Aaaa Any Towing Company",
    "wof:placetype":"venue"
},
  "geometry": {"coordinates":[-73.9813,40.7766],"type":"Point"}
}