{
  "type": "Feature",
  "properties": {
    "addr:full":"86 E State St Gloversville NY 12078",
    "addr:housenumber":"86",
    "addr:postcode":"12078",
    "addr:street":"E State St",
    "iso:country":"US",
    "sg:address":"86 E State St",
    "sg:city":"Gloversville",
    "sg:classifiers":[
        {
            "category":"Social Services",
            "type":"Services"
        }
    ],
    "sg:phone":"+1   ",
    "sg:postcode":"12078",
    "sg:province":"NY",
    "wof:name":"Caton David Csw & Elinor BSN",
    "wof:placetype":"venue"
},
  "geometry": {"coordinates":[-74.331542,43.067861],"type":"Point"}
}