{
  "type": "Feature",
  "properties": {
    "iso:country":"US",
    "sg:address":"2955 Oneida St",
    "sg:city":"Sauquoit",
    "sg:classifiers":[
        {
            "category":"Restaurant",
            "type":"Food & Drink"
        }
    ],
    "sg:phone":"+1   ",
    "sg:postcode":"13456",
    "sg:province":"NY",
    "sg:tags":[
        "drinking",
        "eating",
        "center",
        "bowling"
    ],
    "wof:name":"Orchard Hall Restrnt",
    "wof:placetype":"venue"
},
  "geometry": {"coordinates":[-75.260093,43.004787],"type":"Point"}
}