{
  "type": "Feature",
  "properties": {
    "addr:full":"214 State Hwy 37 Hogansburg NY 13655",
    "addr:housenumber":"214",
    "addr:postcode":"13655",
    "addr:street":"State Hwy 37",
    "iso:country":"US",
    "sg:address":"214 State Hwy 37",
    "sg:city":"Hogansburg",
    "sg:classifiers":[
        {
            "category":"Restaurant",
            "type":"Food & Drink"
        }
    ],
    "sg:phone":"+1 518 358 4396",
    "sg:postcode":"13655",
    "sg:province":"NY",
    "wof:name":"Victory Lane Diner",
    "wof:placetype":"venue"
},
  "geometry": {"coordinates":[-74.693691,44.978237],"type":"Point"}
}