{
  "type": "Feature",
  "properties": {
    "addr:full":"464 Fargo Ave Buffalo NY 14213",
    "addr:housenumber":"464",
    "addr:postcode":"14213",
    "addr:street":"Fargo Ave",
    "iso:country":"US",
    "sg:address":"464 Fargo Ave",
    "sg:city":"Buffalo",
    "sg:classifiers":[
        {
            "category":"Shopping",
            "subcategory":"Discount & Variety Stores",
            "type":"Retail Goods"
        }
    ],
    "sg:phone":"+1   ",
    "sg:postcode":"14213",
    "sg:province":"NY",
    "wof:name":"Dickersons Tax Shop & Variety",
    "wof:placetype":"venue"
},
  "geometry": {"coordinates":[-78.89478800000001,42.907338],"type":"Point"}
}