{
  "type": "Feature",
  "properties": {
    "iso:country":"US",
    "sg:address":"3861 Walden Ave",
    "sg:city":"Lancaster",
    "sg:classifiers":[
        {
            "category":"Autos & Motor Vehicles",
            "subcategory":"Auto Supplies",
            "type":"Retail Goods"
        },
        {
            "category":"Retail",
            "subcategory":"Auto Repair",
            "type":"Services"
        },
        {
            "category":"Sports & Exercise",
            "subcategory":"Race Track",
            "type":"Entertainment"
        }
    ],
    "sg:phone":"+1 716 684 8971",
    "sg:postcode":"14086",
    "sg:province":"NY",
    "sg:tags":[
        "engines-rebuild",
        "shop",
        "exchange",
        "automobile",
        "accessory",
        "machine",
        "equipment",
        "part",
        "car",
        "performance",
        "racing"
    ],
    "sg:website":"http://www.jlperformance.com",
    "wof:name":"J & L Performance",
    "wof:placetype":"venue"
},
  "geometry": {"coordinates":[-78.65530800000001,42.918439],"type":"Point"}
}