{
  "type": "Feature",
  "properties": {
    "iso:country":"US",
    "sg:address":"486 Central Ave",
    "sg:city":"Albany",
    "sg:classifiers":[
        {
            "category":"Building & Trades",
            "subcategory":"Plumbing",
            "type":"Services"
        },
        {
            "category":"Building & Trades",
            "subcategory":"Construction",
            "type":"Services"
        }
    ],
    "sg:phone":"+1 518 459 1835",
    "sg:postcode":"12206",
    "sg:province":"NY",
    "sg:tags":[
        "heater",
        "plumber",
        "repair",
        "specialty",
        "contractor",
        "water",
        "heating",
        "cleaning",
        "plumbing-drain",
        "sewer"
    ],
    "sg:website":"http://www.bassplumbing.net",
    "wof:name":"S C Bass Plumbing Inc",
    "wof:placetype":"venue"
},
  "geometry": {"coordinates":[-73.777923,42.669534],"type":"Point"}
}