{
  "type": "Feature",
  "properties": {
    "addr:full":"1195 Anderson Ave Bronx NY 10452",
    "addr:housenumber":"1195",
    "addr:postcode":"10452",
    "addr:street":"Anderson Ave",
    "iso:country":"US",
    "sg:address":"1195 Anderson Ave",
    "sg:city":"Bronx",
    "sg:classifiers":[
        {
            "category":"Shopping",
            "subcategory":"Clothing, Apparel, & Fashions",
            "type":"Retail Goods"
        }
    ],
    "sg:phone":"+1   ",
    "sg:postcode":"10452",
    "sg:province":"NY",
    "sg:tags":[
        "handcrafted"
    ],
    "wof:name":"ZEM Productions",
    "wof:placetype":"venue"
},
  "geometry": {"coordinates":[-73.923396,40.837304],"type":"Point"}
}