{
  "type": "Feature",
  "properties": {
    "addr:full":"11 Upper Ln Centerport NY 11721",
    "addr:housenumber":"11",
    "addr:postcode":"11721",
    "addr:street":"Upper Ln",
    "iso:country":"US",
    "sg:address":"11 Upper Ln",
    "sg:city":"Centerport",
    "sg:classifiers":[
        {
            "category":"Building & Trades",
            "subcategory":"Electrical",
            "type":"Services"
        }
    ],
    "sg:phone":"+1 631 757 5436",
    "sg:postcode":"11721",
    "sg:province":"NY",
    "sg:tags":[
        "electrician"
    ],
    "wof:name":"Mc Guire Electric",
    "wof:placetype":"venue"
},
  "geometry": {"coordinates":[-73.364092,40.899272],"type":"Point"}
}