{
  "type": "Feature",
  "properties": {
    "iso:country":"US",
    "sg:address":"7009 Suzanne Ln",
    "sg:city":"Schenectady",
    "sg:classifiers":[
        {
            "category":"Shopping",
            "subcategory":"Gifts & Souvenirs",
            "type":"Retail Goods"
        }
    ],
    "sg:phone":"+1   ",
    "sg:postcode":"12303",
    "sg:province":"NY",
    "wof:name":"Annies Gift Shop",
    "wof:placetype":"venue"
},
  "geometry": {"coordinates":[-73.912556,42.717982],"type":"Point"}
}