{
  "type": "Feature",
  "properties": {
    "addr:full":"2422 Ralph Avenue Brooklyn NY 11234",
    "addr:housenumber":"2422",
    "addr:postcode":"11234",
    "addr:street":"Ralph Avenue",
    "iso:country":"US",
    "sg:address":"2422 Ralph Avenue",
    "sg:city":"Brooklyn",
    "sg:classifiers":[
        {
            "category":"Professional",
            "type":"Services"
        }
    ],
    "sg:phone":"+1 212 354 3096",
    "sg:postcode":"11234",
    "sg:province":"NY",
    "sg:tags":[
        "caterer"
    ],
    "wof:name":"Bon Soir Caterers",
    "wof:placetype":"venue"
},
  "geometry": {"coordinates":[-73.917361,40.619119],"type":"Point"}
}