{
  "type": "Feature",
  "properties": {
    "iso:country":"US",
    "sg:address":"415 Sycamore St",
    "sg:city":"Buffalo",
    "sg:classifiers":[
        {
            "category":"Real Estate",
            "subcategory":"Real Estate Agent",
            "type":"Services"
        }
    ],
    "sg:phone":"+1 716 845 5203",
    "sg:postcode":"14204",
    "sg:province":"NY",
    "wof:name":"Pratt-Willert Business Ctr",
    "wof:placetype":"venue"
},
  "geometry": {"coordinates":[-78.855014,42.892577],"type":"Point"}
}