{
  "type": "Feature",
  "properties": {
    "addr:full":"2751 27th St Astoria NY 11102",
    "addr:housenumber":"2751",
    "addr:postcode":"11102",
    "addr:street":"27Th St",
    "iso:country":"US",
    "sg:address":"2751 27th St",
    "sg:city":"Astoria",
    "sg:classifiers":[
        {
            "category":"Health Services",
            "subcategory":"Chiropractor",
            "type":"Services"
        }
    ],
    "sg:phone":"+1 718 728 0612",
    "sg:postcode":"11102",
    "sg:province":"NY",
    "wof:name":"Astoria Accident and Injury Treatment Center",
    "wof:placetype":"venue"
},
  "geometry": {"coordinates":[-73.924004,40.768299],"type":"Point"}
}