{
  "type": "Feature",
  "properties": {
    "iso:country":"US",
    "sg:address":"410 E Church St",
    "sg:city":"Elmira",
    "sg:classifiers":[
        {
            "category":"Professional",
            "type":"Services"
        }
    ],
    "sg:phone":"+1   ",
    "sg:postcode":"14901",
    "sg:province":"NY",
    "wof:name":"Twin Tier Area Plan Inc",
    "wof:placetype":"venue"
},
  "geometry": {"coordinates":[-76.802588,42.091516],"type":"Point"}
}