{
  "type": "Feature",
  "properties": {
    "iso:country":"US",
    "sg:address":"5901 State Rte 21",
    "sg:city":"Williamson",
    "sg:classifiers":[
        {
            "category":"Food & Beverages",
            "subcategory":"Specialty",
            "type":"Retail Goods"
        }
    ],
    "sg:phone":"+1 315 589 2198",
    "sg:postcode":"14589",
    "sg:province":"NY",
    "sg:tags":[
        "water",
        "bulk",
        "company"
    ],
    "wof:name":"Eaton's Water Hauling",
    "wof:placetype":"venue"
},
  "geometry": {"coordinates":[-77.191728,43.2126],"type":"Point"}
}