{
  "type": "Feature",
  "properties": {
    "addr:full":"1140 Ave of the Americas New York NY 10036",
    "addr:housenumber":"1140",
    "addr:postcode":"10036",
    "addr:street":"Ave Of The Americas",
    "iso:country":"US",
    "sg:address":"1140 Ave of the Americas",
    "sg:city":"New York",
    "sg:classifiers":[
        {
            "category":"Professional",
            "type":"Services"
        }
    ],
    "sg:phone":"+1 212 827 3600",
    "sg:postcode":"10036",
    "sg:province":"NY",
    "sg:tags":[
        "establishment"
    ],
    "sg:website":"www.ncee.net",
    "wof:name":"National Council On Economic",
    "wof:placetype":"venue"
},
  "geometry": {"coordinates":[-73.98271099999999,40.756771],"type":"Point"}
}