{
  "type": "Feature",
  "properties": {
    "iso:country":"US",
    "sg:address":"240 Van Wagner Rd",
    "sg:city":"Poughkeepsie",
    "sg:classifiers":[
        {
            "category":"Freight",
            "type":"Transportation"
        }
    ],
    "sg:phone":"+1 845 471 5337",
    "sg:postcode":"12603",
    "sg:province":"NY",
    "sg:tags":[
        "excavation",
        "work",
        "local",
        "trucking"
    ],
    "wof:name":"Rodar Enterprise Incorporated",
    "wof:placetype":"venue"
},
  "geometry": {"coordinates":[-73.888558,41.709574],"type":"Point"}
}