{
  "type": "Feature",
  "properties": {
    "addr:full":"5006 Veterans Memorial Hwy Holbrook NY 11741",
    "addr:housenumber":"5006",
    "addr:postcode":"11741",
    "addr:street":"Veterans Memorial Hwy",
    "iso:country":"US",
    "sg:address":"5006 Veterans Memorial Hwy",
    "sg:city":"Holbrook",
    "sg:classifiers":[
        {
            "category":"Health Services",
            "subcategory":"Chiropractor",
            "type":"Services"
        }
    ],
    "sg:phone":"+1 631 563 6503",
    "sg:postcode":"11741",
    "sg:province":"NY",
    "wof:name":"Saccone Vincent",
    "wof:placetype":"venue"
},
  "geometry": {"coordinates":[-73.985249,40.775586],"type":"Point"}
}