{
  "type": "Feature",
  "properties": {
    "iso:country":"US",
    "sg:address":"57 Leonard St",
    "sg:city":"New York",
    "sg:classifiers":[
        {
            "category":"Organizations",
            "subcategory":"Non-profit Organization",
            "type":"Services"
        },
        {
            "category":"Organizations",
            "subcategory":"Community Association",
            "type":"Services"
        }
    ],
    "sg:phone":"+1 212 925 3320",
    "sg:postcode":"10013",
    "sg:province":"NY",
    "sg:website":"www.citykids.com",
    "wof:name":"City Kids Foundation Inc",
    "wof:placetype":"venue"
},
  "geometry": {"coordinates":[-74.006497,40.718206],"type":"Point"}
}