{
  "type": "Feature",
  "properties": {
    "iso:country":"US",
    "sg:address":"780 Bryant St",
    "sg:city":"Woodmere",
    "sg:classifiers":[
        {
            "category":"Shopping",
            "subcategory":"Stationery & Office Supplies",
            "type":"Retail Goods"
        },
        {
            "category":"Home & Garden",
            "subcategory":"Furniture",
            "type":"Retail Goods"
        }
    ],
    "sg:phone":"+1 516 295 3176",
    "sg:postcode":"11598",
    "sg:province":"NY",
    "sg:tags":[
        "equipment",
        "store"
    ],
    "sg:website":"www.officefurnituremart.com",
    "wof:name":"Office Furniture Mart Inc",
    "wof:placetype":"venue"
},
  "geometry": {"coordinates":[-73.718498,40.631802],"type":"Point"}
}