{
  "type": "Feature",
  "properties": {
    "addr:full":"1160 5th Ave New York NY 10029",
    "addr:housenumber":"1160",
    "addr:postcode":"10029",
    "addr:street":"5Th Ave",
    "iso:country":"US",
    "sg:address":"1160 5th Ave",
    "sg:city":"New York",
    "sg:classifiers":[
        {
            "category":"Health Services",
            "subcategory":"Doctor",
            "type":"Services"
        }
    ],
    "sg:phone":"+1   ",
    "sg:postcode":"10029",
    "sg:province":"NY",
    "sg:tags":[
        "medical"
    ],
    "wof:name":"Marilyn Schiller PHD",
    "wof:placetype":"venue"
},
  "geometry": {"coordinates":[-73.95481599999999,40.789204],"type":"Point"}
}