{
  "type": "Feature",
  "properties": {
    "addr:full":"51 Forest Rd Monroe NY 10950",
    "addr:housenumber":"51",
    "addr:postcode":"10950",
    "addr:street":"Forest Rd",
    "iso:country":"US",
    "sg:address":"51 Forest Rd",
    "sg:city":"Monroe",
    "sg:classifiers":[
        {
            "category":"Freight",
            "type":"Transportation"
        }
    ],
    "sg:phone":"+1   ",
    "sg:postcode":"10950",
    "sg:province":"NY",
    "sg:tags":[
        "arrangement"
    ],
    "wof:name":"Bill Kj Paying Services",
    "wof:placetype":"venue"
},
  "geometry": {"coordinates":[-74.170197,41.34009],"type":"Point"}
}