{
  "type": "Feature",
  "properties": {
    "addr:full":"3550 Conner St Bronx NY 10475",
    "addr:housenumber":"3550",
    "addr:postcode":"10475",
    "addr:street":"Conner St",
    "iso:country":"US",
    "sg:address":"3550 Conner St",
    "sg:city":"Bronx",
    "sg:classifiers":[
        {
            "category":"Retail",
            "subcategory":"Repair Shop",
            "type":"Services"
        }
    ],
    "sg:phone":"+1 347 332 2971",
    "sg:postcode":"10475",
    "sg:province":"NY",
    "sg:tags":[
        "lock",
        "locksmith"
    ],
    "wof:name":"USA Locksmiths",
    "wof:placetype":"venue"
},
  "geometry": {"coordinates":[-73.827341,40.885331],"type":"Point"}
}