{
  "type": "Feature",
  "properties": {
    "iso:country":"US",
    "sg:address":"489 E 93rd St",
    "sg:city":"Brooklyn",
    "sg:classifiers":[
        {
            "category":"Building & Trades",
            "subcategory":"Electrical",
            "type":"Services"
        }
    ],
    "sg:phone":"+1 718 485 6482",
    "sg:postcode":"11212",
    "sg:province":"NY",
    "sg:tags":[
        "electric",
        "contractor"
    ],
    "wof:name":"Quelcon Electric Co",
    "wof:placetype":"venue"
},
  "geometry": {"coordinates":[-73.918519,40.6552],"type":"Point"}
}