{
  "type": "Feature",
  "properties": {
    "iso:country":"US",
    "sg:address":"220 Brentwood Rd",
    "sg:city":"Bay Shore",
    "sg:classifiers":[
        {
            "category":"Building & Trades",
            "subcategory":"Construction",
            "type":"Services"
        }
    ],
    "sg:phone":"+1 631 665 3900",
    "sg:postcode":"11706",
    "sg:province":"NY",
    "sg:tags":[
        "contractor"
    ],
    "sg:website":"www.vintonconstruction.com",
    "wof:name":"Vinton Constr Inc",
    "wof:placetype":"venue"
},
  "geometry": {"coordinates":[-73.237503,40.7355],"type":"Point"}
}