{
  "type": "Feature",
  "properties": {
    "iso:country":"US",
    "sg:address":"350 E 109th St",
    "sg:city":"New York",
    "sg:classifiers":[
        {
            "category":"Professional",
            "subcategory":"Business Services",
            "type":"Services"
        }
    ],
    "sg:phone":"+1 212 426 5657",
    "sg:postcode":"10029",
    "sg:province":"NY",
    "sg:tags":[
        "recording",
        "studio"
    ],
    "wof:name":"Group LLC",
    "wof:placetype":"venue"
},
  "geometry": {"coordinates":[-73.939607,40.791996],"type":"Point"}
}