{
  "type": "Feature",
  "properties": {
    "addr:full":"350 E 109th St New York NY 10029",
    "addr:housenumber":"350",
    "addr:postcode":"10029",
    "addr:street":"E 109Th St",
    "iso:country":"US",
    "sg:address":"350 E 109th St",
    "sg:city":"New York",
    "sg:classifiers":[
        {
            "category":"Professional",
            "subcategory":"Business Services",
            "type":"Services"
        }
    ],
    "sg:phone":"+1 212 426 5657",
    "sg:postcode":"10029",
    "sg:province":"NY",
    "sg:tags":[
        "recording",
        "studio"
    ],
    "wof:name":"Group LLC",
    "wof:placetype":"venue"
},
  "geometry": {"coordinates":[-73.939607,40.791996],"type":"Point"}
}