{
  "type": "Feature",
  "properties": {
    "iso:country":"US",
    "sg:address":"782 Merrick Rd",
    "sg:city":"Baldwin",
    "sg:classifiers":[
        {
            "category":"Manufacturing",
            "subcategory":"Food",
            "type":"Manufacturing & Wholesale Goods"
        }
    ],
    "sg:phone":"+1 516 771 4701",
    "sg:postcode":"11510",
    "sg:province":"NY",
    "sg:tags":[
        "bakery",
        "prod",
        "cookie",
        "bakers-wholesale"
    ],
    "wof:name":"J And S Homemade Delights Corp",
    "wof:placetype":"venue"
},
  "geometry": {"coordinates":[-73.61311000000001,40.650874],"type":"Point"}
}