{
  "type": "Feature",
  "properties": {
    "iso:country":"US",
    "sg:address":"591 State Hwy 17M",
    "sg:city":"Monroe",
    "sg:classifiers":[
        {
            "category":"Real Estate",
            "subcategory":"Real Estate Agent",
            "type":"Services"
        }
    ],
    "sg:phone":"+1 845 781 7650",
    "sg:postcode":"10950",
    "sg:province":"NY",
    "sg:tags":[
        "agency",
        "rental"
    ],
    "wof:name":"Rallye Rent A Car",
    "wof:placetype":"venue"
},
  "geometry": {"coordinates":[-74.184999,41.321707],"type":"Point"}
}