{
  "type": "Feature",
  "properties": {
    "iso:country":"US",
    "sg:address":"3075 Veterans Memoril Hwy",
    "sg:city":"Ronkonkoma",
    "sg:classifiers":[
        {
            "category":"Banks & Credit Unions",
            "subcategory":"Atm",
            "type":"Services"
        }
    ],
    "sg:phone":"+1 631 289 8100",
    "sg:postcode":"11779",
    "sg:province":"NY",
    "sg:tags":[
        "bankruptcy"
    ],
    "wof:name":"Ferraro & Benedetto P C",
    "wof:placetype":"venue"
},
  "geometry": {"coordinates":[-73.13800000000001,40.7883],"type":"Point"}
}