{
  "type": "Feature",
  "properties": {
    "iso:country":"US",
    "sg:address":"20 Indiana Rd",
    "sg:city":"Suffern",
    "sg:classifiers":[
        {
            "category":"Professional",
            "subcategory":"Computer Services",
            "type":"Services"
        }
    ],
    "sg:phone":"+1   ",
    "sg:postcode":"10924",
    "sg:province":"NY",
    "sg:tags":[
        "prepackaged",
        "software"
    ],
    "wof:name":"Worldwide Business Services",
    "wof:placetype":"venue"
},
  "geometry": {"coordinates":[-74.42267099999999,41.333919],"type":"Point"}
}