{
  "type": "Feature",
  "properties": {
    "iso:country":"US",
    "sg:address":"222 Fullerton Ave",
    "sg:city":"Newburgh",
    "sg:classifiers":[
        {
            "category":"Professional",
            "subcategory":"Computer Services",
            "type":"Services"
        }
    ],
    "sg:phone":"+1 845 784 4149",
    "sg:postcode":"12550",
    "sg:province":"NY",
    "sg:tags":[
        "isp",
        "provider",
        "internet"
    ],
    "wof:name":"Al Iman Wealth Internet Business",
    "wof:placetype":"venue"
},
  "geometry": {"coordinates":[-74.025583,41.509289],"type":"Point"}
}