{
  "type": "Feature",
  "properties": {
    "iso:country":"US",
    "sg:address":"116 S Main St",
    "sg:city":"Horseheads",
    "sg:classifiers":[
        {
            "category":"Real Estate",
            "subcategory":"Surveying",
            "type":"Services"
        }
    ],
    "sg:phone":"+1 607 739 9440",
    "sg:postcode":"14845",
    "sg:province":"NY",
    "sg:tags":[
        "surveyor"
    ],
    "wof:name":"Dennis Wieland Land Surveyor",
    "wof:placetype":"venue"
},
  "geometry": {"coordinates":[-76.820426,42.166926],"type":"Point"}
}