{
  "type": "Feature",
  "properties": {
    "addr:full":"2012 Augusta Rd Oriskany Falls NY 13425",
    "addr:housenumber":"2012",
    "addr:postcode":"13425",
    "addr:street":"Augusta Rd",
    "iso:country":"US",
    "sg:address":"2012 Augusta Rd",
    "sg:city":"Oriskany Falls",
    "sg:classifiers":[
        {
            "category":"Farming",
            "subcategory":"Farm",
            "type":"Manufacturing & Wholesale Goods"
        }
    ],
    "sg:phone":"+1 315 843 6135",
    "sg:postcode":"13425",
    "sg:province":"NY",
    "sg:tags":[
        "crop",
        "general"
    ],
    "wof:name":"Carl Lindberg",
    "wof:placetype":"venue"
},
  "geometry": {"coordinates":[-75.480912,42.955882],"type":"Point"}
}