{
  "type": "Feature",
  "properties": {
    "addr:full":"5601 58th St Maspeth NY 11378",
    "addr:housenumber":"5601",
    "addr:postcode":"11378",
    "addr:street":"58Th St",
    "iso:country":"US",
    "sg:address":"5601 58th St",
    "sg:city":"Maspeth",
    "sg:classifiers":[
        {
            "category":"Arena",
            "subcategory":"Sports Club",
            "type":"Entertainment"
        },
        {
            "category":"Sports & Exercise",
            "subcategory":"Sports Center",
            "type":"Entertainment"
        },
        {
            "category":"Sports & Exercise",
            "subcategory":"Tennis Court",
            "type":"Entertainment"
        }
    ],
    "sg:phone":"+1 718 326 5683",
    "sg:postcode":"11378",
    "sg:province":"NY",
    "sg:tags":[
        "courts-private"
    ],
    "wof:name":"Maspeth Tennis Club Inc",
    "wof:placetype":"venue"
},
  "geometry": {"coordinates":[-73.91203299999999,40.722359],"type":"Point"}
}