{
  "type": "Feature",
  "properties": {
    "addr:full":"1 Battery Park New York NY 10004",
    "addr:housenumber":"1",
    "addr:postcode":"10004",
    "addr:street":"Battery Park",
    "iso:country":"US",
    "sg:address":"1 Battery Park",
    "sg:city":"New York",
    "sg:classifiers":[
        {
            "category":"Professional",
            "subcategory":"Lawyer & Legal Services",
            "type":"Services"
        }
    ],
    "sg:phone":"+1 212 480 2184",
    "sg:postcode":"10004",
    "sg:province":"NY",
    "wof:name":"Legal Aid Society",
    "wof:placetype":"venue"
},
  "geometry": {"coordinates":[-74.014135,40.704635],"type":"Point"}
}