{
  "type": "Feature",
  "properties": {
    "addr:full":"3550 White Plains Rd Bronx NY 10467",
    "addr:housenumber":"3550",
    "addr:postcode":"10467",
    "addr:street":"White Plains Rd",
    "iso:country":"US",
    "sg:address":"3550 White Plains Rd",
    "sg:city":"Bronx",
    "sg:classifiers":[
        {
            "category":"Personal",
            "subcategory":"Beauty Salon",
            "type":"Services"
        }
    ],
    "sg:phone":"+1 718 547 7027",
    "sg:postcode":"10467",
    "sg:province":"NY",
    "wof:name":"God Bless Unisex 2",
    "wof:placetype":"venue"
},
  "geometry": {"coordinates":[-73.86577800000001,40.878057],"type":"Point"}
}