{
  "type": "Feature",
  "properties": {
    "addr:full":"4823 18th Avenue Brooklyn NY 11204",
    "addr:housenumber":"4823",
    "addr:postcode":"11204",
    "addr:street":"18Th Avenue",
    "iso:country":"US",
    "sg:address":"4823 18th Avenue",
    "sg:city":"Brooklyn",
    "sg:classifiers":[
        {
            "category":"Shopping",
            "subcategory":"Shoes",
            "type":"Retail Goods"
        }
    ],
    "sg:phone":"+1 718 871 9700",
    "sg:postcode":"11204",
    "sg:province":"NY",
    "sg:tags":[
        "store"
    ],
    "wof:name":"London Kids",
    "wof:placetype":"venue"
},
  "geometry": {"coordinates":[-73.980768,40.628348],"type":"Point"}
}