{
  "type": "Feature",
  "properties": {
    "iso:country":"US",
    "sg:address":"4314 4th Ave between 43rd and 44th",
    "sg:city":"Brooklyn",
    "sg:classifiers":[
        {
            "category":"Restaurant",
            "type":"Food & Drink"
        }
    ],
    "sg:phone":"+1 718 965 1602",
    "sg:postcode":"11220",
    "sg:province":"NY",
    "sg:tags":[
        "traditional",
        "american",
        "mexican"
    ],
    "sg:website":"www.eclipsebrooklyn.com/",
    "wof:name":"Eclipse",
    "wof:placetype":"venue"
},
  "geometry": {"coordinates":[-74.00863200000001,40.650338],"type":"Point"}
}