{
  "type": "Feature",
  "properties": {
    "addr:full":"358 Knickerbocker Ave Brooklyn NY 11237",
    "addr:housenumber":"358",
    "addr:postcode":"11237",
    "addr:street":"Knickerbocker Ave",
    "iso:country":"US",
    "sg:address":"358 Knickerbocker Ave",
    "sg:city":"Brooklyn",
    "sg:classifiers":[
        {
            "category":"Shopping",
            "subcategory":"Mobile Phones",
            "type":"Retail Goods"
        }
    ],
    "sg:phone":"+1 347 750 6361",
    "sg:postcode":"11237",
    "sg:province":"NY",
    "wof:name":"Veko Wireless",
    "wof:placetype":"venue"
},
  "geometry": {"coordinates":[-73.92175899999999,40.700571],"type":"Point"}
}