{
  "type": "Feature",
  "properties": {
    "addr:full":"135 W 106th St New York NY 10025",
    "addr:housenumber":"135",
    "addr:postcode":"10025",
    "addr:street":"W 106Th St",
    "iso:country":"US",
    "sg:address":"135 W 106th St",
    "sg:city":"New York",
    "sg:classifiers":[
        {
            "category":"Social Services",
            "type":"Services"
        }
    ],
    "sg:phone":"+1 212 749 7015",
    "sg:postcode":"10025",
    "sg:province":"NY",
    "sg:tags":[
        "center"
    ],
    "wof:name":"Manhattan Vly Glden Age Sr Ctr",
    "wof:placetype":"venue"
},
  "geometry": {"coordinates":[-73.964928,40.800087],"type":"Point"}
}