{
  "type": "Feature",
  "properties": {
    "iso:country":"US",
    "sg:address":"396 Broadway",
    "sg:city":"New York",
    "sg:classifiers":[
        {
            "category":"Professional",
            "subcategory":"Management & Consulting",
            "type":"Services"
        }
    ],
    "sg:phone":"+1 212 925 6373",
    "sg:postcode":"10013",
    "sg:province":"NY",
    "sg:tags":[
        "consultant",
        "educational"
    ],
    "wof:name":"New Chinese Times LTD",
    "wof:placetype":"venue"
},
  "geometry": {"coordinates":[-74.002821,40.718045],"type":"Point"}
}