{
  "type": "Feature",
  "properties": {
    "addr:full":"515 Fulton Street Brooklyn NY 11201",
    "addr:housenumber":"515",
    "addr:postcode":"11201",
    "addr:street":"Fulton Street",
    "iso:country":"US",
    "sg:address":"515 Fulton Street",
    "sg:city":"Brooklyn",
    "sg:classifiers":[
        {
            "category":"Retail",
            "subcategory":"Portrait Studio",
            "type":"Services"
        }
    ],
    "sg:phone":"+1 718 488 0153",
    "sg:postcode":"11201",
    "sg:province":"NY",
    "sg:tags":[
        "photography",
        "store"
    ],
    "wof:name":"Lora's Jewelry",
    "wof:placetype":"venue"
},
  "geometry": {"coordinates":[-73.98474,40.690533],"type":"Point"}
}