{
  "type": "Feature",
  "properties": {
    "iso:country":"US",
    "sg:address":"4 Detroit St",
    "sg:city":"North Tonawanda",
    "sg:classifiers":[
        {
            "category":"Professional",
            "type":"Services"
        }
    ],
    "sg:phone":"+1 716 693 1395",
    "sg:postcode":"14120",
    "sg:province":"NY",
    "sg:tags":[
        "establishment"
    ],
    "wof:name":"Niacell Corp",
    "wof:placetype":"venue"
},
  "geometry": {"coordinates":[-78.884647,43.026692],"type":"Point"}
}