{
  "type": "Feature",
  "properties": {
    "iso:country":"US",
    "sg:address":"500 Old Liverpool Rd",
    "sg:city":"Liverpool",
    "sg:classifiers":[
        {
            "category":"Recreation",
            "type":"Entertainment"
        }
    ],
    "sg:phone":"+1 315 451 4244",
    "sg:postcode":"13088",
    "sg:province":"NY",
    "sg:tags":[
        "martial",
        "arts",
        "instruction"
    ],
    "wof:name":"Salt City Karate & Kick Boxing",
    "wof:placetype":"venue"
},
  "geometry": {"coordinates":[-76.188327,43.088335],"type":"Point"}
}