{
  "type": "Feature",
  "properties": {
    "iso:country":"US",
    "sg:address":"2140 Pond Rd Unit 8",
    "sg:city":"Ronkonkoma",
    "sg:classifiers":[
        {
            "category":"Building & Trades",
            "subcategory":"Plumbing",
            "type":"Services"
        }
    ],
    "sg:phone":"+1 631 737 0991",
    "sg:postcode":"11779",
    "sg:province":"NY",
    "wof:name":"Lange Plumbing & Heating",
    "wof:placetype":"venue"
},
  "geometry": {"coordinates":[-73.1185,40.797798],"type":"Point"}
}