{
  "type": "Feature",
  "properties": {
    "addr:full":"100 Merriam Hts Wellsville NY 14895",
    "addr:housenumber":"100",
    "addr:postcode":"14895",
    "addr:street":"Merriam Hts",
    "iso:country":"US",
    "sg:address":"100 Merriam Hts",
    "sg:city":"Wellsville",
    "sg:classifiers":[
        {
            "category":"Real Estate",
            "subcategory":"Real Estate Operator",
            "type":"Services"
        }
    ],
    "sg:phone":"+1 585 593 1268",
    "sg:postcode":"14895",
    "sg:province":"NY",
    "sg:tags":[
        "building",
        "apartment"
    ],
    "wof:name":"Wellsville Woods",
    "wof:placetype":"venue"
},
  "geometry": {"coordinates":[-77.92417399999999,42.121081],"type":"Point"}
}