{
  "type": "Feature",
  "properties": {
    "addr:full":"28 Federal Ave Buffalo NY 14225",
    "addr:housenumber":"28",
    "addr:postcode":"14225",
    "addr:street":"Federal Ave",
    "iso:country":"US",
    "sg:address":"28 Federal Ave",
    "sg:city":"Buffalo",
    "sg:classifiers":[
        {
            "category":"Building & Trades",
            "subcategory":"Construction",
            "type":"Services"
        }
    ],
    "sg:phone":"+1 716 631 5122",
    "sg:postcode":"14225",
    "sg:province":"NY",
    "sg:tags":[
        "floor",
        "laying",
        "contractor"
    ],
    "wof:name":"William Hamm Floor Covering",
    "wof:placetype":"venue"
},
  "geometry": {"coordinates":[-78.7568,42.940402],"type":"Point"}
}