{
  "type": "Feature",
  "properties": {
    "iso:country":"US",
    "sg:address":"276 S 7th St",
    "sg:city":"Lindenhurst",
    "sg:classifiers":[
        {
            "category":"Professional",
            "type":"Services"
        }
    ],
    "sg:phone":"+1 631 957 0972",
    "sg:postcode":"11757",
    "sg:province":"NY",
    "sg:tags":[
        "establishment"
    ],
    "wof:name":"A B Intl",
    "wof:placetype":"venue"
},
  "geometry": {"coordinates":[-73.37818900000001,40.682685],"type":"Point"}
}