{
  "type": "Feature",
  "properties": {
    "addr:full":"223 W 70th Street New York NY 10023",
    "addr:housenumber":"223",
    "addr:postcode":"10023",
    "addr:street":"W 70Th Street",
    "iso:country":"US",
    "sg:address":"223 W 70th Street",
    "sg:city":"New York",
    "sg:classifiers":[
        {
            "category":"Arts & Performance",
            "subcategory":"Arts Center",
            "type":"Entertainment"
        }
    ],
    "sg:phone":"+1 212 874 4308",
    "sg:postcode":"10023",
    "sg:province":"NY",
    "sg:tags":[
        "performing"
    ],
    "wof:name":"Performing Arts Sth",
    "wof:placetype":"venue"
},
  "geometry": {"coordinates":[-73.983228,40.777587],"type":"Point"}
}