{
  "type": "Feature",
  "properties": {
    "addr:full":"2558 E Tremont Ave Bronx NY 10461",
    "addr:housenumber":"2558",
    "addr:postcode":"10461",
    "addr:street":"E Tremont Ave",
    "iso:country":"US",
    "sg:address":"2558 E Tremont Ave",
    "sg:city":"Bronx",
    "sg:classifiers":[
        {
            "category":"Building & Trades",
            "subcategory":"Pest Control",
            "type":"Services"
        }
    ],
    "sg:phone":"+1 718 792 7667",
    "sg:postcode":"10461",
    "sg:province":"NY",
    "sg:tags":[
        "termite"
    ],
    "wof:name":"Bongiovi Exterminating",
    "wof:placetype":"venue"
},
  "geometry": {"coordinates":[-73.84939199999999,40.842918],"type":"Point"}
}