{
  "type": "Feature",
  "properties": {
    "addr:full":"7 Tucker Rd Stony Creek NY 12878",
    "addr:housenumber":"7",
    "addr:postcode":"12878",
    "addr:street":"Tucker Rd",
    "iso:country":"US",
    "sg:address":"7 Tucker Rd",
    "sg:city":"Stony Creek",
    "sg:classifiers":[
        {
            "category":"Shopping",
            "subcategory":"Gifts & Souvenirs",
            "type":"Retail Goods"
        }
    ],
    "sg:phone":"+1   ",
    "sg:postcode":"12878",
    "sg:province":"NY",
    "wof:name":"Mountain Creek Gifts",
    "wof:placetype":"venue"
},
  "geometry": {"coordinates":[-73.95913,43.448938],"type":"Point"}
}