{
  "type": "Feature",
  "properties": {
    "addr:full":"5250 Fieldston Rd Bronx NY 10471",
    "addr:housenumber":"5250",
    "addr:postcode":"10471",
    "addr:street":"Fieldston Rd",
    "iso:country":"US",
    "sg:address":"5250 Fieldston Rd",
    "sg:city":"Bronx",
    "sg:classifiers":[
        {
            "category":"Education",
            "subcategory":"School",
            "type":"Public Place"
        }
    ],
    "sg:phone":"+1 718 549 8810",
    "sg:postcode":"10471",
    "sg:province":"NY",
    "sg:tags":[
        "a",
        "summer",
        "operates",
        "also",
        "as",
        "elementary",
        "secondary"
    ],
    "sg:website":"www.riverdale.edu",
    "wof:name":"Riverdale Country School Inc",
    "wof:placetype":"venue"
},
  "geometry": {"coordinates":[-73.90169299999999,40.897142],"type":"Point"}
}