{
  "type": "Feature",
  "properties": {
    "iso:country":"US",
    "sg:address":"894 Manhattan Ave",
    "sg:city":"Brooklyn",
    "sg:classifiers":[
        {
            "category":"Health Services",
            "subcategory":"Hospital",
            "type":"Services"
        }
    ],
    "sg:phone":"+1 718 383 1860",
    "sg:postcode":"11222",
    "sg:province":"NY",
    "sg:tags":[
        "general"
    ],
    "wof:name":"Family Health Ctr",
    "wof:placetype":"venue"
},
  "geometry": {"coordinates":[-73.95398900000001,40.729632],"type":"Point"}
}