{
  "type": "Feature",
  "properties": {
    "addr:full":"30 Rodney Street Brooklyn NY 11211",
    "addr:housenumber":"30",
    "addr:postcode":"11211",
    "addr:street":"Rodney Street",
    "iso:country":"US",
    "sg:address":"30 Rodney Street",
    "sg:city":"Brooklyn",
    "sg:classifiers":[
        {
            "category":"Banks & Credit Unions",
            "subcategory":"Financial Services",
            "type":"Services"
        }
    ],
    "sg:phone":"+1 718 387 4520",
    "sg:postcode":"11211",
    "sg:province":"NY",
    "sg:tags":[
        "broker",
        "mortgage"
    ],
    "wof:name":"Parkview Mortgage Corporation",
    "wof:placetype":"venue"
},
  "geometry": {"coordinates":[-73.964156,40.702165],"type":"Point"}
}