{
  "type": "Feature",
  "properties": {
    "iso:country":"US",
    "sg:address":"29 Broadway Fl 9",
    "sg:city":"New York",
    "sg:classifiers":[
        {
            "category":"Professional",
            "subcategory":"Lawyer & Legal Services",
            "type":"Services"
        }
    ],
    "sg:phone":"+1 212 381 9700",
    "sg:postcode":"10006",
    "sg:province":"NY",
    "sg:website":"www.lambosfirm.com",
    "wof:name":"The Lambos Firm",
    "wof:placetype":"venue"
},
  "geometry": {"coordinates":[-74.331255,40.706004],"type":"Point"}
}