{
  "type": "Feature",
  "properties": {
    "addr:full":"28 Shore Park Rd Great Neck NY 11023",
    "addr:housenumber":"28",
    "addr:postcode":"11023",
    "addr:street":"Shore Park Rd",
    "iso:country":"US",
    "sg:address":"28 Shore Park Rd",
    "sg:city":"Great Neck",
    "sg:classifiers":[
        {
            "category":"Health Services",
            "subcategory":"Doctor",
            "type":"Services"
        }
    ],
    "sg:phone":"+1 516 747 8150",
    "sg:postcode":"11023",
    "sg:province":"NY",
    "wof:name":"Alan Kazlow PC",
    "wof:placetype":"venue"
},
  "geometry": {"coordinates":[-73.748971,40.788132],"type":"Point"}
}