{
  "type": "Feature",
  "properties": {
    "iso:country":"US",
    "sg:address":"91 Knickerbocker Ave",
    "sg:city":"Bohemia",
    "sg:classifiers":[
        {
            "category":"Professional",
            "type":"Services"
        }
    ],
    "sg:phone":"+1 631 567 0949",
    "sg:postcode":"11716",
    "sg:province":"NY",
    "sg:tags":[
        "establishment"
    ],
    "wof:name":"Custom Design",
    "wof:placetype":"venue"
},
  "geometry": {"coordinates":[-73.086906,40.771976],"type":"Point"}
}