{
  "type": "Feature",
  "properties": {
    "addr:full":"8201 Flatlands Ave Brooklyn NY 11236",
    "addr:housenumber":"8201",
    "addr:postcode":"11236",
    "addr:street":"Flatlands Ave",
    "iso:country":"US",
    "sg:address":"8201 Flatlands Ave",
    "sg:city":"Brooklyn",
    "sg:classifiers":[
        {
            "category":"Utilities",
            "subcategory":"Mobile Phone",
            "type":"Services"
        }
    ],
    "sg:phone":"+1 718 444 4183",
    "sg:postcode":"11236",
    "sg:province":"NY",
    "sg:tags":[
        "equipment",
        "paging",
        "signaling",
        "system"
    ],
    "wof:name":"A Z Beeper Inc",
    "wof:placetype":"venue"
},
  "geometry": {"coordinates":[-73.911081,40.636932],"type":"Point"}
}