{
  "type": "Feature",
  "properties": {
    "iso:country":"US",
    "sg:address":"425 Parker Rd",
    "sg:city":"Mount Vision",
    "sg:classifiers":[
        {
            "category":"Wholesale",
            "subcategory":"Metals & Minerals",
            "type":"Manufacturing & Wholesale Goods"
        }
    ],
    "sg:phone":"+1 607 263 5784",
    "sg:postcode":"13810",
    "sg:province":"NY",
    "sg:tags":[
        "center"
    ],
    "wof:name":"Morningstar Metalworks",
    "wof:placetype":"venue"
},
  "geometry": {"coordinates":[-75.176839,42.596757],"type":"Point"}
}