{
  "type": "Feature",
  "properties": {
    "addr:full":"31 Old Lyme Rd Chappaqua NY 10514",
    "addr:housenumber":"31",
    "addr:postcode":"10514",
    "addr:street":"Old Lyme Rd",
    "iso:country":"US",
    "sg:address":"31 Old Lyme Rd",
    "sg:city":"Chappaqua",
    "sg:classifiers":[
        {
            "category":"Shopping",
            "subcategory":"Clothing, Apparel, & Fashions",
            "type":"Retail Goods"
        },
        {
            "category":"Manufacturing",
            "subcategory":"Apparel",
            "type":"Manufacturing & Wholesale Goods"
        }
    ],
    "sg:phone":"+1 914 238 2792",
    "sg:postcode":"10514",
    "sg:province":"NY",
    "sg:tags":[
        "apparel-wholesale",
        "manufacturer",
        "women's"
    ],
    "wof:name":"Option-A",
    "wof:placetype":"venue"
},
  "geometry": {"coordinates":[-73.76088,41.151477],"type":"Point"}
}