{
  "type": "Feature",
  "properties": {
    "addr:full":"199 Jericho Tpke Floral Park NY 11001",
    "addr:housenumber":"199",
    "addr:postcode":"11001",
    "addr:street":"Jericho Tpke",
    "iso:country":"US",
    "sg:address":"199 Jericho Tpke",
    "sg:city":"Floral Park",
    "sg:classifiers":[
        {
            "category":"Food & Beverages",
            "subcategory":"Liquor & Beverages",
            "type":"Retail Goods"
        }
    ],
    "sg:phone":"+1 516 488 6800",
    "sg:postcode":"11001",
    "sg:province":"NY",
    "sg:tags":[
        "beer",
        "spirit",
        "wine"
    ],
    "sg:website":"www.westernliquor.com",
    "wof:name":"Western Liquor Inc",
    "wof:placetype":"venue"
},
  "geometry": {"coordinates":[-73.703245,40.728974],"type":"Point"}
}