{
  "type": "Feature",
  "properties": {
    "addr:full":"4 E 14th St New York NY 10003",
    "addr:housenumber":"4",
    "addr:postcode":"10003",
    "addr:street":"E 14Th St",
    "iso:country":"US",
    "sg:address":"4 E 14th St",
    "sg:city":"New York",
    "sg:classifiers":[
        {
            "category":"Building & Trades",
            "subcategory":"Locksmith",
            "type":"Services"
        }
    ],
    "sg:phone":"+1 212 675 3230",
    "sg:postcode":"10003",
    "sg:province":"NY",
    "sg:tags":[
        "key"
    ],
    "wof:name":"14 St Locksmith 24 Hour",
    "wof:placetype":"venue"
},
  "geometry": {"coordinates":[-73.993301,40.735699],"type":"Point"}
}