{
  "type": "Feature",
  "properties": {
    "iso:country":"US",
    "sg:address":"1020 Lehigh Station Rd",
    "sg:city":"Henrietta",
    "sg:classifiers":[
        {
            "category":"Professional",
            "subcategory":"Accounting & Tax Preparation",
            "type":"Services"
        }
    ],
    "sg:phone":"+1 585 359 3120",
    "sg:postcode":"14467",
    "sg:province":"NY",
    "sg:tags":[
        "billing"
    ],
    "sg:website":"www.uhnllc.com",
    "wof:name":"Universal Health Network",
    "wof:placetype":"venue"
},
  "geometry": {"coordinates":[-77.640692,43.058858],"type":"Point"}
}