{
  "type": "Feature",
  "properties": {
    "addr:full":"22 Jill Ln Monsey NY 10952",
    "addr:housenumber":"22",
    "addr:postcode":"10952",
    "addr:street":"Jill Ln",
    "iso:country":"US",
    "sg:address":"22 Jill Ln",
    "sg:city":"Monsey",
    "sg:classifiers":[
        {
            "category":"Arts & Performance",
            "subcategory":"Dance",
            "type":"Entertainment"
        }
    ],
    "sg:phone":"+1 845 425 4429",
    "sg:postcode":"10952",
    "sg:province":"NY",
    "sg:tags":[
        "instruction",
        "dancing"
    ],
    "wof:name":"5 Star Studio",
    "wof:placetype":"venue"
},
  "geometry": {"coordinates":[-74.063889,41.123829],"type":"Point"}
}