{
  "type": "Feature",
  "properties": {
    "iso:country":"US",
    "sg:address":"116 Bellvale Lakes Rd",
    "sg:city":"Warwick",
    "sg:classifiers":[
        {
            "category":"Professional",
            "type":"Services"
        }
    ],
    "sg:phone":"+1 845 986 7733",
    "sg:postcode":"10990",
    "sg:province":"NY",
    "sg:tags":[
        "consultant",
        "geological"
    ],
    "wof:name":"LA Porta & Assoc",
    "wof:placetype":"venue"
},
  "geometry": {"coordinates":[-74.28508600000001,41.265875],"type":"Point"}
}