{
  "type": "Feature",
  "properties": {
    "addr:full":"839 Prospect Ave Bronx NY 10459",
    "addr:housenumber":"839",
    "addr:postcode":"10459",
    "addr:street":"Prospect Ave",
    "iso:country":"US",
    "sg:address":"839 Prospect Ave",
    "sg:city":"Bronx",
    "sg:classifiers":[
        {
            "category":"Personal",
            "subcategory":"Beauty Salon",
            "type":"Services"
        }
    ],
    "sg:phone":"+1 718 861 2229",
    "sg:postcode":"10459",
    "sg:province":"NY",
    "sg:tags":[
        "manicuring"
    ],
    "wof:name":"New Sunny",
    "wof:placetype":"venue"
},
  "geometry": {"coordinates":[-73.901472,40.820136],"type":"Point"}
}