{
  "type": "Feature",
  "properties": {
    "iso:country":"US",
    "sg:address":"31 Wayside Ln",
    "sg:city":"Selden",
    "sg:classifiers":[
        {
            "category":"Building & Trades",
            "subcategory":"Construction",
            "type":"Services"
        }
    ],
    "sg:phone":"+1 631 476 2396",
    "sg:postcode":"11784",
    "sg:province":"NY",
    "sg:tags":[
        "house"
    ],
    "wof:name":"Danisi Home Improvements",
    "wof:placetype":"venue"
},
  "geometry": {"coordinates":[-73.048608,40.891058],"type":"Point"}
}