{
  "type": "Feature",
  "properties": {
    "iso:country":"US",
    "sg:address":"410 E 51 St",
    "sg:city":"New York",
    "sg:classifiers":[
        {
            "category":"Building & Trades",
            "subcategory":"Construction",
            "type":"Services"
        }
    ],
    "sg:phone":"+1 212 355 8787",
    "sg:postcode":"10022",
    "sg:province":"NY",
    "sg:tags":[
        "general",
        "contractor"
    ],
    "wof:name":"A Design Built Group Inc",
    "wof:placetype":"venue"
},
  "geometry": {"coordinates":[-73.964596,40.753988],"type":"Point"}
}