{
  "type": "Feature",
  "properties": {
    "iso:country":"US",
    "sg:address":"161 Freedom Pl",
    "sg:city":"New York",
    "sg:classifiers":[
        {
            "category":"Food & Beverages",
            "subcategory":"Liquor & Beverages",
            "type":"Retail Goods"
        }
    ],
    "sg:phone":"+1 212 875 9463",
    "sg:postcode":"10069",
    "sg:province":"NY",
    "sg:tags":[
        "beer",
        "spirit",
        "wine"
    ],
    "sg:website":"www.renvino.com",
    "wof:name":"Renaissance Fine Wines & Spirits",
    "wof:placetype":"venue"
},
  "geometry": {"coordinates":[-73.98813,40.777164],"type":"Point"}
}