{
  "type": "Feature",
  "properties": {
    "addr:full":"1750 E 18th St Brooklyn NY 11229",
    "addr:housenumber":"1750",
    "addr:postcode":"11229",
    "addr:street":"E 18Th St",
    "iso:country":"US",
    "sg:address":"1750 E 18th St",
    "sg:city":"Brooklyn",
    "sg:classifiers":[
        {
            "category":"Organizations",
            "subcategory":"Religious Organization",
            "type":"Services"
        }
    ],
    "sg:phone":"+1 718 339 4208",
    "sg:postcode":"11229",
    "sg:province":"NY",
    "sg:tags":[
        "clergy"
    ],
    "wof:name":"Judah London",
    "wof:placetype":"venue"
},
  "geometry": {"coordinates":[-73.95511999999999,40.607333],"type":"Point"}
}