{
  "type": "Feature",
  "properties": {
    "iso:country":"US",
    "sg:address":"760 North Ave",
    "sg:city":"New Rochelle",
    "sg:classifiers":[
        {
            "category":"Personal",
            "subcategory":"Beauty Salon",
            "type":"Services"
        }
    ],
    "sg:phone":"+1   ",
    "sg:postcode":"10801",
    "sg:province":"NY",
    "sg:tags":[
        "shop",
        "clothing",
        "jewelry"
    ],
    "wof:name":"Balestris",
    "wof:placetype":"venue"
},
  "geometry": {"coordinates":[-73.78925700000001,40.927226],"type":"Point"}
}