{
  "type": "Feature",
  "properties": {
    "addr:full":"53 E Main St Port Jervis NY 12771",
    "addr:housenumber":"53",
    "addr:postcode":"12771",
    "addr:street":"E Main St",
    "iso:country":"US",
    "sg:address":"53 E Main St",
    "sg:city":"Port Jervis",
    "sg:classifiers":[
        {
            "category":"Restaurant",
            "type":"Food & Drink"
        }
    ],
    "sg:phone":"+1 845 856 6473",
    "sg:postcode":"12771",
    "sg:province":"NY",
    "sg:tags":[
        "delicatessen"
    ],
    "wof:name":"Main Street Deli & Catering",
    "wof:placetype":"venue"
},
  "geometry": {"coordinates":[-74.68489,41.375461],"type":"Point"}
}