{
  "type": "Feature",
  "properties": {
    "addr:full":"61 Sunset Ave Westhampton Bch NY 11978",
    "addr:housenumber":"61",
    "addr:postcode":"11978",
    "addr:street":"Sunset Ave",
    "iso:country":"US",
    "sg:address":"61 Sunset Ave",
    "sg:city":"Westhampton Bch",
    "sg:classifiers":[
        {
            "category":"Food & Beverages",
            "subcategory":"Groceries & Convenience Stores",
            "type":"Retail Goods"
        }
    ],
    "sg:phone":"+1 631 288 9755",
    "sg:postcode":"11978",
    "sg:province":"NY",
    "sg:website":"www.7-eleven.com",
    "wof:name":"7-Eleven",
    "wof:placetype":"venue"
},
  "geometry": {"coordinates":[-72.645161,40.811028],"type":"Point"}
}