{
  "type": "Feature",
  "properties": {
    "iso:country":"US",
    "sg:address":"78 Westlyn Dr",
    "sg:city":"Nanuet",
    "sg:classifiers":[
        {
            "category":"Building & Trades",
            "subcategory":"Construction",
            "type":"Services"
        }
    ],
    "sg:phone":"+1 845 624 1829",
    "sg:postcode":"10954",
    "sg:province":"NY",
    "sg:tags":[
        "painter"
    ],
    "wof:name":"Cannella's Painting",
    "wof:placetype":"venue"
},
  "geometry": {"coordinates":[-74.002443,41.117564],"type":"Point"}
}