{
  "type": "Feature",
  "properties": {
    "iso:country":"US",
    "sg:address":"931 Conklin St",
    "sg:city":"Farmingdale",
    "sg:classifiers":[
        {
            "category":"Shopping",
            "subcategory":"Computers & Home Electronics",
            "type":"Retail Goods"
        }
    ],
    "sg:phone":"+1 631 694 2503",
    "sg:postcode":"11735",
    "sg:province":"NY",
    "sg:tags":[
        "equipment",
        "electronic",
        "supply"
    ],
    "wof:name":"KRP Electronics",
    "wof:placetype":"venue"
},
  "geometry": {"coordinates":[-73.428343,40.737004],"type":"Point"}
}