{
  "type": "Feature",
  "properties": {
    "iso:country":"US",
    "sg:address":"85 Ave A",
    "sg:city":"New York",
    "sg:classifiers":[
        {
            "category":"Restaurant",
            "type":"Food & Drink"
        }
    ],
    "sg:phone":"+1 212 505 6524",
    "sg:postcode":"10009",
    "sg:province":"NY",
    "sg:tags":[
        "sushi",
        "bar",
        "japanese"
    ],
    "sg:website":"www.takahachi.net",
    "wof:name":"Takahachi",
    "wof:placetype":"venue"
},
  "geometry": {"coordinates":[-73.984067,40.725289],"type":"Point"}
}