{
  "type": "Feature",
  "properties": {
    "addr:full":"724 E 187th St Bronx NY 10458",
    "addr:housenumber":"724",
    "addr:postcode":"10458",
    "addr:street":"E 187Th St",
    "iso:country":"US",
    "sg:address":"724 E 187th St",
    "sg:city":"Bronx",
    "sg:classifiers":[
        {
            "category":"Food & Beverages",
            "subcategory":"Groceries & Convenience Stores",
            "type":"Retail Goods"
        }
    ],
    "sg:phone":"+1   ",
    "sg:postcode":"10458",
    "sg:province":"NY",
    "wof:name":"187th Street Food Mart",
    "wof:placetype":"venue"
},
  "geometry": {"coordinates":[-73.882733,40.853649],"type":"Point"}
}