{
  "type": "Feature",
  "properties": {
    "iso:country":"US",
    "sg:address":"505 5th Avenue",
    "sg:city":"New York",
    "sg:classifiers":[
        {
            "category":"Professional",
            "subcategory":"Computer Services",
            "type":"Services"
        }
    ],
    "sg:phone":"+1 212 490 7196",
    "sg:postcode":"10017",
    "sg:province":"NY",
    "sg:tags":[
        "repair"
    ],
    "wof:name":"Alliance Systems",
    "wof:placetype":"venue"
},
  "geometry": {"coordinates":[-73.98087599999999,40.753643],"type":"Point"}
}