{
  "type": "Feature",
  "properties": {
    "addr:full":"502 Elmwood Ave Buffalo NY 14222",
    "addr:housenumber":"502",
    "addr:postcode":"14222",
    "addr:street":"Elmwood Ave",
    "iso:country":"US",
    "sg:address":"502 Elmwood Ave",
    "sg:city":"Buffalo",
    "sg:classifiers":[
        {
            "category":"Restaurant",
            "type":"Food & Drink"
        }
    ],
    "sg:phone":"+1 716 883 3500",
    "sg:postcode":"14222",
    "sg:province":"NY",
    "sg:tags":[
        "pizza"
    ],
    "wof:name":"Avenue Pizza & Sub",
    "wof:placetype":"venue"
},
  "geometry": {"coordinates":[-78.876999,42.9104],"type":"Point"}
}