{
  "type": "Feature",
  "properties": {
    "iso:country":"US",
    "sg:address":"8604 4th Ave",
    "sg:city":"Brooklyn",
    "sg:classifiers":[
        {
            "category":"Restaurant",
            "type":"Food & Drink"
        }
    ],
    "sg:phone":"+1 718 833 8891",
    "sg:postcode":"11209",
    "sg:province":"NY",
    "sg:tags":[
        "fusion",
        "asian"
    ],
    "wof:name":"Anise",
    "wof:placetype":"venue"
},
  "geometry": {"coordinates":[-74.028363,40.622758],"type":"Point"}
}