{
  "type": "Feature",
  "properties": {
    "addr:full":"653 Lawrence St Elmont NY 11003",
    "addr:housenumber":"653",
    "addr:postcode":"11003",
    "addr:street":"Lawrence St",
    "iso:country":"US",
    "sg:address":"653 Lawrence St",
    "sg:city":"Elmont",
    "sg:classifiers":[
        {
            "category":"Social Services",
            "subcategory":"Child Care",
            "type":"Services"
        },
        {
            "category":"Education",
            "subcategory":"Preschool",
            "type":"Public Place"
        },
        {
            "category":"Education",
            "subcategory":"School",
            "type":"Public Place"
        }
    ],
    "sg:phone":"+1 516 593 1543",
    "sg:postcode":"11003",
    "sg:province":"NY",
    "sg:tags":[
        "elementary",
        "day"
    ],
    "sg:website":"www.myrthodaycare.com",
    "wof:name":"MYRTHO'S DAYCARE",
    "wof:placetype":"venue"
},
  "geometry": {"coordinates":[-73.694703,40.690948],"type":"Point"}
}