{
  "type": "Feature",
  "properties": {
    "addr:full":"510 Madison Ave New York NY 10022",
    "addr:housenumber":"510",
    "addr:postcode":"10022",
    "addr:street":"Madison Ave",
    "iso:country":"US",
    "sg:address":"510 Madison Ave",
    "sg:city":"New York",
    "sg:classifiers":[
        {
            "category":"Shopping",
            "subcategory":"Jewelry",
            "type":"Retail Goods"
        }
    ],
    "sg:phone":"+1 212 644 2852",
    "sg:postcode":"10022",
    "sg:province":"NY",
    "sg:tags":[
        "jeweler"
    ],
    "wof:name":"Lanciani Inc",
    "wof:placetype":"venue"
},
  "geometry": {"coordinates":[-73.97467899999999,40.759114],"type":"Point"}
}