{
  "type": "Feature",
  "properties": {
    "iso:country":"US",
    "sg:address":"221 Canal St",
    "sg:city":"New York",
    "sg:classifiers":[
        {
            "category":"Professional",
            "subcategory":"Business Services",
            "type":"Services"
        }
    ],
    "sg:phone":"+1 212 431 6750",
    "sg:postcode":"10013",
    "sg:province":"NY",
    "sg:tags":[
        "translator",
        "interpreter"
    ],
    "wof:name":"Chinese Secretary Svc",
    "wof:placetype":"venue"
},
  "geometry": {"coordinates":[-73.999956,40.718016],"type":"Point"}
}