{
  "type": "Feature",
  "properties": {
    "iso:country":"US",
    "sg:address":"1182 Chenango St",
    "sg:city":"Binghamton",
    "sg:classifiers":[
        {
            "category":"Organizations",
            "subcategory":"Non-profit Organization",
            "type":"Services"
        },
        {
            "category":"Social Services",
            "subcategory":"Adult Care",
            "type":"Services"
        }
    ],
    "sg:phone":"+1 607 772 6904",
    "sg:postcode":"13901",
    "sg:province":"NY",
    "sg:tags":[
        "residential"
    ],
    "wof:name":"Children's Home",
    "wof:placetype":"venue"
},
  "geometry": {"coordinates":[-75.885086,42.151788],"type":"Point"}
}