{
  "type": "Feature",
  "properties": {
    "addr:full":"4076 Albany Post Rd Hyde Park NY 12538",
    "addr:housenumber":"4076",
    "addr:postcode":"12538",
    "addr:street":"Albany Post Rd",
    "iso:country":"US",
    "sg:address":"4076 Albany Post Rd",
    "sg:city":"Hyde Park",
    "sg:classifiers":[
        {
            "category":"Manufacturing",
            "subcategory":"Food",
            "type":"Manufacturing & Wholesale Goods"
        }
    ],
    "sg:phone":"+1 845 229 8277",
    "sg:postcode":"12538",
    "sg:province":"NY",
    "sg:tags":[
        "mfg",
        "malt",
        "beverage",
        "eating",
        "brewer"
    ],
    "wof:name":"Hyde Park Brewing Co Inc",
    "wof:placetype":"venue"
},
  "geometry": {"coordinates":[-73.934691,41.788234],"type":"Point"}
}