{
  "type": "Feature",
  "properties": {
    "iso:country":"US",
    "sg:address":"87 Jamison Rd",
    "sg:city":"Elma",
    "sg:classifiers":[
        {
            "category":"Restaurant",
            "type":"Food & Drink"
        }
    ],
    "sg:phone":"+1 716 892 1122",
    "sg:postcode":"14059",
    "sg:province":"NY",
    "wof:name":"Grover Cleveland Restaurant",
    "wof:placetype":"venue"
},
  "geometry": {"coordinates":[-78.658078,42.805189],"type":"Point"}
}