{
  "type": "Feature",
  "properties": {
    "iso:country":"US",
    "sg:address":"4246 Ridge Lea Rd",
    "sg:city":"Amherst",
    "sg:classifiers":[
        {
            "category":"Professional",
            "subcategory":"Computer Services",
            "type":"Services"
        }
    ],
    "sg:phone":"+1 716 332 0690",
    "sg:postcode":"14228",
    "sg:province":"NY",
    "sg:tags":[
        "repair"
    ],
    "wof:name":"Nettech Solutions",
    "wof:placetype":"venue"
},
  "geometry": {"coordinates":[-78.812198,42.999909],"type":"Point"}
}