{
  "type": "Feature",
  "properties": {
    "addr:full":"469 7th Ave 3rd Floor New York NY 10018",
    "addr:housenumber":"469;3rd floor",
    "addr:postcode":"10018",
    "addr:street":"7Th Ave",
    "iso:country":"US",
    "sg:address":"469 7th Ave 3rd Floor",
    "sg:city":"New York",
    "sg:classifiers":[
        {
            "category":"Professional",
            "subcategory":"Computer Services",
            "type":"Services"
        }
    ],
    "sg:phone":"+1 646 328 3919",
    "sg:postcode":"10018",
    "sg:province":"NY",
    "sg:tags":[
        "email",
        "email-marketing",
        "esp",
        "mail",
        "email-newsletters",
        "software-as-a-service"
    ],
    "sg:website":"http://www.expertsender.com",
    "wof:name":"ExpertSender",
    "wof:placetype":"venue"
},
  "geometry": {"coordinates":[-73.98975299999999,40.752012],"type":"Point"}
}