{
  "type": "Feature",
  "properties": {
    "iso:country":"US",
    "sg:address":"277 Martine Ave",
    "sg:city":"White Plains",
    "sg:classifiers":[
        {
            "category":"Real Estate",
            "subcategory":"Real Estate Operator",
            "type":"Services"
        }
    ],
    "sg:phone":"+1 914 946 4600",
    "sg:postcode":"10601",
    "sg:province":"NY",
    "sg:tags":[
        "building",
        "commercial"
    ],
    "wof:name":"Broadmar Company",
    "wof:placetype":"venue"
},
  "geometry": {"coordinates":[-73.765659,41.031569],"type":"Point"}
}