{
  "type": "Feature",
  "properties": {
    "addr:full":"6130 Grand Ave NY NY 11378",
    "addr:housenumber":"6130",
    "addr:postcode":"11378",
    "addr:street":"Grand Ave",
    "iso:country":"US",
    "sg:address":"6130 Grand Ave",
    "sg:city":"NY",
    "sg:classifiers":[
        {
            "category":"Arts & Performance",
            "subcategory":"Arts Center",
            "type":"Entertainment"
        }
    ],
    "sg:phone":"+1 718 416 1516",
    "sg:postcode":"11378",
    "sg:province":"NY",
    "sg:tags":[
        "performing"
    ],
    "wof:name":"Landrum School of Dance",
    "wof:placetype":"venue"
},
  "geometry": {"coordinates":[-73.904152,40.721935],"type":"Point"}
}