{
  "type": "Feature",
  "properties": {
    "iso:country":"US",
    "sg:address":"235 Main St",
    "sg:city":"Johnson City",
    "sg:classifiers":[
        {
            "category":"Insurance",
            "subcategory":"Insurance Agent",
            "type":"Services"
        }
    ],
    "sg:phone":"+1 607 797 3313",
    "sg:postcode":"13790",
    "sg:province":"NY",
    "wof:name":"Misata Insurance Agency",
    "wof:placetype":"venue"
},
  "geometry": {"coordinates":[-75.955811,42.115462],"type":"Point"}
}