{
  "type": "Feature",
  "properties": {
    "addr:full":"308 Cortelyou Rd Brooklyn NY 11218",
    "addr:housenumber":"308",
    "addr:postcode":"11218",
    "addr:street":"Cortelyou Rd",
    "iso:country":"US",
    "sg:address":"308 Cortelyou Rd",
    "sg:city":"Brooklyn",
    "sg:classifiers":[
        {
            "category":"Restaurant",
            "type":"Food & Drink"
        }
    ],
    "sg:phone":"+1   ",
    "sg:postcode":"11218",
    "sg:province":"NY",
    "sg:tags":[
        "eating"
    ],
    "wof:name":"Miami Cafe Corporation",
    "wof:placetype":"venue"
},
  "geometry": {"coordinates":[-73.97553499999999,40.638187],"type":"Point"}
}