{
  "type": "Feature",
  "properties": {
    "iso:country":"US",
    "sg:address":"146 Broadway",
    "sg:city":"Hawthorne",
    "sg:classifiers":[
        {
            "category":"Wholesale",
            "subcategory":"Sporting Goods",
            "type":"Manufacturing & Wholesale Goods"
        }
    ],
    "sg:phone":"+1 914 747 3237",
    "sg:postcode":"10532",
    "sg:province":"NY",
    "sg:tags":[
        "recreational",
        "supply"
    ],
    "wof:name":"Peggy Payne & Associates Inc",
    "wof:placetype":"venue"
},
  "geometry": {"coordinates":[-73.80222500000001,41.107302],"type":"Point"}
}