{
  "type": "Feature",
  "properties": {
    "iso:country":"US",
    "sg:address":"17 Westover Rd",
    "sg:city":"Slingerlands",
    "sg:classifiers":[
        {
            "category":"Banks & Credit Unions",
            "subcategory":"Financial Services",
            "type":"Services"
        }
    ],
    "sg:phone":"+1 518 475 0145",
    "sg:postcode":"12159",
    "sg:province":"NY",
    "sg:tags":[
        "investment",
        "private"
    ],
    "wof:name":"RSM Limited Partnership",
    "wof:placetype":"venue"
},
  "geometry": {"coordinates":[-73.89100500000001,42.625972],"type":"Point"}
}