{
  "type": "Feature",
  "properties": {
    "iso:country":"US",
    "sg:address":"101 Clark St",
    "sg:city":"Brooklyn",
    "sg:classifiers":[
        {
            "category":"Health Services",
            "subcategory":"Doctor",
            "type":"Services"
        }
    ],
    "sg:phone":"+1 718 625 6526",
    "sg:postcode":"11201",
    "sg:province":"NY",
    "sg:tags":[
        "physician",
        "surgeon"
    ],
    "wof:name":"Guillermina Deportage MD",
    "wof:placetype":"venue"
},
  "geometry": {"coordinates":[-73.99267399999999,40.697495],"type":"Point"}
}