{
  "type": "Feature",
  "properties": {
    "iso:country":"US",
    "sg:address":"3163 Coney Island Ave",
    "sg:city":"Brooklyn",
    "sg:classifiers":[
        {
            "category":"Sports & Exercise",
            "subcategory":"Gym",
            "type":"Entertainment"
        }
    ],
    "sg:phone":"+1 718 332 7270",
    "sg:postcode":"11235",
    "sg:province":"NY",
    "sg:tags":[
        "club",
        "health",
        "studio",
        "gymnasium"
    ],
    "wof:name":"Curves",
    "wof:placetype":"venue"
},
  "geometry": {"coordinates":[-73.95958,40.578245],"type":"Point"}
}