{
  "type": "Feature",
  "properties": {
    "addr:full":"43 Vassar Rd Poughkeepsie NY 12603",
    "addr:housenumber":"43",
    "addr:postcode":"12603",
    "addr:street":"Vassar Rd",
    "iso:country":"US",
    "sg:address":"43 Vassar Rd",
    "sg:city":"Poughkeepsie",
    "sg:classifiers":[
        {
            "category":"Wholesale",
            "subcategory":"Beer",
            "type":"Manufacturing & Wholesale Goods"
        }
    ],
    "sg:phone":"+1 845 462 1820",
    "sg:postcode":"12603",
    "sg:province":"NY",
    "sg:tags":[
        "ale"
    ],
    "wof:name":"Cutty Discount Beverages",
    "wof:placetype":"venue"
},
  "geometry": {"coordinates":[-73.87488500000001,41.65278],"type":"Point"}
}