{
  "type": "Feature",
  "properties": {
    "iso:country":"US",
    "sg:address":"1070 Carroll St",
    "sg:city":"Brooklyn",
    "sg:classifiers":[
        {
            "category":"Communications",
            "subcategory":"Radio Station",
            "type":"Services"
        }
    ],
    "sg:phone":"+1 718 858 7414",
    "sg:postcode":"11225",
    "sg:province":"NY",
    "wof:name":"Caribbean Spotlight",
    "wof:placetype":"venue"
},
  "geometry": {"coordinates":[-73.95529500000001,40.667162],"type":"Point"}
}