{
  "type": "Feature",
  "properties": {
    "iso:country":"US",
    "sg:address":"12 W 18 St",
    "sg:city":"New York",
    "sg:classifiers":[
        {
            "category":"Utilities",
            "subcategory":"Telephone",
            "type":"Services"
        }
    ],
    "sg:phone":"+1 212 741 5100",
    "sg:postcode":"10011",
    "sg:province":"NY",
    "sg:tags":[
        "company"
    ],
    "wof:name":"A Phone Fantasy",
    "wof:placetype":"venue"
},
  "geometry": {"coordinates":[-73.9948,40.739653],"type":"Point"}
}