{
  "type": "Feature",
  "properties": {
    "iso:country":"US",
    "sg:address":"145 4th Avenue",
    "sg:city":"New York",
    "sg:classifiers":[
        {
            "category":"Education",
            "subcategory":"University",
            "type":"Public Place"
        }
    ],
    "sg:phone":"+1 212 998 7200",
    "sg:postcode":"10003",
    "sg:province":"NY",
    "sg:tags":[
        "college"
    ],
    "wof:name":"New York University",
    "wof:placetype":"venue"
},
  "geometry": {"coordinates":[-73.989688,40.733871],"type":"Point"}
}