{
  "type": "Feature",
  "properties": {
    "addr:full":"415 Viola Rd Spring Valley NY 10977",
    "addr:housenumber":"415",
    "addr:postcode":"10977",
    "addr:street":"Viola Rd",
    "iso:country":"US",
    "sg:address":"415 Viola Rd",
    "sg:city":"Spring Valley",
    "sg:classifiers":[
        {
            "category":"Restaurant",
            "type":"Food & Drink"
        }
    ],
    "sg:phone":"+1   ",
    "sg:postcode":"10977",
    "sg:province":"NY",
    "sg:tags":[
        "catering"
    ],
    "sg:website":"www.classiccaterers.com",
    "wof:name":"Classic Caterers Of Rockland",
    "wof:placetype":"venue"
},
  "geometry": {"coordinates":[-74.064126,41.135128],"type":"Point"}
}