{
  "type": "Feature",
  "properties": {
    "addr:full":"8 Gutheil Ln Great Neck NY 11024",
    "addr:housenumber":"8",
    "addr:postcode":"11024",
    "addr:street":"Gutheil Ln",
    "iso:country":"US",
    "sg:address":"8 Gutheil Ln",
    "sg:city":"Great Neck",
    "sg:classifiers":[
        {
            "category":"Shopping",
            "subcategory":"Jewelry",
            "type":"Retail Goods"
        }
    ],
    "sg:phone":"+1   ",
    "sg:postcode":"11024",
    "sg:province":"NY",
    "wof:name":"Signature Jewelry Corp",
    "wof:placetype":"venue"
},
  "geometry": {"coordinates":[-73.733841,40.808746],"type":"Point"}
}