{
  "type": "Feature",
  "properties": {
    "addr:full":"486 E 169th St Bronx NY 10456",
    "addr:housenumber":"486",
    "addr:postcode":"10456",
    "addr:street":"E 169Th St",
    "iso:country":"US",
    "sg:address":"486 E 169th St",
    "sg:city":"Bronx",
    "sg:classifiers":[
        {
            "category":"Retail",
            "subcategory":"Laundry & Dry Cleaning",
            "type":"Services"
        }
    ],
    "sg:phone":"+1 718 538 1751",
    "sg:postcode":"10456",
    "sg:province":"NY",
    "sg:tags":[
        "cleaners"
    ],
    "wof:name":"Elvis Dry Cleaners",
    "wof:placetype":"venue"
},
  "geometry": {"coordinates":[-73.905175,40.832689],"type":"Point"}
}