{
  "type": "Feature",
  "properties": {
    "addr:full":"612 Calvert St Rome NY 13440",
    "addr:housenumber":"612",
    "addr:postcode":"13440",
    "addr:street":"Calvert St",
    "iso:country":"US",
    "sg:address":"612 Calvert St",
    "sg:city":"Rome",
    "sg:classifiers":[
        {
            "category":"Manufacturing",
            "subcategory":"Tools & Machinery",
            "type":"Manufacturing & Wholesale Goods"
        }
    ],
    "sg:phone":"+1   ",
    "sg:postcode":"13440",
    "sg:province":"NY",
    "sg:tags":[
        "industrial",
        "mfg"
    ],
    "wof:name":"BNP Machine & Service",
    "wof:placetype":"venue"
},
  "geometry": {"coordinates":[-75.468552,43.215083],"type":"Point"}
}