{
  "type": "Feature",
  "properties": {
    "iso:country":"US",
    "sg:address":"31 Wicken Sq",
    "sg:city":"Colonie",
    "sg:classifiers":[
        {
            "category":"Professional",
            "subcategory":"Business Services",
            "type":"Services"
        }
    ],
    "sg:phone":"+1 518 452 7894",
    "sg:postcode":"12205",
    "sg:province":"NY",
    "sg:tags":[
        "process",
        "server"
    ],
    "wof:name":"Willach Technical Svc Inc",
    "wof:placetype":"venue"
},
  "geometry": {"coordinates":[-73.849817,42.742968],"type":"Point"}
}