{
  "type": "Feature",
  "properties": {
    "iso:country":"US",
    "sg:address":"13710 Farmers Boulevard",
    "sg:city":"Jamaica",
    "sg:classifiers":[
        {
            "category":"Retail",
            "subcategory":"Auto Repair",
            "type":"Services"
        }
    ],
    "sg:phone":"+1 718 527 7096",
    "sg:postcode":"11434",
    "sg:province":"NY",
    "wof:name":"137 Farmers Auto Repair",
    "wof:placetype":"venue"
},
  "geometry": {"coordinates":[-73.76396099999999,40.673775],"type":"Point"}
}