{
  "type": "Feature",
  "properties": {
    "iso:country":"US",
    "sg:address":"83 Calvin Ave",
    "sg:city":"Syosset",
    "sg:classifiers":[
        {
            "category":"Professional",
            "subcategory":"Detective & Security Services",
            "type":"Services"
        }
    ],
    "sg:phone":"+1 516 677 0131",
    "sg:postcode":"11791",
    "sg:province":"NY",
    "sg:tags":[
        "information",
        "bureau"
    ],
    "wof:name":"Ogman Client Services Ltd",
    "wof:placetype":"venue"
},
  "geometry": {"coordinates":[-73.50967199999999,40.835547],"type":"Point"}
}