{
  "type": "Feature",
  "properties": {
    "addr:full":"526 W 26th St New York NY 10001",
    "addr:housenumber":"526",
    "addr:postcode":"10001",
    "addr:street":"W 26Th St",
    "iso:country":"US",
    "sg:address":"526 W 26th St",
    "sg:city":"New York",
    "sg:classifiers":[
        {
            "category":"Manufacturing",
            "subcategory":"Apparel",
            "type":"Manufacturing & Wholesale Goods"
        }
    ],
    "sg:phone":"+1 212 691 5956",
    "sg:postcode":"10001",
    "sg:province":"NY",
    "sg:tags":[
        "fur"
    ],
    "wof:name":"Art Resources Transfer Inc",
    "wof:placetype":"venue"
},
  "geometry": {"coordinates":[-74.005094,40.750405],"type":"Point"}
}