{
  "type": "Feature",
  "properties": {
    "iso:country":"US",
    "sg:address":"339 Canada St",
    "sg:city":"Lake George",
    "sg:classifiers":[
        {
            "category":"Government",
            "subcategory":"Office",
            "type":"Public Place"
        }
    ],
    "sg:phone":"+1 518 668 9829",
    "sg:postcode":"12845",
    "sg:province":"NY",
    "sg:tags":[
        "village"
    ],
    "wof:name":"Lake George Student Connection",
    "wof:placetype":"venue"
},
  "geometry": {"coordinates":[-73.712402,43.426344],"type":"Point"}
}