{
  "type": "Feature",
  "properties": {
    "addr:full":"621 E 138th St Bronx NY 10454",
    "addr:housenumber":"621",
    "addr:postcode":"10454",
    "addr:street":"E 138Th St",
    "iso:country":"US",
    "sg:address":"621 E 138th St",
    "sg:city":"Bronx",
    "sg:classifiers":[
        {
            "category":"Professional",
            "subcategory":"Business Services",
            "type":"Services"
        }
    ],
    "sg:phone":"+1 718 292 5180",
    "sg:postcode":"10454",
    "sg:province":"NY",
    "sg:tags":[
        "convention",
        "meeting",
        "facility"
    ],
    "wof:name":"Saloma Maria Isabel Sister",
    "wof:placetype":"venue"
},
  "geometry": {"coordinates":[-73.915611,40.80627],"type":"Point"}
}