{
  "type": "Feature",
  "properties": {
    "addr:full":"2543 Elmwood Ave Buffalo NY 14217",
    "addr:housenumber":"2543",
    "addr:postcode":"14217",
    "addr:street":"Elmwood Ave",
    "iso:country":"US",
    "sg:address":"2543 Elmwood Ave",
    "sg:city":"Buffalo",
    "sg:classifiers":[
        {
            "category":"Retail",
            "subcategory":"Auto Repair",
            "type":"Services"
        }
    ],
    "sg:phone":"+1 716 877 1943",
    "sg:postcode":"14217",
    "sg:province":"NY",
    "sg:tags":[
        "automobile",
        "inspection"
    ],
    "wof:name":"Hawke Automotive",
    "wof:placetype":"venue"
},
  "geometry": {"coordinates":[-78.87866,42.966019],"type":"Point"}
}