{
  "type": "Feature",
  "properties": {
    "iso:country":"US",
    "sg:address":"1875 2nd Ave",
    "sg:city":"New York",
    "sg:classifiers":[
        {
            "category":"Home & Garden",
            "subcategory":"Building Materials",
            "type":"Retail Goods"
        }
    ],
    "sg:phone":"+1 212 876 1100",
    "sg:postcode":"10029",
    "sg:province":"NY",
    "sg:tags":[
        "supply"
    ],
    "wof:name":"Century Lumber/Design of the Century",
    "wof:placetype":"venue"
},
  "geometry": {"coordinates":[-73.9468,40.784801],"type":"Point"}
}