{
  "type": "Feature",
  "properties": {
    "iso:country":"US",
    "sg:address":"75 Larchmont Ave",
    "sg:city":"Larchmont",
    "sg:classifiers":[
        {
            "category":"Organizations",
            "subcategory":"Religious Organization",
            "type":"Services"
        }
    ],
    "sg:phone":"+1 914 834 0317",
    "sg:postcode":"10538",
    "sg:province":"NY",
    "sg:tags":[
        "synagogue"
    ],
    "sg:website":"www.larchmonttemple.org",
    "wof:name":"Larchmont Temple",
    "wof:placetype":"venue"
},
  "geometry": {"coordinates":[-73.74982799999999,40.925062],"type":"Point"}
}