{
  "type": "Feature",
  "properties": {
    "iso:country":"US",
    "sg:address":"517 Ocean View Ave",
    "sg:city":"Brooklyn",
    "sg:classifiers":[
        {
            "category":"Health Services",
            "subcategory":"Doctor",
            "type":"Services"
        }
    ],
    "sg:phone":"+1 347 587 5118",
    "sg:postcode":"11235",
    "sg:province":"NY",
    "wof:name":"Dr Krichevsky Medical Pc",
    "wof:placetype":"venue"
},
  "geometry": {"coordinates":[-73.962689,40.579596],"type":"Point"}
}