{
  "type": "Feature",
  "properties": {
    "addr:full":"22 Lawrence Ave Smithtown NY 11787",
    "addr:housenumber":"22",
    "addr:postcode":"11787",
    "addr:street":"Lawrence Ave",
    "iso:country":"US",
    "sg:address":"22 Lawrence Ave",
    "sg:city":"Smithtown",
    "sg:classifiers":[
        {
            "category":"Professional",
            "subcategory":"Business Services",
            "type":"Services"
        }
    ],
    "sg:phone":"+1 631 265 0490",
    "sg:postcode":"11787",
    "sg:province":"NY",
    "sg:tags":[
        "arbitration"
    ],
    "wof:name":"EAC Community Mediation Ctr",
    "wof:placetype":"venue"
},
  "geometry": {"coordinates":[-73.193485,40.854113],"type":"Point"}
}