{
  "type": "Feature",
  "properties": {
    "iso:country":"US",
    "sg:address":"2065 Bergen St",
    "sg:city":"Bellmore",
    "sg:classifiers":[
        {
            "category":"Building & Trades",
            "subcategory":"Construction",
            "type":"Services"
        }
    ],
    "sg:phone":"+1 516 783 9890",
    "sg:postcode":"11710",
    "sg:province":"NY",
    "sg:tags":[
        "carpentry",
        "contractor"
    ],
    "wof:name":"Design Home Interiors Inc",
    "wof:placetype":"venue"
},
  "geometry": {"coordinates":[-73.524385,40.674035],"type":"Point"}
}