{
  "type": "Feature",
  "properties": {
    "addr:full":"85 Bloomingdale Rd Hicksville NY 11801",
    "addr:housenumber":"85",
    "addr:postcode":"11801",
    "addr:street":"Bloomingdale Rd",
    "iso:country":"US",
    "sg:address":"85 Bloomingdale Rd",
    "sg:city":"Hicksville",
    "sg:classifiers":[
        {
            "category":"Freight",
            "type":"Transportation"
        }
    ],
    "sg:phone":"+1 718 895 0110",
    "sg:postcode":"11801",
    "sg:province":"NY",
    "sg:tags":[
        "trucking"
    ],
    "wof:name":"Curatola Bros",
    "wof:placetype":"venue"
},
  "geometry": {"coordinates":[-73.50540700000001,40.747793],"type":"Point"}
}