{
  "type": "Feature",
  "properties": {
    "addr:full":"360 Aaron Ct Kingston NY 12401",
    "addr:housenumber":"360",
    "addr:postcode":"12401",
    "addr:street":"Aaron Ct",
    "iso:country":"US",
    "sg:address":"360 Aaron Ct",
    "sg:city":"Kingston",
    "sg:classifiers":[
        {
            "category":"Social Services",
            "subcategory":"Adult Care",
            "type":"Services"
        }
    ],
    "sg:phone":"+1 845 331 4965",
    "sg:postcode":"12401",
    "sg:province":"NY",
    "sg:tags":[
        "residential"
    ],
    "wof:name":"People Inc",
    "wof:placetype":"venue"
},
  "geometry": {"coordinates":[-74.01486800000001,41.935217],"type":"Point"}
}