{
  "type": "Feature",
  "properties": {
    "addr:full":"630 Broadway Massapequa NY 11758",
    "addr:housenumber":"630",
    "addr:postcode":"11758",
    "addr:street":"Broadway",
    "iso:country":"US",
    "sg:address":"630 Broadway",
    "sg:city":"Massapequa",
    "sg:classifiers":[
        {
            "category":"Restaurant",
            "type":"Food & Drink"
        }
    ],
    "sg:menulink":"http://www.allmenus.com/ny/massapequa/43577-cjs-family-grill/menu/",
    "sg:phone":"+1 516 795 3260",
    "sg:postcode":"11758",
    "sg:province":"NY",
    "sg:tags":[
        "american"
    ],
    "wof:name":"CJ's Family Grill",
    "wof:placetype":"venue"
},
  "geometry": {"coordinates":[-73.46718300000001,40.68654],"type":"Point"}
}