{
  "type": "Feature",
  "properties": {
    "addr:full":"4 Joyce Rd Hartsdale NY 10530",
    "addr:housenumber":"4",
    "addr:postcode":"10530",
    "addr:street":"Joyce Rd",
    "iso:country":"US",
    "sg:address":"4 Joyce Rd",
    "sg:city":"Hartsdale",
    "sg:classifiers":[
        {
            "category":"Building & Trades",
            "subcategory":"Construction",
            "type":"Services"
        }
    ],
    "sg:phone":"+1 718 324 1731",
    "sg:postcode":"10530",
    "sg:province":"NY",
    "sg:tags":[
        "house"
    ],
    "wof:name":"Clonard Construction Ltd",
    "wof:placetype":"venue"
},
  "geometry": {"coordinates":[-73.82662500000001,41.023191],"type":"Point"}
}