{
  "type": "Feature",
  "properties": {
    "addr:full":"461 W 23rd St New York NY 10011",
    "addr:housenumber":"461",
    "addr:postcode":"10011",
    "addr:street":"W 23Rd St",
    "iso:country":"US",
    "sg:address":"461 W 23rd St",
    "sg:city":"New York",
    "sg:classifiers":[
        {
            "category":"Restaurant",
            "type":"Food & Drink"
        }
    ],
    "sg:phone":"+1 212 243 5497",
    "sg:postcode":"10011",
    "sg:province":"NY",
    "wof:name":"La Traviata",
    "wof:placetype":"venue"
},
  "geometry": {"coordinates":[-74.003502,40.747299],"type":"Point"}
}