{
  "type": "Feature",
  "properties": {
    "iso:country":"US",
    "sg:address":"303 W Old Country Rd",
    "sg:city":"Hicksville",
    "sg:classifiers":[
        {
            "category":"Government",
            "subcategory":"Office",
            "type":"Public Place"
        }
    ],
    "sg:phone":"+1 516 934 8502",
    "sg:postcode":"11801",
    "sg:province":"NY",
    "sg:tags":[
        "government-united",
        "state"
    ],
    "sg:website":"http://www.labor.state.ny.us",
    "wof:name":"New York Department Of Labor",
    "wof:placetype":"venue"
},
  "geometry": {"coordinates":[-73.535411,40.759803],"type":"Point"}
}