{
  "type": "Feature",
  "properties": {
    "iso:country":"US",
    "sg:address":"25 Sunken Orchard Ln",
    "sg:city":"Oyster Bay",
    "sg:classifiers":[
        {
            "category":"Shopping",
            "subcategory":"Computers & Home Electronics",
            "type":"Retail Goods"
        }
    ],
    "sg:phone":"+1   ",
    "sg:postcode":"11771",
    "sg:province":"NY",
    "wof:name":"Marwick LLC",
    "wof:placetype":"venue"
},
  "geometry": {"coordinates":[-73.514982,40.854807],"type":"Point"}
}