{
  "type": "Feature",
  "properties": {
    "iso:country":"US",
    "sg:address":"9 Hickory Ln",
    "sg:city":"Wappingers Falls",
    "sg:classifiers":[
        {
            "category":"Wholesale",
            "subcategory":"Vending Machines",
            "type":"Manufacturing & Wholesale Goods"
        }
    ],
    "sg:phone":"+1   ",
    "sg:postcode":"12590",
    "sg:province":"NY",
    "sg:tags":[
        "operator"
    ],
    "wof:name":"Liberty Vending",
    "wof:placetype":"venue"
},
  "geometry": {"coordinates":[-73.93911,41.5912],"type":"Point"}
}