{
  "type": "Feature",
  "properties": {
    "addr:full":"45 Elm Ave Floral Park NY 11001",
    "addr:housenumber":"45",
    "addr:postcode":"11001",
    "addr:street":"Elm Ave",
    "iso:country":"US",
    "sg:address":"45 Elm Ave",
    "sg:city":"Floral Park",
    "sg:classifiers":[
        {
            "category":"Utilities",
            "subcategory":"Refuse",
            "type":"Services"
        }
    ],
    "sg:phone":"+1   ",
    "sg:postcode":"11001",
    "sg:province":"NY",
    "sg:tags":[
        "system"
    ],
    "wof:name":"Safety-Kleen Corp",
    "wof:placetype":"venue"
},
  "geometry": {"coordinates":[-73.714324,40.719149],"type":"Point"}
}