{
  "type": "Feature",
  "properties": {
    "iso:country":"US",
    "sg:address":"282 Canisteo St",
    "sg:city":"Hornell",
    "sg:classifiers":[
        {
            "category":"Insurance",
            "subcategory":"Insurance Agent",
            "type":"Services"
        }
    ],
    "sg:phone":"+1 607 324 2407",
    "sg:postcode":"14843",
    "sg:province":"NY",
    "wof:name":"Jmw Settlements Inc",
    "wof:placetype":"venue"
},
  "geometry": {"coordinates":[-77.66190899999999,42.320273],"type":"Point"}
}