{
  "type": "Feature",
  "properties": {
    "addr:full":"5 Willis Ave Floral Park NY 11001",
    "addr:housenumber":"5",
    "addr:postcode":"11001",
    "addr:street":"Willis Ave",
    "iso:country":"US",
    "sg:address":"5 Willis Ave",
    "sg:city":"Floral Park",
    "sg:classifiers":[
        {
            "category":"Building & Trades",
            "subcategory":"Landscaping Services",
            "type":"Services"
        }
    ],
    "sg:phone":"+1 516 488 3355",
    "sg:postcode":"11001",
    "sg:province":"NY",
    "sg:tags":[
        "landscape",
        "contractor"
    ],
    "wof:name":"City-Scape Landscaping",
    "wof:placetype":"venue"
},
  "geometry": {"coordinates":[-73.698108,40.731313],"type":"Point"}
}