{
  "type": "Feature",
  "properties": {
    "iso:country":"US",
    "sg:address":"436 9th St",
    "sg:city":"Brooklyn",
    "sg:classifiers":[
        {
            "category":"Real Estate",
            "subcategory":"Real Estate Operator",
            "type":"Services"
        }
    ],
    "sg:phone":"+1 718 499 5801",
    "sg:postcode":"11215",
    "sg:province":"NY",
    "sg:tags":[
        "building",
        "apartment"
    ],
    "wof:name":"Equis Realty Partners LLC",
    "wof:placetype":"venue"
},
  "geometry": {"coordinates":[-73.983208,40.667836],"type":"Point"}
}