{
  "type": "Feature",
  "properties": {
    "addr:full":"2501 Coney Island Ave Brooklyn NY 11223",
    "addr:housenumber":"2501",
    "addr:postcode":"11223",
    "addr:street":"Coney Island Ave",
    "iso:country":"US",
    "sg:address":"2501 Coney Island Ave",
    "sg:city":"Brooklyn",
    "sg:classifiers":[
        {
            "category":"Manufacturing",
            "subcategory":"Signs",
            "type":"Manufacturing & Wholesale Goods"
        }
    ],
    "sg:phone":"+1 718 375 2500",
    "sg:postcode":"11223",
    "sg:province":"NY",
    "wof:name":"Ruven Signs Corp",
    "wof:placetype":"venue"
},
  "geometry": {"coordinates":[-73.960931,40.596049],"type":"Point"}
}