{
  "type": "Feature",
  "properties": {
    "addr:full":"7588 Big Tree Rd Pavilion NY 14525",
    "addr:housenumber":"7588",
    "addr:postcode":"14525",
    "addr:street":"Big Tree Rd",
    "iso:country":"US",
    "sg:address":"7588 Big Tree Rd",
    "sg:city":"Pavilion",
    "sg:classifiers":[
        {
            "category":"Farming",
            "subcategory":"Dairy Farm",
            "type":"Manufacturing & Wholesale Goods"
        }
    ],
    "sg:phone":"+1 585 584 3852",
    "sg:postcode":"14525",
    "sg:province":"NY",
    "wof:name":"Log Well Acres Inc",
    "wof:placetype":"venue"
},
  "geometry": {"coordinates":[-77.980816,42.845198],"type":"Point"}
}