{
  "type": "Feature",
  "properties": {
    "iso:country":"US",
    "sg:address":"156 Wheatley Rd",
    "sg:city":"Glen Head",
    "sg:classifiers":[
        {
            "category":"Banks & Credit Unions",
            "subcategory":"Financial Services",
            "type":"Services"
        }
    ],
    "sg:phone":"+1 516 626 5527",
    "sg:postcode":"11545",
    "sg:province":"NY",
    "sg:tags":[
        "investor"
    ],
    "wof:name":"Johnston EVAns& Lisa Evan",
    "wof:placetype":"venue"
},
  "geometry": {"coordinates":[-73.57987799999999,40.807964],"type":"Point"}
}