{
  "type": "Feature",
  "properties": {
    "addr:full":"5 Albany St Little Falls NY 13365",
    "addr:housenumber":"5",
    "addr:postcode":"13365",
    "addr:street":"Albany St",
    "iso:country":"US",
    "sg:address":"5 Albany St",
    "sg:city":"Little Falls",
    "sg:classifiers":[
        {
            "category":"Restaurant",
            "type":"Food & Drink"
        }
    ],
    "sg:phone":"+1   ",
    "sg:postcode":"13365",
    "sg:province":"NY",
    "sg:tags":[
        "eating"
    ],
    "wof:name":"McDonalds",
    "wof:placetype":"venue"
},
  "geometry": {"coordinates":[-74.856928,43.043294],"type":"Point"}
}