{
  "type": "Feature",
  "properties": {
    "iso:country":"US",
    "sg:address":"40 Carter Rd",
    "sg:city":"New Hampton",
    "sg:classifiers":[
        {
            "category":"Professional",
            "type":"Services"
        }
    ],
    "sg:phone":"+1   ",
    "sg:postcode":"10958",
    "sg:province":"NY",
    "wof:name":"Just For ME Inc",
    "wof:placetype":"venue"
},
  "geometry": {"coordinates":[-74.47328899999999,41.353471],"type":"Point"}
}