{
  "type": "Feature",
  "properties": {
    "iso:country":"US",
    "sg:address":"287 Mt Eve Rd",
    "sg:city":"Goshen",
    "sg:classifiers":[
        {
            "category":"Building & Trades",
            "subcategory":"Landscaping Services",
            "type":"Services"
        },
        {
            "category":"Building & Trades",
            "subcategory":"Construction",
            "type":"Services"
        }
    ],
    "sg:phone":"+1 845 651 2175",
    "sg:postcode":"10924",
    "sg:province":"NY",
    "sg:tags":[
        "designer",
        "consultant",
        "builder",
        "contractor",
        "patio",
        "landscape"
    ],
    "sg:website":"http://www.peterslandscapes.com/",
    "wof:name":"Peters Landscapes Inc",
    "wof:placetype":"venue"
},
  "geometry": {"coordinates":[-74.410342,41.318629],"type":"Point"}
}