{
  "type": "Feature",
  "properties": {
    "iso:country":"US",
    "sg:address":"5916 99th Street",
    "sg:city":"Corona",
    "sg:classifiers":[
        {
            "category":"Shopping",
            "subcategory":"Department Store",
            "type":"Retail Goods"
        }
    ],
    "sg:phone":"+1 718 595 1501",
    "sg:postcode":"11368",
    "sg:province":"NY",
    "wof:name":"Warehouse Supercenter",
    "wof:placetype":"venue"
},
  "geometry": {"coordinates":[-73.859371,40.736707],"type":"Point"}
}