{
  "type": "Feature",
  "properties": {
    "iso:country":"US",
    "sg:address":"235 Greenwich Rd",
    "sg:city":"Bedford",
    "sg:classifiers":[
        {
            "category":"Home & Garden",
            "subcategory":"Garden Supply",
            "type":"Retail Goods"
        }
    ],
    "sg:phone":"+1   ",
    "sg:postcode":"10506",
    "sg:province":"NY",
    "wof:name":"Bedford Nursery",
    "wof:placetype":"venue"
},
  "geometry": {"coordinates":[-73.648723,41.188098],"type":"Point"}
}