{
  "type": "Feature",
  "properties": {
    "addr:full":"425 E 86 St New York NY 10028",
    "addr:housenumber":"425;86",
    "addr:postcode":"10028",
    "addr:street":"E;St",
    "iso:country":"US",
    "sg:address":"425 E 86 St",
    "sg:city":"New York",
    "sg:classifiers":[
        {
            "category":"Health Services",
            "subcategory":"Health Practitioner",
            "type":"Services"
        }
    ],
    "sg:phone":"+1 212 427 7667",
    "sg:postcode":"10028",
    "sg:province":"NY",
    "sg:tags":[
        "pathologist",
        "speech"
    ],
    "wof:name":"Stacey Garsson",
    "wof:placetype":"venue"
},
  "geometry": {"coordinates":[-73.94736399999999,40.776149],"type":"Point"}
}