{
  "type": "Feature",
  "properties": {
    "addr:full":"2410 Barker Ave Bronx NY 10467",
    "addr:housenumber":"2410",
    "addr:postcode":"10467",
    "addr:street":"Barker Ave",
    "iso:country":"US",
    "sg:address":"2410 Barker Ave",
    "sg:city":"Bronx",
    "sg:classifiers":[
        {
            "category":"Taxi",
            "type":"Transportation"
        }
    ],
    "sg:phone":"+1   ",
    "sg:postcode":"10467",
    "sg:province":"NY",
    "sg:tags":[
        "taxicab"
    ],
    "wof:name":"Leonard J Glass",
    "wof:placetype":"venue"
},
  "geometry": {"coordinates":[-73.869304,40.863054],"type":"Point"}
}