{
  "type": "Feature",
  "properties": {
    "addr:full":"676 Motor Pkwy Unit C Hauppauge NY 11788",
    "addr:housenumber":"676;unit c",
    "addr:postcode":"11788",
    "addr:street":"Motor Pkwy",
    "iso:country":"US",
    "sg:address":"676 Motor Pkwy Unit C",
    "sg:city":"Hauppauge",
    "sg:classifiers":[
        {
            "category":"Insurance",
            "subcategory":"Hazard Insurance",
            "type":"Services"
        }
    ],
    "sg:phone":"+1 631 348 7000",
    "sg:postcode":"11788",
    "sg:province":"NY",
    "sg:website":"www.lancedragelin.com/",
    "wof:name":"Lance Dragelin - State Farm Insurance",
    "wof:placetype":"venue"
},
  "geometry": {"coordinates":[-73.240923,40.807409],"type":"Point"}
}