{
  "type": "Feature",
  "properties": {
    "iso:country":"US",
    "sg:address":"7 Wall St",
    "sg:city":"Auburn",
    "sg:classifiers":[
        {
            "category":"Professional",
            "type":"Services"
        }
    ],
    "sg:phone":"+1 315 252 7939",
    "sg:postcode":"13021",
    "sg:province":"NY",
    "sg:tags":[
        "establishment"
    ],
    "wof:name":"Norgim Inc",
    "wof:placetype":"venue"
},
  "geometry": {"coordinates":[-76.571393,42.935961],"type":"Point"}
}