{
  "type": "Feature",
  "properties": {
    "addr:full":"323 W Shore Rd Huntington NY 11743",
    "addr:housenumber":"323",
    "addr:postcode":"11743",
    "addr:street":"W Shore Rd",
    "iso:country":"US",
    "sg:address":"323 W Shore Rd",
    "sg:city":"Huntington",
    "sg:classifiers":[
        {
            "category":"Organizations",
            "subcategory":"Membership Organization",
            "type":"Services"
        }
    ],
    "sg:phone":"+1 631 351 9312",
    "sg:postcode":"11743",
    "sg:province":"NY",
    "sg:tags":[
        "club",
        "private"
    ],
    "sg:website":"http://www.harborboatingclub.net",
    "wof:name":"Harbor Boating Club Inc",
    "wof:placetype":"venue"
},
  "geometry": {"coordinates":[-73.432451,40.896914],"type":"Point"}
}