{
  "type": "Feature",
  "properties": {
    "addr:full":"2267 Town Line Rd Sag Harbor NY 11963",
    "addr:housenumber":"2267",
    "addr:postcode":"11963",
    "addr:street":"Town Line Rd",
    "iso:country":"US",
    "sg:address":"2267 Town Line Rd",
    "sg:city":"Sag Harbor",
    "sg:classifiers":[
        {
            "category":"Professional",
            "subcategory":"Business Services",
            "type":"Services"
        }
    ],
    "sg:phone":"+1   ",
    "sg:postcode":"11963",
    "sg:province":"NY",
    "wof:name":"Craig Design Inc",
    "wof:placetype":"venue"
},
  "geometry": {"coordinates":[-72.275927,40.97435],"type":"Point"}
}