{
  "type": "Feature",
  "properties": {
    "addr:full":"33 Catherine St Hempstead NY 11550",
    "addr:housenumber":"33",
    "addr:postcode":"11550",
    "addr:street":"Catherine St",
    "iso:country":"US",
    "sg:address":"33 Catherine St",
    "sg:city":"Hempstead",
    "sg:classifiers":[
        {
            "category":"Real Estate",
            "subcategory":"Real Estate Agent",
            "type":"Services"
        }
    ],
    "sg:phone":"+1 516 481 8083",
    "sg:postcode":"11550",
    "sg:province":"NY",
    "wof:name":"Elliot M Johnson Real Estate",
    "wof:placetype":"venue"
},
  "geometry": {"coordinates":[-73.613478,40.703642],"type":"Point"}
}