{
  "type": "Feature",
  "properties": {
    "addr:full":"14 Lafayette Sq Ste 510 Buffalo NY 14203",
    "addr:housenumber":"14",
    "addr:postcode":"14203",
    "addr:street":"Lafayette Sq Ste 510",
    "iso:country":"US",
    "sg:address":"14 Lafayette Sq Ste 510",
    "sg:city":"Buffalo",
    "sg:classifiers":[
        {
            "category":"Professional",
            "subcategory":"Lawyer & Legal Services",
            "type":"Services"
        }
    ],
    "sg:phone":"+1 716 853 3801",
    "sg:postcode":"14203",
    "sg:province":"NY",
    "wof:name":"Persico Jennifer Atty",
    "wof:placetype":"venue"
},
  "geometry": {"coordinates":[-78.874199,42.885799],"type":"Point"}
}