{
  "type": "Feature",
  "properties": {
    "addr:full":"565 Fulton Ave Hempstead NY 11550",
    "addr:housenumber":"565",
    "addr:postcode":"11550",
    "addr:street":"Fulton Ave",
    "iso:country":"US",
    "sg:address":"565 Fulton Ave",
    "sg:city":"Hempstead",
    "sg:classifiers":[
        {
            "category":"Banks & Credit Unions",
            "subcategory":"Bank",
            "type":"Services"
        }
    ],
    "sg:phone":"+1 516 489 1138",
    "sg:postcode":"11550",
    "sg:province":"NY",
    "wof:name":"Bank of New York the",
    "wof:placetype":"venue"
},
  "geometry": {"coordinates":[-73.621002,40.709202],"type":"Point"}
}