{
  "type": "Feature",
  "properties": {
    "iso:country":"US",
    "sg:address":"19 Sandy Hollow Rd",
    "sg:city":"Port Washington",
    "sg:classifiers":[
        {
            "category":"Building & Trades",
            "subcategory":"Electrical",
            "type":"Services"
        }
    ],
    "sg:phone":"+1 516 883 2554",
    "sg:postcode":"11050",
    "sg:province":"NY",
    "sg:tags":[
        "consulting",
        "electrical",
        "plum",
        "business",
        "contractor"
    ],
    "wof:name":"Scottys Elec Svce Inc",
    "wof:placetype":"venue"
},
  "geometry": {"coordinates":[-73.69668900000001,40.836775],"type":"Point"}
}