{
  "type": "Feature",
  "properties": {
    "iso:country":"US",
    "sg:address":"99 Copperfield Rd",
    "sg:city":"Rochester",
    "sg:classifiers":[
        {
            "category":"Real Estate",
            "subcategory":"Real Estate Agent",
            "type":"Services"
        }
    ],
    "sg:phone":"+1 585 527 8543",
    "sg:postcode":"14615",
    "sg:province":"NY",
    "wof:name":"Re/Max",
    "wof:placetype":"venue"
},
  "geometry": {"coordinates":[-77.66823599999999,43.228497],"type":"Point"}
}