{
  "type": "Feature",
  "properties": {
    "iso:country":"US",
    "sg:address":"248 Middle Country Rd",
    "sg:city":"Selden",
    "sg:classifiers":[
        {
            "category":"Real Estate",
            "subcategory":"Real Estate Agent",
            "type":"Services"
        }
    ],
    "sg:phone":"+1 631 696 0152",
    "sg:postcode":"11784",
    "sg:province":"NY",
    "sg:tags":[
        "management"
    ],
    "wof:name":"Agathos Real Estate Mgmt Corp",
    "wof:placetype":"venue"
},
  "geometry": {"coordinates":[-73.032703,40.866804],"type":"Point"}
}