{
  "type": "Feature",
  "properties": {
    "iso:country":"US",
    "sg:address":"2231 Burdett Ave",
    "sg:city":"Troy",
    "sg:classifiers":[
        {
            "category":"Health Services",
            "subcategory":"Doctor",
            "type":"Services"
        }
    ],
    "sg:phone":"+1 518 271 1331",
    "sg:postcode":"12180",
    "sg:province":"NY",
    "sg:tags":[
        "physician",
        "surgeon"
    ],
    "wof:name":"Reynolds Marci A",
    "wof:placetype":"venue"
},
  "geometry": {"coordinates":[-73.67113000000001,42.734316],"type":"Point"}
}