{
  "type": "Feature",
  "properties": {
    "iso:country":"US",
    "sg:address":"388 Englewood Ave",
    "sg:city":"Buffalo",
    "sg:classifiers":[
        {
            "category":"Banks & Credit Unions",
            "subcategory":"Bank",
            "type":"Services"
        }
    ],
    "sg:phone":"+1 716 837 2007",
    "sg:postcode":"14223",
    "sg:province":"NY",
    "wof:name":"Morton R Lane Federal Credit Union",
    "wof:placetype":"venue"
},
  "geometry": {"coordinates":[-78.834999,42.9599],"type":"Point"}
}