{
  "type": "Feature",
  "properties": {
    "iso:country":"US",
    "sg:address":"1887 Webster Ave",
    "sg:city":"Bronx",
    "sg:classifiers":[
        {
            "category":"Professional",
            "type":"Services"
        }
    ],
    "sg:phone":"+1 718 716 2582",
    "sg:postcode":"10457",
    "sg:province":"NY",
    "sg:tags":[
        "establishment"
    ],
    "wof:name":"N T Express Cargo",
    "wof:placetype":"venue"
},
  "geometry": {"coordinates":[-73.901264,40.847155],"type":"Point"}
}