{
  "type": "Feature",
  "properties": {
    "addr:full":"59 Bell Ave Blue Point NY 11715",
    "addr:housenumber":"59",
    "addr:postcode":"11715",
    "addr:street":"Bell Ave",
    "iso:country":"US",
    "sg:address":"59 Bell Ave",
    "sg:city":"Blue Point",
    "sg:classifiers":[
        {
            "category":"Professional",
            "type":"Services"
        }
    ],
    "sg:phone":"+1 631 363 7502",
    "sg:postcode":"11715",
    "sg:province":"NY",
    "sg:tags":[
        "establishment"
    ],
    "wof:name":"Mini Travelers Inc",
    "wof:placetype":"venue"
},
  "geometry": {"coordinates":[-73.038939,40.757169],"type":"Point"}
}