{
  "type": "Feature",
  "properties": {
    "addr:full":"1 Hunter Ct Huntington Station NY 11746",
    "addr:housenumber":"1",
    "addr:postcode":"11746",
    "addr:street":"Hunter Ct Huntington",
    "iso:country":"US",
    "sg:address":"1 Hunter Ct",
    "sg:city":"Huntington Station",
    "sg:classifiers":[
        {
            "category":"Communications",
            "subcategory":"Film & Video Production",
            "type":"Services"
        }
    ],
    "sg:phone":"+1   ",
    "sg:postcode":"11746",
    "sg:province":"NY",
    "sg:tags":[
        "motion",
        "picture",
        "distribution"
    ],
    "wof:name":"Sierra Landscaping",
    "wof:placetype":"venue"
},
  "geometry": {"coordinates":[-73.362448,40.824329],"type":"Point"}
}