{
  "type": "Feature",
  "properties": {
    "iso:country":"US",
    "sg:address":"35 Campbell Rd",
    "sg:city":"Napanoch",
    "sg:classifiers":[
        {
            "category":"Recreation",
            "type":"Entertainment"
        }
    ],
    "sg:phone":"+1 845 647 9725",
    "sg:postcode":"12458",
    "sg:province":"NY",
    "sg:tags":[
        "stable"
    ],
    "wof:name":"Totem Pole Stables",
    "wof:placetype":"venue"
},
  "geometry": {"coordinates":[-74.454212,41.846447],"type":"Point"}
}