{
  "type": "Feature",
  "properties": {
    "addr:full":"16 Boenau St Albany NY 12202",
    "addr:housenumber":"16",
    "addr:postcode":"12202",
    "addr:street":"Boenau St",
    "iso:country":"US",
    "sg:address":"16 Boenau St",
    "sg:city":"Albany",
    "sg:classifiers":[
        {
            "category":"Organizations",
            "subcategory":"Religious Organization",
            "type":"Services"
        }
    ],
    "sg:phone":"+1 518 449 3013",
    "sg:postcode":"12202",
    "sg:province":"NY",
    "sg:tags":[
        "clergy"
    ],
    "wof:name":"Willie J Stovall",
    "wof:placetype":"venue"
},
  "geometry": {"coordinates":[-73.768579,42.639262],"type":"Point"}
}