{
  "type": "Feature",
  "properties": {
    "addr:full":"496 Smithtown Byp Smithtown NY 11787",
    "addr:housenumber":"496",
    "addr:postcode":"11787",
    "addr:street":"Byp",
    "iso:country":"US",
    "sg:address":"496 Smithtown Byp",
    "sg:city":"Smithtown",
    "sg:classifiers":[
        {
            "category":"Health Services",
            "subcategory":"Doctor",
            "type":"Services"
        }
    ],
    "sg:phone":"+1 631 361 4495",
    "sg:postcode":"11787",
    "sg:province":"NY",
    "sg:tags":[
        "medical"
    ],
    "wof:name":"J Andrew Fantl MD",
    "wof:placetype":"venue"
},
  "geometry": {"coordinates":[-73.174775,40.843915],"type":"Point"}
}