{
  "type": "Feature",
  "properties": {
    "iso:country":"US",
    "sg:address":"338 Eggleston Hill Rd",
    "sg:city":"Cooperstown",
    "sg:classifiers":[
        {
            "category":"Professional",
            "type":"Services"
        }
    ],
    "sg:phone":"+1   ",
    "sg:postcode":"13326",
    "sg:province":"NY",
    "wof:name":"Trails End Lodge",
    "wof:placetype":"venue"
},
  "geometry": {"coordinates":[-74.931166,42.598527],"type":"Point"}
}