{
  "type": "Feature",
  "properties": {
    "addr:full":"10514 27th Avenue East Elmhurst NY 11369",
    "addr:housenumber":"10514",
    "addr:postcode":"11369",
    "addr:street":"27Th Avenue",
    "iso:country":"US",
    "sg:address":"10514 27th Avenue",
    "sg:city":"East Elmhurst",
    "sg:classifiers":[
        {
            "category":"Building & Trades",
            "subcategory":"Construction",
            "type":"Services"
        }
    ],
    "sg:phone":"+1 718 429 3676",
    "sg:postcode":"11369",
    "sg:province":"NY",
    "sg:tags":[
        "contractor"
    ],
    "wof:name":"Pioneer Cox General Construction Corporation",
    "wof:placetype":"venue"
},
  "geometry": {"coordinates":[-73.865228,40.764948],"type":"Point"}
}