{
  "type": "Feature",
  "properties": {
    "addr:full":"9 Greentree Dr Medford NY 11763",
    "addr:housenumber":"9",
    "addr:postcode":"11763",
    "addr:street":"Greentree Dr",
    "iso:country":"US",
    "sg:address":"9 Greentree Dr",
    "sg:city":"Medford",
    "sg:classifiers":[
        {
            "category":"Building & Trades",
            "subcategory":"Electrical",
            "type":"Services"
        }
    ],
    "sg:phone":"+1 631 924 2808",
    "sg:postcode":"11763",
    "sg:province":"NY",
    "sg:tags":[
        "electric",
        "contractor"
    ],
    "wof:name":"G E Family Electric Corp",
    "wof:placetype":"venue"
},
  "geometry": {"coordinates":[-72.957098,40.842776],"type":"Point"}
}