{
  "type": "Feature",
  "properties": {
    "iso:country":"US",
    "sg:address":"4004 Junction Blvd",
    "sg:city":"Corona",
    "sg:classifiers":[
        {
            "category":"Deli",
            "type":"Food & Drink"
        },
        {
            "category":"Food & Beverages",
            "subcategory":"Bakery",
            "type":"Retail Goods"
        }
    ],
    "sg:phone":"+1 718 205 2661",
    "sg:postcode":"11368",
    "sg:province":"NY",
    "sg:tags":[
        "sandwich"
    ],
    "wof:name":"Subway Sandwiches",
    "wof:placetype":"venue"
},
  "geometry": {"coordinates":[-73.86945799999999,40.748949],"type":"Point"}
}