{
  "type": "Feature",
  "properties": {
    "addr:full":"2477 65th St Brooklyn NY 11204",
    "addr:housenumber":"2477",
    "addr:postcode":"11204",
    "addr:street":"65Th St",
    "iso:country":"US",
    "sg:address":"2477 65th St",
    "sg:city":"Brooklyn",
    "sg:classifiers":[
        {
            "category":"Education",
            "subcategory":"Dance Studio",
            "type":"Public Place"
        }
    ],
    "sg:phone":"+1 718 376 6008",
    "sg:postcode":"11204",
    "sg:province":"NY",
    "sg:tags":[
        "instruction",
        "dancing"
    ],
    "wof:name":"Startime Dance & Performing",
    "wof:placetype":"venue"
},
  "geometry": {"coordinates":[-73.97435900000001,40.609699],"type":"Point"}
}