{
  "type": "Feature",
  "properties": {
    "iso:country":"US",
    "sg:address":"922 S Lake Blvd",
    "sg:city":"Mahopac",
    "sg:classifiers":[
        {
            "category":"Shopping",
            "subcategory":"Clothing, Apparel, & Fashions",
            "type":"Retail Goods"
        }
    ],
    "sg:phone":"+1 914 628 2000",
    "sg:postcode":"10541",
    "sg:province":"NY",
    "sg:tags":[
        "item",
        "boutique"
    ],
    "wof:name":"HRH Boutique",
    "wof:placetype":"venue"
},
  "geometry": {"coordinates":[-73.73644,41.372013],"type":"Point"}
}