{
  "type": "Feature",
  "properties": {
    "addr:full":"120 E 75 St New York NY 10021",
    "addr:housenumber":"120;75",
    "addr:postcode":"10021",
    "addr:street":"E;St",
    "iso:country":"US",
    "sg:address":"120 E 75 St",
    "sg:city":"New York",
    "sg:classifiers":[
        {
            "category":"Professional",
            "subcategory":"Business Services",
            "type":"Services"
        }
    ],
    "sg:phone":"+1 212 794 8861",
    "sg:postcode":"10021",
    "sg:province":"NY",
    "wof:name":"Plater Wagner Interiors",
    "wof:placetype":"venue"
},
  "geometry": {"coordinates":[-73.961202,40.772519],"type":"Point"}
}