{
  "type": "Feature",
  "properties": {
    "iso:country":"US",
    "sg:address":"44 Massachusetts Ave",
    "sg:city":"Congers",
    "sg:classifiers":[
        {
            "category":"Building & Trades",
            "subcategory":"Construction",
            "type":"Services"
        }
    ],
    "sg:phone":"+1 845 268 9294",
    "sg:postcode":"10920",
    "sg:province":"NY",
    "sg:tags":[
        "contractor"
    ],
    "wof:name":"Irish Mosaics Inc",
    "wof:placetype":"venue"
},
  "geometry": {"coordinates":[-73.929664,41.144823],"type":"Point"}
}