{
  "type": "Feature",
  "properties": {
    "iso:country":"US",
    "sg:address":"125 Merrick Rd",
    "sg:city":"Rockville Centre",
    "sg:classifiers":[
        {
            "category":"Travel",
            "subcategory":"Hotels & Motels",
            "type":"Entertainment"
        }
    ],
    "sg:phone":"+1 516 599 0582",
    "sg:postcode":"11570",
    "sg:province":"NY",
    "wof:name":"Hilton",
    "wof:placetype":"venue"
},
  "geometry": {"coordinates":[-73.648017,40.65675],"type":"Point"}
}