{
  "type": "Feature",
  "properties": {
    "iso:country":"US",
    "sg:address":"310 Hinchey Rd",
    "sg:city":"Rochester",
    "sg:classifiers":[
        {
            "category":"Organizations",
            "subcategory":"Religious Organization",
            "type":"Services"
        }
    ],
    "sg:phone":"+1 585 235 1210",
    "sg:postcode":"14624",
    "sg:province":"NY",
    "wof:name":"Saint Helens Church Rectory",
    "wof:placetype":"venue"
},
  "geometry": {"coordinates":[-77.679256,43.138829],"type":"Point"}
}