{
  "type": "Feature",
  "properties": {
    "addr:full":"270 Smith St Brooklyn NY 11231",
    "addr:housenumber":"270",
    "addr:postcode":"11231",
    "addr:street":"Smith St",
    "iso:country":"US",
    "sg:address":"270 Smith St",
    "sg:city":"Brooklyn",
    "sg:classifiers":[
        {
            "category":"Restaurant",
            "type":"Food & Drink"
        }
    ],
    "sg:phone":"+1 718 643 2861",
    "sg:postcode":"11231",
    "sg:province":"NY",
    "sg:tags":[
        "french"
    ],
    "sg:website":"www.sue-perette.com",
    "wof:name":"Sue Perette",
    "wof:placetype":"venue"
},
  "geometry": {"coordinates":[-73.99336599999999,40.682651],"type":"Point"}
}