{
  "type": "Feature",
  "properties": {
    "iso:country":"US",
    "sg:address":"147 E 57th St",
    "sg:city":"New York",
    "sg:classifiers":[
        {
            "category":"Shopping",
            "subcategory":"Department Store",
            "type":"Retail Goods"
        }
    ],
    "sg:phone":"+1 212 421 9000",
    "sg:postcode":"10022",
    "sg:province":"NY",
    "sg:website":"www.hammacher.com",
    "wof:name":"Hammacher Schlemmer & Co",
    "wof:placetype":"venue"
},
  "geometry": {"coordinates":[-73.967658,40.76041],"type":"Point"}
}