{
  "type": "Feature",
  "properties": {
    "iso:country":"US",
    "sg:address":"304 Brighton Beach Ave",
    "sg:city":"Brooklyn",
    "sg:classifiers":[
        {
            "category":"Shopping",
            "subcategory":"Shoes",
            "type":"Retail Goods"
        }
    ],
    "sg:phone":"+1 718 616 2220",
    "sg:postcode":"11235",
    "sg:province":"NY",
    "wof:name":"Affordable Shoes",
    "wof:placetype":"venue"
},
  "geometry": {"coordinates":[-73.96328699999999,40.577131],"type":"Point"}
}