{
  "type": "Feature",
  "properties": {
    "iso:country":"US",
    "sg:address":"100 Benkert St",
    "sg:city":"Bethpage",
    "sg:classifiers":[
        {
            "category":"Health Services",
            "subcategory":"Medical Lab",
            "type":"Services"
        }
    ],
    "sg:phone":"+1 516 822 1720",
    "sg:postcode":"11714",
    "sg:province":"NY",
    "sg:tags":[
        "laboratory",
        "dental"
    ],
    "wof:name":"Duerrdent Laboratory Inc",
    "wof:placetype":"venue"
},
  "geometry": {"coordinates":[-73.481461,40.742566],"type":"Point"}
}