{
  "type": "Feature",
  "properties": {
    "addr:full":"2385 New York Ave Huntington Sta NY 11746",
    "addr:housenumber":"2385",
    "addr:postcode":"11746",
    "addr:street":"New York Ave",
    "iso:country":"US",
    "sg:address":"2385 New York Ave",
    "sg:city":"Huntington Sta",
    "sg:classifiers":[
        {
            "category":"Retail",
            "subcategory":"Animal Services",
            "type":"Services"
        }
    ],
    "sg:phone":"+1 631 424 9720",
    "sg:postcode":"11746",
    "sg:province":"NY",
    "sg:tags":[
        "pet",
        "grooming",
        "washing"
    ],
    "wof:name":"New Yorkie Ave",
    "wof:placetype":"venue"
},
  "geometry": {"coordinates":[-73.408012,40.814279],"type":"Point"}
}