{
  "type": "Feature",
  "properties": {
    "iso:country":"US",
    "sg:address":"264 Gramatan Ave",
    "sg:city":"Mount Vernon",
    "sg:classifiers":[
        {
            "category":"Cinema",
            "subcategory":"Movie Rental",
            "type":"Entertainment"
        }
    ],
    "sg:phone":"+1   ",
    "sg:postcode":"10550",
    "sg:province":"NY",
    "sg:tags":[
        "video",
        "cassette",
        "rent",
        "rec",
        "retail",
        "tape"
    ],
    "wof:name":"Vernon Video",
    "wof:placetype":"venue"
},
  "geometry": {"coordinates":[-73.837588,40.91719],"type":"Point"}
}