{
  "type": "Feature",
  "properties": {
    "iso:country":"US",
    "sg:address":"350 96th St",
    "sg:city":"Brooklyn",
    "sg:classifiers":[
        {
            "category":"Building & Trades",
            "subcategory":"Construction",
            "type":"Services"
        }
    ],
    "sg:phone":"+1 516 214 9270",
    "sg:postcode":"11209",
    "sg:province":"NY",
    "sg:tags":[
        "wallcoverings-installation",
        "wallpaper",
        "painting",
        "contractor"
    ],
    "wof:name":"Multi-Tone Decorating Company",
    "wof:placetype":"venue"
},
  "geometry": {"coordinates":[-74.03268300000001,40.615903],"type":"Point"}
}