{
  "type": "Feature",
  "properties": {
    "iso:country":"US",
    "sg:address":"51 Round Pound Ln",
    "sg:city":"Sag Harbor",
    "sg:classifiers":[
        {
            "category":"Organizations",
            "subcategory":"Non-profit Organization",
            "type":"Services"
        }
    ],
    "sg:phone":"+1 631 725 4605",
    "sg:postcode":"11963",
    "sg:province":"NY",
    "wof:name":"Clay Art Guild Of The Hamptons",
    "wof:placetype":"venue"
},
  "geometry": {"coordinates":[-72.288253,40.981438],"type":"Point"}
}