{
  "type": "Feature",
  "properties": {
    "iso:country":"US",
    "sg:address":"5591 State Hwy 5",
    "sg:city":"Vernon",
    "sg:classifiers":[
        {
            "category":"Sports & Exercise",
            "subcategory":"Race Track",
            "type":"Entertainment"
        }
    ],
    "sg:phone":"+1 315 829 4557",
    "sg:postcode":"13476",
    "sg:province":"NY",
    "wof:name":"New Utica Rome Speedway",
    "wof:placetype":"venue"
},
  "geometry": {"coordinates":[-75.526826,43.077473],"type":"Point"}
}