{
  "type": "Feature",
  "properties": {
    "iso:country":"US",
    "sg:address":"3003 New Hyde Park Rd",
    "sg:city":"New Hyde Park",
    "sg:classifiers":[
        {
            "category":"Health Services",
            "subcategory":"Doctor",
            "type":"Services"
        }
    ],
    "sg:phone":"+1 516 775 2800",
    "sg:postcode":"11042",
    "sg:province":"NY",
    "sg:tags":[
        "throat",
        "specialist",
        "ear",
        "nose"
    ],
    "wof:name":"Otolaryngology-Facial Plas Sur",
    "wof:placetype":"venue"
},
  "geometry": {"coordinates":[-73.689575,40.762423],"type":"Point"}
}