{
  "type": "Feature",
  "properties": {
    "iso:country":"US",
    "sg:address":"365 W Route 59",
    "sg:city":"Nanuet",
    "sg:classifiers":[
        {
            "category":"Fast Food",
            "type":"Food & Drink"
        },
        {
            "category":"Restaurant",
            "type":"Food & Drink"
        }
    ],
    "sg:phone":"+1 845 624 6666",
    "sg:postcode":"10954",
    "sg:province":"NY",
    "sg:tags":[
        "mexican",
        "take"
    ],
    "sg:website":"http://www.zipweb.com/?businessName=FiestaCancun/",
    "wof:name":"Fiesta Cancun",
    "wof:placetype":"venue"
},
  "geometry": {"coordinates":[-74.026239,41.101552],"type":"Point"}
}