{
  "type": "Feature",
  "properties": {
    "addr:full":"2705 Avenue U Brooklyn NY 11229",
    "addr:housenumber":"2705",
    "addr:postcode":"11229",
    "addr:street":"Avenue U",
    "iso:country":"US",
    "sg:address":"2705 Avenue U",
    "sg:city":"Brooklyn",
    "sg:classifiers":[
        {
            "category":"Communications",
            "subcategory":"Film & Video Production",
            "type":"Services"
        }
    ],
    "sg:phone":"+1 718 368 4440",
    "sg:postcode":"11229",
    "sg:province":"NY",
    "sg:tags":[
        "equipment",
        "leasing",
        "supplies-renting"
    ],
    "wof:name":"Video Imax",
    "wof:placetype":"venue"
},
  "geometry": {"coordinates":[-73.94470200000001,40.600125],"type":"Point"}
}