{
  "type": "Feature",
  "properties": {
    "iso:country":"US",
    "sg:address":"1000 Turk Hill Rd",
    "sg:city":"Fairport",
    "sg:classifiers":[
        {
            "category":"Manufacturing",
            "subcategory":"Retail Goods",
            "type":"Manufacturing & Wholesale Goods"
        }
    ],
    "sg:phone":"+1 585 223 6560",
    "sg:postcode":"14450",
    "sg:province":"NY",
    "sg:tags":[
        "assembly",
        "fabricating"
    ],
    "wof:name":"Ampack",
    "wof:placetype":"venue"
},
  "geometry": {"coordinates":[-77.43214500000001,43.096073],"type":"Point"}
}