{
  "type": "Feature",
  "properties": {
    "addr:full":"1 Buffalo River Pl Buffalo NY 14210",
    "addr:housenumber":"1",
    "addr:postcode":"14210",
    "addr:street":"Buffalo River Pl",
    "iso:country":"US",
    "sg:address":"1 Buffalo River Pl",
    "sg:city":"Buffalo",
    "sg:classifiers":[
        {
            "category":"Professional",
            "subcategory":"Business Services",
            "type":"Services"
        }
    ],
    "sg:phone":"+1   ",
    "sg:postcode":"14210",
    "sg:province":"NY",
    "sg:tags":[
        "bagging",
        "contract"
    ],
    "wof:name":"Buffalo Contract Bagging LLC",
    "wof:placetype":"venue"
},
  "geometry": {"coordinates":[-78.851005,42.865984],"type":"Point"}
}