{
  "type": "Feature",
  "properties": {
    "addr:full":"300 Pearl St Buffalo NY 14202",
    "addr:housenumber":"300",
    "addr:postcode":"14202",
    "addr:street":"Pearl St",
    "iso:country":"US",
    "sg:address":"300 Pearl St",
    "sg:city":"Buffalo",
    "sg:classifiers":[
        {
            "category":"Government",
            "subcategory":"Office",
            "type":"Public Place"
        }
    ],
    "sg:phone":"+1 716 551 4461",
    "sg:postcode":"14202",
    "sg:province":"NY",
    "sg:tags":[
        "federal",
        "program"
    ],
    "sg:website":"www.fda.gov",
    "wof:name":"US Food & Drug Adm",
    "wof:placetype":"venue"
},
  "geometry": {"coordinates":[-78.874674,42.888734],"type":"Point"}
}