{
  "type": "Feature",
  "properties": {
    "addr:full":"600 W 142nd St New York NY 10031",
    "addr:housenumber":"600",
    "addr:postcode":"10031",
    "addr:street":"W 142Nd St",
    "iso:country":"US",
    "sg:address":"600 W 142nd St",
    "sg:city":"New York",
    "sg:classifiers":[
        {
            "category":"Restaurant",
            "type":"Food & Drink"
        }
    ],
    "sg:menulink":"http://www.allmenus.com/ny/new-york/48727-la-oaxaquena/menu/",
    "sg:phone":"+1 646 938 4012",
    "sg:postcode":"10031",
    "sg:province":"NY",
    "sg:tags":[
        "mexican"
    ],
    "wof:name":"La Oaxaquena",
    "wof:placetype":"venue"
},
  "geometry": {"coordinates":[-73.95197,40.824563],"type":"Point"}
}