{
  "type": "Feature",
  "properties": {
    "iso:country":"US",
    "sg:address":"7 N Main St",
    "sg:city":"Gloversville",
    "sg:classifiers":[
        {
            "category":"Shopping",
            "subcategory":"Jewelry",
            "type":"Retail Goods"
        }
    ],
    "sg:phone":"+1   ",
    "sg:postcode":"12078",
    "sg:province":"NY",
    "sg:tags":[
        "repair"
    ],
    "wof:name":"Vandewalker Jewelry & Repr Ctr",
    "wof:placetype":"venue"
},
  "geometry": {"coordinates":[-74.345271,43.051074],"type":"Point"}
}