{
  "type": "Feature",
  "properties": {
    "iso:country":"US",
    "sg:address":"435 Van Nest Ave",
    "sg:city":"Bronx",
    "sg:classifiers":[
        {
            "category":"Manufacturing",
            "subcategory":"Apparel",
            "type":"Manufacturing & Wholesale Goods"
        }
    ],
    "sg:phone":"+1   ",
    "sg:postcode":"10460",
    "sg:province":"NY",
    "sg:tags":[
        "awning",
        "canvas",
        "mfg",
        "acrylic",
        "vinyl"
    ],
    "sg:website":"www.acmeawn.com",
    "wof:name":"Acme Awning Co Inc",
    "wof:placetype":"venue"
},
  "geometry": {"coordinates":[-73.871764,40.839432],"type":"Point"}
}