{
  "type": "Feature",
  "properties": {
    "addr:full":"156 Tacoma Ave Buffalo NY 14216",
    "addr:housenumber":"156",
    "addr:postcode":"14216",
    "addr:street":"Tacoma Ave",
    "iso:country":"US",
    "sg:address":"156 Tacoma Ave",
    "sg:city":"Buffalo",
    "sg:classifiers":[
        {
            "category":"Government",
            "subcategory":"Office",
            "type":"Public Place"
        }
    ],
    "sg:phone":"+1 716 873 8481",
    "sg:postcode":"14216",
    "sg:province":"NY",
    "sg:tags":[
        "department",
        "recreation",
        "park",
        "center"
    ],
    "sg:website":"http://www.berc.org",
    "wof:name":"Public Wrks Parks Streets Dept",
    "wof:placetype":"venue"
},
  "geometry": {"coordinates":[-78.86663,42.951494],"type":"Point"}
}