{
  "type": "Feature",
  "properties": {
    "addr:full":"94 Baxter St New York NY 10013",
    "addr:housenumber":"94",
    "addr:postcode":"10013",
    "addr:street":"Baxter St",
    "iso:country":"US",
    "sg:address":"94 Baxter St",
    "sg:city":"New York",
    "sg:classifiers":[
        {
            "category":"Restaurant",
            "type":"Food & Drink"
        }
    ],
    "sg:phone":"+1 212 941 6679",
    "sg:postcode":"10013",
    "sg:province":"NY",
    "sg:tags":[
        "eating",
        "chinese"
    ],
    "wof:name":"Marco Polo Noodle Shop",
    "wof:placetype":"venue"
},
  "geometry": {"coordinates":[-73.999803,40.716757],"type":"Point"}
}