{
  "type": "Feature",
  "properties": {
    "iso:country":"US",
    "sg:address":"9745 Queens Blvd Ste 1220",
    "sg:city":"Rego Park",
    "sg:classifiers":[
        {
            "category":"Health Services",
            "subcategory":"Doctor",
            "type":"Services"
        },
        {
            "category":"Health Services",
            "subcategory":"Clinic",
            "type":"Services"
        }
    ],
    "sg:phone":"+1 718 896 2500",
    "sg:postcode":"11374",
    "sg:province":"NY",
    "sg:tags":[
        "counseling",
        "mental"
    ],
    "sg:website":"www.acqc.org",
    "wof:name":"ACQC - AIDS Center of Queens County",
    "wof:placetype":"venue"
},
  "geometry": {"coordinates":[-73.859602,40.72933],"type":"Point"}
}