{
  "type": "Feature",
  "properties": {
    "iso:country":"US",
    "sg:address":"105 Old Country Rd",
    "sg:city":"East Quogue",
    "sg:classifiers":[
        {
            "category":"Building & Trades",
            "subcategory":"Construction",
            "type":"Services"
        }
    ],
    "sg:phone":"+1 631 653 6435",
    "sg:postcode":"11942",
    "sg:province":"NY",
    "sg:tags":[
        "contractor"
    ],
    "wof:name":"Henrys General Contractor",
    "wof:placetype":"venue"
},
  "geometry": {"coordinates":[-72.587963,40.845944],"type":"Point"}
}