{
  "type": "Feature",
  "properties": {
    "iso:country":"US",
    "sg:address":"200 Blue Point Ave",
    "sg:city":"Blue Point",
    "sg:classifiers":[
        {
            "category":"Professional",
            "subcategory":"Engineering",
            "type":"Services"
        }
    ],
    "sg:phone":"+1 631 363 2683",
    "sg:postcode":"11715",
    "sg:province":"NY",
    "sg:tags":[
        "engineer"
    ],
    "sg:website":"www.vollbrush.com",
    "wof:name":"Vollmuth & Brush Engnrng",
    "wof:placetype":"venue"
},
  "geometry": {"coordinates":[-73.03635800000001,40.748557],"type":"Point"}
}