{
  "type": "Feature",
  "properties": {
    "addr:full":"1735 Central Ave Albany NY 12205",
    "addr:housenumber":"1735",
    "addr:postcode":"12205",
    "addr:street":"Central Ave",
    "iso:country":"US",
    "sg:address":"1735 Central Ave",
    "sg:city":"Albany",
    "sg:classifiers":[
        {
            "category":"Professional",
            "subcategory":"Advertising",
            "type":"Services"
        }
    ],
    "sg:phone":"+1 518 218 1173",
    "sg:postcode":"12205",
    "sg:province":"NY",
    "wof:name":"Customer Information Ctr",
    "wof:placetype":"venue"
},
  "geometry": {"coordinates":[-73.842,42.725645],"type":"Point"}
}