{
  "type": "Feature",
  "properties": {
    "iso:country":"US",
    "sg:address":"9202 Akron Rd",
    "sg:city":"Akron",
    "sg:classifiers":[
        {
            "category":"Farming",
            "subcategory":"Livestock Farm",
            "type":"Manufacturing & Wholesale Goods"
        }
    ],
    "sg:phone":"+1 716 542 9216",
    "sg:postcode":"14001",
    "sg:province":"NY",
    "sg:tags":[
        "feedlot",
        "hog",
        "or",
        "beef",
        "cattle"
    ],
    "wof:name":"Stahl Dairy Farm",
    "wof:placetype":"venue"
},
  "geometry": {"coordinates":[-78.518658,43.089642],"type":"Point"}
}