{
  "type": "Feature",
  "properties": {
    "iso:country":"US",
    "sg:address":"14 Elm St",
    "sg:city":"Cooperstown",
    "sg:classifiers":[
        {
            "category":"Travel",
            "subcategory":"Hotels & Motels",
            "type":"Entertainment"
        }
    ],
    "sg:phone":"+1   ",
    "sg:postcode":"13326",
    "sg:province":"NY",
    "sg:tags":[
        "operation"
    ],
    "wof:name":"Angelholm Bed N Breakfast",
    "wof:placetype":"venue"
},
  "geometry": {"coordinates":[-74.925831,42.698364],"type":"Point"}
}