{
  "type": "Feature",
  "properties": {
    "addr:full":"600 N Work St Falconer NY 14733",
    "addr:housenumber":"600",
    "addr:postcode":"14733",
    "addr:street":"N Work St",
    "iso:country":"US",
    "sg:address":"600 N Work St",
    "sg:city":"Falconer",
    "sg:classifiers":[
        {
            "category":"Manufacturing",
            "subcategory":"Tools & Machinery",
            "type":"Manufacturing & Wholesale Goods"
        }
    ],
    "sg:phone":"+1 716 488 1975",
    "sg:postcode":"14733",
    "sg:province":"NY",
    "sg:tags":[
        "die",
        "industrial",
        "mold",
        "maker",
        "mfg"
    ],
    "wof:name":"Stuart Tool & Die Inc",
    "wof:placetype":"venue"
},
  "geometry": {"coordinates":[-79.20509699999999,42.124925],"type":"Point"}
}