{
  "type": "Feature",
  "properties": {
    "addr:full":"38 E Main St Webster NY 14580",
    "addr:housenumber":"38",
    "addr:postcode":"14580",
    "addr:street":"E Main St",
    "iso:country":"US",
    "sg:address":"38 E Main St",
    "sg:city":"Webster",
    "sg:classifiers":[
        {
            "category":"Shopping",
            "subcategory":"Florist",
            "type":"Retail Goods"
        }
    ],
    "sg:phone":"+1 585 265 0572",
    "sg:postcode":"14580",
    "sg:province":"NY",
    "wof:name":"Our Father's Flowers",
    "wof:placetype":"venue"
},
  "geometry": {"coordinates":[-77.428139,43.212581],"type":"Point"}
}