{
  "type": "Feature",
  "properties": {
    "addr:full":"40 E 34 St New York NY 10016",
    "addr:housenumber":"40;34",
    "addr:postcode":"10016",
    "addr:street":"E;St",
    "iso:country":"US",
    "sg:address":"40 E 34 St",
    "sg:city":"New York",
    "sg:classifiers":[
        {
            "category":"Professional",
            "subcategory":"Accounting & Tax Preparation",
            "type":"Services"
        }
    ],
    "sg:phone":"+1 212 448 0010",
    "sg:postcode":"10016",
    "sg:province":"NY",
    "sg:tags":[
        "account",
        "public",
        "certified"
    ],
    "wof:name":"Van Buren & Hauke",
    "wof:placetype":"venue"
},
  "geometry": {"coordinates":[-73.98136100000001,40.747144],"type":"Point"}
}