{
  "type": "Feature",
  "properties": {
    "addr:full":"214 W 80 St New York NY 10024",
    "addr:housenumber":"214",
    "addr:postcode":"10024",
    "addr:street":"W 80 St",
    "iso:country":"US",
    "sg:address":"214 W 80 St",
    "sg:city":"New York",
    "sg:classifiers":[
        {
            "category":"Parking",
            "type":"Transportation"
        }
    ],
    "sg:phone":"+1 212 799 8794",
    "sg:postcode":"10024",
    "sg:province":"NY",
    "sg:tags":[
        "garage"
    ],
    "wof:name":"Edison Park Fast",
    "wof:placetype":"venue"
},
  "geometry": {"coordinates":[-73.979114,40.784239],"type":"Point"}
}