{
  "type": "Feature",
  "properties": {
    "addr:full":"6 Ridgeway Dr Great Neck NY 11024",
    "addr:housenumber":"6",
    "addr:postcode":"11024",
    "addr:street":"Ridgeway Dr",
    "iso:country":"US",
    "sg:address":"6 Ridgeway Dr",
    "sg:city":"Great Neck",
    "sg:classifiers":[
        {
            "category":"Professional",
            "subcategory":"Lawyer & Legal Services",
            "type":"Services"
        }
    ],
    "sg:phone":"+1 516 466 1155",
    "sg:postcode":"11024",
    "sg:province":"NY",
    "sg:tags":[
        "attorney"
    ],
    "wof:name":"Jay S Goodman",
    "wof:placetype":"venue"
},
  "geometry": {"coordinates":[-73.74102999999999,40.811559],"type":"Point"}
}