{
  "type": "Feature",
  "properties": {
    "iso:country":"US",
    "sg:address":"5760 Cmns Park",
    "sg:city":"East Syracuse",
    "sg:classifiers":[
        {
            "category":"Professional",
            "subcategory":"Research",
            "type":"Services"
        }
    ],
    "sg:phone":"+1 315 492 2905",
    "sg:postcode":"13057",
    "sg:province":"NY",
    "sg:tags":[
        "marketing"
    ],
    "wof:name":"Delta Marketing Dynamics",
    "wof:placetype":"venue"
},
  "geometry": {"coordinates":[-76.054058,43.04942],"type":"Point"}
}