{
  "type": "Feature",
  "properties": {
    "iso:country":"US",
    "sg:address":"3124 Jericho Tpke",
    "sg:city":"Commack",
    "sg:classifiers":[
        {
            "category":"Shopping",
            "subcategory":"Department Store",
            "type":"Retail Goods"
        },
        {
            "category":"Wholesale",
            "subcategory":"Computers",
            "type":"Manufacturing & Wholesale Goods"
        },
        {
            "category":"Professional",
            "subcategory":"Computer Services",
            "type":"Services"
        }
    ],
    "sg:phone":"+1 631 462 1178",
    "sg:postcode":"11725",
    "sg:province":"NY",
    "sg:tags":[
        "repair"
    ],
    "wof:name":"Best Buy Inc",
    "wof:placetype":"venue"
},
  "geometry": {"coordinates":[-73.274597,40.8396],"type":"Point"}
}