{
  "type": "Feature",
  "properties": {
    "addr:full":"140 Bryant Bridge Rd Saratoga Springs NY 12866",
    "addr:housenumber":"140",
    "addr:postcode":"12866",
    "addr:street":"Bryant Bridge Rd",
    "iso:country":"US",
    "sg:address":"140 Bryant Bridge Rd",
    "sg:city":"Saratoga Springs",
    "sg:classifiers":[
        {
            "category":"Personal",
            "type":"Services"
        }
    ],
    "sg:phone":"+1 518 583 2065",
    "sg:postcode":"12866",
    "sg:province":"NY",
    "sg:tags":[
        "miscellaneous"
    ],
    "wof:name":"Bryant Bridge Enterprises",
    "wof:placetype":"venue"
},
  "geometry": {"coordinates":[-73.661241,43.093237],"type":"Point"}
}