{
  "type": "Feature",
  "properties": {
    "addr:full":"138 Brandywine Ter S Rochester NY 14623",
    "addr:housenumber":"138",
    "addr:postcode":"14623",
    "addr:street":"Brandywine Ter S",
    "iso:country":"US",
    "sg:address":"138 Brandywine Ter S",
    "sg:city":"Rochester",
    "sg:classifiers":[
        {
            "category":"Personal",
            "subcategory":"Beauty Salon",
            "type":"Services"
        }
    ],
    "sg:phone":"+1   ",
    "sg:postcode":"14623",
    "sg:province":"NY",
    "sg:tags":[
        "shop"
    ],
    "wof:name":"Darz Creations",
    "wof:placetype":"venue"
},
  "geometry": {"coordinates":[-77.657611,43.060701],"type":"Point"}
}