{
  "type": "Feature",
  "properties": {
    "iso:country":"US",
    "sg:address":"420 Jericho Tpke",
    "sg:city":"Syosset",
    "sg:classifiers":[
        {
            "category":"Utilities",
            "subcategory":"Mobile Phone",
            "type":"Services"
        }
    ],
    "sg:phone":"+1 516 364 3900",
    "sg:postcode":"11791",
    "sg:province":"NY",
    "sg:tags":[
        "telephone",
        "cellular"
    ],
    "wof:name":"Bellstar Wireless",
    "wof:placetype":"venue"
},
  "geometry": {"coordinates":[-73.498597,40.810579],"type":"Point"}
}