{
  "type": "Feature",
  "properties": {
    "iso:country":"US",
    "sg:address":"6877 Peck Rd",
    "sg:city":"Syracuse",
    "sg:classifiers":[
        {
            "category":"Building & Trades",
            "subcategory":"Construction",
            "type":"Services"
        }
    ],
    "sg:phone":"+1 315 635 4669",
    "sg:postcode":"13209",
    "sg:province":"NY",
    "sg:tags":[
        "house"
    ],
    "wof:name":"Schlegel Constr",
    "wof:placetype":"venue"
},
  "geometry": {"coordinates":[-76.302582,43.102632],"type":"Point"}
}