{
  "type": "Feature",
  "properties": {
    "addr:full":"12 Montgomery Ave Mastic NY 11950",
    "addr:housenumber":"12",
    "addr:postcode":"11950",
    "addr:street":"Montgomery Ave",
    "iso:country":"US",
    "sg:address":"12 Montgomery Ave",
    "sg:city":"Mastic",
    "sg:classifiers":[
        {
            "category":"Building & Trades",
            "subcategory":"Landscaping Services",
            "type":"Services"
        }
    ],
    "sg:phone":"+1 631 395 3402",
    "sg:postcode":"11950",
    "sg:province":"NY",
    "sg:tags":[
        "landscape",
        "contractor"
    ],
    "wof:name":"Green Island Scapes",
    "wof:placetype":"venue"
},
  "geometry": {"coordinates":[-72.839066,40.806622],"type":"Point"}
}