{
  "type": "Feature",
  "properties": {
    "addr:full":"89 5th Ave New York NY 10003",
    "addr:housenumber":"89",
    "addr:postcode":"10003",
    "addr:street":"5Th Ave",
    "iso:country":"US",
    "sg:address":"89 5th Ave",
    "sg:city":"New York",
    "sg:classifiers":[
        {
            "category":"Professional",
            "subcategory":"Lawyer & Legal Services",
            "type":"Services"
        }
    ],
    "sg:phone":"+1 212 206 9099",
    "sg:postcode":"10003",
    "sg:province":"NY",
    "wof:name":"Townsend Kim Atty",
    "wof:placetype":"venue"
},
  "geometry": {"coordinates":[-73.99250000000001,40.737701],"type":"Point"}
}