{
  "type": "Feature",
  "properties": {
    "addr:full":"1025 Eastern Parkway Brooklyn NY 11213",
    "addr:housenumber":"1025",
    "addr:postcode":"11213",
    "addr:street":"Eastern Parkway",
    "iso:country":"US",
    "sg:address":"1025 Eastern Parkway",
    "sg:city":"Brooklyn",
    "sg:classifiers":[
        {
            "category":"Education",
            "subcategory":"School",
            "type":"Public Place"
        }
    ],
    "sg:phone":"+1 718 774 2640",
    "sg:postcode":"11213",
    "sg:province":"NY",
    "sg:tags":[
        "high",
        "middle",
        "elementary"
    ],
    "wof:name":"New York City Community School District 17 Region 6",
    "wof:placetype":"venue"
},
  "geometry": {"coordinates":[-73.93415400000001,40.669288],"type":"Point"}
}