{
  "type": "Feature",
  "properties": {
    "addr:full":"246 E 51st St New York NY 10022",
    "addr:housenumber":"246",
    "addr:postcode":"10022",
    "addr:street":"E 51St St",
    "iso:country":"US",
    "sg:address":"246 E 51st St",
    "sg:city":"New York",
    "sg:classifiers":[
        {
            "category":"Personal",
            "subcategory":"Massage",
            "type":"Services"
        },
        {
            "category":"Health Services",
            "subcategory":"Health Practitioner",
            "type":"Services"
        }
    ],
    "sg:phone":"+1 212 355 8288",
    "sg:postcode":"10022",
    "sg:province":"NY",
    "sg:tags":[
        "acupuncture"
    ],
    "wof:name":"Sunflower Traditional Center",
    "wof:placetype":"venue"
},
  "geometry": {"coordinates":[-73.968738,40.755539],"type":"Point"}
}