{
  "type": "Feature",
  "properties": {
    "addr:full":"167 Burgess Rd Hoosick Falls NY 12090",
    "addr:housenumber":"167",
    "addr:postcode":"12090",
    "addr:street":"Burgess Rd",
    "iso:country":"US",
    "sg:address":"167 Burgess Rd",
    "sg:city":"Hoosick Falls",
    "sg:classifiers":[
        {
            "category":"Farming",
            "subcategory":"Farm",
            "type":"Manufacturing & Wholesale Goods"
        }
    ],
    "sg:phone":"+1 518 686 5476",
    "sg:postcode":"12090",
    "sg:province":"NY",
    "sg:tags":[
        "crop",
        "general"
    ],
    "wof:name":"High Acres",
    "wof:placetype":"venue"
},
  "geometry": {"coordinates":[-73.299992,42.899257],"type":"Point"}
}