{
  "type": "Feature",
  "properties": {
    "iso:country":"US",
    "sg:address":"370 Central Park W",
    "sg:city":"New York",
    "sg:classifiers":[
        {
            "category":"Building & Trades",
            "subcategory":"Construction",
            "type":"Services"
        }
    ],
    "sg:phone":"+1 212 316 3882",
    "sg:postcode":"10025",
    "sg:province":"NY",
    "sg:tags":[
        "contractor"
    ],
    "wof:name":"Offsite Technologies",
    "wof:placetype":"venue"
},
  "geometry": {"coordinates":[-73.964056,40.792494],"type":"Point"}
}