{
  "type": "Feature",
  "properties": {
    "iso:country":"US",
    "sg:address":"207 Hallock Rd",
    "sg:city":"Stony Brook",
    "sg:classifiers":[
        {
            "category":"Government",
            "subcategory":"Office",
            "type":"Public Place"
        }
    ],
    "sg:phone":"+1 631 854 1515",
    "sg:postcode":"11790",
    "sg:province":"NY",
    "wof:name":"Honorable Lawrence J Bracken",
    "wof:placetype":"venue"
},
  "geometry": {"coordinates":[-73.123841,40.874397],"type":"Point"}
}