{
  "type": "Feature",
  "properties": {
    "iso:country":"US",
    "sg:address":"41 Dorset Rd",
    "sg:city":"Hampton",
    "sg:classifiers":[
        {
            "category":"Professional",
            "type":"Services"
        }
    ],
    "sg:phone":"+1 631 324 6794",
    "sg:postcode":"12815",
    "sg:province":"NY",
    "sg:tags":[
        "establishment"
    ],
    "wof:name":"Precision Mark-Outs Inc",
    "wof:placetype":"venue"
},
  "geometry": {"coordinates":[-73.69858600000001,43.732793],"type":"Point"}
}