{
  "type": "Feature",
  "properties": {
    "addr:full":"389 E Main St Patchogue NY 11772",
    "addr:housenumber":"389",
    "addr:postcode":"11772",
    "addr:street":"E Main St",
    "iso:country":"US",
    "sg:address":"389 E Main St",
    "sg:city":"Patchogue",
    "sg:classifiers":[
        {
            "category":"Personal",
            "subcategory":"Beauty Salon",
            "type":"Services"
        }
    ],
    "sg:phone":"+1 631 569 4408",
    "sg:postcode":"11772",
    "sg:province":"NY",
    "sg:tags":[
        "hair",
        "stylist"
    ],
    "wof:name":"Platinum Hair Salon",
    "wof:placetype":"venue"
},
  "geometry": {"coordinates":[-73.00103900000001,40.766599],"type":"Point"}
}