{
  "type": "Feature",
  "properties": {
    "iso:country":"US",
    "sg:address":"3781 Main St",
    "sg:city":"Buffalo",
    "sg:classifiers":[
        {
            "category":"Sports & Exercise",
            "subcategory":"Golf",
            "type":"Entertainment"
        }
    ],
    "sg:phone":"+1 716 862 9470",
    "sg:postcode":"14226",
    "sg:province":"NY",
    "wof:name":"Grover Cleveland Pro Shop",
    "wof:placetype":"venue"
},
  "geometry": {"coordinates":[-78.809303,42.9613],"type":"Point"}
}