{
  "type": "Feature",
  "properties": {
    "iso:country":"US",
    "sg:address":"135 Ivory St",
    "sg:city":"Frewsburg",
    "sg:classifiers":[
        {
            "category":"Education",
            "subcategory":"School",
            "type":"Public Place"
        }
    ],
    "sg:phone":"+1 716 569 5630",
    "sg:postcode":"14738",
    "sg:province":"NY",
    "wof:name":"Robert Jackson Elementary Schl",
    "wof:placetype":"venue"
},
  "geometry": {"coordinates":[-79.151188,42.059537],"type":"Point"}
}