{
  "type": "Feature",
  "properties": {
    "iso:country":"US",
    "sg:address":"701 Calder Ave",
    "sg:city":"Yorkville",
    "sg:classifiers":[
        {
            "category":"Real Estate",
            "subcategory":"Real Estate Agent",
            "type":"Services"
        }
    ],
    "sg:phone":"+1 315 736 8571",
    "sg:postcode":"13495",
    "sg:province":"NY",
    "wof:name":"Davis Camp Estate LLC",
    "wof:placetype":"venue"
},
  "geometry": {"coordinates":[-75.280627,43.112859],"type":"Point"}
}