{
  "type": "Feature",
  "properties": {
    "iso:country":"US",
    "sg:address":"3 Joseph Ln",
    "sg:city":"Hicksville",
    "sg:classifiers":[
        {
            "category":"Shopping",
            "subcategory":"Computers & Home Electronics",
            "type":"Retail Goods"
        }
    ],
    "sg:phone":"+1   ",
    "sg:postcode":"11801",
    "sg:province":"NY",
    "sg:tags":[
        "software"
    ],
    "wof:name":"Computer Rising Inc",
    "wof:placetype":"venue"
},
  "geometry": {"coordinates":[-73.505048,40.765602],"type":"Point"}
}