{
  "type": "Feature",
  "properties": {
    "iso:country":"US",
    "sg:address":"170 E 77th Street",
    "sg:city":"New York",
    "sg:classifiers":[
        {
            "category":"Health Services",
            "subcategory":"Doctor",
            "type":"Services"
        }
    ],
    "sg:phone":"+1 212 585 0076",
    "sg:postcode":"10021",
    "sg:province":"NY",
    "wof:name":"Choy Daniel S J MD",
    "wof:placetype":"venue"
},
  "geometry": {"coordinates":[-73.959051,40.773237],"type":"Point"}
}