{
  "type": "Feature",
  "properties": {
    "addr:full":"88-28 Roosevelt Ave Queens NY 11373",
    "addr:housenumber":"88-28",
    "addr:postcode":"11373",
    "addr:street":"Roosevelt Ave",
    "iso:country":"US",
    "sg:address":"88-28 Roosevelt Ave",
    "sg:city":"Queens",
    "sg:classifiers":[
        {
            "category":"Restaurant",
            "type":"Food & Drink"
        }
    ],
    "sg:postcode":"11373",
    "sg:province":"NY",
    "sg:tags":[
        "mexican"
    ],
    "wof:name":"Delicias Isabel",
    "wof:placetype":"venue"
},
  "geometry": {"coordinates":[-73.877719,40.74807],"type":"Point"}
}