{
  "type": "Feature",
  "properties": {
    "iso:country":"US",
    "sg:address":"129 State Hwy 6n",
    "sg:city":"Mahopac",
    "sg:classifiers":[
        {
            "category":"Retail",
            "subcategory":"Auto Repair",
            "type":"Services"
        }
    ],
    "sg:phone":"+1 845 621 5919",
    "sg:postcode":"10541",
    "sg:province":"NY",
    "sg:tags":[
        "wrecker"
    ],
    "wof:name":"Skyline Towing & Recovery",
    "wof:placetype":"venue"
},
  "geometry": {"coordinates":[-73.781368,41.349635],"type":"Point"}
}