{
  "type": "Feature",
  "properties": {
    "iso:country":"US",
    "sg:address":"87 Shoshone St",
    "sg:city":"Buffalo",
    "sg:classifiers":[
        {
            "category":"Real Estate",
            "subcategory":"Real Estate Agent",
            "type":"Services"
        }
    ],
    "sg:phone":"+1 716 833 2505",
    "sg:postcode":"14214",
    "sg:province":"NY",
    "sg:tags":[
        "organization",
        "membership"
    ],
    "wof:name":"Internationl All Str Sprt",
    "wof:placetype":"venue"
},
  "geometry": {"coordinates":[-78.835576,42.947536],"type":"Point"}
}