{
  "type": "Feature",
  "properties": {
    "addr:full":"49th St at 6th Ave New York NY 10019",
    "addr:postcode":"10019",
    "addr:street":"49Th St;Ave",
    "iso:country":"US",
    "sg:address":"49th St at 6th Ave",
    "sg:city":"New York",
    "sg:classifiers":[
        {
            "category":"Restaurant",
            "type":"Food & Drink"
        },
        {
            "category":"Food Court",
            "type":"Food & Drink"
        }
    ],
    "sg:postcode":"10019",
    "sg:province":"NY",
    "sg:tags":[
        "middle",
        "stand",
        "eastern"
    ],
    "sg:website":"49thand6th.com",
    "wof:name":"49th and 6th Halal Food Truck",
    "wof:placetype":"venue"
},
  "geometry": {"coordinates":[-73.98085500000001,40.759266],"type":"Point"}
}