{
  "type": "Feature",
  "properties": {
    "addr:full":"11 Maple Dr W New Hyde Park NY 11040",
    "addr:housenumber":"11",
    "addr:postcode":"11040",
    "addr:street":"Maple Dr W New Hyde Park",
    "iso:country":"US",
    "sg:address":"11 Maple Dr W",
    "sg:city":"New Hyde Park",
    "sg:classifiers":[
        {
            "category":"Building & Trades",
            "subcategory":"Construction",
            "type":"Services"
        }
    ],
    "sg:phone":"+1 516 326 7474",
    "sg:postcode":"11040",
    "sg:province":"NY",
    "sg:tags":[
        "hanging",
        "contractor"
    ],
    "wof:name":"Cappa Partners Corp",
    "wof:placetype":"venue"
},
  "geometry": {"coordinates":[-73.684617,40.744722],"type":"Point"}
}