{
  "type": "Feature",
  "properties": {
    "addr:full":"Bay Plaza Shopping Center 2210 Bartow Ave Bronx NY 10475",
    "addr:housenumber":"2210",
    "addr:postcode":"10475",
    "addr:street":"Bartow Ave",
    "iso:country":"US",
    "sg:address":"Bay Plaza Shopping Center 2210 Bartow Ave",
    "sg:city":"Bronx",
    "sg:classifiers":[
        {
            "category":"Shopping",
            "subcategory":"Department Store",
            "type":"Retail Goods"
        }
    ],
    "sg:phone":"+1 718 862 9125",
    "sg:postcode":"10475",
    "sg:province":"NY",
    "sg:website":"www.jcpenney.com",
    "wof:name":"JC Penney",
    "wof:placetype":"venue"
},
  "geometry": {"coordinates":[-73.823515,40.869006],"type":"Point"}
}