{
  "type": "Feature",
  "properties": {
    "iso:country":"US",
    "sg:address":"28 Cottage Ave",
    "sg:city":"Bay Shore",
    "sg:classifiers":[
        {
            "category":"Restaurant",
            "type":"Food & Drink"
        }
    ],
    "sg:phone":"+1   ",
    "sg:postcode":"11706",
    "sg:province":"NY",
    "sg:tags":[
        "drinking",
        "eating"
    ],
    "wof:name":"Porkys & Glenns Seafood House",
    "wof:placetype":"venue"
},
  "geometry": {"coordinates":[-73.244304,40.710318],"type":"Point"}
}