{
  "type": "Feature",
  "properties": {
    "addr:full":"56 E 34th St New York NY 10016",
    "addr:housenumber":"56",
    "addr:postcode":"10016",
    "addr:street":"E 34Th St",
    "iso:country":"US",
    "sg:address":"56 E 34th St",
    "sg:city":"New York",
    "sg:classifiers":[
        {
            "category":"Personal",
            "subcategory":"Beauty Salon",
            "type":"Services"
        },
        {
            "category":"Personal",
            "subcategory":"Hair Removal",
            "type":"Services"
        }
    ],
    "sg:phone":"+1 212 779 2465",
    "sg:postcode":"10016",
    "sg:province":"NY",
    "sg:website":"www.shapenyc.com/",
    "wof:name":"Shape Nyc",
    "wof:placetype":"venue"
},
  "geometry": {"coordinates":[-73.982281,40.747164],"type":"Point"}
}