{
  "type": "Feature",
  "properties": {
    "addr:full":"50 Independent Way Brewster NY 10509",
    "addr:housenumber":"50",
    "addr:postcode":"10509",
    "addr:street":"Independent Way",
    "iso:country":"US",
    "sg:address":"50 Independent Way",
    "sg:city":"Brewster",
    "sg:classifiers":[
        {
            "category":"Home & Garden",
            "subcategory":"Home Furnishings",
            "type":"Retail Goods"
        }
    ],
    "sg:phone":"+1 845 278 6765",
    "sg:postcode":"10509",
    "sg:province":"NY",
    "sg:tags":[
        "linen"
    ],
    "wof:name":"Linens 'n Things",
    "wof:placetype":"venue"
},
  "geometry": {"coordinates":[-73.625883,41.415818],"type":"Point"}
}