{
  "type": "Feature",
  "properties": {
    "addr:full":"3832 State Hwy 29 Johnstown NY 12095",
    "addr:housenumber":"3832",
    "addr:postcode":"12095",
    "addr:street":"State Hwy 29",
    "iso:country":"US",
    "sg:address":"3832 State Hwy 29",
    "sg:city":"Johnstown",
    "sg:classifiers":[
        {
            "category":"Building & Trades",
            "subcategory":"Landscaping Services",
            "type":"Services"
        }
    ],
    "sg:phone":"+1 518 736 1345",
    "sg:postcode":"12095",
    "sg:province":"NY",
    "sg:tags":[
        "lawn",
        "maintenance",
        "grounds"
    ],
    "wof:name":"Clark Cleaning Svc & Lawn Care",
    "wof:placetype":"venue"
},
  "geometry": {"coordinates":[-74.432112,43.030297],"type":"Point"}
}