{
  "type": "Feature",
  "properties": {
    "addr:full":"11 Frost Ln Cornwall NY 12518",
    "addr:housenumber":"11",
    "addr:postcode":"12518",
    "addr:street":"Frost Ln",
    "iso:country":"US",
    "sg:address":"11 Frost Ln",
    "sg:city":"Cornwall",
    "sg:classifiers":[
        {
            "category":"Professional",
            "subcategory":"Business Services",
            "type":"Services"
        }
    ],
    "sg:phone":"+1 845 534 7668",
    "sg:postcode":"12518",
    "sg:province":"NY",
    "sg:tags":[
        "arbitration"
    ],
    "wof:name":"Rodney Wells",
    "wof:placetype":"venue"
},
  "geometry": {"coordinates":[-74.044189,41.444317],"type":"Point"}
}