{
  "type": "Feature",
  "properties": {
    "iso:country":"US",
    "sg:address":"7481 Henry Clay Blvd",
    "sg:city":"Liverpool",
    "sg:classifiers":[
        {
            "category":"Insurance",
            "subcategory":"Insurance Agent",
            "type":"Services"
        }
    ],
    "sg:phone":"+1 315 461 1282",
    "sg:postcode":"13088",
    "sg:province":"NY",
    "wof:name":"Leonard Hatch Naples Inc",
    "wof:placetype":"venue"
},
  "geometry": {"coordinates":[-76.186904,43.132956],"type":"Point"}
}