{
  "type": "Feature",
  "properties": {
    "addr:full":"345 E 37th St New York NY 10016",
    "addr:housenumber":"345",
    "addr:postcode":"10016",
    "addr:street":"E 37Th St",
    "iso:country":"US",
    "sg:address":"345 E 37th St",
    "sg:city":"New York",
    "sg:classifiers":[
        {
            "category":"Health Services",
            "subcategory":"Doctor",
            "type":"Services"
        }
    ],
    "sg:phone":"+1 212 883 6005",
    "sg:postcode":"10016",
    "sg:province":"NY",
    "sg:tags":[
        "physician",
        "surgeon"
    ],
    "wof:name":"Nyu Midtown Obgyn Ctr",
    "wof:placetype":"venue"
},
  "geometry": {"coordinates":[-73.97256,40.746009],"type":"Point"}
}