{
  "type": "Feature",
  "properties": {
    "addr:full":"149 Fifth Avenue New York NY 10010",
    "addr:housenumber":"149",
    "addr:postcode":"10010",
    "addr:street":"Fifth Avenue",
    "iso:country":"US",
    "sg:address":"149 Fifth Avenue",
    "sg:city":"New York",
    "sg:classifiers":[
        {
            "category":"Professional",
            "subcategory":"Computer Services",
            "type":"Services"
        }
    ],
    "sg:phone":"+1 212 683 2988",
    "sg:postcode":"10010",
    "sg:province":"NY",
    "sg:tags":[
        "whitelabel",
        "social-networks",
        "social-networking",
        "recruiting",
        "social-recruiting",
        "networking",
        "referral-marketing",
        "talentvine"
    ],
    "sg:website":"http://www.selectminds.com",
    "wof:name":"SelectMinds",
    "wof:placetype":"venue"
},
  "geometry": {"coordinates":[-73.99007,40.74088],"type":"Point"}
}