{
  "type": "Feature",
  "properties": {
    "addr:full":"2574 Coney Island Ave Brooklyn NY 11223",
    "addr:housenumber":"2574",
    "addr:postcode":"11223",
    "addr:street":"Coney Island Ave",
    "iso:country":"US",
    "sg:address":"2574 Coney Island Ave",
    "sg:city":"Brooklyn",
    "sg:classifiers":[
        {
            "category":"Manufacturing",
            "subcategory":"Tools & Machinery",
            "type":"Manufacturing & Wholesale Goods"
        }
    ],
    "sg:phone":"+1   ",
    "sg:postcode":"11223",
    "sg:province":"NY",
    "sg:tags":[
        "engine",
        "equipment",
        "electrical",
        "mfg"
    ],
    "wof:name":"Anchor Remanufacturing Inc",
    "wof:placetype":"venue"
},
  "geometry": {"coordinates":[-73.96093399999999,40.594015],"type":"Point"}
}