{
  "type": "Feature",
  "properties": {
    "iso:country":"US",
    "sg:address":"459 Stuyvesant Ave",
    "sg:city":"Rye",
    "sg:classifiers":[
        {
            "category":"Recreation",
            "type":"Entertainment"
        }
    ],
    "sg:phone":"+1   ",
    "sg:postcode":"10580",
    "sg:province":"NY",
    "sg:tags":[
        "club",
        "membership",
        "eating"
    ],
    "sg:website":"www.coveleighclub.org",
    "wof:name":"Coveleigh Club",
    "wof:placetype":"venue"
},
  "geometry": {"coordinates":[-73.692475,40.94672],"type":"Point"}
}