{
  "type": "Feature",
  "properties": {
    "addr:full":"185 Franklin St Ste 5 New York NY 10013",
    "addr:housenumber":"185",
    "addr:postcode":"10013",
    "addr:street":"Franklin St Ste 5",
    "iso:country":"US",
    "sg:address":"185 Franklin St Ste 5",
    "sg:city":"New York",
    "sg:classifiers":[
        {
            "category":"Professional",
            "subcategory":"Lawyer & Legal Services",
            "type":"Services"
        }
    ],
    "sg:phone":"+1 212 334 9200",
    "sg:postcode":"10013",
    "sg:province":"NY",
    "wof:name":"Redniss",
    "wof:placetype":"venue"
},
  "geometry": {"coordinates":[-74.00937399999999,40.719323],"type":"Point"}
}