{
  "type": "Feature",
  "properties": {
    "iso:country":"US",
    "sg:address":"146 Terrace & Guy Brewer",
    "sg:city":"Jamaica",
    "sg:classifiers":[
        {
            "category":"Education",
            "subcategory":"School",
            "type":"Public Place"
        }
    ],
    "sg:phone":"+1 718 528 2238",
    "sg:postcode":"11430",
    "sg:province":"NY",
    "sg:tags":[
        "high",
        "middle",
        "elementary"
    ],
    "wof:name":"N Y City of",
    "wof:placetype":"venue"
},
  "geometry": {"coordinates":[-73.807593,40.664998],"type":"Point"}
}