{
  "type": "Feature",
  "properties": {
    "addr:full":"12401 Liberty Ave South Richmond Hill NY 11419",
    "addr:housenumber":"12401",
    "addr:postcode":"11419",
    "addr:street":"Liberty Ave South",
    "iso:country":"US",
    "sg:address":"12401 Liberty Ave",
    "sg:city":"South Richmond Hill",
    "sg:classifiers":[
        {
            "category":"Shopping",
            "subcategory":"Pharmacy",
            "type":"Retail Goods"
        }
    ],
    "sg:phone":"+1 718 845 3600",
    "sg:postcode":"11419",
    "sg:province":"NY",
    "sg:tags":[
        "drugstore"
    ],
    "wof:name":"Familiar Pharmacy",
    "wof:placetype":"venue"
},
  "geometry": {"coordinates":[-73.820198,40.687901],"type":"Point"}
}