{
  "type": "Feature",
  "properties": {
    "addr:full":"175 Remsen St Ste 1200 Brooklyn NY 11201",
    "addr:housenumber":"175",
    "addr:postcode":"11201",
    "addr:street":"Remsen St Ste 1200",
    "iso:country":"US",
    "sg:address":"175 Remsen St Ste 1200",
    "sg:city":"Brooklyn",
    "sg:classifiers":[
        {
            "category":"Professional",
            "subcategory":"Lawyer & Legal Services",
            "type":"Services"
        }
    ],
    "sg:phone":"+1 718 625 3977",
    "sg:postcode":"11201",
    "sg:province":"NY",
    "wof:name":"Law Office of Robert S Gershon",
    "wof:placetype":"venue"
},
  "geometry": {"coordinates":[-73.991798,40.693298],"type":"Point"}
}