{
  "type": "Feature",
  "properties": {
    "addr:full":"302 Main St Port Washington NY 11050",
    "addr:housenumber":"302",
    "addr:postcode":"11050",
    "addr:street":"Main St",
    "iso:country":"US",
    "sg:address":"302 Main St",
    "sg:city":"Port Washington",
    "sg:classifiers":[
        {
            "category":"Wholesale",
            "subcategory":"Non-durable Goods",
            "type":"Manufacturing & Wholesale Goods"
        }
    ],
    "sg:phone":"+1 516 767 6200",
    "sg:postcode":"11050",
    "sg:province":"NY",
    "wof:name":"Bubba Brown's Treasures",
    "wof:placetype":"venue"
},
  "geometry": {"coordinates":[-73.699032,40.832413],"type":"Point"}
}