{
  "type": "Feature",
  "properties": {
    "addr:full":"207 Cedar Ln Ossining NY 10562",
    "addr:housenumber":"207",
    "addr:postcode":"10562",
    "addr:street":"Cedar Ln",
    "iso:country":"US",
    "sg:address":"207 Cedar Ln",
    "sg:city":"Ossining",
    "sg:classifiers":[
        {
            "category":"Professional",
            "subcategory":"Business Services",
            "type":"Services"
        },
        {
            "category":"Building & Trades",
            "subcategory":"Construction",
            "type":"Services"
        }
    ],
    "sg:phone":"+1 914 923 4350",
    "sg:postcode":"10562",
    "sg:province":"NY",
    "sg:tags":[
        "designer"
    ],
    "wof:name":"Porcelli Associates Inc",
    "wof:placetype":"venue"
},
  "geometry": {"coordinates":[-73.85433999999999,41.190584],"type":"Point"}
}