{
  "type": "Feature",
  "properties": {
    "addr:full":"4212C Hylan Boulevard Staten Island NY 10308",
    "addr:housenumber":"4212c",
    "addr:postcode":"10308",
    "addr:street":"Hylan Boulevard",
    "iso:country":"US",
    "sg:address":"4212C Hylan Boulevard",
    "sg:city":"Staten Island",
    "sg:classifiers":[
        {
            "category":"Ice Cream",
            "type":"Food & Drink"
        }
    ],
    "sg:phone":"+1 718 605 5052",
    "sg:postcode":"10308",
    "sg:province":"NY",
    "sg:tags":[
        "frozen",
        "yogurt"
    ],
    "wof:name":"Ralph's Famous Italian Ices",
    "wof:placetype":"venue"
},
  "geometry": {"coordinates":[-74.15024200000001,40.537615],"type":"Point"}
}