{
  "type": "Feature",
  "properties": {
    "addr:full":"2570 Coney Island Ave Brooklyn NY 11223",
    "addr:housenumber":"2570",
    "addr:postcode":"11223",
    "addr:street":"Coney Island Ave",
    "iso:country":"US",
    "sg:address":"2570 Coney Island Ave",
    "sg:city":"Brooklyn",
    "sg:classifiers":[
        {
            "category":"Autos & Motor Vehicles",
            "subcategory":"Auto Supplies",
            "type":"Retail Goods"
        }
    ],
    "sg:phone":"+1 718 998 1556",
    "sg:postcode":"11223",
    "sg:province":"NY",
    "sg:tags":[
        "automobile",
        "part",
        "tire"
    ],
    "sg:website":"www.straussauto.com",
    "wof:name":"Strauss Discount Auto",
    "wof:placetype":"venue"
},
  "geometry": {"coordinates":[-73.960999,40.5942],"type":"Point"}
}