{
  "type": "Feature",
  "properties": {
    "addr:full":"36 Saint Marks Pl New York NY 10003",
    "addr:housenumber":"36",
    "addr:postcode":"10003",
    "addr:street":"Saint Marks Pl",
    "iso:country":"US",
    "sg:address":"36 Saint Marks Pl",
    "sg:city":"New York",
    "sg:classifiers":[
        {
            "category":"Shopping",
            "subcategory":"Jewelry",
            "type":"Retail Goods"
        }
    ],
    "sg:phone":"+1 646 602 2032",
    "sg:postcode":"10003",
    "sg:province":"NY",
    "wof:name":"Wild Gift Inc",
    "wof:placetype":"venue"
},
  "geometry": {"coordinates":[-73.987701,40.7286],"type":"Point"}
}