{
  "type": "Feature",
  "properties": {
    "addr:full":"1 Schultz St Wurtsboro NY 12771",
    "addr:housenumber":"1",
    "addr:postcode":"12771",
    "addr:street":"Schultz St",
    "iso:country":"US",
    "sg:address":"1 Schultz St",
    "sg:city":"Wurtsboro",
    "sg:classifiers":[
        {
            "category":"Autos & Motor Vehicles",
            "subcategory":"Automobile Sales",
            "type":"Retail Goods"
        }
    ],
    "sg:phone":"+1 845 888 2214",
    "sg:postcode":"12771",
    "sg:province":"NY",
    "sg:tags":[
        "car",
        "dealer"
    ],
    "wof:name":"Wurtsboro Auto Sales",
    "wof:placetype":"venue"
},
  "geometry": {"coordinates":[-74.681195,41.379101],"type":"Point"}
}