{
  "type": "Feature",
  "properties": {
    "addr:full":"155 Newbrook Ln Bay Shore NY 11706",
    "addr:housenumber":"155",
    "addr:postcode":"11706",
    "addr:street":"Newbrook Ln",
    "iso:country":"US",
    "sg:address":"155 Newbrook Ln",
    "sg:city":"Bay Shore",
    "sg:classifiers":[
        {
            "category":"Food & Beverages",
            "subcategory":"Groceries & Convenience Stores",
            "type":"Retail Goods"
        }
    ],
    "sg:phone":"+1   ",
    "sg:postcode":"11706",
    "sg:province":"NY",
    "wof:name":"Bill Vickey D Caterers & Deli",
    "wof:placetype":"venue"
},
  "geometry": {"coordinates":[-73.246325,40.747866],"type":"Point"}
}