{
  "type": "Feature",
  "properties": {
    "iso:country":"US",
    "sg:address":"772 E Main St",
    "sg:city":"Middletown",
    "sg:classifiers":[
        {
            "category":"Home & Garden",
            "subcategory":"Building Materials",
            "type":"Retail Goods"
        }
    ],
    "sg:phone":"+1 845 342 9999",
    "sg:postcode":"10940",
    "sg:province":"NY",
    "sg:tags":[
        "window",
        "siding",
        "contractor"
    ],
    "sg:website":"http://www.northernwindows.com",
    "wof:name":"Northern Windows Siding & Roofing",
    "wof:placetype":"venue"
},
  "geometry": {"coordinates":[-74.36408900000001,41.440301],"type":"Point"}
}