{
  "type": "Feature",
  "properties": {
    "addr:full":"3 Porter Ave Buffalo NY 14201",
    "addr:housenumber":"3",
    "addr:postcode":"14201",
    "addr:street":"Porter Ave",
    "iso:country":"US",
    "sg:address":"3 Porter Ave",
    "sg:city":"Buffalo",
    "sg:classifiers":[
        {
            "category":"Military Area",
            "type":"Public Place"
        }
    ],
    "sg:phone":"+1 716 885 6529",
    "sg:postcode":"14201",
    "sg:province":"NY",
    "sg:tags":[
        "force",
        "armed",
        "recruiting"
    ],
    "sg:website":"http://www.usmc.mil",
    "wof:name":"Marine Corps Recruiting Center",
    "wof:placetype":"venue"
},
  "geometry": {"coordinates":[-78.901488,42.896583],"type":"Point"}
}