{
  "type": "Feature",
  "properties": {
    "iso:country":"US",
    "sg:address":"1667 Saint Marks Ave",
    "sg:city":"Brooklyn",
    "sg:classifiers":[
        {
            "category":"Retail",
            "subcategory":"Auto Repair",
            "type":"Services"
        }
    ],
    "sg:phone":"+1 718 566 7099",
    "sg:postcode":"11233",
    "sg:province":"NY",
    "sg:website":"www.euroluxuryrepair.com",
    "wof:name":"Luxury Automotive Repairs",
    "wof:placetype":"venue"
},
  "geometry": {"coordinates":[-73.911772,40.673297],"type":"Point"}
}