{
  "type": "Feature",
  "properties": {
    "addr:full":"177 S Transit Hill Dr Depew NY 14043",
    "addr:housenumber":"177",
    "addr:postcode":"14043",
    "addr:street":"S Transit Hill Dr",
    "iso:country":"US",
    "sg:address":"177 S Transit Hill Dr",
    "sg:city":"Depew",
    "sg:classifiers":[
        {
            "category":"Freight",
            "type":"Transportation"
        }
    ],
    "sg:phone":"+1   ",
    "sg:postcode":"14043",
    "sg:province":"NY",
    "sg:tags":[
        "operator",
        "local",
        "trucking"
    ],
    "wof:name":"Novo Moving",
    "wof:placetype":"venue"
},
  "geometry": {"coordinates":[-78.707444,42.866477],"type":"Point"}
}