{
  "type": "Feature",
  "properties": {
    "iso:country":"US",
    "sg:address":"259 Hatfield Rd",
    "sg:city":"Cortland",
    "sg:classifiers":[
        {
            "category":"Home & Garden",
            "subcategory":"Building Materials",
            "type":"Retail Goods"
        }
    ],
    "sg:phone":"+1 607 753 9824",
    "sg:postcode":"13045",
    "sg:province":"NY",
    "sg:tags":[
        "door"
    ],
    "wof:name":"Central New York Overhead Drs",
    "wof:placetype":"venue"
},
  "geometry": {"coordinates":[-76.247392,42.62604],"type":"Point"}
}