{
  "type": "Feature",
  "properties": {
    "addr:full":"375 Carlls Path Deer Park NY 11729",
    "addr:housenumber":"375",
    "addr:postcode":"11729",
    "addr:street":"Carlls Path",
    "iso:country":"US",
    "sg:address":"375 Carlls Path",
    "sg:city":"Deer Park",
    "sg:classifiers":[
        {
            "category":"Government",
            "subcategory":"Post Office",
            "type":"Public Place"
        }
    ],
    "sg:phone":"+1   ",
    "sg:postcode":"11729",
    "sg:province":"NY",
    "sg:tags":[
        "postal",
        "us"
    ],
    "wof:name":"Deer Park Post Office",
    "wof:placetype":"venue"
},
  "geometry": {"coordinates":[-73.320713,40.758804],"type":"Point"}
}