{
  "type": "Feature",
  "properties": {
    "addr:full":"990 Flatbush Ave Brooklyn NY 11226",
    "addr:housenumber":"990",
    "addr:postcode":"11226",
    "addr:street":"Flatbush Ave",
    "iso:country":"US",
    "sg:address":"990 Flatbush Ave",
    "sg:city":"Brooklyn",
    "sg:classifiers":[
        {
            "category":"Wholesale",
            "subcategory":"Apparel",
            "type":"Manufacturing & Wholesale Goods"
        }
    ],
    "sg:phone":"+1 718 693 1232",
    "sg:postcode":"11226",
    "sg:province":"NY",
    "sg:tags":[
        "textile",
        "import",
        "export"
    ],
    "wof:name":"Plazatex Textile Import Export",
    "wof:placetype":"venue"
},
  "geometry": {"coordinates":[-73.958189,40.646798],"type":"Point"}
}