{
  "type": "Feature",
  "properties": {
    "iso:country":"US",
    "sg:address":"48 Main St",
    "sg:city":"S Glens Falls",
    "sg:classifiers":[
        {
            "category":"Professional",
            "subcategory":"Computer Services",
            "type":"Services"
        }
    ],
    "sg:phone":"+1 518 743 1147",
    "sg:postcode":"12803",
    "sg:province":"NY",
    "sg:tags":[
        "repair"
    ],
    "sg:website":"www.larac.org",
    "wof:name":"North Country Computers",
    "wof:placetype":"venue"
},
  "geometry": {"coordinates":[-73.638801,43.302774],"type":"Point"}
}