{
  "type": "Feature",
  "properties": {
    "addr:full":"1186 Ridge Rd Webster NY 14580",
    "addr:housenumber":"1186",
    "addr:postcode":"14580",
    "addr:street":"Ridge Rd",
    "iso:country":"US",
    "sg:address":"1186 Ridge Rd",
    "sg:city":"Webster",
    "sg:classifiers":[
        {
            "category":"Autos & Motor Vehicles",
            "subcategory":"Fuel & Gas Station",
            "type":"Retail Goods"
        },
        {
            "category":"Retail",
            "subcategory":"Auto Repair",
            "type":"Services"
        }
    ],
    "sg:phone":"+1 585 872 9903",
    "sg:postcode":"14580",
    "sg:province":"NY",
    "sg:tags":[
        "body",
        "automobile",
        "station",
        "gasoline",
        "painting"
    ],
    "wof:name":"Merz Garage & Service Station",
    "wof:placetype":"venue"
},
  "geometry": {"coordinates":[-77.438847,43.211241],"type":"Point"}
}