{
  "type": "Feature",
  "properties": {
    "addr:full":"1343 E 10th St Brooklyn NY 11230",
    "addr:housenumber":"1343",
    "addr:postcode":"11230",
    "addr:street":"E 10Th St",
    "iso:country":"US",
    "sg:address":"1343 E 10th St",
    "sg:city":"Brooklyn",
    "sg:classifiers":[
        {
            "category":"Professional",
            "subcategory":"Computer Services",
            "type":"Services"
        }
    ],
    "sg:phone":"+1 718 645 4666",
    "sg:postcode":"11230",
    "sg:province":"NY",
    "sg:tags":[
        "website",
        "design"
    ],
    "wof:name":"Chaim Hochman",
    "wof:placetype":"venue"
},
  "geometry": {"coordinates":[-73.964581,40.616914],"type":"Point"}
}