{
  "type": "Feature",
  "properties": {
    "iso:country":"US",
    "sg:address":"1640 Penfield Rd",
    "sg:city":"Rochester",
    "sg:classifiers":[
        {
            "category":"Professional",
            "subcategory":"Accounting & Tax Preparation",
            "type":"Services"
        }
    ],
    "sg:phone":"+1 585 586 1130",
    "sg:postcode":"14625",
    "sg:province":"NY",
    "sg:tags":[
        "accountant",
        "public",
        "accountants-certified"
    ],
    "wof:name":"John A Thorne Cpa",
    "wof:placetype":"venue"
},
  "geometry": {"coordinates":[-77.492544,43.133305],"type":"Point"}
}