{
  "type": "Feature",
  "properties": {
    "addr:full":"2 Estate Dr Middletown NY 10940",
    "addr:housenumber":"2",
    "addr:postcode":"10940",
    "addr:street":"Estate Dr",
    "iso:country":"US",
    "sg:address":"2 Estate Dr",
    "sg:city":"Middletown",
    "sg:classifiers":[
        {
            "category":"Professional",
            "subcategory":"Management & Consulting",
            "type":"Services"
        }
    ],
    "sg:phone":"+1 845 343 6535",
    "sg:postcode":"10940",
    "sg:province":"NY",
    "wof:name":"Norchrist Group",
    "wof:placetype":"venue"
},
  "geometry": {"coordinates":[-74.40297700000001,41.452754],"type":"Point"}
}