{
  "type": "Feature",
  "properties": {
    "iso:country":"US",
    "sg:address":"805 Kings Hwy",
    "sg:city":"Brooklyn",
    "sg:classifiers":[
        {
            "category":"Organizations",
            "subcategory":"Religious Organization",
            "type":"Services"
        }
    ],
    "sg:phone":"+1 718 376 2775",
    "sg:postcode":"11223",
    "sg:province":"NY",
    "sg:tags":[
        "synagogue"
    ],
    "wof:name":"Aish Hatorah Discovery Inc",
    "wof:placetype":"venue"
},
  "geometry": {"coordinates":[-73.96378,40.606816],"type":"Point"}
}