{
  "type": "Feature",
  "properties": {
    "iso:country":"US",
    "sg:address":"680 W Boston Post Rd",
    "sg:city":"Mamaroneck",
    "sg:classifiers":[
        {
            "category":"Personal",
            "type":"Services"
        }
    ],
    "sg:phone":"+1 914 698 1577",
    "sg:postcode":"10543",
    "sg:province":"NY",
    "sg:tags":[
        "therapist",
        "massage"
    ],
    "wof:name":"Robert A Strunsky",
    "wof:placetype":"venue"
},
  "geometry": {"coordinates":[-73.74418300000001,40.939563],"type":"Point"}
}