{
  "type": "Feature",
  "properties": {
    "addr:full":"2136 Middle Country Rd Centereach NY 11720",
    "addr:housenumber":"2136",
    "addr:postcode":"11720",
    "addr:street":"Middle Country Rd",
    "iso:country":"US",
    "sg:address":"2136 Middle Country Rd",
    "sg:city":"Centereach",
    "sg:classifiers":[
        {
            "category":"Restaurant",
            "type":"Food & Drink"
        }
    ],
    "sg:phone":"+1 631 471 5303",
    "sg:postcode":"11720",
    "sg:province":"NY",
    "sg:tags":[
        "greek",
        "pizza"
    ],
    "wof:name":"Elenis Restrnt",
    "wof:placetype":"venue"
},
  "geometry": {"coordinates":[-73.0784,40.8591],"type":"Point"}
}