{
  "type": "Feature",
  "properties": {
    "addr:full":"154 N Plank Rd Newburgh NY 12550",
    "addr:housenumber":"154",
    "addr:postcode":"12550",
    "addr:street":"N Plank Rd",
    "iso:country":"US",
    "sg:address":"154 N Plank Rd",
    "sg:city":"Newburgh",
    "sg:classifiers":[
        {
            "category":"Building & Trades",
            "subcategory":"Construction",
            "type":"Services"
        }
    ],
    "sg:phone":"+1 845 565 0991",
    "sg:postcode":"12550",
    "sg:province":"NY",
    "sg:tags":[
        "front",
        "door",
        "install",
        "store"
    ],
    "wof:name":"New Glass & Storefronts Inc",
    "wof:placetype":"venue"
},
  "geometry": {"coordinates":[-74.03965599999999,41.536401],"type":"Point"}
}