{
  "type": "Feature",
  "properties": {
    "iso:country":"US",
    "sg:address":"2937 Wilkinson Ave",
    "sg:city":"Bronx",
    "sg:classifiers":[
        {
            "category":"Shopping",
            "type":"Retail Goods"
        }
    ],
    "sg:phone":"+1   ",
    "sg:postcode":"10461",
    "sg:province":"NY",
    "sg:tags":[
        "personal",
        "merchandise"
    ],
    "wof:name":"Magickal Realms",
    "wof:placetype":"venue"
},
  "geometry": {"coordinates":[-73.82997400000001,40.85171],"type":"Point"}
}