{
  "type": "Feature",
  "properties": {
    "addr:full":"112 Dewey St Jericho NY 11753",
    "addr:housenumber":"112",
    "addr:postcode":"11753",
    "addr:street":"Dewey St",
    "iso:country":"US",
    "sg:address":"112 Dewey St",
    "sg:city":"Jericho",
    "sg:classifiers":[
        {
            "category":"Real Estate",
            "subcategory":"Real Estate Operator",
            "type":"Services"
        }
    ],
    "sg:phone":"+1 516 250 0997",
    "sg:postcode":"11753",
    "sg:province":"NY",
    "sg:tags":[
        "building",
        "nonresidential"
    ],
    "wof:name":"Island Property Development",
    "wof:placetype":"venue"
},
  "geometry": {"coordinates":[-73.544067,40.787506],"type":"Point"}
}