{
  "type": "Feature",
  "properties": {
    "iso:country":"US",
    "sg:address":"10132 Lefferts Blvd",
    "sg:city":"New York",
    "sg:classifiers":[
        {
            "category":"Professional",
            "subcategory":"Art Services",
            "type":"Services"
        },
        {
            "category":"Professional",
            "subcategory":"Printing & Photocopies",
            "type":"Services"
        }
    ],
    "sg:phone":"+1 718 843 1668",
    "sg:postcode":"11419",
    "sg:province":"NY",
    "sg:tags":[
        "photographer"
    ],
    "sg:website":"www.dstormvideophoto.com",
    "wof:name":"Digital Storm Video & Photo",
    "wof:placetype":"venue"
},
  "geometry": {"coordinates":[-73.82583,40.689626],"type":"Point"}
}