{
  "type": "Feature",
  "properties": {
    "iso:country":"US",
    "sg:address":"8 Brianna Ln",
    "sg:city":"Hilton",
    "sg:classifiers":[
        {
            "category":"Building & Trades",
            "subcategory":"Construction",
            "type":"Services"
        }
    ],
    "sg:phone":"+1 585 392 3080",
    "sg:postcode":"14468",
    "sg:province":"NY",
    "sg:tags":[
        "contractor"
    ],
    "wof:name":"G & A Construction Company",
    "wof:placetype":"venue"
},
  "geometry": {"coordinates":[-77.75911600000001,43.292034],"type":"Point"}
}