{
  "type": "Feature",
  "properties": {
    "iso:country":"US",
    "sg:address":"3633 21st Street",
    "sg:city":"Astoria",
    "sg:classifiers":[
        {
            "category":"Retail",
            "subcategory":"Car Wash",
            "type":"Services"
        }
    ],
    "sg:phone":"+1 718 706 7595",
    "sg:postcode":"11106",
    "sg:province":"NY",
    "wof:name":"John L Car Wash",
    "wof:placetype":"venue"
},
  "geometry": {"coordinates":[-73.93756999999999,40.758867],"type":"Point"}
}