{
  "type": "Feature",
  "properties": {
    "addr:full":"514 W 24th St New York NY 10011",
    "addr:housenumber":"514",
    "addr:postcode":"10011",
    "addr:street":"W 24Th St",
    "iso:country":"US",
    "sg:address":"514 W 24th St",
    "sg:city":"New York",
    "sg:classifiers":[
        {
            "category":"Communications",
            "subcategory":"Film & Video Production",
            "type":"Services"
        }
    ],
    "sg:phone":"+1 646 230 0230",
    "sg:postcode":"10011",
    "sg:province":"NY",
    "sg:tags":[
        "motion",
        "picture"
    ],
    "sg:website":"www.mechanismdigital.com",
    "wof:name":"Mechanism Digital Inc",
    "wof:placetype":"venue"
},
  "geometry": {"coordinates":[-74.006258,40.749316],"type":"Point"}
}