{
  "type": "Feature",
  "properties": {
    "addr:full":"112 Herbert St North Syracuse NY 13212",
    "addr:housenumber":"112",
    "addr:postcode":"13212",
    "addr:street":"Herbert St",
    "iso:country":"US",
    "sg:address":"112 Herbert St",
    "sg:city":"North Syracuse",
    "sg:classifiers":[
        {
            "category":"Building & Trades",
            "subcategory":"Landscaping Services",
            "type":"Services"
        }
    ],
    "sg:phone":"+1 315 458 8456",
    "sg:postcode":"13212",
    "sg:province":"NY",
    "sg:tags":[
        "tree"
    ],
    "wof:name":"Empire Treescapes",
    "wof:placetype":"venue"
},
  "geometry": {"coordinates":[-76.123644,43.136416],"type":"Point"}
}