{
  "type": "Feature",
  "properties": {
    "iso:country":"US",
    "sg:address":"124 Whittier Rd",
    "sg:city":"Rochester",
    "sg:classifiers":[
        {
            "category":"Social Services",
            "subcategory":"Child Care",
            "type":"Services"
        },
        {
            "category":"Education",
            "subcategory":"Preschool",
            "type":"Public Place"
        }
    ],
    "sg:phone":"+1 585 594 2552",
    "sg:postcode":"14624",
    "sg:province":"NY",
    "sg:tags":[
        "kindergarten",
        "school",
        "nursery"
    ],
    "sg:website":"http://www.fallonesfuntime.com",
    "wof:name":"Fallone's Funtime Center",
    "wof:placetype":"venue"
},
  "geometry": {"coordinates":[-77.765073,43.143481],"type":"Point"}
}