{
  "type": "Feature",
  "properties": {
    "addr:full":"265 W 23rd Street New York NY 10011",
    "addr:housenumber":"265",
    "addr:postcode":"10011",
    "addr:street":"W 23Rd Street",
    "iso:country":"US",
    "sg:address":"265 W 23rd Street",
    "sg:city":"New York",
    "sg:classifiers":[
        {
            "category":"Personal",
            "subcategory":"Beauty Salon",
            "type":"Services"
        }
    ],
    "sg:phone":"+1 212 243 9379",
    "sg:postcode":"10011",
    "sg:province":"NY",
    "sg:tags":[
        "hair"
    ],
    "wof:name":"Salon Cecilia",
    "wof:placetype":"venue"
},
  "geometry": {"coordinates":[-73.99820800000001,40.745044],"type":"Point"}
}