{
  "type": "Feature",
  "properties": {
    "addr:full":"80 Highland Rd Glen Cove NY 11542",
    "addr:housenumber":"80",
    "addr:postcode":"11542",
    "addr:street":"Highland Rd",
    "iso:country":"US",
    "sg:address":"80 Highland Rd",
    "sg:city":"Glen Cove",
    "sg:classifiers":[
        {
            "category":"Building & Trades",
            "subcategory":"Construction",
            "type":"Services"
        }
    ],
    "sg:phone":"+1 516 656 9653",
    "sg:postcode":"11542",
    "sg:province":"NY",
    "sg:tags":[
        "motion",
        "picture",
        "set",
        "design"
    ],
    "wof:name":"Miss Jezebel's Prop Rentals",
    "wof:placetype":"venue"
},
  "geometry": {"coordinates":[-73.623628,40.865981],"type":"Point"}
}