{
  "type": "Feature",
  "properties": {
    "iso:country":"US",
    "sg:address":"2658 Gerritsen Ave",
    "sg:city":"Brooklyn",
    "sg:classifiers":[
        {
            "category":"Real Estate",
            "subcategory":"Real Estate Agent",
            "type":"Services"
        }
    ],
    "sg:phone":"+1 718 934 0800",
    "sg:postcode":"11229",
    "sg:province":"NY",
    "wof:name":"Tracey Real Estate Inc",
    "wof:placetype":"venue"
},
  "geometry": {"coordinates":[-73.925472,40.593149],"type":"Point"}
}