{
  "type": "Feature",
  "properties": {
    "addr:full":"20 Thomas Maria Cir Webster NY 14580",
    "addr:housenumber":"20",
    "addr:postcode":"14580",
    "addr:street":"Thomas Maria Cir",
    "iso:country":"US",
    "sg:address":"20 Thomas Maria Cir",
    "sg:city":"Webster",
    "sg:classifiers":[
        {
            "category":"Professional",
            "subcategory":"Management & Consulting",
            "type":"Services"
        }
    ],
    "sg:phone":"+1 585 671 7951",
    "sg:postcode":"14580",
    "sg:province":"NY",
    "sg:tags":[
        "consultant"
    ],
    "wof:name":"DBG Consulting",
    "wof:placetype":"venue"
},
  "geometry": {"coordinates":[-77.49878,43.181296],"type":"Point"}
}