{
  "type": "Feature",
  "properties": {
    "iso:country":"US",
    "sg:address":"208 8th St",
    "sg:city":"Little Valley",
    "sg:classifiers":[
        {
            "category":"Manufacturing",
            "subcategory":"Tools & Machinery",
            "type":"Manufacturing & Wholesale Goods"
        }
    ],
    "sg:phone":"+1   ",
    "sg:postcode":"14755",
    "sg:province":"NY",
    "sg:tags":[
        "machine",
        "shop"
    ],
    "wof:name":"W D F Machine",
    "wof:placetype":"venue"
},
  "geometry": {"coordinates":[-78.802511,42.251223],"type":"Point"}
}