{
  "type": "Feature",
  "properties": {
    "iso:country":"US",
    "sg:address":"156 Hudson Ave",
    "sg:city":"Green Island",
    "sg:classifiers":[
        {
            "category":"Building & Trades",
            "subcategory":"Plumbing",
            "type":"Services"
        }
    ],
    "sg:phone":"+1 518 273 2132",
    "sg:postcode":"12183",
    "sg:province":"NY",
    "sg:tags":[
        "plumbing",
        "contractor"
    ],
    "wof:name":"A A Sewer & Drain",
    "wof:placetype":"venue"
},
  "geometry": {"coordinates":[-73.690651,42.744364],"type":"Point"}
}