{
  "type": "Feature",
  "properties": {
    "addr:full":"128 Milton Ave Ballston Spa NY 12020",
    "addr:housenumber":"128",
    "addr:postcode":"12020",
    "addr:street":"Milton Ave",
    "iso:country":"US",
    "sg:address":"128 Milton Ave",
    "sg:city":"Ballston Spa",
    "sg:classifiers":[
        {
            "category":"Building & Trades",
            "subcategory":"Construction",
            "type":"Services"
        }
    ],
    "sg:phone":"+1 518 363 0146",
    "sg:postcode":"12020",
    "sg:province":"NY",
    "sg:tags":[
        "company"
    ],
    "wof:name":"Reale Construction",
    "wof:placetype":"venue"
},
  "geometry": {"coordinates":[-73.84911099999999,43.005113],"type":"Point"}
}