{
  "type": "Feature",
  "properties": {
    "addr:full":"2545 Hylan Blvd Staten Island NY 10306",
    "addr:housenumber":"2545",
    "addr:postcode":"10306",
    "addr:street":"Hylan Blvd",
    "iso:country":"US",
    "sg:address":"2545 Hylan Blvd",
    "sg:city":"Staten Island",
    "sg:classifiers":[
        {
            "category":"Autos & Motor Vehicles",
            "subcategory":"Automobile Sales",
            "type":"Retail Goods"
        }
    ],
    "sg:phone":"+1 718 987 1231",
    "sg:postcode":"10306",
    "sg:province":"NY",
    "sg:tags":[
        "car",
        "dealer"
    ],
    "wof:name":"Scotts Auto Corner Inc",
    "wof:placetype":"venue"
},
  "geometry": {"coordinates":[-74.110662,40.569776],"type":"Point"}
}