{
  "type": "Feature",
  "properties": {
    "addr:full":"299 Broadway New York NY 10007",
    "addr:housenumber":"299",
    "addr:postcode":"10007",
    "addr:street":"Broadway",
    "iso:country":"US",
    "sg:address":"299 Broadway",
    "sg:city":"New York",
    "sg:classifiers":[
        {
            "category":"Shopping",
            "subcategory":"Computers & Home Electronics",
            "type":"Retail Goods"
        },
        {
            "category":"Professional",
            "subcategory":"Computer Services",
            "type":"Services"
        }
    ],
    "sg:phone":"+1 212 966 3355",
    "sg:postcode":"10007",
    "sg:province":"NY",
    "sg:tags":[
        "repair",
        "consulting",
        "software"
    ],
    "sg:website":"www.chelsea-tech.com",
    "wof:name":"Chelsea Technologies",
    "wof:placetype":"venue"
},
  "geometry": {"coordinates":[-74.005402,40.715199],"type":"Point"}
}