{
  "type": "Feature",
  "properties": {
    "iso:country":"US",
    "sg:address":"93 W Campbell Rd",
    "sg:city":"Schenectady",
    "sg:classifiers":[
        {
            "category":"Professional",
            "type":"Services"
        }
    ],
    "sg:phone":"+1 518 374 6911",
    "sg:postcode":"12306",
    "sg:province":"NY",
    "sg:tags":[
        "establishment"
    ],
    "wof:name":"Innovus Inc",
    "wof:placetype":"venue"
},
  "geometry": {"coordinates":[-73.99139599999999,42.806142],"type":"Point"}
}