{
  "type": "Feature",
  "properties": {
    "iso:country":"US",
    "sg:address":"7 Park Pl",
    "sg:city":"Mechanicville",
    "sg:classifiers":[
        {
            "category":"Shopping",
            "subcategory":"Discount & Variety Stores",
            "type":"Retail Goods"
        }
    ],
    "sg:phone":"+1 518 664 1198",
    "sg:postcode":"12118",
    "sg:province":"NY",
    "wof:name":"Yankee One Dollar Store",
    "wof:placetype":"venue"
},
  "geometry": {"coordinates":[-73.693196,42.901243],"type":"Point"}
}