{
  "type": "Feature",
  "properties": {
    "iso:country":"US",
    "sg:address":"1580 Columbia Tpke",
    "sg:city":"Castletn On Hdsn",
    "sg:classifiers":[
        {
            "category":"Banks & Credit Unions",
            "subcategory":"Investment Brokerage",
            "type":"Services"
        }
    ],
    "sg:phone":"+1 518 477 5468",
    "sg:postcode":"12033",
    "sg:province":"NY",
    "sg:tags":[
        "consultant",
        "planning",
        "financial"
    ],
    "wof:name":"Center Square Asset Mgmt",
    "wof:placetype":"venue"
},
  "geometry": {"coordinates":[-73.686592,42.571581],"type":"Point"}
}