{
  "type": "Feature",
  "properties": {
    "addr:full":"3714 28th Avenue Astoria NY 11103",
    "addr:housenumber":"3714",
    "addr:postcode":"11103",
    "addr:street":"28Th Avenue",
    "iso:country":"US",
    "sg:address":"3714 28th Avenue",
    "sg:city":"Astoria",
    "sg:classifiers":[
        {
            "category":"Health Services",
            "subcategory":"Dentist",
            "type":"Services"
        }
    ],
    "sg:phone":"+1 718 278 5858",
    "sg:postcode":"11103",
    "sg:province":"NY",
    "wof:name":"Liao Kenneth DDS",
    "wof:placetype":"venue"
},
  "geometry": {"coordinates":[-73.91488699999999,40.765905],"type":"Point"}
}