{
  "type": "Feature",
  "properties": {
    "addr:full":"2 Burnage Ln Babylon NY 11702",
    "addr:housenumber":"2",
    "addr:postcode":"11702",
    "addr:street":"Burnage Ln",
    "iso:country":"US",
    "sg:address":"2 Burnage Ln",
    "sg:city":"Babylon",
    "sg:classifiers":[
        {
            "category":"Health Services",
            "subcategory":"Doctor",
            "type":"Services"
        }
    ],
    "sg:phone":"+1 631 587 7641",
    "sg:postcode":"11702",
    "sg:province":"NY",
    "sg:tags":[
        "physician",
        "medical",
        "surgeon"
    ],
    "wof:name":"Conchita A Uyar MD PC",
    "wof:placetype":"venue"
},
  "geometry": {"coordinates":[-73.323807,40.713268],"type":"Point"}
}