{
  "type": "Feature",
  "properties": {
    "addr:full":"2206 Washington St Merrick NY 11566",
    "addr:housenumber":"2206",
    "addr:postcode":"11566",
    "addr:street":"Washington St",
    "iso:country":"US",
    "sg:address":"2206 Washington St",
    "sg:city":"Merrick",
    "sg:classifiers":[
        {
            "category":"Professional",
            "subcategory":"Computer Services",
            "type":"Services"
        }
    ],
    "sg:phone":"+1   ",
    "sg:postcode":"11566",
    "sg:province":"NY",
    "sg:tags":[
        "development",
        "software"
    ],
    "wof:name":"Thoughtprocess Technology LLC",
    "wof:placetype":"venue"
},
  "geometry": {"coordinates":[-73.558874,40.66295],"type":"Point"}
}