{
  "type": "Feature",
  "properties": {
    "iso:country":"US",
    "sg:address":"90 Dix Hwy",
    "sg:city":"Huntington Station",
    "sg:classifiers":[
        {
            "category":"Building & Trades",
            "subcategory":"Landscaping Services",
            "type":"Services"
        }
    ],
    "sg:phone":"+1 631 242 1683",
    "sg:postcode":"11746",
    "sg:province":"NY",
    "sg:tags":[
        "landscape"
    ],
    "wof:name":"Mastrangelo Landscaping",
    "wof:placetype":"venue"
},
  "geometry": {"coordinates":[-73.31713000000001,40.799851],"type":"Point"}
}