{
  "type": "Feature",
  "properties": {
    "iso:country":"US",
    "sg:address":"35 Randolph St",
    "sg:city":"Rochester",
    "sg:classifiers":[
        {
            "category":"Professional",
            "subcategory":"Computer Services",
            "type":"Services"
        }
    ],
    "sg:phone":"+1   ",
    "sg:postcode":"14621",
    "sg:province":"NY",
    "wof:name":"Custom Care Computing",
    "wof:placetype":"venue"
},
  "geometry": {"coordinates":[-77.584197,43.181936],"type":"Point"}
}