{
  "type": "Feature",
  "properties": {
    "addr:full":"571 Fillmore Ave Buffalo NY 14212",
    "addr:housenumber":"571",
    "addr:postcode":"14212",
    "addr:street":"Fillmore Ave",
    "iso:country":"US",
    "sg:address":"571 Fillmore Ave",
    "sg:city":"Buffalo",
    "sg:classifiers":[
        {
            "category":"Insurance",
            "subcategory":"Life Insurance",
            "type":"Services"
        }
    ],
    "sg:phone":"+1 716 854 4704",
    "sg:postcode":"14212",
    "sg:province":"NY",
    "sg:tags":[
        "carrier"
    ],
    "wof:name":"Polish Natl Alliance of US",
    "wof:placetype":"venue"
},
  "geometry": {"coordinates":[-78.839169,42.888745],"type":"Point"}
}