{
  "type": "Feature",
  "properties": {
    "iso:country":"US",
    "sg:address":"8608 4th Avenue",
    "sg:city":"Brooklyn",
    "sg:classifiers":[
        {
            "category":"Restaurant",
            "type":"Food & Drink"
        }
    ],
    "sg:phone":"+1 718 833 5300",
    "sg:postcode":"11209",
    "sg:province":"NY",
    "sg:tags":[
        "fusion",
        "asian",
        "chinese"
    ],
    "sg:website":"www.86noodles.com",
    "wof:name":"86 Noodles",
    "wof:placetype":"venue"
},
  "geometry": {"coordinates":[-74.028373,40.622733],"type":"Point"}
}