{
  "type": "Feature",
  "properties": {
    "addr:full":"40 E 9 St New York NY 10003",
    "addr:housenumber":"40;9",
    "addr:postcode":"10003",
    "addr:street":"E",
    "iso:country":"US",
    "sg:address":"40 E 9 St",
    "sg:city":"New York",
    "sg:classifiers":[
        {
            "category":"Social Services",
            "type":"Services"
        }
    ],
    "sg:phone":"+1 212 614 8096",
    "sg:postcode":"10003",
    "sg:province":"NY",
    "sg:tags":[
        "youth",
        "initiative",
        "employment",
        "starting"
    ],
    "wof:name":"Bouchville Manors",
    "wof:placetype":"venue"
},
  "geometry": {"coordinates":[-73.992529,40.731417],"type":"Point"}
}