{
  "type": "Feature",
  "properties": {
    "addr:full":"299 W Houston St New York NY 10014",
    "addr:housenumber":"299",
    "addr:postcode":"10014",
    "addr:street":"W Houston St",
    "iso:country":"US",
    "sg:address":"299 W Houston St",
    "sg:city":"New York",
    "sg:classifiers":[
        {
            "category":"Professional",
            "subcategory":"Advertising",
            "type":"Services"
        }
    ],
    "sg:phone":"+1 212 206 5800",
    "sg:postcode":"10014",
    "sg:province":"NY",
    "sg:tags":[
        "agency"
    ],
    "wof:name":"Llkfb",
    "wof:placetype":"venue"
},
  "geometry": {"coordinates":[-74.007882,40.72875],"type":"Point"}
}