{
  "type": "Feature",
  "properties": {
    "addr:full":"67 Hollywood Pl Huntington NY 11743",
    "addr:housenumber":"67",
    "addr:postcode":"11743",
    "addr:street":"Hollywood Pl",
    "iso:country":"US",
    "sg:address":"67 Hollywood Pl",
    "sg:city":"Huntington",
    "sg:classifiers":[
        {
            "category":"Shopping",
            "subcategory":"Used Merchandise",
            "type":"Retail Goods"
        }
    ],
    "sg:phone":"+1 631 421 1400",
    "sg:postcode":"11743",
    "sg:province":"NY",
    "sg:tags":[
        "antique"
    ],
    "wof:name":"Cracker Barrel Galleries Inc",
    "wof:placetype":"venue"
},
  "geometry": {"coordinates":[-73.430477,40.865698],"type":"Point"}
}