{
  "type": "Feature",
  "properties": {
    "iso:country":"US",
    "sg:address":"295 Central Park W",
    "sg:city":"New York",
    "sg:classifiers":[
        {
            "category":"Health Services",
            "subcategory":"Doctor",
            "type":"Services"
        }
    ],
    "sg:phone":"+1 212 362 8883",
    "sg:postcode":"10024",
    "sg:province":"NY",
    "sg:tags":[
        "medical"
    ],
    "wof:name":"Felix Kleyman MD",
    "wof:placetype":"venue"
},
  "geometry": {"coordinates":[-73.967696,40.787578],"type":"Point"}
}