{
  "type": "Feature",
  "properties": {
    "iso:country":"US",
    "sg:address":"4704 State Hwy 19",
    "sg:city":"Belmont",
    "sg:classifiers":[
        {
            "category":"Restaurant",
            "type":"Food & Drink"
        }
    ],
    "sg:phone":"+1 585 268 7222",
    "sg:postcode":"14813",
    "sg:province":"NY",
    "wof:name":"Coffee Mill",
    "wof:placetype":"venue"
},
  "geometry": {"coordinates":[-78.001485,42.199106],"type":"Point"}
}