{
  "type": "Feature",
  "properties": {
    "iso:country":"US",
    "sg:address":"3006 State Hwy 50",
    "sg:city":"Saratoga Springs",
    "sg:classifiers":[
        {
            "category":"Food & Beverages",
            "subcategory":"Groceries & Convenience Stores",
            "type":"Retail Goods"
        }
    ],
    "sg:phone":"+1 518 584 8579",
    "sg:postcode":"12866",
    "sg:province":"NY",
    "wof:name":"Amerada Hess Corp",
    "wof:placetype":"venue"
},
  "geometry": {"coordinates":[-73.74995199999999,43.09782],"type":"Point"}
}