{
  "type": "Feature",
  "properties": {
    "addr:full":"4171 Broadway New York NY 10033",
    "addr:housenumber":"4171",
    "addr:postcode":"10033",
    "addr:street":"Broadway",
    "iso:country":"US",
    "sg:address":"4171 Broadway",
    "sg:city":"New York",
    "sg:classifiers":[
        {
            "category":"Home & Garden",
            "subcategory":"Furniture",
            "type":"Retail Goods"
        }
    ],
    "sg:phone":"+1 212 795 6952",
    "sg:postcode":"10033",
    "sg:province":"NY",
    "sg:tags":[
        "store"
    ],
    "sg:website":"www.lunafurniture.com",
    "wof:name":"Luna Furniture Inc",
    "wof:placetype":"venue"
},
  "geometry": {"coordinates":[-73.938301,40.847301],"type":"Point"}
}