{
  "type": "Feature",
  "properties": {
    "iso:country":"US",
    "sg:address":"66 Shore Rd",
    "sg:city":"East Setauket",
    "sg:classifiers":[
        {
            "category":"Recreation",
            "subcategory":"Marina",
            "type":"Entertainment"
        }
    ],
    "sg:phone":"+1 631 941 4640",
    "sg:postcode":"11733",
    "sg:province":"NY",
    "wof:name":"Setauket Harbor Marina LLC",
    "wof:placetype":"venue"
},
  "geometry": {"coordinates":[-73.102395,40.946955],"type":"Point"}
}