{
  "type": "Feature",
  "properties": {
    "addr:full":"1427 Flatbush Ave Brooklyn NY 11210",
    "addr:housenumber":"1427",
    "addr:postcode":"11210",
    "addr:street":"Flatbush Ave",
    "iso:country":"US",
    "sg:address":"1427 Flatbush Ave",
    "sg:city":"Brooklyn",
    "sg:classifiers":[
        {
            "category":"Real Estate",
            "subcategory":"Real Estate Agent",
            "type":"Services"
        }
    ],
    "sg:phone":"+1 718 434 5585",
    "sg:postcode":"11210",
    "sg:province":"NY",
    "sg:website":"www.sunbeamrealty.com",
    "wof:name":"Eclipse Realty",
    "wof:placetype":"venue"
},
  "geometry": {"coordinates":[-73.950005,40.63522],"type":"Point"}
}