{
  "type": "Feature",
  "properties": {
    "iso:country":"US",
    "sg:address":"22 Russell Rd",
    "sg:city":"Wappingers Falls",
    "sg:classifiers":[
        {
            "category":"Building & Trades",
            "subcategory":"Construction",
            "type":"Services"
        }
    ],
    "sg:phone":"+1 845 462 4466",
    "sg:postcode":"12590",
    "sg:province":"NY",
    "sg:tags":[
        "contractor"
    ],
    "wof:name":"McSpendon George",
    "wof:placetype":"venue"
},
  "geometry": {"coordinates":[-73.869499,41.6213],"type":"Point"}
}