{
  "type": "Feature",
  "properties": {
    "addr:full":"609 Rte 109 West Babylon NY 11704",
    "addr:housenumber":"609",
    "addr:postcode":"11704",
    "addr:street":"Rte 109",
    "iso:country":"US",
    "sg:address":"609 Rte 109",
    "sg:city":"West Babylon",
    "sg:classifiers":[
        {
            "category":"Building & Trades",
            "subcategory":"Cleaning & Sanitation",
            "type":"Services"
        }
    ],
    "sg:phone":"+1 631 888 8802",
    "sg:postcode":"11704",
    "sg:province":"NY",
    "wof:name":"Kleen Freeks Cleaning Contr",
    "wof:placetype":"venue"
},
  "geometry": {"coordinates":[-73.37783899999999,40.713798],"type":"Point"}
}