{
  "type": "Feature",
  "properties": {
    "iso:country":"US",
    "sg:address":"17 Deerwood Dr",
    "sg:city":"New City",
    "sg:classifiers":[
        {
            "category":"Manufacturing",
            "subcategory":"Tools & Machinery",
            "type":"Manufacturing & Wholesale Goods"
        }
    ],
    "sg:phone":"+1   ",
    "sg:postcode":"10956",
    "sg:province":"NY",
    "sg:tags":[
        "equipment",
        "peripheral",
        "computer",
        "mfg"
    ],
    "wof:name":"Universal PC Inc",
    "wof:placetype":"venue"
},
  "geometry": {"coordinates":[-74.004024,41.128768],"type":"Point"}
}