{
  "type": "Feature",
  "properties": {
    "iso:country":"US",
    "sg:address":"188 Audubon Avenue",
    "sg:city":"New York",
    "sg:classifiers":[
        {
            "category":"Personal",
            "type":"Services"
        }
    ],
    "sg:phone":"+1 212 928 2878",
    "sg:postcode":"10033",
    "sg:province":"NY",
    "sg:tags":[
        "sewing",
        "alteration"
    ],
    "wof:name":"Emilio M Deschamps Tailoring Shop",
    "wof:placetype":"venue"
},
  "geometry": {"coordinates":[-73.935508,40.844385],"type":"Point"}
}