{
  "type": "Feature",
  "properties": {
    "addr:full":"6 Hutton Ave Nanuet NY 10954",
    "addr:housenumber":"6",
    "addr:postcode":"10954",
    "addr:street":"Hutton Ave",
    "iso:country":"US",
    "sg:address":"6 Hutton Ave",
    "sg:city":"Nanuet",
    "sg:classifiers":[
        {
            "category":"Shopping",
            "subcategory":"Stationery & Office Supplies",
            "type":"Retail Goods"
        },
        {
            "category":"Professional",
            "subcategory":"Printing & Photocopies",
            "type":"Services"
        }
    ],
    "sg:phone":"+1 845 623 6783",
    "sg:postcode":"10954",
    "sg:province":"NY",
    "sg:tags":[
        "photocopying"
    ],
    "wof:name":"Office Max",
    "wof:placetype":"venue"
},
  "geometry": {"coordinates":[-74.019249,41.100903],"type":"Point"}
}