{
  "type": "Feature",
  "properties": {
    "addr:full":"216 3rd Ave Frnt New York NY 10003",
    "addr:housenumber":"216",
    "addr:postcode":"10003",
    "addr:street":"3Rd Ave",
    "iso:country":"US",
    "sg:address":"216 3rd Ave Frnt",
    "sg:city":"New York",
    "sg:classifiers":[
        {
            "category":"Restaurant",
            "type":"Food & Drink"
        }
    ],
    "sg:phone":"+1 212 529 3960",
    "sg:postcode":"10003",
    "sg:province":"NY",
    "sg:tags":[
        "mexican"
    ],
    "wof:name":"Happy Face Chinese & Mexican Restaurant",
    "wof:placetype":"venue"
},
  "geometry": {"coordinates":[-73.9851,40.736198],"type":"Point"}
}