{
  "type": "Feature",
  "properties": {
    "addr:full":"1593 E 94th St Brooklyn NY 11236",
    "addr:housenumber":"1593",
    "addr:postcode":"11236",
    "addr:street":"E 94Th St",
    "iso:country":"US",
    "sg:address":"1593 E 94th St",
    "sg:city":"Brooklyn",
    "sg:classifiers":[
        {
            "category":"Organizations",
            "subcategory":"Religious Organization",
            "type":"Services"
        }
    ],
    "sg:phone":"+1 718 241 8703",
    "sg:postcode":"11236",
    "sg:province":"NY",
    "sg:tags":[
        "clergy"
    ],
    "wof:name":"Abraham Charlap",
    "wof:placetype":"venue"
},
  "geometry": {"coordinates":[-73.892122,40.632322],"type":"Point"}
}