{
  "type": "Feature",
  "properties": {
    "addr:full":"331 Vanderbilt Ave Brooklyn NY 11205",
    "addr:housenumber":"331",
    "addr:postcode":"11205",
    "addr:street":"Vanderbilt Ave",
    "iso:country":"US",
    "sg:address":"331 Vanderbilt Ave",
    "sg:city":"Brooklyn",
    "sg:classifiers":[
        {
            "category":"Professional",
            "type":"Services"
        }
    ],
    "sg:phone":"+1 718 230 3320",
    "sg:postcode":"11205",
    "sg:province":"NY",
    "sg:tags":[
        "establishment"
    ],
    "wof:name":"Ties That Bind",
    "wof:placetype":"venue"
},
  "geometry": {"coordinates":[-73.96890500000001,40.689171],"type":"Point"}
}