{
  "type": "Feature",
  "properties": {
    "iso:country":"US",
    "sg:address":"480 Patchogue Holbrok Rd Unit 23",
    "sg:city":"Holbrook",
    "sg:classifiers":[
        {
            "category":"Restaurant",
            "type":"Food & Drink"
        }
    ],
    "sg:phone":"+1 631 589 7777",
    "sg:postcode":"11741",
    "sg:province":"NY",
    "sg:tags":[
        "pizza"
    ],
    "wof:name":"Carlo's Pizza Oven",
    "wof:placetype":"venue"
},
  "geometry": {"coordinates":[-73.055603,40.7934],"type":"Point"}
}