{
  "type": "Feature",
  "properties": {
    "iso:country":"US",
    "sg:address":"1811 Penfield Rd",
    "sg:city":"Penfield",
    "sg:classifiers":[
        {
            "category":"Restaurant",
            "type":"Food & Drink"
        }
    ],
    "sg:phone":"+1   ",
    "sg:postcode":"14526",
    "sg:province":"NY",
    "sg:tags":[
        "eating"
    ],
    "wof:name":"Pontillos Pizza",
    "wof:placetype":"venue"
},
  "geometry": {"coordinates":[-77.478945,43.129112],"type":"Point"}
}