{
  "type": "Feature",
  "properties": {
    "iso:country":"US",
    "sg:address":"1573 Flatbush Ave",
    "sg:city":"Brooklyn",
    "sg:classifiers":[
        {
            "category":"Shopping",
            "type":"Retail Goods"
        }
    ],
    "sg:phone":"+1   ",
    "sg:postcode":"11210",
    "sg:province":"NY",
    "sg:tags":[
        "mobile",
        "phone",
        "merchandise"
    ],
    "wof:name":"American Telecommunications",
    "wof:placetype":"venue"
},
  "geometry": {"coordinates":[-73.947226,40.632669],"type":"Point"}
}