{
  "type": "Feature",
  "properties": {
    "addr:full":"52 Thorman Ave Hicksville NY 11801",
    "addr:housenumber":"52",
    "addr:postcode":"11801",
    "addr:street":"Thorman Ave",
    "iso:country":"US",
    "sg:address":"52 Thorman Ave",
    "sg:city":"Hicksville",
    "sg:classifiers":[
        {
            "category":"Real Estate",
            "subcategory":"Real Estate Agent",
            "type":"Services"
        }
    ],
    "sg:phone":"+1 516 433 3823",
    "sg:postcode":"11801",
    "sg:province":"NY",
    "wof:name":"Real Estate Development",
    "wof:placetype":"venue"
},
  "geometry": {"coordinates":[-73.52473500000001,40.771554],"type":"Point"}
}