{
  "type": "Feature",
  "properties": {
    "addr:full":"30 Lafayette Ave Ossining NY 10562",
    "addr:housenumber":"30",
    "addr:postcode":"10562",
    "addr:street":"Lafayette Ave",
    "iso:country":"US",
    "sg:address":"30 Lafayette Ave",
    "sg:city":"Ossining",
    "sg:classifiers":[
        {
            "category":"Personal",
            "type":"Services"
        }
    ],
    "sg:phone":"+1 914 923 1899",
    "sg:postcode":"10562",
    "sg:province":"NY",
    "sg:tags":[
        "pet",
        "exercising"
    ],
    "wof:name":"Animal Care Co",
    "wof:placetype":"venue"
},
  "geometry": {"coordinates":[-73.86285100000001,41.151288],"type":"Point"}
}