{
  "type": "Feature",
  "properties": {
    "addr:full":"12 W 72 St New York NY 10023",
    "addr:housenumber":"12",
    "addr:postcode":"10023",
    "addr:street":"W 72 St",
    "iso:country":"US",
    "sg:address":"12 W 72 St",
    "sg:city":"New York",
    "sg:classifiers":[
        {
            "category":"Retail",
            "subcategory":"Repair Shop",
            "type":"Services"
        }
    ],
    "sg:phone":"+1 646 224 0514",
    "sg:postcode":"10023",
    "sg:province":"NY",
    "sg:tags":[
        "lock",
        "locksmith"
    ],
    "wof:name":"AAA Number 1 Locksmith",
    "wof:placetype":"venue"
},
  "geometry": {"coordinates":[-73.976443,40.776312],"type":"Point"}
}