{
  "type": "Feature",
  "properties": {
    "addr:full":"5876 Big Tree Rd Lakeville NY 14480",
    "addr:housenumber":"5876",
    "addr:postcode":"14480",
    "addr:street":"Big Tree Rd",
    "iso:country":"US",
    "sg:address":"5876 Big Tree Rd",
    "sg:city":"Lakeville",
    "sg:classifiers":[
        {
            "category":"Home & Garden",
            "subcategory":"Home Furnishings",
            "type":"Retail Goods"
        }
    ],
    "sg:phone":"+1   ",
    "sg:postcode":"14480",
    "sg:province":"NY",
    "wof:name":"Dianne Krusen",
    "wof:placetype":"venue"
},
  "geometry": {"coordinates":[-77.702223,42.835456],"type":"Point"}
}