{
  "type": "Feature",
  "properties": {
    "addr:full":"1070 Broadway Brooklyn NY 11221",
    "addr:housenumber":"1070",
    "addr:postcode":"11221",
    "addr:street":"Broadway",
    "iso:country":"US",
    "sg:address":"1070 Broadway",
    "sg:city":"Brooklyn",
    "sg:classifiers":[
        {
            "category":"Personal",
            "subcategory":"Beauty Salon",
            "type":"Services"
        }
    ],
    "sg:phone":"+1   ",
    "sg:postcode":"11221",
    "sg:province":"NY",
    "sg:tags":[
        "shop"
    ],
    "wof:name":"Broadway International",
    "wof:placetype":"venue"
},
  "geometry": {"coordinates":[-73.93166600000001,40.694939],"type":"Point"}
}