{
  "type": "Feature",
  "properties": {
    "iso:country":"US",
    "sg:address":"120 E 23 St",
    "sg:city":"New York",
    "sg:classifiers":[
        {
            "category":"Real Estate",
            "subcategory":"Real Estate Agent",
            "type":"Services"
        }
    ],
    "sg:phone":"+1 212 473 8460",
    "sg:postcode":"10010",
    "sg:province":"NY",
    "wof:name":"Gramercy Five Assoc Inc Rl Est",
    "wof:placetype":"venue"
},
  "geometry": {"coordinates":[-73.985551,40.739866],"type":"Point"}
}