{
  "type": "Feature",
  "properties": {
    "iso:country":"US",
    "sg:address":"142 Pine St",
    "sg:city":"Freeport",
    "sg:classifiers":[
        {
            "category":"Organizations",
            "subcategory":"Professional Association",
            "type":"Services"
        }
    ],
    "sg:phone":"+1 516 546 0054",
    "sg:postcode":"11520",
    "sg:province":"NY",
    "wof:name":"Association For The Help",
    "wof:placetype":"venue"
},
  "geometry": {"coordinates":[-73.59011599999999,40.654675],"type":"Point"}
}