{
  "type": "Feature",
  "properties": {
    "addr:full":"509 Grand St New York NY 10002",
    "addr:housenumber":"509",
    "addr:postcode":"10002",
    "addr:street":"Grand St",
    "iso:country":"US",
    "sg:address":"509 Grand St",
    "sg:city":"New York",
    "sg:classifiers":[
        {
            "category":"Building & Trades",
            "subcategory":"Cleaning & Sanitation",
            "type":"Services"
        }
    ],
    "sg:phone":"+1 212 763 0042",
    "sg:postcode":"10002",
    "sg:province":"NY",
    "sg:tags":[
        "newspaper",
        "magazine",
        "janitor",
        "carpet"
    ],
    "sg:website":"www.nybrite.com",
    "wof:name":"N Y Brite",
    "wof:placetype":"venue"
},
  "geometry": {"coordinates":[-73.982101,40.714699],"type":"Point"}
}