{
  "type": "Feature",
  "properties": {
    "iso:country":"US",
    "sg:address":"8851 Tunison Rd",
    "sg:city":"Interlaken",
    "sg:classifiers":[
        {
            "category":"Building & Trades",
            "subcategory":"Construction",
            "type":"Services"
        }
    ],
    "sg:phone":"+1 607 532 4817",
    "sg:postcode":"14847",
    "sg:province":"NY",
    "sg:tags":[
        "resurfacing",
        "laying",
        "refinishing",
        "floor"
    ],
    "wof:name":"Ungleich's Hardwood Floors",
    "wof:placetype":"venue"
},
  "geometry": {"coordinates":[-76.743317,42.587847],"type":"Point"}
}