{
  "type": "Feature",
  "properties": {
    "iso:country":"US",
    "sg:address":"741 Davison Rd",
    "sg:city":"Lockport",
    "sg:classifiers":[
        {
            "category":"Health Services",
            "subcategory":"Doctor",
            "type":"Services"
        }
    ],
    "sg:phone":"+1 716 433 6666",
    "sg:postcode":"14094",
    "sg:province":"NY",
    "sg:tags":[
        "physician",
        "medical",
        "surgeon"
    ],
    "wof:name":"Nazir Gilkar MD PC",
    "wof:placetype":"venue"
},
  "geometry": {"coordinates":[-78.66551699999999,43.157723],"type":"Point"}
}