{
  "type": "Feature",
  "properties": {
    "iso:country":"US",
    "sg:address":"8011 Brewerton Rd",
    "sg:city":"Cicero",
    "sg:phone":"+1 877 212 2551",
    "sg:postcode":"13039",
    "sg:province":"NY",
    "sg:website":"http://www.autorentalsyracuse.com/default.asp",
    "wof:name":"Discount Auto Rental, Inc",
    "wof:placetype":"venue"
},
  "geometry": {"coordinates":[-76.122215,43.156705],"type":"Point"}
}