{
  "type": "Feature",
  "properties": {
    "addr:full":"422 Amsterdam Ave New York NY 10024",
    "addr:housenumber":"422",
    "addr:postcode":"10024",
    "addr:street":"Amsterdam Ave",
    "iso:country":"US",
    "sg:address":"422 Amsterdam Ave",
    "sg:city":"New York",
    "sg:classifiers":[
        {
            "category":"Real Estate",
            "subcategory":"Architect",
            "type":"Services"
        }
    ],
    "sg:phone":"+1   ",
    "sg:postcode":"10024",
    "sg:province":"NY",
    "sg:tags":[
        "architectural"
    ],
    "wof:name":"Peter Brassard Design",
    "wof:placetype":"venue"
},
  "geometry": {"coordinates":[-73.977507,40.78436],"type":"Point"}
}