{
  "type": "Feature",
  "properties": {
    "addr:full":"18 Waterworks Ln Fairport NY 14450",
    "addr:housenumber":"18",
    "addr:postcode":"14450",
    "addr:street":"Waterworks Ln",
    "iso:country":"US",
    "sg:address":"18 Waterworks Ln",
    "sg:city":"Fairport",
    "sg:classifiers":[
        {
            "category":"Professional",
            "subcategory":"Business Services",
            "type":"Services"
        }
    ],
    "sg:phone":"+1 585 425 1107",
    "sg:postcode":"14450",
    "sg:province":"NY",
    "sg:tags":[
        "interior",
        "consultant",
        "designer",
        "design",
        "decorator"
    ],
    "wof:name":"Donna Ehmann Interiors",
    "wof:placetype":"venue"
},
  "geometry": {"coordinates":[-77.445393,43.063334],"type":"Point"}
}