{
  "type": "Feature",
  "properties": {
    "addr:full":"297 Main St Highland Falls NY 10928",
    "addr:housenumber":"297",
    "addr:postcode":"10928",
    "addr:street":"Main St",
    "iso:country":"US",
    "sg:address":"297 Main St",
    "sg:city":"Highland Falls",
    "sg:classifiers":[
        {
            "category":"Cinema",
            "subcategory":"Movie Rental",
            "type":"Entertainment"
        }
    ],
    "sg:phone":"+1 845 446 3000",
    "sg:postcode":"10928",
    "sg:province":"NY",
    "sg:tags":[
        "video",
        "store"
    ],
    "wof:name":"Village Video",
    "wof:placetype":"venue"
},
  "geometry": {"coordinates":[-73.965963,41.369587],"type":"Point"}
}