{
  "type": "Feature",
  "properties": {
    "iso:country":"US",
    "sg:address":"1415 Mott Ave",
    "sg:city":"Far Rockaway",
    "sg:classifiers":[
        {
            "category":"Health Services",
            "subcategory":"Doctor",
            "type":"Services"
        }
    ],
    "sg:phone":"+1 800 813 9596",
    "sg:postcode":"11691",
    "sg:province":"NY",
    "wof:name":"Networks Doctors Inc",
    "wof:placetype":"venue"
},
  "geometry": {"coordinates":[-73.747879,40.601063],"type":"Point"}
}