{
  "type": "Feature",
  "properties": {
    "iso:country":"US",
    "sg:address":"210 East Ave",
    "sg:city":"Newark",
    "sg:classifiers":[
        {
            "category":"Organizations",
            "subcategory":"Community Association",
            "type":"Services"
        }
    ],
    "sg:phone":"+1 315 331 0629",
    "sg:postcode":"14513",
    "sg:province":"NY",
    "sg:tags":[
        "fraternal"
    ],
    "wof:name":"Masonic Temple",
    "wof:placetype":"venue"
},
  "geometry": {"coordinates":[-77.092448,43.045715],"type":"Point"}
}