{
  "type": "Feature",
  "properties": {
    "addr:full":"971 1 Ave New York NY 10022",
    "addr:housenumber":"971",
    "addr:postcode":"10022",
    "addr:street":"1 Ave",
    "iso:country":"US",
    "sg:address":"971 1 Ave",
    "sg:city":"New York",
    "sg:classifiers":[
        {
            "category":"Personal",
            "subcategory":"Shoe Repair & Shine",
            "type":"Services"
        }
    ],
    "sg:phone":"+1 212 759 9266",
    "sg:postcode":"10022",
    "sg:province":"NY",
    "sg:tags":[
        "repairing",
        "boot"
    ],
    "wof:name":"Elite Shoe Repair Corp",
    "wof:placetype":"venue"
},
  "geometry": {"coordinates":[-73.966157,40.753878],"type":"Point"}
}