{
  "type": "Feature",
  "properties": {
    "iso:country":"US",
    "sg:address":"3826 Howlett Hill Rd",
    "sg:city":"Syracuse",
    "sg:classifiers":[
        {
            "category":"Restaurant",
            "type":"Food & Drink"
        }
    ],
    "sg:phone":"+1   ",
    "sg:postcode":"13215",
    "sg:province":"NY",
    "sg:tags":[
        "eating"
    ],
    "wof:name":"Good Source Food Services",
    "wof:placetype":"venue"
},
  "geometry": {"coordinates":[-76.247776,43.01429],"type":"Point"}
}