{
  "type": "Feature",
  "properties": {
    "addr:full":"612 W 187th Street New York NY 10033",
    "addr:housenumber":"612",
    "addr:postcode":"10033",
    "addr:street":"W 187Th Street",
    "iso:country":"US",
    "sg:address":"612 W 187th Street",
    "sg:city":"New York",
    "sg:classifiers":[
        {
            "category":"Education",
            "subcategory":"School",
            "type":"Public Place"
        }
    ],
    "sg:phone":"+1 212 568 7291",
    "sg:postcode":"10033",
    "sg:province":"NY",
    "sg:tags":[
        "high",
        "middle",
        "elementary"
    ],
    "wof:name":"St Elizabeth's School",
    "wof:placetype":"venue"
},
  "geometry": {"coordinates":[-73.93117599999999,40.853267],"type":"Point"}
}