{
  "type": "Feature",
  "properties": {
    "addr:full":"210 Court St Binghamton NY 13901",
    "addr:housenumber":"210",
    "addr:postcode":"13901",
    "addr:street":"Court St",
    "iso:country":"US",
    "sg:address":"210 Court St",
    "sg:city":"Binghamton",
    "sg:classifiers":[
        {
            "category":"Autos & Motor Vehicles",
            "subcategory":"Fuel & Gas Station",
            "type":"Retail Goods"
        }
    ],
    "sg:phone":"+1   ",
    "sg:postcode":"13901",
    "sg:province":"NY",
    "sg:tags":[
        "convenience",
        "station",
        "gasoline",
        "store"
    ],
    "wof:name":"Court Street Getty Mart",
    "wof:placetype":"venue"
},
  "geometry": {"coordinates":[-75.902796,42.100937],"type":"Point"}
}