{
  "type": "Feature",
  "properties": {
    "iso:country":"US",
    "sg:address":"18 Central Park N",
    "sg:city":"New York",
    "sg:classifiers":[
        {
            "category":"Restaurant",
            "type":"Food & Drink"
        }
    ],
    "sg:phone":"+1   ",
    "sg:postcode":"10026",
    "sg:province":"NY",
    "sg:tags":[
        "take",
        "out"
    ],
    "wof:name":"Paninoteca Italiana",
    "wof:placetype":"venue"
},
  "geometry": {"coordinates":[-73.952084,40.798117],"type":"Point"}
}