{
  "type": "Feature",
  "properties": {
    "addr:full":"7 22nd St Jericho NY 11753",
    "addr:housenumber":"7",
    "addr:postcode":"11753",
    "addr:street":"22Nd St",
    "iso:country":"US",
    "sg:address":"7 22nd St",
    "sg:city":"Jericho",
    "sg:classifiers":[
        {
            "category":"Building & Trades",
            "subcategory":"Landscaping Services",
            "type":"Services"
        }
    ],
    "sg:phone":"+1 516 433 1420",
    "sg:postcode":"11753",
    "sg:province":"NY",
    "wof:name":"Thomas Sieb Tree & Shrub Care",
    "wof:placetype":"venue"
},
  "geometry": {"coordinates":[-73.52768,40.782726],"type":"Point"}
}