{
  "type": "Feature",
  "properties": {
    "addr:full":"3450 Winton Pl Rochester NY 14623",
    "addr:housenumber":"3450",
    "addr:postcode":"14623",
    "addr:street":"Winton Pl",
    "iso:country":"US",
    "sg:address":"3450 Winton Pl",
    "sg:city":"Rochester",
    "sg:classifiers":[
        {
            "category":"Professional",
            "type":"Services"
        },
        {
            "category":"Deli",
            "type":"Food & Drink"
        },
        {
            "category":"Restaurant",
            "type":"Food & Drink"
        }
    ],
    "sg:phone":"+1 585 427 8200",
    "sg:postcode":"14623",
    "sg:province":"NY",
    "sg:tags":[
        "delicatessen",
        "style",
        "family",
        "caterer"
    ],
    "sg:website":"http://www.foxsdeli.com",
    "wof:name":"Fox's Gourmet Delicatessen",
    "wof:placetype":"venue"
},
  "geometry": {"coordinates":[-77.58000199999999,43.095989],"type":"Point"}
}