{
  "type": "Feature",
  "properties": {
    "iso:country":"US",
    "sg:address":"2309 Colvin Blvd",
    "sg:city":"Tonawanda",
    "sg:classifiers":[
        {
            "category":"Food & Beverages",
            "subcategory":"Specialty",
            "type":"Retail Goods"
        },
        {
            "category":"Food & Beverages",
            "subcategory":"Supermarket",
            "type":"Retail Goods"
        },
        {
            "category":"Food & Beverages",
            "subcategory":"Groceries & Convenience Stores",
            "type":"Retail Goods"
        }
    ],
    "sg:phone":"+1 716 832 7878",
    "sg:postcode":"14150",
    "sg:province":"NY",
    "sg:tags":[
        "super",
        "grocers-specialty"
    ],
    "sg:website":"http://www.unionfacts.com",
    "wof:name":"Kwik - Fill",
    "wof:placetype":"venue"
},
  "geometry": {"coordinates":[-78.854713,43.002617],"type":"Point"}
}