{
  "type": "Feature",
  "properties": {
    "iso:country":"US",
    "sg:address":"55 Woodland Dr",
    "sg:city":"Oyster Bay",
    "sg:classifiers":[
        {
            "category":"Professional",
            "subcategory":"Business Services",
            "type":"Services"
        }
    ],
    "sg:phone":"+1   ",
    "sg:postcode":"11771",
    "sg:province":"NY",
    "sg:tags":[
        "interior",
        "residential",
        "design",
        "home"
    ],
    "wof:name":"Lees Interior Design Services",
    "wof:placetype":"venue"
},
  "geometry": {"coordinates":[-73.49857299999999,40.858077],"type":"Point"}
}