{
  "type": "Feature",
  "properties": {
    "iso:country":"US",
    "sg:address":"1591 S Park Ave",
    "sg:city":"Buffalo",
    "sg:classifiers":[
        {
            "category":"Restaurant",
            "type":"Food & Drink"
        }
    ],
    "sg:phone":"+1 716 826 5062",
    "sg:postcode":"14220",
    "sg:province":"NY",
    "sg:tags":[
        "deli",
        "delicatessen"
    ],
    "wof:name":"Rachel's Deli",
    "wof:placetype":"venue"
},
  "geometry": {"coordinates":[-78.827499,42.855],"type":"Point"}
}