{
  "type": "Feature",
  "properties": {
    "iso:country":"US",
    "sg:address":"392 Oliver Pl",
    "sg:city":"Bronx",
    "sg:classifiers":[
        {
            "category":"Real Estate",
            "subcategory":"Real Estate Agent",
            "type":"Services"
        }
    ],
    "sg:phone":"+1 718 562 9836",
    "sg:postcode":"10458",
    "sg:province":"NY",
    "wof:name":"Langsam Property Svc Corp",
    "wof:placetype":"venue"
},
  "geometry": {"coordinates":[-73.88550499999999,40.866812],"type":"Point"}
}