{
  "type": "Feature",
  "properties": {
    "addr:full":"122 W 26th St New York NY 10001",
    "addr:housenumber":"122",
    "addr:postcode":"10001",
    "addr:street":"W 26Th St",
    "iso:country":"US",
    "sg:address":"122 W 26th St",
    "sg:city":"New York",
    "sg:classifiers":[
        {
            "category":"Shopping",
            "subcategory":"Clothing, Apparel, & Fashions",
            "type":"Retail Goods"
        }
    ],
    "sg:phone":"+1 212 243 9362",
    "sg:postcode":"10001",
    "sg:province":"NY",
    "sg:tags":[
        "sportswear"
    ],
    "wof:name":"C & T Sportswear Inc",
    "wof:placetype":"venue"
},
  "geometry": {"coordinates":[-73.993814,40.745669],"type":"Point"}
}