{
  "type": "Feature",
  "properties": {
    "iso:country":"US",
    "sg:address":"164 Prospect Ave",
    "sg:city":"Plattsburgh",
    "sg:classifiers":[
        {
            "category":"Organizations",
            "subcategory":"Religious Organization",
            "type":"Services"
        }
    ],
    "sg:phone":"+1 518 563 5799",
    "sg:postcode":"12901",
    "sg:province":"NY",
    "sg:tags":[
        "church"
    ],
    "wof:name":"First Assembly Of God Church",
    "wof:placetype":"venue"
},
  "geometry": {"coordinates":[-73.473118,44.697871],"type":"Point"}
}