{
  "type": "Feature",
  "properties": {
    "iso:country":"US",
    "sg:address":"350 5th Ave 59th Fl.",
    "sg:city":"New York",
    "sg:classifiers":[
        {
            "category":"Professional",
            "subcategory":"Lawyer & Legal Services",
            "type":"Services"
        }
    ],
    "sg:phone":"+1 212 868 0929",
    "sg:postcode":"10118",
    "sg:province":"NY",
    "wof:name":"Caryn S Gartenberg",
    "wof:placetype":"venue"
},
  "geometry": {"coordinates":[-73.984959,40.74807],"type":"Point"}
}