{
  "type": "Feature",
  "properties": {
    "iso:country":"US",
    "sg:address":"3800 W Genesee St",
    "sg:city":"Syracuse",
    "sg:classifiers":[
        {
            "category":"Restaurant",
            "type":"Food & Drink"
        }
    ],
    "sg:phone":"+1 315 468 5535",
    "sg:postcode":"13219",
    "sg:province":"NY",
    "sg:tags":[
        "parlor",
        "ice",
        "cream"
    ],
    "wof:name":"Marnie's Ice Cream",
    "wof:placetype":"venue"
},
  "geometry": {"coordinates":[-76.24051799999999,43.046579],"type":"Point"}
}