{
  "type": "Feature",
  "properties": {
    "addr:full":"504 Sherrill Rd Sherrill NY 13461",
    "addr:housenumber":"504",
    "addr:postcode":"13461",
    "addr:street":"Sherrill Rd",
    "iso:country":"US",
    "sg:address":"504 Sherrill Rd",
    "sg:city":"Sherrill",
    "sg:classifiers":[
        {
            "category":"Retail",
            "subcategory":"Laundry & Dry Cleaning",
            "type":"Services"
        }
    ],
    "sg:phone":"+1   ",
    "sg:postcode":"13461",
    "sg:province":"NY",
    "sg:tags":[
        "garment",
        "plant",
        "agent",
        "drycleaning"
    ],
    "wof:name":"Sherrill Dry Cleaners",
    "wof:placetype":"venue"
},
  "geometry": {"coordinates":[-75.60077699999999,43.06983],"type":"Point"}
}