{
  "type": "Feature",
  "properties": {
    "addr:full":"2317 29th Street Astoria NY 11105",
    "addr:housenumber":"2317",
    "addr:postcode":"11105",
    "addr:street":"29Th Street",
    "iso:country":"US",
    "sg:address":"2317 29th Street",
    "sg:city":"Astoria",
    "sg:classifiers":[
        {
            "category":"Building & Trades",
            "subcategory":"Locksmith",
            "type":"Services"
        }
    ],
    "sg:phone":"+1 718 683 3689",
    "sg:postcode":"11105",
    "sg:province":"NY",
    "sg:tags":[
        "key"
    ],
    "wof:name":"AAA Locksmith and Towing 24 Hrs",
    "wof:placetype":"venue"
},
  "geometry": {"coordinates":[-73.914428,40.774555],"type":"Point"}
}