{
  "type": "Feature",
  "properties": {
    "iso:country":"US",
    "sg:address":"26 Stonehurst Cir",
    "sg:city":"Centereach",
    "sg:classifiers":[
        {
            "category":"Freight",
            "type":"Transportation"
        }
    ],
    "sg:phone":"+1   ",
    "sg:postcode":"11720",
    "sg:province":"NY",
    "sg:tags":[
        "operator",
        "local",
        "trucking"
    ],
    "wof:name":"Malave Trucking Corp",
    "wof:placetype":"venue"
},
  "geometry": {"coordinates":[-73.07270800000001,40.879678],"type":"Point"}
}