{
  "type": "Feature",
  "properties": {
    "iso:country":"US",
    "sg:address":"662 Middle Country Rd",
    "sg:city":"Selden",
    "sg:classifiers":[
        {
            "category":"Fast Food",
            "type":"Food & Drink"
        }
    ],
    "sg:phone":"+1 631 732 1080",
    "sg:postcode":"11784",
    "sg:province":"NY",
    "sg:tags":[
        "chicken",
        "wing"
    ],
    "wof:name":"Pudgie's Famous Chicken",
    "wof:placetype":"venue"
},
  "geometry": {"coordinates":[-73.039101,40.8661],"type":"Point"}
}