{
  "type": "Feature",
  "properties": {
    "addr:full":"376 Audubon Ave New York NY 10033",
    "addr:housenumber":"376",
    "addr:postcode":"10033",
    "addr:street":"Audubon Ave",
    "iso:country":"US",
    "sg:address":"376 Audubon Ave",
    "sg:city":"New York",
    "sg:classifiers":[
        {
            "category":"Taxi",
            "type":"Transportation"
        }
    ],
    "sg:phone":"+1   ",
    "sg:postcode":"10033",
    "sg:province":"NY",
    "sg:tags":[
        "cab"
    ],
    "wof:name":"Professional Car Service Inc",
    "wof:placetype":"venue"
},
  "geometry": {"coordinates":[-73.93140099999999,40.850015],"type":"Point"}
}