{
  "type": "Feature",
  "properties": {
    "iso:country":"US",
    "sg:address":"505 8 Ave",
    "sg:city":"New York",
    "sg:classifiers":[
        {
            "category":"Building & Trades",
            "subcategory":"Construction",
            "type":"Services"
        }
    ],
    "sg:phone":"+1 212 290 8517",
    "sg:postcode":"10018",
    "sg:province":"NY",
    "sg:tags":[
        "restoration",
        "contractor"
    ],
    "wof:name":"Restoration Specialty Services",
    "wof:placetype":"venue"
},
  "geometry": {"coordinates":[-73.99252799999999,40.753474],"type":"Point"}
}