{
  "type": "Feature",
  "properties": {
    "addr:full":"162 Oakside Dr Smithtown NY 11787",
    "addr:housenumber":"162",
    "addr:postcode":"11787",
    "addr:street":"Oakside Dr",
    "iso:country":"US",
    "sg:address":"162 Oakside Dr",
    "sg:city":"Smithtown",
    "sg:classifiers":[
        {
            "category":"Shopping",
            "type":"Retail Goods"
        }
    ],
    "sg:phone":"+1   ",
    "sg:postcode":"11787",
    "sg:province":"NY",
    "sg:tags":[
        "merchandise"
    ],
    "wof:name":"Visual Presentations Co",
    "wof:placetype":"venue"
},
  "geometry": {"coordinates":[-73.20196300000001,40.883659],"type":"Point"}
}