{
  "type": "Feature",
  "properties": {
    "iso:country":"US",
    "sg:address":"19 Sean Ln",
    "sg:city":"Rochester",
    "sg:classifiers":[
        {
            "category":"Building & Trades",
            "subcategory":"Landscaping Services",
            "type":"Services"
        }
    ],
    "sg:phone":"+1 585 429 4660",
    "sg:postcode":"14606",
    "sg:province":"NY",
    "sg:tags":[
        "landscape",
        "contractor"
    ],
    "wof:name":"FJL Landscaping",
    "wof:placetype":"venue"
},
  "geometry": {"coordinates":[-77.740421,43.178275],"type":"Point"}
}