{
  "type": "Feature",
  "properties": {
    "addr:full":"56 Water St Lyons NY 14489",
    "addr:housenumber":"56",
    "addr:postcode":"14489",
    "addr:street":"Water St",
    "iso:country":"US",
    "sg:address":"56 Water St",
    "sg:city":"Lyons",
    "sg:classifiers":[
        {
            "category":"Fast Food",
            "type":"Food & Drink"
        },
        {
            "category":"Restaurant",
            "type":"Food & Drink"
        }
    ],
    "sg:phone":"+1 315 946 0027",
    "sg:postcode":"14489",
    "sg:province":"NY",
    "sg:tags":[
        "hamburger",
        "hot",
        "dog",
        "american",
        "take",
        "chicken"
    ],
    "sg:website":"http://www.mcdonalds.com",
    "wof:name":"McDonald's",
    "wof:placetype":"venue"
},
  "geometry": {"coordinates":[-76.994562,43.062588],"type":"Point"}
}