{
  "type": "Feature",
  "properties": {
    "iso:country":"US",
    "sg:address":"33 Belmont Dr",
    "sg:city":"Shirley",
    "sg:classifiers":[
        {
            "category":"Professional",
            "subcategory":"Business Services",
            "type":"Services"
        }
    ],
    "sg:phone":"+1 631 949 1104",
    "sg:postcode":"11967",
    "sg:province":"NY",
    "wof:name":"Rnt & M Interiors Inc",
    "wof:placetype":"venue"
},
  "geometry": {"coordinates":[-72.88933900000001,40.829364],"type":"Point"}
}