{
  "type": "Feature",
  "properties": {
    "addr:full":"14704 Foch Blvd Jamaica NY 11436",
    "addr:housenumber":"14704",
    "addr:postcode":"11436",
    "addr:street":"Foch Blvd",
    "iso:country":"US",
    "sg:address":"14704 Foch Blvd",
    "sg:city":"Jamaica",
    "sg:classifiers":[
        {
            "category":"Juice Bar",
            "subcategory":"None",
            "type":"Food & Drink"
        }
    ],
    "sg:phone":"+1 718 659 7655",
    "sg:postcode":"11436",
    "sg:province":"NY",
    "sg:tags":[
        "smoothy"
    ],
    "wof:name":"Juicy Food Inc",
    "wof:placetype":"venue"
},
  "geometry": {"coordinates":[-73.793503,40.680099],"type":"Point"}
}