{
  "type": "Feature",
  "properties": {
    "iso:country":"US",
    "sg:address":"160 E Main St",
    "sg:city":"Bay Shore",
    "sg:classifiers":[
        {
            "category":"Banks & Credit Unions",
            "subcategory":"Bank",
            "type":"Services"
        }
    ],
    "sg:phone":"+1 631 666 9300",
    "sg:postcode":"11706",
    "sg:province":"NY",
    "sg:tags":[
        "mortgage",
        "loan",
        "broker",
        "real estate"
    ],
    "sg:website":"www.blarneystonefunding.com",
    "wof:name":"Blarney Stone Funding Inc",
    "wof:placetype":"venue"
},
  "geometry": {"coordinates":[-73.243925,40.723884],"type":"Point"}
}