{
  "type": "Feature",
  "properties": {
    "addr:full":"957 Pennsylvania Ave Brooklyn NY 11207",
    "addr:housenumber":"957",
    "addr:postcode":"11207",
    "addr:street":"Pennsylvania Ave",
    "iso:country":"US",
    "sg:address":"957 Pennsylvania Ave",
    "sg:city":"Brooklyn",
    "sg:classifiers":[
        {
            "category":"Professional",
            "subcategory":"Accounting & Tax Preparation",
            "type":"Services"
        }
    ],
    "sg:phone":"+1 718 629 3329",
    "sg:postcode":"11207",
    "sg:province":"NY",
    "sg:tags":[
        "return",
        "filing"
    ],
    "wof:name":"SSH Associates Income Tax S",
    "wof:placetype":"venue"
},
  "geometry": {"coordinates":[-73.88737500000001,40.654406],"type":"Point"}
}