{
  "type": "Feature",
  "properties": {
    "addr:full":"1804 63 New York NY 10001",
    "addr:housenumber":"1804 63",
    "addr:postcode":"10001",
    "iso:country":"US",
    "sg:address":"1804 63",
    "sg:city":"New York",
    "sg:classifiers":[
        {
            "category":"Wholesale",
            "subcategory":"Computers",
            "type":"Manufacturing & Wholesale Goods"
        }
    ],
    "sg:phone":"+1 718 872 7525",
    "sg:postcode":"10001",
    "sg:province":"NY",
    "wof:name":"A1 Computer Ctr",
    "wof:placetype":"venue"
},
  "geometry": {"coordinates":[-74.008737,40.705636],"type":"Point"}
}