{
  "type": "Feature",
  "properties": {
    "iso:country":"US",
    "sg:address":"3527 Watkins Rd",
    "sg:city":"Horseheads",
    "sg:classifiers":[
        {
            "category":"Travel",
            "subcategory":"Hotels & Motels",
            "type":"Entertainment"
        }
    ],
    "sg:phone":"+1 607 739 3891",
    "sg:postcode":"14845",
    "sg:province":"NY",
    "wof:name":"Marshall Manor Motel Inc",
    "wof:placetype":"venue"
},
  "geometry": {"coordinates":[-76.847528,42.216181],"type":"Point"}
}