{
  "type": "Feature",
  "properties": {
    "iso:country":"US",
    "sg:address":"39 Stanton Cir",
    "sg:city":"New Rochelle",
    "sg:classifiers":[
        {
            "category":"Wholesale",
            "subcategory":"Apparel",
            "type":"Manufacturing & Wholesale Goods"
        }
    ],
    "sg:phone":"+1 914 235 4797",
    "sg:postcode":"10804",
    "sg:province":"NY",
    "sg:tags":[
        "outerwear"
    ],
    "wof:name":"Rainskins",
    "wof:placetype":"venue"
},
  "geometry": {"coordinates":[-73.786052,40.968723],"type":"Point"}
}