{
  "type": "Feature",
  "properties": {
    "iso:country":"US",
    "sg:address":"2343 Kensington Ave",
    "sg:city":"Snyder",
    "sg:classifiers":[
        {
            "category":"Health Services",
            "subcategory":"Optometrist",
            "type":"Services"
        }
    ],
    "sg:phone":"+1 716 839 9810",
    "sg:postcode":"14226",
    "sg:province":"NY",
    "wof:name":"Leonard H Burros OD",
    "wof:placetype":"venue"
},
  "geometry": {"coordinates":[-78.77297,42.955034],"type":"Point"}
}