{
  "type": "Feature",
  "properties": {
    "iso:country":"US",
    "sg:address":"40 W Sunrise Hwy",
    "sg:city":"Freeport",
    "sg:classifiers":[
        {
            "category":"Wholesale",
            "subcategory":"Machinery & Supplies",
            "type":"Manufacturing & Wholesale Goods"
        }
    ],
    "sg:phone":"+1 516 868 5033",
    "sg:postcode":"11520",
    "sg:province":"NY",
    "sg:tags":[
        "salon",
        "beauty"
    ],
    "wof:name":"Tri State Beauty",
    "wof:placetype":"venue"
},
  "geometry": {"coordinates":[-73.59236900000001,40.656059],"type":"Point"}
}