{
  "type": "Feature",
  "properties": {
    "addr:full":"247 E 50th St New York NY 10022",
    "addr:housenumber":"247",
    "addr:postcode":"10022",
    "addr:street":"E 50Th St",
    "iso:country":"US",
    "sg:address":"247 E 50th St",
    "sg:city":"New York",
    "sg:classifiers":[
        {
            "category":"Building & Trades",
            "subcategory":"Locksmith",
            "type":"Services"
        }
    ],
    "sg:phone":"+1 212 421 5599",
    "sg:postcode":"10022",
    "sg:province":"NY",
    "sg:tags":[
        "key"
    ],
    "wof:name":"American Window & Door Inc",
    "wof:placetype":"venue"
},
  "geometry": {"coordinates":[-73.96970399999999,40.755402],"type":"Point"}
}