{
  "type": "Feature",
  "properties": {
    "addr:full":"1790 Main St Keeseville NY 12944",
    "addr:housenumber":"1790",
    "addr:postcode":"12944",
    "addr:street":"Main St",
    "iso:country":"US",
    "sg:address":"1790 Main St",
    "sg:city":"Keeseville",
    "sg:classifiers":[
        {
            "category":"Government",
            "subcategory":"Office",
            "type":"Public Place"
        }
    ],
    "sg:phone":"+1 518 834 9059",
    "sg:postcode":"12944",
    "sg:province":"NY",
    "sg:tags":[
        "village"
    ],
    "wof:name":"Village Of Keeseville Office",
    "wof:placetype":"venue"
},
  "geometry": {"coordinates":[-73.484961,44.506272],"type":"Point"}
}