{
  "type": "Feature",
  "properties": {
    "iso:country":"US",
    "sg:address":"223 Rkwy Tpke",
    "sg:city":"Lawrence",
    "sg:classifiers":[
        {
            "category":"Autos & Motor Vehicles",
            "subcategory":"Fuel & Gas Station",
            "type":"Retail Goods"
        }
    ],
    "sg:phone":"+1 516 239 9409",
    "sg:postcode":"11559",
    "sg:province":"NY",
    "wof:name":"Gritsers Svce Sta",
    "wof:placetype":"venue"
},
  "geometry": {"coordinates":[-73.45616699999999,40.859689],"type":"Point"}
}