{
  "type": "Feature",
  "properties": {
    "addr:full":"53 Rawlinson Rd Rochester NY 14617",
    "addr:housenumber":"53",
    "addr:postcode":"14617",
    "addr:street":"Rawlinson Rd",
    "iso:country":"US",
    "sg:address":"53 Rawlinson Rd",
    "sg:city":"Rochester",
    "sg:classifiers":[
        {
            "category":"Building & Trades",
            "subcategory":"Construction",
            "type":"Services"
        }
    ],
    "sg:phone":"+1 585 544 3353",
    "sg:postcode":"14617",
    "sg:province":"NY",
    "sg:tags":[
        "floor",
        "laying",
        "contractor"
    ],
    "wof:name":"Chinelli Hardwood Flooring",
    "wof:placetype":"venue"
},
  "geometry": {"coordinates":[-77.61684700000001,43.201847],"type":"Point"}
}