{
  "type": "Feature",
  "properties": {
    "iso:country":"US",
    "sg:address":"2602 E 7th St",
    "sg:city":"Brooklyn",
    "sg:classifiers":[
        {
            "category":"Health Services",
            "subcategory":"Doctor",
            "type":"Services"
        }
    ],
    "sg:phone":"+1 718 891 1515",
    "sg:postcode":"11235",
    "sg:province":"NY",
    "sg:tags":[
        "medical"
    ],
    "wof:name":"David G Yep",
    "wof:placetype":"venue"
},
  "geometry": {"coordinates":[-73.961974,40.586359],"type":"Point"}
}