{
  "type": "Feature",
  "properties": {
    "addr:full":"175 Marble Ave Pleasantville NY 10570",
    "addr:housenumber":"175",
    "addr:postcode":"10570",
    "addr:street":"Marble Ave",
    "iso:country":"US",
    "sg:address":"175 Marble Ave",
    "sg:city":"Pleasantville",
    "sg:classifiers":[
        {
            "category":"Building & Trades",
            "subcategory":"Construction",
            "type":"Services"
        }
    ],
    "sg:phone":"+1 914 741 5459",
    "sg:postcode":"10570",
    "sg:province":"NY",
    "sg:tags":[
        "public",
        "contractor",
        "commercial",
        "works",
        "general"
    ],
    "wof:name":"Arben Corp",
    "wof:placetype":"venue"
},
  "geometry": {"coordinates":[-73.78838399999999,41.128378],"type":"Point"}
}