{
  "type": "Feature",
  "properties": {
    "iso:country":"US",
    "sg:address":"6628 Denton Corners Rd",
    "sg:city":"Castile",
    "sg:classifiers":[
        {
            "category":"Travel",
            "subcategory":"Hotels & Motels",
            "type":"Entertainment"
        }
    ],
    "sg:phone":"+1 585 493 2940",
    "sg:postcode":"14427",
    "sg:province":"NY",
    "sg:tags":[
        "breakfast",
        "accommodation",
        "bed"
    ],
    "wof:name":"Meadowood Acres",
    "wof:placetype":"venue"
},
  "geometry": {"coordinates":[-78.04702399999999,42.600007],"type":"Point"}
}