{
  "type": "Feature",
  "properties": {
    "addr:full":"213 State St Binghamton NY 13901",
    "addr:housenumber":"213",
    "addr:postcode":"13901",
    "addr:street":"State St",
    "iso:country":"US",
    "sg:address":"213 State St",
    "sg:city":"Binghamton",
    "sg:classifiers":[
        {
            "category":"Social Services",
            "type":"Services"
        }
    ],
    "sg:phone":"+1 607 724 3462",
    "sg:postcode":"13901",
    "sg:province":"NY",
    "sg:tags":[
        "organization",
        "welfare"
    ],
    "wof:name":"Cooperative Gallery",
    "wof:placetype":"venue"
},
  "geometry": {"coordinates":[-75.911411,42.102218],"type":"Point"}
}