{
  "type": "Feature",
  "properties": {
    "iso:country":"US",
    "sg:address":"962 Luther Rd",
    "sg:city":"East Greenbush",
    "sg:classifiers":[
        {
            "category":"Education",
            "subcategory":"School",
            "type":"Public Place"
        }
    ],
    "sg:phone":"+1 518 477 2496",
    "sg:postcode":"12061",
    "sg:province":"NY",
    "wof:name":"East Greenbush Central School",
    "wof:placetype":"venue"
},
  "geometry": {"coordinates":[-73.69024,42.62079],"type":"Point"}
}