{
  "type": "Feature",
  "properties": {
    "iso:country":"US",
    "sg:address":"11 Broadway Ste 1500",
    "sg:city":"New York",
    "sg:classifiers":[
        {
            "category":"Real Estate",
            "subcategory":"Architect",
            "type":"Services"
        }
    ],
    "sg:phone":"+1 212 732 7012",
    "sg:postcode":"10004",
    "sg:province":"NY",
    "wof:name":"Span",
    "wof:placetype":"venue"
},
  "geometry": {"coordinates":[-74.01424299999999,40.705271],"type":"Point"}
}