{
  "type": "Feature",
  "properties": {
    "iso:country":"US",
    "sg:address":"42 Mark Dr",
    "sg:city":"Holbrook",
    "sg:classifiers":[
        {
            "category":"Building & Trades",
            "subcategory":"Plumbing",
            "type":"Services"
        }
    ],
    "sg:phone":"+1 631 981 3426",
    "sg:postcode":"11741",
    "sg:province":"NY",
    "sg:tags":[
        "plumbing",
        "heating",
        "contractor"
    ],
    "wof:name":"Angelo Plumbing & Heating",
    "wof:placetype":"venue"
},
  "geometry": {"coordinates":[-73.07714300000001,40.774742],"type":"Point"}
}