{
  "type": "Feature",
  "properties": {
    "addr:full":"197 Corporate Dr Binghamton NY 13904",
    "addr:housenumber":"197",
    "addr:postcode":"13904",
    "addr:street":"Corporate Dr",
    "iso:country":"US",
    "sg:address":"197 Corporate Dr",
    "sg:city":"Binghamton",
    "sg:classifiers":[
        {
            "category":"Manufacturing",
            "subcategory":"Retail Goods",
            "type":"Manufacturing & Wholesale Goods"
        }
    ],
    "sg:phone":"+1 607 772 2439",
    "sg:postcode":"13904",
    "sg:province":"NY",
    "sg:tags":[
        "manufacturer"
    ],
    "wof:name":"A-Line Technology",
    "wof:placetype":"venue"
},
  "geometry": {"coordinates":[-75.81683700000001,42.104348],"type":"Point"}
}