{
  "type": "Feature",
  "properties": {
    "addr:full":"35 Matthews St Goshen NY 10924",
    "addr:housenumber":"35",
    "addr:postcode":"10924",
    "addr:street":"Matthews St",
    "iso:country":"US",
    "sg:address":"35 Matthews St",
    "sg:city":"Goshen",
    "sg:classifiers":[
        {
            "category":"Banks & Credit Unions",
            "subcategory":"Bank",
            "type":"Services"
        }
    ],
    "sg:phone":"+1 845 294 5194",
    "sg:postcode":"10924",
    "sg:province":"NY",
    "wof:name":"Bank of the Hudson",
    "wof:placetype":"venue"
},
  "geometry": {"coordinates":[-74.333702,41.396],"type":"Point"}
}