{
  "type": "Feature",
  "properties": {
    "addr:full":"9605 Clarence Center Rd Clarence Center NY 14032",
    "addr:housenumber":"9605",
    "addr:postcode":"14032",
    "addr:street":"Clarence Center Rd",
    "iso:country":"US",
    "sg:address":"9605 Clarence Center Rd",
    "sg:city":"Clarence Center",
    "sg:classifiers":[
        {
            "category":"Manufacturing",
            "subcategory":"Building Materials",
            "type":"Manufacturing & Wholesale Goods"
        }
    ],
    "sg:phone":"+1 716 741 8201",
    "sg:postcode":"14032",
    "sg:province":"NY",
    "wof:name":"Clarance Center Millwork",
    "wof:placetype":"venue"
},
  "geometry": {"coordinates":[-78.62961799999999,43.010324],"type":"Point"}
}