{
  "type": "Feature",
  "properties": {
    "addr:full":"2241 Hylan Blvd Staten Island NY 10306",
    "addr:housenumber":"2241",
    "addr:postcode":"10306",
    "addr:street":"Hylan Blvd",
    "iso:country":"US",
    "sg:address":"2241 Hylan Blvd",
    "sg:city":"Staten Island",
    "sg:classifiers":[
        {
            "category":"Home & Garden",
            "subcategory":"Carpets & Floor Coverings",
            "type":"Retail Goods"
        }
    ],
    "sg:phone":"+1 718 667 6889",
    "sg:postcode":"10306",
    "sg:province":"NY",
    "sg:tags":[
        "flooring"
    ],
    "wof:name":"Hylan Floor Covering Inc",
    "wof:placetype":"venue"
},
  "geometry": {"coordinates":[-74.104139,40.576307],"type":"Point"}
}