{
  "type": "Feature",
  "properties": {
    "addr:full":"1007 Lexington Ave New York NY 10021",
    "addr:housenumber":"1007",
    "addr:postcode":"10021",
    "addr:street":"Lexington Ave",
    "iso:country":"US",
    "sg:address":"1007 Lexington Ave",
    "sg:city":"New York",
    "sg:classifiers":[
        {
            "category":"Restaurant",
            "type":"Food & Drink"
        }
    ],
    "sg:phone":"+1 212 861 5350",
    "sg:postcode":"10021",
    "sg:province":"NY",
    "wof:name":"Swifty's Catering & Events",
    "wof:placetype":"venue"
},
  "geometry": {"coordinates":[-73.961696,40.770709],"type":"Point"}
}