{
  "type": "Feature",
  "properties": {
    "addr:full":"203 Kimberly Dr E Syracuse NY 13219",
    "addr:housenumber":"203",
    "addr:postcode":"13219",
    "addr:street":"Kimberly Dr E",
    "iso:country":"US",
    "sg:address":"203 Kimberly Dr E",
    "sg:city":"Syracuse",
    "sg:classifiers":[
        {
            "category":"Real Estate",
            "subcategory":"Real Estate Agent",
            "type":"Services"
        }
    ],
    "sg:phone":"+1 315 488 8413",
    "sg:postcode":"13219",
    "sg:province":"NY",
    "wof:name":"Retzos Realty Corporation",
    "wof:placetype":"venue"
},
  "geometry": {"coordinates":[-76.23131600000001,43.045326],"type":"Point"}
}