{
  "type": "Feature",
  "properties": {
    "addr:full":"44 White St New York NY 10013",
    "addr:housenumber":"44",
    "addr:postcode":"10013",
    "addr:street":"White St",
    "iso:country":"US",
    "sg:address":"44 White St",
    "sg:city":"New York",
    "sg:classifiers":[
        {
            "category":"Building & Trades",
            "subcategory":"Construction",
            "type":"Services"
        },
        {
            "category":"Home & Garden",
            "subcategory":"Furniture",
            "type":"Retail Goods"
        }
    ],
    "sg:phone":"+1 212 691 7814",
    "sg:postcode":"10013",
    "sg:province":"NY",
    "sg:tags":[
        "interior",
        "design",
        "store"
    ],
    "wof:name":"Sclaroff Steven",
    "wof:placetype":"venue"
},
  "geometry": {"coordinates":[-74.004159,40.718776],"type":"Point"}
}