{
  "type": "Feature",
  "properties": {
    "iso:country":"US",
    "sg:address":"9305 Cabic Rd",
    "sg:city":"Dayton",
    "sg:classifiers":[
        {
            "category":"Shopping",
            "subcategory":"Stationery & Office Supplies",
            "type":"Retail Goods"
        }
    ],
    "sg:phone":"+1   ",
    "sg:postcode":"14041",
    "sg:province":"NY",
    "wof:name":"SOS",
    "wof:placetype":"venue"
},
  "geometry": {"coordinates":[-78.972809,42.394008],"type":"Point"}
}