{
  "type": "Feature",
  "properties": {
    "addr:full":"15009 Bayside Ave Flushing NY 11354",
    "addr:postcode":"15009;11354",
    "addr:street":"Bayside Ave",
    "iso:country":"US",
    "sg:address":"15009 Bayside Ave",
    "sg:city":"Flushing",
    "sg:classifiers":[
        {
            "category":"Deli",
            "type":"Food & Drink"
        }
    ],
    "sg:phone":"+1 718 353 3955",
    "sg:postcode":"11354",
    "sg:province":"NY",
    "wof:name":"Browne Park Deli",
    "wof:placetype":"venue"
},
  "geometry": {"coordinates":[-73.81559799999999,40.771599],"type":"Point"}
}