{
  "type": "Feature",
  "properties": {
    "addr:full":"75 Mineola Ave Roslyn Heights NY 11577",
    "addr:housenumber":"75",
    "addr:postcode":"11577",
    "addr:street":"Mineola Ave",
    "iso:country":"US",
    "sg:address":"75 Mineola Ave",
    "sg:city":"Roslyn Heights",
    "sg:classifiers":[
        {
            "category":"Retail",
            "subcategory":"Funeral Services",
            "type":"Services"
        }
    ],
    "sg:phone":"+1 516 621 4545",
    "sg:postcode":"11577",
    "sg:province":"NY",
    "sg:tags":[
        "cemetery"
    ],
    "wof:name":"Tuckolski John P Funrl Director",
    "wof:placetype":"venue"
},
  "geometry": {"coordinates":[-73.652,40.7896],"type":"Point"}
}