{
  "type": "Feature",
  "properties": {
    "addr:full":"2115 Cortelyou Rd Brooklyn NY 11226",
    "addr:housenumber":"2115",
    "addr:postcode":"11226",
    "addr:street":"Cortelyou Rd",
    "iso:country":"US",
    "sg:address":"2115 Cortelyou Rd",
    "sg:city":"Brooklyn",
    "sg:classifiers":[
        {
            "category":"Utilities",
            "subcategory":"Telephone",
            "type":"Services"
        }
    ],
    "sg:phone":"+1   ",
    "sg:postcode":"11226",
    "sg:province":"NY",
    "sg:tags":[
        "communications"
    ],
    "wof:name":"The True Choice Comm Ctr",
    "wof:placetype":"venue"
},
  "geometry": {"coordinates":[-73.958359,40.643972],"type":"Point"}
}