{
  "type": "Feature",
  "properties": {
    "iso:country":"US",
    "sg:address":"2349 E 71st St",
    "sg:city":"Brooklyn",
    "sg:classifiers":[
        {
            "category":"Building & Trades",
            "subcategory":"Construction",
            "type":"Services"
        }
    ],
    "sg:phone":"+1 347 242 9241",
    "sg:postcode":"11234",
    "sg:province":"NY",
    "sg:tags":[
        "new",
        "remodeling",
        "contractor"
    ],
    "wof:name":"Casabella Construction Corp",
    "wof:placetype":"venue"
},
  "geometry": {"coordinates":[-73.902612,40.615786],"type":"Point"}
}