{
  "type": "Feature",
  "properties": {
    "iso:country":"US",
    "sg:address":"207 E 34th St",
    "sg:city":"New York",
    "sg:classifiers":[
        {
            "category":"Restaurant",
            "type":"Food & Drink"
        }
    ],
    "sg:phone":"+1 212 889 3239",
    "sg:postcode":"10016",
    "sg:province":"NY",
    "sg:tags":[
        "italian"
    ],
    "wof:name":"Nicola Paone",
    "wof:placetype":"venue"
},
  "geometry": {"coordinates":[-73.97779800000001,40.745701],"type":"Point"}
}