{
  "type": "Feature",
  "properties": {
    "iso:country":"US",
    "sg:address":"88 College Ave",
    "sg:city":"Malone",
    "sg:classifiers":[
        {
            "category":"Wholesale",
            "subcategory":"Beer",
            "type":"Manufacturing & Wholesale Goods"
        }
    ],
    "sg:phone":"+1 518 483 5541",
    "sg:postcode":"12953",
    "sg:province":"NY",
    "sg:tags":[
        "ale",
        "merchandise-wholesale"
    ],
    "wof:name":"Marlow Distributing Inc",
    "wof:placetype":"venue"
},
  "geometry": {"coordinates":[-74.28962199999999,44.844553],"type":"Point"}
}