{
  "type": "Feature",
  "properties": {
    "addr:full":"10 Dorothy St Bethpage NY 11714",
    "addr:housenumber":"10",
    "addr:postcode":"11714",
    "addr:street":"Dorothy St",
    "iso:country":"US",
    "sg:address":"10 Dorothy St",
    "sg:city":"Bethpage",
    "sg:classifiers":[
        {
            "category":"Food & Beverages",
            "subcategory":"Liquor & Beverages",
            "type":"Retail Goods"
        }
    ],
    "sg:phone":"+1   ",
    "sg:postcode":"11714",
    "sg:province":"NY",
    "sg:tags":[
        "alcoholic"
    ],
    "wof:name":"SNG Corpdba Bethpage Wine",
    "wof:placetype":"venue"
},
  "geometry": {"coordinates":[-73.477135,40.745586],"type":"Point"}
}