{
  "type": "Feature",
  "properties": {
    "addr:full":"30 Aqueduct St Ossining NY 10562",
    "addr:housenumber":"30",
    "addr:postcode":"10562",
    "addr:street":"Aqueduct St",
    "iso:country":"US",
    "sg:address":"30 Aqueduct St",
    "sg:city":"Ossining",
    "sg:classifiers":[
        {
            "category":"Retail",
            "subcategory":"Auto Repair",
            "type":"Services"
        }
    ],
    "sg:phone":"+1 914 945 0731",
    "sg:postcode":"10562",
    "sg:province":"NY",
    "sg:tags":[
        "automobile",
        "customizing"
    ],
    "wof:name":"Custom Carmotology Corp",
    "wof:placetype":"venue"
},
  "geometry": {"coordinates":[-73.86217499999999,41.164684],"type":"Point"}
}