{
  "type": "Feature",
  "properties": {
    "iso:country":"US",
    "sg:address":"249 Perrys Corners Rd",
    "sg:city":"Amenia",
    "sg:classifiers":[
        {
            "category":"Building & Trades",
            "subcategory":"Construction",
            "type":"Services"
        }
    ],
    "sg:phone":"+1 845 373 9121",
    "sg:postcode":"12501",
    "sg:province":"NY",
    "sg:tags":[
        "steel",
        "crane",
        "erection",
        "rental",
        "structural"
    ],
    "wof:name":"McBreairtys Inc",
    "wof:placetype":"venue"
},
  "geometry": {"coordinates":[-73.54964099999999,41.877457],"type":"Point"}
}