{
  "type": "Feature",
  "properties": {
    "addr:full":"641 Dutchess Tpke Poughkeepsie NY 12603",
    "addr:housenumber":"641",
    "addr:postcode":"12603",
    "addr:street":"Dutchess Tpke",
    "iso:country":"US",
    "sg:address":"641 Dutchess Tpke",
    "sg:city":"Poughkeepsie",
    "sg:classifiers":[
        {
            "category":"Real Estate",
            "subcategory":"Real Estate Operator",
            "type":"Services"
        }
    ],
    "sg:phone":"+1 845 454 9834",
    "sg:postcode":"12603",
    "sg:province":"NY",
    "sg:tags":[
        "apartment"
    ],
    "wof:name":"Hillside Terrace Apartments",
    "wof:placetype":"venue"
},
  "geometry": {"coordinates":[-73.843045,41.725013],"type":"Point"}
}