{
  "type": "Feature",
  "properties": {
    "addr:full":"1238 McDonald Ave Brooklyn NY 11230",
    "addr:housenumber":"1238",
    "addr:postcode":"11230",
    "addr:street":"Mcdonald Ave",
    "iso:country":"US",
    "sg:address":"1238 McDonald Ave",
    "sg:city":"Brooklyn",
    "sg:classifiers":[
        {
            "category":"Autos & Motor Vehicles",
            "subcategory":"Automobile Sales",
            "type":"Retail Goods"
        }
    ],
    "sg:phone":"+1   ",
    "sg:postcode":"11230",
    "sg:province":"NY",
    "wof:name":"Tower Auto Group Inc",
    "wof:placetype":"venue"
},
  "geometry": {"coordinates":[-73.97541699999999,40.621226],"type":"Point"}
}