{
  "type": "Feature",
  "properties": {
    "addr:full":"444 E 81st St New York NY 10028",
    "addr:housenumber":"444",
    "addr:postcode":"10028",
    "addr:street":"E 81St St",
    "iso:country":"US",
    "sg:address":"444 E 81st St",
    "sg:city":"New York",
    "sg:classifiers":[
        {
            "category":"Insurance",
            "subcategory":"Insurance Agent",
            "type":"Services"
        }
    ],
    "sg:phone":"+1 212 327 3007",
    "sg:postcode":"10028",
    "sg:province":"NY",
    "sg:tags":[
        "broker"
    ],
    "wof:name":"4-U Agency",
    "wof:placetype":"venue"
},
  "geometry": {"coordinates":[-73.95008300000001,40.77296],"type":"Point"}
}