{
  "type": "Feature",
  "properties": {
    "iso:country":"US",
    "sg:address":"215 Clyde Ave",
    "sg:city":"Jamestown",
    "sg:classifiers":[
        {
            "category":"Retail",
            "subcategory":"Animal Services",
            "type":"Services"
        }
    ],
    "sg:phone":"+1 716 661 9310",
    "sg:postcode":"14701",
    "sg:province":"NY",
    "sg:tags":[
        "pet",
        "grooming",
        "washing"
    ],
    "wof:name":"Classy Canines",
    "wof:placetype":"venue"
},
  "geometry": {"coordinates":[-79.223494,42.112898],"type":"Point"}
}