{
  "type": "Feature",
  "properties": {
    "addr:full":"561 Fashion Ave New York NY 10018",
    "addr:housenumber":"561",
    "addr:postcode":"10018",
    "addr:street":"Fashion Ave",
    "iso:country":"US",
    "sg:address":"561 Fashion Ave",
    "sg:city":"New York",
    "sg:classifiers":[
        {
            "category":"Manufacturing",
            "subcategory":"Electronics",
            "type":"Manufacturing & Wholesale Goods"
        }
    ],
    "sg:phone":"+1 212 730 7630",
    "sg:postcode":"10018",
    "sg:province":"NY",
    "sg:tags":[
        "modem",
        "set"
    ],
    "wof:name":"Joanna Mandl Inc Modem",
    "wof:placetype":"venue"
},
  "geometry": {"coordinates":[-73.987447,40.755373],"type":"Point"}
}