{
  "type": "Feature",
  "properties": {
    "iso:country":"US",
    "sg:address":"3663 White Plains Rd",
    "sg:city":"Bronx",
    "sg:classifiers":[
        {
            "category":"Organizations",
            "subcategory":"Religious Organization",
            "type":"Services"
        }
    ],
    "sg:phone":"+1   ",
    "sg:postcode":"10467",
    "sg:province":"NY",
    "wof:name":"Church of St John Nam",
    "wof:placetype":"venue"
},
  "geometry": {"coordinates":[-73.86515900000001,40.879495],"type":"Point"}
}