{
  "type": "Feature",
  "properties": {
    "iso:country":"US",
    "sg:address":"33 Flying Point Rd",
    "sg:city":"Southampton",
    "sg:classifiers":[
        {
            "category":"Arts & Performance",
            "subcategory":"Festival",
            "type":"Entertainment"
        }
    ],
    "sg:phone":"+1 631 287 0735",
    "sg:postcode":"11968",
    "sg:province":"NY",
    "sg:tags":[
        "carnival"
    ],
    "wof:name":"Festival Of Hamptons",
    "wof:placetype":"venue"
},
  "geometry": {"coordinates":[-72.37947800000001,40.90081],"type":"Point"}
}