{
  "type": "Feature",
  "properties": {
    "iso:country":"US",
    "sg:address":"17 Chanticleer Dr",
    "sg:city":"Islip",
    "sg:classifiers":[
        {
            "category":"Health Services",
            "subcategory":"Doctor",
            "type":"Services"
        }
    ],
    "sg:phone":"+1 631 968 3163",
    "sg:postcode":"11751",
    "sg:province":"NY",
    "sg:tags":[
        "physician",
        "surgeon"
    ],
    "wof:name":"Mitchell R Oldshein Md",
    "wof:placetype":"venue"
},
  "geometry": {"coordinates":[-73.22084,40.721611],"type":"Point"}
}