{
  "type": "Feature",
  "properties": {
    "addr:full":"107 Mona Dr Buffalo NY 14226",
    "addr:housenumber":"107",
    "addr:postcode":"14226",
    "addr:street":"Mona Dr",
    "iso:country":"US",
    "sg:address":"107 Mona Dr",
    "sg:city":"Buffalo",
    "sg:classifiers":[
        {
            "category":"Banks & Credit Unions",
            "subcategory":"Bank",
            "type":"Services"
        }
    ],
    "sg:phone":"+1 716 693 8350",
    "sg:postcode":"14226",
    "sg:province":"NY",
    "sg:tags":[
        "state",
        "commercial"
    ],
    "wof:name":"Hsbc Bank USA National Assn",
    "wof:placetype":"venue"
},
  "geometry": {"coordinates":[-78.80577099999999,42.949898],"type":"Point"}
}