{
  "type": "Feature",
  "properties": {
    "addr:full":"766 Royal Sunset Dr Webster NY 14580",
    "addr:housenumber":"766",
    "addr:postcode":"14580",
    "addr:street":"Royal Sunset Dr",
    "iso:country":"US",
    "sg:address":"766 Royal Sunset Dr",
    "sg:city":"Webster",
    "sg:classifiers":[
        {
            "category":"Retail",
            "subcategory":"Auto Repair",
            "type":"Services"
        }
    ],
    "sg:phone":"+1 585 354 4292",
    "sg:postcode":"14580",
    "sg:province":"NY",
    "wof:name":"Parkway Automotive And Transmission",
    "wof:placetype":"venue"
},
  "geometry": {"coordinates":[-77.475714,43.203033],"type":"Point"}
}