{
  "type": "Feature",
  "properties": {
    "iso:country":"US",
    "sg:address":"8150 Chimney Heights Blvd",
    "sg:city":"Wolcott",
    "sg:classifiers":[
        {
            "category":"Manufacturing",
            "subcategory":"Food",
            "type":"Manufacturing & Wholesale Goods"
        }
    ],
    "sg:phone":"+1 315 594 2502",
    "sg:postcode":"14590",
    "sg:province":"NY",
    "sg:tags":[
        "winery"
    ],
    "wof:name":"Thorpe Vineyard",
    "wof:placetype":"venue"
},
  "geometry": {"coordinates":[-76.897471,43.286881],"type":"Point"}
}