{
  "type": "Feature",
  "properties": {
    "addr:full":"40 Park Ave New York NY 10016",
    "addr:housenumber":"40",
    "addr:postcode":"10016",
    "addr:street":"Park Ave",
    "iso:country":"US",
    "sg:address":"40 Park Ave",
    "sg:city":"New York",
    "sg:classifiers":[
        {
            "category":"Health Services",
            "subcategory":"Doctor",
            "type":"Services"
        }
    ],
    "sg:phone":"+1 212 213 6790",
    "sg:postcode":"10016",
    "sg:province":"NY",
    "wof:name":"Yih Peggy Md",
    "wof:placetype":"venue"
},
  "geometry": {"coordinates":[-73.980653,40.748493],"type":"Point"}
}