{
  "type": "Feature",
  "properties": {
    "addr:full":"113 S Brandywine Ave Schenectady NY 12307",
    "addr:housenumber":"113",
    "addr:postcode":"12307",
    "addr:street":"S Brandywine Ave",
    "iso:country":"US",
    "sg:address":"113 S Brandywine Ave",
    "sg:city":"Schenectady",
    "sg:classifiers":[
        {
            "category":"Professional",
            "subcategory":"Art Services",
            "type":"Services"
        }
    ],
    "sg:phone":"+1 518 377 9457",
    "sg:postcode":"12307",
    "sg:province":"NY",
    "sg:tags":[
        "photographer"
    ],
    "wof:name":"Photographers & Co",
    "wof:placetype":"venue"
},
  "geometry": {"coordinates":[-73.92796,42.800585],"type":"Point"}
}