{
  "type": "Feature",
  "properties": {
    "iso:country":"US",
    "sg:address":"301 Manchester Rd",
    "sg:city":"Poughkeepsie",
    "sg:classifiers":[
        {
            "category":"Home & Garden",
            "subcategory":"Building Materials",
            "type":"Retail Goods"
        }
    ],
    "sg:phone":"+1 845 473 5246",
    "sg:postcode":"12603",
    "sg:province":"NY",
    "sg:tags":[
        "glass",
        "window",
        "plate"
    ],
    "wof:name":"Win Mobile Auto Glass",
    "wof:placetype":"venue"
},
  "geometry": {"coordinates":[-73.86307499999999,41.68364],"type":"Point"}
}