{
  "type": "Feature",
  "properties": {
    "addr:full":"64 Davison Ct Lockport NY 14094",
    "addr:housenumber":"64",
    "addr:postcode":"14094",
    "addr:street":"Davison Ct",
    "iso:country":"US",
    "sg:address":"64 Davison Ct",
    "sg:city":"Lockport",
    "sg:classifiers":[
        {
            "category":"Health Services",
            "subcategory":"Doctor",
            "type":"Services"
        }
    ],
    "sg:phone":"+1 716 433 8640",
    "sg:postcode":"14094",
    "sg:province":"NY",
    "sg:tags":[
        "physician",
        "surgeon"
    ],
    "wof:name":"Thomas Hughes MD",
    "wof:placetype":"venue"
},
  "geometry": {"coordinates":[-78.664063,43.154992],"type":"Point"}
}