{
  "type": "Feature",
  "properties": {
    "addr:full":"420 Falmouth Rd West Babylon NY 11704",
    "addr:housenumber":"420",
    "addr:postcode":"11704",
    "addr:street":"Falmouth Rd",
    "iso:country":"US",
    "sg:address":"420 Falmouth Rd",
    "sg:city":"West Babylon",
    "sg:classifiers":[
        {
            "category":"Retail",
            "subcategory":"Auto Repair",
            "type":"Services"
        }
    ],
    "sg:phone":"+1 631 376 0650",
    "sg:postcode":"11704",
    "sg:province":"NY",
    "sg:tags":[
        "body",
        "automobile",
        "painting"
    ],
    "wof:name":"Executive Auto Works Inc",
    "wof:placetype":"venue"
},
  "geometry": {"coordinates":[-73.334442,40.714492],"type":"Point"}
}