{
  "type": "Feature",
  "properties": {
    "addr:full":"8105 Lefferts Blvd Kew Gardens NY 11415",
    "addr:housenumber":"8105",
    "addr:postcode":"11415",
    "addr:street":"Lefferts Blvd",
    "iso:country":"US",
    "sg:address":"8105 Lefferts Blvd",
    "sg:city":"Kew Gardens",
    "sg:classifiers":[
        {
            "category":"Cinema",
            "subcategory":"Movie Theater",
            "type":"Entertainment"
        }
    ],
    "sg:phone":"+1 718 441 9835",
    "sg:postcode":"11415",
    "sg:province":"NY",
    "sg:website":"www.kewgardenstheatre.com/",
    "wof:name":"Kew Gardens Cinema",
    "wof:placetype":"venue"
},
  "geometry": {"coordinates":[-73.829697,40.709202],"type":"Point"}
}