{
  "type": "Feature",
  "properties": {
    "addr:full":"275 Pinnacle Rd Rochester NY 14623",
    "addr:housenumber":"275",
    "addr:postcode":"14623",
    "addr:street":"Pinnacle Rd",
    "iso:country":"US",
    "sg:address":"275 Pinnacle Rd",
    "sg:city":"Rochester",
    "sg:classifiers":[
        {
            "category":"Education",
            "subcategory":"School",
            "type":"Public Place"
        }
    ],
    "sg:phone":"+1 585 334 8010",
    "sg:postcode":"14623",
    "sg:province":"NY",
    "sg:tags":[
        "private",
        "special"
    ],
    "wof:name":"Norman Howard School",
    "wof:placetype":"venue"
},
  "geometry": {"coordinates":[-77.582279,43.07998],"type":"Point"}
}