{
  "type": "Feature",
  "properties": {
    "addr:full":"10426 Jamaica Avenue Jamaica NY 11418",
    "addr:housenumber":"10426",
    "addr:postcode":"11418",
    "addr:street":"Jamaica Avenue",
    "iso:country":"US",
    "sg:address":"10426 Jamaica Avenue",
    "sg:city":"Jamaica",
    "sg:classifiers":[
        {
            "category":"Banks & Credit Unions",
            "subcategory":"Financial Services",
            "type":"Services"
        }
    ],
    "sg:phone":"+1 718 849 2386",
    "sg:postcode":"11418",
    "sg:province":"NY",
    "sg:tags":[
        "broker",
        "mortgage"
    ],
    "wof:name":"Golden Philip",
    "wof:placetype":"venue"
},
  "geometry": {"coordinates":[-73.84220500000001,40.695101],"type":"Point"}
}