{
  "type": "Feature",
  "properties": {
    "addr:full":"7295 W Main St Westmoreland NY 13490",
    "addr:housenumber":"7295",
    "addr:postcode":"13490",
    "addr:street":"W Main St",
    "iso:country":"US",
    "sg:address":"7295 W Main St",
    "sg:city":"Westmoreland",
    "sg:classifiers":[
        {
            "category":"Bars & Pubs",
            "type":"Food & Drink"
        }
    ],
    "sg:phone":"+1 315 853 8075",
    "sg:postcode":"13490",
    "sg:province":"NY",
    "wof:name":"Bahas Sports Bar",
    "wof:placetype":"venue"
},
  "geometry": {"coordinates":[-75.408928,43.113266],"type":"Point"}
}