{
  "type": "Feature",
  "properties": {
    "iso:country":"US",
    "sg:address":"2019 River Rd",
    "sg:city":"Niagara Falls",
    "sg:classifiers":[
        {
            "category":"Shopping",
            "subcategory":"Bicycles & Sporting Goods",
            "type":"Retail Goods"
        }
    ],
    "sg:phone":"+1 716 283 3409",
    "sg:postcode":"14304",
    "sg:province":"NY",
    "sg:tags":[
        "tackle",
        "fishing"
    ],
    "wof:name":"Tackle Box",
    "wof:placetype":"venue"
},
  "geometry": {"coordinates":[-78.94192099999999,43.07209],"type":"Point"}
}