{
  "type": "Feature",
  "properties": {
    "addr:full":"4988 Route 22 Amenia NY 12501",
    "addr:housenumber":"4988",
    "addr:postcode":"12501",
    "addr:street":"Route 22",
    "iso:country":"US",
    "sg:address":"4988 Route 22",
    "sg:city":"Amenia",
    "sg:classifiers":[
        {
            "category":"Education",
            "subcategory":"School",
            "type":"Public Place"
        }
    ],
    "sg:phone":"+1 845 373 4120",
    "sg:postcode":"12501",
    "sg:province":"NY",
    "sg:tags":[
        "elementary"
    ],
    "wof:name":"Amenia Elementary School",
    "wof:placetype":"venue"
},
  "geometry": {"coordinates":[-73.55565,41.851697],"type":"Point"}
}