{
  "type": "Feature",
  "properties": {
    "addr:full":"465 Midland Ave Staten Island NY 10306",
    "addr:housenumber":"465",
    "addr:postcode":"10306",
    "addr:street":"Midland Ave",
    "iso:country":"US",
    "sg:address":"465 Midland Ave",
    "sg:city":"Staten Island",
    "sg:classifiers":[
        {
            "category":"Professional",
            "subcategory":"Accounting & Tax Preparation",
            "type":"Services"
        }
    ],
    "sg:phone":"+1 718 987 5284",
    "sg:postcode":"10306",
    "sg:province":"NY",
    "sg:tags":[
        "return",
        "filing"
    ],
    "wof:name":"H & R Block",
    "wof:placetype":"venue"
},
  "geometry": {"coordinates":[-74.097617,40.574773],"type":"Point"}
}