{
  "type": "Feature",
  "properties": {
    "addr:full":"1 Hope St Brooklyn NY 11211",
    "addr:housenumber":"1",
    "addr:postcode":"11211",
    "addr:street":"Hope St",
    "iso:country":"US",
    "sg:address":"1 Hope St",
    "sg:city":"Brooklyn",
    "sg:classifiers":[
        {
            "category":"Restaurant",
            "type":"Food & Drink"
        }
    ],
    "sg:menulink":"http://www.allmenus.com/ny/brooklyn/284204-dantes/menu/",
    "sg:phone":"+1 718 599 1945",
    "sg:postcode":"11211",
    "sg:province":"NY",
    "sg:tags":[
        "new",
        "american"
    ],
    "wof:name":"Dante's",
    "wof:placetype":"venue"
},
  "geometry": {"coordinates":[-73.957888,40.713943],"type":"Point"}
}