{
  "type": "Feature",
  "properties": {
    "addr:full":"510 Maloney Rd Poughkeepsie NY 12603",
    "addr:housenumber":"510",
    "addr:postcode":"12603",
    "addr:street":"Maloney Rd",
    "iso:country":"US",
    "sg:address":"510 Maloney Rd",
    "sg:city":"Poughkeepsie",
    "sg:classifiers":[
        {
            "category":"Utilities",
            "subcategory":"Fuel Oil & Lpg",
            "type":"Services"
        }
    ],
    "sg:phone":"+1 845 463 7000",
    "sg:postcode":"12603",
    "sg:province":"NY",
    "sg:tags":[
        "home",
        "heating"
    ],
    "wof:name":"Buy-Rite Oil Co Inc",
    "wof:placetype":"venue"
},
  "geometry": {"coordinates":[-73.871578,41.641047],"type":"Point"}
}