{
  "type": "Feature",
  "properties": {
    "addr:full":"111 E 55 St New York NY 10022",
    "addr:housenumber":"111;55",
    "addr:postcode":"10022",
    "addr:street":"E;St",
    "iso:country":"US",
    "sg:address":"111 E 55 St",
    "sg:city":"New York",
    "sg:classifiers":[
        {
            "category":"Restaurant",
            "type":"Food & Drink"
        }
    ],
    "sg:phone":"+1   ",
    "sg:postcode":"10022",
    "sg:province":"NY",
    "sg:tags":[
        "eating"
    ],
    "wof:name":"Lite Bites",
    "wof:placetype":"venue"
},
  "geometry": {"coordinates":[-73.970427,40.759905],"type":"Point"}
}