{
  "type": "Feature",
  "properties": {
    "addr:full":"710 Lake Ave Rochester NY 14613",
    "addr:housenumber":"710",
    "addr:postcode":"14613",
    "addr:street":"Lake Ave",
    "iso:country":"US",
    "sg:address":"710 Lake Ave",
    "sg:city":"Rochester",
    "sg:classifiers":[
        {
            "category":"Banks & Credit Unions",
            "subcategory":"Bank",
            "type":"Services"
        }
    ],
    "sg:phone":"+1 585 458 2270",
    "sg:postcode":"14613",
    "sg:province":"NY",
    "sg:tags":[
        "saving",
        "commercial"
    ],
    "wof:name":"Charter One Bank, National Association",
    "wof:placetype":"venue"
},
  "geometry": {"coordinates":[-77.63121,43.177911],"type":"Point"}
}