{
  "type": "Feature",
  "properties": {
    "iso:country":"US",
    "sg:address":"40 Centre St",
    "sg:city":"Woodmere",
    "sg:classifiers":[
        {
            "category":"Shopping",
            "subcategory":"Catalog Store",
            "type":"Retail Goods"
        }
    ],
    "sg:phone":"+1   ",
    "sg:postcode":"11598",
    "sg:province":"NY",
    "sg:tags":[
        "house",
        "mail"
    ],
    "wof:name":"Cheepezecom",
    "wof:placetype":"venue"
},
  "geometry": {"coordinates":[-73.703215,40.63033],"type":"Point"}
}