{
  "type": "Feature",
  "properties": {
    "iso:country":"US",
    "sg:address":"260 Ave of the Americas",
    "sg:city":"New York",
    "sg:classifiers":[
        {
            "category":"Restaurant",
            "type":"Food & Drink"
        }
    ],
    "sg:phone":"+1   ",
    "sg:postcode":"10014",
    "sg:province":"NY",
    "sg:tags":[
        "drinking",
        "eating"
    ],
    "wof:name":"Da Silvano Corp",
    "wof:placetype":"venue"
},
  "geometry": {"coordinates":[-74.002348,40.729024],"type":"Point"}
}