{
  "type": "Feature",
  "properties": {
    "iso:country":"US",
    "sg:address":"7623 Colonial Rd",
    "sg:city":"Brooklyn",
    "sg:classifiers":[
        {
            "category":"Building & Trades",
            "subcategory":"Construction",
            "type":"Services"
        }
    ],
    "sg:phone":"+1 718 439 1479",
    "sg:postcode":"11209",
    "sg:province":"NY",
    "sg:tags":[
        "general",
        "contractor"
    ],
    "wof:name":"Telentos Construction Corp",
    "wof:placetype":"venue"
},
  "geometry": {"coordinates":[-74.03362,40.631439],"type":"Point"}
}