{
  "type": "Feature",
  "properties": {
    "iso:country":"US",
    "sg:address":"825 Boynton Ave",
    "sg:city":"Bronx",
    "sg:classifiers":[
        {
            "category":"Professional",
            "subcategory":"Management & Consulting",
            "type":"Services"
        }
    ],
    "sg:phone":"+1   ",
    "sg:postcode":"10473",
    "sg:province":"NY",
    "wof:name":"Ra Taj Management Inc",
    "wof:placetype":"venue"
},
  "geometry": {"coordinates":[-73.87642099999999,40.820494],"type":"Point"}
}