{
  "type": "Feature",
  "properties": {
    "addr:full":"46-20 Broadway Queens NY 11103",
    "addr:housenumber":"46-20",
    "addr:postcode":"11103",
    "addr:street":"Broadway",
    "iso:country":"US",
    "sg:address":"46-20 Broadway",
    "sg:city":"Queens",
    "sg:classifiers":[
        {
            "category":"Personal",
            "subcategory":"Nail Salon",
            "type":"Services"
        }
    ],
    "sg:phone":"+1 718 278 9744",
    "sg:postcode":"11103",
    "sg:province":"NY",
    "wof:name":"Angie's Beauty Salon",
    "wof:placetype":"venue"
},
  "geometry": {"coordinates":[-73.91384600000001,40.756547],"type":"Point"}
}