{
  "type": "Feature",
  "properties": {
    "addr:full":"2503 E Tremont Ave Bronx NY 10461",
    "addr:housenumber":"2503",
    "addr:postcode":"10461",
    "addr:street":"E Tremont Ave",
    "iso:country":"US",
    "sg:address":"2503 E Tremont Ave",
    "sg:city":"Bronx",
    "sg:classifiers":[
        {
            "category":"Real Estate",
            "subcategory":"Real Estate Agent",
            "type":"Services"
        }
    ],
    "sg:phone":"+1 718 931 4434",
    "sg:postcode":"10461",
    "sg:province":"NY",
    "wof:name":"Gal & Co",
    "wof:placetype":"venue"
},
  "geometry": {"coordinates":[-73.850048,40.842919],"type":"Point"}
}