{
  "type": "Feature",
  "properties": {
    "addr:full":"1 Chili Ave North Chili NY 14546",
    "addr:housenumber":"1",
    "addr:postcode":"14546",
    "addr:street":"Chili Ave North",
    "iso:country":"US",
    "sg:address":"1 Chili Ave",
    "sg:city":"North Chili",
    "sg:classifiers":[
        {
            "category":"Real Estate",
            "subcategory":"Real Estate Operator",
            "type":"Services"
        }
    ],
    "sg:phone":"+1 585 594 9600",
    "sg:postcode":"14546",
    "sg:province":"NY",
    "sg:tags":[
        "apartment"
    ],
    "wof:name":"Chili Commons",
    "wof:placetype":"venue"
},
  "geometry": {"coordinates":[-77.75940199999999,43.02001],"type":"Point"}
}