{
  "type": "Feature",
  "properties": {
    "iso:country":"US",
    "sg:address":"265 Ardsley Rd",
    "sg:city":"Scarsdale",
    "sg:classifiers":[
        {
            "category":"Health Services",
            "subcategory":"Doctor",
            "type":"Services"
        }
    ],
    "sg:phone":"+1 914 723 0113",
    "sg:postcode":"10583",
    "sg:province":"NY",
    "sg:tags":[
        "medical"
    ],
    "wof:name":"Stephen L Weitz MD",
    "wof:placetype":"venue"
},
  "geometry": {"coordinates":[-73.816613,40.991468],"type":"Point"}
}