{
  "type": "Feature",
  "properties": {
    "addr:full":"18 Woodland Ter Nanuet NY 10954",
    "addr:housenumber":"18",
    "addr:postcode":"10954",
    "addr:street":"Woodland Ter Nanuet",
    "iso:country":"US",
    "sg:address":"18 Woodland Ter",
    "sg:city":"Nanuet",
    "sg:classifiers":[
        {
            "category":"Shopping",
            "subcategory":"Gifts & Souvenirs",
            "type":"Retail Goods"
        }
    ],
    "sg:phone":"+1   ",
    "sg:postcode":"10954",
    "sg:province":"NY",
    "sg:tags":[
        "flee"
    ],
    "wof:name":"Ls Co",
    "wof:placetype":"venue"
},
  "geometry": {"coordinates":[-74.02013700000001,41.111648],"type":"Point"}
}