{
  "type": "Feature",
  "properties": {
    "iso:country":"US",
    "sg:address":"221 Heberton Ave",
    "sg:city":"Staten Island",
    "sg:classifiers":[
        {
            "category":"Organizations",
            "subcategory":"Religious Organization",
            "type":"Services"
        }
    ],
    "sg:phone":"+1 718 273 9666",
    "sg:postcode":"10302",
    "sg:province":"NY",
    "sg:tags":[
        "church"
    ],
    "wof:name":"Faith United Methodist Church",
    "wof:placetype":"venue"
},
  "geometry": {"coordinates":[-74.132383,40.635318],"type":"Point"}
}