{
  "type": "Feature",
  "properties": {
    "addr:full":"759 Ocean Pkwy Brooklyn NY 11230",
    "addr:housenumber":"759",
    "addr:postcode":"11230",
    "addr:street":"Ocean Pkwy",
    "iso:country":"US",
    "sg:address":"759 Ocean Pkwy",
    "sg:city":"Brooklyn",
    "sg:classifiers":[
        {
            "category":"Wholesale",
            "subcategory":"Drugs",
            "type":"Manufacturing & Wholesale Goods"
        }
    ],
    "sg:phone":"+1 718 633 6618",
    "sg:postcode":"11230",
    "sg:province":"NY",
    "sg:tags":[
        "cosmetic"
    ],
    "wof:name":"Elite Cosmetics",
    "wof:placetype":"venue"
},
  "geometry": {"coordinates":[-73.971329,40.629181],"type":"Point"}
}