{
  "type": "Feature",
  "properties": {
    "addr:full":"33 Wyoming Dr Huntington Sta NY 11746",
    "addr:housenumber":"33",
    "addr:postcode":"11746",
    "addr:street":"Wyoming Dr",
    "iso:country":"US",
    "sg:address":"33 Wyoming Dr",
    "sg:city":"Huntington Sta",
    "sg:classifiers":[
        {
            "category":"Insurance",
            "subcategory":"Hazard Insurance",
            "type":"Services"
        }
    ],
    "sg:phone":"+1 631 385 2100",
    "sg:postcode":"11746",
    "sg:province":"NY",
    "sg:tags":[
        "profit",
        "sharing",
        "pension",
        "plan"
    ],
    "wof:name":"Griffin Actuarial & Admin Svc",
    "wof:placetype":"venue"
},
  "geometry": {"coordinates":[-73.390933,40.846835],"type":"Point"}
}