{
  "type": "Feature",
  "properties": {
    "iso:country":"US",
    "sg:address":"3947 State Hwy 281",
    "sg:city":"Cortland",
    "sg:classifiers":[
        {
            "category":"Food & Beverages",
            "subcategory":"Groceries & Convenience Stores",
            "type":"Retail Goods"
        }
    ],
    "sg:phone":"+1 607 756 9502",
    "sg:postcode":"13045",
    "sg:province":"NY",
    "wof:name":"A Plus Mini Market",
    "wof:placetype":"venue"
},
  "geometry": {"coordinates":[-76.20410699999999,42.598731],"type":"Point"}
}