{
  "type": "Feature",
  "properties": {
    "addr:full":"377 S Union St Spencerport NY 14559",
    "addr:housenumber":"377",
    "addr:postcode":"14559",
    "addr:street":"S Union St",
    "iso:country":"US",
    "sg:address":"377 S Union St",
    "sg:city":"Spencerport",
    "sg:classifiers":[
        {
            "category":"Travel",
            "subcategory":"Travel Agent",
            "type":"Entertainment"
        }
    ],
    "sg:phone":"+1   ",
    "sg:postcode":"14559",
    "sg:province":"NY",
    "sg:tags":[
        "passenger",
        "agency",
        "transportation",
        "arrangement"
    ],
    "wof:name":"ABC Avanti Travel",
    "wof:placetype":"venue"
},
  "geometry": {"coordinates":[-77.804259,43.182085],"type":"Point"}
}