{
  "type": "Feature",
  "properties": {
    "iso:country":"US",
    "sg:address":"652 Suffolk Ave",
    "sg:city":"Brentwood",
    "sg:classifiers":[
        {
            "category":"Health Services",
            "subcategory":"Doctor",
            "type":"Services"
        }
    ],
    "sg:phone":"+1 631 273 7614",
    "sg:postcode":"11717",
    "sg:province":"NY",
    "sg:tags":[
        "dentist"
    ],
    "wof:name":"Philip Glaser DDS",
    "wof:placetype":"venue"
},
  "geometry": {"coordinates":[-73.250657,40.780141],"type":"Point"}
}