{
  "type": "Feature",
  "properties": {
    "addr:full":"3179 Long Beach Rd Oceanside NY 11572",
    "addr:housenumber":"3179",
    "addr:postcode":"11572",
    "addr:street":"Long Beach Rd",
    "iso:country":"US",
    "sg:address":"3179 Long Beach Rd",
    "sg:city":"Oceanside",
    "sg:classifiers":[
        {
            "category":"Food & Beverages",
            "subcategory":"Liquor & Beverages",
            "type":"Retail Goods"
        }
    ],
    "sg:phone":"+1 516 825 8466",
    "sg:postcode":"11572",
    "sg:province":"NY",
    "sg:tags":[
        "beer",
        "spirit",
        "wine"
    ],
    "sg:website":"www.vino100oceanside.com",
    "wof:name":"Vino 100",
    "wof:placetype":"venue"
},
  "geometry": {"coordinates":[-73.640389,40.634611],"type":"Point"}
}