{
  "type": "Feature",
  "properties": {
    "iso:country":"US",
    "sg:address":"125 Cedarhurst Ave",
    "sg:city":"Cedarhurst",
    "sg:classifiers":[
        {
            "category":"Shopping",
            "subcategory":"Gifts & Souvenirs",
            "type":"Retail Goods"
        }
    ],
    "sg:phone":"+1 516 374 4646",
    "sg:postcode":"11516",
    "sg:province":"NY",
    "sg:tags":[
        "basket",
        "parcel"
    ],
    "wof:name":"Banim",
    "wof:placetype":"venue"
},
  "geometry": {"coordinates":[-73.724673,40.622972],"type":"Point"}
}