{
  "type": "Feature",
  "properties": {
    "iso:country":"US",
    "sg:address":"2005 Linden St",
    "sg:city":"Ogdensburg",
    "sg:classifiers":[
        {
            "category":"Utilities",
            "subcategory":"Electric",
            "type":"Services"
        },
        {
            "category":"Manufacturing",
            "subcategory":"Electronics",
            "type":"Manufacturing & Wholesale Goods"
        }
    ],
    "sg:phone":"+1 315 393 9971",
    "sg:postcode":"13669",
    "sg:province":"NY",
    "sg:tags":[
        "equipment-testing"
    ],
    "wof:name":"Niagara Mohawk Power Corporation",
    "wof:placetype":"venue"
},
  "geometry": {"coordinates":[-75.461601,44.694367],"type":"Point"}
}