{
  "type": "Feature",
  "properties": {
    "addr:full":"103 E 125th St New York NY 10035",
    "addr:housenumber":"103",
    "addr:postcode":"10035",
    "addr:street":"E 125Th St",
    "iso:country":"US",
    "sg:address":"103 E 125th St",
    "sg:city":"New York",
    "sg:classifiers":[
        {
            "category":"Education",
            "subcategory":"School",
            "type":"Public Place"
        },
        {
            "category":"Education",
            "subcategory":"University",
            "type":"Public Place"
        }
    ],
    "sg:phone":"+1 212 987 3673",
    "sg:postcode":"10035",
    "sg:province":"NY",
    "sg:tags":[
        "high",
        "middle",
        "college",
        "elementary"
    ],
    "wof:name":"New York College of Podiatry",
    "wof:placetype":"venue"
},
  "geometry": {"coordinates":[-73.93879699999999,40.805],"type":"Point"}
}