{
  "type": "Feature",
  "properties": {
    "addr:full":"2 Ingraham St Brooklyn NY 11206",
    "addr:housenumber":"2",
    "addr:postcode":"11206",
    "addr:street":"Ingraham St",
    "iso:country":"US",
    "sg:address":"2 Ingraham St",
    "sg:city":"Brooklyn",
    "sg:classifiers":[
        {
            "category":"Building & Trades",
            "subcategory":"Construction",
            "type":"Services"
        }
    ],
    "sg:phone":"+1 718 418 6400",
    "sg:postcode":"11206",
    "sg:province":"NY",
    "sg:tags":[
        "repair",
        "carpentry",
        "contractor"
    ],
    "wof:name":"Prime Frama Inc",
    "wof:placetype":"venue"
},
  "geometry": {"coordinates":[-73.932086,40.707051],"type":"Point"}
}