{
  "type": "Feature",
  "properties": {
    "addr:full":"1050 E 103rd St Brooklyn NY 11236",
    "addr:housenumber":"1050",
    "addr:postcode":"11236",
    "addr:street":"E 103Rd St",
    "iso:country":"US",
    "sg:address":"1050 E 103rd St",
    "sg:city":"Brooklyn",
    "sg:classifiers":[
        {
            "category":"Building & Trades",
            "subcategory":"Construction",
            "type":"Services"
        }
    ],
    "sg:phone":"+1 718 531 0892",
    "sg:postcode":"11236",
    "sg:province":"NY",
    "sg:tags":[
        "house"
    ],
    "wof:name":"C and K Construction",
    "wof:placetype":"venue"
},
  "geometry": {"coordinates":[-73.893264,40.644069],"type":"Point"}
}