{
  "type": "Feature",
  "properties": {
    "addr:full":"42 Pine Hollow Rd Oyster Bay NY 11771",
    "addr:housenumber":"42",
    "addr:postcode":"11771",
    "addr:street":"Pine Hollow Rd",
    "iso:country":"US",
    "sg:address":"42 Pine Hollow Rd",
    "sg:city":"Oyster Bay",
    "sg:classifiers":[
        {
            "category":"Wholesale",
            "subcategory":"Vending Machines",
            "type":"Manufacturing & Wholesale Goods"
        }
    ],
    "sg:phone":"+1   ",
    "sg:postcode":"11771",
    "sg:province":"NY",
    "sg:tags":[
        "operator",
        "equipment"
    ],
    "wof:name":"King Pin Vending",
    "wof:placetype":"venue"
},
  "geometry": {"coordinates":[-73.5325,40.865352],"type":"Point"}
}