{
  "type": "Feature",
  "properties": {
    "iso:country":"US",
    "sg:address":"1419 Sunrise Hwy",
    "sg:city":"Bay Shore",
    "sg:classifiers":[
        {
            "category":"Home & Garden",
            "subcategory":"Mobile Homes",
            "type":"Retail Goods"
        }
    ],
    "sg:phone":"+1   ",
    "sg:postcode":"11706",
    "sg:province":"NY",
    "sg:tags":[
        "fuel",
        "oil",
        "accessory"
    ],
    "wof:name":"Bay Shore MBL Homes P K & Sls",
    "wof:placetype":"venue"
},
  "geometry": {"coordinates":[-73.258253,40.733565],"type":"Point"}
}