{
  "type": "Feature",
  "properties": {
    "iso:country":"US",
    "sg:address":"2 Main Pl",
    "sg:city":"Buffalo",
    "sg:classifiers":[
        {
            "category":"Food & Beverages",
            "subcategory":"Specialty",
            "type":"Retail Goods"
        }
    ],
    "sg:phone":"+1 716 855 2377",
    "sg:postcode":"14202",
    "sg:province":"NY",
    "sg:tags":[
        "tea",
        "coffee"
    ],
    "wof:name":"Liberty Coffee Roastery",
    "wof:placetype":"venue"
},
  "geometry": {"coordinates":[-78.87483400000001,42.88429],"type":"Point"}
}