{
  "type": "Feature",
  "properties": {
    "iso:country":"US",
    "sg:address":"150 Varick St Lbby",
    "sg:city":"Canal Street",
    "sg:classifiers":[
        {
            "category":"Bars & Pubs",
            "subcategory":"Nightclub",
            "type":"Food & Drink"
        }
    ],
    "sg:phone":"+1 212 929 9444",
    "sg:postcode":"10013",
    "sg:province":"NY",
    "sg:tags":[
        "nightlife"
    ],
    "wof:name":"Flow",
    "wof:placetype":"venue"
},
  "geometry": {"coordinates":[-74.005501,40.726398],"type":"Point"}
}