{
  "type": "Feature",
  "properties": {
    "iso:country":"US",
    "sg:address":"38 Vans Ter",
    "sg:city":"Lake Katrine",
    "sg:classifiers":[
        {
            "category":"Building & Trades",
            "subcategory":"Construction",
            "type":"Services"
        }
    ],
    "sg:phone":"+1 845 336 4019",
    "sg:postcode":"12449",
    "sg:province":"NY",
    "sg:tags":[
        "painting",
        "drywall"
    ],
    "wof:name":"Carpinos Taping Pntg & Drywall",
    "wof:placetype":"venue"
},
  "geometry": {"coordinates":[-73.99929,41.98627],"type":"Point"}
}