{
  "type": "Feature",
  "properties": {
    "addr:full":"982 Westchester Ave Bronx NY 10459",
    "addr:housenumber":"982",
    "addr:postcode":"10459",
    "addr:street":"Westchester Ave",
    "iso:country":"US",
    "sg:address":"982 Westchester Ave",
    "sg:city":"Bronx",
    "sg:classifiers":[
        {
            "category":"Home & Garden",
            "subcategory":"Furniture",
            "type":"Retail Goods"
        }
    ],
    "sg:phone":"+1   ",
    "sg:postcode":"10459",
    "sg:province":"NY",
    "wof:name":"Y2k Furniture",
    "wof:placetype":"venue"
},
  "geometry": {"coordinates":[-73.89439900000001,40.823284],"type":"Point"}
}