{
  "type": "Feature",
  "properties": {
    "iso:country":"US",
    "sg:address":"11928 Roosevelt Hwy",
    "sg:city":"Lyndonville",
    "sg:classifiers":[
        {
            "category":"Restaurant",
            "type":"Food & Drink"
        }
    ],
    "sg:phone":"+1 585 765 9244",
    "sg:postcode":"14098",
    "sg:province":"NY",
    "sg:tags":[
        "eating"
    ],
    "wof:name":"The Family Spot Restaurant",
    "wof:placetype":"venue"
},
  "geometry": {"coordinates":[-78.35034,43.349504],"type":"Point"}
}