{
  "type": "Feature",
  "properties": {
    "addr:full":"22 Albany St Elmont NY 11003",
    "addr:housenumber":"22",
    "addr:postcode":"11003",
    "addr:street":"Albany St",
    "iso:country":"US",
    "sg:address":"22 Albany St",
    "sg:city":"Elmont",
    "sg:classifiers":[
        {
            "category":"Manufacturing",
            "subcategory":"Metals",
            "type":"Manufacturing & Wholesale Goods"
        }
    ],
    "sg:phone":"+1   ",
    "sg:postcode":"11003",
    "sg:province":"NY",
    "sg:tags":[
        "metalwork",
        "architectural",
        "mfg"
    ],
    "wof:name":"K & S Ironworks",
    "wof:placetype":"venue"
},
  "geometry": {"coordinates":[-73.709515,40.68635],"type":"Point"}
}