{
  "type": "Feature",
  "properties": {
    "addr:full":"80 Lafayette St New York NY 10013",
    "addr:housenumber":"80",
    "addr:postcode":"10013",
    "addr:street":"Lafayette St",
    "iso:country":"US",
    "sg:address":"80 Lafayette St",
    "sg:city":"New York",
    "sg:classifiers":[
        {
            "category":"Banks & Credit Unions",
            "subcategory":"Bank",
            "type":"Services"
        }
    ],
    "sg:phone":"+1 212 267 1010",
    "sg:postcode":"10013",
    "sg:province":"NY",
    "sg:tags":[
        "depository",
        "banking",
        "check",
        "cashing"
    ],
    "wof:name":"Lazer Check Cashing Corp",
    "wof:placetype":"venue"
},
  "geometry": {"coordinates":[-74.00187099999999,40.716986],"type":"Point"}
}