{
  "type": "Feature",
  "properties": {
    "iso:country":"US",
    "sg:address":"635 N Division St",
    "sg:city":"Peekskill",
    "sg:classifiers":[
        {
            "category":"Home & Garden",
            "subcategory":"Furniture",
            "type":"Retail Goods"
        }
    ],
    "sg:phone":"+1 914 422 0039",
    "sg:postcode":"10566",
    "sg:province":"NY",
    "sg:tags":[
        "store"
    ],
    "wof:name":"Mr Lee Oriental Furniture Store Inc",
    "wof:placetype":"venue"
},
  "geometry": {"coordinates":[-73.917969,41.298229],"type":"Point"}
}