{
  "type": "Feature",
  "properties": {
    "addr:full":"301 E 54th Street New York NY 10022",
    "addr:housenumber":"301",
    "addr:postcode":"10022",
    "addr:street":"E 54Th Street",
    "iso:country":"US",
    "sg:address":"301 E 54th Street",
    "sg:city":"New York",
    "sg:classifiers":[
        {
            "category":"Health Services",
            "subcategory":"Health Practitioner",
            "type":"Services"
        }
    ],
    "sg:phone":"+1 212 759 0292",
    "sg:postcode":"10022",
    "sg:province":"NY",
    "sg:tags":[
        "acupuncture"
    ],
    "wof:name":"Holistic Acupressure Center",
    "wof:placetype":"venue"
},
  "geometry": {"coordinates":[-73.966689,40.757388],"type":"Point"}
}