{
  "type": "Feature",
  "properties": {
    "iso:country":"US",
    "sg:address":"53 Charter Oak Dr",
    "sg:city":"New Canaan",
    "sg:classifiers":[
        {
            "category":"Building & Trades",
            "subcategory":"Landscaping Services",
            "type":"Services"
        }
    ],
    "sg:phone":"+1 203 966 3919",
    "sg:postcode":"06840",
    "sg:province":"NY",
    "sg:tags":[
        "landscape",
        "contractor"
    ],
    "wof:name":"Bianco Landscaping",
    "wof:placetype":"venue"
},
  "geometry": {"coordinates":[-73.482176,41.116314],"type":"Point"}
}