{
  "type": "Feature",
  "properties": {
    "addr:full":"345 Hudson New York NY 10014",
    "addr:housenumber":"345",
    "addr:postcode":"10014",
    "addr:street":"Hudson",
    "iso:country":"US",
    "sg:address":"345 Hudson",
    "sg:city":"New York",
    "sg:classifiers":[
        {
            "category":"Building & Trades",
            "subcategory":"Cleaning & Sanitation",
            "type":"Services"
        }
    ],
    "sg:phone":"+1 877 738 3063",
    "sg:postcode":"10014",
    "sg:province":"NY",
    "sg:tags":[
        "home"
    ],
    "sg:website":"carpetcleanersnewyork.net#cid=yelp",
    "wof:name":"ABC Carpet & Rug Repair",
    "wof:placetype":"venue"
},
  "geometry": {"coordinates":[-74.00728700000001,40.727746],"type":"Point"}
}