{
  "type": "Feature",
  "properties": {
    "iso:country":"US",
    "sg:address":"3770 103rd St",
    "sg:city":"Corona",
    "sg:classifiers":[
        {
            "category":"Shopping",
            "type":"Retail Goods"
        },
        {
            "category":"Manufacturing",
            "subcategory":"Paper Products",
            "type":"Manufacturing & Wholesale Goods"
        }
    ],
    "sg:phone":"+1 718 205 6658",
    "sg:postcode":"11368",
    "sg:province":"NY",
    "sg:tags":[
        "packaging",
        "materials-wholesale",
        "material",
        "manufacturer"
    ],
    "wof:name":"Valente Express Envios Packagi",
    "wof:placetype":"venue"
},
  "geometry": {"coordinates":[-73.857929,40.741566],"type":"Point"}
}