{
  "type": "Feature",
  "properties": {
    "addr:full":"4106 E Tremont Avenue Bronx NY 10465",
    "addr:housenumber":"4106",
    "addr:postcode":"10465",
    "addr:street":"E Tremont Avenue",
    "iso:country":"US",
    "sg:address":"4106 E Tremont Avenue",
    "sg:city":"Bronx",
    "sg:classifiers":[
        {
            "category":"Restaurant",
            "type":"Food & Drink"
        }
    ],
    "sg:phone":"+1 718 824 8070",
    "sg:postcode":"10465",
    "sg:province":"NY",
    "sg:tags":[
        "pizza"
    ],
    "wof:name":"Frank's Pizza",
    "wof:placetype":"venue"
},
  "geometry": {"coordinates":[-73.817211,40.818746],"type":"Point"}
}