{
  "type": "Feature",
  "properties": {
    "addr:full":"205 W 15th Street Ofc New York NY 10011",
    "addr:housenumber":"205",
    "addr:postcode":"10011",
    "addr:street":"W 15Th Street",
    "iso:country":"US",
    "sg:address":"205 W 15th Street Ofc",
    "sg:city":"New York",
    "sg:classifiers":[
        {
            "category":"Real Estate",
            "subcategory":"Real Estate Operator",
            "type":"Services"
        }
    ],
    "sg:phone":"+1 212 924 7991",
    "sg:postcode":"10011",
    "sg:province":"NY",
    "sg:tags":[
        "apartment"
    ],
    "wof:name":"Chelsmore Apartments",
    "wof:placetype":"venue"
},
  "geometry": {"coordinates":[-73.999494,40.739364],"type":"Point"}
}