{
  "type": "Feature",
  "properties": {
    "iso:country":"US",
    "sg:address":"155 Monroe Ave",
    "sg:city":"Rochester",
    "sg:classifiers":[
        {
            "category":"Shopping",
            "subcategory":"Used Merchandise",
            "type":"Retail Goods"
        }
    ],
    "sg:phone":"+1 585 262 4643",
    "sg:postcode":"14607",
    "sg:province":"NY",
    "sg:tags":[
        "antique"
    ],
    "wof:name":"Rochester Antique Market",
    "wof:placetype":"venue"
},
  "geometry": {"coordinates":[-77.60099200000001,43.150719],"type":"Point"}
}