{
  "type": "Feature",
  "properties": {
    "addr:full":"3888 Savage Rd Geneva NY 14456",
    "addr:housenumber":"3888",
    "addr:postcode":"14456",
    "addr:street":"Savage Rd",
    "iso:country":"US",
    "sg:address":"3888 Savage Rd",
    "sg:city":"Geneva",
    "sg:classifiers":[
        {
            "category":"Farming",
            "subcategory":"Dairy Farm",
            "type":"Manufacturing & Wholesale Goods"
        }
    ],
    "sg:phone":"+1 315 789 9130",
    "sg:postcode":"14456",
    "sg:province":"NY",
    "wof:name":"Heifer Haven Farms",
    "wof:placetype":"venue"
},
  "geometry": {"coordinates":[-77.047308,42.841686],"type":"Point"}
}