{
  "type": "Feature",
  "properties": {
    "iso:country":"US",
    "sg:address":"2801 Long Rd",
    "sg:city":"Grand Island",
    "sg:classifiers":[
        {
            "category":"Manufacturing",
            "subcategory":"Chemicals & Compounds",
            "type":"Manufacturing & Wholesale Goods"
        }
    ],
    "sg:phone":"+1   ",
    "sg:postcode":"14072",
    "sg:province":"NY",
    "sg:tags":[
        "research"
    ],
    "wof:name":"Islechem LLC",
    "wof:placetype":"venue"
},
  "geometry": {"coordinates":[-78.998294,43.048511],"type":"Point"}
}