{
  "type": "Feature",
  "properties": {
    "iso:country":"US",
    "sg:address":"464 Franklin St",
    "sg:city":"Buffalo",
    "sg:classifiers":[
        {
            "category":"Health Services",
            "subcategory":"Clinic",
            "type":"Services"
        }
    ],
    "sg:phone":"+1 716 881 0273",
    "sg:postcode":"14202",
    "sg:province":"NY",
    "wof:name":"Lifestage Health",
    "wof:placetype":"venue"
},
  "geometry": {"coordinates":[-78.87282399999999,42.897791],"type":"Point"}
}