{
  "type": "Feature",
  "properties": {
    "addr:full":"2718 Hylan Blvd Staten Island NY 10306",
    "addr:housenumber":"2718",
    "addr:postcode":"10306",
    "addr:street":"Hylan Blvd",
    "iso:country":"US",
    "sg:address":"2718 Hylan Blvd",
    "sg:city":"Staten Island",
    "sg:classifiers":[
        {
            "category":"Shopping",
            "subcategory":"Department Store",
            "type":"Retail Goods"
        }
    ],
    "sg:phone":"+1 718 980 6952",
    "sg:postcode":"10306",
    "sg:province":"NY",
    "sg:tags":[
        "shop"
    ],
    "wof:name":"Home Goods",
    "wof:placetype":"venue"
},
  "geometry": {"coordinates":[-74.114071,40.566147],"type":"Point"}
}