{
  "type": "Feature",
  "properties": {
    "iso:country":"US",
    "sg:address":"2725 State Hwy 14",
    "sg:city":"Montour Falls",
    "sg:classifiers":[
        {
            "category":"Autos & Motor Vehicles",
            "subcategory":"Automobile Sales",
            "type":"Retail Goods"
        }
    ],
    "sg:phone":"+1   ",
    "sg:postcode":"14865",
    "sg:province":"NY",
    "sg:tags":[
        "used"
    ],
    "wof:name":"Finger Lakes Auto Sales",
    "wof:placetype":"venue"
},
  "geometry": {"coordinates":[-76.83968299999999,42.340881],"type":"Point"}
}