{
  "type": "Feature",
  "properties": {
    "iso:country":"US",
    "sg:address":"1554 Astor Ave",
    "sg:city":"Bronx",
    "sg:classifiers":[
        {
            "category":"Health Services",
            "subcategory":"Podiatrist",
            "type":"Services"
        }
    ],
    "sg:phone":"+1   ",
    "sg:postcode":"10469",
    "sg:province":"NY",
    "wof:name":"Barry Finkelstein",
    "wof:placetype":"venue"
},
  "geometry": {"coordinates":[-73.84106800000001,40.85927],"type":"Point"}
}