{
  "type": "Feature",
  "properties": {
    "addr:full":"2001 South Rd Ste B101 Poughkeepsie NY 12601",
    "addr:housenumber":"2001",
    "addr:postcode":"12601",
    "addr:street":"South Rd Ste B101",
    "iso:country":"US",
    "sg:address":"2001 South Rd Ste B101",
    "sg:city":"Poughkeepsie",
    "sg:classifiers":[
        {
            "category":"Shopping",
            "subcategory":"Gifts & Souvenirs",
            "type":"Retail Goods"
        },
        {
            "category":"Health Services",
            "subcategory":"Nursing And Care Facility",
            "type":"Services"
        }
    ],
    "sg:phone":"+1 845 298 0900",
    "sg:postcode":"12601",
    "sg:province":"NY",
    "sg:tags":[
        "shop",
        "equipment",
        "massage",
        "supply"
    ],
    "sg:website":"http://www.brookstone.com",
    "wof:name":"Brookstone",
    "wof:placetype":"venue"
},
  "geometry": {"coordinates":[-73.917007,41.62701],"type":"Point"}
}