{
  "type": "Feature",
  "properties": {
    "addr:full":"1195 Lexington Ave New York NY 10028",
    "addr:housenumber":"1195",
    "addr:postcode":"10028",
    "addr:street":"Lexington Ave",
    "iso:country":"US",
    "sg:address":"1195 Lexington Ave",
    "sg:city":"New York",
    "sg:classifiers":[
        {
            "category":"Personal",
            "subcategory":"Beauty Salon",
            "type":"Services"
        }
    ],
    "sg:phone":"+1 212 879 7369",
    "sg:postcode":"10028",
    "sg:province":"NY",
    "sg:tags":[
        "shop"
    ],
    "wof:name":"Hair By Nigel",
    "wof:placetype":"venue"
},
  "geometry": {"coordinates":[-73.957472,40.776911],"type":"Point"}
}