{
  "type": "Feature",
  "properties": {
    "addr:full":"829 Park Ave New York NY 10021",
    "addr:housenumber":"829",
    "addr:postcode":"10021",
    "addr:street":"Park Ave",
    "iso:country":"US",
    "sg:address":"829 Park Ave",
    "sg:city":"New York",
    "sg:classifiers":[
        {
            "category":"Health Services",
            "subcategory":"Doctor",
            "type":"Services"
        }
    ],
    "sg:phone":"+1 212 472 2572",
    "sg:postcode":"10021",
    "sg:province":"NY",
    "wof:name":"Jaeger Roberta MD",
    "wof:placetype":"venue"
},
  "geometry": {"coordinates":[-73.962097,40.7733],"type":"Point"}
}