{
  "type": "Feature",
  "properties": {
    "addr:full":"1517 Watson Ave Bronx NY 10472",
    "addr:housenumber":"1517",
    "addr:postcode":"10472",
    "addr:street":"Watson Ave",
    "iso:country":"US",
    "sg:address":"1517 Watson Ave",
    "sg:city":"Bronx",
    "sg:classifiers":[
        {
            "category":"Personal",
            "subcategory":"Beauty Salon",
            "type":"Services"
        }
    ],
    "sg:phone":"+1 718 842 8598",
    "sg:postcode":"10472",
    "sg:province":"NY",
    "wof:name":"Salon Joaly Unisex",
    "wof:placetype":"venue"
},
  "geometry": {"coordinates":[-73.879211,40.825993],"type":"Point"}
}