{
  "type": "Feature",
  "properties": {
    "iso:country":"US",
    "sg:address":"601 Dutchess Tpke",
    "sg:city":"Poughkeepsie",
    "sg:classifiers":[
        {
            "category":"Education",
            "subcategory":"School",
            "type":"Public Place"
        }
    ],
    "sg:phone":"+1 845 486 4480",
    "sg:postcode":"12603",
    "sg:province":"NY",
    "sg:website":"www.arlingtonschools.org",
    "wof:name":"Arlington Middle School",
    "wof:placetype":"venue"
},
  "geometry": {"coordinates":[-73.844989,41.723362],"type":"Point"}
}