{
  "type": "Feature",
  "properties": {
    "addr:full":"501 S James St Rome NY 13440",
    "addr:housenumber":"501",
    "addr:postcode":"13440",
    "addr:street":"S James St",
    "iso:country":"US",
    "sg:address":"501 S James St",
    "sg:city":"Rome",
    "sg:classifiers":[
        {
            "category":"Building & Trades",
            "subcategory":"Construction",
            "type":"Services"
        }
    ],
    "sg:phone":"+1 315 336 7700",
    "sg:postcode":"13440",
    "sg:province":"NY",
    "sg:tags":[
        "general",
        "contractor"
    ],
    "wof:name":"Charles Kotary General Contr",
    "wof:placetype":"venue"
},
  "geometry": {"coordinates":[-75.46335500000001,43.205304],"type":"Point"}
}