{
  "type": "Feature",
  "properties": {
    "addr:full":"8 Brunswick Rd Troy NY 12180",
    "addr:housenumber":"8",
    "addr:postcode":"12180",
    "addr:street":"Brunswick Rd",
    "iso:country":"US",
    "sg:address":"8 Brunswick Rd",
    "sg:city":"Troy",
    "sg:classifiers":[
        {
            "category":"Professional",
            "subcategory":"Business Services",
            "type":"Services"
        }
    ],
    "sg:phone":"+1 518 274 5475",
    "sg:postcode":"12180",
    "sg:province":"NY",
    "sg:tags":[
        "recording",
        "independent",
        "label"
    ],
    "wof:name":"Dorian Recordings Tm",
    "wof:placetype":"venue"
},
  "geometry": {"coordinates":[-73.668066,42.722315],"type":"Point"}
}