{
  "type": "Feature",
  "properties": {
    "addr:full":"8644 18th Ave Brooklyn NY 11214",
    "addr:housenumber":"8644",
    "addr:postcode":"11214",
    "addr:street":"18Th Ave",
    "iso:country":"US",
    "sg:address":"8644 18th Ave",
    "sg:city":"Brooklyn",
    "sg:classifiers":[
        {
            "category":"Banks & Credit Unions",
            "subcategory":"Bank",
            "type":"Services"
        }
    ],
    "sg:phone":"+1 718 331 8300",
    "sg:postcode":"11214",
    "sg:province":"NY",
    "wof:name":"Criers Federal Credit Union",
    "wof:placetype":"venue"
},
  "geometry": {"coordinates":[-74.00369999999999,40.606499],"type":"Point"}
}