{
  "type": "Feature",
  "properties": {
    "iso:country":"US",
    "sg:address":"10 Dunwoodie St",
    "sg:city":"Scarsdale",
    "sg:classifiers":[
        {
            "category":"Building & Trades",
            "subcategory":"Construction",
            "type":"Services"
        }
    ],
    "sg:phone":"+1 914 723 8383",
    "sg:postcode":"10583",
    "sg:province":"NY",
    "sg:tags":[
        "general",
        "contractor"
    ],
    "sg:website":"www.thedevelopmentteam.com",
    "wof:name":"TDT Inc",
    "wof:placetype":"venue"
},
  "geometry": {"coordinates":[-73.804959,40.976114],"type":"Point"}
}