{
  "type": "Feature",
  "properties": {
    "addr:full":"8258 Main St Little Genesee NY 14715",
    "addr:housenumber":"8258",
    "addr:postcode":"14715",
    "addr:street":"Main St",
    "iso:country":"US",
    "sg:address":"8258 Main St",
    "sg:city":"Little Genesee",
    "sg:classifiers":[
        {
            "category":"Government",
            "subcategory":"Post Office",
            "type":"Public Place"
        }
    ],
    "sg:phone":"+1 585 928 1242",
    "sg:postcode":"14715",
    "sg:province":"NY",
    "wof:name":"US Post Office",
    "wof:placetype":"venue"
},
  "geometry": {"coordinates":[-78.205995,42.026939],"type":"Point"}
}