{
  "type": "Feature",
  "properties": {
    "iso:country":"US",
    "sg:address":"8012 Transit Rd",
    "sg:city":"Buffalo",
    "sg:classifiers":[
        {
            "category":"Recreation",
            "type":"Entertainment"
        }
    ],
    "sg:phone":"+1 716 565 9261",
    "sg:postcode":"14221",
    "sg:province":"NY",
    "sg:tags":[
        "amusement"
    ],
    "wof:name":"Gymboree Play & Music Ctr",
    "wof:placetype":"venue"
},
  "geometry": {"coordinates":[-78.697019,42.984209],"type":"Point"}
}