{
  "type": "Feature",
  "properties": {
    "iso:country":"US",
    "sg:address":"225 Adams St",
    "sg:city":"Brooklyn",
    "sg:classifiers":[
        {
            "category":"Professional",
            "subcategory":"Lawyer & Legal Services",
            "type":"Services"
        }
    ],
    "sg:phone":"+1 718 979 8068",
    "sg:postcode":"11201",
    "sg:province":"NY",
    "sg:tags":[
        "attorney"
    ],
    "wof:name":"Dellicato & Hiatt Atty",
    "wof:placetype":"venue"
},
  "geometry": {"coordinates":[-73.98853800000001,40.698034],"type":"Point"}
}