{
  "type": "Feature",
  "properties": {
    "addr:full":"58 W 2nd St Fulton NY 13069",
    "addr:housenumber":"58",
    "addr:postcode":"13069",
    "addr:street":"W 2Nd St",
    "iso:country":"US",
    "sg:address":"58 W 2nd St",
    "sg:city":"Fulton",
    "sg:classifiers":[
        {
            "category":"Wholesale",
            "subcategory":"Non-durable Goods",
            "type":"Manufacturing & Wholesale Goods"
        }
    ],
    "sg:phone":"+1 315 592 7065",
    "sg:postcode":"13069",
    "sg:province":"NY",
    "wof:name":"Mark Woodward Distribution",
    "wof:placetype":"venue"
},
  "geometry": {"coordinates":[-76.423075,43.32136],"type":"Point"}
}