{
  "type": "Feature",
  "properties": {
    "iso:country":"US",
    "sg:address":"335 Torrance Ave",
    "sg:city":"Vestal",
    "sg:classifiers":[
        {
            "category":"Wholesale",
            "subcategory":"Toys & Hobbies",
            "type":"Manufacturing & Wholesale Goods"
        }
    ],
    "sg:phone":"+1 607 748 4665",
    "sg:postcode":"13850",
    "sg:province":"NY",
    "wof:name":"John Wirthba Jay Renaissance",
    "wof:placetype":"venue"
},
  "geometry": {"coordinates":[-76.064812,42.080687],"type":"Point"}
}