{
  "type": "Feature",
  "properties": {
    "iso:country":"US",
    "sg:address":"732 N Wellwood Ave",
    "sg:city":"Lindenhurst",
    "sg:classifiers":[
        {
            "category":"Restaurant",
            "type":"Food & Drink"
        }
    ],
    "sg:phone":"+1 631 226 9664",
    "sg:postcode":"11757",
    "sg:province":"NY",
    "sg:tags":[
        "delicatessen"
    ],
    "wof:name":"Deli's Right Inc",
    "wof:placetype":"venue"
},
  "geometry": {"coordinates":[-73.38628,40.703672],"type":"Point"}
}