{
  "type": "Feature",
  "properties": {
    "iso:country":"US",
    "sg:address":"310 Hallock Ave",
    "sg:city":"Port Jeffrsn Sta",
    "sg:classifiers":[
        {
            "category":"Manufacturing",
            "subcategory":"Jewelry",
            "type":"Manufacturing & Wholesale Goods"
        }
    ],
    "sg:phone":"+1 631 473 3344",
    "sg:postcode":"11776",
    "sg:province":"NY",
    "sg:website":"www.billfoxco.com",
    "wof:name":"Bill Fox Balfour Co",
    "wof:placetype":"venue"
},
  "geometry": {"coordinates":[-73.048619,40.931952],"type":"Point"}
}