{
  "type": "Feature",
  "properties": {
    "iso:country":"US",
    "sg:address":"7780 Transit Rd",
    "sg:city":"Buffalo",
    "sg:phone":"+1 716 634 2240",
    "sg:postcode":"14221",
    "sg:province":"NY",
    "sg:website":"http://www.theanimalhospitable.com",
    "wof:name":"Animal Hospitable Vet Clinic - Teresa Labuszewski DVM",
    "wof:placetype":"venue"
},
  "geometry": {"coordinates":[-78.696917,42.980058],"type":"Point"}
}