{
  "type": "Feature",
  "properties": {
    "addr:full":"670 Franklin St Ste 101 Schenectady NY 12305",
    "addr:housenumber":"670",
    "addr:postcode":"12305",
    "addr:street":"Franklin St Ste 101",
    "iso:country":"US",
    "sg:address":"670 Franklin St Ste 101",
    "sg:city":"Schenectady",
    "sg:classifiers":[
        {
            "category":"Health Services",
            "subcategory":"Doctor",
            "type":"Services"
        },
        {
            "category":"Health Services",
            "subcategory":"Health Practitioner",
            "type":"Services"
        }
    ],
    "sg:phone":"+1 518 370 0066",
    "sg:postcode":"12305",
    "sg:province":"NY",
    "sg:tags":[
        "physician",
        "surgeon",
        "surgeons",
        "ophthalmology"
    ],
    "wof:name":"N W Verola Md",
    "wof:placetype":"venue"
},
  "geometry": {"coordinates":[-73.936226,42.811687],"type":"Point"}
}