{
  "type": "Feature",
  "properties": {
    "addr:full":"955 Buffalo Rd Rochester NY 14624",
    "addr:housenumber":"955",
    "addr:postcode":"14624",
    "addr:street":"Buffalo Rd",
    "iso:country":"US",
    "sg:address":"955 Buffalo Rd",
    "sg:city":"Rochester",
    "sg:classifiers":[
        {
            "category":"Personal",
            "subcategory":"Tattoo Parlor",
            "type":"Services"
        }
    ],
    "sg:phone":"+1 585 697 3970",
    "sg:postcode":"14624",
    "sg:province":"NY",
    "sg:tags":[
        "tattooing"
    ],
    "wof:name":"Inksation Tattoos",
    "wof:placetype":"venue"
},
  "geometry": {"coordinates":[-77.67836200000001,43.149953],"type":"Point"}
}