{
  "type": "Feature",
  "properties": {
    "iso:country":"US",
    "sg:address":"1735 Central Ave",
    "sg:city":"Albany",
    "sg:classifiers":[
        {
            "category":"Health Services",
            "subcategory":"Doctor",
            "type":"Services"
        }
    ],
    "sg:phone":"+1 518 869 9453",
    "sg:postcode":"12205",
    "sg:province":"NY",
    "sg:tags":[
        "dentist"
    ],
    "wof:name":"Stephen A Harris DDS",
    "wof:placetype":"venue"
},
  "geometry": {"coordinates":[-73.842,42.725645],"type":"Point"}
}