{
  "type": "Feature",
  "properties": {
    "iso:country":"US",
    "sg:address":"1797 Prospect Place",
    "sg:city":"Brooklyn",
    "sg:classifiers":[
        {
            "category":"Food & Beverages",
            "subcategory":"Groceries & Convenience Stores",
            "type":"Retail Goods"
        }
    ],
    "sg:phone":"+1 718 922 2702",
    "sg:postcode":"11233",
    "sg:province":"NY",
    "wof:name":"Prospect Pl Mini Market",
    "wof:placetype":"venue"
},
  "geometry": {"coordinates":[-73.916999,40.67253],"type":"Point"}
}