{
  "type": "Feature",
  "properties": {
    "iso:country":"US",
    "sg:address":"358 Main St",
    "sg:city":"Arcade",
    "sg:classifiers":[
        {
            "category":"Retail",
            "subcategory":"Funeral Services",
            "type":"Services"
        }
    ],
    "sg:phone":"+1   ",
    "sg:postcode":"14009",
    "sg:province":"NY",
    "sg:tags":[
        "home"
    ],
    "wof:name":"W S Davis Inc",
    "wof:placetype":"venue"
},
  "geometry": {"coordinates":[-78.424677,42.533823],"type":"Point"}
}