{
  "type": "Feature",
  "properties": {
    "iso:country":"US",
    "sg:address":"65 Clyde Ave",
    "sg:city":"Buffalo",
    "sg:classifiers":[
        {
            "category":"Wholesale",
            "subcategory":"Scrap",
            "type":"Manufacturing & Wholesale Goods"
        }
    ],
    "sg:phone":"+1 716 831 7091",
    "sg:postcode":"14215",
    "sg:province":"NY",
    "sg:tags":[
        "recycling",
        "center"
    ],
    "wof:name":"Gemus Inc",
    "wof:placetype":"venue"
},
  "geometry": {"coordinates":[-78.823654,42.936746],"type":"Point"}
}