{
  "type": "Feature",
  "properties": {
    "iso:country":"US",
    "sg:address":"360 Pulaski St",
    "sg:city":"Brooklyn",
    "sg:classifiers":[
        {
            "category":"Social Services",
            "subcategory":"Child Care",
            "type":"Services"
        }
    ],
    "sg:phone":"+1 718 455 5137",
    "sg:postcode":"11206",
    "sg:province":"NY",
    "sg:tags":[
        "day"
    ],
    "wof:name":"Bethune Mary McLeod Day Care Cntr Inc",
    "wof:placetype":"venue"
},
  "geometry": {"coordinates":[-73.93609600000001,40.693802],"type":"Point"}
}