{
  "type": "Feature",
  "properties": {
    "addr:full":"23 Broadway Rocky Point NY 11778",
    "addr:housenumber":"23",
    "addr:postcode":"11778",
    "addr:street":"Broadway",
    "iso:country":"US",
    "sg:address":"23 Broadway",
    "sg:city":"Rocky Point",
    "sg:classifiers":[
        {
            "category":"Personal",
            "subcategory":"Beauty Salon",
            "type":"Services"
        }
    ],
    "sg:phone":"+1 631 821 6407",
    "sg:postcode":"11778",
    "sg:province":"NY",
    "wof:name":"Elegant Touch Nail Care",
    "wof:placetype":"venue"
},
  "geometry": {"coordinates":[-72.923615,40.948271],"type":"Point"}
}