{
  "type": "Feature",
  "properties": {
    "iso:country":"US",
    "sg:address":"466 Central Ave",
    "sg:city":"Cedarhurst",
    "sg:classifiers":[
        {
            "category":"Real Estate",
            "subcategory":"Real Estate Agent",
            "type":"Services"
        }
    ],
    "sg:phone":"+1 516 295 0819",
    "sg:postcode":"11516",
    "sg:province":"NY",
    "wof:name":"Hirth Real Estate",
    "wof:placetype":"venue"
},
  "geometry": {"coordinates":[-73.724141,40.621493],"type":"Point"}
}