{
  "type": "Feature",
  "properties": {
    "addr:full":"160 Greenwich Ave Goshen NY 10924",
    "addr:housenumber":"160",
    "addr:postcode":"10924",
    "addr:street":"Greenwich Ave",
    "iso:country":"US",
    "sg:address":"160 Greenwich Ave",
    "sg:city":"Goshen",
    "sg:classifiers":[
        {
            "category":"Wholesale",
            "subcategory":"Computers",
            "type":"Manufacturing & Wholesale Goods"
        },
        {
            "category":"Internet Cafe",
            "subcategory":"None",
            "type":"Food & Drink"
        },
        {
            "category":"Professional",
            "subcategory":"Business Services",
            "type":"Services"
        },
        {
            "category":"Professional",
            "subcategory":"Computer Services",
            "type":"Services"
        }
    ],
    "sg:phone":"+1 845 291 7202",
    "sg:postcode":"10924",
    "sg:province":"NY",
    "sg:tags":[
        "product",
        "coach",
        "network",
        "consultant",
        "system",
        "designer",
        "design",
        "software"
    ],
    "wof:name":"J & J It Consulting Services Inc",
    "wof:placetype":"venue"
},
  "geometry": {"coordinates":[-74.326205,41.400728],"type":"Point"}
}