{
  "type": "Feature",
  "properties": {
    "addr:full":"410 Park Ave Huntington NY 11743",
    "addr:housenumber":"410",
    "addr:postcode":"11743",
    "addr:street":"Park Ave",
    "iso:country":"US",
    "sg:address":"410 Park Ave",
    "sg:city":"Huntington",
    "sg:classifiers":[
        {
            "category":"Food & Beverages",
            "subcategory":"Groceries & Convenience Stores",
            "type":"Retail Goods"
        }
    ],
    "sg:phone":"+1   ",
    "sg:postcode":"11743",
    "sg:province":"NY",
    "sg:tags":[
        "alcoholic"
    ],
    "wof:name":"Park Avenue Deli",
    "wof:placetype":"venue"
},
  "geometry": {"coordinates":[-73.412998,40.874325],"type":"Point"}
}