{
  "type": "Feature",
  "properties": {
    "addr:full":"156 30th St Brooklyn NY 11232",
    "addr:housenumber":"156",
    "addr:postcode":"11232",
    "addr:street":"30Th St",
    "iso:country":"US",
    "sg:address":"156 30th St",
    "sg:city":"Brooklyn",
    "sg:classifiers":[
        {
            "category":"Building & Trades",
            "subcategory":"Plumbing",
            "type":"Services"
        }
    ],
    "sg:phone":"+1 718 965 3293",
    "sg:postcode":"11232",
    "sg:province":"NY",
    "sg:tags":[
        "contractor"
    ],
    "wof:name":"Comfort Specialty Co",
    "wof:placetype":"venue"
},
  "geometry": {"coordinates":[-74.002163,40.658553],"type":"Point"}
}