{
  "type": "Feature",
  "properties": {
    "addr:full":"63 Eagle Valley Rd Sloatsburg NY 10974",
    "addr:housenumber":"63",
    "addr:postcode":"10974",
    "addr:street":"Eagle Valley Rd",
    "iso:country":"US",
    "sg:address":"63 Eagle Valley Rd",
    "sg:city":"Sloatsburg",
    "sg:classifiers":[
        {
            "category":"Professional",
            "subcategory":"Management & Consulting",
            "type":"Services"
        }
    ],
    "sg:phone":"+1   ",
    "sg:postcode":"10974",
    "sg:province":"NY",
    "sg:tags":[
        "public",
        "relations"
    ],
    "wof:name":"Werpr Co",
    "wof:placetype":"venue"
},
  "geometry": {"coordinates":[-74.204975,41.158391],"type":"Point"}
}