{
  "type": "Feature",
  "properties": {
    "addr:full":"5 Greenhouse Cir Port Chester NY 10573",
    "addr:housenumber":"5",
    "addr:postcode":"10573",
    "addr:street":"Greenhouse Cir",
    "iso:country":"US",
    "sg:address":"5 Greenhouse Cir",
    "sg:city":"Port Chester",
    "sg:classifiers":[
        {
            "category":"Professional",
            "subcategory":"Lawyer & Legal Services",
            "type":"Services"
        }
    ],
    "sg:phone":"+1   ",
    "sg:postcode":"10573",
    "sg:province":"NY",
    "wof:name":"Lawrence Lever Atty At",
    "wof:placetype":"venue"
},
  "geometry": {"coordinates":[-73.68494800000001,41.018455],"type":"Point"}
}