{
  "type": "Feature",
  "properties": {
    "addr:full":"97 Pound Hollow Rd Glen Head NY 11545",
    "addr:housenumber":"97",
    "addr:postcode":"11545",
    "addr:street":"Pound Hollow Rd",
    "iso:country":"US",
    "sg:address":"97 Pound Hollow Rd",
    "sg:city":"Glen Head",
    "sg:classifiers":[
        {
            "category":"Insurance",
            "subcategory":"Insurance Agent",
            "type":"Services"
        }
    ],
    "sg:phone":"+1 516 609 9335",
    "sg:postcode":"11545",
    "sg:province":"NY",
    "wof:name":"Simplon Enterprises",
    "wof:placetype":"venue"
},
  "geometry": {"coordinates":[-73.605953,40.846489],"type":"Point"}
}