{
  "type": "Feature",
  "properties": {
    "addr:full":"11 E 26th Street New York NY 10010",
    "addr:housenumber":"11",
    "addr:postcode":"10010",
    "addr:street":"E 26Th Street",
    "iso:country":"US",
    "sg:address":"11 E 26th Street",
    "sg:city":"New York",
    "sg:classifiers":[
        {
            "category":"Professional",
            "subcategory":"Lawyer & Legal Services",
            "type":"Services"
        }
    ],
    "sg:phone":"+1 212 490 3232",
    "sg:postcode":"10010",
    "sg:province":"NY",
    "wof:name":"Hecht and Associates",
    "wof:placetype":"venue"
},
  "geometry": {"coordinates":[-73.987602,40.74322],"type":"Point"}
}