{
  "type": "Feature",
  "properties": {
    "addr:full":"1110 Manhattan Ave Brooklyn NY 11222",
    "addr:housenumber":"1110",
    "addr:postcode":"11222",
    "addr:street":"Manhattan Ave",
    "iso:country":"US",
    "sg:address":"1110 Manhattan Ave",
    "sg:city":"Brooklyn",
    "sg:classifiers":[
        {
            "category":"Coffee & Tea",
            "type":"Food & Drink"
        },
        {
            "category":"Food & Beverages",
            "subcategory":"Bakery",
            "type":"Retail Goods"
        }
    ],
    "sg:postcode":"11222",
    "sg:province":"NY",
    "sg:tags":[
        "sandwich"
    ],
    "wof:name":"Milk and Roses",
    "wof:placetype":"venue"
},
  "geometry": {"coordinates":[-73.954938,40.736403],"type":"Point"}
}