{
  "type": "Feature",
  "properties": {
    "iso:country":"US",
    "sg:address":"125 E 57th St",
    "sg:city":"New York",
    "sg:classifiers":[
        {
            "category":"Shopping",
            "subcategory":"Clothing, Apparel, & Fashions",
            "type":"Retail Goods"
        }
    ],
    "sg:phone":"+1 212 376 4477",
    "sg:postcode":"10022",
    "sg:province":"NY",
    "sg:website":"www.daffys.com",
    "wof:name":"Daffy's",
    "wof:placetype":"venue"
},
  "geometry": {"coordinates":[-73.96991300000001,40.761448],"type":"Point"}
}