{
  "type": "Feature",
  "properties": {
    "addr:full":"5 Notus Ave Staten Island NY 10312",
    "addr:housenumber":"5",
    "addr:postcode":"10312",
    "addr:street":"Notus Ave",
    "iso:country":"US",
    "sg:address":"5 Notus Ave",
    "sg:city":"Staten Island",
    "sg:classifiers":[
        {
            "category":"Building & Trades",
            "subcategory":"Pest Control",
            "type":"Services"
        }
    ],
    "sg:phone":"+1 718 984 5708",
    "sg:postcode":"10312",
    "sg:province":"NY",
    "wof:name":"All Pro Termite & Pest Control",
    "wof:placetype":"venue"
},
  "geometry": {"coordinates":[-74.17528799999999,40.550896],"type":"Point"}
}