{
  "type": "Feature",
  "properties": {
    "iso:country":"US",
    "sg:address":"165 S Broad St",
    "sg:city":"Norwich",
    "sg:classifiers":[
        {
            "category":"Restaurant",
            "type":"Food & Drink"
        }
    ],
    "sg:phone":"+1 607 334 6020",
    "sg:postcode":"13815",
    "sg:province":"NY",
    "wof:name":"Mc Donald's",
    "wof:placetype":"venue"
},
  "geometry": {"coordinates":[-75.522784,42.52042],"type":"Point"}
}