{
  "type": "Feature",
  "properties": {
    "iso:country":"US",
    "sg:address":"70 Heritage Cir",
    "sg:city":"Rochester",
    "sg:classifiers":[
        {
            "category":"Social Services",
            "type":"Services"
        },
        {
            "category":"Organizations",
            "subcategory":"Community Association",
            "type":"Services"
        }
    ],
    "sg:phone":"+1 585 723 2257",
    "sg:postcode":"14615",
    "sg:province":"NY",
    "sg:website":"http://www.kiwanisfwb.org",
    "wof:name":"Kiwanis Club Of Nw Roches",
    "wof:placetype":"venue"
},
  "geometry": {"coordinates":[-77.662628,43.228808],"type":"Point"}
}