{
  "type": "Feature",
  "properties": {
    "addr:full":"22 Metropolitan Ave Middle Village NY 11379",
    "addr:housenumber":"22",
    "addr:postcode":"11379",
    "addr:street":"Metropolitan Ave",
    "iso:country":"US",
    "sg:address":"22 Metropolitan Ave",
    "sg:city":"Middle Village",
    "sg:classifiers":[
        {
            "category":"Personal",
            "type":"Services"
        }
    ],
    "sg:phone":"+1   ",
    "sg:postcode":"11379",
    "sg:province":"NY",
    "sg:tags":[
        "a",
        "custom",
        "tailor",
        "wear",
        "rental",
        "formal"
    ],
    "wof:name":"Van Dons Formal Wr & Cstm Tlrg",
    "wof:placetype":"venue"
},
  "geometry": {"coordinates":[-73.895904,40.712506],"type":"Point"}
}