{
  "type": "Feature",
  "properties": {
    "addr:full":"394 State Hwy 264 Phoenix NY 13135",
    "addr:housenumber":"394",
    "addr:postcode":"13135",
    "addr:street":"State Hwy 264",
    "iso:country":"US",
    "sg:address":"394 State Hwy 264",
    "sg:city":"Phoenix",
    "sg:classifiers":[
        {
            "category":"Shopping",
            "subcategory":"Clothing, Apparel, & Fashions",
            "type":"Retail Goods"
        }
    ],
    "sg:phone":"+1 315 695 3992",
    "sg:postcode":"13135",
    "sg:province":"NY",
    "sg:tags":[
        "tailor"
    ],
    "wof:name":"Sewing Place",
    "wof:placetype":"venue"
},
  "geometry": {"coordinates":[-76.301034,43.264381],"type":"Point"}
}