{
  "type": "Feature",
  "properties": {
    "iso:country":"US",
    "sg:address":"355 Bleecker St",
    "sg:city":"New York",
    "sg:classifiers":[
        {
            "category":"Restaurant",
            "type":"Food & Drink"
        }
    ],
    "sg:phone":"+1 212 242 3271",
    "sg:postcode":"10014",
    "sg:province":"NY",
    "sg:tags":[
        "delicatessen"
    ],
    "wof:name":"Bleeker Mini Mart",
    "wof:placetype":"venue"
},
  "geometry": {"coordinates":[-74.004633,40.73449],"type":"Point"}
}