{
  "type": "Feature",
  "properties": {
    "iso:country":"US",
    "sg:address":"305 Delaware Ave",
    "sg:city":"Buffalo",
    "sg:classifiers":[
        {
            "category":"Professional",
            "subcategory":"Accounting & Tax Preparation",
            "type":"Services"
        }
    ],
    "sg:phone":"+1   ",
    "sg:postcode":"14202",
    "sg:province":"NY",
    "wof:name":"Marilyn Royer CPA",
    "wof:placetype":"venue"
},
  "geometry": {"coordinates":[-78.876068,42.892482],"type":"Point"}
}