{
  "type": "Feature",
  "properties": {
    "addr:full":"850 Zerega Ave Bronx NY 10473",
    "addr:housenumber":"850",
    "addr:postcode":"10473",
    "addr:street":"Zerega Ave",
    "iso:country":"US",
    "sg:address":"850 Zerega Ave",
    "sg:city":"Bronx",
    "sg:classifiers":[
        {
            "category":"Utilities",
            "subcategory":"Refuse",
            "type":"Services"
        }
    ],
    "sg:phone":"+1   ",
    "sg:postcode":"10473",
    "sg:province":"NY",
    "sg:tags":[
        "management",
        "system"
    ],
    "wof:name":"Department of Sanitation Dist",
    "wof:placetype":"venue"
},
  "geometry": {"coordinates":[-73.84295299999999,40.824576],"type":"Point"}
}