{
  "type": "Feature",
  "properties": {
    "iso:country":"US",
    "sg:address":"1352 Long Pond Rd",
    "sg:city":"Rochester",
    "sg:classifiers":[
        {
            "category":"Shopping",
            "subcategory":"Gifts & Souvenirs",
            "type":"Retail Goods"
        }
    ],
    "sg:phone":"+1 585 227 1010",
    "sg:postcode":"14626",
    "sg:province":"NY",
    "sg:tags":[
        "shop"
    ],
    "wof:name":"Spencer Gifts 102",
    "wof:placetype":"venue"
},
  "geometry": {"coordinates":[-77.697581,43.202676],"type":"Point"}
}