{
  "type": "Feature",
  "properties": {
    "addr:full":"36 Chestnut Ln Woodbury NY 11797",
    "addr:housenumber":"36",
    "addr:postcode":"11797",
    "addr:street":"Chestnut Ln",
    "iso:country":"US",
    "sg:address":"36 Chestnut Ln",
    "sg:city":"Woodbury",
    "sg:classifiers":[
        {
            "category":"Shopping",
            "subcategory":"Clothing, Apparel, & Fashions",
            "type":"Retail Goods"
        }
    ],
    "sg:phone":"+1 516 677 5492",
    "sg:postcode":"11797",
    "sg:province":"NY",
    "wof:name":"Long Island Women's Agenda",
    "wof:placetype":"venue"
},
  "geometry": {"coordinates":[-73.480287,40.813322],"type":"Point"}
}