{
  "type": "Feature",
  "properties": {
    "iso:country":"US",
    "sg:address":"803 Montauk Hwy Unit F",
    "sg:city":"Shirley",
    "sg:classifiers":[
        {
            "category":"Arena",
            "subcategory":"Sports Club",
            "type":"Entertainment"
        }
    ],
    "sg:phone":"+1 631 281 5425",
    "sg:postcode":"11967",
    "sg:province":"NY",
    "sg:tags":[
        "martial art"
    ],
    "wof:name":"Vitale Karate Academy",
    "wof:placetype":"venue"
},
  "geometry": {"coordinates":[-72.86952100000001,40.801047],"type":"Point"}
}