{
  "type": "Feature",
  "properties": {
    "addr:full":"6 Willis Ave Syosset NY 11791",
    "addr:housenumber":"6",
    "addr:postcode":"11791",
    "addr:street":"Willis Ave",
    "iso:country":"US",
    "sg:address":"6 Willis Ave",
    "sg:city":"Syosset",
    "sg:classifiers":[
        {
            "category":"Professional",
            "subcategory":"Business Services",
            "type":"Services"
        }
    ],
    "sg:phone":"+1   ",
    "sg:postcode":"11791",
    "sg:province":"NY",
    "sg:tags":[
        "group"
    ],
    "wof:name":"Eagle Eye Enterprises Inc",
    "wof:placetype":"venue"
},
  "geometry": {"coordinates":[-73.50444899999999,40.822358],"type":"Point"}
}