{
  "type": "Feature",
  "properties": {
    "addr:full":"485 Washington Ave Ste 5 Pleasantville NY 10570",
    "addr:housenumber":"485",
    "addr:postcode":"10570",
    "addr:street":"Washington Ave Ste 5",
    "iso:country":"US",
    "sg:address":"485 Washington Ave Ste 5",
    "sg:city":"Pleasantville",
    "sg:classifiers":[
        {
            "category":"Professional",
            "subcategory":"Engineering",
            "type":"Services"
        },
        {
            "category":"Professional",
            "subcategory":"Computer Services",
            "type":"Services"
        }
    ],
    "sg:phone":"+1 914 773 1130",
    "sg:postcode":"10570",
    "sg:province":"NY",
    "sg:tags":[
        "designer",
        "consultant",
        "isp",
        "integration",
        "system",
        "internet",
        "provider",
        "engineer"
    ],
    "sg:website":"http://www.firstmall.com",
    "wof:name":"Computer Net",
    "wof:placetype":"venue"
},
  "geometry": {"coordinates":[-73.782892,41.148025],"type":"Point"}
}