{
  "type": "Feature",
  "properties": {
    "addr:full":"855 Central Ave Albany NY 12206",
    "addr:housenumber":"855",
    "addr:postcode":"12206",
    "addr:street":"Central Ave",
    "iso:country":"US",
    "sg:address":"855 Central Ave",
    "sg:city":"Albany",
    "sg:classifiers":[
        {
            "category":"Real Estate",
            "subcategory":"Real Estate Agent",
            "type":"Services"
        }
    ],
    "sg:phone":"+1 518 486 8478",
    "sg:postcode":"12206",
    "sg:province":"NY",
    "sg:tags":[
        "management"
    ],
    "wof:name":"West Mall Ofc Plz",
    "wof:placetype":"venue"
},
  "geometry": {"coordinates":[-73.787892,42.678194],"type":"Point"}
}