{
  "type": "Feature",
  "properties": {
    "addr:full":"1188 Rhinelander Ave Bronx NY 10461",
    "addr:housenumber":"1188",
    "addr:postcode":"10461",
    "addr:street":"Rhinelander Ave",
    "iso:country":"US",
    "sg:address":"1188 Rhinelander Ave",
    "sg:city":"Bronx",
    "sg:classifiers":[
        {
            "category":"Building & Trades",
            "subcategory":"Construction",
            "type":"Services"
        }
    ],
    "sg:phone":"+1 718 931 5435",
    "sg:postcode":"10461",
    "sg:province":"NY",
    "sg:tags":[
        "painter"
    ],
    "wof:name":"J & M Interiors Inc",
    "wof:placetype":"venue"
},
  "geometry": {"coordinates":[-73.85064199999999,40.853156],"type":"Point"}
}