{
  "type": "Feature",
  "properties": {
    "iso:country":"US",
    "sg:address":"7 Skylark Dr",
    "sg:city":"Spring Valley",
    "sg:classifiers":[
        {
            "category":"Professional",
            "subcategory":"Management & Consulting",
            "type":"Services"
        }
    ],
    "sg:phone":"+1 845 354 2229",
    "sg:postcode":"10977",
    "sg:province":"NY",
    "sg:tags":[
        "business"
    ],
    "wof:name":"Professional Audio Labs Inc",
    "wof:placetype":"venue"
},
  "geometry": {"coordinates":[-74.05761099999999,41.149125],"type":"Point"}
}