{
  "type": "Feature",
  "properties": {
    "iso:country":"US",
    "sg:address":"76 West Ave",
    "sg:city":"Lockport",
    "sg:classifiers":[
        {
            "category":"Professional",
            "subcategory":"Accounting & Tax Preparation",
            "type":"Services"
        }
    ],
    "sg:phone":"+1 716 434 3733",
    "sg:postcode":"14094",
    "sg:province":"NY",
    "sg:tags":[
        "bookkeeping",
        "general"
    ],
    "wof:name":"Frank Cornell Assoc",
    "wof:placetype":"venue"
},
  "geometry": {"coordinates":[-78.69779,43.168657],"type":"Point"}
}