{
  "type": "Feature",
  "properties": {
    "addr:full":"1261 Broadway Lbby New York NY 10001",
    "addr:housenumber":"1261",
    "addr:postcode":"10001",
    "addr:street":"Broadway",
    "iso:country":"US",
    "sg:address":"1261 Broadway Lbby",
    "sg:city":"New York",
    "sg:classifiers":[
        {
            "category":"Professional",
            "subcategory":"Computer Services",
            "type":"Services"
        }
    ],
    "sg:phone":"+1 212 779 0800",
    "sg:postcode":"10001",
    "sg:province":"NY",
    "sg:tags":[
        "repair"
    ],
    "sg:website":"www.1strun.net",
    "wof:name":"1st Run Computer Svces",
    "wof:placetype":"venue"
},
  "geometry": {"coordinates":[-73.996213,40.750051],"type":"Point"}
}