{
  "type": "Feature",
  "properties": {
    "addr:full":"11 Devoe St Brooklyn NY 11211",
    "addr:housenumber":"11",
    "addr:postcode":"11211",
    "addr:street":"Devoe St",
    "iso:country":"US",
    "sg:address":"11 Devoe St",
    "sg:city":"Brooklyn",
    "sg:classifiers":[
        {
            "category":"Shopping",
            "subcategory":"Crafts & Fabrics",
            "type":"Retail Goods"
        }
    ],
    "sg:phone":"+1   ",
    "sg:postcode":"11211",
    "sg:province":"NY",
    "sg:tags":[
        "sewing"
    ],
    "wof:name":"Menger Mfg Co Horse Cloth",
    "wof:placetype":"venue"
},
  "geometry": {"coordinates":[-73.94960399999999,40.713349],"type":"Point"}
}