{
  "type": "Feature",
  "properties": {
    "iso:country":"US",
    "sg:address":"3736 Walden Ave",
    "sg:city":"Lancaster",
    "sg:classifiers":[
        {
            "category":"Building & Trades",
            "subcategory":"Construction",
            "type":"Services"
        }
    ],
    "sg:phone":"+1 716 684 7128",
    "sg:postcode":"14086",
    "sg:province":"NY",
    "sg:tags":[
        "fabricator",
        "metal"
    ],
    "wof:name":"Iron Art Cycles",
    "wof:placetype":"venue"
},
  "geometry": {"coordinates":[-78.66270900000001,42.917245],"type":"Point"}
}