{
  "type": "Feature",
  "properties": {
    "addr:full":"1228 Mead Rd Binghamton NY 13901",
    "addr:housenumber":"1228",
    "addr:postcode":"13901",
    "addr:street":"Mead Rd",
    "iso:country":"US",
    "sg:address":"1228 Mead Rd",
    "sg:city":"Binghamton",
    "sg:classifiers":[
        {
            "category":"Organizations",
            "subcategory":"Religious Organization",
            "type":"Services"
        }
    ],
    "sg:phone":"+1 607 722 0406",
    "sg:postcode":"13901",
    "sg:province":"NY",
    "sg:tags":[
        "clergy"
    ],
    "wof:name":"Thomas Olson",
    "wof:placetype":"venue"
},
  "geometry": {"coordinates":[-75.88239900000001,42.154852],"type":"Point"}
}