{
  "type": "Feature",
  "properties": {
    "iso:country":"US",
    "sg:address":"2146 Jackson Ave",
    "sg:city":"Seaford",
    "sg:classifiers":[
        {
            "category":"Social Services",
            "type":"Services"
        },
        {
            "category":"Health Services",
            "subcategory":"Clinic",
            "type":"Services"
        },
        {
            "category":"Health Services",
            "subcategory":"Health Practitioner",
            "type":"Services"
        }
    ],
    "sg:phone":"+1 516 679 9800",
    "sg:postcode":"11783",
    "sg:province":"NY",
    "sg:tags":[
        "information",
        "mental",
        "family",
        "abuse",
        "individual",
        "marriage",
        "drug",
        "child",
        "addiction",
        "counselor"
    ],
    "sg:website":"http://www.senassauguidancecenter.com",
    "wof:name":"Southeast Nassau Guidance Center",
    "wof:placetype":"venue"
},
  "geometry": {"coordinates":[-73.487257,40.669461],"type":"Point"}
}