{
  "type": "Feature",
  "properties": {
    "addr:full":"9 Clermont St Delmar NY 12054",
    "addr:housenumber":"9",
    "addr:postcode":"12054",
    "addr:street":"Clermont St",
    "iso:country":"US",
    "sg:address":"9 Clermont St",
    "sg:city":"Delmar",
    "sg:classifiers":[
        {
            "category":"Building & Trades",
            "subcategory":"Construction",
            "type":"Services"
        }
    ],
    "sg:phone":"+1 518 439 2833",
    "sg:postcode":"12054",
    "sg:province":"NY",
    "sg:tags":[
        "house"
    ],
    "wof:name":"A A A T Mullaney Contracting",
    "wof:placetype":"venue"
},
  "geometry": {"coordinates":[-73.810543,42.625197],"type":"Point"}
}