{
  "type": "Feature",
  "properties": {
    "iso:country":"US",
    "sg:address":"270 W 45 St",
    "sg:city":"New York",
    "sg:classifiers":[
        {
            "category":"Recreation",
            "type":"Entertainment"
        }
    ],
    "sg:phone":"+1 212 921 0054",
    "sg:postcode":"10036",
    "sg:province":"NY",
    "sg:tags":[
        "ticket"
    ],
    "wof:name":"Leblangs Theatre Tickets",
    "wof:placetype":"venue"
},
  "geometry": {"coordinates":[-73.987898,40.758802],"type":"Point"}
}