{
  "type": "Feature",
  "properties": {
    "addr:full":"15 Southdown Rd Huntington NY 11743",
    "addr:housenumber":"15",
    "addr:postcode":"11743",
    "addr:street":"Southdown Rd",
    "iso:country":"US",
    "sg:address":"15 Southdown Rd",
    "sg:city":"Huntington",
    "sg:classifiers":[
        {
            "category":"Banks & Credit Unions",
            "subcategory":"Bank",
            "type":"Services"
        }
    ],
    "sg:phone":"+1 631 271 6045",
    "sg:postcode":"11743",
    "sg:province":"NY",
    "sg:website":"www.citibank.com",
    "wof:name":"Citibank N A",
    "wof:placetype":"venue"
},
  "geometry": {"coordinates":[-73.426498,40.879902],"type":"Point"}
}