{
  "type": "Feature",
  "properties": {
    "addr:full":"1416 Kings Hwy Brooklyn NY 11229",
    "addr:housenumber":"1416",
    "addr:postcode":"11229",
    "addr:street":"Kings Hwy",
    "iso:country":"US",
    "sg:address":"1416 Kings Hwy",
    "sg:city":"Brooklyn",
    "sg:classifiers":[
        {
            "category":"Arts & Performance",
            "subcategory":"Theater",
            "type":"Entertainment"
        }
    ],
    "sg:phone":"+1 718 998 9131",
    "sg:postcode":"11229",
    "sg:province":"NY",
    "sg:tags":[
        "bureau"
    ],
    "wof:name":"Russian Entertainment & Whlsls",
    "wof:placetype":"venue"
},
  "geometry": {"coordinates":[-73.958353,40.608622],"type":"Point"}
}