{
  "type": "Feature",
  "properties": {
    "iso:country":"US",
    "sg:address":"2506 Pond Rd",
    "sg:city":"Ronkonkoma",
    "sg:classifiers":[
        {
            "category":"Autos & Motor Vehicles",
            "subcategory":"Automobile Sales",
            "type":"Retail Goods"
        }
    ],
    "sg:phone":"+1 631 226 5328",
    "sg:postcode":"11779",
    "sg:province":"NY",
    "sg:tags":[
        "limo"
    ],
    "wof:name":"Churchill Luxury Stretch Limousine",
    "wof:placetype":"venue"
},
  "geometry": {"coordinates":[-73.12018999999999,40.809895],"type":"Point"}
}