{
  "type": "Feature",
  "properties": {
    "iso:country":"US",
    "sg:address":"1600 Harrison Ave Ste 202",
    "sg:city":"Mamaroneck",
    "sg:classifiers":[
        {
            "category":"Shopping",
            "subcategory":"Jewelry",
            "type":"Retail Goods"
        },
        {
            "category":"Manufacturing",
            "subcategory":"Jewelry",
            "type":"Manufacturing & Wholesale Goods"
        }
    ],
    "sg:phone":"+1 914 381 5727",
    "sg:postcode":"10543",
    "sg:province":"NY",
    "sg:tags":[
        "manufacturer",
        "jewelers-wholesale",
        "jeweler"
    ],
    "wof:name":"Ap Creations",
    "wof:placetype":"venue"
},
  "geometry": {"coordinates":[-73.71884900000001,40.958759],"type":"Point"}
}