{
  "type": "Feature",
  "properties": {
    "addr:full":"491 State Hwy 299 Highland NY 12528",
    "addr:housenumber":"491",
    "addr:postcode":"12528",
    "addr:street":"State Hwy 299",
    "iso:country":"US",
    "sg:address":"491 State Hwy 299",
    "sg:city":"Highland",
    "sg:classifiers":[
        {
            "category":"Restaurant",
            "type":"Food & Drink"
        }
    ],
    "sg:phone":"+1 845 691 2128",
    "sg:postcode":"12528",
    "sg:province":"NY",
    "wof:name":"Blimpie Subs & Salads",
    "wof:placetype":"venue"
},
  "geometry": {"coordinates":[-74.025693,41.737306],"type":"Point"}
}