{
  "type": "Feature",
  "properties": {
    "addr:full":"1187 Lexington Ave New York NY 10028",
    "addr:housenumber":"1187",
    "addr:postcode":"10028",
    "addr:street":"Lexington Ave",
    "iso:country":"US",
    "sg:address":"1187 Lexington Ave",
    "sg:city":"New York",
    "sg:classifiers":[
        {
            "category":"Shopping",
            "type":"Retail Goods"
        }
    ],
    "sg:phone":"+1 212 737 5256",
    "sg:postcode":"10028",
    "sg:province":"NY",
    "sg:tags":[
        "coin",
        "dealer",
        "supply"
    ],
    "wof:name":"F H Coin & Stamp Exchange",
    "wof:placetype":"venue"
},
  "geometry": {"coordinates":[-73.95814,40.775752],"type":"Point"}
}