{
  "type": "Feature",
  "properties": {
    "iso:country":"US",
    "sg:address":"4625 North St",
    "sg:city":"Jamesville",
    "sg:classifiers":[
        {
            "category":"Restaurant",
            "type":"Food & Drink"
        }
    ],
    "sg:phone":"+1 315 469 8388",
    "sg:postcode":"13078",
    "sg:province":"NY",
    "sg:tags":[
        "asian",
        "chinese",
        "pan"
    ],
    "wof:name":"Chef Peking Restaurant",
    "wof:placetype":"venue"
},
  "geometry": {"coordinates":[-76.072084,42.99564],"type":"Point"}
}