{
  "type": "Feature",
  "properties": {
    "iso:country":"US",
    "sg:address":"333 E 56th Street",
    "sg:city":"New York",
    "sg:classifiers":[
        {
            "category":"Building & Trades",
            "subcategory":"Locksmith",
            "type":"Services"
        }
    ],
    "sg:phone":"+1 212 492 9576",
    "sg:postcode":"10022",
    "sg:province":"NY",
    "sg:tags":[
        "key"
    ],
    "wof:name":"Any 24 Hour Emergency Locksmith",
    "wof:placetype":"venue"
},
  "geometry": {"coordinates":[-73.964962,40.758302],"type":"Point"}
}