{
  "type": "Feature",
  "properties": {
    "addr:full":"1952 Town Line Rd Aurora NY 13026",
    "addr:housenumber":"1952",
    "addr:postcode":"13026",
    "addr:street":"Town Line Rd",
    "iso:country":"US",
    "sg:address":"1952 Town Line Rd",
    "sg:city":"Aurora",
    "sg:classifiers":[
        {
            "category":"Manufacturing",
            "subcategory":"Building Materials",
            "type":"Manufacturing & Wholesale Goods"
        }
    ],
    "sg:phone":"+1   ",
    "sg:postcode":"13026",
    "sg:province":"NY",
    "sg:tags":[
        "mfg",
        "wood",
        "kitchen",
        "cabinet"
    ],
    "wof:name":"A R D Quality Woodworking",
    "wof:placetype":"venue"
},
  "geometry": {"coordinates":[-76.61448900000001,42.753248],"type":"Point"}
}