{
  "type": "Feature",
  "properties": {
    "addr:full":"55 N Bourndale Rd Manhasset NY 11030",
    "addr:housenumber":"55",
    "addr:postcode":"11030",
    "addr:street":"N Bourndale Rd",
    "iso:country":"US",
    "sg:address":"55 N Bourndale Rd",
    "sg:city":"Manhasset",
    "sg:classifiers":[
        {
            "category":"Building & Trades",
            "subcategory":"Construction",
            "type":"Services"
        }
    ],
    "sg:phone":"+1 516 869 8829",
    "sg:postcode":"11030",
    "sg:province":"NY",
    "sg:tags":[
        "company"
    ],
    "wof:name":"F Construction Assoc NV",
    "wof:placetype":"venue"
},
  "geometry": {"coordinates":[-73.70286299999999,40.801518],"type":"Point"}
}