{
  "type": "Feature",
  "properties": {
    "iso:country":"US",
    "sg:address":"673 5th Ave",
    "sg:city":"New York",
    "sg:classifiers":[
        {
            "category":"Shopping",
            "subcategory":"Clothing, Apparel, & Fashions",
            "type":"Retail Goods"
        }
    ],
    "sg:phone":"+1 212 308 8688",
    "sg:postcode":"10022",
    "sg:province":"NY",
    "wof:name":"Blanc De Chine",
    "wof:placetype":"venue"
},
  "geometry": {"coordinates":[-73.975773,40.760505],"type":"Point"}
}