{
  "type": "Feature",
  "properties": {
    "iso:country":"US",
    "sg:address":"132 E Park Ave",
    "sg:city":"Long Beach",
    "sg:classifiers":[
        {
            "category":"Insurance",
            "subcategory":"Insurance Agent",
            "type":"Services"
        }
    ],
    "sg:phone":"+1 516 431 1464",
    "sg:postcode":"11561",
    "sg:province":"NY",
    "wof:name":"Mark Hudesman",
    "wof:placetype":"venue"
},
  "geometry": {"coordinates":[-73.658973,40.588447],"type":"Point"}
}