{
  "type": "Feature",
  "properties": {
    "iso:country":"US",
    "sg:address":"240 Pine Ridge Rd",
    "sg:city":"Buffalo",
    "sg:classifiers":[
        {
            "category":"Social Services",
            "subcategory":"Child Care",
            "type":"Services"
        },
        {
            "category":"Education",
            "subcategory":"University",
            "type":"Public Place"
        }
    ],
    "sg:phone":"+1 716 896 0700",
    "sg:postcode":"14225",
    "sg:province":"NY",
    "sg:tags":[
        "college",
        "day"
    ],
    "wof:name":"Villa Maria Inst of Music",
    "wof:placetype":"venue"
},
  "geometry": {"coordinates":[-78.796097,42.9119],"type":"Point"}
}