{
  "type": "Feature",
  "properties": {
    "addr:full":"37 Riverside Dr New York NY 10023",
    "addr:housenumber":"37",
    "addr:postcode":"10023",
    "addr:street":"Riverside Dr",
    "iso:country":"US",
    "sg:address":"37 Riverside Dr",
    "sg:city":"New York",
    "sg:classifiers":[
        {
            "category":"Professional",
            "type":"Services"
        },
        {
            "category":"Organizations",
            "subcategory":"Professional Association",
            "type":"Services"
        }
    ],
    "sg:phone":"+1 212 724 3710",
    "sg:postcode":"10023",
    "sg:province":"NY",
    "sg:tags":[
        "doctor"
    ],
    "wof:name":"Marcus & Samberg MDS PC",
    "wof:placetype":"venue"
},
  "geometry": {"coordinates":[-73.984596,40.782902],"type":"Point"}
}