{
  "type": "Feature",
  "properties": {
    "iso:country":"US",
    "sg:address":"349 S Delaware Ave",
    "sg:city":"Lindenhurst",
    "sg:classifiers":[
        {
            "category":"Home & Garden",
            "subcategory":"Building Materials",
            "type":"Retail Goods"
        },
        {
            "category":"Building & Trades",
            "subcategory":"Construction",
            "type":"Services"
        }
    ],
    "sg:phone":"+1 631 957 0703",
    "sg:postcode":"11757",
    "sg:province":"NY",
    "sg:tags":[
        "insulation",
        "contractor"
    ],
    "wof:name":"All Seasons Insulating",
    "wof:placetype":"venue"
},
  "geometry": {"coordinates":[-73.36196099999999,40.68552],"type":"Point"}
}