{
  "type": "Feature",
  "properties": {
    "iso:country":"US",
    "sg:address":"204 Saw Mill River Rd",
    "sg:city":"Elmsford",
    "sg:classifiers":[
        {
            "category":"Building & Trades",
            "subcategory":"Plumbing",
            "type":"Services"
        }
    ],
    "sg:phone":"+1 914 592 4740",
    "sg:postcode":"10523",
    "sg:province":"NY",
    "sg:tags":[
        "conditioning",
        "air",
        "system",
        "contractor"
    ],
    "wof:name":"Mike Chiulli Heating & AC",
    "wof:placetype":"venue"
},
  "geometry": {"coordinates":[-73.814133,41.063426],"type":"Point"}
}