{
  "type": "Feature",
  "properties": {
    "iso:country":"US",
    "sg:address":"1347 N Sea Rd",
    "sg:city":"Southampton",
    "sg:classifiers":[
        {
            "category":"Manufacturing",
            "subcategory":"Building Materials",
            "type":"Manufacturing & Wholesale Goods"
        }
    ],
    "sg:phone":"+1 631 283 3152",
    "sg:postcode":"11968",
    "sg:province":"NY",
    "sg:tags":[
        "mfg",
        "cabinet",
        "wood",
        "carpentry",
        "contractor",
        "kitchen"
    ],
    "wof:name":"Olde Towne Kitchens",
    "wof:placetype":"venue"
},
  "geometry": {"coordinates":[-72.412155,40.921279],"type":"Point"}
}