{
  "type": "Feature",
  "properties": {
    "iso:country":"US",
    "sg:address":"66 E Kingsbridge Rd",
    "sg:city":"Bronx",
    "sg:classifiers":[
        {
            "category":"Building & Trades",
            "subcategory":"Locksmith",
            "type":"Services"
        }
    ],
    "sg:phone":"+1 917 645 9414",
    "sg:postcode":"10468",
    "sg:province":"NY",
    "sg:tags":[
        "key"
    ],
    "wof:name":"Jhon Lock And Key",
    "wof:placetype":"venue"
},
  "geometry": {"coordinates":[-73.89588999999999,40.86667],"type":"Point"}
}