{
  "type": "Feature",
  "properties": {
    "addr:full":"181 E 90 St New York NY 10128",
    "addr:housenumber":"181;90",
    "addr:postcode":"10128",
    "addr:street":"E;St",
    "iso:country":"US",
    "sg:address":"181 E 90 St",
    "sg:city":"New York",
    "sg:classifiers":[
        {
            "category":"Banks & Credit Unions",
            "subcategory":"Bank",
            "type":"Services"
        }
    ],
    "sg:phone":"+1 212 935 9935",
    "sg:postcode":"10128",
    "sg:province":"NY",
    "wof:name":"Chase Manhattan Bank",
    "wof:placetype":"venue"
},
  "geometry": {"coordinates":[-73.952932,40.781921],"type":"Point"}
}