{
  "type": "Feature",
  "properties": {
    "addr:full":"277 Division St North Tonawanda NY 14120",
    "addr:housenumber":"277",
    "addr:postcode":"14120",
    "addr:street":"Division St",
    "iso:country":"US",
    "sg:address":"277 Division St",
    "sg:city":"North Tonawanda",
    "sg:classifiers":[
        {
            "category":"Health Services",
            "subcategory":"Doctor",
            "type":"Services"
        }
    ],
    "sg:phone":"+1 716 692 7156",
    "sg:postcode":"14120",
    "sg:province":"NY",
    "sg:tags":[
        "physician",
        "surgeon"
    ],
    "wof:name":"Yasmin Pervez MD",
    "wof:placetype":"venue"
},
  "geometry": {"coordinates":[-78.860612,43.031096],"type":"Point"}
}