{
  "type": "Feature",
  "properties": {
    "addr:full":"30 Markwood Ln East Northport NY 11731",
    "addr:housenumber":"30",
    "addr:postcode":"11731",
    "addr:street":"Markwood Ln",
    "iso:country":"US",
    "sg:address":"30 Markwood Ln",
    "sg:city":"East Northport",
    "sg:classifiers":[
        {
            "category":"Building & Trades",
            "subcategory":"Construction",
            "type":"Services"
        }
    ],
    "sg:phone":"+1 631 368 6909",
    "sg:postcode":"11731",
    "sg:province":"NY",
    "sg:tags":[
        "hanging",
        "contractor"
    ],
    "wof:name":"Tm Painting",
    "wof:placetype":"venue"
},
  "geometry": {"coordinates":[-73.330662,40.857375],"type":"Point"}
}