{
  "type": "Feature",
  "properties": {
    "addr:full":"60 Lafayette St New York NY 10013",
    "addr:housenumber":"60",
    "addr:postcode":"10013",
    "addr:street":"Lafayette St",
    "iso:country":"US",
    "sg:address":"60 Lafayette St",
    "sg:city":"New York",
    "sg:classifiers":[
        {
            "category":"Education",
            "subcategory":"School",
            "type":"Public Place"
        }
    ],
    "sg:phone":"+1 212 619 0383",
    "sg:postcode":"10013",
    "sg:province":"NY",
    "sg:tags":[
        "high",
        "middle",
        "elementary"
    ],
    "wof:name":"Pins Meditation & Diverson Project",
    "wof:placetype":"venue"
},
  "geometry": {"coordinates":[-74.002403,40.716202],"type":"Point"}
}