{
  "type": "Feature",
  "properties": {
    "addr:full":"2352 Ralph Ave Brooklyn NY 11234",
    "addr:housenumber":"2352",
    "addr:postcode":"11234",
    "addr:street":"Ralph Ave",
    "iso:country":"US",
    "sg:address":"2352 Ralph Ave",
    "sg:city":"Brooklyn",
    "sg:classifiers":[
        {
            "category":"Health Services",
            "subcategory":"Doctor",
            "type":"Services"
        }
    ],
    "sg:phone":"+1 718 444 0950",
    "sg:postcode":"11234",
    "sg:province":"NY",
    "sg:tags":[
        "physician",
        "surgeon"
    ],
    "wof:name":"United Medical",
    "wof:placetype":"venue"
},
  "geometry": {"coordinates":[-73.917366,40.61987],"type":"Point"}
}