{
  "type": "Feature",
  "properties": {
    "addr:full":"32 Old Cahoonzie Rd Sparrow Bush NY 12780",
    "addr:housenumber":"32",
    "addr:postcode":"12780",
    "addr:street":"Old Cahoonzie Rd;Bush",
    "iso:country":"US",
    "sg:address":"32 Old Cahoonzie Rd",
    "sg:city":"Sparrow Bush",
    "sg:classifiers":[
        {
            "category":"Building & Trades",
            "subcategory":"Construction",
            "type":"Services"
        }
    ],
    "sg:phone":"+1 845 858 8092",
    "sg:postcode":"12780",
    "sg:province":"NY",
    "sg:tags":[
        "woodworker"
    ],
    "wof:name":"Dispoz-A-Blade LLC",
    "wof:placetype":"venue"
},
  "geometry": {"coordinates":[-74.72802,41.41117],"type":"Point"}
}