{
  "type": "Feature",
  "properties": {
    "addr:full":"400 S Oyster Bay Rd # 100 Hicksville NY 11801",
    "addr:housenumber":"400",
    "addr:postcode":"11801",
    "addr:street":"S Oyster Bay Rd # 100",
    "iso:country":"US",
    "sg:address":"400 S Oyster Bay Rd # 100",
    "sg:city":"Hicksville",
    "sg:classifiers":[
        {
            "category":"Health Services",
            "subcategory":"Doctor",
            "type":"Services"
        }
    ],
    "sg:phone":"+1 516 933 1717",
    "sg:postcode":"11801",
    "sg:province":"NY",
    "sg:tags":[
        "dermatology",
        "physician",
        "surgeon",
        "surgeons"
    ],
    "wof:name":"Joel Lamm Inc",
    "wof:placetype":"venue"
},
  "geometry": {"coordinates":[-73.50305899999999,40.783329],"type":"Point"}
}