{
  "type": "Feature",
  "properties": {
    "iso:country":"US",
    "sg:address":"355 Lexington Ave",
    "sg:city":"New York",
    "sg:classifiers":[
        {
            "category":"Professional",
            "subcategory":"Lawyer & Legal Services",
            "type":"Services"
        }
    ],
    "sg:phone":"+1   ",
    "sg:postcode":"10017",
    "sg:province":"NY",
    "wof:name":"Taub  Iven R Law Office",
    "wof:placetype":"venue"
},
  "geometry": {"coordinates":[-73.976535,40.750775],"type":"Point"}
}