{
  "type": "Feature",
  "properties": {
    "iso:country":"US",
    "sg:address":"2112 E 66th St",
    "sg:city":"Brooklyn",
    "sg:classifiers":[
        {
            "category":"Building & Trades",
            "subcategory":"Locksmith",
            "type":"Services"
        }
    ],
    "sg:phone":"+1 888 739 5599",
    "sg:postcode":"11234",
    "sg:province":"NY",
    "sg:tags":[
        "key"
    ],
    "wof:name":"0 Zero Zero Zero Twenty Four Hour A Emergency A Lock",
    "wof:placetype":"venue"
},
  "geometry": {"coordinates":[-73.91099800000001,40.617174],"type":"Point"}
}