{
  "type": "Feature",
  "properties": {
    "iso:country":"US",
    "sg:address":"346 Prospect St",
    "sg:city":"Binghamton",
    "sg:classifiers":[
        {
            "category":"Education",
            "subcategory":"School",
            "type":"Public Place"
        }
    ],
    "sg:phone":"+1 607 763 1200",
    "sg:postcode":"13905",
    "sg:province":"NY",
    "sg:website":"http://www.jcschools.com",
    "wof:name":"Johnson Cy Kindergarten Campus",
    "wof:placetype":"venue"
},
  "geometry": {"coordinates":[-75.942402,42.116612],"type":"Point"}
}