{
  "type": "Feature",
  "properties": {
    "addr:full":"375 Park Ave Ste 2702 New York NY 10152",
    "addr:housenumber":"375",
    "addr:postcode":"10152",
    "addr:street":"Park Ave Ste 2702",
    "iso:country":"US",
    "sg:address":"375 Park Ave Ste 2702",
    "sg:city":"New York",
    "sg:classifiers":[
        {
            "category":"Professional",
            "subcategory":"Lawyer & Legal Services",
            "type":"Services"
        }
    ],
    "sg:phone":"+1 212 688 7888",
    "sg:postcode":"10152",
    "sg:province":"NY",
    "wof:name":"Morrissey Francis X Atty",
    "wof:placetype":"venue"
},
  "geometry": {"coordinates":[-73.972211,40.758462],"type":"Point"}
}