{
  "type": "Feature",
  "properties": {
    "addr:full":"559 4th St Troy NY 12180",
    "addr:housenumber":"559",
    "addr:postcode":"12180",
    "addr:street":"4Th St",
    "iso:country":"US",
    "sg:address":"559 4th St",
    "sg:city":"Troy",
    "sg:classifiers":[
        {
            "category":"Professional",
            "type":"Services"
        }
    ],
    "sg:phone":"+1 518 274 2465",
    "sg:postcode":"12180",
    "sg:province":"NY",
    "sg:tags":[
        "establishment"
    ],
    "wof:name":"Bessie Smith Station",
    "wof:placetype":"venue"
},
  "geometry": {"coordinates":[-73.69471299999999,42.712755],"type":"Point"}
}