{
  "type": "Feature",
  "properties": {
    "iso:country":"US",
    "sg:address":"200 Sherwood Ave",
    "sg:city":"Farmingdale",
    "sg:classifiers":[
        {
            "category":"Manufacturing",
            "subcategory":"Retail Goods",
            "type":"Manufacturing & Wholesale Goods"
        }
    ],
    "sg:phone":"+1   ",
    "sg:postcode":"11735",
    "sg:province":"NY",
    "sg:tags":[
        "tattoo",
        "temporary",
        "mfg"
    ],
    "wof:name":"Lemax World Inc",
    "wof:placetype":"venue"
},
  "geometry": {"coordinates":[-73.417834,40.744836],"type":"Point"}
}