{
  "type": "Feature",
  "properties": {
    "addr:full":"26 W Park Ave Ste A Long Beach NY 11561",
    "addr:housenumber":"26",
    "addr:postcode":"11561",
    "addr:street":"W Park Ave Ste A",
    "iso:country":"US",
    "sg:address":"26 W Park Ave Ste A",
    "sg:city":"Long Beach",
    "sg:classifiers":[
        {
            "category":"Shopping",
            "subcategory":"Pharmacy",
            "type":"Retail Goods"
        }
    ],
    "sg:phone":"+1 516 432 7131",
    "sg:postcode":"11561",
    "sg:province":"NY",
    "sg:tags":[
        "drugstore"
    ],
    "wof:name":"Bi-Wise Drugs",
    "wof:placetype":"venue"
},
  "geometry": {"coordinates":[-73.66501100000001,40.588205],"type":"Point"}
}