{
  "type": "Feature",
  "properties": {
    "iso:country":"US",
    "sg:address":"4909 N Jefferson St",
    "sg:city":"Pulaski",
    "sg:classifiers":[
        {
            "category":"Government",
            "subcategory":"Post Office",
            "type":"Public Place"
        }
    ],
    "sg:phone":"+1   ",
    "sg:postcode":"13142",
    "sg:province":"NY",
    "sg:tags":[
        "postal",
        "us"
    ],
    "wof:name":"US Post Office",
    "wof:placetype":"venue"
},
  "geometry": {"coordinates":[-76.126007,43.569273],"type":"Point"}
}