{
  "type": "Feature",
  "properties": {
    "iso:country":"US",
    "sg:address":"2200 Penfield Rd",
    "sg:city":"Penfield",
    "sg:classifiers":[
        {
            "category":"Personal",
            "subcategory":"Beauty Salon",
            "type":"Services"
        }
    ],
    "sg:phone":"+1 585 377 0950",
    "sg:postcode":"14526",
    "sg:province":"NY",
    "sg:tags":[
        "manicuring"
    ],
    "wof:name":"Fancy Nails",
    "wof:placetype":"venue"
},
  "geometry": {"coordinates":[-77.435633,43.130655],"type":"Point"}
}