{
  "type": "Feature",
  "properties": {
    "iso:country":"US",
    "sg:address":"8585 Snowshoe Trl",
    "sg:city":"Cicero",
    "sg:classifiers":[
        {
            "category":"Manufacturing",
            "subcategory":"Metals",
            "type":"Manufacturing & Wholesale Goods"
        }
    ],
    "sg:phone":"+1   ",
    "sg:postcode":"13039",
    "sg:province":"NY",
    "sg:tags":[
        "fabricator"
    ],
    "wof:name":"Mineker Racing",
    "wof:placetype":"venue"
},
  "geometry": {"coordinates":[-76.098902,43.186283],"type":"Point"}
}