{
  "type": "Feature",
  "properties": {
    "iso:country":"US",
    "sg:address":"52 E End Ave",
    "sg:city":"New York",
    "sg:classifiers":[
        {
            "category":"Real Estate",
            "subcategory":"Real Estate Operator",
            "type":"Services"
        }
    ],
    "sg:phone":"+1 212 288 8705",
    "sg:postcode":"10028",
    "sg:province":"NY",
    "sg:tags":[
        "apartment"
    ],
    "wof:name":"52 East End Av Condominium",
    "wof:placetype":"venue"
},
  "geometry": {"coordinates":[-73.9468,40.772099],"type":"Point"}
}