{
  "type": "Feature",
  "properties": {
    "addr:full":"150 W River Rd Gansevoort NY 12831",
    "addr:housenumber":"150",
    "addr:postcode":"12831",
    "addr:street":"W River Rd",
    "iso:country":"US",
    "sg:address":"150 W River Rd",
    "sg:city":"Gansevoort",
    "sg:classifiers":[
        {
            "category":"Autos & Motor Vehicles",
            "subcategory":"Automobile Sales",
            "type":"Retail Goods"
        }
    ],
    "sg:phone":"+1 518 383 4953",
    "sg:postcode":"12831",
    "sg:province":"NY",
    "sg:tags":[
        "car",
        "dealer"
    ],
    "wof:name":"Krystal Motors",
    "wof:placetype":"venue"
},
  "geometry": {"coordinates":[-73.58551,43.180049],"type":"Point"}
}