{
  "type": "Feature",
  "properties": {
    "iso:country":"US",
    "sg:address":"8710 37th Ave",
    "sg:city":"Jackson Heights",
    "sg:classifiers":[
        {
            "category":"Health Services",
            "subcategory":"Doctor",
            "type":"Services"
        },
        {
            "category":"Personal",
            "subcategory":"Hair Removal",
            "type":"Services"
        }
    ],
    "sg:phone":"+1 718 457 7443",
    "sg:postcode":"11372",
    "sg:province":"NY",
    "sg:tags":[
        "podiatrist"
    ],
    "wof:name":"Goldman Gershon DPM",
    "wof:placetype":"venue"
},
  "geometry": {"coordinates":[-73.87960099999999,40.750198],"type":"Point"}
}