{
  "type": "Feature",
  "properties": {
    "addr:full":"193 Kingman Rd Nassau NY 12123",
    "addr:housenumber":"193",
    "addr:postcode":"12123",
    "addr:street":"Kingman Rd",
    "iso:country":"US",
    "sg:address":"193 Kingman Rd",
    "sg:city":"Nassau",
    "sg:classifiers":[
        {
            "category":"Farming",
            "subcategory":"Dairy Farm",
            "type":"Manufacturing & Wholesale Goods"
        }
    ],
    "sg:phone":"+1 518 766 3796",
    "sg:postcode":"12123",
    "sg:province":"NY",
    "wof:name":"Maier Farm",
    "wof:placetype":"venue"
},
  "geometry": {"coordinates":[-73.65356199999999,42.495711],"type":"Point"}
}