{
  "type": "Feature",
  "properties": {
    "addr:full":"1975 Linden Blvd Ste 405 Elmont NY 11003",
    "addr:housenumber":"1975",
    "addr:postcode":"11003",
    "addr:street":"Linden Blvd Ste 405",
    "iso:country":"US",
    "sg:address":"1975 Linden Blvd Ste 405",
    "sg:city":"Elmont",
    "sg:classifiers":[
        {
            "category":"Real Estate",
            "subcategory":"Real Estate Services",
            "type":"Services"
        }
    ],
    "sg:phone":"+1 516 285 4300",
    "sg:postcode":"11003",
    "sg:province":"NY",
    "sg:tags":[
        "management",
        "property"
    ],
    "wof:name":"HK Management LLC",
    "wof:placetype":"venue"
},
  "geometry": {"coordinates":[-73.71803300000001,40.687976],"type":"Point"}
}