{
  "type": "Feature",
  "properties": {
    "iso:country":"US",
    "sg:address":"9739 Ridge Rd W",
    "sg:city":"Brockport",
    "sg:classifiers":[
        {
            "category":"Food & Beverages",
            "subcategory":"Fruits & Vegetables",
            "type":"Retail Goods"
        }
    ],
    "sg:phone":"+1 585 637 2600",
    "sg:postcode":"14420",
    "sg:province":"NY",
    "sg:tags":[
        "farm",
        "market"
    ],
    "wof:name":"Bittersweet",
    "wof:placetype":"venue"
},
  "geometry": {"coordinates":[-77.97517000000001,43.250516],"type":"Point"}
}