{
  "type": "Feature",
  "properties": {
    "addr:full":"1164 49th St Brooklyn NY 11219",
    "addr:housenumber":"1164",
    "addr:postcode":"11219",
    "addr:street":"49Th St",
    "iso:country":"US",
    "sg:address":"1164 49th St",
    "sg:city":"Brooklyn",
    "sg:classifiers":[
        {
            "category":"Manufacturing",
            "subcategory":"Apparel",
            "type":"Manufacturing & Wholesale Goods"
        }
    ],
    "sg:phone":"+1   ",
    "sg:postcode":"11219",
    "sg:province":"NY",
    "sg:tags":[
        "outerwear",
        "mfg"
    ],
    "wof:name":"Cravings Ltd",
    "wof:placetype":"venue"
},
  "geometry": {"coordinates":[-73.99589400000001,40.63743],"type":"Point"}
}