{
  "type": "Feature",
  "properties": {
    "iso:country":"US",
    "sg:address":"212 Kings Hwy",
    "sg:city":"Brooklyn",
    "sg:classifiers":[
        {
            "category":"Utilities",
            "subcategory":"Mobile Phone",
            "type":"Services"
        }
    ],
    "sg:phone":"+1   ",
    "sg:postcode":"11223",
    "sg:province":"NY",
    "sg:tags":[
        "paging"
    ],
    "wof:name":"L & R Elektra Inc",
    "wof:placetype":"venue"
},
  "geometry": {"coordinates":[-73.982371,40.605347],"type":"Point"}
}