{
  "type": "Feature",
  "properties": {
    "addr:full":"1451 E Gun Hill Rd Bronx NY 10469",
    "addr:housenumber":"1451",
    "addr:postcode":"10469",
    "addr:street":"E Gun Hill Rd",
    "iso:country":"US",
    "sg:address":"1451 E Gun Hill Rd",
    "sg:city":"Bronx",
    "sg:classifiers":[
        {
            "category":"Professional",
            "subcategory":"Detective & Security Services",
            "type":"Services"
        }
    ],
    "sg:phone":"+1 718 320 6993",
    "sg:postcode":"10469",
    "sg:province":"NY",
    "sg:tags":[
        "guard"
    ],
    "wof:name":"Prime Protective Systems Inc",
    "wof:placetype":"venue"
},
  "geometry": {"coordinates":[-73.84431600000001,40.869573],"type":"Point"}
}