{
  "type": "Feature",
  "properties": {
    "addr:full":"1510 Ridge Rd W Rochester NY 14420",
    "addr:housenumber":"1510",
    "addr:postcode":"14420",
    "addr:street":"Ridge Rd W",
    "iso:country":"US",
    "sg:address":"1510 Ridge Rd W",
    "sg:city":"Rochester",
    "sg:classifiers":[
        {
            "category":"Health Services",
            "subcategory":"Doctor",
            "type":"Services"
        }
    ],
    "sg:phone":"+1   ",
    "sg:postcode":"14420",
    "sg:province":"NY",
    "wof:name":"Bruce Goldin",
    "wof:placetype":"venue"
},
  "geometry": {"coordinates":[-77.667142,43.205361],"type":"Point"}
}