{
  "type": "Feature",
  "properties": {
    "addr:full":"413 E 120th St New York NY 10035",
    "addr:housenumber":"413",
    "addr:postcode":"10035",
    "addr:street":"E 120Th St",
    "iso:country":"US",
    "sg:address":"413 E 120th St",
    "sg:city":"New York",
    "sg:classifiers":[
        {
            "category":"Professional",
            "subcategory":"Management & Consulting",
            "type":"Services"
        }
    ],
    "sg:phone":"+1 212 410 7707",
    "sg:postcode":"10035",
    "sg:province":"NY",
    "sg:tags":[
        "consultant",
        "business"
    ],
    "wof:name":"Ehcci Imp Inc",
    "wof:placetype":"venue"
},
  "geometry": {"coordinates":[-73.93232999999999,40.798247],"type":"Point"}
}