{
  "type": "Feature",
  "properties": {
    "iso:country":"US",
    "sg:address":"3510 Vienna St",
    "sg:city":"Palmyra",
    "sg:classifiers":[
        {
            "category":"Real Estate",
            "subcategory":"Real Estate Operator",
            "type":"Services"
        }
    ],
    "sg:phone":"+1 315 597 9230",
    "sg:postcode":"14522",
    "sg:province":"NY",
    "sg:tags":[
        "apartment"
    ],
    "wof:name":"Vienna Place",
    "wof:placetype":"venue"
},
  "geometry": {"coordinates":[-77.209847,43.059972],"type":"Point"}
}