{
  "type": "Feature",
  "properties": {
    "iso:country":"US",
    "sg:address":"47 Woods Falls Rd",
    "sg:city":"Altona",
    "sg:classifiers":[
        {
            "category":"Restaurant",
            "type":"Food & Drink"
        }
    ],
    "sg:phone":"+1 518 236 5030",
    "sg:postcode":"12910",
    "sg:province":"NY",
    "sg:tags":[
        "banquet",
        "rooms"
    ],
    "wof:name":"Rainbow Wedding & Banquet",
    "wof:placetype":"venue"
},
  "geometry": {"coordinates":[-73.65594299999999,44.898668],"type":"Point"}
}