{
  "type": "Feature",
  "properties": {
    "addr:full":"18 Railroad Ave Center Moriches NY 11934",
    "addr:housenumber":"18",
    "addr:postcode":"11934",
    "addr:street":"Railroad Ave Center",
    "iso:country":"US",
    "sg:address":"18 Railroad Ave",
    "sg:city":"Center Moriches",
    "sg:classifiers":[
        {
            "category":"Banks & Credit Unions",
            "subcategory":"Investment Brokerage",
            "type":"Services"
        }
    ],
    "sg:phone":"+1 631 874 4600",
    "sg:postcode":"11934",
    "sg:province":"NY",
    "sg:tags":[
        "advisory",
        "financial"
    ],
    "wof:name":"Boothe Financial",
    "wof:placetype":"venue"
},
  "geometry": {"coordinates":[-72.789838,40.800684],"type":"Point"}
}