{
  "type": "Feature",
  "properties": {
    "iso:country":"US",
    "sg:address":"106 Forest Ave",
    "sg:city":"Nesconset",
    "sg:classifiers":[
        {
            "category":"Building & Trades",
            "subcategory":"Construction",
            "type":"Services"
        }
    ],
    "sg:phone":"+1 631 467 7707",
    "sg:postcode":"11767",
    "sg:province":"NY",
    "sg:tags":[
        "glass",
        "work",
        "glazing"
    ],
    "wof:name":"Clear Cut",
    "wof:placetype":"venue"
},
  "geometry": {"coordinates":[-73.126446,40.846446],"type":"Point"}
}