{
  "type": "Feature",
  "properties": {
    "addr:full":"1227 US Hwy 11 Gouverneur NY 13642",
    "addr:housenumber":"1227",
    "addr:postcode":"13642",
    "addr:street":"Us Hwy 11",
    "iso:country":"US",
    "sg:address":"1227 US Hwy 11",
    "sg:city":"Gouverneur",
    "sg:classifiers":[
        {
            "category":"Government",
            "subcategory":"Office",
            "type":"Public Place"
        }
    ],
    "sg:phone":"+1 315 287 7034",
    "sg:postcode":"13642",
    "sg:province":"NY",
    "sg:tags":[
        "transportation"
    ],
    "wof:name":"Motor Vehicles New York Dept",
    "wof:placetype":"venue"
},
  "geometry": {"coordinates":[-75.481537,44.32443],"type":"Point"}
}