{
  "type": "Feature",
  "properties": {
    "addr:full":"111 Pratt Dr Oswego NY 13126",
    "addr:housenumber":"111",
    "addr:postcode":"13126",
    "addr:street":"Pratt Dr",
    "iso:country":"US",
    "sg:address":"111 Pratt Dr",
    "sg:city":"Oswego",
    "sg:classifiers":[
        {
            "category":"Personal",
            "type":"Services"
        }
    ],
    "sg:phone":"+1   ",
    "sg:postcode":"13126",
    "sg:province":"NY",
    "wof:name":"Kathys",
    "wof:placetype":"venue"
},
  "geometry": {"coordinates":[-76.481819,43.355227],"type":"Point"}
}