{
  "type": "Feature",
  "properties": {
    "iso:country":"US",
    "sg:address":"20 W 36th Street",
    "sg:city":"New York",
    "sg:classifiers":[
        {
            "category":"Education",
            "subcategory":"Special Training",
            "type":"Public Place"
        }
    ],
    "sg:phone":"+1 212 563 6600",
    "sg:postcode":"10018",
    "sg:province":"NY",
    "sg:tags":[
        "school",
        "specialty"
    ],
    "wof:name":"New York Bartenders Assoc",
    "wof:placetype":"venue"
},
  "geometry": {"coordinates":[-73.98430399999999,40.75001],"type":"Point"}
}