{
  "type": "Feature",
  "properties": {
    "iso:country":"US",
    "sg:address":"205 Hudson St 6th floor",
    "sg:city":"New York",
    "sg:classifiers":[
        {
            "category":"Personal",
            "type":"Services"
        }
    ],
    "sg:postcode":"10013",
    "sg:province":"NY",
    "sg:tags":[
        "local"
    ],
    "sg:website":"www.communityconnect.com",
    "wof:name":"Community Connect Inc.",
    "wof:placetype":"venue"
},
  "geometry": {"coordinates":[-74.00794,40.723656],"type":"Point"}
}