{
  "type": "Feature",
  "properties": {
    "addr:full":"1185 Rogers Ave Brooklyn NY 11226",
    "addr:housenumber":"1185",
    "addr:postcode":"11226",
    "addr:street":"Rogers Ave",
    "iso:country":"US",
    "sg:address":"1185 Rogers Ave",
    "sg:city":"Brooklyn",
    "sg:classifiers":[
        {
            "category":"Personal",
            "subcategory":"Beauty Salon",
            "type":"Services"
        }
    ],
    "sg:phone":"+1 718 940 3762",
    "sg:postcode":"11226",
    "sg:province":"NY",
    "wof:name":"Mora's Unique Designs",
    "wof:placetype":"venue"
},
  "geometry": {"coordinates":[-73.951504,40.642908],"type":"Point"}
}