{
  "type": "Feature",
  "properties": {
    "iso:country":"US",
    "sg:address":"7913 Bay Pkwy",
    "sg:city":"Brooklyn",
    "sg:classifiers":[
        {
            "category":"Building & Trades",
            "subcategory":"Construction",
            "type":"Services"
        }
    ],
    "sg:phone":"+1 718 236 6333",
    "sg:postcode":"11214",
    "sg:province":"NY",
    "sg:tags":[
        "contractor"
    ],
    "wof:name":"Spectrum General Contracting Incorporated",
    "wof:placetype":"venue"
},
  "geometry": {"coordinates":[-73.989645,40.605722],"type":"Point"}
}