{
  "type": "Feature",
  "properties": {
    "addr:full":"25 Willow Pkwy New Windsor NY 12553",
    "addr:housenumber":"25",
    "addr:postcode":"12553",
    "addr:street":"Willow Pkwy",
    "iso:country":"US",
    "sg:address":"25 Willow Pkwy",
    "sg:city":"New Windsor",
    "sg:classifiers":[
        {
            "category":"Building & Trades",
            "subcategory":"Electrical",
            "type":"Services"
        }
    ],
    "sg:phone":"+1 845 565 0710",
    "sg:postcode":"12553",
    "sg:province":"NY",
    "sg:tags":[
        "electrical",
        "contractor"
    ],
    "wof:name":"Ra Electric",
    "wof:placetype":"venue"
},
  "geometry": {"coordinates":[-74.045946,41.469894],"type":"Point"}
}