{
  "type": "Feature",
  "properties": {
    "addr:full":"208 Walrath Rd Syracuse NY 13205",
    "addr:housenumber":"208",
    "addr:postcode":"13205",
    "addr:street":"Walrath Rd",
    "iso:country":"US",
    "sg:address":"208 Walrath Rd",
    "sg:city":"Syracuse",
    "sg:classifiers":[
        {
            "category":"Autos & Motor Vehicles",
            "subcategory":"Auto Supplies",
            "type":"Retail Goods"
        }
    ],
    "sg:phone":"+1   ",
    "sg:postcode":"13205",
    "sg:province":"NY",
    "wof:name":"Eddie Racing Fast",
    "wof:placetype":"venue"
},
  "geometry": {"coordinates":[-76.138138,43.010857],"type":"Point"}
}