{
  "type": "Feature",
  "properties": {
    "addr:full":"86 Bartlett Dr Manhasset NY 11030",
    "addr:housenumber":"86",
    "addr:postcode":"11030",
    "addr:street":"Bartlett Dr",
    "iso:country":"US",
    "sg:address":"86 Bartlett Dr",
    "sg:city":"Manhasset",
    "sg:classifiers":[
        {
            "category":"Shopping",
            "subcategory":"Computers & Home Electronics",
            "type":"Retail Goods"
        }
    ],
    "sg:phone":"+1 516 365 7002",
    "sg:postcode":"11030",
    "sg:province":"NY",
    "sg:tags":[
        "resale",
        "consumer"
    ],
    "wof:name":"Keenzo Corporation",
    "wof:placetype":"venue"
},
  "geometry": {"coordinates":[-73.670469,40.801633],"type":"Point"}
}