{
  "type": "Feature",
  "properties": {
    "iso:country":"US",
    "sg:address":"3402 Danbury Rd.",
    "sg:city":"Brewster",
    "sg:classifiers":[
        {
            "category":"Personal",
            "type":"Services"
        },
        {
            "category":"Retail",
            "subcategory":"Auto Repair",
            "type":"Services"
        }
    ],
    "sg:phone":"+1 845 278 6166",
    "sg:postcode":"10509",
    "sg:province":"NY",
    "sg:tags":[
        "towing",
        "truck"
    ],
    "sg:website":"http://lisistowing.com",
    "wof:name":"Lisi's Towing Service, Inc.",
    "wof:placetype":"venue"
},
  "geometry": {"coordinates":[-73.594857,41.392865],"type":"Point"}
}