{
  "type": "Feature",
  "properties": {
    "iso:country":"US",
    "sg:address":"3353 Neals Gulf Rd",
    "sg:city":"New Hartford",
    "sg:classifiers":[
        {
            "category":"Building & Trades",
            "subcategory":"Construction",
            "type":"Services"
        }
    ],
    "sg:phone":"+1 315 796 5911",
    "sg:postcode":"13413",
    "sg:province":"NY",
    "sg:tags":[
        "house"
    ],
    "wof:name":"Goddard Construction",
    "wof:placetype":"venue"
},
  "geometry": {"coordinates":[-75.298132,43.023498],"type":"Point"}
}