{
  "type": "Feature",
  "properties": {
    "addr:full":"275 Rockaway Tpke Lawrence NY 11559",
    "addr:housenumber":"275",
    "addr:postcode":"11559",
    "addr:street":"Rockaway Tpke",
    "iso:country":"US",
    "sg:address":"275 Rockaway Tpke",
    "sg:city":"Lawrence",
    "sg:classifiers":[
        {
            "category":"Health Services",
            "subcategory":"Doctor",
            "type":"Services"
        }
    ],
    "sg:phone":"+1 516 371 5800",
    "sg:postcode":"11559",
    "sg:province":"NY",
    "sg:tags":[
        "medicine",
        "practice",
        "internal",
        "family"
    ],
    "wof:name":"Five Towns Family Medical Care",
    "wof:placetype":"venue"
},
  "geometry": {"coordinates":[-73.732697,40.620098],"type":"Point"}
}