{
  "type": "Feature",
  "properties": {
    "iso:country":"US",
    "sg:address":"219 Pinewoods Ave",
    "sg:city":"Troy",
    "sg:classifiers":[
        {
            "category":"Real Estate",
            "subcategory":"Real Estate Services",
            "type":"Services"
        },
        {
            "category":"Real Estate",
            "subcategory":"Real Estate Agent",
            "type":"Services"
        }
    ],
    "sg:phone":"+1 518 272 4143",
    "sg:postcode":"12180",
    "sg:province":"NY",
    "sg:tags":[
        "buyer",
        "broker"
    ],
    "wof:name":"3 Realty",
    "wof:placetype":"venue"
},
  "geometry": {"coordinates":[-73.654549,42.715464],"type":"Point"}
}