{
  "type": "Feature",
  "properties": {
    "iso:country":"US",
    "sg:address":"20 Hawley St",
    "sg:city":"Binghamton",
    "sg:classifiers":[
        {
            "category":"Banks & Credit Unions",
            "subcategory":"Bank",
            "type":"Services"
        }
    ],
    "sg:phone":"+1 607 772 5416",
    "sg:postcode":"13901",
    "sg:province":"NY",
    "sg:tags":[
        "mortgage"
    ],
    "wof:name":"H S B C Mortgage Corporation",
    "wof:placetype":"venue"
},
  "geometry": {"coordinates":[-75.91283300000001,42.097062],"type":"Point"}
}