{
  "type": "Feature",
  "properties": {
    "addr:full":"130 W Water St Painted Post NY 14870",
    "addr:housenumber":"130",
    "addr:postcode":"14870",
    "addr:street":"W Water St",
    "iso:country":"US",
    "sg:address":"130 W Water St",
    "sg:city":"Painted Post",
    "sg:classifiers":[
        {
            "category":"Social Services",
            "type":"Services"
        }
    ],
    "sg:phone":"+1 607 936 0111",
    "sg:postcode":"14870",
    "sg:province":"NY",
    "sg:tags":[
        "organization",
        "welfare"
    ],
    "wof:name":"Pathways Inc",
    "wof:placetype":"venue"
},
  "geometry": {"coordinates":[-77.09549,42.158693],"type":"Point"}
}