{
  "type": "Feature",
  "properties": {
    "addr:full":"72 E 37th St New York NY 10016",
    "addr:housenumber":"72",
    "addr:postcode":"10016",
    "addr:street":"E 37Th St",
    "iso:country":"US",
    "sg:address":"72 E 37th St",
    "sg:city":"New York",
    "sg:classifiers":[
        {
            "category":"Professional",
            "subcategory":"Art Services",
            "type":"Services"
        }
    ],
    "sg:phone":"+1 212 679 2533",
    "sg:postcode":"10016",
    "sg:province":"NY",
    "sg:tags":[
        "photographer"
    ],
    "wof:name":"Al Freni Inc",
    "wof:placetype":"venue"
},
  "geometry": {"coordinates":[-73.98078599999999,40.749362],"type":"Point"}
}