{
  "type": "Feature",
  "properties": {
    "addr:full":"19 Harbor Side Ct Patchogue NY 11772",
    "addr:housenumber":"19",
    "addr:postcode":"11772",
    "addr:street":"Harbor Side Ct",
    "iso:country":"US",
    "sg:address":"19 Harbor Side Ct",
    "sg:city":"Patchogue",
    "sg:classifiers":[
        {
            "category":"Building & Trades",
            "subcategory":"Construction",
            "type":"Services"
        }
    ],
    "sg:phone":"+1 631 447 0608",
    "sg:postcode":"11772",
    "sg:province":"NY",
    "sg:tags":[
        "concrete",
        "contractor"
    ],
    "wof:name":"Rapat Construction Corporation",
    "wof:placetype":"venue"
},
  "geometry": {"coordinates":[-72.986428,40.761409],"type":"Point"}
}