{
  "type": "Feature",
  "properties": {
    "addr:full":"1939 New York Ave Huntington Sta NY 11746",
    "addr:housenumber":"1939",
    "addr:postcode":"11746",
    "addr:street":"New York Ave",
    "iso:country":"US",
    "sg:address":"1939 New York Ave",
    "sg:city":"Huntington Sta",
    "sg:classifiers":[
        {
            "category":"Retail",
            "subcategory":"Laundry & Dry Cleaning",
            "type":"Services"
        }
    ],
    "sg:phone":"+1 631 427 9410",
    "sg:postcode":"11746",
    "sg:province":"NY",
    "wof:name":"Wash Ease Laundry",
    "wof:placetype":"venue"
},
  "geometry": {"coordinates":[-73.41132500000001,40.834554],"type":"Point"}
}