{
  "type": "Feature",
  "properties": {
    "addr:full":"9651 State Hwy 49 Marcy NY 13403",
    "addr:housenumber":"9651",
    "addr:postcode":"13403",
    "addr:street":"State Hwy 49",
    "iso:country":"US",
    "sg:address":"9651 State Hwy 49",
    "sg:city":"Marcy",
    "sg:classifiers":[
        {
            "category":"Retail",
            "subcategory":"Auto Repair",
            "type":"Services"
        }
    ],
    "sg:phone":"+1 315 738 7710",
    "sg:postcode":"13403",
    "sg:province":"NY",
    "sg:tags":[
        "automobile",
        "diagnostic",
        "general"
    ],
    "wof:name":"Automotive Service Center",
    "wof:placetype":"venue"
},
  "geometry": {"coordinates":[-75.24646,43.129712],"type":"Point"}
}