{
  "type": "Feature",
  "properties": {
    "addr:full":"2 Stagedoor Rd Fishkill NY 12524",
    "addr:housenumber":"2",
    "addr:postcode":"12524",
    "addr:street":"Stagedoor Rd",
    "iso:country":"US",
    "sg:address":"2 Stagedoor Rd",
    "sg:city":"Fishkill",
    "sg:classifiers":[
        {
            "category":"Real Estate",
            "subcategory":"Real Estate Operator",
            "type":"Services"
        }
    ],
    "sg:phone":"+1 845 897 3851",
    "sg:postcode":"12524",
    "sg:province":"NY",
    "sg:tags":[
        "commercial"
    ],
    "wof:name":"Lombardi Equities",
    "wof:placetype":"venue"
},
  "geometry": {"coordinates":[-73.899846,41.561665],"type":"Point"}
}