{
  "type": "Feature",
  "properties": {
    "addr:full":"52 Royal Oak Dr Rochester NY 14624",
    "addr:housenumber":"52",
    "addr:postcode":"14624",
    "addr:street":"Royal Oak Dr",
    "iso:country":"US",
    "sg:address":"52 Royal Oak Dr",
    "sg:city":"Rochester",
    "sg:classifiers":[
        {
            "category":"Organizations",
            "subcategory":"Religious Organization",
            "type":"Services"
        }
    ],
    "sg:phone":"+1 585 426 3225",
    "sg:postcode":"14624",
    "sg:province":"NY",
    "sg:tags":[
        "clergy"
    ],
    "wof:name":"Bonnie Nolen",
    "wof:placetype":"venue"
},
  "geometry": {"coordinates":[-77.69277700000001,43.137066],"type":"Point"}
}