{
  "type": "Feature",
  "properties": {
    "addr:full":"195 Arthur Ave Thornwood NY 10594",
    "addr:housenumber":"195",
    "addr:postcode":"10594",
    "addr:street":"Arthur Ave",
    "iso:country":"US",
    "sg:address":"195 Arthur Ave",
    "sg:city":"Thornwood",
    "sg:classifiers":[
        {
            "category":"Building & Trades",
            "subcategory":"Landscaping Services",
            "type":"Services"
        }
    ],
    "sg:phone":"+1 914 747 1482",
    "sg:postcode":"10594",
    "sg:province":"NY",
    "sg:tags":[
        "landscape",
        "contractor"
    ],
    "wof:name":"Mascon Development & Landscpg",
    "wof:placetype":"venue"
},
  "geometry": {"coordinates":[-73.77583300000001,41.119537],"type":"Point"}
}