{
  "type": "Feature",
  "properties": {
    "addr:full":"732 State Hwy 426 Clymer NY 14724",
    "addr:housenumber":"732",
    "addr:postcode":"14724",
    "addr:street":"State Hwy 426 Clymer",
    "iso:country":"US",
    "sg:address":"732 State Hwy 426",
    "sg:city":"Clymer",
    "sg:classifiers":[
        {
            "category":"Farming",
            "subcategory":"Dairy Farm",
            "type":"Manufacturing & Wholesale Goods"
        }
    ],
    "sg:phone":"+1 716 355 6617",
    "sg:postcode":"14724",
    "sg:province":"NY",
    "wof:name":"Dunnewolds Farm",
    "wof:placetype":"venue"
},
  "geometry": {"coordinates":[-79.69910299999999,42.038407],"type":"Point"}
}