{
  "type": "Feature",
  "properties": {
    "iso:country":"US",
    "sg:address":"28 Maryvale Dr",
    "sg:city":"Webster",
    "sg:classifiers":[
        {
            "category":"Building & Trades",
            "subcategory":"Construction",
            "type":"Services"
        }
    ],
    "sg:phone":"+1 585 265 2302",
    "sg:postcode":"14580",
    "sg:province":"NY",
    "sg:tags":[
        "house"
    ],
    "wof:name":"JRL Builders Inc",
    "wof:placetype":"venue"
},
  "geometry": {"coordinates":[-77.425865,43.205095],"type":"Point"}
}