{
  "type": "Feature",
  "properties": {
    "addr:full":"3080 William St Buffalo NY 14227",
    "addr:housenumber":"3080",
    "addr:postcode":"14227",
    "addr:street":"William St",
    "iso:country":"US",
    "sg:address":"3080 William St",
    "sg:city":"Buffalo",
    "sg:classifiers":[
        {
            "category":"Wholesale",
            "subcategory":"Beer",
            "type":"Manufacturing & Wholesale Goods"
        },
        {
            "category":"Food & Beverages",
            "subcategory":"Liquor & Beverages",
            "type":"Retail Goods"
        }
    ],
    "sg:phone":"+1 716 897 0888",
    "sg:postcode":"14227",
    "sg:province":"NY",
    "sg:tags":[
        "manufacturer",
        "ale",
        "bottler",
        "ale-wholesale",
        "beverages-distributors"
    ],
    "wof:name":"Buffalo Beverage Corp",
    "wof:placetype":"venue"
},
  "geometry": {"coordinates":[-78.758021,42.883872],"type":"Point"}
}