{
  "type": "Feature",
  "properties": {
    "iso:country":"US",
    "sg:address":"513 Imperial Way",
    "sg:city":"Bayport",
    "sg:classifiers":[
        {
            "category":"Professional",
            "type":"Services"
        }
    ],
    "sg:phone":"+1 631 363 0031",
    "sg:postcode":"11705",
    "sg:province":"NY",
    "sg:tags":[
        "establishment"
    ],
    "wof:name":"MNT Development Corp",
    "wof:placetype":"venue"
},
  "geometry": {"coordinates":[-73.04459199999999,40.75222],"type":"Point"}
}