{
  "type": "Feature",
  "properties": {
    "addr:full":"673 Main St East Aurora NY 14052",
    "addr:housenumber":"673",
    "addr:postcode":"14052",
    "addr:street":"Main St",
    "iso:country":"US",
    "sg:address":"673 Main St",
    "sg:city":"East Aurora",
    "sg:classifiers":[
        {
            "category":"Cinema",
            "subcategory":"Movie Theater",
            "type":"Entertainment"
        }
    ],
    "sg:phone":"+1 716 652 1660",
    "sg:postcode":"14052",
    "sg:province":"NY",
    "wof:name":"Aurora Theatre",
    "wof:placetype":"venue"
},
  "geometry": {"coordinates":[-78.61098699999999,42.767812],"type":"Point"}
}