{
  "type": "Feature",
  "properties": {
    "iso:country":"US",
    "sg:address":"1716 Church St",
    "sg:city":"Holbrook",
    "sg:classifiers":[
        {
            "category":"Wholesale",
            "subcategory":"Painting Supplies",
            "type":"Manufacturing & Wholesale Goods"
        }
    ],
    "sg:phone":"+1 631 472 8251",
    "sg:postcode":"11741",
    "sg:province":"NY",
    "sg:tags":[
        "finishing",
        "wood"
    ],
    "wof:name":"Colorspec Codings Inc",
    "wof:placetype":"venue"
},
  "geometry": {"coordinates":[-73.06373499999999,40.771068],"type":"Point"}
}