{
  "type": "Feature",
  "properties": {
    "addr:full":"76 Congers Rd New City NY 10956",
    "addr:housenumber":"76",
    "addr:postcode":"10956",
    "addr:street":"Congers Rd",
    "iso:country":"US",
    "sg:address":"76 Congers Rd",
    "sg:city":"New City",
    "sg:classifiers":[
        {
            "category":"Organizations",
            "subcategory":"Religious Organization",
            "type":"Services"
        }
    ],
    "sg:phone":"+1 845 634 1758",
    "sg:postcode":"10956",
    "sg:province":"NY",
    "sg:tags":[
        "church"
    ],
    "wof:name":"New City United Methodist Chr",
    "wof:placetype":"venue"
},
  "geometry": {"coordinates":[-73.98238499999999,41.146957],"type":"Point"}
}