{
  "type": "Feature",
  "properties": {
    "addr:full":"60 Curtis Dr Sound Beach NY 11789",
    "addr:housenumber":"60",
    "addr:postcode":"11789",
    "addr:street":"Curtis Dr Sound Beach",
    "iso:country":"US",
    "sg:address":"60 Curtis Dr",
    "sg:city":"Sound Beach",
    "sg:classifiers":[
        {
            "category":"Shopping",
            "type":"Retail Goods"
        }
    ],
    "sg:phone":"+1   ",
    "sg:postcode":"11789",
    "sg:province":"NY",
    "sg:tags":[
        "merchandise"
    ],
    "wof:name":"Your Motorcycle Shop Inc",
    "wof:placetype":"venue"
},
  "geometry": {"coordinates":[-72.975883,40.952556],"type":"Point"}
}