{
  "type": "Feature",
  "properties": {
    "addr:full":"255 E 207th St Bronx NY 10467",
    "addr:housenumber":"255",
    "addr:postcode":"10467",
    "addr:street":"E 207Th St",
    "iso:country":"US",
    "sg:address":"255 E 207th St",
    "sg:city":"Bronx",
    "sg:classifiers":[
        {
            "category":"Professional",
            "type":"Services"
        }
    ],
    "sg:phone":"+1 718 798 1558",
    "sg:postcode":"10467",
    "sg:province":"NY",
    "sg:tags":[
        "establishment"
    ],
    "wof:name":"255 LLC",
    "wof:placetype":"venue"
},
  "geometry": {"coordinates":[-73.877762,40.875701],"type":"Point"}
}