{
  "type": "Feature",
  "properties": {
    "iso:country":"US",
    "sg:address":"2435 Grand Island Blvd",
    "sg:city":"Grand Island",
    "sg:classifiers":[
        {
            "category":"Banks & Credit Unions",
            "subcategory":"Bank",
            "type":"Services"
        }
    ],
    "sg:phone":"+1 716 625 7600",
    "sg:postcode":"14072",
    "sg:province":"NY",
    "wof:name":"First Niagara Bank",
    "wof:placetype":"venue"
},
  "geometry": {"coordinates":[-78.97054900000001,43.029874],"type":"Point"}
}