{
  "type": "Feature",
  "properties": {
    "iso:country":"US",
    "sg:address":"101 Edden Ln",
    "sg:city":"Syracuse",
    "sg:classifiers":[
        {
            "category":"Freight",
            "type":"Transportation"
        }
    ],
    "sg:phone":"+1   ",
    "sg:postcode":"13212",
    "sg:province":"NY",
    "sg:tags":[
        "local",
        "contract",
        "trucker"
    ],
    "wof:name":"OConnor Trucking",
    "wof:placetype":"venue"
},
  "geometry": {"coordinates":[-76.14126899999999,43.139579],"type":"Point"}
}