{
  "type": "Feature",
  "properties": {
    "iso:country":"US",
    "sg:address":"4021 Bailey Ave",
    "sg:city":"Buffalo",
    "sg:classifiers":[
        {
            "category":"Insurance",
            "subcategory":"Insurance Agent",
            "type":"Services"
        }
    ],
    "sg:phone":"+1 716 838 8080",
    "sg:postcode":"14226",
    "sg:province":"NY",
    "wof:name":"Allstate Insurance Co",
    "wof:placetype":"venue"
},
  "geometry": {"coordinates":[-78.81379099999999,42.964634],"type":"Point"}
}