{
  "type": "Feature",
  "properties": {
    "iso:country":"US",
    "sg:address":"10383 Steamtown Rd",
    "sg:city":"Lindley",
    "sg:classifiers":[
        {
            "category":"Wholesale",
            "subcategory":"Books, Periodicals, & Newspapers",
            "type":"Manufacturing & Wholesale Goods"
        }
    ],
    "sg:phone":"+1 607 372 0489",
    "sg:postcode":"14858",
    "sg:province":"NY",
    "sg:tags":[
        "publisher",
        "book"
    ],
    "wof:name":"Prime Time Painting Press",
    "wof:placetype":"venue"
},
  "geometry": {"coordinates":[-77.08460599999999,42.021643],"type":"Point"}
}