{
  "type": "Feature",
  "properties": {
    "iso:country":"US",
    "sg:address":"11 E 55 St",
    "sg:city":"New York",
    "sg:classifiers":[
        {
            "category":"Restaurant",
            "type":"Food & Drink"
        }
    ],
    "sg:phone":"+1   ",
    "sg:postcode":"10022",
    "sg:province":"NY",
    "sg:tags":[
        "catering"
    ],
    "wof:name":"Cestbon Cafe",
    "wof:placetype":"venue"
},
  "geometry": {"coordinates":[-73.97359299999999,40.761232],"type":"Point"}
}