{
  "type": "Feature",
  "properties": {
    "addr:full":"820 Boynton Ave Bronx NY 10473",
    "addr:housenumber":"820",
    "addr:postcode":"10473",
    "addr:street":"Boynton Ave",
    "iso:country":"US",
    "sg:address":"820 Boynton Ave",
    "sg:city":"Bronx",
    "sg:classifiers":[
        {
            "category":"Real Estate",
            "subcategory":"Real Estate Agent",
            "type":"Services"
        }
    ],
    "sg:phone":"+1 718 991 7352",
    "sg:postcode":"10473",
    "sg:province":"NY",
    "wof:name":"Lafayette-Morrison Housing",
    "wof:placetype":"venue"
},
  "geometry": {"coordinates":[-73.876245,40.820358],"type":"Point"}
}