{
  "type": "Feature",
  "properties": {
    "addr:full":"369 Terry Hill Rd Horseheads NY 14845",
    "addr:housenumber":"369",
    "addr:postcode":"14845",
    "addr:street":"Terry Hill Rd",
    "iso:country":"US",
    "sg:address":"369 Terry Hill Rd",
    "sg:city":"Horseheads",
    "sg:classifiers":[
        {
            "category":"Organizations",
            "subcategory":"Religious Organization",
            "type":"Services"
        }
    ],
    "sg:phone":"+1 607 739 0437",
    "sg:postcode":"14845",
    "sg:province":"NY",
    "sg:tags":[
        "clergy"
    ],
    "wof:name":"John H Valk",
    "wof:placetype":"venue"
},
  "geometry": {"coordinates":[-76.76495,42.29414],"type":"Point"}
}