{
  "type": "Feature",
  "properties": {
    "addr:full":"864 Driving Park Ave # 4 Rochester NY 14613",
    "addr:housenumber":"864",
    "addr:postcode":"14613",
    "addr:street":"Driving Park Ave # 4",
    "iso:country":"US",
    "sg:address":"864 Driving Park Ave # 4",
    "sg:city":"Rochester",
    "sg:classifiers":[
        {
            "category":"Manufacturing",
            "subcategory":"Glass & Minerals",
            "type":"Manufacturing & Wholesale Goods"
        },
        {
            "category":"Manufacturing",
            "subcategory":"Building Materials",
            "type":"Manufacturing & Wholesale Goods"
        }
    ],
    "sg:phone":"+1 585 647 9333",
    "sg:postcode":"14613",
    "sg:province":"NY",
    "sg:tags":[
        "plate",
        "window",
        "glazier",
        "replacement",
        "repair"
    ],
    "wof:name":"Division 8 Glazing",
    "wof:placetype":"venue"
},
  "geometry": {"coordinates":[-77.65307799999999,43.182877],"type":"Point"}
}