{
  "type": "Feature",
  "properties": {
    "addr:full":"853 Lafayette Ave Brooklyn NY 11221",
    "addr:housenumber":"853",
    "addr:postcode":"11221",
    "addr:street":"Lafayette Ave",
    "iso:country":"US",
    "sg:address":"853 Lafayette Ave",
    "sg:city":"Brooklyn",
    "sg:classifiers":[
        {
            "category":"Building & Trades",
            "subcategory":"Construction",
            "type":"Services"
        }
    ],
    "sg:phone":"+1 718 443 8838",
    "sg:postcode":"11221",
    "sg:province":"NY",
    "sg:tags":[
        "company"
    ],
    "wof:name":"Ashraf Construction Co",
    "wof:placetype":"venue"
},
  "geometry": {"coordinates":[-73.937682,40.691491],"type":"Point"}
}