{
  "type": "Feature",
  "properties": {
    "iso:country":"US",
    "sg:address":"120 Pruyn Hill Rd",
    "sg:city":"Mechanicville",
    "sg:classifiers":[
        {
            "category":"Building & Trades",
            "subcategory":"Construction",
            "type":"Services"
        }
    ],
    "sg:phone":"+1 518 664 7224",
    "sg:postcode":"12118",
    "sg:province":"NY",
    "sg:tags":[
        "house"
    ],
    "wof:name":"Gervais Construction Inc",
    "wof:placetype":"venue"
},
  "geometry": {"coordinates":[-73.711922,42.899045],"type":"Point"}
}