{
  "type": "Feature",
  "properties": {
    "iso:country":"US",
    "sg:address":"560 North Ave",
    "sg:city":"New Rochelle",
    "sg:classifiers":[
        {
            "category":"Restaurant",
            "type":"Food & Drink"
        }
    ],
    "sg:phone":"+1 914 637 8560",
    "sg:postcode":"10801",
    "sg:province":"NY",
    "wof:name":"Bombay Express",
    "wof:placetype":"venue"
},
  "geometry": {"coordinates":[-73.787319,40.92079],"type":"Point"}
}