{
  "type": "Feature",
  "properties": {
    "iso:country":"US",
    "sg:address":"929 S Salina St",
    "sg:city":"Syracuse",
    "sg:classifiers":[
        {
            "category":"Shopping",
            "subcategory":"Clothing, Apparel, & Fashions",
            "type":"Retail Goods"
        }
    ],
    "sg:phone":"+1 315 422 3447",
    "sg:postcode":"13202",
    "sg:province":"NY",
    "sg:tags":[
        "furnishing"
    ],
    "wof:name":"Brother 2",
    "wof:placetype":"venue"
},
  "geometry": {"coordinates":[-76.149522,43.036559],"type":"Point"}
}