{
  "type": "Feature",
  "properties": {
    "iso:country":"US",
    "sg:address":"287 Central Ave",
    "sg:city":"White Plains",
    "sg:classifiers":[
        {
            "category":"Bars & Pubs",
            "subcategory":"Sports Bar",
            "type":"Food & Drink"
        }
    ],
    "sg:menulink":"http://www.allmenus.com/ny/white-plains/1724-central-park-sports-pub/menu/",
    "sg:postcode":"10606",
    "sg:province":"NY",
    "sg:tags":[
        "american"
    ],
    "wof:name":"Central Park Sports Pub",
    "wof:placetype":"venue"
},
  "geometry": {"coordinates":[-73.78296899999999,41.034572],"type":"Point"}
}