{
  "type": "Feature",
  "properties": {
    "addr:full":"8 Buena Vista Dr Hastings On Hdsn NY 10706",
    "addr:housenumber":"8",
    "addr:postcode":"10706",
    "addr:street":"Buena Vista Dr",
    "iso:country":"US",
    "sg:address":"8 Buena Vista Dr",
    "sg:city":"Hastings On Hdsn",
    "sg:classifiers":[
        {
            "category":"Manufacturing",
            "subcategory":"Printing",
            "type":"Manufacturing & Wholesale Goods"
        }
    ],
    "sg:phone":"+1 914 478 0400",
    "sg:postcode":"10706",
    "sg:province":"NY",
    "sg:tags":[
        "publisher",
        "music"
    ],
    "wof:name":"Oasis Music Inc",
    "wof:placetype":"venue"
},
  "geometry": {"coordinates":[-73.87591399999999,41.000945],"type":"Point"}
}