{
  "type": "Feature",
  "properties": {
    "addr:full":"8 W 70th St New York NY 10023",
    "addr:housenumber":"8",
    "addr:postcode":"10023",
    "addr:street":"W 70Th St",
    "iso:country":"US",
    "sg:address":"8 W 70th St",
    "sg:city":"New York",
    "sg:classifiers":[
        {
            "category":"Place Of Worship",
            "subcategory":"Synagogue",
            "type":"Public Place"
        }
    ],
    "sg:phone":"+1 212 873 0300",
    "sg:postcode":"10023",
    "sg:province":"NY",
    "wof:name":"Congregation Shearith Israel",
    "wof:placetype":"venue"
},
  "geometry": {"coordinates":[-73.977097,40.775101],"type":"Point"}
}