{
  "type": "Feature",
  "properties": {
    "addr:full":"1502 Avenue J Brooklyn NY 11230",
    "addr:housenumber":"1502",
    "addr:postcode":"11230",
    "addr:street":"Avenue J",
    "iso:country":"US",
    "sg:address":"1502 Avenue J",
    "sg:city":"Brooklyn",
    "sg:classifiers":[
        {
            "category":"Shopping",
            "subcategory":"Crafts & Fabrics",
            "type":"Retail Goods"
        },
        {
            "category":"Shopping",
            "subcategory":"Gifts & Souvenirs",
            "type":"Retail Goods"
        },
        {
            "category":"Shopping",
            "subcategory":"Florist",
            "type":"Retail Goods"
        },
        {
            "category":"Farming",
            "subcategory":"Nursery",
            "type":"Manufacturing & Wholesale Goods"
        },
        {
            "category":"Home & Garden",
            "subcategory":"Garden Supply",
            "type":"Retail Goods"
        },
        {
            "category":"Personal",
            "type":"Services"
        }
    ],
    "sg:phone":"+1 718 377 4350",
    "sg:postcode":"11230",
    "sg:province":"NY",
    "sg:tags":[
        "plant",
        "gardening",
        "nurseries-plants",
        "etc-retail",
        "balloon",
        "tree",
        "dried",
        "basket",
        "trees-silk",
        "flowers",
        "decorator"
    ],
    "sg:website":"www.avenuejflorist.net",
    "wof:name":"Avenue J Florist",
    "wof:placetype":"venue"
},
  "geometry": {"coordinates":[-73.961294,40.625079],"type":"Point"}
}