{
  "type": "Feature",
  "properties": {
    "addr:full":"417 E 72 St New York NY 10021",
    "addr:housenumber":"417;72",
    "addr:postcode":"10021",
    "addr:street":"E;St",
    "iso:country":"US",
    "sg:address":"417 E 72 St",
    "sg:city":"New York",
    "sg:classifiers":[
        {
            "category":"Real Estate",
            "subcategory":"Real Estate Operator",
            "type":"Services"
        }
    ],
    "sg:phone":"+1 212 308 0030",
    "sg:postcode":"10021",
    "sg:province":"NY",
    "sg:tags":[
        "building",
        "apartment"
    ],
    "wof:name":"235 W 71st St LLC",
    "wof:placetype":"venue"
},
  "geometry": {"coordinates":[-73.954252,40.76722],"type":"Point"}
}