{
  "type": "Feature",
  "properties": {
    "addr:full":"269 W 71 St New York NY 10023",
    "addr:housenumber":"269",
    "addr:postcode":"10023",
    "addr:street":"W 71 St",
    "iso:country":"US",
    "sg:address":"269 W 71 St",
    "sg:city":"New York",
    "sg:classifiers":[
        {
            "category":"Professional",
            "subcategory":"Lawyer & Legal Services",
            "type":"Services"
        }
    ],
    "sg:phone":"+1   ",
    "sg:postcode":"10023",
    "sg:province":"NY",
    "wof:name":"Radon Jenik",
    "wof:placetype":"venue"
},
  "geometry": {"coordinates":[-73.983824,40.778571],"type":"Point"}
}