{
  "type": "Feature",
  "properties": {
    "iso:country":"US",
    "sg:address":"67 E Seneca St",
    "sg:city":"Oswego",
    "sg:classifiers":[
        {
            "category":"Bars & Pubs",
            "type":"Food & Drink"
        }
    ],
    "sg:phone":"+1   ",
    "sg:postcode":"13126",
    "sg:province":"NY",
    "sg:tags":[
        "drinking"
    ],
    "wof:name":"Shamrock Tavern",
    "wof:placetype":"venue"
},
  "geometry": {"coordinates":[-76.504925,43.46136],"type":"Point"}
}