{
  "type": "Feature",
  "properties": {
    "iso:country":"US",
    "sg:address":"4 Oxford Xing",
    "sg:city":"New Hartford",
    "sg:classifiers":[
        {
            "category":"Building & Trades",
            "subcategory":"Cleaning & Sanitation",
            "type":"Services"
        }
    ],
    "sg:phone":"+1 315 733 0000",
    "sg:postcode":"13413",
    "sg:province":"NY",
    "sg:tags":[
        "maintenance",
        "contractor"
    ],
    "wof:name":"Colonial Chimney Swee",
    "wof:placetype":"venue"
},
  "geometry": {"coordinates":[-75.278854,43.054199],"type":"Point"}
}