{
  "type": "Feature",
  "properties": {
    "addr:full":"151 S Main St Ellenville NY 12428",
    "addr:housenumber":"151",
    "addr:postcode":"12428",
    "addr:street":"S Main St",
    "iso:country":"US",
    "sg:address":"151 S Main St",
    "sg:city":"Ellenville",
    "sg:classifiers":[
        {
            "category":"Shopping",
            "subcategory":"Computers & Home Electronics",
            "type":"Retail Goods"
        }
    ],
    "sg:phone":"+1   ",
    "sg:postcode":"12428",
    "sg:province":"NY",
    "sg:tags":[
        "repair"
    ],
    "wof:name":"H L Custom Stereo",
    "wof:placetype":"venue"
},
  "geometry": {"coordinates":[-74.39831,41.71404],"type":"Point"}
}