{
  "type": "Feature",
  "properties": {
    "addr:full":"722 Myrtle Ave Brooklyn NY 11205",
    "addr:housenumber":"722",
    "addr:postcode":"11205",
    "addr:street":"Myrtle Ave",
    "iso:country":"US",
    "sg:address":"722 Myrtle Ave",
    "sg:city":"Brooklyn",
    "sg:phone":"+1 718 522 7020",
    "sg:postcode":"11205",
    "sg:province":"NY",
    "sg:tags":[
        "equipment",
        "commercial",
        "supply"
    ],
    "wof:name":"Jasons Kitchen Supply Inc",
    "wof:placetype":"venue"
},
  "geometry": {"coordinates":[-73.955197,40.694688],"type":"Point"}
}