{
  "type": "Feature",
  "properties": {
    "iso:country":"US",
    "sg:address":"7801 3rd Ave Ste 1R",
    "sg:city":"Brooklyn",
    "sg:classifiers":[
        {
            "category":"Building & Trades",
            "subcategory":"Locksmith",
            "type":"Services"
        }
    ],
    "sg:phone":"+1 347 226 5989",
    "sg:postcode":"11228",
    "sg:province":"NY",
    "sg:tags":[
        "key"
    ],
    "sg:website":"www.oncalllocksmithbrooklyn.com",
    "wof:name":"On Call Lockout & Security Services",
    "wof:placetype":"venue"
},
  "geometry": {"coordinates":[-74.02839899999999,40.629083],"type":"Point"}
}