{
  "type": "Feature",
  "properties": {
    "addr:full":"128 Nostrand Ave Brooklyn NY 11205",
    "addr:housenumber":"128",
    "addr:postcode":"11205",
    "addr:street":"Nostrand Ave",
    "iso:country":"US",
    "sg:address":"128 Nostrand Ave",
    "sg:city":"Brooklyn",
    "sg:classifiers":[
        {
            "category":"Food & Beverages",
            "subcategory":"Groceries & Convenience Stores",
            "type":"Retail Goods"
        }
    ],
    "sg:phone":"+1   ",
    "sg:postcode":"11205",
    "sg:province":"NY",
    "wof:name":"Felipe S Grocery",
    "wof:placetype":"venue"
},
  "geometry": {"coordinates":[-73.95278,40.696434],"type":"Point"}
}