{
  "type": "Feature",
  "properties": {
    "iso:country":"US",
    "sg:address":"165 Voice Rd",
    "sg:city":"Carle Place",
    "sg:classifiers":[
        {
            "category":"Restaurant",
            "type":"Food & Drink"
        }
    ],
    "sg:phone":"+1 516 747 3663",
    "sg:postcode":"11514",
    "sg:province":"NY",
    "sg:tags":[
        "pizza"
    ],
    "sg:website":"donfilippo.kpsearch.com",
    "wof:name":"Don Filippo Trattoria Inc",
    "wof:placetype":"venue"
},
  "geometry": {"coordinates":[-73.620499,40.746899],"type":"Point"}
}