{
  "type": "Feature",
  "properties": {
    "addr:full":"28 Pryer Ln Larchmont NY 10538",
    "addr:housenumber":"28",
    "addr:postcode":"10538",
    "addr:street":"Pryer Ln",
    "iso:country":"US",
    "sg:address":"28 Pryer Ln",
    "sg:city":"Larchmont",
    "sg:classifiers":[
        {
            "category":"Banks & Credit Unions",
            "subcategory":"Investment Brokerage",
            "type":"Services"
        }
    ],
    "sg:phone":"+1 914 834 9660",
    "sg:postcode":"10538",
    "sg:province":"NY",
    "sg:tags":[
        "consultant",
        "financial"
    ],
    "wof:name":"A A Fischer & Co Inc",
    "wof:placetype":"venue"
},
  "geometry": {"coordinates":[-73.753244,40.919623],"type":"Point"}
}