{
  "type": "Feature",
  "properties": {
    "iso:country":"US",
    "sg:address":"1040 Oregon Rd",
    "sg:city":"Cortlandt Manor",
    "sg:classifiers":[
        {
            "category":"Shopping",
            "type":"Retail Goods"
        }
    ],
    "sg:phone":"+1 914 737 6660",
    "sg:postcode":"10567",
    "sg:province":"NY",
    "sg:tags":[
        "tropical",
        "fish"
    ],
    "wof:name":"Wet & Wild Aquariums",
    "wof:placetype":"venue"
},
  "geometry": {"coordinates":[-73.898427,41.316435],"type":"Point"}
}