{
  "type": "Feature",
  "properties": {
    "addr:full":"7 Schoen Pl Pittsford NY 14534",
    "addr:housenumber":"7",
    "addr:postcode":"14534",
    "addr:street":"Schoen Pl",
    "iso:country":"US",
    "sg:address":"7 Schoen Pl",
    "sg:city":"Pittsford",
    "sg:classifiers":[
        {
            "category":"Personal",
            "subcategory":"Beauty Salon",
            "type":"Services"
        }
    ],
    "sg:phone":"+1 585 248 8020",
    "sg:postcode":"14534",
    "sg:province":"NY",
    "sg:tags":[
        "shop"
    ],
    "wof:name":"Hair Barn",
    "wof:placetype":"venue"
},
  "geometry": {"coordinates":[-77.510729,43.089398],"type":"Point"}
}