{
  "type": "Feature",
  "properties": {
    "iso:country":"US",
    "sg:address":"112 Phylis Ct",
    "sg:city":"Elmont",
    "sg:classifiers":[
        {
            "category":"Utilities",
            "subcategory":"Refuse",
            "type":"Services"
        }
    ],
    "sg:phone":"+1   ",
    "sg:postcode":"11003",
    "sg:province":"NY",
    "sg:tags":[
        "disposal",
        "rubbish",
        "collection"
    ],
    "wof:name":"Liberty Ashes Inc",
    "wof:placetype":"venue"
},
  "geometry": {"coordinates":[-73.711949,40.705181],"type":"Point"}
}