{
  "type": "Feature",
  "properties": {
    "iso:country":"US",
    "sg:address":"1479 York Ave Frnt 1",
    "sg:city":"New York",
    "sg:classifiers":[
        {
            "category":"Restaurant",
            "type":"Food & Drink"
        }
    ],
    "sg:phone":"+1 212 988 5153",
    "sg:postcode":"10021",
    "sg:province":"NY",
    "sg:tags":[
        "traditional",
        "american"
    ],
    "wof:name":"Dresner's Restaurant",
    "wof:placetype":"venue"
},
  "geometry": {"coordinates":[-73.950996,40.770699],"type":"Point"}
}