{
  "type": "Feature",
  "properties": {
    "iso:country":"US",
    "sg:address":"1998 Foster Valley Rd",
    "sg:city":"Owego",
    "sg:classifiers":[
        {
            "category":"Professional",
            "subcategory":"Management & Consulting",
            "type":"Services"
        }
    ],
    "sg:phone":"+1 607 757 0823",
    "sg:postcode":"13827",
    "sg:province":"NY",
    "sg:tags":[
        "communications",
        "consultant"
    ],
    "wof:name":"A C M Inc",
    "wof:placetype":"venue"
},
  "geometry": {"coordinates":[-76.14353199999999,42.129141],"type":"Point"}
}