{
  "type": "Feature",
  "properties": {
    "addr:full":"60 E 65 St New York NY 10065",
    "addr:housenumber":"60;65",
    "addr:postcode":"10065",
    "addr:street":"E;St",
    "iso:country":"US",
    "sg:address":"60 E 65 St",
    "sg:city":"New York",
    "sg:classifiers":[
        {
            "category":"Retail",
            "subcategory":"Auto Repair",
            "type":"Services"
        }
    ],
    "sg:phone":"+1 212 903 0607",
    "sg:postcode":"10065",
    "sg:province":"NY",
    "sg:tags":[
        "wrecker"
    ],
    "wof:name":"24 Hour 7 Day Emerg Towing",
    "wof:placetype":"venue"
},
  "geometry": {"coordinates":[-73.967657,40.76691],"type":"Point"}
}