{
  "type": "Feature",
  "properties": {
    "addr:full":"28 E 22 St New York NY 10010",
    "addr:housenumber":"28;22",
    "addr:postcode":"10010",
    "addr:street":"E",
    "iso:country":"US",
    "sg:address":"28 E 22 St",
    "sg:city":"New York",
    "sg:classifiers":[
        {
            "category":"Professional",
            "type":"Services"
        }
    ],
    "sg:phone":"+1 212 473 5561",
    "sg:postcode":"10010",
    "sg:province":"NY",
    "sg:tags":[
        "establishment"
    ],
    "wof:name":"Afa Loft Inc",
    "wof:placetype":"venue"
},
  "geometry": {"coordinates":[-73.987317,40.739696],"type":"Point"}
}