{
  "type": "Feature",
  "properties": {
    "iso:country":"US",
    "sg:address":"290 Larkin St",
    "sg:city":"Buffalo",
    "sg:classifiers":[
        {
            "category":"Shopping",
            "subcategory":"Discount & Variety Stores",
            "type":"Retail Goods"
        }
    ],
    "sg:phone":"+1   ",
    "sg:postcode":"14210",
    "sg:province":"NY",
    "sg:tags":[
        "merchandise",
        "general"
    ],
    "wof:name":"Army Navy Surplus Outlet",
    "wof:placetype":"venue"
},
  "geometry": {"coordinates":[-78.852828,42.876333],"type":"Point"}
}