{
  "type": "Feature",
  "properties": {
    "iso:country":"US",
    "sg:address":"1228 Stewart Ave",
    "sg:city":"Bethpage",
    "sg:classifiers":[
        {
            "category":"Real Estate",
            "subcategory":"Real Estate Agent",
            "type":"Services"
        }
    ],
    "sg:phone":"+1 516 932 3559",
    "sg:postcode":"11714",
    "sg:province":"NY",
    "wof:name":"Barbra Enright Realtor",
    "wof:placetype":"venue"
},
  "geometry": {"coordinates":[-73.49898399999999,40.764397],"type":"Point"}
}