{
  "type": "Feature",
  "properties": {
    "addr:full":"360 Merrick Rd Fl 3 Lynbrook NY 11563",
    "addr:housenumber":"360;3",
    "addr:postcode":"11563",
    "addr:street":"Merrick Rd",
    "iso:country":"US",
    "sg:address":"360 Merrick Rd Fl 3",
    "sg:city":"Lynbrook",
    "sg:classifiers":[
        {
            "category":"Health Services",
            "subcategory":"Optometrist",
            "type":"Services"
        }
    ],
    "sg:phone":"+1 516 593 7709",
    "sg:postcode":"11563",
    "sg:province":"NY",
    "wof:name":"Caronia Ronald",
    "wof:placetype":"venue"
},
  "geometry": {"coordinates":[-73.672825,40.657219],"type":"Point"}
}