{
  "type": "Feature",
  "properties": {
    "addr:full":"15 W 84 St New York NY 10024",
    "addr:housenumber":"15",
    "addr:postcode":"10024",
    "addr:street":"W 84 St",
    "iso:country":"US",
    "sg:address":"15 W 84 St",
    "sg:city":"New York",
    "sg:classifiers":[
        {
            "category":"Real Estate",
            "subcategory":"Real Estate Operator",
            "type":"Services"
        }
    ],
    "sg:phone":"+1 212 362 7095",
    "sg:postcode":"10024",
    "sg:province":"NY",
    "sg:tags":[
        "building",
        "apartment"
    ],
    "wof:name":"15 West 84th Apartments Coop",
    "wof:placetype":"venue"
},
  "geometry": {"coordinates":[-73.972791,40.785065],"type":"Point"}
}