{
  "type": "Feature",
  "properties": {
    "iso:country":"US",
    "sg:address":"821 Broadway",
    "sg:city":"New York",
    "sg:classifiers":[
        {
            "category":"Shopping",
            "subcategory":"Shoes",
            "type":"Retail Goods"
        }
    ],
    "sg:phone":"+1 212 253 5511",
    "sg:postcode":"10003",
    "sg:province":"NY",
    "sg:tags":[
        "store"
    ],
    "wof:name":"David Z",
    "wof:placetype":"venue"
},
  "geometry": {"coordinates":[-73.991203,40.733101],"type":"Point"}
}