{
  "type": "Feature",
  "properties": {
    "addr:full":"4307 18th Ave Brooklyn NY 11218",
    "addr:housenumber":"4307",
    "addr:postcode":"11218",
    "addr:street":"18Th Ave",
    "iso:country":"US",
    "sg:address":"4307 18th Ave",
    "sg:city":"Brooklyn",
    "sg:classifiers":[
        {
            "category":"Travel",
            "subcategory":"Travel Agent",
            "type":"Entertainment"
        }
    ],
    "sg:phone":"+1   ",
    "sg:postcode":"11218",
    "sg:province":"NY",
    "sg:tags":[
        "agency"
    ],
    "wof:name":"Beshay Wael",
    "wof:placetype":"venue"
},
  "geometry": {"coordinates":[-73.977073,40.630716],"type":"Point"}
}