{
  "type": "Feature",
  "properties": {
    "iso:country":"US",
    "sg:address":"3636 Main St Suite 2D",
    "sg:city":"Flushing",
    "sg:classifiers":[
        {
            "category":"Banks & Credit Unions",
            "subcategory":"Investment Brokerage",
            "type":"Services"
        },
        {
            "category":"Banks & Credit Unions",
            "subcategory":"Bank",
            "type":"Services"
        },
        {
            "category":"Banks & Credit Unions",
            "subcategory":"Financial Services",
            "type":"Services"
        }
    ],
    "sg:phone":"+1 718 878 3836",
    "sg:postcode":"11354",
    "sg:province":"NY",
    "sg:tags":[
        "advisory",
        "mutual",
        "retirement",
        "annuity",
        "broker",
        "fund",
        "planning",
        "plan",
        "consultant",
        "security",
        "bond",
        "insurance",
        "stock"
    ],
    "sg:website":"http://newyork.citysearch.com/profile/external/604315672/flushing_ny/edward_jones_howard_w_chan.html?publisher=yellowpages&reference_id=1&placement=ypwebsitemip",
    "wof:name":"Edward Jones - HOWARD W CHAN",
    "wof:placetype":"venue"
},
  "geometry": {"coordinates":[-73.830456,40.760231],"type":"Point"}
}