{
  "type": "Feature",
  "properties": {
    "addr:full":"881 Broad St Salamanca NY 14779",
    "addr:housenumber":"881",
    "addr:postcode":"14779",
    "addr:street":"Broad St",
    "iso:country":"US",
    "sg:address":"881 Broad St",
    "sg:city":"Salamanca",
    "sg:classifiers":[
        {
            "category":"Restaurant",
            "type":"Food & Drink"
        }
    ],
    "sg:menulink":"http://www.allmenus.com/ny/salamanca/170054-burger-king/menu/",
    "sg:phone":"+1 716 945 0061",
    "sg:postcode":"14779",
    "sg:province":"NY",
    "sg:tags":[
        "burger",
        "american"
    ],
    "wof:name":"Burger King",
    "wof:placetype":"venue"
},
  "geometry": {"coordinates":[-78.74679399999999,42.15864],"type":"Point"}
}