{
  "type": "Feature",
  "properties": {
    "addr:full":"874 43rd St Brooklyn NY 11232",
    "addr:housenumber":"874",
    "addr:postcode":"11232",
    "addr:street":"43Rd St",
    "iso:country":"US",
    "sg:address":"874 43rd St",
    "sg:city":"Brooklyn",
    "sg:classifiers":[
        {
            "category":"Building & Trades",
            "subcategory":"Construction",
            "type":"Services"
        }
    ],
    "sg:phone":"+1 718 686 6392",
    "sg:postcode":"11232",
    "sg:province":"NY",
    "sg:tags":[
        "house"
    ],
    "wof:name":"Fine & Fair Construction  LLC",
    "wof:placetype":"venue"
},
  "geometry": {"coordinates":[-73.998735,40.644652],"type":"Point"}
}