{
  "type": "Feature",
  "properties": {
    "iso:country":"US",
    "sg:address":"117 Main St",
    "sg:city":"Akron",
    "sg:classifiers":[
        {
            "category":"Retail",
            "subcategory":"Funeral Services",
            "type":"Services"
        }
    ],
    "sg:phone":"+1   ",
    "sg:postcode":"14001",
    "sg:province":"NY",
    "wof:name":"Ross Funeral Home Inc",
    "wof:placetype":"venue"
},
  "geometry": {"coordinates":[-78.49708699999999,43.019977],"type":"Point"}
}