{
  "type": "Feature",
  "properties": {
    "addr:full":"595 Madison Avenue New York NY 10022",
    "addr:housenumber":"595",
    "addr:postcode":"10022",
    "addr:street":"Madison Avenue",
    "iso:country":"US",
    "sg:address":"595 Madison Avenue",
    "sg:city":"New York",
    "sg:classifiers":[
        {
            "category":"Health Services",
            "subcategory":"Dentist",
            "type":"Services"
        }
    ],
    "sg:phone":"+1 212 755 9882",
    "sg:postcode":"10022",
    "sg:province":"NY",
    "wof:name":"Osterman John R DDS",
    "wof:placetype":"venue"
},
  "geometry": {"coordinates":[-73.972167,40.762419],"type":"Point"}
}