{
  "type": "Feature",
  "properties": {
    "addr:full":"247 Dyckman St New York NY 10034",
    "addr:housenumber":"247",
    "addr:postcode":"10034",
    "addr:street":"Dyckman St",
    "iso:country":"US",
    "sg:address":"247 Dyckman St",
    "sg:city":"New York",
    "sg:classifiers":[
        {
            "category":"Restaurant",
            "type":"Food & Drink"
        }
    ],
    "sg:phone":"+1   ",
    "sg:postcode":"10034",
    "sg:province":"NY",
    "wof:name":"Pedros Restaurant",
    "wof:placetype":"venue"
},
  "geometry": {"coordinates":[-73.928551,40.866669],"type":"Point"}
}