{
  "type": "Feature",
  "properties": {
    "addr:full":"536 Barretto St Bronx NY 10474",
    "addr:housenumber":"536",
    "addr:postcode":"10474",
    "addr:street":"Barretto St",
    "iso:country":"US",
    "sg:address":"536 Barretto St",
    "sg:city":"Bronx",
    "sg:classifiers":[
        {
            "category":"Retail",
            "subcategory":"Laundry & Dry Cleaning",
            "type":"Services"
        }
    ],
    "sg:phone":"+1 718 991 1070",
    "sg:postcode":"10474",
    "sg:province":"NY",
    "sg:tags":[
        "cleaners"
    ],
    "wof:name":"Elite Suede & Leather Cleaning",
    "wof:placetype":"venue"
},
  "geometry": {"coordinates":[-73.888434,40.811122],"type":"Point"}
}