{
  "type": "Feature",
  "properties": {
    "addr:full":"424 W Beech St Long Beach NY 11561",
    "addr:housenumber":"424",
    "addr:postcode":"11561",
    "addr:street":"W Beech St",
    "iso:country":"US",
    "sg:address":"424 W Beech St",
    "sg:city":"Long Beach",
    "sg:classifiers":[
        {
            "category":"Recreation",
            "type":"Entertainment"
        }
    ],
    "sg:phone":"+1 516 829 9642",
    "sg:postcode":"11561",
    "sg:province":"NY",
    "sg:tags":[
        "instruction",
        "yoga"
    ],
    "wof:name":"Bikram Yoga Of Great Neck",
    "wof:placetype":"venue"
},
  "geometry": {"coordinates":[-73.677841,40.586023],"type":"Point"}
}