{
  "type": "Feature",
  "properties": {
    "addr:full":"4616 5th Ave Brooklyn NY 11220",
    "addr:housenumber":"4616",
    "addr:postcode":"11220",
    "addr:street":"5Th Ave",
    "iso:country":"US",
    "sg:address":"4616 5th Ave",
    "sg:city":"Brooklyn",
    "sg:classifiers":[
        {
            "category":"Real Estate",
            "subcategory":"Real Estate Agent",
            "type":"Services"
        }
    ],
    "sg:phone":"+1 718 567 7975",
    "sg:postcode":"11220",
    "sg:province":"NY",
    "wof:name":"Two Star Realty",
    "wof:placetype":"venue"
},
  "geometry": {"coordinates":[-74.008555,40.646925],"type":"Point"}
}