{
  "type": "Feature",
  "properties": {
    "addr:full":"46 Prince St Rochester NY 14607",
    "addr:housenumber":"46",
    "addr:postcode":"14607",
    "addr:street":"Prince St",
    "iso:country":"US",
    "sg:address":"46 Prince St",
    "sg:city":"Rochester",
    "sg:classifiers":[
        {
            "category":"Professional",
            "subcategory":"Management & Consulting",
            "type":"Services"
        },
        {
            "category":"Professional",
            "subcategory":"Advertising",
            "type":"Services"
        }
    ],
    "sg:phone":"+1 585 244 4140",
    "sg:postcode":"14607",
    "sg:province":"NY",
    "sg:tags":[
        "marketing",
        "program",
        "agency",
        "consultant"
    ],
    "wof:name":"Cbca Care Management",
    "wof:placetype":"venue"
},
  "geometry": {"coordinates":[-77.589854,43.158936],"type":"Point"}
}