{
  "type": "Feature",
  "properties": {
    "addr:full":"753 Caldwell Rd Herkimer NY 13350",
    "addr:housenumber":"753",
    "addr:postcode":"13350",
    "addr:street":"Caldwell Rd",
    "iso:country":"US",
    "sg:address":"753 Caldwell Rd",
    "sg:city":"Herkimer",
    "sg:phone":"+1 315 866 6747",
    "sg:postcode":"13350",
    "sg:province":"NY",
    "sg:tags":[
        "farm",
        "field",
        "crop"
    ],
    "wof:name":"Clearview Farms",
    "wof:placetype":"venue"
},
  "geometry": {"coordinates":[-75.01260000000001,43.088843],"type":"Point"}
}