{
  "type": "Feature",
  "properties": {
    "addr:full":"476 Joslen Blvd Hudson NY 12534",
    "addr:housenumber":"476",
    "addr:postcode":"12534",
    "addr:street":"Joslen Blvd",
    "iso:country":"US",
    "sg:address":"476 Joslen Blvd",
    "sg:city":"Hudson",
    "sg:classifiers":[
        {
            "category":"Professional",
            "type":"Services"
        }
    ],
    "sg:phone":"+1 518 828 5075",
    "sg:postcode":"12534",
    "sg:province":"NY",
    "sg:tags":[
        "doctor"
    ],
    "wof:name":"David Sullivan & Assocs",
    "wof:placetype":"venue"
},
  "geometry": {"coordinates":[-73.76300000000001,42.276199],"type":"Point"}
}