{
  "type": "Feature",
  "properties": {
    "addr:full":"530 Oliverea Rd Big Indian NY 12410",
    "addr:housenumber":"530",
    "addr:postcode":"12410",
    "addr:street":"Oliverea Rd",
    "iso:country":"US",
    "sg:address":"530 Oliverea Rd",
    "sg:city":"Big Indian",
    "sg:classifiers":[
        {
            "category":"Travel",
            "subcategory":"Hotels & Motels",
            "type":"Entertainment"
        }
    ],
    "sg:phone":"+1   ",
    "sg:postcode":"12410",
    "sg:province":"NY",
    "sg:tags":[
        "drinking",
        "operation"
    ],
    "sg:website":"www.coldspringlodge.com",
    "wof:name":"Cold Spring Lodge",
    "wof:placetype":"venue"
},
  "geometry": {"coordinates":[-74.44847,42.09996],"type":"Point"}
}