{
  "type": "Feature",
  "properties": {
    "iso:country":"US",
    "sg:address":"107 E Beard Ave",
    "sg:city":"Syracuse",
    "sg:classifiers":[
        {
            "category":"Organizations",
            "subcategory":"Religious Organization",
            "type":"Services"
        }
    ],
    "sg:phone":"+1 315 476 3737",
    "sg:postcode":"13205",
    "sg:province":"NY",
    "sg:tags":[
        "church"
    ],
    "wof:name":"New Covenant Baptist Church",
    "wof:placetype":"venue"
},
  "geometry": {"coordinates":[-76.144111,43.027499],"type":"Point"}
}