{
  "type": "Feature",
  "properties": {
    "iso:country":"US",
    "sg:address":"1370 Norton St",
    "sg:city":"Rochester",
    "sg:classifiers":[
        {
            "category":"Shopping",
            "subcategory":"Pharmacy",
            "type":"Retail Goods"
        }
    ],
    "sg:phone":"+1 585 342 6100",
    "sg:postcode":"14621",
    "sg:province":"NY",
    "sg:website":"www.cvs.com",
    "wof:name":"CVS Pharmacy",
    "wof:placetype":"venue"
},
  "geometry": {"coordinates":[-77.584666,43.187396],"type":"Point"}
}