{
  "type": "Feature",
  "properties": {
    "addr:full":"1015 Lynn Dr Valley Stream NY 11580",
    "addr:housenumber":"1015",
    "addr:postcode":"11580",
    "addr:street":"Lynn Dr",
    "iso:country":"US",
    "sg:address":"1015 Lynn Dr",
    "sg:city":"Valley Stream",
    "sg:classifiers":[
        {
            "category":"Communications",
            "type":"Services"
        }
    ],
    "sg:phone":"+1 800 570 2348",
    "sg:postcode":"11580",
    "sg:province":"NY",
    "sg:tags":[
        "recording",
        "rehearsal",
        "studio"
    ],
    "wof:name":"Cd Bros Inc",
    "wof:placetype":"venue"
},
  "geometry": {"coordinates":[-73.701599,40.681301],"type":"Point"}
}