{
  "type": "Feature",
  "properties": {
    "addr:full":"5550 Merrick Rd Massapequa NY 11758",
    "addr:housenumber":"5550",
    "addr:postcode":"11758",
    "addr:street":"Merrick Rd",
    "iso:country":"US",
    "sg:address":"5550 Merrick Rd",
    "sg:city":"Massapequa",
    "sg:classifiers":[
        {
            "category":"Bars & Pubs",
            "type":"Food & Drink"
        }
    ],
    "sg:phone":"+1 516 799 9269",
    "sg:postcode":"11758",
    "sg:province":"NY",
    "wof:name":"Napper Tandy's Of Massapequa",
    "wof:placetype":"venue"
},
  "geometry": {"coordinates":[-73.43182299999999,40.669356],"type":"Point"}
}