{
  "type": "Feature",
  "properties": {
    "addr:full":"36 Bridle Path Saint James NY 11780",
    "addr:housenumber":"36",
    "addr:postcode":"11780",
    "addr:street":"Bridle Path",
    "iso:country":"US",
    "sg:address":"36 Bridle Path",
    "sg:city":"Saint James",
    "sg:classifiers":[
        {
            "category":"Manufacturing",
            "subcategory":"Tools & Machinery",
            "type":"Manufacturing & Wholesale Goods"
        }
    ],
    "sg:phone":"+1   ",
    "sg:postcode":"11780",
    "sg:province":"NY",
    "sg:tags":[
        "process",
        "control",
        "engineering",
        "mfg",
        "instrument"
    ],
    "wof:name":"N A B Enterprises Inc",
    "wof:placetype":"venue"
},
  "geometry": {"coordinates":[-73.189289,40.893327],"type":"Point"}
}