{
  "type": "Feature",
  "properties": {
    "iso:country":"US",
    "sg:address":"279 Hillside Ave",
    "sg:city":"Williston Park",
    "sg:classifiers":[
        {
            "category":"Bars & Pubs",
            "type":"Food & Drink"
        }
    ],
    "sg:phone":"+1   ",
    "sg:postcode":"11596",
    "sg:province":"NY",
    "sg:tags":[
        "drinking"
    ],
    "wof:name":"Williston Tavern",
    "wof:placetype":"venue"
},
  "geometry": {"coordinates":[-73.64993699999999,40.754695],"type":"Point"}
}