{
  "type": "Feature",
  "properties": {
    "addr:full":"1309 Ave U Brooklyn NY 11229",
    "addr:housenumber":"1309",
    "addr:postcode":"11229",
    "addr:street":"Ave U",
    "iso:country":"US",
    "sg:address":"1309 Ave U",
    "sg:city":"Brooklyn",
    "sg:classifiers":[
        {
            "category":"Food & Beverages",
            "subcategory":"Specialty",
            "type":"Retail Goods"
        }
    ],
    "sg:phone":"+1   ",
    "sg:postcode":"11229",
    "sg:province":"NY",
    "sg:tags":[
        "health",
        "vitamin",
        "mfg"
    ],
    "wof:name":"Wealth of Health Nutrition Ctr",
    "wof:placetype":"venue"
},
  "geometry": {"coordinates":[-73.95740000000001,40.598797],"type":"Point"}
}