{
  "type": "Feature",
  "properties": {
    "addr:full":"530 E 86 St New York NY 10028",
    "addr:housenumber":"530;86",
    "addr:postcode":"10028",
    "addr:street":"E;St",
    "iso:country":"US",
    "sg:address":"530 E 86 St",
    "sg:city":"New York",
    "sg:classifiers":[
        {
            "category":"Professional",
            "subcategory":"Engineering",
            "type":"Services"
        }
    ],
    "sg:phone":"+1   ",
    "sg:postcode":"10028",
    "sg:province":"NY",
    "wof:name":"Alexander C Jennison & Pe",
    "wof:placetype":"venue"
},
  "geometry": {"coordinates":[-73.94476400000001,40.774936],"type":"Point"}
}