{
  "type": "Feature",
  "properties": {
    "iso:country":"US",
    "sg:address":"10 Carrington Ct",
    "sg:city":"Poughkeepsie",
    "sg:classifiers":[
        {
            "category":"Education",
            "subcategory":"Vocational School",
            "type":"Public Place"
        }
    ],
    "sg:phone":"+1 845 454 3638",
    "sg:postcode":"12603",
    "sg:province":"NY",
    "sg:tags":[
        "real estate"
    ],
    "wof:name":"Real Estate Learning Ctr",
    "wof:placetype":"venue"
},
  "geometry": {"coordinates":[-73.867121,41.663296],"type":"Point"}
}