{
  "type": "Feature",
  "properties": {
    "iso:country":"US",
    "sg:address":"74 State St",
    "sg:city":"Phoenix",
    "sg:classifiers":[
        {
            "category":"Professional",
            "subcategory":"Lawyer & Legal Services",
            "type":"Services"
        }
    ],
    "sg:phone":"+1 315 695 3032",
    "sg:postcode":"13135",
    "sg:province":"NY",
    "sg:tags":[
        "attorney"
    ],
    "wof:name":"Richard H Jarvis Law Offices",
    "wof:placetype":"venue"
},
  "geometry": {"coordinates":[-76.299286,43.22858],"type":"Point"}
}