{
  "type": "Feature",
  "properties": {
    "addr:full":"108 E 116th St New York NY 10029",
    "addr:housenumber":"108",
    "addr:postcode":"10029",
    "addr:street":"E 116Th St",
    "iso:country":"US",
    "sg:address":"108 E 116th St",
    "sg:city":"New York",
    "sg:classifiers":[
        {
            "category":"Shopping",
            "subcategory":"Clothing, Apparel, & Fashions",
            "type":"Retail Goods"
        }
    ],
    "sg:phone":"+1 212 427 9802",
    "sg:postcode":"10029",
    "sg:province":"NY",
    "wof:name":"B & B Fashions",
    "wof:placetype":"venue"
},
  "geometry": {"coordinates":[-73.94186000000001,40.798673],"type":"Point"}
}