{
  "type": "Feature",
  "properties": {
    "addr:full":"4266 Main St Millport NY 14864",
    "addr:housenumber":"4266",
    "addr:postcode":"14864",
    "addr:street":"Main St",
    "iso:country":"US",
    "sg:address":"4266 Main St",
    "sg:city":"Millport",
    "sg:classifiers":[
        {
            "category":"Government",
            "subcategory":"Post Office",
            "type":"Public Place"
        }
    ],
    "sg:phone":"+1   ",
    "sg:postcode":"14864",
    "sg:province":"NY",
    "sg:tags":[
        "postal",
        "us"
    ],
    "wof:name":"US Post Office",
    "wof:placetype":"venue"
},
  "geometry": {"coordinates":[-76.83453299999999,42.263327],"type":"Point"}
}