{
  "type": "Feature",
  "properties": {
    "iso:country":"US",
    "sg:address":"568 South Rd",
    "sg:city":"Poughkeepsie",
    "sg:classifiers":[
        {
            "category":"Restaurant",
            "type":"Food & Drink"
        }
    ],
    "sg:menulink":"http://www.allmenus.com/ny/poughkeepsie/32300-cappuccino-by-coppolas/menu/",
    "sg:phone":"+1 845 462 4545",
    "sg:postcode":"12601",
    "sg:province":"NY",
    "sg:tags":[
        "italian"
    ],
    "wof:name":"Cappuccino By Coppola's",
    "wof:placetype":"venue"
},
  "geometry": {"coordinates":[-73.928172,41.651027],"type":"Point"}
}