{
  "type": "Feature",
  "properties": {
    "addr:full":"5 Edge Hill Rd Wappingers Falls NY 12590",
    "addr:housenumber":"5",
    "addr:postcode":"12590",
    "addr:street":"Edge Hill Rd",
    "iso:country":"US",
    "sg:address":"5 Edge Hill Rd",
    "sg:city":"Wappingers Falls",
    "sg:classifiers":[
        {
            "category":"Home & Garden",
            "subcategory":"Home Furnishings",
            "type":"Retail Goods"
        }
    ],
    "sg:phone":"+1 845 297 4027",
    "sg:postcode":"12590",
    "sg:province":"NY",
    "sg:tags":[
        "quilting"
    ],
    "wof:name":"Quilt Rack",
    "wof:placetype":"venue"
},
  "geometry": {"coordinates":[-73.924757,41.619286],"type":"Point"}
}