{
  "type": "Feature",
  "properties": {
    "iso:country":"US",
    "sg:address":"15 Loder St",
    "sg:city":"Wellsville",
    "sg:classifiers":[
        {
            "category":"Health Services",
            "subcategory":"Doctor",
            "type":"Services"
        }
    ],
    "sg:phone":"+1 585 596 2040",
    "sg:postcode":"14895",
    "sg:province":"NY",
    "sg:tags":[
        "physician",
        "surgeon"
    ],
    "wof:name":"Women & Children's Health",
    "wof:placetype":"venue"
},
  "geometry": {"coordinates":[-77.94927300000001,42.123972],"type":"Point"}
}