{
  "type": "Feature",
  "properties": {
    "iso:country":"US",
    "sg:address":"51 Crest Ct",
    "sg:city":"Monsey",
    "sg:classifiers":[
        {
            "category":"Professional",
            "type":"Services"
        }
    ],
    "sg:phone":"+1   ",
    "sg:postcode":"10952",
    "sg:province":"NY",
    "wof:name":"Gold Reality",
    "wof:placetype":"venue"
},
  "geometry": {"coordinates":[-74.071518,41.126584],"type":"Point"}
}