{
  "type": "Feature",
  "properties": {
    "iso:country":"US",
    "sg:address":"230 Lyon St",
    "sg:city":"Valley Stream",
    "sg:classifiers":[
        {
            "category":"Professional",
            "type":"Services"
        }
    ],
    "sg:phone":"+1   ",
    "sg:postcode":"11580",
    "sg:province":"NY",
    "wof:name":"Sol Johnson Design",
    "wof:placetype":"venue"
},
  "geometry": {"coordinates":[-73.71641,40.676736],"type":"Point"}
}