{
  "type": "Feature",
  "properties": {
    "addr:full":"1666 State Rte 21 Palmyra NY 14522",
    "addr:housenumber":"1666",
    "addr:postcode":"14522",
    "addr:street":"State Rte 21",
    "iso:country":"US",
    "sg:address":"1666 State Rte 21",
    "sg:city":"Palmyra",
    "sg:classifiers":[
        {
            "category":"Professional",
            "subcategory":"Computer Services",
            "type":"Services"
        }
    ],
    "sg:phone":"+1 315 597 1248",
    "sg:postcode":"14522",
    "sg:province":"NY",
    "sg:tags":[
        "consultant",
        "designer"
    ],
    "wof:name":"Millennium Solutions",
    "wof:placetype":"venue"
},
  "geometry": {"coordinates":[-77.214718,43.069765],"type":"Point"}
}