{
  "type": "Feature",
  "properties": {
    "addr:full":"956 Front St Uniondale NY 11553",
    "addr:housenumber":"956",
    "addr:postcode":"11553",
    "addr:street":"Front St",
    "iso:country":"US",
    "sg:address":"956 Front St",
    "sg:city":"Uniondale",
    "sg:classifiers":[
        {
            "category":"Building & Trades",
            "subcategory":"Cleaning & Sanitation",
            "type":"Services"
        }
    ],
    "sg:phone":"+1 516 538 0433",
    "sg:postcode":"11553",
    "sg:province":"NY",
    "sg:tags":[
        "janitor"
    ],
    "wof:name":"Donalds Cleaning Svc",
    "wof:placetype":"venue"
},
  "geometry": {"coordinates":[-73.594624,40.70929],"type":"Point"}
}