{
  "type": "Feature",
  "properties": {
    "addr:full":"1250 Niagara Falls Blvd Tonawanda NY 14150",
    "addr:housenumber":"1250",
    "addr:postcode":"14150",
    "addr:street":"Niagara Falls Blvd",
    "iso:country":"US",
    "sg:address":"1250 Niagara Falls Blvd",
    "sg:city":"Tonawanda",
    "sg:classifiers":[
        {
            "category":"Food & Beverages",
            "subcategory":"Bakery",
            "type":"Retail Goods"
        }
    ],
    "sg:phone":"+1 716 332 0444",
    "sg:postcode":"14150",
    "sg:province":"NY",
    "sg:tags":[
        "doughnut"
    ],
    "sg:website":"www.krispykreme.com",
    "wof:name":"Krispy Kreme Doughnuts",
    "wof:placetype":"venue"
},
  "geometry": {"coordinates":[-78.82267299999999,42.98942],"type":"Point"}
}