{
  "type": "Feature",
  "properties": {
    "addr:full":"633 Jericho Tpke Syosset NY 11791",
    "addr:housenumber":"633",
    "addr:postcode":"11791",
    "addr:street":"Jericho Tpke",
    "iso:country":"US",
    "sg:address":"633 Jericho Tpke",
    "sg:city":"Syosset",
    "sg:classifiers":[
        {
            "category":"Real Estate",
            "subcategory":"Real Estate Services",
            "type":"Services"
        },
        {
            "category":"Real Estate",
            "subcategory":"Real Estate Agent",
            "type":"Services"
        }
    ],
    "sg:phone":"+1 516 921 0977",
    "sg:postcode":"11791",
    "sg:province":"NY",
    "sg:tags":[
        "rental"
    ],
    "wof:name":"Century 21 Prevete Real Estate",
    "wof:placetype":"venue"
},
  "geometry": {"coordinates":[-73.495177,40.811184],"type":"Point"}
}