{
  "type": "Feature",
  "properties": {
    "addr:full":"622 3rd Ave Fl 31 New York NY 10017",
    "addr:housenumber":"622;31",
    "addr:postcode":"10017",
    "addr:street":"3Rd Ave Fl",
    "iso:country":"US",
    "sg:address":"622 3rd Ave Fl 31",
    "sg:city":"New York",
    "sg:classifiers":[
        {
            "category":"Professional",
            "subcategory":"Accounting & Tax Preparation",
            "type":"Services"
        }
    ],
    "sg:phone":"+1 212 404 6198",
    "sg:postcode":"10017",
    "sg:province":"NY",
    "sg:tags":[
        "accountant"
    ],
    "wof:name":"Fti Consulting",
    "wof:placetype":"venue"
},
  "geometry": {"coordinates":[-73.975475,40.749777],"type":"Point"}
}