{
  "type": "Feature",
  "properties": {
    "addr:full":"1124 Liberty Ave Brooklyn NY 11208",
    "addr:housenumber":"1124",
    "addr:postcode":"11208",
    "addr:street":"Liberty Ave",
    "iso:country":"US",
    "sg:address":"1124 Liberty Ave",
    "sg:city":"Brooklyn",
    "sg:classifiers":[
        {
            "category":"Shopping",
            "subcategory":"Clothing, Apparel, & Fashions",
            "type":"Retail Goods"
        }
    ],
    "sg:phone":"+1   ",
    "sg:postcode":"11208",
    "sg:province":"NY",
    "sg:tags":[
        "ready"
    ],
    "wof:name":"Hot Stuff",
    "wof:placetype":"venue"
},
  "geometry": {"coordinates":[-73.867192,40.678605],"type":"Point"}
}