{
  "type": "Feature",
  "properties": {
    "iso:country":"US",
    "sg:address":"593 Academy St",
    "sg:city":"New York",
    "sg:classifiers":[
        {
            "category":"Professional",
            "type":"Services"
        }
    ],
    "sg:phone":"+1   ",
    "sg:postcode":"10034",
    "sg:province":"NY",
    "wof:name":"Choice Svces Nyc",
    "wof:placetype":"venue"
},
  "geometry": {"coordinates":[-73.92332500000001,40.86366],"type":"Point"}
}