{
  "type": "Feature",
  "properties": {
    "iso:country":"US",
    "sg:address":"500 5th Ave",
    "sg:city":"Brooklyn",
    "sg:classifiers":[
        {
            "category":"Shopping",
            "subcategory":"Jewelry",
            "type":"Retail Goods"
        }
    ],
    "sg:phone":"+1 718 788 4900",
    "sg:postcode":"11215",
    "sg:province":"NY",
    "sg:tags":[
        "jeweler"
    ],
    "wof:name":"Azena's Jewelry Inc",
    "wof:placetype":"venue"
},
  "geometry": {"coordinates":[-73.987999,40.667301],"type":"Point"}
}