{
  "type": "Feature",
  "properties": {
    "iso:country":"US",
    "sg:address":"2540 Town Line Rd",
    "sg:city":"Auburn",
    "sg:classifiers":[
        {
            "category":"Building & Trades",
            "subcategory":"Construction",
            "type":"Services"
        }
    ],
    "sg:phone":"+1 315 252 4459",
    "sg:postcode":"13021",
    "sg:province":"NY",
    "sg:tags":[
        "excavating",
        "contractor"
    ],
    "wof:name":"Tom Weaver Excavating & Ldscpg",
    "wof:placetype":"venue"
},
  "geometry": {"coordinates":[-76.575349,42.838574],"type":"Point"}
}