{
  "type": "Feature",
  "properties": {
    "addr:full":"1151 54th St Brooklyn NY 11219",
    "addr:housenumber":"1151",
    "addr:postcode":"11219",
    "addr:street":"54Th St",
    "iso:country":"US",
    "sg:address":"1151 54th St",
    "sg:city":"Brooklyn",
    "sg:phone":"+1 718 854 2660",
    "sg:postcode":"11219",
    "sg:province":"NY",
    "sg:tags":[
        "equipment",
        "fixture",
        "commercial",
        "store"
    ],
    "wof:name":"A-1 Displays, Inc",
    "wof:placetype":"venue"
},
  "geometry": {"coordinates":[-73.998307,40.634195],"type":"Point"}
}