{
  "type": "Feature",
  "properties": {
    "addr:full":"3512 Co Rd 5 Stanley NY 14561",
    "addr:housenumber":"3512",
    "addr:postcode":"14561",
    "addr:street":"Co Rd 5",
    "iso:country":"US",
    "sg:address":"3512 Co Rd 5",
    "sg:city":"Stanley",
    "sg:classifiers":[
        {
            "category":"Retail",
            "subcategory":"Auto Repair",
            "type":"Services"
        }
    ],
    "sg:phone":"+1 585 526 5551",
    "sg:postcode":"14561",
    "sg:province":"NY",
    "sg:tags":[
        "body"
    ],
    "wof:name":"Reds Auto Works Inc",
    "wof:placetype":"venue"
},
  "geometry": {"coordinates":[-77.077555,42.860213],"type":"Point"}
}