{
  "type": "Feature",
  "properties": {
    "iso:country":"US",
    "sg:address":"119 Benham St",
    "sg:city":"Penn Yan",
    "sg:classifiers":[
        {
            "category":"Wholesale",
            "subcategory":"Farm Supplies",
            "type":"Manufacturing & Wholesale Goods"
        }
    ],
    "sg:phone":"+1 315 536 7420",
    "sg:postcode":"14527",
    "sg:province":"NY",
    "sg:tags":[
        "feed"
    ],
    "wof:name":"Harry Griffin & Sons",
    "wof:placetype":"venue"
},
  "geometry": {"coordinates":[-77.052657,42.66473],"type":"Point"}
}