{
  "type": "Feature",
  "properties": {
    "addr:full":"2348 80th Street Brooklyn NY 11214",
    "addr:housenumber":"2348",
    "addr:postcode":"11214",
    "addr:street":"80Th Street",
    "iso:country":"US",
    "sg:address":"2348 80th Street",
    "sg:city":"Brooklyn",
    "sg:classifiers":[
        {
            "category":"Building & Trades",
            "subcategory":"Construction",
            "type":"Services"
        }
    ],
    "sg:phone":"+1 718 265 4320",
    "sg:postcode":"11214",
    "sg:province":"NY",
    "sg:tags":[
        "contractor"
    ],
    "sg:website":"www.pyramid-construction.com",
    "wof:name":"Pyramid Construction Company",
    "wof:placetype":"venue"
},
  "geometry": {"coordinates":[-73.98728199999999,40.603483],"type":"Point"}
}