{
  "type": "Feature",
  "properties": {
    "addr:full":"36 Longbow Cir Spencerport NY 14559",
    "addr:housenumber":"36",
    "addr:postcode":"14559",
    "addr:street":"Longbow Cir",
    "iso:country":"US",
    "sg:address":"36 Longbow Cir",
    "sg:city":"Spencerport",
    "sg:classifiers":[
        {
            "category":"Building & Trades",
            "subcategory":"Construction",
            "type":"Services"
        }
    ],
    "sg:phone":"+1 585 349 2969",
    "sg:postcode":"14559",
    "sg:province":"NY",
    "sg:tags":[
        "house"
    ],
    "wof:name":"Visac Builders",
    "wof:placetype":"venue"
},
  "geometry": {"coordinates":[-77.826143,43.191177],"type":"Point"}
}