{
  "type": "Feature",
  "properties": {
    "addr:full":"10 E 125th St New York NY 10035",
    "addr:housenumber":"10",
    "addr:postcode":"10035",
    "addr:street":"E 125Th St",
    "iso:country":"US",
    "sg:address":"10 E 125th St",
    "sg:city":"New York",
    "sg:classifiers":[
        {
            "category":"Food & Beverages",
            "subcategory":"Groceries & Convenience Stores",
            "type":"Retail Goods"
        }
    ],
    "sg:phone":"+1 212 369 2665",
    "sg:postcode":"10035",
    "sg:province":"NY",
    "wof:name":"Wild Olive Market",
    "wof:placetype":"venue"
},
  "geometry": {"coordinates":[-73.94163399999999,40.806123],"type":"Point"}
}