{
  "type": "Feature",
  "properties": {
    "iso:country":"US",
    "sg:address":"5 N Front St",
    "sg:city":"New Paltz",
    "sg:classifiers":[
        {
            "category":"Manufacturing",
            "subcategory":"Soap",
            "type":"Manufacturing & Wholesale Goods"
        }
    ],
    "sg:phone":"+1 845 255 2610",
    "sg:postcode":"12561",
    "sg:province":"NY",
    "sg:tags":[
        "detergent"
    ],
    "wof:name":"Rosner Soap",
    "wof:placetype":"venue"
},
  "geometry": {"coordinates":[-74.085251,41.748405],"type":"Point"}
}