{
  "type": "Feature",
  "properties": {
    "addr:full":"687 State Route 17M Monroe NY 10950",
    "addr:housenumber":"687",
    "addr:postcode":"10950",
    "addr:street":"State Route 17M",
    "iso:country":"US",
    "sg:address":"687 State Route 17M",
    "sg:city":"Monroe",
    "sg:classifiers":[
        {
            "category":"Food & Beverages",
            "subcategory":"Meat & Fish",
            "type":"Retail Goods"
        }
    ],
    "sg:phone":"+1 845 782 7996",
    "sg:postcode":"10950",
    "sg:province":"NY",
    "sg:tags":[
        "seafood",
        "market"
    ],
    "wof:name":"Monroe Farm",
    "wof:placetype":"venue"
},
  "geometry": {"coordinates":[-74.189499,41.326099],"type":"Point"}
}