{
  "type": "Feature",
  "properties": {
    "addr:full":"1745 Lakeville Rd Avon NY 14414",
    "addr:housenumber":"1745",
    "addr:postcode":"14414",
    "addr:street":"Lakeville Rd",
    "iso:country":"US",
    "sg:address":"1745 Lakeville Rd",
    "sg:city":"Avon",
    "sg:classifiers":[
        {
            "category":"Manufacturing",
            "subcategory":"Metals",
            "type":"Manufacturing & Wholesale Goods"
        }
    ],
    "sg:phone":"+1   ",
    "sg:postcode":"14414",
    "sg:province":"NY",
    "sg:tags":[
        "machine",
        "screw",
        "shop"
    ],
    "wof:name":"J & H Screw Products Corp",
    "wof:placetype":"venue"
},
  "geometry": {"coordinates":[-77.70685899999999,42.9057],"type":"Point"}
}