{
  "type": "Feature",
  "properties": {
    "addr:full":"1617 Third Ave Manhattan NY 10128",
    "addr:housenumber":"1617",
    "addr:postcode":"10128",
    "addr:street":"Third Ave",
    "iso:country":"US",
    "sg:address":"1617 Third Ave",
    "sg:city":"Manhattan",
    "sg:classifiers":[
        {
            "category":"Government",
            "subcategory":"Post Office",
            "type":"Public Place"
        }
    ],
    "sg:postcode":"10128",
    "sg:province":"NY",
    "wof:name":"US Post Office",
    "wof:placetype":"venue"
},
  "geometry": {"coordinates":[-73.951786,40.781805],"type":"Point"}
}