{
  "type": "Feature",
  "properties": {
    "iso:country":"US",
    "sg:address":"221 W 57 St",
    "sg:city":"New York",
    "sg:classifiers":[
        {
            "category":"Real Estate",
            "subcategory":"Architect",
            "type":"Services"
        }
    ],
    "sg:phone":"+1 212 245 0010",
    "sg:postcode":"10019",
    "sg:province":"NY",
    "sg:website":"www.jca-architects.com",
    "wof:name":"John Ciardullo Assoc",
    "wof:placetype":"venue"
},
  "geometry": {"coordinates":[-73.981004,40.765902],"type":"Point"}
}