{
  "type": "Feature",
  "properties": {
    "addr:full":"150 E 174th St Bronx NY 10457",
    "addr:housenumber":"150",
    "addr:postcode":"10457",
    "addr:street":"E 174Th St",
    "iso:country":"US",
    "sg:address":"150 E 174th St",
    "sg:city":"Bronx",
    "sg:classifiers":[
        {
            "category":"Food & Beverages",
            "subcategory":"Groceries & Convenience Stores",
            "type":"Retail Goods"
        }
    ],
    "sg:phone":"+1 718 716 7938",
    "sg:postcode":"10457",
    "sg:province":"NY",
    "sg:tags":[
        "grocer"
    ],
    "wof:name":"Woodycrest Grocery",
    "wof:placetype":"venue"
},
  "geometry": {"coordinates":[-73.909879,40.844794],"type":"Point"}
}