{
  "type": "Feature",
  "properties": {
    "addr:full":"315 Roxborough Rd Rochester NY 14619",
    "addr:housenumber":"315",
    "addr:postcode":"14619",
    "addr:street":"Roxborough Rd",
    "iso:country":"US",
    "sg:address":"315 Roxborough Rd",
    "sg:city":"Rochester",
    "sg:classifiers":[
        {
            "category":"Shopping",
            "type":"Retail Goods"
        }
    ],
    "sg:phone":"+1 585 328 8485",
    "sg:postcode":"14619",
    "sg:province":"NY",
    "sg:tags":[
        "cards",
        "sport",
        "baseball",
        "memorabilia"
    ],
    "wof:name":"Sports Delight",
    "wof:placetype":"venue"
},
  "geometry": {"coordinates":[-77.660363,43.14047],"type":"Point"}
}