{
  "type": "Feature",
  "properties": {
    "iso:country":"US",
    "sg:address":"314 N Mechanic St",
    "sg:city":"Carthage",
    "sg:classifiers":[
        {
            "category":"Retail",
            "subcategory":"Animal Services",
            "type":"Services"
        }
    ],
    "sg:phone":"+1 315 493 0129",
    "sg:postcode":"13619",
    "sg:province":"NY",
    "sg:tags":[
        "pet",
        "grooming",
        "washing"
    ],
    "wof:name":"Tailored To Purrfection",
    "wof:placetype":"venue"
},
  "geometry": {"coordinates":[-75.611954,43.981507],"type":"Point"}
}