{
  "type": "Feature",
  "properties": {
    "addr:full":"32 Little W 12th St New York NY 10014",
    "addr:housenumber":"32",
    "addr:postcode":"10014",
    "addr:street":"Little W 12Th St",
    "iso:country":"US",
    "sg:address":"32 Little W 12th St",
    "sg:city":"New York",
    "sg:classifiers":[
        {
            "category":"Shopping",
            "subcategory":"Clothing, Apparel, & Fashions",
            "type":"Retail Goods"
        }
    ],
    "sg:phone":"+1   ",
    "sg:postcode":"10014",
    "sg:province":"NY",
    "wof:name":"HP Friends Inc",
    "wof:placetype":"venue"
},
  "geometry": {"coordinates":[-74.007064,40.739731],"type":"Point"}
}