{
  "type": "Feature",
  "properties": {
    "addr:full":"11-50 44 Rd Long Island City NY 11101",
    "addr:housenumber":"11-50",
    "addr:postcode":"11101",
    "addr:street":"44 Rd",
    "iso:country":"US",
    "sg:address":"11-50 44 Rd",
    "sg:city":"Long Island City",
    "sg:classifiers":[
        {
            "category":"Food & Beverages",
            "subcategory":"Groceries & Convenience Stores",
            "type":"Retail Goods"
        }
    ],
    "sg:phone":"+1 718 786 3200",
    "sg:postcode":"11101",
    "sg:province":"NY",
    "wof:name":"Parker House Coffee Co",
    "wof:placetype":"venue"
},
  "geometry": {"coordinates":[-73.948621,40.749129],"type":"Point"}
}