{
  "type": "Feature",
  "properties": {
    "iso:country":"US",
    "sg:address":"2030 Bedford Ave",
    "sg:city":"Brooklyn",
    "sg:classifiers":[
        {
            "category":"Restaurant",
            "type":"Food & Drink"
        }
    ],
    "sg:phone":"+1 718 287 4868",
    "sg:postcode":"11226",
    "sg:province":"NY",
    "wof:name":"Print Fried Chicken",
    "wof:placetype":"venue"
},
  "geometry": {"coordinates":[-73.95643099999999,40.65575],"type":"Point"}
}