{
  "type": "Feature",
  "properties": {
    "addr:full":"250 Glenwild Rd Middle Grove NY 12025",
    "addr:housenumber":"250",
    "addr:postcode":"12025",
    "addr:street":"Glenwild Rd",
    "iso:country":"US",
    "sg:address":"250 Glenwild Rd",
    "sg:city":"Middle Grove",
    "sg:classifiers":[
        {
            "category":"Freight",
            "type":"Transportation"
        }
    ],
    "sg:phone":"+1   ",
    "sg:postcode":"12025",
    "sg:province":"NY",
    "sg:tags":[
        "operator",
        "local",
        "trucking"
    ],
    "wof:name":"Adirondack Delivery",
    "wof:placetype":"venue"
},
  "geometry": {"coordinates":[-74.05868599999999,43.121702],"type":"Point"}
}