{
  "type": "Feature",
  "properties": {
    "addr:full":"26 Lake St Owego NY 13827",
    "addr:housenumber":"26",
    "addr:postcode":"13827",
    "addr:street":"Lake St",
    "iso:country":"US",
    "sg:address":"26 Lake St",
    "sg:city":"Owego",
    "sg:classifiers":[
        {
            "category":"Personal",
            "subcategory":"Barber",
            "type":"Services"
        }
    ],
    "sg:phone":"+1 607 687 9880",
    "sg:postcode":"13827",
    "sg:province":"NY",
    "wof:name":"Andy's Barber Shop",
    "wof:placetype":"venue"
},
  "geometry": {"coordinates":[-76.261506,42.103553],"type":"Point"}
}