{
  "type": "Feature",
  "properties": {
    "iso:country":"US",
    "sg:address":"256 Main St",
    "sg:city":"Beacon",
    "sg:classifiers":[
        {
            "category":"Wholesale",
            "subcategory":"Stationery",
            "type":"Manufacturing & Wholesale Goods"
        }
    ],
    "sg:phone":"+1 845 831 0922",
    "sg:postcode":"12508",
    "sg:province":"NY",
    "sg:tags":[
        "school",
        "supply"
    ],
    "wof:name":"N S News",
    "wof:placetype":"venue"
},
  "geometry": {"coordinates":[-73.97150999999999,41.506072],"type":"Point"}
}