{
  "type": "Feature",
  "properties": {
    "addr:full":"3001 Ford St Exn Ogdensburg NY 13669",
    "addr:housenumber":"3001",
    "addr:postcode":"13669",
    "addr:street":"Ford St",
    "iso:country":"US",
    "sg:address":"3001 Ford St Exn",
    "sg:city":"Ogdensburg",
    "sg:classifiers":[
        {
            "category":"Banks & Credit Unions",
            "subcategory":"Bank",
            "type":"Services"
        }
    ],
    "sg:phone":"+1 315 393 7109",
    "sg:postcode":"13669",
    "sg:province":"NY",
    "sg:tags":[
        "state",
        "commercial"
    ],
    "wof:name":"Community Bank NA",
    "wof:placetype":"venue"
},
  "geometry": {"coordinates":[-75.455933,44.705425],"type":"Point"}
}