{
  "type": "Feature",
  "properties": {
    "addr:full":"49 Genesee St Greene NY 13778",
    "addr:housenumber":"49",
    "addr:postcode":"13778",
    "addr:street":"Genesee St",
    "iso:country":"US",
    "sg:address":"49 Genesee St",
    "sg:city":"Greene",
    "sg:classifiers":[
        {
            "category":"Government",
            "subcategory":"Police Station",
            "type":"Public Place"
        }
    ],
    "sg:phone":"+1 607 656 4275",
    "sg:postcode":"13778",
    "sg:province":"NY",
    "sg:tags":[
        "state"
    ],
    "wof:name":"Troop C",
    "wof:placetype":"venue"
},
  "geometry": {"coordinates":[-75.770991,42.32977],"type":"Point"}
}