{
  "type": "Feature",
  "properties": {
    "addr:full":"4652 3rd Ave Bronx NY 10458",
    "addr:housenumber":"4652",
    "addr:postcode":"10458",
    "addr:street":"3Rd Ave",
    "iso:country":"US",
    "sg:address":"4652 3rd Ave",
    "sg:city":"Bronx",
    "sg:classifiers":[
        {
            "category":"Deli",
            "type":"Food & Drink"
        }
    ],
    "sg:menulink":"http://www.allmenus.com/ny/bronx/52475-kennedys-chicken--biscuits/menu/",
    "sg:phone":"+1 718 684 9969",
    "sg:postcode":"10458",
    "sg:province":"NY",
    "sg:tags":[
        "american"
    ],
    "wof:name":"Kennedy's Chicken & Biscuits",
    "wof:placetype":"venue"
},
  "geometry": {"coordinates":[-73.89098199999999,40.857381],"type":"Point"}
}