{
  "type": "Feature",
  "properties": {
    "addr:full":"45 Tom Miller Rd Plattsburgh NY 12901",
    "addr:housenumber":"45",
    "addr:postcode":"12901",
    "addr:street":"Tom Miller Rd",
    "iso:country":"US",
    "sg:address":"45 Tom Miller Rd",
    "sg:city":"Plattsburgh",
    "sg:classifiers":[
        {
            "category":"Professional",
            "subcategory":"Business Services",
            "type":"Services"
        }
    ],
    "sg:phone":"+1   ",
    "sg:postcode":"12901",
    "sg:province":"NY",
    "wof:name":"United Way of Clinton & Essex",
    "wof:placetype":"venue"
},
  "geometry": {"coordinates":[-73.477897,44.70702],"type":"Point"}
}