{
  "type": "Feature",
  "properties": {
    "iso:country":"US",
    "sg:address":"280 Broadway",
    "sg:city":"Newburgh",
    "sg:classifiers":[
        {
            "category":"Professional",
            "subcategory":"Lawyer & Legal Services",
            "type":"Services"
        }
    ],
    "sg:phone":"+1 845 565 3999",
    "sg:postcode":"12550",
    "sg:province":"NY",
    "sg:tags":[
        "attorney"
    ],
    "wof:name":"Paul Trachte Law Office",
    "wof:placetype":"venue"
},
  "geometry": {"coordinates":[-74.020813,41.500727],"type":"Point"}
}