{
  "type": "Feature",
  "properties": {
    "addr:full":"1 Battery Park Plaza New York NY 10004",
    "addr:housenumber":"1",
    "addr:postcode":"10004",
    "addr:street":"Battery Park",
    "iso:country":"US",
    "sg:address":"1 Battery Park Plaza",
    "sg:city":"New York",
    "sg:classifiers":[
        {
            "category":"Banks & Credit Unions",
            "subcategory":"Financial Services",
            "type":"Services"
        }
    ],
    "sg:phone":"+1 212 972 3600",
    "sg:postcode":"10004",
    "sg:province":"NY",
    "sg:tags":[
        "broker",
        "mortgage"
    ],
    "wof:name":"Meridian Capital Group",
    "wof:placetype":"venue"
},
  "geometry": {"coordinates":[-74.01443500000001,40.70321],"type":"Point"}
}