{
  "type": "Feature",
  "properties": {
    "addr:full":"98 Queens Blvd Rego Park NY 11374",
    "addr:housenumber":"98",
    "addr:postcode":"11374",
    "addr:street":"Queens Blvd",
    "iso:country":"US",
    "sg:address":"98 Queens Blvd",
    "sg:city":"Rego Park",
    "sg:classifiers":[
        {
            "category":"Cinema",
            "subcategory":"Movie Rental",
            "type":"Entertainment"
        }
    ],
    "sg:phone":"+1   ",
    "sg:postcode":"11374",
    "sg:province":"NY",
    "sg:tags":[
        "video",
        "tape"
    ],
    "wof:name":"World Wide Video",
    "wof:placetype":"venue"
},
  "geometry": {"coordinates":[-73.854353,40.72717],"type":"Point"}
}