{
  "type": "Feature",
  "properties": {
    "addr:full":"97 3rd Ave New York NY 10003",
    "addr:housenumber":"97",
    "addr:postcode":"10003",
    "addr:street":"3Rd Ave",
    "iso:country":"US",
    "sg:address":"97 3rd Ave",
    "sg:city":"New York",
    "sg:classifiers":[
        {
            "category":"Shopping",
            "subcategory":"Clothing, Apparel, & Fashions",
            "type":"Retail Goods"
        },
        {
            "category":"Shopping",
            "subcategory":"Jewelry",
            "type":"Retail Goods"
        },
        {
            "category":"Wholesale",
            "subcategory":"Stationery",
            "type":"Manufacturing & Wholesale Goods"
        }
    ],
    "sg:phone":"+1 212 995 5888",
    "sg:postcode":"10003",
    "sg:province":"NY",
    "sg:tags":[
        "clothing",
        "card",
        "women's"
    ],
    "wof:name":"Air Market",
    "wof:placetype":"venue"
},
  "geometry": {"coordinates":[-73.987853,40.732377],"type":"Point"}
}