{
  "type": "Feature",
  "properties": {
    "addr:full":"1030 Flatbush Ave Brooklyn NY 11226",
    "addr:housenumber":"1030",
    "addr:postcode":"11226",
    "addr:street":"Flatbush Ave",
    "iso:country":"US",
    "sg:address":"1030 Flatbush Ave",
    "sg:city":"Brooklyn",
    "sg:classifiers":[
        {
            "category":"Home & Garden",
            "subcategory":"Furniture",
            "type":"Retail Goods"
        }
    ],
    "sg:phone":"+1 718 484 2441",
    "sg:postcode":"11226",
    "sg:province":"NY",
    "sg:tags":[
        "store"
    ],
    "wof:name":"Royal Furniture Inc",
    "wof:placetype":"venue"
},
  "geometry": {"coordinates":[-73.958257,40.64603],"type":"Point"}
}