{
  "type": "Feature",
  "properties": {
    "iso:country":"US",
    "sg:address":"43 Central Ave",
    "sg:city":"Lancaster",
    "sg:classifiers":[
        {
            "category":"Professional",
            "subcategory":"Advertising",
            "type":"Services"
        }
    ],
    "sg:phone":"+1   ",
    "sg:postcode":"14086",
    "sg:province":"NY",
    "sg:tags":[
        "mail",
        "direct"
    ],
    "wof:name":"Niagara Frontier Advg Assoc",
    "wof:placetype":"venue"
},
  "geometry": {"coordinates":[-78.67022299999999,42.90131],"type":"Point"}
}