{
  "type": "Feature",
  "properties": {
    "addr:full":"67 Irving Pl Fl 10 New York NY 10003",
    "addr:housenumber":"67;10",
    "addr:postcode":"10003",
    "addr:street":"Irving Pl Fl",
    "iso:country":"US",
    "sg:address":"67 Irving Pl Fl 10",
    "sg:city":"New York",
    "sg:classifiers":[
        {
            "category":"Health Services",
            "subcategory":"Doctor",
            "type":"Services"
        },
        {
            "category":"Health Services",
            "subcategory":"Hospital",
            "type":"Services"
        }
    ],
    "sg:phone":"+1 212 254 5350",
    "sg:postcode":"10003",
    "sg:province":"NY",
    "wof:name":"Gramercy Surgical Center",
    "wof:placetype":"venue"
},
  "geometry": {"coordinates":[-73.98690000000001,40.7365],"type":"Point"}
}