{
  "type": "Feature",
  "properties": {
    "addr:full":"5286 Merrick Rd Massapequa NY 11758",
    "addr:housenumber":"5286",
    "addr:postcode":"11758",
    "addr:street":"Merrick Rd",
    "iso:country":"US",
    "sg:address":"5286 Merrick Rd",
    "sg:city":"Massapequa",
    "sg:classifiers":[
        {
            "category":"Recreation",
            "type":"Entertainment"
        }
    ],
    "sg:phone":"+1 516 797 0014",
    "sg:postcode":"11758",
    "sg:province":"NY",
    "sg:tags":[
        "martial",
        "arts",
        "instruction"
    ],
    "wof:name":"Fit One Total Body Fitness",
    "wof:placetype":"venue"
},
  "geometry": {"coordinates":[-73.439869,40.667342],"type":"Point"}
}