{
  "type": "Feature",
  "properties": {
    "iso:country":"US",
    "sg:address":"318 Wynn Ln",
    "sg:city":"Port Jefferson",
    "sg:classifiers":[
        {
            "category":"Restaurant",
            "type":"Food & Drink"
        }
    ],
    "sg:menulink":"http://www.allmenus.com/ny/brookhaven/279629-paces-steak-house/menu/",
    "sg:phone":"+1 631 331 9200",
    "sg:postcode":"11777",
    "sg:province":"NY",
    "sg:tags":[
        "american",
        "steakhouse"
    ],
    "wof:name":"Pace's Steak House",
    "wof:placetype":"venue"
},
  "geometry": {"coordinates":[-73.068063,40.944636],"type":"Point"}
}