{
  "type": "Feature",
  "properties": {
    "iso:country":"US",
    "sg:address":"61 Waterford Way",
    "sg:city":"Fairport",
    "sg:classifiers":[
        {
            "category":"Manufacturing",
            "subcategory":"Metals",
            "type":"Manufacturing & Wholesale Goods"
        }
    ],
    "sg:phone":"+1   ",
    "sg:postcode":"14450",
    "sg:province":"NY",
    "sg:tags":[
        "plumbing",
        "contractor"
    ],
    "wof:name":"Karls Plumbing",
    "wof:placetype":"venue"
},
  "geometry": {"coordinates":[-77.40614600000001,43.087165],"type":"Point"}
}