{
  "type": "Feature",
  "properties": {
    "addr:full":"6 Aldrich Ave Binghamton NY 13903",
    "addr:housenumber":"6",
    "addr:postcode":"13903",
    "addr:street":"Aldrich Ave",
    "iso:country":"US",
    "sg:address":"6 Aldrich Ave",
    "sg:city":"Binghamton",
    "sg:classifiers":[
        {
            "category":"Building & Trades",
            "subcategory":"Construction",
            "type":"Services"
        }
    ],
    "sg:phone":"+1 607 771 0000",
    "sg:postcode":"13903",
    "sg:province":"NY",
    "sg:tags":[
        "hanging",
        "maintenance",
        "contractor"
    ],
    "wof:name":"Beach Brothers Inc",
    "wof:placetype":"venue"
},
  "geometry": {"coordinates":[-75.91678400000001,42.083175],"type":"Point"}
}