{
  "type": "Feature",
  "properties": {
    "iso:country":"US",
    "sg:address":"305 Stewart Ave",
    "sg:city":"Ithaca",
    "sg:classifiers":[
        {
            "category":"Cafe",
            "type":"Food & Drink"
        },
        {
            "category":"Restaurant",
            "type":"Food & Drink"
        }
    ],
    "sg:menulink":"http://www.allmenus.com/ny/ithaca/255183-carriage-house-cafe/menu/",
    "sg:phone":"+1 607 645 0152",
    "sg:postcode":"14850",
    "sg:province":"NY",
    "sg:tags":[
        "new",
        "american"
    ],
    "wof:name":"Carriage House Cafe",
    "wof:placetype":"venue"
},
  "geometry": {"coordinates":[-76.489634,42.441992],"type":"Point"}
}