{
  "type": "Feature",
  "properties": {
    "addr:full":"101 Smith Ln Centereach NY 11720",
    "addr:housenumber":"101",
    "addr:postcode":"11720",
    "addr:street":"Smith Ln",
    "iso:country":"US",
    "sg:address":"101 Smith Ln",
    "sg:city":"Centereach",
    "sg:classifiers":[
        {
            "category":"Building & Trades",
            "subcategory":"Construction",
            "type":"Services"
        }
    ],
    "sg:phone":"+1 631 467 2432",
    "sg:postcode":"11720",
    "sg:province":"NY",
    "sg:tags":[
        "contractor"
    ],
    "wof:name":"Danny Longo",
    "wof:placetype":"venue"
},
  "geometry": {"coordinates":[-73.09761899999999,40.847232],"type":"Point"}
}