{
  "type": "Feature",
  "properties": {
    "addr:full":"398 E 148th St Bronx NY 10455",
    "addr:housenumber":"398",
    "addr:postcode":"10455",
    "addr:street":"E 148Th St",
    "iso:country":"US",
    "sg:address":"398 E 148th St",
    "sg:city":"Bronx",
    "sg:classifiers":[
        {
            "category":"Shopping",
            "subcategory":"Pharmacy",
            "type":"Retail Goods"
        }
    ],
    "sg:phone":"+1 718 401 6778",
    "sg:postcode":"10455",
    "sg:province":"NY",
    "wof:name":"Span-AM Pharmacy",
    "wof:placetype":"venue"
},
  "geometry": {"coordinates":[-73.91986,40.815864],"type":"Point"}
}