{
  "type": "Feature",
  "properties": {
    "addr:full":"1841 Broadway New York NY 10023",
    "addr:housenumber":"1841",
    "addr:postcode":"10023",
    "addr:street":"Broadway",
    "iso:country":"US",
    "sg:address":"1841 Broadway",
    "sg:city":"New York",
    "sg:classifiers":[
        {
            "category":"Communications",
            "subcategory":"Film & Video Production",
            "type":"Services"
        }
    ],
    "sg:phone":"+1 212 664 9286",
    "sg:postcode":"10023",
    "sg:province":"NY",
    "sg:tags":[
        "motion",
        "distribution"
    ],
    "wof:name":"Terra Entertainment Inc",
    "wof:placetype":"venue"
},
  "geometry": {"coordinates":[-73.98218799999999,40.769528],"type":"Point"}
}