{
  "type": "Feature",
  "properties": {
    "iso:country":"US",
    "sg:address":"32 Tennyson Ave",
    "sg:city":"Buffalo",
    "sg:classifiers":[
        {
            "category":"Building & Trades",
            "subcategory":"Landscaping Services",
            "type":"Services"
        }
    ],
    "sg:phone":"+1 716 876 5491",
    "sg:postcode":"14216",
    "sg:province":"NY",
    "sg:tags":[
        "lawn"
    ],
    "wof:name":"Greenmeadows Organic Lawns",
    "wof:placetype":"venue"
},
  "geometry": {"coordinates":[-78.86732600000001,42.950952],"type":"Point"}
}