{
  "type": "Feature",
  "properties": {
    "addr:full":"438 W Broadway New York NY 10012",
    "addr:housenumber":"438",
    "addr:postcode":"10012",
    "addr:street":"W Broadway",
    "iso:country":"US",
    "sg:address":"438 W Broadway",
    "sg:city":"New York",
    "sg:classifiers":[
        {
            "category":"Shopping",
            "subcategory":"Shoes",
            "type":"Retail Goods"
        }
    ],
    "sg:phone":"+1 917 691 0012",
    "sg:postcode":"10012",
    "sg:province":"NY",
    "sg:tags":[
        "store"
    ],
    "sg:website":"musette.us",
    "wof:name":"Musette",
    "wof:placetype":"venue"
},
  "geometry": {"coordinates":[-74.001047,40.725609],"type":"Point"}
}