{
  "type": "Feature",
  "properties": {
    "addr:full":"4784 Commercial Dr New Hartford NY 13413",
    "addr:housenumber":"4784",
    "addr:postcode":"13413",
    "addr:street":"Commercial Dr",
    "iso:country":"US",
    "sg:address":"4784 Commercial Dr",
    "sg:city":"New Hartford",
    "sg:classifiers":[
        {
            "category":"Restaurant",
            "type":"Food & Drink"
        }
    ],
    "sg:phone":"+1   ",
    "sg:postcode":"13413",
    "sg:province":"NY",
    "sg:tags":[
        "eating"
    ],
    "wof:name":"Jamsco",
    "wof:placetype":"venue"
},
  "geometry": {"coordinates":[-75.310208,43.09012],"type":"Point"}
}