{
  "type": "Feature",
  "properties": {
    "addr:full":"459 Jerusalem Ave Uniondale NY 11553",
    "addr:housenumber":"459",
    "addr:postcode":"11553",
    "addr:street":"Jerusalem Ave",
    "iso:country":"US",
    "sg:address":"459 Jerusalem Ave",
    "sg:city":"Uniondale",
    "sg:classifiers":[
        {
            "category":"Shopping",
            "subcategory":"Gifts & Souvenirs",
            "type":"Retail Goods"
        }
    ],
    "sg:phone":"+1   ",
    "sg:postcode":"11553",
    "sg:province":"NY",
    "sg:tags":[
        "stationery"
    ],
    "wof:name":"M F Stationery",
    "wof:placetype":"venue"
},
  "geometry": {"coordinates":[-73.599369,40.701708],"type":"Point"}
}