{
  "type": "Feature",
  "properties": {
    "iso:country":"US",
    "sg:address":"315 Flatbush Ave.",
    "sg:city":"Brooklyn",
    "sg:classifiers":[
        {
            "category":"Shopping",
            "subcategory":"Department Store",
            "type":"Retail Goods"
        }
    ],
    "sg:phone":"+1 347 651 1809",
    "sg:postcode":"11217",
    "sg:province":"NY",
    "sg:website":"www.WomansLingerie.org",
    "wof:name":"Womans Lingerie.org",
    "wof:placetype":"venue"
},
  "geometry": {"coordinates":[-73.973016,40.677984],"type":"Point"}
}