{
  "type": "Feature",
  "properties": {
    "iso:country":"US",
    "sg:address":"5 Travers St",
    "sg:city":"Manhasset",
    "sg:classifiers":[
        {
            "category":"Health Services",
            "subcategory":"Doctor",
            "type":"Services"
        }
    ],
    "sg:phone":"+1 516 627 8740",
    "sg:postcode":"11030",
    "sg:province":"NY",
    "sg:tags":[
        "medicine",
        "physician",
        "practice",
        "surgeons",
        "family"
    ],
    "wof:name":"Sharon Ann Finkelstein, M.D.,",
    "wof:placetype":"venue"
},
  "geometry": {"coordinates":[-73.704551,40.797735],"type":"Point"}
}