{
  "type": "Feature",
  "properties": {
    "addr:full":"132 Bronx River Rd Yonkers NY 10704",
    "addr:housenumber":"132",
    "addr:postcode":"10704",
    "addr:street":"Bronx River Rd",
    "iso:country":"US",
    "sg:address":"132 Bronx River Rd",
    "sg:city":"Yonkers",
    "sg:classifiers":[
        {
            "category":"Bagels",
            "type":"Food & Drink"
        },
        {
            "category":"Coffee & Tea",
            "type":"Food & Drink"
        },
        {
            "category":"Food & Beverages",
            "subcategory":"Bakery",
            "type":"Retail Goods"
        },
        {
            "category":"Bakery",
            "type":"Food & Drink"
        },
        {
            "category":"Donuts",
            "type":"Food & Drink"
        }
    ],
    "sg:menulink":"http://www.allmenus.com/ny/yonkers/138801-dunkin-donuts/menu/",
    "sg:phone":"+1 718 454 3501",
    "sg:postcode":"10704",
    "sg:province":"NY",
    "sg:tags":[
        "coffee",
        "tea",
        "american",
        "bagel",
        "bakery",
        "pastry"
    ],
    "wof:name":"Dunkin' Donuts",
    "wof:placetype":"venue"
},
  "geometry": {"coordinates":[-73.858193,40.905641],"type":"Point"}
}