{
  "type": "Feature",
  "properties": {
    "addr:full":"1611 Nostrand Ave Brooklyn NY 11226",
    "addr:housenumber":"1611",
    "addr:postcode":"11226",
    "addr:street":"Nostrand Ave",
    "iso:country":"US",
    "sg:address":"1611 Nostrand Ave",
    "sg:city":"Brooklyn",
    "sg:classifiers":[
        {
            "category":"Freight",
            "type":"Transportation"
        }
    ],
    "sg:phone":"+1   ",
    "sg:postcode":"11226",
    "sg:province":"NY",
    "sg:tags":[
        "arrangement"
    ],
    "wof:name":"Angie Shipping",
    "wof:placetype":"venue"
},
  "geometry": {"coordinates":[-73.948894,40.64519],"type":"Point"}
}