{
  "type": "Feature",
  "properties": {
    "addr:full":"4000 Jericho Tpke Ste 4 East Northport NY 11731",
    "addr:housenumber":"4000",
    "addr:postcode":"11731",
    "addr:street":"Jericho Tpke Ste 4",
    "iso:country":"US",
    "sg:address":"4000 Jericho Tpke Ste 4",
    "sg:city":"East Northport",
    "sg:classifiers":[
        {
            "category":"Shopping",
            "subcategory":"Clothing, Apparel, & Fashions",
            "type":"Retail Goods"
        }
    ],
    "sg:phone":"+1 631 462 2896",
    "sg:postcode":"11731",
    "sg:province":"NY",
    "sg:tags":[
        "accessory",
        "clothing",
        "women's"
    ],
    "wof:name":"dressbarn",
    "wof:placetype":"venue"
},
  "geometry": {"coordinates":[-73.31476000000001,40.840174],"type":"Point"}
}