{
  "type": "Feature",
  "properties": {
    "iso:country":"US",
    "sg:address":"551 W 175th St",
    "sg:city":"New York",
    "sg:classifiers":[
        {
            "category":"Personal",
            "subcategory":"Beauty Salon",
            "type":"Services"
        }
    ],
    "sg:phone":"+1 212 543 2755",
    "sg:postcode":"10033",
    "sg:province":"NY",
    "wof:name":"Annabell's Hair Plus",
    "wof:placetype":"venue"
},
  "geometry": {"coordinates":[-73.93657,40.845434],"type":"Point"}
}