{
  "type": "Feature",
  "properties": {
    "addr:full":"26 Hill St New Canaan NY 06840",
    "addr:housenumber":"26",
    "addr:postcode":"06840",
    "addr:street":"Hill St",
    "iso:country":"US",
    "sg:address":"26 Hill St",
    "sg:city":"New Canaan",
    "sg:classifiers":[
        {
            "category":"Building & Trades",
            "subcategory":"Cleaning & Sanitation",
            "type":"Services"
        }
    ],
    "sg:phone":"+1   ",
    "sg:postcode":"06840",
    "sg:province":"NY",
    "sg:tags":[
        "maintenance"
    ],
    "wof:name":"Flor Cleaning Services",
    "wof:placetype":"venue"
},
  "geometry": {"coordinates":[-73.487995,41.151286],"type":"Point"}
}