{
  "type": "Feature",
  "properties": {
    "addr:full":"1717 Troutman Ste 329 Queens NY 11385",
    "addr:housenumber":"1717",
    "addr:postcode":"11385",
    "addr:street":"Troutman Ste 329",
    "iso:country":"US",
    "sg:address":"1717 Troutman Ste 329",
    "sg:city":"Queens",
    "sg:classifiers":[
        {
            "category":"Arts & Performance",
            "subcategory":"Art Gallery",
            "type":"Entertainment"
        }
    ],
    "sg:phone":"+1 646 467 2232",
    "sg:postcode":"11385",
    "sg:province":"NY",
    "sg:website":"www.reginarex.org/",
    "wof:name":"Regina Rex",
    "wof:placetype":"venue"
},
  "geometry": {"coordinates":[-73.920486,40.708921],"type":"Point"}
}