{
  "type": "Feature",
  "properties": {
    "addr:full":"200 N Galleria Dr Middletown NY 10941",
    "addr:housenumber":"200",
    "addr:postcode":"10941",
    "addr:street":"N Galleria Dr",
    "iso:country":"US",
    "sg:address":"200 N Galleria Dr",
    "sg:city":"Middletown",
    "sg:classifiers":[
        {
            "category":"Restaurant",
            "type":"Food & Drink"
        }
    ],
    "sg:menulink":"http://www.allmenus.com/ny/wallkill/13772-olive-garden-italian-restaurant/menu/",
    "sg:phone":"+1 845 692 8232",
    "sg:postcode":"10941",
    "sg:province":"NY",
    "sg:tags":[
        "italian"
    ],
    "wof:name":"Olive Garden Italian Restaurant",
    "wof:placetype":"venue"
},
  "geometry": {"coordinates":[-74.371562,41.462904],"type":"Point"}
}