{
  "type": "Feature",
  "properties": {
    "addr:full":"2548 Frederick Douglass Blvd New York NY 10030",
    "addr:housenumber":"2548",
    "addr:postcode":"10030",
    "addr:street":"Frederick Douglass Blvd",
    "iso:country":"US",
    "sg:address":"2548 Frederick Douglass Blvd",
    "sg:city":"New York",
    "sg:classifiers":[
        {
            "category":"Local Transit",
            "type":"Transportation"
        }
    ],
    "sg:phone":"+1   ",
    "sg:postcode":"10030",
    "sg:province":"NY",
    "sg:tags":[
        "passenger",
        "transport"
    ],
    "wof:name":"Malcolm Radio Group",
    "wof:placetype":"venue"
},
  "geometry": {"coordinates":[-73.946308,40.816562],"type":"Point"}
}