{
  "type": "Feature",
  "properties": {
    "iso:country":"US",
    "sg:address":"2330 Norton St",
    "sg:city":"Rochester",
    "sg:classifiers":[
        {
            "category":"Local Transit",
            "type":"Transportation"
        }
    ],
    "sg:phone":"+1 585 544 5112",
    "sg:postcode":"14609",
    "sg:province":"NY",
    "sg:tags":[
        "ambulance"
    ],
    "wof:name":"Irondequoit Volunteer Amblnc",
    "wof:placetype":"venue"
},
  "geometry": {"coordinates":[-77.558091,43.188321],"type":"Point"}
}