{
  "type": "Feature",
  "properties": {
    "addr:full":"3665 E Tremont Ave Bronx NY 10465",
    "addr:housenumber":"3665",
    "addr:postcode":"10465",
    "addr:street":"E Tremont Ave",
    "iso:country":"US",
    "sg:address":"3665 E Tremont Ave",
    "sg:city":"Bronx",
    "sg:classifiers":[
        {
            "category":"Health Services",
            "subcategory":"Doctor",
            "type":"Services"
        }
    ],
    "sg:phone":"+1 718 863 7755",
    "sg:postcode":"10465",
    "sg:province":"NY",
    "wof:name":"Baker Barry MD",
    "wof:placetype":"venue"
},
  "geometry": {"coordinates":[-73.823303,40.827801],"type":"Point"}
}