{
  "type": "Feature",
  "properties": {
    "addr:full":"5834 E Circle Dr Cicero NY 13039",
    "addr:housenumber":"5834",
    "addr:postcode":"13039",
    "addr:street":"E Circle Dr",
    "iso:country":"US",
    "sg:address":"5834 E Circle Dr",
    "sg:city":"Cicero",
    "sg:classifiers":[
        {
            "category":"Banks & Credit Unions",
            "subcategory":"Bank",
            "type":"Services"
        }
    ],
    "sg:phone":"+1 315 452 0111",
    "sg:postcode":"13039",
    "sg:province":"NY",
    "sg:tags":[
        "state",
        "commercial"
    ],
    "wof:name":"Fleet",
    "wof:placetype":"venue"
},
  "geometry": {"coordinates":[-76.12056800000001,43.147476],"type":"Point"}
}