{
  "type": "Feature",
  "properties": {
    "addr:full":"1520 W Henrietta Rd Avon NY 14414",
    "addr:housenumber":"1520",
    "addr:postcode":"14414",
    "addr:street":"W Henrietta Rd",
    "iso:country":"US",
    "sg:address":"1520 W Henrietta Rd",
    "sg:city":"Avon",
    "sg:classifiers":[
        {
            "category":"Cinema",
            "subcategory":"Movie Theater",
            "type":"Entertainment"
        }
    ],
    "sg:phone":"+1 585 226 9290",
    "sg:postcode":"14414",
    "sg:province":"NY",
    "wof:name":"Vintage Drive In Theatre",
    "wof:placetype":"venue"
},
  "geometry": {"coordinates":[-77.70468700000001,42.919177],"type":"Point"}
}