{
  "type": "Feature",
  "properties": {
    "addr:full":"11 Red Oak Ln Fishkill NY 12524",
    "addr:housenumber":"11",
    "addr:postcode":"12524",
    "addr:street":"Red Oak Ln",
    "iso:country":"US",
    "sg:address":"11 Red Oak Ln",
    "sg:city":"Fishkill",
    "sg:classifiers":[
        {
            "category":"Manufacturing",
            "subcategory":"Toys & Sporting Goods",
            "type":"Manufacturing & Wholesale Goods"
        }
    ],
    "sg:phone":"+1   ",
    "sg:postcode":"12524",
    "sg:province":"NY",
    "sg:tags":[
        "mfg"
    ],
    "wof:name":"Thomas B Hogan",
    "wof:placetype":"venue"
},
  "geometry": {"coordinates":[-73.91704799999999,41.533471],"type":"Point"}
}