{
  "type": "Feature",
  "properties": {
    "iso:country":"US",
    "sg:address":"43 W 33rd Street",
    "sg:city":"New York",
    "sg:classifiers":[
        {
            "category":"Shopping",
            "subcategory":"Clothing, Apparel, & Fashions",
            "type":"Retail Goods"
        }
    ],
    "sg:phone":"+1 212 244 1616",
    "sg:postcode":"10001",
    "sg:province":"NY",
    "sg:tags":[
        "accessory",
        "clothing",
        "women's"
    ],
    "wof:name":"Offi International Buyers Corporation",
    "wof:placetype":"venue"
},
  "geometry": {"coordinates":[-73.98630300000001,40.748321],"type":"Point"}
}