{
  "type": "Feature",
  "properties": {
    "iso:country":"US",
    "sg:address":"3820 Nostrand Ave",
    "sg:city":"Brooklyn",
    "sg:classifiers":[
        {
            "category":"Professional",
            "type":"Services"
        }
    ],
    "sg:phone":"+1 718 573 8900",
    "sg:postcode":"11235",
    "sg:province":"NY",
    "sg:tags":[
        "establishment"
    ],
    "wof:name":"REH Management",
    "wof:placetype":"venue"
},
  "geometry": {"coordinates":[-73.94002,40.590588],"type":"Point"}
}