{
  "type": "Feature",
  "properties": {
    "iso:country":"US",
    "sg:address":"9017 Main St",
    "sg:city":"Rushford",
    "sg:classifiers":[
        {
            "category":"Insurance",
            "subcategory":"Insurance Agent",
            "type":"Services"
        }
    ],
    "sg:phone":"+1 585 437 2268",
    "sg:postcode":"14777",
    "sg:province":"NY",
    "wof:name":"Davies Insurance Agency",
    "wof:placetype":"venue"
},
  "geometry": {"coordinates":[-78.25081,42.392258],"type":"Point"}
}