{
  "type": "Feature",
  "properties": {
    "iso:country":"US",
    "sg:address":"721 Hiawatha Blvd W",
    "sg:city":"Syracuse",
    "sg:classifiers":[
        {
            "category":"Autos & Motor Vehicles",
            "subcategory":"Automobile Sales",
            "type":"Retail Goods"
        }
    ],
    "sg:phone":"+1 315 426 2600",
    "sg:postcode":"13204",
    "sg:province":"NY",
    "sg:tags":[
        "car",
        "dealer"
    ],
    "wof:name":"Auto House LLC",
    "wof:placetype":"venue"
},
  "geometry": {"coordinates":[-76.17674,43.062046],"type":"Point"}
}