{
  "type": "Feature",
  "properties": {
    "addr:full":"590 Broadway New York NY 10012",
    "addr:housenumber":"590",
    "addr:postcode":"10012",
    "addr:street":"Broadway",
    "iso:country":"US",
    "sg:address":"590 Broadway",
    "sg:city":"New York",
    "sg:classifiers":[
        {
            "category":"Retail",
            "subcategory":"Portrait Studio",
            "type":"Services"
        },
        {
            "category":"Professional",
            "subcategory":"Art Services",
            "type":"Services"
        }
    ],
    "sg:phone":"+1 212 431 3002",
    "sg:postcode":"10012",
    "sg:province":"NY",
    "sg:tags":[
        "photographer",
        "photography",
        "store"
    ],
    "wof:name":"Ricky Photo Lab",
    "wof:placetype":"venue"
},
  "geometry": {"coordinates":[-73.997398,40.7244],"type":"Point"}
}