{
  "type": "Feature",
  "properties": {
    "iso:country":"US",
    "sg:address":"5757 Main St",
    "sg:city":"Buffalo",
    "sg:classifiers":[
        {
            "category":"Education",
            "subcategory":"Special Training",
            "type":"Public Place"
        }
    ],
    "sg:phone":"+1 716 572 1604",
    "sg:postcode":"14221",
    "sg:province":"NY",
    "sg:tags":[
        "tutoring"
    ],
    "wof:name":"Homework Club",
    "wof:placetype":"venue"
},
  "geometry": {"coordinates":[-78.739175,42.963626],"type":"Point"}
}