{
  "type": "Feature",
  "properties": {
    "iso:country":"US",
    "sg:address":"756 Somerdale Dr",
    "sg:city":"Webster",
    "sg:classifiers":[
        {
            "category":"Professional",
            "subcategory":"Computer Services",
            "type":"Services"
        }
    ],
    "sg:phone":"+1   ",
    "sg:postcode":"14580",
    "sg:province":"NY",
    "sg:tags":[
        "communications",
        "datum",
        "telephone"
    ],
    "wof:name":"Webface Media",
    "wof:placetype":"venue"
},
  "geometry": {"coordinates":[-77.480734,43.221591],"type":"Point"}
}