{
  "type": "Feature",
  "properties": {
    "iso:country":"US",
    "sg:address":"56 2nd St",
    "sg:city":"Athens",
    "sg:classifiers":[
        {
            "category":"Building & Trades",
            "subcategory":"Construction",
            "type":"Services"
        }
    ],
    "sg:phone":"+1 518 945 3880",
    "sg:postcode":"12015",
    "sg:province":"NY",
    "sg:tags":[
        "restoration",
        "preservation"
    ],
    "wof:name":"Glenco Construction Co",
    "wof:placetype":"venue"
},
  "geometry": {"coordinates":[-73.81065599999999,42.260977],"type":"Point"}
}