{
  "type": "Feature",
  "properties": {
    "iso:country":"US",
    "sg:address":"48 E High St",
    "sg:city":"Ballston Spa",
    "sg:classifiers":[
        {
            "category":"Banks & Credit Unions",
            "subcategory":"Financial Services",
            "type":"Services"
        }
    ],
    "sg:phone":"+1 518 885 4594",
    "sg:postcode":"12020",
    "sg:province":"NY",
    "sg:tags":[
        "investment",
        "closed"
    ],
    "wof:name":"Halcyon Property Group Inc",
    "wof:placetype":"venue"
},
  "geometry": {"coordinates":[-73.842637,43.001241],"type":"Point"}
}