{
  "type": "Feature",
  "properties": {
    "addr:full":"81 Waters Ave Staten Island NY 10314",
    "addr:housenumber":"81",
    "addr:postcode":"10314",
    "addr:street":"Waters Ave",
    "iso:country":"US",
    "sg:address":"81 Waters Ave",
    "sg:city":"Staten Island",
    "sg:classifiers":[
        {
            "category":"Banks & Credit Unions",
            "subcategory":"Bank",
            "type":"Services"
        },
        {
            "category":"Banks & Credit Unions",
            "subcategory":"Financial Services",
            "type":"Services"
        }
    ],
    "sg:phone":"+1 718 447 8880",
    "sg:postcode":"10314",
    "sg:province":"NY",
    "sg:tags":[
        "broker",
        "mortgage"
    ],
    "wof:name":"Si Bank & Trust",
    "wof:placetype":"venue"
},
  "geometry": {"coordinates":[-74.133797,40.617001],"type":"Point"}
}