{
  "type": "Feature",
  "properties": {
    "addr:full":"195 Chrystie St New York NY 10002",
    "addr:housenumber":"195",
    "addr:postcode":"10002",
    "addr:street":"Chrystie St",
    "iso:country":"US",
    "sg:address":"195 Chrystie St",
    "sg:city":"New York",
    "sg:classifiers":[
        {
            "category":"Professional",
            "subcategory":"Management & Consulting",
            "type":"Services"
        }
    ],
    "sg:phone":"+1   ",
    "sg:postcode":"10002",
    "sg:province":"NY",
    "sg:tags":[
        "public",
        "relations"
    ],
    "wof:name":"Bradbury & Lewis Inc",
    "wof:placetype":"venue"
},
  "geometry": {"coordinates":[-73.992215,40.721365],"type":"Point"}
}