{
  "type": "Feature",
  "properties": {
    "addr:full":"9 Sheldon Guile Blvd Owego NY 13827",
    "addr:housenumber":"9",
    "addr:postcode":"13827",
    "addr:street":"Guile Blvd",
    "iso:country":"US",
    "sg:address":"9 Sheldon Guile Blvd",
    "sg:city":"Owego",
    "sg:classifiers":[
        {
            "category":"Government",
            "subcategory":"Office",
            "type":"Public Place"
        }
    ],
    "sg:phone":"+1 607 687 4120",
    "sg:postcode":"13827",
    "sg:province":"NY",
    "sg:tags":[
        "county",
        "resource"
    ],
    "sg:website":"www.tiogaopp.org",
    "wof:name":"Area Agency On Aging",
    "wof:placetype":"venue"
},
  "geometry": {"coordinates":[-76.272338,42.111932],"type":"Point"}
}