{
  "type": "Feature",
  "properties": {
    "addr:full":"793 N Broadway Yonkers NY 10701",
    "addr:housenumber":"793",
    "addr:postcode":"10701",
    "addr:street":"N Broadway",
    "iso:country":"US",
    "sg:address":"793 N Broadway",
    "sg:city":"Yonkers",
    "sg:classifiers":[
        {
            "category":"Organizations",
            "subcategory":"Religious Organization",
            "type":"Services"
        }
    ],
    "sg:phone":"+1 914 963 6776",
    "sg:postcode":"10701",
    "sg:province":"NY",
    "sg:tags":[
        "church"
    ],
    "sg:website":"www.yonkerssdachurch.org",
    "wof:name":"Seventh Day Adventist Church",
    "wof:placetype":"venue"
},
  "geometry": {"coordinates":[-73.88547,40.9639],"type":"Point"}
}