{
  "type": "Feature",
  "properties": {
    "addr:full":"691 Tubbs Rd Mexico NY 13114",
    "addr:housenumber":"691",
    "addr:postcode":"13114",
    "addr:street":"Tubbs Rd",
    "iso:country":"US",
    "sg:address":"691 Tubbs Rd",
    "sg:city":"Mexico",
    "sg:classifiers":[
        {
            "category":"Building & Trades",
            "subcategory":"Construction",
            "type":"Services"
        }
    ],
    "sg:phone":"+1 315 963 3648",
    "sg:postcode":"13114",
    "sg:province":"NY",
    "sg:tags":[
        "general",
        "contractor"
    ],
    "wof:name":"Lake-Fect Construction",
    "wof:placetype":"venue"
},
  "geometry": {"coordinates":[-76.202821,43.466185],"type":"Point"}
}