{
  "type": "Feature",
  "properties": {
    "addr:full":"109 Dunning Rd Middletown NY 10940",
    "addr:housenumber":"109",
    "addr:postcode":"10940",
    "addr:street":"Dunning Rd",
    "iso:country":"US",
    "sg:address":"109 Dunning Rd",
    "sg:city":"Middletown",
    "sg:classifiers":[
        {
            "category":"Shopping",
            "subcategory":"Computers & Home Electronics",
            "type":"Retail Goods"
        }
    ],
    "sg:phone":"+1 845 344 8355",
    "sg:postcode":"10940",
    "sg:province":"NY",
    "wof:name":"Circuit City",
    "wof:placetype":"venue"
},
  "geometry": {"coordinates":[-74.380696,41.450309],"type":"Point"}
}