{
  "type": "Feature",
  "properties": {
    "iso:country":"US",
    "sg:address":"3 Squires St",
    "sg:city":"Cortland",
    "sg:classifiers":[
        {
            "category":"Autos & Motor Vehicles",
            "subcategory":"Automobile Sales",
            "type":"Retail Goods"
        }
    ],
    "sg:phone":"+1   ",
    "sg:postcode":"13045",
    "sg:province":"NY",
    "sg:tags":[
        "used"
    ],
    "sg:website":"www.akautos.net",
    "wof:name":"A & K Auto",
    "wof:placetype":"venue"
},
  "geometry": {"coordinates":[-76.18631000000001,42.590445],"type":"Point"}
}