{
  "type": "Feature",
  "properties": {
    "addr:full":"151 N Main St New City NY 10956",
    "addr:housenumber":"151",
    "addr:postcode":"10956",
    "addr:street":"N Main St",
    "iso:country":"US",
    "sg:address":"151 N Main St",
    "sg:city":"New City",
    "sg:classifiers":[
        {
            "category":"Professional",
            "subcategory":"Lawyer & Legal Services",
            "type":"Services"
        }
    ],
    "sg:phone":"+1 845 639 0974",
    "sg:postcode":"10956",
    "sg:province":"NY",
    "sg:tags":[
        "attorney"
    ],
    "wof:name":"Birbrower Beldock & Margolis",
    "wof:placetype":"venue"
},
  "geometry": {"coordinates":[-73.98884099999999,41.153873],"type":"Point"}
}