{
  "type": "Feature",
  "properties": {
    "iso:country":"US",
    "sg:address":"10086 Duanesburg Rd",
    "sg:city":"Delanson",
    "sg:classifiers":[
        {
            "category":"Freight",
            "type":"Transportation"
        }
    ],
    "sg:phone":"+1 518 895 2299",
    "sg:postcode":"12053",
    "sg:province":"NY",
    "sg:tags":[
        "delivery"
    ],
    "wof:name":"Q I Delivery",
    "wof:placetype":"venue"
},
  "geometry": {"coordinates":[-74.18528000000001,42.735084],"type":"Point"}
}