{
  "type": "Feature",
  "properties": {
    "iso:country":"US",
    "sg:address":"11599 230th St",
    "sg:city":"Jamaica",
    "sg:classifiers":[
        {
            "category":"Shopping",
            "subcategory":"Computers & Home Electronics",
            "type":"Retail Goods"
        }
    ],
    "sg:phone":"+1 718 949 6700",
    "sg:postcode":"11411",
    "sg:province":"NY",
    "sg:tags":[
        "equipment",
        "dealer"
    ],
    "wof:name":"Golden Touch Computers",
    "wof:placetype":"venue"
},
  "geometry": {"coordinates":[-73.73052199999999,40.694148],"type":"Point"}
}