{
  "type": "Feature",
  "properties": {
    "iso:country":"US",
    "sg:address":"7 Tall Oaks Ct",
    "sg:city":"Manorville",
    "sg:classifiers":[
        {
            "category":"Building & Trades",
            "subcategory":"Construction",
            "type":"Services"
        }
    ],
    "sg:phone":"+1 631 205 0215",
    "sg:postcode":"11949",
    "sg:province":"NY",
    "sg:tags":[
        "home",
        "improvement"
    ],
    "wof:name":"Style Contracting",
    "wof:placetype":"venue"
},
  "geometry": {"coordinates":[-72.840013,40.851406],"type":"Point"}
}