{
  "type": "Feature",
  "properties": {
    "addr:full":"33 Cleveland St Valley Stream NY 11580",
    "addr:housenumber":"33",
    "addr:postcode":"11580",
    "addr:street":"Cleveland St",
    "iso:country":"US",
    "sg:address":"33 Cleveland St",
    "sg:city":"Valley Stream",
    "sg:classifiers":[
        {
            "category":"Shopping",
            "subcategory":"Clothing, Apparel, & Fashions",
            "type":"Retail Goods"
        }
    ],
    "sg:phone":"+1 516 208 2800",
    "sg:postcode":"11580",
    "sg:province":"NY",
    "sg:tags":[
        "lingerie"
    ],
    "wof:name":"Moi Lingerie Inc",
    "wof:placetype":"venue"
},
  "geometry": {"coordinates":[-73.690332,40.661383],"type":"Point"}
}