{
  "type": "Feature",
  "properties": {
    "addr:full":"233 N Jensen Rd Vestal NY 13850",
    "addr:housenumber":"233",
    "addr:postcode":"13850",
    "addr:street":"N Jensen Rd",
    "iso:country":"US",
    "sg:address":"233 N Jensen Rd",
    "sg:city":"Vestal",
    "sg:classifiers":[
        {
            "category":"Home & Garden",
            "subcategory":"Building Materials",
            "type":"Retail Goods"
        }
    ],
    "sg:phone":"+1 607 729 6233",
    "sg:postcode":"13850",
    "sg:province":"NY",
    "wof:name":"County Bldg Supl",
    "wof:placetype":"venue"
},
  "geometry": {"coordinates":[-75.99605200000001,42.100291],"type":"Point"}
}