{
  "type": "Feature",
  "properties": {
    "iso:country":"US",
    "sg:address":"9 Clinton St",
    "sg:city":"New York Mills",
    "sg:classifiers":[
        {
            "category":"Wholesale",
            "subcategory":"Motor Vehicles",
            "type":"Manufacturing & Wholesale Goods"
        }
    ],
    "sg:phone":"+1 315 736 9381",
    "sg:postcode":"13417",
    "sg:province":"NY",
    "wof:name":"Miga Auto Sales Inc",
    "wof:placetype":"venue"
},
  "geometry": {"coordinates":[-75.298727,43.095317],"type":"Point"}
}