{
  "type": "Feature",
  "properties": {
    "iso:country":"US",
    "sg:address":"2600 Netherland Ave # 125",
    "sg:city":"Bronx",
    "sg:classifiers":[
        {
            "category":"Health Services",
            "subcategory":"Doctor",
            "type":"Services"
        }
    ],
    "sg:phone":"+1 718 796 1548",
    "sg:postcode":"10463",
    "sg:province":"NY",
    "sg:tags":[
        "medicine",
        "physician",
        "practice",
        "surgeons",
        "family"
    ],
    "wof:name":"Moshe Rubin Md Inc",
    "wof:placetype":"venue"
},
  "geometry": {"coordinates":[-73.916107,40.878559],"type":"Point"}
}