{
  "type": "Feature",
  "properties": {
    "addr:full":"109 Main St Big Flats NY 14814",
    "addr:housenumber":"109",
    "addr:postcode":"14814",
    "addr:street":"Main St",
    "iso:country":"US",
    "sg:address":"109 Main St",
    "sg:city":"Big Flats",
    "sg:classifiers":[
        {
            "category":"Building & Trades",
            "subcategory":"Cleaning & Sanitation",
            "type":"Services"
        }
    ],
    "sg:phone":"+1 607 562 8747",
    "sg:postcode":"14814",
    "sg:province":"NY",
    "sg:tags":[
        "snow",
        "removal"
    ],
    "wof:name":"Day Home & Lake Property Svc",
    "wof:placetype":"venue"
},
  "geometry": {"coordinates":[-76.93351199999999,42.134573],"type":"Point"}
}