{
  "type": "Feature",
  "properties": {
    "addr:full":"1325 Castle Hill Ave Bronx NY 10462",
    "addr:housenumber":"1325",
    "addr:postcode":"10462",
    "addr:street":"Castle Hill Ave",
    "iso:country":"US",
    "sg:address":"1325 Castle Hill Ave",
    "sg:city":"Bronx",
    "sg:classifiers":[
        {
            "category":"Professional",
            "subcategory":"Lawyer & Legal Services",
            "type":"Services"
        }
    ],
    "sg:phone":"+1   ",
    "sg:postcode":"10462",
    "sg:province":"NY",
    "wof:name":"Maris Mohman",
    "wof:placetype":"venue"
},
  "geometry": {"coordinates":[-73.852034,40.835076],"type":"Point"}
}