{
  "type": "Feature",
  "properties": {
    "addr:full":"4 Wilson Rd Valley Stream NY 11581",
    "addr:housenumber":"4",
    "addr:postcode":"11581",
    "addr:street":"Wilson Rd",
    "iso:country":"US",
    "sg:address":"4 Wilson Rd",
    "sg:city":"Valley Stream",
    "sg:classifiers":[
        {
            "category":"Wholesale",
            "subcategory":"Toys & Hobbies",
            "type":"Manufacturing & Wholesale Goods"
        }
    ],
    "sg:phone":"+1 516 791 9458",
    "sg:postcode":"11581",
    "sg:province":"NY",
    "wof:name":"AG Sales",
    "wof:placetype":"venue"
},
  "geometry": {"coordinates":[-73.700462,40.646115],"type":"Point"}
}