{
  "type": "Feature",
  "properties": {
    "iso:country":"US",
    "sg:address":"491 Cottekill Rd",
    "sg:city":"Stone Ridge",
    "sg:classifiers":[
        {
            "category":"Education",
            "subcategory":"Junior College",
            "type":"Public Place"
        }
    ],
    "sg:phone":"+1 845 687 5000",
    "sg:postcode":"12484",
    "sg:province":"NY",
    "sg:tags":[
        "technical",
        "institute"
    ],
    "sg:website":"www.sunyulster.edu",
    "wof:name":"Ulster County Community Clg",
    "wof:placetype":"venue"
},
  "geometry": {"coordinates":[-74.115128,41.853576],"type":"Point"}
}