{
  "type": "Feature",
  "properties": {
    "iso:country":"US",
    "sg:address":"52 N Pearl St",
    "sg:city":"Albany",
    "sg:classifiers":[
        {
            "category":"Shopping",
            "subcategory":"Florist",
            "type":"Retail Goods"
        }
    ],
    "sg:phone":"+1 518 465 7024",
    "sg:postcode":"12207",
    "sg:province":"NY",
    "wof:name":"Felthousen's Florist",
    "wof:placetype":"venue"
},
  "geometry": {"coordinates":[-73.751606,42.651532],"type":"Point"}
}