{
  "type": "Feature",
  "properties": {
    "iso:country":"US",
    "sg:address":"110 State Hwy 59",
    "sg:city":"Nanuet",
    "sg:classifiers":[
        {
            "category":"Shopping",
            "type":"Retail Goods"
        }
    ],
    "sg:phone":"+1   ",
    "sg:postcode":"10954",
    "sg:province":"NY",
    "sg:tags":[
        "merchandise"
    ],
    "wof:name":"Leslies Swmming Pool Sups 172",
    "wof:placetype":"venue"
},
  "geometry": {"coordinates":[-74.017309,41.098632],"type":"Point"}
}