{
  "type": "Feature",
  "properties": {
    "iso:country":"US",
    "sg:address":"5695 E Townline Rd",
    "sg:city":"Williamson",
    "sg:classifiers":[
        {
            "category":"Retail",
            "subcategory":"Auto Repair",
            "type":"Services"
        }
    ],
    "sg:phone":"+1   ",
    "sg:postcode":"14589",
    "sg:province":"NY",
    "sg:tags":[
        "engine",
        "farm",
        "truck",
        "machinery"
    ],
    "wof:name":"Jakes Repair Shop Inc",
    "wof:placetype":"venue"
},
  "geometry": {"coordinates":[-77.145167,43.208624],"type":"Point"}
}