{
  "type": "Feature",
  "properties": {
    "addr:full":"32 Narrows Rd S Staten Island NY 10305",
    "addr:housenumber":"32",
    "addr:postcode":"10305",
    "addr:street":"Narrows Rd S",
    "iso:country":"US",
    "sg:address":"32 Narrows Rd S",
    "sg:city":"Staten Island",
    "sg:classifiers":[
        {
            "category":"Retail",
            "subcategory":"Laundry & Dry Cleaning",
            "type":"Services"
        }
    ],
    "sg:phone":"+1 718 979 8753",
    "sg:postcode":"10305",
    "sg:province":"NY",
    "sg:tags":[
        "cleaners",
        "rug",
        "carpet"
    ],
    "wof:name":"Dr-Steam OF Si",
    "wof:placetype":"venue"
},
  "geometry": {"coordinates":[-74.069726,40.603725],"type":"Point"}
}