{
  "type": "Feature",
  "properties": {
    "iso:country":"US",
    "sg:address":"15 Linden Ave",
    "sg:city":"Larchmont",
    "sg:classifiers":[
        {
            "category":"Health Services",
            "subcategory":"Doctor",
            "type":"Services"
        }
    ],
    "sg:phone":"+1 914 834 4760",
    "sg:postcode":"10538",
    "sg:province":"NY",
    "sg:tags":[
        "medical"
    ],
    "wof:name":"K Burten MD",
    "wof:placetype":"venue"
},
  "geometry": {"coordinates":[-73.74892699999999,40.920731],"type":"Point"}
}