{
  "type": "Feature",
  "properties": {
    "addr:full":"36 Java St Brooklyn NY 11222",
    "addr:housenumber":"36",
    "addr:postcode":"11222",
    "addr:street":"Java St",
    "iso:country":"US",
    "sg:address":"36 Java St",
    "sg:city":"Brooklyn",
    "sg:classifiers":[
        {
            "category":"Home & Garden",
            "subcategory":"Building Materials",
            "type":"Retail Goods"
        }
    ],
    "sg:phone":"+1 718 349 0638",
    "sg:postcode":"11222",
    "sg:province":"NY",
    "sg:tags":[
        "equipment",
        "fixture",
        "lighting"
    ],
    "wof:name":"E & S Express Inc",
    "wof:placetype":"venue"
},
  "geometry": {"coordinates":[-73.959999,40.730999],"type":"Point"}
}