{
  "type": "Feature",
  "properties": {
    "addr:full":"21 Waverly Ave Brooklyn NY 11205",
    "addr:housenumber":"21",
    "addr:postcode":"11205",
    "addr:street":"Waverly Ave",
    "iso:country":"US",
    "sg:address":"21 Waverly Ave",
    "sg:city":"Brooklyn",
    "sg:classifiers":[
        {
            "category":"Education",
            "subcategory":"School",
            "type":"Public Place"
        }
    ],
    "sg:phone":"+1 718 330 0767",
    "sg:postcode":"11205",
    "sg:province":"NY",
    "wof:name":"United Talmudical Academy Torah Vyirah",
    "wof:placetype":"venue"
},
  "geometry": {"coordinates":[-73.96860100000001,40.697187],"type":"Point"}
}