{
  "type": "Feature",
  "properties": {
    "iso:country":"US",
    "sg:address":"914 Elmwood Ave",
    "sg:city":"Buffalo",
    "sg:classifiers":[
        {
            "category":"Restaurant",
            "type":"Food & Drink"
        }
    ],
    "sg:phone":"+1 716 882 4520",
    "sg:postcode":"14222",
    "sg:province":"NY",
    "sg:tags":[
        "eating"
    ],
    "wof:name":"Great Wall",
    "wof:placetype":"venue"
},
  "geometry": {"coordinates":[-78.876999,42.921799],"type":"Point"}
}