{
  "type": "Feature",
  "properties": {
    "addr:full":"810 W 181st Street New York NY 10033",
    "addr:housenumber":"810",
    "addr:postcode":"10033",
    "addr:street":"W 181St Street",
    "iso:country":"US",
    "sg:address":"810 W 181st Street",
    "sg:city":"New York",
    "sg:classifiers":[
        {
            "category":"Personal",
            "subcategory":"Barber",
            "type":"Services"
        }
    ],
    "sg:phone":"+1 212 923 9654",
    "sg:postcode":"10033",
    "sg:province":"NY",
    "wof:name":"Nilda Beauty Salon & Unisex",
    "wof:placetype":"venue"
},
  "geometry": {"coordinates":[-73.93898900000001,40.851227],"type":"Point"}
}