{
  "type": "Feature",
  "properties": {
    "addr:full":"1550 Deer Park Ave Deer Park NY 11729",
    "addr:housenumber":"1550",
    "addr:postcode":"11729",
    "addr:street":"Deer Park Ave",
    "iso:country":"US",
    "sg:address":"1550 Deer Park Ave",
    "sg:city":"Deer Park",
    "sg:classifiers":[
        {
            "category":"Professional",
            "subcategory":"Lawyer & Legal Services",
            "type":"Services"
        }
    ],
    "sg:phone":"+1 631 667 1023",
    "sg:postcode":"11729",
    "sg:province":"NY",
    "sg:tags":[
        "attorney"
    ],
    "wof:name":"Edward S Raskin",
    "wof:placetype":"venue"
},
  "geometry": {"coordinates":[-73.32523999999999,40.750973],"type":"Point"}
}