{
  "type": "Feature",
  "properties": {
    "addr:full":"2437 46th St Astoria NY 11103",
    "addr:housenumber":"2437",
    "addr:postcode":"11103",
    "addr:street":"46Th St",
    "iso:country":"US",
    "sg:address":"2437 46th St",
    "sg:city":"Astoria",
    "sg:classifiers":[
        {
            "category":"Building & Trades",
            "subcategory":"Construction",
            "type":"Services"
        }
    ],
    "sg:phone":"+1 718 993 9300",
    "sg:postcode":"11103",
    "sg:province":"NY",
    "sg:tags":[
        "system",
        "specialty",
        "heating",
        "contractor",
        "air conditioning"
    ],
    "wof:name":"Edison Cooling Systems Inc",
    "wof:placetype":"venue"
},
  "geometry": {"coordinates":[-73.905827,40.767075],"type":"Point"}
}