{
  "type": "Feature",
  "properties": {
    "iso:country":"US",
    "sg:address":"546 River Rd",
    "sg:city":"Potsdam",
    "sg:classifiers":[
        {
            "category":"Manufacturing",
            "subcategory":"Lumber",
            "type":"Manufacturing & Wholesale Goods"
        }
    ],
    "sg:phone":"+1 315 265 3492",
    "sg:postcode":"13676",
    "sg:province":"NY",
    "sg:tags":[
        "timberland",
        "timber"
    ],
    "wof:name":"Gerald J Thomas",
    "wof:placetype":"venue"
},
  "geometry": {"coordinates":[-75.01102,44.703357],"type":"Point"}
}