{
  "type": "Feature",
  "properties": {
    "iso:country":"US",
    "sg:address":"38 Darryl Lane",
    "sg:city":"Carmel",
    "sg:classifiers":[
        {
            "category":"Communications",
            "type":"Services"
        }
    ],
    "sg:phone":"+1 845 661 9553",
    "sg:postcode":"10512",
    "sg:province":"NY",
    "sg:tags":[
        "web",
        "design"
    ],
    "sg:website":"www.nycseowebdesign.com",
    "wof:name":"NY SEO Services",
    "wof:placetype":"venue"
},
  "geometry": {"coordinates":[-73.687116,41.442946],"type":"Point"}
}