{
  "type": "Feature",
  "properties": {
    "iso:country":"US",
    "sg:address":"7154 Otisco Valley Rd",
    "sg:city":"Preble",
    "sg:classifiers":[
        {
            "category":"Building & Trades",
            "subcategory":"Equipment Rental",
            "type":"Services"
        }
    ],
    "sg:phone":"+1 607 749 8839",
    "sg:postcode":"13141",
    "sg:province":"NY",
    "sg:tags":[
        "camping"
    ],
    "wof:name":"Hillside Tent Rentals",
    "wof:placetype":"venue"
},
  "geometry": {"coordinates":[-76.16580999999999,42.746642],"type":"Point"}
}