{
  "type": "Feature",
  "properties": {
    "addr:full":"28 Reynolds Ln Buchanan NY 10511",
    "addr:housenumber":"28",
    "addr:postcode":"10511",
    "addr:street":"Reynolds Ln",
    "iso:country":"US",
    "sg:address":"28 Reynolds Ln",
    "sg:city":"Buchanan",
    "sg:classifiers":[
        {
            "category":"Retail",
            "subcategory":"Auto Repair",
            "type":"Services"
        }
    ],
    "sg:phone":"+1 888 486 9555",
    "sg:postcode":"10511",
    "sg:province":"NY",
    "sg:tags":[
        "automobile",
        "restoration-antique",
        "classic"
    ],
    "sg:website":"http://www.hotrodhotel.com",
    "wof:name":"Hot Rod Hotel",
    "wof:placetype":"venue"
},
  "geometry": {"coordinates":[-73.93217,41.26582],"type":"Point"}
}