{
  "type": "Feature",
  "properties": {
    "addr:full":"10 Dennison St White Plains NY 10606",
    "addr:housenumber":"10",
    "addr:postcode":"10606",
    "addr:street":"Dennison St",
    "iso:country":"US",
    "sg:address":"10 Dennison St",
    "sg:city":"White Plains",
    "sg:classifiers":[
        {
            "category":"Freight",
            "type":"Transportation"
        }
    ],
    "sg:phone":"+1 914 946 4798",
    "sg:postcode":"10606",
    "sg:province":"NY",
    "sg:tags":[
        "commercial",
        "storage"
    ],
    "wof:name":"Tuck's Moving Svc",
    "wof:placetype":"venue"
},
  "geometry": {"coordinates":[-73.772656,41.025768],"type":"Point"}
}