{
  "type": "Feature",
  "properties": {
    "iso:country":"US",
    "sg:address":"2706 Hempstead Tpke",
    "sg:city":"Levittown",
    "sg:classifiers":[
        {
            "category":"Shopping",
            "subcategory":"Used Merchandise",
            "type":"Retail Goods"
        }
    ],
    "sg:phone":"+1   ",
    "sg:postcode":"11756",
    "sg:province":"NY",
    "wof:name":"U Trade M Book Centers Inc",
    "wof:placetype":"venue"
},
  "geometry": {"coordinates":[-73.53475299999999,40.724347],"type":"Point"}
}