{
  "type": "Feature",
  "properties": {
    "addr:full":"782 Caroline Ave Elmont NY 11003",
    "addr:housenumber":"782",
    "addr:postcode":"11003",
    "addr:street":"Caroline Ave",
    "iso:country":"US",
    "sg:address":"782 Caroline Ave",
    "sg:city":"Elmont",
    "sg:classifiers":[
        {
            "category":"Wholesale",
            "subcategory":"Motor Vehicles",
            "type":"Manufacturing & Wholesale Goods"
        }
    ],
    "sg:phone":"+1 516 872 9087",
    "sg:postcode":"11003",
    "sg:province":"NY",
    "wof:name":"Roche 6e11 Michel",
    "wof:placetype":"venue"
},
  "geometry": {"coordinates":[-73.70607,40.686923],"type":"Point"}
}