{
  "type": "Feature",
  "properties": {
    "addr:full":"101 Central Park W New York NY 10023",
    "addr:housenumber":"101",
    "addr:postcode":"10023",
    "addr:street":"Central Park W",
    "iso:country":"US",
    "sg:address":"101 Central Park W",
    "sg:city":"New York",
    "sg:classifiers":[
        {
            "category":"Real Estate",
            "subcategory":"Real Estate Operator",
            "type":"Services"
        }
    ],
    "sg:phone":"+1 212 874 3122",
    "sg:postcode":"10023",
    "sg:province":"NY",
    "sg:tags":[
        "apartment"
    ],
    "wof:name":"Apartments & Apartment Houses",
    "wof:placetype":"venue"
},
  "geometry": {"coordinates":[-73.977054,40.775002],"type":"Point"}
}