{
  "type": "Feature",
  "properties": {
    "addr:full":"410 Long Island Ave Wyandanch NY 11798",
    "addr:housenumber":"410",
    "addr:postcode":"11798",
    "addr:street":"Long Island Ave",
    "iso:country":"US",
    "sg:address":"410 Long Island Ave",
    "sg:city":"Wyandanch",
    "sg:classifiers":[
        {
            "category":"Structure",
            "subcategory":"Warehouse",
            "type":"Public Place"
        },
        {
            "category":"Retail",
            "subcategory":"Storage",
            "type":"Services"
        }
    ],
    "sg:phone":"+1 631 491 0747",
    "sg:postcode":"11798",
    "sg:province":"NY",
    "sg:tags":[
        "self",
        "warehouses-merchandise"
    ],
    "sg:website":"http://www.estiwarehouse.com",
    "wof:name":"E.S.T.I. Warehouse Inc.",
    "wof:placetype":"venue"
},
  "geometry": {"coordinates":[-73.354938,40.755335],"type":"Point"}
}