{
  "type": "Feature",
  "properties": {
    "addr:full":"224 Court St Brooklyn NY 11201",
    "addr:housenumber":"224",
    "addr:postcode":"11201",
    "addr:street":"Court St",
    "iso:country":"US",
    "sg:address":"224 Court St",
    "sg:city":"Brooklyn",
    "sg:classifiers":[
        {
            "category":"Health Services",
            "subcategory":"Doctor",
            "type":"Services"
        }
    ],
    "sg:phone":"+1 718 643 4292",
    "sg:postcode":"11201",
    "sg:province":"NY",
    "sg:tags":[
        "surgeon",
        "oral"
    ],
    "wof:name":"Reich Steven DDS",
    "wof:placetype":"venue"
},
  "geometry": {"coordinates":[-73.994102,40.686401],"type":"Point"}
}