{
  "type": "Feature",
  "properties": {
    "addr:full":"16 S 9th St New Hyde Park NY 11040",
    "addr:housenumber":"16",
    "addr:postcode":"11040",
    "addr:street":"S 9Th St",
    "iso:country":"US",
    "sg:address":"16 S 9th St",
    "sg:city":"New Hyde Park",
    "sg:classifiers":[
        {
            "category":"Organizations",
            "subcategory":"Professional Association",
            "type":"Services"
        }
    ],
    "sg:phone":"+1 516 326 4575",
    "sg:postcode":"11040",
    "sg:province":"NY",
    "wof:name":"Christian Association-Youth",
    "wof:placetype":"venue"
},
  "geometry": {"coordinates":[-73.686262,40.732167],"type":"Point"}
}