{
  "type": "Feature",
  "properties": {
    "addr:full":"532 E 14 St New York NY 10009",
    "addr:housenumber":"532;14",
    "addr:postcode":"10009",
    "addr:street":"E",
    "iso:country":"US",
    "sg:address":"532 E 14 St",
    "sg:city":"New York",
    "sg:classifiers":[
        {
            "category":"Manufacturing",
            "subcategory":"Apparel",
            "type":"Manufacturing & Wholesale Goods"
        }
    ],
    "sg:phone":"+1 212 673 0223",
    "sg:postcode":"10009",
    "sg:province":"NY",
    "sg:tags":[
        "hat"
    ],
    "wof:name":"William G Johnson",
    "wof:placetype":"venue"
},
  "geometry": {"coordinates":[-73.978616,40.729696],"type":"Point"}
}