{
  "type": "Feature",
  "properties": {
    "iso:country":"US",
    "sg:address":"21 Wawbeek Ave",
    "sg:city":"Tupper Lake",
    "sg:classifiers":[
        {
            "category":"Manufacturing",
            "subcategory":"Lumber",
            "type":"Manufacturing & Wholesale Goods"
        }
    ],
    "sg:phone":"+1   ",
    "sg:postcode":"12986",
    "sg:province":"NY",
    "sg:tags":[
        "company",
        "logging"
    ],
    "wof:name":"ONeill Brothers Logging Inc",
    "wof:placetype":"venue"
},
  "geometry": {"coordinates":[-74.467679,44.222892],"type":"Point"}
}