{
  "type": "Feature",
  "properties": {
    "addr:full":"1503 State Hwy 52 Walden NY 12586",
    "addr:housenumber":"1503",
    "addr:postcode":"12586",
    "addr:street":"State Hwy 52",
    "iso:country":"US",
    "sg:address":"1503 State Hwy 52",
    "sg:city":"Walden",
    "sg:classifiers":[
        {
            "category":"Real Estate",
            "subcategory":"Real Estate Agent",
            "type":"Services"
        }
    ],
    "sg:phone":"+1 845 778 7444",
    "sg:postcode":"12586",
    "sg:province":"NY",
    "wof:name":"Hormann Realty",
    "wof:placetype":"venue"
},
  "geometry": {"coordinates":[-74.23095499999999,41.58742],"type":"Point"}
}