{
  "type": "Feature",
  "properties": {
    "iso:country":"US",
    "sg:address":"1305 State St",
    "sg:city":"Watertown",
    "sg:classifiers":[
        {
            "category":"Food & Beverages",
            "subcategory":"Candy",
            "type":"Retail Goods"
        }
    ],
    "sg:phone":"+1 315 779 8210",
    "sg:postcode":"13601",
    "sg:province":"NY",
    "sg:tags":[
        "confectionery"
    ],
    "wof:name":"Candy Expressions",
    "wof:placetype":"venue"
},
  "geometry": {"coordinates":[-75.888935,43.969423],"type":"Point"}
}