{
  "type": "Feature",
  "properties": {
    "iso:country":"US",
    "sg:address":"421 Commack Rd",
    "sg:city":"Deer Park",
    "sg:classifiers":[
        {
            "category":"Professional",
            "type":"Services"
        }
    ],
    "sg:phone":"+1 631 586 9703",
    "sg:postcode":"11729",
    "sg:province":"NY",
    "sg:tags":[
        "establishment"
    ],
    "wof:name":"R2D Corp",
    "wof:placetype":"venue"
},
  "geometry": {"coordinates":[-73.311255,40.765496],"type":"Point"}
}