{
  "type": "Feature",
  "properties": {
    "addr:full":"10 Henry St Binghamton NY 13901",
    "addr:housenumber":"10",
    "addr:postcode":"13901",
    "addr:street":"Henry St",
    "iso:country":"US",
    "sg:address":"10 Henry St",
    "sg:city":"Binghamton",
    "sg:classifiers":[
        {
            "category":"Organizations",
            "subcategory":"Religious Organization",
            "type":"Services"
        }
    ],
    "sg:phone":"+1 607 722 2308",
    "sg:postcode":"13901",
    "sg:province":"NY",
    "sg:tags":[
        "church"
    ],
    "sg:website":"www.christchurch1810.org",
    "wof:name":"Christ Episcopal Church",
    "wof:placetype":"venue"
},
  "geometry": {"coordinates":[-75.91284400000001,42.100575],"type":"Point"}
}