{
  "type": "Feature",
  "properties": {
    "addr:full":"1471 Watson Ave Bronx NY 10472",
    "addr:housenumber":"1471",
    "addr:postcode":"10472",
    "addr:street":"Watson Ave",
    "iso:country":"US",
    "sg:address":"1471 Watson Ave",
    "sg:city":"Bronx",
    "sg:classifiers":[
        {
            "category":"Shopping",
            "subcategory":"Music",
            "type":"Retail Goods"
        }
    ],
    "sg:phone":"+1   ",
    "sg:postcode":"10472",
    "sg:province":"NY",
    "wof:name":"Downstairs Records",
    "wof:placetype":"venue"
},
  "geometry": {"coordinates":[-73.88082900000001,40.825784],"type":"Point"}
}