{
  "type": "Feature",
  "properties": {
    "iso:country":"US",
    "sg:address":"9 Paradise Rd",
    "sg:city":"Bronxville",
    "sg:classifiers":[
        {
            "category":"Shopping",
            "subcategory":"Beauty & Cosmetics",
            "type":"Retail Goods"
        }
    ],
    "sg:phone":"+1 914 826 4319",
    "sg:postcode":"10708",
    "sg:province":"NY",
    "sg:tags":[
        "perfume"
    ],
    "wof:name":"Clark Botanicals Inc",
    "wof:placetype":"venue"
},
  "geometry": {"coordinates":[-73.830133,40.942735],"type":"Point"}
}