{
  "type": "Feature",
  "properties": {
    "iso:country":"US",
    "sg:address":"325 Blumel Rd",
    "sg:city":"Middletown",
    "sg:classifiers":[
        {
            "category":"Building & Trades",
            "subcategory":"Cleaning & Sanitation",
            "type":"Services"
        }
    ],
    "sg:phone":"+1 845 446 4601",
    "sg:postcode":"10941",
    "sg:province":"NY",
    "sg:tags":[
        "carpet"
    ],
    "wof:name":"Oxy Magic Carpet Cleaning",
    "wof:placetype":"venue"
},
  "geometry": {"coordinates":[-74.360444,41.479674],"type":"Point"}
}