{
  "type": "Feature",
  "properties": {
    "iso:country":"US",
    "sg:address":"1069 Shoemaker Rd",
    "sg:city":"Webster",
    "sg:classifiers":[
        {
            "category":"Building & Trades",
            "subcategory":"Construction",
            "type":"Services"
        }
    ],
    "sg:phone":"+1 585 872 1826",
    "sg:postcode":"14580",
    "sg:province":"NY",
    "sg:tags":[
        "home",
        "remodeling",
        "family",
        "contractor"
    ],
    "wof:name":"Tjs Property Improvement",
    "wof:placetype":"venue"
},
  "geometry": {"coordinates":[-77.447233,43.23902],"type":"Point"}
}