{
  "type": "Feature",
  "properties": {
    "iso:country":"US",
    "sg:address":"16 School St",
    "sg:city":"Rye",
    "sg:classifiers":[
        {
            "category":"Wholesale",
            "subcategory":"Construction Materials",
            "type":"Manufacturing & Wholesale Goods"
        },
        {
            "category":"Wholesale",
            "subcategory":"Durable Goods & Equipment",
            "type":"Manufacturing & Wholesale Goods"
        }
    ],
    "sg:phone":"+1 914 925 9401",
    "sg:postcode":"10580",
    "sg:province":"NY",
    "sg:tags":[
        "importer",
        "paper",
        "specialty",
        "exporter",
        "clay"
    ],
    "wof:name":"Henry I Daty Inc",
    "wof:placetype":"venue"
},
  "geometry": {"coordinates":[-73.68338799999999,40.984318],"type":"Point"}
}