{
  "type": "Feature",
  "properties": {
    "addr:full":"3600 Long Beach Rd Oceanside NY 11572",
    "addr:housenumber":"3600",
    "addr:postcode":"11572",
    "addr:street":"Long Beach Rd",
    "iso:country":"US",
    "sg:address":"3600 Long Beach Rd",
    "sg:city":"Oceanside",
    "sg:classifiers":[
        {
            "category":"Shopping",
            "subcategory":"Department Store",
            "type":"Retail Goods"
        }
    ],
    "sg:phone":"+1 516 763 4788",
    "sg:postcode":"11572",
    "sg:province":"NY",
    "wof:name":"Kohl's",
    "wof:placetype":"venue"
},
  "geometry": {"coordinates":[-73.640198,40.623402],"type":"Point"}
}