{
  "type": "Feature",
  "properties": {
    "addr:full":"45 N Elliott Pl Brooklyn NY 11205",
    "addr:housenumber":"45",
    "addr:postcode":"11205",
    "addr:street":"N Elliott Pl",
    "iso:country":"US",
    "sg:address":"45 N Elliott Pl",
    "sg:city":"Brooklyn",
    "sg:classifiers":[
        {
            "category":"Real Estate",
            "subcategory":"Real Estate Agent",
            "type":"Services"
        }
    ],
    "sg:phone":"+1 718 875 0075",
    "sg:postcode":"11205",
    "sg:province":"NY",
    "sg:tags":[
        "desk",
        "space"
    ],
    "wof:name":"Navy Yard Housing Development",
    "wof:placetype":"venue"
},
  "geometry": {"coordinates":[-73.97739,40.697668],"type":"Point"}
}