{
  "type": "Feature",
  "properties": {
    "iso:country":"US",
    "sg:address":"26 Cindy's Ln",
    "sg:city":"Ballston Spa",
    "sg:classifiers":[
        {
            "category":"Shopping",
            "subcategory":"Gifts & Souvenirs",
            "type":"Retail Goods"
        }
    ],
    "sg:phone":"+1   ",
    "sg:postcode":"12020",
    "sg:province":"NY",
    "wof:name":"Solid Rock Gift Shop",
    "wof:placetype":"venue"
},
  "geometry": {"coordinates":[-73.794742,42.993913],"type":"Point"}
}