{
  "type": "Feature",
  "properties": {
    "addr:full":"120 Bay St Staten Island NY 10301",
    "addr:housenumber":"120",
    "addr:postcode":"10301",
    "addr:street":"Bay St",
    "iso:country":"US",
    "sg:address":"120 Bay St",
    "sg:city":"Staten Island",
    "sg:classifiers":[
        {
            "category":"Government",
            "subcategory":"Office",
            "type":"Public Place"
        }
    ],
    "sg:phone":"+1 718 727 1221",
    "sg:postcode":"10301",
    "sg:province":"NY",
    "sg:tags":[
        "federal",
        "program",
        "adm"
    ],
    "wof:name":"US Service Corps-Retired Execs",
    "wof:placetype":"venue"
},
  "geometry": {"coordinates":[-74.075503,40.639654],"type":"Point"}
}