{
  "type": "Feature",
  "properties": {
    "addr:full":"390 Berry St Brooklyn NY 11211",
    "addr:housenumber":"390",
    "addr:postcode":"11211",
    "addr:street":"Berry St",
    "iso:country":"US",
    "sg:address":"390 Berry St",
    "sg:city":"Brooklyn",
    "sg:classifiers":[
        {
            "category":"Manufacturing",
            "subcategory":"Printing",
            "type":"Manufacturing & Wholesale Goods"
        }
    ],
    "sg:phone":"+1 718 302 9505",
    "sg:postcode":"11211",
    "sg:province":"NY",
    "sg:tags":[
        "printer"
    ],
    "wof:name":"Statewide Printing",
    "wof:placetype":"venue"
},
  "geometry": {"coordinates":[-73.965644,40.710206],"type":"Point"}
}