{
  "type": "Feature",
  "properties": {
    "addr:full":"1119 Erie Blvd W Rome NY 13440",
    "addr:housenumber":"1119",
    "addr:postcode":"13440",
    "addr:street":"Erie Blvd W",
    "iso:country":"US",
    "sg:address":"1119 Erie Blvd W",
    "sg:city":"Rome",
    "sg:classifiers":[
        {
            "category":"Autos & Motor Vehicles",
            "subcategory":"Automobile Sales",
            "type":"Retail Goods"
        }
    ],
    "sg:phone":"+1   ",
    "sg:postcode":"13440",
    "sg:province":"NY",
    "sg:tags":[
        "used"
    ],
    "wof:name":"Falcone Auto Sales",
    "wof:placetype":"venue"
},
  "geometry": {"coordinates":[-75.481908,43.220842],"type":"Point"}
}