{
  "type": "Feature",
  "properties": {
    "iso:country":"US",
    "sg:address":"155 Versailles Rd",
    "sg:city":"Rochester",
    "sg:classifiers":[
        {
            "category":"Professional",
            "subcategory":"Computer Services",
            "type":"Services"
        }
    ],
    "sg:phone":"+1 585 544 6335",
    "sg:postcode":"14621",
    "sg:province":"NY",
    "sg:tags":[
        "consultant",
        "designer"
    ],
    "wof:name":"Caso Computer Consulting",
    "wof:placetype":"venue"
},
  "geometry": {"coordinates":[-77.613725,43.196001],"type":"Point"}
}