{
  "type": "Feature",
  "properties": {
    "addr:full":"21 W 58th St New York NY 10019",
    "addr:housenumber":"21",
    "addr:postcode":"10019",
    "addr:street":"W 58Th St",
    "iso:country":"US",
    "sg:address":"21 W 58th St",
    "sg:city":"New York",
    "sg:classifiers":[
        {
            "category":"Cafe",
            "type":"Food & Drink"
        }
    ],
    "sg:menulink":"http://www.allmenus.com/ny/new-york/247581-green-cafe/menu/",
    "sg:phone":"+1 212 753 8833",
    "sg:postcode":"10019",
    "sg:province":"NY",
    "sg:tags":[
        "american",
        "diner"
    ],
    "wof:name":"Green Cafe",
    "wof:placetype":"venue"
},
  "geometry": {"coordinates":[-73.975213,40.764755],"type":"Point"}
}