{
  "type": "Feature",
  "properties": {
    "iso:country":"US",
    "sg:address":"628 S Main St",
    "sg:city":"North Syracuse",
    "sg:classifiers":[
        {
            "category":"Banks & Credit Unions",
            "subcategory":"Bank",
            "type":"Services"
        }
    ],
    "sg:phone":"+1 315 458 0074",
    "sg:postcode":"13212",
    "sg:province":"NY",
    "sg:tags":[
        "financing"
    ],
    "wof:name":"Wells Fargo Financial Accptnc",
    "wof:placetype":"venue"
},
  "geometry": {"coordinates":[-76.141274,43.123649],"type":"Point"}
}