{
  "type": "Feature",
  "properties": {
    "iso:country":"US",
    "sg:address":"329 Band Camp Rd",
    "sg:city":"Saugerties",
    "sg:classifiers":[
        {
            "category":"Building & Trades",
            "subcategory":"Landscaping Services",
            "type":"Services"
        }
    ],
    "sg:phone":"+1 845 246 1859",
    "sg:postcode":"12477",
    "sg:province":"NY",
    "sg:tags":[
        "landscape"
    ],
    "wof:name":"Rist Deverne",
    "wof:placetype":"venue"
},
  "geometry": {"coordinates":[-74.03654400000001,42.089054],"type":"Point"}
}