{
  "type": "Feature",
  "properties": {
    "addr:full":"2247 1st Ave Manhattan NY 10029",
    "addr:housenumber":"2247",
    "addr:postcode":"10029",
    "addr:street":"1St Ave",
    "iso:country":"US",
    "sg:address":"2247 1st Ave",
    "sg:city":"Manhattan",
    "sg:classifiers":[
        {
            "category":"Restaurant",
            "type":"Food & Drink"
        }
    ],
    "sg:phone":"+1 212 876 8136",
    "sg:postcode":"10029",
    "sg:province":"NY",
    "sg:tags":[
        "mexican"
    ],
    "wof:name":"Los Amigos Restaurant",
    "wof:placetype":"venue"
},
  "geometry": {"coordinates":[-73.935732,40.795605],"type":"Point"}
}