{
  "type": "Feature",
  "properties": {
    "addr:full":"6929 Williams Rd Niagara Falls NY 14304",
    "addr:housenumber":"6929",
    "addr:postcode":"14304",
    "addr:street":"Williams Rd",
    "iso:country":"US",
    "sg:address":"6929 Williams Rd",
    "sg:city":"Niagara Falls",
    "sg:classifiers":[
        {
            "category":"Restaurant",
            "type":"Food & Drink"
        }
    ],
    "sg:phone":"+1 716 297 7616",
    "sg:postcode":"14304",
    "sg:province":"NY",
    "sg:tags":[
        "delicatessen"
    ],
    "wof:name":"All The Best",
    "wof:placetype":"venue"
},
  "geometry": {"coordinates":[-78.940699,43.088004],"type":"Point"}
}