{
  "type": "Feature",
  "properties": {
    "iso:country":"US",
    "sg:address":"3400 Baychester Ave",
    "sg:city":"Bronx",
    "sg:classifiers":[
        {
            "category":"Retail",
            "subcategory":"Repair Shop",
            "type":"Services"
        }
    ],
    "sg:phone":"+1 347 332 2865",
    "sg:postcode":"10475",
    "sg:province":"NY",
    "sg:tags":[
        "lock",
        "locksmith"
    ],
    "wof:name":"USA Locksmiths",
    "wof:placetype":"venue"
},
  "geometry": {"coordinates":[-73.83874299999999,40.881266],"type":"Point"}
}