{
  "type": "Feature",
  "properties": {
    "iso:country":"US",
    "sg:address":"12913 State Hwy 22",
    "sg:city":"Canaan",
    "sg:classifiers":[
        {
            "category":"Building & Trades",
            "subcategory":"Electrical",
            "type":"Services"
        }
    ],
    "sg:phone":"+1 518 781 4801",
    "sg:postcode":"12029",
    "sg:province":"NY",
    "sg:tags":[
        "electrical",
        "contractor"
    ],
    "wof:name":"Dunton Electric",
    "wof:placetype":"venue"
},
  "geometry": {"coordinates":[-73.431645,42.36752],"type":"Point"}
}