{
  "type": "Feature",
  "properties": {
    "addr:full":"266 E 162nd St Bronx NY 10451",
    "addr:housenumber":"266",
    "addr:postcode":"10451",
    "addr:street":"E 162Nd St",
    "iso:country":"US",
    "sg:address":"266 E 162nd St",
    "sg:city":"Bronx",
    "sg:classifiers":[
        {
            "category":"Building & Trades",
            "subcategory":"Construction",
            "type":"Services"
        }
    ],
    "sg:phone":"+1 718 402 9883",
    "sg:postcode":"10451",
    "sg:province":"NY",
    "sg:tags":[
        "carpenter"
    ],
    "wof:name":"Concept Carpentry Corp",
    "wof:placetype":"venue"
},
  "geometry": {"coordinates":[-73.91887199999999,40.826812],"type":"Point"}
}