{
  "type": "Feature",
  "properties": {
    "addr:full":"395 Flatbush Ave Exn Brooklyn NY 11201",
    "addr:housenumber":"395",
    "addr:postcode":"11201",
    "addr:street":"Flatbush Ave",
    "iso:country":"US",
    "sg:address":"395 Flatbush Ave Exn",
    "sg:city":"Brooklyn",
    "sg:classifiers":[
        {
            "category":"Restaurant",
            "type":"Food & Drink"
        }
    ],
    "sg:phone":"+1 718 643 2830",
    "sg:postcode":"11201",
    "sg:province":"NY",
    "wof:name":"For Goodness Steaks",
    "wof:placetype":"venue"
},
  "geometry": {"coordinates":[-73.98102900000001,40.689354],"type":"Point"}
}