{
  "type": "Feature",
  "properties": {
    "addr:full":"86 E 57th St New York NY 10022",
    "addr:housenumber":"86",
    "addr:postcode":"10022",
    "addr:street":"E 57Th St",
    "iso:country":"US",
    "sg:address":"86 E 57th St",
    "sg:city":"New York",
    "sg:classifiers":[
        {
            "category":"Retail",
            "subcategory":"Repair Shop",
            "type":"Services"
        }
    ],
    "sg:phone":"+1 212 937 1207",
    "sg:postcode":"10022",
    "sg:province":"NY",
    "sg:tags":[
        "lock",
        "locksmith"
    ],
    "wof:name":"911 Locksmith",
    "wof:placetype":"venue"
},
  "geometry": {"coordinates":[-73.971797,40.762106],"type":"Point"}
}