{
  "type": "Feature",
  "properties": {
    "addr:full":"10 Meroke Ln Rocky Point NY 11778",
    "addr:housenumber":"10",
    "addr:postcode":"11778",
    "addr:street":"Meroke Ln",
    "iso:country":"US",
    "sg:address":"10 Meroke Ln",
    "sg:city":"Rocky Point",
    "sg:classifiers":[
        {
            "category":"Manufacturing",
            "subcategory":"Printing",
            "type":"Manufacturing & Wholesale Goods"
        }
    ],
    "sg:phone":"+1 631 744 4792",
    "sg:postcode":"11778",
    "sg:province":"NY",
    "sg:tags":[
        "multimedia"
    ],
    "sg:website":"www.nielsenmedia.com",
    "wof:name":"Nielsen Media Research",
    "wof:placetype":"venue"
},
  "geometry": {"coordinates":[-72.948307,40.951143],"type":"Point"}
}