{
  "type": "Feature",
  "properties": {
    "iso:country":"US",
    "sg:address":"500 Bedford Avenue",
    "sg:city":"Brooklyn",
    "sg:classifiers":[
        {
            "category":"Organizations",
            "subcategory":"Religious Organization",
            "type":"Services"
        }
    ],
    "sg:phone":"+1 718 963 3764",
    "sg:postcode":"11211",
    "sg:province":"NY",
    "wof:name":"Cong Yetev Lev",
    "wof:placetype":"venue"
},
  "geometry": {"coordinates":[-73.96440800000001,40.707035],"type":"Point"}
}