{
  "type": "Feature",
  "properties": {
    "iso:country":"US",
    "sg:address":"134 Milbar Blvd",
    "sg:city":"Farmingdale",
    "sg:classifiers":[
        {
            "category":"Wholesale",
            "subcategory":"Apparel",
            "type":"Manufacturing & Wholesale Goods"
        }
    ],
    "sg:phone":"+1 631 753 2017",
    "sg:postcode":"11735",
    "sg:province":"NY",
    "sg:tags":[
        "clothing"
    ],
    "wof:name":"Pretty Pink",
    "wof:placetype":"venue"
},
  "geometry": {"coordinates":[-73.418485,40.750027],"type":"Point"}
}