{
  "type": "Feature",
  "properties": {
    "addr:full":"2268 State Hwy 174 Marietta NY 13110",
    "addr:housenumber":"2268",
    "addr:postcode":"13110",
    "addr:street":"State Hwy 174",
    "iso:country":"US",
    "sg:address":"2268 State Hwy 174",
    "sg:city":"Marietta",
    "sg:classifiers":[
        {
            "category":"Building & Trades",
            "subcategory":"Landscaping Services",
            "type":"Services"
        }
    ],
    "sg:phone":"+1 315 673 9037",
    "sg:postcode":"13110",
    "sg:province":"NY",
    "wof:name":"M D Lawncare",
    "wof:placetype":"venue"
},
  "geometry": {"coordinates":[-76.32386099999999,42.877505],"type":"Point"}
}