{
  "type": "Feature",
  "properties": {
    "addr:full":"2060 Ocean Ave Ronkonkoma NY 11779",
    "addr:housenumber":"2060",
    "addr:postcode":"11779",
    "addr:street":"Ocean Ave",
    "iso:country":"US",
    "sg:address":"2060 Ocean Ave",
    "sg:city":"Ronkonkoma",
    "sg:classifiers":[
        {
            "category":"Restaurant",
            "type":"Food & Drink"
        }
    ],
    "sg:phone":"+1 631 981 8334",
    "sg:postcode":"11779",
    "sg:province":"NY",
    "sg:tags":[
        "cafe"
    ],
    "wof:name":"Bocconcini's II",
    "wof:placetype":"venue"
},
  "geometry": {"coordinates":[-73.121269,40.786882],"type":"Point"}
}