{
  "type": "Feature",
  "properties": {
    "iso:country":"US",
    "sg:address":"122 W 20th Street",
    "sg:city":"New York",
    "sg:classifiers":[
        {
            "category":"Retail",
            "subcategory":"Portrait Studio",
            "type":"Services"
        }
    ],
    "sg:phone":"+1 212 229 1895",
    "sg:postcode":"10011",
    "sg:province":"NY",
    "sg:tags":[
        "photography",
        "store"
    ],
    "wof:name":"Digital Lab",
    "wof:placetype":"venue"
},
  "geometry": {"coordinates":[-73.99480699999999,40.741277],"type":"Point"}
}