{
  "type": "Feature",
  "properties": {
    "addr:full":"156 Stone Church Rd Ballston Spa NY 12020",
    "addr:housenumber":"156",
    "addr:postcode":"12020",
    "addr:street":"Stone Church Rd",
    "iso:country":"US",
    "sg:address":"156 Stone Church Rd",
    "sg:city":"Ballston Spa",
    "sg:classifiers":[
        {
            "category":"Professional",
            "subcategory":"Business Services",
            "type":"Services"
        }
    ],
    "sg:phone":"+1 518 583 9615",
    "sg:postcode":"12020",
    "sg:province":"NY",
    "wof:name":"Ahc Group",
    "wof:placetype":"venue"
},
  "geometry": {"coordinates":[-73.878041,43.067624],"type":"Point"}
}