{
  "type": "Feature",
  "properties": {
    "addr:full":"1237 Castle Hill Ave Bronx NY 10462",
    "addr:housenumber":"1237",
    "addr:postcode":"10462",
    "addr:street":"Castle Hill Ave",
    "iso:country":"US",
    "sg:address":"1237 Castle Hill Ave",
    "sg:city":"Bronx",
    "sg:classifiers":[
        {
            "category":"Health Services",
            "subcategory":"Chiropractor",
            "type":"Services"
        }
    ],
    "sg:phone":"+1 800 640 9314",
    "sg:postcode":"10462",
    "sg:province":"NY",
    "wof:name":"Nathanson George DC",
    "wof:placetype":"venue"
},
  "geometry": {"coordinates":[-73.851439,40.83287],"type":"Point"}
}