{
  "type": "Feature",
  "properties": {
    "iso:country":"US",
    "sg:address":"364 Goodwill Road",
    "sg:city":"Montgomery",
    "sg:classifiers":[
        {
            "category":"Travel",
            "subcategory":"Bed & Breakfast",
            "type":"Entertainment"
        }
    ],
    "sg:phone":"+1 845 457 3457",
    "sg:postcode":"12549",
    "sg:province":"NY",
    "sg:website":"www.buckshomestead.com",
    "wof:name":"Buck's Homestead Bed & Breakfast",
    "wof:placetype":"venue"
},
  "geometry": {"coordinates":[-74.22108299999999,41.517115],"type":"Point"}
}