{
  "type": "Feature",
  "properties": {
    "addr:full":"458 Myrtle Ave Brooklyn NY 11205",
    "addr:housenumber":"458",
    "addr:postcode":"11205",
    "addr:street":"Myrtle Ave",
    "iso:country":"US",
    "sg:address":"458 Myrtle Ave",
    "sg:city":"Brooklyn",
    "sg:classifiers":[
        {
            "category":"Shopping",
            "subcategory":"Clothing, Apparel, & Fashions",
            "type":"Retail Goods"
        }
    ],
    "sg:phone":"+1   ",
    "sg:postcode":"11205",
    "sg:province":"NY",
    "sg:tags":[
        "ready",
        "st"
    ],
    "wof:name":"Fashion World",
    "wof:placetype":"venue"
},
  "geometry": {"coordinates":[-73.967454,40.693178],"type":"Point"}
}