{
  "type": "Feature",
  "properties": {
    "iso:country":"US",
    "sg:address":"2005 Sunset Dr",
    "sg:city":"Lakewood",
    "sg:classifiers":[
        {
            "category":"Wholesale",
            "subcategory":"Electrical",
            "type":"Manufacturing & Wholesale Goods"
        }
    ],
    "sg:phone":"+1 716 483 6401",
    "sg:postcode":"14750",
    "sg:province":"NY",
    "sg:tags":[
        "equipment",
        "electronic"
    ],
    "wof:name":"United Industries Inc",
    "wof:placetype":"venue"
},
  "geometry": {"coordinates":[-79.30072199999999,42.085755],"type":"Point"}
}