{
  "type": "Feature",
  "properties": {
    "addr:full":"69 Villa Ave Yonkers NY 10704",
    "addr:housenumber":"69",
    "addr:postcode":"10704",
    "addr:street":"Villa Ave",
    "iso:country":"US",
    "sg:address":"69 Villa Ave",
    "sg:city":"Yonkers",
    "sg:classifiers":[
        {
            "category":"Building & Trades",
            "subcategory":"Construction",
            "type":"Services"
        }
    ],
    "sg:phone":"+1 914 237 0697",
    "sg:postcode":"10704",
    "sg:province":"NY",
    "sg:tags":[
        "masonry",
        "contractor"
    ],
    "wof:name":"Milford Construction Inc",
    "wof:placetype":"venue"
},
  "geometry": {"coordinates":[-73.85095,40.917333],"type":"Point"}
}