{
  "type": "Feature",
  "properties": {
    "iso:country":"US",
    "sg:address":"2023 Military Tpke",
    "sg:city":"Plattsburgh",
    "sg:classifiers":[
        {
            "category":"Retail",
            "subcategory":"Repair Shop",
            "type":"Services"
        }
    ],
    "sg:phone":"+1   ",
    "sg:postcode":"12901",
    "sg:province":"NY",
    "sg:tags":[
        "furniture"
    ],
    "wof:name":"Wood Magicians",
    "wof:placetype":"venue"
},
  "geometry": {"coordinates":[-73.543813,44.732974],"type":"Point"}
}