{
  "type": "Feature",
  "properties": {
    "iso:country":"US",
    "sg:address":"4915 Broadway Apt 5J",
    "sg:city":"New York",
    "sg:classifiers":[
        {
            "category":"Communications",
            "type":"Services"
        }
    ],
    "sg:phone":"+1 212 569 9246",
    "sg:postcode":"10034",
    "sg:province":"NY",
    "sg:tags":[
        "web",
        "design"
    ],
    "sg:website":"www.eclectrix.net",
    "wof:name":"Eclectrix",
    "wof:placetype":"venue"
},
  "geometry": {"coordinates":[-73.921555,40.866405],"type":"Point"}
}