{
  "type": "Feature",
  "properties": {
    "iso:country":"US",
    "sg:address":"1221 Erie Blvd W",
    "sg:city":"Rome",
    "sg:classifiers":[
        {
            "category":"Food & Beverages",
            "subcategory":"Dairy",
            "type":"Retail Goods"
        },
        {
            "category":"Food & Beverages",
            "subcategory":"Groceries & Convenience Stores",
            "type":"Retail Goods"
        }
    ],
    "sg:phone":"+1 315 337 5329",
    "sg:postcode":"13440",
    "sg:province":"NY",
    "sg:tags":[
        "product"
    ],
    "wof:name":"Nice N Easy Gr Shoppe 511",
    "wof:placetype":"venue"
},
  "geometry": {"coordinates":[-75.489171,43.226867],"type":"Point"}
}