{
  "type": "Feature",
  "properties": {
    "addr:full":"20 Elm St Hornell NY 14843",
    "addr:housenumber":"20",
    "addr:postcode":"14843",
    "addr:street":"Elm St",
    "iso:country":"US",
    "sg:address":"20 Elm St",
    "sg:city":"Hornell",
    "sg:classifiers":[
        {
            "category":"Health Services",
            "subcategory":"Doctor",
            "type":"Services"
        }
    ],
    "sg:phone":"+1 607 324 7240",
    "sg:postcode":"14843",
    "sg:province":"NY",
    "sg:tags":[
        "physician",
        "surgeon"
    ],
    "wof:name":"Joseph P Mc Cormick MD",
    "wof:placetype":"venue"
},
  "geometry": {"coordinates":[-77.659569,42.324781],"type":"Point"}
}