{
  "type": "Feature",
  "properties": {
    "iso:country":"US",
    "sg:address":"10 Gailes Dr",
    "sg:city":"Slingerlands",
    "sg:classifiers":[
        {
            "category":"Professional",
            "type":"Services"
        }
    ],
    "sg:phone":"+1 518 439 5900",
    "sg:postcode":"12159",
    "sg:province":"NY",
    "sg:tags":[
        "establishment"
    ],
    "wof:name":"Invesmart",
    "wof:placetype":"venue"
},
  "geometry": {"coordinates":[-73.87700100000001,42.622095],"type":"Point"}
}