{
  "type": "Feature",
  "properties": {
    "addr:full":"4028 Arrowhead Ln Liverpool NY 13090",
    "addr:housenumber":"4028",
    "addr:postcode":"13090",
    "addr:street":"Arrowhead Ln",
    "iso:country":"US",
    "sg:address":"4028 Arrowhead Ln",
    "sg:city":"Liverpool",
    "sg:classifiers":[
        {
            "category":"Professional",
            "subcategory":"Engineering",
            "type":"Services"
        }
    ],
    "sg:phone":"+1 315 652 8160",
    "sg:postcode":"13090",
    "sg:province":"NY",
    "sg:tags":[
        "engineer"
    ],
    "wof:name":"Durr Engineering",
    "wof:placetype":"venue"
},
  "geometry": {"coordinates":[-76.233193,43.133096],"type":"Point"}
}