{
  "type": "Feature",
  "properties": {
    "addr:full":"20 Cain Dr Brentwood NY 11717",
    "addr:housenumber":"20",
    "addr:postcode":"11717",
    "addr:street":"Cain Dr",
    "iso:country":"US",
    "sg:address":"20 Cain Dr",
    "sg:city":"Brentwood",
    "sg:classifiers":[
        {
            "category":"Shopping",
            "subcategory":"Computers & Home Electronics",
            "type":"Retail Goods"
        }
    ],
    "sg:phone":"+1 631 273 2168",
    "sg:postcode":"11717",
    "sg:province":"NY",
    "sg:tags":[
        "equipment",
        "dealer"
    ],
    "wof:name":"Computer Resource-America Corp",
    "wof:placetype":"venue"
},
  "geometry": {"coordinates":[-73.248002,40.806793],"type":"Point"}
}