{
  "type": "Feature",
  "properties": {
    "iso:country":"US",
    "sg:address":"1586 McDonald Ave",
    "sg:city":"Brooklyn",
    "sg:classifiers":[
        {
            "category":"Shopping",
            "subcategory":"Stationery & Office Supplies",
            "type":"Retail Goods"
        }
    ],
    "sg:phone":"+1 718 339 7293",
    "sg:postcode":"11230",
    "sg:province":"NY",
    "sg:tags":[
        "equipment"
    ],
    "wof:name":"Daily Stop",
    "wof:placetype":"venue"
},
  "geometry": {"coordinates":[-73.974197,40.614399],"type":"Point"}
}