{
  "type": "Feature",
  "properties": {
    "addr:full":"2 Cedar Crest Dr Huntington Station NY 11746",
    "addr:housenumber":"2",
    "addr:postcode":"11746",
    "addr:street":"Cedar Crest Dr",
    "iso:country":"US",
    "sg:address":"2 Cedar Crest Dr",
    "sg:city":"Huntington Station",
    "sg:classifiers":[
        {
            "category":"Banks & Credit Unions",
            "subcategory":"Investment Brokerage",
            "type":"Services"
        }
    ],
    "sg:phone":"+1 631 242 9616",
    "sg:postcode":"11746",
    "sg:province":"NY",
    "sg:tags":[
        "financial"
    ],
    "wof:name":"Capital Dynamics Corp",
    "wof:placetype":"venue"
},
  "geometry": {"coordinates":[-73.299916,40.796687],"type":"Point"}
}