{
  "type": "Feature",
  "properties": {
    "iso:country":"US",
    "sg:address":"77 Main St",
    "sg:city":"Westhampton Bch",
    "sg:classifiers":[
        {
            "category":"Building & Trades",
            "subcategory":"Construction",
            "type":"Services"
        }
    ],
    "sg:phone":"+1 631 288 2100",
    "sg:postcode":"11978",
    "sg:province":"NY",
    "sg:tags":[
        "contractor"
    ],
    "wof:name":"Gessin Contracting Corporation",
    "wof:placetype":"venue"
},
  "geometry": {"coordinates":[-72.644755,40.809092],"type":"Point"}
}