{
  "type": "Feature",
  "properties": {
    "addr:full":"2 Central Park N New York NY 10026",
    "addr:housenumber":"2",
    "addr:postcode":"10026",
    "addr:street":"Central Park N",
    "iso:country":"US",
    "sg:address":"2 Central Park N",
    "sg:city":"New York",
    "sg:classifiers":[
        {
            "category":"Insurance",
            "subcategory":"Health Insurance",
            "type":"Services"
        }
    ],
    "sg:phone":"+1 646 658 7019",
    "sg:postcode":"10026",
    "sg:province":"NY",
    "sg:tags":[
        "plan"
    ],
    "wof:name":"Cigna",
    "wof:placetype":"venue"
},
  "geometry": {"coordinates":[-73.952483,40.798252],"type":"Point"}
}