{
  "type": "Feature",
  "properties": {
    "addr:full":"8811 Roosevelt Ave Jackson Heights NY 11372",
    "addr:housenumber":"8811",
    "addr:postcode":"11372",
    "addr:street":"Roosevelt Ave",
    "iso:country":"US",
    "sg:address":"8811 Roosevelt Ave",
    "sg:city":"Jackson Heights",
    "sg:classifiers":[
        {
            "category":"Real Estate",
            "subcategory":"Real Estate Services",
            "type":"Services"
        },
        {
            "category":"Professional",
            "subcategory":"Lawyer & Legal Services",
            "type":"Services"
        }
    ],
    "sg:phone":"+1 718 424 6263",
    "sg:postcode":"11372",
    "sg:province":"NY",
    "sg:tags":[
        "management",
        "property",
        "notary"
    ],
    "wof:name":"Chapin Realty",
    "wof:placetype":"venue"
},
  "geometry": {"coordinates":[-73.878197,40.748402],"type":"Point"}
}