{
  "type": "Feature",
  "properties": {
    "addr:full":"29 E 9 St New York NY 10003",
    "addr:housenumber":"29;9",
    "addr:postcode":"10003",
    "addr:street":"E",
    "iso:country":"US",
    "sg:address":"29 E 9 St",
    "sg:city":"New York",
    "sg:classifiers":[
        {
            "category":"Wholesale",
            "subcategory":"Apparel",
            "type":"Manufacturing & Wholesale Goods"
        }
    ],
    "sg:phone":"+1 212 473 2669",
    "sg:postcode":"10003",
    "sg:province":"NY",
    "sg:tags":[
        "piece"
    ],
    "wof:name":"Savel of Princeton Inc",
    "wof:placetype":"venue"
},
  "geometry": {"coordinates":[-73.99191999999999,40.731165],"type":"Point"}
}