{
  "type": "Feature",
  "properties": {
    "addr:full":"83 Broadway Newburgh NY 12550",
    "addr:housenumber":"83",
    "addr:postcode":"12550",
    "addr:street":"Broadway",
    "iso:country":"US",
    "sg:address":"83 Broadway",
    "sg:city":"Newburgh",
    "sg:classifiers":[
        {
            "category":"Government",
            "subcategory":"Office",
            "type":"Public Place"
        }
    ],
    "sg:phone":"+1 845 569 7320",
    "sg:postcode":"12550",
    "sg:province":"NY",
    "sg:tags":[
        "city",
        "taxation"
    ],
    "wof:name":"Newburgh Finance Dept",
    "wof:placetype":"venue"
},
  "geometry": {"coordinates":[-74.010632,41.499894],"type":"Point"}
}