{
  "type": "Feature",
  "properties": {
    "iso:country":"US",
    "sg:address":"1404 Route 9",
    "sg:city":"Wappingers Falls",
    "sg:classifiers":[
        {
            "category":"Shopping",
            "subcategory":"Florist",
            "type":"Retail Goods"
        },
        {
            "category":"Food & Beverages",
            "subcategory":"Groceries & Convenience Stores",
            "type":"Retail Goods"
        }
    ],
    "sg:phone":"+1 845 298 9565",
    "sg:postcode":"12590",
    "sg:province":"NY",
    "wof:name":"Stop&Shop",
    "wof:placetype":"venue"
},
  "geometry": {"coordinates":[-73.907899,41.584776],"type":"Point"}
}