{
  "type": "Feature",
  "properties": {
    "iso:country":"US",
    "sg:address":"102 Shinnecock Ave",
    "sg:city":"Massapequa",
    "sg:classifiers":[
        {
            "category":"Communications",
            "subcategory":"Film & Video Production",
            "type":"Services"
        }
    ],
    "sg:phone":"+1   ",
    "sg:postcode":"11758",
    "sg:province":"NY",
    "sg:tags":[
        "motion"
    ],
    "wof:name":"Bill Cusick Productions",
    "wof:placetype":"venue"
},
  "geometry": {"coordinates":[-73.43541399999999,40.659715],"type":"Point"}
}