{
  "type": "Feature",
  "properties": {
    "iso:country":"US",
    "sg:address":"32 Jefferson Ave",
    "sg:city":"Spring Valley",
    "sg:classifiers":[
        {
            "category":"Professional",
            "type":"Services"
        }
    ],
    "sg:phone":"+1 845 354 6716",
    "sg:postcode":"10977",
    "sg:province":"NY",
    "sg:tags":[
        "establishment"
    ],
    "wof:name":"Share Of New Square Respite",
    "wof:placetype":"venue"
},
  "geometry": {"coordinates":[-74.02549999999999,41.139046],"type":"Point"}
}