{
  "type": "Feature",
  "properties": {
    "iso:country":"US",
    "sg:address":"3750 Monroe Ave",
    "sg:city":"Pittsford",
    "sg:classifiers":[
        {
            "category":"Organizations",
            "subcategory":"Professional Association",
            "type":"Services"
        }
    ],
    "sg:phone":"+1 585 385 9450",
    "sg:postcode":"14534",
    "sg:province":"NY",
    "wof:name":"Bricklayers & Allied Craftwork",
    "wof:placetype":"venue"
},
  "geometry": {"coordinates":[-77.52463299999999,43.09464],"type":"Point"}
}