{
  "type": "Feature",
  "properties": {
    "addr:full":"876 Avenue of the Americas Manhattan NY 10001",
    "addr:housenumber":"876",
    "addr:postcode":"10001",
    "addr:street":"Avenue Of The Americas",
    "iso:country":"US",
    "sg:address":"876 Avenue of the Americas",
    "sg:city":"Manhattan",
    "sg:classifiers":[
        {
            "category":"Food & Beverages",
            "subcategory":"Groceries & Convenience Stores",
            "type":"Retail Goods"
        }
    ],
    "sg:phone":"+1 212 213 2431",
    "sg:postcode":"10001",
    "sg:province":"NY",
    "wof:name":"876 Market Deli",
    "wof:placetype":"venue"
},
  "geometry": {"coordinates":[-73.98884700000001,40.747877],"type":"Point"}
}