{
  "type": "Feature",
  "properties": {
    "addr:full":"35 Collegeview Ave Poughkeepsie NY 12603",
    "addr:housenumber":"35",
    "addr:postcode":"12603",
    "addr:street":"Collegeview Ave",
    "iso:country":"US",
    "sg:address":"35 Collegeview Ave",
    "sg:city":"Poughkeepsie",
    "sg:classifiers":[
        {
            "category":"Health Services",
            "subcategory":"Doctor",
            "type":"Services"
        }
    ],
    "sg:phone":"+1 845 471 3580",
    "sg:postcode":"12603",
    "sg:province":"NY",
    "sg:tags":[
        "physician",
        "surgeon",
        "medical"
    ],
    "wof:name":"Arthur W Menken MD PC",
    "wof:placetype":"venue"
},
  "geometry": {"coordinates":[-73.89599,41.69094],"type":"Point"}
}