{
  "type": "Feature",
  "properties": {
    "iso:country":"US",
    "sg:address":"Ft. Washington Park",
    "sg:city":"New York",
    "sg:classifiers":[
        {
            "category":"Restaurant",
            "type":"Food & Drink"
        }
    ],
    "sg:postcode":"10033",
    "sg:province":"NY",
    "sg:tags":[
        "flavor",
        "local"
    ],
    "sg:website":"www.historichousetrust.org/item....",
    "wof:name":"Little Red Lighthouse",
    "wof:placetype":"venue"
},
  "geometry": {"coordinates":[-73.941236,40.853873],"type":"Point"}
}