{
  "type": "Feature",
  "properties": {
    "iso:country":"US",
    "sg:address":"395 Maple St",
    "sg:city":"Rochester",
    "sg:classifiers":[
        {
            "category":"Building & Trades",
            "subcategory":"Plumbing",
            "type":"Services"
        }
    ],
    "sg:phone":"+1 585 436 1029",
    "sg:postcode":"14611",
    "sg:province":"NY",
    "sg:tags":[
        "mechanical",
        "contractor"
    ],
    "sg:website":"www.ancoma.com",
    "wof:name":"Ancoma Inc",
    "wof:placetype":"venue"
},
  "geometry": {"coordinates":[-77.63701399999999,43.15514],"type":"Point"}
}