{
  "type": "Feature",
  "properties": {
    "addr:full":"359 Lake Ave St James NY 11780",
    "addr:housenumber":"359",
    "addr:postcode":"11780",
    "addr:street":"Lake Ave",
    "iso:country":"US",
    "sg:address":"359 Lake Ave",
    "sg:city":"St James",
    "sg:classifiers":[
        {
            "category":"Communications",
            "subcategory":"Film & Video Production",
            "type":"Services"
        }
    ],
    "sg:phone":"+1 631 862 0299",
    "sg:postcode":"11780",
    "sg:province":"NY",
    "sg:tags":[
        "taping"
    ],
    "wof:name":"Media House",
    "wof:placetype":"venue"
},
  "geometry": {"coordinates":[-73.15697,40.87992],"type":"Point"}
}