{
  "type": "Feature",
  "properties": {
    "iso:country":"US",
    "sg:address":"150 W 28th St Ste 803",
    "sg:city":"New York",
    "sg:classifiers":[
        {
            "category":"Personal",
            "type":"Services"
        }
    ],
    "sg:phone":"+1 646 418 1327",
    "sg:postcode":"10001",
    "sg:province":"NY",
    "sg:tags":[
        "local"
    ],
    "wof:name":"Sound Clash Rehearsal Studios",
    "wof:placetype":"venue"
},
  "geometry": {"coordinates":[-73.991952,40.746646],"type":"Point"}
}