{
  "type": "Feature",
  "properties": {
    "iso:country":"US",
    "sg:address":"540 Heathcote Rd",
    "sg:city":"Lindenhurst",
    "sg:classifiers":[
        {
            "category":"Banks & Credit Unions",
            "subcategory":"Financial Services",
            "type":"Services"
        },
        {
            "category":"Banks & Credit Unions",
            "subcategory":"Atm",
            "type":"Services"
        },
        {
            "category":"Food & Beverages",
            "subcategory":"Groceries & Convenience Stores",
            "type":"Retail Goods"
        }
    ],
    "sg:phone":"+1 631 225 0738",
    "sg:postcode":"11757",
    "sg:province":"NY",
    "sg:tags":[
        "money",
        "location",
        "order"
    ],
    "sg:website":"http://www.7-eleven.com",
    "wof:name":"7-Eleven",
    "wof:placetype":"venue"
},
  "geometry": {"coordinates":[-73.376786,40.709272],"type":"Point"}
}