{
  "type": "Feature",
  "properties": {
    "addr:full":"5175 Broadway Depew NY 14043",
    "addr:housenumber":"5175",
    "addr:postcode":"14043",
    "addr:street":"Broadway",
    "iso:country":"US",
    "sg:address":"5175 Broadway",
    "sg:city":"Depew",
    "sg:classifiers":[
        {
            "category":"Restaurant",
            "type":"Food & Drink"
        }
    ],
    "sg:menulink":"http://www.allmenus.com/ny/lancaster/148326-subway/menu/",
    "sg:phone":"+1 716 681 7827",
    "sg:postcode":"14043",
    "sg:province":"NY",
    "sg:tags":[
        "american",
        "sandwich"
    ],
    "wof:name":"Subway",
    "wof:placetype":"venue"
},
  "geometry": {"coordinates":[-78.683565,42.901199],"type":"Point"}
}