{
  "type": "Feature",
  "properties": {
    "iso:country":"US",
    "sg:address":"251 Highland Ave",
    "sg:city":"Middletown",
    "sg:classifiers":[
        {
            "category":"Sports & Exercise",
            "subcategory":"Gym",
            "type":"Entertainment"
        }
    ],
    "sg:phone":"+1 845 695 2418",
    "sg:postcode":"10940",
    "sg:province":"NY",
    "sg:tags":[
        "fitness",
        "physical",
        "facility"
    ],
    "wof:name":"Micheles Total Fitness Salon",
    "wof:placetype":"venue"
},
  "geometry": {"coordinates":[-74.412756,41.461955],"type":"Point"}
}