{
  "type": "Feature",
  "properties": {
    "addr:full":"40 W 72nd St New York NY 10023",
    "addr:housenumber":"40",
    "addr:postcode":"10023",
    "addr:street":"W 72Nd St",
    "iso:country":"US",
    "sg:address":"40 W 72nd St",
    "sg:city":"New York",
    "sg:classifiers":[
        {
            "category":"Health Services",
            "subcategory":"Dentist",
            "type":"Services"
        }
    ],
    "sg:phone":"+1 212 877 3085",
    "sg:postcode":"10023",
    "sg:province":"NY",
    "wof:name":"Tisch Marc DDS",
    "wof:placetype":"venue"
},
  "geometry": {"coordinates":[-73.97784,40.776858],"type":"Point"}
}