{
  "type": "Feature",
  "properties": {
    "addr:full":"3221 E Tremont Ave Bronx NY 10461",
    "addr:housenumber":"3221",
    "addr:postcode":"10461",
    "addr:street":"E Tremont Ave",
    "iso:country":"US",
    "sg:address":"3221 E Tremont Ave",
    "sg:city":"Bronx",
    "sg:classifiers":[
        {
            "category":"Real Estate",
            "subcategory":"Real Estate Agent",
            "type":"Services"
        }
    ],
    "sg:phone":"+1 718 518 1900",
    "sg:postcode":"10461",
    "sg:province":"NY",
    "wof:name":"Aragon Realty Group Inc",
    "wof:placetype":"venue"
},
  "geometry": {"coordinates":[-73.83332900000001,40.836046],"type":"Point"}
}