{
  "type": "Feature",
  "properties": {
    "addr:full":"57 Colgate Dr Plainview NY 11803",
    "addr:housenumber":"57",
    "addr:postcode":"11803",
    "addr:street":"Colgate Dr",
    "iso:country":"US",
    "sg:address":"57 Colgate Dr",
    "sg:city":"Plainview",
    "sg:classifiers":[
        {
            "category":"Banks & Credit Unions",
            "subcategory":"Bank",
            "type":"Services"
        }
    ],
    "sg:phone":"+1 516 367 2280",
    "sg:postcode":"11803",
    "sg:province":"NY",
    "wof:name":"Conqueror Federal Credit Union",
    "wof:placetype":"venue"
},
  "geometry": {"coordinates":[-73.457573,40.798132],"type":"Point"}
}