{
  "type": "Feature",
  "properties": {
    "iso:country":"US",
    "sg:address":"41 Westminster Rd",
    "sg:city":"Rochester",
    "sg:classifiers":[
        {
            "category":"Organizations",
            "subcategory":"Religious Organization",
            "type":"Services"
        }
    ],
    "sg:phone":"+1 585 325 7260",
    "sg:postcode":"14607",
    "sg:province":"NY",
    "sg:tags":[
        "church"
    ],
    "wof:name":"Rochester Monthly Meeting",
    "wof:placetype":"venue"
},
  "geometry": {"coordinates":[-77.582358,43.149931],"type":"Point"}
}