{
  "type": "Feature",
  "properties": {
    "iso:country":"US",
    "sg:address":"361 Stagg St Ste 3",
    "sg:city":"Brooklyn",
    "sg:classifiers":[
        {
            "category":"Shopping",
            "subcategory":"Antiques",
            "type":"Retail Goods"
        },
        {
            "category":"Professional",
            "subcategory":"Art Services",
            "type":"Services"
        }
    ],
    "sg:phone":"+1 718 381 3548",
    "sg:postcode":"11206",
    "sg:province":"NY",
    "sg:tags":[
        "repair",
        "restoration",
        "reproduction"
    ],
    "wof:name":"Df Conservation",
    "wof:placetype":"venue"
},
  "geometry": {"coordinates":[-73.934865,40.710328],"type":"Point"}
}