{
  "type": "Feature",
  "properties": {
    "addr:full":"370 Knickerbocker Ave Brooklyn NY 11237",
    "addr:housenumber":"370",
    "addr:postcode":"11237",
    "addr:street":"Knickerbocker Ave",
    "iso:country":"US",
    "sg:address":"370 Knickerbocker Ave",
    "sg:city":"Brooklyn",
    "sg:classifiers":[
        {
            "category":"Shopping",
            "subcategory":"Clothing, Apparel, & Fashions",
            "type":"Retail Goods"
        }
    ],
    "sg:phone":"+1   ",
    "sg:postcode":"11237",
    "sg:province":"NY",
    "sg:tags":[
        "accessory"
    ],
    "wof:name":"Knickerbocker Boys & Mens",
    "wof:placetype":"venue"
},
  "geometry": {"coordinates":[-73.921132,40.700343],"type":"Point"}
}