{
  "type": "Feature",
  "properties": {
    "addr:full":"2330 Ridge Rd W Rochester NY 14420",
    "addr:housenumber":"2330",
    "addr:postcode":"14420",
    "addr:street":"Ridge Rd W",
    "iso:country":"US",
    "sg:address":"2330 Ridge Rd W",
    "sg:city":"Rochester",
    "sg:classifiers":[
        {
            "category":"Shopping",
            "subcategory":"Shoes",
            "type":"Retail Goods"
        }
    ],
    "sg:phone":"+1   ",
    "sg:postcode":"14420",
    "sg:province":"NY",
    "wof:name":"Dexter Shoe",
    "wof:placetype":"venue"
},
  "geometry": {"coordinates":[-77.69238799999999,43.209331],"type":"Point"}
}