{
  "type": "Feature",
  "properties": {
    "addr:full":"5 S Broadway Yonkers NY 10701",
    "addr:housenumber":"5",
    "addr:postcode":"10701",
    "addr:street":"S Broadway",
    "iso:country":"US",
    "sg:address":"5 S Broadway",
    "sg:city":"Yonkers",
    "sg:classifiers":[
        {
            "category":"Professional",
            "subcategory":"Detective & Security Services",
            "type":"Services"
        }
    ],
    "sg:phone":"+1   ",
    "sg:postcode":"10701",
    "sg:province":"NY",
    "sg:tags":[
        "car"
    ],
    "wof:name":"ASAP Security",
    "wof:placetype":"venue"
},
  "geometry": {"coordinates":[-73.898399,40.933519],"type":"Point"}
}