{
  "type": "Feature",
  "properties": {
    "iso:country":"US",
    "sg:address":"571 Sacandaga Rd",
    "sg:city":"Schenectady",
    "sg:classifiers":[
        {
            "category":"Food & Beverages",
            "subcategory":"Groceries & Convenience Stores",
            "type":"Retail Goods"
        }
    ],
    "sg:phone":"+1 518 372 8719",
    "sg:postcode":"12302",
    "sg:province":"NY",
    "sg:website":"www.stewartsshops.com",
    "wof:name":"Stewart's Shops",
    "wof:placetype":"venue"
},
  "geometry": {"coordinates":[-73.98143399999999,42.860194],"type":"Point"}
}