{
  "type": "Feature",
  "properties": {
    "iso:country":"US",
    "sg:address":"48 W Buffalo St",
    "sg:city":"Warsaw",
    "sg:classifiers":[
        {
            "category":"Personal",
            "type":"Services"
        }
    ],
    "sg:phone":"+1 585 786 3590",
    "sg:postcode":"14569",
    "sg:province":"NY",
    "sg:tags":[
        "therapist",
        "massage",
        "physical"
    ],
    "sg:website":"www.hhmassageandspa.com",
    "wof:name":"Healing Hands Massage & Spa",
    "wof:placetype":"venue"
},
  "geometry": {"coordinates":[-78.13361399999999,42.740219],"type":"Point"}
}