{
  "type": "Feature",
  "properties": {
    "addr:full":"2726 Gerritsen Ave Brooklyn NY 11229",
    "addr:housenumber":"2726",
    "addr:postcode":"11229",
    "addr:street":"Gerritsen Ave",
    "iso:country":"US",
    "sg:address":"2726 Gerritsen Ave",
    "sg:city":"Brooklyn",
    "sg:classifiers":[
        {
            "category":"Health Services",
            "subcategory":"Podiatrist",
            "type":"Services"
        }
    ],
    "sg:phone":"+1 718 648 4163",
    "sg:postcode":"11229",
    "sg:province":"NY",
    "wof:name":"Frank Spinner DPM",
    "wof:placetype":"venue"
},
  "geometry": {"coordinates":[-73.924792,40.592529],"type":"Point"}
}