{
  "type": "Feature",
  "properties": {
    "iso:country":"US",
    "sg:address":"1100 Wantagh Ave",
    "sg:city":"Wantagh",
    "sg:classifiers":[
        {
            "category":"Health Services",
            "subcategory":"Chiropractor",
            "type":"Services"
        }
    ],
    "sg:phone":"+1   ",
    "sg:postcode":"11793",
    "sg:province":"NY",
    "wof:name":"Scher Richard W DC",
    "wof:placetype":"venue"
},
  "geometry": {"coordinates":[-73.50772499999999,40.693801],"type":"Point"}
}