{
  "type": "Feature",
  "properties": {
    "addr:full":"133 E 110th St New York NY 10029",
    "addr:housenumber":"133",
    "addr:postcode":"10029",
    "addr:street":"E 110Th St",
    "iso:country":"US",
    "sg:address":"133 E 110th St",
    "sg:city":"New York",
    "sg:classifiers":[
        {
            "category":"Restaurant",
            "type":"Food & Drink"
        },
        {
            "category":"Food Court",
            "type":"Food & Drink"
        }
    ],
    "sg:postcode":"10029",
    "sg:province":"NY",
    "sg:tags":[
        "mexican",
        "stand"
    ],
    "wof:name":"Holy Mole Tamale!",
    "wof:placetype":"venue"
},
  "geometry": {"coordinates":[-73.94474,40.795175],"type":"Point"}
}