{
  "type": "Feature",
  "properties": {
    "iso:country":"US",
    "sg:address":"267 Collins Rd",
    "sg:city":"Vestal",
    "sg:classifiers":[
        {
            "category":"Wholesale",
            "subcategory":"Computers",
            "type":"Manufacturing & Wholesale Goods"
        }
    ],
    "sg:phone":"+1 607 748 6661",
    "sg:postcode":"13850",
    "sg:province":"NY",
    "wof:name":"Douglas Edwin",
    "wof:placetype":"venue"
},
  "geometry": {"coordinates":[-76.08024,42.013668],"type":"Point"}
}