{
  "type": "Feature",
  "properties": {
    "iso:country":"US",
    "sg:address":"8 Muriel Ave",
    "sg:city":"Rensselaer",
    "sg:classifiers":[
        {
            "category":"Building & Trades",
            "subcategory":"Construction",
            "type":"Services"
        }
    ],
    "sg:phone":"+1 518 449 1376",
    "sg:postcode":"12144",
    "sg:province":"NY",
    "sg:tags":[
        "contractor",
        "laying",
        "flooring",
        "floor"
    ],
    "wof:name":"Classic Floors",
    "wof:placetype":"venue"
},
  "geometry": {"coordinates":[-73.7315,42.619435],"type":"Point"}
}