{
  "type": "Feature",
  "properties": {
    "iso:country":"US",
    "sg:address":"360 S Sunrise Rd",
    "sg:city":"West Babylon",
    "sg:classifiers":[
        {
            "category":"Banks & Credit Unions",
            "subcategory":"Bank",
            "type":"Services"
        }
    ],
    "sg:phone":"+1 631 422 7050",
    "sg:postcode":"11704",
    "sg:province":"NY",
    "sg:tags":[
        "loan",
        "real estate"
    ],
    "wof:name":"Southern Star Mortgage",
    "wof:placetype":"venue"
},
  "geometry": {"coordinates":[-73.363516,40.712549],"type":"Point"}
}