{
  "type": "Feature",
  "properties": {
    "iso:country":"US",
    "sg:address":"289 New Main St",
    "sg:city":"Yonkers",
    "sg:classifiers":[
        {
            "category":"Shopping",
            "subcategory":"Gifts & Souvenirs",
            "type":"Retail Goods"
        },
        {
            "category":"Manufacturing",
            "subcategory":"Paper Products",
            "type":"Manufacturing & Wholesale Goods"
        }
    ],
    "sg:phone":"+1 914 968 7551",
    "sg:postcode":"10701",
    "sg:province":"NY",
    "sg:tags":[
        "manufacturer",
        "cards-wholesale",
        "card",
        "greeting"
    ],
    "wof:name":"Homeric Imports",
    "wof:placetype":"venue"
},
  "geometry": {"coordinates":[-73.89557499999999,40.92838],"type":"Point"}
}