{
  "type": "Feature",
  "properties": {
    "iso:country":"US",
    "sg:address":"222 E 75 St",
    "sg:city":"New York",
    "sg:classifiers":[
        {
            "category":"Building & Trades",
            "subcategory":"Construction",
            "type":"Services"
        }
    ],
    "sg:phone":"+1 212 249 3502",
    "sg:postcode":"10021",
    "sg:province":"NY",
    "sg:tags":[
        "painter"
    ],
    "wof:name":"Amek Painting Renovations",
    "wof:placetype":"venue"
},
  "geometry": {"coordinates":[-73.957358,40.770899],"type":"Point"}
}