{
  "type": "Feature",
  "properties": {
    "addr:full":"560 New York Ave Brooklyn NY 11225",
    "addr:housenumber":"560",
    "addr:postcode":"11225",
    "addr:street":"New York Ave",
    "iso:country":"US",
    "sg:address":"560 New York Ave",
    "sg:city":"Brooklyn",
    "sg:classifiers":[
        {
            "category":"Education",
            "subcategory":"Library",
            "type":"Public Place"
        }
    ],
    "sg:phone":"+1 718 773 1223",
    "sg:postcode":"11225",
    "sg:province":"NY",
    "wof:name":"Crown Heights",
    "wof:placetype":"venue"
},
  "geometry": {"coordinates":[-73.94783099999999,40.661746],"type":"Point"}
}