{
  "type": "Feature",
  "properties": {
    "addr:full":"93 Oak St New Canaan NY 06840",
    "addr:housenumber":"93",
    "addr:postcode":"06840",
    "addr:street":"Oak St",
    "iso:country":"US",
    "sg:address":"93 Oak St",
    "sg:city":"New Canaan",
    "sg:classifiers":[
        {
            "category":"Building & Trades",
            "subcategory":"Landscaping Services",
            "type":"Services"
        }
    ],
    "sg:phone":"+1 203 245 6970",
    "sg:postcode":"06840",
    "sg:province":"NY",
    "sg:tags":[
        "landscape",
        "contractor"
    ],
    "wof:name":"Homesites",
    "wof:placetype":"venue"
},
  "geometry": {"coordinates":[-73.487059,41.142441],"type":"Point"}
}