{
  "type": "Feature",
  "properties": {
    "iso:country":"US",
    "sg:address":"635 Dickson St",
    "sg:city":"Endicott",
    "sg:classifiers":[
        {
            "category":"Retail",
            "subcategory":"Repair Shop",
            "type":"Services"
        },
        {
            "category":"Manufacturing",
            "subcategory":"Electronics",
            "type":"Manufacturing & Wholesale Goods"
        }
    ],
    "sg:phone":"+1 607 773 8461",
    "sg:postcode":"13760",
    "sg:province":"NY",
    "sg:tags":[
        "supply",
        "component",
        "contract",
        "packaging",
        "equipment",
        "electronic"
    ],
    "sg:website":"www.vestalelectronics.com",
    "wof:name":"Vestal Electronic Devices LLC",
    "wof:placetype":"venue"
},
  "geometry": {"coordinates":[-76.07810600000001,42.094497],"type":"Point"}
}