{
  "type": "Feature",
  "properties": {
    "iso:country":"US",
    "sg:address":"1902 State Rte 14",
    "sg:city":"Geneva",
    "sg:classifiers":[
        {
            "category":"Wholesale",
            "subcategory":"Hardware",
            "type":"Manufacturing & Wholesale Goods"
        }
    ],
    "sg:phone":"+1 315 789 4944",
    "sg:postcode":"14456",
    "sg:province":"NY",
    "sg:tags":[
        "equipment",
        "heating",
        "system"
    ],
    "sg:website":"www.irrsupply.com",
    "wof:name":"Northrup Supply Corp",
    "wof:placetype":"venue"
},
  "geometry": {"coordinates":[-76.97797799999999,42.939745],"type":"Point"}
}