{
  "type": "Feature",
  "properties": {
    "addr:full":"2330 Bronx Park E Bronx NY 10467",
    "addr:housenumber":"2330",
    "addr:postcode":"10467",
    "addr:street":"Bronx Park E",
    "iso:country":"US",
    "sg:address":"2330 Bronx Park E",
    "sg:city":"Bronx",
    "sg:classifiers":[
        {
            "category":"Health Services",
            "subcategory":"Doctor",
            "type":"Services"
        }
    ],
    "sg:phone":"+1 718 655 6860",
    "sg:postcode":"10467",
    "sg:province":"NY",
    "wof:name":"Post Graduate Center For Mental Health",
    "wof:placetype":"venue"
},
  "geometry": {"coordinates":[-73.870509,40.86013],"type":"Point"}
}