{
  "type": "Feature",
  "properties": {
    "addr:full":"1300 Flatbush Ave Brooklyn NY 11210",
    "addr:housenumber":"1300",
    "addr:postcode":"11210",
    "addr:street":"Flatbush Ave",
    "iso:country":"US",
    "sg:address":"1300 Flatbush Ave",
    "sg:city":"Brooklyn",
    "sg:classifiers":[
        {
            "category":"Insurance",
            "subcategory":"Insurance Agent",
            "type":"Services"
        }
    ],
    "sg:phone":"+1 718 434 9737",
    "sg:postcode":"11210",
    "sg:province":"NY",
    "wof:name":"Trans One Express Inc",
    "wof:placetype":"venue"
},
  "geometry": {"coordinates":[-73.95278999999999,40.63765],"type":"Point"}
}