{
  "type": "Feature",
  "properties": {
    "addr:full":"400 E Fordham Road Bronx NY 10458",
    "addr:housenumber":"400",
    "addr:postcode":"10458",
    "addr:street":"E Fordham Road",
    "iso:country":"US",
    "sg:address":"400 E Fordham Road",
    "sg:city":"Bronx",
    "sg:classifiers":[
        {
            "category":"Shopping",
            "subcategory":"Optician",
            "type":"Retail Goods"
        }
    ],
    "sg:phone":"+1 718 295 1223",
    "sg:postcode":"10458",
    "sg:province":"NY",
    "sg:tags":[
        "eyewear"
    ],
    "wof:name":"Sears Optical",
    "wof:placetype":"venue"
},
  "geometry": {"coordinates":[-73.89139,40.861676],"type":"Point"}
}