{
  "type": "Feature",
  "properties": {
    "iso:country":"US",
    "sg:address":"4225 Austin Blvd",
    "sg:city":"Island Park",
    "sg:classifiers":[
        {
            "category":"Autos & Motor Vehicles",
            "subcategory":"Fuel & Gas Station",
            "type":"Retail Goods"
        }
    ],
    "sg:phone":"+1 516 432 9263",
    "sg:postcode":"11558",
    "sg:province":"NY",
    "wof:name":"Larry's Crown Svce Sta",
    "wof:placetype":"venue"
},
  "geometry": {"coordinates":[-73.653801,40.6007],"type":"Point"}
}