{
  "type": "Feature",
  "properties": {
    "addr:full":"3 Railroad Ave Wingdale NY 12594",
    "addr:housenumber":"3",
    "addr:postcode":"12594",
    "addr:street":"Railroad Ave",
    "iso:country":"US",
    "sg:address":"3 Railroad Ave",
    "sg:city":"Wingdale",
    "sg:classifiers":[
        {
            "category":"Bars & Pubs",
            "type":"Food & Drink"
        },
        {
            "category":"Restaurant",
            "type":"Food & Drink"
        }
    ],
    "sg:phone":"+1 845 832 9925",
    "sg:postcode":"12594",
    "sg:province":"NY",
    "sg:tags":[
        "tavern"
    ],
    "wof:name":"Jacye's Bar & Grill",
    "wof:placetype":"venue"
},
  "geometry": {"coordinates":[-73.567881,41.646678],"type":"Point"}
}