{
  "type": "Feature",
  "properties": {
    "addr:full":"1219 Gravesend Neck Rd Brooklyn NY 11229",
    "addr:housenumber":"1219",
    "addr:postcode":"11229",
    "addr:street":"Gravesend Neck Rd",
    "iso:country":"US",
    "sg:address":"1219 Gravesend Neck Rd",
    "sg:city":"Brooklyn",
    "sg:classifiers":[
        {
            "category":"Professional",
            "subcategory":"Printing & Photocopies",
            "type":"Services"
        }
    ],
    "sg:phone":"+1 718 627 1020",
    "sg:postcode":"11229",
    "sg:province":"NY",
    "wof:name":"Ink Shop the",
    "wof:placetype":"venue"
},
  "geometry": {"coordinates":[-73.957763,40.594558],"type":"Point"}
}