{
  "type": "Feature",
  "properties": {
    "addr:full":"22 Red Ground Rd Old Westbury NY 11568",
    "addr:housenumber":"22",
    "addr:postcode":"11568",
    "addr:street":"Red Ground Rd",
    "iso:country":"US",
    "sg:address":"22 Red Ground Rd",
    "sg:city":"Old Westbury",
    "sg:classifiers":[
        {
            "category":"Wholesale",
            "subcategory":"Drugs",
            "type":"Manufacturing & Wholesale Goods"
        }
    ],
    "sg:phone":"+1 516 626 0442",
    "sg:postcode":"11568",
    "sg:province":"NY",
    "sg:tags":[
        "aids",
        "discount",
        "health",
        "beauty",
        "general"
    ],
    "wof:name":"East Coast Corp",
    "wof:placetype":"venue"
},
  "geometry": {"coordinates":[-73.614805,40.789551],"type":"Point"}
}