{
  "type": "Feature",
  "properties": {
    "iso:country":"US",
    "sg:address":"364 N Broadway",
    "sg:city":"Sleepy Hollow",
    "sg:classifiers":[
        {
            "category":"Deli",
            "type":"Food & Drink"
        }
    ],
    "sg:phone":"+1 914 631 8686",
    "sg:postcode":"10591",
    "sg:province":"NY",
    "wof:name":"364 North Broadway Deli Corp",
    "wof:placetype":"venue"
},
  "geometry": {"coordinates":[-73.86129800000001,41.088001],"type":"Point"}
}