{
  "type": "Feature",
  "properties": {
    "addr:full":"305 E 161st St Bronx NY 10451",
    "addr:housenumber":"305",
    "addr:postcode":"10451",
    "addr:street":"E 161St St",
    "iso:country":"US",
    "sg:address":"305 E 161st St",
    "sg:city":"Bronx",
    "sg:classifiers":[
        {
            "category":"Shopping",
            "subcategory":"Pharmacy",
            "type":"Retail Goods"
        }
    ],
    "sg:phone":"+1 718 410 4711",
    "sg:postcode":"10451",
    "sg:province":"NY",
    "wof:name":"Ben Tal Chcc Pharmacy Svces",
    "wof:placetype":"venue"
},
  "geometry": {"coordinates":[-73.916393,40.824855],"type":"Point"}
}