{
  "type": "Feature",
  "properties": {
    "addr:full":"1385 Broadway New York NY 10018",
    "addr:housenumber":"1385",
    "addr:postcode":"10018",
    "addr:street":"Broadway",
    "iso:country":"US",
    "sg:address":"1385 Broadway",
    "sg:city":"New York",
    "sg:classifiers":[
        {
            "category":"Shopping",
            "subcategory":"Clothing, Apparel, & Fashions",
            "type":"Retail Goods"
        }
    ],
    "sg:phone":"+1 212 764 5769",
    "sg:postcode":"10018",
    "sg:province":"NY",
    "sg:tags":[
        "shop",
        "gown",
        "bridal"
    ],
    "wof:name":"Bridal Building",
    "wof:placetype":"venue"
},
  "geometry": {"coordinates":[-73.987475,40.752417],"type":"Point"}
}