{
  "type": "Feature",
  "properties": {
    "iso:country":"US",
    "sg:address":"147 Turner Ave",
    "sg:city":"Syracuse",
    "sg:classifiers":[
        {
            "category":"Restaurant",
            "type":"Food & Drink"
        },
        {
            "category":"Bars & Pubs",
            "type":"Food & Drink"
        }
    ],
    "sg:phone":"+1 315 478 9664",
    "sg:postcode":"13219",
    "sg:province":"NY",
    "sg:tags":[
        "drinking"
    ],
    "wof:name":"High Mark Quality Restaurant",
    "wof:placetype":"venue"
},
  "geometry": {"coordinates":[-76.249398,43.045393],"type":"Point"}
}