{
  "type": "Feature",
  "properties": {
    "iso:country":"US",
    "sg:address":"206 Broadway",
    "sg:city":"Amityville",
    "sg:classifiers":[
        {
            "category":"Shopping",
            "subcategory":"Gifts & Souvenirs",
            "type":"Retail Goods"
        }
    ],
    "sg:phone":"+1   ",
    "sg:postcode":"11701",
    "sg:province":"NY",
    "wof:name":"Wig Land",
    "wof:placetype":"venue"
},
  "geometry": {"coordinates":[-73.41746999999999,40.678273],"type":"Point"}
}