{
  "type": "Feature",
  "properties": {
    "iso:country":"US",
    "sg:address":"831 Maple Rd",
    "sg:city":"Buffalo",
    "sg:classifiers":[
        {
            "category":"Health Services",
            "subcategory":"Doctor",
            "type":"Services"
        }
    ],
    "sg:phone":"+1 716 775 1809",
    "sg:postcode":"14221",
    "sg:province":"NY",
    "sg:tags":[
        "physician",
        "surgeon",
        "medical"
    ],
    "wof:name":"Suburban Cardiology PC Fr",
    "wof:placetype":"venue"
},
  "geometry": {"coordinates":[-78.75626800000001,42.990946],"type":"Point"}
}