{
  "type": "Feature",
  "properties": {
    "iso:country":"US",
    "sg:address":"10 Leland Ln",
    "sg:city":"Southampton",
    "sg:classifiers":[
        {
            "category":"Communications",
            "subcategory":"News Services",
            "type":"Services"
        },
        {
            "category":"Real Estate",
            "subcategory":"Real Estate Agent",
            "type":"Services"
        }
    ],
    "sg:phone":"+1 631 283 2330",
    "sg:postcode":"11968",
    "sg:province":"NY",
    "wof:name":"Canterbury Mews",
    "wof:placetype":"venue"
},
  "geometry": {"coordinates":[-72.37988199999999,40.892024],"type":"Point"}
}