{
  "type": "Feature",
  "properties": {
    "iso:country":"US",
    "sg:address":"11819 E Corning Rd",
    "sg:city":"Corning",
    "sg:classifiers":[
        {
            "category":"Manufacturing",
            "subcategory":"Glass & Minerals",
            "type":"Manufacturing & Wholesale Goods"
        }
    ],
    "sg:phone":"+1   ",
    "sg:postcode":"14830",
    "sg:province":"NY",
    "sg:tags":[
        "ready",
        "mix",
        "mfr",
        "concrete"
    ],
    "wof:name":"Corning Concrete Co",
    "wof:placetype":"venue"
},
  "geometry": {"coordinates":[-76.99638899999999,42.122372],"type":"Point"}
}