{
  "type": "Feature",
  "properties": {
    "addr:full":"6001 Strickland Ave Brooklyn NY 11234",
    "addr:housenumber":"6001",
    "addr:postcode":"11234",
    "addr:street":"Strickland Ave",
    "iso:country":"US",
    "sg:address":"6001 Strickland Ave",
    "sg:city":"Brooklyn",
    "sg:classifiers":[
        {
            "category":"Food & Beverages",
            "subcategory":"Bakery",
            "type":"Retail Goods"
        },
        {
            "category":"Wholesale",
            "subcategory":"Groceries",
            "type":"Manufacturing & Wholesale Goods"
        }
    ],
    "sg:phone":"+1 347 462 1588",
    "sg:postcode":"11234",
    "sg:province":"NY",
    "sg:tags":[
        "cooky",
        "crackers-wholesale",
        "bakers-wholesale",
        "manufacturer"
    ],
    "wof:name":"Cocos Custom Cookie",
    "wof:placetype":"venue"
},
  "geometry": {"coordinates":[-73.91378,40.6096],"type":"Point"}
}