{
  "type": "Feature",
  "properties": {
    "addr:full":"189 Columbus Ave New York NY 10023",
    "addr:housenumber":"189",
    "addr:postcode":"10023",
    "addr:street":"Columbus Ave",
    "iso:country":"US",
    "sg:address":"189 Columbus Ave",
    "sg:city":"New York",
    "sg:classifiers":[
        {
            "category":"Restaurant",
            "type":"Food & Drink"
        }
    ],
    "sg:phone":"+1 212 595 2570",
    "sg:postcode":"10023",
    "sg:province":"NY",
    "sg:tags":[
        "mediterranean",
        "french"
    ],
    "wof:name":"Caf? Saint Honore",
    "wof:placetype":"venue"
},
  "geometry": {"coordinates":[-73.98023999999999,40.775069],"type":"Point"}
}