{
  "type": "Feature",
  "properties": {
    "addr:full":"555 Clayton St Central Islip NY 11722",
    "addr:housenumber":"555",
    "addr:postcode":"11722",
    "addr:street":"Clayton St",
    "iso:country":"US",
    "sg:address":"555 Clayton St",
    "sg:city":"Central Islip",
    "sg:classifiers":[
        {
            "category":"Recreation",
            "type":"Entertainment"
        }
    ],
    "sg:phone":"+1 631 436 6050",
    "sg:postcode":"11722",
    "sg:province":"NY",
    "sg:tags":[
        "center"
    ],
    "wof:name":"Central Islip Recreation Ctr",
    "wof:placetype":"venue"
},
  "geometry": {"coordinates":[-73.197164,40.786381],"type":"Point"}
}