{
  "type": "Feature",
  "properties": {
    "iso:country":"US",
    "sg:address":"888 Middle Country Rd",
    "sg:city":"Middle Island",
    "sg:classifiers":[
        {
            "category":"Restaurant",
            "type":"Food & Drink"
        }
    ],
    "sg:phone":"+1 631 924 8188",
    "sg:postcode":"11953",
    "sg:province":"NY",
    "wof:name":"Uncle Rays Kitchen",
    "wof:placetype":"venue"
},
  "geometry": {"coordinates":[-72.940015,40.883544],"type":"Point"}
}