{
  "type": "Feature",
  "properties": {
    "addr:full":"100 W 77th St New York NY 10024",
    "addr:housenumber":"100",
    "addr:postcode":"10024",
    "addr:street":"W 77Th St",
    "iso:country":"US",
    "sg:address":"100 W 77th St",
    "sg:city":"New York",
    "sg:classifiers":[
        {
            "category":"Education",
            "subcategory":"School",
            "type":"Public Place"
        }
    ],
    "sg:phone":"+1 212 362 1674",
    "sg:postcode":"10024",
    "sg:province":"NY",
    "wof:name":"West Prep Academy",
    "wof:placetype":"venue"
},
  "geometry": {"coordinates":[-73.976499,40.780513],"type":"Point"}
}