{
  "type": "Feature",
  "properties": {
    "iso:country":"US",
    "sg:address":"13 E Genesee St",
    "sg:city":"Baldwinsville",
    "sg:classifiers":[
        {
            "category":"Food & Beverages",
            "subcategory":"Liquor & Beverages",
            "type":"Retail Goods"
        }
    ],
    "sg:phone":"+1   ",
    "sg:postcode":"13027",
    "sg:province":"NY",
    "sg:tags":[
        "alcoholic"
    ],
    "wof:name":"Baldwinsville Liquor Store",
    "wof:placetype":"venue"
},
  "geometry": {"coordinates":[-76.33133100000001,43.158834],"type":"Point"}
}