{
  "type": "Feature",
  "properties": {
    "iso:country":"US",
    "sg:address":"1079 Duston Rd",
    "sg:city":"Valley Stream",
    "sg:classifiers":[
        {
            "category":"Education",
            "subcategory":"Vocational School",
            "type":"Public Place"
        }
    ],
    "sg:phone":"+1 516 569 2275",
    "sg:postcode":"11581",
    "sg:province":"NY",
    "sg:tags":[
        "processing",
        "datum"
    ],
    "wof:name":"Mdi Development Inc",
    "wof:placetype":"venue"
},
  "geometry": {"coordinates":[-73.717843,40.647073],"type":"Point"}
}