{
  "type": "Feature",
  "properties": {
    "addr:full":"53 72nd Ave Forest Hills NY 11375",
    "addr:housenumber":"53",
    "addr:postcode":"11375",
    "addr:street":"72Nd Ave",
    "iso:country":"US",
    "sg:address":"53 72nd Ave",
    "sg:city":"Forest Hills",
    "sg:classifiers":[
        {
            "category":"Professional",
            "subcategory":"Management & Consulting",
            "type":"Services"
        }
    ],
    "sg:phone":"+1 718 446 8199",
    "sg:postcode":"11375",
    "sg:province":"NY",
    "wof:name":"Hancock Consulting",
    "wof:placetype":"venue"
},
  "geometry": {"coordinates":[-73.843563,40.717752],"type":"Point"}
}