{
  "type": "Feature",
  "properties": {
    "iso:country":"US",
    "sg:address":"95 W Main St",
    "sg:city":"Allegany",
    "sg:classifiers":[
        {
            "category":"Personal",
            "subcategory":"Beauty Salon",
            "type":"Services"
        }
    ],
    "sg:phone":"+1 716 373 0947",
    "sg:postcode":"14706",
    "sg:province":"NY",
    "sg:tags":[
        "shop"
    ],
    "wof:name":"Hair It Is",
    "wof:placetype":"venue"
},
  "geometry": {"coordinates":[-78.497865,42.092617],"type":"Point"}
}