{
  "type": "Feature",
  "properties": {
    "iso:country":"US",
    "sg:address":"580 E Main St",
    "sg:city":"Middletown",
    "sg:classifiers":[
        {
            "category":"Personal",
            "subcategory":"Beauty Salon",
            "type":"Services"
        }
    ],
    "sg:phone":"+1   ",
    "sg:postcode":"10940",
    "sg:province":"NY",
    "sg:tags":[
        "shop"
    ],
    "wof:name":"Hello Gorgeous Salon Inc",
    "wof:placetype":"venue"
},
  "geometry": {"coordinates":[-74.378652,41.443271],"type":"Point"}
}