{
  "type": "Feature",
  "properties": {
    "iso:country":"US",
    "sg:address":"258 S Main St",
    "sg:city":"New City",
    "sg:classifiers":[
        {
            "category":"Restaurant",
            "type":"Food & Drink"
        }
    ],
    "sg:phone":"+1 845 638 9303",
    "sg:postcode":"10956",
    "sg:province":"NY",
    "sg:website":"www.bennigans.com",
    "wof:name":"Bennigan's Grill & Tavern",
    "wof:placetype":"venue"
},
  "geometry": {"coordinates":[-73.990306,41.142085],"type":"Point"}
}