{
  "type": "Feature",
  "properties": {
    "addr:full":"380 Cozine Ave Apt 5C Brooklyn NY 11207",
    "addr:housenumber":"380;5c",
    "addr:postcode":"11207",
    "addr:street":"Cozine Ave Apt",
    "iso:country":"US",
    "sg:address":"380 Cozine Ave Apt 5C",
    "sg:city":"Brooklyn",
    "sg:classifiers":[
        {
            "category":"Wholesale",
            "subcategory":"Home Furnishings",
            "type":"Manufacturing & Wholesale Goods"
        }
    ],
    "sg:phone":"+1 347 210 5576",
    "sg:postcode":"11207",
    "sg:province":"NY",
    "sg:tags":[
        "manufacturer",
        "baskets-wholesale"
    ],
    "wof:name":"Taking Basket",
    "wof:placetype":"venue"
},
  "geometry": {"coordinates":[-73.878433,40.657965],"type":"Point"}
}