{
  "type": "Feature",
  "properties": {
    "iso:country":"US",
    "sg:address":"950 Danby Rd",
    "sg:city":"Ithaca",
    "sg:classifiers":[
        {
            "category":"Manufacturing",
            "subcategory":"Printing",
            "type":"Manufacturing & Wholesale Goods"
        }
    ],
    "sg:phone":"+1   ",
    "sg:postcode":"14850",
    "sg:province":"NY",
    "sg:tags":[
        "lithographic",
        "computer",
        "commercial",
        "mfg"
    ],
    "wof:name":"NCR",
    "wof:placetype":"venue"
},
  "geometry": {"coordinates":[-76.501015,42.421825],"type":"Point"}
}