{
  "type": "Feature",
  "properties": {
    "addr:full":"300 Merrick Rd Ste 210 Lynbrook NY 11563",
    "addr:housenumber":"300",
    "addr:postcode":"11563",
    "addr:street":"Merrick Rd Ste 210",
    "iso:country":"US",
    "sg:address":"300 Merrick Rd Ste 210",
    "sg:city":"Lynbrook",
    "sg:classifiers":[
        {
            "category":"Professional",
            "subcategory":"Lawyer & Legal Services",
            "type":"Services"
        }
    ],
    "sg:phone":"+1 516 599 6700",
    "sg:postcode":"11563",
    "sg:province":"NY",
    "sg:tags":[
        "plan"
    ],
    "wof:name":"Cooper, Jerome",
    "wof:placetype":"venue"
},
  "geometry": {"coordinates":[-73.671082,40.657084],"type":"Point"}
}