{
  "type": "Feature",
  "properties": {
    "iso:country":"US",
    "sg:address":"184 Ovid St",
    "sg:city":"Seneca Falls",
    "sg:classifiers":[
        {
            "category":"Building & Trades",
            "subcategory":"Construction",
            "type":"Services"
        }
    ],
    "sg:phone":"+1 315 568 5640",
    "sg:postcode":"13148",
    "sg:province":"NY",
    "sg:tags":[
        "specializing",
        "pipeline",
        "contractor",
        "sewer",
        "paving",
        "general"
    ],
    "wof:name":"Seneca Pipe & Paving Inc",
    "wof:placetype":"venue"
},
  "geometry": {"coordinates":[-76.79870200000001,42.896572],"type":"Point"}
}