{
  "type": "Feature",
  "properties": {
    "iso:country":"US",
    "sg:address":"21 Roxbury Rd",
    "sg:city":"Garden City",
    "sg:classifiers":[
        {
            "category":"Professional",
            "subcategory":"Accounting & Tax Preparation",
            "type":"Services"
        }
    ],
    "sg:phone":"+1 516 739 7102",
    "sg:postcode":"11530",
    "sg:province":"NY",
    "sg:tags":[
        "accountant"
    ],
    "wof:name":"Baldessari Kevin P Accountants",
    "wof:placetype":"venue"
},
  "geometry": {"coordinates":[-73.663803,40.718899],"type":"Point"}
}