{
  "type": "Feature",
  "properties": {
    "iso:country":"US",
    "sg:address":"350 Old Country Rd Ste 105",
    "sg:city":"Garden City",
    "sg:classifiers":[
        {
            "category":"Professional",
            "subcategory":"Lawyer & Legal Services",
            "type":"Services"
        }
    ],
    "sg:phone":"+1 516 248 6090",
    "sg:postcode":"11530",
    "sg:province":"NY",
    "wof:name":"Zimler Michael Atty",
    "wof:placetype":"venue"
},
  "geometry": {"coordinates":[-73.635201,40.7397],"type":"Point"}
}