{
  "type": "Feature",
  "properties": {
    "iso:country":"US",
    "sg:address":"1450 E Gun Hill Rd",
    "sg:city":"Bronx",
    "sg:classifiers":[
        {
            "category":"Retail",
            "subcategory":"Repair Shop",
            "type":"Services"
        }
    ],
    "sg:phone":"+1 718 304 8073",
    "sg:postcode":"10469",
    "sg:province":"NY",
    "sg:tags":[
        "lock",
        "locksmith"
    ],
    "wof:name":"A 1 Locksmith",
    "wof:placetype":"venue"
},
  "geometry": {"coordinates":[-73.843586,40.869088],"type":"Point"}
}