{
  "type": "Feature",
  "properties": {
    "addr:full":"221 McKibben St Brooklyn NY 11206",
    "addr:housenumber":"221",
    "addr:postcode":"11206",
    "addr:street":"Mckibben St",
    "iso:country":"US",
    "sg:address":"221 McKibben St",
    "sg:city":"Brooklyn",
    "sg:classifiers":[
        {
            "category":"Manufacturing",
            "subcategory":"Furniture",
            "type":"Manufacturing & Wholesale Goods"
        }
    ],
    "sg:phone":"+1 718 386 0048",
    "sg:postcode":"11206",
    "sg:province":"NY",
    "wof:name":"Casa Stradivari Inc",
    "wof:placetype":"venue"
},
  "geometry": {"coordinates":[-73.938664,40.705444],"type":"Point"}
}