{
  "type": "Feature",
  "properties": {
    "addr:full":"67 Spring Rd Poughkeepsie NY 12601",
    "addr:housenumber":"67",
    "addr:postcode":"12601",
    "addr:street":"Spring Rd",
    "iso:country":"US",
    "sg:address":"67 Spring Rd",
    "sg:city":"Poughkeepsie",
    "sg:classifiers":[
        {
            "category":"Retail",
            "subcategory":"Laundry & Dry Cleaning",
            "type":"Services"
        },
        {
            "category":"Building & Trades",
            "subcategory":"Cleaning & Sanitation",
            "type":"Services"
        }
    ],
    "sg:phone":"+1 845 297 1131",
    "sg:postcode":"12601",
    "sg:province":"NY",
    "sg:tags":[
        "cleaner",
        "house"
    ],
    "wof:name":"James V Brady Cleaning",
    "wof:placetype":"venue"
},
  "geometry": {"coordinates":[-73.906138,41.625857],"type":"Point"}
}