{
  "type": "Feature",
  "properties": {
    "addr:full":"290 Linden Oaks Rochester NY 14625",
    "addr:housenumber":"290",
    "addr:postcode":"14625",
    "addr:street":"Linden Oaks",
    "iso:country":"US",
    "sg:address":"290 Linden Oaks",
    "sg:city":"Rochester",
    "sg:classifiers":[
        {
            "category":"Professional",
            "subcategory":"Lawyer & Legal Services",
            "type":"Services"
        }
    ],
    "sg:phone":"+1 585 248 3800",
    "sg:postcode":"14625",
    "sg:province":"NY",
    "sg:tags":[
        "attorney",
        "trust",
        "estate",
        "wills",
        "drug",
        "elder",
        "charge",
        "planning",
        "criminal",
        "law"
    ],
    "sg:website":"http://www.weinsteinmurphy.com",
    "wof:name":"Weinstein Murphy",
    "wof:placetype":"venue"
},
  "geometry": {"coordinates":[-77.513586,43.121774],"type":"Point"}
}