{
  "type": "Feature",
  "properties": {
    "iso:country":"US",
    "sg:address":"25 Maryland Ave",
    "sg:city":"Freeport",
    "sg:classifiers":[
        {
            "category":"Professional",
            "subcategory":"Management & Consulting",
            "type":"Services"
        }
    ],
    "sg:phone":"+1 732 921 5867",
    "sg:postcode":"11520",
    "sg:province":"NY",
    "sg:tags":[
        "information",
        "technology"
    ],
    "wof:name":"Delan Associates Inc",
    "wof:placetype":"venue"
},
  "geometry": {"coordinates":[-73.597882,40.661827],"type":"Point"}
}