{
  "type": "Feature",
  "properties": {
    "addr:full":"52 Wheaton Rd Erin NY 14838",
    "addr:housenumber":"52",
    "addr:postcode":"14838",
    "addr:street":"Wheaton Rd",
    "iso:country":"US",
    "sg:address":"52 Wheaton Rd",
    "sg:city":"Erin",
    "sg:classifiers":[
        {
            "category":"Manufacturing",
            "subcategory":"Lumber",
            "type":"Manufacturing & Wholesale Goods"
        }
    ],
    "sg:phone":"+1   ",
    "sg:postcode":"14838",
    "sg:province":"NY",
    "sg:tags":[
        "logging"
    ],
    "wof:name":"Meade Logging",
    "wof:placetype":"venue"
},
  "geometry": {"coordinates":[-76.67321099999999,42.178872],"type":"Point"}
}