{
  "type": "Feature",
  "properties": {
    "addr:full":"239 Linden Ave Red Hook NY 12571",
    "addr:housenumber":"239",
    "addr:postcode":"12571",
    "addr:street":"Linden Ave",
    "iso:country":"US",
    "sg:address":"239 Linden Ave",
    "sg:city":"Red Hook",
    "sg:classifiers":[
        {
            "category":"Manufacturing",
            "subcategory":"Food",
            "type":"Manufacturing & Wholesale Goods"
        }
    ],
    "sg:phone":"+1 845 758 9500",
    "sg:postcode":"12571",
    "sg:province":"NY",
    "sg:tags":[
        "cocoa",
        "chocolate"
    ],
    "wof:name":"Taste Budd's Chocolate Dreams",
    "wof:placetype":"venue"
},
  "geometry": {"coordinates":[-73.879023,42.012245],"type":"Point"}
}