{
  "type": "Feature",
  "properties": {
    "iso:country":"US",
    "sg:address":"4523 Avenue N",
    "sg:city":"Brooklyn",
    "sg:classifiers":[
        {
            "category":"Restaurant",
            "type":"Food & Drink"
        }
    ],
    "sg:phone":"+1 718 692 1020",
    "sg:postcode":"11234",
    "sg:province":"NY",
    "wof:name":"Yen Yen Restaurant",
    "wof:placetype":"venue"
},
  "geometry": {"coordinates":[-73.930924,40.618772],"type":"Point"}
}