{
  "type": "Feature",
  "properties": {
    "iso:country":"US",
    "sg:address":"7201 8th Ave",
    "sg:city":"Brooklyn",
    "sg:classifiers":[
        {
            "category":"Real Estate",
            "subcategory":"Real Estate Agent",
            "type":"Services"
        }
    ],
    "sg:phone":"+1 718 745 4298",
    "sg:postcode":"11228",
    "sg:province":"NY",
    "wof:name":"Colandrea Properties",
    "wof:placetype":"venue"
},
  "geometry": {"coordinates":[-74.017223,40.628101],"type":"Point"}
}