{
  "type": "Feature",
  "properties": {
    "iso:country":"US",
    "sg:address":"5951 Co Rd 37",
    "sg:city":"Springwater",
    "sg:classifiers":[
        {
            "category":"Freight",
            "type":"Transportation"
        }
    ],
    "sg:phone":"+1   ",
    "sg:postcode":"14560",
    "sg:province":"NY",
    "sg:tags":[
        "operator",
        "trucking"
    ],
    "wof:name":"Jeffrey S Simons",
    "wof:placetype":"venue"
},
  "geometry": {"coordinates":[-77.542539,42.737093],"type":"Point"}
}