{
  "type": "Feature",
  "properties": {
    "iso:country":"US",
    "sg:address":"42 Main St",
    "sg:city":"Bedford Hills",
    "sg:classifiers":[
        {
            "category":"Professional",
            "subcategory":"Management & Consulting",
            "type":"Services"
        }
    ],
    "sg:phone":"+1 914 666 2020",
    "sg:postcode":"10507",
    "sg:province":"NY",
    "sg:tags":[
        "fuel"
    ],
    "sg:website":"www.bscmi.com",
    "wof:name":"Bourne Stenstrom Capital Mgmt",
    "wof:placetype":"venue"
},
  "geometry": {"coordinates":[-73.700456,41.235947],"type":"Point"}
}