{
  "type": "Feature",
  "properties": {
    "addr:full":"82 Lee Ave Brooklyn NY 11211",
    "addr:housenumber":"82",
    "addr:postcode":"11211",
    "addr:street":"Lee Ave",
    "iso:country":"US",
    "sg:address":"82 Lee Ave",
    "sg:city":"Brooklyn",
    "sg:classifiers":[
        {
            "category":"Food & Beverages",
            "subcategory":"Meat & Fish",
            "type":"Retail Goods"
        }
    ],
    "sg:phone":"+1 718 963 1100",
    "sg:postcode":"11211",
    "sg:province":"NY",
    "sg:tags":[
        "shop"
    ],
    "wof:name":"Satmar Butcher & Meat Mkt",
    "wof:placetype":"venue"
},
  "geometry": {"coordinates":[-73.959503,40.7052],"type":"Point"}
}