{
  "type": "Feature",
  "properties": {
    "iso:country":"US",
    "sg:address":"103 Reservoir Ave",
    "sg:city":"Rochester",
    "sg:classifiers":[
        {
            "category":"Personal",
            "type":"Services"
        }
    ],
    "sg:phone":"+1 585 747 9260",
    "sg:postcode":"14620",
    "sg:province":"NY",
    "sg:tags":[
        "control",
        "weight"
    ],
    "wof:name":"Supergirl Fitness",
    "wof:placetype":"venue"
},
  "geometry": {"coordinates":[-77.610198,43.131715],"type":"Point"}
}