{
  "type": "Feature",
  "properties": {
    "iso:country":"US",
    "sg:address":"85 Watervliet Ave",
    "sg:city":"Albany",
    "sg:classifiers":[
        {
            "category":"Health Services",
            "subcategory":"Clinic",
            "type":"Services"
        }
    ],
    "sg:phone":"+1   ",
    "sg:postcode":"12206",
    "sg:province":"NY",
    "wof:name":"Cares",
    "wof:placetype":"venue"
},
  "geometry": {"coordinates":[-73.78079700000001,42.67876],"type":"Point"}
}