{
  "type": "Feature",
  "properties": {
    "addr:full":"28 Wooster St New York NY 10013",
    "addr:housenumber":"28",
    "addr:postcode":"10013",
    "addr:street":"Wooster St",
    "iso:country":"US",
    "sg:address":"28 Wooster St",
    "sg:city":"New York",
    "sg:classifiers":[
        {
            "category":"Recreation",
            "type":"Entertainment"
        }
    ],
    "sg:phone":"+1 212 625 9224",
    "sg:postcode":"10013",
    "sg:province":"NY",
    "sg:tags":[
        "amusement"
    ],
    "wof:name":"Guild & Greyshkul",
    "wof:placetype":"venue"
},
  "geometry": {"coordinates":[-74.00358199999999,40.720894],"type":"Point"}
}