{
  "type": "Feature",
  "properties": {
    "iso:country":"US",
    "sg:address":"203 E Park Ave",
    "sg:city":"Long Beach",
    "sg:classifiers":[
        {
            "category":"Autos & Motor Vehicles",
            "subcategory":"Auto Supplies",
            "type":"Retail Goods"
        },
        {
            "category":"Retail",
            "subcategory":"Auto Repair",
            "type":"Services"
        }
    ],
    "sg:phone":"+1 516 889 9740",
    "sg:postcode":"11561",
    "sg:province":"NY",
    "sg:tags":[
        "tire"
    ],
    "sg:website":"www.mobil.com",
    "wof:name":"MOBIL LONG BEACH AUTOMOTIVE & TIRE SPECIALIST",
    "wof:placetype":"venue"
},
  "geometry": {"coordinates":[-73.65810999999999,40.588837],"type":"Point"}
}