{
  "type": "Feature",
  "properties": {
    "addr:full":"269 Robbins Ln Syosset NY 11791",
    "addr:housenumber":"269",
    "addr:postcode":"11791",
    "addr:street":"Robbins Ln",
    "iso:country":"US",
    "sg:address":"269 Robbins Ln",
    "sg:city":"Syosset",
    "sg:classifiers":[
        {
            "category":"Wholesale",
            "subcategory":"Electrical",
            "type":"Manufacturing & Wholesale Goods"
        }
    ],
    "sg:phone":"+1 516 931 5199",
    "sg:postcode":"11791",
    "sg:province":"NY",
    "sg:tags":[
        "electronic",
        "representative"
    ],
    "wof:name":"Continental Electric Sales",
    "wof:placetype":"venue"
},
  "geometry": {"coordinates":[-73.51528399999999,40.797662],"type":"Point"}
}