{
  "type": "Feature",
  "properties": {
    "iso:country":"US",
    "sg:address":"949 E Tremont Ave",
    "sg:city":"Bronx",
    "sg:classifiers":[
        {
            "category":"Health Services",
            "subcategory":"Podiatrist",
            "type":"Services"
        }
    ],
    "sg:phone":"+1   ",
    "sg:postcode":"10460",
    "sg:province":"NY",
    "wof:name":"Jaron Corp",
    "wof:placetype":"venue"
},
  "geometry": {"coordinates":[-73.883354,40.841754],"type":"Point"}
}