{
  "type": "Feature",
  "properties": {
    "iso:country":"US",
    "sg:address":"80 1st Avenue",
    "sg:city":"New York",
    "sg:classifiers":[
        {
            "category":"Retail",
            "subcategory":"Portrait Studio",
            "type":"Services"
        },
        {
            "category":"Professional",
            "subcategory":"Art Services",
            "type":"Services"
        }
    ],
    "sg:phone":"+1 212 647 9400",
    "sg:postcode":"10009",
    "sg:province":"NY",
    "sg:tags":[
        "photographer",
        "photography",
        "store"
    ],
    "wof:name":"David S Waitz Photography",
    "wof:placetype":"venue"
},
  "geometry": {"coordinates":[-73.986684,40.725683],"type":"Point"}
}