{
  "type": "Feature",
  "properties": {
    "iso:country":"US",
    "sg:address":"1883 Front St",
    "sg:city":"East Meadow",
    "sg:classifiers":[
        {
            "category":"Autos & Motor Vehicles",
            "subcategory":"Fuel & Gas Station",
            "type":"Retail Goods"
        }
    ],
    "sg:phone":"+1 516 542 0820",
    "sg:postcode":"11554",
    "sg:province":"NY",
    "wof:name":"Front Street Automobile Svc Cntr",
    "wof:placetype":"venue"
},
  "geometry": {"coordinates":[-73.56440000000001,40.719898],"type":"Point"}
}