{
  "type": "Feature",
  "properties": {
    "iso:country":"US",
    "sg:address":"4 E Church St",
    "sg:city":"Adams",
    "sg:classifiers":[
        {
            "category":"Personal",
            "subcategory":"Beauty Salon",
            "type":"Services"
        }
    ],
    "sg:phone":"+1 315 232 2540",
    "sg:postcode":"13605",
    "sg:province":"NY",
    "sg:tags":[
        "shop",
        "tanning"
    ],
    "wof:name":"Shear Delite Salon",
    "wof:placetype":"venue"
},
  "geometry": {"coordinates":[-76.023651,43.809265],"type":"Point"}
}