{
  "type": "Feature",
  "properties": {
    "addr:full":"103 Dryden Rd Ithaca NY 14850",
    "addr:housenumber":"103",
    "addr:postcode":"14850",
    "addr:street":"Dryden Rd",
    "iso:country":"US",
    "sg:address":"103 Dryden Rd",
    "sg:city":"Ithaca",
    "sg:classifiers":[
        {
            "category":"Cinema",
            "subcategory":"Movie Rental",
            "type":"Entertainment"
        }
    ],
    "sg:phone":"+1 607 272 3502",
    "sg:postcode":"14850",
    "sg:province":"NY",
    "sg:tags":[
        "leasing",
        "video",
        "disc",
        "tape"
    ],
    "sg:website":"www.collegetownvideo.com",
    "wof:name":"Collegetown Video Inc",
    "wof:placetype":"venue"
},
  "geometry": {"coordinates":[-76.48741200000001,42.442065],"type":"Point"}
}