{
  "type": "Feature",
  "properties": {
    "addr:full":"38 Yale Ave Ossining NY 10562",
    "addr:housenumber":"38",
    "addr:postcode":"10562",
    "addr:street":"Yale Ave",
    "iso:country":"US",
    "sg:address":"38 Yale Ave",
    "sg:city":"Ossining",
    "sg:classifiers":[
        {
            "category":"Real Estate",
            "subcategory":"Real Estate Agent",
            "type":"Services"
        }
    ],
    "sg:phone":"+1 914 941 0091",
    "sg:postcode":"10562",
    "sg:province":"NY",
    "sg:tags":[
        "agency",
        "rental"
    ],
    "wof:name":"JGAS Rentals Inc",
    "wof:placetype":"venue"
},
  "geometry": {"coordinates":[-73.860703,41.165312],"type":"Point"}
}