{
  "type": "Feature",
  "properties": {
    "addr:full":"2768 Niagara Falls Blvd Niagara Falls NY 14304",
    "addr:housenumber":"2768",
    "addr:postcode":"14304",
    "addr:street":"Niagara Falls Blvd",
    "iso:country":"US",
    "sg:address":"2768 Niagara Falls Blvd",
    "sg:city":"Niagara Falls",
    "sg:classifiers":[
        {
            "category":"Insurance",
            "subcategory":"Insurance Agent",
            "type":"Services"
        }
    ],
    "sg:phone":"+1 716 694 3404",
    "sg:postcode":"14304",
    "sg:province":"NY",
    "wof:name":"State Farm Insurance",
    "wof:placetype":"venue"
},
  "geometry": {"coordinates":[-78.898698,43.090762],"type":"Point"}
}