{
  "type": "Feature",
  "properties": {
    "iso:country":"US",
    "sg:address":"63 Conyingham Ave",
    "sg:city":"Staten Island",
    "sg:classifiers":[
        {
            "category":"Professional",
            "subcategory":"Art Services",
            "type":"Services"
        }
    ],
    "sg:phone":"+1 718 390 0855",
    "sg:postcode":"10301",
    "sg:province":"NY",
    "sg:tags":[
        "photographer"
    ],
    "wof:name":"Gerard Franciosa Photography",
    "wof:placetype":"venue"
},
  "geometry": {"coordinates":[-74.10270300000001,40.63598],"type":"Point"}
}