{
  "type": "Feature",
  "properties": {
    "addr:full":"3682 Seneca Tpke Canastota NY 13032",
    "addr:housenumber":"3682",
    "addr:postcode":"13032",
    "addr:street":"Seneca Tpke",
    "iso:country":"US",
    "sg:address":"3682 Seneca Tpke",
    "sg:city":"Canastota",
    "sg:classifiers":[
        {
            "category":"Autos & Motor Vehicles",
            "subcategory":"Automobile Sales",
            "type":"Retail Goods"
        }
    ],
    "sg:phone":"+1 315 697 3516",
    "sg:postcode":"13032",
    "sg:province":"NY",
    "sg:tags":[
        "car",
        "dealer"
    ],
    "wof:name":"Sal's Auto Ctr",
    "wof:placetype":"venue"
},
  "geometry": {"coordinates":[-75.740163,43.071176],"type":"Point"}
}