{
  "type": "Feature",
  "properties": {
    "addr:full":"372 S Plank Rd Newburgh NY 12550",
    "addr:housenumber":"372",
    "addr:postcode":"12550",
    "addr:street":"S Plank Rd",
    "iso:country":"US",
    "sg:address":"372 S Plank Rd",
    "sg:city":"Newburgh",
    "sg:classifiers":[
        {
            "category":"Insurance",
            "subcategory":"Hazard Insurance",
            "type":"Services"
        }
    ],
    "sg:phone":"+1 845 566 3469",
    "sg:postcode":"12550",
    "sg:province":"NY",
    "sg:tags":[
        "commercial",
        "business"
    ],
    "wof:name":"Benefit Mall",
    "wof:placetype":"venue"
},
  "geometry": {"coordinates":[-74.08869900000001,41.53521],"type":"Point"}
}