{
  "type": "Feature",
  "properties": {
    "iso:country":"US",
    "sg:address":"412 52nd St",
    "sg:city":"Brooklyn",
    "sg:classifiers":[
        {
            "category":"Personal",
            "subcategory":"Beauty Salon",
            "type":"Services"
        }
    ],
    "sg:phone":"+1 718 567 8550",
    "sg:postcode":"11220",
    "sg:province":"NY",
    "wof:name":"Giselle Beauty Salon",
    "wof:placetype":"venue"
},
  "geometry": {"coordinates":[-74.01174,40.644094],"type":"Point"}
}