{
  "type": "Feature",
  "properties": {
    "addr:full":"490 Persse Rd Fonda NY 12068",
    "addr:housenumber":"490",
    "addr:postcode":"12068",
    "addr:street":"Persse Rd",
    "iso:country":"US",
    "sg:address":"490 Persse Rd",
    "sg:city":"Fonda",
    "sg:classifiers":[
        {
            "category":"Farming",
            "subcategory":"Farm",
            "type":"Manufacturing & Wholesale Goods"
        }
    ],
    "sg:phone":"+1 518 853 4022",
    "sg:postcode":"12068",
    "sg:province":"NY",
    "wof:name":"Adirondack Maple Farms",
    "wof:placetype":"venue"
},
  "geometry": {"coordinates":[-74.432919,42.972651],"type":"Point"}
}