{
  "type": "Feature",
  "properties": {
    "addr:full":"7432 County House Rd Auburn NY 13021",
    "addr:housenumber":"7432",
    "addr:postcode":"13021",
    "addr:street":"County House Rd",
    "iso:country":"US",
    "sg:address":"7432 County House Rd",
    "sg:city":"Auburn",
    "sg:classifiers":[
        {
            "category":"Social Services",
            "subcategory":"Adult Care",
            "type":"Services"
        }
    ],
    "sg:phone":"+1 315 258 2100",
    "sg:postcode":"13021",
    "sg:province":"NY",
    "sg:tags":[
        "residential",
        "facility",
        "treatment",
        "emotionally",
        "for"
    ],
    "wof:name":"Childrens Center",
    "wof:placetype":"venue"
},
  "geometry": {"coordinates":[-76.539153,42.980993],"type":"Point"}
}