{
  "type": "Feature",
  "properties": {
    "iso:country":"US",
    "sg:address":"239 Beach 116 St",
    "sg:city":"Rockaway",
    "sg:classifiers":[
        {
            "category":"Restaurant",
            "type":"Food & Drink"
        }
    ],
    "sg:phone":"+1 718 608 6424",
    "sg:postcode":"11694",
    "sg:province":"NY",
    "sg:tags":[
        "polish"
    ],
    "wof:name":"Lublin Deli",
    "wof:placetype":"venue"
},
  "geometry": {"coordinates":[-73.837451,40.58009],"type":"Point"}
}