{
  "type": "Feature",
  "properties": {
    "addr:full":"67 Schlenker Ave Cheektowaga NY 14225",
    "addr:housenumber":"67",
    "addr:postcode":"14225",
    "addr:street":"Schlenker Ave",
    "iso:country":"US",
    "sg:address":"67 Schlenker Ave",
    "sg:city":"Cheektowaga",
    "sg:classifiers":[
        {
            "category":"Building & Trades",
            "subcategory":"Construction",
            "type":"Services"
        }
    ],
    "sg:phone":"+1 716 685 4353",
    "sg:postcode":"14225",
    "sg:province":"NY",
    "sg:tags":[
        "painter"
    ],
    "wof:name":"Esscorp Painting & Wallcover",
    "wof:placetype":"venue"
},
  "geometry": {"coordinates":[-78.752978,42.905489],"type":"Point"}
}