{
  "type": "Feature",
  "properties": {
    "addr:full":"375 Park Ave New York NY 10022",
    "addr:housenumber":"375",
    "addr:postcode":"10022",
    "addr:street":"Park Ave",
    "iso:country":"US",
    "sg:address":"375 Park Ave",
    "sg:city":"New York",
    "sg:classifiers":[
        {
            "category":"Parking",
            "type":"Transportation"
        }
    ],
    "sg:phone":"+1 212 644 7429",
    "sg:postcode":"10022",
    "sg:province":"NY",
    "sg:tags":[
        "garage"
    ],
    "wof:name":"Meyers Parking System",
    "wof:placetype":"venue"
},
  "geometry": {"coordinates":[-73.97275399999999,40.758647],"type":"Point"}
}