{
  "type": "Feature",
  "properties": {
    "addr:full":"85 Friar Dr Rochester NY 14626",
    "addr:housenumber":"85",
    "addr:postcode":"14626",
    "addr:street":"Friar Dr",
    "iso:country":"US",
    "sg:address":"85 Friar Dr",
    "sg:city":"Rochester",
    "sg:classifiers":[
        {
            "category":"Internet Cafe",
            "subcategory":"None",
            "type":"Food & Drink"
        },
        {
            "category":"Professional",
            "subcategory":"Computer Services",
            "type":"Services"
        }
    ],
    "sg:phone":"+1 585 227 0810",
    "sg:postcode":"14626",
    "sg:province":"NY",
    "sg:tags":[
        "publisher",
        "product",
        "software",
        "developer"
    ],
    "wof:name":"Abacus 21, Inc.",
    "wof:placetype":"venue"
},
  "geometry": {"coordinates":[-77.72476,43.222277],"type":"Point"}
}