{
  "type": "Feature",
  "properties": {
    "addr:full":"153 E 33rd St New York NY 10016",
    "addr:housenumber":"153",
    "addr:postcode":"10016",
    "addr:street":"E 33Rd St",
    "iso:country":"US",
    "sg:address":"153 E 33rd St",
    "sg:city":"New York",
    "sg:classifiers":[
        {
            "category":"Restaurant",
            "type":"Food & Drink"
        }
    ],
    "sg:phone":"+1 212 779 4953",
    "sg:postcode":"10016",
    "sg:province":"NY",
    "sg:tags":[
        "indian"
    ],
    "sg:website":"www.curryncurry.com/",
    "wof:name":"Curry & Curry",
    "wof:placetype":"venue"
},
  "geometry": {"coordinates":[-73.979478,40.745562],"type":"Point"}
}