{
  "type": "Feature",
  "properties": {
    "addr:full":"1249 Avenue U Brooklyn NY 11229",
    "addr:housenumber":"1249",
    "addr:postcode":"11229",
    "addr:street":"Avenue U",
    "iso:country":"US",
    "sg:address":"1249 Avenue U",
    "sg:city":"Brooklyn",
    "sg:classifiers":[
        {
            "category":"Restaurant",
            "type":"Food & Drink"
        }
    ],
    "sg:menulink":"http://www.allmenus.com/ny/brooklyn/62046-la-villita/menu/",
    "sg:phone":"+1 718 998 0222",
    "sg:postcode":"11229",
    "sg:province":"NY",
    "sg:tags":[
        "mexican"
    ],
    "wof:name":"La Villita",
    "wof:placetype":"venue"
},
  "geometry": {"coordinates":[-73.958968,40.598552],"type":"Point"}
}