{
  "type": "Feature",
  "properties": {
    "iso:country":"US",
    "sg:address":"740 Riverside Dr",
    "sg:city":"Johnson City",
    "sg:classifiers":[
        {
            "category":"Shopping",
            "subcategory":"Florist",
            "type":"Retail Goods"
        }
    ],
    "sg:phone":"+1 607 729 3555",
    "sg:postcode":"13790",
    "sg:province":"NY",
    "sg:website":"www.dillenbecks.com",
    "wof:name":"Dillenbeck's Flowers",
    "wof:placetype":"venue"
},
  "geometry": {"coordinates":[-75.968828,42.113617],"type":"Point"}
}