{
  "type": "Feature",
  "properties": {
    "addr:full":"5914 Ave N Brooklyn NY 11234",
    "addr:housenumber":"5914",
    "addr:postcode":"11234",
    "addr:street":"Ave N",
    "iso:country":"US",
    "sg:address":"5914 Ave N",
    "sg:city":"Brooklyn",
    "sg:classifiers":[
        {
            "category":"Food & Beverages",
            "subcategory":"Meat & Fish",
            "type":"Retail Goods"
        }
    ],
    "sg:phone":"+1 718 209 3474",
    "sg:postcode":"11234",
    "sg:province":"NY",
    "sg:tags":[
        "seafood",
        "market"
    ],
    "sg:website":"www.seatidegourmet.com",
    "wof:name":"Seatide Gourmet Fish Market",
    "wof:placetype":"venue"
},
  "geometry": {"coordinates":[-73.921558,40.613286],"type":"Point"}
}