{
  "type": "Feature",
  "properties": {
    "addr:full":"48 High St Tupper Lake NY 12986",
    "addr:housenumber":"48",
    "addr:postcode":"12986",
    "addr:street":"High St",
    "iso:country":"US",
    "sg:address":"48 High St",
    "sg:city":"Tupper Lake",
    "sg:classifiers":[
        {
            "category":"Organizations",
            "subcategory":"Religious Organization",
            "type":"Services"
        }
    ],
    "sg:phone":"+1 518 359 3838",
    "sg:postcode":"12986",
    "sg:province":"NY",
    "sg:tags":[
        "monastery",
        "convent"
    ],
    "wof:name":"Holy Ghost Convent",
    "wof:placetype":"venue"
},
  "geometry": {"coordinates":[-74.466531,44.221038],"type":"Point"}
}