{
  "type": "Feature",
  "properties": {
    "iso:country":"US",
    "sg:address":"76 Riverdale Avenue",
    "sg:city":"Brooklyn",
    "sg:classifiers":[
        {
            "category":"Education",
            "subcategory":"School",
            "type":"Public Place"
        }
    ],
    "sg:phone":"+1 718 495 0952",
    "sg:postcode":"11212",
    "sg:province":"NY",
    "sg:tags":[
        "high",
        "middle",
        "elementary"
    ],
    "wof:name":"N Y City of",
    "wof:placetype":"venue"
},
  "geometry": {"coordinates":[-73.913488,40.660168],"type":"Point"}
}