{
  "type": "Feature",
  "properties": {
    "iso:country":"US",
    "sg:address":"1315 Middle Country Rd Ste 3",
    "sg:city":"Centereach",
    "sg:classifiers":[
        {
            "category":"Restaurant",
            "type":"Food & Drink"
        }
    ],
    "sg:phone":"+1 631 696 0411",
    "sg:postcode":"11720",
    "sg:province":"NY",
    "sg:tags":[
        "italian"
    ],
    "sg:website":"www.badolatosmarket.com",
    "wof:name":"Badolato's Market",
    "wof:placetype":"venue"
},
  "geometry": {"coordinates":[-73.059414,40.862113],"type":"Point"}
}