{
  "type": "Feature",
  "properties": {
    "addr:full":"778 Spur Dr N Bay Shore NY 11706",
    "addr:housenumber":"778",
    "addr:postcode":"11706",
    "addr:street":"Spur Dr N",
    "iso:country":"US",
    "sg:address":"778 Spur Dr N",
    "sg:city":"Bay Shore",
    "sg:classifiers":[
        {
            "category":"Building & Trades",
            "subcategory":"Landscaping Services",
            "type":"Services"
        }
    ],
    "sg:phone":"+1 631 666 2267",
    "sg:postcode":"11706",
    "sg:province":"NY",
    "sg:tags":[
        "landscape",
        "contractor"
    ],
    "wof:name":"Danny B's Landscaping",
    "wof:placetype":"venue"
},
  "geometry": {"coordinates":[-73.245357,40.752645],"type":"Point"}
}