{
  "type": "Feature",
  "properties": {
    "iso:country":"US",
    "sg:address":"1322 Co Rd 107",
    "sg:city":"Fort Johnson",
    "sg:classifiers":[
        {
            "category":"Retail",
            "subcategory":"Animal Services",
            "type":"Services"
        }
    ],
    "sg:phone":"+1 518 842 4139",
    "sg:postcode":"12070",
    "sg:province":"NY",
    "sg:tags":[
        "pet",
        "grooming",
        "washing"
    ],
    "wof:name":"Diane's KLIP 'n Klean",
    "wof:placetype":"venue"
},
  "geometry": {"coordinates":[-74.258673,43.012216],"type":"Point"}
}