{
  "type": "Feature",
  "properties": {
    "iso:country":"US",
    "sg:address":"134 Turner Rd",
    "sg:city":"Pearl River",
    "sg:classifiers":[
        {
            "category":"Building & Trades",
            "subcategory":"Construction",
            "type":"Services"
        }
    ],
    "sg:phone":"+1 845 735 9556",
    "sg:postcode":"10965",
    "sg:province":"NY",
    "sg:tags":[
        "nonresidential"
    ],
    "wof:name":"Accord Contracting & Mfg",
    "wof:placetype":"venue"
},
  "geometry": {"coordinates":[-74.02145400000001,41.051008],"type":"Point"}
}