{
  "type": "Feature",
  "properties": {
    "iso:country":"US",
    "sg:address":"61 Roslyn Rd",
    "sg:city":"Roslyn Heights",
    "sg:classifiers":[
        {
            "category":"Building & Trades",
            "subcategory":"Construction",
            "type":"Services"
        }
    ],
    "sg:phone":"+1 516 621 6699",
    "sg:postcode":"11577",
    "sg:province":"NY",
    "sg:tags":[
        "installs",
        "mfg",
        "custom",
        "cabinet"
    ],
    "wof:name":"Seco Systems",
    "wof:placetype":"venue"
},
  "geometry": {"coordinates":[-73.641384,40.792471],"type":"Point"}
}