{
  "type": "Feature",
  "properties": {
    "addr:full":"3187 Steinway Street Astoria NY 11103",
    "addr:housenumber":"3187",
    "addr:postcode":"11103",
    "addr:street":"Steinway Street",
    "iso:country":"US",
    "sg:address":"3187 Steinway Street",
    "sg:city":"Astoria",
    "sg:classifiers":[
        {
            "category":"Professional",
            "subcategory":"Lawyer & Legal Services",
            "type":"Services"
        }
    ],
    "sg:phone":"+1 718 729 5959",
    "sg:postcode":"11103",
    "sg:province":"NY",
    "wof:name":"Karavias Jason Atty",
    "wof:placetype":"venue"
},
  "geometry": {"coordinates":[-73.918736,40.759297],"type":"Point"}
}