{
  "type": "Feature",
  "properties": {
    "iso:country":"US",
    "sg:address":"1389 Atlantic Ave",
    "sg:city":"Brooklyn",
    "sg:classifiers":[
        {
            "category":"Retail",
            "subcategory":"Auto Repair",
            "type":"Services"
        }
    ],
    "sg:phone":"+1 718 221 1133",
    "sg:postcode":"11216",
    "sg:province":"NY",
    "sg:tags":[
        "repairing",
        "automobile"
    ],
    "wof:name":"New Horizon Automotive Inc",
    "wof:placetype":"venue"
},
  "geometry": {"coordinates":[-73.94380200000001,40.678299],"type":"Point"}
}