{
  "type": "Feature",
  "properties": {
    "addr:full":"2547 Youngstown Lockport Rd Ransomville NY 14131",
    "addr:housenumber":"2547",
    "addr:postcode":"14131",
    "addr:street":"Lockport Rd",
    "iso:country":"US",
    "sg:address":"2547 Youngstown Lockport Rd",
    "sg:city":"Ransomville",
    "sg:classifiers":[
        {
            "category":"Banks & Credit Unions",
            "subcategory":"Bank",
            "type":"Services"
        }
    ],
    "sg:phone":"+1 716 791 3009",
    "sg:postcode":"14131",
    "sg:province":"NY",
    "sg:tags":[
        "saving",
        "commercial"
    ],
    "sg:website":"http://fnfg.com",
    "wof:name":"First Niagara Bank",
    "wof:placetype":"venue"
},
  "geometry": {"coordinates":[-78.909716,43.238559],"type":"Point"}
}