{
  "type": "Feature",
  "properties": {
    "addr:full":"261 W 29th St New York NY 10001",
    "addr:housenumber":"261",
    "addr:postcode":"10001",
    "addr:street":"W 29Th St",
    "iso:country":"US",
    "sg:address":"261 W 29th St",
    "sg:city":"New York",
    "sg:classifiers":[
        {
            "category":"Professional",
            "subcategory":"Art Services",
            "type":"Services"
        }
    ],
    "sg:phone":"+1 212 629 8946",
    "sg:postcode":"10001",
    "sg:province":"NY",
    "sg:tags":[
        "graphic",
        "designer"
    ],
    "wof:name":"Kervel Studio",
    "wof:placetype":"venue"
},
  "geometry": {"coordinates":[-73.99439599999999,40.748385],"type":"Point"}
}