{
  "type": "Feature",
  "properties": {
    "addr:full":"986 Newell Rd Middlesex NY 14507",
    "addr:housenumber":"986",
    "addr:postcode":"14507",
    "addr:street":"Newell Rd",
    "iso:country":"US",
    "sg:address":"986 Newell Rd",
    "sg:city":"Middlesex",
    "sg:classifiers":[
        {
            "category":"Building & Trades",
            "subcategory":"Construction",
            "type":"Services"
        }
    ],
    "sg:phone":"+1 585 554 4639",
    "sg:postcode":"14507",
    "sg:province":"NY",
    "sg:tags":[
        "floor",
        "laying",
        "contractor"
    ],
    "wof:name":"Rowe Flooring",
    "wof:placetype":"venue"
},
  "geometry": {"coordinates":[-77.30935700000001,42.714642],"type":"Point"}
}