{
  "type": "Feature",
  "properties": {
    "addr:full":"740 Bergen St Brooklyn NY 11238",
    "addr:housenumber":"740",
    "addr:postcode":"11238",
    "addr:street":"Bergen St",
    "iso:country":"US",
    "sg:address":"740 Bergen St",
    "sg:city":"Brooklyn",
    "sg:classifiers":[
        {
            "category":"Bakery",
            "type":"Food & Drink"
        }
    ],
    "sg:phone":"+1 718 399 6777",
    "sg:postcode":"11238",
    "sg:province":"NY",
    "sg:website":"www.dsjustdesserts.com",
    "wof:name":"D's Just Desserts",
    "wof:placetype":"venue"
},
  "geometry": {"coordinates":[-73.964127,40.678554],"type":"Point"}
}