{
  "type": "Feature",
  "properties": {
    "addr:full":"311 W 43 St Ste 405 New York NY 10036",
    "addr:housenumber":"311;405",
    "addr:postcode":"10036",
    "addr:street":"W 43 St Ste",
    "iso:country":"US",
    "sg:address":"311 W 43 St Ste 405",
    "sg:city":"New York",
    "sg:classifiers":[
        {
            "category":"Arts & Performance",
            "subcategory":"Arts Center",
            "type":"Entertainment"
        },
        {
            "category":"Health Services",
            "subcategory":"Health Practitioner",
            "type":"Services"
        }
    ],
    "sg:phone":"+1 212 245 7278",
    "sg:postcode":"10036",
    "sg:province":"NY",
    "sg:tags":[
        "performing",
        "therapy",
        "physical"
    ],
    "sg:website":"www.papt.biz/",
    "wof:name":"Performing Arts Physical Therapy",
    "wof:placetype":"venue"
},
  "geometry": {"coordinates":[-73.98998400000001,40.758455],"type":"Point"}
}