{
  "type": "Feature",
  "properties": {
    "addr:full":"59 Rutledge St Brooklyn NY 11211",
    "addr:housenumber":"59",
    "addr:postcode":"11211",
    "addr:street":"Rutledge St",
    "iso:country":"US",
    "sg:address":"59 Rutledge St",
    "sg:city":"Brooklyn",
    "sg:classifiers":[
        {
            "category":"Manufacturing",
            "subcategory":"Printing",
            "type":"Manufacturing & Wholesale Goods"
        }
    ],
    "sg:phone":"+1   ",
    "sg:postcode":"11211",
    "sg:province":"NY",
    "sg:tags":[
        "book"
    ],
    "wof:name":"Yofi Book Publishing Inc",
    "wof:placetype":"venue"
},
  "geometry": {"coordinates":[-73.960634,40.699682],"type":"Point"}
}