{
  "type": "Feature",
  "properties": {
    "addr:full":"134 12th St Brooklyn NY 11215",
    "addr:housenumber":"134",
    "addr:postcode":"11215",
    "addr:street":"12Th St",
    "iso:country":"US",
    "sg:address":"134 12th St",
    "sg:city":"Brooklyn",
    "sg:classifiers":[
        {
            "category":"Building & Trades",
            "subcategory":"Construction",
            "type":"Services"
        }
    ],
    "sg:phone":"+1 718 832 8882",
    "sg:postcode":"11215",
    "sg:province":"NY",
    "sg:tags":[
        "steel",
        "fabrication",
        "welding"
    ],
    "wof:name":"Eternity Stainless Steel",
    "wof:placetype":"venue"
},
  "geometry": {"coordinates":[-73.993835,40.670393],"type":"Point"}
}