{
  "type": "Feature",
  "properties": {
    "iso:country":"US",
    "sg:address":"605 W 188th St",
    "sg:city":"New York",
    "sg:classifiers":[
        {
            "category":"Retail",
            "subcategory":"Funeral Services",
            "type":"Services"
        }
    ],
    "sg:phone":"+1   ",
    "sg:postcode":"10040",
    "sg:province":"NY",
    "wof:name":"DBari Funeral Home",
    "wof:placetype":"venue"
},
  "geometry": {"coordinates":[-73.931652,40.854219],"type":"Point"}
}