{
  "type": "Feature",
  "properties": {
    "iso:country":"US",
    "sg:address":"743 Town Line Rd",
    "sg:city":"Elma",
    "sg:classifiers":[
        {
            "category":"Wholesale",
            "subcategory":"Sporting Goods",
            "type":"Manufacturing & Wholesale Goods"
        }
    ],
    "sg:phone":"+1 716 683 2047",
    "sg:postcode":"14059",
    "sg:province":"NY",
    "wof:name":"Jim Bar Trap Supplies",
    "wof:placetype":"venue"
},
  "geometry": {"coordinates":[-78.577595,42.854851],"type":"Point"}
}