{
  "type": "Feature",
  "properties": {
    "iso:country":"US",
    "sg:address":"2372 Victory Blvd",
    "sg:city":"Staten Island",
    "sg:classifiers":[
        {
            "category":"Health Services",
            "subcategory":"Doctor",
            "type":"Services"
        }
    ],
    "sg:phone":"+1 718 761 3700",
    "sg:postcode":"10314",
    "sg:province":"NY",
    "wof:name":"Lacqua Frank Dr MD",
    "wof:placetype":"venue"
},
  "geometry": {"coordinates":[-74.142477,40.610905],"type":"Point"}
}