{
  "type": "Feature",
  "properties": {
    "iso:country":"US",
    "sg:address":"883 Upper Mountain Rd",
    "sg:city":"Lewiston",
    "sg:classifiers":[
        {
            "category":"Wholesale",
            "subcategory":"Vending Machines",
            "type":"Manufacturing & Wholesale Goods"
        }
    ],
    "sg:phone":"+1   ",
    "sg:postcode":"14092",
    "sg:province":"NY",
    "sg:tags":[
        "operator"
    ],
    "wof:name":"New Age Vending",
    "wof:placetype":"venue"
},
  "geometry": {"coordinates":[-79.017337,43.156292],"type":"Point"}
}