{
  "type": "Feature",
  "properties": {
    "iso:country":"US",
    "sg:address":"580 Pelham Rd",
    "sg:city":"New Rochelle",
    "sg:classifiers":[
        {
            "category":"Building & Trades",
            "subcategory":"Construction",
            "type":"Services"
        }
    ],
    "sg:phone":"+1 914 738 8394",
    "sg:postcode":"10805",
    "sg:province":"NY",
    "sg:tags":[
        "excavation",
        "excavating",
        "contractor"
    ],
    "wof:name":"Correia Construction Corp",
    "wof:placetype":"venue"
},
  "geometry": {"coordinates":[-73.785421,40.892784],"type":"Point"}
}