{
  "type": "Feature",
  "properties": {
    "addr:full":"191 Speigletown Rd Troy NY 12182",
    "addr:housenumber":"191",
    "addr:postcode":"12182",
    "addr:street":"Speigletown Rd",
    "iso:country":"US",
    "sg:address":"191 Speigletown Rd",
    "sg:city":"Troy",
    "sg:classifiers":[
        {
            "category":"Manufacturing",
            "subcategory":"Printing",
            "type":"Manufacturing & Wholesale Goods"
        }
    ],
    "sg:phone":"+1   ",
    "sg:postcode":"12182",
    "sg:province":"NY",
    "sg:tags":[
        "lithographic",
        "commercial"
    ],
    "wof:name":"September Klein Prod Print MGT",
    "wof:placetype":"venue"
},
  "geometry": {"coordinates":[-73.636393,42.802555],"type":"Point"}
}