{
  "type": "Feature",
  "properties": {
    "addr:full":"24 Dutchess Dr Orangeburg NY 10962",
    "addr:housenumber":"24",
    "addr:postcode":"10962",
    "addr:street":"Dutchess Dr",
    "iso:country":"US",
    "sg:address":"24 Dutchess Dr",
    "sg:city":"Orangeburg",
    "sg:classifiers":[
        {
            "category":"Professional",
            "subcategory":"Business Services",
            "type":"Services"
        }
    ],
    "sg:phone":"+1 845 398 3090",
    "sg:postcode":"10962",
    "sg:province":"NY",
    "sg:tags":[
        "transcribing",
        "disc"
    ],
    "wof:name":"Medi-Trans Plus",
    "wof:placetype":"venue"
},
  "geometry": {"coordinates":[-73.968439,41.040607],"type":"Point"}
}