{
  "type": "Feature",
  "properties": {
    "addr:full":"23 Potter St Farmingdale NY 11735",
    "addr:housenumber":"23",
    "addr:postcode":"11735",
    "addr:street":"Potter St",
    "iso:country":"US",
    "sg:address":"23 Potter St",
    "sg:city":"Farmingdale",
    "sg:classifiers":[
        {
            "category":"Building & Trades",
            "subcategory":"Construction",
            "type":"Services"
        }
    ],
    "sg:phone":"+1 516 249 1600",
    "sg:postcode":"11735",
    "sg:province":"NY",
    "sg:tags":[
        "demolition",
        "contractor"
    ],
    "wof:name":"Ambition Industries LLC",
    "wof:placetype":"venue"
},
  "geometry": {"coordinates":[-73.43391200000001,40.724488],"type":"Point"}
}