{
  "type": "Feature",
  "properties": {
    "iso:country":"US",
    "sg:address":"1043 Erie Blvd E",
    "sg:city":"Syracuse",
    "sg:classifiers":[
        {
            "category":"Building & Trades",
            "subcategory":"Plumbing",
            "type":"Services"
        }
    ],
    "sg:phone":"+1 315 475 3131",
    "sg:postcode":"13210",
    "sg:province":"NY",
    "sg:tags":[
        "conditioning",
        "air",
        "system",
        "contractor"
    ],
    "wof:name":"Meier Supply Co Inc",
    "wof:placetype":"venue"
},
  "geometry": {"coordinates":[-76.13493099999999,43.050761],"type":"Point"}
}