{
  "type": "Feature",
  "properties": {
    "addr:full":"631 E 220th St Bronx NY 10467",
    "addr:housenumber":"631",
    "addr:postcode":"10467",
    "addr:street":"E 220Th St",
    "iso:country":"US",
    "sg:address":"631 E 220th St",
    "sg:city":"Bronx",
    "sg:classifiers":[
        {
            "category":"Shopping",
            "subcategory":"Gifts & Souvenirs",
            "type":"Retail Goods"
        }
    ],
    "sg:phone":"+1 718 654 3520",
    "sg:postcode":"10467",
    "sg:province":"NY",
    "sg:tags":[
        "cards",
        "greeting"
    ],
    "wof:name":"Arrington Gift Card Shop",
    "wof:placetype":"venue"
},
  "geometry": {"coordinates":[-73.863049,40.884629],"type":"Point"}
}