{
  "type": "Feature",
  "properties": {
    "iso:country":"US",
    "sg:address":"1201 Wantagh Ave",
    "sg:city":"Wantagh",
    "sg:classifiers":[
        {
            "category":"Banks & Credit Unions",
            "subcategory":"Bank",
            "type":"Services"
        }
    ],
    "sg:phone":"+1 516 783 5860",
    "sg:postcode":"11793",
    "sg:province":"NY",
    "wof:name":"JPMorgan Chase & Co",
    "wof:placetype":"venue"
},
  "geometry": {"coordinates":[-73.507492,40.693515],"type":"Point"}
}