{
  "type": "Feature",
  "properties": {
    "addr:full":"82 Susan Dr Newburgh NY 12550",
    "addr:housenumber":"82",
    "addr:postcode":"12550",
    "addr:street":"Susan Dr",
    "iso:country":"US",
    "sg:address":"82 Susan Dr",
    "sg:city":"Newburgh",
    "sg:classifiers":[
        {
            "category":"Utilities",
            "subcategory":"Fuel Oil & Lpg",
            "type":"Services"
        }
    ],
    "sg:phone":"+1 845 565 3913",
    "sg:postcode":"12550",
    "sg:province":"NY",
    "sg:tags":[
        "oils-fuel"
    ],
    "wof:name":"Direct Fuel Co",
    "wof:placetype":"venue"
},
  "geometry": {"coordinates":[-74.004344,41.536102],"type":"Point"}
}