{
  "type": "Feature",
  "properties": {
    "iso:country":"US",
    "sg:address":"3641 28th St",
    "sg:city":"Astoria",
    "sg:classifiers":[
        {
            "category":"Education",
            "subcategory":"School",
            "type":"Public Place"
        }
    ],
    "sg:phone":"+1 718 937 0605",
    "sg:postcode":"11106",
    "sg:province":"NY",
    "wof:name":"Long Beach City School District (Inc)",
    "wof:placetype":"venue"
},
  "geometry": {"coordinates":[-73.932258,40.757579],"type":"Point"}
}