{
  "type": "Feature",
  "properties": {
    "addr:full":"1484 E 26th St Brooklyn NY 11210",
    "addr:housenumber":"1484",
    "addr:postcode":"11210",
    "addr:street":"E 26Th St",
    "iso:country":"US",
    "sg:address":"1484 E 26th St",
    "sg:city":"Brooklyn",
    "sg:classifiers":[
        {
            "category":"Retail",
            "subcategory":"Repair Shop",
            "type":"Services"
        },
        {
            "category":"Building & Trades",
            "subcategory":"Plumbing",
            "type":"Services"
        }
    ],
    "sg:phone":"+1 718 377 8122",
    "sg:postcode":"11210",
    "sg:province":"NY",
    "sg:tags":[
        "system",
        "air",
        "refrigeration",
        "conditioning",
        "contractor",
        "unit"
    ],
    "wof:name":"HI Rely Conditioning Corp",
    "wof:placetype":"venue"
},
  "geometry": {"coordinates":[-73.948747,40.616421],"type":"Point"}
}