{
  "type": "Feature",
  "properties": {
    "addr:full":"40 Romer Ave Pleasantville NY 10570",
    "addr:housenumber":"40",
    "addr:postcode":"10570",
    "addr:street":"Romer Ave",
    "iso:country":"US",
    "sg:address":"40 Romer Ave",
    "sg:city":"Pleasantville",
    "sg:classifiers":[
        {
            "category":"Organizations",
            "subcategory":"Professional Association",
            "type":"Services"
        }
    ],
    "sg:phone":"+1 914 747 9331",
    "sg:postcode":"10570",
    "sg:province":"NY",
    "wof:name":"Teachers Association",
    "wof:placetype":"venue"
},
  "geometry": {"coordinates":[-73.78552999999999,41.134892],"type":"Point"}
}