{
  "type": "Feature",
  "properties": {
    "addr:full":"164 Gerdes Rd New Canaan NY 06840",
    "addr:housenumber":"164",
    "addr:postcode":"06840",
    "addr:street":"Gerdes Rd",
    "iso:country":"US",
    "sg:address":"164 Gerdes Rd",
    "sg:city":"New Canaan",
    "sg:classifiers":[
        {
            "category":"Organizations",
            "subcategory":"Community Association",
            "type":"Services"
        }
    ],
    "sg:phone":"+1   ",
    "sg:postcode":"06840",
    "sg:province":"NY",
    "wof:name":"Trout Unlimited",
    "wof:placetype":"venue"
},
  "geometry": {"coordinates":[-73.475189,41.123347],"type":"Point"}
}