{
  "type": "Feature",
  "properties": {
    "iso:country":"US",
    "sg:address":"1054 70th St",
    "sg:city":"Brooklyn",
    "sg:classifiers":[
        {
            "category":"Building & Trades",
            "subcategory":"Construction",
            "type":"Services"
        }
    ],
    "sg:phone":"+1 718 680 3139",
    "sg:postcode":"11228",
    "sg:province":"NY",
    "sg:tags":[
        "general",
        "contractor"
    ],
    "wof:name":"San Martin Construction Co",
    "wof:placetype":"venue"
},
  "geometry": {"coordinates":[-74.00984699999999,40.626477],"type":"Point"}
}