{
  "type": "Feature",
  "properties": {
    "addr:full":"16807 Baisley Blvd Jamaica NY 11434",
    "addr:housenumber":"16807",
    "addr:postcode":"11434",
    "addr:street":"Baisley Blvd",
    "iso:country":"US",
    "sg:address":"16807 Baisley Blvd",
    "sg:city":"Jamaica",
    "sg:classifiers":[
        {
            "category":"Retail",
            "subcategory":"Auto Repair",
            "type":"Services"
        }
    ],
    "sg:phone":"+1 718 527 9802",
    "sg:postcode":"11434",
    "sg:province":"NY",
    "sg:tags":[
        "body",
        "shop"
    ],
    "wof:name":"Indianapolis 500",
    "wof:placetype":"venue"
},
  "geometry": {"coordinates":[-73.775299,40.680401],"type":"Point"}
}