{
  "type": "Feature",
  "properties": {
    "addr:full":"239 Laurel Ave Northport NY 11768",
    "addr:housenumber":"239",
    "addr:postcode":"11768",
    "addr:street":"Laurel Ave",
    "iso:country":"US",
    "sg:address":"239 Laurel Ave",
    "sg:city":"Northport",
    "sg:classifiers":[
        {
            "category":"Wholesale",
            "subcategory":"Computers",
            "type":"Manufacturing & Wholesale Goods"
        },
        {
            "category":"Professional",
            "subcategory":"Computer Services",
            "type":"Services"
        }
    ],
    "sg:phone":"+1 631 486 2798",
    "sg:postcode":"11768",
    "sg:province":"NY",
    "sg:tags":[
        "repair"
    ],
    "wof:name":"Quadra International",
    "wof:placetype":"venue"
},
  "geometry": {"coordinates":[-73.337121,40.893958],"type":"Point"}
}