{
  "type": "Feature",
  "properties": {
    "iso:country":"US",
    "sg:address":"10 Raymond Ave",
    "sg:city":"Poughkeepsie",
    "sg:classifiers":[
        {
            "category":"Education",
            "subcategory":"Special Training",
            "type":"Public Place"
        }
    ],
    "sg:phone":"+1 845 454 2980",
    "sg:postcode":"12604",
    "sg:province":"NY",
    "sg:tags":[
        "tutoring"
    ],
    "wof:name":"Masters Academy",
    "wof:placetype":"venue"
},
  "geometry": {"coordinates":[-73.90136699999999,41.695493],"type":"Point"}
}