{
  "type": "Feature",
  "properties": {
    "addr:full":"105 Central Park Plz Buffalo NY 14214",
    "addr:housenumber":"105",
    "addr:postcode":"14214",
    "addr:street":"Central Park Plz",
    "iso:country":"US",
    "sg:address":"105 Central Park Plz",
    "sg:city":"Buffalo",
    "sg:classifiers":[
        {
            "category":"Shopping",
            "subcategory":"Computers & Home Electronics",
            "type":"Retail Goods"
        }
    ],
    "sg:phone":"+1   ",
    "sg:postcode":"14214",
    "sg:province":"NY",
    "wof:name":"Radio Shack",
    "wof:placetype":"venue"
},
  "geometry": {"coordinates":[-78.833189,42.938066],"type":"Point"}
}