{
  "type": "Feature",
  "properties": {
    "addr:full":"3675 E Tremont Ave Bronx NY 10465",
    "addr:housenumber":"3675",
    "addr:postcode":"10465",
    "addr:street":"E Tremont Ave",
    "iso:country":"US",
    "sg:address":"3675 E Tremont Ave",
    "sg:city":"Bronx",
    "sg:classifiers":[
        {
            "category":"Health Services",
            "subcategory":"Chiropractor",
            "type":"Services"
        }
    ],
    "sg:phone":"+1 718 824 1377",
    "sg:postcode":"10465",
    "sg:province":"NY",
    "wof:name":"Rabadi Ariq Chrprctr",
    "wof:placetype":"venue"
},
  "geometry": {"coordinates":[-73.82289900000001,40.827499],"type":"Point"}
}