{
  "type": "Feature",
  "properties": {
    "iso:country":"US",
    "sg:address":"334 Cornelia St",
    "sg:city":"Plattsburgh",
    "sg:classifiers":[
        {
            "category":"Professional",
            "subcategory":"Secretarial Services",
            "type":"Services"
        }
    ],
    "sg:phone":"+1 518 561 2162",
    "sg:postcode":"12901",
    "sg:province":"NY",
    "sg:tags":[
        "reporting",
        "business"
    ],
    "wof:name":"UPS Stores The",
    "wof:placetype":"venue"
},
  "geometry": {"coordinates":[-73.479968,44.697343],"type":"Point"}
}