{
  "type": "Feature",
  "properties": {
    "iso:country":"US",
    "sg:address":"745 Titus Ave",
    "sg:city":"Rochester",
    "sg:classifiers":[
        {
            "category":"Real Estate",
            "subcategory":"Developer",
            "type":"Services"
        },
        {
            "category":"Building & Trades",
            "subcategory":"Landscaping Services",
            "type":"Services"
        }
    ],
    "sg:phone":"+1 585 544 5650",
    "sg:postcode":"14617",
    "sg:province":"NY",
    "sg:tags":[
        "landscape",
        "contractor"
    ],
    "wof:name":"Romeo Land Development LLC",
    "wof:placetype":"venue"
},
  "geometry": {"coordinates":[-77.597266,43.210624],"type":"Point"}
}