{
  "type": "Feature",
  "properties": {
    "addr:full":"250 W 43rd St New York NY 10036",
    "addr:housenumber":"250",
    "addr:postcode":"10036",
    "addr:street":"W 43Rd St",
    "iso:country":"US",
    "sg:address":"250 W 43rd St",
    "sg:city":"New York",
    "sg:classifiers":[
        {
            "category":"Cafe",
            "type":"Food & Drink"
        }
    ],
    "sg:menulink":"http://www.allmenus.com/ny/new-york/248078-lucky-star-cafe/menu/",
    "sg:phone":"+1 212 764 7920",
    "sg:postcode":"10036",
    "sg:province":"NY",
    "sg:tags":[
        "american",
        "diner"
    ],
    "wof:name":"Lucky Star Cafe",
    "wof:placetype":"venue"
},
  "geometry": {"coordinates":[-73.988499,40.757424],"type":"Point"}
}