{
  "type": "Feature",
  "properties": {
    "iso:country":"US",
    "sg:address":"473 Pleasantview Ave",
    "sg:city":"Syracuse",
    "sg:classifiers":[
        {
            "category":"Building & Trades",
            "subcategory":"Construction",
            "type":"Services"
        }
    ],
    "sg:phone":"+1 315 454 5517",
    "sg:postcode":"13208",
    "sg:province":"NY",
    "sg:tags":[
        "hanging",
        "contractor"
    ],
    "wof:name":"Paul Painter",
    "wof:placetype":"venue"
},
  "geometry": {"coordinates":[-76.134393,43.077034],"type":"Point"}
}