{
  "type": "Feature",
  "properties": {
    "addr:full":"13 Vine Ct Carle Place NY 11514",
    "addr:housenumber":"13",
    "addr:postcode":"11514",
    "addr:street":"Vine Ct",
    "iso:country":"US",
    "sg:address":"13 Vine Ct",
    "sg:city":"Carle Place",
    "sg:classifiers":[
        {
            "category":"Building & Trades",
            "subcategory":"Landscaping Services",
            "type":"Services"
        }
    ],
    "sg:phone":"+1 516 294 3393",
    "sg:postcode":"11514",
    "sg:province":"NY",
    "sg:tags":[
        "landscape"
    ],
    "wof:name":"Mtm Ponds & Landscaping",
    "wof:placetype":"venue"
},
  "geometry": {"coordinates":[-73.620521,40.752556],"type":"Point"}
}