{
  "type": "Feature",
  "properties": {
    "addr:full":"167 Flanders St Ste D7 Rochester NY 14619",
    "addr:housenumber":"167",
    "addr:postcode":"14619",
    "addr:street":"Flanders St Ste D7",
    "iso:country":"US",
    "sg:address":"167 Flanders St Ste D7",
    "sg:city":"Rochester",
    "sg:classifiers":[
        {
            "category":"Professional",
            "subcategory":"Computer Services",
            "type":"Services"
        }
    ],
    "sg:phone":"+1 585 436 0567",
    "sg:postcode":"14619",
    "sg:province":"NY",
    "sg:tags":[
        "consultant",
        "designer",
        "system",
        "software"
    ],
    "wof:name":"Rochester Software Technologies",
    "wof:placetype":"venue"
},
  "geometry": {"coordinates":[-77.649981,43.13596],"type":"Point"}
}