{
  "type": "Feature",
  "properties": {
    "addr:full":"497 Canal Street Manhattan NY 10013",
    "addr:housenumber":"497",
    "addr:postcode":"10013",
    "addr:street":"Canal Street",
    "iso:country":"US",
    "sg:address":"497 Canal Street",
    "sg:city":"Manhattan",
    "sg:classifiers":[
        {
            "category":"Real Estate",
            "subcategory":"Architect",
            "type":"Services"
        }
    ],
    "sg:phone":"+1 866 789 8436",
    "sg:postcode":"10013",
    "sg:province":"NY",
    "sg:website":"www.theometrics.com",
    "wof:name":"Theometrics",
    "wof:placetype":"venue"
},
  "geometry": {"coordinates":[-74.008329,40.724251],"type":"Point"}
}