{
  "type": "Feature",
  "properties": {
    "addr:full":"796A Franklin Ave Brooklyn NY 11238",
    "addr:housenumber":"796a",
    "addr:postcode":"11238",
    "addr:street":"Franklin Ave",
    "iso:country":"US",
    "sg:address":"796A Franklin Ave",
    "sg:city":"Brooklyn",
    "sg:classifiers":[
        {
            "category":"Restaurant",
            "type":"Food & Drink"
        }
    ],
    "sg:phone":"+1 718 771 0635",
    "sg:postcode":"11238",
    "sg:province":"NY",
    "sg:tags":[
        "caribbean"
    ],
    "wof:name":"JamRock Kitchen",
    "wof:placetype":"venue"
},
  "geometry": {"coordinates":[-73.957746,40.671251],"type":"Point"}
}