{
  "type": "Feature",
  "properties": {
    "addr:full":"508 Utica St Ithaca NY 14850",
    "addr:housenumber":"508",
    "addr:postcode":"14850",
    "addr:street":"Utica St",
    "iso:country":"US",
    "sg:address":"508 Utica St",
    "sg:city":"Ithaca",
    "sg:classifiers":[
        {
            "category":"Restaurant",
            "type":"Food & Drink"
        }
    ],
    "sg:phone":"+1   ",
    "sg:postcode":"14850",
    "sg:province":"NY",
    "sg:tags":[
        "eating"
    ],
    "wof:name":"I Mama Bushes",
    "wof:placetype":"venue"
},
  "geometry": {"coordinates":[-76.498621,42.450593],"type":"Point"}
}