{
  "type": "Feature",
  "properties": {
    "addr:full":"170 Sandy Lane Rd Mohawk NY 13407",
    "addr:housenumber":"170",
    "addr:postcode":"13407",
    "addr:street":"Sandy Lane Rd",
    "iso:country":"US",
    "sg:address":"170 Sandy Lane Rd",
    "sg:city":"Mohawk",
    "sg:classifiers":[
        {
            "category":"Freight",
            "type":"Transportation"
        }
    ],
    "sg:phone":"+1   ",
    "sg:postcode":"13407",
    "sg:province":"NY",
    "sg:tags":[
        "local",
        "without",
        "storage",
        "milk",
        "trucking"
    ],
    "wof:name":"Richard Obreza Trucking Inc",
    "wof:placetype":"venue"
},
  "geometry": {"coordinates":[-74.90756500000001,43.014056],"type":"Point"}
}