{
  "type": "Feature",
  "properties": {
    "iso:country":"US",
    "sg:address":"483 Central Avenue",
    "sg:city":"Brooklyn",
    "sg:classifiers":[
        {
            "category":"Organizations",
            "subcategory":"Religious Organization",
            "type":"Services"
        }
    ],
    "sg:phone":"+1 718 443 7818",
    "sg:postcode":"11221",
    "sg:province":"NY",
    "wof:name":"Hispana Alfa & Omega",
    "wof:placetype":"venue"
},
  "geometry": {"coordinates":[-73.913037,40.691326],"type":"Point"}
}