{
  "type": "Feature",
  "properties": {
    "addr:full":"140 Elgar Pl Bronx NY 10475",
    "addr:housenumber":"140",
    "addr:postcode":"10475",
    "addr:street":"Elgar Pl",
    "iso:country":"US",
    "sg:address":"140 Elgar Pl",
    "sg:city":"Bronx",
    "sg:classifiers":[
        {
            "category":"Shopping",
            "subcategory":"Clothing, Apparel, & Fashions",
            "type":"Retail Goods"
        }
    ],
    "sg:phone":"+1   ",
    "sg:postcode":"10475",
    "sg:province":"NY",
    "sg:tags":[
        "poetic",
        "book",
        "t"
    ],
    "wof:name":"Poetic Treasures Inc",
    "wof:placetype":"venue"
},
  "geometry": {"coordinates":[-73.82173400000001,40.863545],"type":"Point"}
}