{
  "type": "Feature",
  "properties": {
    "iso:country":"US",
    "sg:address":"141 Co Rd 7",
    "sg:city":"Clifton Springs",
    "sg:classifiers":[
        {
            "category":"Professional",
            "type":"Services"
        }
    ],
    "sg:phone":"+1 315 597 9644",
    "sg:postcode":"14537",
    "sg:province":"NY",
    "wof:name":"Safe Guard Home Svc Inc",
    "wof:placetype":"venue"
},
  "geometry": {"coordinates":[-77.161644,43.029618],"type":"Point"}
}