{
  "type": "Feature",
  "properties": {
    "iso:country":"US",
    "sg:address":"3040 Gildersleeve Rd",
    "sg:city":"Marion",
    "sg:classifiers":[
        {
            "category":"Wholesale",
            "subcategory":"Durable Goods & Equipment",
            "type":"Manufacturing & Wholesale Goods"
        }
    ],
    "sg:phone":"+1 315 597 2847",
    "sg:postcode":"14505",
    "sg:province":"NY",
    "sg:tags":[
        "importer"
    ],
    "wof:name":"Angel Eyes",
    "wof:placetype":"venue"
},
  "geometry": {"coordinates":[-77.23533,43.184665],"type":"Point"}
}