{
  "type": "Feature",
  "properties": {
    "addr:full":"152 6th St Brooklyn NY 11215",
    "addr:housenumber":"152",
    "addr:postcode":"11215",
    "addr:street":"6Th St",
    "iso:country":"US",
    "sg:address":"152 6th St",
    "sg:city":"Brooklyn",
    "sg:classifiers":[
        {
            "category":"Manufacturing",
            "subcategory":"Glass & Minerals",
            "type":"Manufacturing & Wholesale Goods"
        },
        {
            "category":"Retail",
            "subcategory":"Auto Repair",
            "type":"Services"
        }
    ],
    "sg:phone":"+1 718 797 4204",
    "sg:postcode":"11215",
    "sg:province":"NY",
    "sg:tags":[
        "plate",
        "window",
        "windshield",
        "glass-auto"
    ],
    "wof:name":"Wholesale Auto Glass Distributors, Inc.",
    "wof:placetype":"venue"
},
  "geometry": {"coordinates":[-73.990331,40.67366],"type":"Point"}
}