{
  "type": "Feature",
  "properties": {
    "addr:full":"2481 McDonald Ave Brooklyn NY 11223",
    "addr:housenumber":"2481",
    "addr:postcode":"11223",
    "addr:street":"Mcdonald Ave",
    "iso:country":"US",
    "sg:address":"2481 McDonald Ave",
    "sg:city":"Brooklyn",
    "sg:classifiers":[
        {
            "category":"Retail",
            "subcategory":"Auto Repair",
            "type":"Services"
        }
    ],
    "sg:phone":"+1 718 627 9073",
    "sg:postcode":"11223",
    "sg:province":"NY",
    "sg:tags":[
        "body",
        "shop",
        "automobile",
        "removal",
        "dent",
        "painting",
        "repairing"
    ],
    "wof:name":"Super Elegant Auto Body Inc",
    "wof:placetype":"venue"
},
  "geometry": {"coordinates":[-73.97380099999999,40.591599],"type":"Point"}
}