{
  "type": "Feature",
  "properties": {
    "iso:country":"US",
    "sg:address":"4400 Dewey Ave",
    "sg:city":"Rochester",
    "sg:classifiers":[
        {
            "category":"Manufacturing",
            "subcategory":"Chemicals & Compounds",
            "type":"Manufacturing & Wholesale Goods"
        },
        {
            "category":"Manufacturing",
            "subcategory":"Tools & Machinery",
            "type":"Manufacturing & Wholesale Goods"
        },
        {
            "category":"Building & Trades",
            "subcategory":"Construction",
            "type":"Services"
        },
        {
            "category":"Home & Garden",
            "subcategory":"Building Materials",
            "type":"Retail Goods"
        },
        {
            "category":"Wholesale",
            "subcategory":"Painting Supplies",
            "type":"Manufacturing & Wholesale Goods"
        },
        {
            "category":"Autos & Motor Vehicles",
            "subcategory":"Auto Supplies",
            "type":"Retail Goods"
        },
        {
            "category":"Building & Trades",
            "subcategory":"Equipment Rental",
            "type":"Services"
        },
        {
            "category":"Manufacturing",
            "subcategory":"Building Materials",
            "type":"Manufacturing & Wholesale Goods"
        }
    ],
    "sg:phone":"+1 585 663 5806",
    "sg:postcode":"14616",
    "sg:province":"NY",
    "sg:tags":[
        "shop",
        "paint",
        "wall",
        "automobile",
        "wallpaper",
        "coating",
        "contractor",
        "paint-wholesale",
        "spraying",
        "body",
        "wallcoverings-installation",
        "wallcoverings",
        "improvement",
        "equipment-renting",
        "painter",
        "manufacturer"
    ],
    "sg:website":"http://rochester.citysearch.com/profile/external/7788912/rochester_ny/sherwin_williams.html?publisher=yellowpages&reference_id=1&placement=ypwebsitemip",
    "wof:name":"Sherwin-Williams",
    "wof:placetype":"venue"
},
  "geometry": {"coordinates":[-77.64679599999999,43.252163],"type":"Point"}
}