{
  "type": "Feature",
  "properties": {
    "iso:country":"US",
    "sg:address":"434 Court St",
    "sg:city":"Brooklyn",
    "sg:classifiers":[
        {
            "category":"Shopping",
            "subcategory":"Used Merchandise",
            "type":"Retail Goods"
        }
    ],
    "sg:phone":"+1 718 243 9094",
    "sg:postcode":"11231",
    "sg:province":"NY",
    "sg:tags":[
        "clothing"
    ],
    "wof:name":"Olive's Very Vintage",
    "wof:placetype":"venue"
},
  "geometry": {"coordinates":[-73.99764399999999,40.67898],"type":"Point"}
}