{
  "type": "Feature",
  "properties": {
    "iso:country":"US",
    "sg:address":"1610 E 19th St",
    "sg:city":"Brooklyn",
    "sg:classifiers":[
        {
            "category":"Personal",
            "subcategory":"Beauty Salon",
            "type":"Services"
        }
    ],
    "sg:phone":"+1 718 336 7373",
    "sg:postcode":"11229",
    "sg:province":"NY",
    "sg:tags":[
        "unisex",
        "hair",
        "cosmetologist"
    ],
    "wof:name":"Studio 19 Salon & Spa",
    "wof:placetype":"venue"
},
  "geometry": {"coordinates":[-73.954762,40.61061],"type":"Point"}
}