{
  "type": "Feature",
  "properties": {
    "iso:country":"US",
    "sg:address":"3134 58th St",
    "sg:city":"Woodside",
    "sg:classifiers":[
        {
            "category":"Health Services",
            "subcategory":"Chiropractor",
            "type":"Services"
        }
    ],
    "sg:phone":"+1 718 204 5263",
    "sg:postcode":"11377",
    "sg:province":"NY",
    "wof:name":"Dc Techhnical",
    "wof:placetype":"venue"
},
  "geometry": {"coordinates":[-73.90365799999999,40.756296],"type":"Point"}
}