{
  "type": "Feature",
  "properties": {
    "iso:country":"US",
    "sg:address":"231 W Main St",
    "sg:city":"Elkland",
    "sg:classifiers":[
        {
            "category":"Travel",
            "subcategory":"Hotels & Motels",
            "type":"Entertainment"
        }
    ],
    "sg:phone":"+1 814 258 7144",
    "sg:postcode":"16920",
    "sg:province":"NY",
    "sg:tags":[
        "breakfast",
        "accommodation",
        "bed"
    ],
    "wof:name":"Marigold Manor Bed & Breakfast",
    "wof:placetype":"venue"
},
  "geometry": {"coordinates":[-77.315912,41.987089],"type":"Point"}
}