{
  "type": "Feature",
  "properties": {
    "addr:full":"150 Clearbrook Rd Elmsford NY 10523",
    "addr:housenumber":"150",
    "addr:postcode":"10523",
    "addr:street":"Clearbrook Rd",
    "iso:country":"US",
    "sg:address":"150 Clearbrook Rd",
    "sg:city":"Elmsford",
    "sg:classifiers":[
        {
            "category":"Building & Trades",
            "subcategory":"Plumbing",
            "type":"Services"
        }
    ],
    "sg:phone":"+1 914 592 5768",
    "sg:postcode":"10523",
    "sg:province":"NY",
    "sg:tags":[
        "air",
        "heating",
        "conditioning",
        "contractor"
    ],
    "wof:name":"McQuay Service",
    "wof:placetype":"venue"
},
  "geometry": {"coordinates":[-73.81399500000001,41.073287],"type":"Point"}
}