{
  "type": "Feature",
  "properties": {
    "addr:full":"41 Park Ave New York NY 10016",
    "addr:housenumber":"41",
    "addr:postcode":"10016",
    "addr:street":"Park Ave",
    "iso:country":"US",
    "sg:address":"41 Park Ave",
    "sg:city":"New York",
    "sg:classifiers":[
        {
            "category":"Professional",
            "subcategory":"Employment Agencies",
            "type":"Services"
        }
    ],
    "sg:phone":"+1 212 838 6500",
    "sg:postcode":"10016",
    "sg:province":"NY",
    "sg:tags":[
        "opportunity"
    ],
    "wof:name":"Hurley North Personnel Agency",
    "wof:placetype":"venue"
},
  "geometry": {"coordinates":[-73.979973,40.748794],"type":"Point"}
}