{
  "type": "Feature",
  "properties": {
    "addr:full":"120 Navy Walk Brooklyn NY 11201",
    "addr:housenumber":"120",
    "addr:postcode":"11201",
    "addr:street":"Navy Walk",
    "iso:country":"US",
    "sg:address":"120 Navy Walk",
    "sg:city":"Brooklyn",
    "sg:classifiers":[
        {
            "category":"Real Estate",
            "subcategory":"Real Estate Agent",
            "type":"Services"
        }
    ],
    "sg:phone":"+1 718 624 7316",
    "sg:postcode":"11201",
    "sg:province":"NY",
    "sg:tags":[
        "authorities",
        "housing"
    ],
    "wof:name":"New York City Housing Auth",
    "wof:placetype":"venue"
},
  "geometry": {"coordinates":[-73.980732,40.694673],"type":"Point"}
}