{
  "type": "Feature",
  "properties": {
    "addr:full":"43-14 Main St Lower Level Flushing NY 11355",
    "addr:housenumber":"43-14",
    "addr:postcode":"11355",
    "addr:street":"Main St",
    "iso:country":"US",
    "sg:address":"43-14 Main St Lower Level",
    "sg:city":"Flushing",
    "sg:classifiers":[
        {
            "category":"Professional",
            "type":"Services"
        }
    ],
    "sg:phone":"+1 646 233 3599",
    "sg:postcode":"11355",
    "sg:province":"NY",
    "wof:name":"Four Dimensions",
    "wof:placetype":"venue"
},
  "geometry": {"coordinates":[-73.826694,40.752207],"type":"Point"}
}