{
  "type": "Feature",
  "properties": {
    "addr:full":"4850 Broad Rd Ste 2C Syracuse NY 13215",
    "addr:housenumber":"4850",
    "addr:postcode":"13215",
    "addr:street":"Broad Rd Ste 2C",
    "iso:country":"US",
    "sg:address":"4850 Broad Rd Ste 2C",
    "sg:city":"Syracuse",
    "sg:classifiers":[
        {
            "category":"Personal",
            "subcategory":"Adult",
            "type":"Services"
        }
    ],
    "sg:phone":"+1 315 492 5915",
    "sg:postcode":"13215",
    "sg:province":"NY",
    "sg:tags":[
        "midwife"
    ],
    "sg:website":"http://www.janicebeaman.com",
    "wof:name":"Janice Beaman",
    "wof:placetype":"venue"
},
  "geometry": {"coordinates":[-76.170247,43.006875],"type":"Point"}
}