{
  "type": "Feature",
  "properties": {
    "addr:full":"2031 5 Ave New York NY 10035",
    "addr:housenumber":"2031",
    "addr:postcode":"10035",
    "addr:street":"5 Ave",
    "iso:country":"US",
    "sg:address":"2031 5 Ave",
    "sg:city":"New York",
    "sg:classifiers":[
        {
            "category":"Organizations",
            "subcategory":"Religious Organization",
            "type":"Services"
        }
    ],
    "sg:phone":"+1 212 289 4374",
    "sg:postcode":"10035",
    "sg:province":"NY",
    "sg:tags":[
        "church"
    ],
    "wof:name":"Believers Christian Fellowship",
    "wof:placetype":"venue"
},
  "geometry": {"coordinates":[-73.941771,40.807089],"type":"Point"}
}