{
  "type": "Feature",
  "properties": {
    "iso:country":"US",
    "sg:address":"414 W 56 St",
    "sg:city":"New York",
    "sg:classifiers":[
        {
            "category":"Wholesale",
            "subcategory":"Electrical",
            "type":"Manufacturing & Wholesale Goods"
        }
    ],
    "sg:phone":"+1 212 581 6110",
    "sg:postcode":"10019",
    "sg:province":"NY",
    "sg:tags":[
        "control",
        "security",
        "system"
    ],
    "wof:name":"Metropolitan Protection Grp",
    "wof:placetype":"venue"
},
  "geometry": {"coordinates":[-73.98877899999999,40.768203],"type":"Point"}
}