{
  "type": "Feature",
  "properties": {
    "addr:full":"88 Public Sq Watertown NY 13601",
    "addr:housenumber":"88",
    "addr:postcode":"13601",
    "addr:street":"Public Sq",
    "iso:country":"US",
    "sg:address":"88 Public Sq",
    "sg:city":"Watertown",
    "sg:classifiers":[
        {
            "category":"Shopping",
            "subcategory":"Clothing, Apparel, & Fashions",
            "type":"Retail Goods"
        }
    ],
    "sg:phone":"+1   ",
    "sg:postcode":"13601",
    "sg:province":"NY",
    "sg:tags":[
        "tuxedo",
        "rental"
    ],
    "wof:name":"Bella At Tuxedo Junction",
    "wof:placetype":"venue"
},
  "geometry": {"coordinates":[-75.909976,43.97459],"type":"Point"}
}