{
  "type": "Feature",
  "properties": {
    "iso:country":"US",
    "sg:address":"37 W 57th St",
    "sg:city":"New York",
    "sg:classifiers":[
        {
            "category":"Personal",
            "subcategory":"Massage",
            "type":"Services"
        },
        {
            "category":"Personal",
            "subcategory":"Day Spa",
            "type":"Services"
        }
    ],
    "sg:phone":"+1 212 688 9400",
    "sg:postcode":"10019",
    "sg:province":"NY",
    "sg:website":"www.sothyspa.com",
    "wof:name":"L'Institut Sothys",
    "wof:placetype":"venue"
},
  "geometry": {"coordinates":[-73.975998,40.764211],"type":"Point"}
}