{
  "type": "Feature",
  "properties": {
    "iso:country":"US",
    "sg:address":"870 S Broadway",
    "sg:city":"Hicksville",
    "sg:classifiers":[
        {
            "category":"Retail",
            "subcategory":"Auto Repair",
            "type":"Services"
        }
    ],
    "sg:phone":"+1 516 935 8006",
    "sg:postcode":"11801",
    "sg:province":"NY",
    "sg:tags":[
        "automobile",
        "top",
        "upholstery"
    ],
    "wof:name":"Craftman Auto",
    "wof:placetype":"venue"
},
  "geometry": {"coordinates":[-73.501402,40.747194],"type":"Point"}
}