{
  "type": "Feature",
  "properties": {
    "addr:full":"24740 Jericho Tpke Floral Park NY 11001",
    "addr:housenumber":"24740",
    "addr:postcode":"11001",
    "addr:street":"Jericho Tpke",
    "iso:country":"US",
    "sg:address":"24740 Jericho Tpke",
    "sg:city":"Floral Park",
    "sg:classifiers":[
        {
            "category":"Wholesale",
            "subcategory":"Stationery",
            "type":"Manufacturing & Wholesale Goods"
        },
        {
            "category":"Shopping",
            "type":"Retail Goods"
        }
    ],
    "sg:phone":"+1 516 775 4200",
    "sg:postcode":"11001",
    "sg:province":"NY",
    "sg:tags":[
        "machine",
        "equipment",
        "business",
        "form",
        "system"
    ],
    "sg:website":"www.candlebusiness.com",
    "wof:name":"Candle Business Systems Inc",
    "wof:placetype":"venue"
},
  "geometry": {"coordinates":[-73.72038499999999,40.725474],"type":"Point"}
}