{
  "type": "Feature",
  "properties": {
    "addr:full":"366 Hempstead Ave Malverne NY 11565",
    "addr:housenumber":"366",
    "addr:postcode":"11565",
    "addr:street":"Hempstead Ave",
    "iso:country":"US",
    "sg:address":"366 Hempstead Ave",
    "sg:city":"Malverne",
    "sg:classifiers":[
        {
            "category":"Restaurant",
            "type":"Food & Drink"
        }
    ],
    "sg:menulink":"http://www.allmenus.com/ny/malverne/239079-blue-sky-bistro/menu/",
    "sg:phone":"+1 516 599 9002",
    "sg:postcode":"11565",
    "sg:province":"NY",
    "sg:tags":[
        "american"
    ],
    "wof:name":"Blue Sky Bistro",
    "wof:placetype":"venue"
},
  "geometry": {"coordinates":[-73.667439,40.677883],"type":"Point"}
}