{
  "type": "Feature",
  "properties": {
    "addr:full":"164 E 33rd St New York NY 10016",
    "addr:housenumber":"164",
    "addr:postcode":"10016",
    "addr:street":"E 33Rd St",
    "iso:country":"US",
    "sg:address":"164 E 33rd St",
    "sg:city":"New York",
    "sg:classifiers":[
        {
            "category":"Retail",
            "subcategory":"Laundry & Dry Cleaning",
            "type":"Services"
        }
    ],
    "sg:phone":"+1 212 448 9252",
    "sg:postcode":"10016",
    "sg:province":"NY",
    "wof:name":"New World Cleaners",
    "wof:placetype":"venue"
},
  "geometry": {"coordinates":[-73.979698,40.745499],"type":"Point"}
}