{
  "type": "Feature",
  "properties": {
    "addr:full":"3150 Broadway New York NY 10027",
    "addr:housenumber":"3150",
    "addr:postcode":"10027",
    "addr:street":"Broadway",
    "iso:country":"US",
    "sg:address":"3150 Broadway",
    "sg:city":"New York",
    "sg:classifiers":[
        {
            "category":"Retail",
            "subcategory":"Repair Shop",
            "type":"Services"
        }
    ],
    "sg:phone":"+1 212 315 2020",
    "sg:postcode":"10027",
    "sg:province":"NY",
    "sg:tags":[
        "lock",
        "locksmith"
    ],
    "wof:name":"Mobile Locksmith",
    "wof:placetype":"venue"
},
  "geometry": {"coordinates":[-73.959379,40.813968],"type":"Point"}
}