{
  "type": "Feature",
  "properties": {
    "addr:full":"1250 Ocean Ave Brooklyn NY 11230",
    "addr:housenumber":"1250",
    "addr:postcode":"11230",
    "addr:street":"Ocean Ave",
    "iso:country":"US",
    "sg:address":"1250 Ocean Ave",
    "sg:city":"Brooklyn",
    "sg:classifiers":[
        {
            "category":"Professional",
            "type":"Services"
        }
    ],
    "sg:phone":"+1 718 724 1600",
    "sg:postcode":"11230",
    "sg:province":"NY",
    "sg:tags":[
        "establishment"
    ],
    "wof:name":"Shapels Associates Custom",
    "wof:placetype":"venue"
},
  "geometry": {"coordinates":[-73.95752400000001,40.631553],"type":"Point"}
}