{
  "type": "Feature",
  "properties": {
    "iso:country":"US",
    "sg:address":"1600 Cedar St",
    "sg:city":"Elmira",
    "sg:classifiers":[
        {
            "category":"Professional",
            "subcategory":"Accounting & Tax Preparation",
            "type":"Services"
        }
    ],
    "sg:phone":"+1 607 271 9115",
    "sg:postcode":"14904",
    "sg:province":"NY",
    "sg:tags":[
        "return",
        "filing"
    ],
    "wof:name":"Jackson Hewitt Tax Svc",
    "wof:placetype":"venue"
},
  "geometry": {"coordinates":[-76.79347799999999,42.058167],"type":"Point"}
}