{
  "type": "Feature",
  "properties": {
    "addr:full":"100 Wall St New York NY 10005",
    "addr:housenumber":"100",
    "addr:postcode":"10005",
    "addr:street":"Wall St",
    "iso:country":"US",
    "sg:address":"100 Wall St",
    "sg:city":"New York",
    "sg:classifiers":[
        {
            "category":"Banks & Credit Unions",
            "subcategory":"Bank",
            "type":"Services"
        }
    ],
    "sg:phone":"+1 212 968 9888",
    "sg:postcode":"10005",
    "sg:province":"NY",
    "wof:name":"Taipei Bank of New York Agency",
    "wof:placetype":"venue"
},
  "geometry": {"coordinates":[-74.007301,40.7052],"type":"Point"}
}