{
  "type": "Feature",
  "properties": {
    "iso:country":"US",
    "sg:address":"215 E Main St",
    "sg:city":"Huntington",
    "sg:classifiers":[
        {
            "category":"Wholesale",
            "subcategory":"Electrical",
            "type":"Manufacturing & Wholesale Goods"
        }
    ],
    "sg:phone":"+1 631 385 8171",
    "sg:postcode":"11743",
    "sg:province":"NY",
    "sg:tags":[
        "equipment",
        "electronic",
        "supply"
    ],
    "wof:name":"Bluestar International LTD",
    "wof:placetype":"venue"
},
  "geometry": {"coordinates":[-73.392398,40.882045],"type":"Point"}
}