{
  "type": "Feature",
  "properties": {
    "addr:full":"2 E Park Row Clinton NY 13323",
    "addr:housenumber":"2",
    "addr:postcode":"13323",
    "addr:street":"E Park Row",
    "iso:country":"US",
    "sg:address":"2 E Park Row",
    "sg:city":"Clinton",
    "sg:classifiers":[
        {
            "category":"Social Services",
            "type":"Services"
        }
    ],
    "sg:phone":"+1   ",
    "sg:postcode":"13323",
    "sg:province":"NY",
    "wof:name":"Susan J Alguire Csw",
    "wof:placetype":"venue"
},
  "geometry": {"coordinates":[-75.37804199999999,43.049959],"type":"Point"}
}