{
  "type": "Feature",
  "properties": {
    "addr:full":"183 S Ocean Ave Patchogue NY 11772",
    "addr:housenumber":"183",
    "addr:postcode":"11772",
    "addr:street":"S Ocean Ave",
    "iso:country":"US",
    "sg:address":"183 S Ocean Ave",
    "sg:city":"Patchogue",
    "sg:classifiers":[
        {
            "category":"Food & Beverages",
            "subcategory":"Supermarket",
            "type":"Retail Goods"
        }
    ],
    "sg:phone":"+1 631 654 0240",
    "sg:postcode":"11772",
    "sg:province":"NY",
    "sg:tags":[
        "super",
        "store"
    ],
    "wof:name":"La Confiaza",
    "wof:placetype":"venue"
},
  "geometry": {"coordinates":[-73.013713,40.762463],"type":"Point"}
}