{
  "type": "Feature",
  "properties": {
    "iso:country":"US",
    "sg:address":"198 Wyona St",
    "sg:city":"Brooklyn",
    "sg:classifiers":[
        {
            "category":"Social Services",
            "subcategory":"Child Care",
            "type":"Services"
        }
    ],
    "sg:phone":"+1   ",
    "sg:postcode":"11207",
    "sg:province":"NY",
    "sg:tags":[
        "day"
    ],
    "wof:name":"Under 1 Umbrella Day Care",
    "wof:placetype":"venue"
},
  "geometry": {"coordinates":[-73.893556,40.674239],"type":"Point"}
}