{
  "type": "Feature",
  "properties": {
    "addr:full":"375 State Hwy 59 Airmont NY 10952",
    "addr:housenumber":"375",
    "addr:postcode":"10952",
    "addr:street":"State Hwy 59",
    "iso:country":"US",
    "sg:address":"375 State Hwy 59",
    "sg:city":"Airmont",
    "sg:classifiers":[
        {
            "category":"Shopping",
            "type":"Retail Goods"
        }
    ],
    "sg:phone":"+1 845 356 5624",
    "sg:postcode":"10952",
    "sg:province":"NY",
    "sg:tags":[
        "monument"
    ],
    "wof:name":"Spring Valley Monument",
    "wof:placetype":"venue"
},
  "geometry": {"coordinates":[-74.093024,41.110337],"type":"Point"}
}