{
  "type": "Feature",
  "properties": {
    "addr:full":"168 Mott St New York NY 10013",
    "addr:housenumber":"168",
    "addr:postcode":"10013",
    "addr:street":"Mott St",
    "iso:country":"US",
    "sg:address":"168 Mott St",
    "sg:city":"New York",
    "sg:classifiers":[
        {
            "category":"Banks & Credit Unions",
            "subcategory":"Financial Services",
            "type":"Services"
        }
    ],
    "sg:phone":"+1 212 966 2453",
    "sg:postcode":"10013",
    "sg:province":"NY",
    "wof:name":"Silvermark International",
    "wof:placetype":"venue"
},
  "geometry": {"coordinates":[-73.99610800000001,40.719931],"type":"Point"}
}