{
  "type": "Feature",
  "properties": {
    "addr:full":"204 Martine Ave White Plains NY 10601",
    "addr:housenumber":"204",
    "addr:postcode":"10601",
    "addr:street":"Martine Ave",
    "iso:country":"US",
    "sg:address":"204 Martine Ave",
    "sg:city":"White Plains",
    "sg:classifiers":[
        {
            "category":"Personal",
            "subcategory":"Beauty Salon",
            "type":"Services"
        }
    ],
    "sg:phone":"+1 914 946 9407",
    "sg:postcode":"10601",
    "sg:province":"NY",
    "sg:tags":[
        "shop"
    ],
    "wof:name":"Creation Plus",
    "wof:placetype":"venue"
},
  "geometry": {"coordinates":[-73.764291,41.031787],"type":"Point"}
}