{
  "type": "Feature",
  "properties": {
    "iso:country":"US",
    "sg:address":"101 Broad St",
    "sg:city":"Plattsburgh",
    "sg:classifiers":[
        {
            "category":"Social Services",
            "subcategory":"Child Care",
            "type":"Services"
        }
    ],
    "sg:phone":"+1 518 564 2329",
    "sg:postcode":"12901",
    "sg:province":"NY",
    "sg:tags":[
        "day"
    ],
    "wof:name":"Third Age Adult Day Center",
    "wof:placetype":"venue"
},
  "geometry": {"coordinates":[-73.46396300000001,44.694581],"type":"Point"}
}