{
  "type": "Feature",
  "properties": {
    "iso:country":"US",
    "sg:address":"1 Chatham St",
    "sg:city":"Kinderhook",
    "sg:classifiers":[
        {
            "category":"Shopping",
            "type":"Retail Goods"
        }
    ],
    "sg:phone":"+1   ",
    "sg:postcode":"12106",
    "sg:province":"NY",
    "sg:tags":[
        "merchandise"
    ],
    "wof:name":"Masterpiece Arts & Framing",
    "wof:placetype":"venue"
},
  "geometry": {"coordinates":[-73.69736399999999,42.395879],"type":"Point"}
}