{
  "type": "Feature",
  "properties": {
    "addr:full":"7152 E Genesee St Fayetteville NY 13066",
    "addr:housenumber":"7152",
    "addr:postcode":"13066",
    "addr:street":"E Genesee St",
    "iso:country":"US",
    "sg:address":"7152 E Genesee St",
    "sg:city":"Fayetteville",
    "sg:classifiers":[
        {
            "category":"Shopping",
            "subcategory":"Computers & Home Electronics",
            "type":"Retail Goods"
        }
    ],
    "sg:phone":"+1 315 637 0470",
    "sg:postcode":"13066",
    "sg:province":"NY",
    "sg:tags":[
        "hardware",
        "equipment"
    ],
    "wof:name":"Stoneledge Group Inc",
    "wof:placetype":"venue"
},
  "geometry": {"coordinates":[-76.027872,43.028699],"type":"Point"}
}