{
  "type": "Feature",
  "properties": {
    "iso:country":"US",
    "sg:address":"310 Sea Cliff Ave",
    "sg:city":"Sea Cliff",
    "sg:classifiers":[
        {
            "category":"Shopping",
            "type":"Retail Goods"
        }
    ],
    "sg:phone":"+1   ",
    "sg:postcode":"11579",
    "sg:province":"NY",
    "sg:tags":[
        "merchandise"
    ],
    "wof:name":"Art & Soul Creations Inc",
    "wof:placetype":"venue"
},
  "geometry": {"coordinates":[-73.649108,40.849467],"type":"Point"}
}