{
  "type": "Feature",
  "properties": {
    "addr:full":"3199 123rd Street Flushing NY 11354",
    "addr:housenumber":"3199",
    "addr:postcode":"11354",
    "addr:street":"123Rd Street",
    "iso:country":"US",
    "sg:address":"3199 123rd Street",
    "sg:city":"Flushing",
    "sg:classifiers":[
        {
            "category":"Building & Trades",
            "subcategory":"Plumbing",
            "type":"Services"
        }
    ],
    "sg:phone":"+1 718 961 3066",
    "sg:postcode":"11354",
    "sg:province":"NY",
    "wof:name":"Conservation Contracting Group",
    "wof:placetype":"venue"
},
  "geometry": {"coordinates":[-73.8456,40.768096],"type":"Point"}
}