{
  "type": "Feature",
  "properties": {
    "addr:full":"357 S 14th St Lindenhurst NY 11757",
    "addr:housenumber":"357",
    "addr:postcode":"11757",
    "addr:street":"S 14Th St",
    "iso:country":"US",
    "sg:address":"357 S 14th St",
    "sg:city":"Lindenhurst",
    "sg:classifiers":[
        {
            "category":"Shopping",
            "subcategory":"Computers & Home Electronics",
            "type":"Retail Goods"
        }
    ],
    "sg:phone":"+1   ",
    "sg:postcode":"11757",
    "sg:province":"NY",
    "wof:name":"La Mas Computers Inc",
    "wof:placetype":"venue"
},
  "geometry": {"coordinates":[-73.382769,40.678381],"type":"Point"}
}