{
  "type": "Feature",
  "properties": {
    "addr:full":"21 101st Avenue Brooklyn NY 11208",
    "addr:housenumber":"21",
    "addr:postcode":"11208",
    "addr:street":"101St Avenue",
    "iso:country":"US",
    "sg:address":"21 101st Avenue",
    "sg:city":"Brooklyn",
    "sg:classifiers":[
        {
            "category":"Shopping",
            "subcategory":"Music",
            "type":"Retail Goods"
        }
    ],
    "sg:phone":"+1 718 277 1119",
    "sg:postcode":"11208",
    "sg:province":"NY",
    "sg:tags":[
        "dvd's"
    ],
    "wof:name":"Friend Music",
    "wof:placetype":"venue"
},
  "geometry": {"coordinates":[-73.864035,40.679276],"type":"Point"}
}