{
  "type": "Feature",
  "properties": {
    "addr:full":"198 Delaware Ave Delmar NY 12054",
    "addr:housenumber":"198",
    "addr:postcode":"12054",
    "addr:street":"Delaware Ave",
    "iso:country":"US",
    "sg:address":"198 Delaware Ave",
    "sg:city":"Delmar",
    "sg:classifiers":[
        {
            "category":"Real Estate",
            "subcategory":"Architect",
            "type":"Services"
        }
    ],
    "sg:phone":"+1 518 439 4795",
    "sg:postcode":"12054",
    "sg:province":"NY",
    "sg:tags":[
        "architectural"
    ],
    "wof:name":"Keystone Architectural Svcs",
    "wof:placetype":"venue"
},
  "geometry": {"coordinates":[-73.81482099999999,42.628597],"type":"Point"}
}