{
  "type": "Feature",
  "properties": {
    "addr:full":"2025 Bath Ave Brooklyn NY 11214",
    "addr:housenumber":"2025",
    "addr:postcode":"11214",
    "addr:street":"Bath Ave",
    "iso:country":"US",
    "sg:address":"2025 Bath Ave",
    "sg:city":"Brooklyn",
    "sg:classifiers":[
        {
            "category":"Retail",
            "subcategory":"Repair Shop",
            "type":"Services"
        }
    ],
    "sg:phone":"+1 718 766 2413",
    "sg:postcode":"11214",
    "sg:province":"NY",
    "sg:tags":[
        "lock",
        "locksmith"
    ],
    "wof:name":"24 Hour Emergency Locksmith",
    "wof:placetype":"venue"
},
  "geometry": {"coordinates":[-74.000162,40.600491],"type":"Point"}
}