{
  "type": "Feature",
  "properties": {
    "addr:full":"71-73 Yellowstone Blvd Queens NY 11375",
    "addr:housenumber":"71-73",
    "addr:postcode":"11375",
    "addr:street":"Yellowstone Blvd",
    "iso:country":"US",
    "sg:address":"71-73 Yellowstone Blvd",
    "sg:city":"Queens",
    "sg:classifiers":[
        {
            "category":"Personal",
            "subcategory":"Nail Salon",
            "type":"Services"
        }
    ],
    "sg:phone":"+1 718 813 3811",
    "sg:postcode":"11375",
    "sg:province":"NY",
    "sg:website":"divame.vpweb.com/",
    "wof:name":"Diva-Licious Nail and Spa",
    "wof:placetype":"venue"
},
  "geometry": {"coordinates":[-73.855203,40.720737],"type":"Point"}
}