{
  "type": "Feature",
  "properties": {
    "addr:full":"1113 Harlem Rd Buffalo NY 14227",
    "addr:housenumber":"1113",
    "addr:postcode":"14227",
    "addr:street":"Harlem Rd",
    "iso:country":"US",
    "sg:address":"1113 Harlem Rd",
    "sg:city":"Buffalo",
    "sg:classifiers":[
        {
            "category":"Autos & Motor Vehicles",
            "subcategory":"Auto Supplies",
            "type":"Retail Goods"
        }
    ],
    "sg:phone":"+1   ",
    "sg:postcode":"14227",
    "sg:province":"NY",
    "wof:name":"Premier Car Audio",
    "wof:placetype":"venue"
},
  "geometry": {"coordinates":[-78.787178,42.871461],"type":"Point"}
}