{
  "type": "Feature",
  "properties": {
    "addr:full":"450 William St Buffalo NY 14204",
    "addr:housenumber":"450",
    "addr:postcode":"14204",
    "addr:street":"William St",
    "iso:country":"US",
    "sg:address":"450 William St",
    "sg:city":"Buffalo",
    "sg:classifiers":[
        {
            "category":"Organizations",
            "subcategory":"Religious Organization",
            "type":"Services"
        }
    ],
    "sg:phone":"+1 716 855 3746",
    "sg:postcode":"14204",
    "sg:province":"NY",
    "sg:tags":[
        "church"
    ],
    "wof:name":"Greater St Matthew Missionary",
    "wof:placetype":"venue"
},
  "geometry": {"coordinates":[-78.85424,42.885161],"type":"Point"}
}