{
  "type": "Feature",
  "properties": {
    "addr:full":"112 North Ave New Rochelle NY 10801",
    "addr:housenumber":"112",
    "addr:postcode":"10801",
    "addr:street":"North Ave",
    "iso:country":"US",
    "sg:address":"112 North Ave",
    "sg:city":"New Rochelle",
    "sg:classifiers":[
        {
            "category":"Social Services",
            "type":"Services"
        }
    ],
    "sg:phone":"+1 914 636 9120",
    "sg:postcode":"10801",
    "sg:province":"NY",
    "sg:tags":[
        "organization",
        "welfare"
    ],
    "wof:name":"American Legion",
    "wof:placetype":"venue"
},
  "geometry": {"coordinates":[-73.779161,40.907679],"type":"Point"}
}