{
  "type": "Feature",
  "properties": {
    "iso:country":"US",
    "sg:address":"408 Easton St",
    "sg:city":"Ronkonkoma",
    "sg:classifiers":[
        {
            "category":"Wholesale",
            "subcategory":"Chemicals & Plastics",
            "type":"Manufacturing & Wholesale Goods"
        }
    ],
    "sg:phone":"+1 631 471 2468",
    "sg:postcode":"11779",
    "sg:province":"NY",
    "wof:name":"Texkem",
    "wof:placetype":"venue"
},
  "geometry": {"coordinates":[-73.141114,40.802423],"type":"Point"}
}