{
  "type": "Feature",
  "properties": {
    "addr:full":"1468 Madison Ave New York NY 10029",
    "addr:housenumber":"1468",
    "addr:postcode":"10029",
    "addr:street":"Madison Ave",
    "iso:country":"US",
    "sg:address":"1468 Madison Ave",
    "sg:city":"New York",
    "sg:classifiers":[
        {
            "category":"Professional",
            "subcategory":"Research",
            "type":"Services"
        }
    ],
    "sg:phone":"+1 212 241 8484",
    "sg:postcode":"10029",
    "sg:province":"NY",
    "sg:tags":[
        "development",
        "laboratory"
    ],
    "wof:name":"Mt Sinai Hospital School-Med",
    "wof:placetype":"venue"
},
  "geometry": {"coordinates":[-73.952743,40.789168],"type":"Point"}
}