{
  "type": "Feature",
  "properties": {
    "addr:full":"1247 Taft Ave Endicott NY 13760",
    "addr:housenumber":"1247",
    "addr:postcode":"13760",
    "addr:street":"Taft Ave",
    "iso:country":"US",
    "sg:address":"1247 Taft Ave",
    "sg:city":"Endicott",
    "sg:classifiers":[
        {
            "category":"Professional",
            "subcategory":"Computer Services",
            "type":"Services"
        }
    ],
    "sg:phone":"+1 607 748 4145",
    "sg:postcode":"13760",
    "sg:province":"NY",
    "sg:tags":[
        "development",
        "consulting",
        "software"
    ],
    "sg:website":"www.synapseinfo.com",
    "wof:name":"Synapse Information Resources",
    "wof:placetype":"venue"
},
  "geometry": {"coordinates":[-76.04492399999999,42.144731],"type":"Point"}
}