{
  "type": "Feature",
  "properties": {
    "addr:full":"114 S Main St Belfast NY 14711",
    "addr:housenumber":"114",
    "addr:postcode":"14711",
    "addr:street":"S Main St",
    "iso:country":"US",
    "sg:address":"114 S Main St",
    "sg:city":"Belfast",
    "sg:classifiers":[
        {
            "category":"Shopping",
            "subcategory":"Hobbies, Toys, & Games",
            "type":"Retail Goods"
        }
    ],
    "sg:phone":"+1   ",
    "sg:postcode":"14711",
    "sg:province":"NY",
    "wof:name":"Delectable Collectables",
    "wof:placetype":"venue"
},
  "geometry": {"coordinates":[-78.111879,42.340422],"type":"Point"}
}