{
  "type": "Feature",
  "properties": {
    "addr:full":"212 Fullerton Ave Newburgh NY 12550",
    "addr:housenumber":"212",
    "addr:postcode":"12550",
    "addr:street":"Fullerton Ave",
    "iso:country":"US",
    "sg:address":"212 Fullerton Ave",
    "sg:city":"Newburgh",
    "sg:classifiers":[
        {
            "category":"Freight",
            "type":"Transportation"
        }
    ],
    "sg:phone":"+1 845 562 1523",
    "sg:postcode":"12550",
    "sg:province":"NY",
    "sg:tags":[
        "trucking"
    ],
    "wof:name":"SWC Trucking",
    "wof:placetype":"venue"
},
  "geometry": {"coordinates":[-74.0256,41.508146],"type":"Point"}
}