{
  "type": "Feature",
  "properties": {
    "iso:country":"US",
    "sg:address":"150 Main St",
    "sg:city":"Oneida",
    "sg:classifiers":[
        {
            "category":"Professional",
            "subcategory":"Lawyer & Legal Services",
            "type":"Services"
        }
    ],
    "sg:phone":"+1 315 363 2270",
    "sg:postcode":"13421",
    "sg:province":"NY",
    "sg:tags":[
        "attorney"
    ],
    "wof:name":"William F Wilcox",
    "wof:placetype":"venue"
},
  "geometry": {"coordinates":[-75.651777,43.094833],"type":"Point"}
}