{
  "type": "Feature",
  "properties": {
    "iso:country":"US",
    "sg:address":"2174 Mitchell St",
    "sg:city":"Bellmore",
    "sg:classifiers":[
        {
            "category":"Retail",
            "subcategory":"Portrait Studio",
            "type":"Services"
        },
        {
            "category":"Professional",
            "subcategory":"Art Services",
            "type":"Services"
        }
    ],
    "sg:phone":"+1 516 221 4058",
    "sg:postcode":"11710",
    "sg:province":"NY",
    "sg:tags":[
        "photographer",
        "photography",
        "commercial",
        "m",
        "photo"
    ],
    "wof:name":"Photographic Creations Inc",
    "wof:placetype":"venue"
},
  "geometry": {"coordinates":[-73.54209400000001,40.668841],"type":"Point"}
}