{
  "type": "Feature",
  "properties": {
    "iso:country":"US",
    "sg:address":"4010 Austin Blvd",
    "sg:city":"Island Park",
    "sg:classifiers":[
        {
            "category":"Retail",
            "subcategory":"Laundry & Dry Cleaning",
            "type":"Services"
        }
    ],
    "sg:phone":"+1 516 431 2424",
    "sg:postcode":"11558",
    "sg:province":"NY",
    "sg:tags":[
        "cleaners"
    ],
    "wof:name":"J & J Cleaners",
    "wof:placetype":"venue"
},
  "geometry": {"coordinates":[-73.64424099999999,40.612117],"type":"Point"}
}