{
  "type": "Feature",
  "properties": {
    "addr:full":"230 Ridgecrest Rd Briarcliff Manor NY 10510",
    "addr:housenumber":"230",
    "addr:postcode":"10510",
    "addr:street":"Ridgecrest Rd",
    "iso:country":"US",
    "sg:address":"230 Ridgecrest Rd",
    "sg:city":"Briarcliff Manor",
    "sg:classifiers":[
        {
            "category":"Communications",
            "subcategory":"Film & Video Production",
            "type":"Services"
        }
    ],
    "sg:phone":"+1 914 944 3060",
    "sg:postcode":"10510",
    "sg:province":"NY",
    "sg:tags":[
        "motion",
        "distribution",
        "legal"
    ],
    "wof:name":"Fiscal Dynamics",
    "wof:placetype":"venue"
},
  "geometry": {"coordinates":[-73.858559,41.13421],"type":"Point"}
}