{
  "type": "Feature",
  "properties": {
    "iso:country":"US",
    "sg:address":"125 Park Ave",
    "sg:city":"New York",
    "sg:classifiers":[
        {
            "category":"Freight",
            "type":"Transportation"
        }
    ],
    "sg:phone":"+1 212 557 2966",
    "sg:postcode":"10017",
    "sg:province":"NY",
    "sg:tags":[
        "courier"
    ],
    "wof:name":"Dart Courier",
    "wof:placetype":"venue"
},
  "geometry": {"coordinates":[-73.97781999999999,40.751706],"type":"Point"}
}