{
  "type": "Feature",
  "properties": {
    "iso:country":"US",
    "sg:address":"280 River Rd",
    "sg:city":"Peru",
    "sg:classifiers":[
        {
            "category":"Farming",
            "subcategory":"Dairy Farm",
            "type":"Manufacturing & Wholesale Goods"
        }
    ],
    "sg:phone":"+1 518 643 7803",
    "sg:postcode":"12972",
    "sg:province":"NY",
    "wof:name":"B C F Farms",
    "wof:placetype":"venue"
},
  "geometry": {"coordinates":[-73.553231,44.563132],"type":"Point"}
}