{
  "type": "Feature",
  "properties": {
    "addr:full":"105 Gebhardt Ave Syracuse NY 13208",
    "addr:housenumber":"105",
    "addr:postcode":"13208",
    "addr:street":"Gebhardt Ave",
    "iso:country":"US",
    "sg:address":"105 Gebhardt Ave",
    "sg:city":"Syracuse",
    "sg:classifiers":[
        {
            "category":"Building & Trades",
            "subcategory":"Plumbing",
            "type":"Services"
        }
    ],
    "sg:phone":"+1 315 434 9262",
    "sg:postcode":"13208",
    "sg:province":"NY",
    "wof:name":"McDonald Plumbing & Heating",
    "wof:placetype":"venue"
},
  "geometry": {"coordinates":[-76.153475,43.061923],"type":"Point"}
}