{
  "type": "Feature",
  "properties": {
    "iso:country":"US",
    "sg:address":"128 Ridge St",
    "sg:city":"Glens Falls",
    "sg:classifiers":[
        {
            "category":"Shopping",
            "subcategory":"Pharmacy",
            "type":"Retail Goods"
        }
    ],
    "sg:phone":"+1   ",
    "sg:postcode":"12801",
    "sg:province":"NY",
    "sg:tags":[
        "drug",
        "store"
    ],
    "wof:name":"Eckerd",
    "wof:placetype":"venue"
},
  "geometry": {"coordinates":[-73.643717,43.313662],"type":"Point"}
}