{
  "type": "Feature",
  "properties": {
    "iso:country":"US",
    "sg:address":"4208 State Hwy 50",
    "sg:city":"Saratoga Springs",
    "sg:classifiers":[
        {
            "category":"Food & Beverages",
            "subcategory":"Liquor & Beverages",
            "type":"Retail Goods"
        }
    ],
    "sg:phone":"+1 518 581 3181",
    "sg:postcode":"12866",
    "sg:province":"NY",
    "wof:name":"Jones & Fifty Wine & Liquor",
    "wof:placetype":"venue"
},
  "geometry": {"coordinates":[-73.72079100000001,43.123187],"type":"Point"}
}