{
  "type": "Feature",
  "properties": {
    "addr:full":"19 Murray St New York NY 10007",
    "addr:housenumber":"19",
    "addr:postcode":"10007",
    "addr:street":"Murray St",
    "iso:country":"US",
    "sg:address":"19 Murray St",
    "sg:city":"New York",
    "sg:classifiers":[
        {
            "category":"Real Estate",
            "subcategory":"Architect",
            "type":"Services"
        }
    ],
    "sg:phone":"+1 212 571 9154",
    "sg:postcode":"10007",
    "sg:province":"NY",
    "sg:tags":[
        "architecture"
    ],
    "wof:name":"Dennis Belfiore Architect PC",
    "wof:placetype":"venue"
},
  "geometry": {"coordinates":[-74.008062,40.713415],"type":"Point"}
}