{
  "type": "Feature",
  "properties": {
    "iso:country":"US",
    "sg:address":"707 Owego Rd",
    "sg:city":"Candor",
    "sg:phone":"+1 607 659 7707",
    "sg:postcode":"13743",
    "sg:province":"NY",
    "sg:tags":[
        "vegetable",
        "farm"
    ],
    "sg:website":"www.ironkettlefarm.com",
    "wof:name":"Iron Kettle Farm",
    "wof:placetype":"venue"
},
  "geometry": {"coordinates":[-76.315264,42.196904],"type":"Point"}
}