{
  "type": "Feature",
  "properties": {
    "addr:full":"201 Edward Curry Ave Staten Island NY 10314",
    "addr:housenumber":"201",
    "addr:postcode":"10314",
    "addr:street":"Edward Curry Ave",
    "iso:country":"US",
    "sg:address":"201 Edward Curry Ave",
    "sg:city":"Staten Island",
    "sg:classifiers":[
        {
            "category":"Professional",
            "subcategory":"Computer Services",
            "type":"Services"
        }
    ],
    "sg:postcode":"10314",
    "sg:province":"NY",
    "sg:website":"http://www.risingresults.com",
    "wof:name":"Rising Results",
    "wof:placetype":"venue"
},
  "geometry": {"coordinates":[-74.178968,40.609048],"type":"Point"}
}