{
  "type": "Feature",
  "properties": {
    "iso:country":"US",
    "sg:address":"160 W End Ave",
    "sg:city":"New York",
    "sg:classifiers":[
        {
            "category":"Local Transit",
            "type":"Transportation"
        }
    ],
    "sg:phone":"+1   ",
    "sg:postcode":"10023",
    "sg:province":"NY",
    "sg:tags":[
        "passenger"
    ],
    "wof:name":"Es Limousine",
    "wof:placetype":"venue"
},
  "geometry": {"coordinates":[-73.98568299999999,40.77801],"type":"Point"}
}