{
  "type": "Feature",
  "properties": {
    "addr:full":"3035 Co Rd 47 Norwood NY 13668",
    "addr:housenumber":"3035;47",
    "addr:postcode":"13668",
    "addr:street":"Co Rd",
    "iso:country":"US",
    "sg:address":"3035 Co Rd 47",
    "sg:city":"Norwood",
    "sg:classifiers":[
        {
            "category":"Social Services",
            "type":"Services"
        }
    ],
    "sg:phone":"+1 315 353 7307",
    "sg:postcode":"13668",
    "sg:province":"NY",
    "sg:tags":[
        "organization",
        "welfare"
    ],
    "wof:name":"Habitate-Humanity Raquette Vly",
    "wof:placetype":"venue"
},
  "geometry": {"coordinates":[-74.93550999999999,44.77002],"type":"Point"}
}