{
  "type": "Feature",
  "properties": {
    "iso:country":"US",
    "sg:address":"183 Webster St",
    "sg:city":"Malone",
    "sg:classifiers":[
        {
            "category":"Education",
            "subcategory":"School",
            "type":"Public Place"
        }
    ],
    "sg:phone":"+1 518 483 7802",
    "sg:postcode":"12953",
    "sg:province":"NY",
    "wof:name":"Davis Elementary School",
    "wof:placetype":"venue"
},
  "geometry": {"coordinates":[-74.29672100000001,44.840233],"type":"Point"}
}