{
  "type": "Feature",
  "properties": {
    "addr:full":"119 Broadway Hicksville NY 11801",
    "addr:housenumber":"119",
    "addr:postcode":"11801",
    "addr:street":"Broadway",
    "iso:country":"US",
    "sg:address":"119 Broadway",
    "sg:city":"Hicksville",
    "sg:classifiers":[
        {
            "category":"Recreation",
            "type":"Entertainment"
        }
    ],
    "sg:phone":"+1 516 606 1382",
    "sg:postcode":"11801",
    "sg:province":"NY",
    "sg:tags":[
        "aquarium"
    ],
    "wof:name":"Aquariums Alive",
    "wof:placetype":"venue"
},
  "geometry": {"coordinates":[-73.52272499999999,40.766835],"type":"Point"}
}