{
  "type": "Feature",
  "properties": {
    "iso:country":"US",
    "sg:address":"82 Old River Rd",
    "sg:city":"North Creek",
    "sg:classifiers":[
        {
            "category":"Building & Trades",
            "subcategory":"Construction",
            "type":"Services"
        }
    ],
    "sg:phone":"+1 518 251 3269",
    "sg:postcode":"12853",
    "sg:province":"NY",
    "sg:tags":[
        "house"
    ],
    "wof:name":"Persons Construction",
    "wof:placetype":"venue"
},
  "geometry": {"coordinates":[-73.99575400000001,43.708438],"type":"Point"}
}