{
  "type": "Feature",
  "properties": {
    "iso:country":"US",
    "sg:address":"208 Tarrytown Rd",
    "sg:city":"White Plains",
    "sg:classifiers":[
        {
            "category":"Retail",
            "subcategory":"Car Wash",
            "type":"Services"
        }
    ],
    "sg:phone":"+1 914 684 8552",
    "sg:postcode":"10607",
    "sg:province":"NY",
    "sg:tags":[
        "carwash"
    ],
    "wof:name":"Route 119 Hillside Corp",
    "wof:placetype":"venue"
},
  "geometry": {"coordinates":[-73.78729199999999,41.040519],"type":"Point"}
}