{
  "type": "Feature",
  "properties": {
    "iso:country":"US",
    "sg:address":"84 Johnson Pl",
    "sg:city":"Oceanside",
    "sg:classifiers":[
        {
            "category":"Shopping",
            "subcategory":"Used Merchandise",
            "type":"Retail Goods"
        }
    ],
    "sg:phone":"+1 516 766 3302",
    "sg:postcode":"11572",
    "sg:province":"NY",
    "sg:tags":[
        "material"
    ],
    "wof:name":"John Bruzzo Inc",
    "wof:placetype":"venue"
},
  "geometry": {"coordinates":[-73.633306,40.650363],"type":"Point"}
}