{
  "type": "Feature",
  "properties": {
    "addr:full":"2280 Burnett St Brooklyn NY 11229",
    "addr:housenumber":"2280",
    "addr:postcode":"11229",
    "addr:street":"Burnett St",
    "iso:country":"US",
    "sg:address":"2280 Burnett St",
    "sg:city":"Brooklyn",
    "sg:classifiers":[
        {
            "category":"Personal",
            "type":"Services"
        }
    ],
    "sg:phone":"+1 718 769 8122",
    "sg:postcode":"11229",
    "sg:province":"NY",
    "sg:tags":[
        "electrolysis"
    ],
    "wof:name":"Carol Stevens",
    "wof:placetype":"venue"
},
  "geometry": {"coordinates":[-73.932917,40.602339],"type":"Point"}
}