{
  "type": "Feature",
  "properties": {
    "addr:full":"315 W Klein Rd Buffalo NY 14221",
    "addr:housenumber":"315",
    "addr:postcode":"14221",
    "addr:street":"W Klein Rd",
    "iso:country":"US",
    "sg:address":"315 W Klein Rd",
    "sg:city":"Buffalo",
    "sg:classifiers":[
        {
            "category":"Building & Trades",
            "subcategory":"Construction",
            "type":"Services"
        }
    ],
    "sg:phone":"+1 716 689 2409",
    "sg:postcode":"14221",
    "sg:province":"NY",
    "sg:tags":[
        "house",
        "general",
        "residential",
        "contractor"
    ],
    "wof:name":"Barbalato Builders Inc",
    "wof:placetype":"venue"
},
  "geometry": {"coordinates":[-78.745994,43.002082],"type":"Point"}
}