{
  "type": "Feature",
  "properties": {
    "iso:country":"US",
    "sg:address":"330 Riverside Dr",
    "sg:city":"New York",
    "sg:classifiers":[
        {
            "category":"Manufacturing",
            "subcategory":"Tools & Machinery",
            "type":"Manufacturing & Wholesale Goods"
        }
    ],
    "sg:phone":"+1   ",
    "sg:postcode":"10025",
    "sg:province":"NY",
    "sg:tags":[
        "pattern",
        "industrial",
        "mfg"
    ],
    "wof:name":"Health Patterns LLC",
    "wof:placetype":"venue"
},
  "geometry": {"coordinates":[-73.97004699999999,40.802265],"type":"Point"}
}