{
  "type": "Feature",
  "properties": {
    "addr:full":"1194 Deer Park Ave North Babylon NY 11703",
    "addr:housenumber":"1194",
    "addr:postcode":"11703",
    "addr:street":"Deer Park Ave North",
    "iso:country":"US",
    "sg:address":"1194 Deer Park Ave",
    "sg:city":"North Babylon",
    "sg:classifiers":[
        {
            "category":"Ice Cream",
            "type":"Food & Drink"
        }
    ],
    "sg:menulink":"http://www.allmenus.com/ny/babylon/98827-friendlys-restaurant/menu/",
    "sg:phone":"+1 516 586 7545",
    "sg:postcode":"11703",
    "sg:province":"NY",
    "sg:tags":[
        "burger",
        "american"
    ],
    "wof:name":"Friendly's Restaurant",
    "wof:placetype":"venue"
},
  "geometry": {"coordinates":[-73.32065900000001,40.736837],"type":"Point"}
}