{
  "type": "Feature",
  "properties": {
    "iso:country":"US",
    "sg:address":"1532 Maiden Ln",
    "sg:city":"Rochester",
    "sg:classifiers":[
        {
            "category":"Food & Beverages",
            "subcategory":"Fruits & Vegetables",
            "type":"Retail Goods"
        }
    ],
    "sg:phone":"+1 585 227 4198",
    "sg:postcode":"14626",
    "sg:province":"NY",
    "sg:tags":[
        "farm",
        "market"
    ],
    "wof:name":"De Coninck Farm Market",
    "wof:placetype":"venue"
},
  "geometry": {"coordinates":[-77.684629,43.223731],"type":"Point"}
}