{
  "type": "Feature",
  "properties": {
    "addr:full":"331 East 10th Street New York NY 10009",
    "addr:housenumber":"331",
    "addr:postcode":"10009",
    "addr:street":"East 10Th Street",
    "iso:country":"US",
    "sg:address":"331 East 10th Street",
    "sg:city":"New York",
    "sg:classifiers":[
        {
            "category":"Education",
            "subcategory":"Library",
            "type":"Public Place"
        }
    ],
    "sg:phone":"+1 212 228 4747",
    "sg:postcode":"10009",
    "sg:province":"NY",
    "sg:website":"www.nypl.org/branch/local/man/ts...",
    "wof:name":"New York Public Library - Tompkins Square Branch",
    "wof:placetype":"venue"
},
  "geometry": {"coordinates":[-73.980417,40.727329],"type":"Point"}
}