{
  "type": "Feature",
  "properties": {
    "iso:country":"US",
    "sg:address":"658 Grand St",
    "sg:city":"Brooklyn",
    "sg:classifiers":[
        {
            "category":"Shopping",
            "subcategory":"Thrift Store",
            "type":"Retail Goods"
        }
    ],
    "sg:phone":"+1 718 218 6028",
    "sg:postcode":"11211",
    "sg:province":"NY",
    "wof:name":"Drawing Down the Moon",
    "wof:placetype":"venue"
},
  "geometry": {"coordinates":[-73.946049,40.711338],"type":"Point"}
}