{
  "type": "Feature",
  "properties": {
    "iso:country":"US",
    "sg:address":"351 W Mountain Rd",
    "sg:city":"Queensbury",
    "sg:classifiers":[
        {
            "category":"Wholesale",
            "subcategory":"Petroleum",
            "type":"Manufacturing & Wholesale Goods"
        }
    ],
    "sg:phone":"+1   ",
    "sg:postcode":"12804",
    "sg:province":"NY",
    "sg:tags":[
        "pipeline",
        "operation"
    ],
    "wof:name":"Thomas Flahenty",
    "wof:placetype":"venue"
},
  "geometry": {"coordinates":[-73.72162299999999,43.282353],"type":"Point"}
}