{
  "type": "Feature",
  "properties": {
    "iso:country":"US",
    "sg:address":"2 Minerva Ln",
    "sg:city":"Centereach",
    "sg:classifiers":[
        {
            "category":"Professional",
            "subcategory":"Detective & Security Services",
            "type":"Services"
        }
    ],
    "sg:phone":"+1 631 774 7644",
    "sg:postcode":"11720",
    "sg:province":"NY",
    "sg:tags":[
        "information",
        "bureau"
    ],
    "wof:name":"Schuyler Marketing Servi",
    "wof:placetype":"venue"
},
  "geometry": {"coordinates":[-73.097748,40.85347],"type":"Point"}
}