{
  "type": "Feature",
  "properties": {
    "iso:country":"US",
    "sg:address":"2 Todd Ct",
    "sg:city":"Yaphank",
    "sg:classifiers":[
        {
            "category":"Wholesale",
            "subcategory":"Home Furnishings",
            "type":"Manufacturing & Wholesale Goods"
        }
    ],
    "sg:phone":"+1 631 650 1000",
    "sg:postcode":"11980",
    "sg:province":"NY",
    "sg:tags":[
        "picture",
        "frame"
    ],
    "sg:website":"www.framerica.com",
    "wof:name":"Framerica Corp",
    "wof:placetype":"venue"
},
  "geometry": {"coordinates":[-72.94388499999999,40.810877],"type":"Point"}
}