{
  "type": "Feature",
  "properties": {
    "iso:country":"US",
    "sg:address":"34 Christen Ct",
    "sg:city":"Lancaster",
    "sg:classifiers":[
        {
            "category":"Manufacturing",
            "subcategory":"Printing",
            "type":"Manufacturing & Wholesale Goods"
        }
    ],
    "sg:phone":"+1   ",
    "sg:postcode":"14086",
    "sg:province":"NY",
    "sg:tags":[
        "periodical"
    ],
    "wof:name":"Drag Racing News",
    "wof:placetype":"venue"
},
  "geometry": {"coordinates":[-78.667518,42.886521],"type":"Point"}
}