{
  "type": "Feature",
  "properties": {
    "addr:full":"5 E 19 St New York NY 10003",
    "addr:housenumber":"5;19",
    "addr:postcode":"10003",
    "addr:street":"E",
    "iso:country":"US",
    "sg:address":"5 E 19 St",
    "sg:city":"New York",
    "sg:classifiers":[
        {
            "category":"Professional",
            "subcategory":"Computer Services",
            "type":"Services"
        }
    ],
    "sg:phone":"+1   ",
    "sg:postcode":"10003",
    "sg:province":"NY",
    "sg:tags":[
        "development",
        "web",
        "design",
        "site"
    ],
    "wof:name":"Digital Madness",
    "wof:placetype":"venue"
},
  "geometry": {"coordinates":[-73.990155,40.738687],"type":"Point"}
}