{
  "type": "Feature",
  "properties": {
    "addr:full":"69 E Mount Airy Rd Croton On Hudson NY 10520",
    "addr:housenumber":"69",
    "addr:postcode":"10520",
    "addr:street":"E Mount Airy Rd",
    "iso:country":"US",
    "sg:address":"69 E Mount Airy Rd",
    "sg:city":"Croton On Hudson",
    "sg:classifiers":[
        {
            "category":"Building & Trades",
            "subcategory":"Plumbing",
            "type":"Services"
        }
    ],
    "sg:phone":"+1 914 271 4116",
    "sg:postcode":"10520",
    "sg:province":"NY",
    "sg:tags":[
        "mechanical",
        "contractor"
    ],
    "wof:name":"K-Mac Mechanical",
    "wof:placetype":"venue"
},
  "geometry": {"coordinates":[-73.875659,41.226924],"type":"Point"}
}