{
  "type": "Feature",
  "properties": {
    "addr:full":"112 Brooklea Dr Fayetteville NY 13066",
    "addr:housenumber":"112",
    "addr:postcode":"13066",
    "addr:street":"Brooklea Dr",
    "iso:country":"US",
    "sg:address":"112 Brooklea Dr",
    "sg:city":"Fayetteville",
    "sg:classifiers":[
        {
            "category":"Food & Beverages",
            "subcategory":"Liquor & Beverages",
            "type":"Retail Goods"
        }
    ],
    "sg:phone":"+1 315 637 1504",
    "sg:postcode":"13066",
    "sg:province":"NY",
    "sg:tags":[
        "alcoholic"
    ],
    "wof:name":"Deckers Wine & Spirits",
    "wof:placetype":"venue"
},
  "geometry": {"coordinates":[-76.012128,43.030632],"type":"Point"}
}