{
  "type": "Feature",
  "properties": {
    "iso:country":"US",
    "sg:address":"191 Banker Rd",
    "sg:city":"Plattsburgh",
    "sg:classifiers":[
        {
            "category":"Restaurant",
            "type":"Food & Drink"
        }
    ],
    "sg:phone":"+1 518 825 2000",
    "sg:postcode":"12962",
    "sg:province":"NY",
    "sg:tags":[
        "out"
    ],
    "wof:name":"Home Bistro Foods",
    "wof:placetype":"venue"
},
  "geometry": {"coordinates":[-73.544085,44.701266],"type":"Point"}
}