{
  "type": "Feature",
  "properties": {
    "addr:full":"12 Hallock Dr Washingtonville NY 10992",
    "addr:housenumber":"12",
    "addr:postcode":"10992",
    "addr:street":"Hallock Dr",
    "iso:country":"US",
    "sg:address":"12 Hallock Dr",
    "sg:city":"Washingtonville",
    "sg:classifiers":[
        {
            "category":"Shopping",
            "subcategory":"Used Merchandise",
            "type":"Retail Goods"
        }
    ],
    "sg:phone":"+1 845 496 8015",
    "sg:postcode":"10992",
    "sg:province":"NY",
    "sg:tags":[
        "shop",
        "thrift"
    ],
    "wof:name":"Country Store",
    "wof:placetype":"venue"
},
  "geometry": {"coordinates":[-74.152584,41.424934],"type":"Point"}
}