{
  "type": "Feature",
  "properties": {
    "iso:country":"US",
    "sg:address":"24 Scarsdale Ave",
    "sg:city":"Scarsdale",
    "sg:classifiers":[
        {
            "category":"Food & Beverages",
            "subcategory":"Groceries & Convenience Stores",
            "type":"Retail Goods"
        }
    ],
    "sg:phone":"+1   ",
    "sg:postcode":"10583",
    "sg:province":"NY",
    "wof:name":"Dynamic Market Initiatives",
    "wof:placetype":"venue"
},
  "geometry": {"coordinates":[-73.811723,40.977933],"type":"Point"}
}