{
  "type": "Feature",
  "properties": {
    "addr:full":"7211 10th Ave Brooklyn NY 11228",
    "addr:housenumber":"7211",
    "addr:postcode":"11228",
    "addr:street":"10Th Ave",
    "iso:country":"US",
    "sg:address":"7211 10th Ave",
    "sg:city":"Brooklyn",
    "sg:classifiers":[
        {
            "category":"Organizations",
            "subcategory":"Professional Association",
            "type":"Services"
        }
    ],
    "sg:phone":"+1   ",
    "sg:postcode":"11228",
    "sg:province":"NY",
    "wof:name":"Federtion of Assod Lconion Soc",
    "wof:placetype":"venue"
},
  "geometry": {"coordinates":[-74.01272299999999,40.625467],"type":"Point"}
}