{
  "type": "Feature",
  "properties": {
    "iso:country":"US",
    "sg:address":"450 Fashion Ave",
    "sg:city":"New York",
    "sg:classifiers":[
        {
            "category":"Professional",
            "subcategory":"Accounting & Tax Preparation",
            "type":"Services"
        }
    ],
    "sg:phone":"+1 212 594 6970",
    "sg:postcode":"10123",
    "sg:province":"NY",
    "sg:tags":[
        "accountant"
    ],
    "wof:name":"Jeffrey J Coren CPA",
    "wof:placetype":"venue"
},
  "geometry": {"coordinates":[-73.990134,40.751659],"type":"Point"}
}