{
  "type": "Feature",
  "properties": {
    "addr:full":"5501 Broadway Bronx NY 10463",
    "addr:housenumber":"5501",
    "addr:postcode":"10463",
    "addr:street":"Broadway",
    "iso:country":"US",
    "sg:address":"5501 Broadway",
    "sg:city":"Bronx",
    "sg:classifiers":[
        {
            "category":"Ice Cream",
            "type":"Food & Drink"
        }
    ],
    "sg:menulink":"http://www.allmenus.com/ny/bronx/243497-baskin-robbins/menu/",
    "sg:phone":"+1 718 432 2606",
    "sg:postcode":"10463",
    "sg:province":"NY",
    "sg:tags":[
        "american"
    ],
    "wof:name":"Baskin-Robbins",
    "wof:placetype":"venue"
},
  "geometry": {"coordinates":[-73.906532,40.876899],"type":"Point"}
}