{
  "type": "Feature",
  "properties": {
    "addr:full":"412 86th St Brooklyn NY 11209",
    "addr:housenumber":"412",
    "addr:postcode":"11209",
    "addr:street":"86Th St",
    "iso:country":"US",
    "sg:address":"412 86th St",
    "sg:city":"Brooklyn",
    "sg:classifiers":[
        {
            "category":"Restaurant",
            "type":"Food & Drink"
        }
    ],
    "sg:phone":"+1   ",
    "sg:postcode":"11209",
    "sg:province":"NY",
    "sg:tags":[
        "eating"
    ],
    "wof:name":"Riviera Pizza & Restaurant",
    "wof:placetype":"venue"
},
  "geometry": {"coordinates":[-74.02646,40.621593],"type":"Point"}
}