{
  "type": "Feature",
  "properties": {
    "iso:country":"US",
    "sg:address":"3125 41st St #2R",
    "sg:city":"New York",
    "sg:classifiers":[
        {
            "category":"Professional",
            "type":"Services"
        },
        {
            "category":"Education",
            "subcategory":"School",
            "type":"Public Place"
        }
    ],
    "sg:phone":"+1 646 221 1442",
    "sg:postcode":"11103",
    "sg:province":"NY",
    "sg:website":"www.andreaprivatespanish.com",
    "wof:name":"Andrea Private Spanish",
    "wof:placetype":"venue"
},
  "geometry": {"coordinates":[-73.916752,40.760351],"type":"Point"}
}