{
  "type": "Feature",
  "properties": {
    "addr:full":"60 Eileen Ct Buffalo NY 14227",
    "addr:housenumber":"60",
    "addr:postcode":"14227",
    "addr:street":"Eileen Ct",
    "iso:country":"US",
    "sg:address":"60 Eileen Ct",
    "sg:city":"Buffalo",
    "sg:classifiers":[
        {
            "category":"Shopping",
            "subcategory":"Gifts & Souvenirs",
            "type":"Retail Goods"
        }
    ],
    "sg:phone":"+1   ",
    "sg:postcode":"14227",
    "sg:province":"NY",
    "wof:name":"Unique Gifts & Decor",
    "wof:placetype":"venue"
},
  "geometry": {"coordinates":[-78.728375,42.865426],"type":"Point"}
}