{
  "type": "Feature",
  "properties": {
    "addr:full":"778 Seneca Ave Queens NY 11385",
    "addr:housenumber":"778",
    "addr:postcode":"11385",
    "addr:street":"Seneca Ave",
    "iso:country":"US",
    "sg:address":"778 Seneca Ave",
    "sg:city":"Queens",
    "sg:classifiers":[
        {
            "category":"Food & Beverages",
            "subcategory":"Cheese",
            "type":"Retail Goods"
        },
        {
            "category":"Professional",
            "subcategory":"Business Services",
            "type":"Services"
        }
    ],
    "sg:phone":"+1 718 497 5637",
    "sg:postcode":"11385",
    "sg:province":"NY",
    "sg:tags":[
        "delivery",
        "cheesesteaks"
    ],
    "wof:name":"Crazy Joe's Cheese Steaks",
    "wof:placetype":"venue"
},
  "geometry": {"coordinates":[-73.906127,40.701865],"type":"Point"}
}