{
  "type": "Feature",
  "properties": {
    "iso:country":"US",
    "sg:address":"32 Center St",
    "sg:city":"Albany",
    "sg:classifiers":[
        {
            "category":"Organizations",
            "subcategory":"Community Association",
            "type":"Services"
        }
    ],
    "sg:phone":"+1 518 482 5845",
    "sg:postcode":"12204",
    "sg:province":"NY",
    "sg:tags":[
        "club"
    ],
    "wof:name":"German-American Club Of Albany",
    "wof:placetype":"venue"
},
  "geometry": {"coordinates":[-73.737066,42.671557],"type":"Point"}
}