{
  "type": "Feature",
  "properties": {
    "addr:full":"260 Washington St Watertown NY 13601",
    "addr:housenumber":"260",
    "addr:postcode":"13601",
    "addr:street":"Washington St",
    "iso:country":"US",
    "sg:address":"260 Washington St",
    "sg:city":"Watertown",
    "sg:classifiers":[
        {
            "category":"Manufacturing",
            "subcategory":"Printing",
            "type":"Manufacturing & Wholesale Goods"
        }
    ],
    "sg:phone":"+1 315 788 3638",
    "sg:postcode":"13601",
    "sg:province":"NY",
    "sg:tags":[
        "newspaper",
        "publisher"
    ],
    "wof:name":"Watertown Daily Times Inc",
    "wof:placetype":"venue"
},
  "geometry": {"coordinates":[-75.911254,43.972376],"type":"Point"}
}