{
  "type": "Feature",
  "properties": {
    "iso:country":"US",
    "sg:address":"28 Church St",
    "sg:city":"Buffalo",
    "sg:classifiers":[
        {
            "category":"Professional",
            "subcategory":"Lawyer & Legal Services",
            "type":"Services"
        }
    ],
    "sg:phone":"+1 716 852 4519",
    "sg:postcode":"14202",
    "sg:province":"NY",
    "wof:name":"Hodgson Russ atty",
    "wof:placetype":"venue"
},
  "geometry": {"coordinates":[-78.87665699999999,42.883136],"type":"Point"}
}