{
  "type": "Feature",
  "properties": {
    "addr:full":"120-160 W 97th St Manhattan NY 10025",
    "addr:housenumber":"120-160",
    "addr:postcode":"10025",
    "addr:street":"W 97Th St",
    "iso:country":"US",
    "sg:address":"120-160 W 97th St",
    "sg:city":"Manhattan",
    "sg:classifiers":[
        {
            "category":"Real Estate",
            "subcategory":"Real Estate Operator",
            "type":"Services"
        }
    ],
    "sg:phone":"+1 212 594 6660",
    "sg:postcode":"10025",
    "sg:province":"NY",
    "sg:tags":[
        "apartment"
    ],
    "sg:website":"www.stonehengenyc.com/properties...",
    "wof:name":"Stonehenge Village",
    "wof:placetype":"venue"
},
  "geometry": {"coordinates":[-73.969138,40.794303],"type":"Point"}
}