{
  "type": "Feature",
  "properties": {
    "iso:country":"US",
    "sg:address":"3608 Eckhardt Rd",
    "sg:city":"Hamburg",
    "sg:classifiers":[
        {
            "category":"Recreation",
            "subcategory":"Fishing",
            "type":"Entertainment"
        },
        {
            "category":"Sports & Exercise",
            "subcategory":"Playing Field",
            "type":"Entertainment"
        }
    ],
    "sg:phone":"+1 716 648 2243",
    "sg:postcode":"14075",
    "sg:province":"NY",
    "sg:tags":[
        "preserve",
        "farm",
        "game",
        "hunting"
    ],
    "sg:website":"http://www.highcountrylodge.com",
    "wof:name":"High Country Lodge Inc",
    "wof:placetype":"venue"
},
  "geometry": {"coordinates":[-78.853562,42.68531],"type":"Point"}
}