{
  "type": "Feature",
  "properties": {
    "addr:full":"476 Klondike Ave Staten Island NY 10314",
    "addr:housenumber":"476",
    "addr:postcode":"10314",
    "addr:street":"Klondike Ave",
    "iso:country":"US",
    "sg:address":"476 Klondike Ave",
    "sg:city":"Staten Island",
    "sg:classifiers":[
        {
            "category":"Health Services",
            "subcategory":"Doctor",
            "type":"Services"
        }
    ],
    "sg:phone":"+1 718 761 1156",
    "sg:postcode":"10314",
    "sg:province":"NY",
    "sg:tags":[
        "medicine",
        "internal"
    ],
    "wof:name":"Maddela Elizabeth Dr",
    "wof:placetype":"venue"
},
  "geometry": {"coordinates":[-74.15239699999999,40.586498],"type":"Point"}
}