{
  "type": "Feature",
  "properties": {
    "addr:full":"139 Wickham Ave Middletown NY 10940",
    "addr:housenumber":"139",
    "addr:postcode":"10940",
    "addr:street":"Wickham Ave",
    "iso:country":"US",
    "sg:address":"139 Wickham Ave",
    "sg:city":"Middletown",
    "sg:classifiers":[
        {
            "category":"Autos & Motor Vehicles",
            "subcategory":"Automobile Sales",
            "type":"Retail Goods"
        }
    ],
    "sg:phone":"+1   ",
    "sg:postcode":"10940",
    "sg:province":"NY",
    "sg:tags":[
        "used"
    ],
    "wof:name":"A Plus Auto Sales & Service",
    "wof:placetype":"venue"
},
  "geometry": {"coordinates":[-74.41416599999999,41.451053],"type":"Point"}
}