{
  "type": "Feature",
  "properties": {
    "addr:full":"20216 Rockaway Point Blvd Breezy Point NY 11697",
    "addr:housenumber":"20216",
    "addr:postcode":"11697",
    "addr:street":"Rockaway Point Blvd",
    "iso:country":"US",
    "sg:address":"20216 Rockaway Point Blvd",
    "sg:city":"Breezy Point",
    "sg:classifiers":[
        {
            "category":"Banks & Credit Unions",
            "subcategory":"Bank",
            "type":"Services"
        }
    ],
    "sg:phone":"+1 718 634 3600",
    "sg:postcode":"11697",
    "sg:province":"NY",
    "wof:name":"Ridgewood Savings Bank",
    "wof:placetype":"venue"
},
  "geometry": {"coordinates":[-73.911102,40.560902],"type":"Point"}
}