{
  "type": "Feature",
  "properties": {
    "addr:full":"342 Broadway New York NY 10013",
    "addr:housenumber":"342",
    "addr:postcode":"10013",
    "addr:street":"Broadway",
    "iso:country":"US",
    "sg:address":"342 Broadway",
    "sg:city":"New York",
    "sg:classifiers":[
        {
            "category":"Real Estate",
            "subcategory":"Real Estate Services",
            "type":"Services"
        }
    ],
    "sg:phone":"+1 212 385 3510",
    "sg:postcode":"10013",
    "sg:province":"NY",
    "wof:name":"Poplar Media",
    "wof:placetype":"venue"
},
  "geometry": {"coordinates":[-74.013295,40.716597],"type":"Point"}
}