{
  "type": "Feature",
  "properties": {
    "addr:full":"5 Fairlawn Ct Rye NY 10580",
    "addr:housenumber":"5",
    "addr:postcode":"10580",
    "addr:street":"Fairlawn Ct",
    "iso:country":"US",
    "sg:address":"5 Fairlawn Ct",
    "sg:city":"Rye",
    "sg:classifiers":[
        {
            "category":"Professional",
            "subcategory":"Lawyer & Legal Services",
            "type":"Services"
        }
    ],
    "sg:phone":"+1   ",
    "sg:postcode":"10580",
    "sg:province":"NY",
    "wof:name":"Parent Neil Law Offices PC",
    "wof:placetype":"venue"
},
  "geometry": {"coordinates":[-73.685728,40.95876],"type":"Point"}
}