{
  "type": "Feature",
  "properties": {
    "addr:full":"16 South St Dryden NY 13053",
    "addr:housenumber":"16",
    "addr:postcode":"13053",
    "addr:street":"South St",
    "iso:country":"US",
    "sg:address":"16 South St",
    "sg:city":"Dryden",
    "sg:classifiers":[
        {
            "category":"Government",
            "subcategory":"Police Station",
            "type":"Public Place"
        }
    ],
    "sg:phone":"+1 607 844 8118",
    "sg:postcode":"13053",
    "sg:province":"NY",
    "sg:tags":[
        "department"
    ],
    "wof:name":"Dryden Village Police Dept",
    "wof:placetype":"venue"
},
  "geometry": {"coordinates":[-76.29774399999999,42.489632],"type":"Point"}
}