{
  "type": "Feature",
  "properties": {
    "iso:country":"US",
    "sg:address":"8 W 38th St",
    "sg:city":"New York",
    "sg:classifiers":[
        {
            "category":"Real Estate",
            "subcategory":"Real Estate Operator",
            "type":"Services"
        }
    ],
    "sg:phone":"+1 212 354 4740",
    "sg:postcode":"10018",
    "sg:province":"NY",
    "sg:tags":[
        "building",
        "apartment"
    ],
    "wof:name":"Curzon House Owners Corp",
    "wof:placetype":"venue"
},
  "geometry": {"coordinates":[-73.985831,40.752167],"type":"Point"}
}