{
  "type": "Feature",
  "properties": {
    "iso:country":"US",
    "sg:address":"33 N 3rd Ave",
    "sg:city":"Mount Vernon",
    "sg:classifiers":[
        {
            "category":"Professional",
            "subcategory":"Computer Services",
            "type":"Services"
        }
    ],
    "sg:phone":"+1 914 830 3805",
    "sg:postcode":"10550",
    "sg:province":"NY",
    "sg:tags":[
        "design",
        "system"
    ],
    "wof:name":"Jaha Technologies",
    "wof:placetype":"venue"
},
  "geometry": {"coordinates":[-73.836359,40.913859],"type":"Point"}
}