{
  "type": "Feature",
  "properties": {
    "addr:full":"36 Madison Ave Westbury NY 11590",
    "addr:housenumber":"36",
    "addr:postcode":"11590",
    "addr:street":"Madison Ave",
    "iso:country":"US",
    "sg:address":"36 Madison Ave",
    "sg:city":"Westbury",
    "sg:classifiers":[
        {
            "category":"Building & Trades",
            "subcategory":"Landscaping Services",
            "type":"Services"
        }
    ],
    "sg:phone":"+1 516 364 6410",
    "sg:postcode":"11590",
    "sg:province":"NY",
    "sg:tags":[
        "landscape"
    ],
    "wof:name":"Posillico Augie Landscaping",
    "wof:placetype":"venue"
},
  "geometry": {"coordinates":[-73.59113000000001,40.751878],"type":"Point"}
}