{
  "type": "Feature",
  "properties": {
    "iso:country":"US",
    "sg:address":"1363 Jerusalem Ave",
    "sg:city":"Merrick",
    "sg:classifiers":[
        {
            "category":"Professional",
            "type":"Services"
        }
    ],
    "sg:phone":"+1 516 222 1252",
    "sg:postcode":"11566",
    "sg:province":"NY",
    "sg:tags":[
        "caterer"
    ],
    "wof:name":"Iannuzzi Fine Foods & Catering",
    "wof:placetype":"venue"
},
  "geometry": {"coordinates":[-73.569728,40.694161],"type":"Point"}
}