{
  "type": "Feature",
  "properties": {
    "iso:country":"US",
    "sg:address":"14 Heaney Dr",
    "sg:city":"Beacon",
    "sg:classifiers":[
        {
            "category":"Shopping",
            "type":"Retail Goods"
        }
    ],
    "sg:phone":"+1 845 838 1020",
    "sg:postcode":"12508",
    "sg:province":"NY",
    "sg:tags":[
        "art",
        "gallery",
        "dealer"
    ],
    "wof:name":"DSA Fine Art LTD",
    "wof:placetype":"venue"
},
  "geometry": {"coordinates":[-73.965851,41.494012],"type":"Point"}
}