{
  "type": "Feature",
  "properties": {
    "iso:country":"US",
    "sg:address":"42 W Main St",
    "sg:city":"East Islip",
    "sg:classifiers":[
        {
            "category":"Retail",
            "subcategory":"Auto Repair",
            "type":"Services"
        }
    ],
    "sg:phone":"+1 631 581 1197",
    "sg:postcode":"11730",
    "sg:province":"NY",
    "wof:name":"Charlie's Auto Repair Svce",
    "wof:placetype":"venue"
},
  "geometry": {"coordinates":[-73.193001,40.730801],"type":"Point"}
}