{
  "type": "Feature",
  "properties": {
    "addr:full":"2211 Coney Island Ave Brooklyn NY 11223",
    "addr:housenumber":"2211",
    "addr:postcode":"11223",
    "addr:street":"Coney Island Ave",
    "iso:country":"US",
    "sg:address":"2211 Coney Island Ave",
    "sg:city":"Brooklyn",
    "sg:classifiers":[
        {
            "category":"Wholesale",
            "subcategory":"Non-durable Goods",
            "type":"Manufacturing & Wholesale Goods"
        }
    ],
    "sg:phone":"+1 718 645 1700",
    "sg:postcode":"11223",
    "sg:province":"NY",
    "wof:name":"Herman Greiff Inc",
    "wof:placetype":"venue"
},
  "geometry": {"coordinates":[-73.96156499999999,40.604528],"type":"Point"}
}