{
  "type": "Feature",
  "properties": {
    "addr:full":"197 Wyckoff Ave Brooklyn NY 11237",
    "addr:housenumber":"197",
    "addr:postcode":"11237",
    "addr:street":"Wyckoff Ave",
    "iso:country":"US",
    "sg:address":"197 Wyckoff Ave",
    "sg:city":"Brooklyn",
    "sg:classifiers":[
        {
            "category":"Retail",
            "subcategory":"Auto Repair",
            "type":"Services"
        }
    ],
    "sg:phone":"+1 718 381 8428",
    "sg:postcode":"11237",
    "sg:province":"NY",
    "sg:tags":[
        "tire"
    ],
    "wof:name":"Cesar Flat Fix",
    "wof:placetype":"venue"
},
  "geometry": {"coordinates":[-73.916298,40.702499],"type":"Point"}
}