{
  "type": "Feature",
  "properties": {
    "addr:full":"64 Jericho Tpke Syosset NY 11791",
    "addr:housenumber":"64",
    "addr:postcode":"11791",
    "addr:street":"Jericho Tpke",
    "iso:country":"US",
    "sg:address":"64 Jericho Tpke",
    "sg:city":"Syosset",
    "sg:classifiers":[
        {
            "category":"Personal",
            "type":"Services"
        }
    ],
    "sg:phone":"+1 516 496 3136",
    "sg:postcode":"11791",
    "sg:province":"NY",
    "sg:tags":[
        "towing"
    ],
    "wof:name":"Island Towing Inc",
    "wof:placetype":"venue"
},
  "geometry": {"coordinates":[-73.510696,40.809898],"type":"Point"}
}