{
  "type": "Feature",
  "properties": {
    "iso:country":"US",
    "sg:address":"515 Acorn St",
    "sg:city":"Deer Park",
    "sg:classifiers":[
        {
            "category":"Manufacturing",
            "subcategory":"Printing",
            "type":"Manufacturing & Wholesale Goods"
        }
    ],
    "sg:phone":"+1 631 595 9623",
    "sg:postcode":"11729",
    "sg:province":"NY",
    "sg:tags":[
        "printer"
    ],
    "wof:name":"Long Island Business Forms",
    "wof:placetype":"venue"
},
  "geometry": {"coordinates":[-73.34429,40.758095],"type":"Point"}
}