{
  "type": "Feature",
  "properties": {
    "iso:country":"US",
    "sg:address":"530 E 76 St",
    "sg:city":"New York",
    "sg:classifiers":[
        {
            "category":"Professional",
            "subcategory":"Management & Consulting",
            "type":"Services"
        }
    ],
    "sg:phone":"+1 212 439 7740",
    "sg:postcode":"10021",
    "sg:province":"NY",
    "sg:tags":[
        "consultant",
        "business"
    ],
    "wof:name":"Corporate Development",
    "wof:placetype":"venue"
},
  "geometry": {"coordinates":[-73.94990300000001,40.768622],"type":"Point"}
}