{
  "type": "Feature",
  "properties": {
    "iso:country":"US",
    "sg:address":"346 Route 212",
    "sg:city":"Saugerties",
    "sg:classifiers":[
        {
            "category":"Restaurant",
            "type":"Food & Drink"
        }
    ],
    "sg:phone":"+1 845 246 7135",
    "sg:postcode":"12477",
    "sg:province":"NY",
    "wof:name":"Starway Cafe",
    "wof:placetype":"venue"
},
  "geometry": {"coordinates":[-73.979513,42.082792],"type":"Point"}
}