{
  "type": "Feature",
  "properties": {
    "addr:full":"129 Hempstead Tpke Elmont NY 11003",
    "addr:housenumber":"129",
    "addr:postcode":"11003",
    "addr:street":"Hempstead Tpke",
    "iso:country":"US",
    "sg:address":"129 Hempstead Tpke",
    "sg:city":"Elmont",
    "sg:classifiers":[
        {
            "category":"Autos & Motor Vehicles",
            "subcategory":"Automobile Sales",
            "type":"Retail Goods"
        }
    ],
    "sg:phone":"+1   ",
    "sg:postcode":"11003",
    "sg:province":"NY",
    "sg:tags":[
        "used"
    ],
    "wof:name":"Four Seasons Auto Sales",
    "wof:placetype":"venue"
},
  "geometry": {"coordinates":[-73.722835,40.709463],"type":"Point"}
}