{
  "type": "Feature",
  "properties": {
    "addr:full":"74 Redwood Ln Painted Post NY 14850",
    "addr:housenumber":"74",
    "addr:postcode":"14850",
    "addr:street":"Redwood Ln",
    "iso:country":"US",
    "sg:address":"74 Redwood Ln",
    "sg:city":"Painted Post",
    "sg:classifiers":[
        {
            "category":"Professional",
            "type":"Services"
        }
    ],
    "sg:phone":"+1 607 936 2641",
    "sg:postcode":"14850",
    "sg:province":"NY",
    "sg:tags":[
        "establishment"
    ],
    "wof:name":"Lunsford Precious",
    "wof:placetype":"venue"
},
  "geometry": {"coordinates":[-76.41353100000001,42.416972],"type":"Point"}
}