{
  "type": "Feature",
  "properties": {
    "addr:full":"30 E Suffolk Ave Central Islip NY 11722",
    "addr:housenumber":"30",
    "addr:postcode":"11722",
    "addr:street":"E Suffolk Ave",
    "iso:country":"US",
    "sg:address":"30 E Suffolk Ave",
    "sg:city":"Central Islip",
    "sg:classifiers":[
        {
            "category":"Freight",
            "type":"Transportation"
        }
    ],
    "sg:phone":"+1   ",
    "sg:postcode":"11722",
    "sg:province":"NY",
    "sg:tags":[
        "arrangement"
    ],
    "wof:name":"Naviera Latina",
    "wof:placetype":"venue"
},
  "geometry": {"coordinates":[-73.201037,40.790856],"type":"Point"}
}