{
  "type": "Feature",
  "properties": {
    "addr:full":"896 Franklin Ave Valley Stream NY 11580",
    "addr:housenumber":"896",
    "addr:postcode":"11580",
    "addr:street":"Franklin Ave",
    "iso:country":"US",
    "sg:address":"896 Franklin Ave",
    "sg:city":"Valley Stream",
    "sg:classifiers":[
        {
            "category":"Wholesale",
            "subcategory":"Construction Materials",
            "type":"Manufacturing & Wholesale Goods"
        }
    ],
    "sg:phone":"+1 516 561 4294",
    "sg:postcode":"11580",
    "sg:province":"NY",
    "wof:name":"Ronnies",
    "wof:placetype":"venue"
},
  "geometry": {"coordinates":[-73.68583099999999,40.68343],"type":"Point"}
}