{
  "type": "Feature",
  "properties": {
    "addr:full":"316 Delaware Ave Delmar NY 12054",
    "addr:housenumber":"316",
    "addr:postcode":"12054",
    "addr:street":"Delaware Ave",
    "iso:country":"US",
    "sg:address":"316 Delaware Ave",
    "sg:city":"Delmar",
    "sg:classifiers":[
        {
            "category":"Banks & Credit Unions",
            "subcategory":"Investment Brokerage",
            "type":"Services"
        }
    ],
    "sg:phone":"+1 518 475 7642",
    "sg:postcode":"12054",
    "sg:province":"NY",
    "sg:tags":[
        "stock",
        "bond"
    ],
    "sg:website":"www.edwardjones.com",
    "wof:name":"Edward Jones",
    "wof:placetype":"venue"
},
  "geometry": {"coordinates":[-73.827817,42.62401],"type":"Point"}
}