{
  "type": "Feature",
  "properties": {
    "addr:full":"124 Old Chester Rd Goshen NY 10924",
    "addr:housenumber":"124",
    "addr:postcode":"10924",
    "addr:street":"Old Chester Rd",
    "iso:country":"US",
    "sg:address":"124 Old Chester Rd",
    "sg:city":"Goshen",
    "sg:classifiers":[
        {
            "category":"Building & Trades",
            "subcategory":"Construction",
            "type":"Services"
        }
    ],
    "sg:phone":"+1 845 294 3970",
    "sg:postcode":"10924",
    "sg:province":"NY",
    "sg:tags":[
        "carpentry",
        "contractor"
    ],
    "wof:name":"Premier Carpentry",
    "wof:placetype":"venue"
},
  "geometry": {"coordinates":[-74.308892,41.391901],"type":"Point"}
}