{
  "type": "Feature",
  "properties": {
    "iso:country":"US",
    "sg:address":"37 W Main St",
    "sg:city":"Cortland",
    "sg:classifiers":[
        {
            "category":"Shopping",
            "subcategory":"Music",
            "type":"Retail Goods"
        }
    ],
    "sg:phone":"+1   ",
    "sg:postcode":"13045",
    "sg:province":"NY",
    "wof:name":"Music Gallery",
    "wof:placetype":"venue"
},
  "geometry": {"coordinates":[-76.189789,42.608139],"type":"Point"}
}