{
  "type": "Feature",
  "properties": {
    "addr:full":"5600 Broadway St Lancaster NY 14086",
    "addr:housenumber":"5600",
    "addr:postcode":"14086",
    "addr:street":"Broadway St",
    "iso:country":"US",
    "sg:address":"5600 Broadway St",
    "sg:city":"Lancaster",
    "sg:classifiers":[
        {
            "category":"Organizations",
            "subcategory":"Religious Organization",
            "type":"Services"
        }
    ],
    "sg:phone":"+1 716 683 0570",
    "sg:postcode":"14086",
    "sg:province":"NY",
    "sg:tags":[
        "church"
    ],
    "wof:name":"Vine Wesleyan Church",
    "wof:placetype":"venue"
},
  "geometry": {"coordinates":[-78.66194900000001,42.898258],"type":"Point"}
}