{
  "type": "Feature",
  "properties": {
    "iso:country":"US",
    "sg:address":"66 Mahan St",
    "sg:city":"West Babylon",
    "sg:classifiers":[
        {
            "category":"Manufacturing",
            "subcategory":"Metals",
            "type":"Manufacturing & Wholesale Goods"
        },
        {
            "category":"Building & Trades",
            "subcategory":"Construction",
            "type":"Services"
        }
    ],
    "sg:phone":"+1 631 253 9400",
    "sg:postcode":"11704",
    "sg:province":"NY",
    "sg:tags":[
        "duct",
        "fabricator",
        "work",
        "sheet"
    ],
    "wof:name":"Eastern Metalworks Inc",
    "wof:placetype":"venue"
},
  "geometry": {"coordinates":[-73.377923,40.739154],"type":"Point"}
}