{
  "type": "Feature",
  "properties": {
    "iso:country":"US",
    "sg:address":"631 N Union St",
    "sg:city":"Olean",
    "sg:classifiers":[
        {
            "category":"Wholesale",
            "subcategory":"Hardware",
            "type":"Manufacturing & Wholesale Goods"
        }
    ],
    "sg:phone":"+1 716 372 2191",
    "sg:postcode":"14760",
    "sg:province":"NY",
    "sg:tags":[
        "equipment",
        "heating",
        "system"
    ],
    "wof:name":"IRR Supply Ctr Inc",
    "wof:placetype":"venue"
},
  "geometry": {"coordinates":[-78.43237000000001,42.088669],"type":"Point"}
}