{
  "type": "Feature",
  "properties": {
    "iso:country":"US",
    "sg:address":"1066 Madison Ave",
    "sg:city":"Albany",
    "sg:classifiers":[
        {
            "category":"Bakery",
            "type":"Food & Drink"
        },
        {
            "category":"Coffee & Tea",
            "type":"Food & Drink"
        },
        {
            "category":"Bagels",
            "type":"Food & Drink"
        },
        {
            "category":"Donuts",
            "type":"Food & Drink"
        }
    ],
    "sg:menulink":"http://www.allmenus.com/ny/albany/138155-dunkin-donuts/menu/",
    "sg:phone":"+1 516 378 9186",
    "sg:postcode":"12208",
    "sg:province":"NY",
    "sg:tags":[
        "american",
        "pastry"
    ],
    "wof:name":"Dunkin' Donuts",
    "wof:placetype":"venue"
},
  "geometry": {"coordinates":[-73.79057,42.665166],"type":"Point"}
}