{
  "type": "Feature",
  "properties": {
    "addr:full":"800 Syska Rd Ossining NY 10562",
    "addr:housenumber":"800",
    "addr:postcode":"10562",
    "addr:street":"Syska Rd",
    "iso:country":"US",
    "sg:address":"800 Syska Rd",
    "sg:city":"Ossining",
    "sg:classifiers":[
        {
            "category":"Building & Trades",
            "subcategory":"Pest Control",
            "type":"Services"
        }
    ],
    "sg:phone":"+1 914 941 8134",
    "sg:postcode":"10562",
    "sg:province":"NY",
    "wof:name":"Excellent Exterminators",
    "wof:placetype":"venue"
},
  "geometry": {"coordinates":[-73.794455,41.21265],"type":"Point"}
}