{
  "type": "Feature",
  "properties": {
    "addr:full":"155 E 44th St New York NY 10017",
    "addr:housenumber":"155",
    "addr:postcode":"10017",
    "addr:street":"E 44Th St",
    "iso:country":"US",
    "sg:address":"155 E 44th St",
    "sg:city":"New York",
    "sg:classifiers":[
        {
            "category":"Personal",
            "subcategory":"Beauty Salon",
            "type":"Services"
        },
        {
            "category":"Personal",
            "subcategory":"Day Spa",
            "type":"Services"
        },
        {
            "category":"Personal",
            "subcategory":"Nail Salon",
            "type":"Services"
        }
    ],
    "sg:phone":"+1 212 682 6073",
    "sg:postcode":"10017",
    "sg:province":"NY",
    "sg:tags":[
        "hair"
    ],
    "sg:website":"www.spabutterfly.com",
    "wof:name":"Spa Butterfly",
    "wof:placetype":"venue"
},
  "geometry": {"coordinates":[-73.97415700000001,40.752327],"type":"Point"}
}