{
  "type": "Feature",
  "properties": {
    "addr:full":"3543 Kellogg Rd Cortland NY 13045",
    "addr:housenumber":"3543",
    "addr:postcode":"13045",
    "addr:street":"Kellogg Rd",
    "iso:country":"US",
    "sg:address":"3543 Kellogg Rd",
    "sg:city":"Cortland",
    "sg:classifiers":[
        {
            "category":"Autos & Motor Vehicles",
            "subcategory":"Automobile Sales",
            "type":"Retail Goods"
        }
    ],
    "sg:phone":"+1 607 756 5779",
    "sg:postcode":"13045",
    "sg:province":"NY",
    "sg:tags":[
        "car",
        "dealer"
    ],
    "wof:name":"Eastman's Auto",
    "wof:placetype":"venue"
},
  "geometry": {"coordinates":[-76.135057,42.580777],"type":"Point"}
}