{
  "type": "Feature",
  "properties": {
    "addr:full":"1656 Military Rd Niagara Falls NY 14304",
    "addr:housenumber":"1656",
    "addr:postcode":"14304",
    "addr:street":"Military Rd",
    "iso:country":"US",
    "sg:address":"1656 Military Rd",
    "sg:city":"Niagara Falls",
    "sg:classifiers":[
        {
            "category":"Shopping",
            "subcategory":"Clothing, Apparel, & Fashions",
            "type":"Retail Goods"
        }
    ],
    "sg:phone":"+1 716 297 9080",
    "sg:postcode":"14304",
    "sg:province":"NY",
    "sg:tags":[
        "designer"
    ],
    "wof:name":"Polo Ralph Lauren Factory Str",
    "wof:placetype":"venue"
},
  "geometry": {"coordinates":[-78.97118399999999,43.093458],"type":"Point"}
}