{
  "type": "Feature",
  "properties": {
    "addr:full":"950 Chemung St Horseheads NY 14845",
    "addr:housenumber":"950",
    "addr:postcode":"14845",
    "addr:street":"Chemung St",
    "iso:country":"US",
    "sg:address":"950 Chemung St",
    "sg:city":"Horseheads",
    "sg:classifiers":[
        {
            "category":"Restaurant",
            "type":"Food & Drink"
        }
    ],
    "sg:menulink":"http://www.allmenus.com/ny/horseheads/11459-dennys/menu/",
    "sg:phone":"+1 607 795 4135",
    "sg:postcode":"14845",
    "sg:province":"NY",
    "sg:tags":[
        "american",
        "diner"
    ],
    "wof:name":"Denny's",
    "wof:placetype":"venue"
},
  "geometry": {"coordinates":[-76.836789,42.158587],"type":"Point"}
}