{
  "type": "Feature",
  "properties": {
    "iso:country":"US",
    "sg:address":"4004 Case St",
    "sg:city":"Elmhurst",
    "sg:classifiers":[
        {
            "category":"Professional",
            "subcategory":"Employment Agencies",
            "type":"Services"
        }
    ],
    "sg:phone":"+1 718 606 6458",
    "sg:postcode":"11373",
    "sg:province":"NY",
    "wof:name":"Employment Agency",
    "wof:placetype":"venue"
},
  "geometry": {"coordinates":[-73.87680899999999,40.748164],"type":"Point"}
}