{
  "type": "Feature",
  "properties": {
    "addr:full":"95 N Main St Wellsville NY 14895",
    "addr:housenumber":"95",
    "addr:postcode":"14895",
    "addr:street":"N Main St",
    "iso:country":"US",
    "sg:address":"95 N Main St",
    "sg:city":"Wellsville",
    "sg:classifiers":[
        {
            "category":"Food & Beverages",
            "subcategory":"Candy",
            "type":"Retail Goods"
        }
    ],
    "sg:phone":"+1   ",
    "sg:postcode":"14895",
    "sg:province":"NY",
    "wof:name":"Sweet Attitudes Chocolates",
    "wof:placetype":"venue"
},
  "geometry": {"coordinates":[-77.94649800000001,42.120757],"type":"Point"}
}