{
  "type": "Feature",
  "properties": {
    "addr:full":"488 State Hwy 17M Monroe NY 10950",
    "addr:housenumber":"488",
    "addr:postcode":"10950",
    "addr:street":"State Hwy",
    "iso:country":"US",
    "sg:address":"488 State Hwy 17M",
    "sg:city":"Monroe",
    "sg:classifiers":[
        {
            "category":"Shopping",
            "subcategory":"Pharmacy",
            "type":"Retail Goods"
        }
    ],
    "sg:phone":"+1 845 783 7807",
    "sg:postcode":"10950",
    "sg:province":"NY",
    "wof:name":"CVS Pharmacy",
    "wof:placetype":"venue"
},
  "geometry": {"coordinates":[-74.177688,41.31974],"type":"Point"}
}