{
  "type": "Feature",
  "properties": {
    "addr:full":"304 Park Ave S New York NY 10010",
    "addr:housenumber":"304",
    "addr:postcode":"10010",
    "addr:street":"Park Ave S",
    "iso:country":"US",
    "sg:address":"304 Park Ave S",
    "sg:city":"New York",
    "sg:classifiers":[
        {
            "category":"Communications",
            "subcategory":"Newspaper",
            "type":"Services"
        }
    ],
    "sg:phone":"+1 212 777 6655",
    "sg:postcode":"10010",
    "sg:province":"NY",
    "sg:tags":[
        "print",
        "medium"
    ],
    "wof:name":"Maloney Group Ltd",
    "wof:placetype":"venue"
},
  "geometry": {"coordinates":[-73.986504,40.7402],"type":"Point"}
}