{
  "type": "Feature",
  "properties": {
    "addr:full":"871 5th Ave New York NY 10065",
    "addr:housenumber":"871",
    "addr:postcode":"10065",
    "addr:street":"5Th Ave",
    "iso:country":"US",
    "sg:address":"871 5th Ave",
    "sg:city":"New York",
    "sg:classifiers":[
        {
            "category":"Health Services",
            "subcategory":"Doctor",
            "type":"Services"
        }
    ],
    "sg:phone":"+1   ",
    "sg:postcode":"10065",
    "sg:province":"NY",
    "sg:tags":[
        "dentist"
    ],
    "wof:name":"Roger M Gershon DDS",
    "wof:placetype":"venue"
},
  "geometry": {"coordinates":[-73.968441,40.770517],"type":"Point"}
}