{
  "type": "Feature",
  "properties": {
    "iso:country":"US",
    "sg:address":"1982 W Danby Rd",
    "sg:city":"Newfield",
    "sg:classifiers":[
        {
            "category":"Retail",
            "subcategory":"Repair Shop",
            "type":"Services"
        }
    ],
    "sg:phone":"+1 607 699 9986",
    "sg:postcode":"14867",
    "sg:province":"NY",
    "sg:tags":[
        "lock",
        "locksmith"
    ],
    "wof:name":"Pop-A-Lock",
    "wof:placetype":"venue"
},
  "geometry": {"coordinates":[-76.537736,42.342518],"type":"Point"}
}