{
  "type": "Feature",
  "properties": {
    "iso:country":"US",
    "sg:address":"220 Front St",
    "sg:city":"Hempstead",
    "sg:classifiers":[
        {
            "category":"Professional",
            "subcategory":"Employment Agencies",
            "type":"Services"
        }
    ],
    "sg:phone":"+1 516 485 4777",
    "sg:postcode":"11550",
    "sg:province":"NY",
    "sg:tags":[
        "temporary",
        "labor"
    ],
    "wof:name":"Labor Ready 1852",
    "wof:placetype":"venue"
},
  "geometry": {"coordinates":[-73.62689,40.705195],"type":"Point"}
}