{
  "type": "Feature",
  "properties": {
    "addr:full":"104 W 14th Street New York NY 10011",
    "addr:housenumber":"104",
    "addr:postcode":"10011",
    "addr:street":"W 14Th Street",
    "iso:country":"US",
    "sg:address":"104 W 14th Street",
    "sg:city":"New York",
    "sg:classifiers":[
        {
            "category":"Retail",
            "subcategory":"Portrait Studio",
            "type":"Services"
        }
    ],
    "sg:phone":"+1 212 647 7382",
    "sg:postcode":"10011",
    "sg:province":"NY",
    "sg:tags":[
        "photography",
        "store"
    ],
    "wof:name":"A S Photo Lab",
    "wof:placetype":"venue"
},
  "geometry": {"coordinates":[-73.996894,40.737478],"type":"Point"}
}