{
  "type": "Feature",
  "properties": {
    "addr:full":"357 Park Lane Cir Lockport NY 14094",
    "addr:housenumber":"357",
    "addr:postcode":"14094",
    "addr:street":"Park Lane Cir",
    "iso:country":"US",
    "sg:address":"357 Park Lane Cir",
    "sg:city":"Lockport",
    "sg:classifiers":[
        {
            "category":"Professional",
            "subcategory":"Art Services",
            "type":"Services"
        }
    ],
    "sg:phone":"+1 716 434 0242",
    "sg:postcode":"14094",
    "sg:province":"NY",
    "sg:tags":[
        "graphic",
        "designer"
    ],
    "wof:name":"Digital Graphix",
    "wof:placetype":"venue"
},
  "geometry": {"coordinates":[-78.66853399999999,43.167157],"type":"Point"}
}