{
  "type": "Feature",
  "properties": {
    "iso:country":"US",
    "sg:address":"37 Walden Ave",
    "sg:city":"Buffalo",
    "sg:classifiers":[
        {
            "category":"Bars & Pubs",
            "type":"Food & Drink"
        }
    ],
    "sg:phone":"+1 716 892 2543",
    "sg:postcode":"14211",
    "sg:province":"NY",
    "sg:tags":[
        "drinking"
    ],
    "wof:name":"Earl's Tavern",
    "wof:placetype":"venue"
},
  "geometry": {"coordinates":[-78.834678,42.903532],"type":"Point"}
}