{
  "type": "Feature",
  "properties": {
    "addr:full":"3235 State St Caledonia NY 14423",
    "addr:housenumber":"3235",
    "addr:postcode":"14423",
    "addr:street":"State St",
    "iso:country":"US",
    "sg:address":"3235 State St",
    "sg:city":"Caledonia",
    "sg:classifiers":[
        {
            "category":"Restaurant",
            "type":"Food & Drink"
        }
    ],
    "sg:menulink":"http://www.allmenus.com/ny/caledonia/148239-subway/menu/",
    "sg:phone":"+1 585 538 4445",
    "sg:postcode":"14423",
    "sg:province":"NY",
    "sg:tags":[
        "american",
        "sandwich"
    ],
    "wof:name":"Subway",
    "wof:placetype":"venue"
},
  "geometry": {"coordinates":[-77.84942100000001,42.969937],"type":"Point"}
}