{
  "type": "Feature",
  "properties": {
    "addr:full":"128 E Genesee St Syracuse NY 13202",
    "addr:housenumber":"128",
    "addr:postcode":"13202",
    "addr:street":"E Genesee St",
    "iso:country":"US",
    "sg:address":"128 E Genesee St",
    "sg:city":"Syracuse",
    "sg:classifiers":[
        {
            "category":"Personal",
            "subcategory":"Beauty Salon",
            "type":"Services"
        }
    ],
    "sg:phone":"+1 315 476 4247",
    "sg:postcode":"13202",
    "sg:province":"NY",
    "sg:tags":[
        "shop"
    ],
    "wof:name":"Samson & Co",
    "wof:placetype":"venue"
},
  "geometry": {"coordinates":[-76.15096200000001,43.050238],"type":"Point"}
}