{
  "type": "Feature",
  "properties": {
    "addr:full":"3429 Culver Rd Rochester NY 14622",
    "addr:housenumber":"3429",
    "addr:postcode":"14622",
    "addr:street":"Culver Rd",
    "iso:country":"US",
    "sg:address":"3429 Culver Rd",
    "sg:city":"Rochester",
    "sg:classifiers":[
        {
            "category":"Health Services",
            "subcategory":"Doctor",
            "type":"Services"
        },
        {
            "category":"Health Services",
            "subcategory":"Dentist",
            "type":"Services"
        }
    ],
    "sg:phone":"+1 585 544 2225",
    "sg:postcode":"14622",
    "sg:province":"NY",
    "sg:tags":[
        "dentists-oral",
        "physician",
        "maxillofacial",
        "surgeons",
        "surgery",
        "oral"
    ],
    "wof:name":"Benesh, Mark L Dds",
    "wof:placetype":"venue"
},
  "geometry": {"coordinates":[-77.55999199999999,43.211662],"type":"Point"}
}