{
  "type": "Feature",
  "properties": {
    "iso:country":"US",
    "sg:address":"4322 50th St",
    "sg:city":"Woodside",
    "sg:classifiers":[
        {
            "category":"Health Services",
            "subcategory":"Chiropractor",
            "type":"Services"
        }
    ],
    "sg:phone":"+1 718 478 2500",
    "sg:postcode":"11377",
    "sg:province":"NY",
    "wof:name":"Fernandez Jose M Dr",
    "wof:placetype":"venue"
},
  "geometry": {"coordinates":[-73.914703,40.744301],"type":"Point"}
}