{
  "type": "Feature",
  "properties": {
    "addr:full":"1025 Robinson Hill Rd Johnson City NY 13790",
    "addr:housenumber":"1025",
    "addr:postcode":"13790",
    "addr:street":"Robinson Hill Rd",
    "iso:country":"US",
    "sg:address":"1025 Robinson Hill Rd",
    "sg:city":"Johnson City",
    "sg:classifiers":[
        {
            "category":"Organizations",
            "subcategory":"Religious Organization",
            "type":"Services"
        }
    ],
    "sg:phone":"+1 607 798 7662",
    "sg:postcode":"13790",
    "sg:province":"NY",
    "sg:tags":[
        "church"
    ],
    "wof:name":"United With Christ",
    "wof:placetype":"venue"
},
  "geometry": {"coordinates":[-75.98876799999999,42.13997],"type":"Point"}
}