{
  "type": "Feature",
  "properties": {
    "addr:full":"25 Pleasant St New Rochelle NY 10801",
    "addr:housenumber":"25",
    "addr:postcode":"10801",
    "addr:street":"Pleasant St",
    "iso:country":"US",
    "sg:address":"25 Pleasant St",
    "sg:city":"New Rochelle",
    "sg:classifiers":[
        {
            "category":"Building & Trades",
            "subcategory":"Construction",
            "type":"Services"
        }
    ],
    "sg:phone":"+1 914 636 3342",
    "sg:postcode":"10801",
    "sg:province":"NY",
    "sg:tags":[
        "hanging",
        "contractor"
    ],
    "wof:name":"Oliveros Painting",
    "wof:placetype":"venue"
},
  "geometry": {"coordinates":[-73.767493,40.929273],"type":"Point"}
}