{
  "type": "Feature",
  "properties": {
    "addr:full":"51 Klein Rd Buffalo NY 14221",
    "addr:housenumber":"51",
    "addr:postcode":"14221",
    "addr:street":"Klein Rd",
    "iso:country":"US",
    "sg:address":"51 Klein Rd",
    "sg:city":"Buffalo",
    "sg:classifiers":[
        {
            "category":"Building & Trades",
            "subcategory":"Landscaping Services",
            "type":"Services"
        }
    ],
    "sg:phone":"+1 716 688 4794",
    "sg:postcode":"14221",
    "sg:province":"NY",
    "wof:name":"Buckley Nursery",
    "wof:placetype":"venue"
},
  "geometry": {"coordinates":[-78.73818199999999,43.002082],"type":"Point"}
}