{
  "type": "Feature",
  "properties": {
    "iso:country":"US",
    "sg:address":"479 N Perry St",
    "sg:city":"Johnstown",
    "sg:classifiers":[
        {
            "category":"Manufacturing",
            "subcategory":"Tools & Machinery",
            "type":"Manufacturing & Wholesale Goods"
        }
    ],
    "sg:phone":"+1   ",
    "sg:postcode":"12095",
    "sg:province":"NY",
    "sg:tags":[
        "equipment",
        "commercial",
        "laundry",
        "mfg"
    ],
    "wof:name":"Twin City Dry Cleaners",
    "wof:placetype":"venue"
},
  "geometry": {"coordinates":[-74.366913,43.026747],"type":"Point"}
}