{
  "type": "Feature",
  "properties": {
    "addr:full":"73 N Plank Rd Newburgh NY 12550",
    "addr:housenumber":"73",
    "addr:postcode":"12550",
    "addr:street":"N Plank Rd",
    "iso:country":"US",
    "sg:address":"73 N Plank Rd",
    "sg:city":"Newburgh",
    "sg:classifiers":[
        {
            "category":"Bakery",
            "type":"Food & Drink"
        },
        {
            "category":"Coffee & Tea",
            "type":"Food & Drink"
        },
        {
            "category":"Bagels",
            "type":"Food & Drink"
        },
        {
            "category":"Donuts",
            "type":"Food & Drink"
        }
    ],
    "sg:menulink":"http://www.allmenus.com/ny/newburgh/138591-dunkin-donuts/menu/",
    "sg:phone":"+1 914 788 9100",
    "sg:postcode":"12550",
    "sg:province":"NY",
    "sg:tags":[
        "american",
        "pastry"
    ],
    "wof:name":"Dunkin' Donuts",
    "wof:placetype":"venue"
},
  "geometry": {"coordinates":[-74.02101500000001,41.52013],"type":"Point"}
}