{
  "type": "Feature",
  "properties": {
    "iso:country":"US",
    "sg:address":"1504 Pine St",
    "sg:city":"Endicott",
    "sg:classifiers":[
        {
            "category":"Personal",
            "subcategory":"Beauty Salon",
            "type":"Services"
        }
    ],
    "sg:phone":"+1 607 786 9491",
    "sg:postcode":"13760",
    "sg:province":"NY",
    "wof:name":"Robilotti",
    "wof:placetype":"venue"
},
  "geometry": {"coordinates":[-76.04542600000001,42.115024],"type":"Point"}
}