{
  "type": "Feature",
  "properties": {
    "iso:country":"US",
    "sg:address":"2464 Baird Rd",
    "sg:city":"Penfield",
    "sg:classifiers":[
        {
            "category":"Retail",
            "subcategory":"Repair Shop",
            "type":"Services"
        }
    ],
    "sg:phone":"+1 585 586 0036",
    "sg:postcode":"14526",
    "sg:province":"NY",
    "sg:tags":[
        "machine",
        "washing"
    ],
    "wof:name":"Ted's Appliance Svc",
    "wof:placetype":"venue"
},
  "geometry": {"coordinates":[-77.46170499999999,43.117347],"type":"Point"}
}