{
  "type": "Feature",
  "properties": {
    "iso:country":"US",
    "sg:address":"531 Krumkill Rd",
    "sg:city":"Albany",
    "sg:classifiers":[
        {
            "category":"Freight",
            "type":"Transportation"
        }
    ],
    "sg:phone":"+1   ",
    "sg:postcode":"12203",
    "sg:province":"NY",
    "sg:tags":[
        "operator",
        "local",
        "trucking"
    ],
    "wof:name":"Mariana Trucking Co",
    "wof:placetype":"venue"
},
  "geometry": {"coordinates":[-73.854907,42.666089],"type":"Point"}
}