{
  "type": "Feature",
  "properties": {
    "addr:full":"75 Steven Dr Buffalo NY 14227",
    "addr:housenumber":"75",
    "addr:postcode":"14227",
    "addr:street":"Steven Dr",
    "iso:country":"US",
    "sg:address":"75 Steven Dr",
    "sg:city":"Buffalo",
    "sg:classifiers":[
        {
            "category":"Professional",
            "subcategory":"Computer Services",
            "type":"Services"
        }
    ],
    "sg:phone":"+1 716 668 8176",
    "sg:postcode":"14227",
    "sg:province":"NY",
    "sg:tags":[
        "consulting",
        "maintenance"
    ],
    "wof:name":"Tronix Micro Systems",
    "wof:placetype":"venue"
},
  "geometry": {"coordinates":[-78.72184300000001,42.864671],"type":"Point"}
}