{
  "type": "Feature",
  "properties": {
    "addr:full":"790 8th Ave New York NY 10019",
    "addr:housenumber":"790",
    "addr:postcode":"10019",
    "addr:street":"8Th Ave",
    "iso:country":"US",
    "sg:address":"790 8th Ave",
    "sg:city":"New York",
    "sg:classifiers":[
        {
            "category":"Travel",
            "subcategory":"Hotels & Motels",
            "type":"Entertainment"
        }
    ],
    "sg:phone":"+1 212 581 7000",
    "sg:postcode":"10019",
    "sg:province":"NY",
    "sg:website":"www.timessquare.hgi.com",
    "wof:name":"Hilton Garden Inn Times Square",
    "wof:placetype":"venue"
},
  "geometry": {"coordinates":[-73.986451,40.761382],"type":"Point"}
}