{
  "type": "Feature",
  "properties": {
    "iso:country":"US",
    "sg:address":"118 Kisco Ave",
    "sg:city":"Mt Kisco",
    "sg:classifiers":[
        {
            "category":"Food & Beverages",
            "subcategory":"Fruits & Vegetables",
            "type":"Retail Goods"
        }
    ],
    "sg:phone":"+1 914 241 4434",
    "sg:postcode":"10549",
    "sg:province":"NY",
    "sg:tags":[
        "produce"
    ],
    "wof:name":"Z S Fresh",
    "wof:placetype":"venue"
},
  "geometry": {"coordinates":[-73.726365,41.214353],"type":"Point"}
}