{
  "type": "Feature",
  "properties": {
    "addr:full":"344 Kell Ave Staten Island NY 10314",
    "addr:housenumber":"344",
    "addr:postcode":"10314",
    "addr:street":"Kell Ave",
    "iso:country":"US",
    "sg:address":"344 Kell Ave",
    "sg:city":"Staten Island",
    "sg:classifiers":[
        {
            "category":"Real Estate",
            "subcategory":"Developer",
            "type":"Services"
        }
    ],
    "sg:phone":"+1 718 698 3960",
    "sg:postcode":"10314",
    "sg:province":"NY",
    "sg:tags":[
        "builder",
        "cemetery",
        "operative"
    ],
    "wof:name":"Heritage Hill",
    "wof:placetype":"venue"
},
  "geometry": {"coordinates":[-74.13498199999999,40.605802],"type":"Point"}
}