{
  "type": "Feature",
  "properties": {
    "addr:full":"22 Pine Ridge Dr Smithtown NY 11787",
    "addr:housenumber":"22",
    "addr:postcode":"11787",
    "addr:street":"Pine Ridge Dr",
    "iso:country":"US",
    "sg:address":"22 Pine Ridge Dr",
    "sg:city":"Smithtown",
    "sg:classifiers":[
        {
            "category":"Building & Trades",
            "subcategory":"Construction",
            "type":"Services"
        }
    ],
    "sg:phone":"+1 631 543 1033",
    "sg:postcode":"11787",
    "sg:province":"NY",
    "sg:tags":[
        "house"
    ],
    "wof:name":"J/H Remodeling Inc",
    "wof:placetype":"venue"
},
  "geometry": {"coordinates":[-73.24853400000001,40.838564],"type":"Point"}
}