{
  "type": "Feature",
  "properties": {
    "iso:country":"US",
    "sg:address":"327 Beach 19th St",
    "sg:city":"Far Rockaway",
    "sg:classifiers":[
        {
            "category":"Health Services",
            "subcategory":"Hospital",
            "type":"Services"
        }
    ],
    "sg:phone":"+1 718 869 7650",
    "sg:postcode":"11691",
    "sg:province":"NY",
    "sg:website":"www.ehs.org",
    "wof:name":"St Johns Episcopal Hospital",
    "wof:placetype":"venue"
},
  "geometry": {"coordinates":[-73.75309799999999,40.598099],"type":"Point"}
}