{
  "type": "Feature",
  "properties": {
    "iso:country":"US",
    "sg:address":"29 Lincoln Rd",
    "sg:city":"Medford",
    "sg:classifiers":[
        {
            "category":"Building & Trades",
            "subcategory":"Construction",
            "type":"Services"
        }
    ],
    "sg:phone":"+1 631 345 2539",
    "sg:postcode":"11763",
    "sg:province":"NY",
    "sg:tags":[
        "roofing",
        "contractor"
    ],
    "wof:name":"M Stevens Roofing Company Inc",
    "wof:placetype":"venue"
},
  "geometry": {"coordinates":[-72.953923,40.824707],"type":"Point"}
}