{
  "type": "Feature",
  "properties": {
    "addr:full":"2653 Coney Island Ave Brooklyn NY 11223",
    "addr:housenumber":"2653",
    "addr:postcode":"11223",
    "addr:street":"Coney Island Ave",
    "iso:country":"US",
    "sg:address":"2653 Coney Island Ave",
    "sg:city":"Brooklyn",
    "sg:classifiers":[
        {
            "category":"Sports & Exercise",
            "subcategory":"Gym",
            "type":"Entertainment"
        }
    ],
    "sg:phone":"+1 718 646 1400",
    "sg:postcode":"11223",
    "sg:province":"NY",
    "sg:tags":[
        "spa",
        "health"
    ],
    "wof:name":"Zebra Club",
    "wof:placetype":"venue"
},
  "geometry": {"coordinates":[-73.96062499999999,40.591939],"type":"Point"}
}