{
  "type": "Feature",
  "properties": {
    "iso:country":"US",
    "sg:address":"2956 Union Rd Ste 1A",
    "sg:city":"Cheektowaga",
    "sg:classifiers":[
        {
            "category":"Professional",
            "subcategory":"Lawyer & Legal Services",
            "type":"Services"
        }
    ],
    "sg:phone":"+1 716 681 0505",
    "sg:postcode":"14227",
    "sg:province":"NY",
    "sg:tags":[
        "divorce",
        "attorney",
        "criminal",
        "law",
        "bankruptcy"
    ],
    "sg:website":"http://www.wojtan.com",
    "wof:name":"Wojtan Gary J",
    "wof:placetype":"venue"
},
  "geometry": {"coordinates":[-78.754414,42.892792],"type":"Point"}
}