{
  "type": "Feature",
  "properties": {
    "addr:full":"3471 Richmond Rd Staten Island NY 10306",
    "addr:housenumber":"3471",
    "addr:postcode":"10306",
    "addr:street":"Richmond Rd",
    "iso:country":"US",
    "sg:address":"3471 Richmond Rd",
    "sg:city":"Staten Island",
    "sg:classifiers":[
        {
            "category":"Cafe",
            "type":"Food & Drink"
        }
    ],
    "sg:menulink":"http://www.allmenus.com/ny/staten-island/43401-nicos-cafe--trattoria/menu/",
    "sg:phone":"+1 718 351 5510",
    "sg:postcode":"10306",
    "sg:province":"NY",
    "sg:tags":[
        "italian"
    ],
    "wof:name":"Nico's Cafe & Trattoria",
    "wof:placetype":"venue"
},
  "geometry": {"coordinates":[-74.136517,40.572845],"type":"Point"}
}