{
  "type": "Feature",
  "properties": {
    "addr:full":"7081 US Hwy 9 Plattsburgh NY 12901",
    "addr:housenumber":"7081",
    "addr:postcode":"12901",
    "addr:street":"Us Hwy 9",
    "iso:country":"US",
    "sg:address":"7081 US Hwy 9",
    "sg:city":"Plattsburgh",
    "sg:classifiers":[
        {
            "category":"Restaurant",
            "type":"Food & Drink"
        }
    ],
    "sg:phone":"+1 518 563 6980",
    "sg:postcode":"12901",
    "sg:province":"NY",
    "wof:name":"Domenic's Restaurate",
    "wof:placetype":"venue"
},
  "geometry": {"coordinates":[-73.43695200000001,44.725149],"type":"Point"}
}