{
  "type": "Feature",
  "properties": {
    "addr:full":"1412 Unionport Rd Bronx NY 10462",
    "addr:housenumber":"1412",
    "addr:postcode":"10462",
    "addr:street":"Unionport Rd",
    "iso:country":"US",
    "sg:address":"1412 Unionport Rd",
    "sg:city":"Bronx",
    "sg:classifiers":[
        {
            "category":"Personal",
            "subcategory":"Beauty Salon",
            "type":"Services"
        }
    ],
    "sg:phone":"+1 718 824 0555",
    "sg:postcode":"10462",
    "sg:province":"NY",
    "wof:name":"Rosa's Beauty Shop",
    "wof:placetype":"venue"
},
  "geometry": {"coordinates":[-73.85428,40.834761],"type":"Point"}
}