{
  "type": "Feature",
  "properties": {
    "addr:full":"7 N Perry St Johnstown NY 12095",
    "addr:housenumber":"7",
    "addr:postcode":"12095",
    "addr:street":"N Perry St",
    "iso:country":"US",
    "sg:address":"7 N Perry St",
    "sg:city":"Johnstown",
    "sg:classifiers":[
        {
            "category":"Shopping",
            "subcategory":"Department Store",
            "type":"Retail Goods"
        },
        {
            "category":"Shopping",
            "subcategory":"Gifts & Souvenirs",
            "type":"Retail Goods"
        }
    ],
    "sg:phone":"+1 518 736 1021",
    "sg:postcode":"12095",
    "sg:province":"NY",
    "wof:name":"Bountiful",
    "wof:placetype":"venue"
},
  "geometry": {"coordinates":[-74.371385,43.007954],"type":"Point"}
}