{
  "type": "Feature",
  "properties": {
    "addr:full":"1622 Brentwood Rd Bay Shore NY 11706",
    "addr:housenumber":"1622",
    "addr:postcode":"11706",
    "addr:street":"Brentwood Rd",
    "iso:country":"US",
    "sg:address":"1622 Brentwood Rd",
    "sg:city":"Bay Shore",
    "sg:classifiers":[
        {
            "category":"Professional",
            "subcategory":"Lawyer & Legal Services",
            "type":"Services"
        }
    ],
    "sg:phone":"+1 631 231 7500",
    "sg:postcode":"11706",
    "sg:province":"NY",
    "sg:tags":[
        "attorney"
    ],
    "wof:name":"Zuckerman & Powers Esquires",
    "wof:placetype":"venue"
},
  "geometry": {"coordinates":[-73.24630000000001,40.763],"type":"Point"}
}