{
  "type": "Feature",
  "properties": {
    "addr:full":"171 E Main St Huntington NY 11743",
    "addr:housenumber":"171",
    "addr:postcode":"11743",
    "addr:street":"E Main St",
    "iso:country":"US",
    "sg:address":"171 E Main St",
    "sg:city":"Huntington",
    "sg:classifiers":[
        {
            "category":"Building & Trades",
            "subcategory":"Construction",
            "type":"Services"
        }
    ],
    "sg:phone":"+1 631 271 4900",
    "sg:postcode":"11743",
    "sg:province":"NY",
    "sg:tags":[
        "contractor"
    ],
    "wof:name":"Haddock Contracting Inc",
    "wof:placetype":"venue"
},
  "geometry": {"coordinates":[-73.400768,40.880249],"type":"Point"}
}