{
  "type": "Feature",
  "properties": {
    "addr:full":"1838 Anthony Ave Bronx NY 10457",
    "addr:housenumber":"1838",
    "addr:postcode":"10457",
    "addr:street":"Anthony Ave",
    "iso:country":"US",
    "sg:address":"1838 Anthony Ave",
    "sg:city":"Bronx",
    "sg:classifiers":[
        {
            "category":"Retail",
            "subcategory":"Laundry & Dry Cleaning",
            "type":"Services"
        }
    ],
    "sg:phone":"+1 718 299 8219",
    "sg:postcode":"10457",
    "sg:province":"NY",
    "sg:tags":[
        "cleaners"
    ],
    "wof:name":"Mariel's Cleaners",
    "wof:placetype":"venue"
},
  "geometry": {"coordinates":[-73.903565,40.847908],"type":"Point"}
}