{
  "type": "Feature",
  "properties": {
    "addr:full":"295 Auburn Ave Buffalo NY 14213",
    "addr:housenumber":"295",
    "addr:postcode":"14213",
    "addr:street":"Auburn Ave",
    "iso:country":"US",
    "sg:address":"295 Auburn Ave",
    "sg:city":"Buffalo",
    "sg:classifiers":[
        {
            "category":"Autos & Motor Vehicles",
            "subcategory":"Automobile Sales",
            "type":"Retail Goods"
        }
    ],
    "sg:phone":"+1 800 698 8813",
    "sg:postcode":"14213",
    "sg:province":"NY",
    "sg:tags":[
        "limo"
    ],
    "wof:name":"Mr Limousine Of Buffalo",
    "wof:placetype":"venue"
},
  "geometry": {"coordinates":[-78.889662,42.91835],"type":"Point"}
}