{
  "type": "Feature",
  "properties": {
    "addr:full":"3407 Old Yorktown Rd Yorktown Heights NY 10598",
    "addr:housenumber":"3407",
    "addr:postcode":"10598",
    "addr:street":"Old Yorktown Rd",
    "iso:country":"US",
    "sg:address":"3407 Old Yorktown Rd",
    "sg:city":"Yorktown Heights",
    "sg:classifiers":[
        {
            "category":"Education",
            "subcategory":"School",
            "type":"Public Place"
        }
    ],
    "sg:phone":"+1 914 245 3385",
    "sg:postcode":"10598",
    "sg:province":"NY",
    "wof:name":"Lakeland Alternative High Schl",
    "wof:placetype":"venue"
},
  "geometry": {"coordinates":[-73.815161,41.322002],"type":"Point"}
}