{
  "type": "Feature",
  "properties": {
    "addr:full":"14 Clooney Dr Henrietta NY 14467",
    "addr:housenumber":"14",
    "addr:postcode":"14467",
    "addr:street":"Clooney Dr",
    "iso:country":"US",
    "sg:address":"14 Clooney Dr",
    "sg:city":"Henrietta",
    "sg:classifiers":[
        {
            "category":"Professional",
            "subcategory":"Computer Services",
            "type":"Services"
        }
    ],
    "sg:phone":"+1 585 359 2187",
    "sg:postcode":"14467",
    "sg:province":"NY",
    "sg:tags":[
        "technical",
        "assistance",
        "support"
    ],
    "wof:name":"Sellerstrations",
    "wof:placetype":"venue"
},
  "geometry": {"coordinates":[-77.615763,43.057235],"type":"Point"}
}