{
  "type": "Feature",
  "properties": {
    "iso:country":"US",
    "sg:address":"2 Rocklea Dr",
    "sg:city":"Rochester",
    "sg:classifiers":[
        {
            "category":"Shopping",
            "subcategory":"Gifts & Souvenirs",
            "type":"Retail Goods"
        }
    ],
    "sg:phone":"+1   ",
    "sg:postcode":"14624",
    "sg:province":"NY",
    "wof:name":"Sweet Home Gifts",
    "wof:placetype":"venue"
},
  "geometry": {"coordinates":[-77.725505,43.147168],"type":"Point"}
}