{
  "type": "Feature",
  "properties": {
    "iso:country":"US",
    "sg:address":"307 7 Ave",
    "sg:city":"New York",
    "sg:classifiers":[
        {
            "category":"Wholesale",
            "subcategory":"Office Equipment",
            "type":"Manufacturing & Wholesale Goods"
        },
        {
            "category":"Shopping",
            "subcategory":"Stationery & Office Supplies",
            "type":"Retail Goods"
        }
    ],
    "sg:phone":"+1 212 741 5081",
    "sg:postcode":"10001",
    "sg:province":"NY",
    "sg:tags":[
        "album",
        "scrapbook",
        "computer"
    ],
    "wof:name":"Design Partners LLC",
    "wof:placetype":"venue"
},
  "geometry": {"coordinates":[-73.991563,40.749705],"type":"Point"}
}