{
  "type": "Feature",
  "properties": {
    "iso:country":"US",
    "sg:address":"1998 State Hwy 22B",
    "sg:city":"Morrisonville",
    "sg:classifiers":[
        {
            "category":"Food & Beverages",
            "subcategory":"Groceries & Convenience Stores",
            "type":"Retail Goods"
        }
    ],
    "sg:phone":"+1 518 561 8500",
    "sg:postcode":"12962",
    "sg:province":"NY",
    "wof:name":"Bill's Mini-Mart",
    "wof:placetype":"venue"
},
  "geometry": {"coordinates":[-73.551621,44.697668],"type":"Point"}
}