{
  "type": "Feature",
  "properties": {
    "iso:country":"US",
    "sg:address":"27 Northampton Rd",
    "sg:city":"Amsterdam",
    "sg:classifiers":[
        {
            "category":"Shopping",
            "subcategory":"Party Supplies",
            "type":"Retail Goods"
        }
    ],
    "sg:phone":"+1 518 843 2988",
    "sg:postcode":"12010",
    "sg:province":"NY",
    "sg:tags":[
        "decoration",
        "rental"
    ],
    "wof:name":"Party Fun And More",
    "wof:placetype":"venue"
},
  "geometry": {"coordinates":[-74.19869199999999,42.948761],"type":"Point"}
}