{
  "type": "Feature",
  "properties": {
    "addr:full":"83 Lott Ln Staten Island NY 10314",
    "addr:housenumber":"83",
    "addr:postcode":"10314",
    "addr:street":"Lott Ln",
    "iso:country":"US",
    "sg:address":"83 Lott Ln",
    "sg:city":"Staten Island",
    "sg:classifiers":[
        {
            "category":"Building & Trades",
            "subcategory":"Construction",
            "type":"Services"
        }
    ],
    "sg:phone":"+1 718 477 4445",
    "sg:postcode":"10314",
    "sg:province":"NY",
    "sg:tags":[
        "general",
        "contractor"
    ],
    "wof:name":"J & K Construction Corp",
    "wof:placetype":"venue"
},
  "geometry": {"coordinates":[-74.16649700000001,40.577304],"type":"Point"}
}