{
  "type": "Feature",
  "properties": {
    "addr:full":"12 Brewster Ter New Rochelle NY 10804",
    "addr:housenumber":"12",
    "addr:postcode":"10804",
    "addr:street":"Brewster Ter",
    "iso:country":"US",
    "sg:address":"12 Brewster Ter",
    "sg:city":"New Rochelle",
    "sg:classifiers":[
        {
            "category":"Professional",
            "subcategory":"Business Services",
            "type":"Services"
        }
    ],
    "sg:phone":"+1 914 576 1452",
    "sg:postcode":"10804",
    "sg:province":"NY",
    "sg:tags":[
        "event"
    ],
    "wof:name":"Pinkmonkey Events",
    "wof:placetype":"venue"
},
  "geometry": {"coordinates":[-73.794543,40.936023],"type":"Point"}
}