{
  "type": "Feature",
  "properties": {
    "iso:country":"US",
    "sg:address":"271 North Ave",
    "sg:city":"New Rochelle",
    "sg:classifiers":[
        {
            "category":"Professional",
            "subcategory":"Lawyer & Legal Services",
            "type":"Services"
        }
    ],
    "sg:phone":"+1 914 235 7234",
    "sg:postcode":"10801",
    "sg:province":"NY",
    "sg:tags":[
        "attorney"
    ],
    "wof:name":"Todd Rothenberg",
    "wof:placetype":"venue"
},
  "geometry": {"coordinates":[-73.782736,40.911964],"type":"Point"}
}