{
  "type": "Feature",
  "properties": {
    "iso:country":"US",
    "sg:address":"124 E Main St Suite 204",
    "sg:city":"Babylon",
    "sg:classifiers":[
        {
            "category":"Health Services",
            "subcategory":"Health Practitioner",
            "type":"Services"
        }
    ],
    "sg:phone":"+1 631 482 1344",
    "sg:postcode":"11702",
    "sg:province":"NY",
    "sg:tags":[
        "therapist",
        "physical"
    ],
    "wof:name":"Dynamic Performance Physical Therapy",
    "wof:placetype":"venue"
},
  "geometry": {"coordinates":[-73.32114199999999,40.696979],"type":"Point"}
}