{
  "type": "Feature",
  "properties": {
    "addr:full":"129 Ridge Street New York NY 10002",
    "addr:housenumber":"129",
    "addr:postcode":"10002",
    "addr:street":"Ridge Street",
    "iso:country":"US",
    "sg:address":"129 Ridge Street",
    "sg:city":"New York",
    "sg:classifiers":[
        {
            "category":"Deli",
            "type":"Food & Drink"
        },
        {
            "category":"Food & Beverages",
            "subcategory":"Bakery",
            "type":"Retail Goods"
        }
    ],
    "sg:phone":"+1 212 358 9989",
    "sg:postcode":"10002",
    "sg:province":"NY",
    "sg:tags":[
        "sandwich"
    ],
    "wof:name":"Pueblo Deli Grocery",
    "wof:placetype":"venue"
},
  "geometry": {"coordinates":[-73.983093,40.719472],"type":"Point"}
}