{
  "type": "Feature",
  "properties": {
    "addr:full":"5611 Palisade Ave Bronx NY 10471",
    "addr:housenumber":"5611",
    "addr:postcode":"10471",
    "addr:street":"Palisade Ave",
    "iso:country":"US",
    "sg:address":"5611 Palisade Ave",
    "sg:city":"Bronx",
    "sg:classifiers":[
        {
            "category":"Health Services",
            "subcategory":"Health Practitioner",
            "type":"Services"
        }
    ],
    "sg:phone":"+1   ",
    "sg:postcode":"10471",
    "sg:province":"NY",
    "wof:name":"Lorrie Gold",
    "wof:placetype":"venue"
},
  "geometry": {"coordinates":[-73.91034000000001,40.906651],"type":"Point"}
}