{
  "type": "Feature",
  "properties": {
    "iso:country":"US",
    "sg:address":"620 8th Ave",
    "sg:city":"New York",
    "sg:classifiers":[
        {
            "category":"Shopping",
            "subcategory":"Department Store",
            "type":"Retail Goods"
        },
        {
            "category":"Shopping",
            "subcategory":"Clothing, Apparel, & Fashions",
            "type":"Retail Goods"
        },
        {
            "category":"Home & Garden",
            "subcategory":"Garden Supply",
            "type":"Retail Goods"
        }
    ],
    "sg:phone":"+1 212 382 2300",
    "sg:postcode":"10018",
    "sg:province":"NY",
    "sg:tags":[
        "accessory",
        "clothing",
        "women's"
    ],
    "sg:website":"www.muji.us",
    "wof:name":"Muji",
    "wof:placetype":"venue"
},
  "geometry": {"coordinates":[-73.98978700000001,40.757221],"type":"Point"}
}