{
  "type": "Feature",
  "properties": {
    "addr:full":"20 Daniel St Amsterdam NY 12010",
    "addr:housenumber":"20",
    "addr:postcode":"12010",
    "addr:street":"Daniel St",
    "iso:country":"US",
    "sg:address":"20 Daniel St",
    "sg:city":"Amsterdam",
    "sg:classifiers":[
        {
            "category":"Professional",
            "subcategory":"Engineering",
            "type":"Services"
        }
    ],
    "sg:phone":"+1   ",
    "sg:postcode":"12010",
    "sg:province":"NY",
    "wof:name":"Civil Service Employees A",
    "wof:placetype":"venue"
},
  "geometry": {"coordinates":[-74.21397399999999,42.933091],"type":"Point"}
}