{
  "type": "Feature",
  "properties": {
    "iso:country":"US",
    "sg:address":"586 Winterton Rd",
    "sg:city":"Bloomingburg",
    "sg:classifiers":[
        {
            "category":"Wholesale",
            "subcategory":"Machinery & Supplies",
            "type":"Manufacturing & Wholesale Goods"
        }
    ],
    "sg:phone":"+1 845 733 4926",
    "sg:postcode":"12701",
    "sg:province":"NY",
    "sg:tags":[
        "contractor"
    ],
    "wof:name":"L B Smith Inc",
    "wof:placetype":"venue"
},
  "geometry": {"coordinates":[-74.476398,41.518181],"type":"Point"}
}