{
  "type": "Feature",
  "properties": {
    "addr:full":"664 Lexington Ave New York NY 10022",
    "addr:housenumber":"664",
    "addr:postcode":"10022",
    "addr:street":"Lexington Ave",
    "iso:country":"US",
    "sg:address":"664 Lexington Ave",
    "sg:city":"New York",
    "sg:classifiers":[
        {
            "category":"Shopping",
            "subcategory":"Luggage & Leather Goods",
            "type":"Retail Goods"
        }
    ],
    "sg:phone":"+1 212 906 0099",
    "sg:postcode":"10022",
    "sg:province":"NY",
    "wof:name":"Bonetta World Inc",
    "wof:placetype":"venue"
},
  "geometry": {"coordinates":[-73.969829,40.760037],"type":"Point"}
}