{
  "type": "Feature",
  "properties": {
    "addr:full":"170 Sanfordville Rd Warwick NY 10990",
    "addr:housenumber":"170",
    "addr:postcode":"10990",
    "addr:street":"Sanfordville Rd",
    "iso:country":"US",
    "sg:address":"170 Sanfordville Rd",
    "sg:city":"Warwick",
    "sg:classifiers":[
        {
            "category":"Education",
            "subcategory":"School",
            "type":"Public Place"
        }
    ],
    "sg:phone":"+1 845 988 0330",
    "sg:postcode":"10990",
    "sg:province":"NY",
    "wof:name":"Orange Ulster BOCES",
    "wof:placetype":"venue"
},
  "geometry": {"coordinates":[-74.389134,41.241905],"type":"Point"}
}