{
  "type": "Feature",
  "properties": {
    "iso:country":"US",
    "sg:address":"38 W 21st St Rm 300",
    "sg:city":"New York",
    "sg:classifiers":[
        {
            "category":"Retail",
            "subcategory":"Portrait Studio",
            "type":"Services"
        },
        {
            "category":"Professional",
            "subcategory":"Lawyer & Legal Services",
            "type":"Services"
        }
    ],
    "sg:phone":"+1 212 226 6344",
    "sg:postcode":"10010",
    "sg:province":"NY",
    "sg:tags":[
        "photography",
        "store"
    ],
    "wof:name":"Bond Art and Science",
    "wof:placetype":"venue"
},
  "geometry": {"coordinates":[-73.99179599999999,40.740659],"type":"Point"}
}