{
  "type": "Feature",
  "properties": {
    "addr:full":"61 E Kingsbridge Rd Bronx NY 10468",
    "addr:housenumber":"61",
    "addr:postcode":"10468",
    "addr:street":"E Kingsbridge Rd",
    "iso:country":"US",
    "sg:address":"61 E Kingsbridge Rd",
    "sg:city":"Bronx",
    "sg:classifiers":[
        {
            "category":"Shopping",
            "subcategory":"Jewelry",
            "type":"Retail Goods"
        }
    ],
    "sg:phone":"+1 718 733 7040",
    "sg:postcode":"10468",
    "sg:province":"NY",
    "wof:name":"Gold Star",
    "wof:placetype":"venue"
},
  "geometry": {"coordinates":[-73.89591299999999,40.867007],"type":"Point"}
}