{
  "type": "Feature",
  "properties": {
    "iso:country":"US",
    "sg:address":"40 Park Ave",
    "sg:city":"New York",
    "sg:classifiers":[
        {
            "category":"Communications",
            "subcategory":"Film & Video Production",
            "type":"Services"
        }
    ],
    "sg:phone":"+1 212 532 4268",
    "sg:postcode":"10016",
    "sg:province":"NY",
    "sg:tags":[
        "studio",
        "facility"
    ],
    "wof:name":"C M Productions",
    "wof:placetype":"venue"
},
  "geometry": {"coordinates":[-73.980087,40.748897],"type":"Point"}
}