{
  "type": "Feature",
  "properties": {
    "iso:country":"US",
    "sg:address":"907 Carter Creek Dr",
    "sg:city":"Grand Island",
    "sg:classifiers":[
        {
            "category":"Organizations",
            "subcategory":"Religious Organization",
            "type":"Services"
        }
    ],
    "sg:phone":"+1 716 688 4605",
    "sg:postcode":"14072",
    "sg:province":"NY",
    "sg:tags":[
        "church"
    ],
    "wof:name":"Church Of Jesus Christ Of Lds",
    "wof:placetype":"venue"
},
  "geometry": {"coordinates":[-78.961696,42.986773],"type":"Point"}
}