{
  "type": "Feature",
  "properties": {
    "addr:full":"37 George St Troy NY 12183",
    "addr:housenumber":"37",
    "addr:postcode":"12183",
    "addr:street":"George St",
    "iso:country":"US",
    "sg:address":"37 George St",
    "sg:city":"Troy",
    "sg:classifiers":[
        {
            "category":"Insurance",
            "subcategory":"Insurance Agent",
            "type":"Services"
        }
    ],
    "sg:phone":"+1 518 271 1394",
    "sg:postcode":"12183",
    "sg:province":"NY",
    "wof:name":"Bartolotta Connolly Insurance",
    "wof:placetype":"venue"
},
  "geometry": {"coordinates":[-73.69301400000001,42.739962],"type":"Point"}
}