{
  "type": "Feature",
  "properties": {
    "iso:country":"US",
    "sg:address":"9 Sheldon Ave",
    "sg:city":"Auburn",
    "sg:classifiers":[
        {
            "category":"Professional",
            "type":"Services"
        }
    ],
    "sg:phone":"+1 315 253 3129",
    "sg:postcode":"13021",
    "sg:province":"NY",
    "sg:tags":[
        "arts",
        "artist"
    ],
    "wof:name":"Luba Hanuschak Artist",
    "wof:placetype":"venue"
},
  "geometry": {"coordinates":[-76.58551900000001,42.93431],"type":"Point"}
}