{
  "type": "Feature",
  "properties": {
    "addr:full":"1615 9th Ave Ste 202 Bohemia NY 11716",
    "addr:housenumber":"1615",
    "addr:postcode":"11716",
    "addr:street":"9Th Ave Ste 202",
    "iso:country":"US",
    "sg:address":"1615 9th Ave Ste 202",
    "sg:city":"Bohemia",
    "sg:classifiers":[
        {
            "category":"Banks & Credit Unions",
            "subcategory":"Financial Services",
            "type":"Services"
        },
        {
            "category":"Professional",
            "subcategory":"Credit Reporting & Collection",
            "type":"Services"
        }
    ],
    "sg:phone":"+1 888 897 7084",
    "sg:postcode":"11716",
    "sg:province":"NY",
    "sg:tags":[
        "repair"
    ],
    "sg:website":"www.scoremorecredit.com",
    "wof:name":"Score More Credit",
    "wof:placetype":"venue"
},
  "geometry": {"coordinates":[-73.14064399999999,40.78768],"type":"Point"}
}