{
  "type": "Feature",
  "properties": {
    "addr:full":"88 Tollgate Rd Averill Park NY 12018",
    "addr:housenumber":"88",
    "addr:postcode":"12018",
    "addr:street":"Tollgate Rd",
    "iso:country":"US",
    "sg:address":"88 Tollgate Rd",
    "sg:city":"Averill Park",
    "sg:classifiers":[
        {
            "category":"Building & Trades",
            "subcategory":"Construction",
            "type":"Services"
        }
    ],
    "sg:phone":"+1 518 674 1152",
    "sg:postcode":"12018",
    "sg:province":"NY",
    "sg:tags":[
        "residential"
    ],
    "wof:name":"CC Construction Company",
    "wof:placetype":"venue"
},
  "geometry": {"coordinates":[-73.59094,42.649348],"type":"Point"}
}