{
  "type": "Feature",
  "properties": {
    "addr:full":"15 Main St Akron NY 14001",
    "addr:housenumber":"15",
    "addr:postcode":"14001",
    "addr:street":"Main St",
    "iso:country":"US",
    "sg:address":"15 Main St",
    "sg:city":"Akron",
    "sg:classifiers":[
        {
            "category":"Restaurant",
            "type":"Food & Drink"
        }
    ],
    "sg:phone":"+1 716 542 2280",
    "sg:postcode":"14001",
    "sg:province":"NY",
    "wof:name":"Akron House",
    "wof:placetype":"venue"
},
  "geometry": {"coordinates":[-78.502788,43.02021],"type":"Point"}
}