{
  "type": "Feature",
  "properties": {
    "addr:full":"79 Shady Creek Rd Rochester NY 14623",
    "addr:housenumber":"79",
    "addr:postcode":"14623",
    "addr:street":"Shady Creek Rd",
    "iso:country":"US",
    "sg:address":"79 Shady Creek Rd",
    "sg:city":"Rochester",
    "sg:classifiers":[
        {
            "category":"Building & Trades",
            "subcategory":"Construction",
            "type":"Services"
        }
    ],
    "sg:phone":"+1 585 615 7757",
    "sg:postcode":"14623",
    "sg:province":"NY",
    "sg:tags":[
        "residential",
        "commercial"
    ],
    "wof:name":"Native Sons Home Repair Svcs",
    "wof:placetype":"venue"
},
  "geometry": {"coordinates":[-77.588668,43.078837],"type":"Point"}
}