{
  "type": "Feature",
  "properties": {
    "iso:country":"US",
    "sg:address":"379 Green Valley Rd",
    "sg:city":"Staten Island",
    "sg:classifiers":[
        {
            "category":"Building & Trades",
            "subcategory":"Construction",
            "type":"Services"
        }
    ],
    "sg:phone":"+1 718 948 6414",
    "sg:postcode":"10312",
    "sg:province":"NY",
    "sg:tags":[
        "hanging",
        "contractor"
    ],
    "wof:name":"S & G Cleaning Service Inc",
    "wof:placetype":"venue"
},
  "geometry": {"coordinates":[-74.193102,40.549459],"type":"Point"}
}