{
  "type": "Feature",
  "properties": {
    "iso:country":"US",
    "sg:address":"298 Greece Ridge Center Dr",
    "sg:city":"Rochester",
    "sg:classifiers":[
        {
            "category":"Shopping",
            "subcategory":"Bicycles & Sporting Goods",
            "type":"Retail Goods"
        }
    ],
    "sg:phone":"+1   ",
    "sg:postcode":"14626",
    "sg:province":"NY",
    "wof:name":"Premier Sports Center",
    "wof:placetype":"venue"
},
  "geometry": {"coordinates":[-77.696348,43.20492],"type":"Point"}
}