{
  "type": "Feature",
  "properties": {
    "addr:full":"2 Malcolm X Blvd Brooklyn NY 11221",
    "addr:housenumber":"2",
    "addr:postcode":"11221",
    "addr:street":"Malcolm X Blvd",
    "iso:country":"US",
    "sg:address":"2 Malcolm X Blvd",
    "sg:city":"Brooklyn",
    "sg:classifiers":[
        {
            "category":"Shopping",
            "subcategory":"Computers & Home Electronics",
            "type":"Retail Goods"
        }
    ],
    "sg:phone":"+1 718 452 4269",
    "sg:postcode":"11221",
    "sg:province":"NY",
    "sg:tags":[
        "equipment",
        "dealer"
    ],
    "wof:name":"Socram Computers",
    "wof:placetype":"venue"
},
  "geometry": {"coordinates":[-73.93120399999999,40.693692],"type":"Point"}
}