{
  "type": "Feature",
  "properties": {
    "iso:country":"US",
    "sg:address":"40-35 82nd St.",
    "sg:city":"Flushing",
    "sg:classifiers":[
        {
            "category":"Food & Beverages",
            "subcategory":"Groceries & Convenience Stores",
            "type":"Retail Goods"
        }
    ],
    "sg:phone":"+1 718 205 7362",
    "sg:postcode":"11373",
    "sg:province":"NY",
    "wof:name":"Mango Rico",
    "wof:placetype":"venue"
},
  "geometry": {"coordinates":[-73.88377199999999,40.746719],"type":"Point"}
}