{
  "type": "Feature",
  "properties": {
    "iso:country":"US",
    "sg:address":"231 W 29th Street",
    "sg:city":"New York",
    "sg:classifiers":[
        {
            "category":"Shopping",
            "subcategory":"Clothing, Apparel, & Fashions",
            "type":"Retail Goods"
        }
    ],
    "sg:phone":"+1 212 239 2459",
    "sg:postcode":"10001",
    "sg:province":"NY",
    "sg:tags":[
        "clothing",
        "women's"
    ],
    "sg:website":"www.laurenmerkin.com",
    "wof:name":"Lauren Merkin Productions",
    "wof:placetype":"venue"
},
  "geometry": {"coordinates":[-73.994203,40.748634],"type":"Point"}
}