{
  "type": "Feature",
  "properties": {
    "addr:full":"1700 State St Schenectady NY 12304",
    "addr:housenumber":"1700",
    "addr:postcode":"12304",
    "addr:street":"State St",
    "iso:country":"US",
    "sg:address":"1700 State St",
    "sg:city":"Schenectady",
    "sg:classifiers":[
        {
            "category":"Autos & Motor Vehicles",
            "subcategory":"Automobile Sales",
            "type":"Retail Goods"
        }
    ],
    "sg:phone":"+1   ",
    "sg:postcode":"12304",
    "sg:province":"NY",
    "sg:tags":[
        "car",
        "used"
    ],
    "wof:name":"Eddie A Auto Sales",
    "wof:placetype":"venue"
},
  "geometry": {"coordinates":[-73.90797499999999,42.783941],"type":"Point"}
}