{
  "type": "Feature",
  "properties": {
    "iso:country":"US",
    "sg:address":"762 59th St",
    "sg:city":"Brooklyn",
    "sg:classifiers":[
        {
            "category":"Health Services",
            "subcategory":"Doctor",
            "type":"Services"
        }
    ],
    "sg:phone":"+1 718 567 8899",
    "sg:postcode":"11220",
    "sg:province":"NY",
    "sg:tags":[
        "practice",
        "family"
    ],
    "wof:name":"Jennan Comprehesive Medical",
    "wof:placetype":"venue"
},
  "geometry": {"coordinates":[-74.009687,40.636232],"type":"Point"}
}