{
  "type": "Feature",
  "properties": {
    "iso:country":"US",
    "sg:address":"7 Old Rd",
    "sg:city":"Elmsford",
    "sg:classifiers":[
        {
            "category":"Restaurant",
            "type":"Food & Drink"
        }
    ],
    "sg:phone":"+1   ",
    "sg:postcode":"10523",
    "sg:province":"NY",
    "sg:tags":[
        "cafe",
        "del"
    ],
    "wof:name":"Carmines Italian Deli & Cafe",
    "wof:placetype":"venue"
},
  "geometry": {"coordinates":[-73.811436,41.051456],"type":"Point"}
}