{
  "type": "Feature",
  "properties": {
    "addr:full":"67 S Main St Gloversville NY 12078",
    "addr:housenumber":"67",
    "addr:postcode":"12078",
    "addr:street":"S Main St",
    "iso:country":"US",
    "sg:address":"67 S Main St",
    "sg:city":"Gloversville",
    "sg:classifiers":[
        {
            "category":"Professional",
            "type":"Services"
        }
    ],
    "sg:phone":"+1 518 773 7387",
    "sg:postcode":"12078",
    "sg:province":"NY",
    "sg:tags":[
        "establishment"
    ],
    "wof:name":"James A Brennan Meml Humane",
    "wof:placetype":"venue"
},
  "geometry": {"coordinates":[-74.347058,43.048581],"type":"Point"}
}