{
  "type": "Feature",
  "properties": {
    "iso:country":"US",
    "sg:address":"171 W 107th St",
    "sg:city":"New York",
    "sg:classifiers":[
        {
            "category":"Social Services",
            "type":"Services"
        }
    ],
    "sg:phone":"+1 212 663 4070",
    "sg:postcode":"10025",
    "sg:province":"NY",
    "sg:tags":[
        "family",
        "child"
    ],
    "wof:name":"Bloomingdale Family Program",
    "wof:placetype":"venue"
},
  "geometry": {"coordinates":[-73.963644,40.800322],"type":"Point"}
}