{
  "type": "Feature",
  "properties": {
    "iso:country":"US",
    "sg:address":"20 Manning Dr",
    "sg:city":"East Northport",
    "sg:classifiers":[
        {
            "category":"Recreation",
            "type":"Entertainment"
        }
    ],
    "sg:phone":"+1 631 368 2605",
    "sg:postcode":"11731",
    "sg:province":"NY",
    "sg:tags":[
        "club",
        "sport"
    ],
    "wof:name":"Commack Soccer League Inc",
    "wof:placetype":"venue"
},
  "geometry": {"coordinates":[-73.310737,40.852002],"type":"Point"}
}