{
  "type": "Feature",
  "properties": {
    "iso:country":"US",
    "sg:address":"106 Norfolk St",
    "sg:city":"New York",
    "sg:classifiers":[
        {
            "category":"Manufacturing",
            "subcategory":"Apparel",
            "type":"Manufacturing & Wholesale Goods"
        }
    ],
    "sg:phone":"+1   ",
    "sg:postcode":"10002",
    "sg:province":"NY",
    "sg:tags":[
        "design",
        "hat",
        "accessory"
    ],
    "wof:name":"Casa De Rodriguez",
    "wof:placetype":"venue"
},
  "geometry": {"coordinates":[-73.986897,40.719016],"type":"Point"}
}