{
  "type": "Feature",
  "properties": {
    "iso:country":"US",
    "sg:address":"18 Roe Ave",
    "sg:city":"Albany",
    "sg:classifiers":[
        {
            "category":"Manufacturing",
            "subcategory":"Signs",
            "type":"Manufacturing & Wholesale Goods"
        },
        {
            "category":"Manufacturing",
            "subcategory":"Apparel",
            "type":"Manufacturing & Wholesale Goods"
        }
    ],
    "sg:phone":"+1 518 435 9670",
    "sg:postcode":"12205",
    "sg:province":"NY",
    "sg:tags":[
        "flag",
        "banner",
        "specialty",
        "mfg"
    ],
    "sg:website":"www.capitalsignsmith.com",
    "wof:name":"Capital Signsmith Inc",
    "wof:placetype":"venue"
},
  "geometry": {"coordinates":[-73.799588,42.700578],"type":"Point"}
}