{
  "type": "Feature",
  "properties": {
    "iso:country":"US",
    "sg:address":"33 Willoughby Path",
    "sg:city":"East Northport",
    "sg:classifiers":[
        {
            "category":"Professional",
            "type":"Services"
        }
    ],
    "sg:phone":"+1 631 499 8040",
    "sg:postcode":"11731",
    "sg:province":"NY",
    "sg:tags":[
        "establishment"
    ],
    "wof:name":"John F Murry Co Inc",
    "wof:placetype":"venue"
},
  "geometry": {"coordinates":[-73.32477299999999,40.831872],"type":"Point"}
}