{
  "type": "Feature",
  "properties": {
    "addr:full":"929 Dundee-Glenora Rd Dundee NY 14837",
    "addr:housenumber":"929",
    "addr:postcode":"14837",
    "addr:street":"Dundee-Glenora Rd",
    "iso:country":"US",
    "sg:address":"929 Dundee-Glenora Rd",
    "sg:city":"Dundee",
    "sg:classifiers":[
        {
            "category":"Government",
            "subcategory":"Office",
            "type":"Public Place"
        }
    ],
    "sg:phone":"+1 607 243 8121",
    "sg:postcode":"14837",
    "sg:province":"NY",
    "sg:tags":[
        "village"
    ],
    "wof:name":"Dundee Waste Water Plant",
    "wof:placetype":"venue"
},
  "geometry": {"coordinates":[-76.969098,42.516091],"type":"Point"}
}