{
  "type": "Feature",
  "properties": {
    "iso:country":"US",
    "sg:address":"668 Seneca Ave",
    "sg:city":"Flushing",
    "sg:classifiers":[
        {
            "category":"Banks & Credit Unions",
            "subcategory":"Bank",
            "type":"Services"
        }
    ],
    "sg:phone":"+1 718 821 5528",
    "sg:postcode":"11385",
    "sg:province":"NY",
    "sg:tags":[
        "money",
        "transfer"
    ],
    "wof:name":"Western Union",
    "wof:placetype":"venue"
},
  "geometry": {"coordinates":[-73.90889900000001,40.703519],"type":"Point"}
}