{
  "type": "Feature",
  "properties": {
    "iso:country":"US",
    "sg:address":"2140 Bartow Ave",
    "sg:city":"Bronx",
    "sg:classifiers":[
        {
            "category":"Shopping",
            "subcategory":"Clothing, Apparel, & Fashions",
            "type":"Retail Goods"
        }
    ],
    "sg:phone":"+1   ",
    "sg:postcode":"10475",
    "sg:province":"NY",
    "sg:tags":[
        "family"
    ],
    "wof:name":"Sooeun Company",
    "wof:placetype":"venue"
},
  "geometry": {"coordinates":[-73.82238700000001,40.868636],"type":"Point"}
}