{
  "type": "Feature",
  "properties": {
    "addr:full":"831 Ave of the Americas New York NY 10001",
    "addr:housenumber":"831",
    "addr:postcode":"10001",
    "addr:street":"Ave Of The Americas",
    "iso:country":"US",
    "sg:address":"831 Ave of the Americas",
    "sg:city":"New York",
    "sg:classifiers":[
        {
            "category":"Recreation",
            "type":"Entertainment"
        }
    ],
    "sg:phone":"+1 212 244 7300",
    "sg:postcode":"10001",
    "sg:province":"NY",
    "sg:tags":[
        "psychic",
        "medium"
    ],
    "wof:name":"Brandy Demetro Astrology",
    "wof:placetype":"venue"
},
  "geometry": {"coordinates":[-73.99051799999999,40.746038],"type":"Point"}
}