{
  "type": "Feature",
  "properties": {
    "addr:full":"1457 Northern Blvd Manhasset NY 11030",
    "addr:housenumber":"1457",
    "addr:postcode":"11030",
    "addr:street":"Northern Blvd",
    "iso:country":"US",
    "sg:address":"1457 Northern Blvd",
    "sg:city":"Manhasset",
    "sg:classifiers":[
        {
            "category":"Home & Garden",
            "subcategory":"Furniture",
            "type":"Retail Goods"
        }
    ],
    "sg:phone":"+1 516 627 2420",
    "sg:postcode":"11030",
    "sg:province":"NY",
    "sg:tags":[
        "store"
    ],
    "wof:name":"Door Store",
    "wof:placetype":"venue"
},
  "geometry": {"coordinates":[-73.693027,40.793611],"type":"Point"}
}