{
  "type": "Feature",
  "properties": {
    "addr:full":"933 Chestnut Ridge Rd Spring Valley NY 10977",
    "addr:housenumber":"933",
    "addr:postcode":"10977",
    "addr:street":"Chestnut Ridge Rd",
    "iso:country":"US",
    "sg:address":"933 Chestnut Ridge Rd",
    "sg:city":"Spring Valley",
    "sg:classifiers":[
        {
            "category":"Building & Trades",
            "subcategory":"Construction",
            "type":"Services"
        }
    ],
    "sg:phone":"+1 845 578 4093",
    "sg:postcode":"10977",
    "sg:province":"NY",
    "sg:tags":[
        "general",
        "contractor"
    ],
    "wof:name":"Bennie's Professional Floor",
    "wof:placetype":"venue"
},
  "geometry": {"coordinates":[-74.04611199999999,41.100902],"type":"Point"}
}