{
  "type": "Feature",
  "properties": {
    "addr:full":"6 Lewis Rd Saratoga Springs NY 12866",
    "addr:housenumber":"6",
    "addr:postcode":"12866",
    "addr:street":"Lewis Rd",
    "iso:country":"US",
    "sg:address":"6 Lewis Rd",
    "sg:city":"Saratoga Springs",
    "sg:classifiers":[
        {
            "category":"Real Estate",
            "subcategory":"Real Estate Agent",
            "type":"Services"
        }
    ],
    "sg:phone":"+1 518 691 0500",
    "sg:postcode":"12866",
    "sg:province":"NY",
    "wof:name":"Real Estate Executives First",
    "wof:placetype":"venue"
},
  "geometry": {"coordinates":[-73.750692,43.118702],"type":"Point"}
}