{
  "type": "Feature",
  "properties": {
    "iso:country":"US",
    "sg:address":"283 Fulton Ave",
    "sg:city":"Hempstead",
    "sg:classifiers":[
        {
            "category":"Restaurant",
            "type":"Food & Drink"
        }
    ],
    "sg:phone":"+1 516 505 0951",
    "sg:postcode":"11550",
    "sg:province":"NY",
    "wof:name":"Caribe Restaurant",
    "wof:placetype":"venue"
},
  "geometry": {"coordinates":[-73.62698899999999,40.707657],"type":"Point"}
}