{
  "type": "Feature",
  "properties": {
    "iso:country":"US",
    "sg:address":"59 Merrick Rd Ste C",
    "sg:city":"Amityville",
    "sg:classifiers":[
        {
            "category":"Restaurant",
            "type":"Food & Drink"
        }
    ],
    "sg:phone":"+1 631 598 2270",
    "sg:postcode":"11701",
    "sg:province":"NY",
    "wof:name":"Carolina's Ii Pizza & Restaurant",
    "wof:placetype":"venue"
},
  "geometry": {"coordinates":[-73.42087600000001,40.671532],"type":"Point"}
}