{
  "type": "Feature",
  "properties": {
    "addr:full":"1210 Colvin Blvd Buffalo NY 14223",
    "addr:housenumber":"1210",
    "addr:postcode":"14223",
    "addr:street":"Colvin Blvd",
    "iso:country":"US",
    "sg:address":"1210 Colvin Blvd",
    "sg:city":"Buffalo",
    "sg:classifiers":[
        {
            "category":"Food & Beverages",
            "subcategory":"Groceries & Convenience Stores",
            "type":"Retail Goods"
        }
    ],
    "sg:phone":"+1   ",
    "sg:postcode":"14223",
    "sg:province":"NY",
    "wof:name":"Dashs Market",
    "wof:placetype":"venue"
},
  "geometry": {"coordinates":[-78.85852300000001,42.975284],"type":"Point"}
}