{
  "type": "Feature",
  "properties": {
    "addr:full":"2110 Northern Blvd Ste 201 Manhasset NY 11030",
    "addr:housenumber":"2110",
    "addr:postcode":"11030",
    "addr:street":"Northern Blvd Ste 201",
    "iso:country":"US",
    "sg:address":"2110 Northern Blvd Ste 201",
    "sg:city":"Manhasset",
    "sg:classifiers":[
        {
            "category":"Shopping Center",
            "type":"Public Place"
        }
    ],
    "sg:phone":"+1 516 627 6700",
    "sg:postcode":"11030",
    "sg:province":"NY",
    "sg:tags":[
        "mall"
    ],
    "wof:name":"Wheatley Plaza Associates",
    "wof:placetype":"venue"
},
  "geometry": {"coordinates":[-73.67148400000001,40.796607],"type":"Point"}
}