{
  "type": "Feature",
  "properties": {
    "iso:country":"US",
    "sg:address":"5789 Widewaters Pkwy",
    "sg:city":"Syracuse",
    "sg:classifiers":[
        {
            "category":"Banks & Credit Unions",
            "subcategory":"Investment Brokerage",
            "type":"Services"
        }
    ],
    "sg:phone":"+1 315 449 2715",
    "sg:postcode":"13214",
    "sg:province":"NY",
    "sg:tags":[
        "planning",
        "financial"
    ],
    "wof:name":"American Express",
    "wof:placetype":"venue"
},
  "geometry": {"coordinates":[-76.06353,43.046161],"type":"Point"}
}