{
  "type": "Feature",
  "properties": {
    "iso:country":"US",
    "sg:address":"145 Rochester St",
    "sg:city":"Salamanca",
    "sg:classifiers":[
        {
            "category":"Wholesale",
            "subcategory":"Construction Materials",
            "type":"Manufacturing & Wholesale Goods"
        }
    ],
    "sg:phone":"+1 716 945 5331",
    "sg:postcode":"14779",
    "sg:province":"NY",
    "sg:tags":[
        "lumber"
    ],
    "wof:name":"Sundried Wood Technologies",
    "wof:placetype":"venue"
},
  "geometry": {"coordinates":[-78.709698,42.159595],"type":"Point"}
}