{
  "type": "Feature",
  "properties": {
    "iso:country":"US",
    "sg:address":"134 State St",
    "sg:city":"Albany",
    "sg:classifiers":[
        {
            "category":"Shopping",
            "subcategory":"News",
            "type":"Retail Goods"
        }
    ],
    "sg:phone":"+1 518 427 7365",
    "sg:postcode":"12207",
    "sg:province":"NY",
    "sg:tags":[
        "dealer"
    ],
    "wof:name":"Max's Snax",
    "wof:placetype":"venue"
},
  "geometry": {"coordinates":[-73.75478,42.650801],"type":"Point"}
}