{
  "type": "Feature",
  "properties": {
    "addr:full":"132 Mott St Oceanside NY 11572",
    "addr:housenumber":"132",
    "addr:postcode":"11572",
    "addr:street":"Mott St",
    "iso:country":"US",
    "sg:address":"132 Mott St",
    "sg:city":"Oceanside",
    "sg:classifiers":[
        {
            "category":"Shopping",
            "subcategory":"Stationery & Office Supplies",
            "type":"Retail Goods"
        }
    ],
    "sg:phone":"+1 516 766 7917",
    "sg:postcode":"11572",
    "sg:province":"NY",
    "sg:tags":[
        "stationer",
        "equipment"
    ],
    "wof:name":"Guppa Enterprises",
    "wof:placetype":"venue"
},
  "geometry": {"coordinates":[-73.634697,40.626202],"type":"Point"}
}