{
  "type": "Feature",
  "properties": {
    "addr:full":"522 Trolley Blvd Rochester NY 14606",
    "addr:housenumber":"522",
    "addr:postcode":"14606",
    "addr:street":"Trolley Blvd",
    "iso:country":"US",
    "sg:address":"522 Trolley Blvd",
    "sg:city":"Rochester",
    "sg:classifiers":[
        {
            "category":"Professional",
            "subcategory":"Business Services",
            "type":"Services"
        }
    ],
    "sg:phone":"+1 585 426 5420",
    "sg:postcode":"14606",
    "sg:province":"NY",
    "sg:tags":[
        "automobile",
        "used",
        "auctioneer"
    ],
    "sg:website":"www.salvagemgt.com",
    "wof:name":"Insurance Auto Auctions Inc",
    "wof:placetype":"venue"
},
  "geometry": {"coordinates":[-77.683026,43.171611],"type":"Point"}
}