{
  "type": "Feature",
  "properties": {
    "iso:country":"US",
    "sg:address":"1725 Purdy St",
    "sg:city":"Bronx",
    "sg:classifiers":[
        {
            "category":"Freight",
            "type":"Transportation"
        }
    ],
    "sg:phone":"+1 718 863 4841",
    "sg:postcode":"10462",
    "sg:province":"NY",
    "sg:tags":[
        "trucking"
    ],
    "wof:name":"Ebony Trucking",
    "wof:placetype":"venue"
},
  "geometry": {"coordinates":[-73.854851,40.841369],"type":"Point"}
}