{
  "type": "Feature",
  "properties": {
    "iso:country":"US",
    "sg:address":"41 Prospect Ave",
    "sg:city":"Ardsley",
    "sg:classifiers":[
        {
            "category":"Retail",
            "subcategory":"Repair Shop",
            "type":"Services"
        }
    ],
    "sg:phone":"+1 914 693 3325",
    "sg:postcode":"10502",
    "sg:province":"NY",
    "sg:tags":[
        "clocks",
        "parts"
    ],
    "wof:name":"Youth Employment Svc",
    "wof:placetype":"venue"
},
  "geometry": {"coordinates":[-73.84001499999999,41.005004],"type":"Point"}
}