{
  "type": "Feature",
  "properties": {
    "iso:country":"US",
    "sg:address":"4756 Route 50",
    "sg:city":"Gansevoort",
    "sg:classifiers":[
        {
            "category":"Personal",
            "type":"Services"
        },
        {
            "category":"Shopping",
            "subcategory":"Antiques",
            "type":"Retail Goods"
        },
        {
            "category":"Professional",
            "subcategory":"Business Services",
            "type":"Services"
        }
    ],
    "sg:phone":"+1 518 798 4289",
    "sg:postcode":"12831",
    "sg:province":"NY",
    "sg:tags":[
        "auction",
        "estates-sales",
        "liquidation",
        "appraiser",
        "appraisal"
    ],
    "sg:website":"http://www.cherrytreeauction.com",
    "wof:name":"Michael S Smith Antiques",
    "wof:placetype":"venue"
},
  "geometry": {"coordinates":[-73.66557400000001,43.165058],"type":"Point"}
}