{
  "type": "Feature",
  "properties": {
    "addr:full":"13515 37th Ave Flushing NY 11354",
    "addr:housenumber":"13515",
    "addr:postcode":"11354",
    "addr:street":"37Th Ave",
    "iso:country":"US",
    "sg:address":"13515 37th Ave",
    "sg:city":"Flushing",
    "sg:classifiers":[
        {
            "category":"Health Services",
            "subcategory":"Doctor",
            "type":"Services"
        }
    ],
    "sg:phone":"+1 718 321 3373",
    "sg:postcode":"11354",
    "sg:province":"NY",
    "wof:name":"J P& P Consolidated Corp",
    "wof:placetype":"venue"
},
  "geometry": {"coordinates":[-73.83185899999999,40.761423],"type":"Point"}
}