{
  "type": "Feature",
  "properties": {
    "addr:full":"5417 Merrick Rd Massapequa NY 11758",
    "addr:housenumber":"5417",
    "addr:postcode":"11758",
    "addr:street":"Merrick Rd",
    "iso:country":"US",
    "sg:address":"5417 Merrick Rd",
    "sg:city":"Massapequa",
    "sg:classifiers":[
        {
            "category":"Professional",
            "subcategory":"Accounting & Tax Preparation",
            "type":"Services"
        }
    ],
    "sg:phone":"+1 516 798 3546",
    "sg:postcode":"11758",
    "sg:province":"NY",
    "sg:tags":[
        "return",
        "filing"
    ],
    "wof:name":"R & G Brenner Income Tax Ctr",
    "wof:placetype":"venue"
},
  "geometry": {"coordinates":[-73.43678,40.668296],"type":"Point"}
}