{
  "type": "Feature",
  "properties": {
    "iso:country":"US",
    "sg:address":"118 Montgomery St",
    "sg:city":"Rhinebeck",
    "sg:classifiers":[
        {
            "category":"Building & Trades",
            "subcategory":"Construction",
            "type":"Services"
        }
    ],
    "sg:phone":"+1 845 876 1666",
    "sg:postcode":"12572",
    "sg:province":"NY",
    "sg:tags":[
        "painter"
    ],
    "wof:name":"A Quality Painting",
    "wof:placetype":"venue"
},
  "geometry": {"coordinates":[-73.91437000000001,41.934909],"type":"Point"}
}