{
  "type": "Feature",
  "properties": {
    "addr:full":"20 Meacham Ave Elmont NY 11003",
    "addr:housenumber":"20",
    "addr:postcode":"11003",
    "addr:street":"Meacham Ave",
    "iso:country":"US",
    "sg:address":"20 Meacham Ave",
    "sg:city":"Elmont",
    "sg:classifiers":[
        {
            "category":"Insurance",
            "subcategory":"Insurance Agent",
            "type":"Services"
        }
    ],
    "sg:phone":"+1 516 775 3955",
    "sg:postcode":"11003",
    "sg:province":"NY",
    "wof:name":"Nationwide",
    "wof:placetype":"venue"
},
  "geometry": {"coordinates":[-73.690431,40.707],"type":"Point"}
}