{
  "type": "Feature",
  "properties": {
    "addr:full":"153 Amsterdam Ave Staten Island NY 10314",
    "addr:housenumber":"153",
    "addr:postcode":"10314",
    "addr:street":"Amsterdam Ave",
    "iso:country":"US",
    "sg:address":"153 Amsterdam Ave",
    "sg:city":"Staten Island",
    "sg:classifiers":[
        {
            "category":"Retail",
            "subcategory":"Repair Shop",
            "type":"Services"
        }
    ],
    "sg:phone":"+1   ",
    "sg:postcode":"10314",
    "sg:province":"NY",
    "wof:name":"Gasworks Inc",
    "wof:placetype":"venue"
},
  "geometry": {"coordinates":[-74.16893,40.604588],"type":"Point"}
}