{
  "type": "Feature",
  "properties": {
    "addr:full":"10 E 70 St New York NY 10021",
    "addr:housenumber":"10;70",
    "addr:postcode":"10021",
    "addr:street":"E",
    "iso:country":"US",
    "sg:address":"10 E 70 St",
    "sg:city":"New York",
    "sg:classifiers":[
        {
            "category":"Shopping",
            "subcategory":"Used Merchandise",
            "type":"Retail Goods"
        }
    ],
    "sg:phone":"+1   ",
    "sg:postcode":"10021",
    "sg:province":"NY",
    "wof:name":"Rose Paulette Fine & Rare Bks",
    "wof:placetype":"venue"
},
  "geometry": {"coordinates":[-73.966829,40.770635],"type":"Point"}
}