{
  "type": "Feature",
  "properties": {
    "addr:full":"122 S 2nd Ave Mechanicville NY 12118",
    "addr:housenumber":"122",
    "addr:postcode":"12118",
    "addr:street":"S 2Nd Ave",
    "iso:country":"US",
    "sg:address":"122 S 2nd Ave",
    "sg:city":"Mechanicville",
    "sg:classifiers":[
        {
            "category":"Professional",
            "subcategory":"Lawyer & Legal Services",
            "type":"Services"
        }
    ],
    "sg:phone":"+1 518 664 6114",
    "sg:postcode":"12118",
    "sg:province":"NY",
    "sg:tags":[
        "attorney"
    ],
    "wof:name":"Carola Bagnoli & Tollisen",
    "wof:placetype":"venue"
},
  "geometry": {"coordinates":[-73.69105,42.902527],"type":"Point"}
}