{
  "type": "Feature",
  "properties": {
    "iso:country":"US",
    "sg:address":"1844 East Ave",
    "sg:city":"Rochester",
    "sg:classifiers":[
        {
            "category":"Restaurant",
            "type":"Food & Drink"
        }
    ],
    "sg:phone":"+1   ",
    "sg:postcode":"14610",
    "sg:province":"NY",
    "sg:tags":[
        "eating"
    ],
    "wof:name":"Wendys",
    "wof:placetype":"venue"
},
  "geometry": {"coordinates":[-77.5531,43.144992],"type":"Point"}
}