{
  "type": "Feature",
  "properties": {
    "addr:full":"227 E 59 St New York NY 10022",
    "addr:housenumber":"227;59",
    "addr:postcode":"10022",
    "addr:street":"E;St",
    "iso:country":"US",
    "sg:address":"227 E 59 St",
    "sg:city":"New York",
    "sg:classifiers":[
        {
            "category":"Manufacturing",
            "subcategory":"Furniture",
            "type":"Manufacturing & Wholesale Goods"
        },
        {
            "category":"Building & Trades",
            "subcategory":"Construction",
            "type":"Services"
        }
    ],
    "sg:phone":"+1 212 750 9800",
    "sg:postcode":"10022",
    "sg:province":"NY",
    "sg:tags":[
        "manufacture",
        "household",
        "wood",
        "woodworker"
    ],
    "wof:name":"Manhattan Cabinetry Inc",
    "wof:placetype":"venue"
},
  "geometry": {"coordinates":[-73.964748,40.760919],"type":"Point"}
}