{
  "type": "Feature",
  "properties": {
    "iso:country":"US",
    "sg:address":"277 E 3rd St",
    "sg:city":"Mt Vernon",
    "sg:classifiers":[
        {
            "category":"Retail",
            "subcategory":"Laundry & Dry Cleaning",
            "type":"Services"
        }
    ],
    "sg:phone":"+1 914 663 1738",
    "sg:postcode":"10553",
    "sg:province":"NY",
    "wof:name":"City Wide Super Laundry Ctr",
    "wof:placetype":"venue"
},
  "geometry": {"coordinates":[-73.82482,40.909283],"type":"Point"}
}