{
  "type": "Feature",
  "properties": {
    "iso:country":"US",
    "sg:address":"39 Union Pl",
    "sg:city":"Islip",
    "sg:classifiers":[
        {
            "category":"Professional",
            "type":"Services"
        }
    ],
    "sg:phone":"+1   ",
    "sg:postcode":"11751",
    "sg:province":"NY",
    "wof:name":"Home Vision Center",
    "wof:placetype":"venue"
},
  "geometry": {"coordinates":[-73.214068,40.720694],"type":"Point"}
}