{
  "type": "Feature",
  "properties": {
    "iso:country":"US",
    "sg:address":"2215 Burdett Ave",
    "sg:city":"Troy",
    "sg:classifiers":[
        {
            "category":"Social Services",
            "type":"Services"
        }
    ],
    "sg:phone":"+1 518 271 3445",
    "sg:postcode":"12180",
    "sg:province":"NY",
    "sg:tags":[
        "program",
        "crisis",
        "rape"
    ],
    "wof:name":"Sexual Assault Cr Cntr Rensler",
    "wof:placetype":"venue"
},
  "geometry": {"coordinates":[-73.670785,42.735696],"type":"Point"}
}