{
  "type": "Feature",
  "properties": {
    "addr:full":"632 Broadway New York NY 10012",
    "addr:housenumber":"632",
    "addr:postcode":"10012",
    "addr:street":"Broadway",
    "iso:country":"US",
    "sg:address":"632 Broadway",
    "sg:city":"New York",
    "sg:classifiers":[
        {
            "category":"Professional",
            "subcategory":"Management & Consulting",
            "type":"Services"
        }
    ],
    "sg:phone":"+1   ",
    "sg:postcode":"10012",
    "sg:province":"NY",
    "sg:tags":[
        "marketing",
        "email",
        "campaign"
    ],
    "wof:name":"Industryscoop",
    "wof:placetype":"venue"
},
  "geometry": {"coordinates":[-73.99628800000001,40.725695],"type":"Point"}
}