{
  "type": "Feature",
  "properties": {
    "iso:country":"US",
    "sg:address":"29 Laurie Lea",
    "sg:city":"Buffalo",
    "sg:classifiers":[
        {
            "category":"Place Of Worship",
            "subcategory":"Church",
            "type":"Public Place"
        },
        {
            "category":"Place Of Worship",
            "type":"Public Place"
        },
        {
            "category":"Organizations",
            "subcategory":"Religious Organization",
            "type":"Services"
        }
    ],
    "sg:phone":"+1 716 741 2947",
    "sg:postcode":"14221",
    "sg:province":"NY",
    "sg:tags":[
        "god",
        "god-independent",
        "churches-assemblies"
    ],
    "wof:name":"Trinity Capital Funding Inc",
    "wof:placetype":"venue"
},
  "geometry": {"coordinates":[-78.735497,42.999908],"type":"Point"}
}