{
  "type": "Feature",
  "properties": {
    "addr:full":"180 Locust Avenue Bronx NY 10454",
    "addr:housenumber":"180",
    "addr:postcode":"10454",
    "addr:street":"Locust Avenue",
    "iso:country":"US",
    "sg:address":"180 Locust Avenue",
    "sg:city":"Bronx",
    "sg:classifiers":[
        {
            "category":"Personal",
            "type":"Services"
        }
    ],
    "sg:phone":"+1 718 742 0825",
    "sg:postcode":"10454",
    "sg:province":"NY",
    "sg:tags":[
        "mover"
    ],
    "wof:name":"Brothers & Company",
    "wof:placetype":"venue"
},
  "geometry": {"coordinates":[-73.908574,40.80068],"type":"Point"}
}