{
  "type": "Feature",
  "properties": {
    "addr:full":"26 W Broad St Haverstraw NY 10927",
    "addr:housenumber":"26",
    "addr:postcode":"10927",
    "addr:street":"W Broad St",
    "iso:country":"US",
    "sg:address":"26 W Broad St",
    "sg:city":"Haverstraw",
    "sg:classifiers":[
        {
            "category":"Wholesale",
            "subcategory":"Painting Supplies",
            "type":"Manufacturing & Wholesale Goods"
        }
    ],
    "sg:phone":"+1 845 947 0019",
    "sg:postcode":"10927",
    "sg:province":"NY",
    "sg:tags":[
        "paint"
    ],
    "wof:name":"Andrews Paints & Varnish Co",
    "wof:placetype":"venue"
},
  "geometry": {"coordinates":[-73.96526799999999,41.197374],"type":"Point"}
}