{
  "type": "Feature",
  "properties": {
    "iso:country":"US",
    "sg:address":"8 Hawley St",
    "sg:city":"Binghamton",
    "sg:classifiers":[
        {
            "category":"Banks & Credit Unions",
            "subcategory":"Investment Brokerage",
            "type":"Services"
        }
    ],
    "sg:phone":"+1 607 722 4600",
    "sg:postcode":"13901",
    "sg:province":"NY",
    "sg:tags":[
        "advisory",
        "financial"
    ],
    "wof:name":"Primerica",
    "wof:placetype":"venue"
},
  "geometry": {"coordinates":[-75.91371599999999,42.097246],"type":"Point"}
}