{
  "type": "Feature",
  "properties": {
    "addr:full":"9518 Avenue L Brooklyn NY 11236",
    "addr:housenumber":"9518",
    "addr:postcode":"11236",
    "addr:street":"Avenue L",
    "iso:country":"US",
    "sg:address":"9518 Avenue L",
    "sg:city":"Brooklyn",
    "sg:classifiers":[
        {
            "category":"Retail",
            "subcategory":"Veterinary Services",
            "type":"Services"
        }
    ],
    "sg:phone":"+1 718 444 5151",
    "sg:postcode":"11236",
    "sg:province":"NY",
    "sg:tags":[
        "veterinarian"
    ],
    "wof:name":"A A A Animal Medicine & Surgery Clinic",
    "wof:placetype":"venue"
},
  "geometry": {"coordinates":[-73.89630099999999,40.637901],"type":"Point"}
}