{
  "type": "Feature",
  "properties": {
    "addr:full":"6 N Main St New City NY 10956",
    "addr:housenumber":"6",
    "addr:postcode":"10956",
    "addr:street":"N Main St",
    "iso:country":"US",
    "sg:address":"6 N Main St",
    "sg:city":"New City",
    "sg:classifiers":[
        {
            "category":"Restaurant",
            "type":"Food & Drink"
        }
    ],
    "sg:phone":"+1   ",
    "sg:postcode":"10956",
    "sg:province":"NY",
    "sg:tags":[
        "eating"
    ],
    "wof:name":"Main Street Cafe",
    "wof:placetype":"venue"
},
  "geometry": {"coordinates":[-73.98901600000001,41.150898],"type":"Point"}
}