{
  "type": "Feature",
  "properties": {
    "addr:full":"551 Myrtle Ave Brooklyn NY 11205",
    "addr:housenumber":"551",
    "addr:postcode":"11205",
    "addr:street":"Myrtle Ave",
    "iso:country":"US",
    "sg:address":"551 Myrtle Ave",
    "sg:city":"Brooklyn",
    "sg:classifiers":[
        {
            "category":"Food & Beverages",
            "subcategory":"Groceries & Convenience Stores",
            "type":"Retail Goods"
        }
    ],
    "sg:phone":"+1 718 623 8303",
    "sg:postcode":"11205",
    "sg:province":"NY",
    "wof:name":"Emerson Grocery",
    "wof:placetype":"venue"
},
  "geometry": {"coordinates":[-73.962402,40.693901],"type":"Point"}
}