{
  "type": "Feature",
  "properties": {
    "addr:full":"1502 State St Schenectady NY 12304",
    "addr:housenumber":"1502",
    "addr:postcode":"12304",
    "addr:street":"State St",
    "iso:country":"US",
    "sg:address":"1502 State St",
    "sg:city":"Schenectady",
    "sg:classifiers":[
        {
            "category":"Professional",
            "subcategory":"Advertising",
            "type":"Services"
        }
    ],
    "sg:phone":"+1 518 874 2009",
    "sg:postcode":"12304",
    "sg:province":"NY",
    "sg:tags":[
        "advertising-telephone",
        "fax",
        "telemarketing"
    ],
    "wof:name":"Liman Ii",
    "wof:placetype":"venue"
},
  "geometry": {"coordinates":[-73.916267,42.791271],"type":"Point"}
}