{
  "type": "Feature",
  "properties": {
    "addr:full":"325 State Hwy 303 Orangeburg NY 10962",
    "addr:housenumber":"325",
    "addr:postcode":"10962",
    "addr:street":"State Hwy 303",
    "iso:country":"US",
    "sg:address":"325 State Hwy 303",
    "sg:city":"Orangeburg",
    "sg:classifiers":[
        {
            "category":"Restaurant",
            "type":"Food & Drink"
        }
    ],
    "sg:phone":"+1   ",
    "sg:postcode":"10962",
    "sg:province":"NY",
    "sg:tags":[
        "tavern"
    ],
    "wof:name":"Orangeburg Tavern",
    "wof:placetype":"venue"
},
  "geometry": {"coordinates":[-73.945168,41.047264],"type":"Point"}
}