{
  "type": "Feature",
  "properties": {
    "addr:full":"141 E 61st St Frnt New York NY 10021",
    "addr:housenumber":"141",
    "addr:postcode":"10021",
    "addr:street":"E 61St St",
    "iso:country":"US",
    "sg:address":"141 E 61st St Frnt",
    "sg:city":"New York",
    "sg:classifiers":[
        {
            "category":"Retail",
            "subcategory":"Laundry & Dry Cleaning",
            "type":"Services"
        }
    ],
    "sg:phone":"+1 212 838 0996",
    "sg:postcode":"10021",
    "sg:province":"NY",
    "wof:name":"Lowy H Cleaners & Tailors",
    "wof:placetype":"venue"
},
  "geometry": {"coordinates":[-73.96729999999999,40.7635],"type":"Point"}
}