{
  "type": "Feature",
  "properties": {
    "addr:full":"1674 Carter Ave Bronx NY 10457",
    "addr:housenumber":"1674",
    "addr:postcode":"10457",
    "addr:street":"Carter Ave",
    "iso:country":"US",
    "sg:address":"1674 Carter Ave",
    "sg:city":"Bronx",
    "sg:classifiers":[
        {
            "category":"Retail",
            "subcategory":"Auto Repair",
            "type":"Services"
        },
        {
            "category":"Autos & Motor Vehicles",
            "subcategory":"Auto Supplies",
            "type":"Retail Goods"
        }
    ],
    "sg:phone":"+1 718 294 4865",
    "sg:postcode":"10457",
    "sg:province":"NY",
    "sg:tags":[
        "engine",
        "rebuilding",
        "parts",
        "automobile"
    ],
    "wof:name":"L & B Machine Shop Inc",
    "wof:placetype":"venue"
},
  "geometry": {"coordinates":[-73.903561,40.84419],"type":"Point"}
}