{
  "type": "Feature",
  "properties": {
    "addr:full":"1953 52nd St Brooklyn NY 11204",
    "addr:housenumber":"1953",
    "addr:postcode":"11204",
    "addr:street":"52Nd St",
    "iso:country":"US",
    "sg:address":"1953 52nd St",
    "sg:city":"Brooklyn",
    "sg:classifiers":[
        {
            "category":"Building & Trades",
            "subcategory":"Construction",
            "type":"Services"
        }
    ],
    "sg:phone":"+1 718 338 7451",
    "sg:postcode":"11204",
    "sg:province":"NY",
    "sg:tags":[
        "general",
        "contractor"
    ],
    "wof:name":"Vinny & M Construction",
    "wof:placetype":"venue"
},
  "geometry": {"coordinates":[-73.979039,40.624645],"type":"Point"}
}