{
  "type": "Feature",
  "properties": {
    "iso:country":"US",
    "sg:address":"15 Maria Ct",
    "sg:city":"Sayville",
    "sg:classifiers":[
        {
            "category":"Wholesale",
            "subcategory":"Machinery & Supplies",
            "type":"Manufacturing & Wholesale Goods"
        }
    ],
    "sg:phone":"+1 631 567 5303",
    "sg:postcode":"11782",
    "sg:province":"NY",
    "sg:tags":[
        "equipment",
        "irrigation",
        "system"
    ],
    "wof:name":"Tru Green Irrigation",
    "wof:placetype":"venue"
},
  "geometry": {"coordinates":[-73.091409,40.757935],"type":"Point"}
}