{
  "type": "Feature",
  "properties": {
    "iso:country":"US",
    "sg:address":"3924 Seton Ave",
    "sg:city":"Bronx",
    "sg:classifiers":[
        {
            "category":"Professional",
            "subcategory":"Management & Consulting",
            "type":"Services"
        }
    ],
    "sg:phone":"+1 718 994 2573",
    "sg:postcode":"10466",
    "sg:province":"NY",
    "wof:name":"Langway Management Inc",
    "wof:placetype":"venue"
},
  "geometry": {"coordinates":[-73.83710600000001,40.890758],"type":"Point"}
}