{
  "type": "Feature",
  "properties": {
    "addr:full":"161 E 74th Street New York NY 10021",
    "addr:housenumber":"161",
    "addr:postcode":"10021",
    "addr:street":"E 74Th Street",
    "iso:country":"US",
    "sg:address":"161 E 74th Street",
    "sg:city":"New York",
    "sg:classifiers":[
        {
            "category":"Health Services",
            "subcategory":"Doctor",
            "type":"Services"
        }
    ],
    "sg:phone":"+1 212 249 2454",
    "sg:postcode":"10021",
    "sg:province":"NY",
    "wof:name":"Fayer Steven MD",
    "wof:placetype":"venue"
},
  "geometry": {"coordinates":[-73.96033799999999,40.771474],"type":"Point"}
}