{
  "type": "Feature",
  "properties": {
    "iso:country":"US",
    "sg:address":"415 Oser Ave",
    "sg:city":"Hauppauge",
    "sg:classifiers":[
        {
            "category":"Wholesale",
            "subcategory":"Office Equipment",
            "type":"Manufacturing & Wholesale Goods"
        }
    ],
    "sg:phone":"+1 631 435 9100",
    "sg:postcode":"11788",
    "sg:province":"NY",
    "sg:tags":[
        "machine",
        "mailing"
    ],
    "sg:website":"www.4ims.com",
    "wof:name":"Innovative Mailing & Shipping",
    "wof:placetype":"venue"
},
  "geometry": {"coordinates":[-73.256862,40.816468],"type":"Point"}
}