{
  "type": "Feature",
  "properties": {
    "addr:full":"4022 5th Ave Brooklyn NY 11232",
    "addr:housenumber":"4022",
    "addr:postcode":"11232",
    "addr:street":"5Th Ave",
    "iso:country":"US",
    "sg:address":"4022 5th Ave",
    "sg:city":"Brooklyn",
    "sg:classifiers":[
        {
            "category":"Food & Beverages",
            "subcategory":"Groceries & Convenience Stores",
            "type":"Retail Goods"
        }
    ],
    "sg:phone":"+1 718 438 2067",
    "sg:postcode":"11232",
    "sg:province":"NY",
    "wof:name":"Plaza Mexico",
    "wof:placetype":"venue"
},
  "geometry": {"coordinates":[-74.00509599999999,40.650299],"type":"Point"}
}