{
  "type": "Feature",
  "properties": {
    "addr:full":"111 Joseph Ave Staten Island NY 10314",
    "addr:housenumber":"111",
    "addr:postcode":"10314",
    "addr:street":"Joseph Ave",
    "iso:country":"US",
    "sg:address":"111 Joseph Ave",
    "sg:city":"Staten Island",
    "sg:classifiers":[
        {
            "category":"Health Services",
            "subcategory":"Health Practitioner",
            "type":"Services"
        }
    ],
    "sg:phone":"+1 718 982 1642",
    "sg:postcode":"10314",
    "sg:province":"NY",
    "sg:tags":[
        "acupuncture"
    ],
    "wof:name":"Bruce Dublin",
    "wof:placetype":"venue"
},
  "geometry": {"coordinates":[-74.136741,40.600302],"type":"Point"}
}