{
  "type": "Feature",
  "properties": {
    "addr:full":"74 W Islip Rd West Islip NY 11795",
    "addr:housenumber":"74",
    "addr:postcode":"11795",
    "addr:street":"W Islip Rd",
    "iso:country":"US",
    "sg:address":"74 W Islip Rd",
    "sg:city":"West Islip",
    "sg:classifiers":[
        {
            "category":"Bars & Pubs",
            "type":"Food & Drink"
        }
    ],
    "sg:phone":"+1   ",
    "sg:postcode":"11795",
    "sg:province":"NY",
    "sg:tags":[
        "tavern"
    ],
    "wof:name":"P J Ryans",
    "wof:placetype":"venue"
},
  "geometry": {"coordinates":[-73.316181,40.689838],"type":"Point"}
}