{
  "type": "Feature",
  "properties": {
    "iso:country":"US",
    "sg:address":"7 Burkhardt Ave",
    "sg:city":"Bethpage",
    "sg:classifiers":[
        {
            "category":"Government",
            "subcategory":"Office",
            "type":"Public Place"
        }
    ],
    "sg:phone":"+1 516 822 6192",
    "sg:postcode":"11714",
    "sg:province":"NY",
    "sg:tags":[
        "village"
    ],
    "wof:name":"Oyster Bay Town Office",
    "wof:placetype":"venue"
},
  "geometry": {"coordinates":[-73.479433,40.744547],"type":"Point"}
}