{
  "type": "Feature",
  "properties": {
    "iso:country":"US",
    "sg:address":"2056 E Ridge Rd",
    "sg:city":"Rochester",
    "sg:classifiers":[
        {
            "category":"Shopping",
            "subcategory":"Party Supplies",
            "type":"Retail Goods"
        },
        {
            "category":"Shopping",
            "subcategory":"Crafts & Fabrics",
            "type":"Retail Goods"
        },
        {
            "category":"Shopping",
            "subcategory":"Florist",
            "type":"Retail Goods"
        }
    ],
    "sg:phone":"+1 585 544 8733",
    "sg:postcode":"14622",
    "sg:province":"NY",
    "sg:tags":[
        "plant",
        "etc-retail",
        "dried",
        "wedding",
        "trees-silk",
        "flowers"
    ],
    "sg:website":"http://www.redrosefloristrochester.com",
    "wof:name":"Red Rose Florist & Gift Shop",
    "wof:placetype":"venue"
},
  "geometry": {"coordinates":[-77.56264899999999,43.203219],"type":"Point"}
}