{
  "type": "Feature",
  "properties": {
    "iso:country":"US",
    "sg:address":"1 Merit Ct",
    "sg:city":"Brooklyn",
    "sg:classifiers":[
        {
            "category":"Recreation",
            "type":"Entertainment"
        }
    ],
    "sg:phone":"+1 718 769 2112",
    "sg:postcode":"11229",
    "sg:province":"NY",
    "sg:tags":[
        "club",
        "membership"
    ],
    "wof:name":"Shellbank Yacht Club Inc",
    "wof:placetype":"venue"
},
  "geometry": {"coordinates":[-73.92601500000001,40.588336],"type":"Point"}
}