{
  "type": "Feature",
  "properties": {
    "iso:country":"US",
    "sg:address":"140 Terminal Dr",
    "sg:city":"Plainview",
    "sg:classifiers":[
        {
            "category":"Manufacturing",
            "subcategory":"Signs",
            "type":"Manufacturing & Wholesale Goods"
        }
    ],
    "sg:phone":"+1   ",
    "sg:postcode":"11803",
    "sg:province":"NY",
    "sg:tags":[
        "manufacture",
        "neon",
        "custom"
    ],
    "sg:website":"www.goingsign.com",
    "wof:name":"Going Sign Co Inc",
    "wof:placetype":"venue"
},
  "geometry": {"coordinates":[-73.470015,40.792683],"type":"Point"}
}