{
  "type": "Feature",
  "properties": {
    "addr:full":"101 Bracken Rd Montgomery NY 12549",
    "addr:housenumber":"101",
    "addr:postcode":"12549",
    "addr:street":"Bracken Rd",
    "iso:country":"US",
    "sg:address":"101 Bracken Rd",
    "sg:city":"Montgomery",
    "sg:classifiers":[
        {
            "category":"Professional",
            "subcategory":"Accounting & Tax Preparation",
            "type":"Services"
        }
    ],
    "sg:phone":"+1 845 457 1100",
    "sg:postcode":"12549",
    "sg:province":"NY",
    "sg:tags":[
        "accountant"
    ],
    "wof:name":"Nugent & Haeussler PC",
    "wof:placetype":"venue"
},
  "geometry": {"coordinates":[-74.20410200000001,41.52],"type":"Point"}
}