{
  "type": "Feature",
  "properties": {
    "iso:country":"US",
    "sg:address":"815 Harlem Rd",
    "sg:city":"Buffalo",
    "sg:classifiers":[
        {
            "category":"Sports & Exercise",
            "subcategory":"Bowling",
            "type":"Entertainment"
        }
    ],
    "sg:phone":"+1 716 825 2505",
    "sg:postcode":"14224",
    "sg:province":"NY",
    "sg:tags":[
        "center"
    ],
    "wof:name":"AMF",
    "wof:placetype":"venue"
},
  "geometry": {"coordinates":[-78.787181,42.869579],"type":"Point"}
}