{
  "type": "Feature",
  "properties": {
    "addr:full":"5300 W Genesee St Camillus NY 13031",
    "addr:housenumber":"5300",
    "addr:postcode":"13031",
    "addr:street":"W Genesee St",
    "iso:country":"US",
    "sg:address":"5300 W Genesee St",
    "sg:city":"Camillus",
    "sg:classifiers":[
        {
            "category":"Restaurant",
            "type":"Food & Drink"
        }
    ],
    "sg:menulink":"http://www.allmenus.com/ny/camillus/11255-dennys/menu/",
    "sg:phone":"+1 315 488 1887",
    "sg:postcode":"13031",
    "sg:province":"NY",
    "sg:tags":[
        "american",
        "diner"
    ],
    "wof:name":"Denny's",
    "wof:placetype":"venue"
},
  "geometry": {"coordinates":[-76.26900999999999,43.041259],"type":"Point"}
}