{
  "type": "Feature",
  "properties": {
    "addr:full":"2233 E 27th St Brooklyn NY 11229",
    "addr:housenumber":"2233",
    "addr:postcode":"11229",
    "addr:street":"E 27Th St",
    "iso:country":"US",
    "sg:address":"2233 E 27th St",
    "sg:city":"Brooklyn",
    "sg:classifiers":[
        {
            "category":"Insurance",
            "subcategory":"Insurance Agent",
            "type":"Services"
        }
    ],
    "sg:phone":"+1 718 934 0629",
    "sg:postcode":"11229",
    "sg:province":"NY",
    "wof:name":"Optimum Insurance Agency Group",
    "wof:placetype":"venue"
},
  "geometry": {"coordinates":[-73.943923,40.596396],"type":"Point"}
}