{
  "type": "Feature",
  "properties": {
    "iso:country":"US",
    "sg:address":"2309 Co Rd 35",
    "sg:city":"Norwood",
    "sg:classifiers":[
        {
            "category":"Home & Garden",
            "subcategory":"Building Materials",
            "type":"Retail Goods"
        }
    ],
    "sg:phone":"+1   ",
    "sg:postcode":"13676",
    "sg:province":"NY",
    "wof:name":"Red K Stables",
    "wof:placetype":"venue"
},
  "geometry": {"coordinates":[-75.065682,44.719117],"type":"Point"}
}