{
  "type": "Feature",
  "properties": {
    "iso:country":"US",
    "sg:address":"3 Summerville Rd",
    "sg:city":"Goshen",
    "sg:classifiers":[
        {
            "category":"Real Estate",
            "subcategory":"Real Estate Agent",
            "type":"Services"
        }
    ],
    "sg:phone":"+1 845 651 2342",
    "sg:postcode":"10924",
    "sg:province":"NY",
    "wof:name":"Palo Realty Corp",
    "wof:placetype":"venue"
},
  "geometry": {"coordinates":[-74.31702,41.3525],"type":"Point"}
}