{
  "type": "Feature",
  "properties": {
    "addr:full":"44 E 167th St Bronx NY 10452",
    "addr:housenumber":"44",
    "addr:postcode":"10452",
    "addr:street":"E 167Th St",
    "iso:country":"US",
    "sg:address":"44 E 167th St",
    "sg:city":"Bronx",
    "sg:classifiers":[
        {
            "category":"Food & Beverages",
            "subcategory":"Meat & Fish",
            "type":"Retail Goods"
        }
    ],
    "sg:phone":"+1   ",
    "sg:postcode":"10452",
    "sg:province":"NY",
    "wof:name":"Lees Fish Market",
    "wof:placetype":"venue"
},
  "geometry": {"coordinates":[-73.92049900000001,40.835401],"type":"Point"}
}