{
  "type": "Feature",
  "properties": {
    "addr:full":"214 Jericho Tpke Syosset NY 11791",
    "addr:housenumber":"214",
    "addr:postcode":"11791",
    "addr:street":"Jericho Tpke",
    "iso:country":"US",
    "sg:address":"214 Jericho Tpke",
    "sg:city":"Syosset",
    "sg:classifiers":[
        {
            "category":"Personal",
            "subcategory":"Nail Salon",
            "type":"Services"
        }
    ],
    "sg:phone":"+1 516 921 6677",
    "sg:postcode":"11791",
    "sg:province":"NY",
    "wof:name":"M Gallery Nails",
    "wof:placetype":"venue"
},
  "geometry": {"coordinates":[-73.509067,40.810008],"type":"Point"}
}