{
  "type": "Feature",
  "properties": {
    "iso:country":"US",
    "sg:address":"1 Halyard Ct",
    "sg:city":"Cold Spring Harbor",
    "sg:classifiers":[
        {
            "category":"Professional",
            "subcategory":"Computer Services",
            "type":"Services"
        }
    ],
    "sg:phone":"+1 631 692 8174",
    "sg:postcode":"11724",
    "sg:province":"NY",
    "sg:tags":[
        "related"
    ],
    "wof:name":"Island Logistic Systems",
    "wof:placetype":"venue"
},
  "geometry": {"coordinates":[-73.45809199999999,40.868356],"type":"Point"}
}