{
  "type": "Feature",
  "properties": {
    "iso:country":"US",
    "sg:address":"3191 E Tremont Ave",
    "sg:city":"Bronx",
    "sg:classifiers":[
        {
            "category":"Restaurant",
            "type":"Food & Drink"
        }
    ],
    "sg:phone":"+1 718 824 0032",
    "sg:postcode":"10461",
    "sg:province":"NY",
    "sg:tags":[
        "delicatessen"
    ],
    "wof:name":"Wedge Inn",
    "wof:placetype":"venue"
},
  "geometry": {"coordinates":[-73.834175,40.837458],"type":"Point"}
}