{
  "type": "Feature",
  "properties": {
    "iso:country":"US",
    "sg:address":"2382 Bathgate Ave",
    "sg:city":"Bronx",
    "sg:classifiers":[
        {
            "category":"Professional",
            "type":"Services"
        }
    ],
    "sg:phone":"+1 718 733 8627",
    "sg:postcode":"10458",
    "sg:province":"NY",
    "sg:tags":[
        "establishment"
    ],
    "wof:name":"2382 Bathgate Avenue",
    "wof:placetype":"venue"
},
  "geometry": {"coordinates":[-73.890269,40.856134],"type":"Point"}
}