{
  "type": "Feature",
  "properties": {
    "addr:full":"660 Fairview Ave Ridgewood NY 11385",
    "addr:housenumber":"660",
    "addr:postcode":"11385",
    "addr:street":"Fairview Ave",
    "iso:country":"US",
    "sg:address":"660 Fairview Ave",
    "sg:city":"Ridgewood",
    "sg:classifiers":[
        {
            "category":"Education",
            "subcategory":"Vocational School",
            "type":"Public Place"
        }
    ],
    "sg:phone":"+1 718 381 3004",
    "sg:postcode":"11385",
    "sg:province":"NY",
    "sg:tags":[
        "cosmetology"
    ],
    "wof:name":"Le Chic Hair Studio",
    "wof:placetype":"venue"
},
  "geometry": {"coordinates":[-73.905845,40.706508],"type":"Point"}
}