{
  "type": "Feature",
  "properties": {
    "addr:full":"100 Broad St Gloversville NY 12078",
    "addr:housenumber":"100",
    "addr:postcode":"12078",
    "addr:street":"Broad St",
    "iso:country":"US",
    "sg:address":"100 Broad St",
    "sg:city":"Gloversville",
    "sg:classifiers":[
        {
            "category":"Building & Trades",
            "subcategory":"Electrical",
            "type":"Services"
        }
    ],
    "sg:phone":"+1 518 785 6744",
    "sg:postcode":"12078",
    "sg:province":"NY",
    "sg:tags":[
        "electric",
        "contractor"
    ],
    "wof:name":"Capital District Electric Svc",
    "wof:placetype":"venue"
},
  "geometry": {"coordinates":[-74.35171699999999,43.048541],"type":"Point"}
}