{
  "type": "Feature",
  "properties": {
    "addr:full":"399 Jerusalem Ave Hicksville NY 11801",
    "addr:housenumber":"399",
    "addr:postcode":"11801",
    "addr:street":"Jerusalem Ave",
    "iso:country":"US",
    "sg:address":"399 Jerusalem Ave",
    "sg:city":"Hicksville",
    "sg:classifiers":[
        {
            "category":"Wholesale",
            "subcategory":"Fruits & Vegetables",
            "type":"Manufacturing & Wholesale Goods"
        }
    ],
    "sg:phone":"+1 516 938 9246",
    "sg:postcode":"11801",
    "sg:province":"NY",
    "wof:name":"Quality Wholesale Produce Inc",
    "wof:placetype":"venue"
},
  "geometry": {"coordinates":[-73.518657,40.750155],"type":"Point"}
}