{
  "type": "Feature",
  "properties": {
    "iso:country":"US",
    "sg:address":"7636 Wild Turkey",
    "sg:city":"Liverpool",
    "sg:classifiers":[
        {
            "category":"Education",
            "subcategory":"Special Training",
            "type":"Public Place"
        }
    ],
    "sg:phone":"+1 315 457 9863",
    "sg:postcode":"13090",
    "sg:province":"NY",
    "sg:tags":[
        "instruction",
        "music"
    ],
    "wof:name":"Music A LA Carte",
    "wof:placetype":"venue"
},
  "geometry": {"coordinates":[-76.171722,43.140916],"type":"Point"}
}