{
  "type": "Feature",
  "properties": {
    "iso:country":"US",
    "sg:address":"43 Old Rte 6",
    "sg:city":"Brewster",
    "sg:classifiers":[
        {
            "category":"Manufacturing",
            "subcategory":"Metals",
            "type":"Manufacturing & Wholesale Goods"
        },
        {
            "category":"Wholesale",
            "subcategory":"Hardware",
            "type":"Manufacturing & Wholesale Goods"
        }
    ],
    "sg:phone":"+1 845 279 8075",
    "sg:postcode":"10509",
    "sg:province":"NY",
    "sg:tags":[
        "plumbing",
        "fixture",
        "supply"
    ],
    "wof:name":"N & S Supply Of Brewster Inc",
    "wof:placetype":"venue"
},
  "geometry": {"coordinates":[-73.65360200000001,41.413291],"type":"Point"}
}