{
  "type": "Feature",
  "properties": {
    "iso:country":"US",
    "sg:address":"206 E Seneca St",
    "sg:city":"Manlius",
    "sg:classifiers":[
        {
            "category":"Sports & Exercise",
            "subcategory":"Gym",
            "type":"Entertainment"
        }
    ],
    "sg:phone":"+1   ",
    "sg:postcode":"13104",
    "sg:province":"NY",
    "sg:tags":[
        "fitness",
        "physical",
        "facility"
    ],
    "wof:name":"Holos Mind Body Fitness",
    "wof:placetype":"venue"
},
  "geometry": {"coordinates":[-75.976615,43.001802],"type":"Point"}
}