{
  "type": "Feature",
  "properties": {
    "addr:full":"2601 Ocean Pkwy Brooklyn NY 11235",
    "addr:housenumber":"2601",
    "addr:postcode":"11235",
    "addr:street":"Ocean Pkwy",
    "iso:country":"US",
    "sg:address":"2601 Ocean Pkwy",
    "sg:city":"Brooklyn",
    "sg:classifiers":[
        {
            "category":"Restaurant",
            "type":"Food & Drink"
        }
    ],
    "sg:menulink":"http://www.allmenus.com/ny/brooklyn/53531-subway/menu/",
    "sg:phone":"+1 718 616 4161",
    "sg:postcode":"11235",
    "sg:province":"NY",
    "sg:tags":[
        "american",
        "sandwich"
    ],
    "wof:name":"Subway",
    "wof:placetype":"venue"
},
  "geometry": {"coordinates":[-73.965872,40.586601],"type":"Point"}
}