{
  "type": "Feature",
  "properties": {
    "addr:full":"561 Fashion Ave New York NY 10018",
    "addr:housenumber":"561",
    "addr:postcode":"10018",
    "addr:street":"Fashion Ave",
    "iso:country":"US",
    "sg:address":"561 Fashion Ave",
    "sg:city":"New York",
    "sg:classifiers":[
        {
            "category":"Sports & Exercise",
            "subcategory":"Bicycle Rental",
            "type":"Entertainment"
        }
    ],
    "sg:phone":"+1 212 768 8500",
    "sg:postcode":"10018",
    "sg:province":"NY",
    "sg:tags":[
        "wear"
    ],
    "wof:name":"Telluride Clothing Company",
    "wof:placetype":"venue"
},
  "geometry": {"coordinates":[-73.987532,40.7548],"type":"Point"}
}