{
  "type": "Feature",
  "properties": {
    "addr:full":"1590 Babcock Rd Baldwinsville NY 13027",
    "addr:housenumber":"1590",
    "addr:postcode":"13027",
    "addr:street":"Babcock Rd",
    "iso:country":"US",
    "sg:address":"1590 Babcock Rd",
    "sg:city":"Baldwinsville",
    "sg:phone":"+1 315 635 7456",
    "sg:postcode":"13027",
    "sg:province":"NY",
    "sg:tags":[
        "farm"
    ],
    "wof:name":"Schader Family Farms",
    "wof:placetype":"venue"
},
  "geometry": {"coordinates":[-76.38454299999999,43.188598],"type":"Point"}
}