{
  "type": "Feature",
  "properties": {
    "iso:country":"US",
    "sg:address":"1815 State St",
    "sg:city":"Schenectady",
    "sg:classifiers":[
        {
            "category":"Banks & Credit Unions",
            "subcategory":"Investment Brokerage",
            "type":"Services"
        }
    ],
    "sg:phone":"+1 518 372 5500",
    "sg:postcode":"12304",
    "sg:province":"NY",
    "sg:tags":[
        "security"
    ],
    "wof:name":"Advantage Capital Corporation",
    "wof:placetype":"venue"
},
  "geometry": {"coordinates":[-73.90320199999999,42.779838],"type":"Point"}
}