{
  "type": "Feature",
  "properties": {
    "addr:full":"60 7th St Garden City NY 11530",
    "addr:housenumber":"60",
    "addr:postcode":"11530",
    "addr:street":"7Th St",
    "iso:country":"US",
    "sg:address":"60 7th St",
    "sg:city":"Garden City",
    "sg:classifiers":[
        {
            "category":"Shopping",
            "subcategory":"Used Merchandise",
            "type":"Retail Goods"
        }
    ],
    "sg:phone":"+1 516 746 9694",
    "sg:postcode":"11530",
    "sg:province":"NY",
    "sg:tags":[
        "antique",
        "consignment",
        "store"
    ],
    "wof:name":"Garden City Exchange",
    "wof:placetype":"venue"
},
  "geometry": {"coordinates":[-73.640404,40.723999],"type":"Point"}
}