{
  "type": "Feature",
  "properties": {
    "addr:full":"3037 Ave U Brooklyn NY 11229",
    "addr:housenumber":"3037",
    "addr:postcode":"11229",
    "addr:street":"Ave U",
    "iso:country":"US",
    "sg:address":"3037 Ave U",
    "sg:city":"Brooklyn",
    "sg:classifiers":[
        {
            "category":"Health Services",
            "subcategory":"Doctor",
            "type":"Services"
        }
    ],
    "sg:phone":"+1   ",
    "sg:postcode":"11229",
    "sg:province":"NY",
    "wof:name":"Vladimir Lempert DDS",
    "wof:placetype":"venue"
},
  "geometry": {"coordinates":[-73.93645600000001,40.601092],"type":"Point"}
}