{
  "type": "Feature",
  "properties": {
    "addr:full":"2357 Middle Country Rd Centereach NY 11720",
    "addr:housenumber":"2357",
    "addr:postcode":"11720",
    "addr:street":"Middle Country Rd",
    "iso:country":"US",
    "sg:address":"2357 Middle Country Rd",
    "sg:city":"Centereach",
    "sg:classifiers":[
        {
            "category":"Personal",
            "type":"Services"
        }
    ],
    "sg:phone":"+1 631 588 6441",
    "sg:postcode":"11720",
    "sg:province":"NY",
    "sg:tags":[
        "sewing",
        "alteration"
    ],
    "wof:name":"Rosies Tailoring",
    "wof:placetype":"venue"
},
  "geometry": {"coordinates":[-73.45168,40.858191],"type":"Point"}
}