{
  "type": "Feature",
  "properties": {
    "iso:country":"US",
    "sg:address":"100 Clearbrook Rd",
    "sg:city":"Elmsford",
    "sg:classifiers":[
        {
            "category":"Banks & Credit Unions",
            "subcategory":"Bank",
            "type":"Services"
        }
    ],
    "sg:phone":"+1 914 347 0395",
    "sg:postcode":"10523",
    "sg:province":"NY",
    "sg:tags":[
        "state",
        "commercial"
    ],
    "wof:name":"Independence Community Bank",
    "wof:placetype":"venue"
},
  "geometry": {"coordinates":[-73.81399,41.074173],"type":"Point"}
}