{
  "type": "Feature",
  "properties": {
    "iso:country":"US",
    "sg:address":"36 Colfax Ave",
    "sg:city":"Staten Island",
    "sg:classifiers":[
        {
            "category":"Real Estate",
            "subcategory":"Real Estate Agent",
            "type":"Services"
        }
    ],
    "sg:phone":"+1 718 979 8149",
    "sg:postcode":"10306",
    "sg:province":"NY",
    "wof:name":"Vista Realty LLC",
    "wof:placetype":"venue"
},
  "geometry": {"coordinates":[-74.110248,40.581289],"type":"Point"}
}