{
  "type": "Feature",
  "properties": {
    "iso:country":"US",
    "sg:address":"49 W 46 St",
    "sg:city":"New York",
    "sg:classifiers":[
        {
            "category":"Building & Trades",
            "subcategory":"Construction",
            "type":"Services"
        }
    ],
    "sg:phone":"+1 212 921 2625",
    "sg:postcode":"10036",
    "sg:province":"NY",
    "sg:tags":[
        "elevator"
    ],
    "wof:name":"49 46 LLC Elevator",
    "wof:placetype":"venue"
},
  "geometry": {"coordinates":[-73.98102,40.756789],"type":"Point"}
}