{
  "type": "Feature",
  "properties": {
    "iso:country":"US",
    "sg:address":"300 Essjay Rd",
    "sg:city":"Buffalo",
    "sg:classifiers":[
        {
            "category":"Professional",
            "subcategory":"Credit Reporting & Collection",
            "type":"Services"
        }
    ],
    "sg:phone":"+1 716 565 3600",
    "sg:postcode":"14221",
    "sg:province":"NY",
    "wof:name":"Experian Info Solutions Inc",
    "wof:placetype":"venue"
},
  "geometry": {"coordinates":[-78.73592499999999,42.976976],"type":"Point"}
}