{
  "type": "Feature",
  "properties": {
    "iso:country":"US",
    "sg:address":"275 Lenox Ave",
    "sg:city":"New York",
    "sg:classifiers":[
        {
            "category":"Organizations",
            "subcategory":"Non-profit Organization",
            "type":"Services"
        }
    ],
    "sg:phone":"+1 212 665 7010",
    "sg:postcode":"10027",
    "sg:province":"NY",
    "sg:website":"www.hbany.org",
    "wof:name":"Harlem Business Alliance",
    "wof:placetype":"venue"
},
  "geometry": {"coordinates":[-73.946276,40.806715],"type":"Point"}
}