{
  "type": "Feature",
  "properties": {
    "addr:full":"121 W 128th St New York NY 10027",
    "addr:housenumber":"121",
    "addr:postcode":"10027",
    "addr:street":"W 128Th St",
    "iso:country":"US",
    "sg:address":"121 W 128th St",
    "sg:city":"New York",
    "sg:classifiers":[
        {
            "category":"Health Services",
            "subcategory":"Clinic",
            "type":"Services"
        }
    ],
    "sg:phone":"+1 212 491 8613",
    "sg:postcode":"10027",
    "sg:province":"NY",
    "sg:tags":[
        "treatment",
        "drug",
        "center"
    ],
    "wof:name":"Harlem Rehabilitation Center",
    "wof:placetype":"venue"
},
  "geometry": {"coordinates":[-73.946456,40.810703],"type":"Point"}
}