{
  "type": "Feature",
  "properties": {
    "addr:full":"215 State Hwy 303 Congers NY 10920",
    "addr:housenumber":"215",
    "addr:postcode":"10920",
    "addr:street":"State Hwy 303",
    "iso:country":"US",
    "sg:address":"215 State Hwy 303",
    "sg:city":"Congers",
    "sg:classifiers":[
        {
            "category":"Wholesale",
            "subcategory":"Drugs",
            "type":"Manufacturing & Wholesale Goods"
        }
    ],
    "sg:phone":"+1 845 268 0589",
    "sg:postcode":"10920",
    "sg:province":"NY",
    "sg:tags":[
        "pharmaceutical",
        "product"
    ],
    "wof:name":"Allied Coading",
    "wof:placetype":"venue"
},
  "geometry": {"coordinates":[-73.936592,41.16286],"type":"Point"}
}