{
  "type": "Feature",
  "properties": {
    "iso:country":"US",
    "sg:address":"10414 85th Ave",
    "sg:city":"Richmond Hill",
    "sg:classifiers":[
        {
            "category":"Education",
            "subcategory":"School",
            "type":"Public Place"
        }
    ],
    "sg:phone":"+1 718 847 7489",
    "sg:postcode":"11418",
    "sg:province":"NY",
    "sg:tags":[
        "high",
        "middle",
        "elementary"
    ],
    "wof:name":"Weldon Christopher",
    "wof:placetype":"venue"
},
  "geometry": {"coordinates":[-73.844515,40.698563],"type":"Point"}
}