{
  "type": "Feature",
  "properties": {
    "addr:full":"15608 Crossbay Blvd Howard Beach NY 11414",
    "addr:postcode":"15608;11414",
    "addr:street":"Crossbay Blvd",
    "iso:country":"US",
    "sg:address":"15608 Crossbay Blvd",
    "sg:city":"Howard Beach",
    "sg:classifiers":[
        {
            "category":"Personal",
            "subcategory":"Nail Salon",
            "type":"Services"
        }
    ],
    "sg:phone":"+1 718 835 1575",
    "sg:postcode":"11414",
    "sg:province":"NY",
    "wof:name":"Joy's Nail",
    "wof:placetype":"venue"
},
  "geometry": {"coordinates":[-73.841301,40.663898],"type":"Point"}
}