{
  "type": "Feature",
  "properties": {
    "iso:country":"US",
    "sg:address":"2154 Edenwald Ave",
    "sg:city":"Bronx",
    "sg:classifiers":[
        {
            "category":"Retail",
            "subcategory":"Repair Shop",
            "type":"Services"
        }
    ],
    "sg:phone":"+1 347 803 1348",
    "sg:postcode":"10466",
    "sg:province":"NY",
    "sg:tags":[
        "major",
        "refinishing",
        "appliance",
        "dryer",
        "small",
        "washer"
    ],
    "sg:website":"http://www.yext.com/p/superpages/americare-appliance-repair-bronx-new-york2.html",
    "wof:name":"Americare Appliance Repair",
    "wof:placetype":"venue"
},
  "geometry": {"coordinates":[-73.838381,40.894063],"type":"Point"}
}