{
  "type": "Feature",
  "properties": {
    "iso:country":"US",
    "sg:address":"563 Centerville Rd",
    "sg:city":"Pulaski",
    "sg:classifiers":[
        {
            "category":"Travel",
            "subcategory":"Campground",
            "type":"Entertainment"
        }
    ],
    "sg:phone":"+1 315 298 6655",
    "sg:postcode":"13142",
    "sg:province":"NY",
    "wof:name":"Trapper's Place",
    "wof:placetype":"venue"
},
  "geometry": {"coordinates":[-76.11270500000001,43.563843],"type":"Point"}
}