{
  "type": "Feature",
  "properties": {
    "addr:full":"3658 Broadway New York NY 10031",
    "addr:housenumber":"3658",
    "addr:postcode":"10031",
    "addr:street":"Broadway",
    "iso:country":"US",
    "sg:address":"3658 Broadway",
    "sg:city":"New York",
    "sg:classifiers":[
        {
            "category":"Professional",
            "subcategory":"Advertising",
            "type":"Services"
        }
    ],
    "sg:phone":"+1 212 281 1222",
    "sg:postcode":"10031",
    "sg:province":"NY",
    "wof:name":"DSWEISSPHOTOS.COM",
    "wof:placetype":"venue"
},
  "geometry": {"coordinates":[-73.947226,40.830846],"type":"Point"}
}