{
  "type": "Feature",
  "properties": {
    "addr:full":"90 Gnarled Hollow Rd East Setauket NY 11733",
    "addr:housenumber":"90",
    "addr:postcode":"11733",
    "addr:street":"Gnarled Hollow Rd",
    "iso:country":"US",
    "sg:address":"90 Gnarled Hollow Rd",
    "sg:city":"East Setauket",
    "sg:classifiers":[
        {
            "category":"Building & Trades",
            "subcategory":"Construction",
            "type":"Services"
        }
    ],
    "sg:phone":"+1 631 664 4952",
    "sg:postcode":"11733",
    "sg:province":"NY",
    "sg:tags":[
        "painter"
    ],
    "wof:name":"Caa Drywall & Painting Co",
    "wof:placetype":"venue"
},
  "geometry": {"coordinates":[-73.098595,40.930566],"type":"Point"}
}