{
  "type": "Feature",
  "properties": {
    "iso:country":"US",
    "sg:address":"205 Ave A Buzzer # 3",
    "sg:city":"Manhattan",
    "sg:classifiers":[
        {
            "category":"Shopping",
            "subcategory":"Computers & Home Electronics",
            "type":"Retail Goods"
        },
        {
            "category":"Building & Trades",
            "subcategory":"Construction",
            "type":"Services"
        }
    ],
    "sg:phone":"+1 646 918 6191",
    "sg:postcode":"10009",
    "sg:province":"NY",
    "sg:tags":[
        "installation",
        "theatre",
        "contractor"
    ],
    "sg:website":"www.brighthometheater.com",
    "wof:name":"Bright Home Theater",
    "wof:placetype":"venue"
},
  "geometry": {"coordinates":[-73.9813,40.729611],"type":"Point"}
}