{
  "type": "Feature",
  "properties": {
    "iso:country":"US",
    "sg:address":"243 E Main St",
    "sg:city":"Elbridge",
    "sg:classifiers":[
        {
            "category":"Wholesale",
            "subcategory":"Durable Goods & Equipment",
            "type":"Manufacturing & Wholesale Goods"
        }
    ],
    "sg:phone":"+1 315 689 5247",
    "sg:postcode":"13060",
    "sg:province":"NY",
    "sg:tags":[
        "representative",
        "manufacturer"
    ],
    "wof:name":"G B Stump & Assoc",
    "wof:placetype":"venue"
},
  "geometry": {"coordinates":[-76.439166,43.036054],"type":"Point"}
}