{
  "type": "Feature",
  "properties": {
    "addr:full":"6390 Amboy Road Staten Island NY 10309",
    "addr:housenumber":"6390",
    "addr:postcode":"10309",
    "addr:street":"Amboy Road",
    "iso:country":"US",
    "sg:address":"6390 Amboy Road",
    "sg:city":"Staten Island",
    "sg:classifiers":[
        {
            "category":"Shopping",
            "subcategory":"Florist",
            "type":"Retail Goods"
        }
    ],
    "sg:phone":"+1 718 356 3636",
    "sg:postcode":"10309",
    "sg:province":"NY",
    "sg:website":"www.flowersbybernard.com",
    "wof:name":"Flowers by Bernard",
    "wof:placetype":"venue"
},
  "geometry": {"coordinates":[-74.218834,40.537174],"type":"Point"}
}