{
  "type": "Feature",
  "properties": {
    "addr:full":"230 W 17th Street New York NY 10011",
    "addr:housenumber":"230",
    "addr:postcode":"10011",
    "addr:street":"W 17Th Street",
    "iso:country":"US",
    "sg:address":"230 W 17th Street",
    "sg:city":"New York",
    "sg:classifiers":[
        {
            "category":"Real Estate",
            "subcategory":"Architect",
            "type":"Services"
        }
    ],
    "sg:phone":"+1 212 366 0342",
    "sg:postcode":"10011",
    "sg:province":"NY",
    "wof:name":"Dugan Dennis Architect",
    "wof:placetype":"venue"
},
  "geometry": {"coordinates":[-73.99915300000001,40.740808],"type":"Point"}
}