{
  "type": "Feature",
  "properties": {
    "iso:country":"US",
    "sg:address":"280 Monroe Dr",
    "sg:city":"Mastic Beach",
    "sg:classifiers":[
        {
            "category":"Professional",
            "subcategory":"Computer Services",
            "type":"Services"
        }
    ],
    "sg:phone":"+1   ",
    "sg:postcode":"11951",
    "sg:province":"NY",
    "sg:tags":[
        "related"
    ],
    "wof:name":"Mini Micro System",
    "wof:placetype":"venue"
},
  "geometry": {"coordinates":[-72.84769799999999,40.769504],"type":"Point"}
}