{
  "type": "Feature",
  "properties": {
    "addr:full":"7 Lake St White Plains NY 10603",
    "addr:housenumber":"7",
    "addr:postcode":"10603",
    "addr:street":"Lake St",
    "iso:country":"US",
    "sg:address":"7 Lake St",
    "sg:city":"White Plains",
    "sg:classifiers":[
        {
            "category":"Real Estate",
            "subcategory":"Real Estate Agent",
            "type":"Services"
        }
    ],
    "sg:phone":"+1 914 683 5551",
    "sg:postcode":"10603",
    "sg:province":"NY",
    "sg:tags":[
        "building",
        "opera",
        "nonresidential"
    ],
    "wof:name":"Camille Realty Inc",
    "wof:placetype":"venue"
},
  "geometry": {"coordinates":[-73.763683,41.036537],"type":"Point"}
}