{
  "type": "Feature",
  "properties": {
    "addr:full":"456 Brooklyn Ave Brooklyn NY 11225",
    "addr:housenumber":"456",
    "addr:postcode":"11225",
    "addr:street":"Brooklyn Ave",
    "iso:country":"US",
    "sg:address":"456 Brooklyn Ave",
    "sg:city":"Brooklyn",
    "sg:classifiers":[
        {
            "category":"Professional",
            "type":"Services"
        }
    ],
    "sg:phone":"+1   ",
    "sg:postcode":"11225",
    "sg:province":"NY",
    "wof:name":"Lendix Inc",
    "wof:placetype":"venue"
},
  "geometry": {"coordinates":[-73.94557500000001,40.663972],"type":"Point"}
}