{
  "type": "Feature",
  "properties": {
    "addr:full":"10 Dubon Ct Farmingdale NY 11735",
    "addr:housenumber":"10",
    "addr:postcode":"11735",
    "addr:street":"Dubon Ct",
    "iso:country":"US",
    "sg:address":"10 Dubon Ct",
    "sg:city":"Farmingdale",
    "sg:classifiers":[
        {
            "category":"Wholesale",
            "subcategory":"Non-durable Goods",
            "type":"Manufacturing & Wholesale Goods"
        }
    ],
    "sg:phone":"+1 631 753 0033",
    "sg:postcode":"11735",
    "sg:province":"NY",
    "wof:name":"AJS Systems Inc",
    "wof:placetype":"venue"
},
  "geometry": {"coordinates":[-73.41681800000001,40.751833],"type":"Point"}
}