{
  "type": "Feature",
  "properties": {
    "iso:country":"US",
    "sg:address":"55 Columbia St",
    "sg:city":"New York",
    "sg:classifiers":[
        {
            "category":"Shopping",
            "subcategory":"Pharmacy",
            "type":"Retail Goods"
        }
    ],
    "sg:phone":"+1   ",
    "sg:postcode":"10002",
    "sg:province":"NY",
    "sg:tags":[
        "drug",
        "store"
    ],
    "wof:name":"Columbia Drug",
    "wof:placetype":"venue"
},
  "geometry": {"coordinates":[-73.98043800000001,40.716785],"type":"Point"}
}