{
  "type": "Feature",
  "properties": {
    "iso:country":"US",
    "sg:address":"479 Wiler Rd",
    "sg:city":"Hilton",
    "sg:classifiers":[
        {
            "category":"Restaurant",
            "type":"Food & Drink"
        }
    ],
    "sg:phone":"+1 585 964 5806",
    "sg:postcode":"14468",
    "sg:province":"NY",
    "sg:tags":[
        "house",
        "steak",
        "barbecue"
    ],
    "wof:name":"Fred Barbque",
    "wof:placetype":"venue"
},
  "geometry": {"coordinates":[-77.89082000000001,43.29541],"type":"Point"}
}