{
  "type": "Feature",
  "properties": {
    "addr:full":"80 Earhart Dr Williamsville NY 14221",
    "addr:housenumber":"80",
    "addr:postcode":"14221",
    "addr:street":"Earhart Dr",
    "iso:country":"US",
    "sg:address":"80 Earhart Dr",
    "sg:city":"Williamsville",
    "sg:classifiers":[
        {
            "category":"Wholesale",
            "subcategory":"Medical Equipment & Supplies",
            "type":"Manufacturing & Wholesale Goods"
        }
    ],
    "sg:phone":"+1 716 688 7260",
    "sg:postcode":"14221",
    "sg:province":"NY",
    "sg:tags":[
        "physician",
        "surgeon"
    ],
    "sg:website":"www.wnysurgical.com",
    "wof:name":"Western New York Surgical Supl",
    "wof:placetype":"venue"
},
  "geometry": {"coordinates":[-78.71462,42.954933],"type":"Point"}
}