{
  "type": "Feature",
  "properties": {
    "addr:full":"51 Canal St New York NY 10002",
    "addr:housenumber":"51",
    "addr:postcode":"10002",
    "addr:street":"Canal St",
    "iso:country":"US",
    "sg:address":"51 Canal St",
    "sg:city":"New York",
    "sg:classifiers":[
        {
            "category":"Shopping",
            "subcategory":"Beauty & Cosmetics",
            "type":"Retail Goods"
        }
    ],
    "sg:phone":"+1 212 226 1262",
    "sg:postcode":"10002",
    "sg:province":"NY",
    "sg:tags":[
        "supply"
    ],
    "wof:name":"Mimoso Facial World Corp",
    "wof:placetype":"venue"
},
  "geometry": {"coordinates":[-73.991715,40.714991],"type":"Point"}
}