{
  "type": "Feature",
  "properties": {
    "iso:country":"US",
    "sg:address":"29 Stewart Cir",
    "sg:city":"Centereach",
    "sg:classifiers":[
        {
            "category":"Professional",
            "subcategory":"Computer Services",
            "type":"Services"
        }
    ],
    "sg:phone":"+1 631 451 1676",
    "sg:postcode":"11720",
    "sg:province":"NY",
    "sg:tags":[
        "graphics"
    ],
    "wof:name":"R R Graphic Design Studios",
    "wof:placetype":"venue"
},
  "geometry": {"coordinates":[-73.076911,40.871733],"type":"Point"}
}