{
  "type": "Feature",
  "properties": {
    "addr:full":"12 Shull St Ilion NY 13357",
    "addr:housenumber":"12",
    "addr:postcode":"13357",
    "addr:street":"Shull St",
    "iso:country":"US",
    "sg:address":"12 Shull St",
    "sg:city":"Ilion",
    "sg:classifiers":[
        {
            "category":"Insurance",
            "subcategory":"Insurance Agent",
            "type":"Services"
        }
    ],
    "sg:phone":"+1 315 894 0888",
    "sg:postcode":"13357",
    "sg:province":"NY",
    "wof:name":"Erie Insurance",
    "wof:placetype":"venue"
},
  "geometry": {"coordinates":[-75.05156700000001,43.020902],"type":"Point"}
}