{
  "type": "Feature",
  "properties": {
    "iso:country":"US",
    "sg:address":"3 Audrey Ave",
    "sg:city":"Oyster Bay",
    "sg:classifiers":[
        {
            "category":"Mining & Drilling",
            "type":"Manufacturing & Wholesale Goods"
        }
    ],
    "sg:phone":"+1 516 922 4170",
    "sg:postcode":"11771",
    "sg:province":"NY",
    "sg:tags":[
        "development",
        "gas",
        "oil",
        "exploration"
    ],
    "wof:name":"Environmental Remediation",
    "wof:placetype":"venue"
},
  "geometry": {"coordinates":[-73.532479,40.873324],"type":"Point"}
}