{
  "type": "Feature",
  "properties": {
    "addr:full":"7 S Melcher St Johnstown NY 12095",
    "addr:housenumber":"7",
    "addr:postcode":"12095",
    "addr:street":"S Melcher St",
    "iso:country":"US",
    "sg:address":"7 S Melcher St",
    "sg:city":"Johnstown",
    "sg:phone":"+1   ",
    "sg:postcode":"12095",
    "sg:province":"NY",
    "sg:tags":[
        "leather",
        "textile",
        "upholstery",
        "finisher"
    ],
    "wof:name":"Designs For Designers",
    "wof:placetype":"venue"
},
  "geometry": {"coordinates":[-74.375744,43.005826],"type":"Point"}
}