{
  "type": "Feature",
  "properties": {
    "addr:full":"681 Lexington Ave. 5th Floor New York NY 10022",
    "addr:housenumber":"681;5th floor",
    "addr:postcode":"10022",
    "addr:street":"Lexington Ave.",
    "iso:country":"US",
    "sg:address":"681 Lexington Ave. 5th Floor",
    "sg:city":"New York",
    "sg:classifiers":[
        {
            "category":"Health Services",
            "subcategory":"Chiropractor",
            "type":"Services"
        }
    ],
    "sg:phone":"+1 212 688 5770",
    "sg:postcode":"10022",
    "sg:province":"NY",
    "sg:website":"www.bochnerchiropractic.com",
    "wof:name":"Bochner Chiropractic Care",
    "wof:placetype":"venue"
},
  "geometry": {"coordinates":[-73.969221,40.760402],"type":"Point"}
}