{
  "type": "Feature",
  "properties": {
    "addr:full":"95 Cabot St West Babylon NY 11704",
    "addr:housenumber":"95",
    "addr:postcode":"11704",
    "addr:street":"Cabot St",
    "iso:country":"US",
    "sg:address":"95 Cabot St",
    "sg:city":"West Babylon",
    "sg:classifiers":[
        {
            "category":"Wholesale",
            "subcategory":"Machinery & Supplies",
            "type":"Manufacturing & Wholesale Goods"
        }
    ],
    "sg:phone":"+1 631 694 7700",
    "sg:postcode":"11704",
    "sg:province":"NY",
    "sg:tags":[
        "equipment",
        "industrial"
    ],
    "wof:name":"World Wide Industrial Supplies",
    "wof:placetype":"venue"
},
  "geometry": {"coordinates":[-73.39155100000001,40.730149],"type":"Point"}
}