{
  "type": "Feature",
  "properties": {
    "iso:country":"US",
    "sg:address":"10176 State Hwy 60",
    "sg:city":"Fredonia",
    "sg:classifiers":[
        {
            "category":"Recreation",
            "type":"Entertainment"
        }
    ],
    "sg:phone":"+1 716 672 8888",
    "sg:postcode":"14063",
    "sg:province":"NY",
    "sg:tags":[
        "course",
        "golf"
    ],
    "wof:name":"Vineyard Falls",
    "wof:placetype":"venue"
},
  "geometry": {"coordinates":[-79.304699,42.442996],"type":"Point"}
}