{
  "type": "Feature",
  "properties": {
    "iso:country":"US",
    "sg:address":"6 Elyon Rd",
    "sg:city":"Monsey",
    "sg:classifiers":[
        {
            "category":"Organizations",
            "subcategory":"Religious Organization",
            "type":"Services"
        }
    ],
    "sg:phone":"+1 845 352 6407",
    "sg:postcode":"10952",
    "sg:province":"NY",
    "sg:tags":[
        "clergy"
    ],
    "wof:name":"Yaakov Fogel",
    "wof:placetype":"venue"
},
  "geometry": {"coordinates":[-74.071055,41.114912],"type":"Point"}
}