{
  "type": "Feature",
  "properties": {
    "iso:country":"US",
    "sg:address":"5 Middle Rd",
    "sg:city":"Willsboro",
    "sg:classifiers":[
        {
            "category":"Shopping",
            "subcategory":"Computers & Home Electronics",
            "type":"Retail Goods"
        }
    ],
    "sg:phone":"+1 518 963 7499",
    "sg:postcode":"12996",
    "sg:province":"NY",
    "sg:tags":[
        "software"
    ],
    "wof:name":"Smart Works",
    "wof:placetype":"venue"
},
  "geometry": {"coordinates":[-73.391509,44.357358],"type":"Point"}
}