{
  "type": "Feature",
  "properties": {
    "iso:country":"US",
    "sg:address":"1431 59th St",
    "sg:city":"Brooklyn",
    "sg:classifiers":[
        {
            "category":"Organizations",
            "subcategory":"Community Association",
            "type":"Services"
        }
    ],
    "sg:phone":"+1 718 972 7971",
    "sg:postcode":"11219",
    "sg:province":"NY",
    "sg:tags":[
        "club"
    ],
    "wof:name":"Chaveirim",
    "wof:placetype":"venue"
},
  "geometry": {"coordinates":[-73.99505000000001,40.62768],"type":"Point"}
}