{
  "type": "Feature",
  "properties": {
    "iso:country":"US",
    "sg:address":"519 Burnet Ave",
    "sg:city":"Syracuse",
    "sg:classifiers":[
        {
            "category":"Building & Trades",
            "subcategory":"Electrical",
            "type":"Services"
        }
    ],
    "sg:phone":"+1 315 471 6718",
    "sg:postcode":"13203",
    "sg:province":"NY",
    "sg:tags":[
        "electrical",
        "electric",
        "contractor"
    ],
    "wof:name":"Jim Stagnitta Electric",
    "wof:placetype":"venue"
},
  "geometry": {"coordinates":[-76.136786,43.052245],"type":"Point"}
}