{
  "type": "Feature",
  "properties": {
    "addr:full":"211 E 43rd St New York NY 10017",
    "addr:housenumber":"211",
    "addr:postcode":"10017",
    "addr:street":"E 43Rd St",
    "iso:country":"US",
    "sg:address":"211 E 43rd St",
    "sg:city":"New York",
    "sg:classifiers":[
        {
            "category":"Government",
            "subcategory":"Office",
            "type":"Public Place"
        }
    ],
    "sg:phone":"+1 212 949 4478",
    "sg:postcode":"10017",
    "sg:province":"NY",
    "sg:tags":[
        "federal",
        "affairs"
    ],
    "wof:name":"Mission Of Bolivia To The UN",
    "wof:placetype":"venue"
},
  "geometry": {"coordinates":[-73.97185,40.750655],"type":"Point"}
}