{
  "type": "Feature",
  "properties": {
    "addr:full":"3340 Hillside Ave New Hyde Park NY 11040",
    "addr:housenumber":"3340",
    "addr:postcode":"11040",
    "addr:street":"Hillside Ave",
    "iso:country":"US",
    "sg:address":"3340 Hillside Ave",
    "sg:city":"New Hyde Park",
    "sg:classifiers":[
        {
            "category":"Insurance",
            "subcategory":"Insurance Agent",
            "type":"Services"
        }
    ],
    "sg:phone":"+1 516 747 7900",
    "sg:postcode":"11040",
    "sg:province":"NY",
    "wof:name":"Allstate",
    "wof:placetype":"venue"
},
  "geometry": {"coordinates":[-73.66016500000001,40.752822],"type":"Point"}
}