{
  "type": "Feature",
  "properties": {
    "iso:country":"US",
    "sg:address":"29 Locust Ave",
    "sg:city":"Rye",
    "sg:classifiers":[
        {
            "category":"Real Estate",
            "subcategory":"Real Estate Agent",
            "type":"Services"
        }
    ],
    "sg:phone":"+1 914 967 1118",
    "sg:postcode":"10580",
    "sg:province":"NY",
    "sg:website":"www.prudentialrand.com",
    "wof:name":"Prudential Rand",
    "wof:placetype":"venue"
},
  "geometry": {"coordinates":[-73.68704,40.982593],"type":"Point"}
}