{
  "type": "Feature",
  "properties": {
    "addr:full":"16223 Hillside Ave Jamaica NY 11432",
    "addr:housenumber":"16223",
    "addr:postcode":"11432",
    "addr:street":"Hillside Ave",
    "iso:country":"US",
    "sg:address":"16223 Hillside Ave",
    "sg:city":"Jamaica",
    "sg:classifiers":[
        {
            "category":"Restaurant",
            "type":"Food & Drink"
        }
    ],
    "sg:menulink":"http://www.allmenus.com/ny/queens/49611-genesis-1/menu/",
    "sg:phone":"+1 718 739 8443",
    "sg:postcode":"11432",
    "sg:province":"NY",
    "sg:tags":[
        "indian",
        "asian"
    ],
    "wof:name":"Genesis #1",
    "wof:placetype":"venue"
},
  "geometry": {"coordinates":[-73.80004700000001,40.708552],"type":"Point"}
}