{
  "type": "Feature",
  "properties": {
    "iso:country":"US",
    "sg:address":"654 Main St",
    "sg:city":"Montauk",
    "sg:classifiers":[
        {
            "category":"Food & Beverages",
            "subcategory":"Groceries & Convenience Stores",
            "type":"Retail Goods"
        }
    ],
    "sg:phone":"+1   ",
    "sg:postcode":"11944",
    "sg:province":"NY",
    "wof:name":"Montauk IGA",
    "wof:placetype":"venue"
},
  "geometry": {"coordinates":[-72.360962,41.107002],"type":"Point"}
}