{
  "type": "Feature",
  "properties": {
    "iso:country":"US",
    "sg:address":"2233 Nesconset Hwy",
    "sg:city":"Lake Grove",
    "sg:classifiers":[
        {
            "category":"Personal",
            "subcategory":"Hair Removal",
            "type":"Services"
        }
    ],
    "sg:phone":"+1 631 588 1100",
    "sg:postcode":"11755",
    "sg:province":"NY",
    "sg:tags":[
        "removing"
    ],
    "wof:name":"Terri Levin",
    "wof:placetype":"venue"
},
  "geometry": {"coordinates":[-73.136685,40.865151],"type":"Point"}
}