{
  "type": "Feature",
  "properties": {
    "addr:full":"14 Schuman Rd Millwood NY 10546",
    "addr:housenumber":"14",
    "addr:postcode":"10546",
    "addr:street":"Schuman Rd",
    "iso:country":"US",
    "sg:address":"14 Schuman Rd",
    "sg:city":"Millwood",
    "sg:classifiers":[
        {
            "category":"Education",
            "subcategory":"School",
            "type":"Public Place"
        }
    ],
    "sg:phone":"+1 914 941 1991",
    "sg:postcode":"10546",
    "sg:province":"NY",
    "wof:name":"Devereux Millwood Learning Center",
    "wof:placetype":"venue"
},
  "geometry": {"coordinates":[-73.7985,41.187801],"type":"Point"}
}