{
  "type": "Feature",
  "properties": {
    "addr:full":"100 Grand St E Westbury NY 11590",
    "addr:housenumber":"100",
    "addr:postcode":"11590",
    "addr:street":"Grand St E",
    "iso:country":"US",
    "sg:address":"100 Grand St E",
    "sg:city":"Westbury",
    "sg:classifiers":[
        {
            "category":"Building & Trades",
            "subcategory":"Electrical",
            "type":"Services"
        }
    ],
    "sg:phone":"+1 516 470 1831",
    "sg:postcode":"11590",
    "sg:province":"NY",
    "sg:tags":[
        "wire",
        "products-wholesale",
        "manufacturer"
    ],
    "wof:name":"Verazzano Group, Inc.",
    "wof:placetype":"venue"
},
  "geometry": {"coordinates":[-73.568389,40.755608],"type":"Point"}
}