{
  "type": "Feature",
  "properties": {
    "addr:full":"172 New Dorp Ln Staten Island NY 10306",
    "addr:housenumber":"172",
    "addr:postcode":"10306",
    "addr:street":"New Dorp Ln",
    "iso:country":"US",
    "sg:address":"172 New Dorp Ln",
    "sg:city":"Staten Island",
    "sg:classifiers":[
        {
            "category":"Wholesale",
            "subcategory":"Apparel",
            "type":"Manufacturing & Wholesale Goods"
        }
    ],
    "sg:phone":"+1 718 351 8440",
    "sg:postcode":"10306",
    "sg:province":"NY",
    "sg:tags":[
        "clothing",
        "accessory"
    ],
    "wof:name":"Andreas Closet Ltd",
    "wof:placetype":"venue"
},
  "geometry": {"coordinates":[-74.11528,40.573402],"type":"Point"}
}