{
  "type": "Feature",
  "properties": {
    "iso:country":"US",
    "sg:address":"316 W Bridge St",
    "sg:city":"Catskill",
    "sg:classifiers":[
        {
            "category":"Shopping",
            "subcategory":"Discount & Variety Stores",
            "type":"Retail Goods"
        }
    ],
    "sg:phone":"+1   ",
    "sg:postcode":"12414",
    "sg:province":"NY",
    "wof:name":"Dollar Tree",
    "wof:placetype":"venue"
},
  "geometry": {"coordinates":[-73.882559,42.214545],"type":"Point"}
}