{
  "type": "Feature",
  "properties": {
    "iso:country":"US",
    "sg:address":"299 Central Park W",
    "sg:city":"New York",
    "sg:classifiers":[
        {
            "category":"Real Estate",
            "subcategory":"Real Estate Agent",
            "type":"Services"
        }
    ],
    "sg:phone":"+1 212 712 1730",
    "sg:postcode":"10024",
    "sg:province":"NY",
    "wof:name":"Catskill Real Estate LLC",
    "wof:placetype":"venue"
},
  "geometry": {"coordinates":[-73.967927,40.787222],"type":"Point"}
}