{
  "type": "Feature",
  "properties": {
    "iso:country":"US",
    "sg:address":"984 50th St",
    "sg:city":"Brooklyn",
    "sg:classifiers":[
        {
            "category":"Health Services",
            "subcategory":"Doctor",
            "type":"Services"
        }
    ],
    "sg:phone":"+1 718 854 6100",
    "sg:postcode":"11219",
    "sg:province":"NY",
    "wof:name":"Jacobowiz Isreal",
    "wof:placetype":"venue"
},
  "geometry": {"coordinates":[-73.999689,40.638519],"type":"Point"}
}