{
  "type": "Feature",
  "properties": {
    "iso:country":"US",
    "sg:address":"740 64th St",
    "sg:city":"Brooklyn",
    "sg:classifiers":[
        {
            "category":"Health Services",
            "subcategory":"Doctor",
            "type":"Services"
        }
    ],
    "sg:phone":"+1 718 439 2000",
    "sg:postcode":"11220",
    "sg:province":"NY",
    "sg:tags":[
        "physician",
        "surgeon"
    ],
    "wof:name":"Kingsboro Medical Group",
    "wof:placetype":"venue"
},
  "geometry": {"coordinates":[-74.012635,40.633718],"type":"Point"}
}