{
  "type": "Feature",
  "properties": {
    "iso:country":"US",
    "sg:address":"33 Great Neck Rd",
    "sg:city":"Great Neck",
    "sg:classifiers":[
        {
            "category":"Personal",
            "subcategory":"Beauty Salon",
            "type":"Services"
        }
    ],
    "sg:phone":"+1   ",
    "sg:postcode":"11021",
    "sg:province":"NY",
    "sg:tags":[
        "shop"
    ],
    "wof:name":"J&J Nail Salon",
    "wof:placetype":"venue"
},
  "geometry": {"coordinates":[-73.728087,40.785986],"type":"Point"}
}