{
  "type": "Feature",
  "properties": {
    "addr:full":"700 South Ave Rochester NY 14620",
    "addr:housenumber":"700",
    "addr:postcode":"14620",
    "addr:street":"South Ave",
    "iso:country":"US",
    "sg:address":"700 South Ave",
    "sg:city":"Rochester",
    "sg:classifiers":[
        {
            "category":"Building & Trades",
            "subcategory":"Plumbing",
            "type":"Services"
        }
    ],
    "sg:phone":"+1 585 442 2500",
    "sg:postcode":"14620",
    "sg:province":"NY",
    "sg:tags":[
        "contractor"
    ],
    "wof:name":"Indoor Air Quality Solutions",
    "wof:placetype":"venue"
},
  "geometry": {"coordinates":[-77.60441899999999,43.14155],"type":"Point"}
}