{
  "type": "Feature",
  "properties": {
    "addr:full":"9619 69th Ave Forest Hills NY 11375",
    "addr:housenumber":"9619",
    "addr:postcode":"11375",
    "addr:street":"69Th Ave",
    "iso:country":"US",
    "sg:address":"9619 69th Ave",
    "sg:city":"Forest Hills",
    "sg:classifiers":[
        {
            "category":"Building & Trades",
            "subcategory":"Locksmith",
            "type":"Services"
        }
    ],
    "sg:phone":"+1 347 392 3391",
    "sg:postcode":"11375",
    "sg:province":"NY",
    "sg:tags":[
        "key"
    ],
    "wof:name":"24 Hr Forest Hills Emergency Fast Lock",
    "wof:placetype":"venue"
},
  "geometry": {"coordinates":[-73.85229099999999,40.717004],"type":"Point"}
}