{
  "type": "Feature",
  "properties": {
    "addr:full":"6 East Ln Armonk NY 10504",
    "addr:housenumber":"6",
    "addr:postcode":"10504",
    "addr:street":"East Ln",
    "iso:country":"US",
    "sg:address":"6 East Ln",
    "sg:city":"Armonk",
    "sg:classifiers":[
        {
            "category":"Communications",
            "subcategory":"Film & Video Production",
            "type":"Services"
        }
    ],
    "sg:phone":"+1 914 273 4098",
    "sg:postcode":"10504",
    "sg:province":"NY",
    "sg:tags":[
        "motion"
    ],
    "wof:name":"East Lane Productions Inc",
    "wof:placetype":"venue"
},
  "geometry": {"coordinates":[-73.69605300000001,41.115981],"type":"Point"}
}