{
  "type": "Feature",
  "properties": {
    "addr:full":"225 S End Ave. Manhattan NY 10280",
    "addr:housenumber":"225",
    "addr:postcode":"10280",
    "addr:street":"S End Ave.",
    "iso:country":"US",
    "sg:address":"225 S End Ave.",
    "sg:city":"Manhattan",
    "sg:classifiers":[
        {
            "category":"Retail",
            "subcategory":"Laundry & Dry Cleaning",
            "type":"Services"
        }
    ],
    "sg:phone":"+1 212 945 3075",
    "sg:postcode":"10280",
    "sg:province":"NY",
    "wof:name":"Liberty Cleaners",
    "wof:placetype":"venue"
},
  "geometry": {"coordinates":[-74.0168003831,40.7096200523],"type":"Point"}
}