{
  "type": "Feature",
  "properties": {
    "addr:full":"893 Newport Rd Utica NY 13502",
    "addr:housenumber":"893",
    "addr:postcode":"13502",
    "addr:street":"Newport Rd",
    "iso:country":"US",
    "sg:address":"893 Newport Rd",
    "sg:city":"Utica",
    "sg:classifiers":[
        {
            "category":"Wholesale",
            "subcategory":"Toys & Hobbies",
            "type":"Manufacturing & Wholesale Goods"
        }
    ],
    "sg:phone":"+1 315 733 4004",
    "sg:postcode":"13502",
    "sg:province":"NY",
    "wof:name":"Touch of Country",
    "wof:placetype":"venue"
},
  "geometry": {"coordinates":[-75.11360500000001,43.143778],"type":"Point"}
}