{
  "type": "Feature",
  "properties": {
    "addr:full":"51 Lakeview Ave Rockville Centre NY 11570",
    "addr:housenumber":"51",
    "addr:postcode":"11570",
    "addr:street":"Lakeview Ave",
    "iso:country":"US",
    "sg:address":"51 Lakeview Ave",
    "sg:city":"Rockville Centre",
    "sg:classifiers":[
        {
            "category":"Shopping",
            "subcategory":"Discount & Variety Stores",
            "type":"Retail Goods"
        }
    ],
    "sg:phone":"+1 516 764 2228",
    "sg:postcode":"11570",
    "sg:province":"NY",
    "sg:tags":[
        "merchandise",
        "general"
    ],
    "wof:name":"Guard Supply Co",
    "wof:placetype":"venue"
},
  "geometry": {"coordinates":[-73.64783799999999,40.665903],"type":"Point"}
}