{
  "type": "Feature",
  "properties": {
    "addr:full":"17 Slater Dr Schenectady NY 12302",
    "addr:housenumber":"17",
    "addr:postcode":"12302",
    "addr:street":"Slater Dr",
    "iso:country":"US",
    "sg:address":"17 Slater Dr",
    "sg:city":"Schenectady",
    "sg:classifiers":[
        {
            "category":"Shopping",
            "subcategory":"Hobbies, Toys, & Games",
            "type":"Retail Goods"
        }
    ],
    "sg:phone":"+1   ",
    "sg:postcode":"12302",
    "sg:province":"NY",
    "wof:name":"R & J Toys",
    "wof:placetype":"venue"
},
  "geometry": {"coordinates":[-73.91383500000001,42.886675],"type":"Point"}
}