{
  "type": "Feature",
  "properties": {
    "addr:full":"379 Troy Ave Brooklyn NY 11213",
    "addr:housenumber":"379",
    "addr:postcode":"11213",
    "addr:street":"Troy Ave",
    "iso:country":"US",
    "sg:address":"379 Troy Ave",
    "sg:city":"Brooklyn",
    "sg:classifiers":[
        {
            "category":"Personal",
            "subcategory":"Beauty Salon",
            "type":"Services"
        }
    ],
    "sg:phone":"+1 718 735 4939",
    "sg:postcode":"11213",
    "sg:province":"NY",
    "wof:name":"Ketal Beauty Salon",
    "wof:placetype":"venue"
},
  "geometry": {"coordinates":[-73.936989,40.664775],"type":"Point"}
}