{
  "type": "Feature",
  "properties": {
    "iso:country":"US",
    "sg:address":"1927 Eggert Rd",
    "sg:city":"Buffalo",
    "sg:classifiers":[
        {
            "category":"Restaurant",
            "type":"Food & Drink"
        }
    ],
    "sg:phone":"+1   ",
    "sg:postcode":"14226",
    "sg:province":"NY",
    "wof:name":"Cobtis Restrnt",
    "wof:placetype":"venue"
},
  "geometry": {"coordinates":[-78.814684,42.97742],"type":"Point"}
}