{
  "type": "Feature",
  "properties": {
    "addr:full":"1844 Nostrand Ave Brooklyn NY 11226",
    "addr:housenumber":"1844",
    "addr:postcode":"11226",
    "addr:street":"Nostrand Ave",
    "iso:country":"US",
    "sg:address":"1844 Nostrand Ave",
    "sg:city":"Brooklyn",
    "sg:classifiers":[
        {
            "category":"Food & Beverages",
            "subcategory":"Groceries & Convenience Stores",
            "type":"Retail Goods"
        }
    ],
    "sg:phone":"+1 718 284 2290",
    "sg:postcode":"11226",
    "sg:province":"NY",
    "wof:name":"Avenue D Grocery Incorporated",
    "wof:placetype":"venue"
},
  "geometry": {"coordinates":[-73.948684,40.640804],"type":"Point"}
}