{
  "type": "Feature",
  "properties": {
    "addr:full":"2 17th St East Hampton NY 11937",
    "addr:housenumber":"2",
    "addr:postcode":"11937",
    "addr:street":"17Th St",
    "iso:country":"US",
    "sg:address":"2 17th St",
    "sg:city":"East Hampton",
    "sg:classifiers":[
        {
            "category":"Retail",
            "subcategory":"Laundry & Dry Cleaning",
            "type":"Services"
        }
    ],
    "sg:phone":"+1 631 668 7123",
    "sg:postcode":"11937",
    "sg:province":"NY",
    "sg:tags":[
        "cleaners",
        "rug",
        "carpet"
    ],
    "wof:name":"Hampton Carpet Cleaning",
    "wof:placetype":"venue"
},
  "geometry": {"coordinates":[-72.16090699999999,41.018516],"type":"Point"}
}