{
  "type": "Feature",
  "properties": {
    "iso:country":"US",
    "sg:address":"9 Orchard St",
    "sg:city":"Monsey",
    "sg:classifiers":[
        {
            "category":"Organizations",
            "subcategory":"Religious Organization",
            "type":"Services"
        }
    ],
    "sg:phone":"+1 845 352 3876",
    "sg:postcode":"10952",
    "sg:province":"NY",
    "sg:tags":[
        "clergy"
    ],
    "wof:name":"Mendel Morris",
    "wof:placetype":"venue"
},
  "geometry": {"coordinates":[-74.06999999999999,41.109856],"type":"Point"}
}