{
  "type": "Feature",
  "properties": {
    "addr:full":"501 New Karner Rd Albany NY 12205",
    "addr:housenumber":"501",
    "addr:postcode":"12205",
    "addr:street":"New Karner Rd",
    "iso:country":"US",
    "sg:address":"501 New Karner Rd",
    "sg:city":"Albany",
    "sg:classifiers":[
        {
            "category":"Shopping",
            "subcategory":"Crafts & Fabrics",
            "type":"Retail Goods"
        }
    ],
    "sg:phone":"+1 518 456 8885",
    "sg:postcode":"12205",
    "sg:province":"NY",
    "sg:tags":[
        "material",
        "quilting",
        "supply"
    ],
    "sg:website":"www.clasonline.com",
    "wof:name":"Flying Geese Fabrics",
    "wof:placetype":"venue"
},
  "geometry": {"coordinates":[-73.839483,42.742804],"type":"Point"}
}