{
  "type": "Feature",
  "properties": {
    "addr:full":"314 North Ave Hilton NY 14468",
    "addr:housenumber":"314",
    "addr:postcode":"14468",
    "addr:street":"North Ave",
    "iso:country":"US",
    "sg:address":"314 North Ave",
    "sg:city":"Hilton",
    "sg:classifiers":[
        {
            "category":"Building & Trades",
            "subcategory":"Construction",
            "type":"Services"
        }
    ],
    "sg:phone":"+1 585 392 4435",
    "sg:postcode":"14468",
    "sg:province":"NY",
    "sg:tags":[
        "hanging",
        "contractor"
    ],
    "wof:name":"Al Meyvis Jr",
    "wof:placetype":"venue"
},
  "geometry": {"coordinates":[-77.794738,43.316269],"type":"Point"}
}