{
  "type": "Feature",
  "properties": {
    "addr:full":"1813 68th Street Brooklyn NY 11204",
    "addr:housenumber":"1813",
    "addr:postcode":"11204",
    "addr:street":"68Th Street",
    "iso:country":"US",
    "sg:address":"1813 68th Street",
    "sg:city":"Brooklyn",
    "sg:classifiers":[
        {
            "category":"Building & Trades",
            "subcategory":"Plumbing",
            "type":"Services"
        }
    ],
    "sg:phone":"+1 718 236 8758",
    "sg:postcode":"11204",
    "sg:province":"NY",
    "wof:name":"D & C Plumbing & Watermain Contractors",
    "wof:placetype":"venue"
},
  "geometry": {"coordinates":[-73.991629,40.617327],"type":"Point"}
}