{
  "type": "Feature",
  "properties": {
    "iso:country":"US",
    "sg:address":"1422 Slaterville Rd",
    "sg:city":"Ithaca",
    "sg:classifiers":[
        {
            "category":"Organizations",
            "subcategory":"Religious Organization",
            "type":"Services"
        }
    ],
    "sg:phone":"+1   ",
    "sg:postcode":"14850",
    "sg:province":"NY",
    "wof:name":"Hillside Alliance Church Inc",
    "wof:placetype":"venue"
},
  "geometry": {"coordinates":[-76.46860100000001,42.427132],"type":"Point"}
}