{
  "type": "Feature",
  "properties": {
    "addr:full":"39 Yosemite Ave White Plains NY 10607",
    "addr:housenumber":"39",
    "addr:postcode":"10607",
    "addr:street":"Yosemite Ave",
    "iso:country":"US",
    "sg:address":"39 Yosemite Ave",
    "sg:city":"White Plains",
    "sg:classifiers":[
        {
            "category":"Building & Trades",
            "subcategory":"Construction",
            "type":"Services"
        }
    ],
    "sg:phone":"+1 914 761 7096",
    "sg:postcode":"10607",
    "sg:province":"NY",
    "sg:tags":[
        "downspouts",
        "gutter"
    ],
    "wof:name":"Rodrigo Seamless Gutters",
    "wof:placetype":"venue"
},
  "geometry": {"coordinates":[-73.800802,41.044941],"type":"Point"}
}