{
  "type": "Feature",
  "properties": {
    "addr:full":"66 Saint Marks Avenue Brooklyn NY 11217",
    "addr:housenumber":"66",
    "addr:postcode":"11217",
    "addr:street":"Saint Marks Avenue",
    "iso:country":"US",
    "sg:address":"66 Saint Marks Avenue",
    "sg:city":"Brooklyn",
    "sg:classifiers":[
        {
            "category":"Personal",
            "subcategory":"Barber",
            "type":"Services"
        }
    ],
    "sg:phone":"+1 718 857 1594",
    "sg:postcode":"11217",
    "sg:province":"NY",
    "wof:name":"Ruthies Neighborhood Barber",
    "wof:placetype":"venue"
},
  "geometry": {"coordinates":[-73.97506300000001,40.679821],"type":"Point"}
}