{
  "type": "Feature",
  "properties": {
    "iso:country":"US",
    "sg:address":"30 Glenn St",
    "sg:city":"White Plains",
    "sg:classifiers":[
        {
            "category":"Health Services",
            "subcategory":"Doctor",
            "type":"Services"
        }
    ],
    "sg:phone":"+1 914 422 3215",
    "sg:postcode":"10603",
    "sg:province":"NY",
    "sg:tags":[
        "physician",
        "surgeon"
    ],
    "wof:name":"Bennett Solnick MD",
    "wof:placetype":"venue"
},
  "geometry": {"coordinates":[-73.77051899999999,41.050663],"type":"Point"}
}