{
  "type": "Feature",
  "properties": {
    "iso:country":"US",
    "sg:address":"100 Fairport Village Lndg",
    "sg:city":"Fairport",
    "sg:classifiers":[
        {
            "category":"Shopping",
            "subcategory":"Hobbies, Toys, & Games",
            "type":"Retail Goods"
        }
    ],
    "sg:phone":"+1 585 377 7040",
    "sg:postcode":"14450",
    "sg:province":"NY",
    "sg:tags":[
        "craft"
    ],
    "wof:name":"Karen's Crafts",
    "wof:placetype":"venue"
},
  "geometry": {"coordinates":[-77.44345,43.10011],"type":"Point"}
}