{
  "type": "Feature",
  "properties": {
    "iso:country":"US",
    "sg:address":"844 Gragevine Ct",
    "sg:city":"Highland Mills",
    "sg:classifiers":[
        {
            "category":"Shopping",
            "subcategory":"Discount & Variety Stores",
            "type":"Retail Goods"
        }
    ],
    "sg:phone":"+1 845 928 5455",
    "sg:postcode":"10930",
    "sg:province":"NY",
    "sg:tags":[
        "outlet"
    ],
    "wof:name":"Ferdi North American Inc",
    "wof:placetype":"venue"
},
  "geometry": {"coordinates":[-74.120903,41.3503],"type":"Point"}
}