{
  "type": "Feature",
  "properties": {
    "addr:full":"1006 Grand Blvd Deer Park NY 11729",
    "addr:housenumber":"1006",
    "addr:postcode":"11729",
    "addr:street":"Grand Blvd",
    "iso:country":"US",
    "sg:address":"1006 Grand Blvd",
    "sg:city":"Deer Park",
    "sg:classifiers":[
        {
            "category":"Wholesale",
            "subcategory":"Construction Materials",
            "type":"Manufacturing & Wholesale Goods"
        }
    ],
    "sg:phone":"+1 631 254 2558",
    "sg:postcode":"11729",
    "sg:province":"NY",
    "sg:tags":[
        "mosaic"
    ],
    "wof:name":"Artsaics Studios",
    "wof:placetype":"venue"
},
  "geometry": {"coordinates":[-73.296689,40.760761],"type":"Point"}
}