{
  "type": "Feature",
  "properties": {
    "iso:country":"US",
    "sg:address":"13 W Park Ave",
    "sg:city":"Auburn",
    "sg:classifiers":[
        {
            "category":"Retail",
            "subcategory":"Auto Repair",
            "type":"Services"
        }
    ],
    "sg:phone":"+1 315 252 2012",
    "sg:postcode":"13021",
    "sg:province":"NY",
    "sg:tags":[
        "repairing",
        "automobile"
    ],
    "wof:name":"Minde's Garage",
    "wof:placetype":"venue"
},
  "geometry": {"coordinates":[-76.567179,42.942404],"type":"Point"}
}