{
  "type": "Feature",
  "properties": {
    "iso:country":"US",
    "sg:address":"8245 Main Rd",
    "sg:city":"East Marion",
    "sg:classifiers":[
        {
            "category":"Professional",
            "subcategory":"Business Services",
            "type":"Services"
        }
    ],
    "sg:phone":"+1   ",
    "sg:postcode":"11939",
    "sg:province":"NY",
    "wof:name":"Eastern Artisans Inc",
    "wof:placetype":"venue"
},
  "geometry": {"coordinates":[-72.322457,41.135499],"type":"Point"}
}