{
  "type": "Feature",
  "properties": {
    "addr:full":"78 E Spring St Buffalo NY 14221",
    "addr:housenumber":"78",
    "addr:postcode":"14221",
    "addr:street":"E Spring St",
    "iso:country":"US",
    "sg:address":"78 E Spring St",
    "sg:city":"Buffalo",
    "sg:classifiers":[
        {
            "category":"Restaurant",
            "type":"Food & Drink"
        }
    ],
    "sg:phone":"+1 716 633 2424",
    "sg:postcode":"14221",
    "sg:province":"NY",
    "sg:tags":[
        "parlor",
        "eating",
        "ice",
        "cream"
    ],
    "wof:name":"Jenny's Ice Cream",
    "wof:placetype":"venue"
},
  "geometry": {"coordinates":[-78.745302,42.963675],"type":"Point"}
}