{
  "type": "Feature",
  "properties": {
    "addr:full":"302 River St Rochester NY 14612",
    "addr:housenumber":"302",
    "addr:postcode":"14612",
    "addr:street":"River St",
    "iso:country":"US",
    "sg:address":"302 River St",
    "sg:city":"Rochester",
    "sg:classifiers":[
        {
            "category":"Building & Trades",
            "subcategory":"Construction",
            "type":"Services"
        }
    ],
    "sg:phone":"+1 585 865 2994",
    "sg:postcode":"14612",
    "sg:province":"NY",
    "sg:tags":[
        "house"
    ],
    "wof:name":"Shayoung Contractors Corp",
    "wof:placetype":"venue"
},
  "geometry": {"coordinates":[-77.613479,43.247522],"type":"Point"}
}