{
  "type": "Feature",
  "properties": {
    "iso:country":"US",
    "sg:address":"13 Main St",
    "sg:city":"Brockport",
    "sg:classifiers":[
        {
            "category":"Personal",
            "subcategory":"Beauty Salon",
            "type":"Services"
        }
    ],
    "sg:phone":"+1   ",
    "sg:postcode":"14420",
    "sg:province":"NY",
    "sg:tags":[
        "shop",
        "barber"
    ],
    "wof:name":"Village Hair Designers",
    "wof:placetype":"venue"
},
  "geometry": {"coordinates":[-77.93819999999999,43.216371],"type":"Point"}
}