{
  "type": "Feature",
  "properties": {
    "iso:country":"US",
    "sg:address":"1395 Clinton St",
    "sg:city":"Buffalo",
    "sg:classifiers":[
        {
            "category":"Home & Garden",
            "subcategory":"Furniture",
            "type":"Retail Goods"
        }
    ],
    "sg:phone":"+1 716 827 9188",
    "sg:postcode":"14206",
    "sg:province":"NY",
    "sg:tags":[
        "top",
        "counter"
    ],
    "wof:name":"Ultimate Solid Surface",
    "wof:placetype":"venue"
},
  "geometry": {"coordinates":[-78.824761,42.873875],"type":"Point"}
}