{
  "type": "Feature",
  "properties": {
    "addr:full":"80 Merrick Rd Amityville NY 11701",
    "addr:housenumber":"80",
    "addr:postcode":"11701",
    "addr:street":"Merrick Rd",
    "iso:country":"US",
    "sg:address":"80 Merrick Rd",
    "sg:city":"Amityville",
    "sg:classifiers":[
        {
            "category":"Professional",
            "subcategory":"Accounting & Tax Preparation",
            "type":"Services"
        }
    ],
    "sg:phone":"+1 631 842 2571",
    "sg:postcode":"11701",
    "sg:province":"NY",
    "sg:tags":[
        "return",
        "filing"
    ],
    "wof:name":"Amity Harbor Tax Svc",
    "wof:placetype":"venue"
},
  "geometry": {"coordinates":[-73.418435,40.671444],"type":"Point"}
}