{
  "type": "Feature",
  "properties": {
    "addr:full":"30 W 26th St New York NY 10010",
    "addr:housenumber":"30",
    "addr:postcode":"10010",
    "addr:street":"W 26Th St",
    "iso:country":"US",
    "sg:address":"30 W 26th St",
    "sg:city":"New York",
    "sg:classifiers":[
        {
            "category":"Professional",
            "type":"Services"
        }
    ],
    "sg:phone":"+1 212 633 2830",
    "sg:postcode":"10010",
    "sg:province":"NY",
    "sg:tags":[
        "establishment"
    ],
    "wof:name":"Informative",
    "wof:placetype":"venue"
},
  "geometry": {"coordinates":[-73.99104,40.744507],"type":"Point"}
}