{
  "type": "Feature",
  "properties": {
    "addr:full":"1365 York Ave New York NY 10021",
    "addr:housenumber":"1365",
    "addr:postcode":"10021",
    "addr:street":"York Ave",
    "iso:country":"US",
    "sg:address":"1365 York Ave",
    "sg:city":"New York",
    "sg:classifiers":[
        {
            "category":"Health Services",
            "subcategory":"Health Practitioner",
            "type":"Services"
        }
    ],
    "sg:phone":"+1 212 472 5820",
    "sg:postcode":"10021",
    "sg:province":"NY",
    "sg:tags":[
        "therapist",
        "physical"
    ],
    "wof:name":"Equilibrium Physical Therapy",
    "wof:placetype":"venue"
},
  "geometry": {"coordinates":[-73.95359000000001,40.767075],"type":"Point"}
}