{
  "type": "Feature",
  "properties": {
    "addr:full":"93 Broadway Brooklyn NY 11211",
    "addr:housenumber":"93",
    "addr:postcode":"11211",
    "addr:street":"Broadway",
    "iso:country":"US",
    "sg:address":"93 Broadway",
    "sg:city":"Brooklyn",
    "sg:classifiers":[
        {
            "category":"Retail",
            "subcategory":"Funeral Services",
            "type":"Services"
        }
    ],
    "sg:phone":"+1   ",
    "sg:postcode":"11211",
    "sg:province":"NY",
    "wof:name":"Yereim Orthodox Chapel",
    "wof:placetype":"venue"
},
  "geometry": {"coordinates":[-73.96398600000001,40.71039],"type":"Point"}
}