{
  "type": "Feature",
  "properties": {
    "addr:full":"1040 Pearl St Schenectady NY 12303",
    "addr:housenumber":"1040",
    "addr:postcode":"12303",
    "addr:street":"Pearl St",
    "iso:country":"US",
    "sg:address":"1040 Pearl St",
    "sg:city":"Schenectady",
    "sg:classifiers":[
        {
            "category":"Organizations",
            "subcategory":"Religious Organization",
            "type":"Services"
        }
    ],
    "sg:phone":"+1 518 374 4005",
    "sg:postcode":"12303",
    "sg:province":"NY",
    "sg:tags":[
        "church"
    ],
    "wof:name":"Holy Name-Jesus Polish Ntnl",
    "wof:placetype":"venue"
},
  "geometry": {"coordinates":[-73.943896,42.793726],"type":"Point"}
}