{
  "type": "Feature",
  "properties": {
    "addr:full":"120 Seneca St Geneva NY 14456",
    "addr:housenumber":"120",
    "addr:postcode":"14456",
    "addr:street":"Seneca St",
    "iso:country":"US",
    "sg:address":"120 Seneca St",
    "sg:city":"Geneva",
    "sg:classifiers":[
        {
            "category":"Restaurant",
            "type":"Food & Drink"
        }
    ],
    "sg:phone":"+1   ",
    "sg:postcode":"14456",
    "sg:province":"NY",
    "sg:tags":[
        "shop",
        "sub",
        "pizza"
    ],
    "wof:name":"Cousins Pizza and Subs",
    "wof:placetype":"venue"
},
  "geometry": {"coordinates":[-76.984903,42.86676],"type":"Point"}
}