{
  "type": "Feature",
  "properties": {
    "addr:full":"720 North Ave New Rochelle NY 10801",
    "addr:housenumber":"720",
    "addr:postcode":"10801",
    "addr:street":"North Ave",
    "iso:country":"US",
    "sg:address":"720 North Ave",
    "sg:city":"New Rochelle",
    "sg:classifiers":[
        {
            "category":"Restaurant",
            "type":"Food & Drink"
        }
    ],
    "sg:menulink":"http://www.allmenus.com/ny/new-rochelle/189260-mcdonalds/menu/",
    "sg:postcode":"10801",
    "sg:province":"NY",
    "sg:tags":[
        "burger",
        "american"
    ],
    "wof:name":"McDonald's",
    "wof:placetype":"venue"
},
  "geometry": {"coordinates":[-73.78888499999999,40.926244],"type":"Point"}
}