{
  "type": "Feature",
  "properties": {
    "iso:country":"US",
    "sg:address":"1 Lakeview Dr",
    "sg:city":"Peekskill",
    "sg:classifiers":[
        {
            "category":"Real Estate",
            "subcategory":"Real Estate Operator",
            "type":"Services"
        }
    ],
    "sg:phone":"+1 914 737 9131",
    "sg:postcode":"10566",
    "sg:province":"NY",
    "sg:tags":[
        "apartment"
    ],
    "wof:name":"Peekskill Towers Corp",
    "wof:placetype":"venue"
},
  "geometry": {"coordinates":[-73.925828,41.299425],"type":"Point"}
}