{
  "type": "Feature",
  "properties": {
    "addr:full":"85 Rockaway Ave Brooklyn NY 11233",
    "addr:housenumber":"85",
    "addr:postcode":"11233",
    "addr:street":"Rockaway Ave",
    "iso:country":"US",
    "sg:address":"85 Rockaway Ave",
    "sg:city":"Brooklyn",
    "sg:classifiers":[
        {
            "category":"Place Of Worship",
            "subcategory":"Church",
            "type":"Public Place"
        },
        {
            "category":"Place Of Worship",
            "type":"Public Place"
        }
    ],
    "sg:phone":"+1 718 455 1405",
    "sg:postcode":"11233",
    "sg:province":"NY",
    "sg:tags":[
        "churches-apostolic",
        "churches-pentecostal-apostolic"
    ],
    "wof:name":"Prayer Tabernacle International",
    "wof:placetype":"venue"
},
  "geometry": {"coordinates":[-73.911186,40.680098],"type":"Point"}
}