{
  "type": "Feature",
  "properties": {
    "addr:full":"804 Cauldwell Ave Bronx NY 10456",
    "addr:housenumber":"804",
    "addr:postcode":"10456",
    "addr:street":"Cauldwell Ave",
    "iso:country":"US",
    "sg:address":"804 Cauldwell Ave",
    "sg:city":"Bronx",
    "sg:classifiers":[
        {
            "category":"Food & Beverages",
            "subcategory":"Groceries & Convenience Stores",
            "type":"Retail Goods"
        }
    ],
    "sg:phone":"+1 718 292 1661",
    "sg:postcode":"10456",
    "sg:province":"NY",
    "sg:tags":[
        "grocer"
    ],
    "wof:name":"Cauldwell Deli Grocery",
    "wof:placetype":"venue"
},
  "geometry": {"coordinates":[-73.90771100000001,40.82104],"type":"Point"}
}