{
  "type": "Feature",
  "properties": {
    "addr:full":"629 Fifth Ave Pelham NY 10803",
    "addr:housenumber":"629",
    "addr:postcode":"10803",
    "addr:street":"Fifth Ave",
    "iso:country":"US",
    "sg:address":"629 Fifth Ave",
    "sg:city":"Pelham",
    "sg:classifiers":[
        {
            "category":"Professional",
            "subcategory":"Employment Agencies",
            "type":"Services"
        },
        {
            "category":"Professional",
            "subcategory":"Business Services",
            "type":"Services"
        }
    ],
    "sg:phone":"+1 914 738 8070",
    "sg:postcode":"10803",
    "sg:province":"NY",
    "sg:tags":[
        "consultants-referral",
        "consultant",
        "coach"
    ],
    "wof:name":"Lynn Drobbin & Associates",
    "wof:placetype":"venue"
},
  "geometry": {"coordinates":[-73.804416,40.920505],"type":"Point"}
}