{
  "type": "Feature",
  "properties": {
    "iso:country":"US",
    "sg:address":"264 W Fordham Rd",
    "sg:city":"Bronx",
    "sg:classifiers":[
        {
            "category":"Banks & Credit Unions",
            "subcategory":"Financial Services",
            "type":"Services"
        }
    ],
    "sg:phone":"+1 718 618 0447",
    "sg:postcode":"10468",
    "sg:province":"NY",
    "sg:tags":[
        "broker",
        "mortgage"
    ],
    "wof:name":"Yolimar Brokerage",
    "wof:placetype":"venue"
},
  "geometry": {"coordinates":[-73.910748,40.861538],"type":"Point"}
}