{
  "type": "Feature",
  "properties": {
    "iso:country":"US",
    "sg:address":"1448 Chambers Rd",
    "sg:city":"Beaver Dams",
    "sg:classifiers":[
        {
            "category":"Government",
            "subcategory":"Office",
            "type":"Public Place"
        }
    ],
    "sg:phone":"+1 607 739 5598",
    "sg:postcode":"14812",
    "sg:province":"NY",
    "sg:tags":[
        "legislative",
        "body"
    ],
    "wof:name":"Town of Catlin",
    "wof:placetype":"venue"
},
  "geometry": {"coordinates":[-76.910023,42.270268],"type":"Point"}
}