{
  "type": "Feature",
  "properties": {
    "iso:country":"US",
    "sg:address":"241 E Broadway",
    "sg:city":"New York",
    "sg:classifiers":[
        {
            "category":"Professional",
            "type":"Services"
        }
    ],
    "sg:phone":"+1 212 791 2727",
    "sg:postcode":"10002",
    "sg:province":"NY",
    "sg:tags":[
        "religious"
    ],
    "wof:name":"Congregation Zemach Zedek",
    "wof:placetype":"venue"
},
  "geometry": {"coordinates":[-73.98629800000001,40.714401],"type":"Point"}
}