{
  "type": "Feature",
  "properties": {
    "iso:country":"US",
    "sg:address":"301 McLennan Dr",
    "sg:city":"Fayetteville",
    "sg:classifiers":[
        {
            "category":"Social Services",
            "subcategory":"Child Care",
            "type":"Services"
        }
    ],
    "sg:phone":"+1   ",
    "sg:postcode":"13066",
    "sg:province":"NY",
    "sg:tags":[
        "day"
    ],
    "wof:name":"Hug A Bunch",
    "wof:placetype":"venue"
},
  "geometry": {"coordinates":[-76.03026199999999,43.035177],"type":"Point"}
}