{
  "type": "Feature",
  "properties": {
    "addr:full":"124 Main St Chester NY 10918",
    "addr:housenumber":"124",
    "addr:postcode":"10918",
    "addr:street":"Main St",
    "iso:country":"US",
    "sg:address":"124 Main St",
    "sg:city":"Chester",
    "sg:classifiers":[
        {
            "category":"Real Estate",
            "subcategory":"Real Estate Services",
            "type":"Services"
        },
        {
            "category":"Real Estate",
            "subcategory":"Real Estate Agent",
            "type":"Services"
        }
    ],
    "sg:phone":"+1 845 469 7781",
    "sg:postcode":"10918",
    "sg:province":"NY",
    "sg:tags":[
        "buyer",
        "broker"
    ],
    "wof:name":"Foley Scott V Realtors & Insurance Inc",
    "wof:placetype":"venue"
},
  "geometry": {"coordinates":[-74.277125,41.354975],"type":"Point"}
}