{
  "type": "Feature",
  "properties": {
    "iso:country":"US",
    "sg:address":"1460 Old Rte 22",
    "sg:city":"Brewster",
    "sg:classifiers":[
        {
            "category":"Shopping",
            "subcategory":"Florist",
            "type":"Retail Goods"
        },
        {
            "category":"Home & Garden",
            "subcategory":"Garden Supply",
            "type":"Retail Goods"
        }
    ],
    "sg:phone":"+1 845 278 7111",
    "sg:postcode":"10509",
    "sg:province":"NY",
    "sg:tags":[
        "nurseryman",
        "flower"
    ],
    "wof:name":"Venamy Orchids Inc",
    "wof:placetype":"venue"
},
  "geometry": {"coordinates":[-73.58202,41.461121],"type":"Point"}
}