{
  "type": "Feature",
  "properties": {
    "addr:full":"367 S Sunrise Rd West Babylon NY 11704",
    "addr:housenumber":"367",
    "addr:postcode":"11704",
    "addr:street":"S Sunrise Rd",
    "iso:country":"US",
    "sg:address":"367 S Sunrise Rd",
    "sg:city":"West Babylon",
    "sg:classifiers":[
        {
            "category":"Retail",
            "subcategory":"Auto Repair",
            "type":"Services"
        }
    ],
    "sg:phone":"+1 631 321 4893",
    "sg:postcode":"11704",
    "sg:province":"NY",
    "sg:tags":[
        "body",
        "automobile",
        "painting"
    ],
    "wof:name":"West Babylon Collision",
    "wof:placetype":"venue"
},
  "geometry": {"coordinates":[-73.36426400000001,40.712296],"type":"Point"}
}