{
  "type": "Feature",
  "properties": {
    "addr:full":"5721 18th Avenue Brooklyn NY 11204",
    "addr:housenumber":"5721",
    "addr:postcode":"11204",
    "addr:street":"18Th Avenue",
    "iso:country":"US",
    "sg:address":"5721 18th Avenue",
    "sg:city":"Brooklyn",
    "sg:classifiers":[
        {
            "category":"Deli",
            "type":"Food & Drink"
        },
        {
            "category":"Food & Beverages",
            "subcategory":"Bakery",
            "type":"Retail Goods"
        }
    ],
    "sg:phone":"+1 718 256 1809",
    "sg:postcode":"11204",
    "sg:province":"NY",
    "sg:tags":[
        "sandwich"
    ],
    "wof:name":"Deli Plus",
    "wof:placetype":"venue"
},
  "geometry": {"coordinates":[-73.985506,40.623589],"type":"Point"}
}