{
  "type": "Feature",
  "properties": {
    "iso:country":"US",
    "sg:address":"August Wilson Theatre 245 W 52nd St",
    "sg:city":"New York",
    "sg:classifiers":[
        {
            "category":"Arts & Performance",
            "subcategory":"Arts Center",
            "type":"Entertainment"
        }
    ],
    "sg:phone":"+1 212 239 6200",
    "sg:postcode":"10019",
    "sg:province":"NY",
    "sg:tags":[
        "performing"
    ],
    "sg:website":"www.JerseyBoysInfo.com/Broadway",
    "wof:name":"Jersey Boys",
    "wof:placetype":"venue"
},
  "geometry": {"coordinates":[-73.98410199999999,40.763077],"type":"Point"}
}