{
  "type": "Feature",
  "properties": {
    "addr:full":"96 Maiden Ln Kingston NY 12401",
    "addr:housenumber":"96",
    "addr:postcode":"12401",
    "addr:street":"Maiden Ln",
    "iso:country":"US",
    "sg:address":"96 Maiden Ln",
    "sg:city":"Kingston",
    "sg:classifiers":[
        {
            "category":"Professional",
            "subcategory":"Lawyer & Legal Services",
            "type":"Services"
        }
    ],
    "sg:phone":"+1 845 338 7222",
    "sg:postcode":"12401",
    "sg:province":"NY",
    "sg:tags":[
        "attorney"
    ],
    "wof:name":"Aegis Abstract Co",
    "wof:placetype":"venue"
},
  "geometry": {"coordinates":[-74.01714,41.930844],"type":"Point"}
}