{
  "type": "Feature",
  "properties": {
    "iso:country":"US",
    "sg:address":"7001 Amboy Rd",
    "sg:city":"Staten Island",
    "sg:classifiers":[
        {
            "category":"Health Services",
            "subcategory":"Medical Lab",
            "type":"Services"
        }
    ],
    "sg:phone":"+1 718 227 9961",
    "sg:postcode":"10307",
    "sg:province":"NY",
    "sg:tags":[
        "laboratory"
    ],
    "wof:name":"Quest Diagnotics",
    "wof:placetype":"venue"
},
  "geometry": {"coordinates":[-74.234258,40.515459],"type":"Point"}
}