{
  "type": "Feature",
  "properties": {
    "iso:country":"US",
    "sg:address":"3655 E Tremont Ave",
    "sg:city":"Bronx",
    "sg:classifiers":[
        {
            "category":"Personal",
            "type":"Services"
        }
    ],
    "sg:phone":"+1 800 868 3933",
    "sg:postcode":"10465",
    "sg:province":"NY",
    "sg:tags":[
        "mover"
    ],
    "wof:name":"Mighty Mike's Moving Express Inc",
    "wof:placetype":"venue"
},
  "geometry": {"coordinates":[-73.823515,40.82804],"type":"Point"}
}