{
  "type": "Feature",
  "properties": {
    "iso:country":"US",
    "sg:address":"143 Union St",
    "sg:city":"Mineola",
    "sg:classifiers":[
        {
            "category":"Building & Trades",
            "subcategory":"Landscaping Services",
            "type":"Services"
        }
    ],
    "sg:phone":"+1 516 294 0298",
    "sg:postcode":"11501",
    "sg:province":"NY",
    "wof:name":"Aldo Gatta Landscaping",
    "wof:placetype":"venue"
},
  "geometry": {"coordinates":[-73.62960200000001,40.746999],"type":"Point"}
}