{
  "type": "Feature",
  "properties": {
    "addr:full":"650 Manhattan Ave Apt 1 Brooklyn NY 11222",
    "addr:housenumber":"650;1",
    "addr:postcode":"11222",
    "addr:street":"Manhattan Ave Apt",
    "iso:country":"US",
    "sg:address":"650 Manhattan Ave Apt 1",
    "sg:city":"Brooklyn",
    "sg:classifiers":[
        {
            "category":"Shopping",
            "subcategory":"Jewelry",
            "type":"Retail Goods"
        }
    ],
    "sg:phone":"+1 718 383 6203",
    "sg:postcode":"11222",
    "sg:province":"NY",
    "wof:name":"Milano Fine Jewelery Inc",
    "wof:placetype":"venue"
},
  "geometry": {"coordinates":[-73.95086499999999,40.724453],"type":"Point"}
}