{
  "type": "Feature",
  "properties": {
    "addr:full":"81 Irondequoit Mall Dr Rochester NY 14622",
    "addr:housenumber":"81",
    "addr:postcode":"14622",
    "addr:street":"Irondequoit Mall Dr",
    "iso:country":"US",
    "sg:address":"81 Irondequoit Mall Dr",
    "sg:city":"Rochester",
    "sg:classifiers":[
        {
            "category":"Shopping",
            "subcategory":"Beauty & Cosmetics",
            "type":"Retail Goods"
        }
    ],
    "sg:phone":"+1   ",
    "sg:postcode":"14622",
    "sg:province":"NY",
    "sg:tags":[
        "hair",
        "product",
        "skin",
        "care"
    ],
    "wof:name":"Buth-Na-Bodhaige Inc",
    "wof:placetype":"venue"
},
  "geometry": {"coordinates":[-77.57333199999999,43.199559],"type":"Point"}
}