{
  "type": "Feature",
  "properties": {
    "addr:full":"273 Columbus Ave Tuckahoe NY 10707",
    "addr:housenumber":"273",
    "addr:postcode":"10707",
    "addr:street":"Columbus Ave",
    "iso:country":"US",
    "sg:address":"273 Columbus Ave",
    "sg:city":"Tuckahoe",
    "sg:classifiers":[
        {
            "category":"Real Estate",
            "subcategory":"Real Estate Agent",
            "type":"Services"
        }
    ],
    "sg:phone":"+1 914 793 9688",
    "sg:postcode":"10707",
    "sg:province":"NY",
    "wof:name":"Priority Real Estate Advisory",
    "wof:placetype":"venue"
},
  "geometry": {"coordinates":[-73.821226,40.958411],"type":"Point"}
}