{
  "type": "Feature",
  "properties": {
    "addr:full":"174 Washington Ave Albany NY 12210",
    "addr:housenumber":"174",
    "addr:postcode":"12210",
    "addr:street":"Washington Ave",
    "iso:country":"US",
    "sg:address":"174 Washington Ave",
    "sg:city":"Albany",
    "sg:classifiers":[
        {
            "category":"Professional",
            "subcategory":"Lawyer & Legal Services",
            "type":"Services"
        }
    ],
    "sg:phone":"+1 518 464 6464",
    "sg:postcode":"12210",
    "sg:province":"NY",
    "sg:tags":[
        "attorney"
    ],
    "wof:name":"David Brickman Attorney",
    "wof:placetype":"venue"
},
  "geometry": {"coordinates":[-73.76244699999999,42.656154],"type":"Point"}
}