{
  "type": "Feature",
  "properties": {
    "addr:full":"4081 State Hwy 31 Clay NY 13041",
    "addr:housenumber":"4081",
    "addr:postcode":"13041",
    "addr:street":"State Hwy 31",
    "iso:country":"US",
    "sg:address":"4081 State Hwy 31",
    "sg:city":"Clay",
    "sg:classifiers":[
        {
            "category":"Professional",
            "subcategory":"Accounting & Tax Preparation",
            "type":"Services"
        }
    ],
    "sg:phone":"+1 315 652 3104",
    "sg:postcode":"13041",
    "sg:province":"NY",
    "sg:tags":[
        "return",
        "filing"
    ],
    "wof:name":"H & R Block Tax Svc",
    "wof:placetype":"venue"
},
  "geometry": {"coordinates":[-76.23142799999999,43.18565],"type":"Point"}
}