{
  "type": "Feature",
  "properties": {
    "addr:full":"271 Piermont Ave Piermont NY 10968",
    "addr:housenumber":"271",
    "addr:postcode":"10968",
    "addr:street":"Piermont Ave",
    "iso:country":"US",
    "sg:address":"271 Piermont Ave",
    "sg:city":"Piermont",
    "sg:classifiers":[
        {
            "category":"Personal",
            "subcategory":"Beauty Salon",
            "type":"Services"
        },
        {
            "category":"Personal",
            "subcategory":"Skin Care",
            "type":"Services"
        }
    ],
    "sg:phone":"+1 201 840 5568",
    "sg:postcode":"10968",
    "sg:province":"NY",
    "wof:name":"Robert Lawrence Salon",
    "wof:placetype":"venue"
},
  "geometry": {"coordinates":[-73.919101,41.035315],"type":"Point"}
}