{
  "type": "Feature",
  "properties": {
    "iso:country":"US",
    "sg:address":"1901 Utica Ave",
    "sg:city":"Brooklyn",
    "sg:classifiers":[
        {
            "category":"Health Services",
            "subcategory":"Doctor",
            "type":"Services"
        }
    ],
    "sg:phone":"+1 718 968 8700",
    "sg:postcode":"11234",
    "sg:province":"NY",
    "sg:tags":[
        "physician",
        "surgeon"
    ],
    "wof:name":"Brook Plaza Ophthalmology",
    "wof:placetype":"venue"
},
  "geometry": {"coordinates":[-73.92731499999999,40.623825],"type":"Point"}
}