{
  "type": "Feature",
  "properties": {
    "iso:country":"US",
    "sg:address":"217 McKinley Ave",
    "sg:city":"Buffalo",
    "sg:classifiers":[
        {
            "category":"Food & Beverages",
            "subcategory":"Specialty",
            "type":"Retail Goods"
        }
    ],
    "sg:phone":"+1   ",
    "sg:postcode":"14217",
    "sg:province":"NY",
    "sg:tags":[
        "shop",
        "coffee"
    ],
    "wof:name":"Gloria Jeans Gourmet Coffee",
    "wof:placetype":"venue"
},
  "geometry": {"coordinates":[-78.858998,42.964639],"type":"Point"}
}