{
  "type": "Feature",
  "properties": {
    "addr:full":"104 Cayuga St Fulton NY 13069",
    "addr:housenumber":"104",
    "addr:postcode":"13069",
    "addr:street":"Cayuga St",
    "iso:country":"US",
    "sg:address":"104 Cayuga St",
    "sg:city":"Fulton",
    "sg:classifiers":[
        {
            "category":"Professional",
            "subcategory":"Employment Agencies",
            "type":"Services"
        }
    ],
    "sg:phone":"+1 315 598 8230",
    "sg:postcode":"13069",
    "sg:province":"NY",
    "sg:tags":[
        "help",
        "supply"
    ],
    "wof:name":"Adecco Staffing",
    "wof:placetype":"venue"
},
  "geometry": {"coordinates":[-76.416274,43.324196],"type":"Point"}
}