{
  "type": "Feature",
  "properties": {
    "iso:country":"US",
    "sg:address":"2101 Washington Ave",
    "sg:city":"Seaford",
    "sg:classifiers":[
        {
            "category":"Professional",
            "type":"Services"
        }
    ],
    "sg:phone":"+1 516 781 8049",
    "sg:postcode":"11783",
    "sg:province":"NY",
    "sg:tags":[
        "establishment"
    ],
    "wof:name":"Perception Technology Corp",
    "wof:placetype":"venue"
},
  "geometry": {"coordinates":[-73.48474899999999,40.670418],"type":"Point"}
}