{
  "type": "Feature",
  "properties": {
    "iso:country":"US",
    "sg:address":"2 W Main St",
    "sg:city":"Victor",
    "sg:classifiers":[
        {
            "category":"Banks & Credit Unions",
            "subcategory":"Investment Brokerage",
            "type":"Services"
        },
        {
            "category":"Banks & Credit Unions",
            "subcategory":"Bank",
            "type":"Services"
        },
        {
            "category":"Banks & Credit Unions",
            "subcategory":"Financial Services",
            "type":"Services"
        }
    ],
    "sg:phone":"+1 877 900 1782",
    "sg:postcode":"14564",
    "sg:province":"NY",
    "sg:tags":[
        "advisory",
        "mutual",
        "retirement",
        "annuity",
        "broker",
        "fund",
        "planning",
        "plan",
        "consultant",
        "security",
        "bond",
        "insurance",
        "stock"
    ],
    "sg:website":"http://rochester.citysearch.com/profile/external/604312192/victor_ny/edward_jones_david_g_green.html?publisher=yellowpages&reference_id=1&placement=ypwebsitemip",
    "wof:name":"Edward Jones - DAVID G GREEN",
    "wof:placetype":"venue"
},
  "geometry": {"coordinates":[-77.409561,42.982529],"type":"Point"}
}