{
  "type": "Feature",
  "properties": {
    "addr:full":"704 Arthur St Syracuse NY 13207",
    "addr:housenumber":"704",
    "addr:postcode":"13207",
    "addr:street":"Arthur St",
    "iso:country":"US",
    "sg:address":"704 Arthur St",
    "sg:city":"Syracuse",
    "sg:classifiers":[
        {
            "category":"Insurance",
            "subcategory":"Insurance Agent",
            "type":"Services"
        }
    ],
    "sg:phone":"+1 315 474 3017",
    "sg:postcode":"13207",
    "sg:province":"NY",
    "wof:name":"Erie Insurance",
    "wof:placetype":"venue"
},
  "geometry": {"coordinates":[-76.17690899999999,43.030044],"type":"Point"}
}