{
  "type": "Feature",
  "properties": {
    "iso:country":"US",
    "sg:address":"236 W 30 St",
    "sg:city":"New York",
    "sg:classifiers":[
        {
            "category":"Professional",
            "subcategory":"Business Services",
            "type":"Services"
        }
    ],
    "sg:phone":"+1 212 695 1899",
    "sg:postcode":"10001",
    "sg:province":"NY",
    "wof:name":"Michael M Krieger",
    "wof:placetype":"venue"
},
  "geometry": {"coordinates":[-73.994546,40.749164],"type":"Point"}
}