{
  "type": "Feature",
  "properties": {
    "iso:country":"US",
    "sg:address":"23 Elm St",
    "sg:city":"Westfield",
    "sg:classifiers":[
        {
            "category":"Government",
            "subcategory":"Office",
            "type":"Public Place"
        }
    ],
    "sg:phone":"+1 716 326 3932",
    "sg:postcode":"14787",
    "sg:province":"NY",
    "sg:tags":[
        "city",
        "program"
    ],
    "wof:name":"Westfield Water Pollution",
    "wof:placetype":"venue"
},
  "geometry": {"coordinates":[-79.576211,42.321799],"type":"Point"}
}