{
  "type": "Feature",
  "properties": {
    "addr:full":"14 Mirrielees Rd Great Neck NY 11021",
    "addr:housenumber":"14",
    "addr:postcode":"11021",
    "addr:street":"Mirrielees Rd",
    "iso:country":"US",
    "sg:address":"14 Mirrielees Rd",
    "sg:city":"Great Neck",
    "sg:classifiers":[
        {
            "category":"Arts & Performance",
            "subcategory":"Theater",
            "type":"Entertainment"
        }
    ],
    "sg:phone":"+1 516 829 9687",
    "sg:postcode":"11021",
    "sg:province":"NY",
    "sg:tags":[
        "bureau"
    ],
    "wof:name":"A-1 Entertainment",
    "wof:placetype":"venue"
},
  "geometry": {"coordinates":[-73.73759,40.780501],"type":"Point"}
}