{
  "type": "Feature",
  "properties": {
    "addr:full":"17 Franklin Ave Lynbrook NY 11563",
    "addr:housenumber":"17",
    "addr:postcode":"11563",
    "addr:street":"Franklin Ave",
    "iso:country":"US",
    "sg:address":"17 Franklin Ave",
    "sg:city":"Lynbrook",
    "sg:classifiers":[
        {
            "category":"Professional",
            "subcategory":"Accounting & Tax Preparation",
            "type":"Services"
        }
    ],
    "sg:phone":"+1 516 599 4458",
    "sg:postcode":"11563",
    "sg:province":"NY",
    "sg:tags":[
        "accountant"
    ],
    "wof:name":"Kenneth S Moskowitz CPA",
    "wof:placetype":"venue"
},
  "geometry": {"coordinates":[-73.673269,40.670865],"type":"Point"}
}