{
  "type": "Feature",
  "properties": {
    "iso:country":"US",
    "sg:address":"4062 Broadway Ave",
    "sg:city":"New York",
    "sg:classifiers":[
        {
            "category":"Shopping",
            "subcategory":"Mobile Phones",
            "type":"Retail Goods"
        }
    ],
    "sg:phone":"+1 212 923 1126",
    "sg:postcode":"10025",
    "sg:province":"NY",
    "wof:name":"Hipoint Wireless",
    "wof:placetype":"venue"
},
  "geometry": {"coordinates":[-73.964755,40.807025],"type":"Point"}
}