{
  "type": "Feature",
  "properties": {
    "addr:full":"611 Madison Ave New York NY 10022",
    "addr:housenumber":"611",
    "addr:postcode":"10022",
    "addr:street":"Madison Ave",
    "iso:country":"US",
    "sg:address":"611 Madison Ave",
    "sg:city":"New York",
    "sg:classifiers":[
        {
            "category":"Shopping",
            "subcategory":"Jewelry",
            "type":"Retail Goods"
        }
    ],
    "sg:phone":"+1 212 758 4301",
    "sg:postcode":"10022",
    "sg:province":"NY",
    "sg:tags":[
        "jeweler"
    ],
    "wof:name":"Agatha",
    "wof:placetype":"venue"
},
  "geometry": {"coordinates":[-73.97235999999999,40.762288],"type":"Point"}
}