{
  "type": "Feature",
  "properties": {
    "addr:full":"51 Main St Lockport NY 14094",
    "addr:housenumber":"51",
    "addr:postcode":"14094",
    "addr:street":"Main St",
    "iso:country":"US",
    "sg:address":"51 Main St",
    "sg:city":"Lockport",
    "sg:classifiers":[
        {
            "category":"Wholesale",
            "subcategory":"Jewelry",
            "type":"Manufacturing & Wholesale Goods"
        },
        {
            "category":"Manufacturing",
            "subcategory":"Jewelry",
            "type":"Manufacturing & Wholesale Goods"
        },
        {
            "category":"Retail",
            "subcategory":"Repair Shop",
            "type":"Services"
        }
    ],
    "sg:phone":"+1 716 439 4748",
    "sg:postcode":"14094",
    "sg:province":"NY",
    "sg:tags":[
        "repairing",
        "jeweler",
        "clock",
        "finding",
        "supply"
    ],
    "wof:name":"Reflective Solutions Inc",
    "wof:placetype":"venue"
},
  "geometry": {"coordinates":[-78.69222000000001,43.16994],"type":"Point"}
}