{
  "type": "Feature",
  "properties": {
    "addr:full":"10 Fawn Ln Queensbury NY 12804",
    "addr:housenumber":"10",
    "addr:postcode":"12804",
    "addr:street":"Fawn Ln",
    "iso:country":"US",
    "sg:address":"10 Fawn Ln",
    "sg:city":"Queensbury",
    "sg:classifiers":[
        {
            "category":"Wholesale",
            "subcategory":"Machinery & Supplies",
            "type":"Manufacturing & Wholesale Goods"
        }
    ],
    "sg:phone":"+1 518 745 7172",
    "sg:postcode":"12804",
    "sg:province":"NY",
    "sg:tags":[
        "equipment",
        "industrial"
    ],
    "wof:name":"Barrd Industrial LLC",
    "wof:placetype":"venue"
},
  "geometry": {"coordinates":[-73.718957,43.311617],"type":"Point"}
}