{
  "type": "Feature",
  "properties": {
    "addr:full":"1316 Montauk Hwy Oakdale NY 11769",
    "addr:housenumber":"1316",
    "addr:postcode":"11769",
    "addr:street":"Montauk Hwy",
    "iso:country":"US",
    "sg:address":"1316 Montauk Hwy",
    "sg:city":"Oakdale",
    "sg:classifiers":[
        {
            "category":"Shopping",
            "subcategory":"Tobacco",
            "type":"Retail Goods"
        }
    ],
    "sg:phone":"+1 631 218 0580",
    "sg:postcode":"11769",
    "sg:province":"NY",
    "sg:tags":[
        "shop"
    ],
    "wof:name":"Oakdale Smoke Shop",
    "wof:placetype":"venue"
},
  "geometry": {"coordinates":[-73.131203,40.742199],"type":"Point"}
}