{
  "type": "Feature",
  "properties": {
    "addr:full":"10 E Hampton Dr East Hampton NY 11937",
    "addr:housenumber":"10",
    "addr:postcode":"11937",
    "addr:street":"E Hampton Dr East",
    "iso:country":"US",
    "sg:address":"10 E Hampton Dr",
    "sg:city":"East Hampton",
    "sg:classifiers":[
        {
            "category":"Professional",
            "subcategory":"Lawyer & Legal Services",
            "type":"Services"
        }
    ],
    "sg:phone":"+1 631 324 3262",
    "sg:postcode":"11937",
    "sg:province":"NY",
    "sg:tags":[
        "attorney"
    ],
    "wof:name":"Marvin Hyman",
    "wof:placetype":"venue"
},
  "geometry": {"coordinates":[-72.172982,40.983535],"type":"Point"}
}