{
  "type": "Feature",
  "properties": {
    "iso:country":"US",
    "sg:address":"11 Vernon Ave",
    "sg:city":"Mastic",
    "sg:classifiers":[
        {
            "category":"Autos & Motor Vehicles",
            "subcategory":"Motorcycle Sales",
            "type":"Retail Goods"
        }
    ],
    "sg:phone":"+1 631 772 2281",
    "sg:postcode":"11950",
    "sg:province":"NY",
    "wof:name":"American Custom Choppers Inc",
    "wof:placetype":"venue"
},
  "geometry": {"coordinates":[-72.843304,40.806846],"type":"Point"}
}