{
  "type": "Feature",
  "properties": {
    "addr:full":"3215 Southwestern Blvd Orchard Park NY 14127",
    "addr:housenumber":"3215",
    "addr:postcode":"14127",
    "addr:street":"Southwestern Blvd",
    "iso:country":"US",
    "sg:address":"3215 Southwestern Blvd",
    "sg:city":"Orchard Park",
    "sg:classifiers":[
        {
            "category":"Shopping",
            "subcategory":"Gifts & Souvenirs",
            "type":"Retail Goods"
        }
    ],
    "sg:phone":"+1 716 677 0800",
    "sg:postcode":"14127",
    "sg:province":"NY",
    "sg:tags":[
        "cards",
        "greeting"
    ],
    "wof:name":"Cardsmart Greetings Crossroads",
    "wof:placetype":"venue"
},
  "geometry": {"coordinates":[-78.753244,42.79546],"type":"Point"}
}