{
  "type": "Feature",
  "properties": {
    "iso:country":"US",
    "sg:address":"4 S Main St",
    "sg:city":"Franklinville",
    "sg:classifiers":[
        {
            "category":"Professional",
            "subcategory":"Lawyer & Legal Services",
            "type":"Services"
        }
    ],
    "sg:phone":"+1 716 676 5524",
    "sg:postcode":"14737",
    "sg:province":"NY",
    "sg:tags":[
        "attorney"
    ],
    "wof:name":"Moriarty & Swanz",
    "wof:placetype":"venue"
},
  "geometry": {"coordinates":[-78.457898,42.336875],"type":"Point"}
}