{
  "type": "Feature",
  "properties": {
    "iso:country":"US",
    "sg:address":"3501 Henneberry Rd",
    "sg:city":"Jamesville",
    "sg:classifiers":[
        {
            "category":"Manufacturing",
            "subcategory":"Metals",
            "type":"Manufacturing & Wholesale Goods"
        }
    ],
    "sg:phone":"+1 315 682 2512",
    "sg:postcode":"13078",
    "sg:province":"NY",
    "sg:tags":[
        "casting"
    ],
    "wof:name":"Caldwell & Ward Casting Co",
    "wof:placetype":"venue"
},
  "geometry": {"coordinates":[-76.000637,42.944587],"type":"Point"}
}