{
  "type": "Feature",
  "properties": {
    "iso:country":"US",
    "sg:address":"4 Center St",
    "sg:city":"Glens Falls",
    "sg:classifiers":[
        {
            "category":"Social Services",
            "subcategory":"Job Training",
            "type":"Services"
        }
    ],
    "sg:phone":"+1 518 926 7500",
    "sg:postcode":"12801",
    "sg:province":"NY",
    "sg:tags":[
        "rehabilitation"
    ],
    "wof:name":"Glens Falls Physical Therapy",
    "wof:placetype":"venue"
},
  "geometry": {"coordinates":[-73.641265,43.31132],"type":"Point"}
}