{
  "type": "Feature",
  "properties": {
    "addr:full":"200 Bay St Staten Island NY 10301",
    "addr:housenumber":"200",
    "addr:postcode":"10301",
    "addr:street":"Bay St",
    "iso:country":"US",
    "sg:address":"200 Bay St",
    "sg:city":"Staten Island",
    "sg:classifiers":[
        {
            "category":"Local Transit",
            "type":"Transportation"
        }
    ],
    "sg:phone":"+1 718 447 2500",
    "sg:postcode":"10301",
    "sg:province":"NY",
    "sg:tags":[
        "car"
    ],
    "wof:name":"De Joys Car Svc",
    "wof:placetype":"venue"
},
  "geometry": {"coordinates":[-74.07668,40.637491],"type":"Point"}
}