{
  "type": "Feature",
  "properties": {
    "iso:country":"US",
    "sg:address":"1839 Central Ave",
    "sg:city":"Albany",
    "sg:classifiers":[
        {
            "category":"Health Services",
            "subcategory":"Doctor",
            "type":"Services"
        }
    ],
    "sg:phone":"+1 518 464 0402",
    "sg:postcode":"12205",
    "sg:province":"NY",
    "sg:tags":[
        "dentist"
    ],
    "wof:name":"Small Smiles Dentistry-Albany",
    "wof:placetype":"venue"
},
  "geometry": {"coordinates":[-73.84766999999999,42.730587],"type":"Point"}
}