{
  "type": "Feature",
  "properties": {
    "addr:full":"299 Smithtown Blvd Nesconset NY 11767",
    "addr:housenumber":"299",
    "addr:postcode":"11767",
    "addr:street":"Smithtown Blvd",
    "iso:country":"US",
    "sg:address":"299 Smithtown Blvd",
    "sg:city":"Nesconset",
    "sg:classifiers":[
        {
            "category":"Wholesale",
            "subcategory":"Non-durable Goods",
            "type":"Manufacturing & Wholesale Goods"
        }
    ],
    "sg:phone":"+1 631 580 7023",
    "sg:postcode":"11767",
    "sg:province":"NY",
    "sg:tags":[
        "advertising",
        "specialty"
    ],
    "wof:name":"Global Network Products",
    "wof:placetype":"venue"
},
  "geometry": {"coordinates":[-73.13949100000001,40.832438],"type":"Point"}
}