{
  "type": "Feature",
  "properties": {
    "addr:full":"178 Industrial Loop Staten Island NY 10309",
    "addr:housenumber":"178",
    "addr:postcode":"10309",
    "addr:street":"Industrial Loop",
    "iso:country":"US",
    "sg:address":"178 Industrial Loop",
    "sg:city":"Staten Island",
    "sg:classifiers":[
        {
            "category":"Wholesale",
            "subcategory":"Electrical",
            "type":"Manufacturing & Wholesale Goods"
        }
    ],
    "sg:phone":"+1 718 317 7860",
    "sg:postcode":"10309",
    "sg:province":"NY",
    "sg:tags":[
        "appliance"
    ],
    "wof:name":"Independent Appliance Install",
    "wof:placetype":"venue"
},
  "geometry": {"coordinates":[-74.23116400000001,40.548602],"type":"Point"}
}