{
  "type": "Feature",
  "properties": {
    "addr:full":"399 Alexander St Rochester NY 14607",
    "addr:housenumber":"399",
    "addr:postcode":"14607",
    "addr:street":"Alexander St",
    "iso:country":"US",
    "sg:address":"399 Alexander St",
    "sg:city":"Rochester",
    "sg:classifiers":[
        {
            "category":"Social Services",
            "type":"Services"
        }
    ],
    "sg:phone":"+1 585 546 5180",
    "sg:postcode":"14607",
    "sg:province":"NY",
    "sg:tags":[
        "counseling"
    ],
    "wof:name":"KAVOD",
    "wof:placetype":"venue"
},
  "geometry": {"coordinates":[-77.591885,43.159946],"type":"Point"}
}