{
  "type": "Feature",
  "properties": {
    "addr:full":"25921 Union Tpke Glen Oaks NY 11004",
    "addr:housenumber":"25921",
    "addr:postcode":"11004",
    "addr:street":"Union Tpke",
    "iso:country":"US",
    "sg:address":"25921 Union Tpke",
    "sg:city":"Glen Oaks",
    "sg:classifiers":[
        {
            "category":"Restaurant",
            "type":"Food & Drink"
        }
    ],
    "sg:phone":"+1 718 962 1220",
    "sg:postcode":"11004",
    "sg:province":"NY",
    "sg:tags":[
        "pizza"
    ],
    "wof:name":"Marcella's Pizzeria Restaurant",
    "wof:placetype":"venue"
},
  "geometry": {"coordinates":[-73.71260100000001,40.746899],"type":"Point"}
}