{
  "type": "Feature",
  "properties": {
    "iso:country":"US",
    "sg:address":"523 5th Ave",
    "sg:city":"Pelham",
    "sg:classifiers":[
        {
            "category":"Local Transit",
            "type":"Transportation"
        }
    ],
    "sg:phone":"+1 914 738 6636",
    "sg:postcode":"10803",
    "sg:province":"NY",
    "sg:tags":[
        "limousine"
    ],
    "wof:name":"Nicholas Limousine Svc",
    "wof:placetype":"venue"
},
  "geometry": {"coordinates":[-73.80517,40.919537],"type":"Point"}
}