{
  "type": "Feature",
  "properties": {
    "iso:country":"US",
    "sg:address":"2417 3rd Ave",
    "sg:city":"Bronx",
    "sg:classifiers":[
        {
            "category":"Professional",
            "type":"Services"
        }
    ],
    "sg:phone":"+1 718 718 6651",
    "sg:postcode":"10451",
    "sg:province":"NY",
    "sg:tags":[
        "establishment"
    ],
    "wof:name":"DMBJ Productions",
    "wof:placetype":"venue"
},
  "geometry": {"coordinates":[-73.93123799999999,40.808178],"type":"Point"}
}