{
  "type": "Feature",
  "properties": {
    "addr:full":"345 Rte 25A Miller Place NY 11764",
    "addr:housenumber":"345",
    "addr:postcode":"11764",
    "addr:street":"Rte 25A",
    "iso:country":"US",
    "sg:address":"345 Rte 25A",
    "sg:city":"Miller Place",
    "sg:classifiers":[
        {
            "category":"Shopping",
            "type":"Retail Goods"
        }
    ],
    "sg:phone":"+1 631 928 5898",
    "sg:postcode":"11764",
    "sg:province":"NY",
    "sg:tags":[
        "product",
        "merchandise",
        "animal",
        "mfg"
    ],
    "wof:name":"Dee Jos More Than Pet Sups Ltd",
    "wof:placetype":"venue"
},
  "geometry": {"coordinates":[-72.993441,40.941161],"type":"Point"}
}