{
  "type": "Feature",
  "properties": {
    "iso:country":"US",
    "sg:address":"169 Port Richmond Ave",
    "sg:city":"Staten Island",
    "sg:classifiers":[
        {
            "category":"Banks & Credit Unions",
            "subcategory":"Bank",
            "type":"Services"
        }
    ],
    "sg:phone":"+1 718 442 5375",
    "sg:postcode":"10302",
    "sg:province":"NY",
    "sg:tags":[
        "money",
        "transfer"
    ],
    "wof:name":"Western Union",
    "wof:placetype":"venue"
},
  "geometry": {"coordinates":[-74.133752,40.637456],"type":"Point"}
}