{
  "type": "Feature",
  "properties": {
    "iso:country":"US",
    "sg:address":"67 N Broadway",
    "sg:city":"Hicksville",
    "sg:classifiers":[
        {
            "category":"Autos & Motor Vehicles",
            "subcategory":"Motorcycle Sales",
            "type":"Retail Goods"
        }
    ],
    "sg:phone":"+1   ",
    "sg:postcode":"11801",
    "sg:province":"NY",
    "sg:tags":[
        "personal",
        "power",
        "boat"
    ],
    "sg:website":"www.likawasaki.com",
    "wof:name":"Long Island Kawasaki-Yamaha",
    "wof:placetype":"venue"
},
  "geometry": {"coordinates":[-73.531719,40.781411],"type":"Point"}
}