{
  "type": "Feature",
  "properties": {
    "addr:full":"68 Sentinel Rd Lake Placid NY 12946",
    "addr:housenumber":"68",
    "addr:postcode":"12946",
    "addr:street":"Sentinel Rd",
    "iso:country":"US",
    "sg:address":"68 Sentinel Rd",
    "sg:city":"Lake Placid",
    "sg:classifiers":[
        {
            "category":"Food & Beverages",
            "subcategory":"Specialty",
            "type":"Retail Goods"
        }
    ],
    "sg:phone":"+1 518 523 4676",
    "sg:postcode":"12946",
    "sg:province":"NY",
    "sg:tags":[
        "health",
        "diet"
    ],
    "wof:name":"Bean's Goods",
    "wof:placetype":"venue"
},
  "geometry": {"coordinates":[-73.98119199999999,44.276379],"type":"Point"}
}