{
  "type": "Feature",
  "properties": {
    "iso:country":"US",
    "sg:address":"207 Durbin Rd",
    "sg:city":"Hannibal",
    "sg:classifiers":[
        {
            "category":"Building & Trades",
            "subcategory":"Construction",
            "type":"Services"
        }
    ],
    "sg:phone":"+1 315 564 5525",
    "sg:postcode":"13074",
    "sg:province":"NY",
    "sg:tags":[
        "contractor"
    ],
    "wof:name":"Stanley Carter Drywall",
    "wof:placetype":"venue"
},
  "geometry": {"coordinates":[-76.59686499999999,43.301111],"type":"Point"}
}