{
  "type": "Feature",
  "properties": {
    "addr:full":"157 W Main St Victor NY 14564",
    "addr:housenumber":"157",
    "addr:postcode":"14564",
    "addr:street":"W Main St",
    "iso:country":"US",
    "sg:address":"157 W Main St",
    "sg:city":"Victor",
    "sg:classifiers":[
        {
            "category":"Wholesale",
            "subcategory":"Durable Goods & Equipment",
            "type":"Manufacturing & Wholesale Goods"
        },
        {
            "category":"Wholesale",
            "subcategory":"Chemicals & Plastics",
            "type":"Manufacturing & Wholesale Goods"
        }
    ],
    "sg:phone":"+1 585 924 9230",
    "sg:postcode":"14564",
    "sg:province":"NY",
    "sg:tags":[
        "supply",
        "janitorial",
        "representative",
        "manufacturer"
    ],
    "wof:name":"Norsen Sales & Marketing Inc",
    "wof:placetype":"venue"
},
  "geometry": {"coordinates":[-77.413687,42.984411],"type":"Point"}
}