{
  "type": "Feature",
  "properties": {
    "addr:full":"63 Surrey Cir Shirley NY 11967",
    "addr:housenumber":"63",
    "addr:postcode":"11967",
    "addr:street":"Surrey Cir",
    "iso:country":"US",
    "sg:address":"63 Surrey Cir",
    "sg:city":"Shirley",
    "sg:classifiers":[
        {
            "category":"Recreation",
            "type":"Entertainment"
        }
    ],
    "sg:phone":"+1 631 395 0358",
    "sg:postcode":"11967",
    "sg:province":"NY",
    "sg:tags":[
        "martial",
        "arts",
        "instruction"
    ],
    "wof:name":"Kempo Take KWON Do Martial",
    "wof:placetype":"venue"
},
  "geometry": {"coordinates":[-72.864868,40.79723],"type":"Point"}
}