{
  "type": "Feature",
  "properties": {
    "addr:full":"422 W 34th St New York NY 10001",
    "addr:housenumber":"422",
    "addr:postcode":"10001",
    "addr:street":"W 34Th St",
    "iso:country":"US",
    "sg:address":"422 W 34th St",
    "sg:city":"New York",
    "sg:classifiers":[
        {
            "category":"Professional",
            "type":"Services"
        }
    ],
    "sg:phone":"+1 212 643 2390",
    "sg:postcode":"10001",
    "sg:province":"NY",
    "sg:tags":[
        "establishment"
    ],
    "wof:name":"433 W 34 St Owners Corp",
    "wof:placetype":"venue"
},
  "geometry": {"coordinates":[-73.99680600000001,40.753406],"type":"Point"}
}