{
  "type": "Feature",
  "properties": {
    "iso:country":"US",
    "sg:address":"4440 Stephanie Dr",
    "sg:city":"Manlius",
    "sg:classifiers":[
        {
            "category":"Wholesale",
            "subcategory":"Durable Goods & Equipment",
            "type":"Manufacturing & Wholesale Goods"
        }
    ],
    "sg:phone":"+1 315 682 6055",
    "sg:postcode":"13104",
    "sg:province":"NY",
    "sg:tags":[
        "representative",
        "manufacturer"
    ],
    "sg:website":"www.esarep.com",
    "wof:name":"Empire State Assoc",
    "wof:placetype":"venue"
},
  "geometry": {"coordinates":[-75.930159,42.987564],"type":"Point"}
}