{
  "type": "Feature",
  "properties": {
    "addr:full":"306 E 178th St Bronx NY 10457",
    "addr:housenumber":"306",
    "addr:postcode":"10457",
    "addr:street":"E 178Th St",
    "iso:country":"US",
    "sg:address":"306 E 178th St",
    "sg:city":"Bronx",
    "sg:classifiers":[
        {
            "category":"Wholesale",
            "subcategory":"Groceries",
            "type":"Manufacturing & Wholesale Goods"
        }
    ],
    "sg:phone":"+1 718 299 6449",
    "sg:postcode":"10457",
    "sg:province":"NY",
    "sg:tags":[
        "grocer"
    ],
    "wof:name":"D & F Grocery Store",
    "wof:placetype":"venue"
},
  "geometry": {"coordinates":[-73.902496,40.849998],"type":"Point"}
}