{
  "type": "Feature",
  "properties": {
    "iso:country":"US",
    "sg:address":"1836 Hylan Blvd",
    "sg:city":"Staten Island",
    "sg:classifiers":[
        {
            "category":"Restaurant",
            "type":"Food & Drink"
        }
    ],
    "sg:phone":"+1 718 667 3344",
    "sg:postcode":"10305",
    "sg:province":"NY",
    "sg:website":"www.cafemaremonte.com",
    "wof:name":"Maremonte Restaurant",
    "wof:placetype":"venue"
},
  "geometry": {"coordinates":[-74.094396,40.584423],"type":"Point"}
}