{
  "type": "Feature",
  "properties": {
    "addr:full":"3458 Carey Ln Baldwin NY 11510",
    "addr:housenumber":"3458",
    "addr:postcode":"11510",
    "addr:street":"Carey Ln",
    "iso:country":"US",
    "sg:address":"3458 Carey Ln",
    "sg:city":"Baldwin",
    "sg:classifiers":[
        {
            "category":"Home & Garden",
            "subcategory":"Household Appliances",
            "type":"Retail Goods"
        }
    ],
    "sg:phone":"+1 516 483 6095",
    "sg:postcode":"11510",
    "sg:province":"NY",
    "sg:tags":[
        "repair"
    ],
    "wof:name":"Sadona Bros Special Aplliances",
    "wof:placetype":"venue"
},
  "geometry": {"coordinates":[-73.600353,40.625152],"type":"Point"}
}