{
  "type": "Feature",
  "properties": {
    "iso:country":"US",
    "sg:address":"2326 84th St",
    "sg:city":"Brooklyn",
    "sg:classifiers":[
        {
            "category":"Organizations",
            "subcategory":"Religious Organization",
            "type":"Services"
        }
    ],
    "sg:phone":"+1 718 372 3112",
    "sg:postcode":"11214",
    "sg:province":"NY",
    "sg:tags":[
        "clergy"
    ],
    "wof:name":"Raynolds Basilious",
    "wof:placetype":"venue"
},
  "geometry": {"coordinates":[-73.988676,40.600706],"type":"Point"}
}