{
  "type": "Feature",
  "properties": {
    "iso:country":"US",
    "sg:address":"143 Remsen St",
    "sg:city":"Cohoes",
    "sg:classifiers":[
        {
            "category":"Personal",
            "subcategory":"Barber",
            "type":"Services"
        }
    ],
    "sg:phone":"+1 518 233 0685",
    "sg:postcode":"12047",
    "sg:province":"NY",
    "wof:name":"Tony Horan's Barber Shop",
    "wof:placetype":"venue"
},
  "geometry": {"coordinates":[-73.70102799999999,42.773502],"type":"Point"}
}