{
  "type": "Feature",
  "properties": {
    "addr:full":"16 Avenue W Brooklyn NY 11223",
    "addr:housenumber":"16",
    "addr:postcode":"11223",
    "addr:street":"Avenue W",
    "iso:country":"US",
    "sg:address":"16 Avenue W",
    "sg:city":"Brooklyn",
    "sg:classifiers":[
        {
            "category":"Insurance",
            "subcategory":"Health Insurance",
            "type":"Services"
        }
    ],
    "sg:phone":"+1 718 853 5921",
    "sg:postcode":"11223",
    "sg:province":"NY",
    "sg:tags":[
        "market"
    ],
    "wof:name":"Natural Spot",
    "wof:placetype":"venue"
},
  "geometry": {"coordinates":[-73.985422,40.631418],"type":"Point"}
}