{
  "type": "Feature",
  "properties": {
    "addr:full":"936 Garnsey Rd Palmyra NY 14522",
    "addr:housenumber":"936",
    "addr:postcode":"14522",
    "addr:street":"Garnsey Rd",
    "iso:country":"US",
    "sg:address":"936 Garnsey Rd",
    "sg:city":"Palmyra",
    "sg:classifiers":[
        {
            "category":"Wholesale",
            "subcategory":"Motor Vehicles",
            "type":"Manufacturing & Wholesale Goods"
        }
    ],
    "sg:phone":"+1 315 597 6899",
    "sg:postcode":"14522",
    "sg:province":"NY",
    "sg:tags":[
        "body",
        "auto"
    ],
    "wof:name":"Chriss Sales & Service",
    "wof:placetype":"venue"
},
  "geometry": {"coordinates":[-77.17972399999999,43.045859],"type":"Point"}
}