{
  "type": "Feature",
  "properties": {
    "addr:full":"183 Owasco Rd Auburn NY 13021",
    "addr:housenumber":"183",
    "addr:postcode":"13021",
    "addr:street":"Owasco Rd",
    "iso:country":"US",
    "sg:address":"183 Owasco Rd",
    "sg:city":"Auburn",
    "sg:classifiers":[
        {
            "category":"Organizations",
            "subcategory":"Religious Organization",
            "type":"Services"
        }
    ],
    "sg:phone":"+1 315 258 7377",
    "sg:postcode":"13021",
    "sg:province":"NY",
    "sg:tags":[
        "reach",
        "ministry"
    ],
    "wof:name":"Ministries Faith Hope & Love",
    "wof:placetype":"venue"
},
  "geometry": {"coordinates":[-76.547591,42.92349],"type":"Point"}
}