{
  "type": "Feature",
  "properties": {
    "addr:full":"1669 Sheepshead Bay Rd Brooklyn NY 11235",
    "addr:housenumber":"1669",
    "addr:postcode":"11235",
    "addr:street":"Sheepshead Bay Rd",
    "iso:country":"US",
    "sg:address":"1669 Sheepshead Bay Rd",
    "sg:city":"Brooklyn",
    "sg:classifiers":[
        {
            "category":"Shopping",
            "subcategory":"Shoes",
            "type":"Retail Goods"
        }
    ],
    "sg:phone":"+1 718 646 1808",
    "sg:postcode":"11235",
    "sg:province":"NY",
    "sg:tags":[
        "store"
    ],
    "sg:website":"www.minicentroshoes.com/",
    "wof:name":"Mini Centro",
    "wof:placetype":"venue"
},
  "geometry": {"coordinates":[-73.95193399999999,40.586019],"type":"Point"}
}