{
  "type": "Feature",
  "properties": {
    "addr:full":"319 Taughannock Blvd Ithaca NY 14850",
    "addr:housenumber":"319",
    "addr:postcode":"14850",
    "addr:street":"Taughannock Blvd",
    "iso:country":"US",
    "sg:address":"319 Taughannock Blvd",
    "sg:city":"Ithaca",
    "sg:classifiers":[
        {
            "category":"Bars & Pubs",
            "type":"Food & Drink"
        }
    ],
    "sg:phone":"+1   ",
    "sg:postcode":"14850",
    "sg:province":"NY",
    "sg:tags":[
        "cafe",
        "bar"
    ],
    "wof:name":"Kellys Dockside Kafe",
    "wof:placetype":"venue"
},
  "geometry": {"coordinates":[-76.51244,42.442094],"type":"Point"}
}