{
  "type": "Feature",
  "properties": {
    "addr:full":"1137 Garden Ave Niagara Falls NY 14305",
    "addr:housenumber":"1137",
    "addr:postcode":"14305",
    "addr:street":"Garden Ave",
    "iso:country":"US",
    "sg:address":"1137 Garden Ave",
    "sg:city":"Niagara Falls",
    "sg:classifiers":[
        {
            "category":"Organizations",
            "subcategory":"Religious Organization",
            "type":"Services"
        }
    ],
    "sg:phone":"+1 716 284 9892",
    "sg:postcode":"14305",
    "sg:province":"NY",
    "sg:tags":[
        "clergy"
    ],
    "wof:name":"William E Feagin",
    "wof:placetype":"venue"
},
  "geometry": {"coordinates":[-79.046708,43.113334],"type":"Point"}
}