{
  "type": "Feature",
  "properties": {
    "addr:full":"616 Buffalo St Jamestown NY 14701",
    "addr:housenumber":"616",
    "addr:postcode":"14701",
    "addr:street":"Buffalo St",
    "iso:country":"US",
    "sg:address":"616 Buffalo St",
    "sg:city":"Jamestown",
    "sg:classifiers":[
        {
            "category":"Manufacturing",
            "subcategory":"Metals",
            "type":"Manufacturing & Wholesale Goods"
        }
    ],
    "sg:phone":"+1 716 665 5243",
    "sg:postcode":"14701",
    "sg:province":"NY",
    "sg:tags":[
        "production",
        "grinding"
    ],
    "sg:website":"www.mastergrindedm.com",
    "wof:name":"MASTERGRIND/Edm",
    "wof:placetype":"venue"
},
  "geometry": {"coordinates":[-79.215267,42.106748],"type":"Point"}
}