{
  "type": "Feature",
  "properties": {
    "iso:country":"US",
    "sg:address":"13677 Main Rd",
    "sg:city":"Akron",
    "sg:classifiers":[
        {
            "category":"Retail",
            "subcategory":"Auto Repair",
            "type":"Services"
        }
    ],
    "sg:phone":"+1 716 542 2643",
    "sg:postcode":"14001",
    "sg:province":"NY",
    "sg:tags":[
        "automobile",
        "inspection"
    ],
    "wof:name":"Dick Walser Svc Inc",
    "wof:placetype":"venue"
},
  "geometry": {"coordinates":[-78.463544,42.997955],"type":"Point"}
}