{
  "type": "Feature",
  "properties": {
    "iso:country":"US",
    "sg:address":"26 Circle Ave",
    "sg:city":"North Creek",
    "sg:classifiers":[
        {
            "category":"Government",
            "subcategory":"Post Office",
            "type":"Public Place"
        }
    ],
    "sg:phone":"+1 518 251 2121",
    "sg:postcode":"12853",
    "sg:province":"NY",
    "wof:name":"US Post Office",
    "wof:placetype":"venue"
},
  "geometry": {"coordinates":[-73.98401200000001,43.698657],"type":"Point"}
}