{
  "type": "Feature",
  "properties": {
    "addr:full":"12211 Hillside Ave Richmond Hill NY 11418",
    "addr:housenumber":"12211",
    "addr:postcode":"11418",
    "addr:street":"Hillside Ave",
    "iso:country":"US",
    "sg:address":"12211 Hillside Ave",
    "sg:city":"Richmond Hill",
    "sg:classifiers":[
        {
            "category":"Autos & Motor Vehicles",
            "subcategory":"Automobile Sales",
            "type":"Retail Goods"
        }
    ],
    "sg:phone":"+1 718 896 6666",
    "sg:postcode":"11418",
    "sg:province":"NY",
    "sg:tags":[
        "limo"
    ],
    "wof:name":"Boulevard Private Car Svce Inc",
    "wof:placetype":"venue"
},
  "geometry": {"coordinates":[-73.82820100000001,40.702301],"type":"Point"}
}