{
  "type": "Feature",
  "properties": {
    "iso:country":"US",
    "sg:address":"301 Factory Ave",
    "sg:city":"Syracuse",
    "sg:classifiers":[
        {
            "category":"Retail",
            "subcategory":"Auto Repair",
            "type":"Services"
        }
    ],
    "sg:phone":"+1 315 454 3114",
    "sg:postcode":"13208",
    "sg:province":"NY",
    "sg:tags":[
        "body",
        "automobile",
        "painting"
    ],
    "wof:name":"Donofrio's Body & Paint Shop",
    "wof:placetype":"venue"
},
  "geometry": {"coordinates":[-76.139949,43.0905],"type":"Point"}
}