{
  "type": "Feature",
  "properties": {
    "iso:country":"US",
    "sg:address":"406 Mendon Center Rd",
    "sg:city":"Pittsford",
    "sg:classifiers":[
        {
            "category":"Professional",
            "subcategory":"Lawyer & Legal Services",
            "type":"Services"
        }
    ],
    "sg:phone":"+1 585 586 0635",
    "sg:postcode":"14534",
    "sg:province":"NY",
    "sg:tags":[
        "attorney"
    ],
    "wof:name":"Cathy J Bardenstein",
    "wof:placetype":"venue"
},
  "geometry": {"coordinates":[-77.535273,43.052539],"type":"Point"}
}