{
  "type": "Feature",
  "properties": {
    "addr:full":"3904 Laurel Avenue Brooklyn NY 11224",
    "addr:housenumber":"3904",
    "addr:postcode":"11224",
    "addr:street":"Laurel Avenue",
    "iso:country":"US",
    "sg:address":"3904 Laurel Avenue",
    "sg:city":"Brooklyn",
    "sg:classifiers":[
        {
            "category":"Organizations",
            "subcategory":"Religious Organization",
            "type":"Services"
        }
    ],
    "sg:phone":"+1 718 372 9897",
    "sg:postcode":"11224",
    "sg:province":"NY",
    "wof:name":"Unbroken Chain Fellowship",
    "wof:placetype":"venue"
},
  "geometry": {"coordinates":[-74.00843999999999,40.577822],"type":"Point"}
}