{
  "type": "Feature",
  "properties": {
    "addr:full":"956 51st St Brooklyn NY 11219",
    "addr:housenumber":"956",
    "addr:postcode":"11219",
    "addr:street":"51St St",
    "iso:country":"US",
    "sg:address":"956 51st St",
    "sg:city":"Brooklyn",
    "sg:classifiers":[
        {
            "category":"Utilities",
            "subcategory":"Mobile Phone",
            "type":"Services"
        }
    ],
    "sg:phone":"+1 718 853 9088",
    "sg:postcode":"11219",
    "sg:province":"NY",
    "sg:tags":[
        "telephone",
        "cellular"
    ],
    "wof:name":"World Of Accessories",
    "wof:placetype":"venue"
},
  "geometry": {"coordinates":[-74.00089,40.638596],"type":"Point"}
}