{
  "type": "Feature",
  "properties": {
    "iso:country":"US",
    "sg:address":"28-43 Steinway St",
    "sg:city":"Astoria",
    "sg:classifiers":[
        {
            "category":"Restaurant",
            "type":"Food & Drink"
        }
    ],
    "sg:phone":"+1 718 721 8181",
    "sg:postcode":"11103",
    "sg:province":"NY",
    "sg:tags":[
        "american",
        "latin"
    ],
    "sg:website":"thezonesportslounge.com/",
    "wof:name":"The ZONE - La Zona Cibaena",
    "wof:placetype":"venue"
},
  "geometry": {"coordinates":[-73.91396400000001,40.769985],"type":"Point"}
}