{
  "type": "Feature",
  "properties": {
    "iso:country":"US",
    "sg:address":"341 Columbus Ave",
    "sg:city":"New York",
    "sg:classifiers":[
        {
            "category":"Shopping",
            "subcategory":"Clothing, Apparel, & Fashions",
            "type":"Retail Goods"
        }
    ],
    "sg:phone":"+1 212 362 3000",
    "sg:postcode":"10024",
    "sg:province":"NY",
    "sg:tags":[
        "sport",
        "wear",
        "sportswear"
    ],
    "wof:name":"Eileen Fisher Boutique",
    "wof:placetype":"venue"
},
  "geometry": {"coordinates":[-73.976799,40.780399],"type":"Point"}
}