{
  "type": "Feature",
  "properties": {
    "addr:full":"700 E 241st St Bronx NY 10470",
    "addr:housenumber":"700",
    "addr:postcode":"10470",
    "addr:street":"E 241St St",
    "iso:country":"US",
    "sg:address":"700 E 241st St",
    "sg:city":"Bronx",
    "sg:classifiers":[
        {
            "category":"Autos & Motor Vehicles",
            "subcategory":"Fuel & Gas Station",
            "type":"Retail Goods"
        }
    ],
    "sg:phone":"+1 718 882 6800",
    "sg:postcode":"10470",
    "sg:province":"NY",
    "sg:tags":[
        "oil"
    ],
    "wof:name":"KAT Petroleum Inc",
    "wof:placetype":"venue"
},
  "geometry": {"coordinates":[-73.850105,40.90329],"type":"Point"}
}