{
  "type": "Feature",
  "properties": {
    "addr:full":"2182 Ridgeway Ave Rochester NY 14626",
    "addr:housenumber":"2182",
    "addr:postcode":"14626",
    "addr:street":"Ridgeway Ave",
    "iso:country":"US",
    "sg:address":"2182 Ridgeway Ave",
    "sg:city":"Rochester",
    "sg:classifiers":[
        {
            "category":"Health Services",
            "subcategory":"Nursing And Care Facility",
            "type":"Services"
        }
    ],
    "sg:phone":"+1 585 723 8120",
    "sg:postcode":"14626",
    "sg:province":"NY",
    "wof:name":"Heritage Christian Services",
    "wof:placetype":"venue"
},
  "geometry": {"coordinates":[-77.699679,43.187526],"type":"Point"}
}