{
  "type": "Feature",
  "properties": {
    "iso:country":"US",
    "sg:address":"1880 Rochester Rd",
    "sg:city":"Canandaigua",
    "sg:classifiers":[
        {
            "category":"Shopping",
            "subcategory":"Florist",
            "type":"Retail Goods"
        }
    ],
    "sg:phone":"+1 585 394 1830",
    "sg:postcode":"14425",
    "sg:province":"NY",
    "sg:tags":[
        "plant",
        "flower"
    ],
    "sg:website":"www.flowersbystella.com",
    "wof:name":"Flowers By Stella Inc",
    "wof:placetype":"venue"
},
  "geometry": {"coordinates":[-77.32747500000001,42.93902],"type":"Point"}
}