{
  "type": "Feature",
  "properties": {
    "iso:country":"US",
    "sg:address":"242 E 72nd St",
    "sg:city":"New York",
    "sg:classifiers":[
        {
            "category":"Real Estate",
            "subcategory":"Real Estate Services",
            "type":"Services"
        }
    ],
    "sg:phone":"+1 212 873 1100",
    "sg:postcode":"10021",
    "sg:province":"NY",
    "wof:name":"Goodman I Michael Real Estate",
    "wof:placetype":"venue"
},
  "geometry": {"coordinates":[-73.95970199999999,40.769299],"type":"Point"}
}