{
  "type": "Feature",
  "properties": {
    "iso:country":"US",
    "sg:address":"49 Ann St",
    "sg:city":"New York",
    "sg:classifiers":[
        {
            "category":"Manufacturing",
            "subcategory":"Printing",
            "type":"Manufacturing & Wholesale Goods"
        }
    ],
    "sg:phone":"+1   ",
    "sg:postcode":"10038",
    "sg:province":"NY",
    "sg:tags":[
        "lithographic",
        "commercial"
    ],
    "wof:name":"South Bridge Press Inc",
    "wof:placetype":"venue"
},
  "geometry": {"coordinates":[-74.006427,40.710232],"type":"Point"}
}