{
  "type": "Feature",
  "properties": {
    "iso:country":"US",
    "sg:address":"1620 Wayneport Rd",
    "sg:city":"Macedon",
    "sg:classifiers":[
        {
            "category":"Building & Trades",
            "subcategory":"Construction",
            "type":"Services"
        }
    ],
    "sg:phone":"+1 585 292 0160",
    "sg:postcode":"14502",
    "sg:province":"NY",
    "sg:tags":[
        "general",
        "contractor"
    ],
    "sg:website":"www.toomeysconstruction.com",
    "wof:name":"Toomeys Construction Co LTD",
    "wof:placetype":"venue"
},
  "geometry": {"coordinates":[-77.360956,43.064875],"type":"Point"}
}