{
  "type": "Feature",
  "properties": {
    "iso:country":"US",
    "sg:address":"214 Ferndale Dr",
    "sg:city":"Syracuse",
    "sg:classifiers":[
        {
            "category":"Building & Trades",
            "subcategory":"Cleaning & Sanitation",
            "type":"Services"
        }
    ],
    "sg:phone":"+1 315 378 0170",
    "sg:postcode":"13205",
    "sg:province":"NY",
    "sg:tags":[
        "commercial"
    ],
    "wof:name":"Cleaning Service Engineers",
    "wof:placetype":"venue"
},
  "geometry": {"coordinates":[-76.14589100000001,43.003298],"type":"Point"}
}