{
  "type": "Feature",
  "properties": {
    "iso:country":"US",
    "sg:address":"129 N Broadway",
    "sg:city":"Hicksville",
    "sg:classifiers":[
        {
            "category":"Restaurant",
            "type":"Food & Drink"
        }
    ],
    "sg:phone":"+1 516 933 8999",
    "sg:postcode":"11801",
    "sg:province":"NY",
    "sg:tags":[
        "afghan"
    ],
    "wof:name":"Kabul Grill",
    "wof:placetype":"venue"
},
  "geometry": {"coordinates":[-73.527289,40.772437],"type":"Point"}
}