{
  "type": "Feature",
  "properties": {
    "addr:full":"3 S Village Ave Rockville Centre NY 11570",
    "addr:housenumber":"3",
    "addr:postcode":"11570",
    "addr:street":"S Village Ave",
    "iso:country":"US",
    "sg:address":"3 S Village Ave",
    "sg:city":"Rockville Centre",
    "sg:classifiers":[
        {
            "category":"Shopping",
            "subcategory":"Florist",
            "type":"Retail Goods"
        }
    ],
    "sg:phone":"+1 800 647 5480",
    "sg:postcode":"11570",
    "sg:province":"NY",
    "wof:name":"Miss Daisy Flower Shop",
    "wof:placetype":"venue"
},
  "geometry": {"coordinates":[-73.64803499999999,40.655452],"type":"Point"}
}