{
  "type": "Feature",
  "properties": {
    "iso:country":"US",
    "sg:address":"225 Broad Hollow Rd",
    "sg:city":"Melville",
    "sg:classifiers":[
        {
            "category":"Banks & Credit Unions",
            "subcategory":"Bank",
            "type":"Services"
        }
    ],
    "sg:phone":"+1 631 845 4900",
    "sg:postcode":"11747",
    "sg:province":"NY",
    "sg:tags":[
        "mortgage",
        "loan",
        "banker",
        "real estate"
    ],
    "wof:name":"American Century Mortgage Ban",
    "wof:placetype":"venue"
},
  "geometry": {"coordinates":[-73.42325,40.762874],"type":"Point"}
}