{
  "type": "Feature",
  "properties": {
    "iso:country":"US",
    "sg:address":"4162 Union Rd",
    "sg:city":"Cheektowaga",
    "sg:classifiers":[
        {
            "category":"Personal",
            "subcategory":"Beauty Salon",
            "type":"Services"
        }
    ],
    "sg:phone":"+1 716 626 4442",
    "sg:postcode":"14225",
    "sg:province":"NY",
    "sg:tags":[
        "manicuring"
    ],
    "wof:name":"Nail Time Airport Plaza",
    "wof:placetype":"venue"
},
  "geometry": {"coordinates":[-78.754209,42.928559],"type":"Point"}
}