{
  "type": "Feature",
  "properties": {
    "iso:country":"US",
    "sg:address":"101 McClean Ave",
    "sg:city":"Staten Island",
    "sg:classifiers":[
        {
            "category":"Food & Beverages",
            "subcategory":"Meat & Fish",
            "type":"Retail Goods"
        }
    ],
    "sg:phone":"+1 718 981 6060",
    "sg:postcode":"10305",
    "sg:province":"NY",
    "sg:tags":[
        "shop"
    ],
    "wof:name":"Arrochar Superette Inc",
    "wof:placetype":"venue"
},
  "geometry": {"coordinates":[-74.06529999999999,40.598301],"type":"Point"}
}