{
  "type": "Feature",
  "properties": {
    "addr:full":"2590 Ridgeway Ave Rochester NY 14626",
    "addr:housenumber":"2590",
    "addr:postcode":"14626",
    "addr:street":"Ridgeway Ave",
    "iso:country":"US",
    "sg:address":"2590 Ridgeway Ave",
    "sg:city":"Rochester",
    "sg:classifiers":[
        {
            "category":"Coffee & Tea",
            "type":"Food & Drink"
        }
    ],
    "sg:menulink":"http://www.allmenus.com/ny/rochester/113304-starbucks-coffee/menu/",
    "sg:phone":"+1 585 723 6050",
    "sg:postcode":"14626",
    "sg:province":"NY",
    "sg:tags":[
        "american"
    ],
    "wof:name":"Starbucks Coffee",
    "wof:placetype":"venue"
},
  "geometry": {"coordinates":[-77.701013,43.187825],"type":"Point"}
}