{
  "type": "Feature",
  "properties": {
    "iso:country":"US",
    "sg:address":"7017 Bay Parkway",
    "sg:city":"Brooklyn",
    "sg:classifiers":[
        {
            "category":"Retail",
            "subcategory":"Car Wash",
            "type":"Services"
        }
    ],
    "sg:phone":"+1 718 234 1606",
    "sg:postcode":"11204",
    "sg:province":"NY",
    "wof:name":"Super Clean Car Wash",
    "wof:placetype":"venue"
},
  "geometry": {"coordinates":[-73.98441,40.610801],"type":"Point"}
}