{
  "type": "Feature",
  "properties": {
    "addr:full":"271 Neptune Ave Brooklyn NY 11235",
    "addr:housenumber":"271",
    "addr:postcode":"11235",
    "addr:street":"Neptune Ave",
    "iso:country":"US",
    "sg:address":"271 Neptune Ave",
    "sg:city":"Brooklyn",
    "sg:classifiers":[
        {
            "category":"Restaurant",
            "type":"Food & Drink"
        }
    ],
    "sg:menulink":"http://www.allmenus.com/ny/brooklyn/63099-new-china/menu/",
    "sg:phone":"+1 718 769 7429",
    "sg:postcode":"11235",
    "sg:province":"NY",
    "sg:tags":[
        "asian",
        "chinese"
    ],
    "wof:name":"New China",
    "wof:placetype":"venue"
},
  "geometry": {"coordinates":[-73.963415,40.581195],"type":"Point"}
}