{
  "type": "Feature",
  "properties": {
    "addr:full":"55 Old Shipyard Ln Southold NY 11971",
    "addr:housenumber":"55",
    "addr:postcode":"11971",
    "addr:street":"Old Shipyard Ln",
    "iso:country":"US",
    "sg:address":"55 Old Shipyard Ln",
    "sg:city":"Southold",
    "sg:classifiers":[
        {
            "category":"Marine",
            "type":"Transportation"
        }
    ],
    "sg:phone":"+1   ",
    "sg:postcode":"11971",
    "sg:province":"NY",
    "sg:tags":[
        "water",
        "transport"
    ],
    "wof:name":"Maverick Fly",
    "wof:placetype":"venue"
},
  "geometry": {"coordinates":[-72.41633299999999,41.063742],"type":"Point"}
}