{
  "type": "Feature",
  "properties": {
    "iso:country":"US",
    "sg:address":"3 Commercial Ave",
    "sg:city":"Garden City",
    "sg:classifiers":[
        {
            "category":"Real Estate",
            "subcategory":"Real Estate Operator",
            "type":"Services"
        }
    ],
    "sg:phone":"+1 516 741 8048",
    "sg:postcode":"11530",
    "sg:province":"NY",
    "sg:tags":[
        "company",
        "holding"
    ],
    "wof:name":"Bdsr Corporation",
    "wof:placetype":"venue"
},
  "geometry": {"coordinates":[-73.618082,40.727714],"type":"Point"}
}