{
  "type": "Feature",
  "properties": {
    "iso:country":"US",
    "sg:address":"6605 Bay Parkway",
    "sg:city":"Brooklyn",
    "sg:classifiers":[
        {
            "category":"Shopping",
            "subcategory":"Pharmacy",
            "type":"Retail Goods"
        }
    ],
    "sg:phone":"+1 718 232 0810",
    "sg:postcode":"11204",
    "sg:province":"NY",
    "sg:tags":[
        "drugstore"
    ],
    "wof:name":"Health Plus Pharmacy Corporation",
    "wof:placetype":"venue"
},
  "geometry": {"coordinates":[-73.982247,40.613211],"type":"Point"}
}