{
  "type": "Feature",
  "properties": {
    "addr:full":"2171 2nd Ave between 111th St and 112th St New York NY 10079",
    "addr:housenumber":"2171",
    "addr:postcode":"10079",
    "addr:street":"2Nd Ave Between 111Th St And 112Th St",
    "iso:country":"US",
    "sg:address":"2171 2nd Ave between 111th St and 112th St",
    "sg:city":"New York",
    "sg:classifiers":[
        {
            "category":"Bars & Pubs",
            "subcategory":"Lounge",
            "type":"Food & Drink"
        }
    ],
    "sg:postcode":"10079",
    "sg:province":"NY",
    "wof:name":"Dexy's Lounge",
    "wof:placetype":"venue"
},
  "geometry": {"coordinates":[-73.939786,40.79426],"type":"Point"}
}