{
  "type": "Feature",
  "properties": {
    "addr:full":"100 Park Ave Fl 35 New York NY 10017",
    "addr:housenumber":"100;35",
    "addr:postcode":"10017",
    "addr:street":"Park Ave Fl",
    "iso:country":"US",
    "sg:address":"100 Park Ave Fl 35",
    "sg:city":"New York",
    "sg:classifiers":[
        {
            "category":"Banks & Credit Unions",
            "subcategory":"Investment Brokerage",
            "type":"Services"
        }
    ],
    "sg:phone":"+1 212 351 5630",
    "sg:postcode":"10017",
    "sg:province":"NY",
    "sg:tags":[
        "investing"
    ],
    "wof:name":"General American Investors Inc",
    "wof:placetype":"venue"
},
  "geometry": {"coordinates":[-73.978737,40.751019],"type":"Point"}
}