{
  "type": "Feature",
  "properties": {
    "addr:full":"15 Reiter Rd East Aurora NY 14052",
    "addr:housenumber":"15",
    "addr:postcode":"14052",
    "addr:street":"Reiter Rd",
    "iso:country":"US",
    "sg:address":"15 Reiter Rd",
    "sg:city":"East Aurora",
    "sg:classifiers":[
        {
            "category":"Organizations",
            "subcategory":"Non-profit Organization",
            "type":"Services"
        }
    ],
    "sg:phone":"+1 716 655 1335",
    "sg:postcode":"14052",
    "sg:province":"NY",
    "wof:name":"Lothlorien Therapeutic Riding",
    "wof:placetype":"venue"
},
  "geometry": {"coordinates":[-78.577884,42.766349],"type":"Point"}
}