{
  "type": "Feature",
  "properties": {
    "iso:country":"US",
    "sg:address":"234 Warren St",
    "sg:city":"Hudson",
    "sg:classifiers":[
        {
            "category":"Personal",
            "subcategory":"Beauty Salon",
            "type":"Services"
        }
    ],
    "sg:phone":"+1 518 822 9234",
    "sg:postcode":"12534",
    "sg:province":"NY",
    "sg:tags":[
        "hair"
    ],
    "wof:name":"Jim Wach Salon",
    "wof:placetype":"venue"
},
  "geometry": {"coordinates":[-73.791933,42.253849],"type":"Point"}
}