{
  "type": "Feature",
  "properties": {
    "addr:full":"2506 Belmont Ave Bronx NY 10458",
    "addr:housenumber":"2506",
    "addr:postcode":"10458",
    "addr:street":"Belmont Ave",
    "iso:country":"US",
    "sg:address":"2506 Belmont Ave",
    "sg:city":"Bronx",
    "sg:classifiers":[
        {
            "category":"Retail",
            "subcategory":"Event Space",
            "type":"Services"
        }
    ],
    "sg:phone":"+1 347 271 8456",
    "sg:postcode":"10458",
    "sg:province":"NY",
    "sg:tags":[
        "venue"
    ],
    "wof:name":"Ciszek Hall",
    "wof:placetype":"venue"
},
  "geometry": {"coordinates":[-73.883888,40.857336],"type":"Point"}
}