{
  "type": "Feature",
  "properties": {
    "iso:country":"US",
    "sg:address":"415 Ringgold St",
    "sg:city":"Peekskill",
    "sg:classifiers":[
        {
            "category":"Building & Trades",
            "subcategory":"Plumbing",
            "type":"Services"
        }
    ],
    "sg:phone":"+1 914 739 1191",
    "sg:postcode":"10566",
    "sg:province":"NY",
    "sg:tags":[
        "plumbing",
        "contractor"
    ],
    "wof:name":"Olsen Jim Plumbing & Heating",
    "wof:placetype":"venue"
},
  "geometry": {"coordinates":[-73.92362799999999,41.282547],"type":"Point"}
}