{
  "type": "Feature",
  "properties": {
    "iso:country":"US",
    "sg:address":"437 Mamaroneck Ave",
    "sg:city":"Mamaroneck",
    "sg:classifiers":[
        {
            "category":"Shopping",
            "subcategory":"Clothing, Apparel, & Fashions",
            "type":"Retail Goods"
        }
    ],
    "sg:phone":"+1 914 698 3883",
    "sg:postcode":"10543",
    "sg:province":"NY",
    "wof:name":"Marianne's Fashions",
    "wof:placetype":"venue"
},
  "geometry": {"coordinates":[-73.736744,40.952469],"type":"Point"}
}