{
  "type": "Feature",
  "properties": {
    "iso:country":"US",
    "sg:address":"1164 Sprague Rd",
    "sg:city":"Chemung",
    "sg:classifiers":[
        {
            "category":"Retail",
            "subcategory":"Auto Repair",
            "type":"Services"
        }
    ],
    "sg:phone":"+1 607 565 4903",
    "sg:postcode":"14825",
    "sg:province":"NY",
    "sg:tags":[
        "truck"
    ],
    "wof:name":"Lyon Fleet Store",
    "wof:placetype":"venue"
},
  "geometry": {"coordinates":[-76.59580800000001,42.050945],"type":"Point"}
}