{
  "type": "Feature",
  "properties": {
    "addr:full":"10101 37th Ave Corona NY 11368",
    "addr:housenumber":"10101",
    "addr:postcode":"11368",
    "addr:street":"37Th Ave",
    "iso:country":"US",
    "sg:address":"10101 37th Ave",
    "sg:city":"Corona",
    "sg:classifiers":[
        {
            "category":"Restaurant",
            "type":"Food & Drink"
        }
    ],
    "sg:phone":"+1 718 429 5158",
    "sg:postcode":"11368",
    "sg:province":"NY",
    "wof:name":"Antilla's Restaurant",
    "wof:placetype":"venue"
},
  "geometry": {"coordinates":[-73.866203,40.752899],"type":"Point"}
}