{
  "type": "Feature",
  "properties": {
    "iso:country":"US",
    "sg:address":"518 Central St",
    "sg:city":"Endicott",
    "sg:classifiers":[
        {
            "category":"Wholesale",
            "subcategory":"Machinery & Supplies",
            "type":"Manufacturing & Wholesale Goods"
        }
    ],
    "sg:phone":"+1 607 754 8486",
    "sg:postcode":"13760",
    "sg:province":"NY",
    "sg:tags":[
        "rubber",
        "product"
    ],
    "wof:name":"J J Short Assoc Inc",
    "wof:placetype":"venue"
},
  "geometry": {"coordinates":[-76.057374,42.099646],"type":"Point"}
}