{
  "type": "Feature",
  "properties": {
    "addr:full":"421 State Hwy 59 Monsey NY 10952",
    "addr:housenumber":"421",
    "addr:postcode":"10952",
    "addr:street":"State Hwy 59",
    "iso:country":"US",
    "sg:address":"421 State Hwy 59",
    "sg:city":"Monsey",
    "sg:classifiers":[
        {
            "category":"Home & Garden",
            "subcategory":"Building Materials",
            "type":"Retail Goods"
        }
    ],
    "sg:phone":"+1   ",
    "sg:postcode":"10952",
    "sg:province":"NY",
    "sg:tags":[
        "decorative",
        "hardware",
        "bath"
    ],
    "wof:name":"Aarons Decorative Bath & Hdwr",
    "wof:placetype":"venue"
},
  "geometry": {"coordinates":[-74.08602,41.108942],"type":"Point"}
}