{
  "type": "Feature",
  "properties": {
    "iso:country":"US",
    "sg:address":"14 Amelia Dr",
    "sg:city":"Schenectady",
    "sg:classifiers":[
        {
            "category":"Building & Trades",
            "subcategory":"Construction",
            "type":"Services"
        }
    ],
    "sg:phone":"+1 518 869 0220",
    "sg:postcode":"12309",
    "sg:province":"NY",
    "sg:tags":[
        "contractor"
    ],
    "wof:name":"Finecraft Building",
    "wof:placetype":"venue"
},
  "geometry": {"coordinates":[-73.856495,42.765525],"type":"Point"}
}