{
  "type": "Feature",
  "properties": {
    "iso:country":"US",
    "sg:address":"50 N Ferry Rd",
    "sg:city":"Shelter Island",
    "sg:classifiers":[
        {
            "category":"Professional",
            "type":"Services"
        }
    ],
    "sg:phone":"+1 631 749 1874",
    "sg:postcode":"11964",
    "sg:province":"NY",
    "sg:tags":[
        "establishment"
    ],
    "wof:name":"C & C Enterprises LTD",
    "wof:placetype":"venue"
},
  "geometry": {"coordinates":[-72.339196,41.071256],"type":"Point"}
}