{
  "type": "Feature",
  "properties": {
    "addr:full":"275 W Hoffman Ave Lindenhurst NY 11757",
    "addr:housenumber":"275",
    "addr:postcode":"11757",
    "addr:street":"W Hoffman Ave",
    "iso:country":"US",
    "sg:address":"275 W Hoffman Ave",
    "sg:city":"Lindenhurst",
    "sg:classifiers":[
        {
            "category":"Manufacturing",
            "subcategory":"Tools & Machinery",
            "type":"Manufacturing & Wholesale Goods"
        }
    ],
    "sg:phone":"+1   ",
    "sg:postcode":"11757",
    "sg:province":"NY",
    "sg:tags":[
        "parts",
        "assembly",
        "manufacturer"
    ],
    "wof:name":"Koflers Tool and Die Inc",
    "wof:placetype":"venue"
},
  "geometry": {"coordinates":[-73.381901,40.684306],"type":"Point"}
}