{
  "type": "Feature",
  "properties": {
    "addr:full":"112 Olean St East Aurora NY 14052",
    "addr:housenumber":"112",
    "addr:postcode":"14052",
    "addr:street":"Olean St",
    "iso:country":"US",
    "sg:address":"112 Olean St",
    "sg:city":"East Aurora",
    "sg:classifiers":[
        {
            "category":"Health Services",
            "subcategory":"Doctor",
            "type":"Services"
        }
    ],
    "sg:phone":"+1 716 805 1072",
    "sg:postcode":"14052",
    "sg:province":"NY",
    "sg:tags":[
        "physician",
        "surgeon"
    ],
    "wof:name":"Shawn Cotton MD",
    "wof:placetype":"venue"
},
  "geometry": {"coordinates":[-78.60788700000001,42.763665],"type":"Point"}
}