{
  "type": "Feature",
  "properties": {
    "iso:country":"US",
    "sg:address":"2846 Webster Ave",
    "sg:city":"Bronx",
    "sg:classifiers":[
        {
            "category":"Parking",
            "type":"Transportation"
        }
    ],
    "sg:phone":"+1 718 933 4751",
    "sg:postcode":"10458",
    "sg:province":"NY",
    "sg:tags":[
        "garage"
    ],
    "wof:name":"Castle Parking Corp",
    "wof:placetype":"venue"
},
  "geometry": {"coordinates":[-73.88489199999999,40.866536],"type":"Point"}
}