{
  "type": "Feature",
  "properties": {
    "iso:country":"US",
    "sg:address":"1760 State St",
    "sg:city":"Schenectady",
    "sg:classifiers":[
        {
            "category":"Wholesale",
            "subcategory":"Machinery & Supplies",
            "type":"Manufacturing & Wholesale Goods"
        }
    ],
    "sg:phone":"+1 518 370 3888",
    "sg:postcode":"12304",
    "sg:province":"NY",
    "sg:tags":[
        "salon",
        "beauty"
    ],
    "wof:name":"Smith's Beauty Supply Stores",
    "wof:placetype":"venue"
},
  "geometry": {"coordinates":[-73.90527400000001,42.781432],"type":"Point"}
}