{
  "type": "Feature",
  "properties": {
    "addr:full":"416 Kenmore Ave Buffalo NY 14223",
    "addr:housenumber":"416",
    "addr:postcode":"14223",
    "addr:street":"Kenmore Ave",
    "iso:country":"US",
    "sg:address":"416 Kenmore Ave",
    "sg:city":"Buffalo",
    "sg:classifiers":[
        {
            "category":"Shopping",
            "subcategory":"Pharmacy",
            "type":"Retail Goods"
        }
    ],
    "sg:phone":"+1 716 362 0460",
    "sg:postcode":"14223",
    "sg:province":"NY",
    "sg:tags":[
        "drugstore"
    ],
    "sg:website":"www.thedrugshoppe.com",
    "wof:name":"Drug Shoppe The",
    "wof:placetype":"venue"
},
  "geometry": {"coordinates":[-78.833258,42.958172],"type":"Point"}
}