{
  "type": "Feature",
  "properties": {
    "addr:full":"26 Roberson Ave Pine Bush NY 12566",
    "addr:housenumber":"26",
    "addr:postcode":"12566",
    "addr:street":"Roberson Ave",
    "iso:country":"US",
    "sg:address":"26 Roberson Ave",
    "sg:city":"Pine Bush",
    "sg:classifiers":[
        {
            "category":"Shopping",
            "subcategory":"Gifts & Souvenirs",
            "type":"Retail Goods"
        }
    ],
    "sg:phone":"+1   ",
    "sg:postcode":"12566",
    "sg:province":"NY",
    "wof:name":"Painted Lady",
    "wof:placetype":"venue"
},
  "geometry": {"coordinates":[-74.35287599999999,41.549264],"type":"Point"}
}