{
  "type": "Feature",
  "properties": {
    "addr:full":"39 Sherman Ave New York NY 10040",
    "addr:housenumber":"39",
    "addr:postcode":"10040",
    "addr:street":"Sherman Ave",
    "iso:country":"US",
    "sg:address":"39 Sherman Ave",
    "sg:city":"New York",
    "sg:classifiers":[
        {
            "category":"Shopping",
            "subcategory":"Pharmacy",
            "type":"Retail Goods"
        }
    ],
    "sg:phone":"+1   ",
    "sg:postcode":"10040",
    "sg:province":"NY",
    "wof:name":"Vim Pharmacy",
    "wof:placetype":"venue"
},
  "geometry": {"coordinates":[-73.92859799999999,40.862614],"type":"Point"}
}