{
  "type": "Feature",
  "properties": {
    "iso:country":"US",
    "sg:address":"5477 Nesconset Hwy",
    "sg:city":"Mount Sinai",
    "sg:classifiers":[
        {
            "category":"Autos & Motor Vehicles",
            "subcategory":"Fuel & Gas Station",
            "type":"Retail Goods"
        }
    ],
    "sg:phone":"+1 631 473 1216",
    "sg:postcode":"11766",
    "sg:province":"NY",
    "wof:name":"Bob's Svce Center II",
    "wof:placetype":"venue"
},
  "geometry": {"coordinates":[-73.0317,40.9324],"type":"Point"}
}