{
  "type": "Feature",
  "properties": {
    "addr:full":"3400 Transit Rd Depew NY 14043",
    "addr:housenumber":"3400",
    "addr:postcode":"14043",
    "addr:street":"Transit Rd",
    "iso:country":"US",
    "sg:address":"3400 Transit Rd",
    "sg:city":"Depew",
    "sg:classifiers":[
        {
            "category":"Restaurant",
            "type":"Food & Drink"
        }
    ],
    "sg:phone":"+1 716 668 9843",
    "sg:postcode":"14043",
    "sg:province":"NY",
    "sg:tags":[
        "style",
        "family"
    ],
    "wof:name":"Lucky's Family Restaurant",
    "wof:placetype":"venue"
},
  "geometry": {"coordinates":[-78.69695299999999,42.860081],"type":"Point"}
}