{
  "type": "Feature",
  "properties": {
    "iso:country":"US",
    "sg:address":"268 Clark St",
    "sg:city":"Auburn",
    "sg:classifiers":[
        {
            "category":"Retail",
            "subcategory":"Funeral Services",
            "type":"Services"
        }
    ],
    "sg:phone":"+1   ",
    "sg:postcode":"13021",
    "sg:province":"NY",
    "wof:name":"Cheche Funeral Home",
    "wof:placetype":"venue"
},
  "geometry": {"coordinates":[-76.58421300000001,42.931365],"type":"Point"}
}