{
  "type": "Feature",
  "properties": {
    "iso:country":"US",
    "sg:address":"10529 Savage Rd",
    "sg:city":"Chaffee",
    "sg:classifiers":[
        {
            "category":"Building & Trades",
            "subcategory":"Construction",
            "type":"Services"
        }
    ],
    "sg:phone":"+1 716 492 3637",
    "sg:postcode":"14030",
    "sg:province":"NY",
    "sg:tags":[
        "general",
        "contractor"
    ],
    "wof:name":"Expert Exterior Construction",
    "wof:placetype":"venue"
},
  "geometry": {"coordinates":[-78.536997,42.591712],"type":"Point"}
}