{
  "type": "Feature",
  "properties": {
    "addr:full":"6041 Rose Arbor Ln Cicero NY 13039",
    "addr:housenumber":"6041",
    "addr:postcode":"13039",
    "addr:street":"Rose Arbor Ln",
    "iso:country":"US",
    "sg:address":"6041 Rose Arbor Ln",
    "sg:city":"Cicero",
    "sg:classifiers":[
        {
            "category":"Wholesale",
            "subcategory":"Machinery & Supplies",
            "type":"Manufacturing & Wholesale Goods"
        }
    ],
    "sg:phone":"+1 315 437 3379",
    "sg:postcode":"13039",
    "sg:province":"NY",
    "sg:tags":[
        "industrial"
    ],
    "wof:name":"R M Headlee Co Inc",
    "wof:placetype":"venue"
},
  "geometry": {"coordinates":[-76.10199900000001,43.149374],"type":"Point"}
}