{
  "type": "Feature",
  "properties": {
    "iso:country":"US",
    "sg:address":"853 Broadway",
    "sg:city":"New York",
    "sg:classifiers":[
        {
            "category":"Real Estate",
            "subcategory":"Architect",
            "type":"Services"
        }
    ],
    "sg:phone":"+1 212 505 1726",
    "sg:postcode":"10003",
    "sg:province":"NY",
    "wof:name":"May David Archt",
    "wof:placetype":"venue"
},
  "geometry": {"coordinates":[-73.990846,40.734562],"type":"Point"}
}