{
  "type": "Feature",
  "properties": {
    "addr:full":"1310 48th Street Brooklyn NY 11219",
    "addr:housenumber":"1310",
    "addr:postcode":"11219",
    "addr:street":"48Th Street",
    "iso:country":"US",
    "sg:address":"1310 48th Street",
    "sg:city":"Brooklyn",
    "sg:classifiers":[
        {
            "category":"Professional",
            "subcategory":"Lawyer & Legal Services",
            "type":"Services"
        }
    ],
    "sg:phone":"+1 718 851 4521",
    "sg:postcode":"11219",
    "sg:province":"NY",
    "wof:name":"Zalcman Helen M ESQ",
    "wof:placetype":"venue"
},
  "geometry": {"coordinates":[-73.99133,40.635436],"type":"Point"}
}