{
  "type": "Feature",
  "properties": {
    "iso:country":"US",
    "sg:address":"208 Krumville Rd",
    "sg:city":"Olivebridge",
    "sg:classifiers":[
        {
            "category":"Shopping",
            "type":"Retail Goods"
        }
    ],
    "sg:phone":"+1 845 657 2100",
    "sg:postcode":"12461",
    "sg:province":"NY",
    "sg:tags":[
        "material",
        "artist",
        "supply"
    ],
    "wof:name":"DNA Stretchers",
    "wof:placetype":"venue"
},
  "geometry": {"coordinates":[-74.21563999999999,41.909489],"type":"Point"}
}