{
  "type": "Feature",
  "properties": {
    "addr:full":"101-01 Foster Ave Brooklyn NY 11230",
    "addr:housenumber":"101-01",
    "addr:postcode":"11230",
    "addr:street":"Foster Ave",
    "iso:country":"US",
    "sg:address":"101-01 Foster Ave",
    "sg:city":"Brooklyn",
    "sg:classifiers":[
        {
            "category":"Home & Garden",
            "subcategory":"Garden Supply",
            "type":"Retail Goods"
        },
        {
            "category":"Building & Trades",
            "subcategory":"Construction",
            "type":"Services"
        },
        {
            "category":"Wholesale",
            "subcategory":"Home Furnishings",
            "type":"Manufacturing & Wholesale Goods"
        }
    ],
    "sg:phone":"+1 718 339 6160",
    "sg:postcode":"11230",
    "sg:province":"NY",
    "sg:tags":[
        "blind",
        "interior",
        "design",
        "shade"
    ],
    "sg:website":"simonsdecorating.com",
    "wof:name":"Simon's Decorating & Design",
    "wof:placetype":"venue"
},
  "geometry": {"coordinates":[-73.976398,40.627661],"type":"Point"}
}