{
  "type": "Feature",
  "properties": {
    "iso:country":"US",
    "sg:address":"735 Amsterdam Ave",
    "sg:city":"New York",
    "sg:classifiers":[
        {
            "category":"Shopping",
            "subcategory":"Pharmacy",
            "type":"Retail Goods"
        }
    ],
    "sg:phone":"+1 212 865 9700",
    "sg:postcode":"10025",
    "sg:province":"NY",
    "sg:tags":[
        "drugstore"
    ],
    "wof:name":"New Amsterdam Drug Mart Inc",
    "wof:placetype":"venue"
},
  "geometry": {"coordinates":[-73.97080200000001,40.793598],"type":"Point"}
}