{
  "type": "Feature",
  "properties": {
    "addr:full":"370 Lexington Ave New York NY 10017",
    "addr:housenumber":"370",
    "addr:postcode":"10017",
    "addr:street":"Lexington Ave",
    "iso:country":"US",
    "sg:address":"370 Lexington Ave",
    "sg:city":"New York",
    "sg:classifiers":[
        {
            "category":"Restaurant",
            "type":"Food & Drink"
        }
    ],
    "sg:phone":"+1 212 867 1946",
    "sg:postcode":"10017",
    "sg:province":"NY",
    "sg:tags":[
        "italian"
    ],
    "sg:website":"nooitogo.com",
    "wof:name":"Nooi Pasta To-Go",
    "wof:placetype":"venue"
},
  "geometry": {"coordinates":[-73.976607,40.750715],"type":"Point"}
}