{
  "type": "Feature",
  "properties": {
    "addr:full":"77 W 66 St New York NY 10023",
    "addr:housenumber":"77",
    "addr:postcode":"10023",
    "addr:street":"W 66 St",
    "iso:country":"US",
    "sg:address":"77 W 66 St",
    "sg:city":"New York",
    "sg:classifiers":[
        {
            "category":"Manufacturing",
            "subcategory":"Printing",
            "type":"Manufacturing & Wholesale Goods"
        }
    ],
    "sg:phone":"+1 212 456 0100",
    "sg:postcode":"10023",
    "sg:province":"NY",
    "sg:tags":[
        "publisher"
    ],
    "sg:website":"www.hyperionbooks.com",
    "wof:name":"Hyperion",
    "wof:placetype":"venue"
},
  "geometry": {"coordinates":[-73.979865,40.772749],"type":"Point"}
}