{
  "type": "Feature",
  "properties": {
    "iso:country":"US",
    "sg:address":"119 N Park Ave Ste 300",
    "sg:city":"Rockville Centre",
    "sg:classifiers":[
        {
            "category":"Professional",
            "subcategory":"Lawyer & Legal Services",
            "type":"Services"
        }
    ],
    "sg:phone":"+1 516 766 5770",
    "sg:postcode":"11570",
    "sg:province":"NY",
    "wof:name":"Milone Louis J Jr Atty",
    "wof:placetype":"venue"
},
  "geometry": {"coordinates":[-73.644897,40.6604],"type":"Point"}
}