{
  "type": "Feature",
  "properties": {
    "iso:country":"US",
    "sg:address":"8014 13th Ave",
    "sg:city":"Brooklyn",
    "sg:classifiers":[
        {
            "category":"Health Services",
            "subcategory":"Doctor",
            "type":"Services"
        }
    ],
    "sg:phone":"+1 718 238 1000",
    "sg:postcode":"11228",
    "sg:province":"NY",
    "sg:tags":[
        "medical"
    ],
    "wof:name":"Island Heights Pediatrics",
    "wof:placetype":"venue"
},
  "geometry": {"coordinates":[-74.010803,40.617298],"type":"Point"}
}