{
  "type": "Feature",
  "properties": {
    "iso:country":"US",
    "sg:address":"59 Central Ave",
    "sg:city":"Farmingdale",
    "sg:classifiers":[
        {
            "category":"Retail",
            "subcategory":"Repair Shop",
            "type":"Services"
        }
    ],
    "sg:phone":"+1 631 420 6925",
    "sg:postcode":"11735",
    "sg:province":"NY",
    "sg:tags":[
        "installs",
        "re",
        "conditioner",
        "commercial",
        "air"
    ],
    "wof:name":"Corona Jackson Rfrgn Svce",
    "wof:placetype":"venue"
},
  "geometry": {"coordinates":[-73.41085099999999,40.753013],"type":"Point"}
}