{
  "type": "Feature",
  "properties": {
    "iso:country":"US",
    "sg:address":"7 Harwood Ln",
    "sg:city":"East Rochester",
    "sg:classifiers":[
        {
            "category":"Organizations",
            "subcategory":"Community Association",
            "type":"Services"
        }
    ],
    "sg:phone":"+1   ",
    "sg:postcode":"14445",
    "sg:province":"NY",
    "wof:name":"Blue Army Rochester Chapter",
    "wof:placetype":"venue"
},
  "geometry": {"coordinates":[-77.504532,43.115505],"type":"Point"}
}