{
  "type": "Feature",
  "properties": {
    "iso:country":"US",
    "sg:address":"2817 Ave U",
    "sg:city":"Brooklyn",
    "sg:classifiers":[
        {
            "category":"Shopping",
            "subcategory":"Department Store",
            "type":"Retail Goods"
        }
    ],
    "sg:phone":"+1   ",
    "sg:postcode":"11229",
    "sg:province":"NY",
    "wof:name":"U-Variety",
    "wof:placetype":"venue"
},
  "geometry": {"coordinates":[-73.943015,40.600376],"type":"Point"}
}