{
  "type": "Feature",
  "properties": {
    "iso:country":"US",
    "sg:address":"27 Smith St",
    "sg:city":"Brooklyn",
    "sg:classifiers":[
        {
            "category":"Restaurant",
            "type":"Food & Drink"
        }
    ],
    "sg:phone":"+1 718 643 7777",
    "sg:postcode":"11201",
    "sg:province":"NY",
    "sg:tags":[
        "pizza"
    ],
    "sg:website":"www.saporitapizza.com/",
    "wof:name":"Saporita Pizza",
    "wof:placetype":"venue"
},
  "geometry": {"coordinates":[-73.98747400000001,40.690619],"type":"Point"}
}