{
  "type": "Feature",
  "properties": {
    "addr:full":"60 New Hampshire Ave Bay Shore NY 11706",
    "addr:housenumber":"60",
    "addr:postcode":"11706",
    "addr:street":"New Hampshire Ave",
    "iso:country":"US",
    "sg:address":"60 New Hampshire Ave",
    "sg:city":"Bay Shore",
    "sg:classifiers":[
        {
            "category":"Local Transit",
            "type":"Transportation"
        }
    ],
    "sg:phone":"+1   ",
    "sg:postcode":"11706",
    "sg:province":"NY",
    "sg:tags":[
        "passenger"
    ],
    "wof:name":"Laxmi Trans Corp",
    "wof:placetype":"venue"
},
  "geometry": {"coordinates":[-73.252623,40.760213],"type":"Point"}
}