{
  "type": "Feature",
  "properties": {
    "addr:full":"423 Evergreen Ct Central Valley NY 10917",
    "addr:housenumber":"423",
    "addr:postcode":"10917",
    "addr:street":"Evergreen Ct",
    "iso:country":"US",
    "sg:address":"423 Evergreen Ct",
    "sg:city":"Central Valley",
    "sg:classifiers":[
        {
            "category":"Shopping",
            "subcategory":"Clothing, Apparel, & Fashions",
            "type":"Retail Goods"
        }
    ],
    "sg:phone":"+1 845 928 2424",
    "sg:postcode":"10917",
    "sg:province":"NY",
    "sg:tags":[
        "furnishing"
    ],
    "sg:website":"www.zegna.com",
    "wof:name":"Ermenegildo Zegna Outlet Store",
    "wof:placetype":"venue"
},
  "geometry": {"coordinates":[-74.12626299999999,41.316345],"type":"Point"}
}