{
  "type": "Feature",
  "properties": {
    "iso:country":"US",
    "sg:address":"5262 Oakridge Dr",
    "sg:city":"Hamburg",
    "sg:classifiers":[
        {
            "category":"Shopping",
            "subcategory":"Hobbies, Toys, & Games",
            "type":"Retail Goods"
        }
    ],
    "sg:phone":"+1   ",
    "sg:postcode":"14075",
    "sg:province":"NY",
    "wof:name":"Wind & Wynd Kites & Toys",
    "wof:placetype":"venue"
},
  "geometry": {"coordinates":[-78.80697600000001,42.739978],"type":"Point"}
}