{
  "type": "Feature",
  "properties": {
    "addr:full":"296 Bleecker St New York NY 10014",
    "addr:housenumber":"296",
    "addr:postcode":"10014",
    "addr:street":"Bleecker St",
    "iso:country":"US",
    "sg:address":"296 Bleecker St",
    "sg:city":"New York",
    "sg:classifiers":[
        {
            "category":"Restaurant",
            "type":"Food & Drink"
        }
    ],
    "sg:phone":"+1 212 488 2700",
    "sg:postcode":"10014",
    "sg:province":"NY",
    "sg:tags":[
        "italian",
        "pizza"
    ],
    "sg:website":"www.villapazzo.com",
    "wof:name":"Villa Pazzo",
    "wof:placetype":"venue"
},
  "geometry": {"coordinates":[-74.00361100000001,40.732316],"type":"Point"}
}