{
  "type": "Feature",
  "properties": {
    "iso:country":"US",
    "sg:address":"38 State Hwy 59",
    "sg:city":"Spring Valley",
    "sg:classifiers":[
        {
            "category":"Professional",
            "subcategory":"Business Services",
            "type":"Services"
        }
    ],
    "sg:phone":"+1 845 356 9140",
    "sg:postcode":"10977",
    "sg:province":"NY",
    "sg:tags":[
        "broker",
        "merchandise"
    ],
    "wof:name":"Spring Valley Auto Brokers",
    "wof:placetype":"venue"
},
  "geometry": {"coordinates":[-74.04440099999999,41.109052],"type":"Point"}
}