{
  "type": "Feature",
  "properties": {
    "addr:full":"95 Browns Rd Scottsville NY 14546",
    "addr:housenumber":"95",
    "addr:postcode":"14546",
    "addr:street":"Browns Rd",
    "iso:country":"US",
    "sg:address":"95 Browns Rd",
    "sg:city":"Scottsville",
    "sg:classifiers":[
        {
            "category":"Building & Trades",
            "subcategory":"Electrical",
            "type":"Services"
        },
        {
            "category":"Building & Trades",
            "subcategory":"Construction",
            "type":"Services"
        }
    ],
    "sg:phone":"+1 585 889 8517",
    "sg:postcode":"14546",
    "sg:province":"NY",
    "sg:tags":[
        "installation",
        "floor",
        "laying",
        "rod",
        "contractor",
        "lightning"
    ],
    "wof:name":"Trescott Installations",
    "wof:placetype":"venue"
},
  "geometry": {"coordinates":[-77.749926,43.029542],"type":"Point"}
}