{
  "type": "Feature",
  "properties": {
    "addr:full":"203 Broadway Newburgh NY 12550",
    "addr:housenumber":"203",
    "addr:postcode":"12550",
    "addr:street":"Broadway",
    "iso:country":"US",
    "sg:address":"203 Broadway",
    "sg:city":"Newburgh",
    "sg:classifiers":[
        {
            "category":"Bars & Pubs",
            "type":"Food & Drink"
        }
    ],
    "sg:phone":"+1   ",
    "sg:postcode":"12550",
    "sg:province":"NY",
    "sg:tags":[
        "drinking"
    ],
    "wof:name":"Oasis Restaurant Sports Bar",
    "wof:placetype":"venue"
},
  "geometry": {"coordinates":[-74.015748,41.500325],"type":"Point"}
}