{
  "type": "Feature",
  "properties": {
    "addr:full":"952 Hempstead Tpke Franklin Square NY 11010",
    "addr:housenumber":"952",
    "addr:postcode":"11010",
    "addr:street":"Hempstead Tpke",
    "iso:country":"US",
    "sg:address":"952 Hempstead Tpke",
    "sg:city":"Franklin Square",
    "sg:classifiers":[
        {
            "category":"Personal",
            "subcategory":"Barber",
            "type":"Services"
        }
    ],
    "sg:phone":"+1 516 775 0632",
    "sg:postcode":"11010",
    "sg:province":"NY",
    "wof:name":"Franklin Square Barber Shop",
    "wof:placetype":"venue"
},
  "geometry": {"coordinates":[-73.67179899999999,40.7071],"type":"Point"}
}