{
  "type": "Feature",
  "properties": {
    "addr:full":"1409 Harlem Rd Buffalo NY 14206",
    "addr:housenumber":"1409",
    "addr:postcode":"14206",
    "addr:street":"Harlem Rd",
    "iso:country":"US",
    "sg:address":"1409 Harlem Rd",
    "sg:city":"Buffalo",
    "sg:classifiers":[
        {
            "category":"Professional",
            "subcategory":"Business Services",
            "type":"Services"
        }
    ],
    "sg:phone":"+1 716 895 9530",
    "sg:postcode":"14206",
    "sg:province":"NY",
    "sg:tags":[
        "engraver"
    ],
    "wof:name":"Engraving The Moments",
    "wof:placetype":"venue"
},
  "geometry": {"coordinates":[-78.78461,42.880358],"type":"Point"}
}