{
  "type": "Feature",
  "properties": {
    "addr:full":"310 Court Street Brooklyn NY 11231",
    "addr:housenumber":"310",
    "addr:postcode":"11231",
    "addr:street":"Court Street",
    "iso:country":"US",
    "sg:address":"310 Court Street",
    "sg:city":"Brooklyn",
    "sg:classifiers":[
        {
            "category":"Personal",
            "subcategory":"Nail Salon",
            "type":"Services"
        }
    ],
    "sg:phone":"+1 718 855 4398",
    "sg:postcode":"11231",
    "sg:province":"NY",
    "wof:name":"Pearl Lin's Nails",
    "wof:placetype":"venue"
},
  "geometry": {"coordinates":[-73.995462,40.683581],"type":"Point"}
}