{
  "type": "Feature",
  "properties": {
    "iso:country":"US",
    "sg:address":"223 Mohawk Ave",
    "sg:city":"Scotia",
    "sg:classifiers":[
        {
            "category":"Personal",
            "subcategory":"Beauty Salon",
            "type":"Services"
        }
    ],
    "sg:phone":"+1 518 372 4497",
    "sg:postcode":"12302",
    "sg:province":"NY",
    "wof:name":"Gemmette's Classique",
    "wof:placetype":"venue"
},
  "geometry": {"coordinates":[-73.966583,42.827191],"type":"Point"}
}