{
  "type": "Feature",
  "properties": {
    "iso:country":"US",
    "sg:address":"115 Kings Hwy",
    "sg:city":"Congers",
    "sg:classifiers":[
        {
            "category":"Building & Trades",
            "subcategory":"Construction",
            "type":"Services"
        }
    ],
    "sg:phone":"+1 845 268 4318",
    "sg:postcode":"10920",
    "sg:province":"NY",
    "sg:tags":[
        "hanging",
        "contractor"
    ],
    "wof:name":"Anthony Falsetti Painting",
    "wof:placetype":"venue"
},
  "geometry": {"coordinates":[-73.946032,41.143266],"type":"Point"}
}