{
  "type": "Feature",
  "properties": {
    "addr:full":"4401 Hickory Hollow Ln Carmel NY 10512",
    "addr:housenumber":"4401",
    "addr:postcode":"10512",
    "addr:street":"Hickory Hollow Ln",
    "iso:country":"US",
    "sg:address":"4401 Hickory Hollow Ln",
    "sg:city":"Carmel",
    "sg:classifiers":[
        {
            "category":"Real Estate",
            "subcategory":"Real Estate Agent",
            "type":"Services"
        }
    ],
    "sg:phone":"+1 914 393 9447",
    "sg:postcode":"10512",
    "sg:province":"NY",
    "wof:name":"Lawrence Houlihan",
    "wof:placetype":"venue"
},
  "geometry": {"coordinates":[-73.651359,41.434914],"type":"Point"}
}