{
  "type": "Feature",
  "properties": {
    "addr:full":"7004 Kessel St Forest Hills NY 11375",
    "addr:housenumber":"7004",
    "addr:postcode":"11375",
    "addr:street":"Kessel St",
    "iso:country":"US",
    "sg:address":"7004 Kessel St",
    "sg:city":"Forest Hills",
    "sg:classifiers":[
        {
            "category":"Health Services",
            "subcategory":"Doctor",
            "type":"Services"
        }
    ],
    "sg:phone":"+1 718 544 2923",
    "sg:postcode":"11375",
    "sg:province":"NY",
    "wof:name":"D'arienzo Nicholas Dr",
    "wof:placetype":"venue"
},
  "geometry": {"coordinates":[-73.851097,40.713902],"type":"Point"}
}