{
  "type": "Feature",
  "properties": {
    "addr:full":"2430 Hoagland Rd Mount Morris NY 14510",
    "addr:housenumber":"2430",
    "addr:postcode":"14510",
    "addr:street":"Hoagland Rd",
    "iso:country":"US",
    "sg:address":"2430 Hoagland Rd",
    "sg:city":"Mount Morris",
    "sg:classifiers":[
        {
            "category":"Shopping",
            "subcategory":"Clothing, Apparel, & Fashions",
            "type":"Retail Goods"
        }
    ],
    "sg:phone":"+1   ",
    "sg:postcode":"14510",
    "sg:province":"NY",
    "sg:tags":[
        "wear"
    ],
    "wof:name":"Country Clothes For Every",
    "wof:placetype":"venue"
},
  "geometry": {"coordinates":[-77.922865,42.647179],"type":"Point"}
}