{
  "type": "Feature",
  "properties": {
    "addr:full":"1398 Myrtle Ave Brooklyn NY 11237",
    "addr:housenumber":"1398",
    "addr:postcode":"11237",
    "addr:street":"Myrtle Ave",
    "iso:country":"US",
    "sg:address":"1398 Myrtle Ave",
    "sg:city":"Brooklyn",
    "sg:classifiers":[
        {
            "category":"Retail",
            "subcategory":"Laundry & Dry Cleaning",
            "type":"Services"
        }
    ],
    "sg:phone":"+1 718 455 7378",
    "sg:postcode":"11237",
    "sg:province":"NY",
    "sg:tags":[
        "cleaner",
        "plant",
        "drycleaning"
    ],
    "wof:name":"R & S French Cleaners",
    "wof:placetype":"venue"
},
  "geometry": {"coordinates":[-73.919701,40.698601],"type":"Point"}
}