{
  "type": "Feature",
  "properties": {
    "iso:country":"US",
    "sg:address":"1936 Deer Park Ave",
    "sg:city":"Deer Park",
    "sg:classifiers":[
        {
            "category":"Shopping",
            "subcategory":"Gifts & Souvenirs",
            "type":"Retail Goods"
        }
    ],
    "sg:phone":"+1   ",
    "sg:postcode":"11729",
    "sg:province":"NY",
    "sg:tags":[
        "novelty",
        "card"
    ],
    "wof:name":"Sand Castle Gift Shop Ltd",
    "wof:placetype":"venue"
},
  "geometry": {"coordinates":[-73.330111,40.763252],"type":"Point"}
}