{
  "type": "Feature",
  "properties": {
    "iso:country":"US",
    "sg:address":"3430 Daansen Rd",
    "sg:city":"Walworth",
    "sg:classifiers":[
        {
            "category":"Building & Trades",
            "subcategory":"Landscaping Services",
            "type":"Services"
        }
    ],
    "sg:phone":"+1 585 872 1590",
    "sg:postcode":"14568",
    "sg:province":"NY",
    "sg:tags":[
        "landscape"
    ],
    "wof:name":"Phoenix Botanical Inc",
    "wof:placetype":"venue"
},
  "geometry": {"coordinates":[-77.252787,43.124656],"type":"Point"}
}