{
  "type": "Feature",
  "properties": {
    "iso:country":"US",
    "sg:address":"105 Townsend Ave",
    "sg:city":"Johnstown",
    "sg:classifiers":[
        {
            "category":"Shopping",
            "subcategory":"Bicycles & Sporting Goods",
            "type":"Retail Goods"
        }
    ],
    "sg:phone":"+1   ",
    "sg:postcode":"12095",
    "sg:province":"NY",
    "sg:tags":[
        "repair"
    ],
    "wof:name":"Adirondack Sports Center Inc",
    "wof:placetype":"venue"
},
  "geometry": {"coordinates":[-74.359644,43.019986],"type":"Point"}
}