{
  "type": "Feature",
  "properties": {
    "addr:full":"285 E Main St Mount Kisco NY 10549",
    "addr:housenumber":"285",
    "addr:postcode":"10549",
    "addr:street":"E Main St",
    "iso:country":"US",
    "sg:address":"285 E Main St",
    "sg:city":"Mount Kisco",
    "sg:classifiers":[
        {
            "category":"Real Estate",
            "subcategory":"Architect",
            "type":"Services"
        }
    ],
    "sg:phone":"+1 914 666 5900",
    "sg:postcode":"10549",
    "sg:province":"NY",
    "wof:name":"Kaeyer Garment & Davidson PC",
    "wof:placetype":"venue"
},
  "geometry": {"coordinates":[-73.725403,41.2005],"type":"Point"}
}