{
  "type": "Feature",
  "properties": {
    "iso:country":"US",
    "sg:address":"87 Christopher St",
    "sg:city":"New York",
    "sg:classifiers":[
        {
            "category":"Personal",
            "subcategory":"Beauty Salon",
            "type":"Services"
        }
    ],
    "sg:phone":"+1 212 366 0824",
    "sg:postcode":"10014",
    "sg:province":"NY",
    "wof:name":"Free Time Salon",
    "wof:placetype":"venue"
},
  "geometry": {"coordinates":[-74.003539,40.733616],"type":"Point"}
}