{
  "type": "Feature",
  "properties": {
    "addr:full":"79 College Rd Monsey NY 10952",
    "addr:housenumber":"79",
    "addr:postcode":"10952",
    "addr:street":"College Rd",
    "iso:country":"US",
    "sg:address":"79 College Rd",
    "sg:city":"Monsey",
    "sg:classifiers":[
        {
            "category":"Retail",
            "subcategory":"Repair Shop",
            "type":"Services"
        }
    ],
    "sg:phone":"+1 845 362 8777",
    "sg:postcode":"10952",
    "sg:province":"NY",
    "sg:tags":[
        "lock",
        "locksmith"
    ],
    "wof:name":"Locksmiths",
    "wof:placetype":"venue"
},
  "geometry": {"coordinates":[-74.088892,41.115967],"type":"Point"}
}