{
  "type": "Feature",
  "properties": {
    "addr:full":"911 83rd St Brooklyn NY 11228",
    "addr:housenumber":"911",
    "addr:postcode":"11228",
    "addr:street":"83Rd St",
    "iso:country":"US",
    "sg:address":"911 83rd St",
    "sg:city":"Brooklyn",
    "sg:classifiers":[
        {
            "category":"Restaurant",
            "type":"Food & Drink"
        }
    ],
    "sg:phone":"+1   ",
    "sg:postcode":"11228",
    "sg:province":"NY",
    "wof:name":"Mzs Lounge Inc",
    "wof:placetype":"venue"
},
  "geometry": {"coordinates":[-74.018807,40.619932],"type":"Point"}
}