{
  "type": "Feature",
  "properties": {
    "addr:full":"70 Vanderbilt Motr Pkwy Commack NY 11725",
    "addr:housenumber":"70",
    "addr:postcode":"11725",
    "addr:street":"Vanderbilt Motr Pkwy",
    "iso:country":"US",
    "sg:address":"70 Vanderbilt Motr Pkwy",
    "sg:city":"Commack",
    "sg:classifiers":[
        {
            "category":"Shopping",
            "subcategory":"Adult",
            "type":"Retail Goods"
        },
        {
            "category":"Restaurant",
            "type":"Food & Drink"
        }
    ],
    "sg:phone":"+1 631 543 4177",
    "sg:postcode":"11725",
    "sg:province":"NY",
    "sg:tags":[
        "entertainment"
    ],
    "wof:name":"The Scene Restaurant & Lounge",
    "wof:placetype":"venue"
},
  "geometry": {"coordinates":[-73.288498,40.815701],"type":"Point"}
}