{
  "type": "Feature",
  "properties": {
    "iso:country":"US",
    "sg:address":"260 Quincy St",
    "sg:city":"Brooklyn",
    "sg:classifiers":[
        {
            "category":"Organizations",
            "subcategory":"Religious Organization",
            "type":"Services"
        }
    ],
    "sg:phone":"+1   ",
    "sg:postcode":"11216",
    "sg:province":"NY",
    "wof:name":"John Wesley Methodist Church",
    "wof:placetype":"venue"
},
  "geometry": {"coordinates":[-73.954538,40.686512],"type":"Point"}
}