{
  "type": "Feature",
  "properties": {
    "iso:country":"US",
    "sg:address":"200 Atlantic Ave",
    "sg:city":"New Hyde Park",
    "sg:classifiers":[
        {
            "category":"Wholesale",
            "subcategory":"Construction Materials",
            "type":"Manufacturing & Wholesale Goods"
        }
    ],
    "sg:phone":"+1   ",
    "sg:postcode":"11040",
    "sg:province":"NY",
    "sg:tags":[
        "mfg",
        "tool",
        "edge",
        "hand"
    ],
    "wof:name":"Joseph G Pollard Company Inc",
    "wof:placetype":"venue"
},
  "geometry": {"coordinates":[-73.657051,40.736826],"type":"Point"}
}