{
  "type": "Feature",
  "properties": {
    "addr:full":"326 Starin Ave Buffalo NY 14216",
    "addr:housenumber":"326",
    "addr:postcode":"14216",
    "addr:street":"Starin Ave",
    "iso:country":"US",
    "sg:address":"326 Starin Ave",
    "sg:city":"Buffalo",
    "sg:classifiers":[
        {
            "category":"Health Services",
            "subcategory":"Doctor",
            "type":"Services"
        }
    ],
    "sg:phone":"+1 716 836 1599",
    "sg:postcode":"14216",
    "sg:province":"NY",
    "sg:tags":[
        "physician",
        "surgeon"
    ],
    "wof:name":"Thomas J Murphy MD",
    "wof:placetype":"venue"
},
  "geometry": {"coordinates":[-78.844076,42.948598],"type":"Point"}
}