{
  "type": "Feature",
  "properties": {
    "iso:country":"US",
    "sg:address":"3524 Rombouts Ave",
    "sg:city":"Bronx",
    "sg:classifiers":[
        {
            "category":"Building & Trades",
            "subcategory":"Construction",
            "type":"Services"
        }
    ],
    "sg:phone":"+1 718 994 1666",
    "sg:postcode":"10475",
    "sg:province":"NY",
    "sg:tags":[
        "general",
        "contractor"
    ],
    "wof:name":"Strongback Corp",
    "wof:placetype":"venue"
},
  "geometry": {"coordinates":[-73.830139,40.884682],"type":"Point"}
}