{
  "type": "Feature",
  "properties": {
    "addr:full":"10223 89th Ave Richmond Hill NY 11418",
    "addr:housenumber":"10223",
    "addr:postcode":"11418",
    "addr:street":"89Th Ave",
    "iso:country":"US",
    "sg:address":"10223 89th Ave",
    "sg:city":"Richmond Hill",
    "sg:classifiers":[
        {
            "category":"Building & Trades",
            "subcategory":"Construction",
            "type":"Services"
        }
    ],
    "sg:phone":"+1 877 207 3700",
    "sg:postcode":"11418",
    "sg:province":"NY",
    "sg:tags":[
        "contractor"
    ],
    "wof:name":"People's Constr Co",
    "wof:placetype":"venue"
},
  "geometry": {"coordinates":[-73.844002,40.693298],"type":"Point"}
}