{
  "type": "Feature",
  "properties": {
    "addr:full":"201 Main St Dansville NY 14437",
    "addr:housenumber":"201",
    "addr:postcode":"14437",
    "addr:street":"Main St",
    "iso:country":"US",
    "sg:address":"201 Main St",
    "sg:city":"Dansville",
    "sg:classifiers":[
        {
            "category":"Health Services",
            "subcategory":"Doctor",
            "type":"Services"
        }
    ],
    "sg:phone":"+1 585 335 6170",
    "sg:postcode":"14437",
    "sg:province":"NY",
    "sg:tags":[
        "dentist"
    ],
    "wof:name":"Dansville Family Dental Care",
    "wof:placetype":"venue"
},
  "geometry": {"coordinates":[-77.696905,42.561792],"type":"Point"}
}