{
  "type": "Feature",
  "properties": {
    "addr:full":"123 W 43rd Street New York NY 10036",
    "addr:housenumber":"123",
    "addr:postcode":"10036",
    "addr:street":"W 43Rd Street",
    "iso:country":"US",
    "sg:address":"123 W 43rd Street",
    "sg:city":"New York",
    "sg:classifiers":[
        {
            "category":"Education",
            "subcategory":"School",
            "type":"Public Place"
        }
    ],
    "sg:phone":"+1 212 382 1875",
    "sg:postcode":"10036",
    "sg:province":"NY",
    "sg:tags":[
        "high",
        "middle",
        "elementary"
    ],
    "wof:name":"Town Hall Repertory Company",
    "wof:placetype":"venue"
},
  "geometry": {"coordinates":[-73.98445100000001,40.755887],"type":"Point"}
}