{
  "type": "Feature",
  "properties": {
    "addr:full":"1454 Rockaway Pkwy Brooklyn NY 11236",
    "addr:housenumber":"1454",
    "addr:postcode":"11236",
    "addr:street":"Rockaway Pkwy",
    "iso:country":"US",
    "sg:address":"1454 Rockaway Pkwy",
    "sg:city":"Brooklyn",
    "sg:classifiers":[
        {
            "category":"Professional",
            "subcategory":"Business Services",
            "type":"Services"
        }
    ],
    "sg:phone":"+1 718 723 0026",
    "sg:postcode":"11236",
    "sg:province":"NY",
    "wof:name":"2mac Meetings & Events Plg",
    "wof:placetype":"venue"
},
  "geometry": {"coordinates":[-73.901776,40.644649],"type":"Point"}
}