{
  "type": "Feature",
  "properties": {
    "addr:full":"90 Colin Dr Holbrook NY 11741",
    "addr:housenumber":"90",
    "addr:postcode":"11741",
    "addr:street":"Colin Dr",
    "iso:country":"US",
    "sg:address":"90 Colin Dr",
    "sg:city":"Holbrook",
    "sg:classifiers":[
        {
            "category":"Education",
            "subcategory":"Vocational School",
            "type":"Public Place"
        }
    ],
    "sg:phone":"+1 631 472 1975",
    "sg:postcode":"11741",
    "sg:province":"NY",
    "sg:tags":[
        "training",
        "computer"
    ],
    "wof:name":"Insource America",
    "wof:placetype":"venue"
},
  "geometry": {"coordinates":[-73.04825700000001,40.776374],"type":"Point"}
}