{
  "type": "Feature",
  "properties": {
    "addr:full":"400 Endo Blvd Garden City NY 11530",
    "addr:housenumber":"400",
    "addr:postcode":"11530",
    "addr:street":"Endo Blvd",
    "iso:country":"US",
    "sg:address":"400 Endo Blvd",
    "sg:city":"Garden City",
    "sg:classifiers":[
        {
            "category":"Health Services",
            "subcategory":"Doctor",
            "type":"Services"
        }
    ],
    "sg:phone":"+1 516 832 8504",
    "sg:postcode":"11530",
    "sg:province":"NY",
    "wof:name":"Center For Specialized Eye Surgery",
    "wof:placetype":"venue"
},
  "geometry": {"coordinates":[-73.591599,40.7346],"type":"Point"}
}