{
  "type": "Feature",
  "properties": {
    "addr:full":"271 Thomas St Hurley NY 12443",
    "addr:housenumber":"271",
    "addr:postcode":"12443",
    "addr:street":"Thomas St",
    "iso:country":"US",
    "sg:address":"271 Thomas St",
    "sg:city":"Hurley",
    "sg:classifiers":[
        {
            "category":"Manufacturing",
            "subcategory":"Retail Goods",
            "type":"Manufacturing & Wholesale Goods"
        }
    ],
    "sg:phone":"+1 845 334 9590",
    "sg:postcode":"12443",
    "sg:province":"NY",
    "sg:tags":[
        "manufacturer"
    ],
    "sg:website":"www.universalgymequipment.com",
    "wof:name":"Universal Gym Equipment",
    "wof:placetype":"venue"
},
  "geometry": {"coordinates":[-74.051305,41.925823],"type":"Point"}
}