{
  "type": "Feature",
  "properties": {
    "addr:full":"2360 Benson Ave Brooklyn NY 11214",
    "addr:housenumber":"2360",
    "addr:postcode":"11214",
    "addr:street":"Benson Ave",
    "iso:country":"US",
    "sg:address":"2360 Benson Ave",
    "sg:city":"Brooklyn",
    "sg:classifiers":[
        {
            "category":"Education",
            "subcategory":"School",
            "type":"Public Place"
        }
    ],
    "sg:phone":"+1 718 946 3796",
    "sg:postcode":"11214",
    "sg:province":"NY",
    "sg:tags":[
        "high",
        "middle",
        "elementary"
    ],
    "wof:name":"Nicholas Schiavo",
    "wof:placetype":"venue"
},
  "geometry": {"coordinates":[-73.99183600000001,40.597788],"type":"Point"}
}