{
  "type": "Feature",
  "properties": {
    "addr:full":"525 E 11 St New York NY 10009",
    "addr:housenumber":"525;11",
    "addr:postcode":"10009",
    "addr:street":"E;St",
    "iso:country":"US",
    "sg:address":"525 E 11 St",
    "sg:city":"New York",
    "sg:classifiers":[
        {
            "category":"Real Estate",
            "subcategory":"Real Estate Operator",
            "type":"Services"
        }
    ],
    "sg:phone":"+1 212 228 1302",
    "sg:postcode":"10009",
    "sg:province":"NY",
    "sg:tags":[
        "condominium"
    ],
    "wof:name":"Fillmore",
    "wof:placetype":"venue"
},
  "geometry": {"coordinates":[-73.97986299999999,40.727772],"type":"Point"}
}