{
  "type": "Feature",
  "properties": {
    "iso:country":"US",
    "sg:address":"105 Loepere St",
    "sg:city":"Buffalo",
    "sg:classifiers":[
        {
            "category":"Retail",
            "subcategory":"Repair Shop",
            "type":"Services"
        }
    ],
    "sg:phone":"+1 716 894 1070",
    "sg:postcode":"14212",
    "sg:province":"NY",
    "sg:tags":[
        "related"
    ],
    "wof:name":"Spinner Repair",
    "wof:placetype":"venue"
},
  "geometry": {"coordinates":[-78.83444799999999,42.894402],"type":"Point"}
}