{
  "type": "Feature",
  "properties": {
    "addr:full":"3018 Steinway St Astoria NY 11103",
    "addr:housenumber":"3018",
    "addr:postcode":"11103",
    "addr:street":"Steinway St",
    "iso:country":"US",
    "sg:address":"3018 Steinway St",
    "sg:city":"Astoria",
    "sg:classifiers":[
        {
            "category":"Banks & Credit Unions",
            "subcategory":"Bank",
            "type":"Services"
        }
    ],
    "sg:phone":"+1 718 932 4800",
    "sg:postcode":"11103",
    "sg:province":"NY",
    "wof:name":"Abny",
    "wof:placetype":"venue"
},
  "geometry": {"coordinates":[-73.915516,40.763506],"type":"Point"}
}