{
  "type": "Feature",
  "properties": {
    "addr:full":"70 E End Ave New York NY 10028",
    "addr:housenumber":"70",
    "addr:postcode":"10028",
    "addr:street":"E End Ave",
    "iso:country":"US",
    "sg:address":"70 E End Ave",
    "sg:city":"New York",
    "sg:classifiers":[
        {
            "category":"Retail",
            "subcategory":"Laundry & Dry Cleaning",
            "type":"Services"
        }
    ],
    "sg:phone":"+1 212 879 1637",
    "sg:postcode":"10028",
    "sg:province":"NY",
    "sg:tags":[
        "cleaners"
    ],
    "wof:name":"New Rocket Cleaners",
    "wof:placetype":"venue"
},
  "geometry": {"coordinates":[-73.94647000000001,40.772641],"type":"Point"}
}