{
  "type": "Feature",
  "properties": {
    "iso:country":"US",
    "sg:address":"321 Lake Simon Rd",
    "sg:city":"Tupper Lake",
    "sg:classifiers":[
        {
            "category":"Travel",
            "subcategory":"Campground",
            "type":"Entertainment"
        }
    ],
    "sg:phone":"+1   ",
    "sg:postcode":"12986",
    "sg:province":"NY",
    "sg:tags":[
        "trailer"
    ],
    "wof:name":"Ampersand Group",
    "wof:placetype":"venue"
},
  "geometry": {"coordinates":[-74.472865,44.197962],"type":"Point"}
}