{
  "type": "Feature",
  "properties": {
    "addr:full":"3019 Tibbett Ave Bronx NY 10463",
    "addr:housenumber":"3019",
    "addr:postcode":"10463",
    "addr:street":"Tibbett Ave",
    "iso:country":"US",
    "sg:address":"3019 Tibbett Ave",
    "sg:city":"Bronx",
    "sg:classifiers":[
        {
            "category":"Retail",
            "subcategory":"Auto Repair",
            "type":"Services"
        }
    ],
    "sg:phone":"+1 718 601 8850",
    "sg:postcode":"10463",
    "sg:province":"NY",
    "sg:tags":[
        "muffler",
        "exhaust",
        "system",
        "general"
    ],
    "wof:name":"Marty's Auto Clinic Inc",
    "wof:placetype":"venue"
},
  "geometry": {"coordinates":[-73.908637,40.880623],"type":"Point"}
}