{
  "type": "Feature",
  "properties": {
    "addr:full":"391 Nostrand Ave Brooklyn NY 11216",
    "addr:housenumber":"391",
    "addr:postcode":"11216",
    "addr:street":"Nostrand Ave",
    "iso:country":"US",
    "sg:address":"391 Nostrand Ave",
    "sg:city":"Brooklyn",
    "sg:classifiers":[
        {
            "category":"Professional",
            "subcategory":"Management & Consulting",
            "type":"Services"
        }
    ],
    "sg:phone":"+1 718 623 6880",
    "sg:postcode":"11216",
    "sg:province":"NY",
    "sg:tags":[
        "consultant",
        "training"
    ],
    "wof:name":"Good Brother's Training Ctr",
    "wof:placetype":"venue"
},
  "geometry": {"coordinates":[-73.950281,40.684379],"type":"Point"}
}