{
  "type": "Feature",
  "properties": {
    "addr:full":"262 State Hwy 306 Monsey NY 10952",
    "addr:housenumber":"262",
    "addr:postcode":"10952",
    "addr:street":"State Hwy 306",
    "iso:country":"US",
    "sg:address":"262 State Hwy 306",
    "sg:city":"Monsey",
    "sg:classifiers":[
        {
            "category":"Organizations",
            "subcategory":"Religious Organization",
            "type":"Services"
        }
    ],
    "sg:phone":"+1 845 354 1766",
    "sg:postcode":"10952",
    "sg:province":"NY",
    "sg:tags":[
        "clergy"
    ],
    "wof:name":"Mattis Kantor",
    "wof:placetype":"venue"
},
  "geometry": {"coordinates":[-74.066644,41.136786],"type":"Point"}
}