{
  "type": "Feature",
  "properties": {
    "addr:full":"30 N Greeley Ave Chappaqua NY 10514",
    "addr:housenumber":"30",
    "addr:postcode":"10514",
    "addr:street":"N Greeley Ave",
    "iso:country":"US",
    "sg:address":"30 N Greeley Ave",
    "sg:city":"Chappaqua",
    "sg:classifiers":[
        {
            "category":"Retail",
            "subcategory":"Veterinary Services",
            "type":"Services"
        }
    ],
    "sg:phone":"+1 914 238 8100",
    "sg:postcode":"10514",
    "sg:province":"NY",
    "sg:tags":[
        "veterinarian"
    ],
    "sg:website":"www.newcastlevet.com",
    "wof:name":"New Castle Veterinary Hospital",
    "wof:placetype":"venue"
},
  "geometry": {"coordinates":[-73.771004,41.161201],"type":"Point"}
}