{
  "type": "Feature",
  "properties": {
    "iso:country":"US",
    "sg:address":"14 Johnson Dr",
    "sg:city":"Warwick",
    "sg:classifiers":[
        {
            "category":"Professional",
            "type":"Services"
        }
    ],
    "sg:phone":"+1   ",
    "sg:postcode":"10990",
    "sg:province":"NY",
    "wof:name":"Digital Interface",
    "wof:placetype":"venue"
},
  "geometry": {"coordinates":[-74.30540000000001,41.247013],"type":"Point"}
}