{
  "type": "Feature",
  "properties": {
    "addr:full":"93 2nd Place, BSMT Brooklyn NY 11231",
    "addr:housenumber":"93",
    "addr:postcode":"11231",
    "addr:street":"2Nd Place",
    "iso:country":"US",
    "sg:address":"93 2nd Place, BSMT",
    "sg:city":"Brooklyn",
    "sg:classifiers":[
        {
            "category":"Professional",
            "subcategory":"Computer Services",
            "type":"Services"
        }
    ],
    "sg:phone":"+1 347 683 2016",
    "sg:postcode":"11231",
    "sg:province":"NY",
    "sg:tags":[
        "mobile",
        "mobile-web-dashboard",
        "aggregation",
        "api",
        "communication",
        "im",
        "networking",
        "iphone",
        "blackberry",
        "symbian",
        "windows-mobile",
        "nyc"
    ],
    "sg:website":"http://www.combo.com",
    "wof:name":"Meta Industries",
    "wof:placetype":"venue"
},
  "geometry": {"coordinates":[-73.99234,40.678256],"type":"Point"}
}