{
  "type": "Feature",
  "properties": {
    "iso:country":"US",
    "sg:address":"630 5th Ave",
    "sg:city":"New York",
    "sg:classifiers":[
        {
            "category":"Banks & Credit Unions",
            "subcategory":"Bank",
            "type":"Services"
        }
    ],
    "sg:phone":"+1 212 962 5800",
    "sg:postcode":"10111",
    "sg:province":"NY",
    "wof:name":"Ogaki Kyoritsu Bank the",
    "wof:placetype":"venue"
},
  "geometry": {"coordinates":[-73.977127,40.758928],"type":"Point"}
}