{
  "type": "Feature",
  "properties": {
    "iso:country":"US",
    "sg:address":"169 Haviland Rd",
    "sg:city":"Queensbury",
    "sg:classifiers":[
        {
            "category":"Building & Trades",
            "subcategory":"Landscaping Services",
            "type":"Services"
        }
    ],
    "sg:phone":"+1 518 792 4958",
    "sg:postcode":"12804",
    "sg:province":"NY",
    "sg:tags":[
        "designer",
        "landscape"
    ],
    "wof:name":"Miller Associates",
    "wof:placetype":"venue"
},
  "geometry": {"coordinates":[-73.65736699999999,43.358712],"type":"Point"}
}