{
  "type": "Feature",
  "properties": {
    "iso:country":"US",
    "sg:address":"348 Liberty Ave",
    "sg:city":"Brooklyn",
    "sg:classifiers":[
        {
            "category":"Banks & Credit Unions",
            "subcategory":"Bank",
            "type":"Services"
        }
    ],
    "sg:phone":"+1 718 495 0010",
    "sg:postcode":"11207",
    "sg:province":"NY",
    "sg:tags":[
        "cashing",
        "check"
    ],
    "wof:name":"WJJ Check Cashing",
    "wof:placetype":"venue"
},
  "geometry": {"coordinates":[-73.896764,40.674271],"type":"Point"}
}