{
  "type": "Feature",
  "properties": {
    "addr:full":"105 N Clark St Olean NY 14760",
    "addr:housenumber":"105",
    "addr:postcode":"14760",
    "addr:street":"N Clark St",
    "iso:country":"US",
    "sg:address":"105 N Clark St",
    "sg:city":"Olean",
    "sg:classifiers":[
        {
            "category":"Real Estate",
            "subcategory":"Surveying",
            "type":"Services"
        }
    ],
    "sg:phone":"+1 716 372 0871",
    "sg:postcode":"14760",
    "sg:province":"NY",
    "sg:tags":[
        "surveyor"
    ],
    "wof:name":"Robert C Ackerman Pls Assoc",
    "wof:placetype":"venue"
},
  "geometry": {"coordinates":[-78.403098,42.074884],"type":"Point"}
}