{
  "type": "Feature",
  "properties": {
    "iso:country":"US",
    "sg:address":"2741 Long Beach Rd",
    "sg:city":"Oceanside",
    "sg:classifiers":[
        {
            "category":"Personal",
            "subcategory":"Barber",
            "type":"Services"
        }
    ],
    "sg:phone":"+1 516 536 3567",
    "sg:postcode":"11572",
    "sg:province":"NY",
    "wof:name":"Oceanside Barber Shop",
    "wof:placetype":"venue"
},
  "geometry": {"coordinates":[-73.638926,40.645063],"type":"Point"}
}