{
  "type": "Feature",
  "properties": {
    "addr:full":"Nedra Lane & Arden Avenue Staten Island NY 10312",
    "addr:postcode":"10312",
    "addr:street":"Nedra Lane & Arden Avenue",
    "iso:country":"US",
    "sg:address":"Nedra Lane & Arden Avenue",
    "sg:city":"Staten Island",
    "sg:classifiers":[
        {
            "category":"Education",
            "subcategory":"School",
            "type":"Public Place"
        }
    ],
    "sg:phone":"+1 718 984 1197",
    "sg:postcode":"10312",
    "sg:province":"NY",
    "sg:tags":[
        "high",
        "middle",
        "elementary"
    ],
    "wof:name":"N Y City of",
    "wof:placetype":"venue"
},
  "geometry": {"coordinates":[-74.177694,40.548411],"type":"Point"}
}