{
  "type": "Feature",
  "properties": {
    "addr:full":"426 W 55 St New York NY 10019",
    "addr:housenumber":"426",
    "addr:postcode":"10019",
    "addr:street":"W 55 St",
    "iso:country":"US",
    "sg:address":"426 W 55 St",
    "sg:city":"New York",
    "sg:classifiers":[
        {
            "category":"Building & Trades",
            "subcategory":"Construction",
            "type":"Services"
        }
    ],
    "sg:phone":"+1 212 245 4240",
    "sg:postcode":"10019",
    "sg:province":"NY",
    "sg:tags":[
        "floral",
        "scenic",
        "props"
    ],
    "wof:name":"Tropical Fantasies Inc",
    "wof:placetype":"venue"
},
  "geometry": {"coordinates":[-73.988958,40.767425],"type":"Point"}
}