{
  "type": "Feature",
  "properties": {
    "iso:country":"US",
    "sg:address":"2061 Steinway Street",
    "sg:city":"Astoria",
    "sg:classifiers":[
        {
            "category":"Building & Trades",
            "subcategory":"Plumbing",
            "type":"Services"
        }
    ],
    "sg:phone":"+1 718 278 0758",
    "sg:postcode":"11105",
    "sg:province":"NY",
    "wof:name":"Union Plumbing & Heating Company",
    "wof:placetype":"venue"
},
  "geometry": {"coordinates":[-73.903082,40.775193],"type":"Point"}
}