{
  "type": "Feature",
  "properties": {
    "addr:full":"7 Rosalie Pl Commack NY 11725",
    "addr:housenumber":"7",
    "addr:postcode":"11725",
    "addr:street":"Rosalie Pl",
    "iso:country":"US",
    "sg:address":"7 Rosalie Pl",
    "sg:city":"Commack",
    "sg:classifiers":[
        {
            "category":"Professional",
            "type":"Services"
        }
    ],
    "sg:phone":"+1 631 858 2222",
    "sg:postcode":"11725",
    "sg:province":"NY",
    "sg:tags":[
        "establishment"
    ],
    "wof:name":"Berry Hill Assoc Inc",
    "wof:placetype":"venue"
},
  "geometry": {"coordinates":[-73.300112,40.840413],"type":"Point"}
}