{
  "type": "Feature",
  "properties": {
    "addr:full":"1407 Broadway Rm 314 New York NY 10018",
    "addr:housenumber":"1407;314",
    "addr:postcode":"10018",
    "addr:street":"Broadway Rm",
    "iso:country":"US",
    "sg:address":"1407 Broadway Rm 314",
    "sg:city":"New York",
    "sg:classifiers":[
        {
            "category":"Education",
            "subcategory":"Special Training",
            "type":"Public Place"
        }
    ],
    "sg:phone":"+1 646 778 5300",
    "sg:postcode":"10018",
    "sg:province":"NY",
    "sg:tags":[
        "school",
        "specialty"
    ],
    "wof:name":"Just For Wraps",
    "wof:placetype":"venue"
},
  "geometry": {"coordinates":[-73.987139,40.753443],"type":"Point"}
}