{
  "type": "Feature",
  "properties": {
    "iso:country":"US",
    "sg:address":"2343 Penfield Rd",
    "sg:city":"Penfield",
    "sg:classifiers":[
        {
            "category":"Manufacturing",
            "subcategory":"Lumber",
            "type":"Manufacturing & Wholesale Goods"
        }
    ],
    "sg:phone":"+1 585 377 6320",
    "sg:postcode":"14526",
    "sg:province":"NY",
    "sg:tags":[
        "sawmill"
    ],
    "wof:name":"Smith's Mill Portable Swmllng",
    "wof:placetype":"venue"
},
  "geometry": {"coordinates":[-77.42258699999999,43.128818],"type":"Point"}
}