{
  "type": "Feature",
  "properties": {
    "addr:full":"68 Greenpoint Ave Brooklyn NY 11222",
    "addr:housenumber":"68",
    "addr:postcode":"11222",
    "addr:street":"Greenpoint Ave",
    "iso:country":"US",
    "sg:address":"68 Greenpoint Ave",
    "sg:city":"Brooklyn",
    "sg:classifiers":[
        {
            "category":"Wholesale",
            "subcategory":"Groceries",
            "type":"Manufacturing & Wholesale Goods"
        }
    ],
    "sg:phone":"+1 718 383 0853",
    "sg:postcode":"11222",
    "sg:province":"NY",
    "wof:name":"Brooklyn Chocolate & Cocoa Co",
    "wof:placetype":"venue"
},
  "geometry": {"coordinates":[-73.958308,40.729713],"type":"Point"}
}