{
  "type": "Feature",
  "properties": {
    "addr:full":"65 Filors Ln Stony Point NY 10980",
    "addr:housenumber":"65",
    "addr:postcode":"10980",
    "addr:street":"Filors Ln",
    "iso:country":"US",
    "sg:address":"65 Filors Ln",
    "sg:city":"Stony Point",
    "sg:classifiers":[
        {
            "category":"Banks & Credit Unions",
            "subcategory":"Investment Brokerage",
            "type":"Services"
        }
    ],
    "sg:phone":"+1 845 942 1481",
    "sg:postcode":"10980",
    "sg:province":"NY",
    "sg:tags":[
        "stock",
        "bond"
    ],
    "wof:name":"Classy Association Stock Hold",
    "wof:placetype":"venue"
},
  "geometry": {"coordinates":[-73.99185199999999,41.218878],"type":"Point"}
}