{
  "type": "Feature",
  "properties": {
    "iso:country":"US",
    "sg:address":"9880 Transit Rd",
    "sg:city":"East Amherst",
    "sg:classifiers":[
        {
            "category":"Manufacturing",
            "subcategory":"Chemicals & Compounds",
            "type":"Manufacturing & Wholesale Goods"
        },
        {
            "category":"Wholesale",
            "subcategory":"Painting Supplies",
            "type":"Manufacturing & Wholesale Goods"
        }
    ],
    "sg:phone":"+1 716 853 5776",
    "sg:postcode":"14051",
    "sg:province":"NY",
    "sg:tags":[
        "paint",
        "product",
        "consulting",
        "business",
        "mfg"
    ],
    "wof:name":"Coatings Alliance LLC",
    "wof:placetype":"venue"
},
  "geometry": {"coordinates":[-78.69702100000001,43.035593],"type":"Point"}
}