{
  "type": "Feature",
  "properties": {
    "addr:full":"3755 90th St Jackson Heights NY 11372",
    "addr:housenumber":"3755",
    "addr:postcode":"11372",
    "addr:street":"90Th St",
    "iso:country":"US",
    "sg:address":"3755 90th St",
    "sg:city":"Jackson Heights",
    "sg:classifiers":[
        {
            "category":"Building & Trades",
            "subcategory":"Locksmith",
            "type":"Services"
        }
    ],
    "sg:phone":"+1 718 335 1743",
    "sg:postcode":"11372",
    "sg:province":"NY",
    "sg:tags":[
        "key"
    ],
    "wof:name":"Tri State Securities",
    "wof:placetype":"venue"
},
  "geometry": {"coordinates":[-73.876503,40.749298],"type":"Point"}
}