{
  "type": "Feature",
  "properties": {
    "addr:full":"1913 W 8th St Brooklyn NY 11223",
    "addr:housenumber":"1913",
    "addr:postcode":"11223",
    "addr:street":"W 8Th St",
    "iso:country":"US",
    "sg:address":"1913 W 8th St",
    "sg:city":"Brooklyn",
    "sg:classifiers":[
        {
            "category":"Manufacturing",
            "subcategory":"Signs",
            "type":"Manufacturing & Wholesale Goods"
        }
    ],
    "sg:phone":"+1 718 648 4900",
    "sg:postcode":"11223",
    "sg:province":"NY",
    "sg:tags":[
        "advertising",
        "specialty"
    ],
    "wof:name":"Express Signs",
    "wof:placetype":"venue"
},
  "geometry": {"coordinates":[-73.979826,40.598852],"type":"Point"}
}