{
  "type": "Feature",
  "properties": {
    "iso:country":"US",
    "sg:address":"1165 Morris Park Ave",
    "sg:city":"Bronx",
    "sg:classifiers":[
        {
            "category":"Health Services",
            "subcategory":"Doctor",
            "type":"Services"
        }
    ],
    "sg:phone":"+1 718 430 3814",
    "sg:postcode":"10461",
    "sg:province":"NY",
    "sg:tags":[
        "physician",
        "surgeon"
    ],
    "wof:name":"Samuel Koszer MD",
    "wof:placetype":"venue"
},
  "geometry": {"coordinates":[-73.849863,40.851043],"type":"Point"}
}