{
  "type": "Feature",
  "properties": {
    "addr:full":"6245 Sheridan Dr Buffalo NY 14221",
    "addr:housenumber":"6245",
    "addr:postcode":"14221",
    "addr:street":"Sheridan Dr",
    "iso:country":"US",
    "sg:address":"6245 Sheridan Dr",
    "sg:city":"Buffalo",
    "sg:classifiers":[
        {
            "category":"Insurance",
            "subcategory":"Insurance Agent",
            "type":"Services"
        }
    ],
    "sg:phone":"+1 716 839 0788",
    "sg:postcode":"14221",
    "sg:province":"NY",
    "wof:name":"Mutual Of Omaha Insurance Co",
    "wof:placetype":"venue"
},
  "geometry": {"coordinates":[-78.69946,42.978066],"type":"Point"}
}