{
  "type": "Feature",
  "properties": {
    "iso:country":"US",
    "sg:address":"1229 Montauk Hwy",
    "sg:city":"Oakdale",
    "sg:classifiers":[
        {
            "category":"Insurance",
            "subcategory":"Insurance Agent",
            "type":"Services"
        }
    ],
    "sg:phone":"+1 631 567 2772",
    "sg:postcode":"11769",
    "sg:province":"NY",
    "sg:tags":[
        "auto"
    ],
    "sg:website":"http://clickserve.dartsearch.net/link/click?lid=43000000277021432",
    "wof:name":"Allstate Insurance Company - Christopher S Brauer",
    "wof:placetype":"venue"
},
  "geometry": {"coordinates":[-73.129491,40.741539],"type":"Point"}
}