{
  "type": "Feature",
  "properties": {
    "iso:country":"US",
    "sg:address":"4568 Woodchuck Rd",
    "sg:city":"East Aurora",
    "sg:classifiers":[
        {
            "category":"Farming",
            "subcategory":"Dairy Farm",
            "type":"Manufacturing & Wholesale Goods"
        }
    ],
    "sg:phone":"+1 716 655 0382",
    "sg:postcode":"14052",
    "sg:province":"NY",
    "wof:name":"R & M Creekside Farm",
    "wof:placetype":"venue"
},
  "geometry": {"coordinates":[-78.518154,42.765669],"type":"Point"}
}