{
  "type": "Feature",
  "properties": {
    "iso:country":"US",
    "sg:address":"10680 Main Rd",
    "sg:city":"Mattituck",
    "sg:classifiers":[
        {
            "category":"Utilities",
            "subcategory":"Fuel Oil & Lpg",
            "type":"Services"
        }
    ],
    "sg:phone":"+1 631 298 4197",
    "sg:postcode":"11952",
    "sg:province":"NY",
    "sg:tags":[
        "oils-fuel"
    ],
    "wof:name":"Eckert Oil Service Inc",
    "wof:placetype":"venue"
},
  "geometry": {"coordinates":[-72.536692,40.986506],"type":"Point"}
}