{
  "type": "Feature",
  "properties": {
    "iso:country":"US",
    "sg:address":"1422 Ogden Ave",
    "sg:city":"Bronx",
    "sg:classifiers":[
        {
            "category":"Retail",
            "subcategory":"Auto Repair",
            "type":"Services"
        }
    ],
    "sg:phone":"+1   ",
    "sg:postcode":"10452",
    "sg:province":"NY",
    "sg:tags":[
        "transmission"
    ],
    "wof:name":"Sandro Transmission",
    "wof:placetype":"venue"
},
  "geometry": {"coordinates":[-73.92337999999999,40.844135],"type":"Point"}
}