{
  "type": "Feature",
  "properties": {
    "iso:country":"US",
    "sg:address":"1271 Walden Ave",
    "sg:city":"Buffalo",
    "sg:classifiers":[
        {
            "category":"Personal",
            "subcategory":"Beauty Salon",
            "type":"Services"
        }
    ],
    "sg:phone":"+1   ",
    "sg:postcode":"14211",
    "sg:province":"NY",
    "sg:tags":[
        "shop"
    ],
    "wof:name":"Francel Beauty Shop",
    "wof:placetype":"venue"
},
  "geometry": {"coordinates":[-78.78857499999999,42.90733],"type":"Point"}
}