{
  "type": "Feature",
  "properties": {
    "addr:full":"710 W 173rd St New York NY 10032",
    "addr:housenumber":"710",
    "addr:postcode":"10032",
    "addr:street":"W 173Rd St",
    "iso:country":"US",
    "sg:address":"710 W 173rd St",
    "sg:city":"New York",
    "sg:classifiers":[
        {
            "category":"Professional",
            "subcategory":"Management & Consulting",
            "type":"Services"
        }
    ],
    "sg:phone":"+1 212 740 3859",
    "sg:postcode":"10032",
    "sg:province":"NY",
    "sg:tags":[
        "consultant"
    ],
    "wof:name":"Consulting Services Carst",
    "wof:placetype":"venue"
},
  "geometry": {"coordinates":[-73.94248399999999,40.846076],"type":"Point"}
}