{
  "type": "Feature",
  "properties": {
    "iso:country":"US",
    "sg:address":"3432 Nostrand Ave",
    "sg:city":"Brooklyn",
    "sg:classifiers":[
        {
            "category":"Food & Beverages",
            "subcategory":"Bakery",
            "type":"Retail Goods"
        }
    ],
    "sg:phone":"+1 718 769 1254",
    "sg:postcode":"11229",
    "sg:province":"NY",
    "sg:tags":[
        "sandwich"
    ],
    "wof:name":"Brennan & Carr",
    "wof:placetype":"venue"
},
  "geometry": {"coordinates":[-73.942001,40.6003],"type":"Point"}
}