{
  "type": "Feature",
  "properties": {
    "iso:country":"US",
    "sg:address":"19 S Broadway",
    "sg:city":"Tarrytown",
    "sg:classifiers":[
        {
            "category":"Professional",
            "subcategory":"Management & Consulting",
            "type":"Services"
        }
    ],
    "sg:phone":"+1   ",
    "sg:postcode":"10591",
    "sg:province":"NY",
    "sg:tags":[
        "retail",
        "direct",
        "sales"
    ],
    "wof:name":"Cmp Designs",
    "wof:placetype":"venue"
},
  "geometry": {"coordinates":[-73.85871,41.075492],"type":"Point"}
}