{
  "type": "Feature",
  "properties": {
    "addr:full":"2670 Millersport Hwy Getzville NY 14068",
    "addr:postcode":"2670;14068",
    "addr:street":"Millersport Hwy",
    "iso:country":"US",
    "sg:address":"2670 Millersport Hwy",
    "sg:city":"Getzville",
    "sg:classifiers":[
        {
            "category":"Building & Trades",
            "subcategory":"Construction",
            "type":"Services"
        }
    ],
    "sg:phone":"+1 716 689 2213",
    "sg:postcode":"14068",
    "sg:province":"NY",
    "sg:tags":[
        "roofing",
        "general",
        "contractor"
    ],
    "wof:name":"Collingwood Roofing Systems",
    "wof:placetype":"venue"
},
  "geometry": {"coordinates":[-78.767398,43.016516],"type":"Point"}
}