{
  "type": "Feature",
  "properties": {
    "addr:full":"4108 Lafayette Rd Jamesville NY 13078",
    "addr:housenumber":"4108",
    "addr:postcode":"13078",
    "iso:country":"US",
    "sg:address":"4108 Lafayette Rd",
    "sg:city":"Jamesville",
    "sg:classifiers":[
        {
            "category":"Insurance",
            "subcategory":"Insurance Agent",
            "type":"Services"
        }
    ],
    "sg:phone":"+1 315 475 4106",
    "sg:postcode":"13078",
    "sg:province":"NY",
    "wof:name":"Chubb Life America",
    "wof:placetype":"venue"
},
  "geometry": {"coordinates":[-76.106706,42.972051],"type":"Point"}
}