{
  "type": "Feature",
  "properties": {
    "iso:country":"US",
    "sg:address":"1344 Union St",
    "sg:city":"Schenectady",
    "sg:classifiers":[
        {
            "category":"Health Services",
            "subcategory":"Podiatrist",
            "type":"Services"
        }
    ],
    "sg:phone":"+1   ",
    "sg:postcode":"12308",
    "sg:province":"NY",
    "wof:name":"Foot Doctors",
    "wof:placetype":"venue"
},
  "geometry": {"coordinates":[-73.91748699999999,42.809588],"type":"Point"}
}