{
  "type": "Feature",
  "properties": {
    "iso:country":"US",
    "sg:address":"220 White Plains Rd",
    "sg:city":"Tarrytown",
    "sg:classifiers":[
        {
            "category":"Education",
            "subcategory":"Special Training",
            "type":"Public Place"
        }
    ],
    "sg:phone":"+1 914 366 6000",
    "sg:postcode":"10591",
    "sg:province":"NY",
    "sg:tags":[
        "medical",
        "continuing"
    ],
    "wof:name":"Rxperience  LLC",
    "wof:placetype":"venue"
},
  "geometry": {"coordinates":[-73.844323,41.06326],"type":"Point"}
}