{
  "type": "Feature",
  "properties": {
    "iso:country":"US",
    "sg:address":"36 Brinkerhoff St",
    "sg:city":"Plattsburgh",
    "sg:classifiers":[
        {
            "category":"Social Services",
            "type":"Services"
        }
    ],
    "sg:phone":"+1 518 561 2330",
    "sg:postcode":"12901",
    "sg:province":"NY",
    "wof:name":"C E F Crisis Helpline Inc",
    "wof:placetype":"venue"
},
  "geometry": {"coordinates":[-73.45478300000001,44.697059],"type":"Point"}
}