{
  "type": "Feature",
  "properties": {
    "addr:full":"1901 Vestal Pkwy W Vestal NY 13850",
    "addr:housenumber":"1901",
    "addr:postcode":"13850",
    "addr:street":"Vestal Pkwy W",
    "iso:country":"US",
    "sg:address":"1901 Vestal Pkwy W",
    "sg:city":"Vestal",
    "sg:classifiers":[
        {
            "category":"Home & Garden",
            "subcategory":"Home Furnishings",
            "type":"Retail Goods"
        }
    ],
    "sg:phone":"+1 607 748 4351",
    "sg:postcode":"13850",
    "sg:province":"NY",
    "sg:tags":[
        "cutlery"
    ],
    "wof:name":"Cutco Cutlery",
    "wof:placetype":"venue"
},
  "geometry": {"coordinates":[-76.088021,42.073408],"type":"Point"}
}