{
  "type": "Feature",
  "properties": {
    "iso:country":"US",
    "sg:address":"69 Merry Ln",
    "sg:city":"Jericho",
    "sg:classifiers":[
        {
            "category":"Real Estate",
            "subcategory":"Real Estate Agent",
            "type":"Services"
        }
    ],
    "sg:phone":"+1 516 822 4226",
    "sg:postcode":"11753",
    "sg:province":"NY",
    "wof:name":"Deneral Realty Assoc",
    "wof:placetype":"venue"
},
  "geometry": {"coordinates":[-73.530171,40.790683],"type":"Point"}
}