{
  "type": "Feature",
  "properties": {
    "addr:full":"408 London Road Staten Island NY 10306",
    "addr:housenumber":"408",
    "addr:postcode":"10306",
    "addr:street":"London Road",
    "iso:country":"US",
    "sg:address":"408 London Road",
    "sg:city":"Staten Island",
    "sg:classifiers":[
        {
            "category":"Building & Trades",
            "subcategory":"Construction",
            "type":"Services"
        }
    ],
    "sg:phone":"+1 718 351 4506",
    "sg:postcode":"10306",
    "sg:province":"NY",
    "sg:tags":[
        "contractor"
    ],
    "wof:name":"L T Land Development Corporation",
    "wof:placetype":"venue"
},
  "geometry": {"coordinates":[-74.137933,40.578049],"type":"Point"}
}