{
  "type": "Feature",
  "properties": {
    "addr:full":"5800 Seneca St Elma NY 14059",
    "addr:housenumber":"5800",
    "addr:postcode":"14059",
    "addr:street":"Seneca St",
    "iso:country":"US",
    "sg:address":"5800 Seneca St",
    "sg:city":"Elma",
    "sg:classifiers":[
        {
            "category":"Building & Trades",
            "subcategory":"Plumbing",
            "type":"Services"
        }
    ],
    "sg:phone":"+1 716 674 5800",
    "sg:postcode":"14059",
    "sg:province":"NY",
    "sg:tags":[
        "plumbing",
        "contractor"
    ],
    "wof:name":"Aurora Plumbing Co Inc",
    "wof:placetype":"venue"
},
  "geometry": {"coordinates":[-78.695931,42.827168],"type":"Point"}
}