{
  "type": "Feature",
  "properties": {
    "iso:country":"US",
    "sg:address":"4603 E Genesee St",
    "sg:city":"Syracuse",
    "sg:classifiers":[
        {
            "category":"Restaurant",
            "type":"Food & Drink"
        }
    ],
    "sg:menulink":"http://www.allmenus.com/ny/de-witt/96808-ihop/menu/",
    "sg:phone":"+1 315 446 0915",
    "sg:postcode":"13214",
    "sg:province":"NY",
    "sg:tags":[
        "sandwich",
        "salad",
        "burger",
        "soup",
        "american",
        "steakhouse",
        "wrap"
    ],
    "wof:name":"IHOP",
    "wof:placetype":"venue"
},
  "geometry": {"coordinates":[-76.063744,43.034457],"type":"Point"}
}