{
  "type": "Feature",
  "properties": {
    "addr:full":"230 E 9th St 2nd Fl New York NY 10079",
    "addr:housenumber":"230",
    "addr:postcode":"10079",
    "addr:street":"E 9Th St",
    "iso:country":"US",
    "sg:address":"230 E 9th St 2nd Fl",
    "sg:city":"New York",
    "sg:classifiers":[
        {
            "category":"Tea Room",
            "subcategory":"None",
            "type":"Food & Drink"
        },
        {
            "category":"Restaurant",
            "type":"Food & Drink"
        }
    ],
    "sg:phone":"+1 212 228 8030",
    "sg:postcode":"10079",
    "sg:province":"NY",
    "sg:tags":[
        "japanese"
    ],
    "sg:website":"www.chaanteahouse.com",
    "wof:name":"Cha-An",
    "wof:placetype":"venue"
},
  "geometry": {"coordinates":[-73.98812,40.729479],"type":"Point"}
}