{
  "type": "Feature",
  "properties": {
    "iso:country":"US",
    "sg:address":"487 Humboldt Pkwy",
    "sg:city":"Buffalo",
    "sg:classifiers":[
        {
            "category":"Bars & Pubs",
            "type":"Food & Drink"
        }
    ],
    "sg:phone":"+1 716 884 6430",
    "sg:postcode":"14208",
    "sg:province":"NY",
    "wof:name":"Humboldt Inn",
    "wof:placetype":"venue"
},
  "geometry": {"coordinates":[-78.84385399999999,42.921386],"type":"Point"}
}