{
  "type": "Feature",
  "properties": {
    "addr:full":"138 Orchard St Frnt 1 New York NY 10002",
    "addr:housenumber":"138;1",
    "addr:postcode":"10002",
    "addr:street":"Orchard St Frnt",
    "iso:country":"US",
    "sg:address":"138 Orchard St Frnt 1",
    "sg:city":"New York",
    "sg:classifiers":[
        {
            "category":"Food & Beverages",
            "subcategory":"Groceries & Convenience Stores",
            "type":"Retail Goods"
        }
    ],
    "sg:phone":"+1 212 260 6263",
    "sg:postcode":"10002",
    "sg:province":"NY",
    "wof:name":"Healthy Drive Inc",
    "wof:placetype":"venue"
},
  "geometry": {"coordinates":[-73.98904,40.720039],"type":"Point"}
}