{
  "type": "Feature",
  "properties": {
    "iso:country":"US",
    "sg:address":"18 N Phillips Ave",
    "sg:city":"Speonk",
    "sg:classifiers":[
        {
            "category":"Health Services",
            "subcategory":"Health Practitioner",
            "type":"Services"
        }
    ],
    "sg:phone":"+1 631 325 3400",
    "sg:postcode":"11972",
    "sg:province":"NY",
    "sg:tags":[
        "therapist",
        "physical"
    ],
    "wof:name":"Speonk Physical Therapy",
    "wof:placetype":"venue"
},
  "geometry": {"coordinates":[-72.704672,40.820472],"type":"Point"}
}