{
  "type": "Feature",
  "properties": {
    "iso:country":"US",
    "sg:address":"1299 Portland Ave",
    "sg:city":"Rochester",
    "sg:classifiers":[
        {
            "category":"Health Services",
            "subcategory":"Doctor",
            "type":"Services"
        }
    ],
    "sg:phone":"+1 585 342 7902",
    "sg:postcode":"14621",
    "sg:province":"NY",
    "sg:tags":[
        "dentist"
    ],
    "wof:name":"Sarah J Smith DDS",
    "wof:placetype":"venue"
},
  "geometry": {"coordinates":[-77.58421800000001,43.189004],"type":"Point"}
}