{
  "type": "Feature",
  "properties": {
    "addr:full":"111 N 9th St Lindenhurst NY 11757",
    "addr:housenumber":"111",
    "addr:postcode":"11757",
    "addr:street":"N 9Th St",
    "iso:country":"US",
    "sg:address":"111 N 9th St",
    "sg:city":"Lindenhurst",
    "sg:classifiers":[
        {
            "category":"Building & Trades",
            "subcategory":"Construction",
            "type":"Services"
        }
    ],
    "sg:phone":"+1 631 225 7443",
    "sg:postcode":"11757",
    "sg:province":"NY",
    "sg:tags":[
        "resurfacing",
        "laying",
        "refinishing",
        "floor"
    ],
    "wof:name":"Miracle Touch Woodfloor Sndng",
    "wof:placetype":"venue"
},
  "geometry": {"coordinates":[-73.382109,40.686992],"type":"Point"}
}