{
  "type": "Feature",
  "properties": {
    "addr:full":"154 Kipp St Sherman NY 14781",
    "addr:housenumber":"154",
    "addr:postcode":"14781",
    "addr:street":"Kipp St",
    "iso:country":"US",
    "sg:address":"154 Kipp St",
    "sg:city":"Sherman",
    "sg:classifiers":[
        {
            "category":"Building & Trades",
            "subcategory":"Pest Control",
            "type":"Services"
        }
    ],
    "sg:phone":"+1 716 761 7905",
    "sg:postcode":"14781",
    "sg:province":"NY",
    "wof:name":"Orkin Exterminating Co",
    "wof:placetype":"venue"
},
  "geometry": {"coordinates":[-79.60283200000001,42.16531],"type":"Point"}
}