{
  "type": "Feature",
  "properties": {
    "addr:full":"222 Lake Ave Yonkers NY 10701",
    "addr:housenumber":"222",
    "addr:postcode":"10701",
    "addr:street":"Lake Ave",
    "iso:country":"US",
    "sg:address":"222 Lake Ave",
    "sg:city":"Yonkers",
    "sg:classifiers":[
        {
            "category":"Retail",
            "subcategory":"Repair Shop",
            "type":"Services"
        }
    ],
    "sg:phone":"+1 914 476 9556",
    "sg:postcode":"10701",
    "sg:province":"NY",
    "sg:tags":[
        "refinishing",
        "furniture"
    ],
    "wof:name":"Marvin's Antiques & Refinish",
    "wof:placetype":"venue"
},
  "geometry": {"coordinates":[-73.881894,40.945488],"type":"Point"}
}