{
  "type": "Feature",
  "properties": {
    "iso:country":"US",
    "sg:address":"82 Main St",
    "sg:city":"Brewster",
    "sg:classifiers":[
        {
            "category":"Taxi",
            "type":"Transportation"
        }
    ],
    "sg:phone":"+1 845 279 1398",
    "sg:postcode":"10509",
    "sg:province":"NY",
    "sg:tags":[
        "taxicab"
    ],
    "wof:name":"Manny's Taxi",
    "wof:placetype":"venue"
},
  "geometry": {"coordinates":[-73.616737,41.394522],"type":"Point"}
}