{
  "type": "Feature",
  "properties": {
    "addr:full":"4 Forest Ct Huntington NY 11743",
    "addr:housenumber":"4",
    "addr:postcode":"11743",
    "addr:street":"Forest Ct",
    "iso:country":"US",
    "sg:address":"4 Forest Ct",
    "sg:city":"Huntington",
    "sg:classifiers":[
        {
            "category":"Wholesale",
            "subcategory":"Plants",
            "type":"Manufacturing & Wholesale Goods"
        }
    ],
    "sg:phone":"+1 631 421 9499",
    "sg:postcode":"11743",
    "sg:province":"NY",
    "sg:tags":[
        "flower",
        "supply"
    ],
    "wof:name":"Decorative Traditions Inc",
    "wof:placetype":"venue"
},
  "geometry": {"coordinates":[-73.411948,40.892489],"type":"Point"}
}