{
  "type": "Feature",
  "properties": {
    "addr:full":"16 Main St Hempstead NY 11550",
    "addr:housenumber":"16",
    "addr:postcode":"11550",
    "addr:street":"Main St",
    "iso:country":"US",
    "sg:address":"16 Main St",
    "sg:city":"Hempstead",
    "sg:classifiers":[
        {
            "category":"Health Services",
            "subcategory":"Hospital",
            "type":"Services"
        }
    ],
    "sg:phone":"+1 516 485 4300",
    "sg:postcode":"11550",
    "sg:province":"NY",
    "sg:tags":[
        "mental"
    ],
    "wof:name":"Mental Health Assoc Of Nassa",
    "wof:placetype":"venue"
},
  "geometry": {"coordinates":[-73.62427099999999,40.707764],"type":"Point"}
}