{
  "type": "Feature",
  "properties": {
    "iso:country":"US",
    "sg:address":"6534 Town Hall Rd",
    "sg:city":"Auburn",
    "sg:classifiers":[
        {
            "category":"Professional",
            "subcategory":"Business Services",
            "type":"Services"
        }
    ],
    "sg:phone":"+1 315 252 0544",
    "sg:postcode":"13021",
    "sg:province":"NY",
    "sg:tags":[
        "auctioneer"
    ],
    "wof:name":"Tom Defurio",
    "wof:placetype":"venue"
},
  "geometry": {"coordinates":[-76.50851,42.928135],"type":"Point"}
}