{
  "type": "Feature",
  "properties": {
    "addr:full":"2115 Ave J Brooklyn NY 11210",
    "addr:housenumber":"2115",
    "addr:postcode":"11210",
    "addr:street":"Ave J",
    "iso:country":"US",
    "sg:address":"2115 Ave J",
    "sg:city":"Brooklyn",
    "sg:classifiers":[
        {
            "category":"Autos & Motor Vehicles",
            "subcategory":"Auto Supplies",
            "type":"Retail Goods"
        }
    ],
    "sg:phone":"+1 917 642 6861",
    "sg:postcode":"11210",
    "sg:province":"NY",
    "sg:tags":[
        "automobile",
        "used"
    ],
    "wof:name":"S Auto Sales Wholesale",
    "wof:placetype":"venue"
},
  "geometry": {"coordinates":[-73.95454599999999,40.626005],"type":"Point"}
}