{
  "type": "Feature",
  "properties": {
    "iso:country":"US",
    "sg:address":"501 Lexington Ave",
    "sg:city":"New York",
    "sg:classifiers":[
        {
            "category":"Retail",
            "subcategory":"Repair Shop",
            "type":"Services"
        }
    ],
    "sg:phone":"+1 212 792 9411",
    "sg:postcode":"10017",
    "sg:province":"NY",
    "sg:tags":[
        "lock",
        "locksmith"
    ],
    "wof:name":"24 Hour Locksmith Eastside",
    "wof:placetype":"venue"
},
  "geometry": {"coordinates":[-73.973276,40.755243],"type":"Point"}
}