{
  "type": "Feature",
  "properties": {
    "iso:country":"US",
    "sg:address":"11668 Broadway St",
    "sg:city":"Alden",
    "sg:classifiers":[
        {
            "category":"Bars & Pubs",
            "type":"Food & Drink"
        }
    ],
    "sg:phone":"+1   ",
    "sg:postcode":"14004",
    "sg:province":"NY",
    "sg:tags":[
        "drinking"
    ],
    "wof:name":"Poplar Inn",
    "wof:placetype":"venue"
},
  "geometry": {"coordinates":[-78.544968,42.892582],"type":"Point"}
}