{
  "type": "Feature",
  "properties": {
    "iso:country":"US",
    "sg:address":"315 Madison Avenue Suite 511",
    "sg:city":"New York",
    "sg:classifiers":[
        {
            "category":"Health Services",
            "subcategory":"Chiropractor",
            "type":"Services"
        }
    ],
    "sg:phone":"+1 212 883 8700",
    "sg:postcode":"10017",
    "sg:province":"NY",
    "sg:website":"www.lambchiropractic.com",
    "wof:name":"Lamb Chiropractic & Wellness",
    "wof:placetype":"venue"
},
  "geometry": {"coordinates":[-73.979294,40.752544],"type":"Point"}
}