{
  "type": "Feature",
  "properties": {
    "addr:full":"7610 State Hwy 68 Ogdensburg NY 13669",
    "addr:housenumber":"7610",
    "addr:postcode":"13669",
    "addr:street":"State Hwy 68",
    "iso:country":"US",
    "sg:address":"7610 State Hwy 68",
    "sg:city":"Ogdensburg",
    "sg:classifiers":[
        {
            "category":"Building & Trades",
            "subcategory":"Equipment Rental",
            "type":"Services"
        }
    ],
    "sg:phone":"+1 315 393 3230",
    "sg:postcode":"13669",
    "sg:province":"NY",
    "sg:tags":[
        "heavy",
        "construction"
    ],
    "wof:name":"Collins Equipment Corp",
    "wof:placetype":"venue"
},
  "geometry": {"coordinates":[-75.46925,44.689235],"type":"Point"}
}