{
  "type": "Feature",
  "properties": {
    "addr:full":"34 Court St Lancaster NY 14086",
    "addr:housenumber":"34",
    "addr:postcode":"14086",
    "addr:street":"Court St",
    "iso:country":"US",
    "sg:address":"34 Court St",
    "sg:city":"Lancaster",
    "sg:classifiers":[
        {
            "category":"Building & Trades",
            "subcategory":"Construction",
            "type":"Services"
        }
    ],
    "sg:phone":"+1 716 681 2222",
    "sg:postcode":"14086",
    "sg:province":"NY",
    "sg:tags":[
        "house",
        "nonresidential"
    ],
    "wof:name":"Weig Enterprises",
    "wof:placetype":"venue"
},
  "geometry": {"coordinates":[-78.661691,42.899259],"type":"Point"}
}