{
  "type": "Feature",
  "properties": {
    "addr:full":"40 Kisco Ave Mt Kisco NY 10549",
    "addr:housenumber":"40",
    "addr:postcode":"10549",
    "addr:street":"Kisco Ave Mt Kisco",
    "iso:country":"US",
    "sg:address":"40 Kisco Ave",
    "sg:city":"Mt Kisco",
    "sg:classifiers":[
        {
            "category":"Health Services",
            "subcategory":"Health Practitioner",
            "type":"Services"
        }
    ],
    "sg:phone":"+1 914 241 0106",
    "sg:postcode":"10549",
    "sg:province":"NY",
    "sg:tags":[
        "therapist",
        "physical"
    ],
    "wof:name":"Sports Physical Therapy-Ny",
    "wof:placetype":"venue"
},
  "geometry": {"coordinates":[-73.72835000000001,41.210999],"type":"Point"}
}