{
  "type": "Feature",
  "properties": {
    "addr:full":"45 E Main St Patchogue NY 11772",
    "addr:housenumber":"45",
    "addr:postcode":"11772",
    "addr:street":"E Main St",
    "iso:country":"US",
    "sg:address":"45 E Main St",
    "sg:city":"Patchogue",
    "sg:classifiers":[
        {
            "category":"Building & Trades",
            "subcategory":"Construction",
            "type":"Services"
        }
    ],
    "sg:phone":"+1 631 475 8009",
    "sg:postcode":"11772",
    "sg:province":"NY",
    "sg:tags":[
        "company"
    ],
    "wof:name":"RJT Construction Corp",
    "wof:placetype":"venue"
},
  "geometry": {"coordinates":[-73.01308299999999,40.765771],"type":"Point"}
}