{
  "type": "Feature",
  "properties": {
    "addr:full":"2120 36th Ave Long Island City NY 11106",
    "addr:housenumber":"2120",
    "addr:postcode":"11106",
    "addr:street":"36Th Ave",
    "iso:country":"US",
    "sg:address":"2120 36th Ave",
    "sg:city":"Long Island City",
    "sg:classifiers":[
        {
            "category":"Retail",
            "subcategory":"Laundry & Dry Cleaning",
            "type":"Services"
        }
    ],
    "sg:phone":"+1 718 482 8842",
    "sg:postcode":"11106",
    "sg:province":"NY",
    "wof:name":"Yoon Young",
    "wof:placetype":"venue"
},
  "geometry": {"coordinates":[-73.936671,40.759679],"type":"Point"}
}