{
  "type": "Feature",
  "properties": {
    "iso:country":"US",
    "sg:address":"451 Main St",
    "sg:city":"Armonk",
    "sg:classifiers":[
        {
            "category":"Local Transit",
            "type":"Transportation"
        }
    ],
    "sg:phone":"+1   ",
    "sg:postcode":"10504",
    "sg:province":"NY",
    "sg:tags":[
        "limousine"
    ],
    "wof:name":"Armonk Limousine Service",
    "wof:placetype":"venue"
},
  "geometry": {"coordinates":[-73.71333799999999,41.128449],"type":"Point"}
}