{
  "type": "Feature",
  "properties": {
    "addr:full":"100 5th Ave New York NY 10011",
    "addr:housenumber":"100",
    "addr:postcode":"10011",
    "addr:street":"5Th Ave",
    "iso:country":"US",
    "sg:address":"100 5th Ave",
    "sg:city":"New York",
    "sg:classifiers":[
        {
            "category":"Real Estate",
            "subcategory":"Real Estate Operator",
            "type":"Services"
        }
    ],
    "sg:phone":"+1 212 206 0736",
    "sg:postcode":"10011",
    "sg:province":"NY",
    "sg:tags":[
        "apartment"
    ],
    "wof:name":"Loft 14",
    "wof:placetype":"venue"
},
  "geometry": {"coordinates":[-73.993049,40.73703],"type":"Point"}
}