{
  "type": "Feature",
  "properties": {
    "addr:full":"345 7 Ave New York NY 10001",
    "addr:housenumber":"345",
    "addr:postcode":"10001",
    "addr:street":"7 Ave",
    "iso:country":"US",
    "sg:address":"345 7 Ave",
    "sg:city":"New York",
    "sg:classifiers":[
        {
            "category":"Shopping",
            "subcategory":"Clothing, Apparel, & Fashions",
            "type":"Retail Goods"
        }
    ],
    "sg:phone":"+1 212 967 9669",
    "sg:postcode":"10001",
    "sg:province":"NY",
    "sg:tags":[
        "fur",
        "business"
    ],
    "wof:name":"Georges Papas Furs",
    "wof:placetype":"venue"
},
  "geometry": {"coordinates":[-73.991563,40.749705],"type":"Point"}
}