{
  "type": "Feature",
  "properties": {
    "iso:country":"US",
    "sg:address":"474 Portion Rd",
    "sg:city":"Lake Ronkonkoma",
    "sg:classifiers":[
        {
            "category":"Banks & Credit Unions",
            "subcategory":"Bank",
            "type":"Services"
        },
        {
            "category":"Banks & Credit Unions",
            "subcategory":"Financial Services",
            "type":"Services"
        }
    ],
    "sg:phone":"+1 631 588 1564",
    "sg:postcode":"11779",
    "sg:province":"NY",
    "sg:tags":[
        "broker",
        "mortgage"
    ],
    "wof:name":"TD Bank",
    "wof:placetype":"venue"
},
  "geometry": {"coordinates":[-73.092957,40.829983],"type":"Point"}
}