{
  "type": "Feature",
  "properties": {
    "addr:full":"960 New York Ave Brooklyn NY 11203",
    "addr:housenumber":"960",
    "addr:postcode":"11203",
    "addr:street":"New York Ave",
    "iso:country":"US",
    "sg:address":"960 New York Ave",
    "sg:city":"Brooklyn",
    "sg:classifiers":[
        {
            "category":"Education",
            "subcategory":"School",
            "type":"Public Place"
        }
    ],
    "sg:phone":"+1 718 287 9199",
    "sg:postcode":"11203",
    "sg:province":"NY",
    "wof:name":"Johnson Preparatory School",
    "wof:placetype":"venue"
},
  "geometry": {"coordinates":[-73.94663799999999,40.65015],"type":"Point"}
}