{
  "type": "Feature",
  "properties": {
    "addr:full":"83 Drexhall Ln Rochester NY 14612",
    "addr:housenumber":"83",
    "addr:postcode":"14612",
    "addr:street":"Drexhall Ln",
    "iso:country":"US",
    "sg:address":"83 Drexhall Ln",
    "sg:city":"Rochester",
    "sg:classifiers":[
        {
            "category":"Bars & Pubs",
            "type":"Food & Drink"
        }
    ],
    "sg:phone":"+1 585 266 9559",
    "sg:postcode":"14612",
    "sg:province":"NY",
    "wof:name":"Curley's Saloon",
    "wof:placetype":"venue"
},
  "geometry": {"coordinates":[-77.69338,43.260543],"type":"Point"}
}