{
  "type": "Feature",
  "properties": {
    "addr:full":"185 7th Ave Brooklyn NY 11215",
    "addr:housenumber":"185",
    "addr:postcode":"11215",
    "addr:street":"7Th Ave",
    "iso:country":"US",
    "sg:address":"185 7th Ave",
    "sg:city":"Brooklyn",
    "sg:classifiers":[
        {
            "category":"Personal",
            "subcategory":"Nail Salon",
            "type":"Services"
        }
    ],
    "sg:phone":"+1 718 788 2277",
    "sg:postcode":"11215",
    "sg:province":"NY",
    "wof:name":"Kim Dae Young",
    "wof:placetype":"venue"
},
  "geometry": {"coordinates":[-73.97779800000001,40.6712],"type":"Point"}
}