{
  "type": "Feature",
  "properties": {
    "addr:full":"1623 Eastern Pkwy Schenectady NY 12309",
    "addr:housenumber":"1623",
    "addr:postcode":"12309",
    "addr:street":"Eastern Pkwy",
    "iso:country":"US",
    "sg:address":"1623 Eastern Pkwy",
    "sg:city":"Schenectady",
    "sg:classifiers":[
        {
            "category":"Wholesale",
            "subcategory":"Apparel",
            "type":"Manufacturing & Wholesale Goods"
        }
    ],
    "sg:phone":"+1 518 374 5155",
    "sg:postcode":"12309",
    "sg:province":"NY",
    "sg:tags":[
        "embroidery"
    ],
    "wof:name":"Uv Image Experts",
    "wof:placetype":"venue"
},
  "geometry": {"coordinates":[-73.911816,42.806545],"type":"Point"}
}