{
  "type": "Feature",
  "properties": {
    "iso:country":"US",
    "sg:address":"7 Washington Ave",
    "sg:city":"Albany",
    "sg:classifiers":[
        {
            "category":"Professional",
            "subcategory":"Engineering",
            "type":"Services"
        }
    ],
    "sg:phone":"+1 518 452 3545",
    "sg:postcode":"12205",
    "sg:province":"NY",
    "sg:tags":[
        "engineer"
    ],
    "sg:website":"www.chashsells.com",
    "wof:name":"Charles H Sells Inc",
    "wof:placetype":"venue"
},
  "geometry": {"coordinates":[-73.81649299999999,42.701857],"type":"Point"}
}