{
  "type": "Feature",
  "properties": {
    "iso:country":"US",
    "sg:address":"2066 State Rte 21",
    "sg:city":"Canandaigua",
    "sg:classifiers":[
        {
            "category":"Building & Trades",
            "subcategory":"Construction",
            "type":"Services"
        }
    ],
    "sg:phone":"+1 585 396 5850",
    "sg:postcode":"14424",
    "sg:province":"NY",
    "sg:tags":[
        "excavation",
        "contractor",
        "general"
    ],
    "wof:name":"Hansen Contracting LTD",
    "wof:placetype":"venue"
},
  "geometry": {"coordinates":[-77.22931800000001,42.928292],"type":"Point"}
}