{
  "type": "Feature",
  "properties": {
    "iso:country":"US",
    "sg:address":"137 Broadway",
    "sg:city":"Huntington Sta",
    "sg:classifiers":[
        {
            "category":"Restaurant",
            "type":"Food & Drink"
        }
    ],
    "sg:phone":"+1 631 351 9789",
    "sg:postcode":"11746",
    "sg:province":"NY",
    "wof:name":"Huntington Road House Inc",
    "wof:placetype":"venue"
},
  "geometry": {"coordinates":[-73.407467,40.854409],"type":"Point"}
}