{
  "type": "Feature",
  "properties": {
    "addr:full":"1655 Grand Ave North Baldwin NY 11510",
    "addr:housenumber":"1655",
    "addr:postcode":"11510",
    "addr:street":"Grand Ave North",
    "iso:country":"US",
    "sg:address":"1655 Grand Ave",
    "sg:city":"North Baldwin",
    "sg:classifiers":[
        {
            "category":"Shopping",
            "subcategory":"Pharmacy",
            "type":"Retail Goods"
        }
    ],
    "sg:phone":"+1 516 867 8200",
    "sg:postcode":"11510",
    "sg:province":"NY",
    "wof:name":"Aim Drugs & Surgical",
    "wof:placetype":"venue"
},
  "geometry": {"coordinates":[-73.609908,40.670137],"type":"Point"}
}