{
  "type": "Feature",
  "properties": {
    "addr:full":"516 Rte 25A Mt Sinai NY 11766",
    "addr:housenumber":"516",
    "addr:postcode":"11766",
    "addr:street":"Rte 25A",
    "iso:country":"US",
    "sg:address":"516 Rte 25A",
    "sg:city":"Mt Sinai",
    "sg:classifiers":[
        {
            "category":"Banks & Credit Unions",
            "subcategory":"Bank",
            "type":"Services"
        }
    ],
    "sg:phone":"+1 631 474 4404",
    "sg:postcode":"11766",
    "sg:province":"NY",
    "sg:tags":[
        "loan",
        "real estate"
    ],
    "wof:name":"Columbia Home Loans",
    "wof:placetype":"venue"
},
  "geometry": {"coordinates":[-73.016402,40.93626],"type":"Point"}
}