{
  "type": "Feature",
  "properties": {
    "iso:country":"US",
    "sg:address":"129 Lake Ave",
    "sg:city":"Middletown",
    "sg:classifiers":[
        {
            "category":"Restaurant",
            "type":"Food & Drink"
        }
    ],
    "sg:phone":"+1   ",
    "sg:postcode":"10940",
    "sg:province":"NY",
    "sg:tags":[
        "eating"
    ],
    "wof:name":"Cuchifrito Las Dos Hermanas",
    "wof:placetype":"venue"
},
  "geometry": {"coordinates":[-74.434533,41.457699],"type":"Point"}
}