{
  "type": "Feature",
  "properties": {
    "addr:full":"1704 Amsterdam Ave New York NY 10031",
    "addr:housenumber":"1704",
    "addr:postcode":"10031",
    "addr:street":"Amsterdam Ave",
    "iso:country":"US",
    "sg:address":"1704 Amsterdam Ave",
    "sg:city":"New York",
    "sg:classifiers":[
        {
            "category":"Shopping",
            "subcategory":"Clothing, Apparel, & Fashions",
            "type":"Retail Goods"
        }
    ],
    "sg:phone":"+1 212 368 1151",
    "sg:postcode":"10031",
    "sg:province":"NY",
    "wof:name":"B T Discounts",
    "wof:placetype":"venue"
},
  "geometry": {"coordinates":[-73.94775300000001,40.825121],"type":"Point"}
}