{
  "type": "Feature",
  "properties": {
    "iso:country":"US",
    "sg:address":"10 E Genesee St",
    "sg:city":"Auburn",
    "sg:classifiers":[
        {
            "category":"Restaurant",
            "type":"Food & Drink"
        }
    ],
    "sg:phone":"+1   ",
    "sg:postcode":"13021",
    "sg:province":"NY",
    "sg:tags":[
        "eating"
    ],
    "wof:name":"Dauts",
    "wof:placetype":"venue"
},
  "geometry": {"coordinates":[-76.563113,42.933028],"type":"Point"}
}