{
  "type": "Feature",
  "properties": {
    "iso:country":"US",
    "sg:address":"2900 Southern Blvd",
    "sg:city":"Bronx",
    "sg:classifiers":[
        {
            "category":"Restaurant",
            "type":"Food & Drink"
        }
    ],
    "sg:phone":"+1 718 220 0300",
    "sg:postcode":"10460",
    "sg:province":"NY",
    "sg:tags":[
        "caterer"
    ],
    "wof:name":"Abigail Kirsch At The Ny Btncl",
    "wof:placetype":"venue"
},
  "geometry": {"coordinates":[-73.88087299999999,40.857698],"type":"Point"}
}