{
  "type": "Feature",
  "properties": {
    "iso:country":"US",
    "sg:address":"1169 Woods Rd",
    "sg:city":"Germantown",
    "sg:classifiers":[
        {
            "category":"Building & Trades",
            "subcategory":"Construction",
            "type":"Services"
        }
    ],
    "sg:phone":"+1 518 537 5191",
    "sg:postcode":"12526",
    "sg:province":"NY",
    "sg:tags":[
        "carpentry",
        "contractor"
    ],
    "wof:name":"Creative Cabinet & Rmdlg Co",
    "wof:placetype":"venue"
},
  "geometry": {"coordinates":[-73.896698,42.128138],"type":"Point"}
}