{
  "type": "Feature",
  "properties": {
    "iso:country":"US",
    "sg:address":"20 Downs Rd",
    "sg:city":"Monticello",
    "sg:classifiers":[
        {
            "category":"Wholesale",
            "subcategory":"Sporting Goods",
            "type":"Manufacturing & Wholesale Goods"
        }
    ],
    "sg:phone":"+1 845 794 9521",
    "sg:postcode":"12701",
    "sg:province":"NY",
    "wof:name":"Paintball Madness",
    "wof:placetype":"venue"
},
  "geometry": {"coordinates":[-74.636021,41.645385],"type":"Point"}
}