{
  "type": "Feature",
  "properties": {
    "iso:country":"US",
    "sg:address":"150 Sullivan St",
    "sg:city":"New York",
    "sg:classifiers":[
        {
            "category":"Shopping",
            "subcategory":"Used Merchandise",
            "type":"Retail Goods"
        }
    ],
    "sg:phone":"+1 212 982 5699",
    "sg:postcode":"10012",
    "sg:province":"NY",
    "sg:tags":[
        "antique"
    ],
    "wof:name":"Depression Modern",
    "wof:placetype":"venue"
},
  "geometry": {"coordinates":[-74.001924,40.726947],"type":"Point"}
}