{
  "type": "Feature",
  "properties": {
    "addr:full":"8251 New Floyd Rd Rome NY 13440",
    "addr:housenumber":"8251",
    "addr:postcode":"13440",
    "addr:street":"New Floyd Rd",
    "iso:country":"US",
    "sg:address":"8251 New Floyd Rd",
    "sg:city":"Rome",
    "sg:classifiers":[
        {
            "category":"Manufacturing",
            "subcategory":"Retail Goods",
            "type":"Manufacturing & Wholesale Goods"
        }
    ],
    "sg:phone":"+1   ",
    "sg:postcode":"13440",
    "sg:province":"NY",
    "sg:tags":[
        "product",
        "mfg",
        "supply"
    ],
    "wof:name":"Great Scott Lawn",
    "wof:placetype":"venue"
},
  "geometry": {"coordinates":[-75.336315,43.218486],"type":"Point"}
}