{
  "type": "Feature",
  "properties": {
    "addr:full":"1071 Stoneleigh Ave Carmel NY 10512",
    "addr:housenumber":"1071",
    "addr:postcode":"10512",
    "addr:street":"Stoneleigh Ave",
    "iso:country":"US",
    "sg:address":"1071 Stoneleigh Ave",
    "sg:city":"Carmel",
    "sg:classifiers":[
        {
            "category":"Personal",
            "subcategory":"Hair Removal",
            "type":"Services"
        }
    ],
    "sg:phone":"+1 845 225 0011",
    "sg:postcode":"10512",
    "sg:province":"NY",
    "sg:website":"www.stoneleighmedispa.com",
    "wof:name":"Stoneleigh Medi Spa",
    "wof:placetype":"venue"
},
  "geometry": {"coordinates":[-73.667911,41.41241],"type":"Point"}
}