{
  "type": "Feature",
  "properties": {
    "addr:full":"170 William St Roslyn NY 11575",
    "addr:housenumber":"170",
    "addr:postcode":"11575",
    "addr:street":"William St",
    "iso:country":"US",
    "sg:address":"170 William St",
    "sg:city":"Roslyn",
    "sg:classifiers":[
        {
            "category":"Health Services",
            "subcategory":"Doctor",
            "type":"Services"
        }
    ],
    "sg:phone":"+1 212 312 5243",
    "sg:postcode":"11575",
    "sg:province":"NY",
    "sg:tags":[
        "medical"
    ],
    "wof:name":"Anesthesiology Department",
    "wof:placetype":"venue"
},
  "geometry": {"coordinates":[-73.589416,40.681874],"type":"Point"}
}