{
  "type": "Feature",
  "properties": {
    "addr:full":"362 5th Avenue Lbby New York NY 10001",
    "addr:housenumber":"362",
    "addr:postcode":"10001",
    "addr:street":"5Th Avenue",
    "iso:country":"US",
    "sg:address":"362 5th Avenue Lbby",
    "sg:city":"New York",
    "sg:classifiers":[
        {
            "category":"Professional",
            "subcategory":"Lawyer & Legal Services",
            "type":"Services"
        }
    ],
    "sg:phone":"+1 212 594 6098",
    "sg:postcode":"10001",
    "sg:province":"NY",
    "wof:name":"Geller Tatyana Lawyer",
    "wof:placetype":"venue"
},
  "geometry": {"coordinates":[-73.984201,40.748853],"type":"Point"}
}