{
  "type": "Feature",
  "properties": {
    "iso:country":"US",
    "sg:address":"137 Kirkland Ave",
    "sg:city":"Clinton",
    "sg:classifiers":[
        {
            "category":"Wholesale",
            "subcategory":"Machinery & Supplies",
            "type":"Manufacturing & Wholesale Goods"
        }
    ],
    "sg:phone":"+1 315 853 5604",
    "sg:postcode":"13323",
    "sg:province":"NY",
    "sg:tags":[
        "hardware",
        "industrial"
    ],
    "wof:name":"R K C Products",
    "wof:placetype":"venue"
},
  "geometry": {"coordinates":[-75.37182799999999,43.069389],"type":"Point"}
}