{
  "type": "Feature",
  "properties": {
    "iso:country":"US",
    "sg:address":"92 Oak St",
    "sg:city":"New Canaan",
    "sg:classifiers":[
        {
            "category":"Professional",
            "subcategory":"Accounting & Tax Preparation",
            "type":"Services"
        }
    ],
    "sg:phone":"+1   ",
    "sg:postcode":"06840",
    "sg:province":"NY",
    "wof:name":"Portanova Jeffrey J",
    "wof:placetype":"venue"
},
  "geometry": {"coordinates":[-73.487351,41.141999],"type":"Point"}
}