{
  "type": "Feature",
  "properties": {
    "iso:country":"US",
    "sg:address":"176 Warwick St",
    "sg:city":"Brooklyn",
    "sg:classifiers":[
        {
            "category":"Real Estate",
            "subcategory":"Real Estate Agent",
            "type":"Services"
        }
    ],
    "sg:phone":"+1   ",
    "sg:postcode":"11207",
    "sg:province":"NY",
    "sg:tags":[
        "travel",
        "agency"
    ],
    "wof:name":"Lamonts Real Estate",
    "wof:placetype":"venue"
},
  "geometry": {"coordinates":[-73.88749900000001,40.679711],"type":"Point"}
}