{
  "type": "Feature",
  "properties": {
    "addr:full":"4863 W Lake Rd Dunkirk NY 14048",
    "addr:housenumber":"4863",
    "addr:postcode":"14048",
    "addr:street":"W Lake Rd",
    "iso:country":"US",
    "sg:address":"4863 W Lake Rd",
    "sg:city":"Dunkirk",
    "sg:classifiers":[
        {
            "category":"Retail",
            "subcategory":"Car Wash",
            "type":"Services"
        }
    ],
    "sg:phone":"+1 716 366 5175",
    "sg:postcode":"14048",
    "sg:province":"NY",
    "sg:tags":[
        "automobile",
        "detail",
        "clean"
    ],
    "wof:name":"Auto Trend Detailing",
    "wof:placetype":"venue"
},
  "geometry": {"coordinates":[-79.376238,42.462417],"type":"Point"}
}