{
  "type": "Feature",
  "properties": {
    "addr:full":"72 Avenue O Brooklyn NY 11204",
    "addr:housenumber":"72",
    "addr:postcode":"11204",
    "addr:street":"Avenue O",
    "iso:country":"US",
    "sg:address":"72 Avenue O",
    "sg:city":"Brooklyn",
    "sg:classifiers":[
        {
            "category":"Retail",
            "subcategory":"Laundry & Dry Cleaning",
            "type":"Services"
        }
    ],
    "sg:phone":"+1 718 236 2206",
    "sg:postcode":"11204",
    "sg:province":"NY",
    "wof:name":"Diamond Cleaners",
    "wof:placetype":"venue"
},
  "geometry": {"coordinates":[-73.98249800000001,40.610298],"type":"Point"}
}