{
  "type": "Feature",
  "properties": {
    "addr:full":"4701 Queens Boulevard Sunnyside NY 11104",
    "addr:housenumber":"4701",
    "addr:postcode":"11104",
    "addr:street":"Queens Boulevard",
    "iso:country":"US",
    "sg:address":"4701 Queens Boulevard",
    "sg:city":"Sunnyside",
    "sg:classifiers":[
        {
            "category":"Health Services",
            "subcategory":"Doctor",
            "type":"Services"
        }
    ],
    "sg:phone":"+1 718 784 7500",
    "sg:postcode":"11104",
    "sg:province":"NY",
    "wof:name":"Balaescu Mihaela MD",
    "wof:placetype":"venue"
},
  "geometry": {"coordinates":[-73.917725,40.743219],"type":"Point"}
}