{
  "type": "Feature",
  "properties": {
    "iso:country":"US",
    "sg:address":"3117 Webster Ave",
    "sg:city":"Bronx",
    "sg:classifiers":[
        {
            "category":"Shopping",
            "subcategory":"Used Merchandise",
            "type":"Retail Goods"
        }
    ],
    "sg:phone":"+1 718 405 1399",
    "sg:postcode":"10467",
    "sg:province":"NY",
    "sg:tags":[
        "shop",
        "thrift"
    ],
    "wof:name":"Goodwill Industries",
    "wof:placetype":"venue"
},
  "geometry": {"coordinates":[-73.875095,40.87288],"type":"Point"}
}