{
  "type": "Feature",
  "properties": {
    "iso:country":"US",
    "sg:address":"57 Montague St",
    "sg:city":"Brooklyn",
    "sg:classifiers":[
        {
            "category":"Professional",
            "subcategory":"Lawyer & Legal Services",
            "type":"Services"
        }
    ],
    "sg:phone":"+1 888 234 4332",
    "sg:postcode":"11201",
    "sg:province":"NY",
    "wof:name":"Creative Synergy",
    "wof:placetype":"venue"
},
  "geometry": {"coordinates":[-73.997,40.695683],"type":"Point"}
}