{
  "type": "Feature",
  "properties": {
    "addr:full":"9592 Hayes Rd Marcy NY 13403",
    "addr:housenumber":"9592",
    "addr:postcode":"13403",
    "addr:street":"Hayes Rd",
    "iso:country":"US",
    "sg:address":"9592 Hayes Rd",
    "sg:city":"Marcy",
    "sg:classifiers":[
        {
            "category":"Organizations",
            "subcategory":"Membership Organization",
            "type":"Services"
        }
    ],
    "sg:phone":"+1 315 768 1007",
    "sg:postcode":"13403",
    "sg:province":"NY",
    "wof:name":"United Cerebral Palsy",
    "wof:placetype":"venue"
},
  "geometry": {"coordinates":[-75.28179299999999,43.161691],"type":"Point"}
}