{
  "type": "Feature",
  "properties": {
    "addr:full":"76 Beach Rd Stony Point NY 10980",
    "addr:housenumber":"76",
    "addr:postcode":"10980",
    "addr:street":"Beach Rd",
    "iso:country":"US",
    "sg:address":"76 Beach Rd",
    "sg:city":"Stony Point",
    "sg:classifiers":[
        {
            "category":"Retail",
            "subcategory":"Repair Shop",
            "type":"Services"
        }
    ],
    "sg:phone":"+1   ",
    "sg:postcode":"10980",
    "sg:province":"NY",
    "wof:name":"T Z Marine Service",
    "wof:placetype":"venue"
},
  "geometry": {"coordinates":[-73.97465,41.227992],"type":"Point"}
}