{
  "type": "Feature",
  "properties": {
    "iso:country":"US",
    "sg:address":"2204 W Genesee St",
    "sg:city":"Syracuse",
    "sg:classifiers":[
        {
            "category":"Restaurant",
            "type":"Food & Drink"
        }
    ],
    "sg:phone":"+1 315 468 0011",
    "sg:postcode":"13219",
    "sg:province":"NY",
    "wof:name":"San Remo Pizzeria",
    "wof:placetype":"venue"
},
  "geometry": {"coordinates":[-76.198055,43.047573],"type":"Point"}
}