{
  "type": "Feature",
  "properties": {
    "addr:full":"170 Ave B New York NY 10009",
    "addr:housenumber":"170",
    "addr:postcode":"10009",
    "addr:street":"Ave B",
    "iso:country":"US",
    "sg:address":"170 Ave B",
    "sg:city":"New York",
    "sg:classifiers":[
        {
            "category":"Shopping",
            "type":"Retail Goods"
        }
    ],
    "sg:phone":"+1 212 228 1232",
    "sg:postcode":"10009",
    "sg:province":"NY",
    "sg:website":"www.tokyorebel.com/",
    "wof:name":"Tokyo Rebel",
    "wof:placetype":"venue"
},
  "geometry": {"coordinates":[-73.979839,40.727316],"type":"Point"}
}