{
  "type": "Feature",
  "properties": {
    "iso:country":"US",
    "sg:address":"122 E Seneca St",
    "sg:city":"Manlius",
    "sg:classifiers":[
        {
            "category":"Social Services",
            "subcategory":"Child Care",
            "type":"Services"
        }
    ],
    "sg:phone":"+1   ",
    "sg:postcode":"13104",
    "sg:province":"NY",
    "sg:tags":[
        "day"
    ],
    "wof:name":"Clic Community Learning & Info",
    "wof:placetype":"venue"
},
  "geometry": {"coordinates":[-75.977924,43.001453],"type":"Point"}
}