{
  "type": "Feature",
  "properties": {
    "addr:full":"11355 Genesee St Alden NY 14004",
    "addr:housenumber":"11355",
    "addr:postcode":"14004",
    "addr:street":"Genesee St",
    "iso:country":"US",
    "sg:address":"11355 Genesee St",
    "sg:city":"Alden",
    "sg:classifiers":[
        {
            "category":"Real Estate",
            "subcategory":"Developer",
            "type":"Services"
        }
    ],
    "sg:phone":"+1 716 937 7924",
    "sg:postcode":"14004",
    "sg:province":"NY",
    "sg:tags":[
        "cemetery"
    ],
    "wof:name":"Salem Cemetery Society Inc",
    "wof:placetype":"venue"
},
  "geometry": {"coordinates":[-78.564029,42.944667],"type":"Point"}
}