{
  "type": "Feature",
  "properties": {
    "iso:country":"US",
    "sg:address":"2005 Ocean Ave",
    "sg:city":"Brooklyn",
    "sg:classifiers":[
        {
            "category":"Health Services",
            "subcategory":"Doctor",
            "type":"Services"
        }
    ],
    "sg:phone":"+1 718 375 8032",
    "sg:postcode":"11230",
    "sg:province":"NY",
    "wof:name":"Zamdborg Yury MD",
    "wof:placetype":"venue"
},
  "geometry": {"coordinates":[-73.953903,40.613201],"type":"Point"}
}