{
  "type": "Feature",
  "properties": {
    "addr:full":"7 North Rd S Glens Falls NY 12803",
    "addr:housenumber":"7",
    "addr:postcode":"12803",
    "addr:street":"North Rd",
    "iso:country":"US",
    "sg:address":"7 North Rd",
    "sg:city":"S Glens Falls",
    "sg:classifiers":[
        {
            "category":"Building & Trades",
            "subcategory":"Construction",
            "type":"Services"
        }
    ],
    "sg:phone":"+1 518 792 4809",
    "sg:postcode":"12803",
    "sg:province":"NY",
    "sg:tags":[
        "roofing",
        "contractor"
    ],
    "wof:name":"Varney Contracting Co",
    "wof:placetype":"venue"
},
  "geometry": {"coordinates":[-73.65237999999999,43.287934],"type":"Point"}
}