{
  "type": "Feature",
  "properties": {
    "addr:full":"24 W Carver St Huntington NY 11743",
    "addr:housenumber":"24",
    "addr:postcode":"11743",
    "addr:street":"W Carver St",
    "iso:country":"US",
    "sg:address":"24 W Carver St",
    "sg:city":"Huntington",
    "sg:classifiers":[
        {
            "category":"Banks & Credit Unions",
            "subcategory":"Bank",
            "type":"Services"
        }
    ],
    "sg:phone":"+1 631 427 3100",
    "sg:postcode":"11743",
    "sg:province":"NY",
    "wof:name":"Wells Fargo",
    "wof:placetype":"venue"
},
  "geometry": {"coordinates":[-73.427159,40.868951],"type":"Point"}
}