{
  "type": "Feature",
  "properties": {
    "addr:full":"506 Hawleyton Rd Binghamton NY 13903",
    "addr:housenumber":"506",
    "addr:postcode":"13903",
    "addr:street":"Hawleyton Rd",
    "iso:country":"US",
    "sg:address":"506 Hawleyton Rd",
    "sg:city":"Binghamton",
    "sg:classifiers":[
        {
            "category":"Building & Trades",
            "subcategory":"Construction",
            "type":"Services"
        }
    ],
    "sg:phone":"+1 607 669 4208",
    "sg:postcode":"13903",
    "sg:province":"NY",
    "sg:tags":[
        "well",
        "drilling"
    ],
    "wof:name":"Cline & Son Well Drilling",
    "wof:placetype":"venue"
},
  "geometry": {"coordinates":[-75.955923,41.999916],"type":"Point"}
}