{
  "type": "Feature",
  "properties": {
    "iso:country":"US",
    "sg:address":"55 Union Rd",
    "sg:city":"Spring Valley",
    "sg:classifiers":[
        {
            "category":"Wholesale",
            "subcategory":"Dairy",
            "type":"Manufacturing & Wholesale Goods"
        }
    ],
    "sg:phone":"+1 845 425 6455",
    "sg:postcode":"10977",
    "sg:province":"NY",
    "sg:tags":[
        "product"
    ],
    "wof:name":"Spring Valley Dairy Corp",
    "wof:placetype":"venue"
},
  "geometry": {"coordinates":[-74.048559,41.121818],"type":"Point"}
}