{
  "type": "Feature",
  "properties": {
    "addr:full":"64 W Main St East Islip NY 11730",
    "addr:housenumber":"64",
    "addr:postcode":"11730",
    "addr:street":"W Main St",
    "iso:country":"US",
    "sg:address":"64 W Main St",
    "sg:city":"East Islip",
    "sg:classifiers":[
        {
            "category":"Real Estate",
            "subcategory":"Real Estate Services",
            "type":"Services"
        },
        {
            "category":"Banks & Credit Unions",
            "subcategory":"Bank",
            "type":"Services"
        }
    ],
    "sg:phone":"+1 631 277 2220",
    "sg:postcode":"11730",
    "sg:province":"NY",
    "sg:tags":[
        "property",
        "management"
    ],
    "sg:website":"coldwellbankermoves.com",
    "wof:name":"Coldwell Banker",
    "wof:placetype":"venue"
},
  "geometry": {"coordinates":[-73.19375100000001,40.730445],"type":"Point"}
}