{
  "type": "Feature",
  "properties": {
    "iso:country":"US",
    "sg:address":"666 W End Ave",
    "sg:city":"New York",
    "sg:classifiers":[
        {
            "category":"Social Services",
            "type":"Services"
        }
    ],
    "sg:phone":"+1   ",
    "sg:postcode":"10025",
    "sg:province":"NY",
    "wof:name":"Barbara I Willinger",
    "wof:placetype":"venue"
},
  "geometry": {"coordinates":[-73.974689,40.793037],"type":"Point"}
}