{
  "type": "Feature",
  "properties": {
    "addr:full":"6 Lake Shore Dr W Dunkirk NY 14048",
    "addr:housenumber":"6",
    "addr:postcode":"14048",
    "addr:street":"Lake Shore Dr W",
    "iso:country":"US",
    "sg:address":"6 Lake Shore Dr W",
    "sg:city":"Dunkirk",
    "sg:classifiers":[
        {
            "category":"Restaurant",
            "type":"Food & Drink"
        }
    ],
    "sg:phone":"+1 716 366 4187",
    "sg:postcode":"14048",
    "sg:province":"NY",
    "wof:name":"Demetri's On The Lake",
    "wof:placetype":"venue"
},
  "geometry": {"coordinates":[-79.33582800000001,42.487287],"type":"Point"}
}