{
  "type": "Feature",
  "properties": {
    "iso:country":"US",
    "sg:address":"76 Joan Dr",
    "sg:city":"Yonkers",
    "sg:classifiers":[
        {
            "category":"Manufacturing",
            "subcategory":"Buildings",
            "type":"Manufacturing & Wholesale Goods"
        },
        {
            "category":"Building & Trades",
            "subcategory":"Construction",
            "type":"Services"
        }
    ],
    "sg:phone":"+1 914 207 7843",
    "sg:postcode":"10704",
    "sg:province":"NY",
    "sg:tags":[
        "home",
        "builder",
        "contractor"
    ],
    "wof:name":"Broadford Home Improvement",
    "wof:placetype":"venue"
},
  "geometry": {"coordinates":[-73.85355,40.922694],"type":"Point"}
}