{
  "type": "Feature",
  "properties": {
    "iso:country":"US",
    "sg:address":"1597 Ridge Rd W",
    "sg:city":"Rochester",
    "sg:classifiers":[
        {
            "category":"Taxi",
            "type":"Transportation"
        }
    ],
    "sg:phone":"+1 585 663 4444",
    "sg:postcode":"14615",
    "sg:province":"NY",
    "sg:tags":[
        "taxicab"
    ],
    "wof:name":"Greecetown Taxi",
    "wof:placetype":"venue"
},
  "geometry": {"coordinates":[-77.66768999999999,43.205294],"type":"Point"}
}