{
  "type": "Feature",
  "properties": {
    "iso:country":"US",
    "sg:address":"677 Dutchess Tpke",
    "sg:city":"Poughkeepsie",
    "sg:classifiers":[
        {
            "category":"Real Estate",
            "subcategory":"Real Estate Agent",
            "type":"Services"
        },
        {
            "category":"Real Estate",
            "subcategory":"Real Estate Operator",
            "type":"Services"
        }
    ],
    "sg:phone":"+1 845 454 4119",
    "sg:postcode":"12603",
    "sg:province":"NY",
    "sg:tags":[
        "building",
        "nonresidential"
    ],
    "wof:name":"Delking Properties LLC",
    "wof:placetype":"venue"
},
  "geometry": {"coordinates":[-73.841854,41.726223],"type":"Point"}
}