{
  "type": "Feature",
  "properties": {
    "iso:country":"US",
    "sg:address":"1619 Daboll Rd",
    "sg:city":"Clyde",
    "sg:classifiers":[
        {
            "category":"Wholesale",
            "subcategory":"Durable Goods & Equipment",
            "type":"Manufacturing & Wholesale Goods"
        }
    ],
    "sg:phone":"+1 315 923 2960",
    "sg:postcode":"14433",
    "sg:province":"NY",
    "sg:tags":[
        "fire",
        "extinguisher"
    ],
    "wof:name":"Millennium Fire Extinguishers",
    "wof:placetype":"venue"
},
  "geometry": {"coordinates":[-76.828295,43.072122],"type":"Point"}
}