{
  "type": "Feature",
  "properties": {
    "addr:full":"504 E 74 St New York NY 10021",
    "addr:housenumber":"504;74",
    "addr:postcode":"10021",
    "addr:street":"E;St",
    "iso:country":"US",
    "sg:address":"504 E 74 St",
    "sg:city":"New York",
    "sg:classifiers":[
        {
            "category":"Real Estate",
            "subcategory":"Real Estate Operator",
            "type":"Services"
        }
    ],
    "sg:phone":"+1 212 734 7744",
    "sg:postcode":"10021",
    "sg:province":"NY",
    "sg:tags":[
        "building",
        "commercial",
        "operates"
    ],
    "wof:name":"C/O Pambartim Realty Corp",
    "wof:placetype":"venue"
},
  "geometry": {"coordinates":[-73.950361,40.767078],"type":"Point"}
}