{
  "type": "Feature",
  "properties": {
    "addr:full":"18 Richardson St Brooklyn NY 11211",
    "addr:housenumber":"18",
    "addr:postcode":"11211",
    "addr:street":"Richardson St",
    "iso:country":"US",
    "sg:address":"18 Richardson St",
    "sg:city":"Brooklyn",
    "sg:classifiers":[
        {
            "category":"Building & Trades",
            "subcategory":"Construction",
            "type":"Services"
        }
    ],
    "sg:phone":"+1 718 387 1391",
    "sg:postcode":"11211",
    "sg:province":"NY",
    "sg:tags":[
        "woodworker"
    ],
    "wof:name":"Peter Billow Fine Woodworking",
    "wof:placetype":"venue"
},
  "geometry": {"coordinates":[-73.950594,40.718156],"type":"Point"}
}