{
  "type": "Feature",
  "properties": {
    "addr:full":"782 Rogers Avenue Brooklyn NY 11226",
    "addr:housenumber":"782",
    "addr:postcode":"11226",
    "addr:street":"Rogers Avenue",
    "iso:country":"US",
    "sg:address":"782 Rogers Avenue",
    "sg:city":"Brooklyn",
    "sg:classifiers":[
        {
            "category":"Social Services",
            "subcategory":"Child Care",
            "type":"Services"
        },
        {
            "category":"Education",
            "subcategory":"Preschool",
            "type":"Public Place"
        },
        {
            "category":"Education",
            "subcategory":"School",
            "type":"Public Place"
        }
    ],
    "sg:phone":"+1 718 462 5009",
    "sg:postcode":"11226",
    "sg:province":"NY",
    "sg:tags":[
        "elementary",
        "day"
    ],
    "wof:name":"First Impressions Nursery School",
    "wof:placetype":"venue"
},
  "geometry": {"coordinates":[-73.952747,40.651883],"type":"Point"}
}