{
  "type": "Feature",
  "properties": {
    "iso:country":"US",
    "sg:address":"309 W 49 St",
    "sg:city":"New York",
    "sg:classifiers":[
        {
            "category":"Communications",
            "subcategory":"Film & Video Production",
            "type":"Services"
        }
    ],
    "sg:phone":"+1 212 237 5326",
    "sg:postcode":"10019",
    "sg:province":"NY",
    "sg:tags":[
        "television",
        "commercial"
    ],
    "wof:name":"Eye Patch Productions",
    "wof:placetype":"venue"
},
  "geometry": {"coordinates":[-73.989189,40.762827],"type":"Point"}
}