{
  "type": "Feature",
  "properties": {
    "addr:full":"385 Cleveland Dr Buffalo NY 14215",
    "addr:housenumber":"385",
    "addr:postcode":"14215",
    "addr:street":"Cleveland Dr",
    "iso:country":"US",
    "sg:address":"385 Cleveland Dr",
    "sg:city":"Buffalo",
    "sg:classifiers":[
        {
            "category":"Health Services",
            "subcategory":"Doctor",
            "type":"Services"
        }
    ],
    "sg:phone":"+1 716 834 3344",
    "sg:postcode":"14215",
    "sg:province":"NY",
    "sg:tags":[
        "physician",
        "surgeon"
    ],
    "wof:name":"Chouchani & Sayegh",
    "wof:placetype":"venue"
},
  "geometry": {"coordinates":[-78.786441,42.944838],"type":"Point"}
}