{
  "type": "Feature",
  "properties": {
    "iso:country":"US",
    "sg:address":"20 E John St",
    "sg:city":"Hicksville",
    "sg:classifiers":[
        {
            "category":"Building & Trades",
            "subcategory":"Construction",
            "type":"Services"
        }
    ],
    "sg:phone":"+1 516 822 8225",
    "sg:postcode":"11801",
    "sg:province":"NY",
    "sg:tags":[
        "concrete",
        "contractor"
    ],
    "wof:name":"Kilkenny Construction Co Inc",
    "wof:placetype":"venue"
},
  "geometry": {"coordinates":[-73.522347,40.770416],"type":"Point"}
}