{
  "type": "Feature",
  "properties": {
    "addr:full":"2303 Bronxwood Ave Bronx NY 10469",
    "addr:housenumber":"2303",
    "addr:postcode":"10469",
    "addr:street":"Bronxwood Ave",
    "iso:country":"US",
    "sg:address":"2303 Bronxwood Ave",
    "sg:city":"Bronx",
    "sg:classifiers":[
        {
            "category":"Health Services",
            "subcategory":"Doctor",
            "type":"Services"
        }
    ],
    "sg:phone":"+1 718 547 7505",
    "sg:postcode":"10469",
    "sg:province":"NY",
    "sg:tags":[
        "dentist"
    ],
    "wof:name":"Marvin A Frimmer DDS",
    "wof:placetype":"venue"
},
  "geometry": {"coordinates":[-73.861783,40.861211],"type":"Point"}
}