{
  "type": "Feature",
  "properties": {
    "addr:full":"70 Elm St Hicksville NY 11801",
    "addr:housenumber":"70",
    "addr:postcode":"11801",
    "addr:street":"Elm St",
    "iso:country":"US",
    "sg:address":"70 Elm St",
    "sg:city":"Hicksville",
    "sg:classifiers":[
        {
            "category":"Professional",
            "subcategory":"Accounting & Tax Preparation",
            "type":"Services"
        }
    ],
    "sg:phone":"+1 516 933 3555",
    "sg:postcode":"11801",
    "sg:province":"NY",
    "sg:tags":[
        "consultant"
    ],
    "wof:name":"Tax Correction Agency Inc",
    "wof:placetype":"venue"
},
  "geometry": {"coordinates":[-73.51354600000001,40.773644],"type":"Point"}
}