{
  "type": "Feature",
  "properties": {
    "iso:country":"US",
    "sg:address":"122 Van Vlack Rd",
    "sg:city":"Hopewell Jct",
    "sg:classifiers":[
        {
            "category":"Building & Trades",
            "subcategory":"Landscaping Services",
            "type":"Services"
        }
    ],
    "sg:phone":"+1 845 227 8520",
    "sg:postcode":"12533",
    "sg:province":"NY",
    "sg:tags":[
        "tree"
    ],
    "wof:name":"R & D Tree Svc",
    "wof:placetype":"venue"
},
  "geometry": {"coordinates":[-73.802374,41.561119],"type":"Point"}
}