{
  "type": "Feature",
  "properties": {
    "addr:full":"75 Maiden Ln Ste 318 New York NY 10038",
    "addr:housenumber":"75;318",
    "addr:postcode":"10038",
    "addr:street":"Maiden Ln Ste",
    "iso:country":"US",
    "sg:address":"75 Maiden Ln Ste 318",
    "sg:city":"New York",
    "sg:classifiers":[
        {
            "category":"Real Estate",
            "subcategory":"Real Estate Services",
            "type":"Services"
        }
    ],
    "sg:phone":"+1 212 402 4200",
    "sg:postcode":"10038",
    "sg:province":"NY",
    "sg:website":"www.browncastro.com/",
    "wof:name":"Brown Castro Realty",
    "wof:placetype":"venue"
},
  "geometry": {"coordinates":[-74.007383,40.707817],"type":"Point"}
}