{
  "type": "Feature",
  "properties": {
    "iso:country":"US",
    "sg:address":"63 Center St.",
    "sg:city":"East Aurora",
    "sg:classifiers":[
        {
            "category":"Professional",
            "subcategory":"Computer Services",
            "type":"Services"
        }
    ],
    "sg:phone":"+1 585 507 0018",
    "sg:postcode":"14052",
    "sg:province":"NY",
    "sg:tags":[
        "polling",
        "social-networking",
        "news-aggregation",
        "blog-aggregation",
        "social-polling",
        "web-2-0"
    ],
    "sg:website":"http://www.pikk.com/",
    "wof:name":"Pikk",
    "wof:placetype":"venue"
},
  "geometry": {"coordinates":[-78.622525,42.767541],"type":"Point"}
}