{
  "type": "Feature",
  "properties": {
    "iso:country":"US",
    "sg:address":"315 N Forest Rd",
    "sg:city":"Buffalo",
    "sg:classifiers":[
        {
            "category":"Real Estate",
            "subcategory":"Real Estate Services",
            "type":"Services"
        },
        {
            "category":"Real Estate",
            "subcategory":"Real Estate Agent",
            "type":"Services"
        }
    ],
    "sg:phone":"+1 716 633 9601",
    "sg:postcode":"14221",
    "sg:province":"NY",
    "sg:tags":[
        "buyer",
        "broker"
    ],
    "wof:name":"Sperry Van Ness Commercial Realty",
    "wof:placetype":"venue"
},
  "geometry": {"coordinates":[-78.75965100000001,42.968765],"type":"Point"}
}