{
  "type": "Feature",
  "properties": {
    "addr:full":"1043 West Ave Buffalo NY 14213",
    "addr:housenumber":"1043",
    "addr:postcode":"14213",
    "addr:street":"West Ave",
    "iso:country":"US",
    "sg:address":"1043 West Ave",
    "sg:city":"Buffalo",
    "sg:classifiers":[
        {
            "category":"Restaurant",
            "type":"Food & Drink"
        }
    ],
    "sg:phone":"+1 716 881 2205",
    "sg:postcode":"14213",
    "sg:province":"NY",
    "sg:tags":[
        "pizza"
    ],
    "wof:name":"Paulie's",
    "wof:placetype":"venue"
},
  "geometry": {"coordinates":[-78.896734,42.91868],"type":"Point"}
}