{
  "type": "Feature",
  "properties": {
    "addr:full":"875 Mill Rd Jamestown NY 14701",
    "addr:housenumber":"875",
    "addr:postcode":"14701",
    "addr:street":"Mill Rd",
    "iso:country":"US",
    "sg:address":"875 Mill Rd",
    "sg:city":"Jamestown",
    "sg:classifiers":[
        {
            "category":"Social Services",
            "type":"Services"
        }
    ],
    "sg:phone":"+1 716 665 2591",
    "sg:postcode":"14701",
    "sg:province":"NY",
    "sg:tags":[
        "counseling"
    ],
    "wof:name":"Compassionate Christian Cnslng",
    "wof:placetype":"venue"
},
  "geometry": {"coordinates":[-79.283187,42.036525],"type":"Point"}
}