{
  "type": "Feature",
  "properties": {
    "addr:full":"13861 Francis Lewis Boulevard Rosedale NY 11422",
    "addr:housenumber":"13861",
    "addr:postcode":"11422",
    "addr:street":"Francis Lewis Boulevard",
    "iso:country":"US",
    "sg:address":"13861 Francis Lewis Boulevard",
    "sg:city":"Rosedale",
    "sg:classifiers":[
        {
            "category":"Restaurant",
            "type":"Food & Drink"
        }
    ],
    "sg:phone":"+1 718 525 3900",
    "sg:postcode":"11422",
    "sg:province":"NY",
    "wof:name":"Best Wok",
    "wof:placetype":"venue"
},
  "geometry": {"coordinates":[-73.737064,40.667443],"type":"Point"}
}