{
  "type": "Feature",
  "properties": {
    "iso:country":"US",
    "sg:address":"70 Pattonwood Dr",
    "sg:city":"Rochester",
    "sg:classifiers":[
        {
            "category":"Manufacturing",
            "subcategory":"Apparel",
            "type":"Manufacturing & Wholesale Goods"
        }
    ],
    "sg:phone":"+1   ",
    "sg:postcode":"14617",
    "sg:province":"NY",
    "sg:tags":[
        "canvas",
        "product",
        "mfg"
    ],
    "wof:name":"C M Textile Fabrication",
    "wof:placetype":"venue"
},
  "geometry": {"coordinates":[-77.608622,43.24835],"type":"Point"}
}