{
  "type": "Feature",
  "properties": {
    "addr:full":"14 Brooklyn Ave Ste 103 Valley Stream NY 11581",
    "addr:housenumber":"14",
    "addr:postcode":"11581",
    "addr:street":"Brooklyn Ave Ste 103",
    "iso:country":"US",
    "sg:address":"14 Brooklyn Ave Ste 103",
    "sg:city":"Valley Stream",
    "sg:classifiers":[
        {
            "category":"Banks & Credit Unions",
            "subcategory":"Financial Services",
            "type":"Services"
        }
    ],
    "sg:phone":"+1 516 792 1289",
    "sg:postcode":"11581",
    "sg:province":"NY",
    "sg:tags":[
        "broker",
        "mortgage"
    ],
    "wof:name":"Alliance Mortgage",
    "wof:placetype":"venue"
},
  "geometry": {"coordinates":[-73.699966,40.659053],"type":"Point"}
}