{
  "type": "Feature",
  "properties": {
    "iso:country":"US",
    "sg:address":"2923 Glenwood Rd",
    "sg:city":"Brooklyn",
    "sg:classifiers":[
        {
            "category":"Professional",
            "type":"Services"
        }
    ],
    "sg:phone":"+1   ",
    "sg:postcode":"11210",
    "sg:province":"NY",
    "wof:name":"Dvj Inc",
    "wof:placetype":"venue"
},
  "geometry": {"coordinates":[-73.94796100000001,40.634051],"type":"Point"}
}