{
  "type": "Feature",
  "properties": {
    "addr:full":"5 Marion St Hicksville NY 11801",
    "addr:housenumber":"5",
    "addr:postcode":"11801",
    "addr:street":"Marion St",
    "iso:country":"US",
    "sg:address":"5 Marion St",
    "sg:city":"Hicksville",
    "sg:classifiers":[
        {
            "category":"Building & Trades",
            "subcategory":"Construction",
            "type":"Services"
        }
    ],
    "sg:phone":"+1 516 935 6621",
    "sg:postcode":"11801",
    "sg:province":"NY",
    "sg:tags":[
        "drywall",
        "contractor"
    ],
    "wof:name":"Josan Construction Corp",
    "wof:placetype":"venue"
},
  "geometry": {"coordinates":[-73.522265,40.780167],"type":"Point"}
}