{
  "type": "Feature",
  "properties": {
    "addr:full":"16307 Depot Road Flushing NY 11358",
    "addr:housenumber":"16307",
    "addr:postcode":"11358",
    "addr:street":"Depot Road",
    "iso:country":"US",
    "sg:address":"16307 Depot Road",
    "sg:city":"Flushing",
    "sg:classifiers":[
        {
            "category":"Banks & Credit Unions",
            "subcategory":"Investment Brokerage",
            "type":"Services"
        }
    ],
    "sg:phone":"+1 718 461 2233",
    "sg:postcode":"11358",
    "sg:province":"NY",
    "sg:tags":[
        "investing"
    ],
    "wof:name":"Metro Finance Consulting",
    "wof:placetype":"venue"
},
  "geometry": {"coordinates":[-73.802403,40.76196],"type":"Point"}
}