{
  "type": "Feature",
  "properties": {
    "iso:country":"US",
    "sg:address":"570 Nostrand Ave",
    "sg:city":"Brooklyn",
    "sg:classifiers":[
        {
            "category":"Shopping",
            "subcategory":"Department Store",
            "type":"Retail Goods"
        }
    ],
    "sg:phone":"+1 718 623 2930",
    "sg:postcode":"11216",
    "sg:province":"NY",
    "sg:tags":[
        "shop"
    ],
    "wof:name":"Teddie's Department Store",
    "wof:placetype":"venue"
},
  "geometry": {"coordinates":[-73.949692,40.679395],"type":"Point"}
}