{
  "type": "Feature",
  "properties": {
    "addr:full":"2958 Avenue Z Brooklyn NY 11235",
    "addr:housenumber":"2958",
    "addr:postcode":"11235",
    "addr:street":"Avenue Z",
    "iso:country":"US",
    "sg:address":"2958 Avenue Z",
    "sg:city":"Brooklyn",
    "sg:classifiers":[
        {
            "category":"Health Services",
            "subcategory":"Doctor",
            "type":"Services"
        }
    ],
    "sg:phone":"+1 718 891 4411",
    "sg:postcode":"11235",
    "sg:province":"NY",
    "wof:name":"Kane Alvin H MD",
    "wof:placetype":"venue"
},
  "geometry": {"coordinates":[-73.93849899999999,40.5896],"type":"Point"}
}