{
  "type": "Feature",
  "properties": {
    "addr:full":"249 Jennings Rd Cold Spring Hbr NY 11724",
    "addr:housenumber":"249",
    "addr:postcode":"11724",
    "addr:street":"Jennings Rd",
    "iso:country":"US",
    "sg:address":"249 Jennings Rd",
    "sg:city":"Cold Spring Hbr",
    "sg:classifiers":[
        {
            "category":"Professional",
            "subcategory":"Computer Services",
            "type":"Services"
        }
    ],
    "sg:phone":"+1 631 367 6240",
    "sg:postcode":"11724",
    "sg:province":"NY",
    "sg:tags":[
        "internet"
    ],
    "wof:name":"E Bill Solutions",
    "wof:placetype":"venue"
},
  "geometry": {"coordinates":[-73.46551100000001,40.88324],"type":"Point"}
}