{
  "type": "Feature",
  "properties": {
    "addr:full":"2210 Nesconset Hwy Stony Brook NY 11790",
    "addr:housenumber":"2210",
    "addr:postcode":"11790",
    "addr:street":"Nesconset Hwy",
    "iso:country":"US",
    "sg:address":"2210 Nesconset Hwy",
    "sg:city":"Stony Brook",
    "sg:classifiers":[
        {
            "category":"Banks & Credit Unions",
            "subcategory":"Bank",
            "type":"Services"
        }
    ],
    "sg:phone":"+1 631 751 8587",
    "sg:postcode":"11790",
    "sg:province":"NY",
    "sg:tags":[
        "state",
        "commercial"
    ],
    "wof:name":"Chase Manhattan",
    "wof:placetype":"venue"
},
  "geometry": {"coordinates":[-73.10926499999999,40.881512],"type":"Point"}
}