{
  "type": "Feature",
  "properties": {
    "iso:country":"US",
    "sg:address":"30 Harriman Dr",
    "sg:city":"Goshen",
    "sg:classifiers":[
        {
            "category":"Health Services",
            "subcategory":"Hospital",
            "type":"Services"
        }
    ],
    "sg:phone":"+1 845 291 2140",
    "sg:postcode":"10924",
    "sg:province":"NY",
    "sg:website":"www.ormc.org",
    "wof:name":"ORANGE COUNTY NY",
    "wof:placetype":"venue"
},
  "geometry": {"coordinates":[-74.320606,41.389918],"type":"Point"}
}