{
  "type": "Feature",
  "properties": {
    "addr:full":"7548 Main Street Fishers Victor NY 14564",
    "addr:housenumber":"7548",
    "addr:postcode":"14564",
    "addr:street":"Main Street",
    "iso:country":"US",
    "sg:address":"7548 Main Street Fishers",
    "sg:city":"Victor",
    "sg:classifiers":[
        {
            "category":"Restaurant",
            "type":"Food & Drink"
        }
    ],
    "sg:phone":"+1 585 742 3280",
    "sg:postcode":"14564",
    "sg:province":"NY",
    "wof:name":"Fisher's Station",
    "wof:placetype":"venue"
},
  "geometry": {"coordinates":[-77.448611,43.00847],"type":"Point"}
}