{
  "type": "Feature",
  "properties": {
    "iso:country":"US",
    "sg:address":"92 Holbrook Rd",
    "sg:city":"Centereach",
    "sg:classifiers":[
        {
            "category":"Arts & Performance",
            "subcategory":"Theater",
            "type":"Entertainment"
        }
    ],
    "sg:phone":"+1 631 737 0025",
    "sg:postcode":"11720",
    "sg:province":"NY",
    "sg:tags":[
        "entertainer"
    ],
    "wof:name":"Get In Tune Productions",
    "wof:placetype":"venue"
},
  "geometry": {"coordinates":[-73.082194,40.849814],"type":"Point"}
}