{
  "type": "Feature",
  "properties": {
    "addr:full":"40 Elmont Rd Elmont NY 11003",
    "addr:housenumber":"40",
    "addr:postcode":"11003",
    "addr:street":"Elmont Rd",
    "iso:country":"US",
    "sg:address":"40 Elmont Rd",
    "sg:city":"Elmont",
    "sg:classifiers":[
        {
            "category":"Banks & Credit Unions",
            "subcategory":"Bank",
            "type":"Services"
        }
    ],
    "sg:phone":"+1 516 622 2366",
    "sg:postcode":"11003",
    "sg:province":"NY",
    "sg:tags":[
        "loan",
        "mortgage",
        "real estate"
    ],
    "wof:name":"Vip Mortgage Corp",
    "wof:placetype":"venue"
},
  "geometry": {"coordinates":[-73.70965099999999,40.707628],"type":"Point"}
}