{
  "type": "Feature",
  "properties": {
    "addr:full":"1200 Waters Place Bronx NY 10461",
    "addr:housenumber":"1200",
    "addr:postcode":"10461",
    "addr:street":"Waters Place",
    "iso:country":"US",
    "sg:address":"1200 Waters Place",
    "sg:city":"Bronx",
    "sg:classifiers":[
        {
            "category":"Health Services",
            "subcategory":"Doctor",
            "type":"Services"
        }
    ],
    "sg:phone":"+1 718 892 3298",
    "sg:postcode":"10461",
    "sg:province":"NY",
    "wof:name":"E & T and Allergy Assoc",
    "wof:placetype":"venue"
},
  "geometry": {"coordinates":[-73.838374,40.842658],"type":"Point"}
}