{
  "type": "Feature",
  "properties": {
    "iso:country":"US",
    "sg:address":"350 Moreland Rd",
    "sg:city":"Commack",
    "sg:classifiers":[
        {
            "category":"Personal",
            "type":"Services"
        }
    ],
    "sg:phone":"+1 631 343 7102",
    "sg:postcode":"11725",
    "sg:province":"NY",
    "sg:tags":[
        "mover"
    ],
    "sg:website":"www.libertymoving.com",
    "wof:name":"Liberty Moving Storage",
    "wof:placetype":"venue"
},
  "geometry": {"coordinates":[-73.2705,40.813838],"type":"Point"}
}