{
  "type": "Feature",
  "properties": {
    "iso:country":"US",
    "sg:address":"3501 Vestal Pkwy E",
    "sg:city":"Vestal",
    "sg:classifiers":[
        {
            "category":"Shopping",
            "type":"Retail Goods"
        }
    ],
    "sg:phone":"+1   ",
    "sg:postcode":"13850",
    "sg:province":"NY",
    "sg:tags":[
        "equipment",
        "merchandise"
    ],
    "wof:name":"Northeast Canopy",
    "wof:placetype":"venue"
},
  "geometry": {"coordinates":[-75.98641499999999,42.096737],"type":"Point"}
}