{
  "type": "Feature",
  "properties": {
    "addr:full":"19 Crestwood Ave Selden NY 11784",
    "addr:housenumber":"19",
    "addr:postcode":"11784",
    "addr:street":"Crestwood Ave",
    "iso:country":"US",
    "sg:address":"19 Crestwood Ave",
    "sg:city":"Selden",
    "sg:classifiers":[
        {
            "category":"Freight",
            "type":"Transportation"
        }
    ],
    "sg:phone":"+1   ",
    "sg:postcode":"11784",
    "sg:province":"NY",
    "sg:tags":[
        "operator",
        "local",
        "trucking"
    ],
    "wof:name":"Cac Transport Ltd",
    "wof:placetype":"venue"
},
  "geometry": {"coordinates":[-73.03204599999999,40.84639],"type":"Point"}
}