{
  "type": "Feature",
  "properties": {
    "iso:country":"US",
    "sg:address":"49 S Main St",
    "sg:city":"Spring Valley",
    "sg:classifiers":[
        {
            "category":"Social Services",
            "type":"Services"
        }
    ],
    "sg:phone":"+1 845 352 3608",
    "sg:postcode":"10977",
    "sg:province":"NY",
    "sg:tags":[
        "organization",
        "welfare"
    ],
    "wof:name":"Economic Opportunity Cmmssn",
    "wof:placetype":"venue"
},
  "geometry": {"coordinates":[-74.044967,41.10796],"type":"Point"}
}