{
  "type": "Feature",
  "properties": {
    "iso:country":"US",
    "sg:address":"277 Broadway",
    "sg:city":"New York",
    "sg:classifiers":[
        {
            "category":"Professional",
            "subcategory":"Lawyer & Legal Services",
            "type":"Services"
        }
    ],
    "sg:phone":"+1 212 962 1200",
    "sg:postcode":"10007",
    "sg:province":"NY",
    "sg:tags":[
        "attorney"
    ],
    "wof:name":"Fogelgaren Forman & Bergman Llp",
    "wof:placetype":"venue"
},
  "geometry": {"coordinates":[-74.006153,40.714333],"type":"Point"}
}