{
  "type": "Feature",
  "properties": {
    "iso:country":"US",
    "sg:address":"625 Colesville Rd",
    "sg:city":"Binghamton",
    "sg:classifiers":[
        {
            "category":"Professional",
            "subcategory":"Art Services",
            "type":"Services"
        }
    ],
    "sg:phone":"+1 607 775 2339",
    "sg:postcode":"13904",
    "sg:province":"NY",
    "sg:tags":[
        "taxidermist"
    ],
    "wof:name":"Mountian & Stream Taxidermy",
    "wof:placetype":"venue"
},
  "geometry": {"coordinates":[-75.79199699999999,42.123971],"type":"Point"}
}