{
  "type": "Feature",
  "properties": {
    "addr:full":"168 E Kiln Rd Au Sable Forks NY 12912",
    "addr:housenumber":"168",
    "addr:postcode":"12912",
    "addr:street":"E Kiln Rd Au",
    "iso:country":"US",
    "sg:address":"168 E Kiln Rd",
    "sg:city":"Au Sable Forks",
    "sg:classifiers":[
        {
            "category":"Freight",
            "type":"Transportation"
        }
    ],
    "sg:phone":"+1 518 647 2292",
    "sg:postcode":"12912",
    "sg:province":"NY",
    "sg:tags":[
        "commercial",
        "storage"
    ],
    "wof:name":"East Kiln Boat Storage",
    "wof:placetype":"venue"
},
  "geometry": {"coordinates":[-73.77588900000001,44.468571],"type":"Point"}
}