{
  "type": "Feature",
  "properties": {
    "iso:country":"US",
    "sg:address":"1636 Bruckner Blvd",
    "sg:city":"Bronx",
    "sg:classifiers":[
        {
            "category":"Professional",
            "subcategory":"Accounting & Tax Preparation",
            "type":"Services"
        }
    ],
    "sg:phone":"+1 718 542 3100",
    "sg:postcode":"10473",
    "sg:province":"NY",
    "sg:tags":[
        "transmission",
        "return"
    ],
    "wof:name":"D & C Professional Svc",
    "wof:placetype":"venue"
},
  "geometry": {"coordinates":[-73.87314600000001,40.824092],"type":"Point"}
}