{
  "type": "Feature",
  "properties": {
    "iso:country":"US",
    "sg:address":"930 Oriskany St W",
    "sg:city":"Utica",
    "sg:classifiers":[
        {
            "category":"Retail",
            "subcategory":"Repair Shop",
            "type":"Services"
        }
    ],
    "sg:phone":"+1 315 724 4303",
    "sg:postcode":"13502",
    "sg:province":"NY",
    "sg:tags":[
        "equipment",
        "music",
        "instruction-instrumental"
    ],
    "sg:website":"http://www.stagemusicpianos.com",
    "wof:name":"Stage Music",
    "wof:placetype":"venue"
},
  "geometry": {"coordinates":[-75.244451,43.107483],"type":"Point"}
}