{
  "type": "Feature",
  "properties": {
    "addr:full":"2012 Merrick Rd Merrick NY 11566",
    "addr:housenumber":"2012",
    "addr:postcode":"11566",
    "addr:street":"Merrick Rd",
    "iso:country":"US",
    "sg:address":"2012 Merrick Rd",
    "sg:city":"Merrick",
    "sg:classifiers":[
        {
            "category":"Restaurant",
            "type":"Food & Drink"
        }
    ],
    "sg:menulink":"http://www.allmenus.com/ny/bellmore-merrick/255030-la-bottega-italian-gourmet/menu/",
    "sg:phone":"+1 516 223 0800",
    "sg:postcode":"11566",
    "sg:province":"NY",
    "sg:tags":[
        "italian"
    ],
    "wof:name":"La Bottega Italian Gourmet",
    "wof:placetype":"venue"
},
  "geometry": {"coordinates":[-73.544709,40.6587],"type":"Point"}
}