{
  "type": "Feature",
  "properties": {
    "addr:full":"42 Ackert Hook Rd Rhinebeck NY 12572",
    "addr:housenumber":"42",
    "addr:postcode":"12572",
    "addr:street":"Ackert Hook Rd",
    "iso:country":"US",
    "sg:address":"42 Ackert Hook Rd",
    "sg:city":"Rhinebeck",
    "sg:classifiers":[
        {
            "category":"Building & Trades",
            "subcategory":"Construction",
            "type":"Services"
        }
    ],
    "sg:phone":"+1 845 876 6666",
    "sg:postcode":"12572",
    "sg:province":"NY",
    "sg:tags":[
        "excavating",
        "contractor"
    ],
    "wof:name":"Mc Guire Excavating",
    "wof:placetype":"venue"
},
  "geometry": {"coordinates":[-73.89663299999999,41.910236],"type":"Point"}
}