{
  "type": "Feature",
  "properties": {
    "iso:country":"US",
    "sg:address":"366 Veterans Memorial Hwy Ste 2",
    "sg:city":"Commack",
    "sg:classifiers":[
        {
            "category":"Health Services",
            "subcategory":"Health Practitioner",
            "type":"Services"
        }
    ],
    "sg:phone":"+1 631 543 2068",
    "sg:postcode":"11725",
    "sg:province":"NY",
    "sg:tags":[
        "therapy",
        "physical"
    ],
    "wof:name":"THERA SPORTS PLUS PHYSICAL THERAPY",
    "wof:placetype":"venue"
},
  "geometry": {"coordinates":[-73.259101,40.832147],"type":"Point"}
}