{
  "type": "Feature",
  "properties": {
    "iso:country":"US",
    "sg:address":"2084 E Main St",
    "sg:city":"Mohegan Lake",
    "sg:classifiers":[
        {
            "category":"Shopping",
            "subcategory":"Music",
            "type":"Retail Goods"
        }
    ],
    "sg:phone":"+1   ",
    "sg:postcode":"10547",
    "sg:province":"NY",
    "wof:name":"Hollywood Entertainment Corp",
    "wof:placetype":"venue"
},
  "geometry": {"coordinates":[-73.846788,41.32738],"type":"Point"}
}