{
  "type": "Feature",
  "properties": {
    "iso:country":"US",
    "sg:address":"26 Pocahontas St W",
    "sg:city":"Massapequa",
    "sg:classifiers":[
        {
            "category":"Health Services",
            "subcategory":"Health Practitioner",
            "type":"Services"
        }
    ],
    "sg:phone":"+1   ",
    "sg:postcode":"11758",
    "sg:province":"NY",
    "wof:name":"Ron Paust",
    "wof:placetype":"venue"
},
  "geometry": {"coordinates":[-73.443898,40.660915],"type":"Point"}
}