{
  "type": "Feature",
  "properties": {
    "addr:full":"6301 11th Ave Brooklyn NY 11219",
    "addr:housenumber":"6301",
    "addr:postcode":"11219",
    "addr:street":"11Th Ave",
    "iso:country":"US",
    "sg:address":"6301 11th Ave",
    "sg:city":"Brooklyn",
    "sg:classifiers":[
        {
            "category":"Food & Beverages",
            "subcategory":"Groceries & Convenience Stores",
            "type":"Retail Goods"
        }
    ],
    "sg:phone":"+1 718 837 0025",
    "sg:postcode":"11219",
    "sg:province":"NY",
    "sg:tags":[
        "grocer"
    ],
    "wof:name":"Scaturro Food Market",
    "wof:placetype":"venue"
},
  "geometry": {"coordinates":[-74.004751,40.629373],"type":"Point"}
}