{
  "type": "Feature",
  "properties": {
    "addr:full":"150 Manhattan Ave New York NY 10025",
    "addr:housenumber":"150",
    "addr:postcode":"10025",
    "addr:street":"Manhattan Ave",
    "iso:country":"US",
    "sg:address":"150 Manhattan Ave",
    "sg:city":"New York",
    "sg:classifiers":[
        {
            "category":"Food & Beverages",
            "subcategory":"Groceries & Convenience Stores",
            "type":"Retail Goods"
        }
    ],
    "sg:phone":"+1 212 749 9416",
    "sg:postcode":"10025",
    "sg:province":"NY",
    "sg:tags":[
        "grocer"
    ],
    "wof:name":"Juana Grocery Corp",
    "wof:placetype":"venue"
},
  "geometry": {"coordinates":[-73.960956,40.79906],"type":"Point"}
}