{
  "type": "Feature",
  "properties": {
    "iso:country":"US",
    "sg:address":"2917 Wynsum Ave",
    "sg:city":"Merrick",
    "sg:classifiers":[
        {
            "category":"Health Services",
            "subcategory":"Chiropractor",
            "type":"Services"
        }
    ],
    "sg:phone":"+1 516 379 1104",
    "sg:postcode":"11566",
    "sg:province":"NY",
    "wof:name":"West Hempstead Chiropractic",
    "wof:placetype":"venue"
},
  "geometry": {"coordinates":[-73.537751,40.65069],"type":"Point"}
}