{
  "type": "Feature",
  "properties": {
    "addr:full":"30 E 111th St New York NY 10029",
    "addr:housenumber":"30",
    "addr:postcode":"10029",
    "addr:street":"E 111Th St",
    "iso:country":"US",
    "sg:address":"30 E 111th St",
    "sg:city":"New York",
    "sg:classifiers":[
        {
            "category":"Professional",
            "type":"Services"
        }
    ],
    "sg:phone":"+1 212 860 7201",
    "sg:postcode":"10029",
    "sg:province":"NY",
    "sg:tags":[
        "elementary",
        "school"
    ],
    "wof:name":"East Harlem Council For Human Scves",
    "wof:placetype":"venue"
},
  "geometry": {"coordinates":[-73.9478,40.796902],"type":"Point"}
}