{
  "type": "Feature",
  "properties": {
    "addr:full":"20 Franklin St Franklin Square NY 11010",
    "addr:housenumber":"20",
    "addr:postcode":"11010",
    "addr:street":"Franklin St",
    "iso:country":"US",
    "sg:address":"20 Franklin St",
    "sg:city":"Franklin Square",
    "sg:classifiers":[
        {
            "category":"Restaurant",
            "type":"Food & Drink"
        }
    ],
    "sg:phone":"+1 516 488 0488",
    "sg:postcode":"11010",
    "sg:province":"NY",
    "sg:tags":[
        "caterer"
    ],
    "wof:name":"Carriage House",
    "wof:placetype":"venue"
},
  "geometry": {"coordinates":[-73.674195,40.708662],"type":"Point"}
}