{
  "type": "Feature",
  "properties": {
    "iso:country":"US",
    "sg:address":"6185 W Quaker St",
    "sg:city":"Orchard Park",
    "sg:classifiers":[
        {
            "category":"Restaurant",
            "type":"Food & Drink"
        }
    ],
    "sg:phone":"+1   ",
    "sg:postcode":"14127",
    "sg:province":"NY",
    "sg:tags":[
        "ice",
        "cream"
    ],
    "wof:name":"Snowflake Creamery",
    "wof:placetype":"venue"
},
  "geometry": {"coordinates":[-78.756721,42.763463],"type":"Point"}
}