{
  "type": "Feature",
  "properties": {
    "iso:country":"US",
    "sg:address":"904 46th St",
    "sg:city":"Brooklyn",
    "sg:classifiers":[
        {
            "category":"Organizations",
            "subcategory":"Religious Organization",
            "type":"Services"
        }
    ],
    "sg:phone":"+1 718 435 8339",
    "sg:postcode":"11219",
    "sg:province":"NY",
    "sg:tags":[
        "clergy"
    ],
    "wof:name":"Naftali Lebowitz",
    "wof:placetype":"venue"
},
  "geometry": {"coordinates":[-73.997089,40.64069],"type":"Point"}
}