{
  "type": "Feature",
  "properties": {
    "addr:full":"204 Packwood Rd Waterloo NY 13165",
    "addr:housenumber":"204",
    "addr:postcode":"13165",
    "addr:street":"Packwood Rd",
    "iso:country":"US",
    "sg:address":"204 Packwood Rd",
    "sg:city":"Waterloo",
    "sg:classifiers":[
        {
            "category":"Shopping",
            "type":"Retail Goods"
        }
    ],
    "sg:phone":"+1 315 781 2494",
    "sg:postcode":"13165",
    "sg:province":"NY",
    "sg:tags":[
        "picture",
        "frame"
    ],
    "wof:name":"Eagle Bridge Custom Framing",
    "wof:placetype":"venue"
},
  "geometry": {"coordinates":[-76.951337,42.903079],"type":"Point"}
}