{
  "type": "Feature",
  "properties": {
    "addr:full":"110 Madison Ave New York NY 10016",
    "addr:housenumber":"110",
    "addr:postcode":"10016",
    "addr:street":"Madison Ave",
    "iso:country":"US",
    "sg:address":"110 Madison Ave",
    "sg:city":"New York",
    "sg:classifiers":[
        {
            "category":"Restaurant",
            "type":"Food & Drink"
        }
    ],
    "sg:menulink":"http://www.allmenus.com/ny/new-york/2919-meli-melo/menu/",
    "sg:phone":"+1 212 686 5551",
    "sg:postcode":"10016",
    "sg:province":"NY",
    "sg:tags":[
        "french",
        "italian"
    ],
    "wof:name":"Meli Melo",
    "wof:placetype":"venue"
},
  "geometry": {"coordinates":[-73.985355,40.745092],"type":"Point"}
}