{
  "type": "Feature",
  "properties": {
    "addr:full":"514 E 2nd St Brooklyn NY 11218",
    "addr:housenumber":"514",
    "addr:postcode":"11218",
    "addr:street":"E 2Nd St",
    "iso:country":"US",
    "sg:address":"514 E 2nd St",
    "sg:city":"Brooklyn",
    "sg:classifiers":[
        {
            "category":"Organizations",
            "subcategory":"Religious Organization",
            "type":"Services"
        }
    ],
    "sg:phone":"+1 718 633 3473",
    "sg:postcode":"11218",
    "sg:province":"NY",
    "sg:tags":[
        "clergy"
    ],
    "wof:name":"Abraham M Barnetsky",
    "wof:placetype":"venue"
},
  "geometry": {"coordinates":[-73.977678,40.639861],"type":"Point"}
}