{
  "type": "Feature",
  "properties": {
    "addr:full":"76 Hendricks Ave Staten Island NY 10301",
    "addr:housenumber":"76",
    "addr:postcode":"10301",
    "addr:street":"Hendricks Ave",
    "iso:country":"US",
    "sg:address":"76 Hendricks Ave",
    "sg:city":"Staten Island",
    "sg:classifiers":[
        {
            "category":"Building & Trades",
            "subcategory":"Construction",
            "type":"Services"
        }
    ],
    "sg:phone":"+1 718 981 5129",
    "sg:postcode":"10301",
    "sg:province":"NY",
    "sg:tags":[
        "house"
    ],
    "wof:name":"Zlunka Henry Construction Co",
    "wof:placetype":"venue"
},
  "geometry": {"coordinates":[-74.083834,40.640353],"type":"Point"}
}