{
  "type": "Feature",
  "properties": {
    "iso:country":"US",
    "sg:address":"45 York Rd",
    "sg:city":"Cohoes",
    "sg:classifiers":[
        {
            "category":"Personal",
            "subcategory":"Beauty Salon",
            "type":"Services"
        }
    ],
    "sg:phone":"+1 518 237 5875",
    "sg:postcode":"12047",
    "sg:province":"NY",
    "wof:name":"Shear Attitude",
    "wof:placetype":"venue"
},
  "geometry": {"coordinates":[-73.722679,42.77066],"type":"Point"}
}