{
  "type": "Feature",
  "properties": {
    "iso:country":"US",
    "sg:address":"1 Francis St",
    "sg:city":"Seneca Falls",
    "sg:classifiers":[
        {
            "category":"Banks & Credit Unions",
            "subcategory":"Bank",
            "type":"Services"
        }
    ],
    "sg:phone":"+1 585 248 7585",
    "sg:postcode":"13148",
    "sg:province":"NY",
    "sg:tags":[
        "national",
        "commercial"
    ],
    "wof:name":"Citibank",
    "wof:placetype":"venue"
},
  "geometry": {"coordinates":[-76.792368,42.903144],"type":"Point"}
}