{
  "type": "Feature",
  "properties": {
    "iso:country":"US",
    "sg:address":"479 Northland Ave",
    "sg:city":"Buffalo",
    "sg:classifiers":[
        {
            "category":"Insurance",
            "subcategory":"Insurance Agent",
            "type":"Services"
        }
    ],
    "sg:phone":"+1 716 856 3145",
    "sg:postcode":"14211",
    "sg:province":"NY",
    "wof:name":"Suleman & Assoc",
    "wof:placetype":"venue"
},
  "geometry": {"coordinates":[-78.841781,42.919046],"type":"Point"}
}