{
  "type": "Feature",
  "properties": {
    "addr:full":"336 Rockaway Tpke Lawrence NY 11559",
    "addr:housenumber":"336",
    "addr:postcode":"11559",
    "addr:street":"Rockaway Tpke",
    "iso:country":"US",
    "sg:address":"336 Rockaway Tpke",
    "sg:city":"Lawrence",
    "sg:classifiers":[
        {
            "category":"Autos & Motor Vehicles",
            "subcategory":"Fuel & Gas Station",
            "type":"Retail Goods"
        }
    ],
    "sg:phone":"+1 516 239 2115",
    "sg:postcode":"11559",
    "sg:province":"NY",
    "wof:name":"Rockaway Amaco",
    "wof:placetype":"venue"
},
  "geometry": {"coordinates":[-73.737801,40.6297],"type":"Point"}
}