{
  "type": "Feature",
  "properties": {
    "iso:country":"US",
    "sg:address":"70 Temple St",
    "sg:city":"Avon",
    "sg:classifiers":[
        {
            "category":"Building & Trades",
            "subcategory":"Landscaping Services",
            "type":"Services"
        }
    ],
    "sg:phone":"+1 585 226 8828",
    "sg:postcode":"14414",
    "sg:province":"NY",
    "sg:tags":[
        "landscape"
    ],
    "wof:name":"Brede Landscaping",
    "wof:placetype":"venue"
},
  "geometry": {"coordinates":[-77.74429000000001,42.909658],"type":"Point"}
}