{
  "type": "Feature",
  "properties": {
    "addr:full":"10 E 5th St Deer Park NY 11729",
    "addr:housenumber":"10",
    "addr:postcode":"11729",
    "addr:street":"E 5Th St",
    "iso:country":"US",
    "sg:address":"10 E 5th St",
    "sg:city":"Deer Park",
    "sg:classifiers":[
        {
            "category":"Professional",
            "subcategory":"Business Services",
            "type":"Services"
        }
    ],
    "sg:phone":"+1 631 667 2281",
    "sg:postcode":"11729",
    "sg:province":"NY",
    "sg:website":"www.vtsn.com",
    "wof:name":"Vehicle Tracking Solutions",
    "wof:placetype":"venue"
},
  "geometry": {"coordinates":[-73.32445,40.761942],"type":"Point"}
}