{
  "type": "Feature",
  "properties": {
    "addr:full":"557 86th St Brooklyn NY 11209",
    "addr:housenumber":"557",
    "addr:postcode":"11209",
    "addr:street":"86Th St",
    "iso:country":"US",
    "sg:address":"557 86th St",
    "sg:city":"Brooklyn",
    "sg:classifiers":[
        {
            "category":"Shopping",
            "subcategory":"Florist",
            "type":"Retail Goods"
        }
    ],
    "sg:phone":"+1 718 833 7848",
    "sg:postcode":"11209",
    "sg:province":"NY",
    "sg:website":"www.fruitflowers.com",
    "wof:name":"FruitFlowers",
    "wof:placetype":"venue"
},
  "geometry": {"coordinates":[-74.02504,40.620783],"type":"Point"}
}