{
  "type": "Feature",
  "properties": {
    "iso:country":"US",
    "sg:address":"507 Bunker Hill Rd",
    "sg:city":"Oswego",
    "sg:classifiers":[
        {
            "category":"Farming",
            "subcategory":"Orchard",
            "type":"Manufacturing & Wholesale Goods"
        }
    ],
    "sg:phone":"+1 315 342 3793",
    "sg:postcode":"13126",
    "sg:province":"NY",
    "sg:tags":[
        "fruit",
        "tree"
    ],
    "wof:name":"Fruit Valley Greenhouses",
    "wof:placetype":"venue"
},
  "geometry": {"coordinates":[-76.554096,43.421146],"type":"Point"}
}