{
  "type": "Feature",
  "properties": {
    "addr:full":"233 E 67th St New York NY 10021",
    "addr:housenumber":"233",
    "addr:postcode":"10021",
    "addr:street":"E 67Th St",
    "iso:country":"US",
    "sg:address":"233 E 67th St",
    "sg:city":"New York",
    "sg:classifiers":[
        {
            "category":"Retail",
            "subcategory":"Laundry & Dry Cleaning",
            "type":"Services"
        }
    ],
    "sg:phone":"+1 212 472 0630",
    "sg:postcode":"10021",
    "sg:province":"NY",
    "wof:name":"Manhattan East Valet",
    "wof:placetype":"venue"
},
  "geometry": {"coordinates":[-73.960999,40.7659],"type":"Point"}
}