{
  "type": "Feature",
  "properties": {
    "addr:full":"1603 Straight Path Wyandanch NY 11798",
    "addr:housenumber":"1603",
    "addr:postcode":"11798",
    "addr:street":"Straight Path",
    "iso:country":"US",
    "sg:address":"1603 Straight Path",
    "sg:city":"Wyandanch",
    "sg:classifiers":[
        {
            "category":"Restaurant",
            "type":"Food & Drink"
        }
    ],
    "sg:menulink":"http://www.allmenus.com/ny/babylon/256172-dah-wah-kitchen/menu/",
    "sg:phone":"+1 631 643 7444",
    "sg:postcode":"11798",
    "sg:province":"NY",
    "sg:tags":[
        "asian",
        "chinese"
    ],
    "wof:name":"Dah Wah Kitchen",
    "wof:placetype":"venue"
},
  "geometry": {"coordinates":[-73.359318,40.756285],"type":"Point"}
}