{
  "type": "Feature",
  "properties": {
    "addr:full":"1740 Flatbush Ave Brooklyn NY 11210",
    "addr:housenumber":"1740",
    "addr:postcode":"11210",
    "addr:street":"Flatbush Ave",
    "iso:country":"US",
    "sg:address":"1740 Flatbush Ave",
    "sg:city":"Brooklyn",
    "sg:classifiers":[
        {
            "category":"Building & Trades",
            "subcategory":"Construction",
            "type":"Services"
        }
    ],
    "sg:phone":"+1 718 377 5333",
    "sg:postcode":"11210",
    "sg:province":"NY",
    "sg:tags":[
        "waterproofing",
        "contractor"
    ],
    "wof:name":"Richard Waterproofing Contr",
    "wof:placetype":"venue"
},
  "geometry": {"coordinates":[-73.94290599999999,40.628396],"type":"Point"}
}