{
  "type": "Feature",
  "properties": {
    "addr:full":"148 E 46th St New York NY 10017",
    "addr:housenumber":"148",
    "addr:postcode":"10017",
    "addr:street":"E 46Th St",
    "iso:country":"US",
    "sg:address":"148 E 46th St",
    "sg:city":"New York",
    "sg:classifiers":[
        {
            "category":"Restaurant",
            "type":"Food & Drink"
        }
    ],
    "sg:menulink":"http://www.allmenus.com/ny/new-york/252231-joy-curry--tandoor/menu/",
    "sg:phone":"+1 212 490 1277",
    "sg:postcode":"10017",
    "sg:province":"NY",
    "sg:tags":[
        "indian",
        "asian"
    ],
    "wof:name":"Joy Curry & Tandoor",
    "wof:placetype":"venue"
},
  "geometry": {"coordinates":[-73.973556,40.753722],"type":"Point"}
}