{
  "type": "Feature",
  "properties": {
    "addr:full":"3009 Ave J Brooklyn NY 11210",
    "addr:housenumber":"3009",
    "addr:postcode":"11210",
    "addr:street":"Ave J",
    "iso:country":"US",
    "sg:address":"3009 Ave J",
    "sg:city":"Brooklyn",
    "sg:classifiers":[
        {
            "category":"Arts & Performance",
            "subcategory":"Arts Center",
            "type":"Entertainment"
        },
        {
            "category":"Personal",
            "type":"Services"
        },
        {
            "category":"Sports & Exercise",
            "subcategory":"Playing Field",
            "type":"Entertainment"
        }
    ],
    "sg:phone":"+1 718 253 0939",
    "sg:postcode":"11210",
    "sg:province":"NY",
    "sg:tags":[
        "local",
        "performing",
        "instruction",
        "fitness"
    ],
    "sg:website":"www.dancefeverstudios.com",
    "wof:name":"Dancefever Studios",
    "wof:placetype":"venue"
},
  "geometry": {"coordinates":[-73.94678399999999,40.626783],"type":"Point"}
}