{
  "type": "Feature",
  "properties": {
    "addr:full":"222 Montrose Ave Brooklyn NY 11206",
    "addr:housenumber":"222",
    "addr:postcode":"11206",
    "addr:street":"Montrose Ave",
    "iso:country":"US",
    "sg:address":"222 Montrose Ave",
    "sg:city":"Brooklyn",
    "sg:classifiers":[
        {
            "category":"Shopping",
            "subcategory":"Books",
            "type":"Retail Goods"
        },
        {
            "category":"Shopping",
            "subcategory":"Used Merchandise",
            "type":"Retail Goods"
        }
    ],
    "sg:phone":"+1 718 609 6066",
    "sg:postcode":"11206",
    "sg:province":"NY",
    "sg:tags":[
        "mags",
        "vintage",
        "books",
        "video",
        "music",
        "consignment"
    ],
    "wof:name":"The Vortex",
    "wof:placetype":"venue"
},
  "geometry": {"coordinates":[-73.94020500000001,40.707623],"type":"Point"}
}