{
  "type": "Feature",
  "properties": {
    "iso:country":"US",
    "sg:address":"21 Feagles Rd",
    "sg:city":"Warwick",
    "sg:classifiers":[
        {
            "category":"Professional",
            "subcategory":"Research",
            "type":"Services"
        }
    ],
    "sg:phone":"+1 845 258 1000",
    "sg:postcode":"10990",
    "sg:province":"NY",
    "sg:tags":[
        "marketing",
        "consultant"
    ],
    "wof:name":"Business Demographics Inc",
    "wof:placetype":"venue"
},
  "geometry": {"coordinates":[-74.453968,41.275685],"type":"Point"}
}