{
  "type": "Feature",
  "properties": {
    "iso:country":"US",
    "sg:address":"34 W Main St",
    "sg:city":"Malone",
    "sg:classifiers":[
        {
            "category":"Health Services",
            "subcategory":"Doctor",
            "type":"Services"
        }
    ],
    "sg:phone":"+1 518 563 8880",
    "sg:postcode":"12953",
    "sg:province":"NY",
    "sg:tags":[
        "physician",
        "surgeon"
    ],
    "wof:name":"Women's Health Care-Gynecology",
    "wof:placetype":"venue"
},
  "geometry": {"coordinates":[-74.29418099999999,44.848705],"type":"Point"}
}