{
  "type": "Feature",
  "properties": {
    "iso:country":"US",
    "sg:address":"58 Turner Dr",
    "sg:city":"Chappaqua",
    "sg:classifiers":[
        {
            "category":"Wholesale",
            "subcategory":"Machinery & Supplies",
            "type":"Manufacturing & Wholesale Goods"
        }
    ],
    "sg:phone":"+1 914 241 0010",
    "sg:postcode":"10514",
    "sg:province":"NY",
    "sg:tags":[
        "equipment",
        "industrial"
    ],
    "wof:name":"Emenex Mfg Corp",
    "wof:placetype":"venue"
},
  "geometry": {"coordinates":[-73.772497,41.197729],"type":"Point"}
}