{
  "type": "Feature",
  "properties": {
    "iso:country":"US",
    "sg:address":"29 Main St",
    "sg:city":"Chester",
    "sg:classifiers":[
        {
            "category":"Shopping",
            "subcategory":"Books",
            "type":"Retail Goods"
        }
    ],
    "sg:phone":"+1   ",
    "sg:postcode":"10918",
    "sg:province":"NY",
    "sg:tags":[
        "house",
        "used",
        "merchandise",
        "mail"
    ],
    "wof:name":"A R Backer Books",
    "wof:placetype":"venue"
},
  "geometry": {"coordinates":[-74.271976,41.362241],"type":"Point"}
}