{
  "type": "Feature",
  "properties": {
    "iso:country":"US",
    "sg:address":"4300 Culver Rd",
    "sg:city":"Rochester",
    "sg:classifiers":[
        {
            "category":"Restaurant",
            "type":"Food & Drink"
        }
    ],
    "sg:phone":"+1 585 467 2750",
    "sg:postcode":"14622",
    "sg:province":"NY",
    "wof:name":"Mastrella's Irondequolt Steak",
    "wof:placetype":"venue"
},
  "geometry": {"coordinates":[-77.54714800000001,43.226948],"type":"Point"}
}