{
  "type": "Feature",
  "properties": {
    "addr:full":"2608 Genesee St Utica NY 13502",
    "addr:housenumber":"2608",
    "addr:postcode":"13502",
    "addr:street":"Genesee St",
    "iso:country":"US",
    "sg:address":"2608 Genesee St",
    "sg:city":"Utica",
    "sg:classifiers":[
        {
            "category":"Health Services",
            "subcategory":"Clinic",
            "type":"Services"
        }
    ],
    "sg:phone":"+1 315 735 8521",
    "sg:postcode":"13502",
    "sg:province":"NY",
    "sg:tags":[
        "a",
        "visiting",
        "operates",
        "as",
        "nurse",
        "association"
    ],
    "wof:name":"Visiting Nurse Assn",
    "wof:placetype":"venue"
},
  "geometry": {"coordinates":[-75.27773500000001,43.078488],"type":"Point"}
}