{
  "type": "Feature",
  "properties": {
    "addr:full":"7 Westchester Plz Elmsford NY 10523",
    "addr:housenumber":"7",
    "addr:postcode":"10523",
    "addr:street":"Westchester Plz",
    "iso:country":"US",
    "sg:address":"7 Westchester Plz",
    "sg:city":"Elmsford",
    "sg:classifiers":[
        {
            "category":"Food & Beverages",
            "subcategory":"Specialty",
            "type":"Retail Goods"
        }
    ],
    "sg:phone":"+1 914 592 3155",
    "sg:postcode":"10523",
    "sg:province":"NY",
    "sg:tags":[
        "health",
        "diet"
    ],
    "sg:website":"www.antiox.com",
    "wof:name":"Health Maintenance Programs",
    "wof:placetype":"venue"
},
  "geometry": {"coordinates":[-73.81076899999999,41.069891],"type":"Point"}
}