{
  "type": "Feature",
  "properties": {
    "addr:full":"103 Waverly St Yonkers NY 10701",
    "addr:housenumber":"103",
    "addr:postcode":"10701",
    "addr:street":"Waverly St",
    "iso:country":"US",
    "sg:address":"103 Waverly St",
    "sg:city":"Yonkers",
    "sg:classifiers":[
        {
            "category":"Building & Trades",
            "subcategory":"Construction",
            "type":"Services"
        }
    ],
    "sg:phone":"+1 914 968 8213",
    "sg:postcode":"10701",
    "sg:province":"NY",
    "sg:tags":[
        "contractor"
    ],
    "wof:name":"Collado Contracting",
    "wof:placetype":"venue"
},
  "geometry": {"coordinates":[-73.89347600000001,40.929108],"type":"Point"}
}