{
  "type": "Feature",
  "properties": {
    "addr:full":"5401 Church Ave Brooklyn NY 11203",
    "addr:housenumber":"5401",
    "addr:postcode":"11203",
    "addr:street":"Church Ave",
    "iso:country":"US",
    "sg:address":"5401 Church Ave",
    "sg:city":"Brooklyn",
    "sg:classifiers":[
        {
            "category":"Deli",
            "type":"Food & Drink"
        },
        {
            "category":"Food & Beverages",
            "subcategory":"Bakery",
            "type":"Retail Goods"
        }
    ],
    "sg:phone":"+1 347 295 1511",
    "sg:postcode":"11203",
    "sg:province":"NY",
    "sg:tags":[
        "sandwich"
    ],
    "wof:name":"5401 Gourmet Deli",
    "wof:placetype":"venue"
},
  "geometry": {"coordinates":[-73.926541,40.652526],"type":"Point"}
}