{
  "type": "Feature",
  "properties": {
    "iso:country":"US",
    "sg:address":"434 6 Ave",
    "sg:city":"New York",
    "sg:classifiers":[
        {
            "category":"Shopping",
            "subcategory":"Photographic Equipment",
            "type":"Retail Goods"
        }
    ],
    "sg:phone":"+1   ",
    "sg:postcode":"10011",
    "sg:province":"NY",
    "sg:tags":[
        "photo",
        "supply"
    ],
    "wof:name":"Village Photo",
    "wof:placetype":"venue"
},
  "geometry": {"coordinates":[-74.001413,40.731065],"type":"Point"}
}