{
  "type": "Feature",
  "properties": {
    "addr:full":"5404 State Hwy 281 Homer NY 13077",
    "addr:housenumber":"5404",
    "addr:postcode":"13077",
    "addr:street":"State Hwy 281",
    "iso:country":"US",
    "sg:address":"5404 State Hwy 281",
    "sg:city":"Homer",
    "sg:classifiers":[
        {
            "category":"Restaurant",
            "type":"Food & Drink"
        }
    ],
    "sg:phone":"+1   ",
    "sg:postcode":"13077",
    "sg:province":"NY",
    "sg:tags":[
        "eating"
    ],
    "wof:name":"Rosemary M Phillips",
    "wof:placetype":"venue"
},
  "geometry": {"coordinates":[-76.181144,42.657506],"type":"Point"}
}