{
  "type": "Feature",
  "properties": {
    "addr:full":"505 Park Ave New York NY 10022",
    "addr:housenumber":"505",
    "addr:postcode":"10022",
    "addr:street":"Park Ave",
    "iso:country":"US",
    "sg:address":"505 Park Ave",
    "sg:city":"New York",
    "sg:classifiers":[
        {
            "category":"Professional",
            "subcategory":"Accounting & Tax Preparation",
            "type":"Services"
        }
    ],
    "sg:phone":"+1 212 888 5959",
    "sg:postcode":"10022",
    "sg:province":"NY",
    "sg:tags":[
        "bookkeeping",
        "general"
    ],
    "sg:website":"www.accountingmanagement.com",
    "wof:name":"Montrose Accounting Co LLC",
    "wof:placetype":"venue"
},
  "geometry": {"coordinates":[-73.969388,40.763299],"type":"Point"}
}