{
  "type": "Feature",
  "properties": {
    "iso:country":"US",
    "sg:address":"980 Westfall Rd",
    "sg:city":"Rochester",
    "sg:classifiers":[
        {
            "category":"Health Services",
            "subcategory":"Doctor",
            "type":"Services"
        }
    ],
    "sg:phone":"+1 585 442 4690",
    "sg:postcode":"14618",
    "sg:province":"NY",
    "sg:tags":[
        "physician",
        "surgeon"
    ],
    "wof:name":"Westfall Cardiology Pllc",
    "wof:placetype":"venue"
},
  "geometry": {"coordinates":[-77.59340899999999,43.115467],"type":"Point"}
}