{
  "type": "Feature",
  "properties": {
    "iso:country":"US",
    "sg:address":"4228 Ridge Lea Rd",
    "sg:city":"Buffalo",
    "sg:classifiers":[
        {
            "category":"Building & Trades",
            "subcategory":"Electrical",
            "type":"Services"
        }
    ],
    "sg:phone":"+1 716 807 0030",
    "sg:postcode":"14228",
    "sg:province":"NY",
    "sg:tags":[
        "general",
        "electrical",
        "contractor"
    ],
    "wof:name":"Bison Electrical Services",
    "wof:placetype":"venue"
},
  "geometry": {"coordinates":[-78.811931,42.99982],"type":"Point"}
}