{
  "type": "Feature",
  "properties": {
    "addr:full":"67 Grant Ave Harrison NY 10528",
    "addr:housenumber":"67",
    "addr:postcode":"10528",
    "addr:street":"Grant Ave",
    "iso:country":"US",
    "sg:address":"67 Grant Ave",
    "sg:city":"Harrison",
    "sg:classifiers":[
        {
            "category":"Retail",
            "subcategory":"Repair Shop",
            "type":"Services"
        },
        {
            "category":"Building & Trades",
            "subcategory":"Plumbing",
            "type":"Services"
        }
    ],
    "sg:phone":"+1 914 946 5558",
    "sg:postcode":"10528",
    "sg:province":"NY",
    "sg:tags":[
        "installation",
        "heating",
        "system",
        "air",
        "conditioning",
        "plumbing",
        "contractor"
    ],
    "sg:website":"www.bruniandcampisi.com",
    "wof:name":"Bruni & Campisi Plumbing & Htg",
    "wof:placetype":"venue"
},
  "geometry": {"coordinates":[-73.707365,40.968952],"type":"Point"}
}