{
  "type": "Feature",
  "properties": {
    "iso:country":"US",
    "sg:address":"667 Powell St",
    "sg:city":"Brooklyn",
    "sg:classifiers":[
        {
            "category":"Retail",
            "subcategory":"Auto Repair",
            "type":"Services"
        }
    ],
    "sg:phone":"+1   ",
    "sg:postcode":"11212",
    "sg:province":"NY",
    "sg:tags":[
        "automotive"
    ],
    "wof:name":"Leroy Binns",
    "wof:placetype":"venue"
},
  "geometry": {"coordinates":[-73.900835,40.658034],"type":"Point"}
}