{
  "type": "Feature",
  "properties": {
    "addr:full":"1571 Ridge Rd E Rochester NY 14621",
    "addr:housenumber":"1571",
    "addr:postcode":"14621",
    "addr:street":"Ridge Rd E",
    "iso:country":"US",
    "sg:address":"1571 Ridge Rd E",
    "sg:city":"Rochester",
    "sg:classifiers":[
        {
            "category":"Restaurant",
            "type":"Food & Drink"
        }
    ],
    "sg:phone":"+1 585 266 0109",
    "sg:postcode":"14621",
    "sg:province":"NY",
    "sg:website":"www.mcdonalds.com",
    "wof:name":"Mc Donald's",
    "wof:placetype":"venue"
},
  "geometry": {"coordinates":[-77.57556200000001,43.199169],"type":"Point"}
}