{
  "type": "Feature",
  "properties": {
    "iso:country":"US",
    "sg:address":"472 Grand Blvd",
    "sg:city":"Deer Park",
    "sg:classifiers":[
        {
            "category":"Deli",
            "type":"Food & Drink"
        }
    ],
    "sg:menulink":"http://www.allmenus.com/ny/babylon/254620-venezia-delicatessen--caterers/menu/",
    "sg:phone":"+1 631 242 1165",
    "sg:postcode":"11729",
    "sg:province":"NY",
    "sg:tags":[
        "american"
    ],
    "wof:name":"Venezia Delicatessen & Caterers",
    "wof:placetype":"venue"
},
  "geometry": {"coordinates":[-73.32867299999999,40.756976],"type":"Point"}
}