{
  "type": "Feature",
  "properties": {
    "addr:full":"815 Westchester Ave Bronx NY 10455",
    "addr:housenumber":"815",
    "addr:postcode":"10455",
    "addr:street":"Westchester Ave",
    "iso:country":"US",
    "sg:address":"815 Westchester Ave",
    "sg:city":"Bronx",
    "sg:classifiers":[
        {
            "category":"Manufacturing",
            "subcategory":"Printing",
            "type":"Manufacturing & Wholesale Goods"
        }
    ],
    "sg:phone":"+1   ",
    "sg:postcode":"10455",
    "sg:province":"NY",
    "sg:tags":[
        "periodical"
    ],
    "wof:name":"Nyc Taxi Magazine Corp",
    "wof:placetype":"venue"
},
  "geometry": {"coordinates":[-73.901872,40.819597],"type":"Point"}
}