{
  "type": "Feature",
  "properties": {
    "addr:full":"65 State Hwy 96 Owego NY 13827",
    "addr:housenumber":"65",
    "addr:postcode":"13827",
    "addr:street":"State Hwy 96",
    "iso:country":"US",
    "sg:address":"65 State Hwy 96",
    "sg:city":"Owego",
    "sg:classifiers":[
        {
            "category":"Restaurant",
            "type":"Food & Drink"
        }
    ],
    "sg:phone":"+1 607 687 2668",
    "sg:postcode":"13827",
    "sg:province":"NY",
    "sg:tags":[
        "parlor",
        "ice",
        "cream"
    ],
    "wof:name":"Owego Soft Serve",
    "wof:placetype":"venue"
},
  "geometry": {"coordinates":[-76.27197099999999,42.127458],"type":"Point"}
}