{
  "type": "Feature",
  "properties": {
    "iso:country":"US",
    "sg:address":"146 Main St",
    "sg:city":"Port Washington",
    "sg:classifiers":[
        {
            "category":"Retail",
            "subcategory":"Laundry & Dry Cleaning",
            "type":"Services"
        }
    ],
    "sg:phone":"+1 516 883 0808",
    "sg:postcode":"11050",
    "sg:province":"NY",
    "sg:tags":[
        "cleaners"
    ],
    "wof:name":"Fancy Cleaners",
    "wof:placetype":"venue"
},
  "geometry": {"coordinates":[-73.69135799999999,40.830312],"type":"Point"}
}