{
  "type": "Feature",
  "properties": {
    "iso:country":"US",
    "sg:address":"Bedford Ave & Flushing Ave",
    "sg:city":"Brooklyn",
    "sg:classifiers":[
        {
            "category":"Autos & Motor Vehicles",
            "subcategory":"Fuel & Gas Station",
            "type":"Retail Goods"
        }
    ],
    "sg:postcode":"11226",
    "sg:province":"NY",
    "wof:name":"Pride gas station",
    "wof:placetype":"venue"
},
  "geometry": {"coordinates":[-73.957025,40.698971],"type":"Point"}
}