{
  "type": "Feature",
  "properties": {
    "addr:full":"4410 Austin Blvd Island Park NY 11558",
    "addr:housenumber":"4410",
    "addr:postcode":"11558",
    "addr:street":"Austin Blvd;Park",
    "iso:country":"US",
    "sg:address":"4410 Austin Blvd",
    "sg:city":"Island Park",
    "sg:classifiers":[
        {
            "category":"Autos & Motor Vehicles",
            "subcategory":"Motorcycle Sales",
            "type":"Retail Goods"
        }
    ],
    "sg:phone":"+1   ",
    "sg:postcode":"11558",
    "sg:province":"NY",
    "sg:tags":[
        "importer",
        "scooter"
    ],
    "wof:name":"New ERA Trans Inc",
    "wof:placetype":"venue"
},
  "geometry": {"coordinates":[-73.65144600000001,40.603323],"type":"Point"}
}