{
  "type": "Feature",
  "properties": {
    "iso:country":"US",
    "sg:address":"18 E 53rd Street",
    "sg:city":"New York",
    "sg:classifiers":[
        {
            "category":"Health Services",
            "subcategory":"Dentist",
            "type":"Services"
        }
    ],
    "sg:phone":"+1 212 308 7504",
    "sg:postcode":"10022",
    "sg:province":"NY",
    "wof:name":"Schwartz Marc I Dr DMD",
    "wof:placetype":"venue"
},
  "geometry": {"coordinates":[-73.975818,40.76041],"type":"Point"}
}