{
  "type": "Feature",
  "properties": {
    "addr:full":"155 E 38th St New York NY 10016",
    "addr:housenumber":"155",
    "addr:postcode":"10016",
    "addr:street":"E 38Th St",
    "iso:country":"US",
    "sg:address":"155 E 38th St",
    "sg:city":"New York",
    "sg:classifiers":[
        {
            "category":"Professional",
            "subcategory":"Business Services",
            "type":"Services"
        }
    ],
    "sg:phone":"+1 212 697 6170",
    "sg:postcode":"10016",
    "sg:province":"NY",
    "sg:tags":[
        "agent",
        "artist"
    ],
    "sg:website":"www.anitagrien.com",
    "wof:name":"Anita Grien Rep Artists",
    "wof:placetype":"venue"
},
  "geometry": {"coordinates":[-73.976702,40.748561],"type":"Point"}
}