{
  "type": "Feature",
  "properties": {
    "iso:country":"US",
    "sg:address":"27 Stewart St",
    "sg:city":"Brooklyn",
    "sg:classifiers":[
        {
            "category":"Building & Trades",
            "subcategory":"Plumbing",
            "type":"Services"
        }
    ],
    "sg:phone":"+1 718 443 0018",
    "sg:postcode":"11207",
    "sg:province":"NY",
    "sg:tags":[
        "mechanical",
        "contractor"
    ],
    "wof:name":"Central Mechanical Systems",
    "wof:placetype":"venue"
},
  "geometry": {"coordinates":[-73.90439600000001,40.680007],"type":"Point"}
}