{
  "type": "Feature",
  "properties": {
    "addr:full":"12491 Hanford Rd Silver Creek NY 14136",
    "addr:housenumber":"12491",
    "addr:postcode":"14136",
    "addr:street":"Hanford Rd",
    "iso:country":"US",
    "sg:address":"12491 Hanford Rd",
    "sg:city":"Silver Creek",
    "sg:classifiers":[
        {
            "category":"Building & Trades",
            "subcategory":"Plumbing",
            "type":"Services"
        }
    ],
    "sg:phone":"+1 716 934 4863",
    "sg:postcode":"14136",
    "sg:province":"NY",
    "sg:tags":[
        "plumbing",
        "air",
        "heating",
        "conditioning",
        "contractor"
    ],
    "wof:name":"Guarcellos",
    "wof:placetype":"venue"
},
  "geometry": {"coordinates":[-79.141541,42.546376],"type":"Point"}
}