{
  "type": "Feature",
  "properties": {
    "iso:country":"US",
    "sg:address":"1459 Wythe Pl",
    "sg:city":"Bronx",
    "sg:classifiers":[
        {
            "category":"Social Services",
            "subcategory":"Job Training",
            "type":"Services"
        }
    ],
    "sg:phone":"+1 718 537 3592",
    "sg:postcode":"10452",
    "sg:province":"NY",
    "sg:tags":[
        "retardation",
        "disabled",
        "mental",
        "dev"
    ],
    "wof:name":"Unique People Svc Inc",
    "wof:placetype":"venue"
},
  "geometry": {"coordinates":[-73.91380100000001,40.841153],"type":"Point"}
}