{
  "type": "Feature",
  "properties": {
    "addr:full":"333 Plymouth Ave S Rochester NY 14608",
    "addr:housenumber":"333",
    "addr:postcode":"14608",
    "addr:street":"Plymouth Ave S",
    "iso:country":"US",
    "sg:address":"333 Plymouth Ave S",
    "sg:city":"Rochester",
    "sg:classifiers":[
        {
            "category":"Arena",
            "subcategory":"Sports Club",
            "type":"Entertainment"
        }
    ],
    "sg:phone":"+1 585 262 2009",
    "sg:postcode":"14608",
    "sg:province":"NY",
    "sg:tags":[
        "recreation",
        "amusement"
    ],
    "wof:name":"Frontier Fields",
    "wof:placetype":"venue"
},
  "geometry": {"coordinates":[-77.613113,43.148954],"type":"Point"}
}