{
  "type": "Feature",
  "properties": {
    "addr:full":"70 W 40th St Fl 9 New York NY 10018",
    "addr:housenumber":"70;9",
    "addr:postcode":"new;10018",
    "addr:street":"W 40Th St",
    "iso:country":"US",
    "sg:address":"70 W 40th St Fl 9",
    "sg:city":"New York",
    "sg:classifiers":[
        {
            "category":"Professional",
            "subcategory":"Employment Agencies",
            "type":"Services"
        }
    ],
    "sg:phone":"+1 212 867 8080",
    "sg:postcode":"10018",
    "sg:province":"NY",
    "wof:name":"Hire Options Inc",
    "wof:placetype":"venue"
},
  "geometry": {"coordinates":[-73.98453000000001,40.753184],"type":"Point"}
}