{
  "type": "Feature",
  "properties": {
    "addr:full":"43 Saratoga Ave S Glens Falls NY 12803",
    "addr:housenumber":"43",
    "addr:postcode":"12803",
    "addr:street":"Saratoga Ave S Glens",
    "iso:country":"US",
    "sg:address":"43 Saratoga Ave",
    "sg:city":"S Glens Falls",
    "sg:classifiers":[
        {
            "category":"Personal",
            "subcategory":"Beauty Salon",
            "type":"Services"
        }
    ],
    "sg:phone":"+1 518 793 2473",
    "sg:postcode":"12803",
    "sg:province":"NY",
    "wof:name":"Elaine's Shear Glamour",
    "wof:placetype":"venue"
},
  "geometry": {"coordinates":[-73.63584299999999,43.296404],"type":"Point"}
}