{
  "type": "Feature",
  "properties": {
    "addr:full":"1040 N Broadway Massapequa NY 11758",
    "addr:housenumber":"1040",
    "addr:postcode":"11758",
    "addr:street":"N Broadway",
    "iso:country":"US",
    "sg:address":"1040 N Broadway",
    "sg:city":"Massapequa",
    "sg:classifiers":[
        {
            "category":"Home & Garden",
            "subcategory":"Building Materials",
            "type":"Retail Goods"
        }
    ],
    "sg:phone":"+1 516 694 3591",
    "sg:postcode":"11758",
    "sg:province":"NY",
    "sg:website":"http://www.nicolettesforthehome.com",
    "wof:name":"Nicolette's for the Home",
    "wof:placetype":"venue"
},
  "geometry": {"coordinates":[-73.46109,40.70977],"type":"Point"}
}