{
  "type": "Feature",
  "properties": {
    "addr:full":"112 N Main St Elmira NY 14901",
    "addr:housenumber":"112",
    "addr:postcode":"14901",
    "addr:street":"N Main St",
    "iso:country":"US",
    "sg:address":"112 N Main St",
    "sg:city":"Elmira",
    "sg:classifiers":[
        {
            "category":"Shopping",
            "subcategory":"Gifts & Souvenirs",
            "type":"Retail Goods"
        }
    ],
    "sg:phone":"+1 607 733 8569",
    "sg:postcode":"14901",
    "sg:province":"NY",
    "sg:tags":[
        "shop"
    ],
    "wof:name":"Pineapple House",
    "wof:placetype":"venue"
},
  "geometry": {"coordinates":[-76.807241,42.087977],"type":"Point"}
}