{
  "type": "Feature",
  "properties": {
    "iso:country":"US",
    "sg:address":"151 Industrial Loop",
    "sg:city":"Staten Island",
    "sg:classifiers":[
        {
            "category":"Wholesale",
            "subcategory":"Home Furnishings",
            "type":"Manufacturing & Wholesale Goods"
        }
    ],
    "sg:phone":"+1 718 967 5559",
    "sg:postcode":"10309",
    "sg:province":"NY",
    "sg:tags":[
        "blind",
        "shade"
    ],
    "wof:name":"Decor-Rite the Vertical Blind Factory",
    "wof:placetype":"venue"
},
  "geometry": {"coordinates":[-74.230797,40.549801],"type":"Point"}
}