{
  "type": "Feature",
  "properties": {
    "addr:full":"608 Vine St Liverpool NY 13088",
    "addr:housenumber":"608",
    "addr:postcode":"13088",
    "addr:street":"Vine St",
    "iso:country":"US",
    "sg:address":"608 Vine St",
    "sg:city":"Liverpool",
    "sg:classifiers":[
        {
            "category":"Structure",
            "subcategory":"Office Building",
            "type":"Public Place"
        }
    ],
    "sg:phone":"+1 315 457 2306",
    "sg:postcode":"13088",
    "sg:province":"NY",
    "sg:tags":[
        "park"
    ],
    "wof:name":"Aspen & Vine Properties",
    "wof:placetype":"venue"
},
  "geometry": {"coordinates":[-76.205078,43.104369],"type":"Point"}
}