{
  "type": "Feature",
  "properties": {
    "addr:full":"100 E Main St Endicott NY 13760",
    "addr:housenumber":"100",
    "addr:postcode":"13760",
    "addr:street":"E Main St",
    "iso:country":"US",
    "sg:address":"100 E Main St",
    "sg:city":"Endicott",
    "sg:classifiers":[
        {
            "category":"Shopping",
            "subcategory":"Pharmacy",
            "type":"Retail Goods"
        }
    ],
    "sg:phone":"+1   ",
    "sg:postcode":"13760",
    "sg:province":"NY",
    "sg:tags":[
        "laboratory",
        "photofinishing",
        "f"
    ],
    "wof:name":"Eckerd",
    "wof:placetype":"venue"
},
  "geometry": {"coordinates":[-76.063903,42.095038],"type":"Point"}
}