{
  "type": "Feature",
  "properties": {
    "iso:country":"US",
    "sg:address":"620 Westfall Rd",
    "sg:city":"Rochester",
    "sg:classifiers":[
        {
            "category":"Government",
            "subcategory":"Office",
            "type":"Public Place"
        }
    ],
    "sg:phone":"+1 585 241 5770",
    "sg:postcode":"14620",
    "sg:province":"NY",
    "sg:tags":[
        "state",
        "resource"
    ],
    "wof:name":"Community Services Office",
    "wof:placetype":"venue"
},
  "geometry": {"coordinates":[-77.607456,43.115039],"type":"Point"}
}