{
  "type": "Feature",
  "properties": {
    "addr:full":"69 Central Ave Brooklyn NY 11206",
    "addr:housenumber":"69",
    "addr:postcode":"11206",
    "addr:street":"Central Ave",
    "iso:country":"US",
    "sg:address":"69 Central Ave",
    "sg:city":"Brooklyn",
    "sg:classifiers":[
        {
            "category":"Banks & Credit Unions",
            "subcategory":"Bank",
            "type":"Services"
        }
    ],
    "sg:phone":"+1 718 381 1500",
    "sg:postcode":"11206",
    "sg:province":"NY",
    "sg:tags":[
        "financing"
    ],
    "wof:name":"Fund For The City Of Ny",
    "wof:placetype":"venue"
},
  "geometry": {"coordinates":[-73.929805,40.700824],"type":"Point"}
}