{
  "type": "Feature",
  "properties": {
    "addr:full":"198 Reutter Dr Duanesburg NY 12056",
    "addr:housenumber":"198",
    "addr:postcode":"12056",
    "addr:street":"Reutter Dr",
    "iso:country":"US",
    "sg:address":"198 Reutter Dr",
    "sg:city":"Duanesburg",
    "sg:classifiers":[
        {
            "category":"Building & Trades",
            "subcategory":"Construction",
            "type":"Services"
        }
    ],
    "sg:phone":"+1 518 355 1905",
    "sg:postcode":"12056",
    "sg:province":"NY",
    "sg:tags":[
        "nonresidential"
    ],
    "wof:name":"Upstate Building Specialities",
    "wof:placetype":"venue"
},
  "geometry": {"coordinates":[-74.036817,42.755777],"type":"Point"}
}