{
  "type": "Feature",
  "properties": {
    "addr:full":"400 Main St Islip NY 11751",
    "addr:housenumber":"400",
    "addr:postcode":"11751",
    "addr:street":"Main St",
    "iso:country":"US",
    "sg:address":"400 Main St",
    "sg:city":"Islip",
    "sg:classifiers":[
        {
            "category":"Shopping",
            "subcategory":"Crafts & Fabrics",
            "type":"Retail Goods"
        }
    ],
    "sg:phone":"+1 631 206 6215",
    "sg:postcode":"11751",
    "sg:province":"NY",
    "sg:tags":[
        "shop",
        "material",
        "quilting",
        "sewing",
        "supply"
    ],
    "sg:website":"http://www.sewwhatsnew.biz",
    "wof:name":"Sew What's New",
    "wof:placetype":"venue"
},
  "geometry": {"coordinates":[-73.21581999999999,40.728668],"type":"Point"}
}