{
  "type": "Feature",
  "properties": {
    "addr:full":"1389 5 Ave Bay Shore NY 11706",
    "addr:housenumber":"1389",
    "addr:postcode":"11706",
    "addr:street":"5 Ave",
    "iso:country":"US",
    "sg:address":"1389 5 Ave",
    "sg:city":"Bay Shore",
    "sg:classifiers":[
        {
            "category":"Restaurant",
            "type":"Food & Drink"
        }
    ],
    "sg:phone":"+1 631 666 4490",
    "sg:postcode":"11706",
    "sg:province":"NY",
    "sg:tags":[
        "delicatessen"
    ],
    "wof:name":"Ranko News Inc",
    "wof:placetype":"venue"
},
  "geometry": {"coordinates":[-73.26101800000001,40.730034],"type":"Point"}
}