{
  "type": "Feature",
  "properties": {
    "addr:full":"2318 Nostrand Avenue Brooklyn NY 11210",
    "addr:housenumber":"2318",
    "addr:postcode":"11210",
    "addr:street":"Nostrand Avenue",
    "iso:country":"US",
    "sg:address":"2318 Nostrand Avenue",
    "sg:city":"Brooklyn",
    "sg:classifiers":[
        {
            "category":"Restaurant",
            "type":"Food & Drink"
        }
    ],
    "sg:phone":"+1 718 951 7459",
    "sg:postcode":"11210",
    "sg:province":"NY",
    "sg:tags":[
        "chinese"
    ],
    "wof:name":"Didi Chinese Restaurant",
    "wof:placetype":"venue"
},
  "geometry": {"coordinates":[-73.94703199999999,40.628334],"type":"Point"}
}