{
  "type": "Feature",
  "properties": {
    "addr:full":"15 Koenig Cir Tonawanda NY 14150",
    "addr:housenumber":"15",
    "addr:postcode":"14150",
    "addr:street":"Koenig Cir",
    "iso:country":"US",
    "sg:address":"15 Koenig Cir",
    "sg:city":"Tonawanda",
    "sg:classifiers":[
        {
            "category":"Organizations",
            "subcategory":"Religious Organization",
            "type":"Services"
        }
    ],
    "sg:phone":"+1 716 836 6220",
    "sg:postcode":"14150",
    "sg:province":"NY",
    "wof:name":"Zion United Church Of Christ",
    "wof:placetype":"venue"
},
  "geometry": {"coordinates":[-78.835506,43.000467],"type":"Point"}
}