{
  "type": "Feature",
  "properties": {
    "addr:full":"58 N Main St Angola NY 14006",
    "addr:housenumber":"58",
    "addr:postcode":"14006",
    "addr:street":"N Main St",
    "iso:country":"US",
    "sg:address":"58 N Main St",
    "sg:city":"Angola",
    "sg:classifiers":[
        {
            "category":"Professional",
            "subcategory":"Business Services",
            "type":"Services"
        }
    ],
    "sg:phone":"+1 716 549 7653",
    "sg:postcode":"14006",
    "sg:province":"NY",
    "sg:tags":[
        "real estate",
        "auctioneer"
    ],
    "wof:name":"Phil Cinque Auction Svc Inc",
    "wof:placetype":"venue"
},
  "geometry": {"coordinates":[-79.02776900000001,42.639871],"type":"Point"}
}