{
  "type": "Feature",
  "properties": {
    "addr:full":"155 E 56 St New York NY 10022",
    "addr:housenumber":"155;56",
    "addr:postcode":"10022",
    "addr:street":"E;St",
    "iso:country":"US",
    "sg:address":"155 E 56 St",
    "sg:city":"New York",
    "sg:classifiers":[
        {
            "category":"Manufacturing",
            "subcategory":"Wood Products",
            "type":"Manufacturing & Wholesale Goods"
        }
    ],
    "sg:phone":"+1   ",
    "sg:postcode":"10022",
    "sg:province":"NY",
    "sg:tags":[
        "mfg",
        "cork",
        "supply"
    ],
    "wof:name":"Korquins",
    "wof:placetype":"venue"
},
  "geometry": {"coordinates":[-73.968311,40.759823],"type":"Point"}
}