{
  "type": "Feature",
  "properties": {
    "addr:full":"852 10th Avenue New York NY 10019",
    "addr:housenumber":"852",
    "addr:postcode":"10019",
    "addr:street":"10Th Avenue",
    "iso:country":"US",
    "sg:address":"852 10th Avenue",
    "sg:city":"New York",
    "sg:classifiers":[
        {
            "category":"Shopping",
            "subcategory":"Florist",
            "type":"Retail Goods"
        }
    ],
    "sg:phone":"+1 212 765 6929",
    "sg:postcode":"10019",
    "sg:province":"NY",
    "wof:name":"Simpon & Company Florists",
    "wof:placetype":"venue"
},
  "geometry": {"coordinates":[-73.988748,40.768606],"type":"Point"}
}