{
  "type": "Feature",
  "properties": {
    "iso:country":"US",
    "sg:address":"700 Merrick Rd",
    "sg:city":"Baldwin",
    "sg:classifiers":[
        {
            "category":"Building & Trades",
            "subcategory":"Construction",
            "type":"Services"
        }
    ],
    "sg:phone":"+1 516 623 2271",
    "sg:postcode":"11510",
    "sg:province":"NY",
    "sg:tags":[
        "asbestos",
        "removal"
    ],
    "wof:name":"Best Way Abatement",
    "wof:placetype":"venue"
},
  "geometry": {"coordinates":[-73.61433100000001,40.651529],"type":"Point"}
}