{
  "type": "Feature",
  "properties": {
    "addr:full":"35 Smith St Nanuet NY 10954",
    "addr:housenumber":"35",
    "addr:postcode":"10954",
    "addr:street":"Smith St",
    "iso:country":"US",
    "sg:address":"35 Smith St",
    "sg:city":"Nanuet",
    "sg:classifiers":[
        {
            "category":"Health Services",
            "subcategory":"Doctor",
            "type":"Services"
        }
    ],
    "sg:phone":"+1 845 623 7100",
    "sg:postcode":"10954",
    "sg:province":"NY",
    "sg:tags":[
        "physician",
        "surgeon"
    ],
    "wof:name":"Clarkstown Pediatrics Assoc",
    "wof:placetype":"venue"
},
  "geometry": {"coordinates":[-73.99958100000001,41.093242],"type":"Point"}
}