{
  "type": "Feature",
  "properties": {
    "iso:country":"US",
    "sg:address":"1 Willard Ave",
    "sg:city":"Houghton",
    "sg:classifiers":[
        {
            "category":"Education",
            "subcategory":"College",
            "type":"Public Place"
        }
    ],
    "sg:phone":"+1 585 567 9602",
    "sg:postcode":"14744",
    "sg:province":"NY",
    "wof:name":"Campus Center Store",
    "wof:placetype":"venue"
},
  "geometry": {"coordinates":[-78.154247,42.427876],"type":"Point"}
}