{
  "type": "Feature",
  "properties": {
    "iso:country":"US",
    "sg:address":"62 Republic St",
    "sg:city":"Buffalo",
    "sg:classifiers":[
        {
            "category":"Social Services",
            "type":"Services"
        }
    ],
    "sg:phone":"+1 716 852 1262",
    "sg:postcode":"14204",
    "sg:province":"NY",
    "sg:tags":[
        "organization",
        "welfare"
    ],
    "wof:name":"CAO Head Start Program",
    "wof:placetype":"venue"
},
  "geometry": {"coordinates":[-78.86239399999999,42.866376],"type":"Point"}
}