{
  "type": "Feature",
  "properties": {
    "addr:full":"740 Driving Park Ave Rochester NY 14613",
    "addr:housenumber":"740",
    "addr:postcode":"14613",
    "addr:street":"Driving Park Ave",
    "iso:country":"US",
    "sg:address":"740 Driving Park Ave",
    "sg:city":"Rochester",
    "sg:classifiers":[
        {
            "category":"Recreation",
            "type":"Entertainment"
        }
    ],
    "sg:phone":"+1   ",
    "sg:postcode":"14613",
    "sg:province":"NY",
    "wof:name":"Holy Apostles Church",
    "wof:placetype":"venue"
},
  "geometry": {"coordinates":[-77.65326899999999,43.182984],"type":"Point"}
}