{
  "type": "Feature",
  "properties": {
    "addr:full":"2870 Wilson Ave Bellmore NY 11710",
    "addr:housenumber":"2870",
    "addr:postcode":"11710",
    "addr:street":"Wilson Ave",
    "iso:country":"US",
    "sg:address":"2870 Wilson Ave",
    "sg:city":"Bellmore",
    "sg:classifiers":[
        {
            "category":"Professional",
            "type":"Services"
        }
    ],
    "sg:phone":"+1   ",
    "sg:postcode":"11710",
    "sg:province":"NY",
    "wof:name":"Imagebeyondcom Ltd",
    "wof:placetype":"venue"
},
  "geometry": {"coordinates":[-73.52149199999999,40.673543],"type":"Point"}
}