{
  "type": "Feature",
  "properties": {
    "iso:country":"US",
    "sg:address":"98 Hotchkiss St",
    "sg:city":"Jamestown",
    "sg:classifiers":[
        {
            "category":"Wholesale",
            "subcategory":"Electrical",
            "type":"Manufacturing & Wholesale Goods"
        }
    ],
    "sg:phone":"+1 716 665 2970",
    "sg:postcode":"14701",
    "sg:province":"NY",
    "sg:tags":[
        "equipment",
        "electronic"
    ],
    "wof:name":"United Indus Dstrs of Jmestown",
    "wof:placetype":"venue"
},
  "geometry": {"coordinates":[-79.22689099999999,42.113287],"type":"Point"}
}