{
  "type": "Feature",
  "properties": {
    "addr:full":"806 Nostrand Ave Brooklyn NY 11216",
    "addr:housenumber":"806",
    "addr:postcode":"11216",
    "addr:street":"Nostrand Ave",
    "iso:country":"US",
    "sg:address":"806 Nostrand Ave",
    "sg:city":"Brooklyn",
    "sg:classifiers":[
        {
            "category":"Travel",
            "subcategory":"Travel Agent",
            "type":"Entertainment"
        }
    ],
    "sg:phone":"+1 718 467 1395",
    "sg:postcode":"11216",
    "sg:province":"NY",
    "sg:tags":[
        "agency",
        "bureau"
    ],
    "wof:name":"Trident Intl Travel",
    "wof:placetype":"venue"
},
  "geometry": {"coordinates":[-73.950456,40.671272],"type":"Point"}
}