{
  "type": "Feature",
  "properties": {
    "addr:full":"10705 Guy R Brewer Blvd Jamaica NY 11433",
    "addr:housenumber":"10705",
    "addr:postcode":"11433",
    "addr:street":"Guy R Brewer Blvd",
    "iso:country":"US",
    "sg:address":"10705 Guy R Brewer Blvd",
    "sg:city":"Jamaica",
    "sg:classifiers":[
        {
            "category":"Retail",
            "subcategory":"Repair Shop",
            "type":"Services"
        }
    ],
    "sg:phone":"+1 718 805 8281",
    "sg:postcode":"11433",
    "sg:province":"NY",
    "sg:tags":[
        "reupholstery",
        "furniture"
    ],
    "sg:website":"www.dkfurnitureandupholstery.com",
    "wof:name":"Dk Furniture & Upholstery",
    "wof:placetype":"venue"
},
  "geometry": {"coordinates":[-73.79223,40.697951],"type":"Point"}
}