{
  "type": "Feature",
  "properties": {
    "addr:full":"3900 Victory Blvd Staten Island NY 10314",
    "addr:housenumber":"3900",
    "addr:postcode":"10314",
    "addr:street":"Victory Blvd",
    "iso:country":"US",
    "sg:address":"3900 Victory Blvd",
    "sg:city":"Staten Island",
    "sg:classifiers":[
        {
            "category":"Shopping",
            "subcategory":"Clothing, Apparel, & Fashions",
            "type":"Retail Goods"
        }
    ],
    "sg:phone":"+1 917 612 6534",
    "sg:postcode":"10314",
    "sg:province":"NY",
    "wof:name":"All Skull Wear",
    "wof:placetype":"venue"
},
  "geometry": {"coordinates":[-74.18423,40.594373],"type":"Point"}
}