{
  "type": "Feature",
  "properties": {
    "addr:full":"11 Seeger Dr Nanuet NY 10954",
    "addr:housenumber":"11",
    "addr:postcode":"10954",
    "addr:street":"Seeger Dr",
    "iso:country":"US",
    "sg:address":"11 Seeger Dr",
    "sg:city":"Nanuet",
    "sg:classifiers":[
        {
            "category":"Food & Beverages",
            "subcategory":"Bakery",
            "type":"Retail Goods"
        },
        {
            "category":"Wholesale",
            "subcategory":"Groceries",
            "type":"Manufacturing & Wholesale Goods"
        }
    ],
    "sg:phone":"+1 845 627 2323",
    "sg:postcode":"10954",
    "sg:province":"NY",
    "sg:tags":[
        "baker"
    ],
    "wof:name":"Carousel Cakes",
    "wof:placetype":"venue"
},
  "geometry": {"coordinates":[-74.002314,41.099207],"type":"Point"}
}