{
  "type": "Feature",
  "properties": {
    "addr:full":"285 W Broadway New York NY 10013",
    "addr:housenumber":"285",
    "addr:postcode":"10013",
    "addr:street":"W Broadway",
    "iso:country":"US",
    "sg:address":"285 W Broadway",
    "sg:city":"New York",
    "sg:classifiers":[
        {
            "category":"Communications",
            "subcategory":"Film & Video Production",
            "type":"Services"
        }
    ],
    "sg:phone":"+1 212 343 3099",
    "sg:postcode":"10013",
    "sg:province":"NY",
    "sg:tags":[
        "motion",
        "picture",
        "studio",
        "producer"
    ],
    "wof:name":"Clock Wise Productions Inc",
    "wof:placetype":"venue"
},
  "geometry": {"coordinates":[-74.004845,40.720857],"type":"Point"}
}