{
  "type": "Feature",
  "properties": {
    "addr:full":"297 Wantagh Ave Levittown NY 11756",
    "addr:housenumber":"297",
    "addr:postcode":"11756",
    "addr:street":"Wantagh Ave",
    "iso:country":"US",
    "sg:address":"297 Wantagh Ave",
    "sg:city":"Levittown",
    "sg:classifiers":[
        {
            "category":"Food & Beverages",
            "subcategory":"Bakery",
            "type":"Retail Goods"
        }
    ],
    "sg:phone":"+1   ",
    "sg:postcode":"11756",
    "sg:province":"NY",
    "wof:name":"Levittown Park Bakery",
    "wof:placetype":"venue"
},
  "geometry": {"coordinates":[-73.50019399999999,40.716135],"type":"Point"}
}