{
  "type": "Feature",
  "properties": {
    "addr:full":"575 Mill Rd Staten Island NY 10306",
    "addr:housenumber":"575",
    "addr:postcode":"10306",
    "addr:street":"Mill Rd",
    "iso:country":"US",
    "sg:address":"575 Mill Rd",
    "sg:city":"Staten Island",
    "sg:classifiers":[
        {
            "category":"Organizations",
            "subcategory":"Community Association",
            "type":"Services"
        }
    ],
    "sg:phone":"+1 718 667 4120",
    "sg:postcode":"10306",
    "sg:province":"NY",
    "sg:tags":[
        "military"
    ],
    "wof:name":"Oakwood Heights VFW Post",
    "wof:placetype":"venue"
},
  "geometry": {"coordinates":[-74.116168,40.556412],"type":"Point"}
}