{
  "type": "Feature",
  "properties": {
    "addr:full":"13 Newkirk Plz Brooklyn NY 11226",
    "addr:housenumber":"13",
    "addr:postcode":"11226",
    "addr:street":"Newkirk Plz",
    "iso:country":"US",
    "sg:address":"13 Newkirk Plz",
    "sg:city":"Brooklyn",
    "sg:classifiers":[
        {
            "category":"Food & Beverages",
            "subcategory":"Groceries & Convenience Stores",
            "type":"Retail Goods"
        }
    ],
    "sg:phone":"+1 718 434 1207",
    "sg:postcode":"11226",
    "sg:province":"NY",
    "sg:tags":[
        "grocer"
    ],
    "wof:name":"Plaza Grocery Store",
    "wof:placetype":"venue"
},
  "geometry": {"coordinates":[-73.96278,40.635389],"type":"Point"}
}