{
  "type": "Feature",
  "properties": {
    "iso:country":"US",
    "sg:address":"1328 Broadway",
    "sg:city":"New York",
    "sg:classifiers":[
        {
            "category":"Travel",
            "subcategory":"Travel Agent",
            "type":"Entertainment"
        }
    ],
    "sg:phone":"+1 212 239 3156",
    "sg:postcode":"10001",
    "sg:province":"NY",
    "sg:tags":[
        "agency",
        "bureau"
    ],
    "wof:name":"Himalayan Adventures Tours",
    "wof:placetype":"venue"
},
  "geometry": {"coordinates":[-73.987816,40.749902],"type":"Point"}
}