{
  "type": "Feature",
  "properties": {
    "iso:country":"US",
    "sg:address":"141 Bedell Ave",
    "sg:city":"Hempstead",
    "sg:classifiers":[
        {
            "category":"Social Services",
            "subcategory":"Child Care",
            "type":"Services"
        }
    ],
    "sg:phone":"+1 516 565 3966",
    "sg:postcode":"11550",
    "sg:province":"NY",
    "wof:name":"Terry's Childcare",
    "wof:placetype":"venue"
},
  "geometry": {"coordinates":[-73.640371,40.710038],"type":"Point"}
}