{
  "type": "Feature",
  "properties": {
    "iso:country":"US",
    "sg:address":"870 Maple Rd",
    "sg:city":"Buffalo",
    "sg:classifiers":[
        {
            "category":"Restaurant",
            "type":"Food & Drink"
        }
    ],
    "sg:phone":"+1   ",
    "sg:postcode":"14221",
    "sg:province":"NY",
    "sg:tags":[
        "eating"
    ],
    "wof:name":"Wendys",
    "wof:placetype":"venue"
},
  "geometry": {"coordinates":[-78.754732,42.991103],"type":"Point"}
}