{
  "type": "Feature",
  "properties": {
    "iso:country":"US",
    "sg:address":"89 Montauk Hwy",
    "sg:city":"Copiague",
    "sg:phone":"+1 631 693 4552",
    "sg:postcode":"11726",
    "sg:province":"NY",
    "sg:website":"http://omgshowerdoors.net",
    "wof:name":"OMG Shower Doors Inc.",
    "wof:placetype":"venue"
},
  "geometry": {"coordinates":[-73.40306099999999,40.667648],"type":"Point"}
}