{
  "type": "Feature",
  "properties": {
    "addr:full":"257 Main Rd Akron NY 14001",
    "addr:housenumber":"257",
    "addr:postcode":"14001",
    "addr:street":"Main Rd",
    "iso:country":"US",
    "sg:address":"257 Main Rd",
    "sg:city":"Akron",
    "sg:classifiers":[
        {
            "category":"Autos & Motor Vehicles",
            "subcategory":"Auto Supplies",
            "type":"Retail Goods"
        }
    ],
    "sg:phone":"+1 585 542 5755",
    "sg:postcode":"14001",
    "sg:province":"NY",
    "sg:tags":[
        "automobile",
        "parts"
    ],
    "wof:name":"Wally's Auto Parts",
    "wof:placetype":"venue"
},
  "geometry": {"coordinates":[-78.45661,42.996606],"type":"Point"}
}