{
  "type": "Feature",
  "properties": {
    "addr:full":"20 W 22nd St Ste 1409 New York NY 10010",
    "addr:housenumber":"20",
    "addr:postcode":"10010",
    "addr:street":"W 22Nd St Ste 1409",
    "iso:country":"US",
    "sg:address":"20 W 22nd St Ste 1409",
    "sg:city":"New York",
    "sg:classifiers":[
        {
            "category":"Shopping",
            "subcategory":"Antiques",
            "type":"Retail Goods"
        }
    ],
    "sg:phone":"+1 212 260 2255",
    "sg:postcode":"10010",
    "sg:province":"NY",
    "wof:name":"Hess Restorations",
    "wof:placetype":"venue"
},
  "geometry": {"coordinates":[-73.991609,40.741274],"type":"Point"}
}