{
  "type": "Feature",
  "properties": {
    "iso:country":"US",
    "sg:address":"184 Rhode Island St",
    "sg:city":"Buffalo",
    "sg:classifiers":[
        {
            "category":"Organizations",
            "subcategory":"Community Association",
            "type":"Services"
        }
    ],
    "sg:phone":"+1 716 881 0679",
    "sg:postcode":"14213",
    "sg:province":"NY",
    "sg:tags":[
        "club",
        "sport",
        "amateur",
        "team"
    ],
    "wof:name":"Wincrest Sportsmen",
    "wof:placetype":"venue"
},
  "geometry": {"coordinates":[-78.893204,42.9076],"type":"Point"}
}