{
  "type": "Feature",
  "properties": {
    "iso:country":"US",
    "sg:address":"890 Green Pl",
    "sg:city":"Woodmere",
    "sg:classifiers":[
        {
            "category":"Manufacturing",
            "subcategory":"Tools & Machinery",
            "type":"Manufacturing & Wholesale Goods"
        }
    ],
    "sg:phone":"+1   ",
    "sg:postcode":"11598",
    "sg:province":"NY",
    "sg:tags":[
        "equipment",
        "calculating",
        "mfg"
    ],
    "wof:name":"Storch Assoc Inc",
    "wof:placetype":"venue"
},
  "geometry": {"coordinates":[-73.719635,40.637691],"type":"Point"}
}