{
  "type": "Feature",
  "properties": {
    "iso:country":"US",
    "sg:address":"93 W Campbell Rd",
    "sg:city":"Schenectady",
    "sg:classifiers":[
        {
            "category":"Shopping",
            "subcategory":"News",
            "type":"Retail Goods"
        }
    ],
    "sg:phone":"+1 518 346 2796",
    "sg:postcode":"12306",
    "sg:province":"NY",
    "sg:tags":[
        "dealer"
    ],
    "wof:name":"Court Side News",
    "wof:placetype":"venue"
},
  "geometry": {"coordinates":[-73.99139599999999,42.806142],"type":"Point"}
}