{
  "type": "Feature",
  "properties": {
    "addr:full":"48 Brooklyn Ave Massapequa NY 11758",
    "addr:housenumber":"48",
    "addr:postcode":"11758",
    "addr:street":"Brooklyn Ave",
    "iso:country":"US",
    "sg:address":"48 Brooklyn Ave",
    "sg:city":"Massapequa",
    "sg:classifiers":[
        {
            "category":"Autos & Motor Vehicles",
            "subcategory":"Fuel & Gas Station",
            "type":"Retail Goods"
        },
        {
            "category":"Retail",
            "subcategory":"Auto Repair",
            "type":"Services"
        }
    ],
    "sg:phone":"+1 516 795 6226",
    "sg:postcode":"11758",
    "sg:province":"NY",
    "wof:name":"J & R Auto Repair",
    "wof:placetype":"venue"
},
  "geometry": {"coordinates":[-73.477014,40.677135],"type":"Point"}
}