{
  "type": "Feature",
  "properties": {
    "addr:full":"148 Roslyn Rd Mineola NY 11501",
    "addr:housenumber":"148",
    "addr:postcode":"11501",
    "addr:street":"Roslyn Rd",
    "iso:country":"US",
    "sg:address":"148 Roslyn Rd",
    "sg:city":"Mineola",
    "sg:classifiers":[
        {
            "category":"Recreation",
            "type":"Entertainment"
        }
    ],
    "sg:phone":"+1   ",
    "sg:postcode":"11501",
    "sg:province":"NY",
    "wof:name":"Fit For Life",
    "wof:placetype":"venue"
},
  "geometry": {"coordinates":[-73.634512,40.745792],"type":"Point"}
}