{
  "type": "Feature",
  "properties": {
    "iso:country":"US",
    "sg:address":"2810 5th Ave",
    "sg:city":"Troy",
    "sg:classifiers":[
        {
            "category":"Wholesale",
            "subcategory":"Auto Parts",
            "type":"Manufacturing & Wholesale Goods"
        }
    ],
    "sg:phone":"+1 518 274 2121",
    "sg:postcode":"12180",
    "sg:province":"NY",
    "sg:website":"www.napaonline.com",
    "wof:name":"NAPA Auto Parts",
    "wof:placetype":"venue"
},
  "geometry": {"coordinates":[-73.682936,42.745816],"type":"Point"}
}