{
  "type": "Feature",
  "properties": {
    "addr:full":"1 Beach 105th St Far Rockaway NY 11694",
    "addr:housenumber":"1",
    "addr:postcode":"11694",
    "addr:street":"Beach 105Th St",
    "iso:country":"US",
    "sg:address":"1 Beach 105th St",
    "sg:city":"Far Rockaway",
    "sg:classifiers":[
        {
            "category":"Retail",
            "subcategory":"Animal Services",
            "type":"Services"
        }
    ],
    "sg:phone":"+1 718 641 1310",
    "sg:postcode":"11694",
    "sg:province":"NY",
    "sg:tags":[
        "horse",
        "training"
    ],
    "wof:name":"James Ferraro",
    "wof:placetype":"venue"
},
  "geometry": {"coordinates":[-73.825878,40.582664],"type":"Point"}
}