{
  "type": "Feature",
  "properties": {
    "addr:full":"7318 3rd Ave Brooklyn NY 11209",
    "addr:housenumber":"7318",
    "addr:postcode":"11209",
    "addr:street":"3Rd Ave",
    "iso:country":"US",
    "sg:address":"7318 3rd Ave",
    "sg:city":"Brooklyn",
    "sg:classifiers":[
        {
            "category":"Sports & Exercise",
            "subcategory":"Gym",
            "type":"Entertainment"
        }
    ],
    "sg:phone":"+1 718 833 1250",
    "sg:postcode":"11209",
    "sg:province":"NY",
    "sg:tags":[
        "spa",
        "health"
    ],
    "wof:name":"Aida's Spa",
    "wof:placetype":"venue"
},
  "geometry": {"coordinates":[-74.027541,40.632301],"type":"Point"}
}