{
  "type": "Feature",
  "properties": {
    "iso:country":"US",
    "sg:address":"22 Long Pond Rd",
    "sg:city":"Wading River",
    "sg:classifiers":[
        {
            "category":"Building & Trades",
            "subcategory":"Construction",
            "type":"Services"
        }
    ],
    "sg:phone":"+1 631 929 6334",
    "sg:postcode":"11792",
    "sg:province":"NY",
    "sg:tags":[
        "house"
    ],
    "wof:name":"RC Const Corp",
    "wof:placetype":"venue"
},
  "geometry": {"coordinates":[-72.84472700000001,40.92917],"type":"Point"}
}