{
  "type": "Feature",
  "properties": {
    "iso:country":"US",
    "sg:address":"282 S Main St",
    "sg:city":"New City",
    "sg:classifiers":[
        {
            "category":"Restaurant",
            "type":"Food & Drink"
        }
    ],
    "sg:phone":"+1   ",
    "sg:postcode":"10956",
    "sg:province":"NY",
    "sg:tags":[
        "eating"
    ],
    "wof:name":"New City Kosher Deli Inc",
    "wof:placetype":"venue"
},
  "geometry": {"coordinates":[-73.990881,41.135698],"type":"Point"}
}