{
  "type": "Feature",
  "properties": {
    "addr:full":"328 Clock Tower Commons Dr Brewster NY 10509",
    "addr:housenumber":"328",
    "addr:postcode":"10509",
    "addr:street":"Clock;Commons Dr",
    "iso:country":"US",
    "sg:address":"328 Clock Tower Commons Dr",
    "sg:city":"Brewster",
    "sg:classifiers":[
        {
            "category":"Building & Trades",
            "subcategory":"Construction",
            "type":"Services"
        }
    ],
    "sg:phone":"+1 845 279 1239",
    "sg:postcode":"10509",
    "sg:province":"NY",
    "sg:tags":[
        "contractor"
    ],
    "wof:name":"Bluebook Of Building & Constr",
    "wof:placetype":"venue"
},
  "geometry": {"coordinates":[-73.57330899999999,41.420229],"type":"Point"}
}