{
  "type": "Feature",
  "properties": {
    "iso:country":"US",
    "sg:address":"250 Clearbrook Rd",
    "sg:city":"Elmsford",
    "sg:classifiers":[
        {
            "category":"Wholesale",
            "subcategory":"Apparel",
            "type":"Manufacturing & Wholesale Goods"
        }
    ],
    "sg:phone":"+1 914 347 8686",
    "sg:postcode":"10523",
    "sg:province":"NY",
    "sg:tags":[
        "clothing"
    ],
    "sg:website":"www.merrillsharpe.com",
    "wof:name":"Merrill Sharpe LTD",
    "wof:placetype":"venue"
},
  "geometry": {"coordinates":[-73.81383,41.071807],"type":"Point"}
}