{
  "type": "Feature",
  "properties": {
    "addr:full":"43 Clarkson St New York NY 10014",
    "addr:housenumber":"43",
    "addr:postcode":"10014",
    "addr:street":"Clarkson St",
    "iso:country":"US",
    "sg:address":"43 Clarkson St",
    "sg:city":"New York",
    "sg:classifiers":[
        {
            "category":"Professional",
            "subcategory":"Lawyer & Legal Services",
            "type":"Services"
        }
    ],
    "sg:phone":"+1 212 625 2525",
    "sg:postcode":"10014",
    "sg:province":"NY",
    "wof:name":"Law Offices of Julian Riley the",
    "wof:placetype":"venue"
},
  "geometry": {"coordinates":[-74.008008,40.7297],"type":"Point"}
}