{
  "type": "Feature",
  "properties": {
    "addr:full":"238 E 9 St New York NY 10003",
    "addr:housenumber":"238;9",
    "addr:postcode":"10003",
    "addr:street":"E",
    "iso:country":"US",
    "sg:address":"238 E 9 St",
    "sg:city":"New York",
    "sg:classifiers":[
        {
            "category":"Retail",
            "subcategory":"Auto Repair",
            "type":"Services"
        }
    ],
    "sg:phone":"+1 646 237 9397",
    "sg:postcode":"10003",
    "sg:province":"NY",
    "sg:tags":[
        "wrecker"
    ],
    "wof:name":"Emergency Anytime Towing",
    "wof:placetype":"venue"
},
  "geometry": {"coordinates":[-73.987391,40.729192],"type":"Point"}
}