{
  "type": "Feature",
  "properties": {
    "addr:full":"7 Theresa Ct Patchogue NY 11772",
    "addr:housenumber":"7",
    "addr:postcode":"11772",
    "addr:street":"Theresa Ct",
    "iso:country":"US",
    "sg:address":"7 Theresa Ct",
    "sg:city":"Patchogue",
    "sg:classifiers":[
        {
            "category":"Manufacturing",
            "subcategory":"Tools & Machinery",
            "type":"Manufacturing & Wholesale Goods"
        }
    ],
    "sg:phone":"+1   ",
    "sg:postcode":"11772",
    "sg:province":"NY",
    "sg:tags":[
        "machine",
        "mfg"
    ],
    "wof:name":"DK Deburring",
    "wof:placetype":"venue"
},
  "geometry": {"coordinates":[-72.998644,40.793644],"type":"Point"}
}