{
  "type": "Feature",
  "properties": {
    "addr:full":"115-02 Liberty Ave Queens NY 11419",
    "addr:housenumber":"115-02",
    "addr:postcode":"11419",
    "addr:street":"Liberty Ave",
    "iso:country":"US",
    "sg:address":"115-02 Liberty Ave",
    "sg:city":"Queens",
    "sg:classifiers":[
        {
            "category":"Shopping",
            "subcategory":"Pharmacy",
            "type":"Retail Goods"
        }
    ],
    "sg:phone":"+1 718 835 9500",
    "sg:postcode":"11419",
    "sg:province":"NY",
    "sg:tags":[
        "drugstore"
    ],
    "sg:website":"www.duanereade.com/",
    "wof:name":"Duane Reade",
    "wof:placetype":"venue"
},
  "geometry": {"coordinates":[-73.82771099999999,40.685745],"type":"Point"}
}