{
  "type": "Feature",
  "properties": {
    "iso:country":"US",
    "sg:address":"1263 52nd St",
    "sg:city":"Brooklyn",
    "sg:classifiers":[
        {
            "category":"Education",
            "subcategory":"School",
            "type":"Public Place"
        }
    ],
    "sg:phone":"+1 718 851 7242",
    "sg:postcode":"11219",
    "sg:province":"NY",
    "wof:name":"Yeshiva M'Kor Boruch",
    "wof:placetype":"venue"
},
  "geometry": {"coordinates":[-73.994265,40.63376],"type":"Point"}
}