{
  "type": "Feature",
  "properties": {
    "iso:country":"US",
    "sg:address":"20 Finch Ln",
    "sg:city":"Levittown",
    "sg:classifiers":[
        {
            "category":"Building & Trades",
            "subcategory":"Construction",
            "type":"Services"
        }
    ],
    "sg:phone":"+1 516 520 0824",
    "sg:postcode":"11756",
    "sg:province":"NY",
    "sg:tags":[
        "house"
    ],
    "wof:name":"Macs Home Improvements",
    "wof:placetype":"venue"
},
  "geometry": {"coordinates":[-73.53331900000001,40.740062],"type":"Point"}
}