{
  "type": "Feature",
  "properties": {
    "iso:country":"US",
    "sg:address":"145 Pinelawn Rd",
    "sg:city":"Melville",
    "sg:classifiers":[
        {
            "category":"Banks & Credit Unions",
            "subcategory":"Investment Brokerage",
            "type":"Services"
        }
    ],
    "sg:phone":"+1 631 777 1707",
    "sg:postcode":"11747",
    "sg:province":"NY",
    "sg:tags":[
        "advisory"
    ],
    "wof:name":"Steven Brill Advisors Inc",
    "wof:placetype":"venue"
},
  "geometry": {"coordinates":[-73.412262,40.785986],"type":"Point"}
}