{
  "type": "Feature",
  "properties": {
    "iso:country":"US",
    "sg:address":"3578 White Plains Rd",
    "sg:city":"Bronx",
    "sg:classifiers":[
        {
            "category":"Insurance",
            "subcategory":"Insurance Agent",
            "type":"Services"
        }
    ],
    "sg:phone":"+1 718 655 6565",
    "sg:postcode":"10467",
    "sg:province":"NY",
    "sg:tags":[
        "broker"
    ],
    "wof:name":"Cathor Brokerage",
    "wof:placetype":"venue"
},
  "geometry": {"coordinates":[-73.865415,40.878852],"type":"Point"}
}