{
  "type": "Feature",
  "properties": {
    "iso:country":"US",
    "sg:address":"582 Balltown Rd",
    "sg:city":"Schenectady",
    "sg:classifiers":[
        {
            "category":"Communications",
            "type":"Services"
        }
    ],
    "sg:phone":"+1 518 372 3459",
    "sg:postcode":"12304",
    "sg:province":"NY",
    "wof:name":"Capital Communications Fed. Cu",
    "wof:placetype":"venue"
},
  "geometry": {"coordinates":[-73.893066,42.78463],"type":"Point"}
}