{
  "type": "Feature",
  "properties": {
    "iso:country":"US",
    "sg:address":"765 Park Ave",
    "sg:city":"New York",
    "sg:classifiers":[
        {
            "category":"Professional",
            "type":"Services"
        }
    ],
    "sg:phone":"+1 212 717 0432",
    "sg:postcode":"10021",
    "sg:province":"NY",
    "sg:tags":[
        "establishment"
    ],
    "wof:name":"Liberty St Inc",
    "wof:placetype":"venue"
},
  "geometry": {"coordinates":[-73.963374,40.771545],"type":"Point"}
}