{
  "type": "Feature",
  "properties": {
    "addr:full":"546 Casanova St Bronx NY 10474",
    "addr:housenumber":"546",
    "addr:postcode":"10474",
    "addr:street":"Casanova St",
    "iso:country":"US",
    "sg:address":"546 Casanova St",
    "sg:city":"Bronx",
    "sg:classifiers":[
        {
            "category":"Manufacturing",
            "subcategory":"Metals",
            "type":"Manufacturing & Wholesale Goods"
        },
        {
            "category":"Manufacturing",
            "subcategory":"Tools & Machinery",
            "type":"Manufacturing & Wholesale Goods"
        }
    ],
    "sg:phone":"+1 718 861 0820",
    "sg:postcode":"10474",
    "sg:province":"NY",
    "sg:tags":[
        "steel",
        "shop",
        "job"
    ],
    "wof:name":"Ajay Supply Co Inc",
    "wof:placetype":"venue"
},
  "geometry": {"coordinates":[-73.88932,40.810789],"type":"Point"}
}