{
  "type": "Feature",
  "properties": {
    "addr:full":"575 Lexington Ave Rm 801 New York NY 10022",
    "addr:housenumber":"575;801",
    "addr:postcode":"10022",
    "addr:street":"Lexington Ave Rm",
    "iso:country":"US",
    "sg:address":"575 Lexington Ave Rm 801",
    "sg:city":"New York",
    "sg:classifiers":[
        {
            "category":"Banks & Credit Unions",
            "subcategory":"Investment Brokerage",
            "type":"Services"
        }
    ],
    "sg:phone":"+1 212 624 1929",
    "sg:postcode":"10022",
    "sg:province":"NY",
    "sg:tags":[
        "investing"
    ],
    "wof:name":"Proctor Investments",
    "wof:placetype":"venue"
},
  "geometry": {"coordinates":[-73.971733,40.757039],"type":"Point"}
}