{
  "type": "Feature",
  "properties": {
    "addr:full":"179 Widger Rd Spencerport NY 14559",
    "addr:housenumber":"179",
    "addr:postcode":"14559",
    "addr:street":"Widger Rd",
    "iso:country":"US",
    "sg:address":"179 Widger Rd",
    "sg:city":"Spencerport",
    "sg:classifiers":[
        {
            "category":"Arts & Performance",
            "subcategory":"Theater",
            "type":"Entertainment"
        }
    ],
    "sg:phone":"+1   ",
    "sg:postcode":"14559",
    "sg:province":"NY",
    "sg:tags":[
        "group"
    ],
    "wof:name":"Buck N Chuck",
    "wof:placetype":"venue"
},
  "geometry": {"coordinates":[-77.846819,43.138868],"type":"Point"}
}