{
  "type": "Feature",
  "properties": {
    "iso:country":"US",
    "sg:address":"87 Clay St",
    "sg:city":"Brooklyn",
    "sg:classifiers":[
        {
            "category":"Professional",
            "type":"Services"
        }
    ],
    "sg:phone":"+1 718 349 2700",
    "sg:postcode":"11222",
    "sg:province":"NY",
    "sg:tags":[
        "caterer"
    ],
    "wof:name":"Yachting Confidential",
    "wof:placetype":"venue"
},
  "geometry": {"coordinates":[-73.95442,40.736806],"type":"Point"}
}