{
  "type": "Feature",
  "properties": {
    "iso:country":"US",
    "sg:address":"42 Marian Ln",
    "sg:city":"Jericho",
    "sg:classifiers":[
        {
            "category":"Manufacturing",
            "subcategory":"Printing",
            "type":"Manufacturing & Wholesale Goods"
        }
    ],
    "sg:phone":"+1   ",
    "sg:postcode":"11753",
    "sg:province":"NY",
    "sg:tags":[
        "publishing"
    ],
    "wof:name":"Publisher Support Services",
    "wof:placetype":"venue"
},
  "geometry": {"coordinates":[-73.52833099999999,40.796245],"type":"Point"}
}