{
  "type": "Feature",
  "properties": {
    "addr:full":"11 W 40th St Manhattan NY 10018",
    "addr:housenumber":"11",
    "addr:postcode":"10018",
    "addr:street":"W 40Th St",
    "iso:country":"US",
    "sg:address":"11 W 40th St",
    "sg:city":"Manhattan",
    "sg:classifiers":[
        {
            "category":"Real Estate",
            "subcategory":"Real Estate Services",
            "type":"Services"
        }
    ],
    "sg:phone":"+1 516 732 7595",
    "sg:postcode":"10018",
    "sg:province":"NY",
    "sg:tags":[
        "home",
        "inspector"
    ],
    "sg:website":"www.howsmyhousehomeinspections.c...",
    "wof:name":"Hows My House Home Inspection",
    "wof:placetype":"venue"
},
  "geometry": {"coordinates":[-73.982399,40.752458],"type":"Point"}
}