{
  "type": "Feature",
  "properties": {
    "addr:full":"625 Hancock St Ithaca NY 14850",
    "addr:housenumber":"625",
    "addr:postcode":"14850",
    "addr:street":"Hancock St",
    "iso:country":"US",
    "sg:address":"625 Hancock St",
    "sg:city":"Ithaca",
    "sg:classifiers":[
        {
            "category":"Recreation",
            "type":"Entertainment"
        }
    ],
    "sg:phone":"+1 607 272 4461",
    "sg:postcode":"14850",
    "sg:province":"NY",
    "sg:tags":[
        "hall",
        "auditorium"
    ],
    "wof:name":"Northside Community Ctr",
    "wof:placetype":"venue"
},
  "geometry": {"coordinates":[-76.506337,42.445774],"type":"Point"}
}