{
  "type": "Feature",
  "properties": {
    "addr:full":"12 Rolling Hills Rd Niskayuna NY 12309",
    "addr:housenumber":"12",
    "addr:postcode":"12309",
    "addr:street":"Rolling Hills Rd",
    "iso:country":"US",
    "sg:address":"12 Rolling Hills Rd",
    "sg:city":"Niskayuna",
    "sg:classifiers":[
        {
            "category":"Building & Trades",
            "subcategory":"Construction",
            "type":"Services"
        }
    ],
    "sg:phone":"+1 518 458 1424",
    "sg:postcode":"12309",
    "sg:province":"NY",
    "sg:tags":[
        "roofing",
        "contractor"
    ],
    "wof:name":"Home Beautifiers Inc",
    "wof:placetype":"venue"
},
  "geometry": {"coordinates":[-73.839681,42.752002],"type":"Point"}
}