{
  "type": "Feature",
  "properties": {
    "iso:country":"US",
    "sg:address":"714 Broadway",
    "sg:city":"New York",
    "sg:classifiers":[
        {
            "category":"Health Services",
            "subcategory":"Doctor",
            "type":"Services"
        }
    ],
    "sg:phone":"+1 212 674 1710",
    "sg:postcode":"10003",
    "sg:province":"NY",
    "sg:tags":[
        "clinic",
        "medical"
    ],
    "wof:name":"New York Ctr For Sxual Gidance",
    "wof:placetype":"venue"
},
  "geometry": {"coordinates":[-73.994252,40.728412],"type":"Point"}
}