{
  "type": "Feature",
  "properties": {
    "addr:full":"1843 83rd St Brooklyn NY 11214",
    "addr:housenumber":"1843",
    "addr:postcode":"11214",
    "addr:street":"83Rd St",
    "iso:country":"US",
    "sg:address":"1843 83rd St",
    "sg:city":"Brooklyn",
    "sg:classifiers":[
        {
            "category":"Building & Trades",
            "subcategory":"Construction",
            "type":"Services"
        }
    ],
    "sg:phone":"+1 718 256 5565",
    "sg:postcode":"11214",
    "sg:province":"NY",
    "sg:tags":[
        "contractor"
    ],
    "wof:name":"Triple V Contracting Corp",
    "wof:placetype":"venue"
},
  "geometry": {"coordinates":[-73.999341,40.608328],"type":"Point"}
}