{
  "type": "Feature",
  "properties": {
    "addr:full":"13 W Bank St Cold Spring NY 10516",
    "addr:housenumber":"13",
    "addr:postcode":"10516",
    "addr:street":"W Bank St",
    "iso:country":"US",
    "sg:address":"13 W Bank St",
    "sg:city":"Cold Spring",
    "sg:classifiers":[
        {
            "category":"Building & Trades",
            "subcategory":"Cleaning & Sanitation",
            "type":"Services"
        }
    ],
    "sg:phone":"+1   ",
    "sg:postcode":"10516",
    "sg:province":"NY",
    "sg:tags":[
        "maintenance"
    ],
    "wof:name":"Mojo Cleaners",
    "wof:placetype":"venue"
},
  "geometry": {"coordinates":[-73.946416,41.419221],"type":"Point"}
}