{
  "type": "Feature",
  "properties": {
    "addr:full":"1225 Park Ave New York NY 10128",
    "addr:housenumber":"1225",
    "addr:postcode":"10128",
    "addr:street":"Park Ave",
    "iso:country":"US",
    "sg:address":"1225 Park Ave",
    "sg:city":"New York",
    "sg:classifiers":[
        {
            "category":"Professional",
            "subcategory":"Lawyer & Legal Services",
            "type":"Services"
        }
    ],
    "sg:phone":"+1   ",
    "sg:postcode":"10128",
    "sg:province":"NY",
    "wof:name":"Morris Wirth",
    "wof:placetype":"venue"
},
  "geometry": {"coordinates":[-73.952569,40.786363],"type":"Point"}
}