{
  "type": "Feature",
  "properties": {
    "addr:full":"3162 Lake Rd Horseheads NY 14845",
    "addr:housenumber":"3162",
    "addr:postcode":"14845",
    "addr:street":"Lake Rd",
    "iso:country":"US",
    "sg:address":"3162 Lake Rd",
    "sg:city":"Horseheads",
    "sg:classifiers":[
        {
            "category":"Shopping",
            "subcategory":"Computers & Home Electronics",
            "type":"Retail Goods"
        }
    ],
    "sg:phone":"+1 607 796 5383",
    "sg:postcode":"14845",
    "sg:province":"NY",
    "sg:tags":[
        "equipment",
        "dealer"
    ],
    "wof:name":"Truetech",
    "wof:placetype":"venue"
},
  "geometry": {"coordinates":[-76.814584,42.1433],"type":"Point"}
}