{
  "type": "Feature",
  "properties": {
    "addr:full":"1 Rockefeller Plz New York NY 10020",
    "addr:housenumber":"1",
    "addr:postcode":"10020",
    "addr:street":"Rockefeller Plz",
    "iso:country":"US",
    "sg:address":"1 Rockefeller Plz",
    "sg:city":"New York",
    "sg:classifiers":[
        {
            "category":"Food & Beverages",
            "subcategory":"Bakery",
            "type":"Retail Goods"
        }
    ],
    "sg:phone":"+1 212 780 0577",
    "sg:postcode":"10020",
    "sg:province":"NY",
    "sg:tags":[
        "sandwich"
    ],
    "sg:website":"wichcraftnyc.com",
    "wof:name":"'Wichcraft",
    "wof:placetype":"venue"
},
  "geometry": {"coordinates":[-73.978844,40.758197],"type":"Point"}
}