{
  "type": "Feature",
  "properties": {
    "addr:full":"552 W 48 St New York NY 10036",
    "addr:housenumber":"552",
    "addr:postcode":"10036",
    "addr:street":"W 48 St",
    "iso:country":"US",
    "sg:address":"552 W 48 St",
    "sg:city":"New York",
    "sg:classifiers":[
        {
            "category":"Retail",
            "subcategory":"Auto Repair",
            "type":"Services"
        }
    ],
    "sg:phone":"+1 212 265 3052",
    "sg:postcode":"10036",
    "sg:province":"NY",
    "sg:tags":[
        "installs",
        "plate",
        "radio",
        "car",
        "glass"
    ],
    "wof:name":"Statue Liberty Glass",
    "wof:placetype":"venue"
},
  "geometry": {"coordinates":[-73.994738,40.764092],"type":"Point"}
}