{
  "type": "Feature",
  "properties": {
    "addr:full":"5842 Main St Flushing NY 11355",
    "addr:housenumber":"5842",
    "addr:postcode":"11355",
    "addr:street":"Main St",
    "iso:country":"US",
    "sg:address":"5842 Main St",
    "sg:city":"Flushing",
    "sg:classifiers":[
        {
            "category":"Health Services",
            "subcategory":"Doctor",
            "type":"Services"
        }
    ],
    "sg:phone":"+1 718 539 3312",
    "sg:postcode":"11355",
    "sg:province":"NY",
    "wof:name":"Farrell Robert Dr",
    "wof:placetype":"venue"
},
  "geometry": {"coordinates":[-73.825897,40.744301],"type":"Point"}
}