{
  "type": "Feature",
  "properties": {
    "iso:country":"US",
    "sg:address":"76 Main St",
    "sg:city":"Cold Spring",
    "sg:classifiers":[
        {
            "category":"Shopping",
            "subcategory":"Gifts & Souvenirs",
            "type":"Retail Goods"
        }
    ],
    "sg:phone":"+1 845 265 2895",
    "sg:postcode":"10516",
    "sg:province":"NY",
    "sg:tags":[
        "shop"
    ],
    "wof:name":"Brass Pear LTD",
    "wof:placetype":"venue"
},
  "geometry": {"coordinates":[-73.958372,41.417831],"type":"Point"}
}