{
  "type": "Feature",
  "properties": {
    "addr:full":"21 Powers St Brooklyn NY 11211",
    "addr:housenumber":"21",
    "addr:postcode":"11211",
    "addr:street":"Powers St",
    "iso:country":"US",
    "sg:address":"21 Powers St",
    "sg:city":"Brooklyn",
    "sg:classifiers":[
        {
            "category":"Wholesale",
            "subcategory":"Electrical",
            "type":"Manufacturing & Wholesale Goods"
        }
    ],
    "sg:phone":"+1 718 599 0793",
    "sg:postcode":"11211",
    "sg:province":"NY",
    "sg:tags":[
        "recording",
        "studio"
    ],
    "wof:name":"Bowlmor Records",
    "wof:placetype":"venue"
},
  "geometry": {"coordinates":[-73.949646,40.7119],"type":"Point"}
}