{
  "type": "Feature",
  "properties": {
    "iso:country":"US",
    "sg:address":"1235 Glen Carlyn Dr",
    "sg:city":"Farmington",
    "sg:classifiers":[
        {
            "category":"Wholesale",
            "subcategory":"Durable Goods & Equipment",
            "type":"Manufacturing & Wholesale Goods"
        }
    ],
    "sg:phone":"+1 585 924 4880",
    "sg:postcode":"14425",
    "sg:province":"NY",
    "sg:tags":[
        "representative",
        "manufacturer"
    ],
    "wof:name":"Baker Assoc",
    "wof:placetype":"venue"
},
  "geometry": {"coordinates":[-77.346164,42.974818],"type":"Point"}
}