{
  "type": "Feature",
  "properties": {
    "addr:full":"240 N Main St Minoa NY 13116",
    "addr:housenumber":"240",
    "addr:postcode":"13116",
    "addr:street":"N Main St",
    "iso:country":"US",
    "sg:address":"240 N Main St",
    "sg:city":"Minoa",
    "sg:classifiers":[
        {
            "category":"Government",
            "subcategory":"Office",
            "type":"Public Place"
        }
    ],
    "sg:phone":"+1 315 656 3100",
    "sg:postcode":"13116",
    "sg:province":"NY",
    "sg:tags":[
        "village"
    ],
    "wof:name":"Minoa Clerk's Office",
    "wof:placetype":"venue"
},
  "geometry": {"coordinates":[-76.000758,43.077288],"type":"Point"}
}