{
  "type": "Feature",
  "properties": {
    "iso:country":"US",
    "sg:address":"11117 Queens Blvd",
    "sg:city":"Forest Hills",
    "sg:classifiers":[
        {
            "category":"Health Services",
            "subcategory":"Doctor",
            "type":"Services"
        }
    ],
    "sg:phone":"+1 800 585 1348",
    "sg:postcode":"11375",
    "sg:province":"NY",
    "wof:name":"Khasidy Levan MD",
    "wof:placetype":"venue"
},
  "geometry": {"coordinates":[-73.837901,40.71914],"type":"Point"}
}