{
  "type": "Feature",
  "properties": {
    "iso:country":"US",
    "sg:address":"2900 N Westchester Ave",
    "sg:city":"Purchase",
    "sg:classifiers":[
        {
            "category":"Wholesale",
            "subcategory":"Office Equipment",
            "type":"Manufacturing & Wholesale Goods"
        }
    ],
    "sg:phone":"+1 914 253 9009",
    "sg:postcode":"10577",
    "sg:province":"NY",
    "sg:tags":[
        "machine",
        "duplicating",
        "copying"
    ],
    "sg:website":"www.ricoh-socal.com",
    "wof:name":"Ricoh Business Systems",
    "wof:placetype":"venue"
},
  "geometry": {"coordinates":[-73.69807,41.009504],"type":"Point"}
}