{
  "type": "Feature",
  "properties": {
    "addr:full":"507 77th St Brooklyn NY 11209",
    "addr:housenumber":"507",
    "addr:postcode":"11209",
    "addr:street":"77Th St",
    "iso:country":"US",
    "sg:address":"507 77th St",
    "sg:city":"Brooklyn",
    "sg:classifiers":[
        {
            "category":"Local Transit",
            "type":"Transportation"
        }
    ],
    "sg:phone":"+1 718 238 3550",
    "sg:postcode":"11209",
    "sg:province":"NY",
    "sg:tags":[
        "car",
        "transport",
        "passenger"
    ],
    "wof:name":"Seventy Seventh St Car Service",
    "wof:placetype":"venue"
},
  "geometry": {"coordinates":[-74.020957,40.626689],"type":"Point"}
}