{
  "type": "Feature",
  "properties": {
    "addr:full":"15 Piazza Rd Kerhonkson NY 12446",
    "addr:postcode":"12446",
    "addr:street":"Piazza Rd",
    "iso:country":"US",
    "sg:address":"15 Piazza Rd",
    "sg:city":"Kerhonkson",
    "sg:classifiers":[
        {
            "category":"Building & Trades",
            "subcategory":"Construction",
            "type":"Services"
        }
    ],
    "sg:phone":"+1 845 626 3075",
    "sg:postcode":"12446",
    "sg:province":"NY",
    "sg:tags":[
        "carpentry",
        "contractor"
    ],
    "wof:name":"Subae Construction",
    "wof:placetype":"venue"
},
  "geometry": {"coordinates":[-74.26978200000001,41.805835],"type":"Point"}
}