{
  "type": "Feature",
  "properties": {
    "addr:full":"14 Hutchinson Ct Great Neck NY 11023",
    "addr:housenumber":"14",
    "addr:postcode":"11023",
    "addr:street":"Hutchinson Ct",
    "iso:country":"US",
    "sg:address":"14 Hutchinson Ct",
    "sg:city":"Great Neck",
    "sg:classifiers":[
        {
            "category":"Real Estate",
            "subcategory":"Real Estate Agent",
            "type":"Services"
        }
    ],
    "sg:phone":"+1 516 482 2989",
    "sg:postcode":"11023",
    "sg:province":"NY",
    "wof:name":"Shore Frc Incorporate",
    "wof:placetype":"venue"
},
  "geometry": {"coordinates":[-73.720101,40.798953],"type":"Point"}
}