{
  "type": "Feature",
  "properties": {
    "iso:country":"US",
    "sg:address":"33 Route 304",
    "sg:city":"Nanuet",
    "sg:classifiers":[
        {
            "category":"Social Services",
            "subcategory":"Child Care",
            "type":"Services"
        }
    ],
    "sg:phone":"+1 845 624 0114",
    "sg:postcode":"10954",
    "sg:province":"NY",
    "sg:tags":[
        "nursery",
        "day",
        "referral"
    ],
    "wof:name":"Wee Play",
    "wof:placetype":"venue"
},
  "geometry": {"coordinates":[-73.997998,41.097594],"type":"Point"}
}