{
  "type": "Feature",
  "properties": {
    "iso:country":"US",
    "sg:address":"87 W End Avenue",
    "sg:city":"Brooklyn",
    "sg:classifiers":[
        {
            "category":"Shopping",
            "subcategory":"Pharmacy",
            "type":"Retail Goods"
        }
    ],
    "sg:phone":"+1 718 332 2210",
    "sg:postcode":"11235",
    "sg:province":"NY",
    "sg:tags":[
        "drugstore"
    ],
    "wof:name":"Manhattan Beach Pharmacy",
    "wof:placetype":"venue"
},
  "geometry": {"coordinates":[-73.953262,40.579539],"type":"Point"}
}