{
  "type": "Feature",
  "properties": {
    "addr:full":"5 Chestnut Park Ct New City NY 10956",
    "addr:housenumber":"5",
    "addr:postcode":"10956",
    "addr:street":"Chestnut Park Ct",
    "iso:country":"US",
    "sg:address":"5 Chestnut Park Ct",
    "sg:city":"New City",
    "sg:classifiers":[
        {
            "category":"Real Estate",
            "subcategory":"Real Estate Operator",
            "type":"Services"
        }
    ],
    "sg:phone":"+1 845 634 5745",
    "sg:postcode":"10956",
    "sg:province":"NY",
    "sg:tags":[
        "building",
        "apartment"
    ],
    "wof:name":"49-51 West 85th Street Corp",
    "wof:placetype":"venue"
},
  "geometry": {"coordinates":[-74.00676799999999,41.127539],"type":"Point"}
}