{
  "type": "Feature",
  "properties": {
    "addr:full":"13650 Roosevelt Ave Flushing NY 11354",
    "addr:housenumber":"13650",
    "addr:postcode":"11354",
    "addr:street":"Roosevelt Ave",
    "iso:country":"US",
    "sg:address":"13650 Roosevelt Ave",
    "sg:city":"Flushing",
    "sg:classifiers":[
        {
            "category":"Shopping",
            "subcategory":"Department Store",
            "type":"Retail Goods"
        }
    ],
    "sg:phone":"+1 718 358 9000",
    "sg:postcode":"11354",
    "sg:province":"NY",
    "sg:website":"www.macys.com",
    "wof:name":"Gertz Long Island",
    "wof:placetype":"venue"
},
  "geometry": {"coordinates":[-73.828903,40.7598],"type":"Point"}
}