{
  "type": "Feature",
  "properties": {
    "iso:country":"US",
    "sg:address":"1641 Commons Pkwy",
    "sg:city":"Macedon",
    "sg:classifiers":[
        {
            "category":"Professional",
            "type":"Services"
        }
    ],
    "sg:phone":"+1 315 986 4615",
    "sg:postcode":"14502",
    "sg:province":"NY",
    "sg:tags":[
        "establishment"
    ],
    "wof:name":"G & L Assoc LP",
    "wof:placetype":"venue"
},
  "geometry": {"coordinates":[-77.325261,43.066737],"type":"Point"}
}