{
  "type": "Feature",
  "properties": {
    "addr:full":"9 Minetta Street New York NY 10012",
    "addr:housenumber":"9",
    "addr:postcode":"10012",
    "addr:street":"Minetta Street",
    "iso:country":"US",
    "sg:address":"9 Minetta Street",
    "sg:city":"New York",
    "sg:classifiers":[
        {
            "category":"Travel",
            "subcategory":"Hotels & Motels",
            "type":"Entertainment"
        }
    ],
    "sg:phone":"+1 212 475 4756",
    "sg:postcode":"10012",
    "sg:province":"NY",
    "wof:name":"Mini Suites of Minetta",
    "wof:placetype":"venue"
},
  "geometry": {"coordinates":[-74.00124,40.729798],"type":"Point"}
}