{
  "type": "Feature",
  "properties": {
    "iso:country":"US",
    "sg:address":"2428 Bouck Ave",
    "sg:city":"Bronx",
    "sg:classifiers":[
        {
            "category":"Building & Trades",
            "subcategory":"Construction",
            "type":"Services"
        }
    ],
    "sg:phone":"+1 718 231 4374",
    "sg:postcode":"10469",
    "sg:province":"NY",
    "sg:tags":[
        "hanging",
        "contractor"
    ],
    "wof:name":"Castorinas Painting Inc",
    "wof:placetype":"venue"
},
  "geometry": {"coordinates":[-73.850089,40.862355],"type":"Point"}
}