{
  "type": "Feature",
  "properties": {
    "iso:country":"US",
    "sg:address":"55 Willoughby Street",
    "sg:city":"Brooklyn",
    "sg:classifiers":[
        {
            "category":"Home & Garden",
            "subcategory":"Furniture",
            "type":"Retail Goods"
        }
    ],
    "sg:phone":"+1 718 237 2738",
    "sg:postcode":"11201",
    "sg:province":"NY",
    "sg:tags":[
        "store"
    ],
    "wof:name":"Futon Warehouse",
    "wof:placetype":"venue"
},
  "geometry": {"coordinates":[-73.986887,40.692331],"type":"Point"}
}