{
  "type": "Feature",
  "properties": {
    "addr:full":"640 5th Ave New York NY 10019",
    "addr:housenumber":"640",
    "addr:postcode":"10019",
    "addr:street":"5Th Ave",
    "iso:country":"US",
    "sg:address":"640 5th Ave",
    "sg:city":"New York",
    "sg:classifiers":[
        {
            "category":"Banks & Credit Unions",
            "subcategory":"Bank",
            "type":"Services"
        }
    ],
    "sg:phone":"+1 212 541 8650",
    "sg:postcode":"10019",
    "sg:province":"NY",
    "sg:website":"www.citibank.com",
    "wof:name":"Citibank N A",
    "wof:placetype":"venue"
},
  "geometry": {"coordinates":[-73.976994,40.759543],"type":"Point"}
}