{
  "type": "Feature",
  "properties": {
    "addr:full":"112 Woodvale Ave Staten Island NY 10309",
    "addr:housenumber":"112",
    "addr:postcode":"10309",
    "addr:street":"Woodvale Ave",
    "iso:country":"US",
    "sg:address":"112 Woodvale Ave",
    "sg:city":"Staten Island",
    "sg:classifiers":[
        {
            "category":"Manufacturing",
            "subcategory":"Wood Products",
            "type":"Manufacturing & Wholesale Goods"
        }
    ],
    "sg:phone":"+1   ",
    "sg:postcode":"10309",
    "sg:province":"NY",
    "sg:tags":[
        "mfg"
    ],
    "wof:name":"Ferenzi Framing",
    "wof:placetype":"venue"
},
  "geometry": {"coordinates":[-74.20976899999999,40.521594],"type":"Point"}
}