{
  "type": "Feature",
  "properties": {
    "iso:country":"US",
    "sg:address":"17 Main St",
    "sg:city":"Saranac Lake",
    "sg:classifiers":[
        {
            "category":"Health Services",
            "subcategory":"Hospital",
            "type":"Services"
        }
    ],
    "sg:phone":"+1 518 891 2319",
    "sg:postcode":"12983",
    "sg:province":"NY",
    "sg:tags":[
        "mental"
    ],
    "wof:name":"North Star Industries",
    "wof:placetype":"venue"
},
  "geometry": {"coordinates":[-74.131412,44.326811],"type":"Point"}
}