{
  "type": "Feature",
  "properties": {
    "addr:full":"425 Hoyt St Brooklyn NY 11231",
    "addr:housenumber":"425",
    "addr:postcode":"11231",
    "addr:street":"Hoyt St",
    "iso:country":"US",
    "sg:address":"425 Hoyt St",
    "sg:city":"Brooklyn",
    "sg:classifiers":[
        {
            "category":"Building & Trades",
            "subcategory":"Plumbing",
            "type":"Services"
        }
    ],
    "sg:phone":"+1 888 791 3778",
    "sg:postcode":"11231",
    "sg:province":"NY",
    "wof:name":"Josephine The Plumber Inc",
    "wof:placetype":"venue"
},
  "geometry": {"coordinates":[-73.994039,40.677089],"type":"Point"}
}