{
  "type": "Feature",
  "properties": {
    "addr:full":"3001 Eastchester Road Bronx NY 10469",
    "addr:housenumber":"3001",
    "addr:postcode":"10469",
    "addr:street":"Eastchester Road",
    "iso:country":"US",
    "sg:address":"3001 Eastchester Road",
    "sg:city":"Bronx",
    "sg:classifiers":[
        {
            "category":"Restaurant",
            "type":"Food & Drink"
        },
        {
            "category":"Deli",
            "type":"Food & Drink"
        },
        {
            "category":"Food & Beverages",
            "subcategory":"Bakery",
            "type":"Retail Goods"
        }
    ],
    "sg:phone":"+1 718 320 3036",
    "sg:postcode":"10469",
    "sg:province":"NY",
    "sg:tags":[
        "delicatessen",
        "sandwich"
    ],
    "wof:name":"Deli Mart",
    "wof:placetype":"venue"
},
  "geometry": {"coordinates":[-73.84281799999999,40.869493],"type":"Point"}
}