{
  "type": "Feature",
  "properties": {
    "iso:country":"US",
    "sg:address":"90 Sharron Ave",
    "sg:city":"Plattsburgh",
    "sg:classifiers":[
        {
            "category":"Shopping",
            "subcategory":"Bicycles & Sporting Goods",
            "type":"Retail Goods"
        }
    ],
    "sg:phone":"+1 518 562 8123",
    "sg:postcode":"12901",
    "sg:province":"NY",
    "sg:tags":[
        "equipment",
        "hockey"
    ],
    "wof:name":"Hockey Plus",
    "wof:placetype":"venue"
},
  "geometry": {"coordinates":[-73.455027,44.676946],"type":"Point"}
}