{
  "type": "Feature",
  "properties": {
    "iso:country":"US",
    "sg:address":"38 New Hartford Shopping Center",
    "sg:city":"New Hartford",
    "sg:classifiers":[
        {
            "category":"Food & Beverages",
            "subcategory":"Specialty",
            "type":"Retail Goods"
        }
    ],
    "sg:phone":"+1   ",
    "sg:postcode":"13413",
    "sg:province":"NY",
    "wof:name":"Peters Crncpia Hlth Gourmet Fd",
    "wof:placetype":"venue"
},
  "geometry": {"coordinates":[-75.29186,43.077993],"type":"Point"}
}