{
  "type": "Feature",
  "properties": {
    "iso:country":"US",
    "sg:address":"2965 Hempstead Tpke",
    "sg:city":"Levittown",
    "sg:classifiers":[
        {
            "category":"Shopping",
            "type":"Retail Goods"
        }
    ],
    "sg:phone":"+1 516 731 9344",
    "sg:postcode":"11756",
    "sg:province":"NY",
    "sg:tags":[
        "pet",
        "shop"
    ],
    "wof:name":"PETCO",
    "wof:placetype":"venue"
},
  "geometry": {"coordinates":[-73.526039,40.724813],"type":"Point"}
}