{
  "type": "Feature",
  "properties": {
    "iso:country":"US",
    "sg:address":"2464 Grand Concourse",
    "sg:city":"Bronx",
    "sg:classifiers":[
        {
            "category":"Shopping",
            "subcategory":"Shoes",
            "type":"Retail Goods"
        }
    ],
    "sg:phone":"+1   ",
    "sg:postcode":"10458",
    "sg:province":"NY",
    "sg:tags":[
        "athletic",
        "apparel",
        "sport",
        "footwear"
    ],
    "wof:name":"Olympia Athletic Sports Inc",
    "wof:placetype":"venue"
},
  "geometry": {"coordinates":[-73.897051,40.86238],"type":"Point"}
}