{
  "type": "Feature",
  "properties": {
    "iso:country":"US",
    "sg:address":"1849 50th St",
    "sg:city":"Brooklyn",
    "sg:classifiers":[
        {
            "category":"Professional",
            "subcategory":"Computer Services",
            "type":"Services"
        }
    ],
    "sg:phone":"+1   ",
    "sg:postcode":"11204",
    "sg:province":"NY",
    "sg:tags":[
        "consultant"
    ],
    "wof:name":"MI Consulting",
    "wof:placetype":"venue"
},
  "geometry": {"coordinates":[-73.980571,40.62737],"type":"Point"}
}