{
  "type": "Feature",
  "properties": {
    "iso:country":"US",
    "sg:address":"11 State Hwy 29",
    "sg:city":"Greenwich",
    "sg:classifiers":[
        {
            "category":"Building & Trades",
            "subcategory":"Plumbing",
            "type":"Services"
        }
    ],
    "sg:phone":"+1 518 793 2862",
    "sg:postcode":"12834",
    "sg:province":"NY",
    "sg:tags":[
        "conditioning",
        "air",
        "system",
        "contractor"
    ],
    "sg:website":"www.suburbanenergy.com",
    "wof:name":"Suburban Energy Svc",
    "wof:placetype":"venue"
},
  "geometry": {"coordinates":[-73.499309,43.090394],"type":"Point"}
}