{
  "type": "Feature",
  "properties": {
    "addr:full":"1121 Front St Vestal NY 13850",
    "addr:housenumber":"1121",
    "addr:postcode":"13850",
    "addr:street":"Front St",
    "iso:country":"US",
    "sg:address":"1121 Front St",
    "sg:city":"Vestal",
    "sg:classifiers":[
        {
            "category":"Building & Trades",
            "subcategory":"Construction",
            "type":"Services"
        }
    ],
    "sg:phone":"+1 607 748 2701",
    "sg:postcode":"13850",
    "sg:province":"NY",
    "sg:tags":[
        "hanging",
        "contractor"
    ],
    "wof:name":"Sorochnsky Painting",
    "wof:placetype":"venue"
},
  "geometry": {"coordinates":[-76.07185800000001,42.079904],"type":"Point"}
}