{
  "type": "Feature",
  "properties": {
    "iso:country":"US",
    "sg:address":"780 Blossom Rd",
    "sg:city":"Rochester",
    "sg:classifiers":[
        {
            "category":"Health Services",
            "subcategory":"Doctor",
            "type":"Services"
        },
        {
            "category":"Health Services",
            "subcategory":"Clinic",
            "type":"Services"
        }
    ],
    "sg:phone":"+1 585 288 2420",
    "sg:postcode":"14610",
    "sg:province":"NY",
    "sg:tags":[
        "psychological",
        "psychologist"
    ],
    "wof:name":"Santo W Bentivegna Psychlgst",
    "wof:placetype":"venue"
},
  "geometry": {"coordinates":[-77.55059900000001,43.149399],"type":"Point"}
}