{
  "type": "Feature",
  "properties": {
    "iso:country":"US",
    "sg:address":"17 Technology Pl",
    "sg:city":"East Syracuse",
    "sg:classifiers":[
        {
            "category":"Professional",
            "subcategory":"Computer Services",
            "type":"Services"
        }
    ],
    "sg:phone":"+1 315 671 6200",
    "sg:postcode":"13057",
    "sg:province":"NY",
    "sg:tags":[
        "internet"
    ],
    "wof:name":"Dreamscape Online Inc",
    "wof:placetype":"venue"
},
  "geometry": {"coordinates":[-76.056602,43.086919],"type":"Point"}
}