{
  "type": "Feature",
  "properties": {
    "iso:country":"US",
    "sg:address":"8 Kisco Ave",
    "sg:city":"Mt Kisco",
    "sg:classifiers":[
        {
            "category":"Real Estate",
            "subcategory":"Real Estate Agent",
            "type":"Services"
        }
    ],
    "sg:phone":"+1 914 244 4317",
    "sg:postcode":"10549",
    "sg:province":"NY",
    "sg:tags":[
        "management"
    ],
    "sg:website":"www.killingtonhouses.com",
    "wof:name":"KILLINGTONHOUSES.COM",
    "wof:placetype":"venue"
},
  "geometry": {"coordinates":[-73.72914400000001,41.21],"type":"Point"}
}