{
  "type": "Feature",
  "properties": {
    "iso:country":"US",
    "sg:address":"7105 64th St",
    "sg:city":"Ridgewood",
    "sg:classifiers":[
        {
            "category":"Autos & Motor Vehicles",
            "subcategory":"Automobile Sales",
            "type":"Retail Goods"
        }
    ],
    "sg:phone":"+1 718 417 4242",
    "sg:postcode":"11385",
    "sg:province":"NY",
    "sg:tags":[
        "car"
    ],
    "wof:name":"La Fres Ford",
    "wof:placetype":"venue"
},
  "geometry": {"coordinates":[-73.892601,40.701401],"type":"Point"}
}