{
  "type": "Feature",
  "properties": {
    "addr:full":"2555 Boston Rd Bronx NY 10467",
    "addr:housenumber":"2555",
    "addr:postcode":"10467",
    "addr:street":"Boston Rd",
    "iso:country":"US",
    "sg:address":"2555 Boston Rd",
    "sg:city":"Bronx",
    "sg:classifiers":[
        {
            "category":"Manufacturing",
            "subcategory":"Printing",
            "type":"Manufacturing & Wholesale Goods"
        }
    ],
    "sg:phone":"+1   ",
    "sg:postcode":"10467",
    "sg:province":"NY",
    "sg:tags":[
        "commercial",
        "offset"
    ],
    "wof:name":"Walton Press Inc",
    "wof:placetype":"venue"
},
  "geometry": {"coordinates":[-73.86422399999999,40.864101],"type":"Point"}
}