{
  "type": "Feature",
  "properties": {
    "iso:country":"US",
    "sg:address":"526 East Ave",
    "sg:city":"Medina",
    "sg:classifiers":[
        {
            "category":"Building & Trades",
            "subcategory":"Construction",
            "type":"Services"
        }
    ],
    "sg:phone":"+1 585 798 1790",
    "sg:postcode":"14103",
    "sg:province":"NY",
    "sg:tags":[
        "marking",
        "maintenance",
        "parking"
    ],
    "wof:name":"Medina Public Works Dept",
    "wof:placetype":"venue"
},
  "geometry": {"coordinates":[-78.379829,43.219404],"type":"Point"}
}