{
  "type": "Feature",
  "properties": {
    "addr:full":"435 Fulton St Brooklyn NY 11201",
    "addr:housenumber":"435",
    "addr:postcode":"11201",
    "addr:street":"Fulton St",
    "iso:country":"US",
    "sg:address":"435 Fulton St",
    "sg:city":"Brooklyn",
    "sg:classifiers":[
        {
            "category":"Shopping",
            "subcategory":"Jewelry",
            "type":"Retail Goods"
        }
    ],
    "sg:phone":"+1 718 237 8858",
    "sg:postcode":"11201",
    "sg:province":"NY",
    "wof:name":"Jay Jewelers",
    "wof:placetype":"venue"
},
  "geometry": {"coordinates":[-73.987675,40.69175],"type":"Point"}
}