{
  "type": "Feature",
  "properties": {
    "addr:full":"35 Ira Rd Syosset NY 11791",
    "addr:housenumber":"35",
    "addr:postcode":"11791",
    "addr:street":"Ira Rd",
    "iso:country":"US",
    "sg:address":"35 Ira Rd",
    "sg:city":"Syosset",
    "sg:classifiers":[
        {
            "category":"Sports & Exercise",
            "subcategory":"Gym",
            "type":"Entertainment"
        }
    ],
    "sg:phone":"+1   ",
    "sg:postcode":"11791",
    "sg:province":"NY",
    "sg:tags":[
        "fitness",
        "physical",
        "facility"
    ],
    "wof:name":"Curves For Women",
    "wof:placetype":"venue"
},
  "geometry": {"coordinates":[-73.50021,40.823525],"type":"Point"}
}