{
  "type": "Feature",
  "properties": {
    "addr:full":"750 E Adams St Syracuse NY 13210",
    "addr:housenumber":"750",
    "addr:postcode":"13210",
    "addr:street":"E Adams St",
    "iso:country":"US",
    "sg:address":"750 E Adams St",
    "sg:city":"Syracuse",
    "sg:classifiers":[
        {
            "category":"Government",
            "subcategory":"Court House",
            "type":"Public Place"
        }
    ],
    "sg:phone":"+1 315 464 8309",
    "sg:postcode":"13210",
    "sg:province":"NY",
    "sg:tags":[
        "state",
        "counsel"
    ],
    "sg:website":"www.oag.state.ny.us",
    "wof:name":"Attorney General",
    "wof:placetype":"venue"
},
  "geometry": {"coordinates":[-76.13784699999999,43.042677],"type":"Point"}
}