{
  "type": "Feature",
  "properties": {
    "addr:full":"200 S Union St Spencerport NY 14559",
    "addr:housenumber":"200",
    "addr:postcode":"14559",
    "addr:street":"S Union St",
    "iso:country":"US",
    "sg:address":"200 S Union St",
    "sg:city":"Spencerport",
    "sg:classifiers":[
        {
            "category":"Social Services",
            "type":"Services"
        }
    ],
    "sg:phone":"+1 585 352 3250",
    "sg:postcode":"14559",
    "sg:province":"NY",
    "wof:name":"Senior Ogden Center",
    "wof:placetype":"venue"
},
  "geometry": {"coordinates":[-77.800707,43.190679],"type":"Point"}
}