{
  "type": "Feature",
  "properties": {
    "iso:country":"US",
    "sg:address":"499 Park Ave",
    "sg:city":"New York",
    "sg:classifiers":[
        {
            "category":"Professional",
            "subcategory":"Lawyer & Legal Services",
            "type":"Services"
        }
    ],
    "sg:phone":"+1 212 889 9250",
    "sg:postcode":"10022",
    "sg:province":"NY",
    "wof:name":"Aronoff Steven K Attorney PC",
    "wof:placetype":"venue"
},
  "geometry": {"coordinates":[-73.969601,40.762531],"type":"Point"}
}