{
  "type": "Feature",
  "properties": {
    "addr:full":"2390 Ford Rd Newark NY 14513",
    "addr:housenumber":"2390",
    "addr:postcode":"14513",
    "addr:street":"Ford Rd",
    "iso:country":"US",
    "sg:address":"2390 Ford Rd",
    "sg:city":"Newark",
    "sg:classifiers":[
        {
            "category":"Building & Trades",
            "subcategory":"Construction",
            "type":"Services"
        }
    ],
    "sg:phone":"+1 315 331 2866",
    "sg:postcode":"14513",
    "sg:province":"NY",
    "sg:tags":[
        "contractor"
    ],
    "wof:name":"Rkv Contracting",
    "wof:placetype":"venue"
},
  "geometry": {"coordinates":[-77.09974800000001,43.093775],"type":"Point"}
}