{
  "type": "Feature",
  "properties": {
    "addr:full":"600 Johnson Ave Brooklyn NY 11237",
    "addr:housenumber":"600",
    "addr:postcode":"11237",
    "addr:street":"Johnson Ave",
    "iso:country":"US",
    "sg:address":"600 Johnson Ave",
    "sg:city":"Brooklyn",
    "sg:classifiers":[
        {
            "category":"Wholesale",
            "subcategory":"Non-durable Goods",
            "type":"Manufacturing & Wholesale Goods"
        }
    ],
    "sg:phone":"+1   ",
    "sg:postcode":"11237",
    "sg:province":"NY",
    "sg:tags":[
        "product",
        "mfg"
    ],
    "wof:name":"Royal Products Inc",
    "wof:placetype":"venue"
},
  "geometry": {"coordinates":[-73.925301,40.708745],"type":"Point"}
}