{
  "type": "Feature",
  "properties": {
    "iso:country":"US",
    "sg:address":"44 W Main St",
    "sg:city":"Norwich",
    "sg:classifiers":[
        {
            "category":"Government",
            "subcategory":"Office",
            "type":"Public Place"
        }
    ],
    "sg:phone":"+1 607 334 7114",
    "sg:postcode":"13815",
    "sg:province":"NY",
    "wof:name":"Womens Infants & Children",
    "wof:placetype":"venue"
},
  "geometry": {"coordinates":[-75.52769499999999,42.530845],"type":"Point"}
}