{
  "type": "Feature",
  "properties": {
    "addr:full":"202 Bridge St Ithaca NY 14850",
    "addr:housenumber":"202",
    "addr:postcode":"14850",
    "addr:street":"Bridge St",
    "iso:country":"US",
    "sg:address":"202 Bridge St",
    "sg:city":"Ithaca",
    "sg:classifiers":[
        {
            "category":"Shopping",
            "subcategory":"Computers & Home Electronics",
            "type":"Retail Goods"
        }
    ],
    "sg:phone":"+1 607 277 3981",
    "sg:postcode":"14850",
    "sg:province":"NY",
    "sg:tags":[
        "publisher",
        "book"
    ],
    "sg:website":"http://www.lexiconbridge.com",
    "wof:name":"Lexicon Bridge Publishers",
    "wof:placetype":"venue"
},
  "geometry": {"coordinates":[-76.48016200000001,42.432779],"type":"Point"}
}