{
  "type": "Feature",
  "properties": {
    "iso:country":"US",
    "sg:address":"516 Farm Ranch Rd W",
    "sg:city":"Bethpage",
    "sg:classifiers":[
        {
            "category":"Wholesale",
            "subcategory":"Durable Goods & Equipment",
            "type":"Manufacturing & Wholesale Goods"
        }
    ],
    "sg:phone":"+1   ",
    "sg:postcode":"11714",
    "sg:province":"NY",
    "sg:tags":[
        "resellers",
        "optical",
        "e",
        "telescope",
        "mfg"
    ],
    "wof:name":"Technotronics",
    "wof:placetype":"venue"
},
  "geometry": {"coordinates":[-73.501232,40.738306],"type":"Point"}
}