{
  "type": "Feature",
  "properties": {
    "addr:full":"1759 Ridge Rd E Rochester NY 14621",
    "addr:housenumber":"1759",
    "addr:postcode":"14621",
    "addr:street":"Ridge Rd E",
    "iso:country":"US",
    "sg:address":"1759 Ridge Rd E",
    "sg:city":"Rochester",
    "sg:classifiers":[
        {
            "category":"Shopping",
            "subcategory":"Clothing, Apparel, & Fashions",
            "type":"Retail Goods"
        }
    ],
    "sg:phone":"+1 585 266 6010",
    "sg:postcode":"14621",
    "sg:province":"NY",
    "sg:website":"www.rainbowshops.com",
    "wof:name":"Rainbow",
    "wof:placetype":"venue"
},
  "geometry": {"coordinates":[-77.569524,43.201105],"type":"Point"}
}