{
  "type": "Feature",
  "properties": {
    "iso:country":"US",
    "sg:address":"5912 Commane Rd",
    "sg:city":"La Fayette",
    "sg:classifiers":[
        {
            "category":"Building & Trades",
            "subcategory":"Construction",
            "type":"Services"
        }
    ],
    "sg:phone":"+1 315 699 6878",
    "sg:postcode":"13084",
    "sg:province":"NY",
    "sg:tags":[
        "insulation",
        "heat",
        "contractor"
    ],
    "wof:name":"Efficient Technologies Inc",
    "wof:placetype":"venue"
},
  "geometry": {"coordinates":[-76.102287,42.921427],"type":"Point"}
}