{
  "type": "Feature",
  "properties": {
    "addr:full":"331 S End Ave New York NY 10280",
    "addr:housenumber":"331",
    "addr:postcode":"10280",
    "addr:street":"S End Ave",
    "iso:country":"US",
    "sg:address":"331 S End Ave",
    "sg:city":"New York",
    "sg:classifiers":[
        {
            "category":"Banks & Credit Unions",
            "subcategory":"Bank",
            "type":"Services"
        }
    ],
    "sg:phone":"+1 212 935 9935",
    "sg:postcode":"10280",
    "sg:province":"NY",
    "sg:tags":[
        "state",
        "commercial"
    ],
    "wof:name":"Chase Manhattan Bank",
    "wof:placetype":"venue"
},
  "geometry": {"coordinates":[-74.01619700000001,40.7108],"type":"Point"}
}