{
  "type": "Feature",
  "properties": {
    "iso:country":"US",
    "sg:address":"84 Moore St",
    "sg:city":"Brooklyn",
    "sg:classifiers":[
        {
            "category":"Shopping",
            "subcategory":"Stationery & Office Supplies",
            "type":"Retail Goods"
        }
    ],
    "sg:phone":"+1   ",
    "sg:postcode":"11206",
    "sg:province":"NY",
    "wof:name":"Victory Toy Store",
    "wof:placetype":"venue"
},
  "geometry": {"coordinates":[-73.941159,40.703808],"type":"Point"}
}