{
  "type": "Feature",
  "properties": {
    "addr:full":"332 Baynes St Buffalo NY 14213",
    "addr:housenumber":"332",
    "addr:postcode":"14213",
    "addr:street":"Baynes St",
    "iso:country":"US",
    "sg:address":"332 Baynes St",
    "sg:city":"Buffalo",
    "sg:classifiers":[
        {
            "category":"Organizations",
            "subcategory":"Religious Organization",
            "type":"Services"
        }
    ],
    "sg:phone":"+1 716 885 6641",
    "sg:postcode":"14213",
    "sg:province":"NY",
    "wof:name":"First United Methodist Church",
    "wof:placetype":"venue"
},
  "geometry": {"coordinates":[-78.88490299999999,42.924301],"type":"Point"}
}