{
  "type": "Feature",
  "properties": {
    "iso:country":"US",
    "sg:address":"130 W 30 St",
    "sg:city":"New York",
    "sg:classifiers":[
        {
            "category":"Social Services",
            "type":"Services"
        }
    ],
    "sg:phone":"+1   ",
    "sg:postcode":"10001",
    "sg:province":"NY",
    "sg:tags":[
        "consulting"
    ],
    "wof:name":"Schneider Consulting Group",
    "wof:placetype":"venue"
},
  "geometry": {"coordinates":[-73.991839,40.748038],"type":"Point"}
}