{
  "type": "Feature",
  "properties": {
    "iso:country":"US",
    "sg:address":"248 Vineyard Rd",
    "sg:city":"Huntington",
    "sg:classifiers":[
        {
            "category":"Insurance",
            "subcategory":"Insurance Agent",
            "type":"Services"
        }
    ],
    "sg:phone":"+1 631 351 1220",
    "sg:postcode":"11743",
    "sg:province":"NY",
    "wof:name":"Ramon Mosteiro CLU Inc",
    "wof:placetype":"venue"
},
  "geometry": {"coordinates":[-73.413433,40.897504],"type":"Point"}
}