{
  "type": "Feature",
  "properties": {
    "iso:country":"US",
    "sg:address":"198 New York Ave",
    "sg:city":"Huntington",
    "sg:classifiers":[
        {
            "category":"Personal",
            "subcategory":"Beauty Salon",
            "type":"Services"
        }
    ],
    "sg:phone":"+1 631 424 8080",
    "sg:postcode":"11743",
    "sg:province":"NY",
    "wof:name":"Halo Hair",
    "wof:placetype":"venue"
},
  "geometry": {"coordinates":[-73.423918,40.87576],"type":"Point"}
}