{
  "type": "Feature",
  "properties": {
    "addr:full":"5 Milano Ct Croton On Hudson NY 10520",
    "addr:housenumber":"5",
    "addr:postcode":"10520",
    "addr:street":"Milano Ct",
    "iso:country":"US",
    "sg:address":"5 Milano Ct",
    "sg:city":"Croton On Hudson",
    "sg:classifiers":[
        {
            "category":"Social Services",
            "type":"Services"
        }
    ],
    "sg:phone":"+1   ",
    "sg:postcode":"10520",
    "sg:province":"NY",
    "wof:name":"John L Tufanio",
    "wof:placetype":"venue"
},
  "geometry": {"coordinates":[-73.921178,41.238297],"type":"Point"}
}