{
  "type": "Feature",
  "properties": {
    "iso:country":"US",
    "sg:address":"1300 Victory Blvd",
    "sg:city":"Staten Island",
    "sg:classifiers":[
        {
            "category":"Building & Trades",
            "subcategory":"Construction",
            "type":"Services"
        }
    ],
    "sg:phone":"+1 718 273 2789",
    "sg:postcode":"10301",
    "sg:province":"NY",
    "sg:tags":[
        "product",
        "asphalt"
    ],
    "wof:name":"Vincent Paving & Seal Coating",
    "wof:placetype":"venue"
},
  "geometry": {"coordinates":[-74.10677699999999,40.61506],"type":"Point"}
}