{
  "type": "Feature",
  "properties": {
    "addr:full":"454 W 41st St New York NY 10036",
    "addr:housenumber":"454",
    "addr:postcode":"10036",
    "addr:street":"W 41St St",
    "iso:country":"US",
    "sg:address":"454 W 41st St",
    "sg:city":"New York",
    "sg:classifiers":[
        {
            "category":"Real Estate",
            "subcategory":"Real Estate Operator",
            "type":"Services"
        }
    ],
    "sg:phone":"+1 212 695 2301",
    "sg:postcode":"10036",
    "sg:province":"NY",
    "sg:tags":[
        "building",
        "apartment"
    ],
    "wof:name":"J Alden Enterprises Ltd",
    "wof:placetype":"venue"
},
  "geometry": {"coordinates":[-73.995537,40.758689],"type":"Point"}
}