{
  "type": "Feature",
  "properties": {
    "iso:country":"US",
    "sg:address":"2987 Hempstead Tpke",
    "sg:city":"Levittown",
    "sg:classifiers":[
        {
            "category":"Autos & Motor Vehicles",
            "subcategory":"Auto Supplies",
            "type":"Retail Goods"
        }
    ],
    "sg:phone":"+1 516 579 7500",
    "sg:postcode":"11756",
    "sg:province":"NY",
    "sg:tags":[
        "automobile",
        "parts"
    ],
    "sg:website":"www.autobarn.com",
    "wof:name":"Auto Barn",
    "wof:placetype":"venue"
},
  "geometry": {"coordinates":[-73.52702600000001,40.724768],"type":"Point"}
}