{
  "type": "Feature",
  "properties": {
    "addr:full":"701 Pelham Rd New Rochelle NY 10805",
    "addr:housenumber":"701",
    "addr:postcode":"10805",
    "addr:street":"Pelham Rd",
    "iso:country":"US",
    "sg:address":"701 Pelham Rd",
    "sg:city":"New Rochelle",
    "sg:classifiers":[
        {
            "category":"Professional",
            "subcategory":"Accounting & Tax Preparation",
            "type":"Services"
        }
    ],
    "sg:phone":"+1   ",
    "sg:postcode":"10805",
    "sg:province":"NY",
    "wof:name":"Jerome Cohen",
    "wof:placetype":"venue"
},
  "geometry": {"coordinates":[-73.788308,40.889798],"type":"Point"}
}