{
  "type": "Feature",
  "properties": {
    "addr:full":"649 Taylor Rd Massena NY 13662",
    "addr:housenumber":"649",
    "addr:postcode":"13662",
    "addr:street":"Taylor Rd",
    "iso:country":"US",
    "sg:address":"649 Taylor Rd",
    "sg:city":"Massena",
    "sg:classifiers":[
        {
            "category":"Professional",
            "subcategory":"Business Services",
            "type":"Services"
        }
    ],
    "sg:phone":"+1   ",
    "sg:postcode":"13662",
    "sg:province":"NY",
    "sg:tags":[
        "consulting",
        "workplace"
    ],
    "wof:name":"Vanguard Cmmnctions Consulting",
    "wof:placetype":"venue"
},
  "geometry": {"coordinates":[-74.803628,44.889382],"type":"Point"}
}