{
  "type": "Feature",
  "properties": {
    "addr:full":"1255 40th St Brooklyn NY 11218",
    "addr:housenumber":"1255",
    "addr:postcode":"11218",
    "addr:street":"40Th St",
    "iso:country":"US",
    "sg:address":"1255 40th St",
    "sg:city":"Brooklyn",
    "sg:classifiers":[
        {
            "category":"Banks & Credit Unions",
            "subcategory":"Bank",
            "type":"Services"
        }
    ],
    "sg:phone":"+1 718 435 4907",
    "sg:postcode":"11218",
    "sg:province":"NY",
    "sg:tags":[
        "broker",
        "mortgage"
    ],
    "wof:name":"Gallery The Funding Inc",
    "wof:placetype":"venue"
},
  "geometry": {"coordinates":[-73.98775000000001,40.640859],"type":"Point"}
}