{
  "type": "Feature",
  "properties": {
    "addr:full":"179 Frowein Rd East Moriches NY 11940",
    "addr:housenumber":"179",
    "addr:postcode":"11940",
    "addr:street":"Frowein Rd",
    "iso:country":"US",
    "sg:address":"179 Frowein Rd",
    "sg:city":"East Moriches",
    "sg:classifiers":[
        {
            "category":"Utilities",
            "subcategory":"Fuel Oil & Lpg",
            "type":"Services"
        }
    ],
    "sg:phone":"+1   ",
    "sg:postcode":"11940",
    "sg:province":"NY",
    "sg:tags":[
        "dealer"
    ],
    "wof:name":"Seaview Fuel",
    "wof:placetype":"venue"
},
  "geometry": {"coordinates":[-72.778533,40.808724],"type":"Point"}
}