{
  "type": "Feature",
  "properties": {
    "addr:full":"419 Park Avenue S New York NY 10016",
    "addr:housenumber":"419",
    "addr:postcode":"10016",
    "addr:street":"Park Avenue S",
    "iso:country":"US",
    "sg:address":"419 Park Avenue S",
    "sg:city":"New York",
    "sg:classifiers":[
        {
            "category":"Building & Trades",
            "subcategory":"Construction",
            "type":"Services"
        }
    ],
    "sg:phone":"+1 212 213 4500",
    "sg:postcode":"10016",
    "sg:province":"NY",
    "sg:tags":[
        "interior",
        "design"
    ],
    "sg:website":"www.keiserassociates.com",
    "wof:name":"Keiser Associates",
    "wof:placetype":"venue"
},
  "geometry": {"coordinates":[-73.983526,40.743684],"type":"Point"}
}