{
  "type": "Feature",
  "properties": {
    "iso:country":"US",
    "sg:address":"292 High St",
    "sg:city":"Buffalo",
    "sg:classifiers":[
        {
            "category":"Social Services",
            "type":"Services"
        }
    ],
    "sg:phone":"+1 716 882 4637",
    "sg:postcode":"14204",
    "sg:province":"NY",
    "wof:name":"Moot Senior Citizen Center",
    "wof:placetype":"venue"
},
  "geometry": {"coordinates":[-78.858543,42.900329],"type":"Point"}
}