{
  "type": "Feature",
  "properties": {
    "iso:country":"US",
    "sg:address":"1616 George St",
    "sg:city":"Queens",
    "sg:classifiers":[
        {
            "category":"Retail",
            "subcategory":"Event Space",
            "type":"Services"
        }
    ],
    "sg:phone":"+1 718 381 7000",
    "sg:postcode":"11385",
    "sg:province":"NY",
    "sg:tags":[
        "venue"
    ],
    "wof:name":"Welcome Banquet Hall",
    "wof:placetype":"venue"
},
  "geometry": {"coordinates":[-73.90415,40.696465],"type":"Point"}
}