{
  "type": "Feature",
  "properties": {
    "addr:full":"178 Simonson Ave Staten Island NY 10303",
    "addr:housenumber":"178",
    "addr:postcode":"10303",
    "addr:street":"Simonson Ave",
    "iso:country":"US",
    "sg:address":"178 Simonson Ave",
    "sg:city":"Staten Island",
    "sg:classifiers":[
        {
            "category":"Social Services",
            "subcategory":"Child Care",
            "type":"Services"
        }
    ],
    "sg:phone":"+1   ",
    "sg:postcode":"10303",
    "sg:province":"NY",
    "sg:tags":[
        "day"
    ],
    "wof:name":"4 Angels Day Care",
    "wof:placetype":"venue"
},
  "geometry": {"coordinates":[-74.152145,40.633133],"type":"Point"}
}