{
  "type": "Feature",
  "properties": {
    "iso:country":"US",
    "sg:address":"187 Troy Ave",
    "sg:city":"Brooklyn",
    "sg:classifiers":[
        {
            "category":"Wholesale",
            "subcategory":"Scrap",
            "type":"Manufacturing & Wholesale Goods"
        }
    ],
    "sg:phone":"+1 718 493 2901",
    "sg:postcode":"11213",
    "sg:province":"NY",
    "sg:tags":[
        "recycling",
        "center"
    ],
    "wof:name":"Tomra Metro Inc",
    "wof:placetype":"venue"
},
  "geometry": {"coordinates":[-73.936234,40.673187],"type":"Point"}
}