{
  "type": "Feature",
  "properties": {
    "iso:country":"US",
    "sg:address":"11 Loughlin Dr",
    "sg:city":"Shirley",
    "sg:classifiers":[
        {
            "category":"Autos & Motor Vehicles",
            "subcategory":"Auto Supplies",
            "type":"Retail Goods"
        }
    ],
    "sg:phone":"+1 631 395 9014",
    "sg:postcode":"11967",
    "sg:province":"NY",
    "sg:tags":[
        "battery"
    ],
    "wof:name":"Battery Doctor",
    "wof:placetype":"venue"
},
  "geometry": {"coordinates":[-72.87284200000001,40.779939],"type":"Point"}
}