{
  "type": "Feature",
  "properties": {
    "addr:full":"343 Adelphi St Brooklyn NY 11238",
    "addr:housenumber":"343",
    "addr:postcode":"11238",
    "addr:street":"Adelphi St",
    "iso:country":"US",
    "sg:address":"343 Adelphi St",
    "sg:city":"Brooklyn",
    "sg:classifiers":[
        {
            "category":"Building & Trades",
            "subcategory":"Electrical",
            "type":"Services"
        }
    ],
    "sg:phone":"+1 718 783 8135",
    "sg:postcode":"11238",
    "sg:province":"NY",
    "sg:tags":[
        "electrical",
        "contractor"
    ],
    "wof:name":"Palazzo Design Inc",
    "wof:placetype":"venue"
},
  "geometry": {"coordinates":[-73.970466,40.686651],"type":"Point"}
}