{
  "type": "Feature",
  "properties": {
    "addr:full":"1044 University Ave Rochester NY 14607",
    "addr:housenumber":"1044",
    "addr:postcode":"14607",
    "addr:street":"University Ave",
    "iso:country":"US",
    "sg:address":"1044 University Ave",
    "sg:city":"Rochester",
    "sg:classifiers":[
        {
            "category":"Manufacturing",
            "subcategory":"Printing",
            "type":"Manufacturing & Wholesale Goods"
        }
    ],
    "sg:phone":"+1 585 256 0070",
    "sg:postcode":"14607",
    "sg:province":"NY",
    "sg:tags":[
        "screen"
    ],
    "wof:name":"T-Shirt Express Corp",
    "wof:placetype":"venue"
},
  "geometry": {"coordinates":[-77.57232999999999,43.152069],"type":"Point"}
}