{
  "type": "Feature",
  "properties": {
    "iso:country":"US",
    "sg:address":"6 Fairlawn Ave",
    "sg:city":"Middletown",
    "sg:classifiers":[
        {
            "category":"Social Services",
            "subcategory":"Job Training",
            "type":"Services"
        }
    ],
    "sg:phone":"+1 845 341 1224",
    "sg:postcode":"10940",
    "sg:province":"NY",
    "sg:tags":[
        "rehabilitation"
    ],
    "wof:name":"Prosthetic Rehab Ctr",
    "wof:placetype":"venue"
},
  "geometry": {"coordinates":[-74.40346099999999,41.453058],"type":"Point"}
}