{
  "type": "Feature",
  "properties": {
    "iso:country":"US",
    "sg:address":"106 Meadowdale Ln",
    "sg:city":"Buffalo",
    "sg:classifiers":[
        {
            "category":"Bars & Pubs",
            "type":"Food & Drink"
        }
    ],
    "sg:phone":"+1 716 677 2712",
    "sg:postcode":"14224",
    "sg:province":"NY",
    "wof:name":"Jonathan Gross Enterprises Inc",
    "wof:placetype":"venue"
},
  "geometry": {"coordinates":[-78.70487,42.842769],"type":"Point"}
}