{
  "type": "Feature",
  "properties": {
    "iso:country":"US",
    "sg:address":"34 E Genesee St",
    "sg:city":"Baldwinsville",
    "sg:classifiers":[
        {
            "category":"Utilities",
            "subcategory":"Mobile Phone",
            "type":"Services"
        }
    ],
    "sg:phone":"+1 315 638 3733",
    "sg:postcode":"13027",
    "sg:province":"NY",
    "sg:tags":[
        "telephone",
        "cellular"
    ],
    "wof:name":"Cellular Shop",
    "wof:placetype":"venue"
},
  "geometry": {"coordinates":[-76.326785,43.159144],"type":"Point"}
}