{
  "type": "Feature",
  "properties": {
    "iso:country":"US",
    "sg:address":"438 W 116th St",
    "sg:city":"New York",
    "sg:classifiers":[
        {
            "category":"Shopping",
            "subcategory":"Computers & Home Electronics",
            "type":"Retail Goods"
        }
    ],
    "sg:phone":"+1   ",
    "sg:postcode":"10027",
    "sg:province":"NY",
    "sg:tags":[
        "technical",
        "sales",
        "merchandise"
    ],
    "wof:name":"Evory Technologies Inc",
    "wof:placetype":"venue"
},
  "geometry": {"coordinates":[-73.96059099999999,40.806484],"type":"Point"}
}