{
  "type": "Feature",
  "properties": {
    "addr:full":"341 Columbus Ave New York NY 10024",
    "addr:housenumber":"341",
    "addr:postcode":"10024",
    "addr:street":"Columbus Ave",
    "iso:country":"US",
    "sg:address":"341 Columbus Ave",
    "sg:city":"New York",
    "sg:classifiers":[
        {
            "category":"Professional",
            "subcategory":"Business Services",
            "type":"Services"
        }
    ],
    "sg:phone":"+1 212 799 5900",
    "sg:postcode":"10024",
    "sg:province":"NY",
    "sg:tags":[
        "decor",
        "consultant",
        "design",
        "interior",
        "home",
        "decorator"
    ],
    "sg:website":"www.dwr.com",
    "wof:name":"Design Within Reach",
    "wof:placetype":"venue"
},
  "geometry": {"coordinates":[-73.976862,40.780024],"type":"Point"}
}