{
  "type": "Feature",
  "properties": {
    "addr:full":"1535 Broadway Manhattan NY 10036",
    "addr:housenumber":"1535",
    "addr:postcode":"10036",
    "addr:street":"Broadway",
    "iso:country":"US",
    "sg:address":"1535 Broadway",
    "sg:city":"Manhattan",
    "sg:classifiers":[
        {
            "category":"Arts & Performance",
            "subcategory":"Arts Center",
            "type":"Entertainment"
        }
    ],
    "sg:phone":"+1 212 382 0100",
    "sg:postcode":"10036",
    "sg:province":"NY",
    "wof:name":"Marquis Theatre",
    "wof:placetype":"venue"
},
  "geometry": {"coordinates":[-73.985517,40.758408],"type":"Point"}
}