{
  "type": "Feature",
  "properties": {
    "addr:full":"600 Thayer Rd West Point NY 10996",
    "addr:housenumber":"600",
    "addr:postcode":"10996",
    "addr:street":"Thayer Rd",
    "iso:country":"US",
    "sg:address":"600 Thayer Rd",
    "sg:city":"West Point",
    "sg:classifiers":[
        {
            "category":"Professional",
            "type":"Services"
        }
    ],
    "sg:phone":"+1 845 446 0913",
    "sg:postcode":"10996",
    "sg:province":"NY",
    "sg:tags":[
        "establishment"
    ],
    "wof:name":"TNLCN Ward",
    "wof:placetype":"venue"
},
  "geometry": {"coordinates":[-73.95631899999999,41.390399],"type":"Point"}
}