{
  "type": "Feature",
  "properties": {
    "iso:country":"US",
    "sg:address":"15 Knickerbocker Ave Unit 3",
    "sg:city":"Holbrook",
    "sg:classifiers":[
        {
            "category":"Social Services",
            "subcategory":"Child Care",
            "type":"Services"
        },
        {
            "category":"Education",
            "subcategory":"Preschool",
            "type":"Public Place"
        },
        {
            "category":"Education",
            "subcategory":"School",
            "type":"Public Place"
        }
    ],
    "sg:phone":"+1 631 471 2252",
    "sg:postcode":"11741",
    "sg:province":"NY",
    "sg:tags":[
        "elementary",
        "day"
    ],
    "wof:name":"Learning Seeds of Holbrook Inc",
    "wof:placetype":"venue"
},
  "geometry": {"coordinates":[-73.091103,40.8097],"type":"Point"}
}