{
  "type": "Feature",
  "properties": {
    "addr:full":"1 Interstate Ave Albany NY 12205",
    "addr:housenumber":"1",
    "addr:postcode":"12205",
    "addr:street":"Interstate Ave",
    "iso:country":"US",
    "sg:address":"1 Interstate Ave",
    "sg:city":"Albany",
    "sg:classifiers":[
        {
            "category":"Freight",
            "type":"Transportation"
        }
    ],
    "sg:phone":"+1 518 438 6100",
    "sg:postcode":"12205",
    "sg:province":"NY",
    "sg:tags":[
        "delivery"
    ],
    "sg:website":"www.cdl.net",
    "wof:name":"C D & L",
    "wof:placetype":"venue"
},
  "geometry": {"coordinates":[-73.81403,42.694159],"type":"Point"}
}