{
  "type": "Feature",
  "properties": {
    "addr:full":"146 Henry St New York NY 10002",
    "addr:housenumber":"146",
    "addr:postcode":"10002",
    "addr:street":"Henry St",
    "iso:country":"US",
    "sg:address":"146 Henry St",
    "sg:city":"New York",
    "sg:classifiers":[
        {
            "category":"Food & Beverages",
            "subcategory":"Fruits & Vegetables",
            "type":"Retail Goods"
        }
    ],
    "sg:phone":"+1 212 227 1327",
    "sg:postcode":"10002",
    "sg:province":"NY",
    "sg:tags":[
        "produce"
    ],
    "wof:name":"Fresh From Produce Inc",
    "wof:placetype":"venue"
},
  "geometry": {"coordinates":[-73.98860000000001,40.713511],"type":"Point"}
}