{
  "type": "Feature",
  "properties": {
    "addr:full":"10818 72nd Ave Forest Hills NY 11375",
    "addr:housenumber":"10818",
    "addr:postcode":"11375",
    "addr:street":"72Nd Ave",
    "iso:country":"US",
    "sg:address":"10818 72nd Ave",
    "sg:city":"Forest Hills",
    "sg:classifiers":[
        {
            "category":"Professional",
            "subcategory":"Lawyer & Legal Services",
            "type":"Services"
        }
    ],
    "sg:phone":"+1 516 921 3434",
    "sg:postcode":"11375",
    "sg:province":"NY",
    "wof:name":"Exective Title Agency Llc",
    "wof:placetype":"venue"
},
  "geometry": {"coordinates":[-73.842499,40.719501],"type":"Point"}
}