{
  "type": "Feature",
  "properties": {
    "addr:full":"313 E Main St Patchogue NY 11772",
    "addr:housenumber":"313",
    "addr:postcode":"11772",
    "addr:street":"E Main St",
    "iso:country":"US",
    "sg:address":"313 E Main St",
    "sg:city":"Patchogue",
    "sg:classifiers":[
        {
            "category":"Shopping",
            "type":"Retail Goods"
        }
    ],
    "sg:phone":"+1 631 475 5353",
    "sg:postcode":"11772",
    "sg:province":"NY",
    "sg:tags":[
        "stamp",
        "collector",
        "for"
    ],
    "sg:website":"www.millersmint.com",
    "wof:name":"Miller's Mint",
    "wof:placetype":"venue"
},
  "geometry": {"coordinates":[-73.007122,40.766076],"type":"Point"}
}