{
  "type": "Feature",
  "properties": {
    "addr:full":"110 E 59th St New York NY 10022",
    "addr:housenumber":"110",
    "addr:postcode":"10022",
    "addr:street":"E 59Th St",
    "iso:country":"US",
    "sg:address":"110 E 59th St",
    "sg:city":"New York",
    "sg:classifiers":[
        {
            "category":"Recreation",
            "type":"Entertainment"
        }
    ],
    "sg:phone":"+1 212 821 0100",
    "sg:postcode":"10022",
    "sg:province":"NY",
    "sg:tags":[
        "active",
        "life"
    ],
    "wof:name":"Imax Corporation",
    "wof:placetype":"venue"
},
  "geometry": {"coordinates":[-73.96929900000001,40.7626],"type":"Point"}
}