{
  "type": "Feature",
  "properties": {
    "addr:full":"1801 Penfield Rd Penfield NY 14526",
    "addr:housenumber":"1801",
    "addr:postcode":"14526",
    "addr:street":"Penfield Rd",
    "iso:country":"US",
    "sg:address":"1801 Penfield Rd",
    "sg:city":"Penfield",
    "sg:classifiers":[
        {
            "category":"Shopping",
            "subcategory":"Optical Goods",
            "type":"Retail Goods"
        },
        {
            "category":"Shopping",
            "subcategory":"Optician",
            "type":"Retail Goods"
        },
        {
            "category":"Health Services",
            "subcategory":"Optometrist",
            "type":"Services"
        },
        {
            "category":"Personal",
            "subcategory":"Shoe Repair & Shine",
            "type":"Services"
        }
    ],
    "sg:phone":"+1 585 568 8728",
    "sg:postcode":"14526",
    "sg:province":"NY",
    "sg:tags":[
        "lens",
        "contact",
        "sunglass"
    ],
    "sg:website":"http://www.lankfordwarner.com",
    "wof:name":"Lankford-Warner Opticians",
    "wof:placetype":"venue"
},
  "geometry": {"coordinates":[-77.479409,43.129061],"type":"Point"}
}