{
  "type": "Feature",
  "properties": {
    "addr:full":"1552 Merrick Rd North Merrick NY 11566",
    "addr:housenumber":"1552",
    "addr:postcode":"11566",
    "addr:street":"Merrick Rd",
    "iso:country":"US",
    "sg:address":"1552 Merrick Rd",
    "sg:city":"North Merrick",
    "sg:classifiers":[
        {
            "category":"Restaurant",
            "type":"Food & Drink"
        }
    ],
    "sg:phone":"+1 516 379 1639",
    "sg:postcode":"11566",
    "sg:province":"NY",
    "wof:name":"China King II",
    "wof:placetype":"venue"
},
  "geometry": {"coordinates":[-73.565076,40.653737],"type":"Point"}
}