{
  "type": "Feature",
  "properties": {
    "addr:full":"235 E 9 St New York NY 10003",
    "addr:housenumber":"235;9",
    "addr:postcode":"10003",
    "addr:street":"E",
    "iso:country":"US",
    "sg:address":"235 E 9 St",
    "sg:city":"New York",
    "sg:classifiers":[
        {
            "category":"Shopping",
            "type":"Retail Goods"
        }
    ],
    "sg:phone":"+1   ",
    "sg:postcode":"10003",
    "sg:province":"NY",
    "sg:tags":[
        "merchandise"
    ],
    "wof:name":"Whiskers",
    "wof:placetype":"venue"
},
  "geometry": {"coordinates":[-73.987527,40.72944],"type":"Point"}
}