{
  "type": "Feature",
  "properties": {
    "iso:country":"US",
    "sg:address":"439 Central Ave",
    "sg:city":"Rochester",
    "sg:classifiers":[
        {
            "category":"Professional",
            "subcategory":"Art Services",
            "type":"Services"
        },
        {
            "category":"Wholesale",
            "subcategory":"Non-durable Goods",
            "type":"Manufacturing & Wholesale Goods"
        }
    ],
    "sg:phone":"+1 585 987 6940",
    "sg:postcode":"14605",
    "sg:province":"NY",
    "sg:tags":[
        "commercial",
        "clothing",
        "advertising"
    ],
    "wof:name":"Namedroppers Sports Wear",
    "wof:placetype":"venue"
},
  "geometry": {"coordinates":[-77.604474,43.162792],"type":"Point"}
}