{
  "type": "Feature",
  "properties": {
    "addr:full":"840 W End Ave New York NY 10025",
    "addr:housenumber":"840",
    "addr:postcode":"10025",
    "addr:street":"W End Ave",
    "iso:country":"US",
    "sg:address":"840 W End Ave",
    "sg:city":"New York",
    "sg:classifiers":[
        {
            "category":"Professional",
            "type":"Services"
        }
    ],
    "sg:phone":"+1 212 316 1258",
    "sg:postcode":"10025",
    "sg:province":"NY",
    "sg:tags":[
        "establishment"
    ],
    "wof:name":"Aish Hatorah Intl",
    "wof:placetype":"venue"
},
  "geometry": {"coordinates":[-73.970423,40.799071],"type":"Point"}
}