{
  "type": "Feature",
  "properties": {
    "addr:full":"34 Liberty St Arcade NY 14009",
    "addr:housenumber":"34",
    "addr:postcode":"14009",
    "addr:street":"Liberty St",
    "iso:country":"US",
    "sg:address":"34 Liberty St",
    "sg:city":"Arcade",
    "sg:classifiers":[
        {
            "category":"Manufacturing",
            "subcategory":"Metals",
            "type":"Manufacturing & Wholesale Goods"
        }
    ],
    "sg:phone":"+1   ",
    "sg:postcode":"14009",
    "sg:province":"NY",
    "sg:tags":[
        "windows",
        "plate",
        "door",
        "glass",
        "auto"
    ],
    "wof:name":"Arcade Glass Works",
    "wof:placetype":"venue"
},
  "geometry": {"coordinates":[-78.422049,42.533301],"type":"Point"}
}