{
  "type": "Feature",
  "properties": {
    "addr:full":"497 Greeley Ave Staten Island NY 10306",
    "addr:housenumber":"497",
    "addr:postcode":"10306",
    "addr:street":"Greeley Ave",
    "iso:country":"US",
    "sg:address":"497 Greeley Ave",
    "sg:city":"Staten Island",
    "sg:classifiers":[
        {
            "category":"Personal",
            "subcategory":"Beauty Salon",
            "type":"Services"
        }
    ],
    "sg:phone":"+1   ",
    "sg:postcode":"10306",
    "sg:province":"NY",
    "sg:tags":[
        "shop"
    ],
    "wof:name":"Tess Color Hair Salon",
    "wof:placetype":"venue"
},
  "geometry": {"coordinates":[-74.097392,40.571893],"type":"Point"}
}