{
  "type": "Feature",
  "properties": {
    "iso:country":"US",
    "sg:address":"1045 Park Ave",
    "sg:city":"New York",
    "sg:classifiers":[
        {
            "category":"Food & Beverages",
            "subcategory":"Groceries & Convenience Stores",
            "type":"Retail Goods"
        }
    ],
    "sg:phone":"+1 212 828 4401",
    "sg:postcode":"10028",
    "sg:province":"NY",
    "sg:tags":[
        "market"
    ],
    "wof:name":"Communique The Mature Market",
    "wof:placetype":"venue"
},
  "geometry": {"coordinates":[-73.95673499999999,40.78065],"type":"Point"}
}