{
  "type": "Feature",
  "properties": {
    "iso:country":"US",
    "sg:address":"14 Barclay Rd",
    "sg:city":"Scarsdale",
    "sg:classifiers":[
        {
            "category":"Manufacturing",
            "subcategory":"Metals",
            "type":"Manufacturing & Wholesale Goods"
        }
    ],
    "sg:phone":"+1 914 722 6010",
    "sg:postcode":"10583",
    "sg:province":"NY",
    "sg:tags":[
        "valve"
    ],
    "wof:name":"Morse Fluid Technologies",
    "wof:placetype":"venue"
},
  "geometry": {"coordinates":[-73.809163,40.995064],"type":"Point"}
}