{
  "type": "Feature",
  "properties": {
    "addr:full":"208 W Miller St Elmira NY 14904",
    "addr:housenumber":"208",
    "addr:postcode":"14904",
    "addr:street":"W Miller St",
    "iso:country":"US",
    "sg:address":"208 W Miller St",
    "sg:city":"Elmira",
    "sg:classifiers":[
        {
            "category":"Bars & Pubs",
            "type":"Food & Drink"
        }
    ],
    "sg:phone":"+1 607 732 9437",
    "sg:postcode":"14904",
    "sg:province":"NY",
    "sg:tags":[
        "tavern"
    ],
    "wof:name":"Keefe Tavern Inc",
    "wof:placetype":"venue"
},
  "geometry": {"coordinates":[-76.802583,42.073847],"type":"Point"}
}