{
  "type": "Feature",
  "properties": {
    "addr:full":"28 Greentree Dr Scarsdale NY 10583",
    "addr:housenumber":"28",
    "addr:postcode":"10583",
    "addr:street":"Greentree Dr",
    "iso:country":"US",
    "sg:address":"28 Greentree Dr",
    "sg:city":"Scarsdale",
    "sg:classifiers":[
        {
            "category":"Real Estate",
            "subcategory":"Real Estate Services",
            "type":"Services"
        },
        {
            "category":"Real Estate",
            "subcategory":"Real Estate Agent",
            "type":"Services"
        }
    ],
    "sg:phone":"+1 914 723 5119",
    "sg:postcode":"10583",
    "sg:province":"NY",
    "sg:tags":[
        "buyer",
        "broker"
    ],
    "wof:name":"N & L Realty Llc Co Frank V Ritacco And",
    "wof:placetype":"venue"
},
  "geometry": {"coordinates":[-73.77722199999999,40.976479],"type":"Point"}
}