{
  "type": "Feature",
  "properties": {
    "addr:full":"3916 Dyre Ave Bronx NY 10466",
    "addr:housenumber":"3916",
    "addr:postcode":"10466",
    "addr:street":"Dyre Ave",
    "iso:country":"US",
    "sg:address":"3916 Dyre Ave",
    "sg:city":"Bronx",
    "sg:classifiers":[
        {
            "category":"Building & Trades",
            "subcategory":"Construction",
            "type":"Services"
        }
    ],
    "sg:phone":"+1 718 994 3752",
    "sg:postcode":"10466",
    "sg:province":"NY",
    "sg:tags":[
        "equipment",
        "installation"
    ],
    "wof:name":"Michael Domenici Elec Contg",
    "wof:placetype":"venue"
},
  "geometry": {"coordinates":[-73.831091,40.89028],"type":"Point"}
}