{
  "type": "Feature",
  "properties": {
    "iso:country":"US",
    "sg:address":"12 Scott Ct",
    "sg:city":"East Setauket",
    "sg:classifiers":[
        {
            "category":"Manufacturing",
            "subcategory":"Signs",
            "type":"Manufacturing & Wholesale Goods"
        }
    ],
    "sg:phone":"+1   ",
    "sg:postcode":"11733",
    "sg:province":"NY",
    "sg:tags":[
        "advertising",
        "specialty"
    ],
    "wof:name":"Miller Mohr Display Inc",
    "wof:placetype":"venue"
},
  "geometry": {"coordinates":[-73.09512599999999,40.939972],"type":"Point"}
}