{
  "type": "Feature",
  "properties": {
    "addr:full":"1 Main St W Rochester NY 14614",
    "addr:housenumber":"1",
    "addr:postcode":"14614",
    "addr:street":"Main St W",
    "iso:country":"US",
    "sg:address":"1 Main St W",
    "sg:city":"Rochester",
    "sg:classifiers":[
        {
            "category":"Real Estate",
            "subcategory":"Real Estate Operator",
            "type":"Services"
        }
    ],
    "sg:phone":"+1 585 454 2702",
    "sg:postcode":"14614",
    "sg:province":"NY",
    "sg:tags":[
        "building",
        "parks"
    ],
    "wof:name":"Four Corners Building",
    "wof:placetype":"venue"
},
  "geometry": {"coordinates":[-77.61325600000001,43.155538],"type":"Point"}
}