{
  "type": "Feature",
  "properties": {
    "addr:full":"150 Park Ave Amityville NY 11701",
    "addr:housenumber":"150",
    "addr:postcode":"11701",
    "addr:street":"Park Ave",
    "iso:country":"US",
    "sg:address":"150 Park Ave",
    "sg:city":"Amityville",
    "sg:classifiers":[
        {
            "category":"Education",
            "subcategory":"School",
            "type":"Public Place"
        }
    ],
    "sg:phone":"+1 631 598 6500",
    "sg:postcode":"11701",
    "sg:province":"NY",
    "wof:name":"Amityville Public Schools",
    "wof:placetype":"venue"
},
  "geometry": {"coordinates":[-73.418289,40.675509],"type":"Point"}
}