{
  "type": "Feature",
  "properties": {
    "addr:full":"527 Grand Street New York NY 10002",
    "addr:housenumber":"527",
    "addr:postcode":"10002",
    "addr:street":"Grand Street",
    "iso:country":"US",
    "sg:address":"527 Grand Street",
    "sg:city":"New York",
    "sg:classifiers":[
        {
            "category":"Shopping",
            "subcategory":"Pharmacy",
            "type":"Retail Goods"
        }
    ],
    "sg:phone":"+1 212 388 0888",
    "sg:postcode":"10002",
    "sg:province":"NY",
    "sg:tags":[
        "drugstore"
    ],
    "wof:name":"People Choice Pharmacy",
    "wof:placetype":"venue"
},
  "geometry": {"coordinates":[-73.98170500000001,40.714595],"type":"Point"}
}