{
  "type": "Feature",
  "properties": {
    "addr:full":"165 Forest Ave Locust Valley NY 11560",
    "addr:housenumber":"165",
    "addr:postcode":"11560",
    "addr:street":"Forest Ave",
    "iso:country":"US",
    "sg:address":"165 Forest Ave",
    "sg:city":"Locust Valley",
    "sg:classifiers":[
        {
            "category":"Building & Trades",
            "subcategory":"Construction",
            "type":"Services"
        }
    ],
    "sg:phone":"+1 516 676 1199",
    "sg:postcode":"11560",
    "sg:province":"NY",
    "sg:tags":[
        "sewer",
        "contractor"
    ],
    "wof:name":"E Z Sewer & Drain",
    "wof:placetype":"venue"
},
  "geometry": {"coordinates":[-73.60154300000001,40.875446],"type":"Point"}
}