{
  "type": "Feature",
  "properties": {
    "iso:country":"US",
    "sg:address":"179 E 115th St",
    "sg:city":"New York",
    "sg:classifiers":[
        {
            "category":"Restaurant",
            "type":"Food & Drink"
        }
    ],
    "sg:phone":"+1 212 360 5775",
    "sg:postcode":"10029",
    "sg:province":"NY",
    "wof:name":"Citi Pizza",
    "wof:placetype":"venue"
},
  "geometry": {"coordinates":[-73.94118899999999,40.797725],"type":"Point"}
}