{
  "type": "Feature",
  "properties": {
    "addr:full":"137 Margaret St Plattsburgh NY 12901",
    "addr:housenumber":"137",
    "addr:postcode":"12901",
    "addr:street":"Margaret St",
    "iso:country":"US",
    "sg:address":"137 Margaret St",
    "sg:city":"Plattsburgh",
    "sg:classifiers":[
        {
            "category":"Real Estate",
            "subcategory":"Real Estate Agent",
            "type":"Services"
        }
    ],
    "sg:phone":"+1 518 565 4444",
    "sg:postcode":"12901",
    "sg:province":"NY",
    "sg:tags":[
        "executive"
    ],
    "wof:name":"Real Property Star Exemption",
    "wof:placetype":"venue"
},
  "geometry": {"coordinates":[-73.453137,44.699178],"type":"Point"}
}