{
  "type": "Feature",
  "properties": {
    "addr:full":"54 Seacrest Ave Staten Island NY 10312",
    "addr:housenumber":"54",
    "addr:postcode":"10312",
    "addr:street":"Seacrest Ave",
    "iso:country":"US",
    "sg:address":"54 Seacrest Ave",
    "sg:city":"Staten Island",
    "sg:classifiers":[
        {
            "category":"Freight",
            "type":"Transportation"
        }
    ],
    "sg:phone":"+1 718 967 4839",
    "sg:postcode":"10312",
    "sg:province":"NY",
    "sg:tags":[
        "trucking"
    ],
    "wof:name":"PDQ Inc",
    "wof:placetype":"venue"
},
  "geometry": {"coordinates":[-74.15229600000001,40.534648],"type":"Point"}
}