{
  "type": "Feature",
  "properties": {
    "addr:full":"1458 Webster Avenue Bronx NY 10456",
    "addr:housenumber":"1458",
    "addr:postcode":"10456",
    "addr:street":"Webster Avenue",
    "iso:country":"US",
    "sg:address":"1458 Webster Avenue",
    "sg:city":"Bronx",
    "sg:classifiers":[
        {
            "category":"Education",
            "subcategory":"School",
            "type":"Public Place"
        }
    ],
    "sg:phone":"+1 718 538 3920",
    "sg:postcode":"10456",
    "sg:province":"NY",
    "wof:name":"South Bronx Headstart Program",
    "wof:placetype":"venue"
},
  "geometry": {"coordinates":[-73.906424,40.837514],"type":"Point"}
}