{
  "type": "Feature",
  "properties": {
    "iso:country":"US",
    "sg:address":"2120 Eagle Harbor Waterport Rd",
    "sg:city":"Albion",
    "sg:classifiers":[
        {
            "category":"Food & Beverages",
            "subcategory":"Fruits & Vegetables",
            "type":"Retail Goods"
        }
    ],
    "sg:phone":"+1 585 682 4470",
    "sg:postcode":"14411",
    "sg:province":"NY",
    "sg:tags":[
        "produce"
    ],
    "wof:name":"Rush's Vegetables",
    "wof:placetype":"venue"
},
  "geometry": {"coordinates":[-78.25129699999999,43.311977],"type":"Point"}
}