{
  "type": "Feature",
  "properties": {
    "addr:full":"360 Columbia Tpke Rensselaer NY 12144",
    "addr:housenumber":"360",
    "addr:postcode":"12144",
    "addr:street":"Columbia Tpke",
    "iso:country":"US",
    "sg:address":"360 Columbia Tpke",
    "sg:city":"Rensselaer",
    "sg:classifiers":[
        {
            "category":"Manufacturing",
            "subcategory":"Printing",
            "type":"Manufacturing & Wholesale Goods"
        }
    ],
    "sg:phone":"+1 518 479 3667",
    "sg:postcode":"12144",
    "sg:province":"NY",
    "sg:tags":[
        "printer"
    ],
    "wof:name":"Suburban Printers Inc",
    "wof:placetype":"venue"
},
  "geometry": {"coordinates":[-73.72371699999999,42.607796],"type":"Point"}
}