{
  "type": "Feature",
  "properties": {
    "addr:full":"91 Broadway Greenlawn NY 11740",
    "addr:housenumber":"91",
    "addr:postcode":"11740",
    "addr:street":"Broadway",
    "iso:country":"US",
    "sg:address":"91 Broadway",
    "sg:city":"Greenlawn",
    "sg:classifiers":[
        {
            "category":"Professional",
            "subcategory":"Employment Agencies",
            "type":"Services"
        }
    ],
    "sg:phone":"+1 631 368 2670",
    "sg:postcode":"11740",
    "sg:province":"NY",
    "sg:website":"www.lmbprofessional.com",
    "wof:name":"L M B Professional Services Inc",
    "wof:placetype":"venue"
},
  "geometry": {"coordinates":[-73.364531,40.866692],"type":"Point"}
}