{
  "type": "Feature",
  "properties": {
    "iso:country":"US",
    "sg:address":"825 Winona Blvd",
    "sg:city":"Rochester",
    "sg:classifiers":[
        {
            "category":"Real Estate",
            "subcategory":"Developer",
            "type":"Services"
        }
    ],
    "sg:phone":"+1 585 266 8520",
    "sg:postcode":"14617",
    "sg:province":"NY",
    "wof:name":"J Battle Development",
    "wof:placetype":"venue"
},
  "geometry": {"coordinates":[-77.607411,43.219542],"type":"Point"}
}