{
  "type": "Feature",
  "properties": {
    "iso:country":"US",
    "sg:address":"2 Farmstead Ln",
    "sg:city":"Water Mill",
    "sg:classifiers":[
        {
            "category":"Communications",
            "subcategory":"Film & Video Production",
            "type":"Services"
        }
    ],
    "sg:phone":"+1   ",
    "sg:postcode":"11976",
    "sg:province":"NY",
    "sg:tags":[
        "motion"
    ],
    "wof:name":"Imperatrice Productions Inc",
    "wof:placetype":"venue"
},
  "geometry": {"coordinates":[-72.357647,40.938862],"type":"Point"}
}