{
  "type": "Feature",
  "properties": {
    "iso:country":"US",
    "sg:address":"127 Wolf Rd Colonie",
    "sg:city":"Albany",
    "sg:phone":"+1 518 458 7700",
    "sg:postcode":"12205",
    "sg:province":"NY",
    "sg:website":"http://www.goodyeartires.com/",
    "wof:name":"De Nooyer Chevrolet",
    "wof:placetype":"venue"
},
  "geometry": {"coordinates":[-73.80774700000001,42.717781],"type":"Point"}
}