{
  "type": "Feature",
  "properties": {
    "iso:country":"US",
    "sg:address":"560 5th Ave",
    "sg:city":"Brooklyn",
    "sg:classifiers":[
        {
            "category":"Bars & Pubs",
            "type":"Food & Drink"
        },
        {
            "category":"Restaurant",
            "type":"Food & Drink"
        }
    ],
    "sg:phone":"+1 718 369 0077",
    "sg:postcode":"11215",
    "sg:province":"NY",
    "sg:tags":[
        "new",
        "american"
    ],
    "sg:website":"www.sidecarbrooklyn.com",
    "wof:name":"Sidecar Bar & Grill",
    "wof:placetype":"venue"
},
  "geometry": {"coordinates":[-73.989557,40.665264],"type":"Point"}
}