{
  "type": "Feature",
  "properties": {
    "addr:full":"625 Atlantic Ave Brooklyn NY 11217",
    "addr:housenumber":"625",
    "addr:postcode":"11217",
    "addr:street":"Atlantic Ave",
    "iso:country":"US",
    "sg:address":"625 Atlantic Ave",
    "sg:city":"Brooklyn",
    "sg:classifiers":[
        {
            "category":"Food & Beverages",
            "subcategory":"Groceries & Convenience Stores",
            "type":"Retail Goods"
        }
    ],
    "sg:phone":"+1 718 399 6161",
    "sg:postcode":"11217",
    "sg:province":"NY",
    "sg:website":"www.pathmark.com",
    "wof:name":"Pathmark Supermarket",
    "wof:placetype":"venue"
},
  "geometry": {"coordinates":[-73.975022,40.683693],"type":"Point"}
}