{
  "type": "Feature",
  "properties": {
    "iso:country":"US",
    "sg:address":"197 Manhattan Ave",
    "sg:city":"Hawthorne",
    "sg:classifiers":[
        {
            "category":"Travel",
            "subcategory":"Travel Agent",
            "type":"Entertainment"
        }
    ],
    "sg:phone":"+1   ",
    "sg:postcode":"10532",
    "sg:province":"NY",
    "sg:tags":[
        "agency"
    ],
    "wof:name":"Mathew Sunny Travel",
    "wof:placetype":"venue"
},
  "geometry": {"coordinates":[-73.789511,41.10173],"type":"Point"}
}