{
  "type": "Feature",
  "properties": {
    "addr:full":"135 Clinton St Hempstead NY 11550",
    "addr:housenumber":"135",
    "addr:postcode":"11550",
    "addr:street":"Clinton St",
    "iso:country":"US",
    "sg:address":"135 Clinton St",
    "sg:city":"Hempstead",
    "sg:classifiers":[
        {
            "category":"Professional",
            "subcategory":"Advertising",
            "type":"Services"
        }
    ],
    "sg:phone":"+1 516 292 3355",
    "sg:postcode":"11550",
    "sg:province":"NY",
    "sg:tags":[
        "counselor"
    ],
    "wof:name":"Capital Publications Co",
    "wof:placetype":"venue"
},
  "geometry": {"coordinates":[-73.619855,40.709804],"type":"Point"}
}