{
  "type": "Feature",
  "properties": {
    "addr:full":"10 McClellan Cir Buffalo NY 14220",
    "addr:housenumber":"10",
    "addr:postcode":"14220",
    "addr:street":"Mcclellan Cir",
    "iso:country":"US",
    "sg:address":"10 McClellan Cir",
    "sg:city":"Buffalo",
    "sg:classifiers":[
        {
            "category":"Health Services",
            "subcategory":"Health Practitioner",
            "type":"Services"
        }
    ],
    "sg:phone":"+1   ",
    "sg:postcode":"14220",
    "sg:province":"NY",
    "wof:name":"Mount Mercy Speech Center",
    "wof:placetype":"venue"
},
  "geometry": {"coordinates":[-78.81504200000001,42.844213],"type":"Point"}
}