{
  "type": "Feature",
  "properties": {
    "addr:full":"320 Baychester Avenue Bronx NY 10475",
    "addr:housenumber":"320",
    "addr:postcode":"10475",
    "addr:street":"Baychester Avenue",
    "iso:country":"US",
    "sg:address":"320 Baychester Avenue",
    "sg:city":"Bronx",
    "sg:classifiers":[
        {
            "category":"Shopping",
            "subcategory":"Clothing, Apparel, & Fashions",
            "type":"Retail Goods"
        }
    ],
    "sg:phone":"+1 718 862 9644",
    "sg:postcode":"10475",
    "sg:province":"NY",
    "sg:tags":[
        "costume"
    ],
    "wof:name":"Party City of the Bronx",
    "wof:placetype":"venue"
},
  "geometry": {"coordinates":[-73.831067,40.867793],"type":"Point"}
}