{
  "type": "Feature",
  "properties": {
    "addr:full":"15 Cat Hollow Rd Bayville NY 11709",
    "addr:housenumber":"15",
    "addr:postcode":"11709",
    "addr:street":"Cat Hollow Rd",
    "iso:country":"US",
    "sg:address":"15 Cat Hollow Rd",
    "sg:city":"Bayville",
    "sg:classifiers":[
        {
            "category":"Railroad",
            "type":"Transportation"
        }
    ],
    "sg:phone":"+1   ",
    "sg:postcode":"11709",
    "sg:province":"NY",
    "sg:tags":[
        "operator",
        "line"
    ],
    "wof:name":"Athletic Entrprises Lt",
    "wof:placetype":"venue"
},
  "geometry": {"coordinates":[-73.566473,40.904044],"type":"Point"}
}