{
  "type": "Feature",
  "properties": {
    "iso:country":"US",
    "sg:address":"5001 State Hwy 417",
    "sg:city":"Allegany",
    "sg:classifiers":[
        {
            "category":"Shopping",
            "subcategory":"Tobacco",
            "type":"Retail Goods"
        }
    ],
    "sg:phone":"+1 716 372 4066",
    "sg:postcode":"14706",
    "sg:province":"NY",
    "sg:tags":[
        "cigarette",
        "cigar",
        "dealer"
    ],
    "wof:name":"Ron's Smoke Shop",
    "wof:placetype":"venue"
},
  "geometry": {"coordinates":[-78.577866,42.096213],"type":"Point"}
}