{
  "type": "Feature",
  "properties": {
    "addr:full":"934 E 22nd St Brooklyn NY 11210",
    "addr:housenumber":"934",
    "addr:postcode":"11210",
    "addr:street":"E 22Nd St",
    "iso:country":"US",
    "sg:address":"934 E 22nd St",
    "sg:city":"Brooklyn",
    "sg:classifiers":[
        {
            "category":"Professional",
            "subcategory":"Employment Agencies",
            "type":"Services"
        }
    ],
    "sg:phone":"+1 718 258 0195",
    "sg:postcode":"11210",
    "sg:province":"NY",
    "wof:name":"Local 906 Employer Finder Inc",
    "wof:placetype":"venue"
},
  "geometry": {"coordinates":[-73.954993,40.62856],"type":"Point"}
}