{
  "type": "Feature",
  "properties": {
    "addr:full":"1393 York Ave New York NY 10021",
    "addr:housenumber":"1393",
    "addr:postcode":"10021",
    "addr:street":"York Ave",
    "iso:country":"US",
    "sg:address":"1393 York Ave",
    "sg:city":"New York",
    "sg:classifiers":[
        {
            "category":"Organizations",
            "subcategory":"Religious Organization",
            "type":"Services"
        }
    ],
    "sg:phone":"+1 212 737 2720",
    "sg:postcode":"10021",
    "sg:province":"NY",
    "sg:tags":[
        "church"
    ],
    "sg:website":"www.epiphanynyc.org/",
    "wof:name":"Church of the Epiphany",
    "wof:placetype":"venue"
},
  "geometry": {"coordinates":[-73.952996,40.768506],"type":"Point"}
}