{
  "type": "Feature",
  "properties": {
    "iso:country":"US",
    "sg:address":"982 Townline Rd",
    "sg:city":"Penn Yan",
    "sg:classifiers":[
        {
            "category":"Retail",
            "subcategory":"Auto Repair",
            "type":"Services"
        }
    ],
    "sg:phone":"+1 315 536 6325",
    "sg:postcode":"14527",
    "sg:province":"NY",
    "sg:tags":[
        "repairing",
        "automobile"
    ],
    "wof:name":"Kevin Anderson's Garage",
    "wof:placetype":"venue"
},
  "geometry": {"coordinates":[-77.016014,42.714686],"type":"Point"}
}