{
  "type": "Feature",
  "properties": {
    "addr:full":"210 Pinehurst Ave New York NY 10033",
    "addr:housenumber":"210",
    "addr:postcode":"10033",
    "addr:street":"Pinehurst Ave",
    "iso:country":"US",
    "sg:address":"210 Pinehurst Ave",
    "sg:city":"New York",
    "sg:classifiers":[
        {
            "category":"Professional",
            "type":"Services"
        }
    ],
    "sg:phone":"+1 212 740 3579",
    "sg:postcode":"10033",
    "sg:province":"NY",
    "wof:name":"F Vargas Svc",
    "wof:placetype":"venue"
},
  "geometry": {"coordinates":[-73.93819499999999,40.854011],"type":"Point"}
}