{
  "type": "Feature",
  "properties": {
    "addr:full":"9 Morris Ln Clifton Park NY 12065",
    "addr:housenumber":"9",
    "addr:postcode":"12065",
    "addr:street":"Morris Ln",
    "iso:country":"US",
    "sg:address":"9 Morris Ln",
    "sg:city":"Clifton Park",
    "sg:classifiers":[
        {
            "category":"Personal",
            "subcategory":"Beauty Salon",
            "type":"Services"
        }
    ],
    "sg:phone":"+1 518 373 1465",
    "sg:postcode":"12065",
    "sg:province":"NY",
    "wof:name":"Hair 2000",
    "wof:placetype":"venue"
},
  "geometry": {"coordinates":[-73.759666,42.819842],"type":"Point"}
}