{
  "type": "Feature",
  "properties": {
    "addr:full":"4 Hampton Rd Oceanside NY 11572",
    "addr:housenumber":"4",
    "addr:postcode":"11572",
    "addr:street":"Hampton Rd",
    "iso:country":"US",
    "sg:address":"4 Hampton Rd",
    "sg:city":"Oceanside",
    "sg:classifiers":[
        {
            "category":"Retail",
            "subcategory":"Auto Rental",
            "type":"Services"
        }
    ],
    "sg:phone":"+1 516 594 1918",
    "sg:postcode":"11572",
    "sg:province":"NY",
    "sg:tags":[
        "renting",
        "truck",
        "leasing"
    ],
    "wof:name":"U-Haul Co",
    "wof:placetype":"venue"
},
  "geometry": {"coordinates":[-73.653915,40.626841],"type":"Point"}
}