{
  "type": "Feature",
  "properties": {
    "addr:full":"2265 Co Rd 28 Canandaigua NY 14424",
    "addr:housenumber":"2265;28",
    "addr:postcode":"14424",
    "addr:street":"Co Rd",
    "iso:country":"US",
    "sg:address":"2265 Co Rd 28",
    "sg:city":"Canandaigua",
    "sg:classifiers":[
        {
            "category":"Building & Trades",
            "subcategory":"Landscaping Services",
            "type":"Services"
        }
    ],
    "sg:phone":"+1 585 393 0408",
    "sg:postcode":"14424",
    "sg:province":"NY",
    "wof:name":"Oakridge Landscaping",
    "wof:placetype":"venue"
},
  "geometry": {"coordinates":[-77.28589700000001,42.920861],"type":"Point"}
}