{
  "type": "Feature",
  "properties": {
    "iso:country":"US",
    "sg:address":"1201 Broadway St",
    "sg:city":"Buffalo",
    "sg:classifiers":[
        {
            "category":"Real Estate",
            "subcategory":"Real Estate Operator",
            "type":"Services"
        }
    ],
    "sg:phone":"+1 716 893 0716",
    "sg:postcode":"14212",
    "sg:province":"NY",
    "sg:tags":[
        "building",
        "apartment"
    ],
    "wof:name":"Francis John Apartments",
    "wof:placetype":"venue"
},
  "geometry": {"coordinates":[-78.83000199999999,42.894699],"type":"Point"}
}