{
  "type": "Feature",
  "properties": {
    "addr:full":"1205 38th St Brooklyn NY 11218",
    "addr:housenumber":"1205",
    "addr:postcode":"11218",
    "addr:street":"38Th St",
    "iso:country":"US",
    "sg:address":"1205 38th St",
    "sg:city":"Brooklyn",
    "sg:classifiers":[
        {
            "category":"Shopping",
            "type":"Retail Goods"
        },
        {
            "category":"Professional",
            "subcategory":"Management & Consulting",
            "type":"Services"
        }
    ],
    "sg:phone":"+1 718 633 8383",
    "sg:postcode":"11218",
    "sg:province":"NY",
    "sg:tags":[
        "publisher",
        "educational",
        "marketing",
        "calculator",
        "material",
        "program"
    ],
    "wof:name":"D & S Marketing Systems Inc",
    "wof:placetype":"venue"
},
  "geometry": {"coordinates":[-73.98573,40.641298],"type":"Point"}
}