{
  "type": "Feature",
  "properties": {
    "addr:full":"39 Stringham Ave Valley Stream NY 11580",
    "addr:housenumber":"39",
    "addr:postcode":"11580",
    "addr:street":"Stringham Ave",
    "iso:country":"US",
    "sg:address":"39 Stringham Ave",
    "sg:city":"Valley Stream",
    "sg:classifiers":[
        {
            "category":"Shopping",
            "subcategory":"Stationery & Office Supplies",
            "type":"Retail Goods"
        }
    ],
    "sg:phone":"+1 516 823 9003",
    "sg:postcode":"11580",
    "sg:province":"NY",
    "sg:tags":[
        "equipment"
    ],
    "wof:name":"Diversifex Inc",
    "wof:placetype":"venue"
},
  "geometry": {"coordinates":[-73.707802,40.668201],"type":"Point"}
}