{
  "type": "Feature",
  "properties": {
    "addr:full":"114 Fulton St New York NY 10038",
    "addr:housenumber":"114",
    "addr:postcode":"10038",
    "addr:street":"Fulton St",
    "iso:country":"US",
    "sg:address":"114 Fulton St",
    "sg:city":"New York",
    "sg:classifiers":[
        {
            "category":"Building & Trades",
            "subcategory":"Construction",
            "type":"Services"
        }
    ],
    "sg:phone":"+1 212 608 0100",
    "sg:postcode":"10038",
    "sg:province":"NY",
    "sg:tags":[
        "general",
        "contractor"
    ],
    "wof:name":"Cross Construction",
    "wof:placetype":"venue"
},
  "geometry": {"coordinates":[-74.007699,40.7101],"type":"Point"}
}