{
  "type": "Feature",
  "properties": {
    "iso:country":"US",
    "sg:address":"3400 Boston Rd",
    "sg:city":"Bronx",
    "sg:classifiers":[
        {
            "category":"Professional",
            "subcategory":"Management & Consulting",
            "type":"Services"
        }
    ],
    "sg:phone":"+1 718 547 3803",
    "sg:postcode":"10469",
    "sg:province":"NY",
    "sg:tags":[
        "consultant",
        "automation"
    ],
    "wof:name":"Stanson Automated LLC",
    "wof:placetype":"venue"
},
  "geometry": {"coordinates":[-73.849884,40.875875],"type":"Point"}
}