{
  "type": "Feature",
  "properties": {
    "addr:full":"6 Tower Hts Albany NY 12211",
    "addr:housenumber":"6",
    "addr:postcode":"12211",
    "addr:street":"Tower Hts",
    "iso:country":"US",
    "sg:address":"6 Tower Hts",
    "sg:city":"Albany",
    "sg:classifiers":[
        {
            "category":"Home & Garden",
            "subcategory":"Carpets & Floor Coverings",
            "type":"Retail Goods"
        }
    ],
    "sg:phone":"+1 518 459 7732",
    "sg:postcode":"12211",
    "sg:province":"NY",
    "sg:tags":[
        "flooring",
        "contractor"
    ],
    "wof:name":"Fiaco Brothers Hardwood Flooring",
    "wof:placetype":"venue"
},
  "geometry": {"coordinates":[-73.776157,42.71307],"type":"Point"}
}