{
  "type": "Feature",
  "properties": {
    "addr:full":"1103 Oak St Syracuse NY 13203",
    "addr:housenumber":"1103",
    "addr:postcode":"13203",
    "addr:street":"Oak St",
    "iso:country":"US",
    "sg:address":"1103 Oak St",
    "sg:city":"Syracuse",
    "sg:classifiers":[
        {
            "category":"Manufacturing",
            "subcategory":"Tools & Machinery",
            "type":"Manufacturing & Wholesale Goods"
        }
    ],
    "sg:phone":"+1   ",
    "sg:postcode":"13203",
    "sg:province":"NY",
    "sg:tags":[
        "electrical",
        "mfg"
    ],
    "wof:name":"Cda Electromechanical Labs",
    "wof:placetype":"venue"
},
  "geometry": {"coordinates":[-76.136494,43.068418],"type":"Point"}
}