{
  "type": "Feature",
  "properties": {
    "iso:country":"US",
    "sg:address":"172 Marine St",
    "sg:city":"Farmingdale",
    "sg:classifiers":[
        {
            "category":"Home & Garden",
            "subcategory":"Building Materials",
            "type":"Retail Goods"
        }
    ],
    "sg:phone":"+1   ",
    "sg:postcode":"11735",
    "sg:province":"NY",
    "wof:name":"I G A Corp Inc",
    "wof:placetype":"venue"
},
  "geometry": {"coordinates":[-73.41562999999999,40.71488],"type":"Point"}
}