{
  "type": "Feature",
  "properties": {
    "addr:full":"423 St Marys Rd Parish NY 13131",
    "addr:housenumber":"423",
    "addr:postcode":"13131",
    "addr:street":"St Marys Rd",
    "iso:country":"US",
    "sg:address":"423 St Marys Rd",
    "sg:city":"Parish",
    "sg:classifiers":[
        {
            "category":"Professional",
            "subcategory":"Business Services",
            "type":"Services"
        }
    ],
    "sg:phone":"+1 315 625 4764",
    "sg:postcode":"13131",
    "sg:province":"NY",
    "sg:tags":[
        "organizing",
        "services-household"
    ],
    "wof:name":"Valleygate Management",
    "wof:placetype":"venue"
},
  "geometry": {"coordinates":[-76.03572800000001,43.444809],"type":"Point"}
}