{
  "type": "Feature",
  "properties": {
    "addr:full":"30 Mill Rd Greenfield Ctr NY 12833",
    "addr:housenumber":"30",
    "addr:postcode":"12833",
    "addr:street":"Mill Rd",
    "iso:country":"US",
    "sg:address":"30 Mill Rd",
    "sg:city":"Greenfield Ctr",
    "sg:classifiers":[
        {
            "category":"Wholesale",
            "subcategory":"Construction Materials",
            "type":"Manufacturing & Wholesale Goods"
        }
    ],
    "sg:phone":"+1 518 584 8232",
    "sg:postcode":"12833",
    "sg:province":"NY",
    "sg:tags":[
        "sand",
        "gravel"
    ],
    "wof:name":"William J Bokus Industries",
    "wof:placetype":"venue"
},
  "geometry": {"coordinates":[-73.838415,43.09417],"type":"Point"}
}