{
  "type": "Feature",
  "properties": {
    "iso:country":"US",
    "sg:address":"10 Shore Blvd",
    "sg:city":"Brooklyn",
    "sg:classifiers":[
        {
            "category":"Banks & Credit Unions",
            "subcategory":"Bank",
            "type":"Services"
        }
    ],
    "sg:phone":"+1 718 332 3003",
    "sg:postcode":"11235",
    "sg:province":"NY",
    "sg:tags":[
        "loan",
        "real estate"
    ],
    "wof:name":"Nationwide Financial Grp",
    "wof:placetype":"venue"
},
  "geometry": {"coordinates":[-73.95412,40.582598],"type":"Point"}
}