{
  "type": "Feature",
  "properties": {
    "addr:full":"90 Grassmere Park Rochester NY 14612",
    "addr:housenumber":"90",
    "addr:postcode":"14612",
    "addr:street":"Grassmere Park",
    "iso:country":"US",
    "sg:address":"90 Grassmere Park",
    "sg:city":"Rochester",
    "sg:classifiers":[
        {
            "category":"Retail",
            "subcategory":"Auto Repair",
            "type":"Services"
        }
    ],
    "sg:phone":"+1 585 266 6070",
    "sg:postcode":"14612",
    "sg:province":"NY",
    "sg:tags":[
        "body",
        "automobile",
        "painting"
    ],
    "wof:name":"Jamie's Showroom Collision",
    "wof:placetype":"venue"
},
  "geometry": {"coordinates":[-77.625101,43.237499],"type":"Point"}
}