{
  "type": "Feature",
  "properties": {
    "iso:country":"US",
    "sg:address":"80 Ross Hill Rd",
    "sg:city":"Conklin",
    "sg:classifiers":[
        {
            "category":"Freight",
            "type":"Transportation"
        }
    ],
    "sg:phone":"+1 405 210 6207",
    "sg:postcode":"13748",
    "sg:province":"NY",
    "sg:tags":[
        "driver",
        "leasing",
        "truck"
    ],
    "wof:name":"Bobby Ervin",
    "wof:placetype":"venue"
},
  "geometry": {"coordinates":[-75.849137,42.013272],"type":"Point"}
}