{
  "type": "Feature",
  "properties": {
    "addr:full":"1070 Madison Ave New York NY 10028",
    "addr:housenumber":"1070",
    "addr:postcode":"10028",
    "addr:street":"Madison Ave",
    "iso:country":"US",
    "sg:address":"1070 Madison Ave",
    "sg:city":"New York",
    "sg:classifiers":[
        {
            "category":"Shopping",
            "subcategory":"Jewelry",
            "type":"Retail Goods"
        }
    ],
    "sg:phone":"+1 212 744 3202",
    "sg:postcode":"10028",
    "sg:province":"NY",
    "sg:tags":[
        "jeweler"
    ],
    "sg:website":"www.jjmarco.com",
    "wof:name":"J J Marco",
    "wof:placetype":"venue"
},
  "geometry": {"coordinates":[-73.96162699999999,40.777003],"type":"Point"}
}