{
  "type": "Feature",
  "properties": {
    "addr:full":"6709 Main St Flushing NY 11367",
    "addr:housenumber":"6709",
    "addr:postcode":"11367",
    "addr:street":"Main St",
    "iso:country":"US",
    "sg:address":"6709 Main St",
    "sg:city":"Flushing",
    "sg:classifiers":[
        {
            "category":"Health Services",
            "subcategory":"Doctor",
            "type":"Services"
        },
        {
            "category":"Health Services",
            "subcategory":"Dentist",
            "type":"Services"
        }
    ],
    "sg:phone":"+1 718 275 7768",
    "sg:postcode":"11367",
    "sg:province":"NY",
    "wof:name":"Huntington Dental & Medical",
    "wof:placetype":"venue"
},
  "geometry": {"coordinates":[-73.825104,40.733799],"type":"Point"}
}