{
  "type": "Feature",
  "properties": {
    "addr:full":"240 Joslen Blvd Hudson NY 12534",
    "addr:housenumber":"240",
    "addr:postcode":"12534",
    "addr:street":"Joslen Blvd",
    "iso:country":"US",
    "sg:address":"240 Joslen Blvd",
    "sg:city":"Hudson",
    "sg:classifiers":[
        {
            "category":"Place Of Worship",
            "subcategory":"Synagogue",
            "type":"Public Place"
        },
        {
            "category":"Place Of Worship",
            "type":"Public Place"
        }
    ],
    "sg:phone":"+1 518 828 6848",
    "sg:postcode":"12534",
    "sg:province":"NY",
    "sg:tags":[
        "synagogues-reform",
        "church"
    ],
    "sg:website":"http://www.congregationansheemeth.org",
    "wof:name":"Congregation Anshe Emeth",
    "wof:placetype":"venue"
},
  "geometry": {"coordinates":[-73.77046199999999,42.264751],"type":"Point"}
}