{
  "type": "Feature",
  "properties": {
    "iso:country":"US",
    "sg:address":"1418 Neptune Ave",
    "sg:city":"Brooklyn",
    "sg:classifiers":[
        {
            "category":"Professional",
            "subcategory":"Management & Consulting",
            "type":"Services"
        }
    ],
    "sg:phone":"+1 718 946 9103",
    "sg:postcode":"11224",
    "sg:province":"NY",
    "sg:tags":[
        "consultant"
    ],
    "wof:name":"Sym Consulting Intl Corp",
    "wof:placetype":"venue"
},
  "geometry": {"coordinates":[-73.982923,40.579094],"type":"Point"}
}