{
  "type": "Feature",
  "properties": {
    "addr:full":"3836 Flatlands Avenue Brooklyn NY 11234",
    "addr:housenumber":"3836",
    "addr:postcode":"11234",
    "addr:street":"Flatlands Avenue",
    "iso:country":"US",
    "sg:address":"3836 Flatlands Avenue",
    "sg:city":"Brooklyn",
    "sg:classifiers":[
        {
            "category":"Food & Beverages",
            "subcategory":"Groceries & Convenience Stores",
            "type":"Retail Goods"
        }
    ],
    "sg:phone":"+1 718 338 9112",
    "sg:postcode":"11234",
    "sg:province":"NY",
    "wof:name":"Mike & Ralph Mascolo",
    "wof:placetype":"venue"
},
  "geometry": {"coordinates":[-73.93787500000001,40.619457],"type":"Point"}
}