{
  "type": "Feature",
  "properties": {
    "addr:full":"6610 Ralph Ct Niagara Falls NY 14304",
    "addr:housenumber":"6610",
    "addr:postcode":"14304",
    "addr:street":"Ralph Ct",
    "iso:country":"US",
    "sg:address":"6610 Ralph Ct",
    "sg:city":"Niagara Falls",
    "sg:classifiers":[
        {
            "category":"Home & Garden",
            "subcategory":"Building Materials",
            "type":"Retail Goods"
        }
    ],
    "sg:phone":"+1 716 298 5817",
    "sg:postcode":"14304",
    "sg:province":"NY",
    "sg:tags":[
        "glass",
        "window",
        "plate"
    ],
    "sg:website":"www.sgwr.com",
    "wof:name":"Superglass Windshield Repair",
    "wof:placetype":"venue"
},
  "geometry": {"coordinates":[-78.98589699999999,43.114174],"type":"Point"}
}