{
  "type": "Feature",
  "properties": {
    "addr:full":"6 Park Ave Arkport NY 14807",
    "addr:housenumber":"6",
    "addr:postcode":"14807",
    "addr:street":"Park Ave",
    "iso:country":"US",
    "sg:address":"6 Park Ave",
    "sg:city":"Arkport",
    "sg:classifiers":[
        {
            "category":"Government",
            "subcategory":"Fire Station",
            "type":"Public Place"
        }
    ],
    "sg:phone":"+1 607 295 7750",
    "sg:postcode":"14807",
    "sg:province":"NY",
    "sg:tags":[
        "department"
    ],
    "wof:name":"Arkport Fire Dept",
    "wof:placetype":"venue"
},
  "geometry": {"coordinates":[-77.695258,42.39294],"type":"Point"}
}