{
  "type": "Feature",
  "properties": {
    "addr:full":"205 W End Ave #1L New York NY 10023",
    "addr:housenumber":"205;1l",
    "addr:postcode":"10023",
    "addr:street":"W End Ave #",
    "iso:country":"US",
    "sg:address":"205 W End Ave #1L",
    "sg:city":"New York",
    "sg:classifiers":[
        {
            "category":"Health Services",
            "subcategory":"Health Practitioner",
            "type":"Services"
        }
    ],
    "sg:phone":"+1 212 224 0087",
    "sg:postcode":"10023",
    "sg:province":"NY",
    "sg:tags":[
        "acupuncture"
    ],
    "sg:website":"www.nycpoints.com",
    "wof:name":"NYC Points Acupuncture PC",
    "wof:placetype":"venue"
},
  "geometry": {"coordinates":[-73.986397,40.77864],"type":"Point"}
}