{
  "type": "Feature",
  "properties": {
    "iso:country":"US",
    "sg:address":"53 School St",
    "sg:city":"Richville",
    "sg:classifiers":[
        {
            "category":"Health Services",
            "subcategory":"Hospital",
            "type":"Services"
        },
        {
            "category":"Health Services",
            "subcategory":"Clinic",
            "type":"Services"
        }
    ],
    "sg:phone":"+1 315 287 4264",
    "sg:postcode":"13681",
    "sg:province":"NY",
    "sg:tags":[
        "information",
        "treatment",
        "alcoholism"
    ],
    "sg:website":"http://cphospital.org",
    "wof:name":"Canton Potsdam Hospital-Rehab",
    "wof:placetype":"venue"
},
  "geometry": {"coordinates":[-75.39560899999999,44.417332],"type":"Point"}
}