{
  "type": "Feature",
  "properties": {
    "addr:full":"111 Wadsworth Ave New York NY 10033",
    "addr:housenumber":"111",
    "addr:postcode":"10033",
    "addr:street":"Wadsworth Ave",
    "iso:country":"US",
    "sg:address":"111 Wadsworth Ave",
    "sg:city":"New York",
    "sg:classifiers":[
        {
            "category":"Building & Trades",
            "subcategory":"Construction",
            "type":"Services"
        }
    ],
    "sg:phone":"+1 845 313 3384",
    "sg:postcode":"10033",
    "sg:province":"NY",
    "sg:tags":[
        "residential"
    ],
    "wof:name":"Marble Arch Properties",
    "wof:placetype":"venue"
},
  "geometry": {"coordinates":[-73.936403,40.847871],"type":"Point"}
}