{
  "type": "Feature",
  "properties": {
    "addr:full":"1099 Jay St Rochester NY 14611",
    "addr:housenumber":"1099",
    "addr:postcode":"14611",
    "addr:street":"Jay St",
    "iso:country":"US",
    "sg:address":"1099 Jay St",
    "sg:city":"Rochester",
    "sg:classifiers":[
        {
            "category":"Professional",
            "subcategory":"Management & Consulting",
            "type":"Services"
        }
    ],
    "sg:phone":"+1 585 235 0440",
    "sg:postcode":"14611",
    "sg:province":"NY",
    "sg:tags":[
        "fire",
        "consultant",
        "protection"
    ],
    "sg:website":"www.phillipsllc.com",
    "wof:name":"Phillips & Assoc",
    "wof:placetype":"venue"
},
  "geometry": {"coordinates":[-77.649253,43.159289],"type":"Point"}
}