{
  "type": "Feature",
  "properties": {
    "iso:country":"US",
    "sg:address":"7401 19th Ave",
    "sg:city":"Brooklyn",
    "sg:classifiers":[
        {
            "category":"Building & Trades",
            "subcategory":"Construction",
            "type":"Services"
        }
    ],
    "sg:phone":"+1 718 256 4627",
    "sg:postcode":"11204",
    "sg:province":"NY",
    "wof:name":"Lg Mola Corp",
    "wof:placetype":"venue"
},
  "geometry": {"coordinates":[-73.993968,40.612173],"type":"Point"}
}