{
  "type": "Feature",
  "properties": {
    "addr:full":"210 E 198th St Bronx NY 10458",
    "addr:housenumber":"210",
    "addr:postcode":"10458",
    "addr:street":"E 198Th St",
    "iso:country":"US",
    "sg:address":"210 E 198th St",
    "sg:city":"Bronx",
    "sg:classifiers":[
        {
            "category":"Personal",
            "subcategory":"Beauty Salon",
            "type":"Services"
        }
    ],
    "sg:phone":"+1 718 329 3442",
    "sg:postcode":"10458",
    "sg:province":"NY",
    "sg:tags":[
        "manicuring"
    ],
    "wof:name":"New Rose Nail",
    "wof:placetype":"venue"
},
  "geometry": {"coordinates":[-73.890231,40.86969],"type":"Point"}
}