{
  "type": "Feature",
  "properties": {
    "addr:full":"2377 Harlem Rd Buffalo NY 14225",
    "addr:housenumber":"2377",
    "addr:postcode":"14225",
    "addr:street":"Harlem Rd",
    "iso:country":"US",
    "sg:address":"2377 Harlem Rd",
    "sg:city":"Buffalo",
    "sg:classifiers":[
        {
            "category":"Food & Beverages",
            "subcategory":"Bakery",
            "type":"Retail Goods"
        }
    ],
    "sg:phone":"+1 716 891 5182",
    "sg:postcode":"14225",
    "sg:province":"NY",
    "sg:tags":[
        "baker"
    ],
    "wof:name":"Wonder Hostess Thrift Store",
    "wof:placetype":"venue"
},
  "geometry": {"coordinates":[-78.78449999999999,42.9086],"type":"Point"}
}