{
  "type": "Feature",
  "properties": {
    "addr:full":"2470 Charles Ct North Bellmore NY 11710",
    "addr:housenumber":"2470",
    "addr:postcode":"11710",
    "addr:street":"Charles Ct North",
    "iso:country":"US",
    "sg:address":"2470 Charles Ct",
    "sg:city":"North Bellmore",
    "sg:classifiers":[
        {
            "category":"Autos & Motor Vehicles",
            "subcategory":"Automobile Sales",
            "type":"Retail Goods"
        }
    ],
    "sg:phone":"+1 718 417 5555",
    "sg:postcode":"11710",
    "sg:province":"NY",
    "sg:tags":[
        "limo"
    ],
    "wof:name":"CRA Limousine Svce",
    "wof:placetype":"venue"
},
  "geometry": {"coordinates":[-73.540389,40.688195],"type":"Point"}
}