{
  "type": "Feature",
  "properties": {
    "iso:country":"US",
    "sg:address":"73 Bridge St",
    "sg:city":"Newburgh",
    "sg:classifiers":[
        {
            "category":"Shopping",
            "subcategory":"News",
            "type":"Retail Goods"
        }
    ],
    "sg:phone":"+1 845 562 9040",
    "sg:postcode":"12550",
    "sg:province":"NY",
    "sg:tags":[
        "dealer"
    ],
    "wof:name":"Hudson News Co",
    "wof:placetype":"venue"
},
  "geometry": {"coordinates":[-74.020357,41.4923],"type":"Point"}
}