{
  "type": "Feature",
  "properties": {
    "addr:full":"5537 Broadway Bronx NY 10463",
    "addr:housenumber":"5537",
    "addr:postcode":"10463",
    "addr:street":"Broadway",
    "iso:country":"US",
    "sg:address":"5537 Broadway",
    "sg:city":"Bronx",
    "sg:classifiers":[
        {
            "category":"Shopping",
            "subcategory":"Shoes",
            "type":"Retail Goods"
        }
    ],
    "sg:phone":"+1   ",
    "sg:postcode":"10463",
    "sg:province":"NY",
    "wof:name":"Mister Footwear",
    "wof:placetype":"venue"
},
  "geometry": {"coordinates":[-73.90532399999999,40.878273],"type":"Point"}
}