{
  "type": "Feature",
  "properties": {
    "addr:full":"1359 51st St Brooklyn NY 11219",
    "addr:housenumber":"1359",
    "addr:postcode":"11219",
    "addr:street":"51St St",
    "iso:country":"US",
    "sg:address":"1359 51st St",
    "sg:city":"Brooklyn",
    "sg:classifiers":[
        {
            "category":"Organizations",
            "subcategory":"Religious Organization",
            "type":"Services"
        }
    ],
    "sg:phone":"+1 718 438 2395",
    "sg:postcode":"11219",
    "sg:province":"NY",
    "sg:tags":[
        "clergy"
    ],
    "wof:name":"Devorah Mandel",
    "wof:placetype":"venue"
},
  "geometry": {"coordinates":[-73.992024,40.63342],"type":"Point"}
}