{
  "type": "Feature",
  "properties": {
    "iso:country":"US",
    "sg:address":"431 Lamoreaux Pl",
    "sg:city":"Elmira Heights",
    "sg:classifiers":[
        {
            "category":"Building & Trades",
            "subcategory":"Plumbing",
            "type":"Services"
        }
    ],
    "sg:phone":"+1 607 733 8700",
    "sg:postcode":"14903",
    "sg:province":"NY",
    "sg:tags":[
        "plumbing",
        "contractor"
    ],
    "wof:name":"Fix-It Man Plumbing & Heating",
    "wof:placetype":"venue"
},
  "geometry": {"coordinates":[-76.81019499999999,42.125673],"type":"Point"}
}