{
  "type": "Feature",
  "properties": {
    "addr:full":"2147 White Plains Rd Bronx NY 10462",
    "addr:housenumber":"2147",
    "addr:postcode":"10462",
    "addr:street":"White Plains Rd",
    "iso:country":"US",
    "sg:address":"2147 White Plains Rd",
    "sg:city":"Bronx",
    "sg:classifiers":[
        {
            "category":"Shopping",
            "subcategory":"Computers & Home Electronics",
            "type":"Retail Goods"
        }
    ],
    "sg:phone":"+1   ",
    "sg:postcode":"10462",
    "sg:province":"NY",
    "sg:tags":[
        "music",
        "store"
    ],
    "wof:name":"R & D Music Company Inc",
    "wof:placetype":"venue"
},
  "geometry": {"coordinates":[-73.867724,40.856405],"type":"Point"}
}