{
  "type": "Feature",
  "properties": {
    "iso:country":"US",
    "sg:address":"17 St. Mark's Pl",
    "sg:city":"New York",
    "sg:classifiers":[
        {
            "category":"Personal",
            "subcategory":"Tattoo Parlor",
            "type":"Services"
        },
        {
            "category":"Personal",
            "subcategory":"Piercing",
            "type":"Services"
        }
    ],
    "sg:phone":"+1 212 777 2430",
    "sg:postcode":"10003",
    "sg:province":"NY",
    "wof:name":"Whatever Tattoo",
    "wof:placetype":"venue"
},
  "geometry": {"coordinates":[-73.988826,40.729183],"type":"Point"}
}