{
  "type": "Feature",
  "properties": {
    "addr:full":"630 9th Ave Ste 203 New York NY 10036",
    "addr:housenumber":"630;203",
    "addr:postcode":"10036",
    "addr:street":"9Th Ave Ste",
    "iso:country":"US",
    "sg:address":"630 9th Ave Ste 203",
    "sg:city":"New York",
    "sg:classifiers":[
        {
            "category":"Professional",
            "subcategory":"Lawyer & Legal Services",
            "type":"Services"
        }
    ],
    "sg:phone":"+1 212 459 2707",
    "sg:postcode":"10036",
    "sg:province":"NY",
    "wof:name":"Lesser Michael C",
    "wof:placetype":"venue"
},
  "geometry": {"coordinates":[-73.991501,40.759998],"type":"Point"}
}