{
  "type": "Feature",
  "properties": {
    "addr:full":"2740 Martin Ave Bellmore NY 11710",
    "addr:housenumber":"2740",
    "addr:postcode":"11710",
    "addr:street":"Martin Ave",
    "iso:country":"US",
    "sg:address":"2740 Martin Ave",
    "sg:city":"Bellmore",
    "sg:classifiers":[
        {
            "category":"Government",
            "subcategory":"Office",
            "type":"Public Place"
        }
    ],
    "sg:phone":"+1 631 549 8700",
    "sg:postcode":"11710",
    "sg:province":"NY",
    "sg:tags":[
        "village"
    ],
    "wof:name":"Huntington Hotline",
    "wof:placetype":"venue"
},
  "geometry": {"coordinates":[-73.52652999999999,40.674961],"type":"Point"}
}