{
  "type": "Feature",
  "properties": {
    "addr:full":"1246 Pine Ave Niagara Falls NY 14301",
    "addr:housenumber":"1246",
    "addr:postcode":"14301",
    "addr:street":"Pine Ave",
    "iso:country":"US",
    "sg:address":"1246 Pine Ave",
    "sg:city":"Niagara Falls",
    "sg:classifiers":[
        {
            "category":"Personal",
            "subcategory":"Beauty Salon",
            "type":"Services"
        }
    ],
    "sg:phone":"+1 716 285 4308",
    "sg:postcode":"14301",
    "sg:province":"NY",
    "wof:name":"Darlene's Hair Styling",
    "wof:placetype":"venue"
},
  "geometry": {"coordinates":[-79.046601,43.094931],"type":"Point"}
}