{
  "type": "Feature",
  "properties": {
    "iso:country":"US",
    "sg:address":"666 E 180th St",
    "sg:city":"Bronx",
    "sg:classifiers":[
        {
            "category":"Organizations",
            "subcategory":"Religious Organization",
            "type":"Services"
        }
    ],
    "sg:phone":"+1 718 364 6211",
    "sg:postcode":"10457",
    "sg:province":"NY",
    "sg:tags":[
        "church"
    ],
    "wof:name":"Pentecostal Tabernacle Inc",
    "wof:placetype":"venue"
},
  "geometry": {"coordinates":[-73.888992,40.848145],"type":"Point"}
}