{
  "type": "Feature",
  "properties": {
    "addr:full":"353 Wantagh Ave Levittown NY 11756",
    "addr:housenumber":"353",
    "addr:postcode":"11756",
    "addr:street":"Wantagh Ave",
    "iso:country":"US",
    "sg:address":"353 Wantagh Ave",
    "sg:city":"Levittown",
    "sg:classifiers":[
        {
            "category":"Personal",
            "subcategory":"Beauty Salon",
            "type":"Services"
        }
    ],
    "sg:phone":"+1 516 731 7755",
    "sg:postcode":"11756",
    "sg:province":"NY",
    "wof:name":"Anthony & Co",
    "wof:placetype":"venue"
},
  "geometry": {"coordinates":[-73.501008,40.715308],"type":"Point"}
}