{
  "type": "Feature",
  "properties": {
    "addr:full":"198 E 100th St # 1 New York NY 10029",
    "addr:housenumber":"198",
    "addr:postcode":"10029",
    "addr:street":"E 100Th St # 1",
    "iso:country":"US",
    "sg:address":"198 E 100th St # 1",
    "sg:city":"New York",
    "sg:classifiers":[
        {
            "category":"Organizations",
            "subcategory":"Religious Organization",
            "type":"Services"
        }
    ],
    "sg:phone":"+1 212 876 7461",
    "sg:postcode":"10029",
    "sg:province":"NY",
    "wof:name":"Church of God of 100 Street",
    "wof:placetype":"venue"
},
  "geometry": {"coordinates":[-73.9487,40.788101],"type":"Point"}
}