{
  "type": "Feature",
  "properties": {
    "iso:country":"US",
    "sg:address":"8612 3rd Ave",
    "sg:city":"Brooklyn",
    "sg:classifiers":[
        {
            "category":"Bakery",
            "type":"Food & Drink"
        }
    ],
    "sg:menulink":"http://www.allmenus.com/ny/brooklyn/223976-cinnabon/menu/",
    "sg:phone":"+1 718 238 3092",
    "sg:postcode":"11209",
    "sg:province":"NY",
    "sg:tags":[
        "american",
        "pastry"
    ],
    "wof:name":"Cinnabon",
    "wof:placetype":"venue"
},
  "geometry": {"coordinates":[-74.03110599999999,40.623363],"type":"Point"}
}