{
  "type": "Feature",
  "properties": {
    "iso:country":"US",
    "sg:address":"2000 S Winton Rd",
    "sg:city":"Rochester",
    "sg:classifiers":[
        {
            "category":"Professional",
            "subcategory":"Accounting & Tax Preparation",
            "type":"Services"
        }
    ],
    "sg:phone":"+1 585 292 1136",
    "sg:postcode":"14618",
    "sg:province":"NY",
    "sg:tags":[
        "accountant"
    ],
    "wof:name":"Guardian Financial Svc",
    "wof:placetype":"venue"
},
  "geometry": {"coordinates":[-77.57599399999999,43.107456],"type":"Point"}
}