{
  "type": "Feature",
  "properties": {
    "addr:full":"6329 Townline Rd Byron NY 14422",
    "addr:housenumber":"6329",
    "addr:postcode":"14422",
    "addr:street":"Townline Rd",
    "iso:country":"US",
    "sg:address":"6329 Townline Rd",
    "sg:city":"Byron",
    "sg:classifiers":[
        {
            "category":"Wholesale",
            "subcategory":"Machinery & Supplies",
            "type":"Manufacturing & Wholesale Goods"
        }
    ],
    "sg:phone":"+1 585 548 7157",
    "sg:postcode":"14422",
    "sg:province":"NY",
    "sg:tags":[
        "fire",
        "department",
        "equipment"
    ],
    "wof:name":"C C & D Specialties",
    "wof:placetype":"venue"
},
  "geometry": {"coordinates":[-78.063923,43.079743],"type":"Point"}
}