{
  "type": "Feature",
  "properties": {
    "addr:full":"345 W 58th St New York NY 10019",
    "addr:housenumber":"345",
    "addr:postcode":"10019",
    "addr:street":"W 58Th St",
    "iso:country":"US",
    "sg:address":"345 W 58th St",
    "sg:city":"New York",
    "sg:classifiers":[
        {
            "category":"Professional",
            "type":"Services"
        }
    ],
    "sg:phone":"+1 212 586 3721",
    "sg:postcode":"10019",
    "sg:province":"NY",
    "sg:tags":[
        "establishment"
    ],
    "wof:name":"Federation Hebrew History",
    "wof:placetype":"venue"
},
  "geometry": {"coordinates":[-73.984216,40.768124],"type":"Point"}
}