{
  "type": "Feature",
  "properties": {
    "addr:full":"6856 S Transit Rd Lockport NY 14094",
    "addr:housenumber":"6856",
    "addr:postcode":"14094",
    "addr:street":"S Transit Rd",
    "iso:country":"US",
    "sg:address":"6856 S Transit Rd",
    "sg:city":"Lockport",
    "sg:classifiers":[
        {
            "category":"Restaurant",
            "type":"Food & Drink"
        }
    ],
    "sg:phone":"+1   ",
    "sg:postcode":"14094",
    "sg:province":"NY",
    "wof:name":"Jimmy BS",
    "wof:placetype":"venue"
},
  "geometry": {"coordinates":[-78.696962,43.091434],"type":"Point"}
}