{
  "type": "Feature",
  "properties": {
    "iso:country":"US",
    "sg:address":"4 Harbor Park Dr",
    "sg:city":"Port Washington",
    "sg:classifiers":[
        {
            "category":"Home & Garden",
            "subcategory":"Hardware",
            "type":"Retail Goods"
        }
    ],
    "sg:phone":"+1 516 484 4406",
    "sg:postcode":"11050",
    "sg:province":"NY",
    "sg:tags":[
        "store"
    ],
    "wof:name":"Harris Hardware Industries Corp",
    "wof:placetype":"venue"
},
  "geometry": {"coordinates":[-73.655602,40.812099],"type":"Point"}
}