{
  "type": "Feature",
  "properties": {
    "addr:full":"1707 Old Country Rd Elmsford NY 10523",
    "addr:housenumber":"1707",
    "addr:postcode":"10523",
    "addr:street":"Old Country Rd",
    "iso:country":"US",
    "sg:address":"1707 Old Country Rd",
    "sg:city":"Elmsford",
    "sg:classifiers":[
        {
            "category":"Education",
            "subcategory":"Special Training",
            "type":"Public Place"
        }
    ],
    "sg:phone":"+1 914 592 5949",
    "sg:postcode":"10523",
    "sg:province":"NY",
    "sg:tags":[
        "medical"
    ],
    "wof:name":"Meded Interactive Inc",
    "wof:placetype":"venue"
},
  "geometry": {"coordinates":[-73.81445600000001,41.065118],"type":"Point"}
}