{
  "type": "Feature",
  "properties": {
    "addr:full":"226 Clinton St Binghamton NY 13905",
    "addr:housenumber":"226",
    "addr:postcode":"13905",
    "addr:street":"Clinton St",
    "iso:country":"US",
    "sg:address":"226 Clinton St",
    "sg:city":"Binghamton",
    "sg:classifiers":[
        {
            "category":"Social Services",
            "subcategory":"Adult Care",
            "type":"Services"
        },
        {
            "category":"Social Services",
            "type":"Services"
        }
    ],
    "sg:phone":"+1 607 729 6214",
    "sg:postcode":"13905",
    "sg:province":"NY",
    "sg:tags":[
        "organization",
        "senior",
        "executive",
        "citizen"
    ],
    "wof:name":"First Ward Senior Center",
    "wof:placetype":"venue"
},
  "geometry": {"coordinates":[-75.930907,42.107223],"type":"Point"}
}