{
  "type": "Feature",
  "properties": {
    "addr:full":"158 Chelsea St Staten Island NY 10307",
    "addr:housenumber":"158",
    "addr:postcode":"10307",
    "addr:street":"Chelsea St",
    "iso:country":"US",
    "sg:address":"158 Chelsea St",
    "sg:city":"Staten Island",
    "sg:classifiers":[
        {
            "category":"Professional",
            "subcategory":"Computer Services",
            "type":"Services"
        }
    ],
    "sg:phone":"+1 718 356 0990",
    "sg:postcode":"10307",
    "sg:province":"NY",
    "sg:website":"www.jssweb.net",
    "wof:name":"JSSWEB.NET",
    "wof:placetype":"venue"
},
  "geometry": {"coordinates":[-74.24473,40.505524],"type":"Point"}
}