{
  "type": "Feature",
  "properties": {
    "iso:country":"US",
    "sg:address":"8 Park Ave",
    "sg:city":"Manhasset",
    "sg:classifiers":[
        {
            "category":"Shopping",
            "subcategory":"Pets & Pet Supplies",
            "type":"Retail Goods"
        }
    ],
    "sg:phone":"+1 516 869 3378",
    "sg:postcode":"11030",
    "sg:province":"NY",
    "sg:tags":[
        "store",
        "groomers"
    ],
    "sg:website":"1800bullysticks.com",
    "wof:name":"Pets Boutique",
    "wof:placetype":"venue"
},
  "geometry": {"coordinates":[-73.698759,40.796912],"type":"Point"}
}