{
  "type": "Feature",
  "properties": {
    "addr:full":"203 Black Meadow Rd Chester NY 10918",
    "addr:housenumber":"203",
    "addr:postcode":"10918",
    "addr:street":"Black Meadow Rd",
    "iso:country":"US",
    "sg:address":"203 Black Meadow Rd",
    "sg:city":"Chester",
    "sg:classifiers":[
        {
            "category":"Manufacturing",
            "subcategory":"Buildings",
            "type":"Manufacturing & Wholesale Goods"
        },
        {
            "category":"Building & Trades",
            "subcategory":"Construction",
            "type":"Services"
        }
    ],
    "sg:phone":"+1 845 469 4090",
    "sg:postcode":"10918",
    "sg:province":"NY",
    "sg:tags":[
        "home",
        "builder",
        "contractor"
    ],
    "wof:name":"Valeo Pillar Corp.",
    "wof:placetype":"venue"
},
  "geometry": {"coordinates":[-74.292463,41.340262],"type":"Point"}
}