{
  "type": "Feature",
  "properties": {
    "iso:country":"US",
    "sg:address":"23128 Merrick Blvd",
    "sg:city":"Springfield Gardens",
    "sg:classifiers":[
        {
            "category":"Professional",
            "subcategory":"Accounting & Tax Preparation",
            "type":"Services"
        }
    ],
    "sg:phone":"+1 718 978 9616",
    "sg:postcode":"11413",
    "sg:province":"NY",
    "sg:tags":[
        "accountant"
    ],
    "wof:name":"Walker & Assocs",
    "wof:placetype":"venue"
},
  "geometry": {"coordinates":[-73.73850299999999,40.675301],"type":"Point"}
}