{
  "type": "Feature",
  "properties": {
    "iso:country":"US",
    "sg:address":"2951 Judith Dr",
    "sg:city":"Bellmore",
    "sg:classifiers":[
        {
            "category":"Banks & Credit Unions",
            "subcategory":"Investment Brokerage",
            "type":"Services"
        }
    ],
    "sg:phone":"+1 516 221 0467",
    "sg:postcode":"11710",
    "sg:province":"NY",
    "sg:tags":[
        "advisory"
    ],
    "wof:name":"Jlk Financial Services",
    "wof:placetype":"venue"
},
  "geometry": {"coordinates":[-73.52069,40.650379],"type":"Point"}
}