{
  "type": "Feature",
  "properties": {
    "addr:full":"122 W High St Painted Post NY 14870",
    "addr:housenumber":"122",
    "addr:postcode":"14870",
    "addr:street":"W High St",
    "iso:country":"US",
    "sg:address":"122 W High St",
    "sg:city":"Painted Post",
    "sg:classifiers":[
        {
            "category":"Personal",
            "subcategory":"Beauty Salon",
            "type":"Services"
        }
    ],
    "sg:phone":"+1   ",
    "sg:postcode":"14870",
    "sg:province":"NY",
    "sg:tags":[
        "shop"
    ],
    "wof:name":"Oasis Beauty & Tanning Full Sv",
    "wof:placetype":"venue"
},
  "geometry": {"coordinates":[-77.090384,42.160157],"type":"Point"}
}