{
  "type": "Feature",
  "properties": {
    "addr:full":"131 Storer Ave Staten Island NY 10309",
    "addr:housenumber":"131",
    "addr:postcode":"10309",
    "addr:street":"Storer Ave",
    "iso:country":"US",
    "sg:address":"131 Storer Ave",
    "sg:city":"Staten Island",
    "sg:classifiers":[
        {
            "category":"Real Estate",
            "subcategory":"Real Estate Services",
            "type":"Services"
        }
    ],
    "sg:phone":"+1 718 227 0375",
    "sg:postcode":"10309",
    "sg:province":"NY",
    "sg:tags":[
        "home",
        "inspector"
    ],
    "wof:name":"Crown Mark Electrical Cntrctg",
    "wof:placetype":"venue"
},
  "geometry": {"coordinates":[-74.233343,40.538571],"type":"Point"}
}