{
  "type": "Feature",
  "properties": {
    "addr:full":"42 W Merrick Rd Valley Stream NY 11580",
    "addr:housenumber":"42",
    "addr:postcode":"11580",
    "addr:street":"W Merrick Rd",
    "iso:country":"US",
    "sg:address":"42 W Merrick Rd",
    "sg:city":"Valley Stream",
    "sg:classifiers":[
        {
            "category":"Autos & Motor Vehicles",
            "subcategory":"Fuel & Gas Station",
            "type":"Retail Goods"
        }
    ],
    "sg:phone":"+1 516 825 9742",
    "sg:postcode":"11580",
    "sg:province":"NY",
    "wof:name":"D & D Svc Sta",
    "wof:placetype":"venue"
},
  "geometry": {"coordinates":[-73.69940200000001,40.665199],"type":"Point"}
}