{
  "type": "Feature",
  "properties": {
    "iso:country":"US",
    "sg:address":"244 Hudson Ave",
    "sg:city":"Albany",
    "sg:classifiers":[
        {
            "category":"Social Services",
            "type":"Services"
        },
        {
            "category":"Organizations",
            "subcategory":"Membership Organization",
            "type":"Services"
        }
    ],
    "sg:phone":"+1 518 465 0641",
    "sg:postcode":"12210",
    "sg:province":"NY",
    "sg:tags":[
        "support",
        "group"
    ],
    "sg:website":"http://www.coalitionforaging.org",
    "wof:name":"New York State Coalition For The Aging",
    "wof:placetype":"venue"
},
  "geometry": {"coordinates":[-73.76246399999999,42.651631],"type":"Point"}
}