{
  "type": "Feature",
  "properties": {
    "addr:full":"4919 Syracuse Rd Cazenovia NY 13035",
    "addr:housenumber":"4919",
    "addr:postcode":"13035",
    "addr:street":"Syracuse Rd",
    "iso:country":"US",
    "sg:address":"4919 Syracuse Rd",
    "sg:city":"Cazenovia",
    "sg:classifiers":[
        {
            "category":"Cinema",
            "subcategory":"Movie Rental",
            "type":"Entertainment"
        }
    ],
    "sg:phone":"+1   ",
    "sg:postcode":"13035",
    "sg:province":"NY",
    "sg:tags":[
        "video",
        "tape"
    ],
    "wof:name":"Coffey Film/Video",
    "wof:placetype":"venue"
},
  "geometry": {"coordinates":[-75.884263,42.944669],"type":"Point"}
}