{
  "type": "Feature",
  "properties": {
    "addr:full":"364 Broadway Newburgh NY 12550",
    "addr:housenumber":"364",
    "addr:postcode":"12550",
    "addr:street":"Broadway",
    "iso:country":"US",
    "sg:address":"364 Broadway",
    "sg:city":"Newburgh",
    "sg:classifiers":[
        {
            "category":"Utilities",
            "subcategory":"Mobile Phone",
            "type":"Services"
        }
    ],
    "sg:phone":"+1 845 563 7300",
    "sg:postcode":"12550",
    "sg:province":"NY",
    "sg:tags":[
        "telephone",
        "cellular"
    ],
    "wof:name":"Keep N Touch Wireless",
    "wof:placetype":"venue"
},
  "geometry": {"coordinates":[-74.024675,41.501012],"type":"Point"}
}