{
  "type": "Feature",
  "properties": {
    "addr:full":"248 W 35 St New York NY 10001",
    "addr:housenumber":"248",
    "addr:postcode":"10001",
    "addr:street":"W 35 St",
    "iso:country":"US",
    "sg:address":"248 W 35 St",
    "sg:city":"New York",
    "sg:classifiers":[
        {
            "category":"Manufacturing",
            "subcategory":"Tools & Machinery",
            "type":"Manufacturing & Wholesale Goods"
        }
    ],
    "sg:phone":"+1 212 465 8883",
    "sg:postcode":"10001",
    "sg:province":"NY",
    "sg:tags":[
        "pattern",
        "industrial"
    ],
    "wof:name":"Ny Pattern & Sample Ctr Inc",
    "wof:placetype":"venue"
},
  "geometry": {"coordinates":[-73.99195899999999,40.752203],"type":"Point"}
}