{
  "type": "Feature",
  "properties": {
    "addr:full":"2118 Quentin Rd Brooklyn NY 11229",
    "addr:housenumber":"2118",
    "addr:postcode":"11229",
    "addr:street":"Quentin Rd",
    "iso:country":"US",
    "sg:address":"2118 Quentin Rd",
    "sg:city":"Brooklyn",
    "sg:classifiers":[
        {
            "category":"Health Services",
            "subcategory":"Doctor",
            "type":"Services"
        }
    ],
    "sg:phone":"+1   ",
    "sg:postcode":"11229",
    "sg:province":"NY",
    "sg:tags":[
        "physician"
    ],
    "wof:name":"Susan Zilkha MD",
    "wof:placetype":"venue"
},
  "geometry": {"coordinates":[-73.951348,40.60893],"type":"Point"}
}