{
  "type": "Feature",
  "properties": {
    "addr:full":"576 W Park Ave Long Beach NY 11561",
    "addr:housenumber":"576",
    "addr:postcode":"11561",
    "addr:street":"W Park Ave",
    "iso:country":"US",
    "sg:address":"576 W Park Ave",
    "sg:city":"Long Beach",
    "sg:classifiers":[
        {
            "category":"Retail",
            "subcategory":"Auto Repair",
            "type":"Services"
        }
    ],
    "sg:phone":"+1 516 431 8600",
    "sg:postcode":"11561",
    "sg:province":"NY",
    "sg:tags":[
        "repairing",
        "automobile"
    ],
    "wof:name":"Empire Motor Group Inc",
    "wof:placetype":"venue"
},
  "geometry": {"coordinates":[-73.67958900000001,40.588325],"type":"Point"}
}