{
  "type": "Feature",
  "properties": {
    "addr:full":"117 Valley Rd Katonah NY 10536",
    "addr:housenumber":"117",
    "addr:postcode":"10536",
    "addr:street":"Valley Rd",
    "iso:country":"US",
    "sg:address":"117 Valley Rd",
    "sg:city":"Katonah",
    "sg:classifiers":[
        {
            "category":"Organizations",
            "subcategory":"Religious Organization",
            "type":"Services"
        }
    ],
    "sg:phone":"+1 914 232 3356",
    "sg:postcode":"10536",
    "sg:province":"NY",
    "sg:tags":[
        "church"
    ],
    "wof:name":"St Mary's Church",
    "wof:placetype":"venue"
},
  "geometry": {"coordinates":[-73.689803,41.254082],"type":"Point"}
}