{
  "type": "Feature",
  "properties": {
    "iso:country":"US",
    "sg:address":"227 Mc Kinley Ter",
    "sg:city":"Centerport",
    "sg:classifiers":[
        {
            "category":"Building & Trades",
            "subcategory":"Construction",
            "type":"Services"
        }
    ],
    "sg:phone":"+1 631 425 2690",
    "sg:postcode":"11721",
    "sg:province":"NY",
    "sg:tags":[
        "general",
        "contractor"
    ],
    "wof:name":"ESA",
    "wof:placetype":"venue"
},
  "geometry": {"coordinates":[-73.37973100000001,40.896594],"type":"Point"}
}