{
  "type": "Feature",
  "properties": {
    "iso:country":"US",
    "sg:address":"134 Burrs Ln",
    "sg:city":"Dix Hills",
    "sg:classifiers":[
        {
            "category":"Professional",
            "subcategory":"Lawyer & Legal Services",
            "type":"Services"
        }
    ],
    "sg:phone":"+1 631 491 9190",
    "sg:postcode":"11746",
    "sg:province":"NY",
    "sg:tags":[
        "attorney"
    ],
    "wof:name":"Audrey Shey",
    "wof:placetype":"venue"
},
  "geometry": {"coordinates":[-73.366918,40.786499],"type":"Point"}
}