{
  "type": "Feature",
  "properties": {
    "iso:country":"US",
    "sg:address":"5816 7th Ave",
    "sg:city":"Brooklyn",
    "sg:classifiers":[
        {
            "category":"Shopping",
            "subcategory":"Gifts & Souvenirs",
            "type":"Retail Goods"
        }
    ],
    "sg:phone":"+1 718 492 4788",
    "sg:postcode":"11220",
    "sg:province":"NY",
    "sg:tags":[
        "shop"
    ],
    "wof:name":"Commercial Kemaz Inc",
    "wof:placetype":"venue"
},
  "geometry": {"coordinates":[-74.01114,40.637542],"type":"Point"}
}