{
  "type": "Feature",
  "properties": {
    "addr:full":"4 Enterprise Dr Albany NY 12204",
    "addr:housenumber":"4",
    "addr:postcode":"12204",
    "addr:street":"Enterprise Dr",
    "iso:country":"US",
    "sg:address":"4 Enterprise Dr",
    "sg:city":"Albany",
    "sg:classifiers":[
        {
            "category":"Wholesale",
            "subcategory":"Hardware",
            "type":"Manufacturing & Wholesale Goods"
        }
    ],
    "sg:phone":"+1 518 472 1040",
    "sg:postcode":"12204",
    "sg:province":"NY",
    "sg:tags":[
        "fastener"
    ],
    "wof:name":"Thruway Fasteners",
    "wof:placetype":"venue"
},
  "geometry": {"coordinates":[-73.734866,42.671293],"type":"Point"}
}