{
  "type": "Feature",
  "properties": {
    "addr:full":"1021 E 14th St Brooklyn NY 11230",
    "addr:housenumber":"1021",
    "addr:postcode":"11230",
    "addr:street":"E 14Th St",
    "iso:country":"US",
    "sg:address":"1021 E 14th St",
    "sg:city":"Brooklyn",
    "sg:classifiers":[
        {
            "category":"Organizations",
            "subcategory":"Religious Organization",
            "type":"Services"
        }
    ],
    "sg:phone":"+1 718 252 1388",
    "sg:postcode":"11230",
    "sg:province":"NY",
    "sg:tags":[
        "clergy"
    ],
    "wof:name":"Ralph Shain",
    "wof:placetype":"venue"
},
  "geometry": {"coordinates":[-73.961862,40.623187],"type":"Point"}
}