{
  "type": "Feature",
  "properties": {
    "addr:full":"48 Oakhill Dr Hamburg NY 14075",
    "addr:housenumber":"48",
    "addr:postcode":"14075",
    "addr:street":"Oakhill Dr",
    "iso:country":"US",
    "sg:address":"48 Oakhill Dr",
    "sg:city":"Hamburg",
    "sg:classifiers":[
        {
            "category":"Home & Garden",
            "subcategory":"Building Materials",
            "type":"Retail Goods"
        }
    ],
    "sg:phone":"+1 716 662 5102",
    "sg:postcode":"14075",
    "sg:province":"NY",
    "sg:tags":[
        "energy",
        "conservation",
        "prod"
    ],
    "wof:name":"Efficient Solutions Inc",
    "wof:placetype":"venue"
},
  "geometry": {"coordinates":[-78.849104,42.729875],"type":"Point"}
}