{
  "type": "Feature",
  "properties": {
    "addr:full":"1920 Richmond Ter Staten Island NY 10302",
    "addr:housenumber":"1920",
    "addr:postcode":"10302",
    "addr:street":"Richmond Ter",
    "iso:country":"US",
    "sg:address":"1920 Richmond Ter",
    "sg:city":"Staten Island",
    "sg:classifiers":[
        {
            "category":"Restaurant",
            "type":"Food & Drink"
        }
    ],
    "sg:phone":"+1 718 442 6038",
    "sg:postcode":"10302",
    "sg:province":"NY",
    "wof:name":"Bermay Luncheonette",
    "wof:placetype":"venue"
},
  "geometry": {"coordinates":[-74.129251,40.638481],"type":"Point"}
}