{
  "type": "Feature",
  "properties": {
    "iso:country":"US",
    "sg:address":"959 Broadway St",
    "sg:city":"Buffalo",
    "sg:classifiers":[
        {
            "category":"Building & Trades",
            "subcategory":"Equipment Rental",
            "type":"Services"
        }
    ],
    "sg:phone":"+1 716 895 9832",
    "sg:postcode":"14212",
    "sg:province":"NY",
    "sg:tags":[
        "appliance",
        "furniture"
    ],
    "wof:name":"Rent-Way",
    "wof:placetype":"venue"
},
  "geometry": {"coordinates":[-78.83826500000001,42.893131],"type":"Point"}
}