{
  "type": "Feature",
  "properties": {
    "addr:full":"2430 Route 9 Fishkill NY 12524",
    "addr:housenumber":"2430",
    "addr:postcode":"12524",
    "addr:street":"Route 9",
    "iso:country":"US",
    "sg:address":"2430 Route 9",
    "sg:city":"Fishkill",
    "sg:classifiers":[
        {
            "category":"Shopping",
            "subcategory":"Department Store",
            "type":"Retail Goods"
        }
    ],
    "sg:phone":"+1 845 896 8767",
    "sg:postcode":"12524",
    "sg:province":"NY",
    "wof:name":"Sam's Club 1-Hour Photo",
    "wof:placetype":"venue"
},
  "geometry": {"coordinates":[-73.893501,41.5373],"type":"Point"}
}