{
  "type": "Feature",
  "properties": {
    "iso:country":"US",
    "sg:address":"157 Central Ave",
    "sg:city":"Albany",
    "sg:classifiers":[
        {
            "category":"Shopping",
            "subcategory":"Clothing, Apparel, & Fashions",
            "type":"Retail Goods"
        }
    ],
    "sg:phone":"+1 518 432 5296",
    "sg:postcode":"12206",
    "sg:province":"NY",
    "wof:name":"Al's Cycle & Streetware",
    "wof:placetype":"venue"
},
  "geometry": {"coordinates":[-73.76852700000001,42.661176],"type":"Point"}
}