{
  "type": "Feature",
  "properties": {
    "addr:full":"6666 Old Collamer Rd East Syracuse NY 13057",
    "addr:housenumber":"6666",
    "addr:postcode":"13057",
    "addr:street":"Old Collamer Rd",
    "iso:country":"US",
    "sg:address":"6666 Old Collamer Rd",
    "sg:city":"East Syracuse",
    "sg:classifiers":[
        {
            "category":"Professional",
            "subcategory":"Computer Services",
            "type":"Services"
        }
    ],
    "sg:phone":"+1 315 431 4676",
    "sg:postcode":"13057",
    "sg:province":"NY",
    "sg:tags":[
        "hardware",
        "lease"
    ],
    "wof:name":"Ontario Investments Inc",
    "wof:placetype":"venue"
},
  "geometry": {"coordinates":[-76.083468,43.094428],"type":"Point"}
}