{
  "type": "Feature",
  "properties": {
    "iso:country":"US",
    "sg:address":"900 Jefferson Rd",
    "sg:city":"Rochester",
    "sg:classifiers":[
        {
            "category":"Professional",
            "subcategory":"Management & Consulting",
            "type":"Services"
        }
    ],
    "sg:phone":"+1 585 292 1906",
    "sg:postcode":"14623",
    "sg:province":"NY",
    "sg:tags":[
        "break",
        "coffee",
        "supply"
    ],
    "wof:name":"Mc Cullagh Coffee",
    "wof:placetype":"venue"
},
  "geometry": {"coordinates":[-77.615908,43.087248],"type":"Point"}
}