{
  "type": "Feature",
  "properties": {
    "addr:full":"14414 243rd St Rosedale NY 11422",
    "addr:housenumber":"14414",
    "addr:postcode":"11422",
    "addr:street":"243Rd St",
    "iso:country":"US",
    "sg:address":"14414 243rd St",
    "sg:city":"Rosedale",
    "sg:classifiers":[
        {
            "category":"Social Services",
            "subcategory":"Child Care",
            "type":"Services"
        }
    ],
    "sg:phone":"+1 718 528 1381",
    "sg:postcode":"11422",
    "sg:province":"NY",
    "sg:tags":[
        "nursery",
        "day"
    ],
    "wof:name":"Score Learning Center",
    "wof:placetype":"venue"
},
  "geometry": {"coordinates":[-73.73563,40.665461],"type":"Point"}
}