{
  "type": "Feature",
  "properties": {
    "addr:full":"1703 Little Britain Rd Rock Tavern NY 12575",
    "addr:housenumber":"1703",
    "addr:postcode":"12575",
    "addr:street":"Little Britain Rd",
    "iso:country":"US",
    "sg:address":"1703 Little Britain Rd",
    "sg:city":"Rock Tavern",
    "sg:classifiers":[
        {
            "category":"Building & Trades",
            "subcategory":"Construction",
            "type":"Services"
        }
    ],
    "sg:phone":"+1 845 496 6255",
    "sg:postcode":"12575",
    "sg:province":"NY",
    "sg:tags":[
        "masonry",
        "contractor"
    ],
    "wof:name":"Dirk Polman Mason Contractors",
    "wof:placetype":"venue"
},
  "geometry": {"coordinates":[-74.154544,41.472047],"type":"Point"}
}