{
  "type": "Feature",
  "properties": {
    "addr:full":"56 Bay St Staten Island NY 10301",
    "addr:housenumber":"56",
    "addr:postcode":"10301",
    "addr:street":"Bay St",
    "iso:country":"US",
    "sg:address":"56 Bay St",
    "sg:city":"Staten Island",
    "sg:classifiers":[
        {
            "category":"Wholesale",
            "subcategory":"Durable Goods & Equipment",
            "type":"Manufacturing & Wholesale Goods"
        }
    ],
    "sg:phone":"+1 718 273 7632",
    "sg:postcode":"10301",
    "sg:province":"NY",
    "sg:tags":[
        "importer"
    ],
    "wof:name":"Alexandria International Trdng",
    "wof:placetype":"venue"
},
  "geometry": {"coordinates":[-74.075675,40.640299],"type":"Point"}
}