{
  "type": "Feature",
  "properties": {
    "addr:full":"315 W End Avenue New York NY 10023",
    "addr:housenumber":"315",
    "addr:postcode":"10023",
    "addr:street":"W End Avenue",
    "iso:country":"US",
    "sg:address":"315 W End Avenue",
    "sg:city":"New York",
    "sg:classifiers":[
        {
            "category":"Professional",
            "subcategory":"Lawyer & Legal Services",
            "type":"Services"
        }
    ],
    "sg:phone":"+1 212 580 1160",
    "sg:postcode":"10023",
    "sg:province":"NY",
    "wof:name":"Fioramonti Frank R Attorney",
    "wof:placetype":"venue"
},
  "geometry": {"coordinates":[-73.98319600000001,40.781584],"type":"Point"}
}