{
  "type": "Feature",
  "properties": {
    "iso:country":"US",
    "sg:address":"5427 N Burdick St",
    "sg:city":"Fayetteville",
    "sg:classifiers":[
        {
            "category":"Autos & Motor Vehicles",
            "subcategory":"Automobile Sales",
            "type":"Retail Goods"
        }
    ],
    "sg:phone":"+1 315 637 5001",
    "sg:postcode":"13066",
    "sg:province":"NY",
    "sg:tags":[
        "new",
        "car"
    ],
    "sg:website":"http://www.fayettevilledodge.com",
    "wof:name":"Fayetteville Dodge Inc",
    "wof:placetype":"venue"
},
  "geometry": {"coordinates":[-76.017303,43.0369],"type":"Point"}
}