{
  "type": "Feature",
  "properties": {
    "addr:full":"99 Wall Street New York NY 10005",
    "addr:housenumber":"99",
    "addr:postcode":"10005",
    "addr:street":"Wall Street",
    "iso:country":"US",
    "sg:address":"99 Wall Street",
    "sg:city":"New York",
    "sg:classifiers":[
        {
            "category":"Building & Trades",
            "subcategory":"Construction",
            "type":"Services"
        }
    ],
    "sg:phone":"+1 212 343 7262",
    "sg:postcode":"10005",
    "sg:province":"NY",
    "sg:tags":[
        "contractor"
    ],
    "wof:name":"Aj International Construction",
    "wof:placetype":"venue"
},
  "geometry": {"coordinates":[-74.006775,40.704755],"type":"Point"}
}