{
  "type": "Feature",
  "properties": {
    "addr:full":"714 Terrace Pl Uniondale NY 11553",
    "addr:housenumber":"714",
    "addr:postcode":"11553",
    "addr:street":"Terrace Pl",
    "iso:country":"US",
    "sg:address":"714 Terrace Pl",
    "sg:city":"Uniondale",
    "sg:classifiers":[
        {
            "category":"Personal",
            "subcategory":"Beauty Salon",
            "type":"Services"
        }
    ],
    "sg:phone":"+1 516 564 8890",
    "sg:postcode":"11553",
    "sg:province":"NY",
    "wof:name":"Sensation",
    "wof:placetype":"venue"
},
  "geometry": {"coordinates":[-73.587744,40.695294],"type":"Point"}
}