{
  "type": "Feature",
  "properties": {
    "addr:full":"526 W 26th St between Tenth & Eleventh Ave Manhattan NY 10001",
    "addr:housenumber":"526",
    "addr:postcode":"10001",
    "addr:street":"W 26Th St;Ave",
    "iso:country":"US",
    "sg:address":"526 W 26th St between Tenth & Eleventh Ave",
    "sg:city":"Manhattan",
    "sg:classifiers":[
        {
            "category":"Arts & Performance",
            "subcategory":"Art Gallery",
            "type":"Entertainment"
        }
    ],
    "sg:phone":"+1 646 734 9072",
    "sg:postcode":"10001",
    "sg:province":"NY",
    "sg:website":"www.puzzleartproject.com",
    "wof:name":"Puzzle Art Project @ Reaves Gallery",
    "wof:placetype":"venue"
},
  "geometry": {"coordinates":[-74.004203,40.750124],"type":"Point"}
}