{
  "type": "Feature",
  "properties": {
    "addr:full":"496 Rock Ave Exd Chestertown NY 12817",
    "addr:housenumber":"496",
    "addr:postcode":"12817",
    "addr:street":"Rock Ave Exd",
    "iso:country":"US",
    "sg:address":"496 Rock Ave Exd",
    "sg:city":"Chestertown",
    "sg:classifiers":[
        {
            "category":"Building & Trades",
            "subcategory":"Landscaping Services",
            "type":"Services"
        }
    ],
    "sg:phone":"+1 518 494 2053",
    "sg:postcode":"12817",
    "sg:province":"NY",
    "wof:name":"Vic Aitken Landscape Services",
    "wof:placetype":"venue"
},
  "geometry": {"coordinates":[-73.76904500000001,43.637743],"type":"Point"}
}