{
  "type": "Feature",
  "properties": {
    "iso:country":"US",
    "sg:address":"3514 Delaware Ave",
    "sg:city":"Kenmore",
    "sg:classifiers":[
        {
            "category":"Organizations",
            "subcategory":"Professional Association",
            "type":"Services"
        },
        {
            "category":"Health Services",
            "subcategory":"Doctor",
            "type":"Services"
        }
    ],
    "sg:phone":"+1 716 871 8672",
    "sg:postcode":"14217",
    "sg:province":"NY",
    "sg:tags":[
        "dentist",
        "dental"
    ],
    "wof:name":"Eighth District Service Corp",
    "wof:placetype":"venue"
},
  "geometry": {"coordinates":[-78.87242000000001,42.980746],"type":"Point"}
}