{
  "type": "Feature",
  "properties": {
    "iso:country":"US",
    "sg:address":"1610 Old Country Rd",
    "sg:city":"Westbury",
    "sg:classifiers":[
        {
            "category":"Health Services",
            "subcategory":"Doctor",
            "type":"Services"
        }
    ],
    "sg:phone":"+1 516 228 4900",
    "sg:postcode":"11590",
    "sg:province":"NY",
    "wof:name":"Care One Medical",
    "wof:placetype":"venue"
},
  "geometry": {"coordinates":[-73.60030399999999,40.745701],"type":"Point"}
}