{
  "type": "Feature",
  "properties": {
    "addr:full":"152 N Mac Questen Pkwy Mt Vernon NY 10550",
    "addr:housenumber":"152",
    "addr:postcode":"10550",
    "addr:street":"N Mac Questen Pkwy",
    "iso:country":"US",
    "sg:address":"152 N Mac Questen Pkwy",
    "sg:city":"Mt Vernon",
    "sg:classifiers":[
        {
            "category":"Wholesale",
            "subcategory":"Machinery & Supplies",
            "type":"Manufacturing & Wholesale Goods"
        }
    ],
    "sg:phone":"+1 914 237 7001",
    "sg:postcode":"10550",
    "sg:province":"NY",
    "sg:tags":[
        "container",
        "receptacle",
        "garbage"
    ],
    "wof:name":"Hudson Valley Container Corp",
    "wof:placetype":"venue"
},
  "geometry": {"coordinates":[-73.84728200000001,40.914509],"type":"Point"}
}