{
  "type": "Feature",
  "properties": {
    "addr:full":"63 Commercial Ave Garden City NY 11530",
    "addr:housenumber":"63",
    "addr:postcode":"11530",
    "addr:street":"Commercial Ave",
    "iso:country":"US",
    "sg:address":"63 Commercial Ave",
    "sg:city":"Garden City",
    "sg:classifiers":[
        {
            "category":"Food & Beverages",
            "subcategory":"Liquor & Beverages",
            "type":"Retail Goods"
        }
    ],
    "sg:phone":"+1 888 568 3700",
    "sg:postcode":"11530",
    "sg:province":"NY",
    "sg:tags":[
        "beer",
        "spirit",
        "wine"
    ],
    "wof:name":"Phillips Wine & Spirits",
    "wof:placetype":"venue"
},
  "geometry": {"coordinates":[-73.618955,40.727596],"type":"Point"}
}