{
  "type": "Feature",
  "properties": {
    "addr:full":"3702 48th St Long Island City NY 11104",
    "addr:housenumber":"3702",
    "addr:postcode":"11104",
    "addr:street":"48Th St",
    "iso:country":"US",
    "sg:address":"3702 48th St",
    "sg:city":"Long Island City",
    "sg:classifiers":[
        {
            "category":"Home & Garden",
            "subcategory":"Home Furnishings",
            "type":"Retail Goods"
        },
        {
            "category":"Building & Trades",
            "subcategory":"Construction",
            "type":"Services"
        }
    ],
    "sg:phone":"+1 718 729 3881",
    "sg:postcode":"11104",
    "sg:province":"NY",
    "sg:tags":[
        "interior",
        "bath",
        "design",
        "kitchen"
    ],
    "wof:name":"Milestone Kitchen & Bath Corp",
    "wof:placetype":"venue"
},
  "geometry": {"coordinates":[-73.91536499999999,40.751075],"type":"Point"}
}