{
  "type": "Feature",
  "properties": {
    "addr:full":"37 US Hwy 9w West Haverstraw NY 10993",
    "addr:housenumber":"37",
    "addr:postcode":"10993",
    "addr:street":"Us Hwy 9W West",
    "iso:country":"US",
    "sg:address":"37 US Hwy 9w",
    "sg:city":"West Haverstraw",
    "sg:classifiers":[
        {
            "category":"Restaurant",
            "type":"Food & Drink"
        }
    ],
    "sg:phone":"+1   ",
    "sg:postcode":"10993",
    "sg:province":"NY",
    "sg:tags":[
        "eating"
    ],
    "wof:name":"Carvel Ice Cream",
    "wof:placetype":"venue"
},
  "geometry": {"coordinates":[-73.985876,41.213314],"type":"Point"}
}