{
  "type": "Feature",
  "properties": {
    "iso:country":"US",
    "sg:address":"25 Woodhull Ct",
    "sg:city":"Northport",
    "sg:classifiers":[
        {
            "category":"Professional",
            "subcategory":"Lawyer & Legal Services",
            "type":"Services"
        }
    ],
    "sg:phone":"+1 631 262 7224",
    "sg:postcode":"11768",
    "sg:province":"NY",
    "wof:name":"Di Fiore Elizabeth Atty",
    "wof:placetype":"venue"
},
  "geometry": {"coordinates":[-73.347099,40.895401],"type":"Point"}
}