{
  "type": "Feature",
  "properties": {
    "iso:country":"US",
    "sg:address":"20 Pond St",
    "sg:city":"Goldens Bridge",
    "sg:classifiers":[
        {
            "category":"Shopping",
            "type":"Retail Goods"
        }
    ],
    "sg:phone":"+1   ",
    "sg:postcode":"10526",
    "sg:province":"NY",
    "sg:tags":[
        "merchandise"
    ],
    "wof:name":"Stokes Biocomm",
    "wof:placetype":"venue"
},
  "geometry": {"coordinates":[-73.67118499999999,41.292193],"type":"Point"}
}