{
  "type": "Feature",
  "properties": {
    "addr:full":"10 Mitchell Pl New York NY 10017",
    "addr:housenumber":"10",
    "addr:postcode":"10017",
    "addr:street":"Mitchell Pl",
    "iso:country":"US",
    "sg:address":"10 Mitchell Pl",
    "sg:city":"New York",
    "sg:classifiers":[
        {
            "category":"Wholesale",
            "subcategory":"Toys & Hobbies",
            "type":"Manufacturing & Wholesale Goods"
        }
    ],
    "sg:phone":"+1 212 355 8773",
    "sg:postcode":"10017",
    "sg:province":"NY",
    "wof:name":"Phillip Halyard Art",
    "wof:placetype":"venue"
},
  "geometry": {"coordinates":[-73.96567,40.75314],"type":"Point"}
}