{
  "type": "Feature",
  "properties": {
    "addr:full":"23 Mohonk Rd High Falls NY 12440",
    "addr:housenumber":"23",
    "addr:postcode":"12440",
    "addr:street":"Mohonk Rd",
    "iso:country":"US",
    "sg:address":"23 Mohonk Rd",
    "sg:city":"High Falls",
    "sg:classifiers":[
        {
            "category":"Recreation",
            "type":"Entertainment"
        }
    ],
    "sg:phone":"+1 845 687 9311",
    "sg:postcode":"12440",
    "sg:province":"NY",
    "sg:tags":[
        "historical"
    ],
    "sg:website":"www.canalmuseum.org",
    "wof:name":"D & H Canal Historical",
    "wof:placetype":"venue"
},
  "geometry": {"coordinates":[-74.12648,41.826291],"type":"Point"}
}