{
  "type": "Feature",
  "properties": {
    "iso:country":"US",
    "sg:address":"160 Aspen Look Dr",
    "sg:city":"Henrietta",
    "sg:classifiers":[
        {
            "category":"Professional",
            "subcategory":"Computer Services",
            "type":"Services"
        }
    ],
    "sg:phone":"+1 585 321 3350",
    "sg:postcode":"14467",
    "sg:province":"NY",
    "sg:tags":[
        "consultant",
        "designer"
    ],
    "wof:name":"Carpe Datum Inc",
    "wof:placetype":"venue"
},
  "geometry": {"coordinates":[-77.619423,43.033625],"type":"Point"}
}