{
  "type": "Feature",
  "properties": {
    "iso:country":"US",
    "sg:address":"43 Brookside Ave",
    "sg:city":"Nyack",
    "sg:classifiers":[
        {
            "category":"Retail",
            "subcategory":"Car Wash",
            "type":"Services"
        }
    ],
    "sg:phone":"+1 845 358 9337",
    "sg:postcode":"10960",
    "sg:province":"NY",
    "sg:tags":[
        "automobile",
        "detail",
        "clean"
    ],
    "wof:name":"Fritz Auto Detailing",
    "wof:placetype":"venue"
},
  "geometry": {"coordinates":[-73.924747,41.085246],"type":"Point"}
}