{
  "type": "Feature",
  "properties": {
    "iso:country":"US",
    "sg:address":"576 Western Ave",
    "sg:city":"Albany",
    "sg:classifiers":[
        {
            "category":"Professional",
            "subcategory":"Computer Services",
            "type":"Services"
        },
        {
            "category":"Internet Cafe",
            "subcategory":"None",
            "type":"Food & Drink"
        }
    ],
    "sg:phone":"+1 518 402 3652",
    "sg:postcode":"12203",
    "sg:province":"NY",
    "sg:tags":[
        "product",
        "software"
    ],
    "wof:name":"Brandongroup Inc",
    "wof:placetype":"venue"
},
  "geometry": {"coordinates":[-73.79510000000001,42.667568],"type":"Point"}
}