{
  "type": "Feature",
  "properties": {
    "addr:full":"9 E 40th St Fl 16 New York NY 10016",
    "addr:housenumber":"9;16",
    "addr:postcode":"10016",
    "addr:street":"E 40Th St Fl",
    "iso:country":"US",
    "sg:address":"9 E 40th St Fl 16",
    "sg:city":"New York",
    "sg:classifiers":[
        {
            "category":"Professional",
            "subcategory":"Lawyer & Legal Services",
            "type":"Services"
        }
    ],
    "sg:phone":"+1 212 354 1920",
    "sg:postcode":"10016",
    "sg:province":"NY",
    "wof:name":"Law Offices of David J Wray",
    "wof:placetype":"venue"
},
  "geometry": {"coordinates":[-73.980915,40.751907],"type":"Point"}
}