{
  "type": "Feature",
  "properties": {
    "iso:country":"US",
    "sg:address":"101 Progress Rd",
    "sg:city":"Broadalbin",
    "sg:classifiers":[
        {
            "category":"Communications",
            "type":"Services"
        }
    ],
    "sg:phone":"+1 518 883 4500",
    "sg:postcode":"12078",
    "sg:province":"NY",
    "wof:name":"Fulton County Tele Bbrokers",
    "wof:placetype":"venue"
},
  "geometry": {"coordinates":[-74.271866,43.041726],"type":"Point"}
}