{
  "type": "Feature",
  "properties": {
    "addr:full":"1290 Broad Hollow Rd Farmingdale NY 11735",
    "addr:housenumber":"1290",
    "addr:postcode":"11735",
    "addr:street":"Broad Hollow Rd",
    "iso:country":"US",
    "sg:address":"1290 Broad Hollow Rd",
    "sg:city":"Farmingdale",
    "sg:classifiers":[
        {
            "category":"Home & Garden",
            "subcategory":"Carpets & Floor Coverings",
            "type":"Retail Goods"
        }
    ],
    "sg:phone":"+1   ",
    "sg:postcode":"11735",
    "sg:province":"NY",
    "sg:tags":[
        "store"
    ],
    "wof:name":"Flack Jim Carpet Sales Inc",
    "wof:placetype":"venue"
},
  "geometry": {"coordinates":[-73.423714,40.730233],"type":"Point"}
}