{
  "type": "Feature",
  "properties": {
    "addr:full":"359 Dewitt Avenue Brooklyn NY 11207",
    "addr:housenumber":"359",
    "addr:postcode":"11207",
    "addr:street":"Dewitt Avenue",
    "iso:country":"US",
    "sg:address":"359 Dewitt Avenue",
    "sg:city":"Brooklyn",
    "sg:classifiers":[
        {
            "category":"Retail",
            "subcategory":"Auto Repair",
            "type":"Services"
        }
    ],
    "sg:phone":"+1 718 257 9400",
    "sg:postcode":"11207",
    "sg:province":"NY",
    "wof:name":"Budget Tires",
    "wof:placetype":"venue"
},
  "geometry": {"coordinates":[-73.896863,40.656194],"type":"Point"}
}