{
  "type": "Feature",
  "properties": {
    "addr:full":"179 Hillside Ave New York NY 10040",
    "addr:housenumber":"179",
    "addr:postcode":"10040",
    "addr:street":"Hillside Ave",
    "iso:country":"US",
    "sg:address":"179 Hillside Ave",
    "sg:city":"New York",
    "sg:classifiers":[
        {
            "category":"Bars & Pubs",
            "type":"Food & Drink"
        }
    ],
    "sg:menulink":"http://www.allmenus.com/ny/new-york/49600-happy-garden-restaurant--bar/menu/",
    "sg:phone":"+1 718 523 6280",
    "sg:postcode":"10040",
    "sg:province":"NY",
    "sg:tags":[
        "asian",
        "chinese"
    ],
    "wof:name":"Happy Garden Restaurant & Bar",
    "wof:placetype":"venue"
},
  "geometry": {"coordinates":[-73.925252,40.861308],"type":"Point"}
}