{
  "type": "Feature",
  "properties": {
    "addr:full":"1468 Burlingham Rd Pine Bush NY 12566",
    "addr:housenumber":"1468",
    "addr:postcode":"12566",
    "addr:street":"Burlingham Rd",
    "iso:country":"US",
    "sg:address":"1468 Burlingham Rd",
    "sg:city":"Pine Bush",
    "sg:classifiers":[
        {
            "category":"Building & Trades",
            "subcategory":"Plumbing",
            "type":"Services"
        }
    ],
    "sg:phone":"+1 845 744 6148",
    "sg:postcode":"12566",
    "sg:province":"NY",
    "sg:tags":[
        "contractor"
    ],
    "wof:name":"Dave Starke Plumbing & Htg LLC",
    "wof:placetype":"venue"
},
  "geometry": {"coordinates":[-74.333898,41.613285],"type":"Point"}
}