{
  "type": "Feature",
  "properties": {
    "addr:full":"622 Broadway New York NY 10012",
    "addr:housenumber":"622",
    "addr:postcode":"10012",
    "addr:street":"Broadway",
    "iso:country":"US",
    "sg:address":"622 Broadway",
    "sg:city":"New York",
    "sg:classifiers":[
        {
            "category":"Shopping",
            "subcategory":"Computers & Home Electronics",
            "type":"Retail Goods"
        }
    ],
    "sg:phone":"+1 212 673 4067",
    "sg:postcode":"10012",
    "sg:province":"NY",
    "sg:tags":[
        "supply",
        "electronic",
        "equipment",
        "game",
        "video",
        "rental"
    ],
    "wof:name":"Best Buy",
    "wof:placetype":"venue"
},
  "geometry": {"coordinates":[-73.99619300000001,40.725822],"type":"Point"}
}