{
  "type": "Feature",
  "properties": {
    "iso:country":"US",
    "sg:address":"19 Smith St",
    "sg:city":"Deer Park",
    "sg:classifiers":[
        {
            "category":"Manufacturing",
            "subcategory":"Retail Goods",
            "type":"Manufacturing & Wholesale Goods"
        }
    ],
    "sg:phone":"+1   ",
    "sg:postcode":"11729",
    "sg:province":"NY",
    "sg:tags":[
        "product",
        "mfg"
    ],
    "wof:name":"Diamond Industries",
    "wof:placetype":"venue"
},
  "geometry": {"coordinates":[-73.330251,40.766581],"type":"Point"}
}