{
  "type": "Feature",
  "properties": {
    "addr:full":"3551 85th St Jackson Heights NY 11372",
    "addr:housenumber":"3551",
    "addr:postcode":"11372",
    "addr:street":"85Th St",
    "iso:country":"US",
    "sg:address":"3551 85th St",
    "sg:city":"Jackson Heights",
    "sg:classifiers":[
        {
            "category":"Health Services",
            "subcategory":"Dentist",
            "type":"Services"
        }
    ],
    "sg:phone":"+1 718 779 3949",
    "sg:postcode":"11372",
    "sg:province":"NY",
    "wof:name":"DR Rincon Family Dentistry I PLLC",
    "wof:placetype":"venue"
},
  "geometry": {"coordinates":[-73.881609,40.751588],"type":"Point"}
}