{
  "type": "Feature",
  "properties": {
    "addr:full":"386 Butler St Brooklyn NY 11217",
    "addr:housenumber":"386",
    "addr:postcode":"11217",
    "addr:street":"Butler St",
    "iso:country":"US",
    "sg:address":"386 Butler St",
    "sg:city":"Brooklyn",
    "sg:classifiers":[
        {
            "category":"Arts & Performance",
            "subcategory":"Theater",
            "type":"Entertainment"
        }
    ],
    "sg:phone":"+1 718 857 1334",
    "sg:postcode":"11217",
    "sg:province":"NY",
    "sg:tags":[
        "group"
    ],
    "wof:name":"Free Willie Entertainment Inc",
    "wof:placetype":"venue"
},
  "geometry": {"coordinates":[-73.980633,40.679737],"type":"Point"}
}