{
  "type": "Feature",
  "properties": {
    "addr:full":"1500 Howard Rd Rochester NY 14624",
    "addr:housenumber":"1500",
    "addr:postcode":"14624",
    "addr:street":"Howard Rd",
    "iso:country":"US",
    "sg:address":"1500 Howard Rd",
    "sg:city":"Rochester",
    "sg:classifiers":[
        {
            "category":"Coffee & Tea",
            "type":"Food & Drink"
        },
        {
            "category":"Cafe",
            "type":"Food & Drink"
        }
    ],
    "sg:menulink":"http://www.allmenus.com/ny/gates/19217-cafe-geo/menu/",
    "sg:phone":"+1 585 426 1760",
    "sg:postcode":"14624",
    "sg:province":"NY",
    "sg:tags":[
        "american"
    ],
    "wof:name":"Cafe Geo",
    "wof:placetype":"venue"
},
  "geometry": {"coordinates":[-77.690831,43.13382],"type":"Point"}
}