{
  "type": "Feature",
  "properties": {
    "iso:country":"US",
    "sg:address":"146 Main St",
    "sg:city":"Northport",
    "sg:classifiers":[
        {
            "category":"Retail",
            "subcategory":"Repair Shop",
            "type":"Services"
        }
    ],
    "sg:phone":"+1 631 229 0344",
    "sg:postcode":"11768",
    "sg:province":"NY",
    "sg:tags":[
        "lock",
        "locksmith"
    ],
    "wof:name":"24 Hour Locksmith",
    "wof:placetype":"venue"
},
  "geometry": {"coordinates":[-73.34966300000001,40.900381],"type":"Point"}
}