{
  "type": "Feature",
  "properties": {
    "iso:country":"US",
    "sg:address":"373 McDonald Ave",
    "sg:city":"Brooklyn",
    "sg:classifiers":[
        {
            "category":"Retail",
            "subcategory":"Laundry & Dry Cleaning",
            "type":"Services"
        }
    ],
    "sg:phone":"+1 718 854 4079",
    "sg:postcode":"11218",
    "sg:province":"NY",
    "sg:tags":[
        "drycleaning",
        "plant"
    ],
    "wof:name":"Sals Dry Cleaners",
    "wof:placetype":"venue"
},
  "geometry": {"coordinates":[-73.97930100000001,40.642799],"type":"Point"}
}