{
  "type": "Feature",
  "properties": {
    "iso:country":"US",
    "sg:address":"2864 Rte 112",
    "sg:city":"Medford",
    "sg:classifiers":[
        {
            "category":"Retail",
            "subcategory":"Auto Repair",
            "type":"Services"
        }
    ],
    "sg:phone":"+1 631 698 2600",
    "sg:postcode":"11763",
    "sg:province":"NY",
    "sg:tags":[
        "body",
        "automobile",
        "painting"
    ],
    "wof:name":"All Collision Svc",
    "wof:placetype":"venue"
},
  "geometry": {"coordinates":[-72.9952,40.828342],"type":"Point"}
}