{
  "type": "Feature",
  "properties": {
    "iso:country":"US",
    "sg:address":"17 Heritage Dr",
    "sg:city":"New City",
    "sg:classifiers":[
        {
            "category":"Professional",
            "subcategory":"Lawyer & Legal Services",
            "type":"Services"
        }
    ],
    "sg:phone":"+1   ",
    "sg:postcode":"10956",
    "sg:province":"NY",
    "wof:name":"Sklerov & Associates PC",
    "wof:placetype":"venue"
},
  "geometry": {"coordinates":[-73.987082,41.159835],"type":"Point"}
}