{
  "type": "Feature",
  "properties": {
    "iso:country":"US",
    "sg:address":"123 Hawkins Dr",
    "sg:city":"Montgomery",
    "sg:classifiers":[
        {
            "category":"Personal",
            "subcategory":"Tanning Parlor",
            "type":"Services"
        },
        {
            "category":"Personal",
            "subcategory":"Nail Salon",
            "type":"Services"
        }
    ],
    "sg:phone":"+1 845 457 4180",
    "sg:postcode":"12549",
    "sg:province":"NY",
    "wof:name":"Fantastic Cuts",
    "wof:placetype":"venue"
},
  "geometry": {"coordinates":[-74.213303,41.5117],"type":"Point"}
}