{
  "type": "Feature",
  "properties": {
    "iso:country":"US",
    "sg:address":"258 Middle Country Rd",
    "sg:city":"Selden",
    "sg:classifiers":[
        {
            "category":"Retail",
            "subcategory":"Auto Repair",
            "type":"Services"
        }
    ],
    "sg:phone":"+1 631 736 2222",
    "sg:postcode":"11784",
    "sg:province":"NY",
    "sg:tags":[
        "repairing",
        "automobile"
    ],
    "sg:website":"www.meineke.com",
    "wof:name":"Meineke Car Care Ctr",
    "wof:placetype":"venue"
},
  "geometry": {"coordinates":[-73.03261500000001,40.866826],"type":"Point"}
}