{
  "type": "Feature",
  "properties": {
    "addr:full":"25 St Agnes Ln Albany NY 12211",
    "addr:housenumber":"25",
    "addr:postcode":"12211",
    "addr:street":"St Agnes Ln",
    "iso:country":"US",
    "sg:address":"25 St Agnes Ln",
    "sg:city":"Albany",
    "sg:classifiers":[
        {
            "category":"Communications",
            "type":"Services"
        }
    ],
    "sg:phone":"+1   ",
    "sg:postcode":"12211",
    "sg:province":"NY",
    "sg:tags":[
        "communication"
    ],
    "wof:name":"Rame Communications Inc",
    "wof:placetype":"venue"
},
  "geometry": {"coordinates":[-73.75129,42.676623],"type":"Point"}
}