{
  "type": "Feature",
  "properties": {
    "iso:country":"US",
    "sg:address":"146 E Main St",
    "sg:city":"Angelica",
    "sg:classifiers":[
        {
            "category":"Food & Beverages",
            "subcategory":"Specialty",
            "type":"Retail Goods"
        },
        {
            "category":"Wholesale",
            "subcategory":"Groceries",
            "type":"Manufacturing & Wholesale Goods"
        },
        {
            "category":"Food & Beverages",
            "subcategory":"Groceries & Convenience Stores",
            "type":"Retail Goods"
        }
    ],
    "sg:phone":"+1 585 466 3219",
    "sg:postcode":"14709",
    "sg:province":"NY",
    "sg:tags":[
        "grocers-wholesale",
        "grocers-specialty"
    ],
    "wof:name":"Harris Grocry",
    "wof:placetype":"venue"
},
  "geometry": {"coordinates":[-78.009094,42.304204],"type":"Point"}
}