{
  "type": "Feature",
  "properties": {
    "addr:full":"840 E 134th St Bronx NY 10454",
    "addr:housenumber":"840",
    "addr:postcode":"10454",
    "addr:street":"E 134Th St",
    "iso:country":"US",
    "sg:address":"840 E 134th St",
    "sg:city":"Bronx",
    "sg:classifiers":[
        {
            "category":"Arts & Performance",
            "subcategory":"Theater",
            "type":"Entertainment"
        }
    ],
    "sg:phone":"+1 718 401 2700",
    "sg:postcode":"10454",
    "sg:province":"NY",
    "sg:tags":[
        "equipment",
        "lighting",
        "theatrical",
        "stage"
    ],
    "wof:name":"Royce Lighting",
    "wof:placetype":"venue"
},
  "geometry": {"coordinates":[-73.91118,40.800643],"type":"Point"}
}