{
  "type": "Feature",
  "properties": {
    "addr:full":"8910 37th Avenue Jackson Heights NY 11372",
    "addr:housenumber":"8910",
    "addr:postcode":"11372",
    "addr:street":"37Th Avenue",
    "iso:country":"US",
    "sg:address":"8910 37th Avenue",
    "sg:city":"Jackson Heights",
    "sg:classifiers":[
        {
            "category":"Building & Trades",
            "subcategory":"Locksmith",
            "type":"Services"
        }
    ],
    "sg:phone":"+1 718 807 2457",
    "sg:postcode":"11372",
    "sg:province":"NY",
    "sg:tags":[
        "key"
    ],
    "wof:name":"A Locksmith Business 24 Hrs",
    "wof:placetype":"venue"
},
  "geometry": {"coordinates":[-73.877628,40.750334],"type":"Point"}
}