{
  "type": "Feature",
  "properties": {
    "iso:country":"US",
    "sg:address":"878 New Loudon Rd",
    "sg:city":"Latham",
    "sg:classifiers":[
        {
            "category":"Shopping",
            "subcategory":"Florist",
            "type":"Retail Goods"
        }
    ],
    "sg:phone":"+1 518 782 0136",
    "sg:postcode":"12110",
    "sg:province":"NY",
    "wof:name":"Floral Shoppe & Gifts",
    "wof:placetype":"venue"
},
  "geometry": {"coordinates":[-73.75861999999999,42.754939],"type":"Point"}
}