{
  "type": "Feature",
  "properties": {
    "iso:country":"US",
    "sg:address":"4115 Northern Boulevard",
    "sg:city":"Long Island City",
    "sg:classifiers":[
        {
            "category":"Autos & Motor Vehicles",
            "subcategory":"Auto Supplies",
            "type":"Retail Goods"
        }
    ],
    "sg:phone":"+1 718 729 3500",
    "sg:postcode":"11101",
    "sg:province":"NY",
    "sg:tags":[
        "tire"
    ],
    "wof:name":"Tm & T Tire",
    "wof:placetype":"venue"
},
  "geometry": {"coordinates":[-73.92193399999999,40.753085],"type":"Point"}
}