{
  "type": "Feature",
  "properties": {
    "addr:full":"2 Wheeler Rd Central Islip NY 11722",
    "addr:housenumber":"2",
    "addr:postcode":"11722",
    "addr:street":"Wheeler Rd",
    "iso:country":"US",
    "sg:address":"2 Wheeler Rd",
    "sg:city":"Central Islip",
    "sg:classifiers":[
        {
            "category":"Shopping",
            "subcategory":"Department Store",
            "type":"Retail Goods"
        }
    ],
    "sg:phone":"+1 631 851 0782",
    "sg:postcode":"11722",
    "sg:province":"NY",
    "sg:tags":[
        "shop"
    ],
    "wof:name":"Central Islip Discount/Variety",
    "wof:placetype":"venue"
},
  "geometry": {"coordinates":[-73.202005,40.790655],"type":"Point"}
}