{
  "type": "Feature",
  "properties": {
    "addr:full":"47 N Central Ave Hartsdale NY 10530",
    "addr:housenumber":"47",
    "addr:postcode":"10530",
    "addr:street":"N Central Ave",
    "iso:country":"US",
    "sg:address":"47 N Central Ave",
    "sg:city":"Hartsdale",
    "sg:classifiers":[
        {
            "category":"Professional",
            "subcategory":"Business Services",
            "type":"Services"
        }
    ],
    "sg:phone":"+1 914 285 9124",
    "sg:postcode":"10530",
    "sg:province":"NY",
    "sg:tags":[
        "interior",
        "consultant",
        "design",
        "decorator"
    ],
    "wof:name":"BNV Interiors",
    "wof:placetype":"venue"
},
  "geometry": {"coordinates":[-73.796691,41.020479],"type":"Point"}
}