{
  "type": "Feature",
  "properties": {
    "addr:full":"2333 Rte 112 Medford NY 11763",
    "addr:housenumber":"2333",
    "addr:postcode":"11763",
    "addr:street":"Rte 112",
    "iso:country":"US",
    "sg:address":"2333 Rte 112",
    "sg:city":"Medford",
    "sg:classifiers":[
        {
            "category":"Personal",
            "subcategory":"Beauty Salon",
            "type":"Services"
        }
    ],
    "sg:phone":"+1 631 207 5626",
    "sg:postcode":"11763",
    "sg:province":"NY",
    "sg:tags":[
        "manicuring"
    ],
    "wof:name":"Locomotion",
    "wof:placetype":"venue"
},
  "geometry": {"coordinates":[-72.999833,40.816975],"type":"Point"}
}