{
  "type": "Feature",
  "properties": {
    "iso:country":"US",
    "sg:address":"1060 Western Ave",
    "sg:city":"Albany",
    "sg:classifiers":[
        {
            "category":"Shopping",
            "subcategory":"Gifts & Souvenirs",
            "type":"Retail Goods"
        }
    ],
    "sg:phone":"+1   ",
    "sg:postcode":"12203",
    "sg:province":"NY",
    "wof:name":"Special Items Inc",
    "wof:placetype":"venue"
},
  "geometry": {"coordinates":[-73.816839,42.674354],"type":"Point"}
}