{
  "type": "Feature",
  "properties": {
    "iso:country":"US",
    "sg:address":"122 Henry Street",
    "sg:city":"New York",
    "sg:classifiers":[
        {
            "category":"Education",
            "subcategory":"School",
            "type":"Public Place"
        }
    ],
    "sg:phone":"+1 212 964 0350",
    "sg:postcode":"10002",
    "sg:province":"NY",
    "sg:tags":[
        "high",
        "middle",
        "elementary"
    ],
    "wof:name":"New York City Community School District 2 Region 9",
    "wof:placetype":"venue"
},
  "geometry": {"coordinates":[-73.991432,40.713155],"type":"Point"}
}