{
  "type": "Feature",
  "properties": {
    "addr:full":"135 Northern Pkwy Riverhead NY 11901",
    "addr:housenumber":"135",
    "addr:postcode":"11901",
    "addr:street":"Northern Pkwy",
    "iso:country":"US",
    "sg:address":"135 Northern Pkwy",
    "sg:city":"Riverhead",
    "sg:classifiers":[
        {
            "category":"Building & Trades",
            "subcategory":"Construction",
            "type":"Services"
        }
    ],
    "sg:phone":"+1 631 369 7499",
    "sg:postcode":"11901",
    "sg:province":"NY",
    "sg:tags":[
        "contractor"
    ],
    "wof:name":"Riverhead Estates Inc",
    "wof:placetype":"venue"
},
  "geometry": {"coordinates":[-72.669236,40.928623],"type":"Point"}
}