{
  "type": "Feature",
  "properties": {
    "addr:full":"13216 105th Street Ozone Park NY 11417",
    "addr:housenumber":"13216",
    "addr:postcode":"11417",
    "addr:street":"105Th Street",
    "iso:country":"US",
    "sg:address":"13216 105th Street",
    "sg:city":"Ozone Park",
    "sg:classifiers":[
        {
            "category":"Building & Trades",
            "subcategory":"Construction",
            "type":"Services"
        }
    ],
    "sg:phone":"+1 718 738 5596",
    "sg:postcode":"11417",
    "sg:province":"NY",
    "sg:tags":[
        "contractor"
    ],
    "wof:name":"Kmd Construction",
    "wof:placetype":"venue"
},
  "geometry": {"coordinates":[-73.834774,40.676504],"type":"Point"}
}