{
  "type": "Feature",
  "properties": {
    "iso:country":"US",
    "sg:address":"5166 Main St",
    "sg:city":"Williamsville",
    "sg:classifiers":[
        {
            "category":"Health Services",
            "subcategory":"Doctor",
            "type":"Services"
        }
    ],
    "sg:phone":"+1 716 631 3567",
    "sg:postcode":"14221",
    "sg:province":"NY",
    "sg:tags":[
        "physician",
        "surgeon"
    ],
    "wof:name":"Richard B Narins MD",
    "wof:placetype":"venue"
},
  "geometry": {"coordinates":[-78.759631,42.960456],"type":"Point"}
}