{
  "type": "Feature",
  "properties": {
    "addr:full":"1770 W Main St Riverhead NY 11901",
    "addr:housenumber":"1770",
    "addr:postcode":"11901",
    "addr:street":"W Main St",
    "iso:country":"US",
    "sg:address":"1770 W Main St",
    "sg:city":"Riverhead",
    "sg:classifiers":[
        {
            "category":"Shopping",
            "subcategory":"Discount & Variety Stores",
            "type":"Retail Goods"
        }
    ],
    "sg:phone":"+1 631 208 0078",
    "sg:postcode":"11901",
    "sg:province":"NY",
    "sg:tags":[
        "outlet"
    ],
    "wof:name":"Dkny",
    "wof:placetype":"venue"
},
  "geometry": {"coordinates":[-72.69909699999999,40.916698],"type":"Point"}
}