{
  "type": "Feature",
  "properties": {
    "iso:country":"US",
    "sg:address":"5105 State Hwy 38",
    "sg:city":"Owasco",
    "sg:classifiers":[
        {
            "category":"Organizations",
            "subcategory":"Religious Organization",
            "type":"Services"
        }
    ],
    "sg:phone":"+1 315 784 5047",
    "sg:postcode":"13021",
    "sg:province":"NY",
    "sg:tags":[
        "church"
    ],
    "wof:name":"Owasco Reformed Church",
    "wof:placetype":"venue"
},
  "geometry": {"coordinates":[-76.533159,42.865292],"type":"Point"}
}