{
  "type": "Feature",
  "properties": {
    "iso:country":"US",
    "sg:address":"186 Granny Rd",
    "sg:city":"Farmingville",
    "sg:classifiers":[
        {
            "category":"Health Services",
            "subcategory":"Podiatrist",
            "type":"Services"
        }
    ],
    "sg:phone":"+1 631 736 4272",
    "sg:postcode":"11738",
    "sg:province":"NY",
    "wof:name":"Farmingville Foot Care",
    "wof:placetype":"venue"
},
  "geometry": {"coordinates":[-73.010603,40.839378],"type":"Point"}
}