{
  "type": "Feature",
  "properties": {
    "addr:full":"138 Bayview Ave Port Washington NY 11050",
    "addr:housenumber":"138",
    "addr:postcode":"11050",
    "addr:street":"Bayview Ave",
    "iso:country":"US",
    "sg:address":"138 Bayview Ave",
    "sg:city":"Port Washington",
    "sg:classifiers":[
        {
            "category":"Arts & Performance",
            "subcategory":"Theater",
            "type":"Entertainment"
        }
    ],
    "sg:phone":"+1 516 767 8929",
    "sg:postcode":"11050",
    "sg:province":"NY",
    "sg:tags":[
        "theatrical",
        "bureau"
    ],
    "wof:name":"Magicsong Production Inc",
    "wof:placetype":"venue"
},
  "geometry": {"coordinates":[-73.68822900000001,40.828194],"type":"Point"}
}