{
  "type": "Feature",
  "properties": {
    "addr:full":"110 River St Saranac Lake NY 12983",
    "addr:housenumber":"110",
    "addr:postcode":"12983",
    "addr:street":"River St",
    "iso:country":"US",
    "sg:address":"110 River St",
    "sg:city":"Saranac Lake",
    "sg:classifiers":[
        {
            "category":"Restaurant",
            "type":"Food & Drink"
        }
    ],
    "sg:phone":"+1   ",
    "sg:postcode":"12983",
    "sg:province":"NY",
    "sg:tags":[
        "fast"
    ],
    "wof:name":"Burger King",
    "wof:placetype":"venue"
},
  "geometry": {"coordinates":[-74.125266,44.323736],"type":"Point"}
}