{
  "type": "Feature",
  "properties": {
    "addr:full":"315 Bowery St New York NY 10003",
    "addr:housenumber":"315",
    "addr:postcode":"10003",
    "addr:street":"Bowery St",
    "iso:country":"US",
    "sg:address":"315 Bowery St",
    "sg:city":"New York",
    "sg:classifiers":[
        {
            "category":"Shopping",
            "subcategory":"Clothing, Apparel, & Fashions",
            "type":"Retail Goods"
        }
    ],
    "sg:phone":"+1 212 358 0315",
    "sg:postcode":"10003",
    "sg:province":"NY",
    "sg:tags":[
        "men's",
        "clothing"
    ],
    "sg:website":"www.johnvarvatos.com",
    "wof:name":"John Varvatos",
    "wof:placetype":"venue"
},
  "geometry": {"coordinates":[-73.992127,40.72519],"type":"Point"}
}