{
  "type": "Feature",
  "properties": {
    "iso:country":"US",
    "sg:address":"93 Congress St",
    "sg:city":"Troy",
    "sg:classifiers":[
        {
            "category":"Shopping",
            "subcategory":"Clothing, Apparel, & Fashions",
            "type":"Retail Goods"
        }
    ],
    "sg:phone":"+1 518 687 2332",
    "sg:postcode":"12180",
    "sg:province":"NY",
    "wof:name":"Queen Bee's",
    "wof:placetype":"venue"
},
  "geometry": {"coordinates":[-73.689807,42.728763],"type":"Point"}
}