{
  "type": "Feature",
  "properties": {
    "iso:country":"US",
    "sg:address":"115 Montauk Hwy",
    "sg:city":"Westhampton Bch",
    "sg:classifiers":[
        {
            "category":"Restaurant",
            "type":"Food & Drink"
        }
    ],
    "sg:phone":"+1 631 288 5678",
    "sg:postcode":"11978",
    "sg:province":"NY",
    "wof:name":"Crazy Dog Ice Cream",
    "wof:placetype":"venue"
},
  "geometry": {"coordinates":[-72.64519199999999,40.821734],"type":"Point"}
}