{
  "type": "Feature",
  "properties": {
    "iso:country":"US",
    "sg:address":"3836 Richmond Avenue",
    "sg:city":"Staten Island",
    "sg:classifiers":[
        {
            "category":"Real Estate",
            "subcategory":"Real Estate Services",
            "type":"Services"
        },
        {
            "category":"Banks & Credit Unions",
            "subcategory":"Financial Services",
            "type":"Services"
        }
    ],
    "sg:phone":"+1 718 356 9200",
    "sg:postcode":"10312",
    "sg:province":"NY",
    "sg:tags":[
        "broker",
        "mortgage"
    ],
    "sg:website":"www.volpe-realty.com",
    "wof:name":"Volpe Realty",
    "wof:placetype":"venue"
},
  "geometry": {"coordinates":[-74.165498,40.544642],"type":"Point"}
}