{
  "type": "Feature",
  "properties": {
    "addr:full":"159 W 25th St New York NY 10001",
    "addr:housenumber":"159",
    "addr:postcode":"10001",
    "addr:street":"W 25Th St",
    "iso:country":"US",
    "sg:address":"159 W 25th St",
    "sg:city":"New York",
    "sg:classifiers":[
        {
            "category":"Building & Trades",
            "subcategory":"Construction",
            "type":"Services"
        }
    ],
    "sg:phone":"+1 212 929 2102",
    "sg:postcode":"10001",
    "sg:province":"NY",
    "sg:tags":[
        "company"
    ],
    "wof:name":"Lizbee Construction",
    "wof:placetype":"venue"
},
  "geometry": {"coordinates":[-73.99339999999999,40.74474],"type":"Point"}
}