{
  "type": "Feature",
  "properties": {
    "addr:full":"249 W 18 St New York NY 10011",
    "addr:housenumber":"249",
    "addr:postcode":"10011",
    "addr:street":"W 18 St",
    "iso:country":"US",
    "sg:address":"249 W 18 St",
    "sg:city":"New York",
    "sg:classifiers":[
        {
            "category":"Wholesale",
            "subcategory":"Apparel",
            "type":"Manufacturing & Wholesale Goods"
        }
    ],
    "sg:phone":"+1 212 206 8022",
    "sg:postcode":"10011",
    "sg:province":"NY",
    "sg:tags":[
        "wholesaler",
        "distributor",
        "uniform",
        "accessory"
    ],
    "wof:name":"B Schlesinger & Sons Inc",
    "wof:placetype":"venue"
},
  "geometry": {"coordinates":[-73.999782,40.741826],"type":"Point"}
}