{
  "type": "Feature",
  "properties": {
    "addr:full":"667 Carroll St Brooklyn NY 11215",
    "addr:housenumber":"667",
    "addr:postcode":"11215",
    "addr:street":"Carroll St",
    "iso:country":"US",
    "sg:address":"667 Carroll St",
    "sg:city":"Brooklyn",
    "sg:classifiers":[
        {
            "category":"Shopping",
            "subcategory":"Computers & Home Electronics",
            "type":"Retail Goods"
        }
    ],
    "sg:phone":"+1 718 638 6441",
    "sg:postcode":"11215",
    "sg:province":"NY",
    "sg:tags":[
        "audio"
    ],
    "wof:name":"Integral Systems",
    "wof:placetype":"venue"
},
  "geometry": {"coordinates":[-73.980457,40.675095],"type":"Point"}
}