{
  "type": "Feature",
  "properties": {
    "addr:full":"3976 61st St Woodside NY 11377",
    "addr:housenumber":"3976",
    "addr:postcode":"11377",
    "addr:street":"61St St",
    "iso:country":"US",
    "sg:address":"3976 61st St",
    "sg:city":"Woodside",
    "sg:classifiers":[
        {
            "category":"Bars & Pubs",
            "type":"Food & Drink"
        }
    ],
    "sg:phone":"+1 718 429 8849",
    "sg:postcode":"11377",
    "sg:province":"NY",
    "sg:tags":[
        "brew"
    ],
    "wof:name":"Toucan Tommy",
    "wof:placetype":"venue"
},
  "geometry": {"coordinates":[-73.903667,40.738214],"type":"Point"}
}