{
  "type": "Feature",
  "properties": {
    "iso:country":"US",
    "sg:address":"109 Johns Estate Rd",
    "sg:city":"Pine Bush",
    "sg:classifiers":[
        {
            "category":"Retail",
            "subcategory":"Animal Services",
            "type":"Services"
        }
    ],
    "sg:phone":"+1 845 744 2863",
    "sg:postcode":"12566",
    "sg:province":"NY",
    "wof:name":"Tamarack Manor",
    "wof:placetype":"venue"
},
  "geometry": {"coordinates":[-74.33630700000001,41.610993],"type":"Point"}
}