{
  "type": "Feature",
  "properties": {
    "iso:country":"US",
    "sg:address":"1435 Niagara Falls Blvd",
    "sg:city":"Amherst",
    "sg:classifiers":[
        {
            "category":"Retail",
            "subcategory":"Auto Repair",
            "type":"Services"
        }
    ],
    "sg:phone":"+1 716 836 7049",
    "sg:postcode":"14228",
    "sg:province":"NY",
    "sg:tags":[
        "repairing",
        "automobile"
    ],
    "sg:website":"www.sears.com",
    "wof:name":"Sears Auto & Tire Ctr",
    "wof:placetype":"venue"
},
  "geometry": {"coordinates":[-78.82243800000001,42.993691],"type":"Point"}
}