{
  "type": "Feature",
  "properties": {
    "iso:country":"US",
    "sg:address":"16 Woodland Dr",
    "sg:city":"Port Jervis",
    "sg:classifiers":[
        {
            "category":"Retail",
            "subcategory":"Auto Repair",
            "type":"Services"
        }
    ],
    "sg:phone":"+1 845 856 5702",
    "sg:postcode":"12771",
    "sg:province":"NY",
    "sg:tags":[
        "repairing",
        "automobile"
    ],
    "wof:name":"D & H Garage",
    "wof:placetype":"venue"
},
  "geometry": {"coordinates":[-74.68110799999999,41.359781],"type":"Point"}
}