{
  "type": "Feature",
  "properties": {
    "iso:country":"US",
    "sg:address":"87 Guernsey St",
    "sg:city":"Brooklyn",
    "sg:classifiers":[
        {
            "category":"Building & Trades",
            "subcategory":"Electrical",
            "type":"Services"
        }
    ],
    "sg:phone":"+1 718 388 2460",
    "sg:postcode":"11222",
    "sg:province":"NY",
    "sg:tags":[
        "general",
        "electrical",
        "contractor"
    ],
    "wof:name":"Gary Electric Corp",
    "wof:placetype":"venue"
},
  "geometry": {"coordinates":[-73.953114,40.723923],"type":"Point"}
}