{
  "type": "Feature",
  "properties": {
    "iso:country":"US",
    "sg:address":"350 Kisco Ave",
    "sg:city":"Mt Kisco",
    "sg:classifiers":[
        {
            "category":"Shopping",
            "subcategory":"Stationery & Office Supplies",
            "type":"Retail Goods"
        }
    ],
    "sg:phone":"+1 914 242 2106",
    "sg:postcode":"10549",
    "sg:province":"NY",
    "wof:name":"Staples",
    "wof:placetype":"venue"
},
  "geometry": {"coordinates":[-73.726794,41.22007],"type":"Point"}
}