{
  "type": "Feature",
  "properties": {
    "addr:full":"7747 River Rd Baldwinsville NY 13027",
    "addr:housenumber":"7747",
    "addr:postcode":"13027",
    "addr:street":"River Rd",
    "iso:country":"US",
    "sg:address":"7747 River Rd",
    "sg:city":"Baldwinsville",
    "sg:classifiers":[
        {
            "category":"Building & Trades",
            "subcategory":"Construction",
            "type":"Services"
        }
    ],
    "sg:phone":"+1 315 727 5287",
    "sg:postcode":"13027",
    "sg:province":"NY",
    "sg:tags":[
        "general",
        "contractor"
    ],
    "wof:name":"Onondaga Builders Inc",
    "wof:placetype":"venue"
},
  "geometry": {"coordinates":[-76.264532,43.146897],"type":"Point"}
}