{
  "type": "Feature",
  "properties": {
    "addr:full":"180 Rutledge St Brooklyn NY 11211",
    "addr:housenumber":"180",
    "addr:postcode":"11211",
    "addr:street":"Rutledge St",
    "iso:country":"US",
    "sg:address":"180 Rutledge St",
    "sg:city":"Brooklyn",
    "sg:classifiers":[
        {
            "category":"Organizations",
            "subcategory":"Religious Organization",
            "type":"Services"
        }
    ],
    "sg:phone":"+1 718 388 4293",
    "sg:postcode":"11211",
    "sg:province":"NY",
    "sg:tags":[
        "clergy"
    ],
    "wof:name":"Chaim Gross",
    "wof:placetype":"venue"
},
  "geometry": {"coordinates":[-73.954745,40.70339],"type":"Point"}
}