{
  "type": "Feature",
  "properties": {
    "addr:full":"5280 Wells Curtice Rd Canandaigua NY 14424",
    "addr:housenumber":"5280",
    "addr:postcode":"14424",
    "addr:street":"Wells Curtice Rd",
    "iso:country":"US",
    "sg:address":"5280 Wells Curtice Rd",
    "sg:city":"Canandaigua",
    "sg:classifiers":[
        {
            "category":"Professional",
            "subcategory":"Lawyer & Legal Services",
            "type":"Services"
        }
    ],
    "sg:phone":"+1 585 394 3088",
    "sg:postcode":"14424",
    "sg:province":"NY",
    "sg:tags":[
        "attorney"
    ],
    "wof:name":"L Edward Monaghan",
    "wof:placetype":"venue"
},
  "geometry": {"coordinates":[-77.30277599999999,42.801213],"type":"Point"}
}