{
  "type": "Feature",
  "properties": {
    "addr:full":"500 Grand St New York NY 10002",
    "addr:housenumber":"500",
    "addr:postcode":"10002",
    "addr:street":"Grand St",
    "iso:country":"US",
    "sg:address":"500 Grand St",
    "sg:city":"New York",
    "sg:classifiers":[
        {
            "category":"Real Estate",
            "subcategory":"Developer",
            "type":"Services"
        }
    ],
    "sg:phone":"+1 212 673 0253",
    "sg:postcode":"10002",
    "sg:province":"NY",
    "wof:name":"Afco Development LLC",
    "wof:placetype":"venue"
},
  "geometry": {"coordinates":[-73.982761,40.714879],"type":"Point"}
}