{
  "type": "Feature",
  "properties": {
    "iso:country":"US",
    "sg:address":"340 W 12 St",
    "sg:city":"New York",
    "sg:classifiers":[
        {
            "category":"Banks & Credit Unions",
            "subcategory":"Investment Brokerage",
            "type":"Services"
        }
    ],
    "sg:phone":"+1 212 421 5244",
    "sg:postcode":"10014",
    "sg:province":"NY",
    "wof:name":"Colleen Investment LLC",
    "wof:placetype":"venue"
},
  "geometry": {"coordinates":[-74.00773700000001,40.737477],"type":"Point"}
}