{
  "type": "Feature",
  "properties": {
    "addr:full":"138 Sterling St Watertown NY 13601",
    "addr:housenumber":"138",
    "addr:postcode":"13601",
    "addr:street":"Sterling St",
    "iso:country":"US",
    "sg:address":"138 Sterling St",
    "sg:city":"Watertown",
    "sg:classifiers":[
        {
            "category":"Organizations",
            "subcategory":"Community Association",
            "type":"Services"
        }
    ],
    "sg:phone":"+1 315 788 0911",
    "sg:postcode":"13601",
    "sg:province":"NY",
    "sg:tags":[
        "military"
    ],
    "wof:name":"American Legion",
    "wof:placetype":"venue"
},
  "geometry": {"coordinates":[-75.90966,43.972229],"type":"Point"}
}