{
  "type": "Feature",
  "properties": {
    "addr:full":"388 Greenwich St New York NY 10013",
    "addr:housenumber":"388",
    "addr:postcode":"10013",
    "addr:street":"Greenwich St",
    "iso:country":"US",
    "sg:address":"388 Greenwich St",
    "sg:city":"New York",
    "sg:classifiers":[
        {
            "category":"Professional",
            "subcategory":"Employment Agencies",
            "type":"Services"
        }
    ],
    "sg:phone":"+1 212 816 2703",
    "sg:postcode":"10013",
    "sg:province":"NY",
    "sg:tags":[
        "help",
        "supply"
    ],
    "wof:name":"Adecco Staffing",
    "wof:placetype":"venue"
},
  "geometry": {"coordinates":[-74.010201,40.720338],"type":"Point"}
}