{
  "type": "Feature",
  "properties": {
    "addr:full":"200 E End Ave New York NY 10128",
    "addr:housenumber":"200",
    "addr:postcode":"10128",
    "addr:street":"E End Ave",
    "iso:country":"US",
    "sg:address":"200 E End Ave",
    "sg:city":"New York",
    "sg:classifiers":[
        {
            "category":"Manufacturing",
            "subcategory":"Printing",
            "type":"Manufacturing & Wholesale Goods"
        }
    ],
    "sg:phone":"+1 212 423 1171",
    "sg:postcode":"10128",
    "sg:province":"NY",
    "sg:tags":[
        "publisher",
        "guide"
    ],
    "wof:name":"Center For Collaborative",
    "wof:placetype":"venue"
},
  "geometry": {"coordinates":[-73.94291200000001,40.777492],"type":"Point"}
}