{
  "type": "Feature",
  "properties": {
    "addr:full":"200 E 15 St New York NY 10003",
    "addr:housenumber":"200;15",
    "addr:postcode":"10003",
    "addr:street":"E;St",
    "iso:country":"US",
    "sg:address":"200 E 15 St",
    "sg:city":"New York",
    "sg:classifiers":[
        {
            "category":"Retail",
            "subcategory":"Repair Shop",
            "type":"Services"
        }
    ],
    "sg:phone":"+1 917 477 6021",
    "sg:postcode":"10003",
    "sg:province":"NY",
    "sg:tags":[
        "lock",
        "locksmith"
    ],
    "wof:name":"24 Hour 7 Day Emerg Locksmith",
    "wof:placetype":"venue"
},
  "geometry": {"coordinates":[-73.985242,40.733371],"type":"Point"}
}