{
  "type": "Feature",
  "properties": {
    "iso:country":"US",
    "sg:address":"45 W 34th Street",
    "sg:city":"New York",
    "sg:classifiers":[
        {
            "category":"Professional",
            "subcategory":"Lawyer & Legal Services",
            "type":"Services"
        }
    ],
    "sg:phone":"+1 212 947 1919",
    "sg:postcode":"10001",
    "sg:province":"NY",
    "wof:name":"Cohen Richard L",
    "wof:placetype":"venue"
},
  "geometry": {"coordinates":[-73.98773,40.749795],"type":"Point"}
}