{
  "type": "Feature",
  "properties": {
    "addr:full":"1302 Watson Blvd Endicott NY 13760",
    "addr:housenumber":"1302",
    "addr:postcode":"13760",
    "addr:street":"Watson Blvd",
    "iso:country":"US",
    "sg:address":"1302 Watson Blvd",
    "sg:city":"Endicott",
    "sg:classifiers":[
        {
            "category":"Travel",
            "subcategory":"Hotels & Motels",
            "type":"Entertainment"
        }
    ],
    "sg:phone":"+1 607 748 1551",
    "sg:postcode":"13760",
    "sg:province":"NY",
    "wof:name":"Gance's Motel",
    "wof:placetype":"venue"
},
  "geometry": {"coordinates":[-76.046977,42.109231],"type":"Point"}
}