{
  "type": "Feature",
  "properties": {
    "addr:full":"35 Neptune Avenue Brooklyn NY 11235",
    "addr:housenumber":"35",
    "addr:postcode":"11235",
    "addr:street":"Neptune Avenue",
    "iso:country":"US",
    "sg:address":"35 Neptune Avenue",
    "sg:city":"Brooklyn",
    "sg:classifiers":[
        {
            "category":"Retail",
            "subcategory":"Auto Rental",
            "type":"Services"
        }
    ],
    "sg:phone":"+1 718 421 2277",
    "sg:postcode":"11235",
    "sg:province":"NY",
    "sg:tags":[
        "car"
    ],
    "sg:website":"www.regencyleasing.com",
    "wof:name":"Regency Leasing",
    "wof:placetype":"venue"
},
  "geometry": {"coordinates":[-73.955384,40.582754],"type":"Point"}
}