{
  "type": "Feature",
  "properties": {
    "addr:full":"338 Washington St Newburgh NY 12550",
    "addr:housenumber":"338",
    "addr:postcode":"12550",
    "addr:street":"Washington St",
    "iso:country":"US",
    "sg:address":"338 Washington St",
    "sg:city":"Newburgh",
    "sg:classifiers":[
        {
            "category":"Building & Trades",
            "subcategory":"Construction",
            "type":"Services"
        }
    ],
    "sg:phone":"+1 845 561 5262",
    "sg:postcode":"12550",
    "sg:province":"NY",
    "sg:tags":[
        "dry wall",
        "contractor"
    ],
    "wof:name":"Atlantic Drywall Corp",
    "wof:placetype":"venue"
},
  "geometry": {"coordinates":[-74.025943,41.499433],"type":"Point"}
}