{
  "type": "Feature",
  "properties": {
    "addr:full":"1048 Castle Hill Ave Bronx NY 10472",
    "addr:housenumber":"1048",
    "addr:postcode":"10472",
    "addr:street":"Castle Hill Ave",
    "iso:country":"US",
    "sg:address":"1048 Castle Hill Ave",
    "sg:city":"Bronx",
    "sg:classifiers":[
        {
            "category":"Personal",
            "subcategory":"Barber",
            "type":"Services"
        }
    ],
    "sg:phone":"+1 718 822 1765",
    "sg:postcode":"10472",
    "sg:province":"NY",
    "wof:name":"Touch Up",
    "wof:placetype":"venue"
},
  "geometry": {"coordinates":[-73.850123,40.828828],"type":"Point"}
}