{
  "type": "Feature",
  "properties": {
    "iso:country":"US",
    "sg:address":"2985 Lakeview Rd",
    "sg:city":"Hamburg",
    "sg:classifiers":[
        {
            "category":"Organizations",
            "subcategory":"Community Association",
            "type":"Services"
        }
    ],
    "sg:phone":"+1   ",
    "sg:postcode":"14075",
    "sg:province":"NY",
    "sg:tags":[
        "civic",
        "social"
    ],
    "wof:name":"Hamburg Lkshore Ovrseas Vtrans",
    "wof:placetype":"venue"
},
  "geometry": {"coordinates":[-78.879222,42.715487],"type":"Point"}
}