{
  "type": "Feature",
  "properties": {
    "addr:full":"106 W Ramapo Rd Garnerville NY 10923",
    "addr:housenumber":"106",
    "addr:postcode":"10923",
    "addr:street":"W Ramapo Rd",
    "iso:country":"US",
    "sg:address":"106 W Ramapo Rd",
    "sg:city":"Garnerville",
    "sg:classifiers":[
        {
            "category":"Autos & Motor Vehicles",
            "subcategory":"Auto Supplies",
            "type":"Retail Goods"
        }
    ],
    "sg:phone":"+1 845 362 3050",
    "sg:postcode":"10923",
    "sg:province":"NY",
    "sg:tags":[
        "automobile",
        "parts"
    ],
    "wof:name":"Advanced Automotive Design Crp",
    "wof:placetype":"venue"
},
  "geometry": {"coordinates":[-74.01042099999999,41.19724],"type":"Point"}
}