{
  "type": "Feature",
  "properties": {
    "iso:country":"US",
    "sg:address":"90 S Portage St",
    "sg:city":"Westfield",
    "sg:classifiers":[
        {
            "category":"Home & Garden",
            "subcategory":"Building Materials",
            "type":"Retail Goods"
        }
    ],
    "sg:phone":"+1   ",
    "sg:postcode":"14787",
    "sg:province":"NY",
    "wof:name":"L H C Inc",
    "wof:placetype":"venue"
},
  "geometry": {"coordinates":[-79.57601,42.317679],"type":"Point"}
}