{
  "type": "Feature",
  "properties": {
    "addr:full":"770 Lexington Ave New York NY 10065",
    "addr:housenumber":"770",
    "addr:postcode":"10065",
    "addr:street":"Lexington Ave",
    "iso:country":"US",
    "sg:address":"770 Lexington Ave",
    "sg:city":"New York",
    "sg:classifiers":[
        {
            "category":"Professional",
            "subcategory":"Lawyer & Legal Services",
            "type":"Services"
        }
    ],
    "sg:phone":"+1 212 935 6000",
    "sg:postcode":"10065",
    "sg:province":"NY",
    "wof:name":"Bab Donald atty",
    "wof:placetype":"venue"
},
  "geometry": {"coordinates":[-73.96771099999999,40.763135],"type":"Point"}
}