{
  "type": "Feature",
  "properties": {
    "addr:full":"439 E 6th St New York NY 10079",
    "addr:housenumber":"439",
    "addr:postcode":"10079",
    "addr:street":"E 6Th St",
    "iso:country":"US",
    "sg:address":"439 E 6th St",
    "sg:city":"New York",
    "sg:classifiers":[
        {
            "category":"Shopping",
            "subcategory":"Music",
            "type":"Retail Goods"
        }
    ],
    "sg:phone":"+1 212 473 2870",
    "sg:postcode":"10079",
    "sg:province":"NY",
    "sg:tags":[
        "dvd's"
    ],
    "wof:name":"A1 Records",
    "wof:placetype":"venue"
},
  "geometry": {"coordinates":[-73.985297,40.726032],"type":"Point"}
}