{
  "type": "Feature",
  "properties": {
    "addr:full":"404 5th Avenue New York NY 10018",
    "addr:housenumber":"404",
    "addr:postcode":"10018",
    "addr:street":"5Th Avenue",
    "iso:country":"US",
    "sg:address":"404 5th Avenue",
    "sg:city":"New York",
    "sg:classifiers":[
        {
            "category":"Health Services",
            "subcategory":"Hospital",
            "type":"Services"
        }
    ],
    "sg:phone":"+1 212 736 0227",
    "sg:postcode":"10018",
    "sg:province":"NY",
    "sg:website":"www.jewishhome.org",
    "wof:name":"The Jewish Home & Hospital",
    "wof:placetype":"venue"
},
  "geometry": {"coordinates":[-73.98325,40.750189],"type":"Point"}
}