{
  "type": "Feature",
  "properties": {
    "addr:full":"1800 Grand Concourse Bronx NY 10457",
    "addr:housenumber":"1800",
    "addr:postcode":"10457",
    "addr:street":"Grand Concourse",
    "iso:country":"US",
    "sg:address":"1800 Grand Concourse",
    "sg:city":"Bronx",
    "sg:classifiers":[
        {
            "category":"Organizations",
            "subcategory":"Religious Organization",
            "type":"Services"
        }
    ],
    "sg:phone":"+1 718 716 5552",
    "sg:postcode":"10457",
    "sg:province":"NY",
    "sg:tags":[
        "church"
    ],
    "wof:name":"Pilgrim United Church Of God",
    "wof:placetype":"venue"
},
  "geometry": {"coordinates":[-73.90562,40.849925],"type":"Point"}
}