{
  "type": "Feature",
  "properties": {
    "addr:full":"16 Avenue T Brooklyn NY 11223",
    "addr:housenumber":"16",
    "addr:postcode":"11223",
    "addr:street":"Avenue T",
    "iso:country":"US",
    "sg:address":"16 Avenue T",
    "sg:city":"Brooklyn",
    "sg:classifiers":[
        {
            "category":"Health Services",
            "subcategory":"Doctor",
            "type":"Services"
        }
    ],
    "sg:phone":"+1 718 372 3539",
    "sg:postcode":"11223",
    "sg:province":"NY",
    "wof:name":"Benanti Philip E DO PC",
    "wof:placetype":"venue"
},
  "geometry": {"coordinates":[-73.9851,40.597801],"type":"Point"}
}