{
  "type": "Feature",
  "properties": {
    "addr:full":"1601 Bronxdale Ave Bronx NY 10462",
    "addr:housenumber":"1601",
    "addr:postcode":"10462",
    "addr:street":"Bronxdale Ave",
    "iso:country":"US",
    "sg:address":"1601 Bronxdale Ave",
    "sg:city":"Bronx",
    "sg:classifiers":[
        {
            "category":"Autos & Motor Vehicles",
            "subcategory":"Auto Supplies",
            "type":"Retail Goods"
        }
    ],
    "sg:phone":"+1 718 518 7400",
    "sg:postcode":"10462",
    "sg:province":"NY",
    "sg:tags":[
        "automobile",
        "parts"
    ],
    "sg:website":"www.wawparts.com",
    "wof:name":"Woodbury Warehouse Inc",
    "wof:placetype":"venue"
},
  "geometry": {"coordinates":[-73.858519,40.844894],"type":"Point"}
}