{
  "type": "Feature",
  "properties": {
    "addr:full":"194 Deer Park Ave Babylon NY 11702",
    "addr:housenumber":"194",
    "addr:postcode":"11702",
    "addr:street":"Deer Park Ave",
    "iso:country":"US",
    "sg:address":"194 Deer Park Ave",
    "sg:city":"Babylon",
    "sg:classifiers":[
        {
            "category":"Health Services",
            "subcategory":"Chiropractor",
            "type":"Services"
        }
    ],
    "sg:phone":"+1 631 321 6300",
    "sg:postcode":"11702",
    "sg:province":"NY",
    "wof:name":"Amdur Chiropractic PC",
    "wof:placetype":"venue"
},
  "geometry": {"coordinates":[-73.32244300000001,40.700193],"type":"Point"}
}