{
  "type": "Feature",
  "properties": {
    "iso:country":"US",
    "sg:address":"480 Patchogue-Holbrook Rd",
    "sg:city":"Holbrook",
    "sg:classifiers":[
        {
            "category":"Sports & Exercise",
            "subcategory":"Gym",
            "type":"Entertainment"
        }
    ],
    "sg:phone":"+1 631 472 8300",
    "sg:postcode":"11741",
    "sg:province":"NY",
    "sg:tags":[
        "club",
        "health",
        "studio",
        "gymnasium"
    ],
    "wof:name":"Curves",
    "wof:placetype":"venue"
},
  "geometry": {"coordinates":[-73.08250700000001,40.813888],"type":"Point"}
}