{
  "type": "Feature",
  "properties": {
    "addr:full":"11700 Grove St Delevan NY 14042",
    "addr:housenumber":"11700",
    "addr:postcode":"14042",
    "addr:street":"Grove St",
    "iso:country":"US",
    "sg:address":"11700 Grove St",
    "sg:city":"Delevan",
    "sg:classifiers":[
        {
            "category":"Manufacturing",
            "subcategory":"Lumber",
            "type":"Manufacturing & Wholesale Goods"
        }
    ],
    "sg:phone":"+1   ",
    "sg:postcode":"14042",
    "sg:province":"NY",
    "sg:tags":[
        "logging"
    ],
    "wof:name":"Delaneys Logging & Trucking",
    "wof:placetype":"venue"
},
  "geometry": {"coordinates":[-78.48966799999999,42.511278],"type":"Point"}
}