{
  "type": "Feature",
  "properties": {
    "addr:full":"336 E 69 St New York NY 10021",
    "addr:housenumber":"336;69",
    "addr:postcode":"10021",
    "addr:street":"E;St",
    "iso:country":"US",
    "sg:address":"336 E 69 St",
    "sg:city":"New York",
    "sg:classifiers":[
        {
            "category":"Organizations",
            "subcategory":"Non-profit Organization",
            "type":"Services"
        },
        {
            "category":"Professional",
            "subcategory":"Management & Consulting",
            "type":"Services"
        }
    ],
    "sg:phone":"+1 212 861 5911",
    "sg:postcode":"10021",
    "sg:province":"NY",
    "sg:tags":[
        "public",
        "relations"
    ],
    "wof:name":"International Debutantes Ball",
    "wof:placetype":"venue"
},
  "geometry": {"coordinates":[-73.958106,40.766169],"type":"Point"}
}