{
  "type": "Feature",
  "properties": {
    "addr:full":"3986 Lockport Olcott Rd Lockport NY 14094",
    "addr:housenumber":"3986",
    "addr:postcode":"14094",
    "addr:street":"Olcott Rd",
    "iso:country":"US",
    "sg:address":"3986 Lockport Olcott Rd",
    "sg:city":"Lockport",
    "sg:classifiers":[
        {
            "category":"Restaurant",
            "type":"Food & Drink"
        }
    ],
    "sg:phone":"+1 716 433 4477",
    "sg:postcode":"14094",
    "sg:province":"NY",
    "sg:website":"www.subway.com",
    "wof:name":"Subway Sandwiches & Salads",
    "wof:placetype":"venue"
},
  "geometry": {"coordinates":[-78.67714700000001,43.223888],"type":"Point"}
}