{
  "type": "Feature",
  "properties": {
    "addr:full":"341 Park Ave Corning NY 14830",
    "addr:housenumber":"341",
    "addr:postcode":"14830",
    "addr:street":"Park Ave",
    "iso:country":"US",
    "sg:address":"341 Park Ave",
    "sg:city":"Corning",
    "sg:classifiers":[
        {
            "category":"Insurance",
            "subcategory":"Insurance Agent",
            "type":"Services"
        }
    ],
    "sg:phone":"+1 607 962 6866",
    "sg:postcode":"14830",
    "sg:province":"NY",
    "wof:name":"State Farm Insurance",
    "wof:placetype":"venue"
},
  "geometry": {"coordinates":[-77.036491,42.131659],"type":"Point"}
}