{
  "type": "Feature",
  "properties": {
    "addr:full":"539 5th Ave Brooklyn NY 11215",
    "addr:housenumber":"539",
    "addr:postcode":"11215",
    "addr:street":"5Th Ave",
    "iso:country":"US",
    "sg:address":"539 5th Ave",
    "sg:city":"Brooklyn",
    "sg:classifiers":[
        {
            "category":"Food & Beverages",
            "subcategory":"Liquor & Beverages",
            "type":"Retail Goods"
        }
    ],
    "sg:phone":"+1 718 768 5402",
    "sg:postcode":"11215",
    "sg:province":"NY",
    "sg:tags":[
        "store"
    ],
    "wof:name":"Bay River Wines & Liquors",
    "wof:placetype":"venue"
},
  "geometry": {"coordinates":[-73.989172,40.665647],"type":"Point"}
}