{
  "type": "Feature",
  "properties": {
    "addr:full":"86 N Division St St Johnsville NY 13452",
    "addr:housenumber":"86",
    "addr:postcode":"13452",
    "addr:street":"N Division St",
    "iso:country":"US",
    "sg:address":"86 N Division St",
    "sg:city":"St Johnsville",
    "sg:classifiers":[
        {
            "category":"Autos & Motor Vehicles",
            "subcategory":"Automobile Sales",
            "type":"Retail Goods"
        }
    ],
    "sg:phone":"+1 518 568 2905",
    "sg:postcode":"13452",
    "sg:province":"NY",
    "sg:tags":[
        "car",
        "dealer"
    ],
    "wof:name":"Family Ties Auto Sales",
    "wof:placetype":"venue"
},
  "geometry": {"coordinates":[-74.67839499999999,43.004102],"type":"Point"}
}