{
  "type": "Feature",
  "properties": {
    "iso:country":"US",
    "sg:address":"460 Park Ave",
    "sg:city":"New York",
    "sg:classifiers":[
        {
            "category":"Banks & Credit Unions",
            "subcategory":"Bank",
            "type":"Services"
        }
    ],
    "sg:phone":"+1 212 753 5880",
    "sg:postcode":"10022",
    "sg:province":"NY",
    "wof:name":"Citibank",
    "wof:placetype":"venue"
},
  "geometry": {"coordinates":[-73.970417,40.762154],"type":"Point"}
}