{
  "type": "Feature",
  "properties": {
    "addr:full":"19 River St Chateaugay NY 12983",
    "addr:housenumber":"19",
    "addr:postcode":"12983",
    "addr:street":"River St",
    "iso:country":"US",
    "sg:address":"19 River St",
    "sg:city":"Chateaugay",
    "sg:classifiers":[
        {
            "category":"Government",
            "subcategory":"Post Office",
            "type":"Public Place"
        }
    ],
    "sg:phone":"+1 518 497 6012",
    "sg:postcode":"12983",
    "sg:province":"NY",
    "wof:name":"US Post Office",
    "wof:placetype":"venue"
},
  "geometry": {"coordinates":[-74.079673,44.926519],"type":"Point"}
}