{
  "type": "Feature",
  "properties": {
    "addr:full":"2107 Palmer Ave Larchmont NY 10538",
    "addr:housenumber":"2107",
    "addr:postcode":"10538",
    "addr:street":"Palmer Ave",
    "iso:country":"US",
    "sg:address":"2107 Palmer Ave",
    "sg:city":"Larchmont",
    "sg:classifiers":[
        {
            "category":"Autos & Motor Vehicles",
            "subcategory":"Fuel & Gas Station",
            "type":"Retail Goods"
        }
    ],
    "sg:phone":"+1 914 834 8006",
    "sg:postcode":"10538",
    "sg:province":"NY",
    "sg:tags":[
        "oil"
    ],
    "wof:name":"Glacomo Service II",
    "wof:placetype":"venue"
},
  "geometry": {"coordinates":[-73.76418200000001,40.92891],"type":"Point"}
}