{
  "type": "Feature",
  "properties": {
    "addr:full":"358 W 44th St New York NY 10036",
    "addr:housenumber":"358",
    "addr:postcode":"10036",
    "addr:street":"W 44Th St",
    "iso:country":"US",
    "sg:address":"358 W 44th St",
    "sg:city":"New York",
    "sg:classifiers":[
        {
            "category":"Personal",
            "type":"Services"
        }
    ],
    "sg:phone":"+1 212 492 9673",
    "sg:postcode":"10036",
    "sg:province":"NY",
    "sg:tags":[
        "towing"
    ],
    "wof:name":"A 24 Hrs Emergency Towing",
    "wof:placetype":"venue"
},
  "geometry": {"coordinates":[-73.9907,40.759201],"type":"Point"}
}