{
  "type": "Feature",
  "properties": {
    "iso:country":"US",
    "sg:address":"5259 Decker Rd",
    "sg:city":"Marion",
    "sg:classifiers":[
        {
            "category":"Farming",
            "subcategory":"Farm",
            "type":"Manufacturing & Wholesale Goods"
        }
    ],
    "sg:phone":"+1 315 331 1184",
    "sg:postcode":"14505",
    "sg:province":"NY",
    "sg:tags":[
        "crop",
        "general"
    ],
    "wof:name":"Howard Faro",
    "wof:placetype":"venue"
},
  "geometry": {"coordinates":[-77.12973100000001,43.130333],"type":"Point"}
}