{
  "type": "Feature",
  "properties": {
    "iso:country":"US",
    "sg:address":"577 New Lots Ave",
    "sg:city":"Brooklyn",
    "sg:classifiers":[
        {
            "category":"Food & Beverages",
            "subcategory":"Groceries & Convenience Stores",
            "type":"Retail Goods"
        }
    ],
    "sg:phone":"+1 718 495 5200",
    "sg:postcode":"11207",
    "sg:province":"NY",
    "sg:tags":[
        "product"
    ],
    "wof:name":"Basil Leaf Intl Foods Inc",
    "wof:placetype":"venue"
},
  "geometry": {"coordinates":[-73.887812,40.664202],"type":"Point"}
}