{
  "type": "Feature",
  "properties": {
    "addr:full":"742 Elm St Groton NY 13073",
    "addr:housenumber":"742",
    "addr:postcode":"13073",
    "addr:street":"Elm St",
    "iso:country":"US",
    "sg:address":"742 Elm St",
    "sg:city":"Groton",
    "sg:classifiers":[
        {
            "category":"Transit Center",
            "subcategory":"Freight",
            "type":"Transportation"
        },
        {
            "category":"Freight",
            "type":"Transportation"
        }
    ],
    "sg:phone":"+1 607 898 9704",
    "sg:postcode":"13073",
    "sg:province":"NY",
    "sg:tags":[
        "local",
        "trucking-motor",
        "trucking"
    ],
    "wof:name":"William J Bartos",
    "wof:placetype":"venue"
},
  "geometry": {"coordinates":[-76.34799700000001,42.584795],"type":"Point"}
}