{
  "type": "Feature",
  "properties": {
    "iso:country":"US",
    "sg:address":"395 Fort Salonga Rd",
    "sg:city":"Northport",
    "sg:classifiers":[
        {
            "category":"Personal",
            "type":"Services"
        },
        {
            "category":"Sports & Exercise",
            "subcategory":"Gym",
            "type":"Entertainment"
        }
    ],
    "sg:phone":"+1 631 604 4453",
    "sg:postcode":"11768",
    "sg:province":"NY",
    "sg:tags":[
        "trainer",
        "consultant",
        "physical",
        "fitness"
    ],
    "wof:name":"FT Northport",
    "wof:placetype":"venue"
},
  "geometry": {"coordinates":[-73.34016800000001,40.892235],"type":"Point"}
}