{
  "type": "Feature",
  "properties": {
    "iso:country":"US",
    "sg:address":"613 Washington Ave",
    "sg:city":"Brooklyn",
    "sg:classifiers":[
        {
            "category":"Retail",
            "subcategory":"Auto Repair",
            "type":"Services"
        }
    ],
    "sg:phone":"+1 718 789 8533",
    "sg:postcode":"11238",
    "sg:province":"NY",
    "sg:tags":[
        "repairing",
        "tire"
    ],
    "wof:name":"Hercules Tire Shop",
    "wof:placetype":"venue"
},
  "geometry": {"coordinates":[-73.96383899999999,40.678607],"type":"Point"}
}