{
  "type": "Feature",
  "properties": {
    "iso:country":"US",
    "sg:address":"3514 Avenue S",
    "sg:city":"Brooklyn",
    "sg:classifiers":[
        {
            "category":"Shopping",
            "subcategory":"Party Supplies",
            "type":"Retail Goods"
        },
        {
            "category":"Personal",
            "type":"Services"
        }
    ],
    "sg:phone":"+1 718 998 6420",
    "sg:postcode":"11234",
    "sg:province":"NY",
    "sg:tags":[
        "planning",
        "event"
    ],
    "sg:website":"www.jrballoon.com",
    "wof:name":"J&R Wholesale Balloon Distributors, LLC",
    "wof:placetype":"venue"
},
  "geometry": {"coordinates":[-73.93197499999999,40.609339],"type":"Point"}
}