{
  "type": "Feature",
  "properties": {
    "iso:country":"US",
    "sg:address":"418 S Marginal Rd",
    "sg:city":"Jericho",
    "sg:classifiers":[
        {
            "category":"Professional",
            "subcategory":"Employment Agencies",
            "type":"Services"
        }
    ],
    "sg:phone":"+1 516 433 4900",
    "sg:postcode":"11753",
    "sg:province":"NY",
    "sg:tags":[
        "opportunity"
    ],
    "wof:name":"Principal Asset",
    "wof:placetype":"venue"
},
  "geometry": {"coordinates":[-73.53862100000001,40.783731],"type":"Point"}
}