{
  "type": "Feature",
  "properties": {
    "iso:country":"US",
    "sg:address":"400 Jericho Tpke",
    "sg:city":"Jericho",
    "sg:classifiers":[
        {
            "category":"Professional",
            "subcategory":"Lawyer & Legal Services",
            "type":"Services"
        }
    ],
    "sg:phone":"+1 516 931 4088",
    "sg:postcode":"11753",
    "sg:province":"NY",
    "wof:name":"Moskowitz Michael L Atty",
    "wof:placetype":"venue"
},
  "geometry": {"coordinates":[-73.53449999999999,40.795502],"type":"Point"}
}