{
  "type": "Feature",
  "properties": {
    "addr:full":"11 The Oaks Roslyn NY 11576",
    "addr:housenumber":"11",
    "addr:postcode":"11576",
    "addr:street":"The Oaks",
    "iso:country":"US",
    "sg:address":"11 The Oaks",
    "sg:city":"Roslyn",
    "sg:classifiers":[
        {
            "category":"Professional",
            "subcategory":"Engineering",
            "type":"Services"
        }
    ],
    "sg:phone":"+1 516 621 7402",
    "sg:postcode":"11576",
    "sg:province":"NY",
    "sg:tags":[
        "equipment",
        "supply"
    ],
    "wof:name":"Cargo Machinery Inc",
    "wof:placetype":"venue"
},
  "geometry": {"coordinates":[-73.666623,40.796781],"type":"Point"}
}