{
  "type": "Feature",
  "properties": {
    "addr:full":"19 Bridge St Slingerlands NY 12159",
    "addr:housenumber":"19",
    "addr:postcode":"12159",
    "addr:street":"Bridge St",
    "iso:country":"US",
    "sg:address":"19 Bridge St",
    "sg:city":"Slingerlands",
    "sg:classifiers":[
        {
            "category":"Professional",
            "type":"Services"
        }
    ],
    "sg:phone":"+1   ",
    "sg:postcode":"12159",
    "sg:province":"NY",
    "wof:name":"Tm Systems Corp",
    "wof:placetype":"venue"
},
  "geometry": {"coordinates":[-73.858987,42.62892],"type":"Point"}
}