{
  "type": "Feature",
  "properties": {
    "addr:full":"304 Hudson St New York NY 10013",
    "addr:housenumber":"304",
    "addr:postcode":"10013",
    "addr:street":"Hudson St",
    "iso:country":"US",
    "sg:address":"304 Hudson St",
    "sg:city":"New York",
    "sg:classifiers":[
        {
            "category":"Retail",
            "subcategory":"Portrait Studio",
            "type":"Services"
        },
        {
            "category":"Professional",
            "subcategory":"Art Services",
            "type":"Services"
        }
    ],
    "sg:phone":"+1 212 243 7770",
    "sg:postcode":"10013",
    "sg:province":"NY",
    "sg:tags":[
        "photographer",
        "photography",
        "store"
    ],
    "wof:name":"Le Point Studios",
    "wof:placetype":"venue"
},
  "geometry": {"coordinates":[-74.31692,40.726028],"type":"Point"}
}