{
  "type": "Feature",
  "properties": {
    "iso:country":"US",
    "sg:address":"534 W 114th St",
    "sg:city":"New York",
    "sg:classifiers":[
        {
            "category":"Organizations",
            "subcategory":"Community Association",
            "type":"Services"
        }
    ],
    "sg:phone":"+1   ",
    "sg:postcode":"10025",
    "sg:province":"NY",
    "wof:name":"Kappa Lapha Theta",
    "wof:placetype":"venue"
},
  "geometry": {"coordinates":[-73.964139,40.806225],"type":"Point"}
}