{
  "type": "Feature",
  "properties": {
    "addr:full":"W 23rd St New York NY 10011",
    "addr:postcode":"10011",
    "addr:street":"W 23Rd St",
    "iso:country":"US",
    "sg:address":"W 23rd St",
    "sg:city":"New York",
    "sg:classifiers":[
        {
            "category":"Landmark",
            "subcategory":"Historic",
            "type":"Public Place"
        }
    ],
    "sg:phone":"+1 212 336 6666",
    "sg:postcode":"10011",
    "sg:province":"NY",
    "sg:tags":[
        "building",
        "historical"
    ],
    "sg:website":"www.chelseapiers.com/pp01.htm",
    "wof:name":"Pier Park",
    "wof:placetype":"venue"
},
  "geometry": {"coordinates":[-73.999905,40.745885],"type":"Point"}
}