{
  "type": "Feature",
  "properties": {
    "addr:full":"62 Enter Ln Islandia NY 11749",
    "addr:housenumber":"62",
    "addr:postcode":"11749",
    "addr:street":"Enter Ln",
    "iso:country":"US",
    "sg:address":"62 Enter Ln",
    "sg:city":"Islandia",
    "sg:classifiers":[
        {
            "category":"Manufacturing",
            "subcategory":"Chemicals & Compounds",
            "type":"Manufacturing & Wholesale Goods"
        }
    ],
    "sg:phone":"+1 631 232 1126",
    "sg:postcode":"11749",
    "sg:province":"NY",
    "sg:tags":[
        "lithographing",
        "ink"
    ],
    "wof:name":"KOHL & Madden Printing Ink",
    "wof:placetype":"venue"
},
  "geometry": {"coordinates":[-73.189978,40.807081],"type":"Point"}
}