{
  "type": "Feature",
  "properties": {
    "addr:full":"130 Park St Malone NY 12953",
    "addr:housenumber":"130",
    "addr:postcode":"12953",
    "addr:street":"Park St",
    "iso:country":"US",
    "sg:address":"130 Park St",
    "sg:city":"Malone",
    "sg:classifiers":[
        {
            "category":"Health Services",
            "subcategory":"Doctor",
            "type":"Services"
        }
    ],
    "sg:phone":"+1 518 483 3330",
    "sg:postcode":"12953",
    "sg:province":"NY",
    "sg:tags":[
        "medical"
    ],
    "wof:name":"Quereshy Mahmood A MD Facc",
    "wof:placetype":"venue"
},
  "geometry": {"coordinates":[-74.291967,44.856336],"type":"Point"}
}