{
  "type": "Feature",
  "properties": {
    "iso:country":"US",
    "sg:address":"178 Richmond Blvd",
    "sg:city":"Ronkonkoma",
    "sg:classifiers":[
        {
            "category":"Food & Beverages",
            "subcategory":"Groceries & Convenience Stores",
            "type":"Retail Goods"
        }
    ],
    "sg:phone":"+1 631 471 0007",
    "sg:postcode":"11779",
    "sg:province":"NY",
    "wof:name":"Ronko Convenience Store",
    "wof:placetype":"venue"
},
  "geometry": {"coordinates":[-73.142748,40.823521],"type":"Point"}
}