{
  "type": "Feature",
  "properties": {
    "addr:full":"716 Hoosick Rd Troy NY 12180",
    "addr:housenumber":"716",
    "addr:postcode":"12180",
    "addr:street":"Hoosick Rd",
    "iso:country":"US",
    "sg:address":"716 Hoosick Rd",
    "sg:city":"Troy",
    "sg:classifiers":[
        {
            "category":"Banks & Credit Unions",
            "subcategory":"Bank",
            "type":"Services"
        }
    ],
    "sg:phone":"+1 518 270 7800",
    "sg:postcode":"12180",
    "sg:province":"NY",
    "sg:tags":[
        "savings",
        "institution"
    ],
    "wof:name":"Hudson River Bank & Trust",
    "wof:placetype":"venue"
},
  "geometry": {"coordinates":[-73.644666,42.743933],"type":"Point"}
}