{
  "type": "Feature",
  "properties": {
    "addr:full":"1457 Broadway Brooklyn NY 11221",
    "addr:housenumber":"1457",
    "addr:postcode":"11221",
    "addr:street":"Broadway",
    "iso:country":"US",
    "sg:address":"1457 Broadway",
    "sg:city":"Brooklyn",
    "sg:classifiers":[
        {
            "category":"Health Services",
            "subcategory":"Doctor",
            "type":"Services"
        }
    ],
    "sg:phone":"+1 718 455 3371",
    "sg:postcode":"11221",
    "sg:province":"NY",
    "sg:tags":[
        "physician",
        "medical",
        "surgeon"
    ],
    "wof:name":"Henry Sardar MD",
    "wof:placetype":"venue"
},
  "geometry": {"coordinates":[-73.919527,40.688227],"type":"Point"}
}