{
  "type": "Feature",
  "properties": {
    "addr:full":"70 Kean St West Babylon NY 11704",
    "addr:housenumber":"70",
    "addr:postcode":"11704",
    "addr:street":"Kean St",
    "iso:country":"US",
    "sg:address":"70 Kean St",
    "sg:city":"West Babylon",
    "sg:classifiers":[
        {
            "category":"Education",
            "subcategory":"School",
            "type":"Public Place"
        }
    ],
    "sg:phone":"+1   ",
    "sg:postcode":"11704",
    "sg:province":"NY",
    "wof:name":"Old Bethpage Rifle Pistol CLB",
    "wof:placetype":"venue"
},
  "geometry": {"coordinates":[-73.380692,40.738005],"type":"Point"}
}