{
  "type": "Feature",
  "properties": {
    "iso:country":"US",
    "sg:address":"288 Fulton Ave",
    "sg:city":"Hempstead",
    "sg:classifiers":[
        {
            "category":"Travel",
            "subcategory":"Travel Agent",
            "type":"Entertainment"
        }
    ],
    "sg:phone":"+1   ",
    "sg:postcode":"11550",
    "sg:province":"NY",
    "sg:tags":[
        "agency"
    ],
    "wof:name":"Corfinge",
    "wof:placetype":"venue"
},
  "geometry": {"coordinates":[-73.62698899999999,40.707657],"type":"Point"}
}