{
  "type": "Feature",
  "properties": {
    "addr:full":"24 Maple Rd East Setauket NY 11733",
    "addr:housenumber":"24",
    "addr:postcode":"11733",
    "addr:street":"Maple Rd",
    "iso:country":"US",
    "sg:address":"24 Maple Rd",
    "sg:city":"East Setauket",
    "sg:classifiers":[
        {
            "category":"Wholesale",
            "subcategory":"Stationery",
            "type":"Manufacturing & Wholesale Goods"
        }
    ],
    "sg:phone":"+1 631 751 0986",
    "sg:postcode":"11733",
    "sg:province":"NY",
    "sg:tags":[
        "supply"
    ],
    "wof:name":"Kenny Delco Sales Corp",
    "wof:placetype":"venue"
},
  "geometry": {"coordinates":[-73.11039100000001,40.961218],"type":"Point"}
}