{
  "type": "Feature",
  "properties": {
    "addr:full":"75 Landing Meadow Rd Smithtown NY 11787",
    "addr:housenumber":"75",
    "addr:postcode":"11787",
    "addr:street":"Landing Meadow Rd",
    "iso:country":"US",
    "sg:address":"75 Landing Meadow Rd",
    "sg:city":"Smithtown",
    "sg:classifiers":[
        {
            "category":"Health Services",
            "subcategory":"Hospital",
            "type":"Services"
        }
    ],
    "sg:phone":"+1 631 265 3180",
    "sg:postcode":"11787",
    "sg:province":"NY",
    "sg:tags":[
        "mental"
    ],
    "wof:name":"Suffolk Institute",
    "wof:placetype":"venue"
},
  "geometry": {"coordinates":[-73.201414,40.875244],"type":"Point"}
}