{
  "type": "Feature",
  "properties": {
    "iso:country":"US",
    "sg:address":"21 New Sparrowbush Rd",
    "sg:city":"Latham",
    "sg:classifiers":[
        {
            "category":"Freight",
            "type":"Transportation"
        }
    ],
    "sg:phone":"+1   ",
    "sg:postcode":"12110",
    "sg:province":"NY",
    "sg:tags":[
        "operator",
        "trucking"
    ],
    "wof:name":"Airport Motor Freight",
    "wof:placetype":"venue"
},
  "geometry": {"coordinates":[-73.775599,42.766327],"type":"Point"}
}