{
  "type": "Feature",
  "properties": {
    "addr:full":"10108 Park Lane S Richmond Hill NY 11418",
    "addr:housenumber":"10108",
    "addr:postcode":"11418",
    "addr:street":"Park Lane;Richmond",
    "iso:country":"US",
    "sg:address":"10108 Park Lane S",
    "sg:city":"Richmond Hill",
    "sg:classifiers":[
        {
            "category":"Organizations",
            "subcategory":"Non-profit Organization",
            "type":"Services"
        }
    ],
    "sg:phone":"+1 718 805 6892",
    "sg:postcode":"11418",
    "sg:province":"NY",
    "sg:tags":[
        "service/non-profit",
        "community"
    ],
    "wof:name":"Independence Resident",
    "wof:placetype":"venue"
},
  "geometry": {"coordinates":[-73.847672,40.698536],"type":"Point"}
}