{
  "type": "Feature",
  "properties": {
    "iso:country":"US",
    "sg:address":"127 Main St",
    "sg:city":"Stamford",
    "sg:classifiers":[
        {
            "category":"Food & Beverages",
            "subcategory":"Groceries & Convenience Stores",
            "type":"Retail Goods"
        }
    ],
    "sg:phone":"+1   ",
    "sg:postcode":"12167",
    "sg:province":"NY",
    "wof:name":"Grand Union Store 1803",
    "wof:placetype":"venue"
},
  "geometry": {"coordinates":[-74.619878,42.410187],"type":"Point"}
}