{
  "type": "Feature",
  "properties": {
    "iso:country":"US",
    "sg:address":"23 W 35 St",
    "sg:city":"New York",
    "sg:classifiers":[
        {
            "category":"Wholesale",
            "subcategory":"Machinery & Supplies",
            "type":"Manufacturing & Wholesale Goods"
        }
    ],
    "sg:phone":"+1 212 604 9064",
    "sg:postcode":"10001",
    "sg:province":"NY",
    "sg:tags":[
        "equipment",
        "industrial"
    ],
    "wof:name":"Industrial Evolution",
    "wof:placetype":"venue"
},
  "geometry": {"coordinates":[-73.98671,40.750214],"type":"Point"}
}