{
  "type": "Feature",
  "properties": {
    "addr:full":"6737 Myrtle Ave Glendale NY 11385",
    "addr:housenumber":"6737",
    "addr:postcode":"11385",
    "addr:street":"Myrtle Ave",
    "iso:country":"US",
    "sg:address":"6737 Myrtle Ave",
    "sg:city":"Glendale",
    "sg:classifiers":[
        {
            "category":"Personal",
            "subcategory":"Nail Salon",
            "type":"Services"
        }
    ],
    "sg:phone":"+1 718 628 4991",
    "sg:postcode":"11385",
    "sg:province":"NY",
    "wof:name":"Divine Nails",
    "wof:placetype":"venue"
},
  "geometry": {"coordinates":[-73.88515,40.701695],"type":"Point"}
}