{
  "type": "Feature",
  "properties": {
    "iso:country":"US",
    "sg:address":"5719 4th Ave",
    "sg:city":"Brooklyn",
    "sg:classifiers":[
        {
            "category":"Retail",
            "subcategory":"Laundry & Dry Cleaning",
            "type":"Services"
        }
    ],
    "sg:phone":"+1 718 492 4601",
    "sg:postcode":"11220",
    "sg:province":"NY",
    "sg:tags":[
        "cleaners"
    ],
    "wof:name":"Sunrise Cleaners",
    "wof:placetype":"venue"
},
  "geometry": {"coordinates":[-74.017095,40.642043],"type":"Point"}
}