{
  "type": "Feature",
  "properties": {
    "iso:country":"US",
    "sg:address":"6 Harned Dr",
    "sg:city":"Centerport",
    "sg:classifiers":[
        {
            "category":"Professional",
            "subcategory":"Management & Consulting",
            "type":"Services"
        }
    ],
    "sg:phone":"+1 631 757 6520",
    "sg:postcode":"11721",
    "sg:province":"NY",
    "sg:tags":[
        "consultant"
    ],
    "wof:name":"Architectural Audio Visual Co",
    "wof:placetype":"venue"
},
  "geometry": {"coordinates":[-73.365424,40.887663],"type":"Point"}
}