{
  "type": "Feature",
  "properties": {
    "addr:full":"650 W 50th St New York NY 10019",
    "addr:housenumber":"650",
    "addr:postcode":"10019",
    "addr:street":"W 50Th St",
    "iso:country":"US",
    "sg:address":"650 W 50th St",
    "sg:city":"New York",
    "sg:classifiers":[
        {
            "category":"Professional",
            "subcategory":"Management & Consulting",
            "type":"Services"
        }
    ],
    "sg:phone":"+1 212 373 9501",
    "sg:postcode":"10019",
    "sg:province":"NY",
    "sg:tags":[
        "planning",
        "advertising",
        "business",
        "strategic"
    ],
    "wof:name":"Sandino Group LLC",
    "wof:placetype":"venue"
},
  "geometry": {"coordinates":[-73.995811,40.766209],"type":"Point"}
}