{
  "type": "Feature",
  "properties": {
    "iso:country":"US",
    "sg:address":"1711 2nd Ave",
    "sg:city":"New York",
    "sg:classifiers":[
        {
            "category":"Restaurant",
            "type":"Food & Drink"
        }
    ],
    "sg:phone":"+1 212 427 3077",
    "sg:postcode":"10128",
    "sg:province":"NY",
    "sg:tags":[
        "thai"
    ],
    "sg:website":"oshathaikitchennyc.com",
    "wof:name":"Osha",
    "wof:placetype":"venue"
},
  "geometry": {"coordinates":[-73.950767,40.779699],"type":"Point"}
}