{
  "type": "Feature",
  "properties": {
    "addr:full":"2 Pulaski Rd Kings Park NY 11754",
    "addr:housenumber":"2",
    "addr:postcode":"11754",
    "addr:street":"Pulaski Rd",
    "iso:country":"US",
    "sg:address":"2 Pulaski Rd",
    "sg:city":"Kings Park",
    "sg:classifiers":[
        {
            "category":"Restaurant",
            "type":"Food & Drink"
        }
    ],
    "sg:phone":"+1 631 269 5774",
    "sg:postcode":"11754",
    "sg:province":"NY",
    "wof:name":"Hokie Pokie",
    "wof:placetype":"venue"
},
  "geometry": {"coordinates":[-73.258982,40.88534],"type":"Point"}
}