{
  "type": "Feature",
  "properties": {
    "addr:full":"561 E 3rd St Brooklyn NY 11218",
    "addr:housenumber":"561",
    "addr:postcode":"11218",
    "addr:street":"E 3Rd St",
    "iso:country":"US",
    "sg:address":"561 E 3rd St",
    "sg:city":"Brooklyn",
    "sg:classifiers":[
        {
            "category":"Health Services",
            "subcategory":"Doctor",
            "type":"Services"
        }
    ],
    "sg:phone":"+1   ",
    "sg:postcode":"11218",
    "sg:province":"NY",
    "wof:name":"Family Dentistry",
    "wof:placetype":"venue"
},
  "geometry": {"coordinates":[-73.976679,40.640522],"type":"Point"}
}