{
  "type": "Feature",
  "properties": {
    "addr:full":"4343 Bowne St Flushing NY 11355",
    "addr:housenumber":"4343",
    "addr:postcode":"11355",
    "addr:street":"Bowne St",
    "iso:country":"US",
    "sg:address":"4343 Bowne St",
    "sg:city":"Flushing",
    "sg:classifiers":[
        {
            "category":"Social Services",
            "subcategory":"Child Care",
            "type":"Services"
        }
    ],
    "sg:phone":"+1 718 445 5090",
    "sg:postcode":"11355",
    "sg:province":"NY",
    "sg:tags":[
        "day"
    ],
    "wof:name":"The Little Cherry Daycare Center Inc",
    "wof:placetype":"venue"
},
  "geometry": {"coordinates":[-73.81950399999999,40.755001],"type":"Point"}
}