{
  "type": "Feature",
  "properties": {
    "addr:full":"717 W 181st Street New York NY 10033",
    "addr:housenumber":"717",
    "addr:postcode":"10033",
    "addr:street":"W 181St Street",
    "iso:country":"US",
    "sg:address":"717 W 181st Street",
    "sg:city":"New York",
    "sg:classifiers":[
        {
            "category":"Food & Beverages",
            "subcategory":"Groceries & Convenience Stores",
            "type":"Retail Goods"
        }
    ],
    "sg:phone":"+1 212 928 8061",
    "sg:postcode":"10033",
    "sg:province":"NY",
    "wof:name":"Tejada Grocery",
    "wof:placetype":"venue"
},
  "geometry": {"coordinates":[-73.937005,40.850437],"type":"Point"}
}