{
  "type": "Feature",
  "properties": {
    "addr:full":"330 Jervis Ave Copiague NY 11726",
    "addr:housenumber":"330",
    "addr:postcode":"11726",
    "addr:street":"Jervis Ave",
    "iso:country":"US",
    "sg:address":"330 Jervis Ave",
    "sg:city":"Copiague",
    "sg:classifiers":[
        {
            "category":"Wholesale",
            "subcategory":"Painting Supplies",
            "type":"Manufacturing & Wholesale Goods"
        }
    ],
    "sg:phone":"+1 631 225 8848",
    "sg:postcode":"11726",
    "sg:province":"NY",
    "wof:name":"Guerin Design",
    "wof:placetype":"venue"
},
  "geometry": {"coordinates":[-73.395582,40.662892],"type":"Point"}
}