{
  "type": "Feature",
  "properties": {
    "addr:full":"375 State Hwy 32 Central Valley NY 10917",
    "addr:housenumber":"375",
    "addr:postcode":"10917",
    "addr:street":"State Hwy 32 Central",
    "iso:country":"US",
    "sg:address":"375 State Hwy 32",
    "sg:city":"Central Valley",
    "sg:classifiers":[
        {
            "category":"Banks & Credit Unions",
            "subcategory":"Investment Brokerage",
            "type":"Services"
        }
    ],
    "sg:phone":"+1 845 928 1528",
    "sg:postcode":"10917",
    "sg:province":"NY",
    "sg:tags":[
        "advisory",
        "financial"
    ],
    "sg:website":"www.bkst.com",
    "wof:name":"Brookstreet Securities Corp",
    "wof:placetype":"venue"
},
  "geometry": {"coordinates":[-74.124089,41.334886],"type":"Point"}
}