{
  "type": "Feature",
  "properties": {
    "iso:country":"US",
    "sg:address":"8 Claverton Ct",
    "sg:city":"Melville",
    "sg:classifiers":[
        {
            "category":"Travel",
            "subcategory":"Campground",
            "type":"Entertainment"
        }
    ],
    "sg:phone":"+1   ",
    "sg:postcode":"11747",
    "sg:province":"NY",
    "sg:tags":[
        "camp"
    ],
    "wof:name":"Baldwin Morey & Caryl",
    "wof:placetype":"venue"
},
  "geometry": {"coordinates":[-73.37803599999999,40.779736],"type":"Point"}
}