{
  "type": "Feature",
  "properties": {
    "addr:full":"1410 48th St Brooklyn NY 11219",
    "addr:housenumber":"1410",
    "addr:postcode":"11219",
    "addr:street":"48Th St",
    "iso:country":"US",
    "sg:address":"1410 48th St",
    "sg:city":"Brooklyn",
    "sg:classifiers":[
        {
            "category":"Wholesale",
            "subcategory":"Medical Equipment & Supplies",
            "type":"Manufacturing & Wholesale Goods"
        },
        {
            "category":"Health Services",
            "subcategory":"Health Practitioner",
            "type":"Services"
        }
    ],
    "sg:phone":"+1 718 853 4327",
    "sg:postcode":"11219",
    "sg:province":"NY",
    "sg:tags":[
        "assistive",
        "device",
        "audiologists",
        "aid",
        "hearing"
    ],
    "wof:name":"Hearite Audiological",
    "wof:placetype":"venue"
},
  "geometry": {"coordinates":[-73.98912300000001,40.634115],"type":"Point"}
}