{
  "type": "Feature",
  "properties": {
    "addr:full":"3670 State Hwy 13 Truxton NY 13158",
    "addr:housenumber":"3670",
    "addr:postcode":"13158",
    "addr:street":"State Hwy 13",
    "iso:country":"US",
    "sg:address":"3670 State Hwy 13",
    "sg:city":"Truxton",
    "sg:classifiers":[
        {
            "category":"Organizations",
            "subcategory":"Religious Organization",
            "type":"Services"
        }
    ],
    "sg:phone":"+1 607 842 6404",
    "sg:postcode":"13158",
    "sg:province":"NY",
    "sg:tags":[
        "church"
    ],
    "wof:name":"Truxton United Methodist Chr",
    "wof:placetype":"venue"
},
  "geometry": {"coordinates":[-76.04568,42.696375],"type":"Point"}
}