{
  "type": "Feature",
  "properties": {
    "addr:full":"215 Amsterdam Ave New York NY 10023",
    "addr:housenumber":"215",
    "addr:postcode":"10023",
    "addr:street":"Amsterdam Ave",
    "iso:country":"US",
    "sg:address":"215 Amsterdam Ave",
    "sg:city":"New York",
    "sg:classifiers":[
        {
            "category":"Retail",
            "subcategory":"Laundry & Dry Cleaning",
            "type":"Services"
        }
    ],
    "sg:phone":"+1 212 595 2686",
    "sg:postcode":"10023",
    "sg:province":"NY",
    "sg:tags":[
        "cleaner"
    ],
    "wof:name":"Mayson Cleaner",
    "wof:placetype":"venue"
},
  "geometry": {"coordinates":[-73.98290299999999,40.7771],"type":"Point"}
}