{
  "type": "Feature",
  "properties": {
    "addr:full":"26 1st Ave Pelham NY 10803",
    "addr:housenumber":"26",
    "addr:postcode":"10803",
    "addr:street":"1St Ave",
    "iso:country":"US",
    "sg:address":"26 1st Ave",
    "sg:city":"Pelham",
    "sg:classifiers":[
        {
            "category":"Organizations",
            "subcategory":"Religious Organization",
            "type":"Services"
        }
    ],
    "sg:phone":"+1 914 738 1218",
    "sg:postcode":"10803",
    "sg:province":"NY",
    "sg:tags":[
        "order"
    ],
    "wof:name":"Marist High Schl Kunioto Japan",
    "wof:placetype":"venue"
},
  "geometry": {"coordinates":[-73.812657,40.912747],"type":"Point"}
}