{
  "type": "Feature",
  "properties": {
    "iso:country":"US",
    "sg:address":"127 Main St",
    "sg:city":"Geneseo",
    "sg:classifiers":[
        {
            "category":"Personal",
            "subcategory":"Beauty Salon",
            "type":"Services"
        }
    ],
    "sg:phone":"+1   ",
    "sg:postcode":"14454",
    "sg:province":"NY",
    "sg:tags":[
        "shop"
    ],
    "wof:name":"Expressions",
    "wof:placetype":"venue"
},
  "geometry": {"coordinates":[-77.81711799999999,42.79492],"type":"Point"}
}