{
  "type": "Feature",
  "properties": {
    "iso:country":"US",
    "sg:address":"1333 Pacific St",
    "sg:city":"Brooklyn",
    "sg:classifiers":[
        {
            "category":"Freight",
            "type":"Transportation"
        }
    ],
    "sg:phone":"+1   ",
    "sg:postcode":"11216",
    "sg:province":"NY",
    "wof:name":"New Genisiss Development Inc",
    "wof:placetype":"venue"
},
  "geometry": {"coordinates":[-73.948277,40.677667],"type":"Point"}
}