{
  "type": "Feature",
  "properties": {
    "addr:full":"537 Johnson Ave Brooklyn NY 11237",
    "addr:housenumber":"537",
    "addr:postcode":"11237",
    "addr:street":"Johnson Ave",
    "iso:country":"US",
    "sg:address":"537 Johnson Ave",
    "sg:city":"Brooklyn",
    "sg:classifiers":[
        {
            "category":"Banks & Credit Unions",
            "subcategory":"Financial Services",
            "type":"Services"
        }
    ],
    "sg:phone":"+1 347 881 9766",
    "sg:postcode":"11237",
    "sg:province":"NY",
    "sg:tags":[
        "international",
        "trade"
    ],
    "wof:name":"Yamei Trading Inc",
    "wof:placetype":"venue"
},
  "geometry": {"coordinates":[-73.926108,40.708808],"type":"Point"}
}