{
  "type": "Feature",
  "properties": {
    "addr:full":"41 Union Sq W New York NY 10003",
    "addr:housenumber":"41",
    "addr:postcode":"10003",
    "addr:street":"Union Sq W",
    "iso:country":"US",
    "sg:address":"41 Union Sq W",
    "sg:city":"New York",
    "sg:classifiers":[
        {
            "category":"Coffee & Tea",
            "type":"Food & Drink"
        }
    ],
    "sg:menulink":"http://www.allmenus.com/ny/new-york/113340-starbucks-coffee/menu/",
    "sg:phone":"+1 646 336 6945",
    "sg:postcode":"10003",
    "sg:province":"NY",
    "sg:tags":[
        "american"
    ],
    "wof:name":"Starbucks Coffee",
    "wof:placetype":"venue"
},
  "geometry": {"coordinates":[-73.99094700000001,40.737216],"type":"Point"}
}