{
  "type": "Feature",
  "properties": {
    "iso:country":"US",
    "sg:address":"417 Ives Hill Rd",
    "sg:city":"Afton",
    "sg:classifiers":[
        {
            "category":"Professional",
            "subcategory":"Printing & Photocopies",
            "type":"Services"
        }
    ],
    "sg:phone":"+1 607 639 4100",
    "sg:postcode":"13730",
    "sg:province":"NY",
    "sg:tags":[
        "services-commercial"
    ],
    "wof:name":"Fischer Printing",
    "wof:placetype":"venue"
},
  "geometry": {"coordinates":[-75.527581,42.209872],"type":"Point"}
}