{
  "type": "Feature",
  "properties": {
    "iso:country":"US",
    "sg:address":"170 Franklin St",
    "sg:city":"Buffalo",
    "sg:classifiers":[
        {
            "category":"Health Services",
            "subcategory":"Clinic",
            "type":"Services"
        }
    ],
    "sg:phone":"+1 716 856 2702",
    "sg:postcode":"14202",
    "sg:province":"NY",
    "sg:tags":[
        "home"
    ],
    "wof:name":"All Metro Health Care",
    "wof:placetype":"venue"
},
  "geometry": {"coordinates":[-78.875758,42.888892],"type":"Point"}
}