{
  "type": "Feature",
  "properties": {
    "addr:full":"4403 16th Avenue Brooklyn NY 11204",
    "addr:housenumber":"4403",
    "addr:postcode":"11204",
    "addr:street":"16Th Avenue",
    "iso:country":"US",
    "sg:address":"4403 16th Avenue",
    "sg:city":"Brooklyn",
    "sg:classifiers":[
        {
            "category":"Shopping",
            "subcategory":"Books",
            "type":"Retail Goods"
        }
    ],
    "sg:phone":"+1 718 438 8414",
    "sg:postcode":"11204",
    "sg:province":"NY",
    "sg:tags":[
        "bookstore"
    ],
    "sg:website":"www.seforimworld.com",
    "wof:name":"Seforim World",
    "wof:placetype":"venue"
},
  "geometry": {"coordinates":[-73.98262800000001,40.633623],"type":"Point"}
}