{
  "type": "Feature",
  "properties": {
    "addr:full":"112 E 61st St Manhattan NY 10065",
    "addr:housenumber":"112",
    "addr:postcode":"10065",
    "addr:street":"E 61St St",
    "iso:country":"US",
    "sg:address":"112 E 61st St",
    "sg:city":"Manhattan",
    "sg:classifiers":[
        {
            "category":"Health Services",
            "subcategory":"Clinic",
            "type":"Services"
        }
    ],
    "sg:phone":"+1 212 371 1200",
    "sg:postcode":"10065",
    "sg:province":"NY",
    "sg:tags":[
        "spa",
        "medical"
    ],
    "sg:website":"www.skinnymedspa.com",
    "wof:name":"Skinny \u00a0Medspa",
    "wof:placetype":"venue"
},
  "geometry": {"coordinates":[-73.968407,40.763712],"type":"Point"}
}