{
  "type": "Feature",
  "properties": {
    "iso:country":"US",
    "sg:address":"3 Medical Dr Ste D",
    "sg:city":"Port Jefferson Sta",
    "sg:classifiers":[
        {
            "category":"Health Services",
            "subcategory":"Doctor",
            "type":"Services"
        }
    ],
    "sg:phone":"+1 631 928 7500",
    "sg:postcode":"11776",
    "sg:province":"NY",
    "sg:tags":[
        "surgeon",
        "oral"
    ],
    "wof:name":"Nathan David DDS",
    "wof:placetype":"venue"
},
  "geometry": {"coordinates":[-73.042503,40.930401],"type":"Point"}
}