{
  "type": "Feature",
  "properties": {
    "iso:country":"US",
    "sg:address":"3 Onderdonk Ave",
    "sg:city":"Rensselaer",
    "sg:classifiers":[
        {
            "category":"Professional",
            "subcategory":"Management & Consulting",
            "type":"Services"
        }
    ],
    "sg:phone":"+1 518 479 4542",
    "sg:postcode":"12144",
    "sg:province":"NY",
    "sg:tags":[
        "consultant"
    ],
    "wof:name":"Ellen Tunison Nurse Consulting",
    "wof:placetype":"venue"
},
  "geometry": {"coordinates":[-73.72848399999999,42.613216],"type":"Point"}
}