{
  "type": "Feature",
  "properties": {
    "addr:full":"3108 Broadway Astoria NY 11106",
    "addr:housenumber":"3108",
    "addr:postcode":"11106",
    "addr:street":"Broadway",
    "iso:country":"US",
    "sg:address":"3108 Broadway",
    "sg:city":"Astoria",
    "sg:classifiers":[
        {
            "category":"Shopping",
            "subcategory":"Clothing, Apparel, & Fashions",
            "type":"Retail Goods"
        },
        {
            "category":"Shopping",
            "subcategory":"Shoes",
            "type":"Retail Goods"
        },
        {
            "category":"Military Area",
            "subcategory":"Restricted Area",
            "type":"Public Place"
        }
    ],
    "sg:phone":"+1 718 278 9156",
    "sg:postcode":"11106",
    "sg:province":"NY",
    "sg:tags":[
        "army",
        "work",
        "navy",
        "jean",
        "clothing",
        "store",
        "clothes"
    ],
    "wof:name":"Browns Army & Navy Store Inc",
    "wof:placetype":"venue"
},
  "geometry": {"coordinates":[-73.936031,40.767635],"type":"Point"}
}