{
  "type": "Feature",
  "properties": {
    "addr:full":"887 Hempstead Tpke Franklin Square NY 11010",
    "addr:housenumber":"887",
    "addr:postcode":"11010",
    "addr:street":"Hempstead Tpke",
    "iso:country":"US",
    "sg:address":"887 Hempstead Tpke",
    "sg:city":"Franklin Square",
    "sg:classifiers":[
        {
            "category":"Arts & Performance",
            "subcategory":"Art Gallery",
            "type":"Entertainment"
        }
    ],
    "sg:phone":"+1 516 270 3544",
    "sg:postcode":"11010",
    "sg:province":"NY",
    "wof:name":"Art Frame",
    "wof:placetype":"venue"
},
  "geometry": {"coordinates":[-73.672755,40.707016],"type":"Point"}
}