{
  "type": "Feature",
  "properties": {
    "addr:full":"8 Candido Ave S Shirley NY 11967",
    "addr:housenumber":"8",
    "addr:postcode":"11967",
    "addr:street":"Candido Ave S Shirley",
    "iso:country":"US",
    "sg:address":"8 Candido Ave S",
    "sg:city":"Shirley",
    "sg:classifiers":[
        {
            "category":"Shopping",
            "subcategory":"Computers & Home Electronics",
            "type":"Retail Goods"
        }
    ],
    "sg:phone":"+1 631 281 0071",
    "sg:postcode":"11967",
    "sg:province":"NY",
    "sg:tags":[
        "equipment",
        "electronic",
        "supply"
    ],
    "wof:name":"Electronic & Mktng National",
    "wof:placetype":"venue"
},
  "geometry": {"coordinates":[-72.874881,40.801194],"type":"Point"}
}