{
  "type": "Feature",
  "properties": {
    "iso:country":"US",
    "sg:address":"71 Clinton Rd Ste 300",
    "sg:city":"Garden City",
    "sg:classifiers":[
        {
            "category":"Professional",
            "subcategory":"Lawyer & Legal Services",
            "type":"Services"
        }
    ],
    "sg:phone":"+1 516 294 5200",
    "sg:postcode":"11530",
    "sg:province":"NY",
    "wof:name":"Picciano & Scahill PC",
    "wof:placetype":"venue"
},
  "geometry": {"coordinates":[-73.620598,40.7239],"type":"Point"}
}