{
  "type": "Feature",
  "properties": {
    "addr:full":"601 W Jericho Tpke Huntington NY 11743",
    "addr:housenumber":"601",
    "addr:postcode":"11743",
    "addr:street":"W Jericho Tpke",
    "iso:country":"US",
    "sg:address":"601 W Jericho Tpke",
    "sg:city":"Huntington",
    "sg:classifiers":[
        {
            "category":"Recreation",
            "type":"Entertainment"
        }
    ],
    "sg:phone":"+1 631 385 2312",
    "sg:postcode":"11743",
    "sg:province":"NY",
    "sg:tags":[
        "martial",
        "arts",
        "instruction"
    ],
    "sg:website":"www.serrajitsu.com",
    "wof:name":"Serra Brazilian Jiu Jitsu",
    "wof:placetype":"venue"
},
  "geometry": {"coordinates":[-73.435396,40.827865],"type":"Point"}
}