{
  "type": "Feature",
  "properties": {
    "iso:country":"US",
    "sg:address":"6 Schuyler St",
    "sg:city":"Belmont",
    "sg:classifiers":[
        {
            "category":"Wholesale",
            "subcategory":"Machinery & Supplies",
            "type":"Manufacturing & Wholesale Goods"
        }
    ],
    "sg:phone":"+1 585 268 9294",
    "sg:postcode":"14813",
    "sg:province":"NY",
    "sg:tags":[
        "equipment",
        "establishment"
    ],
    "wof:name":"Alleghany County Elections",
    "wof:placetype":"venue"
},
  "geometry": {"coordinates":[-78.033644,42.223267],"type":"Point"}
}