{
  "type": "Feature",
  "properties": {
    "iso:country":"US",
    "sg:address":"75 Portman Rd",
    "sg:city":"New Rochelle",
    "sg:classifiers":[
        {
            "category":"Home & Garden",
            "subcategory":"Garden Supply",
            "type":"Retail Goods"
        }
    ],
    "sg:phone":"+1 914 636 4428",
    "sg:postcode":"10801",
    "sg:province":"NY",
    "sg:tags":[
        "nurseryman"
    ],
    "wof:name":"Mario Bulfamante & Sons",
    "wof:placetype":"venue"
},
  "geometry": {"coordinates":[-73.77194900000001,40.927893],"type":"Point"}
}