{
  "type": "Feature",
  "properties": {
    "addr:full":"21 Roe Ave Albany NY 12205",
    "addr:housenumber":"21",
    "addr:postcode":"12205",
    "addr:street":"Roe Ave",
    "iso:country":"US",
    "sg:address":"21 Roe Ave",
    "sg:city":"Albany",
    "sg:classifiers":[
        {
            "category":"Freight",
            "type":"Transportation"
        }
    ],
    "sg:phone":"+1 518 446 9277",
    "sg:postcode":"12205",
    "sg:province":"NY",
    "sg:tags":[
        "delivery"
    ],
    "sg:website":"www.loomisfargo.com",
    "wof:name":"AMSA Courier",
    "wof:placetype":"venue"
},
  "geometry": {"coordinates":[-73.799899,42.700727],"type":"Point"}
}