{
  "type": "Feature",
  "properties": {
    "iso:country":"US",
    "sg:address":"3705 N Buffalo St",
    "sg:city":"Orchard Park",
    "sg:classifiers":[
        {
            "category":"Retail",
            "subcategory":"Car Wash",
            "type":"Services"
        }
    ],
    "sg:phone":"+1 716 662 5559",
    "sg:postcode":"14127",
    "sg:province":"NY",
    "sg:tags":[
        "polishing",
        "washing"
    ],
    "wof:name":"Quaker Towne Auto Wash",
    "wof:placetype":"venue"
},
  "geometry": {"coordinates":[-78.746138,42.782217],"type":"Point"}
}