{
  "type": "Feature",
  "properties": {
    "iso:country":"US",
    "sg:address":"8 W Main St",
    "sg:city":"Patchogue",
    "sg:classifiers":[
        {
            "category":"Retail",
            "subcategory":"Laundry & Dry Cleaning",
            "type":"Services"
        }
    ],
    "sg:phone":"+1 631 509 5900",
    "sg:postcode":"11772",
    "sg:province":"NY",
    "wof:name":"Sleep Tight Incorporated",
    "wof:placetype":"venue"
},
  "geometry": {"coordinates":[-73.528871,40.765568],"type":"Point"}
}