{
  "type": "Feature",
  "properties": {
    "addr:full":"803 Kings Hwy Brooklyn NY 11223",
    "addr:housenumber":"803",
    "addr:postcode":"11223",
    "addr:street":"Kings Hwy",
    "iso:country":"US",
    "sg:address":"803 Kings Hwy",
    "sg:city":"Brooklyn",
    "sg:classifiers":[
        {
            "category":"Health Services",
            "subcategory":"Doctor",
            "type":"Services"
        }
    ],
    "sg:phone":"+1   ",
    "sg:postcode":"11223",
    "sg:province":"NY",
    "wof:name":"Adhut Mordehai",
    "wof:placetype":"venue"
},
  "geometry": {"coordinates":[-73.96376600000001,40.606822],"type":"Point"}
}