{
  "type": "Feature",
  "properties": {
    "iso:country":"US",
    "sg:address":"2 Castle Ct",
    "sg:city":"Albany",
    "sg:classifiers":[
        {
            "category":"Building & Trades",
            "subcategory":"Construction",
            "type":"Services"
        }
    ],
    "sg:phone":"+1 518 459 6378",
    "sg:postcode":"12211",
    "sg:province":"NY",
    "sg:tags":[
        "house"
    ],
    "wof:name":"Action Home Inspections LLC",
    "wof:placetype":"venue"
},
  "geometry": {"coordinates":[-73.77425100000001,42.695752],"type":"Point"}
}