{
  "type": "Feature",
  "properties": {
    "addr:full":"6 Raymond Ave Poughkeepsie NY 12604",
    "addr:housenumber":"6",
    "addr:postcode":"12604",
    "addr:street":"Raymond Ave",
    "iso:country":"US",
    "sg:address":"6 Raymond Ave",
    "sg:city":"Poughkeepsie",
    "sg:classifiers":[
        {
            "category":"Health Services",
            "subcategory":"Medical Lab",
            "type":"Services"
        }
    ],
    "sg:phone":"+1 845 473 4808",
    "sg:postcode":"12604",
    "sg:province":"NY",
    "sg:tags":[
        "laboratory"
    ],
    "wof:name":"Perfection Plus Dental Lab",
    "wof:placetype":"venue"
},
  "geometry": {"coordinates":[-73.901377,41.695065],"type":"Point"}
}