{
  "type": "Feature",
  "properties": {
    "iso:country":"US",
    "sg:address":"1600 Railroad Ave",
    "sg:city":"Holbrook",
    "sg:classifiers":[
        {
            "category":"Building & Trades",
            "subcategory":"Landscaping Services",
            "type":"Services"
        }
    ],
    "sg:phone":"+1 631 285 6767",
    "sg:postcode":"11741",
    "sg:province":"NY",
    "sg:tags":[
        "landscape",
        "contractor"
    ],
    "wof:name":"Louis Barbato Landscaping Inc",
    "wof:placetype":"venue"
},
  "geometry": {"coordinates":[-73.089327,40.809383],"type":"Point"}
}