{
  "type": "Feature",
  "properties": {
    "iso:country":"US",
    "sg:address":"106 Co Rd 36",
    "sg:city":"Margaretville",
    "sg:classifiers":[
        {
            "category":"Building & Trades",
            "subcategory":"Construction",
            "type":"Services"
        }
    ],
    "sg:phone":"+1 845 586 3157",
    "sg:postcode":"12477",
    "sg:province":"NY",
    "sg:tags":[
        "grading",
        "contractor"
    ],
    "wof:name":"Delaware County Highway Dept",
    "wof:placetype":"venue"
},
  "geometry": {"coordinates":[-74.00432000000001,42.110105],"type":"Point"}
}