{
  "type": "Feature",
  "properties": {
    "iso:country":"US",
    "sg:address":"4 Riverside Dr",
    "sg:city":"Utica",
    "sg:classifiers":[
        {
            "category":"Arts & Performance",
            "subcategory":"Dance",
            "type":"Entertainment"
        }
    ],
    "sg:phone":"+1 315 733 2500",
    "sg:postcode":"13502",
    "sg:province":"NY",
    "sg:tags":[
        "instruction",
        "dancing"
    ],
    "wof:name":"Dance Works Studio",
    "wof:placetype":"venue"
},
  "geometry": {"coordinates":[-75.210787,43.116458],"type":"Point"}
}