{
  "type": "Feature",
  "properties": {
    "iso:country":"US",
    "sg:address":"147 N 6th St",
    "sg:city":"Brooklyn",
    "sg:classifiers":[
        {
            "category":"Real Estate",
            "subcategory":"Real Estate Agent",
            "type":"Services"
        }
    ],
    "sg:phone":"+1 718 302 2285",
    "sg:postcode":"11211",
    "sg:province":"NY",
    "wof:name":"Northside Plaza Inc",
    "wof:placetype":"venue"
},
  "geometry": {"coordinates":[-73.959132,40.718044],"type":"Point"}
}