{
  "type": "Feature",
  "properties": {
    "addr:full":"129 26th St Brooklyn NY 11232",
    "addr:housenumber":"129",
    "addr:postcode":"11232",
    "addr:street":"26Th St",
    "iso:country":"US",
    "sg:address":"129 26th St",
    "sg:city":"Brooklyn",
    "sg:classifiers":[
        {
            "category":"Wholesale",
            "subcategory":"Apparel",
            "type":"Manufacturing & Wholesale Goods"
        }
    ],
    "sg:phone":"+1 718 788 8587",
    "sg:postcode":"11232",
    "sg:province":"NY",
    "sg:tags":[
        "piece"
    ],
    "wof:name":"United Needlework Corp",
    "wof:placetype":"venue"
},
  "geometry": {"coordinates":[-74.00130299999999,40.661753],"type":"Point"}
}