{
  "type": "Feature",
  "properties": {
    "iso:country":"US",
    "sg:address":"3674 Commerce Pl",
    "sg:city":"Hamburg",
    "sg:classifiers":[
        {
            "category":"Health Services",
            "subcategory":"Doctor",
            "type":"Services"
        }
    ],
    "sg:phone":"+1 716 648 4345",
    "sg:postcode":"14075",
    "sg:province":"NY",
    "sg:tags":[
        "physician",
        "surgeon"
    ],
    "wof:name":"Southtowns Woman's Group",
    "wof:placetype":"venue"
},
  "geometry": {"coordinates":[-78.849214,42.741094],"type":"Point"}
}