{
  "type": "Feature",
  "properties": {
    "iso:country":"US",
    "sg:address":"591 Co Hwy 19",
    "sg:city":"Constable",
    "sg:classifiers":[
        {
            "category":"Retail",
            "subcategory":"Veterinary Services",
            "type":"Services"
        }
    ],
    "sg:phone":"+1 518 483 9660",
    "sg:postcode":"12926",
    "sg:province":"NY",
    "sg:tags":[
        "veterinarian"
    ],
    "wof:name":"Westville Animal Hospital",
    "wof:placetype":"venue"
},
  "geometry": {"coordinates":[-74.40245299999999,44.912375],"type":"Point"}
}