{
  "type": "Feature",
  "properties": {
    "iso:country":"US",
    "sg:address":"4 State St",
    "sg:city":"Middleport",
    "sg:classifiers":[
        {
            "category":"Restaurant",
            "type":"Food & Drink"
        }
    ],
    "sg:phone":"+1 716 735 7621",
    "sg:postcode":"14105",
    "sg:province":"NY",
    "sg:tags":[
        "pizza"
    ],
    "wof:name":"Village Pizzeria",
    "wof:placetype":"venue"
},
  "geometry": {"coordinates":[-78.47627300000001,43.212479],"type":"Point"}
}