{
  "type": "Feature",
  "properties": {
    "iso:country":"US",
    "sg:address":"810 Broadway",
    "sg:city":"New York",
    "sg:classifiers":[
        {
            "category":"Restaurant",
            "type":"Food & Drink"
        }
    ],
    "sg:phone":"+1 212 388 1884",
    "sg:postcode":"10003",
    "sg:province":"NY",
    "sg:tags":[
        "japanese"
    ],
    "wof:name":"Sushi Ariyoshi",
    "wof:placetype":"venue"
},
  "geometry": {"coordinates":[-73.99088999999999,40.732542],"type":"Point"}
}