{
  "type": "Feature",
  "properties": {
    "addr:full":"5049 Watson Ave Bronx NY 10472",
    "addr:housenumber":"5049",
    "addr:postcode":"10472",
    "addr:street":"Watson Ave",
    "iso:country":"US",
    "sg:address":"5049 Watson Ave",
    "sg:city":"Bronx",
    "sg:classifiers":[
        {
            "category":"Shopping",
            "subcategory":"Computers & Home Electronics",
            "type":"Retail Goods"
        }
    ],
    "sg:phone":"+1   ",
    "sg:postcode":"10472",
    "sg:province":"NY",
    "wof:name":"Botanica San Miguel & St Ana",
    "wof:placetype":"venue"
},
  "geometry": {"coordinates":[-73.850882,40.829638],"type":"Point"}
}