{
  "type": "Feature",
  "properties": {
    "addr:full":"2700 Henry Hudson Pkwy E Bronx NY 10463",
    "addr:housenumber":"2700",
    "addr:postcode":"10463",
    "addr:street":"Henry Hudson Pkwy E",
    "iso:country":"US",
    "sg:address":"2700 Henry Hudson Pkwy E",
    "sg:city":"Bronx",
    "sg:classifiers":[
        {
            "category":"Health Services",
            "subcategory":"Doctor",
            "type":"Services"
        }
    ],
    "sg:phone":"+1 718 543 0604",
    "sg:postcode":"10463",
    "sg:province":"NY",
    "sg:tags":[
        "medical"
    ],
    "wof:name":"Dr Mark Hecht",
    "wof:placetype":"venue"
},
  "geometry": {"coordinates":[-73.915785,40.882469],"type":"Point"}
}