{
  "type": "Feature",
  "properties": {
    "iso:country":"US",
    "sg:address":"1860 Veterans Hwy",
    "sg:city":"Islandia",
    "sg:classifiers":[
        {
            "category":"Shopping",
            "subcategory":"Optician",
            "type":"Retail Goods"
        },
        {
            "category":"Shopping",
            "subcategory":"Beauty & Cosmetics",
            "type":"Retail Goods"
        },
        {
            "category":"Shopping",
            "subcategory":"Pharmacy",
            "type":"Retail Goods"
        }
    ],
    "sg:phone":"+1 631 851 8940",
    "sg:postcode":"11749",
    "sg:province":"NY",
    "sg:tags":[
        "drugstore",
        "eyewear",
        "supply"
    ],
    "sg:website":"www.walgreens.com",
    "wof:name":"Walgreens",
    "wof:placetype":"venue"
},
  "geometry": {"coordinates":[-73.17571700000001,40.801446],"type":"Point"}
}