{
  "type": "Feature",
  "properties": {
    "iso:country":"US",
    "sg:address":"502 7th Ave",
    "sg:city":"Brooklyn",
    "sg:classifiers":[
        {
            "category":"Real Estate",
            "subcategory":"Real Estate Agent",
            "type":"Services"
        }
    ],
    "sg:phone":"+1 718 768 0900",
    "sg:postcode":"11215",
    "sg:province":"NY",
    "wof:name":"Park Ridge Property",
    "wof:placetype":"venue"
},
  "geometry": {"coordinates":[-73.986682,40.66093],"type":"Point"}
}