{
  "type": "Feature",
  "properties": {
    "iso:country":"US",
    "sg:address":"25317 Northern Blvd",
    "sg:city":"Little Neck",
    "sg:classifiers":[
        {
            "category":"Restaurant",
            "type":"Food & Drink"
        }
    ],
    "sg:menulink":"http://www.allmenus.com/ny/queens/131357-greek-islands-restaurant/menu/",
    "sg:phone":"+1 718 279 5922",
    "sg:postcode":"11362",
    "sg:province":"NY",
    "sg:tags":[
        "greek"
    ],
    "wof:name":"Greek Islands Restaurant",
    "wof:placetype":"venue"
},
  "geometry": {"coordinates":[-73.73552599999999,40.770761],"type":"Point"}
}