{
  "type": "Feature",
  "properties": {
    "iso:country":"US",
    "sg:address":"807 Manhattan Ave",
    "sg:city":"Brooklyn",
    "sg:classifiers":[
        {
            "category":"Banks & Credit Unions",
            "subcategory":"Bank",
            "type":"Services"
        }
    ],
    "sg:phone":"+1 718 706 2901",
    "sg:postcode":"11222",
    "sg:province":"NY",
    "sg:website":"www.northforkbank.com",
    "wof:name":"CapitalOne",
    "wof:placetype":"venue"
},
  "geometry": {"coordinates":[-73.95335799999999,40.727967],"type":"Point"}
}