{
  "type": "Feature",
  "properties": {
    "addr:full":"2 Franklin Ave Ste 2 Brooklyn NY 11211",
    "addr:housenumber":"2",
    "addr:postcode":"11211",
    "addr:street":"Franklin Ave Ste 2",
    "iso:country":"US",
    "sg:address":"2 Franklin Ave Ste 2",
    "sg:city":"Brooklyn",
    "sg:classifiers":[
        {
            "category":"Real Estate",
            "subcategory":"Real Estate Services",
            "type":"Services"
        }
    ],
    "sg:phone":"+1 718 222 1500",
    "sg:postcode":"11211",
    "sg:province":"NY",
    "sg:tags":[
        "management",
        "property"
    ],
    "wof:name":"King David Intl Realty",
    "wof:placetype":"venue"
},
  "geometry": {"coordinates":[-73.9589,40.699402],"type":"Point"}
}