{
  "type": "Feature",
  "properties": {
    "iso:country":"US",
    "sg:address":"741 Trim St",
    "sg:city":"Kirkwood",
    "sg:classifiers":[
        {
            "category":"Building & Trades",
            "subcategory":"Construction",
            "type":"Services"
        }
    ],
    "sg:phone":"+1 607 775 2986",
    "sg:postcode":"13795",
    "sg:province":"NY",
    "sg:tags":[
        "general",
        "contractor"
    ],
    "wof:name":"Whitney's Plasterers",
    "wof:placetype":"venue"
},
  "geometry": {"coordinates":[-75.747173,42.075565],"type":"Point"}
}