{
  "type": "Feature",
  "properties": {
    "addr:full":"137 Ludlow St New York NY 10002",
    "addr:housenumber":"137",
    "addr:postcode":"10002",
    "addr:street":"Ludlow St",
    "iso:country":"US",
    "sg:address":"137 Ludlow St",
    "sg:city":"New York",
    "sg:classifiers":[
        {
            "category":"Restaurant",
            "type":"Food & Drink"
        }
    ],
    "sg:phone":"+1 212 529 2153",
    "sg:postcode":"10002",
    "sg:province":"NY",
    "wof:name":"Libation",
    "wof:placetype":"venue"
},
  "geometry": {"coordinates":[-73.98831199999999,40.720397],"type":"Point"}
}