{
  "type": "Feature",
  "properties": {
    "addr:full":"17 Church St Arcade NY 14009",
    "addr:housenumber":"17",
    "addr:postcode":"14009",
    "addr:street":"Church St",
    "iso:country":"US",
    "sg:address":"17 Church St",
    "sg:city":"Arcade",
    "sg:classifiers":[
        {
            "category":"Government",
            "subcategory":"Police Station",
            "type":"Public Place"
        }
    ],
    "sg:phone":"+1 585 492 3111",
    "sg:postcode":"14009",
    "sg:province":"NY",
    "sg:tags":[
        "protection"
    ],
    "wof:name":"Police Department",
    "wof:placetype":"venue"
},
  "geometry": {"coordinates":[-78.424764,42.534878],"type":"Point"}
}