{
  "type": "Feature",
  "properties": {
    "addr:full":"3312 106th St Corona NY 11368",
    "addr:housenumber":"3312",
    "addr:postcode":"11368",
    "addr:street":"106Th St",
    "iso:country":"US",
    "sg:address":"3312 106th St",
    "sg:city":"Corona",
    "sg:classifiers":[
        {
            "category":"Place Of Worship",
            "subcategory":"Church",
            "type":"Public Place"
        },
        {
            "category":"Place Of Worship",
            "type":"Public Place"
        },
        {
            "category":"Organizations",
            "subcategory":"Religious Organization",
            "type":"Services"
        }
    ],
    "sg:phone":"+1 718 803 0149",
    "sg:postcode":"11368",
    "sg:province":"NY",
    "sg:tags":[
        "churches-evangelical",
        "denomination",
        "covenant",
        "churches-interdenominational",
        "churches-covenant",
        "churches-various"
    ],
    "wof:name":"Iglesia Evangelica Pentecoste S",
    "wof:placetype":"venue"
},
  "geometry": {"coordinates":[-73.862925,40.757503],"type":"Point"}
}