{
  "type": "Feature",
  "properties": {
    "iso:country":"US",
    "sg:address":"2221 Jerusalem Ave",
    "sg:city":"Merrick",
    "sg:classifiers":[
        {
            "category":"Education",
            "subcategory":"Music School",
            "type":"Public Place"
        }
    ],
    "sg:phone":"+1 516 765 3360",
    "sg:postcode":"11566",
    "sg:province":"NY",
    "sg:tags":[
        "instrument",
        "teacher",
        "musical"
    ],
    "wof:name":"All Island Music",
    "wof:placetype":"venue"
},
  "geometry": {"coordinates":[-73.55025000000001,40.690673],"type":"Point"}
}