{
  "type": "Feature",
  "properties": {
    "iso:country":"US",
    "sg:address":"2209 Merrick Rd",
    "sg:city":"Merrick",
    "sg:classifiers":[
        {
            "category":"Health Services",
            "subcategory":"Health Practitioner",
            "type":"Services"
        }
    ],
    "sg:phone":"+1 516 771 2623",
    "sg:postcode":"11566",
    "sg:province":"NY",
    "sg:tags":[
        "therapist",
        "physical"
    ],
    "wof:name":"Suydam Physical Therapy",
    "wof:placetype":"venue"
},
  "geometry": {"coordinates":[-73.543345,40.659361],"type":"Point"}
}