{
  "type": "Feature",
  "properties": {
    "iso:country":"US",
    "sg:address":"154 Market St",
    "sg:city":"Potsdam",
    "sg:classifiers":[
        {
            "category":"Home & Garden",
            "subcategory":"Furniture",
            "type":"Retail Goods"
        }
    ],
    "sg:phone":"+1 315 265 3631",
    "sg:postcode":"13676",
    "sg:province":"NY",
    "wof:name":"North Country Rent-To-Own",
    "wof:placetype":"venue"
},
  "geometry": {"coordinates":[-74.986919,44.679887],"type":"Point"}
}