{
  "type": "Feature",
  "properties": {
    "addr:full":"200 Waring Rd Syracuse NY 13224",
    "addr:housenumber":"200",
    "addr:postcode":"13224",
    "addr:street":"Waring Rd",
    "iso:country":"US",
    "sg:address":"200 Waring Rd",
    "sg:city":"Syracuse",
    "sg:classifiers":[
        {
            "category":"Restaurant",
            "type":"Food & Drink"
        }
    ],
    "sg:phone":"+1 315 445 1976",
    "sg:postcode":"13224",
    "sg:province":"NY",
    "wof:name":"Saratoga Steaks & Seafood",
    "wof:placetype":"venue"
},
  "geometry": {"coordinates":[-76.10160999999999,43.0218],"type":"Point"}
}