{
  "type": "Feature",
  "properties": {
    "addr:full":"130 Crotty Rd Middletown NY 10940",
    "addr:housenumber":"130",
    "addr:postcode":"10940",
    "addr:street":"Crotty Rd",
    "iso:country":"US",
    "sg:address":"130 Crotty Rd",
    "sg:city":"Middletown",
    "sg:classifiers":[
        {
            "category":"Manufacturing",
            "subcategory":"Glass & Minerals",
            "type":"Manufacturing & Wholesale Goods"
        }
    ],
    "sg:phone":"+1 845 692 4486",
    "sg:postcode":"10940",
    "sg:province":"NY",
    "sg:tags":[
        "ready",
        "concrete",
        "construction",
        "mfg"
    ],
    "wof:name":"E Tetz & Sons Inc",
    "wof:placetype":"venue"
},
  "geometry": {"coordinates":[-74.34091600000001,41.459087],"type":"Point"}
}