{
  "type": "Feature",
  "properties": {
    "iso:country":"US",
    "sg:address":"195 N Broadway",
    "sg:city":"Hicksville",
    "sg:classifiers":[
        {
            "category":"Retail",
            "subcategory":"Portrait Studio",
            "type":"Services"
        },
        {
            "category":"Professional",
            "subcategory":"Art Services",
            "type":"Services"
        }
    ],
    "sg:phone":"+1 516 933 6515",
    "sg:postcode":"11801",
    "sg:province":"NY",
    "sg:tags":[
        "photographer",
        "photography",
        "store"
    ],
    "wof:name":"Consumer Program Inc",
    "wof:placetype":"venue"
},
  "geometry": {"coordinates":[-73.529099,40.776299],"type":"Point"}
}