{
  "type": "Feature",
  "properties": {
    "addr:full":"28 E 4th St Fl 5 New York NY 10003",
    "addr:housenumber":"28;5",
    "addr:postcode":"10003",
    "addr:street":"E 4Th St",
    "iso:country":"US",
    "sg:address":"28 E 4th St Fl 5",
    "sg:city":"New York",
    "sg:classifiers":[
        {
            "category":"Home & Garden",
            "subcategory":"Garden Supply",
            "type":"Retail Goods"
        }
    ],
    "sg:phone":"+1 212 674 8111",
    "sg:postcode":"10003",
    "sg:province":"NY",
    "sg:tags":[
        "nursery",
        "gardening"
    ],
    "sg:website":"www.plantworksnyc.com",
    "wof:name":"Plantworks Inc",
    "wof:placetype":"venue"
},
  "geometry": {"coordinates":[-73.99279799999999,40.727501],"type":"Point"}
}