{
  "type": "Feature",
  "properties": {
    "iso:country":"US",
    "sg:address":"2770 Sunrise Hwy",
    "sg:city":"Bellmore",
    "sg:classifiers":[
        {
            "category":"Restaurant",
            "type":"Food & Drink"
        }
    ],
    "sg:menulink":"http://www.allmenus.com/ny/bellmore-merrick/58842-piccolo/menu/",
    "sg:phone":"+1 516 679 8787",
    "sg:postcode":"11710",
    "sg:province":"NY",
    "sg:tags":[
        "italian"
    ],
    "wof:name":"Piccolo",
    "wof:placetype":"venue"
},
  "geometry": {"coordinates":[-73.525064,40.669105],"type":"Point"}
}