{
  "type": "Feature",
  "properties": {
    "addr:full":"2465 Broadway New York NY 10025",
    "addr:housenumber":"2465",
    "addr:postcode":"10025",
    "addr:street":"Broadway",
    "iso:country":"US",
    "sg:address":"2465 Broadway",
    "sg:city":"New York",
    "sg:classifiers":[
        {
            "category":"Health Services",
            "subcategory":"Optometrist",
            "type":"Services"
        },
        {
            "category":"Health Services",
            "subcategory":"Doctor",
            "type":"Services"
        }
    ],
    "sg:phone":"+1 212 496 4600",
    "sg:postcode":"10025",
    "sg:province":"NY",
    "sg:tags":[
        "ophthalmologist",
        "practice",
        "family"
    ],
    "sg:website":"www.mpgcares.com",
    "wof:name":"Manhattan's Physician Group",
    "wof:placetype":"venue"
},
  "geometry": {"coordinates":[-73.974346,40.791978],"type":"Point"}
}