{
  "type": "Feature",
  "properties": {
    "iso:country":"US",
    "sg:address":"1484 Welcher Rd",
    "sg:city":"Newark",
    "sg:classifiers":[
        {
            "category":"Retail",
            "subcategory":"Repair Shop",
            "type":"Services"
        }
    ],
    "sg:phone":"+1 315 331 2521",
    "sg:postcode":"14513",
    "sg:province":"NY",
    "sg:tags":[
        "lawn",
        "mower"
    ],
    "wof:name":"Arcadia Lawn Mower",
    "wof:placetype":"venue"
},
  "geometry": {"coordinates":[-77.09173800000001,43.063725],"type":"Point"}
}