{
  "type": "Feature",
  "properties": {
    "addr:full":"1208 State Rte 104 Ontario NY 14519",
    "addr:housenumber":"1208",
    "addr:postcode":"14519",
    "addr:street":"State Rte 104",
    "iso:country":"US",
    "sg:address":"1208 State Rte 104",
    "sg:city":"Ontario",
    "sg:classifiers":[
        {
            "category":"Restaurant",
            "type":"Food & Drink"
        }
    ],
    "sg:phone":"+1   ",
    "sg:postcode":"14519",
    "sg:province":"NY",
    "sg:tags":[
        "eating"
    ],
    "wof:name":"Pizza Hut",
    "wof:placetype":"venue"
},
  "geometry": {"coordinates":[-77.306408,43.227627],"type":"Point"}
}