{
  "type": "Feature",
  "properties": {
    "addr:full":"646 10th Ave New York NY 10036",
    "addr:housenumber":"646",
    "addr:postcode":"10036",
    "addr:street":"10Th Ave",
    "iso:country":"US",
    "sg:address":"646 10th Ave",
    "sg:city":"New York",
    "sg:classifiers":[
        {
            "category":"Shopping",
            "subcategory":"Pharmacy",
            "type":"Retail Goods"
        }
    ],
    "sg:phone":"+1 212 956 1100",
    "sg:postcode":"10036",
    "sg:province":"NY",
    "sg:tags":[
        "drugstore"
    ],
    "sg:website":"www.thriftwaynyc.com",
    "wof:name":"Thriftway Pharmacy NYC",
    "wof:placetype":"venue"
},
  "geometry": {"coordinates":[-73.99354700000001,40.76183],"type":"Point"}
}