{
  "type": "Feature",
  "properties": {
    "addr:full":"35 Rancho Dr Cortlandt Manor NY 10567",
    "addr:housenumber":"35",
    "addr:postcode":"10567",
    "addr:street":"Rancho Dr Cortlandt",
    "iso:country":"US",
    "sg:address":"35 Rancho Dr",
    "sg:city":"Cortlandt Manor",
    "sg:classifiers":[
        {
            "category":"Building & Trades",
            "subcategory":"Construction",
            "type":"Services"
        }
    ],
    "sg:phone":"+1 914 734 9739",
    "sg:postcode":"10567",
    "sg:province":"NY",
    "sg:tags":[
        "house"
    ],
    "wof:name":"Alto Contracting Inc",
    "wof:placetype":"venue"
},
  "geometry": {"coordinates":[-73.896394,41.307432],"type":"Point"}
}