{
  "type": "Feature",
  "properties": {
    "iso:country":"US",
    "sg:address":"3325 E Main Street Rd",
    "sg:city":"Attica",
    "sg:classifiers":[
        {
            "category":"Health Services",
            "subcategory":"Doctor",
            "type":"Services"
        }
    ],
    "sg:phone":"+1 585 591 0800",
    "sg:postcode":"14011",
    "sg:province":"NY",
    "sg:tags":[
        "physician",
        "family",
        "practice",
        "surgeons",
        "medicine",
        "surgeon"
    ],
    "wof:name":"O S Khokhar Md",
    "wof:placetype":"venue"
},
  "geometry": {"coordinates":[-78.260245,42.861898],"type":"Point"}
}