{
  "type": "Feature",
  "properties": {
    "addr:full":"1262 S Main St Elmira NY 14904",
    "addr:housenumber":"1262",
    "addr:postcode":"14904",
    "addr:street":"S Main St",
    "iso:country":"US",
    "sg:address":"1262 S Main St",
    "sg:city":"Elmira",
    "sg:classifiers":[
        {
            "category":"Autos & Motor Vehicles",
            "subcategory":"Automobile Sales",
            "type":"Retail Goods"
        }
    ],
    "sg:phone":"+1 607 737 5065",
    "sg:postcode":"14904",
    "sg:province":"NY",
    "sg:tags":[
        "car",
        "dealer"
    ],
    "wof:name":"Dalton Auto Sales",
    "wof:placetype":"venue"
},
  "geometry": {"coordinates":[-76.79274599999999,42.058811],"type":"Point"}
}