{
  "type": "Feature",
  "properties": {
    "iso:country":"US",
    "sg:address":"400 Rella Blvd",
    "sg:city":"Suffern",
    "sg:classifiers":[
        {
            "category":"Home & Garden",
            "subcategory":"Carpets & Floor Coverings",
            "type":"Retail Goods"
        },
        {
            "category":"Building & Trades",
            "subcategory":"Construction",
            "type":"Services"
        }
    ],
    "sg:phone":"+1 845 369 6555",
    "sg:postcode":"10901",
    "sg:province":"NY",
    "sg:tags":[
        "resurfacing",
        "work",
        "laying",
        "refinishing"
    ],
    "wof:name":"Pinnacle Flooring LLC",
    "wof:placetype":"venue"
},
  "geometry": {"coordinates":[-74.10944000000001,41.118237],"type":"Point"}
}