{
  "type": "Feature",
  "properties": {
    "addr:full":"67 Main St Brewster NY 10509",
    "addr:housenumber":"67",
    "addr:postcode":"10509",
    "addr:street":"Main St",
    "iso:country":"US",
    "sg:address":"67 Main St",
    "sg:city":"Brewster",
    "sg:classifiers":[
        {
            "category":"Government",
            "subcategory":"Office",
            "type":"Public Place"
        }
    ],
    "sg:phone":"+1 845 279 9164",
    "sg:postcode":"10509",
    "sg:province":"NY",
    "sg:tags":[
        "village"
    ],
    "wof:name":"Brewster North Parking",
    "wof:placetype":"venue"
},
  "geometry": {"coordinates":[-73.618386,41.394321],"type":"Point"}
}