{
  "type": "Feature",
  "properties": {
    "iso:country":"US",
    "sg:address":"535 W 22 St",
    "sg:city":"New York",
    "sg:classifiers":[
        {
            "category":"Shopping",
            "subcategory":"Catalog Store",
            "type":"Retail Goods"
        }
    ],
    "sg:phone":"+1 212 925 0325",
    "sg:postcode":"10011",
    "sg:province":"NY",
    "sg:tags":[
        "mail",
        "book",
        "house"
    ],
    "wof:name":"Printed Matter Bookstore",
    "wof:placetype":"venue"
},
  "geometry": {"coordinates":[-74.007075,40.74808],"type":"Point"}
}