{
  "type": "Feature",
  "properties": {
    "iso:country":"US",
    "sg:address":"291 Echo Ave",
    "sg:city":"Sound Beach",
    "sg:classifiers":[
        {
            "category":"Personal",
            "subcategory":"Barber",
            "type":"Services"
        }
    ],
    "sg:phone":"+1 631 209 2075",
    "sg:postcode":"11789",
    "sg:province":"NY",
    "wof:name":"Impressive Cuts Barber Shop",
    "wof:placetype":"venue"
},
  "geometry": {"coordinates":[-72.981718,40.953499],"type":"Point"}
}