{
  "type": "Feature",
  "properties": {
    "addr:full":"242 E 137th St Bronx NY 10451",
    "addr:housenumber":"242",
    "addr:postcode":"10451",
    "addr:street":"E 137Th St",
    "iso:country":"US",
    "sg:address":"242 E 137th St",
    "sg:city":"Bronx",
    "sg:classifiers":[
        {
            "category":"Manufacturing",
            "subcategory":"Textiles",
            "type":"Manufacturing & Wholesale Goods"
        }
    ],
    "sg:phone":"+1 718 401 0759",
    "sg:postcode":"10451",
    "sg:province":"NY",
    "wof:name":"Anmertex Textiles Svc",
    "wof:placetype":"venue"
},
  "geometry": {"coordinates":[-73.928133,40.810499],"type":"Point"}
}