{
  "type": "Feature",
  "properties": {
    "iso:country":"US",
    "sg:address":"10720 Liberty Ave",
    "sg:city":"Ozone Park",
    "sg:classifiers":[
        {
            "category":"Deli",
            "type":"Food & Drink"
        },
        {
            "category":"Food & Beverages",
            "subcategory":"Bakery",
            "type":"Retail Goods"
        }
    ],
    "sg:phone":"+1 718 641 6365",
    "sg:postcode":"11417",
    "sg:province":"NY",
    "sg:tags":[
        "sandwich"
    ],
    "wof:name":"Two Way Deli Grocery Corp",
    "wof:placetype":"venue"
},
  "geometry": {"coordinates":[-73.83413899999999,40.683337],"type":"Point"}
}