{
  "type": "Feature",
  "properties": {
    "addr:full":"900 South Ave Staten Island NY 10314",
    "addr:housenumber":"900",
    "addr:postcode":"10314",
    "addr:street":"South Ave",
    "iso:country":"US",
    "sg:address":"900 South Ave",
    "sg:city":"Staten Island",
    "sg:classifiers":[
        {
            "category":"Restaurant",
            "type":"Food & Drink"
        }
    ],
    "sg:phone":"+1 718 568 2258",
    "sg:postcode":"10314",
    "sg:province":"NY",
    "wof:name":"P & J Enterprises",
    "wof:placetype":"venue"
},
  "geometry": {"coordinates":[-74.173721,40.615186],"type":"Point"}
}