{
  "type": "Feature",
  "properties": {
    "iso:country":"US",
    "sg:address":"171 Valley Rd",
    "sg:city":"New Rochelle",
    "sg:classifiers":[
        {
            "category":"Travel",
            "subcategory":"Travel Agent",
            "type":"Entertainment"
        }
    ],
    "sg:phone":"+1   ",
    "sg:postcode":"10804",
    "sg:province":"NY",
    "sg:tags":[
        "agency"
    ],
    "wof:name":"Principe Imports",
    "wof:placetype":"venue"
},
  "geometry": {"coordinates":[-73.790736,40.940759],"type":"Point"}
}