{
  "type": "Feature",
  "properties": {
    "iso:country":"US",
    "sg:address":"25 Corporate Dr",
    "sg:city":"Holtsville",
    "sg:classifiers":[
        {
            "category":"Building & Trades",
            "subcategory":"Equipment Rental",
            "type":"Services"
        }
    ],
    "sg:phone":"+1   ",
    "sg:postcode":"11742",
    "sg:province":"NY",
    "sg:tags":[
        "medical",
        "retail",
        "rent",
        "supply"
    ],
    "wof:name":"Prime Care Medical Supplies",
    "wof:placetype":"venue"
},
  "geometry": {"coordinates":[-73.039264,40.801074],"type":"Point"}
}