{
  "type": "Feature",
  "properties": {
    "iso:country":"US",
    "sg:address":"7014 Begole Rd",
    "sg:city":"Mount Morris",
    "sg:phone":"+1 585 658 4601",
    "sg:postcode":"14510",
    "sg:province":"NY",
    "sg:tags":[
        "wheat",
        "f",
        "farm",
        "corn",
        "cash",
        "grain"
    ],
    "wof:name":"Osage Farm",
    "wof:placetype":"venue"
},
  "geometry": {"coordinates":[-77.87761999999999,42.683927],"type":"Point"}
}