{
  "type": "Feature",
  "properties": {
    "addr:full":"49 Mahan St West Babylon NY 11704",
    "addr:housenumber":"49",
    "addr:postcode":"11704",
    "addr:street":"Mahan St",
    "iso:country":"US",
    "sg:address":"49 Mahan St",
    "sg:city":"West Babylon",
    "sg:classifiers":[
        {
            "category":"Manufacturing",
            "subcategory":"Paper Products",
            "type":"Manufacturing & Wholesale Goods"
        }
    ],
    "sg:phone":"+1 631 563 8801",
    "sg:postcode":"11704",
    "sg:province":"NY",
    "sg:tags":[
        "label"
    ],
    "wof:name":"Superior Label Co",
    "wof:placetype":"venue"
},
  "geometry": {"coordinates":[-73.37791199999999,40.739525],"type":"Point"}
}