{
  "type": "Feature",
  "properties": {
    "addr:full":"35 Broadway Freeport NY 11520",
    "addr:housenumber":"35",
    "addr:postcode":"11520",
    "addr:street":"Broadway",
    "iso:country":"US",
    "sg:address":"35 Broadway",
    "sg:city":"Freeport",
    "sg:classifiers":[
        {
            "category":"Retail",
            "subcategory":"Laundry & Dry Cleaning",
            "type":"Services"
        }
    ],
    "sg:phone":"+1 516 378 9144",
    "sg:postcode":"11520",
    "sg:province":"NY",
    "sg:tags":[
        "cleaners"
    ],
    "wof:name":"Comet Drive In Cleaners",
    "wof:placetype":"venue"
},
  "geometry": {"coordinates":[-73.58244999999999,40.658263],"type":"Point"}
}