{
  "type": "Feature",
  "properties": {
    "addr:full":"756 Utica Ave Brooklyn NY 11203",
    "addr:housenumber":"756",
    "addr:postcode":"11203",
    "addr:street":"Utica Ave",
    "iso:country":"US",
    "sg:address":"756 Utica Ave",
    "sg:city":"Brooklyn",
    "sg:classifiers":[
        {
            "category":"Autos & Motor Vehicles",
            "subcategory":"Fuel & Gas Station",
            "type":"Retail Goods"
        }
    ],
    "sg:phone":"+1 718 245 1400",
    "sg:postcode":"11203",
    "sg:province":"NY",
    "sg:website":"www.bp.com/heliospower/modularho...",
    "wof:name":"Madelyn Barker",
    "wof:placetype":"venue"
},
  "geometry": {"coordinates":[-73.930881,40.654785],"type":"Point"}
}