{
  "type": "Feature",
  "properties": {
    "addr:full":"47 Co Rd 9 Gouverneur NY 13642",
    "addr:housenumber":"47;9",
    "addr:postcode":"13642",
    "addr:street":"Co Rd",
    "iso:country":"US",
    "sg:address":"47 Co Rd 9",
    "sg:city":"Gouverneur",
    "sg:classifiers":[
        {
            "category":"Freight",
            "type":"Transportation"
        }
    ],
    "sg:phone":"+1   ",
    "sg:postcode":"13642",
    "sg:province":"NY",
    "sg:tags":[
        "operator",
        "local",
        "trucking"
    ],
    "wof:name":"DNB Trash Removal",
    "wof:placetype":"venue"
},
  "geometry": {"coordinates":[-75.53532800000001,44.259718],"type":"Point"}
}