{
  "type": "Feature",
  "properties": {
    "iso:country":"US",
    "sg:address":"702 Locust St",
    "sg:city":"Mt Vernon",
    "sg:classifiers":[
        {
            "category":"Personal",
            "subcategory":"Beauty Salon",
            "type":"Services"
        }
    ],
    "sg:phone":"+1 914 663 6205",
    "sg:postcode":"10552",
    "sg:province":"NY",
    "wof:name":"Artistic Touch Hair Salon",
    "wof:placetype":"venue"
},
  "geometry": {"coordinates":[-73.83913699999999,40.926497],"type":"Point"}
}