{
  "type": "Feature",
  "properties": {
    "iso:country":"US",
    "sg:address":"119 S Main St",
    "sg:city":"Delevan",
    "sg:phone":"+1 716 492 2115",
    "sg:postcode":"14042",
    "sg:province":"NY",
    "sg:tags":[
        "farm",
        "field",
        "crop"
    ],
    "wof:name":"Bradley Marble",
    "wof:placetype":"venue"
},
  "geometry": {"coordinates":[-78.480582,42.482284],"type":"Point"}
}