{
  "type": "Feature",
  "properties": {
    "addr:full":"35 Freemans Bridge Rd Scotia NY 12302",
    "addr:housenumber":"35",
    "addr:postcode":"12302",
    "addr:street":"Freemans Bridge Rd",
    "iso:country":"US",
    "sg:address":"35 Freemans Bridge Rd",
    "sg:city":"Scotia",
    "sg:classifiers":[
        {
            "category":"Retail",
            "subcategory":"Auto Repair",
            "type":"Services"
        }
    ],
    "sg:phone":"+1 518 377 5370",
    "sg:postcode":"12302",
    "sg:province":"NY",
    "sg:tags":[
        "repairing",
        "automobile"
    ],
    "wof:name":"Riverview Auto Sales LLC",
    "wof:placetype":"venue"
},
  "geometry": {"coordinates":[-73.93261699999999,42.835324],"type":"Point"}
}