{
  "type": "Feature",
  "properties": {
    "addr:full":"2239 Grand Ave Bronx NY 10453",
    "addr:housenumber":"2239",
    "addr:postcode":"10453",
    "addr:street":"Grand Ave",
    "iso:country":"US",
    "sg:address":"2239 Grand Ave",
    "sg:city":"Bronx",
    "sg:classifiers":[
        {
            "category":"Health Services",
            "subcategory":"Doctor",
            "type":"Services"
        }
    ],
    "sg:phone":"+1 718 295 8699",
    "sg:postcode":"10453",
    "sg:province":"NY",
    "sg:tags":[
        "medical"
    ],
    "wof:name":"Assoc Advanc For The Advanceme",
    "wof:placetype":"venue"
},
  "geometry": {"coordinates":[-73.90642,40.857865],"type":"Point"}
}