{
  "type": "Feature",
  "properties": {
    "iso:country":"US",
    "sg:address":"167 Bettridge Rd",
    "sg:city":"Churchville",
    "sg:classifiers":[
        {
            "category":"Autos & Motor Vehicles",
            "subcategory":"Auto Supplies",
            "type":"Retail Goods"
        }
    ],
    "sg:phone":"+1   ",
    "sg:postcode":"14428",
    "sg:province":"NY",
    "sg:tags":[
        "automobile",
        "parts",
        "classic"
    ],
    "wof:name":"Lt Classic Auto Parts",
    "wof:placetype":"venue"
},
  "geometry": {"coordinates":[-77.827719,43.072907],"type":"Point"}
}