{
  "type": "Feature",
  "properties": {
    "addr:full":"203 Massachusetts Ave Massapequa NY 11758",
    "addr:housenumber":"203",
    "addr:postcode":"11758",
    "addr:street":"Massachusetts Ave",
    "iso:country":"US",
    "sg:address":"203 Massachusetts Ave",
    "sg:city":"Massapequa",
    "sg:classifiers":[
        {
            "category":"Insurance",
            "subcategory":"Insurance Agent",
            "type":"Services"
        }
    ],
    "sg:phone":"+1 516 795 5273",
    "sg:postcode":"11758",
    "sg:province":"NY",
    "wof:name":"Selected Benefits",
    "wof:placetype":"venue"
},
  "geometry": {"coordinates":[-73.46306300000001,40.687817],"type":"Point"}
}