{
  "type": "Feature",
  "properties": {
    "addr:full":"145 2nd Ave New York NY 10003",
    "addr:housenumber":"145",
    "addr:postcode":"10003",
    "addr:street":"2Nd Ave",
    "iso:country":"US",
    "sg:address":"145 2nd Ave",
    "sg:city":"New York",
    "sg:classifiers":[
        {
            "category":"Coffee & Tea",
            "type":"Food & Drink"
        }
    ],
    "sg:menulink":"http://www.allmenus.com/ny/new-york/113398-starbucks-coffee/menu/",
    "sg:phone":"+1 212 780 0024",
    "sg:postcode":"10003",
    "sg:province":"NY",
    "sg:tags":[
        "american"
    ],
    "wof:name":"Starbucks Coffee",
    "wof:placetype":"venue"
},
  "geometry": {"coordinates":[-73.987459,40.729463],"type":"Point"}
}