{
  "type": "Feature",
  "properties": {
    "iso:country":"US",
    "sg:address":"271 Stone Schoolhouse Rd",
    "sg:city":"Bloomingburg",
    "sg:classifiers":[
        {
            "category":"Manufacturing",
            "subcategory":"Printing",
            "type":"Manufacturing & Wholesale Goods"
        }
    ],
    "sg:phone":"+1 845 733 4404",
    "sg:postcode":"12721",
    "sg:province":"NY",
    "sg:tags":[
        "newspaper"
    ],
    "wof:name":"D & H Canvas",
    "wof:placetype":"venue"
},
  "geometry": {"coordinates":[-74.400674,41.568411],"type":"Point"}
}