{
  "type": "Feature",
  "properties": {
    "iso:country":"US",
    "sg:address":"13 E 37th St",
    "sg:city":"New York",
    "sg:classifiers":[
        {
            "category":"Professional",
            "type":"Services"
        }
    ],
    "sg:phone":"+1 212 685 7354",
    "sg:postcode":"10016",
    "sg:province":"NY",
    "sg:tags":[
        "establishment"
    ],
    "wof:name":"John Francis Borrelli Archtct",
    "wof:placetype":"venue"
},
  "geometry": {"coordinates":[-73.97995299999999,40.748985],"type":"Point"}
}