{
  "type": "Feature",
  "properties": {
    "addr:full":"104 E 183rd Street Bronx NY 10453",
    "addr:housenumber":"104",
    "addr:postcode":"10453",
    "addr:street":"E 183Rd Street",
    "iso:country":"US",
    "sg:address":"104 E 183rd Street",
    "sg:city":"Bronx",
    "sg:classifiers":[
        {
            "category":"Restaurant",
            "type":"Food & Drink"
        }
    ],
    "sg:phone":"+1 718 367 4779",
    "sg:postcode":"10453",
    "sg:province":"NY",
    "wof:name":"Juans Restaurant",
    "wof:placetype":"venue"
},
  "geometry": {"coordinates":[-73.90182799999999,40.857941],"type":"Point"}
}