{
  "type": "Feature",
  "properties": {
    "iso:country":"US",
    "sg:address":"221 Commack Rd",
    "sg:city":"Commack",
    "sg:classifiers":[
        {
            "category":"Personal",
            "subcategory":"Beauty Salon",
            "type":"Services"
        }
    ],
    "sg:phone":"+1 631 462 0500",
    "sg:postcode":"11725",
    "sg:province":"NY",
    "wof:name":"Sensational",
    "wof:placetype":"venue"
},
  "geometry": {"coordinates":[-73.294785,40.837518],"type":"Point"}
}