{
  "type": "Feature",
  "properties": {
    "addr:full":"394 Flatbush Ave Brooklyn NY 11238",
    "addr:housenumber":"394",
    "addr:postcode":"11238",
    "addr:street":"Flatbush Ave",
    "iso:country":"US",
    "sg:address":"394 Flatbush Ave",
    "sg:city":"Brooklyn",
    "sg:classifiers":[
        {
            "category":"Personal",
            "subcategory":"Beauty Salon",
            "type":"Services"
        }
    ],
    "sg:phone":"+1   ",
    "sg:postcode":"11238",
    "sg:province":"NY",
    "sg:tags":[
        "shop"
    ],
    "wof:name":"Rokia Hair Braiding",
    "wof:placetype":"venue"
},
  "geometry": {"coordinates":[-73.97087399999999,40.675045],"type":"Point"}
}