{
  "type": "Feature",
  "properties": {
    "iso:country":"US",
    "sg:address":"1450 42nd St",
    "sg:city":"Brooklyn",
    "sg:classifiers":[
        {
            "category":"Wholesale",
            "subcategory":"Jewelry",
            "type":"Manufacturing & Wholesale Goods"
        }
    ],
    "sg:phone":"+1 718 853 4765",
    "sg:postcode":"11219",
    "sg:province":"NY",
    "sg:tags":[
        "silver"
    ],
    "wof:name":"King Silver Inc",
    "wof:placetype":"venue"
},
  "geometry": {"coordinates":[-73.984533,40.636905],"type":"Point"}
}