{
  "type": "Feature",
  "properties": {
    "iso:country":"US",
    "sg:address":"124 Maple Ave",
    "sg:city":"Bay Shore",
    "sg:classifiers":[
        {
            "category":"Bars & Pubs",
            "type":"Food & Drink"
        }
    ],
    "sg:menulink":"http://www.allmenus.com/ny/islip/229580-molly-malones-waterfront-pub--restaurant/menu/",
    "sg:phone":"+1 631 969 2232",
    "sg:postcode":"11706",
    "sg:province":"NY",
    "sg:tags":[
        "irish"
    ],
    "wof:name":"Molly Malone's Waterfront Pub & Restaurant",
    "wof:placetype":"venue"
},
  "geometry": {"coordinates":[-73.24078299999999,40.71519],"type":"Point"}
}