{
  "type": "Feature",
  "properties": {
    "addr:full":"600 W 187th St New York NY 10033",
    "addr:housenumber":"600",
    "addr:postcode":"10033",
    "addr:street":"W 187Th St",
    "iso:country":"US",
    "sg:address":"600 W 187th St",
    "sg:city":"New York",
    "sg:classifiers":[
        {
            "category":"Real Estate",
            "subcategory":"Real Estate Operator",
            "type":"Services"
        }
    ],
    "sg:phone":"+1 212 923 6999",
    "sg:postcode":"10033",
    "sg:province":"NY",
    "sg:tags":[
        "building",
        "apartment",
        "an"
    ],
    "wof:name":"West 187 St Properties Inc",
    "wof:placetype":"venue"
},
  "geometry": {"coordinates":[-73.93222799999999,40.853581],"type":"Point"}
}