{
  "type": "Feature",
  "properties": {
    "addr:full":"146 Quassaick Ave New Windsor NY 12553",
    "addr:housenumber":"146",
    "addr:postcode":"12553",
    "addr:street":"Quassaick Ave",
    "iso:country":"US",
    "sg:address":"146 Quassaick Ave",
    "sg:city":"New Windsor",
    "sg:classifiers":[
        {
            "category":"Building & Trades",
            "subcategory":"Construction",
            "type":"Services"
        }
    ],
    "sg:phone":"+1 845 561 0489",
    "sg:postcode":"12553",
    "sg:province":"NY",
    "sg:tags":[
        "contractor"
    ],
    "wof:name":"Lucas Michael Fire Restoration",
    "wof:placetype":"venue"
},
  "geometry": {"coordinates":[-74.01979799999999,41.481998],"type":"Point"}
}