{
  "type": "Feature",
  "properties": {
    "addr:full":"62 Fulton St White Plains NY 10606",
    "addr:housenumber":"62",
    "addr:postcode":"10606",
    "addr:street":"Fulton St",
    "iso:country":"US",
    "sg:address":"62 Fulton St",
    "sg:city":"White Plains",
    "sg:classifiers":[
        {
            "category":"Building & Trades",
            "subcategory":"Electrical",
            "type":"Services"
        }
    ],
    "sg:phone":"+1 914 683 6831",
    "sg:postcode":"10606",
    "sg:province":"NY",
    "sg:tags":[
        "electrical",
        "contractor"
    ],
    "wof:name":"Ampul Electric Inc",
    "wof:placetype":"venue"
},
  "geometry": {"coordinates":[-73.78477700000001,41.035048],"type":"Point"}
}