{
  "type": "Feature",
  "properties": {
    "iso:country":"US",
    "sg:address":"1080 Long Island Ave",
    "sg:city":"Deer Park",
    "sg:classifiers":[
        {
            "category":"Retail",
            "subcategory":"Repair Shop",
            "type":"Services"
        }
    ],
    "sg:phone":"+1 631 243 1361",
    "sg:postcode":"11729",
    "sg:province":"NY",
    "sg:tags":[
        "lighting",
        "fixture"
    ],
    "wof:name":"Daylight Lighting Svc",
    "wof:placetype":"venue"
},
  "geometry": {"coordinates":[-73.29529700000001,40.770143],"type":"Point"}
}