{
  "type": "Feature",
  "properties": {
    "addr:full":"27 Shadow Ln Larchmont NY 10538",
    "addr:housenumber":"27",
    "addr:postcode":"10538",
    "addr:street":"Shadow Ln",
    "iso:country":"US",
    "sg:address":"27 Shadow Ln",
    "sg:city":"Larchmont",
    "sg:classifiers":[
        {
            "category":"Health Services",
            "subcategory":"Doctor",
            "type":"Services"
        }
    ],
    "sg:phone":"+1 914 834 0059",
    "sg:postcode":"10538",
    "sg:province":"NY",
    "sg:tags":[
        "medical"
    ],
    "wof:name":"Finkelstein BR",
    "wof:placetype":"venue"
},
  "geometry": {"coordinates":[-73.762511,40.927588],"type":"Point"}
}