{
  "type": "Feature",
  "properties": {
    "addr:full":"133 Woodbine Ave Northport NY 11768",
    "addr:housenumber":"133",
    "addr:postcode":"11768",
    "addr:street":"Woodbine Ave",
    "iso:country":"US",
    "sg:address":"133 Woodbine Ave",
    "sg:city":"Northport",
    "sg:classifiers":[
        {
            "category":"Professional",
            "subcategory":"Computer Services",
            "type":"Services"
        }
    ],
    "sg:phone":"+1   ",
    "sg:postcode":"11768",
    "sg:province":"NY",
    "sg:tags":[
        "travel",
        "agency",
        "programing",
        "custom"
    ],
    "wof:name":"Identry LLC",
    "wof:placetype":"venue"
},
  "geometry": {"coordinates":[-73.351786,40.900057],"type":"Point"}
}