{
  "type": "Feature",
  "properties": {
    "addr:full":"1228 Madison Ave New York NY 10128",
    "addr:housenumber":"1228",
    "addr:postcode":"10128",
    "addr:street":"Madison Ave",
    "iso:country":"US",
    "sg:address":"1228 Madison Ave",
    "sg:city":"New York",
    "sg:classifiers":[
        {
            "category":"Shopping",
            "subcategory":"Photographic Equipment",
            "type":"Retail Goods"
        }
    ],
    "sg:phone":"+1   ",
    "sg:postcode":"10128",
    "sg:province":"NY",
    "sg:tags":[
        "leather",
        "camera",
        "supply",
        "g",
        "luggage"
    ],
    "wof:name":"Moormends Luggage & Cameras",
    "wof:placetype":"venue"
},
  "geometry": {"coordinates":[-73.957702,40.782406],"type":"Point"}
}