{
  "type": "Feature",
  "properties": {
    "addr:full":"223 E 66 St New York NY 10065",
    "addr:housenumber":"223;66",
    "addr:postcode":"10065",
    "addr:street":"E;St",
    "iso:country":"US",
    "sg:address":"223 E 66 St",
    "sg:city":"New York",
    "sg:classifiers":[
        {
            "category":"Professional",
            "subcategory":"Business Services",
            "type":"Services"
        }
    ],
    "sg:phone":"+1   ",
    "sg:postcode":"10065",
    "sg:province":"NY",
    "sg:tags":[
        "interior",
        "design"
    ],
    "wof:name":"Suzanne Earls Carr Inc",
    "wof:placetype":"venue"
},
  "geometry": {"coordinates":[-73.961822,40.765385],"type":"Point"}
}