{
  "type": "Feature",
  "properties": {
    "iso:country":"US",
    "sg:address":"40 Holden Blvd",
    "sg:city":"Staten Island",
    "sg:classifiers":[
        {
            "category":"Building & Trades",
            "subcategory":"Plumbing",
            "type":"Services"
        }
    ],
    "sg:phone":"+1 718 816 1458",
    "sg:postcode":"10314",
    "sg:province":"NY",
    "sg:tags":[
        "heating",
        "contractor"
    ],
    "wof:name":"J & S Plumbing & Heating Inc",
    "wof:placetype":"venue"
},
  "geometry": {"coordinates":[-74.122243,40.604238],"type":"Point"}
}