{
  "type": "Feature",
  "properties": {
    "iso:country":"US",
    "sg:address":"271 E Main St",
    "sg:city":"Springville",
    "sg:classifiers":[
        {
            "category":"Retail",
            "subcategory":"Funeral Services",
            "type":"Services"
        }
    ],
    "sg:phone":"+1 716 592 7822",
    "sg:postcode":"14141",
    "sg:province":"NY",
    "sg:tags":[
        "director"
    ],
    "wof:name":"Smith Weismantel Funeral Home",
    "wof:placetype":"venue"
},
  "geometry": {"coordinates":[-78.65818299999999,42.508406],"type":"Point"}
}