{
  "type": "Feature",
  "properties": {
    "iso:country":"US",
    "sg:address":"775 University Ave",
    "sg:city":"Rochester",
    "sg:classifiers":[
        {
            "category":"Wholesale",
            "subcategory":"Non-durable Goods",
            "type":"Manufacturing & Wholesale Goods"
        }
    ],
    "sg:phone":"+1 585 473 5172",
    "sg:postcode":"14607",
    "sg:province":"NY",
    "sg:tags":[
        "advertising"
    ],
    "wof:name":"National Advertising Co",
    "wof:placetype":"venue"
},
  "geometry": {"coordinates":[-77.581217,43.154713],"type":"Point"}
}