{
  "type": "Feature",
  "properties": {
    "iso:country":"US",
    "sg:address":"1 Stewart Ave",
    "sg:city":"Hicksville",
    "sg:classifiers":[
        {
            "category":"Park",
            "type":"Public Place"
        }
    ],
    "sg:phone":"+1 516 733 8404",
    "sg:postcode":"11801",
    "sg:province":"NY",
    "wof:name":"Oyster Bay Town of",
    "wof:placetype":"venue"
},
  "geometry": {"coordinates":[-73.537102,40.7477],"type":"Point"}
}