{
  "type": "Feature",
  "properties": {
    "iso:country":"US",
    "sg:address":"67 Ward Rd",
    "sg:city":"Salt Point",
    "sg:classifiers":[
        {
            "category":"Building & Trades",
            "subcategory":"Construction",
            "type":"Services"
        }
    ],
    "sg:phone":"+1 845 266 8700",
    "sg:postcode":"12578",
    "sg:province":"NY",
    "sg:tags":[
        "painter"
    ],
    "sg:website":"www.millenniumpainting.com",
    "wof:name":"Millennium Painting Inc",
    "wof:placetype":"venue"
},
  "geometry": {"coordinates":[-73.840748,41.807762],"type":"Point"}
}