{
  "type": "Feature",
  "properties": {
    "addr:full":"135 E 57th St New York NY 10022",
    "addr:housenumber":"135",
    "addr:postcode":"10022",
    "addr:street":"E 57Th St",
    "iso:country":"US",
    "sg:address":"135 E 57th St",
    "sg:city":"New York",
    "sg:classifiers":[
        {
            "category":"Banks & Credit Unions",
            "subcategory":"Financial Services",
            "type":"Services"
        }
    ],
    "sg:phone":"+1 212 659 0170",
    "sg:postcode":"10022",
    "sg:province":"NY",
    "sg:website":"www.guggenheimpartners.com",
    "wof:name":"Guggenheim Partners",
    "wof:placetype":"venue"
},
  "geometry": {"coordinates":[-73.96939500000001,40.761355],"type":"Point"}
}