{
  "type": "Feature",
  "properties": {
    "addr:full":"732 10th Ave New York NY 10019",
    "addr:housenumber":"732",
    "addr:postcode":"10019",
    "addr:street":"10Th Ave",
    "iso:country":"US",
    "sg:address":"732 10th Ave",
    "sg:city":"New York",
    "sg:classifiers":[
        {
            "category":"Shopping",
            "subcategory":"Department Store",
            "type":"Retail Goods"
        }
    ],
    "sg:phone":"+1 212 977 3500",
    "sg:postcode":"10019",
    "sg:province":"NY",
    "wof:name":"Ramses At 10 Ave Corp",
    "wof:placetype":"venue"
},
  "geometry": {"coordinates":[-73.991632,40.764619],"type":"Point"}
}