{
  "type": "Feature",
  "properties": {
    "addr:full":"141 W 36 St New York NY 10018",
    "addr:housenumber":"141",
    "addr:postcode":"10018",
    "addr:street":"W 36 St",
    "iso:country":"US",
    "sg:address":"141 W 36 St",
    "sg:city":"New York",
    "sg:classifiers":[
        {
            "category":"Wholesale",
            "subcategory":"Apparel",
            "type":"Manufacturing & Wholesale Goods"
        }
    ],
    "sg:phone":"+1 212 354 7300",
    "sg:postcode":"10018",
    "sg:province":"NY",
    "sg:tags":[
        "textile",
        "broker"
    ],
    "wof:name":"Gonzalez Associates Inc",
    "wof:placetype":"venue"
},
  "geometry": {"coordinates":[-73.989231,40.752109],"type":"Point"}
}