{
  "type": "Feature",
  "properties": {
    "addr:full":"75 Montague St Brooklyn NY 11201",
    "addr:housenumber":"75",
    "addr:postcode":"11201",
    "addr:street":"Montague St",
    "iso:country":"US",
    "sg:address":"75 Montague St",
    "sg:city":"Brooklyn",
    "sg:classifiers":[
        {
            "category":"Recreation",
            "type":"Entertainment"
        }
    ],
    "sg:phone":"+1 718 624 0810",
    "sg:postcode":"11201",
    "sg:province":"NY",
    "sg:tags":[
        "athletic",
        "club",
        "membership",
        "casino",
        "private"
    ],
    "wof:name":"Heights Casino",
    "wof:placetype":"venue"
},
  "geometry": {"coordinates":[-73.99630000000001,40.695499],"type":"Point"}
}