{
  "type": "Feature",
  "properties": {
    "iso:country":"US",
    "sg:address":"925 Walt Whitman Rd",
    "sg:city":"Melville",
    "sg:classifiers":[
        {
            "category":"Shopping",
            "subcategory":"Clothing, Apparel, & Fashions",
            "type":"Retail Goods"
        }
    ],
    "sg:phone":"+1 631 423 3091",
    "sg:postcode":"11747",
    "sg:province":"NY",
    "wof:name":"Mandee Shops",
    "wof:placetype":"venue"
},
  "geometry": {"coordinates":[-73.413325,40.796778],"type":"Point"}
}