{
  "type": "Feature",
  "properties": {
    "addr:full":"42 N Moore St New York NY 10013",
    "addr:housenumber":"42",
    "addr:postcode":"10013",
    "addr:street":"N Moore St",
    "iso:country":"US",
    "sg:address":"42 N Moore St",
    "sg:city":"New York",
    "sg:classifiers":[
        {
            "category":"Real Estate",
            "subcategory":"Architect",
            "type":"Services"
        }
    ],
    "sg:phone":"+1 212 219 9931",
    "sg:postcode":"10013",
    "sg:province":"NY",
    "sg:tags":[
        "architectural"
    ],
    "wof:name":"Kirschnfeld Jhathan Architects",
    "wof:placetype":"venue"
},
  "geometry": {"coordinates":[-74.00733700000001,40.719715],"type":"Point"}
}