{
  "type": "Feature",
  "properties": {
    "addr:full":"10 Church St Chateaugay NY 12920",
    "addr:housenumber":"10",
    "addr:postcode":"12920",
    "addr:street":"Church St",
    "iso:country":"US",
    "sg:address":"10 Church St",
    "sg:city":"Chateaugay",
    "sg:classifiers":[
        {
            "category":"Place Of Worship",
            "subcategory":"Church",
            "type":"Public Place"
        },
        {
            "category":"Place Of Worship",
            "type":"Public Place"
        },
        {
            "category":"Organizations",
            "subcategory":"Religious Organization",
            "type":"Services"
        }
    ],
    "sg:phone":"+1 518 497 6117",
    "sg:postcode":"12920",
    "sg:province":"NY",
    "sg:tags":[
        "churches-methodist"
    ],
    "wof:name":"United Methodist Church",
    "wof:placetype":"venue"
},
  "geometry": {"coordinates":[-74.07755299999999,44.924938],"type":"Point"}
}