{
  "type": "Feature",
  "properties": {
    "iso:country":"US",
    "sg:address":"360 Violet Ave",
    "sg:city":"Poughkeepsie",
    "sg:classifiers":[
        {
            "category":"Health Services",
            "subcategory":"Doctor",
            "type":"Services"
        }
    ],
    "sg:phone":"+1 845 876 7958",
    "sg:postcode":"12601",
    "sg:province":"NY",
    "sg:tags":[
        "physician",
        "surgeon",
        "medical"
    ],
    "wof:name":"Aguila Demetrio Jr MD",
    "wof:placetype":"venue"
},
  "geometry": {"coordinates":[-73.90907799999999,41.735703],"type":"Point"}
}