{
  "type": "Feature",
  "properties": {
    "iso:country":"US",
    "sg:address":"1640 New Hwy",
    "sg:city":"Farmingdale",
    "sg:classifiers":[
        {
            "category":"Food & Beverages",
            "subcategory":"Specialty",
            "type":"Retail Goods"
        }
    ],
    "sg:phone":"+1 631 845 7703",
    "sg:postcode":"11735",
    "sg:province":"NY",
    "sg:tags":[
        "vitamin"
    ],
    "wof:name":"Eniran Mfg",
    "wof:placetype":"venue"
},
  "geometry": {"coordinates":[-73.413172,40.739466],"type":"Point"}
}