{
  "type": "Feature",
  "properties": {
    "iso:country":"US",
    "sg:address":"1838 Adee Ave",
    "sg:city":"Bronx",
    "sg:classifiers":[
        {
            "category":"Retail",
            "subcategory":"Repair Shop",
            "type":"Services"
        }
    ],
    "sg:phone":"+1 718 379 1317",
    "sg:postcode":"10469",
    "sg:province":"NY",
    "sg:tags":[
        "plumbing",
        "drain",
        "cleaning",
        "sewer"
    ],
    "wof:name":"Pyramid Fire Protection",
    "wof:placetype":"venue"
},
  "geometry": {"coordinates":[-73.83761699999999,40.870935],"type":"Point"}
}