{
  "type": "Feature",
  "properties": {
    "iso:country":"US",
    "sg:address":"57 Main St",
    "sg:city":"Carmel",
    "sg:classifiers":[
        {
            "category":"Travel",
            "subcategory":"Hotels & Motels",
            "type":"Entertainment"
        }
    ],
    "sg:phone":"+1 845 225 9874",
    "sg:postcode":"10533",
    "sg:province":"NY",
    "wof:name":"Smalley Inn",
    "wof:placetype":"venue"
},
  "geometry": {"coordinates":[-73.869446,41.039471],"type":"Point"}
}