{
  "type": "Feature",
  "properties": {
    "iso:country":"US",
    "sg:address":"501 Acorn St",
    "sg:city":"Deer Park",
    "sg:classifiers":[
        {
            "category":"Manufacturing",
            "subcategory":"Retail Goods",
            "type":"Manufacturing & Wholesale Goods"
        }
    ],
    "sg:phone":"+1 631 667 0083",
    "sg:postcode":"11729",
    "sg:province":"NY",
    "sg:tags":[
        "manufacturer"
    ],
    "wof:name":"Premier Care Industries Inc",
    "wof:placetype":"venue"
},
  "geometry": {"coordinates":[-73.346949,40.757483],"type":"Point"}
}