{
  "type": "Feature",
  "properties": {
    "addr:full":"24110 N Conduit Ave Rosedale NY 11422",
    "addr:housenumber":"24110",
    "addr:postcode":"11422",
    "addr:street":"N Conduit Ave",
    "iso:country":"US",
    "sg:address":"24110 N Conduit Ave",
    "sg:city":"Rosedale",
    "sg:classifiers":[
        {
            "category":"Personal",
            "subcategory":"Beauty Salon",
            "type":"Services"
        }
    ],
    "sg:phone":"+1 718 525 6183",
    "sg:postcode":"11422",
    "sg:province":"NY",
    "sg:tags":[
        "hair",
        "stylist"
    ],
    "wof:name":"A Cut Of Class Beauty Parlor",
    "wof:placetype":"venue"
},
  "geometry": {"coordinates":[-73.736469,40.666569],"type":"Point"}
}