{
  "type": "Feature",
  "properties": {
    "addr:full":"2306 McDonald Ave Brooklyn NY 11223",
    "addr:housenumber":"2306",
    "addr:postcode":"11223",
    "addr:street":"Mcdonald Ave",
    "iso:country":"US",
    "sg:address":"2306 McDonald Ave",
    "sg:city":"Brooklyn",
    "sg:classifiers":[
        {
            "category":"Retail",
            "subcategory":"Repair Shop",
            "type":"Services"
        }
    ],
    "sg:phone":"+1 718 851 0159",
    "sg:postcode":"11223",
    "sg:province":"NY",
    "sg:tags":[
        "sell",
        "food",
        "equipment"
    ],
    "wof:name":"Double I Restaurant Service",
    "wof:placetype":"venue"
},
  "geometry": {"coordinates":[-73.97349800000001,40.59577],"type":"Point"}
}