{
  "type": "Feature",
  "properties": {
    "addr:full":"2114 E 66th St Brooklyn NY 11234",
    "addr:housenumber":"2114",
    "addr:postcode":"11234",
    "addr:street":"E 66Th St",
    "iso:country":"US",
    "sg:address":"2114 E 66th St",
    "sg:city":"Brooklyn",
    "sg:classifiers":[
        {
            "category":"Home & Garden",
            "subcategory":"Home Furnishings",
            "type":"Retail Goods"
        }
    ],
    "sg:phone":"+1 718 763 9249",
    "sg:postcode":"11234",
    "sg:province":"NY",
    "sg:tags":[
        "cover",
        "slip"
    ],
    "wof:name":"David's Custom Slip Covers",
    "wof:placetype":"venue"
},
  "geometry": {"coordinates":[-73.909398,40.615899],"type":"Point"}
}