{
  "type": "Feature",
  "properties": {
    "iso:country":"US",
    "sg:address":"294 New York Ave",
    "sg:city":"Huntington",
    "sg:classifiers":[
        {
            "category":"Insurance",
            "subcategory":"Insurance Agent",
            "type":"Services"
        }
    ],
    "sg:phone":"+1 631 271 1615",
    "sg:postcode":"11743",
    "sg:province":"NY",
    "sg:tags":[
        "union",
        "credit",
        "bank"
    ],
    "sg:website":"statefarm.com",
    "wof:name":"Callahan John Agency Inc",
    "wof:placetype":"venue"
},
  "geometry": {"coordinates":[-73.425201,40.873501],"type":"Point"}
}