{
  "type": "Feature",
  "properties": {
    "iso:country":"US",
    "sg:address":"2321 Sheridan Ave",
    "sg:city":"Schenectady",
    "sg:classifiers":[
        {
            "category":"Wholesale",
            "subcategory":"Medical Equipment & Supplies",
            "type":"Manufacturing & Wholesale Goods"
        }
    ],
    "sg:phone":"+1 518 381 4311",
    "sg:postcode":"12309",
    "sg:province":"NY",
    "sg:tags":[
        "marketing",
        "product"
    ],
    "wof:name":"Bedrail Solutions LLC",
    "wof:placetype":"venue"
},
  "geometry": {"coordinates":[-73.90178299999999,42.829382],"type":"Point"}
}