{
  "type": "Feature",
  "properties": {
    "addr:full":"6 Depot Sq Tuckahoe NY 10707",
    "addr:housenumber":"6",
    "addr:postcode":"10707",
    "addr:street":"Depot Sq",
    "iso:country":"US",
    "sg:address":"6 Depot Sq",
    "sg:city":"Tuckahoe",
    "sg:classifiers":[
        {
            "category":"Personal",
            "subcategory":"Beauty Salon",
            "type":"Services"
        },
        {
            "category":"Personal",
            "subcategory":"Barber",
            "type":"Services"
        }
    ],
    "sg:phone":"+1 914 337 9725",
    "sg:postcode":"10707",
    "sg:province":"NY",
    "sg:tags":[
        "shop"
    ],
    "wof:name":"Mario's Barber Shop",
    "wof:placetype":"venue"
},
  "geometry": {"coordinates":[-73.82789200000001,40.950167],"type":"Point"}
}