{
  "type": "Feature",
  "properties": {
    "iso:country":"US",
    "sg:address":"3125 State Hwy 26",
    "sg:city":"Oriskany Falls",
    "sg:classifiers":[
        {
            "category":"Farming",
            "subcategory":"Dairy Farm",
            "type":"Manufacturing & Wholesale Goods"
        }
    ],
    "sg:phone":"+1 315 843 7095",
    "sg:postcode":"13425",
    "sg:province":"NY",
    "wof:name":"Warner Leuenberger",
    "wof:placetype":"venue"
},
  "geometry": {"coordinates":[-75.500981,43.019585],"type":"Point"}
}