{
  "type": "Feature",
  "properties": {
    "addr:full":"888 7th Ave New York NY 10106",
    "addr:housenumber":"888",
    "addr:postcode":"10106",
    "addr:street":"7Th Ave",
    "iso:country":"US",
    "sg:address":"888 7th Ave",
    "sg:city":"New York",
    "sg:classifiers":[
        {
            "category":"Real Estate",
            "subcategory":"Real Estate Services",
            "type":"Services"
        }
    ],
    "sg:phone":"+1 212 765 0950",
    "sg:postcode":"10106",
    "sg:province":"NY",
    "sg:tags":[
        "management",
        "property"
    ],
    "wof:name":"Vornado Office Management Llc",
    "wof:placetype":"venue"
},
  "geometry": {"coordinates":[-73.9804,40.764702],"type":"Point"}
}