{
  "type": "Feature",
  "properties": {
    "iso:country":"US",
    "sg:address":"119 Marcourt Dr",
    "sg:city":"Chappaqua",
    "sg:classifiers":[
        {
            "category":"Farming",
            "subcategory":"Nursery",
            "type":"Manufacturing & Wholesale Goods"
        }
    ],
    "sg:phone":"+1 914 238 3957",
    "sg:postcode":"10514",
    "sg:province":"NY",
    "wof:name":"Chappqua Ctr For Nurs Yars Inc",
    "wof:placetype":"venue"
},
  "geometry": {"coordinates":[-73.781959,41.171709],"type":"Point"}
}