{
  "type": "Feature",
  "properties": {
    "addr:full":"977 48th St Brooklyn NY 11219",
    "addr:housenumber":"977",
    "addr:postcode":"11219",
    "addr:street":"48Th St",
    "iso:country":"US",
    "sg:address":"977 48th St",
    "sg:city":"Brooklyn",
    "sg:classifiers":[
        {
            "category":"Health Services",
            "subcategory":"Doctor",
            "type":"Services"
        }
    ],
    "sg:phone":"+1 718 283 8260",
    "sg:postcode":"11219",
    "sg:province":"NY",
    "sg:tags":[
        "physician",
        "surgeon"
    ],
    "wof:name":"Simon G Kupchik MD",
    "wof:placetype":"venue"
},
  "geometry": {"coordinates":[-73.999387,40.640665],"type":"Point"}
}