{
  "type": "Feature",
  "properties": {
    "iso:country":"US",
    "sg:address":"977 48th St",
    "sg:city":"Brooklyn",
    "sg:classifiers":[
        {
            "category":"Health Services",
            "subcategory":"Doctor",
            "type":"Services"
        }
    ],
    "sg:phone":"+1 718 283 8260",
    "sg:postcode":"11219",
    "sg:province":"NY",
    "sg:tags":[
        "physician",
        "surgeon"
    ],
    "wof:name":"Simon G Kupchik MD",
    "wof:placetype":"venue"
},
  "geometry": {"coordinates":[-73.999387,40.640665],"type":"Point"}
}