{
  "type": "Feature",
  "properties": {
    "addr:full":"1959 Westchester Avenue Bronx NY 10462",
    "addr:housenumber":"1959",
    "addr:postcode":"10462",
    "addr:street":"Westchester Avenue",
    "iso:country":"US",
    "sg:address":"1959 Westchester Avenue",
    "sg:city":"Bronx",
    "sg:classifiers":[
        {
            "category":"Shopping",
            "subcategory":"Pharmacy",
            "type":"Retail Goods"
        }
    ],
    "sg:phone":"+1 718 824 3745",
    "sg:postcode":"10462",
    "sg:province":"NY",
    "sg:tags":[
        "drugstore"
    ],
    "wof:name":"Drug Mart Corporation",
    "wof:placetype":"venue"
},
  "geometry": {"coordinates":[-73.858816,40.833491],"type":"Point"}
}