{
  "type": "Feature",
  "properties": {
    "iso:country":"US",
    "sg:address":"1 Vernon Pl",
    "sg:city":"Mt Vernon",
    "sg:classifiers":[
        {
            "category":"Personal",
            "subcategory":"Beauty Salon",
            "type":"Services"
        }
    ],
    "sg:phone":"+1 914 667 6500",
    "sg:postcode":"10552",
    "sg:province":"NY",
    "sg:tags":[
        "manicuring"
    ],
    "wof:name":"Cosy Nail & Tanning",
    "wof:placetype":"venue"
},
  "geometry": {"coordinates":[-73.828982,40.922761],"type":"Point"}
}