{
  "type": "Feature",
  "properties": {
    "iso:country":"US",
    "sg:address":"14 Queens Dr",
    "sg:city":"Cheektowaga",
    "sg:classifiers":[
        {
            "category":"Personal",
            "type":"Services"
        }
    ],
    "sg:phone":"+1 716 633 2230",
    "sg:postcode":"14225",
    "sg:province":"NY",
    "sg:tags":[
        "therapist",
        "massage"
    ],
    "wof:name":"Airport Massage Therapy",
    "wof:placetype":"venue"
},
  "geometry": {"coordinates":[-78.75845700000001,42.942234],"type":"Point"}
}