{
  "type": "Feature",
  "properties": {
    "iso:country":"US",
    "sg:address":"2052 Cross Bronx Expy",
    "sg:city":"Bronx",
    "sg:classifiers":[
        {
            "category":"Recreation",
            "type":"Entertainment"
        }
    ],
    "sg:phone":"+1 718 708 7632",
    "sg:postcode":"10472",
    "sg:province":"NY",
    "sg:tags":[
        "hall",
        "auditorium"
    ],
    "wof:name":"Kayara Hall",
    "wof:placetype":"venue"
},
  "geometry": {"coordinates":[-73.854466,40.83129],"type":"Point"}
}