{
  "type": "Feature",
  "properties": {
    "iso:country":"US",
    "sg:address":"566 Co Rte 41",
    "sg:city":"Hudson Falls",
    "sg:classifiers":[
        {
            "category":"Farming",
            "subcategory":"Dairy Farm",
            "type":"Manufacturing & Wholesale Goods"
        }
    ],
    "sg:phone":"+1 518 747 8572",
    "sg:postcode":"12839",
    "sg:province":"NY",
    "wof:name":"Daniel Lindsay",
    "wof:placetype":"venue"
},
  "geometry": {"coordinates":[-73.498088,43.358535],"type":"Point"}
}