{
  "type": "Feature",
  "properties": {
    "iso:country":"US",
    "sg:address":"21 Whitewood Dr",
    "sg:city":"Rocky Point",
    "sg:classifiers":[
        {
            "category":"Manufacturing",
            "subcategory":"Tools & Machinery",
            "type":"Manufacturing & Wholesale Goods"
        }
    ],
    "sg:phone":"+1   ",
    "sg:postcode":"11778",
    "sg:province":"NY",
    "sg:tags":[
        "surgical",
        "industrial",
        "mfg"
    ],
    "wof:name":"Double Cut Manufacturing Inc",
    "wof:placetype":"venue"
},
  "geometry": {"coordinates":[-72.94998,40.954446],"type":"Point"}
}