{
  "type": "Feature",
  "properties": {
    "iso:country":"US",
    "sg:address":"136 N Main St",
    "sg:city":"Holland",
    "sg:classifiers":[
        {
            "category":"Manufacturing",
            "subcategory":"Tools & Machinery",
            "type":"Manufacturing & Wholesale Goods"
        }
    ],
    "sg:phone":"+1   ",
    "sg:postcode":"14080",
    "sg:province":"NY",
    "sg:tags":[
        "machine",
        "rebuilding"
    ],
    "wof:name":"Uhmac Inc",
    "wof:placetype":"venue"
},
  "geometry": {"coordinates":[-78.546612,42.643689],"type":"Point"}
}