{
  "type": "Feature",
  "properties": {
    "addr:full":"3588 Stony Point Rd Grand Island NY 14072",
    "addr:housenumber":"3588",
    "addr:postcode":"14072",
    "addr:street":"Stony Point Rd",
    "iso:country":"US",
    "sg:address":"3588 Stony Point Rd",
    "sg:city":"Grand Island",
    "sg:classifiers":[
        {
            "category":"Building & Trades",
            "subcategory":"Pest Control",
            "type":"Services"
        }
    ],
    "sg:phone":"+1 716 774 8354",
    "sg:postcode":"14072",
    "sg:province":"NY",
    "wof:name":"Hygientech Of Wny",
    "wof:placetype":"venue"
},
  "geometry": {"coordinates":[-78.945267,43.055442],"type":"Point"}
}