{
  "type": "Feature",
  "properties": {
    "addr:full":"423 Atlantic Ave Brooklyn NY 11217",
    "addr:housenumber":"423",
    "addr:postcode":"11217",
    "addr:street":"Atlantic Ave",
    "iso:country":"US",
    "sg:address":"423 Atlantic Ave",
    "sg:city":"Brooklyn",
    "sg:classifiers":[
        {
            "category":"Professional",
            "type":"Services"
        }
    ],
    "sg:phone":"+1 917 532 8111",
    "sg:postcode":"11217",
    "sg:province":"NY",
    "sg:tags":[
        "planning",
        "event"
    ],
    "sg:website":"ruthlapinevents.com",
    "wof:name":"Ruth Lapin Events",
    "wof:placetype":"venue"
},
  "geometry": {"coordinates":[-73.98390499999999,40.68657],"type":"Point"}
}