{
  "type": "Feature",
  "properties": {
    "iso:country":"US",
    "sg:address":"28 Blauvelt Rd",
    "sg:city":"Monsey",
    "sg:classifiers":[
        {
            "category":"Organizations",
            "subcategory":"Religious Organization",
            "type":"Services"
        }
    ],
    "sg:phone":"+1 845 352 6839",
    "sg:postcode":"10952",
    "sg:province":"NY",
    "sg:tags":[
        "clergy"
    ],
    "wof:name":"Moshe Gobioff",
    "wof:placetype":"venue"
},
  "geometry": {"coordinates":[-74.06951100000001,41.119026],"type":"Point"}
}