{
  "type": "Feature",
  "properties": {
    "addr:full":"1030 W Jericho Tpke Smithtown NY 11787",
    "addr:housenumber":"1030",
    "addr:postcode":"11787",
    "addr:street":"W Jericho Tpke",
    "iso:country":"US",
    "sg:address":"1030 W Jericho Tpke",
    "sg:city":"Smithtown",
    "sg:classifiers":[
        {
            "category":"Professional",
            "subcategory":"Advertising",
            "type":"Services"
        },
        {
            "category":"Manufacturing",
            "subcategory":"Printing",
            "type":"Manufacturing & Wholesale Goods"
        }
    ],
    "sg:phone":"+1 631 543 7445",
    "sg:postcode":"11787",
    "sg:province":"NY",
    "sg:tags":[
        "counselor",
        "publishing"
    ],
    "wof:name":"Entertainment This Week",
    "wof:placetype":"venue"
},
  "geometry": {"coordinates":[-73.252003,40.84757],"type":"Point"}
}