{
  "type": "Feature",
  "properties": {
    "addr:full":"53 Walnut Ave E Farmingdale NY 11735",
    "addr:housenumber":"53",
    "addr:postcode":"11735",
    "addr:street":"Walnut Ave E",
    "iso:country":"US",
    "sg:address":"53 Walnut Ave E",
    "sg:city":"Farmingdale",
    "sg:classifiers":[
        {
            "category":"Building & Trades",
            "subcategory":"Plumbing",
            "type":"Services"
        }
    ],
    "sg:phone":"+1 631 249 8104",
    "sg:postcode":"11735",
    "sg:province":"NY",
    "sg:tags":[
        "contractor"
    ],
    "wof:name":"Joes Plumbing & Heating",
    "wof:placetype":"venue"
},
  "geometry": {"coordinates":[-73.431816,40.732666],"type":"Point"}
}