{
  "type": "Feature",
  "properties": {
    "addr:full":"2052 Belmont Ave Elmont NY 11003",
    "addr:housenumber":"2052",
    "addr:postcode":"11003",
    "addr:street":"Belmont Ave",
    "iso:country":"US",
    "sg:address":"2052 Belmont Ave",
    "sg:city":"Elmont",
    "sg:classifiers":[
        {
            "category":"Organizations",
            "subcategory":"Religious Organization",
            "type":"Services"
        }
    ],
    "sg:phone":"+1 516 354 7873",
    "sg:postcode":"11003",
    "sg:province":"NY",
    "wof:name":"McKenzie John S",
    "wof:placetype":"venue"
},
  "geometry": {"coordinates":[-73.715655,40.699943],"type":"Point"}
}