{
  "type": "Feature",
  "properties": {
    "addr:full":"1290 Fron Street Binghamton NY 13905",
    "addr:housenumber":"1290",
    "addr:postcode":"13905",
    "addr:street":"Fron Street",
    "iso:country":"US",
    "sg:address":"1290 Fron Street",
    "sg:city":"Binghamton",
    "sg:classifiers":[
        {
            "category":"Restaurant",
            "type":"Food & Drink"
        }
    ],
    "sg:postcode":"13905",
    "sg:province":"NY",
    "sg:website":"www.weismarkets.com/index.php",
    "wof:name":"Weis Markets",
    "wof:placetype":"venue"
},
  "geometry": {"coordinates":[-75.895076,42.159857],"type":"Point"}
}