{
  "type": "Feature",
  "properties": {
    "addr:full":"14330 22nd Rd Whitestone NY 11357",
    "addr:housenumber":"14330",
    "addr:postcode":"11357",
    "addr:street":"22Nd Rd",
    "iso:country":"US",
    "sg:address":"14330 22nd Rd",
    "sg:city":"Whitestone",
    "sg:classifiers":[
        {
            "category":"Professional",
            "subcategory":"Computer Services",
            "type":"Services"
        }
    ],
    "sg:phone":"+1 718 888 1691",
    "sg:postcode":"11357",
    "sg:province":"NY",
    "sg:tags":[
        "consultant",
        "designer",
        "system"
    ],
    "sg:website":"http://www.objectvision.net",
    "wof:name":"Objectvision",
    "wof:placetype":"venue"
},
  "geometry": {"coordinates":[-73.82592,40.779055],"type":"Point"}
}