{
  "type": "Feature",
  "properties": {
    "addr:full":"1777 Western Ave Albany NY 12203",
    "addr:housenumber":"1777",
    "addr:postcode":"12203",
    "addr:street":"Western Ave",
    "iso:country":"US",
    "sg:address":"1777 Western Ave",
    "sg:city":"Albany",
    "sg:classifiers":[
        {
            "category":"Real Estate",
            "subcategory":"Real Estate Services",
            "type":"Services"
        }
    ],
    "sg:phone":"+1 518 690 0267",
    "sg:postcode":"12203",
    "sg:province":"NY",
    "sg:tags":[
        "abstract",
        "title"
    ],
    "wof:name":"A1 Title",
    "wof:placetype":"venue"
},
  "geometry": {"coordinates":[-73.865835,42.690003],"type":"Point"}
}