{
  "type": "Feature",
  "properties": {
    "addr:full":"4135 37th Street Long Island City NY 11101",
    "addr:housenumber":"4135",
    "addr:postcode":"11101",
    "addr:street":"37Th Street",
    "iso:country":"US",
    "sg:address":"4135 37th Street",
    "sg:city":"Long Island City",
    "sg:classifiers":[
        {
            "category":"Restaurant",
            "type":"Food & Drink"
        }
    ],
    "sg:phone":"+1 718 784 0502",
    "sg:postcode":"11101",
    "sg:province":"NY",
    "wof:name":"Queen's Restaurant Supplies",
    "wof:placetype":"venue"
},
  "geometry": {"coordinates":[-73.92734400000001,40.746569],"type":"Point"}
}