{
  "type": "Feature",
  "properties": {
    "addr:full":"2 Calvert Dr Syosset NY 11791",
    "addr:housenumber":"2",
    "addr:postcode":"11791",
    "addr:street":"Calvert Dr",
    "iso:country":"US",
    "sg:address":"2 Calvert Dr",
    "sg:city":"Syosset",
    "sg:classifiers":[
        {
            "category":"Health Services",
            "subcategory":"Health Practitioner",
            "type":"Services"
        }
    ],
    "sg:phone":"+1   ",
    "sg:postcode":"11791",
    "sg:province":"NY",
    "wof:name":"Rosalie Menduni",
    "wof:placetype":"venue"
},
  "geometry": {"coordinates":[-73.486125,40.833189],"type":"Point"}
}