{
  "type": "Feature",
  "properties": {
    "iso:country":"US",
    "sg:address":"206 Broadway",
    "sg:city":"Brooklyn",
    "sg:classifiers":[
        {
            "category":"Building & Trades",
            "subcategory":"Electrical",
            "type":"Services"
        }
    ],
    "sg:phone":"+1 718 486 6798",
    "sg:postcode":"11211",
    "sg:province":"NY",
    "sg:tags":[
        "electrical",
        "contractor"
    ],
    "wof:name":"Can Do Electric",
    "wof:placetype":"venue"
},
  "geometry": {"coordinates":[-73.960869,40.709418],"type":"Point"}
}