{
  "type": "Feature",
  "properties": {
    "addr:full":"28 Johnes St Newburgh NY 12550",
    "addr:housenumber":"28",
    "addr:postcode":"12550",
    "addr:street":"Johnes St",
    "iso:country":"US",
    "sg:address":"28 Johnes St",
    "sg:city":"Newburgh",
    "sg:classifiers":[
        {
            "category":"Wholesale",
            "subcategory":"Hardware",
            "type":"Manufacturing & Wholesale Goods"
        },
        {
            "category":"Home & Garden",
            "subcategory":"Building Materials",
            "type":"Retail Goods"
        }
    ],
    "sg:phone":"+1 845 565 5220",
    "sg:postcode":"12550",
    "sg:province":"NY",
    "sg:tags":[
        "plumbing",
        "fixture",
        "heating",
        "supply"
    ],
    "sg:website":"www.rimsupply.com",
    "wof:name":"R I M Plumbing & Heating Sup",
    "wof:placetype":"venue"
},
  "geometry": {"coordinates":[-74.010205,41.494747],"type":"Point"}
}