{
  "type": "Feature",
  "properties": {
    "addr:full":"41 Flatbush Ave Brooklyn NY 11217",
    "addr:housenumber":"41",
    "addr:postcode":"11217",
    "addr:street":"Flatbush Ave",
    "iso:country":"US",
    "sg:address":"41 Flatbush Ave",
    "sg:city":"Brooklyn",
    "sg:classifiers":[
        {
            "category":"Shopping",
            "subcategory":"Jewelry",
            "type":"Retail Goods"
        }
    ],
    "sg:phone":"+1 718 624 7292",
    "sg:postcode":"11217",
    "sg:province":"NY",
    "wof:name":"Flatbush Jewelry Exchange",
    "wof:placetype":"venue"
},
  "geometry": {"coordinates":[-73.979797,40.687599],"type":"Point"}
}