{
  "type": "Feature",
  "properties": {
    "addr:full":"198 Columbia Hts Brooklyn NY 11201",
    "addr:housenumber":"198",
    "addr:postcode":"11201",
    "addr:street":"Columbia Hts",
    "iso:country":"US",
    "sg:address":"198 Columbia Hts",
    "sg:city":"Brooklyn",
    "sg:classifiers":[
        {
            "category":"Shopping",
            "subcategory":"Pharmacy",
            "type":"Retail Goods"
        }
    ],
    "sg:phone":"+1 718 858 1234",
    "sg:postcode":"11201",
    "sg:province":"NY",
    "sg:tags":[
        "drugstore"
    ],
    "wof:name":"Future Group Limo And Car Service Inc",
    "wof:placetype":"venue"
},
  "geometry": {"coordinates":[-73.997069,40.697146],"type":"Point"}
}