{
  "type": "Feature",
  "properties": {
    "addr:full":"801 6 Ave New York NY 10001",
    "addr:housenumber":"801",
    "addr:postcode":"10001",
    "addr:street":"6 Ave",
    "iso:country":"US",
    "sg:address":"801 6 Ave",
    "sg:city":"New York",
    "sg:classifiers":[
        {
            "category":"Food & Beverages",
            "subcategory":"Groceries & Convenience Stores",
            "type":"Retail Goods"
        }
    ],
    "sg:phone":"+1   ",
    "sg:postcode":"10001",
    "sg:province":"NY",
    "wof:name":"Garden Grocery & Deli",
    "wof:placetype":"venue"
},
  "geometry": {"coordinates":[-73.990968,40.745421],"type":"Point"}
}