{
  "type": "Feature",
  "properties": {
    "iso:country":"US",
    "sg:address":"128 State Rte 245",
    "sg:city":"Rushville",
    "sg:classifiers":[
        {
            "category":"Government",
            "subcategory":"Office",
            "type":"Public Place"
        }
    ],
    "sg:phone":"+1   ",
    "sg:postcode":"14544",
    "sg:province":"NY",
    "sg:tags":[
        "sector",
        "department",
        "regulation",
        "commercial",
        "store"
    ],
    "wof:name":"Kc Collectables",
    "wof:placetype":"venue"
},
  "geometry": {"coordinates":[-77.238944,42.756921],"type":"Point"}
}