{
  "type": "Feature",
  "properties": {
    "addr:full":"60 Porter Lynch Rd Norwood NY 13668",
    "addr:housenumber":"60",
    "addr:postcode":"13668",
    "addr:street":"Porter Lynch Rd",
    "iso:country":"US",
    "sg:address":"60 Porter Lynch Rd",
    "sg:city":"Norwood",
    "sg:classifiers":[
        {
            "category":"Manufacturing",
            "subcategory":"Food",
            "type":"Manufacturing & Wholesale Goods"
        }
    ],
    "sg:phone":"+1   ",
    "sg:postcode":"13668",
    "sg:province":"NY",
    "sg:tags":[
        "preparation",
        "mfg"
    ],
    "wof:name":"M K S Enterprises Inc",
    "wof:placetype":"venue"
},
  "geometry": {"coordinates":[-74.91801100000001,44.786587],"type":"Point"}
}