{
  "type": "Feature",
  "properties": {
    "addr:full":"4874 Mount Read Blvd Rochester NY 14616",
    "addr:housenumber":"4874",
    "addr:postcode":"14616",
    "addr:street":"Mount Read",
    "iso:country":"US",
    "sg:address":"4874 Mount Read Blvd",
    "sg:city":"Rochester",
    "sg:classifiers":[
        {
            "category":"Insurance",
            "subcategory":"Insurance Agent",
            "type":"Services"
        }
    ],
    "sg:phone":"+1 585 663 1571",
    "sg:postcode":"14616",
    "sg:province":"NY",
    "wof:name":"Jane G Camiolo Insurance",
    "wof:placetype":"venue"
},
  "geometry": {"coordinates":[-77.659121,43.25003],"type":"Point"}
}