{
  "type": "Feature",
  "properties": {
    "addr:full":"40 Hardscrabble Rd North Salem NY 10560",
    "addr:housenumber":"40",
    "addr:postcode":"10560",
    "addr:street":"Hardscrabble Rd",
    "iso:country":"US",
    "sg:address":"40 Hardscrabble Rd",
    "sg:city":"North Salem",
    "sg:classifiers":[
        {
            "category":"Wholesale",
            "subcategory":"Plants",
            "type":"Manufacturing & Wholesale Goods"
        }
    ],
    "sg:phone":"+1 914 669 5633",
    "sg:postcode":"10560",
    "sg:province":"NY",
    "sg:tags":[
        "nursery",
        "stock"
    ],
    "wof:name":"Hardscrabble Farms",
    "wof:placetype":"venue"
},
  "geometry": {"coordinates":[-73.629963,41.350107],"type":"Point"}
}