{
  "type": "Feature",
  "properties": {
    "iso:country":"US",
    "sg:address":"291 Main St",
    "sg:city":"Farmingville",
    "sg:classifiers":[
        {
            "category":"Utilities",
            "subcategory":"Mobile Phone",
            "type":"Services"
        }
    ],
    "sg:phone":"+1 516 293 0303",
    "sg:postcode":"11782",
    "sg:province":"NY",
    "sg:tags":[
        "telephone",
        "cellular"
    ],
    "wof:name":"Jet Communications",
    "wof:placetype":"venue"
},
  "geometry": {"coordinates":[-73.08981799999999,40.7322],"type":"Point"}
}