{
  "type": "Feature",
  "properties": {
    "addr:full":"447 Elizabeth St Oneida NY 13421",
    "addr:housenumber":"447",
    "addr:postcode":"13421",
    "addr:street":"Elizabeth St",
    "iso:country":"US",
    "sg:address":"447 Elizabeth St",
    "sg:city":"Oneida",
    "sg:classifiers":[
        {
            "category":"Social Services",
            "subcategory":"Child Care",
            "type":"Services"
        }
    ],
    "sg:phone":"+1   ",
    "sg:postcode":"13421",
    "sg:province":"NY",
    "sg:tags":[
        "day"
    ],
    "wof:name":"New Concept Day Care",
    "wof:placetype":"venue"
},
  "geometry": {"coordinates":[-75.6451,43.087499],"type":"Point"}
}