{
  "type": "Feature",
  "properties": {
    "iso:country":"US",
    "sg:address":"2094 Seneca St",
    "sg:city":"Buffalo",
    "sg:classifiers":[
        {
            "category":"Professional",
            "subcategory":"Computer Services",
            "type":"Services"
        }
    ],
    "sg:phone":"+1 716 827 0656",
    "sg:postcode":"14210",
    "sg:province":"NY",
    "sg:tags":[
        "internet"
    ],
    "wof:name":"2094 Seneca St",
    "wof:placetype":"venue"
},
  "geometry": {"coordinates":[-78.809074,42.854917],"type":"Point"}
}