{
  "type": "Feature",
  "properties": {
    "iso:country":"US",
    "sg:address":"7419 15th Ave",
    "sg:city":"Brooklyn",
    "sg:classifiers":[
        {
            "category":"Building & Trades",
            "subcategory":"Construction",
            "type":"Services"
        }
    ],
    "sg:phone":"+1 718 645 6934",
    "sg:postcode":"11228",
    "sg:province":"NY",
    "sg:tags":[
        "resurfacing",
        "refinishing",
        "flooring",
        "floor"
    ],
    "wof:name":"Buono's Flooring Co Inc",
    "wof:placetype":"venue"
},
  "geometry": {"coordinates":[-74.00279999999999,40.617699],"type":"Point"}
}