{
  "type": "Feature",
  "properties": {
    "iso:country":"US",
    "sg:address":"167 N 9th St",
    "sg:city":"Brooklyn",
    "sg:classifiers":[
        {
            "category":"Home & Garden",
            "subcategory":"Home Furnishings",
            "type":"Retail Goods"
        }
    ],
    "sg:phone":"+1 718 384 7886",
    "sg:postcode":"11222",
    "sg:province":"NY",
    "sg:tags":[
        "decor"
    ],
    "sg:website":"www.scandinaviangrace.com",
    "wof:name":"Scandinavian Grace",
    "wof:placetype":"venue"
},
  "geometry": {"coordinates":[-73.95624100000001,40.718764],"type":"Point"}
}