{
  "type": "Feature",
  "properties": {
    "addr:full":"43 Potter Ave New Rochelle NY 10801",
    "addr:housenumber":"43",
    "addr:postcode":"10801",
    "addr:street":"Potter Ave",
    "iso:country":"US",
    "sg:address":"43 Potter Ave",
    "sg:city":"New Rochelle",
    "sg:classifiers":[
        {
            "category":"Retail",
            "subcategory":"Auto Repair",
            "type":"Services"
        }
    ],
    "sg:phone":"+1   ",
    "sg:postcode":"10801",
    "sg:province":"NY",
    "sg:tags":[
        "body",
        "shop"
    ],
    "wof:name":"New Rochelle Auto Body Inc",
    "wof:placetype":"venue"
},
  "geometry": {"coordinates":[-73.77284400000001,40.926427],"type":"Point"}
}