{
  "type": "Feature",
  "properties": {
    "addr:full":"63 S Main St Freeport NY 11520",
    "addr:housenumber":"63",
    "addr:postcode":"11520",
    "addr:street":"S Main St",
    "iso:country":"US",
    "sg:address":"63 S Main St",
    "sg:city":"Freeport",
    "sg:classifiers":[
        {
            "category":"Personal",
            "subcategory":"Barber",
            "type":"Services"
        }
    ],
    "sg:phone":"+1 516 378 0016",
    "sg:postcode":"11520",
    "sg:province":"NY",
    "wof:name":"Royal Kutz Barber Shop",
    "wof:placetype":"venue"
},
  "geometry": {"coordinates":[-73.580428,40.65483],"type":"Point"}
}