{
  "type": "Feature",
  "properties": {
    "iso:country":"US",
    "sg:address":"1864 Lyndon Blvd",
    "sg:city":"Falconer",
    "sg:classifiers":[
        {
            "category":"Manufacturing",
            "subcategory":"Tools & Machinery",
            "type":"Manufacturing & Wholesale Goods"
        },
        {
            "category":"Wholesale",
            "subcategory":"Machinery & Supplies",
            "type":"Manufacturing & Wholesale Goods"
        },
        {
            "category":"Manufacturing",
            "subcategory":"Building Materials",
            "type":"Manufacturing & Wholesale Goods"
        }
    ],
    "sg:phone":"+1 716 665 2801",
    "sg:postcode":"14733",
    "sg:province":"NY",
    "sg:tags":[
        "solid",
        "tools-electric",
        "industrial",
        "surface",
        "equipment"
    ],
    "sg:website":"http://www.bartontool.com",
    "wof:name":"Barton Tool Inc.",
    "wof:placetype":"venue"
},
  "geometry": {"coordinates":[-79.183313,42.113367],"type":"Point"}
}