{
  "type": "Feature",
  "properties": {
    "iso:country":"US",
    "sg:address":"1951 60th St",
    "sg:city":"Brooklyn",
    "sg:classifiers":[
        {
            "category":"Building & Trades",
            "subcategory":"Landscaping Services",
            "type":"Services"
        }
    ],
    "sg:phone":"+1 718 259 8677",
    "sg:postcode":"11204",
    "sg:province":"NY",
    "sg:tags":[
        "landscape",
        "contractor"
    ],
    "wof:name":"Nicholas Ottombrino Landscpg",
    "wof:placetype":"venue"
},
  "geometry": {"coordinates":[-73.98369,40.620119],"type":"Point"}
}