{
  "type": "Feature",
  "properties": {
    "addr:full":"250 W 127th Street New York NY 10027",
    "addr:housenumber":"250",
    "addr:postcode":"10027",
    "addr:street":"W 127Th Street",
    "iso:country":"US",
    "sg:address":"250 W 127th Street",
    "sg:city":"New York",
    "sg:classifiers":[
        {
            "category":"Education",
            "subcategory":"School",
            "type":"Public Place"
        }
    ],
    "sg:phone":"+1 212 864 2400",
    "sg:postcode":"10027",
    "sg:province":"NY",
    "sg:tags":[
        "high",
        "middle",
        "elementary"
    ],
    "wof:name":"N Y City of",
    "wof:placetype":"venue"
},
  "geometry": {"coordinates":[-73.94828,40.810792],"type":"Point"}
}