{
  "type": "Feature",
  "properties": {
    "addr:full":"138 W 72nd St Frnt New York NY 10023",
    "addr:housenumber":"138",
    "addr:postcode":"10023",
    "addr:street":"W 72Nd St",
    "iso:country":"US",
    "sg:address":"138 W 72nd St Frnt",
    "sg:city":"New York",
    "sg:classifiers":[
        {
            "category":"Professional",
            "type":"Services"
        },
        {
            "category":"Deli",
            "type":"Food & Drink"
        },
        {
            "category":"Restaurant",
            "type":"Food & Drink"
        }
    ],
    "sg:phone":"+1 212 877 2721",
    "sg:postcode":"10023",
    "sg:province":"NY",
    "sg:tags":[
        "kosher",
        "caterer"
    ],
    "sg:website":"www.fineandschapiro.com/",
    "wof:name":"Fine & Schapiro",
    "wof:placetype":"venue"
},
  "geometry": {"coordinates":[-73.980103,40.778],"type":"Point"}
}