{
  "type": "Feature",
  "properties": {
    "addr:full":"55 Wolkoff Ln Staten Island NY 10303",
    "addr:housenumber":"55",
    "addr:postcode":"10303",
    "addr:street":"Wolkoff Ln",
    "iso:country":"US",
    "sg:address":"55 Wolkoff Ln",
    "sg:city":"Staten Island",
    "sg:classifiers":[
        {
            "category":"Organizations",
            "subcategory":"Religious Organization",
            "type":"Services"
        }
    ],
    "sg:phone":"+1 718 983 1308",
    "sg:postcode":"10303",
    "sg:province":"NY",
    "sg:tags":[
        "clergy"
    ],
    "wof:name":"Adrian Tenhor",
    "wof:placetype":"venue"
},
  "geometry": {"coordinates":[-74.166121,40.622076],"type":"Point"}
}