{
  "type": "Feature",
  "properties": {
    "addr:full":"2280 8th Ave New York NY 10027",
    "addr:housenumber":"2280",
    "addr:postcode":"10027",
    "addr:street":"8Th Ave",
    "iso:country":"US",
    "sg:address":"2280 8th Ave",
    "sg:city":"New York",
    "sg:classifiers":[
        {
            "category":"Shopping",
            "type":"Retail Goods"
        }
    ],
    "sg:phone":"+1   ",
    "sg:postcode":"10027",
    "sg:province":"NY",
    "sg:tags":[
        "consulting",
        "management",
        "merchandise"
    ],
    "wof:name":"A & G Fashions",
    "wof:placetype":"venue"
},
  "geometry": {"coordinates":[-73.952209,40.808558],"type":"Point"}
}