{
  "type": "Feature",
  "properties": {
    "iso:country":"US",
    "sg:address":"212 Broadway",
    "sg:city":"Amityville",
    "sg:classifiers":[
        {
            "category":"Shopping",
            "subcategory":"Clothing, Apparel, & Fashions",
            "type":"Retail Goods"
        }
    ],
    "sg:phone":"+1   ",
    "sg:postcode":"11701",
    "sg:province":"NY",
    "wof:name":"Omphalos",
    "wof:placetype":"venue"
},
  "geometry": {"coordinates":[-73.417118,40.680265],"type":"Point"}
}