{
  "type": "Feature",
  "properties": {
    "addr:full":"1670 E 19th St Brooklyn NY 11229",
    "addr:housenumber":"1670",
    "addr:postcode":"11229",
    "addr:street":"E 19Th St",
    "iso:country":"US",
    "sg:address":"1670 E 19th St",
    "sg:city":"Brooklyn",
    "sg:classifiers":[
        {
            "category":"Retail",
            "subcategory":"Repair Shop",
            "type":"Services"
        }
    ],
    "sg:phone":"+1 718 339 2931",
    "sg:postcode":"11229",
    "sg:province":"NY",
    "sg:tags":[
        "upholsterer"
    ],
    "wof:name":"Simon's Decorating & Design",
    "wof:placetype":"venue"
},
  "geometry": {"coordinates":[-73.95460199999999,40.609618],"type":"Point"}
}