{
  "type": "Feature",
  "properties": {
    "iso:country":"US",
    "sg:address":"29 Lincoln Ave",
    "sg:city":"Farmingdale",
    "sg:classifiers":[
        {
            "category":"Shopping",
            "subcategory":"Clothing, Apparel, & Fashions",
            "type":"Retail Goods"
        }
    ],
    "sg:phone":"+1 516 293 2591",
    "sg:postcode":"11735",
    "sg:province":"NY",
    "wof:name":"Crystal Fashion",
    "wof:placetype":"venue"
},
  "geometry": {"coordinates":[-73.42202399999999,40.710829],"type":"Point"}
}