{
  "type": "Feature",
  "properties": {
    "addr:full":"438 Court St Brooklyn NY 11231",
    "addr:housenumber":"438",
    "addr:postcode":"11231",
    "addr:street":"Court St",
    "iso:country":"US",
    "sg:address":"438 Court St",
    "sg:city":"Brooklyn",
    "sg:classifiers":[
        {
            "category":"Personal",
            "subcategory":"Beauty Salon",
            "type":"Services"
        }
    ],
    "sg:phone":"+1 718 625 3065",
    "sg:postcode":"11231",
    "sg:province":"NY",
    "sg:tags":[
        "nail",
        "manicuring"
    ],
    "wof:name":"Jin Beauty Nail",
    "wof:placetype":"venue"
},
  "geometry": {"coordinates":[-73.997704,40.6791],"type":"Point"}
}