{
  "type": "Feature",
  "properties": {
    "iso:country":"US",
    "sg:address":"4408 Milestrip Rd",
    "sg:city":"Buffalo",
    "sg:classifiers":[
        {
            "category":"Restaurant",
            "type":"Food & Drink"
        }
    ],
    "sg:menulink":"http://www.allmenus.com/ny/hamburg/64398-chuck-e-cheeses/menu/",
    "sg:phone":"+1 716 822 2221",
    "sg:postcode":"14219",
    "sg:province":"NY",
    "sg:tags":[
        "american",
        "pizza"
    ],
    "wof:name":"Chuck E. Cheese's",
    "wof:placetype":"venue"
},
  "geometry": {"coordinates":[-78.814785,42.789955],"type":"Point"}
}