{
  "type": "Feature",
  "properties": {
    "iso:country":"US",
    "sg:address":"100 Roberts St",
    "sg:city":"Binghamton",
    "sg:classifiers":[
        {
            "category":"Restaurant",
            "type":"Food & Drink"
        }
    ],
    "sg:phone":"+1   ",
    "sg:postcode":"13901",
    "sg:province":"NY",
    "sg:tags":[
        "eating"
    ],
    "wof:name":"Grandma Jos Wings Over Broome",
    "wof:placetype":"venue"
},
  "geometry": {"coordinates":[-75.90182,42.108638],"type":"Point"}
}