{
  "type": "Feature",
  "properties": {
    "iso:country":"US",
    "sg:address":"1 Guy Park Ave",
    "sg:city":"Amsterdam",
    "sg:classifiers":[
        {
            "category":"Health Services",
            "subcategory":"Doctor",
            "type":"Services"
        }
    ],
    "sg:phone":"+1 518 842 0373",
    "sg:postcode":"12010",
    "sg:province":"NY",
    "sg:tags":[
        "medical"
    ],
    "wof:name":"James M Charland MD",
    "wof:placetype":"venue"
},
  "geometry": {"coordinates":[-74.19311999999999,42.940188],"type":"Point"}
}