{
  "type": "Feature",
  "properties": {
    "addr:full":"1811 Williamsbridge Rd Bronx NY 10461",
    "addr:housenumber":"1811",
    "addr:postcode":"10461",
    "addr:street":"Williamsbridge Rd",
    "iso:country":"US",
    "sg:address":"1811 Williamsbridge Rd",
    "sg:city":"Bronx",
    "sg:classifiers":[
        {
            "category":"Restaurant",
            "type":"Food & Drink"
        }
    ],
    "sg:phone":"+1 718 823 9248",
    "sg:postcode":"10461",
    "sg:province":"NY",
    "sg:tags":[
        "chinese"
    ],
    "wof:name":"China King Restaurant",
    "wof:placetype":"venue"
},
  "geometry": {"coordinates":[-73.851601,40.850399],"type":"Point"}
}