{
  "type": "Feature",
  "properties": {
    "addr:full":"1135 Morris Park Avenue Bronx NY 10461",
    "addr:housenumber":"1135",
    "addr:postcode":"10461",
    "addr:street":"Morris Park Avenue",
    "iso:country":"US",
    "sg:address":"1135 Morris Park Avenue",
    "sg:city":"Bronx",
    "sg:classifiers":[
        {
            "category":"Bakery",
            "type":"Food & Drink"
        },
        {
            "category":"Bagels",
            "subcategory":"None",
            "type":"Food & Drink"
        }
    ],
    "sg:phone":"+1 718 829 5198",
    "sg:postcode":"10461",
    "sg:province":"NY",
    "wof:name":"B&B Bakery",
    "wof:placetype":"venue"
},
  "geometry": {"coordinates":[-73.851581,40.850232],"type":"Point"}
}