{
  "type": "Feature",
  "properties": {
    "iso:country":"US",
    "sg:address":"440 Hover Ave",
    "sg:city":"Germantown",
    "sg:classifiers":[
        {
            "category":"Building & Trades",
            "subcategory":"Construction",
            "type":"Services"
        }
    ],
    "sg:phone":"+1 518 537 4248",
    "sg:postcode":"12526",
    "sg:province":"NY",
    "sg:tags":[
        "masonry",
        "contractor"
    ],
    "wof:name":"Richard Duntz & Son",
    "wof:placetype":"venue"
},
  "geometry": {"coordinates":[-73.875553,42.133067],"type":"Point"}
}