{
  "type": "Feature",
  "properties": {
    "addr:full":"6309 Hidden Meadow Dr Marcy NY 13403",
    "addr:housenumber":"6309",
    "addr:postcode":"13403",
    "addr:street":"Hidden Meadow Dr",
    "iso:country":"US",
    "sg:address":"6309 Hidden Meadow Dr",
    "sg:city":"Marcy",
    "sg:classifiers":[
        {
            "category":"Building & Trades",
            "subcategory":"Plumbing",
            "type":"Services"
        }
    ],
    "sg:phone":"+1 315 724 3294",
    "sg:postcode":"13403",
    "sg:province":"NY",
    "sg:tags":[
        "contractor"
    ],
    "wof:name":"G M Hewitt Inc",
    "wof:placetype":"venue"
},
  "geometry": {"coordinates":[-75.249253,43.168312],"type":"Point"}
}