{
  "type": "Feature",
  "properties": {
    "addr:full":"122 Buffalo Ave Freeport NY 11520",
    "addr:housenumber":"122",
    "addr:postcode":"11520",
    "addr:street":"Buffalo Ave",
    "iso:country":"US",
    "sg:address":"122 Buffalo Ave",
    "sg:city":"Freeport",
    "sg:classifiers":[
        {
            "category":"Wholesale",
            "subcategory":"Scrap",
            "type":"Manufacturing & Wholesale Goods"
        }
    ],
    "sg:phone":"+1 516 378 9463",
    "sg:postcode":"11520",
    "sg:province":"NY",
    "sg:tags":[
        "auto",
        "material"
    ],
    "sg:website":"www.freeportautoparts.com",
    "wof:name":"Freeport Auto Parts & Wrecking",
    "wof:placetype":"venue"
},
  "geometry": {"coordinates":[-73.571445,40.652077],"type":"Point"}
}