{
  "type": "Feature",
  "properties": {
    "addr:full":"140 Main St Grahamsville NY 12740",
    "addr:housenumber":"140",
    "addr:postcode":"12740",
    "addr:street":"Main St",
    "iso:country":"US",
    "sg:address":"140 Main St",
    "sg:city":"Grahamsville",
    "sg:classifiers":[
        {
            "category":"Insurance",
            "subcategory":"Hazard Insurance",
            "type":"Services"
        }
    ],
    "sg:phone":"+1 845 985 0065",
    "sg:postcode":"12740",
    "sg:province":"NY",
    "sg:tags":[
        "commercial",
        "business"
    ],
    "wof:name":"Turtz Ins",
    "wof:placetype":"venue"
},
  "geometry": {"coordinates":[-74.54428299999999,41.846219],"type":"Point"}
}