{
  "type": "Feature",
  "properties": {
    "addr:full":"205 E 42nd St New York NY 10017",
    "addr:housenumber":"205",
    "addr:postcode":"10017",
    "addr:street":"E 42Nd St",
    "iso:country":"US",
    "sg:address":"205 E 42nd St",
    "sg:city":"New York",
    "sg:classifiers":[
        {
            "category":"Insurance",
            "subcategory":"Insurance Agent",
            "type":"Services"
        }
    ],
    "sg:phone":"+1 212 885 1530",
    "sg:postcode":"10017",
    "sg:province":"NY",
    "sg:tags":[
        "agency"
    ],
    "wof:name":"Great American",
    "wof:placetype":"venue"
},
  "geometry": {"coordinates":[-73.972236,40.749927],"type":"Point"}
}