{
  "type": "Feature",
  "properties": {
    "addr:full":"161 Avenue of the Americ New York NY 10013",
    "addr:housenumber":"161",
    "addr:postcode":"10013",
    "addr:street":"Avenue Of The",
    "iso:country":"US",
    "sg:address":"161 Avenue of the Americ",
    "sg:city":"New York",
    "sg:classifiers":[
        {
            "category":"Professional",
            "subcategory":"Lawyer & Legal Services",
            "type":"Services"
        }
    ],
    "sg:phone":"+1 212 768 1666",
    "sg:postcode":"10013",
    "sg:province":"NY",
    "wof:name":"Kerson Edward W Atty",
    "wof:placetype":"venue"
},
  "geometry": {"coordinates":[-74.004086,40.72538],"type":"Point"}
}