{
  "type": "Feature",
  "properties": {
    "iso:country":"US",
    "sg:address":"561 Wilson Ave",
    "sg:city":"Brooklyn",
    "sg:classifiers":[
        {
            "category":"Shopping",
            "subcategory":"Clothing, Apparel, & Fashions",
            "type":"Retail Goods"
        }
    ],
    "sg:phone":"+1 718 453 2714",
    "sg:postcode":"11207",
    "sg:province":"NY",
    "sg:tags":[
        "sportswear"
    ],
    "wof:name":"Jessica Sportswear",
    "wof:placetype":"venue"
},
  "geometry": {"coordinates":[-73.90907799999999,40.69138],"type":"Point"}
}