{
  "type": "Feature",
  "properties": {
    "addr:full":"1443 Western Ave Albany NY 12203",
    "addr:housenumber":"1443",
    "addr:postcode":"12203",
    "addr:street":"Western Ave",
    "iso:country":"US",
    "sg:address":"1443 Western Ave",
    "sg:city":"Albany",
    "sg:classifiers":[
        {
            "category":"Health Services",
            "subcategory":"Doctor",
            "type":"Services"
        }
    ],
    "sg:phone":"+1 518 438 9894",
    "sg:postcode":"12203",
    "sg:province":"NY",
    "wof:name":"Dr Leonard Bero Dentistry",
    "wof:placetype":"venue"
},
  "geometry": {"coordinates":[-73.834052,42.679949],"type":"Point"}
}