{
  "type": "Feature",
  "properties": {
    "iso:country":"US",
    "sg:address":"304 W 14 St",
    "sg:city":"New York",
    "sg:classifiers":[
        {
            "category":"Retail",
            "subcategory":"Auto Repair",
            "type":"Services"
        }
    ],
    "sg:phone":"+1 917 477 6067",
    "sg:postcode":"10014",
    "sg:province":"NY",
    "sg:tags":[
        "wrecker"
    ],
    "wof:name":"Emergency 7 Day Towing",
    "wof:placetype":"venue"
},
  "geometry": {"coordinates":[-74.00511299999999,40.740746],"type":"Point"}
}