{
  "type": "Feature",
  "properties": {
    "iso:country":"US",
    "sg:address":"227 Milton Rd",
    "sg:city":"Rye",
    "sg:classifiers":[
        {
            "category":"Banks & Credit Unions",
            "subcategory":"Investment Brokerage",
            "type":"Services"
        }
    ],
    "sg:phone":"+1 914 967 4016",
    "sg:postcode":"10580",
    "sg:province":"NY",
    "sg:tags":[
        "advisory"
    ],
    "wof:name":"Weston Capital",
    "wof:placetype":"venue"
},
  "geometry": {"coordinates":[-73.685638,40.972408],"type":"Point"}
}