{
  "type": "Feature",
  "properties": {
    "iso:country":"US",
    "sg:address":"1 Pineview Ct",
    "sg:city":"Waterford",
    "sg:classifiers":[
        {
            "category":"Building & Trades",
            "subcategory":"Construction",
            "type":"Services"
        }
    ],
    "sg:phone":"+1 518 237 6925",
    "sg:postcode":"12188",
    "sg:province":"NY",
    "sg:tags":[
        "contractor"
    ],
    "wof:name":"American Sun Control",
    "wof:placetype":"venue"
},
  "geometry": {"coordinates":[-73.697245,42.823198],"type":"Point"}
}