{
  "type": "Feature",
  "properties": {
    "iso:country":"US",
    "sg:address":"1433 Cleveland Dr",
    "sg:city":"Buffalo",
    "sg:classifiers":[
        {
            "category":"Building & Trades",
            "subcategory":"Construction",
            "type":"Services"
        }
    ],
    "sg:phone":"+1 716 632 7792",
    "sg:postcode":"14225",
    "sg:province":"NY",
    "sg:tags":[
        "house"
    ],
    "wof:name":"Home Tech Remodeling",
    "wof:placetype":"venue"
},
  "geometry": {"coordinates":[-78.74582599999999,42.941416],"type":"Point"}
}