{
  "type": "Feature",
  "properties": {
    "addr:full":"10904 Northern Blvd Corona NY 11368",
    "addr:housenumber":"10904",
    "addr:postcode":"11368",
    "addr:street":"Northern Blvd",
    "iso:country":"US",
    "sg:address":"10904 Northern Blvd",
    "sg:city":"Corona",
    "sg:classifiers":[
        {
            "category":"Manufacturing",
            "subcategory":"Buildings",
            "type":"Manufacturing & Wholesale Goods"
        },
        {
            "category":"Building & Trades",
            "subcategory":"Construction",
            "type":"Services"
        }
    ],
    "sg:phone":"+1 718 446 6900",
    "sg:postcode":"11368",
    "sg:province":"NY",
    "sg:tags":[
        "home",
        "builder",
        "contractor"
    ],
    "wof:name":"Coldwell Banker Home Value Rea",
    "wof:placetype":"venue"
},
  "geometry": {"coordinates":[-73.84659600000001,40.760044],"type":"Point"}
}