{
  "type": "Feature",
  "properties": {
    "addr:full":"3120 Shippers Rd Vestal NY 13850",
    "addr:housenumber":"3120",
    "addr:postcode":"13850",
    "addr:street":"Shippers Rd",
    "iso:country":"US",
    "sg:address":"3120 Shippers Rd",
    "sg:city":"Vestal",
    "sg:classifiers":[
        {
            "category":"Wholesale",
            "subcategory":"Scrap",
            "type":"Manufacturing & Wholesale Goods"
        }
    ],
    "sg:phone":"+1 607 797 2331",
    "sg:postcode":"13850",
    "sg:province":"NY",
    "sg:tags":[
        "recycling",
        "center"
    ],
    "wof:name":"Star Inc",
    "wof:placetype":"venue"
},
  "geometry": {"coordinates":[-76.00503999999999,42.099922],"type":"Point"}
}