{
  "type": "Feature",
  "properties": {
    "addr:full":"6295 Dorchester Rd Lockport NY 14094",
    "addr:housenumber":"6295",
    "addr:postcode":"14094",
    "addr:street":"Dorchester Rd",
    "iso:country":"US",
    "sg:address":"6295 Dorchester Rd",
    "sg:city":"Lockport",
    "sg:classifiers":[
        {
            "category":"Manufacturing",
            "subcategory":"Printing",
            "type":"Manufacturing & Wholesale Goods"
        }
    ],
    "sg:phone":"+1   ",
    "sg:postcode":"14094",
    "sg:province":"NY",
    "sg:tags":[
        "publishing"
    ],
    "wof:name":"Liberty Press",
    "wof:placetype":"venue"
},
  "geometry": {"coordinates":[-78.69168500000001,43.150318],"type":"Point"}
}