{
  "type": "Feature",
  "properties": {
    "addr:full":"366 Graham Ave Brooklyn NY 11211",
    "addr:housenumber":"366",
    "addr:postcode":"11211",
    "addr:street":"Graham Ave",
    "iso:country":"US",
    "sg:address":"366 Graham Ave",
    "sg:city":"Brooklyn",
    "sg:classifiers":[
        {
            "category":"Shopping",
            "subcategory":"Optical Goods",
            "type":"Retail Goods"
        }
    ],
    "sg:phone":"+1 718 387 3590",
    "sg:postcode":"11211",
    "sg:province":"NY",
    "sg:tags":[
        "optician"
    ],
    "wof:name":"Sharp Vision Optical",
    "wof:placetype":"venue"
},
  "geometry": {"coordinates":[-73.944615,40.715939],"type":"Point"}
}