{
  "type": "Feature",
  "properties": {
    "addr:full":"3736 Henry Hudson Pkwy E Bronx NY 10463",
    "addr:housenumber":"3736",
    "addr:postcode":"10463",
    "addr:street":"Henry Hudson Pkwy E",
    "iso:country":"US",
    "sg:address":"3736 Henry Hudson Pkwy E",
    "sg:city":"Bronx",
    "sg:classifiers":[
        {
            "category":"Health Services",
            "subcategory":"Doctor",
            "type":"Services"
        }
    ],
    "sg:phone":"+1 718 543 5624",
    "sg:postcode":"10463",
    "sg:province":"NY",
    "sg:tags":[
        "medical"
    ],
    "wof:name":"Oberlander & Hirsch LLP",
    "wof:placetype":"venue"
},
  "geometry": {"coordinates":[-73.909774,40.888304],"type":"Point"}
}