{
  "type": "Feature",
  "properties": {
    "addr:full":"1331 Utica Ave Brooklyn NY 11203",
    "addr:housenumber":"1331",
    "addr:postcode":"11203",
    "addr:street":"Utica Ave",
    "iso:country":"US",
    "sg:address":"1331 Utica Ave",
    "sg:city":"Brooklyn",
    "sg:classifiers":[
        {
            "category":"Retail",
            "subcategory":"Auto Repair",
            "type":"Services"
        }
    ],
    "sg:phone":"+1   ",
    "sg:postcode":"11203",
    "sg:province":"NY",
    "sg:tags":[
        "automotive"
    ],
    "wof:name":"Magda Foreign Car Service",
    "wof:placetype":"venue"
},
  "geometry": {"coordinates":[-73.929199,40.641886],"type":"Point"}
}