{
  "type": "Feature",
  "properties": {
    "iso:country":"US",
    "sg:address":"204 N Center St",
    "sg:city":"East Syracuse",
    "sg:classifiers":[
        {
            "category":"Government",
            "subcategory":"Fire Station",
            "type":"Public Place"
        }
    ],
    "sg:phone":"+1 315 437 3541",
    "sg:postcode":"13057",
    "sg:province":"NY",
    "sg:tags":[
        "department"
    ],
    "wof:name":"East Syracuse Fire Dept",
    "wof:placetype":"venue"
},
  "geometry": {"coordinates":[-76.070915,43.065016],"type":"Point"}
}