{
  "type": "Feature",
  "properties": {
    "iso:country":"US",
    "sg:address":"860 Ives Settlement Rd",
    "sg:city":"Bainbridge",
    "sg:classifiers":[
        {
            "category":"Farming",
            "subcategory":"Dairy Farm",
            "type":"Manufacturing & Wholesale Goods"
        }
    ],
    "sg:phone":"+1 607 895 6500",
    "sg:postcode":"13733",
    "sg:province":"NY",
    "sg:tags":[
        "corn"
    ],
    "wof:name":"Pershing Schlafer and Son",
    "wof:placetype":"venue"
},
  "geometry": {"coordinates":[-75.442404,42.375423],"type":"Point"}
}