{
  "type": "Feature",
  "properties": {
    "addr:full":"3755 Military Rd Niagara Falls NY 14305",
    "addr:housenumber":"3755",
    "addr:postcode":"14305",
    "addr:street":"Military Rd",
    "iso:country":"US",
    "sg:address":"3755 Military Rd",
    "sg:city":"Niagara Falls",
    "sg:classifiers":[
        {
            "category":"Autos & Motor Vehicles",
            "subcategory":"Automobile Sales",
            "type":"Retail Goods"
        }
    ],
    "sg:phone":"+1   ",
    "sg:postcode":"14305",
    "sg:province":"NY",
    "sg:tags":[
        "used"
    ],
    "wof:name":"Ken Currie Motors Inc",
    "wof:placetype":"venue"
},
  "geometry": {"coordinates":[-79.00003599999999,43.122978],"type":"Point"}
}