{
  "type": "Feature",
  "properties": {
    "addr:full":"841 Franklin Ave Thornwood NY 10594",
    "addr:housenumber":"841",
    "addr:postcode":"10594",
    "addr:street":"Franklin Ave",
    "iso:country":"US",
    "sg:address":"841 Franklin Ave",
    "sg:city":"Thornwood",
    "sg:classifiers":[
        {
            "category":"Home & Garden",
            "subcategory":"Garden Supply",
            "type":"Retail Goods"
        }
    ],
    "sg:phone":"+1 914 769 6104",
    "sg:postcode":"10594",
    "sg:province":"NY",
    "sg:tags":[
        "lawn",
        "mower"
    ],
    "wof:name":"M & F Pinto",
    "wof:placetype":"venue"
},
  "geometry": {"coordinates":[-73.78151099999999,41.122602],"type":"Point"}
}