{
  "type": "Feature",
  "properties": {
    "iso:country":"US",
    "sg:address":"390 Manor Road",
    "sg:city":"Staten Island",
    "sg:classifiers":[
        {
            "category":"Professional",
            "subcategory":"Lawyer & Legal Services",
            "type":"Services"
        }
    ],
    "sg:phone":"+1 718 816 5510",
    "sg:postcode":"10314",
    "sg:province":"NY",
    "wof:name":"Wynne Court Reporting",
    "wof:placetype":"venue"
},
  "geometry": {"coordinates":[-74.123474,40.618055],"type":"Point"}
}