{
  "type": "Feature",
  "properties": {
    "iso:country":"US",
    "sg:address":"3084 Niagara St",
    "sg:city":"Niagara Falls",
    "sg:classifiers":[
        {
            "category":"Wholesale",
            "subcategory":"Hardware",
            "type":"Manufacturing & Wholesale Goods"
        },
        {
            "category":"Manufacturing",
            "subcategory":"Food",
            "type":"Manufacturing & Wholesale Goods"
        }
    ],
    "sg:phone":"+1 716 282 1606",
    "sg:postcode":"14303",
    "sg:province":"NY",
    "sg:tags":[
        "beverage",
        "soft",
        "dispensing",
        "drink",
        "mfg"
    ],
    "wof:name":"Johnnie Ryan Co Inc",
    "wof:placetype":"venue"
},
  "geometry": {"coordinates":[-79.023291,43.088308],"type":"Point"}
}