{
  "type": "Feature",
  "properties": {
    "addr:full":"37 Heatherwood Rd Fairport NY 14450",
    "addr:housenumber":"37",
    "addr:postcode":"14450",
    "addr:street":"Heatherwood Rd",
    "iso:country":"US",
    "sg:address":"37 Heatherwood Rd",
    "sg:city":"Fairport",
    "sg:classifiers":[
        {
            "category":"Professional",
            "subcategory":"Business Services",
            "type":"Services"
        }
    ],
    "sg:phone":"+1 585 377 4808",
    "sg:postcode":"14450",
    "sg:province":"NY",
    "sg:tags":[
        "technical",
        "training",
        "managerial"
    ],
    "wof:name":"Pen Associates of Rochester",
    "wof:placetype":"venue"
},
  "geometry": {"coordinates":[-77.430408,43.113934],"type":"Point"}
}