{
  "type": "Feature",
  "properties": {
    "iso:country":"US",
    "sg:address":"104 W 27 St",
    "sg:city":"New York",
    "sg:classifiers":[
        {
            "category":"Personal",
            "type":"Services"
        }
    ],
    "sg:phone":"+1 212 352 0600",
    "sg:postcode":"10001",
    "sg:province":"NY",
    "sg:tags":[
        "info",
        "consumer"
    ],
    "wof:name":"Digital Transcation Mchs LLC",
    "wof:placetype":"venue"
},
  "geometry": {"coordinates":[-73.99376100000001,40.746504],"type":"Point"}
}