{
  "type": "Feature",
  "properties": {
    "addr:full":"5234 Co Rd 4 Burdett NY 14818",
    "addr:housenumber":"5234",
    "addr:postcode":"14818",
    "addr:street":"Co Rd 4",
    "iso:country":"US",
    "sg:address":"5234 Co Rd 4",
    "sg:city":"Burdett",
    "sg:classifiers":[
        {
            "category":"Retail",
            "subcategory":"Auto Repair",
            "type":"Services"
        }
    ],
    "sg:phone":"+1   ",
    "sg:postcode":"14818",
    "sg:province":"NY",
    "sg:tags":[
        "general"
    ],
    "wof:name":"Marvin Secord Garage",
    "wof:placetype":"venue"
},
  "geometry": {"coordinates":[-76.82867400000001,42.474075],"type":"Point"}
}