{
  "type": "Feature",
  "properties": {
    "addr:full":"607 High Falls Rd Saugerties NY 12477",
    "addr:housenumber":"607",
    "addr:postcode":"12477",
    "addr:street":"High Falls Rd",
    "iso:country":"US",
    "sg:address":"607 High Falls Rd",
    "sg:city":"Saugerties",
    "sg:classifiers":[
        {
            "category":"Retail",
            "subcategory":"Portrait Studio",
            "type":"Services"
        }
    ],
    "sg:phone":"+1 518 678 6251",
    "sg:postcode":"12477",
    "sg:province":"NY",
    "sg:tags":[
        "photographer"
    ],
    "wof:name":"Evergreen Studios Inc",
    "wof:placetype":"venue"
},
  "geometry": {"coordinates":[-73.97851,42.157486],"type":"Point"}
}