{
  "type": "Feature",
  "properties": {
    "iso:country":"US",
    "sg:address":"10 Leach Rd",
    "sg:city":"Lyons",
    "sg:classifiers":[
        {
            "category":"Government",
            "subcategory":"Office",
            "type":"Public Place"
        }
    ],
    "sg:phone":"+1 315 946 4948",
    "sg:postcode":"14489",
    "sg:province":"NY",
    "wof:name":"Senator Michael F Nozzolio",
    "wof:placetype":"venue"
},
  "geometry": {"coordinates":[-77.00170900000001,43.056174],"type":"Point"}
}