{
  "type": "Feature",
  "properties": {
    "iso:country":"US",
    "sg:address":"2784 Fulton St",
    "sg:city":"Brooklyn",
    "sg:classifiers":[
        {
            "category":"Shopping",
            "subcategory":"Clothing, Apparel, & Fashions",
            "type":"Retail Goods"
        }
    ],
    "sg:phone":"+1   ",
    "sg:postcode":"11207",
    "sg:province":"NY",
    "wof:name":"Asqui Corp",
    "wof:placetype":"venue"
},
  "geometry": {"coordinates":[-73.891975,40.677897],"type":"Point"}
}