{
  "type": "Feature",
  "properties": {
    "addr:full":"20 Woods Ln Scarsdale NY 10583",
    "addr:housenumber":"20",
    "addr:postcode":"10583",
    "addr:street":"Woods Ln",
    "iso:country":"US",
    "sg:address":"20 Woods Ln",
    "sg:city":"Scarsdale",
    "sg:classifiers":[
        {
            "category":"Building & Trades",
            "subcategory":"Construction",
            "type":"Services"
        }
    ],
    "sg:phone":"+1 914 472 3373",
    "sg:postcode":"10583",
    "sg:province":"NY",
    "sg:tags":[
        "general",
        "contractor"
    ],
    "wof:name":"Avellino Construction",
    "wof:placetype":"venue"
},
  "geometry": {"coordinates":[-73.790347,40.982889],"type":"Point"}
}