{
  "type": "Feature",
  "properties": {
    "addr:full":"10 S Oyster Bay Rd Syosset NY 11791",
    "addr:housenumber":"10",
    "addr:postcode":"11791",
    "addr:street":"S Oyster Bay Rd",
    "iso:country":"US",
    "sg:address":"10 S Oyster Bay Rd",
    "sg:city":"Syosset",
    "sg:classifiers":[
        {
            "category":"Home & Garden",
            "subcategory":"Home Furnishings",
            "type":"Retail Goods"
        }
    ],
    "sg:phone":"+1   ",
    "sg:postcode":"11791",
    "sg:province":"NY",
    "wof:name":"Cutlers Lighting Fixtures",
    "wof:placetype":"venue"
},
  "geometry": {"coordinates":[-73.501957,40.809449],"type":"Point"}
}