{
  "type": "Feature",
  "properties": {
    "iso:country":"US",
    "sg:address":"69 Ave B",
    "sg:city":"West Babylon",
    "sg:classifiers":[
        {
            "category":"Manufacturing",
            "subcategory":"Tools & Machinery",
            "type":"Manufacturing & Wholesale Goods"
        }
    ],
    "sg:phone":"+1 631 643 6690",
    "sg:postcode":"11704",
    "sg:province":"NY",
    "sg:tags":[
        "machine",
        "shop"
    ],
    "wof:name":"Matrix Machining Corp",
    "wof:placetype":"venue"
},
  "geometry": {"coordinates":[-73.35600100000001,40.703519],"type":"Point"}
}