{
  "type": "Feature",
  "properties": {
    "iso:country":"US",
    "sg:address":"209 Northern Blvd # 18",
    "sg:city":"Floral Park",
    "sg:classifiers":[
        {
            "category":"Autos & Motor Vehicles",
            "subcategory":"Automobile Sales",
            "type":"Retail Goods"
        },
        {
            "category":"Retail",
            "subcategory":"Auto Repair",
            "type":"Services"
        }
    ],
    "sg:phone":"+1 718 428 7222",
    "sg:postcode":"11001",
    "sg:province":"NY",
    "sg:tags":[
        "car"
    ],
    "wof:name":"Saab At Bayside",
    "wof:placetype":"venue"
},
  "geometry": {"coordinates":[-73.70839700000001,40.725399],"type":"Point"}
}