{
  "type": "Feature",
  "properties": {
    "addr:full":"122 W 22nd St New York NY 10011",
    "addr:housenumber":"122",
    "addr:postcode":"10011",
    "addr:street":"W 22Nd St",
    "iso:country":"US",
    "sg:address":"122 W 22nd St",
    "sg:city":"New York",
    "sg:classifiers":[
        {
            "category":"Home & Garden",
            "subcategory":"Garden Supply",
            "type":"Retail Goods"
        },
        {
            "category":"Home & Garden",
            "subcategory":"Home Furnishings",
            "type":"Retail Goods"
        }
    ],
    "sg:phone":"+1 212 741 5555",
    "sg:postcode":"10011",
    "sg:province":"NY",
    "sg:tags":[
        "decor",
        "nursery",
        "gardening"
    ],
    "sg:website":"www.americanfoliagedesign.com/de...",
    "wof:name":"American Foliage & Design Group Inc",
    "wof:placetype":"venue"
},
  "geometry": {"coordinates":[-73.99400300000001,40.742699],"type":"Point"}
}