{
  "type": "Feature",
  "properties": {
    "iso:country":"US",
    "sg:address":"115 Henry St",
    "sg:city":"Binghamton",
    "sg:classifiers":[
        {
            "category":"Government",
            "subcategory":"Post Office",
            "type":"Public Place"
        }
    ],
    "sg:phone":"+1 607 773 2162",
    "sg:postcode":"13901",
    "sg:province":"NY",
    "wof:name":"Passports",
    "wof:placetype":"venue"
},
  "geometry": {"coordinates":[-75.90636600000001,42.101819],"type":"Point"}
}