{
  "type": "Feature",
  "properties": {
    "iso:country":"US",
    "sg:address":"895 Franklin Ave",
    "sg:city":"Brooklyn",
    "sg:classifiers":[
        {
            "category":"Wholesale",
            "subcategory":"Jewelry",
            "type":"Manufacturing & Wholesale Goods"
        }
    ],
    "sg:phone":"+1 718 771 6702",
    "sg:postcode":"11225",
    "sg:province":"NY",
    "sg:tags":[
        "stone"
    ],
    "wof:name":"R & S Gold Exchange",
    "wof:placetype":"venue"
},
  "geometry": {"coordinates":[-73.958634,40.668807],"type":"Point"}
}