{
  "type": "Feature",
  "properties": {
    "addr:full":"241 W 23rd St New York NY 10011",
    "addr:housenumber":"241",
    "addr:postcode":"10011",
    "addr:street":"W 23Rd St",
    "iso:country":"US",
    "sg:address":"241 W 23rd St",
    "sg:city":"New York",
    "sg:classifiers":[
        {
            "category":"Retail",
            "subcategory":"Repair Shop",
            "type":"Services"
        }
    ],
    "sg:phone":"+1 212 492 9500",
    "sg:postcode":"10011",
    "sg:province":"NY",
    "sg:tags":[
        "lock",
        "locksmith"
    ],
    "wof:name":"All 24 Hour 7 Day Er Locksmith",
    "wof:placetype":"venue"
},
  "geometry": {"coordinates":[-73.99757099999999,40.744872],"type":"Point"}
}