{
  "type": "Feature",
  "properties": {
    "addr:full":"188 Nassau Ave Brooklyn NY 11222",
    "addr:housenumber":"188",
    "addr:postcode":"11222",
    "addr:street":"Nassau Ave",
    "iso:country":"US",
    "sg:address":"188 Nassau Ave",
    "sg:city":"Brooklyn",
    "sg:classifiers":[
        {
            "category":"Education",
            "subcategory":"Special Training",
            "type":"Public Place"
        }
    ],
    "sg:phone":"+1 718 383 1666",
    "sg:postcode":"11222",
    "sg:province":"NY",
    "sg:tags":[
        "school",
        "driving"
    ],
    "wof:name":"Polonia Driving School",
    "wof:placetype":"venue"
},
  "geometry": {"coordinates":[-73.945801,40.725399],"type":"Point"}
}