{
  "type": "Feature",
  "properties": {
    "addr:full":"1687 Foster Ave Schenectady NY 12308",
    "addr:housenumber":"1687",
    "addr:postcode":"12308",
    "addr:street":"Foster Ave",
    "iso:country":"US",
    "sg:address":"1687 Foster Ave",
    "sg:city":"Schenectady",
    "sg:classifiers":[
        {
            "category":"Restaurant",
            "type":"Food & Drink"
        }
    ],
    "sg:menulink":"http://www.allmenus.com/ny/schenectady/33428-john-riccitellos/menu/",
    "sg:phone":"+1 518 374 1574",
    "sg:postcode":"12308",
    "sg:province":"NY",
    "sg:tags":[
        "american"
    ],
    "wof:name":"John Riccitello's",
    "wof:placetype":"venue"
},
  "geometry": {"coordinates":[-73.92711,42.824433],"type":"Point"}
}