{
  "type": "Feature",
  "properties": {
    "iso:country":"US",
    "sg:address":"927 Port Washington Blvd",
    "sg:city":"Port Washington",
    "sg:classifiers":[
        {
            "category":"Health Services",
            "subcategory":"Chiropractor",
            "type":"Services"
        }
    ],
    "sg:phone":"+1 516 627 7463",
    "sg:postcode":"11050",
    "sg:province":"NY",
    "wof:name":"Laurence Oliviero DC",
    "wof:placetype":"venue"
},
  "geometry": {"coordinates":[-73.683791,40.829405],"type":"Point"}
}