{
  "type": "Feature",
  "properties": {
    "iso:country":"US",
    "sg:address":"39 W 29th St",
    "sg:city":"New York",
    "sg:classifiers":[
        {
            "category":"Professional",
            "subcategory":"Management & Consulting",
            "type":"Services"
        }
    ],
    "sg:phone":"+1 212 686 6004",
    "sg:postcode":"10001",
    "sg:province":"NY",
    "sg:tags":[
        "consultant"
    ],
    "wof:name":"Proximo Consulting Services",
    "wof:placetype":"venue"
},
  "geometry": {"coordinates":[-73.98987099999999,40.746636],"type":"Point"}
}