{
  "type": "Feature",
  "properties": {
    "addr:full":"63 Marc Ct Westbury NY 11590",
    "addr:housenumber":"63",
    "addr:postcode":"11590",
    "addr:street":"Marc Ct",
    "iso:country":"US",
    "sg:address":"63 Marc Ct",
    "sg:city":"Westbury",
    "sg:classifiers":[
        {
            "category":"Shopping",
            "subcategory":"Catalog Store",
            "type":"Retail Goods"
        }
    ],
    "sg:phone":"+1 516 333 7515",
    "sg:postcode":"11590",
    "sg:province":"NY",
    "sg:tags":[
        "e"
    ],
    "wof:name":"Blue Grotto Media Inc",
    "wof:placetype":"venue"
},
  "geometry": {"coordinates":[-73.571527,40.773373],"type":"Point"}
}