{
  "type": "Feature",
  "properties": {
    "iso:country":"US",
    "sg:address":"577 W Hill Rd",
    "sg:city":"Sherburne",
    "sg:classifiers":[
        {
            "category":"Home & Garden",
            "subcategory":"Building Materials",
            "type":"Retail Goods"
        }
    ],
    "sg:phone":"+1   ",
    "sg:postcode":"13460",
    "sg:province":"NY",
    "wof:name":"Smyrna Flat Iron Lumber",
    "wof:placetype":"venue"
},
  "geometry": {"coordinates":[-75.53307700000001,42.685285],"type":"Point"}
}