{
  "type": "Feature",
  "properties": {
    "addr:full":"9 South Ave Webster NY 14580",
    "addr:housenumber":"9",
    "addr:postcode":"14580",
    "addr:street":"South Ave",
    "iso:country":"US",
    "sg:address":"9 South Ave",
    "sg:city":"Webster",
    "sg:classifiers":[
        {
            "category":"Restaurant",
            "type":"Food & Drink"
        }
    ],
    "sg:phone":"+1   ",
    "sg:postcode":"14580",
    "sg:province":"NY",
    "sg:tags":[
        "eating"
    ],
    "wof:name":"Pizza Tonight",
    "wof:placetype":"venue"
},
  "geometry": {"coordinates":[-77.430396,43.210251],"type":"Point"}
}