{
  "type": "Feature",
  "properties": {
    "addr:full":"3900 Union Rd Buffalo NY 14225",
    "addr:housenumber":"3900",
    "addr:postcode":"14225",
    "addr:street":"Union Rd",
    "iso:country":"US",
    "sg:address":"3900 Union Rd",
    "sg:city":"Buffalo",
    "sg:classifiers":[
        {
            "category":"Deli",
            "type":"Food & Drink"
        }
    ],
    "sg:menulink":"http://www.allmenus.com/ny/cheektowaga/245770-dibellas-submarines/menu/",
    "sg:phone":"+1 716 632 4573",
    "sg:postcode":"14225",
    "sg:province":"NY",
    "sg:tags":[
        "american"
    ],
    "wof:name":"Dibella's Submarines",
    "wof:placetype":"venue"
},
  "geometry": {"coordinates":[-78.754352,42.920971],"type":"Point"}
}