{
  "type": "Feature",
  "properties": {
    "iso:country":"US",
    "sg:address":"47 Briar Ave",
    "sg:city":"Albany",
    "sg:classifiers":[
        {
            "category":"Building & Trades",
            "subcategory":"Construction",
            "type":"Services"
        }
    ],
    "sg:phone":"+1 518 438 5860",
    "sg:postcode":"12203",
    "sg:province":"NY",
    "sg:tags":[
        "concrete",
        "contractor"
    ],
    "wof:name":"Pauls Poured Walls",
    "wof:placetype":"venue"
},
  "geometry": {"coordinates":[-73.822914,42.665839],"type":"Point"}
}