{
  "type": "Feature",
  "properties": {
    "iso:country":"US",
    "sg:address":"6816 Fort Hamilton Parkway",
    "sg:city":"Brooklyn",
    "sg:classifiers":[
        {
            "category":"Coffee & Tea",
            "type":"Food & Drink"
        }
    ],
    "sg:phone":"+1 718 238 3066",
    "sg:postcode":"11219",
    "sg:province":"NY",
    "wof:name":"ABC Cafe",
    "wof:placetype":"venue"
},
  "geometry": {"coordinates":[-74.01154,40.62908],"type":"Point"}
}