{
  "type": "Feature",
  "properties": {
    "addr:full":"1051 Liberty Ave Brooklyn NY 11208",
    "addr:housenumber":"1051",
    "addr:postcode":"11208",
    "addr:street":"Liberty Ave",
    "iso:country":"US",
    "sg:address":"1051 Liberty Ave",
    "sg:city":"Brooklyn",
    "sg:classifiers":[
        {
            "category":"Home & Garden",
            "subcategory":"Furniture",
            "type":"Retail Goods"
        }
    ],
    "sg:phone":"+1   ",
    "sg:postcode":"11208",
    "sg:province":"NY",
    "wof:name":"Silaco Furniture Corp",
    "wof:placetype":"venue"
},
  "geometry": {"coordinates":[-73.870019,40.678344],"type":"Point"}
}