{
  "type": "Feature",
  "properties": {
    "iso:country":"US",
    "sg:address":"624 Titus Ave",
    "sg:city":"Rochester",
    "sg:classifiers":[
        {
            "category":"Health Services",
            "subcategory":"Chiropractor",
            "type":"Services"
        }
    ],
    "sg:phone":"+1 585 266 2440",
    "sg:postcode":"14617",
    "sg:province":"NY",
    "sg:tags":[
        "chiropractic"
    ],
    "wof:name":"Bag Pipes",
    "wof:placetype":"venue"
},
  "geometry": {"coordinates":[-77.59974099999999,43.210631],"type":"Point"}
}