{
  "type": "Feature",
  "properties": {
    "addr:full":"48 Mac Dougal St New York NY 10012",
    "addr:housenumber":"48",
    "addr:postcode":"10012",
    "addr:street":"Mac Dougal St",
    "iso:country":"US",
    "sg:address":"48 Mac Dougal St",
    "sg:city":"New York",
    "sg:classifiers":[
        {
            "category":"Restaurant",
            "type":"Food & Drink"
        }
    ],
    "sg:phone":"+1 212 358 1707",
    "sg:postcode":"10012",
    "sg:province":"NY",
    "wof:name":"AMA Restaurant",
    "wof:placetype":"venue"
},
  "geometry": {"coordinates":[-74.002128,40.727928],"type":"Point"}
}