{
  "type": "Feature",
  "properties": {
    "addr:full":"6401 Jericho Tpke Commack NY 11725",
    "addr:housenumber":"6401",
    "addr:postcode":"11725",
    "addr:street":"Jericho Tpke",
    "iso:country":"US",
    "sg:address":"6401 Jericho Tpke",
    "sg:city":"Commack",
    "sg:classifiers":[
        {
            "category":"Ice Cream",
            "type":"Food & Drink"
        }
    ],
    "sg:menulink":"http://www.allmenus.com/ny/huntington/230237-marble-slab-creamery/menu/",
    "sg:postcode":"11725",
    "sg:province":"NY",
    "sg:tags":[
        "american"
    ],
    "wof:name":"Marble Slab Creamery",
    "wof:placetype":"venue"
},
  "geometry": {"coordinates":[-73.294068,40.843137],"type":"Point"}
}