{
  "type": "Feature",
  "properties": {
    "addr:full":"1121 E 96th St Brooklyn NY 11236",
    "addr:housenumber":"1121",
    "addr:postcode":"11236",
    "addr:street":"E 96Th St",
    "iso:country":"US",
    "sg:address":"1121 E 96th St",
    "sg:city":"Brooklyn",
    "sg:classifiers":[
        {
            "category":"Social Services",
            "subcategory":"Adult Care",
            "type":"Services"
        }
    ],
    "sg:phone":"+1 718 272 9101",
    "sg:postcode":"11236",
    "sg:province":"NY",
    "sg:tags":[
        "residential"
    ],
    "wof:name":"ARC",
    "wof:placetype":"venue"
},
  "geometry": {"coordinates":[-73.901449,40.643242],"type":"Point"}
}