{
  "type": "Feature",
  "properties": {
    "addr:full":"444 E 52 St New York NY 10022",
    "addr:housenumber":"444;52",
    "addr:postcode":"10022",
    "addr:street":"E;St",
    "iso:country":"US",
    "sg:address":"444 E 52 St",
    "sg:city":"New York",
    "sg:classifiers":[
        {
            "category":"Communications",
            "subcategory":"Film & Video Production",
            "type":"Services"
        }
    ],
    "sg:phone":"+1 212 308 7777",
    "sg:postcode":"10022",
    "sg:province":"NY",
    "sg:tags":[
        "motion"
    ],
    "wof:name":"Caribbean Pictures Ltd",
    "wof:placetype":"venue"
},
  "geometry": {"coordinates":[-73.964637,40.754923],"type":"Point"}
}