{
  "type": "Feature",
  "properties": {
    "addr:full":"82 Lightwood Ln Rochester NY 14606",
    "addr:housenumber":"82",
    "addr:postcode":"14606",
    "addr:street":"Lightwood Ln",
    "iso:country":"US",
    "sg:address":"82 Lightwood Ln",
    "sg:city":"Rochester",
    "sg:classifiers":[
        {
            "category":"Building & Trades",
            "subcategory":"Cleaning & Sanitation",
            "type":"Services"
        }
    ],
    "sg:phone":"+1 585 426 4760",
    "sg:postcode":"14606",
    "sg:province":"NY",
    "sg:tags":[
        "janitor",
        "maintenance"
    ],
    "wof:name":"Pinu Janitorial Services Inc",
    "wof:placetype":"venue"
},
  "geometry": {"coordinates":[-77.715037,43.176926],"type":"Point"}
}