{
  "type": "Feature",
  "properties": {
    "addr:full":"5012 49th St Woodside NY 11377",
    "addr:housenumber":"5012",
    "addr:postcode":"11377",
    "addr:street":"49Th St",
    "iso:country":"US",
    "sg:address":"5012 49th St",
    "sg:city":"Woodside",
    "sg:classifiers":[
        {
            "category":"Retail",
            "subcategory":"Auto Repair",
            "type":"Services"
        }
    ],
    "sg:phone":"+1 800 479 9339",
    "sg:postcode":"11377",
    "sg:province":"NY",
    "wof:name":"Comex Auto Repair",
    "wof:placetype":"venue"
},
  "geometry": {"coordinates":[-73.91736,40.736693],"type":"Point"}
}