{
  "type": "Feature",
  "properties": {
    "addr:full":"44 Sage Rd Waterford NY 12188",
    "addr:housenumber":"44",
    "addr:postcode":"12188",
    "addr:street":"Sage Rd",
    "iso:country":"US",
    "sg:address":"44 Sage Rd",
    "sg:city":"Waterford",
    "sg:classifiers":[
        {
            "category":"Building & Trades",
            "subcategory":"Construction",
            "type":"Services"
        }
    ],
    "sg:phone":"+1 518 233 8097",
    "sg:postcode":"12188",
    "sg:province":"NY",
    "sg:tags":[
        "house"
    ],
    "wof:name":"Campbell Construction",
    "wof:placetype":"venue"
},
  "geometry": {"coordinates":[-73.69002,42.813064],"type":"Point"}
}