{
  "type": "Feature",
  "properties": {
    "addr:full":"22 Saw Mill River Rd Hawthorne NY 10532",
    "addr:housenumber":"22",
    "addr:postcode":"mill;10532",
    "addr:street":"Saw;River Rd",
    "iso:country":"US",
    "sg:address":"22 Saw Mill River Rd",
    "sg:city":"Hawthorne",
    "sg:classifiers":[
        {
            "category":"Professional",
            "subcategory":"Lawyer & Legal Services",
            "type":"Services"
        }
    ],
    "sg:phone":"+1 914 347 2300",
    "sg:postcode":"10532",
    "sg:province":"NY",
    "wof:name":"Maiocchi Anthony Atty",
    "wof:placetype":"venue"
},
  "geometry": {"coordinates":[-73.8172,41.093201],"type":"Point"}
}