{
  "type": "Feature",
  "properties": {
    "addr:full":"610 Oxford St Westbury NY 11590",
    "addr:housenumber":"610",
    "addr:postcode":"11590",
    "addr:street":"Oxford St",
    "iso:country":"US",
    "sg:address":"610 Oxford St",
    "sg:city":"Westbury",
    "sg:classifiers":[
        {
            "category":"Health Services",
            "subcategory":"Doctor",
            "type":"Services"
        }
    ],
    "sg:phone":"+1 516 997 4610",
    "sg:postcode":"11590",
    "sg:province":"NY",
    "sg:tags":[
        "medical"
    ],
    "wof:name":"Persaud Ronald G",
    "wof:placetype":"venue"
},
  "geometry": {"coordinates":[-73.57471,40.763974],"type":"Point"}
}