{
  "type": "Feature",
  "properties": {
    "addr:full":"393 Sunrise Hwy Ste B Lynbrook NY 11563",
    "addr:housenumber":"393",
    "addr:postcode":"11563",
    "addr:street":"Sunrise Hwy Ste B",
    "iso:country":"US",
    "sg:address":"393 Sunrise Hwy Ste B",
    "sg:city":"Lynbrook",
    "sg:classifiers":[
        {
            "category":"Retail",
            "subcategory":"Repair Shop",
            "type":"Services"
        },
        {
            "category":"Shopping",
            "subcategory":"Crafts & Fabrics",
            "type":"Retail Goods"
        }
    ],
    "sg:phone":"+1 516 596 9205",
    "sg:postcode":"11563",
    "sg:province":"NY",
    "sg:tags":[
        "reupholstery",
        "store",
        "furniture"
    ],
    "wof:name":"David's Fabric & Trim",
    "wof:placetype":"venue"
},
  "geometry": {"coordinates":[-73.671402,40.6549],"type":"Point"}
}