{
  "type": "Feature",
  "properties": {
    "addr:full":"269 W 23rd St New York NY 10011",
    "addr:housenumber":"269",
    "addr:postcode":"10011",
    "addr:street":"W 23Rd St",
    "iso:country":"US",
    "sg:address":"269 W 23rd St",
    "sg:city":"New York",
    "sg:classifiers":[
        {
            "category":"Restaurant",
            "type":"Food & Drink"
        }
    ],
    "sg:phone":"+1 646 486 4441",
    "sg:postcode":"10011",
    "sg:province":"NY",
    "sg:website":"www.gudtfood.com",
    "wof:name":"F & B Gudt Food Restaurant",
    "wof:placetype":"venue"
},
  "geometry": {"coordinates":[-73.996956,40.74453],"type":"Point"}
}