{
  "type": "Feature",
  "properties": {
    "iso:country":"US",
    "sg:address":"2404 Watson Blvd",
    "sg:city":"Endicott",
    "sg:classifiers":[
        {
            "category":"Professional",
            "subcategory":"Management & Consulting",
            "type":"Services"
        }
    ],
    "sg:phone":"+1 607 754 5770",
    "sg:postcode":"13760",
    "sg:province":"NY",
    "sg:tags":[
        "environmental"
    ],
    "wof:name":"Walter B Satterthwaite Assoc",
    "wof:placetype":"venue"
},
  "geometry": {"coordinates":[-76.03586,42.109642],"type":"Point"}
}