{
  "type": "Feature",
  "properties": {
    "iso:country":"US",
    "sg:address":"20 N Broadway",
    "sg:city":"White Plains",
    "sg:classifiers":[
        {
            "category":"Shopping",
            "subcategory":"Used Merchandise",
            "type":"Retail Goods"
        }
    ],
    "sg:phone":"+1   ",
    "sg:postcode":"10601",
    "sg:province":"NY",
    "wof:name":"Jacqueline Graber Antiques",
    "wof:placetype":"venue"
},
  "geometry": {"coordinates":[-73.762821,41.034155],"type":"Point"}
}