{
  "type": "Feature",
  "properties": {
    "iso:country":"US",
    "sg:address":"23 Floral Ave",
    "sg:city":"Binghamton",
    "sg:classifiers":[
        {
            "category":"Food & Beverages",
            "subcategory":"Groceries & Convenience Stores",
            "type":"Retail Goods"
        }
    ],
    "sg:phone":"+1 607 798 0263",
    "sg:postcode":"13905",
    "sg:province":"NY",
    "wof:name":"Red Apple",
    "wof:placetype":"venue"
},
  "geometry": {"coordinates":[-75.94525299999999,42.110899],"type":"Point"}
}