{
  "type": "Feature",
  "properties": {
    "addr:full":"14338 37th Ave Flushing NY 11354",
    "addr:housenumber":"14338",
    "addr:postcode":"11354",
    "addr:street":"37Th Ave",
    "iso:country":"US",
    "sg:address":"14338 37th Ave",
    "sg:city":"Flushing",
    "sg:classifiers":[
        {
            "category":"Education",
            "subcategory":"School",
            "type":"Public Place"
        }
    ],
    "sg:phone":"+1 718 886 5240",
    "sg:postcode":"11354",
    "sg:province":"NY",
    "wof:name":"Global English Academy",
    "wof:placetype":"venue"
},
  "geometry": {"coordinates":[-73.82389499999999,40.7633],"type":"Point"}
}