{
  "type": "Feature",
  "properties": {
    "iso:country":"US",
    "sg:address":"891 W Jericho Tpke",
    "sg:city":"Smithtown",
    "sg:classifiers":[
        {
            "category":"Retail",
            "subcategory":"Veterinary Services",
            "type":"Services"
        }
    ],
    "sg:phone":"+1 631 543 0333",
    "sg:postcode":"11787",
    "sg:province":"NY",
    "sg:tags":[
        "veterinarian"
    ],
    "wof:name":"Kaplan Scott DVM",
    "wof:placetype":"venue"
},
  "geometry": {"coordinates":[-73.2444,40.848099],"type":"Point"}
}