{
  "type": "Feature",
  "properties": {
    "iso:country":"US",
    "sg:address":"23 Gravel Hill Rd",
    "sg:city":"Hampton Bays",
    "sg:classifiers":[
        {
            "category":"Building & Trades",
            "subcategory":"Construction",
            "type":"Services"
        }
    ],
    "sg:phone":"+1 631 728 1529",
    "sg:postcode":"11946",
    "sg:province":"NY",
    "sg:tags":[
        "contractor"
    ],
    "wof:name":"Oscar Vasquez General Contr",
    "wof:placetype":"venue"
},
  "geometry": {"coordinates":[-72.510654,40.879509],"type":"Point"}
}