{
  "type": "Feature",
  "properties": {
    "iso:country":"US",
    "sg:address":"440 E 75 St",
    "sg:city":"New York",
    "sg:classifiers":[
        {
            "category":"Wholesale",
            "subcategory":"Medical Equipment & Supplies",
            "type":"Manufacturing & Wholesale Goods"
        },
        {
            "category":"Shopping",
            "subcategory":"Beauty & Cosmetics",
            "type":"Retail Goods"
        }
    ],
    "sg:phone":"+1 212 772 9680",
    "sg:postcode":"10021",
    "sg:province":"NY",
    "sg:tags":[
        "instrument",
        "surgical",
        "appliance",
        "pharmaceutical"
    ],
    "wof:name":"Harold Ellis Drugs & Surgicals",
    "wof:placetype":"venue"
},
  "geometry": {"coordinates":[-73.953053,40.769128],"type":"Point"}
}