{
  "type": "Feature",
  "properties": {
    "addr:full":"1615 Avenue U Brooklyn NY 11229",
    "addr:housenumber":"1615",
    "addr:postcode":"11229",
    "addr:street":"Avenue U",
    "iso:country":"US",
    "sg:address":"1615 Avenue U",
    "sg:city":"Brooklyn",
    "sg:classifiers":[
        {
            "category":"Restaurant",
            "type":"Food & Drink"
        }
    ],
    "sg:menulink":"http://www.allmenus.com/ny/brooklyn/62075-luigis/menu/",
    "sg:phone":"+1 718 382 9100",
    "sg:postcode":"11229",
    "sg:province":"NY",
    "sg:tags":[
        "american",
        "pizza"
    ],
    "wof:name":"Luigi's",
    "wof:placetype":"venue"
},
  "geometry": {"coordinates":[-73.955375,40.598917],"type":"Point"}
}