{
  "type": "Feature",
  "properties": {
    "addr:full":"1526 49th St Brooklyn NY 11219",
    "addr:housenumber":"1526",
    "addr:postcode":"11219",
    "addr:street":"49Th St",
    "iso:country":"US",
    "sg:address":"1526 49th St",
    "sg:city":"Brooklyn",
    "sg:classifiers":[
        {
            "category":"Building & Trades",
            "subcategory":"Construction",
            "type":"Services"
        }
    ],
    "sg:phone":"+1 718 851 4726",
    "sg:postcode":"11219",
    "sg:province":"NY",
    "sg:tags":[
        "house"
    ],
    "wof:name":"Rychik Design & Construction",
    "wof:placetype":"venue"
},
  "geometry": {"coordinates":[-73.98599900000001,40.631332],"type":"Point"}
}