{
  "type": "Feature",
  "properties": {
    "addr:full":"1665 Ridge Rd E Rochester NY 14621",
    "addr:housenumber":"1665",
    "addr:postcode":"14621",
    "addr:street":"Ridge Rd E",
    "iso:country":"US",
    "sg:address":"1665 Ridge Rd E",
    "sg:city":"Rochester",
    "sg:classifiers":[
        {
            "category":"Insurance",
            "subcategory":"Insurance Agent",
            "type":"Services"
        }
    ],
    "sg:phone":"+1 585 473 4130",
    "sg:postcode":"14621",
    "sg:province":"NY",
    "wof:name":"Pucci Insurance Consultants",
    "wof:placetype":"venue"
},
  "geometry": {"coordinates":[-77.57163,43.200575],"type":"Point"}
}