{
  "type": "Feature",
  "properties": {
    "addr:full":"320 E Boston Post Rd Mamaroneck NY 10543",
    "addr:housenumber":"320",
    "addr:postcode":"10543",
    "addr:street":"E Boston Post Rd",
    "iso:country":"US",
    "sg:address":"320 E Boston Post Rd",
    "sg:city":"Mamaroneck",
    "sg:classifiers":[
        {
            "category":"Organizations",
            "subcategory":"Religious Organization",
            "type":"Services"
        }
    ],
    "sg:phone":"+1   ",
    "sg:postcode":"10543",
    "sg:province":"NY",
    "wof:name":"Holy Trinity Church",
    "wof:placetype":"venue"
},
  "geometry": {"coordinates":[-73.730828,40.950011],"type":"Point"}
}