{
  "type": "Feature",
  "properties": {
    "addr:full":"62 Mill St Phelps NY 14532",
    "addr:housenumber":"62",
    "addr:postcode":"14532",
    "addr:street":"Mill St",
    "iso:country":"US",
    "sg:address":"62 Mill St",
    "sg:city":"Phelps",
    "sg:classifiers":[
        {
            "category":"Government",
            "subcategory":"Office",
            "type":"Public Place"
        }
    ],
    "sg:phone":"+1 315 548 8003",
    "sg:postcode":"14532",
    "sg:province":"NY",
    "sg:tags":[
        "village"
    ],
    "wof:name":"Phelps Village Barn",
    "wof:placetype":"venue"
},
  "geometry": {"coordinates":[-77.05762,42.963515],"type":"Point"}
}