{
  "type": "Feature",
  "properties": {
    "iso:country":"US",
    "sg:address":"4607 48th Avenue",
    "sg:city":"Woodside",
    "sg:classifiers":[
        {
            "category":"Shopping",
            "subcategory":"Computers & Home Electronics",
            "type":"Retail Goods"
        },
        {
            "category":"Communications",
            "subcategory":"Television Station",
            "type":"Services"
        }
    ],
    "sg:phone":"+1 718 371 4567",
    "sg:postcode":"11377",
    "sg:province":"NY",
    "sg:tags":[
        "repair",
        "satellite",
        "cable",
        "tv",
        "system",
        "equipment"
    ],
    "wof:name":"Continental Satellite",
    "wof:placetype":"venue"
},
  "geometry": {"coordinates":[-73.91940700000001,40.739322],"type":"Point"}
}