{
  "type": "Feature",
  "properties": {
    "iso:country":"US",
    "sg:address":"9 Northwood Ln",
    "sg:city":"Patchogue",
    "sg:classifiers":[
        {
            "category":"Real Estate",
            "subcategory":"Real Estate Services",
            "type":"Services"
        },
        {
            "category":"Real Estate",
            "subcategory":"Real Estate Agent",
            "type":"Services"
        }
    ],
    "sg:phone":"+1 631 475 1800",
    "sg:postcode":"11772",
    "sg:province":"NY",
    "sg:tags":[
        "management"
    ],
    "wof:name":"Metro House Constructors",
    "wof:placetype":"venue"
},
  "geometry": {"coordinates":[-73.033382,40.762842],"type":"Point"}
}