{
  "type": "Feature",
  "properties": {
    "addr:full":"117 Oliver Ave Yonkers NY 10701",
    "addr:housenumber":"117",
    "addr:postcode":"10701",
    "addr:street":"Oliver Ave",
    "iso:country":"US",
    "sg:address":"117 Oliver Ave",
    "sg:city":"Yonkers",
    "sg:classifiers":[
        {
            "category":"Taxi",
            "type":"Transportation"
        }
    ],
    "sg:phone":"+1 914 969 0167",
    "sg:postcode":"10701",
    "sg:province":"NY",
    "sg:tags":[
        "delivery"
    ],
    "wof:name":"F's Delivery",
    "wof:placetype":"venue"
},
  "geometry": {"coordinates":[-73.887117,40.933352],"type":"Point"}
}