{
  "type": "Feature",
  "properties": {
    "addr:full":"69-02 Roosevelt Avenue Queens NY 11377",
    "addr:housenumber":"69-02",
    "addr:postcode":"11377",
    "addr:street":"Roosevelt Avenue",
    "iso:country":"US",
    "sg:address":"69-02 Roosevelt Avenue",
    "sg:city":"Queens",
    "sg:classifiers":[
        {
            "category":"Restaurant",
            "type":"Food & Drink"
        },
        {
            "category":"Bakery",
            "type":"Food & Drink"
        }
    ],
    "sg:phone":"+1 718 898 1900",
    "sg:postcode":"11377",
    "sg:province":"NY",
    "sg:tags":[
        "filipino"
    ],
    "wof:name":"Krystal's Pastry Shop",
    "wof:placetype":"venue"
},
  "geometry": {"coordinates":[-73.89609900000001,40.746136],"type":"Point"}
}