{
  "type": "Feature",
  "properties": {
    "addr:full":"659 Mason St Westbury NY 11590",
    "addr:housenumber":"659",
    "addr:postcode":"11590",
    "addr:street":"Mason St",
    "iso:country":"US",
    "sg:address":"659 Mason St",
    "sg:city":"Westbury",
    "sg:classifiers":[
        {
            "category":"Building & Trades",
            "subcategory":"Landscaping Services",
            "type":"Services"
        }
    ],
    "sg:phone":"+1 516 876 8471",
    "sg:postcode":"11590",
    "sg:province":"NY",
    "wof:name":"Ep Tree Services",
    "wof:placetype":"venue"
},
  "geometry": {"coordinates":[-73.57275799999999,40.751624],"type":"Point"}
}