{
  "type": "Feature",
  "properties": {
    "iso:country":"US",
    "sg:address":"4274 Lakeville Rd",
    "sg:city":"Geneseo",
    "sg:classifiers":[
        {
            "category":"Restaurant",
            "type":"Food & Drink"
        }
    ],
    "sg:phone":"+1 585 243 9609",
    "sg:postcode":"14454",
    "sg:province":"NY",
    "wof:name":"Oriental Taste",
    "wof:placetype":"venue"
},
  "geometry": {"coordinates":[-77.787963,42.797242],"type":"Point"}
}