{
  "type": "Feature",
  "properties": {
    "iso:country":"US",
    "sg:address":"11 Renee Ln",
    "sg:city":"Nanuet",
    "sg:classifiers":[
        {
            "category":"Government",
            "subcategory":"Fire Station",
            "type":"Public Place"
        }
    ],
    "sg:phone":"+1 845 624 1306",
    "sg:postcode":"10954",
    "sg:province":"NY",
    "sg:tags":[
        "department"
    ],
    "wof:name":"Bardonia Substation",
    "wof:placetype":"venue"
},
  "geometry": {"coordinates":[-73.99218500000001,41.107515],"type":"Point"}
}