{
  "type": "Feature",
  "properties": {
    "iso:country":"US",
    "sg:address":"13 Technology Dr",
    "sg:city":"Stony Brook",
    "sg:classifiers":[
        {
            "category":"Education",
            "subcategory":"School",
            "type":"Public Place"
        }
    ],
    "sg:phone":"+1 631 632 9150",
    "sg:postcode":"11733",
    "sg:province":"NY",
    "sg:tags":[
        "educational",
        "administrative"
    ],
    "wof:name":"State Univ NY At Stony Brook",
    "wof:placetype":"venue"
},
  "geometry": {"coordinates":[-73.086557,40.89869],"type":"Point"}
}