{
  "type": "Feature",
  "properties": {
    "addr:full":"1340 Lincoln Ave Holbrook NY 11741",
    "addr:housenumber":"1340",
    "addr:postcode":"11741",
    "addr:street":"Lincoln Ave",
    "iso:country":"US",
    "sg:address":"1340 Lincoln Ave",
    "sg:city":"Holbrook",
    "sg:classifiers":[
        {
            "category":"Professional",
            "subcategory":"Engineering",
            "type":"Services"
        }
    ],
    "sg:phone":"+1 631 737 2803",
    "sg:postcode":"11741",
    "sg:province":"NY",
    "sg:tags":[
        "consultant"
    ],
    "wof:name":"L G Hellmann Corporation",
    "wof:placetype":"venue"
},
  "geometry": {"coordinates":[-73.084017,40.779484],"type":"Point"}
}