{
  "type": "Feature",
  "properties": {
    "addr:full":"355 S Main St Albion NY 14411",
    "addr:housenumber":"355",
    "addr:postcode":"14411",
    "addr:street":"S Main St",
    "iso:country":"US",
    "sg:address":"355 S Main St",
    "sg:city":"Albion",
    "sg:classifiers":[
        {
            "category":"Social Services",
            "subcategory":"Adult Care",
            "type":"Services"
        }
    ],
    "sg:phone":"+1 585 589 7832",
    "sg:postcode":"14411",
    "sg:province":"NY",
    "sg:tags":[
        "residential"
    ],
    "wof:name":"Clover Hill Adult Residence",
    "wof:placetype":"venue"
},
  "geometry": {"coordinates":[-78.19391,43.235988],"type":"Point"}
}