{
  "type": "Feature",
  "properties": {
    "addr:full":"720 East Ave Rochester NY 14607",
    "addr:housenumber":"720",
    "addr:postcode":"14607",
    "addr:street":"East Ave",
    "iso:country":"US",
    "sg:address":"720 East Ave",
    "sg:city":"Rochester",
    "sg:classifiers":[
        {
            "category":"Health Services",
            "subcategory":"Doctor",
            "type":"Services"
        }
    ],
    "sg:phone":"+1   ",
    "sg:postcode":"14607",
    "sg:province":"NY",
    "sg:tags":[
        "medical"
    ],
    "wof:name":"Hobart A Lener MD PC",
    "wof:placetype":"venue"
},
  "geometry": {"coordinates":[-77.586388,43.153225],"type":"Point"}
}