{
  "type": "Feature",
  "properties": {
    "iso:country":"US",
    "sg:address":"58 Main St",
    "sg:city":"New Paltz",
    "sg:classifiers":[
        {
            "category":"Bars & Pubs",
            "type":"Food & Drink"
        }
    ],
    "sg:phone":"+1 845 255 3400",
    "sg:postcode":"12561",
    "sg:province":"NY",
    "wof:name":"Cabaloosa",
    "wof:placetype":"venue"
},
  "geometry": {"coordinates":[-74.08644099999999,41.747568],"type":"Point"}
}