{
  "type": "Feature",
  "properties": {
    "addr:full":"46 Railroad St Huntington Station NY 11746",
    "addr:housenumber":"46",
    "addr:postcode":"11746",
    "addr:street":"Railroad St",
    "iso:country":"US",
    "sg:address":"46 Railroad St",
    "sg:city":"Huntington Station",
    "sg:classifiers":[
        {
            "category":"Personal",
            "type":"Services"
        }
    ],
    "sg:phone":"+1 631 424 3976",
    "sg:postcode":"11746",
    "sg:province":"NY",
    "sg:tags":[
        "mover"
    ],
    "wof:name":"Go Mini's",
    "wof:placetype":"venue"
},
  "geometry": {"coordinates":[-73.416121,40.849929],"type":"Point"}
}