{
  "type": "Feature",
  "properties": {
    "addr:full":"220 Nagle Avenue New York NY 10034",
    "addr:housenumber":"220",
    "addr:postcode":"10034",
    "addr:street":"Nagle Avenue",
    "iso:country":"US",
    "sg:address":"220 Nagle Avenue",
    "sg:city":"New York",
    "sg:classifiers":[
        {
            "category":"Restaurant",
            "type":"Food & Drink"
        }
    ],
    "sg:phone":"+1 212 304 1035",
    "sg:postcode":"10034",
    "sg:province":"NY",
    "sg:tags":[
        "pizza"
    ],
    "wof:name":"M I New Millennium Rest",
    "wof:placetype":"venue"
},
  "geometry": {"coordinates":[-73.92413500000001,40.86175],"type":"Point"}
}