{
  "type": "Feature",
  "properties": {
    "addr:full":"430 Graham Ave Brooklyn NY 11211",
    "addr:housenumber":"430",
    "addr:postcode":"ave;11211",
    "addr:street":"Graham",
    "iso:country":"US",
    "sg:address":"430 Graham Ave",
    "sg:city":"Brooklyn",
    "sg:classifiers":[
        {
            "category":"Real Estate",
            "subcategory":"Real Estate Agent",
            "type":"Services"
        }
    ],
    "sg:phone":"+1 718 389 3255",
    "sg:postcode":"11211",
    "sg:province":"NY",
    "wof:name":"Tat Realtor Corp",
    "wof:placetype":"venue"
},
  "geometry": {"coordinates":[-73.944833,40.717603],"type":"Point"}
}