{
  "type": "Feature",
  "properties": {
    "addr:full":"600 Ridge Rd W Rochester NY 14615",
    "addr:housenumber":"600",
    "addr:postcode":"14615",
    "addr:street":"Ridge Rd W",
    "iso:country":"US",
    "sg:address":"600 Ridge Rd W",
    "sg:city":"Rochester",
    "sg:classifiers":[
        {
            "category":"Restaurant",
            "type":"Food & Drink"
        }
    ],
    "sg:menulink":"http://www.allmenus.com/ny/rochester/208252-taco-bell/menu/",
    "sg:phone":"+1 585 865 5094",
    "sg:postcode":"14615",
    "sg:province":"NY",
    "sg:tags":[
        "mexican"
    ],
    "wof:name":"Taco Bell",
    "wof:placetype":"venue"
},
  "geometry": {"coordinates":[-77.64295300000001,43.202412],"type":"Point"}
}