{
  "type": "Feature",
  "properties": {
    "addr:full":"612 Woodward Ave Ridgewood NY 11385",
    "addr:housenumber":"612",
    "addr:postcode":"11385",
    "addr:street":"Woodward Ave",
    "iso:country":"US",
    "sg:address":"612 Woodward Ave",
    "sg:city":"Ridgewood",
    "sg:classifiers":[
        {
            "category":"Place Of Worship",
            "subcategory":"Church",
            "type":"Public Place"
        },
        {
            "category":"Place Of Worship",
            "type":"Public Place"
        }
    ],
    "sg:phone":"+1 718 497 1136",
    "sg:postcode":"11385",
    "sg:province":"NY",
    "sg:tags":[
        "churches-non-denominational"
    ],
    "wof:name":"House Of Worship Christian Chu",
    "wof:placetype":"venue"
},
  "geometry": {"coordinates":[-73.907676,40.706042],"type":"Point"}
}