{
  "type": "Feature",
  "properties": {
    "addr:full":"9406 59th Ave Elmhurst NY 11373",
    "addr:housenumber":"9406",
    "addr:postcode":"11373",
    "addr:street":"59Th Ave",
    "iso:country":"US",
    "sg:address":"9406 59th Ave",
    "sg:city":"Elmhurst",
    "sg:classifiers":[
        {
            "category":"Health Services",
            "subcategory":"Doctor",
            "type":"Services"
        }
    ],
    "sg:phone":"+1 718 699 9737",
    "sg:postcode":"11373",
    "sg:province":"NY",
    "wof:name":"Gorski John MD",
    "wof:placetype":"venue"
},
  "geometry": {"coordinates":[-73.86660000000001,40.734798],"type":"Point"}
}