{
  "type": "Feature",
  "properties": {
    "iso:country":"US",
    "sg:address":"51 Page Ave",
    "sg:city":"Staten Island",
    "sg:classifiers":[
        {
            "category":"Personal",
            "subcategory":"Barber",
            "type":"Services"
        }
    ],
    "sg:phone":"+1   ",
    "sg:postcode":"10309",
    "sg:province":"NY",
    "sg:tags":[
        "shop"
    ],
    "wof:name":"French Twist",
    "wof:placetype":"venue"
},
  "geometry": {"coordinates":[-74.234971,40.521799],"type":"Point"}
}