{
  "type": "Feature",
  "properties": {
    "addr:full":"425 W 59th Street New York NY 10019",
    "addr:housenumber":"425",
    "addr:postcode":"10019",
    "addr:street":"W 59Th Street",
    "iso:country":"US",
    "sg:address":"425 W 59th Street",
    "sg:city":"New York",
    "sg:classifiers":[
        {
            "category":"Health Services",
            "subcategory":"Doctor",
            "type":"Services"
        }
    ],
    "sg:phone":"+1 212 492 5500",
    "sg:postcode":"10019",
    "sg:province":"NY",
    "wof:name":"Shah-Mehta Bijal MD",
    "wof:placetype":"venue"
},
  "geometry": {"coordinates":[-73.986728,40.769918],"type":"Point"}
}