{
  "type": "Feature",
  "properties": {
    "addr:full":"169 State Hwy 17K Newburgh NY 12575",
    "addr:housenumber":"169",
    "addr:postcode":"12575",
    "addr:street":"State Hwy 17K",
    "iso:country":"US",
    "sg:address":"169 State Hwy 17K",
    "sg:city":"Newburgh",
    "sg:classifiers":[
        {
            "category":"Building & Trades",
            "subcategory":"Electrical",
            "type":"Services"
        }
    ],
    "sg:phone":"+1 845 567 7400",
    "sg:postcode":"12575",
    "sg:province":"NY",
    "sg:tags":[
        "electric",
        "contractor"
    ],
    "wof:name":"General Electric Corporate Air",
    "wof:placetype":"venue"
},
  "geometry": {"coordinates":[-74.09505299999999,41.510878],"type":"Point"}
}