{
  "type": "Feature",
  "properties": {
    "iso:country":"US",
    "sg:address":"1476 White Plains Rd",
    "sg:city":"Bronx",
    "sg:classifiers":[
        {
            "category":"Retail",
            "subcategory":"Repair Shop",
            "type":"Services"
        }
    ],
    "sg:phone":"+1 347 293 0427",
    "sg:postcode":"10462",
    "sg:province":"NY",
    "sg:tags":[
        "lock",
        "locksmith"
    ],
    "wof:name":"USA Locksmiths",
    "wof:placetype":"venue"
},
  "geometry": {"coordinates":[-73.863246,40.836064],"type":"Point"}
}