{
  "type": "Feature",
  "properties": {
    "iso:country":"US",
    "sg:address":"133 Wolf Rd",
    "sg:city":"Albany",
    "sg:classifiers":[
        {
            "category":"Retail",
            "subcategory":"Laundry & Dry Cleaning",
            "type":"Services"
        }
    ],
    "sg:phone":"+1 518 482 4768",
    "sg:postcode":"12205",
    "sg:province":"NY",
    "sg:tags":[
        "cleaners",
        "rug",
        "carpet"
    ],
    "wof:name":"Richardson Rug & Carpet Clnrs",
    "wof:placetype":"venue"
},
  "geometry": {"coordinates":[-73.806629,42.718338],"type":"Point"}
}