{
  "type": "Feature",
  "properties": {
    "addr:full":"244 E 32 St New York NY 10016",
    "addr:housenumber":"244;32",
    "addr:postcode":"10016",
    "addr:street":"E;St",
    "iso:country":"US",
    "sg:address":"244 E 32 St",
    "sg:city":"New York",
    "sg:classifiers":[
        {
            "category":"Building & Trades",
            "subcategory":"Cleaning & Sanitation",
            "type":"Services"
        }
    ],
    "sg:phone":"+1 212 951 7300",
    "sg:postcode":"10016",
    "sg:province":"NY",
    "sg:tags":[
        "property",
        "maintenance"
    ],
    "wof:name":"244 LLC",
    "wof:placetype":"venue"
},
  "geometry": {"coordinates":[-73.977576,40.743843],"type":"Point"}
}