{
  "type": "Feature",
  "properties": {
    "iso:country":"US",
    "sg:address":"185 E 85th St",
    "sg:city":"New York",
    "sg:classifiers":[
        {
            "category":"Professional",
            "subcategory":"Computer Services",
            "type":"Services"
        }
    ],
    "sg:phone":"+1 212 427 0014",
    "sg:postcode":"10028",
    "sg:province":"NY",
    "sg:tags":[
        "software",
        "integration",
        "reseller",
        "developer"
    ],
    "wof:name":"M D M",
    "wof:placetype":"venue"
},
  "geometry": {"coordinates":[-73.955354,40.77871],"type":"Point"}
}