{
  "type": "Feature",
  "properties": {
    "addr:full":"660 Broadway New York NY 10012",
    "addr:housenumber":"660",
    "addr:postcode":"10012",
    "addr:street":"Broadway",
    "iso:country":"US",
    "sg:address":"660 Broadway",
    "sg:city":"New York",
    "sg:classifiers":[
        {
            "category":"Professional",
            "type":"Services"
        }
    ],
    "sg:phone":"+1 212 385 4560",
    "sg:postcode":"10012",
    "sg:province":"NY",
    "sg:tags":[
        "establishment"
    ],
    "wof:name":"National Down Syndrome",
    "wof:placetype":"venue"
},
  "geometry": {"coordinates":[-73.995554,40.726623],"type":"Point"}
}