{
  "type": "Feature",
  "properties": {
    "addr:full":"1891 Harte St Baldwin NY 11510",
    "addr:housenumber":"1891",
    "addr:postcode":"11510",
    "addr:street":"Harte St",
    "iso:country":"US",
    "sg:address":"1891 Harte St",
    "sg:city":"Baldwin",
    "sg:classifiers":[
        {
            "category":"Organizations",
            "subcategory":"Membership Organization",
            "type":"Services"
        }
    ],
    "sg:phone":"+1 516 223 5268",
    "sg:postcode":"11510",
    "sg:province":"NY",
    "wof:name":"Steuben Society of America",
    "wof:placetype":"venue"
},
  "geometry": {"coordinates":[-73.61253600000001,40.663405],"type":"Point"}
}