{
  "type": "Feature",
  "properties": {
    "addr:full":"160 Clymer St Brooklyn NY 11211",
    "addr:housenumber":"160",
    "addr:postcode":"11211",
    "addr:street":"Clymer St",
    "iso:country":"US",
    "sg:address":"160 Clymer St",
    "sg:city":"Brooklyn",
    "sg:classifiers":[
        {
            "category":"Organizations",
            "subcategory":"Religious Organization",
            "type":"Services"
        }
    ],
    "sg:phone":"+1 718 782 8636",
    "sg:postcode":"11211",
    "sg:province":"NY",
    "sg:tags":[
        "clergy"
    ],
    "wof:name":"Moses Zupnick",
    "wof:placetype":"venue"
},
  "geometry": {"coordinates":[-73.962413,40.707206],"type":"Point"}
}