{
  "type": "Feature",
  "properties": {
    "iso:country":"US",
    "sg:address":"8377 Brewerton Rd",
    "sg:city":"Cicero",
    "sg:classifiers":[
        {
            "category":"Government",
            "subcategory":"Fire Station",
            "type":"Public Place"
        }
    ],
    "sg:phone":"+1 315 699 7721",
    "sg:postcode":"13039",
    "sg:province":"NY",
    "sg:tags":[
        "protection"
    ],
    "wof:name":"Cicero Fire Dept Station 1",
    "wof:placetype":"venue"
},
  "geometry": {"coordinates":[-76.12299,43.184903],"type":"Point"}
}