{
  "type": "Feature",
  "properties": {
    "addr:full":"204 E 112th St New York NY 10029",
    "addr:housenumber":"204",
    "addr:postcode":"10029",
    "addr:street":"E 112Th St",
    "iso:country":"US",
    "sg:address":"204 E 112th St",
    "sg:city":"New York",
    "sg:classifiers":[
        {
            "category":"Personal",
            "subcategory":"Barber",
            "type":"Services"
        }
    ],
    "sg:phone":"+1 212 410 1812",
    "sg:postcode":"10029",
    "sg:province":"NY",
    "wof:name":"Agustin Barber Shop Unisex",
    "wof:placetype":"venue"
},
  "geometry": {"coordinates":[-73.939736,40.79444],"type":"Point"}
}