{
  "type": "Feature",
  "properties": {
    "addr:full":"700 Cantiague Rock Rd Jericho NY 11753",
    "addr:housenumber":"700",
    "addr:postcode":"11753",
    "addr:street":"Cantiague Rock Rd",
    "iso:country":"US",
    "sg:address":"700 Cantiague Rock Rd",
    "sg:city":"Jericho",
    "sg:classifiers":[
        {
            "category":"Health Services",
            "subcategory":"Clinic",
            "type":"Services"
        }
    ],
    "sg:phone":"+1 516 937 1440",
    "sg:postcode":"11753",
    "sg:province":"NY",
    "sg:tags":[
        "counseling",
        "mental"
    ],
    "wof:name":"Pollak Ira M Dr Psychologist",
    "wof:placetype":"venue"
},
  "geometry": {"coordinates":[-73.55349699999999,40.7784],"type":"Point"}
}