{
  "type": "Feature",
  "properties": {
    "iso:country":"US",
    "sg:address":"18 Sound View Dr",
    "sg:city":"Sag Harbor",
    "sg:classifiers":[
        {
            "category":"Communications",
            "type":"Services"
        }
    ],
    "sg:phone":"+1 631 725 6261",
    "sg:postcode":"11963",
    "sg:province":"NY",
    "wof:name":"Gourvitz Communications",
    "wof:placetype":"venue"
},
  "geometry": {"coordinates":[-72.276149,40.999403],"type":"Point"}
}