{
  "type": "Feature",
  "properties": {
    "iso:country":"US",
    "sg:address":"730 5th Avenue",
    "sg:city":"New York",
    "sg:classifiers":[
        {
            "category":"Shopping",
            "subcategory":"Shoes",
            "type":"Retail Goods"
        }
    ],
    "sg:phone":"+1 212 977 7676",
    "sg:postcode":"10019",
    "sg:province":"NY",
    "sg:tags":[
        "store"
    ],
    "wof:name":"Donna Magli America",
    "wof:placetype":"venue"
},
  "geometry": {"coordinates":[-73.974114,40.762793],"type":"Point"}
}