{
  "type": "Feature",
  "properties": {
    "iso:country":"US",
    "sg:address":"25 W 31 St",
    "sg:city":"New York",
    "sg:classifiers":[
        {
            "category":"Manufacturing",
            "subcategory":"Printing",
            "type":"Manufacturing & Wholesale Goods"
        }
    ],
    "sg:phone":"+1 212 594 5494",
    "sg:postcode":"10001",
    "sg:province":"NY",
    "sg:tags":[
        "printer"
    ],
    "sg:website":"www.mdprepress.com",
    "wof:name":"Miller & Debel Prepress Svc",
    "wof:placetype":"venue"
},
  "geometry": {"coordinates":[-73.987337,40.747079],"type":"Point"}
}