{
  "type": "Feature",
  "properties": {
    "addr:full":"50 Clinton St Lowr Hempstead NY 11550",
    "addr:housenumber":"50",
    "addr:postcode":"11550",
    "addr:street":"Clinton St Lowr",
    "iso:country":"US",
    "sg:address":"50 Clinton St Lowr",
    "sg:city":"Hempstead",
    "sg:classifiers":[
        {
            "category":"Sports & Exercise",
            "subcategory":"Gym",
            "type":"Entertainment"
        }
    ],
    "sg:phone":"+1 516 505 4300",
    "sg:postcode":"11550",
    "sg:province":"NY",
    "sg:tags":[
        "trainer"
    ],
    "sg:website":"www.northshorelij.com",
    "wof:name":"North Shore Lij Health Systems",
    "wof:placetype":"venue"
},
  "geometry": {"coordinates":[-73.61889600000001,40.707699],"type":"Point"}
}