{
  "type": "Feature",
  "properties": {
    "addr:full":"7611 Roosevelt Ave Jackson Heights NY 11372",
    "addr:housenumber":"7611",
    "addr:postcode":"11372",
    "addr:street":"Roosevelt Ave",
    "iso:country":"US",
    "sg:address":"7611 Roosevelt Ave",
    "sg:city":"Jackson Heights",
    "sg:classifiers":[
        {
            "category":"Personal",
            "subcategory":"Nail Salon",
            "type":"Services"
        }
    ],
    "sg:phone":"+1 718 396 3556",
    "sg:postcode":"11372",
    "sg:province":"NY",
    "wof:name":"Jimmy Nail Salon",
    "wof:placetype":"venue"
},
  "geometry": {"coordinates":[-73.889099,40.7472],"type":"Point"}
}