{
  "type": "Feature",
  "properties": {
    "iso:country":"US",
    "sg:address":"217 Roslyn Rd",
    "sg:city":"Roslyn Heights",
    "sg:classifiers":[
        {
            "category":"Wholesale",
            "subcategory":"Furniture",
            "type":"Manufacturing & Wholesale Goods"
        }
    ],
    "sg:phone":"+1 516 626 0233",
    "sg:postcode":"11577",
    "sg:province":"NY",
    "wof:name":"RTB Roslyn Corp",
    "wof:placetype":"venue"
},
  "geometry": {"coordinates":[-73.639562,40.786637],"type":"Point"}
}