{
  "type": "Feature",
  "properties": {
    "addr:full":"290 Ivory Rd Frewsburg NY 14738",
    "addr:housenumber":"290",
    "addr:postcode":"14738",
    "addr:street":"Ivory Rd",
    "iso:country":"US",
    "sg:address":"290 Ivory Rd",
    "sg:city":"Frewsburg",
    "sg:classifiers":[
        {
            "category":"Freight",
            "type":"Transportation"
        }
    ],
    "sg:phone":"+1   ",
    "sg:postcode":"14738",
    "sg:province":"NY",
    "sg:tags":[
        "operator",
        "local",
        "trucking"
    ],
    "wof:name":"Strong Trucking",
    "wof:placetype":"venue"
},
  "geometry": {"coordinates":[-79.059974,42.057119],"type":"Point"}
}