{
  "type": "Feature",
  "properties": {
    "addr:full":"928 State Hwy 96 Phelps NY 14532",
    "addr:housenumber":"928",
    "addr:postcode":"14532",
    "addr:street":"State Hwy 96",
    "iso:country":"US",
    "sg:address":"928 State Hwy 96",
    "sg:city":"Phelps",
    "sg:classifiers":[
        {
            "category":"Health Services",
            "subcategory":"Doctor",
            "type":"Services"
        }
    ],
    "sg:phone":"+1 315 548 9537",
    "sg:postcode":"14532",
    "sg:province":"NY",
    "sg:tags":[
        "physician",
        "surgeon"
    ],
    "wof:name":"A Thomas Pulvino MD",
    "wof:placetype":"venue"
},
  "geometry": {"coordinates":[-77.019374,42.948358],"type":"Point"}
}