{
  "type": "Feature",
  "properties": {
    "addr:full":"3559 77th St Jackson Heights NY 11372",
    "addr:housenumber":"3559",
    "addr:postcode":"11372",
    "addr:street":"77Th St",
    "iso:country":"US",
    "sg:address":"3559 77th St",
    "sg:city":"Jackson Heights",
    "sg:classifiers":[
        {
            "category":"Shopping",
            "subcategory":"Mobile Phones",
            "type":"Retail Goods"
        }
    ],
    "sg:phone":"+1 718 533 0303",
    "sg:postcode":"11372",
    "sg:province":"NY",
    "wof:name":"Hi-Venus Wireless Inc",
    "wof:placetype":"venue"
},
  "geometry": {"coordinates":[-73.889049,40.750716],"type":"Point"}
}