{
  "type": "Feature",
  "properties": {
    "addr:full":"129 E 39th St Frnt New York NY 10016",
    "addr:housenumber":"129",
    "addr:postcode":"10016",
    "addr:street":"E 39Th St",
    "iso:country":"US",
    "sg:address":"129 E 39th St Frnt",
    "sg:city":"New York",
    "sg:classifiers":[
        {
            "category":"Retail",
            "subcategory":"Laundry & Dry Cleaning",
            "type":"Services"
        }
    ],
    "sg:phone":"+1 212 682 6855",
    "sg:postcode":"10016",
    "sg:province":"NY",
    "wof:name":"Murray Hill Dry Cleaner & Laundry",
    "wof:placetype":"venue"
},
  "geometry": {"coordinates":[-73.977402,40.7495],"type":"Point"}
}