{
  "type": "Feature",
  "properties": {
    "addr:full":"412 E 240th St Bronx NY 10470",
    "addr:housenumber":"412",
    "addr:postcode":"10470",
    "addr:street":"E 240Th St",
    "iso:country":"US",
    "sg:address":"412 E 240th St",
    "sg:city":"Bronx",
    "sg:classifiers":[
        {
            "category":"Professional",
            "type":"Services"
        }
    ],
    "sg:phone":"+1 718 324 1608",
    "sg:postcode":"10470",
    "sg:province":"NY",
    "sg:tags":[
        "establishment"
    ],
    "wof:name":"Trux & Trax",
    "wof:placetype":"venue"
},
  "geometry": {"coordinates":[-73.86304,40.901424],"type":"Point"}
}