{
  "type": "Feature",
  "properties": {
    "iso:country":"US",
    "sg:address":"610 Broadway",
    "sg:city":"Massapequa",
    "sg:classifiers":[
        {
            "category":"Recreation",
            "type":"Entertainment"
        }
    ],
    "sg:phone":"+1 631 896 9391",
    "sg:postcode":"11758",
    "sg:province":"NY",
    "sg:tags":[
        "martial",
        "arts",
        "instruction"
    ],
    "wof:name":"Jeet Kune Do Martial Arts",
    "wof:placetype":"venue"
},
  "geometry": {"coordinates":[-73.467907,40.684152],"type":"Point"}
}