{
  "type": "Feature",
  "properties": {
    "addr:full":"8369 N Main St Interlaken NY 14847",
    "addr:housenumber":"8369",
    "addr:postcode":"14847",
    "addr:street":"N Main St",
    "iso:country":"US",
    "sg:address":"8369 N Main St",
    "sg:city":"Interlaken",
    "sg:classifiers":[
        {
            "category":"Government",
            "subcategory":"Police Station",
            "type":"Public Place"
        }
    ],
    "sg:phone":"+1 607 532 4466",
    "sg:postcode":"14847",
    "sg:province":"NY",
    "sg:tags":[
        "department"
    ],
    "wof:name":"Interlaken Police Dept",
    "wof:placetype":"venue"
},
  "geometry": {"coordinates":[-76.724802,42.618747],"type":"Point"}
}