{
  "type": "Feature",
  "properties": {
    "iso:country":"US",
    "sg:address":"260 Pond Path",
    "sg:city":"South Setauket",
    "sg:classifiers":[
        {
            "category":"Food & Beverages",
            "subcategory":"Groceries & Convenience Stores",
            "type":"Retail Goods"
        }
    ],
    "sg:phone":"+1 631 585 4585",
    "sg:postcode":"11720",
    "sg:province":"NY",
    "sg:tags":[
        "grocer"
    ],
    "wof:name":"Super Stop & Shop",
    "wof:placetype":"venue"
},
  "geometry": {"coordinates":[-73.102599,40.883905],"type":"Point"}
}