{
  "type": "Feature",
  "properties": {
    "addr:full":"815 Manor Rd Staten Island NY 10314",
    "addr:housenumber":"815",
    "addr:postcode":"10314",
    "addr:street":"Manor Rd",
    "iso:country":"US",
    "sg:address":"815 Manor Rd",
    "sg:city":"Staten Island",
    "sg:classifiers":[
        {
            "category":"Real Estate",
            "subcategory":"Real Estate Agent",
            "type":"Services"
        }
    ],
    "sg:phone":"+1 718 698 4900",
    "sg:postcode":"10314",
    "sg:province":"NY",
    "sg:tags":[
        "authorities",
        "housing"
    ],
    "sg:website":"www.nyc.gov",
    "wof:name":"New York City Housing Auth",
    "wof:placetype":"venue"
},
  "geometry": {"coordinates":[-74.12097,40.607999],"type":"Point"}
}