{
  "type": "Feature",
  "properties": {
    "addr:full":"37 Wheeler Ave Pleasantville NY 10570",
    "addr:housenumber":"37",
    "addr:postcode":"10570",
    "addr:street":"Wheeler Ave",
    "iso:country":"US",
    "sg:address":"37 Wheeler Ave",
    "sg:city":"Pleasantville",
    "sg:classifiers":[
        {
            "category":"Deli",
            "type":"Food & Drink"
        },
        {
            "category":"Restaurant",
            "type":"Food & Drink"
        }
    ],
    "sg:phone":"+1 914 747 4601",
    "sg:postcode":"10570",
    "sg:province":"NY",
    "sg:tags":[
        "mexican"
    ],
    "sg:website":"www.sundancedeli.com",
    "wof:name":"Sundance Deli",
    "wof:placetype":"venue"
},
  "geometry": {"coordinates":[-73.791875,41.134543],"type":"Point"}
}