{
  "type": "Feature",
  "properties": {
    "iso:country":"US",
    "sg:address":"143 Main St",
    "sg:city":"Boonville",
    "sg:classifiers":[
        {
            "category":"Shopping",
            "subcategory":"Discount & Variety Stores",
            "type":"Retail Goods"
        }
    ],
    "sg:phone":"+1 315 942 4476",
    "sg:postcode":"13309",
    "sg:province":"NY",
    "wof:name":"Eckerd",
    "wof:placetype":"venue"
},
  "geometry": {"coordinates":[-75.333821,43.483323],"type":"Point"}
}