{
  "type": "Feature",
  "properties": {
    "iso:country":"US",
    "sg:address":"27 Shaver Hill Rd",
    "sg:city":"Andes",
    "sg:classifiers":[
        {
            "category":"Farming",
            "subcategory":"Farm",
            "type":"Manufacturing & Wholesale Goods"
        }
    ],
    "sg:phone":"+1 845 676 3615",
    "sg:postcode":"13754",
    "sg:province":"NY",
    "sg:tags":[
        "crop",
        "general"
    ],
    "wof:name":"Misty Morning Farm Inc",
    "wof:placetype":"venue"
},
  "geometry": {"coordinates":[-75.44148300000001,42.067111],"type":"Point"}
}