{
  "type": "Feature",
  "properties": {
    "addr:full":"3240 Chili Ave Rochester NY 14624",
    "addr:housenumber":"3240",
    "addr:postcode":"14624",
    "addr:street":"Chili Ave",
    "iso:country":"US",
    "sg:address":"3240 Chili Ave",
    "sg:city":"Rochester",
    "sg:classifiers":[
        {
            "category":"Restaurant",
            "type":"Food & Drink"
        }
    ],
    "sg:menulink":"http://www.allmenus.com/ny/rochester/19220-bill-grays/menu/",
    "sg:phone":"+1 585 889 8260",
    "sg:postcode":"14624",
    "sg:province":"NY",
    "sg:tags":[
        "american"
    ],
    "wof:name":"Bill Gray's",
    "wof:placetype":"venue"
},
  "geometry": {"coordinates":[-77.665733,43.140286],"type":"Point"}
}