{
  "type": "Feature",
  "properties": {
    "iso:country":"US",
    "name:eng_x_preferred":[
        "125 St"
    ],
    "wof:name":"125 St",
    "wof:placetype":"venue"
},
  "geometry": {"coordinates":[-73.952343,40.811109],"type":"Point"}
}