{
  "type": "Feature",
  "properties": {
    "iso:country":"US",
    "sg:address":"230 W 72 St",
    "sg:city":"New York",
    "sg:classifiers":[
        {
            "category":"Professional",
            "subcategory":"Lawyer & Legal Services",
            "type":"Services"
        }
    ],
    "sg:phone":"+1 212 769 0777",
    "sg:postcode":"10023",
    "sg:province":"NY",
    "wof:name":"Irving D Chodosh Atty",
    "wof:placetype":"venue"
},
  "geometry": {"coordinates":[-73.983936,40.779422],"type":"Point"}
}