{
  "type": "Feature",
  "properties": {
    "iso:country":"US",
    "sg:address":"143 Burwell Rd",
    "sg:city":"Rochester",
    "sg:classifiers":[
        {
            "category":"Professional",
            "subcategory":"Accounting & Tax Preparation",
            "type":"Services"
        }
    ],
    "sg:phone":"+1 585 342 6345",
    "sg:postcode":"14617",
    "sg:province":"NY",
    "sg:tags":[
        "accountant"
    ],
    "wof:name":"Jerry L Bond CPA",
    "wof:placetype":"venue"
},
  "geometry": {"coordinates":[-77.60671499999999,43.203898],"type":"Point"}
}