{
  "type": "Feature",
  "properties": {
    "iso:country":"US",
    "sg:address":"8 E Washington St",
    "sg:city":"Bath",
    "sg:classifiers":[
        {
            "category":"Health Services",
            "subcategory":"Doctor",
            "type":"Services"
        }
    ],
    "sg:phone":"+1 607 776 2800",
    "sg:postcode":"14810",
    "sg:province":"NY",
    "sg:tags":[
        "dentist"
    ],
    "wof:name":"John B Wahlig DDS",
    "wof:placetype":"venue"
},
  "geometry": {"coordinates":[-77.317593,42.33691],"type":"Point"}
}