{
  "type": "Feature",
  "properties": {
    "iso:country":"US",
    "sg:address":"40 W Mosholu Pkwy S",
    "sg:city":"Bronx",
    "sg:classifiers":[
        {
            "category":"Retail",
            "subcategory":"Portrait Studio",
            "type":"Services"
        }
    ],
    "sg:phone":"+1   ",
    "sg:postcode":"10468",
    "sg:province":"NY",
    "sg:tags":[
        "photo"
    ],
    "wof:name":"API/Ifl Photo",
    "wof:placetype":"venue"
},
  "geometry": {"coordinates":[-73.887007,40.882263],"type":"Point"}
}