{
  "type": "Feature",
  "properties": {
    "addr:full":"6261 State Hwy 31 Cicero NY 13039",
    "addr:housenumber":"6261",
    "addr:postcode":"13039",
    "addr:street":"State Hwy 31",
    "iso:country":"US",
    "sg:address":"6261 State Hwy 31",
    "sg:city":"Cicero",
    "sg:classifiers":[
        {
            "category":"Health Services",
            "subcategory":"Doctor",
            "type":"Services"
        }
    ],
    "sg:phone":"+1 315 698 8648",
    "sg:postcode":"13039",
    "sg:province":"NY",
    "sg:tags":[
        "dentist"
    ],
    "wof:name":"Joseph A Sweet DDS",
    "wof:placetype":"venue"
},
  "geometry": {"coordinates":[-76.08761199999999,43.176917],"type":"Point"}
}