{
  "type": "Feature",
  "properties": {
    "iso:country":"US",
    "sg:address":"24 Mineah Rd",
    "sg:city":"Freeville",
    "sg:classifiers":[
        {
            "category":"Health Services",
            "subcategory":"Clinic",
            "type":"Services"
        },
        {
            "category":"Health Services",
            "subcategory":"Health Practitioner",
            "type":"Services"
        }
    ],
    "sg:phone":"+1 607 844 3440",
    "sg:postcode":"13068",
    "sg:province":"NY",
    "sg:tags":[
        "therapist",
        "therapy",
        "physical"
    ],
    "wof:name":"Finger Lakes Physical Therapy. P.C.",
    "wof:placetype":"venue"
},
  "geometry": {"coordinates":[-76.373454,42.477293],"type":"Point"}
}