{
  "type": "Feature",
  "properties": {
    "iso:country":"US",
    "sg:address":"535 Division St",
    "sg:city":"North Tonawanda",
    "sg:classifiers":[
        {
            "category":"Food & Beverages",
            "subcategory":"Groceries & Convenience Stores",
            "type":"Retail Goods"
        }
    ],
    "sg:phone":"+1 716 693 2802",
    "sg:postcode":"14120",
    "sg:province":"NY",
    "sg:tags":[
        "grocer"
    ],
    "sg:website":"www.budweyssupermarket.com",
    "wof:name":"Budweys Supermarket",
    "wof:placetype":"venue"
},
  "geometry": {"coordinates":[-78.86394,43.038757],"type":"Point"}
}