{
  "type": "Feature",
  "properties": {
    "addr:full":"65 Deer Park Ave Babylon NY 11702",
    "addr:housenumber":"65",
    "addr:postcode":"11702",
    "addr:street":"Deer Park Ave",
    "iso:country":"US",
    "sg:address":"65 Deer Park Ave",
    "sg:city":"Babylon",
    "sg:classifiers":[
        {
            "category":"Manufacturing",
            "subcategory":"Apparel",
            "type":"Manufacturing & Wholesale Goods"
        }
    ],
    "sg:phone":"+1 631 661 0492",
    "sg:postcode":"11702",
    "sg:province":"NY",
    "sg:tags":[
        "mfg",
        "bridal",
        "piece",
        "dress",
        "supply"
    ],
    "sg:website":"www.alvinavalenta.com",
    "wof:name":"Alvina Vlenta Couture Collectn",
    "wof:placetype":"venue"
},
  "geometry": {"coordinates":[-73.322846,40.697646],"type":"Point"}
}