{
  "type": "Feature",
  "properties": {
    "addr:full":"197 Franklin Ave Brooklyn NY 11205",
    "addr:housenumber":"197",
    "addr:postcode":"11205",
    "addr:street":"Franklin Ave",
    "iso:country":"US",
    "sg:address":"197 Franklin Ave",
    "sg:city":"Brooklyn",
    "sg:classifiers":[
        {
            "category":"Retail",
            "subcategory":"Funeral Services",
            "type":"Services"
        }
    ],
    "sg:phone":"+1 718 875 1036",
    "sg:postcode":"11205",
    "sg:province":"NY",
    "sg:tags":[
        "director",
        "home",
        "cemetery"
    ],
    "wof:name":"James H Willie Funeral Home Inc",
    "wof:placetype":"venue"
},
  "geometry": {"coordinates":[-73.9571,40.6908],"type":"Point"}
}