{
  "type": "Feature",
  "properties": {
    "iso:country":"US",
    "sg:address":"3 Avanti Dr",
    "sg:city":"Rochester",
    "sg:classifiers":[
        {
            "category":"Banks & Credit Unions",
            "subcategory":"Financial Services",
            "type":"Services"
        }
    ],
    "sg:phone":"+1 585 436 2209",
    "sg:postcode":"14606",
    "sg:province":"NY",
    "sg:tags":[
        "investing"
    ],
    "wof:name":"Jacobson Group L P",
    "wof:placetype":"venue"
},
  "geometry": {"coordinates":[-77.687055,43.15256],"type":"Point"}
}