{
  "type": "Feature",
  "properties": {
    "addr:full":"1013 Willoughby Ave Brooklyn NY 11221",
    "addr:housenumber":"1013",
    "addr:postcode":"11221",
    "addr:street":"Willoughby Ave",
    "iso:country":"US",
    "sg:address":"1013 Willoughby Ave",
    "sg:city":"Brooklyn",
    "sg:classifiers":[
        {
            "category":"Building & Trades",
            "subcategory":"Plumbing",
            "type":"Services"
        }
    ],
    "sg:phone":"+1 718 417 3393",
    "sg:postcode":"11221",
    "sg:province":"NY",
    "wof:name":"Empire Air Conditioning & Heating Corp",
    "wof:placetype":"venue"
},
  "geometry": {"coordinates":[-73.92872800000001,40.699183],"type":"Point"}
}