{
  "type": "Feature",
  "properties": {
    "addr:full":"110 Ramsey Pl Albany NY 12209",
    "addr:housenumber":"110",
    "addr:postcode":"12209",
    "addr:street":"Ramsey Pl",
    "iso:country":"US",
    "sg:address":"110 Ramsey Pl",
    "sg:city":"Albany",
    "sg:classifiers":[
        {
            "category":"Wholesale",
            "subcategory":"Machinery & Supplies",
            "type":"Manufacturing & Wholesale Goods"
        }
    ],
    "sg:phone":"+1 518 438 3331",
    "sg:postcode":"12209",
    "sg:province":"NY",
    "sg:tags":[
        "ship",
        "chandler"
    ],
    "wof:name":"Albany Ship Supply Co",
    "wof:placetype":"venue"
},
  "geometry": {"coordinates":[-73.79661,42.645684],"type":"Point"}
}