{
  "type": "Feature",
  "properties": {
    "addr:full":"795 Hoosick Rd Troy NY 12180",
    "addr:housenumber":"795",
    "addr:postcode":"12180",
    "addr:street":"Hoosick Rd",
    "iso:country":"US",
    "sg:address":"795 Hoosick Rd",
    "sg:city":"Troy",
    "sg:classifiers":[
        {
            "category":"Autos & Motor Vehicles",
            "subcategory":"Automobile Sales",
            "type":"Retail Goods"
        }
    ],
    "sg:phone":"+1 518 279 3400",
    "sg:postcode":"12180",
    "sg:province":"NY",
    "sg:tags":[
        "new",
        "truck",
        "car"
    ],
    "sg:website":"http://www.actionchevrolet.com",
    "wof:name":"Action Chevrolet, Subaru, Geo",
    "wof:placetype":"venue"
},
  "geometry": {"coordinates":[-73.63671100000001,42.748578],"type":"Point"}
}