{
  "type": "Feature",
  "properties": {
    "iso:country":"US",
    "sg:address":"Empire State Building 5TH Avenue",
    "sg:city":"New York",
    "sg:classifiers":[
        {
            "category":"Professional",
            "subcategory":"Advertising",
            "type":"Services"
        }
    ],
    "sg:phone":"+55 11 9809 1862",
    "sg:postcode":"10118",
    "sg:province":"NY",
    "sg:tags":[
        "advertisers",
        "advertisement",
        "payment",
        "online-payment",
        "merchant",
        "lead-generation",
        "leads",
        "adleads"
    ],
    "sg:website":"http://www.pago.me",
    "wof:name":"PagoPago",
    "wof:placetype":"venue"
},
  "geometry": {"coordinates":[-73.973968,40.762966],"type":"Point"}
}