{
  "type": "Feature",
  "properties": {
    "iso:country":"US",
    "sg:address":"98 Main St",
    "sg:city":"Binghamton",
    "sg:classifiers":[
        {
            "category":"Organizations",
            "subcategory":"Labor Organization",
            "type":"Services"
        }
    ],
    "sg:phone":"+1 607 723 7543",
    "sg:postcode":"13905",
    "sg:province":"NY",
    "sg:tags":[
        "union"
    ],
    "wof:name":"Laborers Local Union 7",
    "wof:placetype":"venue"
},
  "geometry": {"coordinates":[-75.925175,42.100523],"type":"Point"}
}