{
  "type": "Feature",
  "properties": {
    "addr:full":"2465 Bathgate Ave Bronx NY 10458",
    "addr:housenumber":"2465",
    "addr:postcode":"10458",
    "addr:street":"Bathgate Ave",
    "iso:country":"US",
    "sg:address":"2465 Bathgate Ave",
    "sg:city":"Bronx",
    "sg:classifiers":[
        {
            "category":"Education",
            "subcategory":"Special Training",
            "type":"Public Place"
        }
    ],
    "sg:phone":"+1 718 329 5178",
    "sg:postcode":"10458",
    "sg:province":"NY",
    "sg:tags":[
        "center"
    ],
    "wof:name":"N Y League For Early Learning",
    "wof:placetype":"venue"
},
  "geometry": {"coordinates":[-73.888824,40.858012],"type":"Point"}
}