{
  "type": "Feature",
  "properties": {
    "addr:full":"364 Longnecker St Buffalo NY 14206",
    "addr:housenumber":"364",
    "addr:postcode":"14206",
    "addr:street":"Longnecker St",
    "iso:country":"US",
    "sg:address":"364 Longnecker St",
    "sg:city":"Buffalo",
    "sg:classifiers":[
        {
            "category":"Building & Trades",
            "subcategory":"Construction",
            "type":"Services"
        }
    ],
    "sg:phone":"+1 716 894 3567",
    "sg:postcode":"14206",
    "sg:province":"NY",
    "sg:tags":[
        "specializing",
        "spray",
        "painting"
    ],
    "wof:name":"Brightway Restoration & Pntg",
    "wof:placetype":"venue"
},
  "geometry": {"coordinates":[-78.808542,42.892815],"type":"Point"}
}