{
  "type": "Feature",
  "properties": {
    "addr:full":"10 W End Ave Stamford NY 12167",
    "addr:housenumber":"10",
    "addr:postcode":"12167",
    "addr:street":"W End Ave",
    "iso:country":"US",
    "sg:address":"10 W End Ave",
    "sg:city":"Stamford",
    "sg:classifiers":[
        {
            "category":"Health Services",
            "subcategory":"Chiropractor",
            "type":"Services"
        }
    ],
    "sg:phone":"+1 607 652 7174",
    "sg:postcode":"12167",
    "sg:province":"NY",
    "sg:tags":[
        "chiropractic"
    ],
    "wof:name":"Swenson Norman R",
    "wof:placetype":"venue"
},
  "geometry": {"coordinates":[-74.62381000000001,42.410019],"type":"Point"}
}