{
  "type": "Feature",
  "properties": {
    "iso:country":"US",
    "sg:address":"34 E Post Rd",
    "sg:city":"White Plains",
    "sg:classifiers":[
        {
            "category":"Autos & Motor Vehicles",
            "subcategory":"Fuel & Gas Station",
            "type":"Retail Goods"
        }
    ],
    "sg:phone":"+1   ",
    "sg:postcode":"10601",
    "sg:province":"NY",
    "sg:tags":[
        "station",
        "gasoline"
    ],
    "wof:name":"Barrier White Plains Citgo",
    "wof:placetype":"venue"
},
  "geometry": {"coordinates":[-73.769008,41.026896],"type":"Point"}
}