{
  "type": "Feature",
  "properties": {
    "addr:full":"190 Sterling St Greenport NY 11944",
    "addr:housenumber":"190",
    "addr:postcode":"11944",
    "addr:street":"Sterling St",
    "iso:country":"US",
    "sg:address":"190 Sterling St",
    "sg:city":"Greenport",
    "sg:classifiers":[
        {
            "category":"Manufacturing",
            "subcategory":"Metals",
            "type":"Manufacturing & Wholesale Goods"
        }
    ],
    "sg:phone":"+1 631 477 8800",
    "sg:postcode":"11944",
    "sg:province":"NY",
    "sg:tags":[
        "steel"
    ],
    "wof:name":"Hanffs Marine Structure",
    "wof:placetype":"venue"
},
  "geometry": {"coordinates":[-72.360891,41.108269],"type":"Point"}
}