{
  "type": "Feature",
  "properties": {
    "addr:full":"40 Stobe Ave Staten Island NY 10306",
    "addr:housenumber":"40",
    "addr:postcode":"10306",
    "addr:street":"Stobe Ave",
    "iso:country":"US",
    "sg:address":"40 Stobe Ave",
    "sg:city":"Staten Island",
    "sg:classifiers":[
        {
            "category":"Building & Trades",
            "subcategory":"Electrical",
            "type":"Services"
        }
    ],
    "sg:phone":"+1 718 351 8666",
    "sg:postcode":"10306",
    "sg:province":"NY",
    "sg:tags":[
        "specializing",
        "alarm",
        "contractor",
        "electrical",
        "security",
        "or"
    ],
    "wof:name":"State Wide SEC Srvllance Camra",
    "wof:placetype":"venue"
},
  "geometry": {"coordinates":[-74.102846,40.585403],"type":"Point"}
}