{
  "type": "Feature",
  "properties": {
    "addr:full":"79 Church St Hoosick Falls NY 12090",
    "addr:housenumber":"79",
    "addr:postcode":"12090",
    "addr:street":"Church St",
    "iso:country":"US",
    "sg:address":"79 Church St",
    "sg:city":"Hoosick Falls",
    "sg:classifiers":[
        {
            "category":"Retail",
            "subcategory":"Animal Services",
            "type":"Services"
        }
    ],
    "sg:phone":"+1 518 686 7660",
    "sg:postcode":"12090",
    "sg:province":"NY",
    "sg:tags":[
        "pet",
        "grooming",
        "washing"
    ],
    "wof:name":"Paw Fection Dog Grooming",
    "wof:placetype":"venue"
},
  "geometry": {"coordinates":[-73.352001,42.899639],"type":"Point"}
}