{
  "type": "Feature",
  "properties": {
    "addr:full":"174 S Main St Canandaigua NY 14424",
    "addr:housenumber":"174",
    "addr:postcode":"14424",
    "addr:street":"S Main St",
    "iso:country":"US",
    "sg:address":"174 S Main St",
    "sg:city":"Canandaigua",
    "sg:classifiers":[
        {
            "category":"Building & Trades",
            "subcategory":"Equipment Rental",
            "type":"Services"
        }
    ],
    "sg:phone":"+1 585 393 9210",
    "sg:postcode":"14424",
    "sg:province":"NY",
    "wof:name":"Rent-A-Center",
    "wof:placetype":"venue"
},
  "geometry": {"coordinates":[-77.279706,42.885166],"type":"Point"}
}