{
  "type": "Feature",
  "properties": {
    "iso:country":"US",
    "sg:address":"366 Madison Ave",
    "sg:city":"New York",
    "sg:classifiers":[
        {
            "category":"Arts & Performance",
            "subcategory":"Theater",
            "type":"Entertainment"
        }
    ],
    "sg:phone":"+1 212 661 7500",
    "sg:postcode":"10017",
    "sg:province":"NY",
    "sg:tags":[
        "producer",
        "form",
        "show",
        "long",
        "radio",
        "distributor",
        "talk"
    ],
    "wof:name":"E F M Media Management Inc",
    "wof:placetype":"venue"
},
  "geometry": {"coordinates":[-73.977656,40.755077],"type":"Point"}
}