{
  "type": "Feature",
  "properties": {
    "addr:full":"120 Forsyth St Bsmt North New York NY 10002",
    "addr:housenumber":"120",
    "addr:postcode":"10002",
    "addr:street":"Forsyth St;North",
    "iso:country":"US",
    "sg:address":"120 Forsyth St Bsmt North",
    "sg:city":"New York",
    "sg:classifiers":[
        {
            "category":"Autos & Motor Vehicles",
            "subcategory":"Automobile Sales",
            "type":"Retail Goods"
        }
    ],
    "sg:phone":"+1 212 431 5919",
    "sg:postcode":"10002",
    "sg:province":"NY",
    "sg:tags":[
        "limo"
    ],
    "wof:name":"Sun Fat Tat Express Corp",
    "wof:placetype":"venue"
},
  "geometry": {"coordinates":[-73.992273,40.719096],"type":"Point"}
}