{
  "type": "Feature",
  "properties": {
    "iso:country":"US",
    "sg:address":"51 E Main St",
    "sg:city":"Smithtown",
    "sg:classifiers":[
        {
            "category":"Insurance",
            "subcategory":"Insurance Agent",
            "type":"Services"
        }
    ],
    "sg:phone":"+1 631 366 2586",
    "sg:postcode":"11787",
    "sg:province":"NY",
    "wof:name":"Prudential",
    "wof:placetype":"venue"
},
  "geometry": {"coordinates":[-73.192319,40.855563],"type":"Point"}
}