{
  "type": "Feature",
  "properties": {
    "iso:country":"US",
    "sg:address":"200 Herriman St",
    "sg:city":"Syracuse",
    "sg:classifiers":[
        {
            "category":"Parking",
            "type":"Transportation"
        }
    ],
    "sg:phone":"+1   ",
    "sg:postcode":"13204",
    "sg:province":"NY",
    "sg:tags":[
        "automobile"
    ],
    "wof:name":"Allright Central Parking",
    "wof:placetype":"venue"
},
  "geometry": {"coordinates":[-76.177156,43.037696],"type":"Point"}
}