{
  "type": "Feature",
  "properties": {
    "iso:country":"US",
    "sg:address":"71 Dover Green",
    "sg:city":"Staten Island",
    "sg:classifiers":[
        {
            "category":"Building & Trades",
            "subcategory":"Equipment Rental",
            "type":"Services"
        }
    ],
    "sg:phone":"+1 718 317 1935",
    "sg:postcode":"10312",
    "sg:province":"NY",
    "wof:name":"Throwing A Party",
    "wof:placetype":"venue"
},
  "geometry": {"coordinates":[-74.198097,40.557917],"type":"Point"}
}