{
  "type": "Feature",
  "properties": {
    "iso:country":"US",
    "sg:address":"45 Waterford Way",
    "sg:city":"Fairport",
    "sg:classifiers":[
        {
            "category":"Shopping",
            "subcategory":"Used Merchandise",
            "type":"Retail Goods"
        }
    ],
    "sg:phone":"+1 585 223 3970",
    "sg:postcode":"14450",
    "sg:province":"NY",
    "sg:tags":[
        "shop",
        "consignment"
    ],
    "wof:name":"Babys Inn Inc",
    "wof:placetype":"venue"
},
  "geometry": {"coordinates":[-77.403413,43.083622],"type":"Point"}
}