{
  "type": "Feature",
  "properties": {
    "addr:full":"40 Kendall Ct Altamont NY 12009",
    "addr:housenumber":"40",
    "addr:postcode":"12009",
    "addr:street":"Kendall Ct",
    "iso:country":"US",
    "sg:address":"40 Kendall Ct",
    "sg:city":"Altamont",
    "sg:classifiers":[
        {
            "category":"Building & Trades",
            "subcategory":"Construction",
            "type":"Services"
        }
    ],
    "sg:phone":"+1 518 872 2977",
    "sg:postcode":"12009",
    "sg:province":"NY",
    "sg:tags":[
        "house"
    ],
    "wof:name":"Buckeye Home Improvement",
    "wof:placetype":"venue"
},
  "geometry": {"coordinates":[-74.08524199999999,42.654975],"type":"Point"}
}