{
  "type": "Feature",
  "properties": {
    "iso:country":"US",
    "sg:address":"300 W 135th St",
    "sg:city":"New York",
    "sg:classifiers":[
        {
            "category":"Building & Trades",
            "subcategory":"Plumbing",
            "type":"Services"
        }
    ],
    "sg:phone":"+1 212 694 8976",
    "sg:postcode":"10030",
    "sg:province":"NY",
    "sg:tags":[
        "mechanical",
        "contractor"
    ],
    "wof:name":"KSW Mechanical",
    "wof:placetype":"venue"
},
  "geometry": {"coordinates":[-73.947934,40.817084],"type":"Point"}
}