{
  "type": "Feature",
  "properties": {
    "iso:country":"US",
    "sg:address":"2810 Rte 112",
    "sg:city":"Medford",
    "sg:classifiers":[
        {
            "category":"Food & Beverages",
            "subcategory":"Groceries & Convenience Stores",
            "type":"Retail Goods"
        }
    ],
    "sg:phone":"+1 631 696 6481",
    "sg:postcode":"11763",
    "sg:province":"NY",
    "sg:website":"www.7-eleven.com",
    "wof:name":"7-Eleven",
    "wof:placetype":"venue"
},
  "geometry": {"coordinates":[-72.99508,40.827431],"type":"Point"}
}