{
  "type": "Feature",
  "properties": {
    "addr:full":"1752 McDonald Ave Brooklyn NY 11230",
    "addr:housenumber":"1752",
    "addr:postcode":"11230",
    "addr:street":"Mcdonald Ave",
    "iso:country":"US",
    "sg:address":"1752 McDonald Ave",
    "sg:city":"Brooklyn",
    "sg:classifiers":[
        {
            "category":"Restaurant",
            "type":"Food & Drink"
        }
    ],
    "sg:phone":"+1 718 975 2060",
    "sg:postcode":"11230",
    "sg:province":"NY",
    "wof:name":"Sanremo Cafe",
    "wof:placetype":"venue"
},
  "geometry": {"coordinates":[-73.973266,40.61016],"type":"Point"}
}