{
  "type": "Feature",
  "properties": {
    "wof:name":"Mapzen",
    "wof:placetype":"venue"
},
  "geometry": {"coordinates":[-73.99047374725301,40.744176331776],"type":"Point"}
}