{
  "type": "Feature",
  "properties": {
    "wof:name":"Mapzen",
    "wof:placetype":"venue"
},
  "geometry": {"coordinates":[-73.990452,40.744225],"type":"Point"}
}