{
  "type": "Feature",
  "properties": {
    "addr:full":"30 West 26th St, New York, NY 10010",
    "addr:github":"https://github.com/mapzen/",
    "addr:housenumber":30,
    "addr:postcode":10010,
    "addr:street":"West 26th St",
    "addr:twitter":"https://twitter.com/mapzen",
    "addr:website":"https://mapzen.com/",
    "wof:name":"Mapzen",
    "wof:placetype":"venue"
},
  "geometry": {"coordinates":[-73.99047400000001,40.744152],"type":"Point"}
}