{
  "type": "Feature",
  "properties": {
    "wof:name":"Mapzen",
    "wof:placetype":"venue"
},
  "geometry": {"coordinates":[-73.99047400000001,40.744152],"type":"Point"}
}