{
  "type": "Feature",
  "properties": {
    "addr:full":"106 S Loder Ave Endicott NY 13760",
    "addr:housenumber":"106",
    "addr:postcode":"13760",
    "addr:street":"S Loder Ave",
    "iso:country":"US",
    "sg:address":"106 S Loder Ave",
    "sg:city":"Endicott",
    "sg:classifiers":[
        {
            "category":"Freight",
            "type":"Transportation"
        }
    ],
    "sg:phone":"+1   ",
    "sg:postcode":"13760",
    "sg:province":"NY",
    "sg:tags":[
        "operator",
        "local",
        "trucking"
    ],
    "wof:name":"J Setzer Trucking",
    "wof:placetype":"venue"
},
  "geometry": {"coordinates":[-76.062771,42.097065],"type":"Point"}
}