{
  "type": "Feature",
  "properties": {
    "addr:full":"1005 58th St Brooklyn NY 11219",
    "addr:housenumber":"1005",
    "addr:postcode":"11219",
    "addr:street":"58Th St",
    "iso:country":"US",
    "sg:address":"1005 58th St",
    "sg:city":"Brooklyn",
    "sg:classifiers":[
        {
            "category":"Personal",
            "subcategory":"Beauty Salon",
            "type":"Services"
        }
    ],
    "sg:phone":"+1   ",
    "sg:postcode":"11219",
    "sg:province":"NY",
    "sg:tags":[
        "shop"
    ],
    "wof:name":"Beatas Nail Salon",
    "wof:placetype":"venue"
},
  "geometry": {"coordinates":[-74.001786,40.632759],"type":"Point"}
}