{
  "type": "Feature",
  "properties": {
    "iso:country":"US",
    "sg:address":"420 Holecek Ave",
    "sg:city":"Elmira",
    "sg:classifiers":[
        {
            "category":"Building & Trades",
            "subcategory":"Construction",
            "type":"Services"
        }
    ],
    "sg:phone":"+1 607 767 0915",
    "sg:postcode":"14904",
    "sg:province":"NY",
    "sg:tags":[
        "roofing",
        "contractor"
    ],
    "wof:name":"TUD Roofing",
    "wof:placetype":"venue"
},
  "geometry": {"coordinates":[-76.82517900000001,42.072631],"type":"Point"}
}