{
  "type": "Feature",
  "properties": {
    "addr:full":"3740 Broadway New York NY 10032",
    "addr:housenumber":"3740",
    "addr:postcode":"10032",
    "addr:street":"Broadway",
    "iso:country":"US",
    "sg:address":"3740 Broadway",
    "sg:city":"New York",
    "sg:classifiers":[
        {
            "category":"Autos & Motor Vehicles",
            "subcategory":"Fuel & Gas Station",
            "type":"Retail Goods"
        }
    ],
    "sg:phone":"+1 212 368 2785",
    "sg:postcode":"10032",
    "sg:province":"NY",
    "wof:name":"Broadway Amana",
    "wof:placetype":"venue"
},
  "geometry": {"coordinates":[-73.945724,40.832715],"type":"Point"}
}