{
  "type": "Feature",
  "properties": {
    "addr:full":"1117 13th St Niagara Falls NY 14301",
    "addr:housenumber":"1117",
    "addr:postcode":"14301",
    "addr:street":"13Th St",
    "iso:country":"US",
    "sg:address":"1117 13th St",
    "sg:city":"Niagara Falls",
    "sg:classifiers":[
        {
            "category":"Shopping",
            "subcategory":"Used Merchandise",
            "type":"Retail Goods"
        }
    ],
    "sg:phone":"+1   ",
    "sg:postcode":"14301",
    "sg:province":"NY",
    "wof:name":"Mayfair Antiques",
    "wof:placetype":"venue"
},
  "geometry": {"coordinates":[-79.046802,43.099411],"type":"Point"}
}