{
  "type": "Feature",
  "properties": {
    "iso:country":"US",
    "sg:address":"116 W 23rd St",
    "sg:city":"New York",
    "sg:classifiers":[
        {
            "category":"Shopping",
            "subcategory":"Jewelry",
            "type":"Retail Goods"
        }
    ],
    "sg:phone":"+1 212 752 5552",
    "sg:postcode":"10011",
    "sg:province":"NY",
    "sg:tags":[
        "jeweler"
    ],
    "wof:name":"J Fay Corp",
    "wof:placetype":"venue"
},
  "geometry": {"coordinates":[-73.99533,40.743838],"type":"Point"}
}