{
  "type": "Feature",
  "properties": {
    "iso:country":"US",
    "sg:address":"245 Wolfs Ln",
    "sg:city":"Pelham",
    "sg:classifiers":[
        {
            "category":"Building & Trades",
            "subcategory":"Construction",
            "type":"Services"
        }
    ],
    "sg:phone":"+1 914 738 3859",
    "sg:postcode":"10803",
    "sg:province":"NY",
    "sg:tags":[
        "hanging",
        "contractor"
    ],
    "wof:name":"Roberts Cstm Pntg Restoration",
    "wof:placetype":"venue"
},
  "geometry": {"coordinates":[-73.812533,40.904862],"type":"Point"}
}