{
  "type": "Feature",
  "properties": {
    "addr:full":"610 Wilson Ave Brooklyn NY 11207",
    "addr:housenumber":"610",
    "addr:postcode":"11207",
    "addr:street":"Wilson Ave",
    "iso:country":"US",
    "sg:address":"610 Wilson Ave",
    "sg:city":"Brooklyn",
    "sg:classifiers":[
        {
            "category":"Shopping",
            "subcategory":"Pharmacy",
            "type":"Retail Goods"
        }
    ],
    "sg:phone":"+1 718 919 9131",
    "sg:postcode":"11207",
    "sg:province":"NY",
    "sg:tags":[
        "drugstore"
    ],
    "wof:name":"Rimco Pharmacy Inc",
    "wof:placetype":"venue"
},
  "geometry": {"coordinates":[-73.906502,40.689602],"type":"Point"}
}