{
  "type": "Feature",
  "properties": {
    "iso:country":"US",
    "sg:address":"27 Hazard Pkwy",
    "sg:city":"Albion",
    "sg:classifiers":[
        {
            "category":"Social Services",
            "subcategory":"Job Training",
            "type":"Services"
        }
    ],
    "sg:phone":"+1   ",
    "sg:postcode":"14411",
    "sg:province":"NY",
    "wof:name":"Career Management Services",
    "wof:placetype":"venue"
},
  "geometry": {"coordinates":[-78.19464600000001,43.238161],"type":"Point"}
}