{
  "type": "Feature",
  "properties": {
    "iso:country":"US",
    "sg:address":"163 Merrick Rd",
    "sg:city":"Lynbrook",
    "sg:classifiers":[
        {
            "category":"Shopping",
            "subcategory":"Hobbies, Toys, & Games",
            "type":"Retail Goods"
        }
    ],
    "sg:phone":"+1   ",
    "sg:postcode":"11563",
    "sg:province":"NY",
    "wof:name":"Helenas Miniature Shop",
    "wof:placetype":"venue"
},
  "geometry": {"coordinates":[-73.664782,40.658314],"type":"Point"}
}