{
  "type": "Feature",
  "properties": {
    "iso:country":"US",
    "sg:address":"370 Manhattan Ave",
    "sg:city":"New York",
    "sg:classifiers":[
        {
            "category":"Health Services",
            "subcategory":"Doctor",
            "type":"Services"
        }
    ],
    "sg:phone":"+1 212 932 2684",
    "sg:postcode":"10026",
    "sg:province":"NY",
    "wof:name":"Thomas John",
    "wof:placetype":"venue"
},
  "geometry": {"coordinates":[-73.95259900000001,40.801899],"type":"Point"}
}