{
  "type": "Feature",
  "properties": {
    "iso:country":"US",
    "sg:address":"120 Bradford Ave",
    "sg:city":"Mamaroneck",
    "sg:classifiers":[
        {
            "category":"Building & Trades",
            "subcategory":"Electrical",
            "type":"Services"
        }
    ],
    "sg:phone":"+1 914 381 1940",
    "sg:postcode":"10543",
    "sg:province":"NY",
    "sg:tags":[
        "equipment",
        "fixtures-wholesale",
        "lighting",
        "manufacturer",
        "contractor"
    ],
    "wof:name":"Cangianni Electrical Inc",
    "wof:placetype":"venue"
},
  "geometry": {"coordinates":[-73.737482,40.959594],"type":"Point"}
}