{
  "type": "Feature",
  "properties": {
    "iso:country":"US",
    "sg:address":"80 Debora Dr",
    "sg:city":"Plainview",
    "sg:classifiers":[
        {
            "category":"Arts & Performance",
            "subcategory":"Theater",
            "type":"Entertainment"
        }
    ],
    "sg:phone":"+1   ",
    "sg:postcode":"11803",
    "sg:province":"NY",
    "sg:tags":[
        "theatrical"
    ],
    "wof:name":"Best Modern Theatre",
    "wof:placetype":"venue"
},
  "geometry": {"coordinates":[-73.474071,40.765987],"type":"Point"}
}