{
  "type": "Feature",
  "properties": {
    "addr:full":"927 Franklin Ave Garden City NY 11530",
    "addr:housenumber":"927",
    "addr:postcode":"11530",
    "addr:street":"Franklin Ave",
    "iso:country":"US",
    "sg:address":"927 Franklin Ave",
    "sg:city":"Garden City",
    "sg:classifiers":[
        {
            "category":"Deli",
            "type":"Food & Drink"
        },
        {
            "category":"Cafe",
            "type":"Food & Drink"
        }
    ],
    "sg:menulink":"http://www.allmenus.com/ny/garden-city/233633-mahalo-natural--ogranic-cafe/menu/",
    "sg:phone":"+1 516 663 0920",
    "sg:postcode":"11530",
    "sg:province":"NY",
    "sg:tags":[
        "american"
    ],
    "wof:name":"Mahalo Natural & Ogranic Cafe",
    "wof:placetype":"venue"
},
  "geometry": {"coordinates":[-73.635238,40.728534],"type":"Point"}
}