{
  "type": "Feature",
  "properties": {
    "addr:full":"13 N Franklin St Hempstead NY 11550",
    "addr:housenumber":"13",
    "addr:postcode":"11550",
    "addr:street":"N Franklin St",
    "iso:country":"US",
    "sg:address":"13 N Franklin St",
    "sg:city":"Hempstead",
    "sg:classifiers":[
        {
            "category":"Local Transit",
            "type":"Transportation"
        }
    ],
    "sg:phone":"+1   ",
    "sg:postcode":"11550",
    "sg:province":"NY",
    "sg:tags":[
        "medical"
    ],
    "wof:name":"Latino Livery Service",
    "wof:placetype":"venue"
},
  "geometry": {"coordinates":[-73.62652199999999,40.706374],"type":"Point"}
}