{
  "type": "Feature",
  "properties": {
    "addr:full":"13809 20th Ave College Point NY 11356",
    "addr:housenumber":"13809",
    "addr:postcode":"11356",
    "addr:street":"20Th Ave",
    "iso:country":"US",
    "sg:address":"13809 20th Ave",
    "sg:city":"College Point",
    "sg:classifiers":[
        {
            "category":"Fast Food",
            "type":"Food & Drink"
        }
    ],
    "sg:phone":"+1 718 358 1177",
    "sg:postcode":"11356",
    "sg:province":"NY",
    "sg:website":"www.mcdonalds.com",
    "wof:name":"McDonald's",
    "wof:placetype":"venue"
},
  "geometry": {"coordinates":[-73.830027,40.781709],"type":"Point"}
}