{
  "type": "Feature",
  "properties": {
    "iso:country":"US",
    "sg:address":"601 Turner Pl",
    "sg:city":"Ithaca",
    "sg:classifiers":[
        {
            "category":"Organizations",
            "subcategory":"Religious Organization",
            "type":"Services"
        }
    ],
    "sg:phone":"+1 607 273 3919",
    "sg:postcode":"14850",
    "sg:province":"NY",
    "sg:tags":[
        "clergy"
    ],
    "wof:name":"Earl E Andrews",
    "wof:placetype":"venue"
},
  "geometry": {"coordinates":[-76.496613,42.434422],"type":"Point"}
}