{
  "type": "Feature",
  "properties": {
    "iso:country":"US",
    "sg:address":"8925 W Main St",
    "sg:city":"Honeoye",
    "sg:classifiers":[
        {
            "category":"Autos & Motor Vehicles",
            "subcategory":"Automobile Sales",
            "type":"Retail Goods"
        }
    ],
    "sg:phone":"+1 585 229 2088",
    "sg:postcode":"14471",
    "sg:province":"NY",
    "sg:tags":[
        "car",
        "dealer"
    ],
    "wof:name":"DAT Enterprises",
    "wof:placetype":"venue"
},
  "geometry": {"coordinates":[-77.517628,42.790271],"type":"Point"}
}