{
  "type": "Feature",
  "properties": {
    "iso:country":"US",
    "sg:address":"367 Horseblock Rd",
    "sg:city":"Farmingville",
    "sg:classifiers":[
        {
            "category":"Utilities",
            "subcategory":"Mobile Phone",
            "type":"Services"
        }
    ],
    "sg:phone":"+1 631 716 3355",
    "sg:postcode":"11738",
    "sg:province":"NY",
    "sg:tags":[
        "telephone",
        "cellular"
    ],
    "wof:name":"Wireless Hut",
    "wof:placetype":"venue"
},
  "geometry": {"coordinates":[-73.04883,40.836102],"type":"Point"}
}