{
  "type": "Feature",
  "properties": {
    "iso:country":"US",
    "sg:address":"1455 Myrtle Ave",
    "sg:city":"Brooklyn",
    "sg:classifiers":[
        {
            "category":"Professional",
            "subcategory":"Lawyer & Legal Services",
            "type":"Services"
        }
    ],
    "sg:phone":"+1 718 487 0800",
    "sg:postcode":"11237",
    "sg:province":"NY",
    "wof:name":"Brooklyn Legal Svc",
    "wof:placetype":"venue"
},
  "geometry": {"coordinates":[-73.918043,40.698899],"type":"Point"}
}