{
  "type": "Feature",
  "properties": {
    "iso:country":"US",
    "sg:address":"1220 Broadway",
    "sg:city":"New York",
    "sg:classifiers":[
        {
            "category":"Parking",
            "type":"Transportation"
        }
    ],
    "sg:phone":"+1 212 244 5064",
    "sg:postcode":"10001",
    "sg:province":"NY",
    "sg:tags":[
        "garage"
    ],
    "wof:name":"Ezey Parking Systems",
    "wof:placetype":"venue"
},
  "geometry": {"coordinates":[-73.988305,40.747535],"type":"Point"}
}