{
  "type": "Feature",
  "properties": {
    "addr:full":"450 Bronxville Rd Bronxville NY 10708",
    "addr:housenumber":"450",
    "addr:postcode":"10708",
    "addr:street":"Bronxville Rd",
    "iso:country":"US",
    "sg:address":"450 Bronxville Rd",
    "sg:city":"Bronxville",
    "sg:classifiers":[
        {
            "category":"Professional",
            "subcategory":"Computer Services",
            "type":"Services"
        },
        {
            "category":"Shopping",
            "subcategory":"Computers & Home Electronics",
            "type":"Retail Goods"
        }
    ],
    "sg:phone":"+1 914 337 9030",
    "sg:postcode":"10708",
    "sg:province":"NY",
    "sg:tags":[
        "custom",
        "programing",
        "software"
    ],
    "sg:website":"www.costguard.com",
    "wof:name":"At-Your-Service Software Inc",
    "wof:placetype":"venue"
},
  "geometry": {"coordinates":[-73.841199,40.94978],"type":"Point"}
}