{
  "type": "Feature",
  "properties": {
    "addr:full":"31 Eastlake Dr Thiells NY 10984",
    "addr:housenumber":"31",
    "addr:postcode":"10984",
    "addr:street":"Eastlake Dr",
    "iso:country":"US",
    "sg:address":"31 Eastlake Dr",
    "sg:city":"Thiells",
    "sg:classifiers":[
        {
            "category":"Building & Trades",
            "subcategory":"Construction",
            "type":"Services"
        }
    ],
    "sg:phone":"+1 845 429 1434",
    "sg:postcode":"10984",
    "sg:province":"NY",
    "sg:tags":[
        "contractor"
    ],
    "wof:name":"Ramapo Fence",
    "wof:placetype":"venue"
},
  "geometry": {"coordinates":[-74.013891,41.211551],"type":"Point"}
}