{
  "type": "Feature",
  "properties": {
    "addr:full":"135 E 65 St New York NY 10065",
    "addr:housenumber":"135;65",
    "addr:postcode":"10065",
    "addr:street":"E;St",
    "iso:country":"US",
    "sg:address":"135 E 65 St",
    "sg:city":"New York",
    "sg:classifiers":[
        {
            "category":"Professional",
            "subcategory":"Management & Consulting",
            "type":"Services"
        }
    ],
    "sg:phone":"+1 212 288 5676",
    "sg:postcode":"10065",
    "sg:province":"NY",
    "sg:tags":[
        "strategic",
        "creative"
    ],
    "wof:name":"Lpny",
    "wof:placetype":"venue"
},
  "geometry": {"coordinates":[-73.966567,40.766694],"type":"Point"}
}