{
  "type": "Feature",
  "properties": {
    "iso:country":"US",
    "sg:address":"743 E 243rd St",
    "sg:city":"Bronx",
    "sg:classifiers":[
        {
            "category":"Health Services",
            "subcategory":"Nursing And Care Facility",
            "type":"Services"
        }
    ],
    "sg:phone":"+1 718 994 6545",
    "sg:postcode":"10470",
    "sg:province":"NY",
    "sg:tags":[
        "home",
        "convalescent"
    ],
    "wof:name":"Catholic Guardian Soc Home",
    "wof:placetype":"venue"
},
  "geometry": {"coordinates":[-73.847747,40.906184],"type":"Point"}
}