{
  "type": "Feature",
  "properties": {
    "addr:full":"71 E Carmans Rd Farmingdale NY 11735",
    "addr:housenumber":"71",
    "addr:postcode":"11735",
    "addr:street":"E Carmans Rd",
    "iso:country":"US",
    "sg:address":"71 E Carmans Rd",
    "sg:city":"Farmingdale",
    "sg:classifiers":[
        {
            "category":"Shopping",
            "subcategory":"Clothing, Apparel, & Fashions",
            "type":"Retail Goods"
        }
    ],
    "sg:phone":"+1 631 293 0410",
    "sg:postcode":"11735",
    "sg:province":"NY",
    "sg:tags":[
        "designer"
    ],
    "wof:name":"Dresses For Less",
    "wof:placetype":"venue"
},
  "geometry": {"coordinates":[-73.426382,40.732934],"type":"Point"}
}