{
  "type": "Feature",
  "properties": {
    "iso:country":"US",
    "sg:address":"3849 State Rte 5 and 20",
    "sg:city":"Canandaigua",
    "sg:classifiers":[
        {
            "category":"Freight",
            "type":"Transportation"
        }
    ],
    "sg:phone":"+1   ",
    "sg:postcode":"14424",
    "sg:province":"NY",
    "sg:tags":[
        "self",
        "storage"
    ],
    "wof:name":"Brookside of Hopewell",
    "wof:placetype":"venue"
},
  "geometry": {"coordinates":[-77.213859,42.863946],"type":"Point"}
}