{
  "type": "Feature",
  "properties": {
    "iso:country":"US",
    "sg:address":"282 Columbia St",
    "sg:city":"Cohoes",
    "sg:classifiers":[
        {
            "category":"Retail",
            "subcategory":"Funeral Services",
            "type":"Services"
        }
    ],
    "sg:phone":"+1 518 237 5931",
    "sg:postcode":"12047",
    "sg:province":"NY",
    "sg:tags":[
        "director"
    ],
    "wof:name":"A G Boivin's Sons Funeral Home",
    "wof:placetype":"venue"
},
  "geometry": {"coordinates":[-73.715311,42.772518],"type":"Point"}
}