{
  "type": "Feature",
  "properties": {
    "iso:country":"US",
    "sg:address":"33 Walt Whitman Rd",
    "sg:city":"Huntington Station",
    "sg:classifiers":[
        {
            "category":"Wholesale",
            "subcategory":"Non-durable Goods",
            "type":"Manufacturing & Wholesale Goods"
        }
    ],
    "sg:phone":"+1 631 424 2000",
    "sg:postcode":"11746",
    "sg:province":"NY",
    "sg:tags":[
        "packaging",
        "broker"
    ],
    "wof:name":"Jespen Industries Inc",
    "wof:placetype":"venue"
},
  "geometry": {"coordinates":[-73.41129599999999,40.82951],"type":"Point"}
}