{
  "type": "Feature",
  "properties": {
    "iso:country":"US",
    "sg:address":"613 Pine Ave",
    "sg:city":"Niagara Falls",
    "sg:classifiers":[
        {
            "category":"Personal",
            "subcategory":"Beauty Salon",
            "type":"Services"
        }
    ],
    "sg:phone":"+1 716 282 2806",
    "sg:postcode":"14301",
    "sg:province":"NY",
    "sg:tags":[
        "shop"
    ],
    "wof:name":"Albert's World Of Coiffures",
    "wof:placetype":"venue"
},
  "geometry": {"coordinates":[-79.055179,43.094428],"type":"Point"}
}