{
  "type": "Feature",
  "properties": {
    "addr:full":"3204 3rd Ave Bronx NY 10451",
    "addr:housenumber":"3204",
    "addr:postcode":"10451",
    "addr:street":"3Rd Ave",
    "iso:country":"US",
    "sg:address":"3204 3rd Ave",
    "sg:city":"Bronx",
    "sg:classifiers":[
        {
            "category":"Restaurant",
            "type":"Food & Drink"
        }
    ],
    "sg:phone":"+1 718 585 1373",
    "sg:postcode":"10451",
    "sg:province":"NY",
    "wof:name":"Pan-Americana",
    "wof:placetype":"venue"
},
  "geometry": {"coordinates":[-73.90866800000001,40.823974],"type":"Point"}
}