{
  "type": "Feature",
  "properties": {
    "iso:country":"US",
    "sg:address":"16 Windsor Rd",
    "sg:city":"Massena",
    "sg:classifiers":[
        {
            "category":"Health Services",
            "subcategory":"Doctor",
            "type":"Services"
        }
    ],
    "sg:phone":"+1   ",
    "sg:postcode":"13662",
    "sg:province":"NY",
    "wof:name":"Carl R Scruggs DDS",
    "wof:placetype":"venue"
},
  "geometry": {"coordinates":[-74.90544800000001,44.926437],"type":"Point"}
}