{
  "type": "Feature",
  "properties": {
    "iso:country":"US",
    "sg:address":"82 Glen Cove Rd",
    "sg:city":"Greenvale",
    "sg:classifiers":[
        {
            "category":"Health Services",
            "subcategory":"Doctor",
            "type":"Services"
        }
    ],
    "sg:phone":"+1   ",
    "sg:postcode":"11548",
    "sg:province":"NY",
    "sg:tags":[
        "dentist"
    ],
    "wof:name":"Witold R Wegorzewski",
    "wof:placetype":"venue"
},
  "geometry": {"coordinates":[-73.626497,40.814862],"type":"Point"}
}