{
  "type": "Feature",
  "properties": {
    "iso:country":"US",
    "sg:address":"316 5th Ave",
    "sg:city":"New York",
    "sg:classifiers":[
        {
            "category":"Health Services",
            "subcategory":"Health Practitioner",
            "type":"Services"
        }
    ],
    "sg:phone":"+1 212 868 0946",
    "sg:postcode":"10001",
    "sg:province":"NY",
    "sg:tags":[
        "nurse",
        "registry"
    ],
    "wof:name":"Foster Nurses Agency",
    "wof:placetype":"venue"
},
  "geometry": {"coordinates":[-73.985811,40.74674],"type":"Point"}
}