{
  "type": "Feature",
  "properties": {
    "iso:country":"US",
    "sg:address":"867 E 23rd St",
    "sg:city":"Brooklyn",
    "sg:classifiers":[
        {
            "category":"Organizations",
            "subcategory":"Religious Organization",
            "type":"Services"
        }
    ],
    "sg:phone":"+1 718 692 4357",
    "sg:postcode":"11210",
    "sg:province":"NY",
    "sg:tags":[
        "clergy"
    ],
    "wof:name":"T Plotsker",
    "wof:placetype":"venue"
},
  "geometry": {"coordinates":[-73.954003,40.629276],"type":"Point"}
}