{
  "type": "Feature",
  "properties": {
    "iso:country":"US",
    "sg:address":"1785 Wildey Rd",
    "sg:city":"Nunda",
    "sg:classifiers":[
        {
            "category":"Arena",
            "subcategory":"Sports Club",
            "type":"Entertainment"
        }
    ],
    "sg:phone":"+1 585 943 2681",
    "sg:postcode":"14517",
    "sg:province":"NY",
    "sg:tags":[
        "soccer"
    ],
    "wof:name":"Skills N Drills",
    "wof:placetype":"venue"
},
  "geometry": {"coordinates":[-77.951926,42.606604],"type":"Point"}
}