{
  "type": "Feature",
  "properties": {
    "addr:full":"361 Hillside Ave Williston Park NY 11596",
    "addr:housenumber":"361",
    "addr:postcode":"11596",
    "addr:street":"Hillside Ave",
    "iso:country":"US",
    "sg:address":"361 Hillside Ave",
    "sg:city":"Williston Park",
    "sg:classifiers":[
        {
            "category":"Cafe",
            "type":"Food & Drink"
        },
        {
            "category":"Restaurant",
            "type":"Food & Drink"
        }
    ],
    "sg:menulink":"http://www.allmenus.com/ny/williston-park/233677-cafe-sport/menu/",
    "sg:phone":"+1 516 742 6540",
    "sg:postcode":"11596",
    "sg:province":"NY",
    "sg:tags":[
        "portuguese"
    ],
    "wof:name":"Cafe Sport",
    "wof:placetype":"venue"
},
  "geometry": {"coordinates":[-73.652575,40.754209],"type":"Point"}
}