{
  "type": "Feature",
  "properties": {
    "addr:full":"82 Lockrow Rd Troy NY 12180",
    "addr:housenumber":"82",
    "addr:postcode":"12180",
    "addr:street":"Lockrow Rd",
    "iso:country":"US",
    "sg:address":"82 Lockrow Rd",
    "sg:city":"Troy",
    "sg:classifiers":[
        {
            "category":"Professional",
            "subcategory":"Management & Consulting",
            "type":"Services"
        }
    ],
    "sg:phone":"+1 518 279 1877",
    "sg:postcode":"12180",
    "sg:province":"NY",
    "sg:tags":[
        "relation",
        "public"
    ],
    "wof:name":"Entertainment Mktg NY Stat",
    "wof:placetype":"venue"
},
  "geometry": {"coordinates":[-73.553197,42.776546],"type":"Point"}
}