{
  "type": "Feature",
  "properties": {
    "addr:full":"199 Riverhead Rd Westhampton Beach NY 11978",
    "addr:housenumber":"199",
    "addr:postcode":"11978",
    "addr:street":"Riverhead Rd",
    "iso:country":"US",
    "sg:address":"199 Riverhead Rd",
    "sg:city":"Westhampton Beach",
    "sg:classifiers":[
        {
            "category":"Utilities",
            "subcategory":"Natural Gas",
            "type":"Services"
        }
    ],
    "sg:phone":"+1   ",
    "sg:postcode":"11978",
    "sg:province":"NY",
    "wof:name":"Synergy Gas of Bennett 1772",
    "wof:placetype":"venue"
},
  "geometry": {"coordinates":[-72.646872,40.831285],"type":"Point"}
}