{
  "type": "Feature",
  "properties": {
    "addr:full":"1310 Stanford St Schenectady NY 12308",
    "addr:housenumber":"1310",
    "addr:postcode":"12308",
    "addr:street":"Stanford St",
    "iso:country":"US",
    "sg:address":"1310 Stanford St",
    "sg:city":"Schenectady",
    "sg:classifiers":[
        {
            "category":"Utilities",
            "subcategory":"Refuse",
            "type":"Services"
        }
    ],
    "sg:phone":"+1 518 393 2034",
    "sg:postcode":"12308",
    "sg:province":"NY",
    "sg:tags":[
        "garbage",
        "collection"
    ],
    "wof:name":"Accumulation Svc",
    "wof:placetype":"venue"
},
  "geometry": {"coordinates":[-73.922641,42.805343],"type":"Point"}
}