{
  "type": "Feature",
  "properties": {
    "addr:full":"23 Wiltshire Pl Bronxville NY 10708",
    "addr:housenumber":"23",
    "addr:postcode":"10708",
    "addr:street":"Wiltshire Pl",
    "iso:country":"US",
    "sg:address":"23 Wiltshire Pl",
    "sg:city":"Bronxville",
    "sg:classifiers":[
        {
            "category":"Education",
            "subcategory":"Special Training",
            "type":"Public Place"
        }
    ],
    "sg:phone":"+1 914 961 1364",
    "sg:postcode":"10708",
    "sg:province":"NY",
    "wof:name":"Rhythm & Song LLC",
    "wof:placetype":"venue"
},
  "geometry": {"coordinates":[-73.839359,40.949974],"type":"Point"}
}