{
  "type": "Feature",
  "properties": {
    "addr:full":"1000 Craigville Rd Chester NY 10918",
    "addr:housenumber":"1000",
    "addr:postcode":"10918",
    "addr:street":"Craigville Rd",
    "iso:country":"US",
    "sg:address":"1000 Craigville Rd",
    "sg:city":"Chester",
    "sg:classifiers":[
        {
            "category":"Building & Trades",
            "subcategory":"Electrical",
            "type":"Services"
        }
    ],
    "sg:phone":"+1 845 774 8166",
    "sg:postcode":"10918",
    "sg:province":"NY",
    "sg:tags":[
        "electric",
        "contractor"
    ],
    "wof:name":"BJS Electric",
    "wof:placetype":"venue"
},
  "geometry": {"coordinates":[-74.224214,41.37007],"type":"Point"}
}