{
  "type": "Feature",
  "properties": {
    "iso:country":"US",
    "sg:address":"101 E 2nd St",
    "sg:city":"Elmira",
    "sg:classifiers":[
        {
            "category":"Wholesale",
            "subcategory":"Electrical",
            "type":"Manufacturing & Wholesale Goods"
        }
    ],
    "sg:phone":"+1 607 733 9188",
    "sg:postcode":"14901",
    "sg:province":"NY",
    "sg:tags":[
        "equipment",
        "electric",
        "supply"
    ],
    "sg:website":"www.itbooth.com",
    "wof:name":"Booth Electric Supply",
    "wof:placetype":"venue"
},
  "geometry": {"coordinates":[-76.807311,42.092011],"type":"Point"}
}