{
  "type": "Feature",
  "properties": {
    "iso:country":"US",
    "sg:address":"99 Springfield Blvd",
    "sg:city":"Springfield Gardens",
    "sg:classifiers":[
        {
            "category":"Restaurant",
            "type":"Food & Drink"
        }
    ],
    "sg:menulink":"http://www.allmenus.com/ny/queens/236914-spring-gardens-restaurant/menu/",
    "sg:phone":"+1 718 341 4480",
    "sg:postcode":"11413",
    "sg:province":"NY",
    "sg:tags":[
        "american",
        "jamaican"
    ],
    "wof:name":"Spring Gardens Restaurant",
    "wof:placetype":"venue"
},
  "geometry": {"coordinates":[-73.758522,40.664716],"type":"Point"}
}