{
  "type": "Feature",
  "properties": {
    "iso:country":"US",
    "sg:address":"400 W End Ave",
    "sg:city":"New York",
    "sg:classifiers":[
        {
            "category":"Health Services",
            "subcategory":"Health Practitioner",
            "type":"Services"
        }
    ],
    "sg:phone":"+1 212 362 4098",
    "sg:postcode":"10024",
    "sg:province":"NY",
    "sg:tags":[
        "psychotherapist"
    ],
    "wof:name":"Jerry Agate",
    "wof:placetype":"venue"
},
  "geometry": {"coordinates":[-73.980648,40.784906],"type":"Point"}
}