{
  "type": "Feature",
  "properties": {
    "addr:full":"142 W 26th St New York NY 10001",
    "addr:housenumber":"142",
    "addr:postcode":"10001",
    "addr:street":"W 26Th St",
    "iso:country":"US",
    "sg:address":"142 W 26th St",
    "sg:city":"New York",
    "sg:classifiers":[
        {
            "category":"Professional",
            "subcategory":"Business Services",
            "type":"Services"
        }
    ],
    "sg:phone":"+1 718 638 3039",
    "sg:postcode":"10001",
    "sg:province":"NY",
    "wof:name":"Distinctive Floral",
    "wof:placetype":"venue"
},
  "geometry": {"coordinates":[-73.993375,40.745423],"type":"Point"}
}