{
  "type": "Feature",
  "properties": {
    "addr:full":"2114 Factory Outlet Blvd Niagara Falls NY 14304",
    "addr:housenumber":"2114",
    "addr:postcode":"14304",
    "addr:street":"Factory Outlet Blvd",
    "iso:country":"US",
    "sg:address":"2114 Factory Outlet Blvd",
    "sg:city":"Niagara Falls",
    "sg:classifiers":[
        {
            "category":"Retail",
            "subcategory":"Auto Repair",
            "type":"Services"
        }
    ],
    "sg:phone":"+1 716 297 9881",
    "sg:postcode":"14304",
    "sg:province":"NY",
    "sg:tags":[
        "automobile",
        "lubrication"
    ],
    "wof:name":"Valvoline Instant Oil Change",
    "wof:placetype":"venue"
},
  "geometry": {"coordinates":[-78.98045500000001,43.099488],"type":"Point"}
}