{
  "type": "Feature",
  "properties": {
    "addr:full":"1153 Coney Island Ave Brooklyn NY 11230",
    "addr:housenumber":"1153",
    "addr:postcode":"11230",
    "addr:street":"Coney Island Ave",
    "iso:country":"US",
    "sg:address":"1153 Coney Island Ave",
    "sg:city":"Brooklyn",
    "sg:classifiers":[
        {
            "category":"Retail",
            "subcategory":"Funeral Services",
            "type":"Services"
        }
    ],
    "sg:phone":"+1 718 854 6900",
    "sg:postcode":"11230",
    "sg:province":"NY",
    "sg:tags":[
        "cemetery"
    ],
    "wof:name":"West End Funeral Chapel",
    "wof:placetype":"venue"
},
  "geometry": {"coordinates":[-73.965897,40.629299],"type":"Point"}
}