{
  "type": "Feature",
  "properties": {
    "addr:full":"220 W 19 St New York NY 10011",
    "addr:housenumber":"220",
    "addr:postcode":"10011",
    "addr:street":"W 19 St",
    "iso:country":"US",
    "sg:address":"220 W 19 St",
    "sg:city":"New York",
    "sg:classifiers":[
        {
            "category":"Professional",
            "type":"Services"
        }
    ],
    "sg:phone":"+1 212 627 4157",
    "sg:postcode":"10011",
    "sg:province":"NY",
    "sg:tags":[
        "establishment"
    ],
    "wof:name":"Henry K LTD",
    "wof:placetype":"venue"
},
  "geometry": {"coordinates":[-74.000016,40.742609],"type":"Point"}
}