{
  "type": "Feature",
  "properties": {
    "addr:full":"87 Ellis St Staten Island NY 10307",
    "addr:housenumber":"87",
    "addr:postcode":"10307",
    "addr:street":"Ellis St",
    "iso:country":"US",
    "sg:address":"87 Ellis St",
    "sg:city":"Staten Island",
    "sg:classifiers":[
        {
            "category":"Bus Charters",
            "type":"Transportation"
        }
    ],
    "sg:phone":"+1 718 420 0167",
    "sg:postcode":"10307",
    "sg:province":"NY",
    "sg:tags":[
        "rental"
    ],
    "wof:name":"Us Coachways Inc",
    "wof:placetype":"venue"
},
  "geometry": {"coordinates":[-74.241714,40.517556],"type":"Point"}
}