{
  "type": "Feature",
  "properties": {
    "iso:country":"US",
    "sg:address":"3023 Brighton 6th St",
    "sg:city":"Brooklyn",
    "sg:classifiers":[
        {
            "category":"Building & Trades",
            "subcategory":"Construction",
            "type":"Services"
        }
    ],
    "sg:phone":"+1 718 332 5359",
    "sg:postcode":"11235",
    "sg:province":"NY",
    "sg:tags":[
        "house"
    ],
    "wof:name":"MBA Construction Company Inc",
    "wof:placetype":"venue"
},
  "geometry": {"coordinates":[-73.96153200000001,40.578185],"type":"Point"}
}