{
  "type": "Feature",
  "properties": {
    "addr:full":"3915 Millersport Hwy Buffalo NY 14228",
    "addr:housenumber":"3915",
    "addr:postcode":"14228",
    "addr:street":"Millersport Hwy",
    "iso:country":"US",
    "sg:address":"3915 Millersport Hwy",
    "sg:city":"Buffalo",
    "sg:classifiers":[
        {
            "category":"Organizations",
            "subcategory":"Religious Organization",
            "type":"Services"
        }
    ],
    "sg:phone":"+1 716 689 9832",
    "sg:postcode":"14228",
    "sg:province":"NY",
    "sg:tags":[
        "church"
    ],
    "wof:name":"Amherst Alliance Church",
    "wof:placetype":"venue"
},
  "geometry": {"coordinates":[-78.737853,43.043717],"type":"Point"}
}