{
  "type": "Feature",
  "properties": {
    "addr:full":"44 Butler Pl Brooklyn NY 11238",
    "addr:housenumber":"44",
    "addr:postcode":"11238",
    "addr:street":"Butler Pl",
    "iso:country":"US",
    "sg:address":"44 Butler Pl",
    "sg:city":"Brooklyn",
    "sg:classifiers":[
        {
            "category":"Real Estate",
            "subcategory":"Real Estate Agent",
            "type":"Services"
        }
    ],
    "sg:phone":"+1 718 783 6988",
    "sg:postcode":"11238",
    "sg:province":"NY",
    "sg:tags":[
        "management",
        "property"
    ],
    "wof:name":"Butler Plaza Condominium",
    "wof:placetype":"venue"
},
  "geometry": {"coordinates":[-73.9683,40.674999],"type":"Point"}
}