{
  "type": "Feature",
  "properties": {
    "addr:full":"84 Main St Binghamton NY 13905",
    "addr:housenumber":"84",
    "addr:postcode":"13905",
    "addr:street":"Main St",
    "iso:country":"US",
    "sg:address":"84 Main St",
    "sg:city":"Binghamton",
    "sg:classifiers":[
        {
            "category":"Health Services",
            "subcategory":"Health Practitioner",
            "type":"Services"
        }
    ],
    "sg:phone":"+1   ",
    "sg:postcode":"13905",
    "sg:province":"NY",
    "wof:name":"Bauer Edna Liebman",
    "wof:placetype":"venue"
},
  "geometry": {"coordinates":[-75.923931,42.100138],"type":"Point"}
}