{
  "type": "Feature",
  "properties": {
    "addr:full":"2875 Richmond Avenue Staten Island NY 10314",
    "addr:housenumber":"2875",
    "addr:postcode":"10314",
    "addr:street":"Richmond Avenue",
    "iso:country":"US",
    "sg:address":"2875 Richmond Avenue",
    "sg:city":"Staten Island",
    "sg:classifiers":[
        {
            "category":"Shopping",
            "subcategory":"Pharmacy",
            "type":"Retail Goods"
        },
        {
            "category":"Food & Beverages",
            "subcategory":"Groceries & Convenience Stores",
            "type":"Retail Goods"
        }
    ],
    "sg:phone":"+1 718 761 8484",
    "sg:postcode":"10314",
    "sg:province":"NY",
    "sg:tags":[
        "drugstore"
    ],
    "wof:name":"Pathmark Pharmacy of Richmond Av",
    "wof:placetype":"venue"
},
  "geometry": {"coordinates":[-74.169589,40.574858],"type":"Point"}
}