{
  "type": "Feature",
  "properties": {
    "addr:full":"535 N Union St Olean NY 14760",
    "addr:housenumber":"535",
    "addr:postcode":"14760",
    "addr:street":"N Union St",
    "iso:country":"US",
    "sg:address":"535 N Union St",
    "sg:city":"Olean",
    "sg:classifiers":[
        {
            "category":"Restaurant",
            "type":"Food & Drink"
        }
    ],
    "sg:phone":"+1 716 372 5030",
    "sg:postcode":"14760",
    "sg:province":"NY",
    "wof:name":"Sean Patrick's Pub & Grill",
    "wof:placetype":"venue"
},
  "geometry": {"coordinates":[-78.430024,42.085991],"type":"Point"}
}