{
  "type": "Feature",
  "properties": {
    "iso:country":"US",
    "sg:address":"7 Northway",
    "sg:city":"Bronxville",
    "sg:classifiers":[
        {
            "category":"Shopping",
            "subcategory":"Jewelry",
            "type":"Retail Goods"
        }
    ],
    "sg:phone":"+1   ",
    "sg:postcode":"10708",
    "sg:province":"NY",
    "wof:name":"Gold Castle Jewelry",
    "wof:placetype":"venue"
},
  "geometry": {"coordinates":[-73.814989,40.935196],"type":"Point"}
}