{
  "type": "Feature",
  "properties": {
    "addr:full":"155 Chambers Street New York NY 10007",
    "addr:housenumber":"155",
    "addr:postcode":"10007",
    "addr:street":"Chambers Street",
    "iso:country":"US",
    "sg:address":"155 Chambers Street",
    "sg:city":"New York",
    "sg:classifiers":[
        {
            "category":"Professional",
            "type":"Services"
        }
    ],
    "sg:phone":"+1 212 346 0632",
    "sg:postcode":"10007",
    "sg:province":"NY",
    "sg:tags":[
        "caterer"
    ],
    "wof:name":"The Burns Catering Group",
    "wof:placetype":"venue"
},
  "geometry": {"coordinates":[-74.010116,40.715914],"type":"Point"}
}