{
  "type": "Feature",
  "properties": {
    "addr:full":"4704 18th Ave Brooklyn NY 11204",
    "addr:housenumber":"4704",
    "addr:postcode":"11204",
    "addr:street":"18Th Ave",
    "iso:country":"US",
    "sg:address":"4704 18th Ave",
    "sg:city":"Brooklyn",
    "sg:classifiers":[
        {
            "category":"Professional",
            "subcategory":"Management & Consulting",
            "type":"Services"
        },
        {
            "category":"Shopping",
            "subcategory":"Gifts & Souvenirs",
            "type":"Retail Goods"
        }
    ],
    "sg:phone":"+1 718 871 7278",
    "sg:postcode":"11204",
    "sg:province":"NY",
    "sg:tags":[
        "party",
        "planning",
        "merchandise",
        "supply"
    ],
    "wof:name":"Exclusive Party Goods Inc",
    "wof:placetype":"venue"
},
  "geometry": {"coordinates":[-73.98047,40.628947],"type":"Point"}
}