{
  "type": "Feature",
  "properties": {
    "addr:full":"279 E 51st St Brooklyn NY 11203",
    "addr:housenumber":"279",
    "addr:postcode":"11203",
    "addr:street":"E 51St St",
    "iso:country":"US",
    "sg:address":"279 E 51st St",
    "sg:city":"Brooklyn",
    "sg:classifiers":[
        {
            "category":"Professional",
            "subcategory":"Management & Consulting",
            "type":"Services"
        }
    ],
    "sg:phone":"+1 718 953 9352",
    "sg:postcode":"11203",
    "sg:province":"NY",
    "wof:name":"Ees Management",
    "wof:placetype":"venue"
},
  "geometry": {"coordinates":[-73.929545,40.654175],"type":"Point"}
}