{
  "type": "Feature",
  "properties": {
    "addr:full":"6060 State Hwy 55 Swan Lake NY 12783",
    "addr:housenumber":"6060",
    "addr:postcode":"12783",
    "addr:street":"State Hwy 55",
    "iso:country":"US",
    "sg:address":"6060 State Hwy 55",
    "sg:city":"Swan Lake",
    "sg:classifiers":[
        {
            "category":"Retail",
            "subcategory":"Auto Repair",
            "type":"Services"
        }
    ],
    "sg:phone":"+1 845 292 6440",
    "sg:postcode":"12783",
    "sg:province":"NY",
    "sg:tags":[
        "repairing",
        "automobile"
    ],
    "wof:name":"Cara's Used Cars & Auto Repair",
    "wof:placetype":"venue"
},
  "geometry": {"coordinates":[-74.78210199999999,41.752151],"type":"Point"}
}