{
  "type": "Feature",
  "properties": {
    "iso:country":"US",
    "sg:address":"307 Sobieski St",
    "sg:city":"Buffalo",
    "sg:classifiers":[
        {
            "category":"Health Services",
            "subcategory":"Nursing And Care Facility",
            "type":"Services"
        }
    ],
    "sg:phone":"+1 716 886 2525",
    "sg:postcode":"14211",
    "sg:province":"NY",
    "sg:tags":[
        "home",
        "retirement",
        "community"
    ],
    "wof:name":"Kowal Apartments",
    "wof:placetype":"venue"
},
  "geometry": {"coordinates":[-78.832594,42.901476],"type":"Point"}
}