{
  "type": "Feature",
  "properties": {
    "iso:country":"US",
    "sg:address":"2370 Coney Island Avenue",
    "sg:city":"Brooklyn",
    "sg:classifiers":[
        {
            "category":"Shopping",
            "subcategory":"Mobile Phones",
            "type":"Retail Goods"
        }
    ],
    "sg:phone":"+1 800 893 1387",
    "sg:postcode":"11223",
    "sg:province":"NY",
    "wof:name":"Mishanie Moshe",
    "wof:placetype":"venue"
},
  "geometry": {"coordinates":[-73.961427,40.600171],"type":"Point"}
}