{
  "type": "Feature",
  "properties": {
    "addr:full":"228 Maple Dr Fayetteville NY 13066",
    "addr:housenumber":"228",
    "addr:postcode":"13066",
    "addr:street":"Maple Dr",
    "iso:country":"US",
    "sg:address":"228 Maple Dr",
    "sg:city":"Fayetteville",
    "sg:classifiers":[
        {
            "category":"Wholesale",
            "subcategory":"Machinery & Supplies",
            "type":"Manufacturing & Wholesale Goods"
        }
    ],
    "sg:phone":"+1 315 449 0978",
    "sg:postcode":"13066",
    "sg:province":"NY",
    "sg:tags":[
        "new",
        "industrial",
        "used",
        "equipment"
    ],
    "wof:name":"Fitzsimmons Capital Equipment",
    "wof:placetype":"venue"
},
  "geometry": {"coordinates":[-76.05446000000001,43.028657],"type":"Point"}
}