{
  "type": "Feature",
  "properties": {
    "addr:full":"82 Allison Rd Waddington NY 13694",
    "addr:housenumber":"82",
    "addr:postcode":"13694",
    "addr:street":"Allison Rd",
    "iso:country":"US",
    "sg:address":"82 Allison Rd",
    "sg:city":"Waddington",
    "sg:classifiers":[
        {
            "category":"Social Services",
            "subcategory":"Adult Care",
            "type":"Services"
        }
    ],
    "sg:phone":"+1 315 388 5868",
    "sg:postcode":"13694",
    "sg:province":"NY",
    "sg:tags":[
        "home",
        "group"
    ],
    "wof:name":"St Lawrence NYSARC Inc",
    "wof:placetype":"venue"
},
  "geometry": {"coordinates":[-75.173942,44.846832],"type":"Point"}
}