{
  "type": "Feature",
  "properties": {
    "addr:full":"4501 4th Ave Brooklyn NY 11220",
    "addr:housenumber":"4501",
    "addr:postcode":"11220",
    "addr:street":"4Th Ave",
    "iso:country":"US",
    "sg:address":"4501 4th Ave",
    "sg:city":"Brooklyn",
    "sg:classifiers":[
        {
            "category":"Food & Beverages",
            "subcategory":"Bakery",
            "type":"Retail Goods"
        }
    ],
    "sg:phone":"+1 718 853 5165",
    "sg:postcode":"11220",
    "sg:province":"NY",
    "sg:tags":[
        "baker"
    ],
    "wof:name":"Savoy 4 Bakery Inc",
    "wof:placetype":"venue"
},
  "geometry": {"coordinates":[-74.00949900000001,40.649101],"type":"Point"}
}