{
  "type": "Feature",
  "properties": {
    "addr:full":"1260 6 Ave New York NY 10020",
    "addr:housenumber":"1260",
    "addr:postcode":"10020",
    "addr:street":"6 Ave",
    "iso:country":"US",
    "sg:address":"1260 6 Ave",
    "sg:city":"New York",
    "sg:classifiers":[
        {
            "category":"Retail",
            "subcategory":"Repair Shop",
            "type":"Services"
        }
    ],
    "sg:phone":"+1 212 937 2995",
    "sg:postcode":"10020",
    "sg:province":"NY",
    "sg:tags":[
        "lock",
        "locksmith"
    ],
    "wof:name":"Amnur Locksmith",
    "wof:placetype":"venue"
},
  "geometry": {"coordinates":[-73.980886,40.75927],"type":"Point"}
}