{
  "type": "Feature",
  "properties": {
    "addr:full":"3894 Park Ave Bronx NY 10457",
    "addr:housenumber":"3894",
    "addr:postcode":"10457",
    "addr:street":"Park Ave",
    "iso:country":"US",
    "sg:address":"3894 Park Ave",
    "sg:city":"Bronx",
    "sg:classifiers":[
        {
            "category":"Retail",
            "subcategory":"Auto Repair",
            "type":"Services"
        }
    ],
    "sg:phone":"+1 718 583 8250",
    "sg:postcode":"10457",
    "sg:province":"NY",
    "sg:tags":[
        "body",
        "shop"
    ],
    "wof:name":"Hi-Tech Auto Body",
    "wof:placetype":"venue"
},
  "geometry": {"coordinates":[-73.903397,40.839802],"type":"Point"}
}