{
  "type": "Feature",
  "properties": {
    "iso:country":"US",
    "sg:address":"3890 Griffin Rd",
    "sg:city":"Syracuse",
    "sg:classifiers":[
        {
            "category":"Building & Trades",
            "subcategory":"Cleaning & Sanitation",
            "type":"Services"
        }
    ],
    "sg:phone":"+1 315 469 1367",
    "sg:postcode":"13215",
    "sg:province":"NY",
    "sg:tags":[
        "property",
        "maintenance"
    ],
    "wof:name":"Onondaga Hill Property Mntnc",
    "wof:placetype":"venue"
},
  "geometry": {"coordinates":[-76.19213499999999,42.971286],"type":"Point"}
}