{
  "type": "Feature",
  "properties": {
    "iso:country":"US",
    "sg:address":"810 South St",
    "sg:city":"Peekskill",
    "sg:classifiers":[
        {
            "category":"Shopping",
            "type":"Retail Goods"
        }
    ],
    "sg:phone":"+1 914 739 9226",
    "sg:postcode":"10566",
    "sg:province":"NY",
    "sg:tags":[
        "candle"
    ],
    "wof:name":"Candles By Foster",
    "wof:placetype":"venue"
},
  "geometry": {"coordinates":[-73.922566,41.289437],"type":"Point"}
}