{
  "type": "Feature",
  "properties": {
    "addr:full":"1425 Amsterdam Ave New York NY 10027",
    "addr:housenumber":"1425",
    "addr:postcode":"10027",
    "addr:street":"Amsterdam Ave",
    "iso:country":"US",
    "sg:address":"1425 Amsterdam Ave",
    "sg:city":"New York",
    "sg:classifiers":[
        {
            "category":"Building & Trades",
            "subcategory":"Plumbing",
            "type":"Services"
        }
    ],
    "sg:phone":"+1 212 694 7211",
    "sg:postcode":"10027",
    "sg:province":"NY",
    "sg:tags":[
        "heating",
        "contractor"
    ],
    "wof:name":"American Maintenance Tech Svc",
    "wof:placetype":"venue"
},
  "geometry": {"coordinates":[-73.954122,40.816146],"type":"Point"}
}