{
  "type": "Feature",
  "properties": {
    "iso:country":"US",
    "sg:address":"227 S 2nd Ave",
    "sg:city":"Mechanicville",
    "sg:classifiers":[
        {
            "category":"Shopping",
            "type":"Retail Goods"
        }
    ],
    "sg:phone":"+1 518 664 4173",
    "sg:postcode":"12118",
    "sg:province":"NY",
    "sg:tags":[
        "merchandise",
        "monument"
    ],
    "wof:name":"Mechanicville Memorial Company",
    "wof:placetype":"venue"
},
  "geometry": {"coordinates":[-73.690918,42.900479],"type":"Point"}
}