{
  "type": "Feature",
  "properties": {
    "iso:country":"US",
    "sg:address":"1370 Pittsford Mendon Rd",
    "sg:city":"Mendon",
    "sg:classifiers":[
        {
            "category":"Banks & Credit Unions",
            "subcategory":"Investment Brokerage",
            "type":"Services"
        }
    ],
    "sg:phone":"+1 585 624 3650",
    "sg:postcode":"14506",
    "sg:province":"NY",
    "sg:tags":[
        "security"
    ],
    "wof:name":"Bullfinch Fund",
    "wof:placetype":"venue"
},
  "geometry": {"coordinates":[-77.505562,42.999977],"type":"Point"}
}