{
  "type": "Feature",
  "properties": {
    "iso:country":"US",
    "sg:address":"9038 Lake Rd",
    "sg:city":"Barker",
    "sg:classifiers":[
        {
            "category":"Personal",
            "type":"Services"
        }
    ],
    "sg:phone":"+1 716 795 3776",
    "sg:postcode":"14012",
    "sg:province":"NY",
    "sg:tags":[
        "therapist",
        "massage"
    ],
    "wof:name":"S M Austin Massage Therapy",
    "wof:placetype":"venue"
},
  "geometry": {"coordinates":[-78.52975600000001,43.346809],"type":"Point"}
}