{
  "type": "Feature",
  "properties": {
    "iso:country":"US",
    "sg:address":"9 Howard Ave",
    "sg:city":"White Plains",
    "sg:classifiers":[
        {
            "category":"Insurance",
            "subcategory":"Insurance Agent",
            "type":"Services"
        }
    ],
    "sg:phone":"+1 914 949 5343",
    "sg:postcode":"10606",
    "sg:province":"NY",
    "sg:tags":[
        "administrator",
        "pension"
    ],
    "wof:name":"Spt Pensions",
    "wof:placetype":"venue"
},
  "geometry": {"coordinates":[-73.771676,41.020189],"type":"Point"}
}