{
  "type": "Feature",
  "properties": {
    "addr:full":"6410 Fresh Pond Rd Ridgewood NY 11385",
    "addr:housenumber":"6410",
    "addr:postcode":"11385",
    "addr:street":"Fresh Pond Rd",
    "iso:country":"US",
    "sg:address":"6410 Fresh Pond Rd",
    "sg:city":"Ridgewood",
    "sg:classifiers":[
        {
            "category":"Bakery",
            "type":"Food & Drink"
        }
    ],
    "sg:phone":"+1 718 417 5700",
    "sg:postcode":"11385",
    "sg:province":"NY",
    "wof:name":"Catania Bakery",
    "wof:placetype":"venue"
},
  "geometry": {"coordinates":[-73.89919999999999,40.7099],"type":"Point"}
}