{
  "type": "Feature",
  "properties": {
    "iso:country":"US",
    "sg:address":"563 Ayrault Rd",
    "sg:city":"Fairport",
    "sg:classifiers":[
        {
            "category":"Building & Trades",
            "subcategory":"Construction",
            "type":"Services"
        }
    ],
    "sg:phone":"+1 585 388 9085",
    "sg:postcode":"14450",
    "sg:province":"NY",
    "sg:tags":[
        "house"
    ],
    "wof:name":"Robert Proderick General Rmdlg",
    "wof:placetype":"venue"
},
  "geometry": {"coordinates":[-77.452237,43.078983],"type":"Point"}
}