{
  "type": "Feature",
  "properties": {
    "addr:full":"860 United Nations Plz New York NY 10017",
    "addr:housenumber":"860",
    "addr:postcode":"10017",
    "addr:street":"United Nations Plz",
    "iso:country":"US",
    "sg:address":"860 United Nations Plz",
    "sg:city":"New York",
    "sg:classifiers":[
        {
            "category":"Wholesale",
            "subcategory":"Machinery & Supplies",
            "type":"Manufacturing & Wholesale Goods"
        },
        {
            "category":"Manufacturing",
            "subcategory":"Food",
            "type":"Manufacturing & Wholesale Goods"
        }
    ],
    "sg:phone":"+1 212 685 5171",
    "sg:postcode":"10017",
    "sg:province":"NY",
    "sg:tags":[
        "distiller",
        "industrial"
    ],
    "wof:name":"J Gerney & Co",
    "wof:placetype":"venue"
},
  "geometry": {"coordinates":[-73.966616,40.753243],"type":"Point"}
}