{
  "type": "Feature",
  "properties": {
    "iso:country":"US",
    "sg:address":"250 Dean St",
    "sg:city":"Brooklyn",
    "sg:classifiers":[
        {
            "category":"Building & Trades",
            "subcategory":"Locksmith",
            "type":"Services"
        }
    ],
    "sg:phone":"+1 347 464 3835",
    "sg:postcode":"11217",
    "sg:province":"NY",
    "sg:tags":[
        "key"
    ],
    "wof:name":"15 Street Lock Service",
    "wof:placetype":"venue"
},
  "geometry": {"coordinates":[-73.983576,40.684672],"type":"Point"}
}