{
  "type": "Feature",
  "properties": {
    "addr:full":"6330 Townline Rd Byron NY 14422",
    "addr:housenumber":"6330",
    "addr:postcode":"14422",
    "addr:street":"Townline Rd",
    "iso:country":"US",
    "sg:address":"6330 Townline Rd",
    "sg:city":"Byron",
    "sg:classifiers":[
        {
            "category":"Home & Garden",
            "subcategory":"Hardware",
            "type":"Retail Goods"
        }
    ],
    "sg:phone":"+1 585 548 2278",
    "sg:postcode":"14422",
    "sg:province":"NY",
    "sg:tags":[
        "store"
    ],
    "wof:name":"Do It Best",
    "wof:placetype":"venue"
},
  "geometry": {"coordinates":[-78.06389299999999,43.079676],"type":"Point"}
}