{
  "type": "Feature",
  "properties": {
    "iso:country":"US",
    "sg:address":"1350 Ave of the Americas",
    "sg:city":"New York",
    "sg:classifiers":[
        {
            "category":"Professional",
            "subcategory":"Lawyer & Legal Services",
            "type":"Services"
        }
    ],
    "sg:phone":"+1 212 957 3634",
    "sg:postcode":"10019",
    "sg:province":"NY",
    "sg:tags":[
        "attorney"
    ],
    "wof:name":"Bruce Fischer Atty At Law",
    "wof:placetype":"venue"
},
  "geometry": {"coordinates":[-73.978268,40.762638],"type":"Point"}
}