{
  "type": "Feature",
  "properties": {
    "addr:full":"246 5th Ave New York NY 10001",
    "addr:housenumber":"246",
    "addr:postcode":"10001",
    "addr:street":"5Th Ave",
    "iso:country":"US",
    "sg:address":"246 5th Ave",
    "sg:city":"New York",
    "sg:classifiers":[
        {
            "category":"Health Services",
            "subcategory":"Doctor",
            "type":"Services"
        }
    ],
    "sg:phone":"+1 212 679 6666",
    "sg:postcode":"10001",
    "sg:province":"NY",
    "wof:name":"Indo-Guayanese Trinidadian Medical Office",
    "wof:placetype":"venue"
},
  "geometry": {"coordinates":[-73.987396,40.744598],"type":"Point"}
}