{
  "type": "Feature",
  "properties": {
    "addr:full":"290 Madison Ave New York NY 10017",
    "addr:housenumber":"290",
    "addr:postcode":"10017",
    "addr:street":"Madison Ave",
    "iso:country":"US",
    "sg:address":"290 Madison Ave",
    "sg:city":"New York",
    "sg:classifiers":[
        {
            "category":"Professional",
            "type":"Services"
        }
    ],
    "sg:phone":"+1 212 213 3905",
    "sg:postcode":"10017",
    "sg:province":"NY",
    "sg:tags":[
        "establishment"
    ],
    "wof:name":"First Opinion",
    "wof:placetype":"venue"
},
  "geometry": {"coordinates":[-73.98000500000001,40.751867],"type":"Point"}
}