{
  "type": "Feature",
  "properties": {
    "addr:full":"76 Canton St Baldwinsville NY 13027",
    "addr:housenumber":"76",
    "addr:postcode":"13027",
    "addr:street":"Canton St",
    "iso:country":"US",
    "sg:address":"76 Canton St",
    "sg:city":"Baldwinsville",
    "sg:classifiers":[
        {
            "category":"Social Services",
            "type":"Services"
        }
    ],
    "sg:phone":"+1 315 638 2171",
    "sg:postcode":"13027",
    "sg:province":"NY",
    "sg:tags":[
        "organization",
        "welfare"
    ],
    "wof:name":"Baldwinsville Meals On Wheels",
    "wof:placetype":"venue"
},
  "geometry": {"coordinates":[-76.33483099999999,43.148158],"type":"Point"}
}