{
  "type": "Feature",
  "properties": {
    "addr:full":"4802 Ave M Brooklyn NY 11234",
    "addr:housenumber":"4802",
    "addr:postcode":"11234",
    "addr:street":"Ave M",
    "iso:country":"US",
    "sg:address":"4802 Ave M",
    "sg:city":"Brooklyn",
    "sg:classifiers":[
        {
            "category":"Real Estate",
            "subcategory":"Real Estate Agent",
            "type":"Services"
        }
    ],
    "sg:phone":"+1 718 377 1439",
    "sg:postcode":"11234",
    "sg:province":"NY",
    "wof:name":"Great Deal Realty Corp",
    "wof:placetype":"venue"
},
  "geometry": {"coordinates":[-73.928151,40.62122],"type":"Point"}
}