{
  "type": "Feature",
  "properties": {
    "iso:country":"US",
    "sg:address":"901 Quentin Road",
    "sg:city":"Brooklyn",
    "sg:classifiers":[
        {
            "category":"Education",
            "subcategory":"School",
            "type":"Public Place"
        }
    ],
    "sg:phone":"+1 718 375 7100",
    "sg:postcode":"11223",
    "sg:province":"NY",
    "sg:tags":[
        "high",
        "middle",
        "elementary"
    ],
    "wof:name":"Yeshiva Ateret Torah",
    "wof:placetype":"venue"
},
  "geometry": {"coordinates":[-73.96360300000001,40.607761],"type":"Point"}
}