{
  "type": "Feature",
  "properties": {
    "addr:full":"45 Red Cedar Ln Staten Island NY 10309",
    "addr:housenumber":"45",
    "addr:postcode":"10309",
    "addr:street":"Red Cedar Ln",
    "iso:country":"US",
    "sg:address":"45 Red Cedar Ln",
    "sg:city":"Staten Island",
    "sg:classifiers":[
        {
            "category":"Shopping",
            "subcategory":"Gifts & Souvenirs",
            "type":"Retail Goods"
        }
    ],
    "sg:phone":"+1 718 317 4999",
    "sg:postcode":"10309",
    "sg:province":"NY",
    "sg:tags":[
        "balloon",
        "artist"
    ],
    "wof:name":"Balloon Art",
    "wof:placetype":"venue"
},
  "geometry": {"coordinates":[-74.22219200000001,40.539532],"type":"Point"}
}