{
  "type": "Feature",
  "properties": {
    "iso:country":"US",
    "sg:address":"172 Columbia Tpke",
    "sg:city":"Rensselaer",
    "sg:classifiers":[
        {
            "category":"Shopping",
            "subcategory":"Florist",
            "type":"Retail Goods"
        }
    ],
    "sg:phone":"+1 518 477 6426",
    "sg:postcode":"12144",
    "sg:province":"NY",
    "wof:name":"Pam's Arrangement",
    "wof:placetype":"venue"
},
  "geometry": {"coordinates":[-73.73550899999999,42.6204],"type":"Point"}
}