{
  "type": "Feature",
  "properties": {
    "iso:country":"US",
    "sg:address":"116 West 23rd Street Suite 500",
    "sg:city":"New York",
    "sg:classifiers":[
        {
            "category":"Professional",
            "subcategory":"Computer Services",
            "type":"Services"
        }
    ],
    "sg:phone":"+1 206 438 1910",
    "sg:postcode":"10011",
    "sg:province":"NY",
    "sg:website":"http://www.groundtruth.com",
    "wof:name":"Ground Truth",
    "wof:placetype":"venue"
},
  "geometry": {"coordinates":[-73.99533,40.743838],"type":"Point"}
}