{
  "type": "Feature",
  "properties": {
    "addr:full":"525 11 Ave New York NY 10018",
    "addr:postcode":"10018",
    "addr:street":"525 11 Ave",
    "iso:country":"US",
    "sg:address":"525 11 Ave",
    "sg:city":"New York",
    "sg:classifiers":[
        {
            "category":"Travel",
            "subcategory":"Travel Agent",
            "type":"Entertainment"
        }
    ],
    "sg:phone":"+1 212 971 6306",
    "sg:postcode":"10018",
    "sg:province":"NY",
    "sg:tags":[
        "bus",
        "line",
        "agency"
    ],
    "wof:name":"Greyhound Bus Lines",
    "wof:placetype":"venue"
},
  "geometry": {"coordinates":[-74.000584,40.757692],"type":"Point"}
}