{
  "type": "Feature",
  "properties": {
    "addr:full":"220 Melville Rd Huntington Station NY 11746",
    "addr:housenumber":"220",
    "addr:postcode":"11746",
    "addr:street":"Melville Rd",
    "iso:country":"US",
    "sg:address":"220 Melville Rd",
    "sg:city":"Huntington Station",
    "sg:classifiers":[
        {
            "category":"Professional",
            "subcategory":"Computer Services",
            "type":"Services"
        }
    ],
    "sg:phone":"+1 631 549 6700",
    "sg:postcode":"11746",
    "sg:province":"NY",
    "sg:tags":[
        "design",
        "system"
    ],
    "wof:name":"Start Media Solutions Group",
    "wof:placetype":"venue"
},
  "geometry": {"coordinates":[-73.402103,40.817263],"type":"Point"}
}