{
  "type": "Feature",
  "properties": {
    "iso:country":"US",
    "sg:address":"1546 Hanover St",
    "sg:city":"Yorktown Heights",
    "sg:classifiers":[
        {
            "category":"Retail",
            "subcategory":"Repair Shop",
            "type":"Services"
        }
    ],
    "sg:phone":"+1 914 245 5276",
    "sg:postcode":"10598",
    "sg:province":"NY",
    "sg:tags":[
        "lock",
        "locksmith"
    ],
    "wof:name":"Cross County Lock & Alarm",
    "wof:placetype":"venue"
},
  "geometry": {"coordinates":[-73.771345,41.261474],"type":"Point"}
}