{
  "type": "Feature",
  "properties": {
    "addr:full":"101 Broad St Plattsburgh NY 12901",
    "addr:housenumber":"101",
    "addr:postcode":"12901",
    "addr:street":"Broad St",
    "iso:country":"US",
    "sg:address":"101 Broad St",
    "sg:city":"Plattsburgh",
    "sg:classifiers":[
        {
            "category":"Cafe",
            "type":"Food & Drink"
        }
    ],
    "sg:menulink":"http://www.allmenus.com/ny/plattsburgh/155751-wow-cafe--wingery/menu/",
    "sg:phone":"+1 518 564 2206",
    "sg:postcode":"12901",
    "sg:province":"NY",
    "sg:tags":[
        "american"
    ],
    "wof:name":"Wow Cafe & Wingery",
    "wof:placetype":"venue"
},
  "geometry": {"coordinates":[-73.464797,44.694894],"type":"Point"}
}