{
  "type": "Feature",
  "properties": {
    "iso:country":"US",
    "sg:address":"11 Park Pl",
    "sg:city":"New York",
    "sg:classifiers":[
        {
            "category":"Social Services",
            "type":"Services"
        }
    ],
    "sg:phone":"+1 212 962 7559",
    "sg:postcode":"10007",
    "sg:province":"NY",
    "sg:tags":[
        "organization",
        "welfare"
    ],
    "wof:name":"Ny Foundation-Senior Citizens",
    "wof:placetype":"venue"
},
  "geometry": {"coordinates":[-74.008785,40.713062],"type":"Point"}
}