{
  "type": "Feature",
  "properties": {
    "iso:country":"US",
    "sg:address":"40 Horseshoe Hill Rd",
    "sg:city":"Pound Ridge",
    "sg:classifiers":[
        {
            "category":"Health Services",
            "subcategory":"Health Practitioner",
            "type":"Services"
        }
    ],
    "sg:phone":"+1   ",
    "sg:postcode":"10576",
    "sg:province":"NY",
    "wof:name":"Rachel W Bush",
    "wof:placetype":"venue"
},
  "geometry": {"coordinates":[-73.57056,41.193446],"type":"Point"}
}