{
  "type": "Feature",
  "properties": {
    "addr:full":"3875 Bates Rd Medina NY 14103",
    "addr:housenumber":"3875",
    "addr:postcode":"14103",
    "addr:street":"Bates Rd",
    "iso:country":"US",
    "sg:address":"3875 Bates Rd",
    "sg:city":"Medina",
    "sg:classifiers":[
        {
            "category":"Recreation",
            "type":"Entertainment"
        },
        {
            "category":"Organizations",
            "subcategory":"Community Association",
            "type":"Services"
        }
    ],
    "sg:phone":"+1 585 798 0667",
    "sg:postcode":"14103",
    "sg:province":"NY",
    "sg:tags":[
        "club",
        "membership",
        "drinking"
    ],
    "wof:name":"Junior Wilson Sportmen's Club",
    "wof:placetype":"venue"
},
  "geometry": {"coordinates":[-78.37049399999999,43.224215],"type":"Point"}
}