{
  "type": "Feature",
  "properties": {
    "iso:country":"US",
    "sg:address":"27108 Union Tpke",
    "sg:city":"New Hyde Park",
    "sg:classifiers":[
        {
            "category":"Shopping",
            "subcategory":"Pharmacy",
            "type":"Retail Goods"
        }
    ],
    "sg:phone":"+1 718 347 3900",
    "sg:postcode":"11040",
    "sg:province":"NY",
    "sg:tags":[
        "drugstore"
    ],
    "wof:name":"Lakeville Pharmacy Corp",
    "wof:placetype":"venue"
},
  "geometry": {"coordinates":[-73.702797,40.751701],"type":"Point"}
}