{
  "type": "Feature",
  "properties": {
    "addr:full":"40 Mc Master St Ballston Spa NY 12020",
    "addr:housenumber":"40",
    "addr:postcode":"12020",
    "addr:street":"Mc Master St",
    "iso:country":"US",
    "sg:address":"40 Mc Master St",
    "sg:city":"Ballston Spa",
    "sg:classifiers":[
        {
            "category":"Government",
            "subcategory":"Office",
            "type":"Public Place"
        }
    ],
    "sg:phone":"+1 518 885 2225",
    "sg:postcode":"12020",
    "sg:province":"NY",
    "wof:name":"Saratoga County Personnel Dept",
    "wof:placetype":"venue"
},
  "geometry": {"coordinates":[-73.85004000000001,42.998862],"type":"Point"}
}