{
  "type": "Feature",
  "properties": {
    "iso:country":"US",
    "sg:address":"80 Boyce Rd",
    "sg:city":"Pine Bush",
    "sg:classifiers":[
        {
            "category":"Professional",
            "type":"Services"
        }
    ],
    "sg:phone":"+1 845 744 6080",
    "sg:postcode":"12566",
    "sg:province":"NY",
    "sg:tags":[
        "establishment"
    ],
    "wof:name":"GEIT Solutions",
    "wof:placetype":"venue"
},
  "geometry": {"coordinates":[-74.307503,41.616924],"type":"Point"}
}