{
  "type": "Feature",
  "properties": {
    "iso:country":"US",
    "sg:address":"9 N Windsor Ave",
    "sg:city":"Brightwaters",
    "sg:classifiers":[
        {
            "category":"Shopping",
            "subcategory":"Jewelry",
            "type":"Retail Goods"
        }
    ],
    "sg:phone":"+1 631 666 4181",
    "sg:postcode":"11718",
    "sg:province":"NY",
    "wof:name":"Gemaginations Ltd",
    "wof:placetype":"venue"
},
  "geometry": {"coordinates":[-73.266502,40.721401],"type":"Point"}
}