{
  "type": "Feature",
  "properties": {
    "iso:country":"US",
    "sg:address":"371 Central Ave",
    "sg:city":"Lawrence",
    "sg:classifiers":[
        {
            "category":"Health Services",
            "subcategory":"Doctor",
            "type":"Services"
        }
    ],
    "sg:phone":"+1 516 569 4700",
    "sg:postcode":"11559",
    "sg:province":"NY",
    "sg:tags":[
        "medical"
    ],
    "wof:name":"Mark Sperber MD",
    "wof:placetype":"venue"
},
  "geometry": {"coordinates":[-73.72694799999999,40.619299],"type":"Point"}
}