{
  "type": "Feature",
  "properties": {
    "iso:country":"US",
    "sg:address":"242 Buick Pl",
    "sg:city":"East Meadow",
    "sg:classifiers":[
        {
            "category":"Insurance",
            "subcategory":"Insurance Agent",
            "type":"Services"
        }
    ],
    "sg:phone":"+1 516 796 5649",
    "sg:postcode":"11554",
    "sg:province":"NY",
    "wof:name":"SMT Insurance",
    "wof:placetype":"venue"
},
  "geometry": {"coordinates":[-73.546887,40.732585],"type":"Point"}
}