{
  "type": "Feature",
  "properties": {
    "addr:full":"1585 Mc Donald St Bronx NY 10461",
    "addr:housenumber":"1585",
    "addr:postcode":"10461",
    "addr:street":"Mc Donald St",
    "iso:country":"US",
    "sg:address":"1585 Mc Donald St",
    "sg:city":"Bronx",
    "sg:classifiers":[
        {
            "category":"Retail",
            "subcategory":"Repair Shop",
            "type":"Services"
        }
    ],
    "sg:phone":"+1 347 293 0054",
    "sg:postcode":"10461",
    "sg:province":"NY",
    "sg:tags":[
        "lock",
        "locksmith"
    ],
    "wof:name":"1 Hour Emergency Locksmith",
    "wof:placetype":"venue"
},
  "geometry": {"coordinates":[-73.84298200000001,40.855416],"type":"Point"}
}