{
  "type": "Feature",
  "properties": {
    "iso:country":"US",
    "sg:address":"115 Lee Ave",
    "sg:city":"Brooklyn",
    "sg:classifiers":[
        {
            "category":"Shopping",
            "subcategory":"Pharmacy",
            "type":"Retail Goods"
        }
    ],
    "sg:phone":"+1 718 384 0234",
    "sg:postcode":"11211",
    "sg:province":"NY",
    "sg:tags":[
        "drugstore"
    ],
    "wof:name":"Shimon's Pharmacy",
    "wof:placetype":"venue"
},
  "geometry": {"coordinates":[-73.958702,40.7048],"type":"Point"}
}