{
  "type": "Feature",
  "properties": {
    "addr:full":"161 Centereach Mall Centereach NY 11720",
    "addr:housenumber":"161",
    "addr:postcode":"11720",
    "addr:street":"Centereach Mall",
    "iso:country":"US",
    "sg:address":"161 Centereach Mall",
    "sg:city":"Centereach",
    "sg:classifiers":[
        {
            "category":"Sports & Exercise",
            "subcategory":"Gym",
            "type":"Entertainment"
        }
    ],
    "sg:phone":"+1 631 737 1987",
    "sg:postcode":"11720",
    "sg:province":"NY",
    "sg:website":"www.planetfitness.com",
    "wof:name":"Planet Fitness - Long Island",
    "wof:placetype":"venue"
},
  "geometry": {"coordinates":[-73.262882,40.861347],"type":"Point"}
}