{
  "type": "Feature",
  "properties": {
    "iso:country":"US",
    "sg:address":"48 Lamar St",
    "sg:city":"West Babylon",
    "sg:classifiers":[
        {
            "category":"Manufacturing",
            "subcategory":"Signs",
            "type":"Manufacturing & Wholesale Goods"
        }
    ],
    "sg:phone":"+1 631 643 6366",
    "sg:postcode":"11704",
    "sg:province":"NY",
    "sg:tags":[
        "advertising",
        "specialty"
    ],
    "wof:name":"All Suffolk Neon & Sign",
    "wof:placetype":"venue"
},
  "geometry": {"coordinates":[-73.376929,40.733859],"type":"Point"}
}