{
  "type": "Feature",
  "properties": {
    "addr:full":"258 E 96th St Brooklyn NY 11212",
    "addr:housenumber":"258",
    "addr:postcode":"11212",
    "addr:street":"E 96Th St",
    "iso:country":"US",
    "sg:address":"258 E 96th St",
    "sg:city":"Brooklyn",
    "sg:classifiers":[
        {
            "category":"Personal",
            "subcategory":"Beauty Salon",
            "type":"Services"
        }
    ],
    "sg:phone":"+1 718 385 9440",
    "sg:postcode":"11212",
    "sg:province":"NY",
    "wof:name":"Hair Studio",
    "wof:placetype":"venue"
},
  "geometry": {"coordinates":[-73.920169,40.659845],"type":"Point"}
}