{
  "type": "Feature",
  "properties": {
    "iso:country":"US",
    "sg:address":"14 Whitwell Place",
    "sg:city":"Brooklyn",
    "sg:classifiers":[
        {
            "category":"Restaurant",
            "type":"Food & Drink"
        },
        {
            "category":"Food & Beverages",
            "subcategory":"Meat & Fish",
            "type":"Retail Goods"
        }
    ],
    "sg:phone":"+1 718 855 8887",
    "sg:postcode":"11215",
    "sg:province":"NY",
    "sg:tags":[
        "seafood",
        "market"
    ],
    "wof:name":"T J Kings Lobster",
    "wof:placetype":"venue"
},
  "geometry": {"coordinates":[-73.985713,40.676724],"type":"Point"}
}