{
  "type": "Feature",
  "properties": {
    "iso:country":"US",
    "sg:address":"97 E Genesee St Ste 4",
    "sg:city":"Skaneateles",
    "sg:classifiers":[
        {
            "category":"Personal",
            "type":"Services"
        }
    ],
    "sg:phone":"+1 315 685 5048",
    "sg:postcode":"13152",
    "sg:province":"NY",
    "sg:tags":[
        "assistant"
    ],
    "wof:name":"John Dau Foundation",
    "wof:placetype":"venue"
},
  "geometry": {"coordinates":[-76.423984,42.945213],"type":"Point"}
}