{
  "type": "Feature",
  "properties": {
    "addr:full":"628 Washington St Buffalo NY 14203",
    "addr:housenumber":"628",
    "addr:postcode":"14203",
    "addr:street":"Washington St",
    "iso:country":"US",
    "sg:address":"628 Washington St",
    "sg:city":"Buffalo",
    "sg:classifiers":[
        {
            "category":"Professional",
            "subcategory":"Printing & Photocopies",
            "type":"Services"
        }
    ],
    "sg:phone":"+1 716 853 2679",
    "sg:postcode":"14203",
    "sg:province":"NY",
    "wof:name":"Copy-Right USA Llc",
    "wof:placetype":"venue"
},
  "geometry": {"coordinates":[-78.87152500000001,42.89108],"type":"Point"}
}