{
  "type": "Feature",
  "properties": {
    "iso:country":"US",
    "sg:address":"1628 Winton Rd N",
    "sg:city":"Rochester",
    "sg:classifiers":[
        {
            "category":"Retail",
            "subcategory":"Auto Repair",
            "type":"Services"
        }
    ],
    "sg:phone":"+1 585 224 0290",
    "sg:postcode":"14609",
    "sg:province":"NY",
    "sg:tags":[
        "repairing",
        "automobile",
        "general"
    ],
    "wof:name":"Tony's Culver Atlantic",
    "wof:placetype":"venue"
},
  "geometry": {"coordinates":[-77.53854800000001,43.176061],"type":"Point"}
}