{
  "type": "Feature",
  "properties": {
    "addr:full":"10702 Crossbay Blvd Ozone Park NY 11417",
    "addr:housenumber":"10702",
    "addr:postcode":"11417",
    "addr:street":"Crossbay Blvd",
    "iso:country":"US",
    "sg:address":"10702 Crossbay Blvd",
    "sg:city":"Ozone Park",
    "sg:classifiers":[
        {
            "category":"Real Estate",
            "subcategory":"Real Estate Services",
            "type":"Services"
        }
    ],
    "sg:phone":"+1 718 835 5000",
    "sg:postcode":"11417",
    "sg:province":"NY",
    "sg:tags":[
        "management",
        "property"
    ],
    "wof:name":"Century Twenty One Fortune Realty",
    "wof:placetype":"venue"
},
  "geometry": {"coordinates":[-73.84451799999999,40.678751],"type":"Point"}
}