{
  "type": "Feature",
  "properties": {
    "addr:full":"78 W 3rd St New York NY 10012",
    "addr:housenumber":"78",
    "addr:postcode":"10012",
    "addr:street":"W 3Rd St",
    "iso:country":"US",
    "sg:address":"78 W 3rd St",
    "sg:city":"New York",
    "sg:classifiers":[
        {
            "category":"Deli",
            "type":"Food & Drink"
        }
    ],
    "sg:phone":"+1 212 777 2269",
    "sg:postcode":"10012",
    "sg:province":"NY",
    "wof:name":"West Third Street Deli",
    "wof:placetype":"venue"
},
  "geometry": {"coordinates":[-73.99859600000001,40.729801],"type":"Point"}
}