{
  "type": "Feature",
  "properties": {
    "addr:full":"5329 W Main St Amenia NY 12501",
    "addr:housenumber":"5329",
    "addr:postcode":"12501",
    "addr:street":"W Main St",
    "iso:country":"US",
    "sg:address":"5329 W Main St",
    "sg:city":"Amenia",
    "sg:classifiers":[
        {
            "category":"Restaurant",
            "type":"Food & Drink"
        }
    ],
    "sg:phone":"+1 845 373 7374",
    "sg:postcode":"12501",
    "sg:province":"NY",
    "sg:website":"www.subway.com",
    "wof:name":"Subway Sandwiches & Salads",
    "wof:placetype":"venue"
},
  "geometry": {"coordinates":[-73.55847799999999,41.84923],"type":"Point"}
}