{
  "type": "Feature",
  "properties": {
    "addr:full":"86 E 7th St New York NY 10003",
    "addr:housenumber":"86",
    "addr:postcode":"10003",
    "addr:street":"E 7Th St",
    "iso:country":"US",
    "sg:address":"86 E 7th St",
    "sg:city":"New York",
    "sg:classifiers":[
        {
            "category":"Coffee & Tea",
            "type":"Food & Drink"
        }
    ],
    "sg:phone":"+1 212 388 9731",
    "sg:postcode":"10003",
    "sg:province":"NY",
    "sg:website":"www.abraconyc.com/",
    "wof:name":"Abra?o",
    "wof:placetype":"venue"
},
  "geometry": {"coordinates":[-73.98602,40.727096],"type":"Point"}
}