{
  "type": "Feature",
  "properties": {
    "iso:country":"US",
    "sg:address":"140 Green Ln",
    "sg:city":"Bedford Hills",
    "sg:classifiers":[
        {
            "category":"Retail",
            "subcategory":"Auto Repair",
            "type":"Services"
        }
    ],
    "sg:phone":"+1 914 666 8443",
    "sg:postcode":"10507",
    "sg:province":"NY",
    "sg:tags":[
        "body",
        "automobile",
        "painting"
    ],
    "wof:name":"B C Motors",
    "wof:placetype":"venue"
},
  "geometry": {"coordinates":[-73.714344,41.226061],"type":"Point"}
}