{
  "type": "Feature",
  "properties": {
    "addr:full":"796 Deer Park Ave North Babylon NY 11703",
    "addr:housenumber":"796",
    "addr:postcode":"11703",
    "addr:street":"Deer Park Ave North",
    "iso:country":"US",
    "sg:address":"796 Deer Park Ave",
    "sg:city":"North Babylon",
    "sg:classifiers":[
        {
            "category":"Health Services",
            "subcategory":"Doctor",
            "type":"Services"
        }
    ],
    "sg:phone":"+1 631 321 1045",
    "sg:postcode":"11703",
    "sg:province":"NY",
    "sg:tags":[
        "physician",
        "surgeon"
    ],
    "wof:name":"Michael H Polcino PC",
    "wof:placetype":"venue"
},
  "geometry": {"coordinates":[-73.32278700000001,40.723311],"type":"Point"}
}