{
  "type": "Feature",
  "properties": {
    "addr:full":"121 Bolivar Rd Wellsville NY 14895",
    "addr:housenumber":"121",
    "addr:postcode":"14895",
    "addr:street":"Bolivar Rd",
    "iso:country":"US",
    "sg:address":"121 Bolivar Rd",
    "sg:city":"Wellsville",
    "sg:classifiers":[
        {
            "category":"Restaurant",
            "type":"Food & Drink"
        }
    ],
    "sg:menulink":"http://www.allmenus.com/ny/wellsville/86298-little-caesars-pizza/menu/",
    "sg:phone":"+1 585 593 0040",
    "sg:postcode":"14895",
    "sg:province":"NY",
    "sg:tags":[
        "american",
        "pizza"
    ],
    "wof:name":"Little Caesar's Pizza",
    "wof:placetype":"venue"
},
  "geometry": {"coordinates":[-77.962098,42.126158],"type":"Point"}
}