{
  "type": "Feature",
  "properties": {
    "addr:full":"1890 Forest Ave Staten Island NY 10303",
    "addr:housenumber":"1890",
    "addr:postcode":"10303",
    "addr:street":"Forest Ave",
    "iso:country":"US",
    "sg:address":"1890 Forest Ave",
    "sg:city":"Staten Island",
    "sg:classifiers":[
        {
            "category":"Organizations",
            "subcategory":"Religious Organization",
            "type":"Services"
        }
    ],
    "sg:phone":"+1 718 448 7273",
    "sg:postcode":"10303",
    "sg:province":"NY",
    "sg:tags":[
        "church"
    ],
    "wof:name":"Christ United Methodist Church",
    "wof:placetype":"venue"
},
  "geometry": {"coordinates":[-74.151534,40.625357],"type":"Point"}
}