{
  "type": "Feature",
  "properties": {
    "addr:full":"25 Bond St New York NY 10012",
    "addr:housenumber":"25",
    "addr:postcode":"10012",
    "addr:street":"Bond St",
    "iso:country":"US",
    "sg:address":"25 Bond St",
    "sg:city":"New York",
    "sg:classifiers":[
        {
            "category":"Professional",
            "subcategory":"Management & Consulting",
            "type":"Services"
        }
    ],
    "sg:phone":"+1 212 982 6537",
    "sg:postcode":"10012",
    "sg:province":"NY",
    "sg:tags":[
        "construction"
    ],
    "wof:name":"Morgan Construction Ny Inc",
    "wof:placetype":"venue"
},
  "geometry": {"coordinates":[-73.992324,40.725721],"type":"Point"}
}