{
  "type": "Feature",
  "properties": {
    "addr:full":"28 Track Dr Binghamton NY 13904",
    "addr:housenumber":"28",
    "addr:postcode":"13904",
    "addr:street":"Track Dr",
    "iso:country":"US",
    "sg:address":"28 Track Dr",
    "sg:city":"Binghamton",
    "sg:classifiers":[
        {
            "category":"Wholesale",
            "subcategory":"Toys & Hobbies",
            "type":"Manufacturing & Wholesale Goods"
        }
    ],
    "sg:phone":"+1 607 775 0615",
    "sg:postcode":"13904",
    "sg:province":"NY",
    "sg:tags":[
        "wholesaler"
    ],
    "wof:name":"Bridgewater Wholesale Inc",
    "wof:placetype":"venue"
},
  "geometry": {"coordinates":[-75.83775300000001,42.104645],"type":"Point"}
}