{
  "type": "Feature",
  "properties": {
    "addr:full":"3676 Maxwell Dr Wantagh NY 11793",
    "addr:housenumber":"3676",
    "addr:postcode":"11793",
    "addr:street":"Maxwell Dr",
    "iso:country":"US",
    "sg:address":"3676 Maxwell Dr",
    "sg:city":"Wantagh",
    "sg:classifiers":[
        {
            "category":"Professional",
            "subcategory":"Management & Consulting",
            "type":"Services"
        }
    ],
    "sg:phone":"+1   ",
    "sg:postcode":"11793",
    "sg:province":"NY",
    "wof:name":"Cole Communications & Mktg",
    "wof:placetype":"venue"
},
  "geometry": {"coordinates":[-73.498374,40.690987],"type":"Point"}
}