{
  "type": "Feature",
  "properties": {
    "addr:full":"401 W 14th St New York NY 10014",
    "addr:housenumber":"401",
    "addr:postcode":"10014",
    "addr:street":"W 14Th St",
    "iso:country":"US",
    "sg:address":"401 W 14th St",
    "sg:city":"New York",
    "sg:classifiers":[
        {
            "category":"Wholesale",
            "subcategory":"Computers",
            "type":"Manufacturing & Wholesale Goods"
        }
    ],
    "sg:phone":"+1 212 444 3400",
    "sg:postcode":"10014",
    "sg:province":"NY",
    "sg:website":"www.apple.com",
    "wof:name":"Apple Store",
    "wof:placetype":"venue"
},
  "geometry": {"coordinates":[-74.00547400000001,40.740992],"type":"Point"}
}