{
  "type": "Feature",
  "properties": {
    "addr:full":"320 Long Island Ave Wyandanch NY 11798",
    "addr:housenumber":"320",
    "addr:postcode":"11798",
    "addr:street":"Long Island Ave",
    "iso:country":"US",
    "sg:address":"320 Long Island Ave",
    "sg:city":"Wyandanch",
    "sg:classifiers":[
        {
            "category":"Taxi",
            "type":"Transportation"
        }
    ],
    "sg:phone":"+1   ",
    "sg:postcode":"11798",
    "sg:province":"NY",
    "sg:tags":[
        "taxicab"
    ],
    "wof:name":"Jds Transportation Inc",
    "wof:placetype":"venue"
},
  "geometry": {"coordinates":[-73.357972,40.754525],"type":"Point"}
}