{
  "type": "Feature",
  "properties": {
    "addr:full":"6331 Genesee St Lancaster NY 14086",
    "addr:housenumber":"6331",
    "addr:postcode":"14086",
    "addr:street":"Genesee St",
    "iso:country":"US",
    "sg:address":"6331 Genesee St",
    "sg:city":"Lancaster",
    "sg:classifiers":[
        {
            "category":"Professional",
            "subcategory":"Computer Services",
            "type":"Services"
        }
    ],
    "sg:phone":"+1   ",
    "sg:postcode":"14086",
    "sg:province":"NY",
    "sg:tags":[
        "related"
    ],
    "wof:name":"Buffalo Info Tech",
    "wof:placetype":"venue"
},
  "geometry": {"coordinates":[-78.58038999999999,42.94689],"type":"Point"}
}