{
  "type": "Feature",
  "properties": {
    "iso:country":"US",
    "sg:address":"22 Musket Dr",
    "sg:city":"Shirley",
    "sg:classifiers":[
        {
            "category":"Building & Trades",
            "subcategory":"Construction",
            "type":"Services"
        }
    ],
    "sg:phone":"+1 631 399 2925",
    "sg:postcode":"11967",
    "sg:province":"NY",
    "sg:tags":[
        "general",
        "contractor"
    ],
    "wof:name":"Island Construction Co",
    "wof:placetype":"venue"
},
  "geometry": {"coordinates":[-72.872992,40.784444],"type":"Point"}
}