{
  "type": "Feature",
  "properties": {
    "iso:country":"US",
    "sg:address":"390 Emerson Pl",
    "sg:city":"Uniondale",
    "sg:classifiers":[
        {
            "category":"Professional",
            "subcategory":"Lawyer & Legal Services",
            "type":"Services"
        }
    ],
    "sg:phone":"+1 516 538 6767",
    "sg:postcode":"11553",
    "sg:province":"NY",
    "sg:tags":[
        "attorney"
    ],
    "wof:name":"Firm",
    "wof:placetype":"venue"
},
  "geometry": {"coordinates":[-73.587416,40.706375],"type":"Point"}
}