{
  "type": "Feature",
  "properties": {
    "addr:full":"9424 Farragut Rd Brooklyn NY 11236",
    "addr:housenumber":"9424",
    "addr:postcode":"11236",
    "addr:street":"Farragut Rd",
    "iso:country":"US",
    "sg:address":"9424 Farragut Rd",
    "sg:city":"Brooklyn",
    "sg:classifiers":[
        {
            "category":"Health Services",
            "subcategory":"Doctor",
            "type":"Services"
        }
    ],
    "sg:phone":"+1 718 257 0131",
    "sg:postcode":"11236",
    "sg:province":"NY",
    "sg:tags":[
        "medical"
    ],
    "wof:name":"Louise Devita MD",
    "wof:placetype":"venue"
},
  "geometry": {"coordinates":[-73.905739,40.645378],"type":"Point"}
}