{
  "type": "Feature",
  "properties": {
    "iso:country":"US",
    "sg:address":"2452 Flatbush Ave",
    "sg:city":"Brooklyn",
    "sg:classifiers":[
        {
            "category":"Professional",
            "subcategory":"Business Services",
            "type":"Services"
        }
    ],
    "sg:phone":"+1 718 859 6473",
    "sg:postcode":"11234",
    "sg:province":"NY",
    "sg:tags":[
        "interior",
        "consultant",
        "design",
        "decorator"
    ],
    "wof:name":"Paradise Decorators Inc",
    "wof:placetype":"venue"
},
  "geometry": {"coordinates":[-73.923867,40.611186],"type":"Point"}
}