{
  "type": "Feature",
  "properties": {
    "addr:full":"109 Celeste Ct Brooklyn NY 11229",
    "addr:housenumber":"109",
    "addr:postcode":"11229",
    "addr:street":"Celeste Ct",
    "iso:country":"US",
    "sg:address":"109 Celeste Ct",
    "sg:city":"Brooklyn",
    "sg:classifiers":[
        {
            "category":"Building & Trades",
            "subcategory":"Pest Control",
            "type":"Services"
        }
    ],
    "sg:phone":"+1 718 648 4713",
    "sg:postcode":"11229",
    "sg:province":"NY",
    "wof:name":"Prompt Certified Exterminators",
    "wof:placetype":"venue"
},
  "geometry": {"coordinates":[-73.93065300000001,40.595741],"type":"Point"}
}