{
  "type": "Feature",
  "properties": {
    "addr:full":"5633 Tower Hill Rd Byron NY 14422",
    "addr:housenumber":"5633",
    "addr:postcode":"14422",
    "addr:street":"Tower Hill Rd",
    "iso:country":"US",
    "sg:address":"5633 Tower Hill Rd",
    "sg:city":"Byron",
    "sg:classifiers":[
        {
            "category":"Farming",
            "subcategory":"Farm",
            "type":"Manufacturing & Wholesale Goods"
        }
    ],
    "sg:phone":"+1 585 548 7178",
    "sg:postcode":"14422",
    "sg:province":"NY",
    "sg:tags":[
        "crop",
        "general"
    ],
    "wof:name":"Zuber Farms A Partnership",
    "wof:placetype":"venue"
},
  "geometry": {"coordinates":[-78.106729,43.090832],"type":"Point"}
}