{
  "type": "Feature",
  "properties": {
    "iso:country":"US",
    "sg:address":"10 Edgewood Ave",
    "sg:city":"Smithtown",
    "sg:classifiers":[
        {
            "category":"Banks & Credit Unions",
            "subcategory":"Investment Brokerage",
            "type":"Services"
        }
    ],
    "sg:phone":"+1 631 863 2706",
    "sg:postcode":"11787",
    "sg:province":"NY",
    "sg:tags":[
        "investing",
        "consultant",
        "planning",
        "financial"
    ],
    "sg:website":"www.paragoncapitalonline.com",
    "wof:name":"Paragon Capital Management",
    "wof:placetype":"venue"
},
  "geometry": {"coordinates":[-73.20349899999999,40.856602],"type":"Point"}
}