{
  "type": "Feature",
  "properties": {
    "iso:country":"US",
    "sg:address":"1654 49th St",
    "sg:city":"Brooklyn",
    "sg:classifiers":[
        {
            "category":"Organizations",
            "subcategory":"Religious Organization",
            "type":"Services"
        }
    ],
    "sg:phone":"+1 718 851 0040",
    "sg:postcode":"11204",
    "sg:province":"NY",
    "sg:tags":[
        "clergy"
    ],
    "wof:name":"Joseph Schon",
    "wof:placetype":"venue"
},
  "geometry": {"coordinates":[-73.984127,40.630313],"type":"Point"}
}