{
  "type": "Feature",
  "properties": {
    "addr:full":"2761 E Henrietta Rd Henrietta NY 14623",
    "addr:housenumber":"2761",
    "addr:postcode":"14623",
    "addr:street":"E Henrietta Rd",
    "iso:country":"US",
    "sg:address":"2761 E Henrietta Rd",
    "sg:city":"Henrietta",
    "sg:classifiers":[
        {
            "category":"Personal",
            "subcategory":"Beauty Salon",
            "type":"Services"
        }
    ],
    "sg:phone":"+1 585 334 2440",
    "sg:postcode":"14623",
    "sg:province":"NY",
    "wof:name":"Vibe Salon & Spa",
    "wof:placetype":"venue"
},
  "geometry": {"coordinates":[-77.60923099999999,43.06556],"type":"Point"}
}