{
  "type": "Feature",
  "properties": {
    "addr:full":"125 Musgnug Ave Mineola NY 11501",
    "addr:housenumber":"125",
    "addr:postcode":"11501",
    "addr:street":"Musgnug Ave",
    "iso:country":"US",
    "sg:address":"125 Musgnug Ave",
    "sg:city":"Mineola",
    "sg:classifiers":[
        {
            "category":"Building & Trades",
            "subcategory":"Construction",
            "type":"Services"
        }
    ],
    "sg:phone":"+1 516 747 0236",
    "sg:postcode":"11501",
    "sg:province":"NY",
    "sg:tags":[
        "carpenter"
    ],
    "wof:name":"Gandarella Carpentry",
    "wof:placetype":"venue"
},
  "geometry": {"coordinates":[-73.64111699999999,40.750942],"type":"Point"}
}