{
  "type": "Feature",
  "properties": {
    "iso:country":"US",
    "sg:address":"106 Industrial St",
    "sg:city":"Rochester",
    "sg:classifiers":[
        {
            "category":"Building & Trades",
            "subcategory":"Construction",
            "type":"Services"
        }
    ],
    "sg:phone":"+1 585 454 6590",
    "sg:postcode":"14608",
    "sg:province":"NY",
    "sg:tags":[
        "paving",
        "driveway",
        "asphalt",
        "contractor"
    ],
    "wof:name":"Tandoi Paving Corporation",
    "wof:placetype":"venue"
},
  "geometry": {"coordinates":[-77.623025,43.156101],"type":"Point"}
}