{
  "type": "Feature",
  "properties": {
    "addr:full":"516 Cross St Watertown NY 13601",
    "addr:housenumber":"516",
    "addr:postcode":"13601",
    "addr:street":"Cross St",
    "iso:country":"US",
    "sg:address":"516 Cross St",
    "sg:city":"Watertown",
    "sg:classifiers":[
        {
            "category":"Building & Trades",
            "subcategory":"Construction",
            "type":"Services"
        }
    ],
    "sg:phone":"+1 315 786 0912",
    "sg:postcode":"13601",
    "sg:province":"NY",
    "sg:tags":[
        "restoration",
        "cleaning",
        "patio",
        "deck"
    ],
    "wof:name":"Fleming Painting & Pressure",
    "wof:placetype":"venue"
},
  "geometry": {"coordinates":[-75.92357199999999,43.974301],"type":"Point"}
}