{
  "type": "Feature",
  "properties": {
    "iso:country":"US",
    "sg:address":"3309 Blossom Ln",
    "sg:city":"North Tonawanda",
    "sg:classifiers":[
        {
            "category":"Building & Trades",
            "subcategory":"Landscaping Services",
            "type":"Services"
        }
    ],
    "sg:phone":"+1 716 523 4636",
    "sg:postcode":"14120",
    "sg:province":"NY",
    "wof:name":"Beaver Lawn Care",
    "wof:placetype":"venue"
},
  "geometry": {"coordinates":[-78.858238,43.082009],"type":"Point"}
}