{
  "type": "Feature",
  "properties": {
    "iso:country":"US",
    "sg:address":"300 Great Neck Rd",
    "sg:city":"Great Neck",
    "sg:classifiers":[
        {
            "category":"Retail",
            "subcategory":"Auto Rental",
            "type":"Services"
        }
    ],
    "sg:phone":"+1 516 466 6606",
    "sg:postcode":"11021",
    "sg:province":"NY",
    "sg:tags":[
        "automobile",
        "leasing"
    ],
    "wof:name":"BCA Leasing LTD",
    "wof:placetype":"venue"
},
  "geometry": {"coordinates":[-73.73188,40.779033],"type":"Point"}
}