{
  "type": "Feature",
  "properties": {
    "addr:full":"230 Ramblewood Dr Utica NY 13502",
    "addr:housenumber":"230",
    "addr:postcode":"13502",
    "addr:street":"Ramblewood Dr",
    "iso:country":"US",
    "sg:address":"230 Ramblewood Dr",
    "sg:city":"Utica",
    "sg:classifiers":[
        {
            "category":"Manufacturing",
            "subcategory":"Buildings",
            "type":"Manufacturing & Wholesale Goods"
        },
        {
            "category":"Building & Trades",
            "subcategory":"Construction",
            "type":"Services"
        }
    ],
    "sg:phone":"+1 315 335 3884",
    "sg:postcode":"13502",
    "sg:province":"NY",
    "sg:tags":[
        "home",
        "builder",
        "contractor"
    ],
    "wof:name":"Foley Builders, Inc",
    "wof:placetype":"venue"
},
  "geometry": {"coordinates":[-75.20777,43.140611],"type":"Point"}
}