{
  "type": "Feature",
  "properties": {
    "addr:full":"240 W 35th St New York NY 10001",
    "addr:housenumber":"240",
    "addr:postcode":"10001",
    "addr:street":"W 35Th St",
    "iso:country":"US",
    "sg:address":"240 W 35th St",
    "sg:city":"New York",
    "sg:classifiers":[
        {
            "category":"Retail",
            "subcategory":"Repair Shop",
            "type":"Services"
        }
    ],
    "sg:phone":"+1 212 719 5065",
    "sg:postcode":"10001",
    "sg:province":"NY",
    "wof:name":"Compu Pattern Service Inc",
    "wof:placetype":"venue"
},
  "geometry": {"coordinates":[-73.992135,40.752301],"type":"Point"}
}