{
  "type": "Feature",
  "properties": {
    "addr:full":"52 W 21 St New York NY 10010",
    "addr:housenumber":"52",
    "addr:postcode":"10010",
    "addr:street":"W 21 St",
    "iso:country":"US",
    "sg:address":"52 W 21 St",
    "sg:city":"New York",
    "sg:classifiers":[
        {
            "category":"Shopping",
            "subcategory":"Luggage & Leather Goods",
            "type":"Retail Goods"
        }
    ],
    "sg:phone":"+1 212 206 7323",
    "sg:postcode":"10010",
    "sg:province":"NY",
    "sg:tags":[
        "portfolio"
    ],
    "sg:website":"www.houseofportfolio.com",
    "wof:name":"House Of Portfolio",
    "wof:placetype":"venue"
},
  "geometry": {"coordinates":[-73.992504,40.740846],"type":"Point"}
}