{
  "type": "Feature",
  "properties": {
    "addr:full":"90 John Street Rm 301 New York NY 10038",
    "addr:housenumber":"90;301",
    "addr:postcode":"10038",
    "addr:street":"John Street Rm",
    "iso:country":"US",
    "sg:address":"90 John Street Rm 301",
    "sg:city":"New York",
    "sg:classifiers":[
        {
            "category":"Professional",
            "subcategory":"Lawyer & Legal Services",
            "type":"Services"
        }
    ],
    "sg:phone":"+1 646 442 3100",
    "sg:postcode":"10038",
    "sg:province":"NY",
    "wof:name":"Lsny Manhattan",
    "wof:placetype":"venue"
},
  "geometry": {"coordinates":[-74.006671,40.708251],"type":"Point"}
}