{
  "type": "Feature",
  "properties": {
    "addr:full":"122 La Salle St New York NY 10027",
    "addr:housenumber":"122",
    "addr:postcode":"10027",
    "addr:street":"La Salle St",
    "iso:country":"US",
    "sg:address":"122 La Salle St",
    "sg:city":"New York",
    "sg:classifiers":[
        {
            "category":"Retail",
            "subcategory":"Laundry & Dry Cleaning",
            "type":"Services"
        }
    ],
    "sg:phone":"+1 212 864 0269",
    "sg:postcode":"10027",
    "sg:province":"NY",
    "wof:name":"125 Lasalle Laundry And Cleaners",
    "wof:placetype":"venue"
},
  "geometry": {"coordinates":[-73.960059,40.813773],"type":"Point"}
}