{
  "type": "Feature",
  "properties": {
    "addr:full":"860 10th Avenue New York NY 10019",
    "addr:housenumber":"860",
    "addr:postcode":"10019",
    "addr:street":"10Th Avenue",
    "iso:country":"US",
    "sg:address":"860 10th Avenue",
    "sg:city":"New York",
    "sg:classifiers":[
        {
            "category":"Restaurant",
            "type":"Food & Drink"
        }
    ],
    "sg:phone":"+1 212 262 6162",
    "sg:postcode":"10019",
    "sg:province":"NY",
    "sg:tags":[
        "chinese"
    ],
    "wof:name":"Bei Jing Chinese Foods",
    "wof:placetype":"venue"
},
  "geometry": {"coordinates":[-73.988939,40.768584],"type":"Point"}
}