{
  "type": "Feature",
  "properties": {
    "addr:full":"835 Richmond Ave Buffalo NY 14222",
    "addr:housenumber":"835",
    "addr:postcode":"14222",
    "addr:street":"Richmond Ave",
    "iso:country":"US",
    "sg:address":"835 Richmond Ave",
    "sg:city":"Buffalo",
    "sg:classifiers":[
        {
            "category":"Retail",
            "subcategory":"Laundry & Dry Cleaning",
            "type":"Services"
        }
    ],
    "sg:phone":"+1 412 478 5658",
    "sg:postcode":"14222",
    "sg:province":"NY",
    "sg:tags":[
        "cleaner",
        "rug",
        "carpet"
    ],
    "wof:name":"Williams Brothers Cleaning",
    "wof:placetype":"venue"
},
  "geometry": {"coordinates":[-78.880951,42.925984],"type":"Point"}
}