{
  "type": "Feature",
  "properties": {
    "iso:country":"US",
    "sg:address":"7521 Highbridge Rd",
    "sg:city":"Manlius",
    "sg:classifiers":[
        {
            "category":"Retail",
            "subcategory":"Portrait Studio",
            "type":"Services"
        }
    ],
    "sg:phone":"+1 315 682 4626",
    "sg:postcode":"13104",
    "sg:province":"NY",
    "sg:tags":[
        "photographer"
    ],
    "wof:name":"Photography By John Farnach",
    "wof:placetype":"venue"
},
  "geometry": {"coordinates":[-75.995178,43.010389],"type":"Point"}
}