{
  "type": "Feature",
  "properties": {
    "addr:full":"2 Livingston St Geneseo NY 14454",
    "addr:housenumber":"2",
    "addr:postcode":"14454",
    "addr:street":"Livingston St",
    "iso:country":"US",
    "sg:address":"2 Livingston St",
    "sg:city":"Geneseo",
    "sg:classifiers":[
        {
            "category":"Government",
            "subcategory":"Office",
            "type":"Public Place"
        }
    ],
    "sg:phone":"+1 585 243 7960",
    "sg:postcode":"14454",
    "sg:province":"NY",
    "wof:name":"Livingston County Veteran Affr",
    "wof:placetype":"venue"
},
  "geometry": {"coordinates":[-77.806786,42.802675],"type":"Point"}
}