{
  "type": "Feature",
  "properties": {
    "addr:full":"899 Broadway Westbury NY 11590",
    "addr:housenumber":"899",
    "addr:postcode":"11590",
    "addr:street":"Broadway",
    "iso:country":"US",
    "sg:address":"899 Broadway",
    "sg:city":"Westbury",
    "sg:classifiers":[
        {
            "category":"Health Services",
            "subcategory":"Clinic",
            "type":"Services"
        }
    ],
    "sg:phone":"+1 516 876 6260",
    "sg:postcode":"11590",
    "sg:province":"NY",
    "sg:tags":[
        "home",
        "care"
    ],
    "wof:name":"Personal-Touch Home Care Inc",
    "wof:placetype":"venue"
},
  "geometry": {"coordinates":[-73.567336,40.759414],"type":"Point"}
}