{
  "type": "Feature",
  "properties": {
    "addr:full":"3861 Buffalo Rd Rochester NY 14624",
    "addr:housenumber":"3861",
    "addr:postcode":"14624",
    "addr:street":"Buffalo Rd",
    "iso:country":"US",
    "sg:address":"3861 Buffalo Rd",
    "sg:city":"Rochester",
    "sg:classifiers":[
        {
            "category":"Wholesale",
            "subcategory":"Painting Supplies",
            "type":"Manufacturing & Wholesale Goods"
        },
        {
            "category":"Retail",
            "subcategory":"Repair Shop",
            "type":"Services"
        },
        {
            "category":"Home & Garden",
            "subcategory":"Hardware",
            "type":"Retail Goods"
        },
        {
            "category":"Home & Garden",
            "subcategory":"Building Materials",
            "type":"Retail Goods"
        },
        {
            "category":"Wholesale",
            "subcategory":"Hardware",
            "type":"Manufacturing & Wholesale Goods"
        },
        {
            "category":"Home & Garden",
            "subcategory":"Garden Supply",
            "type":"Retail Goods"
        }
    ],
    "sg:phone":"+1 585 594 1110",
    "sg:postcode":"14624",
    "sg:province":"NY",
    "sg:tags":[
        "renting",
        "lawn",
        "outdoor",
        "power",
        "equipment",
        "equipment-sales",
        "landscaping",
        "saw",
        "paint",
        "store"
    ],
    "sg:website":"http://www.stihldealer.net/default-dealer-042096.aspx",
    "wof:name":"Specialty Tools, Inc",
    "wof:placetype":"venue"
},
  "geometry": {"coordinates":[-77.76294300000001,43.137547],"type":"Point"}
}