{
  "type": "Feature",
  "properties": {
    "addr:full":"452 South Ave Staten Island NY 10303",
    "addr:housenumber":"452",
    "addr:postcode":"10303",
    "addr:street":"South Ave",
    "iso:country":"US",
    "sg:address":"452 South Ave",
    "sg:city":"Staten Island",
    "sg:classifiers":[
        {
            "category":"Retail",
            "subcategory":"Car Wash",
            "type":"Services"
        }
    ],
    "sg:phone":"+1 718 494 7500",
    "sg:postcode":"10303",
    "sg:province":"NY",
    "sg:tags":[
        "polishing",
        "washing"
    ],
    "sg:website":"www.vipwashandlube.com",
    "wof:name":"Vip Wash & Lube",
    "wof:placetype":"venue"
},
  "geometry": {"coordinates":[-74.166451,40.629527],"type":"Point"}
}