{
  "type": "Feature",
  "properties": {
    "addr:full":"146 Kensington Rd Garden City NY 11530",
    "addr:housenumber":"146",
    "addr:postcode":"11530",
    "addr:street":"Kensington Rd",
    "iso:country":"US",
    "sg:address":"146 Kensington Rd",
    "sg:city":"Garden City",
    "sg:classifiers":[
        {
            "category":"Utilities",
            "subcategory":"Telephone",
            "type":"Services"
        }
    ],
    "sg:phone":"+1   ",
    "sg:postcode":"11530",
    "sg:province":"NY",
    "sg:tags":[
        "on",
        "industry",
        "beverage",
        "newsletter",
        "provider"
    ],
    "wof:name":"Bevnetcom",
    "wof:placetype":"venue"
},
  "geometry": {"coordinates":[-73.657875,40.728786],"type":"Point"}
}