{
  "type": "Feature",
  "properties": {
    "iso:country":"US",
    "sg:address":"137 Miller Rd",
    "sg:city":"Hicksville",
    "sg:classifiers":[
        {
            "category":"Insurance",
            "subcategory":"Insurance Agent",
            "type":"Services"
        },
        {
            "category":"Insurance",
            "subcategory":"Hazard Insurance",
            "type":"Services"
        }
    ],
    "sg:phone":"+1 516 942 0892",
    "sg:postcode":"11801",
    "sg:province":"NY",
    "sg:tags":[
        "adjuster"
    ],
    "wof:name":"Acclaim Adjusting",
    "wof:placetype":"venue"
},
  "geometry": {"coordinates":[-73.51628599999999,40.781633],"type":"Point"}
}