{
  "type": "Feature",
  "properties": {
    "iso:country":"US",
    "sg:address":"109 N Meadow St",
    "sg:city":"Ithaca",
    "sg:classifiers":[
        {
            "category":"Shopping",
            "subcategory":"Tobacco",
            "type":"Retail Goods"
        }
    ],
    "sg:phone":"+1   ",
    "sg:postcode":"14850",
    "sg:province":"NY",
    "sg:tags":[
        "product"
    ],
    "wof:name":"C & C Tobacco Outlet",
    "wof:placetype":"venue"
},
  "geometry": {"coordinates":[-76.508308,42.440047],"type":"Point"}
}