{
  "type": "Feature",
  "properties": {
    "addr:full":"1010 44th Ave Long Island City NY 11101",
    "addr:housenumber":"1010",
    "addr:postcode":"11101",
    "addr:street":"44Th Ave",
    "iso:country":"US",
    "sg:address":"1010 44th Ave",
    "sg:city":"Long Island City",
    "sg:classifiers":[
        {
            "category":"Retail",
            "subcategory":"Repair Shop",
            "type":"Services"
        }
    ],
    "sg:phone":"+1 718 786 0104",
    "sg:postcode":"11101",
    "sg:province":"NY",
    "sg:tags":[
        "reupholstery",
        "furniture"
    ],
    "wof:name":"J M Upholstery",
    "wof:placetype":"venue"
},
  "geometry": {"coordinates":[-73.950401,40.750198],"type":"Point"}
}