{
  "type": "Feature",
  "properties": {
    "iso:country":"US",
    "sg:address":"909 Main St W",
    "sg:city":"Rochester",
    "sg:classifiers":[
        {
            "category":"Health Services",
            "subcategory":"Doctor",
            "type":"Services"
        }
    ],
    "sg:phone":"+1 585 368 3800",
    "sg:postcode":"14611",
    "sg:province":"NY",
    "wof:name":"Jensen Rosalynd DDS",
    "wof:placetype":"venue"
},
  "geometry": {"coordinates":[-77.636781,43.15004],"type":"Point"}
}