{
  "type": "Feature",
  "properties": {
    "iso:country":"US",
    "sg:address":"118 W 80 St",
    "sg:city":"New York",
    "sg:classifiers":[
        {
            "category":"Professional",
            "subcategory":"Art Services",
            "type":"Services"
        }
    ],
    "sg:phone":"+1 212 580 3010",
    "sg:postcode":"10024",
    "sg:province":"NY",
    "sg:tags":[
        "graphic",
        "designer"
    ],
    "wof:name":"Lance Wyman LTD",
    "wof:placetype":"venue"
},
  "geometry": {"coordinates":[-73.977467,40.783545],"type":"Point"}
}