{
  "type": "Feature",
  "properties": {
    "iso:country":"US",
    "sg:address":"147 Gazza Blvd",
    "sg:city":"Farmingdale",
    "sg:classifiers":[
        {
            "category":"Manufacturing",
            "subcategory":"Petroleum Products",
            "type":"Manufacturing & Wholesale Goods"
        }
    ],
    "sg:phone":"+1 631 752 1688",
    "sg:postcode":"11735",
    "sg:province":"NY",
    "wof:name":"Century Petroleum LTD",
    "wof:placetype":"venue"
},
  "geometry": {"coordinates":[-73.421057,40.746701],"type":"Point"}
}