{
  "type": "Feature",
  "properties": {
    "addr:full":"1330 E 65th St Brooklyn NY 11234",
    "addr:housenumber":"1330",
    "addr:postcode":"11234",
    "addr:street":"E 65Th St",
    "iso:country":"US",
    "sg:address":"1330 E 65th St",
    "sg:city":"Brooklyn",
    "sg:classifiers":[
        {
            "category":"Building & Trades",
            "subcategory":"Plumbing",
            "type":"Services"
        }
    ],
    "sg:phone":"+1 718 251 7425",
    "sg:postcode":"11234",
    "sg:province":"NY",
    "wof:name":"Mark's Drain Cleaning Services",
    "wof:placetype":"venue"
},
  "geometry": {"coordinates":[-73.91656,40.62112],"type":"Point"}
}