{
  "type": "Feature",
  "properties": {
    "iso:country":"US",
    "sg:address":"333 Jerusalem Ave",
    "sg:city":"Hicksville",
    "sg:classifiers":[
        {
            "category":"Home & Garden",
            "subcategory":"Household Appliances",
            "type":"Retail Goods"
        }
    ],
    "sg:phone":"+1 516 433 6302",
    "sg:postcode":"11801",
    "sg:province":"NY",
    "sg:tags":[
        "cleaners",
        "vacuum"
    ],
    "wof:name":"ABC Vac & Sew",
    "wof:placetype":"venue"
},
  "geometry": {"coordinates":[-73.520466,40.754496],"type":"Point"}
}