{
  "type": "Feature",
  "properties": {
    "addr:full":"8708 Justice Ave Elmhurst NY 11373",
    "addr:housenumber":"8708",
    "addr:postcode":"11373",
    "addr:street":"Justice Ave",
    "iso:country":"US",
    "sg:address":"8708 Justice Ave",
    "sg:city":"Elmhurst",
    "sg:classifiers":[
        {
            "category":"Health Services",
            "subcategory":"Doctor",
            "type":"Services"
        }
    ],
    "sg:phone":"+1 718 424 8660",
    "sg:postcode":"11373",
    "sg:province":"NY",
    "wof:name":"Harhash Sawey MD",
    "wof:placetype":"venue"
},
  "geometry": {"coordinates":[-73.875709,40.737089],"type":"Point"}
}