{
  "type": "Feature",
  "properties": {
    "addr:full":"4406 Oak Beach Assn Babylon NY 11702",
    "addr:housenumber":"4406",
    "addr:postcode":"11702",
    "addr:street":"Oak",
    "iso:country":"US",
    "sg:address":"4406 Oak Beach Assn",
    "sg:city":"Babylon",
    "sg:classifiers":[
        {
            "category":"Manufacturing",
            "subcategory":"Apparel",
            "type":"Manufacturing & Wholesale Goods"
        }
    ],
    "sg:phone":"+1   ",
    "sg:postcode":"11702",
    "sg:province":"NY",
    "sg:tags":[
        "product",
        "boat",
        "mfg"
    ],
    "wof:name":"South Shore Kayacks",
    "wof:placetype":"venue"
},
  "geometry": {"coordinates":[-73.29862,40.63854],"type":"Point"}
}