{
  "type": "Feature",
  "properties": {
    "addr:full":"428 Park Pl Brooklyn NY 11238",
    "addr:housenumber":"428",
    "addr:postcode":"11238",
    "addr:street":"Park Pl",
    "iso:country":"US",
    "sg:address":"428 Park Pl",
    "sg:city":"Brooklyn",
    "sg:classifiers":[
        {
            "category":"Personal",
            "subcategory":"Massage",
            "type":"Services"
        }
    ],
    "sg:phone":"+1 347 325 3434",
    "sg:postcode":"11238",
    "sg:province":"NY",
    "sg:website":"www.mamamoonnyc.com",
    "wof:name":"Jennifer Mayer, LMT, NCTMB",
    "wof:placetype":"venue"
},
  "geometry": {"coordinates":[-73.96387199999999,40.675363],"type":"Point"}
}