{
  "type": "Feature",
  "properties": {
    "addr:full":"9388 Clipnock Rd Stafford NY 14143",
    "addr:housenumber":"9388",
    "addr:postcode":"14143",
    "addr:street":"Clipnock Rd",
    "iso:country":"US",
    "sg:address":"9388 Clipnock Rd",
    "sg:city":"Stafford",
    "sg:classifiers":[
        {
            "category":"Shopping",
            "subcategory":"Florist",
            "type":"Retail Goods"
        }
    ],
    "sg:phone":"+1   ",
    "sg:postcode":"14143",
    "sg:province":"NY",
    "wof:name":"Accents By Renee",
    "wof:placetype":"venue"
},
  "geometry": {"coordinates":[-78.08076199999999,42.958174],"type":"Point"}
}