{
  "type": "Feature",
  "properties": {
    "addr:full":"7601 4th Avenue Brooklyn NY 11209",
    "addr:housenumber":"7601",
    "addr:postcode":"11209",
    "addr:street":"4Th Avenue",
    "iso:country":"US",
    "sg:address":"7601 4th Avenue",
    "sg:city":"Brooklyn",
    "sg:classifiers":[
        {
            "category":"Health Services",
            "subcategory":"Doctor",
            "type":"Services"
        }
    ],
    "sg:phone":"+1 718 745 8879",
    "sg:postcode":"11209",
    "sg:province":"NY",
    "wof:name":"Endoscopic Ambulatory Speciality Center of Bayridge",
    "wof:placetype":"venue"
},
  "geometry": {"coordinates":[-74.025357,40.630109],"type":"Point"}
}