{
  "type": "Feature",
  "properties": {
    "addr:full":"332 Stanley Ave Mamaroneck NY 10543",
    "addr:housenumber":"332",
    "addr:postcode":"10543",
    "addr:street":"Stanley Ave",
    "iso:country":"US",
    "sg:address":"332 Stanley Ave",
    "sg:city":"Mamaroneck",
    "sg:classifiers":[
        {
            "category":"Manufacturing",
            "subcategory":"Buildings",
            "type":"Manufacturing & Wholesale Goods"
        },
        {
            "category":"Building & Trades",
            "subcategory":"Construction",
            "type":"Services"
        }
    ],
    "sg:phone":"+1 732 742 2488",
    "sg:postcode":"10543",
    "sg:province":"NY",
    "sg:tags":[
        "home",
        "builder",
        "contractor"
    ],
    "wof:name":"Di Carlo Home Improvements",
    "wof:placetype":"venue"
},
  "geometry": {"coordinates":[-73.738012,40.950922],"type":"Point"}
}