{
  "type": "Feature",
  "properties": {
    "addr:full":"27 Union Sq W New York NY 10003",
    "addr:housenumber":"27",
    "addr:postcode":"10003",
    "addr:street":"Union Sq W",
    "iso:country":"US",
    "sg:address":"27 Union Sq W",
    "sg:city":"New York",
    "sg:classifiers":[
        {
            "category":"Health Services",
            "subcategory":"Doctor",
            "type":"Services"
        }
    ],
    "sg:phone":"+1 212 627 5500",
    "sg:postcode":"10003",
    "sg:province":"NY",
    "wof:name":"Uniting Against Lung Cancer",
    "wof:placetype":"venue"
},
  "geometry": {"coordinates":[-73.99100300000001,40.736502],"type":"Point"}
}