{
  "type": "Feature",
  "properties": {
    "iso:country":"US",
    "sg:address":"4005 West Rd",
    "sg:city":"Cortland",
    "sg:classifiers":[
        {
            "category":"Health Services",
            "subcategory":"Health Practitioner",
            "type":"Services"
        }
    ],
    "sg:phone":"+1 607 753 6000",
    "sg:postcode":"13045",
    "sg:province":"NY",
    "sg:tags":[
        "therapist",
        "physical"
    ],
    "wof:name":"Cortland Memorial Outpatient",
    "wof:placetype":"venue"
},
  "geometry": {"coordinates":[-76.201925,42.601952],"type":"Point"}
}