{
  "type": "Feature",
  "properties": {
    "iso:country":"US",
    "sg:address":"36 Church St",
    "sg:city":"Syosset",
    "sg:classifiers":[
        {
            "category":"Organizations",
            "subcategory":"Religious Organization",
            "type":"Services"
        }
    ],
    "sg:phone":"+1 516 921 2240",
    "sg:postcode":"11791",
    "sg:province":"NY",
    "sg:tags":[
        "child",
        "day",
        "care",
        "church"
    ],
    "wof:name":"Community Church Of Syosset",
    "wof:placetype":"venue"
},
  "geometry": {"coordinates":[-73.50370700000001,40.828688],"type":"Point"}
}