{
  "type": "Feature",
  "properties": {
    "addr:full":"226 E 120th St New York NY 10035",
    "addr:housenumber":"226",
    "addr:postcode":"10035",
    "addr:street":"E 120Th St",
    "iso:country":"US",
    "sg:address":"226 E 120th St",
    "sg:city":"New York",
    "sg:classifiers":[
        {
            "category":"Organizations",
            "subcategory":"Religious Organization",
            "type":"Services"
        }
    ],
    "sg:phone":"+1 212 860 1510",
    "sg:postcode":"10035",
    "sg:province":"NY",
    "sg:tags":[
        "pentecostal",
        "church"
    ],
    "wof:name":"Bethel Gospel Assembly Inc",
    "wof:placetype":"venue"
},
  "geometry": {"coordinates":[-73.93639,40.799751],"type":"Point"}
}