{
  "type": "Feature",
  "properties": {
    "iso:country":"US",
    "sg:address":"1334 Gerling St",
    "sg:city":"Schenectady",
    "sg:classifiers":[
        {
            "category":"Restaurant",
            "type":"Food & Drink"
        }
    ],
    "sg:menulink":"http://www.allmenus.com/ny/schenectady/27888-new-china-restaurant/menu/",
    "sg:phone":"+1 518 346 3141",
    "sg:postcode":"12308",
    "sg:province":"NY",
    "sg:tags":[
        "asian",
        "chinese"
    ],
    "wof:name":"New China Restaurant",
    "wof:placetype":"venue"
},
  "geometry": {"coordinates":[-73.90911199999999,42.823277],"type":"Point"}
}