{
  "type": "Feature",
  "properties": {
    "iso:country":"US",
    "sg:address":"3830 Monroe Ave",
    "sg:city":"Pittsford",
    "sg:classifiers":[
        {
            "category":"Retail",
            "subcategory":"Auto Repair",
            "type":"Services"
        }
    ],
    "sg:phone":"+1 585 381 5610",
    "sg:postcode":"14534",
    "sg:province":"NY",
    "sg:tags":[
        "repairing",
        "automobile"
    ],
    "wof:name":"Sutherland Service Ctr",
    "wof:placetype":"venue"
},
  "geometry": {"coordinates":[-77.525026,43.09487],"type":"Point"}
}