{
  "type": "Feature",
  "properties": {
    "iso:country":"US",
    "sg:address":"1300 Castle Hill Ave",
    "sg:city":"Bronx",
    "sg:classifiers":[
        {
            "category":"Retail",
            "subcategory":"Repair Shop",
            "type":"Services"
        }
    ],
    "sg:phone":"+1 718 304 8121",
    "sg:postcode":"10462",
    "sg:province":"NY",
    "sg:tags":[
        "lock",
        "locksmith"
    ],
    "wof:name":"AAA Locksmith",
    "wof:placetype":"venue"
},
  "geometry": {"coordinates":[-73.85207,40.835625],"type":"Point"}
}