{
  "type": "Feature",
  "properties": {
    "iso:country":"US",
    "sg:address":"32 Birch Hill Rd",
    "sg:city":"Locust Valley",
    "sg:classifiers":[
        {
            "category":"Personal",
            "subcategory":"Barber",
            "type":"Services"
        }
    ],
    "sg:phone":"+1 516 676 9350",
    "sg:postcode":"11560",
    "sg:province":"NY",
    "wof:name":"Hunts Barbershop",
    "wof:placetype":"venue"
},
  "geometry": {"coordinates":[-73.596982,40.875309],"type":"Point"}
}