{
  "type": "Feature",
  "properties": {
    "iso:country":"US",
    "sg:address":"43 Robert Pitt Dr",
    "sg:city":"Monsey",
    "sg:classifiers":[
        {
            "category":"Education",
            "subcategory":"School",
            "type":"Public Place"
        }
    ],
    "sg:phone":"+1 845 577 6160",
    "sg:postcode":"10952",
    "sg:province":"NY",
    "sg:tags":[
        "elementary"
    ],
    "wof:name":"Elmwood Elementary School",
    "wof:placetype":"venue"
},
  "geometry": {"coordinates":[-74.064984,41.11067],"type":"Point"}
}