{
  "type": "Feature",
  "properties": {
    "iso:country":"US",
    "sg:address":"110 E Main St",
    "sg:city":"Elbridge",
    "sg:classifiers":[
        {
            "category":"Professional",
            "subcategory":"Business Services",
            "type":"Services"
        }
    ],
    "sg:phone":"+1 315 689 6635",
    "sg:postcode":"13060",
    "sg:province":"NY",
    "sg:tags":[
        "embroidery"
    ],
    "wof:name":"Stitch In Time",
    "wof:placetype":"venue"
},
  "geometry": {"coordinates":[-76.447759,43.034397],"type":"Point"}
}