{
  "type": "Feature",
  "properties": {
    "iso:country":"US",
    "sg:address":"7979 Victor-Pittsford Rd",
    "sg:city":"Victor",
    "sg:classifiers":[
        {
            "category":"Shopping",
            "subcategory":"Department Store",
            "type":"Retail Goods"
        }
    ],
    "sg:phone":"+1 585 425 8840",
    "sg:postcode":"14564",
    "sg:province":"NY",
    "wof:name":"Lord & Taylor",
    "wof:placetype":"venue"
},
  "geometry": {"coordinates":[-77.440434,43.03059],"type":"Point"}
}