{
  "type": "Feature",
  "properties": {
    "addr:full":"137 Greenwood Dr Massapequa NY 11758",
    "addr:housenumber":"137",
    "addr:postcode":"11758",
    "addr:street":"Greenwood Dr",
    "iso:country":"US",
    "sg:address":"137 Greenwood Dr",
    "sg:city":"Massapequa",
    "sg:classifiers":[
        {
            "category":"Wholesale",
            "subcategory":"Non-durable Goods",
            "type":"Manufacturing & Wholesale Goods"
        }
    ],
    "sg:phone":"+1 516 796 6380",
    "sg:postcode":"11758",
    "sg:province":"NY",
    "sg:tags":[
        "merchandise-wholesale"
    ],
    "wof:name":"Sjs Distributors Corp.",
    "wof:placetype":"venue"
},
  "geometry": {"coordinates":[-73.480418,40.704451],"type":"Point"}
}