{
  "type": "Feature",
  "properties": {
    "iso:country":"US",
    "sg:address":"5993 Byron Holley Rd",
    "sg:city":"Byron",
    "sg:classifiers":[
        {
            "category":"Local Transit",
            "type":"Transportation"
        }
    ],
    "sg:phone":"+1 585 548 9918",
    "sg:postcode":"14422",
    "sg:province":"NY",
    "sg:tags":[
        "limousine"
    ],
    "wof:name":"L L Limousine Svc",
    "wof:placetype":"venue"
},
  "geometry": {"coordinates":[-78.06587399999999,43.121376],"type":"Point"}
}