{
  "type": "Feature",
  "properties": {
    "addr:full":"1008 Woodfield Dr Schenectady NY 12309",
    "addr:housenumber":"1008",
    "addr:postcode":"12309",
    "addr:street":"Woodfield Dr",
    "iso:country":"US",
    "sg:address":"1008 Woodfield Dr",
    "sg:city":"Schenectady",
    "sg:classifiers":[
        {
            "category":"Real Estate",
            "subcategory":"Real Estate Services",
            "type":"Services"
        },
        {
            "category":"Real Estate",
            "subcategory":"Real Estate Agent",
            "type":"Services"
        }
    ],
    "sg:phone":"+1 518 605 0702",
    "sg:postcode":"12309",
    "sg:province":"NY",
    "sg:tags":[
        "buyer",
        "broker"
    ],
    "wof:name":"Charlie Patton Realty",
    "wof:placetype":"venue"
},
  "geometry": {"coordinates":[-73.84121,42.779285],"type":"Point"}
}