{
  "type": "Feature",
  "properties": {
    "addr:full":"1692 E 16th St Brooklyn NY 11229",
    "addr:housenumber":"1692",
    "addr:postcode":"11229",
    "addr:street":"E 16Th St",
    "iso:country":"US",
    "sg:address":"1692 E 16th St",
    "sg:city":"Brooklyn",
    "sg:classifiers":[
        {
            "category":"Wholesale",
            "subcategory":"Books, Periodicals, & Newspapers",
            "type":"Manufacturing & Wholesale Goods"
        }
    ],
    "sg:phone":"+1 718 339 6591",
    "sg:postcode":"11229",
    "sg:province":"NY",
    "sg:tags":[
        "print",
        "medium"
    ],
    "wof:name":"Quentin News Inc",
    "wof:placetype":"venue"
},
  "geometry": {"coordinates":[-73.957397,40.608601],"type":"Point"}
}