{
  "type": "Feature",
  "properties": {
    "addr:full":"2699 Clarks Corners Rd Marathon NY 13803",
    "addr:housenumber":"2699",
    "addr:postcode":"13803",
    "addr:street":"Clarks Corners Rd",
    "iso:country":"US",
    "sg:address":"2699 Clarks Corners Rd",
    "sg:city":"Marathon",
    "sg:classifiers":[
        {
            "category":"Building & Trades",
            "subcategory":"Landscaping Services",
            "type":"Services"
        }
    ],
    "sg:phone":"+1 607 849 6393",
    "sg:postcode":"13803",
    "sg:province":"NY",
    "sg:tags":[
        "landscape",
        "contractor"
    ],
    "wof:name":"Countree Lawn and Landscape",
    "wof:placetype":"venue"
},
  "geometry": {"coordinates":[-76.094864,42.441089],"type":"Point"}
}