{
  "type": "Feature",
  "properties": {
    "addr:full":"201 W 54 St New York NY 10019",
    "addr:housenumber":"201",
    "addr:postcode":"10019",
    "addr:street":"W 54 St",
    "iso:country":"US",
    "sg:address":"201 W 54 St",
    "sg:city":"New York",
    "sg:classifiers":[
        {
            "category":"Arts & Performance",
            "subcategory":"Theater",
            "type":"Entertainment"
        }
    ],
    "sg:phone":"+1 212 247 1051",
    "sg:postcode":"10019",
    "sg:province":"NY",
    "sg:tags":[
        "entertainer"
    ],
    "wof:name":"Belly Dancing By Serena Stds",
    "wof:placetype":"venue"
},
  "geometry": {"coordinates":[-73.98246899999999,40.764033],"type":"Point"}
}