{
  "type": "Feature",
  "properties": {
    "iso:country":"US",
    "sg:address":"5200 Ledge Ln",
    "sg:city":"Buffalo",
    "sg:classifiers":[
        {
            "category":"Retail",
            "subcategory":"Laundry & Dry Cleaning",
            "type":"Services"
        }
    ],
    "sg:phone":"+1 716 633 9335",
    "sg:postcode":"14221",
    "sg:province":"NY",
    "sg:tags":[
        "chimney"
    ],
    "wof:name":"Tophat Chimney Sweeper",
    "wof:placetype":"venue"
},
  "geometry": {"coordinates":[-78.688744,42.987652],"type":"Point"}
}