{
  "type": "Feature",
  "properties": {
    "addr:full":"391 S Pearl St Ste 1 Albany NY 12202",
    "addr:housenumber":"391",
    "addr:postcode":"12202",
    "addr:street":"S Pearl St Ste 1",
    "iso:country":"US",
    "sg:address":"391 S Pearl St Ste 1",
    "sg:city":"Albany",
    "sg:classifiers":[
        {
            "category":"Wholesale",
            "subcategory":"Books, Periodicals, & Newspapers",
            "type":"Manufacturing & Wholesale Goods"
        }
    ],
    "sg:phone":"+1 518 465 1530",
    "sg:postcode":"12202",
    "sg:province":"NY",
    "sg:tags":[
        "publisher",
        "book"
    ],
    "wof:name":"Albany Express",
    "wof:placetype":"venue"
},
  "geometry": {"coordinates":[-73.75850699999999,42.638597],"type":"Point"}
}