{
  "type": "Feature",
  "properties": {
    "iso:country":"US",
    "sg:address":"3800 Delaware Ave",
    "sg:city":"Kenmore",
    "sg:classifiers":[
        {
            "category":"Health Services",
            "subcategory":"Doctor",
            "type":"Services"
        }
    ],
    "sg:phone":"+1 716 876 3737",
    "sg:postcode":"14217",
    "sg:province":"NY",
    "sg:tags":[
        "physician",
        "surgeon",
        "clinic",
        "medical"
    ],
    "wof:name":"George A Haddad MD",
    "wof:placetype":"venue"
},
  "geometry": {"coordinates":[-78.873378,42.987442],"type":"Point"}
}