{
  "type": "Feature",
  "properties": {
    "addr:full":"3205 Church Ave Brooklyn NY 11226",
    "addr:housenumber":"3205",
    "addr:postcode":"11226",
    "addr:street":"Church Ave",
    "iso:country":"US",
    "sg:address":"3205 Church Ave",
    "sg:city":"Brooklyn",
    "sg:classifiers":[
        {
            "category":"Shopping",
            "subcategory":"Clothing, Apparel, & Fashions",
            "type":"Retail Goods"
        }
    ],
    "sg:phone":"+1 718 940 8252",
    "sg:postcode":"11226",
    "sg:province":"NY",
    "sg:tags":[
        "accessory",
        "clothing",
        "women's"
    ],
    "wof:name":"Ms Dress Shop",
    "wof:placetype":"venue"
},
  "geometry": {"coordinates":[-73.947609,40.651038],"type":"Point"}
}