{
  "type": "Feature",
  "properties": {
    "iso:country":"US",
    "sg:address":"26 Park Ave",
    "sg:city":"Geneva",
    "sg:classifiers":[
        {
            "category":"Building & Trades",
            "subcategory":"Plumbing",
            "type":"Services"
        }
    ],
    "sg:phone":"+1 315 789 3013",
    "sg:postcode":"14456",
    "sg:province":"NY",
    "sg:tags":[
        "contractor",
        "con"
    ],
    "wof:name":"DS Plumbing and Heating",
    "wof:placetype":"venue"
},
  "geometry": {"coordinates":[-76.985782,42.86375],"type":"Point"}
}