{
  "type": "Feature",
  "properties": {
    "addr:full":"468 W 143rd St New York NY 10031",
    "addr:housenumber":"468",
    "addr:postcode":"10031",
    "addr:street":"W 143Rd St",
    "iso:country":"US",
    "sg:address":"468 W 143rd St",
    "sg:city":"New York",
    "sg:classifiers":[
        {
            "category":"Education",
            "subcategory":"School",
            "type":"Public Place"
        }
    ],
    "sg:phone":"+1 212 926 5820",
    "sg:postcode":"10031",
    "sg:province":"NY",
    "wof:name":"Our Lady of Lourdes School",
    "wof:placetype":"venue"
},
  "geometry": {"coordinates":[-73.947959,40.823526],"type":"Point"}
}