{
  "type": "Feature",
  "properties": {
    "addr:full":"5 Shaker Hollow Rd Setauket NY 11733",
    "addr:housenumber":"5",
    "addr:postcode":"11733",
    "addr:street":"Shaker Hollow Rd",
    "iso:country":"US",
    "sg:address":"5 Shaker Hollow Rd",
    "sg:city":"Setauket",
    "sg:classifiers":[
        {
            "category":"Professional",
            "subcategory":"Management & Consulting",
            "type":"Services"
        }
    ],
    "sg:phone":"+1 631 751 7230",
    "sg:postcode":"11733",
    "sg:province":"NY",
    "sg:tags":[
        "consultant"
    ],
    "wof:name":"Old Field Advisors LLC",
    "wof:placetype":"venue"
},
  "geometry": {"coordinates":[-73.123057,40.946824],"type":"Point"}
}