{
  "type": "Feature",
  "properties": {
    "iso:country":"US",
    "sg:address":"891 Manor Rd",
    "sg:city":"Staten Island",
    "sg:classifiers":[
        {
            "category":"Shopping",
            "subcategory":"Florist",
            "type":"Retail Goods"
        }
    ],
    "sg:phone":"+1 718 370 8011",
    "sg:postcode":"10314",
    "sg:province":"NY",
    "wof:name":"Manor Florist",
    "wof:placetype":"venue"
},
  "geometry": {"coordinates":[-74.120711,40.604611],"type":"Point"}
}