{
  "type": "Feature",
  "properties": {
    "iso:country":"US",
    "sg:address":"1129 Northern Blvd",
    "sg:city":"Manhasset",
    "sg:classifiers":[
        {
            "category":"Health Services",
            "subcategory":"Doctor",
            "type":"Services"
        }
    ],
    "sg:phone":"+1 212 628 7779",
    "sg:postcode":"11030",
    "sg:province":"NY",
    "sg:tags":[
        "surgeon",
        "cosmetic"
    ],
    "wof:name":"Lukash Frederick MD",
    "wof:placetype":"venue"
},
  "geometry": {"coordinates":[-73.70393799999999,40.79073],"type":"Point"}
}