{
  "type": "Feature",
  "properties": {
    "addr:full":"19 Fawn Ln Lowman NY 14814",
    "addr:housenumber":"19",
    "addr:postcode":"14814",
    "addr:street":"Fawn Ln",
    "iso:country":"US",
    "sg:address":"19 Fawn Ln",
    "sg:city":"Lowman",
    "sg:classifiers":[
        {
            "category":"Building & Trades",
            "subcategory":"Construction",
            "type":"Services"
        }
    ],
    "sg:phone":"+1 607 732 1106",
    "sg:postcode":"14814",
    "sg:province":"NY",
    "sg:tags":[
        "painter"
    ],
    "wof:name":"Thomas H Ritter",
    "wof:placetype":"venue"
},
  "geometry": {"coordinates":[-76.93895999999999,42.151417],"type":"Point"}
}