{
  "type": "Feature",
  "properties": {
    "addr:full":"24 W 26th St New York NY 10010",
    "addr:housenumber":"24",
    "addr:postcode":"10010",
    "addr:street":"W 26Th St",
    "iso:country":"US",
    "sg:address":"24 W 26th St",
    "sg:city":"New York",
    "sg:classifiers":[
        {
            "category":"Manufacturing",
            "subcategory":"Apparel",
            "type":"Manufacturing & Wholesale Goods"
        }
    ],
    "sg:phone":"+1   ",
    "sg:postcode":"10010",
    "sg:province":"NY",
    "sg:tags":[
        "clothing",
        "mfg"
    ],
    "wof:name":"Regal Wear Inc",
    "wof:placetype":"venue"
},
  "geometry": {"coordinates":[-73.991165,40.744576],"type":"Point"}
}