{
  "type": "Feature",
  "properties": {
    "addr:full":"834 62nd St Brooklyn NY 11220",
    "addr:housenumber":"834",
    "addr:postcode":"11220",
    "addr:street":"62Nd St",
    "iso:country":"US",
    "sg:address":"834 62nd St",
    "sg:city":"Brooklyn",
    "sg:classifiers":[
        {
            "category":"Building & Trades",
            "subcategory":"Plumbing",
            "type":"Services"
        }
    ],
    "sg:phone":"+1 718 745 7227",
    "sg:postcode":"11220",
    "sg:province":"NY",
    "sg:tags":[
        "specializing",
        "contractor",
        "water",
        "plumbing",
        "line",
        "main"
    ],
    "wof:name":"Pullini Wtr Main Sewer Contrs",
    "wof:placetype":"venue"
},
  "geometry": {"coordinates":[-74.009163,40.63343],"type":"Point"}
}