{
  "type": "Feature",
  "properties": {
    "addr:full":"8 Lundy Rd Wawarsing NY 12489",
    "addr:housenumber":"8",
    "addr:postcode":"12489",
    "addr:street":"Lundy Rd",
    "iso:country":"US",
    "sg:address":"8 Lundy Rd",
    "sg:city":"Wawarsing",
    "sg:classifiers":[
        {
            "category":"Building & Trades",
            "subcategory":"Plumbing",
            "type":"Services"
        }
    ],
    "sg:phone":"+1 845 647 1385",
    "sg:postcode":"12489",
    "sg:province":"NY",
    "sg:tags":[
        "plumbing",
        "contractor"
    ],
    "wof:name":"Northeast Plumbing Spec Corp",
    "wof:placetype":"venue"
},
  "geometry": {"coordinates":[-74.35919199999999,41.760181],"type":"Point"}
}