{
  "type": "Feature",
  "properties": {
    "iso:country":"US",
    "sg:address":"685 Weaver St",
    "sg:city":"Larchmont",
    "sg:classifiers":[
        {
            "category":"Organizations",
            "subcategory":"Community Association",
            "type":"Services"
        }
    ],
    "sg:phone":"+1 914 834 1443",
    "sg:postcode":"10538",
    "sg:province":"NY",
    "sg:tags":[
        "environmental",
        "org"
    ],
    "wof:name":"Sheldrake Environmental Center",
    "wof:placetype":"venue"
},
  "geometry": {"coordinates":[-73.769276,40.952001],"type":"Point"}
}