{
  "type": "Feature",
  "properties": {
    "addr:full":"164 Mace Chasm Rd Keeseville NY 12944",
    "addr:housenumber":"164",
    "addr:postcode":"12944",
    "addr:street":"Mace Chasm Rd",
    "iso:country":"US",
    "sg:address":"164 Mace Chasm Rd",
    "sg:city":"Keeseville",
    "sg:classifiers":[
        {
            "category":"Recreation",
            "type":"Entertainment"
        }
    ],
    "sg:phone":"+1 518 834 5046",
    "sg:postcode":"12944",
    "sg:province":"NY",
    "sg:tags":[
        "stable"
    ],
    "wof:name":"Paradise Stables",
    "wof:placetype":"venue"
},
  "geometry": {"coordinates":[-73.468615,44.473473],"type":"Point"}
}