{
  "type": "Feature",
  "properties": {
    "addr:full":"148 Tate Rd Hoosick Falls NY 12090",
    "addr:housenumber":"148",
    "addr:postcode":"12090",
    "addr:street":"Tate Rd",
    "iso:country":"US",
    "sg:address":"148 Tate Rd",
    "sg:city":"Hoosick Falls",
    "sg:classifiers":[
        {
            "category":"Farming",
            "subcategory":"Dairy Farm",
            "type":"Manufacturing & Wholesale Goods"
        }
    ],
    "sg:phone":"+1 518 686 9883",
    "sg:postcode":"12090",
    "sg:province":"NY",
    "wof:name":"Luke Land Farms",
    "wof:placetype":"venue"
},
  "geometry": {"coordinates":[-73.373267,42.918322],"type":"Point"}
}