{
  "type": "Feature",
  "properties": {
    "addr:full":"9 Elmore Pl East Northport NY 11731",
    "addr:housenumber":"9",
    "addr:postcode":"11731",
    "addr:street":"Elmore Pl",
    "iso:country":"US",
    "sg:address":"9 Elmore Pl",
    "sg:city":"East Northport",
    "sg:classifiers":[
        {
            "category":"Real Estate",
            "subcategory":"Real Estate Agent",
            "type":"Services"
        }
    ],
    "sg:phone":"+1 631 499 3052",
    "sg:postcode":"11731",
    "sg:province":"NY",
    "wof:name":"Prudential",
    "wof:placetype":"venue"
},
  "geometry": {"coordinates":[-73.33183699999999,40.840032],"type":"Point"}
}