{
  "type": "Feature",
  "properties": {
    "addr:full":"750 Harry L Dr Johnson City NY 13790",
    "addr:housenumber":"750",
    "addr:postcode":"13790",
    "addr:street":"Harry L Dr",
    "iso:country":"US",
    "sg:address":"750 Harry L Dr",
    "sg:city":"Johnson City",
    "sg:classifiers":[
        {
            "category":"Bus Charters",
            "type":"Transportation"
        }
    ],
    "sg:phone":"+1 607 797 2006",
    "sg:postcode":"13790",
    "sg:province":"NY",
    "sg:tags":[
        "rental"
    ],
    "sg:website":"www.shaferbus.com",
    "wof:name":"Shafer's Bus Lines",
    "wof:placetype":"venue"
},
  "geometry": {"coordinates":[-75.979124,42.122685],"type":"Point"}
}