{
  "type": "Feature",
  "properties": {
    "addr:full":"2005 Ave U Brooklyn NY 11229",
    "addr:housenumber":"2005",
    "addr:postcode":"11229",
    "addr:street":"Ave U",
    "iso:country":"US",
    "sg:address":"2005 Ave U",
    "sg:city":"Brooklyn",
    "sg:classifiers":[
        {
            "category":"Banks & Credit Unions",
            "subcategory":"Bank",
            "type":"Services"
        }
    ],
    "sg:phone":"+1 718 769 7502",
    "sg:postcode":"11229",
    "sg:province":"NY",
    "sg:tags":[
        "cashing",
        "check"
    ],
    "wof:name":"I & B Beck Cashiers",
    "wof:placetype":"venue"
},
  "geometry": {"coordinates":[-73.950417,40.599565],"type":"Point"}
}