{
  "type": "Feature",
  "properties": {
    "iso:country":"US",
    "sg:address":"308 W Main St Ste 205",
    "sg:city":"Smithtown",
    "sg:classifiers":[
        {
            "category":"Banks & Credit Unions",
            "subcategory":"Financial Services",
            "type":"Services"
        }
    ],
    "sg:phone":"+1 631 486 2826",
    "sg:postcode":"11787",
    "sg:province":"NY",
    "sg:tags":[
        "broker",
        "mortgage"
    ],
    "wof:name":"Accent Mortgage Council",
    "wof:placetype":"venue"
},
  "geometry": {"coordinates":[-73.205955,40.856952],"type":"Point"}
}