{
  "type": "Feature",
  "properties": {
    "addr:full":"2317 Washington Avenue Bronx NY 10458",
    "addr:housenumber":"2317",
    "addr:postcode":"10458",
    "addr:street":"Washington Avenue",
    "iso:country":"US",
    "sg:address":"2317 Washington Avenue",
    "sg:city":"Bronx",
    "sg:classifiers":[
        {
            "category":"Organizations",
            "subcategory":"Religious Organization",
            "type":"Services"
        }
    ],
    "sg:phone":"+1 718 561 8248",
    "sg:postcode":"10458",
    "sg:province":"NY",
    "wof:name":"Yarumal Mission Society",
    "wof:placetype":"venue"
},
  "geometry": {"coordinates":[-73.892982,40.855618],"type":"Point"}
}