{
  "type": "Feature",
  "properties": {
    "iso:country":"US",
    "sg:address":"3173 Long Beach Rd",
    "sg:city":"Oceanside",
    "sg:classifiers":[
        {
            "category":"Shopping",
            "subcategory":"Clothing, Apparel, & Fashions",
            "type":"Retail Goods"
        }
    ],
    "sg:phone":"+1 516 766 3100",
    "sg:postcode":"11572",
    "sg:province":"NY",
    "sg:tags":[
        "handbag",
        "luggage"
    ],
    "wof:name":"Protass",
    "wof:placetype":"venue"
},
  "geometry": {"coordinates":[-73.640404,40.634701],"type":"Point"}
}