{
  "type": "Feature",
  "properties": {
    "iso:country":"US",
    "sg:address":"91 Longfellow Ave",
    "sg:city":"Levittown",
    "sg:classifiers":[
        {
            "category":"Banks & Credit Unions",
            "subcategory":"Investment Brokerage",
            "type":"Services"
        }
    ],
    "sg:phone":"+1 516 622 9312",
    "sg:postcode":"11756",
    "sg:province":"NY",
    "sg:tags":[
        "advisory"
    ],
    "wof:name":"De Oliveira Development",
    "wof:placetype":"venue"
},
  "geometry": {"coordinates":[-73.491821,40.722991],"type":"Point"}
}