{
  "type": "Feature",
  "properties": {
    "addr:full":"4211 Sunset Dr Marion NY 14505",
    "addr:housenumber":"4211",
    "addr:postcode":"14505",
    "addr:street":"Sunset Dr",
    "iso:country":"US",
    "sg:address":"4211 Sunset Dr",
    "sg:city":"Marion",
    "sg:classifiers":[
        {
            "category":"Professional",
            "subcategory":"Business Services",
            "type":"Services"
        },
        {
            "category":"Utilities",
            "type":"Services"
        }
    ],
    "sg:phone":"+1 315 926 6856",
    "sg:postcode":"14505",
    "sg:province":"NY",
    "sg:tags":[
        "water",
        "treatment"
    ],
    "wof:name":"Alpha Omega Environmental Inc",
    "wof:placetype":"venue"
},
  "geometry": {"coordinates":[-77.181894,43.147457],"type":"Point"}
}