{
  "type": "Feature",
  "properties": {
    "iso:country":"US",
    "sg:address":"514 Stewarts Corners Rd",
    "sg:city":"Pennellville",
    "sg:classifiers":[
        {
            "category":"Farming",
            "subcategory":"Orchard",
            "type":"Manufacturing & Wholesale Goods"
        },
        {
            "category":"Retail",
            "subcategory":"Animal Services",
            "type":"Services"
        }
    ],
    "sg:phone":"+1 315 695 4702",
    "sg:postcode":"13132",
    "sg:province":"NY",
    "sg:tags":[
        "transportation",
        "livestock",
        "hauling"
    ],
    "wof:name":"Lawrence Town",
    "wof:placetype":"venue"
},
  "geometry": {"coordinates":[-76.262308,43.280778],"type":"Point"}
}