{
  "type": "Feature",
  "properties": {
    "iso:country":"US",
    "sg:address":"1862 8th Ave",
    "sg:city":"Watervliet",
    "sg:classifiers":[
        {
            "category":"Bars & Pubs",
            "type":"Food & Drink"
        },
        {
            "category":"Restaurant",
            "type":"Food & Drink"
        }
    ],
    "sg:phone":"+1 518 326 0104",
    "sg:postcode":"12189",
    "sg:province":"NY",
    "sg:tags":[
        "tavern"
    ],
    "wof:name":"Larry's Tavern",
    "wof:placetype":"venue"
},
  "geometry": {"coordinates":[-73.707561,42.731019],"type":"Point"}
}