{
  "type": "Feature",
  "properties": {
    "addr:full":"155 E Main St Smithtown NY 11787",
    "addr:housenumber":"155",
    "addr:postcode":"11787",
    "addr:street":"E Main St",
    "iso:country":"US",
    "sg:address":"155 E Main St",
    "sg:city":"Smithtown",
    "sg:classifiers":[
        {
            "category":"Professional",
            "subcategory":"Management & Consulting",
            "type":"Services"
        }
    ],
    "sg:phone":"+1 631 724 9100",
    "sg:postcode":"11787",
    "sg:province":"NY",
    "sg:tags":[
        "marketing"
    ],
    "wof:name":"Pro Ctive Direct Marketing",
    "wof:placetype":"venue"
},
  "geometry": {"coordinates":[-73.183671,40.856169],"type":"Point"}
}