{
  "type": "Feature",
  "properties": {
    "addr:full":"2507 James St Syracuse NY 13206",
    "addr:housenumber":"2507",
    "addr:postcode":"13206",
    "addr:street":"James St",
    "iso:country":"US",
    "sg:address":"2507 James St",
    "sg:city":"Syracuse",
    "sg:classifiers":[
        {
            "category":"Government",
            "subcategory":"Post Office",
            "type":"Public Place"
        }
    ],
    "sg:phone":"+1 315 463 8822",
    "sg:postcode":"13206",
    "sg:province":"NY",
    "wof:name":"US Post Office",
    "wof:placetype":"venue"
},
  "geometry": {"coordinates":[-76.11201,43.068574],"type":"Point"}
}