{
  "type": "Feature",
  "properties": {
    "addr:full":"181 2nd Ave Brooklyn NY 11215",
    "addr:housenumber":"181",
    "addr:postcode":"11215",
    "addr:street":"2Nd Ave",
    "iso:country":"US",
    "sg:address":"181 2nd Ave",
    "sg:city":"Brooklyn",
    "sg:classifiers":[
        {
            "category":"Home & Garden",
            "subcategory":"Building Materials",
            "type":"Retail Goods"
        }
    ],
    "sg:phone":"+1 718 768 5141",
    "sg:postcode":"11215",
    "sg:province":"NY",
    "wof:name":"F Ranieri & Son Corp",
    "wof:placetype":"venue"
},
  "geometry": {"coordinates":[-73.996398,40.668991],"type":"Point"}
}