{
  "type": "Feature",
  "properties": {
    "addr:full":"1007 Clarkson Ave Brooklyn NY 11212",
    "addr:housenumber":"1007",
    "addr:postcode":"11212",
    "addr:street":"Clarkson Ave",
    "iso:country":"US",
    "sg:address":"1007 Clarkson Ave",
    "sg:city":"Brooklyn",
    "sg:classifiers":[
        {
            "category":"Restaurant",
            "type":"Food & Drink"
        }
    ],
    "sg:phone":"+1   ",
    "sg:postcode":"11212",
    "sg:province":"NY",
    "sg:tags":[
        "chinese"
    ],
    "wof:name":"Chinese 1",
    "wof:placetype":"venue"
},
  "geometry": {"coordinates":[-73.924075,40.658619],"type":"Point"}
}