{
  "type": "Feature",
  "properties": {
    "iso:country":"US",
    "sg:address":"95 Maher Ln",
    "sg:city":"Harriman",
    "sg:classifiers":[
        {
            "category":"Arena",
            "subcategory":"Sports Club",
            "type":"Entertainment"
        }
    ],
    "sg:phone":"+1 845 781 7822",
    "sg:postcode":"10926",
    "sg:province":"NY",
    "sg:tags":[
        "martial art"
    ],
    "wof:name":"United Martial Arts Center",
    "wof:placetype":"venue"
},
  "geometry": {"coordinates":[-74.139942,41.312992],"type":"Point"}
}