{
  "type": "Feature",
  "properties": {
    "iso:country":"US",
    "sg:address":"11 Benson Pl",
    "sg:city":"Wurtsboro",
    "sg:classifiers":[
        {
            "category":"Building & Trades",
            "subcategory":"Plumbing",
            "type":"Services"
        },
        {
            "category":"Home & Garden",
            "subcategory":"Hardware",
            "type":"Retail Goods"
        }
    ],
    "sg:phone":"+1 845 888 5755",
    "sg:postcode":"12790",
    "sg:province":"NY",
    "sg:tags":[
        "filtration",
        "supply",
        "work",
        "purification",
        "water",
        "equipment"
    ],
    "sg:website":"http://www.jco.ascopubs.org",
    "wof:name":"Jco Inc",
    "wof:placetype":"venue"
},
  "geometry": {"coordinates":[-74.48680299999999,41.574284],"type":"Point"}
}