{
  "type": "Feature",
  "properties": {
    "iso:country":"US",
    "sg:address":"170 US Hwy 9w",
    "sg:city":"Congers",
    "sg:classifiers":[
        {
            "category":"Building & Trades",
            "subcategory":"Electrical",
            "type":"Services"
        }
    ],
    "sg:phone":"+1 845 267 2339",
    "sg:postcode":"10920",
    "sg:province":"NY",
    "sg:tags":[
        "electric",
        "contractor"
    ],
    "wof:name":"Allphase Electric LLC",
    "wof:placetype":"venue"
},
  "geometry": {"coordinates":[-73.92882299999999,41.160685],"type":"Point"}
}