{
  "type": "Feature",
  "properties": {
    "iso:country":"US",
    "sg:address":"86 Argonne Rd E",
    "sg:city":"Hampton Bays",
    "sg:classifiers":[
        {
            "category":"Education",
            "subcategory":"School",
            "type":"Public Place"
        }
    ],
    "sg:phone":"+1 631 723 2100",
    "sg:postcode":"11946",
    "sg:province":"NY",
    "sg:website":"www.hbschools.us",
    "wof:name":"Hampton Bays School District",
    "wof:placetype":"venue"
},
  "geometry": {"coordinates":[-72.509924,40.875408],"type":"Point"}
}