{
  "type": "Feature",
  "properties": {
    "iso:country":"US",
    "sg:address":"293 George Rd",
    "sg:city":"Freeville",
    "sg:classifiers":[
        {
            "category":"Retail",
            "subcategory":"Auto Repair",
            "type":"Services"
        }
    ],
    "sg:phone":"+1 607 844 3926",
    "sg:postcode":"13068",
    "sg:province":"NY",
    "sg:tags":[
        "repairing",
        "automobile"
    ],
    "wof:name":"Foxes Automotive",
    "wof:placetype":"venue"
},
  "geometry": {"coordinates":[-76.32861699999999,42.496776],"type":"Point"}
}