{
  "type": "Feature",
  "properties": {
    "iso:country":"US",
    "sg:address":"372 Central Park W",
    "sg:city":"New York",
    "sg:classifiers":[
        {
            "category":"Health Services",
            "subcategory":"Doctor",
            "type":"Services"
        }
    ],
    "sg:phone":"+1 212 721 1300",
    "sg:postcode":"10025",
    "sg:province":"NY",
    "wof:name":"Y Mamdani Medical Services PC",
    "wof:placetype":"venue"
},
  "geometry": {"coordinates":[-73.96427199999999,40.79252],"type":"Point"}
}