{
  "type": "Feature",
  "properties": {
    "iso:country":"US",
    "sg:address":"808 Palmer Ave",
    "sg:city":"Mamaroneck",
    "sg:classifiers":[
        {
            "category":"Autos & Motor Vehicles",
            "subcategory":"Fuel & Gas Station",
            "type":"Retail Goods"
        }
    ],
    "sg:phone":"+1   ",
    "sg:postcode":"10543",
    "sg:province":"NY",
    "sg:tags":[
        "station",
        "gasoline"
    ],
    "wof:name":"Twin Acres Service Station",
    "wof:placetype":"venue"
},
  "geometry": {"coordinates":[-73.745744,40.94359],"type":"Point"}
}