{
  "type": "Feature",
  "properties": {
    "addr:full":"218-01 41 Avenue Long Island City NY 11101",
    "addr:housenumber":"218-01",
    "addr:postcode":"11101",
    "addr:street":"41 Avenue",
    "iso:country":"US",
    "sg:address":"218-01 41 Avenue",
    "sg:city":"Long Island City",
    "sg:classifiers":[
        {
            "category":"Education",
            "subcategory":"School",
            "type":"Public Place"
        }
    ],
    "sg:phone":"+1 718 937 6005",
    "sg:postcode":"11101",
    "sg:province":"NY",
    "sg:tags":[
        "high",
        "middle",
        "elementary"
    ],
    "wof:name":"N Y City of",
    "wof:placetype":"venue"
},
  "geometry": {"coordinates":[-73.94108799999999,40.748843],"type":"Point"}
}