{
  "type": "Feature",
  "properties": {
    "addr:full":"225 E 70 St New York NY 10021",
    "addr:housenumber":"225;70",
    "addr:postcode":"10021",
    "addr:street":"E;St",
    "iso:country":"US",
    "sg:address":"225 E 70 St",
    "sg:city":"New York",
    "sg:classifiers":[
        {
            "category":"Professional",
            "subcategory":"Engineering",
            "type":"Services"
        }
    ],
    "sg:phone":"+1 212 585 1626",
    "sg:postcode":"10021",
    "sg:province":"NY",
    "sg:tags":[
        "planner",
        "architect",
        "engineer"
    ],
    "wof:name":"Courland Raphael H",
    "wof:placetype":"venue"
},
  "geometry": {"coordinates":[-73.959489,40.767674],"type":"Point"}
}