{
  "type": "Feature",
  "properties": {
    "iso:country":"US",
    "sg:address":"6540 Old Lake Shore Rd",
    "sg:city":"Derby",
    "sg:classifiers":[
        {
            "category":"Professional",
            "subcategory":"Lawyer & Legal Services",
            "type":"Services"
        }
    ],
    "sg:phone":"+1   ",
    "sg:postcode":"14047",
    "sg:province":"NY",
    "wof:name":"Stasia Z Vogel Attorney",
    "wof:placetype":"venue"
},
  "geometry": {"coordinates":[-78.975398,42.709037],"type":"Point"}
}