{
  "type": "Feature",
  "properties": {
    "addr:full":"6493 Ridings Rd Syracuse NY 13206",
    "addr:housenumber":"6493",
    "addr:postcode":"13206",
    "addr:street":"Ridings Rd",
    "iso:country":"US",
    "sg:address":"6493 Ridings Rd",
    "sg:city":"Syracuse",
    "sg:classifiers":[
        {
            "category":"Shopping",
            "subcategory":"Computers & Home Electronics",
            "type":"Retail Goods"
        }
    ],
    "sg:phone":"+1 315 432 5545",
    "sg:postcode":"13206",
    "sg:province":"NY",
    "sg:tags":[
        "software"
    ],
    "wof:name":"Clear Mark",
    "wof:placetype":"venue"
},
  "geometry": {"coordinates":[-76.108656,43.085249],"type":"Point"}
}