{
  "type": "Feature",
  "properties": {
    "addr:full":"9345 Kingtown Beach Rd Trumansburg NY 14886",
    "addr:housenumber":"9345",
    "addr:postcode":"14886",
    "addr:street":"Kingtown Beach Rd",
    "iso:country":"US",
    "sg:address":"9345 Kingtown Beach Rd",
    "sg:city":"Trumansburg",
    "sg:classifiers":[
        {
            "category":"Professional",
            "subcategory":"Management & Consulting",
            "type":"Services"
        }
    ],
    "sg:phone":"+1   ",
    "sg:postcode":"14886",
    "sg:province":"NY",
    "sg:tags":[
        "business"
    ],
    "wof:name":"Jerry Feist",
    "wof:placetype":"venue"
},
  "geometry": {"coordinates":[-76.647507,42.572001],"type":"Point"}
}