{
  "type": "Feature",
  "properties": {
    "addr:full":"1709 Kings Hwy Brooklyn NY 11229",
    "addr:housenumber":"1709",
    "addr:postcode":"11229",
    "addr:street":"Kings Hwy",
    "iso:country":"US",
    "sg:address":"1709 Kings Hwy",
    "sg:city":"Brooklyn",
    "sg:classifiers":[
        {
            "category":"Shopping",
            "subcategory":"Clothing, Apparel, & Fashions",
            "type":"Retail Goods"
        }
    ],
    "sg:phone":"+1 718 998 2300",
    "sg:postcode":"11229",
    "sg:province":"NY",
    "sg:tags":[
        "tailor"
    ],
    "wof:name":"Wasserberger's Son's",
    "wof:placetype":"venue"
},
  "geometry": {"coordinates":[-73.955692,40.609974],"type":"Point"}
}