{
  "type": "Feature",
  "properties": {
    "addr:full":"5605 5th Ave Brooklyn NY 11220",
    "addr:housenumber":"5605",
    "addr:postcode":"11220",
    "addr:street":"5Th Ave",
    "iso:country":"US",
    "sg:address":"5605 5th Ave",
    "sg:city":"Brooklyn",
    "sg:classifiers":[
        {
            "category":"Food & Beverages",
            "subcategory":"Groceries & Convenience Stores",
            "type":"Retail Goods"
        }
    ],
    "sg:phone":"+1 718 492 9400",
    "sg:postcode":"11220",
    "sg:province":"NY",
    "wof:name":"La Fe",
    "wof:placetype":"venue"
},
  "geometry": {"coordinates":[-74.013802,40.641499],"type":"Point"}
}