{
  "type": "Feature",
  "properties": {
    "iso:country":"US",
    "sg:address":"274 Greece Ridge Center Dr",
    "sg:city":"Rochester",
    "sg:classifiers":[
        {
            "category":"Shopping",
            "subcategory":"Shoes",
            "type":"Retail Goods"
        }
    ],
    "sg:phone":"+1 585 225 4024",
    "sg:postcode":"14626",
    "sg:province":"NY",
    "wof:name":"Lady Foot Locker",
    "wof:placetype":"venue"
},
  "geometry": {"coordinates":[-77.696305,43.204906],"type":"Point"}
}