{
  "type": "Feature",
  "properties": {
    "iso:country":"US",
    "sg:address":"266 Sea Cliff Ave",
    "sg:city":"Sea Cliff",
    "sg:classifiers":[
        {
            "category":"Real Estate",
            "subcategory":"Real Estate Agent",
            "type":"Services"
        }
    ],
    "sg:phone":"+1 516 759 6822",
    "sg:postcode":"11579",
    "sg:province":"NY",
    "wof:name":"Gale Daniel Real Estate",
    "wof:placetype":"venue"
},
  "geometry": {"coordinates":[-73.64649900000001,40.849296],"type":"Point"}
}