{
  "type": "Feature",
  "properties": {
    "addr:full":"11134 Sutphin Blvd Jamaica NY 11435",
    "addr:housenumber":"11134",
    "addr:postcode":"11435",
    "addr:street":"Sutphin Blvd",
    "iso:country":"US",
    "sg:address":"11134 Sutphin Blvd",
    "sg:city":"Jamaica",
    "sg:classifiers":[
        {
            "category":"Restaurant",
            "type":"Food & Drink"
        }
    ],
    "sg:menulink":"http://www.allmenus.com/ny/queens/236656-guinee-restaurant-african/menu/",
    "sg:phone":"+1 718 835 5630",
    "sg:postcode":"11435",
    "sg:province":"NY",
    "sg:tags":[
        "jamaican"
    ],
    "wof:name":"Guinee Restaurant African",
    "wof:placetype":"venue"
},
  "geometry": {"coordinates":[-73.79514899999999,40.688004],"type":"Point"}
}