{
  "type": "Feature",
  "properties": {
    "addr:full":"750 E Adams St Syracuse NY 13210",
    "addr:housenumber":"750",
    "addr:postcode":"13210",
    "addr:street":"E Adams St",
    "iso:country":"US",
    "sg:address":"750 E Adams St",
    "sg:city":"Syracuse",
    "sg:classifiers":[
        {
            "category":"Health Services",
            "subcategory":"Hospital",
            "type":"Services"
        }
    ],
    "sg:phone":"+1 315 464 5540",
    "sg:postcode":"13210",
    "sg:province":"NY",
    "sg:website":"www.upstate.edu",
    "wof:name":"State University Of New York",
    "wof:placetype":"venue"
},
  "geometry": {"coordinates":[-76.13784699999999,43.042677],"type":"Point"}
}