{
  "type": "Feature",
  "properties": {
    "addr:full":"928 Broadway New York NY 10010",
    "addr:housenumber":"928",
    "addr:postcode":"10010",
    "addr:street":"Broadway",
    "iso:country":"US",
    "sg:address":"928 Broadway",
    "sg:city":"New York",
    "sg:classifiers":[
        {
            "category":"Wholesale",
            "subcategory":"Electrical",
            "type":"Manufacturing & Wholesale Goods"
        },
        {
            "category":"Manufacturing",
            "subcategory":"Tools & Machinery",
            "type":"Manufacturing & Wholesale Goods"
        }
    ],
    "sg:phone":"+1 212 254 4400",
    "sg:postcode":"10010",
    "sg:province":"NY",
    "sg:tags":[
        "lighting",
        "fixture",
        "representative"
    ],
    "wof:name":"Continental Lighting Sales",
    "wof:placetype":"venue"
},
  "geometry": {"coordinates":[-73.989389,40.740312],"type":"Point"}
}