{
  "type": "Feature",
  "properties": {
    "addr:full":"1740 E Jericho Tpke Huntington NY 11743",
    "addr:housenumber":"1740",
    "addr:postcode":"11743",
    "addr:street":"E Jericho Tpke",
    "iso:country":"US",
    "sg:address":"1740 E Jericho Tpke",
    "sg:city":"Huntington",
    "sg:classifiers":[
        {
            "category":"Banks & Credit Unions",
            "subcategory":"Bank",
            "type":"Services"
        }
    ],
    "sg:phone":"+1 631 858 1243",
    "sg:postcode":"11743",
    "sg:province":"NY",
    "sg:tags":[
        "loan",
        "real estate"
    ],
    "sg:website":"www.americanhm.com",
    "wof:name":"American Home Mortgage",
    "wof:placetype":"venue"
},
  "geometry": {"coordinates":[-73.339561,40.833416],"type":"Point"}
}