{
  "type": "Feature",
  "properties": {
    "iso:country":"US",
    "sg:address":"4507 Co Rd 16",
    "sg:city":"Canandaigua",
    "sg:classifiers":[
        {
            "category":"Professional",
            "subcategory":"Engineering",
            "type":"Services"
        }
    ],
    "sg:phone":"+1   ",
    "sg:postcode":"14424",
    "sg:province":"NY",
    "sg:tags":[
        "modeling",
        "analysis"
    ],
    "wof:name":"Fem-A",
    "wof:placetype":"venue"
},
  "geometry": {"coordinates":[-77.293678,42.810261],"type":"Point"}
}