{
  "type": "Feature",
  "properties": {
    "iso:country":"US",
    "sg:address":"155 E 31st St Apt 14F",
    "sg:city":"New York",
    "sg:classifiers":[
        {
            "category":"Health Services",
            "subcategory":"Doctor",
            "type":"Services"
        }
    ],
    "sg:phone":"+1 212 213 6156",
    "sg:postcode":"10016",
    "sg:province":"NY",
    "wof:name":"Alpert Michael C MD",
    "wof:placetype":"venue"
},
  "geometry": {"coordinates":[-73.980273,40.744373],"type":"Point"}
}