{
  "type": "Feature",
  "properties": {
    "iso:country":"US",
    "sg:address":"3159 S Winton Rd",
    "sg:city":"Rochester",
    "sg:classifiers":[
        {
            "category":"Banks & Credit Unions",
            "subcategory":"Bank",
            "type":"Services"
        }
    ],
    "sg:phone":"+1 585 272 1390",
    "sg:postcode":"14623",
    "sg:province":"NY",
    "sg:tags":[
        "federal"
    ],
    "wof:name":"Flower City Federal Credit Un",
    "wof:placetype":"venue"
},
  "geometry": {"coordinates":[-77.582036,43.089899],"type":"Point"}
}