{
  "type": "Feature",
  "properties": {
    "addr:full":"36 Hilltop Dr Springville NY 14141",
    "addr:housenumber":"36",
    "addr:postcode":"14141",
    "addr:street":"Hilltop Dr",
    "iso:country":"US",
    "sg:address":"36 Hilltop Dr",
    "sg:city":"Springville",
    "sg:classifiers":[
        {
            "category":"Building & Trades",
            "subcategory":"Construction",
            "type":"Services"
        }
    ],
    "sg:phone":"+1 716 592 3409",
    "sg:postcode":"14141",
    "sg:province":"NY",
    "sg:tags":[
        "siding",
        "contractor"
    ],
    "wof:name":"Brent D Jagow",
    "wof:placetype":"venue"
},
  "geometry": {"coordinates":[-78.65776099999999,42.512795],"type":"Point"}
}