{
  "type": "Feature",
  "properties": {
    "iso:country":"US",
    "sg:address":"65 Central Park W",
    "sg:city":"New York",
    "sg:classifiers":[
        {
            "category":"Professional",
            "subcategory":"Business Services",
            "type":"Services"
        }
    ],
    "sg:phone":"+1 212 877 7749",
    "sg:postcode":"10023",
    "sg:province":"NY",
    "wof:name":"Cherokee Group Inc",
    "wof:placetype":"venue"
},
  "geometry": {"coordinates":[-73.978497,40.772794],"type":"Point"}
}