{
  "type": "Feature",
  "properties": {
    "iso:country":"US",
    "sg:address":"319 Church Ave",
    "sg:city":"Brooklyn",
    "sg:classifiers":[
        {
            "category":"Bakery",
            "type":"Food & Drink"
        }
    ],
    "sg:phone":"+1 718 686 8371",
    "sg:postcode":"11218",
    "sg:province":"NY",
    "wof:name":"Cafe Expresso",
    "wof:placetype":"venue"
},
  "geometry": {"coordinates":[-73.977097,40.643902],"type":"Point"}
}