{
  "type": "Feature",
  "properties": {
    "iso:country":"US",
    "sg:address":"53 Shore Dr",
    "sg:city":"Rochester",
    "sg:classifiers":[
        {
            "category":"Building & Trades",
            "subcategory":"Plumbing",
            "type":"Services"
        }
    ],
    "sg:phone":"+1 585 338 9715",
    "sg:postcode":"14622",
    "sg:province":"NY",
    "sg:tags":[
        "plumber"
    ],
    "wof:name":"Bill S Sewer Drain",
    "wof:placetype":"venue"
},
  "geometry": {"coordinates":[-77.54505399999999,43.214116],"type":"Point"}
}