{
  "type": "Feature",
  "properties": {
    "iso:country":"US",
    "sg:address":"1881 Jackson Rd",
    "sg:city":"Penfield",
    "sg:classifiers":[
        {
            "category":"Social Services",
            "subcategory":"Child Care",
            "type":"Services"
        }
    ],
    "sg:phone":"+1 585 377 0122",
    "sg:postcode":"14526",
    "sg:province":"NY",
    "sg:tags":[
        "church",
        "place",
        "worship",
        "day",
        "center"
    ],
    "sg:website":"http://www.penfieldpresbyterian.org",
    "wof:name":"Penfield Day Care Center",
    "wof:placetype":"venue"
},
  "geometry": {"coordinates":[-77.454323,43.14772],"type":"Point"}
}