{
  "type": "Feature",
  "properties": {
    "addr:full":"250 Bedford Ave Brooklyn NY 11211",
    "addr:housenumber":"250",
    "addr:postcode":"11211",
    "addr:street":"Bedford Ave",
    "iso:country":"US",
    "sg:address":"250 Bedford Ave",
    "sg:city":"Brooklyn",
    "sg:classifiers":[
        {
            "category":"Shopping",
            "subcategory":"Pharmacy",
            "type":"Retail Goods"
        }
    ],
    "sg:phone":"+1 718 384 7026",
    "sg:postcode":"11211",
    "sg:province":"NY",
    "sg:tags":[
        "drugstore"
    ],
    "sg:website":"www.duanereade.com",
    "wof:name":"Duane Reade",
    "wof:placetype":"venue"
},
  "geometry": {"coordinates":[-73.96005700000001,40.715688],"type":"Point"}
}