{
  "type": "Feature",
  "properties": {
    "iso:country":"US",
    "sg:address":"703 S Decatur St",
    "sg:city":"Watkins Glen",
    "sg:classifiers":[
        {
            "category":"Health Services",
            "subcategory":"Doctor",
            "type":"Services"
        }
    ],
    "sg:phone":"+1 607 535 4929",
    "sg:postcode":"14891",
    "sg:province":"NY",
    "sg:tags":[
        "dentist"
    ],
    "wof:name":"Orthodontic Associates",
    "wof:placetype":"venue"
},
  "geometry": {"coordinates":[-76.865984,42.370961],"type":"Point"}
}