{
  "type": "Feature",
  "properties": {
    "iso:country":"US",
    "sg:address":"911 Tonawanda St",
    "sg:city":"Buffalo",
    "sg:classifiers":[
        {
            "category":"Real Estate",
            "subcategory":"Architect",
            "type":"Services"
        }
    ],
    "sg:phone":"+1 716 877 1003",
    "sg:postcode":"14207",
    "sg:province":"NY",
    "wof:name":"Construction Project Svc",
    "wof:placetype":"venue"
},
  "geometry": {"coordinates":[-78.905592,42.953165],"type":"Point"}
}