{
  "type": "Feature",
  "properties": {
    "iso:country":"US",
    "sg:address":"5 Emma Ln",
    "sg:city":"Clifton Park",
    "sg:classifiers":[
        {
            "category":"Professional",
            "subcategory":"Lawyer & Legal Services",
            "type":"Services"
        }
    ],
    "sg:phone":"+1 518 373 0333",
    "sg:postcode":"12065",
    "sg:province":"NY",
    "sg:website":"www.jwplaw.com",
    "wof:name":"Jones Bonnie McGuire Atty",
    "wof:placetype":"venue"
},
  "geometry": {"coordinates":[-73.796813,42.867451],"type":"Point"}
}