{
  "type": "Feature",
  "properties": {
    "iso:country":"US",
    "sg:address":"300 Woodcleft Ave",
    "sg:city":"Freeport",
    "sg:classifiers":[
        {
            "category":"Real Estate",
            "subcategory":"Real Estate Services",
            "type":"Services"
        }
    ],
    "sg:phone":"+1 516 623 4340",
    "sg:postcode":"11520",
    "sg:province":"NY",
    "sg:tags":[
        "company",
        "title"
    ],
    "wof:name":"Secure Land LLC",
    "wof:placetype":"venue"
},
  "geometry": {"coordinates":[-73.58163,40.631627],"type":"Point"}
}