{
  "type": "Feature",
  "properties": {
    "addr:full":"3725 Jeffrey Blvd Buffalo NY 14219",
    "addr:housenumber":"3725",
    "addr:postcode":"14219",
    "addr:street":"Jeffrey Blvd",
    "iso:country":"US",
    "sg:address":"3725 Jeffrey Blvd",
    "sg:city":"Buffalo",
    "sg:classifiers":[
        {
            "category":"Building & Trades",
            "subcategory":"Equipment Rental",
            "type":"Services"
        }
    ],
    "sg:phone":"+1 716 822 4515",
    "sg:postcode":"14219",
    "sg:province":"NY",
    "sg:tags":[
        "environmental",
        "industrial",
        "leasing"
    ],
    "wof:name":"Baker Tanks Inc",
    "wof:placetype":"venue"
},
  "geometry": {"coordinates":[-78.834541,42.785961],"type":"Point"}
}