{
  "type": "Feature",
  "properties": {
    "addr:full":"1527 39th St Brooklyn NY 11218",
    "addr:housenumber":"1527",
    "addr:postcode":"11218",
    "addr:street":"39Th St",
    "iso:country":"US",
    "sg:address":"1527 39th St",
    "sg:city":"Brooklyn",
    "sg:classifiers":[
        {
            "category":"Organizations",
            "subcategory":"Religious Organization",
            "type":"Services"
        }
    ],
    "sg:phone":"+1 718 431 1424",
    "sg:postcode":"11218",
    "sg:province":"NY",
    "sg:tags":[
        "clergy"
    ],
    "wof:name":"Shia H Jungreis",
    "wof:placetype":"venue"
},
  "geometry": {"coordinates":[-73.98007800000001,40.637049],"type":"Point"}
}