{
  "type": "Feature",
  "properties": {
    "addr:full":"17 E 65 St New York NY 10065",
    "addr:housenumber":"17;65",
    "addr:postcode":"10065",
    "addr:street":"E;St",
    "iso:country":"US",
    "sg:address":"17 E 65 St",
    "sg:city":"New York",
    "sg:classifiers":[
        {
            "category":"Building & Trades",
            "subcategory":"Construction",
            "type":"Services"
        }
    ],
    "sg:phone":"+1 212 628 1335",
    "sg:postcode":"10065",
    "sg:province":"NY",
    "sg:tags":[
        "hanging",
        "contractor"
    ],
    "wof:name":"Martin J Zimet",
    "wof:placetype":"venue"
},
  "geometry": {"coordinates":[-73.969448,40.767863],"type":"Point"}
}