{
  "type": "Feature",
  "properties": {
    "iso:country":"US",
    "sg:address":"135 Oser Ave",
    "sg:city":"Hauppauge",
    "sg:classifiers":[
        {
            "category":"Manufacturing",
            "subcategory":"Printing",
            "type":"Manufacturing & Wholesale Goods"
        }
    ],
    "sg:phone":"+1   ",
    "sg:postcode":"11788",
    "sg:province":"NY",
    "sg:tags":[
        "periodical"
    ],
    "wof:name":"Twentieth Century Guitar",
    "wof:placetype":"venue"
},
  "geometry": {"coordinates":[-73.246048,40.817173],"type":"Point"}
}