{
  "type": "Feature",
  "properties": {
    "iso:country":"US",
    "sg:address":"33 West St",
    "sg:city":"Warwick",
    "sg:classifiers":[
        {
            "category":"Retail",
            "subcategory":"Auto Repair",
            "type":"Services"
        }
    ],
    "sg:phone":"+1 845 986 3689",
    "sg:postcode":"10990",
    "sg:province":"NY",
    "sg:tags":[
        "repairing",
        "automobile"
    ],
    "wof:name":"Doty Automotive",
    "wof:placetype":"venue"
},
  "geometry": {"coordinates":[-74.362094,41.256664],"type":"Point"}
}