{
  "type": "Feature",
  "properties": {
    "addr:full":"2663 Wehrle Dr Buffalo NY 14221",
    "addr:postcode":"2663;14221",
    "addr:street":"Wehrle Dr",
    "iso:country":"US",
    "sg:address":"2663 Wehrle Dr",
    "sg:city":"Buffalo",
    "sg:classifiers":[
        {
            "category":"Social Services",
            "subcategory":"Adult Care",
            "type":"Services"
        }
    ],
    "sg:phone":"+1 716 632 2568",
    "sg:postcode":"14221",
    "sg:province":"NY",
    "sg:tags":[
        "home",
        "group",
        "residential"
    ],
    "wof:name":"Wehrle Residence",
    "wof:placetype":"venue"
},
  "geometry": {"coordinates":[-78.69380099999999,42.9563],"type":"Point"}
}