{
  "type": "Feature",
  "properties": {
    "addr:full":"125 W Tremont Ave Bronx NY 10453",
    "addr:housenumber":"125",
    "addr:postcode":"10453",
    "addr:street":"W Tremont Ave",
    "iso:country":"US",
    "sg:address":"125 W Tremont Ave",
    "sg:city":"Bronx",
    "sg:classifiers":[
        {
            "category":"Professional",
            "type":"Services"
        }
    ],
    "sg:phone":"+1 718 466 5534",
    "sg:postcode":"10453",
    "sg:province":"NY",
    "wof:name":"Tres K Multiservice",
    "wof:placetype":"venue"
},
  "geometry": {"coordinates":[-73.91346799999999,40.850155],"type":"Point"}
}