{
  "type": "Feature",
  "properties": {
    "addr:full":"156 Hope St Ste 1 Brooklyn NY 11211",
    "addr:housenumber":"156",
    "addr:postcode":"11211",
    "addr:street":"Hope St Ste 1",
    "iso:country":"US",
    "sg:address":"156 Hope St Ste 1",
    "sg:city":"Brooklyn",
    "sg:classifiers":[
        {
            "category":"Real Estate",
            "subcategory":"Real Estate Services",
            "type":"Services"
        }
    ],
    "sg:phone":"+1 718 355 9002",
    "sg:postcode":"11211",
    "sg:province":"NY",
    "wof:name":"Prime Quarters",
    "wof:placetype":"venue"
},
  "geometry": {"coordinates":[-73.952056,40.711741],"type":"Point"}
}