{
  "type": "Feature",
  "properties": {
    "iso:country":"US",
    "sg:address":"644 E 3rd St",
    "sg:city":"Brooklyn",
    "sg:classifiers":[
        {
            "category":"Building & Trades",
            "subcategory":"Construction",
            "type":"Services"
        }
    ],
    "sg:phone":"+1 718 972 2196",
    "sg:postcode":"11218",
    "sg:province":"NY",
    "sg:tags":[
        "contractor"
    ],
    "sg:website":"www.progressiveconstructiongroup...",
    "wof:name":"Progressive Construction Group Inc",
    "wof:placetype":"venue"
},
  "geometry": {"coordinates":[-73.976225,40.636262],"type":"Point"}
}