{
  "type": "Feature",
  "properties": {
    "addr:full":"2024 Hillside Ave New Hyde Park NY 11040",
    "addr:housenumber":"2024",
    "addr:postcode":"11040",
    "addr:street":"Hillside Ave",
    "iso:country":"US",
    "sg:address":"2024 Hillside Ave",
    "sg:city":"New Hyde Park",
    "sg:classifiers":[
        {
            "category":"Restaurant",
            "type":"Food & Drink"
        }
    ],
    "sg:phone":"+1 516 488 5100",
    "sg:postcode":"11040",
    "sg:province":"NY",
    "wof:name":"Portofino",
    "wof:placetype":"venue"
},
  "geometry": {"coordinates":[-73.70084,40.738934],"type":"Point"}
}