{
  "type": "Feature",
  "properties": {
    "addr:full":"1 Park Pl Ste 215 Fredonia NY 14063",
    "addr:housenumber":"1",
    "addr:postcode":"14063",
    "addr:street":"Park Pl Ste 215",
    "iso:country":"US",
    "sg:address":"1 Park Pl Ste 215",
    "sg:city":"Fredonia",
    "sg:classifiers":[
        {
            "category":"Health Services",
            "subcategory":"Dentist",
            "type":"Services"
        }
    ],
    "sg:phone":"+1 716 672 4363",
    "sg:postcode":"14063",
    "sg:province":"NY",
    "wof:name":"John Jou, D.M.D. And Thy A. Bui, D.M.D., P.C.",
    "wof:placetype":"venue"
},
  "geometry": {"coordinates":[-79.34931899999999,42.453609],"type":"Point"}
}