{
  "type": "Feature",
  "properties": {
    "addr:full":"1104 Lafayette Avenue Brooklyn NY 11221",
    "addr:housenumber":"1104",
    "addr:postcode":"11221",
    "addr:street":"Lafayette Avenue",
    "iso:country":"US",
    "sg:address":"1104 Lafayette Avenue",
    "sg:city":"Brooklyn",
    "sg:classifiers":[
        {
            "category":"Restaurant",
            "type":"Food & Drink"
        }
    ],
    "sg:phone":"+1 718 455 5413",
    "sg:postcode":"11221",
    "sg:province":"NY",
    "sg:tags":[
        "pizza"
    ],
    "wof:name":"Kennedy Pizza & Chicken",
    "wof:placetype":"venue"
},
  "geometry": {"coordinates":[-73.927604,40.692494],"type":"Point"}
}