{
  "type": "Feature",
  "properties": {
    "addr:full":"38 Main St Warwick NY 10990",
    "addr:housenumber":"38",
    "addr:postcode":"10990",
    "addr:street":"Main St",
    "iso:country":"US",
    "sg:address":"38 Main St",
    "sg:city":"Warwick",
    "sg:classifiers":[
        {
            "category":"Shopping",
            "subcategory":"Jewelry",
            "type":"Retail Goods"
        }
    ],
    "sg:phone":"+1 845 986 2248",
    "sg:postcode":"10990",
    "sg:province":"NY",
    "sg:tags":[
        "diamond"
    ],
    "sg:website":"http://foreverjewelers.com",
    "wof:name":"Forever Jewelers",
    "wof:placetype":"venue"
},
  "geometry": {"coordinates":[-74.359577,41.257078],"type":"Point"}
}