{
  "type": "Feature",
  "properties": {
    "iso:country":"US",
    "sg:address":"10702 101st Ave",
    "sg:city":"Ozone Park",
    "sg:classifiers":[
        {
            "category":"Deli",
            "type":"Food & Drink"
        },
        {
            "category":"Food & Beverages",
            "subcategory":"Bakery",
            "type":"Retail Goods"
        }
    ],
    "sg:phone":"+1 718 322 6540",
    "sg:postcode":"11416",
    "sg:province":"NY",
    "sg:tags":[
        "sandwich"
    ],
    "wof:name":"Taste Deli & Grill",
    "wof:placetype":"venue"
},
  "geometry": {"coordinates":[-73.835947,40.68697],"type":"Point"}
}