{
  "type": "Feature",
  "properties": {
    "addr:full":"1 United Nations Plz New York NY 10017",
    "addr:housenumber":"1",
    "addr:postcode":"10017",
    "addr:street":"United Nations Plz",
    "iso:country":"US",
    "sg:address":"1 United Nations Plz",
    "sg:city":"New York",
    "sg:classifiers":[
        {
            "category":"Banks & Credit Unions",
            "subcategory":"Bank",
            "type":"Services"
        }
    ],
    "sg:phone":"+1 212 740 7093",
    "sg:postcode":"10017",
    "sg:province":"NY",
    "wof:name":"Chase",
    "wof:placetype":"venue"
},
  "geometry": {"coordinates":[-73.96910699999999,40.749426],"type":"Point"}
}