{
  "type": "Feature",
  "properties": {
    "iso:country":"US",
    "sg:address":"989 Atlantic Ave",
    "sg:city":"Baldwin",
    "sg:classifiers":[
        {
            "category":"Food & Beverages",
            "subcategory":"Bakery",
            "type":"Retail Goods"
        }
    ],
    "sg:phone":"+1 516 868 2101",
    "sg:postcode":"11510",
    "sg:province":"NY",
    "sg:tags":[
        "baker"
    ],
    "wof:name":"Milburn Enterprises",
    "wof:placetype":"venue"
},
  "geometry": {"coordinates":[-73.608349,40.639604],"type":"Point"}
}