{
  "type": "Feature",
  "properties": {
    "addr:full":"1659 1st Ave New York NY 10028",
    "addr:housenumber":"1659",
    "addr:postcode":"10028",
    "addr:street":"1St Ave",
    "iso:country":"US",
    "sg:address":"1659 1st Ave",
    "sg:city":"New York",
    "sg:classifiers":[
        {
            "category":"Restaurant",
            "type":"Food & Drink"
        }
    ],
    "sg:menulink":"http://www.allmenus.com/ny/new-york/7481-taco-today/menu/",
    "sg:phone":"+1 212 860 2266",
    "sg:postcode":"10028",
    "sg:province":"NY",
    "sg:tags":[
        "mexican"
    ],
    "wof:name":"Taco Today",
    "wof:placetype":"venue"
},
  "geometry": {"coordinates":[-73.949106,40.777221],"type":"Point"}
}