{
  "type": "Feature",
  "properties": {
    "iso:country":"US",
    "sg:address":"8 Secor Glen Rd",
    "sg:city":"Hartsdale",
    "sg:classifiers":[
        {
            "category":"Arts & Performance",
            "subcategory":"Theater",
            "type":"Entertainment"
        }
    ],
    "sg:phone":"+1 914 682 1818",
    "sg:postcode":"10530",
    "sg:province":"NY",
    "sg:tags":[
        "magician"
    ],
    "wof:name":"Will Astound You Prdctns Inc",
    "wof:placetype":"venue"
},
  "geometry": {"coordinates":[-73.81933100000001,41.029528],"type":"Point"}
}