{
  "type": "Feature",
  "properties": {
    "iso:country":"US",
    "sg:address":"171 Marshall St",
    "sg:city":"Syracuse",
    "sg:classifiers":[
        {
            "category":"Personal",
            "subcategory":"Tattoo Parlor",
            "type":"Services"
        }
    ],
    "sg:phone":"+1 315 472 0854",
    "sg:postcode":"13210",
    "sg:province":"NY",
    "sg:tags":[
        "tattooing"
    ],
    "wof:name":"Halo Tattoo's",
    "wof:placetype":"venue"
},
  "geometry": {"coordinates":[-76.135593,43.041669],"type":"Point"}
}