{
  "type": "Feature",
  "properties": {
    "iso:country":"US",
    "sg:address":"463 E 178th St",
    "sg:city":"Bronx",
    "sg:classifiers":[
        {
            "category":"Shopping",
            "subcategory":"Music",
            "type":"Retail Goods"
        }
    ],
    "sg:phone":"+1   ",
    "sg:postcode":"10457",
    "sg:province":"NY",
    "wof:name":"Cima Records",
    "wof:placetype":"venue"
},
  "geometry": {"coordinates":[-73.89777599999999,40.848584],"type":"Point"}
}