{
  "type": "Feature",
  "properties": {
    "addr:full":"6 Oxford Ct Apt 8001 Suffern NY 10901",
    "addr:housenumber":"6",
    "addr:postcode":"8001;10901",
    "addr:street":"Oxford Ct Apt",
    "iso:country":"US",
    "sg:address":"6 Oxford Ct Apt 8001",
    "sg:city":"Suffern",
    "sg:classifiers":[
        {
            "category":"Real Estate",
            "subcategory":"Real Estate Services",
            "type":"Services"
        },
        {
            "category":"Real Estate",
            "subcategory":"Real Estate Agent",
            "type":"Services"
        }
    ],
    "sg:phone":"+1 845 357 9100",
    "sg:postcode":"10901",
    "sg:province":"NY",
    "sg:tags":[
        "buyer",
        "broker"
    ],
    "wof:name":"Clair Realty Co",
    "wof:placetype":"venue"
},
  "geometry": {"coordinates":[-74.13017000000001,41.105464],"type":"Point"}
}