{
  "type": "Feature",
  "properties": {
    "iso:country":"US",
    "sg:address":"50 Floyds Run",
    "sg:city":"Bohemia",
    "sg:classifiers":[
        {
            "category":"Wholesale",
            "subcategory":"Machinery & Supplies",
            "type":"Manufacturing & Wholesale Goods"
        }
    ],
    "sg:phone":"+1 631 244 7979",
    "sg:postcode":"11716",
    "sg:province":"NY",
    "sg:tags":[
        "used"
    ],
    "sg:website":"www.wohlassociates.com",
    "wof:name":"Wohl Associates Inc",
    "wof:placetype":"venue"
},
  "geometry": {"coordinates":[-73.115756,40.782407],"type":"Point"}
}