{
  "type": "Feature",
  "properties": {
    "addr:full":"12 Scott St Bainbridge NY 13733",
    "addr:housenumber":"12",
    "addr:postcode":"13733",
    "addr:street":"Scott St",
    "iso:country":"US",
    "sg:address":"12 Scott St",
    "sg:city":"Bainbridge",
    "sg:classifiers":[
        {
            "category":"Shopping",
            "subcategory":"Clothing, Apparel, & Fashions",
            "type":"Retail Goods"
        }
    ],
    "sg:phone":"+1 607 967 4264",
    "sg:postcode":"13733",
    "sg:province":"NY",
    "wof:name":"BFG Clothiers",
    "wof:placetype":"venue"
},
  "geometry": {"coordinates":[-75.483194,42.293781],"type":"Point"}
}