{
  "type": "Feature",
  "properties": {
    "iso:country":"US",
    "sg:address":"15 N Main St",
    "sg:city":"Earlville",
    "sg:classifiers":[
        {
            "category":"Real Estate",
            "subcategory":"Real Estate Agent",
            "type":"Services"
        }
    ],
    "sg:phone":"+1 315 691 3011",
    "sg:postcode":"13332",
    "sg:province":"NY",
    "wof:name":"Corey's Real Estate",
    "wof:placetype":"venue"
},
  "geometry": {"coordinates":[-75.545337,42.74044],"type":"Point"}
}