{
  "type": "Feature",
  "properties": {
    "addr:full":"1153 Liberty Ave Brooklyn NY 11208",
    "addr:housenumber":"1153",
    "addr:postcode":"11208",
    "addr:street":"Liberty Ave",
    "iso:country":"US",
    "sg:address":"1153 Liberty Ave",
    "sg:city":"Brooklyn",
    "sg:classifiers":[
        {
            "category":"Home & Garden",
            "subcategory":"Home Furnishings",
            "type":"Retail Goods"
        }
    ],
    "sg:phone":"+1   ",
    "sg:postcode":"11208",
    "sg:province":"NY",
    "sg:tags":[
        "linen",
        "novelty"
    ],
    "wof:name":"Perfect Home Linen Corp",
    "wof:placetype":"venue"
},
  "geometry": {"coordinates":[-73.86648599999999,40.678856],"type":"Point"}
}