{
  "type": "Feature",
  "properties": {
    "iso:country":"US",
    "sg:address":"22415 Linden Boulevard",
    "sg:city":"Cambria Heights",
    "sg:classifiers":[
        {
            "category":"Restaurant",
            "type":"Food & Drink"
        }
    ],
    "sg:phone":"+1 718 525 8284",
    "sg:postcode":"11411",
    "sg:province":"NY",
    "wof:name":"Boston Jerk Palace & Restaurant",
    "wof:placetype":"venue"
},
  "geometry": {"coordinates":[-73.736003,40.693967],"type":"Point"}
}