{
  "type": "Feature",
  "properties": {
    "iso:country":"US",
    "sg:address":"5133 Aten Rd",
    "sg:city":"Groveland",
    "sg:classifiers":[
        {
            "category":"Building & Trades",
            "subcategory":"Construction",
            "type":"Services"
        }
    ],
    "sg:phone":"+1 585 243 4181",
    "sg:postcode":"14462",
    "sg:province":"NY",
    "sg:tags":[
        "contractor"
    ],
    "wof:name":"Tim Seely Roofing",
    "wof:placetype":"venue"
},
  "geometry": {"coordinates":[-77.749067,42.701679],"type":"Point"}
}