{
  "type": "Feature",
  "properties": {
    "iso:country":"US",
    "sg:address":"150 Wyandanch Ave",
    "sg:city":"Wyandanch",
    "sg:classifiers":[
        {
            "category":"Wholesale",
            "subcategory":"Home Furnishings",
            "type":"Manufacturing & Wholesale Goods"
        }
    ],
    "sg:phone":"+1 631 643 8274",
    "sg:postcode":"11798",
    "sg:province":"NY",
    "sg:tags":[
        "plumbing",
        "supplies-wholesale",
        "part",
        "fixture",
        "manufacturer"
    ],
    "sg:website":"http://www.tashsales.com",
    "wof:name":"Tash Sales Co., Inc.",
    "wof:placetype":"venue"
},
  "geometry": {"coordinates":[-73.359099,40.741616],"type":"Point"}
}