{
  "type": "Feature",
  "properties": {
    "addr:full":"7254 Amboy Rd Staten Island NY 10307",
    "addr:housenumber":"7254",
    "addr:postcode":"10307",
    "addr:street":"Amboy Rd",
    "iso:country":"US",
    "sg:address":"7254 Amboy Rd",
    "sg:city":"Staten Island",
    "sg:classifiers":[
        {
            "category":"Food & Beverages",
            "subcategory":"Groceries & Convenience Stores",
            "type":"Retail Goods"
        }
    ],
    "sg:phone":"+1 718 967 4700",
    "sg:postcode":"10307",
    "sg:province":"NY",
    "sg:tags":[
        "grocer"
    ],
    "wof:name":"Tottenville Food Mart Inc",
    "wof:placetype":"venue"
},
  "geometry": {"coordinates":[-74.24015300000001,40.511636],"type":"Point"}
}