{
  "type": "Feature",
  "properties": {
    "iso:country":"US",
    "sg:address":"9 Virginia Cir",
    "sg:city":"Newburgh",
    "sg:classifiers":[
        {
            "category":"Education",
            "subcategory":"Special Training",
            "type":"Public Place"
        }
    ],
    "sg:phone":"+1 845 569 1983",
    "sg:postcode":"12550",
    "sg:province":"NY",
    "sg:tags":[
        "tutoring"
    ],
    "wof:name":"Count It All Joy",
    "wof:placetype":"venue"
},
  "geometry": {"coordinates":[-74.029003,41.535387],"type":"Point"}
}