{
  "type": "Feature",
  "properties": {
    "iso:country":"US",
    "sg:address":"271 Patrice Ter",
    "sg:city":"Williamsville",
    "sg:classifiers":[
        {
            "category":"Professional",
            "subcategory":"Engineering",
            "type":"Services"
        }
    ],
    "sg:phone":"+1 716 633 6353",
    "sg:postcode":"14221",
    "sg:province":"NY",
    "sg:tags":[
        "engineer"
    ],
    "wof:name":"Professional Engineering Svc",
    "wof:placetype":"venue"
},
  "geometry": {"coordinates":[-78.70215899999999,42.988918],"type":"Point"}
}