{
  "type": "Feature",
  "properties": {
    "addr:full":"201 W 21st St New York NY 10011",
    "addr:housenumber":"201",
    "addr:postcode":"10011",
    "addr:street":"W 21St St",
    "iso:country":"US",
    "sg:address":"201 W 21st St",
    "sg:city":"New York",
    "sg:classifiers":[
        {
            "category":"Professional",
            "subcategory":"Management & Consulting",
            "type":"Services"
        }
    ],
    "sg:phone":"+1 212 675 7696",
    "sg:postcode":"10011",
    "sg:province":"NY",
    "sg:tags":[
        "public",
        "relations"
    ],
    "wof:name":"Ungemach Communications LLC",
    "wof:placetype":"venue"
},
  "geometry": {"coordinates":[-73.999422,40.744009],"type":"Point"}
}