{
  "type": "Feature",
  "properties": {
    "addr:full":"34 Webster St North Tonawanda NY 14120",
    "addr:housenumber":"34",
    "addr:postcode":"14120",
    "addr:street":"Webster St",
    "iso:country":"US",
    "sg:address":"34 Webster St",
    "sg:city":"North Tonawanda",
    "sg:classifiers":[
        {
            "category":"Shopping",
            "subcategory":"Hobbies, Toys, & Games",
            "type":"Retail Goods"
        }
    ],
    "sg:phone":"+1 716 692 4221",
    "sg:postcode":"14120",
    "sg:province":"NY",
    "sg:tags":[
        "craft",
        "supply"
    ],
    "wof:name":"Udderly Country",
    "wof:placetype":"venue"
},
  "geometry": {"coordinates":[-78.87786800000001,43.022362],"type":"Point"}
}