{
  "type": "Feature",
  "properties": {
    "addr:full":"20 Century Hill Dr # 203 Latham NY 12110",
    "addr:housenumber":"20",
    "addr:postcode":"12110",
    "addr:street":"Century Hill Dr # 203",
    "iso:country":"US",
    "sg:address":"20 Century Hill Dr # 203",
    "sg:city":"Latham",
    "sg:classifiers":[
        {
            "category":"Building & Trades",
            "subcategory":"Cleaning & Sanitation",
            "type":"Services"
        }
    ],
    "sg:phone":"+1 518 810 0200",
    "sg:postcode":"12110",
    "sg:province":"NY",
    "sg:tags":[
        "construction",
        "site-clean-up"
    ],
    "wof:name":"Reenergy Holdings",
    "wof:placetype":"venue"
},
  "geometry": {"coordinates":[-73.754983,42.771551],"type":"Point"}
}