{
  "type": "Feature",
  "properties": {
    "addr:full":"101 Church St Freeport NY 11520",
    "addr:housenumber":"101",
    "addr:postcode":"11520",
    "addr:street":"Church St",
    "iso:country":"US",
    "sg:address":"101 Church St",
    "sg:city":"Freeport",
    "sg:classifiers":[
        {
            "category":"Shopping",
            "type":"Retail Goods"
        }
    ],
    "sg:phone":"+1 516 771 6491",
    "sg:postcode":"11520",
    "sg:province":"NY",
    "sg:tags":[
        "merchandise"
    ],
    "wof:name":"Mt Carmel Botanica",
    "wof:placetype":"venue"
},
  "geometry": {"coordinates":[-73.58129700000001,40.652986],"type":"Point"}
}