{
  "type": "Feature",
  "properties": {
    "addr:full":"275 Madison Avenue, 6th Floor, New York NY 10016",
    "addr:housenumber":"275;6th floor",
    "addr:postcode":"10016",
    "addr:street":"Madison Avenue",
    "iso:country":"US",
    "sg:address":"275 Madison Avenue, 6th Floor,",
    "sg:city":"New York",
    "sg:classifiers":[
        {
            "category":"Professional",
            "subcategory":"Computer Services",
            "type":"Services"
        }
    ],
    "sg:phone":"+91 22 3937 9999",
    "sg:postcode":"10016",
    "sg:province":"NY",
    "sg:tags":[
        "investment-research",
        "business-research",
        "409a-valuation",
        "ip-research",
        "data-analytics",
        "kpo",
        "outsourcing"
    ],
    "sg:website":"http://www.aranca.com",
    "wof:name":"Aranca",
    "wof:placetype":"venue"
},
  "geometry": {"coordinates":[-73.98045,40.750956],"type":"Point"}
}