{
  "type": "Feature",
  "properties": {
    "iso:country":"US",
    "sg:address":"426 Montauk Hwy",
    "sg:city":"East Quogue",
    "sg:classifiers":[
        {
            "category":"Health Services",
            "subcategory":"Doctor",
            "type":"Services"
        }
    ],
    "sg:phone":"+1 631 653 4479",
    "sg:postcode":"11942",
    "sg:province":"NY",
    "sg:tags":[
        "dentist"
    ],
    "wof:name":"John J Romano DDS",
    "wof:placetype":"venue"
},
  "geometry": {"coordinates":[-72.572592,40.850581],"type":"Point"}
}