{
  "type": "Feature",
  "properties": {
    "iso:country":"US",
    "sg:address":"157 Hester St",
    "sg:city":"New York",
    "sg:classifiers":[
        {
            "category":"Shopping",
            "subcategory":"Gifts & Souvenirs",
            "type":"Retail Goods"
        }
    ],
    "sg:phone":"+1   ",
    "sg:postcode":"10013",
    "sg:province":"NY",
    "wof:name":"J J Beauty Gift Shop Inc",
    "wof:placetype":"venue"
},
  "geometry": {"coordinates":[-73.995785,40.717426],"type":"Point"}
}