{
  "type": "Feature",
  "properties": {
    "addr:full":"3142 State Hwy 417 Olean NY 14760",
    "addr:housenumber":"3142",
    "addr:postcode":"14760",
    "addr:street":"State Hwy 417",
    "iso:country":"US",
    "sg:address":"3142 State Hwy 417",
    "sg:city":"Olean",
    "sg:classifiers":[
        {
            "category":"Shopping",
            "subcategory":"Bicycles & Sporting Goods",
            "type":"Retail Goods"
        }
    ],
    "sg:phone":"+1 716 373 6593",
    "sg:postcode":"14760",
    "sg:province":"NY",
    "sg:website":"www.olympiasports.net",
    "wof:name":"Olympia Sports",
    "wof:placetype":"venue"
},
  "geometry": {"coordinates":[-78.46787,42.076825],"type":"Point"}
}