{
  "type": "Feature",
  "properties": {
    "iso:country":"US",
    "sg:address":"246 E 58th St",
    "sg:city":"New York",
    "sg:classifiers":[
        {
            "category":"Professional",
            "subcategory":"Management & Consulting",
            "type":"Services"
        }
    ],
    "sg:phone":"+1 212 223 7479",
    "sg:postcode":"10022",
    "sg:province":"NY",
    "sg:tags":[
        "consultant",
        "lighting"
    ],
    "wof:name":"George Balle Lighting Design",
    "wof:placetype":"venue"
},
  "geometry": {"coordinates":[-73.96563399999999,40.76036],"type":"Point"}
}