{
  "type": "Feature",
  "properties": {
    "addr:full":"133 Hawthorne St Massapequa Park NY 11762",
    "addr:housenumber":"133",
    "addr:postcode":"11762",
    "addr:street":"Hawthorne St",
    "iso:country":"US",
    "sg:address":"133 Hawthorne St",
    "sg:city":"Massapequa Park",
    "sg:classifiers":[
        {
            "category":"Professional",
            "subcategory":"Management & Consulting",
            "type":"Services"
        }
    ],
    "sg:phone":"+1   ",
    "sg:postcode":"11762",
    "sg:province":"NY",
    "wof:name":"Caesar Industries",
    "wof:placetype":"venue"
},
  "geometry": {"coordinates":[-73.450704,40.690473],"type":"Point"}
}