{
  "type": "Feature",
  "properties": {
    "addr:full":"136 Saint James Pl Brooklyn NY 11238",
    "addr:housenumber":"136",
    "addr:postcode":"11238",
    "addr:street":"Saint James Pl",
    "iso:country":"US",
    "sg:address":"136 Saint James Pl",
    "sg:city":"Brooklyn",
    "sg:classifiers":[
        {
            "category":"Building & Trades",
            "subcategory":"Locksmith",
            "type":"Services"
        }
    ],
    "sg:phone":"+1 877 551 1763",
    "sg:postcode":"11238",
    "sg:province":"NY",
    "sg:tags":[
        "key"
    ],
    "wof:name":"0 Zero Zero Zero Twenty Four Hour A Emergency A Lock",
    "wof:placetype":"venue"
},
  "geometry": {"coordinates":[-73.96446899999999,40.686005],"type":"Point"}
}