{
  "type": "Feature",
  "properties": {
    "addr:full":"72 Henry St Brooklyn NY 11201",
    "addr:housenumber":"72",
    "addr:postcode":"11201",
    "addr:street":"Henry St",
    "iso:country":"US",
    "sg:address":"72 Henry St",
    "sg:city":"Brooklyn",
    "sg:classifiers":[
        {
            "category":"Personal",
            "subcategory":"Beauty Salon",
            "type":"Services"
        }
    ],
    "sg:phone":"+1 718 222 0400",
    "sg:postcode":"11201",
    "sg:province":"NY",
    "sg:tags":[
        "hair"
    ],
    "wof:name":"Diva Salon",
    "wof:placetype":"venue"
},
  "geometry": {"coordinates":[-73.99256699999999,40.698697],"type":"Point"}
}