{
  "type": "Feature",
  "properties": {
    "addr:full":"13 Coventry Ln Brewster NY 10509",
    "addr:housenumber":"13",
    "addr:postcode":"10509",
    "addr:street":"Coventry Ln",
    "iso:country":"US",
    "sg:address":"13 Coventry Ln",
    "sg:city":"Brewster",
    "sg:classifiers":[
        {
            "category":"Local Transit",
            "type":"Transportation"
        }
    ],
    "sg:phone":"+1 845 278 4440",
    "sg:postcode":"10509",
    "sg:province":"NY",
    "sg:tags":[
        "limousine"
    ],
    "wof:name":"Spectacular Limousine Svc",
    "wof:placetype":"venue"
},
  "geometry": {"coordinates":[-73.56567,41.371803],"type":"Point"}
}