{
  "type": "Feature",
  "properties": {
    "addr:full":"335 Clarke Ave Staten Island NY 10306",
    "addr:housenumber":"335",
    "addr:postcode":"10306",
    "addr:street":"Clarke Ave",
    "iso:country":"US",
    "sg:address":"335 Clarke Ave",
    "sg:city":"Staten Island",
    "sg:classifiers":[
        {
            "category":"Shopping",
            "subcategory":"Catalog Store",
            "type":"Retail Goods"
        }
    ],
    "sg:phone":"+1   ",
    "sg:postcode":"10306",
    "sg:province":"NY",
    "sg:tags":[
        "mail",
        "doll",
        "order",
        "accessory"
    ],
    "wof:name":"Living Doll",
    "wof:placetype":"venue"
},
  "geometry": {"coordinates":[-74.141705,40.56856],"type":"Point"}
}