{
  "type": "Feature",
  "properties": {
    "addr:full":"1407 Avenue U Brooklyn NY 11229",
    "addr:housenumber":"1407",
    "addr:postcode":"11229",
    "addr:street":"Avenue U",
    "iso:country":"US",
    "sg:address":"1407 Avenue U",
    "sg:city":"Brooklyn",
    "sg:classifiers":[
        {
            "category":"Health Services",
            "subcategory":"Doctor",
            "type":"Services"
        }
    ],
    "sg:phone":"+1 718 998 6684",
    "sg:postcode":"11229",
    "sg:province":"NY",
    "sg:tags":[
        "podiatrist"
    ],
    "wof:name":"Arnowitz Richard Dr",
    "wof:placetype":"venue"
},
  "geometry": {"coordinates":[-73.956802,40.5989],"type":"Point"}
}