{
  "type": "Feature",
  "properties": {
    "iso:country":"US",
    "sg:address":"2359 Mound Rd",
    "sg:city":"Waterloo",
    "sg:classifiers":[
        {
            "category":"Wholesale",
            "subcategory":"Machinery & Supplies",
            "type":"Manufacturing & Wholesale Goods"
        },
        {
            "category":"Manufacturing",
            "subcategory":"Metals",
            "type":"Manufacturing & Wholesale Goods"
        }
    ],
    "sg:phone":"+1 315 539 9246",
    "sg:postcode":"13165",
    "sg:province":"NY",
    "sg:tags":[
        "manufacture",
        "equipment",
        "conveyor",
        "conveying"
    ],
    "wof:name":"Finger Lakes Conveyors Inc",
    "wof:placetype":"venue"
},
  "geometry": {"coordinates":[-76.837282,42.912593],"type":"Point"}
}