{
  "type": "Feature",
  "properties": {
    "iso:country":"US",
    "sg:address":"230 Jay St Apt 4C",
    "sg:city":"Brooklyn",
    "sg:classifiers":[
        {
            "category":"Professional",
            "subcategory":"Management & Consulting",
            "type":"Services"
        },
        {
            "category":"Professional",
            "subcategory":"Employment Agencies",
            "type":"Services"
        }
    ],
    "sg:phone":"+1 718 802 1338",
    "sg:postcode":"11201",
    "sg:province":"NY",
    "sg:tags":[
        "consultant",
        "resource",
        "human"
    ],
    "wof:name":"Affairs Ny",
    "wof:placetype":"venue"
},
  "geometry": {"coordinates":[-73.987038,40.69767],"type":"Point"}
}