{
  "type": "Feature",
  "properties": {
    "iso:country":"US",
    "sg:address":"99 N 10th St",
    "sg:city":"Brooklyn",
    "sg:classifiers":[
        {
            "category":"Shopping",
            "subcategory":"Bicycles & Sporting Goods",
            "type":"Retail Goods"
        }
    ],
    "sg:phone":"+1   ",
    "sg:postcode":"11211",
    "sg:province":"NY",
    "sg:tags":[
        "equipment",
        "skateboarding"
    ],
    "wof:name":"Kcdc Skate Shop",
    "wof:placetype":"venue"
},
  "geometry": {"coordinates":[-73.957717,40.720795],"type":"Point"}
}