{
  "type": "Feature",
  "properties": {
    "iso:country":"US",
    "sg:address":"20 Crestwood Dr",
    "sg:city":"Clifton Park",
    "sg:classifiers":[
        {
            "category":"Real Estate",
            "subcategory":"Real Estate Agent",
            "type":"Services"
        }
    ],
    "sg:phone":"+1 518 371 2966",
    "sg:postcode":"12065",
    "sg:province":"NY",
    "wof:name":"Rayvas Inc",
    "wof:placetype":"venue"
},
  "geometry": {"coordinates":[-73.789203,42.869147],"type":"Point"}
}