{
  "type": "Feature",
  "properties": {
    "iso:country":"US",
    "sg:address":"309 Clinton Ave",
    "sg:city":"Brooklyn",
    "sg:classifiers":[
        {
            "category":"Social Services",
            "subcategory":"Adult Care",
            "type":"Services"
        }
    ],
    "sg:phone":"+1 718 230 0158",
    "sg:postcode":"11205",
    "sg:province":"NY",
    "sg:tags":[
        "home",
        "religious",
        "residential"
    ],
    "wof:name":"Catholic Guardian Society",
    "wof:placetype":"venue"
},
  "geometry": {"coordinates":[-73.96779600000001,40.688999],"type":"Point"}
}