{
  "type": "Feature",
  "properties": {
    "iso:country":"US",
    "sg:address":"60 Central Ave",
    "sg:city":"Cortland",
    "sg:classifiers":[
        {
            "category":"Government",
            "subcategory":"Office",
            "type":"Public Place"
        }
    ],
    "sg:phone":"+1 607 753 5042",
    "sg:postcode":"13045",
    "sg:province":"NY",
    "wof:name":"Cortland Cnty Information Tech",
    "wof:placetype":"venue"
},
  "geometry": {"coordinates":[-76.176408,42.600257],"type":"Point"}
}