{
  "type": "Feature",
  "properties": {
    "iso:country":"US",
    "sg:address":"390 Crystal Run Rd Crystal Run Medical Arts Commons Bldg",
    "sg:city":"Middletown",
    "sg:classifiers":[
        {
            "category":"Personal",
            "subcategory":"Day Spa",
            "type":"Services"
        }
    ],
    "sg:phone":"+1 845 703 7727",
    "sg:postcode":"10941",
    "sg:province":"NY",
    "sg:website":"www.woodhousespas.com",
    "wof:name":"The Woodhouse Day Spa",
    "wof:placetype":"venue"
},
  "geometry": {"coordinates":[-74.346643,41.455037],"type":"Point"}
}