{
  "type": "Feature",
  "properties": {
    "addr:full":"373 Rockaway Pkwy Valley Stream NY 11580",
    "addr:housenumber":"373",
    "addr:postcode":"11580",
    "addr:street":"Rockaway Pkwy",
    "iso:country":"US",
    "sg:address":"373 Rockaway Pkwy",
    "sg:city":"Valley Stream",
    "sg:classifiers":[
        {
            "category":"Restaurant",
            "type":"Food & Drink"
        }
    ],
    "sg:phone":"+1 516 825 3386",
    "sg:postcode":"11580",
    "sg:province":"NY",
    "sg:tags":[
        "pizza"
    ],
    "wof:name":"Tony's Pizza",
    "wof:placetype":"venue"
},
  "geometry": {"coordinates":[-73.693001,40.675499],"type":"Point"}
}