{
  "type": "Feature",
  "properties": {
    "addr:full":"15 Cobbee Rd Latham NY 12110",
    "addr:housenumber":"15",
    "addr:postcode":"12110",
    "addr:street":"Cobbee Rd",
    "iso:country":"US",
    "sg:address":"15 Cobbee Rd",
    "sg:city":"Latham",
    "sg:classifiers":[
        {
            "category":"Education",
            "subcategory":"Dance Studio",
            "type":"Public Place"
        }
    ],
    "sg:phone":"+1   ",
    "sg:postcode":"12110",
    "sg:province":"NY",
    "wof:name":"Conway Sisters Dance Studio",
    "wof:placetype":"venue"
},
  "geometry": {"coordinates":[-73.756283,42.75629],"type":"Point"}
}