{
  "type": "Feature",
  "properties": {
    "addr:full":"120 Madison St Chittenango NY 13037",
    "addr:housenumber":"120",
    "addr:postcode":"13037",
    "addr:street":"Madison St",
    "iso:country":"US",
    "sg:address":"120 Madison St",
    "sg:city":"Chittenango",
    "sg:classifiers":[
        {
            "category":"Professional",
            "type":"Services"
        }
    ],
    "sg:phone":"+1 315 687 3240",
    "sg:postcode":"13037",
    "sg:province":"NY",
    "sg:tags":[
        "establishment"
    ],
    "sg:website":"www.calvary.net",
    "wof:name":"Plyboo America Inc",
    "wof:placetype":"venue"
},
  "geometry": {"coordinates":[-75.86652599999999,43.042116],"type":"Point"}
}