{
  "type": "Feature",
  "properties": {
    "iso:country":"US",
    "sg:address":"619 Merrick Ave",
    "sg:city":"East Meadow",
    "sg:classifiers":[
        {
            "category":"Personal",
            "type":"Services"
        },
        {
            "category":"Retail",
            "subcategory":"Laundry & Dry Cleaning",
            "type":"Services"
        }
    ],
    "sg:phone":"+1 516 486 2400",
    "sg:postcode":"11554",
    "sg:province":"NY",
    "sg:tags":[
        "sewing",
        "alteration"
    ],
    "wof:name":"East Meadow Cleaners",
    "wof:placetype":"venue"
},
  "geometry": {"coordinates":[-73.569603,40.706402],"type":"Point"}
}