{
  "type": "Feature",
  "properties": {
    "iso:country":"US",
    "sg:address":"72 Spring St",
    "sg:city":"Manhattan",
    "sg:classifiers":[
        {
            "category":"Coffee & Tea",
            "type":"Food & Drink"
        }
    ],
    "sg:phone":"+1 212 219 2961",
    "sg:postcode":"10012",
    "sg:province":"NY",
    "sg:website":"www.starbucks.com",
    "wof:name":"Starbucks",
    "wof:placetype":"venue"
},
  "geometry": {"coordinates":[-73.997879,40.722386],"type":"Point"}
}