{
  "type": "Feature",
  "properties": {
    "iso:country":"US",
    "sg:address":"3685 Lockport Rd",
    "sg:city":"Sanborn",
    "sg:classifiers":[
        {
            "category":"Manufacturing",
            "subcategory":"Paper Products",
            "type":"Manufacturing & Wholesale Goods"
        }
    ],
    "sg:phone":"+1   ",
    "sg:postcode":"14132",
    "sg:province":"NY",
    "sg:tags":[
        "pr",
        "commercial",
        "converted",
        "lithographic",
        "mfg"
    ],
    "wof:name":"American Coaster Co Inc",
    "wof:placetype":"venue"
},
  "geometry": {"coordinates":[-78.848483,43.122635],"type":"Point"}
}