{
  "type": "Feature",
  "properties": {
    "addr:full":"105 Clinton St Schenectady NY 12305",
    "addr:housenumber":"105",
    "addr:postcode":"12305",
    "addr:street":"Clinton St",
    "iso:country":"US",
    "sg:address":"105 Clinton St",
    "sg:city":"Schenectady",
    "sg:classifiers":[
        {
            "category":"Organizations",
            "subcategory":"Labor Organization",
            "type":"Services"
        }
    ],
    "sg:phone":"+1 518 374 6704",
    "sg:postcode":"12305",
    "sg:province":"NY",
    "wof:name":"Laborers Local # 157",
    "wof:placetype":"venue"
},
  "geometry": {"coordinates":[-73.93901700000001,42.813608],"type":"Point"}
}