{
  "type": "Feature",
  "properties": {
    "addr:full":"12910 Deerfield Dr Chaffee NY 14030",
    "addr:housenumber":"12910",
    "addr:postcode":"14030",
    "addr:street":"Deerfield Dr",
    "iso:country":"US",
    "sg:address":"12910 Deerfield Dr",
    "sg:city":"Chaffee",
    "sg:classifiers":[
        {
            "category":"Building & Trades",
            "subcategory":"Construction",
            "type":"Services"
        }
    ],
    "sg:phone":"+1 716 496 5401",
    "sg:postcode":"14030",
    "sg:province":"NY",
    "sg:tags":[
        "residential"
    ],
    "wof:name":"Wiedeman & Sons Construction",
    "wof:placetype":"venue"
},
  "geometry": {"coordinates":[-78.50188799999999,42.544418],"type":"Point"}
}