{
  "type": "Feature",
  "properties": {
    "addr:full":"425 E 25th Street New York NY 10010",
    "addr:housenumber":"425",
    "addr:postcode":"10010",
    "addr:street":"E 25Th Street",
    "iso:country":"US",
    "sg:address":"425 E 25th Street",
    "sg:city":"New York",
    "sg:classifiers":[
        {
            "category":"Education",
            "subcategory":"University",
            "type":"Public Place"
        }
    ],
    "sg:phone":"+1 212 481 3780",
    "sg:postcode":"10010",
    "sg:province":"NY",
    "sg:tags":[
        "college"
    ],
    "wof:name":"N Y City of",
    "wof:placetype":"venue"
},
  "geometry": {"coordinates":[-73.97524199999999,40.737293],"type":"Point"}
}