{
  "type": "Feature",
  "properties": {
    "iso:country":"US",
    "sg:address":"1086 President St",
    "sg:city":"Brooklyn",
    "sg:classifiers":[
        {
            "category":"Wholesale",
            "subcategory":"Electrical",
            "type":"Manufacturing & Wholesale Goods"
        }
    ],
    "sg:phone":"+1 718 771 3716",
    "sg:postcode":"11225",
    "sg:province":"NY",
    "sg:tags":[
        "electronic"
    ],
    "wof:name":"Jupiter Systems",
    "wof:placetype":"venue"
},
  "geometry": {"coordinates":[-73.954109,40.668197],"type":"Point"}
}