{
  "type": "Feature",
  "properties": {
    "iso:country":"US",
    "sg:address":"9 East St",
    "sg:city":"Edmeston",
    "sg:classifiers":[
        {
            "category":"Manufacturing",
            "subcategory":"Printing",
            "type":"Manufacturing & Wholesale Goods"
        }
    ],
    "sg:phone":"+1 607 965 8155",
    "sg:postcode":"13335",
    "sg:province":"NY",
    "sg:tags":[
        "printer"
    ],
    "sg:website":"www.bishopprintshop.com",
    "wof:name":"Bishop Print Shop",
    "wof:placetype":"venue"
},
  "geometry": {"coordinates":[-75.24376100000001,42.697832],"type":"Point"}
}