{
  "type": "Feature",
  "properties": {
    "addr:full":"700 Main St East Aurora NY 14052",
    "addr:housenumber":"700",
    "addr:postcode":"14052",
    "addr:street":"Main St",
    "iso:country":"US",
    "sg:address":"700 Main St",
    "sg:city":"East Aurora",
    "sg:classifiers":[
        {
            "category":"Shopping",
            "subcategory":"Hobbies, Toys, & Games",
            "type":"Retail Goods"
        }
    ],
    "sg:phone":"+1   ",
    "sg:postcode":"14052",
    "sg:province":"NY",
    "wof:name":"Toy Loft LTD",
    "wof:placetype":"venue"
},
  "geometry": {"coordinates":[-78.60942799999999,42.767928],"type":"Point"}
}