{
  "type": "Feature",
  "properties": {
    "addr:full":"961 40th Street Brooklyn NY 11219",
    "addr:housenumber":"961",
    "addr:postcode":"11219",
    "addr:street":"40Th Street",
    "iso:country":"US",
    "sg:address":"961 40th Street",
    "sg:city":"Brooklyn",
    "sg:classifiers":[
        {
            "category":"Retail",
            "subcategory":"Repair Shop",
            "type":"Services"
        }
    ],
    "sg:phone":"+1 718 436 0120",
    "sg:postcode":"11219",
    "sg:province":"NY",
    "sg:tags":[
        "reupholstery",
        "furniture"
    ],
    "wof:name":"Five Star Upholstery",
    "wof:placetype":"venue"
},
  "geometry": {"coordinates":[-73.99406,40.644543],"type":"Point"}
}