{
  "type": "Feature",
  "properties": {
    "addr:full":"1535 63rd St Brooklyn NY 11219",
    "addr:housenumber":"1535",
    "addr:postcode":"11219",
    "addr:street":"63Rd St",
    "iso:country":"US",
    "sg:address":"1535 63rd St",
    "sg:city":"Brooklyn",
    "sg:classifiers":[
        {
            "category":"Manufacturing",
            "subcategory":"Apparel",
            "type":"Manufacturing & Wholesale Goods"
        }
    ],
    "sg:phone":"+1 718 621 9331",
    "sg:postcode":"11219",
    "sg:province":"NY",
    "sg:tags":[
        "sportswear"
    ],
    "wof:name":"Chaz & R Inc",
    "wof:placetype":"venue"
},
  "geometry": {"coordinates":[-73.994247,40.623674],"type":"Point"}
}