{
  "type": "Feature",
  "properties": {
    "iso:country":"US",
    "sg:address":"211 N Comrie Ave",
    "sg:city":"Johnstown",
    "sg:classifiers":[
        {
            "category":"Personal",
            "subcategory":"Tanning Parlor",
            "type":"Services"
        }
    ],
    "sg:phone":"+1 518 762 1840",
    "sg:postcode":"12095",
    "sg:province":"NY",
    "sg:tags":[
        "salon"
    ],
    "wof:name":"Total Tan",
    "wof:placetype":"venue"
},
  "geometry": {"coordinates":[-74.36083600000001,43.013868],"type":"Point"}
}