{
  "type": "Feature",
  "properties": {
    "addr:full":"115 Rochester St Fulton NY 13069",
    "addr:housenumber":"115",
    "addr:postcode":"13069",
    "addr:street":"Rochester St",
    "iso:country":"US",
    "sg:address":"115 Rochester St",
    "sg:city":"Fulton",
    "sg:classifiers":[
        {
            "category":"Shopping",
            "subcategory":"Optical Goods",
            "type":"Retail Goods"
        }
    ],
    "sg:phone":"+1 315 598 8505",
    "sg:postcode":"13069",
    "sg:province":"NY",
    "sg:tags":[
        "optician"
    ],
    "wof:name":"Empire Vision Ctr",
    "wof:placetype":"venue"
},
  "geometry": {"coordinates":[-76.415785,43.322902],"type":"Point"}
}