{
  "type": "Feature",
  "properties": {
    "iso:country":"US",
    "sg:address":"4 Bashford St",
    "sg:city":"Yonkers",
    "sg:classifiers":[
        {
            "category":"Building & Trades",
            "subcategory":"Construction",
            "type":"Services"
        }
    ],
    "sg:phone":"+1 914 963 7177",
    "sg:postcode":"10701",
    "sg:province":"NY",
    "sg:tags":[
        "general",
        "contractor"
    ],
    "wof:name":"Bashford Construction Co Inc",
    "wof:placetype":"venue"
},
  "geometry": {"coordinates":[-73.900312,40.936478],"type":"Point"}
}