{
  "type": "Feature",
  "properties": {
    "iso:country":"US",
    "sg:address":"149 Beach 6th St",
    "sg:city":"Far Rockaway",
    "sg:classifiers":[
        {
            "category":"Organizations",
            "subcategory":"Non-profit Organization",
            "type":"Services"
        }
    ],
    "sg:phone":"+1 718 945 0782",
    "sg:postcode":"11691",
    "sg:province":"NY",
    "sg:website":"www.technoedge.org",
    "wof:name":"Techno Edge Comm Dev Corp",
    "wof:placetype":"venue"
},
  "geometry": {"coordinates":[-73.819042,40.609635],"type":"Point"}
}