{
  "type": "Feature",
  "properties": {
    "addr:full":"566 W 181st St New York NY 10033",
    "addr:housenumber":"566",
    "addr:postcode":"10033",
    "addr:street":"W 181St St",
    "iso:country":"US",
    "sg:address":"566 W 181st St",
    "sg:city":"New York",
    "sg:classifiers":[
        {
            "category":"Shopping",
            "subcategory":"Clothing, Apparel, & Fashions",
            "type":"Retail Goods"
        }
    ],
    "sg:phone":"+1 212 928 7515",
    "sg:postcode":"10033",
    "sg:province":"NY",
    "sg:tags":[
        "sportswear"
    ],
    "wof:name":"Bonita Ladieswear Inc",
    "wof:placetype":"venue"
},
  "geometry": {"coordinates":[-73.933224,40.848953],"type":"Point"}
}