{
  "type": "Feature",
  "properties": {
    "iso:country":"US",
    "sg:address":"427 E 155th St",
    "sg:city":"Bronx",
    "sg:classifiers":[
        {
            "category":"Organizations",
            "subcategory":"Religious Organization",
            "type":"Services"
        }
    ],
    "sg:phone":"+1 718 993 3405",
    "sg:postcode":"10455",
    "sg:province":"NY",
    "wof:name":"Renewal Our Lady of the Angels Frncscn Frrs of the",
    "wof:placetype":"venue"
},
  "geometry": {"coordinates":[-73.914597,40.82],"type":"Point"}
}