{
  "type": "Feature",
  "properties": {
    "iso:country":"US",
    "sg:address":"2515 Pauline Ave Apt 6",
    "sg:city":"Schenectady",
    "sg:classifiers":[
        {
            "category":"Health Services",
            "subcategory":"Clinic",
            "type":"Services"
        }
    ],
    "sg:phone":"+1 518 356 1350",
    "sg:postcode":"12306",
    "sg:province":"NY",
    "sg:tags":[
        "welfare"
    ],
    "wof:name":"Creative Health Impressions",
    "wof:placetype":"venue"
},
  "geometry": {"coordinates":[-73.96768400000001,42.789803],"type":"Point"}
}