{
  "type": "Feature",
  "properties": {
    "addr:full":"3 Wilbur Rd Thiells NY 10901",
    "addr:housenumber":"3",
    "addr:postcode":"10901",
    "addr:street":"Wilbur Rd",
    "iso:country":"US",
    "sg:address":"3 Wilbur Rd",
    "sg:city":"Thiells",
    "sg:classifiers":[
        {
            "category":"Social Services",
            "type":"Services"
        }
    ],
    "sg:phone":"+1 845 947 6395",
    "sg:postcode":"10901",
    "sg:province":"NY",
    "sg:tags":[
        "senior",
        "citizen"
    ],
    "wof:name":"Foster Grandparent Program",
    "wof:placetype":"venue"
},
  "geometry": {"coordinates":[-74.107321,41.146386],"type":"Point"}
}