{
  "type": "Feature",
  "properties": {
    "iso:country":"US",
    "sg:address":"21 Evelyn Rd",
    "sg:city":"Plainview",
    "sg:classifiers":[
        {
            "category":"Professional",
            "subcategory":"Accounting & Tax Preparation",
            "type":"Services"
        }
    ],
    "sg:phone":"+1   ",
    "sg:postcode":"11803",
    "sg:province":"NY",
    "wof:name":"Ronald Shapey CPA",
    "wof:placetype":"venue"
},
  "geometry": {"coordinates":[-73.48747,40.774068],"type":"Point"}
}