{
  "type": "Feature",
  "properties": {
    "addr:full":"325 Rutledge St Brooklyn NY 11211",
    "addr:housenumber":"325",
    "addr:postcode":"11211",
    "addr:street":"Rutledge St",
    "iso:country":"US",
    "sg:address":"325 Rutledge St",
    "sg:city":"Brooklyn",
    "sg:classifiers":[
        {
            "category":"Manufacturing",
            "subcategory":"Printing",
            "type":"Manufacturing & Wholesale Goods"
        }
    ],
    "sg:phone":"+1 718 599 3757",
    "sg:postcode":"11211",
    "sg:province":"NY",
    "sg:tags":[
        "printer"
    ],
    "wof:name":"General Printing",
    "wof:placetype":"venue"
},
  "geometry": {"coordinates":[-73.951847,40.705365],"type":"Point"}
}