{
  "type": "Feature",
  "properties": {
    "iso:country":"US",
    "sg:address":"2889 Two Rod Rd",
    "sg:city":"East Aurora",
    "sg:classifiers":[
        {
            "category":"Building & Trades",
            "subcategory":"Electrical",
            "type":"Services"
        }
    ],
    "sg:phone":"+1 716 655 3401",
    "sg:postcode":"14052",
    "sg:province":"NY",
    "sg:tags":[
        "electrician",
        "fabrication",
        "welding"
    ],
    "wof:name":"Techtronics",
    "wof:placetype":"venue"
},
  "geometry": {"coordinates":[-78.554013,42.805908],"type":"Point"}
}