{
  "type": "Feature",
  "properties": {
    "iso:country":"US",
    "sg:address":"816 E Boston Post Rd",
    "sg:city":"Mamaroneck",
    "sg:classifiers":[
        {
            "category":"Autos & Motor Vehicles",
            "subcategory":"Automobile Sales",
            "type":"Retail Goods"
        }
    ],
    "sg:phone":"+1 914 698 4686",
    "sg:postcode":"10543",
    "sg:province":"NY",
    "sg:tags":[
        "car",
        "dealer"
    ],
    "wof:name":"Toyota City",
    "wof:placetype":"venue"
},
  "geometry": {"coordinates":[-73.724718,40.953472],"type":"Point"}
}