{
  "type": "Feature",
  "properties": {
    "addr:full":"60 Farnum Blvd Franklin Square NY 11010",
    "addr:housenumber":"60",
    "addr:postcode":"11010",
    "addr:street":"Farnum Blvd",
    "iso:country":"US",
    "sg:address":"60 Farnum Blvd",
    "sg:city":"Franklin Square",
    "sg:classifiers":[
        {
            "category":"Building & Trades",
            "subcategory":"Construction",
            "type":"Services"
        }
    ],
    "sg:phone":"+1 800 479 1333",
    "sg:postcode":"11010",
    "sg:province":"NY",
    "sg:tags":[
        "contractor"
    ],
    "wof:name":"B F M Contracting",
    "wof:placetype":"venue"
},
  "geometry": {"coordinates":[-73.684281,40.710176],"type":"Point"}
}