{
  "type": "Feature",
  "properties": {
    "iso:country":"US",
    "sg:address":"331 W 87 St",
    "sg:city":"New York",
    "sg:classifiers":[
        {
            "category":"Retail",
            "subcategory":"Repair Shop",
            "type":"Services"
        }
    ],
    "sg:phone":"+1 646 224 0771",
    "sg:postcode":"10024",
    "sg:province":"NY",
    "sg:tags":[
        "lock",
        "locksmith"
    ],
    "wof:name":"AAA Emergency A Locksmith",
    "wof:placetype":"venue"
},
  "geometry": {"coordinates":[-73.979246,40.790356],"type":"Point"}
}