{
  "type": "Feature",
  "properties": {
    "iso:country":"US",
    "sg:address":"1855 Monroe Ave",
    "sg:city":"Rochester",
    "sg:classifiers":[
        {
            "category":"Personal",
            "subcategory":"Beauty Salon",
            "type":"Services"
        }
    ],
    "sg:phone":"+1   ",
    "sg:postcode":"14618",
    "sg:province":"NY",
    "sg:tags":[
        "hairdresser"
    ],
    "wof:name":"Squire Stylist",
    "wof:placetype":"venue"
},
  "geometry": {"coordinates":[-77.565977,43.127731],"type":"Point"}
}