{
  "type": "Feature",
  "properties": {
    "addr:full":"584 Lafayette Ave Brooklyn NY 11205",
    "addr:housenumber":"584",
    "addr:postcode":"11205",
    "addr:street":"Lafayette Ave",
    "iso:country":"US",
    "sg:address":"584 Lafayette Ave",
    "sg:city":"Brooklyn",
    "sg:classifiers":[
        {
            "category":"Personal",
            "subcategory":"Beauty Salon",
            "type":"Services"
        }
    ],
    "sg:phone":"+1 718 623 8325",
    "sg:postcode":"11205",
    "sg:province":"NY",
    "wof:name":"African Queen Hair Braiding",
    "wof:placetype":"venue"
},
  "geometry": {"coordinates":[-73.954162,40.689379],"type":"Point"}
}