{
  "type": "Feature",
  "properties": {
    "addr:full":"65 Fleetwood Rd Commack NY 11725",
    "addr:housenumber":"65",
    "addr:postcode":"11725",
    "addr:street":"Fleetwood Rd",
    "iso:country":"US",
    "sg:address":"65 Fleetwood Rd",
    "sg:city":"Commack",
    "sg:classifiers":[
        {
            "category":"Building & Trades",
            "subcategory":"Construction",
            "type":"Services"
        }
    ],
    "sg:phone":"+1 631 544 5163",
    "sg:postcode":"11725",
    "sg:province":"NY",
    "sg:tags":[
        "residential",
        "painting"
    ],
    "wof:name":"L&L Painting & Home Decorating",
    "wof:placetype":"venue"
},
  "geometry": {"coordinates":[-73.256947,40.862596],"type":"Point"}
}