{
  "type": "Feature",
  "properties": {
    "addr:full":"43 8 Ave New York NY 10014",
    "addr:postcode":"10014",
    "addr:street":"43 8 Ave",
    "iso:country":"US",
    "sg:address":"43 8 Ave",
    "sg:city":"New York",
    "sg:classifiers":[
        {
            "category":"Farming",
            "subcategory":"Nursery",
            "type":"Manufacturing & Wholesale Goods"
        }
    ],
    "sg:phone":"+1 212 463 9577",
    "sg:postcode":"10014",
    "sg:province":"NY",
    "sg:tags":[
        "ornamental"
    ],
    "wof:name":"Hatleberg/Decastro Orchids",
    "wof:placetype":"venue"
},
  "geometry": {"coordinates":[-74.004952,40.737289],"type":"Point"}
}