{
  "type": "Feature",
  "properties": {
    "addr:full":"1232 Castle Hill Ave Frnt Bronx NY 10462",
    "addr:housenumber":"1232",
    "addr:postcode":"10462",
    "addr:street":"Castle Hill Ave",
    "iso:country":"US",
    "sg:address":"1232 Castle Hill Ave Frnt",
    "sg:city":"Bronx",
    "sg:classifiers":[
        {
            "category":"Retail",
            "subcategory":"Laundry & Dry Cleaning",
            "type":"Services"
        }
    ],
    "sg:phone":"+1 718 892 1274",
    "sg:postcode":"10462",
    "sg:province":"NY",
    "wof:name":"Sssr Inc",
    "wof:placetype":"venue"
},
  "geometry": {"coordinates":[-73.85659800000001,40.842098],"type":"Point"}
}