{
  "type": "Feature",
  "properties": {
    "iso:country":"US",
    "sg:address":"143 Pollok Pl",
    "sg:city":"Hicksville",
    "sg:classifiers":[
        {
            "category":"Building & Trades",
            "subcategory":"Landscaping Services",
            "type":"Services"
        }
    ],
    "sg:phone":"+1 516 822 4953",
    "sg:postcode":"11801",
    "sg:province":"NY",
    "wof:name":"Frank Dugan Landscaping Co",
    "wof:placetype":"venue"
},
  "geometry": {"coordinates":[-73.50764700000001,40.784921],"type":"Point"}
}