{
  "type": "Feature",
  "properties": {
    "iso:country":"US",
    "sg:address":"21 Perron Dr",
    "sg:city":"Wurtsboro",
    "sg:classifiers":[
        {
            "category":"Travel",
            "subcategory":"Hotels & Motels",
            "type":"Entertainment"
        }
    ],
    "sg:phone":"+1   ",
    "sg:postcode":"12790",
    "sg:province":"NY",
    "wof:name":"Days Inn",
    "wof:placetype":"venue"
},
  "geometry": {"coordinates":[-74.497912,41.56848],"type":"Point"}
}