{
  "type": "Feature",
  "properties": {
    "addr:full":"686 Albany Ave Amityville NY 11701",
    "addr:housenumber":"686",
    "addr:postcode":"11701",
    "addr:street":"Albany Ave",
    "iso:country":"US",
    "sg:address":"686 Albany Ave",
    "sg:city":"Amityville",
    "sg:classifiers":[
        {
            "category":"Building & Trades",
            "subcategory":"Electrical",
            "type":"Services"
        }
    ],
    "sg:phone":"+1 631 842 2880",
    "sg:postcode":"11701",
    "sg:province":"NY",
    "sg:tags":[
        "electric",
        "contractor"
    ],
    "wof:name":"Robert F Lutz Electrical Contr",
    "wof:placetype":"venue"
},
  "geometry": {"coordinates":[-73.40219399999999,40.714666],"type":"Point"}
}