{
  "type": "Feature",
  "properties": {
    "iso:country":"US",
    "sg:address":"20 West 38th Street Suite 403",
    "sg:city":"Manhattan",
    "sg:classifiers":[
        {
            "category":"Professional",
            "subcategory":"Computer Services",
            "type":"Services"
        }
    ],
    "sg:phone":"+1 212 221 1388",
    "sg:postcode":"10018",
    "sg:province":"NY",
    "sg:tags":[
        "repair"
    ],
    "sg:website":"www.recovery-experts.com/",
    "wof:name":"Data Recovery Experts",
    "wof:placetype":"venue"
},
  "geometry": {"coordinates":[-73.98392,40.751213],"type":"Point"}
}