{
  "type": "Feature",
  "properties": {
    "addr:full":"840 W Fingerboard Rd Staten Island NY 10305",
    "addr:housenumber":"840",
    "addr:postcode":"10305",
    "addr:street":"W Fingerboard Rd",
    "iso:country":"US",
    "sg:address":"840 W Fingerboard Rd",
    "sg:city":"Staten Island",
    "sg:classifiers":[
        {
            "category":"Wholesale",
            "subcategory":"Non-durable Goods",
            "type":"Manufacturing & Wholesale Goods"
        }
    ],
    "sg:phone":"+1 718 447 0798",
    "sg:postcode":"10305",
    "sg:province":"NY",
    "wof:name":"DArgenio Leather Import",
    "wof:placetype":"venue"
},
  "geometry": {"coordinates":[-74.083349,40.601879],"type":"Point"}
}