{
  "type": "Feature",
  "properties": {
    "addr:full":"33 Lewis Rd Binghamton NY 13905",
    "addr:housenumber":"33",
    "addr:postcode":"13905",
    "addr:street":"Lewis Rd",
    "iso:country":"US",
    "sg:address":"33 Lewis Rd",
    "sg:city":"Binghamton",
    "sg:classifiers":[
        {
            "category":"Real Estate",
            "subcategory":"Real Estate Agent",
            "type":"Services"
        }
    ],
    "sg:phone":"+1 607 798 1655",
    "sg:postcode":"13905",
    "sg:province":"NY",
    "wof:name":"Jmi",
    "wof:placetype":"venue"
},
  "geometry": {"coordinates":[-75.935895,42.14386],"type":"Point"}
}