{
  "type": "Feature",
  "properties": {
    "addr:full":"1211 2nd Ave New York NY 10021",
    "addr:housenumber":"1211",
    "addr:postcode":"10021",
    "addr:street":"2Nd Ave",
    "iso:country":"US",
    "sg:address":"1211 2nd Ave",
    "sg:city":"New York",
    "sg:classifiers":[
        {
            "category":"Wholesale",
            "subcategory":"Home Furnishings",
            "type":"Manufacturing & Wholesale Goods"
        }
    ],
    "sg:phone":"+1 212 753 3731",
    "sg:postcode":"10021",
    "sg:province":"NY",
    "sg:tags":[
        "blind",
        "shade"
    ],
    "wof:name":"New Town House Decor Inc",
    "wof:placetype":"venue"
},
  "geometry": {"coordinates":[-73.96230300000001,40.7635],"type":"Point"}
}