{
  "type": "Feature",
  "properties": {
    "iso:country":"US",
    "sg:address":"2 E Stemmer Ln",
    "sg:city":"Suffern",
    "sg:classifiers":[
        {
            "category":"Shopping",
            "subcategory":"Computers & Home Electronics",
            "type":"Retail Goods"
        }
    ],
    "sg:phone":"+1 845 357 3312",
    "sg:postcode":"10901",
    "sg:province":"NY",
    "sg:tags":[
        "publishing"
    ],
    "wof:name":"Administrative Edge",
    "wof:placetype":"venue"
},
  "geometry": {"coordinates":[-74.096615,41.117826],"type":"Point"}
}