{
  "type": "Feature",
  "properties": {
    "iso:country":"US",
    "sg:address":"44 Midwood Rd",
    "sg:city":"Rockville Centre",
    "sg:classifiers":[
        {
            "category":"Real Estate",
            "subcategory":"Real Estate Agent",
            "type":"Services"
        }
    ],
    "sg:phone":"+1 516 594 6961",
    "sg:postcode":"11570",
    "sg:province":"NY",
    "wof:name":"M Barrett Assoc",
    "wof:placetype":"venue"
},
  "geometry": {"coordinates":[-73.63780199999999,40.672001],"type":"Point"}
}