{
  "type": "Feature",
  "properties": {
    "addr:full":"1689 Flatbush Ave Brooklyn NY 11210",
    "addr:housenumber":"1689",
    "addr:postcode":"11210",
    "addr:street":"Flatbush Ave",
    "iso:country":"US",
    "sg:address":"1689 Flatbush Ave",
    "sg:city":"Brooklyn",
    "sg:classifiers":[
        {
            "category":"Banks & Credit Unions",
            "subcategory":"Bank",
            "type":"Services"
        }
    ],
    "sg:phone":"+1 718 677 9000",
    "sg:postcode":"11210",
    "sg:province":"NY",
    "sg:tags":[
        "loan",
        "real estate"
    ],
    "wof:name":"J R Mortgages",
    "wof:placetype":"venue"
},
  "geometry": {"coordinates":[-73.94382,40.629458],"type":"Point"}
}