{
  "type": "Feature",
  "properties": {
    "iso:country":"US",
    "sg:address":"110 W 40 St",
    "sg:city":"New York",
    "sg:classifiers":[
        {
            "category":"Professional",
            "subcategory":"Lawyer & Legal Services",
            "type":"Services"
        }
    ],
    "sg:phone":"+1 212 840 1907",
    "sg:postcode":"10018",
    "sg:province":"NY",
    "sg:tags":[
        "attorney"
    ],
    "wof:name":"Mahesh Dave Law Office",
    "wof:placetype":"venue"
},
  "geometry": {"coordinates":[-73.98649500000001,40.754028],"type":"Point"}
}