{
  "type": "Feature",
  "properties": {
    "iso:country":"US",
    "sg:address":"90 Bailey Rd",
    "sg:city":"Hilton",
    "sg:classifiers":[
        {
            "category":"Shopping",
            "subcategory":"Clothing, Apparel, & Fashions",
            "type":"Retail Goods"
        }
    ],
    "sg:phone":"+1 585 392 6162",
    "sg:postcode":"14468",
    "sg:province":"NY",
    "sg:tags":[
        "apparel",
        "racing",
        "sportswear",
        "merchandise"
    ],
    "wof:name":"Kearney, Tim & Co",
    "wof:placetype":"venue"
},
  "geometry": {"coordinates":[-77.76170500000001,43.254584],"type":"Point"}
}