{
  "type": "Feature",
  "properties": {
    "addr:full":"24 Hollow Ln Westhampton NY 11977",
    "addr:housenumber":"24",
    "addr:postcode":"11977",
    "addr:street":"Hollow Ln",
    "iso:country":"US",
    "sg:address":"24 Hollow Ln",
    "sg:city":"Westhampton",
    "sg:classifiers":[
        {
            "category":"Health Services",
            "subcategory":"Medical Lab",
            "type":"Services"
        }
    ],
    "sg:phone":"+1 631 288 4873",
    "sg:postcode":"11977",
    "sg:province":"NY",
    "sg:tags":[
        "laboratory"
    ],
    "sg:website":"www.bioreference.com/",
    "wof:name":"Bio-Reference Laboratories Inc",
    "wof:placetype":"venue"
},
  "geometry": {"coordinates":[-72.684943,40.818784],"type":"Point"}
}