{
  "type": "Feature",
  "properties": {
    "addr:full":"2047 N Madison St Rome NY 13440",
    "addr:housenumber":"2047",
    "addr:postcode":"13440",
    "addr:street":"N Madison St",
    "iso:country":"US",
    "sg:address":"2047 N Madison St",
    "sg:city":"Rome",
    "sg:classifiers":[
        {
            "category":"Personal",
            "subcategory":"Beauty Salon",
            "type":"Services"
        }
    ],
    "sg:phone":"+1   ",
    "sg:postcode":"13440",
    "sg:province":"NY",
    "sg:tags":[
        "shop"
    ],
    "wof:name":"Utopia",
    "wof:placetype":"venue"
},
  "geometry": {"coordinates":[-75.44191499999999,43.238486],"type":"Point"}
}