{
  "type": "Feature",
  "properties": {
    "addr:full":"1820 Lexington Ave New York NY 10029",
    "addr:housenumber":"1820",
    "addr:postcode":"10029",
    "addr:street":"Lexington Ave",
    "iso:country":"US",
    "sg:address":"1820 Lexington Ave",
    "sg:city":"New York",
    "sg:classifiers":[
        {
            "category":"Social Services",
            "type":"Services"
        }
    ],
    "sg:phone":"+1   ",
    "sg:postcode":"10029",
    "sg:province":"NY",
    "sg:tags":[
        "profit",
        "crisis",
        "center"
    ],
    "wof:name":"East Harlem Neighborhood Base",
    "wof:placetype":"venue"
},
  "geometry": {"coordinates":[-73.943152,40.796554],"type":"Point"}
}