{
  "type": "Feature",
  "properties": {
    "iso:country":"US",
    "sg:address":"10 Pixley Industrial Pkwy",
    "sg:city":"Rochester",
    "sg:classifiers":[
        {
            "category":"Wholesale",
            "subcategory":"Machinery & Supplies",
            "type":"Manufacturing & Wholesale Goods"
        }
    ],
    "sg:phone":"+1 585 426 1210",
    "sg:postcode":"14624",
    "sg:province":"NY",
    "sg:tags":[
        "forklift",
        "equipment",
        "material",
        "handling"
    ],
    "wof:name":"Wellco Equipment Llc",
    "wof:placetype":"venue"
},
  "geometry": {"coordinates":[-77.708883,43.141064],"type":"Point"}
}