{
  "type": "Feature",
  "properties": {
    "iso:country":"US",
    "sg:address":"8266 W Henrietta Rd",
    "sg:city":"Rush",
    "sg:classifiers":[
        {
            "category":"Building & Trades",
            "subcategory":"Construction",
            "type":"Services"
        }
    ],
    "sg:phone":"+1 585 533 9051",
    "sg:postcode":"14543",
    "sg:province":"NY",
    "sg:tags":[
        "concrete",
        "contractor"
    ],
    "wof:name":"Sandstone Development",
    "wof:placetype":"venue"
},
  "geometry": {"coordinates":[-77.682062,42.968581],"type":"Point"}
}