{
  "type": "Feature",
  "properties": {
    "iso:country":"US",
    "sg:address":"1840 1 Ave",
    "sg:city":"New York",
    "sg:classifiers":[
        {
            "category":"Retail",
            "subcategory":"Auto Repair",
            "type":"Services"
        }
    ],
    "sg:phone":"+1 646 307 4806",
    "sg:postcode":"10128",
    "sg:province":"NY",
    "sg:tags":[
        "wrecker"
    ],
    "wof:name":"24hr Auto Repair",
    "wof:placetype":"venue"
},
  "geometry": {"coordinates":[-73.94842199999999,40.778182],"type":"Point"}
}