{
  "type": "Feature",
  "properties": {
    "iso:country":"US",
    "sg:address":"350 Park Ave",
    "sg:city":"New York",
    "sg:classifiers":[
        {
            "category":"Professional",
            "subcategory":"Research",
            "type":"Services"
        }
    ],
    "sg:phone":"+1 212 935 1040",
    "sg:postcode":"10022",
    "sg:province":"NY",
    "sg:tags":[
        "commercial",
        "physical"
    ],
    "wof:name":"Toho Gas Co Ltd",
    "wof:placetype":"venue"
},
  "geometry": {"coordinates":[-73.973341,40.758094],"type":"Point"}
}