{
  "type": "Feature",
  "properties": {
    "addr:full":"275 E 169th St Bronx NY 10456",
    "addr:housenumber":"275",
    "addr:postcode":"10456",
    "addr:street":"E 169Th St",
    "iso:country":"US",
    "sg:address":"275 E 169th St",
    "sg:city":"Bronx",
    "sg:classifiers":[
        {
            "category":"Food & Beverages",
            "subcategory":"Groceries & Convenience Stores",
            "type":"Retail Goods"
        }
    ],
    "sg:phone":"+1 718 681 4575",
    "sg:postcode":"10456",
    "sg:province":"NY",
    "sg:tags":[
        "grocer"
    ],
    "wof:name":"AMK Superette Corp",
    "wof:placetype":"venue"
},
  "geometry": {"coordinates":[-73.91211699999999,40.835122],"type":"Point"}
}