{
  "type": "Feature",
  "properties": {
    "addr:full":"1133 Broadway Suite 604 New York NY 10010",
    "addr:housenumber":"1133;suite 604",
    "addr:postcode":"10010",
    "addr:street":"Broadway",
    "iso:country":"US",
    "sg:address":"1133 Broadway Suite 604",
    "sg:city":"New York",
    "sg:classifiers":[
        {
            "category":"Communications",
            "type":"Services"
        },
        {
            "category":"Professional",
            "subcategory":"Computer Services",
            "type":"Services"
        }
    ],
    "sg:phone":"+1 212 255 3970",
    "sg:postcode":"10010",
    "sg:province":"NY",
    "sg:tags":[
        "repair",
        "design",
        "web"
    ],
    "sg:website":"www.pillarcc.com/",
    "wof:name":"Pillar Consulting Corporation",
    "wof:placetype":"venue"
},
  "geometry": {"coordinates":[-73.989035,40.743838],"type":"Point"}
}