{
  "type": "Feature",
  "properties": {
    "iso:country":"US",
    "sg:address":"23 Thacher St",
    "sg:city":"Albany",
    "sg:classifiers":[
        {
            "category":"Wholesale",
            "subcategory":"Electrical",
            "type":"Manufacturing & Wholesale Goods"
        }
    ],
    "sg:phone":"+1 518 449 7010",
    "sg:postcode":"12207",
    "sg:province":"NY",
    "sg:tags":[
        "control",
        "security",
        "system"
    ],
    "wof:name":"Maximum Security Prod Corp",
    "wof:placetype":"venue"
},
  "geometry": {"coordinates":[-73.74372099999999,42.662109],"type":"Point"}
}