{
  "type": "Feature",
  "properties": {
    "addr:full":"6424 11th Ave Brooklyn NY 11219",
    "addr:housenumber":"6424",
    "addr:postcode":"11219",
    "addr:street":"11Th Ave",
    "iso:country":"US",
    "sg:address":"6424 11th Ave",
    "sg:city":"Brooklyn",
    "sg:classifiers":[
        {
            "category":"Shopping",
            "subcategory":"Gifts & Souvenirs",
            "type":"Retail Goods"
        }
    ],
    "sg:phone":"+1 718 680 5154",
    "sg:postcode":"11219",
    "sg:province":"NY",
    "sg:tags":[
        "shop",
        "equipment"
    ],
    "wof:name":"Wonderland Greeting Cards",
    "wof:placetype":"venue"
},
  "geometry": {"coordinates":[-74.00599699999999,40.628799],"type":"Point"}
}