{
  "type": "Feature",
  "properties": {
    "iso:country":"US",
    "sg:address":"1105 Castle Hill Ave",
    "sg:city":"Bronx",
    "sg:classifiers":[
        {
            "category":"Personal",
            "subcategory":"Beauty Salon",
            "type":"Services"
        }
    ],
    "sg:phone":"+1   ",
    "sg:postcode":"10472",
    "sg:province":"NY",
    "sg:tags":[
        "shop"
    ],
    "wof:name":"Lisa Nails Care",
    "wof:placetype":"venue"
},
  "geometry": {"coordinates":[-73.85065400000001,40.829985],"type":"Point"}
}