{
  "type": "Feature",
  "properties": {
    "iso:country":"US",
    "sg:address":"270 Titicus Rd",
    "sg:city":"North Salem",
    "sg:classifiers":[
        {
            "category":"Government",
            "subcategory":"Office",
            "type":"Public Place"
        }
    ],
    "sg:phone":"+1 914 669 5952",
    "sg:postcode":"10560",
    "sg:province":"NY",
    "sg:tags":[
        "village"
    ],
    "wof:name":"Building Department",
    "wof:placetype":"venue"
},
  "geometry": {"coordinates":[-73.59159699999999,41.328527],"type":"Point"}
}