{
  "type": "Feature",
  "properties": {
    "iso:country":"US",
    "sg:address":"155 State Hwy 303",
    "sg:city":"Congers",
    "sg:classifiers":[
        {
            "category":"Professional",
            "subcategory":"Employment Agencies",
            "type":"Services"
        }
    ],
    "sg:phone":"+1 845 268 8700",
    "sg:postcode":"10920",
    "sg:province":"NY",
    "sg:tags":[
        "opportunity"
    ],
    "wof:name":"AGA Global Resources Corp",
    "wof:placetype":"venue"
},
  "geometry": {"coordinates":[-73.938546,41.134817],"type":"Point"}
}