{
  "type": "Feature",
  "properties": {
    "addr:full":"937 Rogers Ave Brooklyn NY 11226",
    "addr:housenumber":"937",
    "addr:postcode":"11226",
    "addr:street":"Rogers Ave",
    "iso:country":"US",
    "sg:address":"937 Rogers Ave",
    "sg:city":"Brooklyn",
    "sg:classifiers":[
        {
            "category":"Retail",
            "subcategory":"Repair Shop",
            "type":"Services"
        }
    ],
    "sg:phone":"+1 718 282 1448",
    "sg:postcode":"11226",
    "sg:province":"NY",
    "sg:tags":[
        "boiler"
    ],
    "wof:name":"Berger Welding Co Inc",
    "wof:placetype":"venue"
},
  "geometry": {"coordinates":[-73.952028,40.647402],"type":"Point"}
}