{
  "type": "Feature",
  "properties": {
    "addr:full":"1750 44th St Brooklyn NY 11204",
    "addr:housenumber":"1750",
    "addr:postcode":"11204",
    "addr:street":"44Th St",
    "iso:country":"US",
    "sg:address":"1750 44th St",
    "sg:city":"Brooklyn",
    "sg:classifiers":[
        {
            "category":"Real Estate",
            "subcategory":"Real Estate Agent",
            "type":"Services"
        }
    ],
    "sg:phone":"+1 718 435 2485",
    "sg:postcode":"11204",
    "sg:province":"NY",
    "wof:name":"1711 E 15 Realty Corp",
    "wof:placetype":"venue"
},
  "geometry": {"coordinates":[-73.97906500000001,40.631766],"type":"Point"}
}