{
  "type": "Feature",
  "properties": {
    "iso:country":"US",
    "sg:address":"8 Waring Rd",
    "sg:city":"Pound Ridge",
    "sg:classifiers":[
        {
            "category":"Professional",
            "subcategory":"Business Services",
            "type":"Services"
        }
    ],
    "sg:phone":"+1 914 234 2838",
    "sg:postcode":"10576",
    "sg:province":"NY",
    "sg:tags":[
        "interior",
        "consultant",
        "design",
        "decorator"
    ],
    "wof:name":"Tromped-Up Inc",
    "wof:placetype":"venue"
},
  "geometry": {"coordinates":[-73.600368,41.169706],"type":"Point"}
}