{
  "type": "Feature",
  "properties": {
    "addr:full":"2 James St Hudson NY 12534",
    "addr:housenumber":"2",
    "addr:postcode":"12534",
    "addr:street":"James St",
    "iso:country":"US",
    "sg:address":"2 James St",
    "sg:city":"Hudson",
    "sg:classifiers":[
        {
            "category":"Restaurant",
            "type":"Food & Drink"
        }
    ],
    "sg:phone":"+1 518 822 9298",
    "sg:postcode":"12534",
    "sg:province":"NY",
    "wof:name":"Bob's Restaurant",
    "wof:placetype":"venue"
},
  "geometry": {"coordinates":[-73.76280199999999,42.261101],"type":"Point"}
}