{
  "type": "Feature",
  "properties": {
    "iso:country":"US",
    "sg:address":"45 Columbia Ave",
    "sg:city":"Thornwood",
    "sg:classifiers":[
        {
            "category":"Manufacturing",
            "subcategory":"Motor Vehicles & Parts",
            "type":"Manufacturing & Wholesale Goods"
        }
    ],
    "sg:phone":"+1 914 769 9491",
    "sg:postcode":"10594",
    "sg:province":"NY",
    "sg:tags":[
        "automobile",
        "supply"
    ],
    "wof:name":"AMS Distributors Inc",
    "wof:placetype":"venue"
},
  "geometry": {"coordinates":[-73.783137,41.119039],"type":"Point"}
}