{
  "type": "Feature",
  "properties": {
    "addr:full":"16919 Jamaica Ave Jamaica NY 11432",
    "addr:housenumber":"16919",
    "addr:postcode":"11432",
    "addr:street":"Jamaica Ave",
    "iso:country":"US",
    "sg:address":"16919 Jamaica Ave",
    "sg:city":"Jamaica",
    "sg:classifiers":[
        {
            "category":"Personal",
            "subcategory":"Nail Salon",
            "type":"Services"
        }
    ],
    "sg:phone":"+1 718 523 1086",
    "sg:postcode":"11432",
    "sg:province":"NY",
    "wof:name":"Queen Nails 169, Inc.",
    "wof:placetype":"venue"
},
  "geometry": {"coordinates":[-73.79690600000001,40.704651],"type":"Point"}
}