{
  "type": "Feature",
  "properties": {
    "addr:full":"12 Ave J Ronkonkoma NY 11779",
    "addr:postcode":"11779",
    "addr:street":"12 Ave J Ronkonkoma",
    "iso:country":"US",
    "sg:address":"12 Ave J",
    "sg:city":"Ronkonkoma",
    "sg:classifiers":[
        {
            "category":"Shopping",
            "subcategory":"Clothing, Apparel, & Fashions",
            "type":"Retail Goods"
        }
    ],
    "sg:phone":"+1 631 475 6101",
    "sg:postcode":"11779",
    "sg:province":"NY",
    "sg:tags":[
        "uniform"
    ],
    "wof:name":"Uniforms N' Things",
    "wof:placetype":"venue"
},
  "geometry": {"coordinates":[-73.093671,40.822364],"type":"Point"}
}