{
  "type": "Feature",
  "properties": {
    "addr:full":"3234 Steinway Street Astoria NY 11103",
    "addr:housenumber":"3234",
    "addr:postcode":"11103",
    "addr:street":"Steinway Street",
    "iso:country":"US",
    "sg:address":"3234 Steinway Street",
    "sg:city":"Astoria",
    "sg:classifiers":[
        {
            "category":"Health Services",
            "subcategory":"Dentist",
            "type":"Services"
        }
    ],
    "sg:phone":"+1 718 728 3427",
    "sg:postcode":"11103",
    "sg:province":"NY",
    "wof:name":"Stein Jerome DDS",
    "wof:placetype":"venue"
},
  "geometry": {"coordinates":[-73.91930499999999,40.758805],"type":"Point"}
}