{
  "type": "Feature",
  "properties": {
    "addr:full":"330 Hudson Street New York NY 10013",
    "addr:housenumber":"330",
    "addr:postcode":"10013",
    "addr:street":"Hudson Street",
    "iso:country":"US",
    "sg:address":"330 Hudson Street",
    "sg:city":"New York",
    "sg:classifiers":[
        {
            "category":"Wholesale",
            "subcategory":"Computers",
            "type":"Manufacturing & Wholesale Goods"
        }
    ],
    "sg:phone":"+1 212 627 2008",
    "sg:postcode":"10013",
    "sg:province":"NY",
    "wof:name":"Timatt Computer Solutions",
    "wof:placetype":"venue"
},
  "geometry": {"coordinates":[-74.007368,40.726905],"type":"Point"}
}