{
  "type": "Feature",
  "properties": {
    "addr:full":"62 University Place New York NY 10003",
    "addr:housenumber":"62",
    "addr:postcode":"10003",
    "addr:street":"University Place",
    "iso:country":"US",
    "sg:address":"62 University Place",
    "sg:city":"New York",
    "sg:classifiers":[
        {
            "category":"Restaurant",
            "type":"Food & Drink"
        }
    ],
    "sg:phone":"+1 212 995 0816",
    "sg:postcode":"10003",
    "sg:province":"NY",
    "wof:name":"Wrapp City",
    "wof:placetype":"venue"
},
  "geometry": {"coordinates":[-73.9935,40.732874],"type":"Point"}
}