{
  "type": "Feature",
  "properties": {
    "addr:full":"1918 Gates Ave Ridgewood NY 11385",
    "addr:housenumber":"1918",
    "addr:postcode":"11385",
    "addr:street":"Gates Ave",
    "iso:country":"US",
    "sg:address":"1918 Gates Ave",
    "sg:city":"Ridgewood",
    "sg:classifiers":[
        {
            "category":"Building & Trades",
            "subcategory":"Construction",
            "type":"Services"
        }
    ],
    "sg:phone":"+1 718 628 1324",
    "sg:postcode":"11385",
    "sg:province":"NY",
    "sg:tags":[
        "contractor"
    ],
    "wof:name":"York Tile & Marble Co",
    "wof:placetype":"venue"
},
  "geometry": {"coordinates":[-73.905348,40.706118],"type":"Point"}
}