{
  "type": "Feature",
  "properties": {
    "addr:full":"7579 Maple Rd Akron NY 14001",
    "addr:housenumber":"7579",
    "addr:postcode":"14001",
    "addr:street":"Maple Rd",
    "iso:country":"US",
    "sg:address":"7579 Maple Rd",
    "sg:city":"Akron",
    "sg:classifiers":[
        {
            "category":"Professional",
            "type":"Services"
        }
    ],
    "sg:phone":"+1 716 542 1511",
    "sg:postcode":"14001",
    "sg:province":"NY",
    "sg:tags":[
        "establishment"
    ],
    "wof:name":"Bay Creek",
    "wof:placetype":"venue"
},
  "geometry": {"coordinates":[-78.512384,43.052784],"type":"Point"}
}