{
  "type": "Feature",
  "properties": {
    "iso:country":"US",
    "sg:address":"17 Blackberry Hill Rd",
    "sg:city":"Katonah",
    "sg:classifiers":[
        {
            "category":"Banks & Credit Unions",
            "subcategory":"Investment Brokerage",
            "type":"Services"
        }
    ],
    "sg:phone":"+1 914 234 4011",
    "sg:postcode":"10536",
    "sg:province":"NY",
    "sg:tags":[
        "advisory",
        "financial"
    ],
    "wof:name":"Tsuris Funding",
    "wof:placetype":"venue"
},
  "geometry": {"coordinates":[-73.722263,41.30746],"type":"Point"}
}