{
  "type": "Feature",
  "properties": {
    "addr:full":"21 Devoe St Brooklyn NY 11211",
    "addr:housenumber":"21",
    "addr:postcode":"11211",
    "addr:street":"Devoe St",
    "iso:country":"US",
    "sg:address":"21 Devoe St",
    "sg:city":"Brooklyn",
    "sg:classifiers":[
        {
            "category":"Communications",
            "subcategory":"Film & Video Production",
            "type":"Services"
        }
    ],
    "sg:phone":"+1   ",
    "sg:postcode":"11211",
    "sg:province":"NY",
    "sg:tags":[
        "motion"
    ],
    "wof:name":"Ripped Productions",
    "wof:placetype":"venue"
},
  "geometry": {"coordinates":[-73.949955,40.713304],"type":"Point"}
}