{
  "type": "Feature",
  "properties": {
    "addr:full":"304 Tompkins Ave Brooklyn NY 11216",
    "addr:housenumber":"304",
    "addr:postcode":"11216",
    "addr:street":"Tompkins Ave",
    "iso:country":"US",
    "sg:address":"304 Tompkins Ave",
    "sg:city":"Brooklyn",
    "sg:classifiers":[
        {
            "category":"Personal",
            "subcategory":"Beauty Salon",
            "type":"Services"
        }
    ],
    "sg:phone":"+1   ",
    "sg:postcode":"11216",
    "sg:province":"NY",
    "sg:tags":[
        "shop"
    ],
    "wof:name":"Pee Wees Playhouse",
    "wof:placetype":"venue"
},
  "geometry": {"coordinates":[-73.944712,40.686998],"type":"Point"}
}