{
  "type": "Feature",
  "properties": {
    "iso:country":"US",
    "sg:address":"156 W 56th St",
    "sg:city":"New York",
    "sg:classifiers":[
        {
            "category":"Travel",
            "subcategory":"Hotels & Motels",
            "type":"Entertainment"
        }
    ],
    "sg:phone":"+1 212 246 8032",
    "sg:postcode":"10019",
    "sg:province":"NY",
    "wof:name":"Jtbi New York",
    "wof:placetype":"venue"
},
  "geometry": {"coordinates":[-73.97968400000001,40.764329],"type":"Point"}
}