{
  "type": "Feature",
  "properties": {
    "iso:country":"US",
    "sg:address":"1106 Rte 112",
    "sg:city":"Port Jefferson Station",
    "sg:classifiers":[
        {
            "category":"Food & Beverages",
            "subcategory":"Liquor & Beverages",
            "type":"Retail Goods"
        }
    ],
    "sg:phone":"+1 631 331 7979",
    "sg:postcode":"11776",
    "sg:province":"NY",
    "sg:tags":[
        "alcoholic"
    ],
    "wof:name":"Z Best Liquors",
    "wof:placetype":"venue"
},
  "geometry": {"coordinates":[-73.04297699999999,40.921285],"type":"Point"}
}