{
  "type": "Feature",
  "properties": {
    "addr:full":"444 Thomas S Boyland St Brooklyn NY 11212",
    "addr:housenumber":"444",
    "addr:postcode":"11212",
    "addr:street":"Thomas S Boyland St",
    "iso:country":"US",
    "sg:address":"444 Thomas S Boyland St",
    "sg:city":"Brooklyn",
    "sg:classifiers":[
        {
            "category":"Health Services",
            "subcategory":"Clinic",
            "type":"Services"
        }
    ],
    "sg:phone":"+1 718 922 3490",
    "sg:postcode":"11212",
    "sg:province":"NY",
    "sg:tags":[
        "home"
    ],
    "wof:name":"Bhrags Home Care Inc",
    "wof:placetype":"venue"
},
  "geometry": {"coordinates":[-73.91381199999999,40.670064],"type":"Point"}
}