{
  "type": "Feature",
  "properties": {
    "addr:full":"6 Mill Creek Rd Stony Brook NY 11790",
    "addr:housenumber":"6",
    "addr:postcode":"11790",
    "addr:street":"Mill Creek Rd",
    "iso:country":"US",
    "sg:address":"6 Mill Creek Rd",
    "sg:city":"Stony Brook",
    "sg:classifiers":[
        {
            "category":"Building & Trades",
            "subcategory":"Electrical",
            "type":"Services"
        }
    ],
    "sg:phone":"+1 631 751 1751",
    "sg:postcode":"11790",
    "sg:province":"NY",
    "sg:tags":[
        "electrical",
        "contractor"
    ],
    "wof:name":"Lake Grove Electric Inc",
    "wof:placetype":"venue"
},
  "geometry": {"coordinates":[-73.148554,40.916447],"type":"Point"}
}