{
  "type": "Feature",
  "properties": {
    "addr:full":"7509 71st Avenue Middle Village NY 11379",
    "addr:housenumber":"7509",
    "addr:postcode":"11379",
    "addr:street":"71St Avenue",
    "iso:country":"US",
    "sg:address":"7509 71st Avenue",
    "sg:city":"Middle Village",
    "sg:classifiers":[
        {
            "category":"Sports & Exercise",
            "subcategory":"Gym",
            "type":"Entertainment"
        }
    ],
    "sg:phone":"+1 718 326 2496",
    "sg:postcode":"11379",
    "sg:province":"NY",
    "wof:name":"Coliseum Gym & Fitness Center",
    "wof:placetype":"venue"
},
  "geometry": {"coordinates":[-73.875469,40.706929],"type":"Point"}
}