{
  "type": "Feature",
  "properties": {
    "addr:full":"400 Lakeville Rd New Hyde Park NY 11042",
    "addr:housenumber":"400",
    "addr:postcode":"11042",
    "addr:street":"Lakeville Rd",
    "iso:country":"US",
    "sg:address":"400 Lakeville Rd",
    "sg:city":"New Hyde Park",
    "sg:classifiers":[
        {
            "category":"Health Services",
            "subcategory":"Doctor",
            "type":"Services"
        },
        {
            "category":"Health Services",
            "subcategory":"Clinic",
            "type":"Services"
        }
    ],
    "sg:phone":"+1 718 470 8767",
    "sg:postcode":"11042",
    "sg:province":"NY",
    "sg:tags":[
        "counseling",
        "mental"
    ],
    "wof:name":"Novick Rona PHD",
    "wof:placetype":"venue"
},
  "geometry": {"coordinates":[-73.69259599999999,40.7598],"type":"Point"}
}