{
  "type": "Feature",
  "properties": {
    "iso:country":"US",
    "sg:address":"128 Green St",
    "sg:city":"Hudson",
    "sg:classifiers":[
        {
            "category":"Shopping",
            "subcategory":"Florist",
            "type":"Retail Goods"
        }
    ],
    "sg:phone":"+1 518 828 9952",
    "sg:postcode":"12534",
    "sg:province":"NY",
    "sg:website":"www.roseryflowershop.com",
    "wof:name":"Rosery Flower Shop the",
    "wof:placetype":"venue"
},
  "geometry": {"coordinates":[-73.77510100000001,42.248402],"type":"Point"}
}