{
  "type": "Feature",
  "properties": {
    "iso:country":"US",
    "sg:address":"601 Seneca Ave",
    "sg:city":"Ridgewood",
    "sg:classifiers":[
        {
            "category":"Food & Beverages",
            "subcategory":"Ethnic Foods",
            "type":"Retail Goods"
        }
    ],
    "sg:phone":"+1 718 418 5880",
    "sg:postcode":"11385",
    "sg:province":"NY",
    "wof:name":"Seneca Garden",
    "wof:placetype":"venue"
},
  "geometry": {"coordinates":[-73.90990499999999,40.704115],"type":"Point"}
}