{
  "type": "Feature",
  "properties": {
    "iso:country":"US",
    "sg:address":"30 Donovan Dr",
    "sg:city":"Buffalo",
    "sg:classifiers":[
        {
            "category":"Social Services",
            "subcategory":"Child Care",
            "type":"Services"
        }
    ],
    "sg:phone":"+1 716 894 1001",
    "sg:postcode":"14211",
    "sg:province":"NY",
    "wof:name":"Tonya's Daycare Ctr",
    "wof:placetype":"venue"
},
  "geometry": {"coordinates":[-78.82744700000001,42.913056],"type":"Point"}
}