{
  "type": "Feature",
  "properties": {
    "iso:country":"US",
    "sg:address":"211 W 80 St",
    "sg:city":"New York",
    "sg:classifiers":[
        {
            "category":"Wholesale",
            "subcategory":"Electrical",
            "type":"Manufacturing & Wholesale Goods"
        }
    ],
    "sg:phone":"+1   ",
    "sg:postcode":"10024",
    "sg:province":"NY",
    "sg:tags":[
        "computer",
        "electronic",
        "mfg"
    ],
    "wof:name":"Central Teletronics",
    "wof:placetype":"venue"
},
  "geometry": {"coordinates":[-73.979141,40.784426],"type":"Point"}
}