{
  "type": "Feature",
  "properties": {
    "addr:full":"811 Seneca Ave Ridgewood NY 11385",
    "addr:housenumber":"811",
    "addr:postcode":"11385",
    "addr:street":"Seneca Ave",
    "iso:country":"US",
    "sg:address":"811 Seneca Ave",
    "sg:city":"Ridgewood",
    "sg:classifiers":[
        {
            "category":"Restaurant",
            "type":"Food & Drink"
        }
    ],
    "sg:menulink":"http://www.allmenus.com/ny/queens/93989-el-arco-iris-restaurant/menu/",
    "sg:phone":"+1 718 386 9265",
    "sg:postcode":"11385",
    "sg:province":"NY",
    "sg:tags":[
        "dominican"
    ],
    "wof:name":"El Arco Iris Restaurant",
    "wof:placetype":"venue"
},
  "geometry": {"coordinates":[-73.90530800000001,40.701392],"type":"Point"}
}