{
  "type": "Feature",
  "properties": {
    "iso:country":"US",
    "sg:address":"547 Greenbush Rd",
    "sg:city":"Blauvelt",
    "sg:classifiers":[
        {
            "category":"Building & Trades",
            "subcategory":"Plumbing",
            "type":"Services"
        },
        {
            "category":"Building & Trades",
            "subcategory":"Construction",
            "type":"Services"
        }
    ],
    "sg:phone":"+1 845 353 8788",
    "sg:postcode":"10913",
    "sg:province":"NY",
    "sg:tags":[
        "plumber",
        "industrial",
        "system",
        "specialty",
        "heating",
        "contractors-commercial",
        "contractor",
        "air conditioning"
    ],
    "wof:name":"Master Plumbing & Heating",
    "wof:placetype":"venue"
},
  "geometry": {"coordinates":[-73.946715,41.078483],"type":"Point"}
}