{
  "type": "Feature",
  "properties": {
    "addr:full":"115 Philip St Albany NY 12202",
    "addr:housenumber":"115",
    "addr:postcode":"12202",
    "addr:street":"Philip St",
    "iso:country":"US",
    "sg:address":"115 Philip St",
    "sg:city":"Albany",
    "sg:classifiers":[
        {
            "category":"Restaurant",
            "type":"Food & Drink"
        }
    ],
    "sg:menulink":"http://www.allmenus.com/ny/albany/61710-mansion-hill-inn--restaurant/menu/",
    "sg:phone":"+1 518 465 2038",
    "sg:postcode":"12202",
    "sg:province":"NY",
    "sg:tags":[
        "american"
    ],
    "wof:name":"Mansion Hill Inn & Restaurant",
    "wof:placetype":"venue"
},
  "geometry": {"coordinates":[-73.75995500000001,42.644405],"type":"Point"}
}