{
  "type": "Feature",
  "properties": {
    "iso:country":"US",
    "sg:address":"188 Ashburton Ave",
    "sg:city":"Yonkers",
    "sg:classifiers":[
        {
            "category":"Restaurant",
            "type":"Food & Drink"
        }
    ],
    "sg:phone":"+1 914 969 0551",
    "sg:postcode":"10701",
    "sg:province":"NY",
    "wof:name":"Bandar Fast Food Inc",
    "wof:placetype":"venue"
},
  "geometry": {"coordinates":[-73.88843,40.939281],"type":"Point"}
}