{
  "type": "Feature",
  "properties": {
    "iso:country":"US",
    "sg:address":"1121 Morris Park Ave",
    "sg:city":"Bronx",
    "sg:classifiers":[
        {
            "category":"Retail",
            "subcategory":"Funeral Services",
            "type":"Services"
        }
    ],
    "sg:phone":"+1 718 863 2000",
    "sg:postcode":"10461",
    "sg:province":"NY",
    "sg:tags":[
        "director",
        "home"
    ],
    "wof:name":"John Dormi & Sons Inc",
    "wof:placetype":"venue"
},
  "geometry": {"coordinates":[-73.85136799999999,40.850304],"type":"Point"}
}