{
  "type": "Feature",
  "properties": {
    "iso:country":"US",
    "sg:address":"10011 Liberty Ave",
    "sg:city":"Ozone Park",
    "sg:classifiers":[
        {
            "category":"Autos & Motor Vehicles",
            "subcategory":"Automobile Sales",
            "type":"Retail Goods"
        },
        {
            "category":"Building & Trades",
            "subcategory":"Locksmith",
            "type":"Services"
        }
    ],
    "sg:phone":"+1 718 850 7287",
    "sg:postcode":"11417",
    "sg:province":"NY",
    "sg:tags":[
        "car",
        "key"
    ],
    "wof:name":"East Coast Auto Sales",
    "wof:placetype":"venue"
},
  "geometry": {"coordinates":[-73.84002,40.68118],"type":"Point"}
}