{
  "type": "Feature",
  "properties": {
    "addr:full":"3864 10th Ave New York NY 10034",
    "addr:housenumber":"3864",
    "addr:postcode":"10034",
    "addr:street":"10Th Ave",
    "iso:country":"US",
    "sg:address":"3864 10th Ave",
    "sg:city":"New York",
    "sg:classifiers":[
        {
            "category":"Restaurant",
            "type":"Food & Drink"
        }
    ],
    "sg:menulink":"http://www.allmenus.com/ny/new-york/47979-ten-tan/menu/",
    "sg:phone":"+1 212 304 0330",
    "sg:postcode":"10034",
    "sg:province":"NY",
    "sg:tags":[
        "asian",
        "chinese"
    ],
    "wof:name":"Ten-Tan",
    "wof:placetype":"venue"
},
  "geometry": {"coordinates":[-73.91944700000001,40.863846],"type":"Point"}
}