{
  "type": "Feature",
  "properties": {
    "addr:full":"4 Melissa Dr Farmingville NY 11738",
    "addr:housenumber":"4",
    "addr:postcode":"11738",
    "addr:street":"Melissa Dr",
    "iso:country":"US",
    "sg:address":"4 Melissa Dr",
    "sg:city":"Farmingville",
    "sg:classifiers":[
        {
            "category":"Real Estate",
            "subcategory":"Real Estate Operator",
            "type":"Services"
        }
    ],
    "sg:phone":"+1 631 732 2472",
    "sg:postcode":"11738",
    "sg:province":"NY",
    "sg:tags":[
        "building",
        "nonresidential"
    ],
    "wof:name":"John J Pyatt",
    "wof:placetype":"venue"
},
  "geometry": {"coordinates":[-73.011807,40.836755],"type":"Point"}
}