{
  "type": "Feature",
  "properties": {
    "addr:full":"60 Lorimer St Brooklyn NY 11206",
    "addr:housenumber":"60",
    "addr:postcode":"11206",
    "addr:street":"Lorimer St",
    "iso:country":"US",
    "sg:address":"60 Lorimer St",
    "sg:city":"Brooklyn",
    "sg:classifiers":[
        {
            "category":"Organizations",
            "subcategory":"Professional Association",
            "type":"Services"
        }
    ],
    "sg:phone":"+1 718 486 0115",
    "sg:postcode":"11206",
    "sg:province":"NY",
    "wof:name":"D & M Assn",
    "wof:placetype":"venue"
},
  "geometry": {"coordinates":[-73.953856,40.700165],"type":"Point"}
}