{
  "type": "Feature",
  "properties": {
    "addr:full":"1321 Madison Ave New York NY 10128",
    "addr:housenumber":"1321",
    "addr:postcode":"10128",
    "addr:street":"Madison Ave",
    "iso:country":"US",
    "sg:address":"1321 Madison Ave",
    "sg:city":"New York",
    "sg:classifiers":[
        {
            "category":"Personal",
            "subcategory":"Barber",
            "type":"Services"
        }
    ],
    "sg:phone":"+1 212 828 8209",
    "sg:postcode":"10128",
    "sg:province":"NY",
    "wof:name":"Hair By Kasia",
    "wof:placetype":"venue"
},
  "geometry": {"coordinates":[-73.95508700000001,40.785819],"type":"Point"}
}