{
  "type": "Feature",
  "properties": {
    "iso:country":"US",
    "sg:address":"1785 Western Ave",
    "sg:city":"Albany",
    "sg:classifiers":[
        {
            "category":"Restaurant",
            "type":"Food & Drink"
        }
    ],
    "sg:menulink":"http://www.allmenus.com/ny/guilderland/62885-paesans-pizza/menu/",
    "sg:phone":"+1 518 464 0725",
    "sg:postcode":"12203",
    "sg:province":"NY",
    "sg:tags":[
        "american",
        "pizza"
    ],
    "wof:name":"Paesan's Pizza",
    "wof:placetype":"venue"
},
  "geometry": {"coordinates":[-73.86518700000001,42.690299],"type":"Point"}
}