{
  "type": "Feature",
  "properties": {
    "iso:country":"US",
    "sg:address":"255 Fieldston Ter",
    "sg:city":"Bronx",
    "sg:classifiers":[
        {
            "category":"Organizations",
            "subcategory":"Religious Organization",
            "type":"Services"
        }
    ],
    "sg:phone":"+1   ",
    "sg:postcode":"10471",
    "sg:province":"NY",
    "wof:name":"Daniel Nickerson",
    "wof:placetype":"venue"
},
  "geometry": {"coordinates":[-73.899113,40.896607],"type":"Point"}
}