{
  "type": "Feature",
  "properties": {
    "iso:country":"US",
    "sg:address":"39 Montcalm Ave",
    "sg:city":"Plattsburgh",
    "sg:classifiers":[
        {
            "category":"Retail",
            "subcategory":"Laundry & Dry Cleaning",
            "type":"Services"
        }
    ],
    "sg:phone":"+1 518 562 8659",
    "sg:postcode":"12901",
    "sg:province":"NY",
    "wof:name":"Montcalm Avenue Laundry",
    "wof:placetype":"venue"
},
  "geometry": {"coordinates":[-73.46075999999999,44.70122],"type":"Point"}
}