{
  "type": "Feature",
  "properties": {
    "addr:full":"469 Fashion Ave 4th Fl New York NY 10018",
    "addr:housenumber":"469",
    "addr:postcode":"10018",
    "addr:street":"Fashion Ave",
    "iso:country":"US",
    "sg:address":"469 Fashion Ave 4th Fl",
    "sg:city":"New York",
    "sg:classifiers":[
        {
            "category":"Communications",
            "subcategory":"Newspaper",
            "type":"Services"
        }
    ],
    "sg:phone":"+1 212 359 9502",
    "sg:postcode":"10018",
    "sg:province":"NY",
    "sg:tags":[
        "print",
        "medium"
    ],
    "sg:website":"www.affluentpageluxuryindex.com",
    "wof:name":"The Affluent Page",
    "wof:placetype":"venue"
},
  "geometry": {"coordinates":[-73.98992699999999,40.75188],"type":"Point"}
}