{
  "type": "Feature",
  "properties": {
    "addr:full":"15 E 71 St New York NY 10021",
    "addr:housenumber":"15;71",
    "addr:postcode":"10021",
    "addr:street":"E;St",
    "iso:country":"US",
    "sg:address":"15 E 71 St",
    "sg:city":"New York",
    "sg:classifiers":[
        {
            "category":"Personal",
            "subcategory":"Beauty Salon",
            "type":"Services"
        }
    ],
    "sg:phone":"+1 212 396 3530",
    "sg:postcode":"10021",
    "sg:province":"NY",
    "sg:tags":[
        "shop"
    ],
    "wof:name":"Yossi",
    "wof:placetype":"venue"
},
  "geometry": {"coordinates":[-73.966503,40.771503],"type":"Point"}
}