{
  "type": "Feature",
  "properties": {
    "addr:full":"5429 Flatlands Ave Brooklyn NY 11234",
    "addr:housenumber":"5429",
    "addr:postcode":"11234",
    "addr:street":"Flatlands Ave",
    "iso:country":"US",
    "sg:address":"5429 Flatlands Ave",
    "sg:city":"Brooklyn",
    "sg:classifiers":[
        {
            "category":"Retail",
            "subcategory":"Laundry & Dry Cleaning",
            "type":"Services"
        }
    ],
    "sg:phone":"+1 718 209 4178",
    "sg:postcode":"11234",
    "sg:province":"NY",
    "sg:tags":[
        "cleaner"
    ],
    "wof:name":"White Linen Cleaners",
    "wof:placetype":"venue"
},
  "geometry": {"coordinates":[-73.923546,40.628911],"type":"Point"}
}