{
  "type": "Feature",
  "properties": {
    "iso:country":"US",
    "sg:address":"80 Red Schoolhouse Rd",
    "sg:city":"Spring Valley",
    "sg:classifiers":[
        {
            "category":"Wholesale",
            "subcategory":"Computers",
            "type":"Manufacturing & Wholesale Goods"
        },
        {
            "category":"Wholesale",
            "subcategory":"Stationery",
            "type":"Manufacturing & Wholesale Goods"
        }
    ],
    "sg:phone":"+1 845 356 4631",
    "sg:postcode":"10977",
    "sg:province":"NY",
    "sg:tags":[
        "paper",
        "equipment",
        "processing",
        "word",
        "supply"
    ],
    "wof:name":"Office Communications Co",
    "wof:placetype":"venue"
},
  "geometry": {"coordinates":[-74.05573699999999,41.08206],"type":"Point"}
}