{
  "type": "Feature",
  "properties": {
    "iso:country":"US",
    "sg:address":"1412 Myrtle Ave",
    "sg:city":"Brooklyn",
    "sg:classifiers":[
        {
            "category":"Shopping",
            "subcategory":"Clothing, Apparel, & Fashions",
            "type":"Retail Goods"
        }
    ],
    "sg:phone":"+1   ",
    "sg:postcode":"11237",
    "sg:province":"NY",
    "sg:tags":[
        "family",
        "store"
    ],
    "wof:name":"Jaspreet & Manpreet Inc",
    "wof:placetype":"venue"
},
  "geometry": {"coordinates":[-73.91836499999999,40.698808],"type":"Point"}
}