{
  "type": "Feature",
  "properties": {
    "iso:country":"US",
    "sg:address":"2325 Owego Rd",
    "sg:city":"Vestal",
    "sg:classifiers":[
        {
            "category":"Retail",
            "subcategory":"Laundry & Dry Cleaning",
            "type":"Services"
        },
        {
            "category":"Building & Trades",
            "subcategory":"Cleaning & Sanitation",
            "type":"Services"
        },
        {
            "category":"Home & Garden",
            "subcategory":"Carpets & Floor Coverings",
            "type":"Retail Goods"
        }
    ],
    "sg:phone":"+1 607 722 0022",
    "sg:postcode":"13850",
    "sg:province":"NY",
    "sg:tags":[
        "cleaner",
        "upholstery",
        "fire",
        "rug",
        "damage",
        "water",
        "restoration"
    ],
    "sg:website":"http://www.stanleysteemer.com",
    "wof:name":"Stanley Steemer",
    "wof:placetype":"venue"
},
  "geometry": {"coordinates":[-76.09962899999999,42.067527],"type":"Point"}
}