{
  "type": "Feature",
  "properties": {
    "iso:country":"US",
    "sg:address":"149 Lake Rd",
    "sg:city":"Ballston Lake",
    "sg:classifiers":[
        {
            "category":"Building & Trades",
            "subcategory":"Construction",
            "type":"Services"
        }
    ],
    "sg:phone":"+1 518 384 0104",
    "sg:postcode":"12019",
    "sg:province":"NY",
    "sg:tags":[
        "contractor"
    ],
    "wof:name":"Real Breton Contractor",
    "wof:placetype":"venue"
},
  "geometry": {"coordinates":[-73.850521,42.949067],"type":"Point"}
}