{
  "type": "Feature",
  "properties": {
    "addr:full":"159 Avenue C New York NY 10009",
    "addr:housenumber":"159",
    "addr:postcode":"10009",
    "addr:street":"Avenue C",
    "iso:country":"US",
    "sg:address":"159 Avenue C",
    "sg:city":"New York",
    "sg:classifiers":[
        {
            "category":"Retail",
            "subcategory":"Laundry & Dry Cleaning",
            "type":"Services"
        }
    ],
    "sg:phone":"+1 212 477 6000",
    "sg:postcode":"10009",
    "sg:province":"NY",
    "wof:name":"Christy William Internet Cafe",
    "wof:placetype":"venue"
},
  "geometry": {"coordinates":[-73.97779800000001,40.7257],"type":"Point"}
}