{
  "type": "Feature",
  "properties": {
    "iso:country":"US",
    "sg:address":"150 William St",
    "sg:city":"Manhattan",
    "sg:classifiers":[
        {
            "category":"Deli",
            "type":"Food & Drink"
        }
    ],
    "sg:phone":"+1 212 571 2114",
    "sg:postcode":"10038",
    "sg:province":"NY",
    "wof:name":"150 Market",
    "wof:placetype":"venue"
},
  "geometry": {"coordinates":[-74.006066,40.709831],"type":"Point"}
}