{
  "type": "Feature",
  "properties": {
    "addr:full":"1 W 30 St New York NY 10001",
    "addr:housenumber":"1",
    "addr:postcode":"10001",
    "addr:street":"W 30 St",
    "iso:country":"US",
    "sg:address":"1 W 30 St",
    "sg:city":"New York",
    "sg:classifiers":[
        {
            "category":"Professional",
            "type":"Services"
        }
    ],
    "sg:phone":"+1 212 564 8104",
    "sg:postcode":"10001",
    "sg:province":"NY",
    "sg:tags":[
        "establishment"
    ],
    "wof:name":"John Knight LTD",
    "wof:placetype":"venue"
},
  "geometry": {"coordinates":[-73.988452,40.746789],"type":"Point"}
}