{
  "type": "Feature",
  "properties": {
    "addr:full":"1351 E Bay Ave Bronx NY 10474",
    "addr:housenumber":"1351",
    "addr:postcode":"10474",
    "addr:street":"E Bay Ave",
    "iso:country":"US",
    "sg:address":"1351 E Bay Ave",
    "sg:city":"Bronx",
    "sg:classifiers":[
        {
            "category":"Government",
            "subcategory":"Office",
            "type":"Public Place"
        }
    ],
    "sg:phone":"+1 718 842 1910",
    "sg:postcode":"10474",
    "sg:province":"NY",
    "sg:tags":[
        "administrative",
        "program",
        "health"
    ],
    "wof:name":"New York Road Runners Club",
    "wof:placetype":"venue"
},
  "geometry": {"coordinates":[-73.88237100000001,40.809172],"type":"Point"}
}