{
  "type": "Feature",
  "properties": {
    "addr:full":"99 Madison Ave New York NY 10016",
    "addr:housenumber":"99",
    "addr:postcode":"10016",
    "addr:street":"Madison Ave",
    "iso:country":"US",
    "sg:address":"99 Madison Ave",
    "sg:city":"New York",
    "sg:classifiers":[
        {
            "category":"Banks & Credit Unions",
            "subcategory":"Bank",
            "type":"Services"
        }
    ],
    "sg:phone":"+1 212 532 4444",
    "sg:postcode":"10016",
    "sg:province":"NY",
    "wof:name":"Habib Amer Bank",
    "wof:placetype":"venue"
},
  "geometry": {"coordinates":[-73.977203,40.744499],"type":"Point"}
}