{
  "type": "Feature",
  "properties": {
    "iso:country":"US",
    "sg:address":"39 Washington Ave",
    "sg:city":"Pleasantville",
    "sg:classifiers":[
        {
            "category":"Professional",
            "subcategory":"Art Services",
            "type":"Services"
        },
        {
            "category":"Professional",
            "subcategory":"Printing & Photocopies",
            "type":"Services"
        },
        {
            "category":"Communications",
            "type":"Services"
        }
    ],
    "sg:phone":"+1 914 449 6100",
    "sg:postcode":"10570",
    "sg:province":"NY",
    "sg:tags":[
        "web",
        "graphic",
        "design"
    ],
    "sg:website":"webdesignpleasantville.com/#cid=...",
    "wof:name":"VariDirect Solutions",
    "wof:placetype":"venue"
},
  "geometry": {"coordinates":[-73.791757,41.135279],"type":"Point"}
}