{
  "type": "Feature",
  "properties": {
    "addr:full":"235 Mohawk Dr Tribes Hill NY 12177",
    "addr:housenumber":"235",
    "addr:postcode":"12177",
    "addr:street":"Mohawk Dr Tribes",
    "iso:country":"US",
    "sg:address":"235 Mohawk Dr",
    "sg:city":"Tribes Hill",
    "sg:classifiers":[
        {
            "category":"Building & Trades",
            "subcategory":"Construction",
            "type":"Services"
        }
    ],
    "sg:phone":"+1 518 829 5010",
    "sg:postcode":"12177",
    "sg:province":"NY",
    "sg:tags":[
        "general",
        "contractor"
    ],
    "wof:name":"Zroc Construction Corp",
    "wof:placetype":"venue"
},
  "geometry": {"coordinates":[-74.279956,42.954897],"type":"Point"}
}