{
  "type": "Feature",
  "properties": {
    "addr:full":"6180 Grand Ave Maspeth NY 11378",
    "addr:housenumber":"6180",
    "addr:postcode":"11378",
    "addr:street":"Grand Ave",
    "iso:country":"US",
    "sg:address":"6180 Grand Ave",
    "sg:city":"Maspeth",
    "sg:classifiers":[
        {
            "category":"Autos & Motor Vehicles",
            "subcategory":"Fuel & Gas Station",
            "type":"Retail Goods"
        }
    ],
    "sg:phone":"+1 800 873 8782",
    "sg:postcode":"11378",
    "sg:province":"NY",
    "wof:name":"Bardon Mi-Vic Service Station",
    "wof:placetype":"venue"
},
  "geometry": {"coordinates":[-73.903503,40.722],"type":"Point"}
}