{
  "type": "Feature",
  "properties": {
    "iso:country":"US",
    "sg:address":"5463 State Hwy 12",
    "sg:city":"Norwich",
    "sg:classifiers":[
        {
            "category":"Shopping",
            "subcategory":"Department Store",
            "type":"Retail Goods"
        }
    ],
    "sg:phone":"+1 607 334 2204",
    "sg:postcode":"13815",
    "sg:province":"NY",
    "wof:name":"Sears Roebuck & Co",
    "wof:placetype":"venue"
},
  "geometry": {"coordinates":[-75.525547,42.551826],"type":"Point"}
}