{
  "type": "Feature",
  "properties": {
    "addr:full":"33-10 21st St Astoria NY 11106",
    "addr:housenumber":"33-10",
    "addr:postcode":"11106",
    "addr:street":"21St St",
    "iso:country":"US",
    "sg:address":"33-10 21st St",
    "sg:city":"Astoria",
    "sg:classifiers":[
        {
            "category":"Restaurant",
            "type":"Food & Drink"
        }
    ],
    "sg:phone":"+1 718 210 5557",
    "sg:postcode":"11106",
    "sg:province":"NY",
    "sg:tags":[
        "italian",
        "pizza"
    ],
    "wof:name":"Giorgio's Pizzeria",
    "wof:placetype":"venue"
},
  "geometry": {"coordinates":[-73.932446,40.764381],"type":"Point"}
}