{
  "type": "Feature",
  "properties": {
    "addr:full":"32 Rita Ave Monsey NY 10952",
    "addr:housenumber":"32",
    "addr:postcode":"10952",
    "addr:street":"Rita Ave",
    "iso:country":"US",
    "sg:address":"32 Rita Ave",
    "sg:city":"Monsey",
    "sg:classifiers":[
        {
            "category":"Building & Trades",
            "subcategory":"Equipment Rental",
            "type":"Services"
        }
    ],
    "sg:phone":"+1 845 425 2485",
    "sg:postcode":"10952",
    "sg:province":"NY",
    "sg:tags":[
        "renting",
        "leasing",
        "furniture"
    ],
    "wof:name":"Simcha Tables And Chairs Renting",
    "wof:placetype":"venue"
},
  "geometry": {"coordinates":[-74.06658899999999,41.12323],"type":"Point"}
}