{
  "type": "Feature",
  "properties": {
    "iso:country":"US",
    "sg:address":"5505 Old Goodrich Rd",
    "sg:city":"Clarence",
    "sg:classifiers":[
        {
            "category":"Retail",
            "subcategory":"Animal Services",
            "type":"Services"
        }
    ],
    "sg:phone":"+1 716 741 3688",
    "sg:postcode":"14031",
    "sg:province":"NY",
    "sg:tags":[
        "horse",
        "training"
    ],
    "wof:name":"Nancy Bechtel Training Stables",
    "wof:placetype":"venue"
},
  "geometry": {"coordinates":[-78.64208600000001,42.99446],"type":"Point"}
}