{
  "type": "Feature",
  "properties": {
    "addr:full":"447 Brighton Rd Tonawanda NY 14150",
    "addr:housenumber":"447",
    "addr:postcode":"14150",
    "addr:street":"Brighton Rd",
    "iso:country":"US",
    "sg:address":"447 Brighton Rd",
    "sg:city":"Tonawanda",
    "sg:classifiers":[
        {
            "category":"Personal",
            "subcategory":"Beauty Salon",
            "type":"Services"
        }
    ],
    "sg:phone":"+1   ",
    "sg:postcode":"14150",
    "sg:province":"NY",
    "sg:tags":[
        "shop"
    ],
    "wof:name":"Delook Hair Salon & Spa Inc",
    "wof:placetype":"venue"
},
  "geometry": {"coordinates":[-78.857105,42.991056],"type":"Point"}
}