{
  "type": "Feature",
  "properties": {
    "addr:full":"1 Brittany Ter Rock Tavern NY 12575",
    "addr:housenumber":"1",
    "addr:postcode":"12575",
    "addr:street":"Brittany Ter Rock",
    "iso:country":"US",
    "sg:address":"1 Brittany Ter",
    "sg:city":"Rock Tavern",
    "sg:classifiers":[
        {
            "category":"Utilities",
            "subcategory":"Cable",
            "type":"Services"
        }
    ],
    "sg:phone":"+1 845 496 6432",
    "sg:postcode":"12575",
    "sg:province":"NY",
    "sg:tags":[
        "television"
    ],
    "wof:name":"Mystic Star Systems LTD",
    "wof:placetype":"venue"
},
  "geometry": {"coordinates":[-74.13403099999999,41.461707],"type":"Point"}
}