{
  "type": "Feature",
  "properties": {
    "iso:country":"US",
    "sg:address":"30 S Broadway",
    "sg:city":"Yonkers",
    "sg:classifiers":[
        {
            "category":"Professional",
            "subcategory":"Lawyer & Legal Services",
            "type":"Services"
        }
    ],
    "sg:phone":"+1   ",
    "sg:postcode":"10701",
    "sg:province":"NY",
    "wof:name":"Leonard Buddington Jr",
    "wof:placetype":"venue"
},
  "geometry": {"coordinates":[-73.89882799999999,40.932661],"type":"Point"}
}