{
  "type": "Feature",
  "properties": {
    "iso:country":"US",
    "sg:address":"30 Glen St",
    "sg:city":"Glen Cove",
    "sg:classifiers":[
        {
            "category":"Professional",
            "type":"Services"
        }
    ],
    "sg:phone":"+1 516 676 5207",
    "sg:postcode":"11542",
    "sg:province":"NY",
    "sg:tags":[
        "establishment"
    ],
    "wof:name":"Takoya USA Inc",
    "wof:placetype":"venue"
},
  "geometry": {"coordinates":[-73.630199,40.863829],"type":"Point"}
}