{
  "type": "Feature",
  "properties": {
    "addr:full":"743 Astor Ave Bronx NY 10467",
    "addr:housenumber":"743",
    "addr:postcode":"10467",
    "addr:street":"Astor Ave",
    "iso:country":"US",
    "sg:address":"743 Astor Ave",
    "sg:city":"Bronx",
    "sg:classifiers":[
        {
            "category":"Manufacturing",
            "subcategory":"Food",
            "type":"Manufacturing & Wholesale Goods"
        }
    ],
    "sg:phone":"+1   ",
    "sg:postcode":"10467",
    "sg:province":"NY",
    "sg:tags":[
        "bakery"
    ],
    "wof:name":"A K & J Bakery Inc",
    "wof:placetype":"venue"
},
  "geometry": {"coordinates":[-73.86612100000001,40.859661],"type":"Point"}
}