{
  "type": "Feature",
  "properties": {
    "addr:full":"7800 Shore Front Pkwy Far Rockaway NY 11693",
    "addr:housenumber":"7800",
    "addr:postcode":"11693",
    "addr:street":"Shore Front Pkwy",
    "iso:country":"US",
    "sg:address":"7800 Shore Front Pkwy",
    "sg:city":"Far Rockaway",
    "sg:classifiers":[
        {
            "category":"Retail",
            "subcategory":"Laundry & Dry Cleaning",
            "type":"Services"
        }
    ],
    "sg:phone":"+1 718 318 3867",
    "sg:postcode":"11693",
    "sg:province":"NY",
    "sg:tags":[
        "linen",
        "rental"
    ],
    "wof:name":"Tri-State Textile Services",
    "wof:placetype":"venue"
},
  "geometry": {"coordinates":[-73.80605,40.586436],"type":"Point"}
}