{
  "type": "Feature",
  "properties": {
    "iso:country":"US",
    "sg:address":"1141 Fulton St",
    "sg:city":"Brooklyn",
    "sg:classifiers":[
        {
            "category":"Food & Beverages",
            "subcategory":"Groceries & Convenience Stores",
            "type":"Retail Goods"
        }
    ],
    "sg:phone":"+1 718 638 0030",
    "sg:postcode":"11238",
    "sg:province":"NY",
    "sg:tags":[
        "grocer"
    ],
    "wof:name":"Neighborhood Grocery Store",
    "wof:placetype":"venue"
},
  "geometry": {"coordinates":[-73.95666900000001,40.681487],"type":"Point"}
}