{
  "type": "Feature",
  "properties": {
    "iso:country":"US",
    "sg:address":"35 Stockbridge Rd",
    "sg:city":"Slingerlands",
    "sg:classifiers":[
        {
            "category":"Insurance",
            "subcategory":"Hazard Insurance",
            "type":"Services"
        }
    ],
    "sg:phone":"+1 518 439 6202",
    "sg:postcode":"12159",
    "sg:province":"NY",
    "sg:tags":[
        "commercial",
        "business"
    ],
    "wof:name":"Harleysville Insurance",
    "wof:placetype":"venue"
},
  "geometry": {"coordinates":[-73.869563,42.632563],"type":"Point"}
}