{
  "type": "Feature",
  "properties": {
    "iso:country":"US",
    "sg:address":"54 Audubon Ave",
    "sg:city":"Binghamton",
    "sg:classifiers":[
        {
            "category":"Professional",
            "subcategory":"Detective & Security Services",
            "type":"Services"
        }
    ],
    "sg:phone":"+1 607 772 6007",
    "sg:postcode":"13903",
    "sg:province":"NY",
    "sg:tags":[
        "car"
    ],
    "wof:name":"Absolute Security Service",
    "wof:placetype":"venue"
},
  "geometry": {"coordinates":[-75.940552,42.087575],"type":"Point"}
}