{
  "type": "Feature",
  "properties": {
    "iso:country":"US",
    "sg:address":"1050 Western Ave",
    "sg:city":"Albany",
    "sg:classifiers":[
        {
            "category":"Food & Beverages",
            "subcategory":"Groceries & Convenience Stores",
            "type":"Retail Goods"
        }
    ],
    "sg:phone":"+1   ",
    "sg:postcode":"12203",
    "sg:province":"NY",
    "wof:name":"Stewarts",
    "wof:placetype":"venue"
},
  "geometry": {"coordinates":[-73.81744999999999,42.674639],"type":"Point"}
}