{
  "type": "Feature",
  "properties": {
    "iso:country":"US",
    "sg:address":"230 Hudson Ave",
    "sg:city":"Rochester",
    "sg:classifiers":[
        {
            "category":"Retail",
            "subcategory":"Car Wash",
            "type":"Services"
        }
    ],
    "sg:phone":"+1 585 232 9691",
    "sg:postcode":"14605",
    "sg:province":"NY",
    "sg:tags":[
        "polishing",
        "washing"
    ],
    "wof:name":"Touch Of Class Car Wash",
    "wof:placetype":"venue"
},
  "geometry": {"coordinates":[-77.601893,43.167754],"type":"Point"}
}