{
  "type": "Feature",
  "properties": {
    "iso:country":"US",
    "sg:address":"18 Woodbine Rd",
    "sg:city":"Delmar",
    "sg:classifiers":[
        {
            "category":"Professional",
            "subcategory":"Management & Consulting",
            "type":"Services"
        }
    ],
    "sg:phone":"+1 518 439 4112",
    "sg:postcode":"12054",
    "sg:province":"NY",
    "sg:tags":[
        "consultant"
    ],
    "wof:name":"Athena Strategic Council",
    "wof:placetype":"venue"
},
  "geometry": {"coordinates":[-73.85147499999999,42.623757],"type":"Point"}
}