{
  "type": "Feature",
  "properties": {
    "addr:full":"252 W 37th St New York NY 10018",
    "addr:housenumber":"252",
    "addr:postcode":"10018",
    "addr:street":"W 37Th St",
    "iso:country":"US",
    "sg:address":"252 W 37th St",
    "sg:city":"New York",
    "sg:classifiers":[
        {
            "category":"Shopping",
            "subcategory":"Clothing, Apparel, & Fashions",
            "type":"Retail Goods"
        }
    ],
    "sg:phone":"+1 212 629 0770",
    "sg:postcode":"10018",
    "sg:province":"NY",
    "sg:tags":[
        "clothing",
        "women's"
    ],
    "wof:name":"Nuri Fashion",
    "wof:placetype":"venue"
},
  "geometry": {"coordinates":[-73.991435,40.753573],"type":"Point"}
}