{
  "type": "Feature",
  "properties": {
    "addr:full":"2013 Amsterdam Ave New York NY 10032",
    "addr:housenumber":"2013",
    "addr:postcode":"10032",
    "addr:street":"Amsterdam Ave",
    "iso:country":"US",
    "sg:address":"2013 Amsterdam Ave",
    "sg:city":"New York",
    "sg:classifiers":[
        {
            "category":"Education",
            "subcategory":"College",
            "type":"Public Place"
        }
    ],
    "sg:phone":"+1 212 568 1313",
    "sg:postcode":"10032",
    "sg:province":"NY",
    "sg:tags":[
        "academic",
        "school"
    ],
    "wof:name":"College Brokerage",
    "wof:placetype":"venue"
},
  "geometry": {"coordinates":[-73.940893,40.834166],"type":"Point"}
}