{
  "type": "Feature",
  "properties": {
    "iso:country":"US",
    "sg:address":"1937 E 17th St",
    "sg:city":"Brooklyn",
    "sg:classifiers":[
        {
            "category":"Building & Trades",
            "subcategory":"Construction",
            "type":"Services"
        }
    ],
    "sg:phone":"+1 718 339 4004",
    "sg:postcode":"11229",
    "sg:province":"NY",
    "sg:tags":[
        "general",
        "contractor"
    ],
    "wof:name":"Golden Gate Construction",
    "wof:placetype":"venue"
},
  "geometry": {"coordinates":[-73.954994,40.602184],"type":"Point"}
}