{
  "type": "Feature",
  "properties": {
    "iso:country":"US",
    "sg:address":"133 Beekman St",
    "sg:city":"New York",
    "sg:classifiers":[
        {
            "category":"Shopping",
            "subcategory":"Pharmacy",
            "type":"Retail Goods"
        }
    ],
    "sg:phone":"+1 212 227 9260",
    "sg:postcode":"10038",
    "sg:province":"NY",
    "sg:tags":[
        "drugstore"
    ],
    "wof:name":"Avanir Pharmaceuticals",
    "wof:placetype":"venue"
},
  "geometry": {"coordinates":[-74.122221,40.707467],"type":"Point"}
}