{
  "type": "Feature",
  "properties": {
    "iso:country":"US",
    "sg:address":"111 Haynes Ct",
    "sg:city":"Ronkonkoma",
    "sg:classifiers":[
        {
            "category":"Manufacturing",
            "subcategory":"Electronics",
            "type":"Manufacturing & Wholesale Goods"
        }
    ],
    "sg:phone":"+1 631 981 0900",
    "sg:postcode":"11779",
    "sg:province":"NY",
    "sg:tags":[
        "equipment",
        "electronic",
        "supply"
    ],
    "sg:website":"www.rodelco-usa.com",
    "wof:name":"Rodelco Electronics Corp",
    "wof:placetype":"venue"
},
  "geometry": {"coordinates":[-73.11282799999999,40.795831],"type":"Point"}
}