{
  "type": "Feature",
  "properties": {
    "addr:full":"120 Benchley Pl Bronx NY 10475",
    "addr:housenumber":"120",
    "addr:postcode":"10475",
    "addr:street":"Benchley Pl",
    "iso:country":"US",
    "sg:address":"120 Benchley Pl",
    "sg:city":"Bronx",
    "sg:classifiers":[
        {
            "category":"Health Services",
            "subcategory":"Doctor",
            "type":"Services"
        }
    ],
    "sg:phone":"+1 718 320 1000",
    "sg:postcode":"10475",
    "sg:province":"NY",
    "sg:tags":[
        "physician",
        "surgeon"
    ],
    "wof:name":"Charles Merker MD",
    "wof:placetype":"venue"
},
  "geometry": {"coordinates":[-73.826171,40.873802],"type":"Point"}
}