{
  "type": "Feature",
  "properties": {
    "iso:country":"US",
    "sg:address":"4100 Baldwin Rd",
    "sg:city":"Rushville",
    "sg:classifiers":[
        {
            "category":"Education",
            "subcategory":"School",
            "type":"Public Place"
        }
    ],
    "sg:phone":"+1 585 554 6441",
    "sg:postcode":"14544",
    "sg:province":"NY",
    "sg:website":"www.mwcsd.k12.ny.us",
    "wof:name":"Marcus Whitman Jr Sr High Schl",
    "wof:placetype":"venue"
},
  "geometry": {"coordinates":[-77.231126,42.777466],"type":"Point"}
}