{
  "type": "Feature",
  "properties": {
    "iso:country":"US",
    "sg:address":"167 Raintree Pkwy",
    "sg:city":"Tonawanda",
    "sg:classifiers":[
        {
            "category":"Professional",
            "subcategory":"Management & Consulting",
            "type":"Services"
        }
    ],
    "sg:phone":"+1   ",
    "sg:postcode":"14150",
    "sg:province":"NY",
    "wof:name":"Construction Consultants Group",
    "wof:placetype":"venue"
},
  "geometry": {"coordinates":[-78.84932000000001,43.014561],"type":"Point"}
}