{
  "type": "Feature",
  "properties": {
    "iso:country":"US",
    "sg:address":"11 Northview Dr",
    "sg:city":"Penn Yan",
    "sg:classifiers":[
        {
            "category":"Building & Trades",
            "subcategory":"Construction",
            "type":"Services"
        }
    ],
    "sg:phone":"+1 315 536 9948",
    "sg:postcode":"14527",
    "sg:province":"NY",
    "sg:tags":[
        "woodworking"
    ],
    "wof:name":"Wayne Haines Woodworking",
    "wof:placetype":"venue"
},
  "geometry": {"coordinates":[-77.068015,42.667072],"type":"Point"}
}