{
  "type": "Feature",
  "properties": {
    "addr:full":"5760 S Transit Rd Lockport NY 14094",
    "addr:housenumber":"5760",
    "addr:postcode":"14094",
    "addr:street":"S Transit Rd",
    "iso:country":"US",
    "sg:address":"5760 S Transit Rd",
    "sg:city":"Lockport",
    "sg:classifiers":[
        {
            "category":"Restaurant",
            "type":"Food & Drink"
        }
    ],
    "sg:menulink":"http://www.allmenus.com/ny/lockport/115984-quiznos-sub/menu/",
    "sg:phone":"+1 716 433 5588",
    "sg:postcode":"14094",
    "sg:province":"NY",
    "sg:tags":[
        "wrap",
        "american",
        "sandwich"
    ],
    "wof:name":"Quiznos Sub",
    "wof:placetype":"venue"
},
  "geometry": {"coordinates":[-78.69689700000001,43.146267],"type":"Point"}
}