{
  "type": "Feature",
  "properties": {
    "addr:full":"95 Avenue U Brooklyn NY 11223",
    "addr:housenumber":"95",
    "addr:postcode":"11223",
    "addr:street":"Avenue U",
    "iso:country":"US",
    "sg:address":"95 Avenue U",
    "sg:city":"Brooklyn",
    "sg:classifiers":[
        {
            "category":"Restaurant",
            "type":"Food & Drink"
        }
    ],
    "sg:phone":"+1 718 714 1008",
    "sg:postcode":"11223",
    "sg:province":"NY",
    "wof:name":"Croce's South Philly Cheesesteak & Panzarotti",
    "wof:placetype":"venue"
},
  "geometry": {"coordinates":[-73.98068600000001,40.596261],"type":"Point"}
}