{
  "type": "Feature",
  "properties": {
    "addr:full":"3794 103rd Street Corona NY 11368",
    "addr:housenumber":"3794",
    "addr:postcode":"11368",
    "addr:street":"103Rd Street",
    "iso:country":"US",
    "sg:address":"3794 103rd Street",
    "sg:city":"Corona",
    "sg:classifiers":[
        {
            "category":"Banks & Credit Unions",
            "subcategory":"Bank",
            "type":"Services"
        }
    ],
    "sg:phone":"+1 718 935 9935",
    "sg:postcode":"11368",
    "sg:province":"NY",
    "wof:name":"Chase Bank",
    "wof:placetype":"venue"
},
  "geometry": {"coordinates":[-73.863923,40.751985],"type":"Point"}
}