{
  "type": "Feature",
  "properties": {
    "addr:full":"320 E 65 St New York NY 10065",
    "addr:housenumber":"320;65",
    "addr:postcode":"10065",
    "addr:street":"E;St",
    "iso:country":"US",
    "sg:address":"320 E 65 St",
    "sg:city":"New York",
    "sg:classifiers":[
        {
            "category":"Health Services",
            "subcategory":"Doctor",
            "type":"Services"
        }
    ],
    "sg:phone":"+1 212 988 2634",
    "sg:postcode":"10065",
    "sg:province":"NY",
    "sg:tags":[
        "physician",
        "surgeon",
        "medical"
    ],
    "wof:name":"Ida M Tiongco PC",
    "wof:placetype":"venue"
},
  "geometry": {"coordinates":[-73.959642,40.763505],"type":"Point"}
}