{
  "type": "Feature",
  "properties": {
    "iso:country":"US",
    "sg:address":"919 West St",
    "sg:city":"Pelham",
    "sg:classifiers":[
        {
            "category":"Home & Garden",
            "subcategory":"Furniture",
            "type":"Retail Goods"
        }
    ],
    "sg:phone":"+1 914 235 6005",
    "sg:postcode":"10803",
    "sg:province":"NY",
    "wof:name":"Room To Room Corp",
    "wof:placetype":"venue"
},
  "geometry": {"coordinates":[-73.817875,40.890919],"type":"Point"}
}