{
  "type": "Feature",
  "properties": {
    "addr:full":"85-77 67th Road New York NY 11374",
    "addr:housenumber":"85-77",
    "addr:postcode":"11374",
    "addr:street":"67Th Road",
    "iso:country":"US",
    "sg:address":"85-77 67th Road",
    "sg:city":"New York",
    "sg:classifiers":[
        {
            "category":"Professional",
            "subcategory":"Art Services",
            "type":"Services"
        }
    ],
    "sg:phone":"+1 718 897 8028",
    "sg:postcode":"11374",
    "sg:province":"NY",
    "sg:tags":[
        "photographer"
    ],
    "sg:website":"www.henryleungphotography.com",
    "wof:name":"Henry Leung Photography",
    "wof:placetype":"venue"
},
  "geometry": {"coordinates":[-73.85945700000001,40.717339],"type":"Point"}
}