{
  "type": "Feature",
  "properties": {
    "addr:full":"410 Amsterdam Ave Manhattan NY 10024",
    "addr:housenumber":"410",
    "addr:postcode":"10024",
    "addr:street":"Amsterdam Ave",
    "iso:country":"US",
    "sg:address":"410 Amsterdam Ave",
    "sg:city":"Manhattan",
    "sg:classifiers":[
        {
            "category":"Bars & Pubs",
            "subcategory":"Wine Bar",
            "type":"Food & Drink"
        },
        {
            "category":"Wholesale",
            "subcategory":"Home Furnishings",
            "type":"Manufacturing & Wholesale Goods"
        }
    ],
    "sg:phone":"+1 212 873 6252",
    "sg:postcode":"10024",
    "sg:province":"NY",
    "sg:tags":[
        "plate",
        "tapas/small"
    ],
    "sg:website":"tolaninyc.com/",
    "wof:name":"Tolani Wine Restaurant",
    "wof:placetype":"venue"
},
  "geometry": {"coordinates":[-73.978221,40.783609],"type":"Point"}
}