{
  "type": "Feature",
  "properties": {
    "addr:full":"170 Acorn Dr Delanson NY 12053",
    "addr:housenumber":"170",
    "addr:postcode":"12053",
    "addr:street":"Acorn Dr",
    "iso:country":"US",
    "sg:address":"170 Acorn Dr",
    "sg:city":"Delanson",
    "sg:classifiers":[
        {
            "category":"Building & Trades",
            "subcategory":"Landscaping Services",
            "type":"Services"
        }
    ],
    "sg:phone":"+1 518 895 8275",
    "sg:postcode":"12053",
    "sg:province":"NY",
    "sg:tags":[
        "landscape"
    ],
    "wof:name":"Acorn Acres",
    "wof:placetype":"venue"
},
  "geometry": {"coordinates":[-74.17475,42.74309],"type":"Point"}
}