{
  "type": "Feature",
  "properties": {
    "addr:full":"1271 Ave of the Americas New York NY 10020",
    "addr:postcode":"10020",
    "addr:street":"1271 Ave Of The Americas",
    "iso:country":"US",
    "sg:address":"1271 Ave of the Americas",
    "sg:city":"New York",
    "sg:classifiers":[
        {
            "category":"Professional",
            "subcategory":"Management & Consulting",
            "type":"Services"
        }
    ],
    "sg:phone":"+1   ",
    "sg:postcode":"10020",
    "sg:province":"NY",
    "sg:tags":[
        "book"
    ],
    "wof:name":"Time Warner",
    "wof:placetype":"venue"
},
  "geometry": {"coordinates":[-73.980267,40.760144],"type":"Point"}
}