{
  "type": "Feature",
  "properties": {
    "addr:full":"2275 Pine Neck Rd Southold NY 11971",
    "addr:housenumber":"2275",
    "addr:postcode":"11971",
    "addr:street":"Pine Neck Rd",
    "iso:country":"US",
    "sg:address":"2275 Pine Neck Rd",
    "sg:city":"Southold",
    "sg:classifiers":[
        {
            "category":"Building & Trades",
            "subcategory":"Landscaping Services",
            "type":"Services"
        }
    ],
    "sg:phone":"+1 631 765 6098",
    "sg:postcode":"11971",
    "sg:province":"NY",
    "sg:tags":[
        "landscape"
    ],
    "wof:name":"Inviting Environments",
    "wof:placetype":"venue"
},
  "geometry": {"coordinates":[-72.42891,41.053469],"type":"Point"}
}