{
  "type": "Feature",
  "properties": {
    "addr:full":"7 Main St Walden NY 12586",
    "addr:housenumber":"7",
    "addr:postcode":"12586",
    "addr:street":"Main St",
    "iso:country":"US",
    "sg:address":"7 Main St",
    "sg:city":"Walden",
    "sg:classifiers":[
        {
            "category":"Personal",
            "subcategory":"Beauty Salon",
            "type":"Services"
        }
    ],
    "sg:phone":"+1 845 778 4226",
    "sg:postcode":"12586",
    "sg:province":"NY",
    "wof:name":"Clippers Hair Salon",
    "wof:placetype":"venue"
},
  "geometry": {"coordinates":[-74.18779499999999,41.560715],"type":"Point"}
}