{
  "type": "Feature",
  "properties": {
    "iso:country":"US",
    "sg:address":"349 Siebert Rd",
    "sg:city":"Medusa",
    "sg:classifiers":[
        {
            "category":"Retail",
            "subcategory":"Auto Repair",
            "type":"Services"
        }
    ],
    "sg:phone":"+1   ",
    "sg:postcode":"12120",
    "sg:province":"NY",
    "sg:tags":[
        "general"
    ],
    "wof:name":"Dns Automative Inc",
    "wof:placetype":"venue"
},
  "geometry": {"coordinates":[-74.146957,42.422291],"type":"Point"}
}