{
  "type": "Feature",
  "properties": {
    "iso:country":"US",
    "sg:address":"245 E 40th St",
    "sg:city":"New York",
    "sg:classifiers":[
        {
            "category":"Professional",
            "subcategory":"Advertising",
            "type":"Services"
        }
    ],
    "sg:phone":"+1 212 697 3292",
    "sg:postcode":"10016",
    "sg:province":"NY",
    "sg:tags":[
        "agency"
    ],
    "wof:name":"SAI Advertising",
    "wof:placetype":"venue"
},
  "geometry": {"coordinates":[-73.973209,40.748661],"type":"Point"}
}