{
  "type": "Feature",
  "properties": {
    "iso:country":"US",
    "sg:address":"708 Walt Whitman Rd",
    "sg:city":"Melville",
    "sg:classifiers":[
        {
            "category":"Insurance",
            "subcategory":"Insurance Agent",
            "type":"Services"
        }
    ],
    "sg:phone":"+1 631 421 1450",
    "sg:postcode":"11747",
    "sg:province":"NY",
    "wof:name":"Bloodhound Investigations",
    "wof:placetype":"venue"
},
  "geometry": {"coordinates":[-73.41113300000001,40.804153],"type":"Point"}
}