{
  "type": "Feature",
  "properties": {
    "iso:country":"US",
    "sg:address":"939 N Broadway",
    "sg:city":"Massapequa",
    "sg:classifiers":[
        {
            "category":"Shopping",
            "subcategory":"Gifts & Souvenirs",
            "type":"Retail Goods"
        }
    ],
    "sg:phone":"+1 516 797 9898",
    "sg:postcode":"11758",
    "sg:province":"NY",
    "sg:tags":[
        "shop"
    ],
    "wof:name":"Heart To Heart Gift Shop Inc",
    "wof:placetype":"venue"
},
  "geometry": {"coordinates":[-73.462112,40.702659],"type":"Point"}
}