{
  "type": "Feature",
  "properties": {
    "iso:country":"US",
    "sg:address":"20 Railroad Ave",
    "sg:city":"Babylon",
    "sg:classifiers":[
        {
            "category":"Fast Food",
            "type":"Food & Drink"
        },
        {
            "category":"Deli",
            "type":"Food & Drink"
        },
        {
            "category":"Restaurant",
            "type":"Food & Drink"
        }
    ],
    "sg:phone":"+1 631 321 6515",
    "sg:postcode":"11702",
    "sg:province":"NY",
    "sg:tags":[
        "greek",
        "delicatessen",
        "mediterranean",
        "american",
        "take"
    ],
    "wof:name":"Babylon Gyro",
    "wof:placetype":"venue"
},
  "geometry": {"coordinates":[-73.32336599999999,40.700062],"type":"Point"}
}