{
  "type": "Feature",
  "properties": {
    "addr:full":"13850 Jamaica Ave Jamaica NY 11435",
    "addr:housenumber":"13850",
    "addr:postcode":"11435",
    "addr:street":"Jamaica Ave",
    "iso:country":"US",
    "sg:address":"13850 Jamaica Ave",
    "sg:city":"Jamaica",
    "sg:classifiers":[
        {
            "category":"Restaurant",
            "type":"Food & Drink"
        },
        {
            "category":"Ice Cream",
            "type":"Food & Drink"
        }
    ],
    "sg:phone":"+1 718 291 3107",
    "sg:postcode":"11435",
    "sg:province":"NY",
    "sg:tags":[
        "frozen",
        "dessert"
    ],
    "sg:website":"http://www.baskinrobbins.com",
    "wof:name":"Baskin Robbins",
    "wof:placetype":"venue"
},
  "geometry": {"coordinates":[-73.807945,40.701759],"type":"Point"}
}