{
  "type": "Feature",
  "properties": {
    "iso:country":"US",
    "sg:address":"1835 Merrick Rd",
    "sg:city":"Merrick",
    "sg:classifiers":[
        {
            "category":"Real Estate",
            "subcategory":"Real Estate Agent",
            "type":"Services"
        }
    ],
    "sg:phone":"+1 516 546 2000",
    "sg:postcode":"11566",
    "sg:province":"NY",
    "wof:name":"Prudential Long Island Realty",
    "wof:placetype":"venue"
},
  "geometry": {"coordinates":[-73.55367699999999,40.654207],"type":"Point"}
}