{
  "type": "Feature",
  "properties": {
    "addr:full":"1887 Amsterdam Ave New York NY 10032",
    "addr:housenumber":"1887",
    "addr:postcode":"10032",
    "addr:street":"Amsterdam Ave",
    "iso:country":"US",
    "sg:address":"1887 Amsterdam Ave",
    "sg:city":"New York",
    "sg:classifiers":[
        {
            "category":"Education",
            "subcategory":"School",
            "type":"Public Place"
        }
    ],
    "sg:phone":"+1 888 698 3220",
    "sg:postcode":"10032",
    "sg:province":"NY",
    "wof:name":"New York Training & Employment Center",
    "wof:placetype":"venue"
},
  "geometry": {"coordinates":[-73.94362,40.830399],"type":"Point"}
}