{
  "type": "Feature",
  "properties": {
    "iso:country":"US",
    "sg:address":"148 N 10th St",
    "sg:city":"Brooklyn",
    "sg:classifiers":[
        {
            "category":"Wholesale",
            "subcategory":"Groceries",
            "type":"Manufacturing & Wholesale Goods"
        }
    ],
    "sg:phone":"+1 718 384 3838",
    "sg:postcode":"11211",
    "sg:province":"NY",
    "sg:tags":[
        "general"
    ],
    "wof:name":"Synlyco Ltd",
    "wof:placetype":"venue"
},
  "geometry": {"coordinates":[-73.956638,40.719968],"type":"Point"}
}