{
  "type": "Feature",
  "properties": {
    "addr:full":"345 Warner Ave Syracuse NY 13205",
    "addr:housenumber":"345",
    "addr:postcode":"13205",
    "addr:street":"Warner Ave",
    "iso:country":"US",
    "sg:address":"345 Warner Ave",
    "sg:city":"Syracuse",
    "sg:classifiers":[
        {
            "category":"Organizations",
            "subcategory":"Religious Organization",
            "type":"Services"
        }
    ],
    "sg:phone":"+1 315 478 3513",
    "sg:postcode":"13205",
    "sg:province":"NY",
    "sg:tags":[
        "clergy"
    ],
    "wof:name":"Samuel Wagner",
    "wof:placetype":"venue"
},
  "geometry": {"coordinates":[-76.14859199999999,43.021991],"type":"Point"}
}