{
  "type": "Feature",
  "properties": {
    "addr:full":"31 2nd Pl Brooklyn NY 11231",
    "addr:housenumber":"31",
    "addr:postcode":"11231",
    "addr:street":"2Nd Pl",
    "iso:country":"US",
    "sg:address":"31 2nd Pl",
    "sg:city":"Brooklyn",
    "sg:classifiers":[
        {
            "category":"Building & Trades",
            "subcategory":"Plumbing",
            "type":"Services"
        }
    ],
    "sg:phone":"+1 718 852 7875",
    "sg:postcode":"11231",
    "sg:province":"NY",
    "wof:name":"A M J Plumbing And Contracting",
    "wof:placetype":"venue"
},
  "geometry": {"coordinates":[-73.999786,40.680344],"type":"Point"}
}