{
  "type": "Feature",
  "properties": {
    "iso:country":"US",
    "sg:address":"658 Fulton Ave",
    "sg:city":"Hempstead",
    "sg:classifiers":[
        {
            "category":"Restaurant",
            "type":"Food & Drink"
        }
    ],
    "sg:phone":"+1 516 485 3651",
    "sg:postcode":"11550",
    "sg:province":"NY",
    "wof:name":"Roadrunner",
    "wof:placetype":"venue"
},
  "geometry": {"coordinates":[-73.617897,40.709499],"type":"Point"}
}