{
  "type": "Feature",
  "properties": {
    "addr:full":"265 Malta St Brooklyn NY 11207",
    "addr:housenumber":"265",
    "addr:postcode":"11207",
    "addr:street":"Malta St",
    "iso:country":"US",
    "sg:address":"265 Malta St",
    "sg:city":"Brooklyn",
    "sg:classifiers":[
        {
            "category":"Wholesale",
            "subcategory":"Dairy",
            "type":"Manufacturing & Wholesale Goods"
        }
    ],
    "sg:phone":"+1 718 272 4500",
    "sg:postcode":"11207",
    "sg:province":"NY",
    "sg:tags":[
        "product",
        "milk"
    ],
    "wof:name":"Beyer Farms Inc",
    "wof:placetype":"venue"
},
  "geometry": {"coordinates":[-73.892145,40.655181],"type":"Point"}
}