{
  "type": "Feature",
  "properties": {
    "iso:country":"US",
    "sg:address":"602 Greenwich St",
    "sg:city":"Hempstead",
    "sg:classifiers":[
        {
            "category":"Shopping",
            "type":"Retail Goods"
        }
    ],
    "sg:phone":"+1   ",
    "sg:postcode":"11550",
    "sg:province":"NY",
    "sg:tags":[
        "merchandise"
    ],
    "wof:name":"S & S Memorials Inc",
    "wof:placetype":"venue"
},
  "geometry": {"coordinates":[-73.606251,40.695304],"type":"Point"}
}