{
  "type": "Feature",
  "properties": {
    "addr:full":"8 Eric Ct Sayville NY 11782",
    "addr:housenumber":"8",
    "addr:postcode":"11782",
    "addr:street":"Eric Ct",
    "iso:country":"US",
    "sg:address":"8 Eric Ct",
    "sg:city":"Sayville",
    "sg:classifiers":[
        {
            "category":"Building & Trades",
            "subcategory":"Landscaping Services",
            "type":"Services"
        }
    ],
    "sg:phone":"+1 631 567 3993",
    "sg:postcode":"11782",
    "sg:province":"NY",
    "sg:tags":[
        "landscape",
        "contractor"
    ],
    "wof:name":"Radigan's Landscaping",
    "wof:placetype":"venue"
},
  "geometry": {"coordinates":[-73.08374000000001,40.723522],"type":"Point"}
}