{
  "type": "Feature",
  "properties": {
    "addr:full":"371 Locust Ave Oakdale NY 11769",
    "addr:housenumber":"371",
    "addr:postcode":"11769",
    "addr:street":"Locust Ave",
    "iso:country":"US",
    "sg:address":"371 Locust Ave",
    "sg:city":"Oakdale",
    "sg:classifiers":[
        {
            "category":"Education",
            "subcategory":"School",
            "type":"Public Place"
        },
        {
            "category":"Education",
            "subcategory":"Special Training",
            "type":"Public Place"
        }
    ],
    "sg:phone":"+1 631 244 5950",
    "sg:postcode":"11769",
    "sg:province":"NY",
    "sg:tags":[
        "care",
        "center",
        "day",
        "child"
    ],
    "wof:name":"Islip Learning Center",
    "wof:placetype":"venue"
},
  "geometry": {"coordinates":[-73.11190499999999,40.745209],"type":"Point"}
}