{
  "type": "Feature",
  "properties": {
    "iso:country":"US",
    "sg:address":"2 Olcott Pl",
    "sg:city":"Buffalo",
    "sg:classifiers":[
        {
            "category":"Building & Trades",
            "subcategory":"Plumbing",
            "type":"Services"
        }
    ],
    "sg:phone":"+1 716 892 3822",
    "sg:postcode":"14225",
    "sg:province":"NY",
    "sg:tags":[
        "product",
        "management",
        "energy",
        "system"
    ],
    "wof:name":"Welch's Energy",
    "wof:placetype":"venue"
},
  "geometry": {"coordinates":[-78.796666,42.918595],"type":"Point"}
}