{
  "type": "Feature",
  "properties": {
    "iso:country":"US",
    "sg:address":"31 Tarrytown Rd",
    "sg:city":"White Plains",
    "sg:classifiers":[
        {
            "category":"Restaurant",
            "type":"Food & Drink"
        }
    ],
    "sg:phone":"+1   ",
    "sg:postcode":"10607",
    "sg:province":"NY",
    "sg:tags":[
        "eating"
    ],
    "wof:name":"Regent Luncheonette The",
    "wof:placetype":"venue"
},
  "geometry": {"coordinates":[-73.780799,41.037213],"type":"Point"}
}