{
  "type": "Feature",
  "properties": {
    "addr:full":"2501 Webster Ave Bronx NY 10458",
    "addr:housenumber":"2501",
    "addr:postcode":"10458",
    "addr:street":"Webster Ave",
    "iso:country":"US",
    "sg:address":"2501 Webster Ave",
    "sg:city":"Bronx",
    "sg:classifiers":[
        {
            "category":"Manufacturing",
            "subcategory":"Textiles",
            "type":"Manufacturing & Wholesale Goods"
        },
        {
            "category":"Shopping",
            "subcategory":"Crafts & Fabrics",
            "type":"Retail Goods"
        }
    ],
    "sg:phone":"+1 347 270 0757",
    "sg:postcode":"10458",
    "sg:province":"NY",
    "sg:tags":[
        "shop"
    ],
    "wof:name":"Textile Creations",
    "wof:placetype":"venue"
},
  "geometry": {"coordinates":[-73.892014,40.861066],"type":"Point"}
}