{
  "type": "Feature",
  "properties": {
    "addr:full":"3243 W Lake Rd Wilson NY 14172",
    "addr:housenumber":"3243",
    "addr:postcode":"14172",
    "addr:street":"W Lake Rd",
    "iso:country":"US",
    "sg:address":"3243 W Lake Rd",
    "sg:city":"Wilson",
    "sg:classifiers":[
        {
            "category":"Food & Beverages",
            "subcategory":"Liquor & Beverages",
            "type":"Retail Goods"
        }
    ],
    "sg:phone":"+1   ",
    "sg:postcode":"14172",
    "sg:province":"NY",
    "sg:tags":[
        "alcoholic"
    ],
    "wof:name":"EDS",
    "wof:placetype":"venue"
},
  "geometry": {"coordinates":[-78.86124599999999,43.307051],"type":"Point"}
}