{
  "type": "Feature",
  "properties": {
    "iso:country":"US",
    "sg:address":"1023 Caton Ave",
    "sg:city":"Elmira",
    "sg:classifiers":[
        {
            "category":"Manufacturing",
            "subcategory":"Metals",
            "type":"Manufacturing & Wholesale Goods"
        }
    ],
    "sg:phone":"+1   ",
    "sg:postcode":"14904",
    "sg:province":"NY",
    "sg:tags":[
        "industrial",
        "mfg",
        "re",
        "machinery",
        "stampings",
        "welding"
    ],
    "wof:name":"Mega Tool & Manufacturing",
    "wof:placetype":"venue"
},
  "geometry": {"coordinates":[-76.807864,42.061385],"type":"Point"}
}