{
  "type": "Feature",
  "properties": {
    "addr:full":"54 N Main St Holley NY 14470",
    "addr:housenumber":"54",
    "addr:postcode":"14470",
    "addr:street":"N Main St",
    "iso:country":"US",
    "sg:address":"54 N Main St",
    "sg:city":"Holley",
    "sg:classifiers":[
        {
            "category":"Organizations",
            "subcategory":"Religious Organization",
            "type":"Services"
        }
    ],
    "sg:phone":"+1 585 638 6602",
    "sg:postcode":"14470",
    "sg:province":"NY",
    "sg:tags":[
        "church"
    ],
    "wof:name":"New Covenant Worship Ctr",
    "wof:placetype":"venue"
},
  "geometry": {"coordinates":[-78.02655,43.229469],"type":"Point"}
}