{
  "type": "Feature",
  "properties": {
    "addr:full":"106 Scottsdale Cir Liverpool NY 13088",
    "addr:housenumber":"106",
    "addr:postcode":"13088",
    "addr:street":"Scottsdale Cir",
    "iso:country":"US",
    "sg:address":"106 Scottsdale Cir",
    "sg:city":"Liverpool",
    "sg:classifiers":[
        {
            "category":"Organizations",
            "subcategory":"Professional Association",
            "type":"Services"
        },
        {
            "category":"Education",
            "subcategory":"Special Training",
            "type":"Public Place"
        },
        {
            "category":"Professional",
            "subcategory":"Employment Agencies",
            "type":"Services"
        },
        {
            "category":"Professional",
            "subcategory":"Business Services",
            "type":"Services"
        },
        {
            "category":"Personal",
            "subcategory":"Adult",
            "type":"Services"
        }
    ],
    "sg:phone":"+1 315 382 5783",
    "sg:postcode":"13088",
    "sg:province":"NY",
    "sg:tags":[
        "coach",
        "resume",
        "career",
        "consultant",
        "coaching-business",
        "vocational",
        "counseling"
    ],
    "wof:name":"Rock Solid Resumes",
    "wof:placetype":"venue"
},
  "geometry": {"coordinates":[-76.177071,43.112271],"type":"Point"}
}