{
  "type": "Feature",
  "properties": {
    "addr:full":"965 Lexington Ave New York NY 10021",
    "addr:housenumber":"965",
    "addr:postcode":"10021",
    "addr:street":"Lexington Ave",
    "iso:country":"US",
    "sg:address":"965 Lexington Ave",
    "sg:city":"New York",
    "sg:classifiers":[
        {
            "category":"Restaurant",
            "type":"Food & Drink"
        }
    ],
    "sg:menulink":"http://www.allmenus.com/ny/new-york/7802-mariella-pizza/menu/",
    "sg:phone":"+1 212 249 0796",
    "sg:postcode":"10021",
    "sg:province":"NY",
    "sg:tags":[
        "american",
        "pizza"
    ],
    "wof:name":"Mariella Pizza",
    "wof:placetype":"venue"
},
  "geometry": {"coordinates":[-73.962816,40.769158],"type":"Point"}
}