{
  "type": "Feature",
  "properties": {
    "addr:full":"5 Jamar Dr Fayetteville NY 13066",
    "addr:housenumber":"5",
    "addr:postcode":"13066",
    "addr:street":"Jamar Dr",
    "iso:country":"US",
    "sg:address":"5 Jamar Dr",
    "sg:city":"Fayetteville",
    "sg:classifiers":[
        {
            "category":"Shopping",
            "subcategory":"Musical Instruments",
            "type":"Retail Goods"
        }
    ],
    "sg:phone":"+1 315 446 0365",
    "sg:postcode":"13066",
    "sg:province":"NY",
    "sg:tags":[
        "music",
        "dealer"
    ],
    "wof:name":"Cornucopia Music",
    "wof:placetype":"venue"
},
  "geometry": {"coordinates":[-76.05645,43.02794],"type":"Point"}
}