{
  "type": "Feature",
  "properties": {
    "iso:country":"US",
    "sg:address":"10 Wicker St",
    "sg:city":"Ticonderoga",
    "sg:classifiers":[
        {
            "category":"Wholesale",
            "subcategory":"Scrap",
            "type":"Manufacturing & Wholesale Goods"
        }
    ],
    "sg:phone":"+1 518 585 9273",
    "sg:postcode":"12883",
    "sg:province":"NY",
    "sg:tags":[
        "recycling",
        "center"
    ],
    "wof:name":"Tomra Of Ny",
    "wof:placetype":"venue"
},
  "geometry": {"coordinates":[-73.436032,43.850449],"type":"Point"}
}