{
  "type": "Feature",
  "properties": {
    "iso:country":"US",
    "sg:address":"South St",
    "sg:city":"New York",
    "sg:classifiers":[
        {
            "category":"Shopping",
            "subcategory":"Optician",
            "type":"Retail Goods"
        }
    ],
    "sg:phone":"+1 212 566 4507",
    "sg:postcode":"10038",
    "sg:province":"NY",
    "sg:tags":[
        "eyewear"
    ],
    "wof:name":"Sunglass Hut International",
    "wof:placetype":"venue"
},
  "geometry": {"coordinates":[-74.003998,40.705799],"type":"Point"}
}