{
  "type": "Feature",
  "properties": {
    "addr:full":"81 Harrison Ave Brooklyn NY 11206",
    "addr:housenumber":"81",
    "addr:postcode":"11206",
    "addr:street":"Harrison Ave",
    "iso:country":"US",
    "sg:address":"81 Harrison Ave",
    "sg:city":"Brooklyn",
    "sg:classifiers":[
        {
            "category":"Shopping",
            "type":"Retail Goods"
        }
    ],
    "sg:phone":"+1   ",
    "sg:postcode":"11206",
    "sg:province":"NY",
    "sg:tags":[
        "merchandise"
    ],
    "wof:name":"Schwartz Fish Store",
    "wof:placetype":"venue"
},
  "geometry": {"coordinates":[-73.95126,40.703957],"type":"Point"}
}