{
  "type": "Feature",
  "properties": {
    "addr:full":"7561 31st Ave East Elmhurst NY 11370",
    "addr:housenumber":"7561",
    "addr:postcode":"11370",
    "addr:street":"31St Ave",
    "iso:country":"US",
    "sg:address":"7561 31st Ave",
    "sg:city":"East Elmhurst",
    "sg:classifiers":[
        {
            "category":"Restaurant",
            "type":"Food & Drink"
        }
    ],
    "sg:phone":"+1 718 505 0515",
    "sg:postcode":"11370",
    "sg:province":"NY",
    "wof:name":"Plaka",
    "wof:placetype":"venue"
},
  "geometry": {"coordinates":[-73.891971,40.758602],"type":"Point"}
}