{
  "type": "Feature",
  "properties": {
    "iso:country":"US",
    "sg:address":"1911 Richmond Ave",
    "sg:city":"Staten Island",
    "sg:classifiers":[
        {
            "category":"Banks & Credit Unions",
            "subcategory":"Investment Brokerage",
            "type":"Services"
        }
    ],
    "sg:phone":"+1 718 761 9414",
    "sg:postcode":"10314",
    "sg:province":"NY",
    "sg:tags":[
        "stock",
        "bond"
    ],
    "wof:name":"DTC Capital",
    "wof:placetype":"venue"
},
  "geometry": {"coordinates":[-74.163287,40.601681],"type":"Point"}
}