{
  "type": "Feature",
  "properties": {
    "addr:full":"2331 Broadway Schenectady NY 12306",
    "addr:housenumber":"2331",
    "addr:postcode":"12306",
    "addr:street":"Broadway",
    "iso:country":"US",
    "sg:address":"2331 Broadway",
    "sg:city":"Schenectady",
    "sg:classifiers":[
        {
            "category":"Health Services",
            "subcategory":"Chiropractor",
            "type":"Services"
        }
    ],
    "sg:phone":"+1   ",
    "sg:postcode":"12306",
    "sg:province":"NY",
    "wof:name":"Thomas C Hackett Dr",
    "wof:placetype":"venue"
},
  "geometry": {"coordinates":[-73.970313,42.795888],"type":"Point"}
}