{
  "type": "Feature",
  "properties": {
    "addr:full":"118 E 25th 3rd Fl New York NY 10010",
    "addr:housenumber":"118;3rd fl",
    "addr:postcode":"10010",
    "addr:street":"E 25Th",
    "iso:country":"US",
    "sg:address":"118 E 25th 3rd Fl",
    "sg:city":"New York",
    "sg:classifiers":[
        {
            "category":"Building & Trades",
            "subcategory":"Construction",
            "type":"Services"
        },
        {
            "category":"Real Estate",
            "subcategory":"Architect",
            "type":"Services"
        }
    ],
    "sg:phone":"+1 310 890 8882",
    "sg:postcode":"10010",
    "sg:province":"NY",
    "sg:tags":[
        "interior",
        "design"
    ],
    "sg:website":"www.bermdesign.com",
    "wof:name":"Berm Design",
    "wof:placetype":"venue"
},
  "geometry": {"coordinates":[-73.98458100000001,40.740865],"type":"Point"}
}