{
  "type": "Feature",
  "properties": {
    "addr:full":"381 W End Ave New York NY 10024",
    "addr:housenumber":"381",
    "addr:postcode":"10024",
    "addr:street":"W End Ave",
    "iso:country":"US",
    "sg:address":"381 W End Ave",
    "sg:city":"New York",
    "sg:classifiers":[
        {
            "category":"Health Services",
            "subcategory":"Doctor",
            "type":"Services"
        }
    ],
    "sg:phone":"+1 212 724 7935",
    "sg:postcode":"10024",
    "sg:province":"NY",
    "sg:tags":[
        "physician",
        "surgeon"
    ],
    "wof:name":"Lila Greenwald MD",
    "wof:placetype":"venue"
},
  "geometry": {"coordinates":[-73.98116400000001,40.784354],"type":"Point"}
}