{
  "type": "Feature",
  "properties": {
    "iso:country":"US",
    "sg:address":"46 Wolfle St",
    "sg:city":"Glen Cove",
    "sg:classifiers":[
        {
            "category":"Health Services",
            "subcategory":"Doctor",
            "type":"Services"
        }
    ],
    "sg:phone":"+1   ",
    "sg:postcode":"11542",
    "sg:province":"NY",
    "wof:name":"Mark E Arbetman DDS PC",
    "wof:placetype":"venue"
},
  "geometry": {"coordinates":[-73.615602,40.855024],"type":"Point"}
}