{
  "type": "Feature",
  "properties": {
    "addr:full":"30 Kearney Dr Rochester NY 14617",
    "addr:housenumber":"30",
    "addr:postcode":"14617",
    "addr:street":"Kearney Dr",
    "iso:country":"US",
    "sg:address":"30 Kearney Dr",
    "sg:city":"Rochester",
    "sg:classifiers":[
        {
            "category":"Organizations",
            "subcategory":"Professional Association",
            "type":"Services"
        }
    ],
    "sg:phone":"+1   ",
    "sg:postcode":"14617",
    "sg:province":"NY",
    "wof:name":"Driver & Safety Educators",
    "wof:placetype":"venue"
},
  "geometry": {"coordinates":[-77.579412,43.20667],"type":"Point"}
}