{
  "type": "Feature",
  "properties": {
    "addr:full":"182 Ave B New York NY 10009",
    "addr:housenumber":"182",
    "addr:postcode":"10009",
    "addr:street":"Ave B",
    "iso:country":"US",
    "sg:address":"182 Ave B",
    "sg:city":"New York",
    "sg:classifiers":[
        {
            "category":"Coffee & Tea",
            "type":"Food & Drink"
        },
        {
            "category":"Bakery",
            "type":"Food & Drink"
        }
    ],
    "sg:phone":"+1 212 677 4460",
    "sg:postcode":"10009",
    "sg:province":"NY",
    "wof:name":"The Little Bird Cafe",
    "wof:placetype":"venue"
},
  "geometry": {"coordinates":[-73.979366,40.727784],"type":"Point"}
}