{
  "type": "Feature",
  "properties": {
    "addr:full":"5 Adler Dr East Syracuse NY 13057",
    "addr:housenumber":"5",
    "addr:postcode":"13057",
    "addr:street":"Adler Dr",
    "iso:country":"US",
    "sg:address":"5 Adler Dr",
    "sg:city":"East Syracuse",
    "sg:classifiers":[
        {
            "category":"Wholesale",
            "subcategory":"Electrical",
            "type":"Manufacturing & Wholesale Goods"
        }
    ],
    "sg:phone":"+1 315 437 8309",
    "sg:postcode":"13057",
    "sg:province":"NY",
    "sg:tags":[
        "control"
    ],
    "wof:name":"Great Lakes Controls Corp",
    "wof:placetype":"venue"
},
  "geometry": {"coordinates":[-76.07941099999999,43.094974],"type":"Point"}
}