{
  "type": "Feature",
  "properties": {
    "iso:country":"US",
    "sg:address":"330 Madison Ave",
    "sg:city":"New York",
    "sg:classifiers":[
        {
            "category":"Professional",
            "subcategory":"Management & Consulting",
            "type":"Services"
        }
    ],
    "sg:phone":"+1 212 370 9460",
    "sg:postcode":"10017",
    "sg:province":"NY",
    "wof:name":"ARC Partners Inc",
    "wof:placetype":"venue"
},
  "geometry": {"coordinates":[-73.979287,40.752801],"type":"Point"}
}