{
  "type": "Feature",
  "properties": {
    "iso:country":"US",
    "sg:address":"102 Old S Plank Rd",
    "sg:city":"Newburgh",
    "sg:classifiers":[
        {
            "category":"Wholesale",
            "subcategory":"Books, Periodicals, & Newspapers",
            "type":"Manufacturing & Wholesale Goods"
        }
    ],
    "sg:phone":"+1 845 561 6360",
    "sg:postcode":"12550",
    "sg:province":"NY",
    "sg:tags":[
        "distributor"
    ],
    "sg:website":"www.pcfcorp.com",
    "wof:name":"Publishers Circulation",
    "wof:placetype":"venue"
},
  "geometry": {"coordinates":[-74.065742,41.524371],"type":"Point"}
}