{
  "type": "Feature",
  "properties": {
    "addr:full":"371 W Church St Elmira NY 14901",
    "addr:housenumber":"371",
    "addr:postcode":"14901",
    "addr:street":"W Church St",
    "iso:country":"US",
    "sg:address":"371 W Church St",
    "sg:city":"Elmira",
    "sg:classifiers":[
        {
            "category":"Health Services",
            "subcategory":"Health Practitioner",
            "type":"Services"
        }
    ],
    "sg:phone":"+1 607 732 5427",
    "sg:postcode":"14901",
    "sg:province":"NY",
    "sg:tags":[
        "psychologist"
    ],
    "wof:name":"JRD Psychological Svc",
    "wof:placetype":"venue"
},
  "geometry": {"coordinates":[-76.813436,42.088315],"type":"Point"}
}