{
  "type": "Feature",
  "properties": {
    "iso:country":"US",
    "sg:address":"11 N Division St",
    "sg:city":"Peekskill",
    "sg:classifiers":[
        {
            "category":"Restaurant",
            "type":"Food & Drink"
        }
    ],
    "sg:phone":"+1 914 930 7347",
    "sg:postcode":"10566",
    "sg:province":"NY",
    "wof:name":"Tnh Restaurant",
    "wof:placetype":"venue"
},
  "geometry": {"coordinates":[-73.92022299999999,41.290673],"type":"Point"}
}