{
  "type": "Feature",
  "properties": {
    "iso:country":"US",
    "sg:address":"136 Troy Rd",
    "sg:city":"Ithaca",
    "sg:classifiers":[
        {
            "category":"Professional",
            "type":"Services"
        }
    ],
    "sg:phone":"+1 607 277 4965",
    "sg:postcode":"14850",
    "sg:province":"NY",
    "sg:tags":[
        "establishment"
    ],
    "wof:name":"Iacovelli & Iacovelli",
    "wof:placetype":"venue"
},
  "geometry": {"coordinates":[-76.478053,42.40975],"type":"Point"}
}