{
  "type": "Feature",
  "properties": {
    "addr:full":"9 Shady Creek Rd Pleasant Valley NY 12569",
    "addr:housenumber":"9",
    "addr:postcode":"12569",
    "addr:street":"Shady Creek Rd",
    "iso:country":"US",
    "sg:address":"9 Shady Creek Rd",
    "sg:city":"Pleasant Valley",
    "sg:classifiers":[
        {
            "category":"Wholesale",
            "subcategory":"Motor Vehicles",
            "type":"Manufacturing & Wholesale Goods"
        }
    ],
    "sg:phone":"+1 845 635 9732",
    "sg:postcode":"12569",
    "sg:province":"NY",
    "wof:name":"A/J Autowholesale",
    "wof:placetype":"venue"
},
  "geometry": {"coordinates":[-73.838846,41.728416],"type":"Point"}
}