{
  "type": "Feature",
  "properties": {
    "addr:full":"1680 1st Ave New York NY 10128",
    "addr:housenumber":"1680",
    "addr:postcode":"10128",
    "addr:street":"1St Ave",
    "iso:country":"US",
    "sg:address":"1680 1st Ave",
    "sg:city":"New York",
    "sg:classifiers":[
        {
            "category":"Restaurant",
            "type":"Food & Drink"
        }
    ],
    "sg:phone":"+1 212 876 9332",
    "sg:postcode":"10128",
    "sg:province":"NY",
    "wof:name":"New Sunny East Restaurant",
    "wof:placetype":"venue"
},
  "geometry": {"coordinates":[-73.94879899999999,40.777699],"type":"Point"}
}