{
  "type": "Feature",
  "properties": {
    "iso:country":"US",
    "sg:address":"27 Lincoln Rd",
    "sg:city":"Montauk",
    "sg:classifiers":[
        {
            "category":"Travel",
            "subcategory":"Travel Agent",
            "type":"Entertainment"
        }
    ],
    "sg:phone":"+1   ",
    "sg:postcode":"11954",
    "sg:province":"NY",
    "sg:tags":[
        "operator",
        "tour"
    ],
    "wof:name":"Tours of Hamptons",
    "wof:placetype":"venue"
},
  "geometry": {"coordinates":[-71.969066,41.029685],"type":"Point"}
}