{
  "type": "Feature",
  "properties": {
    "addr:full":"36 Sunrise Hwy Baldwin NY 11510",
    "addr:housenumber":"36",
    "addr:postcode":"11510",
    "addr:street":"Sunrise Hwy",
    "iso:country":"US",
    "sg:address":"36 Sunrise Hwy",
    "sg:city":"Baldwin",
    "sg:classifiers":[
        {
            "category":"Autos & Motor Vehicles",
            "subcategory":"Automobile Sales",
            "type":"Retail Goods"
        }
    ],
    "sg:phone":"+1   ",
    "sg:postcode":"11510",
    "sg:province":"NY",
    "sg:tags":[
        "motorcycle"
    ],
    "wof:name":"Go Kart Shop",
    "wof:placetype":"venue"
},
  "geometry": {"coordinates":[-73.60816,40.656176],"type":"Point"}
}