{
  "type": "Feature",
  "properties": {
    "addr:full":"25 W Ridge Rd Warwick NY 10990",
    "addr:housenumber":"25",
    "addr:postcode":"10990",
    "addr:street":"W Ridge Rd",
    "iso:country":"US",
    "sg:address":"25 W Ridge Rd",
    "sg:city":"Warwick",
    "sg:classifiers":[
        {
            "category":"Building & Trades",
            "subcategory":"Landscaping Services",
            "type":"Services"
        }
    ],
    "sg:phone":"+1 845 986 5986",
    "sg:postcode":"10990",
    "sg:province":"NY",
    "wof:name":"Michael E Holt",
    "wof:placetype":"venue"
},
  "geometry": {"coordinates":[-74.374897,41.285933],"type":"Point"}
}