{
  "type": "Feature",
  "properties": {
    "addr:full":"1773 Amsterdam Ave New York NY 10031",
    "addr:housenumber":"1773",
    "addr:postcode":"10031",
    "addr:street":"Amsterdam Ave",
    "iso:country":"US",
    "sg:address":"1773 Amsterdam Ave",
    "sg:city":"New York",
    "sg:classifiers":[
        {
            "category":"Retail",
            "subcategory":"Laundry & Dry Cleaning",
            "type":"Services"
        }
    ],
    "sg:phone":"+1 212 491 6610",
    "sg:postcode":"10031",
    "sg:province":"NY",
    "wof:name":"F & C Laundromat",
    "wof:placetype":"venue"
},
  "geometry": {"coordinates":[-73.946406,40.826632],"type":"Point"}
}