{
  "type": "Feature",
  "properties": {
    "addr:full":"243 Jefferson St Centerport NY 11721",
    "addr:housenumber":"243",
    "addr:postcode":"11721",
    "addr:street":"Jefferson St",
    "iso:country":"US",
    "sg:address":"243 Jefferson St",
    "sg:city":"Centerport",
    "sg:classifiers":[
        {
            "category":"Building & Trades",
            "subcategory":"Construction",
            "type":"Services"
        }
    ],
    "sg:phone":"+1 631 421 3738",
    "sg:postcode":"11721",
    "sg:province":"NY",
    "sg:tags":[
        "contractor",
        "painting",
        "hanging"
    ],
    "wof:name":"Paul F Schmitz",
    "wof:placetype":"venue"
},
  "geometry": {"coordinates":[-73.381873,40.894643],"type":"Point"}
}