{
  "type": "Feature",
  "properties": {
    "addr:full":"71 Milbar Blvd Farmingdale NY 11735",
    "addr:housenumber":"71",
    "addr:postcode":"11735",
    "addr:street":"Milbar Blvd",
    "iso:country":"US",
    "sg:address":"71 Milbar Blvd",
    "sg:city":"Farmingdale",
    "sg:classifiers":[
        {
            "category":"Communications",
            "subcategory":"Film & Video Production",
            "type":"Services"
        },
        {
            "category":"Manufacturing",
            "subcategory":"Tools & Machinery",
            "type":"Manufacturing & Wholesale Goods"
        }
    ],
    "sg:phone":"+1 516 420 7410",
    "sg:postcode":"11735",
    "sg:province":"NY",
    "sg:tags":[
        "picture",
        "medium",
        "mfg",
        "motion",
        "tape",
        "recording",
        "duplication"
    ],
    "wof:name":"Silva Communications Corp",
    "wof:placetype":"venue"
},
  "geometry": {"coordinates":[-73.416337,40.750149],"type":"Point"}
}