{
  "type": "Feature",
  "properties": {
    "iso:country":"US",
    "sg:address":"81 Spring St",
    "sg:city":"New York",
    "sg:classifiers":[
        {
            "category":"Real Estate",
            "subcategory":"Real Estate Agent",
            "type":"Services"
        }
    ],
    "sg:phone":"+1 646 613 1844",
    "sg:postcode":"10012",
    "sg:province":"NY",
    "wof:name":"Bayard House Condominium",
    "wof:placetype":"venue"
},
  "geometry": {"coordinates":[-73.998649,40.723014],"type":"Point"}
}