{
  "type": "Feature",
  "properties": {
    "addr:full":"411 Lillian Blvd Holbrook NY 11741",
    "addr:housenumber":"411",
    "addr:postcode":"11741",
    "addr:street":"Lillian Blvd",
    "iso:country":"US",
    "sg:address":"411 Lillian Blvd",
    "sg:city":"Holbrook",
    "sg:classifiers":[
        {
            "category":"Building & Trades",
            "subcategory":"Plumbing",
            "type":"Services"
        }
    ],
    "sg:phone":"+1 631 467 8745",
    "sg:postcode":"11741",
    "sg:province":"NY",
    "sg:tags":[
        "contractor"
    ],
    "wof:name":"Gas Works",
    "wof:placetype":"venue"
},
  "geometry": {"coordinates":[-73.069999,40.794279],"type":"Point"}
}