{
  "type": "Feature",
  "properties": {
    "iso:country":"US",
    "sg:address":"2150 Grand Ave",
    "sg:city":"North Baldwin",
    "sg:classifiers":[
        {
            "category":"Shopping",
            "subcategory":"Bicycles & Sporting Goods",
            "type":"Retail Goods"
        }
    ],
    "sg:phone":"+1 516 223 8989",
    "sg:postcode":"11510",
    "sg:province":"NY",
    "sg:tags":[
        "equipment",
        "diver",
        "supply"
    ],
    "wof:name":"Danny's Dive Shop",
    "wof:placetype":"venue"
},
  "geometry": {"coordinates":[-73.609026,40.656995],"type":"Point"}
}