{
  "type": "Feature",
  "properties": {
    "iso:country":"US",
    "sg:address":"155 W 13 St",
    "sg:city":"New York",
    "sg:classifiers":[
        {
            "category":"Restaurant",
            "type":"Food & Drink"
        }
    ],
    "sg:phone":"+1   ",
    "sg:postcode":"10011",
    "sg:province":"NY",
    "sg:tags":[
        "eating"
    ],
    "wof:name":"Savory Sojourns Ltd Inc",
    "wof:placetype":"venue"
},
  "geometry": {"coordinates":[-73.99896,40.737271],"type":"Point"}
}