{
  "type": "Feature",
  "properties": {
    "iso:country":"US",
    "sg:address":"1599 New York Ave",
    "sg:city":"Brooklyn",
    "sg:classifiers":[
        {
            "category":"Professional",
            "subcategory":"Computer Services",
            "type":"Services"
        }
    ],
    "sg:phone":"+1   ",
    "sg:postcode":"11210",
    "sg:province":"NY",
    "sg:tags":[
        "related"
    ],
    "wof:name":"Flg Systems Inc",
    "wof:placetype":"venue"
},
  "geometry": {"coordinates":[-73.944591,40.632301],"type":"Point"}
}