{
  "type": "Feature",
  "properties": {
    "iso:country":"US",
    "sg:address":"4278 New York Ave",
    "sg:city":"Island Park",
    "sg:classifiers":[
        {
            "category":"Building & Trades",
            "subcategory":"Construction",
            "type":"Services"
        }
    ],
    "sg:phone":"+1 516 432 8246",
    "sg:postcode":"11558",
    "sg:province":"NY",
    "sg:tags":[
        "house"
    ],
    "wof:name":"Miranda Home Improvements Inc",
    "wof:placetype":"venue"
},
  "geometry": {"coordinates":[-73.646908,40.603469],"type":"Point"}
}