{
  "type": "Feature",
  "properties": {
    "addr:full":"801 9th Ave New York NY 10019",
    "addr:housenumber":"801",
    "addr:postcode":"10019",
    "addr:street":"9Th Ave",
    "iso:country":"US",
    "sg:address":"801 9th Ave",
    "sg:city":"New York",
    "sg:classifiers":[
        {
            "category":"Fast Food",
            "type":"Food & Drink"
        },
        {
            "category":"Restaurant",
            "type":"Food & Drink"
        }
    ],
    "sg:phone":"+1 212 977 1150",
    "sg:postcode":"10019",
    "sg:province":"NY",
    "sg:tags":[
        "burger",
        "breakfast",
        "brunch",
        "diner"
    ],
    "sg:website":"www.georgioscountrygrill.com",
    "wof:name":"Georgio's Country Grill",
    "wof:placetype":"venue"
},
  "geometry": {"coordinates":[-73.98781200000001,40.765601],"type":"Point"}
}