{
  "type": "Feature",
  "properties": {
    "iso:country":"US",
    "sg:address":"206 W 125th St",
    "sg:city":"New York",
    "sg:classifiers":[
        {
            "category":"Shopping",
            "subcategory":"Jewelry",
            "type":"Retail Goods"
        }
    ],
    "sg:phone":"+1 212 280 6698",
    "sg:postcode":"10027",
    "sg:province":"NY",
    "sg:tags":[
        "jeweler"
    ],
    "wof:name":"Gold City Of Harlem Inc",
    "wof:placetype":"venue"
},
  "geometry": {"coordinates":[-73.95107,40.810034],"type":"Point"}
}