{
  "type": "Feature",
  "properties": {
    "addr:full":"1424 Blondell Ave Bronx NY 10461",
    "addr:housenumber":"1424",
    "addr:postcode":"10461",
    "addr:street":"Blondell Ave",
    "iso:country":"US",
    "sg:address":"1424 Blondell Ave",
    "sg:city":"Bronx",
    "sg:classifiers":[
        {
            "category":"Wholesale",
            "subcategory":"Auto Parts",
            "type":"Manufacturing & Wholesale Goods"
        }
    ],
    "sg:phone":"+1 718 792 2155",
    "sg:postcode":"10461",
    "sg:province":"NY",
    "sg:tags":[
        "alternator",
        "generator"
    ],
    "wof:name":"Bronx Ignition",
    "wof:placetype":"venue"
},
  "geometry": {"coordinates":[-73.842837,40.842906],"type":"Point"}
}