{
  "type": "Feature",
  "properties": {
    "addr:full":"28 E 28th St Fl 9 New York NY 10016",
    "addr:housenumber":"28;9",
    "addr:postcode":"new;10016",
    "addr:street":"E 28Th St",
    "iso:country":"US",
    "sg:address":"28 E 28th St Fl 9",
    "sg:city":"New York",
    "sg:classifiers":[
        {
            "category":"Banks & Credit Unions",
            "subcategory":"Financial Services",
            "type":"Services"
        }
    ],
    "sg:phone":"+1 203 661 0405",
    "sg:postcode":"10016",
    "sg:province":"NY",
    "sg:tags":[
        "broker",
        "mortgage"
    ],
    "wof:name":"C P C",
    "wof:placetype":"venue"
},
  "geometry": {"coordinates":[-73.985618,40.743821],"type":"Point"}
}