{
  "type": "Feature",
  "properties": {
    "iso:country":"US",
    "sg:address":"10 White St",
    "sg:city":"Frewsburg",
    "sg:classifiers":[
        {
            "category":"Retail",
            "subcategory":"Repair Shop",
            "type":"Services"
        }
    ],
    "sg:phone":"+1   ",
    "sg:postcode":"14709",
    "sg:province":"NY",
    "sg:tags":[
        "supply"
    ],
    "wof:name":"White Sales & Service",
    "wof:placetype":"venue"
},
  "geometry": {"coordinates":[-78.01436200000001,42.308778],"type":"Point"}
}