{
  "type": "Feature",
  "properties": {
    "addr:full":"369 Rose Ct Yorktown Heights NY 10598",
    "addr:housenumber":"369",
    "addr:postcode":"10598",
    "addr:street":"Rose Ct",
    "iso:country":"US",
    "sg:address":"369 Rose Ct",
    "sg:city":"Yorktown Heights",
    "sg:classifiers":[
        {
            "category":"Professional",
            "subcategory":"Advertising",
            "type":"Services"
        }
    ],
    "sg:phone":"+1 914 962 2800",
    "sg:postcode":"10598",
    "sg:province":"NY",
    "sg:tags":[
        "mail"
    ],
    "wof:name":"Money Mailer",
    "wof:placetype":"venue"
},
  "geometry": {"coordinates":[-73.77904599999999,41.260946],"type":"Point"}
}