{
  "type": "Feature",
  "properties": {
    "iso:country":"US",
    "sg:address":"469 Main St",
    "sg:city":"Arcade",
    "sg:classifiers":[
        {
            "category":"Food & Beverages",
            "subcategory":"Groceries & Convenience Stores",
            "type":"Retail Goods"
        }
    ],
    "sg:phone":"+1 585 492 2020",
    "sg:postcode":"14009",
    "sg:province":"NY",
    "wof:name":"Coffee & More",
    "wof:placetype":"venue"
},
  "geometry": {"coordinates":[-78.44995400000001,42.532468],"type":"Point"}
}