{
  "type": "Feature",
  "properties": {
    "addr:full":"105 Carlough Rd Unit B Bohemia NY 11716",
    "addr:housenumber":"105",
    "addr:postcode":"11716",
    "addr:street":"Carlough Rd Unit B",
    "iso:country":"US",
    "sg:address":"105 Carlough Rd Unit B",
    "sg:city":"Bohemia",
    "sg:classifiers":[
        {
            "category":"Wholesale",
            "subcategory":"Office Equipment",
            "type":"Manufacturing & Wholesale Goods"
        },
        {
            "category":"Shopping",
            "subcategory":"Computers & Home Electronics",
            "type":"Retail Goods"
        }
    ],
    "sg:phone":"+1 631 567 6755",
    "sg:postcode":"11716",
    "sg:province":"NY",
    "sg:tags":[
        "scanning",
        "printer",
        "plotting",
        "supply"
    ],
    "wof:name":"Spotlight Designs Ltd",
    "wof:placetype":"venue"
},
  "geometry": {"coordinates":[-73.09154100000001,40.775407],"type":"Point"}
}