{
  "type": "Feature",
  "properties": {
    "iso:country":"US",
    "sg:address":"85 Knollwood Rd",
    "sg:city":"White Plains",
    "sg:classifiers":[
        {
            "category":"Restaurant",
            "type":"Food & Drink"
        }
    ],
    "sg:phone":"+1   ",
    "sg:postcode":"10607",
    "sg:province":"NY",
    "sg:tags":[
        "italian"
    ],
    "wof:name":"Pizza & Brew",
    "wof:placetype":"venue"
},
  "geometry": {"coordinates":[-73.809286,41.036803],"type":"Point"}
}