{
  "type": "Feature",
  "properties": {
    "iso:country":"US",
    "sg:address":"3612 34th Avenue",
    "sg:city":"Astoria",
    "sg:classifiers":[
        {
            "category":"Professional",
            "subcategory":"Lawyer & Legal Services",
            "type":"Services"
        }
    ],
    "sg:phone":"+1 718 361 0075",
    "sg:postcode":"11106",
    "sg:province":"NY",
    "wof:name":"Kazazis & Alimaras Llp",
    "wof:placetype":"venue"
},
  "geometry": {"coordinates":[-73.923168,40.757746],"type":"Point"}
}