{
  "type": "Feature",
  "properties": {
    "iso:country":"US",
    "sg:address":"2 Main St",
    "sg:city":"Hempstead",
    "sg:classifiers":[
        {
            "category":"Shopping",
            "subcategory":"Gifts & Souvenirs",
            "type":"Retail Goods"
        }
    ],
    "sg:phone":"+1 800 564 0226",
    "sg:postcode":"11550",
    "sg:province":"NY",
    "sg:tags":[
        "flower"
    ],
    "wof:name":"Ariella Flowers & Gifts Inc",
    "wof:placetype":"venue"
},
  "geometry": {"coordinates":[-73.623389,40.706316],"type":"Point"}
}