{
  "type": "Feature",
  "properties": {
    "iso:country":"US",
    "sg:address":"40 Main St",
    "sg:city":"Massena",
    "sg:classifiers":[
        {
            "category":"Professional",
            "subcategory":"Credit Reporting & Collection",
            "type":"Services"
        }
    ],
    "sg:phone":"+1 315 769 0031",
    "sg:postcode":"13662",
    "sg:province":"NY",
    "sg:tags":[
        "agency"
    ],
    "sg:website":"www.capcollect.com",
    "wof:name":"Capital Collections",
    "wof:placetype":"venue"
},
  "geometry": {"coordinates":[-74.893016,44.93151],"type":"Point"}
}