{
  "type": "Feature",
  "properties": {
    "addr:full":"404 Albee Sq Brooklyn NY 11201",
    "addr:housenumber":"404",
    "addr:postcode":"11201",
    "addr:street":"Albee Sq",
    "iso:country":"US",
    "sg:address":"404 Albee Sq",
    "sg:city":"Brooklyn",
    "sg:classifiers":[
        {
            "category":"Wholesale",
            "subcategory":"Vending Machines",
            "type":"Manufacturing & Wholesale Goods"
        }
    ],
    "sg:phone":"+1   ",
    "sg:postcode":"11201",
    "sg:province":"NY",
    "sg:tags":[
        "operator"
    ],
    "wof:name":"Mostafa Kamal",
    "wof:placetype":"venue"
},
  "geometry": {"coordinates":[-73.983566,40.690387],"type":"Point"}
}