{
  "type": "Feature",
  "properties": {
    "iso:country":"US",
    "sg:address":"1880 Bedford Ave",
    "sg:city":"Bellmore",
    "sg:classifiers":[
        {
            "category":"Freight",
            "type":"Transportation"
        }
    ],
    "sg:phone":"+1   ",
    "sg:postcode":"11710",
    "sg:province":"NY",
    "sg:tags":[
        "operator",
        "trucking"
    ],
    "wof:name":"Uat Corp",
    "wof:placetype":"venue"
},
  "geometry": {"coordinates":[-73.55466800000001,40.696991],"type":"Point"}
}