{
  "type": "Feature",
  "properties": {
    "addr:full":"20 Manor Rd Rhinebeck NY 12572",
    "addr:housenumber":"20",
    "addr:postcode":"12572",
    "addr:street":"Manor Rd",
    "iso:country":"US",
    "sg:address":"20 Manor Rd",
    "sg:city":"Rhinebeck",
    "sg:classifiers":[
        {
            "category":"Social Services",
            "subcategory":"Child Care",
            "type":"Services"
        }
    ],
    "sg:phone":"+1   ",
    "sg:postcode":"12572",
    "sg:province":"NY",
    "sg:tags":[
        "day"
    ],
    "wof:name":"Parent Choice Childrens Center",
    "wof:placetype":"venue"
},
  "geometry": {"coordinates":[-73.90157600000001,41.922843],"type":"Point"}
}