{
  "type": "Feature",
  "properties": {
    "addr:full":"292 Ronkonkoma Ave Ronkonkoma NY 11779",
    "addr:housenumber":"292",
    "addr:postcode":"11779",
    "addr:street":"Ronkonkoma Ave",
    "iso:country":"US",
    "sg:address":"292 Ronkonkoma Ave",
    "sg:city":"Ronkonkoma",
    "sg:classifiers":[
        {
            "category":"Autos & Motor Vehicles",
            "subcategory":"Fuel & Gas Station",
            "type":"Retail Goods"
        }
    ],
    "sg:phone":"+1   ",
    "sg:postcode":"11779",
    "sg:province":"NY",
    "sg:tags":[
        "station",
        "gasoline"
    ],
    "wof:name":"60 Gas Stop Inc",
    "wof:placetype":"venue"
},
  "geometry": {"coordinates":[-73.112036,40.813685],"type":"Point"}
}