{
  "type": "Feature",
  "properties": {
    "addr:full":"1501 Myrtle Ave Brooklyn NY 11237",
    "addr:housenumber":"1501",
    "addr:postcode":"11237",
    "addr:street":"Myrtle Ave",
    "iso:country":"US",
    "sg:address":"1501 Myrtle Ave",
    "sg:city":"Brooklyn",
    "sg:classifiers":[
        {
            "category":"Personal",
            "subcategory":"Barber",
            "type":"Services"
        }
    ],
    "sg:phone":"+1 718 366 5940",
    "sg:postcode":"11237",
    "sg:province":"NY",
    "wof:name":"M L B",
    "wof:placetype":"venue"
},
  "geometry": {"coordinates":[-73.91529800000001,40.699001],"type":"Point"}
}