{
  "type": "Feature",
  "properties": {
    "iso:country":"US",
    "sg:address":"122 Pleasant St",
    "sg:city":"Keeseville",
    "sg:classifiers":[
        {
            "category":"Health Services",
            "subcategory":"Doctor",
            "type":"Services"
        }
    ],
    "sg:phone":"+1 518 834 7001",
    "sg:postcode":"12944",
    "sg:province":"NY",
    "sg:tags":[
        "dentist"
    ],
    "wof:name":"Keesville Dental",
    "wof:placetype":"venue"
},
  "geometry": {"coordinates":[-73.486739,44.502424],"type":"Point"}
}