{
  "type": "Feature",
  "properties": {
    "addr:full":"789 Mac Donough St Brooklyn NY 11233",
    "addr:housenumber":"789",
    "addr:postcode":"11233",
    "addr:street":"Mac Donough St",
    "iso:country":"US",
    "sg:address":"789 Mac Donough St",
    "sg:city":"Brooklyn",
    "sg:classifiers":[
        {
            "category":"Professional",
            "subcategory":"Computer Services",
            "type":"Services"
        }
    ],
    "sg:phone":"+1   ",
    "sg:postcode":"11233",
    "sg:province":"NY",
    "sg:tags":[
        "training",
        "consulting"
    ],
    "wof:name":"E Greene Tech & Co",
    "wof:placetype":"venue"
},
  "geometry": {"coordinates":[-73.913308,40.684521],"type":"Point"}
}