{
  "type": "Feature",
  "properties": {
    "iso:country":"US",
    "sg:address":"70 Main St",
    "sg:city":"Northport",
    "sg:classifiers":[
        {
            "category":"Shopping",
            "subcategory":"Stationery & Office Supplies",
            "type":"Retail Goods"
        }
    ],
    "sg:phone":"+1 631 754 0159",
    "sg:postcode":"11768",
    "sg:province":"NY",
    "sg:tags":[
        "equipment"
    ],
    "wof:name":"Arndt Stationery",
    "wof:placetype":"venue"
},
  "geometry": {"coordinates":[-73.35050200000001,40.9002],"type":"Point"}
}