{
  "type": "Feature",
  "properties": {
    "iso:country":"US",
    "sg:address":"319 W Main St",
    "sg:city":"Batavia",
    "sg:classifiers":[
        {
            "category":"Wholesale",
            "subcategory":"Vending Machines",
            "type":"Manufacturing & Wholesale Goods"
        }
    ],
    "sg:phone":"+1   ",
    "sg:postcode":"14020",
    "sg:province":"NY",
    "sg:tags":[
        "operator",
        "eating"
    ],
    "wof:name":"Loose Ends Vending Inc",
    "wof:placetype":"venue"
},
  "geometry": {"coordinates":[-78.19865299999999,43.003043],"type":"Point"}
}