{
  "type": "Feature",
  "properties": {
    "addr:full":"11 N Broadway Yonkers NY 10701",
    "addr:housenumber":"11",
    "addr:postcode":"10701",
    "addr:street":"N Broadway",
    "iso:country":"US",
    "sg:address":"11 N Broadway",
    "sg:city":"Yonkers",
    "sg:classifiers":[
        {
            "category":"Retail",
            "subcategory":"Repair Shop",
            "type":"Services"
        }
    ],
    "sg:phone":"+1 914 968 4492",
    "sg:postcode":"10701",
    "sg:province":"NY",
    "sg:tags":[
        "watch"
    ],
    "wof:name":"Swiss Watch Hospital-Yonkers",
    "wof:placetype":"venue"
},
  "geometry": {"coordinates":[-73.89827699999999,40.935303],"type":"Point"}
}