{
  "type": "Feature",
  "properties": {
    "addr:full":"144 Maple Ave Catskill NY 12414",
    "addr:housenumber":"144",
    "addr:postcode":"12414",
    "addr:street":"Maple Ave",
    "iso:country":"US",
    "sg:address":"144 Maple Ave",
    "sg:city":"Catskill",
    "sg:classifiers":[
        {
            "category":"Autos & Motor Vehicles",
            "subcategory":"Automobile Sales",
            "type":"Retail Goods"
        }
    ],
    "sg:phone":"+1   ",
    "sg:postcode":"12414",
    "sg:province":"NY",
    "sg:tags":[
        "used"
    ],
    "wof:name":"Trebors",
    "wof:placetype":"venue"
},
  "geometry": {"coordinates":[-73.872905,42.22],"type":"Point"}
}