{
  "type": "Feature",
  "properties": {
    "addr:full":"2059 Brighton Henrietta Town Line Rd Rochester NY 14623",
    "addr:housenumber":"2059",
    "addr:postcode":"14623",
    "addr:street":"Brighton Henrietta Town Line Rd",
    "iso:country":"US",
    "sg:address":"2059 Brighton Henrietta Town Line Rd",
    "sg:city":"Rochester",
    "sg:classifiers":[
        {
            "category":"Building & Trades",
            "subcategory":"Landscaping Services",
            "type":"Services"
        }
    ],
    "sg:phone":"+1 585 424 4476",
    "sg:postcode":"14623",
    "sg:province":"NY",
    "sg:tags":[
        "lawn",
        "maintenance",
        "grounds"
    ],
    "sg:website":"www.broccologroup.com",
    "wof:name":"Broccolo Tree & Lawn Care Inc",
    "wof:placetype":"venue"
},
  "geometry": {"coordinates":[-77.614035,43.094666],"type":"Point"}
}