{
  "type": "Feature",
  "properties": {
    "iso:country":"US",
    "sg:address":"373 Downing Dr",
    "sg:city":"Yorktown Heights",
    "sg:classifiers":[
        {
            "category":"Cinema",
            "subcategory":"Movie Rental",
            "type":"Entertainment"
        }
    ],
    "sg:phone":"+1 914 243 4500",
    "sg:postcode":"10598",
    "sg:province":"NY",
    "sg:tags":[
        "leasing",
        "video",
        "disc",
        "tape"
    ],
    "wof:name":"Captain Video Yorktown Heights",
    "wof:placetype":"venue"
},
  "geometry": {"coordinates":[-73.79636499999999,41.275594],"type":"Point"}
}