{
  "type": "Feature",
  "properties": {
    "addr:full":"429 N Central Ave White Plains NY 10606",
    "addr:housenumber":"429",
    "addr:postcode":"10606",
    "addr:street":"N Central Ave",
    "iso:country":"US",
    "sg:address":"429 N Central Ave",
    "sg:city":"White Plains",
    "sg:classifiers":[
        {
            "category":"Professional",
            "subcategory":"Accounting & Tax Preparation",
            "type":"Services"
        }
    ],
    "sg:phone":"+1 914 686 1444",
    "sg:postcode":"10606",
    "sg:province":"NY",
    "sg:tags":[
        "return",
        "filing"
    ],
    "wof:name":"Barresi Insurance",
    "wof:placetype":"venue"
},
  "geometry": {"coordinates":[-73.787249,41.031819],"type":"Point"}
}