{
  "type": "Feature",
  "properties": {
    "iso:country":"US",
    "sg:address":"980 Mirabelle Ave",
    "sg:city":"Westbury",
    "sg:classifiers":[
        {
            "category":"Retail",
            "subcategory":"Portrait Studio",
            "type":"Services"
        }
    ],
    "sg:phone":"+1 516 334 5401",
    "sg:postcode":"11590",
    "sg:province":"NY",
    "sg:tags":[
        "photographer"
    ],
    "wof:name":"Say Cheese",
    "wof:placetype":"venue"
},
  "geometry": {"coordinates":[-73.56393199999999,40.751073],"type":"Point"}
}