{
  "type": "Feature",
  "properties": {
    "addr:full":"1040 Ridge Rd E Rochester NY 14621",
    "addr:housenumber":"1040",
    "addr:postcode":"14621",
    "addr:street":"Ridge Rd E",
    "iso:country":"US",
    "sg:address":"1040 Ridge Rd E",
    "sg:city":"Rochester",
    "sg:classifiers":[
        {
            "category":"Home & Garden",
            "subcategory":"Hardware",
            "type":"Retail Goods"
        }
    ],
    "sg:phone":"+1 585 544 5154",
    "sg:postcode":"14621",
    "sg:province":"NY",
    "sg:tags":[
        "tool",
        "used"
    ],
    "wof:name":"Harbor Freight Tools USA Inc",
    "wof:placetype":"venue"
},
  "geometry": {"coordinates":[-77.585477,43.197514],"type":"Point"}
}