{
  "type": "Feature",
  "properties": {
    "iso:country":"US",
    "sg:address":"2070 Risser Rd",
    "sg:city":"Canandaigua",
    "sg:classifiers":[
        {
            "category":"Building & Trades",
            "subcategory":"Construction",
            "type":"Services"
        }
    ],
    "sg:phone":"+1 585 394 7339",
    "sg:postcode":"14424",
    "sg:province":"NY",
    "sg:tags":[
        "home",
        "improvement"
    ],
    "wof:name":"John Carson Home Improvement",
    "wof:placetype":"venue"
},
  "geometry": {"coordinates":[-77.29453100000001,42.934235],"type":"Point"}
}