{
  "type": "Feature",
  "properties": {
    "addr:full":"18 Browning Rd Massena NY 13662",
    "addr:housenumber":"18",
    "addr:postcode":"13662",
    "addr:street":"Browning Rd",
    "iso:country":"US",
    "sg:address":"18 Browning Rd",
    "sg:city":"Massena",
    "sg:classifiers":[
        {
            "category":"Building & Trades",
            "subcategory":"Construction",
            "type":"Services"
        }
    ],
    "sg:phone":"+1 315 769 2268",
    "sg:postcode":"13662",
    "sg:province":"NY",
    "sg:tags":[
        "contractor"
    ],
    "wof:name":"Legault Custom Builders Inc",
    "wof:placetype":"venue"
},
  "geometry": {"coordinates":[-74.94936300000001,44.92616],"type":"Point"}
}