{
  "type": "Feature",
  "properties": {
    "iso:country":"US",
    "sg:address":"636 Starin Ave",
    "sg:city":"Buffalo",
    "sg:classifiers":[
        {
            "category":"Building & Trades",
            "subcategory":"Construction",
            "type":"Services"
        }
    ],
    "sg:phone":"+1 716 835 2719",
    "sg:postcode":"14216",
    "sg:province":"NY",
    "sg:tags":[
        "house"
    ],
    "wof:name":"Design Within Improvements",
    "wof:placetype":"venue"
},
  "geometry": {"coordinates":[-78.84390399999999,42.956519],"type":"Point"}
}