{
  "type": "Feature",
  "properties": {
    "addr:full":"130 7 Ave New York NY 10011",
    "addr:housenumber":"130",
    "addr:postcode":"10011",
    "addr:street":"7 Ave",
    "iso:country":"US",
    "sg:address":"130 7 Ave",
    "sg:city":"New York",
    "sg:classifiers":[
        {
            "category":"Professional",
            "subcategory":"Business Services",
            "type":"Services"
        }
    ],
    "sg:phone":"+1 212 414 1700",
    "sg:postcode":"10011",
    "sg:province":"NY",
    "sg:tags":[
        "recording",
        "music",
        "studio",
        "producer",
        "manufacturer"
    ],
    "sg:website":"www.artemisrecords.com",
    "wof:name":"Artemis Records",
    "wof:placetype":"venue"
},
  "geometry": {"coordinates":[-74.000693,40.736974],"type":"Point"}
}