{
  "type": "Feature",
  "properties": {
    "iso:country":"US",
    "sg:address":"172 Cortlandt St",
    "sg:city":"Tarrytown",
    "sg:classifiers":[
        {
            "category":"Restaurant",
            "type":"Food & Drink"
        }
    ],
    "sg:phone":"+1   ",
    "sg:postcode":"10591",
    "sg:province":"NY",
    "sg:tags":[
        "eating"
    ],
    "wof:name":"Carols Kitchen",
    "wof:placetype":"venue"
},
  "geometry": {"coordinates":[-73.86278900000001,41.083383],"type":"Point"}
}