{
  "type": "Feature",
  "properties": {
    "addr:full":"855 Conklin St Farmingdale NY 11735",
    "addr:housenumber":"855",
    "addr:postcode":"11735",
    "addr:street":"Conklin St",
    "iso:country":"US",
    "sg:address":"855 Conklin St",
    "sg:city":"Farmingdale",
    "sg:classifiers":[
        {
            "category":"Wholesale",
            "subcategory":"Home Furnishings",
            "type":"Manufacturing & Wholesale Goods"
        },
        {
            "category":"Wholesale",
            "subcategory":"Durable Goods & Equipment",
            "type":"Manufacturing & Wholesale Goods"
        }
    ],
    "sg:phone":"+1 631 694 5959",
    "sg:postcode":"11735",
    "sg:province":"NY",
    "sg:tags":[
        "portrait",
        "frame",
        "picture"
    ],
    "sg:website":"www.abbotart.com",
    "wof:name":"Abbot Art",
    "wof:placetype":"venue"
},
  "geometry": {"coordinates":[-73.429377,40.736684],"type":"Point"}
}