{
  "type": "Feature",
  "properties": {
    "addr:full":"962 US Hwy 11 Gouverneur NY 13642",
    "addr:housenumber":"962",
    "addr:postcode":"13642",
    "addr:street":"Us Hwy 11",
    "iso:country":"US",
    "sg:address":"962 US Hwy 11",
    "sg:city":"Gouverneur",
    "sg:classifiers":[
        {
            "category":"Restaurant",
            "type":"Food & Drink"
        }
    ],
    "sg:phone":"+1 315 287 4231",
    "sg:postcode":"13642",
    "sg:province":"NY",
    "wof:name":"Gentry's Clam Cove",
    "wof:placetype":"venue"
},
  "geometry": {"coordinates":[-75.50247299999999,44.309698],"type":"Point"}
}