{
  "type": "Feature",
  "properties": {
    "addr:full":"145 E 81st St New York NY 10028",
    "addr:housenumber":"145",
    "addr:postcode":"10028",
    "addr:street":"E 81St St",
    "iso:country":"US",
    "sg:address":"145 E 81st St",
    "sg:city":"New York",
    "sg:classifiers":[
        {
            "category":"Banks & Credit Unions",
            "subcategory":"Investment Brokerage",
            "type":"Services"
        }
    ],
    "sg:phone":"+1 212 472 2228",
    "sg:postcode":"10028",
    "sg:province":"NY",
    "sg:tags":[
        "advisory",
        "financial"
    ],
    "wof:name":"Crusader Investments LLC",
    "wof:placetype":"venue"
},
  "geometry": {"coordinates":[-73.956419,40.775733],"type":"Point"}
}