{
  "type": "Feature",
  "properties": {
    "addr:full":"354 2nd St Brooklyn NY 11215",
    "addr:housenumber":"354",
    "addr:postcode":"11215",
    "addr:street":"2Nd St",
    "iso:country":"US",
    "sg:address":"354 2nd St",
    "sg:city":"Brooklyn",
    "sg:classifiers":[
        {
            "category":"Home & Garden",
            "subcategory":"Garden Supply",
            "type":"Retail Goods"
        }
    ],
    "sg:phone":"+1 718 499 2098",
    "sg:postcode":"11215",
    "sg:province":"NY",
    "sg:tags":[
        "fountain",
        "display"
    ],
    "wof:name":"Park Slope Gardens LLC",
    "wof:placetype":"venue"
},
  "geometry": {"coordinates":[-73.98440600000001,40.67434],"type":"Point"}
}