{
  "type": "Feature",
  "properties": {
    "addr:full":"400 Madison Ave New York NY 10017",
    "addr:housenumber":"400",
    "addr:postcode":"10017",
    "addr:street":"Madison Ave",
    "iso:country":"US",
    "sg:address":"400 Madison Ave",
    "sg:city":"New York",
    "sg:classifiers":[
        {
            "category":"Banks & Credit Unions",
            "subcategory":"Investment Brokerage",
            "type":"Services"
        },
        {
            "category":"Professional",
            "subcategory":"Management & Consulting",
            "type":"Services"
        }
    ],
    "sg:phone":"+1 212 421 1100",
    "sg:postcode":"10017",
    "sg:province":"NY",
    "sg:tags":[
        "consultant",
        "security",
        "business"
    ],
    "sg:website":"www.xroadsllc.com",
    "wof:name":"Crossroads Capital Partners",
    "wof:placetype":"venue"
},
  "geometry": {"coordinates":[-73.976698,40.756407],"type":"Point"}
}