{
  "type": "Feature",
  "properties": {
    "iso:country":"US",
    "sg:address":"95 Main St",
    "sg:city":"Poughkeepsie",
    "sg:classifiers":[
        {
            "category":"Food & Beverages",
            "subcategory":"Groceries & Convenience Stores",
            "type":"Retail Goods"
        }
    ],
    "sg:phone":"+1   ",
    "sg:postcode":"12601",
    "sg:province":"NY",
    "wof:name":"El Azteca Grocery",
    "wof:placetype":"venue"
},
  "geometry": {"coordinates":[-73.93623599999999,41.705708],"type":"Point"}
}