{
  "type": "Feature",
  "properties": {
    "addr:full":"202 Carlton Dr Syracuse NY 13214",
    "addr:housenumber":"202",
    "addr:postcode":"13214",
    "addr:street":"Carlton Dr",
    "iso:country":"US",
    "sg:address":"202 Carlton Dr",
    "sg:city":"Syracuse",
    "sg:classifiers":[
        {
            "category":"Wholesale",
            "subcategory":"Construction Materials",
            "type":"Manufacturing & Wholesale Goods"
        }
    ],
    "sg:phone":"+1 315 446 7842",
    "sg:postcode":"13214",
    "sg:province":"NY",
    "sg:tags":[
        "building",
        "architectural",
        "supply"
    ],
    "wof:name":"R G T Sales Inc",
    "wof:placetype":"venue"
},
  "geometry": {"coordinates":[-76.089302,43.044675],"type":"Point"}
}