{
  "type": "Feature",
  "properties": {
    "iso:country":"US",
    "sg:address":"239 E Meadow Ave",
    "sg:city":"East Meadow",
    "sg:classifiers":[
        {
            "category":"Real Estate",
            "subcategory":"Real Estate Agent",
            "type":"Services"
        }
    ],
    "sg:phone":"+1 516 735 5287",
    "sg:postcode":"11554",
    "sg:province":"NY",
    "wof:name":"Jafa Realty Corp",
    "wof:placetype":"venue"
},
  "geometry": {"coordinates":[-73.562172,40.717809],"type":"Point"}
}