{
  "type": "Feature",
  "properties": {
    "addr:full":"124 Main St Ste 3 Huntington NY 11743",
    "addr:housenumber":"124",
    "addr:postcode":"11743",
    "addr:street":"Main St Ste 3",
    "iso:country":"US",
    "sg:address":"124 Main St Ste 3",
    "sg:city":"Huntington",
    "sg:classifiers":[
        {
            "category":"Health Services",
            "subcategory":"Doctor",
            "type":"Services"
        }
    ],
    "sg:phone":"+1 631 423 3535",
    "sg:postcode":"11743",
    "sg:province":"NY",
    "sg:tags":[
        "physician",
        "pediatrics-orthopedic",
        "surgeons",
        "orthopedics",
        "surgeon",
        "surgery"
    ],
    "wof:name":"Arthur Bernhang Md Pc",
    "wof:placetype":"venue"
},
  "geometry": {"coordinates":[-73.42053,40.873978],"type":"Point"}
}