{
  "type": "Feature",
  "properties": {
    "iso:country":"US",
    "sg:address":"1320 State Hwy 9j",
    "sg:city":"Castletn On Hdsn",
    "sg:classifiers":[
        {
            "category":"Professional",
            "subcategory":"Business Services",
            "type":"Services"
        }
    ],
    "sg:phone":"+1 518 732 7044",
    "sg:postcode":"12033",
    "sg:province":"NY",
    "sg:tags":[
        "painter",
        "sign"
    ],
    "wof:name":"Troy Neon Sign Corp",
    "wof:placetype":"venue"
},
  "geometry": {"coordinates":[-73.74354099999999,42.562596],"type":"Point"}
}