{
  "type": "Feature",
  "properties": {
    "iso:country":"US",
    "sg:address":"42 Lake St",
    "sg:city":"Owego",
    "sg:classifiers":[
        {
            "category":"Shopping",
            "subcategory":"Gifts & Souvenirs",
            "type":"Retail Goods"
        }
    ],
    "sg:phone":"+1 607 687 9242",
    "sg:postcode":"13827",
    "sg:province":"NY",
    "sg:tags":[
        "shop"
    ],
    "wof:name":"Artisan's Townhouse",
    "wof:placetype":"venue"
},
  "geometry": {"coordinates":[-76.261351,42.103318],"type":"Point"}
}