{
  "type": "Feature",
  "properties": {
    "iso:country":"US",
    "sg:address":"9 Dillon Rd",
    "sg:city":"Larchmont",
    "sg:classifiers":[
        {
            "category":"Building & Trades",
            "subcategory":"Construction",
            "type":"Services"
        }
    ],
    "sg:phone":"+1 914 633 5142",
    "sg:postcode":"10538",
    "sg:province":"NY",
    "sg:tags":[
        "hanging",
        "contractor"
    ],
    "wof:name":"Wilson Painting",
    "wof:placetype":"venue"
},
  "geometry": {"coordinates":[-73.763465,40.921283],"type":"Point"}
}