{
  "type": "Feature",
  "properties": {
    "iso:country":"US",
    "sg:address":"50 White St",
    "sg:city":"New York",
    "sg:classifiers":[
        {
            "category":"Real Estate",
            "subcategory":"Real Estate Operator",
            "type":"Services"
        }
    ],
    "sg:phone":"+1 212 966 6408",
    "sg:postcode":"10013",
    "sg:province":"NY",
    "sg:tags":[
        "building",
        "apartment",
        "elevator"
    ],
    "wof:name":"48-50 White St Corp",
    "wof:placetype":"venue"
},
  "geometry": {"coordinates":[-74.004081,40.718649],"type":"Point"}
}