{
  "type": "Feature",
  "properties": {
    "addr:full":"1949 Adam Clayton Powell Jr Blvd New York NY 10026",
    "addr:housenumber":"1949",
    "addr:postcode":"10026",
    "addr:street":"Adam Clayton Powell Jr Blvd",
    "iso:country":"US",
    "sg:address":"1949 Adam Clayton Powell Jr Blvd",
    "sg:city":"New York",
    "sg:classifiers":[
        {
            "category":"Personal",
            "subcategory":"Beauty Salon",
            "type":"Services"
        }
    ],
    "sg:phone":"+1 646 319 6823",
    "sg:postcode":"10026",
    "sg:province":"NY",
    "wof:name":"Dennis Bailey Hair Specialist",
    "wof:placetype":"venue"
},
  "geometry": {"coordinates":[-73.951672,40.804191],"type":"Point"}
}