{
  "type": "Feature",
  "properties": {
    "iso:country":"US",
    "sg:address":"404 W Albany St",
    "sg:city":"Herkimer",
    "sg:classifiers":[
        {
            "category":"Organizations",
            "subcategory":"Non-profit Organization",
            "type":"Services"
        }
    ],
    "sg:phone":"+1 315 867 6148",
    "sg:postcode":"13350",
    "sg:province":"NY",
    "sg:tags":[
        "alternative",
        "abortion"
    ],
    "wof:name":"Care Net Pregnancy CTR-Cny",
    "wof:placetype":"venue"
},
  "geometry": {"coordinates":[-74.99158300000001,43.023509],"type":"Point"}
}