{
  "type": "Feature",
  "properties": {
    "addr:full":"2555 River Rd Schenectady NY 12309",
    "addr:housenumber":"2555",
    "addr:postcode":"12309",
    "addr:street":"River Rd",
    "iso:country":"US",
    "sg:address":"2555 River Rd",
    "sg:city":"Schenectady",
    "sg:classifiers":[
        {
            "category":"Government",
            "subcategory":"Office",
            "type":"Public Place"
        }
    ],
    "sg:phone":"+1 518 377 1400",
    "sg:postcode":"12309",
    "sg:province":"NY",
    "sg:tags":[
        "village"
    ],
    "wof:name":"Niskayuna Transfer Station",
    "wof:placetype":"venue"
},
  "geometry": {"coordinates":[-73.865858,42.812269],"type":"Point"}
}