{
  "type": "Feature",
  "properties": {
    "addr:full":"2442 N Triphammer Rd Ithaca NY 14850",
    "addr:housenumber":"2442",
    "addr:postcode":"14850",
    "addr:street":"N Triphammer Rd",
    "iso:country":"US",
    "sg:address":"2442 N Triphammer Rd",
    "sg:city":"Ithaca",
    "sg:classifiers":[
        {
            "category":"Retail",
            "subcategory":"Veterinary Services",
            "type":"Services"
        }
    ],
    "sg:phone":"+1 607 257 8401",
    "sg:postcode":"14850",
    "sg:province":"NY",
    "sg:tags":[
        "veterinarian"
    ],
    "wof:name":"Cayuga Pet Hospital",
    "wof:placetype":"venue"
},
  "geometry": {"coordinates":[-76.490039,42.49139],"type":"Point"}
}