{
  "type": "Feature",
  "properties": {
    "iso:country":"US",
    "sg:address":"4 Spencer Ct",
    "sg:city":"Brooklyn",
    "sg:classifiers":[
        {
            "category":"Building & Trades",
            "subcategory":"Construction",
            "type":"Services"
        }
    ],
    "sg:phone":"+1 718 789 2320",
    "sg:postcode":"11205",
    "sg:province":"NY",
    "sg:tags":[
        "general",
        "contractor"
    ],
    "wof:name":"Wright General Construction",
    "wof:placetype":"venue"
},
  "geometry": {"coordinates":[-73.95441099999999,40.690351],"type":"Point"}
}