{
  "type": "Feature",
  "properties": {
    "iso:country":"US",
    "sg:address":"13 E 170",
    "sg:city":"New York",
    "sg:classifiers":[
        {
            "category":"Shopping",
            "subcategory":"Mobile Phones",
            "type":"Retail Goods"
        }
    ],
    "sg:phone":"+1 347 591 1154",
    "sg:postcode":"10001",
    "sg:province":"NY",
    "wof:name":"MetroPCS",
    "wof:placetype":"venue"
},
  "geometry": {"coordinates":[-73.987922,40.732706],"type":"Point"}
}