{
  "type": "Feature",
  "properties": {
    "addr:full":"2151 Albany Post Rd Montrose NY 10548",
    "addr:housenumber":"2151",
    "addr:postcode":"10548",
    "addr:street":"Albany Post Rd",
    "iso:country":"US",
    "sg:address":"2151 Albany Post Rd",
    "sg:city":"Montrose",
    "sg:classifiers":[
        {
            "category":"Restaurant",
            "type":"Food & Drink"
        }
    ],
    "sg:phone":"+1 845 737 0172",
    "sg:postcode":"10548",
    "sg:province":"NY",
    "wof:name":"Fulgums Rest & Bar",
    "wof:placetype":"venue"
},
  "geometry": {"coordinates":[-73.924719,41.241605],"type":"Point"}
}