{
  "type": "Feature",
  "properties": {
    "iso:country":"US",
    "sg:address":"6 Brook Hollow Rd",
    "sg:city":"Pittsford",
    "sg:classifiers":[
        {
            "category":"Manufacturing",
            "subcategory":"Printing",
            "type":"Manufacturing & Wholesale Goods"
        }
    ],
    "sg:phone":"+1   ",
    "sg:postcode":"14534",
    "sg:province":"NY",
    "sg:tags":[
        "cards",
        "greeting",
        "mfg"
    ],
    "wof:name":"Youre Invited",
    "wof:placetype":"venue"
},
  "geometry": {"coordinates":[-77.482427,43.072876],"type":"Point"}
}