{
  "type": "Feature",
  "properties": {
    "addr:full":"72 S 4th Ave Mt Vernon NY 10550",
    "addr:housenumber":"72",
    "addr:postcode":"10550",
    "addr:street":"S 4Th Ave",
    "iso:country":"US",
    "sg:address":"72 S 4th Ave",
    "sg:city":"Mt Vernon",
    "sg:classifiers":[
        {
            "category":"Food & Beverages",
            "subcategory":"Fruits & Vegetables",
            "type":"Retail Goods"
        }
    ],
    "sg:phone":"+1 914 667 6001",
    "sg:postcode":"10550",
    "sg:province":"NY",
    "sg:tags":[
        "produce"
    ],
    "wof:name":"K C Farmer's Market Corp",
    "wof:placetype":"venue"
},
  "geometry": {"coordinates":[-73.836736,40.910998],"type":"Point"}
}