{
  "type": "Feature",
  "properties": {
    "addr:full":"400 Madison Ave New York NY 10017",
    "addr:housenumber":"400",
    "addr:postcode":"10017",
    "addr:street":"Madison Ave",
    "iso:country":"US",
    "sg:address":"400 Madison Ave",
    "sg:city":"New York",
    "sg:classifiers":[
        {
            "category":"Arena",
            "subcategory":"Sports Club",
            "type":"Entertainment"
        }
    ],
    "sg:phone":"+1 212 888 9088",
    "sg:postcode":"10017",
    "sg:province":"NY",
    "sg:tags":[
        "manager",
        "agency",
        "employment",
        "recruiter",
        "promoter"
    ],
    "wof:name":"International Sports Properties Ltd",
    "wof:placetype":"venue"
},
  "geometry": {"coordinates":[-73.976997,40.756001],"type":"Point"}
}