{
  "type": "Feature",
  "properties": {
    "addr:full":"411 West Ave Albion NY 14411",
    "addr:housenumber":"411",
    "addr:postcode":"14411",
    "addr:street":"West Ave",
    "iso:country":"US",
    "sg:address":"411 West Ave",
    "sg:city":"Albion",
    "sg:classifiers":[
        {
            "category":"Retail",
            "subcategory":"Auto Rental",
            "type":"Services"
        }
    ],
    "sg:phone":"+1 585 589 6471",
    "sg:postcode":"14411",
    "sg:province":"NY",
    "sg:tags":[
        "renting",
        "automobile"
    ],
    "wof:name":"Enterprise Rent A Car",
    "wof:placetype":"venue"
},
  "geometry": {"coordinates":[-78.205956,43.240848],"type":"Point"}
}