{
  "type": "Feature",
  "properties": {
    "iso:country":"US",
    "sg:address":"120 Wall St",
    "sg:city":"New York",
    "sg:classifiers":[
        {
            "category":"Organizations",
            "subcategory":"Non-profit Organization",
            "type":"Services"
        }
    ],
    "sg:phone":"+1 212 344 5878",
    "sg:postcode":"10005",
    "sg:province":"NY",
    "sg:tags":[
        "service/non-profit",
        "community"
    ],
    "sg:website":"www.aafny.org",
    "wof:name":"Asian American Federation",
    "wof:placetype":"venue"
},
  "geometry": {"coordinates":[-74.00599699999999,40.704708],"type":"Point"}
}