{
  "type": "Feature",
  "properties": {
    "iso:country":"US",
    "sg:address":"501 W Main St",
    "sg:city":"Patchogue",
    "sg:classifiers":[
        {
            "category":"Professional",
            "subcategory":"Business Services",
            "type":"Services"
        }
    ],
    "sg:phone":"+1 631 289 6815",
    "sg:postcode":"11772",
    "sg:province":"NY",
    "sg:tags":[
        "legal"
    ],
    "wof:name":"Davis and Prager",
    "wof:placetype":"venue"
},
  "geometry": {"coordinates":[-73.031808,40.759716],"type":"Point"}
}