{
  "type": "Feature",
  "properties": {
    "iso:country":"US",
    "sg:address":"3 New Plaza York Plz",
    "sg:city":"New York",
    "sg:classifiers":[
        {
            "category":"Sports & Exercise",
            "subcategory":"Golf",
            "type":"Entertainment"
        }
    ],
    "sg:phone":"+1 800 830 1577",
    "sg:postcode":"10001",
    "sg:province":"NY",
    "wof:name":"New York Health & Racquet Club",
    "wof:placetype":"venue"
},
  "geometry": {"coordinates":[-73.986569,40.750404],"type":"Point"}
}