{
  "type": "Feature",
  "properties": {
    "addr:full":"180 W 58th St Manhattan NY 10019",
    "addr:housenumber":"180",
    "addr:postcode":"10019",
    "addr:street":"W 58Th St",
    "iso:country":"US",
    "sg:address":"180 W 58th St",
    "sg:city":"Manhattan",
    "sg:classifiers":[
        {
            "category":"Building & Trades",
            "subcategory":"Cleaning & Sanitation",
            "type":"Services"
        },
        {
            "category":"Home & Garden",
            "subcategory":"Carpets & Floor Coverings",
            "type":"Retail Goods"
        }
    ],
    "sg:phone":"+1 646 535 7489",
    "sg:postcode":"10019",
    "sg:province":"NY",
    "sg:tags":[
        "installation",
        "carpeting"
    ],
    "wof:name":"Persian Rug Cleaning",
    "wof:placetype":"venue"
},
  "geometry": {"coordinates":[-73.979071,40.765988],"type":"Point"}
}