{
  "type": "Feature",
  "properties": {
    "addr:full":"1325 Smith Ridge Rd New Canaan NY 06840",
    "addr:housenumber":"1325",
    "addr:postcode":"06840",
    "addr:street":"Smith Ridge Rd",
    "iso:country":"US",
    "sg:address":"1325 Smith Ridge Rd",
    "sg:city":"New Canaan",
    "sg:classifiers":[
        {
            "category":"Health Services",
            "subcategory":"Health Practitioner",
            "type":"Services"
        }
    ],
    "sg:phone":"+1 203 972 1719",
    "sg:postcode":"06840",
    "sg:province":"NY",
    "sg:tags":[
        "healing"
    ],
    "wof:name":"K Nisenson Healing Arts",
    "wof:placetype":"venue"
},
  "geometry": {"coordinates":[-73.507295,41.195486],"type":"Point"}
}