{
  "type": "Feature",
  "properties": {
    "iso:country":"US",
    "sg:address":"631 Geyser Rd",
    "sg:city":"Ballston Spa",
    "sg:classifiers":[
        {
            "category":"Retail",
            "subcategory":"Repair Shop",
            "type":"Services"
        }
    ],
    "sg:phone":"+1 518 884 9591",
    "sg:postcode":"12020",
    "sg:province":"NY",
    "sg:tags":[
        "scooter",
        "motorcycle",
        "motor"
    ],
    "wof:name":"Behind Bars Motorcycle Co Inc",
    "wof:placetype":"venue"
},
  "geometry": {"coordinates":[-73.86429,43.042999],"type":"Point"}
}