{
  "type": "Feature",
  "properties": {
    "iso:country":"US",
    "sg:address":"40 Woodside Dr",
    "sg:city":"Rochester",
    "sg:classifiers":[
        {
            "category":"Building & Trades",
            "subcategory":"Construction",
            "type":"Services"
        }
    ],
    "sg:phone":"+1 585 594 4188",
    "sg:postcode":"14624",
    "sg:province":"NY",
    "sg:tags":[
        "house"
    ],
    "wof:name":"Salzetta Home Improvement",
    "wof:placetype":"venue"
},
  "geometry": {"coordinates":[-77.78113999999999,43.119257],"type":"Point"}
}