{
  "type": "Feature",
  "properties": {
    "iso:country":"US",
    "sg:address":"1883 Deer Park Ave",
    "sg:city":"Deer Park",
    "sg:classifiers":[
        {
            "category":"Home & Garden",
            "subcategory":"Hardware",
            "type":"Retail Goods"
        }
    ],
    "sg:phone":"+1 631 667 1424",
    "sg:postcode":"11729",
    "sg:province":"NY",
    "wof:name":"A & J Hardware & Plbg Spply Co",
    "wof:placetype":"venue"
},
  "geometry": {"coordinates":[-73.328305,40.759227],"type":"Point"}
}