{
  "type": "Feature",
  "properties": {
    "addr:full":"350 Rockaway Tpke Cedarhurst NY 11516",
    "addr:housenumber":"350",
    "addr:postcode":"11516",
    "addr:street":"Rockaway Tpke",
    "iso:country":"US",
    "sg:address":"350 Rockaway Tpke",
    "sg:city":"Cedarhurst",
    "sg:classifiers":[
        {
            "category":"Autos & Motor Vehicles",
            "subcategory":"Fuel & Gas Station",
            "type":"Retail Goods"
        }
    ],
    "sg:phone":"+1 516 239 2748",
    "sg:postcode":"11516",
    "sg:province":"NY",
    "sg:tags":[
        "oil"
    ],
    "wof:name":"Cedarhurst Getty",
    "wof:placetype":"venue"
},
  "geometry": {"coordinates":[-73.734534,40.623233],"type":"Point"}
}