{
  "type": "Feature",
  "properties": {
    "addr:full":"231 Main St Staten Island NY 10307",
    "addr:housenumber":"231",
    "addr:postcode":"10307",
    "addr:street":"Main St",
    "iso:country":"US",
    "sg:address":"231 Main St",
    "sg:city":"Staten Island",
    "sg:classifiers":[
        {
            "category":"Personal",
            "subcategory":"Barber",
            "type":"Services"
        }
    ],
    "sg:phone":"+1 718 984 9229",
    "sg:postcode":"10307",
    "sg:province":"NY",
    "wof:name":"Pete's Haircutters",
    "wof:placetype":"venue"
},
  "geometry": {"coordinates":[-74.24704800000001,40.509388],"type":"Point"}
}