{
  "type": "Feature",
  "properties": {
    "addr:full":"881 E 52nd St Brooklyn NY 11203",
    "addr:housenumber":"881",
    "addr:postcode":"11203",
    "addr:street":"E 52Nd St",
    "iso:country":"US",
    "sg:address":"881 E 52nd St",
    "sg:city":"Brooklyn",
    "sg:classifiers":[
        {
            "category":"Home & Garden",
            "subcategory":"Furniture",
            "type":"Retail Goods"
        }
    ],
    "sg:phone":"+1 718 629 4202",
    "sg:postcode":"11203",
    "sg:province":"NY",
    "sg:tags":[
        "store"
    ],
    "wof:name":"Emilia Interiors",
    "wof:placetype":"venue"
},
  "geometry": {"coordinates":[-73.926903,40.6385],"type":"Point"}
}