{
  "type": "Feature",
  "properties": {
    "addr:full":"438 56th St Brooklyn NY 11220",
    "addr:housenumber":"438",
    "addr:postcode":"11220",
    "addr:street":"56Th St",
    "iso:country":"US",
    "sg:address":"438 56th St",
    "sg:city":"Brooklyn",
    "sg:classifiers":[
        {
            "category":"Health Services",
            "subcategory":"Doctor",
            "type":"Services"
        }
    ],
    "sg:phone":"+1 718 439 4979",
    "sg:postcode":"11220",
    "sg:province":"NY",
    "wof:name":"Kim Seong J",
    "wof:placetype":"venue"
},
  "geometry": {"coordinates":[-74.015297,40.642502],"type":"Point"}
}