{
  "type": "Feature",
  "properties": {
    "iso:country":"US",
    "sg:address":"27 Tea Pl",
    "sg:city":"Tappan",
    "sg:classifiers":[
        {
            "category":"Building & Trades",
            "subcategory":"Electrical",
            "type":"Services"
        }
    ],
    "sg:phone":"+1 845 359 5336",
    "sg:postcode":"10983",
    "sg:province":"NY",
    "sg:tags":[
        "electrician",
        "contractor"
    ],
    "wof:name":"Tappan Electric",
    "wof:placetype":"venue"
},
  "geometry": {"coordinates":[-73.96471099999999,41.025742],"type":"Point"}
}