{
  "type": "Feature",
  "properties": {
    "addr:full":"8505 Whitney Ave Elmhurst NY 11373",
    "addr:housenumber":"8505",
    "addr:postcode":"11373",
    "addr:street":"Whitney Ave",
    "iso:country":"US",
    "sg:address":"8505 Whitney Ave",
    "sg:city":"Elmhurst",
    "sg:classifiers":[
        {
            "category":"Restaurant",
            "type":"Food & Drink"
        }
    ],
    "sg:phone":"+1 718 424 7300",
    "sg:postcode":"11373",
    "sg:province":"NY",
    "sg:tags":[
        "chinese"
    ],
    "wof:name":"Fu Fan Chinese Restaurant",
    "wof:placetype":"venue"
},
  "geometry": {"coordinates":[-73.880302,40.741402],"type":"Point"}
}