{
  "type": "Feature",
  "properties": {
    "addr:full":"939 Route 146 Clifton Park NY 12065",
    "addr:housenumber":"939",
    "addr:postcode":"12065",
    "addr:street":"Route 146;Park",
    "iso:country":"US",
    "sg:address":"939 Route 146",
    "sg:city":"Clifton Park",
    "sg:classifiers":[
        {
            "category":"Health Services",
            "subcategory":"Dentist",
            "type":"Services"
        }
    ],
    "sg:phone":"+1 518 383 3020",
    "sg:postcode":"12065",
    "sg:province":"NY",
    "sg:website":"www.sungchang.com",
    "wof:name":"SUNG CHANG S",
    "wof:placetype":"venue"
},
  "geometry": {"coordinates":[-73.803164,42.868089],"type":"Point"}
}