{
  "type": "Feature",
  "properties": {
    "iso:country":"US",
    "sg:address":"306 Burns St",
    "sg:city":"Forest Hills",
    "sg:classifiers":[
        {
            "category":"Manufacturing",
            "subcategory":"Apparel",
            "type":"Manufacturing & Wholesale Goods"
        }
    ],
    "sg:phone":"+1   ",
    "sg:postcode":"11375",
    "sg:province":"NY",
    "sg:tags":[
        "woman",
        "mfg"
    ],
    "wof:name":"Hybrid Enterprises Inc",
    "wof:placetype":"venue"
},
  "geometry": {"coordinates":[-73.836831,40.714199],"type":"Point"}
}