{
  "type": "Feature",
  "properties": {
    "addr:full":"314 48th St Brooklyn NY 11220",
    "addr:housenumber":"314",
    "addr:postcode":"11220",
    "addr:street":"48Th St",
    "iso:country":"US",
    "sg:address":"314 48th St",
    "sg:city":"Brooklyn",
    "sg:classifiers":[
        {
            "category":"Building & Trades",
            "subcategory":"Construction",
            "type":"Services"
        }
    ],
    "sg:phone":"+1 718 765 1200",
    "sg:postcode":"11220",
    "sg:province":"NY",
    "sg:tags":[
        "painting",
        "drywall",
        "plastering"
    ],
    "wof:name":"Wall-Tone Painting & Finishing",
    "wof:placetype":"venue"
},
  "geometry": {"coordinates":[-74.01164900000001,40.647683],"type":"Point"}
}