{
  "type": "Feature",
  "properties": {
    "addr:full":"520 E 70th Street New York NY 10021",
    "addr:housenumber":"520",
    "addr:postcode":"10021",
    "addr:street":"E 70Th Street",
    "iso:country":"US",
    "sg:address":"520 E 70th Street",
    "sg:city":"New York",
    "sg:classifiers":[
        {
            "category":"Health Services",
            "subcategory":"Doctor",
            "type":"Services"
        }
    ],
    "sg:phone":"+1 212 746 2220",
    "sg:postcode":"10021",
    "sg:province":"NY",
    "wof:name":"Kuhel William MD",
    "wof:placetype":"venue"
},
  "geometry": {"coordinates":[-73.954404,40.765277],"type":"Point"}
}