{
  "type": "Feature",
  "properties": {
    "addr:full":"3539 White Plains Rd Bronx NY 10467",
    "addr:housenumber":"3539",
    "addr:postcode":"10467",
    "addr:street":"White Plains Rd",
    "iso:country":"US",
    "sg:address":"3539 White Plains Rd",
    "sg:city":"Bronx",
    "sg:classifiers":[
        {
            "category":"Freight",
            "type":"Transportation"
        }
    ],
    "sg:phone":"+1   ",
    "sg:postcode":"10467",
    "sg:province":"NY",
    "sg:tags":[
        "arrangement"
    ],
    "wof:name":"Laparkan Trading LTD",
    "wof:placetype":"venue"
},
  "geometry": {"coordinates":[-73.865343,40.879174],"type":"Point"}
}