{
  "type": "Feature",
  "properties": {
    "iso:country":"US",
    "sg:address":"3955 Glen Eldridge Rd",
    "sg:city":"Burdett",
    "sg:classifiers":[
        {
            "category":"Health Services",
            "subcategory":"Doctor",
            "type":"Services"
        }
    ],
    "sg:phone":"+1 607 546 2370",
    "sg:postcode":"14818",
    "sg:province":"NY",
    "sg:tags":[
        "physician",
        "surgeon"
    ],
    "wof:name":"Thomas Hanewald MD",
    "wof:placetype":"venue"
},
  "geometry": {"coordinates":[-76.867592,42.425578],"type":"Point"}
}