{
  "type": "Feature",
  "properties": {
    "iso:country":"US",
    "sg:address":"6700 Lake Ave",
    "sg:city":"Williamson",
    "sg:classifiers":[
        {
            "category":"Farming",
            "subcategory":"Orchard",
            "type":"Manufacturing & Wholesale Goods"
        }
    ],
    "sg:phone":"+1 315 589 2366",
    "sg:postcode":"14589",
    "sg:province":"NY",
    "sg:tags":[
        "farm",
        "frozen",
        "fruit",
        "packaged",
        "cherry"
    ],
    "wof:name":"J H Verbridge & Son Inc",
    "wof:placetype":"venue"
},
  "geometry": {"coordinates":[-77.186896,43.243606],"type":"Point"}
}