{
  "type": "Feature",
  "properties": {
    "iso:country":"US",
    "sg:address":"270 Cumberland St",
    "sg:city":"Rochester",
    "sg:classifiers":[
        {
            "category":"Organizations",
            "subcategory":"Religious Organization",
            "type":"Services"
        }
    ],
    "sg:phone":"+1 585 454 4175",
    "sg:postcode":"14605",
    "sg:province":"NY",
    "sg:tags":[
        "church"
    ],
    "wof:name":"Progressive Church Of God",
    "wof:placetype":"venue"
},
  "geometry": {"coordinates":[-77.60610699999999,43.161441],"type":"Point"}
}