{
  "type": "Feature",
  "properties": {
    "iso:country":"US",
    "sg:address":"90 Co Rd 60",
    "sg:city":"Cambridge",
    "sg:classifiers":[
        {
            "category":"Recreation",
            "type":"Entertainment"
        }
    ],
    "sg:phone":"+1 518 677 3545",
    "sg:postcode":"12816",
    "sg:province":"NY",
    "sg:tags":[
        "stable"
    ],
    "wof:name":"Chestnut Ridge Stables",
    "wof:placetype":"venue"
},
  "geometry": {"coordinates":[-73.45808599999999,43.006401],"type":"Point"}
}