{
  "type": "Feature",
  "properties": {
    "iso:country":"US",
    "sg:address":"1 Gifford Rd",
    "sg:city":"Schenectady",
    "sg:classifiers":[
        {
            "category":"Retail",
            "subcategory":"Auto Repair",
            "type":"Services"
        }
    ],
    "sg:phone":"+1   ",
    "sg:postcode":"12304",
    "sg:province":"NY",
    "sg:tags":[
        "general"
    ],
    "wof:name":"United Auto Clinic",
    "wof:placetype":"venue"
},
  "geometry": {"coordinates":[-73.89960499999999,42.77482],"type":"Point"}
}