{
  "type": "Feature",
  "properties": {
    "addr:full":"809 S Holmes St Schenectady NY 12302",
    "addr:housenumber":"809",
    "addr:postcode":"12302",
    "addr:street":"S Holmes St",
    "iso:country":"US",
    "sg:address":"809 S Holmes St",
    "sg:city":"Schenectady",
    "sg:classifiers":[
        {
            "category":"Building & Trades",
            "subcategory":"Electrical",
            "type":"Services"
        }
    ],
    "sg:phone":"+1 518 393 5009",
    "sg:postcode":"12302",
    "sg:province":"NY",
    "sg:tags":[
        "electric",
        "contractor"
    ],
    "wof:name":"Tech Valley Elec Constr Mntnc",
    "wof:placetype":"venue"
},
  "geometry": {"coordinates":[-73.97741000000001,42.821356],"type":"Point"}
}