{
  "type": "Feature",
  "properties": {
    "addr:full":"19 Glenridge Rd Schenectady NY 12302",
    "addr:housenumber":"19",
    "addr:postcode":"12302",
    "addr:street":"Glenridge Rd",
    "iso:country":"US",
    "sg:address":"19 Glenridge Rd",
    "sg:city":"Schenectady",
    "sg:classifiers":[
        {
            "category":"Building & Trades",
            "subcategory":"Construction",
            "type":"Services"
        }
    ],
    "sg:phone":"+1 518 688 0898",
    "sg:postcode":"12302",
    "sg:province":"NY",
    "sg:tags":[
        "planning",
        "remodeling",
        "kitchen"
    ],
    "wof:name":"Paul Perry Kitchens LLC",
    "wof:placetype":"venue"
},
  "geometry": {"coordinates":[-73.93015200000001,42.868677],"type":"Point"}
}