{
  "type": "Feature",
  "properties": {
    "addr:full":"206 W Glenville Rd Scotia NY 12302",
    "addr:housenumber":"206",
    "addr:postcode":"12302",
    "addr:street":"W Glenville Rd",
    "iso:country":"US",
    "sg:address":"206 W Glenville Rd",
    "sg:city":"Scotia",
    "sg:classifiers":[
        {
            "category":"Government",
            "subcategory":"Fire Station",
            "type":"Public Place"
        }
    ],
    "sg:phone":"+1 518 384 0137",
    "sg:postcode":"12302",
    "sg:province":"NY",
    "sg:tags":[
        "department"
    ],
    "wof:name":"West Glenville Fire Dept",
    "wof:placetype":"venue"
},
  "geometry": {"coordinates":[-74.015004,42.927443],"type":"Point"}
}