{
  "type": "Feature",
  "properties": {
    "addr:full":"500 N James St Rome NY 13440",
    "addr:housenumber":"500",
    "addr:postcode":"13440",
    "addr:street":"N James St",
    "iso:country":"US",
    "sg:address":"500 N James St",
    "sg:city":"Rome",
    "sg:classifiers":[
        {
            "category":"Restaurant",
            "type":"Food & Drink"
        }
    ],
    "sg:phone":"+1 315 336 9556",
    "sg:postcode":"13440",
    "sg:province":"NY",
    "wof:name":"Big Daddy Sandwiches Soups",
    "wof:placetype":"venue"
},
  "geometry": {"coordinates":[-75.452558,43.216077],"type":"Point"}
}