{
  "type": "Feature",
  "properties": {
    "addr:full":"12 Partyka Rd Clinton NY 13323",
    "addr:housenumber":"12",
    "addr:postcode":"13323",
    "addr:street":"Partyka Rd",
    "iso:country":"US",
    "sg:address":"12 Partyka Rd",
    "sg:city":"Clinton",
    "sg:classifiers":[
        {
            "category":"Wholesale",
            "subcategory":"Machinery & Supplies",
            "type":"Manufacturing & Wholesale Goods"
        }
    ],
    "sg:phone":"+1 315 724 3903",
    "sg:postcode":"13323",
    "sg:province":"NY",
    "sg:tags":[
        "crane",
        "derrick"
    ],
    "wof:name":"Sierson Welding & Crane Svc",
    "wof:placetype":"venue"
},
  "geometry": {"coordinates":[-75.356056,43.083718],"type":"Point"}
}