{
  "type": "Feature",
  "properties": {
    "addr:full":"2791 W 5th St Brooklyn NY 11224",
    "addr:housenumber":"2791",
    "addr:postcode":"11224",
    "addr:street":"W 5Th St",
    "iso:country":"US",
    "sg:address":"2791 W 5th St",
    "sg:city":"Brooklyn",
    "sg:classifiers":[
        {
            "category":"Health Services",
            "subcategory":"Doctor",
            "type":"Services"
        }
    ],
    "sg:phone":"+1   ",
    "sg:postcode":"11224",
    "sg:province":"NY",
    "wof:name":"Bright Smile Dental",
    "wof:placetype":"venue"
},
  "geometry": {"coordinates":[-73.97160700000001,40.580428],"type":"Point"}
}