{
  "type": "Feature",
  "properties": {
    "addr:full":"1209A Hempstead Tpke Franklin Square NY 11010",
    "addr:housenumber":"1209a",
    "addr:postcode":"11010",
    "addr:street":"Hempstead Tpke",
    "iso:country":"US",
    "sg:address":"1209A Hempstead Tpke",
    "sg:city":"Franklin Square",
    "sg:classifiers":[
        {
            "category":"Banks & Credit Unions",
            "subcategory":"Financial Services",
            "type":"Services"
        }
    ],
    "sg:phone":"+1 516 775 5212",
    "sg:postcode":"11010",
    "sg:province":"NY",
    "sg:tags":[
        "broker",
        "mortgage"
    ],
    "wof:name":"Amb Funding Corp",
    "wof:placetype":"venue"
},
  "geometry": {"coordinates":[-73.68180099999999,40.708],"type":"Point"}
}