{
  "type": "Feature",
  "properties": {
    "iso:country":"US",
    "sg:address":"99 Broadway",
    "sg:city":"Lynbrook",
    "sg:classifiers":[
        {
            "category":"Personal",
            "subcategory":"Nail Salon",
            "type":"Services"
        }
    ],
    "sg:phone":"+1 516 593 0353",
    "sg:postcode":"11563",
    "sg:province":"NY",
    "wof:name":"Jin's Nail Salon",
    "wof:placetype":"venue"
},
  "geometry": {"coordinates":[-73.6735,40.655701],"type":"Point"}
}