{
  "type": "Feature",
  "properties": {
    "addr:full":"7 Catherine St East Northport NY 11731",
    "addr:housenumber":"7",
    "addr:postcode":"11731",
    "addr:street":"Catherine St",
    "iso:country":"US",
    "sg:address":"7 Catherine St",
    "sg:city":"East Northport",
    "sg:classifiers":[
        {
            "category":"Building & Trades",
            "subcategory":"Plumbing",
            "type":"Services"
        }
    ],
    "sg:phone":"+1 631 261 0587",
    "sg:postcode":"11731",
    "sg:province":"NY",
    "sg:tags":[
        "contractor"
    ],
    "wof:name":"Carmine Alfieri",
    "wof:placetype":"venue"
},
  "geometry": {"coordinates":[-73.33526999999999,40.880897],"type":"Point"}
}