{
  "type": "Feature",
  "properties": {
    "addr:full":"122 Troy Rd East Greenbush NY 12061",
    "addr:housenumber":"122",
    "addr:postcode":"12061",
    "addr:street":"Troy Rd",
    "iso:country":"US",
    "sg:address":"122 Troy Rd",
    "sg:city":"East Greenbush",
    "sg:classifiers":[
        {
            "category":"Bars & Pubs",
            "type":"Food & Drink"
        }
    ],
    "sg:menulink":"http://www.allmenus.com/ny/east-greenbush/35261-cracker-barrel-old-country-store/menu/",
    "sg:phone":"+1 518 479 3646",
    "sg:postcode":"12061",
    "sg:province":"NY",
    "sg:tags":[
        "american",
        "southern"
    ],
    "wof:name":"Cracker Barrel Old Country Store",
    "wof:placetype":"venue"
},
  "geometry": {"coordinates":[-73.700816,42.625296],"type":"Point"}
}