{
  "type": "Feature",
  "properties": {
    "iso:country":"US",
    "sg:address":"129 E Main St",
    "sg:city":"Hornell",
    "sg:classifiers":[
        {
            "category":"Health Services",
            "subcategory":"Clinic",
            "type":"Services"
        }
    ],
    "sg:phone":"+1 607 324 0994",
    "sg:postcode":"14843",
    "sg:province":"NY",
    "sg:tags":[
        "home",
        "care"
    ],
    "wof:name":"Stuven A L C",
    "wof:placetype":"venue"
},
  "geometry": {"coordinates":[-77.646276,42.317389],"type":"Point"}
}