{
  "type": "Feature",
  "properties": {
    "iso:country":"US",
    "sg:address":"2215 Midland Ave",
    "sg:city":"Syracuse",
    "sg:classifiers":[
        {
            "category":"Real Estate",
            "subcategory":"Real Estate Agent",
            "type":"Services"
        }
    ],
    "sg:phone":"+1 315 472 7334",
    "sg:postcode":"13205",
    "sg:province":"NY",
    "sg:tags":[
        "cooperative"
    ],
    "wof:name":"Barber Service",
    "wof:placetype":"venue"
},
  "geometry": {"coordinates":[-76.14824299999999,43.017498],"type":"Point"}
}