{
  "type": "Feature",
  "properties": {
    "iso:country":"US",
    "sg:address":"224 E 204th St",
    "sg:city":"Bronx",
    "sg:classifiers":[
        {
            "category":"Health Services",
            "subcategory":"Doctor",
            "type":"Services"
        }
    ],
    "sg:phone":"+1 718 563 1209",
    "sg:postcode":"10458",
    "sg:province":"NY",
    "sg:tags":[
        "clinic"
    ],
    "wof:name":"Mac Clinic Inc",
    "wof:placetype":"venue"
},
  "geometry": {"coordinates":[-73.885615,40.874465],"type":"Point"}
}