{
  "type": "Feature",
  "properties": {
    "iso:country":"US",
    "sg:address":"12 Beechridge Ct",
    "sg:city":"Clifton Park",
    "sg:classifiers":[
        {
            "category":"Professional",
            "subcategory":"Art Services",
            "type":"Services"
        }
    ],
    "sg:phone":"+1 518 371 9658",
    "sg:postcode":"12065",
    "sg:province":"NY",
    "sg:tags":[
        "graphic",
        "designer"
    ],
    "wof:name":"Panarama Design",
    "wof:placetype":"venue"
},
  "geometry": {"coordinates":[-73.796331,42.872292],"type":"Point"}
}