{
  "type": "Feature",
  "properties": {
    "addr:full":"71-30 Roosevelt Ave Queens NY 11377",
    "addr:housenumber":"71-30",
    "addr:postcode":"11377",
    "addr:street":"Roosevelt Ave",
    "iso:country":"US",
    "sg:address":"71-30 Roosevelt Ave",
    "sg:city":"Queens",
    "sg:classifiers":[
        {
            "category":"Bars & Pubs",
            "type":"Food & Drink"
        },
        {
            "category":"Restaurant",
            "type":"Food & Drink"
        },
        {
            "category":"Bars & Pubs",
            "subcategory":"Lounge",
            "type":"Food & Drink"
        }
    ],
    "sg:phone":"+1 718 779 7912",
    "sg:postcode":"11377",
    "sg:province":"NY",
    "sg:tags":[
        "thai",
        "karaoke"
    ],
    "wof:name":"Playground Authentic Thai Cuisine",
    "wof:placetype":"venue"
},
  "geometry": {"coordinates":[-73.893781,40.746361],"type":"Point"}
}