{
  "type": "Feature",
  "properties": {
    "iso:country":"US",
    "sg:address":"37 W Islip Rd",
    "sg:city":"West Islip",
    "sg:classifiers":[
        {
            "category":"Farming",
            "subcategory":"Fish & Marine Products",
            "type":"Manufacturing & Wholesale Goods"
        }
    ],
    "sg:phone":"+1 631 661 4010",
    "sg:postcode":"11795",
    "sg:province":"NY",
    "sg:tags":[
        "fisherman"
    ],
    "wof:name":"Captain Jacks LLC",
    "wof:placetype":"venue"
},
  "geometry": {"coordinates":[-73.315586,40.688549],"type":"Point"}
}