{
  "type": "Feature",
  "properties": {
    "iso:country":"US",
    "sg:address":"40 E Main St",
    "sg:city":"Malone",
    "sg:classifiers":[
        {
            "category":"Restaurant",
            "type":"Food & Drink"
        }
    ],
    "sg:phone":"+1 518 483 8007",
    "sg:postcode":"12953",
    "sg:province":"NY",
    "wof:name":"Napolis Pizza",
    "wof:placetype":"venue"
},
  "geometry": {"coordinates":[-74.29141799999999,44.84891],"type":"Point"}
}