{
  "type": "Feature",
  "properties": {
    "addr:full":"33 Harrison St Johnson City NY 13790",
    "addr:housenumber":"33",
    "addr:postcode":"13790",
    "addr:street":"Harrison St",
    "iso:country":"US",
    "sg:address":"33 Harrison St",
    "sg:city":"Johnson City",
    "sg:classifiers":[
        {
            "category":"Health Services",
            "subcategory":"Medical Lab",
            "type":"Services"
        }
    ],
    "sg:phone":"+1 607 763 6151",
    "sg:postcode":"13790",
    "sg:province":"NY",
    "sg:tags":[
        "laboratory"
    ],
    "wof:name":"UHS Hospitals Laboratories",
    "wof:placetype":"venue"
},
  "geometry": {"coordinates":[-75.959074,42.114749],"type":"Point"}
}