{
  "type": "Feature",
  "properties": {
    "iso:country":"US",
    "sg:address":"110 Roxbury Pk",
    "sg:city":"East Amherst",
    "sg:classifiers":[
        {
            "category":"Insurance",
            "subcategory":"Hazard Insurance",
            "type":"Services"
        }
    ],
    "sg:phone":"+1 716 634 7521",
    "sg:postcode":"14051",
    "sg:province":"NY",
    "sg:tags":[
        "bond"
    ],
    "wof:name":"Amherst Bail Bonds",
    "wof:placetype":"venue"
},
  "geometry": {"coordinates":[-78.71430700000001,43.005744],"type":"Point"}
}