{
  "type": "Feature",
  "properties": {
    "addr:full":"333 Georgia Ave Brooklyn NY 11207",
    "addr:housenumber":"333",
    "addr:postcode":"11207",
    "addr:street":"Georgia Ave",
    "iso:country":"US",
    "sg:address":"333 Georgia Ave",
    "sg:city":"Brooklyn",
    "sg:classifiers":[
        {
            "category":"Personal",
            "subcategory":"Beauty Salon",
            "type":"Services"
        }
    ],
    "sg:phone":"+1 718 922 5923",
    "sg:postcode":"11207",
    "sg:province":"NY",
    "sg:tags":[
        "manicuring"
    ],
    "wof:name":"Rab's Nails",
    "wof:placetype":"venue"
},
  "geometry": {"coordinates":[-73.896736,40.668112],"type":"Point"}
}