{
  "type": "Feature",
  "properties": {
    "addr:full":"181 Roweland Ave Delmar NY 12054",
    "addr:housenumber":"181",
    "addr:postcode":"12054",
    "addr:street":"Roweland Ave",
    "iso:country":"US",
    "sg:address":"181 Roweland Ave",
    "sg:city":"Delmar",
    "sg:classifiers":[
        {
            "category":"Shopping",
            "subcategory":"Bicycles & Sporting Goods",
            "type":"Retail Goods"
        }
    ],
    "sg:phone":"+1   ",
    "sg:postcode":"12054",
    "sg:province":"NY",
    "wof:name":"Mad Dog Specialty Bicycles",
    "wof:placetype":"venue"
},
  "geometry": {"coordinates":[-73.827856,42.610333],"type":"Point"}
}