{
  "type": "Feature",
  "properties": {
    "iso:country":"US",
    "sg:address":"105 Page Ave",
    "sg:city":"Staten Island",
    "sg:classifiers":[
        {
            "category":"Sports & Exercise",
            "subcategory":"Gym",
            "type":"Entertainment"
        }
    ],
    "sg:phone":"+1 718 966 9642",
    "sg:postcode":"10309",
    "sg:province":"NY",
    "sg:tags":[
        "yoga"
    ],
    "wof:name":"Yoga South",
    "wof:placetype":"venue"
},
  "geometry": {"coordinates":[-74.234818,40.522155],"type":"Point"}
}