{
  "type": "Feature",
  "properties": {
    "iso:country":"US",
    "sg:address":"77 Buffalo Ave",
    "sg:city":"Freeport",
    "sg:classifiers":[
        {
            "category":"Retail",
            "subcategory":"Auto Repair",
            "type":"Services"
        }
    ],
    "sg:phone":"+1 516 223 2303",
    "sg:postcode":"11520",
    "sg:province":"NY",
    "sg:tags":[
        "body",
        "automobile",
        "painting"
    ],
    "wof:name":"Collision King Nassau County",
    "wof:placetype":"venue"
},
  "geometry": {"coordinates":[-73.570925,40.650169],"type":"Point"}
}