{
  "type": "Feature",
  "properties": {
    "addr:full":"515 Court St Brooklyn NY 11231",
    "addr:housenumber":"515",
    "addr:postcode":"11231",
    "addr:street":"Court St",
    "iso:country":"US",
    "sg:address":"515 Court St",
    "sg:city":"Brooklyn",
    "sg:classifiers":[
        {
            "category":"Arts & Performance",
            "subcategory":"Arts Center",
            "type":"Entertainment"
        },
        {
            "category":"Education",
            "subcategory":"School",
            "type":"Public Place"
        }
    ],
    "sg:postcode":"11231",
    "sg:province":"NY",
    "sg:website":"brooklynbrainery.com",
    "wof:name":"Brooklyn Brainery",
    "wof:placetype":"venue"
},
  "geometry": {"coordinates":[-73.99914200000001,40.675218],"type":"Point"}
}