{
  "type": "Feature",
  "properties": {
    "iso:country":"US",
    "sg:address":"45 Research Way",
    "sg:city":"East Setauket",
    "sg:classifiers":[
        {
            "category":"Banks & Credit Unions",
            "subcategory":"Investment Brokerage",
            "type":"Services"
        }
    ],
    "sg:phone":"+1 631 941 0200",
    "sg:postcode":"11733",
    "sg:province":"NY",
    "sg:tags":[
        "consultant",
        "planning",
        "financial"
    ],
    "wof:name":"SMTB Financial Group",
    "wof:placetype":"venue"
},
  "geometry": {"coordinates":[-73.08730300000001,40.903263],"type":"Point"}
}