{
  "type": "Feature",
  "properties": {
    "addr:full":"599 Edgewood Dr Westbury NY 11590",
    "addr:housenumber":"599",
    "addr:postcode":"11590",
    "addr:street":"Edgewood Dr",
    "iso:country":"US",
    "sg:address":"599 Edgewood Dr",
    "sg:city":"Westbury",
    "sg:classifiers":[
        {
            "category":"Building & Trades",
            "subcategory":"Plumbing",
            "type":"Services"
        }
    ],
    "sg:phone":"+1 516 997 2826",
    "sg:postcode":"11590",
    "sg:province":"NY",
    "sg:tags":[
        "system",
        "contractor",
        "air conditioning"
    ],
    "wof:name":"Dun-Rite A Condtioning Htg Co",
    "wof:placetype":"venue"
},
  "geometry": {"coordinates":[-73.56648300000001,40.75108],"type":"Point"}
}