{
  "type": "Feature",
  "properties": {
    "iso:country":"US",
    "sg:address":"268 Central Ave",
    "sg:city":"Albany",
    "sg:classifiers":[
        {
            "category":"Professional",
            "subcategory":"Art Services",
            "type":"Services"
        }
    ],
    "sg:phone":"+1 518 449 3066",
    "sg:postcode":"12206",
    "sg:province":"NY",
    "sg:tags":[
        "graphic",
        "commercial",
        "designer",
        "artist"
    ],
    "wof:name":"Graphic Techniques Incorporated",
    "wof:placetype":"venue"
},
  "geometry": {"coordinates":[-73.771508,42.663901],"type":"Point"}
}