{
  "type": "Feature",
  "properties": {
    "addr:full":"160 E 56th St New York NY 10022",
    "addr:housenumber":"160",
    "addr:postcode":"10022",
    "addr:street":"E 56Th St",
    "iso:country":"US",
    "sg:address":"160 E 56th St",
    "sg:city":"New York",
    "sg:classifiers":[
        {
            "category":"Health Services",
            "subcategory":"Optometrist",
            "type":"Services"
        },
        {
            "category":"Health Services",
            "subcategory":"Doctor",
            "type":"Services"
        }
    ],
    "sg:phone":"+1 212 758 3838",
    "sg:postcode":"10022",
    "sg:province":"NY",
    "wof:name":"Vista Alliance",
    "wof:placetype":"venue"
},
  "geometry": {"coordinates":[-73.964996,40.7575],"type":"Point"}
}