{
  "type": "Feature",
  "properties": {
    "addr:full":"3560 Broadway New York NY 10031",
    "addr:housenumber":"3560",
    "addr:postcode":"10031",
    "addr:street":"Broadway",
    "iso:country":"US",
    "sg:address":"3560 Broadway",
    "sg:city":"New York",
    "sg:classifiers":[
        {
            "category":"Home & Garden",
            "subcategory":"Household Appliances",
            "type":"Retail Goods"
        },
        {
            "category":"Home & Garden",
            "subcategory":"Home Furnishings",
            "type":"Retail Goods"
        },
        {
            "category":"Home & Garden",
            "subcategory":"Furniture",
            "type":"Retail Goods"
        }
    ],
    "sg:postcode":"10031",
    "sg:province":"NY",
    "sg:tags":[
        "kitchen",
        "store",
        "bath"
    ],
    "wof:name":"Hamilton Palace",
    "wof:placetype":"venue"
},
  "geometry": {"coordinates":[-73.949799,40.827099],"type":"Point"}
}