{
  "type": "Feature",
  "properties": {
    "addr:full":"115 Fulton St New York NY 10038",
    "addr:housenumber":"115",
    "addr:postcode":"10038",
    "addr:street":"Fulton St",
    "iso:country":"US",
    "sg:address":"115 Fulton St",
    "sg:city":"New York",
    "sg:classifiers":[
        {
            "category":"Professional",
            "subcategory":"Research",
            "type":"Services"
        }
    ],
    "sg:phone":"+1 212 871 0839",
    "sg:postcode":"10038",
    "sg:province":"NY",
    "sg:tags":[
        "development",
        "marketing",
        "product"
    ],
    "wof:name":"Advent Product Development",
    "wof:placetype":"venue"
},
  "geometry": {"coordinates":[-74.006602,40.709659],"type":"Point"}
}