{
  "type": "Feature",
  "properties": {
    "iso:country":"US",
    "sg:address":"1 Comus Rd",
    "sg:city":"Rocky Point",
    "sg:classifiers":[
        {
            "category":"Building & Trades",
            "subcategory":"Construction",
            "type":"Services"
        }
    ],
    "sg:phone":"+1 631 821 3746",
    "sg:postcode":"11778",
    "sg:province":"NY",
    "sg:tags":[
        "contractor"
    ],
    "wof:name":"RVK Contracting",
    "wof:placetype":"venue"
},
  "geometry": {"coordinates":[-72.91614199999999,40.950351],"type":"Point"}
}