{
  "type": "Feature",
  "properties": {
    "iso:country":"US",
    "sg:address":"206 Eden St",
    "sg:city":"Buffalo",
    "sg:classifiers":[
        {
            "category":"Wholesale",
            "subcategory":"Machinery & Supplies",
            "type":"Manufacturing & Wholesale Goods"
        }
    ],
    "sg:phone":"+1 716 824 4663",
    "sg:postcode":"14220",
    "sg:province":"NY",
    "sg:tags":[
        "equipment",
        "pump",
        "industrial"
    ],
    "wof:name":"Rochester Industrial Supply Co",
    "wof:placetype":"venue"
},
  "geometry": {"coordinates":[-78.823599,42.836454],"type":"Point"}
}