{
  "type": "Feature",
  "properties": {
    "addr:full":"1088 Central Park Ave Scarsdale NY 10583",
    "addr:housenumber":"1088",
    "addr:postcode":"10583",
    "addr:street":"Central Park Ave",
    "iso:country":"US",
    "sg:address":"1088 Central Park Ave",
    "sg:city":"Scarsdale",
    "sg:classifiers":[
        {
            "category":"Banks & Credit Unions",
            "subcategory":"Bank",
            "type":"Services"
        }
    ],
    "sg:phone":"+1 914 723 1638",
    "sg:postcode":"10583",
    "sg:province":"NY",
    "sg:tags":[
        "loan",
        "real estate"
    ],
    "wof:name":"Countrywide Home Loans",
    "wof:placetype":"venue"
},
  "geometry": {"coordinates":[-73.81926199999999,40.994587],"type":"Point"}
}