{
  "type": "Feature",
  "properties": {
    "iso:country":"US",
    "sg:address":"57 W 8th Street",
    "sg:city":"New York",
    "sg:classifiers":[
        {
            "category":"Shopping",
            "subcategory":"Shoes",
            "type":"Retail Goods"
        }
    ],
    "sg:phone":"+1 212 253 5012",
    "sg:postcode":"10011",
    "sg:province":"NY",
    "sg:tags":[
        "store"
    ],
    "sg:website":"www.sagashoes.com",
    "wof:name":"Saga Fine Shoes",
    "wof:placetype":"venue"
},
  "geometry": {"coordinates":[-73.99887099999999,40.733516],"type":"Point"}
}