{
  "type": "Feature",
  "properties": {
    "iso:country":"US",
    "sg:address":"6202 16th Ave",
    "sg:city":"Brooklyn",
    "sg:classifiers":[
        {
            "category":"Social Services",
            "subcategory":"Child Care",
            "type":"Services"
        }
    ],
    "sg:phone":"+1   ",
    "sg:postcode":"11204",
    "sg:province":"NY",
    "sg:tags":[
        "residential",
        "day"
    ],
    "wof:name":"Adult Day Health Center",
    "wof:placetype":"venue"
},
  "geometry": {"coordinates":[-73.99375999999999,40.623214],"type":"Point"}
}