{
  "type": "Feature",
  "properties": {
    "iso:country":"US",
    "sg:address":"387 Church St",
    "sg:city":"Saratoga Springs",
    "sg:classifiers":[
        {
            "category":"Professional",
            "type":"Services"
        }
    ],
    "sg:phone":"+1 518 583 2177",
    "sg:postcode":"12866",
    "sg:province":"NY",
    "sg:tags":[
        "establishment"
    ],
    "wof:name":"Imagine Hand Painted Murals",
    "wof:placetype":"venue"
},
  "geometry": {"coordinates":[-73.820425,43.086676],"type":"Point"}
}