{
  "type": "Feature",
  "properties": {
    "iso:country":"US",
    "sg:address":"78 Main St",
    "sg:city":"Sayville",
    "sg:classifiers":[
        {
            "category":"Shopping",
            "subcategory":"Bicycles & Sporting Goods",
            "type":"Retail Goods"
        },
        {
            "category":"Shopping",
            "subcategory":"Clothing, Apparel, & Fashions",
            "type":"Retail Goods"
        }
    ],
    "sg:phone":"+1 631 244 7669",
    "sg:postcode":"11782",
    "sg:province":"NY",
    "sg:tags":[
        "merchandise",
        "store",
        "general"
    ],
    "wof:name":"Kelley Boys Surf & Sport Ltd",
    "wof:placetype":"venue"
},
  "geometry": {"coordinates":[-73.084541,40.734862],"type":"Point"}
}