{
  "type": "Feature",
  "properties": {
    "addr:full":"7414 Colonial Rd Brooklyn NY 11209",
    "addr:housenumber":"7414",
    "addr:postcode":"11209",
    "addr:street":"Colonial Rd",
    "iso:country":"US",
    "sg:address":"7414 Colonial Rd",
    "sg:city":"Brooklyn",
    "sg:classifiers":[
        {
            "category":"Retail",
            "subcategory":"Repair Shop",
            "type":"Services"
        }
    ],
    "sg:phone":"+1 718 791 6069",
    "sg:postcode":"11209",
    "sg:province":"NY",
    "wof:name":"Somarc",
    "wof:placetype":"venue"
},
  "geometry": {"coordinates":[-74.033196,40.632856],"type":"Point"}
}