{
  "type": "Feature",
  "properties": {
    "iso:country":"US",
    "sg:address":"31 Upper Sheep Pasture Rd",
    "sg:city":"Setauket",
    "sg:classifiers":[
        {
            "category":"Health Services",
            "subcategory":"Health Practitioner",
            "type":"Services"
        }
    ],
    "sg:phone":"+1 631 751 5880",
    "sg:postcode":"11733",
    "sg:province":"NY",
    "sg:tags":[
        "pathologist",
        "speech"
    ],
    "wof:name":"Three Village Speech",
    "wof:placetype":"venue"
},
  "geometry": {"coordinates":[-73.10047400000001,40.918625],"type":"Point"}
}