{
  "type": "Feature",
  "properties": {
    "iso:country":"US",
    "sg:address":"415 84th St",
    "sg:city":"Brooklyn",
    "sg:classifiers":[
        {
            "category":"Banks & Credit Unions",
            "subcategory":"Investment Brokerage",
            "type":"Services"
        }
    ],
    "sg:phone":"+1 718 748 2646",
    "sg:postcode":"11209",
    "sg:province":"NY",
    "sg:tags":[
        "security"
    ],
    "wof:name":"Awan Estates",
    "wof:placetype":"venue"
},
  "geometry": {"coordinates":[-74.02555700000001,40.623124],"type":"Point"}
}