{
  "type": "Feature",
  "properties": {
    "iso:country":"US",
    "sg:address":"24 Sterlington Commons",
    "sg:city":"Greenport",
    "sg:classifiers":[
        {
            "category":"Social Services",
            "type":"Services"
        },
        {
            "category":"Health Services",
            "subcategory":"Clinic",
            "type":"Services"
        },
        {
            "category":"Personal",
            "type":"Services"
        }
    ],
    "sg:phone":"+1 631 477 4067",
    "sg:postcode":"11944",
    "sg:province":"NY",
    "sg:tags":[
        "information",
        "mental",
        "family",
        "counselors-licensed",
        "individual",
        "marriage",
        "child",
        "professional",
        "counselor"
    ],
    "wof:name":"Family Service League",
    "wof:placetype":"venue"
},
  "geometry": {"coordinates":[-72.363595,41.100972],"type":"Point"}
}