{
  "type": "Feature",
  "properties": {
    "iso:country":"US",
    "sg:address":"6029 Jericho Tpke",
    "sg:city":"Commack",
    "sg:classifiers":[
        {
            "category":"Restaurant",
            "type":"Food & Drink"
        }
    ],
    "sg:menulink":"http://www.allmenus.com/ny/huntington/64064-tian-tian-buffet/menu/",
    "sg:phone":"+1 631 462 0805",
    "sg:postcode":"11725",
    "sg:province":"NY",
    "sg:tags":[
        "asian",
        "chinese"
    ],
    "wof:name":"Tian Tian Buffet",
    "wof:placetype":"venue"
},
  "geometry": {"coordinates":[-73.306517,40.841419],"type":"Point"}
}