{
  "type": "Feature",
  "properties": {
    "addr:full":"5862 Lake Ave Orchard Park NY 14127",
    "addr:housenumber":"5862",
    "addr:postcode":"14127",
    "addr:street":"Lake Ave",
    "iso:country":"US",
    "sg:address":"5862 Lake Ave",
    "sg:city":"Orchard Park",
    "sg:classifiers":[
        {
            "category":"Building & Trades",
            "subcategory":"Landscaping Services",
            "type":"Services"
        }
    ],
    "sg:phone":"+1 716 662 3462",
    "sg:postcode":"14127",
    "sg:province":"NY",
    "sg:tags":[
        "landscape",
        "contractor"
    ],
    "wof:name":"Total Landscape Services",
    "wof:placetype":"venue"
},
  "geometry": {"coordinates":[-78.769048,42.79652],"type":"Point"}
}