{
  "type": "Feature",
  "properties": {
    "addr:full":"7624 15th Ave Brooklyn NY 11228",
    "addr:housenumber":"7624",
    "addr:postcode":"11228",
    "addr:street":"15Th Ave",
    "iso:country":"US",
    "sg:address":"7624 15th Ave",
    "sg:city":"Brooklyn",
    "sg:classifiers":[
        {
            "category":"Retail",
            "subcategory":"Repair Shop",
            "type":"Services"
        }
    ],
    "sg:phone":"+1 718 236 7718",
    "sg:postcode":"11228",
    "sg:province":"NY",
    "sg:tags":[
        "machine",
        "electrical"
    ],
    "wof:name":"Accurate Appliance Repair Inc",
    "wof:placetype":"venue"
},
  "geometry": {"coordinates":[-74.00418500000001,40.616665],"type":"Point"}
}