{
  "type": "Feature",
  "properties": {
    "iso:country":"US",
    "sg:address":"2 W 46 St",
    "sg:city":"New York",
    "sg:classifiers":[
        {
            "category":"Travel",
            "subcategory":"Travel Agent",
            "type":"Entertainment"
        }
    ],
    "sg:phone":"+1   ",
    "sg:postcode":"10036",
    "sg:province":"NY",
    "wof:name":"Accent On Travel",
    "wof:placetype":"venue"
},
  "geometry": {"coordinates":[-73.98225499999999,40.757387],"type":"Point"}
}