{
  "type": "Feature",
  "properties": {
    "addr:full":"76 Willoughby St Brooklyn NY 11201",
    "addr:housenumber":"76",
    "addr:postcode":"11201",
    "addr:street":"Willoughby St",
    "iso:country":"US",
    "sg:address":"76 Willoughby St",
    "sg:city":"Brooklyn",
    "sg:classifiers":[
        {
            "category":"Shopping",
            "subcategory":"Jewelry",
            "type":"Retail Goods"
        }
    ],
    "sg:phone":"+1 718 422 0072",
    "sg:postcode":"11201",
    "sg:province":"NY",
    "sg:tags":[
        "stone",
        "metal",
        "precious"
    ],
    "wof:name":"Estells Fine Jewelry",
    "wof:placetype":"venue"
},
  "geometry": {"coordinates":[-73.985703,40.692101],"type":"Point"}
}