{
  "type": "Feature",
  "properties": {
    "addr:full":"400 Lorimer St Brooklyn NY 11206",
    "addr:housenumber":"400",
    "addr:postcode":"11206",
    "addr:street":"Lorimer St",
    "iso:country":"US",
    "sg:address":"400 Lorimer St",
    "sg:city":"Brooklyn",
    "sg:classifiers":[
        {
            "category":"Food & Beverages",
            "subcategory":"Groceries & Convenience Stores",
            "type":"Retail Goods"
        }
    ],
    "sg:phone":"+1 718 486 7809",
    "sg:postcode":"11206",
    "sg:province":"NY",
    "wof:name":"Los Compadres Grocery",
    "wof:placetype":"venue"
},
  "geometry": {"coordinates":[-73.948502,40.708698],"type":"Point"}
}