{
  "type": "Feature",
  "properties": {
    "addr:full":"1040 Pelhamdale Ave Pelham NY 10803",
    "addr:housenumber":"1040",
    "addr:postcode":"10803",
    "addr:street":"Pelhamdale Ave",
    "iso:country":"US",
    "sg:address":"1040 Pelhamdale Ave",
    "sg:city":"Pelham",
    "sg:classifiers":[
        {
            "category":"Professional",
            "type":"Services"
        }
    ],
    "sg:phone":"+1   ",
    "sg:postcode":"10803",
    "sg:province":"NY",
    "wof:name":"Lindlan Co Inc",
    "wof:placetype":"venue"
},
  "geometry": {"coordinates":[-73.801654,40.892138],"type":"Point"}
}