{
  "type": "Feature",
  "properties": {
    "iso:country":"US",
    "sg:address":"180 Ridge St",
    "sg:city":"Glens Falls",
    "sg:classifiers":[
        {
            "category":"Shopping",
            "subcategory":"Used Merchandise",
            "type":"Retail Goods"
        }
    ],
    "sg:phone":"+1   ",
    "sg:postcode":"12801",
    "sg:province":"NY",
    "wof:name":"Antique Arcade",
    "wof:placetype":"venue"
},
  "geometry": {"coordinates":[-73.643557,43.317039],"type":"Point"}
}