{
  "type": "Feature",
  "properties": {
    "iso:country":"US",
    "sg:address":"260 Mountaindale Rd",
    "sg:city":"Yonkers",
    "sg:classifiers":[
        {
            "category":"Building & Trades",
            "subcategory":"Construction",
            "type":"Services"
        }
    ],
    "sg:phone":"+1 914 793 1011",
    "sg:postcode":"10710",
    "sg:province":"NY",
    "sg:tags":[
        "hanging",
        "contractor"
    ],
    "wof:name":"Home Time",
    "wof:placetype":"venue"
},
  "geometry": {"coordinates":[-73.847606,40.962123],"type":"Point"}
}