{
  "type": "Feature",
  "properties": {
    "iso:country":"US",
    "sg:address":"1095 Hamlin Parma Tl Rd",
    "sg:city":"Hilton",
    "sg:classifiers":[
        {
            "category":"Retail",
            "subcategory":"Auto Repair",
            "type":"Services"
        }
    ],
    "sg:phone":"+1 585 392 4880",
    "sg:postcode":"14468",
    "sg:province":"NY",
    "sg:tags":[
        "repairing",
        "automobile"
    ],
    "sg:website":"www.bobkaisersrepair.com",
    "wof:name":"Bob Kaiser's Repair Inc",
    "wof:placetype":"venue"
},
  "geometry": {"coordinates":[-77.82459,43.306182],"type":"Point"}
}