{
  "type": "Feature",
  "properties": {
    "iso:country":"US",
    "sg:address":"811 W Jericho Tpke",
    "sg:city":"Smithtown",
    "sg:classifiers":[
        {
            "category":"Insurance",
            "subcategory":"Insurance Agent",
            "type":"Services"
        }
    ],
    "sg:phone":"+1 631 979 1919",
    "sg:postcode":"11787",
    "sg:province":"NY",
    "wof:name":"John J Glennon Inc",
    "wof:placetype":"venue"
},
  "geometry": {"coordinates":[-73.248205,40.848352],"type":"Point"}
}