{
  "type": "Feature",
  "properties": {
    "addr:full":"1060 Beach 20th St Far Rockaway NY 11691",
    "addr:housenumber":"1060",
    "addr:postcode":"11691",
    "addr:street":"Beach 20Th St",
    "iso:country":"US",
    "sg:address":"1060 Beach 20th St",
    "sg:city":"Far Rockaway",
    "sg:classifiers":[
        {
            "category":"Shopping",
            "subcategory":"Clothing, Apparel, & Fashions",
            "type":"Retail Goods"
        }
    ],
    "sg:phone":"+1 718 327 8535",
    "sg:postcode":"11691",
    "sg:province":"NY",
    "sg:tags":[
        "accessory",
        "clothing",
        "women's"
    ],
    "wof:name":"D' Jeannette Boutique",
    "wof:placetype":"venue"
},
  "geometry": {"coordinates":[-73.75287,40.603433],"type":"Point"}
}