{
  "type": "Feature",
  "properties": {
    "iso:country":"US",
    "sg:address":"798 Old Rte 9",
    "sg:city":"Fishkill",
    "sg:classifiers":[
        {
            "category":"Professional",
            "subcategory":"Accounting & Tax Preparation",
            "type":"Services"
        }
    ],
    "sg:phone":"+1 845 897 2570",
    "sg:postcode":"12524",
    "sg:province":"NY",
    "sg:tags":[
        "accountant",
        "auditing",
        "bookkeeping"
    ],
    "wof:name":"Andre Moglia & Co",
    "wof:placetype":"venue"
},
  "geometry": {"coordinates":[-73.901173,41.551148],"type":"Point"}
}