{
  "type": "Feature",
  "properties": {
    "addr:full":"20 Hanford Ln New Canaan NY 06840",
    "addr:housenumber":"20",
    "addr:postcode":"06840",
    "addr:street":"Hanford Ln",
    "iso:country":"US",
    "sg:address":"20 Hanford Ln",
    "sg:city":"New Canaan",
    "sg:classifiers":[
        {
            "category":"Health Services",
            "subcategory":"Doctor",
            "type":"Services"
        }
    ],
    "sg:phone":"+1   ",
    "sg:postcode":"06840",
    "sg:province":"NY",
    "sg:tags":[
        "medical"
    ],
    "wof:name":"Chun Ryo Sook Dr",
    "wof:placetype":"venue"
},
  "geometry": {"coordinates":[-73.513116,41.138378],"type":"Point"}
}