{
  "type": "Feature",
  "properties": {
    "iso:country":"US",
    "sg:address":"7615 Easton St",
    "sg:city":"Lowville",
    "sg:classifiers":[
        {
            "category":"Social Services",
            "type":"Services"
        }
    ],
    "sg:phone":"+1 315 376 9475",
    "sg:postcode":"13367",
    "sg:province":"NY",
    "sg:tags":[
        "organization",
        "welfare"
    ],
    "wof:name":"Chase House",
    "wof:placetype":"venue"
},
  "geometry": {"coordinates":[-75.49781400000001,43.786569],"type":"Point"}
}