{
  "type": "Feature",
  "properties": {
    "addr:full":"250 Riverside Dr New York NY 10025",
    "addr:housenumber":"250",
    "addr:postcode":"10025",
    "addr:street":"Riverside Dr",
    "iso:country":"US",
    "sg:address":"250 Riverside Dr",
    "sg:city":"New York",
    "sg:classifiers":[
        {
            "category":"Professional",
            "subcategory":"Art Services",
            "type":"Services"
        }
    ],
    "sg:phone":"+1   ",
    "sg:postcode":"10025",
    "sg:province":"NY",
    "sg:tags":[
        "commercial",
        "design"
    ],
    "wof:name":"Dixie Reinhardt Designs",
    "wof:placetype":"venue"
},
  "geometry": {"coordinates":[-73.97365000000001,40.797149],"type":"Point"}
}