{
  "type": "Feature",
  "properties": {
    "addr:full":"50 E 42nd Street New York NY 10017",
    "addr:housenumber":"50",
    "addr:postcode":"10017",
    "addr:street":"E 42Nd Street",
    "iso:country":"US",
    "sg:address":"50 E 42nd Street",
    "sg:city":"New York",
    "sg:classifiers":[
        {
            "category":"Health Services",
            "subcategory":"Doctor",
            "type":"Services"
        }
    ],
    "sg:phone":"+1 212 599 2900",
    "sg:postcode":"10017",
    "sg:province":"NY",
    "wof:name":"Kelwin Group",
    "wof:placetype":"venue"
},
  "geometry": {"coordinates":[-73.97896799999999,40.752537],"type":"Point"}
}