{
  "type": "Feature",
  "properties": {
    "addr:full":"600 Washington Str New York NY 10014",
    "addr:housenumber":"600",
    "addr:postcode":"10014",
    "addr:street":"Washington Str",
    "iso:country":"US",
    "sg:address":"600 Washington Str",
    "sg:city":"New York",
    "sg:classifiers":[
        {
            "category":"Real Estate",
            "subcategory":"Real Estate Operator",
            "type":"Services"
        }
    ],
    "sg:phone":"+1 212 206 3824",
    "sg:postcode":"10014",
    "sg:province":"NY",
    "sg:tags":[
        "apartment"
    ],
    "sg:website":"www.equityapartments.com/new-yor...",
    "wof:name":"600 Washington",
    "wof:placetype":"venue"
},
  "geometry": {"coordinates":[-74.009067,40.730629],"type":"Point"}
}