{
  "type": "Feature",
  "properties": {
    "addr:full":"351 College Ave Elmira NY 14901",
    "addr:housenumber":"351",
    "addr:postcode":"14901",
    "addr:street":"College Ave",
    "iso:country":"US",
    "sg:address":"351 College Ave",
    "sg:city":"Elmira",
    "sg:classifiers":[
        {
            "category":"Shopping",
            "subcategory":"Jewelry",
            "type":"Retail Goods"
        }
    ],
    "sg:phone":"+1 607 733 1300",
    "sg:postcode":"14901",
    "sg:province":"NY",
    "sg:tags":[
        "jeweler"
    ],
    "wof:name":"Weaver Goldsmithing",
    "wof:placetype":"venue"
},
  "geometry": {"coordinates":[-76.810947,42.090685],"type":"Point"}
}