{
  "type": "Feature",
  "properties": {
    "addr:full":"1065 Culver Rd Rochester NY 14609",
    "addr:housenumber":"1065",
    "addr:postcode":"14609",
    "addr:street":"Culver Rd",
    "iso:country":"US",
    "sg:address":"1065 Culver Rd",
    "sg:city":"Rochester",
    "sg:classifiers":[
        {
            "category":"Retail",
            "subcategory":"Auto Repair",
            "type":"Services"
        }
    ],
    "sg:phone":"+1 585 288 4770",
    "sg:postcode":"14609",
    "sg:province":"NY",
    "sg:tags":[
        "repairing",
        "automobile"
    ],
    "wof:name":"J & H Automotive Svc Ctr",
    "wof:placetype":"venue"
},
  "geometry": {"coordinates":[-77.563834,43.164205],"type":"Point"}
}