{
  "type": "Feature",
  "properties": {
    "addr:full":"1875 Park Ave New York NY 10035",
    "addr:housenumber":"1875",
    "addr:postcode":"10035",
    "addr:street":"Park Ave",
    "iso:country":"US",
    "sg:address":"1875 Park Ave",
    "sg:city":"New York",
    "sg:classifiers":[
        {
            "category":"Freight",
            "type":"Transportation"
        }
    ],
    "sg:phone":"+1 212 247 6683",
    "sg:postcode":"10035",
    "sg:province":"NY",
    "sg:tags":[
        "mover"
    ],
    "sg:website":"www.galil.com",
    "wof:name":"Galil Moving & Storage Inc",
    "wof:placetype":"venue"
},
  "geometry": {"coordinates":[-73.93787,40.806395],"type":"Point"}
}