{
  "type": "Feature",
  "properties": {
    "addr:full":"5861 Thompson Rd Syracuse NY 13214",
    "addr:housenumber":"5861",
    "addr:postcode":"13214",
    "addr:street":"Thompson Rd",
    "iso:country":"US",
    "sg:address":"5861 Thompson Rd",
    "sg:city":"Syracuse",
    "sg:classifiers":[
        {
            "category":"Wholesale",
            "subcategory":"Machinery & Supplies",
            "type":"Manufacturing & Wholesale Goods"
        }
    ],
    "sg:phone":"+1 315 449 8400",
    "sg:postcode":"13214",
    "sg:province":"NY",
    "sg:tags":[
        "salon",
        "beauty"
    ],
    "wof:name":"Royal Beauty Supply",
    "wof:placetype":"venue"
},
  "geometry": {"coordinates":[-76.082094,43.053651],"type":"Point"}
}