{
  "type": "Feature",
  "properties": {
    "addr:full":"499 Deer Park Ave Babylon NY 11702",
    "addr:housenumber":"499",
    "addr:postcode":"11702",
    "addr:street":"Deer Park Ave",
    "iso:country":"US",
    "sg:address":"499 Deer Park Ave",
    "sg:city":"Babylon",
    "sg:classifiers":[
        {
            "category":"Health Services",
            "subcategory":"Health Practitioner",
            "type":"Services"
        }
    ],
    "sg:phone":"+1 631 376 2492",
    "sg:postcode":"11702",
    "sg:province":"NY",
    "sg:tags":[
        "acupuncture"
    ],
    "wof:name":"Balance Health & Wellness Ctr",
    "wof:placetype":"venue"
},
  "geometry": {"coordinates":[-73.322011,40.705463],"type":"Point"}
}