{
  "type": "Feature",
  "properties": {
    "iso:country":"US",
    "sg:address":"722 Shore Rd",
    "sg:city":"Lindenhurst",
    "sg:classifiers":[
        {
            "category":"Restaurant",
            "type":"Food & Drink"
        }
    ],
    "sg:phone":"+1 631 225 1717",
    "sg:postcode":"11757",
    "sg:province":"NY",
    "sg:tags":[
        "caterer"
    ],
    "wof:name":"Hogan's Delicatessens",
    "wof:placetype":"venue"
},
  "geometry": {"coordinates":[-73.366272,40.671828],"type":"Point"}
}