{
  "type": "Feature",
  "properties": {
    "addr:full":"RR 9 Athens NY 12015",
    "addr:postcode":"12015",
    "addr:street":"Rr 9",
    "iso:country":"US",
    "sg:address":"RR 9",
    "sg:city":"Athens",
    "sg:classifiers":[
        {
            "category":"Autos & Motor Vehicles",
            "subcategory":"Auto Supplies",
            "type":"Retail Goods"
        }
    ],
    "sg:phone":"+1 518 945 2780",
    "sg:postcode":"12015",
    "sg:province":"NY",
    "sg:tags":[
        "tire"
    ],
    "wof:name":"Schmidt Bros",
    "wof:placetype":"venue"
},
  "geometry": {"coordinates":[-73.8321,42.287601],"type":"Point"}
}