{
  "type": "Feature",
  "properties": {
    "iso:country":"US",
    "sg:address":"1267 Flushing Ave",
    "sg:city":"Brooklyn",
    "sg:classifiers":[
        {
            "category":"Shopping",
            "type":"Retail Goods"
        }
    ],
    "sg:phone":"+1 718 417 1513",
    "sg:postcode":"11237",
    "sg:province":"NY",
    "sg:tags":[
        "product",
        "wood"
    ],
    "wof:name":"Fantastic Wood Carving",
    "wof:placetype":"venue"
},
  "geometry": {"coordinates":[-73.922647,40.708762],"type":"Point"}
}