{
  "type": "Feature",
  "properties": {
    "addr:full":"600 Madison Ave New York NY 10022",
    "addr:housenumber":"600",
    "addr:postcode":"10022",
    "addr:street":"Madison Ave",
    "iso:country":"US",
    "sg:address":"600 Madison Ave",
    "sg:city":"New York",
    "sg:classifiers":[
        {
            "category":"Real Estate",
            "subcategory":"Real Estate Operator",
            "type":"Services"
        }
    ],
    "sg:phone":"+1 212 759 9001",
    "sg:postcode":"10022",
    "sg:province":"NY",
    "sg:tags":[
        "owner",
        "residential",
        "commercial"
    ],
    "wof:name":"Bluestar LLC",
    "wof:placetype":"venue"
},
  "geometry": {"coordinates":[-73.972121,40.762662],"type":"Point"}
}