{
  "type": "Feature",
  "properties": {
    "addr:full":"622 Manhattan Ave Thornwood NY 10594",
    "addr:housenumber":"622",
    "addr:postcode":"10594",
    "addr:street":"Manhattan Ave",
    "iso:country":"US",
    "sg:address":"622 Manhattan Ave",
    "sg:city":"Thornwood",
    "sg:classifiers":[
        {
            "category":"Education",
            "subcategory":"Special Training",
            "type":"Public Place"
        }
    ],
    "sg:phone":"+1 914 741 1478",
    "sg:postcode":"10594",
    "sg:province":"NY",
    "sg:tags":[
        "educational"
    ],
    "wof:name":"Board Of Co-Op Educational Svc",
    "wof:placetype":"venue"
},
  "geometry": {"coordinates":[-73.78780999999999,41.115235],"type":"Point"}
}