{
  "type": "Feature",
  "properties": {
    "addr:full":"1 Cross Island Pkwy Rosedale NY 11426",
    "addr:housenumber":"1",
    "addr:postcode":"11426",
    "addr:street":"Cross Island Pkwy",
    "iso:country":"US",
    "sg:address":"1 Cross Island Pkwy",
    "sg:city":"Rosedale",
    "sg:classifiers":[
        {
            "category":"Freight",
            "type":"Transportation"
        }
    ],
    "sg:phone":"+1 718 528 1888",
    "sg:postcode":"11426",
    "sg:province":"NY",
    "sg:tags":[
        "shipping",
        "agent",
        "arrangement"
    ],
    "wof:name":"Dewell Container Shipping Corp",
    "wof:placetype":"venue"
},
  "geometry": {"coordinates":[-73.72489,40.739566],"type":"Point"}
}