{
  "type": "Feature",
  "properties": {
    "addr:full":"2200 Mercer St Baldwinsville NY 13027",
    "addr:housenumber":"2200",
    "addr:postcode":"13027",
    "addr:street":"Mercer St",
    "iso:country":"US",
    "sg:address":"2200 Mercer St",
    "sg:city":"Baldwinsville",
    "sg:classifiers":[
        {
            "category":"Professional",
            "subcategory":"Secretarial Services",
            "type":"Services"
        },
        {
            "category":"Professional",
            "subcategory":"Employment Agencies",
            "type":"Services"
        }
    ],
    "sg:phone":"+1 315 638 0430",
    "sg:postcode":"13027",
    "sg:province":"NY",
    "sg:tags":[
        "typing"
    ],
    "wof:name":"Mlm Transcription",
    "wof:placetype":"venue"
},
  "geometry": {"coordinates":[-76.350797,43.166711],"type":"Point"}
}