{
  "type": "Feature",
  "properties": {
    "iso:country":"US",
    "sg:address":"2975 N Westchester Ave",
    "sg:city":"Purchase",
    "sg:classifiers":[
        {
            "category":"Insurance",
            "subcategory":"Insurance Agent",
            "type":"Services"
        }
    ],
    "sg:phone":"+1 914 696 3000",
    "sg:postcode":"10577",
    "sg:province":"NY",
    "sg:website":"www.insurancemre.com",
    "wof:name":"Martin Rosner Eleftherion Inc",
    "wof:placetype":"venue"
},
  "geometry": {"coordinates":[-73.697717,41.009302],"type":"Point"}
}