{
  "type": "Feature",
  "properties": {
    "addr:full":"1409 Curry Rd Schenectady NY 12306",
    "addr:housenumber":"1409",
    "addr:postcode":"12306",
    "addr:street":"Curry Rd",
    "iso:country":"US",
    "sg:address":"1409 Curry Rd",
    "sg:city":"Schenectady",
    "sg:classifiers":[
        {
            "category":"Manufacturing",
            "subcategory":"Furniture",
            "type":"Manufacturing & Wholesale Goods"
        }
    ],
    "sg:phone":"+1 518 355 4295",
    "sg:postcode":"12306",
    "sg:province":"NY",
    "sg:tags":[
        "fixture",
        "store"
    ],
    "wof:name":"Diversified Store Fixtures Inc",
    "wof:placetype":"venue"
},
  "geometry": {"coordinates":[-73.96244799999999,42.783371],"type":"Point"}
}