{
  "type": "Feature",
  "properties": {
    "iso:country":"US",
    "sg:address":"70 Dahill Rd",
    "sg:city":"Brooklyn",
    "sg:classifiers":[
        {
            "category":"Freight",
            "type":"Transportation"
        }
    ],
    "sg:phone":"+1   ",
    "sg:postcode":"11218",
    "sg:province":"NY",
    "sg:tags":[
        "interstate",
        "trucking"
    ],
    "wof:name":"Kasfia Inc",
    "wof:placetype":"venue"
},
  "geometry": {"coordinates":[-73.980915,40.644991],"type":"Point"}
}