{
  "type": "Feature",
  "properties": {
    "addr:full":"278 Lark St Albany NY 12210",
    "addr:housenumber":"278",
    "addr:postcode":"12210",
    "addr:street":"Lark St",
    "iso:country":"US",
    "sg:address":"278 Lark St",
    "sg:city":"Albany",
    "sg:classifiers":[
        {
            "category":"Personal",
            "subcategory":"Tattoo Parlor",
            "type":"Services"
        },
        {
            "category":"Personal",
            "subcategory":"Piercing",
            "type":"Services"
        }
    ],
    "sg:phone":"+1 518 434 4907",
    "sg:postcode":"12210",
    "sg:province":"NY",
    "sg:tags":[
        "body"
    ],
    "sg:website":"http://www.larkvegas.com",
    "wof:name":"A Lark Vegas Piercing Co",
    "wof:placetype":"venue"
},
  "geometry": {"coordinates":[-73.766685,42.653439],"type":"Point"}
}