{
  "type": "Feature",
  "properties": {
    "addr:full":"149 Duane St New York NY 10013",
    "addr:housenumber":"149",
    "addr:postcode":"10013",
    "addr:street":"Duane St",
    "iso:country":"US",
    "sg:address":"149 Duane St",
    "sg:city":"New York",
    "sg:classifiers":[
        {
            "category":"Real Estate",
            "subcategory":"Real Estate Agent",
            "type":"Services"
        }
    ],
    "sg:phone":"+1 212 267 1999",
    "sg:postcode":"10013",
    "sg:province":"NY",
    "wof:name":"Duane Fabs Property Corp",
    "wof:placetype":"venue"
},
  "geometry": {"coordinates":[-74.007097,40.715998],"type":"Point"}
}