{
  "type": "Feature",
  "properties": {
    "addr:full":"399 Little East Neck Rd N West Babylon NY 11704",
    "addr:housenumber":"399",
    "addr:postcode":"11704",
    "addr:street":"Little East Neck Rd N",
    "iso:country":"US",
    "sg:address":"399 Little East Neck Rd N",
    "sg:city":"West Babylon",
    "sg:classifiers":[
        {
            "category":"Professional",
            "type":"Services"
        }
    ],
    "sg:phone":"+1 631 957 5959",
    "sg:postcode":"11704",
    "sg:province":"NY",
    "sg:tags":[
        "establishment"
    ],
    "wof:name":"Easy Shellfish Inc",
    "wof:placetype":"venue"
},
  "geometry": {"coordinates":[-73.34383699999999,40.70388],"type":"Point"}
}