{
  "type": "Feature",
  "properties": {
    "addr:full":"219 Mott Street New York NY 10012",
    "addr:housenumber":"219",
    "addr:postcode":"10012",
    "addr:street":"Mott Street",
    "iso:country":"US",
    "sg:address":"219 Mott Street",
    "sg:city":"New York",
    "sg:classifiers":[
        {
            "category":"Shopping",
            "subcategory":"Shoes",
            "type":"Retail Goods"
        }
    ],
    "sg:phone":"+1 212 431 0483",
    "sg:postcode":"10012",
    "sg:province":"NY",
    "sg:tags":[
        "store"
    ],
    "wof:name":"Castillo Rosado",
    "wof:placetype":"venue"
},
  "geometry": {"coordinates":[-73.997103,40.725638],"type":"Point"}
}