{
  "type": "Feature",
  "properties": {
    "iso:country":"US",
    "sg:address":"31 Lincoln St",
    "sg:city":"Canton",
    "sg:classifiers":[
        {
            "category":"Professional",
            "subcategory":"Accounting & Tax Preparation",
            "type":"Services"
        }
    ],
    "sg:phone":"+1 315 386 4684",
    "sg:postcode":"13617",
    "sg:province":"NY",
    "wof:name":"Carol Roche A",
    "wof:placetype":"venue"
},
  "geometry": {"coordinates":[-75.16820300000001,44.589601],"type":"Point"}
}