{
  "type": "Feature",
  "properties": {
    "iso:country":"US",
    "sg:address":"1510 Dewey Ave",
    "sg:city":"Rochester",
    "sg:classifiers":[
        {
            "category":"Shopping",
            "subcategory":"Used Merchandise",
            "type":"Retail Goods"
        }
    ],
    "sg:phone":"+1 585 254 0684",
    "sg:postcode":"14615",
    "sg:province":"NY",
    "sg:tags":[
        "furniture"
    ],
    "wof:name":"Art's Used Furniture",
    "wof:placetype":"venue"
},
  "geometry": {"coordinates":[-77.638777,43.195328],"type":"Point"}
}