{
  "type": "Feature",
  "properties": {
    "iso:country":"US",
    "sg:address":"160 Grand Blvd",
    "sg:city":"Long Beach",
    "sg:classifiers":[
        {
            "category":"Building & Trades",
            "subcategory":"Electrical",
            "type":"Services"
        }
    ],
    "sg:phone":"+1 516 431 7804",
    "sg:postcode":"11561",
    "sg:province":"NY",
    "sg:tags":[
        "electrical",
        "contractor"
    ],
    "wof:name":"Novak Corporation",
    "wof:placetype":"venue"
},
  "geometry": {"coordinates":[-73.684079,40.585895],"type":"Point"}
}