{
  "type": "Feature",
  "properties": {
    "iso:country":"US",
    "sg:address":"363 Oakwood Ave",
    "sg:city":"East Aurora",
    "sg:classifiers":[
        {
            "category":"Museum",
            "type":"Entertainment"
        }
    ],
    "sg:phone":"+1 716 652 4735",
    "sg:postcode":"14052",
    "sg:province":"NY",
    "wof:name":"Elbert Hubbard-Roycroft Muse",
    "wof:placetype":"venue"
},
  "geometry": {"coordinates":[-78.620852,42.765686],"type":"Point"}
}