{
  "type": "Feature",
  "properties": {
    "iso:country":"US",
    "sg:address":"407 Erie St",
    "sg:city":"Little Valley",
    "sg:classifiers":[
        {
            "category":"Food & Beverages",
            "subcategory":"Groceries & Convenience Stores",
            "type":"Retail Goods"
        }
    ],
    "sg:phone":"+1   ",
    "sg:postcode":"14755",
    "sg:province":"NY",
    "wof:name":"Dairyland",
    "wof:placetype":"venue"
},
  "geometry": {"coordinates":[-78.80257,42.251453],"type":"Point"}
}