{
  "type": "Feature",
  "properties": {
    "iso:country":"US",
    "sg:address":"245 5th Ave",
    "sg:city":"New York",
    "sg:classifiers":[
        {
            "category":"Health Services",
            "subcategory":"Clinic",
            "type":"Services"
        }
    ],
    "sg:phone":"+1   ",
    "sg:postcode":"10016",
    "sg:province":"NY",
    "sg:tags":[
        "shop",
        "medical",
        "agency",
        "research",
        "thrift"
    ],
    "wof:name":"Irvington Institute For Immuno",
    "wof:placetype":"venue"
},
  "geometry": {"coordinates":[-73.987487,40.744184],"type":"Point"}
}