{
  "type": "Feature",
  "properties": {
    "addr:full":"377 Schroon River Rd Warrensburg NY 12885",
    "addr:housenumber":"377",
    "addr:postcode":"12885",
    "addr:street":"Schroon River Rd",
    "iso:country":"US",
    "sg:address":"377 Schroon River Rd",
    "sg:city":"Warrensburg",
    "sg:classifiers":[
        {
            "category":"Social Services",
            "type":"Services"
        }
    ],
    "sg:phone":"+1 518 623 3291",
    "sg:postcode":"12885",
    "sg:province":"NY",
    "sg:tags":[
        "organization",
        "welfare"
    ],
    "sg:website":"www.cce.cornell.edu",
    "wof:name":"Cornell Cooperative Extension",
    "wof:placetype":"venue"
},
  "geometry": {"coordinates":[-73.749989,43.511475],"type":"Point"}
}