{
  "type": "Feature",
  "properties": {
    "iso:country":"US",
    "sg:address":"151 Old Liverpool Rd",
    "sg:city":"Liverpool",
    "sg:classifiers":[
        {
            "category":"Real Estate",
            "subcategory":"Real Estate Operator",
            "type":"Services"
        }
    ],
    "sg:phone":"+1 315 451 3300",
    "sg:postcode":"13088",
    "sg:province":"NY",
    "sg:tags":[
        "dwelling"
    ],
    "wof:name":"Onondaga Lake Townhomes",
    "wof:placetype":"venue"
},
  "geometry": {"coordinates":[-76.182658,43.083819],"type":"Point"}
}