{
  "type": "Feature",
  "properties": {
    "addr:full":"730 10th Ave Corner of W 50th St New York NY 10079",
    "addr:housenumber":"730",
    "addr:postcode":"10079",
    "addr:street":"10Th Ave Corner Of W 50Th St",
    "iso:country":"US",
    "sg:address":"730 10th Ave Corner of W 50th St",
    "sg:city":"New York",
    "sg:classifiers":[
        {
            "category":"Restaurant",
            "type":"Food & Drink"
        }
    ],
    "sg:phone":"+1 212 541 6900",
    "sg:postcode":"10079",
    "sg:province":"NY",
    "sg:tags":[
        "pizza"
    ],
    "sg:website":"www.fatsals.com",
    "wof:name":"Fat Sal's Pizza",
    "wof:placetype":"venue"
},
  "geometry": {"coordinates":[-73.99184200000001,40.764585],"type":"Point"}
}