{
  "type": "Feature",
  "properties": {
    "iso:country":"US",
    "sg:address":"1740 Western Ave",
    "sg:city":"Albany",
    "sg:classifiers":[
        {
            "category":"Health Services",
            "subcategory":"Health Practitioner",
            "type":"Services"
        }
    ],
    "sg:phone":"+1   ",
    "sg:postcode":"12203",
    "sg:province":"NY",
    "wof:name":"Linda S Vara",
    "wof:placetype":"venue"
},
  "geometry": {"coordinates":[-73.860882,42.688533],"type":"Point"}
}