{
  "type": "Feature",
  "properties": {
    "addr:full":"2487 65th St Brooklyn NY 11204",
    "addr:housenumber":"2487",
    "addr:postcode":"11204",
    "addr:street":"65Th St",
    "iso:country":"US",
    "sg:address":"2487 65th St",
    "sg:city":"Brooklyn",
    "sg:classifiers":[
        {
            "category":"Food & Beverages",
            "subcategory":"Groceries & Convenience Stores",
            "type":"Retail Goods"
        }
    ],
    "sg:phone":"+1   ",
    "sg:postcode":"11204",
    "sg:province":"NY",
    "wof:name":"Nikopol Grocery & Vegetab",
    "wof:placetype":"venue"
},
  "geometry": {"coordinates":[-73.97463500000001,40.60992],"type":"Point"}
}