{
  "type": "Feature",
  "properties": {
    "iso:country":"US",
    "sg:address":"1801 E Main St",
    "sg:city":"Rochester",
    "sg:classifiers":[
        {
            "category":"Education",
            "subcategory":"School",
            "type":"Public Place"
        }
    ],
    "sg:phone":"+1 585 288 3130",
    "sg:postcode":"14609",
    "sg:province":"NY",
    "sg:tags":[
        "high"
    ],
    "sg:website":"http://www.easthighschool.net",
    "wof:name":"East High School",
    "wof:placetype":"venue"
},
  "geometry": {"coordinates":[-77.56303200000001,43.159803],"type":"Point"}
}