{
  "type": "Feature",
  "properties": {
    "addr:full":"269 Bay 20th St Brooklyn NY 11214",
    "addr:housenumber":"269",
    "addr:postcode":"11214",
    "addr:street":"Bay 20Th St",
    "iso:country":"US",
    "sg:address":"269 Bay 20th St",
    "sg:city":"Brooklyn",
    "sg:classifiers":[
        {
            "category":"Professional",
            "subcategory":"Employment Agencies",
            "type":"Services"
        }
    ],
    "sg:phone":"+1 212 683 5820",
    "sg:postcode":"11214",
    "sg:province":"NY",
    "sg:tags":[
        "opportunity"
    ],
    "wof:name":"D. Stamler Associates",
    "wof:placetype":"venue"
},
  "geometry": {"coordinates":[-74.006396,40.601382],"type":"Point"}
}