{
  "type": "Feature",
  "properties": {
    "addr:full":"336 Main St Beacon NY 12508",
    "addr:housenumber":"336",
    "addr:postcode":"12508",
    "addr:street":"Main St",
    "iso:country":"US",
    "sg:address":"336 Main St",
    "sg:city":"Beacon",
    "sg:classifiers":[
        {
            "category":"Retail",
            "subcategory":"Repair Shop",
            "type":"Services"
        }
    ],
    "sg:phone":"+1 845 831 0093",
    "sg:postcode":"12508",
    "sg:province":"NY",
    "sg:tags":[
        "reupholstery",
        "furniture"
    ],
    "sg:website":"www.sunwallpaperandpaint.com",
    "wof:name":"SUN WALLPAPER & PAINT INC",
    "wof:placetype":"venue"
},
  "geometry": {"coordinates":[-73.96892200000001,41.504635],"type":"Point"}
}