{
  "type": "Feature",
  "properties": {
    "addr:full":"710 Black River Blvd N Rome NY 13440",
    "addr:housenumber":"710",
    "addr:postcode":"13440",
    "addr:street":"Black River Blvd N",
    "iso:country":"US",
    "sg:address":"710 Black River Blvd N",
    "sg:city":"Rome",
    "sg:classifiers":[
        {
            "category":"Health Services",
            "subcategory":"Doctor",
            "type":"Services"
        }
    ],
    "sg:phone":"+1 315 339 5364",
    "sg:postcode":"13440",
    "sg:province":"NY",
    "sg:tags":[
        "dentist"
    ],
    "wof:name":"Dr Mitchell W Wilbert DDS",
    "wof:placetype":"venue"
},
  "geometry": {"coordinates":[-75.448003,43.218108],"type":"Point"}
}