{
  "type": "Feature",
  "properties": {
    "iso:country":"US",
    "sg:address":"1637 Broadhollow Rd",
    "sg:city":"Farmingdale",
    "sg:classifiers":[
        {
            "category":"Recreation",
            "subcategory":"Playground",
            "type":"Entertainment"
        }
    ],
    "sg:phone":"+1 631 752 1115",
    "sg:postcode":"11735",
    "sg:province":"NY",
    "wof:name":"Rainbow Direct Swingsets",
    "wof:placetype":"venue"
},
  "geometry": {"coordinates":[-73.422741,40.742363],"type":"Point"}
}