{
  "type": "Feature",
  "properties": {
    "addr:full":"214 Greene Ave Sayville NY 11782",
    "addr:housenumber":"214",
    "addr:postcode":"11782",
    "addr:street":"Greene Ave",
    "iso:country":"US",
    "sg:address":"214 Greene Ave",
    "sg:city":"Sayville",
    "sg:classifiers":[
        {
            "category":"Home & Garden",
            "subcategory":"Garden Supply",
            "type":"Retail Goods"
        }
    ],
    "sg:phone":"+1 631 589 6560",
    "sg:postcode":"11782",
    "sg:province":"NY",
    "sg:tags":[
        "sprinkler"
    ],
    "wof:name":"Active Irrigation",
    "wof:placetype":"venue"
},
  "geometry": {"coordinates":[-73.084332,40.732809],"type":"Point"}
}