{
  "type": "Feature",
  "properties": {
    "addr:full":"4 Winston Dr Rhinebeck NY 12572",
    "addr:housenumber":"4",
    "addr:postcode":"12572",
    "addr:street":"Winston Dr",
    "iso:country":"US",
    "sg:address":"4 Winston Dr",
    "sg:city":"Rhinebeck",
    "sg:classifiers":[
        {
            "category":"Real Estate",
            "subcategory":"Real Estate Agent",
            "type":"Services"
        }
    ],
    "sg:phone":"+1 845 876 7208",
    "sg:postcode":"12572",
    "sg:province":"NY",
    "wof:name":"Gail Lee Realtor",
    "wof:placetype":"venue"
},
  "geometry": {"coordinates":[-73.875938,41.963829],"type":"Point"}
}