{
  "type": "Feature",
  "properties": {
    "addr:full":"33 Flying Point Rd Southampton NY 11968",
    "addr:housenumber":"33",
    "addr:postcode":"11968",
    "addr:street":"Flying Point Rd",
    "iso:country":"US",
    "sg:address":"33 Flying Point Rd",
    "sg:city":"Southampton",
    "sg:classifiers":[
        {
            "category":"Building & Trades",
            "subcategory":"Construction",
            "type":"Services"
        }
    ],
    "sg:phone":"+1 631 204 8800",
    "sg:postcode":"11968",
    "sg:province":"NY",
    "sg:tags":[
        "home",
        "builder"
    ],
    "wof:name":"Burns Development Corp",
    "wof:placetype":"venue"
},
  "geometry": {"coordinates":[-72.382734,40.904162],"type":"Point"}
}