{
  "type": "Feature",
  "properties": {
    "addr:full":"2015 Richmond Ter Staten Island NY 10302",
    "addr:housenumber":"2015",
    "addr:postcode":"10302",
    "addr:street":"Richmond Ter",
    "iso:country":"US",
    "sg:address":"2015 Richmond Ter",
    "sg:city":"Staten Island",
    "sg:classifiers":[
        {
            "category":"Marine",
            "type":"Transportation"
        }
    ],
    "sg:phone":"+1 718 727 3633",
    "sg:postcode":"10302",
    "sg:province":"NY",
    "sg:tags":[
        "towing"
    ],
    "sg:website":"www.morantug.com",
    "wof:name":"Moran Inc",
    "wof:placetype":"venue"
},
  "geometry": {"coordinates":[-74.12952199999999,40.639181],"type":"Point"}
}