{
  "type": "Feature",
  "properties": {
    "addr:full":"15626 Northern Blvd Flushing NY 11354",
    "addr:housenumber":"15626",
    "addr:postcode":"11354",
    "addr:street":"Northern Blvd",
    "iso:country":"US",
    "sg:address":"15626 Northern Blvd",
    "sg:city":"Flushing",
    "sg:classifiers":[
        {
            "category":"Restaurant",
            "type":"Food & Drink"
        }
    ],
    "sg:phone":"+1 718 886 1368",
    "sg:postcode":"11354",
    "sg:province":"NY",
    "sg:tags":[
        "korean",
        "chinese"
    ],
    "wof:name":"Jang Won Ru Restaurant Inc",
    "wof:placetype":"venue"
},
  "geometry": {"coordinates":[-73.808899,40.763901],"type":"Point"}
}