{
  "type": "Feature",
  "properties": {
    "iso:country":"US",
    "sg:address":"976 3rd Ave",
    "sg:city":"Brooklyn",
    "sg:classifiers":[
        {
            "category":"Food & Beverages",
            "subcategory":"Liquor & Beverages",
            "type":"Retail Goods"
        }
    ],
    "sg:phone":"+1 718 499 2257",
    "sg:postcode":"11232",
    "sg:province":"NY",
    "sg:tags":[
        "beer",
        "wine",
        "spirit",
        "alcoholic"
    ],
    "sg:website":"www.brooklynliquors.com/",
    "wof:name":"Brooklyn Liquors",
    "wof:placetype":"venue"
},
  "geometry": {"coordinates":[-74.007301,40.654701],"type":"Point"}
}