{
  "type": "Feature",
  "properties": {
    "addr:full":"1850 New York Ave Huntington Station NY 11746",
    "addr:housenumber":"1850",
    "addr:postcode":"11746",
    "addr:street":"New York Ave Huntington",
    "iso:country":"US",
    "sg:address":"1850 New York Ave",
    "sg:city":"Huntington Station",
    "sg:classifiers":[
        {
            "category":"Government",
            "subcategory":"Court House",
            "type":"Public Place"
        }
    ],
    "sg:phone":"+1 631 854 4545",
    "sg:postcode":"11746",
    "sg:province":"NY",
    "wof:name":"3rd Dist Court",
    "wof:placetype":"venue"
},
  "geometry": {"coordinates":[-73.41231399999999,40.838503],"type":"Point"}
}