{
  "type": "Feature",
  "properties": {
    "iso:country":"US",
    "sg:address":"788 Genesee St",
    "sg:city":"Corfu",
    "sg:classifiers":[
        {
            "category":"Farming",
            "subcategory":"Livestock Farm",
            "type":"Manufacturing & Wholesale Goods"
        }
    ],
    "sg:phone":"+1 585 599 3846",
    "sg:postcode":"14036",
    "sg:province":"NY",
    "wof:name":"Willowtree Farms",
    "wof:placetype":"venue"
},
  "geometry": {"coordinates":[-78.42683599999999,42.955935],"type":"Point"}
}