{
  "type": "Feature",
  "properties": {
    "addr:full":"108 Pelham Dr Cornwall NY 12518",
    "addr:housenumber":"108",
    "addr:postcode":"12518",
    "addr:street":"Pelham Dr",
    "iso:country":"US",
    "sg:address":"108 Pelham Dr",
    "sg:city":"Cornwall",
    "sg:classifiers":[
        {
            "category":"Professional",
            "subcategory":"Management & Consulting",
            "type":"Services"
        }
    ],
    "sg:phone":"+1   ",
    "sg:postcode":"12518",
    "sg:province":"NY",
    "sg:tags":[
        "retail",
        "direct",
        "sales"
    ],
    "wof:name":"Lisa Lewyta",
    "wof:placetype":"venue"
},
  "geometry": {"coordinates":[-74.04897200000001,41.437834],"type":"Point"}
}