{
  "type": "Feature",
  "properties": {
    "addr:full":"16 Forest St New Canaan NY 06840",
    "addr:housenumber":"16",
    "addr:postcode":"06840",
    "addr:street":"Forest St",
    "iso:country":"US",
    "sg:address":"16 Forest St",
    "sg:city":"New Canaan",
    "sg:classifiers":[
        {
            "category":"Building & Trades",
            "subcategory":"Construction",
            "type":"Services"
        }
    ],
    "sg:phone":"+1 203 966 9388",
    "sg:postcode":"06840",
    "sg:province":"NY",
    "sg:tags":[
        "contractor"
    ],
    "wof:name":"Franco Building Assoc",
    "wof:placetype":"venue"
},
  "geometry": {"coordinates":[-73.49210100000001,41.148387],"type":"Point"}
}