{
  "type": "Feature",
  "properties": {
    "addr:full":"148 39th St Brooklyn NY 11232",
    "addr:housenumber":"148",
    "addr:postcode":"11232",
    "addr:street":"39Th St",
    "iso:country":"US",
    "sg:address":"148 39th St",
    "sg:city":"Brooklyn",
    "sg:classifiers":[
        {
            "category":"Wholesale",
            "subcategory":"Groceries",
            "type":"Manufacturing & Wholesale Goods"
        }
    ],
    "sg:phone":"+1 718 832 5300",
    "sg:postcode":"11232",
    "sg:province":"NY",
    "sg:tags":[
        "food",
        "product"
    ],
    "wof:name":"Goldleaf Distibuters LLC",
    "wof:placetype":"venue"
},
  "geometry": {"coordinates":[-74.011374,40.655878],"type":"Point"}
}