{
  "type": "Feature",
  "properties": {
    "iso:country":"US",
    "sg:address":"440 State Rte 104",
    "sg:city":"Ontario",
    "sg:classifiers":[
        {
            "category":"Travel",
            "subcategory":"Hotels & Motels",
            "type":"Entertainment"
        }
    ],
    "sg:phone":"+1   ",
    "sg:postcode":"14519",
    "sg:province":"NY",
    "sg:tags":[
        "operation"
    ],
    "wof:name":"Ontario Motel",
    "wof:placetype":"venue"
},
  "geometry": {"coordinates":[-77.352076,43.225764],"type":"Point"}
}