{
  "type": "Feature",
  "properties": {
    "iso:country":"US",
    "sg:address":"605 Old Country Rd",
    "sg:city":"Plainview",
    "sg:classifiers":[
        {
            "category":"Shopping",
            "subcategory":"Stationery & Office Supplies",
            "type":"Retail Goods"
        }
    ],
    "sg:phone":"+1 516 433 9850",
    "sg:postcode":"11803",
    "sg:province":"NY",
    "sg:tags":[
        "stationer"
    ],
    "wof:name":"Old Country Rd Card & Gifts",
    "wof:placetype":"venue"
},
  "geometry": {"coordinates":[-73.494883,40.770987],"type":"Point"}
}