{
  "type": "Feature",
  "properties": {
    "iso:country":"US",
    "sg:address":"127 Montrose Ave",
    "sg:city":"Brooklyn",
    "sg:classifiers":[
        {
            "category":"Building & Trades",
            "subcategory":"Construction",
            "type":"Services"
        }
    ],
    "sg:phone":"+1 718 919 8653",
    "sg:postcode":"11206",
    "sg:province":"NY",
    "sg:tags":[
        "contractor"
    ],
    "wof:name":"Barton's Hardwood Doors & Glass",
    "wof:placetype":"venue"
},
  "geometry": {"coordinates":[-73.944397,40.707199],"type":"Point"}
}