{
  "type": "Feature",
  "properties": {
    "addr:full":"308 W 94 St New York NY 10025",
    "addr:housenumber":"308",
    "addr:postcode":"10025",
    "addr:street":"W 94 St",
    "iso:country":"US",
    "sg:address":"308 W 94 St",
    "sg:city":"New York",
    "sg:classifiers":[
        {
            "category":"Retail",
            "subcategory":"Repair Shop",
            "type":"Services"
        }
    ],
    "sg:phone":"+1 646 224 0948",
    "sg:postcode":"10025",
    "sg:province":"NY",
    "sg:tags":[
        "lock",
        "locksmith"
    ],
    "wof:name":"Emergency Locksmith",
    "wof:placetype":"venue"
},
  "geometry": {"coordinates":[-73.97623299999999,40.794827],"type":"Point"}
}