{
  "type": "Feature",
  "properties": {
    "iso:country":"US",
    "sg:address":"27 Lebanon St",
    "sg:city":"Hamilton",
    "sg:classifiers":[
        {
            "category":"Food & Beverages",
            "subcategory":"Liquor & Beverages",
            "type":"Retail Goods"
        }
    ],
    "sg:phone":"+1 315 824 1740",
    "sg:postcode":"13346",
    "sg:province":"NY",
    "wof:name":"Village Wine & Spirits",
    "wof:placetype":"venue"
},
  "geometry": {"coordinates":[-75.545241,42.826439],"type":"Point"}
}