{
  "type": "Feature",
  "properties": {
    "iso:country":"US",
    "sg:address":"607 Soundview Ave",
    "sg:city":"Bronx",
    "sg:classifiers":[
        {
            "category":"Health Services",
            "subcategory":"Doctor",
            "type":"Services"
        }
    ],
    "sg:phone":"+1 718 328 1944",
    "sg:postcode":"10473",
    "sg:province":"NY",
    "sg:tags":[
        "medical",
        "dental",
        "clinic",
        "center"
    ],
    "wof:name":"Soundview Medical Physician PC",
    "wof:placetype":"venue"
},
  "geometry": {"coordinates":[-73.863309,40.818566],"type":"Point"}
}