{
  "type": "Feature",
  "properties": {
    "addr:full":"287 Skidmore Rd Deer Park NY 11729",
    "addr:housenumber":"287",
    "addr:postcode":"11729",
    "addr:street":"Skidmore Rd",
    "iso:country":"US",
    "sg:address":"287 Skidmore Rd",
    "sg:city":"Deer Park",
    "sg:classifiers":[
        {
            "category":"Professional",
            "type":"Services"
        }
    ],
    "sg:phone":"+1 631 243 0535",
    "sg:postcode":"11729",
    "sg:province":"NY",
    "sg:tags":[
        "establishment"
    ],
    "wof:name":"John R Auto",
    "wof:placetype":"venue"
},
  "geometry": {"coordinates":[-73.308018,40.747234],"type":"Point"}
}