{
  "type": "Feature",
  "properties": {
    "addr:full":"115 Broadway Hicksville NY 11801",
    "addr:housenumber":"115",
    "addr:postcode":"11801",
    "addr:street":"Broadway",
    "iso:country":"US",
    "sg:address":"115 Broadway",
    "sg:city":"Hicksville",
    "sg:classifiers":[
        {
            "category":"Shopping",
            "subcategory":"Clothing, Apparel, & Fashions",
            "type":"Retail Goods"
        }
    ],
    "sg:phone":"+1 516 390 0713",
    "sg:postcode":"11801",
    "sg:province":"NY",
    "sg:tags":[
        "accessory",
        "women's"
    ],
    "wof:name":"Rose Boutique",
    "wof:placetype":"venue"
},
  "geometry": {"coordinates":[-73.522452,40.76649],"type":"Point"}
}