{
  "type": "Feature",
  "properties": {
    "addr:full":"2271 Culver Rd Rochester NY 14609",
    "addr:housenumber":"2271",
    "addr:postcode":"14609",
    "addr:street":"Culver Rd",
    "iso:country":"US",
    "sg:address":"2271 Culver Rd",
    "sg:city":"Rochester",
    "sg:classifiers":[
        {
            "category":"Autos & Motor Vehicles",
            "subcategory":"Fuel & Gas Station",
            "type":"Retail Goods"
        }
    ],
    "sg:phone":"+1   ",
    "sg:postcode":"14609",
    "sg:province":"NY",
    "sg:tags":[
        "grocery",
        "station",
        "gasoline"
    ],
    "wof:name":"Kwik - Fill",
    "wof:placetype":"venue"
},
  "geometry": {"coordinates":[-77.56088699999999,43.185538],"type":"Point"}
}