{
  "type": "Feature",
  "properties": {
    "addr:full":"152 Andrews Rd Vestal NY 13850",
    "addr:housenumber":"152",
    "addr:postcode":"13850",
    "addr:street":"Andrews Rd",
    "iso:country":"US",
    "sg:address":"152 Andrews Rd",
    "sg:city":"Vestal",
    "sg:classifiers":[
        {
            "category":"Social Services",
            "type":"Services"
        }
    ],
    "sg:phone":"+1 607 786 8839",
    "sg:postcode":"13850",
    "sg:province":"NY",
    "sg:tags":[
        "youth",
        "organization",
        "center"
    ],
    "wof:name":"Senior League Of Vestal",
    "wof:placetype":"venue"
},
  "geometry": {"coordinates":[-76.023453,42.082121],"type":"Point"}
}