{
  "type": "Feature",
  "properties": {
    "addr:full":"59 Clinton Ave Salt Point NY 12578",
    "addr:housenumber":"59",
    "addr:postcode":"12578",
    "addr:street":"Clinton Ave",
    "iso:country":"US",
    "sg:address":"59 Clinton Ave",
    "sg:city":"Salt Point",
    "sg:classifiers":[
        {
            "category":"Building & Trades",
            "subcategory":"Landscaping Services",
            "type":"Services"
        }
    ],
    "sg:phone":"+1 845 266 8802",
    "sg:postcode":"12578",
    "sg:province":"NY",
    "sg:tags":[
        "tree"
    ],
    "wof:name":"Living Tree Woodland",
    "wof:placetype":"venue"
},
  "geometry": {"coordinates":[-73.826685,41.80148],"type":"Point"}
}