{
  "type": "Feature",
  "properties": {
    "iso:country":"US",
    "sg:address":"111 Mercer St",
    "sg:city":"New York",
    "sg:classifiers":[
        {
            "category":"Real Estate",
            "subcategory":"Architect",
            "type":"Services"
        }
    ],
    "sg:phone":"+1 212 226 0303",
    "sg:postcode":"10012",
    "sg:province":"NY",
    "sg:tags":[
        "architectural"
    ],
    "wof:name":"Archi-Tectionics",
    "wof:placetype":"venue"
},
  "geometry": {"coordinates":[-73.998851,40.724354],"type":"Point"}
}