{
  "type": "Feature",
  "properties": {
    "addr:full":"16 Lawrence Pl Yonkers NY 10701",
    "addr:housenumber":"16",
    "addr:postcode":"10701",
    "addr:street":"Lawrence Pl",
    "iso:country":"US",
    "sg:address":"16 Lawrence Pl",
    "sg:city":"Yonkers",
    "sg:classifiers":[
        {
            "category":"Shopping",
            "subcategory":"Clothing, Apparel, & Fashions",
            "type":"Retail Goods"
        }
    ],
    "sg:phone":"+1 914 968 6863",
    "sg:postcode":"10701",
    "sg:province":"NY",
    "wof:name":"Alawie Ali",
    "wof:placetype":"venue"
},
  "geometry": {"coordinates":[-73.887362,40.926608],"type":"Point"}
}