{
  "type": "Feature",
  "properties": {
    "addr:full":"84 Inwood Ave Port Chester NY 10573",
    "addr:housenumber":"84",
    "addr:postcode":"10573",
    "addr:street":"Inwood Ave",
    "iso:country":"US",
    "sg:address":"84 Inwood Ave",
    "sg:city":"Port Chester",
    "sg:classifiers":[
        {
            "category":"Professional",
            "type":"Services"
        }
    ],
    "sg:phone":"+1 914 937 2468",
    "sg:postcode":"10573",
    "sg:province":"NY",
    "sg:tags":[
        "hanging",
        "contractor"
    ],
    "wof:name":"Studio 141",
    "wof:placetype":"venue"
},
  "geometry": {"coordinates":[-73.67719,40.997392],"type":"Point"}
}