{
  "type": "Feature",
  "properties": {
    "addr:full":"90 Crystal Run Rd Ste 409 Middletown NY 10941",
    "addr:housenumber":"90",
    "addr:postcode":"10941",
    "addr:street":"Crystal Run Rd Ste 409",
    "iso:country":"US",
    "sg:address":"90 Crystal Run Rd Ste 409",
    "sg:city":"Middletown",
    "sg:classifiers":[
        {
            "category":"Professional",
            "subcategory":"Lawyer & Legal Services",
            "type":"Services"
        }
    ],
    "sg:phone":"+1 845 988 1515",
    "sg:postcode":"10941",
    "sg:province":"NY",
    "sg:website":"www.mid-hudsonlaw.com",
    "wof:name":"Myrow Jay R The Law Office",
    "wof:placetype":"venue"
},
  "geometry": {"coordinates":[-74.359953,41.448124],"type":"Point"}
}