{
  "type": "Feature",
  "properties": {
    "addr:full":"4315 12th Ave Brooklyn NY 11219",
    "addr:housenumber":"4315",
    "addr:postcode":"11219",
    "addr:street":"12Th Ave",
    "iso:country":"US",
    "sg:address":"4315 12th Ave",
    "sg:city":"Brooklyn",
    "sg:classifiers":[
        {
            "category":"Organizations",
            "subcategory":"Religious Organization",
            "type":"Services"
        }
    ],
    "sg:phone":"+1 718 437 5065",
    "sg:postcode":"11219",
    "sg:province":"NY",
    "wof:name":"Congregation Heichel Tzvi",
    "wof:placetype":"venue"
},
  "geometry": {"coordinates":[-73.991286,40.63919],"type":"Point"}
}