{
  "type": "Feature",
  "properties": {
    "iso:country":"US",
    "sg:address":"28 Howell Dr",
    "sg:city":"Smithtown",
    "sg:classifiers":[
        {
            "category":"Arts & Performance",
            "subcategory":"Theater",
            "type":"Entertainment"
        }
    ],
    "sg:phone":"+1 631 361 7245",
    "sg:postcode":"11787",
    "sg:province":"NY",
    "wof:name":"Glen Anthony Productions Inc",
    "wof:placetype":"venue"
},
  "geometry": {"coordinates":[-73.174447,40.863524],"type":"Point"}
}