{
  "type": "Feature",
  "properties": {
    "addr:full":"163 Atlantic Ave Unit C Lynbrook NY 11563",
    "addr:housenumber":"163",
    "addr:postcode":"11563",
    "addr:street":"Atlantic Ave Unit C",
    "iso:country":"US",
    "sg:address":"163 Atlantic Ave Unit C",
    "sg:city":"Lynbrook",
    "sg:classifiers":[
        {
            "category":"Personal",
            "subcategory":"Beauty Salon",
            "type":"Services"
        }
    ],
    "sg:phone":"+1 516 887 7884",
    "sg:postcode":"11563",
    "sg:province":"NY",
    "wof:name":"Beyond Illusions",
    "wof:placetype":"venue"
},
  "geometry": {"coordinates":[-73.66984600000001,40.651886],"type":"Point"}
}