{
  "type": "Feature",
  "properties": {
    "iso:country":"US",
    "sg:address":"145 E 57th Street",
    "sg:city":"Brooklyn",
    "sg:classifiers":[
        {
            "category":"Building & Trades",
            "subcategory":"Locksmith",
            "type":"Services"
        }
    ],
    "sg:phone":"+1 347 225 8835",
    "sg:postcode":"11203",
    "sg:province":"NY",
    "sg:tags":[
        "key"
    ],
    "wof:name":"000123-57 St Locksmith Anytime 247",
    "wof:placetype":"venue"
},
  "geometry": {"coordinates":[-73.923462,40.651868],"type":"Point"}
}