{
  "type": "Feature",
  "properties": {
    "addr:full":"13775 Queens Blvd Jamaica NY 11435",
    "addr:housenumber":"13775",
    "addr:postcode":"11435",
    "addr:street":"Queens Blvd",
    "iso:country":"US",
    "sg:address":"13775 Queens Blvd",
    "sg:city":"Jamaica",
    "sg:classifiers":[
        {
            "category":"Food & Beverages",
            "subcategory":"Groceries & Convenience Stores",
            "type":"Retail Goods"
        }
    ],
    "sg:phone":"+1 718 291 5353",
    "sg:postcode":"11435",
    "sg:province":"NY",
    "wof:name":"Stop 1 Market",
    "wof:placetype":"venue"
},
  "geometry": {"coordinates":[-73.81860399999999,40.709099],"type":"Point"}
}