{
  "type": "Feature",
  "properties": {
    "addr:full":"165 Schunnemunk Rd Monroe NY 10950",
    "addr:housenumber":"165",
    "addr:postcode":"10950",
    "addr:street":"Schunnemunk Rd",
    "iso:country":"US",
    "sg:address":"165 Schunnemunk Rd",
    "sg:city":"Monroe",
    "sg:classifiers":[
        {
            "category":"Building & Trades",
            "subcategory":"Construction",
            "type":"Services"
        }
    ],
    "sg:phone":"+1 888 642 9100",
    "sg:postcode":"10950",
    "sg:province":"NY",
    "sg:tags":[
        "interior",
        "design"
    ],
    "sg:website":"www.holdnstorage.com",
    "wof:name":"Hold n' Storage",
    "wof:placetype":"venue"
},
  "geometry": {"coordinates":[-74.17865399999999,41.340681],"type":"Point"}
}