{
  "type": "Feature",
  "properties": {
    "addr:full":"240 Clove Rd Staten Island NY 10310",
    "addr:housenumber":"240",
    "addr:postcode":"10310",
    "addr:street":"Clove Rd",
    "iso:country":"US",
    "sg:address":"240 Clove Rd",
    "sg:city":"Staten Island",
    "sg:classifiers":[
        {
            "category":"Retail",
            "subcategory":"Auto Repair",
            "type":"Services"
        }
    ],
    "sg:phone":"+1 718 448 0800",
    "sg:postcode":"10310",
    "sg:province":"NY",
    "sg:tags":[
        "body",
        "shop",
        "painting",
        "automobile"
    ],
    "sg:website":"www.cloveauto.com/",
    "wof:name":"Clove Auto Body",
    "wof:placetype":"venue"
},
  "geometry": {"coordinates":[-74.126648,40.634251],"type":"Point"}
}