{
  "type": "Feature",
  "properties": {
    "addr:full":"460 Stone Rd West Hurley NY 12491",
    "addr:housenumber":"460",
    "addr:postcode":"12491",
    "addr:street":"Stone Rd",
    "iso:country":"US",
    "sg:address":"460 Stone Rd",
    "sg:city":"West Hurley",
    "sg:classifiers":[
        {
            "category":"Building & Trades",
            "subcategory":"Construction",
            "type":"Services"
        }
    ],
    "sg:phone":"+1 845 338 9027",
    "sg:postcode":"12491",
    "sg:province":"NY",
    "sg:tags":[
        "concrete",
        "contractor"
    ],
    "wof:name":"Precision Concrete Structure",
    "wof:placetype":"venue"
},
  "geometry": {"coordinates":[-74.13352,41.934723],"type":"Point"}
}