{
  "type": "Feature",
  "properties": {
    "addr:full":"901 W Beech St Long Beach NY 11561",
    "addr:housenumber":"901",
    "addr:postcode":"11561",
    "addr:street":"W Beech St",
    "iso:country":"US",
    "sg:address":"901 W Beech St",
    "sg:city":"Long Beach",
    "sg:classifiers":[
        {
            "category":"Wholesale",
            "subcategory":"Stationery",
            "type":"Manufacturing & Wholesale Goods"
        }
    ],
    "sg:phone":"+1 516 432 4500",
    "sg:postcode":"11561",
    "sg:province":"NY",
    "sg:tags":[
        "supply"
    ],
    "wof:name":"Computer Forms Plus Inc",
    "wof:placetype":"venue"
},
  "geometry": {"coordinates":[-73.691165,40.586094],"type":"Point"}
}