{
  "type": "Feature",
  "properties": {
    "addr:full":"1342 Military Rd Niagara Falls NY 14304",
    "addr:housenumber":"1342",
    "addr:postcode":"14304",
    "addr:street":"Military Rd",
    "iso:country":"US",
    "sg:address":"1342 Military Rd",
    "sg:city":"Niagara Falls",
    "sg:classifiers":[
        {
            "category":"Professional",
            "subcategory":"Computer Services",
            "type":"Services"
        }
    ],
    "sg:phone":"+1 716 692 2274",
    "sg:postcode":"14304",
    "sg:province":"NY",
    "sg:tags":[
        "prep",
        "design",
        "system",
        "programing",
        "custom"
    ],
    "wof:name":"NTS Data Service Inc",
    "wof:placetype":"venue"
},
  "geometry": {"coordinates":[-78.97003100000001,43.09226],"type":"Point"}
}