{
  "type": "Feature",
  "properties": {
    "iso:country":"US",
    "sg:address":"197 Woodchuck Hill Rd",
    "sg:city":"Newport",
    "sg:classifiers":[
        {
            "category":"Building & Trades",
            "subcategory":"Construction",
            "type":"Services"
        }
    ],
    "sg:phone":"+1 315 845 1616",
    "sg:postcode":"13416",
    "sg:province":"NY",
    "sg:tags":[
        "excavation",
        "contractor"
    ],
    "wof:name":"Rowe Hauling & Excavating",
    "wof:placetype":"venue"
},
  "geometry": {"coordinates":[-74.992098,43.186026],"type":"Point"}
}