{
  "type": "Feature",
  "properties": {
    "addr:full":"1805 Spring Valley Rd Ossining NY 10562",
    "addr:housenumber":"1805",
    "addr:postcode":"10562",
    "addr:street":"Spring Valley Rd",
    "iso:country":"US",
    "sg:address":"1805 Spring Valley Rd",
    "sg:city":"Ossining",
    "sg:classifiers":[
        {
            "category":"Professional",
            "subcategory":"Management & Consulting",
            "type":"Services"
        }
    ],
    "sg:phone":"+1 914 271 3640",
    "sg:postcode":"10562",
    "sg:province":"NY",
    "sg:tags":[
        "marketing",
        "consultant"
    ],
    "wof:name":"Probe Communications Intl Inc",
    "wof:placetype":"venue"
},
  "geometry": {"coordinates":[-73.81590300000001,41.209841],"type":"Point"}
}