{
  "type": "Feature",
  "properties": {
    "addr:full":"62 W 47th Street New York NY 10036",
    "addr:housenumber":"62",
    "addr:postcode":"10036",
    "addr:street":"W 47Th Street",
    "iso:country":"US",
    "sg:address":"62 W 47th Street",
    "sg:city":"New York",
    "sg:classifiers":[
        {
            "category":"Shopping",
            "subcategory":"Jewelry",
            "type":"Retail Goods"
        }
    ],
    "sg:phone":"+1 212 391 2167",
    "sg:postcode":"10036",
    "sg:province":"NY",
    "wof:name":"Central Jewelry Company",
    "wof:placetype":"venue"
},
  "geometry": {"coordinates":[-73.98056800000001,40.757506],"type":"Point"}
}