{
  "type": "Feature",
  "properties": {
    "iso:country":"US",
    "sg:address":"114 W 27 St",
    "sg:city":"New York",
    "sg:classifiers":[
        {
            "category":"Professional",
            "subcategory":"Art Services",
            "type":"Services"
        }
    ],
    "sg:phone":"+1 212 645 8417",
    "sg:postcode":"10001",
    "sg:province":"NY",
    "sg:tags":[
        "photo",
        "photography",
        "commercial",
        "studio",
        "portrait"
    ],
    "wof:name":"Lyn Hughes Photography",
    "wof:placetype":"venue"
},
  "geometry": {"coordinates":[-73.99354099999999,40.746381],"type":"Point"}
}