{
  "type": "Feature",
  "properties": {
    "iso:country":"US",
    "sg:address":"1672 Monroe Ave",
    "sg:city":"Rochester",
    "sg:classifiers":[
        {
            "category":"Professional",
            "subcategory":"Accounting & Tax Preparation",
            "type":"Services"
        }
    ],
    "sg:phone":"+1   ",
    "sg:postcode":"14618",
    "sg:province":"NY",
    "wof:name":"Lori K Locey CPA",
    "wof:placetype":"venue"
},
  "geometry": {"coordinates":[-77.56930199999999,43.131195],"type":"Point"}
}