{
  "type": "Feature",
  "properties": {
    "addr:full":"260 North Rd Poughkeepsie NY 12601",
    "addr:housenumber":"260",
    "addr:postcode":"12601",
    "addr:street":"North Rd",
    "iso:country":"US",
    "sg:address":"260 North Rd",
    "sg:city":"Poughkeepsie",
    "sg:classifiers":[
        {
            "category":"Wholesale",
            "subcategory":"Medical Equipment & Supplies",
            "type":"Manufacturing & Wholesale Goods"
        }
    ],
    "sg:phone":"+1 845 471 1010",
    "sg:postcode":"12601",
    "sg:province":"NY",
    "wof:name":"Alamo Med & Surgical Sup Co",
    "wof:placetype":"venue"
},
  "geometry": {"coordinates":[-73.932225,41.736074],"type":"Point"}
}