{
  "type": "Feature",
  "properties": {
    "addr:full":"221 Madison St New York NY 10002",
    "addr:housenumber":"221",
    "addr:postcode":"10002",
    "addr:street":"Madison St",
    "iso:country":"US",
    "sg:address":"221 Madison St",
    "sg:city":"New York",
    "sg:classifiers":[
        {
            "category":"Professional",
            "subcategory":"Accounting & Tax Preparation",
            "type":"Services"
        }
    ],
    "sg:phone":"+1 212 227 1819",
    "sg:postcode":"10002",
    "sg:province":"NY",
    "sg:tags":[
        "return",
        "filing"
    ],
    "sg:website":"www.jacksonhewitt.com",
    "wof:name":"Jackson Hewitt Tax Svc",
    "wof:placetype":"venue"
},
  "geometry": {"coordinates":[-73.988917,40.712797],"type":"Point"}
}