{
  "type": "Feature",
  "properties": {
    "addr:full":"40 Atkinson St Rochester NY 14608",
    "addr:housenumber":"40",
    "addr:postcode":"14608",
    "addr:street":"Atkinson St",
    "iso:country":"US",
    "sg:address":"40 Atkinson St",
    "sg:city":"Rochester",
    "sg:classifiers":[
        {
            "category":"Building & Trades",
            "subcategory":"Construction",
            "type":"Services"
        }
    ],
    "sg:phone":"+1 585 232 4890",
    "sg:postcode":"14608",
    "sg:province":"NY",
    "sg:tags":[
        "painter"
    ],
    "wof:name":"A-1 Services",
    "wof:placetype":"venue"
},
  "geometry": {"coordinates":[-77.615746,43.149909],"type":"Point"}
}