{
  "type": "Feature",
  "properties": {
    "addr:full":"24 S Greeley Ave Chappaqua NY 10514",
    "addr:housenumber":"24",
    "addr:postcode":"10514",
    "addr:street":"S Greeley Ave",
    "iso:country":"US",
    "sg:address":"24 S Greeley Ave",
    "sg:city":"Chappaqua",
    "sg:classifiers":[
        {
            "category":"Personal",
            "subcategory":"Day Spa",
            "type":"Services"
        }
    ],
    "sg:phone":"+1 914 238 8830",
    "sg:postcode":"10514",
    "sg:province":"NY",
    "sg:website":"www.emmarydayspa.com",
    "wof:name":"Emmary Day Spa",
    "wof:placetype":"venue"
},
  "geometry": {"coordinates":[-73.772757,41.158927],"type":"Point"}
}