{
  "type": "Feature",
  "properties": {
    "iso:country":"US",
    "sg:address":"2500 Richmond Ave",
    "sg:city":"Staten Island",
    "sg:classifiers":[
        {
            "category":"Building & Trades",
            "subcategory":"Plumbing",
            "type":"Services"
        },
        {
            "category":"Building & Trades",
            "subcategory":"Construction",
            "type":"Services"
        }
    ],
    "sg:phone":"+1 718 966 8600",
    "sg:postcode":"10314",
    "sg:province":"NY",
    "sg:tags":[
        "contractor"
    ],
    "sg:website":"www.siplumbing.com",
    "wof:name":"Staten Island Plumbing",
    "wof:placetype":"venue"
},
  "geometry": {"coordinates":[-74.16817,40.588035],"type":"Point"}
}