{
  "type": "Feature",
  "properties": {
    "iso:country":"US",
    "sg:address":"29 E Kingsbridge Road",
    "sg:city":"Bronx",
    "sg:classifiers":[
        {
            "category":"Food & Beverages",
            "subcategory":"Groceries & Convenience Stores",
            "type":"Retail Goods"
        }
    ],
    "sg:phone":"+1 800 293 8606",
    "sg:postcode":"10468",
    "sg:province":"NY",
    "wof:name":"Short Stop Candy & Grocery Store",
    "wof:placetype":"venue"
},
  "geometry": {"coordinates":[-73.896338,40.867179],"type":"Point"}
}