{
  "type": "Feature",
  "properties": {
    "iso:country":"US",
    "sg:address":"4861 N Jefferson St",
    "sg:city":"Pulaski",
    "sg:classifiers":[
        {
            "category":"Building & Trades",
            "subcategory":"Equipment Rental",
            "type":"Services"
        }
    ],
    "sg:phone":"+1 315 298 6930",
    "sg:postcode":"13142",
    "sg:province":"NY",
    "sg:tags":[
        "camping"
    ],
    "wof:name":"Rent A Tent Inc",
    "wof:placetype":"venue"
},
  "geometry": {"coordinates":[-76.127371,43.567234],"type":"Point"}
}