{
  "type": "Feature",
  "properties": {
    "iso:country":"US",
    "sg:address":"2552 State Hwy 89",
    "sg:city":"Seneca Falls",
    "sg:classifiers":[
        {
            "category":"Arts & Performance",
            "subcategory":"Theater",
            "type":"Entertainment"
        }
    ],
    "sg:phone":"+1 315 568 0994",
    "sg:postcode":"13148",
    "sg:province":"NY",
    "sg:tags":[
        "bureau"
    ],
    "wof:name":"Lakeside Entertainment",
    "wof:placetype":"venue"
},
  "geometry": {"coordinates":[-76.754853,42.901222],"type":"Point"}
}