{
  "type": "Feature",
  "properties": {
    "iso:country":"US",
    "sg:address":"1100 Howard St",
    "sg:city":"Peekskill",
    "sg:classifiers":[
        {
            "category":"Real Estate",
            "subcategory":"Real Estate Agent",
            "type":"Services"
        }
    ],
    "sg:phone":"+1 914 736 9247",
    "sg:postcode":"10566",
    "sg:province":"NY",
    "wof:name":"Williams Realty",
    "wof:placetype":"venue"
},
  "geometry": {"coordinates":[-73.91534299999999,41.292994],"type":"Point"}
}