{
  "type": "Feature",
  "properties": {
    "addr:full":"48 Wall St New York NY 10005",
    "addr:housenumber":"48",
    "addr:postcode":"10005",
    "addr:street":"Wall St",
    "iso:country":"US",
    "sg:address":"48 Wall St",
    "sg:city":"New York",
    "sg:classifiers":[
        {
            "category":"Health Services",
            "subcategory":"Clinic",
            "type":"Services"
        }
    ],
    "sg:phone":"+1 212 346 9000",
    "sg:postcode":"10005",
    "sg:province":"NY",
    "sg:website":"www.lordspv.com",
    "wof:name":"Daiwa Health Co-2 Inc",
    "wof:placetype":"venue"
},
  "geometry": {"coordinates":[-74.008813,40.706012],"type":"Point"}
}