{
  "type": "Feature",
  "properties": {
    "addr:full":"387 E Fordham Rd Bronx NY 10458",
    "addr:housenumber":"387",
    "addr:postcode":"10458",
    "addr:street":"E Fordham Rd",
    "iso:country":"US",
    "sg:address":"387 E Fordham Rd",
    "sg:city":"Bronx",
    "sg:classifiers":[
        {
            "category":"Retail",
            "subcategory":"Repair Shop",
            "type":"Services"
        }
    ],
    "sg:phone":"+1 718 764 5337",
    "sg:postcode":"10458",
    "sg:province":"NY",
    "sg:tags":[
        "lock",
        "locksmith"
    ],
    "wof:name":"24 7 Emergency Locksmith",
    "wof:placetype":"venue"
},
  "geometry": {"coordinates":[-73.89138,40.861701],"type":"Point"}
}