{
  "type": "Feature",
  "properties": {
    "addr:full":"120 Bay St Vestal NY 13850",
    "addr:housenumber":"120",
    "addr:postcode":"13850",
    "addr:street":"Bay St",
    "iso:country":"US",
    "sg:address":"120 Bay St",
    "sg:city":"Vestal",
    "sg:classifiers":[
        {
            "category":"Wholesale",
            "subcategory":"Apparel",
            "type":"Manufacturing & Wholesale Goods"
        }
    ],
    "sg:phone":"+1 607 584 5000",
    "sg:postcode":"13850",
    "sg:province":"NY",
    "sg:tags":[
        "safety",
        "shoes"
    ],
    "wof:name":"E J Footwear",
    "wof:placetype":"venue"
},
  "geometry": {"coordinates":[-75.948581,42.084765],"type":"Point"}
}