{
  "type": "Feature",
  "properties": {
    "iso:country":"US",
    "sg:address":"335 W 16th St",
    "sg:city":"New York",
    "sg:classifiers":[
        {
            "category":"Sports & Exercise",
            "subcategory":"Gym",
            "type":"Entertainment"
        }
    ],
    "sg:phone":"+1 212 206 6472",
    "sg:postcode":"10011",
    "sg:province":"NY",
    "sg:tags":[
        "trainer"
    ],
    "sg:website":"www.libertyhealthadvantage.com",
    "wof:name":"Liberty Health Advantage",
    "wof:placetype":"venue"
},
  "geometry": {"coordinates":[-74.463185,40.741615],"type":"Point"}
}