{
  "type": "Feature",
  "properties": {
    "addr:full":"888 7th Avenue New York NY 10106",
    "addr:housenumber":"888",
    "addr:postcode":"10106",
    "addr:street":"7Th Avenue",
    "iso:country":"US",
    "sg:address":"888 7th Avenue",
    "sg:city":"New York",
    "sg:classifiers":[
        {
            "category":"Professional",
            "subcategory":"Computer Services",
            "type":"Services"
        }
    ],
    "sg:phone":"+1 212 492 5800",
    "sg:postcode":"10106",
    "sg:province":"NY",
    "sg:website":"http://www.kaplan.com",
    "wof:name":"Kaplan",
    "wof:placetype":"venue"
},
  "geometry": {"coordinates":[-73.99110899999999,40.750319],"type":"Point"}
}