{
  "type": "Feature",
  "properties": {
    "addr:full":"915 Ditmas Ave Brooklyn NY 11218",
    "addr:housenumber":"915",
    "addr:postcode":"11218",
    "addr:street":"Ditmas Ave",
    "iso:country":"US",
    "sg:address":"915 Ditmas Ave",
    "sg:city":"Brooklyn",
    "sg:classifiers":[
        {
            "category":"Wholesale",
            "subcategory":"Auto Parts",
            "type":"Manufacturing & Wholesale Goods"
        }
    ],
    "sg:phone":"+1 718 768 8884",
    "sg:postcode":"11218",
    "sg:province":"NY",
    "sg:tags":[
        "material",
        "used"
    ],
    "wof:name":"Anton Junicic Enterpises",
    "wof:placetype":"venue"
},
  "geometry": {"coordinates":[-73.968192,40.636705],"type":"Point"}
}