{
  "type": "Feature",
  "properties": {
    "addr:full":"282a 19th St Ste 2 Brooklyn NY 11215",
    "addr:housenumber":"282a",
    "addr:postcode":"11215",
    "addr:street":"19Th St Ste 2",
    "iso:country":"US",
    "sg:address":"282a 19th St Ste 2",
    "sg:city":"Brooklyn",
    "sg:classifiers":[
        {
            "category":"Professional",
            "subcategory":"Art Services",
            "type":"Services"
        },
        {
            "category":"Communications",
            "type":"Services"
        }
    ],
    "sg:phone":"+1 516 643 3185",
    "sg:postcode":"11215",
    "sg:province":"NY",
    "sg:tags":[
        "web",
        "graphic",
        "design"
    ],
    "sg:website":"dianakdesign.com",
    "wof:name":"Dianak Design",
    "wof:placetype":"venue"
},
  "geometry": {"coordinates":[-73.990841,40.661328],"type":"Point"}
}