{
  "type": "Feature",
  "properties": {
    "addr:full":"309 Fanning Blvd Riverhead NY 11901",
    "addr:housenumber":"309",
    "addr:postcode":"11901",
    "addr:street":"Fanning Blvd",
    "iso:country":"US",
    "sg:address":"309 Fanning Blvd",
    "sg:city":"Riverhead",
    "sg:classifiers":[
        {
            "category":"Professional",
            "subcategory":"Lawyer & Legal Services",
            "type":"Services"
        }
    ],
    "sg:phone":"+1 631 369 4925",
    "sg:postcode":"11901",
    "sg:province":"NY",
    "wof:name":"Gotcha Legal Process Svc",
    "wof:placetype":"venue"
},
  "geometry": {"coordinates":[-72.656504,40.939509],"type":"Point"}
}