{
  "type": "Feature",
  "properties": {
    "iso:country":"US",
    "sg:address":"91 Park St",
    "sg:city":"Binghamton",
    "sg:classifiers":[
        {
            "category":"Organizations",
            "subcategory":"Religious Organization",
            "type":"Services"
        }
    ],
    "sg:phone":"+1 607 729 4003",
    "sg:postcode":"13905",
    "sg:province":"NY",
    "sg:tags":[
        "clergy"
    ],
    "wof:name":"C Earle Cowden",
    "wof:placetype":"venue"
},
  "geometry": {"coordinates":[-75.94527600000001,42.106316],"type":"Point"}
}