{
  "type": "Feature",
  "properties": {
    "addr:full":"420 Broadway Brooklyn NY 11211",
    "addr:housenumber":"420",
    "addr:postcode":"11211",
    "addr:street":"Broadway",
    "iso:country":"US",
    "sg:address":"420 Broadway",
    "sg:city":"Brooklyn",
    "sg:classifiers":[
        {
            "category":"Real Estate",
            "subcategory":"Real Estate Agent",
            "type":"Services"
        }
    ],
    "sg:phone":"+1 718 599 7000",
    "sg:postcode":"11211",
    "sg:province":"NY",
    "sg:tags":[
        "management"
    ],
    "wof:name":"USA Home Financial LLC",
    "wof:placetype":"venue"
},
  "geometry": {"coordinates":[-73.952913,40.7067],"type":"Point"}
}