{
  "type": "Feature",
  "properties": {
    "iso:country":"US",
    "sg:address":"Windsor Hwy",
    "sg:city":"New Windsor",
    "sg:classifiers":[
        {
            "category":"Retail",
            "subcategory":"Funeral Services",
            "type":"Services"
        }
    ],
    "sg:phone":"+1 845 561 5473",
    "sg:postcode":"12553",
    "sg:province":"NY",
    "sg:tags":[
        "cemetery"
    ],
    "wof:name":"Calvary Cemetery",
    "wof:placetype":"venue"
},
  "geometry": {"coordinates":[-74.05880000000001,41.4692],"type":"Point"}
}