{
  "type": "Feature",
  "properties": {
    "addr:full":"250 Varet St Brooklyn NY 11206",
    "addr:housenumber":"250",
    "addr:postcode":"11206",
    "addr:street":"Varet St",
    "iso:country":"US",
    "sg:address":"250 Varet St",
    "sg:city":"Brooklyn",
    "sg:classifiers":[
        {
            "category":"Retail",
            "subcategory":"Auto Repair",
            "type":"Services"
        }
    ],
    "sg:phone":"+1 718 456 4370",
    "sg:postcode":"11206",
    "sg:province":"NY",
    "sg:tags":[
        "body",
        "automobile",
        "painting"
    ],
    "wof:name":"Nick's Auto Collision",
    "wof:placetype":"venue"
},
  "geometry": {"coordinates":[-73.933988,40.703952],"type":"Point"}
}