{
  "type": "Feature",
  "properties": {
    "addr:full":"155 White Plains Rd Tarrytown NY 10591",
    "addr:housenumber":"155",
    "addr:postcode":"10591",
    "addr:street":"White Plains Rd",
    "iso:country":"US",
    "sg:address":"155 White Plains Rd",
    "sg:city":"Tarrytown",
    "sg:classifiers":[
        {
            "category":"Organizations",
            "subcategory":"Political Organization",
            "type":"Services"
        }
    ],
    "sg:phone":"+1 914 631 8990",
    "sg:postcode":"10591",
    "sg:province":"NY",
    "sg:tags":[
        "international",
        "membership"
    ],
    "wof:name":"Wango",
    "wof:placetype":"venue"
},
  "geometry": {"coordinates":[-73.85441299999999,41.064211],"type":"Point"}
}