{
  "type": "Feature",
  "properties": {
    "iso:country":"US",
    "sg:address":"518 Montauk Hwy",
    "sg:city":"Eastport",
    "sg:classifiers":[
        {
            "category":"Shopping",
            "type":"Retail Goods"
        }
    ],
    "sg:phone":"+1 631 325 1504",
    "sg:postcode":"11941",
    "sg:province":"NY",
    "sg:tags":[
        "art",
        "gallery",
        "dealer"
    ],
    "wof:name":"Art N Soul Studio",
    "wof:placetype":"venue"
},
  "geometry": {"coordinates":[-72.730356,40.825798],"type":"Point"}
}