{
  "type": "Feature",
  "properties": {
    "addr:full":"396 W 255th St Bronx NY 10471",
    "addr:housenumber":"396",
    "addr:postcode":"10471",
    "addr:street":"W 255Th St",
    "iso:country":"US",
    "sg:address":"396 W 255th St",
    "sg:city":"Bronx",
    "sg:classifiers":[
        {
            "category":"Building & Trades",
            "subcategory":"Construction",
            "type":"Services"
        }
    ],
    "sg:phone":"+1 718 601 8354",
    "sg:postcode":"10471",
    "sg:province":"NY",
    "sg:tags":[
        "general",
        "contractor"
    ],
    "wof:name":"Hudsonview Construction",
    "wof:placetype":"venue"
},
  "geometry": {"coordinates":[-73.903784,40.902549],"type":"Point"}
}