{
  "type": "Feature",
  "properties": {
    "iso:country":"US",
    "sg:address":"710 State Highway 2",
    "sg:city":"Troy",
    "sg:classifiers":[
        {
            "category":"Professional",
            "subcategory":"Lawyer & Legal Services",
            "type":"Services"
        }
    ],
    "sg:phone":"+1 518 279 4292",
    "sg:postcode":"12180",
    "sg:province":"NY",
    "sg:tags":[
        "attorney",
        "practice"
    ],
    "wof:name":"Jr Kenneth Mc Guire",
    "wof:placetype":"venue"
},
  "geometry": {"coordinates":[-73.581749,42.734985],"type":"Point"}
}