{
  "type": "Feature",
  "properties": {
    "addr:full":"420 W State St Olean NY 14760",
    "addr:housenumber":"420",
    "addr:postcode":"14760",
    "addr:street":"W State St",
    "iso:country":"US",
    "sg:address":"420 W State St",
    "sg:city":"Olean",
    "sg:classifiers":[
        {
            "category":"Real Estate",
            "subcategory":"Real Estate Agent",
            "type":"Services"
        }
    ],
    "sg:phone":"+1 716 373 2025",
    "sg:postcode":"14760",
    "sg:province":"NY",
    "wof:name":"Gabriel American Realty",
    "wof:placetype":"venue"
},
  "geometry": {"coordinates":[-78.434079,42.077533],"type":"Point"}
}