{
  "type": "Feature",
  "properties": {
    "addr:full":"118 Wabash Ave Rochester NY 14617",
    "addr:housenumber":"118",
    "addr:postcode":"14617",
    "addr:street":"Wabash Ave",
    "iso:country":"US",
    "sg:address":"118 Wabash Ave",
    "sg:city":"Rochester",
    "sg:classifiers":[
        {
            "category":"Building & Trades",
            "subcategory":"Construction",
            "type":"Services"
        }
    ],
    "sg:phone":"+1 585 342 4405",
    "sg:postcode":"14617",
    "sg:province":"NY",
    "sg:tags":[
        "carpenter",
        "contractor"
    ],
    "wof:name":"Valco Construction",
    "wof:placetype":"venue"
},
  "geometry": {"coordinates":[-77.598882,43.251653],"type":"Point"}
}