{
  "type": "Feature",
  "properties": {
    "iso:country":"US",
    "sg:address":"6662 Boston State Rd",
    "sg:city":"Hamburg",
    "sg:classifiers":[
        {
            "category":"Shopping",
            "subcategory":"Bicycles & Sporting Goods",
            "type":"Retail Goods"
        }
    ],
    "sg:phone":"+1 716 646 1319",
    "sg:postcode":"14075",
    "sg:province":"NY",
    "sg:tags":[
        "equipment",
        "exercise"
    ],
    "wof:name":"Jacobs Ladder",
    "wof:placetype":"venue"
},
  "geometry": {"coordinates":[-78.79942699999999,42.707027],"type":"Point"}
}