{
  "type": "Feature",
  "properties": {
    "addr:full":"517 Steuben Rd Herkimer NY 13350",
    "addr:housenumber":"517",
    "addr:postcode":"13350",
    "addr:street":"Steuben Rd",
    "iso:country":"US",
    "sg:address":"517 Steuben Rd",
    "sg:city":"Herkimer",
    "sg:classifiers":[
        {
            "category":"Retail",
            "subcategory":"Laundry & Dry Cleaning",
            "type":"Services"
        }
    ],
    "sg:phone":"+1   ",
    "sg:postcode":"13350",
    "sg:province":"NY",
    "wof:name":"Le Annes Style and Dry Clg Sp",
    "wof:placetype":"venue"
},
  "geometry": {"coordinates":[-74.99014699999999,43.034672],"type":"Point"}
}