{
  "type": "Feature",
  "properties": {
    "iso:country":"US",
    "sg:address":"26 Leroy Ave",
    "sg:city":"Tarrytown",
    "sg:classifiers":[
        {
            "category":"Professional",
            "type":"Services"
        },
        {
            "category":"Professional",
            "subcategory":"Management & Consulting",
            "type":"Services"
        }
    ],
    "sg:phone":"+1 914 631 6442",
    "sg:postcode":"10591",
    "sg:province":"NY",
    "sg:tags":[
        "building",
        "use",
        "selection",
        "consultant",
        "site",
        "land",
        "establishment"
    ],
    "wof:name":"Vandor & Vandor Ltd",
    "wof:placetype":"venue"
},
  "geometry": {"coordinates":[-73.859832,41.06959],"type":"Point"}
}