{
  "type": "Feature",
  "properties": {
    "iso:country":"US",
    "sg:address":"1618 Ave M",
    "sg:city":"Brooklyn",
    "sg:classifiers":[
        {
            "category":"Cinema",
            "subcategory":"Movie Rental",
            "type":"Entertainment"
        }
    ],
    "sg:phone":"+1   ",
    "sg:postcode":"11230",
    "sg:province":"NY",
    "sg:tags":[
        "video",
        "tape"
    ],
    "wof:name":"Ave M Video",
    "wof:placetype":"venue"
},
  "geometry": {"coordinates":[-73.95827,40.618124],"type":"Point"}
}