{
  "type": "Feature",
  "properties": {
    "iso:country":"US",
    "sg:address":"4610 Wetzel Rd",
    "sg:city":"Liverpool",
    "sg:classifiers":[
        {
            "category":"Social Services",
            "subcategory":"Child Care",
            "type":"Services"
        }
    ],
    "sg:phone":"+1 315 622 4815",
    "sg:postcode":"13090",
    "sg:province":"NY",
    "wof:name":"Before & After School Child",
    "wof:placetype":"venue"
},
  "geometry": {"coordinates":[-76.192667,43.150704],"type":"Point"}
}