{
  "type": "Feature",
  "properties": {
    "iso:country":"US",
    "sg:address":"1 Hunter Ave",
    "sg:city":"Armonk",
    "sg:classifiers":[
        {
            "category":"Education",
            "subcategory":"Music School",
            "type":"Public Place"
        }
    ],
    "sg:phone":"+1 914 765 0461",
    "sg:postcode":"10504",
    "sg:province":"NY",
    "sg:tags":[
        "instrument",
        "teacher",
        "musical"
    ],
    "wof:name":"Soundworks Inc",
    "wof:placetype":"venue"
},
  "geometry": {"coordinates":[-73.700136,41.124976],"type":"Point"}
}