{
  "type": "Feature",
  "properties": {
    "iso:country":"US",
    "sg:address":"230 Park St",
    "sg:city":"New Canaan",
    "sg:classifiers":[
        {
            "category":"Wholesale",
            "subcategory":"Non-durable Goods",
            "type":"Manufacturing & Wholesale Goods"
        }
    ],
    "sg:phone":"+1 203 966 7061",
    "sg:postcode":"06840",
    "sg:province":"NY",
    "wof:name":"Eastern Moon Imports LLC",
    "wof:placetype":"venue"
},
  "geometry": {"coordinates":[-73.49423899999999,41.140989],"type":"Point"}
}