{
  "type": "Feature",
  "properties": {
    "addr:full":"88 3rd Ave Brooklyn NY 11217",
    "addr:housenumber":"88",
    "addr:postcode":"11217",
    "addr:street":"3Rd Ave",
    "iso:country":"US",
    "sg:address":"88 3rd Ave",
    "sg:city":"Brooklyn",
    "sg:classifiers":[
        {
            "category":"Organizations",
            "subcategory":"Membership Organization",
            "type":"Services"
        }
    ],
    "sg:phone":"+1 718 222 1088",
    "sg:postcode":"11217",
    "sg:province":"NY",
    "wof:name":"New York City Parent Orgnzng",
    "wof:placetype":"venue"
},
  "geometry": {"coordinates":[-73.98192,40.683724],"type":"Point"}
}