{
  "type": "Feature",
  "properties": {
    "iso:country":"US",
    "sg:address":"208 Plitt Ave",
    "sg:city":"Farmingdale",
    "sg:classifiers":[
        {
            "category":"Professional",
            "type":"Services"
        }
    ],
    "sg:phone":"+1   ",
    "sg:postcode":"11735",
    "sg:province":"NY",
    "wof:name":"Plant Guy Inc",
    "wof:placetype":"venue"
},
  "geometry": {"coordinates":[-73.453729,40.718928],"type":"Point"}
}