{
  "type": "Feature",
  "properties": {
    "iso:country":"US",
    "sg:address":"434 W 120th Street",
    "sg:city":"New York",
    "sg:classifiers":[
        {
            "category":"Building & Trades",
            "subcategory":"Construction",
            "type":"Services"
        }
    ],
    "sg:phone":"+1 212 864 3181",
    "sg:postcode":"10027",
    "sg:province":"NY",
    "sg:tags":[
        "contractor"
    ],
    "sg:website":"www.mamais.com",
    "wof:name":"Mamais Contracting",
    "wof:placetype":"venue"
},
  "geometry": {"coordinates":[-73.958169,40.808877],"type":"Point"}
}