{
  "type": "Feature",
  "properties": {
    "iso:country":"US",
    "sg:address":"3048 W 12th St",
    "sg:city":"Brooklyn",
    "sg:classifiers":[
        {
            "category":"Arts & Performance",
            "subcategory":"Theater",
            "type":"Entertainment"
        }
    ],
    "sg:phone":"+1 718 266 8463",
    "sg:postcode":"11224",
    "sg:province":"NY",
    "sg:tags":[
        "bureau"
    ],
    "wof:name":"Coney Island Entertainment Inc",
    "wof:placetype":"venue"
},
  "geometry": {"coordinates":[-73.979764,40.573598],"type":"Point"}
}