{
  "type": "Feature",
  "properties": {
    "iso:country":"US",
    "sg:address":"444 State Hwy 211",
    "sg:city":"Middletown",
    "sg:classifiers":[
        {
            "category":"Retail",
            "subcategory":"Auto Repair",
            "type":"Services"
        }
    ],
    "sg:phone":"+1 845 344 0576",
    "sg:postcode":"10940",
    "sg:province":"NY",
    "sg:tags":[
        "repairing",
        "automobile"
    ],
    "wof:name":"Penske Auto Ctr",
    "wof:placetype":"venue"
},
  "geometry": {"coordinates":[-74.44980099999999,41.465475],"type":"Point"}
}