{
  "type": "Feature",
  "properties": {
    "iso:country":"US",
    "sg:address":"609 Dingens St",
    "sg:city":"Buffalo",
    "sg:classifiers":[
        {
            "category":"Social Services",
            "subcategory":"Job Training",
            "type":"Services"
        }
    ],
    "sg:phone":"+1 716 891 9591",
    "sg:postcode":"14206",
    "sg:province":"NY",
    "sg:tags":[
        "rehabilitation"
    ],
    "wof:name":"Comprehensive Rehabilitation",
    "wof:placetype":"venue"
},
  "geometry": {"coordinates":[-78.79482,42.877624],"type":"Point"}
}