{
  "type": "Feature",
  "properties": {
    "addr:full":"225 Broad St Staten Island NY 10304",
    "addr:housenumber":"225",
    "addr:postcode":"10304",
    "addr:street":"Broad St",
    "iso:country":"US",
    "sg:address":"225 Broad St",
    "sg:city":"Staten Island",
    "sg:classifiers":[
        {
            "category":"Professional",
            "subcategory":"Accounting & Tax Preparation",
            "type":"Services"
        }
    ],
    "sg:phone":"+1 718 273 9170",
    "sg:postcode":"10304",
    "sg:province":"NY",
    "sg:tags":[
        "return",
        "filing"
    ],
    "wof:name":"Jackson Hewitt",
    "wof:placetype":"venue"
},
  "geometry": {"coordinates":[-74.082134,40.623936],"type":"Point"}
}