{
  "type": "Feature",
  "properties": {
    "iso:country":"US",
    "sg:address":"328 Etna St",
    "sg:city":"Brooklyn",
    "sg:classifiers":[
        {
            "category":"Professional",
            "type":"Services"
        }
    ],
    "sg:phone":"+1   ",
    "sg:postcode":"11208",
    "sg:province":"NY",
    "wof:name":"Godfrey Grenion",
    "wof:placetype":"venue"
},
  "geometry": {"coordinates":[-73.872848,40.686882],"type":"Point"}
}