{
  "type": "Feature",
  "properties": {
    "addr:full":"9 Baywood Ln Bayport NY 11705",
    "addr:housenumber":"9",
    "addr:postcode":"11705",
    "addr:street":"Baywood Ln",
    "iso:country":"US",
    "sg:address":"9 Baywood Ln",
    "sg:city":"Bayport",
    "sg:classifiers":[
        {
            "category":"Building & Trades",
            "subcategory":"Construction",
            "type":"Services"
        }
    ],
    "sg:phone":"+1 631 472 4791",
    "sg:postcode":"11705",
    "sg:province":"NY",
    "sg:tags":[
        "contractor"
    ],
    "wof:name":"Bertolino Brothers Pools Inc",
    "wof:placetype":"venue"
},
  "geometry": {"coordinates":[-73.069059,40.737459],"type":"Point"}
}