{
  "type": "Feature",
  "properties": {
    "iso:country":"US",
    "sg:address":"901 Old Liverpool Rd",
    "sg:city":"Liverpool",
    "sg:classifiers":[
        {
            "category":"Real Estate",
            "subcategory":"Real Estate Agent",
            "type":"Services"
        }
    ],
    "sg:phone":"+1 315 457 0032",
    "sg:postcode":"13088",
    "sg:province":"NY",
    "sg:tags":[
        "broker"
    ],
    "wof:name":"Rita Taylor Real Estate Inc",
    "wof:placetype":"venue"
},
  "geometry": {"coordinates":[-76.198717,43.099622],"type":"Point"}
}