{
  "type": "Feature",
  "properties": {
    "addr:full":"178 Garfield St Rochester NY 14611",
    "addr:housenumber":"178",
    "addr:postcode":"14611",
    "addr:street":"Garfield St",
    "iso:country":"US",
    "sg:address":"178 Garfield St",
    "sg:city":"Rochester",
    "sg:classifiers":[
        {
            "category":"Personal",
            "subcategory":"Beauty Salon",
            "type":"Services"
        }
    ],
    "sg:phone":"+1   ",
    "sg:postcode":"14611",
    "sg:province":"NY",
    "sg:tags":[
        "shop"
    ],
    "wof:name":"Kut Kleen",
    "wof:placetype":"venue"
},
  "geometry": {"coordinates":[-77.654534,43.144769],"type":"Point"}
}