{
  "type": "Feature",
  "properties": {
    "iso:country":"US",
    "sg:address":"1420 Williamsbridge Rd",
    "sg:city":"Bronx",
    "sg:classifiers":[
        {
            "category":"Professional",
            "subcategory":"Employment Agencies",
            "type":"Services"
        }
    ],
    "sg:phone":"+1 718 794 3613",
    "sg:postcode":"10461",
    "sg:province":"NY",
    "wof:name":"New York Driving School",
    "wof:placetype":"venue"
},
  "geometry": {"coordinates":[-73.84433900000001,40.842413],"type":"Point"}
}