{
  "type": "Feature",
  "properties": {
    "addr:full":"16 W 36 St New York NY 10018",
    "addr:housenumber":"16",
    "addr:postcode":"10018",
    "addr:street":"W 36 St",
    "iso:country":"US",
    "sg:address":"16 W 36 St",
    "sg:city":"New York",
    "sg:classifiers":[
        {
            "category":"Wholesale",
            "subcategory":"Apparel",
            "type":"Manufacturing & Wholesale Goods"
        }
    ],
    "sg:phone":"+1 212 947 3790",
    "sg:postcode":"10018",
    "sg:province":"NY",
    "sg:tags":[
        "woolen",
        "worsted",
        "woven",
        "lad",
        "fabric"
    ],
    "wof:name":"Claremore Textiles Corp",
    "wof:placetype":"venue"
},
  "geometry": {"coordinates":[-73.986529,40.750818],"type":"Point"}
}