{
  "type": "Feature",
  "properties": {
    "addr:full":"313 W 37th St New York NY 10018",
    "addr:housenumber":"313",
    "addr:postcode":"10018",
    "addr:street":"W 37Th St",
    "iso:country":"US",
    "sg:address":"313 W 37th St",
    "sg:city":"New York",
    "sg:classifiers":[
        {
            "category":"Real Estate",
            "subcategory":"Real Estate Agent",
            "type":"Services"
        }
    ],
    "sg:phone":"+1 212 563 1428",
    "sg:postcode":"10018",
    "sg:province":"NY",
    "wof:name":"Barry Gorman",
    "wof:placetype":"venue"
},
  "geometry": {"coordinates":[-73.99462200000001,40.75521],"type":"Point"}
}