{
  "type": "Feature",
  "properties": {
    "addr:full":"25 Carmine St New York NY 10014",
    "addr:housenumber":"25",
    "addr:postcode":"10014",
    "addr:street":"Carmine St",
    "iso:country":"US",
    "sg:address":"25 Carmine St",
    "sg:city":"New York",
    "sg:classifiers":[
        {
            "category":"Insurance",
            "subcategory":"Hazard Insurance",
            "type":"Services"
        }
    ],
    "sg:phone":"+1 212 974 8758",
    "sg:postcode":"10014",
    "sg:province":"NY",
    "sg:tags":[
        "fund",
        "pension"
    ],
    "wof:name":"Acim Acli",
    "wof:placetype":"venue"
},
  "geometry": {"coordinates":[-74.003703,40.730042],"type":"Point"}
}