{
  "type": "Feature",
  "properties": {
    "addr:full":"218 Dutton Ave Buffalo NY 14211",
    "addr:housenumber":"218",
    "addr:postcode":"14211",
    "addr:street":"Dutton Ave",
    "iso:country":"US",
    "sg:address":"218 Dutton Ave",
    "sg:city":"Buffalo",
    "sg:classifiers":[
        {
            "category":"Social Services",
            "subcategory":"Child Care",
            "type":"Services"
        }
    ],
    "sg:phone":"+1   ",
    "sg:postcode":"14211",
    "sg:province":"NY",
    "sg:tags":[
        "day"
    ],
    "wof:name":"Forever Young Day Care",
    "wof:placetype":"venue"
},
  "geometry": {"coordinates":[-78.83273,42.920644],"type":"Point"}
}