{
  "type": "Feature",
  "properties": {
    "addr:full":"417 Larkfield Rd East Northport NY 11731",
    "addr:housenumber":"417",
    "addr:postcode":"11731",
    "addr:street":"Larkfield Rd",
    "iso:country":"US",
    "sg:address":"417 Larkfield Rd",
    "sg:city":"East Northport",
    "sg:classifiers":[
        {
            "category":"Professional",
            "type":"Services"
        }
    ],
    "sg:phone":"+1 631 754 6100",
    "sg:postcode":"11731",
    "sg:province":"NY",
    "sg:tags":[
        "establishment"
    ],
    "wof:name":"Medical Recovery Inc",
    "wof:placetype":"venue"
},
  "geometry": {"coordinates":[-73.321322,40.865857],"type":"Point"}
}