{
  "type": "Feature",
  "properties": {
    "iso:country":"US",
    "sg:address":"6094 Dahlberg Rd",
    "sg:city":"Portland",
    "sg:classifiers":[
        {
            "category":"Wholesale",
            "subcategory":"Meat",
            "type":"Manufacturing & Wholesale Goods"
        }
    ],
    "sg:phone":"+1 716 792 7291",
    "sg:postcode":"14769",
    "sg:province":"NY",
    "sg:tags":[
        "product"
    ],
    "wof:name":"Watson's Deer Processing",
    "wof:placetype":"venue"
},
  "geometry": {"coordinates":[-79.447586,42.403286],"type":"Point"}
}