{
  "type": "Feature",
  "properties": {
    "addr:full":"44 Dalliba Avenue Watervliet NY 12189",
    "addr:housenumber":"44",
    "addr:postcode":"12189",
    "addr:street":"Dalliba Avenue",
    "iso:country":"US",
    "sg:address":"44 Dalliba Avenue",
    "sg:city":"Watervliet",
    "sg:classifiers":[
        {
            "category":"Professional",
            "subcategory":"Computer Services",
            "type":"Services"
        }
    ],
    "sg:phone":"+1 518 266 6051",
    "sg:postcode":"12189",
    "sg:province":"NY",
    "sg:tags":[
        "incubator",
        "bianys",
        "upstate-ny"
    ],
    "sg:website":"http://www.ceg.org/wic/index.htm",
    "wof:name":"Watervliet Innovation Center",
    "wof:placetype":"venue"
},
  "geometry": {"coordinates":[-73.70332000000001,42.720054],"type":"Point"}
}