{
  "type": "Feature",
  "properties": {
    "iso:country":"US",
    "sg:address":"500 W 111th St",
    "sg:city":"New York",
    "sg:classifiers":[
        {
            "category":"Professional",
            "subcategory":"Research",
            "type":"Services"
        }
    ],
    "sg:phone":"+1 212 316 5045",
    "sg:postcode":"10025",
    "sg:province":"NY",
    "sg:tags":[
        "environmental",
        "ecological"
    ],
    "wof:name":"Environmental Policy Svc",
    "wof:placetype":"venue"
},
  "geometry": {"coordinates":[-73.96392299999999,40.803855],"type":"Point"}
}