{
  "type": "Feature",
  "properties": {
    "addr:full":"11050 71st Road Forest Hills NY 11375",
    "addr:housenumber":"11050",
    "addr:postcode":"11375",
    "addr:street":"71St Road",
    "iso:country":"US",
    "sg:address":"11050 71st Road",
    "sg:city":"Forest Hills",
    "sg:classifiers":[
        {
            "category":"Health Services",
            "subcategory":"Doctor",
            "type":"Services"
        }
    ],
    "sg:phone":"+1 718 268 1112",
    "sg:postcode":"11375",
    "sg:province":"NY",
    "wof:name":"Krumholz David MD",
    "wof:placetype":"venue"
},
  "geometry": {"coordinates":[-73.840648,40.72179],"type":"Point"}
}