{
  "type": "Feature",
  "properties": {
    "iso:country":"US",
    "sg:address":"221 Dewey Ave",
    "sg:city":"Rochester",
    "sg:classifiers":[
        {
            "category":"Organizations",
            "subcategory":"Labor Organization",
            "type":"Services"
        }
    ],
    "sg:phone":"+1 585 458 1908",
    "sg:postcode":"14608",
    "sg:province":"NY",
    "wof:name":"United Auto Workers Local 1097",
    "wof:placetype":"venue"
},
  "geometry": {"coordinates":[-77.635378,43.168544],"type":"Point"}
}