{
  "type": "Feature",
  "properties": {
    "addr:full":"2444 86th St Brooklyn NY 11214",
    "addr:housenumber":"2444",
    "addr:postcode":"11214",
    "addr:street":"86Th St",
    "iso:country":"US",
    "sg:address":"2444 86th St",
    "sg:city":"Brooklyn",
    "sg:classifiers":[
        {
            "category":"Retail",
            "subcategory":"Funeral Services",
            "type":"Services"
        }
    ],
    "sg:phone":"+1   ",
    "sg:postcode":"11214",
    "sg:province":"NY",
    "wof:name":"E J Graziano",
    "wof:placetype":"venue"
},
  "geometry": {"coordinates":[-73.988224,40.5985],"type":"Point"}
}