{
  "type": "Feature",
  "properties": {
    "addr:full":"92 Pulpmill Rd Chateaugay NY 12920",
    "addr:housenumber":"92",
    "addr:postcode":"12920",
    "addr:street":"Pulpmill Rd",
    "iso:country":"US",
    "sg:address":"92 Pulpmill Rd",
    "sg:city":"Chateaugay",
    "sg:classifiers":[
        {
            "category":"Building & Trades",
            "subcategory":"Construction",
            "type":"Services"
        }
    ],
    "sg:phone":"+1 518 497 3059",
    "sg:postcode":"12920",
    "sg:province":"NY",
    "sg:tags":[
        "excavation",
        "contractor"
    ],
    "wof:name":"R Godding Leonard",
    "wof:placetype":"venue"
},
  "geometry": {"coordinates":[-74.072919,44.906054],"type":"Point"}
}