{
  "type": "Feature",
  "properties": {
    "addr:full":"5126 59th Street Woodside NY 11377",
    "addr:housenumber":"5126",
    "addr:postcode":"11377",
    "addr:street":"59Th Street",
    "iso:country":"US",
    "sg:address":"5126 59th Street",
    "sg:city":"Woodside",
    "sg:classifiers":[
        {
            "category":"Home & Garden",
            "subcategory":"Furniture",
            "type":"Retail Goods"
        }
    ],
    "sg:phone":"+1 718 335 9100",
    "sg:postcode":"11377",
    "sg:province":"NY",
    "sg:tags":[
        "store"
    ],
    "wof:name":"ABC New York Corporation",
    "wof:placetype":"venue"
},
  "geometry": {"coordinates":[-73.906616,40.735157],"type":"Point"}
}