{
  "type": "Feature",
  "properties": {
    "iso:country":"US",
    "sg:address":"200 W 90th St",
    "sg:city":"New York",
    "sg:classifiers":[
        {
            "category":"Health Services",
            "subcategory":"Doctor",
            "type":"Services"
        }
    ],
    "sg:phone":"+1 212 799 3902",
    "sg:postcode":"10024",
    "sg:province":"NY",
    "wof:name":"Elman Lynn",
    "wof:placetype":"venue"
},
  "geometry": {"coordinates":[-73.97473100000001,40.790753],"type":"Point"}
}