{
  "type": "Feature",
  "properties": {
    "iso:country":"US",
    "sg:address":"1496 Montauk Hwy",
    "sg:city":"Mastic",
    "sg:classifiers":[
        {
            "category":"Personal",
            "subcategory":"Beauty Salon",
            "type":"Services"
        },
        {
            "category":"Personal",
            "subcategory":"Barber",
            "type":"Services"
        }
    ],
    "sg:phone":"+1 631 281 0005",
    "sg:postcode":"11950",
    "sg:province":"NY",
    "sg:tags":[
        "hair"
    ],
    "wof:name":"Sam's Barber Shop",
    "wof:placetype":"venue"
},
  "geometry": {"coordinates":[-72.845157,40.805635],"type":"Point"}
}