{
  "type": "Feature",
  "properties": {
    "addr:full":"505 Park Ave New York NY 10022",
    "addr:housenumber":"505",
    "addr:postcode":"10022",
    "addr:street":"Park Ave",
    "iso:country":"US",
    "sg:address":"505 Park Ave",
    "sg:city":"New York",
    "sg:classifiers":[
        {
            "category":"Professional",
            "subcategory":"Lawyer & Legal Services",
            "type":"Services"
        }
    ],
    "sg:phone":"+1 212 755 5510",
    "sg:postcode":"10022",
    "sg:province":"NY",
    "sg:tags":[
        "attorney"
    ],
    "sg:website":"www.loebblockptrs.com",
    "wof:name":"Loeb Block & Wacksman",
    "wof:placetype":"venue"
},
  "geometry": {"coordinates":[-73.96959699999999,40.7631],"type":"Point"}
}