{
  "type": "Feature",
  "properties": {
    "iso:country":"US",
    "sg:address":"35 E Grassy Sprain Rd",
    "sg:city":"Yonkers",
    "sg:classifiers":[
        {
            "category":"Social Services",
            "type":"Services"
        }
    ],
    "sg:phone":"+1 914 337 4367",
    "sg:postcode":"10710",
    "sg:province":"NY",
    "sg:tags":[
        "employee",
        "assistance",
        "program"
    ],
    "wof:name":"Riverside Emplyee Assist Prgrm",
    "wof:placetype":"venue"
},
  "geometry": {"coordinates":[-73.850453,40.958507],"type":"Point"}
}