{
  "type": "Feature",
  "properties": {
    "iso:country":"US",
    "sg:address":"299 Orange St",
    "sg:city":"Albany",
    "sg:classifiers":[
        {
            "category":"Personal",
            "subcategory":"Beauty Salon",
            "type":"Services"
        }
    ],
    "sg:phone":"+1 518 436 0326",
    "sg:postcode":"12210",
    "sg:province":"NY",
    "wof:name":"Hair & Weave",
    "wof:placetype":"venue"
},
  "geometry": {"coordinates":[-73.75899099999999,42.658317],"type":"Point"}
}