{
  "type": "Feature",
  "properties": {
    "addr:full":"122 Hudson St New York NY 10013",
    "addr:housenumber":"122",
    "addr:postcode":"10013",
    "addr:street":"Hudson St",
    "iso:country":"US",
    "sg:address":"122 Hudson St",
    "sg:city":"New York",
    "sg:classifiers":[
        {
            "category":"Shopping",
            "type":"Retail Goods"
        }
    ],
    "sg:phone":"+1 212 625 9090",
    "sg:postcode":"10013",
    "sg:province":"NY",
    "sg:tags":[
        "picture"
    ],
    "wof:name":"Blow Up Pictures",
    "wof:placetype":"venue"
},
  "geometry": {"coordinates":[-74.00847,40.72061],"type":"Point"}
}