{
  "type": "Feature",
  "properties": {
    "iso:country":"US",
    "sg:address":"1786 Monroe Ave",
    "sg:city":"Rochester",
    "sg:classifiers":[
        {
            "category":"Autos & Motor Vehicles",
            "subcategory":"Auto Supplies",
            "type":"Retail Goods"
        }
    ],
    "sg:phone":"+1 585 473 7040",
    "sg:postcode":"14618",
    "sg:province":"NY",
    "sg:tags":[
        "automobile",
        "parts"
    ],
    "wof:name":"Twelve Corners Auto Parts Inc",
    "wof:placetype":"venue"
},
  "geometry": {"coordinates":[-77.566935,43.12872],"type":"Point"}
}