{
  "type": "Feature",
  "properties": {
    "addr:full":"563 E Main St Batavia NY 14020",
    "addr:housenumber":"563",
    "addr:postcode":"14020",
    "addr:street":"E Main St",
    "iso:country":"US",
    "sg:address":"563 E Main St",
    "sg:city":"Batavia",
    "sg:classifiers":[
        {
            "category":"Sports & Exercise",
            "subcategory":"Gym",
            "type":"Entertainment"
        }
    ],
    "sg:phone":"+1 585 343 3535",
    "sg:postcode":"14020",
    "sg:province":"NY",
    "sg:tags":[
        "club",
        "health",
        "studio",
        "gymnasium"
    ],
    "wof:name":"Curves",
    "wof:placetype":"venue"
},
  "geometry": {"coordinates":[-78.167362,42.99544],"type":"Point"}
}