{
  "type": "Feature",
  "properties": {
    "iso:country":"US",
    "sg:address":"2788 Long Beach Rd",
    "sg:city":"Oceanside",
    "sg:classifiers":[
        {
            "category":"Personal",
            "subcategory":"Beauty Salon",
            "type":"Services"
        }
    ],
    "sg:phone":"+1 516 764 7700",
    "sg:postcode":"11572",
    "sg:province":"NY",
    "sg:tags":[
        "manicuring"
    ],
    "wof:name":"Commack Blooming Nails Inc",
    "wof:placetype":"venue"
},
  "geometry": {"coordinates":[-73.640062,40.642991],"type":"Point"}
}