{
  "type": "Feature",
  "properties": {
    "addr:full":"662 Nostrand Ave Brooklyn NY 11216",
    "addr:housenumber":"662",
    "addr:postcode":"11216",
    "addr:street":"Nostrand Ave",
    "iso:country":"US",
    "sg:address":"662 Nostrand Ave",
    "sg:city":"Brooklyn",
    "sg:classifiers":[
        {
            "category":"Building & Trades",
            "subcategory":"Construction",
            "type":"Services"
        }
    ],
    "sg:phone":"+1 718 756 7480",
    "sg:postcode":"11216",
    "sg:province":"NY",
    "sg:tags":[
        "general",
        "contractor"
    ],
    "wof:name":"Grant Construction",
    "wof:placetype":"venue"
},
  "geometry": {"coordinates":[-73.950057,40.675464],"type":"Point"}
}