{
  "type": "Feature",
  "properties": {
    "addr:full":"102 S Main St Pittsford NY 14534",
    "addr:housenumber":"102",
    "addr:postcode":"14534",
    "addr:street":"S Main St",
    "iso:country":"US",
    "sg:address":"102 S Main St",
    "sg:city":"Pittsford",
    "sg:classifiers":[
        {
            "category":"Professional",
            "subcategory":"Lawyer & Legal Services",
            "type":"Services"
        }
    ],
    "sg:phone":"+1 585 248 3305",
    "sg:postcode":"14534",
    "sg:province":"NY",
    "sg:tags":[
        "attorney"
    ],
    "wof:name":"Fred Lester Esq",
    "wof:placetype":"venue"
},
  "geometry": {"coordinates":[-77.519363,43.084621],"type":"Point"}
}