{
  "type": "Feature",
  "properties": {
    "addr:full":"4219 College Point Blvd Flushing NY 11355",
    "addr:housenumber":"4219",
    "addr:postcode":"11355",
    "addr:street":"College Point Blvd",
    "iso:country":"US",
    "sg:address":"4219 College Point Blvd",
    "sg:city":"Flushing",
    "sg:classifiers":[
        {
            "category":"Restaurant",
            "type":"Food & Drink"
        }
    ],
    "sg:phone":"+1 718 661 1080",
    "sg:postcode":"11355",
    "sg:province":"NY",
    "wof:name":"Palacio De Las Empanada 2",
    "wof:placetype":"venue"
},
  "geometry": {"coordinates":[-73.832802,40.754299],"type":"Point"}
}