{
  "type": "Feature",
  "properties": {
    "addr:full":"247 W 36th St New York NY 10018",
    "addr:housenumber":"247",
    "addr:postcode":"10018",
    "addr:street":"W 36Th St",
    "iso:country":"US",
    "sg:address":"247 W 36th St",
    "sg:city":"New York",
    "sg:classifiers":[
        {
            "category":"Professional",
            "subcategory":"Lawyer & Legal Services",
            "type":"Services"
        }
    ],
    "sg:phone":"+1 212 643 0000",
    "sg:postcode":"10018",
    "sg:province":"NY",
    "wof:name":"Rokos Samuel",
    "wof:placetype":"venue"
},
  "geometry": {"coordinates":[-73.990971,40.752982],"type":"Point"}
}