{
  "type": "Feature",
  "properties": {
    "addr:full":"154 9th Ave Manhattan NY 10011",
    "addr:housenumber":"154",
    "addr:postcode":"10011",
    "addr:street":"9Th Ave",
    "iso:country":"US",
    "sg:address":"154 9th Ave",
    "sg:city":"Manhattan",
    "sg:classifiers":[
        {
            "category":"Shopping",
            "subcategory":"Beauty & Cosmetics",
            "type":"Retail Goods"
        },
        {
            "category":"Professional",
            "subcategory":"Lawyer & Legal Services",
            "type":"Services"
        },
        {
            "category":"Shopping",
            "subcategory":"Pharmacy",
            "type":"Retail Goods"
        }
    ],
    "sg:phone":"+1 212 255 8000",
    "sg:postcode":"10011",
    "sg:province":"NY",
    "sg:tags":[
        "notary",
        "drugstore",
        "supply"
    ],
    "wof:name":"Chelsea Royal Care Pharmacy, Inc",
    "wof:placetype":"venue"
},
  "geometry": {"coordinates":[-74.002662,40.744195],"type":"Point"}
}