{
  "type": "Feature",
  "properties": {
    "iso:country":"US",
    "sg:address":"1065 Lochland Rd",
    "sg:city":"Geneva",
    "sg:classifiers":[
        {
            "category":"Organizations",
            "subcategory":"Non-profit Organization",
            "type":"Services"
        }
    ],
    "sg:phone":"+1 315 789 5208",
    "sg:postcode":"14456",
    "sg:province":"NY",
    "sg:website":"www.lochland.org",
    "wof:name":"Lochland School Inc",
    "wof:placetype":"venue"
},
  "geometry": {"coordinates":[-76.97909199999999,42.842791],"type":"Point"}
}