{
  "type": "Feature",
  "properties": {
    "addr:full":"1646 Dahill Rd Brooklyn NY 11223",
    "addr:housenumber":"1646",
    "addr:postcode":"11223",
    "addr:street":"Dahill Rd",
    "iso:country":"US",
    "sg:address":"1646 Dahill Rd",
    "sg:city":"Brooklyn",
    "sg:classifiers":[
        {
            "category":"Professional",
            "subcategory":"Art Services",
            "type":"Services"
        }
    ],
    "sg:phone":"+1 718 339 8121",
    "sg:postcode":"11223",
    "sg:province":"NY",
    "sg:tags":[
        "photographer"
    ],
    "wof:name":"John Calabrese Photography",
    "wof:placetype":"venue"
},
  "geometry": {"coordinates":[-73.973838,40.607529],"type":"Point"}
}