{
  "type": "Feature",
  "properties": {
    "iso:country":"US",
    "sg:address":"4330 Katonah Ave",
    "sg:city":"Bronx",
    "sg:classifiers":[
        {
            "category":"Restaurant",
            "type":"Food & Drink"
        }
    ],
    "sg:phone":"+1 718 798 1002",
    "sg:postcode":"10470",
    "sg:province":"NY",
    "sg:tags":[
        "style",
        "eating",
        "family"
    ],
    "wof:name":"Celtic Kitchen",
    "wof:placetype":"venue"
},
  "geometry": {"coordinates":[-73.867582,40.899699],"type":"Point"}
}