{
  "type": "Feature",
  "properties": {
    "iso:country":"US",
    "sg:address":"1219 Park Ave",
    "sg:city":"Utica",
    "sg:classifiers":[
        {
            "category":"Wholesale",
            "subcategory":"Auto Parts",
            "type":"Manufacturing & Wholesale Goods"
        }
    ],
    "sg:phone":"+1 315 732 1141",
    "sg:postcode":"13501",
    "sg:province":"NY",
    "sg:tags":[
        "body",
        "automobile",
        "shop"
    ],
    "wof:name":"Genesee Paint & Glass Co",
    "wof:placetype":"venue"
},
  "geometry": {"coordinates":[-75.241778,43.09586],"type":"Point"}
}