{
  "type": "Feature",
  "properties": {
    "addr:full":"44 Secor Ln Pelham NY 10803",
    "addr:housenumber":"44",
    "addr:postcode":"10803",
    "addr:street":"Secor Ln",
    "iso:country":"US",
    "sg:address":"44 Secor Ln",
    "sg:city":"Pelham",
    "sg:classifiers":[
        {
            "category":"Freight",
            "type":"Transportation"
        }
    ],
    "sg:phone":"+1 914 712 3700",
    "sg:postcode":"10803",
    "sg:province":"NY",
    "sg:tags":[
        "company",
        "storage",
        "trucking",
        "moving",
        "mover",
        "local"
    ],
    "wof:name":"American Moving & Storage Inc",
    "wof:placetype":"venue"
},
  "geometry": {"coordinates":[-73.816529,40.895135],"type":"Point"}
}