{
  "type": "Feature",
  "properties": {
    "iso:country":"US",
    "sg:address":"414 E 75th Street",
    "sg:city":"New York",
    "sg:classifiers":[
        {
            "category":"Banks & Credit Unions",
            "subcategory":"Investment Brokerage",
            "type":"Services"
        }
    ],
    "sg:phone":"+1 212 434 7002",
    "sg:postcode":"10021",
    "sg:province":"NY",
    "sg:tags":[
        "investing"
    ],
    "wof:name":"A I International Corporation",
    "wof:placetype":"venue"
},
  "geometry": {"coordinates":[-73.95864,40.768396],"type":"Point"}
}