{
  "type": "Feature",
  "properties": {
    "iso:country":"US",
    "sg:address":"50 Market St",
    "sg:city":"Poughkeepsie",
    "sg:classifiers":[
        {
            "category":"Government",
            "subcategory":"Office",
            "type":"Public Place"
        }
    ],
    "sg:phone":"+1 845 486 2600",
    "sg:postcode":"12601",
    "sg:province":"NY",
    "sg:tags":[
        "executive"
    ],
    "wof:name":"Family Court",
    "wof:placetype":"venue"
},
  "geometry": {"coordinates":[-73.929795,41.702068],"type":"Point"}
}