{
  "type": "Feature",
  "properties": {
    "addr:full":"1861 Montauk Hwy Brookhaven NY 11719",
    "addr:housenumber":"1861",
    "addr:postcode":"11719",
    "addr:street":"Montauk Hwy",
    "iso:country":"US",
    "sg:address":"1861 Montauk Hwy",
    "sg:city":"Brookhaven",
    "sg:classifiers":[
        {
            "category":"Autos & Motor Vehicles",
            "subcategory":"Automobile Sales",
            "type":"Retail Goods"
        }
    ],
    "sg:phone":"+1   ",
    "sg:postcode":"11719",
    "sg:province":"NY",
    "sg:tags":[
        "used"
    ],
    "wof:name":"Wishy",
    "wof:placetype":"venue"
},
  "geometry": {"coordinates":[-72.93308,40.775934],"type":"Point"}
}