{
  "type": "Feature",
  "properties": {
    "addr:full":"33 Clinton St Saratoga Springs NY 12866",
    "addr:housenumber":"33",
    "addr:postcode":"12866",
    "addr:street":"Clinton St",
    "iso:country":"US",
    "sg:address":"33 Clinton St",
    "sg:city":"Saratoga Springs",
    "sg:classifiers":[
        {
            "category":"Professional",
            "subcategory":"Management & Consulting",
            "type":"Services"
        }
    ],
    "sg:phone":"+1 518 583 1121",
    "sg:postcode":"12866",
    "sg:province":"NY",
    "sg:website":"www.bradleygrp.com",
    "wof:name":"Bradley Group Inc",
    "wof:placetype":"venue"
},
  "geometry": {"coordinates":[-73.788404,43.083599],"type":"Point"}
}