{
  "type": "Feature",
  "properties": {
    "addr:full":"11 E 47th St Rm 6R New York NY 10017",
    "addr:housenumber":"11",
    "addr:postcode":"10017",
    "addr:street":"E 47Th St;6R",
    "iso:country":"US",
    "sg:address":"11 E 47th St Rm 6R",
    "sg:city":"New York",
    "sg:classifiers":[
        {
            "category":"Professional",
            "subcategory":"Lawyer & Legal Services",
            "type":"Services"
        }
    ],
    "sg:phone":"+1 212 371 7810",
    "sg:postcode":"10017",
    "sg:province":"NY",
    "wof:name":"Lester A Epstein & Associates",
    "wof:placetype":"venue"
},
  "geometry": {"coordinates":[-73.977997,40.7565],"type":"Point"}
}