{
  "type": "Feature",
  "properties": {
    "addr:full":"565 W 23rd St New York NY 10011",
    "addr:housenumber":"565",
    "addr:postcode":"10011",
    "addr:street":"W 23Rd St",
    "iso:country":"US",
    "sg:address":"565 W 23rd St",
    "sg:city":"New York",
    "sg:classifiers":[
        {
            "category":"Restaurant",
            "type":"Food & Drink"
        }
    ],
    "sg:phone":"+1   ",
    "sg:postcode":"10011",
    "sg:province":"NY",
    "sg:tags":[
        "club",
        "gentleman"
    ],
    "wof:name":"Priviledge NY",
    "wof:placetype":"venue"
},
  "geometry": {"coordinates":[-74.005574,40.748172],"type":"Point"}
}