{
  "type": "Feature",
  "properties": {
    "addr:full":"1410 Broadway 39th St, Concourse Level New York NY 10018",
    "addr:housenumber":"1410",
    "addr:postcode":"10018",
    "addr:street":"Broadway 39Th St",
    "iso:country":"US",
    "sg:address":"1410 Broadway 39th St, Concourse Level",
    "sg:city":"New York",
    "sg:classifiers":[
        {
            "category":"Health Services",
            "subcategory":"Health Practitioner",
            "type":"Services"
        },
        {
            "category":"Health Services",
            "subcategory":"Chiropractor",
            "type":"Services"
        }
    ],
    "sg:phone":"+1 212 354 2225",
    "sg:postcode":"10018",
    "sg:province":"NY",
    "sg:tags":[
        "nutritionist"
    ],
    "sg:website":"www.bcwnyc.com",
    "wof:name":"Broadway Chiropractic And Wellness",
    "wof:placetype":"venue"
},
  "geometry": {"coordinates":[-73.986771,40.753202],"type":"Point"}
}