{
  "type": "Feature",
  "properties": {
    "addr:full":"197 Worth St New York NY 10013",
    "addr:housenumber":"197",
    "addr:postcode":"10013",
    "addr:street":"Worth St",
    "iso:country":"US",
    "sg:address":"197 Worth St",
    "sg:city":"New York",
    "sg:classifiers":[
        {
            "category":"Insurance",
            "subcategory":"Insurance Agent",
            "type":"Services"
        }
    ],
    "sg:phone":"+1 212 608 6945",
    "sg:postcode":"10013",
    "sg:province":"NY",
    "wof:name":"Chinatown Brokerage House",
    "wof:placetype":"venue"
},
  "geometry": {"coordinates":[-73.998785,40.713689],"type":"Point"}
}