{
  "type": "Feature",
  "properties": {
    "iso:country":"US",
    "sg:address":"22 Jefferson Ave",
    "sg:city":"Centereach",
    "sg:classifiers":[
        {
            "category":"Education",
            "subcategory":"School",
            "type":"Public Place"
        }
    ],
    "sg:phone":"+1 631 285 8400",
    "sg:postcode":"11720",
    "sg:province":"NY",
    "sg:website":"www.middlecountry.k12.ny.us",
    "wof:name":"Selden Middle School",
    "wof:placetype":"venue"
},
  "geometry": {"coordinates":[-73.06222,40.876883],"type":"Point"}
}