{
  "type": "Feature",
  "properties": {
    "addr:full":"544 E Main St Palmyra NY 14522",
    "addr:housenumber":"544",
    "addr:postcode":"14522",
    "addr:street":"E Main St",
    "iso:country":"US",
    "sg:address":"544 E Main St",
    "sg:city":"Palmyra",
    "sg:classifiers":[
        {
            "category":"Banks & Credit Unions",
            "subcategory":"Bank",
            "type":"Services"
        }
    ],
    "sg:phone":"+1 315 548 2511",
    "sg:postcode":"14522",
    "sg:province":"NY",
    "wof:name":"Ontario National Bank",
    "wof:placetype":"venue"
},
  "geometry": {"coordinates":[-77.225165,43.063286],"type":"Point"}
}