{
  "type": "Feature",
  "properties": {
    "iso:country":"US",
    "sg:address":"1825 26th Road",
    "sg:city":"Long Island City",
    "sg:classifiers":[
        {
            "category":"Personal",
            "type":"Services"
        }
    ],
    "sg:phone":"+1 718 204 1030",
    "sg:postcode":"11102",
    "sg:province":"NY",
    "sg:tags":[
        "party",
        "planning",
        "event"
    ],
    "sg:website":"www.videoconcepts.com",
    "wof:name":"Video Concepts",
    "wof:placetype":"venue"
},
  "geometry": {"coordinates":[-73.92584600000001,40.773372],"type":"Point"}
}