{
  "type": "Feature",
  "properties": {
    "addr:full":"1216 Ave U Brooklyn NY 11229",
    "addr:housenumber":"1216",
    "addr:postcode":"11229",
    "addr:street":"Ave U",
    "iso:country":"US",
    "sg:address":"1216 Ave U",
    "sg:city":"Brooklyn",
    "sg:classifiers":[
        {
            "category":"Health Services",
            "subcategory":"Doctor",
            "type":"Services"
        }
    ],
    "sg:phone":"+1 718 375 9899",
    "sg:postcode":"11229",
    "sg:province":"NY",
    "sg:tags":[
        "dentist"
    ],
    "wof:name":"Throne & Chasky",
    "wof:placetype":"venue"
},
  "geometry": {"coordinates":[-73.95960599999999,40.598391],"type":"Point"}
}