{
  "type": "Feature",
  "properties": {
    "iso:country":"US",
    "sg:address":"529 E 12 St",
    "sg:city":"New York",
    "sg:classifiers":[
        {
            "category":"Organizations",
            "subcategory":"Professional Association",
            "type":"Services"
        }
    ],
    "sg:phone":"+1 212 473 7006",
    "sg:postcode":"10009",
    "sg:province":"NY",
    "wof:name":"527-529 East 12 St Tenant Assn",
    "wof:placetype":"venue"
},
  "geometry": {"coordinates":[-73.979465,40.728451],"type":"Point"}
}