{
  "type": "Feature",
  "properties": {
    "iso:country":"US",
    "sg:address":"223 Park Ave",
    "sg:city":"Hicksville",
    "sg:classifiers":[
        {
            "category":"Building & Trades",
            "subcategory":"Electrical",
            "type":"Services"
        }
    ],
    "sg:phone":"+1 516 931 2288",
    "sg:postcode":"11801",
    "sg:province":"NY",
    "sg:tags":[
        "security",
        "installation",
        "system"
    ],
    "wof:name":"Universal Security Systems",
    "wof:placetype":"venue"
},
  "geometry": {"coordinates":[-73.521795,40.773832],"type":"Point"}
}