{
  "type": "Feature",
  "properties": {
    "iso:country":"US",
    "sg:address":"143 Wilson Park Dr",
    "sg:city":"Tarrytown",
    "sg:classifiers":[
        {
            "category":"Building & Trades",
            "subcategory":"Landscaping Services",
            "type":"Services"
        }
    ],
    "sg:phone":"+1 914 524 9041",
    "sg:postcode":"10591",
    "sg:province":"NY",
    "sg:tags":[
        "landscape"
    ],
    "wof:name":"Carsto Design",
    "wof:placetype":"venue"
},
  "geometry": {"coordinates":[-73.851753,41.084393],"type":"Point"}
}