{
  "type": "Feature",
  "properties": {
    "addr:full":"712 Burke Ave Bronx NY 10467",
    "addr:housenumber":"712",
    "addr:postcode":"10467",
    "addr:street":"Burke Ave",
    "iso:country":"US",
    "sg:address":"712 Burke Ave",
    "sg:city":"Bronx",
    "sg:classifiers":[
        {
            "category":"Shopping",
            "subcategory":"Stationery & Office Supplies",
            "type":"Retail Goods"
        }
    ],
    "sg:phone":"+1 718 652 0082",
    "sg:postcode":"10467",
    "sg:province":"NY",
    "sg:tags":[
        "stationer"
    ],
    "wof:name":"712 Grocery Corp",
    "wof:placetype":"venue"
},
  "geometry": {"coordinates":[-73.86656499999999,40.871358],"type":"Point"}
}