{
  "type": "Feature",
  "properties": {
    "addr:full":"3250 Steinway St Astoria NY 11103",
    "addr:housenumber":"3250",
    "addr:postcode":"11103",
    "addr:street":"Steinway St",
    "iso:country":"US",
    "sg:address":"3250 Steinway St",
    "sg:city":"Astoria",
    "sg:classifiers":[
        {
            "category":"Restaurant",
            "type":"Food & Drink"
        }
    ],
    "sg:postcode":"11103",
    "sg:province":"NY",
    "sg:tags":[
        "diner"
    ],
    "wof:name":"Astoria Diner",
    "wof:placetype":"venue"
},
  "geometry": {"coordinates":[-73.919533,40.75835],"type":"Point"}
}