{
  "type": "Feature",
  "properties": {
    "iso:country":"US",
    "sg:address":"266 W Main St",
    "sg:city":"Malone",
    "sg:classifiers":[
        {
            "category":"Cinema",
            "subcategory":"Movie Rental",
            "type":"Entertainment"
        }
    ],
    "sg:phone":"+1 518 481 5649",
    "sg:postcode":"12953",
    "sg:province":"NY",
    "sg:tags":[
        "leasing",
        "video",
        "disc",
        "tape"
    ],
    "sg:website":"www.moviegallery.com",
    "wof:name":"Movie Gallery",
    "wof:placetype":"venue"
},
  "geometry": {"coordinates":[-74.30809000000001,44.848118],"type":"Point"}
}