{
  "type": "Feature",
  "properties": {
    "addr:full":"122 E 42nd St New York NY 10168",
    "addr:housenumber":"122",
    "addr:postcode":"10168",
    "addr:street":"E 42Nd St",
    "iso:country":"US",
    "sg:address":"122 E 42nd St",
    "sg:city":"New York",
    "sg:classifiers":[
        {
            "category":"Professional",
            "subcategory":"Lawyer & Legal Services",
            "type":"Services"
        }
    ],
    "sg:phone":"+1 212 986 2340",
    "sg:postcode":"10168",
    "sg:province":"NY",
    "wof:name":"Jordan & Hamburg",
    "wof:placetype":"venue"
},
  "geometry": {"coordinates":[-73.976997,40.751801],"type":"Point"}
}