{
  "type": "Feature",
  "properties": {
    "iso:country":"US",
    "sg:address":"5480 Bartel Rd",
    "sg:city":"Brewerton",
    "sg:classifiers":[
        {
            "category":"Restaurant",
            "type":"Food & Drink"
        }
    ],
    "sg:menulink":"http://www.allmenus.com/ny/cicero/169803-burger-king/menu/",
    "sg:phone":"+1 315 668 6011",
    "sg:postcode":"13029",
    "sg:province":"NY",
    "sg:tags":[
        "burger",
        "american"
    ],
    "wof:name":"Burger King",
    "wof:placetype":"venue"
},
  "geometry": {"coordinates":[-76.136928,43.232703],"type":"Point"}
}