{
  "type": "Feature",
  "properties": {
    "addr:full":"120 Congers Rd Congers NY 10920",
    "addr:housenumber":"120",
    "addr:postcode":"10920",
    "addr:street":"Congers Rd",
    "iso:country":"US",
    "sg:address":"120 Congers Rd",
    "sg:city":"Congers",
    "sg:classifiers":[
        {
            "category":"Building & Trades",
            "subcategory":"Construction",
            "type":"Services"
        }
    ],
    "sg:phone":"+1 845 268 6908",
    "sg:postcode":"10920",
    "sg:province":"NY",
    "sg:tags":[
        "home",
        "improvement"
    ],
    "wof:name":"Alternatives",
    "wof:placetype":"venue"
},
  "geometry": {"coordinates":[-73.94801099999999,41.151679],"type":"Point"}
}