{
  "type": "Feature",
  "properties": {
    "addr:full":"1894 Sterling Pl Brooklyn NY 11233",
    "addr:housenumber":"1894",
    "addr:postcode":"11233",
    "addr:street":"Sterling Pl",
    "iso:country":"US",
    "sg:address":"1894 Sterling Pl",
    "sg:city":"Brooklyn",
    "sg:classifiers":[
        {
            "category":"Retail",
            "subcategory":"Auto Repair",
            "type":"Services"
        }
    ],
    "sg:phone":"+1 718 346 6338",
    "sg:postcode":"11233",
    "sg:province":"NY",
    "sg:tags":[
        "repairing",
        "automobile"
    ],
    "wof:name":"General Auto Co Repair",
    "wof:placetype":"venue"
},
  "geometry": {"coordinates":[-73.915825,40.67059],"type":"Point"}
}