{
  "type": "Feature",
  "properties": {
    "addr:full":"39 Central Ave Cortland NY 13045",
    "addr:housenumber":"39",
    "addr:postcode":"13045",
    "addr:street":"Central Ave",
    "iso:country":"US",
    "sg:address":"39 Central Ave",
    "sg:city":"Cortland",
    "sg:classifiers":[
        {
            "category":"Personal",
            "subcategory":"Beauty Salon",
            "type":"Services"
        }
    ],
    "sg:phone":"+1 607 756 0383",
    "sg:postcode":"13045",
    "sg:province":"NY",
    "wof:name":"Central Hair Studio",
    "wof:placetype":"venue"
},
  "geometry": {"coordinates":[-76.17921200000001,42.600031],"type":"Point"}
}