{
  "type": "Feature",
  "properties": {
    "iso:country":"US",
    "sg:address":"197 Genesee St",
    "sg:city":"Auburn",
    "sg:classifiers":[
        {
            "category":"Health Services",
            "subcategory":"Doctor",
            "type":"Services"
        }
    ],
    "sg:phone":"+1 315 253 7631",
    "sg:postcode":"13021",
    "sg:province":"NY",
    "sg:tags":[
        "dentist"
    ],
    "wof:name":"Lesch Lesch & Nangle",
    "wof:placetype":"venue"
},
  "geometry": {"coordinates":[-76.572909,42.928401],"type":"Point"}
}