{
  "type": "Feature",
  "properties": {
    "iso:country":"US",
    "sg:address":"68 W Lincoln Ave",
    "sg:city":"Mt Vernon",
    "sg:classifiers":[
        {
            "category":"Restaurant",
            "type":"Food & Drink"
        }
    ],
    "sg:phone":"+1 914 665 8800",
    "sg:postcode":"10550",
    "sg:province":"NY",
    "wof:name":"J Lincoln Barbeque",
    "wof:placetype":"venue"
},
  "geometry": {"coordinates":[-73.84100599999999,40.917298],"type":"Point"}
}