{
  "type": "Feature",
  "properties": {
    "iso:country":"US",
    "sg:address":"111 Pawling St",
    "sg:city":"Hagaman",
    "sg:classifiers":[
        {
            "category":"Restaurant",
            "type":"Food & Drink"
        }
    ],
    "sg:phone":"+1   ",
    "sg:postcode":"12086",
    "sg:province":"NY",
    "sg:tags":[
        "eating"
    ],
    "wof:name":"Cronies",
    "wof:placetype":"venue"
},
  "geometry": {"coordinates":[-74.15113599999999,42.974869],"type":"Point"}
}