{
  "type": "Feature",
  "properties": {
    "addr:full":"6 Woodlawn Ave Corning NY 14830",
    "addr:housenumber":"6",
    "addr:postcode":"14830",
    "addr:street":"Woodlawn Ave",
    "iso:country":"US",
    "sg:address":"6 Woodlawn Ave",
    "sg:city":"Corning",
    "sg:classifiers":[
        {
            "category":"Professional",
            "type":"Services"
        }
    ],
    "sg:phone":"+1   ",
    "sg:postcode":"14830",
    "sg:province":"NY",
    "wof:name":"Clayton M Walker Jr",
    "wof:placetype":"venue"
},
  "geometry": {"coordinates":[-77.06725900000001,42.151256],"type":"Point"}
}