{
  "type": "Feature",
  "properties": {
    "addr:full":"3581 Bayview St Seaford NY 11783",
    "addr:housenumber":"3581",
    "addr:postcode":"11783",
    "addr:street":"Bayview St",
    "iso:country":"US",
    "sg:address":"3581 Bayview St",
    "sg:city":"Seaford",
    "sg:classifiers":[
        {
            "category":"Building & Trades",
            "subcategory":"Electrical",
            "type":"Services"
        },
        {
            "category":"Home & Garden",
            "subcategory":"Home Furnishings",
            "type":"Retail Goods"
        }
    ],
    "sg:phone":"+1 516 826 3311",
    "sg:postcode":"11783",
    "sg:province":"NY",
    "sg:tags":[
        "lighting",
        "electrical",
        "contractor"
    ],
    "wof:name":"Mohrmann Electric Inc",
    "wof:placetype":"venue"
},
  "geometry": {"coordinates":[-73.498406,40.65827],"type":"Point"}
}