{
  "type": "Feature",
  "properties": {
    "addr:full":"6909 108th St Forest Hills NY 11375",
    "addr:housenumber":"6909",
    "addr:postcode":"11375",
    "addr:street":"108Th St",
    "iso:country":"US",
    "sg:address":"6909 108th St",
    "sg:city":"Forest Hills",
    "sg:classifiers":[
        {
            "category":"Real Estate",
            "subcategory":"Real Estate Services",
            "type":"Services"
        }
    ],
    "sg:phone":"+1 718 575 9292",
    "sg:postcode":"11375",
    "sg:province":"NY",
    "sg:tags":[
        "management",
        "property"
    ],
    "wof:name":"Rachlin Managmnt Corp",
    "wof:placetype":"venue"
},
  "geometry": {"coordinates":[-73.845001,40.723999],"type":"Point"}
}