{
  "type": "Feature",
  "properties": {
    "iso:country":"US",
    "sg:address":"389 E Main St",
    "sg:city":"Middletown",
    "sg:classifiers":[
        {
            "category":"Health Services",
            "subcategory":"Medical Lab",
            "type":"Services"
        }
    ],
    "sg:phone":"+1 845 342 5928",
    "sg:postcode":"10940",
    "sg:province":"NY",
    "sg:tags":[
        "laboratory"
    ],
    "wof:name":"Lab Corp Of America",
    "wof:placetype":"venue"
},
  "geometry": {"coordinates":[-74.39559,41.444692],"type":"Point"}
}