{
  "type": "Feature",
  "properties": {
    "iso:country":"US",
    "sg:address":"1795 Middle Country Rd",
    "sg:city":"Centereach",
    "sg:classifiers":[
        {
            "category":"Shopping",
            "subcategory":"Musical Instruments",
            "type":"Retail Goods"
        }
    ],
    "sg:phone":"+1 631 585 2323",
    "sg:postcode":"11720",
    "sg:province":"NY",
    "wof:name":"Music Land",
    "wof:placetype":"venue"
},
  "geometry": {"coordinates":[-73.075585,40.85995],"type":"Point"}
}