{
  "type": "Feature",
  "properties": {
    "iso:country":"US",
    "sg:address":"36 Center St",
    "sg:city":"Hamburg",
    "sg:classifiers":[
        {
            "category":"Personal",
            "subcategory":"Beauty Salon",
            "type":"Services"
        }
    ],
    "sg:phone":"+1 716 648 1490",
    "sg:postcode":"14075",
    "sg:province":"NY",
    "wof:name":"Village Hair Shop Inc",
    "wof:placetype":"venue"
},
  "geometry": {"coordinates":[-78.83432000000001,42.717292],"type":"Point"}
}