{
  "type": "Feature",
  "properties": {
    "iso:country":"US",
    "sg:address":"6091 Myrtle AVE",
    "sg:city":"Queens",
    "sg:classifiers":[
        {
            "category":"Building & Trades",
            "subcategory":"Plumbing",
            "type":"Services"
        },
        {
            "category":"Building & Trades",
            "subcategory":"Construction",
            "type":"Services"
        }
    ],
    "sg:phone":"+1 718 210 0168",
    "sg:postcode":"11385",
    "sg:province":"NY",
    "sg:tags":[
        "air",
        "heating",
        "conditioning/hvac"
    ],
    "sg:website":"ridgewoodemergencyplumbingandhea...",
    "wof:name":"Ridgewood Emergency Plumbing and Heating",
    "wof:placetype":"venue"
},
  "geometry": {"coordinates":[-73.89506900000001,40.700971],"type":"Point"}
}