{
  "type": "Feature",
  "properties": {
    "iso:country":"US",
    "sg:address":"580 Veterans Hwy",
    "sg:city":"Hauppauge",
    "sg:classifiers":[
        {
            "category":"Restaurant",
            "type":"Food & Drink"
        }
    ],
    "sg:menulink":"http://www.allmenus.com/ny/smithtown/59059-sushi-sakura/menu/",
    "sg:phone":"+1 631 366 4054",
    "sg:postcode":"11788",
    "sg:province":"NY",
    "sg:tags":[
        "japanese",
        "asian"
    ],
    "wof:name":"Sushi Sakura",
    "wof:placetype":"venue"
},
  "geometry": {"coordinates":[-73.24302299999999,40.826812],"type":"Point"}
}