{
  "type": "Feature",
  "properties": {
    "addr:full":"2056 Broadway New York NY 10023",
    "addr:housenumber":"2056",
    "addr:postcode":"10023",
    "addr:street":"Broadway",
    "iso:country":"US",
    "sg:address":"2056 Broadway",
    "sg:city":"New York",
    "sg:classifiers":[
        {
            "category":"Food & Beverages",
            "subcategory":"Liquor & Beverages",
            "type":"Retail Goods"
        }
    ],
    "sg:phone":"+1 212 875 1200",
    "sg:postcode":"10023",
    "sg:province":"NY",
    "sg:tags":[
        "beer",
        "spirit",
        "wine"
    ],
    "sg:website":"www.bacchusnyc.com",
    "wof:name":"Bacchus Wine Made Simple",
    "wof:placetype":"venue"
},
  "geometry": {"coordinates":[-73.981796,40.778],"type":"Point"}
}