{
  "type": "Feature",
  "properties": {
    "addr:full":"229 W 42nd St New York NY 10036",
    "addr:housenumber":"229",
    "addr:postcode":"10036",
    "addr:street":"W 42Nd St",
    "iso:country":"US",
    "sg:address":"229 W 42nd St",
    "sg:city":"New York",
    "sg:classifiers":[
        {
            "category":"Arts & Performance",
            "subcategory":"Theater",
            "type":"Entertainment"
        }
    ],
    "sg:phone":"+1 212 719 3301",
    "sg:postcode":"10036",
    "sg:province":"NY",
    "sg:tags":[
        "dance",
        "company"
    ],
    "wof:name":"Buglisi-Foreman Dance",
    "wof:placetype":"venue"
},
  "geometry": {"coordinates":[-73.98913899999999,40.756957],"type":"Point"}
}