{
  "type": "Feature",
  "properties": {
    "addr:full":"4714 4th Ave Brooklyn NY 11220",
    "addr:housenumber":"4714",
    "addr:postcode":"11220",
    "addr:street":"4Th Ave",
    "iso:country":"US",
    "sg:address":"4714 4th Ave",
    "sg:city":"Brooklyn",
    "sg:classifiers":[
        {
            "category":"Home & Garden",
            "subcategory":"Building Materials",
            "type":"Retail Goods"
        }
    ],
    "sg:phone":"+1 718 439 5025",
    "sg:postcode":"11220",
    "sg:province":"NY",
    "sg:tags":[
        "plumbing",
        "fixture",
        "supply"
    ],
    "wof:name":"J R Hardware",
    "wof:placetype":"venue"
},
  "geometry": {"coordinates":[-74.011408,40.647716],"type":"Point"}
}