{
  "type": "Feature",
  "properties": {
    "addr:full":"18 Vanderbilt Pkwy Manhasset NY 11030",
    "addr:housenumber":"18",
    "addr:postcode":"11030",
    "addr:street":"Vanderbilt Pkwy",
    "iso:country":"US",
    "sg:address":"18 Vanderbilt Pkwy",
    "sg:city":"Manhasset",
    "sg:classifiers":[
        {
            "category":"Banks & Credit Unions",
            "subcategory":"Bank",
            "type":"Services"
        }
    ],
    "sg:phone":"+1 516 627 3999",
    "sg:postcode":"11030",
    "sg:province":"NY",
    "sg:website":"www.citibank.com",
    "wof:name":"Citibank N A",
    "wof:placetype":"venue"
},
  "geometry": {"coordinates":[-73.681712,40.793761],"type":"Point"}
}