{
  "type": "Feature",
  "properties": {
    "addr:full":"131 Buell Ave Buffalo NY 14225",
    "addr:housenumber":"131",
    "addr:postcode":"14225",
    "addr:street":"Buell Ave",
    "iso:country":"US",
    "sg:address":"131 Buell Ave",
    "sg:city":"Buffalo",
    "sg:classifiers":[
        {
            "category":"Travel",
            "subcategory":"Hotels & Motels",
            "type":"Entertainment"
        },
        {
            "category":"Retail",
            "subcategory":"Event Space",
            "type":"Services"
        }
    ],
    "sg:phone":"+1 800 345 8082",
    "sg:postcode":"14225",
    "sg:province":"NY",
    "sg:tags":[
        "facility",
        "banquet",
        "reception",
        "lodging",
        "corporate",
        "hall"
    ],
    "sg:website":"http://ad.doubleclick.net/clk;222816988;46581822;v?http://www.hiexpress.com/redirect?path=hd&brandCode=ex&hotelCode=bufap&_PMID=99601036&cm_mmc=mdpr-_-yellowpages-_-ex-_-bufap",
    "wof:name":"Holiday Inn Express Hotel & Suites Buffalo-Airport",
    "wof:placetype":"venue"
},
  "geometry": {"coordinates":[-78.737534,42.92946],"type":"Point"}
}