{
  "type": "Feature",
  "properties": {
    "addr:full":"682 Sunrise Hwy Baldwin NY 11510",
    "addr:housenumber":"682",
    "addr:postcode":"11510",
    "addr:street":"Sunrise Hwy",
    "iso:country":"US",
    "sg:address":"682 Sunrise Hwy",
    "sg:city":"Baldwin",
    "sg:classifiers":[
        {
            "category":"Personal",
            "subcategory":"Beauty Salon",
            "type":"Services"
        }
    ],
    "sg:phone":"+1 516 223 2600",
    "sg:postcode":"11510",
    "sg:province":"NY",
    "sg:tags":[
        "shop"
    ],
    "wof:name":"Supercuts",
    "wof:placetype":"venue"
},
  "geometry": {"coordinates":[-73.613985,40.656428],"type":"Point"}
}