{
  "type": "Feature",
  "properties": {
    "iso:country":"US",
    "sg:address":"4510 Lewis Rd",
    "sg:city":"Walworth",
    "sg:phone":"+1 315 524 4410",
    "sg:postcode":"14568",
    "sg:province":"NY",
    "sg:tags":[
        "farm",
        "field",
        "crop"
    ],
    "wof:name":"Robert Guillaume",
    "wof:placetype":"venue"
},
  "geometry": {"coordinates":[-77.308131,43.175303],"type":"Point"}
}