{
  "type": "Feature",
  "properties": {
    "addr:full":"524 W 207th Street New York NY 10034",
    "addr:housenumber":"524",
    "addr:postcode":"10034",
    "addr:street":"W 207Th Street",
    "iso:country":"US",
    "sg:address":"524 W 207th Street",
    "sg:city":"New York",
    "sg:classifiers":[
        {
            "category":"Restaurant",
            "type":"Food & Drink"
        }
    ],
    "sg:phone":"+1 212 942 0032",
    "sg:postcode":"10034",
    "sg:province":"NY",
    "wof:name":"Polanco Edito",
    "wof:placetype":"venue"
},
  "geometry": {"coordinates":[-73.919545,40.865335],"type":"Point"}
}