{
  "type": "Feature",
  "properties": {
    "iso:country":"US",
    "sg:address":"525 E 68th St",
    "sg:city":"New York",
    "sg:classifiers":[
        {
            "category":"Health Services",
            "subcategory":"Doctor",
            "type":"Services"
        }
    ],
    "sg:phone":"+1 212 746 4644",
    "sg:postcode":"10065",
    "sg:province":"NY",
    "wof:name":"Reddy Cvr Dr",
    "wof:placetype":"venue"
},
  "geometry": {"coordinates":[-73.954774,40.764176],"type":"Point"}
}