{
  "type": "Feature",
  "properties": {
    "addr:full":"6 Valentine Ln Roslyn NY 11576",
    "addr:housenumber":"6",
    "addr:postcode":"11576",
    "addr:street":"Valentine Ln",
    "iso:country":"US",
    "sg:address":"6 Valentine Ln",
    "sg:city":"Roslyn",
    "sg:classifiers":[
        {
            "category":"Banks & Credit Unions",
            "subcategory":"Investment Brokerage",
            "type":"Services"
        }
    ],
    "sg:phone":"+1 516 229 4317",
    "sg:postcode":"11576",
    "sg:province":"NY",
    "sg:tags":[
        "advisory",
        "financial"
    ],
    "wof:name":"Orix Financial Svc Inc",
    "wof:placetype":"venue"
},
  "geometry": {"coordinates":[-73.646169,40.799305],"type":"Point"}
}