{
  "type": "Feature",
  "properties": {
    "addr:full":"33 Limestone Rd Armonk NY 10504",
    "addr:housenumber":"33",
    "addr:postcode":"10504",
    "addr:street":"Limestone Rd",
    "iso:country":"US",
    "sg:address":"33 Limestone Rd",
    "sg:city":"Armonk",
    "sg:classifiers":[
        {
            "category":"Shopping",
            "subcategory":"Clothing, Apparel, & Fashions",
            "type":"Retail Goods"
        }
    ],
    "sg:phone":"+1   ",
    "sg:postcode":"10504",
    "sg:province":"NY",
    "wof:name":"Lady Laura Ind Inc",
    "wof:placetype":"venue"
},
  "geometry": {"coordinates":[-73.703378,41.119636],"type":"Point"}
}