{
  "type": "Feature",
  "properties": {
    "addr:full":"1 Park Ave Manhasset NY 11030",
    "addr:housenumber":"1",
    "addr:postcode":"11030",
    "addr:street":"Park Ave",
    "iso:country":"US",
    "sg:address":"1 Park Ave",
    "sg:city":"Manhasset",
    "sg:classifiers":[
        {
            "category":"Real Estate",
            "subcategory":"Real Estate Operator",
            "type":"Services"
        }
    ],
    "sg:phone":"+1 516 627 4600",
    "sg:postcode":"11030",
    "sg:province":"NY",
    "sg:tags":[
        "apartment"
    ],
    "wof:name":"Carole Lovejoy Real Estate Inc",
    "wof:placetype":"venue"
},
  "geometry": {"coordinates":[-73.699203,40.797001],"type":"Point"}
}