{
  "type": "Feature",
  "properties": {
    "iso:country":"US",
    "sg:address":"386 Sunrise Hwy",
    "sg:city":"Lynbrook",
    "sg:classifiers":[
        {
            "category":"Shopping",
            "subcategory":"Clothing, Apparel, & Fashions",
            "type":"Retail Goods"
        }
    ],
    "sg:phone":"+1 516 599 5804",
    "sg:postcode":"11563",
    "sg:province":"NY",
    "sg:tags":[
        "fur",
        "business"
    ],
    "wof:name":"Primadonna Furs",
    "wof:placetype":"venue"
},
  "geometry": {"coordinates":[-73.674256,40.655325],"type":"Point"}
}