{
  "type": "Feature",
  "properties": {
    "addr:full":"239 E 79 St New York NY 10075",
    "addr:housenumber":"239;79",
    "addr:postcode":"10075",
    "addr:street":"E;St",
    "iso:country":"US",
    "sg:address":"239 E 79 St",
    "sg:city":"New York",
    "sg:classifiers":[
        {
            "category":"Professional",
            "subcategory":"Business Services",
            "type":"Services"
        }
    ],
    "sg:phone":"+1 212 772 0390",
    "sg:postcode":"10075",
    "sg:province":"NY",
    "sg:tags":[
        "interior",
        "consultant",
        "design",
        "decorator"
    ],
    "wof:name":"Lili Maali Designs Inc",
    "wof:placetype":"venue"
},
  "geometry": {"coordinates":[-73.95729300000001,40.774283],"type":"Point"}
}