{
  "type": "Feature",
  "properties": {
    "iso:country":"US",
    "sg:address":"50 Charles Lindbergh Blvd",
    "sg:city":"Uniondale",
    "sg:classifiers":[
        {
            "category":"Health Services",
            "subcategory":"Doctor",
            "type":"Services"
        }
    ],
    "sg:phone":"+1 516 229 2278",
    "sg:postcode":"11553",
    "sg:province":"NY",
    "wof:name":"Computer Surgeon",
    "wof:placetype":"venue"
},
  "geometry": {"coordinates":[-73.604641,40.726002],"type":"Point"}
}