{
  "type": "Feature",
  "properties": {
    "iso:country":"US",
    "sg:address":"40 Harbor Hill Dr",
    "sg:city":"Rochester",
    "sg:classifiers":[
        {
            "category":"Organizations",
            "subcategory":"Religious Organization",
            "type":"Services"
        }
    ],
    "sg:phone":"+1 585 342 6376",
    "sg:postcode":"14617",
    "sg:province":"NY",
    "sg:tags":[
        "clergy"
    ],
    "wof:name":"Lawrence E Witmer",
    "wof:placetype":"venue"
},
  "geometry": {"coordinates":[-77.608555,43.242503],"type":"Point"}
}