{
  "type": "Feature",
  "properties": {
    "addr:full":"120 Crescent Rd Piermont NY 10968",
    "addr:housenumber":"120",
    "addr:postcode":"10968",
    "addr:street":"Crescent Rd",
    "iso:country":"US",
    "sg:address":"120 Crescent Rd",
    "sg:city":"Piermont",
    "sg:classifiers":[
        {
            "category":"Building & Trades",
            "subcategory":"Electrical",
            "type":"Services"
        }
    ],
    "sg:phone":"+1 845 365 1099",
    "sg:postcode":"10968",
    "sg:province":"NY",
    "sg:tags":[
        "electrician",
        "contractor"
    ],
    "wof:name":"Almasi Electric Inc",
    "wof:placetype":"venue"
},
  "geometry": {"coordinates":[-73.919285,41.040196],"type":"Point"}
}