{
  "type": "Feature",
  "properties": {
    "addr:full":"640 E Boston Post Rd Mamaroneck NY 10543",
    "addr:housenumber":"640",
    "addr:postcode":"10543",
    "addr:street":"E Boston Post Rd",
    "iso:country":"US",
    "sg:address":"640 E Boston Post Rd",
    "sg:city":"Mamaroneck",
    "sg:classifiers":[
        {
            "category":"Restaurant",
            "type":"Food & Drink"
        }
    ],
    "sg:phone":"+1 914 381 1017",
    "sg:postcode":"10543",
    "sg:province":"NY",
    "wof:name":"Applebee's Neighborhood Grill",
    "wof:placetype":"venue"
},
  "geometry": {"coordinates":[-73.726496,40.952559],"type":"Point"}
}