{
  "type": "Feature",
  "properties": {
    "iso:country":"US",
    "sg:address":"200 Park Ave",
    "sg:city":"New York",
    "sg:classifiers":[
        {
            "category":"Banks & Credit Unions",
            "subcategory":"Investment Brokerage",
            "type":"Services"
        }
    ],
    "sg:phone":"+1 212 808 7474",
    "sg:postcode":"10017",
    "sg:province":"NY",
    "sg:tags":[
        "advisory"
    ],
    "wof:name":"Knoll Capital Management Co",
    "wof:placetype":"venue"
},
  "geometry": {"coordinates":[-73.975807,40.754678],"type":"Point"}
}