{
  "type": "Feature",
  "properties": {
    "addr:full":"2210 State Hwy 345 Madrid NY 13660",
    "addr:housenumber":"2210",
    "addr:postcode":"13660",
    "addr:street":"State Hwy 345",
    "iso:country":"US",
    "sg:address":"2210 State Hwy 345",
    "sg:city":"Madrid",
    "sg:classifiers":[
        {
            "category":"Building & Trades",
            "subcategory":"Plumbing",
            "type":"Services"
        }
    ],
    "sg:phone":"+1 315 322 0804",
    "sg:postcode":"13660",
    "sg:province":"NY",
    "sg:tags":[
        "contractor"
    ],
    "wof:name":"AC Huttel Inc",
    "wof:placetype":"venue"
},
  "geometry": {"coordinates":[-75.13421200000001,44.762938],"type":"Point"}
}