{
  "type": "Feature",
  "properties": {
    "addr:full":"675 Morris Ave Bronx NY 10451",
    "addr:housenumber":"675",
    "addr:postcode":"10451",
    "addr:street":"Morris Ave",
    "iso:country":"US",
    "sg:address":"675 Morris Ave",
    "sg:city":"Bronx",
    "sg:classifiers":[
        {
            "category":"Food & Beverages",
            "subcategory":"Groceries & Convenience Stores",
            "type":"Retail Goods"
        }
    ],
    "sg:phone":"+1 347 590 8300",
    "sg:postcode":"10451",
    "sg:province":"NY",
    "sg:website":"www.finefaresupermakrts.com",
    "wof:name":"Fine Fare Supermarket",
    "wof:placetype":"venue"
},
  "geometry": {"coordinates":[-73.92131500000001,40.820613],"type":"Point"}
}