{
  "type": "Feature",
  "properties": {
    "iso:country":"US",
    "sg:address":"100 Bethune Blvd",
    "sg:city":"Spring Valley",
    "sg:classifiers":[
        {
            "category":"Organizations",
            "subcategory":"Religious Organization",
            "type":"Services"
        }
    ],
    "sg:phone":"+1 845 352 9473",
    "sg:postcode":"10977",
    "sg:province":"NY",
    "sg:tags":[
        "church"
    ],
    "wof:name":"House Of Prayer",
    "wof:placetype":"venue"
},
  "geometry": {"coordinates":[-74.041568,41.122089],"type":"Point"}
}