{
  "type": "Feature",
  "properties": {
    "iso:country":"US",
    "sg:address":"37 W 47 St",
    "sg:city":"New York",
    "sg:classifiers":[
        {
            "category":"Shopping",
            "subcategory":"Jewelry",
            "type":"Retail Goods"
        }
    ],
    "sg:phone":"+1   ",
    "sg:postcode":"10036",
    "sg:province":"NY",
    "wof:name":"Ermar Creations Corporation",
    "wof:placetype":"venue"
},
  "geometry": {"coordinates":[-73.980859,40.757584],"type":"Point"}
}