{
  "type": "Feature",
  "properties": {
    "addr:full":"211 Fellows Rd Mechanicville NY 12118",
    "addr:housenumber":"211",
    "addr:postcode":"12118",
    "addr:street":"Fellows Rd",
    "iso:country":"US",
    "sg:address":"211 Fellows Rd",
    "sg:city":"Mechanicville",
    "sg:classifiers":[
        {
            "category":"Retail",
            "subcategory":"Car Wash",
            "type":"Services"
        }
    ],
    "sg:phone":"+1 518 665 1111",
    "sg:postcode":"12118",
    "sg:province":"NY",
    "sg:tags":[
        "carwash",
        "automobile",
        "detail",
        "clean"
    ],
    "wof:name":"Dubrays Auto Body & Detailing",
    "wof:placetype":"venue"
},
  "geometry": {"coordinates":[-73.724718,42.868951],"type":"Point"}
}