{
  "type": "Feature",
  "properties": {
    "addr:full":"55 E End Ave New York NY 10028",
    "addr:housenumber":"55",
    "addr:postcode":"10028",
    "addr:street":"E End Ave",
    "iso:country":"US",
    "sg:address":"55 E End Ave",
    "sg:city":"New York",
    "sg:classifiers":[
        {
            "category":"Professional",
            "type":"Services"
        }
    ],
    "sg:phone":"+1   ",
    "sg:postcode":"10028",
    "sg:province":"NY",
    "wof:name":"Emilie Jackson",
    "wof:placetype":"venue"
},
  "geometry": {"coordinates":[-73.94687,40.771804],"type":"Point"}
}