{
  "type": "Feature",
  "properties": {
    "addr:full":"468 Broadway Newburgh NY 12550",
    "addr:housenumber":"468",
    "addr:postcode":"12550",
    "addr:street":"Broadway",
    "iso:country":"US",
    "sg:address":"468 Broadway",
    "sg:city":"Newburgh",
    "sg:classifiers":[
        {
            "category":"Organizations",
            "subcategory":"Religious Organization",
            "type":"Services"
        }
    ],
    "sg:phone":"+1 845 561 0176",
    "sg:postcode":"12550",
    "sg:province":"NY",
    "wof:name":"Grace United Methodist Church",
    "wof:placetype":"venue"
},
  "geometry": {"coordinates":[-74.028198,41.501301],"type":"Point"}
}