{
  "type": "Feature",
  "properties": {
    "addr:full":"105 Harbor St Syracuse NY 13204",
    "addr:housenumber":"105",
    "addr:postcode":"13204",
    "addr:street":"Harbor St",
    "iso:country":"US",
    "sg:address":"105 Harbor St",
    "sg:city":"Syracuse",
    "sg:classifiers":[
        {
            "category":"Retail",
            "subcategory":"Auto Repair",
            "type":"Services"
        }
    ],
    "sg:phone":"+1   ",
    "sg:postcode":"13204",
    "sg:province":"NY",
    "sg:tags":[
        "corvette",
        "parts"
    ],
    "wof:name":"Corvette Barn",
    "wof:placetype":"venue"
},
  "geometry": {"coordinates":[-76.186694,43.055693],"type":"Point"}
}