{
  "type": "Feature",
  "properties": {
    "iso:country":"US",
    "sg:address":"609 W 57 St",
    "sg:city":"New York",
    "sg:classifiers":[
        {
            "category":"Retail",
            "subcategory":"Auto Repair",
            "type":"Services"
        }
    ],
    "sg:phone":"+1 917 210 5414",
    "sg:postcode":"10019",
    "sg:province":"NY",
    "sg:tags":[
        "wrecker"
    ],
    "wof:name":"Lubaucher Auto Rescue",
    "wof:placetype":"venue"
},
  "geometry": {"coordinates":[-73.994032,40.771422],"type":"Point"}
}