{
  "type": "Feature",
  "properties": {
    "iso:country":"US",
    "sg:address":"1357 E Gun Hill Rd",
    "sg:city":"Bronx",
    "sg:classifiers":[
        {
            "category":"Personal",
            "subcategory":"Beauty Salon",
            "type":"Services"
        }
    ],
    "sg:phone":"+1 718 654 6253",
    "sg:postcode":"10469",
    "sg:province":"NY",
    "sg:tags":[
        "manicuring"
    ],
    "wof:name":"Nail Heaven",
    "wof:placetype":"venue"
},
  "geometry": {"coordinates":[-73.846147,40.87052],"type":"Point"}
}