{
  "type": "Feature",
  "properties": {
    "addr:full":"14408 Liberty Avenue Jamaica NY 11435",
    "addr:housenumber":"14408",
    "addr:postcode":"11435",
    "addr:street":"Liberty Avenue",
    "iso:country":"US",
    "sg:address":"14408 Liberty Avenue",
    "sg:city":"Jamaica",
    "sg:classifiers":[
        {
            "category":"Building & Trades",
            "subcategory":"Construction",
            "type":"Services"
        }
    ],
    "sg:phone":"+1 718 262 0522",
    "sg:postcode":"11435",
    "sg:province":"NY",
    "sg:tags":[
        "contractor"
    ],
    "wof:name":"A1 State General Building & Remodeling Contractors",
    "wof:placetype":"venue"
},
  "geometry": {"coordinates":[-73.808498,40.692727],"type":"Point"}
}