{
  "type": "Feature",
  "properties": {
    "iso:country":"US",
    "sg:address":"33 1st Ave 2nd Fl",
    "sg:city":"New York",
    "sg:classifiers":[
        {
            "category":"Personal",
            "subcategory":"Day Spa",
            "type":"Services"
        }
    ],
    "sg:phone":"+1 212 777 3283",
    "sg:postcode":"10003",
    "sg:province":"NY",
    "sg:website":"www.waterfrontspanyc.com",
    "wof:name":"Water Front Spa",
    "wof:placetype":"venue"
},
  "geometry": {"coordinates":[-73.988176,40.724199],"type":"Point"}
}