{
  "type": "Feature",
  "properties": {
    "addr:full":"3618 Quentin Rd Brooklyn NY 11234",
    "addr:housenumber":"3618",
    "addr:postcode":"11234",
    "addr:street":"Quentin Rd",
    "iso:country":"US",
    "sg:address":"3618 Quentin Rd",
    "sg:city":"Brooklyn",
    "sg:classifiers":[
        {
            "category":"Home & Garden",
            "subcategory":"Building Materials",
            "type":"Retail Goods"
        }
    ],
    "sg:phone":"+1 718 627 5225",
    "sg:postcode":"11234",
    "sg:province":"NY",
    "sg:tags":[
        "windows"
    ],
    "wof:name":"Side By Side Home Improvement",
    "wof:placetype":"venue"
},
  "geometry": {"coordinates":[-73.936111,40.614978],"type":"Point"}
}