{
  "type": "Feature",
  "properties": {
    "addr:full":"376 Bay 44th St Brooklyn NY 11214",
    "addr:housenumber":"376",
    "addr:postcode":"11214",
    "addr:street":"Bay 44Th St",
    "iso:country":"US",
    "sg:address":"376 Bay 44th St",
    "sg:city":"Brooklyn",
    "sg:classifiers":[
        {
            "category":"Arts & Performance",
            "subcategory":"Arts Center",
            "type":"Entertainment"
        },
        {
            "category":"Education",
            "subcategory":"Special Training",
            "type":"Public Place"
        }
    ],
    "sg:phone":"+1 347 492 0534",
    "sg:postcode":"11214",
    "sg:province":"NY",
    "sg:tags":[
        "school",
        "performing",
        "specialty"
    ],
    "sg:website":"www.genesis-repertory.org",
    "wof:name":"Genesis Repertory",
    "wof:placetype":"venue"
},
  "geometry": {"coordinates":[-73.99414,40.587743],"type":"Point"}
}