{
  "type": "Feature",
  "properties": {
    "addr:full":"8208 Fernleaf Ct Buffalo NY 14221",
    "addr:housenumber":"8208",
    "addr:postcode":"14221",
    "addr:street":"Fernleaf Ct",
    "iso:country":"US",
    "sg:address":"8208 Fernleaf Ct",
    "sg:city":"Buffalo",
    "sg:classifiers":[
        {
            "category":"Restaurant",
            "type":"Food & Drink"
        }
    ],
    "sg:phone":"+1 716 689 3723",
    "sg:postcode":"14221",
    "sg:province":"NY",
    "sg:tags":[
        "cafe"
    ],
    "wof:name":"Tea Time",
    "wof:placetype":"venue"
},
  "geometry": {"coordinates":[-78.683436,42.996286],"type":"Point"}
}