{
  "type": "Feature",
  "properties": {
    "addr:full":"2 Taylor Ave Poughkeepsie NY 12601",
    "addr:housenumber":"2",
    "addr:postcode":"12601",
    "addr:street":"Taylor Ave",
    "iso:country":"US",
    "sg:address":"2 Taylor Ave",
    "sg:city":"Poughkeepsie",
    "sg:classifiers":[
        {
            "category":"Autos & Motor Vehicles",
            "subcategory":"Automobile Sales",
            "type":"Retail Goods"
        }
    ],
    "sg:phone":"+1 845 452 3600",
    "sg:postcode":"12601",
    "sg:province":"NY",
    "sg:tags":[
        "truck"
    ],
    "wof:name":"Healey International Trucks",
    "wof:placetype":"venue"
},
  "geometry": {"coordinates":[-73.927747,41.712717],"type":"Point"}
}