{
  "type": "Feature",
  "properties": {
    "iso:country":"US",
    "sg:address":"11 Mulberry St",
    "sg:city":"Middletown",
    "sg:classifiers":[
        {
            "category":"Organizations",
            "subcategory":"Religious Organization",
            "type":"Services"
        }
    ],
    "sg:phone":"+1 845 343 6460",
    "sg:postcode":"10940",
    "sg:province":"NY",
    "sg:tags":[
        "church"
    ],
    "wof:name":"First Baptist Church",
    "wof:placetype":"venue"
},
  "geometry": {"coordinates":[-74.42243999999999,41.444485],"type":"Point"}
}