{
  "type": "Feature",
  "properties": {
    "addr:full":"380 US Hwy 202 Somers NY 10589",
    "addr:housenumber":"380",
    "addr:postcode":"10589",
    "addr:street":"Us Hwy 202",
    "iso:country":"US",
    "sg:address":"380 US Hwy 202",
    "sg:city":"Somers",
    "sg:classifiers":[
        {
            "category":"Shopping",
            "subcategory":"Optical Goods",
            "type":"Retail Goods"
        }
    ],
    "sg:phone":"+1 914 277 5550",
    "sg:postcode":"10589",
    "sg:province":"NY",
    "sg:tags":[
        "optician"
    ],
    "wof:name":"Somers Eye Ctr",
    "wof:placetype":"venue"
},
  "geometry": {"coordinates":[-73.693899,41.327125],"type":"Point"}
}