{
  "type": "Feature",
  "properties": {
    "iso:country":"US",
    "sg:address":"444 Community Dr",
    "sg:city":"Manhasset",
    "sg:classifiers":[
        {
            "category":"Health Services",
            "subcategory":"Dentist",
            "type":"Services"
        }
    ],
    "sg:phone":"+1 516 627 8400",
    "sg:postcode":"11030",
    "sg:province":"NY",
    "wof:name":"Posner-Katz Suzanne DDS",
    "wof:placetype":"venue"
},
  "geometry": {"coordinates":[-73.70322299999999,40.779028],"type":"Point"}
}