{
  "type": "Feature",
  "properties": {
    "addr:full":"1125 Park Ave New York NY 10128",
    "addr:housenumber":"1125",
    "addr:postcode":"10128",
    "addr:street":"Park Ave",
    "iso:country":"US",
    "sg:address":"1125 Park Ave",
    "sg:city":"New York",
    "sg:classifiers":[
        {
            "category":"Real Estate",
            "subcategory":"Real Estate Operator",
            "type":"Services"
        }
    ],
    "sg:phone":"+1 212 831 5839",
    "sg:postcode":"10128",
    "sg:province":"NY",
    "sg:tags":[
        "building",
        "apartment"
    ],
    "wof:name":"1125 Park Avenue Corp",
    "wof:placetype":"venue"
},
  "geometry": {"coordinates":[-73.954927,40.783118],"type":"Point"}
}