{
  "type": "Feature",
  "properties": {
    "addr:full":"8 Nostrand Ave Selden NY 11784",
    "addr:housenumber":"8",
    "addr:postcode":"11784",
    "addr:street":"Nostrand Ave",
    "iso:country":"US",
    "sg:address":"8 Nostrand Ave",
    "sg:city":"Selden",
    "sg:classifiers":[
        {
            "category":"Professional",
            "subcategory":"Secretarial Services",
            "type":"Services"
        }
    ],
    "sg:phone":"+1 631 732 2300",
    "sg:postcode":"11784",
    "sg:province":"NY",
    "sg:tags":[
        "reporting",
        "court"
    ],
    "wof:name":"Other Office",
    "wof:placetype":"venue"
},
  "geometry": {"coordinates":[-73.05781899999999,40.889753],"type":"Point"}
}