{
  "type": "Feature",
  "properties": {
    "addr:full":"232 E 56th St Brooklyn NY 11203",
    "addr:housenumber":"232",
    "addr:postcode":"11203",
    "addr:street":"E 56Th St",
    "iso:country":"US",
    "sg:address":"232 E 56th St",
    "sg:city":"Brooklyn",
    "sg:classifiers":[
        {
            "category":"Social Services",
            "subcategory":"Child Care",
            "type":"Services"
        }
    ],
    "sg:phone":"+1 718 498 0957",
    "sg:postcode":"11203",
    "sg:province":"NY",
    "sg:tags":[
        "kindergarten",
        "academic",
        "school",
        "day"
    ],
    "wof:name":"Alexandrina-Yale Home Inc",
    "wof:placetype":"venue"
},
  "geometry": {"coordinates":[-73.92469800000001,40.651402],"type":"Point"}
}