{
  "type": "Feature",
  "properties": {
    "addr:full":"625 State Hwy 6n Mahopac NY 10541",
    "addr:housenumber":"625",
    "addr:postcode":"10541",
    "addr:street":"State Hwy",
    "iso:country":"US",
    "sg:address":"625 State Hwy 6n",
    "sg:city":"Mahopac",
    "sg:classifiers":[
        {
            "category":"Insurance",
            "subcategory":"Insurance Agent",
            "type":"Services"
        }
    ],
    "sg:phone":"+1 845 628 1700",
    "sg:postcode":"10541",
    "sg:province":"NY",
    "sg:tags":[
        "broker"
    ],
    "wof:name":"Spain Realty",
    "wof:placetype":"venue"
},
  "geometry": {"coordinates":[-73.75861999999999,41.374093],"type":"Point"}
}