{
  "type": "Feature",
  "properties": {
    "iso:country":"US",
    "sg:address":"2101 E 16th St",
    "sg:city":"Brooklyn",
    "sg:classifiers":[
        {
            "category":"Health Services",
            "subcategory":"Doctor",
            "type":"Services"
        }
    ],
    "sg:phone":"+1 718 266 9779",
    "sg:postcode":"11229",
    "sg:province":"NY",
    "wof:name":"21st Avenue Medical Plaza PC",
    "wof:placetype":"venue"
},
  "geometry": {"coordinates":[-73.95545300000001,40.598919],"type":"Point"}
}