{
  "type": "Feature",
  "properties": {
    "addr:full":"16 Truro Ln Hempstead NY 11550",
    "addr:housenumber":"16",
    "addr:postcode":"11550",
    "addr:street":"Truro Ln",
    "iso:country":"US",
    "sg:address":"16 Truro Ln",
    "sg:city":"Hempstead",
    "sg:classifiers":[
        {
            "category":"Building & Trades",
            "subcategory":"Construction",
            "type":"Services"
        }
    ],
    "sg:phone":"+1 516 505 1875",
    "sg:postcode":"11550",
    "sg:province":"NY",
    "sg:tags":[
        "house"
    ],
    "wof:name":"Melgar Quality Home",
    "wof:placetype":"venue"
},
  "geometry": {"coordinates":[-73.609177,40.710831],"type":"Point"}
}