{
  "type": "Feature",
  "properties": {
    "addr:full":"1867 Empire Blvd Webster NY 14580",
    "addr:housenumber":"1867",
    "addr:postcode":"14580",
    "addr:street":"Empire Blvd",
    "iso:country":"US",
    "sg:address":"1867 Empire Blvd",
    "sg:city":"Webster",
    "sg:classifiers":[
        {
            "category":"Autos & Motor Vehicles",
            "subcategory":"Fuel & Gas Station",
            "type":"Retail Goods"
        }
    ],
    "sg:phone":"+1   ",
    "sg:postcode":"14580",
    "sg:province":"NY",
    "sg:tags":[
        "station",
        "gasoline"
    ],
    "wof:name":"Mobil Mart",
    "wof:placetype":"venue"
},
  "geometry": {"coordinates":[-77.50230999999999,43.193042],"type":"Point"}
}