{
  "type": "Feature",
  "properties": {
    "iso:country":"US",
    "sg:address":"846 Scarsdale Ave",
    "sg:city":"Scarsdale",
    "sg:classifiers":[
        {
            "category":"Sports & Exercise",
            "subcategory":"Gym",
            "type":"Entertainment"
        }
    ],
    "sg:phone":"+1 914 722 7646",
    "sg:postcode":"10583",
    "sg:province":"NY",
    "sg:tags":[
        "fitness",
        "physical",
        "facility"
    ],
    "wof:name":"Center For Movement",
    "wof:placetype":"venue"
},
  "geometry": {"coordinates":[-73.80932799999999,40.985029],"type":"Point"}
}