{
  "type": "Feature",
  "properties": {
    "iso:country":"US",
    "sg:address":"170 Gardiners Ave",
    "sg:city":"Levittown",
    "sg:classifiers":[
        {
            "category":"Building & Trades",
            "subcategory":"Locksmith",
            "type":"Services"
        }
    ],
    "sg:phone":"+1 516 796 1986",
    "sg:postcode":"11756",
    "sg:province":"NY",
    "sg:tags":[
        "key"
    ],
    "wof:name":"A 24 Hour A Emergency Locksmith",
    "wof:placetype":"venue"
},
  "geometry": {"coordinates":[-73.515602,40.721298],"type":"Point"}
}