{
  "type": "Feature",
  "properties": {
    "iso:country":"US",
    "sg:address":"73 Lang Ave",
    "sg:city":"Buffalo",
    "sg:classifiers":[
        {
            "category":"Building & Trades",
            "subcategory":"Construction",
            "type":"Services"
        }
    ],
    "sg:phone":"+1 716 893 5448",
    "sg:postcode":"14215",
    "sg:province":"NY",
    "sg:tags":[
        "contractor"
    ],
    "wof:name":"AES Improvements",
    "wof:placetype":"venue"
},
  "geometry": {"coordinates":[-78.811188,42.918563],"type":"Point"}
}