{
  "type": "Feature",
  "properties": {
    "addr:full":"483 Cherry St Bedford Hills NY 10507",
    "addr:housenumber":"483",
    "addr:postcode":"10507",
    "addr:street":"Cherry St",
    "iso:country":"US",
    "sg:address":"483 Cherry St",
    "sg:city":"Bedford Hills",
    "sg:classifiers":[
        {
            "category":"Retail",
            "subcategory":"Auto Repair",
            "type":"Services"
        }
    ],
    "sg:phone":"+1   ",
    "sg:postcode":"10507",
    "sg:province":"NY",
    "sg:tags":[
        "automotive"
    ],
    "wof:name":"Northern Auto Sound & Security",
    "wof:placetype":"venue"
},
  "geometry": {"coordinates":[-73.70049,41.238884],"type":"Point"}
}