{
  "type": "Feature",
  "properties": {
    "iso:country":"US",
    "sg:address":"1467 W Water St",
    "sg:city":"Elmira",
    "sg:classifiers":[
        {
            "category":"Manufacturing",
            "subcategory":"Signs",
            "type":"Manufacturing & Wholesale Goods"
        }
    ],
    "sg:phone":"+1   ",
    "sg:postcode":"14905",
    "sg:province":"NY",
    "sg:tags":[
        "specialty",
        "mfg"
    ],
    "wof:name":"Operation House ID",
    "wof:placetype":"venue"
},
  "geometry": {"coordinates":[-76.85101899999999,42.077518],"type":"Point"}
}