{
  "type": "Feature",
  "properties": {
    "iso:country":"US",
    "sg:address":"2 Flowerfield Ste 24",
    "sg:city":"Saint James",
    "sg:classifiers":[
        {
            "category":"Health Services",
            "subcategory":"Optometrist",
            "type":"Services"
        }
    ],
    "sg:phone":"+1 631 584 5310",
    "sg:postcode":"11780",
    "sg:province":"NY",
    "wof:name":"Night Vision Creations",
    "wof:placetype":"venue"
},
  "geometry": {"coordinates":[-73.146455,40.895834],"type":"Point"}
}