{
  "type": "Feature",
  "properties": {
    "addr:full":"1825 Givan Ave Bronx NY 10469",
    "addr:housenumber":"1825",
    "addr:postcode":"10469",
    "addr:street":"Givan Ave",
    "iso:country":"US",
    "sg:address":"1825 Givan Ave",
    "sg:city":"Bronx",
    "sg:classifiers":[
        {
            "category":"Retail",
            "subcategory":"Auto Repair",
            "type":"Services"
        }
    ],
    "sg:phone":"+1 718 379 2100",
    "sg:postcode":"10469",
    "sg:province":"NY",
    "sg:tags":[
        "body",
        "automobile",
        "painting"
    ],
    "wof:name":"Universe Auto Body",
    "wof:placetype":"venue"
},
  "geometry": {"coordinates":[-73.839431,40.876621],"type":"Point"}
}