{
  "type": "Feature",
  "properties": {
    "iso:country":"US",
    "sg:address":"1924 Bedell Rd",
    "sg:city":"Grand Island",
    "sg:classifiers":[
        {
            "category":"Building & Trades",
            "subcategory":"Equipment Rental",
            "type":"Services"
        }
    ],
    "sg:phone":"+1   ",
    "sg:postcode":"14072",
    "sg:province":"NY",
    "wof:name":"Dirty Harrys Amusements",
    "wof:placetype":"venue"
},
  "geometry": {"coordinates":[-78.96554500000001,43.03632],"type":"Point"}
}