{
  "type": "Feature",
  "properties": {
    "iso:country":"US",
    "sg:address":"1078 Route 9",
    "sg:city":"Fishkill",
    "sg:classifiers":[
        {
            "category":"Retail",
            "subcategory":"Storage",
            "type":"Services"
        }
    ],
    "sg:phone":"+1 845 896 8960",
    "sg:postcode":"12524",
    "sg:province":"NY",
    "sg:tags":[
        "self"
    ],
    "sg:website":"www.guardianselfstorage.com",
    "wof:name":"Guardian Self-Storage",
    "wof:placetype":"venue"
},
  "geometry": {"coordinates":[-73.903397,41.561298],"type":"Point"}
}