{
  "type": "Feature",
  "properties": {
    "iso:country":"US",
    "sg:address":"275 Jefferson Ave",
    "sg:city":"Canandaigua",
    "sg:classifiers":[
        {
            "category":"Real Estate",
            "subcategory":"Real Estate Operator",
            "type":"Services"
        }
    ],
    "sg:phone":"+1 585 396 2730",
    "sg:postcode":"14424",
    "sg:province":"NY",
    "sg:tags":[
        "apartment"
    ],
    "wof:name":"Lakeside Village Apts",
    "wof:placetype":"venue"
},
  "geometry": {"coordinates":[-77.272401,42.886669],"type":"Point"}
}