{
  "type": "Feature",
  "properties": {
    "addr:full":"4 Jones St East Setauket NY 11733",
    "addr:housenumber":"4",
    "addr:postcode":"11733",
    "addr:street":"Jones St",
    "iso:country":"US",
    "sg:address":"4 Jones St",
    "sg:city":"East Setauket",
    "sg:classifiers":[
        {
            "category":"Building & Trades",
            "subcategory":"Construction",
            "type":"Services"
        }
    ],
    "sg:phone":"+1 631 751 0961",
    "sg:postcode":"11733",
    "sg:province":"NY",
    "sg:tags":[
        "contractor"
    ],
    "wof:name":"Aqua Earth Inc",
    "wof:placetype":"venue"
},
  "geometry": {"coordinates":[-73.10318100000001,40.940967],"type":"Point"}
}