{
  "type": "Feature",
  "properties": {
    "addr:full":"31 S Westcott Rd Schenectady NY 12306",
    "addr:housenumber":"31",
    "addr:postcode":"12306",
    "addr:street":"S Westcott Rd",
    "iso:country":"US",
    "sg:address":"31 S Westcott Rd",
    "sg:city":"Schenectady",
    "sg:classifiers":[
        {
            "category":"Restaurant",
            "type":"Food & Drink"
        }
    ],
    "sg:phone":"+1   ",
    "sg:postcode":"12306",
    "sg:province":"NY",
    "sg:tags":[
        "eating"
    ],
    "wof:name":"Conscious Cuisine",
    "wof:placetype":"venue"
},
  "geometry": {"coordinates":[-73.98838499999999,42.769875],"type":"Point"}
}