{
  "type": "Feature",
  "properties": {
    "addr:full":"867 9th Ave New York NY 10019",
    "addr:housenumber":"867",
    "addr:postcode":"10019",
    "addr:street":"9Th Ave",
    "iso:country":"US",
    "sg:address":"867 9th Ave",
    "sg:city":"New York",
    "sg:classifiers":[
        {
            "category":"Restaurant",
            "type":"Food & Drink"
        },
        {
            "category":"Bars & Pubs",
            "subcategory":"Dive Bar",
            "type":"Food & Drink"
        }
    ],
    "sg:phone":"+1 212 974 2826",
    "sg:postcode":"10019",
    "sg:province":"NY",
    "sg:website":"www.lpgnyc.com/",
    "wof:name":"Lincoln Park Grill",
    "wof:placetype":"venue"
},
  "geometry": {"coordinates":[-73.986,40.7677],"type":"Point"}
}