{
  "type": "Feature",
  "properties": {
    "addr:full":"84 E 7 St New York NY 10003",
    "addr:housenumber":"84;7",
    "addr:postcode":"10003",
    "addr:street":"E",
    "iso:country":"US",
    "sg:address":"84 E 7 St",
    "sg:city":"New York",
    "sg:classifiers":[
        {
            "category":"Shopping",
            "subcategory":"Clothing, Apparel, & Fashions",
            "type":"Retail Goods"
        }
    ],
    "sg:phone":"+1   ",
    "sg:postcode":"10003",
    "sg:province":"NY",
    "sg:tags":[
        "family"
    ],
    "wof:name":"Amarcord Vintage Fashion",
    "wof:placetype":"venue"
},
  "geometry": {"coordinates":[-73.987403,40.727821],"type":"Point"}
}