{
  "type": "Feature",
  "properties": {
    "addr:full":"251 East Ave Hilton NY 14468",
    "addr:housenumber":"251",
    "addr:postcode":"14468",
    "addr:street":"East Ave",
    "iso:country":"US",
    "sg:address":"251 East Ave",
    "sg:city":"Hilton",
    "sg:classifiers":[
        {
            "category":"Health Services",
            "subcategory":"Medical Lab",
            "type":"Services"
        }
    ],
    "sg:phone":"+1   ",
    "sg:postcode":"14468",
    "sg:province":"NY",
    "sg:tags":[
        "laboratory",
        "dental"
    ],
    "wof:name":"Richardson Professional Dental",
    "wof:placetype":"venue"
},
  "geometry": {"coordinates":[-77.786355,43.28966],"type":"Point"}
}