{
  "type": "Feature",
  "properties": {
    "iso:country":"US",
    "sg:address":"33 Chazy Lake Rd",
    "sg:city":"Saranac",
    "sg:classifiers":[
        {
            "category":"Building & Trades",
            "subcategory":"Construction",
            "type":"Services"
        }
    ],
    "sg:phone":"+1 518 293 8226",
    "sg:postcode":"12981",
    "sg:province":"NY",
    "sg:tags":[
        "contractor"
    ],
    "wof:name":"Lyon Mountain Ironworks",
    "wof:placetype":"venue"
},
  "geometry": {"coordinates":[-73.736852,44.661827],"type":"Point"}
}