{
  "type": "Feature",
  "properties": {
    "iso:country":"US",
    "sg:address":"520 8th Avenue",
    "sg:city":"New York",
    "sg:classifiers":[
        {
            "category":"Arts & Performance",
            "subcategory":"Arts Center",
            "type":"Entertainment"
        },
        {
            "category":"Cinema",
            "subcategory":"Movie Theater",
            "type":"Entertainment"
        }
    ],
    "sg:phone":"+1 212 268 3717",
    "sg:postcode":"10018",
    "sg:province":"NY",
    "sg:tags":[
        "performing"
    ],
    "wof:name":"Voice & Vision",
    "wof:placetype":"venue"
},
  "geometry": {"coordinates":[-73.992514,40.75345],"type":"Point"}
}