{
  "type": "Feature",
  "properties": {
    "addr:full":"1090 Morris Park Ave Bronx NY 10461",
    "addr:housenumber":"1090",
    "addr:postcode":"10461",
    "addr:street":"Morris Park Ave",
    "iso:country":"US",
    "sg:address":"1090 Morris Park Ave",
    "sg:city":"Bronx",
    "sg:classifiers":[
        {
            "category":"Professional",
            "subcategory":"Business Services",
            "type":"Services"
        }
    ],
    "sg:phone":"+1 718 863 6474",
    "sg:postcode":"10461",
    "sg:province":"NY",
    "sg:tags":[
        "embroidery"
    ],
    "wof:name":"Hot Styles Inc",
    "wof:placetype":"venue"
},
  "geometry": {"coordinates":[-73.853414,40.849241],"type":"Point"}
}