{
  "type": "Feature",
  "properties": {
    "iso:country":"US",
    "sg:address":"332 Lattintown Rd",
    "sg:city":"Marlboro",
    "sg:classifiers":[
        {
            "category":"Social Services",
            "subcategory":"Child Care",
            "type":"Services"
        },
        {
            "category":"Education",
            "subcategory":"School",
            "type":"Public Place"
        }
    ],
    "sg:phone":"+1 845 236 3578",
    "sg:postcode":"12542",
    "sg:province":"NY",
    "sg:tags":[
        "day"
    ],
    "wof:name":"Little Friends Pre-School",
    "wof:placetype":"venue"
},
  "geometry": {"coordinates":[-74.000702,41.598999],"type":"Point"}
}