{
  "type": "Feature",
  "properties": {
    "addr:full":"5780 Tilden Hill Rd Verona NY 13478",
    "addr:housenumber":"5780",
    "addr:postcode":"13478",
    "addr:street":"Tilden Hill Rd",
    "iso:country":"US",
    "sg:address":"5780 Tilden Hill Rd",
    "sg:city":"Verona",
    "sg:classifiers":[
        {
            "category":"Shopping",
            "subcategory":"Gifts & Souvenirs",
            "type":"Retail Goods"
        }
    ],
    "sg:phone":"+1   ",
    "sg:postcode":"13478",
    "sg:province":"NY",
    "wof:name":"Rail Fence Quilting Shop",
    "wof:placetype":"venue"
},
  "geometry": {"coordinates":[-75.559314,43.142577],"type":"Point"}
}