{
  "type": "Feature",
  "properties": {
    "addr:full":"67 Maple Ave Staten Island NY 10302",
    "addr:housenumber":"67",
    "addr:postcode":"10302",
    "addr:street":"Maple Ave",
    "iso:country":"US",
    "sg:address":"67 Maple Ave",
    "sg:city":"Staten Island",
    "sg:classifiers":[
        {
            "category":"Shopping",
            "subcategory":"Discount & Variety Stores",
            "type":"Retail Goods"
        }
    ],
    "sg:phone":"+1 718 815 5750",
    "sg:postcode":"10302",
    "sg:province":"NY",
    "sg:tags":[
        "post",
        "trading"
    ],
    "wof:name":"Trading Inc",
    "wof:placetype":"venue"
},
  "geometry": {"coordinates":[-74.13379399999999,40.640125],"type":"Point"}
}