{
  "type": "Feature",
  "properties": {
    "addr:full":"691 Pinnacle Rd Voorheesville NY 12186",
    "addr:housenumber":"691",
    "addr:postcode":"12186",
    "addr:street":"Pinnacle Rd",
    "iso:country":"US",
    "sg:address":"691 Pinnacle Rd",
    "sg:city":"Voorheesville",
    "sg:classifiers":[
        {
            "category":"Education",
            "subcategory":"School",
            "type":"Public Place"
        }
    ],
    "sg:phone":"+1 518 872 9187",
    "sg:postcode":"12186",
    "sg:province":"NY",
    "wof:name":"Siena College",
    "wof:placetype":"venue"
},
  "geometry": {"coordinates":[-74.000231,42.636813],"type":"Point"}
}