{
  "type": "Feature",
  "properties": {
    "iso:country":"US",
    "sg:address":"1090 5th Ave",
    "sg:city":"New York",
    "sg:classifiers":[
        {
            "category":"Retail",
            "subcategory":"Auto Repair",
            "type":"Services"
        }
    ],
    "sg:phone":"+1 646 307 4800",
    "sg:postcode":"10128",
    "sg:province":"NY",
    "sg:tags":[
        "wrecker"
    ],
    "wof:name":"Emergency 24 Hr Auto Club",
    "wof:placetype":"venue"
},
  "geometry": {"coordinates":[-73.95812599999999,40.784512],"type":"Point"}
}