{
  "type": "Feature",
  "properties": {
    "addr:full":"324 W 22 St New York NY 10011",
    "addr:housenumber":"324",
    "addr:postcode":"10011",
    "addr:street":"W 22 St",
    "iso:country":"US",
    "sg:address":"324 W 22 St",
    "sg:city":"New York",
    "sg:classifiers":[
        {
            "category":"Real Estate",
            "subcategory":"Real Estate Operator",
            "type":"Services"
        }
    ],
    "sg:phone":"+1 212 675 0934",
    "sg:postcode":"10011",
    "sg:province":"NY",
    "sg:tags":[
        "building",
        "manager",
        "industrial",
        "an"
    ],
    "wof:name":"Kromedge Distributing Co Inc",
    "wof:placetype":"venue"
},
  "geometry": {"coordinates":[-74.001322,40.745468],"type":"Point"}
}