{
  "type": "Feature",
  "properties": {
    "iso:country":"US",
    "sg:address":"17 Colvin Ave",
    "sg:city":"Albany",
    "sg:classifiers":[
        {
            "category":"Personal",
            "subcategory":"Beauty Salon",
            "type":"Services"
        }
    ],
    "sg:phone":"+1 518 512 3806",
    "sg:postcode":"12206",
    "sg:province":"NY",
    "sg:tags":[
        "hair",
        "stylist"
    ],
    "wof:name":"Bella Fiora Hair Studio",
    "wof:placetype":"venue"
},
  "geometry": {"coordinates":[-73.796469,42.6778],"type":"Point"}
}