{
  "type": "Feature",
  "properties": {
    "addr:full":"636 Oak St Copiague NY 11726",
    "addr:housenumber":"636",
    "addr:postcode":"11726",
    "addr:street":"Oak St",
    "iso:country":"US",
    "sg:address":"636 Oak St",
    "sg:city":"Copiague",
    "sg:classifiers":[
        {
            "category":"Retail",
            "subcategory":"Laundry & Dry Cleaning",
            "type":"Services"
        }
    ],
    "sg:phone":"+1 631 842 6565",
    "sg:postcode":"11726",
    "sg:province":"NY",
    "wof:name":"Frank's Laundromat",
    "wof:placetype":"venue"
},
  "geometry": {"coordinates":[-73.388705,40.682143],"type":"Point"}
}