{
  "type": "Feature",
  "properties": {
    "addr:full":"633 Myrtle Ave Brooklyn NY 11205",
    "addr:housenumber":"633",
    "addr:postcode":"11205",
    "addr:street":"Myrtle Ave",
    "iso:country":"US",
    "sg:address":"633 Myrtle Ave",
    "sg:city":"Brooklyn",
    "sg:classifiers":[
        {
            "category":"Food & Beverages",
            "subcategory":"Groceries & Convenience Stores",
            "type":"Retail Goods"
        }
    ],
    "sg:phone":"+1 718 638 2519",
    "sg:postcode":"11205",
    "sg:province":"NY",
    "wof:name":"Cholula Ii Deli Grocery",
    "wof:placetype":"venue"
},
  "geometry": {"coordinates":[-73.95848599999999,40.694448],"type":"Point"}
}