{
  "type": "Feature",
  "properties": {
    "addr:full":"2425 Lorillard Pl Bronx NY 10458",
    "addr:housenumber":"2425",
    "addr:postcode":"10458",
    "addr:street":"Lorillard Pl",
    "iso:country":"US",
    "sg:address":"2425 Lorillard Pl",
    "sg:city":"Bronx",
    "sg:classifiers":[
        {
            "category":"Government",
            "subcategory":"Office",
            "type":"Public Place"
        }
    ],
    "sg:phone":"+1 718 220 7400",
    "sg:postcode":"10458",
    "sg:province":"NY",
    "sg:tags":[
        "city"
    ],
    "wof:name":"City Squash Inc",
    "wof:placetype":"venue"
},
  "geometry": {"coordinates":[-73.888896,40.856748],"type":"Point"}
}