{
  "type": "Feature",
  "properties": {
    "addr:full":"15 Skyline Dr Hawthorne NY 10532",
    "addr:housenumber":"15",
    "addr:postcode":"10532",
    "addr:street":"Skyline Dr",
    "iso:country":"US",
    "sg:address":"15 Skyline Dr",
    "sg:city":"Hawthorne",
    "sg:classifiers":[
        {
            "category":"Professional",
            "subcategory":"Advertising",
            "type":"Services"
        }
    ],
    "sg:phone":"+1 914 593 7200",
    "sg:postcode":"10532",
    "sg:province":"NY",
    "sg:tags":[
        "mail",
        "direct"
    ],
    "wof:name":"Listworks Corp",
    "wof:placetype":"venue"
},
  "geometry": {"coordinates":[-73.811442,41.093144],"type":"Point"}
}