{
  "type": "Feature",
  "properties": {
    "iso:country":"US",
    "sg:address":"274 Seneca St",
    "sg:city":"Ronkonkoma",
    "sg:classifiers":[
        {
            "category":"Organizations",
            "subcategory":"Professional Association",
            "type":"Services"
        }
    ],
    "sg:phone":"+1 631 981 2824",
    "sg:postcode":"11779",
    "sg:province":"NY",
    "sg:tags":[
        "sale"
    ],
    "wof:name":"R&L Fuel Oil Inc",
    "wof:placetype":"venue"
},
  "geometry": {"coordinates":[-73.136864,40.821843],"type":"Point"}
}