{
  "type": "Feature",
  "properties": {
    "addr:full":"9 Carnation Dr Nanuet NY 10954",
    "addr:housenumber":"9",
    "addr:postcode":"10954",
    "addr:street":"Carnation Dr",
    "iso:country":"US",
    "sg:address":"9 Carnation Dr",
    "sg:city":"Nanuet",
    "sg:classifiers":[
        {
            "category":"Professional",
            "subcategory":"Art Services",
            "type":"Services"
        }
    ],
    "sg:phone":"+1 914 672 5595",
    "sg:postcode":"10954",
    "sg:province":"NY",
    "sg:tags":[
        "interior",
        "designer",
        "decorator"
    ],
    "sg:website":"http://www.sensiblestaging.biz",
    "wof:name":"Sensible Staging & Redesign",
    "wof:placetype":"venue"
},
  "geometry": {"coordinates":[-74.012704,41.117594],"type":"Point"}
}