{
  "type": "Feature",
  "properties": {
    "addr:full":"1274 Eggert Rd Buffalo NY 14226",
    "addr:housenumber":"1274",
    "addr:postcode":"14226",
    "addr:street":"Eggert Rd",
    "iso:country":"US",
    "sg:address":"1274 Eggert Rd",
    "sg:city":"Buffalo",
    "sg:classifiers":[
        {
            "category":"Restaurant",
            "type":"Food & Drink"
        }
    ],
    "sg:menulink":"http://www.allmenus.com/ny/amherst/17752-brunos-market-pizzeria/menu/",
    "sg:phone":"+1 716 833 6800",
    "sg:postcode":"14226",
    "sg:province":"NY",
    "sg:tags":[
        "sandwich",
        "salad",
        "american",
        "chicken",
        "pizza",
        "wing",
        "italian"
    ],
    "wof:name":"Bruno's Market Pizzeria",
    "wof:placetype":"venue"
},
  "geometry": {"coordinates":[-78.80381199999999,42.963459],"type":"Point"}
}