{
  "type": "Feature",
  "properties": {
    "addr:full":"58 Martin Ave Blasdell NY 14219",
    "addr:housenumber":"58",
    "addr:postcode":"14219",
    "addr:street":"Martin Ave",
    "iso:country":"US",
    "sg:address":"58 Martin Ave",
    "sg:city":"Blasdell",
    "sg:classifiers":[
        {
            "category":"Building & Trades",
            "subcategory":"Landscaping Services",
            "type":"Services"
        }
    ],
    "sg:phone":"+1 716 827 9107",
    "sg:postcode":"14219",
    "sg:province":"NY",
    "sg:tags":[
        "landscape",
        "contractor"
    ],
    "wof:name":"Barone Enterprise",
    "wof:placetype":"venue"
},
  "geometry": {"coordinates":[-78.83143099999999,42.791973],"type":"Point"}
}