{
  "type": "Feature",
  "properties": {
    "iso:country":"US",
    "sg:address":"159 S Pearl St",
    "sg:city":"Mechanicville",
    "sg:classifiers":[
        {
            "category":"Building & Trades",
            "subcategory":"Construction",
            "type":"Services"
        }
    ],
    "sg:phone":"+1 518 664 3540",
    "sg:postcode":"12118",
    "sg:province":"NY",
    "sg:tags":[
        "excavating",
        "contractor"
    ],
    "wof:name":"Royal R Dyer Construction Co",
    "wof:placetype":"venue"
},
  "geometry": {"coordinates":[-73.67979699999999,42.898236],"type":"Point"}
}