{
  "type": "Feature",
  "properties": {
    "iso:country":"US",
    "sg:address":"1770 Plank Rd",
    "sg:city":"Webster",
    "sg:classifiers":[
        {
            "category":"Professional",
            "subcategory":"Business Services",
            "type":"Services"
        }
    ],
    "sg:phone":"+1 585 872 1981",
    "sg:postcode":"14580",
    "sg:province":"NY",
    "wof:name":"Tal Tee Associates",
    "wof:placetype":"venue"
},
  "geometry": {"coordinates":[-77.376649,43.181977],"type":"Point"}
}