{
  "type": "Feature",
  "properties": {
    "addr:full":"37 Grand St Sidney NY 13838",
    "addr:housenumber":"37",
    "addr:postcode":"13838",
    "addr:street":"Grand St",
    "iso:country":"US",
    "sg:address":"37 Grand St",
    "sg:city":"Sidney",
    "sg:classifiers":[
        {
            "category":"Health Services",
            "subcategory":"Clinic",
            "type":"Services"
        }
    ],
    "sg:phone":"+1 607 563 2152",
    "sg:postcode":"13838",
    "sg:province":"NY",
    "sg:tags":[
        "home",
        "care"
    ],
    "wof:name":"Family Homecare Inc",
    "wof:placetype":"venue"
},
  "geometry": {"coordinates":[-75.391127,42.313986],"type":"Point"}
}