{
  "type": "Feature",
  "properties": {
    "addr:full":"1498 Lawrence Johnson Rd Beaver Dams NY 14812",
    "addr:housenumber":"1498",
    "addr:postcode":"14812",
    "addr:street":"Lawrence Johnson Rd",
    "iso:country":"US",
    "sg:address":"1498 Lawrence Johnson Rd",
    "sg:city":"Beaver Dams",
    "sg:classifiers":[
        {
            "category":"Sports & Exercise",
            "subcategory":"Race Track",
            "type":"Entertainment"
        }
    ],
    "sg:phone":"+1 607 535 4787",
    "sg:postcode":"14812",
    "sg:province":"NY",
    "wof:name":"Rhoads Motorsports",
    "wof:placetype":"venue"
},
  "geometry": {"coordinates":[-76.86969999999999,42.302956],"type":"Point"}
}