{
  "type": "Feature",
  "properties": {
    "addr:full":"730 Ocean Pkwy Brooklyn NY 11230",
    "addr:housenumber":"730",
    "addr:postcode":"11230",
    "addr:street":"Ocean Pkwy",
    "iso:country":"US",
    "sg:address":"730 Ocean Pkwy",
    "sg:city":"Brooklyn",
    "sg:classifiers":[
        {
            "category":"Freight",
            "type":"Transportation"
        }
    ],
    "sg:phone":"+1 718 438 6640",
    "sg:postcode":"11230",
    "sg:province":"NY",
    "sg:tags":[
        "trucking"
    ],
    "wof:name":"Y & D Trucking",
    "wof:placetype":"venue"
},
  "geometry": {"coordinates":[-73.971654,40.630003],"type":"Point"}
}