{
  "type": "Feature",
  "properties": {
    "iso:country":"US",
    "sg:address":"7 Canterbury Dr",
    "sg:city":"Coram",
    "sg:classifiers":[
        {
            "category":"Manufacturing",
            "subcategory":"Motor Vehicles & Parts",
            "type":"Manufacturing & Wholesale Goods"
        }
    ],
    "sg:phone":"+1   ",
    "sg:postcode":"11727",
    "sg:province":"NY",
    "sg:tags":[
        "mfg"
    ],
    "wof:name":"Vivo Sport Design Inc",
    "wof:placetype":"venue"
},
  "geometry": {"coordinates":[-73.015017,40.884646],"type":"Point"}
}