{
  "type": "Feature",
  "properties": {
    "iso:country":"US",
    "sg:address":"1237 Main St E",
    "sg:city":"Rochester",
    "sg:classifiers":[
        {
            "category":"Real Estate",
            "subcategory":"Real Estate Operator",
            "type":"Services"
        }
    ],
    "sg:phone":"+1 585 544 8981",
    "sg:postcode":"14609",
    "sg:province":"NY",
    "sg:tags":[
        "building",
        "nonresidential"
    ],
    "wof:name":"Fedder Industrial Park Inc",
    "wof:placetype":"venue"
},
  "geometry": {"coordinates":[-77.578248,43.161519],"type":"Point"}
}