{
  "type": "Feature",
  "properties": {
    "iso:country":"US",
    "sg:address":"6884 Peck Rd",
    "sg:city":"Syracuse",
    "sg:classifiers":[
        {
            "category":"Wholesale",
            "subcategory":"Plants",
            "type":"Manufacturing & Wholesale Goods"
        }
    ],
    "sg:phone":"+1 315 638 0028",
    "sg:postcode":"13209",
    "sg:province":"NY",
    "sg:tags":[
        "supply"
    ],
    "wof:name":"Klabens Nursery",
    "wof:placetype":"venue"
},
  "geometry": {"coordinates":[-76.302582,43.102632],"type":"Point"}
}