{
  "type": "Feature",
  "properties": {
    "iso:country":"US",
    "sg:address":"911 Route 6",
    "sg:city":"Mahopac",
    "sg:classifiers":[
        {
            "category":"Home & Garden",
            "subcategory":"Building Materials",
            "type":"Retail Goods"
        }
    ],
    "sg:phone":"+1 845 628 8111",
    "sg:postcode":"10541",
    "sg:province":"NY",
    "sg:tags":[
        "supply"
    ],
    "sg:website":"www.decklumber.com",
    "wof:name":"Mahopac Railroad Tie Corp",
    "wof:placetype":"venue"
},
  "geometry": {"coordinates":[-73.72550200000001,41.387901],"type":"Point"}
}