{
  "type": "Feature",
  "properties": {
    "iso:country":"US",
    "sg:address":"223 Floral Ave",
    "sg:city":"Plainview",
    "sg:classifiers":[
        {
            "category":"Professional",
            "subcategory":"Computer Services",
            "type":"Services"
        }
    ],
    "sg:phone":"+1 516 935 3594",
    "sg:postcode":"11803",
    "sg:province":"NY",
    "sg:tags":[
        "processing",
        "datum"
    ],
    "sg:website":"www.ldsllc.com",
    "wof:name":"Land Data Svc",
    "wof:placetype":"venue"
},
  "geometry": {"coordinates":[-73.495448,40.769427],"type":"Point"}
}