{
  "type": "Feature",
  "properties": {
    "iso:country":"US",
    "sg:address":"96 N Main St",
    "sg:city":"Bainbridge",
    "sg:classifiers":[
        {
            "category":"Freight",
            "type":"Transportation"
        }
    ],
    "sg:phone":"+1 607 967 8080",
    "sg:postcode":"13733",
    "sg:province":"NY",
    "sg:tags":[
        "commercial",
        "storage"
    ],
    "wof:name":"Storage Center",
    "wof:placetype":"venue"
},
  "geometry": {"coordinates":[-75.474676,42.297311],"type":"Point"}
}