{
  "type": "Feature",
  "properties": {
    "addr:full":"44 W 63rd St New York NY 10023",
    "addr:housenumber":"44",
    "addr:postcode":"10023",
    "addr:street":"W 63Rd St",
    "iso:country":"US",
    "sg:address":"44 W 63rd St",
    "sg:city":"New York",
    "sg:classifiers":[
        {
            "category":"Restaurant",
            "type":"Food & Drink"
        }
    ],
    "sg:phone":"+1 212 956 1288",
    "sg:postcode":"10023",
    "sg:province":"NY",
    "sg:tags":[
        "new",
        "seafood",
        "american"
    ],
    "sg:website":"www.empirehotelnyc.com/eat-cc.php",
    "wof:name":"Ed's Chowder House",
    "wof:placetype":"venue"
},
  "geometry": {"coordinates":[-73.980818,40.770759],"type":"Point"}
}