{
  "type": "Feature",
  "properties": {
    "iso:country":"US",
    "sg:address":"194 Lauman Ln",
    "sg:city":"Hicksville",
    "sg:classifiers":[
        {
            "category":"Manufacturing",
            "subcategory":"Metals",
            "type":"Manufacturing & Wholesale Goods"
        }
    ],
    "sg:phone":"+1 516 433 4161",
    "sg:postcode":"11801",
    "sg:province":"NY",
    "sg:tags":[
        "fabricated",
        "structural"
    ],
    "wof:name":"Behi Iron Works",
    "wof:placetype":"venue"
},
  "geometry": {"coordinates":[-73.498053,40.743648],"type":"Point"}
}