{
  "type": "Feature",
  "properties": {
    "addr:full":"30 Matthews St Ste 104 Goshen NY 10924",
    "addr:housenumber":"30",
    "addr:postcode":"10924",
    "addr:street":"Matthews St Ste 104",
    "iso:country":"US",
    "sg:address":"30 Matthews St Ste 104",
    "sg:city":"Goshen",
    "sg:classifiers":[
        {
            "category":"Professional",
            "subcategory":"Lawyer & Legal Services",
            "type":"Services"
        }
    ],
    "sg:phone":"+1 845 294 1464",
    "sg:postcode":"10924",
    "sg:province":"NY",
    "sg:tags":[
        "litigation"
    ],
    "sg:website":"www.ramettalawtax.com",
    "wof:name":"Rametta & Rametta",
    "wof:placetype":"venue"
},
  "geometry": {"coordinates":[-74.336348,41.398136],"type":"Point"}
}