{
  "type": "Feature",
  "properties": {
    "addr:full":"448 White Spruce Blvd Rochester NY 14623",
    "addr:housenumber":"448",
    "addr:postcode":"14623",
    "addr:street":"White Spruce Blvd",
    "iso:country":"US",
    "sg:address":"448 White Spruce Blvd",
    "sg:city":"Rochester",
    "sg:classifiers":[
        {
            "category":"Health Services",
            "subcategory":"Doctor",
            "type":"Services"
        },
        {
            "category":"Health Services",
            "subcategory":"Clinic",
            "type":"Services"
        }
    ],
    "sg:phone":"+1 585 424 5680",
    "sg:postcode":"14623",
    "sg:province":"NY",
    "sg:tags":[
        "psychological",
        "physician",
        "psychologist",
        "surgeons",
        "psychiatry"
    ],
    "wof:name":"Law Enfrcment Psychlgcal Assoc",
    "wof:placetype":"venue"
},
  "geometry": {"coordinates":[-77.61693200000001,43.102854],"type":"Point"}
}