{
  "type": "Feature",
  "properties": {
    "iso:country":"US",
    "sg:address":"3706 82nd St",
    "sg:city":"Jackson Heights",
    "sg:classifiers":[
        {
            "category":"Shopping",
            "subcategory":"Mobile Phones",
            "type":"Retail Goods"
        }
    ],
    "sg:phone":"+1 718 565 2300",
    "sg:postcode":"11372",
    "sg:province":"NY",
    "wof:name":"Gj Wireless",
    "wof:placetype":"venue"
},
  "geometry": {"coordinates":[-73.88448,40.749674],"type":"Point"}
}