{
  "type": "Feature",
  "properties": {
    "addr:full":"650 W End Ave New York NY 10025",
    "addr:housenumber":"650",
    "addr:postcode":"10025",
    "addr:street":"W End Ave",
    "iso:country":"US",
    "sg:address":"650 W End Ave",
    "sg:city":"New York",
    "sg:classifiers":[
        {
            "category":"Social Services",
            "type":"Services"
        }
    ],
    "sg:phone":"+1 212 496 2870",
    "sg:postcode":"10025",
    "sg:province":"NY",
    "sg:tags":[
        "psychologist"
    ],
    "wof:name":"Jill C Herbert",
    "wof:placetype":"venue"
},
  "geometry": {"coordinates":[-73.975239,40.792242],"type":"Point"}
}