{
  "type": "Feature",
  "properties": {
    "iso:country":"US",
    "sg:address":"443 Clement Ave",
    "sg:city":"Elmont",
    "sg:classifiers":[
        {
            "category":"Utilities",
            "type":"Services"
        }
    ],
    "sg:phone":"+1   ",
    "sg:postcode":"11003",
    "sg:province":"NY",
    "sg:tags":[
        "sanitary"
    ],
    "wof:name":"Nocella Enterprises Inc",
    "wof:placetype":"venue"
},
  "geometry": {"coordinates":[-73.686858,40.696626],"type":"Point"}
}