{
  "type": "Feature",
  "properties": {
    "addr:full":"1338 71st St Brooklyn NY 11228",
    "addr:housenumber":"1338",
    "addr:postcode":"11228",
    "addr:street":"71St St",
    "iso:country":"US",
    "sg:address":"1338 71st St",
    "sg:city":"Brooklyn",
    "sg:classifiers":[
        {
            "category":"Building & Trades",
            "subcategory":"Construction",
            "type":"Services"
        }
    ],
    "sg:phone":"+1 718 256 6515",
    "sg:postcode":"11228",
    "sg:province":"NY",
    "sg:tags":[
        "drywall",
        "contractor"
    ],
    "wof:name":"Vitech Construction Inc",
    "wof:placetype":"venue"
},
  "geometry": {"coordinates":[-74.003551,40.621709],"type":"Point"}
}