{
  "type": "Feature",
  "properties": {
    "addr:full":"70 Pine St New York NY 10270",
    "addr:housenumber":"70",
    "addr:postcode":"10270",
    "addr:street":"Pine St",
    "iso:country":"US",
    "sg:address":"70 Pine St",
    "sg:city":"New York",
    "sg:classifiers":[
        {
            "category":"Insurance",
            "subcategory":"Insurance Agent",
            "type":"Services"
        }
    ],
    "sg:phone":"+1 212 770 5002",
    "sg:postcode":"10270",
    "sg:province":"NY",
    "sg:tags":[
        "broker"
    ],
    "wof:name":"C V Starr & Co Inc",
    "wof:placetype":"venue"
},
  "geometry": {"coordinates":[-74.008996,40.706953],"type":"Point"}
}