{
  "type": "Feature",
  "properties": {
    "iso:country":"US",
    "sg:address":"13933 89th Ave",
    "sg:city":"Jamaica",
    "sg:classifiers":[
        {
            "category":"Restaurant",
            "type":"Food & Drink"
        }
    ],
    "sg:menulink":"http://www.allmenus.com/ny/queens/52653-dominicano-internacional-restaurant/menu/",
    "sg:phone":"+1 718 657 3433",
    "sg:postcode":"11435",
    "sg:province":"NY",
    "sg:tags":[
        "dominican"
    ],
    "wof:name":"Dominicano Internacional Restaurant",
    "wof:placetype":"venue"
},
  "geometry": {"coordinates":[-73.813135,40.702649],"type":"Point"}
}