{
  "type": "Feature",
  "properties": {
    "addr:full":"2722 Richmond Ter Staten Island NY 10303",
    "addr:housenumber":"2722",
    "addr:postcode":"10303",
    "addr:street":"Richmond Ter",
    "iso:country":"US",
    "sg:address":"2722 Richmond Ter",
    "sg:city":"Staten Island",
    "sg:classifiers":[
        {
            "category":"Food & Beverages",
            "subcategory":"Groceries & Convenience Stores",
            "type":"Retail Goods"
        }
    ],
    "sg:phone":"+1   ",
    "sg:postcode":"10303",
    "sg:province":"NY",
    "wof:name":"Waterfront Deli",
    "wof:placetype":"venue"
},
  "geometry": {"coordinates":[-74.150732,40.636968],"type":"Point"}
}