{
  "type": "Feature",
  "properties": {
    "iso:country":"US",
    "sg:address":"71 Parkway",
    "sg:city":"Rochester",
    "sg:classifiers":[
        {
            "category":"Social Services",
            "subcategory":"Child Care",
            "type":"Services"
        }
    ],
    "sg:phone":"+1 585 254 6784",
    "sg:postcode":"14608",
    "sg:province":"NY",
    "wof:name":"Edgerton Family Day Care",
    "wof:placetype":"venue"
},
  "geometry": {"coordinates":[-77.632572,43.166739],"type":"Point"}
}