{
  "type": "Feature",
  "properties": {
    "addr:full":"1032 3rd St Rensselaer NY 12144",
    "addr:housenumber":"1032",
    "addr:postcode":"12144",
    "addr:street":"3Rd St",
    "iso:country":"US",
    "sg:address":"1032 3rd St",
    "sg:city":"Rensselaer",
    "sg:classifiers":[
        {
            "category":"Retail",
            "subcategory":"Auto Repair",
            "type":"Services"
        }
    ],
    "sg:phone":"+1   ",
    "sg:postcode":"12144",
    "sg:province":"NY",
    "sg:tags":[
        "automotive"
    ],
    "wof:name":"Genes Pavement Sealing",
    "wof:placetype":"venue"
},
  "geometry": {"coordinates":[-73.73533999999999,42.648349],"type":"Point"}
}