{
  "type": "Feature",
  "properties": {
    "iso:country":"US",
    "sg:address":"3446 Long Beach Rd",
    "sg:city":"Oceanside",
    "sg:classifiers":[
        {
            "category":"Ice Cream",
            "type":"Food & Drink"
        }
    ],
    "sg:phone":"+1 516 766 3685",
    "sg:postcode":"11572",
    "sg:province":"NY",
    "sg:tags":[
        "frozen",
        "yogurt"
    ],
    "wof:name":"Tcby Yogurt",
    "wof:placetype":"venue"
},
  "geometry": {"coordinates":[-73.640602,40.626999],"type":"Point"}
}