{
  "type": "Feature",
  "properties": {
    "addr:full":"55 Grand St Newburgh NY 12550",
    "addr:housenumber":"55",
    "addr:postcode":"12550",
    "addr:street":"Grand St",
    "iso:country":"US",
    "sg:address":"55 Grand St",
    "sg:city":"Newburgh",
    "sg:classifiers":[
        {
            "category":"Real Estate",
            "subcategory":"Developer",
            "type":"Services"
        }
    ],
    "sg:phone":"+1 845 561 5473",
    "sg:postcode":"12550",
    "sg:province":"NY",
    "sg:tags":[
        "cemetery"
    ],
    "wof:name":"Calvary Cemetery",
    "wof:placetype":"venue"
},
  "geometry": {"coordinates":[-74.00963299999999,41.501412],"type":"Point"}
}