{
  "type": "Feature",
  "properties": {
    "addr:full":"250 Smithtown Blvd Nesconset NY 11767",
    "addr:housenumber":"250",
    "addr:postcode":"11767",
    "addr:street":"Smithtown Blvd",
    "iso:country":"US",
    "sg:address":"250 Smithtown Blvd",
    "sg:city":"Nesconset",
    "sg:classifiers":[
        {
            "category":"Banks & Credit Unions",
            "subcategory":"Bank",
            "type":"Services"
        }
    ],
    "sg:phone":"+1 631 360 3700",
    "sg:postcode":"11767",
    "sg:province":"NY",
    "sg:tags":[
        "personal",
        "state",
        "commercial",
        "institution"
    ],
    "sg:website":"www.northforkbank.com",
    "wof:name":"North Fork Bank",
    "wof:placetype":"venue"
},
  "geometry": {"coordinates":[-73.146376,40.83303],"type":"Point"}
}