{
  "type": "Feature",
  "properties": {
    "iso:country":"US",
    "sg:address":"80 Baylis Rd",
    "sg:city":"Melville",
    "sg:classifiers":[
        {
            "category":"Banks & Credit Unions",
            "subcategory":"Bank",
            "type":"Services"
        }
    ],
    "sg:phone":"+1 631 420 4700",
    "sg:postcode":"11747",
    "sg:province":"NY",
    "sg:tags":[
        "card"
    ],
    "wof:name":"First Data",
    "wof:placetype":"venue"
},
  "geometry": {"coordinates":[-73.425191,40.773631],"type":"Point"}
}