{
  "type": "Feature",
  "properties": {
    "addr:full":"361 Neptune Ave West Babylon NY 11704",
    "addr:housenumber":"361",
    "addr:postcode":"11704",
    "addr:street":"Neptune Ave",
    "iso:country":"US",
    "sg:address":"361 Neptune Ave",
    "sg:city":"West Babylon",
    "sg:classifiers":[
        {
            "category":"Manufacturing",
            "subcategory":"Rubber & Plastics",
            "type":"Manufacturing & Wholesale Goods"
        },
        {
            "category":"Insurance",
            "subcategory":"Insurance Agent",
            "type":"Services"
        }
    ],
    "sg:phone":"+1 631 321 4400",
    "sg:postcode":"11704",
    "sg:province":"NY",
    "sg:tags":[
        "product",
        "rotational",
        "molding",
        "industry",
        "supply",
        "equipment"
    ],
    "sg:website":"www.chemtainer.com",
    "wof:name":"Rototron Corp",
    "wof:placetype":"venue"
},
  "geometry": {"coordinates":[-73.33546699999999,40.715895],"type":"Point"}
}