{
  "type": "Feature",
  "properties": {
    "addr:full":"23 Charlemagne Dr Nesconset NY 11767",
    "addr:housenumber":"23",
    "addr:postcode":"11767",
    "addr:street":"Charlemagne Dr",
    "iso:country":"US",
    "sg:address":"23 Charlemagne Dr",
    "sg:city":"Nesconset",
    "sg:classifiers":[
        {
            "category":"Manufacturing",
            "subcategory":"Metals",
            "type":"Manufacturing & Wholesale Goods"
        }
    ],
    "sg:phone":"+1   ",
    "sg:postcode":"11767",
    "sg:province":"NY",
    "sg:tags":[
        "stampings",
        "mfg"
    ],
    "wof:name":"Platebiz",
    "wof:placetype":"venue"
},
  "geometry": {"coordinates":[-73.15011800000001,40.851335],"type":"Point"}
}