{
  "type": "Feature",
  "properties": {
    "addr:full":"185 Saint Marks Pl Staten Island NY 10301",
    "addr:housenumber":"185",
    "addr:postcode":"10301",
    "addr:street":"Saint Marks Pl",
    "iso:country":"US",
    "sg:address":"185 Saint Marks Pl",
    "sg:city":"Staten Island",
    "sg:classifiers":[
        {
            "category":"Real Estate",
            "subcategory":"Real Estate Services",
            "type":"Services"
        }
    ],
    "sg:phone":"+1 718 442 3631",
    "sg:postcode":"10301",
    "sg:province":"NY",
    "sg:tags":[
        "management",
        "property"
    ],
    "wof:name":"Castleton Park Houses",
    "wof:placetype":"venue"
},
  "geometry": {"coordinates":[-74.080803,40.645401],"type":"Point"}
}