{
  "type": "Feature",
  "properties": {
    "addr:full":"139 US Hwy 9w Haverstraw NY 10927",
    "addr:housenumber":"139",
    "addr:postcode":"10927",
    "addr:street":"Us Hwy 9W",
    "iso:country":"US",
    "sg:address":"139 US Hwy 9w",
    "sg:city":"Haverstraw",
    "sg:classifiers":[
        {
            "category":"Freight",
            "type":"Transportation"
        }
    ],
    "sg:phone":"+1 845 429 0639",
    "sg:postcode":"10927",
    "sg:province":"NY",
    "sg:tags":[
        "trucking"
    ],
    "wof:name":"Mat Enterprises Of NY",
    "wof:placetype":"venue"
},
  "geometry": {"coordinates":[-73.959498,41.186444],"type":"Point"}
}