{
  "type": "Feature",
  "properties": {
    "addr:full":"368 Eastern Pkwy Brooklyn NY 11225",
    "addr:housenumber":"368",
    "addr:postcode":"11225",
    "addr:street":"Eastern Pkwy",
    "iso:country":"US",
    "sg:address":"368 Eastern Pkwy",
    "sg:city":"Brooklyn",
    "sg:classifiers":[
        {
            "category":"Shopping",
            "subcategory":"Music",
            "type":"Retail Goods"
        }
    ],
    "sg:phone":"+1   ",
    "sg:postcode":"11225",
    "sg:province":"NY",
    "wof:name":"Hagios Records",
    "wof:placetype":"venue"
},
  "geometry": {"coordinates":[-73.956498,40.670366],"type":"Point"}
}