{
  "type": "Feature",
  "properties": {
    "iso:country":"US",
    "sg:address":"29 N Station Plz",
    "sg:city":"Great Neck",
    "sg:classifiers":[
        {
            "category":"Restaurant",
            "type":"Food & Drink"
        }
    ],
    "sg:phone":"+1   ",
    "sg:postcode":"11021",
    "sg:province":"NY",
    "sg:tags":[
        "pizzeria"
    ],
    "wof:name":"Francescas Pizzeria Great Neck",
    "wof:placetype":"venue"
},
  "geometry": {"coordinates":[-73.726562,40.787539],"type":"Point"}
}