{
  "type": "Feature",
  "properties": {
    "addr:full":"2040 Deer Park Ave Deer Park NY 11729",
    "addr:housenumber":"2040",
    "addr:postcode":"11729",
    "addr:street":"Deer Park Ave",
    "iso:country":"US",
    "sg:address":"2040 Deer Park Ave",
    "sg:city":"Deer Park",
    "sg:classifiers":[
        {
            "category":"Professional",
            "type":"Services"
        }
    ],
    "sg:phone":"+1 631 586 3257",
    "sg:postcode":"11729",
    "sg:province":"NY",
    "sg:tags":[
        "establishment"
    ],
    "wof:name":"Platinum Group Direct Inc",
    "wof:placetype":"venue"
},
  "geometry": {"coordinates":[-73.332026,40.768239],"type":"Point"}
}