{
  "type": "Feature",
  "properties": {
    "addr:full":"98 Greenpoint Ave Brooklyn NY 11222",
    "addr:housenumber":"98",
    "addr:postcode":"11222",
    "addr:street":"Greenpoint Ave",
    "iso:country":"US",
    "sg:address":"98 Greenpoint Ave",
    "sg:city":"Brooklyn",
    "sg:classifiers":[
        {
            "category":"Wholesale",
            "subcategory":"Groceries",
            "type":"Manufacturing & Wholesale Goods"
        }
    ],
    "sg:phone":"+1 718 383 0300",
    "sg:postcode":"11222",
    "sg:province":"NY",
    "sg:tags":[
        "frozen",
        "food"
    ],
    "wof:name":"Alfa International Inc",
    "wof:placetype":"venue"
},
  "geometry": {"coordinates":[-73.95464699999999,40.730071],"type":"Point"}
}