{
  "type": "Feature",
  "properties": {
    "addr:full":"949 Rabbit Ear Pass Victor NY 14564",
    "addr:housenumber":"949",
    "addr:postcode":"14564",
    "addr:street":"Rabbit Ear Pass",
    "iso:country":"US",
    "sg:address":"949 Rabbit Ear Pass",
    "sg:city":"Victor",
    "sg:classifiers":[
        {
            "category":"Real Estate",
            "subcategory":"Real Estate Operator",
            "type":"Services"
        }
    ],
    "sg:phone":"+1 585 305 8756",
    "sg:postcode":"14564",
    "sg:province":"NY",
    "sg:tags":[
        "building",
        "nonresidential"
    ],
    "wof:name":"Rodgers Properties",
    "wof:placetype":"venue"
},
  "geometry": {"coordinates":[-77.45272300000001,42.990368],"type":"Point"}
}