{
  "type": "Feature",
  "properties": {
    "addr:full":"111 N Park Ave Rockville Centre NY 11570",
    "addr:housenumber":"111",
    "addr:postcode":"11570",
    "addr:street":"N Park Ave",
    "iso:country":"US",
    "sg:address":"111 N Park Ave",
    "sg:city":"Rockville Centre",
    "sg:classifiers":[
        {
            "category":"Health Services",
            "subcategory":"Doctor",
            "type":"Services"
        }
    ],
    "sg:phone":"+1 516 764 4545",
    "sg:postcode":"11570",
    "sg:province":"NY",
    "sg:tags":[
        "medical"
    ],
    "wof:name":"Linwood Richard A MD",
    "wof:placetype":"venue"
},
  "geometry": {"coordinates":[-73.644842,40.660147],"type":"Point"}
}