{
  "type": "Feature",
  "properties": {
    "addr:full":"1000 Northern Blvd Ste 140 Great Neck NY 11021",
    "addr:housenumber":"1000",
    "addr:postcode":"11021",
    "addr:street":"Northern Blvd Ste 140",
    "iso:country":"US",
    "sg:address":"1000 Northern Blvd Ste 140",
    "sg:city":"Great Neck",
    "sg:classifiers":[
        {
            "category":"Health Services",
            "subcategory":"Doctor",
            "type":"Services"
        }
    ],
    "sg:phone":"+1 516 466 2340",
    "sg:postcode":"11021",
    "sg:province":"NY",
    "wof:name":"Nassau Gastroenterology",
    "wof:placetype":"venue"
},
  "geometry": {"coordinates":[-73.70590199999999,40.786999],"type":"Point"}
}