{
  "type": "Feature",
  "properties": {
    "addr:full":"2114 Brown St Brooklyn NY 11229",
    "addr:housenumber":"2114",
    "addr:postcode":"11229",
    "addr:street":"Brown St",
    "iso:country":"US",
    "sg:address":"2114 Brown St",
    "sg:city":"Brooklyn",
    "sg:classifiers":[
        {
            "category":"Organizations",
            "subcategory":"Religious Organization",
            "type":"Services"
        },
        {
            "category":"Social Services",
            "type":"Services"
        }
    ],
    "sg:phone":"+1 718 332 4120",
    "sg:postcode":"11229",
    "sg:province":"NY",
    "sg:tags":[
        "welfare"
    ],
    "wof:name":"Young Israel of Bedford Bay",
    "wof:placetype":"venue"
},
  "geometry": {"coordinates":[-73.93968,40.598804],"type":"Point"}
}