{
  "type": "Feature",
  "properties": {
    "addr:full":"4 Pinedale Rd Hauppauge NY 11788",
    "addr:housenumber":"4",
    "addr:postcode":"11788",
    "addr:street":"Pinedale Rd",
    "iso:country":"US",
    "sg:address":"4 Pinedale Rd",
    "sg:city":"Hauppauge",
    "sg:classifiers":[
        {
            "category":"Building & Trades",
            "subcategory":"Landscaping Services",
            "type":"Services"
        },
        {
            "category":"Wholesale",
            "subcategory":"Machinery & Supplies",
            "type":"Manufacturing & Wholesale Goods"
        },
        {
            "category":"Professional",
            "subcategory":"Business Services",
            "type":"Services"
        }
    ],
    "sg:phone":"+1 631 360 3305",
    "sg:postcode":"11788",
    "sg:province":"NY",
    "sg:tags":[
        "lawn",
        "installation",
        "consultant",
        "sprinklers-garden",
        "irrigation",
        "system",
        "equipment"
    ],
    "wof:name":"Waterways Irrigation Inc",
    "wof:placetype":"venue"
},
  "geometry": {"coordinates":[-73.18938799999999,40.816554],"type":"Point"}
}