{
  "type": "Feature",
  "properties": {
    "iso:country":"US",
    "sg:address":"59 Prospect Ave",
    "sg:city":"Brentwood",
    "sg:classifiers":[
        {
            "category":"Freight",
            "type":"Transportation"
        }
    ],
    "sg:phone":"+1 631 273 7166",
    "sg:postcode":"11717",
    "sg:province":"NY",
    "wof:name":"D & J Transportation Network",
    "wof:placetype":"venue"
},
  "geometry": {"coordinates":[-73.227374,40.793011],"type":"Point"}
}