{
  "type": "Feature",
  "properties": {
    "iso:country":"US",
    "sg:address":"199 N Middletown Rd",
    "sg:city":"Nanuet",
    "sg:classifiers":[
        {
            "category":"Health Services",
            "subcategory":"Nursing And Care Facility",
            "type":"Services"
        }
    ],
    "sg:phone":"+1 845 623 3904",
    "sg:postcode":"10954",
    "sg:province":"NY",
    "sg:tags":[
        "skilled"
    ],
    "wof:name":"Northern Manor Multicare Ctr",
    "wof:placetype":"venue"
},
  "geometry": {"coordinates":[-74.010914,41.112103],"type":"Point"}
}