{
  "type": "Feature",
  "properties": {
    "iso:country":"US",
    "sg:address":"40 Willow Dr",
    "sg:city":"Buffalo",
    "sg:classifiers":[
        {
            "category":"Building & Trades",
            "subcategory":"Construction",
            "type":"Services"
        }
    ],
    "sg:phone":"+1 716 675 5567",
    "sg:postcode":"14224",
    "sg:province":"NY",
    "sg:tags":[
        "house"
    ],
    "wof:name":"Carl Bueme Construction",
    "wof:placetype":"venue"
},
  "geometry": {"coordinates":[-78.772508,42.838417],"type":"Point"}
}