{
  "type": "Feature",
  "properties": {
    "iso:country":"US",
    "sg:address":"45 W 34th St",
    "sg:city":"New York",
    "sg:classifiers":[
        {
            "category":"Health Services",
            "subcategory":"Health Practitioner",
            "type":"Services"
        }
    ],
    "sg:phone":"+1 212 268 8302",
    "sg:postcode":"10001",
    "sg:province":"NY",
    "sg:tags":[
        "acupuncture"
    ],
    "wof:name":"Charles Deng Acupuncture",
    "wof:placetype":"venue"
},
  "geometry": {"coordinates":[-73.986649,40.749239],"type":"Point"}
}