{
  "type": "Feature",
  "properties": {
    "iso:country":"US",
    "sg:address":"550 Orchard Park Rd",
    "sg:city":"Buffalo",
    "sg:classifiers":[
        {
            "category":"Health Services",
            "subcategory":"Doctor",
            "type":"Services"
        }
    ],
    "sg:phone":"+1 716 677 6000",
    "sg:postcode":"14224",
    "sg:province":"NY",
    "wof:name":"Lewis P Jeffrey MD",
    "wof:placetype":"venue"
},
  "geometry": {"coordinates":[-78.77950300000001,42.832199],"type":"Point"}
}