{
  "type": "Feature",
  "properties": {
    "addr:full":"2504 Grand Ave Baldwin NY 11510",
    "addr:housenumber":"2504",
    "addr:postcode":"11510",
    "addr:street":"Grand Ave",
    "iso:country":"US",
    "sg:address":"2504 Grand Ave",
    "sg:city":"Baldwin",
    "sg:classifiers":[
        {
            "category":"Professional",
            "subcategory":"Lawyer & Legal Services",
            "type":"Services"
        }
    ],
    "sg:phone":"+1 516 546 2003",
    "sg:postcode":"11510",
    "sg:province":"NY",
    "sg:tags":[
        "attorney"
    ],
    "wof:name":"Susan B Lyons",
    "wof:placetype":"venue"
},
  "geometry": {"coordinates":[-73.61300199999999,40.649013],"type":"Point"}
}