{
  "type": "Feature",
  "properties": {
    "iso:country":"US",
    "sg:address":"248 Smithtown Blvd Ste 14",
    "sg:city":"Nesconset",
    "sg:classifiers":[
        {
            "category":"Shopping",
            "subcategory":"Florist",
            "type":"Retail Goods"
        }
    ],
    "sg:phone":"+1 631 979 8848",
    "sg:postcode":"11767",
    "sg:province":"NY",
    "sg:website":"www.flowersbytowers.com/",
    "wof:name":"Towers Flowers",
    "wof:placetype":"venue"
},
  "geometry": {"coordinates":[-73.146508,40.833037],"type":"Point"}
}