{
  "type": "Feature",
  "properties": {
    "iso:country":"US",
    "sg:address":"18 Neil Ct",
    "sg:city":"Oceanside",
    "sg:classifiers":[
        {
            "category":"Shopping",
            "subcategory":"Hobbies, Toys, & Games",
            "type":"Retail Goods"
        }
    ],
    "sg:phone":"+1 516 255 1778",
    "sg:postcode":"11572",
    "sg:province":"NY",
    "wof:name":"Paws & Claws Co",
    "wof:placetype":"venue"
},
  "geometry": {"coordinates":[-73.632946,40.623392],"type":"Point"}
}