{
  "type": "Feature",
  "properties": {
    "addr:full":"16710 Crocheron Ave Flushing NY 11358",
    "addr:housenumber":"16710",
    "addr:postcode":"11358",
    "addr:street":"Crocheron Ave",
    "iso:country":"US",
    "sg:address":"16710 Crocheron Ave",
    "sg:city":"Flushing",
    "sg:classifiers":[
        {
            "category":"Personal",
            "type":"Services"
        },
        {
            "category":"Retail",
            "subcategory":"Portrait Studio",
            "type":"Services"
        },
        {
            "category":"Professional",
            "subcategory":"Art Services",
            "type":"Services"
        },
        {
            "category":"Professional",
            "subcategory":"Printing & Photocopies",
            "type":"Services"
        }
    ],
    "sg:phone":"+1 718 939 0296",
    "sg:postcode":"11358",
    "sg:province":"NY",
    "sg:tags":[
        "photographers-portrait",
        "videography",
        "darkroom",
        "rental",
        "photography",
        "wedding",
        "photographers-commercial",
        "photographic"
    ],
    "sg:website":"http://www.infantinophoto.com",
    "wof:name":"Bruce Infantino Photography",
    "wof:placetype":"venue"
},
  "geometry": {"coordinates":[-73.788326,40.764111],"type":"Point"}
}