{
  "type": "Feature",
  "properties": {
    "iso:country":"US",
    "sg:address":"17 Major Rd",
    "sg:city":"Elizaville",
    "sg:classifiers":[
        {
            "category":"Organizations",
            "subcategory":"Professional Association",
            "type":"Services"
        }
    ],
    "sg:phone":"+1 845 756 2231",
    "sg:postcode":"12523",
    "sg:province":"NY",
    "sg:tags":[
        "sales"
    ],
    "wof:name":"Robert Ascoli Assoc",
    "wof:placetype":"venue"
},
  "geometry": {"coordinates":[-73.79855499999999,42.059109],"type":"Point"}
}