{
  "type": "Feature",
  "properties": {
    "addr:full":"199 Old Monticello Rd Liberty NY 12754",
    "addr:housenumber":"199",
    "addr:postcode":"12754",
    "addr:street":"Old Monticello Rd",
    "iso:country":"US",
    "sg:address":"199 Old Monticello Rd",
    "sg:city":"Liberty",
    "sg:classifiers":[
        {
            "category":"Retail",
            "subcategory":"Auto Repair",
            "type":"Services"
        }
    ],
    "sg:phone":"+1 845 295 0548",
    "sg:postcode":"12754",
    "sg:province":"NY",
    "sg:tags":[
        "machine",
        "automobile",
        "shop"
    ],
    "wof:name":"Steve's Machine Shop Svc",
    "wof:placetype":"venue"
},
  "geometry": {"coordinates":[-74.722031,41.761666],"type":"Point"}
}