{
  "type": "Feature",
  "properties": {
    "iso:country":"US",
    "sg:address":"514 Howard St",
    "sg:city":"Buffalo",
    "sg:classifiers":[
        {
            "category":"Bars & Pubs",
            "subcategory":"Nightclub",
            "type":"Food & Drink"
        }
    ],
    "sg:phone":"+1 716 855 8866",
    "sg:postcode":"14206",
    "sg:province":"NY",
    "sg:tags":[
        "nightlife"
    ],
    "wof:name":"Darren's Tavern",
    "wof:placetype":"venue"
},
  "geometry": {"coordinates":[-78.834909,42.883243],"type":"Point"}
}