{
  "type": "Feature",
  "properties": {
    "addr:full":"1727 Pitkin Avenue Brooklyn NY 11212",
    "addr:housenumber":"1727",
    "addr:postcode":"11212",
    "addr:street":"Pitkin Avenue",
    "iso:country":"US",
    "sg:address":"1727 Pitkin Avenue",
    "sg:city":"Brooklyn",
    "sg:classifiers":[
        {
            "category":"Health Services",
            "subcategory":"Dentist",
            "type":"Services"
        }
    ],
    "sg:phone":"+1 718 566 1305",
    "sg:postcode":"11212",
    "sg:province":"NY",
    "wof:name":"Ipektchi Vahid DMD",
    "wof:placetype":"venue"
},
  "geometry": {"coordinates":[-73.909408,40.669998],"type":"Point"}
}