{
  "type": "Feature",
  "properties": {
    "iso:country":"US",
    "sg:address":"6735 Pittsford Palmyra Rd",
    "sg:city":"Fairport",
    "sg:classifiers":[
        {
            "category":"Retail",
            "subcategory":"Veterinary Services",
            "type":"Services"
        }
    ],
    "sg:phone":"+1 585 223 0940",
    "sg:postcode":"14450",
    "sg:province":"NY",
    "wof:name":"Fairview Veterinary Hospital",
    "wof:placetype":"venue"
},
  "geometry": {"coordinates":[-77.44084599999999,43.069155],"type":"Point"}
}