{
  "type": "Feature",
  "properties": {
    "addr:full":"122 Meserole Ave Brooklyn NY 11222",
    "addr:housenumber":"122",
    "addr:postcode":"11222",
    "addr:street":"Meserole Ave",
    "iso:country":"US",
    "sg:address":"122 Meserole Ave",
    "sg:city":"Brooklyn",
    "sg:classifiers":[
        {
            "category":"Health Services",
            "subcategory":"Doctor",
            "type":"Services"
        }
    ],
    "sg:phone":"+1 718 349 6434",
    "sg:postcode":"11222",
    "sg:province":"NY",
    "sg:tags":[
        "medical"
    ],
    "wof:name":"Pustelak Urszula MD",
    "wof:placetype":"venue"
},
  "geometry": {"coordinates":[-73.9515,40.727402],"type":"Point"}
}