{
  "type": "Feature",
  "properties": {
    "iso:country":"US",
    "sg:address":"4217 Church Avenue",
    "sg:city":"Brooklyn",
    "sg:classifiers":[
        {
            "category":"Shopping",
            "subcategory":"Books",
            "type":"Retail Goods"
        }
    ],
    "sg:phone":"+1 718 282 7565",
    "sg:postcode":"11203",
    "sg:province":"NY",
    "sg:tags":[
        "bookstore"
    ],
    "wof:name":"Bethleham Christian Bookstore",
    "wof:placetype":"venue"
},
  "geometry": {"coordinates":[-73.937547,40.651505],"type":"Point"}
}