{
  "type": "Feature",
  "properties": {
    "iso:country":"US",
    "sg:address":"615 Washington St",
    "sg:city":"Manhattan",
    "sg:classifiers":[
        {
            "category":"Restaurant",
            "type":"Food & Drink"
        }
    ],
    "sg:postcode":"10014",
    "sg:province":"NY",
    "wof:name":"Brimstone",
    "wof:placetype":"venue"
},
  "geometry": {"coordinates":[-74.008915,40.731108],"type":"Point"}
}