{
  "type": "Feature",
  "properties": {
    "iso:country":"US",
    "sg:address":"253 Broadway",
    "sg:city":"Staten Island",
    "sg:classifiers":[
        {
            "category":"Real Estate",
            "subcategory":"Real Estate Agent",
            "type":"Services"
        }
    ],
    "sg:phone":"+1 718 981 3301",
    "sg:postcode":"10310",
    "sg:province":"NY",
    "wof:name":"Jolicoeur Realty",
    "wof:placetype":"venue"
},
  "geometry": {"coordinates":[-74.117135,40.63464],"type":"Point"}
}