{
  "type": "Feature",
  "properties": {
    "addr:full":"80 E 11th St Ste 234 New York NY 10003",
    "addr:housenumber":"80;234",
    "addr:postcode":"10003",
    "addr:street":"E 11Th St Ste",
    "iso:country":"US",
    "sg:address":"80 E 11th St Ste 234",
    "sg:city":"New York",
    "sg:classifiers":[
        {
            "category":"Health Services",
            "subcategory":"Clinic",
            "type":"Services"
        }
    ],
    "sg:phone":"+1 917 847 4217",
    "sg:postcode":"10003",
    "sg:province":"NY",
    "sg:tags":[
        "counseling",
        "mental"
    ],
    "sg:website":"www.drbrustein.com/",
    "wof:name":"Michael Brustein, PsyD",
    "wof:placetype":"venue"
},
  "geometry": {"coordinates":[-73.991756,40.7326],"type":"Point"}
}