{
  "type": "Feature",
  "properties": {
    "addr:full":"4809 Avenue N Brooklyn NY 11234",
    "addr:housenumber":"4809",
    "addr:postcode":"11234",
    "addr:street":"Avenue N",
    "iso:country":"US",
    "sg:address":"4809 Avenue N",
    "sg:city":"Brooklyn",
    "sg:classifiers":[
        {
            "category":"Wholesale",
            "subcategory":"Medical Equipment & Supplies",
            "type":"Manufacturing & Wholesale Goods"
        }
    ],
    "sg:phone":"+1 718 252 4120",
    "sg:postcode":"11234",
    "sg:province":"NY",
    "sg:tags":[
        "physician",
        "surgeon"
    ],
    "wof:name":"Alba International Trading",
    "wof:placetype":"venue"
},
  "geometry": {"coordinates":[-73.927947,40.618958],"type":"Point"}
}