{
  "type": "Feature",
  "properties": {
    "iso:country":"US",
    "sg:address":"411 Vanderbilt Ave",
    "sg:city":"Brooklyn",
    "sg:classifiers":[
        {
            "category":"Retail",
            "subcategory":"Veterinary Services",
            "type":"Services"
        }
    ],
    "sg:phone":"+1 718 638 2276",
    "sg:postcode":"11238",
    "sg:province":"NY",
    "sg:tags":[
        "veterinarian"
    ],
    "wof:name":"Alan Burns, MD",
    "wof:placetype":"venue"
},
  "geometry": {"coordinates":[-73.968243,40.685911],"type":"Point"}
}