{
  "type": "Feature",
  "properties": {
    "iso:country":"US",
    "sg:address":"26 Atlantic Ave",
    "sg:city":"Lynbrook",
    "sg:classifiers":[
        {
            "category":"Professional",
            "type":"Services"
        }
    ],
    "sg:phone":"+1 516 561 8202",
    "sg:postcode":"11563",
    "sg:province":"NY",
    "sg:tags":[
        "establishment"
    ],
    "wof:name":"Strapless Dress LTD",
    "wof:placetype":"venue"
},
  "geometry": {"coordinates":[-73.67169699999999,40.656284],"type":"Point"}
}