{
  "type": "Feature",
  "properties": {
    "iso:country":"US",
    "sg:address":"8 Cottage Gdns",
    "sg:city":"Yonkers",
    "sg:classifiers":[
        {
            "category":"Real Estate",
            "subcategory":"Real Estate Agent",
            "type":"Services"
        }
    ],
    "sg:phone":"+1 914 376 2471",
    "sg:postcode":"10701",
    "sg:province":"NY",
    "sg:tags":[
        "authorities",
        "housing"
    ],
    "wof:name":"Municipal Housing Authority",
    "wof:placetype":"venue"
},
  "geometry": {"coordinates":[-73.896045,40.941693],"type":"Point"}
}