{
  "type": "Feature",
  "properties": {
    "iso:country":"US",
    "sg:address":"111 Berrian Rd",
    "sg:city":"New Rochelle",
    "sg:classifiers":[
        {
            "category":"Education",
            "subcategory":"Special Training",
            "type":"Public Place"
        }
    ],
    "sg:phone":"+1   ",
    "sg:postcode":"10804",
    "sg:province":"NY",
    "wof:name":"New Rochelle Learning Center",
    "wof:placetype":"venue"
},
  "geometry": {"coordinates":[-73.80159999999999,40.939284],"type":"Point"}
}