{
  "type": "Feature",
  "properties": {
    "addr:full":"128 W Lincoln Ave Mt Vernon NY 10550",
    "addr:housenumber":"128",
    "addr:postcode":"10550",
    "addr:street":"W Lincoln Ave",
    "iso:country":"US",
    "sg:address":"128 W Lincoln Ave",
    "sg:city":"Mt Vernon",
    "sg:classifiers":[
        {
            "category":"Retail",
            "subcategory":"Laundry & Dry Cleaning",
            "type":"Services"
        }
    ],
    "sg:phone":"+1 914 776 2269",
    "sg:postcode":"10550",
    "sg:province":"NY",
    "sg:tags":[
        "cleaners",
        "rug",
        "carpet"
    ],
    "wof:name":"Raytone Carpet & Upholstery",
    "wof:placetype":"venue"
},
  "geometry": {"coordinates":[-73.84223,40.916351],"type":"Point"}
}