{
  "type": "Feature",
  "properties": {
    "addr:full":"235 Elizabeth St New York NY 10012",
    "addr:housenumber":"235",
    "addr:postcode":"10012",
    "addr:street":"Elizabeth St",
    "iso:country":"US",
    "sg:address":"235 Elizabeth St",
    "sg:city":"New York",
    "sg:classifiers":[
        {
            "category":"Shopping",
            "subcategory":"Gifts & Souvenirs",
            "type":"Retail Goods"
        }
    ],
    "sg:phone":"+1   ",
    "sg:postcode":"10012",
    "sg:province":"NY",
    "sg:tags":[
        "shop"
    ],
    "wof:name":"Daily 235",
    "wof:placetype":"venue"
},
  "geometry": {"coordinates":[-73.993612,40.724185],"type":"Point"}
}