{
  "type": "Feature",
  "properties": {
    "iso:country":"US",
    "sg:address":"260 Church St",
    "sg:city":"White Plains",
    "sg:classifiers":[
        {
            "category":"Building & Trades",
            "subcategory":"Landscaping Services",
            "type":"Services"
        }
    ],
    "sg:phone":"+1 914 949 8662",
    "sg:postcode":"10603",
    "sg:province":"NY",
    "sg:tags":[
        "landscape",
        "contractor"
    ],
    "wof:name":"Tanglewood Gardens Owners's",
    "wof:placetype":"venue"
},
  "geometry": {"coordinates":[-73.770295,41.039881],"type":"Point"}
}