{
  "type": "Feature",
  "properties": {
    "iso:country":"US",
    "sg:address":"2 Stoutenburgh Dr",
    "sg:city":"Hyde Park",
    "sg:classifiers":[
        {
            "category":"Building & Trades",
            "subcategory":"Construction",
            "type":"Services"
        }
    ],
    "sg:phone":"+1 845 229 2231",
    "sg:postcode":"12538",
    "sg:province":"NY",
    "sg:tags":[
        "woodworking",
        "carpentry",
        "contractor",
        "machinery",
        "mfg"
    ],
    "wof:name":"Hulls Cabinet Shop",
    "wof:placetype":"venue"
},
  "geometry": {"coordinates":[-73.925854,41.794084],"type":"Point"}
}