{
  "type": "Feature",
  "properties": {
    "addr:full":"544 Main St. Beacon NY 12508",
    "addr:housenumber":"544",
    "addr:postcode":"12508",
    "addr:street":"Main St.",
    "iso:country":"US",
    "sg:address":"544 Main St.",
    "sg:city":"Beacon",
    "sg:classifiers":[
        {
            "category":"Professional",
            "type":"Services"
        }
    ],
    "sg:phone":"+1 914 522 4736",
    "sg:postcode":"12508",
    "sg:province":"NY",
    "sg:website":"www,robpennerphotography.com",
    "wof:name":"Rob Penner Photography",
    "wof:placetype":"venue"
},
  "geometry": {"coordinates":[-73.963148,41.50334],"type":"Point"}
}