{
  "type": "Feature",
  "properties": {
    "addr:full":"24 Williams St Granville NY 12832",
    "addr:housenumber":"24",
    "addr:postcode":"12832",
    "addr:street":"Williams St",
    "iso:country":"US",
    "sg:address":"24 Williams St",
    "sg:city":"Granville",
    "sg:classifiers":[
        {
            "category":"Building & Trades",
            "subcategory":"Plumbing",
            "type":"Services"
        }
    ],
    "sg:phone":"+1 518 642 9435",
    "sg:postcode":"12832",
    "sg:province":"NY",
    "sg:tags":[
        "plumbing",
        "contractor"
    ],
    "wof:name":"D & N Plumbing & Heating",
    "wof:placetype":"venue"
},
  "geometry": {"coordinates":[-73.27059199999999,43.403063],"type":"Point"}
}