{
  "type": "Feature",
  "properties": {
    "iso:country":"US",
    "sg:address":"4 Sandstone Ln",
    "sg:city":"Stony Brook",
    "sg:classifiers":[
        {
            "category":"Professional",
            "subcategory":"Engineering",
            "type":"Services"
        }
    ],
    "sg:phone":"+1   ",
    "sg:postcode":"11790",
    "sg:province":"NY",
    "wof:name":"Island Permit Service",
    "wof:placetype":"venue"
},
  "geometry": {"coordinates":[-73.103517,40.898467],"type":"Point"}
}