{
  "type": "Feature",
  "properties": {
    "addr:full":"135 N Park Ave Rockville Centre NY 11570",
    "addr:housenumber":"135",
    "addr:postcode":"11570",
    "addr:street":"N Park Ave",
    "iso:country":"US",
    "sg:address":"135 N Park Ave",
    "sg:city":"Rockville Centre",
    "sg:classifiers":[
        {
            "category":"Personal",
            "type":"Services"
        },
        {
            "category":"Retail",
            "subcategory":"Laundry & Dry Cleaning",
            "type":"Services"
        }
    ],
    "sg:phone":"+1 516 678 1466",
    "sg:postcode":"11570",
    "sg:province":"NY",
    "sg:tags":[
        "sewing",
        "alteration"
    ],
    "wof:name":"Rave Cleaners",
    "wof:placetype":"venue"
},
  "geometry": {"coordinates":[-73.644997,40.661098],"type":"Point"}
}