{
  "type": "Feature",
  "properties": {
    "iso:country":"US",
    "sg:address":"4000 Park Ave",
    "sg:city":"Bronx",
    "sg:classifiers":[
        {
            "category":"Manufacturing",
            "subcategory":"Metals",
            "type":"Manufacturing & Wholesale Goods"
        },
        {
            "category":"Home & Garden",
            "subcategory":"Building Materials",
            "type":"Retail Goods"
        }
    ],
    "sg:phone":"+1 718 901 0001",
    "sg:postcode":"10457",
    "sg:province":"NY",
    "sg:tags":[
        "manufacture",
        "wooden",
        "door",
        "fireproof"
    ],
    "wof:name":"Ace Fire Door Corp",
    "wof:placetype":"venue"
},
  "geometry": {"coordinates":[-73.901914,40.842468],"type":"Point"}
}