{
  "type": "Feature",
  "properties": {
    "addr:full":"31 River View Dr Rochester NY 14623",
    "addr:housenumber":"31",
    "addr:postcode":"14623",
    "addr:street":"River View Dr",
    "iso:country":"US",
    "sg:address":"31 River View Dr",
    "sg:city":"Rochester",
    "sg:classifiers":[
        {
            "category":"Building & Trades",
            "subcategory":"Construction",
            "type":"Services"
        }
    ],
    "sg:phone":"+1 585 232 8286",
    "sg:postcode":"14623",
    "sg:province":"NY",
    "sg:tags":[
        "woodworker"
    ],
    "sg:website":"www.scottgrove.com",
    "wof:name":"Concept Grove Inc",
    "wof:placetype":"venue"
},
  "geometry": {"coordinates":[-77.690147,43.079586],"type":"Point"}
}