{
  "type": "Feature",
  "properties": {
    "iso:country":"US",
    "sg:address":"128 Syracuse Ave",
    "sg:city":"Medford",
    "sg:classifiers":[
        {
            "category":"Wholesale",
            "subcategory":"Groceries",
            "type":"Manufacturing & Wholesale Goods"
        }
    ],
    "sg:phone":"+1 631 289 2370",
    "sg:postcode":"11763",
    "sg:province":"NY",
    "wof:name":"G Patanjo Distributing Company",
    "wof:placetype":"venue"
},
  "geometry": {"coordinates":[-73.009317,40.805565],"type":"Point"}
}