{
  "type": "Feature",
  "properties": {
    "addr:full":"11920 192nd Street Saint Albans NY 11412",
    "addr:housenumber":"11920",
    "addr:postcode":"11412",
    "addr:street":"192Nd Street",
    "iso:country":"US",
    "sg:address":"11920 192nd Street",
    "sg:city":"Saint Albans",
    "sg:classifiers":[
        {
            "category":"Building & Trades",
            "subcategory":"Construction",
            "type":"Services"
        }
    ],
    "sg:phone":"+1 718 977 1710",
    "sg:postcode":"11412",
    "sg:province":"NY",
    "sg:tags":[
        "contractor"
    ],
    "wof:name":"Sunrise Maintenance of Ny",
    "wof:placetype":"venue"
},
  "geometry": {"coordinates":[-73.757946,40.688948],"type":"Point"}
}