{
  "type": "Feature",
  "properties": {
    "addr:full":"231 E 34th Street New York NY 10016",
    "addr:housenumber":"231",
    "addr:postcode":"10016",
    "addr:street":"E 34Th Street",
    "iso:country":"US",
    "sg:address":"231 E 34th Street",
    "sg:city":"New York",
    "sg:classifiers":[
        {
            "category":"Retail",
            "subcategory":"Laundry & Dry Cleaning",
            "type":"Services"
        }
    ],
    "sg:phone":"+1 212 683 1386",
    "sg:postcode":"10016",
    "sg:province":"NY",
    "wof:name":"New Kips Bay Cleaners",
    "wof:placetype":"venue"
},
  "geometry": {"coordinates":[-73.97699900000001,40.74527],"type":"Point"}
}