{
  "type": "Feature",
  "properties": {
    "iso:country":"US",
    "sg:address":"7545 Moccasin Path",
    "sg:city":"Liverpool",
    "sg:classifiers":[
        {
            "category":"Professional",
            "type":"Services"
        }
    ],
    "sg:phone":"+1 315 247 1897",
    "sg:postcode":"13090",
    "sg:province":"NY",
    "wof:name":"AGB Express Svc",
    "wof:placetype":"venue"
},
  "geometry": {"coordinates":[-76.23538000000001,43.134242],"type":"Point"}
}