{
  "type": "Feature",
  "properties": {
    "iso:country":"US",
    "sg:address":"5 Co Rd 9",
    "sg:city":"Hopewell Jct",
    "sg:classifiers":[
        {
            "category":"Health Services",
            "subcategory":"Chiropractor",
            "type":"Services"
        }
    ],
    "sg:phone":"+1 845 226 8229",
    "sg:postcode":"12533",
    "sg:province":"NY",
    "wof:name":"Dutchess Healing Arts Ctr",
    "wof:placetype":"venue"
},
  "geometry": {"coordinates":[-73.692848,41.632009],"type":"Point"}
}