{
  "type": "Feature",
  "properties": {
    "iso:country":"US",
    "sg:address":"84 Brothers Rd",
    "sg:city":"Potsdam",
    "sg:classifiers":[
        {
            "category":"Building & Trades",
            "subcategory":"Electrical",
            "type":"Services"
        }
    ],
    "sg:phone":"+1 315 265 5920",
    "sg:postcode":"13676",
    "sg:province":"NY",
    "sg:tags":[
        "electrical",
        "contractor"
    ],
    "wof:name":"Electrical Connection",
    "wof:placetype":"venue"
},
  "geometry": {"coordinates":[-74.90120400000001,44.665198],"type":"Point"}
}