{
  "type": "Feature",
  "properties": {
    "addr:full":"415 E 52 St New York NY 10022",
    "addr:housenumber":"415;52",
    "addr:postcode":"10022",
    "addr:street":"E;St",
    "iso:country":"US",
    "sg:address":"415 E 52 St",
    "sg:city":"New York",
    "sg:classifiers":[
        {
            "category":"Retail",
            "subcategory":"Auto Repair",
            "type":"Services"
        }
    ],
    "sg:phone":"+1 212 792 0776",
    "sg:postcode":"10022",
    "sg:province":"NY",
    "sg:tags":[
        "wrecker"
    ],
    "wof:name":"International Marble",
    "wof:placetype":"venue"
},
  "geometry": {"coordinates":[-73.964207,40.754852],"type":"Point"}
}