{
  "type": "Feature",
  "properties": {
    "iso:country":"US",
    "sg:address":"100 Riverdale Ave",
    "sg:city":"Yonkers",
    "sg:classifiers":[
        {
            "category":"Organizations",
            "subcategory":"Religious Organization",
            "type":"Services"
        }
    ],
    "sg:phone":"+1 914 968 7402",
    "sg:postcode":"10701",
    "sg:province":"NY",
    "sg:tags":[
        "clergy"
    ],
    "wof:name":"James Wilkins",
    "wof:placetype":"venue"
},
  "geometry": {"coordinates":[-73.900728,40.929185],"type":"Point"}
}