{
  "type": "Feature",
  "properties": {
    "iso:country":"US",
    "sg:address":"20 Dearborn Ave",
    "sg:city":"Patchogue",
    "sg:classifiers":[
        {
            "category":"Autos & Motor Vehicles",
            "subcategory":"Automobile Sales",
            "type":"Retail Goods"
        }
    ],
    "sg:phone":"+1 631 654 3311",
    "sg:postcode":"11772",
    "sg:province":"NY",
    "sg:tags":[
        "limo"
    ],
    "wof:name":"A B C Limousine Svce",
    "wof:placetype":"venue"
},
  "geometry": {"coordinates":[-73.03220399999999,40.7808],"type":"Point"}
}