{
  "type": "Feature",
  "properties": {
    "addr:full":"1720 Lakeville Rd New Hyde Park NY 11040",
    "addr:housenumber":"1720",
    "addr:postcode":"11040",
    "addr:street":"Lakeville Rd",
    "iso:country":"US",
    "sg:address":"1720 Lakeville Rd",
    "sg:city":"New Hyde Park",
    "sg:classifiers":[
        {
            "category":"Shopping",
            "subcategory":"Shoes",
            "type":"Retail Goods"
        }
    ],
    "sg:phone":"+1 516 352 6846",
    "sg:postcode":"11040",
    "sg:province":"NY",
    "sg:tags":[
        "store"
    ],
    "sg:website":"www.martysshoes.com",
    "wof:name":"Marty's Shoes Inc",
    "wof:placetype":"venue"
},
  "geometry": {"coordinates":[-73.69259599999999,40.7439],"type":"Point"}
}