{
  "type": "Feature",
  "properties": {
    "iso:country":"US",
    "sg:address":"357 Aviation Rd",
    "sg:city":"Queensbury",
    "sg:classifiers":[
        {
            "category":"Organizations",
            "subcategory":"Religious Organization",
            "type":"Services"
        }
    ],
    "sg:phone":"+1   ",
    "sg:postcode":"12804",
    "sg:province":"NY",
    "wof:name":"Queensbury Church Of Christ",
    "wof:placetype":"venue"
},
  "geometry": {"coordinates":[-73.698178,43.330295],"type":"Point"}
}