{
  "type": "Feature",
  "properties": {
    "iso:country":"US",
    "sg:address":"458 Old Niskayuna Rd",
    "sg:city":"Latham",
    "sg:classifiers":[
        {
            "category":"Organizations",
            "subcategory":"Religious Organization",
            "type":"Services"
        }
    ],
    "sg:phone":"+1   ",
    "sg:postcode":"12110",
    "sg:province":"NY",
    "wof:name":"Living Hope Community Church",
    "wof:placetype":"venue"
},
  "geometry": {"coordinates":[-73.79792399999999,42.758852],"type":"Point"}
}