{
  "type": "Feature",
  "properties": {
    "addr:full":"656 N French Rd Buffalo NY 14228",
    "addr:housenumber":"656",
    "addr:postcode":"14228",
    "addr:street":"N French Rd",
    "iso:country":"US",
    "sg:address":"656 N French Rd",
    "sg:city":"Buffalo",
    "sg:classifiers":[
        {
            "category":"Real Estate",
            "subcategory":"Developer",
            "type":"Services"
        }
    ],
    "sg:phone":"+1 716 564 6350",
    "sg:postcode":"14228",
    "sg:province":"NY",
    "wof:name":"ETA Cuisenaire",
    "wof:placetype":"venue"
},
  "geometry": {"coordinates":[-78.800455,43.034773],"type":"Point"}
}