{
  "type": "Feature",
  "properties": {
    "addr:full":"380 N Broadway Ste 300 Jericho NY 11753",
    "addr:housenumber":"380",
    "addr:postcode":"11753",
    "addr:street":"N Broadway Ste 300",
    "iso:country":"US",
    "sg:address":"380 N Broadway Ste 300",
    "sg:city":"Jericho",
    "sg:classifiers":[
        {
            "category":"Banks & Credit Unions",
            "subcategory":"Atm",
            "type":"Services"
        }
    ],
    "sg:phone":"+1 516 876 9873",
    "sg:postcode":"11753",
    "sg:province":"NY",
    "sg:tags":[
        "bankruptcy"
    ],
    "wof:name":"Sandler Mitchell P Atty",
    "wof:placetype":"venue"
},
  "geometry": {"coordinates":[-73.53389,40.781768],"type":"Point"}
}