{
  "type": "Feature",
  "properties": {
    "addr:full":"128 Bedford Rd Katonah NY 10536",
    "addr:housenumber":"128",
    "addr:postcode":"10536",
    "addr:street":"Bedford Rd",
    "iso:country":"US",
    "sg:address":"128 Bedford Rd",
    "sg:city":"Katonah",
    "sg:classifiers":[
        {
            "category":"Bars & Pubs",
            "type":"Food & Drink"
        },
        {
            "category":"Restaurant",
            "type":"Food & Drink"
        },
        {
            "category":"Bars & Pubs",
            "subcategory":"Lounge",
            "type":"Food & Drink"
        }
    ],
    "sg:phone":"+1 914 232 0946",
    "sg:postcode":"10536",
    "sg:province":"NY",
    "sg:tags":[
        "grill",
        "american",
        "cocktail"
    ],
    "wof:name":"Katonah Grill",
    "wof:placetype":"venue"
},
  "geometry": {"coordinates":[-73.685581,41.259945],"type":"Point"}
}