{
  "type": "Feature",
  "properties": {
    "iso:country":"US",
    "sg:address":"4959 Nesconset Hwy",
    "sg:city":"Port Jefferson Station",
    "sg:classifiers":[
        {
            "category":"Restaurant",
            "type":"Food & Drink"
        }
    ],
    "sg:menulink":"http://www.allmenus.com/ny/brookhaven/107833-ground-round/menu/",
    "sg:phone":"+1 631 928 0654",
    "sg:postcode":"11776",
    "sg:province":"NY",
    "sg:tags":[
        "american"
    ],
    "wof:name":"Ground Round",
    "wof:placetype":"venue"
},
  "geometry": {"coordinates":[-73.04929799999999,40.923318],"type":"Point"}
}