{
  "type": "Feature",
  "properties": {
    "addr:full":"3625 Eggert Rd Orchard Park NY 14127",
    "addr:housenumber":"3625",
    "addr:postcode":"14127",
    "addr:street":"Eggert Rd",
    "iso:country":"US",
    "sg:address":"3625 Eggert Rd",
    "sg:city":"Orchard Park",
    "sg:classifiers":[
        {
            "category":"Building & Trades",
            "subcategory":"Construction",
            "type":"Services"
        }
    ],
    "sg:phone":"+1 716 662 1600",
    "sg:postcode":"14127",
    "sg:province":"NY",
    "sg:tags":[
        "contractor"
    ],
    "wof:name":"Building Co Inc",
    "wof:placetype":"venue"
},
  "geometry": {"coordinates":[-78.750865,42.786117],"type":"Point"}
}