{
  "type": "Feature",
  "properties": {
    "iso:country":"US",
    "sg:address":"45 Elderberry Rd",
    "sg:city":"Syosset",
    "sg:classifiers":[
        {
            "category":"Professional",
            "subcategory":"Computer Services",
            "type":"Services"
        }
    ],
    "sg:phone":"+1 516 364 0204",
    "sg:postcode":"11791",
    "sg:province":"NY",
    "sg:tags":[
        "prepackaged",
        "software"
    ],
    "wof:name":"Zohar Software & Cmpt Systems",
    "wof:placetype":"venue"
},
  "geometry": {"coordinates":[-73.498453,40.793785],"type":"Point"}
}