{
  "type": "Feature",
  "properties": {
    "iso:country":"US",
    "sg:address":"154 Washington Ave",
    "sg:city":"Brooklyn",
    "sg:classifiers":[
        {
            "category":"Professional",
            "subcategory":"Lawyer & Legal Services",
            "type":"Services"
        }
    ],
    "sg:phone":"+1 718 923 9700",
    "sg:postcode":"11205",
    "sg:province":"NY",
    "sg:tags":[
        "attorney"
    ],
    "wof:name":"Daryll Boyd Jones PC",
    "wof:placetype":"venue"
},
  "geometry": {"coordinates":[-73.967231,40.695158],"type":"Point"}
}