{
  "type": "Feature",
  "properties": {
    "addr:full":"81 Conklin St Farmingdale NY 11735",
    "addr:housenumber":"81",
    "addr:postcode":"11735",
    "addr:street":"Conklin St",
    "iso:country":"US",
    "sg:address":"81 Conklin St",
    "sg:city":"Farmingdale",
    "sg:classifiers":[
        {
            "category":"Building & Trades",
            "subcategory":"Construction",
            "type":"Services"
        }
    ],
    "sg:phone":"+1 516 694 0175",
    "sg:postcode":"11735",
    "sg:province":"NY",
    "sg:tags":[
        "home",
        "improvement"
    ],
    "wof:name":"Alagna Enterprises Inc",
    "wof:placetype":"venue"
},
  "geometry": {"coordinates":[-73.458027,40.730984],"type":"Point"}
}