{
  "type": "Feature",
  "properties": {
    "addr:full":"749 Jefferson Ave Buffalo NY 14204",
    "addr:housenumber":"749",
    "addr:postcode":"14204",
    "addr:street":"Jefferson Ave",
    "iso:country":"US",
    "sg:address":"749 Jefferson Ave",
    "sg:city":"Buffalo",
    "sg:classifiers":[
        {
            "category":"Communications",
            "subcategory":"Radio Station",
            "type":"Services"
        }
    ],
    "sg:phone":"+1 716 854 3436",
    "sg:postcode":"14204",
    "sg:province":"NY",
    "wof:name":"Am Express",
    "wof:placetype":"venue"
},
  "geometry": {"coordinates":[-78.85377,42.895513],"type":"Point"}
}