{
  "type": "Feature",
  "properties": {
    "iso:country":"US",
    "sg:address":"705 Broadway",
    "sg:city":"New York",
    "sg:classifiers":[
        {
            "category":"Food & Beverages",
            "subcategory":"Specialty",
            "type":"Retail Goods"
        }
    ],
    "sg:phone":"+1 212 927 9064",
    "sg:postcode":"10003",
    "sg:province":"NY",
    "sg:tags":[
        "health",
        "diet"
    ],
    "sg:website":"www.gnc.com",
    "wof:name":"GNC",
    "wof:placetype":"venue"
},
  "geometry": {"coordinates":[-73.99397399999999,40.728793],"type":"Point"}
}