{
  "type": "Feature",
  "properties": {
    "addr:full":"4679 Dutch Hill Rd Spr Cincinnatus NY 13040",
    "addr:housenumber":"4679",
    "addr:postcode":"13040",
    "addr:street":"Dutch Hill Rd;Cincinnatus",
    "iso:country":"US",
    "sg:address":"4679 Dutch Hill Rd Spr",
    "sg:city":"Cincinnatus",
    "sg:classifiers":[
        {
            "category":"Shopping",
            "subcategory":"Bicycles & Sporting Goods",
            "type":"Retail Goods"
        }
    ],
    "sg:phone":"+1   ",
    "sg:postcode":"13040",
    "sg:province":"NY",
    "wof:name":"Wyndy Hyl Archery",
    "wof:placetype":"venue"
},
  "geometry": {"coordinates":[-75.96683899999999,42.528484],"type":"Point"}
}