{
  "type": "Feature",
  "properties": {
    "addr:full":"60 Carlton Ave Mastic NY 11950",
    "addr:housenumber":"60",
    "addr:postcode":"11950",
    "addr:street":"Carlton Ave",
    "iso:country":"US",
    "sg:address":"60 Carlton Ave",
    "sg:city":"Mastic",
    "sg:classifiers":[
        {
            "category":"Real Estate",
            "subcategory":"Real Estate Services",
            "type":"Services"
        },
        {
            "category":"Real Estate",
            "subcategory":"Real Estate Agent",
            "type":"Services"
        }
    ],
    "sg:phone":"+1 641 654 2827",
    "sg:postcode":"11950",
    "sg:province":"NY",
    "sg:tags":[
        "buyer",
        "broker"
    ],
    "wof:name":"Your Home Realty",
    "wof:placetype":"venue"
},
  "geometry": {"coordinates":[-72.843307,40.804588],"type":"Point"}
}