{
  "type": "Feature",
  "properties": {
    "iso:country":"US",
    "sg:address":"120 E 87 St",
    "sg:city":"New York",
    "sg:classifiers":[
        {
            "category":"Personal",
            "type":"Services"
        }
    ],
    "sg:phone":"+1 212 987 9820",
    "sg:postcode":"10128",
    "sg:province":"NY",
    "sg:tags":[
        "consultant",
        "fashion"
    ],
    "wof:name":"Fashion Ease",
    "wof:placetype":"venue"
},
  "geometry": {"coordinates":[-73.95568400000001,40.780417],"type":"Point"}
}