{
  "type": "Feature",
  "properties": {
    "addr:full":"435 E 70 St New York NY 10021",
    "addr:housenumber":"435;70",
    "addr:postcode":"10021",
    "addr:street":"E;St",
    "iso:country":"US",
    "sg:address":"435 E 70 St",
    "sg:city":"New York",
    "sg:classifiers":[
        {
            "category":"Health Services",
            "subcategory":"Optometrist",
            "type":"Services"
        }
    ],
    "sg:phone":"+1   ",
    "sg:postcode":"10021",
    "sg:province":"NY",
    "sg:tags":[
        "pediatrics"
    ],
    "wof:name":"Madison East Pediatrics PC",
    "wof:placetype":"venue"
},
  "geometry": {"coordinates":[-73.955257,40.765939],"type":"Point"}
}