{
  "type": "Feature",
  "properties": {
    "addr:full":"458 77th Street Brooklyn NY 11209",
    "addr:housenumber":"458",
    "addr:postcode":"11209",
    "addr:street":"77Th Street",
    "iso:country":"US",
    "sg:address":"458 77th Street",
    "sg:city":"Brooklyn",
    "sg:classifiers":[
        {
            "category":"Health Services",
            "subcategory":"Dentist",
            "type":"Services"
        }
    ],
    "sg:phone":"+1 718 833 3953",
    "sg:postcode":"11209",
    "sg:province":"NY",
    "wof:name":"Bentevis Stavros DDS",
    "wof:placetype":"venue"
},
  "geometry": {"coordinates":[-74.02415499999999,40.628372],"type":"Point"}
}