{
  "type": "Feature",
  "properties": {
    "addr:full":"1370 Reckson Plz Uniondale NY 11556",
    "addr:housenumber":"1370",
    "addr:postcode":"11556",
    "addr:street":"Reckson Plz",
    "iso:country":"US",
    "sg:address":"1370 Reckson Plz",
    "sg:city":"Uniondale",
    "sg:classifiers":[
        {
            "category":"Professional",
            "subcategory":"Lawyer & Legal Services",
            "type":"Services"
        }
    ],
    "sg:phone":"+1 516 394 4200",
    "sg:postcode":"11556",
    "sg:province":"NY",
    "sg:tags":[
        "attorney"
    ],
    "sg:website":"www.duffyduffyandburdo.com",
    "wof:name":"Duffy Duffy & Burdo",
    "wof:placetype":"venue"
},
  "geometry": {"coordinates":[-73.586799,40.720088],"type":"Point"}
}