{
  "type": "Feature",
  "properties": {
    "addr:full":"120 W 9th St Brooklyn NY 11231",
    "addr:housenumber":"120",
    "addr:postcode":"11231",
    "addr:street":"W 9Th St",
    "iso:country":"US",
    "sg:address":"120 W 9th St",
    "sg:city":"Brooklyn",
    "sg:classifiers":[
        {
            "category":"Social Services",
            "type":"Services"
        }
    ],
    "sg:phone":"+1 718 624 6222",
    "sg:postcode":"11231",
    "sg:province":"NY",
    "wof:name":"PAL Head Start Program",
    "wof:placetype":"venue"
},
  "geometry": {"coordinates":[-74.00319399999999,40.676271],"type":"Point"}
}