{
  "type": "Feature",
  "properties": {
    "iso:country":"US",
    "sg:address":"6600 Jericho Tpke",
    "sg:city":"Syosset",
    "sg:classifiers":[
        {
            "category":"Building & Trades",
            "subcategory":"Locksmith",
            "type":"Services"
        }
    ],
    "sg:phone":"+1 516 938 4891",
    "sg:postcode":"11791",
    "sg:province":"NY",
    "sg:tags":[
        "key"
    ],
    "wof:name":"A 24 Hour A Emergency Locksmith",
    "wof:placetype":"venue"
},
  "geometry": {"coordinates":[-73.523697,40.804699],"type":"Point"}
}