{
  "type": "Feature",
  "properties": {
    "iso:country":"US",
    "sg:address":"990 E 181st St",
    "sg:city":"Bronx",
    "sg:classifiers":[
        {
            "category":"Organizations",
            "subcategory":"Religious Organization",
            "type":"Services"
        }
    ],
    "sg:phone":"+1   ",
    "sg:postcode":"10460",
    "sg:province":"NY",
    "wof:name":"New Tabernacle Baptist Church",
    "wof:placetype":"venue"
},
  "geometry": {"coordinates":[-73.87891500000001,40.8442],"type":"Point"}
}