{
  "type": "Feature",
  "properties": {
    "addr:full":"4201 White Plains Rd Bronx NY 10466",
    "addr:housenumber":"4201",
    "addr:postcode":"10466",
    "addr:street":"White Plains Rd",
    "iso:country":"US",
    "sg:address":"4201 White Plains Rd",
    "sg:city":"Bronx",
    "sg:classifiers":[
        {
            "category":"Banks & Credit Unions",
            "subcategory":"Bank",
            "type":"Services"
        }
    ],
    "sg:phone":"+1 718 994 1900",
    "sg:postcode":"10466",
    "sg:province":"NY",
    "sg:tags":[
        "state",
        "commercial"
    ],
    "sg:website":"www.northforkbank.com",
    "wof:name":"North Fork Bank",
    "wof:placetype":"venue"
},
  "geometry": {"coordinates":[-73.856956,40.894168],"type":"Point"}
}