{
  "type": "Feature",
  "properties": {
    "addr:full":"213 Middletown Rd Waterford NY 12188",
    "addr:housenumber":"213",
    "addr:postcode":"12188",
    "addr:street":"Middletown Rd",
    "iso:country":"US",
    "sg:address":"213 Middletown Rd",
    "sg:city":"Waterford",
    "sg:classifiers":[
        {
            "category":"Shopping",
            "subcategory":"Clothing, Apparel, & Fashions",
            "type":"Retail Goods"
        }
    ],
    "sg:phone":"+1   ",
    "sg:postcode":"12188",
    "sg:province":"NY",
    "wof:name":"Andre & Son Furs",
    "wof:placetype":"venue"
},
  "geometry": {"coordinates":[-73.69891699999999,42.817533],"type":"Point"}
}