{
  "type": "Feature",
  "properties": {
    "addr:full":"1327 W Main St Riverhead NY 11901",
    "addr:housenumber":"1327",
    "addr:postcode":"11901",
    "addr:street":"W Main St",
    "iso:country":"US",
    "sg:address":"1327 W Main St",
    "sg:city":"Riverhead",
    "sg:classifiers":[
        {
            "category":"Real Estate",
            "subcategory":"Real Estate Services",
            "type":"Services"
        }
    ],
    "sg:phone":"+1 631 369 5400",
    "sg:postcode":"11901",
    "sg:province":"NY",
    "sg:website":"www.riverheadrealestate.com",
    "wof:name":"Riverhead Real Estate",
    "wof:placetype":"venue"
},
  "geometry": {"coordinates":[-72.696006,40.917136],"type":"Point"}
}