{
  "type": "Feature",
  "properties": {
    "addr:full":"413 Lopez Dr West Hempstead NY 11552",
    "addr:housenumber":"413",
    "addr:postcode":"11552",
    "addr:street":"Lopez Dr West",
    "iso:country":"US",
    "sg:address":"413 Lopez Dr",
    "sg:city":"West Hempstead",
    "sg:classifiers":[
        {
            "category":"Real Estate",
            "subcategory":"Architect",
            "type":"Services"
        }
    ],
    "sg:phone":"+1 516 485 1042",
    "sg:postcode":"11552",
    "sg:province":"NY",
    "wof:name":"Katcher Monroe I & Assocs",
    "wof:placetype":"venue"
},
  "geometry": {"coordinates":[-73.65070299999999,40.691002],"type":"Point"}
}