{
  "type": "Feature",
  "properties": {
    "addr:full":"101 W 84th St New York NY 10024",
    "addr:housenumber":"101",
    "addr:postcode":"10024",
    "addr:street":"W 84Th St",
    "iso:country":"US",
    "sg:address":"101 W 84th St",
    "sg:city":"New York",
    "sg:classifiers":[
        {
            "category":"Retail",
            "subcategory":"Laundry & Dry Cleaning",
            "type":"Services"
        }
    ],
    "sg:phone":"+1 212 721 7712",
    "sg:postcode":"10024",
    "sg:province":"NY",
    "wof:name":"Park West Laundromat",
    "wof:placetype":"venue"
},
  "geometry": {"coordinates":[-73.973099,40.785198],"type":"Point"}
}