{
  "type": "Feature",
  "properties": {
    "iso:country":"US",
    "sg:address":"74 E Main St",
    "sg:city":"Shortsville",
    "sg:classifiers":[
        {
            "category":"Building & Trades",
            "subcategory":"Landscaping Services",
            "type":"Services"
        }
    ],
    "sg:phone":"+1 585 289 3565",
    "sg:postcode":"14548",
    "sg:province":"NY",
    "wof:name":"P & J Lawn Kare",
    "wof:placetype":"venue"
},
  "geometry": {"coordinates":[-77.213129,42.955878],"type":"Point"}
}