{
  "type": "Feature",
  "properties": {
    "addr:full":"949 Creek Rd Attica NY 14011",
    "addr:housenumber":"949",
    "addr:postcode":"14011",
    "addr:street":"Creek Rd",
    "iso:country":"US",
    "sg:address":"949 Creek Rd",
    "sg:city":"Attica",
    "sg:classifiers":[
        {
            "category":"Bus Charters",
            "type":"Transportation"
        }
    ],
    "sg:phone":"+1 585 591 2107",
    "sg:postcode":"14011",
    "sg:province":"NY",
    "sg:tags":[
        "rental"
    ],
    "wof:name":"Attica Bus Svc",
    "wof:placetype":"venue"
},
  "geometry": {"coordinates":[-78.28914899999999,42.83628],"type":"Point"}
}