{
  "type": "Feature",
  "properties": {
    "iso:country":"US",
    "sg:address":"3 Satmar Dr Unit 101",
    "sg:city":"Monroe",
    "sg:classifiers":[
        {
            "category":"Food & Beverages",
            "subcategory":"Groceries & Convenience Stores",
            "type":"Retail Goods"
        }
    ],
    "sg:phone":"+1 845 781 7673",
    "sg:postcode":"10950",
    "sg:province":"NY",
    "wof:name":"Friendly Supermarket",
    "wof:placetype":"venue"
},
  "geometry": {"coordinates":[-74.162598,41.343601],"type":"Point"}
}