{
  "type": "Feature",
  "properties": {
    "iso:country":"US",
    "sg:address":"50 Barker St",
    "sg:city":"Mount Kisco",
    "sg:classifiers":[
        {
            "category":"Wholesale",
            "subcategory":"Jewelry",
            "type":"Manufacturing & Wholesale Goods"
        }
    ],
    "sg:phone":"+1 914 241 4663",
    "sg:postcode":"10549",
    "sg:province":"NY",
    "sg:tags":[
        "stone"
    ],
    "wof:name":"Bidichandani Ind V",
    "wof:placetype":"venue"
},
  "geometry": {"coordinates":[-73.72313200000001,41.212198],"type":"Point"}
}