{
  "type": "Feature",
  "properties": {
    "addr:full":"1381 51st St Brooklyn NY 11219",
    "addr:housenumber":"1381",
    "addr:postcode":"11219",
    "addr:street":"51St St",
    "iso:country":"US",
    "sg:address":"1381 51st St",
    "sg:city":"Brooklyn",
    "sg:classifiers":[
        {
            "category":"Real Estate",
            "subcategory":"Real Estate Agent",
            "type":"Services"
        }
    ],
    "sg:phone":"+1 718 854 9200",
    "sg:postcode":"11219",
    "sg:province":"NY",
    "wof:name":"R & R Equities",
    "wof:placetype":"venue"
},
  "geometry": {"coordinates":[-73.99239900000001,40.633719],"type":"Point"}
}