{
  "type": "Feature",
  "properties": {
    "iso:country":"US",
    "sg:address":"71 Brush Creek Rd",
    "sg:city":"Buffalo",
    "sg:classifiers":[
        {
            "category":"Shopping",
            "subcategory":"Gifts & Souvenirs",
            "type":"Retail Goods"
        }
    ],
    "sg:phone":"+1   ",
    "sg:postcode":"14221",
    "sg:province":"NY",
    "wof:name":"Professional Advertising",
    "wof:placetype":"venue"
},
  "geometry": {"coordinates":[-78.71996799999999,42.992771],"type":"Point"}
}