{
  "type": "Feature",
  "properties": {
    "iso:country":"US",
    "sg:address":"5 Dakota Dr",
    "sg:city":"New Hyde Park",
    "sg:classifiers":[
        {
            "category":"Wholesale",
            "subcategory":"Groceries",
            "type":"Manufacturing & Wholesale Goods"
        }
    ],
    "sg:phone":"+1 516 327 0002",
    "sg:postcode":"11042",
    "sg:province":"NY",
    "sg:tags":[
        "beverage"
    ],
    "wof:name":"Arizona Beverages",
    "wof:placetype":"venue"
},
  "geometry": {"coordinates":[-73.69485899999999,40.759728],"type":"Point"}
}