{
  "type": "Feature",
  "properties": {
    "addr:full":"1200 Morris Park Ave Bronx NY 10461",
    "addr:housenumber":"1200",
    "addr:postcode":"10461",
    "addr:street":"Morris Park Ave",
    "iso:country":"US",
    "sg:address":"1200 Morris Park Ave",
    "sg:city":"Bronx",
    "sg:classifiers":[
        {
            "category":"Retail",
            "subcategory":"Repair Shop",
            "type":"Services"
        }
    ],
    "sg:phone":"+1 718 764 5250",
    "sg:postcode":"10461",
    "sg:province":"NY",
    "sg:tags":[
        "lock",
        "locksmith"
    ],
    "wof:name":"Emergency Locksmith",
    "wof:placetype":"venue"
},
  "geometry": {"coordinates":[-73.848214,40.851091],"type":"Point"}
}