{
  "type": "Feature",
  "properties": {
    "iso:country":"US",
    "sg:address":"2664 Rte 112",
    "sg:city":"Medford",
    "sg:classifiers":[
        {
            "category":"Manufacturing",
            "subcategory":"Petroleum Products",
            "type":"Manufacturing & Wholesale Goods"
        }
    ],
    "sg:phone":"+1 631 207 1563",
    "sg:postcode":"11763",
    "sg:province":"NY",
    "wof:name":"Us Petroleum",
    "wof:placetype":"venue"
},
  "geometry": {"coordinates":[-72.998679,40.820142],"type":"Point"}
}