{
  "type": "Feature",
  "properties": {
    "addr:full":"610 Myrtle Ave Brooklyn NY 11205",
    "addr:housenumber":"610",
    "addr:postcode":"11205",
    "addr:street":"Myrtle Ave",
    "iso:country":"US",
    "sg:address":"610 Myrtle Ave",
    "sg:city":"Brooklyn",
    "sg:classifiers":[
        {
            "category":"Home & Garden",
            "subcategory":"Household Appliances",
            "type":"Retail Goods"
        }
    ],
    "sg:phone":"+1   ",
    "sg:postcode":"11205",
    "sg:province":"NY",
    "wof:name":"Alappliance Co",
    "wof:placetype":"venue"
},
  "geometry": {"coordinates":[-73.959575,40.694099],"type":"Point"}
}