{
  "type": "Feature",
  "properties": {
    "addr:full":"615 Saw Mill River Rd Ardsley NY 10502",
    "addr:housenumber":"615",
    "addr:postcode":"10502",
    "addr:street":"Saw Mill River Rd",
    "iso:country":"US",
    "sg:address":"615 Saw Mill River Rd",
    "sg:city":"Ardsley",
    "sg:classifiers":[
        {
            "category":"Wholesale",
            "subcategory":"Electrical",
            "type":"Manufacturing & Wholesale Goods"
        }
    ],
    "sg:phone":"+1 914 693 2600",
    "sg:postcode":"10502",
    "sg:province":"NY",
    "sg:tags":[
        "sound",
        "equipment",
        "system"
    ],
    "wof:name":"Monte Brothers Inc",
    "wof:placetype":"venue"
},
  "geometry": {"coordinates":[-73.849163,41.010044],"type":"Point"}
}