{
  "type": "Feature",
  "properties": {
    "iso:country":"US",
    "sg:address":"944 N Broadway",
    "sg:city":"Massapequa",
    "sg:classifiers":[
        {
            "category":"Sports & Exercise",
            "subcategory":"Gym",
            "type":"Entertainment"
        }
    ],
    "sg:phone":"+1 516 541 8446",
    "sg:postcode":"11758",
    "sg:province":"NY",
    "sg:tags":[
        "club",
        "health",
        "studio",
        "gymnasium"
    ],
    "wof:name":"Cuts Fitness For Men",
    "wof:placetype":"venue"
},
  "geometry": {"coordinates":[-73.46207200000001,40.702088],"type":"Point"}
}