{
  "type": "Feature",
  "properties": {
    "iso:country":"US",
    "sg:address":"241 Dry Bridge Rd",
    "sg:city":"Mexico",
    "sg:classifiers":[
        {
            "category":"Recreation",
            "subcategory":"Amusement Park",
            "type":"Entertainment"
        },
        {
            "category":"Recreation",
            "subcategory":"Picnic Area",
            "type":"Entertainment"
        }
    ],
    "sg:phone":"+1 315 298 2347",
    "sg:postcode":"13114",
    "sg:province":"NY",
    "sg:tags":[
        "equipment",
        "ride",
        "place",
        "arcade"
    ],
    "wof:name":"Grampa Bob's Animal Park",
    "wof:placetype":"venue"
},
  "geometry": {"coordinates":[-76.15910700000001,43.486134],"type":"Point"}
}