{
  "type": "Feature",
  "properties": {
    "addr:full":"34 E 30 St New York NY 10016",
    "addr:housenumber":"34;30",
    "addr:postcode":"10016",
    "addr:street":"E;St",
    "iso:country":"US",
    "sg:address":"34 E 30 St",
    "sg:city":"New York",
    "sg:classifiers":[
        {
            "category":"Communications",
            "subcategory":"Film & Video Production",
            "type":"Services"
        }
    ],
    "sg:phone":"+1 212 684 2266",
    "sg:postcode":"10016",
    "sg:province":"NY",
    "sg:tags":[
        "television",
        "producer"
    ],
    "wof:name":"Alternate Current Inc",
    "wof:placetype":"venue"
},
  "geometry": {"coordinates":[-73.98335,40.744571],"type":"Point"}
}