{
  "type": "Feature",
  "properties": {
    "addr:full":"520 William Floyd Pkwy Shirley NY 11967",
    "addr:housenumber":"520",
    "addr:postcode":"11967",
    "addr:street":"William Floyd Pkwy",
    "iso:country":"US",
    "sg:address":"520 William Floyd Pkwy",
    "sg:city":"Shirley",
    "sg:classifiers":[
        {
            "category":"Autos & Motor Vehicles",
            "subcategory":"Fuel & Gas Station",
            "type":"Retail Goods"
        }
    ],
    "sg:phone":"+1 631 281 6166",
    "sg:postcode":"11967",
    "sg:province":"NY",
    "wof:name":"Er-Hal Managmnt Corp",
    "wof:placetype":"venue"
},
  "geometry": {"coordinates":[-72.864098,40.784698],"type":"Point"}
}