{
  "type": "Feature",
  "properties": {
    "iso:country":"US",
    "sg:address":"58 Maytime Dr",
    "sg:city":"Jericho",
    "sg:classifiers":[
        {
            "category":"Education",
            "subcategory":"School",
            "type":"Public Place"
        }
    ],
    "sg:phone":"+1 516 203 3640",
    "sg:postcode":"11753",
    "sg:province":"NY",
    "sg:tags":[
        "high",
        "middle",
        "elementary"
    ],
    "wof:name":"Jericho Union Free School District",
    "wof:placetype":"venue"
},
  "geometry": {"coordinates":[-73.529484,40.790507],"type":"Point"}
}