{
  "type": "Feature",
  "properties": {
    "addr:full":"365 Charles St West Hempstead NY 11552",
    "addr:housenumber":"365",
    "addr:postcode":"11552",
    "addr:street":"Charles St West",
    "iso:country":"US",
    "sg:address":"365 Charles St",
    "sg:city":"West Hempstead",
    "sg:classifiers":[
        {
            "category":"Manufacturing",
            "subcategory":"Paper Products",
            "type":"Manufacturing & Wholesale Goods"
        }
    ],
    "sg:phone":"+1 516 539 1020",
    "sg:postcode":"11552",
    "sg:province":"NY",
    "sg:tags":[
        "bag"
    ],
    "wof:name":"Variable Industries Inc",
    "wof:placetype":"venue"
},
  "geometry": {"coordinates":[-73.654055,40.688329],"type":"Point"}
}