{
  "type": "Feature",
  "properties": {
    "addr:full":"33 Lansing St Albany NY 12207",
    "addr:housenumber":"33",
    "addr:postcode":"12207",
    "addr:street":"Lansing St",
    "iso:country":"US",
    "sg:address":"33 Lansing St",
    "sg:city":"Albany",
    "sg:classifiers":[
        {
            "category":"Freight",
            "type":"Transportation"
        }
    ],
    "sg:phone":"+1   ",
    "sg:postcode":"12207",
    "sg:province":"NY",
    "sg:tags":[
        "operator",
        "trucking"
    ],
    "wof:name":"ABC",
    "wof:placetype":"venue"
},
  "geometry": {"coordinates":[-73.74509999999999,42.657595],"type":"Point"}
}