{
  "type": "Feature",
  "properties": {
    "addr:full":"723 New Loudon Rd Latham NY 12110",
    "addr:housenumber":"723",
    "addr:postcode":"12110",
    "addr:street":"New Loudon Rd",
    "iso:country":"US",
    "sg:address":"723 New Loudon Rd",
    "sg:city":"Latham",
    "sg:classifiers":[
        {
            "category":"Autos & Motor Vehicles",
            "subcategory":"Automobile Sales",
            "type":"Retail Goods"
        }
    ],
    "sg:phone":"+1   ",
    "sg:postcode":"12110",
    "sg:province":"NY",
    "wof:name":"Langan Audi East",
    "wof:placetype":"venue"
},
  "geometry": {"coordinates":[-73.762007,42.737783],"type":"Point"}
}