{
  "type": "Feature",
  "properties": {
    "addr:full":"475 Fdr Dr New York NY 10002",
    "addr:housenumber":"475",
    "addr:postcode":"10002",
    "addr:street":"Fdr Dr",
    "iso:country":"US",
    "sg:address":"475 Fdr Dr",
    "sg:city":"New York",
    "sg:classifiers":[
        {
            "category":"Organizations",
            "subcategory":"Religious Organization",
            "type":"Services"
        }
    ],
    "sg:phone":"+1 212 870 3070",
    "sg:postcode":"10002",
    "sg:province":"NY",
    "wof:name":"Riverside Park Fund",
    "wof:placetype":"venue"
},
  "geometry": {"coordinates":[-73.97737499999999,40.713703],"type":"Point"}
}