{
  "type": "Feature",
  "properties": {
    "addr:full":"190 E 95th St New York NY 10128",
    "addr:housenumber":"190",
    "addr:postcode":"10128",
    "addr:street":"E 95Th St",
    "iso:country":"US",
    "sg:address":"190 E 95th St",
    "sg:city":"New York",
    "sg:classifiers":[
        {
            "category":"Retail",
            "subcategory":"Laundry & Dry Cleaning",
            "type":"Services"
        }
    ],
    "sg:phone":"+1 212 876 9295",
    "sg:postcode":"10128",
    "sg:province":"NY",
    "wof:name":"Highgate Cleaners Inc",
    "wof:placetype":"venue"
},
  "geometry": {"coordinates":[-73.949898,40.784401],"type":"Point"}
}