{
  "type": "Feature",
  "properties": {
    "addr:full":"207 Everit Ave Hewlett NY 11557",
    "addr:housenumber":"207",
    "addr:postcode":"11557",
    "addr:street":"Everit Ave",
    "iso:country":"US",
    "sg:address":"207 Everit Ave",
    "sg:city":"Hewlett",
    "sg:classifiers":[
        {
            "category":"Wholesale",
            "subcategory":"Office Equipment",
            "type":"Manufacturing & Wholesale Goods"
        }
    ],
    "sg:phone":"+1 516 295 7500",
    "sg:postcode":"11557",
    "sg:province":"NY",
    "sg:tags":[
        "chalkboard"
    ],
    "wof:name":"Chairman Of The Boards Inc",
    "wof:placetype":"venue"
},
  "geometry": {"coordinates":[-73.689531,40.637423],"type":"Point"}
}