{
  "type": "Feature",
  "properties": {
    "iso:country":"US",
    "sg:address":"434 E Amherst St",
    "sg:city":"Buffalo",
    "sg:classifiers":[
        {
            "category":"Retail",
            "subcategory":"Repair Shop",
            "type":"Services"
        }
    ],
    "sg:phone":"+1 716 447 9842",
    "sg:postcode":"14215",
    "sg:province":"NY",
    "sg:tags":[
        "upholsterer"
    ],
    "wof:name":"A V Iglesias Upholstery",
    "wof:placetype":"venue"
},
  "geometry": {"coordinates":[-78.82229700000001,42.940173],"type":"Point"}
}