{
  "type": "Feature",
  "properties": {
    "iso:country":"US",
    "sg:address":"56 3rd St",
    "sg:city":"Cohoes",
    "sg:classifiers":[
        {
            "category":"Taxi",
            "type":"Transportation"
        }
    ],
    "sg:phone":"+1   ",
    "sg:postcode":"12047",
    "sg:province":"NY",
    "sg:tags":[
        "taxicab"
    ],
    "wof:name":"A L Aubin Car Transporter",
    "wof:placetype":"venue"
},
  "geometry": {"coordinates":[-73.690515,42.770025],"type":"Point"}
}