{
  "type": "Feature",
  "properties": {
    "addr:full":"214 Heberle Rd Rochester NY 14609",
    "addr:housenumber":"214",
    "addr:postcode":"14609",
    "addr:street":"Heberle Rd",
    "iso:country":"US",
    "sg:address":"214 Heberle Rd",
    "sg:city":"Rochester",
    "sg:classifiers":[
        {
            "category":"Building & Trades",
            "subcategory":"Locksmith",
            "type":"Services"
        },
        {
            "category":"Shopping",
            "type":"Retail Goods"
        }
    ],
    "sg:phone":"+1 585 467 6272",
    "sg:postcode":"14609",
    "sg:province":"NY",
    "sg:tags":[
        "locksmiths-commercial",
        "industrial",
        "lock",
        "safe",
        "key",
        "vault"
    ],
    "sg:website":"http://www.accesslockandsafe.net",
    "wof:name":"Access Lock & Safe",
    "wof:placetype":"venue"
},
  "geometry": {"coordinates":[-77.55586700000001,43.193162],"type":"Point"}
}