{
  "type": "Feature",
  "properties": {
    "addr:full":"32 Old Slip New York NY 10005",
    "addr:housenumber":"32",
    "addr:postcode":"10005",
    "addr:street":"Old Slip",
    "iso:country":"US",
    "sg:address":"32 Old Slip",
    "sg:city":"New York",
    "sg:classifiers":[
        {
            "category":"Utilities",
            "subcategory":"Telephone",
            "type":"Services"
        }
    ],
    "sg:phone":"+1   ",
    "sg:postcode":"10005",
    "sg:province":"NY",
    "sg:tags":[
        "telecommunication"
    ],
    "wof:name":"Colotel LLC",
    "wof:placetype":"venue"
},
  "geometry": {"coordinates":[-74.007803,40.703475],"type":"Point"}
}