{
  "type": "Feature",
  "properties": {
    "iso:country":"US",
    "sg:address":"380 N Broadway",
    "sg:city":"Jericho",
    "sg:classifiers":[
        {
            "category":"Professional",
            "subcategory":"Lawyer & Legal Services",
            "type":"Services"
        }
    ],
    "sg:phone":"+1 516 932 6350",
    "sg:postcode":"11753",
    "sg:province":"NY",
    "sg:tags":[
        "attorney"
    ],
    "wof:name":"Howard Kurtzberg",
    "wof:placetype":"venue"
},
  "geometry": {"coordinates":[-73.536406,40.789269],"type":"Point"}
}