{
  "type": "Feature",
  "properties": {
    "iso:country":"US",
    "sg:address":"374 14th St",
    "sg:city":"Buffalo",
    "sg:classifiers":[
        {
            "category":"Professional",
            "subcategory":"Employment Agencies",
            "type":"Services"
        }
    ],
    "sg:phone":"+1 716 883 3481",
    "sg:postcode":"14213",
    "sg:province":"NY",
    "wof:name":"Fulcher",
    "wof:placetype":"venue"
},
  "geometry": {"coordinates":[-78.89074599999999,42.910259],"type":"Point"}
}