{
  "type": "Feature",
  "properties": {
    "addr:full":"1940 Benson Ave Brooklyn NY 11214",
    "addr:housenumber":"1940",
    "addr:postcode":"11214",
    "addr:street":"Benson Ave",
    "iso:country":"US",
    "sg:address":"1940 Benson Ave",
    "sg:city":"Brooklyn",
    "sg:classifiers":[
        {
            "category":"Education",
            "subcategory":"School",
            "type":"Public Place"
        }
    ],
    "sg:phone":"+1 718 331 5300",
    "sg:postcode":"11214",
    "sg:province":"NY",
    "sg:tags":[
        "high",
        "middle",
        "elementary"
    ],
    "wof:name":"Pta Benson Elementary School",
    "wof:placetype":"venue"
},
  "geometry": {"coordinates":[-74.001701,40.603199],"type":"Point"}
}