{
  "type": "Feature",
  "properties": {
    "iso:country":"US",
    "sg:address":"56480 State Hwy 25",
    "sg:city":"Southold",
    "sg:classifiers":[
        {
            "category":"Food & Beverages",
            "subcategory":"Groceries & Convenience Stores",
            "type":"Retail Goods"
        }
    ],
    "sg:phone":"+1 631 765 1400",
    "sg:postcode":"11971",
    "sg:province":"NY",
    "sg:website":"www.7-eleven.com",
    "wof:name":"7-Eleven",
    "wof:placetype":"venue"
},
  "geometry": {"coordinates":[-72.420745,41.06697],"type":"Point"}
}