{
  "type": "Feature",
  "properties": {
    "addr:full":"336 W Main St Patchogue NY 11772",
    "addr:housenumber":"336",
    "addr:postcode":"11772",
    "addr:street":"W Main St",
    "iso:country":"US",
    "sg:address":"336 W Main St",
    "sg:city":"Patchogue",
    "sg:classifiers":[
        {
            "category":"Local Transit",
            "type":"Transportation"
        }
    ],
    "sg:phone":"+1 631 475 5490",
    "sg:postcode":"11772",
    "sg:province":"NY",
    "sg:tags":[
        "ambulance"
    ],
    "wof:name":"Patchogue Ambulance Co",
    "wof:placetype":"venue"
},
  "geometry": {"coordinates":[-73.025674,40.763036],"type":"Point"}
}