{
  "type": "Feature",
  "properties": {
    "addr:full":"115 Plainfield Ave Bedford Hills NY 10507",
    "addr:housenumber":"115",
    "addr:postcode":"10507",
    "addr:street":"Plainfield Ave",
    "iso:country":"US",
    "sg:address":"115 Plainfield Ave",
    "sg:city":"Bedford Hills",
    "sg:classifiers":[
        {
            "category":"Retail",
            "subcategory":"Auto Repair",
            "type":"Services"
        }
    ],
    "sg:phone":"+1 914 666 4876",
    "sg:postcode":"10507",
    "sg:province":"NY",
    "sg:website":"www.ifmcollisioncenter.com",
    "wof:name":"IFM Collision Center",
    "wof:placetype":"venue"
},
  "geometry": {"coordinates":[-73.71391300000001,41.228077],"type":"Point"}
}