{
  "type": "Feature",
  "properties": {
    "iso:country":"US",
    "sg:address":"32 Amity St",
    "sg:city":"Spencerport",
    "sg:classifiers":[
        {
            "category":"Organizations",
            "subcategory":"Religious Organization",
            "type":"Services"
        }
    ],
    "sg:phone":"+1   ",
    "sg:postcode":"14559",
    "sg:province":"NY",
    "sg:tags":[
        "child",
        "day",
        "care"
    ],
    "wof:name":"Countryside",
    "wof:placetype":"venue"
},
  "geometry": {"coordinates":[-77.800562,43.192707],"type":"Point"}
}