{
  "type": "Feature",
  "properties": {
    "iso:country":"US",
    "sg:address":"1510 Union Tpke",
    "sg:city":"Lake Success",
    "sg:classifiers":[
        {
            "category":"Shopping",
            "subcategory":"Bicycles & Sporting Goods",
            "type":"Retail Goods"
        }
    ],
    "sg:phone":"+1 516 775 8400",
    "sg:postcode":"11040",
    "sg:province":"NY",
    "wof:name":"Modell's Sporting Goods",
    "wof:placetype":"venue"
},
  "geometry": {"coordinates":[-73.68831,40.75469],"type":"Point"}
}