{
  "type": "Feature",
  "properties": {
    "iso:country":"US",
    "sg:address":"1815 Riverside Dr",
    "sg:city":"New York",
    "sg:classifiers":[
        {
            "category":"Organizations",
            "subcategory":"Religious Organization",
            "type":"Services"
        }
    ],
    "sg:phone":"+1 212 567 3321",
    "sg:postcode":"10034",
    "sg:province":"NY",
    "sg:tags":[
        "church"
    ],
    "wof:name":"Church Of Jesus Christ",
    "wof:placetype":"venue"
},
  "geometry": {"coordinates":[-73.930741,40.866789],"type":"Point"}
}