{
  "type": "Feature",
  "properties": {
    "iso:country":"US",
    "sg:address":"12433 Broadway St",
    "sg:city":"Alden",
    "sg:classifiers":[
        {
            "category":"Professional",
            "subcategory":"Business Services",
            "type":"Services"
        }
    ],
    "sg:phone":"+1   ",
    "sg:postcode":"14004",
    "sg:province":"NY",
    "sg:tags":[
        "pool",
        "maintenance",
        "swimming"
    ],
    "wof:name":"Crystal Clear Pools",
    "wof:placetype":"venue"
},
  "geometry": {"coordinates":[-78.530406,42.891613],"type":"Point"}
}