{
  "type": "Feature",
  "properties": {
    "addr:full":"245 8 Ave New York NY 10011",
    "addr:housenumber":"245",
    "addr:postcode":"10011",
    "addr:street":"8 Ave",
    "iso:country":"US",
    "sg:address":"245 8 Ave",
    "sg:city":"New York",
    "sg:classifiers":[
        {
            "category":"Professional",
            "subcategory":"Business Services",
            "type":"Services"
        }
    ],
    "sg:phone":"+1 212 366 4310",
    "sg:postcode":"10011",
    "sg:province":"NY",
    "wof:name":"Mail Boxes Etc",
    "wof:placetype":"venue"
},
  "geometry": {"coordinates":[-74.00278900000001,40.739396],"type":"Point"}
}