{
  "type": "Feature",
  "properties": {
    "addr:full":"208 State Hwy 8 Bridgewater NY 13313",
    "addr:housenumber":"208",
    "addr:postcode":"13313",
    "addr:street":"State Hwy 8",
    "iso:country":"US",
    "sg:address":"208 State Hwy 8",
    "sg:city":"Bridgewater",
    "sg:classifiers":[
        {
            "category":"Organizations",
            "subcategory":"Religious Organization",
            "type":"Services"
        }
    ],
    "sg:phone":"+1 315 822 4443",
    "sg:postcode":"13313",
    "sg:province":"NY",
    "sg:tags":[
        "clergy"
    ],
    "wof:name":"Robert M Bligh",
    "wof:placetype":"venue"
},
  "geometry": {"coordinates":[-75.250934,42.872208],"type":"Point"}
}