{
  "type": "Feature",
  "properties": {
    "iso:country":"US",
    "sg:address":"640 Wellwood Ave",
    "sg:city":"Lindenhurst",
    "sg:classifiers":[
        {
            "category":"Restaurant",
            "type":"Food & Drink"
        }
    ],
    "sg:phone":"+1 631 226 9752",
    "sg:postcode":"11757",
    "sg:province":"NY",
    "sg:tags":[
        "delicatessen"
    ],
    "wof:name":"Foods Of Italia",
    "wof:placetype":"venue"
},
  "geometry": {"coordinates":[-73.384124,40.7009],"type":"Point"}
}