{
  "type": "Feature",
  "properties": {
    "iso:country":"US",
    "sg:address":"6960 Lyman Rd",
    "sg:city":"Bergen",
    "sg:classifiers":[
        {
            "category":"Recreation",
            "type":"Entertainment"
        }
    ],
    "sg:phone":"+1   ",
    "sg:postcode":"14416",
    "sg:province":"NY",
    "wof:name":"Eq Eden Ranch",
    "wof:placetype":"venue"
},
  "geometry": {"coordinates":[-78.034722,43.052185],"type":"Point"}
}