{
  "type": "Feature",
  "properties": {
    "addr:full":"928 Southern Blvd Bronx NY 10459",
    "addr:housenumber":"928",
    "addr:postcode":"10459",
    "addr:street":"Southern Blvd",
    "iso:country":"US",
    "sg:address":"928 Southern Blvd",
    "sg:city":"Bronx",
    "sg:classifiers":[
        {
            "category":"Restaurant",
            "type":"Food & Drink"
        }
    ],
    "sg:phone":"+1   ",
    "sg:postcode":"10459",
    "sg:province":"NY",
    "sg:tags":[
        "eating"
    ],
    "wof:name":"Cuernavaca Deli",
    "wof:placetype":"venue"
},
  "geometry": {"coordinates":[-73.892363,40.819748],"type":"Point"}
}