{
  "type": "Feature",
  "properties": {
    "addr:full":"2232 Woodhull Ave Bronx NY 10469",
    "addr:housenumber":"2232",
    "addr:postcode":"10469",
    "addr:street":"Woodhull Ave",
    "iso:country":"US",
    "sg:address":"2232 Woodhull Ave",
    "sg:city":"Bronx",
    "sg:classifiers":[
        {
            "category":"Health Services",
            "subcategory":"Doctor",
            "type":"Services"
        }
    ],
    "sg:phone":"+1 718 881 7990",
    "sg:postcode":"10469",
    "sg:province":"NY",
    "sg:tags":[
        "physician",
        "surgeon"
    ],
    "wof:name":"Ilya V Kaplan MD",
    "wof:placetype":"venue"
},
  "geometry": {"coordinates":[-73.841802,40.858976],"type":"Point"}
}