{
  "type": "Feature",
  "properties": {
    "iso:country":"US",
    "sg:address":"33 Laurel Rd",
    "sg:city":"Pound Ridge",
    "sg:classifiers":[
        {
            "category":"Professional",
            "type":"Services"
        }
    ],
    "sg:phone":"+1 914 764 4072",
    "sg:postcode":"10576",
    "sg:province":"NY",
    "sg:tags":[
        "establishment"
    ],
    "wof:name":"Geocad Inc",
    "wof:placetype":"venue"
},
  "geometry": {"coordinates":[-73.54168199999999,41.206585],"type":"Point"}
}