{
  "type": "Feature",
  "properties": {
    "addr:full":"306 E Hill Rd Canaan NY 12017",
    "addr:housenumber":"306",
    "addr:postcode":"12017",
    "addr:street":"E Hill Rd",
    "iso:country":"US",
    "sg:address":"306 E Hill Rd",
    "sg:city":"Canaan",
    "sg:classifiers":[
        {
            "category":"Personal",
            "subcategory":"Beauty Salon",
            "type":"Services"
        }
    ],
    "sg:phone":"+1   ",
    "sg:postcode":"12017",
    "sg:province":"NY",
    "sg:tags":[
        "shop"
    ],
    "wof:name":"C Richard Salon",
    "wof:placetype":"venue"
},
  "geometry": {"coordinates":[-73.47020500000001,42.30953],"type":"Point"}
}