{
  "type": "Feature",
  "properties": {
    "addr:full":"4770 Transit Rd Depew NY 14043",
    "addr:housenumber":"4770",
    "addr:postcode":"14043",
    "addr:street":"Transit Rd",
    "iso:country":"US",
    "sg:address":"4770 Transit Rd",
    "sg:city":"Depew",
    "sg:classifiers":[
        {
            "category":"Coffee & Tea",
            "type":"Food & Drink"
        }
    ],
    "sg:menulink":"http://www.allmenus.com/ny/cheektowaga/113269-starbucks-coffee/menu/",
    "sg:phone":"+1 716 656 9651",
    "sg:postcode":"14043",
    "sg:province":"NY",
    "sg:tags":[
        "american"
    ],
    "wof:name":"Starbucks Coffee",
    "wof:placetype":"venue"
},
  "geometry": {"coordinates":[-78.697636,42.868249],"type":"Point"}
}