{
  "type": "Feature",
  "properties": {
    "addr:full":"12 Greenwood St Canisteo NY 14823",
    "addr:housenumber":"12",
    "addr:postcode":"14823",
    "addr:street":"Greenwood St",
    "iso:country":"US",
    "sg:address":"12 Greenwood St",
    "sg:city":"Canisteo",
    "sg:classifiers":[
        {
            "category":"Food & Beverages",
            "subcategory":"Bakery",
            "type":"Retail Goods"
        }
    ],
    "sg:phone":"+1   ",
    "sg:postcode":"14823",
    "sg:province":"NY",
    "wof:name":"Towne Talk Bakery",
    "wof:placetype":"venue"
},
  "geometry": {"coordinates":[-77.605716,42.269791],"type":"Point"}
}