{
  "type": "Feature",
  "properties": {
    "addr:full":"55 Colvin Ave Albany NY 12206",
    "addr:housenumber":"55",
    "addr:postcode":"12206",
    "addr:street":"Colvin Ave",
    "iso:country":"US",
    "sg:address":"55 Colvin Ave",
    "sg:city":"Albany",
    "sg:classifiers":[
        {
            "category":"Professional",
            "subcategory":"Lawyer & Legal Services",
            "type":"Services"
        }
    ],
    "sg:phone":"+1 518 462 6765",
    "sg:postcode":"12206",
    "sg:province":"NY",
    "sg:tags":[
        "attorney"
    ],
    "sg:website":"www.legal-aid.org",
    "wof:name":"Legal Aid Society",
    "wof:placetype":"venue"
},
  "geometry": {"coordinates":[-73.795357,42.678455],"type":"Point"}
}