{
  "type": "Feature",
  "properties": {
    "addr:full":"72 Newport St Brooklyn NY 11212",
    "addr:housenumber":"72",
    "addr:postcode":"11212",
    "addr:street":"Newport St",
    "iso:country":"US",
    "sg:address":"72 Newport St",
    "sg:city":"Brooklyn",
    "sg:classifiers":[
        {
            "category":"Personal",
            "subcategory":"Barber",
            "type":"Services"
        }
    ],
    "sg:phone":"+1 718 240 9300",
    "sg:postcode":"11212",
    "sg:province":"NY",
    "wof:name":"Heads R Us",
    "wof:placetype":"venue"
},
  "geometry": {"coordinates":[-73.911897,40.658918],"type":"Point"}
}