{
  "type": "Feature",
  "properties": {
    "iso:country":"US",
    "sg:address":"129 W Main St",
    "sg:city":"Mohawk",
    "sg:classifiers":[
        {
            "category":"Personal",
            "subcategory":"Beauty Salon",
            "type":"Services"
        }
    ],
    "sg:phone":"+1 315 866 7617",
    "sg:postcode":"13407",
    "sg:province":"NY",
    "wof:name":"John Richard's Hair Studio",
    "wof:placetype":"venue"
},
  "geometry": {"coordinates":[-75.01745699999999,43.009637],"type":"Point"}
}