{
  "type": "Feature",
  "properties": {
    "addr:full":"200 Broadway Brooklyn NY 11211",
    "addr:housenumber":"200",
    "addr:postcode":"11211",
    "addr:street":"Broadway",
    "iso:country":"US",
    "sg:address":"200 Broadway",
    "sg:city":"Brooklyn",
    "sg:classifiers":[
        {
            "category":"Building & Trades",
            "subcategory":"Construction",
            "type":"Services"
        }
    ],
    "sg:phone":"+1 718 388 4880",
    "sg:postcode":"11211",
    "sg:province":"NY",
    "sg:tags":[
        "company"
    ],
    "wof:name":"Zsk Contracting Inc",
    "wof:placetype":"venue"
},
  "geometry": {"coordinates":[-73.960696,40.709444],"type":"Point"}
}