{
  "type": "Feature",
  "properties": {
    "addr:full":"2600 Hamburg Tpke Lackawanna NY 14218",
    "addr:housenumber":"2600",
    "addr:postcode":"14218",
    "addr:street":"Hamburg Tpke",
    "iso:country":"US",
    "sg:address":"2600 Hamburg Tpke",
    "sg:city":"Lackawanna",
    "sg:classifiers":[
        {
            "category":"Wholesale",
            "subcategory":"Auto Parts",
            "type":"Manufacturing & Wholesale Goods"
        }
    ],
    "sg:phone":"+1 716 825 8515",
    "sg:postcode":"14218",
    "sg:province":"NY",
    "sg:tags":[
        "automobile",
        "supply"
    ],
    "sg:website":"www.wdautoparts.com",
    "wof:name":"World Discounts",
    "wof:placetype":"venue"
},
  "geometry": {"coordinates":[-78.84523799999999,42.812559],"type":"Point"}
}