{
  "type": "Feature",
  "properties": {
    "addr:full":"448 Middle Country Rd Selden NY 11784",
    "addr:housenumber":"448",
    "addr:postcode":"11784",
    "addr:street":"Middle Country Rd",
    "iso:country":"US",
    "sg:address":"448 Middle Country Rd",
    "sg:city":"Selden",
    "sg:classifiers":[
        {
            "category":"Building & Trades",
            "subcategory":"Construction",
            "type":"Services"
        }
    ],
    "sg:phone":"+1 631 696 1046",
    "sg:postcode":"11784",
    "sg:province":"NY",
    "sg:tags":[
        "general",
        "contractor"
    ],
    "wof:name":"Michael Borrato Gen Cntrctng",
    "wof:placetype":"venue"
},
  "geometry": {"coordinates":[-73.03054,40.867197],"type":"Point"}
}