{
  "type": "Feature",
  "properties": {
    "addr:full":"700 Main St E Rochester NY 14604",
    "addr:housenumber":"700",
    "addr:postcode":"14604",
    "addr:street":"Main St E",
    "iso:country":"US",
    "sg:address":"700 Main St E",
    "sg:city":"Rochester",
    "sg:classifiers":[
        {
            "category":"Professional",
            "subcategory":"Lawyer & Legal Services",
            "type":"Services"
        }
    ],
    "sg:phone":"+1   ",
    "sg:postcode":"14604",
    "sg:province":"NY",
    "wof:name":"Tribbet Lenweaver Sulzer",
    "wof:placetype":"venue"
},
  "geometry": {"coordinates":[-77.59161899999999,43.160436],"type":"Point"}
}