{
  "type": "Feature",
  "properties": {
    "addr:full":"6110 Roosevelt Avenue Woodside NY 11377",
    "addr:housenumber":"6110",
    "addr:postcode":"11377",
    "addr:street":"Roosevelt Avenue",
    "iso:country":"US",
    "sg:address":"6110 Roosevelt Avenue",
    "sg:city":"Woodside",
    "sg:classifiers":[
        {
            "category":"Bakery",
            "type":"Food & Drink"
        }
    ],
    "sg:phone":"+1 718 651 1617",
    "sg:postcode":"11377",
    "sg:province":"NY",
    "wof:name":"Colombiana Bakery",
    "wof:placetype":"venue"
},
  "geometry": {"coordinates":[-73.90283599999999,40.745763],"type":"Point"}
}