{
  "type": "Feature",
  "properties": {
    "addr:full":"163 High Park Blvd Buffalo NY 14226",
    "addr:housenumber":"163",
    "addr:postcode":"14226",
    "addr:street":"High Park Blvd",
    "iso:country":"US",
    "sg:address":"163 High Park Blvd",
    "sg:city":"Buffalo",
    "sg:classifiers":[
        {
            "category":"Wholesale",
            "subcategory":"Non-durable Goods",
            "type":"Manufacturing & Wholesale Goods"
        }
    ],
    "sg:phone":"+1 716 834 0860",
    "sg:postcode":"14226",
    "sg:province":"NY",
    "wof:name":"Mortimer Spiller Co Inc",
    "wof:placetype":"venue"
},
  "geometry": {"coordinates":[-78.800506,42.961116],"type":"Point"}
}