{
  "type": "Feature",
  "properties": {
    "iso:country":"US",
    "sg:address":"111 W 94 St",
    "sg:city":"New York",
    "sg:classifiers":[
        {
            "category":"Retail",
            "subcategory":"Repair Shop",
            "type":"Services"
        }
    ],
    "sg:phone":"+1 646 224 0963",
    "sg:postcode":"10025",
    "sg:province":"NY",
    "sg:tags":[
        "lock",
        "locksmith"
    ],
    "wof:name":"Number 1 Emergency A Locksmith",
    "wof:placetype":"venue"
},
  "geometry": {"coordinates":[-73.96846499999999,40.791562],"type":"Point"}
}