{
  "type": "Feature",
  "properties": {
    "iso:country":"US",
    "sg:address":"60 Lincoln Ave",
    "sg:city":"Rochester",
    "sg:classifiers":[
        {
            "category":"Personal",
            "subcategory":"Beauty Salon",
            "type":"Services"
        }
    ],
    "sg:phone":"+1 585 235 3560",
    "sg:postcode":"14611",
    "sg:province":"NY",
    "sg:tags":[
        "manicuring"
    ],
    "wof:name":"Deborah Nails",
    "wof:placetype":"venue"
},
  "geometry": {"coordinates":[-77.65573999999999,43.148088],"type":"Point"}
}