{
  "type": "Feature",
  "properties": {
    "iso:country":"US",
    "sg:address":"8279 US Hwy 11",
    "sg:city":"Cicero",
    "sg:classifiers":[
        {
            "category":"Home & Garden",
            "subcategory":"Garden Supply",
            "type":"Retail Goods"
        }
    ],
    "sg:phone":"+1   ",
    "sg:postcode":"13039",
    "sg:province":"NY",
    "sg:tags":[
        "repair",
        "lawn",
        "parts",
        "equipment"
    ],
    "wof:name":"North Syracuse Lawn & Snow",
    "wof:placetype":"venue"
},
  "geometry": {"coordinates":[-76.117267,43.169041],"type":"Point"}
}