{
  "type": "Feature",
  "properties": {
    "addr:full":"7475 Route 474 Panama NY 14767",
    "addr:housenumber":"7475",
    "addr:postcode":"14767",
    "addr:street":"Route 474",
    "iso:country":"US",
    "sg:address":"7475 Route 474",
    "sg:city":"Panama",
    "sg:classifiers":[
        {
            "category":"Professional",
            "subcategory":"Lawyer & Legal Services",
            "type":"Services"
        }
    ],
    "sg:phone":"+1 716 782 3609",
    "sg:postcode":"14767",
    "sg:province":"NY",
    "sg:tags":[
        "plan"
    ],
    "wof:name":"John Uria Yoder",
    "wof:placetype":"venue"
},
  "geometry": {"coordinates":[-79.54479000000001,42.07484],"type":"Point"}
}