{
  "type": "Feature",
  "properties": {
    "iso:country":"US",
    "sg:address":"2273 65th Street",
    "sg:city":"Brooklyn",
    "sg:classifiers":[
        {
            "category":"Health Services",
            "subcategory":"Doctor",
            "type":"Services"
        }
    ],
    "sg:phone":"+1 718 236 4970",
    "sg:postcode":"11204",
    "sg:province":"NY",
    "wof:name":"Benson Medical PC",
    "wof:placetype":"venue"
},
  "geometry": {"coordinates":[-73.979292,40.612711],"type":"Point"}
}