{
  "type": "Feature",
  "properties": {
    "iso:country":"US",
    "sg:address":"316 McClellan Ave",
    "sg:city":"Mount Vernon",
    "sg:classifiers":[
        {
            "category":"Banks & Credit Unions",
            "subcategory":"Financial Services",
            "type":"Services"
        }
    ],
    "sg:phone":"+1 914 667 9002",
    "sg:postcode":"10553",
    "sg:province":"NY",
    "sg:tags":[
        "company",
        "holding"
    ],
    "wof:name":"Real Estate Holdings LLC",
    "wof:placetype":"venue"
},
  "geometry": {"coordinates":[-73.817115,40.905333],"type":"Point"}
}