{
  "type": "Feature",
  "properties": {
    "iso:country":"US",
    "sg:address":"80 Jennings Ave",
    "sg:city":"Patchogue",
    "sg:classifiers":[
        {
            "category":"Real Estate",
            "subcategory":"Developer",
            "type":"Services"
        }
    ],
    "sg:phone":"+1 631 447 1971",
    "sg:postcode":"11772",
    "sg:province":"NY",
    "sg:tags":[
        "cemetery"
    ],
    "wof:name":"Cedar Grove Cemetery Assoc",
    "wof:placetype":"venue"
},
  "geometry": {"coordinates":[-73.01678699999999,40.769762],"type":"Point"}
}