{
  "type": "Feature",
  "properties": {
    "addr:full":"515 Union Ave Westbury NY 11590",
    "addr:housenumber":"515",
    "addr:postcode":"11590",
    "addr:street":"Union Ave",
    "iso:country":"US",
    "sg:address":"515 Union Ave",
    "sg:city":"Westbury",
    "sg:classifiers":[
        {
            "category":"Food & Beverages",
            "subcategory":"Groceries & Convenience Stores",
            "type":"Retail Goods"
        }
    ],
    "sg:phone":"+1 516 876 8980",
    "sg:postcode":"11590",
    "sg:province":"NY",
    "wof:name":"Los Primos Grocery",
    "wof:placetype":"venue"
},
  "geometry": {"coordinates":[-73.580264,40.757241],"type":"Point"}
}