{
  "type": "Feature",
  "properties": {
    "addr:full":"21 Old Main St Ste 201 Fishkill NY 12524",
    "addr:housenumber":"21",
    "addr:postcode":"12524",
    "addr:street":"Old Main St Ste 201",
    "iso:country":"US",
    "sg:address":"21 Old Main St Ste 201",
    "sg:city":"Fishkill",
    "sg:classifiers":[
        {
            "category":"Banks & Credit Unions",
            "subcategory":"Investment Brokerage",
            "type":"Services"
        },
        {
            "category":"Banks & Credit Unions",
            "subcategory":"Financial Services",
            "type":"Services"
        }
    ],
    "sg:phone":"+1 845 896 7520",
    "sg:postcode":"12524",
    "sg:province":"NY",
    "sg:tags":[
        "investing",
        "advising"
    ],
    "sg:website":"www.ameripriseadvisors.com",
    "wof:name":"Ameriprise Financial Advisors - Ellis & Associates",
    "wof:placetype":"venue"
},
  "geometry": {"coordinates":[-73.89618400000001,41.533736],"type":"Point"}
}