{
  "type": "Feature",
  "properties": {
    "addr:full":"53 Main St Delhi NY 13753",
    "addr:housenumber":"53",
    "addr:postcode":"13753",
    "addr:street":"Main St",
    "iso:country":"US",
    "sg:address":"53 Main St",
    "sg:city":"Delhi",
    "sg:classifiers":[
        {
            "category":"Food & Beverages",
            "subcategory":"Groceries & Convenience Stores",
            "type":"Retail Goods"
        }
    ],
    "sg:phone":"+1   ",
    "sg:postcode":"13753",
    "sg:province":"NY",
    "sg:tags":[
        "eating"
    ],
    "wof:name":"Good Cheap Food",
    "wof:placetype":"venue"
},
  "geometry": {"coordinates":[-74.92059999999999,42.274407],"type":"Point"}
}