{
  "type": "Feature",
  "properties": {
    "addr:full":"4141 24th St Long Island City NY 11101",
    "addr:housenumber":"4141",
    "addr:postcode":"11101",
    "addr:street":"24Th St",
    "iso:country":"US",
    "sg:address":"4141 24th St",
    "sg:city":"Long Island City",
    "sg:classifiers":[
        {
            "category":"Professional",
            "subcategory":"Employment Agencies",
            "type":"Services"
        }
    ],
    "sg:phone":"+1 718 391 0091",
    "sg:postcode":"11101",
    "sg:province":"NY",
    "wof:name":"Aegis Staffing Inc",
    "wof:placetype":"venue"
},
  "geometry": {"coordinates":[-73.940804,40.751499],"type":"Point"}
}