{
  "type": "Feature",
  "properties": {
    "iso:country":"US",
    "sg:address":"5 Greenfield Ave",
    "sg:city":"Ballston Spa",
    "sg:classifiers":[
        {
            "category":"Personal",
            "subcategory":"Beauty Salon",
            "type":"Services"
        }
    ],
    "sg:phone":"+1 518 885 6685",
    "sg:postcode":"12020",
    "sg:province":"NY",
    "wof:name":"Connie's Clippers",
    "wof:placetype":"venue"
},
  "geometry": {"coordinates":[-73.856768,43.014644],"type":"Point"}
}