{
  "type": "Feature",
  "properties": {
    "addr:full":"2845 Frederick Douglass Blvd New York NY 10039",
    "addr:housenumber":"2845",
    "addr:postcode":"10039",
    "addr:street":"Frederick Douglass Blvd",
    "iso:country":"US",
    "sg:address":"2845 Frederick Douglass Blvd",
    "sg:city":"New York",
    "sg:classifiers":[
        {
            "category":"Food & Beverages",
            "subcategory":"Liquor & Beverages",
            "type":"Retail Goods"
        }
    ],
    "sg:phone":"+1 212 926 8050",
    "sg:postcode":"10039",
    "sg:province":"NY",
    "sg:tags":[
        "beer",
        "spirit",
        "wine"
    ],
    "wof:name":"151 Liquor",
    "wof:placetype":"venue"
},
  "geometry": {"coordinates":[-73.938959,40.827162],"type":"Point"}
}