{
  "type": "Feature",
  "properties": {
    "addr:full":"197 E 76 St New York NY 10021",
    "addr:housenumber":"197;76",
    "addr:postcode":"10021",
    "addr:street":"E;St",
    "iso:country":"US",
    "sg:address":"197 E 76 St",
    "sg:city":"New York",
    "sg:classifiers":[
        {
            "category":"Shopping",
            "subcategory":"Gifts & Souvenirs",
            "type":"Retail Goods"
        }
    ],
    "sg:phone":"+1 212 452 3026",
    "sg:postcode":"10021",
    "sg:province":"NY",
    "sg:tags":[
        "basket",
        "parcel"
    ],
    "wof:name":"Fill-R-Up",
    "wof:placetype":"venue"
},
  "geometry": {"coordinates":[-73.95984900000001,40.773048],"type":"Point"}
}