{
  "type": "Feature",
  "properties": {
    "iso:country":"US",
    "sg:address":"84 Broadway",
    "sg:city":"Greenlawn",
    "sg:classifiers":[
        {
            "category":"Cinema",
            "subcategory":"Movie Rental",
            "type":"Entertainment"
        },
        {
            "category":"Shopping",
            "subcategory":"Computers & Home Electronics",
            "type":"Retail Goods"
        }
    ],
    "sg:phone":"+1 631 261 9062",
    "sg:postcode":"11740",
    "sg:province":"NY",
    "sg:tags":[
        "game",
        "video"
    ],
    "wof:name":"Greenlawn Video",
    "wof:placetype":"venue"
},
  "geometry": {"coordinates":[-73.364502,40.866798],"type":"Point"}
}