{
  "type": "Feature",
  "properties": {
    "addr:full":"82 Emerson Pl Brooklyn NY 11205",
    "addr:housenumber":"82",
    "addr:postcode":"11205",
    "addr:street":"Emerson Pl",
    "iso:country":"US",
    "sg:address":"82 Emerson Pl",
    "sg:city":"Brooklyn",
    "sg:classifiers":[
        {
            "category":"Retail",
            "subcategory":"Auto Repair",
            "type":"Services"
        }
    ],
    "sg:phone":"+1   ",
    "sg:postcode":"11205",
    "sg:province":"NY",
    "sg:tags":[
        "automotive"
    ],
    "wof:name":"Evironmental Protection Agency",
    "wof:placetype":"venue"
},
  "geometry": {"coordinates":[-73.962412,40.694711],"type":"Point"}
}