{
  "type": "Feature",
  "properties": {
    "iso:country":"US",
    "sg:address":"25 Woodland Rd",
    "sg:city":"Mahopac",
    "sg:classifiers":[
        {
            "category":"Building & Trades",
            "subcategory":"Construction",
            "type":"Services"
        }
    ],
    "sg:phone":"+1 845 628 7730",
    "sg:postcode":"10541",
    "sg:province":"NY",
    "sg:tags":[
        "general",
        "contractor"
    ],
    "wof:name":"Robert Kraus Construction",
    "wof:placetype":"venue"
},
  "geometry": {"coordinates":[-73.75606500000001,41.375385],"type":"Point"}
}