{
  "type": "Feature",
  "properties": {
    "iso:country":"US",
    "sg:address":"405 E 42nd St",
    "sg:city":"New York",
    "sg:classifiers":[
        {
            "category":"Communications",
            "subcategory":"News Services",
            "type":"Services"
        }
    ],
    "sg:phone":"+1 212 319 6626",
    "sg:postcode":"10017",
    "sg:province":"NY",
    "wof:name":"German Press",
    "wof:placetype":"venue"
},
  "geometry": {"coordinates":[-73.96835299999999,40.748266],"type":"Point"}
}