{
  "type": "Feature",
  "properties": {
    "iso:country":"US",
    "sg:address":"78 W Main St",
    "sg:city":"Sidney",
    "sg:classifiers":[
        {
            "category":"Professional",
            "type":"Services"
        }
    ],
    "sg:phone":"+1 607 563 3470",
    "sg:postcode":"13838",
    "sg:province":"NY",
    "sg:tags":[
        "establishment"
    ],
    "wof:name":"Prospicience Group",
    "wof:placetype":"venue"
},
  "geometry": {"coordinates":[-75.38900099999999,42.305692],"type":"Point"}
}