{
  "type": "Feature",
  "properties": {
    "addr:full":"3 White Oak Ct Greenfield Ctr NY 12833",
    "addr:housenumber":"3",
    "addr:postcode":"12833",
    "addr:street":"White Oak Ct",
    "iso:country":"US",
    "sg:address":"3 White Oak Ct",
    "sg:city":"Greenfield Ctr",
    "sg:classifiers":[
        {
            "category":"Professional",
            "subcategory":"Accounting & Tax Preparation",
            "type":"Services"
        }
    ],
    "sg:phone":"+1 518 226 0267",
    "sg:postcode":"12833",
    "sg:province":"NY",
    "sg:tags":[
        "billing"
    ],
    "wof:name":"Practice Builders Inc",
    "wof:placetype":"venue"
},
  "geometry": {"coordinates":[-73.904444,43.095004],"type":"Point"}
}