{
  "type": "Feature",
  "properties": {
    "addr:full":"31 Warsoff Pl Brooklyn NY 11205",
    "addr:housenumber":"31",
    "addr:postcode":"11205",
    "addr:street":"Warsoff Pl",
    "iso:country":"US",
    "sg:address":"31 Warsoff Pl",
    "sg:city":"Brooklyn",
    "sg:classifiers":[
        {
            "category":"Home & Garden",
            "subcategory":"Building Materials",
            "type":"Retail Goods"
        }
    ],
    "sg:phone":"+1 212 302 6688",
    "sg:postcode":"11205",
    "sg:province":"NY",
    "sg:tags":[
        "supply"
    ],
    "sg:website":"a1foamspray.com/",
    "wof:name":"A1 Foam Spray Insulation",
    "wof:placetype":"venue"
},
  "geometry": {"coordinates":[-73.95405700000001,40.698225],"type":"Point"}
}