{
  "type": "Feature",
  "properties": {
    "addr:full":"5734 Myrtle Ave Ridgewood NY 11385",
    "addr:housenumber":"5734",
    "addr:postcode":"11385",
    "addr:street":"Myrtle Ave",
    "iso:country":"US",
    "sg:address":"5734 Myrtle Ave",
    "sg:city":"Ridgewood",
    "sg:classifiers":[
        {
            "category":"Shopping",
            "subcategory":"Shoes",
            "type":"Retail Goods"
        }
    ],
    "sg:phone":"+1 718 366 7068",
    "sg:postcode":"11385",
    "sg:province":"NY",
    "sg:tags":[
        "store"
    ],
    "wof:name":"J & M Sneakers",
    "wof:placetype":"venue"
},
  "geometry": {"coordinates":[-73.902427,40.700352],"type":"Point"}
}