{
  "type": "Feature",
  "properties": {
    "addr:full":"1756 Bushwick Avenue Brooklyn NY 11207",
    "addr:housenumber":"1756",
    "addr:postcode":"11207",
    "addr:street":"Bushwick Avenue",
    "iso:country":"US",
    "sg:address":"1756 Bushwick Avenue",
    "sg:city":"Brooklyn",
    "sg:classifiers":[
        {
            "category":"Autos & Motor Vehicles",
            "subcategory":"Fuel & Gas Station",
            "type":"Retail Goods"
        }
    ],
    "sg:phone":"+1 718 240 9046",
    "sg:postcode":"11207",
    "sg:province":"NY",
    "wof:name":"Bushwick Auto Repair",
    "wof:placetype":"venue"
},
  "geometry": {"coordinates":[-73.898946,40.678642],"type":"Point"}
}