{
  "type": "Feature",
  "properties": {
    "addr:full":"31 Fisk St Red Hook NY 12571",
    "addr:housenumber":"31",
    "addr:postcode":"12571",
    "addr:street":"Fisk St",
    "iso:country":"US",
    "sg:address":"31 Fisk St",
    "sg:city":"Red Hook",
    "sg:classifiers":[
        {
            "category":"Building & Trades",
            "subcategory":"Plumbing",
            "type":"Services"
        }
    ],
    "sg:phone":"+1 845 758 6389",
    "sg:postcode":"12571",
    "sg:province":"NY",
    "sg:tags":[
        "repair",
        "contractor"
    ],
    "wof:name":"Professional Sewer & Drain Clg",
    "wof:placetype":"venue"
},
  "geometry": {"coordinates":[-73.87259299999999,41.991431],"type":"Point"}
}