{
  "type": "Feature",
  "properties": {
    "addr:full":"1143 Cook St Dannemora NY 12929",
    "addr:housenumber":"1143",
    "addr:postcode":"12929",
    "addr:street":"Cook St",
    "iso:country":"US",
    "sg:address":"1143 Cook St",
    "sg:city":"Dannemora",
    "sg:classifiers":[
        {
            "category":"Restaurant",
            "type":"Food & Drink"
        }
    ],
    "sg:phone":"+1 518 492 7719",
    "sg:postcode":"12929",
    "sg:province":"NY",
    "sg:tags":[
        "eating"
    ],
    "wof:name":"Windchimes Restaurant",
    "wof:placetype":"venue"
},
  "geometry": {"coordinates":[-73.72335699999999,44.721648],"type":"Point"}
}