{
  "type": "Feature",
  "properties": {
    "addr:full":"891 Jayne Pl Baldwin NY 11510",
    "addr:housenumber":"891",
    "addr:postcode":"11510",
    "addr:street":"Jayne Pl",
    "iso:country":"US",
    "sg:address":"891 Jayne Pl",
    "sg:city":"Baldwin",
    "sg:classifiers":[
        {
            "category":"Banks & Credit Unions",
            "subcategory":"Bank",
            "type":"Services"
        }
    ],
    "sg:phone":"+1 516 377 3477",
    "sg:postcode":"11510",
    "sg:province":"NY",
    "sg:tags":[
        "mortgage"
    ],
    "wof:name":"Skyline Mortgage",
    "wof:placetype":"venue"
},
  "geometry": {"coordinates":[-73.605857,40.658398],"type":"Point"}
}