{
  "type": "Feature",
  "properties": {
    "iso:country":"US",
    "sg:address":"145 Riverside Dr",
    "sg:city":"Binghamton",
    "sg:classifiers":[
        {
            "category":"Insurance",
            "subcategory":"Hazard Insurance",
            "type":"Services"
        },
        {
            "category":"Insurance",
            "subcategory":"Insurance Agent",
            "type":"Services"
        },
        {
            "category":"Insurance",
            "subcategory":"Life Insurance",
            "type":"Services"
        },
        {
            "category":"Insurance",
            "subcategory":"Title Insurance",
            "type":"Services"
        }
    ],
    "sg:phone":"+1 607 722 6479",
    "sg:postcode":"13905",
    "sg:province":"NY",
    "sg:tags":[
        "auto",
        "homeowner"
    ],
    "sg:website":"http://www.nationwide.com/agent/Binghamton-NEW-YORK-insurance-agent/sherry-barton/office.html",
    "wof:name":"Sherry L Barton - Nationwide Insurance",
    "wof:placetype":"venue"
},
  "geometry": {"coordinates":[-75.932861,42.092159],"type":"Point"}
}