{
  "type": "Feature",
  "properties": {
    "iso:country":"US",
    "sg:address":"265 Schuurman Rd",
    "sg:city":"Castletn On Hdsn",
    "sg:classifiers":[
        {
            "category":"Professional",
            "type":"Services"
        }
    ],
    "sg:phone":"+1 518 459 1462",
    "sg:postcode":"12033",
    "sg:province":"NY",
    "sg:tags":[
        "establishment"
    ],
    "wof:name":"NYCE Corp",
    "wof:placetype":"venue"
},
  "geometry": {"coordinates":[-73.70576199999999,42.560306],"type":"Point"}
}