{
  "type": "Feature",
  "properties": {
    "iso:country":"US",
    "sg:address":"204 Jericho Tpke",
    "sg:city":"Floral Park",
    "sg:classifiers":[
        {
            "category":"Autos & Motor Vehicles",
            "subcategory":"Automobile Sales",
            "type":"Retail Goods"
        }
    ],
    "sg:phone":"+1 646 217 4414",
    "sg:postcode":"11001",
    "sg:province":"NY",
    "sg:tags":[
        "limo"
    ],
    "sg:website":"www.mavriktrans.net/?UBL=TRUE",
    "wof:name":"Mavrik Transportation",
    "wof:placetype":"venue"
},
  "geometry": {"coordinates":[-73.70335300000001,40.728545],"type":"Point"}
}