{
  "type": "Feature",
  "properties": {
    "addr:full":"506 6th St Brooklyn NY 11215",
    "addr:housenumber":"506",
    "addr:postcode":"11215",
    "addr:street":"6Th St",
    "iso:country":"US",
    "sg:address":"506 6th St",
    "sg:city":"Brooklyn",
    "sg:classifiers":[
        {
            "category":"Health Services",
            "subcategory":"Hospital",
            "type":"Services"
        }
    ],
    "sg:phone":"+1 718 499 2273",
    "sg:postcode":"11215",
    "sg:province":"NY",
    "sg:tags":[
        "doctor"
    ],
    "sg:website":"www.nym.org",
    "wof:name":"Nym New York Methodist Hospital",
    "wof:placetype":"venue"
},
  "geometry": {"coordinates":[-73.979202,40.668201],"type":"Point"}
}