{
  "type": "Feature",
  "properties": {
    "iso:country":"US",
    "sg:address":"2611 Middle Country Rd",
    "sg:city":"Centereach",
    "sg:classifiers":[
        {
            "category":"Home & Garden",
            "subcategory":"Household Appliances",
            "type":"Retail Goods"
        }
    ],
    "sg:phone":"+1 631 580 4822",
    "sg:postcode":"11720",
    "sg:province":"NY",
    "sg:tags":[
        "cleaners",
        "parts",
        "vacuum"
    ],
    "wof:name":"MPR",
    "wof:placetype":"venue"
},
  "geometry": {"coordinates":[-73.105001,40.858505],"type":"Point"}
}