{
  "type": "Feature",
  "properties": {
    "iso:country":"US",
    "sg:address":"501 Main Street",
    "sg:city":"Islip",
    "sg:classifiers":[
        {
            "category":"Restaurant",
            "type":"Food & Drink"
        }
    ],
    "sg:phone":"+1 631 210 0011",
    "sg:postcode":"11751",
    "sg:province":"NY",
    "sg:tags":[
        "new",
        "american"
    ],
    "wof:name":"Maxwell's",
    "wof:placetype":"venue"
},
  "geometry": {"coordinates":[-73.21404699999999,40.729378],"type":"Point"}
}