{
  "type": "Feature",
  "properties": {
    "iso:country":"US",
    "sg:address":"373 Broadway",
    "sg:city":"New York",
    "sg:classifiers":[
        {
            "category":"Professional",
            "subcategory":"Accounting & Tax Preparation",
            "type":"Services"
        }
    ],
    "sg:phone":"+1 212 431 8283",
    "sg:postcode":"10013",
    "sg:province":"NY",
    "sg:tags":[
        "accountant"
    ],
    "wof:name":"Mo & Cheng",
    "wof:placetype":"venue"
},
  "geometry": {"coordinates":[-74.00327799999999,40.717787],"type":"Point"}
}