{
  "type": "Feature",
  "properties": {
    "addr:full":"16 W 22 St New York NY 10010",
    "addr:housenumber":"16",
    "addr:postcode":"10010",
    "addr:street":"W 22 St",
    "iso:country":"US",
    "sg:address":"16 W 22 St",
    "sg:city":"New York",
    "sg:classifiers":[
        {
            "category":"Professional",
            "subcategory":"Research",
            "type":"Services"
        }
    ],
    "sg:phone":"+1   ",
    "sg:postcode":"10010",
    "sg:province":"NY",
    "sg:tags":[
        "organization",
        "noncommercial"
    ],
    "wof:name":"Embrace Foundation",
    "wof:placetype":"venue"
},
  "geometry": {"coordinates":[-73.99297199999999,40.74197],"type":"Point"}
}