{
  "type": "Feature",
  "properties": {
    "iso:country":"US",
    "sg:address":"25 Little Plains Rd",
    "sg:city":"Huntington",
    "sg:classifiers":[
        {
            "category":"Social Services",
            "type":"Services"
        }
    ],
    "sg:phone":"+1 631 979 9860",
    "sg:postcode":"11743",
    "sg:province":"NY",
    "sg:tags":[
        "organization",
        "welfare"
    ],
    "wof:name":"DDI Directions Case Mgmt",
    "wof:placetype":"venue"
},
  "geometry": {"coordinates":[-73.379183,40.850922],"type":"Point"}
}