{
  "type": "Feature",
  "properties": {
    "iso:country":"US",
    "sg:address":"6 Gramatan Ave",
    "sg:city":"Mt Vernon",
    "sg:classifiers":[
        {
            "category":"Banks & Credit Unions",
            "subcategory":"Bank",
            "type":"Services"
        }
    ],
    "sg:phone":"+1 914 668 9143",
    "sg:postcode":"10550",
    "sg:province":"NY",
    "sg:tags":[
        "loan",
        "real estate"
    ],
    "wof:name":"Prestige Realtors",
    "wof:placetype":"venue"
},
  "geometry": {"coordinates":[-73.837374,40.912646],"type":"Point"}
}