{
  "type": "Feature",
  "properties": {
    "addr:full":"31 Keating Pl Staten Island NY 10314",
    "addr:housenumber":"31",
    "addr:postcode":"10314",
    "addr:street":"Keating Pl",
    "iso:country":"US",
    "sg:address":"31 Keating Pl",
    "sg:city":"Staten Island",
    "sg:classifiers":[
        {
            "category":"Building & Trades",
            "subcategory":"Electrical",
            "type":"Services"
        }
    ],
    "sg:phone":"+1 718 983 9858",
    "sg:postcode":"10314",
    "sg:province":"NY",
    "sg:tags":[
        "electrical",
        "contractor"
    ],
    "wof:name":"Safe & Sound Alarms Inc",
    "wof:placetype":"venue"
},
  "geometry": {"coordinates":[-74.15493499999999,40.593036],"type":"Point"}
}