{
  "type": "Feature",
  "properties": {
    "addr:full":"1049 Liberty Ave Brooklyn NY 11208",
    "addr:housenumber":"1049",
    "addr:postcode":"11208",
    "addr:street":"Liberty Ave",
    "iso:country":"US",
    "sg:address":"1049 Liberty Ave",
    "sg:city":"Brooklyn",
    "sg:classifiers":[
        {
            "category":"Shopping",
            "subcategory":"Crafts & Fabrics",
            "type":"Retail Goods"
        }
    ],
    "sg:phone":"+1 718 277 9337",
    "sg:postcode":"11208",
    "sg:province":"NY",
    "sg:tags":[
        "store"
    ],
    "wof:name":"Nahid Fabrics",
    "wof:placetype":"venue"
},
  "geometry": {"coordinates":[-73.870394,40.678425],"type":"Point"}
}