{
  "type": "Feature",
  "properties": {
    "iso:country":"US",
    "sg:address":"16 Cross St",
    "sg:city":"Falconer",
    "sg:classifiers":[
        {
            "category":"Shopping",
            "subcategory":"Clothing, Apparel, & Fashions",
            "type":"Retail Goods"
        }
    ],
    "sg:phone":"+1 716 487 2600",
    "sg:postcode":"14733",
    "sg:province":"NY",
    "sg:tags":[
        "uniform"
    ],
    "wof:name":"Doritex Corp",
    "wof:placetype":"venue"
},
  "geometry": {"coordinates":[-79.19123399999999,42.117123],"type":"Point"}
}