{
  "type": "Feature",
  "properties": {
    "iso:country":"US",
    "sg:address":"136 Northern Blvd",
    "sg:city":"Great Neck",
    "sg:classifiers":[
        {
            "category":"Cinema",
            "subcategory":"Movie Rental",
            "type":"Entertainment"
        }
    ],
    "sg:phone":"+1 516 487 6752",
    "sg:postcode":"11021",
    "sg:province":"NY",
    "sg:tags":[
        "leasing",
        "video",
        "disc",
        "tape"
    ],
    "sg:website":"www.blockbuster.com",
    "wof:name":"Blockbuster Video",
    "wof:placetype":"venue"
},
  "geometry": {"coordinates":[-73.73028499999999,40.775546],"type":"Point"}
}