{
  "type": "Feature",
  "properties": {
    "iso:country":"US",
    "sg:address":"179 Bay Ridge Ave",
    "sg:city":"Brooklyn",
    "sg:classifiers":[
        {
            "category":"Building & Trades",
            "subcategory":"Plumbing",
            "type":"Services"
        }
    ],
    "sg:phone":"+1 718 317 9576",
    "sg:postcode":"11220",
    "sg:province":"NY",
    "sg:tags":[
        "plumbing",
        "contractor"
    ],
    "wof:name":"Rennie Inc",
    "wof:placetype":"venue"
},
  "geometry": {"coordinates":[-74.030089,40.637213],"type":"Point"}
}