{
  "type": "Feature",
  "properties": {
    "iso:country":"US",
    "sg:address":"1213 Jacob St",
    "sg:city":"Troy",
    "sg:classifiers":[
        {
            "category":"Restaurant",
            "type":"Food & Drink"
        }
    ],
    "sg:phone":"+1 518 235 1709",
    "sg:postcode":"12180",
    "sg:province":"NY",
    "wof:name":"Henry's Restaurant",
    "wof:placetype":"venue"
},
  "geometry": {"coordinates":[-73.67824400000001,42.734486],"type":"Point"}
}