{
  "type": "Feature",
  "properties": {
    "addr:full":"400 Madison Ave Frnt B New York NY 10017",
    "addr:housenumber":"400",
    "addr:postcode":"10017",
    "addr:street":"Madison Ave;B",
    "iso:country":"US",
    "sg:address":"400 Madison Ave Frnt B",
    "sg:city":"New York",
    "sg:classifiers":[
        {
            "category":"Shopping",
            "subcategory":"Jewelry",
            "type":"Retail Goods"
        }
    ],
    "sg:phone":"+1 212 644 4100",
    "sg:postcode":"10017",
    "sg:province":"NY",
    "wof:name":"Madison Jewelers",
    "wof:placetype":"venue"
},
  "geometry": {"coordinates":[-73.977075,40.756061],"type":"Point"}
}