{
  "type": "Feature",
  "properties": {
    "addr:full":"46 Beard St Brooklyn NY 11231",
    "addr:housenumber":"46",
    "addr:postcode":"11231",
    "addr:street":"Beard St",
    "iso:country":"US",
    "sg:address":"46 Beard St",
    "sg:city":"Brooklyn",
    "sg:classifiers":[
        {
            "category":"Bars & Pubs",
            "subcategory":"Dive Bar",
            "type":"Food & Drink"
        }
    ],
    "sg:phone":"+1 718 858 9822",
    "sg:postcode":"11231",
    "sg:province":"NY",
    "wof:name":"Lillies Bar",
    "wof:placetype":"venue"
},
  "geometry": {"coordinates":[-74.01190200000001,40.673],"type":"Point"}
}