{
  "type": "Feature",
  "properties": {
    "iso:country":"US",
    "sg:address":"26 Century Hill Dr",
    "sg:city":"Latham",
    "sg:classifiers":[
        {
            "category":"Real Estate",
            "subcategory":"Real Estate Agent",
            "type":"Services"
        }
    ],
    "sg:phone":"+1 518 783 2100",
    "sg:postcode":"12110",
    "sg:province":"NY",
    "wof:name":"KNC Holdings",
    "wof:placetype":"venue"
},
  "geometry": {"coordinates":[-73.75798899999999,42.771387],"type":"Point"}
}