{
  "type": "Feature",
  "properties": {
    "iso:country":"US",
    "sg:address":"91 Union Ave",
    "sg:city":"Islip",
    "sg:classifiers":[
        {
            "category":"Building & Trades",
            "subcategory":"Construction",
            "type":"Services"
        }
    ],
    "sg:phone":"+1 631 859 3191",
    "sg:postcode":"11751",
    "sg:province":"NY",
    "sg:tags":[
        "contractor"
    ],
    "wof:name":"Isle Installations",
    "wof:placetype":"venue"
},
  "geometry": {"coordinates":[-73.212782,40.726228],"type":"Point"}
}