{
  "type": "Feature",
  "properties": {
    "iso:country":"US",
    "sg:address":"175 W 12th Street Apt 16G",
    "sg:city":"New York",
    "sg:classifiers":[
        {
            "category":"Shopping",
            "subcategory":"Beauty & Cosmetics",
            "type":"Retail Goods"
        }
    ],
    "sg:phone":"+1 212 989 8073",
    "sg:postcode":"10011",
    "sg:province":"NY",
    "sg:tags":[
        "supply"
    ],
    "wof:name":"Beauty Without Cruelty",
    "wof:placetype":"venue"
},
  "geometry": {"coordinates":[-74.000072,40.736997],"type":"Point"}
}