{
  "type": "Feature",
  "properties": {
    "iso:country":"US",
    "sg:address":"1643 Genesee St",
    "sg:city":"Utica",
    "sg:classifiers":[
        {
            "category":"Social Services",
            "type":"Services"
        }
    ],
    "sg:phone":"+1 315 724 5173",
    "sg:postcode":"13501",
    "sg:province":"NY",
    "sg:tags":[
        "health",
        "specialty",
        "outpatient"
    ],
    "wof:name":"Samartan Cnseling Ctr of Mohaw",
    "wof:placetype":"venue"
},
  "geometry": {"coordinates":[-75.25590699999999,43.089209],"type":"Point"}
}