{
  "type": "Feature",
  "properties": {
    "addr:full":"2068 Harwood Dr Sandy Creek NY 13145",
    "addr:housenumber":"2068",
    "addr:postcode":"13145",
    "addr:street":"Harwood Dr",
    "iso:country":"US",
    "sg:address":"2068 Harwood Dr",
    "sg:city":"Sandy Creek",
    "sg:classifiers":[
        {
            "category":"Shopping",
            "subcategory":"Music",
            "type":"Retail Goods"
        }
    ],
    "sg:phone":"+1 315 387 6888",
    "sg:postcode":"13145",
    "sg:province":"NY",
    "sg:tags":[
        "video",
        "disc",
        "tape",
        "cassette"
    ],
    "wof:name":"Myrlin's Videos",
    "wof:placetype":"venue"
},
  "geometry": {"coordinates":[-76.085027,43.644108],"type":"Point"}
}