{
  "type": "Feature",
  "properties": {
    "addr:full":"582 5th Ave Brooklyn NY 11215",
    "addr:housenumber":"582",
    "addr:postcode":"11215",
    "addr:street":"5Th Ave",
    "iso:country":"US",
    "sg:address":"582 5th Ave",
    "sg:city":"Brooklyn",
    "sg:classifiers":[
        {
            "category":"Shopping",
            "subcategory":"Pharmacy",
            "type":"Retail Goods"
        }
    ],
    "sg:phone":"+1 718 499 2616",
    "sg:postcode":"11215",
    "sg:province":"NY",
    "sg:tags":[
        "drugstore"
    ],
    "wof:name":"Brook Medical Pharmacy",
    "wof:placetype":"venue"
},
  "geometry": {"coordinates":[-73.990196,40.6647],"type":"Point"}
}