{
  "type": "Feature",
  "properties": {
    "addr:full":"2549 State Hwy 40 Greenwich NY 12834",
    "addr:housenumber":"2549",
    "addr:postcode":"12834",
    "addr:street":"State Hwy 40",
    "iso:country":"US",
    "sg:address":"2549 State Hwy 40",
    "sg:city":"Greenwich",
    "sg:classifiers":[
        {
            "category":"Manufacturing",
            "subcategory":"Metals",
            "type":"Manufacturing & Wholesale Goods"
        }
    ],
    "sg:phone":"+1 518 692 9930",
    "sg:postcode":"12834",
    "sg:province":"NY",
    "sg:tags":[
        "gates"
    ],
    "sg:website":"www.tymetal.com",
    "wof:name":"Tymetal Corp",
    "wof:placetype":"venue"
},
  "geometry": {"coordinates":[-73.518475,43.103671],"type":"Point"}
}