{
  "type": "Feature",
  "properties": {
    "addr:full":"82 Alkamont Ave Scarsdale NY 10583",
    "addr:housenumber":"82",
    "addr:postcode":"10583",
    "addr:street":"Alkamont Ave",
    "iso:country":"US",
    "sg:address":"82 Alkamont Ave",
    "sg:city":"Scarsdale",
    "sg:classifiers":[
        {
            "category":"Professional",
            "subcategory":"Computer Services",
            "type":"Services"
        }
    ],
    "sg:phone":"+1 914 722 9097",
    "sg:postcode":"10583",
    "sg:province":"NY",
    "sg:tags":[
        "related"
    ],
    "wof:name":"Crimsonbow Inc",
    "wof:placetype":"venue"
},
  "geometry": {"coordinates":[-73.806393,40.980881],"type":"Point"}
}