{
  "type": "Feature",
  "properties": {
    "addr:full":"402 Court St Brooklyn NY 11231",
    "addr:housenumber":"402",
    "addr:postcode":"11231",
    "addr:street":"Court St",
    "iso:country":"US",
    "sg:address":"402 Court St",
    "sg:city":"Brooklyn",
    "sg:classifiers":[
        {
            "category":"Health Services",
            "subcategory":"Dentist",
            "type":"Services"
        }
    ],
    "sg:phone":"+1 718 834 1446",
    "sg:postcode":"11231",
    "sg:province":"NY",
    "wof:name":"Carroll Gardens Dental Associates Pc",
    "wof:placetype":"venue"
},
  "geometry": {"coordinates":[-73.996959,40.680537],"type":"Point"}
}