{
  "type": "Feature",
  "properties": {
    "iso:country":"US",
    "sg:address":"32 E 15 St",
    "sg:city":"New York",
    "sg:classifiers":[
        {
            "category":"Wholesale",
            "subcategory":"Apparel",
            "type":"Manufacturing & Wholesale Goods"
        }
    ],
    "sg:phone":"+1 212 813 0456",
    "sg:postcode":"10003",
    "sg:province":"NY",
    "sg:tags":[
        "necktie"
    ],
    "wof:name":"Altea Inc",
    "wof:placetype":"venue"
},
  "geometry": {"coordinates":[-73.991649,40.736053],"type":"Point"}
}