{
  "type": "Feature",
  "properties": {
    "addr:full":"2968 Ewell Pl Wantagh NY 11793",
    "addr:housenumber":"2968",
    "addr:postcode":"11793",
    "addr:street":"Ewell Pl",
    "iso:country":"US",
    "sg:address":"2968 Ewell Pl",
    "sg:city":"Wantagh",
    "sg:classifiers":[
        {
            "category":"Real Estate",
            "subcategory":"Architect",
            "type":"Services"
        }
    ],
    "sg:phone":"+1 516 785 5559",
    "sg:postcode":"11793",
    "sg:province":"NY",
    "sg:tags":[
        "architects'",
        "specification",
        "construction",
        "builders'",
        "architectural"
    ],
    "wof:name":"Howard Prince Architect",
    "wof:placetype":"venue"
},
  "geometry": {"coordinates":[-73.521659,40.679527],"type":"Point"}
}