{
  "type": "Feature",
  "properties": {
    "addr:full":"5729 61st Street Maspeth NY 11378",
    "addr:housenumber":"5729",
    "addr:postcode":"11378",
    "addr:street":"61St Street",
    "iso:country":"US",
    "sg:address":"5729 61st Street",
    "sg:city":"Maspeth",
    "sg:classifiers":[
        {
            "category":"Restaurant",
            "type":"Food & Drink"
        }
    ],
    "sg:phone":"+1 718 821 5707",
    "sg:postcode":"11378",
    "sg:province":"NY",
    "sg:tags":[
        "pizza"
    ],
    "wof:name":"Three Son Pizzeria",
    "wof:placetype":"venue"
},
  "geometry": {"coordinates":[-73.904336,40.722138],"type":"Point"}
}