{
  "type": "Feature",
  "properties": {
    "iso:country":"US",
    "sg:address":"551 Jefferson Blvd",
    "sg:city":"Staten Island",
    "sg:classifiers":[
        {
            "category":"Building & Trades",
            "subcategory":"Electrical",
            "type":"Services"
        }
    ],
    "sg:phone":"+1 718 967 9513",
    "sg:postcode":"10312",
    "sg:province":"NY",
    "sg:tags":[
        "electric",
        "contractor"
    ],
    "wof:name":"Jen Electrl Contractors Inc",
    "wof:placetype":"venue"
},
  "geometry": {"coordinates":[-74.190577,40.548861],"type":"Point"}
}