{
  "type": "Feature",
  "properties": {
    "addr:full":"429 E 52nd Street New York NY 10022",
    "addr:housenumber":"429",
    "addr:postcode":"10022",
    "addr:street":"E 52Nd Street",
    "iso:country":"US",
    "sg:address":"429 E 52nd Street",
    "sg:city":"New York",
    "sg:classifiers":[
        {
            "category":"Real Estate",
            "subcategory":"Real Estate Operator",
            "type":"Services"
        }
    ],
    "sg:phone":"+1 212 751 1110",
    "sg:postcode":"10022",
    "sg:province":"NY",
    "sg:tags":[
        "apartment"
    ],
    "wof:name":"Rivercourt",
    "wof:placetype":"venue"
},
  "geometry": {"coordinates":[-73.964614,40.75488],"type":"Point"}
}