{
  "type": "Feature",
  "properties": {
    "iso:country":"US",
    "sg:address":"2556 Youngstown Lockport Rd",
    "sg:city":"Ransomville",
    "sg:classifiers":[
        {
            "category":"Autos & Motor Vehicles",
            "subcategory":"Automobile Sales",
            "type":"Retail Goods"
        }
    ],
    "sg:phone":"+1   ",
    "sg:postcode":"14131",
    "sg:province":"NY",
    "sg:tags":[
        "used"
    ],
    "wof:name":"Nash Car Sales & Service",
    "wof:placetype":"venue"
},
  "geometry": {"coordinates":[-78.908323,43.238127],"type":"Point"}
}