{
  "type": "Feature",
  "properties": {
    "addr:full":"8820 Roosevelt Ave Jackson Heights NY 11372",
    "addr:housenumber":"8820",
    "addr:postcode":"11372",
    "addr:street":"Roosevelt Ave",
    "iso:country":"US",
    "sg:address":"8820 Roosevelt Ave",
    "sg:city":"Jackson Heights",
    "sg:classifiers":[
        {
            "category":"Professional",
            "subcategory":"Employment Agencies",
            "type":"Services"
        }
    ],
    "sg:phone":"+1 718 606 1919",
    "sg:postcode":"11372",
    "sg:province":"NY",
    "wof:name":"C And C Employment Agency",
    "wof:placetype":"venue"
},
  "geometry": {"coordinates":[-73.877534,40.748196],"type":"Point"}
}