{
  "type": "Feature",
  "properties": {
    "iso:country":"US",
    "sg:address":"800 Woodbury Rd",
    "sg:city":"Woodbury",
    "sg:classifiers":[
        {
            "category":"Health Services",
            "subcategory":"Medical Lab",
            "type":"Services"
        }
    ],
    "sg:phone":"+1 516 933 1664",
    "sg:postcode":"11797",
    "sg:province":"NY",
    "sg:tags":[
        "laboratory"
    ],
    "wof:name":"Boris Dental Lab Inc",
    "wof:placetype":"venue"
},
  "geometry": {"coordinates":[-73.48275,40.800805],"type":"Point"}
}