{
  "type": "Feature",
  "properties": {
    "addr:full":"1841 Broadway Rm 609 New York NY 10023",
    "addr:housenumber":"1841;609",
    "addr:postcode":"10023",
    "addr:street":"Broadway Rm",
    "iso:country":"US",
    "sg:address":"1841 Broadway Rm 609",
    "sg:city":"New York",
    "sg:classifiers":[
        {
            "category":"Health Services",
            "subcategory":"Health Practitioner",
            "type":"Services"
        }
    ],
    "sg:phone":"+1 212 262 4479",
    "sg:postcode":"10023",
    "sg:province":"NY",
    "sg:tags":[
        "therapy",
        "physical"
    ],
    "wof:name":"Profitness Physical Therapy PC",
    "wof:placetype":"venue"
},
  "geometry": {"coordinates":[-73.982218,40.77686],"type":"Point"}
}