{
  "type": "Feature",
  "properties": {
    "iso:country":"US",
    "sg:address":"608 Montauk Hwy",
    "sg:city":"Shirley",
    "sg:classifiers":[
        {
            "category":"Autos & Motor Vehicles",
            "subcategory":"Automobile Sales",
            "type":"Retail Goods"
        }
    ],
    "sg:phone":"+1 631 399 3677",
    "sg:postcode":"11967",
    "sg:province":"NY",
    "sg:tags":[
        "car",
        "dealer"
    ],
    "wof:name":"Any Car Auto Sales",
    "wof:placetype":"venue"
},
  "geometry": {"coordinates":[-72.87812099999999,40.800451],"type":"Point"}
}