{
  "type": "Feature",
  "properties": {
    "iso:country":"US",
    "sg:address":"3002 State Hwy 50",
    "sg:city":"Saratoga Springs",
    "sg:classifiers":[
        {
            "category":"Autos & Motor Vehicles",
            "subcategory":"Automobile Sales",
            "type":"Retail Goods"
        }
    ],
    "sg:phone":"+1   ",
    "sg:postcode":"12866",
    "sg:province":"NY",
    "wof:name":"New Country",
    "wof:placetype":"venue"
},
  "geometry": {"coordinates":[-73.749595,43.098207],"type":"Point"}
}