{
  "type": "Feature",
  "properties": {
    "iso:country":"US",
    "sg:address":"920 Turin St",
    "sg:city":"Rome",
    "sg:classifiers":[
        {
            "category":"Organizations",
            "subcategory":"Religious Organization",
            "type":"Services"
        }
    ],
    "sg:phone":"+1   ",
    "sg:postcode":"13440",
    "sg:province":"NY",
    "wof:name":"Christian Mssnary Alnce Church",
    "wof:placetype":"venue"
},
  "geometry": {"coordinates":[-75.455353,43.235966],"type":"Point"}
}