{
  "type": "Feature",
  "properties": {
    "iso:country":"US",
    "sg:address":"67 Steele St",
    "sg:city":"Jamestown",
    "sg:classifiers":[
        {
            "category":"Retail",
            "subcategory":"Auto Repair",
            "type":"Services"
        }
    ],
    "sg:phone":"+1 716 487 1494",
    "sg:postcode":"14701",
    "sg:province":"NY",
    "sg:tags":[
        "body",
        "repairing",
        "satellite",
        "di",
        "automobile",
        "cellular",
        "painting"
    ],
    "wof:name":"Joe's Auto Sales",
    "wof:placetype":"venue"
},
  "geometry": {"coordinates":[-79.24353499999999,42.092006],"type":"Point"}
}