{
  "type": "Feature",
  "properties": {
    "addr:full":"1304 Buckley Rd Syracuse NY 13212",
    "addr:housenumber":"1304",
    "addr:postcode":"13212",
    "addr:street":"Buckley Rd",
    "iso:country":"US",
    "sg:address":"1304 Buckley Rd",
    "sg:city":"Syracuse",
    "sg:classifiers":[
        {
            "category":"Health Services",
            "subcategory":"Doctor",
            "type":"Services"
        }
    ],
    "sg:phone":"+1 315 478 3311",
    "sg:postcode":"13212",
    "sg:province":"NY",
    "sg:tags":[
        "physician",
        "surgeon"
    ],
    "wof:name":"Nephrology Associates",
    "wof:placetype":"venue"
},
  "geometry": {"coordinates":[-76.17160699999999,43.092416],"type":"Point"}
}