{
  "type": "Feature",
  "properties": {
    "addr:full":"10 Grace Ln Coram NY 11727",
    "addr:housenumber":"10",
    "addr:postcode":"11727",
    "addr:street":"Grace Ln",
    "iso:country":"US",
    "sg:address":"10 Grace Ln",
    "sg:city":"Coram",
    "sg:classifiers":[
        {
            "category":"Restaurant",
            "type":"Food & Drink"
        }
    ],
    "sg:phone":"+1 631 928 6757",
    "sg:postcode":"11727",
    "sg:province":"NY",
    "sg:tags":[
        "seafood"
    ],
    "wof:name":"Pj Lobster House",
    "wof:placetype":"venue"
},
  "geometry": {"coordinates":[-73.013682,40.894187],"type":"Point"}
}