{
  "type": "Feature",
  "properties": {
    "iso:country":"US",
    "sg:address":"59 Abinet Ct",
    "sg:city":"Selden",
    "sg:classifiers":[
        {
            "category":"Building & Trades",
            "subcategory":"Construction",
            "type":"Services"
        }
    ],
    "sg:phone":"+1 631 736 8655",
    "sg:postcode":"11784",
    "sg:province":"NY",
    "sg:tags":[
        "contractor"
    ],
    "wof:name":"Enjoy Tile",
    "wof:placetype":"venue"
},
  "geometry": {"coordinates":[-73.038804,40.871767],"type":"Point"}
}