{
  "type": "Feature",
  "properties": {
    "iso:country":"US",
    "sg:address":"20 Vernon Pkwy",
    "sg:city":"Mt Vernon",
    "sg:classifiers":[
        {
            "category":"Manufacturing",
            "subcategory":"Tools & Machinery",
            "type":"Manufacturing & Wholesale Goods"
        }
    ],
    "sg:phone":"+1 914 667 1100",
    "sg:postcode":"10552",
    "sg:province":"NY",
    "sg:tags":[
        "cutting"
    ],
    "sg:website":"www.shorinternational.com",
    "wof:name":"Shor International",
    "wof:placetype":"venue"
},
  "geometry": {"coordinates":[-73.82862299999999,40.923401],"type":"Point"}
}