{
  "type": "Feature",
  "properties": {
    "addr:full":"2469 Grand Concourse Bronx NY 10468",
    "addr:housenumber":"2469",
    "addr:postcode":"10468",
    "addr:street":"Grand Concourse",
    "iso:country":"US",
    "sg:address":"2469 Grand Concourse",
    "sg:city":"Bronx",
    "sg:classifiers":[
        {
            "category":"Wholesale",
            "subcategory":"Apparel",
            "type":"Manufacturing & Wholesale Goods"
        }
    ],
    "sg:phone":"+1 718 220 4173",
    "sg:postcode":"10468",
    "sg:province":"NY",
    "wof:name":"No Joon Lee",
    "wof:placetype":"venue"
},
  "geometry": {"coordinates":[-73.897295,40.862186],"type":"Point"}
}