{
  "type": "Feature",
  "properties": {
    "addr:full":"1030 Old Medford Ave Farmingville NY 11738",
    "addr:housenumber":"1030",
    "addr:postcode":"11738",
    "addr:street":"Old Medford Ave",
    "iso:country":"US",
    "sg:address":"1030 Old Medford Ave",
    "sg:city":"Farmingville",
    "sg:classifiers":[
        {
            "category":"Building & Trades",
            "subcategory":"Construction",
            "type":"Services"
        }
    ],
    "sg:phone":"+1 631 451 0550",
    "sg:postcode":"11738",
    "sg:province":"NY",
    "sg:tags":[
        "painter"
    ],
    "wof:name":"John Mones Jr Painting",
    "wof:placetype":"venue"
},
  "geometry": {"coordinates":[-73.014503,40.837299],"type":"Point"}
}