{
  "type": "Feature",
  "properties": {
    "iso:country":"US",
    "sg:address":"3312 Long Beach Rd",
    "sg:city":"Oceanside",
    "sg:classifiers":[
        {
            "category":"Building & Trades",
            "subcategory":"Construction",
            "type":"Services"
        }
    ],
    "sg:phone":"+1 516 764 1901",
    "sg:postcode":"11572",
    "sg:province":"NY",
    "sg:tags":[
        "general",
        "contractor"
    ],
    "wof:name":"Prestige General Contractors",
    "wof:placetype":"venue"
},
  "geometry": {"coordinates":[-73.640989,40.630953],"type":"Point"}
}