{
  "type": "Feature",
  "properties": {
    "addr:full":"102 Garner Ave Buffalo NY 14213",
    "addr:housenumber":"102",
    "addr:postcode":"14213",
    "addr:street":"Garner Ave",
    "iso:country":"US",
    "sg:address":"102 Garner Ave",
    "sg:city":"Buffalo",
    "sg:classifiers":[
        {
            "category":"Home & Garden",
            "subcategory":"Home Furnishings",
            "type":"Retail Goods"
        }
    ],
    "sg:phone":"+1   ",
    "sg:postcode":"14213",
    "sg:province":"NY",
    "wof:name":"Oddos Home Improvement",
    "wof:placetype":"venue"
},
  "geometry": {"coordinates":[-78.890826,42.925002],"type":"Point"}
}