{
  "type": "Feature",
  "properties": {
    "iso:country":"US",
    "sg:address":"47 S 5th Ave",
    "sg:city":"Mount Vernon",
    "sg:classifiers":[
        {
            "category":"Shopping",
            "subcategory":"Catalog Store",
            "type":"Retail Goods"
        }
    ],
    "sg:phone":"+1   ",
    "sg:postcode":"10550",
    "sg:province":"NY",
    "sg:tags":[
        "house",
        "mail"
    ],
    "wof:name":"Lockdown Package Service",
    "wof:placetype":"venue"
},
  "geometry": {"coordinates":[-73.837345,40.910146],"type":"Point"}
}