{
  "type": "Feature",
  "properties": {
    "addr:full":"245 Willis Ave Bronx NY 10454",
    "addr:housenumber":"245",
    "addr:postcode":"10454",
    "addr:street":"Willis Ave",
    "iso:country":"US",
    "sg:address":"245 Willis Ave",
    "sg:city":"Bronx",
    "sg:classifiers":[
        {
            "category":"Home & Garden",
            "subcategory":"Hardware",
            "type":"Retail Goods"
        }
    ],
    "sg:phone":"+1 347 577 1883",
    "sg:postcode":"10454",
    "sg:province":"NY",
    "sg:tags":[
        "store"
    ],
    "wof:name":"Ez Hardware",
    "wof:placetype":"venue"
},
  "geometry": {"coordinates":[-73.9227588663,40.809607886],"type":"Point"}
}