{
  "type": "Feature",
  "properties": {
    "iso:country":"US",
    "sg:address":"7 Clinton Ave",
    "sg:city":"Ellenville",
    "sg:classifiers":[
        {
            "category":"Home & Garden",
            "subcategory":"Building Materials",
            "type":"Retail Goods"
        }
    ],
    "sg:phone":"+1 845 647 4362",
    "sg:postcode":"12428",
    "sg:province":"NY",
    "sg:tags":[
        "door"
    ],
    "wof:name":"Mid Hudson Overhead Door Inc",
    "wof:placetype":"venue"
},
  "geometry": {"coordinates":[-74.387821,41.712227],"type":"Point"}
}