{
  "type": "Feature",
  "properties": {
    "iso:country":"US",
    "sg:address":"506 Homestead Ave",
    "sg:city":"Maybrook",
    "sg:classifiers":[
        {
            "category":"Freight",
            "type":"Transportation"
        }
    ],
    "sg:phone":"+1   ",
    "sg:postcode":"12543",
    "sg:province":"NY",
    "wof:name":"Streetwise Motorcycling Inc",
    "wof:placetype":"venue"
},
  "geometry": {"coordinates":[-74.215834,41.485785],"type":"Point"}
}