{
  "type": "Feature",
  "properties": {
    "addr:full":"10725 Atlantic Ave Richmond Hill NY 11418",
    "addr:housenumber":"10725",
    "addr:postcode":"11418",
    "addr:street":"Atlantic Ave",
    "iso:country":"US",
    "sg:address":"10725 Atlantic Ave",
    "sg:city":"Richmond Hill",
    "sg:classifiers":[
        {
            "category":"Professional",
            "subcategory":"Computer Services",
            "type":"Services"
        }
    ],
    "sg:phone":"+1 718 850 0031",
    "sg:postcode":"11418",
    "sg:province":"NY",
    "sg:tags":[
        "repair"
    ],
    "wof:name":"Computer Repair Plus Inc",
    "wof:placetype":"venue"
},
  "geometry": {"coordinates":[-73.838489,40.691321],"type":"Point"}
}