{
  "type": "Feature",
  "properties": {
    "addr:full":"215 Berkeley Pl Brooklyn NY 11217",
    "addr:housenumber":"215",
    "addr:postcode":"11217",
    "addr:street":"Berkeley Pl",
    "iso:country":"US",
    "sg:address":"215 Berkeley Pl",
    "sg:city":"Brooklyn",
    "sg:classifiers":[
        {
            "category":"Professional",
            "subcategory":"Computer Services",
            "type":"Services"
        }
    ],
    "sg:phone":"+1 800 696 7834",
    "sg:postcode":"11217",
    "sg:province":"NY",
    "sg:tags":[
        "prepackaged",
        "custom",
        "programing",
        "software"
    ],
    "wof:name":"Openetwork Inc",
    "wof:placetype":"venue"
},
  "geometry": {"coordinates":[-73.973536,40.674725],"type":"Point"}
}