{
  "type": "Feature",
  "properties": {
    "addr:full":"122 Keyland Ct Bohemia NY 11716",
    "addr:housenumber":"122",
    "addr:postcode":"11716",
    "addr:street":"Keyland Ct",
    "iso:country":"US",
    "sg:address":"122 Keyland Ct",
    "sg:city":"Bohemia",
    "sg:classifiers":[
        {
            "category":"Manufacturing",
            "subcategory":"Printing",
            "type":"Manufacturing & Wholesale Goods"
        }
    ],
    "sg:phone":"+1   ",
    "sg:postcode":"11716",
    "sg:province":"NY",
    "sg:tags":[
        "commercial",
        "letterpress"
    ],
    "wof:name":"A & B Letterpress Services",
    "wof:placetype":"venue"
},
  "geometry": {"coordinates":[-73.096992,40.776771],"type":"Point"}
}