{
  "type": "Feature",
  "properties": {
    "addr:full":"169 Myrtle Ave Brooklyn NY 11201",
    "addr:housenumber":"169",
    "addr:postcode":"11201",
    "addr:street":"Myrtle Ave",
    "iso:country":"US",
    "sg:address":"169 Myrtle Ave",
    "sg:city":"Brooklyn",
    "sg:classifiers":[
        {
            "category":"Food & Beverages",
            "subcategory":"Groceries & Convenience Stores",
            "type":"Retail Goods"
        }
    ],
    "sg:phone":"+1   ",
    "sg:postcode":"11201",
    "sg:province":"NY",
    "wof:name":"Adella Grocery",
    "wof:placetype":"venue"
},
  "geometry": {"coordinates":[-73.983053,40.693721],"type":"Point"}
}