{
  "type": "Feature",
  "properties": {
    "addr:full":"1785 Victory Blvd Staten Island NY 10314",
    "addr:housenumber":"1785",
    "addr:postcode":"10314",
    "addr:street":"Victory Blvd",
    "iso:country":"US",
    "sg:address":"1785 Victory Blvd",
    "sg:city":"Staten Island",
    "sg:classifiers":[
        {
            "category":"Banks & Credit Unions",
            "subcategory":"Bank",
            "type":"Services"
        }
    ],
    "sg:phone":"+1 718 625 6700",
    "sg:postcode":"10314",
    "sg:province":"NY",
    "sg:tags":[
        "national",
        "commercial"
    ],
    "wof:name":"Fleet",
    "wof:placetype":"venue"
},
  "geometry": {"coordinates":[-74.12371,40.613091],"type":"Point"}
}