{
  "type": "Feature",
  "properties": {
    "iso:country":"US",
    "sg:address":"190 Fremont Ave",
    "sg:city":"Staten Island",
    "sg:classifiers":[
        {
            "category":"Retail",
            "subcategory":"Animal Services",
            "type":"Services"
        }
    ],
    "sg:phone":"+1 718 979 6316",
    "sg:postcode":"10306",
    "sg:province":"NY",
    "wof:name":"Gregory Equine Svs Llc",
    "wof:placetype":"venue"
},
  "geometry": {"coordinates":[-74.10637800000001,40.57724],"type":"Point"}
}