{
  "type": "Feature",
  "properties": {
    "addr:full":"83 Hillside Park Brewster NY 10509",
    "addr:housenumber":"83",
    "addr:postcode":"10509",
    "addr:street":"Hillside Park Brewster",
    "iso:country":"US",
    "sg:address":"83 Hillside Park",
    "sg:city":"Brewster",
    "sg:classifiers":[
        {
            "category":"Real Estate",
            "subcategory":"Real Estate Agent",
            "type":"Services"
        }
    ],
    "sg:phone":"+1 845 279 4761",
    "sg:postcode":"10509",
    "sg:province":"NY",
    "wof:name":"Century 21",
    "wof:placetype":"venue"
},
  "geometry": {"coordinates":[-73.62373599999999,41.397705],"type":"Point"}
}