{
  "type": "Feature",
  "properties": {
    "iso:country":"US",
    "sg:address":"146 Mulberry St",
    "sg:city":"New York",
    "sg:classifiers":[
        {
            "category":"Retail",
            "subcategory":"Repair Shop",
            "type":"Services"
        }
    ],
    "sg:phone":"+1 917 289 9429",
    "sg:postcode":"10013",
    "sg:province":"NY",
    "sg:tags":[
        "lock",
        "locksmith"
    ],
    "wof:name":"7 24 Hour Emergency Locksmith",
    "wof:placetype":"venue"
},
  "geometry": {"coordinates":[-73.99757200000001,40.71857],"type":"Point"}
}