{
  "type": "Feature",
  "properties": {
    "addr:full":"641 Co Rd 52 Greenwich NY 12834",
    "addr:housenumber":"641;52",
    "addr:postcode":"12834",
    "addr:street":"Co Rd",
    "iso:country":"US",
    "sg:address":"641 Co Rd 52",
    "sg:city":"Greenwich",
    "sg:phone":"+1 518 692 2656",
    "sg:postcode":"12834",
    "sg:province":"NY",
    "sg:tags":[
        "farm",
        "field",
        "corn",
        "crop"
    ],
    "wof:name":"Wee Bonnie Farm",
    "wof:placetype":"venue"
},
  "geometry": {"coordinates":[-73.49041200000001,43.148506],"type":"Point"}
}