{
  "type": "Feature",
  "properties": {
    "iso:country":"US",
    "sg:address":"400 Bean Hill Rd",
    "sg:city":"Endicott",
    "sg:classifiers":[
        {
            "category":"Professional",
            "subcategory":"Engineering",
            "type":"Services"
        }
    ],
    "sg:phone":"+1 607 754 6890",
    "sg:postcode":"13760",
    "sg:province":"NY",
    "sg:tags":[
        "marketing",
        "industrial"
    ],
    "wof:name":"Team Solutions Inc",
    "wof:placetype":"venue"
},
  "geometry": {"coordinates":[-76.101619,42.127487],"type":"Point"}
}