{
  "type": "Feature",
  "properties": {
    "iso:country":"US",
    "sg:address":"213 N Franklin St",
    "sg:city":"Watkins Glen",
    "sg:classifiers":[
        {
            "category":"Shopping",
            "type":"Retail Goods"
        }
    ],
    "sg:phone":"+1 607 535 9698",
    "sg:postcode":"14891",
    "sg:province":"NY",
    "sg:tags":[
        "art",
        "gallery",
        "dealer"
    ],
    "wof:name":"Gatherings Gallery",
    "wof:placetype":"venue"
},
  "geometry": {"coordinates":[-76.87407899999999,42.381482],"type":"Point"}
}