{
  "type": "Feature",
  "properties": {
    "iso:country":"US",
    "sg:address":"1145 Union Rd",
    "sg:city":"Buffalo",
    "sg:classifiers":[
        {
            "category":"Bakery",
            "type":"Food & Drink"
        },
        {
            "category":"Coffee & Tea",
            "type":"Food & Drink"
        },
        {
            "category":"Bagels",
            "type":"Food & Drink"
        },
        {
            "category":"Donuts",
            "type":"Food & Drink"
        }
    ],
    "sg:menulink":"http://www.allmenus.com/ny/west-seneca/138783-dunkin-donuts/menu/",
    "sg:phone":"+1 212 831 3085",
    "sg:postcode":"14224",
    "sg:province":"NY",
    "sg:tags":[
        "american",
        "pastry"
    ],
    "wof:name":"Dunkin' Donuts",
    "wof:placetype":"venue"
},
  "geometry": {"coordinates":[-78.75338499999999,42.831182],"type":"Point"}
}