{
  "type": "Feature",
  "properties": {
    "iso:country":"US",
    "sg:address":"6117 S Park Ave",
    "sg:city":"Hamburg",
    "sg:classifiers":[
        {
            "category":"Food & Beverages",
            "subcategory":"Specialty",
            "type":"Retail Goods"
        }
    ],
    "sg:phone":"+1   ",
    "sg:postcode":"14075",
    "sg:province":"NY",
    "sg:tags":[
        "herbal",
        "importer",
        "digestion"
    ],
    "wof:name":"Underberg Sales Corp",
    "wof:placetype":"venue"
},
  "geometry": {"coordinates":[-78.825649,42.728463],"type":"Point"}
}