{
  "type": "Feature",
  "properties": {
    "addr:full":"590 Commerce St Thornwood NY 10594",
    "addr:housenumber":"590",
    "addr:postcode":"10594",
    "addr:street":"Commerce St",
    "iso:country":"US",
    "sg:address":"590 Commerce St",
    "sg:city":"Thornwood",
    "sg:classifiers":[
        {
            "category":"Building & Trades",
            "subcategory":"Landscaping Services",
            "type":"Services"
        }
    ],
    "sg:phone":"+1 914 747 4282",
    "sg:postcode":"10594",
    "sg:province":"NY",
    "sg:tags":[
        "horticultural",
        "consultant"
    ],
    "wof:name":"John Anthony & Assoc LTD",
    "wof:placetype":"venue"
},
  "geometry": {"coordinates":[-73.78884499999999,41.115625],"type":"Point"}
}