{
  "type": "Feature",
  "properties": {
    "addr:full":"25 Old Jerome Ave Yonkers NY 10704",
    "addr:housenumber":"25",
    "addr:postcode":"10704",
    "addr:street":"Old Jerome Ave",
    "iso:country":"US",
    "sg:address":"25 Old Jerome Ave",
    "sg:city":"Yonkers",
    "sg:classifiers":[
        {
            "category":"Building & Trades",
            "subcategory":"Electrical",
            "type":"Services"
        }
    ],
    "sg:phone":"+1 914 776 7835",
    "sg:postcode":"10704",
    "sg:province":"NY",
    "sg:tags":[
        "electrical",
        "contractor"
    ],
    "wof:name":"Royal County Construction Co",
    "wof:placetype":"venue"
},
  "geometry": {"coordinates":[-73.874455,40.906152],"type":"Point"}
}