{
  "type": "Feature",
  "properties": {
    "addr:full":"207 Broadway Valley Stream NY 11580",
    "addr:housenumber":"207",
    "addr:postcode":"11580",
    "addr:street":"Broadway",
    "iso:country":"US",
    "sg:address":"207 Broadway",
    "sg:city":"Valley Stream",
    "sg:classifiers":[
        {
            "category":"Retail",
            "subcategory":"Auto Repair",
            "type":"Services"
        }
    ],
    "sg:phone":"+1 516 285 1373",
    "sg:postcode":"11580",
    "sg:province":"NY",
    "sg:tags":[
        "repairing",
        "automobile"
    ],
    "wof:name":"Cool Heat Mechanic",
    "wof:placetype":"venue"
},
  "geometry": {"coordinates":[-73.72698099999999,40.666432],"type":"Point"}
}