{
  "type": "Feature",
  "properties": {
    "iso:country":"US",
    "sg:address":"2285 Ridgeway Ave",
    "sg:city":"Rochester",
    "sg:classifiers":[
        {
            "category":"Retail",
            "subcategory":"Auto Repair",
            "type":"Services"
        }
    ],
    "sg:phone":"+1 585 723 1333",
    "sg:postcode":"14626",
    "sg:province":"NY",
    "sg:tags":[
        "exchanging",
        "engine"
    ],
    "wof:name":"Drake Engines Inc",
    "wof:placetype":"venue"
},
  "geometry": {"coordinates":[-77.69541,43.188251],"type":"Point"}
}