{
  "type": "Feature",
  "properties": {
    "addr:full":"1 Dag Hammarskjold Plz Fl 31 New York NY 10017",
    "addr:housenumber":"1;31",
    "addr:postcode":"10017",
    "addr:street":"Dag Hammarskjold Plz Fl",
    "iso:country":"US",
    "sg:address":"1 Dag Hammarskjold Plz Fl 31",
    "sg:city":"New York",
    "sg:classifiers":[
        {
            "category":"Banks & Credit Unions",
            "subcategory":"Investment Brokerage",
            "type":"Services"
        }
    ],
    "sg:phone":"+1 212 812 3080",
    "sg:postcode":"10017",
    "sg:province":"NY",
    "sg:tags":[
        "investing"
    ],
    "wof:name":"Eagle Capital Management",
    "wof:placetype":"venue"
},
  "geometry": {"coordinates":[-73.974802,40.753145],"type":"Point"}
}