{
  "type": "Feature",
  "properties": {
    "iso:country":"US",
    "sg:address":"4878 Sunrise Hwy",
    "sg:city":"Massapequa Park",
    "sg:classifiers":[
        {
            "category":"Insurance",
            "subcategory":"Insurance Agent",
            "type":"Services"
        }
    ],
    "sg:phone":"+1 516 541 9600",
    "sg:postcode":"11762",
    "sg:province":"NY",
    "wof:name":"Lighthouse Insurance",
    "wof:placetype":"venue"
},
  "geometry": {"coordinates":[-73.45549800000001,40.67729],"type":"Point"}
}