{
  "type": "Feature",
  "properties": {
    "iso:country":"US",
    "sg:address":"Rockville Ctr",
    "sg:city":"Williston Park",
    "sg:classifiers":[
        {
            "category":"Health Services",
            "subcategory":"Clinic",
            "type":"Services"
        }
    ],
    "sg:phone":"+1 516 248 0006",
    "sg:postcode":"11596",
    "sg:province":"NY",
    "sg:tags":[
        "counseling",
        "mental"
    ],
    "wof:name":"The Center For Psychotherapy",
    "wof:placetype":"venue"
},
  "geometry": {"coordinates":[-73.643997,40.759499],"type":"Point"}
}