{
  "type": "Feature",
  "properties": {
    "addr:full":"50 Gansevoort St New York NY 10026",
    "addr:housenumber":"50",
    "addr:postcode":"10026",
    "addr:street":"Gansevoort St",
    "iso:country":"US",
    "sg:address":"50 Gansevoort St",
    "sg:city":"New York",
    "sg:classifiers":[
        {
            "category":"Bars & Pubs",
            "subcategory":"Lounge",
            "type":"Food & Drink"
        }
    ],
    "sg:phone":"+1 212 255 6676",
    "sg:postcode":"10026",
    "sg:province":"NY",
    "sg:website":"www.pmloungenyc.com/",
    "wof:name":"PM Lounge",
    "wof:placetype":"venue"
},
  "geometry": {"coordinates":[-74.006897,40.7393],"type":"Point"}
}