{
  "type": "Feature",
  "properties": {
    "addr:full":"332 E Utica St Buffalo NY 14208",
    "addr:housenumber":"332",
    "addr:postcode":"14208",
    "addr:street":"E Utica St",
    "iso:country":"US",
    "sg:address":"332 E Utica St",
    "sg:city":"Buffalo",
    "sg:classifiers":[
        {
            "category":"Education",
            "subcategory":"Library",
            "type":"Public Place"
        }
    ],
    "sg:phone":"+1 716 883 4418",
    "sg:postcode":"14208",
    "sg:province":"NY",
    "wof:name":"North Jefferson Branch Library",
    "wof:placetype":"venue"
},
  "geometry": {"coordinates":[-78.85346,42.911184],"type":"Point"}
}