{
  "type": "Feature",
  "properties": {
    "addr:full":"5755 156th St Flushing NY 11355",
    "addr:housenumber":"5755",
    "addr:postcode":"11355",
    "addr:street":"156Th St",
    "iso:country":"US",
    "sg:address":"5755 156th St",
    "sg:city":"Flushing",
    "sg:classifiers":[
        {
            "category":"Real Estate",
            "subcategory":"Real Estate Operator",
            "type":"Services"
        }
    ],
    "sg:phone":"+1 718 762 1412",
    "sg:postcode":"11355",
    "sg:province":"NY",
    "sg:tags":[
        "apartment"
    ],
    "wof:name":"Shiv Shakti Towers Inc",
    "wof:placetype":"venue"
},
  "geometry": {"coordinates":[-73.809956,40.758024],"type":"Point"}
}