{
  "type": "Feature",
  "properties": {
    "iso:country":"US",
    "sg:address":"59 John St",
    "sg:city":"New York",
    "sg:classifiers":[
        {
            "category":"Insurance",
            "subcategory":"Insurance Agent",
            "type":"Services"
        }
    ],
    "sg:phone":"+1 212 732 1543",
    "sg:postcode":"10038",
    "sg:province":"NY",
    "wof:name":"N Friedman & Sons",
    "wof:placetype":"venue"
},
  "geometry": {"coordinates":[-74.007459,40.708975],"type":"Point"}
}