{
  "type": "Feature",
  "properties": {
    "iso:country":"US",
    "sg:address":"40 Fleetwood Ct",
    "sg:city":"Ronkonkoma",
    "sg:classifiers":[
        {
            "category":"Professional",
            "subcategory":"Computer Services",
            "type":"Services"
        }
    ],
    "sg:phone":"+1 631 471 6798",
    "sg:postcode":"11779",
    "sg:province":"NY",
    "sg:tags":[
        "consultant",
        "designer"
    ],
    "sg:website":"www.gostechnicalservices.com",
    "wof:name":"Global Outsourcing Svc",
    "wof:placetype":"venue"
},
  "geometry": {"coordinates":[-73.132486,40.792478],"type":"Point"}
}