{
  "type": "Feature",
  "properties": {
    "addr:full":"127 E Broadway New York NY 10002",
    "addr:housenumber":"127",
    "addr:postcode":"10002",
    "addr:street":"E Broadway",
    "iso:country":"US",
    "sg:address":"127 E Broadway",
    "sg:city":"New York",
    "sg:classifiers":[
        {
            "category":"Wholesale",
            "subcategory":"Non-durable Goods",
            "type":"Manufacturing & Wholesale Goods"
        }
    ],
    "sg:phone":"+1 212 577 6080",
    "sg:postcode":"10002",
    "sg:province":"NY",
    "wof:name":"Fu & Feng Trading Corp",
    "wof:placetype":"venue"
},
  "geometry": {"coordinates":[-73.990588,40.713935],"type":"Point"}
}