{
  "type": "Feature",
  "properties": {
    "addr:full":"230 W 10 St New York NY 10014",
    "addr:housenumber":"230",
    "addr:postcode":"10014",
    "addr:street":"W 10 St",
    "iso:country":"US",
    "sg:address":"230 W 10 St",
    "sg:city":"New York",
    "sg:classifiers":[
        {
            "category":"Professional",
            "subcategory":"Business Services",
            "type":"Services"
        }
    ],
    "sg:phone":"+1 212 414 1885",
    "sg:postcode":"10014",
    "sg:province":"NY",
    "sg:tags":[
        "interior",
        "consultant",
        "design",
        "decorator"
    ],
    "wof:name":"Foundations Interior Designs",
    "wof:placetype":"venue"
},
  "geometry": {"coordinates":[-74.005816,40.733763],"type":"Point"}
}