{
  "type": "Feature",
  "properties": {
    "iso:country":"US",
    "sg:address":"198 Union Ave",
    "sg:city":"Brooklyn",
    "sg:classifiers":[
        {
            "category":"Bars & Pubs",
            "type":"Food & Drink"
        }
    ],
    "sg:phone":"+1 718 963 9300",
    "sg:postcode":"11211",
    "sg:province":"NY",
    "wof:name":"Jarrod's Lounge",
    "wof:placetype":"venue"
},
  "geometry": {"coordinates":[-73.950283,40.706258],"type":"Point"}
}