{
  "type": "Feature",
  "properties": {
    "iso:country":"US",
    "sg:address":"144 Lakes Rd",
    "sg:city":"Monroe",
    "sg:classifiers":[
        {
            "category":"Professional",
            "subcategory":"Art Services",
            "type":"Services"
        }
    ],
    "sg:phone":"+1   ",
    "sg:postcode":"10950",
    "sg:province":"NY",
    "sg:tags":[
        "commercial",
        "design"
    ],
    "wof:name":"Barts Drafting and Art Svc",
    "wof:placetype":"venue"
},
  "geometry": {"coordinates":[-74.198167,41.320684],"type":"Point"}
}