{
  "type": "Feature",
  "properties": {
    "addr:full":"57A N Broadway Tarrytown NY 10591",
    "addr:housenumber":"57a",
    "addr:postcode":"10591",
    "addr:street":"N Broadway",
    "iso:country":"US",
    "sg:address":"57A N Broadway",
    "sg:city":"Tarrytown",
    "sg:classifiers":[
        {
            "category":"Wholesale",
            "subcategory":"Medical Equipment & Supplies",
            "type":"Manufacturing & Wholesale Goods"
        },
        {
            "category":"Shopping",
            "subcategory":"Pharmacy",
            "type":"Retail Goods"
        }
    ],
    "sg:phone":"+1 914 631 2168",
    "sg:postcode":"10591",
    "sg:province":"NY",
    "sg:tags":[
        "home",
        "health",
        "care"
    ],
    "wof:name":"Russell & Lawrie Home Health Care Supplies Inc",
    "wof:placetype":"venue"
},
  "geometry": {"coordinates":[-73.857727,41.078271],"type":"Point"}
}