{
  "type": "Feature",
  "properties": {
    "iso:country":"US",
    "sg:address":"31 Yankee Folly Rd",
    "sg:city":"New Paltz",
    "sg:classifiers":[
        {
            "category":"Recreation",
            "type":"Entertainment"
        }
    ],
    "sg:phone":"+1 845 255 3220",
    "sg:postcode":"12561",
    "sg:province":"NY",
    "sg:tags":[
        "riding",
        "academy"
    ],
    "wof:name":"Lucky C Stables Inc",
    "wof:placetype":"venue"
},
  "geometry": {"coordinates":[-74.151552,41.728373],"type":"Point"}
}