{
  "type": "Feature",
  "properties": {
    "iso:country":"US",
    "sg:address":"81 Pondfield Rd W",
    "sg:city":"Bronxville",
    "sg:classifiers":[
        {
            "category":"Building & Trades",
            "subcategory":"Construction",
            "type":"Services"
        }
    ],
    "sg:phone":"+1 914 961 9435",
    "sg:postcode":"10708",
    "sg:province":"NY",
    "sg:tags":[
        "general",
        "contractor"
    ],
    "wof:name":"S Young Contracting Corp",
    "wof:placetype":"venue"
},
  "geometry": {"coordinates":[-73.84178300000001,40.944286],"type":"Point"}
}