{
  "type": "Feature",
  "properties": {
    "iso:country":"US",
    "sg:address":"1201 Albany St",
    "sg:city":"Utica",
    "sg:classifiers":[
        {
            "category":"Wholesale",
            "subcategory":"Durable Goods & Equipment",
            "type":"Manufacturing & Wholesale Goods"
        }
    ],
    "sg:phone":"+1 315 266 0202",
    "sg:postcode":"13501",
    "sg:province":"NY",
    "sg:tags":[
        "importer"
    ],
    "wof:name":"Royal Imports",
    "wof:placetype":"venue"
},
  "geometry": {"coordinates":[-75.20866599999999,43.083856],"type":"Point"}
}