{
  "type": "Feature",
  "properties": {
    "iso:country":"US",
    "sg:address":"3703 Church Ave",
    "sg:city":"Brooklyn",
    "sg:classifiers":[
        {
            "category":"Personal",
            "subcategory":"Beauty Salon",
            "type":"Services"
        }
    ],
    "sg:phone":"+1 718 826 0780",
    "sg:postcode":"11203",
    "sg:province":"NY",
    "sg:tags":[
        "hair"
    ],
    "wof:name":"Roma Beauty Salon",
    "wof:placetype":"venue"
},
  "geometry": {"coordinates":[-73.942802,40.651248],"type":"Point"}
}