{
  "type": "Feature",
  "properties": {
    "iso:country":"US",
    "sg:address":"11 W 4th St",
    "sg:city":"Oswego",
    "sg:classifiers":[
        {
            "category":"Health Services",
            "subcategory":"Doctor",
            "type":"Services"
        }
    ],
    "sg:phone":"+1 315 342 7360",
    "sg:postcode":"13126",
    "sg:province":"NY",
    "sg:tags":[
        "medical"
    ],
    "wof:name":"Oswego Family Medicine",
    "wof:placetype":"venue"
},
  "geometry": {"coordinates":[-76.51763,43.461463],"type":"Point"}
}