{
  "type": "Feature",
  "properties": {
    "addr:full":"25 N Moore St New York NY 10013",
    "addr:housenumber":"25",
    "addr:postcode":"10013",
    "addr:street":"N Moore St",
    "iso:country":"US",
    "sg:address":"25 N Moore St",
    "sg:city":"New York",
    "sg:classifiers":[
        {
            "category":"Bars & Pubs",
            "subcategory":"Lounge",
            "type":"Food & Drink"
        },
        {
            "category":"Restaurant",
            "type":"Food & Drink"
        },
        {
            "category":"Bars & Pubs",
            "subcategory":"Wine Bar",
            "type":"Food & Drink"
        }
    ],
    "sg:phone":"+1 212 226 5545",
    "sg:postcode":"10013",
    "sg:province":"NY",
    "sg:tags":[
        "new",
        "american"
    ],
    "sg:website":"www.brandylibrary.com",
    "wof:name":"Brandy Library",
    "wof:placetype":"venue"
},
  "geometry": {"coordinates":[-74.00736499999999,40.719816],"type":"Point"}
}