{
  "type": "Feature",
  "properties": {
    "addr:full":"4 Astor Pl New York NY 10003",
    "addr:housenumber":"4",
    "addr:postcode":"10003",
    "addr:street":"Astor Pl",
    "iso:country":"US",
    "sg:address":"4 Astor Pl",
    "sg:city":"New York",
    "sg:classifiers":[
        {
            "category":"Sports & Exercise",
            "subcategory":"Gym",
            "type":"Entertainment"
        }
    ],
    "sg:phone":"+1 212 505 6800",
    "sg:postcode":"10003",
    "sg:province":"NY",
    "sg:tags":[
        "trainer"
    ],
    "sg:website":"www.davidbartongym.com",
    "wof:name":"David Barton Gym",
    "wof:placetype":"venue"
},
  "geometry": {"coordinates":[-73.992265,40.729901],"type":"Point"}
}