{
  "type": "Feature",
  "properties": {
    "addr:full":"6210 Culver Rd Trumansburg NY 14886",
    "addr:housenumber":"6210",
    "addr:postcode":"14886",
    "addr:street":"Culver Rd",
    "iso:country":"US",
    "sg:address":"6210 Culver Rd",
    "sg:city":"Trumansburg",
    "sg:classifiers":[
        {
            "category":"Real Estate",
            "subcategory":"Real Estate Agent",
            "type":"Services"
        }
    ],
    "sg:phone":"+1 607 387 7820",
    "sg:postcode":"14886",
    "sg:province":"NY",
    "sg:tags":[
        "appraiser"
    ],
    "wof:name":"Meixell Appraisal Svc",
    "wof:placetype":"venue"
},
  "geometry": {"coordinates":[-76.703406,42.421737],"type":"Point"}
}