{
  "type": "Feature",
  "properties": {
    "iso:country":"US",
    "sg:address":"1 Iroquois St",
    "sg:city":"Rotterdam Jct",
    "sg:classifiers":[
        {
            "category":"Building & Trades",
            "subcategory":"Construction",
            "type":"Services"
        }
    ],
    "sg:phone":"+1 518 887 7325",
    "sg:postcode":"12150",
    "sg:province":"NY",
    "sg:tags":[
        "product",
        "asphalt"
    ],
    "wof:name":"American Seal Coating",
    "wof:placetype":"venue"
},
  "geometry": {"coordinates":[-74.044467,42.872897],"type":"Point"}
}