{
  "type": "Feature",
  "properties": {
    "iso:country":"US",
    "sg:address":"366 Veterans Memorial Hwy",
    "sg:city":"Commack",
    "sg:classifiers":[
        {
            "category":"Professional",
            "subcategory":"Management & Consulting",
            "type":"Services"
        }
    ],
    "sg:phone":"+1 631 543 1333",
    "sg:postcode":"11725",
    "sg:province":"NY",
    "sg:tags":[
        "business"
    ],
    "wof:name":"Financial Appraisal Services",
    "wof:placetype":"venue"
},
  "geometry": {"coordinates":[-73.259147,40.832384],"type":"Point"}
}