{
  "type": "Feature",
  "properties": {
    "addr:full":"3936 Middle Cheshire Rd Canandaigua NY 14424",
    "addr:housenumber":"3936",
    "addr:postcode":"14424",
    "addr:street":"Middle Cheshire Rd",
    "iso:country":"US",
    "sg:address":"3936 Middle Cheshire Rd",
    "sg:city":"Canandaigua",
    "sg:classifiers":[
        {
            "category":"Wholesale",
            "subcategory":"Construction Materials",
            "type":"Manufacturing & Wholesale Goods"
        }
    ],
    "sg:phone":"+1 585 394 5853",
    "sg:postcode":"14424",
    "sg:province":"NY",
    "sg:tags":[
        "fence"
    ],
    "wof:name":"Fancifence",
    "wof:placetype":"venue"
},
  "geometry": {"coordinates":[-77.30383999999999,42.836646],"type":"Point"}
}