{
  "type": "Feature",
  "properties": {
    "iso:country":"US",
    "sg:address":"10 Main St",
    "sg:city":"Southampton",
    "sg:classifiers":[
        {
            "category":"Shopping",
            "subcategory":"Used Merchandise",
            "type":"Retail Goods"
        }
    ],
    "sg:phone":"+1 631 283 1867",
    "sg:postcode":"11968",
    "sg:province":"NY",
    "sg:tags":[
        "shop",
        "consignment"
    ],
    "wof:name":"Collette Home Consignment",
    "wof:placetype":"venue"
},
  "geometry": {"coordinates":[-72.389416,40.886363],"type":"Point"}
}