{
  "type": "Feature",
  "properties": {
    "iso:country":"US",
    "sg:address":"101 E Shore Rd",
    "sg:city":"Manhasset",
    "sg:classifiers":[
        {
            "category":"Retail",
            "subcategory":"Car Wash",
            "type":"Services"
        }
    ],
    "sg:phone":"+1   ",
    "sg:postcode":"11030",
    "sg:province":"NY",
    "sg:tags":[
        "carwash"
    ],
    "wof:name":"Finesse Fine Motorcar Detail",
    "wof:placetype":"venue"
},
  "geometry": {"coordinates":[-73.707054,40.78869],"type":"Point"}
}