{
  "type": "Feature",
  "properties": {
    "iso:country":"US",
    "sg:address":"5661 Stevens Dr S",
    "sg:city":"Cicero",
    "sg:classifiers":[
        {
            "category":"Professional",
            "subcategory":"Lawyer & Legal Services",
            "type":"Services"
        }
    ],
    "sg:phone":"+1 315 451 0659",
    "sg:postcode":"13039",
    "sg:province":"NY",
    "sg:tags":[
        "process",
        "server"
    ],
    "wof:name":"Speedy Process Service",
    "wof:placetype":"venue"
},
  "geometry": {"coordinates":[-76.12679300000001,43.16386],"type":"Point"}
}