{
  "type": "Feature",
  "properties": {
    "addr:full":"513 W Union St Newark NY 14513",
    "addr:housenumber":"513",
    "addr:postcode":"14513",
    "addr:street":"W Union St",
    "iso:country":"US",
    "sg:address":"513 W Union St",
    "sg:city":"Newark",
    "sg:classifiers":[
        {
            "category":"Shopping",
            "subcategory":"Optical Goods",
            "type":"Retail Goods"
        }
    ],
    "sg:phone":"+1 315 331 3657",
    "sg:postcode":"14513",
    "sg:province":"NY",
    "wof:name":"Pearle Vision",
    "wof:placetype":"venue"
},
  "geometry": {"coordinates":[-77.10673199999999,43.046473],"type":"Point"}
}