{
  "type": "Feature",
  "properties": {
    "iso:country":"US",
    "sg:address":"1429 Mill Ave",
    "sg:city":"Brooklyn",
    "sg:classifiers":[
        {
            "category":"Building & Trades",
            "subcategory":"Plumbing",
            "type":"Services"
        }
    ],
    "sg:phone":"+1 718 444 7771",
    "sg:postcode":"11234",
    "sg:province":"NY",
    "sg:tags":[
        "boiler",
        "cleaning"
    ],
    "wof:name":"Brooklyn Heating Corp",
    "wof:placetype":"venue"
},
  "geometry": {"coordinates":[-73.91595,40.617491],"type":"Point"}
}