{
  "type": "Feature",
  "properties": {
    "iso:country":"US",
    "sg:address":"6316 Walker Rd",
    "sg:city":"Utica",
    "sg:classifiers":[
        {
            "category":"Shopping",
            "subcategory":"Computers & Home Electronics",
            "type":"Retail Goods"
        }
    ],
    "sg:phone":"+1   ",
    "sg:postcode":"13502",
    "sg:province":"NY",
    "wof:name":"Dental Technologoy Solutions",
    "wof:placetype":"venue"
},
  "geometry": {"coordinates":[-75.176158,43.152404],"type":"Point"}
}