{
  "type": "Feature",
  "properties": {
    "addr:full":"4 Winchester Rd Lakewood NY 14750",
    "addr:housenumber":"4",
    "addr:postcode":"14750",
    "addr:street":"Winchester Rd",
    "iso:country":"US",
    "sg:address":"4 Winchester Rd",
    "sg:city":"Lakewood",
    "sg:classifiers":[
        {
            "category":"Professional",
            "subcategory":"Lawyer & Legal Services",
            "type":"Services"
        }
    ],
    "sg:phone":"+1 716 763 1122",
    "sg:postcode":"14750",
    "sg:province":"NY",
    "sg:tags":[
        "attorney"
    ],
    "wof:name":"Gregory L Peterson",
    "wof:placetype":"venue"
},
  "geometry": {"coordinates":[-79.331138,42.106447],"type":"Point"}
}