{
  "type": "Feature",
  "properties": {
    "addr:full":"687 Bronx River Rd Yonkers NY 10704",
    "addr:housenumber":"687",
    "addr:postcode":"10704",
    "addr:street":"Bronx River Rd",
    "iso:country":"US",
    "sg:address":"687 Bronx River Rd",
    "sg:city":"Yonkers",
    "sg:classifiers":[
        {
            "category":"Sports & Exercise",
            "subcategory":"Gym",
            "type":"Entertainment"
        }
    ],
    "sg:phone":"+1 914 237 7727",
    "sg:postcode":"10704",
    "sg:province":"NY",
    "sg:tags":[
        "spa",
        "health"
    ],
    "wof:name":"Spa Pros Mobile Day Spa",
    "wof:placetype":"venue"
},
  "geometry": {"coordinates":[-73.847216,40.921157],"type":"Point"}
}