{
  "type": "Feature",
  "properties": {
    "addr:full":"306 W Union St Newark NY 14513",
    "addr:housenumber":"306",
    "addr:postcode":"14513",
    "addr:street":"W Union St",
    "iso:country":"US",
    "sg:address":"306 W Union St",
    "sg:city":"Newark",
    "sg:classifiers":[
        {
            "category":"Building & Trades",
            "subcategory":"Construction",
            "type":"Services"
        }
    ],
    "sg:phone":"+1 315 587 9400",
    "sg:postcode":"14513",
    "sg:province":"NY",
    "wof:name":"American Roadways Inc",
    "wof:placetype":"venue"
},
  "geometry": {"coordinates":[-77.09986000000001,43.046307],"type":"Point"}
}