{
  "type": "Feature",
  "properties": {
    "iso:country":"US",
    "sg:address":"682 State Hwy 96",
    "sg:city":"Phelps",
    "sg:classifiers":[
        {
            "category":"Bars & Pubs",
            "type":"Food & Drink"
        }
    ],
    "sg:phone":"+1   ",
    "sg:postcode":"14532",
    "sg:province":"NY",
    "sg:tags":[
        "drinking"
    ],
    "wof:name":"Jellybeans",
    "wof:placetype":"venue"
},
  "geometry": {"coordinates":[-76.99187499999999,42.946668],"type":"Point"}
}