{
  "type": "Feature",
  "properties": {
    "addr:full":"17 Computer Dr E Albany NY 12205",
    "addr:postcode":"12205",
    "addr:street":"Dr E",
    "iso:country":"US",
    "sg:address":"17 Computer Dr E",
    "sg:city":"Albany",
    "sg:classifiers":[
        {
            "category":"Banks & Credit Unions",
            "subcategory":"Investment Brokerage",
            "type":"Services"
        }
    ],
    "sg:phone":"+1 518 489 2086",
    "sg:postcode":"12205",
    "sg:province":"NY",
    "sg:tags":[
        "advisory",
        "financial"
    ],
    "wof:name":"Tucker & Assoc",
    "wof:placetype":"venue"
},
  "geometry": {"coordinates":[-73.805015,42.715428],"type":"Point"}
}