{
  "type": "Feature",
  "properties": {
    "addr:full":"47 Lott Ln Staten Island NY 10314",
    "addr:housenumber":"47",
    "addr:postcode":"10314",
    "addr:street":"Lott Ln",
    "iso:country":"US",
    "sg:address":"47 Lott Ln",
    "sg:city":"Staten Island",
    "sg:classifiers":[
        {
            "category":"Professional",
            "subcategory":"Lawyer & Legal Services",
            "type":"Services"
        }
    ],
    "sg:phone":"+1 718 761 2888",
    "sg:postcode":"10314",
    "sg:province":"NY",
    "sg:tags":[
        "attorney"
    ],
    "wof:name":"Kelly Alessi",
    "wof:placetype":"venue"
},
  "geometry": {"coordinates":[-74.166715,40.576594],"type":"Point"}
}