{
  "type": "Feature",
  "properties": {
    "addr:full":"407 Rockaway Pkwy Valley Stream NY 11580",
    "addr:housenumber":"407",
    "addr:postcode":"11580",
    "addr:street":"Rockaway Pkwy",
    "iso:country":"US",
    "sg:address":"407 Rockaway Pkwy",
    "sg:city":"Valley Stream",
    "sg:classifiers":[
        {
            "category":"Retail",
            "subcategory":"Repair Shop",
            "type":"Services"
        }
    ],
    "sg:phone":"+1 516 825 3339",
    "sg:postcode":"11580",
    "sg:province":"NY",
    "sg:tags":[
        "reupholstery",
        "furniture"
    ],
    "wof:name":"Dercola's Upholstery",
    "wof:placetype":"venue"
},
  "geometry": {"coordinates":[-73.69270299999999,40.676201],"type":"Point"}
}