{
  "type": "Feature",
  "properties": {
    "addr:full":"756 Rockaway Pkwy Brooklyn NY 11236",
    "addr:housenumber":"756",
    "addr:postcode":"11236",
    "addr:street":"Rockaway Pkwy",
    "iso:country":"US",
    "sg:address":"756 Rockaway Pkwy",
    "sg:city":"Brooklyn",
    "sg:classifiers":[
        {
            "category":"Building & Trades",
            "subcategory":"Construction",
            "type":"Services"
        }
    ],
    "sg:phone":"+1 718 385 1234",
    "sg:postcode":"11236",
    "sg:province":"NY",
    "sg:tags":[
        "steel",
        "works",
        "iron"
    ],
    "wof:name":"Mack Glassnauth Iron Works",
    "wof:placetype":"venue"
},
  "geometry": {"coordinates":[-73.908968,40.650986],"type":"Point"}
}