{
  "type": "Feature",
  "properties": {
    "addr:full":"8523 18th Avenue Brooklyn NY 11214",
    "addr:housenumber":"8523",
    "addr:postcode":"11214",
    "addr:street":"18Th Avenue",
    "iso:country":"US",
    "sg:address":"8523 18th Avenue",
    "sg:city":"Brooklyn",
    "sg:classifiers":[
        {
            "category":"Deli",
            "type":"Food & Drink"
        },
        {
            "category":"Food & Beverages",
            "subcategory":"Bakery",
            "type":"Retail Goods"
        }
    ],
    "sg:phone":"+1 718 234 2266",
    "sg:postcode":"11214",
    "sg:province":"NY",
    "sg:tags":[
        "sandwich"
    ],
    "wof:name":"Peter's Deli Grocery",
    "wof:placetype":"venue"
},
  "geometry": {"coordinates":[-74.00246,40.607244],"type":"Point"}
}