{
  "type": "Feature",
  "properties": {
    "addr:full":"824 Morrow St Staten Island NY 10303",
    "addr:housenumber":"824",
    "addr:postcode":"10303",
    "addr:street":"Morrow St",
    "iso:country":"US",
    "sg:address":"824 Morrow St",
    "sg:city":"Staten Island",
    "sg:classifiers":[
        {
            "category":"Building & Trades",
            "subcategory":"Plumbing",
            "type":"Services"
        }
    ],
    "sg:phone":"+1 718 980 1148",
    "sg:postcode":"10303",
    "sg:province":"NY",
    "wof:name":"Accurate Plumbing & Heating Corp",
    "wof:placetype":"venue"
},
  "geometry": {"coordinates":[-74.17439400000001,40.625869],"type":"Point"}
}