{
  "type": "Feature",
  "properties": {
    "addr:full":"1991 Western Ave Albany NY 12203",
    "addr:housenumber":"1991",
    "addr:postcode":"12203",
    "addr:street":"Western Ave",
    "iso:country":"US",
    "sg:address":"1991 Western Ave",
    "sg:city":"Albany",
    "sg:classifiers":[
        {
            "category":"Restaurant",
            "type":"Food & Drink"
        }
    ],
    "sg:menulink":"http://www.allmenus.com/ny/guilderland/169782-burger-king/menu/",
    "sg:phone":"+1 518 456 6771",
    "sg:postcode":"12203",
    "sg:province":"NY",
    "sg:tags":[
        "burger",
        "american"
    ],
    "wof:name":"Burger King",
    "wof:placetype":"venue"
},
  "geometry": {"coordinates":[-73.88243900000001,42.696377],"type":"Point"}
}