{
  "type": "Feature",
  "properties": {
    "iso:country":"US",
    "sg:address":"471 Boyle Rd",
    "sg:city":"Selden",
    "sg:classifiers":[
        {
            "category":"Recreation",
            "type":"Entertainment"
        }
    ],
    "sg:phone":"+1 631 473 2075",
    "sg:postcode":"11784",
    "sg:province":"NY",
    "sg:tags":[
        "riding",
        "academy"
    ],
    "wof:name":"Old Town Equestrian Ctr",
    "wof:placetype":"venue"
},
  "geometry": {"coordinates":[-73.05465599999999,40.902007],"type":"Point"}
}