{
  "type": "Feature",
  "properties": {
    "iso:country":"US",
    "sg:address":"7435 E Taft Rd",
    "sg:city":"East Syracuse",
    "sg:classifiers":[
        {
            "category":"Restaurant",
            "type":"Food & Drink"
        }
    ],
    "sg:phone":"+1   ",
    "sg:postcode":"13057",
    "sg:province":"NY",
    "sg:tags":[
        "eating"
    ],
    "wof:name":"JRS Bakes and Bbqs",
    "wof:placetype":"venue"
},
  "geometry": {"coordinates":[-75.999078,43.12359],"type":"Point"}
}