{
  "type": "Feature",
  "properties": {
    "iso:country":"US",
    "sg:address":"515 W 20th St",
    "sg:city":"New York",
    "sg:classifiers":[
        {
            "category":"Professional",
            "subcategory":"Advertising",
            "type":"Services"
        }
    ],
    "sg:phone":"+1 646 284 9813",
    "sg:postcode":"10011",
    "sg:province":"NY",
    "sg:tags":[
        "counselor"
    ],
    "wof:name":"ADK America",
    "wof:placetype":"venue"
},
  "geometry": {"coordinates":[-74.007695,40.746774],"type":"Point"}
}