{
  "type": "Feature",
  "properties": {
    "iso:country":"US",
    "sg:address":"765 Forest Ave",
    "sg:city":"Staten Island",
    "sg:classifiers":[
        {
            "category":"Building & Trades",
            "subcategory":"Locksmith",
            "type":"Services"
        }
    ],
    "sg:phone":"+1 718 448 3333",
    "sg:postcode":"10310",
    "sg:province":"NY",
    "sg:tags":[
        "key"
    ],
    "sg:website":"www.popalockofstatenisland.com",
    "wof:name":"Pop A Lock of Ny",
    "wof:placetype":"venue"
},
  "geometry": {"coordinates":[-74.11460700000001,40.629147],"type":"Point"}
}