{
  "type": "Feature",
  "properties": {
    "iso:country":"US",
    "sg:address":"1326 Globe Ave",
    "sg:city":"Elmont",
    "sg:classifiers":[
        {
            "category":"Restaurant",
            "type":"Food & Drink"
        }
    ],
    "sg:phone":"+1   ",
    "sg:postcode":"11003",
    "sg:province":"NY",
    "sg:tags":[
        "eating"
    ],
    "wof:name":"Marios Pizza",
    "wof:placetype":"venue"
},
  "geometry": {"coordinates":[-73.689745,40.703008],"type":"Point"}
}