{
  "type": "Feature",
  "properties": {
    "iso:country":"US",
    "sg:address":"1020 Co Hwy 25",
    "sg:city":"Richfield Spgs",
    "sg:classifiers":[
        {
            "category":"Professional",
            "subcategory":"Computer Services",
            "type":"Services"
        }
    ],
    "sg:phone":"+1 315 858 0938",
    "sg:postcode":"13439",
    "sg:province":"NY",
    "wof:name":"Hinckley Computer Svc",
    "wof:placetype":"venue"
},
  "geometry": {"coordinates":[-75.053539,42.857299],"type":"Point"}
}