{
  "type": "Feature",
  "properties": {
    "iso:country":"US",
    "sg:address":"171 Park Ave",
    "sg:city":"Amityville",
    "sg:classifiers":[
        {
            "category":"Professional",
            "subcategory":"Lawyer & Legal Services",
            "type":"Services"
        }
    ],
    "sg:phone":"+1   ",
    "sg:postcode":"11701",
    "sg:province":"NY",
    "wof:name":"John T Patafio",
    "wof:placetype":"venue"
},
  "geometry": {"coordinates":[-73.417619,40.67766],"type":"Point"}
}