{
  "type": "Feature",
  "properties": {
    "addr:full":"1002 Alabama Ave Brooklyn NY 11207",
    "addr:housenumber":"1002",
    "addr:postcode":"11207",
    "addr:street":"Alabama Ave",
    "iso:country":"US",
    "sg:address":"1002 Alabama Ave",
    "sg:city":"Brooklyn",
    "sg:classifiers":[
        {
            "category":"Wholesale",
            "subcategory":"Machinery & Supplies",
            "type":"Manufacturing & Wholesale Goods"
        }
    ],
    "sg:phone":"+1 718 649 4904",
    "sg:postcode":"11207",
    "sg:province":"NY",
    "sg:tags":[
        "equipment",
        "industrial",
        "auto"
    ],
    "wof:name":"Airweld",
    "wof:placetype":"venue"
},
  "geometry": {"coordinates":[-73.889296,40.65248],"type":"Point"}
}