{
  "type": "Feature",
  "properties": {
    "addr:full":"55 Green St Hudson NY 12534",
    "addr:housenumber":"55",
    "addr:postcode":"12534",
    "addr:street":"Green St",
    "iso:country":"US",
    "sg:address":"55 Green St",
    "sg:city":"Hudson",
    "sg:classifiers":[
        {
            "category":"Shopping",
            "type":"Retail Goods"
        }
    ],
    "sg:phone":"+1   ",
    "sg:postcode":"12534",
    "sg:province":"NY",
    "sg:tags":[
        "water",
        "equipment",
        "conditioning"
    ],
    "wof:name":"Culligan",
    "wof:placetype":"venue"
},
  "geometry": {"coordinates":[-73.77771799999999,42.248005],"type":"Point"}
}