{
  "type": "Feature",
  "properties": {
    "addr:full":"3110 Lawson Blvd Oceanside NY 11572",
    "addr:housenumber":"3110",
    "addr:postcode":"11572",
    "addr:street":"Lawson Blvd",
    "iso:country":"US",
    "sg:address":"3110 Lawson Blvd",
    "sg:city":"Oceanside",
    "sg:classifiers":[
        {
            "category":"Restaurant",
            "type":"Food & Drink"
        }
    ],
    "sg:phone":"+1 516 992 0621",
    "sg:postcode":"11572",
    "sg:province":"NY",
    "sg:tags":[
        "barbeque"
    ],
    "wof:name":"Bad Bobs Bbq",
    "wof:placetype":"venue"
},
  "geometry": {"coordinates":[-73.654454,40.63588],"type":"Point"}
}