{
  "type": "Feature",
  "properties": {
    "iso:country":"US",
    "sg:address":"67 Albany Ave",
    "sg:city":"Kinderhook",
    "sg:classifiers":[
        {
            "category":"Manufacturing",
            "subcategory":"Buildings",
            "type":"Manufacturing & Wholesale Goods"
        },
        {
            "category":"Building & Trades",
            "subcategory":"Construction",
            "type":"Services"
        }
    ],
    "sg:phone":"+1 518 758 7444",
    "sg:postcode":"12106",
    "sg:province":"NY",
    "sg:tags":[
        "industrial",
        "altering",
        "builder",
        "system",
        "specialty",
        "heating",
        "contractors-commercial",
        "home",
        "contractor",
        "remodeling",
        "air conditioning"
    ],
    "wof:name":"W L Neander Inc",
    "wof:placetype":"venue"
},
  "geometry": {"coordinates":[-73.702843,42.401581],"type":"Point"}
}