{
  "type": "Feature",
  "properties": {
    "addr:full":"211 E 46th Street New York NY 10017",
    "addr:housenumber":"211",
    "addr:postcode":"10017",
    "addr:street":"E 46Th Street",
    "iso:country":"US",
    "sg:address":"211 E 46th Street",
    "sg:city":"New York",
    "sg:classifiers":[
        {
            "category":"Professional",
            "subcategory":"Lawyer & Legal Services",
            "type":"Services"
        }
    ],
    "sg:phone":"+1 212 223 3300",
    "sg:postcode":"10017",
    "sg:province":"NY",
    "wof:name":"Vilkas Gil",
    "wof:placetype":"venue"
},
  "geometry": {"coordinates":[-73.972342,40.753223],"type":"Point"}
}