{
  "type": "Feature",
  "properties": {
    "addr:full":"311 Broadway Monticello NY 12701",
    "addr:housenumber":"311",
    "addr:postcode":"12701",
    "addr:street":"Broadway",
    "iso:country":"US",
    "sg:address":"311 Broadway",
    "sg:city":"Monticello",
    "sg:classifiers":[
        {
            "category":"Shopping",
            "subcategory":"Hobbies, Toys, & Games",
            "type":"Retail Goods"
        }
    ],
    "sg:phone":"+1   ",
    "sg:postcode":"12701",
    "sg:province":"NY",
    "wof:name":"Hobby World",
    "wof:placetype":"venue"
},
  "geometry": {"coordinates":[-74.690617,41.655853],"type":"Point"}
}