{
  "type": "Feature",
  "properties": {
    "iso:country":"US",
    "sg:address":"224 Grenadier Ct",
    "sg:city":"Clifton Park",
    "sg:classifiers":[
        {
            "category":"Retail",
            "subcategory":"Animal Services",
            "type":"Services"
        }
    ],
    "sg:phone":"+1 518 383 4787",
    "sg:postcode":"12065",
    "sg:province":"NY",
    "wof:name":"Alana Stevenson",
    "wof:placetype":"venue"
},
  "geometry": {"coordinates":[-73.730379,42.845003],"type":"Point"}
}