{
  "type": "Feature",
  "properties": {
    "addr:full":"30 Dickinson Ave Nyack NY 10960",
    "addr:housenumber":"30",
    "addr:postcode":"10960",
    "addr:street":"Dickinson Ave",
    "iso:country":"US",
    "sg:address":"30 Dickinson Ave",
    "sg:city":"Nyack",
    "sg:classifiers":[
        {
            "category":"Personal",
            "type":"Services"
        }
    ],
    "sg:phone":"+1 845 358 6602",
    "sg:postcode":"10960",
    "sg:province":"NY",
    "sg:tags":[
        "therapist",
        "massage"
    ],
    "wof:name":"Massage In Motion",
    "wof:placetype":"venue"
},
  "geometry": {"coordinates":[-73.93019200000001,41.090256],"type":"Point"}
}