{
  "type": "Feature",
  "properties": {
    "iso:country":"US",
    "sg:address":"1224 E 37th St",
    "sg:city":"Brooklyn",
    "sg:classifiers":[
        {
            "category":"Freight",
            "type":"Transportation"
        }
    ],
    "sg:phone":"+1 718 677 0910",
    "sg:postcode":"11210",
    "sg:province":"NY",
    "wof:name":"Victory Recovery & Trnsprtn",
    "wof:placetype":"venue"
},
  "geometry": {"coordinates":[-73.940247,40.626444],"type":"Point"}
}