{
  "type": "Feature",
  "properties": {
    "iso:country":"US",
    "sg:address":"348 Old Willets Path",
    "sg:city":"Smithtown",
    "sg:classifiers":[
        {
            "category":"Building & Trades",
            "subcategory":"Construction",
            "type":"Services"
        }
    ],
    "sg:phone":"+1 631 360 3599",
    "sg:postcode":"11787",
    "sg:province":"NY",
    "sg:tags":[
        "house"
    ],
    "wof:name":"Simeone Construction",
    "wof:placetype":"venue"
},
  "geometry": {"coordinates":[-73.235669,40.827493],"type":"Point"}
}