{
  "type": "Feature",
  "properties": {
    "addr:full":"5829 Thompson Rd Syracuse NY 13214",
    "addr:housenumber":"5829",
    "addr:postcode":"13214",
    "addr:street":"Thompson Rd",
    "iso:country":"US",
    "sg:address":"5829 Thompson Rd",
    "sg:city":"Syracuse",
    "sg:classifiers":[
        {
            "category":"Personal",
            "subcategory":"Beauty Salon",
            "type":"Services"
        }
    ],
    "sg:phone":"+1 315 446 0101",
    "sg:postcode":"13214",
    "sg:province":"NY",
    "wof:name":"Omars Beauty Salon",
    "wof:placetype":"venue"
},
  "geometry": {"coordinates":[-76.081879,43.05344],"type":"Point"}
}