{
  "type": "Feature",
  "properties": {
    "iso:country":"US",
    "sg:address":"2963 E Main St",
    "sg:city":"Parish",
    "sg:classifiers":[
        {
            "category":"Government",
            "subcategory":"Post Office",
            "type":"Public Place"
        }
    ],
    "sg:phone":"+1   ",
    "sg:postcode":"13131",
    "sg:province":"NY",
    "sg:tags":[
        "postal",
        "us"
    ],
    "wof:name":"US Post Office",
    "wof:placetype":"venue"
},
  "geometry": {"coordinates":[-76.12213800000001,43.405529],"type":"Point"}
}