{
  "type": "Feature",
  "properties": {
    "addr:full":"47 Walker St Walden NY 12586",
    "addr:housenumber":"47",
    "addr:postcode":"12586",
    "addr:street":"Walker St",
    "iso:country":"US",
    "sg:address":"47 Walker St",
    "sg:city":"Walden",
    "sg:classifiers":[
        {
            "category":"Bars & Pubs",
            "type":"Food & Drink"
        }
    ],
    "sg:phone":"+1   ",
    "sg:postcode":"12586",
    "sg:province":"NY",
    "sg:tags":[
        "drinking"
    ],
    "wof:name":"Sweeneys Mvp Pub Restaurant",
    "wof:placetype":"venue"
},
  "geometry": {"coordinates":[-74.197728,41.562308],"type":"Point"}
}