{
  "type": "Feature",
  "properties": {
    "addr:full":"47 Keap St Brooklyn NY 11211",
    "addr:housenumber":"47",
    "addr:postcode":"11211",
    "addr:street":"Keap St",
    "iso:country":"US",
    "sg:address":"47 Keap St",
    "sg:city":"Brooklyn",
    "sg:classifiers":[
        {
            "category":"Organizations",
            "subcategory":"Religious Organization",
            "type":"Services"
        }
    ],
    "sg:phone":"+1 718 384 1029",
    "sg:postcode":"11211",
    "sg:province":"NY",
    "sg:tags":[
        "clergy"
    ],
    "wof:name":"Berel Polatsek",
    "wof:placetype":"venue"
},
  "geometry": {"coordinates":[-73.963255,40.701862],"type":"Point"}
}