{
  "type": "Feature",
  "properties": {
    "addr:full":"2798 Merrick Rd Bellmore NY 11710",
    "addr:housenumber":"2798",
    "addr:postcode":"11710",
    "addr:street":"Merrick Rd",
    "iso:country":"US",
    "sg:address":"2798 Merrick Rd",
    "sg:city":"Bellmore",
    "sg:classifiers":[
        {
            "category":"Retail",
            "subcategory":"Auto Repair",
            "type":"Services"
        }
    ],
    "sg:phone":"+1   ",
    "sg:postcode":"11710",
    "sg:province":"NY",
    "sg:tags":[
        "station",
        "gasoline",
        "general"
    ],
    "wof:name":"East Bay Automotive Service",
    "wof:placetype":"venue"
},
  "geometry": {"coordinates":[-73.52367,40.664107],"type":"Point"}
}