{
  "type": "Feature",
  "properties": {
    "iso:country":"US",
    "sg:address":"57 Tanager Rd",
    "sg:city":"Mahopac",
    "sg:classifiers":[
        {
            "category":"Home & Garden",
            "subcategory":"Household Appliances",
            "type":"Retail Goods"
        }
    ],
    "sg:phone":"+1 914 235 4020",
    "sg:postcode":"10541",
    "sg:province":"NY",
    "sg:tags":[
        "repair"
    ],
    "wof:name":"All Brands Appliance Svce",
    "wof:placetype":"venue"
},
  "geometry": {"coordinates":[-73.72020000000001,41.372501],"type":"Point"}
}