{
  "type": "Feature",
  "properties": {
    "addr:full":"6508 Roosevelt Ave Woodside NY 11377",
    "addr:housenumber":"6508",
    "addr:postcode":"11377",
    "addr:street":"Roosevelt Ave",
    "iso:country":"US",
    "sg:address":"6508 Roosevelt Ave",
    "sg:city":"Woodside",
    "sg:classifiers":[
        {
            "category":"Shopping",
            "subcategory":"Pharmacy",
            "type":"Retail Goods"
        }
    ],
    "sg:phone":"+1 347 448 6965",
    "sg:postcode":"11377",
    "sg:province":"NY",
    "sg:tags":[
        "drugstore"
    ],
    "wof:name":"Rmr Pharmacy Incorporated",
    "wof:placetype":"venue"
},
  "geometry": {"coordinates":[-73.898929,40.745915],"type":"Point"}
}