{
  "type": "Feature",
  "properties": {
    "addr:full":"1000 Waters Pl Bronx NY 10461",
    "addr:housenumber":"1000",
    "addr:postcode":"10461",
    "addr:street":"Waters Pl",
    "iso:country":"US",
    "sg:address":"1000 Waters Pl",
    "sg:city":"Bronx",
    "sg:classifiers":[
        {
            "category":"Health Services",
            "subcategory":"Doctor",
            "type":"Services"
        }
    ],
    "sg:phone":"+1 718 239 2635",
    "sg:postcode":"10461",
    "sg:province":"NY",
    "wof:name":"Mental Health Office Of",
    "wof:placetype":"venue"
},
  "geometry": {"coordinates":[-73.83825899999999,40.842714],"type":"Point"}
}