{
  "type": "Feature",
  "properties": {
    "addr:full":"96 Viola Rd Suffern NY 10901",
    "addr:housenumber":"96",
    "addr:postcode":"10901",
    "addr:street":"Viola Rd",
    "iso:country":"US",
    "sg:address":"96 Viola Rd",
    "sg:city":"Suffern",
    "sg:classifiers":[
        {
            "category":"Real Estate",
            "subcategory":"Real Estate Agent",
            "type":"Services"
        }
    ],
    "sg:phone":"+1 845 357 5777",
    "sg:postcode":"10901",
    "sg:province":"NY",
    "wof:name":"Viking Realty",
    "wof:placetype":"venue"
},
  "geometry": {"coordinates":[-74.099079,41.137597],"type":"Point"}
}