{
  "type": "Feature",
  "properties": {
    "addr:full":"1402 Gravesend Neck Rd Brooklyn NY 11229",
    "addr:housenumber":"1402",
    "addr:postcode":"11229",
    "addr:street":"Gravesend Neck Rd",
    "iso:country":"US",
    "sg:address":"1402 Gravesend Neck Rd",
    "sg:city":"Brooklyn",
    "sg:classifiers":[
        {
            "category":"Food & Beverages",
            "subcategory":"Fruits & Vegetables",
            "type":"Retail Goods"
        }
    ],
    "sg:phone":"+1   ",
    "sg:postcode":"11229",
    "sg:province":"NY",
    "wof:name":"C K Fruits & Vegetable Store",
    "wof:placetype":"venue"
},
  "geometry": {"coordinates":[-73.955641,40.594774],"type":"Point"}
}