{
  "type": "Feature",
  "properties": {
    "addr:full":"163 Bleecker St New York NY 10012",
    "addr:housenumber":"163",
    "addr:postcode":"10012",
    "addr:street":"Bleecker St",
    "iso:country":"US",
    "sg:address":"163 Bleecker St",
    "sg:city":"New York",
    "sg:classifiers":[
        {
            "category":"Restaurant",
            "type":"Food & Drink"
        }
    ],
    "sg:menulink":"http://www.allmenus.com/ny/new-york/106400-suzies/menu/",
    "sg:phone":"+1 212 777 1395",
    "sg:postcode":"10012",
    "sg:province":"NY",
    "sg:tags":[
        "asian",
        "chinese"
    ],
    "wof:name":"Suzies",
    "wof:placetype":"venue"
},
  "geometry": {"coordinates":[-73.999942,40.728807],"type":"Point"}
}