{
  "type": "Feature",
  "properties": {
    "iso:country":"US",
    "sg:address":"1732 Great Neck Rd",
    "sg:city":"Copiague",
    "sg:classifiers":[
        {
            "category":"Sports & Exercise",
            "subcategory":"Race Track",
            "type":"Entertainment"
        }
    ],
    "sg:phone":"+1 631 789 8900",
    "sg:postcode":"11726",
    "sg:province":"NY",
    "wof:name":"Riverhead Raceway",
    "wof:placetype":"venue"
},
  "geometry": {"coordinates":[-73.39964000000001,40.681045],"type":"Point"}
}