{
  "type": "Feature",
  "properties": {
    "addr:full":"1638 W 8th St Brooklyn NY 11223",
    "addr:housenumber":"1638",
    "addr:postcode":"11223",
    "addr:street":"W 8Th St",
    "iso:country":"US",
    "sg:address":"1638 W 8th St",
    "sg:city":"Brooklyn",
    "sg:classifiers":[
        {
            "category":"Professional",
            "type":"Services"
        }
    ],
    "sg:phone":"+1   ",
    "sg:postcode":"11223",
    "sg:province":"NY",
    "wof:name":"Arm Ing Inc",
    "wof:placetype":"venue"
},
  "geometry": {"coordinates":[-73.981407,40.606512],"type":"Point"}
}