{
  "type": "Feature",
  "properties": {
    "iso:country":"US",
    "sg:address":"8651 Slayton Settlement Rd",
    "sg:city":"Gasport",
    "sg:classifiers":[
        {
            "category":"Farming",
            "subcategory":"Dairy Farm",
            "type":"Manufacturing & Wholesale Goods"
        }
    ],
    "sg:phone":"+1 716 772 7179",
    "sg:postcode":"14067",
    "sg:province":"NY",
    "wof:name":"Verrati Farms LLC",
    "wof:placetype":"venue"
},
  "geometry": {"coordinates":[-78.549082,43.207207],"type":"Point"}
}