{
  "type": "Feature",
  "properties": {
    "addr:full":"29 Westwood Close Irvington NY 10533",
    "addr:housenumber":"29",
    "addr:postcode":"ny 10533",
    "addr:street":"Westwood Close",
    "iso:country":"US",
    "sg:address":"29 Westwood Close",
    "sg:city":"Irvington",
    "sg:classifiers":[
        {
            "category":"Banks & Credit Unions",
            "subcategory":"Bank",
            "type":"Services"
        }
    ],
    "sg:phone":"+1 914 591 8752",
    "sg:postcode":"10533",
    "sg:province":"NY",
    "sg:tags":[
        "loan"
    ],
    "wof:name":"Greenfund Commercial Credit",
    "wof:placetype":"venue"
},
  "geometry": {"coordinates":[-73.864828,41.038488],"type":"Point"}
}