{
  "type": "Feature",
  "properties": {
    "addr:full":"907 Southwestern Dr Jamestown NY 14701",
    "addr:housenumber":"907",
    "addr:postcode":"14701",
    "addr:street":"Southwestern Dr",
    "iso:country":"US",
    "sg:address":"907 Southwestern Dr",
    "sg:city":"Jamestown",
    "sg:classifiers":[
        {
            "category":"Building & Trades",
            "subcategory":"Construction",
            "type":"Services"
        }
    ],
    "sg:phone":"+1 716 483 6629",
    "sg:postcode":"14701",
    "sg:province":"NY",
    "sg:tags":[
        "contractor"
    ],
    "wof:name":"Tefft Construction Co",
    "wof:placetype":"venue"
},
  "geometry": {"coordinates":[-79.28391499999999,42.03846],"type":"Point"}
}