{
  "type": "Feature",
  "properties": {
    "addr:full":"4944 Elgin Cir Syracuse NY 13215",
    "addr:housenumber":"4944",
    "addr:postcode":"13215",
    "addr:street":"Elgin Cir",
    "iso:country":"US",
    "sg:address":"4944 Elgin Cir",
    "sg:city":"Syracuse",
    "sg:classifiers":[
        {
            "category":"Shopping",
            "subcategory":"Beauty & Cosmetics",
            "type":"Retail Goods"
        }
    ],
    "sg:phone":"+1 315 469 0898",
    "sg:postcode":"13215",
    "sg:province":"NY",
    "sg:tags":[
        "equipment",
        "perfume",
        "salons-equipment",
        "supply"
    ],
    "sg:website":"http://www.marykay.com",
    "wof:name":"Mary Kay Cosmetics",
    "wof:placetype":"venue"
},
  "geometry": {"coordinates":[-76.173771,43.006418],"type":"Point"}
}