{
  "type": "Feature",
  "properties": {
    "iso:country":"US",
    "sg:address":"200 Perrin Dr",
    "sg:city":"Rochester",
    "sg:classifiers":[
        {
            "category":"Banks & Credit Unions",
            "subcategory":"Bank",
            "type":"Services"
        }
    ],
    "sg:phone":"+1 585 342 5680",
    "sg:postcode":"14622",
    "sg:province":"NY",
    "sg:tags":[
        "federal",
        "state"
    ],
    "wof:name":"Irondequoit Federal Credit Un",
    "wof:placetype":"venue"
},
  "geometry": {"coordinates":[-77.563565,43.200153],"type":"Point"}
}