{
  "type": "Feature",
  "properties": {
    "iso:country":"US",
    "sg:address":"Hotel At Times Square 59 W 46th St 2nd Fl",
    "sg:city":"Manhattan",
    "sg:classifiers":[
        {
            "category":"Bars & Pubs",
            "subcategory":"Lounge",
            "type":"Food & Drink"
        }
    ],
    "sg:postcode":"10036",
    "sg:province":"NY",
    "wof:name":"Upstairs Bar",
    "wof:placetype":"venue"
},
  "geometry": {"coordinates":[-73.981134,40.757359],"type":"Point"}
}