{
  "type": "Feature",
  "properties": {
    "iso:country":"US",
    "sg:address":"4370 US Hwy 11",
    "sg:city":"De Kalb Junction",
    "sg:classifiers":[
        {
            "category":"Shopping",
            "subcategory":"Used Merchandise",
            "type":"Retail Goods"
        }
    ],
    "sg:phone":"+1 315 347 4230",
    "sg:postcode":"13630",
    "sg:province":"NY",
    "sg:tags":[
        "antique"
    ],
    "wof:name":"B & W Collectables",
    "wof:placetype":"venue"
},
  "geometry": {"coordinates":[-75.270847,44.507504],"type":"Point"}
}