{
  "type": "Feature",
  "properties": {
    "iso:country":"US",
    "sg:address":"290 Malcolm X Blvd",
    "sg:city":"New York",
    "sg:classifiers":[
        {
            "category":"Shopping",
            "subcategory":"Optician",
            "type":"Retail Goods"
        }
    ],
    "sg:phone":"+1 212 876 4229",
    "sg:postcode":"10027",
    "sg:province":"NY",
    "sg:tags":[
        "eyewear"
    ],
    "wof:name":"Cohen's Fashio Optical",
    "wof:placetype":"venue"
},
  "geometry": {"coordinates":[-73.94543899999999,40.807391],"type":"Point"}
}