{
  "type": "Feature",
  "properties": {
    "iso:country":"US",
    "sg:address":"888 Old Country Rd",
    "sg:city":"Plainview",
    "sg:classifiers":[
        {
            "category":"Health Services",
            "subcategory":"Hospital",
            "type":"Services"
        }
    ],
    "sg:phone":"+1 516 719 3000",
    "sg:postcode":"11803",
    "sg:province":"NY",
    "sg:website":"www.northshorelij.com",
    "wof:name":"Plainview Hospital",
    "wof:placetype":"venue"
},
  "geometry": {"coordinates":[-73.481602,40.773781],"type":"Point"}
}