{
  "type": "Feature",
  "properties": {
    "addr:full":"420 Hamilton Valley Rd Spencer NY 14883",
    "addr:housenumber":"420",
    "addr:postcode":"14883",
    "addr:street":"Hamilton Valley Rd",
    "iso:country":"US",
    "sg:address":"420 Hamilton Valley Rd",
    "sg:city":"Spencer",
    "sg:classifiers":[
        {
            "category":"Manufacturing",
            "subcategory":"Lumber",
            "type":"Manufacturing & Wholesale Goods"
        }
    ],
    "sg:phone":"+1 607 589 4240",
    "sg:postcode":"14883",
    "sg:province":"NY",
    "sg:tags":[
        "sawmill"
    ],
    "wof:name":"Rock Oak Lumber",
    "wof:placetype":"venue"
},
  "geometry": {"coordinates":[-76.442123,42.139176],"type":"Point"}
}