{
  "type": "Feature",
  "properties": {
    "iso:country":"US",
    "sg:address":"41 Brewster St",
    "sg:city":"Kingston",
    "sg:classifiers":[
        {
            "category":"Professional",
            "subcategory":"Business Services",
            "type":"Services"
        }
    ],
    "sg:phone":"+1 845 338 3601",
    "sg:postcode":"12401",
    "sg:province":"NY",
    "sg:tags":[
        "mail",
        "voice",
        "messaging"
    ],
    "wof:name":"Business & Pro Answering Svc",
    "wof:placetype":"venue"
},
  "geometry": {"coordinates":[-73.99387299999999,41.925964],"type":"Point"}
}