{
  "type": "Feature",
  "properties": {
    "iso:country":"US",
    "sg:address":"614 Rogers Ave",
    "sg:city":"Brooklyn",
    "sg:classifiers":[
        {
            "category":"Shopping",
            "subcategory":"Clothing, Apparel, & Fashions",
            "type":"Retail Goods"
        }
    ],
    "sg:phone":"+1 718 703 1764",
    "sg:postcode":"11225",
    "sg:province":"NY",
    "sg:tags":[
        "designer"
    ],
    "wof:name":"T C Designs By Tony",
    "wof:placetype":"venue"
},
  "geometry": {"coordinates":[-73.95313899999999,40.656267],"type":"Point"}
}