{
  "type": "Feature",
  "properties": {
    "iso:country":"US",
    "sg:address":"2021 Main St",
    "sg:city":"Niagara Falls",
    "sg:classifiers":[
        {
            "category":"Freight",
            "type":"Transportation"
        }
    ],
    "sg:phone":"+1   ",
    "sg:postcode":"14305",
    "sg:province":"NY",
    "sg:tags":[
        "local",
        "storage",
        "trucking"
    ],
    "wof:name":"Ace Movers of Niagara Inc",
    "wof:placetype":"venue"
},
  "geometry": {"coordinates":[-79.05369,43.107542],"type":"Point"}
}