{
  "type": "Feature",
  "properties": {
    "addr:full":"238 N 9th St Brooklyn NY 11211",
    "addr:housenumber":"238",
    "addr:postcode":"11211",
    "addr:street":"N 9Th St",
    "iso:country":"US",
    "sg:address":"238 N 9th St",
    "sg:city":"Brooklyn",
    "sg:classifiers":[
        {
            "category":"Building & Trades",
            "subcategory":"Construction",
            "type":"Services"
        }
    ],
    "sg:phone":"+1 718 963 3555",
    "sg:postcode":"11211",
    "sg:province":"NY",
    "sg:tags":[
        "maker",
        "cabinet"
    ],
    "wof:name":"Gundy Custom Builders Inc",
    "wof:placetype":"venue"
},
  "geometry": {"coordinates":[-73.95268799999999,40.716574],"type":"Point"}
}