{
  "type": "Feature",
  "properties": {
    "iso:country":"US",
    "sg:address":"24 Rowland Ave",
    "sg:city":"Buffalo",
    "sg:classifiers":[
        {
            "category":"Professional",
            "subcategory":"Engineering",
            "type":"Services"
        }
    ],
    "sg:phone":"+1   ",
    "sg:postcode":"14225",
    "sg:province":"NY",
    "wof:name":"Peggy Wyman",
    "wof:placetype":"venue"
},
  "geometry": {"coordinates":[-78.791618,42.920002],"type":"Point"}
}