{
  "type": "Feature",
  "properties": {
    "addr:full":"4 Santee St Middletown NY 10940",
    "addr:housenumber":"4",
    "addr:postcode":"10940",
    "addr:street":"Santee St",
    "iso:country":"US",
    "sg:address":"4 Santee St",
    "sg:city":"Middletown",
    "sg:classifiers":[
        {
            "category":"Manufacturing",
            "subcategory":"Food",
            "type":"Manufacturing & Wholesale Goods"
        }
    ],
    "sg:phone":"+1   ",
    "sg:postcode":"10940",
    "sg:province":"NY",
    "sg:tags":[
        "grocery",
        "mfg"
    ],
    "wof:name":"Wan Ja Shan",
    "wof:placetype":"venue"
},
  "geometry": {"coordinates":[-74.388831,41.463115],"type":"Point"}
}