{
  "type": "Feature",
  "properties": {
    "iso:country":"US",
    "sg:address":"1 Main St",
    "sg:city":"Newfield",
    "sg:classifiers":[
        {
            "category":"Building & Trades",
            "subcategory":"Construction",
            "type":"Services"
        }
    ],
    "sg:phone":"+1 607 564 0466",
    "sg:postcode":"14867",
    "sg:province":"NY",
    "sg:tags":[
        "contractor"
    ],
    "wof:name":"Anthony Capalongo",
    "wof:placetype":"venue"
},
  "geometry": {"coordinates":[-76.57796399999999,42.369693],"type":"Point"}
}