{
  "type": "Feature",
  "properties": {
    "addr:full":"708 Burnside Ave Inwood NY 11096",
    "addr:housenumber":"708",
    "addr:postcode":"11096",
    "addr:street":"Burnside Ave",
    "iso:country":"US",
    "sg:address":"708 Burnside Ave",
    "sg:city":"Inwood",
    "sg:classifiers":[
        {
            "category":"Retail",
            "subcategory":"Auto Repair",
            "type":"Services"
        }
    ],
    "sg:phone":"+1   ",
    "sg:postcode":"11096",
    "sg:province":"NY",
    "sg:tags":[
        "automobile",
        "used",
        "general"
    ],
    "wof:name":"T & F Performance",
    "wof:placetype":"venue"
},
  "geometry": {"coordinates":[-73.73802499999999,40.623419],"type":"Point"}
}