{
  "type": "Feature",
  "properties": {
    "addr:full":"1997 State Hwy 17M Goshen NY 10924",
    "addr:housenumber":"1997",
    "addr:postcode":"10924",
    "addr:street":"State Hwy",
    "iso:country":"US",
    "sg:address":"1997 State Hwy 17M",
    "sg:city":"Goshen",
    "sg:classifiers":[
        {
            "category":"Wholesale",
            "subcategory":"Medical Equipment & Supplies",
            "type":"Manufacturing & Wholesale Goods"
        }
    ],
    "sg:phone":"+1 845 294 7157",
    "sg:postcode":"10924",
    "sg:province":"NY",
    "wof:name":"Gericare Providers Inc",
    "wof:placetype":"venue"
},
  "geometry": {"coordinates":[-74.32069799999999,41.39158],"type":"Point"}
}