{
  "type": "Feature",
  "properties": {
    "iso:country":"US",
    "sg:address":"707 Executive Blvd",
    "sg:city":"Valley Cottage",
    "sg:classifiers":[
        {
            "category":"Professional",
            "type":"Services"
        }
    ],
    "sg:phone":"+1 845 268 8165",
    "sg:postcode":"10989",
    "sg:province":"NY",
    "wof:name":"Kilns Service & Sales Inc",
    "wof:placetype":"venue"
},
  "geometry": {"coordinates":[-73.943057,41.129374],"type":"Point"}
}