{
  "type": "Feature",
  "properties": {
    "iso:country":"US",
    "sg:address":"506 Piermont Ave",
    "sg:city":"Piermont",
    "sg:classifiers":[
        {
            "category":"Restaurant",
            "type":"Food & Drink"
        }
    ],
    "sg:phone":"+1 845 359 7007",
    "sg:postcode":"10968",
    "sg:province":"NY",
    "sg:website":"www.xaviars.com",
    "wof:name":"Xaviar's Restaurant-Piermont",
    "wof:placetype":"venue"
},
  "geometry": {"coordinates":[-73.916161,41.039824],"type":"Point"}
}