{
  "type": "Feature",
  "properties": {
    "iso:country":"US",
    "sg:address":"911 Park Ave",
    "sg:city":"New York",
    "sg:classifiers":[
        {
            "category":"Health Services",
            "subcategory":"Doctor",
            "type":"Services"
        }
    ],
    "sg:phone":"+1 212 772 7242",
    "sg:postcode":"10075",
    "sg:province":"NY",
    "wof:name":"Luo Wayne Dr MD",
    "wof:placetype":"venue"
},
  "geometry": {"coordinates":[-73.959733,40.776199],"type":"Point"}
}