{
  "type": "Feature",
  "properties": {
    "iso:country":"US",
    "sg:address":"450 N End Ave",
    "sg:city":"New York",
    "sg:classifiers":[
        {
            "category":"Professional",
            "subcategory":"Business Services",
            "type":"Services"
        }
    ],
    "sg:phone":"+1   ",
    "sg:postcode":"10282",
    "sg:province":"NY",
    "sg:tags":[
        "point",
        "sale",
        "payment",
        "solution"
    ],
    "wof:name":"Retail Merchant Services LLC",
    "wof:placetype":"venue"
},
  "geometry": {"coordinates":[-74.013808,40.717608],"type":"Point"}
}