{
  "type": "Feature",
  "properties": {
    "iso:country":"US",
    "sg:address":"90 S Long Beach Rd",
    "sg:city":"Rockville Centre",
    "sg:classifiers":[
        {
            "category":"Wholesale",
            "subcategory":"Non-durable Goods",
            "type":"Manufacturing & Wholesale Goods"
        }
    ],
    "sg:phone":"+1 516 764 8885",
    "sg:postcode":"11570",
    "sg:province":"NY",
    "wof:name":"Marcus Sales Inc",
    "wof:placetype":"venue"
},
  "geometry": {"coordinates":[-73.63549399999999,40.652541],"type":"Point"}
}