{
  "type": "Feature",
  "properties": {
    "addr:full":"66 Main Ave Wynantskill NY 12198",
    "addr:housenumber":"66",
    "addr:postcode":"12198",
    "addr:street":"Main Ave",
    "iso:country":"US",
    "sg:address":"66 Main Ave",
    "sg:city":"Wynantskill",
    "sg:classifiers":[
        {
            "category":"Restaurant",
            "type":"Food & Drink"
        }
    ],
    "sg:menulink":"http://www.allmenus.com/ny/north-greenbush/189356-mcdonalds/menu/",
    "sg:phone":"+1 518 283 2089",
    "sg:postcode":"12198",
    "sg:province":"NY",
    "sg:tags":[
        "burger",
        "american"
    ],
    "wof:name":"McDonald's",
    "wof:placetype":"venue"
},
  "geometry": {"coordinates":[-73.64708899999999,42.697224],"type":"Point"}
}