{
  "type": "Feature",
  "properties": {
    "addr:full":"4549 218th St Bayside NY 11361",
    "addr:housenumber":"4549",
    "addr:postcode":"11361",
    "addr:street":"218Th St",
    "iso:country":"US",
    "sg:address":"4549 218th St",
    "sg:city":"Bayside",
    "sg:classifiers":[
        {
            "category":"Professional",
            "type":"Services"
        }
    ],
    "sg:phone":"+1 718 229 0275",
    "sg:postcode":"11361",
    "sg:province":"NY",
    "sg:tags":[
        "publication",
        "editorial"
    ],
    "wof:name":"Deborah Agosta Editor",
    "wof:placetype":"venue"
},
  "geometry": {"coordinates":[-73.763593,40.76019],"type":"Point"}
}