{
  "type": "Feature",
  "properties": {
    "addr:full":"168 Canal St New York NY 10013",
    "addr:housenumber":"168",
    "addr:postcode":"10013",
    "addr:street":"Canal St",
    "iso:country":"US",
    "sg:address":"168 Canal St",
    "sg:city":"New York",
    "sg:classifiers":[
        {
            "category":"Professional",
            "subcategory":"Accounting & Tax Preparation",
            "type":"Services"
        }
    ],
    "sg:phone":"+1 212 334 1902",
    "sg:postcode":"10013",
    "sg:province":"NY",
    "sg:tags":[
        "accountant"
    ],
    "wof:name":"Mak & Co",
    "wof:placetype":"venue"
},
  "geometry": {"coordinates":[-73.99772,40.716712],"type":"Point"}
}