{
  "type": "Feature",
  "properties": {
    "addr:full":"274 Knickerbocker Ave Brooklyn NY 11237",
    "addr:housenumber":"274",
    "addr:postcode":"11237",
    "addr:street":"Knickerbocker Ave",
    "iso:country":"US",
    "sg:address":"274 Knickerbocker Ave",
    "sg:city":"Brooklyn",
    "sg:classifiers":[
        {
            "category":"Food & Beverages",
            "subcategory":"Groceries & Convenience Stores",
            "type":"Retail Goods"
        }
    ],
    "sg:phone":"+1 718 628 4816",
    "sg:postcode":"11237",
    "sg:province":"NY",
    "wof:name":"El Mercadito",
    "wof:placetype":"venue"
},
  "geometry": {"coordinates":[-73.924599,40.702202],"type":"Point"}
}