{
  "type": "Feature",
  "properties": {
    "addr:full":"310 W 83 St New York NY 10024",
    "addr:housenumber":"310",
    "addr:postcode":"10024",
    "addr:street":"W 83 St",
    "iso:country":"US",
    "sg:address":"310 W 83 St",
    "sg:city":"New York",
    "sg:classifiers":[
        {
            "category":"Retail",
            "subcategory":"Repair Shop",
            "type":"Services"
        }
    ],
    "sg:phone":"+1 646 224 0813",
    "sg:postcode":"10024",
    "sg:province":"NY",
    "sg:tags":[
        "lock",
        "locksmith"
    ],
    "wof:name":"Number 1 Emergency A Number 1",
    "wof:placetype":"venue"
},
  "geometry": {"coordinates":[-73.98103500000001,40.78755],"type":"Point"}
}