{
  "type": "Feature",
  "properties": {
    "addr:full":"623 Agar St Yonkers NY 10701",
    "addr:housenumber":"623",
    "addr:postcode":"10701",
    "addr:street":"Agar St",
    "iso:country":"US",
    "sg:address":"623 Agar St",
    "sg:city":"Yonkers",
    "sg:classifiers":[
        {
            "category":"Building & Trades",
            "subcategory":"Plumbing",
            "type":"Services"
        }
    ],
    "sg:phone":"+1 914 423 3700",
    "sg:postcode":"10701",
    "sg:province":"NY",
    "sg:tags":[
        "plumbing",
        "heating",
        "contractor"
    ],
    "wof:name":"Arthur Pagano Jr Inc",
    "wof:placetype":"venue"
},
  "geometry": {"coordinates":[-73.876852,40.949234],"type":"Point"}
}