{
  "type": "Feature",
  "properties": {
    "iso:country":"US",
    "sg:address":"1223 Albany Rd",
    "sg:city":"Clayville",
    "sg:classifiers":[
        {
            "category":"Wholesale",
            "subcategory":"Construction Materials",
            "type":"Manufacturing & Wholesale Goods"
        },
        {
            "category":"Home & Garden",
            "subcategory":"Building Materials",
            "type":"Retail Goods"
        },
        {
            "category":"Building & Trades",
            "subcategory":"Construction",
            "type":"Services"
        }
    ],
    "sg:phone":"+1 315 737 2000",
    "sg:postcode":"13322",
    "sg:province":"NY",
    "sg:tags":[
        "asphalt",
        "supply",
        "contractor",
        "equipment",
        "paving",
        "masonry",
        "sealcoating"
    ],
    "wof:name":"Barrett Paving Materials Inc",
    "wof:placetype":"venue"
},
  "geometry": {"coordinates":[-75.187471,42.981742],"type":"Point"}
}