{
  "type": "Feature",
  "properties": {
    "addr:full":"5059 E Main Street Rd Batavia NY 14020",
    "addr:housenumber":"5059",
    "addr:postcode":"14020",
    "addr:street":"E Main Street Rd",
    "iso:country":"US",
    "sg:address":"5059 E Main Street Rd",
    "sg:city":"Batavia",
    "sg:classifiers":[
        {
            "category":"Wholesale",
            "subcategory":"Electrical",
            "type":"Manufacturing & Wholesale Goods"
        }
    ],
    "sg:phone":"+1 585 343 3448",
    "sg:postcode":"14020",
    "sg:province":"NY",
    "sg:tags":[
        "equipment",
        "electric",
        "supply"
    ],
    "wof:name":"Country Line Electrical Distrs",
    "wof:placetype":"venue"
},
  "geometry": {"coordinates":[-78.148304,42.992428],"type":"Point"}
}