{
  "type": "Feature",
  "properties": {
    "iso:country":"US",
    "sg:address":"3491 Delaware Ave",
    "sg:city":"Buffalo",
    "sg:classifiers":[
        {
            "category":"Insurance",
            "subcategory":"Insurance Agent",
            "type":"Services"
        }
    ],
    "sg:phone":"+1 716 877 2222",
    "sg:postcode":"14217",
    "sg:province":"NY",
    "wof:name":"Kusch & Koehler Co",
    "wof:placetype":"venue"
},
  "geometry": {"coordinates":[-78.872108,42.979484],"type":"Point"}
}