{
  "type": "Feature",
  "properties": {
    "iso:country":"US",
    "sg:address":"14 Wall St",
    "sg:city":"New York",
    "sg:classifiers":[
        {
            "category":"Manufacturing",
            "subcategory":"Printing",
            "type":"Manufacturing & Wholesale Goods"
        }
    ],
    "sg:phone":"+1   ",
    "sg:postcode":"10005",
    "sg:province":"NY",
    "sg:tags":[
        "newspaper"
    ],
    "wof:name":"Shiv Supplies Inc",
    "wof:placetype":"venue"
},
  "geometry": {"coordinates":[-74.010801,40.707328],"type":"Point"}
}