{
  "type": "Feature",
  "properties": {
    "addr:full":"6051 Transit Rd Depew NY 14043",
    "addr:housenumber":"6051",
    "addr:postcode":"14043",
    "addr:street":"Transit Rd",
    "iso:country":"US",
    "sg:address":"6051 Transit Rd",
    "sg:city":"Depew",
    "sg:classifiers":[
        {
            "category":"Shopping",
            "subcategory":"Department Store",
            "type":"Retail Goods"
        }
    ],
    "sg:phone":"+1 716 685 4968",
    "sg:postcode":"14043",
    "sg:province":"NY",
    "wof:name":"Family Dollar Store",
    "wof:placetype":"venue"
},
  "geometry": {"coordinates":[-78.69690799999999,42.919543],"type":"Point"}
}