{
  "type": "Feature",
  "properties": {
    "addr:full":"21 Spring St Hawthorne NY 10532",
    "addr:housenumber":"21",
    "addr:postcode":"10532",
    "addr:street":"Spring St",
    "iso:country":"US",
    "sg:address":"21 Spring St",
    "sg:city":"Hawthorne",
    "sg:classifiers":[
        {
            "category":"Health Services",
            "subcategory":"Podiatrist",
            "type":"Services"
        }
    ],
    "sg:phone":"+1 914 725 7171",
    "sg:postcode":"10532",
    "sg:province":"NY",
    "wof:name":"Marzano Podiatry",
    "wof:placetype":"venue"
},
  "geometry": {"coordinates":[-73.79319,41.100319],"type":"Point"}
}