{
  "type": "Feature",
  "properties": {
    "iso:country":"US",
    "sg:address":"66 Madison Ave",
    "sg:city":"Manhattan",
    "sg:classifiers":[
        {
            "category":"Restaurant",
            "type":"Food & Drink"
        }
    ],
    "sg:phone":"+1 212 213 0708",
    "sg:postcode":"10016",
    "sg:province":"NY",
    "sg:tags":[
        "mexican"
    ],
    "sg:website":"www.chozanyc.com",
    "wof:name":"Choza Taquer?a",
    "wof:placetype":"venue"
},
  "geometry": {"coordinates":[-73.986362,40.743759],"type":"Point"}
}