{
  "type": "Feature",
  "properties": {
    "addr:full":"2067 Buffalo St Exd Jamestown NY 14701",
    "addr:housenumber":"2067",
    "addr:postcode":"14701",
    "addr:street":"Buffalo St Exd",
    "iso:country":"US",
    "sg:address":"2067 Buffalo St Exd",
    "sg:city":"Jamestown",
    "sg:classifiers":[
        {
            "category":"Professional",
            "subcategory":"Accounting & Tax Preparation",
            "type":"Services"
        }
    ],
    "sg:phone":"+1 716 483 3753",
    "sg:postcode":"14701",
    "sg:province":"NY",
    "sg:tags":[
        "return",
        "filing"
    ],
    "wof:name":"Doktor Bookkeeping & Tax Svc",
    "wof:placetype":"venue"
},
  "geometry": {"coordinates":[-79.20101200000001,42.102845],"type":"Point"}
}