{
  "type": "Feature",
  "properties": {
    "iso:country":"US",
    "sg:address":"40 Liberty St",
    "sg:city":"Arcade",
    "sg:classifiers":[
        {
            "category":"Home & Garden",
            "subcategory":"Home Furnishings",
            "type":"Retail Goods"
        }
    ],
    "sg:phone":"+1   ",
    "sg:postcode":"14009",
    "sg:province":"NY",
    "wof:name":"Susan Pauly",
    "wof:placetype":"venue"
},
  "geometry": {"coordinates":[-78.421757,42.533138],"type":"Point"}
}