{
  "type": "Feature",
  "properties": {
    "addr:full":"334 Amsterdam Avenue New York NY 10023",
    "addr:housenumber":"334",
    "addr:postcode":"10023",
    "addr:street":"Amsterdam Avenue",
    "iso:country":"US",
    "sg:address":"334 Amsterdam Avenue",
    "sg:city":"New York",
    "sg:classifiers":[
        {
            "category":"Sports & Exercise",
            "subcategory":"Gym",
            "type":"Entertainment"
        }
    ],
    "sg:phone":"+1 646 505 4457",
    "sg:postcode":"10023",
    "sg:province":"NY",
    "sg:tags":[
        "pilate"
    ],
    "sg:website":"www.centerstudionyc.com",
    "wof:name":"The Center Studio",
    "wof:placetype":"venue"
},
  "geometry": {"coordinates":[-73.97992600000001,40.780713],"type":"Point"}
}