{
  "type": "Feature",
  "properties": {
    "iso:country":"US",
    "sg:address":"1100 Madison Ave",
    "sg:city":"Albany",
    "sg:classifiers":[
        {
            "category":"Bars & Pubs",
            "subcategory":"Lounge",
            "type":"Food & Drink"
        }
    ],
    "sg:menulink":"http://www.allmenus.com/ny/albany/37603-peking--alibis-martini-lounge/menu/",
    "sg:phone":"+1 518 489 0606",
    "sg:postcode":"12208",
    "sg:province":"NY",
    "sg:tags":[
        "asian",
        "chinese"
    ],
    "wof:name":"Peking & Alibi's Martini Lounge",
    "wof:placetype":"venue"
},
  "geometry": {"coordinates":[-73.79149200000001,42.666058],"type":"Point"}
}