{
  "type": "Feature",
  "properties": {
    "addr:full":"2340 30th Avenue Astoria NY 11102",
    "addr:housenumber":"2340",
    "addr:postcode":"11102",
    "addr:street":"30Th Avenue",
    "iso:country":"US",
    "sg:address":"2340 30th Avenue",
    "sg:city":"Astoria",
    "sg:classifiers":[
        {
            "category":"Health Services",
            "subcategory":"Doctor",
            "type":"Services"
        }
    ],
    "sg:phone":"+1 718 726 3535",
    "sg:postcode":"11102",
    "sg:province":"NY",
    "wof:name":"Mehra Sunil MD",
    "wof:placetype":"venue"
},
  "geometry": {"coordinates":[-73.925918,40.768878],"type":"Point"}
}