{
  "type": "Feature",
  "properties": {
    "iso:country":"US",
    "sg:address":"136 Stevens Ave",
    "sg:city":"Mt Vernon",
    "sg:classifiers":[
        {
            "category":"Health Services",
            "subcategory":"Clinic",
            "type":"Services"
        }
    ],
    "sg:phone":"+1 914 664 1393",
    "sg:postcode":"10550",
    "sg:province":"NY",
    "sg:tags":[
        "home"
    ],
    "wof:name":"Home Health Care Of Mt Vernon",
    "wof:placetype":"venue"
},
  "geometry": {"coordinates":[-73.839963,40.911329],"type":"Point"}
}