{
  "type": "Feature",
  "properties": {
    "iso:country":"US",
    "sg:address":"2911 W 15th St",
    "sg:city":"Brooklyn",
    "sg:classifiers":[
        {
            "category":"Organizations",
            "subcategory":"Membership Organization",
            "type":"Services"
        }
    ],
    "sg:phone":"+1 718 946 9270",
    "sg:postcode":"11224",
    "sg:province":"NY",
    "wof:name":"Genie Foundation",
    "wof:placetype":"venue"
},
  "geometry": {"coordinates":[-73.98234100000001,40.575661],"type":"Point"}
}