{
  "type": "Feature",
  "properties": {
    "addr:full":"508 E 5 St New York NY 10009",
    "addr:housenumber":"508;5",
    "addr:postcode":"10009",
    "addr:street":"E",
    "iso:country":"US",
    "sg:address":"508 E 5 St",
    "sg:city":"New York",
    "sg:classifiers":[
        {
            "category":"Building & Trades",
            "subcategory":"Construction",
            "type":"Services"
        }
    ],
    "sg:phone":"+1 212 674 8399",
    "sg:postcode":"10009",
    "sg:province":"NY",
    "sg:tags":[
        "home",
        "house",
        "improvement"
    ],
    "wof:name":"Edbol Construction Co",
    "wof:placetype":"venue"
},
  "geometry": {"coordinates":[-73.982207,40.723864],"type":"Point"}
}