{
  "type": "Feature",
  "properties": {
    "addr:full":"315 Madison Ave Ste 201 New York NY 10017",
    "addr:housenumber":"315;201",
    "addr:postcode":"10017",
    "addr:street":"Madison Ave Ste",
    "iso:country":"US",
    "sg:address":"315 Madison Ave Ste 201",
    "sg:city":"New York",
    "sg:classifiers":[
        {
            "category":"Personal",
            "subcategory":"Hair Removal",
            "type":"Services"
        },
        {
            "category":"Personal",
            "subcategory":"Skin Care",
            "type":"Services"
        }
    ],
    "sg:phone":"+1 212 557 5700",
    "sg:postcode":"10017",
    "sg:province":"NY",
    "sg:tags":[
        "laser"
    ],
    "sg:website":"www.gentletouchlaser.com",
    "wof:name":"Gentle Touch Laser Center",
    "wof:placetype":"venue"
},
  "geometry": {"coordinates":[-73.97921599999999,40.752586],"type":"Point"}
}