{
  "type": "Feature",
  "properties": {
    "addr:full":"6831 Niagara Falls Blvd Niagara Falls NY 14301",
    "addr:housenumber":"6831",
    "addr:postcode":"14301",
    "addr:street":"Niagara Falls Blvd",
    "iso:country":"US",
    "sg:address":"6831 Niagara Falls Blvd",
    "sg:city":"Niagara Falls",
    "sg:classifiers":[
        {
            "category":"Travel",
            "subcategory":"Hotels & Motels",
            "type":"Entertainment"
        }
    ],
    "sg:phone":"+1 716 283 8142",
    "sg:postcode":"14301",
    "sg:province":"NY",
    "wof:name":"Swiss Cottage Inns",
    "wof:placetype":"venue"
},
  "geometry": {"coordinates":[-78.985945,43.088848],"type":"Point"}
}