{
  "type": "Feature",
  "properties": {
    "addr:full":"1452 Westchester Ave Bronx NY 10472",
    "addr:housenumber":"1452",
    "addr:postcode":"10472",
    "addr:street":"Westchester Ave",
    "iso:country":"US",
    "sg:address":"1452 Westchester Ave",
    "sg:city":"Bronx",
    "sg:classifiers":[
        {
            "category":"Retail",
            "subcategory":"Repair Shop",
            "type":"Services"
        }
    ],
    "sg:phone":"+1 718 732 0065",
    "sg:postcode":"10472",
    "sg:province":"NY",
    "sg:tags":[
        "lock",
        "locksmith"
    ],
    "wof:name":"Locksmith 24 Hours",
    "wof:placetype":"venue"
},
  "geometry": {"coordinates":[-73.882464,40.828246],"type":"Point"}
}