{
  "type": "Feature",
  "properties": {
    "iso:country":"US",
    "sg:address":"141 Ridge Rd",
    "sg:city":"New City",
    "sg:classifiers":[
        {
            "category":"Professional",
            "subcategory":"Management & Consulting",
            "type":"Services"
        }
    ],
    "sg:phone":"+1 845 639 9251",
    "sg:postcode":"10956",
    "sg:province":"NY",
    "sg:tags":[
        "business"
    ],
    "wof:name":"System Research Services Inc",
    "wof:placetype":"venue"
},
  "geometry": {"coordinates":[-73.96185,41.167408],"type":"Point"}
}