{
  "type": "Feature",
  "properties": {
    "iso:country":"US",
    "sg:address":"56 W 22nd St Fl 9",
    "sg:city":"New York",
    "sg:classifiers":[
        {
            "category":"Shopping",
            "subcategory":"Hobbies, Toys, & Games",
            "type":"Retail Goods"
        }
    ],
    "sg:phone":"+1 212 777 7735",
    "sg:postcode":"10010",
    "sg:province":"NY",
    "sg:tags":[
        "toy",
        "store"
    ],
    "wof:name":"Kidrobot",
    "wof:placetype":"venue"
},
  "geometry": {"coordinates":[-73.99293,40.741972],"type":"Point"}
}