{
  "type": "Feature",
  "properties": {
    "addr:full":"59 Blue Ridge Dr Medford NY 11763",
    "addr:housenumber":"59",
    "addr:postcode":"11763",
    "addr:street":"Blue Ridge Dr",
    "iso:country":"US",
    "sg:address":"59 Blue Ridge Dr",
    "sg:city":"Medford",
    "sg:classifiers":[
        {
            "category":"Food & Beverages",
            "subcategory":"Meat & Fish",
            "type":"Retail Goods"
        }
    ],
    "sg:phone":"+1 631 736 7614",
    "sg:postcode":"11763",
    "sg:province":"NY",
    "sg:tags":[
        "market"
    ],
    "wof:name":"Brent Wholesale Meat",
    "wof:placetype":"venue"
},
  "geometry": {"coordinates":[-73.00125,40.843177],"type":"Point"}
}