{
  "type": "Feature",
  "properties": {
    "addr:full":"6700 Thompson Rd Syracuse NY 13211",
    "addr:housenumber":"6700",
    "addr:postcode":"13211",
    "addr:street":"Thompson Rd",
    "iso:country":"US",
    "sg:address":"6700 Thompson Rd",
    "sg:city":"Syracuse",
    "sg:classifiers":[
        {
            "category":"Health Services",
            "subcategory":"Clinic",
            "type":"Services"
        }
    ],
    "sg:phone":"+1 888 648 2211",
    "sg:postcode":"13211",
    "sg:province":"NY",
    "sg:tags":[
        "home",
        "care"
    ],
    "wof:name":"Upstate Homecare",
    "wof:placetype":"venue"
},
  "geometry": {"coordinates":[-76.095491,43.094999],"type":"Point"}
}