{
  "type": "Feature",
  "properties": {
    "iso:country":"US",
    "sg:address":"221 Cleveland Dr",
    "sg:city":"Croton On Hudson",
    "sg:classifiers":[
        {
            "category":"Professional",
            "subcategory":"Management & Consulting",
            "type":"Services"
        }
    ],
    "sg:phone":"+1   ",
    "sg:postcode":"10520",
    "sg:province":"NY",
    "sg:tags":[
        "business"
    ],
    "wof:name":"Energywiz Inc",
    "wof:placetype":"venue"
},
  "geometry": {"coordinates":[-73.872148,41.213568],"type":"Point"}
}