{
  "type": "Feature",
  "properties": {
    "addr:full":"75 Maple St Roslyn Heights NY 11577",
    "addr:housenumber":"75",
    "addr:postcode":"11577",
    "addr:street":"Maple St",
    "iso:country":"US",
    "sg:address":"75 Maple St",
    "sg:city":"Roslyn Heights",
    "sg:classifiers":[
        {
            "category":"Shopping",
            "type":"Retail Goods"
        }
    ],
    "sg:phone":"+1   ",
    "sg:postcode":"11577",
    "sg:province":"NY",
    "sg:tags":[
        "merchandise"
    ],
    "wof:name":"Leslie Marketing",
    "wof:placetype":"venue"
},
  "geometry": {"coordinates":[-73.650267,40.787151],"type":"Point"}
}