{
  "type": "Feature",
  "properties": {
    "iso:country":"US",
    "sg:address":"84 Elm St",
    "sg:city":"Tonawanda",
    "sg:classifiers":[
        {
            "category":"Freight",
            "type":"Transportation"
        }
    ],
    "sg:phone":"+1   ",
    "sg:postcode":"14150",
    "sg:province":"NY",
    "sg:tags":[
        "operator",
        "local",
        "trucking"
    ],
    "wof:name":"Braymiller Delivery Service",
    "wof:placetype":"venue"
},
  "geometry": {"coordinates":[-78.87143500000001,43.012358],"type":"Point"}
}