{
  "type": "Feature",
  "properties": {
    "addr:full":"343 Mamaroneck Ave White Plains NY 10605",
    "addr:housenumber":"343",
    "addr:postcode":"10605",
    "addr:street":"Mamaroneck Ave",
    "iso:country":"US",
    "sg:address":"343 Mamaroneck Ave",
    "sg:city":"White Plains",
    "sg:classifiers":[
        {
            "category":"Food & Beverages",
            "subcategory":"Liquor & Beverages",
            "type":"Retail Goods"
        }
    ],
    "sg:phone":"+1   ",
    "sg:postcode":"10605",
    "sg:province":"NY",
    "sg:tags":[
        "wine"
    ],
    "wof:name":"Carhart Wine & Liquor Store",
    "wof:placetype":"venue"
},
  "geometry": {"coordinates":[-73.763597,41.025464],"type":"Point"}
}