{
  "type": "Feature",
  "properties": {
    "iso:country":"US",
    "sg:address":"20 Floyds Run",
    "sg:city":"Bohemia",
    "sg:classifiers":[
        {
            "category":"Manufacturing",
            "subcategory":"Printing",
            "type":"Manufacturing & Wholesale Goods"
        }
    ],
    "sg:phone":"+1   ",
    "sg:postcode":"11716",
    "sg:province":"NY",
    "sg:tags":[
        "printer",
        "label"
    ],
    "sg:website":"www.aol.com",
    "wof:name":"Janco Press Inc",
    "wof:placetype":"venue"
},
  "geometry": {"coordinates":[-73.115076,40.782466],"type":"Point"}
}