{
  "type": "Feature",
  "properties": {
    "addr:full":"15051 Northern Blvd Flushing NY 11354",
    "addr:housenumber":"15051",
    "addr:postcode":"11354",
    "addr:street":"Northern Blvd",
    "iso:country":"US",
    "sg:address":"15051 Northern Blvd",
    "sg:city":"Flushing",
    "sg:classifiers":[
        {
            "category":"Food & Beverages",
            "subcategory":"Groceries & Convenience Stores",
            "type":"Retail Goods"
        }
    ],
    "sg:phone":"+1 718 461 1911",
    "sg:postcode":"11354",
    "sg:province":"NY",
    "wof:name":"Seoul Shopping Inc",
    "wof:placetype":"venue"
},
  "geometry": {"coordinates":[-73.81300400000001,40.765202],"type":"Point"}
}