{
  "type": "Feature",
  "properties": {
    "addr:full":"10187 Main St Clarence NY 14031",
    "addr:housenumber":"10187",
    "addr:postcode":"14031",
    "addr:street":"Main St",
    "iso:country":"US",
    "sg:address":"10187 Main St",
    "sg:city":"Clarence",
    "sg:classifiers":[
        {
            "category":"Building & Trades",
            "subcategory":"Construction",
            "type":"Services"
        }
    ],
    "sg:phone":"+1 716 759 8645",
    "sg:postcode":"14031",
    "sg:province":"NY",
    "sg:tags":[
        "excavation",
        "demolition",
        "contractor"
    ],
    "sg:website":"http://www.uniteddemolitionandexcavating.com",
    "wof:name":"United Demolition",
    "wof:placetype":"venue"
},
  "geometry": {"coordinates":[-78.610371,42.977652],"type":"Point"}
}