{
  "type": "Feature",
  "properties": {
    "addr:full":"911 State Hwy 6n Mahopac NY 10541",
    "addr:housenumber":"911",
    "addr:postcode":"10541",
    "addr:street":"State Hwy",
    "iso:country":"US",
    "sg:address":"911 State Hwy 6n",
    "sg:city":"Mahopac",
    "sg:classifiers":[
        {
            "category":"Home & Garden",
            "subcategory":"Building Materials",
            "type":"Retail Goods"
        }
    ],
    "sg:phone":"+1 845 628 8111",
    "sg:postcode":"10541",
    "sg:province":"NY",
    "sg:tags":[
        "lumber"
    ],
    "sg:website":"www.mahopacrrtie.com",
    "wof:name":"Mahopac Railroad Tie Co",
    "wof:placetype":"venue"
},
  "geometry": {"coordinates":[-73.734942,41.372372],"type":"Point"}
}