{
  "type": "Feature",
  "properties": {
    "iso:country":"US",
    "sg:address":"17 Durkee St",
    "sg:city":"Plattsburgh",
    "sg:classifiers":[
        {
            "category":"Autos & Motor Vehicles",
            "subcategory":"Automobile Sales",
            "type":"Retail Goods"
        },
        {
            "category":"Retail",
            "subcategory":"Auto Repair",
            "type":"Services"
        }
    ],
    "sg:phone":"+1 518 562 9466",
    "sg:postcode":"12901",
    "sg:province":"NY",
    "sg:tags":[
        "car",
        "dealer",
        "general"
    ],
    "wof:name":"A & L Auto Repair and Sales",
    "wof:placetype":"venue"
},
  "geometry": {"coordinates":[-73.452307,44.694977],"type":"Point"}
}