{
  "type": "Feature",
  "properties": {
    "iso:country":"US",
    "sg:address":"251 W 57 St",
    "sg:city":"New York",
    "sg:classifiers":[
        {
            "category":"Organizations",
            "subcategory":"Religious Organization",
            "type":"Services"
        }
    ],
    "sg:phone":"+1 212 333 3466",
    "sg:postcode":"10019",
    "sg:province":"NY",
    "sg:tags":[
        "church"
    ],
    "wof:name":"Church Of Jesus Christ Of Lds",
    "wof:placetype":"venue"
},
  "geometry": {"coordinates":[-73.981848,40.766287],"type":"Point"}
}