{
  "type": "Feature",
  "properties": {
    "iso:country":"US",
    "sg:address":"211 E 21st St",
    "sg:city":"New York",
    "sg:classifiers":[
        {
            "category":"Building & Trades",
            "subcategory":"Construction",
            "type":"Services"
        }
    ],
    "sg:phone":"+1 212 777 9018",
    "sg:postcode":"10010",
    "sg:province":"NY",
    "sg:tags":[
        "hanging",
        "contractor"
    ],
    "wof:name":"V Kalaj Inc",
    "wof:placetype":"venue"
},
  "geometry": {"coordinates":[-73.99051799999999,40.740262],"type":"Point"}
}