{
  "type": "Feature",
  "properties": {
    "addr:full":"3 Amsterdam Ave Monsey NY 10952",
    "addr:housenumber":"3",
    "addr:postcode":"10952",
    "addr:street":"Amsterdam Ave",
    "iso:country":"US",
    "sg:address":"3 Amsterdam Ave",
    "sg:city":"Monsey",
    "sg:classifiers":[
        {
            "category":"Professional",
            "subcategory":"Research",
            "type":"Services"
        },
        {
            "category":"Professional",
            "subcategory":"Management & Consulting",
            "type":"Services"
        }
    ],
    "sg:phone":"+1 845 362 5116",
    "sg:postcode":"10952",
    "sg:province":"NY",
    "sg:tags":[
        "biologist",
        "business",
        "legal"
    ],
    "wof:name":"Technology Access Partners LLC",
    "wof:placetype":"venue"
},
  "geometry": {"coordinates":[-74.07318600000001,41.155394],"type":"Point"}
}