{
  "type": "Feature",
  "properties": {
    "addr:full":"465 Smithtown Blvd Ste 2 Nesconset NY 11767",
    "addr:housenumber":"465",
    "addr:postcode":"11767",
    "addr:street":"Smithtown Blvd Ste 2",
    "iso:country":"US",
    "sg:address":"465 Smithtown Blvd Ste 2",
    "sg:city":"Nesconset",
    "sg:classifiers":[
        {
            "category":"Real Estate",
            "subcategory":"Real Estate Services",
            "type":"Services"
        },
        {
            "category":"Real Estate",
            "subcategory":"Real Estate Agent",
            "type":"Services"
        }
    ],
    "sg:phone":"+1 631 360 2900",
    "sg:postcode":"11767",
    "sg:province":"NY",
    "sg:tags":[
        "buyer",
        "management",
        "broker"
    ],
    "sg:website":"http://www.hgsold.com",
    "wof:name":"Hough Guidice Realty Assoc",
    "wof:placetype":"venue"
},
  "geometry": {"coordinates":[-73.134979,40.831785],"type":"Point"}
}