{
  "type": "Feature",
  "properties": {
    "iso:country":"US",
    "sg:address":"303 Oxford Blvd",
    "sg:city":"Garden City",
    "sg:classifiers":[
        {
            "category":"Wholesale",
            "subcategory":"Non-durable Goods",
            "type":"Manufacturing & Wholesale Goods"
        }
    ],
    "sg:phone":"+1 718 279 0074",
    "sg:postcode":"11530",
    "sg:province":"NY",
    "sg:tags":[
        "consulting",
        "management"
    ],
    "wof:name":"P2r",
    "wof:placetype":"venue"
},
  "geometry": {"coordinates":[-73.654444,40.716575],"type":"Point"}
}