{
  "type": "Feature",
  "properties": {
    "iso:country":"US",
    "sg:address":"511 Glen St",
    "sg:city":"Glens Falls",
    "sg:classifiers":[
        {
            "category":"Health Services",
            "subcategory":"Doctor",
            "type":"Services"
        }
    ],
    "sg:phone":"+1 518 793 2483",
    "sg:postcode":"12801",
    "sg:province":"NY",
    "sg:tags":[
        "medical"
    ],
    "wof:name":"M C Slaughter MD",
    "wof:placetype":"venue"
},
  "geometry": {"coordinates":[-73.656023,43.317989],"type":"Point"}
}