{
  "type": "Feature",
  "properties": {
    "iso:country":"US",
    "sg:address":"17 Main St",
    "sg:city":"Massena",
    "sg:classifiers":[
        {
            "category":"Professional",
            "subcategory":"Computer Services",
            "type":"Services"
        }
    ],
    "sg:phone":"+1 315 769 1641",
    "sg:postcode":"13662",
    "sg:province":"NY",
    "wof:name":"Novosel Associates",
    "wof:placetype":"venue"
},
  "geometry": {"coordinates":[-74.89297000000001,44.932003],"type":"Point"}
}