{
  "type": "Feature",
  "properties": {
    "addr:full":"891 Amsterdam Ave New York NY 10025",
    "addr:housenumber":"891",
    "addr:postcode":"10025",
    "addr:street":"Amsterdam Ave",
    "iso:country":"US",
    "sg:address":"891 Amsterdam Ave",
    "sg:city":"New York",
    "sg:classifiers":[
        {
            "category":"Restaurant",
            "type":"Food & Drink"
        }
    ],
    "sg:phone":"+1 212 866 4811",
    "sg:postcode":"10025",
    "sg:province":"NY",
    "sg:tags":[
        "out"
    ],
    "wof:name":"Nutrition & Health Program",
    "wof:placetype":"venue"
},
  "geometry": {"coordinates":[-73.96678900000001,40.798747],"type":"Point"}
}