{
  "type": "Feature",
  "properties": {
    "iso:country":"US",
    "sg:address":"215 W 95 St",
    "sg:city":"New York",
    "sg:classifiers":[
        {
            "category":"Arts & Performance",
            "subcategory":"Theater",
            "type":"Entertainment"
        }
    ],
    "sg:phone":"+1 212 678 1713",
    "sg:postcode":"10025",
    "sg:province":"NY",
    "sg:tags":[
        "theatrical"
    ],
    "wof:name":"Special Productions Inc",
    "wof:placetype":"venue"
},
  "geometry": {"coordinates":[-73.971931,40.793871],"type":"Point"}
}