{
  "type": "Feature",
  "properties": {
    "iso:country":"US",
    "sg:address":"494 Cornish Hill Rd",
    "sg:city":"Cooperstown",
    "sg:classifiers":[
        {
            "category":"Professional",
            "subcategory":"Testing Lab",
            "type":"Services"
        }
    ],
    "sg:phone":"+1 607 547 5501",
    "sg:postcode":"13326",
    "sg:province":"NY",
    "sg:tags":[
        "correction",
        "radon"
    ],
    "wof:name":"Cornish Hill Contracting",
    "wof:placetype":"venue"
},
  "geometry": {"coordinates":[-74.905074,42.675932],"type":"Point"}
}