{
  "type": "Feature",
  "properties": {
    "iso:country":"US",
    "sg:address":"1152 Schodack Landing Rd",
    "sg:city":"Schodack Landing",
    "sg:phone":"+1 518 732 2536",
    "sg:postcode":"12156",
    "sg:province":"NY",
    "sg:tags":[
        "farm",
        "field",
        "crop"
    ],
    "wof:name":"Guthridge C Farm of",
    "wof:placetype":"venue"
},
  "geometry": {"coordinates":[-73.71582600000001,42.478361],"type":"Point"}
}