{
  "type": "Feature",
  "properties": {
    "addr:full":"74 Millwood Rd Millwood NY 10546",
    "addr:housenumber":"74",
    "addr:postcode":"10546",
    "addr:street":"Millwood Rd",
    "iso:country":"US",
    "sg:address":"74 Millwood Rd",
    "sg:city":"Millwood",
    "sg:classifiers":[
        {
            "category":"Retail",
            "subcategory":"Repair Shop",
            "type":"Services"
        }
    ],
    "sg:phone":"+1 914 218 2431",
    "sg:postcode":"10546",
    "sg:province":"NY",
    "sg:tags":[
        "lock",
        "locksmith"
    ],
    "wof:name":"USA Locksmith",
    "wof:placetype":"venue"
},
  "geometry": {"coordinates":[-73.797535,41.191589],"type":"Point"}
}