{
  "type": "Feature",
  "properties": {
    "iso:country":"US",
    "sg:address":"19 Evergreen Ave",
    "sg:city":"East Moriches",
    "sg:classifiers":[
        {
            "category":"Shopping",
            "subcategory":"Florist",
            "type":"Retail Goods"
        }
    ],
    "sg:phone":"+1 631 878 0115",
    "sg:postcode":"11940",
    "sg:province":"NY",
    "wof:name":"Kawasaki Greenhouses Inc",
    "wof:placetype":"venue"
},
  "geometry": {"coordinates":[-72.744094,40.810963],"type":"Point"}
}