{
  "type": "Feature",
  "properties": {
    "addr:full":"154 Nassau St Brooklyn NY 11201",
    "addr:housenumber":"154",
    "addr:postcode":"11201",
    "addr:street":"Nassau St",
    "iso:country":"US",
    "sg:address":"154 Nassau St",
    "sg:city":"Brooklyn",
    "sg:classifiers":[
        {
            "category":"Education",
            "subcategory":"School",
            "type":"Public Place"
        }
    ],
    "sg:phone":"+1 718 349 1555",
    "sg:postcode":"11201",
    "sg:province":"NY",
    "wof:name":"Ross & Asmar LLC",
    "wof:placetype":"venue"
},
  "geometry": {"coordinates":[-73.985202,40.698302],"type":"Point"}
}