{
  "type": "Feature",
  "properties": {
    "addr:full":"11 Micieli Place Brooklyn NY 11218",
    "addr:housenumber":"11",
    "addr:postcode":"11218",
    "addr:street":"Micieli Place",
    "iso:country":"US",
    "sg:address":"11 Micieli Place",
    "sg:city":"Brooklyn",
    "sg:classifiers":[
        {
            "category":"Building & Trades",
            "subcategory":"Construction",
            "type":"Services"
        }
    ],
    "sg:phone":"+1 718 435 1255",
    "sg:postcode":"11218",
    "sg:province":"NY",
    "sg:tags":[
        "contractor"
    ],
    "wof:name":"B Uddin Construction Company",
    "wof:placetype":"venue"
},
  "geometry": {"coordinates":[-73.981989,40.646687],"type":"Point"}
}