{
  "type": "Feature",
  "properties": {
    "addr:full":"1123 Bronx River Ave Bronx NY 10472",
    "addr:housenumber":"1123",
    "addr:postcode":"10472",
    "addr:street":"Bronx River Ave",
    "iso:country":"US",
    "sg:address":"1123 Bronx River Ave",
    "sg:city":"Bronx",
    "sg:classifiers":[
        {
            "category":"Building & Trades",
            "subcategory":"Construction",
            "type":"Services"
        }
    ],
    "sg:phone":"+1 718 589 9000",
    "sg:postcode":"10472",
    "sg:province":"NY",
    "sg:tags":[
        "excavation",
        "foundation",
        "contractor"
    ],
    "wof:name":"John Civetta Construction",
    "wof:placetype":"venue"
},
  "geometry": {"coordinates":[-73.883197,40.827676],"type":"Point"}
}