{
  "type": "Feature",
  "properties": {
    "iso:country":"US",
    "sg:address":"1395 Lexington Ave",
    "sg:city":"New York",
    "sg:classifiers":[
        {
            "category":"Education",
            "subcategory":"Dance Studio",
            "type":"Public Place"
        }
    ],
    "sg:phone":"+1 212 415 5552",
    "sg:postcode":"10128",
    "sg:province":"NY",
    "wof:name":"Harkness Dance Center",
    "wof:placetype":"venue"
},
  "geometry": {"coordinates":[-73.952957,40.782873],"type":"Point"}
}