{
  "type": "Feature",
  "properties": {
    "addr:full":"2016 3rd Avenue New York NY 10029",
    "addr:housenumber":"2016",
    "addr:postcode":"10029",
    "addr:street":"3Rd Avenue",
    "iso:country":"US",
    "sg:address":"2016 3rd Avenue",
    "sg:city":"New York",
    "sg:classifiers":[
        {
            "category":"Sports & Exercise",
            "subcategory":"Bicycle Rental",
            "type":"Entertainment"
        }
    ],
    "sg:phone":"+1 212 410 1144",
    "sg:postcode":"10029",
    "sg:province":"NY",
    "sg:tags":[
        "bike"
    ],
    "wof:name":"Heavy Metal Bike Shop",
    "wof:placetype":"venue"
},
  "geometry": {"coordinates":[-73.943382,40.791007],"type":"Point"}
}