{
  "type": "Feature",
  "properties": {
    "addr:full":"1028 E 95th St Brooklyn NY 11236",
    "addr:housenumber":"1028",
    "addr:postcode":"11236",
    "addr:street":"E 95Th St",
    "iso:country":"US",
    "sg:address":"1028 E 95th St",
    "sg:city":"Brooklyn",
    "sg:classifiers":[
        {
            "category":"Personal",
            "subcategory":"Beauty Salon",
            "type":"Services"
        }
    ],
    "sg:phone":"+1 718 363 0600",
    "sg:postcode":"11236",
    "sg:province":"NY",
    "wof:name":"Black Hair",
    "wof:placetype":"venue"
},
  "geometry": {"coordinates":[-73.905509,40.64541],"type":"Point"}
}