{
  "type": "Feature",
  "properties": {
    "iso:country":"US",
    "sg:address":"2529 James St",
    "sg:city":"Syracuse",
    "sg:classifiers":[
        {
            "category":"Bars & Pubs",
            "type":"Food & Drink"
        }
    ],
    "sg:phone":"+1   ",
    "sg:postcode":"13206",
    "sg:province":"NY",
    "sg:tags":[
        "drinking"
    ],
    "wof:name":"Chadwicks",
    "wof:placetype":"venue"
},
  "geometry": {"coordinates":[-76.110564,43.068713],"type":"Point"}
}