{
  "type": "Feature",
  "properties": {
    "iso:country":"US",
    "sg:address":"118 W 20th St",
    "sg:city":"New York",
    "sg:classifiers":[
        {
            "category":"Manufacturing",
            "subcategory":"Apparel",
            "type":"Manufacturing & Wholesale Goods"
        }
    ],
    "sg:phone":"+1   ",
    "sg:postcode":"10011",
    "sg:province":"NY",
    "sg:tags":[
        "bridesmaid",
        "gown",
        "dress",
        "mfg"
    ],
    "wof:name":"Dessy Creations",
    "wof:placetype":"venue"
},
  "geometry": {"coordinates":[-73.99664799999999,40.741943],"type":"Point"}
}