{
  "type": "Feature",
  "properties": {
    "addr:full":"530 Main St Armonk NY 10504",
    "addr:housenumber":"530",
    "addr:postcode":"10504",
    "addr:street":"Main St",
    "iso:country":"US",
    "sg:address":"530 Main St",
    "sg:city":"Armonk",
    "sg:classifiers":[
        {
            "category":"Health Services",
            "subcategory":"Doctor",
            "type":"Services"
        }
    ],
    "sg:phone":"+1 914 273 4071",
    "sg:postcode":"10504",
    "sg:province":"NY",
    "sg:tags":[
        "dentist"
    ],
    "wof:name":"Fred Tripodi DDS",
    "wof:placetype":"venue"
},
  "geometry": {"coordinates":[-73.712932,41.129541],"type":"Point"}
}