{
  "type": "Feature",
  "properties": {
    "addr:full":"495 Broadway New York NY 10012",
    "addr:housenumber":"495",
    "addr:postcode":"10012",
    "addr:street":"Broadway",
    "iso:country":"US",
    "sg:address":"495 Broadway",
    "sg:city":"New York",
    "sg:classifiers":[
        {
            "category":"Shopping",
            "subcategory":"Pharmacy",
            "type":"Retail Goods"
        }
    ],
    "sg:phone":"+1 212 334 0431",
    "sg:postcode":"10012",
    "sg:province":"NY",
    "sg:tags":[
        "drugstore"
    ],
    "wof:name":"Eckerd Pharmacy",
    "wof:placetype":"venue"
},
  "geometry": {"coordinates":[-73.99977699999999,40.721954],"type":"Point"}
}