{
  "type": "Feature",
  "properties": {
    "addr:full":"2176 64th St Brooklyn NY 11204",
    "addr:housenumber":"2176",
    "addr:postcode":"11204",
    "addr:street":"64Th St",
    "iso:country":"US",
    "sg:address":"2176 64th St",
    "sg:city":"Brooklyn",
    "sg:classifiers":[
        {
            "category":"Personal",
            "subcategory":"Beauty Salon",
            "type":"Services"
        }
    ],
    "sg:phone":"+1 718 234 6711",
    "sg:postcode":"11204",
    "sg:province":"NY",
    "sg:tags":[
        "manicuring"
    ],
    "wof:name":"Exotic Nails",
    "wof:placetype":"venue"
},
  "geometry": {"coordinates":[-73.982162,40.615432],"type":"Point"}
}