{
  "type": "Feature",
  "properties": {
    "iso:country":"US",
    "sg:address":"105 Avondale Rd",
    "sg:city":"Yonkers",
    "sg:classifiers":[
        {
            "category":"Recreation",
            "type":"Entertainment"
        }
    ],
    "sg:phone":"+1 914 961 8444",
    "sg:postcode":"10710",
    "sg:province":"NY",
    "sg:tags":[
        "amusement"
    ],
    "wof:name":"Yonkers Children Excel Club",
    "wof:placetype":"venue"
},
  "geometry": {"coordinates":[-73.828086,40.967046],"type":"Point"}
}