{
  "type": "Feature",
  "properties": {
    "addr:full":"50 Wolf Rd Albany NY 12205",
    "addr:housenumber":"50",
    "addr:postcode":"12205",
    "addr:street":"Wolf Rd",
    "iso:country":"US",
    "sg:address":"50 Wolf Rd",
    "sg:city":"Albany",
    "sg:classifiers":[
        {
            "category":"Government",
            "subcategory":"Office",
            "type":"Public Place"
        }
    ],
    "sg:phone":"+1 518 457 6674",
    "sg:postcode":"12205",
    "sg:province":"NY",
    "sg:tags":[
        "state",
        "program"
    ],
    "wof:name":"Water Division",
    "wof:placetype":"venue"
},
  "geometry": {"coordinates":[-73.811673,42.715403],"type":"Point"}
}