{
  "type": "Feature",
  "properties": {
    "addr:full":"3262 Slaterville Rd Brooktondale NY 14817",
    "addr:housenumber":"3262",
    "addr:postcode":"14817",
    "addr:street":"Slaterville Rd",
    "iso:country":"US",
    "sg:address":"3262 Slaterville Rd",
    "sg:city":"Brooktondale",
    "sg:classifiers":[
        {
            "category":"Farming",
            "subcategory":"Dairy Farm",
            "type":"Manufacturing & Wholesale Goods"
        }
    ],
    "sg:phone":"+1 607 539 7579",
    "sg:postcode":"14817",
    "sg:province":"NY",
    "sg:tags":[
        "field",
        "corn",
        "crop"
    ],
    "wof:name":"Mix Family Dairy Farm",
    "wof:placetype":"venue"
},
  "geometry": {"coordinates":[-76.29484600000001,42.378383],"type":"Point"}
}