{
  "type": "Feature",
  "properties": {
    "iso:country":"US",
    "sg:address":"4 Crescent St",
    "sg:city":"Mastic",
    "sg:classifiers":[
        {
            "category":"Home & Garden",
            "subcategory":"Hardware",
            "type":"Retail Goods"
        },
        {
            "category":"Manufacturing",
            "subcategory":"Electronics",
            "type":"Manufacturing & Wholesale Goods"
        }
    ],
    "sg:phone":"+1 631 399 5840",
    "sg:postcode":"11950",
    "sg:province":"NY",
    "sg:tags":[
        "measuring",
        "instrument",
        "device",
        "electronic"
    ],
    "wof:name":"Deb's Electronic",
    "wof:placetype":"venue"
},
  "geometry": {"coordinates":[-72.85131800000001,40.814797],"type":"Point"}
}