{
  "type": "Feature",
  "properties": {
    "addr:full":"86 Kisco Ave Mt Kisco NY 10549",
    "addr:housenumber":"86",
    "addr:postcode":"10549",
    "addr:street":"Kisco Ave Mt Kisco",
    "iso:country":"US",
    "sg:address":"86 Kisco Ave",
    "sg:city":"Mt Kisco",
    "sg:classifiers":[
        {
            "category":"Health Services",
            "subcategory":"Doctor",
            "type":"Services"
        }
    ],
    "sg:phone":"+1 914 241 4312",
    "sg:postcode":"10549",
    "sg:province":"NY",
    "sg:tags":[
        "physician",
        "surgeon"
    ],
    "wof:name":"Lois Tuerk MD",
    "wof:placetype":"venue"
},
  "geometry": {"coordinates":[-73.725922,41.215105],"type":"Point"}
}