{
  "type": "Feature",
  "properties": {
    "iso:country":"US",
    "sg:address":"86 Willow Ave",
    "sg:city":"Larchmont",
    "sg:classifiers":[
        {
            "category":"Professional",
            "subcategory":"Computer Services",
            "type":"Services"
        }
    ],
    "sg:phone":"+1 914 834 3103",
    "sg:postcode":"10538",
    "sg:province":"NY",
    "sg:tags":[
        "publisher",
        "developer",
        "software"
    ],
    "wof:name":"Moran Consulting Service",
    "wof:placetype":"venue"
},
  "geometry": {"coordinates":[-73.75402699999999,40.922869],"type":"Point"}
}