{
  "type": "Feature",
  "properties": {
    "addr:full":"8626 Queens Blvd Elmhurst NY 11373",
    "addr:housenumber":"8626",
    "addr:postcode":"11373",
    "addr:street":"Queens Blvd",
    "iso:country":"US",
    "sg:address":"8626 Queens Blvd",
    "sg:city":"Elmhurst",
    "sg:classifiers":[
        {
            "category":"Professional",
            "subcategory":"Lawyer & Legal Services",
            "type":"Services"
        }
    ],
    "sg:phone":"+1 212 439 2021",
    "sg:postcode":"11373",
    "sg:province":"NY",
    "sg:website":"www.gross-levin.com",
    "wof:name":"Gross Lawrence J Atty",
    "wof:placetype":"venue"
},
  "geometry": {"coordinates":[-73.876901,40.73618],"type":"Point"}
}