{
  "type": "Feature",
  "properties": {
    "iso:country":"US",
    "sg:address":"750 E Adams St",
    "sg:city":"Syracuse",
    "sg:classifiers":[
        {
            "category":"Health Services",
            "subcategory":"Doctor",
            "type":"Services"
        },
        {
            "category":"Health Services",
            "subcategory":"Hospital",
            "type":"Services"
        }
    ],
    "sg:phone":"+1 315 464 5280",
    "sg:postcode":"13210",
    "sg:province":"NY",
    "sg:tags":[
        "physician",
        "surgeons",
        "otorhinolaryngology",
        "nose",
        "throat",
        "ear"
    ],
    "wof:name":"Upstate Medical University",
    "wof:placetype":"venue"
},
  "geometry": {"coordinates":[-76.140511,43.04269],"type":"Point"}
}