{
  "type": "Feature",
  "properties": {
    "addr:full":"687 Old Country Rd Huntington Station NY 11746",
    "addr:housenumber":"687",
    "addr:postcode":"11746",
    "addr:street":"Old Country Rd",
    "iso:country":"US",
    "sg:address":"687 Old Country Rd",
    "sg:city":"Huntington Station",
    "sg:classifiers":[
        {
            "category":"Restaurant",
            "type":"Food & Drink"
        }
    ],
    "sg:menulink":"http://www.allmenus.com/ny/huntington/33483-spuntino/menu/",
    "sg:phone":"+1 631 547 9300",
    "sg:postcode":"11746",
    "sg:province":"NY",
    "sg:tags":[
        "italian"
    ],
    "wof:name":"Spuntino",
    "wof:placetype":"venue"
},
  "geometry": {"coordinates":[-73.35921999999999,40.83093],"type":"Point"}
}