{
  "type": "Feature",
  "properties": {
    "addr:full":"89 Worth St New York NY 10013",
    "addr:housenumber":"89",
    "addr:postcode":"10013",
    "addr:street":"Worth St",
    "iso:country":"US",
    "sg:address":"89 Worth St",
    "sg:city":"New York",
    "sg:classifiers":[
        {
            "category":"Restaurant",
            "type":"Food & Drink"
        }
    ],
    "sg:menulink":"http://www.allmenus.com/ny/new-york/53081-subway/menu/",
    "sg:phone":"+1 212 925 1211",
    "sg:postcode":"10013",
    "sg:province":"NY",
    "sg:tags":[
        "american",
        "sandwich"
    ],
    "wof:name":"Subway",
    "wof:placetype":"venue"
},
  "geometry": {"coordinates":[-74.00488300000001,40.716445],"type":"Point"}
}