{
  "type": "Feature",
  "properties": {
    "addr:full":"3 Brookside Ave Chester NY 10918",
    "addr:housenumber":"3",
    "addr:postcode":"ny 10918",
    "addr:street":"Brookside Ave",
    "iso:country":"US",
    "sg:address":"3 Brookside Ave",
    "sg:city":"Chester",
    "sg:classifiers":[
        {
            "category":"Health Services",
            "subcategory":"Chiropractor",
            "type":"Services"
        }
    ],
    "sg:phone":"+1 845 469 9164",
    "sg:postcode":"10918",
    "sg:province":"NY",
    "wof:name":"Brookside Chiropractic",
    "wof:placetype":"venue"
},
  "geometry": {"coordinates":[-74.270973,41.351256],"type":"Point"}
}