{
  "type": "Feature",
  "properties": {
    "addr:full":"180 W 80th St Ste 218 New York NY 10024",
    "addr:housenumber":"180;218",
    "addr:postcode":"10024",
    "addr:street":"W 80Th St Ste",
    "iso:country":"US",
    "sg:address":"180 W 80th St Ste 218",
    "sg:city":"New York",
    "sg:classifiers":[
        {
            "category":"Real Estate",
            "subcategory":"Real Estate Agent",
            "type":"Services"
        }
    ],
    "sg:phone":"+1 212 873 8188",
    "sg:postcode":"10024",
    "sg:province":"NY",
    "sg:website":"www.frbnewyork.com",
    "wof:name":"First Residential Brokerage",
    "wof:placetype":"venue"
},
  "geometry": {"coordinates":[-73.977475,40.783687],"type":"Point"}
}