{
  "type": "Feature",
  "properties": {
    "iso:country":"US",
    "sg:address":"156 S Liberty Dr",
    "sg:city":"Stony Point",
    "sg:classifiers":[
        {
            "category":"Building & Trades",
            "subcategory":"Landscaping Services",
            "type":"Services"
        }
    ],
    "sg:phone":"+1 845 947 7001",
    "sg:postcode":"10980",
    "sg:province":"NY",
    "wof:name":"Cayot Inc",
    "wof:placetype":"venue"
},
  "geometry": {"coordinates":[-73.986318,41.217862],"type":"Point"}
}