{
  "type": "Feature",
  "properties": {
    "addr:full":"4284 Arthur Kill Rd Staten Island NY 10309",
    "addr:housenumber":"4284",
    "addr:postcode":"10309",
    "addr:street":"Arthur Kill Rd",
    "iso:country":"US",
    "sg:address":"4284 Arthur Kill Rd",
    "sg:city":"Staten Island",
    "sg:classifiers":[
        {
            "category":"Arts & Performance",
            "subcategory":"Theater",
            "type":"Entertainment"
        }
    ],
    "sg:phone":"+1 718 984 0670",
    "sg:postcode":"10309",
    "sg:province":"NY",
    "sg:tags":[
        "bureau"
    ],
    "wof:name":"523 Entertainment",
    "wof:placetype":"venue"
},
  "geometry": {"coordinates":[-74.237178,40.537798],"type":"Point"}
}