{
  "type": "Feature",
  "properties": {
    "addr:full":"3433 Turf Rd Oceanside NY 11572",
    "addr:housenumber":"3433",
    "addr:postcode":"11572",
    "addr:street":"Turf Rd",
    "iso:country":"US",
    "sg:address":"3433 Turf Rd",
    "sg:city":"Oceanside",
    "sg:classifiers":[
        {
            "category":"Professional",
            "subcategory":"Lawyer & Legal Services",
            "type":"Services"
        }
    ],
    "sg:phone":"+1   ",
    "sg:postcode":"11572",
    "sg:province":"NY",
    "wof:name":"Carl Maza",
    "wof:placetype":"venue"
},
  "geometry": {"coordinates":[-73.627825,40.62938],"type":"Point"}
}