{
  "type": "Feature",
  "properties": {
    "addr:full":"64 W 48 St New York NY 10036",
    "addr:housenumber":"64",
    "addr:postcode":"10036",
    "addr:street":"W 48 St",
    "iso:country":"US",
    "sg:address":"64 W 48 St",
    "sg:city":"New York",
    "sg:classifiers":[
        {
            "category":"Retail",
            "subcategory":"Repair Shop",
            "type":"Services"
        }
    ],
    "sg:phone":"+1 212 840 1866",
    "sg:postcode":"10036",
    "sg:province":"NY",
    "sg:tags":[
        "watch"
    ],
    "wof:name":"C C Watch Repair",
    "wof:placetype":"venue"
},
  "geometry": {"coordinates":[-73.98121999999999,40.758492],"type":"Point"}
}