{
  "type": "Feature",
  "properties": {
    "addr:full":"1 Van Cortlandt Park Ave Yonkers NY 10701",
    "addr:housenumber":"1",
    "addr:postcode":"10701",
    "addr:street":"Van Cortlandt Park Ave",
    "iso:country":"US",
    "sg:address":"1 Van Cortlandt Park Ave",
    "sg:city":"Yonkers",
    "sg:classifiers":[
        {
            "category":"Food & Beverages",
            "subcategory":"Groceries & Convenience Stores",
            "type":"Retail Goods"
        }
    ],
    "sg:phone":"+1 914 965 5228",
    "sg:postcode":"10701",
    "sg:province":"NY",
    "sg:tags":[
        "grocer"
    ],
    "wof:name":"Amera Grocery Store",
    "wof:placetype":"venue"
},
  "geometry": {"coordinates":[-73.887727,40.931138],"type":"Point"}
}