{
  "type": "Feature",
  "properties": {
    "iso:country":"US",
    "sg:address":"19 E 9 St",
    "sg:city":"New York",
    "sg:classifiers":[
        {
            "category":"Professional",
            "subcategory":"Lawyer & Legal Services",
            "type":"Services"
        }
    ],
    "sg:phone":"+1 212 375 1677",
    "sg:postcode":"10003",
    "sg:province":"NY",
    "sg:tags":[
        "attorney"
    ],
    "wof:name":"Frank L Durr",
    "wof:placetype":"venue"
},
  "geometry": {"coordinates":[-73.995109,40.732702],"type":"Point"}
}