{
  "type": "Feature",
  "properties": {
    "addr:full":"399 Clinton St Hempstead NY 11550",
    "addr:housenumber":"399",
    "addr:postcode":"11550",
    "addr:street":"Clinton St",
    "iso:country":"US",
    "sg:address":"399 Clinton St",
    "sg:city":"Hempstead",
    "sg:classifiers":[
        {
            "category":"Restaurant",
            "type":"Food & Drink"
        }
    ],
    "sg:phone":"+1   ",
    "sg:postcode":"11550",
    "sg:province":"NY",
    "sg:tags":[
        "eating"
    ],
    "wof:name":"Hing Lung Kitchen",
    "wof:placetype":"venue"
},
  "geometry": {"coordinates":[-73.62073599999999,40.718385],"type":"Point"}
}