{
  "type": "Feature",
  "properties": {
    "addr:full":"330 W 46 St New York NY 10036",
    "addr:housenumber":"330",
    "addr:postcode":"10036",
    "addr:street":"W 46 St",
    "iso:country":"US",
    "sg:address":"330 W 46 St",
    "sg:city":"New York",
    "sg:classifiers":[
        {
            "category":"Restaurant",
            "type":"Food & Drink"
        }
    ],
    "sg:phone":"+1 212 581 1774",
    "sg:postcode":"10036",
    "sg:province":"NY",
    "wof:name":"Mogul 57 Restaurant",
    "wof:placetype":"venue"
},
  "geometry": {"coordinates":[-73.990143,40.760556],"type":"Point"}
}