{
  "type": "Feature",
  "properties": {
    "iso:country":"US",
    "sg:address":"3549 Broadway",
    "sg:city":"New York",
    "sg:classifiers":[
        {
            "category":"Restaurant",
            "type":"Food & Drink"
        }
    ],
    "sg:phone":"+1 212 281 5330",
    "sg:postcode":"10031",
    "sg:province":"NY",
    "sg:website":"www.mcdonalds.com",
    "wof:name":"Mc Donald's",
    "wof:placetype":"venue"
},
  "geometry": {"coordinates":[-73.95016099999999,40.826895],"type":"Point"}
}