{
  "type": "Feature",
  "properties": {
    "iso:country":"US",
    "sg:address":"2100 Brighton Henrietta Town Line Rd Ste 3",
    "sg:city":"Rochester",
    "sg:classifiers":[
        {
            "category":"Shopping",
            "subcategory":"Stationery & Office Supplies",
            "type":"Retail Goods"
        },
        {
            "category":"Manufacturing",
            "subcategory":"Electronics",
            "type":"Manufacturing & Wholesale Goods"
        }
    ],
    "sg:phone":"+1 585 427 2260",
    "sg:postcode":"14623",
    "sg:province":"NY",
    "sg:tags":[
        "machine",
        "printers-equipment",
        "copy"
    ],
    "wof:name":"Upstate Graphics",
    "wof:placetype":"venue"
},
  "geometry": {"coordinates":[-77.621548,43.094461],"type":"Point"}
}