{
  "type": "Feature",
  "properties": {
    "iso:country":"US",
    "sg:address":"5 Loren Dr",
    "sg:city":"Poughkeepsie",
    "sg:classifiers":[
        {
            "category":"Real Estate",
            "subcategory":"Real Estate Agent",
            "type":"Services"
        }
    ],
    "sg:phone":"+1 845 471 5121",
    "sg:postcode":"12603",
    "sg:province":"NY",
    "wof:name":"Kingsgate Realty Inc",
    "wof:placetype":"venue"
},
  "geometry": {"coordinates":[-73.92283500000001,41.673957],"type":"Point"}
}