{
  "type": "Feature",
  "properties": {
    "addr:full":"215 E 4th St Between Aves. A & B New York NY 10009",
    "addr:housenumber":"215",
    "addr:postcode":"10009",
    "addr:street":"E 4Th St;Aves.",
    "iso:country":"US",
    "sg:address":"215 E 4th St Between Aves. A & B",
    "sg:city":"New York",
    "sg:classifiers":[
        {
            "category":"Restaurant",
            "type":"Food & Drink"
        },
        {
            "category":"Bars & Pubs",
            "subcategory":"Wine Bar",
            "type":"Food & Drink"
        }
    ],
    "sg:phone":"+1 212 539 1011",
    "sg:postcode":"10009",
    "sg:province":"NY",
    "sg:tags":[
        "italian"
    ],
    "sg:website":"www.invino-ny.com/",
    "wof:name":"In Vino",
    "wof:placetype":"venue"
},
  "geometry": {"coordinates":[-73.983475,40.723703],"type":"Point"}
}