{
  "type": "Feature",
  "properties": {
    "addr:full":"592 Morris Park Ave Bronx NY 10460",
    "addr:housenumber":"592",
    "addr:postcode":"10460",
    "addr:street":"Morris Park Ave",
    "iso:country":"US",
    "sg:address":"592 Morris Park Ave",
    "sg:city":"Bronx",
    "sg:classifiers":[
        {
            "category":"Shopping",
            "subcategory":"Musical Instruments",
            "type":"Retail Goods"
        }
    ],
    "sg:phone":"+1 718 828 8597",
    "sg:postcode":"10460",
    "sg:province":"NY",
    "sg:tags":[
        "music",
        "dealer"
    ],
    "wof:name":"Prolific Music Group",
    "wof:placetype":"venue"
},
  "geometry": {"coordinates":[-73.86994799999999,40.843598],"type":"Point"}
}