{
  "type": "Feature",
  "properties": {
    "addr:full":"1443 Ocean Pkwy Brooklyn NY 11230",
    "addr:housenumber":"1443",
    "addr:postcode":"11230",
    "addr:street":"Ocean Pkwy",
    "iso:country":"US",
    "sg:address":"1443 Ocean Pkwy",
    "sg:city":"Brooklyn",
    "sg:classifiers":[
        {
            "category":"Health Services",
            "subcategory":"Doctor",
            "type":"Services"
        }
    ],
    "sg:phone":"+1 718 376 9494",
    "sg:postcode":"11230",
    "sg:province":"NY",
    "sg:tags":[
        "physician",
        "surgeon"
    ],
    "wof:name":"Herman Tessler MD",
    "wof:placetype":"venue"
},
  "geometry": {"coordinates":[-73.968204,40.612842],"type":"Point"}
}