{
  "type": "Feature",
  "properties": {
    "iso:country":"US",
    "sg:address":"45 Middle Ave",
    "sg:city":"Holtsville",
    "sg:classifiers":[
        {
            "category":"Restaurant",
            "type":"Food & Drink"
        }
    ],
    "sg:phone":"+1 631 289 3320",
    "sg:postcode":"11742",
    "sg:province":"NY",
    "sg:tags":[
        "traditional",
        "american",
        "steakhouse"
    ],
    "sg:website":"www.charliebrowns.com",
    "wof:name":"Charlie Brown's Steakhouse",
    "wof:placetype":"venue"
},
  "geometry": {"coordinates":[-73.05624299999999,40.815971],"type":"Point"}
}