{
  "type": "Feature",
  "properties": {
    "addr:full":"1500 Noble Ave Bronx NY 10460",
    "addr:housenumber":"1500",
    "addr:postcode":"10460",
    "addr:street":"Noble Ave",
    "iso:country":"US",
    "sg:address":"1500 Noble Ave",
    "sg:city":"Bronx",
    "sg:classifiers":[
        {
            "category":"Cinema",
            "subcategory":"Movie Rental",
            "type":"Entertainment"
        }
    ],
    "sg:phone":"+1   ",
    "sg:postcode":"10460",
    "sg:province":"NY",
    "sg:tags":[
        "video",
        "tape"
    ],
    "wof:name":"Rick Holman Video Producucts",
    "wof:placetype":"venue"
},
  "geometry": {"coordinates":[-73.871376,40.836716],"type":"Point"}
}