{
  "type": "Feature",
  "properties": {
    "addr:full":"119 High St Peekskill NY 10566",
    "addr:housenumber":"119",
    "addr:postcode":"10566",
    "addr:street":"High St",
    "iso:country":"US",
    "sg:address":"119 High St",
    "sg:city":"Peekskill",
    "sg:classifiers":[
        {
            "category":"Building & Trades",
            "subcategory":"Landscaping Services",
            "type":"Services"
        }
    ],
    "sg:phone":"+1 845 736 0272",
    "sg:postcode":"10566",
    "sg:province":"NY",
    "wof:name":"Bantas Tree Service",
    "wof:placetype":"venue"
},
  "geometry": {"coordinates":[-73.913909,41.292816],"type":"Point"}
}