{
  "type": "Feature",
  "properties": {
    "iso:country":"US",
    "sg:address":"4 Lincoln Ave",
    "sg:city":"Holbrook",
    "sg:classifiers":[
        {
            "category":"Communications",
            "type":"Services"
        }
    ],
    "sg:phone":"+1   ",
    "sg:postcode":"11741",
    "sg:province":"NY",
    "sg:tags":[
        "communication"
    ],
    "wof:name":"Tdli Communications Corp",
    "wof:placetype":"venue"
},
  "geometry": {"coordinates":[-73.08373,40.778034],"type":"Point"}
}