{
  "type": "Feature",
  "properties": {
    "addr:full":"547 State Hwy 17M Middletown NY 10940",
    "addr:housenumber":"547",
    "addr:postcode":"10940",
    "addr:street":"State Hwy",
    "iso:country":"US",
    "sg:address":"547 State Hwy 17M",
    "sg:city":"Middletown",
    "sg:classifiers":[
        {
            "category":"Real Estate",
            "subcategory":"Real Estate Agent",
            "type":"Services"
        }
    ],
    "sg:phone":"+1 845 344 1480",
    "sg:postcode":"10940",
    "sg:province":"NY",
    "wof:name":"Real Estate Circuit",
    "wof:placetype":"venue"
},
  "geometry": {"coordinates":[-74.41533800000001,41.470203],"type":"Point"}
}