{
  "type": "Feature",
  "properties": {
    "iso:country":"US",
    "sg:address":"47 Remsen Ave",
    "sg:city":"Monsey",
    "sg:classifiers":[
        {
            "category":"Real Estate",
            "subcategory":"Developer",
            "type":"Services"
        }
    ],
    "sg:phone":"+1 845 356 3586",
    "sg:postcode":"10952",
    "sg:province":"NY",
    "wof:name":"148 Lee Development Corp",
    "wof:placetype":"venue"
},
  "geometry": {"coordinates":[-74.08055899999999,41.114399],"type":"Point"}
}