{
  "type": "Feature",
  "properties": {
    "addr:full":"384 N 4th St Lindenhurst NY 11757",
    "addr:housenumber":"384",
    "addr:postcode":"11757",
    "addr:street":"N 4Th St",
    "iso:country":"US",
    "sg:address":"384 N 4th St",
    "sg:city":"Lindenhurst",
    "sg:classifiers":[
        {
            "category":"Building & Trades",
            "subcategory":"Construction",
            "type":"Services"
        }
    ],
    "sg:phone":"+1 631 226 0750",
    "sg:postcode":"11757",
    "sg:province":"NY",
    "sg:tags":[
        "system",
        "specialty",
        "heating",
        "contractor",
        "air conditioning"
    ],
    "wof:name":"Joe Mirabile Plumbing & Heating",
    "wof:placetype":"venue"
},
  "geometry": {"coordinates":[-73.379345,40.692168],"type":"Point"}
}