{
  "type": "Feature",
  "properties": {
    "addr:full":"144 Ramapo Rd Garnerville NY 10923",
    "addr:housenumber":"144",
    "addr:postcode":"10923",
    "addr:street":"Ramapo Rd",
    "iso:country":"US",
    "sg:address":"144 Ramapo Rd",
    "sg:city":"Garnerville",
    "sg:classifiers":[
        {
            "category":"Bakery",
            "type":"Food & Drink"
        }
    ],
    "sg:phone":"+1 845 269 3448",
    "sg:postcode":"10923",
    "sg:province":"NY",
    "wof:name":"Eben Ezer Bakery",
    "wof:placetype":"venue"
},
  "geometry": {"coordinates":[-73.991272,41.201839],"type":"Point"}
}