{
  "type": "Feature",
  "properties": {
    "iso:country":"US",
    "sg:address":"6438 Shaler Ave",
    "sg:city":"Ridgewood",
    "sg:classifiers":[
        {
            "category":"Retail",
            "subcategory":"Auto Repair",
            "type":"Services"
        }
    ],
    "sg:phone":"+1 718 381 5663",
    "sg:postcode":"11385",
    "sg:province":"NY",
    "wof:name":"R & M Auto Repair",
    "wof:placetype":"venue"
},
  "geometry": {"coordinates":[-73.892303,40.7034],"type":"Point"}
}