{
  "type": "Feature",
  "properties": {
    "addr:full":"46 Rte 25A Setauket NY 11733",
    "addr:housenumber":"46",
    "addr:postcode":"11733",
    "addr:street":"Rte 25A",
    "iso:country":"US",
    "sg:address":"46 Rte 25A",
    "sg:city":"Setauket",
    "sg:classifiers":[
        {
            "category":"Government",
            "subcategory":"Office",
            "type":"Public Place"
        }
    ],
    "sg:phone":"+1 631 854 1500",
    "sg:postcode":"11733",
    "sg:province":"NY",
    "wof:name":"Suffolk County Legislator",
    "wof:placetype":"venue"
},
  "geometry": {"coordinates":[-73.106138,40.94144],"type":"Point"}
}