{
  "type": "Feature",
  "properties": {
    "addr:full":"4 Audabon Cir Rochester NY 14624",
    "addr:housenumber":"4",
    "addr:postcode":"14624",
    "addr:street":"Audabon Cir",
    "iso:country":"US",
    "sg:address":"4 Audabon Cir",
    "sg:city":"Rochester",
    "sg:classifiers":[
        {
            "category":"Retail",
            "subcategory":"Portrait Studio",
            "type":"Services"
        }
    ],
    "sg:phone":"+1 585 426 4250",
    "sg:postcode":"14624",
    "sg:province":"NY",
    "sg:tags":[
        "photo"
    ],
    "wof:name":"Innovative Images Photography",
    "wof:placetype":"venue"
},
  "geometry": {"coordinates":[-77.719373,43.115043],"type":"Point"}
}