{
  "type": "Feature",
  "properties": {
    "iso:country":"US",
    "sg:address":"655 Middle Country Rd Unit C",
    "sg:city":"Saint James",
    "sg:classifiers":[
        {
            "category":"Arts & Performance",
            "subcategory":"Arts Center",
            "type":"Entertainment"
        }
    ],
    "sg:phone":"+1 631 584 7100",
    "sg:postcode":"11780",
    "sg:province":"NY",
    "sg:tags":[
        "performing"
    ],
    "sg:website":"www.dancemagicballroom.com",
    "wof:name":"Dance Magic Ballroom",
    "wof:placetype":"venue"
},
  "geometry": {"coordinates":[-73.155058,40.860606],"type":"Point"}
}