{
  "type": "Feature",
  "properties": {
    "addr:full":"99 W Hawthorne Ave Valley Stream NY 11580",
    "addr:housenumber":"99",
    "addr:postcode":"11580",
    "addr:street":"W Hawthorne Ave",
    "iso:country":"US",
    "sg:address":"99 W Hawthorne Ave",
    "sg:city":"Valley Stream",
    "sg:classifiers":[
        {
            "category":"Professional",
            "subcategory":"Lawyer & Legal Services",
            "type":"Services"
        }
    ],
    "sg:phone":"+1 516 825 7500",
    "sg:postcode":"11580",
    "sg:province":"NY",
    "sg:tags":[
        "attorney"
    ],
    "wof:name":"Joseph R Coryat Law Office",
    "wof:placetype":"venue"
},
  "geometry": {"coordinates":[-73.703981,40.662073],"type":"Point"}
}