{
  "type": "Feature",
  "properties": {
    "addr:full":"16 Washington Ave Coxsackie NY 12051",
    "addr:housenumber":"16",
    "addr:postcode":"12051",
    "addr:street":"Washington Ave",
    "iso:country":"US",
    "sg:address":"16 Washington Ave",
    "sg:city":"Coxsackie",
    "sg:classifiers":[
        {
            "category":"Organizations",
            "subcategory":"Religious Organization",
            "type":"Services"
        }
    ],
    "sg:phone":"+1 518 731 6084",
    "sg:postcode":"12051",
    "sg:province":"NY",
    "sg:tags":[
        "church"
    ],
    "wof:name":"Second Reformed Church",
    "wof:placetype":"venue"
},
  "geometry": {"coordinates":[-73.804571,42.352392],"type":"Point"}
}