{
  "type": "Feature",
  "properties": {
    "addr:full":"901 19th St Watervliet NY 12189",
    "addr:housenumber":"901",
    "addr:postcode":"12189",
    "addr:street":"19Th St",
    "iso:country":"US",
    "sg:address":"901 19th St",
    "sg:city":"Watervliet",
    "sg:classifiers":[
        {
            "category":"Personal",
            "subcategory":"Beauty Salon",
            "type":"Services"
        }
    ],
    "sg:phone":"+1 518 273 9016",
    "sg:postcode":"12189",
    "sg:province":"NY",
    "sg:tags":[
        "unisex",
        "hair",
        "replacement"
    ],
    "wof:name":"Mike's Cut & Style",
    "wof:placetype":"venue"
},
  "geometry": {"coordinates":[-73.709604,42.732402],"type":"Point"}
}