{
  "type": "Feature",
  "properties": {
    "addr:full":"2109 E 18th St Brooklyn NY 11229",
    "addr:housenumber":"2109",
    "addr:postcode":"11229",
    "addr:street":"E 18Th St",
    "iso:country":"US",
    "sg:address":"2109 E 18th St",
    "sg:city":"Brooklyn",
    "sg:classifiers":[
        {
            "category":"Personal",
            "subcategory":"Beauty Salon",
            "type":"Services"
        }
    ],
    "sg:phone":"+1 718 934 8899",
    "sg:postcode":"11229",
    "sg:province":"NY",
    "sg:tags":[
        "hair"
    ],
    "wof:name":"May May Beauty Salon",
    "wof:placetype":"venue"
},
  "geometry": {"coordinates":[-73.953474,40.598836],"type":"Point"}
}