{
  "type": "Feature",
  "properties": {
    "addr:full":"155 E Ames Ct Plainview NY 11803",
    "addr:housenumber":"155",
    "addr:postcode":"11803",
    "addr:street":"E Ames Ct",
    "iso:country":"US",
    "sg:address":"155 E Ames Ct",
    "sg:city":"Plainview",
    "sg:classifiers":[
        {
            "category":"Manufacturing",
            "subcategory":"Electronics",
            "type":"Manufacturing & Wholesale Goods"
        }
    ],
    "sg:phone":"+1   ",
    "sg:postcode":"11803",
    "sg:province":"NY",
    "sg:tags":[
        "mfg",
        "electron",
        "industrial",
        "machinery",
        "tube"
    ],
    "wof:name":"Y & Z Precision Machine Shop",
    "wof:placetype":"venue"
},
  "geometry": {"coordinates":[-73.46496500000001,40.791857],"type":"Point"}
}