{
  "type": "Feature",
  "properties": {
    "addr:full":"632 77th St Brooklyn NY 11209",
    "addr:housenumber":"632",
    "addr:postcode":"11209",
    "addr:street":"77Th St",
    "iso:country":"US",
    "sg:address":"632 77th St",
    "sg:city":"Brooklyn",
    "sg:classifiers":[
        {
            "category":"Professional",
            "type":"Services"
        },
        {
            "category":"Banks & Credit Unions",
            "subcategory":"Bank",
            "type":"Services"
        }
    ],
    "sg:phone":"+1 718 238 8718",
    "sg:postcode":"11209",
    "sg:province":"NY",
    "sg:tags":[
        "machine",
        "teller",
        "automated"
    ],
    "wof:name":"Safe & Sound Atm Inc",
    "wof:placetype":"venue"
},
  "geometry": {"coordinates":[-74.01997,40.626033],"type":"Point"}
}