{
  "type": "Feature",
  "properties": {
    "iso:country":"US",
    "sg:address":"390 Park Ave S",
    "sg:city":"New York",
    "sg:classifiers":[
        {
            "category":"Organizations",
            "subcategory":"Religious Organization",
            "type":"Services"
        }
    ],
    "sg:phone":"+1 212 532 5369",
    "sg:postcode":"10016",
    "sg:province":"NY",
    "sg:tags":[
        "church"
    ],
    "wof:name":"Metropolitan New York ELCA",
    "wof:placetype":"venue"
},
  "geometry": {"coordinates":[-73.984229,40.743207],"type":"Point"}
}