{
  "type": "Feature",
  "properties": {
    "iso:country":"US",
    "sg:address":"163 Hester Street",
    "sg:city":"New York",
    "sg:classifiers":[
        {
            "category":"Shopping",
            "subcategory":"Hobbies, Toys, & Games",
            "type":"Retail Goods"
        },
        {
            "category":"Coffee & Tea",
            "type":"Food & Drink"
        }
    ],
    "sg:postcode":"10013",
    "sg:province":"NY",
    "sg:tags":[
        "toy",
        "store"
    ],
    "wof:name":"Tic Tac Toe Boutique Cafe",
    "wof:placetype":"venue"
},
  "geometry": {"coordinates":[-73.996442,40.717794],"type":"Point"}
}