{
  "type": "Feature",
  "properties": {
    "addr:full":"101 Bedford Rd Chappaqua NY 10514",
    "addr:housenumber":"101",
    "addr:postcode":"10514",
    "addr:street":"Bedford Rd",
    "iso:country":"US",
    "sg:address":"101 Bedford Rd",
    "sg:city":"Chappaqua",
    "sg:classifiers":[
        {
            "category":"Personal",
            "subcategory":"Beauty Salon",
            "type":"Services"
        }
    ],
    "sg:phone":"+1 914 238 2301",
    "sg:postcode":"10514",
    "sg:province":"NY",
    "wof:name":"Cathy Hair & Co",
    "wof:placetype":"venue"
},
  "geometry": {"coordinates":[-73.763947,41.160202],"type":"Point"}
}