{
  "type": "Feature",
  "properties": {
    "addr:full":"450 Nassau Blvd West Hempstead NY 11552",
    "addr:housenumber":"450",
    "addr:postcode":"11552",
    "addr:street":"Nassau Blvd West",
    "iso:country":"US",
    "sg:address":"450 Nassau Blvd",
    "sg:city":"West Hempstead",
    "sg:classifiers":[
        {
            "category":"Government",
            "subcategory":"Office",
            "type":"Public Place"
        }
    ],
    "sg:phone":"+1 516 483 6244",
    "sg:postcode":"11552",
    "sg:province":"NY",
    "sg:tags":[
        "educational",
        "program",
        "administrative"
    ],
    "wof:name":"W Hempstead Uf School",
    "wof:placetype":"venue"
},
  "geometry": {"coordinates":[-73.660462,40.69461],"type":"Point"}
}