{
  "type": "Feature",
  "properties": {
    "addr:full":"1448 57th St Brooklyn NY 11219",
    "addr:housenumber":"1448",
    "addr:postcode":"11219",
    "addr:street":"57Th St",
    "iso:country":"US",
    "sg:address":"1448 57th St",
    "sg:city":"Brooklyn",
    "sg:classifiers":[
        {
            "category":"Organizations",
            "subcategory":"Religious Organization",
            "type":"Services"
        }
    ],
    "sg:phone":"+1 718 633 4339",
    "sg:postcode":"11219",
    "sg:province":"NY",
    "sg:tags":[
        "clergy"
    ],
    "wof:name":"Leon N Gordon",
    "wof:placetype":"venue"
},
  "geometry": {"coordinates":[-73.993242,40.628478],"type":"Point"}
}