{
  "type": "Feature",
  "properties": {
    "addr:full":"501 Atlantic Ave Freeport NY 11520",
    "addr:housenumber":"501",
    "addr:postcode":"11520",
    "addr:street":"Atlantic Ave",
    "iso:country":"US",
    "sg:address":"501 Atlantic Ave",
    "sg:city":"Freeport",
    "sg:classifiers":[
        {
            "category":"Retail",
            "subcategory":"Repair Shop",
            "type":"Services"
        }
    ],
    "sg:phone":"+1 516 213 0877",
    "sg:postcode":"11520",
    "sg:province":"NY",
    "sg:tags":[
        "lock",
        "locksmith"
    ],
    "wof:name":"A 24 Hours Emergency Locksmith",
    "wof:placetype":"venue"
},
  "geometry": {"coordinates":[-73.59687,40.64329],"type":"Point"}
}