{
  "type": "Feature",
  "properties": {
    "addr:full":"131 Tulip Ave Floral Park NY 11001",
    "addr:housenumber":"131",
    "addr:postcode":"11001",
    "addr:street":"Tulip Ave",
    "iso:country":"US",
    "sg:address":"131 Tulip Ave",
    "sg:city":"Floral Park",
    "sg:classifiers":[
        {
            "category":"Professional",
            "subcategory":"Accounting & Tax Preparation",
            "type":"Services"
        }
    ],
    "sg:phone":"+1 516 354 2205",
    "sg:postcode":"11001",
    "sg:province":"NY",
    "sg:tags":[
        "accountant"
    ],
    "wof:name":"Walsh Mulligan & Grote",
    "wof:placetype":"venue"
},
  "geometry": {"coordinates":[-73.704587,40.724966],"type":"Point"}
}