{
  "type": "Feature",
  "properties": {
    "addr:full":"55 Chestnut St Cold Spring NY 10516",
    "addr:housenumber":"55",
    "addr:postcode":"10516",
    "addr:street":"Chestnut St",
    "iso:country":"US",
    "sg:address":"55 Chestnut St",
    "sg:city":"Cold Spring",
    "sg:classifiers":[
        {
            "category":"Food & Beverages",
            "subcategory":"Groceries & Convenience Stores",
            "type":"Retail Goods"
        }
    ],
    "sg:phone":"+1 845 265 9823",
    "sg:postcode":"10516",
    "sg:province":"NY",
    "wof:name":"D P Mart",
    "wof:placetype":"venue"
},
  "geometry": {"coordinates":[-73.95120300000001,41.417741],"type":"Point"}
}