{
  "type": "Feature",
  "properties": {
    "addr:full":"1616 Mermaid Avenue Brooklyn NY 11224",
    "addr:housenumber":"1616",
    "addr:postcode":"11224",
    "addr:street":"Mermaid Avenue",
    "iso:country":"US",
    "sg:address":"1616 Mermaid Avenue",
    "sg:city":"Brooklyn",
    "sg:classifiers":[
        {
            "category":"Building & Trades",
            "subcategory":"Construction",
            "type":"Services"
        }
    ],
    "sg:phone":"+1 718 372 6107",
    "sg:postcode":"11224",
    "sg:province":"NY",
    "sg:tags":[
        "contractor"
    ],
    "wof:name":"Mercon Contracting Corporation",
    "wof:placetype":"venue"
},
  "geometry": {"coordinates":[-73.98407,40.576803],"type":"Point"}
}