{
  "type": "Feature",
  "properties": {
    "addr:full":"70 E 96th St New York NY 10128",
    "addr:housenumber":"70",
    "addr:postcode":"10128",
    "addr:street":"E 96Th St",
    "iso:country":"US",
    "sg:address":"70 E 96th St",
    "sg:city":"New York",
    "sg:classifiers":[
        {
            "category":"Health Services",
            "subcategory":"Optometrist",
            "type":"Services"
        }
    ],
    "sg:phone":"+1 212 289 2244",
    "sg:postcode":"10128",
    "sg:province":"NY",
    "sg:tags":[
        "ophthalmologist"
    ],
    "wof:name":"Barker Barbara Ann MD",
    "wof:placetype":"venue"
},
  "geometry": {"coordinates":[-73.953397,40.786704],"type":"Point"}
}