{
  "type": "Feature",
  "properties": {
    "addr:full":"2886 State Hwy 32 Kingston NY 12401",
    "addr:housenumber":"2886",
    "addr:postcode":"12401",
    "addr:street":"State Hwy 32",
    "iso:country":"US",
    "sg:address":"2886 State Hwy 32",
    "sg:city":"Kingston",
    "sg:classifiers":[
        {
            "category":"Building & Trades",
            "subcategory":"Electrical",
            "type":"Services"
        }
    ],
    "sg:phone":"+1 845 331 4530",
    "sg:postcode":"12401",
    "sg:province":"NY",
    "sg:tags":[
        "electrical",
        "electric",
        "contractor"
    ],
    "wof:name":"B & G Electric Inc",
    "wof:placetype":"venue"
},
  "geometry": {"coordinates":[-74.033286,41.896263],"type":"Point"}
}