{
  "type": "Feature",
  "properties": {
    "iso:country":"US",
    "sg:address":"1250 Norby Rd",
    "sg:city":"Jamestown",
    "sg:classifiers":[
        {
            "category":"Professional",
            "type":"Services"
        }
    ],
    "sg:phone":"+1 716 484 2330",
    "sg:postcode":"14701",
    "sg:province":"NY",
    "sg:tags":[
        "establishment"
    ],
    "wof:name":"Resource Center",
    "wof:placetype":"venue"
},
  "geometry": {"coordinates":[-79.22319899999999,42.053615],"type":"Point"}
}