{
  "type": "Feature",
  "properties": {
    "iso:country":"US",
    "sg:address":"2122 Westchester Ave",
    "sg:city":"Bronx",
    "sg:classifiers":[
        {
            "category":"Insurance",
            "subcategory":"Insurance Agent",
            "type":"Services"
        }
    ],
    "sg:phone":"+1 718 863 5942",
    "sg:postcode":"10462",
    "sg:province":"NY",
    "sg:tags":[
        "consultant"
    ],
    "wof:name":"CYA Brokerage Inc",
    "wof:placetype":"venue"
},
  "geometry": {"coordinates":[-73.853951,40.83387],"type":"Point"}
}