{
  "type": "Feature",
  "properties": {
    "addr:full":"18 Montgomery St Middletown NY 10940",
    "addr:housenumber":"18",
    "addr:postcode":"10940",
    "addr:street":"Montgomery St",
    "iso:country":"US",
    "sg:address":"18 Montgomery St",
    "sg:city":"Middletown",
    "sg:classifiers":[
        {
            "category":"Wholesale",
            "subcategory":"Stationery",
            "type":"Manufacturing & Wholesale Goods"
        },
        {
            "category":"Manufacturing",
            "subcategory":"Printing",
            "type":"Manufacturing & Wholesale Goods"
        }
    ],
    "sg:phone":"+1 845 956 5057",
    "sg:postcode":"10940",
    "sg:province":"NY",
    "sg:tags":[
        "publisher",
        "school",
        "book",
        "supply"
    ],
    "wof:name":"N & N Publishing Company Inc",
    "wof:placetype":"venue"
},
  "geometry": {"coordinates":[-74.415705,41.446041],"type":"Point"}
}