{
  "type": "Feature",
  "properties": {
    "addr:full":"137 Hester St New York NY 10002",
    "addr:housenumber":"137",
    "addr:postcode":"10002",
    "addr:street":"Hester St",
    "iso:country":"US",
    "sg:address":"137 Hester St",
    "sg:city":"New York",
    "sg:classifiers":[
        {
            "category":"Personal",
            "subcategory":"Beauty Salon",
            "type":"Services"
        }
    ],
    "sg:phone":"+1 212 966 8644",
    "sg:postcode":"10002",
    "sg:province":"NY",
    "wof:name":"Jin Ming Huang Trading Inc",
    "wof:placetype":"venue"
},
  "geometry": {"coordinates":[-73.995429,40.717279],"type":"Point"}
}