{
  "type": "Feature",
  "properties": {
    "iso:country":"US",
    "sg:address":"30 Jones St",
    "sg:city":"New York",
    "sg:classifiers":[
        {
            "category":"Professional",
            "subcategory":"Accounting & Tax Preparation",
            "type":"Services"
        }
    ],
    "sg:phone":"+1   ",
    "sg:postcode":"10014",
    "sg:province":"NY",
    "sg:tags":[
        "return"
    ],
    "wof:name":"Taxing Women Inc",
    "wof:placetype":"venue"
},
  "geometry": {"coordinates":[-74.002906,40.731843],"type":"Point"}
}