{
  "type": "Feature",
  "properties": {
    "addr:full":"11 Ferry Street Staten Island NY 10302",
    "addr:housenumber":"11",
    "addr:postcode":"10302",
    "addr:street":"Ferry Street",
    "iso:country":"US",
    "sg:address":"11 Ferry Street",
    "sg:city":"Staten Island",
    "sg:classifiers":[
        {
            "category":"Building & Trades",
            "subcategory":"Construction",
            "type":"Services"
        }
    ],
    "sg:phone":"+1 718 720 4603",
    "sg:postcode":"10302",
    "sg:province":"NY",
    "sg:tags":[
        "contractor"
    ],
    "wof:name":"Formica Construction",
    "wof:placetype":"venue"
},
  "geometry": {"coordinates":[-74.132114,40.640351],"type":"Point"}
}