{
  "type": "Feature",
  "properties": {
    "iso:country":"US",
    "sg:address":"776 Neversink Rd",
    "sg:city":"Liberty",
    "sg:classifiers":[
        {
            "category":"Building & Trades",
            "subcategory":"Construction",
            "type":"Services"
        }
    ],
    "sg:phone":"+1 845 292 2686",
    "sg:postcode":"12754",
    "sg:province":"NY",
    "sg:tags":[
        "home",
        "general",
        "family",
        "contractor"
    ],
    "wof:name":"TK Construction",
    "wof:placetype":"venue"
},
  "geometry": {"coordinates":[-74.682261,41.823633],"type":"Point"}
}