{
  "type": "Feature",
  "properties": {
    "iso:country":"US",
    "sg:address":"40 Roselle St Ste 2",
    "sg:city":"Mineola",
    "sg:classifiers":[
        {
            "category":"Shopping",
            "subcategory":"Hobbies, Toys, & Games",
            "type":"Retail Goods"
        }
    ],
    "sg:phone":"+1 516 747 9009",
    "sg:postcode":"11501",
    "sg:province":"NY",
    "sg:tags":[
        "toy",
        "store"
    ],
    "wof:name":"Toy Truck City",
    "wof:placetype":"venue"
},
  "geometry": {"coordinates":[-73.636045,40.753843],"type":"Point"}
}