{
  "type": "Feature",
  "properties": {
    "addr:full":"518 Stratford Rd Brooklyn NY 11218",
    "addr:housenumber":"518",
    "addr:postcode":"11218",
    "addr:street":"Stratford Rd",
    "iso:country":"US",
    "sg:address":"518 Stratford Rd",
    "sg:city":"Brooklyn",
    "sg:classifiers":[
        {
            "category":"Manufacturing",
            "subcategory":"Printing",
            "type":"Manufacturing & Wholesale Goods"
        }
    ],
    "sg:phone":"+1   ",
    "sg:postcode":"11218",
    "sg:province":"NY",
    "sg:tags":[
        "book"
    ],
    "wof:name":"Wazuri Publishing Company",
    "wof:placetype":"venue"
},
  "geometry": {"coordinates":[-73.967472,40.637364],"type":"Point"}
}