{
  "type": "Feature",
  "properties": {
    "addr:full":"3251 State Hwy 39 Forestville NY 14062",
    "addr:housenumber":"3251",
    "addr:postcode":"14062",
    "addr:street":"State Hwy 39",
    "iso:country":"US",
    "sg:address":"3251 State Hwy 39",
    "sg:city":"Forestville",
    "sg:classifiers":[
        {
            "category":"Farming",
            "subcategory":"Vineyard",
            "type":"Manufacturing & Wholesale Goods"
        }
    ],
    "sg:phone":"+1 716 672 2597",
    "sg:postcode":"14062",
    "sg:province":"NY",
    "sg:tags":[
        "grape"
    ],
    "wof:name":"Richard Feinen",
    "wof:placetype":"venue"
},
  "geometry": {"coordinates":[-79.27335600000001,42.467787],"type":"Point"}
}