{
  "type": "Feature",
  "properties": {
    "addr:full":"141 Roosevelt Ave Massapequa Park NY 11762",
    "addr:housenumber":"141",
    "addr:postcode":"11762",
    "addr:street":"Roosevelt Ave",
    "iso:country":"US",
    "sg:address":"141 Roosevelt Ave",
    "sg:city":"Massapequa Park",
    "sg:classifiers":[
        {
            "category":"Shopping",
            "subcategory":"Musical Instruments",
            "type":"Retail Goods"
        }
    ],
    "sg:phone":"+1   ",
    "sg:postcode":"11762",
    "sg:province":"NY",
    "wof:name":"Dicarlo Guitars",
    "wof:placetype":"venue"
},
  "geometry": {"coordinates":[-73.450642,40.686887],"type":"Point"}
}