{
  "type": "Feature",
  "properties": {
    "addr:full":"1173 Pittsford Victor Rd Pittsford NY 14534",
    "addr:housenumber":"1173",
    "addr:postcode":"14534",
    "addr:street":"Pittsford Victor Rd",
    "iso:country":"US",
    "sg:address":"1173 Pittsford Victor Rd",
    "sg:city":"Pittsford",
    "sg:classifiers":[
        {
            "category":"Professional",
            "subcategory":"Testing Lab",
            "type":"Services"
        }
    ],
    "sg:phone":"+1 585 249 4820",
    "sg:postcode":"14534",
    "sg:province":"NY",
    "sg:tags":[
        "inspection",
        "infrared"
    ],
    "wof:name":"Ergonomy",
    "wof:placetype":"venue"
},
  "geometry": {"coordinates":[-77.46830799999999,43.047034],"type":"Point"}
}