{
  "type": "Feature",
  "properties": {
    "iso:country":"US",
    "sg:address":"229 W Houston Street",
    "sg:city":"New York",
    "sg:classifiers":[
        {
            "category":"Building & Trades",
            "subcategory":"Locksmith",
            "type":"Services"
        }
    ],
    "sg:phone":"+1 212 543 4444",
    "sg:postcode":"10014",
    "sg:province":"NY",
    "sg:tags":[
        "key"
    ],
    "wof:name":"A 24 Hr A Locksmith",
    "wof:placetype":"venue"
},
  "geometry": {"coordinates":[-74.004857,40.72844],"type":"Point"}
}