{
  "type": "Feature",
  "properties": {
    "addr:full":"206 Woodcrest Dr Buffalo NY 14220",
    "addr:housenumber":"206",
    "addr:postcode":"14220",
    "addr:street":"Woodcrest Dr",
    "iso:country":"US",
    "sg:address":"206 Woodcrest Dr",
    "sg:city":"Buffalo",
    "sg:classifiers":[
        {
            "category":"Retail",
            "subcategory":"Auto Repair",
            "type":"Services"
        }
    ],
    "sg:phone":"+1 716 826 0703",
    "sg:postcode":"14220",
    "sg:province":"NY",
    "sg:tags":[
        "repairing",
        "automobile"
    ],
    "wof:name":"Systems Auto",
    "wof:placetype":"venue"
},
  "geometry": {"coordinates":[-78.798666,42.833431],"type":"Point"}
}