{
  "type": "Feature",
  "properties": {
    "addr:full":"153 E 53rd St New York NY 10079",
    "addr:housenumber":"153",
    "addr:postcode":"10079",
    "addr:street":"E 53Rd St",
    "iso:country":"US",
    "sg:address":"153 E 53rd St",
    "sg:city":"New York",
    "sg:classifiers":[
        {
            "category":"Restaurant",
            "type":"Food & Drink"
        }
    ],
    "sg:phone":"+1 212 935 1744",
    "sg:postcode":"10079",
    "sg:province":"NY",
    "wof:name":"Market Cafe and Brick Oven Pizzeria",
    "wof:placetype":"venue"
},
  "geometry": {"coordinates":[-73.97077,40.758277],"type":"Point"}
}