{
  "type": "Feature",
  "properties": {
    "addr:full":"22 E 23rd Street New York NY 10010",
    "addr:housenumber":"22",
    "addr:postcode":"10010",
    "addr:street":"E 23Rd Street",
    "iso:country":"US",
    "sg:address":"22 E 23rd Street",
    "sg:city":"New York",
    "sg:classifiers":[
        {
            "category":"Restaurant",
            "type":"Food & Drink"
        }
    ],
    "sg:phone":"+1 212 353 9140",
    "sg:postcode":"10010",
    "sg:province":"NY",
    "wof:name":"Mc Donalds",
    "wof:placetype":"venue"
},
  "geometry": {"coordinates":[-73.987905,40.740704],"type":"Point"}
}