{
  "type": "Feature",
  "properties": {
    "addr:full":"708 3rd Ave New York NY 10017",
    "addr:housenumber":"708",
    "addr:postcode":"10017",
    "addr:street":"3Rd Ave",
    "iso:country":"US",
    "sg:address":"708 3rd Ave",
    "sg:city":"New York",
    "sg:classifiers":[
        {
            "category":"Professional",
            "subcategory":"Lawyer & Legal Services",
            "type":"Services"
        }
    ],
    "sg:phone":"+1 212 692 9030",
    "sg:postcode":"10017",
    "sg:province":"NY",
    "wof:name":"Crystal And Donohue",
    "wof:placetype":"venue"
},
  "geometry": {"coordinates":[-73.97342999999999,40.752437],"type":"Point"}
}