{
  "type": "Feature",
  "properties": {
    "addr:full":"218 Glen St Glen Cove NY 11542",
    "addr:housenumber":"218",
    "addr:postcode":"11542",
    "addr:street":"Glen St",
    "iso:country":"US",
    "sg:address":"218 Glen St",
    "sg:city":"Glen Cove",
    "sg:classifiers":[
        {
            "category":"Shopping",
            "subcategory":"Clothing, Apparel, & Fashions",
            "type":"Retail Goods"
        }
    ],
    "sg:phone":"+1   ",
    "sg:postcode":"11542",
    "sg:province":"NY",
    "sg:tags":[
        "jewelry"
    ],
    "wof:name":"Gold-N-Links",
    "wof:placetype":"venue"
},
  "geometry": {"coordinates":[-73.622821,40.861274],"type":"Point"}
}