{
  "type": "Feature",
  "properties": {
    "addr:full":"806 Union St Schenectady NY 12308",
    "addr:housenumber":"806",
    "addr:postcode":"12308",
    "addr:street":"Union St",
    "iso:country":"US",
    "sg:address":"806 Union St",
    "sg:city":"Schenectady",
    "sg:classifiers":[
        {
            "category":"Organizations",
            "subcategory":"Religious Organization",
            "type":"Services"
        }
    ],
    "sg:phone":"+1 518 374 4663",
    "sg:postcode":"12308",
    "sg:province":"NY",
    "wof:name":"St John Evangelist Ofc",
    "wof:placetype":"venue"
},
  "geometry": {"coordinates":[-73.932665,42.814946],"type":"Point"}
}