{
  "type": "Feature",
  "properties": {
    "addr:full":"205 Clinton Rd New Hartford NY 13413",
    "addr:housenumber":"205",
    "addr:postcode":"13413",
    "addr:street":"Clinton Rd",
    "iso:country":"US",
    "sg:address":"205 Clinton Rd",
    "sg:city":"New Hartford",
    "sg:classifiers":[
        {
            "category":"Retail",
            "subcategory":"Animal Services",
            "type":"Services"
        }
    ],
    "sg:phone":"+1 315 738 0299",
    "sg:postcode":"13413",
    "sg:province":"NY",
    "sg:tags":[
        "pet",
        "boarding",
        "sitting"
    ],
    "wof:name":"Casey's Kennel",
    "wof:placetype":"venue"
},
  "geometry": {"coordinates":[-75.33514099999999,43.070622],"type":"Point"}
}