{
  "type": "Feature",
  "properties": {
    "addr:full":"1431 Orange Tpke Monroe NY 10950",
    "addr:housenumber":"1431",
    "addr:postcode":"10950",
    "addr:street":"Orange Tpke",
    "iso:country":"US",
    "sg:address":"1431 Orange Tpke",
    "sg:city":"Monroe",
    "sg:classifiers":[
        {
            "category":"Social Services",
            "subcategory":"Child Care",
            "type":"Services"
        },
        {
            "category":"Education",
            "subcategory":"Preschool",
            "type":"Public Place"
        },
        {
            "category":"Education",
            "subcategory":"School",
            "type":"Public Place"
        }
    ],
    "sg:phone":"+1 845 783 2421",
    "sg:postcode":"10950",
    "sg:province":"NY",
    "sg:tags":[
        "elementary",
        "day"
    ],
    "wof:name":"Maple Lane Nursery School",
    "wof:placetype":"venue"
},
  "geometry": {"coordinates":[-74.18440200000001,41.3055],"type":"Point"}
}