{
  "type": "Feature",
  "properties": {
    "iso:country":"US",
    "sg:address":"2202 37th Ave",
    "sg:city":"Long Island City",
    "sg:classifiers":[
        {
            "category":"Retail",
            "subcategory":"Auto Repair",
            "type":"Services"
        }
    ],
    "sg:phone":"+1 718 482 0758",
    "sg:postcode":"11101",
    "sg:province":"NY",
    "wof:name":"T G M Auto Repairs",
    "wof:placetype":"venue"
},
  "geometry": {"coordinates":[-73.936897,40.757999],"type":"Point"}
}