{
  "type": "Feature",
  "properties": {
    "iso:country":"US",
    "sg:address":"747 Zeckendorf Blvd",
    "sg:city":"Garden City",
    "sg:classifiers":[
        {
            "category":"Restaurant",
            "type":"Food & Drink"
        }
    ],
    "sg:phone":"+1   ",
    "sg:postcode":"11530",
    "sg:province":"NY",
    "sg:tags":[
        "cafeteria"
    ],
    "wof:name":"Pushpas Cafeteria",
    "wof:placetype":"venue"
},
  "geometry": {"coordinates":[-73.60610200000001,40.739143],"type":"Point"}
}