{
  "type": "Feature",
  "properties": {
    "addr:full":"5806 Fort Hamilton Pkwy Brooklyn NY 11219",
    "addr:housenumber":"5806",
    "addr:postcode":"11219",
    "addr:street":"Fort Hamilton Pkwy",
    "iso:country":"US",
    "sg:address":"5806 Fort Hamilton Pkwy",
    "sg:city":"Brooklyn",
    "sg:classifiers":[
        {
            "category":"Shopping",
            "subcategory":"Florist",
            "type":"Retail Goods"
        }
    ],
    "sg:phone":"+1 718 853 3448",
    "sg:postcode":"11219",
    "sg:province":"NY",
    "wof:name":"Our Florist & Gift Shop",
    "wof:placetype":"venue"
},
  "geometry": {"coordinates":[-74.00483800000001,40.633665],"type":"Point"}
}