{
  "type": "Feature",
  "properties": {
    "addr:full":"566 State Hwy 82 Hopewell Jct NY 12533",
    "addr:housenumber":"566",
    "addr:postcode":"12533",
    "addr:street":"State Hwy 82",
    "iso:country":"US",
    "sg:address":"566 State Hwy 82",
    "sg:city":"Hopewell Jct",
    "sg:classifiers":[
        {
            "category":"Shopping",
            "type":"Retail Goods"
        }
    ],
    "sg:phone":"+1 845 223 3830",
    "sg:postcode":"12533",
    "sg:province":"NY",
    "sg:tags":[
        "monument"
    ],
    "wof:name":"Barre Memorials",
    "wof:placetype":"venue"
},
  "geometry": {"coordinates":[-73.811448,41.578924],"type":"Point"}
}