{
  "type": "Feature",
  "properties": {
    "addr:full":"990 6th Ave Manhattan NY 10018",
    "addr:housenumber":"990",
    "addr:postcode":"10018",
    "addr:street":"6Th Ave",
    "iso:country":"US",
    "sg:address":"990 6th Ave",
    "sg:city":"Manhattan",
    "sg:classifiers":[
        {
            "category":"Shopping",
            "type":"Retail Goods"
        }
    ],
    "sg:phone":"+1 212 366 0766",
    "sg:postcode":"10018",
    "sg:province":"NY",
    "sg:website":"www.courtsidetshirts.net",
    "wof:name":"Courtside Apparel,Inc",
    "wof:placetype":"venue"
},
  "geometry": {"coordinates":[-73.98659000000001,40.751451],"type":"Point"}
}