{
  "type": "Feature",
  "properties": {
    "iso:country":"US",
    "sg:address":"6630 Lincoln Ave",
    "sg:city":"Lockport",
    "sg:classifiers":[
        {
            "category":"Real Estate",
            "subcategory":"Real Estate Operator",
            "type":"Services"
        }
    ],
    "sg:phone":"+1 716 434 1538",
    "sg:postcode":"14094",
    "sg:province":"NY",
    "sg:tags":[
        "building",
        "operation",
        "commercial"
    ],
    "wof:name":"Chadwick Development",
    "wof:placetype":"venue"
},
  "geometry": {"coordinates":[-78.668052,43.153169],"type":"Point"}
}