{
  "type": "Feature",
  "properties": {
    "addr:full":"30 W 67 St New York NY 10023",
    "addr:housenumber":"30",
    "addr:postcode":"10023",
    "addr:street":"W 67 St",
    "iso:country":"US",
    "sg:address":"30 W 67 St",
    "sg:city":"New York",
    "sg:classifiers":[
        {
            "category":"Professional",
            "subcategory":"Engineering",
            "type":"Services"
        }
    ],
    "sg:phone":"+1 212 456 7777",
    "sg:postcode":"10023",
    "sg:province":"NY",
    "wof:name":"ABC",
    "wof:placetype":"venue"
},
  "geometry": {"coordinates":[-73.980524,40.773812],"type":"Point"}
}