{
  "type": "Feature",
  "properties": {
    "iso:country":"US",
    "sg:address":"34 W 38th St Frnt 1",
    "sg:city":"New York",
    "sg:classifiers":[
        {
            "category":"Manufacturing",
            "subcategory":"Leather Goods",
            "type":"Manufacturing & Wholesale Goods"
        }
    ],
    "sg:phone":"+1 212 730 2372",
    "sg:postcode":"10018",
    "sg:province":"NY",
    "wof:name":"Reliance Leather Group Incorporated",
    "wof:placetype":"venue"
},
  "geometry": {"coordinates":[-73.98386000000001,40.751307],"type":"Point"}
}