{
  "type": "Feature",
  "properties": {
    "addr:full":"1120 E Boston Post Rd Mamaroneck NY 10543",
    "addr:housenumber":"1120",
    "addr:postcode":"10543",
    "addr:street":"E Boston Post Rd",
    "iso:country":"US",
    "sg:address":"1120 E Boston Post Rd",
    "sg:city":"Mamaroneck",
    "sg:classifiers":[
        {
            "category":"Food & Beverages",
            "subcategory":"Groceries & Convenience Stores",
            "type":"Retail Goods"
        }
    ],
    "sg:phone":"+1   ",
    "sg:postcode":"10543",
    "sg:province":"NY",
    "wof:name":"Lords Farm",
    "wof:placetype":"venue"
},
  "geometry": {"coordinates":[-73.71980600000001,40.953942],"type":"Point"}
}