{
  "type": "Feature",
  "properties": {
    "addr:full":"85 Fairbanks Rd Churchville NY 14428",
    "addr:housenumber":"85",
    "addr:postcode":"14428",
    "addr:street":"Fairbanks Rd",
    "iso:country":"US",
    "sg:address":"85 Fairbanks Rd",
    "sg:city":"Churchville",
    "sg:classifiers":[
        {
            "category":"Building & Trades",
            "subcategory":"Landscaping Services",
            "type":"Services"
        }
    ],
    "sg:phone":"+1 585 330 6920",
    "sg:postcode":"14428",
    "sg:province":"NY",
    "sg:tags":[
        "tree"
    ],
    "wof:name":"Topnotch Tree Svc",
    "wof:placetype":"venue"
},
  "geometry": {"coordinates":[-77.82832399999999,43.117522],"type":"Point"}
}