{
  "type": "Feature",
  "properties": {
    "addr:full":"1626A Bedford Ave Brooklyn NY 11225",
    "addr:housenumber":"1626a",
    "addr:postcode":"11225",
    "addr:street":"Bedford Ave",
    "iso:country":"US",
    "sg:address":"1626A Bedford Ave",
    "sg:city":"Brooklyn",
    "sg:classifiers":[
        {
            "category":"Restaurant",
            "type":"Food & Drink"
        }
    ],
    "sg:phone":"+1 718 245 1777",
    "sg:postcode":"11225",
    "sg:province":"NY",
    "sg:tags":[
        "pizza"
    ],
    "sg:website":"www.billyspizzany.com",
    "wof:name":"Billy's Pizzeria Restaurant",
    "wof:placetype":"venue"
},
  "geometry": {"coordinates":[-73.95635299999999,40.667112],"type":"Point"}
}