{
  "type": "Feature",
  "properties": {
    "addr:full":"10410 Jamaica Avenue Richmond Hill NY 11418",
    "addr:housenumber":"10410",
    "addr:postcode":"11418",
    "addr:street":"Jamaica Avenue",
    "iso:country":"US",
    "sg:address":"10410 Jamaica Avenue",
    "sg:city":"Richmond Hill",
    "sg:classifiers":[
        {
            "category":"Restaurant",
            "type":"Food & Drink"
        }
    ],
    "sg:phone":"+1 718 846 8635",
    "sg:postcode":"11418",
    "sg:province":"NY",
    "sg:tags":[
        "pizza"
    ],
    "wof:name":"Tom's Pizzeria & Italian Restaurant",
    "wof:placetype":"venue"
},
  "geometry": {"coordinates":[-73.842924,40.695085],"type":"Point"}
}