{
  "type": "Feature",
  "properties": {
    "iso:country":"US",
    "sg:address":"3507 Mount Read Blvd",
    "sg:city":"Rochester",
    "sg:classifiers":[
        {
            "category":"Restaurant",
            "type":"Food & Drink"
        }
    ],
    "sg:phone":"+1 585 663 4400",
    "sg:postcode":"14616",
    "sg:province":"NY",
    "sg:tags":[
        "style",
        "family"
    ],
    "wof:name":"Tops Friendly Markets Pharmacies",
    "wof:placetype":"venue"
},
  "geometry": {"coordinates":[-77.659012,43.222165],"type":"Point"}
}