{
  "type": "Feature",
  "properties": {
    "iso:country":"US",
    "sg:address":"1423 48th St",
    "sg:city":"Brooklyn",
    "sg:classifiers":[
        {
            "category":"Organizations",
            "subcategory":"Religious Organization",
            "type":"Services"
        }
    ],
    "sg:phone":"+1 718 851 5275",
    "sg:postcode":"11219",
    "sg:province":"NY",
    "sg:tags":[
        "clergy"
    ],
    "wof:name":"Samuel Bochner",
    "wof:placetype":"venue"
},
  "geometry": {"coordinates":[-73.98746,40.633283],"type":"Point"}
}