{
  "type": "Feature",
  "properties": {
    "addr:full":"1013 Longwood Ave Bronx NY 10459",
    "addr:housenumber":"1013",
    "addr:postcode":"10459",
    "addr:street":"Longwood Ave",
    "iso:country":"US",
    "sg:address":"1013 Longwood Ave",
    "sg:city":"Bronx",
    "sg:classifiers":[
        {
            "category":"Travel",
            "subcategory":"Travel Agent",
            "type":"Entertainment"
        }
    ],
    "sg:phone":"+1 718 378 0663",
    "sg:postcode":"10459",
    "sg:province":"NY",
    "sg:tags":[
        "agency",
        "bureau"
    ],
    "wof:name":"Longwood Travel Inc",
    "wof:placetype":"venue"
},
  "geometry": {"coordinates":[-73.89643700000001,40.816585],"type":"Point"}
}