{
  "type": "Feature",
  "properties": {
    "addr:full":"9 Remsen St 2 Nyack NY 10960",
    "addr:housenumber":"9;2",
    "addr:postcode":"10960",
    "addr:street":"Remsen St",
    "iso:country":"US",
    "sg:address":"9 Remsen St 2",
    "sg:city":"Nyack",
    "sg:classifiers":[
        {
            "category":"Restaurant",
            "type":"Food & Drink"
        }
    ],
    "sg:phone":"+1 845 348 1870",
    "sg:postcode":"10960",
    "sg:province":"NY",
    "wof:name":"Eating Bright",
    "wof:placetype":"venue"
},
  "geometry": {"coordinates":[-73.917225,41.089702],"type":"Point"}
}