{
  "type": "Feature",
  "properties": {
    "iso:country":"US",
    "sg:address":"2484 W 1st St",
    "sg:city":"Brooklyn",
    "sg:classifiers":[
        {
            "category":"Professional",
            "subcategory":"Accounting & Tax Preparation",
            "type":"Services"
        }
    ],
    "sg:phone":"+1 718 998 7777",
    "sg:postcode":"11223",
    "sg:province":"NY",
    "sg:tags":[
        "consultant"
    ],
    "wof:name":"Tax Management Inc",
    "wof:placetype":"venue"
},
  "geometry": {"coordinates":[-73.971085,40.590129],"type":"Point"}
}