{
  "type": "Feature",
  "properties": {
    "iso:country":"US",
    "sg:address":"1230 Station Rd",
    "sg:city":"Medford",
    "sg:classifiers":[
        {
            "category":"Freight",
            "type":"Transportation"
        }
    ],
    "sg:phone":"+1   ",
    "sg:postcode":"11763",
    "sg:province":"NY",
    "sg:tags":[
        "local",
        "trucking"
    ],
    "wof:name":"Hbittle and Son",
    "wof:placetype":"venue"
},
  "geometry": {"coordinates":[-72.954903,40.813274],"type":"Point"}
}