{
  "type": "Feature",
  "properties": {
    "addr:full":"18 Royal Palm Dr Buffalo NY 14225",
    "addr:housenumber":"18",
    "addr:postcode":"14225",
    "addr:street":"Royal Palm Dr",
    "iso:country":"US",
    "sg:address":"18 Royal Palm Dr",
    "sg:city":"Buffalo",
    "sg:classifiers":[
        {
            "category":"Personal",
            "type":"Services"
        },
        {
            "category":"Professional",
            "subcategory":"Art Services",
            "type":"Services"
        }
    ],
    "sg:phone":"+1 716 681 2187",
    "sg:postcode":"14225",
    "sg:province":"NY",
    "sg:tags":[
        "photography",
        "videography",
        "wedding"
    ],
    "wof:name":"Nicole Knauber Photography",
    "wof:placetype":"venue"
},
  "geometry": {"coordinates":[-78.725829,42.927341],"type":"Point"}
}