{
  "type": "Feature",
  "properties": {
    "addr:full":"3 Pheasant Ct East Setauket NY 11733",
    "addr:housenumber":"3",
    "addr:postcode":"11733",
    "addr:street":"Pheasant Ct East",
    "iso:country":"US",
    "sg:address":"3 Pheasant Ct",
    "sg:city":"East Setauket",
    "sg:classifiers":[
        {
            "category":"Building & Trades",
            "subcategory":"Electrical",
            "type":"Services"
        }
    ],
    "sg:phone":"+1 631 473 7756",
    "sg:postcode":"11733",
    "sg:province":"NY",
    "sg:tags":[
        "electrical",
        "contractor"
    ],
    "wof:name":"Service Electrical",
    "wof:placetype":"venue"
},
  "geometry": {"coordinates":[-73.08663,40.926356],"type":"Point"}
}