{
  "type": "Feature",
  "properties": {
    "addr:full":"13 Worth St New York NY 10013",
    "addr:housenumber":"13",
    "addr:postcode":"10013",
    "addr:street":"Worth St",
    "iso:country":"US",
    "sg:address":"13 Worth St",
    "sg:city":"New York",
    "sg:classifiers":[
        {
            "category":"Professional",
            "type":"Services"
        }
    ],
    "sg:phone":"+1 212 226 6480",
    "sg:postcode":"10013",
    "sg:province":"NY",
    "sg:website":"www.pistolstudios.com",
    "wof:name":"Pistol Studio",
    "wof:placetype":"venue"
},
  "geometry": {"coordinates":[-74.008121,40.71791],"type":"Point"}
}