{
  "type": "Feature",
  "properties": {
    "iso:country":"US",
    "sg:address":"RR 25",
    "sg:city":"Centerport",
    "sg:classifiers":[
        {
            "category":"Autos & Motor Vehicles",
            "subcategory":"Fuel & Gas Station",
            "type":"Retail Goods"
        },
        {
            "category":"Retail",
            "subcategory":"Auto Repair",
            "type":"Services"
        }
    ],
    "sg:phone":"+1 631 261 4277",
    "sg:postcode":"11721",
    "sg:province":"NY",
    "wof:name":"Centerport Shell Svce",
    "wof:placetype":"venue"
},
  "geometry": {"coordinates":[-73.374298,40.891399],"type":"Point"}
}