{
  "type": "Feature",
  "properties": {
    "addr:full":"169 Wythe Ave Brooklyn NY 11211",
    "addr:housenumber":"169",
    "addr:postcode":"11211",
    "addr:street":"Wythe Ave",
    "iso:country":"US",
    "sg:address":"169 Wythe Ave",
    "sg:city":"Brooklyn",
    "sg:classifiers":[
        {
            "category":"Personal",
            "type":"Services"
        },
        {
            "category":"Personal",
            "subcategory":"Adult",
            "type":"Services"
        }
    ],
    "sg:phone":"+1 917 538 6560",
    "sg:postcode":"11211",
    "sg:province":"NY",
    "sg:tags":[
        "home",
        "midwife"
    ],
    "wof:name":"Doula Rachel",
    "wof:placetype":"venue"
},
  "geometry": {"coordinates":[-73.961038,40.718655],"type":"Point"}
}