{
  "type": "Feature",
  "properties": {
    "addr:full":"900 Walt Whitman Rd Melville NY 11747",
    "addr:housenumber":"900",
    "addr:postcode":"11747",
    "addr:street":"Walt Whitman Rd",
    "iso:country":"US",
    "sg:address":"900 Walt Whitman Rd",
    "sg:city":"Melville",
    "sg:classifiers":[
        {
            "category":"Education",
            "subcategory":"School",
            "type":"Public Place"
        }
    ],
    "sg:phone":"+1 516 921 2805",
    "sg:postcode":"11747",
    "sg:province":"NY",
    "wof:name":"Princeton Review",
    "wof:placetype":"venue"
},
  "geometry": {"coordinates":[-73.41423899999999,40.795517],"type":"Point"}
}