{
  "type": "Feature",
  "properties": {
    "addr:full":"1975 Eastchester Rd Bronx NY 10461",
    "addr:housenumber":"1975",
    "addr:postcode":"10461",
    "addr:street":"Eastchester Rd",
    "iso:country":"US",
    "sg:address":"1975 Eastchester Rd",
    "sg:city":"Bronx",
    "sg:classifiers":[
        {
            "category":"Education",
            "subcategory":"University",
            "type":"Public Place"
        }
    ],
    "sg:phone":"+1 718 430 7021",
    "sg:postcode":"10461",
    "sg:province":"NY",
    "sg:tags":[
        "college"
    ],
    "wof:name":"Albert Einstein College of Medicine of Yeshiva University",
    "wof:placetype":"venue"
},
  "geometry": {"coordinates":[-73.843433,40.852678],"type":"Point"}
}