{
  "type": "Feature",
  "properties": {
    "addr:full":"1370 E 2nd St Jamestown NY 14701",
    "addr:housenumber":"1370",
    "addr:postcode":"14701",
    "addr:street":"E 2Nd St",
    "iso:country":"US",
    "sg:address":"1370 E 2nd St",
    "sg:city":"Jamestown",
    "sg:classifiers":[
        {
            "category":"Food & Beverages",
            "subcategory":"Liquor & Beverages",
            "type":"Retail Goods"
        }
    ],
    "sg:phone":"+1 716 665 3609",
    "sg:postcode":"14701",
    "sg:province":"NY",
    "sg:tags":[
        "alcoholic"
    ],
    "wof:name":"Bardo's Liquor Store",
    "wof:placetype":"venue"
},
  "geometry": {"coordinates":[-79.210554,42.113272],"type":"Point"}
}