{
  "type": "Feature",
  "properties": {
    "addr:full":"629 Old Rte 146 Clifton Park NY 12065",
    "addr:housenumber":"629",
    "addr:postcode":"12065",
    "addr:street":"Old Rte 146;Park",
    "iso:country":"US",
    "sg:address":"629 Old Rte 146",
    "sg:city":"Clifton Park",
    "sg:classifiers":[
        {
            "category":"Government",
            "subcategory":"Fire Station",
            "type":"Public Place"
        }
    ],
    "sg:phone":"+1 518 877 8100",
    "sg:postcode":"12065",
    "sg:province":"NY",
    "sg:tags":[
        "department"
    ],
    "wof:name":"Jonesville Fire District",
    "wof:placetype":"venue"
},
  "geometry": {"coordinates":[-73.780603,42.863721],"type":"Point"}
}