{
  "type": "Feature",
  "properties": {
    "addr:full":"645 Stewart Ave Garden City NY 11530",
    "addr:housenumber":"645",
    "addr:postcode":"11530",
    "addr:street":"Stewart Ave",
    "iso:country":"US",
    "sg:address":"645 Stewart Ave",
    "sg:city":"Garden City",
    "sg:classifiers":[
        {
            "category":"Communications",
            "subcategory":"Newspaper",
            "type":"Services"
        }
    ],
    "sg:phone":"+1 516 227 1300",
    "sg:postcode":"11530",
    "sg:province":"NY",
    "sg:tags":[
        "print",
        "medium"
    ],
    "wof:name":"Retirement Advisors Inc",
    "wof:placetype":"venue"
},
  "geometry": {"coordinates":[-73.611099,40.731899],"type":"Point"}
}