{
  "type": "Feature",
  "properties": {
    "addr:full":"159 E Houston St New York NY 10002",
    "addr:housenumber":"159",
    "addr:postcode":"10002",
    "addr:street":"E Houston St",
    "iso:country":"US",
    "sg:address":"159 E Houston St",
    "sg:city":"New York",
    "sg:classifiers":[
        {
            "category":"Fast Food",
            "type":"Food & Drink"
        },
        {
            "category":"Arts & Performance",
            "subcategory":"Music",
            "type":"Entertainment"
        }
    ],
    "sg:phone":"+1 212 475 0611",
    "sg:postcode":"10002",
    "sg:province":"NY",
    "sg:tags":[
        "burger",
        "venue"
    ],
    "sg:website":"www.thenationalunderground.com",
    "wof:name":"National Underground",
    "wof:placetype":"venue"
},
  "geometry": {"coordinates":[-73.989169,40.723006],"type":"Point"}
}