{
  "type": "Feature",
  "properties": {
    "addr:full":"505 W 51st St New York NY 10019",
    "addr:housenumber":"505",
    "addr:postcode":"10019",
    "addr:street":"W 51St St",
    "iso:country":"US",
    "sg:address":"505 W 51st St",
    "sg:city":"New York",
    "sg:classifiers":[
        {
            "category":"Retail",
            "subcategory":"Auto Repair",
            "type":"Services"
        }
    ],
    "sg:phone":"+1 212 246 7877",
    "sg:postcode":"10019",
    "sg:province":"NY",
    "sg:tags":[
        "repairing",
        "automobile",
        "radiator"
    ],
    "wof:name":"Dave's Auto Radiator Wks",
    "wof:placetype":"venue"
},
  "geometry": {"coordinates":[-73.992401,40.765598],"type":"Point"}
}