{
  "type": "Feature",
  "properties": {
    "addr:full":"113A Division St Manhattan NY 10002",
    "addr:housenumber":"113a",
    "addr:postcode":"10002",
    "addr:street":"Division St",
    "iso:country":"US",
    "sg:address":"113A Division St",
    "sg:city":"Manhattan",
    "sg:classifiers":[
        {
            "category":"Shopping",
            "subcategory":"Crafts & Fabrics",
            "type":"Retail Goods"
        }
    ],
    "sg:postcode":"10002",
    "sg:province":"NY",
    "sg:tags":[
        "store"
    ],
    "wof:name":"Chuen Lee Fabrics",
    "wof:placetype":"venue"
},
  "geometry": {"coordinates":[-73.992166,40.714402],"type":"Point"}
}