{
  "type": "Feature",
  "properties": {
    "iso:country":"US",
    "sg:address":"13350 Whitestone Expy",
    "sg:city":"Flushing",
    "sg:classifiers":[
        {
            "category":"Building & Trades",
            "subcategory":"Plumbing",
            "type":"Services"
        }
    ],
    "sg:phone":"+1 347 542 5230",
    "sg:postcode":"11354",
    "sg:province":"NY",
    "sg:website":"willplumbingandheating.info/",
    "wof:name":"Will Plumbing and Heating",
    "wof:placetype":"venue"
},
  "geometry": {"coordinates":[-73.835784,40.768828],"type":"Point"}
}