{
  "type": "Feature",
  "properties": {
    "iso:country":"US",
    "sg:address":"28 Charles Colman Blvd",
    "sg:city":"Pawling",
    "sg:classifiers":[
        {
            "category":"Shopping",
            "subcategory":"Florist",
            "type":"Retail Goods"
        }
    ],
    "sg:phone":"+1   ",
    "sg:postcode":"12564",
    "sg:province":"NY",
    "wof:name":"Annex Florist",
    "wof:placetype":"venue"
},
  "geometry": {"coordinates":[-73.601331,41.563496],"type":"Point"}
}