{
  "type": "Feature",
  "properties": {
    "addr:full":"383 Bradford Ave Staten Island NY 10309",
    "addr:housenumber":"383",
    "addr:postcode":"10309",
    "addr:street":"Bradford Ave",
    "iso:country":"US",
    "sg:address":"383 Bradford Ave",
    "sg:city":"Staten Island",
    "sg:classifiers":[
        {
            "category":"Building & Trades",
            "subcategory":"Construction",
            "type":"Services"
        }
    ],
    "sg:phone":"+1 718 948 2596",
    "sg:postcode":"10309",
    "sg:province":"NY",
    "sg:tags":[
        "contractor"
    ],
    "wof:name":"Sarcona Masonry Contractors",
    "wof:placetype":"venue"
},
  "geometry": {"coordinates":[-74.206256,40.5302],"type":"Point"}
}