{
  "type": "Feature",
  "properties": {
    "iso:country":"US",
    "sg:address":"570 Klem Rd",
    "sg:city":"Webster",
    "sg:classifiers":[
        {
            "category":"Education",
            "subcategory":"School",
            "type":"Public Place"
        }
    ],
    "sg:phone":"+1 585 671 6757",
    "sg:postcode":"14580",
    "sg:province":"NY",
    "wof:name":"Woodside Nursery School",
    "wof:placetype":"venue"
},
  "geometry": {"coordinates":[-77.499043,43.231089],"type":"Point"}
}