{
  "type": "Feature",
  "properties": {
    "iso:country":"US",
    "sg:address":"2435 Genesee St",
    "sg:city":"Cheektowaga",
    "sg:classifiers":[
        {
            "category":"Government",
            "subcategory":"Fire Station",
            "type":"Public Place"
        }
    ],
    "sg:phone":"+1 716 896 8690",
    "sg:postcode":"14225",
    "sg:province":"NY",
    "sg:tags":[
        "department"
    ],
    "wof:name":"Pine Hill Hose Co",
    "wof:placetype":"venue"
},
  "geometry": {"coordinates":[-78.793235,42.919816],"type":"Point"}
}