{
  "type": "Feature",
  "properties": {
    "iso:country":"US",
    "sg:address":"829 Horton Brook Rd",
    "sg:city":"Roscoe",
    "sg:classifiers":[
        {
            "category":"Travel",
            "subcategory":"Hotels & Motels",
            "type":"Entertainment"
        }
    ],
    "sg:phone":"+1 607 498 4212",
    "sg:postcode":"12776",
    "sg:province":"NY",
    "sg:tags":[
        "resort"
    ],
    "wof:name":"Merrill's Farm",
    "wof:placetype":"venue"
},
  "geometry": {"coordinates":[-74.991221,42.004765],"type":"Point"}
}