{
  "type": "Feature",
  "properties": {
    "addr:full":"1624 New York Ave Huntington Station NY 11746",
    "addr:housenumber":"1624",
    "addr:postcode":"11746",
    "addr:street":"New York Ave Huntington",
    "iso:country":"US",
    "sg:address":"1624 New York Ave",
    "sg:city":"Huntington Station",
    "sg:classifiers":[
        {
            "category":"Restaurant",
            "type":"Food & Drink"
        }
    ],
    "sg:phone":"+1 631 351 9797",
    "sg:postcode":"11746",
    "sg:province":"NY",
    "wof:name":"J & J Southside Restaurant",
    "wof:placetype":"venue"
},
  "geometry": {"coordinates":[-73.412498,40.838299],"type":"Point"}
}