{
  "type": "Feature",
  "properties": {
    "addr:full":"210 W. 70th St. Suite 1 New York NY 10023",
    "addr:housenumber":"210",
    "addr:postcode":"10023",
    "addr:street":"W. 70Th St. Suite 1",
    "iso:country":"US",
    "sg:address":"210 W. 70th St. Suite 1",
    "sg:city":"New York",
    "sg:classifiers":[
        {
            "category":"Health Services",
            "subcategory":"Health Practitioner",
            "type":"Services"
        }
    ],
    "sg:phone":"+1 212 874 9467",
    "sg:postcode":"10023",
    "sg:province":"NY",
    "sg:tags":[
        "nutritionist"
    ],
    "wof:name":"Baum Nutrition",
    "wof:placetype":"venue"
},
  "geometry": {"coordinates":[-73.983497,40.77744],"type":"Point"}
}