{
  "type": "Feature",
  "properties": {
    "addr:full":"11995 W Main St Wolcott NY 14590",
    "addr:housenumber":"11995",
    "addr:postcode":"14590",
    "addr:street":"W Main St",
    "iso:country":"US",
    "sg:address":"11995 W Main St",
    "sg:city":"Wolcott",
    "sg:classifiers":[
        {
            "category":"Autos & Motor Vehicles",
            "subcategory":"Fuel & Gas Station",
            "type":"Retail Goods"
        }
    ],
    "sg:phone":"+1   ",
    "sg:postcode":"14590",
    "sg:province":"NY",
    "sg:tags":[
        "grocery",
        "station",
        "gasoline"
    ],
    "wof:name":"Kwik - Fill",
    "wof:placetype":"venue"
},
  "geometry": {"coordinates":[-76.817714,43.22157],"type":"Point"}
}