{
  "type": "Feature",
  "properties": {
    "addr:full":"829 Sunrise Mall Massapequa NY 11758",
    "addr:housenumber":"829",
    "addr:postcode":"11758",
    "addr:street":"Sunrise Mall",
    "iso:country":"US",
    "sg:address":"829 Sunrise Mall",
    "sg:city":"Massapequa",
    "sg:classifiers":[
        {
            "category":"Wholesale",
            "subcategory":"Electrical",
            "type":"Manufacturing & Wholesale Goods"
        }
    ],
    "sg:phone":"+1 516 797 3326",
    "sg:postcode":"11758",
    "sg:province":"NY",
    "sg:tags":[
        "equipment",
        "electronic",
        "supply"
    ],
    "wof:name":"Jmd International",
    "wof:placetype":"venue"
},
  "geometry": {"coordinates":[-73.434382,40.685485],"type":"Point"}
}