{
  "type": "Feature",
  "properties": {
    "iso:country":"US",
    "sg:address":"934 Wenwood Dr",
    "sg:city":"Bellmore",
    "sg:classifiers":[
        {
            "category":"Shopping",
            "subcategory":"Clothing, Apparel, & Fashions",
            "type":"Retail Goods"
        }
    ],
    "sg:phone":"+1   ",
    "sg:postcode":"11710",
    "sg:province":"NY",
    "wof:name":"Edward & Lisa Hilfer",
    "wof:placetype":"venue"
},
  "geometry": {"coordinates":[-73.539464,40.698964],"type":"Point"}
}