{
  "type": "Feature",
  "properties": {
    "addr:full":"102 10th St Hicksville NY 11801",
    "addr:housenumber":"102",
    "addr:postcode":"11801",
    "addr:street":"10Th St",
    "iso:country":"US",
    "sg:address":"102 10th St",
    "sg:city":"Hicksville",
    "sg:classifiers":[
        {
            "category":"Manufacturing",
            "subcategory":"Printing",
            "type":"Manufacturing & Wholesale Goods"
        }
    ],
    "sg:phone":"+1   ",
    "sg:postcode":"11801",
    "sg:province":"NY",
    "sg:tags":[
        "publishing"
    ],
    "wof:name":"Kbi Music LLC",
    "wof:placetype":"venue"
},
  "geometry": {"coordinates":[-73.516953,40.756717],"type":"Point"}
}