{
  "type": "Feature",
  "properties": {
    "iso:country":"US",
    "sg:address":"34 W 32 St",
    "sg:city":"New York",
    "sg:classifiers":[
        {
            "category":"Manufacturing",
            "subcategory":"Apparel",
            "type":"Manufacturing & Wholesale Goods"
        }
    ],
    "sg:phone":"+1 212 685 5544",
    "sg:postcode":"10001",
    "sg:province":"NY",
    "sg:tags":[
        "fur"
    ],
    "wof:name":"Medina Niassene Inc",
    "wof:placetype":"venue"
},
  "geometry": {"coordinates":[-73.986914,40.747496],"type":"Point"}
}