{
  "type": "Feature",
  "properties": {
    "addr:full":"655 3 Ave New York NY 10017",
    "addr:housenumber":"655",
    "addr:postcode":"10017",
    "addr:street":"3 Ave",
    "iso:country":"US",
    "sg:address":"655 3 Ave",
    "sg:city":"New York",
    "sg:classifiers":[
        {
            "category":"Shopping",
            "subcategory":"Computers & Home Electronics",
            "type":"Retail Goods"
        }
    ],
    "sg:phone":"+1 212 682 7411",
    "sg:postcode":"10017",
    "sg:province":"NY",
    "sg:tags":[
        "software"
    ],
    "wof:name":"Logica Inc",
    "wof:placetype":"venue"
},
  "geometry": {"coordinates":[-73.974935,40.7501],"type":"Point"}
}