{
  "type": "Feature",
  "properties": {
    "iso:country":"US",
    "sg:address":"3240 Lawrence Ave",
    "sg:city":"Oceanside",
    "sg:classifiers":[
        {
            "category":"Freight",
            "type":"Transportation"
        }
    ],
    "sg:phone":"+1   ",
    "sg:postcode":"11572",
    "sg:province":"NY",
    "sg:tags":[
        "heavy",
        "moving",
        "machinery"
    ],
    "wof:name":"Jack Pedowitz Enterprises",
    "wof:placetype":"venue"
},
  "geometry": {"coordinates":[-73.641817,40.632449],"type":"Point"}
}