{
  "type": "Feature",
  "properties": {
    "addr:full":"20 Marlboro Rd Valley Stream NY 11581",
    "addr:housenumber":"20",
    "addr:postcode":"11581",
    "addr:street":"Marlboro Rd",
    "iso:country":"US",
    "sg:address":"20 Marlboro Rd",
    "sg:city":"Valley Stream",
    "sg:classifiers":[
        {
            "category":"Professional",
            "subcategory":"Computer Services",
            "type":"Services"
        }
    ],
    "sg:phone":"+1 516 792 9459",
    "sg:postcode":"11581",
    "sg:province":"NY",
    "sg:tags":[
        "repair"
    ],
    "wof:name":"Rapid Computer Repr Inc",
    "wof:placetype":"venue"
},
  "geometry": {"coordinates":[-73.699586,40.649372],"type":"Point"}
}