{
  "type": "Feature",
  "properties": {
    "addr:full":"336 Electronics Pkwy Liverpool NY 13088",
    "addr:housenumber":"336",
    "addr:postcode":"13088",
    "addr:street":"Electronics Pkwy",
    "iso:country":"US",
    "sg:address":"336 Electronics Pkwy",
    "sg:city":"Liverpool",
    "sg:classifiers":[
        {
            "category":"Social Services",
            "subcategory":"Child Care",
            "type":"Services"
        }
    ],
    "sg:phone":"+1   ",
    "sg:postcode":"13088",
    "sg:province":"NY",
    "sg:tags":[
        "day"
    ],
    "wof:name":"Home Away From Home",
    "wof:placetype":"venue"
},
  "geometry": {"coordinates":[-76.19212400000001,43.0978],"type":"Point"}
}