{
  "type": "Feature",
  "properties": {
    "addr:full":"148 Mercer St New York NY 10012",
    "addr:housenumber":"148",
    "addr:postcode":"10012",
    "addr:street":"Mercer St",
    "iso:country":"US",
    "sg:address":"148 Mercer St",
    "sg:city":"New York",
    "sg:classifiers":[
        {
            "category":"Professional",
            "subcategory":"Management & Consulting",
            "type":"Services"
        }
    ],
    "sg:phone":"+1 212 966 9438",
    "sg:postcode":"10012",
    "sg:province":"NY",
    "sg:tags":[
        "consultant",
        "lighting"
    ],
    "wof:name":"Arc Light & Sound",
    "wof:placetype":"venue"
},
  "geometry": {"coordinates":[-73.997711,40.725498],"type":"Point"}
}