{
  "type": "Feature",
  "properties": {
    "addr:full":"227 Centre St New York NY 10013",
    "addr:housenumber":"227",
    "addr:postcode":"10013",
    "addr:street":"Centre St",
    "iso:country":"US",
    "sg:address":"227 Centre St",
    "sg:city":"New York",
    "sg:classifiers":[
        {
            "category":"Restaurant",
            "type":"Food & Drink"
        }
    ],
    "sg:phone":"+1 212 966 7886",
    "sg:postcode":"10013",
    "sg:province":"NY",
    "sg:tags":[
        "thai"
    ],
    "wof:name":"Saha Thai Cuisine",
    "wof:placetype":"venue"
},
  "geometry": {"coordinates":[-73.99852199999999,40.719801],"type":"Point"}
}