{
  "type": "Feature",
  "properties": {
    "iso:country":"US",
    "sg:address":"70 Charles Lindbergh Blvd",
    "sg:city":"Uniondale",
    "sg:classifiers":[
        {
            "category":"Wholesale",
            "subcategory":"Durable Goods & Equipment",
            "type":"Manufacturing & Wholesale Goods"
        }
    ],
    "sg:phone":"+1 516 542 5825",
    "sg:postcode":"11553",
    "sg:province":"NY",
    "sg:tags":[
        "importer"
    ],
    "wof:name":"Premium Import Co",
    "wof:placetype":"venue"
},
  "geometry": {"coordinates":[-73.604753,40.726223],"type":"Point"}
}