{
  "type": "Feature",
  "properties": {
    "iso:country":"US",
    "sg:address":"477 83rd St",
    "sg:city":"Brooklyn",
    "sg:classifiers":[
        {
            "category":"Personal",
            "subcategory":"Beauty Salon",
            "type":"Services"
        },
        {
            "category":"Personal",
            "subcategory":"Barber",
            "type":"Services"
        }
    ],
    "sg:phone":"+1 718 748 4933",
    "sg:postcode":"11209",
    "sg:province":"NY",
    "sg:tags":[
        "hair"
    ],
    "wof:name":"George's Salon & Barbershop",
    "wof:placetype":"venue"
},
  "geometry": {"coordinates":[-74.025418,40.623928],"type":"Point"}
}