{
  "type": "Feature",
  "properties": {
    "addr:full":"185 Glenerie Blvd Saugerties NY 12477",
    "addr:housenumber":"185",
    "addr:postcode":"12477",
    "addr:street":"Glenerie Blvd",
    "iso:country":"US",
    "sg:address":"185 Glenerie Blvd",
    "sg:city":"Saugerties",
    "sg:classifiers":[
        {
            "category":"Social Services",
            "subcategory":"Child Care",
            "type":"Services"
        }
    ],
    "sg:phone":"+1 845 336 5843",
    "sg:postcode":"12477",
    "sg:province":"NY",
    "sg:tags":[
        "day"
    ],
    "wof:name":"Options Early Childhood Center",
    "wof:placetype":"venue"
},
  "geometry": {"coordinates":[-73.98801,42.015421],"type":"Point"}
}