{
  "type": "Feature",
  "properties": {
    "addr:full":"303 E 81st St New York NY 10028",
    "addr:housenumber":"303",
    "addr:postcode":"10028",
    "addr:street":"E 81St St",
    "iso:country":"US",
    "sg:address":"303 E 81st St",
    "sg:city":"New York",
    "sg:classifiers":[
        {
            "category":"Professional",
            "subcategory":"Management & Consulting",
            "type":"Services"
        }
    ],
    "sg:phone":"+1   ",
    "sg:postcode":"10028",
    "sg:province":"NY",
    "sg:tags":[
        "business"
    ],
    "wof:name":"Bass Consulting Inc",
    "wof:placetype":"venue"
},
  "geometry": {"coordinates":[-73.951723,40.773743],"type":"Point"}
}