{
  "type": "Feature",
  "properties": {
    "iso:country":"US",
    "sg:address":"241 N Pearl St",
    "sg:city":"Albany",
    "sg:classifiers":[
        {
            "category":"Building & Trades",
            "subcategory":"Construction",
            "type":"Services"
        }
    ],
    "sg:phone":"+1 518 463 6985",
    "sg:postcode":"12207",
    "sg:province":"NY",
    "sg:tags":[
        "excavating",
        "contractor"
    ],
    "wof:name":"Cristo Demolition Inc",
    "wof:placetype":"venue"
},
  "geometry": {"coordinates":[-73.749583,42.656277],"type":"Point"}
}