{
  "type": "Feature",
  "properties": {
    "iso:country":"US",
    "sg:address":"730 Bay Ridge Ave",
    "sg:city":"Brooklyn",
    "sg:classifiers":[
        {
            "category":"Building & Trades",
            "subcategory":"Electrical",
            "type":"Services"
        }
    ],
    "sg:phone":"+1 718 238 8841",
    "sg:postcode":"11220",
    "sg:province":"NY",
    "sg:tags":[
        "electrician",
        "contractor"
    ],
    "wof:name":"Mac Electrical",
    "wof:placetype":"venue"
},
  "geometry": {"coordinates":[-74.0158,40.630798],"type":"Point"}
}