{
  "type": "Feature",
  "properties": {
    "addr:full":"417 92nd St Brooklyn NY 11209",
    "addr:housenumber":"417",
    "addr:postcode":"11209",
    "addr:street":"92Nd St",
    "iso:country":"US",
    "sg:address":"417 92nd St",
    "sg:city":"Brooklyn",
    "sg:classifiers":[
        {
            "category":"Personal",
            "subcategory":"Beauty Salon",
            "type":"Services"
        }
    ],
    "sg:phone":"+1 718 680 8288",
    "sg:postcode":"11209",
    "sg:province":"NY",
    "sg:tags":[
        "shop"
    ],
    "wof:name":"Gold Star Hair Styles",
    "wof:placetype":"venue"
},
  "geometry": {"coordinates":[-74.02936800000001,40.61803],"type":"Point"}
}