{
  "type": "Feature",
  "properties": {
    "addr:full":"148 Woodhull Ave Riverhead NY 11901",
    "addr:housenumber":"148",
    "addr:postcode":"11901",
    "addr:street":"Woodhull Ave",
    "iso:country":"US",
    "sg:address":"148 Woodhull Ave",
    "sg:city":"Riverhead",
    "sg:classifiers":[
        {
            "category":"Building & Trades",
            "subcategory":"Plumbing",
            "type":"Services"
        }
    ],
    "sg:phone":"+1 631 727 2869",
    "sg:postcode":"11901",
    "sg:province":"NY",
    "sg:tags":[
        "contractor"
    ],
    "wof:name":"B H Mapes & Son Inc",
    "wof:placetype":"venue"
},
  "geometry": {"coordinates":[-72.664652,40.913775],"type":"Point"}
}