{
  "type": "Feature",
  "properties": {
    "iso:country":"US",
    "sg:address":"132 Magee St",
    "sg:city":"Southampton",
    "sg:classifiers":[
        {
            "category":"Building & Trades",
            "subcategory":"Construction",
            "type":"Services"
        }
    ],
    "sg:phone":"+1 631 287 0580",
    "sg:postcode":"11968",
    "sg:province":"NY",
    "sg:tags":[
        "excavating",
        "contractor"
    ],
    "wof:name":"J & B Trenching",
    "wof:placetype":"venue"
},
  "geometry": {"coordinates":[-72.415492,40.888959],"type":"Point"}
}