{
  "type": "Feature",
  "properties": {
    "iso:country":"US",
    "sg:address":"6 Henry St",
    "sg:city":"Commack",
    "sg:classifiers":[
        {
            "category":"Home & Garden",
            "subcategory":"Home Furnishings",
            "type":"Retail Goods"
        },
        {
            "category":"Home & Garden",
            "subcategory":"Kitchen Supply",
            "type":"Retail Goods"
        },
        {
            "category":"Home & Garden",
            "subcategory":"Furniture",
            "type":"Retail Goods"
        }
    ],
    "sg:phone":"+1 631 462 9605",
    "sg:postcode":"11725",
    "sg:province":"NY",
    "sg:tags":[
        "decor",
        "house",
        "bedding",
        "accessory",
        "housewares",
        "store"
    ],
    "sg:website":"http://www.homegoods.com",
    "wof:name":"HomeGoods",
    "wof:placetype":"venue"
},
  "geometry": {"coordinates":[-73.293797,40.808483],"type":"Point"}
}