{
  "type": "Feature",
  "properties": {
    "iso:country":"US",
    "sg:address":"577 Malvin Mall",
    "sg:city":"Cedarhurst",
    "sg:classifiers":[
        {
            "category":"Shopping",
            "subcategory":"Crafts & Fabrics",
            "type":"Retail Goods"
        }
    ],
    "sg:phone":"+1 516 596 7506",
    "sg:postcode":"11516",
    "sg:province":"NY",
    "sg:tags":[
        "store"
    ],
    "wof:name":"Racheal Fabric & Trim",
    "wof:placetype":"venue"
},
  "geometry": {"coordinates":[-73.72256400000001,40.623398],"type":"Point"}
}