{
  "type": "Feature",
  "properties": {
    "addr:full":"45 E Market St Rhinebeck NY 12572",
    "addr:housenumber":"45",
    "addr:postcode":"12572",
    "addr:street":"E Market St",
    "iso:country":"US",
    "sg:address":"45 E Market St",
    "sg:city":"Rhinebeck",
    "sg:classifiers":[
        {
            "category":"Shopping",
            "subcategory":"Florist",
            "type":"Retail Goods"
        }
    ],
    "sg:phone":"+1   ",
    "sg:postcode":"12572",
    "sg:province":"NY",
    "wof:name":"Gifted Nest",
    "wof:placetype":"venue"
},
  "geometry": {"coordinates":[-73.91119399999999,41.92703],"type":"Point"}
}