{
  "type": "Feature",
  "properties": {
    "addr:full":"718 Linden Blvd Brooklyn NY 11203",
    "addr:housenumber":"718",
    "addr:postcode":"11203",
    "addr:street":"Linden Blvd",
    "iso:country":"US",
    "sg:address":"718 Linden Blvd",
    "sg:city":"Brooklyn",
    "sg:classifiers":[
        {
            "category":"Health Services",
            "subcategory":"Doctor",
            "type":"Services"
        }
    ],
    "sg:phone":"+1 718 856 4098",
    "sg:postcode":"11203",
    "sg:province":"NY",
    "wof:name":"Rao R MD",
    "wof:placetype":"venue"
},
  "geometry": {"coordinates":[-73.931702,40.653599],"type":"Point"}
}