{
  "type": "Feature",
  "properties": {
    "iso:country":"US",
    "sg:address":"5300 North St",
    "sg:city":"Canandaigua",
    "sg:classifiers":[
        {
            "category":"Manufacturing",
            "subcategory":"Tools & Machinery",
            "type":"Manufacturing & Wholesale Goods"
        }
    ],
    "sg:phone":"+1 585 394 8731",
    "sg:postcode":"14424",
    "sg:province":"NY",
    "wof:name":"Compro Tool & Precision Mach",
    "wof:placetype":"venue"
},
  "geometry": {"coordinates":[-77.30143700000001,42.901773],"type":"Point"}
}