{
  "type": "Feature",
  "properties": {
    "addr:full":"8 Ott St Bethpage NY 11714",
    "addr:housenumber":"8",
    "addr:postcode":"11714",
    "addr:street":"Ott St",
    "iso:country":"US",
    "sg:address":"8 Ott St",
    "sg:city":"Bethpage",
    "sg:classifiers":[
        {
            "category":"Building & Trades",
            "subcategory":"Construction",
            "type":"Services"
        }
    ],
    "sg:phone":"+1 516 433 1564",
    "sg:postcode":"11714",
    "sg:province":"NY",
    "sg:tags":[
        "house"
    ],
    "wof:name":"Sema Homes Inc",
    "wof:placetype":"venue"
},
  "geometry": {"coordinates":[-73.476411,40.743738],"type":"Point"}
}