{
  "type": "Feature",
  "properties": {
    "addr:full":"6137 Eckhardt Rd Lake View NY 14085",
    "addr:housenumber":"6137",
    "addr:postcode":"14085",
    "addr:street":"Eckhardt Rd",
    "iso:country":"US",
    "sg:address":"6137 Eckhardt Rd",
    "sg:city":"Lake View",
    "sg:classifiers":[
        {
            "category":"Freight",
            "type":"Transportation"
        }
    ],
    "sg:phone":"+1   ",
    "sg:postcode":"14085",
    "sg:province":"NY",
    "wof:name":"Sgt Transport",
    "wof:placetype":"venue"
},
  "geometry": {"coordinates":[-78.95630800000001,42.718223],"type":"Point"}
}