{
  "type": "Feature",
  "properties": {
    "addr:full":"2134 Frederick Douglass Blvd New York NY 10026",
    "addr:housenumber":"2134",
    "addr:postcode":"10026",
    "addr:street":"Frederick Douglass Blvd",
    "iso:country":"US",
    "sg:address":"2134 Frederick Douglass Blvd",
    "sg:city":"New York",
    "sg:classifiers":[
        {
            "category":"Local Transit",
            "type":"Transportation"
        }
    ],
    "sg:phone":"+1   ",
    "sg:postcode":"10026",
    "sg:province":"NY",
    "sg:tags":[
        "passenger"
    ],
    "wof:name":"New Harlem Car Service Inc",
    "wof:placetype":"venue"
},
  "geometry": {"coordinates":[-73.95538500000001,40.804233],"type":"Point"}
}