{
  "type": "Feature",
  "properties": {
    "addr:full":"141 Orchard Creek Cir Rochester NY 14612",
    "addr:housenumber":"141",
    "addr:postcode":"14612",
    "addr:street":"Orchard Creek Cir",
    "iso:country":"US",
    "sg:address":"141 Orchard Creek Cir",
    "sg:city":"Rochester",
    "sg:classifiers":[
        {
            "category":"Cinema",
            "subcategory":"Movie Rental",
            "type":"Entertainment"
        }
    ],
    "sg:phone":"+1 585 621 3086",
    "sg:postcode":"14612",
    "sg:province":"NY",
    "sg:tags":[
        "motion",
        "picture",
        "distributor",
        "film",
        "exchange"
    ],
    "wof:name":"Ldc Productions",
    "wof:placetype":"venue"
},
  "geometry": {"coordinates":[-77.684974,43.240429],"type":"Point"}
}