{
  "type": "Feature",
  "properties": {
    "iso:country":"US",
    "sg:address":"19 N Ellicott St",
    "sg:city":"Williamsville",
    "sg:classifiers":[
        {
            "category":"Professional",
            "subcategory":"Engineering",
            "type":"Services"
        }
    ],
    "sg:phone":"+1 716 632 7000",
    "sg:postcode":"14221",
    "sg:province":"NY",
    "sg:tags":[
        "engineer"
    ],
    "wof:name":"Bissell Stone Assoc",
    "wof:placetype":"venue"
},
  "geometry": {"coordinates":[-78.739976,42.963718],"type":"Point"}
}