{
  "type": "Feature",
  "properties": {
    "addr:full":"446 5th Ave Pelham NY 10803",
    "addr:housenumber":"446",
    "addr:postcode":"10803",
    "addr:street":"5Th Ave",
    "iso:country":"US",
    "sg:address":"446 5th Ave",
    "sg:city":"Pelham",
    "sg:classifiers":[
        {
            "category":"Manufacturing",
            "subcategory":"Metals",
            "type":"Manufacturing & Wholesale Goods"
        }
    ],
    "sg:phone":"+1   ",
    "sg:postcode":"10803",
    "sg:province":"NY",
    "wof:name":"Metal Man Restoration LLC",
    "wof:placetype":"venue"
},
  "geometry": {"coordinates":[-73.80720599999999,40.916075],"type":"Point"}
}