{
  "type": "Feature",
  "properties": {
    "addr:full":"14 Valewood Dr New Windsor NY 12553",
    "addr:housenumber":"14",
    "addr:postcode":"12553",
    "addr:street":"Valewood Dr",
    "iso:country":"US",
    "sg:address":"14 Valewood Dr",
    "sg:city":"New Windsor",
    "sg:classifiers":[
        {
            "category":"Autos & Motor Vehicles",
            "subcategory":"Automobile Sales",
            "type":"Retail Goods"
        }
    ],
    "sg:phone":"+1   ",
    "sg:postcode":"12553",
    "sg:province":"NY",
    "sg:tags":[
        "used"
    ],
    "wof:name":"Mijans Auto",
    "wof:placetype":"venue"
},
  "geometry": {"coordinates":[-74.03760200000001,41.470618],"type":"Point"}
}