{
  "type": "Feature",
  "properties": {
    "addr:full":"3777 Independence Ave Bronx NY 10463",
    "addr:housenumber":"3777",
    "addr:postcode":"10463",
    "addr:street":"Independence Ave",
    "iso:country":"US",
    "sg:address":"3777 Independence Ave",
    "sg:city":"Bronx",
    "sg:classifiers":[
        {
            "category":"Real Estate",
            "subcategory":"Real Estate Operator",
            "type":"Services"
        }
    ],
    "sg:phone":"+1 718 549 2036",
    "sg:postcode":"10463",
    "sg:province":"NY",
    "sg:tags":[
        "apartment"
    ],
    "wof:name":"Hudson Towers",
    "wof:placetype":"venue"
},
  "geometry": {"coordinates":[-73.91311399999999,40.888745],"type":"Point"}
}