{
  "type": "Feature",
  "properties": {
    "iso:country":"US",
    "sg:address":"870 Violet Ave.",
    "sg:city":"Hyde Park",
    "sg:classifiers":[
        {
            "category":"Restaurant",
            "type":"Food & Drink"
        }
    ],
    "sg:menulink":"http://www.allmenus.com/ny/hyde-park/279102-angelinas-pizza/menu/",
    "sg:phone":"+1 845 229 5200",
    "sg:postcode":"12538",
    "sg:province":"NY",
    "sg:tags":[
        "pasta",
        "american",
        "salad",
        "pizza"
    ],
    "wof:name":"Angelinas Pizza",
    "wof:placetype":"venue"
},
  "geometry": {"coordinates":[-73.909494,41.772014],"type":"Point"}
}