{
  "type": "Feature",
  "properties": {
    "iso:country":"US",
    "sg:address":"967 Centennial Ave",
    "sg:city":"Baldwin",
    "sg:classifiers":[
        {
            "category":"Shopping",
            "subcategory":"Computers & Home Electronics",
            "type":"Retail Goods"
        }
    ],
    "sg:phone":"+1   ",
    "sg:postcode":"11510",
    "sg:province":"NY",
    "wof:name":"Boot Computer",
    "wof:placetype":"venue"
},
  "geometry": {"coordinates":[-73.604024,40.675537],"type":"Point"}
}