{
  "type": "Feature",
  "properties": {
    "iso:country":"US",
    "sg:address":"1371 Church St",
    "sg:city":"Bohemia",
    "sg:classifiers":[
        {
            "category":"Shopping",
            "subcategory":"Clothing, Apparel, & Fashions",
            "type":"Retail Goods"
        }
    ],
    "sg:phone":"+1 631 472 0668",
    "sg:postcode":"11716",
    "sg:province":"NY",
    "sg:tags":[
        "garment"
    ],
    "wof:name":"Competitive Apparel",
    "wof:placetype":"venue"
},
  "geometry": {"coordinates":[-73.08622099999999,40.770506],"type":"Point"}
}