{
  "type": "Feature",
  "properties": {
    "addr:full":"65 Tillary St Brooklyn NY 11201",
    "addr:housenumber":"65",
    "addr:postcode":"11201",
    "addr:street":"Tillary St",
    "iso:country":"US",
    "sg:address":"65 Tillary St",
    "sg:city":"Brooklyn",
    "sg:classifiers":[
        {
            "category":"Retail",
            "subcategory":"Laundry & Dry Cleaning",
            "type":"Services"
        }
    ],
    "sg:phone":"+1 718 624 3645",
    "sg:postcode":"11201",
    "sg:province":"NY",
    "wof:name":"Concord Cleanrs & Lnderers",
    "wof:placetype":"venue"
},
  "geometry": {"coordinates":[-73.98840300000001,40.6964],"type":"Point"}
}