{
  "type": "Feature",
  "properties": {
    "addr:full":"3920 9th Avenue Brooklyn NY 11232",
    "addr:housenumber":"3920",
    "addr:postcode":"11232",
    "addr:street":"9Th Avenue",
    "iso:country":"US",
    "sg:address":"3920 9th Avenue",
    "sg:city":"Brooklyn",
    "sg:classifiers":[
        {
            "category":"Restaurant",
            "type":"Food & Drink"
        }
    ],
    "sg:phone":"+1 718 854 1116",
    "sg:postcode":"11232",
    "sg:province":"NY",
    "sg:tags":[
        "chinese"
    ],
    "wof:name":"Rose Garden Chinese Restaurant",
    "wof:placetype":"venue"
},
  "geometry": {"coordinates":[-73.99565699999999,40.645572],"type":"Point"}
}