{
  "type": "Feature",
  "properties": {
    "iso:country":"US",
    "sg:address":"7023 20th Ave",
    "sg:city":"Brooklyn",
    "sg:classifiers":[
        {
            "category":"Restaurant",
            "type":"Food & Drink"
        }
    ],
    "sg:phone":"+1 718 256 1293",
    "sg:postcode":"11204",
    "sg:province":"NY",
    "sg:tags":[
        "traditional",
        "american"
    ],
    "wof:name":"Brunch Box",
    "wof:placetype":"venue"
},
  "geometry": {"coordinates":[-73.988947,40.613553],"type":"Point"}
}