{
  "type": "Feature",
  "properties": {
    "iso:country":"US",
    "sg:address":"200 N Prospect St",
    "sg:city":"Herkimer",
    "sg:classifiers":[
        {
            "category":"Organizations",
            "subcategory":"Religious Organization",
            "type":"Services"
        }
    ],
    "sg:phone":"+1 315 866 9641",
    "sg:postcode":"13350",
    "sg:province":"NY",
    "sg:tags":[
        "clergy"
    ],
    "wof:name":"Alfred A Lamanna",
    "wof:placetype":"venue"
},
  "geometry": {"coordinates":[-74.989654,43.027059],"type":"Point"}
}