{
  "type": "Feature",
  "properties": {
    "addr:full":"6375 Furnace Rd Ontario NY 14519",
    "addr:housenumber":"6375",
    "addr:postcode":"14519",
    "addr:street":"Furnace Rd",
    "iso:country":"US",
    "sg:address":"6375 Furnace Rd",
    "sg:city":"Ontario",
    "sg:classifiers":[
        {
            "category":"Retail",
            "subcategory":"Auto Repair",
            "type":"Services"
        }
    ],
    "sg:phone":"+1 315 524 4205",
    "sg:postcode":"14519",
    "sg:province":"NY",
    "sg:tags":[
        "automobile",
        "customizing"
    ],
    "wof:name":"Evolution Customs",
    "wof:placetype":"venue"
},
  "geometry": {"coordinates":[-77.278143,43.230694],"type":"Point"}
}