{
  "type": "Feature",
  "properties": {
    "addr:full":"30 W 57th St New York NY 10019",
    "addr:housenumber":"30",
    "addr:postcode":"10019",
    "addr:street":"W 57Th St",
    "iso:country":"US",
    "sg:address":"30 W 57th St",
    "sg:city":"New York",
    "sg:classifiers":[
        {
            "category":"Shopping",
            "subcategory":"Books",
            "type":"Retail Goods"
        }
    ],
    "sg:phone":"+1 212 541 4860",
    "sg:postcode":"10019",
    "sg:province":"NY",
    "sg:tags":[
        "bookstore"
    ],
    "sg:website":"www.bartfield.com",
    "wof:name":"J.N. Bartfield Fine & Rare Books",
    "wof:placetype":"venue"
},
  "geometry": {"coordinates":[-73.97575399999999,40.7637],"type":"Point"}
}