{
  "type": "Feature",
  "properties": {
    "addr:full":"85 E 4th St Dunkirk NY 14048",
    "addr:housenumber":"85",
    "addr:postcode":"14048",
    "addr:street":"E 4Th St",
    "iso:country":"US",
    "sg:address":"85 E 4th St",
    "sg:city":"Dunkirk",
    "sg:classifiers":[
        {
            "category":"Health Services",
            "subcategory":"Dentist",
            "type":"Services"
        }
    ],
    "sg:phone":"+1 716 366 2992",
    "sg:postcode":"14048",
    "sg:province":"NY",
    "wof:name":"Carl E Williams Dds Pc",
    "wof:placetype":"venue"
},
  "geometry": {"coordinates":[-79.33180299999999,42.483514],"type":"Point"}
}