{
  "type": "Feature",
  "properties": {
    "iso:country":"US",
    "sg:address":"42 Main St",
    "sg:city":"Saranac Lake",
    "sg:classifiers":[
        {
            "category":"Restaurant",
            "type":"Food & Drink"
        }
    ],
    "sg:phone":"+1 518 891 5500",
    "sg:postcode":"12983",
    "sg:province":"NY",
    "sg:tags":[
        "pizza"
    ],
    "wof:name":"Owl's Nest Pizza Parlor",
    "wof:placetype":"venue"
},
  "geometry": {"coordinates":[-74.131728,44.326281],"type":"Point"}
}