{
  "type": "Feature",
  "properties": {
    "iso:country":"US",
    "sg:address":"413 N Brewster Rd",
    "sg:city":"Brewster",
    "sg:classifiers":[
        {
            "category":"Professional",
            "subcategory":"Computer Services",
            "type":"Services"
        }
    ],
    "sg:phone":"+1 845 278 6010",
    "sg:postcode":"10509",
    "sg:province":"NY",
    "sg:tags":[
        "consultant",
        "designer",
        "datum",
        "system"
    ],
    "wof:name":"Clad Systems Inc",
    "wof:placetype":"venue"
},
  "geometry": {"coordinates":[-73.608301,41.43145],"type":"Point"}
}