{
  "type": "Feature",
  "properties": {
    "addr:full":"1315 1st Ave New York NY 10021",
    "addr:housenumber":"1315",
    "addr:postcode":"10021",
    "addr:street":"1St Ave",
    "iso:country":"US",
    "sg:address":"1315 1st Ave",
    "sg:city":"New York",
    "sg:classifiers":[
        {
            "category":"Food & Beverages",
            "subcategory":"Bakery",
            "type":"Retail Goods"
        }
    ],
    "sg:phone":"+1 212 396 0700",
    "sg:postcode":"10021",
    "sg:province":"NY",
    "sg:tags":[
        "sandwich"
    ],
    "sg:website":"www.wrapstarny.com",
    "wof:name":"Wrap Star",
    "wof:placetype":"venue"
},
  "geometry": {"coordinates":[-73.956974,40.766949],"type":"Point"}
}