{
  "type": "Feature",
  "properties": {
    "addr:full":"3975 Sedgwick Ave Bronx NY 10463",
    "addr:housenumber":"3975",
    "addr:postcode":"10463",
    "addr:street":"Sedgwick Ave",
    "iso:country":"US",
    "sg:address":"3975 Sedgwick Ave",
    "sg:city":"Bronx",
    "sg:classifiers":[
        {
            "category":"Health Services",
            "subcategory":"Doctor",
            "type":"Services"
        }
    ],
    "sg:phone":"+1 718 796 6055",
    "sg:postcode":"10463",
    "sg:province":"NY",
    "sg:tags":[
        "physician",
        "surgeon"
    ],
    "wof:name":"Steven Grenell MD",
    "wof:placetype":"venue"
},
  "geometry": {"coordinates":[-73.887896,40.88285],"type":"Point"}
}