{
  "type": "Feature",
  "properties": {
    "iso:country":"US",
    "sg:address":"9585 State Hwy 46",
    "sg:city":"Westernville",
    "sg:classifiers":[
        {
            "category":"Government",
            "subcategory":"Office",
            "type":"Public Place"
        }
    ],
    "sg:phone":"+1 315 827 4422",
    "sg:postcode":"13486",
    "sg:province":"NY",
    "sg:tags":[
        "village"
    ],
    "wof:name":"Westernville Highway Garage",
    "wof:placetype":"venue"
},
  "geometry": {"coordinates":[-75.358622,43.3247],"type":"Point"}
}