{
  "type": "Feature",
  "properties": {
    "iso:country":"US",
    "sg:address":"305 24th St",
    "sg:city":"Brooklyn",
    "sg:classifiers":[
        {
            "category":"Retail",
            "subcategory":"Repair Shop",
            "type":"Services"
        },
        {
            "category":"Building & Trades",
            "subcategory":"Construction",
            "type":"Services"
        }
    ],
    "sg:phone":"+1 718 492 4330",
    "sg:postcode":"11232",
    "sg:province":"NY",
    "sg:tags":[
        "ironwork",
        "sheet",
        "metal",
        "contractor"
    ],
    "wof:name":"A & D Iron Works Corp",
    "wof:placetype":"venue"
},
  "geometry": {"coordinates":[-73.996306,40.660671],"type":"Point"}
}