{
  "type": "Feature",
  "properties": {
    "addr:full":"179 N Broad St Norwich NY 13815",
    "addr:housenumber":"179",
    "addr:postcode":"13815",
    "addr:street":"N Broad St",
    "iso:country":"US",
    "sg:address":"179 N Broad St",
    "sg:city":"Norwich",
    "sg:classifiers":[
        {
            "category":"Wholesale",
            "subcategory":"Medical Equipment & Supplies",
            "type":"Manufacturing & Wholesale Goods"
        }
    ],
    "sg:phone":"+1 607 336 5130",
    "sg:postcode":"13815",
    "sg:province":"NY",
    "sg:tags":[
        "physician",
        "surgeon"
    ],
    "wof:name":"Professional Home Care",
    "wof:placetype":"venue"
},
  "geometry": {"coordinates":[-75.524579,42.540562],"type":"Point"}
}