{
  "type": "Feature",
  "properties": {
    "addr:full":"1673 E Main St Rochester NY 14609",
    "addr:housenumber":"1673",
    "addr:postcode":"14609",
    "addr:street":"E Main St",
    "iso:country":"US",
    "sg:address":"1673 E Main St",
    "sg:city":"Rochester",
    "sg:classifiers":[
        {
            "category":"Restaurant",
            "type":"Food & Drink"
        }
    ],
    "sg:menulink":"http://www.allmenus.com/ny/rochester/80733-papa-johns-pizza/menu/",
    "sg:phone":"+1 585 288 7272",
    "sg:postcode":"14609",
    "sg:province":"NY",
    "sg:tags":[
        "american",
        "pizza"
    ],
    "wof:name":"Papa John's Pizza",
    "wof:placetype":"venue"
},
  "geometry": {"coordinates":[-77.566734,43.15955],"type":"Point"}
}