{
  "type": "Feature",
  "properties": {
    "iso:country":"US",
    "sg:address":"220 Fulton St",
    "sg:city":"Farmingdale",
    "sg:classifiers":[
        {
            "category":"Retail",
            "subcategory":"Auto Repair",
            "type":"Services"
        }
    ],
    "sg:phone":"+1 516 755 2277",
    "sg:postcode":"11735",
    "sg:province":"NY",
    "sg:tags":[
        "body",
        "automobile",
        "painting"
    ],
    "wof:name":"Best Way Auto Security & Sound",
    "wof:placetype":"venue"
},
  "geometry": {"coordinates":[-73.456332,40.731163],"type":"Point"}
}