{
  "type": "Feature",
  "properties": {
    "addr:full":"7233 Amboy Road Staten Island NY 10307",
    "addr:housenumber":"7233",
    "addr:postcode":"10307",
    "addr:street":"Amboy Road",
    "iso:country":"US",
    "sg:address":"7233 Amboy Road",
    "sg:city":"Staten Island",
    "sg:classifiers":[
        {
            "category":"Home & Garden",
            "subcategory":"Hardware",
            "type":"Retail Goods"
        },
        {
            "category":"Building & Trades",
            "subcategory":"Locksmith",
            "type":"Services"
        }
    ],
    "sg:phone":"+1 718 317 5900",
    "sg:postcode":"10307",
    "sg:province":"NY",
    "sg:tags":[
        "store",
        "key"
    ],
    "wof:name":"Bob's Locksmith",
    "wof:placetype":"venue"
},
  "geometry": {"coordinates":[-74.238908,40.5123],"type":"Point"}
}