{
  "type": "Feature",
  "properties": {
    "addr:full":"451 E Boston Post Rd Mamaroneck NY 10543",
    "addr:housenumber":"451",
    "addr:postcode":"10543",
    "addr:street":"E Boston Post Rd",
    "iso:country":"US",
    "sg:address":"451 E Boston Post Rd",
    "sg:city":"Mamaroneck",
    "sg:classifiers":[
        {
            "category":"Professional",
            "subcategory":"Business Services",
            "type":"Services"
        },
        {
            "category":"Wholesale",
            "subcategory":"Sporting Goods",
            "type":"Manufacturing & Wholesale Goods"
        }
    ],
    "sg:phone":"+1 914 698 7732",
    "sg:postcode":"10543",
    "sg:province":"NY",
    "sg:tags":[
        "equipment",
        "cleaning",
        "maintenance",
        "retail",
        "pool",
        "swimming"
    ],
    "wof:name":"Olympia Pool Svc Corp",
    "wof:placetype":"venue"
},
  "geometry": {"coordinates":[-73.72778099999999,40.951892],"type":"Point"}
}