{
  "type": "Feature",
  "properties": {
    "addr:full":"2220 E Tremont Ave Bronx NY 10462",
    "addr:housenumber":"2220",
    "addr:postcode":"10462",
    "addr:street":"E Tremont Ave",
    "iso:country":"US",
    "sg:address":"2220 E Tremont Ave",
    "sg:city":"Bronx",
    "sg:classifiers":[
        {
            "category":"Freight",
            "type":"Transportation"
        }
    ],
    "sg:phone":"+1   ",
    "sg:postcode":"10462",
    "sg:province":"NY",
    "sg:tags":[
        "operator",
        "local",
        "trucking"
    ],
    "wof:name":"Anthony Appiah",
    "wof:placetype":"venue"
},
  "geometry": {"coordinates":[-73.855609,40.842129],"type":"Point"}
}