{
  "type": "Feature",
  "properties": {
    "iso:country":"US",
    "sg:address":"78 5th Ave",
    "sg:city":"Westbury",
    "sg:classifiers":[
        {
            "category":"Professional",
            "type":"Services"
        }
    ],
    "sg:phone":"+1   ",
    "sg:postcode":"11590",
    "sg:province":"NY",
    "wof:name":"Gary L Ramis",
    "wof:placetype":"venue"
},
  "geometry": {"coordinates":[-73.589438,40.750533],"type":"Point"}
}