{
  "type": "Feature",
  "properties": {
    "addr:full":"175 E 125th St New York NY 10035",
    "addr:housenumber":"175",
    "addr:postcode":"10035",
    "addr:street":"E 125Th St",
    "iso:country":"US",
    "sg:address":"175 E 125th St",
    "sg:city":"New York",
    "sg:classifiers":[
        {
            "category":"Organizations",
            "subcategory":"Membership Organization",
            "type":"Services"
        }
    ],
    "sg:phone":"+1 212 860 3200",
    "sg:postcode":"10035",
    "sg:province":"NY",
    "wof:name":"Salvation Army The",
    "wof:placetype":"venue"
},
  "geometry": {"coordinates":[-73.93655200000001,40.804194],"type":"Point"}
}