{
  "type": "Feature",
  "properties": {
    "iso:country":"US",
    "sg:address":"17 Cambridge Rd",
    "sg:city":"Great Neck",
    "sg:classifiers":[
        {
            "category":"Building & Trades",
            "subcategory":"Construction",
            "type":"Services"
        }
    ],
    "sg:phone":"+1 516 466 4915",
    "sg:postcode":"11023",
    "sg:province":"NY",
    "sg:tags":[
        "house"
    ],
    "wof:name":"Dewitt Ave Builders Inc",
    "wof:placetype":"venue"
},
  "geometry": {"coordinates":[-73.72781000000001,40.797508],"type":"Point"}
}