{
  "type": "Feature",
  "properties": {
    "iso:country":"US",
    "sg:address":"8512 5th Ave",
    "sg:city":"Brooklyn",
    "sg:classifiers":[
        {
            "category":"Personal",
            "subcategory":"Beauty Salon",
            "type":"Services"
        }
    ],
    "sg:phone":"+1   ",
    "sg:postcode":"11209",
    "sg:province":"NY",
    "sg:tags":[
        "manicurist"
    ],
    "wof:name":"Golden Nails",
    "wof:placetype":"venue"
},
  "geometry": {"coordinates":[-74.02622599999999,40.621611],"type":"Point"}
}