{
  "type": "Feature",
  "properties": {
    "addr:full":"28 Greene Ave Amityville NY 11701",
    "addr:housenumber":"28",
    "addr:postcode":"11701",
    "addr:street":"Greene Ave",
    "iso:country":"US",
    "sg:address":"28 Greene Ave",
    "sg:city":"Amityville",
    "sg:classifiers":[
        {
            "category":"Building & Trades",
            "subcategory":"Construction",
            "type":"Services"
        }
    ],
    "sg:phone":"+1 631 691 3638",
    "sg:postcode":"11701",
    "sg:province":"NY",
    "sg:tags":[
        "house"
    ],
    "wof:name":"Rogers Remodelers",
    "wof:placetype":"venue"
},
  "geometry": {"coordinates":[-73.41871500000001,40.678482],"type":"Point"}
}