{
  "type": "Feature",
  "properties": {
    "addr:full":"4296 Jockey St Ballston Lake NY 12019",
    "addr:housenumber":"4296",
    "addr:postcode":"12019",
    "addr:street":"Jockey St",
    "iso:country":"US",
    "sg:address":"4296 Jockey St",
    "sg:city":"Ballston Lake",
    "sg:classifiers":[
        {
            "category":"Farming",
            "subcategory":"Dairy Farm",
            "type":"Manufacturing & Wholesale Goods"
        }
    ],
    "sg:phone":"+1 518 882 6406",
    "sg:postcode":"12019",
    "sg:province":"NY",
    "wof:name":"Holbrook Farm",
    "wof:placetype":"venue"
},
  "geometry": {"coordinates":[-73.975775,42.970588],"type":"Point"}
}