{
  "type": "Feature",
  "properties": {
    "iso:country":"US",
    "sg:address":"4158 White Plains Rd",
    "sg:city":"Bronx",
    "sg:classifiers":[
        {
            "category":"Food & Beverages",
            "subcategory":"Meat & Fish",
            "type":"Retail Goods"
        }
    ],
    "sg:phone":"+1   ",
    "sg:postcode":"10466",
    "sg:province":"NY",
    "wof:name":"White Plains Road Meat Market",
    "wof:placetype":"venue"
},
  "geometry": {"coordinates":[-73.857782,40.892441],"type":"Point"}
}