{
  "type": "Feature",
  "properties": {
    "addr:full":"5071 Oakwood Dr North Tonawanda NY 14120",
    "addr:housenumber":"5071",
    "addr:postcode":"14120",
    "addr:street":"Oakwood Dr",
    "iso:country":"US",
    "sg:address":"5071 Oakwood Dr",
    "sg:city":"North Tonawanda",
    "sg:classifiers":[
        {
            "category":"Insurance",
            "subcategory":"Insurance Agent",
            "type":"Services"
        }
    ],
    "sg:phone":"+1 716 885 6900",
    "sg:postcode":"14120",
    "sg:province":"NY",
    "wof:name":"Glenn J Frank",
    "wof:placetype":"venue"
},
  "geometry": {"coordinates":[-78.756299,43.08687],"type":"Point"}
}