{
  "type": "Feature",
  "properties": {
    "iso:country":"US",
    "sg:address":"140 Cherry Rd",
    "sg:city":"Rochester",
    "sg:classifiers":[
        {
            "category":"Manufacturing",
            "subcategory":"Metals",
            "type":"Manufacturing & Wholesale Goods"
        }
    ],
    "sg:phone":"+1 585 247 6200",
    "sg:postcode":"14624",
    "sg:province":"NY",
    "sg:tags":[
        "furnace",
        "works",
        "contractor",
        "electrical",
        "blast",
        "welding"
    ],
    "wof:name":"Quality Stainless Fabrication",
    "wof:placetype":"venue"
},
  "geometry": {"coordinates":[-77.735366,43.132142],"type":"Point"}
}