{
  "type": "Feature",
  "properties": {
    "addr:full":"58 North Ave Owego NY 13827",
    "addr:housenumber":"58",
    "addr:postcode":"13827",
    "addr:street":"North Ave",
    "iso:country":"US",
    "sg:address":"58 North Ave",
    "sg:city":"Owego",
    "sg:classifiers":[
        {
            "category":"Health Services",
            "subcategory":"Optometrist",
            "type":"Services"
        }
    ],
    "sg:phone":"+1   ",
    "sg:postcode":"13827",
    "sg:province":"NY",
    "sg:tags":[
        "optical",
        "good"
    ],
    "wof:name":"Binghamton Optical",
    "wof:placetype":"venue"
},
  "geometry": {"coordinates":[-76.262732,42.104111],"type":"Point"}
}