{
  "type": "Feature",
  "properties": {
    "addr:full":"832 Saint Johns Pl Brooklyn NY 11216",
    "addr:housenumber":"832",
    "addr:postcode":"11216",
    "addr:street":"Saint Johns Pl",
    "iso:country":"US",
    "sg:address":"832 Saint Johns Pl",
    "sg:city":"Brooklyn",
    "sg:classifiers":[
        {
            "category":"Travel",
            "subcategory":"Hotels & Motels",
            "type":"Entertainment"
        },
        {
            "category":"Personal",
            "type":"Services"
        }
    ],
    "sg:phone":"+1 718 484 0907",
    "sg:postcode":"11216",
    "sg:province":"NY",
    "sg:tags":[
        "concierge",
        "assistant"
    ],
    "wof:name":"Rerun Studios",
    "wof:placetype":"venue"
},
  "geometry": {"coordinates":[-73.95064499999999,40.671647],"type":"Point"}
}