{
  "type": "Feature",
  "properties": {
    "addr:full":"882 Old Seneca Tpke Skaneateles NY 13152",
    "addr:housenumber":"882",
    "addr:postcode":"13152",
    "addr:street":"Old Seneca Tpke",
    "iso:country":"US",
    "sg:address":"882 Old Seneca Tpke",
    "sg:city":"Skaneateles",
    "sg:classifiers":[
        {
            "category":"Manufacturing",
            "subcategory":"Electronics",
            "type":"Manufacturing & Wholesale Goods"
        }
    ],
    "sg:phone":"+1 315 685 6453",
    "sg:postcode":"13152",
    "sg:province":"NY",
    "sg:tags":[
        "sound",
        "equipment",
        "system"
    ],
    "wof:name":"ADJ Entertainment",
    "wof:placetype":"venue"
},
  "geometry": {"coordinates":[-76.454538,42.958505],"type":"Point"}
}