{
  "type": "Feature",
  "properties": {
    "addr:full":"924 Paulding St Peekskill NY 10566",
    "addr:housenumber":"924",
    "addr:postcode":"10566",
    "addr:street":"Paulding St",
    "iso:country":"US",
    "sg:address":"924 Paulding St",
    "sg:city":"Peekskill",
    "sg:classifiers":[
        {
            "category":"Building & Trades",
            "subcategory":"Construction",
            "type":"Services"
        }
    ],
    "sg:phone":"+1 914 739 5310",
    "sg:postcode":"10566",
    "sg:province":"NY",
    "sg:tags":[
        "masonry",
        "contractor"
    ],
    "wof:name":"Stone Works & Patio Corp",
    "wof:placetype":"venue"
},
  "geometry": {"coordinates":[-73.91918200000001,41.293249],"type":"Point"}
}