{
  "type": "Feature",
  "properties": {
    "iso:country":"US",
    "sg:address":"409 Fulton St",
    "sg:city":"Hannibal",
    "sg:classifiers":[
        {
            "category":"Banks & Credit Unions",
            "subcategory":"Bank",
            "type":"Services"
        }
    ],
    "sg:phone":"+1 315 564 6480",
    "sg:postcode":"13074",
    "sg:province":"NY",
    "sg:tags":[
        "state",
        "commercial"
    ],
    "wof:name":"Fulton Savings Bank Inc",
    "wof:placetype":"venue"
},
  "geometry": {"coordinates":[-76.56794499999999,43.323252],"type":"Point"}
}