{
  "type": "Feature",
  "properties": {
    "iso:country":"US",
    "sg:address":"1312 Montauk Hwy",
    "sg:city":"Oakdale",
    "sg:classifiers":[
        {
            "category":"Retail",
            "subcategory":"Repair Shop",
            "type":"Services"
        }
    ],
    "sg:phone":"+1 631 229 0328",
    "sg:postcode":"11769",
    "sg:province":"NY",
    "sg:tags":[
        "lock",
        "locksmith"
    ],
    "wof:name":"Emergency Locksmith",
    "wof:placetype":"venue"
},
  "geometry": {"coordinates":[-73.13291599999999,40.742678],"type":"Point"}
}