{
  "type": "Feature",
  "properties": {
    "iso:country":"US",
    "sg:address":"1200 Brooks Ave",
    "sg:city":"Rochester",
    "sg:classifiers":[
        {
            "category":"Travel",
            "subcategory":"Hotels & Motels",
            "type":"Entertainment"
        }
    ],
    "sg:phone":"+1 585 529 5000",
    "sg:postcode":"14624",
    "sg:province":"NY",
    "sg:tags":[
        "operation"
    ],
    "wof:name":"Fairfield Inn",
    "wof:placetype":"venue"
},
  "geometry": {"coordinates":[-77.67029700000001,43.13084],"type":"Point"}
}