{
  "type": "Feature",
  "properties": {
    "addr:full":"435 Tupper Rd Newfield NY 14883",
    "addr:housenumber":"435",
    "addr:postcode":"14883",
    "addr:street":"Tupper Rd",
    "iso:country":"US",
    "sg:address":"435 Tupper Rd",
    "sg:city":"Newfield",
    "sg:classifiers":[
        {
            "category":"Shopping",
            "subcategory":"Computers & Home Electronics",
            "type":"Retail Goods"
        }
    ],
    "sg:phone":"+1   ",
    "sg:postcode":"14883",
    "sg:province":"NY",
    "sg:tags":[
        "hardware",
        "software"
    ],
    "wof:name":"Cayuga Computers",
    "wof:placetype":"venue"
},
  "geometry": {"coordinates":[-76.541978,42.317811],"type":"Point"}
}