{
  "type": "Feature",
  "properties": {
    "addr:full":"300 New Hyde Park Rd New Hyde Park NY 11040",
    "addr:housenumber":"300",
    "addr:postcode":"11040",
    "addr:street":"New Hyde Park Rd",
    "iso:country":"US",
    "sg:address":"300 New Hyde Park Rd",
    "sg:city":"New Hyde Park",
    "sg:classifiers":[
        {
            "category":"Park",
            "type":"Public Place"
        },
        {
            "category":"Education",
            "subcategory":"School",
            "type":"Public Place"
        }
    ],
    "sg:phone":"+1 516 354 1223",
    "sg:postcode":"11040",
    "sg:province":"NY",
    "sg:tags":[
        "high",
        "middle",
        "elementary"
    ],
    "wof:name":"New Hyde Park-Garden City Park Union Free School District",
    "wof:placetype":"venue"
},
  "geometry": {"coordinates":[-73.680639,40.735756],"type":"Point"}
}