{
  "type": "Feature",
  "properties": {
    "iso:country":"US",
    "sg:address":"24 E 11 St",
    "sg:city":"New York",
    "sg:classifiers":[
        {
            "category":"Travel",
            "subcategory":"Travel Agent",
            "type":"Entertainment"
        }
    ],
    "sg:phone":"+1 212 982 1535",
    "sg:postcode":"10003",
    "sg:province":"NY",
    "sg:tags":[
        "agency",
        "bureau"
    ],
    "wof:name":"JMC Travel Inc",
    "wof:placetype":"venue"
},
  "geometry": {"coordinates":[-73.994158,40.733685],"type":"Point"}
}