{
  "type": "Feature",
  "properties": {
    "addr:full":"250 E Hartsdale Ave Hartsdale NY 10530",
    "addr:housenumber":"250",
    "addr:postcode":"10530",
    "addr:street":"E Hartsdale Ave",
    "iso:country":"US",
    "sg:address":"250 E Hartsdale Ave",
    "sg:city":"Hartsdale",
    "sg:classifiers":[
        {
            "category":"Health Services",
            "subcategory":"Doctor",
            "type":"Services"
        }
    ],
    "sg:phone":"+1 914 725 5300",
    "sg:postcode":"10530",
    "sg:province":"NY",
    "sg:tags":[
        "medical"
    ],
    "wof:name":"Judith Gordon",
    "wof:placetype":"venue"
},
  "geometry": {"coordinates":[-73.796345,41.012698],"type":"Point"}
}