{
  "type": "Feature",
  "properties": {
    "iso:country":"US",
    "sg:address":"20 Antoinette Dr",
    "sg:city":"Depew",
    "sg:classifiers":[
        {
            "category":"Banks & Credit Unions",
            "subcategory":"Financial Services",
            "type":"Services"
        }
    ],
    "sg:phone":"+1 716 684 9431",
    "sg:postcode":"14043",
    "sg:province":"NY",
    "sg:tags":[
        "company",
        "holding"
    ],
    "wof:name":"Twenty Antoinette Holdings",
    "wof:placetype":"venue"
},
  "geometry": {"coordinates":[-78.692598,42.927314],"type":"Point"}
}