{
  "type": "Feature",
  "properties": {
    "addr:full":"7365 Oswego Rd Liverpool NY 13090",
    "addr:housenumber":"7365",
    "addr:postcode":"13090",
    "addr:street":"Oswego Rd",
    "iso:country":"US",
    "sg:address":"7365 Oswego Rd",
    "sg:city":"Liverpool",
    "sg:classifiers":[
        {
            "category":"Restaurant",
            "type":"Food & Drink"
        }
    ],
    "sg:menulink":"http://www.allmenus.com/ny/clay/73619-pizza-hut/menu/",
    "sg:phone":"+1 315 451 8200",
    "sg:postcode":"13090",
    "sg:province":"NY",
    "sg:tags":[
        "american",
        "pizza"
    ],
    "wof:name":"Pizza Hut",
    "wof:placetype":"venue"
},
  "geometry": {"coordinates":[-76.218632,43.128035],"type":"Point"}
}