{
  "type": "Feature",
  "properties": {
    "addr:full":"1 Pathmark Plz Mount Vernon NY 10550",
    "addr:housenumber":"1",
    "addr:postcode":"10550",
    "addr:street":"Pathmark Plz",
    "iso:country":"US",
    "sg:address":"1 Pathmark Plz",
    "sg:city":"Mount Vernon",
    "sg:classifiers":[
        {
            "category":"Food & Beverages",
            "subcategory":"Groceries & Convenience Stores",
            "type":"Retail Goods"
        }
    ],
    "sg:phone":"+1 914 668 5477",
    "sg:postcode":"10550",
    "sg:province":"NY",
    "sg:tags":[
        "bakery",
        "grocer"
    ],
    "wof:name":"Pathmark",
    "wof:placetype":"venue"
},
  "geometry": {"coordinates":[-73.832318,40.910768],"type":"Point"}
}