{
  "type": "Feature",
  "properties": {
    "iso:country":"US",
    "sg:address":"3256 Bruner Ave",
    "sg:city":"Bronx",
    "sg:classifiers":[
        {
            "category":"Wholesale",
            "subcategory":"Construction Materials",
            "type":"Manufacturing & Wholesale Goods"
        }
    ],
    "sg:phone":"+1 718 320 7973",
    "sg:postcode":"10469",
    "sg:province":"NY",
    "sg:tags":[
        "fence"
    ],
    "wof:name":"Craft Fence Co",
    "wof:placetype":"venue"
},
  "geometry": {"coordinates":[-73.839624,40.875415],"type":"Point"}
}