{
  "type": "Feature",
  "properties": {
    "addr:full":"587 Humboldt St Brooklyn NY 11222",
    "addr:housenumber":"587",
    "addr:postcode":"11222",
    "addr:street":"Humboldt St",
    "iso:country":"US",
    "sg:address":"587 Humboldt St",
    "sg:city":"Brooklyn",
    "sg:classifiers":[
        {
            "category":"Wholesale",
            "subcategory":"Durable Goods & Equipment",
            "type":"Manufacturing & Wholesale Goods"
        }
    ],
    "sg:phone":"+1 718 486 6213",
    "sg:postcode":"11222",
    "sg:province":"NY",
    "sg:tags":[
        "importer"
    ],
    "wof:name":"Ekachai Import",
    "wof:placetype":"venue"
},
  "geometry": {"coordinates":[-73.945049,40.722674],"type":"Point"}
}