{
  "type": "Feature",
  "properties": {
    "iso:country":"US",
    "sg:address":"5710 Cmns Park",
    "sg:city":"East Syracuse",
    "sg:classifiers":[
        {
            "category":"Insurance",
            "subcategory":"Insurance Agent",
            "type":"Services"
        }
    ],
    "sg:phone":"+1 315 449 1444",
    "sg:postcode":"13057",
    "sg:province":"NY",
    "wof:name":"Hrh Insurance",
    "wof:placetype":"venue"
},
  "geometry": {"coordinates":[-76.055066,43.050263],"type":"Point"}
}