{
  "type": "Feature",
  "properties": {
    "addr:full":"8620 Miller Hill Rd Averill Park NY 12018",
    "addr:housenumber":"8620",
    "addr:postcode":"12018",
    "addr:street":"Miller Hill Rd",
    "iso:country":"US",
    "sg:address":"8620 Miller Hill Rd",
    "sg:city":"Averill Park",
    "sg:classifiers":[
        {
            "category":"Wholesale",
            "subcategory":"Plants",
            "type":"Manufacturing & Wholesale Goods"
        }
    ],
    "sg:phone":"+1 518 674 5410",
    "sg:postcode":"12018",
    "sg:province":"NY",
    "sg:tags":[
        "flower"
    ],
    "wof:name":"Engwers Dan Wholesale Flowers",
    "wof:placetype":"venue"
},
  "geometry": {"coordinates":[-73.56381500000001,42.652154],"type":"Point"}
}