{
  "type": "Feature",
  "properties": {
    "iso:country":"US",
    "sg:address":"422 E State St",
    "sg:city":"Olean",
    "sg:classifiers":[
        {
            "category":"Professional",
            "subcategory":"Employment Agencies",
            "type":"Services"
        }
    ],
    "sg:phone":"+1 716 372 0079",
    "sg:postcode":"14760",
    "sg:province":"NY",
    "sg:tags":[
        "opportunity"
    ],
    "wof:name":"Adecco",
    "wof:placetype":"venue"
},
  "geometry": {"coordinates":[-78.423945,42.077611],"type":"Point"}
}