{
  "type": "Feature",
  "properties": {
    "addr:full":"3547 Broadway New York NY 10031",
    "addr:housenumber":"3547",
    "addr:postcode":"10031",
    "addr:street":"Broadway",
    "iso:country":"US",
    "sg:address":"3547 Broadway",
    "sg:city":"New York",
    "sg:classifiers":[
        {
            "category":"Home & Garden",
            "subcategory":"Home Furnishings",
            "type":"Retail Goods"
        }
    ],
    "sg:phone":"+1 212 926 7970",
    "sg:postcode":"10031",
    "sg:province":"NY",
    "sg:tags":[
        "housewares"
    ],
    "wof:name":"CLH Hardware",
    "wof:placetype":"venue"
},
  "geometry": {"coordinates":[-73.95012699999999,40.826956],"type":"Point"}
}