{
  "type": "Feature",
  "properties": {
    "iso:country":"US",
    "sg:address":"209 Clinton Ave",
    "sg:city":"Kingston",
    "sg:classifiers":[
        {
            "category":"Social Services",
            "type":"Services"
        }
    ],
    "sg:phone":"+1   ",
    "sg:postcode":"12401",
    "sg:province":"NY",
    "wof:name":"Family Advocates Inc",
    "wof:placetype":"venue"
},
  "geometry": {"coordinates":[-74.01555500000001,41.932452],"type":"Point"}
}