{
  "type": "Feature",
  "properties": {
    "addr:full":"148 E 38th Street New York NY 10016",
    "addr:housenumber":"148",
    "addr:postcode":"10016",
    "addr:street":"E 38Th Street",
    "iso:country":"US",
    "sg:address":"148 E 38th Street",
    "sg:city":"New York",
    "sg:classifiers":[
        {
            "category":"Health Services",
            "subcategory":"Doctor",
            "type":"Services"
        }
    ],
    "sg:phone":"+1 212 679 4488",
    "sg:postcode":"10016",
    "sg:province":"NY",
    "wof:name":"Heartwise Cardiology",
    "wof:placetype":"venue"
},
  "geometry": {"coordinates":[-73.97753,40.748775],"type":"Point"}
}