{
  "type": "Feature",
  "properties": {
    "addr:full":"P.O. Box 835 Manhattanville Station New York NY 10027-0835",
    "addr:housenumber":"p.o. box 835",
    "addr:postcode":"10027-0835",
    "addr:street":"Manhattanville Station",
    "iso:country":"US",
    "sg:address":"P.O. Box 835 Manhattanville Station",
    "sg:city":"New York",
    "sg:classifiers":[
        {
            "category":"Professional",
            "subcategory":"Computer Services",
            "type":"Services"
        }
    ],
    "sg:postcode":"10027-0835",
    "sg:province":"NY",
    "sg:tags":[
        "technology",
        "software",
        "information-technology",
        "spreadsheet",
        "creative",
        "excel",
        "powerpoint",
        "free-software"
    ],
    "sg:website":"http://www.techronology.com",
    "wof:name":"Techronology",
    "wof:placetype":"venue"
},
  "geometry": {"coordinates":[-73.9532,40.812242],"type":"Point"}
}