{
  "type": "Feature",
  "properties": {
    "addr:full":"415 Willis Ave Williston Park NY 11596",
    "addr:housenumber":"415",
    "addr:postcode":"11596",
    "addr:street":"Willis Ave",
    "iso:country":"US",
    "sg:address":"415 Willis Ave",
    "sg:city":"Williston Park",
    "sg:classifiers":[
        {
            "category":"Organizations",
            "subcategory":"Labor Organization",
            "type":"Services"
        }
    ],
    "sg:phone":"+1 516 739 0105",
    "sg:postcode":"11596",
    "sg:province":"NY",
    "wof:name":"Pension Fund",
    "wof:placetype":"venue"
},
  "geometry": {"coordinates":[-73.64445499999999,40.755075],"type":"Point"}
}