{
  "type": "Feature",
  "properties": {
    "iso:country":"US",
    "sg:address":"7 Tivoli St",
    "sg:city":"Albany",
    "sg:classifiers":[
        {
            "category":"Freight",
            "type":"Transportation"
        }
    ],
    "sg:phone":"+1   ",
    "sg:postcode":"12207",
    "sg:province":"NY",
    "sg:tags":[
        "moving",
        "storage"
    ],
    "wof:name":"Atlantic Coast Riggers",
    "wof:placetype":"venue"
},
  "geometry": {"coordinates":[-73.745673,42.664763],"type":"Point"}
}