{
  "type": "Feature",
  "properties": {
    "addr:full":"144 W. 37th Street Suite 6A New York NY 10018",
    "addr:housenumber":"144",
    "addr:postcode":"10018",
    "addr:street":"W. 37Th Street Suite 6A",
    "iso:country":"US",
    "sg:address":"144 W. 37th Street Suite 6A",
    "sg:city":"New York",
    "sg:classifiers":[
        {
            "category":"Professional",
            "subcategory":"Computer Services",
            "type":"Services"
        }
    ],
    "sg:phone":"+1 212 967 4239",
    "sg:postcode":"10018",
    "sg:province":"NY",
    "sg:tags":[
        "web",
        "ruby",
        "rails",
        "application-development",
        "product-development",
        "geolocation",
        "mobile",
        "design",
        "ux"
    ],
    "sg:website":"http://eastmedia.com",
    "wof:name":"Eastmedia",
    "wof:placetype":"venue"
},
  "geometry": {"coordinates":[-73.988826,40.752577],"type":"Point"}
}