{
  "type": "Feature",
  "properties": {
    "iso:country":"US",
    "sg:address":"168 E 88 St",
    "sg:city":"New York",
    "sg:classifiers":[
        {
            "category":"Retail",
            "subcategory":"Repair Shop",
            "type":"Services"
        }
    ],
    "sg:phone":"+1 917 677 1241",
    "sg:postcode":"10128",
    "sg:province":"NY",
    "sg:tags":[
        "lock",
        "locksmith"
    ],
    "wof:name":"Emergency 7 Day Locksmith",
    "wof:placetype":"venue"
},
  "geometry": {"coordinates":[-73.95360599999999,40.78036],"type":"Point"}
}