{
  "type": "Feature",
  "properties": {
    "iso:country":"US",
    "sg:address":"36 Katherine St",
    "sg:city":"Lancaster",
    "sg:classifiers":[
        {
            "category":"Building & Trades",
            "subcategory":"Construction",
            "type":"Services"
        }
    ],
    "sg:phone":"+1 716 683 4720",
    "sg:postcode":"14086",
    "sg:province":"NY",
    "sg:tags":[
        "house"
    ],
    "wof:name":"Robert Tarasek Construction",
    "wof:placetype":"venue"
},
  "geometry": {"coordinates":[-78.670689,42.919131],"type":"Point"}
}