{
  "type": "Feature",
  "properties": {
    "iso:country":"US",
    "sg:address":"1850 Colvin Blvd",
    "sg:city":"Tonawanda",
    "sg:classifiers":[
        {
            "category":"Shopping",
            "type":"Retail Goods"
        }
    ],
    "sg:phone":"+1 716 838 2898",
    "sg:postcode":"14150",
    "sg:province":"NY",
    "sg:tags":[
        "bookstore",
        "religious"
    ],
    "sg:website":"http://www.promultis.com",
    "wof:name":"Pro Multis Catholic Book & Gift Center",
    "wof:placetype":"venue"
},
  "geometry": {"coordinates":[-78.85279800000001,42.988258],"type":"Point"}
}