{
  "type": "Feature",
  "properties": {
    "addr:full":"9 Sewell St Hempstead NY 11550",
    "addr:housenumber":"9",
    "addr:postcode":"11550",
    "addr:street":"Sewell St",
    "iso:country":"US",
    "sg:address":"9 Sewell St",
    "sg:city":"Hempstead",
    "sg:classifiers":[
        {
            "category":"Professional",
            "subcategory":"Business Services",
            "type":"Services"
        }
    ],
    "sg:phone":"+1 516 538 4698",
    "sg:postcode":"11550",
    "sg:province":"NY",
    "wof:name":"JDJ Communications Inc",
    "wof:placetype":"venue"
},
  "geometry": {"coordinates":[-73.630503,40.701385],"type":"Point"}
}