{
  "type": "Feature",
  "properties": {
    "addr:full":"31 Cobek Ct Brooklyn NY 11223",
    "addr:housenumber":"31",
    "addr:postcode":"11223",
    "addr:street":"Cobek Ct",
    "iso:country":"US",
    "sg:address":"31 Cobek Ct",
    "sg:city":"Brooklyn",
    "sg:classifiers":[
        {
            "category":"Wholesale",
            "subcategory":"Construction Materials",
            "type":"Manufacturing & Wholesale Goods"
        },
        {
            "category":"Manufacturing",
            "subcategory":"Glass & Minerals",
            "type":"Manufacturing & Wholesale Goods"
        }
    ],
    "sg:phone":"+1 718 998 3636",
    "sg:postcode":"11223",
    "sg:province":"NY",
    "sg:tags":[
        "product",
        "for",
        "top",
        "table",
        "retail",
        "marble"
    ],
    "sg:website":"www.wholesalemarbleandgranite.com",
    "wof:name":"Wholesale Marble Importers Inc",
    "wof:placetype":"venue"
},
  "geometry": {"coordinates":[-73.972909,40.587413],"type":"Point"}
}