{
  "type": "Feature",
  "properties": {
    "iso:country":"US",
    "sg:address":"907 Seneca Ave",
    "sg:city":"Ridgewood",
    "sg:classifiers":[
        {
            "category":"Restaurant",
            "type":"Food & Drink"
        }
    ],
    "sg:menulink":"http://www.allmenus.com/ny/queens/93992-golden-star-chinese-restaurant/menu/",
    "sg:phone":"+1 718 417 1873",
    "sg:postcode":"11385",
    "sg:province":"NY",
    "sg:tags":[
        "asian",
        "chinese"
    ],
    "wof:name":"Golden Star Chinese Restaurant",
    "wof:placetype":"venue"
},
  "geometry": {"coordinates":[-73.90404700000001,40.700641],"type":"Point"}
}