{
  "type": "Feature",
  "properties": {
    "addr:full":"30 Sheep Pasture Rd Port Jefferson NY 11777",
    "addr:housenumber":"30",
    "addr:postcode":"11777",
    "addr:street":"Sheep Pasture Rd",
    "iso:country":"US",
    "sg:address":"30 Sheep Pasture Rd",
    "sg:city":"Port Jefferson",
    "sg:classifiers":[
        {
            "category":"Banks & Credit Unions",
            "subcategory":"Bank",
            "type":"Services"
        }
    ],
    "sg:phone":"+1 631 476 8308",
    "sg:postcode":"11777",
    "sg:province":"NY",
    "wof:name":"Citibank",
    "wof:placetype":"venue"
},
  "geometry": {"coordinates":[-73.058622,40.934303],"type":"Point"}
}