{
  "type": "Feature",
  "properties": {
    "iso:country":"US",
    "sg:address":"99 Wall St",
    "sg:city":"New York",
    "sg:classifiers":[
        {
            "category":"Professional",
            "subcategory":"Management & Consulting",
            "type":"Services"
        }
    ],
    "sg:phone":"+1 212 785 4335",
    "sg:postcode":"10005",
    "sg:province":"NY",
    "sg:tags":[
        "marketing",
        "program"
    ],
    "wof:name":"Leadmaster",
    "wof:placetype":"venue"
},
  "geometry": {"coordinates":[-74.007139,40.704949],"type":"Point"}
}