{
  "type": "Feature",
  "properties": {
    "addr:full":"345 Seaview Ave Staten Island NY 10305",
    "addr:housenumber":"345",
    "addr:postcode":"10305",
    "addr:street":"Seaview Ave",
    "iso:country":"US",
    "sg:address":"345 Seaview Ave",
    "sg:city":"Staten Island",
    "sg:classifiers":[
        {
            "category":"Health Services",
            "subcategory":"Doctor",
            "type":"Services"
        },
        {
            "category":"Community Center",
            "type":"Public Place"
        }
    ],
    "sg:phone":"+1 718 980 4888",
    "sg:postcode":"10305",
    "sg:province":"NY",
    "sg:tags":[
        "medical"
    ],
    "sg:website":"www.arimri.com",
    "wof:name":"ARI Open MRI - Atlantic Radiologic Imaging",
    "wof:placetype":"venue"
},
  "geometry": {"coordinates":[-74.090518,40.585895],"type":"Point"}
}