{
  "type": "Feature",
  "properties": {
    "iso:country":"US",
    "sg:address":"57 Brookline Dr",
    "sg:city":"Clifton Park",
    "sg:classifiers":[
        {
            "category":"Building & Trades",
            "subcategory":"Construction",
            "type":"Services"
        }
    ],
    "sg:phone":"+1 518 877 0315",
    "sg:postcode":"12065",
    "sg:province":"NY",
    "sg:tags":[
        "contractor"
    ],
    "wof:name":"Best Edge & Metal Co",
    "wof:placetype":"venue"
},
  "geometry": {"coordinates":[-73.8172,42.905145],"type":"Point"}
}