{
  "type": "Feature",
  "properties": {
    "addr:full":"52 Western Ave Amsterdam NY 12010",
    "addr:housenumber":"52",
    "addr:postcode":"12010",
    "addr:street":"Western Ave",
    "iso:country":"US",
    "sg:address":"52 Western Ave",
    "sg:city":"Amsterdam",
    "sg:phone":"+1 518 882 6050",
    "sg:postcode":"12010",
    "sg:province":"NY",
    "sg:tags":[
        "farm",
        "field",
        "crop"
    ],
    "wof:name":"Anderson Acres",
    "wof:placetype":"venue"
},
  "geometry": {"coordinates":[-74.071527,42.958192],"type":"Point"}
}