{
  "type": "Feature",
  "properties": {
    "addr:full":"64 2nd St Athens NY 12015",
    "addr:housenumber":"64",
    "addr:postcode":"12015",
    "addr:street":"2Nd St",
    "iso:country":"US",
    "sg:address":"64 2nd St",
    "sg:city":"Athens",
    "sg:classifiers":[
        {
            "category":"Real Estate",
            "subcategory":"Architect",
            "type":"Services"
        }
    ],
    "sg:phone":"+1   ",
    "sg:postcode":"12015",
    "sg:province":"NY",
    "sg:tags":[
        "architectural",
        "business"
    ],
    "wof:name":"Athens Architectural Workshop",
    "wof:placetype":"venue"
},
  "geometry": {"coordinates":[-73.81110700000001,42.261204],"type":"Point"}
}