{
  "type": "Feature",
  "properties": {
    "addr:full":"2061 Brighton Henrietta Town Line Rd Rochester NY 14623",
    "addr:housenumber":"2061",
    "addr:postcode":"14623",
    "addr:street":"Brighton Henrietta Town Line Rd",
    "iso:country":"US",
    "sg:address":"2061 Brighton Henrietta Town Line Rd",
    "sg:city":"Rochester",
    "sg:classifiers":[
        {
            "category":"Freight",
            "type":"Transportation"
        }
    ],
    "sg:phone":"+1 585 475 9390",
    "sg:postcode":"14623",
    "sg:province":"NY",
    "sg:tags":[
        "mover"
    ],
    "wof:name":"Adamski Moving & Storage Inc",
    "wof:placetype":"venue"
},
  "geometry": {"coordinates":[-77.614075,43.094664],"type":"Point"}
}