{
  "type": "Feature",
  "properties": {
    "addr:full":"656 St Marys New York NY 10001",
    "addr:housenumber":"656",
    "addr:postcode":"10001",
    "addr:street":"St",
    "iso:country":"US",
    "sg:address":"656 St Marys",
    "sg:city":"New York",
    "sg:classifiers":[
        {
            "category":"Health Services",
            "subcategory":"Doctor",
            "type":"Services"
        }
    ],
    "sg:phone":"+1 718 872 5682",
    "sg:postcode":"10001",
    "sg:province":"NY",
    "wof:name":"The Westchester Medical Group",
    "wof:placetype":"venue"
},
  "geometry": {"coordinates":[-73.91278,40.809123],"type":"Point"}
}