{
  "type": "Feature",
  "properties": {
    "iso:country":"US",
    "sg:address":"27 E Fordham Rd",
    "sg:city":"Bronx",
    "sg:classifiers":[
        {
            "category":"Shopping",
            "subcategory":"Optical Goods",
            "type":"Retail Goods"
        }
    ],
    "sg:phone":"+1   ",
    "sg:postcode":"10468",
    "sg:province":"NY",
    "wof:name":"Jerome Optical",
    "wof:placetype":"venue"
},
  "geometry": {"coordinates":[-73.90107999999999,40.862756],"type":"Point"}
}