{
  "type": "Feature",
  "properties": {
    "iso:country":"US",
    "sg:address":"3421 Co Rd 4",
    "sg:city":"Canandaigua",
    "sg:classifiers":[
        {
            "category":"Food & Beverages",
            "subcategory":"Groceries & Convenience Stores",
            "type":"Retail Goods"
        }
    ],
    "sg:phone":"+1 585 394 6910",
    "sg:postcode":"14424",
    "sg:province":"NY",
    "wof:name":"Little Country Store",
    "wof:placetype":"venue"
},
  "geometry": {"coordinates":[-77.182146,42.9009],"type":"Point"}
}