{
  "type": "Feature",
  "properties": {
    "addr:full":"4158 Lakeville Rd Geneseo NY 14454",
    "addr:postcode":"4158;14454",
    "addr:street":"Lakeville Rd",
    "iso:country":"US",
    "sg:address":"4158 Lakeville Rd",
    "sg:city":"Geneseo",
    "sg:classifiers":[
        {
            "category":"Restaurant",
            "type":"Food & Drink"
        }
    ],
    "sg:phone":"+1   ",
    "sg:postcode":"14454",
    "sg:province":"NY",
    "sg:tags":[
        "eating"
    ],
    "wof:name":"Wendys",
    "wof:placetype":"venue"
},
  "geometry": {"coordinates":[-77.791467,42.796328],"type":"Point"}
}