{
  "type": "Feature",
  "properties": {
    "iso:country":"US",
    "sg:address":"17 Barstow Rd",
    "sg:city":"Great Neck",
    "sg:classifiers":[
        {
            "category":"Real Estate",
            "subcategory":"Real Estate Agent",
            "type":"Services"
        }
    ],
    "sg:phone":"+1 516 466 8114",
    "sg:postcode":"11021",
    "sg:province":"NY",
    "wof:name":"Martin Zelman Real Estate Ents",
    "wof:placetype":"venue"
},
  "geometry": {"coordinates":[-73.725106,40.789013],"type":"Point"}
}