{
  "type": "Feature",
  "properties": {
    "addr:full":"915 E 2nd St Jamestown NY 14701",
    "addr:housenumber":"915",
    "addr:postcode":"14701",
    "addr:street":"E 2Nd St",
    "iso:country":"US",
    "sg:address":"915 E 2nd St",
    "sg:city":"Jamestown",
    "sg:classifiers":[
        {
            "category":"Banks & Credit Unions",
            "subcategory":"Bank",
            "type":"Services"
        }
    ],
    "sg:phone":"+1 716 483 1650",
    "sg:postcode":"14701",
    "sg:province":"NY",
    "sg:tags":[
        "federal"
    ],
    "wof:name":"Jamestown Teachers Federal CU",
    "wof:placetype":"venue"
},
  "geometry": {"coordinates":[-79.22342399999999,42.106671],"type":"Point"}
}