{
  "type": "Feature",
  "properties": {
    "addr:full":"19 Glenridge Rd. #A Glenville NY 12302",
    "addr:housenumber":"19",
    "addr:postcode":"12302",
    "addr:street":"Glenridge Rd. # A",
    "iso:country":"US",
    "sg:address":"19 Glenridge Rd. #A",
    "sg:city":"Glenville",
    "sg:classifiers":[
        {
            "category":"Shopping",
            "subcategory":"Hobbies, Toys, & Games",
            "type":"Retail Goods"
        }
    ],
    "sg:phone":"+1 518 399 0128",
    "sg:postcode":"12302",
    "sg:province":"NY",
    "sg:tags":[
        "shop",
        "hobby"
    ],
    "sg:website":"www.joyfulquilter.com",
    "wof:name":"The Joyful Quilter",
    "wof:placetype":"venue"
},
  "geometry": {"coordinates":[-73.92706800000001,42.868776],"type":"Point"}
}