{
  "type": "Feature",
  "properties": {
    "addr:full":"193 Mount Airy Rd Croton On Hudson NY 10520",
    "addr:housenumber":"193",
    "addr:postcode":"10520",
    "addr:street":"Mount Airy Rd",
    "iso:country":"US",
    "sg:address":"193 Mount Airy Rd",
    "sg:city":"Croton On Hudson",
    "sg:classifiers":[
        {
            "category":"Building & Trades",
            "subcategory":"Construction",
            "type":"Services"
        }
    ],
    "sg:phone":"+1 914 271 3400",
    "sg:postcode":"10520",
    "sg:province":"NY",
    "sg:tags":[
        "general",
        "contractor"
    ],
    "wof:name":"Ral Construction & Conslnt",
    "wof:placetype":"venue"
},
  "geometry": {"coordinates":[-73.878708,41.229482],"type":"Point"}
}