{
  "type": "Feature",
  "properties": {
    "addr:full":"1098 Liberty Ave Brooklyn NY 11208",
    "addr:housenumber":"1098",
    "addr:postcode":"11208",
    "addr:street":"Liberty Ave",
    "iso:country":"US",
    "sg:address":"1098 Liberty Ave",
    "sg:city":"Brooklyn",
    "sg:classifiers":[
        {
            "category":"Health Services",
            "subcategory":"Podiatrist",
            "type":"Services"
        }
    ],
    "sg:phone":"+1   ",
    "sg:postcode":"11208",
    "sg:province":"NY",
    "wof:name":"Vannoy Tamira",
    "wof:placetype":"venue"
},
  "geometry": {"coordinates":[-73.86803399999999,40.678567],"type":"Point"}
}