{
  "type": "Feature",
  "properties": {
    "addr:full":"156 Spencer St Brooklyn NY 11205",
    "addr:housenumber":"156",
    "addr:postcode":"11205",
    "addr:street":"Spencer St",
    "iso:country":"US",
    "sg:address":"156 Spencer St",
    "sg:city":"Brooklyn",
    "sg:classifiers":[
        {
            "category":"Professional",
            "subcategory":"Computer Services",
            "type":"Services"
        }
    ],
    "sg:phone":"+1 718 694 9829",
    "sg:postcode":"11205",
    "sg:province":"NY",
    "sg:tags":[
        "internet"
    ],
    "wof:name":"Gleb Koutepov",
    "wof:placetype":"venue"
},
  "geometry": {"coordinates":[-73.955085,40.693955],"type":"Point"}
}