{
  "type": "Feature",
  "properties": {
    "iso:country":"US",
    "sg:address":"116 N Main St",
    "sg:city":"Milford",
    "sg:classifiers":[
        {
            "category":"Travel",
            "subcategory":"Hotels & Motels",
            "type":"Entertainment"
        }
    ],
    "sg:phone":"+1   ",
    "sg:postcode":"13807",
    "sg:province":"NY",
    "sg:tags":[
        "operation"
    ],
    "wof:name":"Country Meadow Inn",
    "wof:placetype":"venue"
},
  "geometry": {"coordinates":[-74.94520900000001,42.590748],"type":"Point"}
}