{
  "type": "Feature",
  "properties": {
    "addr:full":"60 Sutton Place S New York NY 10022",
    "addr:housenumber":"60",
    "addr:postcode":"10022",
    "addr:street":"Sutton Place S",
    "iso:country":"US",
    "sg:address":"60 Sutton Place S",
    "sg:city":"New York",
    "sg:classifiers":[
        {
            "category":"Building & Trades",
            "subcategory":"Construction",
            "type":"Services"
        }
    ],
    "sg:phone":"+1 212 935 5004",
    "sg:postcode":"10022",
    "sg:province":"NY",
    "sg:tags":[
        "interior",
        "design"
    ],
    "wof:name":"Tom Edwards",
    "wof:placetype":"venue"
},
  "geometry": {"coordinates":[-73.962103,40.755439],"type":"Point"}
}