{
  "type": "Feature",
  "properties": {
    "iso:country":"US",
    "sg:address":"78 Brookside Ave",
    "sg:city":"Chester",
    "sg:classifiers":[
        {
            "category":"Food & Beverages",
            "subcategory":"Groceries & Convenience Stores",
            "type":"Retail Goods"
        }
    ],
    "sg:phone":"+1 845 469 2988",
    "sg:postcode":"10918",
    "sg:province":"NY",
    "sg:tags":[
        "grocer"
    ],
    "wof:name":"Big V Supermarkets Inc Dsd",
    "wof:placetype":"venue"
},
  "geometry": {"coordinates":[-74.285388,41.360543],"type":"Point"}
}