{
  "type": "Feature",
  "properties": {
    "iso:country":"US",
    "sg:address":"250 Lambert Ave",
    "sg:city":"Copiague",
    "sg:classifiers":[
        {
            "category":"Professional",
            "subcategory":"Business Services",
            "type":"Services"
        }
    ],
    "sg:phone":"+1 631 226 3266",
    "sg:postcode":"11726",
    "sg:province":"NY",
    "sg:tags":[
        "stationery",
        "grocery"
    ],
    "wof:name":"TRC Systems Incorporated",
    "wof:placetype":"venue"
},
  "geometry": {"coordinates":[-73.390666,40.680949],"type":"Point"}
}