{
  "type": "Feature",
  "properties": {
    "iso:country":"US",
    "sg:address":"5353 Kings Hwy",
    "sg:city":"Brooklyn",
    "sg:classifiers":[
        {
            "category":"Health Services",
            "subcategory":"Doctor",
            "type":"Services"
        }
    ],
    "sg:phone":"+1 718 739 5200",
    "sg:postcode":"11203",
    "sg:province":"NY",
    "sg:tags":[
        "residential",
        "medical",
        "care"
    ],
    "wof:name":"King Solomon Manor",
    "wof:placetype":"venue"
},
  "geometry": {"coordinates":[-73.925748,40.639473],"type":"Point"}
}