{
  "type": "Feature",
  "properties": {
    "iso:country":"US",
    "sg:address":"73 Pleasant St",
    "sg:city":"Monticello",
    "sg:classifiers":[
        {
            "category":"Wholesale",
            "subcategory":"Seafood",
            "type":"Manufacturing & Wholesale Goods"
        }
    ],
    "sg:phone":"+1 845 791 4345",
    "sg:postcode":"12701",
    "sg:province":"NY",
    "wof:name":"Eden Brook Fish Company",
    "wof:placetype":"venue"
},
  "geometry": {"coordinates":[-74.680367,41.658278],"type":"Point"}
}