{
  "type": "Feature",
  "properties": {
    "iso:country":"US",
    "sg:address":"301 E Shore Rd",
    "sg:city":"Great Neck",
    "sg:classifiers":[
        {
            "category":"Health Services",
            "subcategory":"Doctor",
            "type":"Services"
        }
    ],
    "sg:phone":"+1 516 352 9682",
    "sg:postcode":"11023",
    "sg:province":"NY",
    "sg:tags":[
        "physician",
        "surgeon"
    ],
    "sg:website":"www.surgerycare.org",
    "wof:name":"North Shore Surgical Spclsts",
    "wof:placetype":"venue"
},
  "geometry": {"coordinates":[-73.71376100000001,40.79906],"type":"Point"}
}