{
  "type": "Feature",
  "properties": {
    "iso:country":"US",
    "sg:address":"280 Middle Country Rd",
    "sg:city":"Selden",
    "sg:classifiers":[
        {
            "category":"Shopping",
            "type":"Retail Goods"
        }
    ],
    "sg:phone":"+1 631 732 5556",
    "sg:postcode":"11784",
    "sg:province":"NY",
    "sg:tags":[
        "orthopedic",
        "appliance"
    ],
    "wof:name":"Progressive Orthotics LTD",
    "wof:placetype":"venue"
},
  "geometry": {"coordinates":[-73.032422,40.866873],"type":"Point"}
}