{
  "type": "Feature",
  "properties": {
    "addr:full":"6 Myers Ave Yorkville NY 13495",
    "addr:housenumber":"6",
    "addr:postcode":"13495",
    "addr:street":"Myers Ave",
    "iso:country":"US",
    "sg:address":"6 Myers Ave",
    "sg:city":"Yorkville",
    "sg:classifiers":[
        {
            "category":"Shopping",
            "subcategory":"Florist",
            "type":"Retail Goods"
        }
    ],
    "sg:phone":"+1 315 736 8606",
    "sg:postcode":"13495",
    "sg:province":"NY",
    "wof:name":"Flowers By John And Linda Inc",
    "wof:placetype":"venue"
},
  "geometry": {"coordinates":[-75.27130099999999,43.11187],"type":"Point"}
}