{
  "type": "Feature",
  "properties": {
    "addr:full":"1601 Surf Ave Brooklyn NY 11224",
    "addr:housenumber":"1601",
    "addr:postcode":"11224",
    "addr:street":"Surf Ave",
    "iso:country":"US",
    "sg:address":"1601 Surf Ave",
    "sg:city":"Brooklyn",
    "sg:classifiers":[
        {
            "category":"Retail",
            "subcategory":"Auto Rental",
            "type":"Services"
        }
    ],
    "sg:phone":"+1 718 676 6245",
    "sg:postcode":"11224",
    "sg:province":"NY",
    "sg:tags":[
        "car"
    ],
    "sg:website":"www.skylinecarrental.com",
    "wof:name":"Skyline Car Rental",
    "wof:placetype":"venue"
},
  "geometry": {"coordinates":[-73.983456,40.575596],"type":"Point"}
}