{
  "type": "Feature",
  "properties": {
    "iso:country":"US",
    "sg:address":"2 W 29th St",
    "sg:city":"New York",
    "sg:classifiers":[
        {
            "category":"Retail",
            "subcategory":"Repair Shop",
            "type":"Services"
        }
    ],
    "sg:phone":"+1 212 897 4626",
    "sg:postcode":"10001",
    "sg:province":"NY",
    "sg:tags":[
        "lock",
        "locksmith"
    ],
    "wof:name":"24 Hour 7 Days Emergency Tow",
    "wof:placetype":"venue"
},
  "geometry": {"coordinates":[-73.988592,40.746036],"type":"Point"}
}