{
  "type": "Feature",
  "properties": {
    "addr:full":"9 Neil Ct Oceanside NY 11572",
    "addr:housenumber":"9",
    "addr:postcode":"11572",
    "addr:street":"Neil Ct",
    "iso:country":"US",
    "sg:address":"9 Neil Ct",
    "sg:city":"Oceanside",
    "sg:classifiers":[
        {
            "category":"Professional",
            "type":"Services"
        }
    ],
    "sg:phone":"+1 631 661 2888",
    "sg:postcode":"11572",
    "sg:province":"NY",
    "sg:tags":[
        "establishment"
    ],
    "wof:name":"Three Feet Off",
    "wof:placetype":"venue"
},
  "geometry": {"coordinates":[-73.632811,40.623558],"type":"Point"}
}