{
  "type": "Feature",
  "properties": {
    "addr:full":"341 Somerville Ave Tonawanda NY 14150",
    "addr:housenumber":"341",
    "addr:postcode":"14150",
    "addr:street":"Somerville Ave",
    "iso:country":"US",
    "sg:address":"341 Somerville Ave",
    "sg:city":"Tonawanda",
    "sg:classifiers":[
        {
            "category":"Personal",
            "subcategory":"Shoe Repair & Shine",
            "type":"Services"
        }
    ],
    "sg:phone":"+1 716 835 5944",
    "sg:postcode":"14150",
    "sg:province":"NY",
    "sg:tags":[
        "repairing",
        "boot"
    ],
    "wof:name":"Steve's Shoe Repair",
    "wof:placetype":"venue"
},
  "geometry": {"coordinates":[-78.837807,42.990828],"type":"Point"}
}