{
  "type": "Feature",
  "properties": {
    "addr:full":"22 Chatham St Kinderhook NY 12106",
    "addr:housenumber":"22",
    "addr:postcode":"12106",
    "addr:street":"Chatham St",
    "iso:country":"US",
    "sg:address":"22 Chatham St",
    "sg:city":"Kinderhook",
    "sg:classifiers":[
        {
            "category":"Retail",
            "subcategory":"Auto Repair",
            "type":"Services"
        }
    ],
    "sg:phone":"+1 518 758 2767",
    "sg:postcode":"12106",
    "sg:province":"NY",
    "sg:tags":[
        "body",
        "automobile",
        "painting"
    ],
    "wof:name":"Trombley's Autobody & Repair",
    "wof:placetype":"venue"
},
  "geometry": {"coordinates":[-73.69736399999999,42.395879],"type":"Point"}
}