{
  "type": "Feature",
  "properties": {
    "addr:full":"952 Flushing Ave Brooklyn NY 11206",
    "addr:housenumber":"952",
    "addr:postcode":"11206",
    "addr:street":"Flushing Ave",
    "iso:country":"US",
    "sg:address":"952 Flushing Ave",
    "sg:city":"Brooklyn",
    "sg:classifiers":[
        {
            "category":"Professional",
            "subcategory":"Management & Consulting",
            "type":"Services"
        }
    ],
    "sg:phone":"+1 718 386 8254",
    "sg:postcode":"11206",
    "sg:province":"NY",
    "sg:tags":[
        "consultant",
        "business"
    ],
    "wof:name":"Utilities Consultants",
    "wof:placetype":"venue"
},
  "geometry": {"coordinates":[-73.932976,40.702943],"type":"Point"}
}