{
  "type": "Feature",
  "properties": {
    "addr:full":"50 Rockefeller Plz New York NY 10020",
    "addr:housenumber":"50",
    "addr:postcode":"10020",
    "addr:street":"Rockefeller Plz",
    "iso:country":"US",
    "sg:address":"50 Rockefeller Plz",
    "sg:city":"New York",
    "sg:classifiers":[
        {
            "category":"Building & Trades",
            "subcategory":"Cleaning & Sanitation",
            "type":"Services"
        }
    ],
    "sg:phone":"+1 212 632 5220",
    "sg:postcode":"10020",
    "sg:province":"NY",
    "sg:tags":[
        "maintenance"
    ],
    "wof:name":"Nastasi Maintenance LLC",
    "wof:placetype":"venue"
},
  "geometry": {"coordinates":[-73.978229,40.759414],"type":"Point"}
}