{
  "type": "Feature",
  "properties": {
    "iso:country":"US",
    "sg:address":"1060 Central Ave",
    "sg:city":"Albany",
    "sg:classifiers":[
        {
            "category":"Manufacturing",
            "subcategory":"Metals",
            "type":"Manufacturing & Wholesale Goods"
        }
    ],
    "sg:phone":"+1 518 459 6100",
    "sg:postcode":"12205",
    "sg:province":"NY",
    "sg:tags":[
        "pipe",
        "fitting",
        "valve"
    ],
    "wof:name":"Mechanical Pipe & Supply Corp",
    "wof:placetype":"venue"
},
  "geometry": {"coordinates":[-73.79772699999999,42.686565],"type":"Point"}
}