{
  "type": "Feature",
  "properties": {
    "addr:full":"3239 Westchester Ave Bronx NY 10461",
    "addr:housenumber":"3239",
    "addr:postcode":"10461",
    "addr:street":"Westchester Ave",
    "iso:country":"US",
    "sg:address":"3239 Westchester Ave",
    "sg:city":"Bronx",
    "sg:classifiers":[
        {
            "category":"Home & Garden",
            "subcategory":"Building Materials",
            "type":"Retail Goods"
        }
    ],
    "sg:phone":"+1 718 828 2402",
    "sg:postcode":"10461",
    "sg:province":"NY",
    "sg:tags":[
        "paint"
    ],
    "wof:name":"North Bronx Paint & Hardware",
    "wof:placetype":"venue"
},
  "geometry": {"coordinates":[-73.828947,40.852114],"type":"Point"}
}