{
  "type": "Feature",
  "properties": {
    "iso:country":"US",
    "sg:address":"1717 Fulton Ave",
    "sg:city":"Bronx",
    "sg:classifiers":[
        {
            "category":"Professional",
            "subcategory":"Engineering",
            "type":"Services"
        }
    ],
    "sg:phone":"+1   ",
    "sg:postcode":"10457",
    "sg:province":"NY",
    "wof:name":"Oestreicher Mark PS 171",
    "wof:placetype":"venue"
},
  "geometry": {"coordinates":[-73.896778,40.843459],"type":"Point"}
}