{
  "type": "Feature",
  "properties": {
    "addr:full":"12 N Broadway Yonkers NY 10701",
    "addr:housenumber":"12",
    "addr:postcode":"10701",
    "addr:street":"N Broadway",
    "iso:country":"US",
    "sg:address":"12 N Broadway",
    "sg:city":"Yonkers",
    "sg:classifiers":[
        {
            "category":"Real Estate",
            "subcategory":"Architect",
            "type":"Services"
        }
    ],
    "sg:phone":"+1 914 964 9776",
    "sg:postcode":"10701",
    "sg:province":"NY",
    "wof:name":"Steven M Asaro Architect",
    "wof:placetype":"venue"
},
  "geometry": {"coordinates":[-73.897936,40.933758],"type":"Point"}
}