{
  "type": "Feature",
  "properties": {
    "addr:full":"2271 Broadway New York NY 10024",
    "addr:housenumber":"2271",
    "addr:postcode":"10024",
    "addr:street":"Broadway",
    "iso:country":"US",
    "sg:address":"2271 Broadway",
    "sg:city":"New York",
    "sg:classifiers":[
        {
            "category":"Shopping",
            "subcategory":"Clothing, Apparel, & Fashions",
            "type":"Retail Goods"
        }
    ],
    "sg:phone":"+1 212 595 9071",
    "sg:postcode":"10024",
    "sg:province":"NY",
    "sg:tags":[
        "children's",
        "clothing"
    ],
    "sg:website":"www.gymboree.com",
    "wof:name":"Gymboree",
    "wof:placetype":"venue"
},
  "geometry": {"coordinates":[-73.978996,40.785599],"type":"Point"}
}