{
  "type": "Feature",
  "properties": {
    "addr:full":"387 7th Ave Brooklyn NY 11215",
    "addr:housenumber":"387",
    "addr:postcode":"11215",
    "addr:street":"7Th Ave",
    "iso:country":"US",
    "sg:address":"387 7th Ave",
    "sg:city":"Brooklyn",
    "sg:classifiers":[
        {
            "category":"Home & Garden",
            "subcategory":"Household Appliances",
            "type":"Retail Goods"
        }
    ],
    "sg:phone":"+1 718 832 0060",
    "sg:postcode":"11215",
    "sg:province":"NY",
    "sg:website":"www.brookesewvac.com/",
    "wof:name":"Brooke Vacuums and Appliances",
    "wof:placetype":"venue"
},
  "geometry": {"coordinates":[-73.98300999999999,40.665174],"type":"Point"}
}