{
  "type": "Feature",
  "properties": {
    "addr:full":"19 Tuckahoe Rd Yonkers NY 10710",
    "addr:housenumber":"19",
    "addr:postcode":"10710",
    "addr:street":"Tuckahoe Rd",
    "iso:country":"US",
    "sg:address":"19 Tuckahoe Rd",
    "sg:city":"Yonkers",
    "sg:classifiers":[
        {
            "category":"Food & Beverages",
            "subcategory":"Groceries & Convenience Stores",
            "type":"Retail Goods"
        }
    ],
    "sg:phone":"+1 914 423 5812",
    "sg:postcode":"10710",
    "sg:province":"NY",
    "sg:tags":[
        "grocer"
    ],
    "wof:name":"All Indian Grocery",
    "wof:placetype":"venue"
},
  "geometry": {"coordinates":[-73.871028,40.955808],"type":"Point"}
}