{
  "type": "Feature",
  "properties": {
    "addr:full":"607 Fulton Ave Hempstead NY 11550",
    "addr:housenumber":"607",
    "addr:postcode":"11550",
    "addr:street":"Fulton Ave",
    "iso:country":"US",
    "sg:address":"607 Fulton Ave",
    "sg:city":"Hempstead",
    "sg:classifiers":[
        {
            "category":"Health Services",
            "subcategory":"Doctor",
            "type":"Services"
        }
    ],
    "sg:phone":"+1 516 489 4120",
    "sg:postcode":"11550",
    "sg:province":"NY",
    "wof:name":"Shah Mahesh",
    "wof:placetype":"venue"
},
  "geometry": {"coordinates":[-73.609741,40.711909],"type":"Point"}
}