{
  "type": "Feature",
  "properties": {
    "addr:full":"4 Christopher Ave Highland NY 12528",
    "addr:housenumber":"4",
    "addr:postcode":"12528",
    "addr:street":"Christopher Ave",
    "iso:country":"US",
    "sg:address":"4 Christopher Ave",
    "sg:city":"Highland",
    "sg:classifiers":[
        {
            "category":"Shopping",
            "subcategory":"Hobbies, Toys, & Games",
            "type":"Retail Goods"
        }
    ],
    "sg:phone":"+1   ",
    "sg:postcode":"12528",
    "sg:province":"NY",
    "wof:name":"Hands On Arts & Crafts",
    "wof:placetype":"venue"
},
  "geometry": {"coordinates":[-73.958955,41.719059],"type":"Point"}
}