{
  "type": "Feature",
  "properties": {
    "addr:full":"750 Union St Hudson NY 12534",
    "addr:housenumber":"750",
    "addr:postcode":"12534",
    "addr:street":"Union St",
    "iso:country":"US",
    "sg:address":"750 Union St",
    "sg:city":"Hudson",
    "sg:classifiers":[
        {
            "category":"Banks & Credit Unions",
            "subcategory":"Bank",
            "type":"Services"
        }
    ],
    "sg:phone":"+1 518 828 0185",
    "sg:postcode":"12534",
    "sg:province":"NY",
    "sg:tags":[
        "loan",
        "real estate"
    ],
    "sg:website":"www.valleymortgage.com",
    "wof:name":"Valley Mortgage Co",
    "wof:placetype":"venue"
},
  "geometry": {"coordinates":[-73.783652,42.246099],"type":"Point"}
}