{
  "type": "Feature",
  "properties": {
    "iso:country":"US",
    "sg:address":"30 Columbus Blvd",
    "sg:city":"Amityville",
    "sg:classifiers":[
        {
            "category":"Health Services",
            "subcategory":"Clinic",
            "type":"Services"
        }
    ],
    "sg:phone":"+1 631 789 6561",
    "sg:postcode":"11701",
    "sg:province":"NY",
    "sg:tags":[
        "home"
    ],
    "wof:name":"Odara Home Health Care Agency",
    "wof:placetype":"venue"
},
  "geometry": {"coordinates":[-73.414691,40.704131],"type":"Point"}
}