{
  "type": "Feature",
  "properties": {
    "addr:full":"130 John St Hauppauge NY 11788",
    "addr:housenumber":"130",
    "addr:postcode":"11788",
    "addr:street":"John St",
    "iso:country":"US",
    "sg:address":"130 John St",
    "sg:city":"Hauppauge",
    "sg:classifiers":[
        {
            "category":"Wholesale",
            "subcategory":"Chemicals & Plastics",
            "type":"Manufacturing & Wholesale Goods"
        }
    ],
    "sg:phone":"+1 631 979 6783",
    "sg:postcode":"11788",
    "sg:province":"NY",
    "wof:name":"Ade Intl Corp",
    "wof:placetype":"venue"
},
  "geometry": {"coordinates":[-73.19334600000001,40.822741],"type":"Point"}
}