{
  "type": "Feature",
  "properties": {
    "addr:full":"1400 Winton Rd N Rochester NY 14609",
    "addr:housenumber":"1400",
    "addr:postcode":"14609",
    "addr:street":"Winton Rd N",
    "iso:country":"US",
    "sg:address":"1400 Winton Rd N",
    "sg:city":"Rochester",
    "sg:classifiers":[
        {
            "category":"Organizations",
            "subcategory":"Professional Association",
            "type":"Services"
        }
    ],
    "sg:phone":"+1 585 288 1950",
    "sg:postcode":"14609",
    "sg:province":"NY",
    "sg:website":"www.cancer.org",
    "wof:name":"American Cancer Society",
    "wof:placetype":"venue"
},
  "geometry": {"coordinates":[-77.54055099999999,43.172806],"type":"Point"}
}