{
  "type": "Feature",
  "properties": {
    "addr:full":"90 Myrtle Ave Mahopac NY 10541",
    "addr:housenumber":"90",
    "addr:postcode":"10541",
    "addr:street":"Myrtle Ave",
    "iso:country":"US",
    "sg:address":"90 Myrtle Ave",
    "sg:city":"Mahopac",
    "sg:classifiers":[
        {
            "category":"Organizations",
            "subcategory":"Labor Organization",
            "type":"Services"
        }
    ],
    "sg:phone":"+1 845 628 6435",
    "sg:postcode":"10541",
    "sg:province":"NY",
    "wof:name":"United School Workers Of Maho",
    "wof:placetype":"venue"
},
  "geometry": {"coordinates":[-73.761994,41.360123],"type":"Point"}
}