{
  "type": "Feature",
  "properties": {
    "addr:full":"595 North Ave New Rochelle NY 10801",
    "addr:housenumber":"595",
    "addr:postcode":"10801",
    "addr:street":"North Ave",
    "iso:country":"US",
    "sg:address":"595 North Ave",
    "sg:city":"New Rochelle",
    "sg:classifiers":[
        {
            "category":"Personal",
            "subcategory":"Beauty Salon",
            "type":"Services"
        }
    ],
    "sg:phone":"+1 914 636 3150",
    "sg:postcode":"10801",
    "sg:province":"NY",
    "wof:name":"New Day Salon",
    "wof:placetype":"venue"
},
  "geometry": {"coordinates":[-73.787836,40.922759],"type":"Point"}
}