{
  "type": "Feature",
  "properties": {
    "addr:full":"122 W 27th St Fl 4 New York NY 10001",
    "addr:housenumber":"122;4",
    "addr:postcode":"10001",
    "addr:street":"W 27Th St",
    "iso:country":"US",
    "sg:address":"122 W 27th St Fl 4",
    "sg:city":"New York",
    "sg:classifiers":[
        {
            "category":"Real Estate",
            "subcategory":"Architect",
            "type":"Services"
        }
    ],
    "sg:phone":"+1 212 366 5654",
    "sg:postcode":"10001",
    "sg:province":"NY",
    "wof:name":"Howell Belanger Castelli Architects Inc",
    "wof:placetype":"venue"
},
  "geometry": {"coordinates":[-73.991668,40.745565],"type":"Point"}
}