{
  "type": "Feature",
  "properties": {
    "iso:country":"US",
    "sg:address":"52 Duane St",
    "sg:city":"New York",
    "sg:classifiers":[
        {
            "category":"Professional",
            "subcategory":"Lawyer & Legal Services",
            "type":"Services"
        }
    ],
    "sg:phone":"+1 212 732 6000",
    "sg:postcode":"10007",
    "sg:province":"NY",
    "sg:tags":[
        "attorney"
    ],
    "wof:name":"Mc Carthy & Kelly LLP",
    "wof:placetype":"venue"
},
  "geometry": {"coordinates":[-74.003778,40.714248],"type":"Point"}
}