{
  "type": "Feature",
  "properties": {
    "iso:country":"US",
    "sg:address":"14708 Hillside Avenue",
    "sg:city":"Jamaica",
    "sg:classifiers":[
        {
            "category":"Banks & Credit Unions",
            "subcategory":"Financial Services",
            "type":"Services"
        }
    ],
    "sg:phone":"+1 718 297 7400",
    "sg:postcode":"11435",
    "sg:province":"NY",
    "sg:tags":[
        "broker",
        "mortgage"
    ],
    "wof:name":"Aban Realty",
    "wof:placetype":"venue"
},
  "geometry": {"coordinates":[-73.809456,40.705706],"type":"Point"}
}