{
  "type": "Feature",
  "properties": {
    "iso:country":"US",
    "sg:address":"10 N Somerset Rd",
    "sg:city":"Amityville",
    "sg:classifiers":[
        {
            "category":"Manufacturing",
            "subcategory":"Metals",
            "type":"Manufacturing & Wholesale Goods"
        }
    ],
    "sg:phone":"+1   ",
    "sg:postcode":"11701",
    "sg:province":"NY",
    "sg:tags":[
        "design",
        "furniture"
    ],
    "wof:name":"Beads By Design",
    "wof:placetype":"venue"
},
  "geometry": {"coordinates":[-73.40873999999999,40.69621],"type":"Point"}
}