{
  "type": "Feature",
  "properties": {
    "iso:country":"US",
    "sg:address":"3377 Ocean Harbor Dr",
    "sg:city":"Oceanside",
    "sg:classifiers":[
        {
            "category":"Professional",
            "subcategory":"Accounting & Tax Preparation",
            "type":"Services"
        }
    ],
    "sg:phone":"+1   ",
    "sg:postcode":"11572",
    "sg:province":"NY",
    "wof:name":"Eigen Albert CPA",
    "wof:placetype":"venue"
},
  "geometry": {"coordinates":[-73.658849,40.629071],"type":"Point"}
}