{
  "type": "Feature",
  "properties": {
    "addr:full":"E 59th St Bloomingdales New York NY 10079",
    "addr:postcode":"10079",
    "addr:street":"E 59Th St Bloomingdales",
    "iso:country":"US",
    "sg:address":"E 59th St Bloomingdales",
    "sg:city":"New York",
    "sg:classifiers":[
        {
            "category":"Shopping",
            "subcategory":"Department Store",
            "type":"Retail Goods"
        }
    ],
    "sg:postcode":"10079",
    "sg:province":"NY",
    "wof:name":"Robert Rodriguez",
    "wof:placetype":"venue"
},
  "geometry": {"coordinates":[-73.96657,40.761542],"type":"Point"}
}