{
  "type": "Feature",
  "properties": {
    "iso:country":"US",
    "sg:address":"240 Skip Ln",
    "sg:city":"Bay Shore",
    "sg:classifiers":[
        {
            "category":"Freight",
            "type":"Transportation"
        }
    ],
    "sg:phone":"+1 631 667 5656",
    "sg:postcode":"11706",
    "sg:province":"NY",
    "sg:tags":[
        "trucking"
    ],
    "sg:website":"www.overnite.com",
    "wof:name":"UPS Freight",
    "wof:placetype":"venue"
},
  "geometry": {"coordinates":[-73.284071,40.763341],"type":"Point"}
}