{
  "type": "Feature",
  "properties": {
    "iso:country":"US",
    "sg:address":"38 Dunsbach Ferry Rd",
    "sg:city":"Cohoes",
    "sg:classifiers":[
        {
            "category":"Education",
            "subcategory":"School",
            "type":"Public Place"
        }
    ],
    "sg:phone":"+1 518 785 0222",
    "sg:postcode":"12047",
    "sg:province":"NY",
    "wof:name":"Boght Hills Elementary School",
    "wof:placetype":"venue"
},
  "geometry": {"coordinates":[-73.754515,42.773769],"type":"Point"}
}