{
  "type": "Feature",
  "properties": {
    "iso:country":"US",
    "sg:address":"1622 Old Rte 22",
    "sg:city":"Brewster",
    "sg:classifiers":[
        {
            "category":"Government",
            "subcategory":"Office",
            "type":"Public Place"
        }
    ],
    "sg:phone":"+1 845 279 2905",
    "sg:postcode":"10509",
    "sg:province":"NY",
    "wof:name":"Taconic Developmental",
    "wof:placetype":"venue"
},
  "geometry": {"coordinates":[-73.58202,41.461121],"type":"Point"}
}