{
  "type": "Feature",
  "properties": {
    "iso:country":"US",
    "sg:address":"136 W 72 St",
    "sg:city":"New York",
    "sg:classifiers":[
        {
            "category":"Professional",
            "subcategory":"Computer Services",
            "type":"Services"
        }
    ],
    "sg:phone":"+1 212 769 8783",
    "sg:postcode":"10023",
    "sg:province":"NY",
    "sg:tags":[
        "website",
        "design"
    ],
    "wof:name":"Blade Media",
    "wof:placetype":"venue"
},
  "geometry": {"coordinates":[-73.98087200000001,40.778102],"type":"Point"}
}