{
  "type": "Feature",
  "properties": {
    "addr:full":"717 Vincent Ave Bronx NY 10465",
    "addr:housenumber":"717",
    "addr:postcode":"10465",
    "addr:street":"Vincent Ave",
    "iso:country":"US",
    "sg:address":"717 Vincent Ave",
    "sg:city":"Bronx",
    "sg:classifiers":[
        {
            "category":"Wholesale",
            "subcategory":"Motor Vehicles",
            "type":"Manufacturing & Wholesale Goods"
        }
    ],
    "sg:phone":"+1 718 794 3549",
    "sg:postcode":"10465",
    "sg:province":"NY",
    "sg:tags":[
        "automobile",
        "dealer"
    ],
    "wof:name":"Congers Auto Sales Inc",
    "wof:placetype":"venue"
},
  "geometry": {"coordinates":[-73.817972,40.830212],"type":"Point"}
}