{
  "type": "Feature",
  "properties": {
    "iso:country":"US",
    "sg:address":"2201 Neptune Ave Ste 4",
    "sg:city":"Brooklyn",
    "sg:classifiers":[
        {
            "category":"Manufacturing",
            "subcategory":"Buildings",
            "type":"Manufacturing & Wholesale Goods"
        },
        {
            "category":"Building & Trades",
            "subcategory":"Construction",
            "type":"Services"
        }
    ],
    "sg:phone":"+1 718 265 9358",
    "sg:postcode":"11224",
    "sg:province":"NY",
    "sg:tags":[
        "home",
        "builder",
        "industrial",
        "contractors-commercial",
        "contractor"
    ],
    "sg:website":"http://www.omnibuilding.com",
    "wof:name":"Omni Build, Inc.",
    "wof:placetype":"venue"
},
  "geometry": {"coordinates":[-73.98947099999999,40.57848],"type":"Point"}
}