{
  "type": "Feature",
  "properties": {
    "addr:full":"295 Middle Island Rd Medford NY 11763",
    "addr:housenumber":"295",
    "addr:postcode":"11763",
    "addr:street":"Middle Island Rd",
    "iso:country":"US",
    "sg:address":"295 Middle Island Rd",
    "sg:city":"Medford",
    "sg:classifiers":[
        {
            "category":"Building & Trades",
            "subcategory":"Construction",
            "type":"Services"
        }
    ],
    "sg:phone":"+1 631 696 0066",
    "sg:postcode":"11763",
    "sg:province":"NY",
    "sg:tags":[
        "steel",
        "structural",
        "welding",
        "contractor"
    ],
    "wof:name":"B & J Welding",
    "wof:placetype":"venue"
},
  "geometry": {"coordinates":[-72.98707400000001,40.846893],"type":"Point"}
}