{
  "type": "Feature",
  "properties": {
    "addr:full":"21 Perry Rd Hyde Park NY 12518",
    "addr:housenumber":"21",
    "addr:postcode":"12518",
    "addr:street":"Perry Rd",
    "iso:country":"US",
    "sg:address":"21 Perry Rd",
    "sg:city":"Hyde Park",
    "sg:classifiers":[
        {
            "category":"Building & Trades",
            "subcategory":"Construction",
            "type":"Services"
        }
    ],
    "sg:phone":"+1 845 225 3962",
    "sg:postcode":"12518",
    "sg:province":"NY",
    "sg:tags":[
        "house"
    ],
    "wof:name":"Shay Builders LLC",
    "wof:placetype":"venue"
},
  "geometry": {"coordinates":[-74.036053,41.44151],"type":"Point"}
}