{
  "type": "Feature",
  "properties": {
    "addr:full":"1917 Co Rd 9 Chatham NY 12037",
    "addr:housenumber":"1917",
    "addr:postcode":"12037",
    "addr:street":"Co Rd 9",
    "iso:country":"US",
    "sg:address":"1917 Co Rd 9",
    "sg:city":"Chatham",
    "sg:classifiers":[
        {
            "category":"Shopping",
            "subcategory":"Gifts & Souvenirs",
            "type":"Retail Goods"
        }
    ],
    "sg:phone":"+1   ",
    "sg:postcode":"12037",
    "sg:province":"NY",
    "wof:name":"N & S This & That",
    "wof:placetype":"venue"
},
  "geometry": {"coordinates":[-73.553226,42.355679],"type":"Point"}
}