{
  "type": "Feature",
  "properties": {
    "iso:country":"US",
    "sg:address":"1917 Co Rd 9",
    "sg:city":"Chatham",
    "sg:classifiers":[
        {
            "category":"Shopping",
            "subcategory":"Gifts & Souvenirs",
            "type":"Retail Goods"
        }
    ],
    "sg:phone":"+1   ",
    "sg:postcode":"12037",
    "sg:province":"NY",
    "wof:name":"N & S This & That",
    "wof:placetype":"venue"
},
  "geometry": {"coordinates":[-73.553226,42.355679],"type":"Point"}
}