{
  "type": "Feature",
  "properties": {
    "addr:full":"18730 Linden Blvd Saint Albans NY 11412",
    "addr:housenumber":"18730",
    "addr:postcode":"11412",
    "addr:street":"Linden Blvd",
    "iso:country":"US",
    "sg:address":"18730 Linden Blvd",
    "sg:city":"Saint Albans",
    "sg:classifiers":[
        {
            "category":"Social Services",
            "subcategory":"Child Care",
            "type":"Services"
        }
    ],
    "sg:phone":"+1 718 276 4800",
    "sg:postcode":"11412",
    "sg:province":"NY",
    "sg:tags":[
        "day"
    ],
    "wof:name":"Evangelism Media",
    "wof:placetype":"venue"
},
  "geometry": {"coordinates":[-73.764121,40.691751],"type":"Point"}
}