{
  "type": "Feature",
  "properties": {
    "addr:full":"89 West Ave Canandaigua NY 14424",
    "addr:housenumber":"89",
    "addr:postcode":"14424",
    "addr:street":"West Ave",
    "iso:country":"US",
    "sg:address":"89 West Ave",
    "sg:city":"Canandaigua",
    "sg:classifiers":[
        {
            "category":"Retail",
            "subcategory":"Auto Repair",
            "type":"Services"
        }
    ],
    "sg:phone":"+1 585 396 0550",
    "sg:postcode":"14424",
    "sg:province":"NY",
    "sg:tags":[
        "repairing",
        "shop",
        "general",
        "automotive",
        "automobile"
    ],
    "wof:name":"Palmer Automotive Inc",
    "wof:placetype":"venue"
},
  "geometry": {"coordinates":[-77.28516999999999,42.886359],"type":"Point"}
}