{
  "type": "Feature",
  "properties": {
    "addr:full":"4000 River Rd Tonawanda NY 14150",
    "addr:housenumber":"4000",
    "addr:postcode":"14150",
    "addr:street":"River Rd",
    "iso:country":"US",
    "sg:address":"4000 River Rd",
    "sg:city":"Tonawanda",
    "sg:classifiers":[
        {
            "category":"Autos & Motor Vehicles",
            "subcategory":"Auto Supplies",
            "type":"Retail Goods"
        },
        {
            "category":"Retail",
            "subcategory":"Storage",
            "type":"Services"
        }
    ],
    "sg:phone":"+1 716 877 1126",
    "sg:postcode":"14150",
    "sg:province":"NY",
    "sg:tags":[
        "automobile",
        "self",
        "part",
        "accessory"
    ],
    "sg:website":"http://www.ajaxsmith.com",
    "wof:name":"Ajax-Smith Inc",
    "wof:placetype":"venue"
},
  "geometry": {"coordinates":[-78.934738,42.980683],"type":"Point"}
}