{
  "type": "Feature",
  "properties": {
    "iso:country":"US",
    "sg:address":"1395 Nostrand Ave",
    "sg:city":"Brooklyn",
    "sg:classifiers":[
        {
            "category":"Shopping",
            "subcategory":"Music",
            "type":"Retail Goods"
        }
    ],
    "sg:phone":"+1   ",
    "sg:postcode":"11226",
    "sg:province":"NY",
    "wof:name":"Alpha Records Store",
    "wof:placetype":"venue"
},
  "geometry": {"coordinates":[-73.94960399999999,40.651829],"type":"Point"}
}