{
  "type": "Feature",
  "properties": {
    "addr:full":"6 Cedarfield Ct Southampton NY 11968",
    "addr:housenumber":"6",
    "addr:postcode":"11968",
    "addr:street":"Cedarfield Ct",
    "iso:country":"US",
    "sg:address":"6 Cedarfield Ct",
    "sg:city":"Southampton",
    "sg:classifiers":[
        {
            "category":"Professional",
            "type":"Services"
        }
    ],
    "sg:phone":"+1 631 204 9402",
    "sg:postcode":"11968",
    "sg:province":"NY",
    "sg:tags":[
        "establishment"
    ],
    "wof:name":"Choral Society Of The Hamptons",
    "wof:placetype":"venue"
},
  "geometry": {"coordinates":[-72.40179999999999,40.945185],"type":"Point"}
}