{
  "type": "Feature",
  "properties": {
    "addr:full":"1717 Ridge Rd Webster NY 14580",
    "addr:housenumber":"1717",
    "addr:postcode":"14580",
    "addr:street":"Ridge Rd",
    "iso:country":"US",
    "sg:address":"1717 Ridge Rd",
    "sg:city":"Webster",
    "sg:classifiers":[
        {
            "category":"Wholesale",
            "subcategory":"Farm Supplies",
            "type":"Manufacturing & Wholesale Goods"
        }
    ],
    "sg:phone":"+1 585 265 0877",
    "sg:postcode":"14580",
    "sg:province":"NY",
    "sg:tags":[
        "livestock"
    ],
    "wof:name":"Dnm Farms",
    "wof:placetype":"venue"
},
  "geometry": {"coordinates":[-77.38642299999999,43.221249],"type":"Point"}
}