{
  "type": "Feature",
  "properties": {
    "addr:full":"93 1 Ave New York NY 10003",
    "addr:postcode":"10003",
    "addr:street":"93 1 Ave",
    "iso:country":"US",
    "sg:address":"93 1 Ave",
    "sg:city":"New York",
    "sg:classifiers":[
        {
            "category":"Restaurant",
            "type":"Food & Drink"
        }
    ],
    "sg:phone":"+1   ",
    "sg:postcode":"10003",
    "sg:province":"NY",
    "sg:tags":[
        "indian"
    ],
    "wof:name":"Royal Indian Cuisine",
    "wof:placetype":"venue"
},
  "geometry": {"coordinates":[-73.987968,40.723942],"type":"Point"}
}