{
  "type": "Feature",
  "properties": {
    "iso:country":"US",
    "sg:address":"110 Tiber Rd",
    "sg:city":"Syosset",
    "sg:classifiers":[
        {
            "category":"Professional",
            "subcategory":"Management & Consulting",
            "type":"Services"
        }
    ],
    "sg:phone":"+1   ",
    "sg:postcode":"11791",
    "sg:province":"NY",
    "wof:name":"1718 First Avenue Management",
    "wof:placetype":"venue"
},
  "geometry": {"coordinates":[-73.498294,40.847403],"type":"Point"}
}