{
  "type": "Feature",
  "properties": {
    "iso:country":"US",
    "sg:address":"405 Fair St",
    "sg:city":"Carmel",
    "sg:classifiers":[
        {
            "category":"Autos & Motor Vehicles",
            "subcategory":"Automobile Sales",
            "type":"Retail Goods"
        }
    ],
    "sg:phone":"+1   ",
    "sg:postcode":"10512",
    "sg:province":"NY",
    "sg:tags":[
        "used"
    ],
    "wof:name":"Joseph Tanzi Inc Honda Cars",
    "wof:placetype":"venue"
},
  "geometry": {"coordinates":[-73.644464,41.447064],"type":"Point"}
}