{
  "type": "Feature",
  "properties": {
    "addr:full":"980 Edgewood Ave Rochester NY 14618",
    "addr:housenumber":"980",
    "addr:postcode":"14618",
    "addr:street":"Edgewood Ave",
    "iso:country":"US",
    "sg:address":"980 Edgewood Ave",
    "sg:city":"Rochester",
    "sg:classifiers":[
        {
            "category":"Real Estate",
            "subcategory":"Real Estate Agent",
            "type":"Services"
        }
    ],
    "sg:phone":"+1 585 461 2043",
    "sg:postcode":"14618",
    "sg:province":"NY",
    "wof:name":"Sprague Arnie Realtor",
    "wof:placetype":"venue"
},
  "geometry": {"coordinates":[-77.566114,43.100483],"type":"Point"}
}