{
  "type": "Feature",
  "properties": {
    "addr:full":"519 Riverside Ave Schenectady NY 12302",
    "addr:housenumber":"519",
    "addr:postcode":"12302",
    "addr:street":"Riverside Ave",
    "iso:country":"US",
    "sg:address":"519 Riverside Ave",
    "sg:city":"Schenectady",
    "sg:classifiers":[
        {
            "category":"Shopping",
            "subcategory":"Gifts & Souvenirs",
            "type":"Retail Goods"
        }
    ],
    "sg:phone":"+1   ",
    "sg:postcode":"12302",
    "sg:province":"NY",
    "wof:name":"Gifts of Flavor",
    "wof:placetype":"venue"
},
  "geometry": {"coordinates":[-73.974475,42.826512],"type":"Point"}
}