{
  "type": "Feature",
  "properties": {
    "addr:full":"9202 3rd Ave Brooklyn NY 11209",
    "addr:housenumber":"9202",
    "addr:postcode":"11209",
    "addr:street":"3Rd Ave",
    "iso:country":"US",
    "sg:address":"9202 3rd Ave",
    "sg:city":"Brooklyn",
    "sg:classifiers":[
        {
            "category":"Utilities",
            "subcategory":"Mobile Phone",
            "type":"Services"
        },
        {
            "category":"Coffee & Tea",
            "type":"Food & Drink"
        }
    ],
    "sg:phone":"+1 718 492 7395",
    "sg:postcode":"11209",
    "sg:province":"NY",
    "sg:tags":[
        "shop",
        "wi-fi",
        "espresso",
        "hotspot",
        "restaurant"
    ],
    "sg:website":"http://www.starbuckscoffee.com",
    "wof:name":"Starbucks Coffee",
    "wof:placetype":"venue"
},
  "geometry": {"coordinates":[-74.03278400000001,40.61927],"type":"Point"}
}