{
  "type": "Feature",
  "properties": {
    "addr:full":"1632 York Ave New York NY 10028",
    "addr:housenumber":"1632",
    "addr:postcode":"10028",
    "addr:street":"York Ave",
    "iso:country":"US",
    "sg:address":"1632 York Ave",
    "sg:city":"New York",
    "sg:classifiers":[
        {
            "category":"Professional",
            "type":"Services"
        }
    ],
    "sg:phone":"+1 212 427 0722",
    "sg:postcode":"10028",
    "sg:province":"NY",
    "sg:tags":[
        "caterer"
    ],
    "wof:name":"In House Catering",
    "wof:placetype":"venue"
},
  "geometry": {"coordinates":[-73.946961,40.775669],"type":"Point"}
}