{
  "type": "Feature",
  "properties": {
    "addr:full":"189 Main St Oneonta NY 13820",
    "addr:housenumber":"189",
    "addr:postcode":"13820",
    "addr:street":"Main St",
    "iso:country":"US",
    "sg:address":"189 Main St",
    "sg:city":"Oneonta",
    "sg:classifiers":[
        {
            "category":"Professional",
            "subcategory":"Lawyer & Legal Services",
            "type":"Services"
        }
    ],
    "sg:phone":"+1 607 432 0911",
    "sg:postcode":"13820",
    "sg:province":"NY",
    "sg:tags":[
        "attorney"
    ],
    "wof:name":"Schwartz Law Offices",
    "wof:placetype":"venue"
},
  "geometry": {"coordinates":[-75.062887,42.453084],"type":"Point"}
}