{
  "type": "Feature",
  "properties": {
    "addr:full":"440 W 34th Street New York NY 10001",
    "addr:housenumber":"440",
    "addr:postcode":"10001",
    "addr:street":"W 34Th Street",
    "iso:country":"US",
    "sg:address":"440 W 34th Street",
    "sg:city":"New York",
    "sg:classifiers":[
        {
            "category":"Retail",
            "subcategory":"Auto Repair",
            "type":"Services"
        }
    ],
    "sg:phone":"+1 646 237 1482",
    "sg:postcode":"10001",
    "sg:province":"NY",
    "wof:name":"Auto Repair & 24 Hrtowing",
    "wof:placetype":"venue"
},
  "geometry": {"coordinates":[-73.99782500000001,40.75401],"type":"Point"}
}