{
  "type": "Feature",
  "properties": {
    "addr:full":"4 Hidden Trl Lancaster NY 14086",
    "addr:housenumber":"4",
    "addr:postcode":"14086",
    "addr:street":"Hidden Trl",
    "iso:country":"US",
    "sg:address":"4 Hidden Trl",
    "sg:city":"Lancaster",
    "sg:classifiers":[
        {
            "category":"Organizations",
            "subcategory":"Religious Organization",
            "type":"Services"
        }
    ],
    "sg:phone":"+1 716 684 7440",
    "sg:postcode":"14086",
    "sg:province":"NY",
    "sg:tags":[
        "clergy"
    ],
    "wof:name":"Kowalski M",
    "wof:placetype":"venue"
},
  "geometry": {"coordinates":[-78.66784,42.880921],"type":"Point"}
}