{
  "type": "Feature",
  "properties": {
    "addr:full":"306 W 54th Street New York NY 10019",
    "addr:housenumber":"306",
    "addr:postcode":"10019",
    "addr:street":"W 54Th Street",
    "iso:country":"US",
    "sg:address":"306 W 54th Street",
    "sg:city":"New York",
    "sg:classifiers":[
        {
            "category":"Government",
            "subcategory":"City Hall",
            "type":"Public Place"
        }
    ],
    "sg:phone":"+1 212 767 8400",
    "sg:postcode":"10019",
    "sg:province":"NY",
    "wof:name":"NYPD Midtown North",
    "wof:placetype":"venue"
},
  "geometry": {"coordinates":[-73.985108,40.764914],"type":"Point"}
}