{
  "type": "Feature",
  "properties": {
    "iso:country":"US",
    "sg:address":"198 Anderson Rd",
    "sg:city":"Plattsburgh",
    "sg:classifiers":[
        {
            "category":"Building & Trades",
            "subcategory":"Construction",
            "type":"Services"
        }
    ],
    "sg:phone":"+1 518 563 1973",
    "sg:postcode":"12901",
    "sg:province":"NY",
    "sg:tags":[
        "residential"
    ],
    "wof:name":"Hamel Construction",
    "wof:placetype":"venue"
},
  "geometry": {"coordinates":[-73.51255399999999,44.740193],"type":"Point"}
}