{
  "type": "Feature",
  "properties": {
    "addr:full":"5391 Kings Plz Brooklyn NY 11234",
    "addr:housenumber":"5391",
    "addr:postcode":"11234",
    "addr:street":"Kings Plz",
    "iso:country":"US",
    "sg:address":"5391 Kings Plz",
    "sg:city":"Brooklyn",
    "sg:classifiers":[
        {
            "category":"Professional",
            "subcategory":"Lawyer & Legal Services",
            "type":"Services"
        }
    ],
    "sg:phone":"+1 718 252 8900",
    "sg:postcode":"11234",
    "sg:province":"NY",
    "wof:name":"Michael Matthew Jewelers Inc",
    "wof:placetype":"venue"
},
  "geometry": {"coordinates":[-73.920601,40.611301],"type":"Point"}
}