{
  "type": "Feature",
  "properties": {
    "addr:full":"317 Washington Ave Brooklyn NY 11205",
    "addr:housenumber":"317",
    "addr:postcode":"11205",
    "addr:street":"Washington Ave",
    "iso:country":"US",
    "sg:address":"317 Washington Ave",
    "sg:city":"Brooklyn",
    "sg:classifiers":[
        {
            "category":"Professional",
            "subcategory":"Business Services",
            "type":"Services"
        }
    ],
    "sg:phone":"+1 917 596 6886",
    "sg:postcode":"11205",
    "sg:province":"NY",
    "sg:tags":[
        "patent",
        "searcher"
    ],
    "wof:name":"Prodrafting",
    "wof:placetype":"venue"
},
  "geometry": {"coordinates":[-73.96579800000001,40.688529],"type":"Point"}
}