{
  "type": "Feature",
  "properties": {
    "addr:full":"755 Grand Street Brooklyn NY 11211",
    "addr:housenumber":"755",
    "addr:postcode":"11211",
    "addr:street":"Grand Street",
    "iso:country":"US",
    "sg:address":"755 Grand Street",
    "sg:city":"Brooklyn",
    "sg:classifiers":[
        {
            "category":"Personal",
            "subcategory":"Day Spa",
            "type":"Services"
        }
    ],
    "sg:phone":"+1 718 384 0444",
    "sg:postcode":"11211",
    "sg:province":"NY",
    "wof:name":"Wellness & Beauty Spa",
    "wof:placetype":"venue"
},
  "geometry": {"coordinates":[-73.942964,40.711764],"type":"Point"}
}