{
  "type": "Feature",
  "properties": {
    "addr:full":"9 N Main St East Hampton NY 11937",
    "addr:housenumber":"9",
    "addr:postcode":"11937",
    "addr:street":"N Main St",
    "iso:country":"US",
    "sg:address":"9 N Main St",
    "sg:city":"East Hampton",
    "sg:classifiers":[
        {
            "category":"Real Estate",
            "subcategory":"Real Estate Agent",
            "type":"Services"
        }
    ],
    "sg:phone":"+1 631 324 2424",
    "sg:postcode":"11937",
    "sg:province":"NY",
    "sg:website":"www.lambagency.com",
    "wof:name":"Condie Lamb Real Estate",
    "wof:placetype":"venue"
},
  "geometry": {"coordinates":[-72.184449,40.964764],"type":"Point"}
}