{
  "type": "Feature",
  "properties": {
    "addr:full":"200 Great East Neck Rd West Babylon NY 11704",
    "addr:housenumber":"200",
    "addr:postcode":"11704",
    "addr:street":"Great East Neck Rd",
    "iso:country":"US",
    "sg:address":"200 Great East Neck Rd",
    "sg:city":"West Babylon",
    "sg:classifiers":[
        {
            "category":"Organizations",
            "subcategory":"Religious Organization",
            "type":"Services"
        }
    ],
    "sg:phone":"+1 631 587 1150",
    "sg:postcode":"11704",
    "sg:province":"NY",
    "sg:tags":[
        "church"
    ],
    "wof:name":"St Nicholas Greek Orthodox Chr",
    "wof:placetype":"venue"
},
  "geometry": {"coordinates":[-73.344678,40.693152],"type":"Point"}
}