{
  "type": "Feature",
  "properties": {
    "addr:full":"1467 Bedford Avenue Brooklyn NY 11216",
    "addr:housenumber":"1467",
    "addr:postcode":"11216",
    "addr:street":"Bedford Avenue",
    "iso:country":"US",
    "sg:address":"1467 Bedford Avenue",
    "sg:city":"Brooklyn",
    "sg:classifiers":[
        {
            "category":"Real Estate",
            "subcategory":"Real Estate Services",
            "type":"Services"
        }
    ],
    "sg:phone":"+1 718 484 7664",
    "sg:postcode":"11216",
    "sg:province":"NY",
    "sg:tags":[
        "management",
        "property"
    ],
    "wof:name":"Relo Realty",
    "wof:placetype":"venue"
},
  "geometry": {"coordinates":[-73.95415800000001,40.673011],"type":"Point"}
}