{
  "type": "Feature",
  "properties": {
    "iso:country":"US",
    "sg:address":"37 Genesee St",
    "sg:city":"Avon",
    "sg:classifiers":[
        {
            "category":"Restaurant",
            "type":"Food & Drink"
        }
    ],
    "sg:phone":"+1 585 226 9319",
    "sg:postcode":"14414",
    "sg:province":"NY",
    "wof:name":"Avondale Restaurant",
    "wof:placetype":"venue"
},
  "geometry": {"coordinates":[-77.746324,42.91145],"type":"Point"}
}