{
  "type": "Feature",
  "properties": {
    "addr:full":"6 Fontaine Dr Buffalo NY 14215",
    "addr:housenumber":"6",
    "addr:postcode":"14215",
    "addr:street":"Fontaine Dr",
    "iso:country":"US",
    "sg:address":"6 Fontaine Dr",
    "sg:city":"Buffalo",
    "sg:classifiers":[
        {
            "category":"Airline",
            "type":"Transportation"
        }
    ],
    "sg:phone":"+1   ",
    "sg:postcode":"14215",
    "sg:province":"NY",
    "sg:tags":[
        "scheduled",
        "automobile",
        "air",
        "parking"
    ],
    "sg:website":"www.airportparking.com",
    "wof:name":"Sunpark Inc",
    "wof:placetype":"venue"
},
  "geometry": {"coordinates":[-78.789086,42.942414],"type":"Point"}
}