{
  "type": "Feature",
  "properties": {
    "iso:country":"US",
    "sg:address":"70 Empire Blvd",
    "sg:city":"Rochester",
    "sg:classifiers":[
        {
            "category":"Social Services",
            "type":"Services"
        }
    ],
    "sg:phone":"+1 585 381 9719",
    "sg:postcode":"14609",
    "sg:province":"NY",
    "sg:tags":[
        "counselor",
        "marriage",
        "family"
    ],
    "wof:name":"Lenor L Nesta",
    "wof:placetype":"venue"
},
  "geometry": {"coordinates":[-77.55477,43.176536],"type":"Point"}
}