{
  "type": "Feature",
  "properties": {
    "iso:country":"US",
    "sg:address":"300 Hamilton Ave",
    "sg:city":"White Plains",
    "sg:classifiers":[
        {
            "category":"Government",
            "subcategory":"Office",
            "type":"Public Place"
        }
    ],
    "sg:phone":"+1 914 428 4318",
    "sg:postcode":"10601",
    "sg:province":"NY",
    "sg:tags":[
        "federal",
        "program"
    ],
    "sg:website":"www.fda.gov",
    "wof:name":"US Food & Drug Adm",
    "wof:placetype":"venue"
},
  "geometry": {"coordinates":[-73.768615,41.033671],"type":"Point"}
}