{
  "type": "Feature",
  "properties": {
    "iso:country":"US",
    "sg:address":"422 Chambers Rd",
    "sg:city":"Horseheads",
    "sg:classifiers":[
        {
            "category":"Government",
            "subcategory":"Fire Station",
            "type":"Public Place"
        }
    ],
    "sg:phone":"+1 607 739 7415",
    "sg:postcode":"14845",
    "sg:province":"NY",
    "sg:tags":[
        "protection"
    ],
    "wof:name":"Tompkins Corner Vlntr Fire Co",
    "wof:placetype":"venue"
},
  "geometry": {"coordinates":[-76.890185,42.204863],"type":"Point"}
}