{
  "type": "Feature",
  "properties": {
    "addr:full":"614 Sheepshead Bay Rd Brooklyn NY 11224",
    "addr:housenumber":"614",
    "addr:postcode":"11224",
    "addr:street":"Sheepshead Bay Rd",
    "iso:country":"US",
    "sg:address":"614 Sheepshead Bay Rd",
    "sg:city":"Brooklyn",
    "sg:classifiers":[
        {
            "category":"Real Estate",
            "subcategory":"Developer",
            "type":"Services"
        }
    ],
    "sg:phone":"+1 718 373 3002",
    "sg:postcode":"11224",
    "sg:province":"NY",
    "wof:name":"Newland LLC",
    "wof:placetype":"venue"
},
  "geometry": {"coordinates":[-73.97621100000001,40.579119],"type":"Point"}
}