{
  "type": "Feature",
  "properties": {
    "addr:full":"63 E 9 St New York NY 10003",
    "addr:housenumber":"63;9",
    "addr:postcode":"10003",
    "addr:street":"E",
    "iso:country":"US",
    "sg:address":"63 E 9 St",
    "sg:city":"New York",
    "sg:classifiers":[
        {
            "category":"Shopping",
            "subcategory":"Clothing, Apparel, & Fashions",
            "type":"Retail Goods"
        }
    ],
    "sg:phone":"+1   ",
    "sg:postcode":"10003",
    "sg:province":"NY",
    "wof:name":"A Uno",
    "wof:placetype":"venue"
},
  "geometry": {"coordinates":[-73.993471,40.731939],"type":"Point"}
}