{
  "type": "Feature",
  "properties": {
    "iso:country":"US",
    "sg:address":"1660 New Hyde Park Rd",
    "sg:city":"New Hyde Park",
    "sg:classifiers":[
        {
            "category":"Restaurant",
            "type":"Food & Drink"
        }
    ],
    "sg:phone":"+1 631 390 9634",
    "sg:postcode":"11040",
    "sg:province":"NY",
    "sg:tags":[
        "barbeque"
    ],
    "wof:name":"Sparky's Texas BBQ",
    "wof:placetype":"venue"
},
  "geometry": {"coordinates":[-73.68340999999999,40.743362],"type":"Point"}
}