{
  "type": "Feature",
  "properties": {
    "addr:full":"15920 Crossbay Boulevard Howard Beach NY 11414",
    "addr:postcode":"15920;11414",
    "addr:street":"Crossbay Boulevard",
    "iso:country":"US",
    "sg:address":"15920 Crossbay Boulevard",
    "sg:city":"Howard Beach",
    "sg:classifiers":[
        {
            "category":"Shopping",
            "subcategory":"Mobile Phones",
            "type":"Retail Goods"
        }
    ],
    "sg:phone":"+1 718 738 2600",
    "sg:postcode":"11414",
    "sg:province":"NY",
    "sg:website":"www.wirelesszone.com",
    "wof:name":"Wireless Zone",
    "wof:placetype":"venue"
},
  "geometry": {"coordinates":[-73.83980200000001,40.658286],"type":"Point"}
}