{
  "type": "Feature",
  "properties": {
    "addr:full":"204 Van Dyke St Brooklyn NY 11231",
    "addr:housenumber":"204",
    "addr:postcode":"11231",
    "addr:street":"Van Dyke St",
    "iso:country":"US",
    "sg:address":"204 Van Dyke St",
    "sg:city":"Brooklyn",
    "sg:classifiers":[
        {
            "category":"Wholesale",
            "subcategory":"Groceries",
            "type":"Manufacturing & Wholesale Goods"
        }
    ],
    "sg:phone":"+1 718 522 0979",
    "sg:postcode":"11231",
    "sg:province":"NY",
    "sg:tags":[
        "pet",
        "food"
    ],
    "wof:name":"Beastly Distributing Inc",
    "wof:placetype":"venue"
},
  "geometry": {"coordinates":[-74.01597099999999,40.676614],"type":"Point"}
}