{
  "type": "Feature",
  "properties": {
    "addr:full":"3767 S Park Ave Buffalo NY 14219",
    "addr:housenumber":"3767",
    "addr:postcode":"14219",
    "addr:street":"S Park Ave",
    "iso:country":"US",
    "sg:address":"3767 S Park Ave",
    "sg:city":"Buffalo",
    "sg:classifiers":[
        {
            "category":"Shopping",
            "subcategory":"Hobbies, Toys, & Games",
            "type":"Retail Goods"
        },
        {
            "category":"Shopping",
            "type":"Retail Goods"
        }
    ],
    "sg:phone":"+1 716 825 2361",
    "sg:postcode":"14219",
    "sg:province":"NY",
    "sg:tags":[
        "shop",
        "gallery",
        "merchandise",
        "rock"
    ],
    "sg:website":"www.pastpres.com",
    "wof:name":"Past & Present",
    "wof:placetype":"venue"
},
  "geometry": {"coordinates":[-78.823876,42.796388],"type":"Point"}
}