{
  "type": "Feature",
  "properties": {
    "addr:full":"923 Coney Island Ave Brooklyn NY 11230",
    "addr:housenumber":"923",
    "addr:postcode":"11230",
    "addr:street":"Coney Island Ave",
    "iso:country":"US",
    "sg:address":"923 Coney Island Ave",
    "sg:city":"Brooklyn",
    "sg:classifiers":[
        {
            "category":"Personal",
            "subcategory":"Beauty Salon",
            "type":"Services"
        }
    ],
    "sg:phone":"+1 718 469 0736",
    "sg:postcode":"11230",
    "sg:province":"NY",
    "sg:tags":[
        "shop"
    ],
    "wof:name":"Adam & Eve Unisex Hair Stylsts",
    "wof:placetype":"venue"
},
  "geometry": {"coordinates":[-73.96742500000001,40.634908],"type":"Point"}
}