{
  "type": "Feature",
  "properties": {
    "addr:full":"936 Stewart Ave Bethpage NY 11714",
    "addr:housenumber":"936",
    "addr:postcode":"11714",
    "addr:street":"Stewart Ave",
    "iso:country":"US",
    "sg:address":"936 Stewart Ave",
    "sg:city":"Bethpage",
    "sg:classifiers":[
        {
            "category":"Social Services",
            "type":"Services"
        },
        {
            "category":"Personal",
            "type":"Services"
        }
    ],
    "sg:phone":"+1 516 433 5344",
    "sg:postcode":"11714",
    "sg:province":"NY",
    "sg:tags":[
        "family",
        "counselors-licensed",
        "individual",
        "marriage",
        "child",
        "professional",
        "counselor"
    ],
    "sg:website":"http://www.bada.com",
    "wof:name":"People",
    "wof:placetype":"venue"
},
  "geometry": {"coordinates":[-73.485817,40.757726],"type":"Point"}
}