{
  "type": "Feature",
  "properties": {
    "addr:full":"325 Old Mill Rd Wallkill NY 12589",
    "addr:housenumber":"325",
    "addr:postcode":"12589",
    "addr:street":"Old Mill Rd",
    "iso:country":"US",
    "sg:address":"325 Old Mill Rd",
    "sg:city":"Wallkill",
    "sg:classifiers":[
        {
            "category":"Building & Trades",
            "subcategory":"Landscaping Services",
            "type":"Services"
        }
    ],
    "sg:phone":"+1 845 564 4486",
    "sg:postcode":"12589",
    "sg:province":"NY",
    "wof:name":"Katies Magic Garden",
    "wof:placetype":"venue"
},
  "geometry": {"coordinates":[-74.081356,41.602329],"type":"Point"}
}