{
  "type": "Feature",
  "properties": {
    "iso:country":"US",
    "sg:address":"155 East 50th St",
    "sg:city":"New York",
    "sg:classifiers":[
        {
            "category":"Travel",
            "subcategory":"Hotels & Motels",
            "type":"Entertainment"
        }
    ],
    "sg:phone":"+1 212 751 5710",
    "sg:postcode":"10022",
    "sg:province":"NY",
    "sg:website":"www.affinia.com/New-York-City-Ho...",
    "wof:name":"Affinia 50",
    "wof:placetype":"venue"
},
  "geometry": {"coordinates":[-73.9714,40.756092],"type":"Point"}
}