{
  "type": "Feature",
  "properties": {
    "addr:full":"2-8 Hawley St Binghamton NY 13901",
    "addr:housenumber":"2-8",
    "addr:postcode":"13901",
    "addr:street":"Hawley St",
    "iso:country":"US",
    "sg:address":"2-8 Hawley St",
    "sg:city":"Binghamton",
    "sg:classifiers":[
        {
            "category":"Travel",
            "subcategory":"Hotels & Motels",
            "type":"Entertainment"
        },
        {
            "category":"Retail",
            "subcategory":"Event Space",
            "type":"Services"
        },
        {
            "category":"Travel",
            "subcategory":"Resort",
            "type":"Entertainment"
        }
    ],
    "sg:phone":"+1 800 345 8082",
    "sg:postcode":"13901",
    "sg:province":"NY",
    "sg:tags":[
        "hall",
        "lodging",
        "banquet",
        "reception",
        "facility"
    ],
    "sg:website":"http://ad.doubleclick.net/clk;223371278;47096201;d?http://www.holidayinn.com/redirect?path=hd&brandCode=hi&hotelCode=bgmar&_PMID=99601036&cm_mmc=mdpr-_-yellowpages-_-hi-_-bgmar",
    "wof:name":"Holiday Inn Binghamton-Dwtn (Hawley St)",
    "wof:placetype":"venue"
},
  "geometry": {"coordinates":[-75.914619,42.098751],"type":"Point"}
}