{
  "type": "Feature",
  "properties": {
    "addr:full":"110 Broadway Monticello NY 12701",
    "addr:housenumber":"110",
    "addr:postcode":"12701",
    "addr:street":"Broadway",
    "iso:country":"US",
    "sg:address":"110 Broadway",
    "sg:city":"Monticello",
    "sg:classifiers":[
        {
            "category":"Home & Garden",
            "subcategory":"Building Materials",
            "type":"Retail Goods"
        }
    ],
    "sg:phone":"+1 845 794 4477",
    "sg:postcode":"12701",
    "sg:province":"NY",
    "sg:tags":[
        "glass",
        "window",
        "plate"
    ],
    "wof:name":"Monticello Plate Glass Co",
    "wof:placetype":"venue"
},
  "geometry": {"coordinates":[-74.67441599999999,41.651765],"type":"Point"}
}