{
  "type": "Feature",
  "properties": {
    "iso:country":"US",
    "sg:address":"3510 Sagamore Ave",
    "sg:city":"Mohegan Lake",
    "sg:classifiers":[
        {
            "category":"Shopping",
            "subcategory":"Florist",
            "type":"Retail Goods"
        }
    ],
    "sg:phone":"+1   ",
    "sg:postcode":"10547",
    "sg:province":"NY",
    "wof:name":"Floral Designs",
    "wof:placetype":"venue"
},
  "geometry": {"coordinates":[-73.84607099999999,41.325173],"type":"Point"}
}