{
  "type": "Feature",
  "properties": {
    "iso:country":"US",
    "sg:address":"156 Stoneridge Ct",
    "sg:city":"East Aurora",
    "sg:classifiers":[
        {
            "category":"Building & Trades",
            "subcategory":"Plumbing",
            "type":"Services"
        }
    ],
    "sg:phone":"+1 716 655 6576",
    "sg:postcode":"14052",
    "sg:province":"NY",
    "sg:tags":[
        "conditioning",
        "air",
        "system",
        "contractor"
    ],
    "wof:name":"MPG Properties Htg & Cooling",
    "wof:placetype":"venue"
},
  "geometry": {"coordinates":[-78.593864,42.772652],"type":"Point"}
}