{
  "type": "Feature",
  "properties": {
    "addr:full":"24 Concord Dr Monsey NY 10952",
    "addr:housenumber":"24",
    "addr:postcode":"10952",
    "addr:street":"Concord Dr",
    "iso:country":"US",
    "sg:address":"24 Concord Dr",
    "sg:city":"Monsey",
    "sg:classifiers":[
        {
            "category":"Shopping",
            "subcategory":"Used Merchandise",
            "type":"Retail Goods"
        }
    ],
    "sg:phone":"+1 845 426 0692",
    "sg:postcode":"10952",
    "sg:province":"NY",
    "sg:tags":[
        "antique"
    ],
    "wof:name":"Bits & Pieces",
    "wof:placetype":"venue"
},
  "geometry": {"coordinates":[-74.073891,41.132058],"type":"Point"}
}