{
  "type": "Feature",
  "properties": {
    "addr:full":"545 W 34th St New York NY 10001",
    "addr:housenumber":"545",
    "addr:postcode":"10001",
    "addr:street":"W 34Th St",
    "iso:country":"US",
    "sg:address":"545 W 34th St",
    "sg:city":"New York",
    "sg:classifiers":[
        {
            "category":"Food & Beverages",
            "subcategory":"Liquor & Beverages",
            "type":"Retail Goods"
        }
    ],
    "sg:phone":"+1 212 268 0906",
    "sg:postcode":"10001",
    "sg:province":"NY",
    "sg:tags":[
        "wine"
    ],
    "wof:name":"Banville & Jones Wine Mrchnts",
    "wof:placetype":"venue"
},
  "geometry": {"coordinates":[-74.001054,40.755178],"type":"Point"}
}