{
  "type": "Feature",
  "properties": {
    "addr:full":"136 E 28 St New York NY 10016",
    "addr:housenumber":"136;28",
    "addr:postcode":"10016",
    "addr:street":"E",
    "iso:country":"US",
    "sg:address":"136 E 28 St",
    "sg:city":"New York",
    "sg:classifiers":[
        {
            "category":"Food & Beverages",
            "subcategory":"Candy",
            "type":"Retail Goods"
        }
    ],
    "sg:phone":"+1 212 889 7361",
    "sg:postcode":"10016",
    "sg:province":"NY",
    "sg:tags":[
        "confectionery"
    ],
    "wof:name":"A & S Smoke & Card Shop Inc",
    "wof:placetype":"venue"
},
  "geometry": {"coordinates":[-73.98237899999999,40.742749],"type":"Point"}
}