{
  "type": "Feature",
  "properties": {
    "addr:full":"255 W End Ave New York NY 10023",
    "addr:housenumber":"255",
    "addr:postcode":"10023",
    "addr:street":"W End Ave",
    "iso:country":"US",
    "sg:address":"255 W End Ave",
    "sg:city":"New York",
    "sg:classifiers":[
        {
            "category":"Professional",
            "subcategory":"Management & Consulting",
            "type":"Services"
        }
    ],
    "sg:phone":"+1 212 579 5798",
    "sg:postcode":"10023",
    "sg:province":"NY",
    "sg:tags":[
        "marketing",
        "consultant"
    ],
    "wof:name":"Common Sense Communications",
    "wof:placetype":"venue"
},
  "geometry": {"coordinates":[-73.984844,40.779298],"type":"Point"}
}