{
  "type": "Feature",
  "properties": {
    "addr:full":"7019 37th Avenue Jackson Heights NY 11372",
    "addr:housenumber":"7019",
    "addr:postcode":"11372",
    "addr:street":"37Th Avenue",
    "iso:country":"US",
    "sg:address":"7019 37th Avenue",
    "sg:city":"Jackson Heights",
    "sg:classifiers":[
        {
            "category":"Health Services",
            "subcategory":"Doctor",
            "type":"Services"
        }
    ],
    "sg:phone":"+1 718 457 7955",
    "sg:postcode":"11372",
    "sg:province":"NY",
    "wof:name":"Iliescu Constantin MD",
    "wof:placetype":"venue"
},
  "geometry": {"coordinates":[-73.894668,40.74877],"type":"Point"}
}