{
  "type": "Feature",
  "properties": {
    "iso:country":"US",
    "sg:address":"80 Vista Ter",
    "sg:city":"Mahopac",
    "sg:classifiers":[
        {
            "category":"Real Estate",
            "subcategory":"Real Estate Services",
            "type":"Services"
        }
    ],
    "sg:phone":"+1 914 238 6630",
    "sg:postcode":"10541",
    "sg:province":"NY",
    "wof:name":"Castle Appraisals",
    "wof:placetype":"venue"
},
  "geometry": {"coordinates":[-73.754622,41.375596],"type":"Point"}
}