{
  "type": "Feature",
  "properties": {
    "addr:full":"200 Park Ave Rochester NY 14607",
    "addr:housenumber":"200",
    "addr:postcode":"14607",
    "addr:street":"Park Ave",
    "iso:country":"US",
    "sg:address":"200 Park Ave",
    "sg:city":"Rochester",
    "sg:classifiers":[
        {
            "category":"Professional",
            "subcategory":"Accounting & Tax Preparation",
            "type":"Services"
        }
    ],
    "sg:phone":"+1 585 461 3440",
    "sg:postcode":"14607",
    "sg:province":"NY",
    "sg:tags":[
        "accountant"
    ],
    "wof:name":"John Maggio CPA",
    "wof:placetype":"venue"
},
  "geometry": {"coordinates":[-77.590317,43.150681],"type":"Point"}
}