{
  "type": "Feature",
  "properties": {
    "iso:country":"US",
    "sg:address":"1386 Long Pond Rd",
    "sg:city":"Rochester",
    "sg:classifiers":[
        {
            "category":"Retail",
            "subcategory":"Portrait Studio",
            "type":"Services"
        }
    ],
    "sg:phone":"+1 585 723 5369",
    "sg:postcode":"14626",
    "sg:province":"NY",
    "sg:tags":[
        "photo"
    ],
    "wof:name":"Sears Portrait Studio",
    "wof:placetype":"venue"
},
  "geometry": {"coordinates":[-77.699445,43.200485],"type":"Point"}
}