{
  "type": "Feature",
  "properties": {
    "iso:country":"US",
    "sg:address":"1003 W State St",
    "sg:city":"Olean",
    "sg:classifiers":[
        {
            "category":"Restaurant",
            "type":"Food & Drink"
        }
    ],
    "sg:phone":"+1   ",
    "sg:postcode":"14760",
    "sg:province":"NY",
    "sg:tags":[
        "eating"
    ],
    "wof:name":"A&Js Sub & Pizza Shop",
    "wof:placetype":"venue"
},
  "geometry": {"coordinates":[-78.442246,42.077333],"type":"Point"}
}