{
  "type": "Feature",
  "properties": {
    "addr:full":"3921 9th Ave Brooklyn NY 11232",
    "addr:housenumber":"3921",
    "addr:postcode":"11232",
    "addr:street":"9Th Ave",
    "iso:country":"US",
    "sg:address":"3921 9th Ave",
    "sg:city":"Brooklyn",
    "sg:classifiers":[
        {
            "category":"Shopping",
            "subcategory":"Pharmacy",
            "type":"Retail Goods"
        }
    ],
    "sg:phone":"+1   ",
    "sg:postcode":"11232",
    "sg:province":"NY",
    "wof:name":"Phillips Pharmacy",
    "wof:placetype":"venue"
},
  "geometry": {"coordinates":[-73.99553299999999,40.645453],"type":"Point"}
}