{
  "type": "Feature",
  "properties": {
    "iso:country":"US",
    "sg:address":"104 W 40 St",
    "sg:city":"New York",
    "sg:classifiers":[
        {
            "category":"Communications",
            "subcategory":"News Services",
            "type":"Services"
        }
    ],
    "sg:phone":"+1 212 921 2727",
    "sg:postcode":"10018",
    "sg:province":"NY",
    "wof:name":"Blue Fox Nedgraphics",
    "wof:placetype":"venue"
},
  "geometry": {"coordinates":[-73.986739,40.754162],"type":"Point"}
}