{
  "type": "Feature",
  "properties": {
    "iso:country":"US",
    "sg:address":"16 Schuman Rd",
    "sg:city":"Millwood",
    "sg:classifiers":[
        {
            "category":"Building & Trades",
            "subcategory":"Construction",
            "type":"Services"
        }
    ],
    "sg:phone":"+1 914 762 6801",
    "sg:postcode":"10546",
    "sg:province":"NY",
    "sg:tags":[
        "heavy"
    ],
    "wof:name":"Hudson Canyon Construction",
    "wof:placetype":"venue"
},
  "geometry": {"coordinates":[-73.796468,41.18952],"type":"Point"}
}