{
  "type": "Feature",
  "properties": {
    "iso:country":"US",
    "sg:address":"1732 Fyler Rd",
    "sg:city":"Chittenango",
    "sg:classifiers":[
        {
            "category":"Education",
            "subcategory":"School",
            "type":"Public Place"
        }
    ],
    "sg:phone":"+1 315 687 2840",
    "sg:postcode":"13037",
    "sg:province":"NY",
    "sg:tags":[
        "k-",
        "private"
    ],
    "wof:name":"Chittenango Central School - District Office",
    "wof:placetype":"venue"
},
  "geometry": {"coordinates":[-75.87806999999999,43.08708],"type":"Point"}
}