{
  "type": "Feature",
  "properties": {
    "iso:country":"US",
    "sg:address":"7164 US Hwy 9",
    "sg:city":"Plattsburgh",
    "sg:classifiers":[
        {
            "category":"Professional",
            "subcategory":"Computer Services",
            "type":"Services"
        }
    ],
    "sg:phone":"+1 518 561 6885",
    "sg:postcode":"12901",
    "sg:province":"NY",
    "sg:tags":[
        "repair"
    ],
    "wof:name":"Total Computer Supplies",
    "wof:placetype":"venue"
},
  "geometry": {"coordinates":[-73.424993,44.741777],"type":"Point"}
}