{
  "type": "Feature",
  "properties": {
    "iso:country":"US",
    "sg:address":"107 Eldredge St",
    "sg:city":"Binghamton",
    "sg:classifiers":[
        {
            "category":"Retail",
            "subcategory":"Auto Repair",
            "type":"Services"
        }
    ],
    "sg:phone":"+1 607 723 7602",
    "sg:postcode":"13901",
    "sg:province":"NY",
    "sg:tags":[
        "automotive",
        "part",
        "supply"
    ],
    "wof:name":"All Seasons Radiator",
    "wof:placetype":"venue"
},
  "geometry": {"coordinates":[-75.905828,42.105256],"type":"Point"}
}