{
  "type": "Feature",
  "properties": {
    "addr:full":"14 Brandywine Dr Mastic NY 11950",
    "addr:housenumber":"14",
    "addr:postcode":"11950",
    "addr:street":"Brandywine Dr",
    "iso:country":"US",
    "sg:address":"14 Brandywine Dr",
    "sg:city":"Mastic",
    "sg:classifiers":[
        {
            "category":"Building & Trades",
            "subcategory":"Electrical",
            "type":"Services"
        }
    ],
    "sg:phone":"+1 631 878 0991",
    "sg:postcode":"11950",
    "sg:province":"NY",
    "sg:tags":[
        "designer",
        "electrical"
    ],
    "wof:name":"Pristine Electric Inc",
    "wof:placetype":"venue"
},
  "geometry": {"coordinates":[-72.862679,40.823334],"type":"Point"}
}