{
  "type": "Feature",
  "properties": {
    "addr:full":"681 E Tremont Ave Bronx NY 10457",
    "addr:housenumber":"681",
    "addr:postcode":"10457",
    "addr:street":"E Tremont Ave",
    "iso:country":"US",
    "sg:address":"681 E Tremont Ave",
    "sg:city":"Bronx",
    "sg:classifiers":[
        {
            "category":"Retail",
            "subcategory":"Self-service Laundry",
            "type":"Services"
        }
    ],
    "sg:phone":"+1 718 299 3025",
    "sg:postcode":"10457",
    "sg:province":"NY",
    "wof:name":"Clean City",
    "wof:placetype":"venue"
},
  "geometry": {"coordinates":[-73.89158137139999,40.8457982233],"type":"Point"}
}