{
  "type": "Feature",
  "properties": {
    "iso:country":"US",
    "sg:address":"27 Glen Cove Rd",
    "sg:city":"Greenvale",
    "sg:classifiers":[
        {
            "category":"Home & Garden",
            "subcategory":"Home Furnishings",
            "type":"Retail Goods"
        }
    ],
    "sg:phone":"+1 516 484 7469",
    "sg:postcode":"11548",
    "sg:province":"NY",
    "sg:tags":[
        "mirror"
    ],
    "wof:name":"Shower Door",
    "wof:placetype":"venue"
},
  "geometry": {"coordinates":[-73.628263,40.809847],"type":"Point"}
}