{
  "type": "Feature",
  "properties": {
    "addr:full":"3056 Burnet Ave Syracuse NY 13206",
    "addr:housenumber":"3056",
    "addr:postcode":"13206",
    "addr:street":"Burnet Ave",
    "iso:country":"US",
    "sg:address":"3056 Burnet Ave",
    "sg:city":"Syracuse",
    "sg:classifiers":[
        {
            "category":"Food & Beverages",
            "subcategory":"Bakery",
            "type":"Retail Goods"
        }
    ],
    "sg:phone":"+1 315 431 0879",
    "sg:postcode":"13206",
    "sg:province":"NY",
    "sg:tags":[
        "baker"
    ],
    "wof:name":"BMJ Intl",
    "wof:placetype":"venue"
},
  "geometry": {"coordinates":[-76.095016,43.060507],"type":"Point"}
}