{
  "type": "Feature",
  "properties": {
    "iso:country":"US",
    "sg:address":"2541 Guilderland Ave",
    "sg:city":"Schenectady",
    "sg:classifiers":[
        {
            "category":"Food & Beverages",
            "subcategory":"Groceries & Convenience Stores",
            "type":"Retail Goods"
        }
    ],
    "sg:phone":"+1   ",
    "sg:postcode":"12306",
    "sg:province":"NY",
    "wof:name":"Cumberland Farms 1533",
    "wof:placetype":"venue"
},
  "geometry": {"coordinates":[-73.968739,42.790059],"type":"Point"}
}