{
  "type": "Feature",
  "properties": {
    "addr:full":"450 N Main St Warsaw NY 14569",
    "addr:housenumber":"450",
    "addr:postcode":"14569",
    "addr:street":"N Main St",
    "iso:country":"US",
    "sg:address":"450 N Main St",
    "sg:city":"Warsaw",
    "sg:classifiers":[
        {
            "category":"Health Services",
            "subcategory":"Health Practitioner",
            "type":"Services"
        }
    ],
    "sg:phone":"+1 585 786 2422",
    "sg:postcode":"14569",
    "sg:province":"NY",
    "sg:tags":[
        "audiologists"
    ],
    "wof:name":"Dansville Hearing Ctr",
    "wof:placetype":"venue"
},
  "geometry": {"coordinates":[-78.130807,42.758276],"type":"Point"}
}