{
  "type": "Feature",
  "properties": {
    "addr:full":"6122 4th Ave Brooklyn NY 11220",
    "addr:housenumber":"6122",
    "addr:postcode":"11220",
    "addr:street":"4Th Ave",
    "iso:country":"US",
    "sg:address":"6122 4th Ave",
    "sg:city":"Brooklyn",
    "sg:classifiers":[
        {
            "category":"Food & Beverages",
            "subcategory":"Candy",
            "type":"Retail Goods"
        }
    ],
    "sg:phone":"+1   ",
    "sg:postcode":"11220",
    "sg:province":"NY",
    "wof:name":"Tiamo Discount",
    "wof:placetype":"venue"
},
  "geometry": {"coordinates":[-74.019567,40.639875],"type":"Point"}
}