{
  "type": "Feature",
  "properties": {
    "addr:full":"88 Wicks Rd Brentwood NY 11717",
    "addr:housenumber":"88",
    "addr:postcode":"11717",
    "addr:street":"Wicks Rd",
    "iso:country":"US",
    "sg:address":"88 Wicks Rd",
    "sg:city":"Brentwood",
    "sg:classifiers":[
        {
            "category":"Restaurant",
            "type":"Food & Drink"
        }
    ],
    "sg:phone":"+1   ",
    "sg:postcode":"11717",
    "sg:province":"NY",
    "sg:tags":[
        "eating"
    ],
    "wof:name":"Delicias Restaurant",
    "wof:placetype":"venue"
},
  "geometry": {"coordinates":[-73.26106299999999,40.780334],"type":"Point"}
}