{
  "type": "Feature",
  "properties": {
    "addr:full":"355 Ovington Avenue Brooklyn NY 11209",
    "addr:housenumber":"355",
    "addr:postcode":"11209",
    "addr:street":"Ovington Avenue",
    "iso:country":"US",
    "sg:address":"355 Ovington Avenue",
    "sg:city":"Brooklyn",
    "sg:classifiers":[
        {
            "category":"Health Services",
            "subcategory":"Doctor",
            "type":"Services"
        }
    ],
    "sg:phone":"+1 718 238 1818",
    "sg:postcode":"11209",
    "sg:province":"NY",
    "wof:name":"Florio Francis E MD",
    "wof:placetype":"venue"
},
  "geometry": {"coordinates":[-74.025153,40.634306],"type":"Point"}
}