{
  "type": "Feature",
  "properties": {
    "addr:full":"382 Avenue P Brooklyn NY 11204",
    "addr:housenumber":"382",
    "addr:postcode":"11204",
    "addr:street":"Avenue P",
    "iso:country":"US",
    "sg:address":"382 Avenue P",
    "sg:city":"Brooklyn",
    "sg:classifiers":[
        {
            "category":"Food & Beverages",
            "subcategory":"Groceries & Convenience Stores",
            "type":"Retail Goods"
        }
    ],
    "sg:phone":"+1 718 339 3698",
    "sg:postcode":"11204",
    "sg:province":"NY",
    "wof:name":"JH Trading Of Ny Inc",
    "wof:placetype":"venue"
},
  "geometry": {"coordinates":[-73.973499,40.60862],"type":"Point"}
}