{
  "type": "Feature",
  "properties": {
    "iso:country":"US",
    "sg:address":"560 W 180th St",
    "sg:city":"New York",
    "sg:classifiers":[
        {
            "category":"Wholesale",
            "subcategory":"Books, Periodicals, & Newspapers",
            "type":"Manufacturing & Wholesale Goods"
        },
        {
            "category":"Shopping",
            "subcategory":"Books",
            "type":"Retail Goods"
        }
    ],
    "sg:phone":"+1 212 568 0151",
    "sg:postcode":"10033",
    "sg:province":"NY",
    "sg:tags":[
        "wholesaler",
        "dealer"
    ],
    "wof:name":"Luso-Brazilian Books",
    "wof:placetype":"venue"
},
  "geometry": {"coordinates":[-73.93391200000001,40.848357],"type":"Point"}
}