{
  "type": "Feature",
  "properties": {
    "iso:country":"US",
    "sg:address":"7345 Boyd Rd",
    "sg:city":"Pavilion",
    "sg:classifiers":[
        {
            "category":"Freight",
            "type":"Transportation"
        }
    ],
    "sg:phone":"+1 585 584 9250",
    "sg:postcode":"14525",
    "sg:province":"NY",
    "sg:tags":[
        "commercial",
        "storage"
    ],
    "wof:name":"Covington Self Storage LLC",
    "wof:placetype":"venue"
},
  "geometry": {"coordinates":[-77.983774,42.857463],"type":"Point"}
}