{
  "type": "Feature",
  "properties": {
    "addr:full":"20 E 53rd St New York NY 10022",
    "addr:housenumber":"20",
    "addr:postcode":"10022",
    "addr:street":"E 53Rd St",
    "iso:country":"US",
    "sg:address":"20 E 53rd St",
    "sg:city":"New York",
    "sg:classifiers":[
        {
            "category":"Personal",
            "type":"Services"
        }
    ],
    "sg:phone":"+1 917 289 1367",
    "sg:postcode":"10022",
    "sg:province":"NY",
    "sg:tags":[
        "towing"
    ],
    "wof:name":"24 Hour Always Emergency Towing",
    "wof:placetype":"venue"
},
  "geometry": {"coordinates":[-73.964996,40.7575],"type":"Point"}
}