{
  "type": "Feature",
  "properties": {
    "iso:country":"US",
    "sg:address":"100 Duffy Ave Ste 300",
    "sg:city":"Hicksville",
    "sg:classifiers":[
        {
            "category":"Organizations",
            "subcategory":"Labor Organization",
            "type":"Services"
        }
    ],
    "sg:phone":"+1 516 222 3310",
    "sg:postcode":"11801",
    "sg:province":"NY",
    "wof:name":"National Benefit Fund",
    "wof:placetype":"venue"
},
  "geometry": {"coordinates":[-73.533186,40.764873],"type":"Point"}
}