{
  "type": "Feature",
  "properties": {
    "iso:country":"US",
    "sg:address":"1695 Grand Ave",
    "sg:city":"Bronx",
    "sg:classifiers":[
        {
            "category":"Professional",
            "subcategory":"Management & Consulting",
            "type":"Services"
        }
    ],
    "sg:phone":"+1 718 299 5006",
    "sg:postcode":"10453",
    "sg:province":"NY",
    "wof:name":"Morris Hgts Mews Assocs",
    "wof:placetype":"venue"
},
  "geometry": {"coordinates":[-73.914303,40.848143],"type":"Point"}
}