{
  "type": "Feature",
  "properties": {
    "iso:country":"US",
    "sg:address":"7 1/2 2nd Ave",
    "sg:city":"New York",
    "sg:classifiers":[
        {
            "category":"Restaurant",
            "type":"Food & Drink"
        }
    ],
    "sg:phone":"+1 212 505 9935",
    "sg:postcode":"10003",
    "sg:province":"NY",
    "wof:name":"Panchos Burritos",
    "wof:placetype":"venue"
},
  "geometry": {"coordinates":[-73.99120600000001,40.724015],"type":"Point"}
}