{
  "type": "Feature",
  "properties": {
    "addr:full":"24 Edwards St Arcade NY 14009",
    "addr:housenumber":"24",
    "addr:postcode":"14009",
    "addr:street":"Edwards St",
    "iso:country":"US",
    "sg:address":"24 Edwards St",
    "sg:city":"Arcade",
    "sg:classifiers":[
        {
            "category":"Retail",
            "subcategory":"Car Wash",
            "type":"Services"
        }
    ],
    "sg:phone":"+1 585 492 4575",
    "sg:postcode":"14009",
    "sg:province":"NY",
    "sg:tags":[
        "polishing",
        "washing"
    ],
    "wof:name":"Spray-Away Car Wash",
    "wof:placetype":"venue"
},
  "geometry": {"coordinates":[-78.451016,42.530032],"type":"Point"}
}