{
  "type": "Feature",
  "properties": {
    "iso:country":"US",
    "sg:address":"813 8th Ave",
    "sg:city":"Brooklyn",
    "sg:classifiers":[
        {
            "category":"Professional",
            "subcategory":"Accounting & Tax Preparation",
            "type":"Services"
        }
    ],
    "sg:phone":"+1 718 788 3913",
    "sg:postcode":"11215",
    "sg:province":"NY",
    "sg:tags":[
        "accountant"
    ],
    "wof:name":"Douglas Condon CPA LLC",
    "wof:placetype":"venue"
},
  "geometry": {"coordinates":[-73.979113,40.665784],"type":"Point"}
}