{
  "type": "Feature",
  "properties": {
    "addr:full":"874 S Long Beach Ave Freeport NY 11520",
    "addr:housenumber":"874",
    "addr:postcode":"11520",
    "addr:street":"S Long Beach Ave",
    "iso:country":"US",
    "sg:address":"874 S Long Beach Ave",
    "sg:city":"Freeport",
    "sg:classifiers":[
        {
            "category":"Professional",
            "subcategory":"Computer Services",
            "type":"Services"
        }
    ],
    "sg:phone":"+1 516 867 9247",
    "sg:postcode":"11520",
    "sg:province":"NY",
    "wof:name":"Mugno & Mugno",
    "wof:placetype":"venue"
},
  "geometry": {"coordinates":[-73.585137,40.629835],"type":"Point"}
}