{
  "type": "Feature",
  "properties": {
    "iso:country":"US",
    "sg:address":"62 Landon Hill Rd",
    "sg:city":"Chestertown",
    "sg:classifiers":[
        {
            "category":"Government",
            "subcategory":"Office",
            "type":"Public Place"
        }
    ],
    "sg:phone":"+1 518 494 3952",
    "sg:postcode":"12817",
    "sg:province":"NY",
    "sg:tags":[
        "village"
    ],
    "wof:name":"Chestertown Landfill",
    "wof:placetype":"venue"
},
  "geometry": {"coordinates":[-73.803292,43.660722],"type":"Point"}
}