{
  "type": "Feature",
  "properties": {
    "addr:full":"2212 Attica Rd Darien Center NY 14040",
    "addr:postcode":"2212;14040",
    "addr:street":"Attica Rd",
    "iso:country":"US",
    "sg:address":"2212 Attica Rd",
    "sg:city":"Darien Center",
    "sg:classifiers":[
        {
            "category":"Farming",
            "subcategory":"Dairy Farm",
            "type":"Manufacturing & Wholesale Goods"
        }
    ],
    "sg:phone":"+1 585 547 2363",
    "sg:postcode":"14040",
    "sg:province":"NY",
    "sg:tags":[
        "grain",
        "cash"
    ],
    "wof:name":"George Brothers Farms",
    "wof:placetype":"venue"
},
  "geometry": {"coordinates":[-78.332436,42.887453],"type":"Point"}
}