{
  "type": "Feature",
  "properties": {
    "iso:country":"US",
    "sg:address":"1779 Main St",
    "sg:city":"Delanson",
    "sg:classifiers":[
        {
            "category":"Retail",
            "subcategory":"Funeral Services",
            "type":"Services"
        }
    ],
    "sg:phone":"+1 518 895 2380",
    "sg:postcode":"12053",
    "sg:province":"NY",
    "wof:name":"White Vanburen Funeral Home",
    "wof:placetype":"venue"
},
  "geometry": {"coordinates":[-74.18799799999999,42.745818],"type":"Point"}
}