{
  "type": "Feature",
  "properties": {
    "iso:country":"US",
    "sg:address":"251 Drumcliff Way",
    "sg:city":"Rochester",
    "sg:classifiers":[
        {
            "category":"Professional",
            "subcategory":"Engineering",
            "type":"Services"
        }
    ],
    "sg:phone":"+1 585 225 2023",
    "sg:postcode":"14612",
    "sg:province":"NY",
    "wof:name":"Windworks Design",
    "wof:placetype":"venue"
},
  "geometry": {"coordinates":[-77.68969199999999,43.257083],"type":"Point"}
}