{
  "type": "Feature",
  "properties": {
    "iso:country":"US",
    "sg:address":"3191 Co Rd 10",
    "sg:city":"Canandaigua",
    "sg:classifiers":[
        {
            "category":"Professional",
            "subcategory":"Accounting & Tax Preparation",
            "type":"Services"
        }
    ],
    "sg:phone":"+1 585 394 7380",
    "sg:postcode":"14424",
    "sg:province":"NY",
    "sg:tags":[
        "return",
        "filing"
    ],
    "wof:name":"H & R Block Tax Svc",
    "wof:placetype":"venue"
},
  "geometry": {"coordinates":[-77.245535,42.875622],"type":"Point"}
}