{
  "type": "Feature",
  "properties": {
    "addr:full":"115 The Portage Ticonderoga NY 12883",
    "addr:housenumber":"115",
    "addr:postcode":"12883",
    "addr:street":"The Portage",
    "iso:country":"US",
    "sg:address":"115 The Portage",
    "sg:city":"Ticonderoga",
    "sg:classifiers":[
        {
            "category":"Building & Trades",
            "subcategory":"Plumbing",
            "type":"Services"
        }
    ],
    "sg:phone":"+1 518 585 4493",
    "sg:postcode":"12883",
    "sg:province":"NY",
    "sg:tags":[
        "contractor"
    ],
    "wof:name":"Trombley Plumbing Heating",
    "wof:placetype":"venue"
},
  "geometry": {"coordinates":[-73.423357,43.846194],"type":"Point"}
}