{
  "type": "Feature",
  "properties": {
    "addr:full":"28 Foxwood Dr Apt 1 Pleasantville NY 10570",
    "addr:housenumber":"28;1",
    "addr:postcode":"10570",
    "addr:street":"Foxwood Dr Apt",
    "iso:country":"US",
    "sg:address":"28 Foxwood Dr Apt 1",
    "sg:city":"Pleasantville",
    "sg:classifiers":[
        {
            "category":"Building & Trades",
            "subcategory":"Construction",
            "type":"Services"
        }
    ],
    "sg:phone":"+1 914 479 1108",
    "sg:postcode":"10570",
    "sg:province":"NY",
    "sg:tags":[
        "finishing",
        "wood"
    ],
    "wof:name":"Ultimate Finish Carpentry",
    "wof:placetype":"venue"
},
  "geometry": {"coordinates":[-73.77874799999999,41.14629],"type":"Point"}
}