{
  "type": "Feature",
  "properties": {
    "iso:country":"US",
    "sg:address":"1702 Tanger Dr",
    "sg:city":"Riverhead",
    "sg:classifiers":[
        {
            "category":"Shopping",
            "subcategory":"Clothing, Apparel, & Fashions",
            "type":"Retail Goods"
        }
    ],
    "sg:phone":"+1 631 369 6909",
    "sg:postcode":"11901",
    "sg:province":"NY",
    "wof:name":"Gap Baby Outlet",
    "wof:placetype":"venue"
},
  "geometry": {"coordinates":[-72.679143,40.917587],"type":"Point"}
}