{
  "type": "Feature",
  "properties": {
    "iso:country":"US",
    "sg:address":"105 5th St",
    "sg:city":"Brooklyn",
    "sg:classifiers":[
        {
            "category":"Real Estate",
            "subcategory":"Real Estate Agent",
            "type":"Services"
        }
    ],
    "sg:phone":"+1 718 855 5440",
    "sg:postcode":"11215",
    "sg:province":"NY",
    "wof:name":"Chanin-Court Co",
    "wof:placetype":"venue"
},
  "geometry": {"coordinates":[-73.99198199999999,40.675471],"type":"Point"}
}