{
  "type": "Feature",
  "properties": {
    "iso:country":"US",
    "sg:address":"20 Thornwood Dr",
    "sg:city":"Ithaca",
    "sg:classifiers":[
        {
            "category":"Education",
            "subcategory":"College",
            "type":"Public Place"
        }
    ],
    "sg:phone":"+1 607 257 1081",
    "sg:postcode":"14850",
    "sg:province":"NY",
    "sg:tags":[
        "patent",
        "owner"
    ],
    "wof:name":"Cornell Research Foundation",
    "wof:placetype":"venue"
},
  "geometry": {"coordinates":[-76.462917,42.484037],"type":"Point"}
}