{
  "type": "Feature",
  "properties": {
    "addr:full":"260 Bond St Brooklyn NY 11217",
    "addr:housenumber":"260",
    "addr:postcode":"11217",
    "addr:street":"Bond St",
    "iso:country":"US",
    "sg:address":"260 Bond St",
    "sg:city":"Brooklyn",
    "sg:classifiers":[
        {
            "category":"Manufacturing",
            "subcategory":"Apparel",
            "type":"Manufacturing & Wholesale Goods"
        }
    ],
    "sg:phone":"+1   ",
    "sg:postcode":"11217",
    "sg:province":"NY",
    "sg:tags":[
        "household",
        "furnishing",
        "mfg"
    ],
    "wof:name":"Brown Studio",
    "wof:placetype":"venue"
},
  "geometry": {"coordinates":[-73.98872,40.681343],"type":"Point"}
}