{
  "type": "Feature",
  "properties": {
    "iso:country":"US",
    "sg:address":"1655 Pitkin Ave",
    "sg:city":"Brooklyn",
    "sg:classifiers":[
        {
            "category":"Shopping",
            "subcategory":"Music",
            "type":"Retail Goods"
        }
    ],
    "sg:phone":"+1 718 498 7500",
    "sg:postcode":"11212",
    "sg:province":"NY",
    "sg:tags":[
        "dvd's"
    ],
    "wof:name":"City Sounds Inc",
    "wof:placetype":"venue"
},
  "geometry": {"coordinates":[-73.912201,40.669601],"type":"Point"}
}