{
  "type": "Feature",
  "properties": {
    "addr:full":"4727 Jayson Ave Great Neck NY 11020",
    "addr:housenumber":"4727",
    "addr:postcode":"11020",
    "addr:street":"Jayson Ave",
    "iso:country":"US",
    "sg:address":"4727 Jayson Ave",
    "sg:city":"Great Neck",
    "sg:classifiers":[
        {
            "category":"Building & Trades",
            "subcategory":"Electrical",
            "type":"Services"
        }
    ],
    "sg:phone":"+1 718 304 5816",
    "sg:postcode":"11020",
    "sg:province":"NY",
    "sg:tags":[
        "electric",
        "contractor"
    ],
    "wof:name":"Bana Electric",
    "wof:placetype":"venue"
},
  "geometry": {"coordinates":[-73.72691399999999,40.773651],"type":"Point"}
}