{
  "type": "Feature",
  "properties": {
    "iso:country":"US",
    "sg:address":"181 Clover Hills Dr",
    "sg:city":"Rochester",
    "sg:classifiers":[
        {
            "category":"Banks & Credit Unions",
            "subcategory":"Financial Services",
            "type":"Services"
        }
    ],
    "sg:phone":"+1 585 244 1776",
    "sg:postcode":"14618",
    "sg:province":"NY",
    "sg:tags":[
        "trust",
        "management"
    ],
    "wof:name":"Friedlander Family Foundation",
    "wof:placetype":"venue"
},
  "geometry": {"coordinates":[-77.55224200000001,43.104983],"type":"Point"}
}