{
  "type": "Feature",
  "properties": {
    "addr:full":"230 W 23rd St New York NY 10011",
    "addr:housenumber":"230",
    "addr:postcode":"10011",
    "addr:street":"W 23Rd St",
    "iso:country":"US",
    "sg:address":"230 W 23rd St",
    "sg:city":"New York",
    "sg:classifiers":[
        {
            "category":"Building & Trades",
            "subcategory":"Plumbing",
            "type":"Services"
        }
    ],
    "sg:phone":"+1 866 339 0767",
    "sg:postcode":"10011",
    "sg:province":"NY",
    "wof:name":"A 57th Street Plumbing",
    "wof:placetype":"venue"
},
  "geometry": {"coordinates":[-73.996565,40.744337],"type":"Point"}
}