{
  "type": "Feature",
  "properties": {
    "addr:full":"2454 Lodovick Ave Bronx NY 10469",
    "addr:housenumber":"2454",
    "addr:postcode":"10469",
    "addr:street":"Lodovick Ave",
    "iso:country":"US",
    "sg:address":"2454 Lodovick Ave",
    "sg:city":"Bronx",
    "sg:classifiers":[
        {
            "category":"Social Services",
            "type":"Services"
        }
    ],
    "sg:phone":"+1 718 320 1909",
    "sg:postcode":"10469",
    "sg:province":"NY",
    "wof:name":"Bc Bilingual Inc",
    "wof:placetype":"venue"
},
  "geometry": {"coordinates":[-73.837076,40.860953],"type":"Point"}
}