{
  "type": "Feature",
  "properties": {
    "iso:country":"US",
    "sg:address":"156 W 56 St",
    "sg:city":"New York",
    "sg:classifiers":[
        {
            "category":"Communications",
            "subcategory":"Film & Video Production",
            "type":"Services"
        }
    ],
    "sg:phone":"+1   ",
    "sg:postcode":"10019",
    "sg:province":"NY",
    "sg:tags":[
        "motion"
    ],
    "wof:name":"Blackmore Productions Ltd",
    "wof:placetype":"venue"
},
  "geometry": {"coordinates":[-73.979333,40.764093],"type":"Point"}
}