{
  "type": "Feature",
  "properties": {
    "addr:full":"9 Knollwood Dr Freeville NY 13068",
    "addr:housenumber":"9",
    "addr:postcode":"13068",
    "addr:street":"Knollwood Dr",
    "iso:country":"US",
    "sg:address":"9 Knollwood Dr",
    "sg:city":"Freeville",
    "sg:classifiers":[
        {
            "category":"Building & Trades",
            "subcategory":"Construction",
            "type":"Services"
        }
    ],
    "sg:phone":"+1 607 347 6522",
    "sg:postcode":"13068",
    "sg:province":"NY",
    "sg:tags":[
        "general",
        "contractor"
    ],
    "wof:name":"Bouchard Construction",
    "wof:placetype":"venue"
},
  "geometry": {"coordinates":[-76.371313,42.480427],"type":"Point"}
}