{
  "type": "Feature",
  "properties": {
    "addr:full":"43 Hunting Hollow Ct Huntington Sta NY 11746",
    "addr:housenumber":"43",
    "addr:postcode":"11746",
    "addr:street":"Hunting Hollow Ct",
    "iso:country":"US",
    "sg:address":"43 Hunting Hollow Ct",
    "sg:city":"Huntington Sta",
    "sg:classifiers":[
        {
            "category":"Building & Trades",
            "subcategory":"Landscaping Services",
            "type":"Services"
        }
    ],
    "sg:phone":"+1 631 424 1681",
    "sg:postcode":"11746",
    "sg:province":"NY",
    "sg:tags":[
        "landscape",
        "contractor"
    ],
    "wof:name":"Sempre Landscaping",
    "wof:placetype":"venue"
},
  "geometry": {"coordinates":[-73.35082199999999,40.784436],"type":"Point"}
}