{
  "type": "Feature",
  "properties": {
    "addr:full":"25 Broad St New York NY 10004",
    "addr:housenumber":"25",
    "addr:postcode":"10004",
    "addr:street":"Broad St",
    "iso:country":"US",
    "sg:address":"25 Broad St",
    "sg:city":"New York",
    "sg:classifiers":[
        {
            "category":"Professional",
            "subcategory":"Management & Consulting",
            "type":"Services"
        }
    ],
    "sg:phone":"+1 212 269 0878",
    "sg:postcode":"10004",
    "sg:province":"NY",
    "sg:tags":[
        "consultant"
    ],
    "wof:name":"Courtyard Group Inc",
    "wof:placetype":"venue"
},
  "geometry": {"coordinates":[-74.011459,40.705086],"type":"Point"}
}