{
  "type": "Feature",
  "properties": {
    "addr:full":"1533 Bassett Ave Bronx NY 10461",
    "addr:housenumber":"1533",
    "addr:postcode":"10461",
    "addr:street":"Bassett Ave",
    "iso:country":"US",
    "sg:address":"1533 Bassett Ave",
    "sg:city":"Bronx",
    "sg:classifiers":[
        {
            "category":"Manufacturing",
            "subcategory":"Chemicals & Compounds",
            "type":"Manufacturing & Wholesale Goods"
        }
    ],
    "sg:phone":"+1 718 828 8000",
    "sg:postcode":"10461",
    "sg:province":"NY",
    "sg:tags":[
        "paint",
        "varnish",
        "allied",
        "product"
    ],
    "wof:name":"Amsterdam Colorworks",
    "wof:placetype":"venue"
},
  "geometry": {"coordinates":[-73.841177,40.853963],"type":"Point"}
}