{
  "type": "Feature",
  "properties": {
    "iso:country":"US",
    "sg:address":"970 E 92nd St",
    "sg:city":"Brooklyn",
    "sg:classifiers":[
        {
            "category":"Building & Trades",
            "subcategory":"Electrical",
            "type":"Services"
        }
    ],
    "sg:phone":"+1 718 927 1100",
    "sg:postcode":"11236",
    "sg:province":"NY",
    "sg:tags":[
        "electrical",
        "electric",
        "contractor"
    ],
    "wof:name":"Empire Liberty Electric Corp",
    "wof:placetype":"venue"
},
  "geometry": {"coordinates":[-73.909661,40.64547],"type":"Point"}
}