{
  "type": "Feature",
  "properties": {
    "iso:country":"US",
    "sg:address":"4297 3rd Ave",
    "sg:city":"Bronx",
    "sg:classifiers":[
        {
            "category":"Building & Trades",
            "subcategory":"Construction",
            "type":"Services"
        }
    ],
    "sg:phone":"+1 718 731 8100",
    "sg:postcode":"10457",
    "sg:province":"NY",
    "sg:tags":[
        "concrete",
        "contractor"
    ],
    "wof:name":"Buchalter Construction Corp",
    "wof:placetype":"venue"
},
  "geometry": {"coordinates":[-73.895353,40.8482],"type":"Point"}
}