{
  "type": "Feature",
  "properties": {
    "addr:full":"516 Kibbie Lake Rd Constantia NY 13044",
    "addr:housenumber":"516",
    "addr:postcode":"13044",
    "addr:street":"Kibbie Lake Rd",
    "iso:country":"US",
    "sg:address":"516 Kibbie Lake Rd",
    "sg:city":"Constantia",
    "sg:classifiers":[
        {
            "category":"Shopping",
            "subcategory":"Computers & Home Electronics",
            "type":"Retail Goods"
        }
    ],
    "sg:phone":"+1   ",
    "sg:postcode":"13044",
    "sg:province":"NY",
    "wof:name":"E-Cottage Industries",
    "wof:placetype":"venue"
},
  "geometry": {"coordinates":[-75.96339399999999,43.273899],"type":"Point"}
}