{
  "type": "Feature",
  "properties": {
    "addr:full":"32 Avenue of the Americas 19th Fl New York NY 10013",
    "addr:housenumber":"32",
    "addr:postcode":"10013",
    "addr:street":"Avenue Of The Americas 19Th Fl",
    "iso:country":"US",
    "sg:address":"32 Avenue of the Americas 19th Fl",
    "sg:city":"New York",
    "sg:classifiers":[
        {
            "category":"Professional",
            "subcategory":"Art Services",
            "type":"Services"
        }
    ],
    "sg:phone":"+1 212 812 6600",
    "sg:postcode":"10013",
    "sg:province":"NY",
    "sg:tags":[
        "graphic",
        "design"
    ],
    "sg:website":"www.bartleboglehegarty.com",
    "wof:name":"Bartle Bogle Hegarty",
    "wof:placetype":"venue"
},
  "geometry": {"coordinates":[-74.005239,40.721052],"type":"Point"}
}