{
  "type": "Feature",
  "properties": {
    "addr:full":"451 W 33 St Manhattan NY 10001",
    "addr:housenumber":"451",
    "addr:postcode":"10001",
    "addr:street":"W 33 St",
    "iso:country":"US",
    "sg:address":"451 W 33 St",
    "sg:city":"Manhattan",
    "sg:classifiers":[
        {
            "category":"Food & Beverages",
            "subcategory":"Groceries & Convenience Stores",
            "type":"Retail Goods"
        }
    ],
    "sg:phone":"+1 212 210 2101",
    "sg:postcode":"10001",
    "sg:province":"NY",
    "wof:name":"Cohete Deli's",
    "wof:placetype":"venue"
},
  "geometry": {"coordinates":[-73.99831399999999,40.753383],"type":"Point"}
}