{
  "type": "Feature",
  "properties": {
    "addr:full":"967 Route 22 Brewster NY 10509",
    "addr:housenumber":"967",
    "addr:postcode":"10509",
    "addr:street":"Route 22",
    "iso:country":"US",
    "sg:address":"967 Route 22",
    "sg:city":"Brewster",
    "sg:classifiers":[
        {
            "category":"Education",
            "subcategory":"Kindergarten",
            "type":"Public Place"
        }
    ],
    "sg:phone":"+1 845 279 8686",
    "sg:postcode":"10509",
    "sg:province":"NY",
    "sg:tags":[
        "school",
        "driving"
    ],
    "wof:name":"Putnam Professional School of Driving Inc",
    "wof:placetype":"venue"
},
  "geometry": {"coordinates":[-73.603996,41.396801],"type":"Point"}
}