{
  "type": "Feature",
  "properties": {
    "addr:full":"22 N Cottage St Valley Stream NY 11580",
    "addr:housenumber":"22",
    "addr:postcode":"11580",
    "addr:street":"N Cottage St",
    "iso:country":"US",
    "sg:address":"22 N Cottage St",
    "sg:city":"Valley Stream",
    "sg:classifiers":[
        {
            "category":"Real Estate",
            "subcategory":"Real Estate Agent",
            "type":"Services"
        }
    ],
    "sg:phone":"+1 516 561 7435",
    "sg:postcode":"11580",
    "sg:province":"NY",
    "wof:name":"George J Brucker Appraisal Svc",
    "wof:placetype":"venue"
},
  "geometry": {"coordinates":[-73.694897,40.664004],"type":"Point"}
}