{
  "type": "Feature",
  "properties": {
    "iso:country":"US",
    "sg:address":"2803 Brewerton Rd",
    "sg:city":"Syracuse",
    "sg:classifiers":[
        {
            "category":"Wholesale",
            "subcategory":"Machinery & Supplies",
            "type":"Manufacturing & Wholesale Goods"
        }
    ],
    "sg:phone":"+1 315 455 8257",
    "sg:postcode":"13211",
    "sg:province":"NY",
    "sg:tags":[
        "shop",
        "equipment",
        "salon",
        "barber",
        "beauty"
    ],
    "wof:name":"F H Loeffler",
    "wof:placetype":"venue"
},
  "geometry": {"coordinates":[-76.14615499999999,43.106943],"type":"Point"}
}