{
  "type": "Feature",
  "properties": {
    "addr:full":"7983 Devaul Rd Kirkville NY 13082",
    "addr:housenumber":"7983",
    "addr:postcode":"13082",
    "addr:street":"Devaul Rd",
    "iso:country":"US",
    "sg:address":"7983 Devaul Rd",
    "sg:city":"Kirkville",
    "sg:classifiers":[
        {
            "category":"Freight",
            "type":"Transportation"
        }
    ],
    "sg:phone":"+1 315 687 6235",
    "sg:postcode":"13082",
    "sg:province":"NY",
    "sg:tags":[
        "delivery"
    ],
    "wof:name":"Don's Delivery Svc",
    "wof:placetype":"venue"
},
  "geometry": {"coordinates":[-75.93153100000001,43.104457],"type":"Point"}
}