{
  "type": "Feature",
  "properties": {
    "addr:full":"83 Water St Troy NY 12180",
    "addr:housenumber":"83",
    "addr:postcode":"12180",
    "addr:street":"Water St",
    "iso:country":"US",
    "sg:address":"83 Water St",
    "sg:city":"Troy",
    "sg:classifiers":[
        {
            "category":"Professional",
            "subcategory":"Management & Consulting",
            "type":"Services"
        }
    ],
    "sg:phone":"+1 518 274 4300",
    "sg:postcode":"12180",
    "sg:province":"NY",
    "sg:tags":[
        "environmental",
        "consultant"
    ],
    "wof:name":"D & D Environmental LLC",
    "wof:placetype":"venue"
},
  "geometry": {"coordinates":[-73.696774,42.703903],"type":"Point"}
}