{
  "type": "Feature",
  "properties": {
    "addr:full":"307 82nd St Brooklyn NY 11209",
    "addr:housenumber":"307",
    "addr:postcode":"11209",
    "addr:street":"82Nd St",
    "iso:country":"US",
    "sg:address":"307 82nd St",
    "sg:city":"Brooklyn",
    "sg:classifiers":[
        {
            "category":"Personal",
            "subcategory":"Beauty Salon",
            "type":"Services"
        }
    ],
    "sg:phone":"+1   ",
    "sg:postcode":"11209",
    "sg:province":"NY",
    "sg:tags":[
        "shop"
    ],
    "wof:name":"Mane Event",
    "wof:placetype":"venue"
},
  "geometry": {"coordinates":[-74.02725700000001,40.625838],"type":"Point"}
}