{
  "type": "Feature",
  "properties": {
    "addr:full":"45 E 18 St New York NY 10003",
    "addr:housenumber":"45;18",
    "addr:postcode":"10003",
    "addr:street":"E;St",
    "iso:country":"US",
    "sg:address":"45 E 18 St",
    "sg:city":"New York",
    "sg:classifiers":[
        {
            "category":"Restaurant",
            "type":"Food & Drink"
        }
    ],
    "sg:phone":"+1   ",
    "sg:postcode":"10003",
    "sg:province":"NY",
    "sg:tags":[
        "bar"
    ],
    "wof:name":"Old Town Bar & Restrnt",
    "wof:placetype":"venue"
},
  "geometry": {"coordinates":[-73.990123,40.737795],"type":"Point"}
}