{
  "type": "Feature",
  "properties": {
    "iso:country":"US",
    "sg:address":"2070 State Hwy 52",
    "sg:city":"Hopewell Jct",
    "sg:classifiers":[
        {
            "category":"Building & Trades",
            "subcategory":"Landscaping Services",
            "type":"Services"
        }
    ],
    "sg:phone":"+1 845 896 7293",
    "sg:postcode":"12533",
    "sg:province":"NY",
    "sg:tags":[
        "tree"
    ],
    "sg:website":"www.davey.com",
    "wof:name":"Davey Tree Expert Co",
    "wof:placetype":"venue"
},
  "geometry": {"coordinates":[-73.776347,41.56276],"type":"Point"}
}