{
  "type": "Feature",
  "properties": {
    "addr:full":"535 W 110th St New York NY 10025",
    "addr:housenumber":"535",
    "addr:postcode":"10025",
    "addr:street":"W 110Th St",
    "iso:country":"US",
    "sg:address":"535 W 110th St",
    "sg:city":"New York",
    "sg:classifiers":[
        {
            "category":"Real Estate",
            "subcategory":"Real Estate Operator",
            "type":"Services"
        }
    ],
    "sg:phone":"+1 212 222 0309",
    "sg:postcode":"10025",
    "sg:province":"NY",
    "sg:tags":[
        "building",
        "apartment"
    ],
    "wof:name":"Marsid Realties",
    "wof:placetype":"venue"
},
  "geometry": {"coordinates":[-73.96605700000001,40.803896],"type":"Point"}
}