{
  "type": "Feature",
  "properties": {
    "addr:full":"8922 Doran Ave Glendale NY 11385",
    "addr:housenumber":"8922",
    "addr:postcode":"11385",
    "addr:street":"Doran Ave",
    "iso:country":"US",
    "sg:address":"8922 Doran Ave",
    "sg:city":"Glendale",
    "sg:classifiers":[
        {
            "category":"Real Estate",
            "subcategory":"Real Estate Services",
            "type":"Services"
        },
        {
            "category":"Real Estate",
            "subcategory":"Real Estate Agent",
            "type":"Services"
        }
    ],
    "sg:phone":"+1 718 830 0545",
    "sg:postcode":"11385",
    "sg:province":"NY",
    "sg:tags":[
        "buyer",
        "broker"
    ],
    "wof:name":"Sabino Realty Corp",
    "wof:placetype":"venue"
},
  "geometry": {"coordinates":[-73.865841,40.708521],"type":"Point"}
}