{
  "type": "Feature",
  "properties": {
    "addr:full":"43 Roberts St Endicott NY 13760",
    "addr:housenumber":"43",
    "addr:postcode":"13760",
    "addr:street":"Roberts St",
    "iso:country":"US",
    "sg:address":"43 Roberts St",
    "sg:city":"Endicott",
    "sg:classifiers":[
        {
            "category":"Health Services",
            "subcategory":"Dentist",
            "type":"Services"
        }
    ],
    "sg:phone":"+1 607 785 5830",
    "sg:postcode":"13760",
    "sg:province":"NY",
    "wof:name":"Joseph T Dohnalek",
    "wof:placetype":"venue"
},
  "geometry": {"coordinates":[-76.073486,42.163478],"type":"Point"}
}