{
  "type": "Feature",
  "properties": {
    "iso:country":"US",
    "sg:address":"160 Mill Rd",
    "sg:city":"New Canaan",
    "sg:classifiers":[
        {
            "category":"Professional",
            "subcategory":"Engineering",
            "type":"Services"
        }
    ],
    "sg:phone":"+1   ",
    "sg:postcode":"06840",
    "sg:province":"NY",
    "wof:name":"Black - Lee  John Associates",
    "wof:placetype":"venue"
},
  "geometry": {"coordinates":[-73.449392,41.154161],"type":"Point"}
}