{
  "type": "Feature",
  "properties": {
    "addr:full":"300 Park Ave New York NY 10022",
    "addr:housenumber":"300",
    "addr:postcode":"10022",
    "addr:street":"Park Ave",
    "iso:country":"US",
    "sg:address":"300 Park Ave",
    "sg:city":"New York",
    "sg:classifiers":[
        {
            "category":"Real Estate",
            "subcategory":"Real Estate Agent",
            "type":"Services"
        },
        {
            "category":"Banks & Credit Unions",
            "subcategory":"Financial Services",
            "type":"Services"
        }
    ],
    "sg:phone":"+1 212 572 6377",
    "sg:postcode":"10022",
    "sg:province":"NY",
    "sg:tags":[
        "realty"
    ],
    "wof:name":"New York Realty Services LLC",
    "wof:placetype":"venue"
},
  "geometry": {"coordinates":[-73.97416200000001,40.757008],"type":"Point"}
}