{
  "type": "Feature",
  "properties": {
    "iso:country":"US",
    "sg:address":"505 Kings Hwy",
    "sg:city":"Valley Cottage",
    "sg:classifiers":[
        {
            "category":"Building & Trades",
            "subcategory":"Landscaping Services",
            "type":"Services"
        }
    ],
    "sg:phone":"+1 845 353 5114",
    "sg:postcode":"10989",
    "sg:province":"NY",
    "sg:tags":[
        "landscape",
        "contractor"
    ],
    "wof:name":"Blue Sky Lawncare-Landscape",
    "wof:placetype":"venue"
},
  "geometry": {"coordinates":[-73.94935099999999,41.118645],"type":"Point"}
}