{
  "type": "Feature",
  "properties": {
    "iso:country":"US",
    "sg:address":"345 E 9 St",
    "sg:city":"New York",
    "sg:classifiers":[
        {
            "category":"Personal",
            "subcategory":"Beauty Salon",
            "type":"Services"
        }
    ],
    "sg:phone":"+1   ",
    "sg:postcode":"10003",
    "sg:province":"NY",
    "sg:tags":[
        "shop"
    ],
    "wof:name":"Monique K Skin Care Inc",
    "wof:placetype":"venue"
},
  "geometry": {"coordinates":[-73.985643,40.728707],"type":"Point"}
}