{
  "type": "Feature",
  "properties": {
    "addr:full":"235 Park Ave New York NY 10017",
    "addr:housenumber":"235",
    "addr:postcode":"10017",
    "addr:street":"Park Ave",
    "iso:country":"US",
    "sg:address":"235 Park Ave",
    "sg:city":"New York",
    "sg:classifiers":[
        {
            "category":"Restaurant",
            "type":"Food & Drink"
        }
    ],
    "sg:menulink":"http://www.allmenus.com/ny/new-york/2590-city-crab/menu/",
    "sg:phone":"+1 212 529 3800",
    "sg:postcode":"10017",
    "sg:province":"NY",
    "sg:tags":[
        "seafood",
        "american"
    ],
    "wof:name":"City Crab",
    "wof:placetype":"venue"
},
  "geometry": {"coordinates":[-73.97568699999999,40.754586],"type":"Point"}
}