{
  "type": "Feature",
  "properties": {
    "addr:full":"744 Sheridan Dr Tonawanda NY 14150",
    "addr:housenumber":"744",
    "addr:postcode":"14150",
    "addr:street":"Sheridan Dr",
    "iso:country":"US",
    "sg:address":"744 Sheridan Dr",
    "sg:city":"Tonawanda",
    "sg:classifiers":[
        {
            "category":"Government",
            "subcategory":"Fire Station",
            "type":"Public Place"
        }
    ],
    "sg:phone":"+1 716 873 2801",
    "sg:postcode":"14150",
    "sg:province":"NY",
    "sg:tags":[
        "department",
        "protection"
    ],
    "wof:name":"Sheridan Park Fire Dist No 4",
    "wof:placetype":"venue"
},
  "geometry": {"coordinates":[-78.904706,42.978786],"type":"Point"}
}