{
  "type": "Feature",
  "properties": {
    "iso:country":"US",
    "sg:address":"220 E 42nd St",
    "sg:city":"New York",
    "sg:classifiers":[
        {
            "category":"Professional",
            "subcategory":"Business Services",
            "type":"Services"
        }
    ],
    "sg:phone":"+1 212 758 8130",
    "sg:postcode":"10017",
    "sg:province":"NY",
    "sg:tags":[
        "information",
        "referral"
    ],
    "sg:website":"www.visitbelgium.com",
    "wof:name":"Belgian National Tourist Ofc",
    "wof:placetype":"venue"
},
  "geometry": {"coordinates":[-73.972587,40.74995],"type":"Point"}
}