{
  "type": "Feature",
  "properties": {
    "iso:country":"US",
    "sg:address":"815 Burke Ave",
    "sg:city":"Bronx",
    "sg:classifiers":[
        {
            "category":"Government",
            "subcategory":"Office",
            "type":"Public Place"
        }
    ],
    "sg:phone":"+1 718 519 5101",
    "sg:postcode":"10467",
    "sg:province":"NY",
    "sg:tags":[
        "state",
        "resource"
    ],
    "wof:name":"Community Service Ctr",
    "wof:placetype":"venue"
},
  "geometry": {"coordinates":[-73.862683,40.871439],"type":"Point"}
}