{
  "type": "Feature",
  "properties": {
    "addr:full":"8 W Main St Lockport NY 14094",
    "addr:housenumber":"8",
    "addr:postcode":"14094",
    "addr:street":"W Main St",
    "iso:country":"US",
    "sg:address":"8 W Main St",
    "sg:city":"Lockport",
    "sg:classifiers":[
        {
            "category":"Professional",
            "subcategory":"Lawyer & Legal Services",
            "type":"Services"
        }
    ],
    "sg:phone":"+1 716 433 0143",
    "sg:postcode":"14094",
    "sg:province":"NY",
    "sg:tags":[
        "attorney",
        "practice"
    ],
    "wof:name":"Henry W Schmidt",
    "wof:placetype":"venue"
},
  "geometry": {"coordinates":[-78.695908,43.169075],"type":"Point"}
}