{
  "type": "Feature",
  "properties": {
    "addr:full":"124 Nassau St Ste 2 New York NY 10038",
    "addr:housenumber":"124",
    "addr:postcode":"10038",
    "addr:street":"Nassau St Ste 2",
    "iso:country":"US",
    "sg:address":"124 Nassau St Ste 2",
    "sg:city":"New York",
    "sg:classifiers":[
        {
            "category":"Professional",
            "subcategory":"Lawyer & Legal Services",
            "type":"Services"
        }
    ],
    "sg:phone":"+1 646 587 0188",
    "sg:postcode":"10038",
    "sg:province":"NY",
    "sg:tags":[
        "divorce",
        "law",
        "family"
    ],
    "sg:website":"www.divorceinnyc.com",
    "wof:name":"Liou & Maisonet, PLLC",
    "wof:placetype":"venue"
},
  "geometry": {"coordinates":[-74.00671,40.710855],"type":"Point"}
}