{
  "type": "Feature",
  "properties": {
    "addr:full":"1971 Colvin Blvd Tonawanda NY 14150",
    "addr:housenumber":"1971",
    "addr:postcode":"14150",
    "addr:street":"Colvin Blvd",
    "iso:country":"US",
    "sg:address":"1971 Colvin Blvd",
    "sg:city":"Tonawanda",
    "sg:classifiers":[
        {
            "category":"Banks & Credit Unions",
            "subcategory":"Investment Brokerage",
            "type":"Services"
        },
        {
            "category":"Cinema",
            "subcategory":"Movie Rental",
            "type":"Entertainment"
        },
        {
            "category":"Shopping",
            "subcategory":"Computers & Home Electronics",
            "type":"Retail Goods"
        }
    ],
    "sg:phone":"+1 716 832 2720",
    "sg:postcode":"14150",
    "sg:province":"NY",
    "sg:tags":[
        "leasing",
        "dvd",
        "sale",
        "dvds-rental",
        "video",
        "tape",
        "games-renting"
    ],
    "sg:website":"http://www.familyvideo.com",
    "wof:name":"Family Video",
    "wof:placetype":"venue"
},
  "geometry": {"coordinates":[-78.85275300000001,42.991694],"type":"Point"}
}