{
  "type": "Feature",
  "properties": {
    "iso:country":"US",
    "sg:address":"950 New Loudon Rd",
    "sg:city":"Latham",
    "sg:classifiers":[
        {
            "category":"Banks & Credit Unions",
            "subcategory":"Investment Brokerage",
            "type":"Services"
        }
    ],
    "sg:phone":"+1 518 785 1435",
    "sg:postcode":"12110",
    "sg:province":"NY",
    "sg:tags":[
        "management"
    ],
    "wof:name":"Center Square Asset Mgmt",
    "wof:placetype":"venue"
},
  "geometry": {"coordinates":[-73.754524,42.766587],"type":"Point"}
}