{
  "type": "Feature",
  "properties": {
    "iso:country":"US",
    "sg:address":"2171 Bragg St",
    "sg:city":"Brooklyn",
    "sg:classifiers":[
        {
            "category":"Real Estate",
            "subcategory":"Real Estate Agent",
            "type":"Services"
        }
    ],
    "sg:phone":"+1 718 769 5806",
    "sg:postcode":"11229",
    "sg:province":"NY",
    "sg:tags":[
        "cooperative"
    ],
    "wof:name":"Brigham Park Co Op Sect 3",
    "wof:placetype":"venue"
},
  "geometry": {"coordinates":[-73.935942,40.600456],"type":"Point"}
}