{
  "type": "Feature",
  "properties": {
    "addr:full":"168 James Street Manor East Syracuse NY 13057",
    "addr:housenumber":"168",
    "addr:postcode":"13057",
    "addr:street":"James Street",
    "iso:country":"US",
    "sg:address":"168 James Street Manor",
    "sg:city":"East Syracuse",
    "sg:classifiers":[
        {
            "category":"Social Services",
            "subcategory":"Adult Care",
            "type":"Services"
        }
    ],
    "sg:phone":"+1 315 463 8829",
    "sg:postcode":"13057",
    "sg:province":"NY",
    "sg:tags":[
        "retardation",
        "home",
        "dev",
        "disabled"
    ],
    "wof:name":"Syracuse Developmental Ctr",
    "wof:placetype":"venue"
},
  "geometry": {"coordinates":[-76.066902,43.070583],"type":"Point"}
}