{
  "type": "Feature",
  "properties": {
    "addr:full":"1175 Flatbush Ave Brooklyn NY 11226",
    "addr:housenumber":"1175",
    "addr:postcode":"11226",
    "addr:street":"Flatbush Ave",
    "iso:country":"US",
    "sg:address":"1175 Flatbush Ave",
    "sg:city":"Brooklyn",
    "sg:classifiers":[
        {
            "category":"Insurance",
            "subcategory":"Insurance Agent",
            "type":"Services"
        }
    ],
    "sg:phone":"+1 718 652 4131",
    "sg:postcode":"11226",
    "sg:province":"NY",
    "wof:name":"Priceline Insurance",
    "wof:placetype":"venue"
},
  "geometry": {"coordinates":[-73.955904,40.640959],"type":"Point"}
}