{
  "type": "Feature",
  "properties": {
    "addr:full":"70 Escanaba Ave Staten Island NY 10308",
    "addr:housenumber":"70",
    "addr:postcode":"10308",
    "addr:street":"Escanaba Ave",
    "iso:country":"US",
    "sg:address":"70 Escanaba Ave",
    "sg:city":"Staten Island",
    "sg:classifiers":[
        {
            "category":"Building & Trades",
            "subcategory":"Pest Control",
            "type":"Services"
        }
    ],
    "sg:phone":"+1 718 317 1464",
    "sg:postcode":"10308",
    "sg:province":"NY",
    "wof:name":"K & J Pest Control",
    "wof:placetype":"venue"
},
  "geometry": {"coordinates":[-74.15988400000001,40.551377],"type":"Point"}
}