{
  "type": "Feature",
  "properties": {
    "iso:country":"US",
    "sg:address":"1078 Morris Park Ave",
    "sg:city":"Bronx",
    "sg:classifiers":[
        {
            "category":"Food & Beverages",
            "subcategory":"Bakery",
            "type":"Retail Goods"
        }
    ],
    "sg:phone":"+1 718 892 1736",
    "sg:postcode":"10461",
    "sg:province":"NY",
    "sg:tags":[
        "baker"
    ],
    "wof:name":"Scaglione Joseph Bakery",
    "wof:placetype":"venue"
},
  "geometry": {"coordinates":[-73.8536,40.849201],"type":"Point"}
}