{
  "type": "Feature",
  "properties": {
    "iso:country":"US",
    "sg:address":"347 Violet Ave",
    "sg:city":"Poughkeepsie",
    "sg:classifiers":[
        {
            "category":"Retail",
            "subcategory":"Self-service Laundry",
            "type":"Services"
        }
    ],
    "sg:phone":"+1 845 471 4639",
    "sg:postcode":"12601",
    "sg:province":"NY",
    "wof:name":"Laundromat",
    "wof:placetype":"venue"
},
  "geometry": {"coordinates":[-73.909288,41.736334],"type":"Point"}
}