{
  "type": "Feature",
  "properties": {
    "addr:full":"87 Kathleen Dr Syosset NY 11791",
    "addr:housenumber":"87",
    "addr:postcode":"11791",
    "addr:street":"Kathleen Dr",
    "iso:country":"US",
    "sg:address":"87 Kathleen Dr",
    "sg:city":"Syosset",
    "sg:classifiers":[
        {
            "category":"Professional",
            "subcategory":"Computer Services",
            "type":"Services"
        }
    ],
    "sg:phone":"+1   ",
    "sg:postcode":"11791",
    "sg:province":"NY",
    "sg:tags":[
        "consultant"
    ],
    "wof:name":"Kaolin Computer Service",
    "wof:placetype":"venue"
},
  "geometry": {"coordinates":[-73.501434,40.802537],"type":"Point"}
}