{
  "type": "Feature",
  "properties": {
    "addr:full":"207 Hamden Ave Staten Island NY 10306",
    "addr:housenumber":"207",
    "addr:postcode":"10306",
    "addr:street":"Hamden Ave",
    "iso:country":"US",
    "sg:address":"207 Hamden Ave",
    "sg:city":"Staten Island",
    "sg:classifiers":[
        {
            "category":"Real Estate",
            "subcategory":"Real Estate Agent",
            "type":"Services"
        }
    ],
    "sg:phone":"+1 718 667 1658",
    "sg:postcode":"10306",
    "sg:province":"NY",
    "wof:name":"107 Luquer St Realty Corp",
    "wof:placetype":"venue"
},
  "geometry": {"coordinates":[-74.101596,40.579642],"type":"Point"}
}