{
  "type": "Feature",
  "properties": {
    "iso:country":"US",
    "sg:address":"384 Vine Ln",
    "sg:city":"Buffalo",
    "sg:classifiers":[
        {
            "category":"Shopping",
            "subcategory":"Discount & Variety Stores",
            "type":"Retail Goods"
        }
    ],
    "sg:phone":"+1 716 691 5378",
    "sg:postcode":"14228",
    "sg:province":"NY",
    "wof:name":"In Jest Comedy Variety",
    "wof:placetype":"venue"
},
  "geometry": {"coordinates":[-78.80617700000001,43.049144],"type":"Point"}
}