{
  "type": "Feature",
  "properties": {
    "addr:full":"515 North St White Plains NY 10605",
    "addr:housenumber":"515",
    "addr:postcode":"10605",
    "addr:street":"North St",
    "iso:country":"US",
    "sg:address":"515 North St",
    "sg:city":"White Plains",
    "sg:classifiers":[
        {
            "category":"Restaurant",
            "type":"Food & Drink"
        }
    ],
    "sg:phone":"+1 914 946 6161",
    "sg:postcode":"10605",
    "sg:province":"NY",
    "sg:tags":[
        "caterer"
    ],
    "wof:name":"Hazels Cafe & Catering",
    "wof:placetype":"venue"
},
  "geometry": {"coordinates":[-73.74014099999999,41.021097],"type":"Point"}
}