{
  "type": "Feature",
  "properties": {
    "addr:full":"702 Amsterdam Ave New York NY 10025",
    "addr:housenumber":"702",
    "addr:postcode":"10025",
    "addr:street":"Amsterdam Ave",
    "iso:country":"US",
    "sg:address":"702 Amsterdam Ave",
    "sg:city":"New York",
    "sg:classifiers":[
        {
            "category":"Restaurant",
            "type":"Food & Drink"
        }
    ],
    "sg:menulink":"http://www.allmenus.com/ny/new-york/7034-sifan-nuevo-peruano/menu/",
    "sg:phone":"+1 212 665 9929",
    "sg:postcode":"10025",
    "sg:province":"NY",
    "sg:tags":[
        "french"
    ],
    "wof:name":"Sifan Nuevo Peruano",
    "wof:placetype":"venue"
},
  "geometry": {"coordinates":[-73.97151599999999,40.793001],"type":"Point"}
}