{
  "type": "Feature",
  "properties": {
    "iso:country":"US",
    "sg:address":"32 Whitfield Ln",
    "sg:city":"Coram",
    "sg:classifiers":[
        {
            "category":"Health Services",
            "subcategory":"Clinic",
            "type":"Services"
        }
    ],
    "sg:phone":"+1   ",
    "sg:postcode":"11727",
    "sg:province":"NY",
    "wof:name":"Lifetime Systems Med Billing",
    "wof:placetype":"venue"
},
  "geometry": {"coordinates":[-73.024278,40.896317],"type":"Point"}
}