{
  "type": "Feature",
  "properties": {
    "iso:country":"US",
    "sg:address":"617 Bicycle Path",
    "sg:city":"Port Jeffrsn Sta",
    "sg:classifiers":[
        {
            "category":"Shopping",
            "subcategory":"Clothing, Apparel, & Fashions",
            "type":"Retail Goods"
        }
    ],
    "sg:phone":"+1 631 473 7301",
    "sg:postcode":"11776",
    "sg:province":"NY",
    "wof:name":"Wild Ride Fashions",
    "wof:placetype":"venue"
},
  "geometry": {"coordinates":[-73.03742800000001,40.906502],"type":"Point"}
}