{
  "type": "Feature",
  "properties": {
    "addr:full":"55 Jersey Ave Port Jervis NY 12771",
    "addr:housenumber":"55",
    "addr:postcode":"12771",
    "addr:street":"Jersey Ave",
    "iso:country":"US",
    "sg:address":"55 Jersey Ave",
    "sg:city":"Port Jervis",
    "sg:phone":"+1 845 858 2542",
    "sg:postcode":"12771",
    "sg:province":"NY",
    "sg:tags":[
        "material",
        "fixture",
        "display"
    ],
    "wof:name":"Flannagan's Creative Displays",
    "wof:placetype":"venue"
},
  "geometry": {"coordinates":[-74.68982699999999,41.370584],"type":"Point"}
}