{
  "type": "Feature",
  "properties": {
    "addr:full":"23 Hampton Dr Carmel NY 10512",
    "addr:housenumber":"23",
    "addr:postcode":"10512",
    "addr:street":"Hampton Dr",
    "iso:country":"US",
    "sg:address":"23 Hampton Dr",
    "sg:city":"Carmel",
    "sg:classifiers":[
        {
            "category":"Shopping",
            "subcategory":"Computers & Home Electronics",
            "type":"Retail Goods"
        }
    ],
    "sg:phone":"+1 845 225 6660",
    "sg:postcode":"10512",
    "sg:province":"NY",
    "sg:tags":[
        "equipment",
        "dealer"
    ],
    "wof:name":"Computer Science Corp",
    "wof:placetype":"venue"
},
  "geometry": {"coordinates":[-73.66242699999999,41.474676],"type":"Point"}
}