{
  "type": "Feature",
  "properties": {
    "addr:full":"292 8th Ave New York NY 10001",
    "addr:housenumber":"292",
    "addr:postcode":"10001",
    "addr:street":"8Th Ave",
    "iso:country":"US",
    "sg:address":"292 8th Ave",
    "sg:city":"New York",
    "sg:classifiers":[
        {
            "category":"Retail",
            "subcategory":"Laundry & Dry Cleaning",
            "type":"Services"
        }
    ],
    "sg:phone":"+1 212 675 8966",
    "sg:postcode":"10001",
    "sg:province":"NY",
    "wof:name":"M & N Cleaners",
    "wof:placetype":"venue"
},
  "geometry": {"coordinates":[-73.997803,40.7463],"type":"Point"}
}