{
  "type": "Feature",
  "properties": {
    "iso:country":"US",
    "sg:address":"763 Hoosick Rd",
    "sg:city":"Troy",
    "sg:classifiers":[
        {
            "category":"Health Services",
            "subcategory":"Doctor",
            "type":"Services"
        }
    ],
    "sg:phone":"+1 518 273 3311",
    "sg:postcode":"12180",
    "sg:province":"NY",
    "sg:tags":[
        "physician",
        "surgeon"
    ],
    "wof:name":"Nebres & Patel",
    "wof:placetype":"venue"
},
  "geometry": {"coordinates":[-73.640038,42.7467],"type":"Point"}
}