{
  "type": "Feature",
  "properties": {
    "iso:country":"US",
    "sg:address":"134 W Alhambra Ave",
    "sg:city":"Lindenhurst",
    "sg:classifiers":[
        {
            "category":"Professional",
            "subcategory":"Accounting & Tax Preparation",
            "type":"Services"
        }
    ],
    "sg:phone":"+1   ",
    "sg:postcode":"11757",
    "sg:province":"NY",
    "wof:name":"Basic First Inc",
    "wof:placetype":"venue"
},
  "geometry": {"coordinates":[-73.38596,40.669888],"type":"Point"}
}