{
  "type": "Feature",
  "properties": {
    "addr:full":"2 Hedge Row Congers NY 10920",
    "addr:housenumber":"2",
    "addr:postcode":"10920",
    "addr:street":"Hedge Row",
    "iso:country":"US",
    "sg:address":"2 Hedge Row",
    "sg:city":"Congers",
    "sg:classifiers":[
        {
            "category":"Building & Trades",
            "subcategory":"Electrical",
            "type":"Services"
        }
    ],
    "sg:phone":"+1 845 268 4123",
    "sg:postcode":"10920",
    "sg:province":"NY",
    "sg:tags":[
        "industrial",
        "electrician",
        "contractors-commercial",
        "electric"
    ],
    "wof:name":"Red Star Electric Corp",
    "wof:placetype":"venue"
},
  "geometry": {"coordinates":[-73.94801200000001,41.154415],"type":"Point"}
}