{
  "type": "Feature",
  "properties": {
    "iso:country":"US",
    "sg:address":"350 Central Park West Apt. 16A",
    "sg:city":"Manhattan",
    "sg:classifiers":[
        {
            "category":"Health Services",
            "subcategory":"Doctor",
            "type":"Services"
        }
    ],
    "sg:phone":"+1 212 316 3211",
    "sg:postcode":"10025",
    "sg:province":"NY",
    "sg:tags":[
        "psychiatrist"
    ],
    "sg:website":"www.healthline.com/doctors/psych...",
    "wof:name":"Fiona Graham, MD",
    "wof:placetype":"venue"
},
  "geometry": {"coordinates":[-73.965745,40.790817],"type":"Point"}
}