{
  "type": "Feature",
  "properties": {
    "iso:country":"US",
    "sg:address":"580 2nd Ave",
    "sg:city":"Troy",
    "sg:classifiers":[
        {
            "category":"Professional",
            "type":"Services"
        }
    ],
    "sg:phone":"+1 518 233 1729",
    "sg:postcode":"12182",
    "sg:province":"NY",
    "sg:tags":[
        "establishment"
    ],
    "wof:name":"Clutter Country",
    "wof:placetype":"venue"
},
  "geometry": {"coordinates":[-73.676802,42.775334],"type":"Point"}
}