{
  "type": "Feature",
  "properties": {
    "addr:full":"250 Delaware Ave Buffalo NY 14202",
    "addr:housenumber":"250",
    "addr:postcode":"14202",
    "addr:street":"Delaware Ave",
    "iso:country":"US",
    "sg:address":"250 Delaware Ave",
    "sg:city":"Buffalo",
    "sg:classifiers":[
        {
            "category":"Recreation",
            "type":"Entertainment"
        }
    ],
    "sg:phone":"+1 716 856 4990",
    "sg:postcode":"14202",
    "sg:province":"NY",
    "sg:tags":[
        "riding",
        "academy"
    ],
    "wof:name":"Millennium Dance Academy",
    "wof:placetype":"venue"
},
  "geometry": {"coordinates":[-78.876541,42.891519],"type":"Point"}
}