{
  "type": "Feature",
  "properties": {
    "addr:full":"137 Elm St New Canaan NY 06840",
    "addr:housenumber":"137",
    "addr:postcode":"06840",
    "addr:street":"Elm St",
    "iso:country":"US",
    "sg:address":"137 Elm St",
    "sg:city":"New Canaan",
    "sg:classifiers":[
        {
            "category":"Restaurant",
            "type":"Food & Drink"
        }
    ],
    "sg:phone":"+1 203 966 4867",
    "sg:postcode":"06840",
    "sg:province":"NY",
    "sg:tags":[
        "parlor",
        "ice",
        "cream"
    ],
    "wof:name":"Baskin-Robbins",
    "wof:placetype":"venue"
},
  "geometry": {"coordinates":[-73.493939,41.146905],"type":"Point"}
}