{
  "type": "Feature",
  "properties": {
    "iso:country":"US",
    "sg:address":"89 Main St",
    "sg:city":"Southampton",
    "sg:classifiers":[
        {
            "category":"Shopping",
            "subcategory":"Clothing, Apparel, & Fashions",
            "type":"Retail Goods"
        }
    ],
    "sg:phone":"+1   ",
    "sg:postcode":"11968",
    "sg:province":"NY",
    "wof:name":"Complements Lingerie",
    "wof:placetype":"venue"
},
  "geometry": {"coordinates":[-72.38947400000001,40.884186],"type":"Point"}
}