{
  "type": "Feature",
  "properties": {
    "iso:country":"US",
    "sg:address":"2164 78th St",
    "sg:city":"Brooklyn",
    "sg:classifiers":[
        {
            "category":"Social Services",
            "subcategory":"Job Training",
            "type":"Services"
        }
    ],
    "sg:phone":"+1 718 331 0395",
    "sg:postcode":"11214",
    "sg:province":"NY",
    "sg:tags":[
        "counseling",
        "employment"
    ],
    "wof:name":"JCH Job Placement Ctr",
    "wof:placetype":"venue"
},
  "geometry": {"coordinates":[-73.99028199999999,40.607271],"type":"Point"}
}