{
  "type": "Feature",
  "properties": {
    "addr:full":"40 Gardenville Pkwy W Buffalo NY 14224",
    "addr:housenumber":"40",
    "addr:postcode":"14224",
    "addr:street":"Gardenville Pkwy W",
    "iso:country":"US",
    "sg:address":"40 Gardenville Pkwy W",
    "sg:city":"Buffalo",
    "sg:classifiers":[
        {
            "category":"Professional",
            "subcategory":"Computer Services",
            "type":"Services"
        }
    ],
    "sg:phone":"+1 716 558 4500",
    "sg:postcode":"14224",
    "sg:province":"NY",
    "sg:tags":[
        "design",
        "system"
    ],
    "wof:name":"P C Business Solutions",
    "wof:placetype":"venue"
},
  "geometry": {"coordinates":[-78.757448,42.864251],"type":"Point"}
}