{
  "type": "Feature",
  "properties": {
    "addr:full":"372-374 Bleecker St New York NY 10014",
    "addr:housenumber":"372-374",
    "addr:postcode":"10014",
    "addr:street":"Bleecker St",
    "iso:country":"US",
    "sg:address":"372-374 Bleecker St",
    "sg:city":"New York",
    "sg:classifiers":[
        {
            "category":"Shopping",
            "subcategory":"Clothing, Apparel, & Fashions",
            "type":"Retail Goods"
        }
    ],
    "sg:phone":"+1 212 206 8343",
    "sg:postcode":"10014",
    "sg:province":"NY",
    "sg:tags":[
        "accessory"
    ],
    "sg:website":"www.coach.com",
    "wof:name":"Coach",
    "wof:placetype":"venue"
},
  "geometry": {"coordinates":[-74.004824,40.734943],"type":"Point"}
}