{
  "type": "Feature",
  "properties": {
    "addr:full":"97 Tomhannock Rd Valley Falls NY 12185",
    "addr:housenumber":"97",
    "addr:postcode":"12185",
    "addr:street":"Tomhannock Rd",
    "iso:country":"US",
    "sg:address":"97 Tomhannock Rd",
    "sg:city":"Valley Falls",
    "sg:classifiers":[
        {
            "category":"Recreation",
            "type":"Entertainment"
        },
        {
            "category":"Real Estate",
            "subcategory":"Real Estate Operator",
            "type":"Services"
        }
    ],
    "sg:phone":"+1 518 753 6321",
    "sg:postcode":"12185",
    "sg:province":"NY",
    "sg:tags":[
        "building",
        "nonresidential",
        "hall",
        "auditorium"
    ],
    "wof:name":"Tomhannock United Methodist Ch",
    "wof:placetype":"venue"
},
  "geometry": {"coordinates":[-73.544791,42.869118],"type":"Point"}
}