{
  "type": "Feature",
  "properties": {
    "addr:full":"115 Nichols Ct Hempstead NY 11550",
    "addr:housenumber":"115",
    "addr:postcode":"11550",
    "addr:street":"Nichols Ct",
    "iso:country":"US",
    "sg:address":"115 Nichols Ct",
    "sg:city":"Hempstead",
    "sg:classifiers":[
        {
            "category":"Education",
            "subcategory":"Library",
            "type":"Public Place"
        }
    ],
    "sg:phone":"+1 516 481 6990",
    "sg:postcode":"11550",
    "sg:province":"NY",
    "sg:tags":[
        "executive"
    ],
    "wof:name":"Hempstead Public Library",
    "wof:placetype":"venue"
},
  "geometry": {"coordinates":[-73.62213300000001,40.710113],"type":"Point"}
}