{
  "type": "Feature",
  "properties": {
    "addr:full":"54 Lockwood Ave Bronxville NY 10708",
    "addr:housenumber":"54",
    "addr:postcode":"10708",
    "addr:street":"Lockwood Ave",
    "iso:country":"US",
    "sg:address":"54 Lockwood Ave",
    "sg:city":"Bronxville",
    "sg:classifiers":[
        {
            "category":"Building & Trades",
            "subcategory":"Construction",
            "type":"Services"
        }
    ],
    "sg:phone":"+1 914 738 2232",
    "sg:postcode":"10708",
    "sg:province":"NY",
    "sg:tags":[
        "paving",
        "contractor"
    ],
    "wof:name":"Beltop Paving Co Inc",
    "wof:placetype":"venue"
},
  "geometry": {"coordinates":[-73.806684,40.932527],"type":"Point"}
}