{
  "type": "Feature",
  "properties": {
    "iso:country":"US",
    "sg:address":"7101 Kirkville Rd",
    "sg:city":"East Syracuse",
    "sg:classifiers":[
        {
            "category":"Building & Trades",
            "subcategory":"Landscaping Services",
            "type":"Services"
        }
    ],
    "sg:phone":"+1 315 656 2092",
    "sg:postcode":"13057",
    "sg:province":"NY",
    "sg:tags":[
        "lawn",
        "garden"
    ],
    "sg:website":"www.qscapes.com",
    "wof:name":"Q-Scapes Inc",
    "wof:placetype":"venue"
},
  "geometry": {"coordinates":[-76.03457899999999,43.079813],"type":"Point"}
}