{
  "type": "Feature",
  "properties": {
    "addr:full":"134 N Greenbush Rd Troy NY 12180",
    "addr:housenumber":"134",
    "addr:postcode":"12180",
    "addr:street":"N Greenbush Rd",
    "iso:country":"US",
    "sg:address":"134 N Greenbush Rd",
    "sg:city":"Troy",
    "sg:classifiers":[
        {
            "category":"Organizations",
            "subcategory":"Community Association",
            "type":"Services"
        }
    ],
    "sg:phone":"+1 518 283 1193",
    "sg:postcode":"12180",
    "sg:province":"NY",
    "sg:tags":[
        "fraternal"
    ],
    "wof:name":"Elks Lodge",
    "wof:placetype":"venue"
},
  "geometry": {"coordinates":[-73.688259,42.686614],"type":"Point"}
}