{
  "type": "Feature",
  "properties": {
    "iso:country":"US",
    "sg:address":"667 Driggs Ave",
    "sg:city":"Brooklyn",
    "sg:classifiers":[
        {
            "category":"Coffee & Tea",
            "type":"Food & Drink"
        },
        {
            "category":"Bakery",
            "type":"Food & Drink"
        }
    ],
    "sg:phone":"+1 718 384 1212",
    "sg:postcode":"11211",
    "sg:province":"NY",
    "wof:name":"Margo Patisserie Cafe",
    "wof:placetype":"venue"
},
  "geometry": {"coordinates":[-73.95910499999999,40.714494],"type":"Point"}
}