{
  "type": "Feature",
  "properties": {
    "addr:full":"127 Central Dr Central Square NY 13036",
    "addr:housenumber":"127",
    "addr:postcode":"13036",
    "addr:street":"Central Dr",
    "iso:country":"US",
    "sg:address":"127 Central Dr",
    "sg:city":"Central Square",
    "sg:classifiers":[
        {
            "category":"Shopping",
            "subcategory":"Crafts & Fabrics",
            "type":"Retail Goods"
        }
    ],
    "sg:phone":"+1   ",
    "sg:postcode":"13036",
    "sg:province":"NY",
    "sg:tags":[
        "sewing"
    ],
    "wof:name":"Pearls Golden Thimble",
    "wof:placetype":"venue"
},
  "geometry": {"coordinates":[-76.146164,43.276404],"type":"Point"}
}