{
  "type": "Feature",
  "properties": {
    "iso:country":"US",
    "sg:address":"1733 53rd St",
    "sg:city":"Brooklyn",
    "sg:classifiers":[
        {
            "category":"Organizations",
            "subcategory":"Religious Organization",
            "type":"Services"
        }
    ],
    "sg:phone":"+1 718 435 4242",
    "sg:postcode":"11204",
    "sg:province":"NY",
    "sg:tags":[
        "synagogue"
    ],
    "wof:name":"William Greenwald",
    "wof:placetype":"venue"
},
  "geometry": {"coordinates":[-73.98374200000001,40.626511],"type":"Point"}
}