{
  "type": "Feature",
  "properties": {
    "iso:country":"US",
    "sg:address":"60 Alexander Ave",
    "sg:city":"Farmingdale",
    "sg:classifiers":[
        {
            "category":"Utilities",
            "subcategory":"Telephone",
            "type":"Services"
        }
    ],
    "sg:phone":"+1   ",
    "sg:postcode":"11735",
    "sg:province":"NY",
    "sg:tags":[
        "web",
        "computer",
        "build"
    ],
    "wof:name":"Bloomington Realty Corp",
    "wof:placetype":"venue"
},
  "geometry": {"coordinates":[-73.42544100000001,40.743553],"type":"Point"}
}