{
  "type": "Feature",
  "properties": {
    "iso:country":"US",
    "sg:address":"5902 Ave D",
    "sg:city":"Brooklyn",
    "sg:classifiers":[
        {
            "category":"Professional",
            "type":"Services"
        }
    ],
    "sg:phone":"+1 718 451 4000",
    "sg:postcode":"11203",
    "sg:province":"NY",
    "sg:tags":[
        "establishment"
    ],
    "wof:name":"Elderwear",
    "wof:placetype":"venue"
},
  "geometry": {"coordinates":[-73.91977799999999,40.642646],"type":"Point"}
}