{
  "type": "Feature",
  "properties": {
    "addr:full":"555 Bedford Rd Bedford Hills NY 10507",
    "addr:housenumber":"555",
    "addr:postcode":"10507",
    "addr:street":"Bedford Rd",
    "iso:country":"US",
    "sg:address":"555 Bedford Rd",
    "sg:city":"Bedford Hills",
    "sg:classifiers":[
        {
            "category":"Retail",
            "subcategory":"Auto Repair",
            "type":"Services"
        }
    ],
    "sg:phone":"+1 914 666 7676",
    "sg:postcode":"10507",
    "sg:province":"NY",
    "sg:tags":[
        "body",
        "shop",
        "painting",
        "automobile"
    ],
    "wof:name":"Gary's Auto Body",
    "wof:placetype":"venue"
},
  "geometry": {"coordinates":[-73.71109800000001,41.2285],"type":"Point"}
}