{
  "type": "Feature",
  "properties": {
    "iso:country":"US",
    "sg:address":"400 W 43rd St",
    "sg:city":"New York",
    "sg:classifiers":[
        {
            "category":"Shopping",
            "subcategory":"Clothing, Apparel, & Fashions",
            "type":"Retail Goods"
        }
    ],
    "sg:phone":"+1   ",
    "sg:postcode":"10036",
    "sg:province":"NY",
    "sg:tags":[
        "gown",
        "bridal",
        "formal"
    ],
    "wof:name":"Augustine Bridal",
    "wof:placetype":"venue"
},
  "geometry": {"coordinates":[-73.994372,40.759875],"type":"Point"}
}