{
  "type": "Feature",
  "properties": {
    "iso:country":"US",
    "sg:address":"300 E Rockaway Rd",
    "sg:city":"East Rockaway",
    "sg:classifiers":[
        {
            "category":"Restaurant",
            "type":"Food & Drink"
        }
    ],
    "sg:phone":"+1   ",
    "sg:postcode":"11518",
    "sg:province":"NY",
    "sg:tags":[
        "eating"
    ],
    "wof:name":"Amazing Wok",
    "wof:placetype":"venue"
},
  "geometry": {"coordinates":[-73.673593,40.6414],"type":"Point"}
}