{
  "type": "Feature",
  "properties": {
    "iso:country":"US",
    "sg:address":"372 Dan Troy Dr",
    "sg:city":"Williamsville",
    "sg:classifiers":[
        {
            "category":"Health Services",
            "subcategory":"Doctor",
            "type":"Services"
        }
    ],
    "sg:phone":"+1 716 634 9498",
    "sg:postcode":"14221",
    "sg:province":"NY",
    "sg:tags":[
        "physician",
        "surgeon"
    ],
    "wof:name":"Nicola Borrillo MD",
    "wof:placetype":"venue"
},
  "geometry": {"coordinates":[-78.73481700000001,42.980523],"type":"Point"}
}