{
  "type": "Feature",
  "properties": {
    "addr:full":"1902 Genesee St Utica NY 13502",
    "addr:housenumber":"1902",
    "addr:postcode":"13502",
    "addr:street":"Genesee St",
    "iso:country":"US",
    "sg:address":"1902 Genesee St",
    "sg:city":"Utica",
    "sg:classifiers":[
        {
            "category":"Shopping",
            "subcategory":"Clothing, Apparel, & Fashions",
            "type":"Retail Goods"
        }
    ],
    "sg:phone":"+1 315 797 7677",
    "sg:postcode":"13502",
    "sg:province":"NY",
    "sg:tags":[
        "designer"
    ],
    "wof:name":"Frank Vita Mens Clothier",
    "wof:placetype":"venue"
},
  "geometry": {"coordinates":[-75.260987,43.086844],"type":"Point"}
}