{
  "type": "Feature",
  "properties": {
    "iso:country":"US",
    "sg:address":"331 E 204th St",
    "sg:city":"Bronx",
    "sg:classifiers":[
        {
            "category":"Bars & Pubs",
            "type":"Food & Drink"
        }
    ],
    "sg:phone":"+1 718 655 9947",
    "sg:postcode":"10467",
    "sg:province":"NY",
    "wof:name":"Mc Dwyer's Pub",
    "wof:placetype":"venue"
},
  "geometry": {"coordinates":[-73.87749599999999,40.871835],"type":"Point"}
}