{
  "type": "Feature",
  "properties": {
    "iso:country":"US",
    "sg:address":"164 Flint Ave",
    "sg:city":"Corning",
    "sg:classifiers":[
        {
            "category":"Education",
            "subcategory":"School",
            "type":"Public Place"
        }
    ],
    "sg:phone":"+1 607 962 1514",
    "sg:postcode":"14830",
    "sg:province":"NY",
    "wof:name":"Hugh W Gregg Elementary School",
    "wof:placetype":"venue"
},
  "geometry": {"coordinates":[-77.064166,42.153572],"type":"Point"}
}