{
  "type": "Feature",
  "properties": {
    "addr:full":"249 Jericho Tpke New Hyde Park NY 11040",
    "addr:housenumber":"249",
    "addr:postcode":"11040",
    "addr:street":"Jericho Tpke;Hyde Park",
    "iso:country":"US",
    "sg:address":"249 Jericho Tpke",
    "sg:city":"New Hyde Park",
    "sg:classifiers":[
        {
            "category":"Manufacturing",
            "subcategory":"Printing",
            "type":"Manufacturing & Wholesale Goods"
        }
    ],
    "sg:phone":"+1 516 488 7348",
    "sg:postcode":"11040",
    "sg:province":"NY",
    "sg:tags":[
        "printer"
    ],
    "wof:name":"Agrecolor Inc",
    "wof:placetype":"venue"
},
  "geometry": {"coordinates":[-73.690268,40.731557],"type":"Point"}
}