{
  "type": "Feature",
  "properties": {
    "addr:full":"32 Bingham Rd Marlboro NY 12542",
    "addr:housenumber":"32",
    "addr:postcode":"12542",
    "addr:street":"Bingham Rd",
    "iso:country":"US",
    "sg:address":"32 Bingham Rd",
    "sg:city":"Marlboro",
    "sg:classifiers":[
        {
            "category":"Professional",
            "subcategory":"Business Services",
            "type":"Services"
        }
    ],
    "sg:phone":"+1   ",
    "sg:postcode":"12542",
    "sg:province":"NY",
    "wof:name":"Hill View Enterprises Ltd",
    "wof:placetype":"venue"
},
  "geometry": {"coordinates":[-74.002163,41.586772],"type":"Point"}
}