{
  "type": "Feature",
  "properties": {
    "iso:country":"US",
    "sg:address":"1761 Co Rte 6",
    "sg:city":"Fulton",
    "sg:classifiers":[
        {
            "category":"Manufacturing",
            "subcategory":"Metals",
            "type":"Manufacturing & Wholesale Goods"
        }
    ],
    "sg:phone":"+1   ",
    "sg:postcode":"13069",
    "sg:province":"NY",
    "sg:tags":[
        "tool",
        "mechanic"
    ],
    "wof:name":"Lauren K Stanard",
    "wof:placetype":"venue"
},
  "geometry": {"coordinates":[-76.350246,43.358945],"type":"Point"}
}