{
  "type": "Feature",
  "properties": {
    "addr:full":"3402 37th St Long Island City NY 11101",
    "addr:housenumber":"3402",
    "addr:postcode":"11101",
    "addr:street":"37Th St",
    "iso:country":"US",
    "sg:address":"3402 37th St",
    "sg:city":"Long Island City",
    "sg:classifiers":[
        {
            "category":"Health Services",
            "subcategory":"Doctor",
            "type":"Services"
        }
    ],
    "sg:phone":"+1 718 361 8119",
    "sg:postcode":"11101",
    "sg:province":"NY",
    "sg:tags":[
        "podiatrist"
    ],
    "wof:name":"Pecora Maria Dr",
    "wof:placetype":"venue"
},
  "geometry": {"coordinates":[-73.92289700000001,40.757099],"type":"Point"}
}