{
  "type": "Feature",
  "properties": {
    "iso:country":"US",
    "sg:address":"1 Shrine Pl",
    "sg:city":"Greenlawn",
    "sg:classifiers":[
        {
            "category":"Social Services",
            "subcategory":"Child Care",
            "type":"Services"
        }
    ],
    "sg:phone":"+1 631 261 2524",
    "sg:postcode":"11740",
    "sg:province":"NY",
    "sg:tags":[
        "school",
        "nursery",
        "day"
    ],
    "wof:name":"Humpty Dumpty Nursery School",
    "wof:placetype":"venue"
},
  "geometry": {"coordinates":[-73.353557,40.868899],"type":"Point"}
}