{
  "type": "Feature",
  "properties": {
    "addr:full":"5732 Big Tree Rd Orchard Park NY 14127",
    "addr:housenumber":"5732",
    "addr:postcode":"14127",
    "addr:street":"Big Tree Rd",
    "iso:country":"US",
    "sg:address":"5732 Big Tree Rd",
    "sg:city":"Orchard Park",
    "sg:classifiers":[
        {
            "category":"Manufacturing",
            "subcategory":"Rubber & Plastics",
            "type":"Manufacturing & Wholesale Goods"
        }
    ],
    "sg:phone":"+1   ",
    "sg:postcode":"14127",
    "sg:province":"NY",
    "sg:tags":[
        "primary",
        "molding"
    ],
    "sg:website":"www.pci-tech.com",
    "wof:name":"Polymer Conversions Inc",
    "wof:placetype":"venue"
},
  "geometry": {"coordinates":[-78.774759,42.765154],"type":"Point"}
}