{
  "type": "Feature",
  "properties": {
    "addr:full":"95 W 168th St Bronx NY 10452",
    "addr:housenumber":"95",
    "addr:postcode":"10452",
    "addr:street":"W 168Th St",
    "iso:country":"US",
    "sg:address":"95 W 168th St",
    "sg:city":"Bronx",
    "sg:classifiers":[
        {
            "category":"Social Services",
            "subcategory":"Child Care",
            "type":"Services"
        }
    ],
    "sg:phone":"+1   ",
    "sg:postcode":"10452",
    "sg:province":"NY",
    "sg:tags":[
        "day"
    ],
    "wof:name":"Sacred Heart Head Start I",
    "wof:placetype":"venue"
},
  "geometry": {"coordinates":[-73.924604,40.838374],"type":"Point"}
}