{
  "type": "Feature",
  "properties": {
    "iso:country":"US",
    "sg:address":"1218 Ave M",
    "sg:city":"Brooklyn",
    "sg:classifiers":[
        {
            "category":"Food & Beverages",
            "subcategory":"Meat & Fish",
            "type":"Retail Goods"
        }
    ],
    "sg:phone":"+1   ",
    "sg:postcode":"11230",
    "sg:province":"NY",
    "wof:name":"Fish Net LLC",
    "wof:placetype":"venue"
},
  "geometry": {"coordinates":[-73.962002,40.617705],"type":"Point"}
}