{
  "type": "Feature",
  "properties": {
    "iso:country":"US",
    "sg:address":"8 E 125th St",
    "sg:city":"New York",
    "sg:classifiers":[
        {
            "category":"Shopping",
            "subcategory":"Department Store",
            "type":"Retail Goods"
        }
    ],
    "sg:phone":"+1 212 534 4665",
    "sg:postcode":"10035",
    "sg:province":"NY",
    "sg:tags":[
        "shop"
    ],
    "wof:name":"99 Cents Depot",
    "wof:placetype":"venue"
},
  "geometry": {"coordinates":[-73.940876,40.805779],"type":"Point"}
}