{
  "type": "Feature",
  "properties": {
    "iso:country":"US",
    "sg:address":"244 US Hwy 9w",
    "sg:city":"Haverstraw",
    "sg:classifiers":[
        {
            "category":"Shopping",
            "subcategory":"Bicycles & Sporting Goods",
            "type":"Retail Goods"
        }
    ],
    "sg:phone":"+1 845 429 3254",
    "sg:postcode":"10927",
    "sg:province":"NY",
    "sg:tags":[
        "tackle",
        "fishing"
    ],
    "wof:name":"Matt's Sporting Goods",
    "wof:placetype":"venue"
},
  "geometry": {"coordinates":[-73.98244800000001,41.199392],"type":"Point"}
}