{
  "type": "Feature",
  "properties": {
    "addr:full":"305 W Broadway Suite 1200 New York NY 10013",
    "addr:housenumber":"305",
    "addr:postcode":"10013",
    "addr:street":"W Broadway Suite 1200",
    "iso:country":"US",
    "sg:address":"305 W Broadway Suite 1200",
    "sg:city":"New York",
    "sg:classifiers":[
        {
            "category":"Professional",
            "subcategory":"Lawyer & Legal Services",
            "type":"Services"
        }
    ],
    "sg:phone":"+1 212 571 2181",
    "sg:postcode":"10013",
    "sg:province":"NY",
    "wof:name":"Decateur Shopping Assoc",
    "wof:placetype":"venue"
},
  "geometry": {"coordinates":[-74.004436,40.721561],"type":"Point"}
}