{
  "type": "Feature",
  "properties": {
    "iso:country":"US",
    "sg:address":"818 Flowerdale Rd",
    "sg:city":"Seaford",
    "sg:classifiers":[
        {
            "category":"Manufacturing",
            "subcategory":"Toys & Sporting Goods",
            "type":"Manufacturing & Wholesale Goods"
        }
    ],
    "sg:phone":"+1   ",
    "sg:postcode":"11783",
    "sg:province":"NY",
    "sg:tags":[
        "mfg"
    ],
    "wof:name":"Mikes Custom Clubs",
    "wof:placetype":"venue"
},
  "geometry": {"coordinates":[-73.486683,40.706236],"type":"Point"}
}