{
  "type": "Feature",
  "properties": {
    "addr:full":"135 Ludlow St New York NY 10002",
    "addr:housenumber":"135",
    "addr:postcode":"10002",
    "addr:street":"Ludlow St",
    "iso:country":"US",
    "sg:address":"135 Ludlow St",
    "sg:city":"New York",
    "sg:classifiers":[
        {
            "category":"Building & Trades",
            "subcategory":"Construction",
            "type":"Services"
        }
    ],
    "sg:phone":"+1 212 447 6360",
    "sg:postcode":"10002",
    "sg:province":"NY",
    "sg:tags":[
        "air",
        "heating",
        "conditioning/hvac"
    ],
    "sg:website":"nyaccorp.com/",
    "wof:name":"NYAC Corp",
    "wof:placetype":"venue"
},
  "geometry": {"coordinates":[-73.988339,40.720357],"type":"Point"}
}