{
  "type": "Feature",
  "properties": {
    "iso:country":"US",
    "sg:address":"436 S Union St",
    "sg:city":"Olean",
    "sg:classifiers":[
        {
            "category":"Building & Trades",
            "subcategory":"Equipment Rental",
            "type":"Services"
        }
    ],
    "sg:phone":"+1 716 373 7368",
    "sg:postcode":"14760",
    "sg:province":"NY",
    "sg:tags":[
        "tool"
    ],
    "sg:website":"www.a-1rentall.com",
    "wof:name":"A-1 Rent-All & Sales",
    "wof:placetype":"venue"
},
  "geometry": {"coordinates":[-78.429897,42.072762],"type":"Point"}
}