{
  "type": "Feature",
  "properties": {
    "iso:country":"US",
    "sg:address":"68 Horseblock Rd",
    "sg:city":"Centereach",
    "sg:classifiers":[
        {
            "category":"Home & Garden",
            "subcategory":"Building Materials",
            "type":"Retail Goods"
        }
    ],
    "sg:phone":"+1 631 981 1036",
    "sg:postcode":"11720",
    "sg:province":"NY",
    "sg:tags":[
        "supply"
    ],
    "wof:name":"Long Island Concrete Construction Inc",
    "wof:placetype":"venue"
},
  "geometry": {"coordinates":[-73.0728,40.855099],"type":"Point"}
}