{
  "type": "Feature",
  "properties": {
    "addr:full":"53 W Church St Fairport NY 14450",
    "addr:housenumber":"53",
    "addr:postcode":"14450",
    "addr:street":"W Church St",
    "iso:country":"US",
    "sg:address":"53 W Church St",
    "sg:city":"Fairport",
    "sg:classifiers":[
        {
            "category":"Government",
            "subcategory":"Office",
            "type":"Public Place"
        }
    ],
    "sg:phone":"+1 585 223 9783",
    "sg:postcode":"14450",
    "sg:province":"NY",
    "sg:tags":[
        "village"
    ],
    "wof:name":"Potter Memorial",
    "wof:placetype":"venue"
},
  "geometry": {"coordinates":[-77.44637,43.098625],"type":"Point"}
}