{
  "type": "Feature",
  "properties": {
    "addr:full":"56 Gregory St New City NY 10956",
    "addr:housenumber":"56",
    "addr:postcode":"10956",
    "addr:street":"Gregory St",
    "iso:country":"US",
    "sg:address":"56 Gregory St",
    "sg:city":"New City",
    "sg:classifiers":[
        {
            "category":"Education",
            "subcategory":"School",
            "type":"Public Place"
        }
    ],
    "sg:phone":"+1 845 639 6365",
    "sg:postcode":"10956",
    "sg:province":"NY",
    "sg:website":"www.ccsd.edu",
    "wof:name":"Little Tor Elementary School",
    "wof:placetype":"venue"
},
  "geometry": {"coordinates":[-73.99412100000001,41.152346],"type":"Point"}
}