{
  "type": "Feature",
  "properties": {
    "addr:full":"4 Skyview Pl Melville NY 11747",
    "addr:housenumber":"4",
    "addr:postcode":"11747",
    "addr:street":"Skyview Pl",
    "iso:country":"US",
    "sg:address":"4 Skyview Pl",
    "sg:city":"Melville",
    "sg:classifiers":[
        {
            "category":"Professional",
            "subcategory":"Computer Services",
            "type":"Services"
        }
    ],
    "sg:phone":"+1 516 297 5309",
    "sg:postcode":"11747",
    "sg:province":"NY",
    "sg:tags":[
        "related"
    ],
    "wof:name":"Connected Solutions",
    "wof:placetype":"venue"
},
  "geometry": {"coordinates":[-73.408653,40.802677],"type":"Point"}
}