{
  "type": "Feature",
  "properties": {
    "addr:full":"239 Nassau Blvd S Garden City NY 11530",
    "addr:housenumber":"239",
    "addr:postcode":"11530",
    "addr:street":"Nassau Blvd S",
    "iso:country":"US",
    "sg:address":"239 Nassau Blvd S",
    "sg:city":"Garden City",
    "sg:classifiers":[
        {
            "category":"Building & Trades",
            "subcategory":"Construction",
            "type":"Services"
        }
    ],
    "sg:phone":"+1 516 292 5800",
    "sg:postcode":"11530",
    "sg:province":"NY",
    "sg:tags":[
        "general",
        "contractor"
    ],
    "wof:name":"Cappelli Construction Corp",
    "wof:placetype":"venue"
},
  "geometry": {"coordinates":[-73.660999,40.713218],"type":"Point"}
}