{
  "type": "Feature",
  "properties": {
    "iso:country":"US",
    "sg:address":"7 Fairchild Ct Ste 100",
    "sg:city":"Plainview",
    "sg:classifiers":[
        {
            "category":"Professional",
            "subcategory":"Business Services",
            "type":"Services"
        }
    ],
    "sg:phone":"+1 516 605 1100",
    "sg:postcode":"11803",
    "sg:province":"NY",
    "sg:tags":[
        "development",
        "product",
        "designers-industrial",
        "marketing",
        "commercial",
        "design"
    ],
    "wof:name":"Cm Design Group",
    "wof:placetype":"venue"
},
  "geometry": {"coordinates":[-73.46747499999999,40.796713],"type":"Point"}
}