{
  "type": "Feature",
  "properties": {
    "iso:country":"US",
    "sg:address":"1314 Route 9D",
    "sg:city":"Beacon",
    "sg:classifiers":[
        {
            "category":"Autos & Motor Vehicles",
            "subcategory":"Fuel & Gas Station",
            "type":"Retail Goods"
        },
        {
            "category":"Food & Beverages",
            "subcategory":"Groceries & Convenience Stores",
            "type":"Retail Goods"
        }
    ],
    "sg:phone":"+1 845 831 9040",
    "sg:postcode":"12508",
    "sg:province":"NY",
    "sg:website":"www.sunocoinc.com",
    "wof:name":"On the Go Sunoco",
    "wof:placetype":"venue"
},
  "geometry": {"coordinates":[-73.97351999999999,41.518717],"type":"Point"}
}