{
  "type": "Feature",
  "properties": {
    "addr:full":"3327 Fulton St Brooklyn NY 11208",
    "addr:housenumber":"3327",
    "addr:postcode":"11208",
    "addr:street":"Fulton St",
    "iso:country":"US",
    "sg:address":"3327 Fulton St",
    "sg:city":"Brooklyn",
    "sg:classifiers":[
        {
            "category":"Food & Beverages",
            "subcategory":"Liquor & Beverages",
            "type":"Retail Goods"
        }
    ],
    "sg:phone":"+1 347 295 1602",
    "sg:postcode":"11208",
    "sg:province":"NY",
    "sg:tags":[
        "beer",
        "spirit",
        "wine"
    ],
    "wof:name":"Abc Wine & Liquor",
    "wof:placetype":"venue"
},
  "geometry": {"coordinates":[-73.87270700000001,40.683636],"type":"Point"}
}