{
  "type": "Feature",
  "properties": {
    "addr:full":"13 E 69 St New York NY 10021",
    "addr:housenumber":"13;69",
    "addr:postcode":"10021",
    "addr:street":"E;St",
    "iso:country":"US",
    "sg:address":"13 E 69 St",
    "sg:city":"New York",
    "sg:classifiers":[
        {
            "category":"Shopping",
            "subcategory":"Clothing, Apparel, & Fashions",
            "type":"Retail Goods"
        }
    ],
    "sg:phone":"+1 212 452 3273",
    "sg:postcode":"10021",
    "sg:province":"NY",
    "sg:tags":[
        "shop",
        "bridal"
    ],
    "wof:name":"Lara Helene Inc",
    "wof:placetype":"venue"
},
  "geometry": {"coordinates":[-73.967716,40.770415],"type":"Point"}
}