{
  "type": "Feature",
  "properties": {
    "addr:full":"205 Lexington Ave Fl 4 New York NY 10016",
    "addr:housenumber":"205;4",
    "addr:postcode":"10016",
    "addr:street":"Lexington Ave Fl",
    "iso:country":"US",
    "sg:address":"205 Lexington Ave Fl 4",
    "sg:city":"New York",
    "sg:classifiers":[
        {
            "category":"Professional",
            "subcategory":"Lawyer & Legal Services",
            "type":"Services"
        }
    ],
    "sg:phone":"+1 212 679 7007",
    "sg:postcode":"10016",
    "sg:province":"NY",
    "sg:website":"www.bbbnylaw.com",
    "wof:name":"Brody Benard & Branch",
    "wof:placetype":"venue"
},
  "geometry": {"coordinates":[-73.980268,40.745164],"type":"Point"}
}