{
  "type": "Feature",
  "properties": {
    "addr:full":"40 Evans St Batavia NY 14020",
    "addr:housenumber":"40",
    "addr:postcode":"14020",
    "addr:street":"Evans St",
    "iso:country":"US",
    "sg:address":"40 Evans St",
    "sg:city":"Batavia",
    "sg:classifiers":[
        {
            "category":"Manufacturing",
            "subcategory":"Metals",
            "type":"Manufacturing & Wholesale Goods"
        }
    ],
    "sg:phone":"+1 585 343 8657",
    "sg:postcode":"14020",
    "sg:province":"NY",
    "sg:tags":[
        "screw"
    ],
    "wof:name":"Custom Fasteners Inc",
    "wof:placetype":"venue"
},
  "geometry": {"coordinates":[-78.187338,42.99491],"type":"Point"}
}