{
  "type": "Feature",
  "properties": {
    "addr:full":"2120 Sackett Rd Avon NY 14414",
    "addr:housenumber":"2120",
    "addr:postcode":"14414",
    "addr:street":"Sackett Rd",
    "iso:country":"US",
    "sg:address":"2120 Sackett Rd",
    "sg:city":"Avon",
    "sg:classifiers":[
        {
            "category":"Professional",
            "type":"Services"
        }
    ],
    "sg:phone":"+1 585 226 8100",
    "sg:postcode":"14414",
    "sg:province":"NY",
    "sg:tags":[
        "establishment"
    ],
    "wof:name":"Western New York Empire Corp",
    "wof:placetype":"venue"
},
  "geometry": {"coordinates":[-77.760806,42.897961],"type":"Point"}
}