{
  "type": "Feature",
  "properties": {
    "addr:full":"210 S Denver Ave Bay Shore NY 11706",
    "addr:housenumber":"210",
    "addr:postcode":"11706",
    "addr:street":"S Denver Ave",
    "iso:country":"US",
    "sg:address":"210 S Denver Ave",
    "sg:city":"Bay Shore",
    "sg:classifiers":[
        {
            "category":"Animal Shelter",
            "type":"Public Place"
        },
        {
            "category":"Shopping",
            "subcategory":"Pets & Pet Supplies",
            "type":"Retail Goods"
        }
    ],
    "sg:phone":"+1 631 224 5660",
    "sg:postcode":"11706",
    "sg:province":"NY",
    "sg:tags":[
        "store"
    ],
    "wof:name":"Islip Town of",
    "wof:placetype":"venue"
},
  "geometry": {"coordinates":[-73.237154,40.746696],"type":"Point"}
}