{
  "type": "Feature",
  "properties": {
    "iso:country":"US",
    "sg:address":"337 Knickerbocker Ave",
    "sg:city":"Bohemia",
    "sg:classifiers":[
        {
            "category":"Building & Trades",
            "subcategory":"Construction",
            "type":"Services"
        }
    ],
    "sg:phone":"+1 631 218 8230",
    "sg:postcode":"11716",
    "sg:province":"NY",
    "sg:tags":[
        "insulation",
        "heat",
        "contractor"
    ],
    "wof:name":"Prime Insulation Co Inc",
    "wof:placetype":"venue"
},
  "geometry": {"coordinates":[-73.087698,40.781177],"type":"Point"}
}