{
  "type": "Feature",
  "properties": {
    "addr:full":"92 Washington Ave Cedarhurst NY 11516",
    "addr:housenumber":"92",
    "addr:postcode":"11516",
    "addr:street":"Washington Ave",
    "iso:country":"US",
    "sg:address":"92 Washington Ave",
    "sg:city":"Cedarhurst",
    "sg:classifiers":[
        {
            "category":"Real Estate",
            "subcategory":"Real Estate Services",
            "type":"Services"
        }
    ],
    "sg:phone":"+1 516 569 5959",
    "sg:postcode":"11516",
    "sg:province":"NY",
    "sg:tags":[
        "management",
        "property"
    ],
    "sg:website":"www.arasproperties.com",
    "wof:name":"Aras Properties Inc",
    "wof:placetype":"venue"
},
  "geometry": {"coordinates":[-73.726097,40.6185],"type":"Point"}
}