{
  "type": "Feature",
  "properties": {
    "addr:full":"165 Garden St Roslyn Heights NY 11577",
    "addr:housenumber":"165",
    "addr:postcode":"11577",
    "addr:street":"Garden St",
    "iso:country":"US",
    "sg:address":"165 Garden St",
    "sg:city":"Roslyn Heights",
    "sg:classifiers":[
        {
            "category":"Professional",
            "type":"Services"
        }
    ],
    "sg:phone":"+1 516 626 7896",
    "sg:postcode":"11577",
    "sg:province":"NY",
    "wof:name":"Cor Management Svc",
    "wof:placetype":"venue"
},
  "geometry": {"coordinates":[-73.648499,40.790781],"type":"Point"}
}