{
  "type": "Feature",
  "properties": {
    "addr:full":"5112 W Taft Rd Liverpool NY 13088",
    "addr:housenumber":"5112",
    "addr:postcode":"13088",
    "addr:street":"W Taft Rd",
    "iso:country":"US",
    "sg:address":"5112 W Taft Rd",
    "sg:city":"Liverpool",
    "sg:classifiers":[
        {
            "category":"Health Services",
            "subcategory":"Chiropractor",
            "type":"Services"
        }
    ],
    "sg:phone":"+1   ",
    "sg:postcode":"13088",
    "sg:province":"NY",
    "wof:name":"Meridian Chrprctic Wellness PC",
    "wof:placetype":"venue"
},
  "geometry": {"coordinates":[-76.161552,43.121726],"type":"Point"}
}