{
  "type": "Feature",
  "properties": {
    "iso:country":"US",
    "sg:address":"232 Main St",
    "sg:city":"Port Washington",
    "sg:classifiers":[
        {
            "category":"Social Services",
            "type":"Services"
        }
    ],
    "sg:phone":"+1   ",
    "sg:postcode":"11050",
    "sg:province":"NY",
    "wof:name":"Jeanne Rimsky Theater",
    "wof:placetype":"venue"
},
  "geometry": {"coordinates":[-73.69528099999999,40.83099],"type":"Point"}
}