{
  "type": "Feature",
  "properties": {
    "addr:full":"55 E 115th St New York NY 10029",
    "addr:housenumber":"55",
    "addr:postcode":"10029",
    "addr:street":"E 115Th St",
    "iso:country":"US",
    "sg:address":"55 E 115th St",
    "sg:city":"New York",
    "sg:classifiers":[
        {
            "category":"Building & Trades",
            "subcategory":"Construction",
            "type":"Services"
        }
    ],
    "sg:phone":"+1 212 828 7060",
    "sg:postcode":"10029",
    "sg:province":"NY",
    "sg:tags":[
        "general",
        "contractor"
    ],
    "wof:name":"Falcon Construction",
    "wof:placetype":"venue"
},
  "geometry": {"coordinates":[-73.944001,40.798843],"type":"Point"}
}