{
  "type": "Feature",
  "properties": {
    "addr:full":"5 W Cross St Hawthorne NY 10532",
    "addr:housenumber":"5",
    "addr:postcode":"10532",
    "addr:street":"W Cross St",
    "iso:country":"US",
    "sg:address":"5 W Cross St",
    "sg:city":"Hawthorne",
    "sg:classifiers":[
        {
            "category":"Real Estate",
            "subcategory":"Architect",
            "type":"Services"
        }
    ],
    "sg:phone":"+1 914 769 6660",
    "sg:postcode":"10532",
    "sg:province":"NY",
    "wof:name":"Stephen Vento Ra",
    "wof:placetype":"venue"
},
  "geometry": {"coordinates":[-73.798312,41.107434],"type":"Point"}
}