{
  "type": "Feature",
  "properties": {
    "addr:full":"561 Broadway New York NY 10012",
    "addr:housenumber":"561",
    "addr:postcode":"10012",
    "addr:street":"Broadway",
    "iso:country":"US",
    "sg:address":"561 Broadway",
    "sg:city":"New York",
    "sg:classifiers":[
        {
            "category":"Shopping",
            "subcategory":"Clothing, Apparel, & Fashions",
            "type":"Retail Goods"
        }
    ],
    "sg:phone":"+1 212 343 7012",
    "sg:postcode":"10012",
    "sg:province":"NY",
    "sg:website":"www.mngbymango.com",
    "wof:name":"MNG by Mango",
    "wof:placetype":"venue"
},
  "geometry": {"coordinates":[-73.997961,40.724012],"type":"Point"}
}