{
  "type": "Feature",
  "properties": {
    "addr:full":"300 Main St Oneonta NY 13820",
    "addr:housenumber":"300",
    "addr:postcode":"13820",
    "addr:street":"Main St",
    "iso:country":"US",
    "sg:address":"300 Main St",
    "sg:city":"Oneonta",
    "sg:classifiers":[
        {
            "category":"Shopping",
            "subcategory":"Clothing, Apparel, & Fashions",
            "type":"Retail Goods"
        }
    ],
    "sg:phone":"+1   ",
    "sg:postcode":"13820",
    "sg:province":"NY",
    "wof:name":"Wedding Gallery",
    "wof:placetype":"venue"
},
  "geometry": {"coordinates":[-75.05903499999999,42.456143],"type":"Point"}
}