{
  "type": "Feature",
  "properties": {
    "addr:full":"435 South Ave Jamestown NY 14701",
    "addr:housenumber":"435",
    "addr:postcode":"14701",
    "addr:street":"South Ave",
    "iso:country":"US",
    "sg:address":"435 South Ave",
    "sg:city":"Jamestown",
    "sg:classifiers":[
        {
            "category":"Manufacturing",
            "subcategory":"Building Materials",
            "type":"Manufacturing & Wholesale Goods"
        }
    ],
    "sg:phone":"+1   ",
    "sg:postcode":"14701",
    "sg:province":"NY",
    "sg:tags":[
        "mfg",
        "wood",
        "kitchen",
        "cabinet"
    ],
    "wof:name":"Edwin O Anderson Carpentry",
    "wof:placetype":"venue"
},
  "geometry": {"coordinates":[-79.240167,42.076038],"type":"Point"}
}