{
  "type": "Feature",
  "properties": {
    "iso:country":"US",
    "sg:address":"201 W 87 St",
    "sg:city":"New York",
    "sg:classifiers":[
        {
            "category":"Travel",
            "subcategory":"Hotels & Motels",
            "type":"Entertainment"
        }
    ],
    "sg:phone":"+1 212 362 2432",
    "sg:postcode":"10024",
    "sg:province":"NY",
    "wof:name":"Haverford Hotel",
    "wof:placetype":"venue"
},
  "geometry": {"coordinates":[-73.975948,40.788961],"type":"Point"}
}