{
  "type": "Feature",
  "properties": {
    "addr:full":"560 Broad Hollow Rd Melville NY 11747",
    "addr:housenumber":"560",
    "addr:postcode":"11747",
    "addr:street":"Broad Hollow Rd",
    "iso:country":"US",
    "sg:address":"560 Broad Hollow Rd",
    "sg:city":"Melville",
    "sg:classifiers":[
        {
            "category":"Banks & Credit Unions",
            "subcategory":"Investment Brokerage",
            "type":"Services"
        }
    ],
    "sg:phone":"+1 631 249 0032",
    "sg:postcode":"11747",
    "sg:province":"NY",
    "sg:tags":[
        "security"
    ],
    "wof:name":"V Finance Investments Inc",
    "wof:placetype":"venue"
},
  "geometry": {"coordinates":[-73.42336899999999,40.763069],"type":"Point"}
}