{
  "type": "Feature",
  "properties": {
    "addr:full":"164 Sugar Hill Rd Rexford NY 12148",
    "addr:housenumber":"164",
    "addr:postcode":"12148",
    "addr:street":"Sugar Hill Rd",
    "iso:country":"US",
    "sg:address":"164 Sugar Hill Rd",
    "sg:city":"Rexford",
    "sg:classifiers":[
        {
            "category":"Farming",
            "subcategory":"Dairy Farm",
            "type":"Manufacturing & Wholesale Goods"
        }
    ],
    "sg:phone":"+1 518 371 3659",
    "sg:postcode":"12148",
    "sg:province":"NY",
    "wof:name":"Sugar Hill Sugar View Farm",
    "wof:placetype":"venue"
},
  "geometry": {"coordinates":[-73.840841,42.825787],"type":"Point"}
}