{
  "type": "Feature",
  "properties": {
    "addr:full":"360 Northern Blvd Albany NY 12204",
    "addr:housenumber":"360",
    "addr:postcode":"12204",
    "addr:street":"Northern Blvd",
    "iso:country":"US",
    "sg:address":"360 Northern Blvd",
    "sg:city":"Albany",
    "sg:classifiers":[
        {
            "category":"Insurance",
            "subcategory":"Insurance Agent",
            "type":"Services"
        },
        {
            "category":"Insurance",
            "subcategory":"Hazard Insurance",
            "type":"Services"
        },
        {
            "category":"Insurance",
            "subcategory":"Title Insurance",
            "type":"Services"
        },
        {
            "category":"Insurance",
            "subcategory":"Life Insurance",
            "type":"Services"
        }
    ],
    "sg:phone":"+1 518 449 1390",
    "sg:postcode":"12204",
    "sg:province":"NY",
    "sg:tags":[
        "business",
        "auto",
        "commercial",
        "homeowner",
        "motorcycle",
        "renter"
    ],
    "wof:name":"Allstate Insurance Company - Salvatore Graziano",
    "wof:placetype":"venue"
},
  "geometry": {"coordinates":[-73.748957,42.674751],"type":"Point"}
}