{
  "type": "Feature",
  "properties": {
    "addr:full":"32 Horseshoe Dr Poughkeepsie NY 12603",
    "addr:housenumber":"32",
    "addr:postcode":"12603",
    "addr:street":"Horseshoe Dr",
    "iso:country":"US",
    "sg:address":"32 Horseshoe Dr",
    "sg:city":"Poughkeepsie",
    "sg:classifiers":[
        {
            "category":"Building & Trades",
            "subcategory":"Construction",
            "type":"Services"
        }
    ],
    "sg:phone":"+1 845 473 7011",
    "sg:postcode":"12603",
    "sg:province":"NY",
    "sg:tags":[
        "gutter",
        "contractor"
    ],
    "wof:name":"Atlas Quality Seamless Gutters",
    "wof:placetype":"venue"
},
  "geometry": {"coordinates":[-73.823318,41.680126],"type":"Point"}
}