{
  "type": "Feature",
  "properties": {
    "iso:country":"US",
    "sg:address":"3344 Long Beach Rd",
    "sg:city":"Oceanside",
    "sg:classifiers":[
        {
            "category":"Home & Garden",
            "subcategory":"Household Appliances",
            "type":"Retail Goods"
        }
    ],
    "sg:phone":"+1 516 764 6080",
    "sg:postcode":"11572",
    "sg:province":"NY",
    "wof:name":"Semor Appliance",
    "wof:placetype":"venue"
},
  "geometry": {"coordinates":[-73.64106,40.629907],"type":"Point"}
}