{
  "type": "Feature",
  "properties": {
    "addr:full":"730 Saw Mill River Rd Yonkers NY 10710",
    "addr:housenumber":"730",
    "addr:postcode":"10710",
    "addr:street":"Saw Mill River Rd",
    "iso:country":"US",
    "sg:address":"730 Saw Mill River Rd",
    "sg:city":"Yonkers",
    "sg:classifiers":[
        {
            "category":"Wholesale",
            "subcategory":"Scrap",
            "type":"Manufacturing & Wholesale Goods"
        }
    ],
    "sg:phone":"+1 914 476 2975",
    "sg:postcode":"10710",
    "sg:province":"NY",
    "sg:tags":[
        "metal",
        "iron"
    ],
    "wof:name":"R B Scrap Iron & Metal",
    "wof:placetype":"venue"
},
  "geometry": {"coordinates":[-73.87040500000001,40.960429],"type":"Point"}
}