{
  "type": "Feature",
  "properties": {
    "iso:country":"US",
    "sg:address":"4632 Jersey Hill Rd",
    "sg:city":"Amsterdam",
    "sg:classifiers":[
        {
            "category":"Retail",
            "subcategory":"Animal Services",
            "type":"Services"
        }
    ],
    "sg:phone":"+1 518 882 9357",
    "sg:postcode":"12010",
    "sg:province":"NY",
    "sg:tags":[
        "horse",
        "training"
    ],
    "wof:name":"First Class Stables",
    "wof:placetype":"venue"
},
  "geometry": {"coordinates":[-74.069247,42.988592],"type":"Point"}
}