{
  "type": "Feature",
  "properties": {
    "addr:full":"707 Broadway Ste 2 Massapequa NY 11758",
    "addr:housenumber":"707",
    "addr:postcode":"11758",
    "addr:street":"Broadway Ste 2",
    "iso:country":"US",
    "sg:address":"707 Broadway Ste 2",
    "sg:city":"Massapequa",
    "sg:classifiers":[
        {
            "category":"Social Services",
            "type":"Services"
        },
        {
            "category":"Personal",
            "type":"Services"
        }
    ],
    "sg:phone":"+1 516 797 4851",
    "sg:postcode":"11758",
    "sg:province":"NY",
    "sg:tags":[
        "family",
        "professional",
        "counselors-licensed",
        "individual",
        "marriage",
        "child",
        "counseling",
        "counselor"
    ],
    "wof:name":"Counseling Associates Of Long",
    "wof:placetype":"venue"
},
  "geometry": {"coordinates":[-73.46539300000001,40.6917],"type":"Point"}
}