{
  "type": "Feature",
  "properties": {
    "iso:country":"US",
    "sg:address":"15 Dietz St",
    "sg:city":"Central Islip",
    "sg:classifiers":[
        {
            "category":"Building & Trades",
            "subcategory":"Plumbing",
            "type":"Services"
        }
    ],
    "sg:phone":"+1 631 234 8116",
    "sg:postcode":"11722",
    "sg:province":"NY",
    "sg:tags":[
        "contractor"
    ],
    "wof:name":"Figgies Air Condition",
    "wof:placetype":"venue"
},
  "geometry": {"coordinates":[-73.20357,40.793224],"type":"Point"}
}