{
  "type": "Feature",
  "properties": {
    "iso:country":"US",
    "sg:address":"211 State Hwy 30",
    "sg:city":"Schoharie",
    "sg:classifiers":[
        {
            "category":"Food & Beverages",
            "subcategory":"Groceries & Convenience Stores",
            "type":"Retail Goods"
        }
    ],
    "sg:phone":"+1 518 295 6166",
    "sg:postcode":"12157",
    "sg:province":"NY",
    "wof:name":"Schoharie Greenhill Groc Inc",
    "wof:placetype":"venue"
},
  "geometry": {"coordinates":[-74.30983999999999,42.666697],"type":"Point"}
}