{
  "type": "Feature",
  "properties": {
    "addr:full":"54 W Main St Patchogue NY 11772",
    "addr:housenumber":"54",
    "addr:postcode":"11772",
    "addr:street":"W Main St",
    "iso:country":"US",
    "sg:address":"54 W Main St",
    "sg:city":"Patchogue",
    "sg:classifiers":[
        {
            "category":"Shopping",
            "subcategory":"Department Store",
            "type":"Retail Goods"
        }
    ],
    "sg:phone":"+1 631 758 7079",
    "sg:postcode":"11772",
    "sg:province":"NY",
    "sg:tags":[
        "shop"
    ],
    "wof:name":"Rahama & Dama Inc",
    "wof:placetype":"venue"
},
  "geometry": {"coordinates":[-73.016116,40.765694],"type":"Point"}
}