{
  "type": "Feature",
  "properties": {
    "addr:full":"2110 1 Ave New York NY 10029",
    "addr:housenumber":"2110",
    "addr:postcode":"10029",
    "addr:street":"1 Ave",
    "iso:country":"US",
    "sg:address":"2110 1 Ave",
    "sg:city":"New York",
    "sg:classifiers":[
        {
            "category":"Government",
            "subcategory":"Office",
            "type":"Public Place"
        }
    ],
    "sg:phone":"+1 212 348 9630",
    "sg:postcode":"10029",
    "sg:province":"NY",
    "wof:name":"Congressman Charles B Rangel",
    "wof:placetype":"venue"
},
  "geometry": {"coordinates":[-73.94422299999999,40.783933],"type":"Point"}
}