{
  "type": "Feature",
  "properties": {
    "iso:country":"US",
    "sg:address":"6805 Crossbow Dr",
    "sg:city":"East Syracuse",
    "sg:classifiers":[
        {
            "category":"Wholesale",
            "subcategory":"Chemicals & Plastics",
            "type":"Manufacturing & Wholesale Goods"
        }
    ],
    "sg:phone":"+1 315 437 8461",
    "sg:postcode":"13057",
    "sg:province":"NY",
    "sg:tags":[
        "product"
    ],
    "sg:website":"www.curbell.com",
    "wof:name":"Curbell Inc",
    "wof:placetype":"venue"
},
  "geometry": {"coordinates":[-76.08171,43.102028],"type":"Point"}
}