{
  "type": "Feature",
  "properties": {
    "addr:full":"225 Old Town Rd East Setauket NY 11733",
    "addr:housenumber":"225",
    "addr:postcode":"11733",
    "addr:street":"Old Town Rd",
    "iso:country":"US",
    "sg:address":"225 Old Town Rd",
    "sg:city":"East Setauket",
    "sg:classifiers":[
        {
            "category":"Home & Garden",
            "subcategory":"Garden Supply",
            "type":"Retail Goods"
        }
    ],
    "sg:phone":"+1 631 751 8446",
    "sg:postcode":"11733",
    "sg:province":"NY",
    "sg:tags":[
        "nursery",
        "gardening"
    ],
    "wof:name":"Maeder Nurseries",
    "wof:placetype":"venue"
},
  "geometry": {"coordinates":[-73.305392,40.932631],"type":"Point"}
}