{
  "type": "Feature",
  "properties": {
    "addr:full":"189 Malcolm X Blvd New York NY 10026",
    "addr:housenumber":"189",
    "addr:postcode":"10026",
    "addr:street":"Malcolm X Blvd",
    "iso:country":"US",
    "sg:address":"189 Malcolm X Blvd",
    "sg:city":"New York",
    "sg:classifiers":[
        {
            "category":"Personal",
            "subcategory":"Beauty Salon",
            "type":"Services"
        }
    ],
    "sg:phone":"+1 212 222 0057",
    "sg:postcode":"10026",
    "sg:province":"NY",
    "wof:name":"Boya Hair Braiding Salon",
    "wof:placetype":"venue"
},
  "geometry": {"coordinates":[-73.948033,40.804343],"type":"Point"}
}