{
  "type": "Feature",
  "properties": {
    "addr:full":"6265 Sheridan Drive, Suite 122 Williamsville NY 14221",
    "addr:housenumber":"6265",
    "addr:postcode":"14221",
    "addr:street":"Sheridan Drive Suite 122",
    "iso:country":"US",
    "sg:address":"6265 Sheridan Drive, Suite 122",
    "sg:city":"Williamsville",
    "sg:classifiers":[
        {
            "category":"Social Services",
            "type":"Services"
        },
        {
            "category":"Personal",
            "type":"Services"
        },
        {
            "category":"Health Services",
            "subcategory":"Health Practitioner",
            "type":"Services"
        }
    ],
    "sg:phone":"+1 716 903 5676",
    "sg:postcode":"14221",
    "sg:province":"NY",
    "sg:tags":[
        "individual",
        "family",
        "psychotherapist",
        "professional",
        "counselors-licensed",
        "therapist",
        "marriage",
        "child",
        "counseling",
        "counselor"
    ],
    "wof:name":"Rashida Amra Williams, LCSWR",
    "wof:placetype":"venue"
},
  "geometry": {"coordinates":[-78.70053900000001,42.97814],"type":"Point"}
}