{
  "type": "Feature",
  "properties": {
    "addr:full":"335 Eldert Ln Brooklyn NY 11208",
    "addr:housenumber":"335",
    "addr:postcode":"11208",
    "addr:street":"Eldert Ln",
    "iso:country":"US",
    "sg:address":"335 Eldert Ln",
    "sg:city":"Brooklyn",
    "sg:classifiers":[
        {
            "category":"Professional",
            "subcategory":"Computer Services",
            "type":"Services"
        }
    ],
    "sg:phone":"+1 718 296 2679",
    "sg:postcode":"11208",
    "sg:province":"NY",
    "sg:tags":[
        "related"
    ],
    "wof:name":"Niru Tech",
    "wof:placetype":"venue"
},
  "geometry": {"coordinates":[-73.866162,40.682287],"type":"Point"}
}