{
  "type": "Feature",
  "properties": {
    "addr:full":"12 Monroe Ct Guilderland NY 12084",
    "addr:housenumber":"12",
    "addr:postcode":"12084",
    "addr:street":"Monroe Ct",
    "iso:country":"US",
    "sg:address":"12 Monroe Ct",
    "sg:city":"Guilderland",
    "sg:classifiers":[
        {
            "category":"Banks & Credit Unions",
            "subcategory":"Investment Brokerage",
            "type":"Services"
        }
    ],
    "sg:phone":"+1 518 452 1063",
    "sg:postcode":"12084",
    "sg:province":"NY",
    "sg:tags":[
        "advisory"
    ],
    "wof:name":"Next Financial",
    "wof:placetype":"venue"
},
  "geometry": {"coordinates":[-73.894334,42.691523],"type":"Point"}
}