{
  "type": "Feature",
  "properties": {
    "addr:full":"166 Williamsburg St E Brooklyn NY 11211",
    "addr:housenumber":"166",
    "addr:postcode":"11211",
    "addr:street":"Williamsburg St E",
    "iso:country":"US",
    "sg:address":"166 Williamsburg St E",
    "sg:city":"Brooklyn",
    "sg:classifiers":[
        {
            "category":"Shopping",
            "subcategory":"Optical Goods",
            "type":"Retail Goods"
        }
    ],
    "sg:phone":"+1 718 782 1885",
    "sg:postcode":"11211",
    "sg:province":"NY",
    "sg:tags":[
        "ophthalmic"
    ],
    "wof:name":"Rite Site Optical",
    "wof:placetype":"venue"
},
  "geometry": {"coordinates":[-73.959591,40.703523],"type":"Point"}
}