{
  "type": "Feature",
  "properties": {
    "addr:full":"445 W Jericho Tpke Huntington NY 11743",
    "addr:housenumber":"445",
    "addr:postcode":"11743",
    "addr:street":"W Jericho Tpke",
    "iso:country":"US",
    "sg:address":"445 W Jericho Tpke",
    "sg:city":"Huntington",
    "sg:classifiers":[
        {
            "category":"Retail",
            "subcategory":"Auto Repair",
            "type":"Services"
        }
    ],
    "sg:phone":"+1 631 421 3679",
    "sg:postcode":"11743",
    "sg:province":"NY",
    "wof:name":"Hendershot Auto Tech",
    "wof:placetype":"venue"
},
  "geometry": {"coordinates":[-73.443505,40.824414],"type":"Point"}
}