{
  "type": "Feature",
  "properties": {
    "addr:full":"8510 4th Ave Brooklyn NY 11209",
    "addr:housenumber":"8510",
    "addr:postcode":"11209",
    "addr:street":"4Th Ave",
    "iso:country":"US",
    "sg:address":"8510 4th Ave",
    "sg:city":"Brooklyn",
    "sg:classifiers":[
        {
            "category":"Restaurant",
            "type":"Food & Drink"
        }
    ],
    "sg:phone":"+1 718 808 2112",
    "sg:postcode":"11209",
    "sg:province":"NY",
    "wof:name":"Heat Up",
    "wof:placetype":"venue"
},
  "geometry": {"coordinates":[-74.02814600000001,40.623364],"type":"Point"}
}