{
  "type": "Feature",
  "properties": {
    "iso:country":"US",
    "sg:address":"2686 State Hwy 29",
    "sg:city":"Johnstown",
    "sg:classifiers":[
        {
            "category":"Retail",
            "subcategory":"Auto Repair",
            "type":"Services"
        }
    ],
    "sg:phone":"+1   ",
    "sg:postcode":"12095",
    "sg:province":"NY",
    "sg:tags":[
        "automotive",
        "used",
        "automobile",
        "general"
    ],
    "wof:name":"Fagants Auto Sales & Service",
    "wof:placetype":"venue"
},
  "geometry": {"coordinates":[-74.340005,43.018733],"type":"Point"}
}