{
  "type": "Feature",
  "properties": {
    "iso:country":"US",
    "sg:address":"31 W 47th St",
    "sg:city":"New York",
    "sg:classifiers":[
        {
            "category":"Wholesale",
            "subcategory":"Jewelry",
            "type":"Manufacturing & Wholesale Goods"
        }
    ],
    "sg:phone":"+1 212 719 2330",
    "sg:postcode":"10036",
    "sg:province":"NY",
    "sg:tags":[
        "stone"
    ],
    "wof:name":"Ronex Sales Corp",
    "wof:placetype":"venue"
},
  "geometry": {"coordinates":[-73.981009,40.757668],"type":"Point"}
}