{
  "type": "Feature",
  "properties": {
    "iso:country":"US",
    "sg:address":"352 State Hwy 79",
    "sg:city":"Windsor",
    "sg:classifiers":[
        {
            "category":"Building & Trades",
            "subcategory":"Construction",
            "type":"Services"
        }
    ],
    "sg:phone":"+1 607 655 1800",
    "sg:postcode":"13865",
    "sg:province":"NY",
    "sg:tags":[
        "tile",
        "dealer"
    ],
    "wof:name":"Terrell Tile Co Inc",
    "wof:placetype":"venue"
},
  "geometry": {"coordinates":[-75.624883,42.014178],"type":"Point"}
}