{
  "type": "Feature",
  "properties": {
    "iso:country":"US",
    "sg:address":"38 Shore Dr",
    "sg:city":"Blooming Grove",
    "sg:classifiers":[
        {
            "category":"Building & Trades",
            "subcategory":"Electrical",
            "type":"Services"
        }
    ],
    "sg:phone":"+1 845 496 0146",
    "sg:postcode":"10914",
    "sg:province":"NY",
    "sg:tags":[
        "electrical",
        "contractor"
    ],
    "wof:name":"Empire Electric",
    "wof:placetype":"venue"
},
  "geometry": {"coordinates":[-74.218673,41.411035],"type":"Point"}
}