{
  "type": "Feature",
  "properties": {
    "iso:country":"US",
    "sg:address":"150 E 86 St",
    "sg:city":"New York",
    "sg:classifiers":[
        {
            "category":"Food & Beverages",
            "subcategory":"Candy",
            "type":"Retail Goods"
        }
    ],
    "sg:phone":"+1   ",
    "sg:postcode":"10028",
    "sg:province":"NY",
    "wof:name":"Sweets 86 LLC",
    "wof:placetype":"venue"
},
  "geometry": {"coordinates":[-73.954229,40.778872],"type":"Point"}
}