{
  "type": "Feature",
  "properties": {
    "iso:country":"US",
    "sg:address":"6511 Basile Rowe",
    "sg:city":"East Syracuse",
    "sg:classifiers":[
        {
            "category":"Banks & Credit Unions",
            "subcategory":"Investment Brokerage",
            "type":"Services"
        }
    ],
    "sg:phone":"+1 315 431 4164",
    "sg:postcode":"13057",
    "sg:province":"NY",
    "sg:tags":[
        "advisory",
        "financial"
    ],
    "wof:name":"EBS Financial Group",
    "wof:placetype":"venue"
},
  "geometry": {"coordinates":[-76.057832,43.060663],"type":"Point"}
}