{
  "type": "Feature",
  "properties": {
    "addr:full":"1045 Union Rd Buffalo NY 14224",
    "addr:housenumber":"1045",
    "addr:postcode":"14224",
    "addr:street":"Union Rd",
    "iso:country":"US",
    "sg:address":"1045 Union Rd",
    "sg:city":"Buffalo",
    "sg:classifiers":[
        {
            "category":"Shopping",
            "subcategory":"Jewelry",
            "type":"Retail Goods"
        }
    ],
    "sg:phone":"+1 716 675 9050",
    "sg:postcode":"14224",
    "sg:province":"NY",
    "sg:tags":[
        "repair",
        "diamond"
    ],
    "wof:name":"Pohlman Jewelers",
    "wof:placetype":"venue"
},
  "geometry": {"coordinates":[-78.75340300000001,42.828057],"type":"Point"}
}