{
  "type": "Feature",
  "properties": {
    "addr:full":"114 Chambers St New York NY 10007",
    "addr:housenumber":"114",
    "addr:postcode":"10007",
    "addr:street":"Chambers St",
    "iso:country":"US",
    "sg:address":"114 Chambers St",
    "sg:city":"New York",
    "sg:classifiers":[
        {
            "category":"Shopping",
            "subcategory":"Shoes",
            "type":"Retail Goods"
        }
    ],
    "sg:phone":"+1   ",
    "sg:postcode":"10007",
    "sg:province":"NY",
    "wof:name":"Gabriel Shoe Store",
    "wof:placetype":"venue"
},
  "geometry": {"coordinates":[-74.0085592961,40.7150588519],"type":"Point"}
}