{
  "type": "Feature",
  "properties": {
    "addr:full":"21 Village Gate Way Nyack NY 10960",
    "addr:housenumber":"21",
    "addr:postcode":"10960",
    "addr:street":"Village Gate Way",
    "iso:country":"US",
    "sg:address":"21 Village Gate Way",
    "sg:city":"Nyack",
    "sg:classifiers":[
        {
            "category":"Professional",
            "type":"Services"
        }
    ],
    "sg:phone":"+1   ",
    "sg:postcode":"10960",
    "sg:province":"NY",
    "sg:tags":[
        "house"
    ],
    "wof:name":"Building Institute The",
    "wof:placetype":"venue"
},
  "geometry": {"coordinates":[-73.92728700000001,41.100375],"type":"Point"}
}