{
  "type": "Feature",
  "properties": {
    "addr:full":"64 Fillmore Ave Buffalo NY 14210",
    "addr:housenumber":"64",
    "addr:postcode":"14210",
    "addr:street":"Fillmore Ave",
    "iso:country":"US",
    "sg:address":"64 Fillmore Ave",
    "sg:city":"Buffalo",
    "sg:classifiers":[
        {
            "category":"Building & Trades",
            "subcategory":"Construction",
            "type":"Services"
        }
    ],
    "sg:phone":"+1 716 821 1524",
    "sg:postcode":"14210",
    "sg:province":"NY",
    "sg:tags":[
        "dry wall",
        "contractor"
    ],
    "wof:name":"T L R Interiors Inc",
    "wof:placetype":"venue"
},
  "geometry": {"coordinates":[-78.84262099999999,42.876159],"type":"Point"}
}