{
  "type": "Feature",
  "properties": {
    "addr:full":"3559 Winton Pl Rochester NY 14623",
    "addr:housenumber":"3559",
    "addr:postcode":"14623",
    "addr:street":"Winton Pl",
    "iso:country":"US",
    "sg:address":"3559 Winton Pl",
    "sg:city":"Rochester",
    "sg:classifiers":[
        {
            "category":"Wholesale",
            "subcategory":"Electrical",
            "type":"Manufacturing & Wholesale Goods"
        }
    ],
    "sg:phone":"+1 585 427 7870",
    "sg:postcode":"14623",
    "sg:province":"NY",
    "wof:name":"Northeast Controls-Rochester",
    "wof:placetype":"venue"
},
  "geometry": {"coordinates":[-77.571017,43.094863],"type":"Point"}
}