{
  "type": "Feature",
  "properties": {
    "addr:full":"116 Eldridge St New York NY 10002",
    "addr:housenumber":"116",
    "addr:postcode":"10002",
    "addr:street":"Eldridge St",
    "iso:country":"US",
    "sg:address":"116 Eldridge St",
    "sg:city":"New York",
    "sg:classifiers":[
        {
            "category":"Professional",
            "type":"Services"
        }
    ],
    "sg:phone":"+1 212 219 3332",
    "sg:postcode":"10002",
    "sg:province":"NY",
    "sg:tags":[
        "establishment"
    ],
    "wof:name":"Mr Xian Quan Li",
    "wof:placetype":"venue"
},
  "geometry": {"coordinates":[-73.991916,40.717939],"type":"Point"}
}