{
  "type": "Feature",
  "properties": {
    "addr:full":"1281 Saint Paul St Rochester NY 14621",
    "addr:housenumber":"1281",
    "addr:postcode":"14621",
    "addr:street":"Saint Paul St",
    "iso:country":"US",
    "sg:address":"1281 Saint Paul St",
    "sg:city":"Rochester",
    "sg:classifiers":[
        {
            "category":"Professional",
            "type":"Services"
        }
    ],
    "sg:phone":"+1 585 467 0780",
    "sg:postcode":"14621",
    "sg:province":"NY",
    "sg:tags":[
        "establishment"
    ],
    "wof:name":"Quality Plus",
    "wof:placetype":"venue"
},
  "geometry": {"coordinates":[-77.62516599999999,43.178565],"type":"Point"}
}