{
  "type": "Feature",
  "properties": {
    "addr:full":"5 S Campbell St Bath NY 14810",
    "addr:housenumber":"5",
    "addr:postcode":"14810",
    "addr:street":"S Campbell St",
    "iso:country":"US",
    "sg:address":"5 S Campbell St",
    "sg:city":"Bath",
    "sg:classifiers":[
        {
            "category":"Wholesale",
            "subcategory":"Machinery & Supplies",
            "type":"Manufacturing & Wholesale Goods"
        }
    ],
    "sg:phone":"+1 607 776 9044",
    "sg:postcode":"14810",
    "sg:province":"NY",
    "wof:name":"KLR Machines Inc",
    "wof:placetype":"venue"
},
  "geometry": {"coordinates":[-77.31137200000001,42.332414],"type":"Point"}
}