{
  "type": "Feature",
  "properties": {
    "iso:country":"US",
    "sg:address":"265 Sunrise Hwy",
    "sg:city":"Rockville Centre",
    "sg:classifiers":[
        {
            "category":"Insurance",
            "subcategory":"Insurance Agent",
            "type":"Services"
        }
    ],
    "sg:phone":"+1 516 764 7800",
    "sg:postcode":"11570",
    "sg:province":"NY",
    "wof:name":"OToole Edwin J",
    "wof:placetype":"venue"
},
  "geometry": {"coordinates":[-73.645471,40.657524],"type":"Point"}
}