{
  "type": "Feature",
  "properties": {
    "iso:country":"US",
    "sg:address":"432 W 31st St",
    "sg:city":"New York",
    "sg:classifiers":[
        {
            "category":"Transit Center",
            "subcategory":"Passenger",
            "type":"Transportation"
        }
    ],
    "sg:phone":"+1 212 239 0200",
    "sg:postcode":"10001",
    "sg:province":"NY",
    "sg:website":"www.revolutionrickshaws.com",
    "wof:name":"Revolution Rickshaws",
    "wof:placetype":"venue"
},
  "geometry": {"coordinates":[-73.99936700000001,40.751954],"type":"Point"}
}