{
  "type": "Feature",
  "properties": {
    "addr:full":"4206 8th Avenue Brooklyn NY 11232",
    "addr:housenumber":"4206",
    "addr:postcode":"11232",
    "addr:street":"8Th Avenue",
    "iso:country":"US",
    "sg:address":"4206 8th Avenue",
    "sg:city":"Brooklyn",
    "sg:classifiers":[
        {
            "category":"Personal",
            "subcategory":"Beauty Salon",
            "type":"Services"
        },
        {
            "category":"Personal",
            "subcategory":"Skin Care",
            "type":"Services"
        },
        {
            "category":"Personal",
            "subcategory":"Nail Salon",
            "type":"Services"
        }
    ],
    "sg:phone":"+1 718 438 8200",
    "sg:postcode":"11232",
    "sg:province":"NY",
    "sg:tags":[
        "hair"
    ],
    "wof:name":"8th Ave Spa",
    "wof:placetype":"venue"
},
  "geometry": {"coordinates":[-73.999448,40.645549],"type":"Point"}
}