{
  "type": "Feature",
  "properties": {
    "iso:country":"US",
    "sg:address":"2050 Lexington Ave",
    "sg:city":"New York",
    "sg:classifiers":[
        {
            "category":"Shopping",
            "subcategory":"Discount & Variety Stores",
            "type":"Retail Goods"
        }
    ],
    "sg:phone":"+1 212 876 9851",
    "sg:postcode":"10035",
    "sg:province":"NY",
    "wof:name":"Dollar Magic LLC",
    "wof:placetype":"venue"
},
  "geometry": {"coordinates":[-73.937577,40.804241],"type":"Point"}
}