{
  "type": "Feature",
  "properties": {
    "addr:full":"1600 Avenue L Brooklyn NY 11230",
    "addr:housenumber":"1600",
    "addr:postcode":"11230",
    "addr:street":"Avenue L",
    "iso:country":"US",
    "sg:address":"1600 Avenue L",
    "sg:city":"Brooklyn",
    "sg:classifiers":[
        {
            "category":"Education",
            "subcategory":"School",
            "type":"Public Place"
        }
    ],
    "sg:phone":"+1 718 258 9283",
    "sg:postcode":"11230",
    "sg:province":"NY",
    "sg:tags":[
        "high",
        "middle",
        "elementary"
    ],
    "wof:name":"N Y City of",
    "wof:placetype":"venue"
},
  "geometry": {"coordinates":[-73.959926,40.620352],"type":"Point"}
}