{
  "type": "Feature",
  "properties": {
    "iso:country":"US",
    "sg:address":"1470 Broadway",
    "sg:city":"New York",
    "sg:classifiers":[
        {
            "category":"Retail",
            "subcategory":"Auto Repair",
            "type":"Services"
        }
    ],
    "sg:phone":"+1 646 307 4532",
    "sg:postcode":"10036",
    "sg:province":"NY",
    "sg:tags":[
        "wrecker"
    ],
    "wof:name":"ACTAVA Classic Car Repair",
    "wof:placetype":"venue"
},
  "geometry": {"coordinates":[-73.986639,40.755035],"type":"Point"}
}