{
  "type": "Feature",
  "properties": {
    "addr:full":"133 E 4th St New York NY 10003",
    "addr:housenumber":"133",
    "addr:postcode":"10003",
    "addr:street":"E 4Th St",
    "iso:country":"US",
    "sg:address":"133 E 4th St",
    "sg:city":"New York",
    "sg:classifiers":[
        {
            "category":"Personal",
            "subcategory":"Massage",
            "type":"Services"
        },
        {
            "category":"Personal",
            "subcategory":"Skin Care",
            "type":"Services"
        }
    ],
    "sg:phone":"+1 212 533 1456",
    "sg:postcode":"10003",
    "sg:province":"NY",
    "wof:name":"Lavender Mini Spa",
    "wof:placetype":"venue"
},
  "geometry": {"coordinates":[-73.987156,40.725231],"type":"Point"}
}