{
  "type": "Feature",
  "properties": {
    "addr:full":"78 Willoughby St Brooklyn NY 11201",
    "addr:housenumber":"78",
    "addr:postcode":"11201",
    "addr:street":"Willoughby St",
    "iso:country":"US",
    "sg:address":"78 Willoughby St",
    "sg:city":"Brooklyn",
    "sg:classifiers":[
        {
            "category":"Retail",
            "subcategory":"Repair Shop",
            "type":"Services"
        }
    ],
    "sg:phone":"+1 718 301 7223",
    "sg:postcode":"11201",
    "sg:province":"NY",
    "sg:tags":[
        "lock",
        "locksmith"
    ],
    "wof:name":"All Day Emergency Locksmith",
    "wof:placetype":"venue"
},
  "geometry": {"coordinates":[-73.985868,40.692112],"type":"Point"}
}