{
  "type": "Feature",
  "properties": {
    "iso:country":"US",
    "sg:address":"1255 Bellmore Rd",
    "sg:city":"North Bellmore",
    "sg:classifiers":[
        {
            "category":"Government",
            "subcategory":"Police Station",
            "type":"Public Place"
        }
    ],
    "sg:phone":"+1 516 573 8210",
    "sg:postcode":"11710",
    "sg:province":"NY",
    "sg:tags":[
        "department"
    ],
    "wof:name":"Nassau County Police Dept",
    "wof:placetype":"venue"
},
  "geometry": {"coordinates":[-73.533587,40.689124],"type":"Point"}
}