{
  "type": "Feature",
  "properties": {
    "addr:full":"122 S 4th Ave Mt Vernon NY 10550",
    "addr:housenumber":"122",
    "addr:postcode":"10550",
    "addr:street":"S 4Th Ave",
    "iso:country":"US",
    "sg:address":"122 S 4th Ave",
    "sg:city":"Mt Vernon",
    "sg:classifiers":[
        {
            "category":"Home & Garden",
            "subcategory":"Furniture",
            "type":"Retail Goods"
        }
    ],
    "sg:phone":"+1 914 668 9242",
    "sg:postcode":"10550",
    "sg:province":"NY",
    "wof:name":"Regal Furniture",
    "wof:placetype":"venue"
},
  "geometry": {"coordinates":[-73.835492,40.907311],"type":"Point"}
}