{
  "type": "Feature",
  "properties": {
    "addr:full":"87 Lake St Le Roy NY 14482",
    "addr:housenumber":"87",
    "addr:postcode":"14482",
    "addr:street":"Lake St",
    "iso:country":"US",
    "sg:address":"87 Lake St",
    "sg:city":"Le Roy",
    "sg:classifiers":[
        {
            "category":"Social Services",
            "type":"Services"
        }
    ],
    "sg:phone":"+1 585 768 9329",
    "sg:postcode":"14482",
    "sg:province":"NY",
    "sg:tags":[
        "organization",
        "welfare"
    ],
    "sg:website":"www.lifetimeassistance.org",
    "wof:name":"Lifetime Assistance",
    "wof:placetype":"venue"
},
  "geometry": {"coordinates":[-77.992267,42.981776],"type":"Point"}
}