{
  "type": "Feature",
  "properties": {
    "addr:full":"52 1st Ave Ossining NY 10562",
    "addr:housenumber":"52",
    "addr:postcode":"10562",
    "addr:street":"1St Ave",
    "iso:country":"US",
    "sg:address":"52 1st Ave",
    "sg:city":"Ossining",
    "sg:classifiers":[
        {
            "category":"Manufacturing",
            "subcategory":"Textiles",
            "type":"Manufacturing & Wholesale Goods"
        }
    ],
    "sg:phone":"+1   ",
    "sg:postcode":"10562",
    "sg:province":"NY",
    "sg:tags":[
        "lace",
        "mfg"
    ],
    "wof:name":"Encajes Mexicanos",
    "wof:placetype":"venue"
},
  "geometry": {"coordinates":[-73.845206,41.176237],"type":"Point"}
}