{
  "type": "Feature",
  "properties": {
    "addr:full":"50 Garth Rd Scarsdale NY 10583",
    "addr:housenumber":"50",
    "addr:postcode":"10583",
    "addr:street":"Garth Rd",
    "iso:country":"US",
    "sg:address":"50 Garth Rd",
    "sg:city":"Scarsdale",
    "sg:classifiers":[
        {
            "category":"Retail",
            "subcategory":"Laundry & Dry Cleaning",
            "type":"Services"
        }
    ],
    "sg:phone":"+1   ",
    "sg:postcode":"10583",
    "sg:province":"NY",
    "sg:tags":[
        "hand"
    ],
    "wof:name":"Scarsdale Hand Laundry Inc",
    "wof:placetype":"venue"
},
  "geometry": {"coordinates":[-73.809915,40.987973],"type":"Point"}
}