{
  "type": "Feature",
  "properties": {
    "addr:full":"1015 Prospect Ave Westbury NY 11590",
    "addr:housenumber":"1015",
    "addr:postcode":"11590",
    "addr:street":"Prospect Ave",
    "iso:country":"US",
    "sg:address":"1015 Prospect Ave",
    "sg:city":"Westbury",
    "sg:classifiers":[
        {
            "category":"Personal",
            "subcategory":"Beauty Salon",
            "type":"Services"
        }
    ],
    "sg:phone":"+1 516 334 3060",
    "sg:postcode":"11590",
    "sg:province":"NY",
    "wof:name":"Timeless Beauty Salon",
    "wof:placetype":"venue"
},
  "geometry": {"coordinates":[-73.56026799999999,40.763012],"type":"Point"}
}