{
  "type": "Feature",
  "properties": {
    "iso:country":"US",
    "sg:address":"10794 Darien Rd",
    "sg:city":"Holland",
    "sg:classifiers":[
        {
            "category":"Social Services",
            "subcategory":"Child Care",
            "type":"Services"
        }
    ],
    "sg:phone":"+1 716 652 2176",
    "sg:postcode":"14080",
    "sg:province":"NY",
    "sg:tags":[
        "day"
    ],
    "wof:name":"South Wales Pre School Inc",
    "wof:placetype":"venue"
},
  "geometry": {"coordinates":[-78.579481,42.691815],"type":"Point"}
}