{
  "type": "Feature",
  "properties": {
    "addr:full":"502 Summit Ave Schenectady NY 12307",
    "addr:housenumber":"502",
    "addr:postcode":"12307",
    "addr:street":"Summit Ave",
    "iso:country":"US",
    "sg:address":"502 Summit Ave",
    "sg:city":"Schenectady",
    "sg:classifiers":[
        {
            "category":"Autos & Motor Vehicles",
            "subcategory":"Boat Sales",
            "type":"Retail Goods"
        }
    ],
    "sg:phone":"+1   ",
    "sg:postcode":"12307",
    "sg:province":"NY",
    "wof:name":"Schenectady Canoe Sales",
    "wof:placetype":"venue"
},
  "geometry": {"coordinates":[-73.94640099999999,42.804938],"type":"Point"}
}