{
  "type": "Feature",
  "properties": {
    "iso:country":"US",
    "sg:address":"16010 Co Rd 125",
    "sg:city":"Chaumont",
    "sg:classifiers":[
        {
            "category":"Retail",
            "subcategory":"Auto Repair",
            "type":"Services"
        }
    ],
    "sg:phone":"+1 315 649 5911",
    "sg:postcode":"13622",
    "sg:province":"NY",
    "sg:tags":[
        "repairing",
        "automobile"
    ],
    "wof:name":"Bob's Garage",
    "wof:placetype":"venue"
},
  "geometry": {"coordinates":[-76.05466199999999,44.087791],"type":"Point"}
}