{
  "type": "Feature",
  "properties": {
    "addr:full":"187 Duane St New York NY 10013",
    "addr:housenumber":"187",
    "addr:postcode":"10013",
    "addr:street":"Duane St",
    "iso:country":"US",
    "sg:address":"187 Duane St",
    "sg:city":"New York",
    "sg:classifiers":[
        {
            "category":"Restaurant",
            "type":"Food & Drink"
        }
    ],
    "sg:phone":"+1   ",
    "sg:postcode":"10013",
    "sg:province":"NY",
    "sg:tags":[
        "eating"
    ],
    "wof:name":"Cornerstone Grill",
    "wof:placetype":"venue"
},
  "geometry": {"coordinates":[-74.010396,40.717494],"type":"Point"}
}