{
  "type": "Feature",
  "properties": {
    "iso:country":"US",
    "sg:address":"51 Locustwood Blvd",
    "sg:city":"Elmont",
    "sg:classifiers":[
        {
            "category":"Building & Trades",
            "subcategory":"Construction",
            "type":"Services"
        }
    ],
    "sg:phone":"+1 516 775 1424",
    "sg:postcode":"11003",
    "sg:province":"NY",
    "sg:tags":[
        "house"
    ],
    "wof:name":"Campbell Delson",
    "wof:placetype":"venue"
},
  "geometry": {"coordinates":[-73.72190000000001,40.708709],"type":"Point"}
}