{
  "type": "Feature",
  "properties": {
    "iso:country":"US",
    "sg:address":"54 Ransier Dr",
    "sg:city":"Buffalo",
    "sg:classifiers":[
        {
            "category":"Manufacturing",
            "subcategory":"Metals",
            "type":"Manufacturing & Wholesale Goods"
        }
    ],
    "sg:phone":"+1 716 675 8180",
    "sg:postcode":"14224",
    "sg:province":"NY",
    "sg:tags":[
        "steel",
        "fabrication"
    ],
    "wof:name":"Buffalo Steelwork",
    "wof:placetype":"venue"
},
  "geometry": {"coordinates":[-78.74681200000001,42.847171],"type":"Point"}
}