{
  "type": "Feature",
  "properties": {
    "addr:full":"39 E 78th St Ste 501 New York NY 10075",
    "addr:housenumber":"39;501",
    "addr:postcode":"10075",
    "addr:street":"E 78Th St Ste",
    "iso:country":"US",
    "sg:address":"39 E 78th St Ste 501",
    "sg:city":"New York",
    "sg:classifiers":[
        {
            "category":"Health Services",
            "subcategory":"Doctor",
            "type":"Services"
        }
    ],
    "sg:phone":"+1 212 362 2820",
    "sg:postcode":"10075",
    "sg:province":"NY",
    "wof:name":"West 70 Psychology PC",
    "wof:placetype":"venue"
},
  "geometry": {"coordinates":[-73.96253900000001,40.775766],"type":"Point"}
}