{
  "type": "Feature",
  "properties": {
    "iso:country":"US",
    "sg:address":"70 Woodland Rd",
    "sg:city":"Pleasantville",
    "sg:classifiers":[
        {
            "category":"Building & Trades",
            "subcategory":"Construction",
            "type":"Services"
        }
    ],
    "sg:phone":"+1 914 769 7412",
    "sg:postcode":"10570",
    "sg:province":"NY",
    "sg:tags":[
        "floor",
        "laying",
        "contractor"
    ],
    "wof:name":"Total Carpet Services",
    "wof:placetype":"venue"
},
  "geometry": {"coordinates":[-73.772257,41.145713],"type":"Point"}
}