{
  "type": "Feature",
  "properties": {
    "addr:full":"1584 Saint Johns Place Brooklyn NY 11213",
    "addr:housenumber":"1584",
    "addr:postcode":"11213",
    "addr:street":"Saint Johns Place",
    "iso:country":"US",
    "sg:address":"1584 Saint Johns Place",
    "sg:city":"Brooklyn",
    "sg:classifiers":[
        {
            "category":"Restaurant",
            "type":"Food & Drink"
        }
    ],
    "sg:phone":"+1 718 756 0699",
    "sg:postcode":"11213",
    "sg:province":"NY",
    "wof:name":"Sun Hing Restaurant",
    "wof:placetype":"venue"
},
  "geometry": {"coordinates":[-73.925646,40.670183],"type":"Point"}
}