{
  "type": "Feature",
  "properties": {
    "addr:full":"555 Liberty Ave Brooklyn NY 11207",
    "addr:housenumber":"555",
    "addr:postcode":"11207",
    "addr:street":"Liberty Ave",
    "iso:country":"US",
    "sg:address":"555 Liberty Ave",
    "sg:city":"Brooklyn",
    "sg:classifiers":[
        {
            "category":"Organizations",
            "subcategory":"Religious Organization",
            "type":"Services"
        }
    ],
    "sg:phone":"+1 718 647 0421",
    "sg:postcode":"11207",
    "sg:province":"NY",
    "sg:tags":[
        "church"
    ],
    "wof:name":"True Worship Church",
    "wof:placetype":"venue"
},
  "geometry": {"coordinates":[-73.88979,40.675443],"type":"Point"}
}