{
  "type": "Feature",
  "properties": {
    "iso:country":"US",
    "sg:address":"284 Beecher Rd",
    "sg:city":"Granville",
    "sg:classifiers":[
        {
            "category":"Manufacturing",
            "subcategory":"Printing",
            "type":"Manufacturing & Wholesale Goods"
        }
    ],
    "sg:phone":"+1 518 642 1810",
    "sg:postcode":"12832",
    "sg:province":"NY",
    "sg:tags":[
        "printer"
    ],
    "wof:name":"Printing Plus",
    "wof:placetype":"venue"
},
  "geometry": {"coordinates":[-73.270117,43.386991],"type":"Point"}
}