{
  "type": "Feature",
  "properties": {
    "iso:country":"US",
    "sg:address":"1661 Metropolitan Ave",
    "sg:city":"Bronx",
    "sg:classifiers":[
        {
            "category":"Restaurant",
            "type":"Food & Drink"
        }
    ],
    "sg:phone":"+1 718 822 1616",
    "sg:postcode":"10462",
    "sg:province":"NY",
    "sg:tags":[
        "chinese"
    ],
    "wof:name":"Wing Hing Chinese Restaurant",
    "wof:placetype":"venue"
},
  "geometry": {"coordinates":[-73.856499,40.8405],"type":"Point"}
}