{
  "type": "Feature",
  "properties": {
    "iso:country":"US",
    "sg:address":"227 E 105th St",
    "sg:city":"New York",
    "sg:classifiers":[
        {
            "category":"Retail",
            "subcategory":"Repair Shop",
            "type":"Services"
        }
    ],
    "sg:phone":"+1 212 924 7274",
    "sg:postcode":"10029",
    "sg:province":"NY",
    "wof:name":"Sean Coakley Plumbing & Htg",
    "wof:placetype":"venue"
},
  "geometry": {"coordinates":[-73.943341,40.790265],"type":"Point"}
}