{
  "type": "Feature",
  "properties": {
    "iso:country":"US",
    "sg:address":"2420 N Forest Rd",
    "sg:city":"Getzville",
    "sg:classifiers":[
        {
            "category":"Banks & Credit Unions",
            "subcategory":"Investment Brokerage",
            "type":"Services"
        }
    ],
    "sg:phone":"+1 716 204 2230",
    "sg:postcode":"14068",
    "sg:province":"NY",
    "sg:tags":[
        "security"
    ],
    "wof:name":"Waddell & Reed Inc",
    "wof:placetype":"venue"
},
  "geometry": {"coordinates":[-78.777197,43.009399],"type":"Point"}
}