{
  "type": "Feature",
  "properties": {
    "addr:full":"1224 Park Pl Brooklyn NY 11213",
    "addr:housenumber":"1224",
    "addr:postcode":"11213",
    "addr:street":"Park Pl",
    "iso:country":"US",
    "sg:address":"1224 Park Pl",
    "sg:city":"Brooklyn",
    "sg:classifiers":[
        {
            "category":"Building & Trades",
            "subcategory":"Cleaning & Sanitation",
            "type":"Services"
        }
    ],
    "sg:phone":"+1 718 778 6155",
    "sg:postcode":"11213",
    "sg:province":"NY",
    "sg:tags":[
        "maintenance"
    ],
    "wof:name":"Temco Services Inc",
    "wof:placetype":"venue"
},
  "geometry": {"coordinates":[-73.938338,40.672717],"type":"Point"}
}