{
  "type": "Feature",
  "properties": {
    "addr:full":"103 Twin Oaks Dr Syracuse NY 13206",
    "addr:housenumber":"103",
    "addr:postcode":"13206",
    "addr:street":"Twin Oaks Dr",
    "iso:country":"US",
    "sg:address":"103 Twin Oaks Dr",
    "sg:city":"Syracuse",
    "sg:classifiers":[
        {
            "category":"Health Services",
            "subcategory":"Medical Lab",
            "type":"Services"
        }
    ],
    "sg:phone":"+1 315 432 1961",
    "sg:postcode":"13206",
    "sg:province":"NY",
    "sg:tags":[
        "x"
    ],
    "wof:name":"Mobile Magnetic Resources LTD",
    "wof:placetype":"venue"
},
  "geometry": {"coordinates":[-76.109122,43.090041],"type":"Point"}
}