{
  "type": "Feature",
  "properties": {
    "addr:full":"145 E 72 St New York NY 10021",
    "addr:housenumber":"145;72",
    "addr:postcode":"10021",
    "addr:street":"E;St",
    "iso:country":"US",
    "sg:address":"145 E 72 St",
    "sg:city":"New York",
    "sg:classifiers":[
        {
            "category":"Professional",
            "type":"Services"
        },
        {
            "category":"Shopping",
            "type":"Retail Goods"
        }
    ],
    "sg:phone":"+1 212 472 8741",
    "sg:postcode":"10021",
    "sg:province":"NY",
    "sg:tags":[
        "establishment",
        "merchandise"
    ],
    "wof:name":"Cucalon Eugenia Gallery",
    "wof:placetype":"venue"
},
  "geometry": {"coordinates":[-73.96065,40.769861],"type":"Point"}
}