{
  "type": "Feature",
  "properties": {
    "addr:full":"2331 Curry Rd Schenectady NY 12303",
    "addr:housenumber":"2331",
    "addr:postcode":"12303",
    "addr:street":"Curry Rd",
    "iso:country":"US",
    "sg:address":"2331 Curry Rd",
    "sg:city":"Schenectady",
    "sg:classifiers":[
        {
            "category":"Personal",
            "subcategory":"Beauty Salon",
            "type":"Services"
        }
    ],
    "sg:phone":"+1 518 355 4979",
    "sg:postcode":"12303",
    "sg:province":"NY",
    "wof:name":"L K's Hair & Beauty Salon",
    "wof:placetype":"venue"
},
  "geometry": {"coordinates":[-73.946686,42.770616],"type":"Point"}
}