{
  "type": "Feature",
  "properties": {
    "iso:country":"US",
    "sg:address":"162 W Main St",
    "sg:city":"Middletown",
    "sg:classifiers":[
        {
            "category":"Government",
            "subcategory":"Office",
            "type":"Public Place"
        }
    ],
    "sg:phone":"+1 845 344 1355",
    "sg:postcode":"10940",
    "sg:province":"NY",
    "sg:tags":[
        "federal",
        "program",
        "adm"
    ],
    "wof:name":"US Census Bureau",
    "wof:placetype":"venue"
},
  "geometry": {"coordinates":[-74.430503,41.448207],"type":"Point"}
}