{
  "type": "Feature",
  "properties": {
    "iso:country":"US",
    "sg:address":"256 Harry L Dr",
    "sg:city":"Johnson City",
    "sg:classifiers":[
        {
            "category":"Health Services",
            "subcategory":"Doctor",
            "type":"Services"
        }
    ],
    "sg:phone":"+1 607 777 9475",
    "sg:postcode":"13790",
    "sg:province":"NY",
    "sg:tags":[
        "physician",
        "surgeon"
    ],
    "wof:name":"Tier Pediatric",
    "wof:placetype":"venue"
},
  "geometry": {"coordinates":[-75.958663,42.122675],"type":"Point"}
}