{
  "type": "Feature",
  "properties": {
    "iso:country":"US",
    "sg:address":"88 Geddes St",
    "sg:city":"Holley",
    "sg:classifiers":[
        {
            "category":"Home & Garden",
            "subcategory":"Building Materials",
            "type":"Retail Goods"
        }
    ],
    "sg:phone":"+1   ",
    "sg:postcode":"14470",
    "sg:province":"NY",
    "sg:tags":[
        "builder",
        "lumber",
        "supply"
    ],
    "wof:name":"Stockham Lumber Co",
    "wof:placetype":"venue"
},
  "geometry": {"coordinates":[-78.03437599999999,43.225114],"type":"Point"}
}