{
  "type": "Feature",
  "properties": {
    "addr:full":"9 S Park St Cambridge NY 12816",
    "addr:housenumber":"9",
    "addr:postcode":"12816",
    "addr:street":"S Park St",
    "iso:country":"US",
    "sg:address":"9 S Park St",
    "sg:city":"Cambridge",
    "sg:classifiers":[
        {
            "category":"Real Estate",
            "subcategory":"Real Estate Agent",
            "type":"Services"
        }
    ],
    "sg:phone":"+1 518 677 8588",
    "sg:postcode":"12816",
    "sg:province":"NY",
    "wof:name":"Country Properties Real Estate",
    "wof:placetype":"venue"
},
  "geometry": {"coordinates":[-73.375978,43.026162],"type":"Point"}
}