{
  "type": "Feature",
  "properties": {
    "iso:country":"US",
    "sg:address":"173 Lakeshore Dr",
    "sg:city":"Hilton",
    "sg:classifiers":[
        {
            "category":"Wholesale",
            "subcategory":"Durable Goods & Equipment",
            "type":"Manufacturing & Wholesale Goods"
        }
    ],
    "sg:phone":"+1 585 392 6071",
    "sg:postcode":"14468",
    "sg:province":"NY",
    "wof:name":"World Wide Supplements",
    "wof:placetype":"venue"
},
  "geometry": {"coordinates":[-77.74495,43.332869],"type":"Point"}
}