{
  "type": "Feature",
  "properties": {
    "iso:country":"US",
    "sg:address":"42 N Main St",
    "sg:city":"Mechanicville",
    "sg:classifiers":[
        {
            "category":"Health Services",
            "subcategory":"Doctor",
            "type":"Services"
        }
    ],
    "sg:phone":"+1 518 664 4903",
    "sg:postcode":"12118",
    "sg:province":"NY",
    "sg:tags":[
        "dentist"
    ],
    "wof:name":"Vincent F Fuschino DDS Inc",
    "wof:placetype":"venue"
},
  "geometry": {"coordinates":[-73.68529599999999,42.904041],"type":"Point"}
}