{
  "type": "Feature",
  "properties": {
    "iso:country":"US",
    "sg:address":"275 Marcus Blvd",
    "sg:city":"Hauppauge",
    "sg:classifiers":[
        {
            "category":"Shopping",
            "subcategory":"Computers & Home Electronics",
            "type":"Retail Goods"
        }
    ],
    "sg:phone":"+1 631 434 4770",
    "sg:postcode":"11788",
    "sg:province":"NY",
    "sg:tags":[
        "high",
        "fidelity",
        "stereophonic"
    ],
    "wof:name":"Audio Interiors Inc",
    "wof:placetype":"venue"
},
  "geometry": {"coordinates":[-73.247968,40.818632],"type":"Point"}
}