{
  "type": "Feature",
  "properties": {
    "iso:country":"US",
    "sg:address":"17471 Ridge Rd",
    "sg:city":"La Fargeville",
    "sg:classifiers":[
        {
            "category":"Building & Trades",
            "subcategory":"Construction",
            "type":"Services"
        }
    ],
    "sg:phone":"+1 315 658 9917",
    "sg:postcode":"13656",
    "sg:province":"NY",
    "sg:tags":[
        "contractor"
    ],
    "wof:name":"T and K Fence Systems",
    "wof:placetype":"venue"
},
  "geometry": {"coordinates":[-76.01482900000001,44.159796],"type":"Point"}
}