{
  "type": "Feature",
  "properties": {
    "addr:full":"2949 Long Beach Rd Oceanside NY 11572",
    "addr:housenumber":"2949",
    "addr:postcode":"11572",
    "addr:street":"Long Beach Rd",
    "iso:country":"US",
    "sg:address":"2949 Long Beach Rd",
    "sg:city":"Oceanside",
    "sg:classifiers":[
        {
            "category":"Professional",
            "subcategory":"Accounting & Tax Preparation",
            "type":"Services"
        }
    ],
    "sg:phone":"+1 516 678 5300",
    "sg:postcode":"11572",
    "sg:province":"NY",
    "sg:tags":[
        "accountant"
    ],
    "wof:name":"Steven Rosen CPA",
    "wof:placetype":"venue"
},
  "geometry": {"coordinates":[-73.639765,40.639437],"type":"Point"}
}