{
  "type": "Feature",
  "properties": {
    "addr:full":"138 E Park Ave Long Beach NY 11561",
    "addr:housenumber":"138",
    "addr:postcode":"11561",
    "addr:street":"E Park Ave",
    "iso:country":"US",
    "sg:address":"138 E Park Ave",
    "sg:city":"Long Beach",
    "sg:classifiers":[
        {
            "category":"Professional",
            "subcategory":"Management & Consulting",
            "type":"Services"
        }
    ],
    "sg:phone":"+1 516 889 6664",
    "sg:postcode":"11561",
    "sg:province":"NY",
    "sg:tags":[
        "ac",
        "legal"
    ],
    "wof:name":"Metropolitan Refunds",
    "wof:placetype":"venue"
},
  "geometry": {"coordinates":[-73.65910700000001,40.588446],"type":"Point"}
}