{
  "type": "Feature",
  "properties": {
    "iso:country":"US",
    "sg:address":"1 Elm St",
    "sg:city":"Locust Valley",
    "sg:classifiers":[
        {
            "category":"Wholesale",
            "subcategory":"Machinery & Supplies",
            "type":"Manufacturing & Wholesale Goods"
        }
    ],
    "sg:phone":"+1 516 671 7300",
    "sg:postcode":"11560",
    "sg:province":"NY",
    "sg:tags":[
        "equipment",
        "consulting",
        "industrial",
        "business"
    ],
    "wof:name":"Bio-TEC Systems",
    "wof:placetype":"venue"
},
  "geometry": {"coordinates":[-73.597898,40.874897],"type":"Point"}
}