{
  "type": "Feature",
  "properties": {
    "addr:full":"12 Homewood Ln Dix Hills NY 11746",
    "addr:housenumber":"12",
    "addr:postcode":"11746",
    "addr:street":"Homewood Ln",
    "iso:country":"US",
    "sg:address":"12 Homewood Ln",
    "sg:city":"Dix Hills",
    "sg:classifiers":[
        {
            "category":"Arts & Performance",
            "subcategory":"Theater",
            "type":"Entertainment"
        }
    ],
    "sg:phone":"+1 516 249 9797",
    "sg:postcode":"11746",
    "sg:province":"NY",
    "sg:tags":[
        "entertainer"
    ],
    "wof:name":"Optima Entertainment LTD",
    "wof:placetype":"venue"
},
  "geometry": {"coordinates":[-73.393017,40.786198],"type":"Point"}
}