{
  "type": "Feature",
  "properties": {
    "addr:full":"2413 Carter Rd Geneva NY 14456",
    "addr:housenumber":"2413",
    "addr:postcode":"14456",
    "addr:street":"Carter Rd",
    "iso:country":"US",
    "sg:address":"2413 Carter Rd",
    "sg:city":"Geneva",
    "sg:classifiers":[
        {
            "category":"Shopping",
            "type":"Retail Goods"
        }
    ],
    "sg:phone":"+1 315 789 2354",
    "sg:postcode":"14456",
    "sg:province":"NY",
    "sg:tags":[
        "limb",
        "artificial"
    ],
    "wof:name":"Privately Yours By Oma",
    "wof:placetype":"venue"
},
  "geometry": {"coordinates":[-76.99600599999999,42.916706],"type":"Point"}
}