{
  "type": "Feature",
  "properties": {
    "addr:full":"2011 Steinway St Long Island City NY 11105",
    "addr:housenumber":"2011",
    "addr:postcode":"11105",
    "addr:street":"Steinway St",
    "iso:country":"US",
    "sg:address":"2011 Steinway St",
    "sg:city":"Long Island City",
    "sg:classifiers":[
        {
            "category":"Autos & Motor Vehicles",
            "subcategory":"Automobile Sales",
            "type":"Retail Goods"
        }
    ],
    "sg:phone":"+1 718 777 6565",
    "sg:postcode":"11105",
    "sg:province":"NY",
    "sg:tags":[
        "limo"
    ],
    "wof:name":"Los Andes Car & Limousine Svce",
    "wof:placetype":"venue"
},
  "geometry": {"coordinates":[-73.901949,40.776189],"type":"Point"}
}