{
  "type": "Feature",
  "properties": {
    "iso:country":"US",
    "sg:address":"295 State Hwy 100",
    "sg:city":"Somers",
    "sg:classifiers":[
        {
            "category":"Government",
            "subcategory":"Police Station",
            "type":"Public Place"
        }
    ],
    "sg:phone":"+1 914 277 3651",
    "sg:postcode":"10589",
    "sg:province":"NY",
    "sg:tags":[
        "protection"
    ],
    "wof:name":"Troop K",
    "wof:placetype":"venue"
},
  "geometry": {"coordinates":[-73.68572399999999,41.327772],"type":"Point"}
}