{
  "type": "Feature",
  "properties": {
    "iso:country":"US",
    "sg:address":"325 Essjay Rd",
    "sg:city":"Buffalo",
    "sg:classifiers":[
        {
            "category":"Banks & Credit Unions",
            "subcategory":"Bank",
            "type":"Services"
        }
    ],
    "sg:phone":"+1 716 631 4825",
    "sg:postcode":"14221",
    "sg:province":"NY",
    "sg:tags":[
        "federal",
        "savings",
        "institution"
    ],
    "wof:name":"Washington Mutual Bank",
    "wof:placetype":"venue"
},
  "geometry": {"coordinates":[-78.736559,42.969738],"type":"Point"}
}