{
  "type": "Feature",
  "properties": {
    "addr:full":"648 Jackson Ave Bronx NY 10455",
    "addr:housenumber":"648",
    "addr:postcode":"10455",
    "addr:street":"Jackson Ave",
    "iso:country":"US",
    "sg:address":"648 Jackson Ave",
    "sg:city":"Bronx",
    "sg:classifiers":[
        {
            "category":"Manufacturing",
            "subcategory":"Printing",
            "type":"Manufacturing & Wholesale Goods"
        }
    ],
    "sg:phone":"+1 718 401 5808",
    "sg:postcode":"10455",
    "sg:province":"NY",
    "sg:tags":[
        "printer"
    ],
    "wof:name":"Printing Service",
    "wof:placetype":"venue"
},
  "geometry": {"coordinates":[-73.90817300000001,40.815383],"type":"Point"}
}