{
  "type": "Feature",
  "properties": {
    "addr:full":"2165 Kent Rd Kent NY 14477",
    "addr:housenumber":"2165",
    "addr:postcode":"14477",
    "addr:street":"Kent Rd",
    "iso:country":"US",
    "sg:address":"2165 Kent Rd",
    "sg:city":"Kent",
    "sg:classifiers":[
        {
            "category":"Social Services",
            "type":"Services"
        },
        {
            "category":"Professional",
            "subcategory":"Employment Agencies",
            "type":"Services"
        }
    ],
    "sg:phone":"+1 585 682 4353",
    "sg:postcode":"14477",
    "sg:province":"NY",
    "sg:tags":[
        "workers'",
        "placement",
        "volunteer"
    ],
    "wof:name":"Charis Group",
    "wof:placetype":"venue"
},
  "geometry": {"coordinates":[-78.13549,43.309561],"type":"Point"}
}