{
  "type": "Feature",
  "properties": {
    "addr:full":"74 Buttonwood Rd Staten Island NY 10304",
    "addr:housenumber":"74",
    "addr:postcode":"10304",
    "addr:street":"Buttonwood Rd",
    "iso:country":"US",
    "sg:address":"74 Buttonwood Rd",
    "sg:city":"Staten Island",
    "sg:classifiers":[
        {
            "category":"Building & Trades",
            "subcategory":"Construction",
            "type":"Services"
        }
    ],
    "sg:phone":"+1 718 979 4370",
    "sg:postcode":"10304",
    "sg:province":"NY",
    "sg:tags":[
        "house"
    ],
    "wof:name":"Block 3376 Construction Corp",
    "wof:placetype":"venue"
},
  "geometry": {"coordinates":[-74.109517,40.596792],"type":"Point"}
}