{
  "type": "Feature",
  "properties": {
    "iso:country":"US",
    "sg:address":"123 5th Ave",
    "sg:city":"Pelham",
    "sg:classifiers":[
        {
            "category":"Shopping",
            "subcategory":"Pharmacy",
            "type":"Retail Goods"
        }
    ],
    "sg:phone":"+1 914 738 3333",
    "sg:postcode":"10803",
    "sg:province":"NY",
    "wof:name":"Kleins Pharmacy",
    "wof:placetype":"venue"
},
  "geometry": {"coordinates":[-73.808532,40.913662],"type":"Point"}
}