{
  "type": "Feature",
  "properties": {
    "addr:full":"819 Utica Ave Brooklyn NY 11203",
    "addr:housenumber":"819",
    "addr:postcode":"11203",
    "addr:street":"Utica Ave",
    "iso:country":"US",
    "sg:address":"819 Utica Ave",
    "sg:city":"Brooklyn",
    "sg:classifiers":[
        {
            "category":"Shopping",
            "subcategory":"Clothing, Apparel, & Fashions",
            "type":"Retail Goods"
        }
    ],
    "sg:phone":"+1   ",
    "sg:postcode":"11203",
    "sg:province":"NY",
    "sg:tags":[
        "shoes"
    ],
    "wof:name":"Utica Sneaker King",
    "wof:placetype":"venue"
},
  "geometry": {"coordinates":[-73.930358,40.652377],"type":"Point"}
}