{
  "type": "Feature",
  "properties": {
    "iso:country":"US",
    "sg:address":"255 W 36 St",
    "sg:city":"New York",
    "sg:classifiers":[
        {
            "category":"Shopping",
            "subcategory":"Florist",
            "type":"Retail Goods"
        }
    ],
    "sg:phone":"+1 212 564 4925",
    "sg:postcode":"10018",
    "sg:province":"NY",
    "wof:name":"Flowers By Reuven LTD",
    "wof:placetype":"venue"
},
  "geometry": {"coordinates":[-73.991309,40.752882],"type":"Point"}
}