{
  "type": "Feature",
  "properties": {
    "iso:country":"US",
    "sg:address":"66 Edgar Ave",
    "sg:city":"Brookhaven",
    "sg:classifiers":[
        {
            "category":"Building & Trades",
            "subcategory":"Construction",
            "type":"Services"
        }
    ],
    "sg:phone":"+1 631 286 7182",
    "sg:postcode":"11719",
    "sg:province":"NY",
    "sg:tags":[
        "excavation",
        "contractor"
    ],
    "wof:name":"Bay Area Excavating, Inc.",
    "wof:placetype":"venue"
},
  "geometry": {"coordinates":[-72.913071,40.766676],"type":"Point"}
}