{
  "type": "Feature",
  "properties": {
    "addr:full":"224 W 30 St New York NY 10001",
    "addr:housenumber":"224",
    "addr:postcode":"10001",
    "addr:street":"W 30 St",
    "iso:country":"US",
    "sg:address":"224 W 30 St",
    "sg:city":"New York",
    "sg:classifiers":[
        {
            "category":"Insurance",
            "subcategory":"Insurance Agent",
            "type":"Services"
        }
    ],
    "sg:phone":"+1 212 931 6555",
    "sg:postcode":"10001",
    "sg:province":"NY",
    "wof:name":"Live Insurance",
    "wof:placetype":"venue"
},
  "geometry": {"coordinates":[-73.994809,40.749311],"type":"Point"}
}