{
  "type": "Feature",
  "properties": {
    "addr:full":"234 North Ave New Rochelle NY 10801",
    "addr:housenumber":"234",
    "addr:postcode":"10801",
    "addr:street":"North Ave",
    "iso:country":"US",
    "sg:address":"234 North Ave",
    "sg:city":"New Rochelle",
    "sg:classifiers":[
        {
            "category":"Food & Beverages",
            "subcategory":"Groceries & Convenience Stores",
            "type":"Retail Goods"
        },
        {
            "category":"Restaurant",
            "type":"Food & Drink"
        }
    ],
    "sg:phone":"+1 914 633 7835",
    "sg:postcode":"10801",
    "sg:province":"NY",
    "sg:tags":[
        "delicatessen"
    ],
    "wof:name":"Gino's Deli",
    "wof:placetype":"venue"
},
  "geometry": {"coordinates":[-73.782354,40.911327],"type":"Point"}
}