{
  "type": "Feature",
  "properties": {
    "addr:full":"1340 84th St Brooklyn NY 11228",
    "addr:housenumber":"1340",
    "addr:postcode":"11228",
    "addr:street":"84Th St",
    "iso:country":"US",
    "sg:address":"1340 84th St",
    "sg:city":"Brooklyn",
    "sg:classifiers":[
        {
            "category":"Wholesale",
            "subcategory":"Fruits & Vegetables",
            "type":"Manufacturing & Wholesale Goods"
        }
    ],
    "sg:phone":"+1 718 236 8626",
    "sg:postcode":"11228",
    "sg:province":"NY",
    "sg:tags":[
        "veggie"
    ],
    "wof:name":"Jaraq Produce",
    "wof:placetype":"venue"
},
  "geometry": {"coordinates":[-74.12035400000001,40.614151],"type":"Point"}
}