{
  "type": "Feature",
  "properties": {
    "iso:country":"US",
    "sg:address":"100 W 122nd St",
    "sg:city":"New York",
    "sg:classifiers":[
        {
            "category":"Real Estate",
            "subcategory":"Real Estate Agent",
            "type":"Services"
        }
    ],
    "sg:phone":"+1 212 694 3511",
    "sg:postcode":"10027",
    "sg:province":"NY",
    "sg:tags":[
        "cooperative"
    ],
    "wof:name":"Housing Development Fund Corp",
    "wof:placetype":"venue"
},
  "geometry": {"coordinates":[-73.94973899999999,40.80704],"type":"Point"}
}