{
  "type": "Feature",
  "properties": {
    "iso:country":"US",
    "sg:address":"186 Franklin St",
    "sg:city":"Springville",
    "sg:classifiers":[
        {
            "category":"Education",
            "subcategory":"School",
            "type":"Public Place"
        }
    ],
    "sg:phone":"+1 716 592 7002",
    "sg:postcode":"14141",
    "sg:province":"NY",
    "wof:name":"St Aloysius School",
    "wof:placetype":"venue"
},
  "geometry": {"coordinates":[-78.668605,42.510093],"type":"Point"}
}