{
  "type": "Feature",
  "properties": {
    "addr:full":"4 Regina Rd Airmont NY 10952",
    "addr:housenumber":"4",
    "addr:postcode":"10952",
    "addr:street":"Regina Rd",
    "iso:country":"US",
    "sg:address":"4 Regina Rd",
    "sg:city":"Airmont",
    "sg:classifiers":[
        {
            "category":"Real Estate",
            "subcategory":"Architect",
            "type":"Services"
        }
    ],
    "sg:phone":"+1 845 356 7942",
    "sg:postcode":"10952",
    "sg:province":"NY",
    "sg:tags":[
        "specification",
        "construction",
        "architectural",
        "engineer"
    ],
    "wof:name":"Goldstein Harry J",
    "wof:placetype":"venue"
},
  "geometry": {"coordinates":[-74.07534800000001,41.093849],"type":"Point"}
}