{
  "type": "Feature",
  "properties": {
    "iso:country":"US",
    "sg:address":"835 Yellow Tavern Rd",
    "sg:city":"Geneva",
    "sg:classifiers":[
        {
            "category":"Building & Trades",
            "subcategory":"Electrical",
            "type":"Services"
        }
    ],
    "sg:phone":"+1 315 585 6394",
    "sg:postcode":"14456",
    "sg:province":"NY",
    "sg:tags":[
        "electrical",
        "contractor"
    ],
    "wof:name":"Longs Electric Service",
    "wof:placetype":"venue"
},
  "geometry": {"coordinates":[-76.903594,42.849636],"type":"Point"}
}