{
  "type": "Feature",
  "properties": {
    "iso:country":"US",
    "sg:address":"600 Mamaroneck Ave Ste 106",
    "sg:city":"Harrison",
    "sg:classifiers":[
        {
            "category":"Health Services",
            "subcategory":"Doctor",
            "type":"Services"
        }
    ],
    "sg:phone":"+1 914 948 4277",
    "sg:postcode":"10528",
    "sg:province":"NY",
    "sg:tags":[
        "physician",
        "surgeon"
    ],
    "wof:name":"Arthur V Badikian Md",
    "wof:placetype":"venue"
},
  "geometry": {"coordinates":[-73.74324,40.97842],"type":"Point"}
}