{
  "type": "Feature",
  "properties": {
    "addr:full":"6 S Main St Harriman NY 10926",
    "addr:housenumber":"6",
    "addr:postcode":"10926",
    "addr:street":"S Main St",
    "iso:country":"US",
    "sg:address":"6 S Main St",
    "sg:city":"Harriman",
    "sg:classifiers":[
        {
            "category":"Freight",
            "type":"Transportation"
        }
    ],
    "sg:phone":"+1   ",
    "sg:postcode":"10926",
    "sg:province":"NY",
    "sg:tags":[
        "distance",
        "moving",
        "long",
        "local"
    ],
    "wof:name":"Reliant Trucking",
    "wof:placetype":"venue"
},
  "geometry": {"coordinates":[-74.15005600000001,41.309232],"type":"Point"}
}