{
  "type": "Feature",
  "properties": {
    "addr:full":"626 N Barry Ave Mamaroneck NY 10543",
    "addr:housenumber":"626",
    "addr:postcode":"10543",
    "addr:street":"N Barry Ave",
    "iso:country":"US",
    "sg:address":"626 N Barry Ave",
    "sg:city":"Mamaroneck",
    "sg:classifiers":[
        {
            "category":"Restaurant",
            "type":"Food & Drink"
        }
    ],
    "sg:phone":"+1 914 835 0808",
    "sg:postcode":"10543",
    "sg:province":"NY",
    "sg:tags":[
        "delicatessen"
    ],
    "wof:name":"Guy's Deli",
    "wof:placetype":"venue"
},
  "geometry": {"coordinates":[-73.73179500000001,40.95963],"type":"Point"}
}