{
  "type": "Feature",
  "properties": {
    "iso:country":"US",
    "sg:address":"51 W 16 St",
    "sg:city":"New York",
    "sg:classifiers":[
        {
            "category":"Professional",
            "type":"Services"
        }
    ],
    "sg:phone":"+1 212 924 3323",
    "sg:postcode":"10011",
    "sg:province":"NY",
    "sg:tags":[
        "establishment"
    ],
    "wof:name":"Jane Brinker LTD",
    "wof:placetype":"venue"
},
  "geometry": {"coordinates":[-73.99459299999999,40.73806],"type":"Point"}
}