{
  "type": "Feature",
  "properties": {
    "iso:country":"US",
    "sg:address":"85 N Chestnut St",
    "sg:city":"New Paltz",
    "sg:classifiers":[
        {
            "category":"Autos & Motor Vehicles",
            "subcategory":"Auto Supplies",
            "type":"Retail Goods"
        }
    ],
    "sg:phone":"+1 845 255 0200",
    "sg:postcode":"12561",
    "sg:province":"NY",
    "sg:tags":[
        "automobile",
        "parts"
    ],
    "wof:name":"NAPA Auto Parts",
    "wof:placetype":"venue"
},
  "geometry": {"coordinates":[-74.084924,41.752952],"type":"Point"}
}