{
  "type": "Feature",
  "properties": {
    "addr:full":"806 Nostrand Avenue Brooklyn NY 11216",
    "addr:housenumber":"806",
    "addr:postcode":"11216",
    "addr:street":"Nostrand Avenue",
    "iso:country":"US",
    "sg:address":"806 Nostrand Avenue",
    "sg:city":"Brooklyn",
    "sg:classifiers":[
        {
            "category":"Restaurant",
            "type":"Food & Drink"
        }
    ],
    "sg:phone":"+1 718 771 8933",
    "sg:postcode":"11216",
    "sg:province":"NY",
    "sg:tags":[
        "caribbean"
    ],
    "wof:name":"Cocks Restaurant",
    "wof:placetype":"venue"
},
  "geometry": {"coordinates":[-73.95051100000001,40.671252],"type":"Point"}
}