{
  "type": "Feature",
  "properties": {
    "addr:full":"4 Mount Sinai Ave Mt Sinai NY 11766",
    "addr:housenumber":"4",
    "addr:postcode":"11766",
    "addr:street":"Mount Sinai Ave",
    "iso:country":"US",
    "sg:address":"4 Mount Sinai Ave",
    "sg:city":"Mt Sinai",
    "sg:classifiers":[
        {
            "category":"Building & Trades",
            "subcategory":"Landscaping Services",
            "type":"Services"
        }
    ],
    "sg:phone":"+1 631 928 6360",
    "sg:postcode":"11766",
    "sg:province":"NY",
    "sg:tags":[
        "landscape",
        "contractor"
    ],
    "wof:name":"Cut Above Landscaping",
    "wof:placetype":"venue"
},
  "geometry": {"coordinates":[-73.014442,40.921721],"type":"Point"}
}