{
  "type": "Feature",
  "properties": {
    "iso:country":"US",
    "sg:address":"6 Haviland Ave",
    "sg:city":"South Glens Falls",
    "sg:classifiers":[
        {
            "category":"Building & Trades",
            "subcategory":"Landscaping Services",
            "type":"Services"
        }
    ],
    "sg:phone":"+1 518 792 5156",
    "sg:postcode":"12803",
    "sg:province":"NY",
    "wof:name":"Hadley Harware Lawn & Garden",
    "wof:placetype":"venue"
},
  "geometry": {"coordinates":[-73.62901599999999,43.291967],"type":"Point"}
}