{
  "type": "Feature",
  "properties": {
    "addr:full":"25932 149th Ave Rosedale NY 11422",
    "addr:housenumber":"25932",
    "addr:postcode":"11422",
    "addr:street":"149Th Ave",
    "iso:country":"US",
    "sg:address":"25932 149th Ave",
    "sg:city":"Rosedale",
    "sg:classifiers":[
        {
            "category":"Professional",
            "subcategory":"Detective & Security Services",
            "type":"Services"
        }
    ],
    "sg:phone":"+1 718 723 5863",
    "sg:postcode":"11422",
    "sg:province":"NY",
    "sg:tags":[
        "information",
        "bureau"
    ],
    "wof:name":"Bradley Charter Svc",
    "wof:placetype":"venue"
},
  "geometry": {"coordinates":[-73.72966,40.652869],"type":"Point"}
}