{
  "type": "Feature",
  "properties": {
    "addr:full":"2829 Albemarle Rd Brooklyn NY 11226",
    "addr:housenumber":"2829",
    "addr:postcode":"11226",
    "addr:street":"Albemarle Rd",
    "iso:country":"US",
    "sg:address":"2829 Albemarle Rd",
    "sg:city":"Brooklyn",
    "sg:classifiers":[
        {
            "category":"Freight",
            "type":"Transportation"
        }
    ],
    "sg:phone":"+1   ",
    "sg:postcode":"11226",
    "sg:province":"NY",
    "sg:tags":[
        "local",
        "storage",
        "trucking"
    ],
    "wof:name":"K & G Van Line Co",
    "wof:placetype":"venue"
},
  "geometry": {"coordinates":[-73.95067400000001,40.648157],"type":"Point"}
}