{
  "type": "Feature",
  "properties": {
    "iso:country":"US",
    "sg:address":"803 West St",
    "sg:city":"Stephentown",
    "sg:classifiers":[
        {
            "category":"Building & Trades",
            "subcategory":"Construction",
            "type":"Services"
        }
    ],
    "sg:phone":"+1 518 794 9695",
    "sg:postcode":"12168",
    "sg:province":"NY",
    "sg:tags":[
        "house"
    ],
    "wof:name":"Sharp Builders",
    "wof:placetype":"venue"
},
  "geometry": {"coordinates":[-73.378924,42.507633],"type":"Point"}
}