{
  "type": "Feature",
  "properties": {
    "iso:country":"US",
    "sg:address":"257 State Hwy 446",
    "sg:city":"Cuba",
    "sg:classifiers":[
        {
            "category":"Organizations",
            "subcategory":"Religious Organization",
            "type":"Services"
        }
    ],
    "sg:phone":"+1 716 968 0256",
    "sg:postcode":"14727",
    "sg:province":"NY",
    "sg:tags":[
        "church"
    ],
    "wof:name":"Seventh Heaven Kennels",
    "wof:placetype":"venue"
},
  "geometry": {"coordinates":[-78.32700199999999,42.215659],"type":"Point"}
}