{
  "type": "Feature",
  "properties": {
    "iso:country":"US",
    "sg:address":"41 Queens Blvd",
    "sg:city":"Sunnyside",
    "sg:classifiers":[
        {
            "category":"Restaurant",
            "type":"Food & Drink"
        }
    ],
    "sg:phone":"+1   ",
    "sg:postcode":"11104",
    "sg:province":"NY",
    "sg:tags":[
        "pizzeria"
    ],
    "wof:name":"Giulia Pizzeria & Restrnt Inc",
    "wof:placetype":"venue"
},
  "geometry": {"coordinates":[-73.916703,40.743012],"type":"Point"}
}