{
  "type": "Feature",
  "properties": {
    "addr:full":"135 E 55th Street New York NY 10022",
    "addr:housenumber":"135",
    "addr:postcode":"10022",
    "addr:street":"E 55Th Street",
    "iso:country":"US",
    "sg:address":"135 E 55th Street",
    "sg:city":"New York",
    "sg:classifiers":[
        {
            "category":"Shopping",
            "subcategory":"Clothing, Apparel, & Fashions",
            "type":"Retail Goods"
        }
    ],
    "sg:phone":"+1 212 319 7700",
    "sg:postcode":"10022",
    "sg:province":"NY",
    "sg:tags":[
        "accessory",
        "clothing",
        "women's"
    ],
    "wof:name":"Nina McLemore",
    "wof:placetype":"venue"
},
  "geometry": {"coordinates":[-73.970066,40.759638],"type":"Point"}
}