{
  "type": "Feature",
  "properties": {
    "addr:full":"5703 48th St Maspeth NY 11378",
    "addr:housenumber":"5703",
    "addr:postcode":"11378",
    "addr:street":"48Th St",
    "iso:country":"US",
    "sg:address":"5703 48th St",
    "sg:city":"Maspeth",
    "sg:classifiers":[
        {
            "category":"Food & Beverages",
            "subcategory":"Specialty",
            "type":"Retail Goods"
        }
    ],
    "sg:phone":"+1 718 416 2632",
    "sg:postcode":"11378",
    "sg:province":"NY",
    "sg:tags":[
        "grocers-specialty"
    ],
    "wof:name":"Raja Foods",
    "wof:placetype":"venue"
},
  "geometry": {"coordinates":[-73.918739,40.730921],"type":"Point"}
}