{
  "type": "Feature",
  "properties": {
    "iso:country":"US",
    "sg:address":"57 Armetale Luster",
    "sg:city":"Webster",
    "sg:classifiers":[
        {
            "category":"Building & Trades",
            "subcategory":"Construction",
            "type":"Services"
        }
    ],
    "sg:phone":"+1 585 671 2975",
    "sg:postcode":"14580",
    "sg:province":"NY",
    "sg:tags":[
        "residential"
    ],
    "wof:name":"Viola C Development Corp",
    "wof:placetype":"venue"
},
  "geometry": {"coordinates":[-77.48304899999999,43.19262],"type":"Point"}
}