{
  "type": "Feature",
  "properties": {
    "addr:full":"2081 Brighton Henrietta Town Line Rd Rochester NY 14623",
    "addr:housenumber":"2081",
    "addr:postcode":"14623",
    "addr:street":"Brighton Henrietta Town Line Rd",
    "iso:country":"US",
    "sg:address":"2081 Brighton Henrietta Town Line Rd",
    "sg:city":"Rochester",
    "sg:classifiers":[
        {
            "category":"Building & Trades",
            "subcategory":"Construction",
            "type":"Services"
        }
    ],
    "sg:phone":"+1 585 475 0074",
    "sg:postcode":"14623",
    "sg:province":"NY",
    "sg:tags":[
        "house"
    ],
    "wof:name":"Smails Improvements",
    "wof:placetype":"venue"
},
  "geometry": {"coordinates":[-77.61447099999999,43.094643],"type":"Point"}
}