{
  "type": "Feature",
  "properties": {
    "addr:full":"179 Berry Hill Rd Syosset NY 11791",
    "addr:housenumber":"179",
    "addr:postcode":"11791",
    "addr:street":"Berry Hill Rd",
    "iso:country":"US",
    "sg:address":"179 Berry Hill Rd",
    "sg:city":"Syosset",
    "sg:classifiers":[
        {
            "category":"Wholesale",
            "subcategory":"Electrical",
            "type":"Manufacturing & Wholesale Goods"
        }
    ],
    "sg:phone":"+1 516 496 0264",
    "sg:postcode":"11791",
    "sg:province":"NY",
    "sg:tags":[
        "electronic",
        "business"
    ],
    "wof:name":"AMI Design Enterprises Inc",
    "wof:placetype":"venue"
},
  "geometry": {"coordinates":[-73.50015500000001,40.833338],"type":"Point"}
}