{
  "type": "Feature",
  "properties": {
    "iso:country":"US",
    "sg:address":"141 W 36th Street",
    "sg:city":"New York",
    "sg:classifiers":[
        {
            "category":"Professional",
            "type":"Services"
        }
    ],
    "sg:phone":"+1 917 351 8600",
    "sg:postcode":"10018",
    "sg:province":"NY",
    "sg:website":"www.hs-pr.com/",
    "wof:name":"Harrison & Shriftman",
    "wof:placetype":"venue"
},
  "geometry": {"coordinates":[-73.988439,40.751772],"type":"Point"}
}