{
  "type": "Feature",
  "properties": {
    "addr:full":"1618 E 92nd St Brooklyn NY 11236",
    "addr:housenumber":"1618",
    "addr:postcode":"11236",
    "addr:street":"E 92Nd St",
    "iso:country":"US",
    "sg:address":"1618 E 92nd St",
    "sg:city":"Brooklyn",
    "sg:classifiers":[
        {
            "category":"Shopping",
            "type":"Retail Goods"
        }
    ],
    "sg:phone":"+1   ",
    "sg:postcode":"11236",
    "sg:province":"NY",
    "sg:tags":[
        "merchandise"
    ],
    "wof:name":"My Specialty Shop",
    "wof:placetype":"venue"
},
  "geometry": {"coordinates":[-73.893832,40.631597],"type":"Point"}
}