{
  "type": "Feature",
  "properties": {
    "iso:country":"US",
    "sg:address":"82 Atlantic Ave",
    "sg:city":"Lynbrook",
    "sg:classifiers":[
        {
            "category":"Retail",
            "subcategory":"Laundry & Dry Cleaning",
            "type":"Services"
        }
    ],
    "sg:phone":"+1 516 887 0925",
    "sg:postcode":"11563",
    "sg:province":"NY",
    "sg:tags":[
        "cleaners"
    ],
    "wof:name":"Lincoln Cleaners",
    "wof:placetype":"venue"
},
  "geometry": {"coordinates":[-73.671708,40.654831],"type":"Point"}
}