{
  "type": "Feature",
  "properties": {
    "iso:country":"US",
    "sg:address":"160 W 47 St",
    "sg:city":"New York",
    "sg:classifiers":[
        {
            "category":"Retail",
            "subcategory":"Auto Repair",
            "type":"Services"
        }
    ],
    "sg:phone":"+1 212 937 1196",
    "sg:postcode":"10036",
    "sg:province":"NY",
    "sg:tags":[
        "wrecker"
    ],
    "wof:name":"ABC Towing",
    "wof:placetype":"venue"
},
  "geometry": {"coordinates":[-73.983355,40.758415],"type":"Point"}
}