{
  "type": "Feature",
  "properties": {
    "iso:country":"US",
    "sg:address":"189 7th Ave",
    "sg:city":"New York",
    "sg:classifiers":[
        {
            "category":"Home & Garden",
            "subcategory":"Hardware",
            "type":"Retail Goods"
        }
    ],
    "sg:phone":"+1 212 929 4558",
    "sg:postcode":"10011",
    "sg:province":"NY",
    "sg:tags":[
        "store"
    ],
    "wof:name":"Kove Bros",
    "wof:placetype":"venue"
},
  "geometry": {"coordinates":[-73.996061,40.742786],"type":"Point"}
}