{
  "type": "Feature",
  "properties": {
    "addr:full":"10833 65th Avenue Forest Hills NY 11375",
    "addr:housenumber":"10833",
    "addr:postcode":"11375",
    "addr:street":"65Th Avenue",
    "iso:country":"US",
    "sg:address":"10833 65th Avenue",
    "sg:city":"Forest Hills",
    "sg:classifiers":[
        {
            "category":"Building & Trades",
            "subcategory":"Construction",
            "type":"Services"
        }
    ],
    "sg:phone":"+1 718 897 7089",
    "sg:postcode":"11375",
    "sg:province":"NY",
    "sg:tags":[
        "contractor"
    ],
    "wof:name":"Marsibilio Incorporated",
    "wof:placetype":"venue"
},
  "geometry": {"coordinates":[-73.847843,40.732043],"type":"Point"}
}