{
  "type": "Feature",
  "properties": {
    "iso:country":"US",
    "sg:address":"3262 US Route 9W",
    "sg:city":"New Windsor",
    "sg:classifiers":[
        {
            "category":"Autos & Motor Vehicles",
            "subcategory":"Automobile Sales",
            "type":"Retail Goods"
        }
    ],
    "sg:phone":"+1 845 561 4449",
    "sg:postcode":"12553",
    "sg:province":"NY",
    "sg:tags":[
        "car"
    ],
    "wof:name":"Toyota II",
    "wof:placetype":"venue"
},
  "geometry": {"coordinates":[-74.018303,41.487301],"type":"Point"}
}