{
  "type": "Feature",
  "properties": {
    "addr:full":"29 Simmons St Rochester NY 14606",
    "addr:housenumber":"29",
    "addr:postcode":"14606",
    "addr:street":"Simmons St",
    "iso:country":"US",
    "sg:address":"29 Simmons St",
    "sg:city":"Rochester",
    "sg:classifiers":[
        {
            "category":"Building & Trades",
            "subcategory":"Landscaping Services",
            "type":"Services"
        }
    ],
    "sg:phone":"+1 585 429 6137",
    "sg:postcode":"14606",
    "sg:province":"NY",
    "wof:name":"Daniel P Hochreiter",
    "wof:placetype":"venue"
},
  "geometry": {"coordinates":[-77.693397,43.158659],"type":"Point"}
}