{
  "type": "Feature",
  "properties": {
    "iso:country":"US",
    "sg:address":"14 E 37th St",
    "sg:city":"New York",
    "sg:classifiers":[
        {
            "category":"Shopping",
            "type":"Retail Goods"
        }
    ],
    "sg:phone":"+1 212 532 3600",
    "sg:postcode":"10016",
    "sg:province":"NY",
    "sg:tags":[
        "stationery",
        "art",
        "store",
        "supply"
    ],
    "wof:name":"Irving Berlin Inc",
    "wof:placetype":"venue"
},
  "geometry": {"coordinates":[-73.982337,40.750007],"type":"Point"}
}