{
  "type": "Feature",
  "properties": {
    "iso:country":"US",
    "sg:address":"908 Willoughby Ave",
    "sg:city":"Brooklyn",
    "sg:classifiers":[
        {
            "category":"Professional",
            "subcategory":"Management & Consulting",
            "type":"Services"
        }
    ],
    "sg:phone":"+1 718 452 3449",
    "sg:postcode":"11221",
    "sg:province":"NY",
    "sg:tags":[
        "financial"
    ],
    "wof:name":"Beharrys General Business Svcs",
    "wof:placetype":"venue"
},
  "geometry": {"coordinates":[-73.932303,40.696339],"type":"Point"}
}