{
  "type": "Feature",
  "properties": {
    "iso:country":"US",
    "sg:address":"26 Finley St",
    "sg:city":"Saratoga Springs",
    "sg:classifiers":[
        {
            "category":"Retail",
            "subcategory":"Car Wash",
            "type":"Services"
        }
    ],
    "sg:phone":"+1 518 581 1488",
    "sg:postcode":"12866",
    "sg:province":"NY",
    "sg:tags":[
        "carwash",
        "automobile",
        "detail",
        "clean"
    ],
    "wof:name":"Saratoga Honda Prep Center",
    "wof:placetype":"venue"
},
  "geometry": {"coordinates":[-73.790958,43.071312],"type":"Point"}
}