{
  "type": "Feature",
  "properties": {
    "iso:country":"US",
    "sg:address":"130 N Carll Ave",
    "sg:city":"Babylon",
    "sg:classifiers":[
        {
            "category":"Health Services",
            "subcategory":"Chiropractor",
            "type":"Services"
        }
    ],
    "sg:phone":"+1   ",
    "sg:postcode":"11702",
    "sg:province":"NY",
    "wof:name":"Babylon Care Providers",
    "wof:placetype":"venue"
},
  "geometry": {"coordinates":[-73.32594400000001,40.700712],"type":"Point"}
}