{
  "type": "Feature",
  "properties": {
    "addr:full":"1 Brandywine Dr Deer Park NY 11729",
    "addr:housenumber":"1",
    "addr:postcode":"11729",
    "addr:street":"Brandywine Dr",
    "iso:country":"US",
    "sg:address":"1 Brandywine Dr",
    "sg:city":"Deer Park",
    "sg:classifiers":[
        {
            "category":"Health Services",
            "subcategory":"Clinic",
            "type":"Services"
        }
    ],
    "sg:phone":"+1 631 254 0523",
    "sg:postcode":"11729",
    "sg:province":"NY",
    "sg:tags":[
        "specialty",
        "outpatient"
    ],
    "wof:name":"Sirri LLC",
    "wof:placetype":"venue"
},
  "geometry": {"coordinates":[-73.309637,40.761317],"type":"Point"}
}