{
  "type": "Feature",
  "properties": {
    "addr:full":"492 20th St Niagara Falls NY 14303",
    "addr:housenumber":"492",
    "addr:postcode":"14303",
    "addr:street":"20Th St",
    "iso:country":"US",
    "sg:address":"492 20th St",
    "sg:city":"Niagara Falls",
    "sg:classifiers":[
        {
            "category":"Personal",
            "subcategory":"Beauty Salon",
            "type":"Services"
        }
    ],
    "sg:phone":"+1 716 284 3439",
    "sg:postcode":"14303",
    "sg:province":"NY",
    "wof:name":"Angie's Hairstyling Shop",
    "wof:placetype":"venue"
},
  "geometry": {"coordinates":[-79.037662,43.088553],"type":"Point"}
}