{
  "type": "Feature",
  "properties": {
    "addr:full":"34 Breton Way Fort Edward NY 12828",
    "addr:housenumber":"34",
    "addr:postcode":"12828",
    "addr:street":"Breton Way",
    "iso:country":"US",
    "sg:address":"34 Breton Way",
    "sg:city":"Fort Edward",
    "sg:classifiers":[
        {
            "category":"Shopping",
            "subcategory":"Gifts & Souvenirs",
            "type":"Retail Goods"
        }
    ],
    "sg:phone":"+1 518 747 2885",
    "sg:postcode":"12828",
    "sg:province":"NY",
    "sg:tags":[
        "shop"
    ],
    "wof:name":"Adirondack Gift Shop",
    "wof:placetype":"venue"
},
  "geometry": {"coordinates":[-73.594785,43.242937],"type":"Point"}
}