{
  "type": "Feature",
  "properties": {
    "iso:country":"US",
    "sg:address":"711 Central Park Ave",
    "sg:city":"Scarsdale",
    "sg:classifiers":[
        {
            "category":"Government",
            "subcategory":"Fire Station",
            "type":"Public Place"
        }
    ],
    "sg:phone":"+1 914 723 2500",
    "sg:postcode":"10583",
    "sg:province":"NY",
    "sg:tags":[
        "consultant",
        "protection"
    ],
    "wof:name":"Fire Departments",
    "wof:placetype":"venue"
},
  "geometry": {"coordinates":[-73.816416,40.998168],"type":"Point"}
}