{
  "type": "Feature",
  "properties": {
    "addr:full":"17 Lafayette Ave Staten Island NY 10301",
    "addr:housenumber":"17",
    "addr:postcode":"10301",
    "addr:street":"Lafayette Ave",
    "iso:country":"US",
    "sg:address":"17 Lafayette Ave",
    "sg:city":"Staten Island",
    "sg:classifiers":[
        {
            "category":"Retail",
            "subcategory":"Car Wash",
            "type":"Services"
        }
    ],
    "sg:phone":"+1   ",
    "sg:postcode":"10301",
    "sg:province":"NY",
    "sg:tags":[
        "carwash"
    ],
    "wof:name":"Before & After Auto Detailing",
    "wof:placetype":"venue"
},
  "geometry": {"coordinates":[-74.095795,40.644594],"type":"Point"}
}