{
  "type": "Feature",
  "properties": {
    "addr:full":"502 McDonald Ave Brooklyn NY 11218",
    "addr:housenumber":"502",
    "addr:postcode":"11218",
    "addr:street":"Mcdonald Ave",
    "iso:country":"US",
    "sg:address":"502 McDonald Ave",
    "sg:city":"Brooklyn",
    "sg:classifiers":[
        {
            "category":"Personal",
            "subcategory":"Beauty Salon",
            "type":"Services"
        }
    ],
    "sg:phone":"+1   ",
    "sg:postcode":"11218",
    "sg:province":"NY",
    "sg:tags":[
        "shop"
    ],
    "wof:name":"Tahmima Hair Salon",
    "wof:placetype":"venue"
},
  "geometry": {"coordinates":[-73.979247,40.641548],"type":"Point"}
}