{
  "type": "Feature",
  "properties": {
    "addr:full":"5 Duncliff Ct Albany NY 12205",
    "addr:housenumber":"5",
    "addr:postcode":"12205",
    "addr:street":"Duncliff Ct",
    "iso:country":"US",
    "sg:address":"5 Duncliff Ct",
    "sg:city":"Albany",
    "sg:classifiers":[
        {
            "category":"Utilities",
            "subcategory":"Telephone",
            "type":"Services"
        }
    ],
    "sg:phone":"+1   ",
    "sg:postcode":"12205",
    "sg:province":"NY",
    "sg:tags":[
        "communications"
    ],
    "wof:name":"CM Solutions",
    "wof:placetype":"venue"
},
  "geometry": {"coordinates":[-73.802251,42.708719],"type":"Point"}
}