{
  "type": "Feature",
  "properties": {
    "addr:full":"1026 New York Ave Huntington Station NY 11746",
    "addr:housenumber":"1026",
    "addr:postcode":"11746",
    "addr:street":"New York Ave Huntington",
    "iso:country":"US",
    "sg:address":"1026 New York Ave",
    "sg:city":"Huntington Station",
    "sg:classifiers":[
        {
            "category":"Restaurant",
            "type":"Food & Drink"
        }
    ],
    "sg:phone":"+1 631 683 4224",
    "sg:postcode":"11746",
    "sg:province":"NY",
    "sg:tags":[
        "american",
        "latin"
    ],
    "wof:name":"El Picacho Catracho",
    "wof:placetype":"venue"
},
  "geometry": {"coordinates":[-73.412131,40.857265],"type":"Point"}
}