{
  "type": "Feature",
  "properties": {
    "iso:country":"US",
    "sg:address":"147 Ashdown Rd",
    "sg:city":"Ballston Lake",
    "sg:classifiers":[
        {
            "category":"Building & Trades",
            "subcategory":"Landscaping Services",
            "type":"Services"
        }
    ],
    "sg:phone":"+1 518 399 8733",
    "sg:postcode":"12019",
    "sg:province":"NY",
    "sg:tags":[
        "tree"
    ],
    "sg:website":"www.wardbrotherstreeservice.com/",
    "wof:name":"Ward Brothers Tree Service",
    "wof:placetype":"venue"
},
  "geometry": {"coordinates":[-73.867833,42.899223],"type":"Point"}
}