{
  "type": "Feature",
  "properties": {
    "addr:full":"229 Sullivan Ave Farmingdale NY 11735",
    "addr:housenumber":"229",
    "addr:postcode":"11735",
    "addr:street":"Sullivan Ave",
    "iso:country":"US",
    "sg:address":"229 Sullivan Ave",
    "sg:city":"Farmingdale",
    "sg:classifiers":[
        {
            "category":"Wholesale",
            "subcategory":"Hardware",
            "type":"Manufacturing & Wholesale Goods"
        }
    ],
    "sg:phone":"+1 516 454 8667",
    "sg:postcode":"11735",
    "sg:province":"NY",
    "wof:name":"Snap-On Tools",
    "wof:placetype":"venue"
},
  "geometry": {"coordinates":[-73.455867,40.719522],"type":"Point"}
}