{
  "type": "Feature",
  "properties": {
    "addr:full":"57 Herkimer Rd Scarsdale NY 10583",
    "addr:housenumber":"57",
    "addr:postcode":"10583",
    "addr:street":"Herkimer Rd",
    "iso:country":"US",
    "sg:address":"57 Herkimer Rd",
    "sg:city":"Scarsdale",
    "sg:classifiers":[
        {
            "category":"Real Estate",
            "subcategory":"Real Estate Agent",
            "type":"Services"
        }
    ],
    "sg:phone":"+1 718 638 0127",
    "sg:postcode":"10583",
    "sg:province":"NY",
    "wof:name":"JMP Properties",
    "wof:placetype":"venue"
},
  "geometry": {"coordinates":[-73.76651699999999,40.969826],"type":"Point"}
}