{
  "type": "Feature",
  "properties": {
    "addr:full":"133 E 4 St New York NY 10003",
    "addr:housenumber":"133;4",
    "addr:postcode":"10003",
    "addr:street":"E",
    "iso:country":"US",
    "sg:address":"133 E 4 St",
    "sg:city":"New York",
    "sg:classifiers":[
        {
            "category":"Retail",
            "subcategory":"Repair Shop",
            "type":"Services"
        }
    ],
    "sg:phone":"+1 917 546 1582",
    "sg:postcode":"10003",
    "sg:province":"NY",
    "sg:tags":[
        "lock",
        "locksmith"
    ],
    "wof:name":"Emergency 7 Day Locksmith",
    "wof:placetype":"venue"
},
  "geometry": {"coordinates":[-73.98859299999999,40.726131],"type":"Point"}
}