{
  "type": "Feature",
  "properties": {
    "addr:full":"645 Yale Station Rd Geneva NY 14456",
    "addr:housenumber":"645",
    "addr:postcode":"14456",
    "addr:street":"Yale Station Rd",
    "iso:country":"US",
    "sg:address":"645 Yale Station Rd",
    "sg:city":"Geneva",
    "sg:phone":"+1 315 585 9502",
    "sg:postcode":"14456",
    "sg:province":"NY",
    "sg:tags":[
        "oil"
    ],
    "wof:name":"Ams Oil",
    "wof:placetype":"venue"
},
  "geometry": {"coordinates":[-76.932107,42.805165],"type":"Point"}
}