{
  "type": "Feature",
  "properties": {
    "addr:full":"382 McDonald Ave Brooklyn NY 11218",
    "addr:housenumber":"382",
    "addr:postcode":"11218",
    "addr:street":"Mcdonald Ave",
    "iso:country":"US",
    "sg:address":"382 McDonald Ave",
    "sg:city":"Brooklyn",
    "sg:classifiers":[
        {
            "category":"Banks & Credit Unions",
            "subcategory":"Bank",
            "type":"Services"
        }
    ],
    "sg:phone":"+1 718 436 5247",
    "sg:postcode":"11218",
    "sg:province":"NY",
    "sg:tags":[
        "machine",
        "teller",
        "automated"
    ],
    "wof:name":"ATM Ctr Inc",
    "wof:placetype":"venue"
},
  "geometry": {"coordinates":[-73.979561,40.643103],"type":"Point"}
}