{
  "type": "Feature",
  "properties": {
    "addr:full":"18 E 41st St Rm 1703 New York NY 10017",
    "addr:housenumber":"18",
    "addr:postcode":"1703;10017",
    "addr:street":"E 41St St",
    "iso:country":"US",
    "sg:address":"18 E 41st St Rm 1703",
    "sg:city":"New York",
    "sg:classifiers":[
        {
            "category":"Professional",
            "subcategory":"Employment Agencies",
            "type":"Services"
        }
    ],
    "sg:phone":"+1 212 986 2102",
    "sg:postcode":"10017",
    "sg:province":"NY",
    "wof:name":"Domestic Job Picks",
    "wof:placetype":"venue"
},
  "geometry": {"coordinates":[-73.980452,40.752275],"type":"Point"}
}