{
  "type": "Feature",
  "properties": {
    "iso:country":"US",
    "sg:address":"393 Brook Ave",
    "sg:city":"Bay Shore",
    "sg:classifiers":[
        {
            "category":"Education",
            "subcategory":"School",
            "type":"Public Place"
        }
    ],
    "sg:phone":"+1 631 968 1210",
    "sg:postcode":"11706",
    "sg:province":"NY",
    "wof:name":"Bay Shore Middle School",
    "wof:placetype":"venue"
},
  "geometry": {"coordinates":[-73.255876,40.739335],"type":"Point"}
}