{
  "type": "Feature",
  "properties": {
    "addr:full":"31 W Main St Patchogue NY 11772",
    "addr:housenumber":"31",
    "addr:postcode":"11772",
    "addr:street":"W Main St",
    "iso:country":"US",
    "sg:address":"31 W Main St",
    "sg:city":"Patchogue",
    "sg:classifiers":[
        {
            "category":"Professional",
            "subcategory":"Lawyer & Legal Services",
            "type":"Services"
        }
    ],
    "sg:phone":"+1 631 447 1200",
    "sg:postcode":"11772",
    "sg:province":"NY",
    "wof:name":"Russo & Gajdos LLP",
    "wof:placetype":"venue"
},
  "geometry": {"coordinates":[-73.586073,40.765863],"type":"Point"}
}