{
  "type": "Feature",
  "properties": {
    "iso:country":"US",
    "sg:address":"840 Spencer Rd",
    "sg:city":"Woodstock",
    "sg:classifiers":[
        {
            "category":"Manufacturing",
            "subcategory":"Glass & Minerals",
            "type":"Manufacturing & Wholesale Goods"
        }
    ],
    "sg:phone":"+1   ",
    "sg:postcode":"12433",
    "sg:province":"NY",
    "sg:tags":[
        "mfr",
        "stained"
    ],
    "wof:name":"Cary Roton Studio",
    "wof:placetype":"venue"
},
  "geometry": {"coordinates":[-74.128384,42.01064],"type":"Point"}
}