{
  "type": "Feature",
  "properties": {
    "addr:full":"13 Crosby St New York NY 10013",
    "addr:housenumber":"13",
    "addr:postcode":"10013",
    "addr:street":"Crosby St",
    "iso:country":"US",
    "sg:address":"13 Crosby St",
    "sg:city":"New York",
    "sg:classifiers":[
        {
            "category":"Professional",
            "type":"Services"
        }
    ],
    "sg:phone":"+1 212 226 3670",
    "sg:postcode":"10013",
    "sg:province":"NY",
    "sg:tags":[
        "establishment"
    ],
    "wof:name":"Nakaoka Design Group",
    "wof:placetype":"venue"
},
  "geometry": {"coordinates":[-74.000147,40.719864],"type":"Point"}
}