{
  "type": "Feature",
  "properties": {
    "addr:full":"1847 Victory Boulevard Staten Island NY 10314",
    "addr:housenumber":"1847",
    "addr:postcode":"10314",
    "addr:street":"Victory Boulevard",
    "iso:country":"US",
    "sg:address":"1847 Victory Boulevard",
    "sg:city":"Staten Island",
    "sg:classifiers":[
        {
            "category":"Building & Trades",
            "subcategory":"Construction",
            "type":"Services"
        }
    ],
    "sg:phone":"+1 718 987 5435",
    "sg:postcode":"10314",
    "sg:province":"NY",
    "sg:tags":[
        "contractor"
    ],
    "wof:name":"Craft Master Home Improvement Corporation",
    "wof:placetype":"venue"
},
  "geometry": {"coordinates":[-74.125111,40.61292],"type":"Point"}
}