{
  "type": "Feature",
  "properties": {
    "iso:country":"US",
    "sg:address":"51 Clifton Pl",
    "sg:city":"Port Jefferson Station",
    "sg:classifiers":[
        {
            "category":"Real Estate",
            "subcategory":"Real Estate Agent",
            "type":"Services"
        }
    ],
    "sg:phone":"+1 631 872 4987",
    "sg:postcode":"11776",
    "sg:province":"NY",
    "wof:name":"Anjum Malik",
    "wof:placetype":"venue"
},
  "geometry": {"coordinates":[-73.054683,40.928118],"type":"Point"}
}