{
  "type": "Feature",
  "properties": {
    "iso:country":"US",
    "sg:address":"94 Ridgecrest Rd",
    "sg:city":"Lake Peekskill",
    "sg:classifiers":[
        {
            "category":"Building & Trades",
            "subcategory":"Construction",
            "type":"Services"
        }
    ],
    "sg:phone":"+1 845 526 3356",
    "sg:postcode":"10537",
    "sg:province":"NY",
    "sg:tags":[
        "house"
    ],
    "wof:name":"Pls Construction",
    "wof:placetype":"venue"
},
  "geometry": {"coordinates":[-73.888608,41.345311],"type":"Point"}
}