{
  "type": "Feature",
  "properties": {
    "addr:full":"101 28th Ave Brooklyn NY 11214",
    "addr:housenumber":"101",
    "addr:postcode":"11214",
    "addr:street":"28Th Ave",
    "iso:country":"US",
    "sg:address":"101 28th Ave",
    "sg:city":"Brooklyn",
    "sg:classifiers":[
        {
            "category":"Wholesale",
            "subcategory":"Construction Materials",
            "type":"Manufacturing & Wholesale Goods"
        }
    ],
    "sg:phone":"+1 718 372 8202",
    "sg:postcode":"11214",
    "sg:province":"NY",
    "sg:tags":[
        "glass"
    ],
    "wof:name":"Shattered Glass Inc",
    "wof:placetype":"venue"
},
  "geometry": {"coordinates":[-73.98803100000001,40.586757],"type":"Point"}
}