{
  "type": "Feature",
  "properties": {
    "addr:full":"20 Club Pointe Dr White Plains NY 10605",
    "addr:housenumber":"20",
    "addr:postcode":"10605",
    "addr:street":"Club Pointe Dr",
    "iso:country":"US",
    "sg:address":"20 Club Pointe Dr",
    "sg:city":"White Plains",
    "sg:classifiers":[
        {
            "category":"Professional",
            "subcategory":"Advertising",
            "type":"Services"
        }
    ],
    "sg:phone":"+1 914 682 8032",
    "sg:postcode":"10605",
    "sg:province":"NY",
    "sg:tags":[
        "agency"
    ],
    "wof:name":"Breakstone & Assocs",
    "wof:placetype":"venue"
},
  "geometry": {"coordinates":[-73.736346,41.010356],"type":"Point"}
}