{
  "type": "Feature",
  "properties": {
    "iso:country":"US",
    "sg:address":"1800 Chili Scottsville Rd",
    "sg:city":"Scottsville",
    "sg:classifiers":[
        {
            "category":"Social Services",
            "type":"Services"
        }
    ],
    "sg:phone":"+1 585 889 1810",
    "sg:postcode":"14546",
    "sg:province":"NY",
    "sg:tags":[
        "youth",
        "organization",
        "center"
    ],
    "wof:name":"Monroe County Youth Hockey Inc",
    "wof:placetype":"venue"
},
  "geometry": {"coordinates":[-77.77281499999999,43.033732],"type":"Point"}
}