{
  "type": "Feature",
  "properties": {
    "iso:country":"US",
    "sg:address":"124 W Main St",
    "sg:city":"Endicott",
    "sg:classifiers":[
        {
            "category":"Organizations",
            "subcategory":"Community Association",
            "type":"Services"
        }
    ],
    "sg:phone":"+1 607 757 9136",
    "sg:postcode":"13760",
    "sg:province":"NY",
    "sg:tags":[
        "club"
    ],
    "wof:name":"Lions Clubs-The Triple Cities",
    "wof:placetype":"venue"
},
  "geometry": {"coordinates":[-76.066827,42.095089],"type":"Point"}
}