{
  "type": "Feature",
  "properties": {
    "iso:country":"US",
    "sg:address":"1411 Hanover St",
    "sg:city":"Yorktown Heights",
    "sg:classifiers":[
        {
            "category":"Professional",
            "type":"Services"
        }
    ],
    "sg:phone":"+1   ",
    "sg:postcode":"10598",
    "sg:province":"NY",
    "wof:name":"Lou CAM Inc",
    "wof:placetype":"venue"
},
  "geometry": {"coordinates":[-73.772295,41.254484],"type":"Point"}
}