{
  "type": "Feature",
  "properties": {
    "addr:full":"291 Broadway Rm 806 New York NY 10007",
    "addr:housenumber":"291;806",
    "addr:postcode":"10007",
    "addr:street":"Broadway Rm",
    "iso:country":"US",
    "sg:address":"291 Broadway Rm 806",
    "sg:city":"New York",
    "sg:classifiers":[
        {
            "category":"Building & Trades",
            "subcategory":"Construction",
            "type":"Services"
        }
    ],
    "sg:phone":"+1 212 964 0964",
    "sg:postcode":"10007",
    "sg:province":"NY",
    "sg:tags":[
        "contractor"
    ],
    "wof:name":"Enotria",
    "wof:placetype":"venue"
},
  "geometry": {"coordinates":[-74.04877999999999,40.714797],"type":"Point"}
}