{
  "type": "Feature",
  "properties": {
    "iso:country":"US",
    "sg:address":"2 Middle Country Rd",
    "sg:city":"Middle Island",
    "sg:classifiers":[
        {
            "category":"Restaurant",
            "type":"Food & Drink"
        }
    ],
    "sg:phone":"+1 631 736 3813",
    "sg:postcode":"11953",
    "sg:province":"NY",
    "wof:name":"Garlic Patch At Anjelejo's",
    "wof:placetype":"venue"
},
  "geometry": {"coordinates":[-72.973274,40.87616],"type":"Point"}
}