{
  "type": "Feature",
  "properties": {
    "addr:full":"247 E 78th Street New York NY 10021",
    "addr:housenumber":"247",
    "addr:postcode":"10021",
    "addr:street":"E 78Th Street",
    "iso:country":"US",
    "sg:address":"247 E 78th Street",
    "sg:city":"New York",
    "sg:classifiers":[
        {
            "category":"Retail",
            "subcategory":"Laundry & Dry Cleaning",
            "type":"Services"
        }
    ],
    "sg:phone":"+1 212 879 9432",
    "sg:postcode":"10021",
    "sg:province":"NY",
    "wof:name":"Dragon Tailor Cleaners",
    "wof:placetype":"venue"
},
  "geometry": {"coordinates":[-73.956591,40.773209],"type":"Point"}
}