{
  "type": "Feature",
  "properties": {
    "iso:country":"US",
    "sg:address":"7 Dickel Rd",
    "sg:city":"Scarsdale",
    "sg:classifiers":[
        {
            "category":"Professional",
            "subcategory":"Management & Consulting",
            "type":"Services"
        }
    ],
    "sg:phone":"+1 914 723 3288",
    "sg:postcode":"10583",
    "sg:province":"NY",
    "wof:name":"Willow Management Corp",
    "wof:placetype":"venue"
},
  "geometry": {"coordinates":[-73.776462,41.012443],"type":"Point"}
}