{
  "type": "Feature",
  "properties": {
    "iso:country":"US",
    "sg:address":"936 Woodycrest Ave",
    "sg:city":"Bronx",
    "sg:classifiers":[
        {
            "category":"Health Services",
            "subcategory":"Medical Lab",
            "type":"Services"
        }
    ],
    "sg:phone":"+1 718 681 4759",
    "sg:postcode":"10452",
    "sg:province":"NY",
    "sg:tags":[
        "laboratory"
    ],
    "wof:name":"Sutton Medical Labs",
    "wof:placetype":"venue"
},
  "geometry": {"coordinates":[-73.92923399999999,40.830797],"type":"Point"}
}