{
  "type": "Feature",
  "properties": {
    "addr:full":"26 Century Hill Dr Latham NY 12110",
    "addr:housenumber":"26",
    "addr:postcode":"12110",
    "addr:street":"Century Hill Dr",
    "iso:country":"US",
    "sg:address":"26 Century Hill Dr",
    "sg:city":"Latham",
    "sg:classifiers":[
        {
            "category":"Insurance",
            "subcategory":"Life Insurance",
            "type":"Services"
        }
    ],
    "sg:phone":"+1 518 220 4200",
    "sg:postcode":"12110",
    "sg:province":"NY",
    "sg:tags":[
        "carrier"
    ],
    "wof:name":"New York Life",
    "wof:placetype":"venue"
},
  "geometry": {"coordinates":[-73.75798899999999,42.771387],"type":"Point"}
}