{
  "type": "Feature",
  "properties": {
    "addr:full":"11117 Roosevelt Avenue Corona NY 11368",
    "addr:housenumber":"11117",
    "addr:postcode":"11368",
    "addr:street":"Roosevelt Avenue",
    "iso:country":"US",
    "sg:address":"11117 Roosevelt Avenue",
    "sg:city":"Corona",
    "sg:classifiers":[
        {
            "category":"Restaurant",
            "type":"Food & Drink"
        }
    ],
    "sg:phone":"+1 718 803 8408",
    "sg:postcode":"11368",
    "sg:province":"NY",
    "sg:tags":[
        "pizza"
    ],
    "wof:name":"Victoria's Pizzeria Restaurante",
    "wof:placetype":"venue"
},
  "geometry": {"coordinates":[-73.855282,40.751856],"type":"Point"}
}