{
  "type": "Feature",
  "properties": {
    "iso:country":"US",
    "sg:address":"9337 150th Street",
    "sg:city":"Jamaica",
    "sg:classifiers":[
        {
            "category":"Home & Garden",
            "subcategory":"Furniture",
            "type":"Retail Goods"
        }
    ],
    "sg:phone":"+1 718 658 0193",
    "sg:postcode":"11435",
    "sg:province":"NY",
    "sg:tags":[
        "store"
    ],
    "wof:name":"Novel Kitchens",
    "wof:placetype":"venue"
},
  "geometry": {"coordinates":[-73.803535,40.700572],"type":"Point"}
}