{
  "type": "Feature",
  "properties": {
    "addr:full":"59 Millay Ln Bay Shore NY 11706",
    "addr:housenumber":"59",
    "addr:postcode":"11706",
    "addr:street":"Millay Ln",
    "iso:country":"US",
    "sg:address":"59 Millay Ln",
    "sg:city":"Bay Shore",
    "sg:classifiers":[
        {
            "category":"Retail",
            "subcategory":"Auto Repair",
            "type":"Services"
        }
    ],
    "sg:phone":"+1   ",
    "sg:postcode":"11706",
    "sg:province":"NY",
    "sg:tags":[
        "body"
    ],
    "wof:name":"Greens Collision",
    "wof:placetype":"venue"
},
  "geometry": {"coordinates":[-73.253871,40.746603],"type":"Point"}
}