{
  "type": "Feature",
  "properties": {
    "iso:country":"US",
    "sg:address":"247 Cayuga Rd",
    "sg:city":"Buffalo",
    "sg:classifiers":[
        {
            "category":"Professional",
            "subcategory":"Computer Services",
            "type":"Services"
        }
    ],
    "sg:phone":"+1 716 855 0535",
    "sg:postcode":"14225",
    "sg:province":"NY",
    "sg:tags":[
        "information",
        "retrieval"
    ],
    "wof:name":"Advancenet Corporation",
    "wof:placetype":"venue"
},
  "geometry": {"coordinates":[-78.744371,42.941441],"type":"Point"}
}