{
  "type": "Feature",
  "properties": {
    "addr:full":"106 E Green St Dunkirk NY 14048",
    "addr:housenumber":"106",
    "addr:postcode":"14048",
    "addr:street":"E Green St",
    "iso:country":"US",
    "sg:address":"106 E Green St",
    "sg:city":"Dunkirk",
    "sg:classifiers":[
        {
            "category":"Farming",
            "subcategory":"Nursery",
            "type":"Manufacturing & Wholesale Goods"
        }
    ],
    "sg:phone":"+1 716 366 7520",
    "sg:postcode":"14048",
    "sg:province":"NY",
    "sg:tags":[
        "florist",
        "ornamental"
    ],
    "wof:name":"De Golier Florist & Greenhouse",
    "wof:placetype":"venue"
},
  "geometry": {"coordinates":[-79.327392,42.466245],"type":"Point"}
}