{
  "type": "Feature",
  "properties": {
    "addr:full":"7732 Black Creek Rd Kirkville NY 13082",
    "addr:housenumber":"7732",
    "addr:postcode":"13082",
    "addr:street":"Black Creek Rd",
    "iso:country":"US",
    "sg:address":"7732 Black Creek Rd",
    "sg:city":"Kirkville",
    "sg:classifiers":[
        {
            "category":"Farming",
            "subcategory":"Livestock Farm",
            "type":"Manufacturing & Wholesale Goods"
        }
    ],
    "sg:phone":"+1 315 687 6893",
    "sg:postcode":"13082",
    "sg:province":"NY",
    "sg:tags":[
        "specialty",
        "animal"
    ],
    "wof:name":"Black Creek Beekeepers",
    "wof:placetype":"venue"
},
  "geometry": {"coordinates":[-75.89970599999999,43.095876],"type":"Point"}
}