{
  "type": "Feature",
  "properties": {
    "addr:full":"28 Mott St New York NY 10013",
    "addr:housenumber":"28",
    "addr:postcode":"10013",
    "addr:street":"Mott St",
    "iso:country":"US",
    "sg:address":"28 Mott St",
    "sg:city":"New York",
    "sg:classifiers":[
        {
            "category":"Banks & Credit Unions",
            "subcategory":"Financial Services",
            "type":"Services"
        }
    ],
    "sg:phone":"+1 212 693 0081",
    "sg:postcode":"10013",
    "sg:province":"NY",
    "sg:tags":[
        "international",
        "trade"
    ],
    "wof:name":"Chung Kong Trading Inc",
    "wof:placetype":"venue"
},
  "geometry": {"coordinates":[-73.99878200000001,40.71492],"type":"Point"}
}