{
  "type": "Feature",
  "properties": {
    "addr:full":"89 South St New York NY 10038",
    "addr:housenumber":"89",
    "addr:postcode":"10038",
    "addr:street":"South St",
    "iso:country":"US",
    "sg:address":"89 South St",
    "sg:city":"New York",
    "sg:classifiers":[
        {
            "category":"Professional",
            "subcategory":"Business Services",
            "type":"Services"
        }
    ],
    "sg:phone":"+1 212 267 7070",
    "sg:postcode":"10038",
    "sg:province":"NY",
    "sg:tags":[
        "embroidery"
    ],
    "sg:website":"www.abcde-embroidery.com",
    "wof:name":"ABCDE",
    "wof:placetype":"venue"
},
  "geometry": {"coordinates":[-74.003137,40.706247],"type":"Point"}
}