{
  "type": "Feature",
  "properties": {
    "iso:country":"US",
    "sg:address":"150 Squire Dr",
    "sg:city":"Orchard Park",
    "sg:classifiers":[
        {
            "category":"Health Services",
            "subcategory":"Clinic",
            "type":"Services"
        }
    ],
    "sg:phone":"+1 716 667 7289",
    "sg:postcode":"14127",
    "sg:province":"NY",
    "wof:name":"Marvin Herman",
    "wof:placetype":"venue"
},
  "geometry": {"coordinates":[-78.727023,42.742855],"type":"Point"}
}