{
  "type": "Feature",
  "properties": {
    "iso:country":"US",
    "sg:address":"1333 North Ave",
    "sg:city":"New Rochelle",
    "sg:classifiers":[
        {
            "category":"Wholesale",
            "subcategory":"Vending Machines",
            "type":"Manufacturing & Wholesale Goods"
        }
    ],
    "sg:phone":"+1   ",
    "sg:postcode":"10804",
    "sg:province":"NY",
    "sg:tags":[
        "operates"
    ],
    "wof:name":"C C Vending Inc",
    "wof:placetype":"venue"
},
  "geometry": {"coordinates":[-73.79554400000001,40.946621],"type":"Point"}
}