{
  "type": "Feature",
  "properties": {
    "addr:full":"953 Pittsford Mendon Rd Pittsford NY 14534",
    "addr:housenumber":"953",
    "addr:postcode":"14534",
    "addr:street":"Pittsford Mendon Rd",
    "iso:country":"US",
    "sg:address":"953 Pittsford Mendon Rd",
    "sg:city":"Pittsford",
    "sg:classifiers":[
        {
            "category":"Health Services",
            "subcategory":"Doctor",
            "type":"Services"
        }
    ],
    "sg:phone":"+1 585 624 2044",
    "sg:postcode":"14534",
    "sg:province":"NY",
    "sg:tags":[
        "physician",
        "surgeon"
    ],
    "wof:name":"Robert B Young MD",
    "wof:placetype":"venue"
},
  "geometry": {"coordinates":[-77.51558,43.027954],"type":"Point"}
}