{
  "type": "Feature",
  "properties": {
    "iso:country":"US",
    "sg:address":"60 Cedar Ave",
    "sg:city":"Rockville Centre",
    "sg:classifiers":[
        {
            "category":"Professional",
            "subcategory":"Management & Consulting",
            "type":"Services"
        }
    ],
    "sg:phone":"+1 516 256 9355",
    "sg:postcode":"11570",
    "sg:province":"NY",
    "sg:tags":[
        "fuel"
    ],
    "wof:name":"Lanford Hamilton Capital Mgmt",
    "wof:placetype":"venue"
},
  "geometry": {"coordinates":[-73.638473,40.664624],"type":"Point"}
}