{
  "type": "Feature",
  "properties": {
    "iso:country":"US",
    "sg:address":"80 Klinger Ave",
    "sg:city":"Tonawanda",
    "sg:classifiers":[
        {
            "category":"Arts & Performance",
            "subcategory":"Theater",
            "type":"Entertainment"
        }
    ],
    "sg:phone":"+1 716 692 3859",
    "sg:postcode":"14150",
    "sg:province":"NY",
    "sg:tags":[
        "group"
    ],
    "wof:name":"High Note Productions",
    "wof:placetype":"venue"
},
  "geometry": {"coordinates":[-78.888238,43.010176],"type":"Point"}
}