{
  "type": "Feature",
  "properties": {
    "addr:full":"188 Church Ave Germantown NY 12526",
    "addr:housenumber":"188",
    "addr:postcode":"12526",
    "addr:street":"Church Ave",
    "iso:country":"US",
    "sg:address":"188 Church Ave",
    "sg:city":"Germantown",
    "sg:classifiers":[
        {
            "category":"Farming",
            "subcategory":"Farm",
            "type":"Manufacturing & Wholesale Goods"
        }
    ],
    "sg:phone":"+1 518 537 4563",
    "sg:postcode":"12526",
    "sg:province":"NY",
    "wof:name":"Nahlik Farms LLC",
    "wof:placetype":"venue"
},
  "geometry": {"coordinates":[-73.88184800000001,42.124382],"type":"Point"}
}