{
  "type": "Feature",
  "properties": {
    "addr:full":"3924 E Tremont Ave Bronx NY 10465",
    "addr:housenumber":"3924",
    "addr:postcode":"10465",
    "addr:street":"E Tremont Ave",
    "iso:country":"US",
    "sg:address":"3924 E Tremont Ave",
    "sg:city":"Bronx",
    "sg:classifiers":[
        {
            "category":"Building & Trades",
            "subcategory":"Construction",
            "type":"Services"
        }
    ],
    "sg:phone":"+1 718 829 8551",
    "sg:postcode":"10465",
    "sg:province":"NY",
    "sg:tags":[
        "house",
        "industrial",
        "co"
    ],
    "wof:name":"Inner-City Construction MGT",
    "wof:placetype":"venue"
},
  "geometry": {"coordinates":[-73.818303,40.820788],"type":"Point"}
}