{
  "type": "Feature",
  "properties": {
    "iso:country":"US",
    "sg:address":"8 4th St",
    "sg:city":"Hoosick Falls",
    "sg:classifiers":[
        {
            "category":"Building & Trades",
            "subcategory":"Construction",
            "type":"Services"
        }
    ],
    "sg:phone":"+1 518 686 1868",
    "sg:postcode":"12090",
    "sg:province":"NY",
    "sg:tags":[
        "residential"
    ],
    "wof:name":"Goldstein Construction",
    "wof:placetype":"venue"
},
  "geometry": {"coordinates":[-73.356979,42.896189],"type":"Point"}
}