{
  "type": "Feature",
  "properties": {
    "iso:country":"US",
    "sg:address":"496 Plandome Rd",
    "sg:city":"Manhasset",
    "sg:classifiers":[
        {
            "category":"Manufacturing",
            "subcategory":"Food",
            "type":"Manufacturing & Wholesale Goods"
        },
        {
            "category":"Wholesale",
            "subcategory":"Groceries",
            "type":"Manufacturing & Wholesale Goods"
        }
    ],
    "sg:phone":"+1 516 365 7671",
    "sg:postcode":"11030",
    "sg:province":"NY",
    "sg:tags":[
        "mfg",
        "solid",
        "candy",
        "chocolate",
        "cocoa",
        "including"
    ],
    "wof:name":"Aigner Chocolates Inc",
    "wof:placetype":"venue"
},
  "geometry": {"coordinates":[-73.70077999999999,40.799584],"type":"Point"}
}