{
  "type": "Feature",
  "properties": {
    "iso:country":"US",
    "sg:address":"145 Olivia Dr",
    "sg:city":"Rochester",
    "sg:classifiers":[
        {
            "category":"Building & Trades",
            "subcategory":"Landscaping Services",
            "type":"Services"
        }
    ],
    "sg:phone":"+1 585 723 0546",
    "sg:postcode":"14626",
    "sg:province":"NY",
    "wof:name":"A One Lawn Care",
    "wof:placetype":"venue"
},
  "geometry": {"coordinates":[-77.72040800000001,43.220657],"type":"Point"}
}