{
  "type": "Feature",
  "properties": {
    "iso:country":"US",
    "sg:address":"PO Box 69",
    "sg:city":"Speonk",
    "sg:classifiers":[
        {
            "category":"Shopping",
            "subcategory":"Adult",
            "type":"Retail Goods"
        }
    ],
    "sg:phone":"+1 631 495 4042",
    "sg:postcode":"11972",
    "sg:province":"NY",
    "sg:tags":[
        "entertainment"
    ],
    "sg:website":"www.tracisparadise.com",
    "wof:name":"Traci's Paradise",
    "wof:placetype":"venue"
},
  "geometry": {"coordinates":[-72.701413,40.818115],"type":"Point"}
}