{
  "type": "Feature",
  "properties": {
    "iso:country":"US",
    "sg:address":"20 W 20th St",
    "sg:city":"New York",
    "sg:classifiers":[
        {
            "category":"Autos & Motor Vehicles",
            "subcategory":"Automobile Sales",
            "type":"Retail Goods"
        }
    ],
    "sg:phone":"+1 718 723 5300",
    "sg:postcode":"10011",
    "sg:province":"NY",
    "sg:tags":[
        "limo"
    ],
    "wof:name":"T Z R Transportation",
    "wof:placetype":"venue"
},
  "geometry": {"coordinates":[-73.99240899999999,40.740263],"type":"Point"}
}