{
  "type": "Feature",
  "properties": {
    "addr:full":"2604 Lakeview Rd Lake View NY 14085",
    "addr:housenumber":"2604",
    "addr:postcode":"14085",
    "addr:street":"Lakeview Rd",
    "iso:country":"US",
    "sg:address":"2604 Lakeview Rd",
    "sg:city":"Lake View",
    "sg:classifiers":[
        {
            "category":"Manufacturing",
            "subcategory":"Lumber",
            "type":"Manufacturing & Wholesale Goods"
        }
    ],
    "sg:phone":"+1   ",
    "sg:postcode":"14085",
    "sg:province":"NY",
    "sg:tags":[
        "hardwood",
        "mfg"
    ],
    "wof:name":"Eagle Forrest Products Inc",
    "wof:placetype":"venue"
},
  "geometry": {"coordinates":[-78.903445,42.707647],"type":"Point"}
}