{
  "type": "Feature",
  "properties": {
    "iso:country":"US",
    "sg:address":"52 White Street",
    "sg:city":"New York",
    "sg:classifiers":[
        {
            "category":"Arts & Performance",
            "subcategory":"Arts Center",
            "type":"Entertainment"
        },
        {
            "category":"Cinema",
            "subcategory":"Movie Theater",
            "type":"Entertainment"
        }
    ],
    "sg:phone":"+1 212 226 4085",
    "sg:postcode":"10013",
    "sg:province":"NY",
    "sg:tags":[
        "performing"
    ],
    "wof:name":"Manhattan Childrens Theater",
    "wof:placetype":"venue"
},
  "geometry": {"coordinates":[-74.003827,40.718433],"type":"Point"}
}