{
  "type": "Feature",
  "properties": {
    "addr:full":"1506 Metropolitan Ave Bronx NY 10462",
    "addr:housenumber":"1506",
    "addr:postcode":"10462",
    "addr:street":"Metropolitan Ave",
    "iso:country":"US",
    "sg:address":"1506 Metropolitan Ave",
    "sg:city":"Bronx",
    "sg:classifiers":[
        {
            "category":"Personal",
            "type":"Services"
        }
    ],
    "sg:phone":"+1   ",
    "sg:postcode":"10462",
    "sg:province":"NY",
    "wof:name":"Parkchester Gift Shop",
    "wof:placetype":"venue"
},
  "geometry": {"coordinates":[-73.858445,40.839363],"type":"Point"}
}