{
  "type": "Feature",
  "properties": {
    "addr:full":"204 Hendy Creek Rd Pine City NY 14871",
    "addr:housenumber":"204",
    "addr:postcode":"14871",
    "addr:street":"Hendy Creek Rd",
    "iso:country":"US",
    "sg:address":"204 Hendy Creek Rd",
    "sg:city":"Pine City",
    "sg:classifiers":[
        {
            "category":"Food & Beverages",
            "subcategory":"Groceries & Convenience Stores",
            "type":"Retail Goods"
        }
    ],
    "sg:phone":"+1   ",
    "sg:postcode":"14871",
    "sg:province":"NY",
    "wof:name":"Hendy Creek Market",
    "wof:placetype":"venue"
},
  "geometry": {"coordinates":[-76.889494,42.079096],"type":"Point"}
}