{
  "type": "Feature",
  "properties": {
    "iso:country":"US",
    "sg:address":"110 S Bicycle Path",
    "sg:city":"Selden",
    "sg:classifiers":[
        {
            "category":"Wholesale",
            "subcategory":"Metals & Minerals",
            "type":"Manufacturing & Wholesale Goods"
        }
    ],
    "sg:phone":"+1 631 398 3054",
    "sg:postcode":"11784",
    "sg:province":"NY",
    "sg:tags":[
        "steel"
    ],
    "wof:name":"B & J Steel Supply Corp",
    "wof:placetype":"venue"
},
  "geometry": {"coordinates":[-73.02499400000001,40.853632],"type":"Point"}
}