{
  "type": "Feature",
  "properties": {
    "iso:country":"US",
    "sg:address":"10037 US Hwy 219",
    "sg:city":"West Valley",
    "sg:classifiers":[
        {
            "category":"Professional",
            "type":"Services"
        }
    ],
    "sg:phone":"+1 716 592 0010",
    "sg:postcode":"14171",
    "sg:province":"NY",
    "sg:tags":[
        "establishment"
    ],
    "wof:name":"Wire Creations Inc",
    "wof:placetype":"venue"
},
  "geometry": {"coordinates":[-78.60367599999999,42.380465],"type":"Point"}
}