{
  "type": "Feature",
  "properties": {
    "iso:country":"US",
    "sg:address":"5801 Sunrise Hwy",
    "sg:city":"Holbrook",
    "sg:classifiers":[
        {
            "category":"Restaurant",
            "type":"Food & Drink"
        }
    ],
    "sg:menulink":"http://www.allmenus.com/ny/islip/107254-soup-man/menu/",
    "sg:phone":"+1 631 567 6993",
    "sg:postcode":"11741",
    "sg:province":"NY",
    "sg:tags":[
        "soup",
        "american",
        "salad"
    ],
    "wof:name":"Soup Man",
    "wof:placetype":"venue"
},
  "geometry": {"coordinates":[-73.06623999999999,40.769424],"type":"Point"}
}