{
  "type": "Feature",
  "properties": {
    "addr:full":"19 W Main St Macedon NY 14502",
    "addr:housenumber":"19",
    "addr:postcode":"14502",
    "addr:street":"W Main St",
    "iso:country":"US",
    "sg:address":"19 W Main St",
    "sg:city":"Macedon",
    "sg:classifiers":[
        {
            "category":"Insurance",
            "subcategory":"Insurance Agent",
            "type":"Services"
        }
    ],
    "sg:phone":"+1 585 423 9380",
    "sg:postcode":"14502",
    "sg:province":"NY",
    "sg:tags":[
        "independent"
    ],
    "wof:name":"New York Life",
    "wof:placetype":"venue"
},
  "geometry": {"coordinates":[-77.30596799999999,43.066753],"type":"Point"}
}