{
  "type": "Feature",
  "properties": {
    "addr:full":"625 Jericho Tpke Syosset NY 11791",
    "addr:housenumber":"625",
    "addr:postcode":"11791",
    "addr:street":"Jericho Tpke",
    "iso:country":"US",
    "sg:address":"625 Jericho Tpke",
    "sg:city":"Syosset",
    "sg:classifiers":[
        {
            "category":"Personal",
            "subcategory":"Beauty Salon",
            "type":"Services"
        }
    ],
    "sg:phone":"+1 516 364 6401",
    "sg:postcode":"11791",
    "sg:province":"NY",
    "wof:name":"John Michael & Co",
    "wof:placetype":"venue"
},
  "geometry": {"coordinates":[-73.494062,40.811246],"type":"Point"}
}