{
  "type": "Feature",
  "properties": {
    "addr:full":"244 W 56 St New York NY 10019",
    "addr:housenumber":"244",
    "addr:postcode":"10019",
    "addr:street":"W 56 St",
    "iso:country":"US",
    "sg:address":"244 W 56 St",
    "sg:city":"New York",
    "sg:classifiers":[
        {
            "category":"Building & Trades",
            "subcategory":"Plumbing",
            "type":"Services"
        }
    ],
    "sg:phone":"+1 212 247 0506",
    "sg:postcode":"10019",
    "sg:province":"NY",
    "sg:tags":[
        "conditioning",
        "air",
        "system",
        "contractor"
    ],
    "wof:name":"Atlantic Carpentry",
    "wof:placetype":"venue"
},
  "geometry": {"coordinates":[-73.983082,40.7658],"type":"Point"}
}