{
  "type": "Feature",
  "properties": {
    "addr:full":"1539 Unionport Road Bronx NY 10462",
    "addr:housenumber":"1539",
    "addr:postcode":"10462",
    "addr:street":"Unionport Road",
    "iso:country":"US",
    "sg:address":"1539 Unionport Road",
    "sg:city":"Bronx",
    "sg:classifiers":[
        {
            "category":"Restaurant",
            "type":"Food & Drink"
        }
    ],
    "sg:phone":"+1 718 828 5664",
    "sg:postcode":"10462",
    "sg:province":"NY",
    "sg:tags":[
        "pizza"
    ],
    "wof:name":"Venice Pizzeria & Restaurant",
    "wof:placetype":"venue"
},
  "geometry": {"coordinates":[-73.858602,40.837377],"type":"Point"}
}