{
  "type": "Feature",
  "properties": {
    "addr:full":"54 Main St Mount Morris NY 14510",
    "addr:housenumber":"54",
    "addr:postcode":"14510",
    "addr:street":"Main St",
    "iso:country":"US",
    "sg:address":"54 Main St",
    "sg:city":"Mount Morris",
    "sg:classifiers":[
        {
            "category":"Restaurant",
            "type":"Food & Drink"
        }
    ],
    "sg:phone":"+1   ",
    "sg:postcode":"14510",
    "sg:province":"NY",
    "sg:tags":[
        "eating"
    ],
    "wof:name":"Lynann M Tremblay",
    "wof:placetype":"venue"
},
  "geometry": {"coordinates":[-77.874239,42.72581],"type":"Point"}
}