{
  "type": "Feature",
  "properties": {
    "iso:country":"US",
    "sg:address":"4700 W Lake Rd",
    "sg:city":"Dunkirk",
    "sg:classifiers":[
        {
            "category":"Government",
            "subcategory":"Office",
            "type":"Public Place"
        }
    ],
    "sg:phone":"+1 716 366 0057",
    "sg:postcode":"14048",
    "sg:province":"NY",
    "sg:tags":[
        "village"
    ],
    "wof:name":"Freedonia Waste Water Trtmnt",
    "wof:placetype":"venue"
},
  "geometry": {"coordinates":[-79.36869,42.469687],"type":"Point"}
}