{
  "type": "Feature",
  "properties": {
    "iso:country":"US",
    "sg:address":"848 49th St # 850",
    "sg:city":"Brooklyn",
    "sg:classifiers":[
        {
            "category":"Retail",
            "subcategory":"Portrait Studio",
            "type":"Services"
        },
        {
            "category":"Professional",
            "subcategory":"Art Services",
            "type":"Services"
        }
    ],
    "sg:phone":"+1 718 438 1489",
    "sg:postcode":"11220",
    "sg:province":"NY",
    "sg:tags":[
        "photographer",
        "photography",
        "store"
    ],
    "wof:name":"49th Street Imaging Associates",
    "wof:placetype":"venue"
},
  "geometry": {"coordinates":[-74.118432,40.64089],"type":"Point"}
}