{
  "type": "Feature",
  "properties": {
    "iso:country":"US",
    "sg:address":"17 Maple Ave",
    "sg:city":"Lynbrook",
    "sg:classifiers":[
        {
            "category":"Building & Trades",
            "subcategory":"Plumbing",
            "type":"Services"
        },
        {
            "category":"Building & Trades",
            "subcategory":"Construction",
            "type":"Services"
        }
    ],
    "sg:phone":"+1 516 285 9879",
    "sg:postcode":"11563",
    "sg:province":"NY",
    "sg:tags":[
        "plumber",
        "industrial",
        "system",
        "specialty",
        "heating",
        "contractors-commercial",
        "contractor",
        "air conditioning"
    ],
    "sg:website":"http://makoplumbing.com",
    "wof:name":"Mako Plumbing & Heating Inc",
    "wof:placetype":"venue"
},
  "geometry": {"coordinates":[-73.682677,40.659704],"type":"Point"}
}