{
  "type": "Feature",
  "properties": {
    "iso:country":"US",
    "sg:address":"705 86th Street",
    "sg:city":"Brooklyn",
    "sg:classifiers":[
        {
            "category":"Health Services",
            "subcategory":"Doctor",
            "type":"Services"
        }
    ],
    "sg:phone":"+1 718 836 0600",
    "sg:postcode":"11228",
    "sg:province":"NY",
    "wof:name":"Kang Pritpal S MD",
    "wof:placetype":"venue"
},
  "geometry": {"coordinates":[-74.02196000000001,40.618951],"type":"Point"}
}