{
  "type": "Feature",
  "properties": {
    "iso:country":"US",
    "sg:address":"232 3rd St Ste E101",
    "sg:city":"Brooklyn",
    "sg:classifiers":[
        {
            "category":"Professional",
            "subcategory":"Art Services",
            "type":"Services"
        },
        {
            "category":"Professional",
            "subcategory":"Business Services",
            "type":"Services"
        }
    ],
    "sg:phone":"+1 718 596 3520",
    "sg:postcode":"11215",
    "sg:province":"NY",
    "sg:tags":[
        "development",
        "product",
        "graphic",
        "designers-industrial",
        "marketing",
        "commercial",
        "designer",
        "design"
    ],
    "sg:website":"http://www.swayspace.com",
    "wof:name":"Swayspace",
    "wof:placetype":"venue"
},
  "geometry": {"coordinates":[-73.988022,40.675079],"type":"Point"}
}