{
  "type": "Feature",
  "properties": {
    "iso:country":"US",
    "sg:address":"114 Roberts Rd",
    "sg:city":"Camillus",
    "sg:classifiers":[
        {
            "category":"Education",
            "subcategory":"Special Training",
            "type":"Public Place"
        }
    ],
    "sg:phone":"+1 315 487 3326",
    "sg:postcode":"13031",
    "sg:province":"NY",
    "sg:tags":[
        "instruction",
        "music"
    ],
    "wof:name":"Joe Precourt Guitar & Bass",
    "wof:placetype":"venue"
},
  "geometry": {"coordinates":[-76.264076,43.044886],"type":"Point"}
}