{
  "type": "Feature",
  "properties": {
    "iso:country":"US",
    "sg:address":"230 E Glen Ave",
    "sg:city":"Syracuse",
    "sg:classifiers":[
        {
            "category":"Building & Trades",
            "subcategory":"Construction",
            "type":"Services"
        }
    ],
    "sg:phone":"+1 315 469 3813",
    "sg:postcode":"13205",
    "sg:province":"NY",
    "sg:tags":[
        "general",
        "contractor"
    ],
    "wof:name":"Almost Any Home Improvement",
    "wof:placetype":"venue"
},
  "geometry": {"coordinates":[-76.141211,43.005378],"type":"Point"}
}