{
  "type": "Feature",
  "properties": {
    "iso:country":"US",
    "sg:address":"33 Chardavoyne Rd",
    "sg:city":"Warwick",
    "sg:classifiers":[
        {
            "category":"Building & Trades",
            "subcategory":"Construction",
            "type":"Services"
        }
    ],
    "sg:phone":"+1 845 258 4909",
    "sg:postcode":"10990",
    "sg:province":"NY",
    "sg:tags":[
        "house"
    ],
    "wof:name":"Moore Construction",
    "wof:placetype":"venue"
},
  "geometry": {"coordinates":[-74.429362,41.291278],"type":"Point"}
}