{
  "type": "Feature",
  "properties": {
    "addr:full":"400 Madison Ave New York NY 10017",
    "addr:housenumber":"400",
    "addr:postcode":"10017",
    "addr:street":"Madison Ave",
    "iso:country":"US",
    "sg:address":"400 Madison Ave",
    "sg:city":"New York",
    "sg:classifiers":[
        {
            "category":"Professional",
            "subcategory":"Lawyer & Legal Services",
            "type":"Services"
        }
    ],
    "sg:phone":"+1 718 899 8005",
    "sg:postcode":"10017",
    "sg:province":"NY",
    "wof:name":"Musa-Obregon S Michael Atty",
    "wof:placetype":"venue"
},
  "geometry": {"coordinates":[-73.976997,40.756001],"type":"Point"}
}