{
  "type": "Feature",
  "properties": {
    "iso:country":"US",
    "sg:address":"518 Hawkins Ave",
    "sg:city":"Ronkonkoma",
    "sg:classifiers":[
        {
            "category":"Social Services",
            "type":"Services"
        }
    ],
    "sg:phone":"+1 631 471 0688",
    "sg:postcode":"11779",
    "sg:province":"NY",
    "wof:name":"Ann Haney",
    "wof:placetype":"venue"
},
  "geometry": {"coordinates":[-73.10783499999999,40.827723],"type":"Point"}
}