{
  "type": "Feature",
  "properties": {
    "iso:country":"US",
    "sg:address":"200 Stewart Ave",
    "sg:city":"Bethpage",
    "sg:classifiers":[
        {
            "category":"Education",
            "subcategory":"School",
            "type":"Public Place"
        }
    ],
    "sg:phone":"+1 516 731 9745",
    "sg:postcode":"11714",
    "sg:province":"NY",
    "wof:name":"Plainedge Community Ctr",
    "wof:placetype":"venue"
},
  "geometry": {"coordinates":[-73.482271,40.727568],"type":"Point"}
}