{
  "type": "Feature",
  "properties": {
    "addr:full":"72 Wickatuck Ln Sag Harbor NY 11963",
    "addr:housenumber":"72",
    "addr:postcode":"11963",
    "addr:street":"Wickatuck Ln",
    "iso:country":"US",
    "sg:address":"72 Wickatuck Ln",
    "sg:city":"Sag Harbor",
    "sg:classifiers":[
        {
            "category":"Manufacturing",
            "subcategory":"Glass & Minerals",
            "type":"Manufacturing & Wholesale Goods"
        }
    ],
    "sg:phone":"+1   ",
    "sg:postcode":"11963",
    "sg:province":"NY",
    "sg:tags":[
        "organization",
        "religious",
        "hydraulic",
        "cement",
        "mfg"
    ],
    "wof:name":"Tessarae",
    "wof:placetype":"venue"
},
  "geometry": {"coordinates":[-72.325254,40.983928],"type":"Point"}
}