{
  "type": "Feature",
  "properties": {
    "addr:full":"289 Hudson St New York NY 10013",
    "addr:housenumber":"289",
    "addr:postcode":"10013",
    "addr:street":"Hudson St",
    "iso:country":"US",
    "sg:address":"289 Hudson St",
    "sg:city":"New York",
    "sg:classifiers":[
        {
            "category":"Retail",
            "subcategory":"Auto Repair",
            "type":"Services"
        }
    ],
    "sg:phone":"+1 917 558 9603",
    "sg:postcode":"10013",
    "sg:province":"NY",
    "sg:tags":[
        "wrecker"
    ],
    "wof:name":"Emergency 7 Day Towing",
    "wof:placetype":"venue"
},
  "geometry": {"coordinates":[-74.007683,40.725488],"type":"Point"}
}