{
  "type": "Feature",
  "properties": {
    "addr:full":"49 Bryant Ave Roslyn NY 11576",
    "addr:housenumber":"49",
    "addr:postcode":"11576",
    "addr:street":"Bryant Ave",
    "iso:country":"US",
    "sg:address":"49 Bryant Ave",
    "sg:city":"Roslyn",
    "sg:classifiers":[
        {
            "category":"Banks & Credit Unions",
            "subcategory":"Bank",
            "type":"Services"
        }
    ],
    "sg:phone":"+1 516 326 9140",
    "sg:postcode":"11576",
    "sg:province":"NY",
    "wof:name":"Chase Manhattan",
    "wof:placetype":"venue"
},
  "geometry": {"coordinates":[-73.646789,40.804783],"type":"Point"}
}