{
  "type": "Feature",
  "properties": {
    "addr:full":"5 Gibson Ave White Plains NY 10607",
    "addr:housenumber":"5",
    "addr:postcode":"10607",
    "addr:street":"Gibson Ave",
    "iso:country":"US",
    "sg:address":"5 Gibson Ave",
    "sg:city":"White Plains",
    "sg:classifiers":[
        {
            "category":"Building & Trades",
            "subcategory":"Construction",
            "type":"Services"
        }
    ],
    "sg:phone":"+1 914 328 0082",
    "sg:postcode":"10607",
    "sg:province":"NY",
    "sg:tags":[
        "excavating",
        "contractor"
    ],
    "wof:name":"E J Excavtng",
    "wof:placetype":"venue"
},
  "geometry": {"coordinates":[-73.791003,41.041216],"type":"Point"}
}