{
  "type": "Feature",
  "properties": {
    "addr:full":"1296 Delaware Ave Buffalo NY 14209",
    "addr:housenumber":"1296",
    "addr:postcode":"14209",
    "addr:street":"Delaware Ave",
    "iso:country":"US",
    "sg:address":"1296 Delaware Ave",
    "sg:city":"Buffalo",
    "sg:classifiers":[
        {
            "category":"Health Services",
            "subcategory":"Doctor",
            "type":"Services"
        }
    ],
    "sg:phone":"+1 716 883 3611",
    "sg:postcode":"14209",
    "sg:province":"NY",
    "sg:tags":[
        "physician",
        "surgeon"
    ],
    "wof:name":"John C Hellriegel Jr MD",
    "wof:placetype":"venue"
},
  "geometry": {"coordinates":[-78.86847,42.918056],"type":"Point"}
}