{
  "type": "Feature",
  "properties": {
    "addr:full":"5022 15th Ave Brooklyn NY 11219",
    "addr:housenumber":"5022",
    "addr:postcode":"11219",
    "addr:street":"15Th Ave",
    "iso:country":"US",
    "sg:address":"5022 15th Ave",
    "sg:city":"Brooklyn",
    "sg:classifiers":[
        {
            "category":"Health Services",
            "subcategory":"Doctor",
            "type":"Services"
        }
    ],
    "sg:phone":"+1 718 851 5212",
    "sg:postcode":"11219",
    "sg:province":"NY",
    "wof:name":"Slomowitz Joseph MD",
    "wof:placetype":"venue"
},
  "geometry": {"coordinates":[-73.988602,40.631699],"type":"Point"}
}