{
  "type": "Feature",
  "properties": {
    "iso:country":"US",
    "sg:address":"59 W Main St",
    "sg:city":"Norwich",
    "sg:classifiers":[
        {
            "category":"Professional",
            "subcategory":"Lawyer & Legal Services",
            "type":"Services"
        }
    ],
    "sg:phone":"+1   ",
    "sg:postcode":"13815",
    "sg:province":"NY",
    "wof:name":"James G Cushman",
    "wof:placetype":"venue"
},
  "geometry": {"coordinates":[-75.52847199999999,42.530581],"type":"Point"}
}