{
  "type": "Feature",
  "properties": {
    "addr:full":"259 Capen Rd Brockport NY 14420",
    "addr:housenumber":"259",
    "addr:postcode":"14420",
    "addr:street":"Capen Rd",
    "iso:country":"US",
    "sg:address":"259 Capen Rd",
    "sg:city":"Brockport",
    "sg:classifiers":[
        {
            "category":"Wholesale",
            "subcategory":"Machinery & Supplies",
            "type":"Manufacturing & Wholesale Goods"
        }
    ],
    "sg:phone":"+1 585 637 7510",
    "sg:postcode":"14420",
    "sg:province":"NY",
    "wof:name":"Horsewheels Trailer Sales",
    "wof:placetype":"venue"
},
  "geometry": {"coordinates":[-77.963678,43.160119],"type":"Point"}
}