{
  "type": "Feature",
  "properties": {
    "iso:country":"US",
    "sg:address":"91 1st Ave",
    "sg:city":"New York",
    "sg:classifiers":[
        {
            "category":"Restaurant",
            "type":"Food & Drink"
        }
    ],
    "sg:phone":"+1 212 614 9333",
    "sg:postcode":"10003",
    "sg:province":"NY",
    "sg:website":"www.sigirinyc.com/",
    "wof:name":"Sigiri",
    "wof:placetype":"venue"
},
  "geometry": {"coordinates":[-73.98632499999999,40.726241],"type":"Point"}
}