{
  "type": "Feature",
  "properties": {
    "addr:full":"356 Roberts Ave Yonkers NY 10703",
    "addr:housenumber":"356",
    "addr:postcode":"10703",
    "addr:street":"Roberts Ave",
    "iso:country":"US",
    "sg:address":"356 Roberts Ave",
    "sg:city":"Yonkers",
    "sg:classifiers":[
        {
            "category":"Professional",
            "subcategory":"Secretarial Services",
            "type":"Services"
        }
    ],
    "sg:phone":"+1 914 237 1472",
    "sg:postcode":"10703",
    "sg:province":"NY",
    "sg:tags":[
        "resume"
    ],
    "wof:name":"A Better Resume Svc",
    "wof:placetype":"venue"
},
  "geometry": {"coordinates":[-73.877135,40.958675],"type":"Point"}
}