{
  "type": "Feature",
  "properties": {
    "iso:country":"US",
    "sg:address":"11 Cornelia Street",
    "sg:city":"New York",
    "sg:classifiers":[
        {
            "category":"Building & Trades",
            "subcategory":"Construction",
            "type":"Services"
        }
    ],
    "sg:phone":"+1 212 489 2498",
    "sg:postcode":"10014",
    "sg:province":"NY",
    "sg:tags":[
        "contractor"
    ],
    "wof:name":"Motivated Building Concepts",
    "wof:placetype":"venue"
},
  "geometry": {"coordinates":[-74.001296,40.731723],"type":"Point"}
}