{
  "type": "Feature",
  "properties": {
    "addr:full":"29 Gardiner Pl Walton NY 13856",
    "addr:housenumber":"29",
    "addr:postcode":"13856",
    "addr:street":"Gardiner Pl",
    "iso:country":"US",
    "sg:address":"29 Gardiner Pl",
    "sg:city":"Walton",
    "sg:classifiers":[
        {
            "category":"Restaurant",
            "type":"Food & Drink"
        }
    ],
    "sg:phone":"+1 607 865 4873",
    "sg:postcode":"13856",
    "sg:province":"NY",
    "sg:tags":[
        "style",
        "family"
    ],
    "wof:name":"Candido Old World Coal Brick",
    "wof:placetype":"venue"
},
  "geometry": {"coordinates":[-75.128782,42.168874],"type":"Point"}
}