{
  "type": "Feature",
  "properties": {
    "iso:country":"US",
    "sg:address":"91 Jones Landing Rd",
    "sg:city":"Hammond",
    "sg:classifiers":[
        {
            "category":"Professional",
            "type":"Services"
        }
    ],
    "sg:phone":"+1 315 324 5889",
    "sg:postcode":"13646",
    "sg:province":"NY",
    "sg:tags":[
        "establishment"
    ],
    "wof:name":"De Carr Lyndon",
    "wof:placetype":"venue"
},
  "geometry": {"coordinates":[-75.77981699999999,44.421957],"type":"Point"}
}