{
  "type": "Feature",
  "properties": {
    "addr:full":"17 W 19 St New York NY 10011",
    "addr:housenumber":"17",
    "addr:postcode":"10011",
    "addr:street":"W 19 St",
    "iso:country":"US",
    "sg:address":"17 W 19 St",
    "sg:city":"New York",
    "sg:classifiers":[
        {
            "category":"Bars & Pubs",
            "type":"Food & Drink"
        }
    ],
    "sg:phone":"+1 212 352 2001",
    "sg:postcode":"10011",
    "sg:province":"NY",
    "sg:tags":[
        "club",
        "night"
    ],
    "wof:name":"Gogo Night Club",
    "wof:placetype":"venue"
},
  "geometry": {"coordinates":[-73.994158,40.740286],"type":"Point"}
}