{
  "type": "Feature",
  "properties": {
    "addr:full":"416 W 36 St New York NY 10018",
    "addr:housenumber":"416",
    "addr:postcode":"10018",
    "addr:street":"W 36 St",
    "iso:country":"US",
    "sg:address":"416 W 36 St",
    "sg:city":"New York",
    "sg:classifiers":[
        {
            "category":"Parking",
            "type":"Transportation"
        }
    ],
    "sg:phone":"+1   ",
    "sg:postcode":"10018",
    "sg:province":"NY",
    "sg:tags":[
        "automobile"
    ],
    "wof:name":"Central Parking Corp 6014",
    "wof:placetype":"venue"
},
  "geometry": {"coordinates":[-73.996174,40.754868],"type":"Point"}
}