{
  "type": "Feature",
  "properties": {
    "iso:country":"US",
    "sg:address":"15 Auburn Rd",
    "sg:city":"Lansing",
    "sg:classifiers":[
        {
            "category":"Health Services",
            "subcategory":"Chiropractor",
            "type":"Services"
        }
    ],
    "sg:phone":"+1 607 533 4231",
    "sg:postcode":"14882",
    "sg:province":"NY",
    "sg:tags":[
        "chiropractic"
    ],
    "wof:name":"Lansing Chiropractic Ofc PC",
    "wof:placetype":"venue"
},
  "geometry": {"coordinates":[-76.504802,42.538006],"type":"Point"}
}