{
  "type": "Feature",
  "properties": {
    "iso:country":"US",
    "sg:address":"607 Brooks Rd",
    "sg:city":"Castle Creek",
    "sg:classifiers":[
        {
            "category":"Organizations",
            "subcategory":"Religious Organization",
            "type":"Services"
        }
    ],
    "sg:phone":"+1 607 648 4161",
    "sg:postcode":"13744",
    "sg:province":"NY",
    "sg:tags":[
        "church"
    ],
    "wof:name":"Sacred Heart Ukranian Catholic",
    "wof:placetype":"venue"
},
  "geometry": {"coordinates":[-75.91907500000001,42.219521],"type":"Point"}
}