{
  "type": "Feature",
  "properties": {
    "iso:country":"US",
    "sg:address":"19 Mead Rd",
    "sg:city":"Armonk",
    "sg:classifiers":[
        {
            "category":"Building & Trades",
            "subcategory":"Construction",
            "type":"Services"
        }
    ],
    "sg:phone":"+1 914 273 3826",
    "sg:postcode":"10504",
    "sg:province":"NY",
    "sg:tags":[
        "roofing",
        "industrial",
        "contractors-commercial",
        "contractor"
    ],
    "wof:name":"Hellgren Building And Roofing Inc",
    "wof:placetype":"venue"
},
  "geometry": {"coordinates":[-73.664627,41.138463],"type":"Point"}
}