{
  "type": "Feature",
  "properties": {
    "iso:country":"US",
    "sg:address":"293 Halstead Ave",
    "sg:city":"Harrison",
    "sg:classifiers":[
        {
            "category":"Banks & Credit Unions",
            "subcategory":"Bank",
            "type":"Services"
        }
    ],
    "sg:phone":"+1 914 777 4010",
    "sg:postcode":"10528",
    "sg:province":"NY",
    "wof:name":"Wachovia",
    "wof:placetype":"venue"
},
  "geometry": {"coordinates":[-73.711804,40.968996],"type":"Point"}
}