{
  "type": "Feature",
  "properties": {
    "iso:country":"US",
    "sg:address":"591 Lexington Ave",
    "sg:city":"New York",
    "sg:classifiers":[
        {
            "category":"Restaurant",
            "type":"Food & Drink"
        }
    ],
    "sg:phone":"+1   ",
    "sg:postcode":"10022",
    "sg:province":"NY",
    "sg:tags":[
        "pizza"
    ],
    "wof:name":"Pizza Pax Deli",
    "wof:placetype":"venue"
},
  "geometry": {"coordinates":[-73.971692,40.757157],"type":"Point"}
}