{
  "type": "Feature",
  "properties": {
    "addr:full":"239 W 52nd St New York NY 10019",
    "addr:housenumber":"239",
    "addr:postcode":"10019",
    "addr:street":"W 52Nd St",
    "iso:country":"US",
    "sg:address":"239 W 52nd St",
    "sg:city":"New York",
    "sg:classifiers":[
        {
            "category":"Retail",
            "subcategory":"Auto Repair",
            "type":"Services"
        }
    ],
    "sg:phone":"+1 646 307 4578",
    "sg:postcode":"10019",
    "sg:province":"NY",
    "sg:tags":[
        "wrecker"
    ],
    "wof:name":"A Number 1 Abwawa 24 Hour Car",
    "wof:placetype":"venue"
},
  "geometry": {"coordinates":[-73.984754,40.763384],"type":"Point"}
}