{
  "type": "Feature",
  "properties": {
    "iso:country":"US",
    "sg:address":"6 Union St",
    "sg:city":"Montgomery",
    "sg:classifiers":[
        {
            "category":"Professional",
            "subcategory":"Computer Services",
            "type":"Services"
        }
    ],
    "sg:phone":"+1 845 457 4445",
    "sg:postcode":"12549",
    "sg:province":"NY",
    "sg:tags":[
        "repair"
    ],
    "sg:website":"www.hudsonvalleymac.com",
    "wof:name":"Hudson Valley Mac",
    "wof:placetype":"venue"
},
  "geometry": {"coordinates":[-74.237308,41.527371],"type":"Point"}
}