{
  "type": "Feature",
  "properties": {
    "addr:full":"95 Bowery New York NY 10002",
    "addr:housenumber":"95",
    "addr:postcode":"10002",
    "addr:street":"Bowery",
    "iso:country":"US",
    "sg:address":"95 Bowery",
    "sg:city":"New York",
    "sg:classifiers":[
        {
            "category":"Building & Trades",
            "subcategory":"Locksmith",
            "type":"Services"
        }
    ],
    "sg:phone":"+1 917 289 3791",
    "sg:postcode":"10002",
    "sg:province":"NY",
    "sg:tags":[
        "key"
    ],
    "wof:name":"7 Day Emergency 24 Hr Locksmith",
    "wof:placetype":"venue"
},
  "geometry": {"coordinates":[-73.995499,40.7174],"type":"Point"}
}