{
  "type": "Feature",
  "properties": {
    "addr:full":"544 Middle Rd Oneida NY 13421",
    "addr:housenumber":"544",
    "addr:postcode":"13421",
    "addr:street":"Middle Rd",
    "iso:country":"US",
    "sg:address":"544 Middle Rd",
    "sg:city":"Oneida",
    "sg:classifiers":[
        {
            "category":"Organizations",
            "subcategory":"Membership Organization",
            "type":"Services"
        }
    ],
    "sg:phone":"+1   ",
    "sg:postcode":"13421",
    "sg:province":"NY",
    "wof:name":"Ruritan Association",
    "wof:placetype":"venue"
},
  "geometry": {"coordinates":[-75.61243,43.058196],"type":"Point"}
}