{
  "type": "Feature",
  "properties": {
    "addr:full":"340 Carle Rd Carle Place NY 11514",
    "addr:housenumber":"340",
    "addr:postcode":"11514",
    "addr:street":"Carle Rd",
    "iso:country":"US",
    "sg:address":"340 Carle Rd",
    "sg:city":"Carle Place",
    "sg:classifiers":[
        {
            "category":"Insurance",
            "subcategory":"Insurance Agent",
            "type":"Services"
        }
    ],
    "sg:phone":"+1 516 334 1500",
    "sg:postcode":"11514",
    "sg:province":"NY",
    "sg:tags":[
        "brokerage",
        "life",
        "agency"
    ],
    "wof:name":"Crisona Financial Group Inc",
    "wof:placetype":"venue"
},
  "geometry": {"coordinates":[-73.604091,40.756919],"type":"Point"}
}