{
  "type": "Feature",
  "properties": {
    "iso:country":"US",
    "sg:address":"178 Charles Colman Blvd",
    "sg:city":"Pawling",
    "sg:classifiers":[
        {
            "category":"Real Estate",
            "subcategory":"Developer",
            "type":"Services"
        }
    ],
    "sg:phone":"+1 845 855 3500",
    "sg:postcode":"12564",
    "sg:province":"NY",
    "wof:name":"American Tree & Landscpg Corp",
    "wof:placetype":"venue"
},
  "geometry": {"coordinates":[-73.59990999999999,41.570855],"type":"Point"}
}