{
  "type": "Feature",
  "properties": {
    "iso:country":"US",
    "sg:address":"120 Kisco Ave",
    "sg:city":"Mt Kisco",
    "sg:classifiers":[
        {
            "category":"Professional",
            "type":"Services"
        }
    ],
    "sg:phone":"+1 914 666 5850",
    "sg:postcode":"10549",
    "sg:province":"NY",
    "sg:tags":[
        "establishment"
    ],
    "wof:name":"Sculpt & Fit Of Westchester",
    "wof:placetype":"venue"
},
  "geometry": {"coordinates":[-73.726389,41.214307],"type":"Point"}
}