{
  "type": "Feature",
  "properties": {
    "iso:country":"US",
    "sg:address":"95 Murphy Rd",
    "sg:city":"Swan Lake",
    "sg:classifiers":[
        {
            "category":"Building & Trades",
            "subcategory":"Construction",
            "type":"Services"
        }
    ],
    "sg:phone":"+1 845 794 1939",
    "sg:postcode":"12783",
    "sg:province":"NY",
    "sg:tags":[
        "house"
    ],
    "wof:name":"Northern Contracting",
    "wof:placetype":"venue"
},
  "geometry": {"coordinates":[-74.812781,41.741613],"type":"Point"}
}