{
  "type": "Feature",
  "properties": {
    "addr:full":"599 Lexington Ave New York NY 10022",
    "addr:housenumber":"599",
    "addr:postcode":"10022",
    "addr:street":"Lexington Ave",
    "iso:country":"US",
    "sg:address":"599 Lexington Ave",
    "sg:city":"New York",
    "sg:classifiers":[
        {
            "category":"Professional",
            "subcategory":"Lawyer & Legal Services",
            "type":"Services"
        }
    ],
    "sg:phone":"+1 212 549 0250",
    "sg:postcode":"10022",
    "sg:province":"NY",
    "sg:tags":[
        "attorney"
    ],
    "wof:name":"Cheryl A Mitchell Attorney",
    "wof:placetype":"venue"
},
  "geometry": {"coordinates":[-73.970997,40.758212],"type":"Point"}
}