{
  "type": "Feature",
  "properties": {
    "addr:full":"2016 Quaker Ridge Rd Croton On Hudson NY 10520",
    "addr:housenumber":"2016",
    "addr:postcode":"10520",
    "addr:street":"Quaker Ridge Rd",
    "iso:country":"US",
    "sg:address":"2016 Quaker Ridge Rd",
    "sg:city":"Croton On Hudson",
    "sg:classifiers":[
        {
            "category":"Wholesale",
            "subcategory":"Farm Supplies",
            "type":"Manufacturing & Wholesale Goods"
        }
    ],
    "sg:phone":"+1 914 923 1283",
    "sg:postcode":"10520",
    "sg:province":"NY",
    "sg:tags":[
        "bulb",
        "seed"
    ],
    "wof:name":"Johnathan Green Inc",
    "wof:placetype":"venue"
},
  "geometry": {"coordinates":[-73.865578,41.200738],"type":"Point"}
}