{
  "type": "Feature",
  "properties": {
    "iso:country":"US",
    "sg:address":"10 Mill St",
    "sg:city":"Mt Morris",
    "sg:classifiers":[
        {
            "category":"Restaurant",
            "type":"Food & Drink"
        }
    ],
    "sg:phone":"+1 585 658 9470",
    "sg:postcode":"14510",
    "sg:province":"NY",
    "wof:name":"Mills Race Restaurant",
    "wof:placetype":"venue"
},
  "geometry": {"coordinates":[-77.871247,42.726808],"type":"Point"}
}