{
  "type": "Feature",
  "properties": {
    "addr:full":"37 Massapequa Ave Massapequa NY 11758",
    "addr:housenumber":"37",
    "addr:postcode":"11758",
    "addr:street":"Massapequa Ave",
    "iso:country":"US",
    "sg:address":"37 Massapequa Ave",
    "sg:city":"Massapequa",
    "sg:classifiers":[
        {
            "category":"Home & Garden",
            "subcategory":"Garden Supply",
            "type":"Retail Goods"
        }
    ],
    "sg:phone":"+1 516 541 2182",
    "sg:postcode":"11758",
    "sg:province":"NY",
    "sg:tags":[
        "sprinkler"
    ],
    "wof:name":"Mark's Sprinkler Svc",
    "wof:placetype":"venue"
},
  "geometry": {"coordinates":[-73.47559200000001,40.6555],"type":"Point"}
}