{
  "type": "Feature",
  "properties": {
    "addr:full":"4 Weyant Dr Cedarhurst NY 11516",
    "addr:housenumber":"4",
    "addr:postcode":"11516",
    "addr:street":"Weyant Dr",
    "iso:country":"US",
    "sg:address":"4 Weyant Dr",
    "sg:city":"Cedarhurst",
    "sg:classifiers":[
        {
            "category":"Structure",
            "subcategory":"Office Building",
            "type":"Public Place"
        }
    ],
    "sg:phone":"+1 516 569 5661",
    "sg:postcode":"11516",
    "sg:province":"NY",
    "sg:tags":[
        "park"
    ],
    "wof:name":"Waldo Realty",
    "wof:placetype":"venue"
},
  "geometry": {"coordinates":[-73.721507,40.619245],"type":"Point"}
}