{
  "type": "Feature",
  "properties": {
    "addr:full":"1319 146th Pl Whitestone NY 11357",
    "addr:housenumber":"1319",
    "addr:postcode":"11357",
    "addr:street":"146Th Pl",
    "iso:country":"US",
    "sg:address":"1319 146th Pl",
    "sg:city":"Whitestone",
    "sg:classifiers":[
        {
            "category":"Professional",
            "subcategory":"Advertising",
            "type":"Services"
        }
    ],
    "sg:phone":"+1 646 593 2026",
    "sg:postcode":"11357",
    "sg:province":"NY",
    "sg:tags":[
        "mail",
        "direct"
    ],
    "wof:name":"Direct Mail Labor Service",
    "wof:placetype":"venue"
},
  "geometry": {"coordinates":[-73.81950399999999,40.784674],"type":"Point"}
}