{
  "type": "Feature",
  "properties": {
    "iso:country":"US",
    "sg:address":"782 Donlon Ave",
    "sg:city":"West Hempstead",
    "sg:classifiers":[
        {
            "category":"Professional",
            "subcategory":"Management & Consulting",
            "type":"Services"
        }
    ],
    "sg:phone":"+1 516 292 2194",
    "sg:postcode":"11552",
    "sg:province":"NY",
    "wof:name":"Gomez Management LLC",
    "wof:placetype":"venue"
},
  "geometry": {"coordinates":[-73.654753,40.684129],"type":"Point"}
}