{
  "type": "Feature",
  "properties": {
    "iso:country":"US",
    "sg:address":"20 Randall Ave",
    "sg:city":"Freeport",
    "sg:classifiers":[
        {
            "category":"Professional",
            "subcategory":"Business Services",
            "type":"Services"
        }
    ],
    "sg:phone":"+1 516 868 8325",
    "sg:postcode":"11520",
    "sg:province":"NY",
    "sg:tags":[
        "plant",
        "design",
        "maintenance"
    ],
    "wof:name":"Interior Plant Contractors",
    "wof:placetype":"venue"
},
  "geometry": {"coordinates":[-73.585829,40.659906],"type":"Point"}
}