{
  "type": "Feature",
  "properties": {
    "addr:full":"3812 20th Ave  Astoria NY 11105",
    "addr:housenumber":"3812",
    "addr:postcode":"11105",
    "addr:street":"20Th Ave",
    "iso:country":"US",
    "sg:address":"3812 20th Ave ",
    "sg:city":"Astoria",
    "sg:classifiers":[
        {
            "category":"Coffee & Tea",
            "type":"Food & Drink"
        }
    ],
    "sg:menulink":"http://www.allmenus.com/ny/queens/291526-mikes-coffee-shop/menu/",
    "sg:phone":"+1 718 278 6652",
    "sg:postcode":"11105",
    "sg:province":"NY",
    "wof:name":"Mike's Coffee Shop",
    "wof:placetype":"venue"
},
  "geometry": {"coordinates":[-73.90235199999999,40.776774],"type":"Point"}
}