{
  "type": "Feature",
  "properties": {
    "iso:country":"US",
    "sg:address":"621 Madison Ave",
    "sg:city":"New York",
    "sg:classifiers":[
        {
            "category":"Shopping",
            "subcategory":"Clothing, Apparel, & Fashions",
            "type":"Retail Goods"
        }
    ],
    "sg:postcode":"10079",
    "sg:province":"NY",
    "sg:tags":[
        "clothing",
        "women's"
    ],
    "sg:website":"www.eres.fr",
    "wof:name":"Eres",
    "wof:placetype":"venue"
},
  "geometry": {"coordinates":[-73.971476,40.763476],"type":"Point"}
}