{
  "type": "Feature",
  "properties": {
    "iso:country":"US",
    "sg:address":"303 5th Ave",
    "sg:city":"New York",
    "sg:classifiers":[
        {
            "category":"Retail",
            "subcategory":"Repair Shop",
            "type":"Services"
        },
        {
            "category":"Building & Trades",
            "subcategory":"Plumbing",
            "type":"Services"
        }
    ],
    "sg:phone":"+1 212 481 7806",
    "sg:postcode":"10016",
    "sg:province":"NY",
    "sg:tags":[
        "conditioning",
        "air",
        "refrigeration",
        "system",
        "contractor"
    ],
    "sg:website":"www.arielair.com",
    "wof:name":"Ariel Air Co Inc",
    "wof:placetype":"venue"
},
  "geometry": {"coordinates":[-73.985473,40.747039],"type":"Point"}
}