{
  "type": "Feature",
  "properties": {
    "iso:country":"US",
    "sg:address":"1203 Grand Ave",
    "sg:city":"North Baldwin",
    "sg:classifiers":[
        {
            "category":"Fast Food",
            "type":"Food & Drink"
        }
    ],
    "sg:phone":"+1 516 505 0909",
    "sg:postcode":"11510",
    "sg:province":"NY",
    "sg:tags":[
        "chicken",
        "wing"
    ],
    "wof:name":"Chicken Holiday",
    "wof:placetype":"venue"
},
  "geometry": {"coordinates":[-73.614774,40.680907],"type":"Point"}
}