{
  "type": "Feature",
  "properties": {
    "addr:full":"199 Old Quarry Rd Feura Bush NY 12067",
    "addr:housenumber":"199",
    "addr:postcode":"12067",
    "addr:street":"Old Quarry Rd;Bush",
    "iso:country":"US",
    "sg:address":"199 Old Quarry Rd",
    "sg:city":"Feura Bush",
    "sg:classifiers":[
        {
            "category":"Communications",
            "type":"Services"
        }
    ],
    "sg:phone":"+1 518 767 0522",
    "sg:postcode":"12067",
    "sg:province":"NY",
    "wof:name":"Galaxy Communications",
    "wof:placetype":"venue"
},
  "geometry": {"coordinates":[-73.86196099999999,42.560254],"type":"Point"}
}