{
  "type": "Feature",
  "properties": {
    "addr:full":"86 Eldridge St New York NY 10002",
    "addr:housenumber":"86",
    "addr:postcode":"10002",
    "addr:street":"Eldridge St",
    "iso:country":"US",
    "sg:address":"86 Eldridge St",
    "sg:city":"New York",
    "sg:classifiers":[
        {
            "category":"Professional",
            "subcategory":"Business Services",
            "type":"Services"
        }
    ],
    "sg:phone":"+1   ",
    "sg:postcode":"10002",
    "sg:province":"NY",
    "wof:name":"Liu De Construction",
    "wof:placetype":"venue"
},
  "geometry": {"coordinates":[-73.992445,40.716867],"type":"Point"}
}