{
  "type": "Feature",
  "properties": {
    "iso:country":"US",
    "sg:address":"595 Montauk Hwy",
    "sg:city":"Copiague",
    "sg:classifiers":[
        {
            "category":"Autos & Motor Vehicles",
            "subcategory":"Auto Supplies",
            "type":"Retail Goods"
        }
    ],
    "sg:phone":"+1   ",
    "sg:postcode":"11726",
    "sg:province":"NY",
    "wof:name":"Apoc Automotive",
    "wof:placetype":"venue"
},
  "geometry": {"coordinates":[-73.40025799999999,40.667783],"type":"Point"}
}