{
  "type": "Feature",
  "properties": {
    "addr:full":"44 N Division St Peekskill NY 10566",
    "addr:housenumber":"44",
    "addr:postcode":"10566",
    "addr:street":"N Division St",
    "iso:country":"US",
    "sg:address":"44 N Division St",
    "sg:city":"Peekskill",
    "sg:classifiers":[
        {
            "category":"Museum",
            "type":"Entertainment"
        }
    ],
    "sg:phone":"+1   ",
    "sg:postcode":"10566",
    "sg:province":"NY",
    "sg:tags":[
        "gallery",
        "merchandise"
    ],
    "wof:name":"Driftwood Gallery-Studio",
    "wof:placetype":"venue"
},
  "geometry": {"coordinates":[-73.920016,41.291277],"type":"Point"}
}