{
  "type": "Feature",
  "properties": {
    "addr:full":"504 Vine St Liverpool NY 13088",
    "addr:housenumber":"504",
    "addr:postcode":"13088",
    "addr:street":"Vine St",
    "iso:country":"US",
    "sg:address":"504 Vine St",
    "sg:city":"Liverpool",
    "sg:classifiers":[
        {
            "category":"Professional",
            "subcategory":"Business Services",
            "type":"Services"
        }
    ],
    "sg:phone":"+1 315 457 8980",
    "sg:postcode":"13088",
    "sg:province":"NY",
    "sg:tags":[
        "arbitration"
    ],
    "wof:name":"Mediation Associates-Liverpool",
    "wof:placetype":"venue"
},
  "geometry": {"coordinates":[-76.20513,43.104176],"type":"Point"}
}