{
  "type": "Feature",
  "properties": {
    "iso:country":"US",
    "sg:address":"104 Crosier Rd",
    "sg:city":"Salem",
    "sg:classifiers":[
        {
            "category":"Manufacturing",
            "subcategory":"Tools & Machinery",
            "type":"Manufacturing & Wholesale Goods"
        }
    ],
    "sg:phone":"+1   ",
    "sg:postcode":"12865",
    "sg:province":"NY",
    "sg:tags":[
        "machine",
        "mfg"
    ],
    "wof:name":"Gac Machine Co",
    "wof:placetype":"venue"
},
  "geometry": {"coordinates":[-73.383081,43.277831],"type":"Point"}
}