{
  "type": "Feature",
  "properties": {
    "addr:full":"3530 Francis Lewis Blvd Flushing NY 11358",
    "addr:housenumber":"3530",
    "addr:postcode":"11358",
    "addr:street":"Francis Lewis Blvd",
    "iso:country":"US",
    "sg:address":"3530 Francis Lewis Blvd",
    "sg:city":"Flushing",
    "sg:classifiers":[
        {
            "category":"Insurance",
            "subcategory":"Hazard Insurance",
            "type":"Services"
        },
        {
            "category":"Insurance",
            "subcategory":"Insurance Agent",
            "type":"Services"
        },
        {
            "category":"Insurance",
            "subcategory":"Life Insurance",
            "type":"Services"
        },
        {
            "category":"Insurance",
            "subcategory":"Title Insurance",
            "type":"Services"
        }
    ],
    "sg:phone":"+1 718 886 5151",
    "sg:postcode":"11358",
    "sg:province":"NY",
    "sg:tags":[
        "auto",
        "homeowner"
    ],
    "sg:website":"http://www.nationwide.com/agent/Flushing-NEW-YORK-insurance-agent/schneideragency/office.html",
    "wof:name":"Harry Schneider - Nationwide Insurance",
    "wof:placetype":"venue"
},
  "geometry": {"coordinates":[-73.789845,40.766565],"type":"Point"}
}