{
  "type": "Feature",
  "properties": {
    "iso:country":"US",
    "sg:address":"124 Oregon Rd",
    "sg:city":"Cortlandt Manor",
    "sg:classifiers":[
        {
            "category":"Organizations",
            "subcategory":"Religious Organization",
            "type":"Services"
        }
    ],
    "sg:phone":"+1 914 737 4705",
    "sg:postcode":"10567",
    "sg:province":"NY",
    "sg:tags":[
        "church"
    ],
    "wof:name":"St Columbanus Church",
    "wof:placetype":"venue"
},
  "geometry": {"coordinates":[-73.90163800000001,41.313619],"type":"Point"}
}