{
  "type": "Feature",
  "properties": {
    "iso:country":"US",
    "sg:address":"112 Windsor Ter",
    "sg:city":"Salisbury Mills",
    "sg:classifiers":[
        {
            "category":"Professional",
            "subcategory":"Business Services",
            "type":"Services"
        }
    ],
    "sg:phone":"+1 845 496 9543",
    "sg:postcode":"12577",
    "sg:province":"NY",
    "wof:name":"Gal Friday Office Services",
    "wof:placetype":"venue"
},
  "geometry": {"coordinates":[-74.120063,41.450021],"type":"Point"}
}