{
  "type": "Feature",
  "properties": {
    "addr:full":"163 22nd St Brooklyn NY 11232",
    "addr:housenumber":"163",
    "addr:postcode":"11232",
    "addr:street":"22Nd St",
    "iso:country":"US",
    "sg:address":"163 22nd St",
    "sg:city":"Brooklyn",
    "sg:classifiers":[
        {
            "category":"Building & Trades",
            "subcategory":"Construction",
            "type":"Services"
        }
    ],
    "sg:phone":"+1 718 788 5447",
    "sg:postcode":"11232",
    "sg:province":"NY",
    "sg:tags":[
        "roofing",
        "contractor"
    ],
    "wof:name":"BBR Contracting",
    "wof:placetype":"venue"
},
  "geometry": {"coordinates":[-73.99735699999999,40.663114],"type":"Point"}
}