{
  "type": "Feature",
  "properties": {
    "addr:full":"3 Cabot Ave Elmsford NY 10523",
    "addr:housenumber":"3",
    "addr:postcode":"10523",
    "addr:street":"Cabot Ave",
    "iso:country":"US",
    "sg:address":"3 Cabot Ave",
    "sg:city":"Elmsford",
    "sg:classifiers":[
        {
            "category":"Building & Trades",
            "subcategory":"Construction",
            "type":"Services"
        }
    ],
    "sg:phone":"+1 914 592 6338",
    "sg:postcode":"10523",
    "sg:province":"NY",
    "sg:tags":[
        "general",
        "contractor"
    ],
    "wof:name":"Fairview Contracting Corp",
    "wof:placetype":"venue"
},
  "geometry": {"coordinates":[-73.810709,41.059196],"type":"Point"}
}