{
  "type": "Feature",
  "properties": {
    "addr:full":"21 Ludwig Ave Buffalo NY 14227",
    "addr:housenumber":"21",
    "addr:postcode":"14227",
    "addr:street":"Ludwig Ave",
    "iso:country":"US",
    "sg:address":"21 Ludwig Ave",
    "sg:city":"Buffalo",
    "sg:classifiers":[
        {
            "category":"Building & Trades",
            "subcategory":"Construction",
            "type":"Services"
        }
    ],
    "sg:phone":"+1 716 895 6272",
    "sg:postcode":"14227",
    "sg:province":"NY",
    "sg:tags":[
        "contractor"
    ],
    "wof:name":"Calabrese General Contracting",
    "wof:placetype":"venue"
},
  "geometry": {"coordinates":[-78.766766,42.886699],"type":"Point"}
}