{
  "type": "Feature",
  "properties": {
    "iso:country":"US",
    "sg:address":"10 Mountain Rise",
    "sg:city":"Fairport",
    "sg:classifiers":[
        {
            "category":"Professional",
            "subcategory":"Computer Services",
            "type":"Services"
        }
    ],
    "sg:phone":"+1 585 223 5460",
    "sg:postcode":"14450",
    "sg:province":"NY",
    "wof:name":"Denver Solutions Group",
    "wof:placetype":"venue"
},
  "geometry": {"coordinates":[-77.45888100000001,43.068478],"type":"Point"}
}