{
  "type": "Feature",
  "properties": {
    "addr:full":"25 Rowland St Ballston Spa NY 12020",
    "addr:housenumber":"25",
    "addr:postcode":"12020",
    "addr:street":"Rowland St",
    "iso:country":"US",
    "sg:address":"25 Rowland St",
    "sg:city":"Ballston Spa",
    "sg:classifiers":[
        {
            "category":"Shopping",
            "type":"Retail Goods"
        }
    ],
    "sg:phone":"+1 518 885 3538",
    "sg:postcode":"12020",
    "sg:province":"NY",
    "sg:tags":[
        "candle"
    ],
    "wof:name":"Country Candles",
    "wof:placetype":"venue"
},
  "geometry": {"coordinates":[-73.848862,43.013941],"type":"Point"}
}