{
  "type": "Feature",
  "properties": {
    "addr:full":"17420 142nd Ave Jamaica NY 11434",
    "addr:housenumber":"17420",
    "addr:postcode":"11434",
    "addr:street":"142Nd Ave",
    "iso:country":"US",
    "sg:address":"17420 142nd Ave",
    "sg:city":"Jamaica",
    "sg:classifiers":[
        {
            "category":"Professional",
            "subcategory":"Testing Lab",
            "type":"Services"
        },
        {
            "category":"Building & Trades",
            "subcategory":"Construction",
            "type":"Services"
        }
    ],
    "sg:phone":"+1 718 213 4841",
    "sg:postcode":"11434",
    "sg:province":"NY",
    "sg:tags":[
        "asbestos",
        "detection",
        "consulting",
        "contractor",
        "removal"
    ],
    "wof:name":"Bizpivot International",
    "wof:placetype":"venue"
},
  "geometry": {"coordinates":[-73.76616300000001,40.670516],"type":"Point"}
}