{
  "type": "Feature",
  "properties": {
    "addr:full":"116 Chambers St New York NY 10007",
    "addr:housenumber":"116",
    "addr:postcode":"10007",
    "addr:street":"Chambers St",
    "iso:country":"US",
    "sg:address":"116 Chambers St",
    "sg:city":"New York",
    "sg:classifiers":[
        {
            "category":"Professional",
            "subcategory":"Art Services",
            "type":"Services"
        }
    ],
    "sg:phone":"+1   ",
    "sg:postcode":"10007",
    "sg:province":"NY",
    "sg:tags":[
        "commercial",
        "design"
    ],
    "wof:name":"RE Creative LLC",
    "wof:placetype":"venue"
},
  "geometry": {"coordinates":[-74.008949,40.715258],"type":"Point"}
}