{
  "type": "Feature",
  "properties": {
    "addr:full":"160 W End Avenue New York NY 10023",
    "addr:housenumber":"160",
    "addr:postcode":"10023",
    "addr:street":"W End Avenue",
    "iso:country":"US",
    "sg:address":"160 W End Avenue",
    "sg:city":"New York",
    "sg:classifiers":[
        {
            "category":"Health Services",
            "subcategory":"Health Practitioner",
            "type":"Services"
        }
    ],
    "sg:phone":"+1 212 496 5703",
    "sg:postcode":"10023",
    "sg:province":"NY",
    "sg:tags":[
        "therapy",
        "physical"
    ],
    "wof:name":"Feldenkrais Method",
    "wof:placetype":"venue"
},
  "geometry": {"coordinates":[-73.98660099999999,40.77691],"type":"Point"}
}