{
  "type": "Feature",
  "properties": {
    "addr:full":"777 W End Ave New York NY 10025",
    "addr:housenumber":"777",
    "addr:postcode":"10025",
    "addr:street":"W End Ave",
    "iso:country":"US",
    "sg:address":"777 W End Ave",
    "sg:city":"New York",
    "sg:classifiers":[
        {
            "category":"Organizations",
            "subcategory":"Membership Organization",
            "type":"Services"
        }
    ],
    "sg:phone":"+1 212 222 6487",
    "sg:postcode":"10025",
    "sg:province":"NY",
    "sg:tags":[
        "jewish",
        "record",
        "american",
        "music",
        "archive"
    ],
    "wof:name":"Milken Archves Amrcn Jwish Mus",
    "wof:placetype":"venue"
},
  "geometry": {"coordinates":[-73.972717,40.795929],"type":"Point"}
}