{
  "type": "Feature",
  "properties": {
    "iso:country":"US",
    "sg:address":"448 Middle Country Rd",
    "sg:city":"Selden",
    "sg:classifiers":[
        {
            "category":"Personal",
            "subcategory":"Beauty Salon",
            "type":"Services"
        }
    ],
    "sg:phone":"+1 631 698 3966",
    "sg:postcode":"11784",
    "sg:province":"NY",
    "sg:tags":[
        "shop"
    ],
    "wof:name":"Best Nails",
    "wof:placetype":"venue"
},
  "geometry": {"coordinates":[-73.03054,40.867197],"type":"Point"}
}