{
  "type": "Feature",
  "properties": {
    "iso:country":"US",
    "sg:address":"616 Ave Y",
    "sg:city":"Brooklyn",
    "sg:classifiers":[
        {
            "category":"Wholesale",
            "subcategory":"Electrical",
            "type":"Manufacturing & Wholesale Goods"
        }
    ],
    "sg:phone":"+1 718 787 0674",
    "sg:postcode":"11235",
    "sg:province":"NY",
    "sg:tags":[
        "control",
        "security",
        "system"
    ],
    "wof:name":"S & Y Comm Security Svc",
    "wof:placetype":"venue"
},
  "geometry": {"coordinates":[-73.963812,40.588998],"type":"Point"}
}