{
  "type": "Feature",
  "properties": {
    "addr:full":"210 Lafayette St New York NY 10012",
    "addr:housenumber":"210",
    "addr:postcode":"10012",
    "addr:street":"Lafayette St",
    "iso:country":"US",
    "sg:address":"210 Lafayette St",
    "sg:city":"New York",
    "sg:classifiers":[
        {
            "category":"Home & Garden",
            "subcategory":"Furniture",
            "type":"Retail Goods"
        }
    ],
    "sg:phone":"+1 212 431 2575",
    "sg:postcode":"10012",
    "sg:province":"NY",
    "sg:tags":[
        "store"
    ],
    "sg:website":"www.mitchellgold.com/",
    "wof:name":"Mitchell Gold & Bob Williams",
    "wof:placetype":"venue"
},
  "geometry": {"coordinates":[-73.99771200000001,40.721653],"type":"Point"}
}