{
  "type": "Feature",
  "properties": {
    "iso:country":"US",
    "sg:address":"2755 27th St",
    "sg:city":"Niagara Falls",
    "sg:classifiers":[
        {
            "category":"Manufacturing",
            "subcategory":"Tools & Machinery",
            "type":"Manufacturing & Wholesale Goods"
        }
    ],
    "sg:phone":"+1   ",
    "sg:postcode":"14305",
    "sg:province":"NY",
    "sg:tags":[
        "machinist",
        "precision",
        "for",
        "mfg"
    ],
    "wof:name":"TEK Machine Inc",
    "wof:placetype":"venue"
},
  "geometry": {"coordinates":[-79.030117,43.114044],"type":"Point"}
}