{
  "type": "Feature",
  "properties": {
    "iso:country":"US",
    "sg:address":"189 N Water St",
    "sg:city":"Rochester",
    "sg:classifiers":[
        {
            "category":"Professional",
            "subcategory":"Advertising",
            "type":"Services"
        }
    ],
    "sg:phone":"+1 585 262 6030",
    "sg:postcode":"14604",
    "sg:province":"NY",
    "sg:tags":[
        "counselor"
    ],
    "sg:website":"www.normalcommunications.com",
    "wof:name":"Normal Communications",
    "wof:placetype":"venue"
},
  "geometry": {"coordinates":[-77.612084,43.160846],"type":"Point"}
}