{
  "type": "Feature",
  "properties": {
    "iso:country":"US",
    "sg:address":"2 Welsley Ln",
    "sg:city":"Smithtown",
    "sg:classifiers":[
        {
            "category":"Health Services",
            "subcategory":"Chiropractor",
            "type":"Services"
        }
    ],
    "sg:phone":"+1 631 724 5818",
    "sg:postcode":"11787",
    "sg:province":"NY",
    "wof:name":"Faillace Chiropractic",
    "wof:placetype":"venue"
},
  "geometry": {"coordinates":[-73.19349,40.833186],"type":"Point"}
}