{
  "type": "Feature",
  "properties": {
    "addr:full":"720 Hoosick Rd Ste 5 Troy NY 12180",
    "addr:housenumber":"720",
    "addr:postcode":"12180",
    "addr:street":"Hoosick Rd Ste 5",
    "iso:country":"US",
    "sg:address":"720 Hoosick Rd Ste 5",
    "sg:city":"Troy",
    "sg:classifiers":[
        {
            "category":"Banks & Credit Unions",
            "subcategory":"Bank",
            "type":"Services"
        },
        {
            "category":"Banks & Credit Unions",
            "subcategory":"Financial Services",
            "type":"Services"
        }
    ],
    "sg:phone":"+1 518 273 2400",
    "sg:postcode":"12180",
    "sg:province":"NY",
    "sg:tags":[
        "saving",
        "loan",
        "commercial"
    ],
    "sg:website":"http://www.key.com",
    "wof:name":"Keybank National Association",
    "wof:placetype":"venue"
},
  "geometry": {"coordinates":[-73.64417299999999,42.744228],"type":"Point"}
}