{
  "type": "Feature",
  "properties": {
    "iso:country":"US",
    "sg:address":"12 Plaza Dr",
    "sg:city":"Monticello",
    "sg:classifiers":[
        {
            "category":"Autos & Motor Vehicles",
            "subcategory":"Automobile Sales",
            "type":"Retail Goods"
        },
        {
            "category":"Retail",
            "subcategory":"Auto Rental",
            "type":"Services"
        },
        {
            "category":"Building & Trades",
            "subcategory":"Equipment Rental",
            "type":"Services"
        }
    ],
    "sg:phone":"+1 845 794 2785",
    "sg:postcode":"12701",
    "sg:province":"NY",
    "sg:tags":[
        "truck",
        "used",
        "moving"
    ],
    "sg:website":"http://budgettruck.com/IYP_tl",
    "wof:name":"Rental Operations Inc DBA/Budget Truck Rental",
    "wof:placetype":"venue"
},
  "geometry": {"coordinates":[-74.653797,41.644867],"type":"Point"}
}