{
  "type": "Feature",
  "properties": {
    "iso:country":"US",
    "sg:address":"231 N Union St",
    "sg:city":"Olean",
    "sg:classifiers":[
        {
            "category":"Communications",
            "subcategory":"Radio Station",
            "type":"Services"
        }
    ],
    "sg:phone":"+1 716 375 1015",
    "sg:postcode":"14760",
    "sg:province":"NY",
    "sg:tags":[
        "company",
        "broadcasting"
    ],
    "sg:website":"www.mix1015online.com",
    "wof:name":"WMXO",
    "wof:placetype":"venue"
},
  "geometry": {"coordinates":[-78.429976,42.081214],"type":"Point"}
}