{
  "type": "Feature",
  "properties": {
    "iso:country":"US",
    "sg:address":"1675 Flatbush Ave",
    "sg:city":"Brooklyn",
    "sg:classifiers":[
        {
            "category":"Restaurant",
            "type":"Food & Drink"
        }
    ],
    "sg:phone":"+1   ",
    "sg:postcode":"11210",
    "sg:province":"NY",
    "sg:tags":[
        "eating"
    ],
    "wof:name":"Hope Good Jamaican Restaurant",
    "wof:placetype":"venue"
},
  "geometry": {"coordinates":[-73.943331,40.62873],"type":"Point"}
}