{
  "type": "Feature",
  "properties": {
    "iso:country":"US",
    "sg:address":"181 Clinton St",
    "sg:city":"New York",
    "sg:classifiers":[
        {
            "category":"Restaurant",
            "type":"Food & Drink"
        }
    ],
    "sg:phone":"+1 212 420 1328",
    "sg:postcode":"10002",
    "sg:province":"NY",
    "sg:tags":[
        "out"
    ],
    "wof:name":"May May Kitchen",
    "wof:placetype":"venue"
},
  "geometry": {"coordinates":[-73.98694,40.715774],"type":"Point"}
}