{
  "type": "Feature",
  "properties": {
    "addr:full":"1865 Commerce St Yorktown Heights NY 10598",
    "addr:housenumber":"1865",
    "addr:postcode":"10598",
    "addr:street":"Commerce St",
    "iso:country":"US",
    "sg:address":"1865 Commerce St",
    "sg:city":"Yorktown Heights",
    "sg:classifiers":[
        {
            "category":"Retail",
            "subcategory":"Veterinary Services",
            "type":"Services"
        }
    ],
    "sg:phone":"+1 914 962 5579",
    "sg:postcode":"10598",
    "sg:province":"NY",
    "sg:tags":[
        "hospital",
        "animal"
    ],
    "wof:name":"Heights Hospital For Animals",
    "wof:placetype":"venue"
},
  "geometry": {"coordinates":[-73.780484,41.271462],"type":"Point"}
}