{
  "type": "Feature",
  "properties": {
    "iso:country":"US",
    "sg:address":"125 Main St",
    "sg:city":"Nyack",
    "sg:classifiers":[
        {
            "category":"Shopping",
            "type":"Retail Goods"
        },
        {
            "category":"Home & Garden",
            "subcategory":"Home Furnishings",
            "type":"Retail Goods"
        }
    ],
    "sg:phone":"+1 845 358 7979",
    "sg:postcode":"10960",
    "sg:province":"NY",
    "sg:tags":[
        "art",
        "gallery",
        "merchandise",
        "dealer"
    ],
    "wof:name":"Burd House Gallery Frame Shop",
    "wof:placetype":"venue"
},
  "geometry": {"coordinates":[-73.92016099999999,41.091311],"type":"Point"}
}