{
  "type": "Feature",
  "properties": {
    "iso:country":"US",
    "sg:address":"1350 Deer Park Ave",
    "sg:city":"North Babylon",
    "sg:classifiers":[
        {
            "category":"Health Services",
            "subcategory":"Chiropractor",
            "type":"Services"
        }
    ],
    "sg:phone":"+1   ",
    "sg:postcode":"11703",
    "sg:province":"NY",
    "wof:name":"Christopher Whyte",
    "wof:placetype":"venue"
},
  "geometry": {"coordinates":[-73.322361,40.74388],"type":"Point"}
}