{
  "type": "Feature",
  "properties": {
    "addr:full":"19 Boulevard New Rochelle NY 10801",
    "addr:housenumber":"19",
    "addr:postcode":"10801",
    "addr:street":"Boulevard",
    "iso:country":"US",
    "sg:address":"19 Boulevard",
    "sg:city":"New Rochelle",
    "sg:classifiers":[
        {
            "category":"Organizations",
            "subcategory":"Community Association",
            "type":"Services"
        }
    ],
    "sg:phone":"+1   ",
    "sg:postcode":"10801",
    "sg:province":"NY",
    "wof:name":"Elks B P O No 756",
    "wof:placetype":"venue"
},
  "geometry": {"coordinates":[-73.782462,40.918992],"type":"Point"}
}