{
  "type": "Feature",
  "properties": {
    "iso:country":"US",
    "sg:address":"4110 Bowne Street Apt 2L",
    "sg:city":"Flushing",
    "sg:classifiers":[
        {
            "category":"Health Services",
            "subcategory":"Doctor",
            "type":"Services"
        }
    ],
    "sg:phone":"+1 718 353 4855",
    "sg:postcode":"11355",
    "sg:province":"NY",
    "wof:name":"Kim Kee Y MD",
    "wof:placetype":"venue"
},
  "geometry": {"coordinates":[-73.82383400000001,40.759618],"type":"Point"}
}