{
  "type": "Feature",
  "properties": {
    "iso:country":"US",
    "sg:address":"8902 Co Rd 46",
    "sg:city":"Arkport",
    "sg:classifiers":[
        {
            "category":"Building & Trades",
            "subcategory":"Plumbing",
            "type":"Services"
        }
    ],
    "sg:phone":"+1 607 324 9747",
    "sg:postcode":"14807",
    "sg:province":"NY",
    "sg:tags":[
        "contractor",
        "conditioning",
        "solar",
        "heating"
    ],
    "wof:name":"Four Winds Renewable Energy Co",
    "wof:placetype":"venue"
},
  "geometry": {"coordinates":[-77.644803,42.44229],"type":"Point"}
}