{
  "type": "Feature",
  "properties": {
    "addr:full":"290 5th Ave New Rochelle NY 10801",
    "addr:housenumber":"290",
    "addr:postcode":"10801",
    "addr:street":"5Th Ave",
    "iso:country":"US",
    "sg:address":"290 5th Ave",
    "sg:city":"New Rochelle",
    "sg:classifiers":[
        {
            "category":"Shopping",
            "type":"Retail Goods"
        }
    ],
    "sg:phone":"+1   ",
    "sg:postcode":"10801",
    "sg:province":"NY",
    "sg:tags":[
        "trophy",
        "engraves"
    ],
    "wof:name":"R & F Trophies",
    "wof:placetype":"venue"
},
  "geometry": {"coordinates":[-73.778243,40.927513],"type":"Point"}
}