{
  "type": "Feature",
  "properties": {
    "addr:full":"945 Courtland Ave Bronx NY 10451",
    "addr:housenumber":"945",
    "addr:postcode":"10451",
    "addr:street":"Courtland Ave",
    "iso:country":"US",
    "sg:address":"945 Courtland Ave",
    "sg:city":"Bronx",
    "sg:classifiers":[
        {
            "category":"Freight",
            "type":"Transportation"
        }
    ],
    "sg:phone":"+1   ",
    "sg:postcode":"10451",
    "sg:province":"NY",
    "sg:tags":[
        "operator",
        "local",
        "trucking"
    ],
    "wof:name":"Metro Van Lines Inc",
    "wof:placetype":"venue"
},
  "geometry": {"coordinates":[-73.914751,40.825201],"type":"Point"}
}