{
  "type": "Feature",
  "properties": {
    "addr:full":"6503 Cleary Rd Avon NY 14414",
    "addr:housenumber":"6503",
    "addr:postcode":"14414",
    "addr:street":"Cleary Rd",
    "iso:country":"US",
    "sg:address":"6503 Cleary Rd",
    "sg:city":"Avon",
    "sg:classifiers":[
        {
            "category":"Building & Trades",
            "subcategory":"Construction",
            "type":"Services"
        }
    ],
    "sg:phone":"+1 585 624 8240",
    "sg:postcode":"14414",
    "sg:province":"NY",
    "sg:tags":[
        "house",
        "general",
        "contractor"
    ],
    "wof:name":"Koch Brothers Constructors LLC",
    "wof:placetype":"venue"
},
  "geometry": {"coordinates":[-77.661053,42.887876],"type":"Point"}
}