{
  "type": "Feature",
  "properties": {
    "addr:full":"6684 Pickard Dr Syracuse NY 13211",
    "addr:housenumber":"6684",
    "addr:postcode":"13211",
    "addr:street":"Pickard Dr",
    "iso:country":"US",
    "sg:address":"6684 Pickard Dr",
    "sg:city":"Syracuse",
    "sg:classifiers":[
        {
            "category":"Wholesale",
            "subcategory":"Home Furnishings",
            "type":"Manufacturing & Wholesale Goods"
        }
    ],
    "sg:phone":"+1 315 455 1756",
    "sg:postcode":"13211",
    "sg:province":"NY",
    "sg:tags":[
        "picture",
        "frame"
    ],
    "wof:name":"Syracuse Sales LTD",
    "wof:placetype":"venue"
},
  "geometry": {"coordinates":[-76.110519,43.093472],"type":"Point"}
}