{
  "type": "Feature",
  "properties": {
    "iso:country":"US",
    "sg:address":"1780 Monroe Ave",
    "sg:city":"Rochester",
    "sg:classifiers":[
        {
            "category":"Recreation",
            "type":"Entertainment"
        }
    ],
    "sg:phone":"+1 585 461 1070",
    "sg:postcode":"14618",
    "sg:province":"NY",
    "sg:tags":[
        "martial",
        "arts",
        "instruction"
    ],
    "sg:website":"www.selfdefensecenter.com",
    "wof:name":"United Martial Arts Ctr",
    "wof:placetype":"venue"
},
  "geometry": {"coordinates":[-77.566822,43.12858],"type":"Point"}
}