{
  "type": "Feature",
  "properties": {
    "addr:full":"90 Slaughter Rd Middletown NY 10941",
    "addr:housenumber":"90",
    "addr:postcode":"10941",
    "addr:street":"Slaughter Rd",
    "iso:country":"US",
    "sg:address":"90 Slaughter Rd",
    "sg:city":"Middletown",
    "sg:classifiers":[
        {
            "category":"Home & Garden",
            "subcategory":"Garden Supply",
            "type":"Retail Goods"
        }
    ],
    "sg:phone":"+1 845 692 4300",
    "sg:postcode":"10941",
    "sg:province":"NY",
    "sg:tags":[
        "nursery",
        "gardening"
    ],
    "wof:name":"R & M SEED STORE",
    "wof:placetype":"venue"
},
  "geometry": {"coordinates":[-74.331132,41.462006],"type":"Point"}
}