{
  "type": "Feature",
  "properties": {
    "iso:country":"US",
    "sg:address":"137 Dawson Rd",
    "sg:city":"Schenectady",
    "sg:classifiers":[
        {
            "category":"Professional",
            "subcategory":"Management & Consulting",
            "type":"Services"
        }
    ],
    "sg:phone":"+1   ",
    "sg:postcode":"12302",
    "sg:province":"NY",
    "sg:tags":[
        "business"
    ],
    "wof:name":"Handmade For Dogs",
    "wof:placetype":"venue"
},
  "geometry": {"coordinates":[-74.004272,42.924159],"type":"Point"}
}