{
  "type": "Feature",
  "properties": {
    "addr:full":"1454 New York Ave Huntington Station NY 11746",
    "addr:housenumber":"1454",
    "addr:postcode":"11746",
    "addr:street":"New York Ave Huntington",
    "iso:country":"US",
    "sg:address":"1454 New York Ave",
    "sg:city":"Huntington Station",
    "sg:classifiers":[
        {
            "category":"Deli",
            "type":"Food & Drink"
        },
        {
            "category":"Food & Beverages",
            "subcategory":"Bakery",
            "type":"Retail Goods"
        }
    ],
    "sg:phone":"+1 631 271 4058",
    "sg:postcode":"11746",
    "sg:province":"NY",
    "sg:tags":[
        "sandwich"
    ],
    "wof:name":"Mishael Grocery Corp",
    "wof:placetype":"venue"
},
  "geometry": {"coordinates":[-73.41131799999999,40.846887],"type":"Point"}
}