{
  "type": "Feature",
  "properties": {
    "addr:full":"115 Dyckman St New York NY 10040",
    "addr:housenumber":"115",
    "addr:postcode":"10040",
    "addr:street":"Dyckman St",
    "iso:country":"US",
    "sg:address":"115 Dyckman St",
    "sg:city":"New York",
    "sg:classifiers":[
        {
            "category":"Retail",
            "subcategory":"Self-service Laundry",
            "type":"Services"
        }
    ],
    "sg:phone":"+1   ",
    "sg:postcode":"10040",
    "sg:province":"NY",
    "sg:tags":[
        "coin"
    ],
    "wof:name":"115 Dyckman Laundromat Inc",
    "wof:placetype":"venue"
},
  "geometry": {"coordinates":[-73.925037,40.862059],"type":"Point"}
}