{
  "type": "Feature",
  "properties": {
    "addr:full":"107 College Plz Selden NY 11784",
    "addr:housenumber":"107",
    "addr:postcode":"11784",
    "addr:street":"College Plz",
    "iso:country":"US",
    "sg:address":"107 College Plz",
    "sg:city":"Selden",
    "sg:classifiers":[
        {
            "category":"Shopping",
            "subcategory":"Stationery & Office Supplies",
            "type":"Retail Goods"
        },
        {
            "category":"Professional",
            "subcategory":"Printing & Photocopies",
            "type":"Services"
        }
    ],
    "sg:phone":"+1 631 698 1434",
    "sg:postcode":"11784",
    "sg:province":"NY",
    "sg:tags":[
        "equipment"
    ],
    "wof:name":"Staples the Office Superstore",
    "wof:placetype":"venue"
},
  "geometry": {"coordinates":[-73.04679899999999,40.8699],"type":"Point"}
}