{
  "type": "Feature",
  "properties": {
    "iso:country":"US",
    "sg:address":"1583 Albany Ave",
    "sg:city":"Brooklyn",
    "sg:classifiers":[
        {
            "category":"Professional",
            "type":"Services"
        }
    ],
    "sg:phone":"+1 718 421 4600",
    "sg:postcode":"11210",
    "sg:province":"NY",
    "sg:tags":[
        "establishment"
    ],
    "wof:name":"Kenya White & Assoc Pllc",
    "wof:placetype":"venue"
},
  "geometry": {"coordinates":[-73.937078,40.632898],"type":"Point"}
}