{
  "type": "Feature",
  "properties": {
    "addr:full":"10 Medical Plz Glen Cove NY 11542",
    "addr:housenumber":"10",
    "addr:postcode":"11542",
    "addr:street":"Medical Plz",
    "iso:country":"US",
    "sg:address":"10 Medical Plz",
    "sg:city":"Glen Cove",
    "sg:classifiers":[
        {
            "category":"Health Services",
            "subcategory":"Doctor",
            "type":"Services"
        }
    ],
    "sg:phone":"+1 516 674 7906",
    "sg:postcode":"11542",
    "sg:province":"NY",
    "sg:tags":[
        "medical"
    ],
    "wof:name":"North Shore Dis Radiology",
    "wof:placetype":"venue"
},
  "geometry": {"coordinates":[-73.62258799999999,40.874192],"type":"Point"}
}