{
  "type": "Feature",
  "properties": {
    "iso:country":"US",
    "sg:address":"306 4th St",
    "sg:city":"Ithaca",
    "sg:classifiers":[
        {
            "category":"Retail",
            "subcategory":"Photofinishing",
            "type":"Services"
        }
    ],
    "sg:phone":"+1   ",
    "sg:postcode":"14850",
    "sg:province":"NY",
    "sg:tags":[
        "laboratory",
        "suppl"
    ],
    "wof:name":"Cayuga Color Lab",
    "wof:placetype":"venue"
},
  "geometry": {"coordinates":[-76.506833,42.446571],"type":"Point"}
}