{
  "type": "Feature",
  "properties": {
    "iso:country":"US",
    "sg:address":"1 Wedge Way",
    "sg:city":"Suffern",
    "sg:classifiers":[
        {
            "category":"Professional",
            "subcategory":"Management & Consulting",
            "type":"Services"
        }
    ],
    "sg:phone":"+1 845 368 1836",
    "sg:postcode":"10901",
    "sg:province":"NY",
    "wof:name":"Performance Strategies",
    "wof:placetype":"venue"
},
  "geometry": {"coordinates":[-74.103557,41.122498],"type":"Point"}
}