{
  "type": "Feature",
  "properties": {
    "iso:country":"US",
    "sg:address":"1965 Abbott Rd",
    "sg:city":"Buffalo",
    "sg:classifiers":[
        {
            "category":"Recreation",
            "type":"Entertainment"
        }
    ],
    "sg:phone":"+1   ",
    "sg:postcode":"14218",
    "sg:province":"NY",
    "sg:tags":[
        "club",
        "membership",
        "sport",
        "association"
    ],
    "wof:name":"Steel City Vets World War 11",
    "wof:placetype":"venue"
},
  "geometry": {"coordinates":[-78.79952400000001,42.811639],"type":"Point"}
}