{
  "type": "Feature",
  "properties": {
    "iso:country":"US",
    "sg:address":"26 May St",
    "sg:city":"Webster",
    "sg:classifiers":[
        {
            "category":"Home & Garden",
            "subcategory":"Building Materials",
            "type":"Retail Goods"
        },
        {
            "category":"Shopping",
            "subcategory":"Florist",
            "type":"Retail Goods"
        }
    ],
    "sg:phone":"+1 585 872 2090",
    "sg:postcode":"14580",
    "sg:province":"NY",
    "sg:tags":[
        "glass",
        "window",
        "plate"
    ],
    "wof:name":"Flower City Glass Co Inc",
    "wof:placetype":"venue"
},
  "geometry": {"coordinates":[-77.428833,43.21705],"type":"Point"}
}