{
  "type": "Feature",
  "properties": {
    "addr:full":"134 Center Ave Mamaroneck NY 10543",
    "addr:housenumber":"134",
    "addr:postcode":"10543",
    "addr:street":"Center Ave",
    "iso:country":"US",
    "sg:address":"134 Center Ave",
    "sg:city":"Mamaroneck",
    "sg:classifiers":[
        {
            "category":"Professional",
            "subcategory":"Employment Agencies",
            "type":"Services"
        }
    ],
    "sg:phone":"+1   ",
    "sg:postcode":"10543",
    "sg:province":"NY",
    "wof:name":"Employmt Larchmnt & Mamaronack",
    "wof:placetype":"venue"
},
  "geometry": {"coordinates":[-73.74136,40.952332],"type":"Point"}
}