{
  "type": "Feature",
  "properties": {
    "iso:country":"US",
    "sg:address":"32 Beadel St",
    "sg:city":"Brooklyn",
    "sg:classifiers":[
        {
            "category":"Wholesale",
            "subcategory":"Fruits & Vegetables",
            "type":"Manufacturing & Wholesale Goods"
        }
    ],
    "sg:phone":"+1 718 330 1188",
    "sg:postcode":"11222",
    "sg:province":"NY",
    "sg:tags":[
        "veggie"
    ],
    "wof:name":"Son Yeng Produce",
    "wof:placetype":"venue"
},
  "geometry": {"coordinates":[-73.939606,40.721182],"type":"Point"}
}