{
  "type": "Feature",
  "properties": {
    "addr:full":"464 Peabody Rd Gouverneur NY 13642",
    "addr:housenumber":"464",
    "addr:postcode":"13642",
    "addr:street":"Peabody Rd",
    "iso:country":"US",
    "sg:address":"464 Peabody Rd",
    "sg:city":"Gouverneur",
    "sg:classifiers":[
        {
            "category":"Health Services",
            "subcategory":"Doctor",
            "type":"Services"
        }
    ],
    "sg:phone":"+1 315 562 2244",
    "sg:postcode":"13642",
    "sg:province":"NY",
    "sg:tags":[
        "physician",
        "surgeon"
    ],
    "wof:name":"Gail E Dehart MD",
    "wof:placetype":"venue"
},
  "geometry": {"coordinates":[-75.479823,44.3703],"type":"Point"}
}