{
  "type": "Feature",
  "properties": {
    "addr:full":"147 Old Loudon Rd Latham NY 12110",
    "addr:housenumber":"147",
    "addr:postcode":"12110",
    "addr:street":"Old Loudon Rd",
    "iso:country":"US",
    "sg:address":"147 Old Loudon Rd",
    "sg:city":"Latham",
    "sg:classifiers":[
        {
            "category":"Local Transit",
            "type":"Transportation"
        }
    ],
    "sg:phone":"+1   ",
    "sg:postcode":"12110",
    "sg:province":"NY",
    "sg:tags":[
        "passenger"
    ],
    "wof:name":"Supreme Limousine Service",
    "wof:placetype":"venue"
},
  "geometry": {"coordinates":[-73.759889,42.744256],"type":"Point"}
}