{
  "type": "Feature",
  "properties": {
    "addr:full":"21 Railroad Ave Valley Stream NY 11580",
    "addr:housenumber":"21",
    "addr:postcode":"11580",
    "addr:street":"Railroad Ave",
    "iso:country":"US",
    "sg:address":"21 Railroad Ave",
    "sg:city":"Valley Stream",
    "sg:classifiers":[
        {
            "category":"Manufacturing",
            "subcategory":"Tools & Machinery",
            "type":"Manufacturing & Wholesale Goods"
        }
    ],
    "sg:phone":"+1 516 825 1234",
    "sg:postcode":"11580",
    "sg:province":"NY",
    "sg:tags":[
        "machine",
        "shop"
    ],
    "wof:name":"Valbrook Machine Corp",
    "wof:placetype":"venue"
},
  "geometry": {"coordinates":[-73.688785,40.663342],"type":"Point"}
}