{
  "type": "Feature",
  "properties": {
    "addr:full":"902 Ocean Pkwy Brooklyn NY 11230",
    "addr:housenumber":"902",
    "addr:postcode":"11230",
    "addr:street":"Ocean Pkwy",
    "iso:country":"US",
    "sg:address":"902 Ocean Pkwy",
    "sg:city":"Brooklyn",
    "sg:classifiers":[
        {
            "category":"Education",
            "subcategory":"Special Training",
            "type":"Public Place"
        }
    ],
    "sg:phone":"+1 718 338 0282",
    "sg:postcode":"11230",
    "sg:province":"NY",
    "sg:tags":[
        "program"
    ],
    "wof:name":"E & R Enterprise",
    "wof:placetype":"venue"
},
  "geometry": {"coordinates":[-73.970939,40.626226],"type":"Point"}
}