{
  "type": "Feature",
  "properties": {
    "addr:full":"47 Boundary Ave Farmingdale NY 11735",
    "addr:housenumber":"47",
    "addr:postcode":"11735",
    "addr:street":"Boundary Ave",
    "iso:country":"US",
    "sg:address":"47 Boundary Ave",
    "sg:city":"Farmingdale",
    "sg:classifiers":[
        {
            "category":"Bars & Pubs",
            "type":"Food & Drink"
        }
    ],
    "sg:phone":"+1 516 694 6906",
    "sg:postcode":"11735",
    "sg:province":"NY",
    "wof:name":"Blanche",
    "wof:placetype":"venue"
},
  "geometry": {"coordinates":[-73.46127799999999,40.717348],"type":"Point"}
}