{
  "type": "Feature",
  "properties": {
    "addr:full":"29 S Main St Moravia NY 13118",
    "addr:housenumber":"29",
    "addr:postcode":"13118",
    "addr:street":"S Main St",
    "iso:country":"US",
    "sg:address":"29 S Main St",
    "sg:city":"Moravia",
    "sg:classifiers":[
        {
            "category":"Retail",
            "subcategory":"Auto Repair",
            "type":"Services"
        }
    ],
    "sg:phone":"+1 315 497 3317",
    "sg:postcode":"13118",
    "sg:province":"NY",
    "sg:tags":[
        "repairing",
        "automobile"
    ],
    "wof:name":"Morey's Auto Care",
    "wof:placetype":"venue"
},
  "geometry": {"coordinates":[-76.421003,42.7082],"type":"Point"}
}