{
  "type": "Feature",
  "properties": {
    "addr:full":"35 Division Street New York NY 10002",
    "addr:housenumber":"35",
    "addr:postcode":"10002",
    "addr:street":"Division Street",
    "iso:country":"US",
    "sg:address":"35 Division Street",
    "sg:city":"New York",
    "sg:classifiers":[
        {
            "category":"Social Services",
            "subcategory":"Child Care",
            "type":"Services"
        }
    ],
    "sg:phone":"+1 212 431 3845",
    "sg:postcode":"10002",
    "sg:province":"NY",
    "sg:tags":[
        "day"
    ],
    "wof:name":"Chinatown Day Care Center",
    "wof:placetype":"venue"
},
  "geometry": {"coordinates":[-73.99585,40.714256],"type":"Point"}
}