{
  "type": "Feature",
  "properties": {
    "addr:full":"1 Sintsink Dr W Port Washington NY 11050",
    "addr:housenumber":"1",
    "addr:postcode":"11050",
    "addr:street":"Sintsink Dr W",
    "iso:country":"US",
    "sg:address":"1 Sintsink Dr W",
    "sg:city":"Port Washington",
    "sg:classifiers":[
        {
            "category":"Organizations",
            "subcategory":"Religious Organization",
            "type":"Services"
        }
    ],
    "sg:phone":"+1 516 944 9046",
    "sg:postcode":"11050",
    "sg:province":"NY",
    "wof:name":"Chevrat Tefillah",
    "wof:placetype":"venue"
},
  "geometry": {"coordinates":[-73.71115899999999,40.836915],"type":"Point"}
}