{
  "type": "Feature",
  "properties": {
    "iso:country":"US",
    "sg:address":"1228 E Gun Hill Rd",
    "sg:city":"Bronx",
    "sg:classifiers":[
        {
            "category":"Personal",
            "subcategory":"Beauty Salon",
            "type":"Services"
        }
    ],
    "sg:phone":"+1 718 654 7008",
    "sg:postcode":"10469",
    "sg:province":"NY",
    "sg:tags":[
        "shop"
    ],
    "wof:name":"A & G Beauty Spot",
    "wof:placetype":"venue"
},
  "geometry": {"coordinates":[-73.85088,40.872354],"type":"Point"}
}