{
  "type": "Feature",
  "properties": {
    "addr:full":"40 Ludlow St New York NY 10002",
    "addr:housenumber":"40",
    "addr:postcode":"10002",
    "addr:street":"Ludlow St",
    "iso:country":"US",
    "sg:address":"40 Ludlow St",
    "sg:city":"New York",
    "sg:classifiers":[
        {
            "category":"Home & Garden",
            "subcategory":"Hardware",
            "type":"Retail Goods"
        }
    ],
    "sg:phone":"+1 212 473 3080",
    "sg:postcode":"10002",
    "sg:province":"NY",
    "sg:tags":[
        "store"
    ],
    "wof:name":"Reliance Hardware Corp",
    "wof:placetype":"venue"
},
  "geometry": {"coordinates":[-73.99015799999999,40.716168],"type":"Point"}
}