{
  "type": "Feature",
  "properties": {
    "addr:full":"6260 State Hwy 12 Norwich NY 13815",
    "addr:housenumber":"6260",
    "addr:postcode":"13815",
    "addr:street":"State Hwy 12",
    "iso:country":"US",
    "sg:address":"6260 State Hwy 12",
    "sg:city":"Norwich",
    "sg:classifiers":[
        {
            "category":"Autos & Motor Vehicles",
            "subcategory":"Automobile Sales",
            "type":"Retail Goods"
        }
    ],
    "sg:phone":"+1   ",
    "sg:postcode":"13815",
    "sg:province":"NY",
    "sg:tags":[
        "used"
    ],
    "wof:name":"All Brands Motors",
    "wof:placetype":"venue"
},
  "geometry": {"coordinates":[-75.52567999999999,42.501516],"type":"Point"}
}