{
  "type": "Feature",
  "properties": {
    "iso:country":"US",
    "sg:address":"1469 Deer Park Ave",
    "sg:city":"North Babylon",
    "sg:classifiers":[
        {
            "category":"Insurance",
            "subcategory":"Insurance Agent",
            "type":"Services"
        }
    ],
    "sg:phone":"+1 631 586 3100",
    "sg:postcode":"11703",
    "sg:province":"NY",
    "wof:name":"DCAP Insurance",
    "wof:placetype":"venue"
},
  "geometry": {"coordinates":[-73.323621,40.747265],"type":"Point"}
}