{
  "type": "Feature",
  "properties": {
    "addr:full":"3560 White Plains Rd Bronx NY 10467",
    "addr:housenumber":"3560",
    "addr:postcode":"10467",
    "addr:street":"White Plains Rd",
    "iso:country":"US",
    "sg:address":"3560 White Plains Rd",
    "sg:city":"Bronx",
    "sg:classifiers":[
        {
            "category":"Wholesale",
            "subcategory":"Machinery & Supplies",
            "type":"Manufacturing & Wholesale Goods"
        }
    ],
    "sg:phone":"+1 718 654 8631",
    "sg:postcode":"10467",
    "sg:province":"NY",
    "wof:name":"Wakefield Management & Rl Est",
    "wof:placetype":"venue"
},
  "geometry": {"coordinates":[-73.865343,40.879174],"type":"Point"}
}