{
  "type": "Feature",
  "properties": {
    "addr:full":"297 E Meadow Ave East Meadow NY 11554",
    "addr:housenumber":"297",
    "addr:postcode":"11554",
    "addr:street":"E Meadow Ave",
    "iso:country":"US",
    "sg:address":"297 E Meadow Ave",
    "sg:city":"East Meadow",
    "sg:classifiers":[
        {
            "category":"Freight",
            "type":"Transportation"
        },
        {
            "category":"Local Transit",
            "type":"Transportation"
        }
    ],
    "sg:phone":"+1 516 794 7117",
    "sg:postcode":"11554",
    "sg:province":"NY",
    "sg:tags":[
        "arrangement"
    ],
    "wof:name":"L & M Trucking Co",
    "wof:placetype":"venue"
},
  "geometry": {"coordinates":[-73.561258,40.716377],"type":"Point"}
}