{
  "type": "Feature",
  "properties": {
    "iso:country":"US",
    "sg:address":"115 Carley Ave",
    "sg:city":"Huntington",
    "sg:classifiers":[
        {
            "category":"Retail",
            "subcategory":"Auto Repair",
            "type":"Services"
        }
    ],
    "sg:phone":"+1   ",
    "sg:postcode":"11743",
    "sg:province":"NY",
    "sg:tags":[
        "general"
    ],
    "wof:name":"Walts Repair Shop",
    "wof:placetype":"venue"
},
  "geometry": {"coordinates":[-73.434639,40.866291],"type":"Point"}
}