{
  "type": "Feature",
  "properties": {
    "iso:country":"US",
    "sg:address":"103 Hoffman St",
    "sg:city":"Elmira",
    "sg:classifiers":[
        {
            "category":"Government",
            "subcategory":"Post Office",
            "type":"Public Place"
        }
    ],
    "sg:phone":"+1   ",
    "sg:postcode":"14905",
    "sg:province":"NY",
    "sg:tags":[
        "postal",
        "us"
    ],
    "wof:name":"US Post Office",
    "wof:placetype":"venue"
},
  "geometry": {"coordinates":[-76.822447,42.08467],"type":"Point"}
}