{
  "type": "Feature",
  "properties": {
    "iso:country":"US",
    "sg:address":"850 7 Ave",
    "sg:city":"New York",
    "sg:classifiers":[
        {
            "category":"Health Services",
            "subcategory":"Health Practitioner",
            "type":"Services"
        }
    ],
    "sg:phone":"+1 212 397 8988",
    "sg:postcode":"10019",
    "sg:province":"NY",
    "sg:tags":[
        "acupuncture"
    ],
    "wof:name":"Acupuncture Center For Pain",
    "wof:placetype":"venue"
},
  "geometry": {"coordinates":[-73.98372999999999,40.760456],"type":"Point"}
}