{
  "type": "Feature",
  "properties": {
    "addr:full":"314 E 188th St Bronx NY 10458",
    "addr:housenumber":"314",
    "addr:postcode":"10458",
    "addr:street":"E 188Th St",
    "iso:country":"US",
    "sg:address":"314 E 188th St",
    "sg:city":"Bronx",
    "sg:classifiers":[
        {
            "category":"Food & Beverages",
            "subcategory":"Groceries & Convenience Stores",
            "type":"Retail Goods"
        }
    ],
    "sg:phone":"+1 718 450 3267",
    "sg:postcode":"10458",
    "sg:province":"NY",
    "wof:name":"Torres Grocery",
    "wof:placetype":"venue"
},
  "geometry": {"coordinates":[-73.895021,40.860524],"type":"Point"}
}