{
  "type": "Feature",
  "properties": {
    "addr:full":"927 Grand St Brooklyn NY 11211",
    "addr:housenumber":"927",
    "addr:postcode":"11211",
    "addr:street":"Grand St",
    "iso:country":"US",
    "sg:address":"927 Grand St",
    "sg:city":"Brooklyn",
    "sg:classifiers":[
        {
            "category":"Food & Beverages",
            "subcategory":"Groceries & Convenience Stores",
            "type":"Retail Goods"
        }
    ],
    "sg:phone":"+1 718 302 5804",
    "sg:postcode":"11211",
    "sg:province":"NY",
    "sg:tags":[
        "grocer"
    ],
    "wof:name":"R & J Grocery Store",
    "wof:placetype":"venue"
},
  "geometry": {"coordinates":[-73.934966,40.713399],"type":"Point"}
}