{
  "type": "Feature",
  "properties": {
    "addr:full":"813 Holland Rd Schenectady NY 12303",
    "addr:housenumber":"813",
    "addr:postcode":"12303",
    "addr:street":"Holland Rd",
    "iso:country":"US",
    "sg:address":"813 Holland Rd",
    "sg:city":"Schenectady",
    "sg:classifiers":[
        {
            "category":"Banks & Credit Unions",
            "subcategory":"Investment Brokerage",
            "type":"Services"
        }
    ],
    "sg:phone":"+1 518 346 3201",
    "sg:postcode":"12303",
    "sg:province":"NY",
    "sg:tags":[
        "advisory",
        "financial"
    ],
    "wof:name":"Prestige Financial Svc Inc",
    "wof:placetype":"venue"
},
  "geometry": {"coordinates":[-73.94143699999999,42.798899],"type":"Point"}
}