{
  "type": "Feature",
  "properties": {
    "iso:country":"US",
    "sg:address":"2914 Cheryl Rd",
    "sg:city":"Merrick",
    "sg:classifiers":[
        {
            "category":"Social Services",
            "type":"Services"
        }
    ],
    "sg:phone":"+1 516 867 7552",
    "sg:postcode":"11566",
    "sg:province":"NY",
    "sg:tags":[
        "counselor",
        "marriage",
        "family"
    ],
    "wof:name":"Michael Miller",
    "wof:placetype":"venue"
},
  "geometry": {"coordinates":[-73.538495,40.647821],"type":"Point"}
}