{
  "type": "Feature",
  "properties": {
    "iso:country":"US",
    "sg:address":"500 Bi County Blvd",
    "sg:city":"Farmingdale",
    "sg:classifiers":[
        {
            "category":"Professional",
            "type":"Services"
        }
    ],
    "sg:phone":"+1 631 845 1574",
    "sg:postcode":"11735",
    "sg:province":"NY",
    "sg:tags":[
        "establishment"
    ],
    "wof:name":"500 Bi-County Assoc",
    "wof:placetype":"venue"
},
  "geometry": {"coordinates":[-73.428271,40.725887],"type":"Point"}
}