{
  "type": "Feature",
  "properties": {
    "addr:full":"519 Franklin Ave Brooklyn NY 11238",
    "addr:housenumber":"519",
    "addr:postcode":"11238",
    "addr:street":"Franklin Ave",
    "iso:country":"US",
    "sg:address":"519 Franklin Ave",
    "sg:city":"Brooklyn",
    "sg:classifiers":[
        {
            "category":"Shopping",
            "subcategory":"Clothing, Apparel, & Fashions",
            "type":"Retail Goods"
        }
    ],
    "sg:phone":"+1 718 789 8307",
    "sg:postcode":"11238",
    "sg:province":"NY",
    "sg:tags":[
        "tailor"
    ],
    "wof:name":"Endam Sinthiane Fashion",
    "wof:placetype":"venue"
},
  "geometry": {"coordinates":[-73.95544099999999,40.680408],"type":"Point"}
}