{
  "type": "Feature",
  "properties": {
    "addr:full":"2347 McDonald Ave Brooklyn NY 11223",
    "addr:housenumber":"2347",
    "addr:postcode":"11223",
    "addr:street":"Mcdonald Ave",
    "iso:country":"US",
    "sg:address":"2347 McDonald Ave",
    "sg:city":"Brooklyn",
    "sg:classifiers":[
        {
            "category":"Retail",
            "subcategory":"Auto Repair",
            "type":"Services"
        }
    ],
    "sg:phone":"+1 718 375 6557",
    "sg:postcode":"11223",
    "sg:province":"NY",
    "wof:name":"John's Towing Svce",
    "wof:placetype":"venue"
},
  "geometry": {"coordinates":[-73.97339599999999,40.5947],"type":"Point"}
}