{
  "type": "Feature",
  "properties": {
    "iso:country":"US",
    "sg:address":"29 W 30 St",
    "sg:city":"New York",
    "sg:classifiers":[
        {
            "category":"Wholesale",
            "subcategory":"Home Furnishings",
            "type":"Manufacturing & Wholesale Goods"
        }
    ],
    "sg:phone":"+1 212 290 8484",
    "sg:postcode":"10001",
    "sg:province":"NY",
    "sg:tags":[
        "oriental",
        "rug"
    ],
    "wof:name":"Ahdoot Oriental Rugs Inc",
    "wof:placetype":"venue"
},
  "geometry": {"coordinates":[-73.987202,40.746179],"type":"Point"}
}