{
  "type": "Feature",
  "properties": {
    "addr:full":"189 Curtis Rd Woodmere NY 11598",
    "addr:housenumber":"189",
    "addr:postcode":"11598",
    "addr:street":"Curtis Rd",
    "iso:country":"US",
    "sg:address":"189 Curtis Rd",
    "sg:city":"Woodmere",
    "sg:classifiers":[
        {
            "category":"Professional",
            "subcategory":"Management & Consulting",
            "type":"Services"
        }
    ],
    "sg:phone":"+1 516 569 4557",
    "sg:postcode":"11598",
    "sg:province":"NY",
    "sg:tags":[
        "communications",
        "consultant"
    ],
    "wof:name":"Dbrn Assoc Inc",
    "wof:placetype":"venue"
},
  "geometry": {"coordinates":[-73.697136,40.623405],"type":"Point"}
}