{
  "type": "Feature",
  "properties": {
    "addr:full":"127 Loma Ave Syracuse NY 13208",
    "addr:housenumber":"127",
    "addr:postcode":"13208",
    "addr:street":"Loma Ave",
    "iso:country":"US",
    "sg:address":"127 Loma Ave",
    "sg:city":"Syracuse",
    "sg:classifiers":[
        {
            "category":"Professional",
            "subcategory":"Secretarial Services",
            "type":"Services"
        }
    ],
    "sg:phone":"+1 315 454 4231",
    "sg:postcode":"13208",
    "sg:province":"NY",
    "sg:tags":[
        "reporting",
        "court"
    ],
    "wof:name":"P C Transcription Svc",
    "wof:placetype":"venue"
},
  "geometry": {"coordinates":[-76.14424699999999,43.078748],"type":"Point"}
}