{
  "type": "Feature",
  "properties": {
    "addr:full":"116 E 27 St New York NY 10016",
    "addr:housenumber":"116;27",
    "addr:postcode":"10016",
    "addr:street":"E;St",
    "iso:country":"US",
    "sg:address":"116 E 27 St",
    "sg:city":"New York",
    "sg:classifiers":[
        {
            "category":"Professional",
            "subcategory":"Business Services",
            "type":"Services"
        }
    ],
    "sg:phone":"+1   ",
    "sg:postcode":"10016",
    "sg:province":"NY",
    "wof:name":"Stock Sp Antomy Wrks Medicrome",
    "wof:placetype":"venue"
},
  "geometry": {"coordinates":[-73.98356099999999,40.742301],"type":"Point"}
}