{
  "type": "Feature",
  "properties": {
    "addr:full":"28 Molle St West Babylon NY 11704",
    "addr:housenumber":"28",
    "addr:postcode":"11704",
    "addr:street":"Molle St",
    "iso:country":"US",
    "sg:address":"28 Molle St",
    "sg:city":"West Babylon",
    "sg:classifiers":[
        {
            "category":"Professional",
            "subcategory":"Business Services",
            "type":"Services"
        }
    ],
    "sg:phone":"+1 631 587 0291",
    "sg:postcode":"11704",
    "sg:province":"NY",
    "wof:name":"Wraprite Intl Baggage Protectn",
    "wof:placetype":"venue"
},
  "geometry": {"coordinates":[-73.35824599999999,40.714183],"type":"Point"}
}