{
  "type": "Feature",
  "properties": {
    "iso:country":"US",
    "sg:address":"285 E Main St Ste 208",
    "sg:city":"Smithtown",
    "sg:classifiers":[
        {
            "category":"Health Services",
            "subcategory":"Doctor",
            "type":"Services"
        }
    ],
    "sg:phone":"+1 631 979 1625",
    "sg:postcode":"11787",
    "sg:province":"NY",
    "wof:name":"Dreznick Elliott MD Facg",
    "wof:placetype":"venue"
},
  "geometry": {"coordinates":[-73.177299,40.8549],"type":"Point"}
}