{
  "type": "Feature",
  "properties": {
    "iso:country":"US",
    "sg:address":"131 Joralemon St",
    "sg:city":"Brooklyn",
    "sg:classifiers":[
        {
            "category":"Professional",
            "subcategory":"Research",
            "type":"Services"
        }
    ],
    "sg:phone":"+1 718 858 7702",
    "sg:postcode":"11201",
    "sg:province":"NY",
    "wof:name":"Irevna",
    "wof:placetype":"venue"
},
  "geometry": {"coordinates":[-73.99477400000001,40.693204],"type":"Point"}
}