{
  "type": "Feature",
  "properties": {
    "addr:full":"2124 Broadway Manhattan NY 10023",
    "addr:housenumber":"2124",
    "addr:postcode":"10023",
    "addr:street":"Broadway",
    "iso:country":"US",
    "sg:address":"2124 Broadway",
    "sg:city":"Manhattan",
    "sg:classifiers":[
        {
            "category":"Arts & Performance",
            "subcategory":"Arts Center",
            "type":"Entertainment"
        }
    ],
    "sg:phone":"+1 212 465 6500",
    "sg:postcode":"10023",
    "sg:province":"NY",
    "sg:tags":[
        "performing"
    ],
    "sg:website":"www.cirquedusoleil.com/bananashpeel",
    "wof:name":"Banana Shpeel NYC",
    "wof:placetype":"venue"
},
  "geometry": {"coordinates":[-73.981402,40.780316],"type":"Point"}
}