{
  "type": "Feature",
  "properties": {
    "addr:full":"1630 Delphi Rd Cazenovia NY 13035",
    "addr:housenumber":"1630",
    "addr:postcode":"13035",
    "addr:street":"Delphi Rd",
    "iso:country":"US",
    "sg:address":"1630 Delphi Rd",
    "sg:city":"Cazenovia",
    "sg:classifiers":[
        {
            "category":"Building & Trades",
            "subcategory":"Construction",
            "type":"Services"
        }
    ],
    "sg:phone":"+1 315 662 3260",
    "sg:postcode":"13035",
    "sg:province":"NY",
    "sg:tags":[
        "contractor"
    ],
    "wof:name":"Un Hl Timber Frames",
    "wof:placetype":"venue"
},
  "geometry": {"coordinates":[-75.887384,42.867939],"type":"Point"}
}