{
  "type": "Feature",
  "properties": {
    "addr:full":"1173 Pugsley Avenue Bronx NY 10472",
    "addr:housenumber":"1173",
    "addr:postcode":"10472",
    "addr:street":"Pugsley Avenue",
    "iso:country":"US",
    "sg:address":"1173 Pugsley Avenue",
    "sg:city":"Bronx",
    "sg:classifiers":[
        {
            "category":"Personal",
            "subcategory":"Beauty Salon",
            "type":"Services"
        }
    ],
    "sg:phone":"+1 718 892 0512",
    "sg:postcode":"10472",
    "sg:province":"NY",
    "sg:tags":[
        "hair"
    ],
    "wof:name":"Robert Thomas Hair Stylist",
    "wof:placetype":"venue"
},
  "geometry": {"coordinates":[-73.85719899999999,40.830653],"type":"Point"}
}