{
  "type": "Feature",
  "properties": {
    "addr:full":"168 Lynch St Brooklyn NY 11206",
    "addr:housenumber":"168",
    "addr:postcode":"11206",
    "addr:street":"Lynch St",
    "iso:country":"US",
    "sg:address":"168 Lynch St",
    "sg:city":"Brooklyn",
    "sg:classifiers":[
        {
            "category":"Shopping",
            "subcategory":"Catalog Store",
            "type":"Retail Goods"
        }
    ],
    "sg:phone":"+1 718 384 1205",
    "sg:postcode":"11206",
    "sg:province":"NY",
    "sg:tags":[
        "internet"
    ],
    "wof:name":"Silver Star Intl",
    "wof:placetype":"venue"
},
  "geometry": {"coordinates":[-73.95196900000001,40.703158],"type":"Point"}
}