{
  "type": "Feature",
  "properties": {
    "addr:full":"219 Berkley Rd Buffalo NY 14221",
    "addr:housenumber":"219",
    "addr:postcode":"14221",
    "addr:street":"Berkley Rd",
    "iso:country":"US",
    "sg:address":"219 Berkley Rd",
    "sg:city":"Buffalo",
    "sg:classifiers":[
        {
            "category":"Real Estate",
            "subcategory":"Real Estate Agent",
            "type":"Services"
        }
    ],
    "sg:phone":"+1 716 634 1973",
    "sg:postcode":"14221",
    "sg:province":"NY",
    "sg:tags":[
        "inspection"
    ],
    "wof:name":"Total Home Inspections",
    "wof:placetype":"venue"
},
  "geometry": {"coordinates":[-78.70177099999999,42.962079],"type":"Point"}
}