{
  "type": "Feature",
  "properties": {
    "addr:full":"711 S Westchester Ave White Plains NY 10604",
    "addr:housenumber":"711",
    "addr:postcode":"10604",
    "addr:street":"S Westchester Ave",
    "iso:country":"US",
    "sg:address":"711 S Westchester Ave",
    "sg:city":"White Plains",
    "sg:classifiers":[
        {
            "category":"Health Services",
            "subcategory":"Clinic",
            "type":"Services"
        }
    ],
    "sg:phone":"+1 914 421 2525",
    "sg:postcode":"10604",
    "sg:province":"NY",
    "sg:tags":[
        "education"
    ],
    "wof:name":"National Health Promotion",
    "wof:placetype":"venue"
},
  "geometry": {"coordinates":[-73.73544099999999,41.026902],"type":"Point"}
}