{
  "type": "Feature",
  "properties": {
    "addr:full":"56 Engineers Dr Hicksville NY 11801",
    "addr:housenumber":"56",
    "addr:postcode":"11801",
    "addr:street":"Engineers Dr",
    "iso:country":"US",
    "sg:address":"56 Engineers Dr",
    "sg:city":"Hicksville",
    "sg:classifiers":[
        {
            "category":"Retail",
            "subcategory":"Auto Repair",
            "type":"Services"
        }
    ],
    "sg:phone":"+1   ",
    "sg:postcode":"11801",
    "sg:province":"NY",
    "sg:tags":[
        "body"
    ],
    "wof:name":"Auto-Tech Conversions Inc",
    "wof:placetype":"venue"
},
  "geometry": {"coordinates":[-73.50214200000001,40.74493],"type":"Point"}
}