{
  "type": "Feature",
  "properties": {
    "addr:full":"3879 Bonstead Rd Clay NY 13041",
    "addr:housenumber":"3879",
    "addr:postcode":"13041",
    "addr:street":"Bonstead Rd",
    "iso:country":"US",
    "sg:address":"3879 Bonstead Rd",
    "sg:city":"Clay",
    "sg:classifiers":[
        {
            "category":"Utilities",
            "subcategory":"Cable",
            "type":"Services"
        }
    ],
    "sg:phone":"+1   ",
    "sg:postcode":"13041",
    "sg:province":"NY",
    "sg:tags":[
        "television"
    ],
    "wof:name":"Satline Installations",
    "wof:placetype":"venue"
},
  "geometry": {"coordinates":[-76.229409,43.20661],"type":"Point"}
}