{
  "type": "Feature",
  "properties": {
    "iso:country":"US",
    "sg:address":"288 Ranch Trl",
    "sg:city":"Williamsville",
    "sg:classifiers":[
        {
            "category":"Professional",
            "type":"Services"
        }
    ],
    "sg:phone":"+1 716 636 0005",
    "sg:postcode":"14221",
    "sg:province":"NY",
    "sg:tags":[
        "establishment"
    ],
    "wof:name":"Manzella Productions",
    "wof:placetype":"venue"
},
  "geometry": {"coordinates":[-78.74991199999999,43.000212],"type":"Point"}
}