{
  "type": "Feature",
  "properties": {
    "addr:full":"129 Hawley St Lockport NY 14094",
    "addr:housenumber":"129",
    "addr:postcode":"14094",
    "addr:street":"Hawley St",
    "iso:country":"US",
    "sg:address":"129 Hawley St",
    "sg:city":"Lockport",
    "sg:classifiers":[
        {
            "category":"Real Estate",
            "subcategory":"Real Estate Services",
            "type":"Services"
        },
        {
            "category":"Professional",
            "subcategory":"Research",
            "type":"Services"
        }
    ],
    "sg:phone":"+1 716 433 5933",
    "sg:postcode":"14094",
    "sg:province":"NY",
    "sg:tags":[
        "abstracter",
        "title"
    ],
    "wof:name":"Niagara Square Abstract Company, Inc",
    "wof:placetype":"venue"
},
  "geometry": {"coordinates":[-78.699333,43.168616],"type":"Point"}
}