{
  "type": "Feature",
  "properties": {
    "addr:full":"935 Sheridan Dr Tonawanda NY 14150",
    "addr:housenumber":"935",
    "addr:postcode":"14150",
    "addr:street":"Sheridan Dr",
    "iso:country":"US",
    "sg:address":"935 Sheridan Dr",
    "sg:city":"Tonawanda",
    "sg:classifiers":[
        {
            "category":"Health Services",
            "subcategory":"Chiropractor",
            "type":"Services"
        }
    ],
    "sg:phone":"+1 716 871 9802",
    "sg:postcode":"14150",
    "sg:province":"NY",
    "wof:name":"Miller Chiropractic Wellness",
    "wof:placetype":"venue"
},
  "geometry": {"coordinates":[-78.899489,42.98059],"type":"Point"}
}