{
  "type": "Feature",
  "properties": {
    "iso:country":"US",
    "sg:address":"127 Katonah Ave",
    "sg:city":"Katonah",
    "sg:classifiers":[
        {
            "category":"Professional",
            "type":"Services"
        }
    ],
    "sg:phone":"+1   ",
    "sg:postcode":"10536",
    "sg:province":"NY",
    "wof:name":"Palma Settimi Inc",
    "wof:placetype":"venue"
},
  "geometry": {"coordinates":[-73.684196,41.257849],"type":"Point"}
}