{
  "type": "Feature",
  "properties": {
    "addr:full":"191 S Greeley Ave Chappaqua NY 10514",
    "addr:housenumber":"191",
    "addr:postcode":"10514",
    "addr:street":"S Greeley Ave",
    "iso:country":"US",
    "sg:address":"191 S Greeley Ave",
    "sg:city":"Chappaqua",
    "sg:classifiers":[
        {
            "category":"Organizations",
            "subcategory":"Religious Organization",
            "type":"Services"
        }
    ],
    "sg:phone":"+1 914 238 8751",
    "sg:postcode":"10514",
    "sg:province":"NY",
    "wof:name":"Church of St Mary the Virgin",
    "wof:placetype":"venue"
},
  "geometry": {"coordinates":[-73.773387,41.155797],"type":"Point"}
}