{
  "type": "Feature",
  "properties": {
    "iso:country":"US",
    "sg:address":"496 Driggs Ave",
    "sg:city":"Brooklyn",
    "sg:classifiers":[
        {
            "category":"Shopping",
            "subcategory":"Thrift Store",
            "type":"Retail Goods"
        },
        {
            "category":"Shopping",
            "subcategory":"Discount & Variety Stores",
            "type":"Retail Goods"
        }
    ],
    "sg:phone":"+1 718 384 6665",
    "sg:postcode":"11211",
    "sg:province":"NY",
    "sg:tags":[
        "outlet"
    ],
    "wof:name":"Monk Vintage Thrift Shop",
    "wof:placetype":"venue"
},
  "geometry": {"coordinates":[-73.955057,40.718343],"type":"Point"}
}