{
  "type": "Feature",
  "properties": {
    "addr:full":"6334 Woodhaven Blvd Rego Park NY 11374",
    "addr:housenumber":"6334",
    "addr:postcode":"11374",
    "addr:street":"Woodhaven Blvd",
    "iso:country":"US",
    "sg:address":"6334 Woodhaven Blvd",
    "sg:city":"Rego Park",
    "sg:classifiers":[
        {
            "category":"Home & Garden",
            "subcategory":"Hardware",
            "type":"Retail Goods"
        },
        {
            "category":"Building & Trades",
            "subcategory":"Locksmith",
            "type":"Services"
        }
    ],
    "sg:phone":"+1 718 269 0696",
    "sg:postcode":"11374",
    "sg:province":"NY",
    "sg:tags":[
        "store",
        "key"
    ],
    "wof:name":"A Rego Park Emergency A 24 Hour Locks",
    "wof:placetype":"venue"
},
  "geometry": {"coordinates":[-73.868788,40.723488],"type":"Point"}
}