{
  "type": "Feature",
  "properties": {
    "addr:full":"111 E 15 St New York NY 10003",
    "addr:housenumber":"111;15",
    "addr:postcode":"10003",
    "addr:street":"E;St",
    "iso:country":"US",
    "sg:address":"111 E 15 St",
    "sg:city":"New York",
    "sg:classifiers":[
        {
            "category":"Shopping",
            "subcategory":"Musical Instruments",
            "type":"Retail Goods"
        }
    ],
    "sg:phone":"+1 212 254 9575",
    "sg:postcode":"10003",
    "sg:province":"NY",
    "wof:name":"Johnny Guitar LP",
    "wof:placetype":"venue"
},
  "geometry": {"coordinates":[-73.988867,40.735069],"type":"Point"}
}