{
  "type": "Feature",
  "properties": {
    "addr:full":"26 Court St Ste 2003 Brooklyn NY 11242",
    "addr:housenumber":"26",
    "addr:postcode":"11242",
    "addr:street":"Court St Ste 2003",
    "iso:country":"US",
    "sg:address":"26 Court St Ste 2003",
    "sg:city":"Brooklyn",
    "sg:classifiers":[
        {
            "category":"Professional",
            "subcategory":"Lawyer & Legal Services",
            "type":"Services"
        }
    ],
    "sg:phone":"+1 718 222 5300",
    "sg:postcode":"11242",
    "sg:province":"NY",
    "wof:name":"Nangia & Kazansky Llp",
    "wof:placetype":"venue"
},
  "geometry": {"coordinates":[-73.990799,40.6931],"type":"Point"}
}