{
  "type": "Feature",
  "properties": {
    "iso:country":"US",
    "sg:address":"1262 Powell Ave",
    "sg:city":"Merrick",
    "sg:classifiers":[
        {
            "category":"Social Services",
            "type":"Services"
        }
    ],
    "sg:phone":"+1 516 221 9494",
    "sg:postcode":"11566",
    "sg:province":"NY",
    "sg:tags":[
        "counseling",
        "health",
        "mental"
    ],
    "wof:name":"A Nassau Guidance & Counseling Center",
    "wof:placetype":"venue"
},
  "geometry": {"coordinates":[-73.550301,40.689301],"type":"Point"}
}