{
  "type": "Feature",
  "properties": {
    "addr:full":"141 Scannell Rd Chatham NY 12037",
    "addr:housenumber":"141",
    "addr:postcode":"12037",
    "addr:street":"Scannell Rd",
    "iso:country":"US",
    "sg:address":"141 Scannell Rd",
    "sg:city":"Chatham",
    "sg:classifiers":[
        {
            "category":"Wholesale",
            "subcategory":"Books, Periodicals, & Newspapers",
            "type":"Manufacturing & Wholesale Goods"
        }
    ],
    "sg:phone":"+1 518 392 3068",
    "sg:postcode":"12037",
    "sg:province":"NY",
    "sg:tags":[
        "publisher",
        "book"
    ],
    "wof:name":"S G Phillips Inc",
    "wof:placetype":"venue"
},
  "geometry": {"coordinates":[-73.58818100000001,42.31567],"type":"Point"}
}