{
  "type": "Feature",
  "properties": {
    "iso:country":"US",
    "sg:address":"109 Fort Salonga Rd",
    "sg:city":"Northport",
    "sg:classifiers":[
        {
            "category":"Retail",
            "subcategory":"Laundry & Dry Cleaning",
            "type":"Services"
        }
    ],
    "sg:phone":"+1 631 261 7896",
    "sg:postcode":"11768",
    "sg:province":"NY",
    "wof:name":"Fine Cleaners",
    "wof:placetype":"venue"
},
  "geometry": {"coordinates":[-73.356593,40.888177],"type":"Point"}
}