{
  "type": "Feature",
  "properties": {
    "iso:country":"US",
    "sg:address":"2255 Bedford Ave",
    "sg:city":"Brooklyn",
    "sg:classifiers":[
        {
            "category":"Restaurant",
            "type":"Food & Drink"
        }
    ],
    "sg:phone":"+1 347 442 1304",
    "sg:postcode":"11226",
    "sg:province":"NY",
    "sg:tags":[
        "pizza"
    ],
    "wof:name":"Bedford Pizza",
    "wof:placetype":"venue"
},
  "geometry": {"coordinates":[-73.955589,40.648868],"type":"Point"}
}