{
  "type": "Feature",
  "properties": {
    "addr:full":"29 New Main St Haverstraw NY 10927",
    "addr:housenumber":"29",
    "addr:postcode":"10927",
    "addr:street":"New Main St",
    "iso:country":"US",
    "sg:address":"29 New Main St",
    "sg:city":"Haverstraw",
    "sg:classifiers":[
        {
            "category":"Wholesale",
            "subcategory":"Auto Parts",
            "type":"Manufacturing & Wholesale Goods"
        }
    ],
    "sg:phone":"+1 845 429 1777",
    "sg:postcode":"10927",
    "sg:province":"NY",
    "sg:tags":[
        "automobile",
        "rebuilt"
    ],
    "wof:name":"Town Auto Parts",
    "wof:placetype":"venue"
},
  "geometry": {"coordinates":[-73.965315,41.196444],"type":"Point"}
}