{
  "type": "Feature",
  "properties": {
    "iso:country":"US",
    "sg:address":"195 Smithtown Blvd",
    "sg:city":"Nesconset",
    "sg:classifiers":[
        {
            "category":"Health Services",
            "subcategory":"Chiropractor",
            "type":"Services"
        }
    ],
    "sg:phone":"+1 631 724 1991",
    "sg:postcode":"11767",
    "sg:province":"NY",
    "wof:name":"Di Blanda Anthony E DC",
    "wof:placetype":"venue"
},
  "geometry": {"coordinates":[-73.159302,40.837502],"type":"Point"}
}