{
  "type": "Feature",
  "properties": {
    "addr:full":"304 Kingston Ave Brooklyn NY 11213",
    "addr:housenumber":"304",
    "addr:postcode":"11213",
    "addr:street":"Kingston Ave",
    "iso:country":"US",
    "sg:address":"304 Kingston Ave",
    "sg:city":"Brooklyn",
    "sg:classifiers":[
        {
            "category":"Organizations",
            "subcategory":"Religious Organization",
            "type":"Services"
        }
    ],
    "sg:phone":"+1 718 774 1770",
    "sg:postcode":"11213",
    "sg:province":"NY",
    "sg:tags":[
        "synagogue"
    ],
    "wof:name":"Congregation Lubavitch",
    "wof:placetype":"venue"
},
  "geometry": {"coordinates":[-73.942306,40.669219],"type":"Point"}
}