{
  "type": "Feature",
  "properties": {
    "iso:country":"US",
    "sg:address":"329 Erie St",
    "sg:city":"Buffalo",
    "sg:classifiers":[
        {
            "category":"Restaurant",
            "type":"Food & Drink"
        }
    ],
    "sg:phone":"+1 716 851 6501",
    "sg:postcode":"14202",
    "sg:province":"NY",
    "wof:name":"Hatch Restaurant",
    "wof:placetype":"venue"
},
  "geometry": {"coordinates":[-78.88456600000001,42.878731],"type":"Point"}
}