{
  "type": "Feature",
  "properties": {
    "addr:full":"7 Great Jones St New York NY 10012",
    "addr:housenumber":"7",
    "addr:postcode":"10012",
    "addr:street":"Great Jones St",
    "iso:country":"US",
    "sg:address":"7 Great Jones St",
    "sg:city":"New York",
    "sg:classifiers":[
        {
            "category":"Arts & Performance",
            "subcategory":"Theater",
            "type":"Entertainment"
        }
    ],
    "sg:phone":"+1 212 505 7267",
    "sg:postcode":"10012",
    "sg:province":"NY",
    "sg:tags":[
        "television",
        "program",
        "producer"
    ],
    "wof:name":"Diane Kolyer Productions",
    "wof:placetype":"venue"
},
  "geometry": {"coordinates":[-73.99382,40.727318],"type":"Point"}
}