{
  "type": "Feature",
  "properties": {
    "iso:country":"US",
    "sg:address":"2116 Teall Ave",
    "sg:city":"Syracuse",
    "sg:classifiers":[
        {
            "category":"Shopping",
            "subcategory":"Florist",
            "type":"Retail Goods"
        }
    ],
    "sg:phone":"+1 315 463 8687",
    "sg:postcode":"13206",
    "sg:province":"NY",
    "sg:tags":[
        "fresh",
        "flower",
        "gift"
    ],
    "wof:name":"Marge Polito Florist and Gifts",
    "wof:placetype":"venue"
},
  "geometry": {"coordinates":[-76.12342,43.080442],"type":"Point"}
}