{
  "type": "Feature",
  "properties": {
    "iso:country":"US",
    "sg:address":"1212 Forest Ave",
    "sg:city":"Staten Island",
    "sg:classifiers":[
        {
            "category":"Shopping",
            "subcategory":"Computers & Home Electronics",
            "type":"Retail Goods"
        }
    ],
    "sg:phone":"+1 718 808 0084",
    "sg:postcode":"10310",
    "sg:province":"NY",
    "sg:tags":[
        "equipment",
        "dealer"
    ],
    "wof:name":"NYC Computer",
    "wof:placetype":"venue"
},
  "geometry": {"coordinates":[-74.13131,40.626328],"type":"Point"}
}