{
  "type": "Feature",
  "properties": {
    "addr:full":"258 Hewes St Brooklyn NY 11211",
    "addr:housenumber":"258",
    "addr:postcode":"11211",
    "addr:street":"Hewes St",
    "iso:country":"US",
    "sg:address":"258 Hewes St",
    "sg:city":"Brooklyn",
    "sg:classifiers":[
        {
            "category":"Organizations",
            "subcategory":"Religious Organization",
            "type":"Services"
        }
    ],
    "sg:phone":"+1 718 782 1378",
    "sg:postcode":"11211",
    "sg:province":"NY",
    "sg:tags":[
        "clergy"
    ],
    "wof:name":"Elizabeth Horovitz",
    "wof:placetype":"venue"
},
  "geometry": {"coordinates":[-73.954345,40.705542],"type":"Point"}
}