{
  "type": "Feature",
  "properties": {
    "iso:country":"US",
    "sg:address":"139 Remsen St",
    "sg:city":"Cohoes",
    "sg:classifiers":[
        {
            "category":"Health Services",
            "subcategory":"Doctor",
            "type":"Services"
        }
    ],
    "sg:phone":"+1 518 237 3642",
    "sg:postcode":"12047",
    "sg:province":"NY",
    "sg:tags":[
        "dentist"
    ],
    "wof:name":"Michael Kowal DDS",
    "wof:placetype":"venue"
},
  "geometry": {"coordinates":[-73.700971,42.773386],"type":"Point"}
}