{
  "type": "Feature",
  "properties": {
    "iso:country":"US",
    "sg:address":"2804 Ave X",
    "sg:city":"Brooklyn",
    "sg:classifiers":[
        {
            "category":"Organizations",
            "subcategory":"Religious Organization",
            "type":"Services"
        }
    ],
    "sg:phone":"+1 718 646 4197",
    "sg:postcode":"11235",
    "sg:province":"NY",
    "sg:tags":[
        "clergy"
    ],
    "wof:name":"S Winter",
    "wof:placetype":"venue"
},
  "geometry": {"coordinates":[-73.941649,40.593613],"type":"Point"}
}