{
  "type": "Feature",
  "properties": {
    "iso:country":"US",
    "sg:address":"12 N Park Ave # A",
    "sg:city":"Rockville Centre",
    "sg:classifiers":[
        {
            "category":"Retail",
            "subcategory":"Portrait Studio",
            "type":"Services"
        },
        {
            "category":"Professional",
            "subcategory":"Art Services",
            "type":"Services"
        }
    ],
    "sg:phone":"+1 516 678 7180",
    "sg:postcode":"11570",
    "sg:province":"NY",
    "sg:tags":[
        "photographer",
        "photography",
        "store"
    ],
    "sg:website":"www.kornfeldstudios.com",
    "wof:name":"Kornfeld Studios",
    "wof:placetype":"venue"
},
  "geometry": {"coordinates":[-73.645798,40.6549],"type":"Point"}
}