{
  "type": "Feature",
  "properties": {
    "iso:country":"US",
    "sg:address":"189 Pleasant Grove Rd",
    "sg:city":"Ithaca",
    "sg:classifiers":[
        {
            "category":"Bars & Pubs",
            "type":"Food & Drink"
        },
        {
            "category":"Professional",
            "subcategory":"Employment Agencies",
            "type":"Services"
        },
        {
            "category":"Restaurant",
            "type":"Food & Drink"
        },
        {
            "category":"Organizations",
            "subcategory":"Membership Organization",
            "type":"Services"
        }
    ],
    "sg:phone":"+1 607 257 0011",
    "sg:postcode":"14850",
    "sg:province":"NY",
    "sg:tags":[
        "club",
        "workers'",
        "placement",
        "private",
        "volunteer"
    ],
    "wof:name":"Country Club Ithaca Pro Shop",
    "wof:placetype":"venue"
},
  "geometry": {"coordinates":[-76.477617,42.466784],"type":"Point"}
}