{
  "type": "Feature",
  "properties": {
    "addr:full":"642 High St Buffalo NY 14211",
    "addr:housenumber":"642",
    "addr:postcode":"14211",
    "addr:street":"High St",
    "iso:country":"US",
    "sg:address":"642 High St",
    "sg:city":"Buffalo",
    "sg:classifiers":[
        {
            "category":"Organizations",
            "subcategory":"Religious Organization",
            "type":"Services"
        }
    ],
    "sg:phone":"+1 716 894 2511",
    "sg:postcode":"14211",
    "sg:province":"NY",
    "sg:tags":[
        "church"
    ],
    "wof:name":"Revival Center Church Of God",
    "wof:placetype":"venue"
},
  "geometry": {"coordinates":[-78.844904,42.900191],"type":"Point"}
}