{
  "type": "Feature",
  "properties": {
    "addr:full":"231 E 53rd St New York NY 10022",
    "addr:housenumber":"231",
    "addr:postcode":"10022",
    "addr:street":"E 53Rd St",
    "iso:country":"US",
    "sg:address":"231 E 53rd St",
    "sg:city":"New York",
    "sg:classifiers":[
        {
            "category":"Personal",
            "subcategory":"Beauty Salon",
            "type":"Services"
        }
    ],
    "sg:phone":"+1 212 755 2623",
    "sg:postcode":"10022",
    "sg:province":"NY",
    "sg:tags":[
        "hair"
    ],
    "sg:website":"manishnyc.com/",
    "wof:name":"Manish Hair Salon",
    "wof:placetype":"venue"
},
  "geometry": {"coordinates":[-73.968694,40.757399],"type":"Point"}
}