{
  "type": "Feature",
  "properties": {
    "addr:full":"36 Somerston Rd Yorktown Heights NY 10598",
    "addr:housenumber":"36",
    "addr:postcode":"10598",
    "addr:street":"Somerston Rd",
    "iso:country":"US",
    "sg:address":"36 Somerston Rd",
    "sg:city":"Yorktown Heights",
    "sg:classifiers":[
        {
            "category":"Building & Trades",
            "subcategory":"Construction",
            "type":"Services"
        }
    ],
    "sg:phone":"+1 914 245 8742",
    "sg:postcode":"10598",
    "sg:province":"NY",
    "sg:tags":[
        "carpentry",
        "contractor"
    ],
    "wof:name":"Bova & Sons Inc",
    "wof:placetype":"venue"
},
  "geometry": {"coordinates":[-73.778266,41.326153],"type":"Point"}
}