{
  "type": "Feature",
  "properties": {
    "iso:country":"US",
    "sg:address":"335 Ronkonkoma Ave",
    "sg:city":"Ronkonkoma",
    "sg:classifiers":[
        {
            "category":"Retail",
            "subcategory":"Auto Repair",
            "type":"Services"
        }
    ],
    "sg:phone":"+1 631 585 0911",
    "sg:postcode":"11779",
    "sg:province":"NY",
    "sg:tags":[
        "body",
        "painting",
        "repairing",
        "automobile"
    ],
    "wof:name":"First Place Auto Works Inc",
    "wof:placetype":"venue"
},
  "geometry": {"coordinates":[-73.11166900000001,40.811456],"type":"Point"}
}