{
  "type": "Feature",
  "properties": {
    "iso:country":"US",
    "sg:address":"329 E 22nd St",
    "sg:city":"Manhattan",
    "sg:classifiers":[
        {
            "category":"Parking",
            "type":"Transportation"
        }
    ],
    "sg:phone":"+1 212 564 3199",
    "sg:postcode":"10010",
    "sg:province":"NY",
    "sg:website":"enterpriseparking.com",
    "wof:name":"Enterprise Parking Systems",
    "wof:placetype":"venue"
},
  "geometry": {"coordinates":[-73.979709,40.736757],"type":"Point"}
}