{
  "type": "Feature",
  "properties": {
    "iso:country":"US",
    "sg:address":"60 N Country Rd",
    "sg:city":"Port Jefferson",
    "sg:classifiers":[
        {
            "category":"Retail",
            "subcategory":"Repair Shop",
            "type":"Services"
        }
    ],
    "sg:phone":"+1 631 791 0032",
    "sg:postcode":"11777",
    "sg:province":"NY",
    "sg:tags":[
        "lock",
        "locksmith"
    ],
    "wof:name":"24 Hour Emergency Locksmith",
    "wof:placetype":"venue"
},
  "geometry": {"coordinates":[-73.054879,40.937674],"type":"Point"}
}