{
  "type": "Feature",
  "properties": {
    "iso:country":"US",
    "sg:address":"171 Maple Dr",
    "sg:city":"East Chatham",
    "sg:classifiers":[
        {
            "category":"Professional",
            "subcategory":"Business Services",
            "type":"Services"
        }
    ],
    "sg:phone":"+1 518 392 4513",
    "sg:postcode":"12060",
    "sg:province":"NY",
    "sg:tags":[
        "interior",
        "design"
    ],
    "wof:name":"Nelson Clifton A Jr Ltd",
    "wof:placetype":"venue"
},
  "geometry": {"coordinates":[-73.498299,42.4039],"type":"Point"}
}