{
  "type": "Feature",
  "properties": {
    "iso:country":"US",
    "sg:address":"14163 State Hwy 438",
    "sg:city":"Gowanda",
    "sg:classifiers":[
        {
            "category":"Wholesale",
            "subcategory":"Tobacco Products",
            "type":"Manufacturing & Wholesale Goods"
        }
    ],
    "sg:phone":"+1 716 532 2430",
    "sg:postcode":"14070",
    "sg:province":"NY",
    "wof:name":"Seneca Tobacco",
    "wof:placetype":"venue"
},
  "geometry": {"coordinates":[-78.94068900000001,42.479806],"type":"Point"}
}