{
  "type": "Feature",
  "properties": {
    "addr:full":"1 Heitz Pl Hicksville NY 11801",
    "addr:housenumber":"1",
    "addr:postcode":"11801",
    "addr:street":"Heitz Pl",
    "iso:country":"US",
    "sg:address":"1 Heitz Pl",
    "sg:city":"Hicksville",
    "sg:classifiers":[
        {
            "category":"Museum",
            "type":"Entertainment"
        }
    ],
    "sg:phone":"+1 516 822 7505",
    "sg:postcode":"11801",
    "sg:province":"NY",
    "wof:name":"Hicksville Gregory Museum",
    "wof:placetype":"venue"
},
  "geometry": {"coordinates":[-73.51771599999999,40.769985],"type":"Point"}
}