{
  "type": "Feature",
  "properties": {
    "addr:full":"1128 Ridge Rd Queensbury NY 12804",
    "addr:housenumber":"1128",
    "addr:postcode":"12804",
    "addr:street":"Ridge Rd",
    "iso:country":"US",
    "sg:address":"1128 Ridge Rd",
    "sg:city":"Queensbury",
    "sg:classifiers":[
        {
            "category":"Wholesale",
            "subcategory":"Groceries",
            "type":"Manufacturing & Wholesale Goods"
        }
    ],
    "sg:phone":"+1 518 792 9541",
    "sg:postcode":"12804",
    "sg:province":"NY",
    "sg:tags":[
        "general"
    ],
    "wof:name":"Shahays Country Store",
    "wof:placetype":"venue"
},
  "geometry": {"coordinates":[-73.628317,43.372201],"type":"Point"}
}