{
  "type": "Feature",
  "properties": {
    "iso:country":"US",
    "sg:address":"120 Broadway",
    "sg:city":"Newburgh",
    "sg:classifiers":[
        {
            "category":"Food & Beverages",
            "subcategory":"Groceries & Convenience Stores",
            "type":"Retail Goods"
        }
    ],
    "sg:phone":"+1 845 561 3964",
    "sg:postcode":"12550",
    "sg:province":"NY",
    "wof:name":"Hudson Valley Market",
    "wof:placetype":"venue"
},
  "geometry": {"coordinates":[-74.19972,41.500212],"type":"Point"}
}