{
  "type": "Feature",
  "properties": {
    "addr:full":"1850 Steinway St Astoria NY 11105",
    "addr:housenumber":"1850",
    "addr:postcode":"11105",
    "addr:street":"Steinway St",
    "iso:country":"US",
    "sg:address":"1850 Steinway St",
    "sg:city":"Astoria",
    "sg:classifiers":[
        {
            "category":"Building & Trades",
            "subcategory":"Electrical",
            "type":"Services"
        }
    ],
    "sg:phone":"+1 718 204 0864",
    "sg:postcode":"11105",
    "sg:province":"NY",
    "sg:tags":[
        "electrician"
    ],
    "wof:name":"Anna Electrical Corp",
    "wof:placetype":"venue"
},
  "geometry": {"coordinates":[-73.899002,40.778801],"type":"Point"}
}