{
  "type": "Feature",
  "properties": {
    "iso:country":"US",
    "sg:address":"30 W Bayard St",
    "sg:city":"Seneca Falls",
    "sg:classifiers":[
        {
            "category":"Home & Garden",
            "subcategory":"Furniture",
            "type":"Retail Goods"
        }
    ],
    "sg:phone":"+1 315 568 9431",
    "sg:postcode":"13148",
    "sg:province":"NY",
    "sg:tags":[
        "equipment",
        "kitchen",
        "cabinet"
    ],
    "sg:website":"www.ferraralumber.com",
    "wof:name":"Ferrara Lumber",
    "wof:placetype":"venue"
},
  "geometry": {"coordinates":[-76.79733,42.908515],"type":"Point"}
}