{
  "type": "Feature",
  "properties": {
    "addr:full":"102 N Main St Spencer NY 14883",
    "addr:housenumber":"102",
    "addr:postcode":"14883",
    "addr:street":"N Main St",
    "iso:country":"US",
    "sg:address":"102 N Main St",
    "sg:city":"Spencer",
    "sg:classifiers":[
        {
            "category":"Cafe",
            "type":"Food & Drink"
        }
    ],
    "sg:menulink":"http://www.allmenus.com/ny/spencer/255198-main-street-cafe/menu/",
    "sg:phone":"+1 607 589 7400",
    "sg:postcode":"14883",
    "sg:province":"NY",
    "wof:name":"Main Street Cafe",
    "wof:placetype":"venue"
},
  "geometry": {"coordinates":[-76.492769,42.215734],"type":"Point"}
}