{
  "type": "Feature",
  "properties": {
    "iso:country":"US",
    "sg:address":"829 Washington St 2nd Fl C",
    "sg:city":"Peekskill",
    "sg:classifiers":[
        {
            "category":"Social Services",
            "type":"Services"
        },
        {
            "category":"Social Services",
            "subcategory":"Adult Care",
            "type":"Services"
        }
    ],
    "sg:phone":"+1 914 862 0033",
    "sg:postcode":"10566",
    "sg:province":"NY",
    "sg:tags":[
        "suicide",
        "crisis",
        "prevention",
        "intervention"
    ],
    "wof:name":"Two Skies Inc.",
    "wof:placetype":"venue"
},
  "geometry": {"coordinates":[-73.928057,41.275987],"type":"Point"}
}