{
  "type": "Feature",
  "properties": {
    "addr:full":"1166 Manhattan Ave Brooklyn NY 11222",
    "addr:housenumber":"1166",
    "addr:postcode":"11222",
    "addr:street":"Manhattan Ave",
    "iso:country":"US",
    "sg:address":"1166 Manhattan Ave",
    "sg:city":"Brooklyn",
    "sg:classifiers":[
        {
            "category":"Retail",
            "subcategory":"Portrait Studio",
            "type":"Services"
        },
        {
            "category":"Professional",
            "subcategory":"Art Services",
            "type":"Services"
        }
    ],
    "sg:phone":"+1 718 486 3100",
    "sg:postcode":"11222",
    "sg:province":"NY",
    "sg:tags":[
        "photographer",
        "photography",
        "store"
    ],
    "wof:name":"Kanji Ishii Photography",
    "wof:placetype":"venue"
},
  "geometry": {"coordinates":[-73.95503600000001,40.738275],"type":"Point"}
}