{
  "type": "Feature",
  "properties": {
    "addr:full":"3141 Broadway New York NY 10027",
    "addr:housenumber":"3141",
    "addr:postcode":"10027",
    "addr:street":"Broadway",
    "iso:country":"US",
    "sg:address":"3141 Broadway",
    "sg:city":"New York",
    "sg:classifiers":[
        {
            "category":"Restaurant",
            "type":"Food & Drink"
        }
    ],
    "sg:menulink":"http://www.allmenus.com/ny/new-york/17612-hana-sushi/menu/",
    "sg:phone":"+1 212 316 4761",
    "sg:postcode":"10027",
    "sg:province":"NY",
    "sg:tags":[
        "sushi",
        "japanese",
        "chinese",
        "asian"
    ],
    "wof:name":"Hana Sushi",
    "wof:placetype":"venue"
},
  "geometry": {"coordinates":[-73.959641,40.814071],"type":"Point"}
}