{
  "type": "Feature",
  "properties": {
    "addr:full":"100 Executive Blvd Ossining NY 10562",
    "addr:housenumber":"100",
    "addr:postcode":"10562",
    "addr:street":"Executive Blvd",
    "iso:country":"US",
    "sg:address":"100 Executive Blvd",
    "sg:city":"Ossining",
    "sg:classifiers":[
        {
            "category":"Manufacturing",
            "subcategory":"Printing",
            "type":"Manufacturing & Wholesale Goods"
        }
    ],
    "sg:phone":"+1 914 762 4020",
    "sg:postcode":"10562",
    "sg:province":"NY",
    "sg:tags":[
        "publisher"
    ],
    "wof:name":"Egerton Group LTD",
    "wof:placetype":"venue"
},
  "geometry": {"coordinates":[-73.856853,41.183988],"type":"Point"}
}