{
  "type": "Feature",
  "properties": {
    "addr:full":"50 Medford Ave Patchogue NY 11772",
    "addr:housenumber":"50",
    "addr:postcode":"11772",
    "addr:street":"Medford Ave",
    "iso:country":"US",
    "sg:address":"50 Medford Ave",
    "sg:city":"Patchogue",
    "sg:classifiers":[
        {
            "category":"Professional",
            "subcategory":"Lawyer & Legal Services",
            "type":"Services"
        }
    ],
    "sg:phone":"+1   ",
    "sg:postcode":"11772",
    "sg:province":"NY",
    "wof:name":"Wasserman & Steen",
    "wof:placetype":"venue"
},
  "geometry": {"coordinates":[-73.00711200000001,40.766938],"type":"Point"}
}