{
  "type": "Feature",
  "properties": {
    "iso:country":"US",
    "sg:address":"262 W 38th St",
    "sg:city":"New York",
    "sg:classifiers":[
        {
            "category":"Wholesale",
            "subcategory":"Drugs",
            "type":"Manufacturing & Wholesale Goods"
        }
    ],
    "sg:phone":"+1 212 391 4960",
    "sg:postcode":"10018",
    "sg:province":"NY",
    "wof:name":"Sepia Makeup",
    "wof:placetype":"venue"
},
  "geometry": {"coordinates":[-73.99030500000001,40.753887],"type":"Point"}
}