{
  "type": "Feature",
  "properties": {
    "addr:full":"160 S Travis St Lindenhurst NY 11757",
    "addr:housenumber":"160",
    "addr:postcode":"11757",
    "addr:street":"S Travis St",
    "iso:country":"US",
    "sg:address":"160 S Travis St",
    "sg:city":"Lindenhurst",
    "sg:classifiers":[
        {
            "category":"Retail",
            "subcategory":"Repair Shop",
            "type":"Services"
        }
    ],
    "sg:phone":"+1 631 229 0364",
    "sg:postcode":"11757",
    "sg:province":"NY",
    "sg:tags":[
        "lock",
        "locksmith"
    ],
    "wof:name":"1 Hour Emergency Locksmith",
    "wof:placetype":"venue"
},
  "geometry": {"coordinates":[-73.370437,40.686611],"type":"Point"}
}