{
  "type": "Feature",
  "properties": {
    "iso:country":"US",
    "sg:address":"482 S Cascade Dr",
    "sg:city":"Springville",
    "sg:classifiers":[
        {
            "category":"Building & Trades",
            "subcategory":"Pest Control",
            "type":"Services"
        }
    ],
    "sg:phone":"+1 716 592 3552",
    "sg:postcode":"14141",
    "sg:province":"NY",
    "wof:name":"Birds & The Bees",
    "wof:placetype":"venue"
},
  "geometry": {"coordinates":[-78.690647,42.497849],"type":"Point"}
}