{
  "type": "Feature",
  "properties": {
    "iso:country":"US",
    "sg:address":"5012 October Dr",
    "sg:city":"Syracuse",
    "sg:classifiers":[
        {
            "category":"Building & Trades",
            "subcategory":"Equipment Rental",
            "type":"Services"
        }
    ],
    "sg:phone":"+1 315 487 5228",
    "sg:postcode":"13215",
    "sg:province":"NY",
    "sg:tags":[
        "yard",
        "leasing",
        "store"
    ],
    "wof:name":"Elizabeth Ribarovski",
    "wof:placetype":"venue"
},
  "geometry": {"coordinates":[-76.215701,43.01357],"type":"Point"}
}