{
  "type": "Feature",
  "properties": {
    "addr:full":"214 E 11th St 2D New York NY 10003",
    "addr:housenumber":"214;2d",
    "addr:postcode":"10003",
    "addr:street":"E 11Th St",
    "iso:country":"US",
    "sg:address":"214 E 11th St 2D",
    "sg:city":"New York",
    "sg:classifiers":[
        {
            "category":"Building & Trades",
            "subcategory":"Cleaning & Sanitation",
            "type":"Services"
        }
    ],
    "sg:phone":"+1 646 919 0066",
    "sg:postcode":"10003",
    "sg:province":"NY",
    "sg:tags":[
        "home"
    ],
    "wof:name":"The Wright Cleaning Crew",
    "wof:placetype":"venue"
},
  "geometry": {"coordinates":[-73.987892,40.730785],"type":"Point"}
}