{
  "type": "Feature",
  "properties": {
    "addr:full":"46 Leo Ln Poughquag NY 12570",
    "addr:housenumber":"46",
    "addr:postcode":"12570",
    "addr:street":"Leo Ln",
    "iso:country":"US",
    "sg:address":"46 Leo Ln",
    "sg:city":"Poughquag",
    "sg:classifiers":[
        {
            "category":"Building & Trades",
            "subcategory":"Landscaping Services",
            "type":"Services"
        }
    ],
    "sg:phone":"+1 845 227 9172",
    "sg:postcode":"12570",
    "sg:province":"NY",
    "sg:tags":[
        "landscape"
    ],
    "wof:name":"Bisesto Landscaping",
    "wof:placetype":"venue"
},
  "geometry": {"coordinates":[-73.711923,41.587499],"type":"Point"}
}