{
  "type": "Feature",
  "properties": {
    "iso:country":"US",
    "sg:address":"40 Catherwood Rd Ste 17",
    "sg:city":"Ithaca",
    "sg:classifiers":[
        {
            "category":"Food & Beverages",
            "subcategory":"Specialty",
            "type":"Retail Goods"
        }
    ],
    "sg:phone":"+1 607 257 0394",
    "sg:postcode":"14850",
    "sg:province":"NY",
    "sg:tags":[
        "supplement",
        "vitamin"
    ],
    "sg:website":"http://www.vitaminworld.com",
    "wof:name":"Vitamin World 2143",
    "wof:placetype":"venue"
},
  "geometry": {"coordinates":[-76.486621,42.483746],"type":"Point"}
}