{
  "type": "Feature",
  "properties": {
    "iso:country":"US",
    "sg:address":"19 Sills Ct",
    "sg:city":"Centerport",
    "sg:classifiers":[
        {
            "category":"Professional",
            "type":"Services"
        }
    ],
    "sg:phone":"+1 631 757 6060",
    "sg:postcode":"11721",
    "sg:province":"NY",
    "sg:tags":[
        "establishment"
    ],
    "wof:name":"Wheeler-Blackman Agency Inc",
    "wof:placetype":"venue"
},
  "geometry": {"coordinates":[-73.368526,40.895554],"type":"Point"}
}