{
  "type": "Feature",
  "properties": {
    "addr:full":"238 Mott Street New York NY 10012",
    "addr:housenumber":"238",
    "addr:postcode":"10012",
    "addr:street":"Mott Street",
    "iso:country":"US",
    "sg:address":"238 Mott Street",
    "sg:city":"New York",
    "sg:classifiers":[
        {
            "category":"Shopping",
            "subcategory":"Jewelry",
            "type":"Retail Goods"
        }
    ],
    "sg:phone":"+1 888 841 1109",
    "sg:postcode":"10012",
    "sg:province":"NY",
    "wof:name":"Gas Bijoux",
    "wof:placetype":"venue"
},
  "geometry": {"coordinates":[-73.99479700000001,40.722698],"type":"Point"}
}