{
  "type": "Feature",
  "properties": {
    "iso:country":"US",
    "sg:address":"25 Archer Ave",
    "sg:city":"Mount Vernon",
    "sg:classifiers":[
        {
            "category":"Professional",
            "type":"Services"
        }
    ],
    "sg:phone":"+1   ",
    "sg:postcode":"10550",
    "sg:province":"NY",
    "wof:name":"Vernon Pavers Inc",
    "wof:placetype":"venue"
},
  "geometry": {"coordinates":[-73.83191600000001,40.914326],"type":"Point"}
}