{
  "type": "Feature",
  "properties": {
    "addr:full":"11 Leonard St New York NY 10013",
    "addr:housenumber":"11",
    "addr:postcode":"10013",
    "addr:street":"Leonard St",
    "iso:country":"US",
    "sg:address":"11 Leonard St",
    "sg:city":"New York",
    "sg:classifiers":[
        {
            "category":"Real Estate",
            "subcategory":"Real Estate Operator",
            "type":"Services"
        }
    ],
    "sg:phone":"+1 212 219 1783",
    "sg:postcode":"10013",
    "sg:province":"NY",
    "sg:tags":[
        "building"
    ],
    "wof:name":"Leonard St Associates LLC",
    "wof:placetype":"venue"
},
  "geometry": {"coordinates":[-74.00741499999999,40.718571],"type":"Point"}
}