{
  "type": "Feature",
  "properties": {
    "addr:full":"1225 Main St Niagara Falls NY 14301",
    "addr:housenumber":"1225",
    "addr:postcode":"14301",
    "addr:street":"Main St",
    "iso:country":"US",
    "sg:address":"1225 Main St",
    "sg:city":"Niagara Falls",
    "sg:classifiers":[
        {
            "category":"Shopping",
            "subcategory":"Florist",
            "type":"Retail Goods"
        }
    ],
    "sg:phone":"+1   ",
    "sg:postcode":"14301",
    "sg:province":"NY",
    "wof:name":"S Russon Inc",
    "wof:placetype":"venue"
},
  "geometry": {"coordinates":[-79.05263600000001,43.100631],"type":"Point"}
}