{
  "type": "Feature",
  "properties": {
    "addr:full":"560 S 3rd Ave Mt Vernon NY 10550",
    "addr:housenumber":"560",
    "addr:postcode":"10550",
    "addr:street":"S 3Rd Ave",
    "iso:country":"US",
    "sg:address":"560 S 3rd Ave",
    "sg:city":"Mt Vernon",
    "sg:classifiers":[
        {
            "category":"Wholesale",
            "subcategory":"Electrical",
            "type":"Manufacturing & Wholesale Goods"
        }
    ],
    "sg:phone":"+1 914 237 4000",
    "sg:postcode":"10550",
    "sg:province":"NY",
    "sg:tags":[
        "equipment",
        "electronic",
        "supply"
    ],
    "wof:name":"Amco-Mc Lean Corp",
    "wof:placetype":"venue"
},
  "geometry": {"coordinates":[-73.83015,40.897814],"type":"Point"}
}