{
  "type": "Feature",
  "properties": {
    "addr:full":"188 Montague St Brooklyn NY 11201",
    "addr:housenumber":"188",
    "addr:postcode":"11201",
    "addr:street":"Montague St",
    "iso:country":"US",
    "sg:address":"188 Montague St",
    "sg:city":"Brooklyn",
    "sg:classifiers":[
        {
            "category":"Professional",
            "subcategory":"Business Services",
            "type":"Services"
        },
        {
            "category":"Professional",
            "subcategory":"Secretarial Services",
            "type":"Services"
        }
    ],
    "sg:phone":"+1 718 246 9521",
    "sg:postcode":"11201",
    "sg:province":"NY",
    "sg:tags":[
        "reporting"
    ],
    "wof:name":"Barrister Reporting Service",
    "wof:placetype":"venue"
},
  "geometry": {"coordinates":[-73.99115399999999,40.69391],"type":"Point"}
}