{
  "type": "Feature",
  "properties": {
    "addr:full":"1123 Brighton Beach Ave Brooklyn NY 11235",
    "addr:housenumber":"1123",
    "addr:postcode":"11235",
    "addr:street":"Brighton Beach Ave",
    "iso:country":"US",
    "sg:address":"1123 Brighton Beach Ave",
    "sg:city":"Brooklyn",
    "sg:classifiers":[
        {
            "category":"Shopping",
            "subcategory":"Gifts & Souvenirs",
            "type":"Retail Goods"
        }
    ],
    "sg:phone":"+1 718 648 1410",
    "sg:postcode":"11235",
    "sg:province":"NY",
    "sg:tags":[
        "shop"
    ],
    "wof:name":"Heybe Gift",
    "wof:placetype":"venue"
},
  "geometry": {"coordinates":[-73.956408,40.577988],"type":"Point"}
}