{
  "type": "Feature",
  "properties": {
    "addr:full":"241 Cabrini Blvd New York NY 10033",
    "addr:housenumber":"241",
    "addr:postcode":"10033",
    "addr:street":"Cabrini Blvd",
    "iso:country":"US",
    "sg:address":"241 Cabrini Blvd",
    "sg:city":"New York",
    "sg:classifiers":[
        {
            "category":"Real Estate",
            "subcategory":"Real Estate Services",
            "type":"Services"
        }
    ],
    "sg:phone":"+1 212 928 5100",
    "sg:postcode":"10033",
    "sg:province":"NY",
    "sg:website":"www.simonesong.com",
    "wof:name":"Simone Song Properties",
    "wof:placetype":"venue"
},
  "geometry": {"coordinates":[-73.938126,40.855318],"type":"Point"}
}