{
  "type": "Feature",
  "properties": {
    "addr:full":"43 W 13 St New York NY 10011",
    "addr:housenumber":"43",
    "addr:postcode":"10011",
    "addr:street":"W 13 St",
    "iso:country":"US",
    "sg:address":"43 W 13 St",
    "sg:city":"New York",
    "sg:classifiers":[
        {
            "category":"Professional",
            "type":"Services"
        }
    ],
    "sg:phone":"+1 212 989 9631",
    "sg:postcode":"10011",
    "sg:province":"NY",
    "sg:tags":[
        "establishment"
    ],
    "wof:name":"Lasalla Designs LLC",
    "wof:placetype":"venue"
},
  "geometry": {"coordinates":[-73.996257,40.736153],"type":"Point"}
}