{
  "type": "Feature",
  "properties": {
    "addr:full":"1 Tudor City Pl New York NY 10017",
    "addr:housenumber":"1",
    "addr:postcode":"10017",
    "addr:street":"Tudor City Pl",
    "iso:country":"US",
    "sg:address":"1 Tudor City Pl",
    "sg:city":"New York",
    "sg:classifiers":[
        {
            "category":"Retail",
            "subcategory":"Laundry & Dry Cleaning",
            "type":"Services"
        }
    ],
    "sg:phone":"+1   ",
    "sg:postcode":"10017",
    "sg:province":"NY",
    "sg:tags":[
        "drycleaning",
        "plant"
    ],
    "wof:name":"Tudor Cleaner Inc",
    "wof:placetype":"venue"
},
  "geometry": {"coordinates":[-73.97093599999999,40.748407],"type":"Point"}
}