{
  "type": "Feature",
  "properties": {
    "iso:country":"US",
    "sg:address":"192 Erie St",
    "sg:city":"Lancaster",
    "sg:classifiers":[
        {
            "category":"Manufacturing",
            "subcategory":"Rubber & Plastics",
            "type":"Manufacturing & Wholesale Goods"
        }
    ],
    "sg:phone":"+1 716 684 8628",
    "sg:postcode":"14086",
    "sg:province":"NY",
    "sg:tags":[
        "gasket"
    ],
    "sg:website":"www.quickcutgasket.com",
    "wof:name":"Quick Cut Gasket & Rubber Corp",
    "wof:placetype":"venue"
},
  "geometry": {"coordinates":[-78.66125599999999,42.90621],"type":"Point"}
}