{
  "type": "Feature",
  "properties": {
    "addr:full":"55 E 87th St New York NY 10128",
    "addr:housenumber":"55",
    "addr:postcode":"10128",
    "addr:street":"E 87Th St",
    "iso:country":"US",
    "sg:address":"55 E 87th St",
    "sg:city":"New York",
    "sg:classifiers":[
        {
            "category":"Building & Trades",
            "subcategory":"Construction",
            "type":"Services"
        }
    ],
    "sg:phone":"+1 212 465 1808",
    "sg:postcode":"10128",
    "sg:province":"NY",
    "sg:tags":[
        "interior",
        "design"
    ],
    "wof:name":"Barbara Ostrom Associates Inc",
    "wof:placetype":"venue"
},
  "geometry": {"coordinates":[-73.95819899999999,40.781502],"type":"Point"}
}