{
  "type": "Feature",
  "properties": {
    "addr:full":"105 N Main St Wellsville NY 14895",
    "addr:housenumber":"105",
    "addr:postcode":"14895",
    "addr:street":"N Main St",
    "iso:country":"US",
    "sg:address":"105 N Main St",
    "sg:city":"Wellsville",
    "sg:classifiers":[
        {
            "category":"Restaurant",
            "type":"Food & Drink"
        }
    ],
    "sg:phone":"+1 585 593 2223",
    "sg:postcode":"14895",
    "sg:province":"NY",
    "wof:name":"L'Italia Restaurant",
    "wof:placetype":"venue"
},
  "geometry": {"coordinates":[-77.947898,42.121699],"type":"Point"}
}