{
  "type": "Feature",
  "properties": {
    "addr:full":"730 Alberta Dr Amherst NY 14226",
    "addr:housenumber":"730",
    "addr:postcode":"14226",
    "addr:street":"Alberta Dr",
    "iso:country":"US",
    "sg:address":"730 Alberta Dr",
    "sg:city":"Amherst",
    "sg:classifiers":[
        {
            "category":"Sports & Exercise",
            "subcategory":"Gym",
            "type":"Entertainment"
        }
    ],
    "sg:phone":"+1 716 834 5743",
    "sg:postcode":"14226",
    "sg:province":"NY",
    "sg:tags":[
        "club",
        "health",
        "studio",
        "gymnasium"
    ],
    "wof:name":"Body EFX",
    "wof:placetype":"venue"
},
  "geometry": {"coordinates":[-78.817322,42.988247],"type":"Point"}
}