{
  "type": "Feature",
  "properties": {
    "iso:country":"US",
    "sg:address":"21 Maple Ridge",
    "sg:city":"Ballston Lake",
    "sg:classifiers":[
        {
            "category":"Professional",
            "subcategory":"Management & Consulting",
            "type":"Services"
        }
    ],
    "sg:phone":"+1 518 877 5237",
    "sg:postcode":"12019",
    "sg:province":"NY",
    "sg:tags":[
        "consultant",
        "business"
    ],
    "wof:name":"Remedial Waste Solutions",
    "wof:placetype":"venue"
},
  "geometry": {"coordinates":[-73.80273,42.921322],"type":"Point"}
}