{
  "type": "Feature",
  "properties": {
    "addr:full":"29 Bowery New York NY 10002",
    "addr:housenumber":"29",
    "addr:postcode":"10002",
    "addr:street":"Bowery",
    "iso:country":"US",
    "sg:address":"29 Bowery",
    "sg:city":"New York",
    "sg:classifiers":[
        {
            "category":"Restaurant",
            "type":"Food & Drink"
        }
    ],
    "sg:phone":"+1   ",
    "sg:postcode":"10002",
    "sg:province":"NY",
    "sg:tags":[
        "banking"
    ],
    "wof:name":"Hong Kong & Shanghai Bnkg Corp",
    "wof:placetype":"venue"
},
  "geometry": {"coordinates":[-73.996876,40.71473],"type":"Point"}
}