{
  "type": "Feature",
  "properties": {
    "addr:full":"9465 Corona Avenue Elmhurst NY 11373",
    "addr:housenumber":"9465",
    "addr:postcode":"11373",
    "addr:street":"Corona Avenue",
    "iso:country":"US",
    "sg:address":"9465 Corona Avenue",
    "sg:city":"Elmhurst",
    "sg:classifiers":[
        {
            "category":"Bakery",
            "type":"Food & Drink"
        }
    ],
    "sg:phone":"+1 718 271 5422",
    "sg:postcode":"11373",
    "sg:province":"NY",
    "sg:website":"www.paradero.com/riodelaplata/",
    "wof:name":"Rio De La Plata Bakery Shop",
    "wof:placetype":"venue"
},
  "geometry": {"coordinates":[-73.867575,40.742213],"type":"Point"}
}