{
  "type": "Feature",
  "properties": {
    "addr:full":"77 Mercer St New York NY 10012",
    "addr:housenumber":"77",
    "addr:postcode":"10012",
    "addr:street":"Mercer St",
    "iso:country":"US",
    "sg:address":"77 Mercer St",
    "sg:city":"New York",
    "sg:classifiers":[
        {
            "category":"Arts & Performance",
            "subcategory":"Art Gallery",
            "type":"Entertainment"
        }
    ],
    "sg:phone":"+1 917 449 2683",
    "sg:postcode":"10012",
    "sg:province":"NY",
    "wof:name":"Fitzroy Gallery",
    "wof:placetype":"venue"
},
  "geometry": {"coordinates":[-74.000393,40.722697],"type":"Point"}
}