{
  "type": "Feature",
  "properties": {
    "iso:country":"US",
    "sg:address":"44 Parnell Dr",
    "sg:city":"Smithtown",
    "sg:classifiers":[
        {
            "category":"Home & Garden",
            "subcategory":"Building Materials",
            "type":"Retail Goods"
        },
        {
            "category":"Building & Trades",
            "subcategory":"Construction",
            "type":"Services"
        }
    ],
    "sg:phone":"+1 631 382 9379",
    "sg:postcode":"11787",
    "sg:province":"NY",
    "sg:tags":[
        "industrial",
        "builder",
        "contractor",
        "contractors-commercial",
        "masonry",
        "mason",
        "gazebo",
        "patio"
    ],
    "wof:name":"Majestic Decks & Masonry",
    "wof:placetype":"venue"
},
  "geometry": {"coordinates":[-73.238373,40.85252],"type":"Point"}
}