{
  "type": "Feature",
  "properties": {
    "addr:full":"34 Geneva St Bath NY 14810",
    "addr:housenumber":"34",
    "addr:postcode":"14810",
    "addr:street":"Geneva St",
    "iso:country":"US",
    "sg:address":"34 Geneva St",
    "sg:city":"Bath",
    "sg:classifiers":[
        {
            "category":"Professional",
            "subcategory":"Art Services",
            "type":"Services"
        }
    ],
    "sg:phone":"+1 607 776 3271",
    "sg:postcode":"14810",
    "sg:province":"NY",
    "sg:tags":[
        "designer",
        "display",
        "producer"
    ],
    "wof:name":"Beautiful Treasurers",
    "wof:placetype":"venue"
},
  "geometry": {"coordinates":[-77.315338,42.342024],"type":"Point"}
}