{
  "type": "Feature",
  "properties": {
    "iso:country":"US",
    "sg:address":"1473 Sterling Pl",
    "sg:city":"Brooklyn",
    "sg:classifiers":[
        {
            "category":"Health Services",
            "subcategory":"Doctor",
            "type":"Services"
        }
    ],
    "sg:phone":"+1 718 756 3939",
    "sg:postcode":"11213",
    "sg:province":"NY",
    "sg:tags":[
        "medical"
    ],
    "wof:name":"Ahmad Syeed",
    "wof:placetype":"venue"
},
  "geometry": {"coordinates":[-73.928101,40.671299],"type":"Point"}
}