{
  "type": "Feature",
  "properties": {
    "iso:country":"US",
    "sg:address":"206 George St",
    "sg:city":"Syracuse",
    "sg:classifiers":[
        {
            "category":"Wholesale",
            "subcategory":"Machinery & Supplies",
            "type":"Manufacturing & Wholesale Goods"
        }
    ],
    "sg:phone":"+1 315 458 3909",
    "sg:postcode":"13212",
    "sg:province":"NY",
    "sg:tags":[
        "designed",
        "specially"
    ],
    "wof:name":"Empire Design Services",
    "wof:placetype":"venue"
},
  "geometry": {"coordinates":[-76.13285500000001,43.136296],"type":"Point"}
}