{
  "type": "Feature",
  "properties": {
    "addr:full":"61 Fulton St Brentwood NY 11717",
    "addr:housenumber":"61",
    "addr:postcode":"11717",
    "addr:street":"Fulton St",
    "iso:country":"US",
    "sg:address":"61 Fulton St",
    "sg:city":"Brentwood",
    "sg:classifiers":[
        {
            "category":"Education",
            "subcategory":"Special Training",
            "type":"Public Place"
        }
    ],
    "sg:phone":"+1 631 273 8835",
    "sg:postcode":"11717",
    "sg:province":"NY",
    "sg:tags":[
        "instruction",
        "driving"
    ],
    "wof:name":"Paris Auto School",
    "wof:placetype":"venue"
},
  "geometry": {"coordinates":[-73.233126,40.797231],"type":"Point"}
}