{
  "type": "Feature",
  "properties": {
    "addr:full":"2412 3rd Ave Bronx NY 10454",
    "addr:housenumber":"2412",
    "addr:postcode":"10454",
    "addr:street":"3Rd Ave",
    "iso:country":"US",
    "sg:address":"2412 3rd Ave",
    "sg:city":"Bronx",
    "sg:classifiers":[
        {
            "category":"Restaurant",
            "type":"Food & Drink"
        }
    ],
    "sg:phone":"+1 718 665 2001",
    "sg:postcode":"10454",
    "sg:province":"NY",
    "wof:name":"Bruckner Bar & Grill",
    "wof:placetype":"venue"
},
  "geometry": {"coordinates":[-73.93010700000001,40.808771],"type":"Point"}
}