{
  "type": "Feature",
  "properties": {
    "iso:country":"US",
    "sg:address":"511 Montauk Hwy",
    "sg:city":"Eastport",
    "sg:classifiers":[
        {
            "category":"Shopping",
            "subcategory":"Used Merchandise",
            "type":"Retail Goods"
        }
    ],
    "sg:phone":"+1   ",
    "sg:postcode":"11941",
    "sg:province":"NY",
    "wof:name":"Finest Kind",
    "wof:placetype":"venue"
},
  "geometry": {"coordinates":[-72.730665,40.825694],"type":"Point"}
}