{
  "type": "Feature",
  "properties": {
    "iso:country":"US",
    "sg:address":"Flatlands Ave",
    "sg:city":"Queens",
    "sg:classifiers":[
        {
            "category":"Landmark",
            "subcategory":"Historic",
            "type":"Public Place"
        }
    ],
    "sg:postcode":"11419",
    "sg:province":"NY",
    "sg:tags":[
        "building",
        "historical"
    ],
    "sg:website":"www.nycgovparks.org/parks/B207/",
    "wof:name":"Sarsfield Playground",
    "wof:placetype":"venue"
},
  "geometry": {"coordinates":[-73.89079700000001,40.65054],"type":"Point"}
}