{
  "type": "Feature",
  "properties": {
    "addr:full":"440 Warburton Ave Yonkers NY 10701",
    "addr:housenumber":"440",
    "addr:postcode":"10701",
    "addr:street":"Warburton Ave",
    "iso:country":"US",
    "sg:address":"440 Warburton Ave",
    "sg:city":"Yonkers",
    "sg:classifiers":[
        {
            "category":"Real Estate",
            "subcategory":"Real Estate Agent",
            "type":"Services"
        }
    ],
    "sg:phone":"+1 914 966 8951",
    "sg:postcode":"10701",
    "sg:province":"NY",
    "wof:name":"Grace International Rl Est",
    "wof:placetype":"venue"
},
  "geometry": {"coordinates":[-73.896126,40.94918],"type":"Point"}
}