{
  "type": "Feature",
  "properties": {
    "addr:full":"2329 Sheridan Dr Tonawanda NY 14150",
    "addr:housenumber":"2329",
    "addr:postcode":"14150",
    "addr:street":"Sheridan Dr",
    "iso:country":"US",
    "sg:address":"2329 Sheridan Dr",
    "sg:city":"Tonawanda",
    "sg:classifiers":[
        {
            "category":"Bars & Pubs",
            "type":"Food & Drink"
        },
        {
            "category":"Deli",
            "type":"Food & Drink"
        }
    ],
    "sg:menulink":"http://www.allmenus.com/ny/tonawanda/245864-the-deuce-bar--grill/menu/",
    "sg:phone":"+1 716 862 0591",
    "sg:postcode":"14150",
    "sg:province":"NY",
    "sg:tags":[
        "american"
    ],
    "wof:name":"The Deuce Bar & Grill",
    "wof:placetype":"venue"
},
  "geometry": {"coordinates":[-78.847488,42.980777],"type":"Point"}
}