{
  "type": "Feature",
  "properties": {
    "addr:full":"101 Steamboat Rd Great Neck NY 11024",
    "addr:housenumber":"101",
    "addr:postcode":"11024",
    "addr:street":"Steamboat Rd",
    "iso:country":"US",
    "sg:address":"101 Steamboat Rd",
    "sg:city":"Great Neck",
    "sg:classifiers":[
        {
            "category":"Retail",
            "subcategory":"Portrait Studio",
            "type":"Services"
        }
    ],
    "sg:phone":"+1 516 829 0800",
    "sg:postcode":"11024",
    "sg:province":"NY",
    "sg:tags":[
        "photographer"
    ],
    "wof:name":"Best Picture",
    "wof:placetype":"venue"
},
  "geometry": {"coordinates":[-73.74663700000001,40.808121],"type":"Point"}
}