{
  "type": "Feature",
  "properties": {
    "addr:full":"99 E 198th St Bronx NY 10468",
    "addr:housenumber":"99",
    "addr:postcode":"10468",
    "addr:street":"E 198Th St",
    "iso:country":"US",
    "sg:address":"99 E 198th St",
    "sg:city":"Bronx",
    "sg:classifiers":[
        {
            "category":"Food & Beverages",
            "subcategory":"Groceries & Convenience Stores",
            "type":"Retail Goods"
        }
    ],
    "sg:phone":"+1 718 329 0920",
    "sg:postcode":"10468",
    "sg:province":"NY",
    "sg:tags":[
        "product"
    ],
    "wof:name":"MDY",
    "wof:placetype":"venue"
},
  "geometry": {"coordinates":[-73.89097599999999,40.870159],"type":"Point"}
}