{
  "type": "Feature",
  "properties": {
    "iso:country":"US",
    "sg:address":"203 W 58th Street",
    "sg:city":"New York",
    "sg:classifiers":[
        {
            "category":"Sports & Exercise",
            "subcategory":"Bicycle Rental",
            "type":"Entertainment"
        },
        {
            "category":"Landmark",
            "subcategory":"Tourist Information",
            "type":"Public Place"
        }
    ],
    "sg:phone":"+1 917 836 1409",
    "sg:postcode":"10019",
    "sg:province":"NY",
    "sg:tags":[
        "tour",
        "bike"
    ],
    "sg:website":"www.centralparkbiketours.com",
    "wof:name":"Central Park Bike Tours",
    "wof:placetype":"venue"
},
  "geometry": {"coordinates":[-73.979829,40.766341],"type":"Point"}
}