{
  "type": "Feature",
  "properties": {
    "iso:country":"US",
    "sg:address":"134 Syosset Woodbury Rd",
    "sg:city":"Syosset",
    "sg:classifiers":[
        {
            "category":"Professional",
            "subcategory":"Management & Consulting",
            "type":"Services"
        }
    ],
    "sg:phone":"+1 516 364 1116",
    "sg:postcode":"11791",
    "sg:province":"NY",
    "wof:name":"Jasb Management Inc",
    "wof:placetype":"venue"
},
  "geometry": {"coordinates":[-73.491894,40.827009],"type":"Point"}
}