{
  "type": "Feature",
  "properties": {
    "addr:full":"3505 Galway Rd Ballston Spa NY 12020",
    "addr:housenumber":"3505",
    "addr:postcode":"12020",
    "addr:street":"Galway Rd",
    "iso:country":"US",
    "sg:address":"3505 Galway Rd",
    "sg:city":"Ballston Spa",
    "sg:classifiers":[
        {
            "category":"Retail",
            "subcategory":"Repair Shop",
            "type":"Services"
        }
    ],
    "sg:phone":"+1 518 885 5472",
    "sg:postcode":"12020",
    "sg:province":"NY",
    "sg:tags":[
        "repairing",
        "piano",
        "refinishing"
    ],
    "wof:name":"Piano Place",
    "wof:placetype":"venue"
},
  "geometry": {"coordinates":[-73.911991,43.027905],"type":"Point"}
}