{
  "type": "Feature",
  "properties": {
    "addr:full":"85 Pineapple Walk Brooklyn NY 11201",
    "addr:housenumber":"85",
    "addr:postcode":"11201",
    "addr:street":"Pineapple Walk",
    "iso:country":"US",
    "sg:address":"85 Pineapple Walk",
    "sg:city":"Brooklyn",
    "sg:classifiers":[
        {
            "category":"Shopping",
            "subcategory":"Hobbies, Toys, & Games",
            "type":"Retail Goods"
        }
    ],
    "sg:phone":"+1 718 222 4271",
    "sg:postcode":"11201",
    "sg:province":"NY",
    "sg:tags":[
        "toy",
        "store"
    ],
    "wof:name":"Heights Kids",
    "wof:placetype":"venue"
},
  "geometry": {"coordinates":[-73.99208400000001,40.698033],"type":"Point"}
}