{
  "type": "Feature",
  "properties": {
    "addr:full":"2399 Sweet Home Rd Buffalo NY 14228",
    "addr:housenumber":"2399",
    "addr:postcode":"14228",
    "addr:street":"Sweet Home Rd",
    "iso:country":"US",
    "sg:address":"2399 Sweet Home Rd",
    "sg:city":"Buffalo",
    "sg:classifiers":[
        {
            "category":"Real Estate",
            "subcategory":"Surveying",
            "type":"Services"
        },
        {
            "category":"Professional",
            "subcategory":"Business Services",
            "type":"Services"
        }
    ],
    "sg:phone":"+1 716 691 7100",
    "sg:postcode":"14228",
    "sg:province":"NY",
    "sg:tags":[
        "appraisers-business",
        "industrial",
        "commercial",
        "appraiser"
    ],
    "sg:website":"http://www.garappraisal.com",
    "wof:name":"GAR Associates Inc",
    "wof:placetype":"venue"
},
  "geometry": {"coordinates":[-78.799029,43.024488],"type":"Point"}
}