{
  "type": "Feature",
  "properties": {
    "addr:full":"302 Upton St East Syracuse NY 13057",
    "addr:housenumber":"302",
    "addr:postcode":"13057",
    "addr:street":"Upton St",
    "iso:country":"US",
    "sg:address":"302 Upton St",
    "sg:city":"East Syracuse",
    "sg:classifiers":[
        {
            "category":"Building & Trades",
            "subcategory":"Construction",
            "type":"Services"
        }
    ],
    "sg:phone":"+1 315 437 2712",
    "sg:postcode":"13057",
    "sg:province":"NY",
    "sg:tags":[
        "painter"
    ],
    "wof:name":"L A Painting",
    "wof:placetype":"venue"
},
  "geometry": {"coordinates":[-76.06897499999999,43.065978],"type":"Point"}
}