{
  "type": "Feature",
  "properties": {
    "iso:country":"US",
    "sg:address":"140 Massachusetts Ave",
    "sg:city":"Congers",
    "sg:classifiers":[
        {
            "category":"Organizations",
            "subcategory":"Religious Organization",
            "type":"Services"
        }
    ],
    "sg:phone":"+1 845 267 0324",
    "sg:postcode":"10920",
    "sg:province":"NY",
    "sg:tags":[
        "clergy"
    ],
    "wof:name":"Richard E Knox",
    "wof:placetype":"venue"
},
  "geometry": {"coordinates":[-73.931827,41.137404],"type":"Point"}
}