{
  "type": "Feature",
  "properties": {
    "addr:full":"1983 Jerome Ave Bronx NY 10453",
    "addr:housenumber":"1983",
    "addr:postcode":"10453",
    "addr:street":"Jerome Ave",
    "iso:country":"US",
    "sg:address":"1983 Jerome Ave",
    "sg:city":"Bronx",
    "sg:classifiers":[
        {
            "category":"Personal",
            "subcategory":"Barber",
            "type":"Services"
        }
    ],
    "sg:phone":"+1 718 466 4797",
    "sg:postcode":"10453",
    "sg:province":"NY",
    "wof:name":"J C's Sports Barber Shop",
    "wof:placetype":"venue"
},
  "geometry": {"coordinates":[-73.908619,40.852491],"type":"Point"}
}