{
  "type": "Feature",
  "properties": {
    "iso:country":"US",
    "sg:address":"147 Bradfield Dr",
    "sg:city":"East Amherst",
    "sg:classifiers":[
        {
            "category":"Freight",
            "type":"Transportation"
        }
    ],
    "sg:phone":"+1   ",
    "sg:postcode":"14051",
    "sg:province":"NY",
    "sg:tags":[
        "local",
        "trucking"
    ],
    "wof:name":"Jernigan Trucking Inc",
    "wof:placetype":"venue"
},
  "geometry": {"coordinates":[-78.70018399999999,43.001581],"type":"Point"}
}