{
  "type": "Feature",
  "properties": {
    "addr:full":"297 Bramertown Rd Tuxedo Park NY 10987",
    "addr:housenumber":"297",
    "addr:postcode":"10987",
    "addr:street":"Bramertown Rd",
    "iso:country":"US",
    "sg:address":"297 Bramertown Rd",
    "sg:city":"Tuxedo Park",
    "sg:classifiers":[
        {
            "category":"Wholesale",
            "subcategory":"Machinery & Supplies",
            "type":"Manufacturing & Wholesale Goods"
        }
    ],
    "sg:phone":"+1 845 774 7440",
    "sg:postcode":"10987",
    "sg:province":"NY",
    "sg:tags":[
        "aircraft"
    ],
    "wof:name":"Air America Atlantic Inc",
    "wof:placetype":"venue"
},
  "geometry": {"coordinates":[-74.208134,41.25885],"type":"Point"}
}