{
  "type": "Feature",
  "properties": {
    "addr:full":"217 Madison Ave Elmira NY 14901",
    "addr:housenumber":"217",
    "addr:postcode":"14901",
    "addr:street":"Madison Ave",
    "iso:country":"US",
    "sg:address":"217 Madison Ave",
    "sg:city":"Elmira",
    "sg:classifiers":[
        {
            "category":"Recreation",
            "type":"Entertainment"
        }
    ],
    "sg:phone":"+1 607 737 2843",
    "sg:postcode":"14901",
    "sg:province":"NY",
    "sg:tags":[
        "parks"
    ],
    "wof:name":"Chemung County Parks",
    "wof:placetype":"venue"
},
  "geometry": {"coordinates":[-76.799257,42.090979],"type":"Point"}
}