{
  "type": "Feature",
  "properties": {
    "addr:full":"1211 38th Avenue Long Island City NY 11101",
    "addr:housenumber":"1211",
    "addr:postcode":"11101",
    "addr:street":"38Th Avenue",
    "iso:country":"US",
    "sg:address":"1211 38th Avenue",
    "sg:city":"Long Island City",
    "sg:classifiers":[
        {
            "category":"Shopping",
            "subcategory":"Beauty & Cosmetics",
            "type":"Retail Goods"
        }
    ],
    "sg:phone":"+1 718 609 0059",
    "sg:postcode":"11101",
    "sg:province":"NY",
    "sg:tags":[
        "supply"
    ],
    "wof:name":"B H B Trading",
    "wof:placetype":"venue"
},
  "geometry": {"coordinates":[-73.940516,40.758099],"type":"Point"}
}