{
  "type": "Feature",
  "properties": {
    "addr:full":"2901 3rd Avenue Bronx NY 10455",
    "addr:housenumber":"2901",
    "addr:postcode":"10455",
    "addr:street":"3Rd Avenue",
    "iso:country":"US",
    "sg:address":"2901 3rd Avenue",
    "sg:city":"Bronx",
    "sg:classifiers":[
        {
            "category":"Health Services",
            "subcategory":"Doctor",
            "type":"Services"
        }
    ],
    "sg:phone":"+1 718 585 0306",
    "sg:postcode":"10455",
    "sg:province":"NY",
    "wof:name":"Bronx Women's Pavilion",
    "wof:placetype":"venue"
},
  "geometry": {"coordinates":[-73.91619,40.817054],"type":"Point"}
}