{
  "type": "Feature",
  "properties": {
    "iso:country":"US",
    "sg:address":"239 Sunrise Hwy",
    "sg:city":"Rockville Centre",
    "sg:classifiers":[
        {
            "category":"Wholesale",
            "subcategory":"Construction Materials",
            "type":"Manufacturing & Wholesale Goods"
        },
        {
            "category":"Building & Trades",
            "subcategory":"Construction",
            "type":"Services"
        }
    ],
    "sg:phone":"+1 516 766 5833",
    "sg:postcode":"11570",
    "sg:province":"NY",
    "sg:tags":[
        "planning",
        "remodeling",
        "kitchen"
    ],
    "wof:name":"Architectural Kitchens & Baths",
    "wof:placetype":"venue"
},
  "geometry": {"coordinates":[-73.647488,40.65761],"type":"Point"}
}