{
  "type": "Feature",
  "properties": {
    "addr:full":"4211 28th Avenue Astoria NY 11103",
    "addr:housenumber":"4211",
    "addr:postcode":"11103",
    "addr:street":"28Th Avenue",
    "iso:country":"US",
    "sg:address":"4211 28th Avenue",
    "sg:city":"Astoria",
    "sg:classifiers":[
        {
            "category":"Personal",
            "subcategory":"Beauty Salon",
            "type":"Services"
        }
    ],
    "sg:phone":"+1 718 606 9171",
    "sg:postcode":"11103",
    "sg:province":"NY",
    "sg:tags":[
        "hair"
    ],
    "wof:name":"Salon Brazillian Beauty",
    "wof:placetype":"venue"
},
  "geometry": {"coordinates":[-73.911495,40.764572],"type":"Point"}
}