{
  "type": "Feature",
  "properties": {
    "iso:country":"US",
    "sg:address":"5 Campo Cir",
    "sg:city":"Old Westbury",
    "sg:classifiers":[
        {
            "category":"Shopping",
            "subcategory":"Jewelry",
            "type":"Retail Goods"
        }
    ],
    "sg:phone":"+1   ",
    "sg:postcode":"11568",
    "sg:province":"NY",
    "wof:name":"Tiara Jewelers Inc",
    "wof:placetype":"venue"
},
  "geometry": {"coordinates":[-73.619809,40.758398],"type":"Point"}
}