{
  "type": "Feature",
  "properties": {
    "addr:full":"56 E Main St Johnstown NY 12095",
    "addr:housenumber":"56",
    "addr:postcode":"12095",
    "addr:street":"E Main St",
    "iso:country":"US",
    "sg:address":"56 E Main St",
    "sg:city":"Johnstown",
    "sg:classifiers":[
        {
            "category":"Insurance",
            "subcategory":"Insurance Agent",
            "type":"Services"
        }
    ],
    "sg:phone":"+1 518 736 5153",
    "sg:postcode":"12095",
    "sg:province":"NY",
    "wof:name":"Prudential Insurance Co",
    "wof:placetype":"venue"
},
  "geometry": {"coordinates":[-74.371218,43.006451],"type":"Point"}
}