{
  "type": "Feature",
  "properties": {
    "addr:full":"2322 30th Rd Astoria NY 11102",
    "addr:housenumber":"2322",
    "addr:postcode":"11102",
    "addr:street":"30Th Rd",
    "iso:country":"US",
    "sg:address":"2322 30th Rd",
    "sg:city":"Astoria",
    "sg:classifiers":[
        {
            "category":"Health Services",
            "subcategory":"Doctor",
            "type":"Services"
        }
    ],
    "sg:phone":"+1 718 278 0888",
    "sg:postcode":"11102",
    "sg:province":"NY",
    "wof:name":"Andrea Olanescu, MD",
    "wof:placetype":"venue"
},
  "geometry": {"coordinates":[-73.925956,40.76869],"type":"Point"}
}