{
  "type": "Feature",
  "properties": {
    "addr:full":"1800 Clove Road Staten Island NY 10304",
    "addr:housenumber":"1800",
    "addr:postcode":"10304",
    "addr:street":"Clove Road",
    "iso:country":"US",
    "sg:address":"1800 Clove Road",
    "sg:city":"Staten Island",
    "sg:classifiers":[
        {
            "category":"Health Services",
            "subcategory":"Doctor",
            "type":"Services"
        }
    ],
    "sg:phone":"+1 718 720 6040",
    "sg:postcode":"10304",
    "sg:province":"NY",
    "wof:name":"Staten Island Urological Research PC",
    "wof:placetype":"venue"
},
  "geometry": {"coordinates":[-74.090729,40.608427],"type":"Point"}
}