{
  "type": "Feature",
  "properties": {
    "iso:country":"US",
    "sg:address":"1551 E 23rd St",
    "sg:city":"Brooklyn",
    "sg:classifiers":[
        {
            "category":"Organizations",
            "subcategory":"Membership Organization",
            "type":"Services"
        }
    ],
    "sg:phone":"+1   ",
    "sg:postcode":"11210",
    "sg:province":"NY",
    "wof:name":"Friends of Schumer",
    "wof:placetype":"venue"
},
  "geometry": {"coordinates":[-73.95086499999999,40.612762],"type":"Point"}
}