{
  "type": "Feature",
  "properties": {
    "addr:full":"4312 Avenue D Brooklyn NY 11203",
    "addr:housenumber":"4312",
    "addr:postcode":"11203",
    "addr:street":"Avenue D",
    "iso:country":"US",
    "sg:address":"4312 Avenue D",
    "sg:city":"Brooklyn",
    "sg:classifiers":[
        {
            "category":"Home & Garden",
            "subcategory":"Furniture",
            "type":"Retail Goods"
        }
    ],
    "sg:phone":"+1 718 451 1110",
    "sg:postcode":"11203",
    "sg:province":"NY",
    "sg:tags":[
        "store"
    ],
    "wof:name":"Rapid Furniture",
    "wof:placetype":"venue"
},
  "geometry": {"coordinates":[-73.935378,40.641646],"type":"Point"}
}