{
  "type": "Feature",
  "properties": {
    "addr:full":"7020 Austin St Forest Hills NY 11375",
    "addr:housenumber":"7020",
    "addr:postcode":"11375",
    "addr:street":"Austin St",
    "iso:country":"US",
    "sg:address":"7020 Austin St",
    "sg:city":"Forest Hills",
    "sg:classifiers":[
        {
            "category":"Restaurant",
            "type":"Food & Drink"
        }
    ],
    "sg:menulink":"http://www.allmenus.com/ny/queens/25227-mardi-gras/menu/",
    "sg:phone":"+1 718 261 8555",
    "sg:postcode":"11375",
    "sg:province":"NY",
    "sg:tags":[
        "american",
        "creole",
        "cajun"
    ],
    "wof:name":"Mardi Gras",
    "wof:placetype":"venue"
},
  "geometry": {"coordinates":[-73.84621799999999,40.720676],"type":"Point"}
}