{
  "type": "Feature",
  "properties": {
    "iso:country":"US",
    "sg:address":"958 Utica Ave",
    "sg:city":"Brooklyn",
    "sg:classifiers":[
        {
            "category":"Shopping",
            "subcategory":"Gifts & Souvenirs",
            "type":"Retail Goods"
        }
    ],
    "sg:phone":"+1 718 342 1919",
    "sg:postcode":"11203",
    "sg:province":"NY",
    "sg:tags":[
        "party",
        "supply"
    ],
    "wof:name":"Party Palace",
    "wof:placetype":"venue"
},
  "geometry": {"coordinates":[-73.93011199999999,40.648644],"type":"Point"}
}