{
  "type": "Feature",
  "properties": {
    "addr:full":"5925 Kissena Blvd Flushing NY 11355",
    "addr:housenumber":"5925",
    "addr:postcode":"11355",
    "addr:street":"Kissena Blvd",
    "iso:country":"US",
    "sg:address":"5925 Kissena Blvd",
    "sg:city":"Flushing",
    "sg:classifiers":[
        {
            "category":"Community Center",
            "type":"Public Place"
        }
    ],
    "sg:phone":"+1 718 670 6100",
    "sg:postcode":"11355",
    "sg:province":"NY",
    "sg:tags":[
        "medical"
    ],
    "wof:name":"Nassau Queens Medical Center",
    "wof:placetype":"venue"
},
  "geometry": {"coordinates":[-73.81500200000001,40.739899],"type":"Point"}
}