{
  "type": "Feature",
  "properties": {
    "addr:full":"336 Grand St Brooklyn NY 11211",
    "addr:housenumber":"336",
    "addr:postcode":"11211",
    "addr:street":"Grand St",
    "iso:country":"US",
    "sg:address":"336 Grand St",
    "sg:city":"Brooklyn",
    "sg:classifiers":[
        {
            "category":"Personal",
            "subcategory":"Skin Care",
            "type":"Services"
        },
        {
            "category":"Personal",
            "subcategory":"Day Spa",
            "type":"Services"
        }
    ],
    "sg:phone":"+1 917 533 0323",
    "sg:postcode":"11211",
    "sg:province":"NY",
    "sg:website":"vedaholistics.com",
    "wof:name":"Veda Holistics",
    "wof:placetype":"venue"
},
  "geometry": {"coordinates":[-73.95636500000001,40.712373],"type":"Point"}
}