{
  "type": "Feature",
  "properties": {
    "iso:country":"US",
    "sg:address":"2005 Ridge Rd",
    "sg:city":"Ontario",
    "sg:classifiers":[
        {
            "category":"Personal",
            "subcategory":"Beauty Salon",
            "type":"Services"
        },
        {
            "category":"Personal",
            "subcategory":"Barber",
            "type":"Services"
        }
    ],
    "sg:phone":"+1 315 524 8983",
    "sg:postcode":"14519",
    "sg:province":"NY",
    "sg:tags":[
        "shop"
    ],
    "wof:name":"Furguson Dave Hair Care",
    "wof:placetype":"venue"
},
  "geometry": {"coordinates":[-77.285709,43.221551],"type":"Point"}
}