{
  "type": "Feature",
  "properties": {
    "addr:full":"2395 Grand Concourse Bronx NY 10468",
    "addr:housenumber":"2395",
    "addr:postcode":"10468",
    "addr:street":"Grand Concourse",
    "iso:country":"US",
    "sg:address":"2395 Grand Concourse",
    "sg:city":"Bronx",
    "sg:classifiers":[
        {
            "category":"Shopping",
            "subcategory":"Jewelry",
            "type":"Retail Goods"
        }
    ],
    "sg:phone":"+1   ",
    "sg:postcode":"10468",
    "sg:province":"NY",
    "wof:name":"Mimis Sneakers",
    "wof:placetype":"venue"
},
  "geometry": {"coordinates":[-73.898526,40.85992],"type":"Point"}
}