{
  "type": "Feature",
  "properties": {
    "iso:country":"US",
    "sg:address":"592 Main St",
    "sg:city":"Islip",
    "sg:classifiers":[
        {
            "category":"Organizations",
            "subcategory":"Community Association",
            "type":"Services"
        }
    ],
    "sg:phone":"+1   ",
    "sg:postcode":"11751",
    "sg:province":"NY",
    "wof:name":"Meridan Lodge 691",
    "wof:placetype":"venue"
},
  "geometry": {"coordinates":[-73.21248799999999,40.729387],"type":"Point"}
}