{
  "type": "Feature",
  "properties": {
    "iso:country":"US",
    "sg:address":"843 E 49th St",
    "sg:city":"Brooklyn",
    "sg:classifiers":[
        {
            "category":"Home & Garden",
            "subcategory":"Household Appliances",
            "type":"Retail Goods"
        }
    ],
    "sg:phone":"+1 718 344 3362",
    "sg:postcode":"11203",
    "sg:province":"NY",
    "sg:tags":[
        "repair"
    ],
    "sg:website":"www.appliancerepairbrooklyn.com",
    "wof:name":"Father & Son Appliance Repair",
    "wof:placetype":"venue"
},
  "geometry": {"coordinates":[-73.929947,40.640818],"type":"Point"}
}