{
  "type": "Feature",
  "properties": {
    "addr:full":"272 W 86 St New York NY 10024",
    "addr:housenumber":"272",
    "addr:postcode":"10024",
    "addr:street":"W 86 St",
    "iso:country":"US",
    "sg:address":"272 W 86 St",
    "sg:city":"New York",
    "sg:classifiers":[
        {
            "category":"Professional",
            "subcategory":"Lawyer & Legal Services",
            "type":"Services"
        }
    ],
    "sg:phone":"+1 212 496 5560",
    "sg:postcode":"10024",
    "sg:province":"NY",
    "sg:tags":[
        "attorney"
    ],
    "wof:name":"Lichtman Law Firm",
    "wof:placetype":"venue"
},
  "geometry": {"coordinates":[-73.977423,40.788555],"type":"Point"}
}