{
  "type": "Feature",
  "properties": {
    "addr:full":"10207 Metropolitan Ave Forest Hills NY 11375",
    "addr:housenumber":"10207",
    "addr:postcode":"11375",
    "addr:street":"Metropolitan Ave",
    "iso:country":"US",
    "sg:address":"10207 Metropolitan Ave",
    "sg:city":"Forest Hills",
    "sg:classifiers":[
        {
            "category":"Restaurant",
            "type":"Food & Drink"
        }
    ],
    "sg:phone":"+1 718 793 0820",
    "sg:postcode":"11375",
    "sg:province":"NY",
    "wof:name":"Metro Cafe",
    "wof:placetype":"venue"
},
  "geometry": {"coordinates":[-73.85039500000001,40.710405],"type":"Point"}
}