{
  "type": "Feature",
  "properties": {
    "addr:full":"100 Summit Lk Dr Valhalla NY 10595",
    "addr:housenumber":"100",
    "addr:postcode":"10595",
    "addr:street":"Summit Lk Dr",
    "iso:country":"US",
    "sg:address":"100 Summit Lk Dr",
    "sg:city":"Valhalla",
    "sg:classifiers":[
        {
            "category":"Banks & Credit Unions",
            "subcategory":"Investment Brokerage",
            "type":"Services"
        },
        {
            "category":"Banks & Credit Unions",
            "subcategory":"Financial Services",
            "type":"Services"
        }
    ],
    "sg:phone":"+1 914 747 0200",
    "sg:postcode":"10595",
    "sg:province":"NY",
    "sg:tags":[
        "investing",
        "advising"
    ],
    "sg:website":"www.ameripriseadvisors.com/bert....",
    "wof:name":"Bert Bowler - Ameriprise Financial Advisor",
    "wof:placetype":"venue"
},
  "geometry": {"coordinates":[-73.7771,41.104654],"type":"Point"}
}