{
  "type": "Feature",
  "properties": {
    "iso:country":"US",
    "sg:address":"107 S Broadway",
    "sg:city":"Yonkers",
    "sg:classifiers":[
        {
            "category":"Health Services",
            "subcategory":"Doctor",
            "type":"Services"
        }
    ],
    "sg:phone":"+1 914 378 7000",
    "sg:postcode":"10701",
    "sg:province":"NY",
    "sg:tags":[
        "dentist"
    ],
    "wof:name":"St Joseph's Children's Dental",
    "wof:placetype":"venue"
},
  "geometry": {"coordinates":[-73.897986,40.930445],"type":"Point"}
}