{
  "type": "Feature",
  "properties": {
    "iso:country":"US",
    "sg:address":"915 Knickerbocker Ave",
    "sg:city":"Brooklyn",
    "sg:classifiers":[
        {
            "category":"Retail",
            "subcategory":"Auto Repair",
            "type":"Services"
        }
    ],
    "sg:phone":"+1 718 456 3679",
    "sg:postcode":"11207",
    "sg:province":"NY",
    "sg:tags":[
        "truck"
    ],
    "wof:name":"Tic Service Corp",
    "wof:placetype":"venue"
},
  "geometry": {"coordinates":[-73.903859,40.690701],"type":"Point"}
}