{
  "type": "Feature",
  "properties": {
    "iso:country":"US",
    "sg:address":"335 W 35 St",
    "sg:city":"New York",
    "sg:classifiers":[
        {
            "category":"Shopping",
            "subcategory":"Clothing, Apparel, & Fashions",
            "type":"Retail Goods"
        }
    ],
    "sg:phone":"+1 212 563 5562",
    "sg:postcode":"10001",
    "sg:province":"NY",
    "wof:name":"L & C Fashion Nt Corp",
    "wof:placetype":"venue"
},
  "geometry": {"coordinates":[-73.99503300000001,40.753704],"type":"Point"}
}