{
  "type": "Feature",
  "properties": {
    "iso:country":"US",
    "sg:address":"71 Oak St",
    "sg:city":"Brewster",
    "sg:classifiers":[
        {
            "category":"Manufacturing",
            "subcategory":"Printing",
            "type":"Manufacturing & Wholesale Goods"
        }
    ],
    "sg:phone":"+1   ",
    "sg:postcode":"10509",
    "sg:province":"NY",
    "sg:tags":[
        "lithographic",
        "b",
        "commercial",
        "typesetting"
    ],
    "wof:name":"Millennium Printing & Graphics",
    "wof:placetype":"venue"
},
  "geometry": {"coordinates":[-73.614519,41.395628],"type":"Point"}
}