{
  "type": "Feature",
  "properties": {
    "iso:country":"US",
    "sg:address":"22 River View Hts",
    "sg:city":"Rochester",
    "sg:classifiers":[
        {
            "category":"Retail",
            "subcategory":"Funeral Services",
            "type":"Services"
        }
    ],
    "sg:phone":"+1 585 292 6566",
    "sg:postcode":"14623",
    "sg:province":"NY",
    "sg:tags":[
        "director"
    ],
    "wof:name":"Martin Francis J Funeral",
    "wof:placetype":"venue"
},
  "geometry": {"coordinates":[-77.690108,43.079426],"type":"Point"}
}