{
  "type": "Feature",
  "properties": {
    "addr:full":"2847 S Park Ave Buffalo NY 14218",
    "addr:housenumber":"2847",
    "addr:postcode":"14218",
    "addr:street":"S Park Ave",
    "iso:country":"US",
    "sg:address":"2847 S Park Ave",
    "sg:city":"Buffalo",
    "sg:classifiers":[
        {
            "category":"Bars & Pubs",
            "type":"Food & Drink"
        }
    ],
    "sg:phone":"+1   ",
    "sg:postcode":"14218",
    "sg:province":"NY",
    "sg:tags":[
        "drinking"
    ],
    "wof:name":"Bokans Tavern",
    "wof:placetype":"venue"
},
  "geometry": {"coordinates":[-78.824077,42.822634],"type":"Point"}
}