{
  "type": "Feature",
  "properties": {
    "iso:country":"US",
    "sg:address":"25 Country Club Dr",
    "sg:city":"Rochester",
    "sg:classifiers":[
        {
            "category":"Manufacturing",
            "subcategory":"Paper Products",
            "type":"Manufacturing & Wholesale Goods"
        }
    ],
    "sg:phone":"+1 585 586 6821",
    "sg:postcode":"14618",
    "sg:province":"NY",
    "wof:name":"Basic Marketing Svc Inc",
    "wof:placetype":"venue"
},
  "geometry": {"coordinates":[-77.530225,43.110188],"type":"Point"}
}