{
  "type": "Feature",
  "properties": {
    "iso:country":"US",
    "sg:address":"118 E 40th St",
    "sg:city":"New York",
    "sg:classifiers":[
        {
            "category":"Professional",
            "subcategory":"Management & Consulting",
            "type":"Services"
        }
    ],
    "sg:phone":"+1 212 682 5000",
    "sg:postcode":"10016",
    "sg:province":"NY",
    "sg:tags":[
        "consultant"
    ],
    "wof:name":"MLI Consulting Inc",
    "wof:placetype":"venue"
},
  "geometry": {"coordinates":[-73.977812,40.750532],"type":"Point"}
}