{
  "type": "Feature",
  "properties": {
    "iso:country":"US",
    "sg:address":"197 Main St",
    "sg:city":"Cooperstown",
    "sg:classifiers":[
        {
            "category":"Government",
            "subcategory":"Court House",
            "type":"Public Place"
        }
    ],
    "sg:phone":"+1 607 547 4208",
    "sg:postcode":"13326",
    "sg:province":"NY",
    "sg:tags":[
        "county",
        "counsel"
    ],
    "sg:website":"www.otsegocounty.com",
    "wof:name":"Otsego County Attorney",
    "wof:placetype":"venue"
},
  "geometry": {"coordinates":[-74.929807,42.701182],"type":"Point"}
}