{
  "type": "Feature",
  "properties": {
    "addr:full":"636 Broadway New York NY 10012",
    "addr:housenumber":"636",
    "addr:postcode":"10012",
    "addr:street":"Broadway",
    "iso:country":"US",
    "sg:address":"636 Broadway",
    "sg:city":"New York",
    "sg:classifiers":[
        {
            "category":"Shopping",
            "subcategory":"Jewelry",
            "type":"Retail Goods"
        }
    ],
    "sg:phone":"+1 212 826 3660",
    "sg:postcode":"10012",
    "sg:province":"NY",
    "wof:name":"Boregaard Pedro",
    "wof:placetype":"venue"
},
  "geometry": {"coordinates":[-73.996053,40.72638],"type":"Point"}
}