{
  "type": "Feature",
  "properties": {
    "addr:full":"30 Chandler Sq Port Jefferson NY 11777",
    "addr:housenumber":"30",
    "addr:postcode":"11777",
    "addr:street":"Chandler Sq",
    "iso:country":"US",
    "sg:address":"30 Chandler Sq",
    "sg:city":"Port Jefferson",
    "sg:classifiers":[
        {
            "category":"Professional",
            "type":"Services"
        }
    ],
    "sg:phone":"+1 631 473 9731",
    "sg:postcode":"11777",
    "sg:province":"NY",
    "sg:tags":[
        "establishment"
    ],
    "wof:name":"Chandler's Square Inc",
    "wof:placetype":"venue"
},
  "geometry": {"coordinates":[-73.069598,40.945991],"type":"Point"}
}