{
  "type": "Feature",
  "properties": {
    "addr:full":"108 20180 St Floral Park NY 11001",
    "addr:housenumber":"108",
    "addr:postcode":"20180;11001",
    "iso:country":"US",
    "sg:address":"108 20180 St",
    "sg:city":"Floral Park",
    "sg:classifiers":[
        {
            "category":"Professional",
            "subcategory":"Lawyer & Legal Services",
            "type":"Services"
        }
    ],
    "sg:phone":"+1 718 479 6250",
    "sg:postcode":"11001",
    "sg:province":"NY",
    "sg:website":"budgettruck.com",
    "wof:name":"Budget Truck Rental",
    "wof:placetype":"venue"
},
  "geometry": {"coordinates":[-73.699594,40.717764],"type":"Point"}
}