{
  "type": "Feature",
  "properties": {
    "addr:full":"3728 Potash Hill Rd Vernon Center NY 13477",
    "addr:housenumber":"3728",
    "addr:postcode":"13477",
    "addr:street":"Potash Hill Rd",
    "iso:country":"US",
    "sg:address":"3728 Potash Hill Rd",
    "sg:city":"Vernon Center",
    "sg:classifiers":[
        {
            "category":"Wholesale",
            "subcategory":"Hardware",
            "type":"Manufacturing & Wholesale Goods"
        }
    ],
    "sg:phone":"+1 315 829 6080",
    "sg:postcode":"13477",
    "sg:province":"NY",
    "wof:name":"Pittsburgh Key Bolt & Forging",
    "wof:placetype":"venue"
},
  "geometry": {"coordinates":[-75.488305,43.040982],"type":"Point"}
}