{
  "type": "Feature",
  "properties": {
    "iso:country":"US",
    "sg:address":"5 Maxwell Dr",
    "sg:city":"Clifton Park",
    "sg:classifiers":[
        {
            "category":"Insurance",
            "subcategory":"Insurance Agent",
            "type":"Services"
        }
    ],
    "sg:phone":"+1 518 373 7300",
    "sg:postcode":"12065",
    "sg:province":"NY",
    "sg:website":"www.axaonline.com",
    "wof:name":"Axa Advisors",
    "wof:placetype":"venue"
},
  "geometry": {"coordinates":[-73.78430899999999,42.86509],"type":"Point"}
}