{
  "type": "Feature",
  "properties": {
    "iso:country":"US",
    "sg:address":"8 Main St",
    "sg:city":"Irvington",
    "sg:classifiers":[
        {
            "category":"Building & Trades",
            "subcategory":"Plumbing",
            "type":"Services"
        }
    ],
    "sg:phone":"+1 914 591 4000",
    "sg:postcode":"10533",
    "sg:province":"NY",
    "sg:tags":[
        "contractor"
    ],
    "wof:name":"Emergency Rooter",
    "wof:placetype":"venue"
},
  "geometry": {"coordinates":[-73.87212100000001,41.039669],"type":"Point"}
}