{
  "type": "Feature",
  "properties": {
    "iso:country":"US",
    "sg:address":"41 City Hall Pl",
    "sg:city":"Plattsburgh",
    "sg:classifiers":[
        {
            "category":"Government",
            "subcategory":"Office",
            "type":"Public Place"
        }
    ],
    "sg:phone":"+1 518 563 7708",
    "sg:postcode":"12901",
    "sg:province":"NY",
    "sg:tags":[
        "village"
    ],
    "wof:name":"Plattsburgh Div Of Assessment",
    "wof:placetype":"venue"
},
  "geometry": {"coordinates":[-73.451539,44.699316],"type":"Point"}
}