{
  "type": "Feature",
  "properties": {
    "addr:full":"157 Chambers Street New York NY 10007",
    "addr:housenumber":"157",
    "addr:postcode":"10007",
    "addr:street":"Chambers Street",
    "iso:country":"US",
    "sg:address":"157 Chambers Street",
    "sg:city":"New York",
    "sg:classifiers":[
        {
            "category":"Communications",
            "subcategory":"Newspaper",
            "type":"Services"
        }
    ],
    "sg:phone":"+1 212 608 5990",
    "sg:postcode":"10007",
    "sg:province":"NY",
    "sg:tags":[
        "print",
        "medium"
    ],
    "wof:name":"The Tribeca Tribune",
    "wof:placetype":"venue"
},
  "geometry": {"coordinates":[-74.010228,40.715966],"type":"Point"}
}