{
  "type": "Feature",
  "properties": {
    "iso:country":"US",
    "sg:address":"147 King Arthurs Ct",
    "sg:city":"Rochester",
    "sg:classifiers":[
        {
            "category":"Professional",
            "subcategory":"Computer Services",
            "type":"Services"
        }
    ],
    "sg:phone":"+1 585 697 0208",
    "sg:postcode":"14626",
    "sg:province":"NY",
    "sg:tags":[
        "programming"
    ],
    "wof:name":"D B Computer Connections",
    "wof:placetype":"venue"
},
  "geometry": {"coordinates":[-77.712118,43.219233],"type":"Point"}
}