{
  "type": "Feature",
  "properties": {
    "iso:country":"US",
    "sg:address":"204 Morningstar Rd",
    "sg:city":"Staten Island",
    "sg:classifiers":[
        {
            "category":"Shopping",
            "type":"Retail Goods"
        },
        {
            "category":"Wholesale",
            "subcategory":"Sporting Goods",
            "type":"Manufacturing & Wholesale Goods"
        }
    ],
    "sg:phone":"+1 718 448 8800",
    "sg:postcode":"10303",
    "sg:province":"NY",
    "sg:tags":[
        "light",
        "equipment",
        "above",
        "swimming",
        "christmas",
        "pool",
        "ground"
    ],
    "wof:name":"Holly Hill Pool & Patio Corp",
    "wof:placetype":"venue"
},
  "geometry": {"coordinates":[-74.14584000000001,40.634575],"type":"Point"}
}