{
  "type": "Feature",
  "properties": {
    "iso:country":"US",
    "sg:address":"1504 Washington St",
    "sg:city":"Jamestown",
    "sg:classifiers":[
        {
            "category":"Retail",
            "subcategory":"Car Wash",
            "type":"Services"
        }
    ],
    "sg:phone":"+1 716 664 2494",
    "sg:postcode":"14701",
    "sg:province":"NY",
    "sg:tags":[
        "polishing",
        "washing"
    ],
    "wof:name":"Clean Car Concepts Car Wash",
    "wof:placetype":"venue"
},
  "geometry": {"coordinates":[-79.24528599999999,42.107173],"type":"Point"}
}