{
  "type": "Feature",
  "properties": {
    "addr:full":"4304 Junction Blvd Corona NY 11368",
    "addr:housenumber":"4304",
    "addr:postcode":"11368",
    "addr:street":"Junction Blvd",
    "iso:country":"US",
    "sg:address":"4304 Junction Blvd",
    "sg:city":"Corona",
    "sg:classifiers":[
        {
            "category":"Deli",
            "type":"Food & Drink"
        },
        {
            "category":"Food & Beverages",
            "subcategory":"Bakery",
            "type":"Retail Goods"
        }
    ],
    "sg:phone":"+1 800 213 5806",
    "sg:postcode":"11368",
    "sg:province":"NY",
    "sg:tags":[
        "sandwich"
    ],
    "wof:name":"J & C Deli",
    "wof:placetype":"venue"
},
  "geometry": {"coordinates":[-73.86823699999999,40.745547],"type":"Point"}
}