{
  "type": "Feature",
  "properties": {
    "addr:full":"47 Champlain St Plattsburgh NY 12901",
    "addr:housenumber":"47",
    "addr:postcode":"12901",
    "addr:street":"Champlain St",
    "iso:country":"US",
    "sg:address":"47 Champlain St",
    "sg:city":"Plattsburgh",
    "sg:classifiers":[
        {
            "category":"Shopping",
            "subcategory":"Shoes",
            "type":"Retail Goods"
        }
    ],
    "sg:phone":"+1   ",
    "sg:postcode":"12901",
    "sg:province":"NY",
    "wof:name":"Foot Locker",
    "wof:placetype":"venue"
},
  "geometry": {"coordinates":[-73.461541,44.700268],"type":"Point"}
}