{
  "type": "Feature",
  "properties": {
    "addr:full":"4100 Laconia Ave Bronx NY 10466",
    "addr:housenumber":"4100",
    "addr:postcode":"10466",
    "addr:street":"Laconia Ave",
    "iso:country":"US",
    "sg:address":"4100 Laconia Ave",
    "sg:city":"Bronx",
    "sg:classifiers":[
        {
            "category":"Retail",
            "subcategory":"Repair Shop",
            "type":"Services"
        }
    ],
    "sg:phone":"+1 718 685 5886",
    "sg:postcode":"10466",
    "sg:province":"NY",
    "sg:tags":[
        "lock",
        "locksmith"
    ],
    "wof:name":"Locksmith",
    "wof:placetype":"venue"
},
  "geometry": {"coordinates":[-73.847049,40.887671],"type":"Point"}
}