{
  "type": "Feature",
  "properties": {
    "iso:country":"US",
    "sg:address":"427 Central Ave",
    "sg:city":"Cedarhurst",
    "sg:classifiers":[
        {
            "category":"Shopping",
            "subcategory":"Jewelry",
            "type":"Retail Goods"
        }
    ],
    "sg:phone":"+1 516 569 6262",
    "sg:postcode":"11516",
    "sg:province":"NY",
    "sg:tags":[
        "jeweler"
    ],
    "sg:website":"www.sosjewelry.com",
    "wof:name":"Sos Jewelry Corp",
    "wof:placetype":"venue"
},
  "geometry": {"coordinates":[-73.726303,40.619999],"type":"Point"}
}