{
  "type": "Feature",
  "properties": {
    "addr:full":"552 Broadway New York NY 10012",
    "addr:housenumber":"552",
    "addr:postcode":"10012",
    "addr:street":"Broadway",
    "iso:country":"US",
    "sg:address":"552 Broadway",
    "sg:city":"New York",
    "sg:classifiers":[
        {
            "category":"Arts & Performance",
            "subcategory":"Theater",
            "type":"Entertainment"
        }
    ],
    "sg:phone":"+1 212 431 5562",
    "sg:postcode":"10012",
    "sg:province":"NY",
    "sg:tags":[
        "dance",
        "theatrical",
        "company"
    ],
    "wof:name":"Paul Taylor Dance Foundation",
    "wof:placetype":"venue"
},
  "geometry": {"coordinates":[-73.998197,40.723452],"type":"Point"}
}