{
  "type": "Feature",
  "properties": {
    "addr:full":"13 N 6th Ave Mount Vernon NY 10550",
    "addr:housenumber":"13",
    "addr:postcode":"10550",
    "addr:street":"N 6Th Ave",
    "iso:country":"US",
    "sg:address":"13 N 6th Ave",
    "sg:city":"Mount Vernon",
    "sg:classifiers":[
        {
            "category":"Wholesale",
            "subcategory":"Vending Machines",
            "type":"Manufacturing & Wholesale Goods"
        }
    ],
    "sg:phone":"+1   ",
    "sg:postcode":"10550",
    "sg:province":"NY",
    "sg:tags":[
        "operator",
        "merchandising"
    ],
    "wof:name":"County Cigarette Vending",
    "wof:placetype":"venue"
},
  "geometry": {"coordinates":[-73.839139,40.914104],"type":"Point"}
}