{
  "type": "Feature",
  "properties": {
    "addr:full":"454 Sullivan St Elmira NY 14901",
    "addr:housenumber":"454",
    "addr:postcode":"14901",
    "addr:street":"Sullivan St",
    "iso:country":"US",
    "sg:address":"454 Sullivan St",
    "sg:city":"Elmira",
    "sg:classifiers":[
        {
            "category":"Building & Trades",
            "subcategory":"Construction",
            "type":"Services"
        }
    ],
    "sg:phone":"+1 607 732 4768",
    "sg:postcode":"14901",
    "sg:province":"NY",
    "sg:tags":[
        "painter"
    ],
    "wof:name":"Painting Chappell's",
    "wof:placetype":"venue"
},
  "geometry": {"coordinates":[-76.79553199999999,42.097039],"type":"Point"}
}