{
  "type": "Feature",
  "properties": {
    "iso:country":"US",
    "sg:address":"10 State Hwy 37B",
    "sg:city":"Massena",
    "sg:classifiers":[
        {
            "category":"Retail",
            "subcategory":"Veterinary Services",
            "type":"Services"
        }
    ],
    "sg:phone":"+1 315 764 8387",
    "sg:postcode":"13662",
    "sg:province":"NY",
    "sg:tags":[
        "clinic"
    ],
    "wof:name":"Linder Veterinary Clinic",
    "wof:placetype":"venue"
},
  "geometry": {"coordinates":[-74.895842,44.93538],"type":"Point"}
}