{
  "type": "Feature",
  "properties": {
    "iso:country":"US",
    "sg:address":"168 Driggs Ave",
    "sg:city":"Brooklyn",
    "sg:classifiers":[
        {
            "category":"Restaurant",
            "type":"Food & Drink"
        }
    ],
    "sg:phone":"+1 718 349 1800",
    "sg:postcode":"11222",
    "sg:province":"NY",
    "sg:tags":[
        "caterer"
    ],
    "wof:name":"Szarotka Club & Restaurant",
    "wof:placetype":"venue"
},
  "geometry": {"coordinates":[-73.945194,40.723064],"type":"Point"}
}