{
  "type": "Feature",
  "properties": {
    "iso:country":"US",
    "sg:address":"93 Dyke Rd",
    "sg:city":"Setauket",
    "sg:classifiers":[
        {
            "category":"Building & Trades",
            "subcategory":"Construction",
            "type":"Services"
        }
    ],
    "sg:phone":"+1 631 689 1088",
    "sg:postcode":"11733",
    "sg:province":"NY",
    "sg:tags":[
        "general",
        "contractor"
    ],
    "wof:name":"Essex Construction & Mgmt Corp",
    "wof:placetype":"venue"
},
  "geometry": {"coordinates":[-73.10420999999999,40.95496],"type":"Point"}
}