{
  "type": "Feature",
  "properties": {
    "iso:country":"US",
    "sg:address":"38 Burgess Ave",
    "sg:city":"Huntington Station",
    "sg:classifiers":[
        {
            "category":"Building & Trades",
            "subcategory":"Construction",
            "type":"Services"
        }
    ],
    "sg:phone":"+1 631 424 6218",
    "sg:postcode":"11746",
    "sg:province":"NY",
    "sg:tags":[
        "house"
    ],
    "wof:name":"Total Spectrum Contracting",
    "wof:placetype":"venue"
},
  "geometry": {"coordinates":[-73.416304,40.818947],"type":"Point"}
}