{
  "type": "Feature",
  "properties": {
    "addr:full":"608 Ulster Ave Kingston NY 12401",
    "addr:housenumber":"608",
    "addr:postcode":"12401",
    "addr:street":"Ulster Ave",
    "iso:country":"US",
    "sg:address":"608 Ulster Ave",
    "sg:city":"Kingston",
    "sg:classifiers":[
        {
            "category":"Restaurant",
            "type":"Food & Drink"
        }
    ],
    "sg:phone":"+1 845 338 7443",
    "sg:postcode":"12401",
    "sg:province":"NY",
    "wof:name":"China Rose To Go",
    "wof:placetype":"venue"
},
  "geometry": {"coordinates":[-73.995724,41.945572],"type":"Point"}
}