{
  "type": "Feature",
  "properties": {
    "iso:country":"US",
    "sg:address":"23 S Macquesten Pkwy",
    "sg:city":"Mount Vernon",
    "sg:classifiers":[
        {
            "category":"Professional",
            "subcategory":"Testing Lab",
            "type":"Services"
        }
    ],
    "sg:phone":"+1 914 699 0056",
    "sg:postcode":"10550",
    "sg:province":"NY",
    "sg:tags":[
        "building",
        "material",
        "for"
    ],
    "wof:name":"Delta Testing Laboratories",
    "wof:placetype":"venue"
},
  "geometry": {"coordinates":[-73.84950600000001,40.91223],"type":"Point"}
}