{
  "type": "Feature",
  "properties": {
    "iso:country":"US",
    "sg:address":"823 Greenwich St",
    "sg:city":"New York",
    "sg:classifiers":[
        {
            "category":"Restaurant",
            "type":"Food & Drink"
        }
    ],
    "sg:menulink":"http://www.allmenus.com/ny/new-york/249312-el-faro-restaurant/menu/",
    "sg:phone":"+1 212 929 8210",
    "sg:postcode":"10014",
    "sg:province":"NY",
    "sg:tags":[
        "spanish"
    ],
    "wof:name":"El Faro Restaurant",
    "wof:placetype":"venue"
},
  "geometry": {"coordinates":[-74.006455,40.738725],"type":"Point"}
}