{
  "type": "Feature",
  "properties": {
    "addr:full":"773 Arnett Blvd Rochester NY 14619",
    "addr:housenumber":"773",
    "addr:postcode":"14619",
    "addr:street":"Arnett Blvd",
    "iso:country":"US",
    "sg:address":"773 Arnett Blvd",
    "sg:city":"Rochester",
    "sg:classifiers":[
        {
            "category":"Shopping",
            "subcategory":"Clothing, Apparel, & Fashions",
            "type":"Retail Goods"
        }
    ],
    "sg:phone":"+1 585 436 7382",
    "sg:postcode":"14619",
    "sg:province":"NY",
    "sg:tags":[
        "tailor"
    ],
    "wof:name":"Marston's Custom Tailoring",
    "wof:placetype":"venue"
},
  "geometry": {"coordinates":[-77.65576799999999,43.14214],"type":"Point"}
}