{
  "type": "Feature",
  "properties": {
    "addr:full":"48 W 39 St New York NY 10018",
    "addr:housenumber":"48",
    "addr:postcode":"10018",
    "addr:street":"W 39 St",
    "iso:country":"US",
    "sg:address":"48 W 39 St",
    "sg:city":"New York",
    "sg:classifiers":[
        {
            "category":"Wholesale",
            "subcategory":"Apparel",
            "type":"Manufacturing & Wholesale Goods"
        }
    ],
    "sg:phone":"+1 212 382 1382",
    "sg:postcode":"10018",
    "sg:province":"NY",
    "sg:tags":[
        "item",
        "fashion",
        "plastic"
    ],
    "wof:name":"Saco International",
    "wof:placetype":"venue"
},
  "geometry": {"coordinates":[-73.984358,40.752219],"type":"Point"}
}