{
  "type": "Feature",
  "properties": {
    "addr:full":"60 Wall Street New York NY 10005",
    "addr:housenumber":"60",
    "addr:postcode":"10005",
    "addr:street":"Wall Street",
    "iso:country":"US",
    "sg:address":"60 Wall Street",
    "sg:city":"New York",
    "sg:classifiers":[
        {
            "category":"Personal",
            "subcategory":"Shoe Repair & Shine",
            "type":"Services"
        }
    ],
    "sg:phone":"+1 212 809 9814",
    "sg:postcode":"10005",
    "sg:province":"NY",
    "wof:name":"Cobbler Express Ny Shoe Repair",
    "wof:placetype":"venue"
},
  "geometry": {"coordinates":[-74.00852500000001,40.705974],"type":"Point"}
}