{
  "type": "Feature",
  "properties": {
    "iso:country":"US",
    "sg:address":"55 Albany Ave",
    "sg:city":"Kingston",
    "sg:classifiers":[
        {
            "category":"Organizations",
            "subcategory":"Professional Association",
            "type":"Services"
        }
    ],
    "sg:phone":"+1 845 338 2698",
    "sg:postcode":"12401",
    "sg:province":"NY",
    "sg:tags":[
        "business"
    ],
    "wof:name":"Chamber of Commerce of Ulster",
    "wof:placetype":"venue"
},
  "geometry": {"coordinates":[-74.01415799999999,41.932654],"type":"Point"}
}