{
  "type": "Feature",
  "properties": {
    "addr:full":"132 Shady Hill Rd Apalachin NY 13732",
    "addr:housenumber":"132",
    "addr:postcode":"13732",
    "addr:street":"Shady Hill Rd",
    "iso:country":"US",
    "sg:address":"132 Shady Hill Rd",
    "sg:city":"Apalachin",
    "sg:classifiers":[
        {
            "category":"Building & Trades",
            "subcategory":"Landscaping Services",
            "type":"Services"
        }
    ],
    "sg:phone":"+1 607 625 2177",
    "sg:postcode":"13732",
    "sg:province":"NY",
    "sg:tags":[
        "medical",
        "landscape",
        "contractor"
    ],
    "wof:name":"Loso's Landscaping",
    "wof:placetype":"venue"
},
  "geometry": {"coordinates":[-76.138514,42.056628],"type":"Point"}
}