{
  "type": "Feature",
  "properties": {
    "addr:full":"185 S 5th St Brooklyn NY 11211",
    "addr:housenumber":"185",
    "addr:postcode":"11211",
    "addr:street":"S 5Th St",
    "iso:country":"US",
    "sg:address":"185 S 5th St",
    "sg:city":"Brooklyn",
    "sg:classifiers":[
        {
            "category":"Organizations",
            "subcategory":"Religious Organization",
            "type":"Services"
        }
    ],
    "sg:phone":"+1 718 388 4723",
    "sg:postcode":"11211",
    "sg:province":"NY",
    "sg:tags":[
        "church"
    ],
    "wof:name":"Ukrainian Orthodox Holy",
    "wof:placetype":"venue"
},
  "geometry": {"coordinates":[-73.96181,40.710736],"type":"Point"}
}