{
  "type": "Feature",
  "properties": {
    "addr:full":"4801 90th St Elmhurst NY 11373",
    "addr:housenumber":"4801",
    "addr:postcode":"11373",
    "addr:street":"90Th St",
    "iso:country":"US",
    "sg:address":"4801 90th St",
    "sg:city":"Elmhurst",
    "sg:classifiers":[
        {
            "category":"Education",
            "subcategory":"Special Training",
            "type":"Public Place"
        }
    ],
    "sg:phone":"+1 718 760 1826",
    "sg:postcode":"11373",
    "sg:province":"NY",
    "sg:website":"http://www.autohs.com",
    "wof:name":"New York City Board Of Education",
    "wof:placetype":"venue"
},
  "geometry": {"coordinates":[-73.872719,40.735889],"type":"Point"}
}