{
  "type": "Feature",
  "properties": {
    "iso:country":"US",
    "sg:address":"23 Durkee St",
    "sg:city":"Plattsburgh",
    "sg:classifiers":[
        {
            "category":"Personal",
            "type":"Services"
        }
    ],
    "sg:phone":"+1 518 562 3322",
    "sg:postcode":"12901",
    "sg:province":"NY",
    "sg:tags":[
        "therapist",
        "massage"
    ],
    "wof:name":"Archer Body Works",
    "wof:placetype":"venue"
},
  "geometry": {"coordinates":[-73.45229,44.697668],"type":"Point"}
}