{
  "type": "Feature",
  "properties": {
    "iso:country":"US",
    "sg:address":"4088 Ransomville Rd",
    "sg:city":"Ransomville",
    "sg:classifiers":[
        {
            "category":"Farming",
            "subcategory":"Farm",
            "type":"Manufacturing & Wholesale Goods"
        }
    ],
    "sg:phone":"+1 716 791 4730",
    "sg:postcode":"14131",
    "sg:province":"NY",
    "sg:tags":[
        "crop",
        "general"
    ],
    "wof:name":"Gerald Helmich",
    "wof:placetype":"venue"
},
  "geometry": {"coordinates":[-78.914511,43.215837],"type":"Point"}
}