{
  "type": "Feature",
  "properties": {
    "addr:full":"3002 Steinway Street Astoria NY 11103",
    "addr:housenumber":"3002",
    "addr:postcode":"11103",
    "addr:street":"Steinway Street",
    "iso:country":"US",
    "sg:address":"3002 Steinway Street",
    "sg:city":"Astoria",
    "sg:classifiers":[
        {
            "category":"Personal",
            "subcategory":"Nail Salon",
            "type":"Services"
        }
    ],
    "sg:phone":"+1 718 726 8938",
    "sg:postcode":"11103",
    "sg:province":"NY",
    "wof:name":"Rainbow Beauty Salon",
    "wof:placetype":"venue"
},
  "geometry": {"coordinates":[-73.915031,40.763838],"type":"Point"}
}