{
  "type": "Feature",
  "properties": {
    "iso:country":"US",
    "sg:address":"510 Merrick Rd",
    "sg:city":"Rockville Centre",
    "sg:classifiers":[
        {
            "category":"Professional",
            "subcategory":"Lawyer & Legal Services",
            "type":"Services"
        }
    ],
    "sg:phone":"+1 516 678 2117",
    "sg:postcode":"11570",
    "sg:province":"NY",
    "wof:name":"Jacobson Schwartz Atty",
    "wof:placetype":"venue"
},
  "geometry": {"coordinates":[-73.636002,40.6548],"type":"Point"}
}