{
  "type": "Feature",
  "properties": {
    "iso:country":"US",
    "sg:address":"22 Tiernon Park",
    "sg:city":"Buffalo",
    "sg:classifiers":[
        {
            "category":"Home & Garden",
            "subcategory":"Home Furnishings",
            "type":"Retail Goods"
        }
    ],
    "sg:phone":"+1 716 832 9419",
    "sg:postcode":"14223",
    "sg:province":"NY",
    "sg:tags":[
        "curtain",
        "made",
        "drapery"
    ],
    "wof:name":"Drapery Studio",
    "wof:placetype":"venue"
},
  "geometry": {"coordinates":[-78.836282,42.978589],"type":"Point"}
}