{
  "type": "Feature",
  "properties": {
    "addr:full":"1443 Clinton St Buffalo NY 14206",
    "addr:housenumber":"1443",
    "addr:postcode":"14206",
    "addr:street":"Clinton St",
    "iso:country":"US",
    "sg:address":"1443 Clinton St",
    "sg:city":"Buffalo",
    "sg:classifiers":[
        {
            "category":"Wholesale",
            "subcategory":"Fruits & Vegetables",
            "type":"Manufacturing & Wholesale Goods"
        }
    ],
    "sg:phone":"+1 716 826 2217",
    "sg:postcode":"14206",
    "sg:province":"NY",
    "sg:tags":[
        "veggie",
        "vegetables-wholesale"
    ],
    "wof:name":"Sunset Fruit & Vegetable Packing Co Inc",
    "wof:placetype":"venue"
},
  "geometry": {"coordinates":[-78.823196,42.873402],"type":"Point"}
}