{
  "type": "Feature",
  "properties": {
    "iso:country":"US",
    "sg:address":"1007 Auburn St",
    "sg:city":"Hannibal",
    "sg:classifiers":[
        {
            "category":"Home & Garden",
            "subcategory":"Garden Supply",
            "type":"Retail Goods"
        },
        {
            "category":"Shopping",
            "subcategory":"Gifts & Souvenirs",
            "type":"Retail Goods"
        },
        {
            "category":"Shopping",
            "subcategory":"Crafts & Fabrics",
            "type":"Retail Goods"
        },
        {
            "category":"Shopping",
            "subcategory":"Florist",
            "type":"Retail Goods"
        }
    ],
    "sg:phone":"+1 315 564 6606",
    "sg:postcode":"13074",
    "sg:province":"NY",
    "sg:tags":[
        "plant",
        "etc-retail",
        "dried",
        "basket",
        "trees-silk",
        "flowers"
    ],
    "sg:website":"http://www.travisfloral.com",
    "wof:name":"Travis Floral Shop",
    "wof:placetype":"venue"
},
  "geometry": {"coordinates":[-76.57505500000001,43.315781],"type":"Point"}
}