{
  "type": "Feature",
  "properties": {
    "addr:full":"3744 Vestal Pkwy E Vestal NY 13850",
    "addr:housenumber":"3744",
    "addr:postcode":"13850",
    "addr:street":"Vestal Pkwy E",
    "iso:country":"US",
    "sg:address":"3744 Vestal Pkwy E",
    "sg:city":"Vestal",
    "sg:classifiers":[
        {
            "category":"Bars & Pubs",
            "type":"Food & Drink"
        },
        {
            "category":"Restaurant",
            "type":"Food & Drink"
        }
    ],
    "sg:phone":"+1 607 729 9053",
    "sg:postcode":"13850",
    "sg:province":"NY",
    "sg:tags":[
        "tavern"
    ],
    "sg:website":"http://www.beerjoint.com",
    "wof:name":"The Ale House Inc",
    "wof:placetype":"venue"
},
  "geometry": {"coordinates":[-75.981386,42.096124],"type":"Point"}
}