{
  "type": "Feature",
  "properties": {
    "addr:full":"1 Union Sq W New York NY 10003",
    "addr:housenumber":"1",
    "addr:postcode":"10003",
    "addr:street":"Union Sq W",
    "iso:country":"US",
    "sg:address":"1 Union Sq W",
    "sg:city":"New York",
    "sg:phone":"+1 212 255 6603",
    "sg:postcode":"10003",
    "sg:province":"NY",
    "sg:tags":[
        "fuel",
        "diesel"
    ],
    "wof:name":"Diesel USA",
    "wof:placetype":"venue"
},
  "geometry": {"coordinates":[-73.991145,40.735859],"type":"Point"}
}