{
  "type": "Feature",
  "properties": {
    "addr:full":"1 Ramapo Ave Suffern NY 10901",
    "addr:housenumber":"1",
    "addr:postcode":"10901",
    "addr:street":"Ramapo Ave",
    "iso:country":"US",
    "sg:address":"1 Ramapo Ave",
    "sg:city":"Suffern",
    "sg:classifiers":[
        {
            "category":"Manufacturing",
            "subcategory":"Tools & Machinery",
            "type":"Manufacturing & Wholesale Goods"
        }
    ],
    "sg:phone":"+1 845 357 1600",
    "sg:postcode":"10901",
    "sg:province":"NY",
    "sg:tags":[
        "household",
        "appliance"
    ],
    "sg:website":"www.metrovacworld.com",
    "wof:name":"Metropolitan Vacuum Cleaner Co",
    "wof:placetype":"venue"
},
  "geometry": {"coordinates":[-74.154258,41.113447],"type":"Point"}
}