{
  "type": "Feature",
  "properties": {
    "addr:full":"17 Mark Twain Ln East Setauket NY 11733",
    "addr:housenumber":"17",
    "addr:postcode":"11733",
    "addr:street":"Mark Twain Ln East",
    "iso:country":"US",
    "sg:address":"17 Mark Twain Ln",
    "sg:city":"East Setauket",
    "sg:classifiers":[
        {
            "category":"Building & Trades",
            "subcategory":"Construction",
            "type":"Services"
        }
    ],
    "sg:phone":"+1 631 246 8900",
    "sg:postcode":"11733",
    "sg:province":"NY",
    "sg:tags":[
        "general",
        "contractor"
    ],
    "wof:name":"BNF Contractors Inc",
    "wof:placetype":"venue"
},
  "geometry": {"coordinates":[-73.101079,40.914004],"type":"Point"}
}