{
  "type": "Feature",
  "properties": {
    "addr:full":"19 Elberton Ave Walden NY 12586",
    "addr:housenumber":"19",
    "addr:postcode":"12586",
    "addr:street":"Elberton Ave",
    "iso:country":"US",
    "sg:address":"19 Elberton Ave",
    "sg:city":"Walden",
    "sg:classifiers":[
        {
            "category":"Wholesale",
            "subcategory":"Machinery & Supplies",
            "type":"Manufacturing & Wholesale Goods"
        }
    ],
    "sg:phone":"+1 845 778 4402",
    "sg:postcode":"12586",
    "sg:province":"NY",
    "wof:name":"E/W Distributors",
    "wof:placetype":"venue"
},
  "geometry": {"coordinates":[-74.187315,41.563999],"type":"Point"}
}