{
  "type": "Feature",
  "properties": {
    "iso:country":"US",
    "sg:address":"720 E Franklin St",
    "sg:city":"Endicott",
    "sg:classifiers":[
        {
            "category":"Wholesale",
            "subcategory":"Machinery & Supplies",
            "type":"Manufacturing & Wholesale Goods"
        },
        {
            "category":"Building & Trades",
            "subcategory":"Equipment Rental",
            "type":"Services"
        }
    ],
    "sg:phone":"+1 607 748 3400",
    "sg:postcode":"13760",
    "sg:province":"NY",
    "sg:tags":[
        "heavy",
        "construction",
        "contractor"
    ],
    "sg:website":"http://www.andersonequip.com",
    "wof:name":"Anderson Equipment Company",
    "wof:placetype":"venue"
},
  "geometry": {"coordinates":[-76.055819,42.104289],"type":"Point"}
}