{
  "type": "Feature",
  "properties": {
    "addr:full":"7504 5th Avenue Brooklyn NY 11209",
    "addr:housenumber":"7504",
    "addr:postcode":"11209",
    "addr:street":"5Th Avenue",
    "iso:country":"US",
    "sg:address":"7504 5th Avenue",
    "sg:city":"Brooklyn",
    "sg:classifiers":[
        {
            "category":"Professional",
            "subcategory":"Lawyer & Legal Services",
            "type":"Services"
        }
    ],
    "sg:phone":"+1 718 680 8400",
    "sg:postcode":"11209",
    "sg:province":"NY",
    "sg:tags":[
        "divorce",
        "law",
        "family"
    ],
    "wof:name":"Hanna & Vlahakis",
    "wof:placetype":"venue"
},
  "geometry": {"coordinates":[-74.022851,40.629324],"type":"Point"}
}