{
  "type": "Feature",
  "properties": {
    "addr:full":"6524 Brockport Spencerport Rd Brockport NY 14420",
    "addr:postcode":"6524;14420",
    "addr:street":"Spencerport Rd",
    "iso:country":"US",
    "sg:address":"6524 Brockport Spencerport Rd",
    "sg:city":"Brockport",
    "sg:classifiers":[
        {
            "category":"Retail",
            "subcategory":"Auto Rental",
            "type":"Services"
        }
    ],
    "sg:phone":"+1 585 637 0260",
    "sg:postcode":"14420",
    "sg:province":"NY",
    "sg:tags":[
        "renting",
        "automobile",
        "passenger",
        "car"
    ],
    "wof:name":"Enterprise Rent A Car",
    "wof:placetype":"venue"
},
  "geometry": {"coordinates":[-77.938551,43.198409],"type":"Point"}
}