{
  "type": "Feature",
  "properties": {
    "iso:country":"US",
    "sg:address":"116 Sheridan Blvd",
    "sg:city":"Inwood",
    "sg:classifiers":[
        {
            "category":"Personal",
            "subcategory":"Barber",
            "type":"Services"
        }
    ],
    "sg:phone":"+1 914 837 3558",
    "sg:postcode":"11096",
    "sg:province":"NY",
    "wof:name":"All Star Haircuts",
    "wof:placetype":"venue"
},
  "geometry": {"coordinates":[-73.752487,40.614937],"type":"Point"}
}