{
  "type": "Feature",
  "properties": {
    "iso:country":"US",
    "sg:address":"12 Genesee St",
    "sg:city":"Greene",
    "sg:classifiers":[
        {
            "category":"Utilities",
            "subcategory":"Fuel Oil & Lpg",
            "type":"Services"
        }
    ],
    "sg:phone":"+1   ",
    "sg:postcode":"13778",
    "sg:province":"NY",
    "sg:tags":[
        "liquefied",
        "gas",
        "petroleum"
    ],
    "wof:name":"Halls Gas Service",
    "wof:placetype":"venue"
},
  "geometry": {"coordinates":[-75.769442,42.329226],"type":"Point"}
}