{
  "type": "Feature",
  "properties": {
    "addr:full":"52 Swan St Batavia NY 14020",
    "addr:housenumber":"52",
    "addr:postcode":"14020",
    "addr:street":"Swan St",
    "iso:country":"US",
    "sg:address":"52 Swan St",
    "sg:city":"Batavia",
    "sg:classifiers":[
        {
            "category":"Building & Trades",
            "subcategory":"Construction",
            "type":"Services"
        }
    ],
    "sg:phone":"+1 585 813 0008",
    "sg:postcode":"14020",
    "sg:province":"NY",
    "sg:tags":[
        "contractor"
    ],
    "wof:name":"Kerry E Boyle Construction",
    "wof:placetype":"venue"
},
  "geometry": {"coordinates":[-78.177727,42.993074],"type":"Point"}
}