{
  "type": "Feature",
  "properties": {
    "iso:country":"US",
    "sg:address":"925 S Lake Blvd",
    "sg:city":"Mahopac",
    "sg:classifiers":[
        {
            "category":"Organizations",
            "subcategory":"Non-profit Organization",
            "type":"Services"
        }
    ],
    "sg:phone":"+1 845 621 2203",
    "sg:postcode":"10541",
    "sg:province":"NY",
    "sg:tags":[
        "service/non-profit",
        "community"
    ],
    "sg:website":"national.unitedway.org",
    "wof:name":"United Way of Putnam",
    "wof:placetype":"venue"
},
  "geometry": {"coordinates":[-73.736504,41.3722],"type":"Point"}
}