{
  "type": "Feature",
  "properties": {
    "iso:country":"US",
    "sg:address":"1895 Saunders Settlement Rd",
    "sg:city":"Niagara Falls",
    "sg:classifiers":[
        {
            "category":"Building & Trades",
            "subcategory":"Construction",
            "type":"Services"
        }
    ],
    "sg:phone":"+1 716 297 1161",
    "sg:postcode":"14304",
    "sg:province":"NY",
    "sg:tags":[
        "dry wall",
        "contractor"
    ],
    "wof:name":"Jack Difranco",
    "wof:placetype":"venue"
},
  "geometry": {"coordinates":[-78.934364,43.141732],"type":"Point"}
}