{
  "type": "Feature",
  "properties": {
    "addr:full":"80 Modular Ave Commack NY 11725",
    "addr:housenumber":"80",
    "addr:postcode":"11725",
    "addr:street":"Modular Ave",
    "iso:country":"US",
    "sg:address":"80 Modular Ave",
    "sg:city":"Commack",
    "sg:classifiers":[
        {
            "category":"Wholesale",
            "subcategory":"Machinery & Supplies",
            "type":"Manufacturing & Wholesale Goods"
        },
        {
            "category":"Wholesale",
            "subcategory":"Durable Goods & Equipment",
            "type":"Manufacturing & Wholesale Goods"
        }
    ],
    "sg:phone":"+1 631 864 5588",
    "sg:postcode":"11725",
    "sg:province":"NY",
    "sg:tags":[
        "industrial",
        "representative",
        "manufacturer"
    ],
    "wof:name":"ERA Industrial Sales Corp Inc",
    "wof:placetype":"venue"
},
  "geometry": {"coordinates":[-73.274219,40.811779],"type":"Point"}
}