{
  "type": "Feature",
  "properties": {
    "iso:country":"US",
    "sg:address":"974 Ave of the Americas",
    "sg:city":"New York",
    "sg:classifiers":[
        {
            "category":"Shopping",
            "subcategory":"Clothing, Apparel, & Fashions",
            "type":"Retail Goods"
        }
    ],
    "sg:phone":"+1   ",
    "sg:postcode":"10018",
    "sg:province":"NY",
    "wof:name":"Uno Collections Inc",
    "wof:placetype":"venue"
},
  "geometry": {"coordinates":[-73.987071,40.750506],"type":"Point"}
}