{
  "type": "Feature",
  "properties": {
    "iso:country":"US",
    "sg:address":"616 S Main St",
    "sg:city":"New City",
    "sg:classifiers":[
        {
            "category":"Professional",
            "subcategory":"Lawyer & Legal Services",
            "type":"Services"
        }
    ],
    "sg:phone":"+1 845 639 1320",
    "sg:postcode":"10956",
    "sg:province":"NY",
    "sg:tags":[
        "attorney"
    ],
    "wof:name":"Samimi & Murphy",
    "wof:placetype":"venue"
},
  "geometry": {"coordinates":[-73.992082,41.125921],"type":"Point"}
}