{
  "type": "Feature",
  "properties": {
    "addr:full":"42 Central Park S New York NY 10019",
    "addr:housenumber":"42",
    "addr:postcode":"10019",
    "addr:street":"Central Park S",
    "iso:country":"US",
    "sg:address":"42 Central Park S",
    "sg:city":"New York",
    "sg:classifiers":[
        {
            "category":"Restaurant",
            "type":"Food & Drink"
        }
    ],
    "sg:phone":"+1 212 688 7777",
    "sg:postcode":"10019",
    "sg:province":"NY",
    "sg:tags":[
        "sport",
        "bar"
    ],
    "sg:website":"www.mickeymantles.com",
    "wof:name":"Mickey Mantle's Restaurant and Sports Bar",
    "wof:placetype":"venue"
},
  "geometry": {"coordinates":[-73.97531499999999,40.765302],"type":"Point"}
}