{
  "type": "Feature",
  "properties": {
    "iso:country":"US",
    "sg:address":"120 Lafayette Ave.",
    "sg:city":"Brooklyn",
    "sg:classifiers":[
        {
            "category":"Restaurant",
            "type":"Food & Drink"
        }
    ],
    "sg:postcode":"11205",
    "sg:province":"NY",
    "sg:tags":[
        "caribbean",
        "african"
    ],
    "wof:name":"EN Restaurant and Bar",
    "wof:placetype":"venue"
},
  "geometry": {"coordinates":[-73.972635,40.687403],"type":"Point"}
}