{
  "type": "Feature",
  "properties": {
    "addr:full":"3727 91st Street Jackson Heights NY 11372",
    "addr:housenumber":"3727",
    "addr:postcode":"11372",
    "addr:street":"91St Street",
    "iso:country":"US",
    "sg:address":"3727 91st Street",
    "sg:city":"Jackson Heights",
    "sg:classifiers":[
        {
            "category":"Shopping",
            "subcategory":"Mobile Phones",
            "type":"Retail Goods"
        }
    ],
    "sg:phone":"+1 718 565 5504",
    "sg:postcode":"11372",
    "sg:province":"NY",
    "sg:website":"www.picocircuits.com",
    "wof:name":"Pico Circuits",
    "wof:placetype":"venue"
},
  "geometry": {"coordinates":[-73.87559400000001,40.749537],"type":"Point"}
}