{
  "type": "Feature",
  "properties": {
    "addr:full":"1681 Lyell Ave Rochester NY 14606",
    "addr:housenumber":"1681",
    "addr:postcode":"14606",
    "addr:street":"Lyell Ave",
    "iso:country":"US",
    "sg:address":"1681 Lyell Ave",
    "sg:city":"Rochester",
    "sg:classifiers":[
        {
            "category":"Wholesale",
            "subcategory":"Construction Materials",
            "type":"Manufacturing & Wholesale Goods"
        }
    ],
    "sg:phone":"+1 585 647 4020",
    "sg:postcode":"14606",
    "sg:province":"NY",
    "sg:tags":[
        "pallet",
        "skid"
    ],
    "wof:name":"Pallet Services Inc",
    "wof:placetype":"venue"
},
  "geometry": {"coordinates":[-77.670379,43.164669],"type":"Point"}
}