{
  "type": "Feature",
  "properties": {
    "addr:full":"12 Kisco Ave Mt Kisco NY 10549",
    "addr:housenumber":"12",
    "addr:postcode":"10549",
    "addr:street":"Kisco Ave Mt Kisco",
    "iso:country":"US",
    "sg:address":"12 Kisco Ave",
    "sg:city":"Mt Kisco",
    "sg:classifiers":[
        {
            "category":"Building & Trades",
            "subcategory":"Construction",
            "type":"Services"
        }
    ],
    "sg:phone":"+1 914 244 3886",
    "sg:postcode":"10549",
    "sg:province":"NY",
    "sg:tags":[
        "general",
        "contractor"
    ],
    "wof:name":"Empire Contracting",
    "wof:placetype":"venue"
},
  "geometry": {"coordinates":[-73.729285,41.209848],"type":"Point"}
}