{
  "type": "Feature",
  "properties": {
    "addr:full":"274 W Main St Malone NY 12953",
    "addr:housenumber":"274",
    "addr:postcode":"12953",
    "addr:street":"W Main St",
    "iso:country":"US",
    "sg:address":"274 W Main St",
    "sg:city":"Malone",
    "sg:classifiers":[
        {
            "category":"Personal",
            "type":"Services"
        },
        {
            "category":"Sports & Exercise",
            "subcategory":"Gym",
            "type":"Entertainment"
        },
        {
            "category":"Health Services",
            "subcategory":"Health Practitioner",
            "type":"Services"
        },
        {
            "category":"Arena",
            "subcategory":"Sports Club",
            "type":"Entertainment"
        }
    ],
    "sg:phone":"+1 518 483 8377",
    "sg:postcode":"12953",
    "sg:province":"NY",
    "sg:tags":[
        "control",
        "weight",
        "consultant",
        "program",
        "fitness",
        "physical"
    ],
    "sg:website":"http://www.curves.com",
    "wof:name":"Curves",
    "wof:placetype":"venue"
},
  "geometry": {"coordinates":[-74.30296300000001,44.848469],"type":"Point"}
}