{
  "type": "Feature",
  "properties": {
    "addr:full":"1041 Findlay Ave Bronx NY 10456",
    "addr:housenumber":"1041",
    "addr:postcode":"10456",
    "addr:street":"Findlay Ave",
    "iso:country":"US",
    "sg:address":"1041 Findlay Ave",
    "sg:city":"Bronx",
    "sg:classifiers":[
        {
            "category":"Organizations",
            "subcategory":"Religious Organization",
            "type":"Services"
        }
    ],
    "sg:phone":"+1 718 588 9263",
    "sg:postcode":"10456",
    "sg:province":"NY",
    "sg:tags":[
        "church"
    ],
    "wof:name":"Iglesia Acym Del Bronx",
    "wof:placetype":"venue"
},
  "geometry": {"coordinates":[-73.914242,40.829594],"type":"Point"}
}