{
  "type": "Feature",
  "properties": {
    "addr:full":"403 Main St Port Washington NY 11050",
    "addr:housenumber":"403",
    "addr:postcode":"11050",
    "addr:street":"Main St",
    "iso:country":"US",
    "sg:address":"403 Main St",
    "sg:city":"Port Washington",
    "sg:classifiers":[
        {
            "category":"Wholesale",
            "subcategory":"Sporting Goods",
            "type":"Manufacturing & Wholesale Goods"
        }
    ],
    "sg:phone":"+1 516 767 0141",
    "sg:postcode":"11050",
    "sg:province":"NY",
    "sg:tags":[
        "new",
        "used",
        "boat",
        "chartering"
    ],
    "wof:name":"Lager Yacht Inc",
    "wof:placetype":"venue"
},
  "geometry": {"coordinates":[-73.702056,40.830061],"type":"Point"}
}