{
  "type": "Feature",
  "properties": {
    "addr:full":"196 Elizabeth St New York NY 10012",
    "addr:housenumber":"196",
    "addr:postcode":"10012",
    "addr:street":"Elizabeth St",
    "iso:country":"US",
    "sg:address":"196 Elizabeth St",
    "sg:city":"New York",
    "sg:classifiers":[
        {
            "category":"Restaurant",
            "type":"Food & Drink"
        }
    ],
    "sg:menulink":"http://www.allmenus.com/ny/new-york/2268-lovely-day/menu/",
    "sg:phone":"+1 212 925 3310",
    "sg:postcode":"10012",
    "sg:province":"NY",
    "sg:tags":[
        "thai",
        "asian"
    ],
    "wof:name":"Lovely Day",
    "wof:placetype":"venue"
},
  "geometry": {"coordinates":[-73.99421700000001,40.721775],"type":"Point"}
}