{
  "type": "Feature",
  "properties": {
    "addr:full":"202 Riverside Drive Apt 5G New York NY 10025",
    "addr:housenumber":"202",
    "addr:postcode":"10025",
    "addr:street":"Riverside Drive Apt 5G",
    "iso:country":"US",
    "sg:address":"202 Riverside Drive Apt 5G",
    "sg:city":"New York",
    "sg:classifiers":[
        {
            "category":"Building & Trades",
            "subcategory":"Construction",
            "type":"Services"
        }
    ],
    "sg:phone":"+1 212 662 8888",
    "sg:postcode":"10025",
    "sg:province":"NY",
    "sg:tags":[
        "interior",
        "design"
    ],
    "wof:name":"Cherie Zucker",
    "wof:placetype":"venue"
},
  "geometry": {"coordinates":[-73.96818,40.797043],"type":"Point"}
}