{
  "type": "Feature",
  "properties": {
    "addr:full":"45-20 43 Ave Sunnyside NY 11104",
    "addr:housenumber":"45-20",
    "addr:postcode":"11104",
    "addr:street":"43 Ave",
    "iso:country":"US",
    "sg:address":"45-20 43 Ave",
    "sg:city":"Sunnyside",
    "sg:classifiers":[
        {
            "category":"Health Services",
            "subcategory":"Health Practitioner",
            "type":"Services"
        }
    ],
    "sg:phone":"+1 718 433 0042",
    "sg:postcode":"11104",
    "sg:province":"NY",
    "sg:tags":[
        "acupuncture"
    ],
    "wof:name":"Chang S Acupuncture",
    "wof:placetype":"venue"
},
  "geometry": {"coordinates":[-73.918695,40.744839],"type":"Point"}
}