{
  "type": "Feature",
  "properties": {
    "addr:full":"1668 Hylan Boulevard Staten Island NY 10305",
    "addr:housenumber":"1668",
    "addr:postcode":"10305",
    "addr:street":"Hylan Boulevard",
    "iso:country":"US",
    "sg:address":"1668 Hylan Boulevard",
    "sg:city":"Staten Island",
    "sg:classifiers":[
        {
            "category":"Shopping",
            "subcategory":"Crafts & Fabrics",
            "type":"Retail Goods"
        }
    ],
    "sg:phone":"+1 718 987 0505",
    "sg:postcode":"10305",
    "sg:province":"NY",
    "sg:tags":[
        "art",
        "supply"
    ],
    "wof:name":"Island Art Center",
    "wof:placetype":"venue"
},
  "geometry": {"coordinates":[-74.090896,40.587961],"type":"Point"}
}