{
  "type": "Feature",
  "properties": {
    "iso:country":"US",
    "sg:address":"835 Blooming Grove Tpke",
    "sg:city":"New Windsor",
    "sg:classifiers":[
        {
            "category":"Building & Trades",
            "subcategory":"Construction",
            "type":"Services"
        }
    ],
    "sg:phone":"+1 845 562 3234",
    "sg:postcode":"12553",
    "sg:province":"NY",
    "sg:tags":[
        "carpentry",
        "contractor"
    ],
    "wof:name":"Cela Carpentry LLC",
    "wof:placetype":"venue"
},
  "geometry": {"coordinates":[-74.053349,41.455444],"type":"Point"}
}