{
  "type": "Feature",
  "properties": {
    "addr:full":"15038 Union Tpke Flushing NY 11367",
    "addr:housenumber":"15038",
    "addr:postcode":"11367",
    "addr:street":"Union Tpke",
    "iso:country":"US",
    "sg:address":"15038 Union Tpke",
    "sg:city":"Flushing",
    "sg:classifiers":[
        {
            "category":"Real Estate",
            "subcategory":"Real Estate Services",
            "type":"Services"
        }
    ],
    "sg:phone":"+1 718 591 3142",
    "sg:postcode":"11367",
    "sg:province":"NY",
    "sg:tags":[
        "management",
        "condominium"
    ],
    "wof:name":"Village Mall-Hillcrest Condo",
    "wof:placetype":"venue"
},
  "geometry": {"coordinates":[-73.82687799999999,40.716995],"type":"Point"}
}