{
  "type": "Feature",
  "properties": {
    "iso:country":"US",
    "sg:address":"109 W 38th St",
    "sg:city":"New York",
    "sg:classifiers":[
        {
            "category":"Manufacturing",
            "subcategory":"Retail Goods",
            "type":"Manufacturing & Wholesale Goods"
        }
    ],
    "sg:phone":"+1 212 719 3110",
    "sg:postcode":"10018",
    "sg:province":"NY",
    "sg:tags":[
        "craft",
        "art",
        "mfg"
    ],
    "sg:website":"www.ejoyce.com",
    "wof:name":"Joyce Trimming",
    "wof:placetype":"venue"
},
  "geometry": {"coordinates":[-73.98634199999999,40.75273],"type":"Point"}
}