{
  "type": "Feature",
  "properties": {
    "addr:full":"5524 Main St Williamsville NY 14221",
    "addr:housenumber":"5524",
    "addr:postcode":"14221",
    "addr:street":"Main St",
    "iso:country":"US",
    "sg:address":"5524 Main St",
    "sg:city":"Williamsville",
    "sg:classifiers":[
        {
            "category":"Shopping",
            "subcategory":"Clothing, Apparel, & Fashions",
            "type":"Retail Goods"
        }
    ],
    "sg:phone":"+1 716 631 2722",
    "sg:postcode":"14221",
    "sg:province":"NY",
    "sg:tags":[
        "apparel",
        "clothing",
        "store",
        "women's"
    ],
    "wof:name":"Jacqueline Shoppe",
    "wof:placetype":"venue"
},
  "geometry": {"coordinates":[-78.747401,42.962438],"type":"Point"}
}