{
  "type": "Feature",
  "properties": {
    "addr:full":"161 W 231st St Bronx NY 10463",
    "addr:housenumber":"161",
    "addr:postcode":"10463",
    "addr:street":"W 231St St",
    "iso:country":"US",
    "sg:address":"161 W 231st St",
    "sg:city":"Bronx",
    "sg:classifiers":[
        {
            "category":"Shopping",
            "subcategory":"Florist",
            "type":"Retail Goods"
        }
    ],
    "sg:phone":"+1   ",
    "sg:postcode":"10463",
    "sg:province":"NY",
    "wof:name":"Riverdale Florist",
    "wof:placetype":"venue"
},
  "geometry": {"coordinates":[-73.90304500000001,40.878267],"type":"Point"}
}