{
  "type": "Feature",
  "properties": {
    "addr:full":"110 Heyward St Brooklyn NY 11206",
    "addr:housenumber":"110",
    "addr:postcode":"11206",
    "addr:street":"Heyward St",
    "iso:country":"US",
    "sg:address":"110 Heyward St",
    "sg:city":"Brooklyn",
    "sg:classifiers":[
        {
            "category":"Wholesale",
            "subcategory":"Groceries",
            "type":"Manufacturing & Wholesale Goods"
        }
    ],
    "sg:phone":"+1 718 875 1351",
    "sg:postcode":"11206",
    "sg:province":"NY",
    "sg:tags":[
        "confectionery"
    ],
    "wof:name":"S & P Distributing Inc",
    "wof:placetype":"venue"
},
  "geometry": {"coordinates":[-73.95684199999999,40.700889],"type":"Point"}
}