{
  "type": "Feature",
  "properties": {
    "addr:full":"116 Seneca St Penn Yan NY 14527",
    "addr:housenumber":"116",
    "addr:postcode":"14527",
    "addr:street":"Seneca St",
    "iso:country":"US",
    "sg:address":"116 Seneca St",
    "sg:city":"Penn Yan",
    "sg:classifiers":[
        {
            "category":"Manufacturing",
            "subcategory":"Printing",
            "type":"Manufacturing & Wholesale Goods"
        }
    ],
    "sg:phone":"+1   ",
    "sg:postcode":"14527",
    "sg:province":"NY",
    "sg:tags":[
        "offset"
    ],
    "wof:name":"Tillman Press Inc",
    "wof:placetype":"venue"
},
  "geometry": {"coordinates":[-77.05130200000001,42.660332],"type":"Point"}
}