{
  "type": "Feature",
  "properties": {
    "iso:country":"US",
    "sg:address":"9505 Carousel Center",
    "sg:city":"Syracuse",
    "sg:classifiers":[
        {
            "category":"Shopping",
            "subcategory":"Clothing, Apparel, & Fashions",
            "type":"Retail Goods"
        }
    ],
    "sg:phone":"+1 315 466 3406",
    "sg:postcode":"13290",
    "sg:province":"NY",
    "sg:tags":[
        "sportswear"
    ],
    "sg:website":"www.ae.com",
    "wof:name":"American Eagle Outfitters",
    "wof:placetype":"venue"
},
  "geometry": {"coordinates":[-76.17066199999999,43.067076],"type":"Point"}
}