{
  "type": "Feature",
  "properties": {
    "addr:full":"51 Central Park Ave Yonkers NY 10705",
    "addr:housenumber":"51",
    "addr:postcode":"10705",
    "addr:street":"Central Park Ave",
    "iso:country":"US",
    "sg:address":"51 Central Park Ave",
    "sg:city":"Yonkers",
    "sg:classifiers":[
        {
            "category":"Building & Trades",
            "subcategory":"Construction",
            "type":"Services"
        }
    ],
    "sg:phone":"+1 914 376 1761",
    "sg:postcode":"10705",
    "sg:province":"NY",
    "sg:tags":[
        "floor",
        "wood",
        "refinishing",
        "contractor"
    ],
    "wof:name":"Woodcraft Floors Inc",
    "wof:placetype":"venue"
},
  "geometry": {"coordinates":[-73.87817200000001,40.907095],"type":"Point"}
}