{
  "type": "Feature",
  "properties": {
    "addr:full":"189 Babylon Tpke Roosevelt NY 11575",
    "addr:housenumber":"189",
    "addr:postcode":"11575",
    "addr:street":"Babylon Tpke",
    "iso:country":"US",
    "sg:address":"189 Babylon Tpke",
    "sg:city":"Roosevelt",
    "sg:classifiers":[
        {
            "category":"Government",
            "subcategory":"Office",
            "type":"Public Place"
        }
    ],
    "sg:phone":"+1 718 479 3331",
    "sg:postcode":"11575",
    "sg:province":"NY",
    "sg:tags":[
        "development",
        "economic",
        "agency"
    ],
    "wof:name":"Memorial Economic Dev Corp",
    "wof:placetype":"venue"
},
  "geometry": {"coordinates":[-73.584172,40.675833],"type":"Point"}
}