{
  "type": "Feature",
  "properties": {
    "addr:full":"141 Combs Ave Woodmere NY 11598",
    "addr:housenumber":"141",
    "addr:postcode":"11598",
    "addr:street":"Combs Ave",
    "iso:country":"US",
    "sg:address":"141 Combs Ave",
    "sg:city":"Woodmere",
    "sg:classifiers":[
        {
            "category":"Professional",
            "subcategory":"Management & Consulting",
            "type":"Services"
        }
    ],
    "sg:phone":"+1 516 569 0696",
    "sg:postcode":"11598",
    "sg:province":"NY",
    "wof:name":"Brewster Management Corp",
    "wof:placetype":"venue"
},
  "geometry": {"coordinates":[-73.700299,40.628915],"type":"Point"}
}