{
  "type": "Feature",
  "properties": {
    "addr:full":"38 Wellington Dr New Windsor NY 12553",
    "addr:housenumber":"38",
    "addr:postcode":"12553",
    "addr:street":"Wellington Dr",
    "iso:country":"US",
    "sg:address":"38 Wellington Dr",
    "sg:city":"New Windsor",
    "sg:classifiers":[
        {
            "category":"Freight",
            "type":"Transportation"
        }
    ],
    "sg:phone":"+1   ",
    "sg:postcode":"12553",
    "sg:province":"NY",
    "sg:tags":[
        "operator",
        "local",
        "trucking"
    ],
    "wof:name":"Northstar Trucking Excv",
    "wof:placetype":"venue"
},
  "geometry": {"coordinates":[-74.023704,41.472984],"type":"Point"}
}