{
  "type": "Feature",
  "properties": {
    "iso:country":"US",
    "sg:address":"311 Senator St",
    "sg:city":"Brooklyn",
    "sg:classifiers":[
        {
            "category":"Organizations",
            "subcategory":"Non-profit Organization",
            "type":"Services"
        }
    ],
    "sg:phone":"+1 718 836 8775",
    "sg:postcode":"11220",
    "sg:province":"NY",
    "wof:name":"Guild For Exceptional Children",
    "wof:placetype":"venue"
},
  "geometry": {"coordinates":[-74.023073,40.636279],"type":"Point"}
}