{
  "type": "Feature",
  "properties": {
    "iso:country":"US",
    "sg:address":"6644 Skinner Rd",
    "sg:city":"Rome",
    "sg:classifiers":[
        {
            "category":"Farming",
            "subcategory":"Dairy Farm",
            "type":"Manufacturing & Wholesale Goods"
        }
    ],
    "sg:phone":"+1 315 337 0061",
    "sg:postcode":"13490",
    "sg:province":"NY",
    "wof:name":"Peter & Louis Talma",
    "wof:placetype":"venue"
},
  "geometry": {"coordinates":[-75.46340499999999,43.119085],"type":"Point"}
}