{
  "type": "Feature",
  "properties": {
    "addr:full":"225 Park Row Manhattan NY 10038",
    "addr:housenumber":"225",
    "addr:postcode":"10038",
    "addr:street":"Park Row",
    "iso:country":"US",
    "sg:address":"225 Park Row",
    "sg:city":"Manhattan",
    "sg:classifiers":[
        {
            "category":"Restaurant",
            "type":"Food & Drink"
        }
    ],
    "sg:phone":"+1 212 385 8118",
    "sg:postcode":"10038",
    "sg:province":"NY",
    "sg:tags":[
        "pizza"
    ],
    "wof:name":"Luna Pizza",
    "wof:placetype":"venue"
},
  "geometry": {"coordinates":[-73.998948,40.713298],"type":"Point"}
}