{
  "type": "Feature",
  "properties": {
    "addr:full":"540 Ashland Ave Buffalo NY 14222",
    "addr:housenumber":"540",
    "addr:postcode":"14222",
    "addr:street":"Ashland Ave",
    "iso:country":"US",
    "sg:address":"540 Ashland Ave",
    "sg:city":"Buffalo",
    "sg:classifiers":[
        {
            "category":"Shopping",
            "subcategory":"Bicycles & Sporting Goods",
            "type":"Retail Goods"
        }
    ],
    "sg:phone":"+1   ",
    "sg:postcode":"14222",
    "sg:province":"NY",
    "wof:name":"Chucks Reloading",
    "wof:placetype":"venue"
},
  "geometry": {"coordinates":[-78.878694,42.918987],"type":"Point"}
}