{
  "type": "Feature",
  "properties": {
    "iso:country":"US",
    "sg:address":"46 Beekman Ave",
    "sg:city":"Sleepy Hollow",
    "sg:classifiers":[
        {
            "category":"Professional",
            "subcategory":"Lawyer & Legal Services",
            "type":"Services"
        }
    ],
    "sg:phone":"+1 914 332 7576",
    "sg:postcode":"10591",
    "sg:province":"NY",
    "sg:tags":[
        "notary"
    ],
    "wof:name":"Notary & Public Accountant Co",
    "wof:placetype":"venue"
},
  "geometry": {"coordinates":[-73.860373,41.475144],"type":"Point"}
}