{
  "type": "Feature",
  "properties": {
    "iso:country":"US",
    "sg:address":"1400 Altamont Ave",
    "sg:city":"Schenectady",
    "sg:classifiers":[
        {
            "category":"Food & Beverages",
            "subcategory":"Groceries & Convenience Stores",
            "type":"Retail Goods"
        }
    ],
    "sg:phone":"+1   ",
    "sg:postcode":"12303",
    "sg:province":"NY",
    "sg:tags":[
        "tape",
        "video",
        "rental"
    ],
    "wof:name":"Hannaford 320",
    "wof:placetype":"venue"
},
  "geometry": {"coordinates":[-73.945894,42.784538],"type":"Point"}
}