{
  "type": "Feature",
  "properties": {
    "addr:full":"67 The Blvd Amityville NY 11701",
    "addr:housenumber":"67",
    "addr:postcode":"11701",
    "addr:street":"The Blvd",
    "iso:country":"US",
    "sg:address":"67 The Blvd",
    "sg:city":"Amityville",
    "sg:classifiers":[
        {
            "category":"Organizations",
            "subcategory":"Religious Organization",
            "type":"Services"
        }
    ],
    "sg:phone":"+1 631 789 5610",
    "sg:postcode":"11701",
    "sg:province":"NY",
    "wof:name":"Frank White",
    "wof:placetype":"venue"
},
  "geometry": {"coordinates":[-73.420509,40.701279],"type":"Point"}
}