{
  "type": "Feature",
  "properties": {
    "iso:country":"US",
    "sg:address":"74 Devoe Rd",
    "sg:city":"Chappaqua",
    "sg:classifiers":[
        {
            "category":"Wholesale",
            "subcategory":"Farm Supplies",
            "type":"Manufacturing & Wholesale Goods"
        }
    ],
    "sg:phone":"+1 914 238 8816",
    "sg:postcode":"10514",
    "sg:province":"NY",
    "sg:tags":[
        "raw",
        "product",
        "material"
    ],
    "wof:name":"Kaplow Enterprises",
    "wof:placetype":"venue"
},
  "geometry": {"coordinates":[-73.756012,41.160251],"type":"Point"}
}