{
  "type": "Feature",
  "properties": {
    "iso:country":"US",
    "sg:address":"3036 Old Vestal Rd",
    "sg:city":"Vestal",
    "sg:classifiers":[
        {
            "category":"Shopping",
            "type":"Retail Goods"
        }
    ],
    "sg:phone":"+1 607 770 7387",
    "sg:postcode":"13850",
    "sg:province":"NY",
    "sg:tags":[
        "pet",
        "shop"
    ],
    "wof:name":"Vestal Playful Pets",
    "wof:placetype":"venue"
},
  "geometry": {"coordinates":[-76.001339,42.10316],"type":"Point"}
}