{
  "type": "Feature",
  "properties": {
    "iso:country":"US",
    "sg:address":"120 Ontario St",
    "sg:city":"Rochester",
    "sg:classifiers":[
        {
            "category":"Social Services",
            "subcategory":"Job Training",
            "type":"Services"
        }
    ],
    "sg:phone":"+1   ",
    "sg:postcode":"14605",
    "sg:province":"NY",
    "wof:name":"Rochester Lndscp Techncns Prog",
    "wof:placetype":"venue"
},
  "geometry": {"coordinates":[-77.59399000000001,43.163759],"type":"Point"}
}