{
  "type": "Feature",
  "properties": {
    "iso:country":"US",
    "sg:address":"273 Main St",
    "sg:city":"Farmingdale",
    "sg:classifiers":[
        {
            "category":"Deli",
            "type":"Food & Drink"
        }
    ],
    "sg:menulink":"http://www.allmenus.com/ny/farmingdale/126382-blimpie-subs--sandwiches/menu/",
    "sg:phone":"+1 516 756 0575",
    "sg:postcode":"11735",
    "sg:province":"NY",
    "sg:tags":[
        "wrap",
        "american",
        "sandwich"
    ],
    "wof:name":"Blimpie Subs & Sandwiches",
    "wof:placetype":"venue"
},
  "geometry": {"coordinates":[-73.44547799999999,40.730862],"type":"Point"}
}