{
  "type": "Feature",
  "properties": {
    "iso:country":"US",
    "sg:address":"5306 New Utrecht Ave",
    "sg:city":"Brooklyn",
    "sg:classifiers":[
        {
            "category":"Manufacturing",
            "subcategory":"Apparel",
            "type":"Manufacturing & Wholesale Goods"
        }
    ],
    "sg:phone":"+1   ",
    "sg:postcode":"11219",
    "sg:province":"NY",
    "wof:name":"Pinpoint For Kids",
    "wof:placetype":"venue"
},
  "geometry": {"coordinates":[-73.995361,40.63245],"type":"Point"}
}