{
  "type": "Feature",
  "properties": {
    "iso:country":"US",
    "sg:address":"498 Factory St",
    "sg:city":"Watertown",
    "sg:classifiers":[
        {
            "category":"Restaurant",
            "type":"Food & Drink"
        }
    ],
    "sg:phone":"+1 315 785 9392",
    "sg:postcode":"13601",
    "sg:province":"NY",
    "wof:name":"Coach's Restaurant & Sports",
    "wof:placetype":"venue"
},
  "geometry": {"coordinates":[-75.90168,43.976875],"type":"Point"}
}