{
  "type": "Feature",
  "properties": {
    "iso:country":"US",
    "sg:address":"771 Latimer Hill Rd",
    "sg:city":"Canajoharie",
    "sg:classifiers":[
        {
            "category":"Farming",
            "subcategory":"Dairy Farm",
            "type":"Manufacturing & Wholesale Goods"
        }
    ],
    "sg:phone":"+1 518 673 2668",
    "sg:postcode":"13317",
    "sg:province":"NY",
    "wof:name":"Try-Ayr Farm",
    "wof:placetype":"venue"
},
  "geometry": {"coordinates":[-74.585421,42.832681],"type":"Point"}
}