{
  "type": "Feature",
  "properties": {
    "iso:country":"US",
    "sg:address":"215 Edwards Ave",
    "sg:city":"Calverton",
    "sg:classifiers":[
        {
            "category":"Building & Trades",
            "subcategory":"Construction",
            "type":"Services"
        }
    ],
    "sg:phone":"+1 631 369 9650",
    "sg:postcode":"11933",
    "sg:province":"NY",
    "sg:tags":[
        "designer",
        "dealer",
        "pool",
        "swimming"
    ],
    "wof:name":"Palatial Pools & Construction",
    "wof:placetype":"venue"
},
  "geometry": {"coordinates":[-72.745833,40.912024],"type":"Point"}
}