{
  "type": "Feature",
  "properties": {
    "addr:full":"7690 Foxtail Pine Liverpool NY 13090",
    "addr:housenumber":"7690",
    "addr:postcode":"13090",
    "addr:street":"Foxtail Pine",
    "iso:country":"US",
    "sg:address":"7690 Foxtail Pine",
    "sg:city":"Liverpool",
    "sg:classifiers":[
        {
            "category":"Professional",
            "subcategory":"Secretarial Services",
            "type":"Services"
        }
    ],
    "sg:phone":"+1 315 461 9064",
    "sg:postcode":"13090",
    "sg:province":"NY",
    "sg:tags":[
        "convention",
        "court",
        "reporter"
    ],
    "wof:name":"Jane Zappala",
    "wof:placetype":"venue"
},
  "geometry": {"coordinates":[-76.173648,43.142936],"type":"Point"}
}