{
  "type": "Feature",
  "properties": {
    "addr:full":"510 State St Rochester NY 14608",
    "addr:housenumber":"510",
    "addr:postcode":"14608",
    "addr:street":"State St",
    "iso:country":"US",
    "sg:address":"510 State St",
    "sg:city":"Rochester",
    "sg:classifiers":[
        {
            "category":"Wholesale",
            "subcategory":"Chemicals & Plastics",
            "type":"Manufacturing & Wholesale Goods"
        }
    ],
    "sg:phone":"+1 585 325 4730",
    "sg:postcode":"14608",
    "sg:province":"NY",
    "sg:tags":[
        "distributes",
        "industrial",
        "gas",
        "welding",
        "supply"
    ],
    "sg:website":"www.rochweld.com",
    "wof:name":"Rochester Welding Supply Corp",
    "wof:placetype":"venue"
},
  "geometry": {"coordinates":[-77.622913,43.164333],"type":"Point"}
}