{
  "type": "Feature",
  "properties": {
    "iso:country":"US",
    "sg:address":"22 Co Rd 52",
    "sg:city":"North Lawrence",
    "sg:classifiers":[
        {
            "category":"Wholesale",
            "subcategory":"Groceries",
            "type":"Manufacturing & Wholesale Goods"
        }
    ],
    "sg:phone":"+1 315 389 5111",
    "sg:postcode":"12967",
    "sg:province":"NY",
    "sg:tags":[
        "food",
        "product"
    ],
    "sg:website":"www.coolbrandsinc.com",
    "wof:name":"Coolbrands Dairy Inc",
    "wof:placetype":"venue"
},
  "geometry": {"coordinates":[-74.674995,44.805055],"type":"Point"}
}