{
  "type": "Feature",
  "properties": {
    "addr:full":"160 Walt Whitman Rd Ste 1088 Huntington Station NY 11746",
    "addr:housenumber":"160",
    "addr:postcode":"11746",
    "addr:street":"Walt Whitman Rd Ste 1088 Huntington Station",
    "iso:country":"US",
    "sg:address":"160 Walt Whitman Rd Ste 1088",
    "sg:city":"Huntington Station",
    "sg:classifiers":[
        {
            "category":"Shopping",
            "subcategory":"Shoes",
            "type":"Retail Goods"
        }
    ],
    "sg:phone":"+1 631 421 9255",
    "sg:postcode":"11746",
    "sg:province":"NY",
    "sg:tags":[
        "store"
    ],
    "wof:name":"The Walking Company",
    "wof:placetype":"venue"
},
  "geometry": {"coordinates":[-73.412145,40.823357],"type":"Point"}
}