{
  "type": "Feature",
  "properties": {
    "iso:country":"US",
    "sg:address":"367 E Main St",
    "sg:city":"Waterloo",
    "sg:classifiers":[
        {
            "category":"Health Services",
            "subcategory":"Clinic",
            "type":"Services"
        }
    ],
    "sg:phone":"+1 315 787 4977",
    "sg:postcode":"13165",
    "sg:province":"NY",
    "sg:tags":[
        "welfare"
    ],
    "wof:name":"Seneca Family Health Center",
    "wof:placetype":"venue"
},
  "geometry": {"coordinates":[-76.84610000000001,42.901794],"type":"Point"}
}