{
  "type": "Feature",
  "properties": {
    "addr:full":"754 Allerton Ave Bronx NY 10467",
    "addr:housenumber":"754",
    "addr:postcode":"10467",
    "addr:street":"Allerton Ave",
    "iso:country":"US",
    "sg:address":"754 Allerton Ave",
    "sg:city":"Bronx",
    "sg:classifiers":[
        {
            "category":"Shopping",
            "subcategory":"Jewelry",
            "type":"Retail Goods"
        }
    ],
    "sg:phone":"+1 718 519 8030",
    "sg:postcode":"10467",
    "sg:province":"NY",
    "wof:name":"Cash Gordon",
    "wof:placetype":"venue"
},
  "geometry": {"coordinates":[-73.8653,40.865455],"type":"Point"}
}