{
  "type": "Feature",
  "properties": {
    "iso:country":"US",
    "sg:address":"2021 84th Street",
    "sg:city":"Brooklyn",
    "sg:classifiers":[
        {
            "category":"Professional",
            "subcategory":"Computer Services",
            "type":"Services"
        }
    ],
    "sg:phone":"+1 718 333 9719",
    "sg:postcode":"11214",
    "sg:province":"NY",
    "sg:tags":[
        "repair"
    ],
    "wof:name":"Whitedragon Tech Systems",
    "wof:placetype":"venue"
},
  "geometry": {"coordinates":[-73.996595,40.605505],"type":"Point"}
}