{
  "type": "Feature",
  "properties": {
    "iso:country":"US",
    "sg:address":"455 Rockland St",
    "sg:city":"Westbury",
    "sg:classifiers":[
        {
            "category":"Education",
            "subcategory":"School",
            "type":"Public Place"
        }
    ],
    "sg:phone":"+1 516 876 5082",
    "sg:postcode":"11590",
    "sg:province":"NY",
    "sg:tags":[
        "middle"
    ],
    "wof:name":"Westbury Middle School",
    "wof:placetype":"venue"
},
  "geometry": {"coordinates":[-73.58434,40.762218],"type":"Point"}
}