{
  "type": "Feature",
  "properties": {
    "addr:full":"105 Charles St New York NY 10014",
    "addr:housenumber":"105",
    "addr:postcode":"10014",
    "addr:street":"Charles St",
    "iso:country":"US",
    "sg:address":"105 Charles St",
    "sg:city":"New York",
    "sg:classifiers":[
        {
            "category":"Wholesale",
            "subcategory":"Home Furnishings",
            "type":"Manufacturing & Wholesale Goods"
        }
    ],
    "sg:phone":"+1 212 685 2965",
    "sg:postcode":"10014",
    "sg:province":"NY",
    "sg:tags":[
        "distributor",
        "state",
        "for"
    ],
    "wof:name":"Thomaston Corporation",
    "wof:placetype":"venue"
},
  "geometry": {"coordinates":[-74.00540599999999,40.734673],"type":"Point"}
}