{
  "type": "Feature",
  "properties": {
    "addr:full":"939 Grundy Ave Holbrook NY 11741",
    "addr:housenumber":"939",
    "addr:postcode":"11741",
    "addr:street":"Grundy Ave",
    "iso:country":"US",
    "sg:address":"939 Grundy Ave",
    "sg:city":"Holbrook",
    "sg:classifiers":[
        {
            "category":"Health Services",
            "subcategory":"Doctor",
            "type":"Services"
        }
    ],
    "sg:phone":"+1 631 585 4848",
    "sg:postcode":"11741",
    "sg:province":"NY",
    "sg:tags":[
        "dentist"
    ],
    "wof:name":"Warren M Hulkower DDS",
    "wof:placetype":"venue"
},
  "geometry": {"coordinates":[-73.075692,40.787707],"type":"Point"}
}