{
  "type": "Feature",
  "properties": {
    "addr:full":"37 W 20th St New York NY 10011",
    "addr:housenumber":"37",
    "addr:postcode":"10011",
    "addr:street":"W 20Th St",
    "iso:country":"US",
    "sg:address":"37 W 20th St",
    "sg:city":"New York",
    "sg:classifiers":[
        {
            "category":"Retail",
            "subcategory":"Photofinishing",
            "type":"Services"
        }
    ],
    "sg:phone":"+1 212 727 2727",
    "sg:postcode":"10011",
    "sg:province":"NY",
    "sg:tags":[
        "photo",
        "finishing"
    ],
    "wof:name":"Digital Output On Demand Inc",
    "wof:placetype":"venue"
},
  "geometry": {"coordinates":[-73.99323200000001,40.740597],"type":"Point"}
}