{
  "type": "Feature",
  "properties": {
    "iso:country":"US",
    "sg:address":"614 Bergen St",
    "sg:city":"Brooklyn",
    "sg:classifiers":[
        {
            "category":"Wholesale",
            "subcategory":"Machinery & Supplies",
            "type":"Manufacturing & Wholesale Goods"
        }
    ],
    "sg:phone":"+1 718 622 8785",
    "sg:postcode":"11238",
    "sg:province":"NY",
    "sg:tags":[
        "locksmith"
    ],
    "wof:name":"Mayflower Sales Co Inc",
    "wof:placetype":"venue"
},
  "geometry": {"coordinates":[-73.969848,40.679789],"type":"Point"}
}