{
  "type": "Feature",
  "properties": {
    "iso:country":"US",
    "sg:address":"7010 Lakeport Rd",
    "sg:city":"Chittenango",
    "sg:classifiers":[
        {
            "category":"Museum",
            "type":"Entertainment"
        }
    ],
    "sg:phone":"+1 315 687 3801",
    "sg:postcode":"13037",
    "sg:province":"NY",
    "sg:tags":[
        "gallery"
    ],
    "wof:name":"Chittenango Landing Canal Boat",
    "wof:placetype":"venue"
},
  "geometry": {"coordinates":[-75.87153600000001,43.061885],"type":"Point"}
}