{
  "type": "Feature",
  "properties": {
    "addr:full":"5 W 19th Street New York NY 10011",
    "addr:housenumber":"5",
    "addr:postcode":"10011",
    "addr:street":"W 19Th Street",
    "iso:country":"US",
    "sg:address":"5 W 19th Street",
    "sg:city":"New York",
    "sg:classifiers":[
        {
            "category":"Real Estate",
            "subcategory":"Architect",
            "type":"Services"
        }
    ],
    "sg:phone":"+1 646 472 1177",
    "sg:postcode":"10011",
    "sg:province":"NY",
    "wof:name":"Guido Pace Architects",
    "wof:placetype":"venue"
},
  "geometry": {"coordinates":[-73.99148,40.739148],"type":"Point"}
}