{
  "type": "Feature",
  "properties": {
    "iso:country":"US",
    "sg:address":"32 Main St",
    "sg:city":"Scottsville",
    "sg:classifiers":[
        {
            "category":"Health Services",
            "subcategory":"Dentist",
            "type":"Services"
        }
    ],
    "sg:phone":"+1 585 889 9948",
    "sg:postcode":"14546",
    "sg:province":"NY",
    "sg:tags":[
        "dentists-orthodontists"
    ],
    "sg:website":"http://www.dingusortho.com",
    "wof:name":"Dingus & Rivoli Orthodontics",
    "wof:placetype":"venue"
},
  "geometry": {"coordinates":[-77.750347,43.019679],"type":"Point"}
}