{
  "type": "Feature",
  "properties": {
    "iso:country":"US",
    "sg:address":"1289 State Hwy 220",
    "sg:city":"Mc Donough",
    "sg:classifiers":[
        {
            "category":"Government",
            "subcategory":"Office",
            "type":"Public Place"
        }
    ],
    "sg:phone":"+1 607 647 5571",
    "sg:postcode":"13801",
    "sg:province":"NY",
    "sg:tags":[
        "village"
    ],
    "wof:name":"Mc Donough Town Animal Control",
    "wof:placetype":"venue"
},
  "geometry": {"coordinates":[-75.76788999999999,42.498086],"type":"Point"}
}