{
  "type": "Feature",
  "properties": {
    "iso:country":"US",
    "sg:address":"1841 Brentwood Rd",
    "sg:city":"Brentwood",
    "sg:classifiers":[
        {
            "category":"Government",
            "subcategory":"Office",
            "type":"Public Place"
        }
    ],
    "sg:phone":"+1 631 853 7300",
    "sg:postcode":"11717",
    "sg:province":"NY",
    "sg:tags":[
        "county",
        "program",
        "health"
    ],
    "wof:name":"Suffolk County Mental Health",
    "wof:placetype":"venue"
},
  "geometry": {"coordinates":[-73.246098,40.778648],"type":"Point"}
}