{
  "type": "Feature",
  "properties": {
    "addr:full":"90 Northgate Cir Melville NY 11747",
    "addr:housenumber":"90",
    "addr:postcode":"11747",
    "addr:street":"Northgate Cir",
    "iso:country":"US",
    "sg:address":"90 Northgate Cir",
    "sg:city":"Melville",
    "sg:classifiers":[
        {
            "category":"Manufacturing",
            "subcategory":"Textiles",
            "type":"Manufacturing & Wholesale Goods"
        }
    ],
    "sg:phone":"+1 631 756 7274",
    "sg:postcode":"11747",
    "sg:province":"NY",
    "wof:name":"Jatori Textiles Inc",
    "wof:placetype":"venue"
},
  "geometry": {"coordinates":[-73.430832,40.774639],"type":"Point"}
}