{
  "type": "Feature",
  "properties": {
    "iso:country":"US",
    "sg:address":"18 Windmill Ln",
    "sg:city":"Southampton",
    "sg:classifiers":[
        {
            "category":"Building & Trades",
            "subcategory":"Plumbing",
            "type":"Services"
        }
    ],
    "sg:phone":"+1 631 283 3135",
    "sg:postcode":"11968",
    "sg:province":"NY",
    "sg:tags":[
        "conditioning",
        "air",
        "system",
        "contractor"
    ],
    "wof:name":"Best Temp Central",
    "wof:placetype":"venue"
},
  "geometry": {"coordinates":[-72.39285700000001,40.885555],"type":"Point"}
}