{
  "type": "Feature",
  "properties": {
    "addr:full":"3318 Merrick Rd Wantagh NY 11793",
    "addr:housenumber":"3318",
    "addr:postcode":"11793",
    "addr:street":"Merrick Rd",
    "iso:country":"US",
    "sg:address":"3318 Merrick Rd",
    "sg:city":"Wantagh",
    "sg:classifiers":[
        {
            "category":"Health Services",
            "subcategory":"Doctor",
            "type":"Services"
        }
    ],
    "sg:phone":"+1 516 679 5700",
    "sg:postcode":"11793",
    "sg:province":"NY",
    "sg:tags":[
        "dentist"
    ],
    "wof:name":"Michael Germaine DDS",
    "wof:placetype":"venue"
},
  "geometry": {"coordinates":[-73.508287,40.664809],"type":"Point"}
}