{
  "type": "Feature",
  "properties": {
    "addr:full":"2270 Kimball Street Brooklyn NY 11234",
    "addr:housenumber":"2270",
    "addr:postcode":"11234",
    "addr:street":"Kimball Street",
    "iso:country":"US",
    "sg:address":"2270 Kimball Street",
    "sg:city":"Brooklyn",
    "sg:classifiers":[
        {
            "category":"Health Services",
            "subcategory":"Doctor",
            "type":"Services"
        },
        {
            "category":"Community Center",
            "type":"Public Place"
        }
    ],
    "sg:phone":"+1 718 951 6187",
    "sg:postcode":"11234",
    "sg:province":"NY",
    "sg:tags":[
        "medical"
    ],
    "wof:name":"Kings Plaza Medical Center",
    "wof:placetype":"venue"
},
  "geometry": {"coordinates":[-73.92366,40.607226],"type":"Point"}
}