{
  "type": "Feature",
  "properties": {
    "addr:full":"348 Duanesburg Rd Schenectady NY 12306",
    "addr:housenumber":"348",
    "addr:postcode":"12306",
    "addr:street":"Duanesburg Rd",
    "iso:country":"US",
    "sg:address":"348 Duanesburg Rd",
    "sg:city":"Schenectady",
    "sg:classifiers":[
        {
            "category":"Banks & Credit Unions",
            "subcategory":"Investment Brokerage",
            "type":"Services"
        }
    ],
    "sg:phone":"+1 518 355 4840",
    "sg:postcode":"12306",
    "sg:province":"NY",
    "sg:tags":[
        "trust"
    ],
    "wof:name":"Capital District Painters J A & T C",
    "wof:placetype":"venue"
},
  "geometry": {"coordinates":[-73.982603,42.789888],"type":"Point"}
}