{
  "type": "Feature",
  "properties": {
    "addr:full":"12152 Hanover Rd Silver Creek NY 14136",
    "addr:housenumber":"12152",
    "addr:postcode":"14136",
    "addr:street":"Hanover Rd",
    "iso:country":"US",
    "sg:address":"12152 Hanover Rd",
    "sg:city":"Silver Creek",
    "sg:classifiers":[
        {
            "category":"Farming",
            "subcategory":"Vineyard",
            "type":"Manufacturing & Wholesale Goods"
        }
    ],
    "sg:phone":"+1 716 934 3842",
    "sg:postcode":"14136",
    "sg:province":"NY",
    "sg:tags":[
        "grape"
    ],
    "wof:name":"Lester Wayne Heupel",
    "wof:placetype":"venue"
},
  "geometry": {"coordinates":[-79.146933,42.530187],"type":"Point"}
}