{
  "type": "Feature",
  "properties": {
    "iso:country":"US",
    "sg:address":"65 Ferndale Ave",
    "sg:city":"Selden",
    "sg:classifiers":[
        {
            "category":"Restaurant",
            "type":"Food & Drink"
        }
    ],
    "sg:phone":"+1   ",
    "sg:postcode":"11784",
    "sg:province":"NY",
    "sg:tags":[
        "eating"
    ],
    "wof:name":"Everything Yogurt & Salad",
    "wof:placetype":"venue"
},
  "geometry": {"coordinates":[-73.040722,40.858813],"type":"Point"}
}