{
  "type": "Feature",
  "properties": {
    "iso:country":"US",
    "sg:address":"17 Florence St",
    "sg:city":"Centereach",
    "sg:classifiers":[
        {
            "category":"Social Services",
            "type":"Services"
        }
    ],
    "sg:phone":"+1 631 737 1713",
    "sg:postcode":"11720",
    "sg:province":"NY",
    "sg:tags":[
        "human"
    ],
    "wof:name":"Imperial Foods",
    "wof:placetype":"venue"
},
  "geometry": {"coordinates":[-73.100724,40.868148],"type":"Point"}
}