{
  "type": "Feature",
  "properties": {
    "addr:full":"19333 Jamaica Ave Hollis NY 11423",
    "addr:housenumber":"19333",
    "addr:postcode":"11423",
    "addr:street":"Jamaica Ave",
    "iso:country":"US",
    "sg:address":"19333 Jamaica Ave",
    "sg:city":"Hollis",
    "sg:classifiers":[
        {
            "category":"Real Estate",
            "subcategory":"Real Estate Services",
            "type":"Services"
        },
        {
            "category":"Real Estate",
            "subcategory":"Real Estate Agent",
            "type":"Services"
        }
    ],
    "sg:phone":"+1 718 776 4280",
    "sg:postcode":"11423",
    "sg:province":"NY",
    "sg:tags":[
        "management"
    ],
    "sg:website":"http://www.yves.qpg.com/",
    "wof:name":"Yves Express Realty Inc",
    "wof:placetype":"venue"
},
  "geometry": {"coordinates":[-73.75616100000001,40.713509],"type":"Point"}
}