{
  "type": "Feature",
  "properties": {
    "addr:full":"63 W Market St Corning NY 14830",
    "addr:housenumber":"63",
    "addr:postcode":"14830",
    "addr:street":"W Market St",
    "iso:country":"US",
    "sg:address":"63 W Market St",
    "sg:city":"Corning",
    "sg:classifiers":[
        {
            "category":"Restaurant",
            "type":"Food & Drink"
        }
    ],
    "sg:phone":"+1   ",
    "sg:postcode":"14830",
    "sg:province":"NY",
    "sg:tags":[
        "personal",
        "drinking",
        "eating"
    ],
    "wof:name":"Pelhams Upstate Tuna",
    "wof:placetype":"venue"
},
  "geometry": {"coordinates":[-77.055154,42.143515],"type":"Point"}
}