{
  "type": "Feature",
  "properties": {
    "addr:full":"4956 Western Tpke Duanesburg NY 12056",
    "addr:housenumber":"4956",
    "addr:postcode":"12056",
    "addr:street":"Western Tpke",
    "iso:country":"US",
    "sg:address":"4956 Western Tpke",
    "sg:city":"Duanesburg",
    "sg:classifiers":[
        {
            "category":"Personal",
            "subcategory":"Tanning Parlor",
            "type":"Services"
        }
    ],
    "sg:phone":"+1 518 895 8875",
    "sg:postcode":"12056",
    "sg:province":"NY",
    "sg:tags":[
        "salon"
    ],
    "wof:name":"Wanna Be Tan",
    "wof:placetype":"venue"
},
  "geometry": {"coordinates":[-74.130369,42.761226],"type":"Point"}
}