{
  "type": "Feature",
  "properties": {
    "iso:country":"US",
    "sg:address":"511 Amsterdam Ave",
    "sg:city":"New York",
    "sg:classifiers":[
        {
            "category":"Bars & Pubs",
            "type":"Food & Drink"
        }
    ],
    "sg:phone":"+1 212 799 4643",
    "sg:postcode":"10024",
    "sg:province":"NY",
    "sg:tags":[
        "drinking"
    ],
    "wof:name":"Moonlighting A Lounge",
    "wof:placetype":"venue"
},
  "geometry": {"coordinates":[-73.97564199999999,40.786614],"type":"Point"}
}