{
  "type": "Feature",
  "properties": {
    "iso:country":"US",
    "sg:address":"203 60th Street",
    "sg:city":"Brooklyn",
    "sg:classifiers":[
        {
            "category":"Retail",
            "subcategory":"Auto Repair",
            "type":"Services"
        }
    ],
    "sg:phone":"+1 718 492 7301",
    "sg:postcode":"11220",
    "sg:province":"NY",
    "wof:name":"Drivng More Auto Repair",
    "wof:placetype":"venue"
},
  "geometry": {"coordinates":[-74.022386,40.643375],"type":"Point"}
}