{
  "type": "Feature",
  "properties": {
    "iso:country":"US",
    "sg:address":"2115 Telephone Rd",
    "sg:city":"Le Roy",
    "sg:phone":"+1 585 768 6524",
    "sg:postcode":"14482",
    "sg:province":"NY",
    "sg:tags":[
        "wheat",
        "field",
        "farm",
        "corn",
        "crop",
        "fa"
    ],
    "wof:name":"Kenneth Rogers",
    "wof:placetype":"venue"
},
  "geometry": {"coordinates":[-77.926492,42.912728],"type":"Point"}
}