{
  "type": "Feature",
  "properties": {
    "addr:full":"259 Jefferson Ave Rochester NY 14611",
    "addr:housenumber":"259",
    "addr:postcode":"14611",
    "addr:street":"Jefferson Ave",
    "iso:country":"US",
    "sg:address":"259 Jefferson Ave",
    "sg:city":"Rochester",
    "sg:classifiers":[
        {
            "category":"Food & Beverages",
            "subcategory":"Groceries & Convenience Stores",
            "type":"Retail Goods"
        }
    ],
    "sg:phone":"+1 585 235 3350",
    "sg:postcode":"14611",
    "sg:province":"NY",
    "sg:tags":[
        "grocer"
    ],
    "wof:name":"U S Food Market",
    "wof:placetype":"venue"
},
  "geometry": {"coordinates":[-77.628997,43.150811],"type":"Point"}
}