{
  "type": "Feature",
  "properties": {
    "iso:country":"US",
    "sg:address":"10 Center Rd",
    "sg:city":"Buffalo",
    "sg:classifiers":[
        {
            "category":"Professional",
            "subcategory":"Computer Services",
            "type":"Services"
        }
    ],
    "sg:phone":"+1 716 822 2212",
    "sg:postcode":"14224",
    "sg:province":"NY",
    "sg:tags":[
        "personal",
        "design",
        "system"
    ],
    "wof:name":"CPI Digital Services",
    "wof:placetype":"venue"
},
  "geometry": {"coordinates":[-78.782015,42.839888],"type":"Point"}
}