{
  "type": "Feature",
  "properties": {
    "addr:full":"508 Toleman Rd Rock Tavern NY 12575",
    "addr:housenumber":"508",
    "addr:postcode":"12575",
    "addr:street":"Toleman Rd",
    "iso:country":"US",
    "sg:address":"508 Toleman Rd",
    "sg:city":"Rock Tavern",
    "sg:classifiers":[
        {
            "category":"Professional",
            "subcategory":"Business Services",
            "type":"Services"
        }
    ],
    "sg:phone":"+1 888 294 1077",
    "sg:postcode":"12575",
    "sg:province":"NY",
    "wof:name":"ABC Fixed Asset Inventory MGT",
    "wof:placetype":"venue"
},
  "geometry": {"coordinates":[-74.13779599999999,41.473296],"type":"Point"}
}