{
  "type": "Feature",
  "properties": {
    "iso:country":"US",
    "sg:address":"790 Jefferson Rd",
    "sg:city":"Rochester",
    "sg:classifiers":[
        {
            "category":"Retail",
            "subcategory":"Veterinary Services",
            "type":"Services"
        }
    ],
    "sg:phone":"+1 585 272 8046",
    "sg:postcode":"14623",
    "sg:province":"NY",
    "sg:tags":[
        "clinic",
        "hospital"
    ],
    "sg:website":"http://www.banfield.com",
    "wof:name":"Medical Management International, Inc.",
    "wof:placetype":"venue"
},
  "geometry": {"coordinates":[-77.61875000000001,43.087147],"type":"Point"}
}