{
  "type": "Feature",
  "properties": {
    "addr:full":"29 W 36 St New York NY 10018",
    "addr:housenumber":"29",
    "addr:postcode":"10018",
    "addr:street":"W 36 St",
    "iso:country":"US",
    "sg:address":"29 W 36 St",
    "sg:city":"New York",
    "sg:classifiers":[
        {
            "category":"Wholesale",
            "subcategory":"Jewelry",
            "type":"Manufacturing & Wholesale Goods"
        }
    ],
    "sg:phone":"+1 212 564 8250",
    "sg:postcode":"10018",
    "sg:province":"NY",
    "sg:tags":[
        "costume"
    ],
    "wof:name":"Vetta International Inc",
    "wof:placetype":"venue"
},
  "geometry": {"coordinates":[-73.986114,40.75076],"type":"Point"}
}