{
  "type": "Feature",
  "properties": {
    "addr:full":"1218 Nostrand Ave Brooklyn NY 11225",
    "addr:housenumber":"1218",
    "addr:postcode":"11225",
    "addr:street":"Nostrand Ave",
    "iso:country":"US",
    "sg:address":"1218 Nostrand Ave",
    "sg:city":"Brooklyn",
    "sg:classifiers":[
        {
            "category":"Personal",
            "subcategory":"Beauty Salon",
            "type":"Services"
        }
    ],
    "sg:phone":"+1 718 804 7125",
    "sg:postcode":"11225",
    "sg:province":"NY",
    "sg:tags":[
        "nail",
        "manicuring"
    ],
    "wof:name":"Nostrand Nail Salon",
    "wof:placetype":"venue"
},
  "geometry": {"coordinates":[-73.950401,40.657501],"type":"Point"}
}