{
  "type": "Feature",
  "properties": {
    "iso:country":"US",
    "sg:address":"1225 Howells Rd",
    "sg:city":"Bay Shore",
    "sg:classifiers":[
        {
            "category":"Professional",
            "subcategory":"Computer Services",
            "type":"Services"
        }
    ],
    "sg:phone":"+1 631 254 4680",
    "sg:postcode":"11706",
    "sg:province":"NY",
    "wof:name":"New Wave Computers",
    "wof:placetype":"venue"
},
  "geometry": {"coordinates":[-73.29325300000001,40.757439],"type":"Point"}
}