{
  "type": "Feature",
  "properties": {
    "iso:country":"US",
    "sg:address":"62 Wintergreen Ave",
    "sg:city":"Newburgh",
    "sg:classifiers":[
        {
            "category":"Utilities",
            "type":"Services"
        }
    ],
    "sg:phone":"+1 845 562 3645",
    "sg:postcode":"12550",
    "sg:province":"NY",
    "sg:tags":[
        "sanitary"
    ],
    "wof:name":"B & D Ldscpg & Snow Plowing",
    "wof:placetype":"venue"
},
  "geometry": {"coordinates":[-74.055436,41.517792],"type":"Point"}
}