{
  "type": "Feature",
  "properties": {
    "iso:country":"US",
    "sg:address":"8 Cartwheel Dr",
    "sg:city":"Schenectady",
    "sg:classifiers":[
        {
            "category":"Building & Trades",
            "subcategory":"Landscaping Services",
            "type":"Services"
        }
    ],
    "sg:phone":"+1 518 857 9072",
    "sg:postcode":"12302",
    "sg:province":"NY",
    "sg:tags":[
        "landscape"
    ],
    "wof:name":"Djw All Season Landscaping",
    "wof:placetype":"venue"
},
  "geometry": {"coordinates":[-73.963098,42.841086],"type":"Point"}
}