{
  "type": "Feature",
  "properties": {
    "iso:country":"US",
    "sg:address":"49 Forest Ln",
    "sg:city":"Staten Island",
    "sg:classifiers":[
        {
            "category":"Travel",
            "subcategory":"Travel Agent",
            "type":"Entertainment"
        }
    ],
    "sg:phone":"+1 718 605 1600",
    "sg:postcode":"10307",
    "sg:province":"NY",
    "sg:tags":[
        "agency",
        "bureau"
    ],
    "wof:name":"Sprague Building Corp",
    "wof:placetype":"venue"
},
  "geometry": {"coordinates":[-74.238961,40.503397],"type":"Point"}
}