{
  "type": "Feature",
  "properties": {
    "addr:full":"935 Merrick Rd Baldwin NY 11510",
    "addr:housenumber":"935",
    "addr:postcode":"11510",
    "addr:street":"Merrick Rd",
    "iso:country":"US",
    "sg:address":"935 Merrick Rd",
    "sg:city":"Baldwin",
    "sg:classifiers":[
        {
            "category":"Manufacturing",
            "subcategory":"Printing",
            "type":"Manufacturing & Wholesale Goods"
        }
    ],
    "sg:phone":"+1   ",
    "sg:postcode":"11510",
    "sg:province":"NY",
    "sg:tags":[
        "commercial"
    ],
    "wof:name":"Mr Discount Signs Plus Inc",
    "wof:placetype":"venue"
},
  "geometry": {"coordinates":[-73.60668099999999,40.651342],"type":"Point"}
}