{
  "type": "Feature",
  "properties": {
    "addr:full":"2411 150th Street Whitestone NY 11357",
    "addr:housenumber":"2411",
    "addr:postcode":"11357",
    "addr:street":"150Th Street",
    "iso:country":"US",
    "sg:address":"2411 150th Street",
    "sg:city":"Whitestone",
    "sg:classifiers":[
        {
            "category":"Food & Beverages",
            "subcategory":"Groceries & Convenience Stores",
            "type":"Retail Goods"
        }
    ],
    "sg:phone":"+1 718 939 7575",
    "sg:postcode":"11357",
    "sg:province":"NY",
    "wof:name":"150 Street Produce Corporation",
    "wof:placetype":"venue"
},
  "geometry": {"coordinates":[-73.814691,40.776643],"type":"Point"}
}