{
  "type": "Feature",
  "properties": {
    "addr:full":"2317 Main St Buffalo NY 14214",
    "addr:housenumber":"2317",
    "addr:postcode":"14214",
    "addr:street":"Main St",
    "iso:country":"US",
    "sg:address":"2317 Main St",
    "sg:city":"Buffalo",
    "sg:classifiers":[
        {
            "category":"Banks & Credit Unions",
            "subcategory":"Bank",
            "type":"Services"
        }
    ],
    "sg:phone":"+1 716 834 8914",
    "sg:postcode":"14214",
    "sg:province":"NY",
    "sg:tags":[
        "financing"
    ],
    "wof:name":"American Properties",
    "wof:placetype":"venue"
},
  "geometry": {"coordinates":[-78.846501,42.932247],"type":"Point"}
}