{
  "type": "Feature",
  "properties": {
    "addr:full":"5871 S Transit Rd Lockport NY 14094",
    "addr:housenumber":"5871",
    "addr:postcode":"14094",
    "addr:street":"S Transit Rd",
    "iso:country":"US",
    "sg:address":"5871 S Transit Rd",
    "sg:city":"Lockport",
    "sg:classifiers":[
        {
            "category":"Home & Garden",
            "subcategory":"Building Materials",
            "type":"Retail Goods"
        }
    ],
    "sg:phone":"+1 716 434 6313",
    "sg:postcode":"14094",
    "sg:province":"NY",
    "sg:tags":[
        "improvement",
        "floor",
        "covering"
    ],
    "sg:website":"http://buffalo.citysearch.com/profile/external/7725306/lockport_ny/sherwin_williams.html?publisher=yellowpages&reference_id=1&placement=ypwebsitemip",
    "wof:name":"Sherwin-Williams",
    "wof:placetype":"venue"
},
  "geometry": {"coordinates":[-78.69688600000001,43.139513],"type":"Point"}
}