{
  "type": "Feature",
  "properties": {
    "iso:country":"US",
    "sg:address":"105 Court Street Suite 402",
    "sg:city":"Brooklyn",
    "sg:classifiers":[
        {
            "category":"Professional",
            "subcategory":"Lawyer & Legal Services",
            "type":"Services"
        }
    ],
    "sg:phone":"+1 718 875 7584",
    "sg:postcode":"11201",
    "sg:province":"NY",
    "sg:tags":[
        "divorce",
        "law",
        "family"
    ],
    "sg:website":"www.newyorkfamilylawfirm.com",
    "wof:name":"Law Office Of Brian D. Perskin",
    "wof:placetype":"venue"
},
  "geometry": {"coordinates":[-73.99186,40.690704],"type":"Point"}
}