{
  "type": "Feature",
  "properties": {
    "addr:full":"537 Stewart Ave Bethpage NY 11714",
    "addr:housenumber":"537",
    "addr:postcode":"11714",
    "addr:street":"Stewart Ave",
    "iso:country":"US",
    "sg:address":"537 Stewart Ave",
    "sg:city":"Bethpage",
    "sg:classifiers":[
        {
            "category":"Personal",
            "subcategory":"Beauty Salon",
            "type":"Services"
        }
    ],
    "sg:phone":"+1 516 937 3773",
    "sg:postcode":"11714",
    "sg:province":"NY",
    "wof:name":"Special Effect",
    "wof:placetype":"venue"
},
  "geometry": {"coordinates":[-73.481933,40.743286],"type":"Point"}
}