{
  "type": "Feature",
  "properties": {
    "iso:country":"US",
    "sg:address":"5 Gulf Rd",
    "sg:city":"Wyoming",
    "sg:classifiers":[
        {
            "category":"Shopping",
            "subcategory":"Gifts & Souvenirs",
            "type":"Retail Goods"
        }
    ],
    "sg:phone":"+1 585 495 6650",
    "sg:postcode":"14591",
    "sg:province":"NY",
    "sg:tags":[
        "shop"
    ],
    "wof:name":"Gourmet Gagets & Gifts LLC",
    "wof:placetype":"venue"
},
  "geometry": {"coordinates":[-78.089338,42.828845],"type":"Point"}
}