{
  "type": "Feature",
  "properties": {
    "addr:full":"3187 Steinway St Ste 5 Astoria NY 11103",
    "addr:housenumber":"3187",
    "addr:postcode":"11103",
    "addr:street":"Steinway St Ste 5",
    "iso:country":"US",
    "sg:address":"3187 Steinway St Ste 5",
    "sg:city":"Astoria",
    "sg:classifiers":[
        {
            "category":"Real Estate",
            "subcategory":"Real Estate Services",
            "type":"Services"
        }
    ],
    "sg:phone":"+1 718 777 8212",
    "sg:postcode":"11103",
    "sg:province":"NY",
    "sg:tags":[
        "rental"
    ],
    "sg:website":"http://www.arisinvestments.com",
    "wof:name":"Aris Investments",
    "wof:placetype":"venue"
},
  "geometry": {"coordinates":[-73.918722,40.759315],"type":"Point"}
}