{
  "type": "Feature",
  "properties": {
    "iso:country":"US",
    "sg:address":"26 Ford Ave",
    "sg:city":"Oneonta",
    "sg:classifiers":[
        {
            "category":"Organizations",
            "subcategory":"Community Association",
            "type":"Services"
        }
    ],
    "sg:phone":"+1 607 432 0011",
    "sg:postcode":"13820",
    "sg:province":"NY",
    "wof:name":"Oneonta Family YMCA",
    "wof:placetype":"venue"
},
  "geometry": {"coordinates":[-75.061514,42.455748],"type":"Point"}
}