{
  "type": "Feature",
  "properties": {
    "iso:country":"US",
    "sg:address":"295 Madison Ave Fl 41",
    "sg:city":"New York",
    "sg:classifiers":[
        {
            "category":"Professional",
            "subcategory":"Lawyer & Legal Services",
            "type":"Services"
        }
    ],
    "sg:phone":"+1 212 889 0320",
    "sg:postcode":"10017",
    "sg:province":"NY",
    "wof:name":"Rawkow Cohen & Isaac",
    "wof:placetype":"venue"
},
  "geometry": {"coordinates":[-73.97959899999999,40.752499],"type":"Point"}
}