{
  "type": "Feature",
  "properties": {
    "addr:full":"230 Highland Ave Middletown NY 10940",
    "addr:housenumber":"230",
    "addr:postcode":"10940",
    "addr:street":"Highland Ave",
    "iso:country":"US",
    "sg:address":"230 Highland Ave",
    "sg:city":"Middletown",
    "sg:classifiers":[
        {
            "category":"Building & Trades",
            "subcategory":"Landscaping Services",
            "type":"Services"
        }
    ],
    "sg:phone":"+1 845 346 0261",
    "sg:postcode":"10940",
    "sg:province":"NY",
    "sg:tags":[
        "concrete",
        "contractor"
    ],
    "wof:name":"Simon Landscaping",
    "wof:placetype":"venue"
},
  "geometry": {"coordinates":[-74.41464000000001,41.460137],"type":"Point"}
}