{
  "type": "Feature",
  "properties": {
    "iso:country":"US",
    "sg:address":"126 Quaker Rd",
    "sg:city":"Pomona",
    "sg:classifiers":[
        {
            "category":"Restaurant",
            "type":"Food & Drink"
        }
    ],
    "sg:phone":"+1   ",
    "sg:postcode":"10970",
    "sg:province":"NY",
    "sg:tags":[
        "eating"
    ],
    "wof:name":"Bill Munch Refrigeration",
    "wof:placetype":"venue"
},
  "geometry": {"coordinates":[-74.04139000000001,41.191597],"type":"Point"}
}