{
  "type": "Feature",
  "properties": {
    "iso:country":"US",
    "sg:address":"10 Summit Ave",
    "sg:city":"Williston Park",
    "sg:classifiers":[
        {
            "category":"Health Services",
            "subcategory":"Doctor",
            "type":"Services"
        }
    ],
    "sg:phone":"+1   ",
    "sg:postcode":"11596",
    "sg:province":"NY",
    "sg:tags":[
        "clinic",
        "dentist"
    ],
    "wof:name":"Joseph Schwadron",
    "wof:placetype":"venue"
},
  "geometry": {"coordinates":[-73.63337900000001,40.762522],"type":"Point"}
}