{
  "type": "Feature",
  "properties": {
    "iso:country":"US",
    "sg:address":"173 Grand St",
    "sg:city":"White Plains",
    "sg:classifiers":[
        {
            "category":"Shopping",
            "type":"Retail Goods"
        },
        {
            "category":"Wholesale",
            "subcategory":"Durable Goods & Equipment",
            "type":"Manufacturing & Wholesale Goods"
        }
    ],
    "sg:phone":"+1 914 761 3358",
    "sg:postcode":"10601",
    "sg:province":"NY",
    "sg:tags":[
        "trophy",
        "medal",
        "award"
    ],
    "wof:name":"American Precision Engraving",
    "wof:placetype":"venue"
},
  "geometry": {"coordinates":[-73.76777199999999,41.02936],"type":"Point"}
}