{
  "type": "Feature",
  "properties": {
    "addr:full":"1983 Seminole Ave Bronx NY 10461",
    "addr:housenumber":"1983",
    "addr:postcode":"10461",
    "addr:street":"Seminole Ave",
    "iso:country":"US",
    "sg:address":"1983 Seminole Ave",
    "sg:city":"Bronx",
    "sg:classifiers":[
        {
            "category":"Retail",
            "subcategory":"Laundry & Dry Cleaning",
            "type":"Services"
        }
    ],
    "sg:phone":"+1 718 863 6734",
    "sg:postcode":"10461",
    "sg:province":"NY",
    "sg:tags":[
        "cleaner",
        "rug",
        "carpet"
    ],
    "wof:name":"Magic Carpet Mobile Cleaning Service",
    "wof:placetype":"venue"
},
  "geometry": {"coordinates":[-73.850098,40.856201],"type":"Point"}
}