{
  "type": "Feature",
  "properties": {
    "iso:country":"US",
    "sg:address":"1000 Saddle Rock Rd",
    "sg:city":"Holbrook",
    "sg:classifiers":[
        {
            "category":"Real Estate",
            "subcategory":"Real Estate Operator",
            "type":"Services"
        }
    ],
    "sg:phone":"+1 631 563 0174",
    "sg:postcode":"11741",
    "sg:province":"NY",
    "sg:tags":[
        "building",
        "apartment"
    ],
    "wof:name":"Saddle Rock Apartments",
    "wof:placetype":"venue"
},
  "geometry": {"coordinates":[-73.08116099999999,40.765711],"type":"Point"}
}