{
  "type": "Feature",
  "properties": {
    "addr:full":"30 E 40th St Rm 207 New York NY 10016",
    "addr:housenumber":"30;207",
    "addr:postcode":"10016",
    "addr:street":"E 40Th St Rm",
    "iso:country":"US",
    "sg:address":"30 E 40th St Rm 207",
    "sg:city":"New York",
    "sg:classifiers":[
        {
            "category":"Health Services",
            "subcategory":"Dentist",
            "type":"Services"
        }
    ],
    "sg:phone":"+1 212 696 4979",
    "sg:postcode":"10016",
    "sg:province":"NY",
    "wof:name":"Concerned Dental Care PC",
    "wof:placetype":"venue"
},
  "geometry": {"coordinates":[-73.979589,40.751215],"type":"Point"}
}