{
  "type": "Feature",
  "properties": {
    "addr:full":"740 Hempstead Tpke Franklin Square NY 11010",
    "addr:housenumber":"740",
    "addr:postcode":"11010",
    "addr:street":"Hempstead Tpke",
    "iso:country":"US",
    "sg:address":"740 Hempstead Tpke",
    "sg:city":"Franklin Square",
    "sg:classifiers":[
        {
            "category":"Retail",
            "subcategory":"Auto Repair",
            "type":"Services"
        }
    ],
    "sg:phone":"+1 516 292 9500",
    "sg:postcode":"11010",
    "sg:province":"NY",
    "wof:name":"D & D Complete Automotive Inc",
    "wof:placetype":"venue"
},
  "geometry": {"coordinates":[-73.664497,40.706799],"type":"Point"}
}