{
  "type": "Feature",
  "properties": {
    "addr:full":"885 E 149th St Bronx NY 10455",
    "addr:housenumber":"885",
    "addr:postcode":"10455",
    "addr:street":"E 149Th St",
    "iso:country":"US",
    "sg:address":"885 E 149th St",
    "sg:city":"Bronx",
    "sg:classifiers":[
        {
            "category":"Autos & Motor Vehicles",
            "subcategory":"Automobile Sales",
            "type":"Retail Goods"
        }
    ],
    "sg:phone":"+1 718 239 9000",
    "sg:postcode":"10455",
    "sg:province":"NY",
    "sg:tags":[
        "repair",
        "used",
        "automotive",
        "part",
        "truck",
        "car",
        "new"
    ],
    "wof:name":"Milea Pontiac Buick-GMC",
    "wof:placetype":"venue"
},
  "geometry": {"coordinates":[-73.903397,40.811501],"type":"Point"}
}