{
  "type": "Feature",
  "properties": {
    "iso:country":"US",
    "sg:address":"9 Amsterdam Ave",
    "sg:city":"Medford",
    "sg:classifiers":[
        {
            "category":"Building & Trades",
            "subcategory":"Landscaping Services",
            "type":"Services"
        }
    ],
    "sg:phone":"+1 631 287 3400",
    "sg:postcode":"11763",
    "sg:province":"NY",
    "sg:tags":[
        "designer",
        "landscape"
    ],
    "wof:name":"Landscaping By Dennis",
    "wof:placetype":"venue"
},
  "geometry": {"coordinates":[-72.96716499999999,40.817828],"type":"Point"}
}