{
  "type": "Feature",
  "properties": {
    "addr:full":"120 Main St Gardiner NY 12525",
    "addr:housenumber":"120",
    "addr:postcode":"12525",
    "addr:street":"Main St",
    "iso:country":"US",
    "sg:address":"120 Main St",
    "sg:city":"Gardiner",
    "sg:classifiers":[
        {
            "category":"Building & Trades",
            "subcategory":"Construction",
            "type":"Services"
        }
    ],
    "sg:phone":"+1 845 255 6224",
    "sg:postcode":"12525",
    "sg:province":"NY",
    "sg:tags":[
        "contractor"
    ],
    "wof:name":"Custom Art Tile",
    "wof:placetype":"venue"
},
  "geometry": {"coordinates":[-74.151656,41.680105],"type":"Point"}
}