{
  "type": "Feature",
  "properties": {
    "addr:full":"29 W 34th St Frnt 1 New York NY 10001",
    "addr:housenumber":"29;1",
    "addr:postcode":"10001",
    "addr:street":"W 34Th St Frnt",
    "iso:country":"US",
    "sg:address":"29 W 34th St Frnt 1",
    "sg:city":"New York",
    "sg:classifiers":[
        {
            "category":"Shopping",
            "subcategory":"Shoes",
            "type":"Retail Goods"
        }
    ],
    "sg:phone":"+1 212 564 9702",
    "sg:postcode":"10001",
    "sg:province":"NY",
    "sg:tags":[
        "store"
    ],
    "wof:name":"Geox",
    "wof:placetype":"venue"
},
  "geometry": {"coordinates":[-73.98653400000001,40.749439],"type":"Point"}
}