{
  "type": "Feature",
  "properties": {
    "addr:full":"6 West Ave Owego NY 13827",
    "addr:housenumber":"6",
    "addr:postcode":"13827",
    "addr:street":"West Ave",
    "iso:country":"US",
    "sg:address":"6 West Ave",
    "sg:city":"Owego",
    "sg:classifiers":[
        {
            "category":"Shopping",
            "subcategory":"Crafts & Fabrics",
            "type":"Retail Goods"
        }
    ],
    "sg:phone":"+1 607 687 6811",
    "sg:postcode":"13827",
    "sg:province":"NY",
    "sg:tags":[
        "shop"
    ],
    "wof:name":"Churn Dash",
    "wof:placetype":"venue"
},
  "geometry": {"coordinates":[-76.266925,42.108536],"type":"Point"}
}