{
  "type": "Feature",
  "properties": {
    "addr:full":"921 Livonia Ave Brooklyn NY 11207",
    "addr:housenumber":"921",
    "addr:postcode":"11207",
    "addr:street":"Livonia Ave",
    "iso:country":"US",
    "sg:address":"921 Livonia Ave",
    "sg:city":"Brooklyn",
    "sg:classifiers":[
        {
            "category":"Retail",
            "subcategory":"Laundry & Dry Cleaning",
            "type":"Services"
        }
    ],
    "sg:phone":"+1 718 495 2275",
    "sg:postcode":"11207",
    "sg:province":"NY",
    "sg:tags":[
        "drycleaning",
        "plant"
    ],
    "wof:name":"Ace Cleaners",
    "wof:placetype":"venue"
},
  "geometry": {"coordinates":[-73.882896,40.6665],"type":"Point"}
}