{
  "type": "Feature",
  "properties": {
    "addr:full":"3877 Canal Rd Solsville NY 13402",
    "addr:housenumber":"3877",
    "addr:postcode":"13402",
    "addr:street":"Canal Rd",
    "iso:country":"US",
    "sg:address":"3877 Canal Rd",
    "sg:city":"Solsville",
    "sg:classifiers":[
        {
            "category":"Restaurant",
            "type":"Food & Drink"
        }
    ],
    "sg:phone":"+1   ",
    "sg:postcode":"13402",
    "sg:province":"NY",
    "sg:tags":[
        "drinking",
        "eating"
    ],
    "wof:name":"Hotel Solsville Inc",
    "wof:placetype":"venue"
},
  "geometry": {"coordinates":[-75.519525,42.910448],"type":"Point"}
}