{
  "type": "Feature",
  "properties": {
    "iso:country":"US",
    "sg:address":"2390 Middle Country Rd",
    "sg:city":"Centereach",
    "sg:classifiers":[
        {
            "category":"Food & Beverages",
            "subcategory":"Liquor & Beverages",
            "type":"Retail Goods"
        }
    ],
    "sg:phone":"+1 631 285 6921",
    "sg:postcode":"11720",
    "sg:province":"NY",
    "wof:name":"Aiello Brothers Fine Wine Inc",
    "wof:placetype":"venue"
},
  "geometry": {"coordinates":[-73.093964,40.858015],"type":"Point"}
}