{
  "type": "Feature",
  "properties": {
    "addr:full":"1785 Hertel Ave Buffalo NY 14216",
    "addr:housenumber":"1785",
    "addr:postcode":"14216",
    "addr:street":"Hertel Ave",
    "iso:country":"US",
    "sg:address":"1785 Hertel Ave",
    "sg:city":"Buffalo",
    "sg:classifiers":[
        {
            "category":"Shopping",
            "subcategory":"Clothing, Apparel, & Fashions",
            "type":"Retail Goods"
        }
    ],
    "sg:phone":"+1 716 838 1400",
    "sg:postcode":"14216",
    "sg:province":"NY",
    "sg:tags":[
        "shop",
        "specialty"
    ],
    "wof:name":"Ilya's Bellydance Studio",
    "wof:placetype":"venue"
},
  "geometry": {"coordinates":[-78.843197,42.947511],"type":"Point"}
}