{
  "type": "Feature",
  "properties": {
    "iso:country":"US",
    "sg:address":"1 Kennedy Plz",
    "sg:city":"Utica",
    "sg:classifiers":[
        {
            "category":"Government",
            "subcategory":"Office",
            "type":"Public Place"
        }
    ],
    "sg:phone":"+1 315 792 0121",
    "sg:postcode":"13502",
    "sg:province":"NY",
    "sg:tags":[
        "village"
    ],
    "wof:name":"Utica Purchasing Dept",
    "wof:placetype":"venue"
},
  "geometry": {"coordinates":[-75.237049,43.101999],"type":"Point"}
}