{
  "type": "Feature",
  "properties": {
    "addr:full":"3546 Long Beach Rd Oceanside NY 11572",
    "addr:housenumber":"3546",
    "addr:postcode":"11572",
    "addr:street":"Long Beach Rd",
    "iso:country":"US",
    "sg:address":"3546 Long Beach Rd",
    "sg:city":"Oceanside",
    "sg:classifiers":[
        {
            "category":"Shopping",
            "type":"Retail Goods"
        }
    ],
    "sg:phone":"+1 516 536 3474",
    "sg:postcode":"11572",
    "sg:province":"NY",
    "sg:tags":[
        "merchandise"
    ],
    "wof:name":"Aqua Palais Pet Center Inc",
    "wof:placetype":"venue"
},
  "geometry": {"coordinates":[-73.639582,40.624693],"type":"Point"}
}