{
  "type": "Feature",
  "properties": {
    "iso:country":"US",
    "sg:address":"3202 Emmons Ave",
    "sg:city":"Brooklyn",
    "sg:classifiers":[
        {
            "category":"Restaurant",
            "type":"Food & Drink"
        },
        {
            "category":"Bars & Pubs",
            "subcategory":"Nightclub",
            "type":"Food & Drink"
        }
    ],
    "sg:phone":"+1 718 743 8100",
    "sg:postcode":"11235",
    "sg:province":"NY",
    "sg:tags":[
        "fusion",
        "asian",
        "nightlife"
    ],
    "sg:website":"www.opmnyc.com",
    "wof:name":"OPM",
    "wof:placetype":"venue"
},
  "geometry": {"coordinates":[-73.932733,40.583724],"type":"Point"}
}