{
  "type": "Feature",
  "properties": {
    "addr:full":"4097 Yautzy Rd Canandaigua NY 14424",
    "addr:housenumber":"4097",
    "addr:postcode":"14424",
    "addr:street":"Yautzy Rd",
    "iso:country":"US",
    "sg:address":"4097 Yautzy Rd",
    "sg:city":"Canandaigua",
    "sg:phone":"+1 585 526 6701",
    "sg:postcode":"14424",
    "sg:province":"NY",
    "sg:tags":[
        "farm",
        "field",
        "corn",
        "crop"
    ],
    "wof:name":"Jacob Horst",
    "wof:placetype":"venue"
},
  "geometry": {"coordinates":[-77.184855,42.83497],"type":"Point"}
}