{
  "type": "Feature",
  "properties": {
    "iso:country":"US",
    "sg:address":"448 Lafayette Ave",
    "sg:city":"Brooklyn",
    "sg:classifiers":[
        {
            "category":"Restaurant",
            "type":"Food & Drink"
        }
    ],
    "sg:phone":"+1 718 230 0098",
    "sg:postcode":"11238",
    "sg:province":"NY",
    "wof:name":"Roosters Chicken Rotisserie",
    "wof:placetype":"venue"
},
  "geometry": {"coordinates":[-73.957294,40.68919],"type":"Point"}
}