{
  "type": "Feature",
  "properties": {
    "addr:full":"116 W 176th St Bronx NY 10453",
    "addr:housenumber":"116",
    "addr:postcode":"10453",
    "addr:street":"W 176Th St",
    "iso:country":"US",
    "sg:address":"116 W 176th St",
    "sg:city":"Bronx",
    "sg:classifiers":[
        {
            "category":"Real Estate",
            "subcategory":"Real Estate Agent",
            "type":"Services"
        }
    ],
    "sg:phone":"+1 718 583 3306",
    "sg:postcode":"10453",
    "sg:province":"NY",
    "wof:name":"Tryax Realty Inc",
    "wof:placetype":"venue"
},
  "geometry": {"coordinates":[-73.917675,40.849144],"type":"Point"}
}