{
  "type": "Feature",
  "properties": {
    "addr:full":"2505 37th Avenue Long Island City NY 11101",
    "addr:housenumber":"2505",
    "addr:postcode":"11101",
    "addr:street":"37Th Avenue",
    "iso:country":"US",
    "sg:address":"2505 37th Avenue",
    "sg:city":"Long Island City",
    "sg:classifiers":[
        {
            "category":"Education",
            "subcategory":"School",
            "type":"Public Place"
        }
    ],
    "sg:phone":"+1 718 786 4914",
    "sg:postcode":"11101",
    "sg:province":"NY",
    "sg:tags":[
        "high",
        "middle",
        "elementary"
    ],
    "wof:name":"N Y City Bd of Education",
    "wof:placetype":"venue"
},
  "geometry": {"coordinates":[-73.934579,40.756776],"type":"Point"}
}