{
  "type": "Feature",
  "properties": {
    "addr:full":"2341 Broadway New York NY 10024",
    "addr:housenumber":"2341",
    "addr:postcode":"10024",
    "addr:street":"Broadway",
    "iso:country":"US",
    "sg:address":"2341 Broadway",
    "sg:city":"New York",
    "sg:classifiers":[
        {
            "category":"Personal",
            "subcategory":"Beauty Salon",
            "type":"Services"
        }
    ],
    "sg:phone":"+1 212 595 1177",
    "sg:postcode":"10024",
    "sg:province":"NY",
    "sg:tags":[
        "hair"
    ],
    "wof:name":"Jeffrey Stein Salon",
    "wof:placetype":"venue"
},
  "geometry": {"coordinates":[-73.976997,40.788101],"type":"Point"}
}