{
  "type": "Feature",
  "properties": {
    "addr:full":"96 Main St New Canaan NY 06840",
    "addr:housenumber":"96",
    "addr:postcode":"06840",
    "addr:street":"Main St",
    "iso:country":"US",
    "sg:address":"96 Main St",
    "sg:city":"New Canaan",
    "sg:classifiers":[
        {
            "category":"Home & Garden",
            "subcategory":"Home Furnishings",
            "type":"Retail Goods"
        }
    ],
    "sg:phone":"+1 203 972 2665",
    "sg:postcode":"06840",
    "sg:province":"NY",
    "sg:tags":[
        "utensil",
        "cooking"
    ],
    "sg:website":"www.wirewhisk.com",
    "wof:name":"Wire Whisk",
    "wof:placetype":"venue"
},
  "geometry": {"coordinates":[-73.493612,41.148458],"type":"Point"}
}