{
  "type": "Feature",
  "properties": {
    "iso:country":"US",
    "sg:address":"1320 Park St",
    "sg:city":"Peekskill",
    "sg:classifiers":[
        {
            "category":"Wholesale",
            "subcategory":"Construction Materials",
            "type":"Manufacturing & Wholesale Goods"
        }
    ],
    "sg:phone":"+1 914 737 0471",
    "sg:postcode":"10566",
    "sg:province":"NY",
    "sg:tags":[
        "tile"
    ],
    "wof:name":"Strictly Ceramic Tile",
    "wof:placetype":"venue"
},
  "geometry": {"coordinates":[-73.911534,41.291476],"type":"Point"}
}