{
  "type": "Feature",
  "properties": {
    "addr:full":"120 Westchester Sq Bronx NY 10461",
    "addr:housenumber":"120",
    "addr:postcode":"10461",
    "addr:street":"Westchester Sq",
    "iso:country":"US",
    "sg:address":"120 Westchester Sq",
    "sg:city":"Bronx",
    "sg:classifiers":[
        {
            "category":"Government",
            "subcategory":"Office",
            "type":"Public Place"
        }
    ],
    "sg:phone":"+1 718 792 8300",
    "sg:postcode":"10461",
    "sg:province":"NY",
    "sg:tags":[
        "force",
        "recruiter",
        "recruiting",
        "armed",
        "army"
    ],
    "wof:name":"US Army Recruiting",
    "wof:placetype":"venue"
},
  "geometry": {"coordinates":[-73.84246400000001,40.841077],"type":"Point"}
}