{
  "type": "Feature",
  "properties": {
    "iso:country":"US",
    "sg:address":"49 Franklin St",
    "sg:city":"Sandy Creek",
    "sg:classifiers":[
        {
            "category":"Retail",
            "subcategory":"Animal Services",
            "type":"Services"
        }
    ],
    "sg:phone":"+1 315 387 5852",
    "sg:postcode":"13145",
    "sg:province":"NY",
    "wof:name":"Bellingers Dog Training",
    "wof:placetype":"venue"
},
  "geometry": {"coordinates":[-76.08713,43.647184],"type":"Point"}
}