{
  "type": "Feature",
  "properties": {
    "iso:country":"US",
    "sg:address":"1461 W 10th St",
    "sg:city":"Brooklyn",
    "sg:classifiers":[
        {
            "category":"Home & Garden",
            "subcategory":"Home Furnishings",
            "type":"Retail Goods"
        }
    ],
    "sg:phone":"+1 718 906 1222",
    "sg:postcode":"11204",
    "sg:province":"NY",
    "sg:tags":[
        "window",
        "treatment"
    ],
    "wof:name":"Classic Window Fashion",
    "wof:placetype":"venue"
},
  "geometry": {"coordinates":[-73.983982,40.610841],"type":"Point"}
}