{
  "type": "Feature",
  "properties": {
    "iso:country":"US",
    "sg:address":"3000 Westchester Ave",
    "sg:city":"Purchase",
    "sg:classifiers":[
        {
            "category":"Real Estate",
            "subcategory":"Architect",
            "type":"Services"
        }
    ],
    "sg:phone":"+1 914 701 0101",
    "sg:postcode":"10577",
    "sg:province":"NY",
    "sg:tags":[
        "architects'",
        "specification",
        "construction",
        "builders'",
        "architectural"
    ],
    "wof:name":"ARC Services",
    "wof:placetype":"venue"
},
  "geometry": {"coordinates":[-73.694283,41.00843],"type":"Point"}
}