{
  "type": "Feature",
  "properties": {
    "iso:country":"US",
    "sg:address":"50 E 61 St",
    "sg:city":"New York",
    "sg:classifiers":[
        {
            "category":"Retail",
            "subcategory":"Auto Repair",
            "type":"Services"
        }
    ],
    "sg:phone":"+1 646 307 4500",
    "sg:postcode":"10065",
    "sg:province":"NY",
    "sg:tags":[
        "wrecker"
    ],
    "wof:name":"American Car Repair",
    "wof:placetype":"venue"
},
  "geometry": {"coordinates":[-73.969283,40.764296],"type":"Point"}
}