{
  "type": "Feature",
  "properties": {
    "addr:full":"99 Ellis Street Staten Island NY 10307",
    "addr:housenumber":"99",
    "addr:postcode":"10307",
    "addr:street":"Ellis Street",
    "iso:country":"US",
    "sg:address":"99 Ellis Street",
    "sg:city":"Staten Island",
    "sg:classifiers":[
        {
            "category":"Professional",
            "type":"Services"
        },
        {
            "category":"Food & Beverages",
            "subcategory":"Meat & Fish",
            "type":"Retail Goods"
        }
    ],
    "sg:phone":"+1 718 608 9090",
    "sg:postcode":"10307",
    "sg:province":"NY",
    "sg:tags":[
        "shop",
        "caterer"
    ],
    "wof:name":"La Torre of Tottenville",
    "wof:placetype":"venue"
},
  "geometry": {"coordinates":[-74.24256099999999,40.516451],"type":"Point"}
}