{
  "type": "Feature",
  "properties": {
    "addr:full":"350 E 235th St Bronx NY 10470",
    "addr:housenumber":"350",
    "addr:postcode":"10470",
    "addr:street":"E 235Th St",
    "iso:country":"US",
    "sg:address":"350 E 235th St",
    "sg:city":"Bronx",
    "sg:classifiers":[
        {
            "category":"Professional",
            "type":"Services"
        }
    ],
    "sg:phone":"+1 718 325 0535",
    "sg:postcode":"10470",
    "sg:province":"NY",
    "sg:tags":[
        "writer"
    ],
    "wof:name":"Irina Burns",
    "wof:placetype":"venue"
},
  "geometry": {"coordinates":[-73.865989,40.897723],"type":"Point"}
}