{
  "type": "Feature",
  "properties": {
    "iso:country":"US",
    "sg:address":"491 Smith St",
    "sg:city":"Brooklyn",
    "sg:classifiers":[
        {
            "category":"Building & Trades",
            "subcategory":"Construction",
            "type":"Services"
        }
    ],
    "sg:phone":"+1 718 246 8477",
    "sg:postcode":"11231",
    "sg:province":"NY",
    "sg:tags":[
        "concrete",
        "contractor"
    ],
    "wof:name":"Redhook Concrete Loading Corp",
    "wof:placetype":"venue"
},
  "geometry": {"coordinates":[-73.99757700000001,40.675044],"type":"Point"}
}