{
  "type": "Feature",
  "properties": {
    "addr:full":"440 Whitehall Rd Albany NY 12208",
    "addr:housenumber":"440",
    "addr:postcode":"12208",
    "addr:street":"Whitehall Rd",
    "iso:country":"US",
    "sg:address":"440 Whitehall Rd",
    "sg:city":"Albany",
    "sg:classifiers":[
        {
            "category":"Organizations",
            "subcategory":"Religious Organization",
            "type":"Services"
        }
    ],
    "sg:phone":"+1 518 489 4442",
    "sg:postcode":"12208",
    "sg:province":"NY",
    "sg:tags":[
        "church"
    ],
    "sg:website":"www.timesunion.com/communities/stsophia",
    "wof:name":"St Sophia Greek Orthodox Chr",
    "wof:placetype":"venue"
},
  "geometry": {"coordinates":[-73.81652099999999,42.654458],"type":"Point"}
}