{
  "type": "Feature",
  "properties": {
    "iso:country":"US",
    "sg:address":"1870 Strong Rd",
    "sg:city":"Victor",
    "sg:classifiers":[
        {
            "category":"Food & Beverages",
            "subcategory":"Fruits & Vegetables",
            "type":"Retail Goods"
        }
    ],
    "sg:phone":"+1   ",
    "sg:postcode":"14564",
    "sg:province":"NY",
    "wof:name":"Ronald Bennett",
    "wof:placetype":"venue"
},
  "geometry": {"coordinates":[-77.471445,42.939386],"type":"Point"}
}