{
  "type": "Feature",
  "properties": {
    "addr:full":"2025 Davidson Ave Bronx NY 10453",
    "addr:housenumber":"2025",
    "addr:postcode":"10453",
    "addr:street":"Davidson Ave",
    "iso:country":"US",
    "sg:address":"2025 Davidson Ave",
    "sg:city":"Bronx",
    "sg:classifiers":[
        {
            "category":"Shopping",
            "subcategory":"Gifts & Souvenirs",
            "type":"Retail Goods"
        }
    ],
    "sg:phone":"+1 718 294 7887",
    "sg:postcode":"10453",
    "sg:province":"NY",
    "sg:tags":[
        "party",
        "supply"
    ],
    "wof:name":"Party House",
    "wof:placetype":"venue"
},
  "geometry": {"coordinates":[-73.90956799999999,40.852403],"type":"Point"}
}