{
  "type": "Feature",
  "properties": {
    "iso:country":"US",
    "sg:address":"20 The Plains Rd",
    "sg:city":"Levittown",
    "sg:classifiers":[
        {
            "category":"Building & Trades",
            "subcategory":"Construction",
            "type":"Services"
        }
    ],
    "sg:phone":"+1 516 731 7518",
    "sg:postcode":"11756",
    "sg:province":"NY",
    "sg:tags":[
        "home",
        "improvement"
    ],
    "wof:name":"Joseph Allard Home Improvement",
    "wof:placetype":"venue"
},
  "geometry": {"coordinates":[-73.507946,40.728274],"type":"Point"}
}