{
  "type": "Feature",
  "properties": {
    "addr:full":"1590 Madison Ave New York NY 10029",
    "addr:housenumber":"1590",
    "addr:postcode":"10029",
    "addr:street":"Madison Ave",
    "iso:country":"US",
    "sg:address":"1590 Madison Ave",
    "sg:city":"New York",
    "sg:classifiers":[
        {
            "category":"Professional",
            "subcategory":"Business Services",
            "type":"Services"
        }
    ],
    "sg:phone":"+1 212 876 5177",
    "sg:postcode":"10029",
    "sg:province":"NY",
    "sg:tags":[
        "event"
    ],
    "wof:name":"Lava Event Production",
    "wof:placetype":"venue"
},
  "geometry": {"coordinates":[-73.94934600000001,40.793835],"type":"Point"}
}