{
  "type": "Feature",
  "properties": {
    "addr:full":"49 Grove St New York NY 10014",
    "addr:housenumber":"49",
    "addr:postcode":"10014",
    "addr:street":"Grove St",
    "iso:country":"US",
    "sg:address":"49 Grove St",
    "sg:city":"New York",
    "sg:classifiers":[
        {
            "category":"Shopping",
            "subcategory":"Clothing, Apparel, & Fashions",
            "type":"Retail Goods"
        }
    ],
    "sg:phone":"+1   ",
    "sg:postcode":"10014",
    "sg:province":"NY",
    "wof:name":"Mieko Mintz",
    "wof:placetype":"venue"
},
  "geometry": {"coordinates":[-74.00303099999999,40.733215],"type":"Point"}
}