{
  "type": "Feature",
  "properties": {
    "iso:country":"US",
    "sg:address":"2 Deer Run Rd",
    "sg:city":"Kingston",
    "sg:classifiers":[
        {
            "category":"Building & Trades",
            "subcategory":"Construction",
            "type":"Services"
        }
    ],
    "sg:phone":"+1 845 339 0555",
    "sg:postcode":"12401",
    "sg:province":"NY",
    "sg:tags":[
        "hanging",
        "contractor"
    ],
    "wof:name":"Scoville Painting Co",
    "wof:placetype":"venue"
},
  "geometry": {"coordinates":[-73.97111099999999,41.995622],"type":"Point"}
}