{
  "type": "Feature",
  "properties": {
    "addr:full":"75 E 3 St New York NY 10003",
    "addr:housenumber":"75;3",
    "addr:postcode":"10003",
    "addr:street":"E;St",
    "iso:country":"US",
    "sg:address":"75 E 3 St",
    "sg:city":"New York",
    "sg:classifiers":[
        {
            "category":"Professional",
            "subcategory":"Business Services",
            "type":"Services"
        }
    ],
    "sg:phone":"+1 212 598 9801",
    "sg:postcode":"10003",
    "sg:province":"NY",
    "sg:tags":[
        "messenger"
    ],
    "wof:name":"Mothers Messengers of Nyc",
    "wof:placetype":"venue"
},
  "geometry": {"coordinates":[-73.98849,40.725219],"type":"Point"}
}