{
  "type": "Feature",
  "properties": {
    "iso:country":"US",
    "sg:address":"121 S Ocean Ave",
    "sg:city":"Freeport",
    "sg:classifiers":[
        {
            "category":"Communications",
            "subcategory":"News Services",
            "type":"Services"
        },
        {
            "category":"Health Services",
            "subcategory":"Doctor",
            "type":"Services"
        }
    ],
    "sg:phone":"+1 516 379 5005",
    "sg:postcode":"11520",
    "sg:province":"NY",
    "sg:tags":[
        "physician",
        "surgeon",
        "syndicate"
    ],
    "wof:name":"Howard Grill MD",
    "wof:placetype":"venue"
},
  "geometry": {"coordinates":[-73.58583900000001,40.651905],"type":"Point"}
}