{
  "type": "Feature",
  "properties": {
    "addr:full":"2100 Avenue M Brooklyn NY 11210",
    "addr:housenumber":"2100",
    "addr:postcode":"11210",
    "addr:street":"Avenue M",
    "iso:country":"US",
    "sg:address":"2100 Avenue M",
    "sg:city":"Brooklyn",
    "sg:classifiers":[
        {
            "category":"Professional",
            "subcategory":"Lawyer & Legal Services",
            "type":"Services"
        }
    ],
    "sg:phone":"+1 212 269 3405",
    "sg:postcode":"11210",
    "sg:province":"NY",
    "wof:name":"Tessler Isaac Lawyer",
    "wof:placetype":"venue"
},
  "geometry": {"coordinates":[-73.953796,40.618599],"type":"Point"}
}