{
  "type": "Feature",
  "properties": {
    "addr:full":"1688 Kensington Ave Merrick NY 11566",
    "addr:housenumber":"1688",
    "addr:postcode":"11566",
    "addr:street":"Kensington Ave",
    "iso:country":"US",
    "sg:address":"1688 Kensington Ave",
    "sg:city":"Merrick",
    "sg:classifiers":[
        {
            "category":"Retail",
            "subcategory":"Laundry & Dry Cleaning",
            "type":"Services"
        }
    ],
    "sg:phone":"+1   ",
    "sg:postcode":"11566",
    "sg:province":"NY",
    "sg:tags":[
        "drycleaning",
        "plant"
    ],
    "wof:name":"Ilsa Dry Cleaning Machine",
    "wof:placetype":"venue"
},
  "geometry": {"coordinates":[-73.560873,40.678488],"type":"Point"}
}