{
  "type": "Feature",
  "properties": {
    "iso:country":"US",
    "sg:address":"150 Jordan Ave",
    "sg:city":"Rochester",
    "sg:classifiers":[
        {
            "category":"Shopping",
            "subcategory":"Computers & Home Electronics",
            "type":"Retail Goods"
        }
    ],
    "sg:phone":"+1 585 426 3069",
    "sg:postcode":"14606",
    "sg:province":"NY",
    "sg:tags":[
        "equipment",
        "dealer"
    ],
    "wof:name":"Sunshine Computers",
    "wof:placetype":"venue"
},
  "geometry": {"coordinates":[-77.697363,43.175266],"type":"Point"}
}