{
  "type": "Feature",
  "properties": {
    "addr:full":"131 Chanel Dr E Shirley NY 11967",
    "addr:housenumber":"131",
    "addr:postcode":"11967",
    "addr:street":"Chanel Dr E",
    "iso:country":"US",
    "sg:address":"131 Chanel Dr E",
    "sg:city":"Shirley",
    "sg:classifiers":[
        {
            "category":"Building & Trades",
            "subcategory":"Plumbing",
            "type":"Services"
        }
    ],
    "sg:phone":"+1 631 395 3937",
    "sg:postcode":"11967",
    "sg:province":"NY",
    "sg:tags":[
        "plumbing",
        "contractor"
    ],
    "wof:name":"G C Plumbing & Heating Inc",
    "wof:placetype":"venue"
},
  "geometry": {"coordinates":[-72.85526,40.768316],"type":"Point"}
}