{
  "type": "Feature",
  "properties": {
    "addr:full":"7th St and 1st Ave East Village New York NY 10009",
    "addr:postcode":"10009",
    "addr:street":"7Th St And 1St Ave",
    "iso:country":"US",
    "sg:address":"7th St and 1st Ave East Village",
    "sg:city":"New York",
    "sg:classifiers":[
        {
            "category":"Bars & Pubs",
            "subcategory":"Dive Bar",
            "type":"Food & Drink"
        }
    ],
    "sg:postcode":"10009",
    "sg:province":"NY",
    "wof:name":"No-Name Bar",
    "wof:placetype":"venue"
},
  "geometry": {"coordinates":[-73.985754,40.726991],"type":"Point"}
}