{
  "type": "Feature",
  "properties": {
    "iso:country":"US",
    "sg:address":"323 5th Ave",
    "sg:city":"Brooklyn",
    "sg:classifiers":[
        {
            "category":"Social Services",
            "subcategory":"Child Care",
            "type":"Services"
        }
    ],
    "sg:phone":"+1 718 768 3122",
    "sg:postcode":"11215",
    "sg:province":"NY",
    "sg:tags":[
        "day"
    ],
    "wof:name":"Kids On Fifth",
    "wof:placetype":"venue"
},
  "geometry": {"coordinates":[-73.9832,40.6726],"type":"Point"}
}