{
  "type": "Feature",
  "properties": {
    "addr:full":"212 W 44th St New York NY 10036",
    "addr:housenumber":"212",
    "addr:postcode":"10036",
    "addr:street":"W 44Th St",
    "iso:country":"US",
    "sg:address":"212 W 44th St",
    "sg:city":"New York",
    "sg:classifiers":[
        {
            "category":"Deli",
            "type":"Food & Drink"
        }
    ],
    "sg:phone":"+1 212 840 1859",
    "sg:postcode":"10036",
    "sg:province":"NY",
    "wof:name":"Starlight Deli",
    "wof:placetype":"venue"
},
  "geometry": {"coordinates":[-73.986198,40.7575],"type":"Point"}
}