{
  "type": "Feature",
  "properties": {
    "addr:full":"760 Franklin Ave Brooklyn NY 11238",
    "addr:housenumber":"760",
    "addr:postcode":"11238",
    "addr:street":"Franklin Ave",
    "iso:country":"US",
    "sg:address":"760 Franklin Ave",
    "sg:city":"Brooklyn",
    "sg:classifiers":[
        {
            "category":"Arena",
            "subcategory":"Sports Club",
            "type":"Entertainment"
        }
    ],
    "sg:phone":"+1 718 230 5930",
    "sg:postcode":"11238",
    "sg:province":"NY",
    "sg:tags":[
        "martial art"
    ],
    "wof:name":"Debranche United Shotokan Karate Do",
    "wof:placetype":"venue"
},
  "geometry": {"coordinates":[-73.957464,40.672528],"type":"Point"}
}