{
  "type": "Feature",
  "properties": {
    "iso:country":"US",
    "sg:address":"5613 5th Avenue",
    "sg:city":"Brooklyn",
    "sg:classifiers":[
        {
            "category":"Professional",
            "subcategory":"Lawyer & Legal Services",
            "type":"Services"
        }
    ],
    "sg:phone":"+1 718 439 3377",
    "sg:postcode":"11220",
    "sg:province":"NY",
    "wof:name":"Diana Serrano",
    "wof:placetype":"venue"
},
  "geometry": {"coordinates":[-74.013953,40.641429],"type":"Point"}
}