{
  "type": "Feature",
  "properties": {
    "addr:full":"401 Broadway, Ste 512 New York NY 10013",
    "addr:housenumber":"401;512",
    "addr:postcode":"10013",
    "addr:street":"Broadway Ste",
    "iso:country":"US",
    "sg:address":"401 Broadway, Ste 512",
    "sg:city":"New York",
    "sg:classifiers":[
        {
            "category":"Retail",
            "subcategory":"Portrait Studio",
            "type":"Services"
        }
    ],
    "sg:phone":"+1 212 625 3834",
    "sg:postcode":"10013",
    "sg:province":"NY",
    "sg:tags":[
        "photography",
        "store"
    ],
    "wof:name":"AY Studio INC",
    "wof:placetype":"venue"
},
  "geometry": {"coordinates":[-74.00255300000001,40.718705],"type":"Point"}
}