{
  "type": "Feature",
  "properties": {
    "addr:full":"47 Lochnavar Pkwy Pittsford NY 14534",
    "addr:housenumber":"47",
    "addr:postcode":"14534",
    "addr:street":"Lochnavar Pkwy",
    "iso:country":"US",
    "sg:address":"47 Lochnavar Pkwy",
    "sg:city":"Pittsford",
    "sg:classifiers":[
        {
            "category":"Organizations",
            "subcategory":"Religious Organization",
            "type":"Services"
        }
    ],
    "sg:phone":"+1 585 588 8291",
    "sg:postcode":"14534",
    "sg:province":"NY",
    "sg:tags":[
        "monastery",
        "convent"
    ],
    "wof:name":"Sisters Of St Joseph Daystar",
    "wof:placetype":"venue"
},
  "geometry": {"coordinates":[-77.504425,43.108266],"type":"Point"}
}