{
  "type": "Feature",
  "properties": {
    "iso:country":"US",
    "sg:address":"275 Marcus Blvd",
    "sg:city":"Hauppauge",
    "sg:classifiers":[
        {
            "category":"Professional",
            "subcategory":"Management & Consulting",
            "type":"Services"
        }
    ],
    "sg:phone":"+1 631 436 5800",
    "sg:postcode":"11788",
    "sg:province":"NY",
    "sg:tags":[
        "computer",
        "design",
        "system"
    ],
    "wof:name":"Eberhard Systems",
    "wof:placetype":"venue"
},
  "geometry": {"coordinates":[-73.247968,40.818632],"type":"Point"}
}