{
  "type": "Feature",
  "properties": {
    "addr:full":"42 Claremont Pl Mount Vernon NY 10553",
    "addr:housenumber":"42",
    "addr:postcode":"10553",
    "addr:street":"Claremont Pl",
    "iso:country":"US",
    "sg:address":"42 Claremont Pl",
    "sg:city":"Mount Vernon",
    "sg:classifiers":[
        {
            "category":"Professional",
            "type":"Services"
        }
    ],
    "sg:phone":"+1   ",
    "sg:postcode":"10553",
    "sg:province":"NY",
    "wof:name":"Musical Services",
    "wof:placetype":"venue"
},
  "geometry": {"coordinates":[-73.825952,40.912048],"type":"Point"}
}