{
  "type": "Feature",
  "properties": {
    "iso:country":"US",
    "sg:address":"317 E Church St",
    "sg:city":"Elmira",
    "sg:classifiers":[
        {
            "category":"Government",
            "subcategory":"Office",
            "type":"Public Place"
        }
    ],
    "sg:phone":"+1 607 737 5679",
    "sg:postcode":"14901",
    "sg:province":"NY",
    "sg:tags":[
        "village"
    ],
    "wof:name":"Elmira Public Svc Dept",
    "wof:placetype":"venue"
},
  "geometry": {"coordinates":[-76.803203,42.091349],"type":"Point"}
}