{
  "type": "Feature",
  "properties": {
    "addr:full":"50 Lynwood Ave Farmingville NY 11738",
    "addr:housenumber":"50",
    "addr:postcode":"11738",
    "addr:street":"Lynwood Ave",
    "iso:country":"US",
    "sg:address":"50 Lynwood Ave",
    "sg:city":"Farmingville",
    "sg:classifiers":[
        {
            "category":"Retail",
            "subcategory":"Repair Shop",
            "type":"Services"
        }
    ],
    "sg:phone":"+1 631 721 0016",
    "sg:postcode":"11738",
    "sg:province":"NY",
    "sg:tags":[
        "lock",
        "locksmith"
    ],
    "wof:name":"1 Hour Emergency Locksmith",
    "wof:placetype":"venue"
},
  "geometry": {"coordinates":[-73.029893,40.832889],"type":"Point"}
}