{
  "type": "Feature",
  "properties": {
    "addr:full":"1500 State Hwy 438 Irving NY 14081",
    "addr:housenumber":"1500",
    "addr:postcode":"14081",
    "addr:street":"State Hwy 438",
    "iso:country":"US",
    "sg:address":"1500 State Hwy 438",
    "sg:city":"Irving",
    "sg:classifiers":[
        {
            "category":"Real Estate",
            "subcategory":"Real Estate Operator",
            "type":"Services"
        }
    ],
    "sg:phone":"+1 716 549 0888",
    "sg:postcode":"14081",
    "sg:province":"NY",
    "sg:tags":[
        "building",
        "nonresidential"
    ],
    "wof:name":"Gil Lay Memorial Sports Arena",
    "wof:placetype":"venue"
},
  "geometry": {"coordinates":[-78.99532499999999,42.537399],"type":"Point"}
}