{
  "type": "Feature",
  "properties": {
    "iso:country":"US",
    "sg:address":"442 Sterling Pl",
    "sg:city":"Brooklyn",
    "sg:classifiers":[
        {
            "category":"Arts & Performance",
            "subcategory":"Theater",
            "type":"Entertainment"
        }
    ],
    "sg:phone":"+1 718 623 8302",
    "sg:postcode":"11238",
    "sg:province":"NY",
    "sg:tags":[
        "bureau"
    ],
    "wof:name":"Third Eye Entertainment LLC",
    "wof:placetype":"venue"
},
  "geometry": {"coordinates":[-73.965417,40.675125],"type":"Point"}
}