{
  "type": "Feature",
  "properties": {
    "iso:country":"US",
    "sg:address":"15 Hilton Ave",
    "sg:city":"Hempstead",
    "sg:classifiers":[
        {
            "category":"Restaurant",
            "type":"Food & Drink"
        }
    ],
    "sg:phone":"+1 516 538 9326",
    "sg:postcode":"11550",
    "sg:province":"NY",
    "wof:name":"R U Inc",
    "wof:placetype":"venue"
},
  "geometry": {"coordinates":[-73.631601,40.708246],"type":"Point"}
}