{
  "type": "Feature",
  "properties": {
    "addr:full":"1367 Washington Ave Albany NY 12206",
    "addr:housenumber":"1367",
    "addr:postcode":"12206",
    "addr:street":"Washington Ave",
    "iso:country":"US",
    "sg:address":"1367 Washington Ave",
    "sg:city":"Albany",
    "sg:classifiers":[
        {
            "category":"Health Services",
            "subcategory":"Doctor",
            "type":"Services"
        }
    ],
    "sg:phone":"+1 518 262 5636",
    "sg:postcode":"12206",
    "sg:province":"NY",
    "sg:tags":[
        "medical"
    ],
    "wof:name":"Allen L Carl",
    "wof:placetype":"venue"
},
  "geometry": {"coordinates":[-73.81816499999999,42.688518],"type":"Point"}
}