{
  "type": "Feature",
  "properties": {
    "addr:full":"66 Webster Ave Port Washington NY 11050",
    "addr:housenumber":"66",
    "addr:postcode":"11050",
    "addr:street":"Webster Ave",
    "iso:country":"US",
    "sg:address":"66 Webster Ave",
    "sg:city":"Port Washington",
    "sg:classifiers":[
        {
            "category":"Building & Trades",
            "subcategory":"Plumbing",
            "type":"Services"
        }
    ],
    "sg:phone":"+1 516 767 7569",
    "sg:postcode":"11050",
    "sg:province":"NY",
    "sg:tags":[
        "contractor"
    ],
    "wof:name":"Ventura Plumbing & Heating",
    "wof:placetype":"venue"
},
  "geometry": {"coordinates":[-73.695871,40.830044],"type":"Point"}
}