{
  "type": "Feature",
  "properties": {
    "iso:country":"US",
    "sg:address":"414 Woodland Ln",
    "sg:city":"Webster",
    "sg:classifiers":[
        {
            "category":"Building & Trades",
            "subcategory":"Landscaping Services",
            "type":"Services"
        }
    ],
    "sg:phone":"+1 585 671 0194",
    "sg:postcode":"14580",
    "sg:province":"NY",
    "sg:tags":[
        "landscape"
    ],
    "wof:name":"BT Donnelly Landscaping",
    "wof:placetype":"venue"
},
  "geometry": {"coordinates":[-77.50863099999999,43.217527],"type":"Point"}
}