{
  "type": "Feature",
  "properties": {
    "addr:full":"300 Hampton Rd N Southampton NY 11968",
    "addr:housenumber":"300",
    "addr:postcode":"11968",
    "addr:street":"Hampton Rd N",
    "iso:country":"US",
    "sg:address":"300 Hampton Rd N",
    "sg:city":"Southampton",
    "sg:classifiers":[
        {
            "category":"Insurance",
            "subcategory":"Insurance Agent",
            "type":"Services"
        }
    ],
    "sg:phone":"+1 631 283 8000",
    "sg:postcode":"11968",
    "sg:province":"NY",
    "sg:website":"www.mcrainsurance.com",
    "wof:name":"Maran Corporate Risk Assoc",
    "wof:placetype":"venue"
},
  "geometry": {"coordinates":[-72.391873,40.96258],"type":"Point"}
}