{
  "type": "Feature",
  "properties": {
    "addr:full":"Basement Of Eleven 15 Prince St New York NY 10012",
    "addr:housenumber":"15",
    "addr:postcode":"10012",
    "addr:street":"Prince St",
    "iso:country":"US",
    "sg:address":"Basement Of Eleven 15 Prince St",
    "sg:city":"New York",
    "sg:classifiers":[
        {
            "category":"Shopping",
            "subcategory":"Clothing, Apparel, & Fashions",
            "type":"Retail Goods"
        }
    ],
    "sg:phone":"+1 212 334 5334",
    "sg:postcode":"10012",
    "sg:province":"NY",
    "sg:tags":[
        "men's",
        "clothing"
    ],
    "sg:website":"leeharknessshirtco.com/",
    "wof:name":"Lee Harkness Shirt Co.",
    "wof:placetype":"venue"
},
  "geometry": {"coordinates":[-73.99409199999999,40.72269],"type":"Point"}
}