{
  "type": "Feature",
  "properties": {
    "iso:country":"US",
    "sg:address":"12800 W Main St",
    "sg:city":"Alden",
    "sg:classifiers":[
        {
            "category":"Building & Trades",
            "subcategory":"Construction",
            "type":"Services"
        },
        {
            "category":"Government",
            "subcategory":"Office",
            "type":"Public Place"
        }
    ],
    "sg:phone":"+1 716 937 7336",
    "sg:postcode":"14004",
    "sg:province":"NY",
    "sg:tags":[
        "marking",
        "executive",
        "maintenance",
        "parking"
    ],
    "wof:name":"Alden Town Highway Dept",
    "wof:placetype":"venue"
},
  "geometry": {"coordinates":[-78.51103500000001,42.900429],"type":"Point"}
}