{
  "type": "Feature",
  "properties": {
    "addr:full":"573 Burnside Ave Inwood NY 11096",
    "addr:housenumber":"573",
    "addr:postcode":"11096",
    "addr:street":"Burnside Ave",
    "iso:country":"US",
    "sg:address":"573 Burnside Ave",
    "sg:city":"Inwood",
    "sg:classifiers":[
        {
            "category":"Personal",
            "subcategory":"Nail Salon",
            "type":"Services"
        }
    ],
    "sg:phone":"+1 516 239 1918",
    "sg:postcode":"11096",
    "sg:province":"NY",
    "wof:name":"Ellen Beauty Nail & Spa Inc",
    "wof:placetype":"venue"
},
  "geometry": {"coordinates":[-73.743038,40.622881],"type":"Point"}
}