{
  "type": "Feature",
  "properties": {
    "addr:full":"55 Sunrise Hwy Merrick NY 11566",
    "addr:housenumber":"55",
    "addr:postcode":"11566",
    "addr:street":"Sunrise Hwy",
    "iso:country":"US",
    "sg:address":"55 Sunrise Hwy",
    "sg:city":"Merrick",
    "sg:classifiers":[
        {
            "category":"Building & Trades",
            "subcategory":"Construction",
            "type":"Services"
        }
    ],
    "sg:phone":"+1 516 868 5900",
    "sg:postcode":"11566",
    "sg:province":"NY",
    "sg:tags":[
        "tile",
        "dealer"
    ],
    "wof:name":"Cancos Tile",
    "wof:placetype":"venue"
},
  "geometry": {"coordinates":[-73.56781700000001,40.658653],"type":"Point"}
}