{
  "type": "Feature",
  "properties": {
    "addr:full":"180 Riverside Blvd Lbby 1 New York NY 10069",
    "addr:housenumber":"180;1",
    "addr:postcode":"10069",
    "addr:street":"Riverside Blvd Lbby",
    "iso:country":"US",
    "sg:address":"180 Riverside Blvd Lbby 1",
    "sg:city":"New York",
    "sg:classifiers":[
        {
            "category":"Real Estate",
            "subcategory":"Real Estate Operator",
            "type":"Services"
        }
    ],
    "sg:phone":"+1 646 405 5156",
    "sg:postcode":"10069",
    "sg:province":"NY",
    "sg:tags":[
        "apartment"
    ],
    "wof:name":"Equity Residential",
    "wof:placetype":"venue"
},
  "geometry": {"coordinates":[-73.98840800000001,40.778145],"type":"Point"}
}