{
  "type": "Feature",
  "properties": {
    "iso:country":"US",
    "sg:address":"1634 44th St",
    "sg:city":"Brooklyn",
    "sg:classifiers":[
        {
            "category":"Organizations",
            "subcategory":"Religious Organization",
            "type":"Services"
        }
    ],
    "sg:phone":"+1 718 854 0351",
    "sg:postcode":"11204",
    "sg:province":"NY",
    "sg:tags":[
        "clergy"
    ],
    "wof:name":"J M Josilowski",
    "wof:placetype":"venue"
},
  "geometry": {"coordinates":[-73.980835,40.63281],"type":"Point"}
}