{
  "type": "Feature",
  "properties": {
    "iso:country":"US",
    "sg:address":"114 Smith St",
    "sg:city":"Manlius",
    "sg:classifiers":[
        {
            "category":"Building & Trades",
            "subcategory":"Construction",
            "type":"Services"
        }
    ],
    "sg:phone":"+1 315 682 5870",
    "sg:postcode":"13104",
    "sg:province":"NY",
    "sg:tags":[
        "painting",
        "painter",
        "contractor"
    ],
    "sg:website":"www.timpalmer.net",
    "wof:name":"Palmer Painting Inc",
    "wof:placetype":"venue"
},
  "geometry": {"coordinates":[-75.979403,43.004463],"type":"Point"}
}