{
  "type": "Feature",
  "properties": {
    "iso:country":"US",
    "sg:address":"90 W University St",
    "sg:city":"Alfred",
    "sg:classifiers":[
        {
            "category":"Place Of Worship",
            "type":"Public Place"
        }
    ],
    "sg:phone":"+1 607 545 8366",
    "sg:postcode":"14802",
    "sg:province":"NY",
    "sg:tags":[
        "church"
    ],
    "wof:name":"Alfred Monthly Meeting",
    "wof:placetype":"venue"
},
  "geometry": {"coordinates":[-77.79699100000001,42.252969],"type":"Point"}
}