{
  "type": "Feature",
  "properties": {
    "iso:country":"US",
    "sg:address":"1354 Charlesgate Cir",
    "sg:city":"East Amherst",
    "sg:classifiers":[
        {
            "category":"Organizations",
            "subcategory":"Religious Organization",
            "type":"Services"
        }
    ],
    "sg:phone":"+1 716 688 1686",
    "sg:postcode":"14051",
    "sg:province":"NY",
    "sg:tags":[
        "church"
    ],
    "wof:name":"Ukrainian Orthodox Church",
    "wof:placetype":"venue"
},
  "geometry": {"coordinates":[-78.720861,43.048607],"type":"Point"}
}