{
  "type": "Feature",
  "properties": {
    "iso:country":"US",
    "sg:address":"825 Dean Dr",
    "sg:city":"Baldwin",
    "sg:classifiers":[
        {
            "category":"Building & Trades",
            "subcategory":"Construction",
            "type":"Services"
        }
    ],
    "sg:phone":"+1 516 564 8902",
    "sg:postcode":"11510",
    "sg:province":"NY",
    "sg:tags":[
        "house"
    ],
    "wof:name":"New Pond Construction",
    "wof:placetype":"venue"
},
  "geometry": {"coordinates":[-73.61112300000001,40.683126],"type":"Point"}
}