{
  "type": "Feature",
  "properties": {
    "addr:full":"206 Avenue A New York NY 10009",
    "addr:housenumber":"206",
    "addr:postcode":"10009",
    "addr:street":"Avenue A",
    "iso:country":"US",
    "sg:address":"206 Avenue A",
    "sg:city":"New York",
    "sg:classifiers":[
        {
            "category":"Bars & Pubs",
            "type":"Food & Drink"
        }
    ],
    "sg:menulink":"http://www.allmenus.com/ny/new-york/252624-common-ground-restaurant--bar/menu/",
    "sg:phone":"+1 212 228 6231",
    "sg:postcode":"10009",
    "sg:province":"NY",
    "sg:tags":[
        "american",
        "french"
    ],
    "wof:name":"Common Ground Restaurant & Bar",
    "wof:placetype":"venue"
},
  "geometry": {"coordinates":[-73.980705,40.729422],"type":"Point"}
}