{
  "type": "Feature",
  "properties": {
    "addr:full":"300 E Tremont Ave Bronx NY 10457",
    "addr:housenumber":"300",
    "addr:postcode":"10457",
    "addr:street":"E Tremont Ave",
    "iso:country":"US",
    "sg:address":"300 E Tremont Ave",
    "sg:city":"Bronx",
    "sg:classifiers":[
        {
            "category":"Personal",
            "subcategory":"Barber",
            "type":"Services"
        }
    ],
    "sg:phone":"+1 718 901 0061",
    "sg:postcode":"10457",
    "sg:province":"NY",
    "wof:name":"Michef Barber Shop",
    "wof:placetype":"venue"
},
  "geometry": {"coordinates":[-73.902407,40.848602],"type":"Point"}
}