{
  "type": "Feature",
  "properties": {
    "iso:country":"US",
    "sg:address":"175 Stanton St",
    "sg:city":"New York",
    "sg:classifiers":[
        {
            "category":"Shopping",
            "subcategory":"Bicycles & Sporting Goods",
            "type":"Retail Goods"
        }
    ],
    "sg:phone":"+1 212 475 0102",
    "sg:postcode":"10002",
    "sg:province":"NY",
    "sg:tags":[
        "bike"
    ],
    "sg:website":"www.chariandconyc.com",
    "wof:name":"Chari & Co",
    "wof:placetype":"venue"
},
  "geometry": {"coordinates":[-73.98424900000001,40.719968],"type":"Point"}
}