{
  "type": "Feature",
  "properties": {
    "addr:full":"3084 State Hwy 28 Shokan NY 12481",
    "addr:housenumber":"3084",
    "addr:postcode":"12481",
    "addr:street":"State Hwy 28",
    "iso:country":"US",
    "sg:address":"3084 State Hwy 28",
    "sg:city":"Shokan",
    "sg:classifiers":[
        {
            "category":"Building & Trades",
            "subcategory":"Plumbing",
            "type":"Services"
        }
    ],
    "sg:phone":"+1 845 657 6513",
    "sg:postcode":"12481",
    "sg:province":"NY",
    "sg:tags":[
        "conditioning",
        "air",
        "system",
        "contractor"
    ],
    "wof:name":"Simplicity",
    "wof:placetype":"venue"
},
  "geometry": {"coordinates":[-74.21404200000001,41.973224],"type":"Point"}
}