{
  "type": "Feature",
  "properties": {
    "iso:country":"US",
    "sg:address":"3314 Long Beach Rd",
    "sg:city":"Oceanside",
    "sg:classifiers":[
        {
            "category":"Wholesale",
            "subcategory":"Medical Equipment & Supplies",
            "type":"Manufacturing & Wholesale Goods"
        }
    ],
    "sg:phone":"+1 516 536 5509",
    "sg:postcode":"11572",
    "sg:province":"NY",
    "sg:tags":[
        "physician",
        "surgeon"
    ],
    "wof:name":"Elite Home Care",
    "wof:placetype":"venue"
},
  "geometry": {"coordinates":[-73.640986,40.631005],"type":"Point"}
}