{
  "type": "Feature",
  "properties": {
    "addr:full":"633 3 Ave New York NY 10017",
    "addr:housenumber":"633",
    "addr:postcode":"10017",
    "addr:street":"3 Ave",
    "iso:country":"US",
    "sg:address":"633 3 Ave",
    "sg:city":"New York",
    "sg:classifiers":[
        {
            "category":"Organizations",
            "subcategory":"Non-profit Organization",
            "type":"Services"
        }
    ],
    "sg:phone":"+1 646 871 6300",
    "sg:postcode":"10017",
    "sg:province":"NY",
    "sg:tags":[
        "fund",
        "counselor",
        "raising"
    ],
    "wof:name":"American COMMITTEE-Wei",
    "wof:placetype":"venue"
},
  "geometry": {"coordinates":[-73.974935,40.7501],"type":"Point"}
}