{
  "type": "Feature",
  "properties": {
    "addr:full":"10935 Bennett Rd Dunkirk NY 14048",
    "addr:housenumber":"10935",
    "addr:postcode":"14048",
    "addr:street":"Bennett Rd",
    "iso:country":"US",
    "sg:address":"10935 Bennett Rd",
    "sg:city":"Dunkirk",
    "sg:classifiers":[
        {
            "category":"Retail",
            "subcategory":"Auto Repair",
            "type":"Services"
        }
    ],
    "sg:phone":"+1 716 366 6113",
    "sg:postcode":"14048",
    "sg:province":"NY",
    "sg:tags":[
        "body",
        "automobile",
        "painting"
    ],
    "wof:name":"Vambotti Collision",
    "wof:placetype":"venue"
},
  "geometry": {"coordinates":[-79.32176200000001,42.475008],"type":"Point"}
}