{
  "type": "Feature",
  "properties": {
    "addr:full":"1110 Hylan Blvd Staten Island NY 10305",
    "addr:housenumber":"1110",
    "addr:postcode":"10305",
    "addr:street":"Hylan Blvd",
    "iso:country":"US",
    "sg:address":"1110 Hylan Blvd",
    "sg:city":"Staten Island",
    "sg:classifiers":[
        {
            "category":"Food & Beverages",
            "subcategory":"Candy",
            "type":"Retail Goods"
        }
    ],
    "sg:phone":"+1   ",
    "sg:postcode":"10305",
    "sg:province":"NY",
    "sg:tags":[
        "stationery",
        "prod",
        "tobacco"
    ],
    "wof:name":"Hylan Cards & Gifts",
    "wof:placetype":"venue"
},
  "geometry": {"coordinates":[-74.080761,40.59861],"type":"Point"}
}