{
  "type": "Feature",
  "properties": {
    "iso:country":"US",
    "sg:address":"565 Blossom Rd",
    "sg:city":"Rochester",
    "sg:classifiers":[
        {
            "category":"Wholesale",
            "subcategory":"Durable Goods & Equipment",
            "type":"Manufacturing & Wholesale Goods"
        }
    ],
    "sg:phone":"+1   ",
    "sg:postcode":"14610",
    "sg:province":"NY",
    "sg:tags":[
        "biological",
        "product",
        "mfg",
        "professional"
    ],
    "wof:name":"Parent Is Erie Scientific Co",
    "wof:placetype":"venue"
},
  "geometry": {"coordinates":[-77.558655,43.14946],"type":"Point"}
}