{
  "type": "Feature",
  "properties": {
    "addr:full":"32 N Seneca St West Seneca NY 14224",
    "addr:housenumber":"32",
    "addr:postcode":"14224",
    "addr:street":"N Seneca St",
    "iso:country":"US",
    "sg:address":"32 N Seneca St",
    "sg:city":"West Seneca",
    "sg:classifiers":[
        {
            "category":"Home & Garden",
            "subcategory":"Household Appliances",
            "type":"Retail Goods"
        }
    ],
    "sg:phone":"+1 716 675 4555",
    "sg:postcode":"14224",
    "sg:province":"NY",
    "wof:name":"Ken's Appliance Repair Svc",
    "wof:placetype":"venue"
},
  "geometry": {"coordinates":[-78.78903699999999,42.848161],"type":"Point"}
}