{
  "type": "Feature",
  "properties": {
    "iso:country":"US",
    "sg:address":"80 Princeton Blvd",
    "sg:city":"Buffalo",
    "sg:classifiers":[
        {
            "category":"Professional",
            "subcategory":"Computer Services",
            "type":"Services"
        }
    ],
    "sg:phone":"+1 716 874 3949",
    "sg:postcode":"14217",
    "sg:province":"NY",
    "sg:tags":[
        "related"
    ],
    "wof:name":"Dpent",
    "wof:placetype":"venue"
},
  "geometry": {"coordinates":[-78.867853,42.974192],"type":"Point"}
}