{
  "type": "Feature",
  "properties": {
    "iso:country":"US",
    "sg:address":"43 Glen Cove Rd",
    "sg:city":"Greenvale",
    "sg:classifiers":[
        {
            "category":"Restaurant",
            "type":"Food & Drink"
        }
    ],
    "sg:phone":"+1 516 484 5873",
    "sg:postcode":"11548",
    "sg:province":"NY",
    "sg:tags":[
        "thai"
    ],
    "sg:website":"www.sarinthaicuisine.com",
    "wof:name":"Sarin Thai Cuisine",
    "wof:placetype":"venue"
},
  "geometry": {"coordinates":[-73.627899,40.8092],"type":"Point"}
}