{
  "type": "Feature",
  "properties": {
    "iso:country":"US",
    "sg:address":"30 Pembroke Dr",
    "sg:city":"Massapequa",
    "sg:classifiers":[
        {
            "category":"Communications",
            "type":"Services"
        }
    ],
    "sg:phone":"+1 516 731 3079",
    "sg:postcode":"11758",
    "sg:province":"NY",
    "sg:tags":[
        "translator",
        "interpreter"
    ],
    "wof:name":"Elaine A Wilburn",
    "wof:placetype":"venue"
},
  "geometry": {"coordinates":[-73.480818,40.710206],"type":"Point"}
}