{
  "type": "Feature",
  "properties": {
    "iso:country":"US",
    "sg:address":"28 Michigan Hollow Rd",
    "sg:city":"Spencer",
    "sg:classifiers":[
        {
            "category":"Professional",
            "subcategory":"Computer Services",
            "type":"Services"
        }
    ],
    "sg:phone":"+1 607 277 6467",
    "sg:postcode":"14883",
    "sg:province":"NY",
    "sg:tags":[
        "related"
    ],
    "wof:name":"Peakxl Products Inc",
    "wof:placetype":"venue"
},
  "geometry": {"coordinates":[-76.481336,42.345106],"type":"Point"}
}