{
  "type": "Feature",
  "properties": {
    "addr:full":"838 McLean Ave Yonkers NY 10704",
    "addr:housenumber":"838",
    "addr:postcode":"10704",
    "addr:street":"Mclean Ave",
    "iso:country":"US",
    "sg:address":"838 McLean Ave",
    "sg:city":"Yonkers",
    "sg:classifiers":[
        {
            "category":"Retail",
            "subcategory":"Auto Repair",
            "type":"Services"
        }
    ],
    "sg:phone":"+1   ",
    "sg:postcode":"10704",
    "sg:province":"NY",
    "sg:tags":[
        "general"
    ],
    "wof:name":"Break To Border Repairs",
    "wof:placetype":"venue"
},
  "geometry": {"coordinates":[-73.870496,40.905945],"type":"Point"}
}