{
  "type": "Feature",
  "properties": {
    "addr:full":"337 Central Ave Rear Lawrence NY 11559",
    "addr:housenumber":"337",
    "addr:postcode":"11559",
    "addr:street":"Central Ave Rear Lawrence",
    "iso:country":"US",
    "sg:address":"337 Central Ave Rear",
    "sg:city":"Lawrence",
    "sg:classifiers":[
        {
            "category":"Professional",
            "subcategory":"Lawyer & Legal Services",
            "type":"Services"
        }
    ],
    "sg:phone":"+1 516 295 3575",
    "sg:postcode":"11559",
    "sg:province":"NY",
    "wof:name":"Mernick Paul M Atty",
    "wof:placetype":"venue"
},
  "geometry": {"coordinates":[-73.733002,40.615898],"type":"Point"}
}