{
  "type": "Feature",
  "properties": {
    "iso:country":"US",
    "sg:address":"300 Helfer Ln",
    "sg:city":"Minoa",
    "sg:classifiers":[
        {
            "category":"Social Services",
            "type":"Services"
        }
    ],
    "sg:phone":"+1 315 656 3644",
    "sg:postcode":"13116",
    "sg:province":"NY",
    "wof:name":"Gateway Youth & Family Service",
    "wof:placetype":"venue"
},
  "geometry": {"coordinates":[-76.01329,43.080551],"type":"Point"}
}