{
  "type": "Feature",
  "properties": {
    "addr:full":"103 West 14th Street Manhattan NY 10011",
    "addr:housenumber":"103",
    "addr:postcode":"10011",
    "addr:street":"West 14Th Street",
    "iso:country":"US",
    "sg:address":"103 West 14th Street",
    "sg:city":"Manhattan",
    "sg:classifiers":[
        {
            "category":"Food & Beverages",
            "subcategory":"Groceries & Convenience Stores",
            "type":"Retail Goods"
        }
    ],
    "sg:phone":"+1 212 229 0711",
    "sg:postcode":"10011",
    "sg:province":"NY",
    "wof:name":"7-Eleven",
    "wof:placetype":"venue"
},
  "geometry": {"coordinates":[-73.997203,40.737857],"type":"Point"}
}