{
  "type": "Feature",
  "properties": {
    "addr:full":"584 W 207th St Manhattan NY 10034",
    "addr:housenumber":"584",
    "addr:postcode":"10034",
    "addr:street":"W 207Th St",
    "iso:country":"US",
    "sg:address":"584 W 207th St",
    "sg:city":"Manhattan",
    "sg:classifiers":[
        {
            "category":"Juice Bar",
            "subcategory":"None",
            "type":"Food & Drink"
        },
        {
            "category":"Food & Beverages",
            "subcategory":"Bakery",
            "type":"Retail Goods"
        }
    ],
    "sg:phone":"+1 212 567 6777",
    "sg:postcode":"10034",
    "sg:province":"NY",
    "sg:tags":[
        "smoothy",
        "sandwich"
    ],
    "sg:website":"www.quickfreshusa.com",
    "wof:name":"Quick Fresh",
    "wof:placetype":"venue"
},
  "geometry": {"coordinates":[-73.92074700000001,40.866909],"type":"Point"}
}