{
  "type": "Feature",
  "properties": {
    "iso:country":"US",
    "sg:address":"805 Rockland Ave",
    "sg:city":"Mamaroneck",
    "sg:classifiers":[
        {
            "category":"Building & Trades",
            "subcategory":"Landscaping Services",
            "type":"Services"
        }
    ],
    "sg:phone":"+1 914 381 1564",
    "sg:postcode":"10543",
    "sg:province":"NY",
    "wof:name":"Ron Vitti Turf & Landscaping",
    "wof:placetype":"venue"
},
  "geometry": {"coordinates":[-73.752814,40.948277],"type":"Point"}
}