{
  "type": "Feature",
  "properties": {
    "iso:country":"US",
    "sg:address":"2090 Honeywell Ave",
    "sg:city":"Bronx",
    "sg:classifiers":[
        {
            "category":"Health Services",
            "subcategory":"Doctor",
            "type":"Services"
        }
    ],
    "sg:phone":"+1 718 367 2221",
    "sg:postcode":"10460",
    "sg:province":"NY",
    "wof:name":"Iqbal Muhammad MD",
    "wof:placetype":"venue"
},
  "geometry": {"coordinates":[-73.882401,40.8447],"type":"Point"}
}