{
  "type": "Feature",
  "properties": {
    "addr:full":"20 E 46th Street Rm 903 New York NY 10017",
    "addr:housenumber":"20;903",
    "addr:postcode":"10017",
    "addr:street":"E 46Th Street Rm",
    "iso:country":"US",
    "sg:address":"20 E 46th Street Rm 903",
    "sg:city":"New York",
    "sg:classifiers":[
        {
            "category":"Building & Trades",
            "subcategory":"Construction",
            "type":"Services"
        }
    ],
    "sg:phone":"+1 212 856 9597",
    "sg:postcode":"10017",
    "sg:province":"NY",
    "sg:tags":[
        "contractor"
    ],
    "wof:name":"Federation Development Corporation",
    "wof:placetype":"venue"
},
  "geometry": {"coordinates":[-73.978405,40.755746],"type":"Point"}
}