{
  "type": "Feature",
  "properties": {
    "iso:country":"US",
    "sg:address":"116 Bayberry Ln",
    "sg:city":"New Rochelle",
    "sg:classifiers":[
        {
            "category":"Professional",
            "subcategory":"Engineering",
            "type":"Services"
        }
    ],
    "sg:phone":"+1   ",
    "sg:postcode":"10804",
    "sg:province":"NY",
    "wof:name":"Sph Designs Consulting Engr PC",
    "wof:placetype":"venue"
},
  "geometry": {"coordinates":[-73.772302,40.946691],"type":"Point"}
}