{
  "type": "Feature",
  "properties": {
    "iso:country":"US",
    "sg:address":"1293 Broadway",
    "sg:city":"New York",
    "sg:classifiers":[
        {
            "category":"Shopping",
            "subcategory":"Clothing, Apparel, & Fashions",
            "type":"Retail Goods"
        }
    ],
    "sg:phone":"+1 212 279 8758",
    "sg:postcode":"10001",
    "sg:province":"NY",
    "sg:tags":[
        "hat",
        "accessory"
    ],
    "sg:website":"www.hatandcapemporium.com/",
    "wof:name":"Hat & Cap Emporium",
    "wof:placetype":"venue"
},
  "geometry": {"coordinates":[-73.987996,40.749314],"type":"Point"}
}