{
  "type": "Feature",
  "properties": {
    "addr:full":"7212 New Utrecht Ave Brooklyn NY 11228",
    "addr:housenumber":"7212",
    "addr:postcode":"11228",
    "addr:street":"New Utrecht Ave",
    "iso:country":"US",
    "sg:address":"7212 New Utrecht Ave",
    "sg:city":"Brooklyn",
    "sg:classifiers":[
        {
            "category":"Retail",
            "subcategory":"Repair Shop",
            "type":"Services"
        }
    ],
    "sg:phone":"+1 718 887 3202",
    "sg:postcode":"11228",
    "sg:province":"NY",
    "sg:tags":[
        "lock",
        "locksmith"
    ],
    "wof:name":"24 Hour 7 Day Emerg Lcksmth",
    "wof:placetype":"venue"
},
  "geometry": {"coordinates":[-73.999398,40.618115],"type":"Point"}
}