{
  "type": "Feature",
  "properties": {
    "addr:full":"9 E 38th St New York NY 10016",
    "addr:housenumber":"9",
    "addr:postcode":"10016",
    "addr:street":"E 38Th St",
    "iso:country":"US",
    "sg:address":"9 E 38th St",
    "sg:city":"New York",
    "sg:classifiers":[
        {
            "category":"Professional",
            "type":"Services"
        }
    ],
    "sg:phone":"+1 212 481 8950",
    "sg:postcode":"10016",
    "sg:province":"NY",
    "sg:tags":[
        "establishment"
    ],
    "wof:name":"Brockway Associates",
    "wof:placetype":"venue"
},
  "geometry": {"coordinates":[-73.981692,40.750686],"type":"Point"}
}