{
  "type": "Feature",
  "properties": {
    "addr:full":"205 W Genesee St Fayetteville NY 13066",
    "addr:housenumber":"205",
    "addr:postcode":"13066",
    "addr:street":"W Genesee St",
    "iso:country":"US",
    "sg:address":"205 W Genesee St",
    "sg:city":"Fayetteville",
    "sg:classifiers":[
        {
            "category":"Restaurant",
            "type":"Food & Drink"
        }
    ],
    "sg:phone":"+1   ",
    "sg:postcode":"13066",
    "sg:province":"NY",
    "sg:tags":[
        "eating"
    ],
    "wof:name":"Da Vincis Trattoria",
    "wof:placetype":"venue"
},
  "geometry": {"coordinates":[-76.01676,43.029179],"type":"Point"}
}