{
  "type": "Feature",
  "properties": {
    "iso:country":"US",
    "sg:address":"203 Pinewood Cres",
    "sg:city":"Coram",
    "sg:classifiers":[
        {
            "category":"Real Estate",
            "subcategory":"Real Estate Operator",
            "type":"Services"
        }
    ],
    "sg:phone":"+1 631 696 5430",
    "sg:postcode":"11727",
    "sg:province":"NY",
    "sg:tags":[
        "apartment"
    ],
    "wof:name":"Pinewoods Estates",
    "wof:placetype":"venue"
},
  "geometry": {"coordinates":[-73.0047,40.878101],"type":"Point"}
}