{
  "type": "Feature",
  "properties": {
    "iso:country":"US",
    "sg:address":"1221 Ave of the Americas",
    "sg:city":"New York",
    "sg:classifiers":[
        {
            "category":"Organizations",
            "subcategory":"Professional Association",
            "type":"Services"
        }
    ],
    "sg:phone":"+1   ",
    "sg:postcode":"10020",
    "sg:province":"NY",
    "sg:tags":[
        "periodic",
        "business"
    ],
    "wof:name":"International Council of Shopp",
    "wof:placetype":"venue"
},
  "geometry": {"coordinates":[-73.980986,40.759244],"type":"Point"}
}