{
  "type": "Feature",
  "properties": {
    "addr:full":"11023 Rockaway Boulevard South Ozone Park NY 11420",
    "addr:housenumber":"11023",
    "addr:postcode":"11420",
    "addr:street":"Rockaway Boulevard",
    "iso:country":"US",
    "sg:address":"11023 Rockaway Boulevard",
    "sg:city":"South Ozone Park",
    "sg:classifiers":[
        {
            "category":"Professional",
            "subcategory":"Lawyer & Legal Services",
            "type":"Services"
        }
    ],
    "sg:phone":"+1 718 845 5840",
    "sg:postcode":"11420",
    "sg:province":"NY",
    "sg:website":"www.narainlawfirm.com",
    "wof:name":"Narain Law Firm PC",
    "wof:placetype":"venue"
},
  "geometry": {"coordinates":[-73.82783499999999,40.677697],"type":"Point"}
}