{
  "type": "Feature",
  "properties": {
    "iso:country":"US",
    "sg:address":"320 N Main St",
    "sg:city":"Jamestown",
    "sg:classifiers":[
        {
            "category":"Shopping",
            "subcategory":"Clothing, Apparel, & Fashions",
            "type":"Retail Goods"
        }
    ],
    "sg:phone":"+1   ",
    "sg:postcode":"14701",
    "sg:province":"NY",
    "sg:tags":[
        "shop",
        "bridal"
    ],
    "wof:name":"Bro Laines Bridal",
    "wof:placetype":"venue"
},
  "geometry": {"coordinates":[-79.241496,42.097055],"type":"Point"}
}