{
  "type": "Feature",
  "properties": {
    "addr:full":"420 5th Ave New York NY 10018",
    "addr:housenumber":"420",
    "addr:postcode":"10018",
    "addr:street":"5Th Ave",
    "iso:country":"US",
    "sg:address":"420 5th Ave",
    "sg:city":"New York",
    "sg:classifiers":[
        {
            "category":"Professional",
            "subcategory":"Lawyer & Legal Services",
            "type":"Services"
        }
    ],
    "sg:phone":"+1 212 751 1640",
    "sg:postcode":"10018",
    "sg:province":"NY",
    "sg:tags":[
        "attorney"
    ],
    "wof:name":"Michael G Dowd Law Offices",
    "wof:placetype":"venue"
},
  "geometry": {"coordinates":[-73.983081,40.750466],"type":"Point"}
}