{
  "type": "Feature",
  "properties": {
    "addr:full":"21 Picone Blvd Farmingdale NY 11735",
    "addr:housenumber":"21",
    "addr:postcode":"11735",
    "addr:street":"Picone Blvd",
    "iso:country":"US",
    "sg:address":"21 Picone Blvd",
    "sg:city":"Farmingdale",
    "sg:classifiers":[
        {
            "category":"Freight",
            "type":"Transportation"
        }
    ],
    "sg:phone":"+1   ",
    "sg:postcode":"11735",
    "sg:province":"NY",
    "sg:tags":[
        "operator",
        "trucking"
    ],
    "wof:name":"C C X",
    "wof:placetype":"venue"
},
  "geometry": {"coordinates":[-73.42201,40.742686],"type":"Point"}
}