{
  "type": "Feature",
  "properties": {
    "addr:full":"1280 Mount Read Blvd Rochester NY 14606",
    "addr:housenumber":"1280",
    "addr:postcode":"14606",
    "addr:street":"Mount Read",
    "iso:country":"US",
    "sg:address":"1280 Mount Read Blvd",
    "sg:city":"Rochester",
    "sg:classifiers":[
        {
            "category":"Building & Trades",
            "subcategory":"Construction",
            "type":"Services"
        }
    ],
    "sg:phone":"+1 585 647 1484",
    "sg:postcode":"14606",
    "sg:province":"NY",
    "sg:tags":[
        "contractor"
    ],
    "wof:name":"Comac Builders Supply",
    "wof:placetype":"venue"
},
  "geometry": {"coordinates":[-77.659098,43.179109],"type":"Point"}
}