{
  "type": "Feature",
  "properties": {
    "iso:country":"US",
    "sg:address":"200 W 146th Street",
    "sg:city":"New York",
    "sg:classifiers":[
        {
            "category":"Organizations",
            "subcategory":"Religious Organization",
            "type":"Services"
        }
    ],
    "sg:phone":"+1 212 281 7779",
    "sg:postcode":"10039",
    "sg:province":"NY",
    "wof:name":"Mesiah's Temple",
    "wof:placetype":"venue"
},
  "geometry": {"coordinates":[-73.938683,40.822328],"type":"Point"}
}