{
  "type": "Feature",
  "properties": {
    "addr:full":"267 N Main St Liberty NY 12754",
    "addr:housenumber":"267",
    "addr:postcode":"12754",
    "addr:street":"N Main St",
    "iso:country":"US",
    "sg:address":"267 N Main St",
    "sg:city":"Liberty",
    "sg:classifiers":[
        {
            "category":"Professional",
            "type":"Services"
        }
    ],
    "sg:phone":"+1 845 292 7535",
    "sg:postcode":"12754",
    "sg:province":"NY",
    "sg:tags":[
        "establishment"
    ],
    "wof:name":"Thunder",
    "wof:placetype":"venue"
},
  "geometry": {"coordinates":[-74.747089,41.80176],"type":"Point"}
}