{
  "type": "Feature",
  "properties": {
    "iso:country":"US",
    "sg:address":"122 W Graham Ave",
    "sg:city":"Hempstead",
    "sg:classifiers":[
        {
            "category":"Building & Trades",
            "subcategory":"Construction",
            "type":"Services"
        }
    ],
    "sg:phone":"+1 516 485 3642",
    "sg:postcode":"11550",
    "sg:province":"NY",
    "sg:tags":[
        "siding",
        "contractor"
    ],
    "wof:name":"Best Deal Home Improvements",
    "wof:placetype":"venue"
},
  "geometry": {"coordinates":[-73.628192,40.695431],"type":"Point"}
}