{
  "type": "Feature",
  "properties": {
    "iso:country":"US",
    "sg:address":"9 County Route 17",
    "sg:city":"Russell",
    "sg:classifiers":[
        {
            "category":"Retail",
            "subcategory":"Auto Repair",
            "type":"Services"
        }
    ],
    "sg:phone":"+1 315 347 3694",
    "sg:postcode":"13684",
    "sg:province":"NY",
    "sg:tags":[
        "body",
        "painting",
        "repairing",
        "automobile"
    ],
    "wof:name":"Carlin, Ron's Auto Repairing & Painting",
    "wof:placetype":"venue"
},
  "geometry": {"coordinates":[-75.08224,44.348989],"type":"Point"}
}