{
  "type": "Feature",
  "properties": {
    "iso:country":"US",
    "sg:address":"32 Montauk Hwy",
    "sg:city":"Southampton",
    "sg:classifiers":[
        {
            "category":"Restaurant",
            "type":"Food & Drink"
        }
    ],
    "sg:phone":"+1 631 283 4255",
    "sg:postcode":"11968",
    "sg:province":"NY",
    "wof:name":"Southampton Princess Diner",
    "wof:placetype":"venue"
},
  "geometry": {"coordinates":[-72.426483,40.884731],"type":"Point"}
}