{
  "type": "Feature",
  "properties": {
    "iso:country":"US",
    "sg:address":"1456 Saunders Settlement Rd",
    "sg:city":"Niagara Falls",
    "sg:classifiers":[
        {
            "category":"Education",
            "subcategory":"School",
            "type":"Public Place"
        }
    ],
    "sg:phone":"+1 716 215 3270",
    "sg:postcode":"14305",
    "sg:province":"NY",
    "wof:name":"Colonial Village School",
    "wof:placetype":"venue"
},
  "geometry": {"coordinates":[-78.994675,43.134941],"type":"Point"}
}