{
  "type": "Feature",
  "properties": {
    "iso:country":"US",
    "sg:address":"49 Holiday Pond Rd",
    "sg:city":"Jericho",
    "sg:classifiers":[
        {
            "category":"Health Services",
            "subcategory":"Doctor",
            "type":"Services"
        }
    ],
    "sg:phone":"+1 516 938 1978",
    "sg:postcode":"11753",
    "sg:province":"NY",
    "sg:tags":[
        "medicine",
        "physician",
        "practice",
        "surgeons",
        "family"
    ],
    "wof:name":"Zhu-Ping Zhou, M.D., P.C.",
    "wof:placetype":"venue"
},
  "geometry": {"coordinates":[-73.545103,40.790944],"type":"Point"}
}