{
  "type": "Feature",
  "properties": {
    "iso:country":"US",
    "sg:address":"3491 Harlem Rd",
    "sg:city":"Cheektowaga",
    "sg:classifiers":[
        {
            "category":"Insurance",
            "subcategory":"Insurance Agent",
            "type":"Services"
        }
    ],
    "sg:phone":"+1 716 832 6148",
    "sg:postcode":"14225",
    "sg:province":"NY",
    "wof:name":"Allstate Insurance Co",
    "wof:placetype":"venue"
},
  "geometry": {"coordinates":[-78.784024,42.938911],"type":"Point"}
}