{
  "type": "Feature",
  "properties": {
    "addr:full":"22 W Main St Frewsburg NY 14738",
    "addr:housenumber":"22",
    "addr:postcode":"14738",
    "addr:street":"W Main St",
    "iso:country":"US",
    "sg:address":"22 W Main St",
    "sg:city":"Frewsburg",
    "sg:classifiers":[
        {
            "category":"Shopping",
            "subcategory":"News",
            "type":"Retail Goods"
        }
    ],
    "sg:phone":"+1 716 569 6705",
    "sg:postcode":"14738",
    "sg:province":"NY",
    "sg:tags":[
        "dealer"
    ],
    "wof:name":"Frewsburg News Room",
    "wof:placetype":"venue"
},
  "geometry": {"coordinates":[-79.15994000000001,42.052815],"type":"Point"}
}