{
  "type": "Feature",
  "properties": {
    "addr:full":"180 Varick St New York NY 10014",
    "addr:housenumber":"180",
    "addr:postcode":"10014",
    "addr:street":"Varick St",
    "iso:country":"US",
    "sg:address":"180 Varick St",
    "sg:city":"New York",
    "sg:classifiers":[
        {
            "category":"Professional",
            "type":"Services"
        },
        {
            "category":"Real Estate",
            "subcategory":"Real Estate Agent",
            "type":"Services"
        }
    ],
    "sg:phone":"+1 212 741 3831",
    "sg:postcode":"10014",
    "sg:province":"NY",
    "sg:tags":[
        "holding",
        "restaurant"
    ],
    "wof:name":"180 Varick Street",
    "wof:placetype":"venue"
},
  "geometry": {"coordinates":[-74.005301,40.727438],"type":"Point"}
}