{
  "type": "Feature",
  "properties": {
    "iso:country":"US",
    "sg:address":"767 Mineral Springs Rd",
    "sg:city":"Buffalo",
    "sg:classifiers":[
        {
            "category":"Health Services",
            "subcategory":"Chiropractor",
            "type":"Services"
        }
    ],
    "sg:phone":"+1 716 823 1343",
    "sg:postcode":"14224",
    "sg:province":"NY",
    "wof:name":"Mineral Springs Chiropractic",
    "wof:placetype":"venue"
},
  "geometry": {"coordinates":[-78.78679700000001,42.864498],"type":"Point"}
}