{
  "type": "Feature",
  "properties": {
    "addr:full":"975 Siems Ct North Bellmore NY 11710",
    "addr:housenumber":"975",
    "addr:postcode":"11710",
    "addr:street":"Siems Ct North",
    "iso:country":"US",
    "sg:address":"975 Siems Ct",
    "sg:city":"North Bellmore",
    "sg:classifiers":[
        {
            "category":"Professional",
            "subcategory":"Lawyer & Legal Services",
            "type":"Services"
        }
    ],
    "sg:phone":"+1 516 785 3667",
    "sg:postcode":"11710",
    "sg:province":"NY",
    "wof:name":"Robert Saldarelli Attorney At Law",
    "wof:placetype":"venue"
},
  "geometry": {"coordinates":[-73.540282,40.698357],"type":"Point"}
}