{
  "type": "Feature",
  "properties": {
    "addr:full":"661 Burnside Ave Lawrence NY 11559",
    "addr:housenumber":"661",
    "addr:postcode":"11559",
    "addr:street":"Burnside Ave",
    "iso:country":"US",
    "sg:address":"661 Burnside Ave",
    "sg:city":"Lawrence",
    "sg:classifiers":[
        {
            "category":"Retail",
            "subcategory":"Auto Repair",
            "type":"Services"
        }
    ],
    "sg:phone":"+1 718 227 4357",
    "sg:postcode":"11559",
    "sg:province":"NY",
    "wof:name":"County Auto Repair",
    "wof:placetype":"venue"
},
  "geometry": {"coordinates":[-73.73840300000001,40.623299],"type":"Point"}
}