{
  "type": "Feature",
  "properties": {
    "addr:full":"132 Atlantic Ave West Sayville NY 11796",
    "addr:housenumber":"132",
    "addr:postcode":"11796",
    "addr:street":"Atlantic Ave West",
    "iso:country":"US",
    "sg:address":"132 Atlantic Ave",
    "sg:city":"West Sayville",
    "sg:classifiers":[
        {
            "category":"Manufacturing",
            "subcategory":"Building Materials",
            "type":"Manufacturing & Wholesale Goods"
        },
        {
            "category":"Manufacturing",
            "subcategory":"Rubber & Plastics",
            "type":"Manufacturing & Wholesale Goods"
        }
    ],
    "sg:phone":"+1 631 589 2199",
    "sg:postcode":"11796",
    "sg:province":"NY",
    "sg:tags":[
        "eating"
    ],
    "wof:name":"Fire Island Sea Clam Co Inc",
    "wof:placetype":"venue"
},
  "geometry": {"coordinates":[-73.09226099999999,40.72172],"type":"Point"}
}