{
  "type": "Feature",
  "properties": {
    "addr:full":"450 7th Ave Ste 800 New York NY 10123",
    "addr:housenumber":"450;800",
    "addr:postcode":"10123",
    "addr:street":"7Th Ave Ste",
    "iso:country":"US",
    "sg:address":"450 7th Ave Ste 800",
    "sg:city":"New York",
    "sg:classifiers":[
        {
            "category":"Health Services",
            "subcategory":"Dentist",
            "type":"Services"
        }
    ],
    "sg:phone":"+1 212 695 2173",
    "sg:postcode":"10123",
    "sg:province":"NY",
    "sg:website":"www.ngdentalgallery.com",
    "wof:name":"Natalie Gor, DDS",
    "wof:placetype":"venue"
},
  "geometry": {"coordinates":[-73.99064199999999,40.751384],"type":"Point"}
}