{
  "type": "Feature",
  "properties": {
    "iso:country":"US",
    "sg:address":"327 W Fayette St",
    "sg:city":"Syracuse",
    "sg:classifiers":[
        {
            "category":"Health Services",
            "subcategory":"Doctor",
            "type":"Services"
        }
    ],
    "sg:phone":"+1 315 422 7699",
    "sg:postcode":"13202",
    "sg:province":"NY",
    "sg:tags":[
        "physician",
        "surgeon"
    ],
    "wof:name":"John Tanquary MD",
    "wof:placetype":"venue"
},
  "geometry": {"coordinates":[-76.156243,43.048632],"type":"Point"}
}