{
  "type": "Feature",
  "properties": {
    "iso:country":"US",
    "sg:address":"38 Cain Dr",
    "sg:city":"Brentwood",
    "sg:classifiers":[
        {
            "category":"Building & Trades",
            "subcategory":"Plumbing",
            "type":"Services"
        }
    ],
    "sg:phone":"+1 631 273 2602",
    "sg:postcode":"11717",
    "sg:province":"NY",
    "sg:tags":[
        "ventilation",
        "air",
        "heating",
        "conditioning",
        "contractor"
    ],
    "wof:name":"Alpine Mechanical Systems Inc",
    "wof:placetype":"venue"
},
  "geometry": {"coordinates":[-73.24809500000001,40.806791],"type":"Point"}
}