{
  "type": "Feature",
  "properties": {
    "iso:country":"US",
    "sg:address":"350 Power Ave",
    "sg:city":"Hudson",
    "sg:classifiers":[
        {
            "category":"Wholesale",
            "subcategory":"Photographic Equipment",
            "type":"Manufacturing & Wholesale Goods"
        }
    ],
    "sg:phone":"+1 518 822 8800",
    "sg:postcode":"12534",
    "sg:province":"NY",
    "sg:tags":[
        "audio"
    ],
    "sg:website":"www.rivercable.com",
    "wof:name":"River Cable",
    "wof:placetype":"venue"
},
  "geometry": {"coordinates":[-73.79329799999999,42.247828],"type":"Point"}
}