{
  "type": "Feature",
  "properties": {
    "iso:country":"US",
    "sg:address":"13 Oak St",
    "sg:city":"Hamilton",
    "sg:classifiers":[
        {
            "category":"Education",
            "subcategory":"College",
            "type":"Public Place"
        }
    ],
    "sg:phone":"+1 315 228 1000",
    "sg:postcode":"13329",
    "sg:province":"NY",
    "sg:tags":[
        "university"
    ],
    "wof:name":"SEVEN OAKS GOLF COURSE",
    "wof:placetype":"venue"
},
  "geometry": {"coordinates":[-74.77459399999999,43.103624],"type":"Point"}
}