{
  "type": "Feature",
  "properties": {
    "iso:country":"US",
    "sg:address":"308-310 Oneida St",
    "sg:city":"Fulton",
    "sg:classifiers":[
        {
            "category":"Retail",
            "subcategory":"Repair Shop",
            "type":"Services"
        },
        {
            "category":"Shopping",
            "subcategory":"Computers & Home Electronics",
            "type":"Retail Goods"
        },
        {
            "category":"Wholesale",
            "subcategory":"Office Equipment",
            "type":"Manufacturing & Wholesale Goods"
        },
        {
            "category":"Professional",
            "subcategory":"Printing & Photocopies",
            "type":"Services"
        },
        {
            "category":"Shopping",
            "subcategory":"Stationery & Office Supplies",
            "type":"Retail Goods"
        },
        {
            "category":"Professional",
            "subcategory":"Advertising",
            "type":"Services"
        }
    ],
    "sg:phone":"+1 315 350 3978",
    "sg:postcode":"13069",
    "sg:province":"NY",
    "sg:tags":[
        "product",
        "clock",
        "equipment-repairing",
        "machine",
        "time",
        "advertising-promotional",
        "copy",
        "recorder",
        "furniture"
    ],
    "sg:website":"http://www.fts-inc.com",
    "wof:name":"FTS Office Discounters",
    "wof:placetype":"venue"
},
  "geometry": {"coordinates":[-76.414404,43.325415],"type":"Point"}
}