{
  "type": "Feature",
  "properties": {
    "addr:full":"2008 North St Endicott NY 13760",
    "addr:housenumber":"2008",
    "addr:postcode":"13760",
    "addr:street":"North St",
    "iso:country":"US",
    "sg:address":"2008 North St",
    "sg:city":"Endicott",
    "sg:classifiers":[
        {
            "category":"Autos & Motor Vehicles",
            "subcategory":"Automobile Sales",
            "type":"Retail Goods"
        }
    ],
    "sg:phone":"+1 607 748 9603",
    "sg:postcode":"13760",
    "sg:province":"NY",
    "sg:tags":[
        "car",
        "dealer"
    ],
    "wof:name":"Roma's Auto",
    "wof:placetype":"venue"
},
  "geometry": {"coordinates":[-76.038904,42.106412],"type":"Point"}
}