{
  "type": "Feature",
  "properties": {
    "iso:country":"US",
    "sg:address":"188 Ave B",
    "sg:city":"New York",
    "sg:classifiers":[
        {
            "category":"Bars & Pubs",
            "type":"Food & Drink"
        },
        {
            "category":"Restaurant",
            "type":"Food & Drink"
        },
        {
            "category":"Arts & Performance",
            "subcategory":"Jazz & Blues",
            "type":"Entertainment"
        }
    ],
    "sg:phone":"+1 212 358 1700",
    "sg:postcode":"10009",
    "sg:province":"NY",
    "sg:tags":[
        "brasserie"
    ],
    "sg:website":"www.ruebnyc.com",
    "wof:name":"Rue B",
    "wof:placetype":"venue"
},
  "geometry": {"coordinates":[-73.979417,40.727956],"type":"Point"}
}