{
  "type": "Feature",
  "properties": {
    "iso:country":"US",
    "sg:address":"1801 Dorchester Rd",
    "sg:city":"Brooklyn",
    "sg:classifiers":[
        {
            "category":"Organizations",
            "subcategory":"Membership Organization",
            "type":"Services"
        }
    ],
    "sg:phone":"+1 718 856 8067",
    "sg:postcode":"11226",
    "sg:province":"NY",
    "wof:name":"United Cerebral Palsy",
    "wof:placetype":"venue"
},
  "geometry": {"coordinates":[-73.96050099999999,40.64094],"type":"Point"}
}