{
  "type": "Feature",
  "properties": {
    "iso:country":"US",
    "sg:address":"131 Sullivan St",
    "sg:city":"Wurtsboro",
    "sg:classifiers":[
        {
            "category":"Professional",
            "subcategory":"Lawyer & Legal Services",
            "type":"Services"
        }
    ],
    "sg:phone":"+1 845 888 2259",
    "sg:postcode":"12790",
    "sg:province":"NY",
    "sg:tags":[
        "attorney"
    ],
    "wof:name":"Robert Lander",
    "wof:placetype":"venue"
},
  "geometry": {"coordinates":[-74.478014,41.572401],"type":"Point"}
}