{
  "type": "Feature",
  "properties": {
    "addr:full":"2344 Davidson Ave Bronx NY 10468",
    "addr:housenumber":"2344",
    "addr:postcode":"10468",
    "addr:street":"Davidson Ave",
    "iso:country":"US",
    "sg:address":"2344 Davidson Ave",
    "sg:city":"Bronx",
    "sg:classifiers":[
        {
            "category":"Shopping",
            "subcategory":"Discount & Variety Stores",
            "type":"Retail Goods"
        }
    ],
    "sg:phone":"+1 718 220 2671",
    "sg:postcode":"10468",
    "sg:province":"NY",
    "sg:tags":[
        "millinery",
        "supply"
    ],
    "wof:name":"Fitted Bronx",
    "wof:placetype":"venue"
},
  "geometry": {"coordinates":[-73.904116,40.859935],"type":"Point"}
}