{
  "type": "Feature",
  "properties": {
    "iso:country":"US",
    "sg:address":"446 Alexander St",
    "sg:city":"Rochester",
    "sg:classifiers":[
        {
            "category":"Real Estate",
            "subcategory":"Real Estate Agent",
            "type":"Services"
        }
    ],
    "sg:phone":"+1 585 232 6690",
    "sg:postcode":"14605",
    "sg:province":"NY",
    "wof:name":"Serino Realty Target Realty",
    "wof:placetype":"venue"
},
  "geometry": {"coordinates":[-77.591695,43.160607],"type":"Point"}
}