{
  "type": "Feature",
  "properties": {
    "addr:full":"556 Tompkins Ave Staten Island NY 10305",
    "addr:housenumber":"556",
    "addr:postcode":"10305",
    "addr:street":"Tompkins Ave",
    "iso:country":"US",
    "sg:address":"556 Tompkins Ave",
    "sg:city":"Staten Island",
    "sg:classifiers":[
        {
            "category":"Restaurant",
            "type":"Food & Drink"
        }
    ],
    "sg:phone":"+1 718 524 0790",
    "sg:postcode":"10305",
    "sg:province":"NY",
    "sg:tags":[
        "filipino"
    ],
    "wof:name":"Island's Grand Grill",
    "wof:placetype":"venue"
},
  "geometry": {"coordinates":[-74.071322,40.612609],"type":"Point"}
}