{
  "type": "Feature",
  "properties": {
    "iso:country":"US",
    "sg:address":"13 Border St",
    "sg:city":"Hicksville",
    "sg:classifiers":[
        {
            "category":"Social Services",
            "type":"Services"
        }
    ],
    "sg:phone":"+1 516 433 8600",
    "sg:postcode":"11801",
    "sg:province":"NY",
    "sg:tags":[
        "counseling"
    ],
    "wof:name":"Korean Family Counseling",
    "wof:placetype":"venue"
},
  "geometry": {"coordinates":[-73.540854,40.76036],"type":"Point"}
}