{
  "type": "Feature",
  "properties": {
    "iso:country":"US",
    "sg:address":"114 Oneida St",
    "sg:city":"Fulton",
    "sg:classifiers":[
        {
            "category":"Banks & Credit Unions",
            "subcategory":"Bank",
            "type":"Services"
        },
        {
            "category":"Banks & Credit Unions",
            "subcategory":"Financial Services",
            "type":"Services"
        }
    ],
    "sg:phone":"+1 315 592 9545",
    "sg:postcode":"13069",
    "sg:province":"NY",
    "sg:tags":[
        "commercial",
        "loan",
        "saving"
    ],
    "wof:name":"Pathfinder Bank",
    "wof:placetype":"venue"
},
  "geometry": {"coordinates":[-76.417575,43.325045],"type":"Point"}
}