{
  "type": "Feature",
  "properties": {
    "addr:full":"1 Keller Ave Buffalo NY 14217",
    "addr:postcode":"14217",
    "addr:street":"Keller Ave",
    "iso:country":"US",
    "sg:address":"1 Keller Ave",
    "sg:city":"Buffalo",
    "sg:classifiers":[
        {
            "category":"Shopping",
            "subcategory":"Clothing, Apparel, & Fashions",
            "type":"Retail Goods"
        }
    ],
    "sg:phone":"+1   ",
    "sg:postcode":"14217",
    "sg:province":"NY",
    "wof:name":"Victorias Secret",
    "wof:placetype":"venue"
},
  "geometry": {"coordinates":[-78.882008,42.961341],"type":"Point"}
}