{
  "type": "Feature",
  "properties": {
    "addr:full":"15 Catherwood Rd Ithaca NY 14850",
    "addr:housenumber":"15",
    "addr:postcode":"14850",
    "addr:street":"Catherwood Rd",
    "iso:country":"US",
    "sg:address":"15 Catherwood Rd",
    "sg:city":"Ithaca",
    "sg:classifiers":[
        {
            "category":"Restaurant",
            "type":"Food & Drink"
        }
    ],
    "sg:menulink":"http://www.allmenus.com/ny/lansing/148460-subway/menu/",
    "sg:phone":"+1 607 257 1234",
    "sg:postcode":"14850",
    "sg:province":"NY",
    "sg:tags":[
        "american",
        "sandwich"
    ],
    "wof:name":"Subway",
    "wof:placetype":"venue"
},
  "geometry": {"coordinates":[-76.48755800000001,42.484386],"type":"Point"}
}