{
  "type": "Feature",
  "properties": {
    "iso:country":"US",
    "sg:address":"3074 US Hwy 9w",
    "sg:city":"New Windsor",
    "sg:classifiers":[
        {
            "category":"Health Services",
            "subcategory":"Doctor",
            "type":"Services"
        }
    ],
    "sg:phone":"+1 845 561 8902",
    "sg:postcode":"12553",
    "sg:province":"NY",
    "sg:tags":[
        "dentist"
    ],
    "wof:name":"Jose M Perez DDS",
    "wof:placetype":"venue"
},
  "geometry": {"coordinates":[-74.021917,41.461004],"type":"Point"}
}