{
  "type": "Feature",
  "properties": {
    "addr:full":"8353 E Main Rd Le Roy NY 14482",
    "addr:housenumber":"8353",
    "addr:postcode":"14482",
    "addr:street":"E Main Rd",
    "iso:country":"US",
    "sg:address":"8353 E Main Rd",
    "sg:city":"Le Roy",
    "sg:classifiers":[
        {
            "category":"Building & Trades",
            "subcategory":"Construction",
            "type":"Services"
        }
    ],
    "sg:phone":"+1 585 768 7021",
    "sg:postcode":"14482",
    "sg:province":"NY",
    "sg:tags":[
        "designer",
        "dealer",
        "pool",
        "swimming"
    ],
    "wof:name":"Splash Pools",
    "wof:placetype":"venue"
},
  "geometry": {"coordinates":[-77.93341599999999,42.979287],"type":"Point"}
}