{
  "type": "Feature",
  "properties": {
    "iso:country":"US",
    "sg:address":"6279 State Hwy 36",
    "sg:city":"Hornell",
    "sg:classifiers":[
        {
            "category":"Real Estate",
            "subcategory":"Surveying",
            "type":"Services"
        }
    ],
    "sg:phone":"+1 607 324 6446",
    "sg:postcode":"14843",
    "sg:province":"NY",
    "sg:tags":[
        "surveyor"
    ],
    "sg:website":"www.hubertussurvey.com",
    "wof:name":"Stephen J Hubertus Land Survey",
    "wof:placetype":"venue"
},
  "geometry": {"coordinates":[-77.658278,42.30771],"type":"Point"}
}