{
  "type": "Feature",
  "properties": {
    "iso:country":"US",
    "sg:address":"12663 37th Ave",
    "sg:city":"Corona",
    "sg:classifiers":[
        {
            "category":"Retail",
            "subcategory":"Auto Repair",
            "type":"Services"
        }
    ],
    "sg:phone":"+1 718 396 9660",
    "sg:postcode":"11368",
    "sg:province":"NY",
    "wof:name":"C V Auto Repair",
    "wof:placetype":"venue"
},
  "geometry": {"coordinates":[-73.84233999999999,40.758397],"type":"Point"}
}