{
  "type": "Feature",
  "properties": {
    "addr:full":"232 Madison Ave New York NY 10016",
    "addr:housenumber":"232",
    "addr:postcode":"10016",
    "addr:street":"Madison Ave",
    "iso:country":"US",
    "sg:address":"232 Madison Ave",
    "sg:city":"New York",
    "sg:classifiers":[
        {
            "category":"Professional",
            "subcategory":"Detective & Security Services",
            "type":"Services"
        }
    ],
    "sg:phone":"+1 212 683 6020",
    "sg:postcode":"10016",
    "sg:province":"NY",
    "sg:tags":[
        "guard",
        "patrol"
    ],
    "wof:name":"Domnick G Riley Detective Bur",
    "wof:placetype":"venue"
},
  "geometry": {"coordinates":[-73.981123,40.750282],"type":"Point"}
}