{
  "type": "Feature",
  "properties": {
    "iso:country":"US",
    "sg:address":"1081 Old Country Rd",
    "sg:city":"Riverhead",
    "sg:classifiers":[
        {
            "category":"Shopping",
            "subcategory":"Computers & Home Electronics",
            "type":"Retail Goods"
        }
    ],
    "sg:phone":"+1   ",
    "sg:postcode":"11901",
    "sg:province":"NY",
    "wof:name":"Radio Shack",
    "wof:placetype":"venue"
},
  "geometry": {"coordinates":[-72.67905399999999,40.930188],"type":"Point"}
}