{
  "type": "Feature",
  "properties": {
    "addr:full":"2818 Steinway St Ste 302 Astoria NY 11103",
    "addr:housenumber":"2818",
    "addr:postcode":"11103",
    "addr:street":"Steinway St Ste 302",
    "iso:country":"US",
    "sg:address":"2818 Steinway St Ste 302",
    "sg:city":"Astoria",
    "sg:classifiers":[
        {
            "category":"Health Services",
            "subcategory":"Clinic",
            "type":"Services"
        }
    ],
    "sg:phone":"+1 718 278 3809",
    "sg:postcode":"11103",
    "sg:province":"NY",
    "sg:tags":[
        "outpatient"
    ],
    "wof:name":"Psch Inc",
    "wof:placetype":"venue"
},
  "geometry": {"coordinates":[-73.91382,40.765328],"type":"Point"}
}