{
  "type": "Feature",
  "properties": {
    "iso:country":"US",
    "sg:address":"15 Maple Ave",
    "sg:city":"Sidney",
    "sg:classifiers":[
        {
            "category":"Building & Trades",
            "subcategory":"Plumbing",
            "type":"Services"
        }
    ],
    "sg:phone":"+1 607 563 1192",
    "sg:postcode":"13838",
    "sg:province":"NY",
    "sg:tags":[
        "plumber",
        "industrial",
        "contractors-commercial"
    ],
    "wof:name":"Storey Plumbing Heating & Refrigeration",
    "wof:placetype":"venue"
},
  "geometry": {"coordinates":[-75.391159,42.318459],"type":"Point"}
}