{
  "type": "Feature",
  "properties": {
    "addr:full":"422 Bedford Ave Bellmore NY 11710",
    "addr:housenumber":"422",
    "addr:postcode":"11710",
    "addr:street":"Bedford Ave",
    "iso:country":"US",
    "sg:address":"422 Bedford Ave",
    "sg:city":"Bellmore",
    "sg:classifiers":[
        {
            "category":"Professional",
            "type":"Services"
        }
    ],
    "sg:phone":"+1 516 783 8000",
    "sg:postcode":"11710",
    "sg:province":"NY",
    "sg:tags":[
        "establishment"
    ],
    "wof:name":"Private",
    "wof:placetype":"venue"
},
  "geometry": {"coordinates":[-73.526742,40.66741],"type":"Point"}
}