{
  "type": "Feature",
  "properties": {
    "addr:full":"22 Ridge St Glens Falls NY 12801",
    "addr:housenumber":"22",
    "addr:postcode":"12801",
    "addr:street":"Ridge St",
    "iso:country":"US",
    "sg:address":"22 Ridge St",
    "sg:city":"Glens Falls",
    "sg:classifiers":[
        {
            "category":"Restaurant",
            "type":"Food & Drink"
        }
    ],
    "sg:phone":"+1   ",
    "sg:postcode":"12801",
    "sg:province":"NY",
    "sg:tags":[
        "delicatessen"
    ],
    "wof:name":"Butcher Block Delicatessen",
    "wof:placetype":"venue"
},
  "geometry": {"coordinates":[-73.643956,43.310411],"type":"Point"}
}