{
  "type": "Feature",
  "properties": {
    "iso:country":"US",
    "sg:address":"300 E 91st St",
    "sg:city":"New York",
    "sg:classifiers":[
        {
            "category":"Retail",
            "subcategory":"Laundry & Dry Cleaning",
            "type":"Services"
        }
    ],
    "sg:phone":"+1 212 722 0024",
    "sg:postcode":"10128",
    "sg:province":"NY",
    "wof:name":"Apple Dry Cleaners",
    "wof:placetype":"venue"
},
  "geometry": {"coordinates":[-73.94940099999999,40.781051],"type":"Point"}
}