{
  "type": "Feature",
  "properties": {
    "iso:country":"US",
    "sg:address":"4820 State Hwy 414",
    "sg:city":"Burdett",
    "sg:classifiers":[
        {
            "category":"Real Estate",
            "subcategory":"Real Estate Agent",
            "type":"Services"
        }
    ],
    "sg:phone":"+1 607 546 6010",
    "sg:postcode":"14818",
    "sg:province":"NY",
    "sg:tags":[
        "agency",
        "rental"
    ],
    "wof:name":"Carl's Rent All",
    "wof:placetype":"venue"
},
  "geometry": {"coordinates":[-76.865566,42.462694],"type":"Point"}
}