{
  "type": "Feature",
  "properties": {
    "addr:full":"506 W Old Country Rd Hicksville NY 11801",
    "addr:housenumber":"506",
    "addr:postcode":"11801",
    "addr:street":"W Old Country Rd",
    "iso:country":"US",
    "sg:address":"506 W Old Country Rd",
    "sg:city":"Hicksville",
    "sg:classifiers":[
        {
            "category":"Autos & Motor Vehicles",
            "subcategory":"Automobile Sales",
            "type":"Retail Goods"
        }
    ],
    "sg:phone":"+1 516 931 1131",
    "sg:postcode":"11801",
    "sg:province":"NY",
    "sg:tags":[
        "used"
    ],
    "wof:name":"Lemon Auto Sales",
    "wof:placetype":"venue"
},
  "geometry": {"coordinates":[-73.54324200000001,40.757915],"type":"Point"}
}