{
  "type": "Feature",
  "properties": {
    "iso:country":"US",
    "sg:address":"2 S Platt St",
    "sg:city":"Plattsburgh",
    "sg:classifiers":[
        {
            "category":"Government",
            "subcategory":"Fire Station",
            "type":"Public Place"
        }
    ],
    "sg:phone":"+1 518 561 2466",
    "sg:postcode":"12901",
    "sg:province":"NY",
    "sg:tags":[
        "department"
    ],
    "wof:name":"Plattsburgh Fire Station",
    "wof:placetype":"venue"
},
  "geometry": {"coordinates":[-73.45832,44.687348],"type":"Point"}
}