{
  "type": "Feature",
  "properties": {
    "iso:country":"US",
    "sg:address":"135 Co Rd 128",
    "sg:city":"Johnstown",
    "sg:classifiers":[
        {
            "category":"Shopping",
            "subcategory":"Optical Goods",
            "type":"Retail Goods"
        }
    ],
    "sg:phone":"+1   ",
    "sg:postcode":"12095",
    "sg:province":"NY",
    "wof:name":"Eyewear Boutique",
    "wof:placetype":"venue"
},
  "geometry": {"coordinates":[-74.345663,43.027214],"type":"Point"}
}