{
  "type": "Feature",
  "properties": {
    "addr:full":"144 Toledo St Farmingdale NY 11735",
    "addr:housenumber":"144",
    "addr:postcode":"11735",
    "addr:street":"Toledo St",
    "iso:country":"US",
    "sg:address":"144 Toledo St",
    "sg:city":"Farmingdale",
    "sg:classifiers":[
        {
            "category":"Manufacturing",
            "subcategory":"Rubber & Plastics",
            "type":"Manufacturing & Wholesale Goods"
        }
    ],
    "sg:phone":"+1   ",
    "sg:postcode":"11735",
    "sg:province":"NY",
    "sg:tags":[
        "product",
        "mfg"
    ],
    "wof:name":"Konrad Design",
    "wof:placetype":"venue"
},
  "geometry": {"coordinates":[-73.41506099999999,40.712289],"type":"Point"}
}