{
  "type": "Feature",
  "properties": {
    "addr:full":"146 Wilson Avenue Brooklyn NY 11237",
    "addr:housenumber":"146",
    "addr:postcode":"11237",
    "addr:street":"Wilson Avenue",
    "iso:country":"US",
    "sg:address":"146 Wilson Avenue",
    "sg:city":"Brooklyn",
    "sg:classifiers":[
        {
            "category":"Personal",
            "subcategory":"Barber",
            "type":"Services"
        }
    ],
    "sg:phone":"+1 718 417 3443",
    "sg:postcode":"11237",
    "sg:province":"NY",
    "wof:name":"Al's Barbershop",
    "wof:placetype":"venue"
},
  "geometry": {"coordinates":[-73.925369,40.700449],"type":"Point"}
}