{
  "type": "Feature",
  "properties": {
    "addr:full":"1085 Middle Country Rd Middle Island NY 11953",
    "addr:housenumber":"1085",
    "addr:postcode":"11953",
    "addr:street":"Middle Country Rd Middle Island",
    "iso:country":"US",
    "sg:address":"1085 Middle Country Rd",
    "sg:city":"Middle Island",
    "sg:classifiers":[
        {
            "category":"Shopping",
            "subcategory":"Discount & Variety Stores",
            "type":"Retail Goods"
        }
    ],
    "sg:phone":"+1   ",
    "sg:postcode":"11953",
    "sg:province":"NY",
    "wof:name":"Only 99 Cent Store",
    "wof:placetype":"venue"
},
  "geometry": {"coordinates":[-72.93496399999999,40.884867],"type":"Point"}
}