{
  "type": "Feature",
  "properties": {
    "addr:full":"1708 Montauk Hwy Mastic NY 11950",
    "addr:housenumber":"1708",
    "addr:postcode":"11950",
    "addr:street":"Montauk Hwy",
    "iso:country":"US",
    "sg:address":"1708 Montauk Hwy",
    "sg:city":"Mastic",
    "sg:phone":"+1 631 281 6543",
    "sg:postcode":"11950",
    "sg:province":"NY",
    "wof:name":"Movieland Of Mastic",
    "wof:placetype":"venue"
},
  "geometry": {"coordinates":[-72.83394199999999,40.806234],"type":"Point"}
}