{
  "type": "Feature",
  "properties": {
    "iso:country":"US",
    "sg:address":"8521 Dake Hill Rd",
    "sg:city":"Cattaraugus",
    "sg:classifiers":[
        {
            "category":"Farming",
            "subcategory":"Dairy Farm",
            "type":"Manufacturing & Wholesale Goods"
        }
    ],
    "sg:phone":"+1 716 257 3565",
    "sg:postcode":"14719",
    "sg:province":"NY",
    "wof:name":"Bu T Vu Dairy Farm",
    "wof:placetype":"venue"
},
  "geometry": {"coordinates":[-78.84078,42.351464],"type":"Point"}
}