{
  "type": "Feature",
  "properties": {
    "addr:full":"100 Choir Ln Westbury NY 11590",
    "addr:housenumber":"100",
    "addr:postcode":"11590",
    "addr:street":"Choir Ln",
    "iso:country":"US",
    "sg:address":"100 Choir Ln",
    "sg:city":"Westbury",
    "sg:classifiers":[
        {
            "category":"Professional",
            "subcategory":"Advertising",
            "type":"Services"
        }
    ],
    "sg:phone":"+1   ",
    "sg:postcode":"11590",
    "sg:province":"NY",
    "sg:tags":[
        "mail",
        "direct"
    ],
    "wof:name":"Direct Mail Computer Svcs",
    "wof:placetype":"venue"
},
  "geometry": {"coordinates":[-73.55553999999999,40.751058],"type":"Point"}
}