{
  "type": "Feature",
  "properties": {
    "addr:full":"1080 Catalyn St Fl 2 Schenectady NY 12303",
    "addr:housenumber":"1080;2",
    "addr:postcode":"12303",
    "addr:street":"Catalyn St",
    "iso:country":"US",
    "sg:address":"1080 Catalyn St Fl 2",
    "sg:city":"Schenectady",
    "sg:classifiers":[
        {
            "category":"Manufacturing",
            "subcategory":"Textiles",
            "type":"Manufacturing & Wholesale Goods"
        }
    ],
    "sg:phone":"+1 518 344 7092",
    "sg:postcode":"12303",
    "sg:province":"NY",
    "sg:tags":[
        "goods-wholesale",
        "knit",
        "manufacturer"
    ],
    "wof:name":"Keryakos Inc",
    "wof:placetype":"venue"
},
  "geometry": {"coordinates":[-73.940319,42.790052],"type":"Point"}
}