{
  "type": "Feature",
  "properties": {
    "addr:full":"1333 60th St Brooklyn NY 11219",
    "addr:housenumber":"1333",
    "addr:postcode":"11219",
    "addr:street":"60Th St",
    "iso:country":"US",
    "sg:address":"1333 60th St",
    "sg:city":"Brooklyn",
    "sg:classifiers":[
        {
            "category":"Banks & Credit Unions",
            "subcategory":"Bank",
            "type":"Services"
        }
    ],
    "sg:phone":"+1 347 410 5962",
    "sg:postcode":"11219",
    "sg:province":"NY",
    "wof:name":"Herald National Bank",
    "wof:placetype":"venue"
},
  "geometry": {"coordinates":[-73.99781900000001,40.628588],"type":"Point"}
}