{
  "type": "Feature",
  "properties": {
    "addr:full":"102 Station Rd Willsboro NY 12996",
    "addr:housenumber":"102",
    "addr:postcode":"12996",
    "addr:street":"Station Rd",
    "iso:country":"US",
    "sg:address":"102 Station Rd",
    "sg:city":"Willsboro",
    "sg:classifiers":[
        {
            "category":"Farming",
            "subcategory":"Nursery",
            "type":"Manufacturing & Wholesale Goods"
        },
        {
            "category":"Building & Trades",
            "subcategory":"Landscaping Services",
            "type":"Services"
        }
    ],
    "sg:phone":"+1 518 963 4330",
    "sg:postcode":"12996",
    "sg:province":"NY",
    "sg:tags":[
        "ornamental",
        "supply",
        "landscape",
        "contractor"
    ],
    "wof:name":"Carriage House Garden Center",
    "wof:placetype":"venue"
},
  "geometry": {"coordinates":[-73.40382700000001,44.37293],"type":"Point"}
}