{
  "type": "Feature",
  "properties": {
    "iso:country":"US",
    "sg:address":"3020 N Westchester Ave",
    "sg:city":"Purchase",
    "sg:classifiers":[
        {
            "category":"Professional",
            "subcategory":"Business Services",
            "type":"Services"
        }
    ],
    "sg:phone":"+1 914 251 1590",
    "sg:postcode":"10577",
    "sg:province":"NY",
    "sg:tags":[
        "management",
        "relocation"
    ],
    "wof:name":"Weichert Relocation Resources",
    "wof:placetype":"venue"
},
  "geometry": {"coordinates":[-73.69744799999999,41.009122],"type":"Point"}
}