{
  "type": "Feature",
  "properties": {
    "addr:full":"11 S Main St Southampton NY 11968",
    "addr:housenumber":"11",
    "addr:postcode":"11968",
    "addr:street":"S Main St",
    "iso:country":"US",
    "sg:address":"11 S Main St",
    "sg:city":"Southampton",
    "sg:classifiers":[
        {
            "category":"Shopping",
            "subcategory":"Antiques",
            "type":"Retail Goods"
        }
    ],
    "sg:phone":"+1 631 283 6445",
    "sg:postcode":"11968",
    "sg:province":"NY",
    "wof:name":"Croft Antiques",
    "wof:placetype":"venue"
},
  "geometry": {"coordinates":[-72.389415,40.883997],"type":"Point"}
}