{
  "type": "Feature",
  "properties": {
    "iso:country":"US",
    "sg:address":"438 Ralph Ave",
    "sg:city":"Brooklyn",
    "sg:classifiers":[
        {
            "category":"Organizations",
            "subcategory":"Religious Organization",
            "type":"Services"
        }
    ],
    "sg:phone":"+1 718 756 8128",
    "sg:postcode":"11233",
    "sg:province":"NY",
    "sg:tags":[
        "church",
        "based",
        "face"
    ],
    "wof:name":"Gods Deliverance Temple Inc",
    "wof:placetype":"venue"
},
  "geometry": {"coordinates":[-73.92218,40.67406],"type":"Point"}
}