{
  "type": "Feature",
  "properties": {
    "addr:full":"1696 Sunrise Hwy Bay Shore NY 11706",
    "addr:housenumber":"1696",
    "addr:postcode":"11706",
    "addr:street":"Sunrise Hwy",
    "iso:country":"US",
    "sg:address":"1696 Sunrise Hwy",
    "sg:city":"Bay Shore",
    "sg:classifiers":[
        {
            "category":"Home & Garden",
            "subcategory":"Furniture",
            "type":"Retail Goods"
        }
    ],
    "sg:phone":"+1 631 969 4358",
    "sg:postcode":"11706",
    "sg:province":"NY",
    "sg:website":"www.jenniferfurniture.com",
    "wof:name":"Jennifer Convertibles",
    "wof:placetype":"venue"
},
  "geometry": {"coordinates":[-73.25645,40.733968],"type":"Point"}
}