{
  "type": "Feature",
  "properties": {
    "addr:full":"600 S Geddes St Syracuse NY 13204",
    "addr:housenumber":"600",
    "addr:postcode":"13204",
    "addr:street":"S Geddes St",
    "iso:country":"US",
    "sg:address":"600 S Geddes St",
    "sg:city":"Syracuse",
    "sg:classifiers":[
        {
            "category":"Restaurant",
            "type":"Food & Drink"
        }
    ],
    "sg:phone":"+1   ",
    "sg:postcode":"13204",
    "sg:province":"NY",
    "sg:tags":[
        "eating"
    ],
    "wof:name":"China House Restaurant",
    "wof:placetype":"venue"
},
  "geometry": {"coordinates":[-76.17181600000001,43.041464],"type":"Point"}
}