{
  "type": "Feature",
  "properties": {
    "addr:full":"156 W 56th Street New York NY 10019",
    "addr:housenumber":"156",
    "addr:postcode":"10019",
    "addr:street":"W 56Th Street",
    "iso:country":"US",
    "sg:address":"156 W 56th Street",
    "sg:city":"New York",
    "sg:classifiers":[
        {
            "category":"Professional",
            "subcategory":"Lawyer & Legal Services",
            "type":"Services"
        }
    ],
    "sg:phone":"+1 212 237 1000",
    "sg:postcode":"10019",
    "sg:province":"NY",
    "wof:name":"Windels Marx Lane & Mittendorf",
    "wof:placetype":"venue"
},
  "geometry": {"coordinates":[-73.979803,40.764468],"type":"Point"}
}