{
  "type": "Feature",
  "properties": {
    "iso:country":"US",
    "sg:address":"3603 James St",
    "sg:city":"Syracuse",
    "sg:classifiers":[
        {
            "category":"Personal",
            "subcategory":"Barber",
            "type":"Services"
        }
    ],
    "sg:phone":"+1 315 437 1323",
    "sg:postcode":"13206",
    "sg:province":"NY",
    "wof:name":"Sandy's Appointment Styling",
    "wof:placetype":"venue"
},
  "geometry": {"coordinates":[-76.09613299999999,43.069328],"type":"Point"}
}