{
  "type": "Feature",
  "properties": {
    "addr:full":"260 Edgemoor Rd Rochester NY 14618",
    "addr:housenumber":"260",
    "addr:postcode":"14618",
    "addr:street":"Edgemoor Rd",
    "iso:country":"US",
    "sg:address":"260 Edgemoor Rd",
    "sg:city":"Rochester",
    "sg:classifiers":[
        {
            "category":"Wholesale",
            "subcategory":"Medical Equipment & Supplies",
            "type":"Manufacturing & Wholesale Goods"
        },
        {
            "category":"Shopping",
            "subcategory":"Pharmacy",
            "type":"Retail Goods"
        }
    ],
    "sg:phone":"+1 585 271 0770",
    "sg:postcode":"14618",
    "sg:province":"NY",
    "sg:tags":[
        "home",
        "health",
        "care"
    ],
    "wof:name":"Spencer Dental Supply",
    "wof:placetype":"venue"
},
  "geometry": {"coordinates":[-77.555105,43.132435],"type":"Point"}
}