{
  "type": "Feature",
  "properties": {
    "iso:country":"US",
    "sg:address":"180 N Wantagh Ave",
    "sg:city":"Bethpage",
    "sg:classifiers":[
        {
            "category":"Building & Trades",
            "subcategory":"Construction",
            "type":"Services"
        }
    ],
    "sg:phone":"+1 516 931 8311",
    "sg:postcode":"11714",
    "sg:province":"NY",
    "sg:tags":[
        "material",
        "contractor"
    ],
    "sg:website":"www.bathtubdoctor.com",
    "wof:name":"Bathtub Doctor Inc",
    "wof:placetype":"venue"
},
  "geometry": {"coordinates":[-73.497124,40.728712],"type":"Point"}
}