{
  "type": "Feature",
  "properties": {
    "iso:country":"US",
    "sg:address":"139 S Robinson Ave",
    "sg:city":"Newburgh",
    "sg:classifiers":[
        {
            "category":"Manufacturing",
            "subcategory":"Glass & Minerals",
            "type":"Manufacturing & Wholesale Goods"
        },
        {
            "category":"Retail",
            "subcategory":"Auto Repair",
            "type":"Services"
        }
    ],
    "sg:phone":"+1 845 565 7100",
    "sg:postcode":"12550",
    "sg:province":"NY",
    "sg:tags":[
        "plate",
        "window",
        "windshield",
        "glass-auto"
    ],
    "sg:website":"http://www.glassusa.com/safety",
    "wof:name":"Glass America",
    "wof:placetype":"venue"
},
  "geometry": {"coordinates":[-74.022087,41.494467],"type":"Point"}
}