{
  "type": "Feature",
  "properties": {
    "iso:country":"US",
    "sg:address":"296 W 10 St",
    "sg:city":"New York",
    "sg:classifiers":[
        {
            "category":"Retail",
            "subcategory":"Portrait Studio",
            "type":"Services"
        }
    ],
    "sg:phone":"+1 212 343 8842",
    "sg:postcode":"10014",
    "sg:province":"NY",
    "sg:tags":[
        "photographer"
    ],
    "wof:name":"Donald Graham Photography",
    "wof:placetype":"venue"
},
  "geometry": {"coordinates":[-74.009276,40.733237],"type":"Point"}
}