{
  "type": "Feature",
  "properties": {
    "addr:full":"41 E 11 St New York NY 10003",
    "addr:housenumber":"41;11",
    "addr:postcode":"10003",
    "addr:street":"E;St",
    "iso:country":"US",
    "sg:address":"41 E 11 St",
    "sg:city":"New York",
    "sg:classifiers":[
        {
            "category":"Utilities",
            "subcategory":"Telephone",
            "type":"Services"
        }
    ],
    "sg:phone":"+1   ",
    "sg:postcode":"10003",
    "sg:province":"NY",
    "sg:tags":[
        "communications"
    ],
    "wof:name":"Sapotek Inc",
    "wof:placetype":"venue"
},
  "geometry": {"coordinates":[-73.991281,40.732445],"type":"Point"}
}