{
  "type": "Feature",
  "properties": {
    "addr:full":"11269 Broadway St Alden NY 14004",
    "addr:housenumber":"11269",
    "addr:postcode":"14004",
    "addr:street":"Broadway St",
    "iso:country":"US",
    "sg:address":"11269 Broadway St",
    "sg:city":"Alden",
    "sg:classifiers":[
        {
            "category":"Place Of Worship",
            "subcategory":"Church",
            "type":"Public Place"
        },
        {
            "category":"Place Of Worship",
            "type":"Public Place"
        }
    ],
    "sg:phone":"+1 716 683 5994",
    "sg:postcode":"14004",
    "sg:province":"NY",
    "sg:tags":[
        "testament",
        "christ-new",
        "churches-church",
        "christ"
    ],
    "wof:name":"St Paul's United Church Of Christ",
    "wof:placetype":"venue"
},
  "geometry": {"coordinates":[-78.56518199999999,42.890346],"type":"Point"}
}