{
  "type": "Feature",
  "properties": {
    "iso:country":"US",
    "sg:address":"1040 Portland Ave",
    "sg:city":"Rochester",
    "sg:classifiers":[
        {
            "category":"Professional",
            "type":"Services"
        }
    ],
    "sg:phone":"+1 585 487 2537",
    "sg:postcode":"14621",
    "sg:province":"NY",
    "sg:tags":[
        "establishment"
    ],
    "wof:name":"East House Corp",
    "wof:placetype":"venue"
},
  "geometry": {"coordinates":[-77.58402,43.184389],"type":"Point"}
}