{
  "type": "Feature",
  "properties": {
    "iso:country":"US",
    "sg:address":"30 W 48 St",
    "sg:city":"New York",
    "sg:classifiers":[
        {
            "category":"Freight",
            "type":"Transportation"
        }
    ],
    "sg:phone":"+1   ",
    "sg:postcode":"10036",
    "sg:province":"NY",
    "sg:tags":[
        "courier"
    ],
    "wof:name":"PC Courier",
    "wof:placetype":"venue"
},
  "geometry": {"coordinates":[-73.978927,40.757483],"type":"Point"}
}