{
  "type": "Feature",
  "properties": {
    "addr:full":"7090 Sevier Rd Jamesville NY 13078",
    "addr:housenumber":"7090",
    "addr:postcode":"13078",
    "addr:street":"Sevier Rd",
    "iso:country":"US",
    "sg:address":"7090 Sevier Rd",
    "sg:city":"Jamesville",
    "sg:classifiers":[
        {
            "category":"Shopping",
            "subcategory":"Crafts & Fabrics",
            "type":"Retail Goods"
        }
    ],
    "sg:phone":"+1 315 469 6261",
    "sg:postcode":"13078",
    "sg:province":"NY",
    "sg:tags":[
        "textile"
    ],
    "wof:name":"Ambrose Textile Co",
    "wof:placetype":"venue"
},
  "geometry": {"coordinates":[-76.020409,42.946389],"type":"Point"}
}