{
  "type": "Feature",
  "properties": {
    "addr:full":"3116 Eggert Rd Tonawanda NY 14150",
    "addr:housenumber":"3116",
    "addr:postcode":"14150",
    "addr:street":"Eggert Rd",
    "iso:country":"US",
    "sg:address":"3116 Eggert Rd",
    "sg:city":"Tonawanda",
    "sg:classifiers":[
        {
            "category":"Professional",
            "subcategory":"Management & Consulting",
            "type":"Services"
        }
    ],
    "sg:phone":"+1   ",
    "sg:postcode":"14150",
    "sg:province":"NY",
    "sg:tags":[
        "retail",
        "direct",
        "sales"
    ],
    "wof:name":"Mary Kay",
    "wof:placetype":"venue"
},
  "geometry": {"coordinates":[-78.848174,42.995226],"type":"Point"}
}