{
  "type": "Feature",
  "properties": {
    "addr:full":"114 Deepwood Dr Chappaqua NY 10514",
    "addr:housenumber":"114",
    "addr:postcode":"10514",
    "addr:street":"Deepwood Dr",
    "iso:country":"US",
    "sg:address":"114 Deepwood Dr",
    "sg:city":"Chappaqua",
    "sg:classifiers":[
        {
            "category":"Real Estate",
            "subcategory":"Architect",
            "type":"Services"
        }
    ],
    "sg:phone":"+1   ",
    "sg:postcode":"10514",
    "sg:province":"NY",
    "sg:tags":[
        "architectural"
    ],
    "wof:name":"Gallardo Architects",
    "wof:placetype":"venue"
},
  "geometry": {"coordinates":[-73.796127,41.169292],"type":"Point"}
}