{
  "type": "Feature",
  "properties": {
    "addr:full":"27 Smithfield Blvd Plattsburgh NY 12901",
    "addr:housenumber":"27",
    "addr:postcode":"12901",
    "addr:street":"Smithfield Blvd",
    "iso:country":"US",
    "sg:address":"27 Smithfield Blvd",
    "sg:city":"Plattsburgh",
    "sg:classifiers":[
        {
            "category":"Personal",
            "subcategory":"Beauty Salon",
            "type":"Services"
        }
    ],
    "sg:phone":"+1 518 562 5748",
    "sg:postcode":"12901",
    "sg:province":"NY",
    "wof:name":"Hair Designs By Carmine",
    "wof:placetype":"venue"
},
  "geometry": {"coordinates":[-73.496324,44.703733],"type":"Point"}
}