{
  "type": "Feature",
  "properties": {
    "addr:full":"61 Martling Ave Pleasantville NY 10570",
    "addr:housenumber":"61",
    "addr:postcode":"10570",
    "addr:street":"Martling Ave",
    "iso:country":"US",
    "sg:address":"61 Martling Ave",
    "sg:city":"Pleasantville",
    "sg:classifiers":[
        {
            "category":"Building & Trades",
            "subcategory":"Landscaping Services",
            "type":"Services"
        }
    ],
    "sg:phone":"+1 914 769 9556",
    "sg:postcode":"10570",
    "sg:province":"NY",
    "sg:tags":[
        "landscape"
    ],
    "wof:name":"Chester Onuma",
    "wof:placetype":"venue"
},
  "geometry": {"coordinates":[-73.78877799999999,41.131167],"type":"Point"}
}