{
  "type": "Feature",
  "properties": {
    "addr:full":"65 Bryant Woods S Amherst NY 14228",
    "addr:housenumber":"65",
    "addr:postcode":"14228",
    "addr:street":"Bryant Woods S",
    "iso:country":"US",
    "sg:address":"65 Bryant Woods S",
    "sg:city":"Amherst",
    "sg:classifiers":[
        {
            "category":"Professional",
            "type":"Services"
        }
    ],
    "sg:phone":"+1 716 568 2042",
    "sg:postcode":"14228",
    "sg:province":"NY",
    "sg:tags":[
        "establishment"
    ],
    "wof:name":"Bufrep",
    "wof:placetype":"venue"
},
  "geometry": {"coordinates":[-78.78716,43.020019],"type":"Point"}
}