{
  "type": "Feature",
  "properties": {
    "iso:country":"US",
    "sg:address":"1845 Union Blvd",
    "sg:city":"Bay Shore",
    "sg:classifiers":[
        {
            "category":"Shopping",
            "subcategory":"Crafts & Fabrics",
            "type":"Retail Goods"
        }
    ],
    "sg:phone":"+1 631 666 0280",
    "sg:postcode":"11706",
    "sg:province":"NY",
    "sg:tags":[
        "store"
    ],
    "wof:name":"Julio's Tailoring",
    "wof:placetype":"venue"
},
  "geometry": {"coordinates":[-73.24633,40.726415],"type":"Point"}
}