{
  "type": "Feature",
  "properties": {
    "addr:full":"260 W 91 St New York NY 10024",
    "addr:housenumber":"260",
    "addr:postcode":"10024",
    "addr:street":"W 91 St",
    "iso:country":"US",
    "sg:address":"260 W 91 St",
    "sg:city":"New York",
    "sg:classifiers":[
        {
            "category":"Health Services",
            "subcategory":"Doctor",
            "type":"Services"
        }
    ],
    "sg:phone":"+1   ",
    "sg:postcode":"10024",
    "sg:province":"NY",
    "sg:tags":[
        "medical"
    ],
    "wof:name":"Joseph Klager MD",
    "wof:placetype":"venue"
},
  "geometry": {"coordinates":[-73.975343,40.791878],"type":"Point"}
}