{
  "type": "Feature",
  "properties": {
    "addr:full":"145 Hicks St Apt B48 Brooklyn NY 11201",
    "addr:housenumber":"145",
    "addr:postcode":"11201",
    "addr:street":"Hicks St Apt B48",
    "iso:country":"US",
    "sg:address":"145 Hicks St Apt B48",
    "sg:city":"Brooklyn",
    "sg:classifiers":[
        {
            "category":"Museum",
            "type":"Entertainment"
        }
    ],
    "sg:phone":"+1 718 222 0766",
    "sg:postcode":"11201",
    "sg:province":"NY",
    "wof:name":"Mansion House",
    "wof:placetype":"venue"
},
  "geometry": {"coordinates":[-73.99490400000001,40.697201],"type":"Point"}
}