{
  "type": "Feature",
  "properties": {
    "addr:full":"29 Ogden St Glens Falls NY 12801",
    "addr:housenumber":"29",
    "addr:postcode":"12801",
    "addr:street":"Ogden St",
    "iso:country":"US",
    "sg:address":"29 Ogden St",
    "sg:city":"Glens Falls",
    "sg:classifiers":[
        {
            "category":"Manufacturing",
            "subcategory":"Toys & Sporting Goods",
            "type":"Manufacturing & Wholesale Goods"
        }
    ],
    "sg:phone":"+1   ",
    "sg:postcode":"12801",
    "sg:province":"NY",
    "sg:tags":[
        "mfg"
    ],
    "wof:name":"Angelas Kreations",
    "wof:placetype":"venue"
},
  "geometry": {"coordinates":[-73.653081,43.320121],"type":"Point"}
}