{
  "type": "Feature",
  "properties": {
    "addr:full":"500 Merrick Rd Rockville Centre NY 11570",
    "addr:housenumber":"500",
    "addr:postcode":"11570",
    "addr:street":"Merrick Rd",
    "iso:country":"US",
    "sg:address":"500 Merrick Rd",
    "sg:city":"Rockville Centre",
    "sg:classifiers":[
        {
            "category":"Banks & Credit Unions",
            "subcategory":"Financial Services",
            "type":"Services"
        }
    ],
    "sg:phone":"+1 516 678 0609",
    "sg:postcode":"11570",
    "sg:province":"NY",
    "sg:tags":[
        "broker",
        "mortgage"
    ],
    "wof:name":"NRF Funding",
    "wof:placetype":"venue"
},
  "geometry": {"coordinates":[-73.636138,40.654798],"type":"Point"}
}