{
  "type": "Feature",
  "properties": {
    "addr:full":"611 Jericho Tpke New Hyde Park NY 11040",
    "addr:housenumber":"611",
    "addr:postcode":"11040",
    "addr:street":"Jericho Tpke;Hyde Park",
    "iso:country":"US",
    "sg:address":"611 Jericho Tpke",
    "sg:city":"New Hyde Park",
    "sg:classifiers":[
        {
            "category":"Organizations",
            "subcategory":"Community Association",
            "type":"Services"
        }
    ],
    "sg:phone":"+1   ",
    "sg:postcode":"11040",
    "sg:province":"NY",
    "wof:name":"Order of Sons Italy Cellini L",
    "wof:placetype":"venue"
},
  "geometry": {"coordinates":[-73.68841399999999,40.731944],"type":"Point"}
}