{
  "type": "Feature",
  "properties": {
    "addr:full":"111 Dryden Rd Ithaca NY 14850",
    "addr:housenumber":"111",
    "addr:postcode":"14850",
    "addr:street":"Dryden Rd",
    "iso:country":"US",
    "sg:address":"111 Dryden Rd",
    "sg:city":"Ithaca",
    "sg:classifiers":[
        {
            "category":"Personal",
            "subcategory":"Barber",
            "type":"Services"
        }
    ],
    "sg:phone":"+1   ",
    "sg:postcode":"14850",
    "sg:province":"NY",
    "sg:tags":[
        "shop"
    ],
    "wof:name":"University Barber Shop",
    "wof:placetype":"venue"
},
  "geometry": {"coordinates":[-76.48709100000001,42.442012],"type":"Point"}
}