{
  "type": "Feature",
  "properties": {
    "iso:country":"US",
    "sg:address":"3870 Number Nine Rd",
    "sg:city":"Cazenovia",
    "sg:classifiers":[
        {
            "category":"Wholesale",
            "subcategory":"Construction Materials",
            "type":"Manufacturing & Wholesale Goods"
        }
    ],
    "sg:phone":"+1 315 655 9222",
    "sg:postcode":"13035",
    "sg:province":"NY",
    "sg:tags":[
        "sand",
        "gravel"
    ],
    "wof:name":"Nick W Zupan & Sons Inc",
    "wof:placetype":"venue"
},
  "geometry": {"coordinates":[-75.84258699999999,42.911354],"type":"Point"}
}