{
  "type": "Feature",
  "properties": {
    "iso:country":"US",
    "sg:address":"349 E Commercial St",
    "sg:city":"East Rochester",
    "sg:classifiers":[
        {
            "category":"Professional",
            "subcategory":"Accounting & Tax Preparation",
            "type":"Services"
        }
    ],
    "sg:phone":"+1 585 586 8816",
    "sg:postcode":"14445",
    "sg:province":"NY",
    "sg:tags":[
        "accountant"
    ],
    "wof:name":"John J Marsh Jr CPA",
    "wof:placetype":"venue"
},
  "geometry": {"coordinates":[-77.479496,43.111405],"type":"Point"}
}