{
  "type": "Feature",
  "properties": {
    "addr:full":"234 William Floyd Pkwy # 4 Shirley NY 11967",
    "addr:housenumber":"234",
    "addr:postcode":"11967",
    "addr:street":"William Floyd Pkwy # 4",
    "iso:country":"US",
    "sg:address":"234 William Floyd Pkwy # 4",
    "sg:city":"Shirley",
    "sg:phone":"+1 631 399 4828",
    "sg:postcode":"11967",
    "sg:province":"NY",
    "wof:name":"Sweet Garden Chinese Take-Out Restaurant",
    "wof:placetype":"venue"
},
  "geometry": {"coordinates":[-72.872078,40.75861],"type":"Point"}
}