{
  "type": "Feature",
  "properties": {
    "addr:full":"98 Pondfield Rd Bronxville NY 10708",
    "addr:housenumber":"98",
    "addr:postcode":"10708",
    "addr:street":"Pondfield Rd",
    "iso:country":"US",
    "sg:address":"98 Pondfield Rd",
    "sg:city":"Bronxville",
    "sg:classifiers":[
        {
            "category":"Food & Beverages",
            "subcategory":"Liquor & Beverages",
            "type":"Retail Goods"
        }
    ],
    "sg:phone":"+1   ",
    "sg:postcode":"10708",
    "sg:province":"NY",
    "sg:tags":[
        "eating",
        "alcoholic"
    ],
    "wof:name":"Wine Sprit Emprium of Brnxvlle",
    "wof:placetype":"venue"
},
  "geometry": {"coordinates":[-73.832853,40.939215],"type":"Point"}
}