{
  "type": "Feature",
  "properties": {
    "addr:full":"685 W End Ave New York NY 10025",
    "addr:housenumber":"685",
    "addr:postcode":"10025",
    "addr:street":"W End Ave",
    "iso:country":"US",
    "sg:address":"685 W End Ave",
    "sg:city":"New York",
    "sg:classifiers":[
        {
            "category":"Manufacturing",
            "subcategory":"Furniture",
            "type":"Manufacturing & Wholesale Goods"
        }
    ],
    "sg:phone":"+1 212 932 0366",
    "sg:postcode":"10025",
    "sg:province":"NY",
    "sg:tags":[
        "manufacture",
        "saving",
        "store",
        "space"
    ],
    "sg:website":"www.inovallc.com",
    "wof:name":"Inova Llc",
    "wof:placetype":"venue"
},
  "geometry": {"coordinates":[-73.974602,40.793301],"type":"Point"}
}