{
  "type": "Feature",
  "properties": {
    "iso:country":"US",
    "sg:address":"3107 Rochambeau Ave",
    "sg:city":"Bronx",
    "sg:classifiers":[
        {
            "category":"Organizations",
            "subcategory":"Religious Organization",
            "type":"Services"
        }
    ],
    "sg:phone":"+1 718 881 9458",
    "sg:postcode":"10467",
    "sg:province":"NY",
    "sg:tags":[
        "monastery",
        "convent"
    ],
    "wof:name":"Dominican Sisters Of Hope",
    "wof:placetype":"venue"
},
  "geometry": {"coordinates":[-73.880465,40.874716],"type":"Point"}
}