{
  "type": "Feature",
  "properties": {
    "iso:country":"US",
    "sg:address":"15 Island Bay Ave",
    "sg:city":"Middle Island",
    "sg:classifiers":[
        {
            "category":"Shopping",
            "subcategory":"Computers & Home Electronics",
            "type":"Retail Goods"
        }
    ],
    "sg:phone":"+1   ",
    "sg:postcode":"11953",
    "sg:province":"NY",
    "sg:tags":[
        "custom",
        "sales",
        "system",
        "design",
        "video",
        "audio"
    ],
    "wof:name":"Audio Video Exprnce of Suffolk",
    "wof:placetype":"venue"
},
  "geometry": {"coordinates":[-72.93883700000001,40.878651],"type":"Point"}
}