{
  "type": "Feature",
  "properties": {
    "iso:country":"US",
    "sg:address":"901 Hawleyton Rd",
    "sg:city":"Binghamton",
    "sg:classifiers":[
        {
            "category":"Organizations",
            "subcategory":"Religious Organization",
            "type":"Services"
        }
    ],
    "sg:phone":"+1   ",
    "sg:postcode":"13903",
    "sg:province":"NY",
    "wof:name":"Hawleyton Untd Methdst Church",
    "wof:placetype":"venue"
},
  "geometry": {"coordinates":[-75.958432,41.999382],"type":"Point"}
}