{
  "type": "Feature",
  "properties": {
    "addr:full":"1005 Nichols St Utica NY 13501",
    "addr:housenumber":"1005",
    "addr:postcode":"13501",
    "addr:street":"Nichols St",
    "iso:country":"US",
    "sg:address":"1005 Nichols St",
    "sg:city":"Utica",
    "sg:classifiers":[
        {
            "category":"Building & Trades",
            "subcategory":"Construction",
            "type":"Services"
        }
    ],
    "sg:phone":"+1 315 733 2027",
    "sg:postcode":"13501",
    "sg:province":"NY",
    "sg:tags":[
        "general",
        "contractor"
    ],
    "wof:name":"Eagle Construction",
    "wof:placetype":"venue"
},
  "geometry": {"coordinates":[-75.212542,43.090324],"type":"Point"}
}