{
  "type": "Feature",
  "properties": {
    "addr:full":"283 Hillside Ave Williston Park NY 11596",
    "addr:housenumber":"283",
    "addr:postcode":"11596",
    "addr:street":"Hillside Ave",
    "iso:country":"US",
    "sg:address":"283 Hillside Ave",
    "sg:city":"Williston Park",
    "sg:classifiers":[
        {
            "category":"Deli",
            "type":"Food & Drink"
        }
    ],
    "sg:phone":"+1 516 248 0821",
    "sg:postcode":"11596",
    "sg:province":"NY",
    "wof:name":"Williston Park Deli",
    "wof:placetype":"venue"
},
  "geometry": {"coordinates":[-73.649597,40.7547],"type":"Point"}
}