{
  "type": "Feature",
  "properties": {
    "addr:full":"365 Dupont Ave Tonawanda NY 14150",
    "addr:housenumber":"365",
    "addr:postcode":"14150",
    "addr:street":"Dupont Ave",
    "iso:country":"US",
    "sg:address":"365 Dupont Ave",
    "sg:city":"Tonawanda",
    "sg:classifiers":[
        {
            "category":"Education",
            "subcategory":"School",
            "type":"Public Place"
        }
    ],
    "sg:phone":"+1 716 874 8423",
    "sg:postcode":"14150",
    "sg:province":"NY",
    "wof:name":"Holmes Elementary School",
    "wof:placetype":"venue"
},
  "geometry": {"coordinates":[-78.898113,42.976303],"type":"Point"}
}