{
  "type": "Feature",
  "properties": {
    "iso:country":"US",
    "sg:address":"4565 State Hwy 414",
    "sg:city":"Seneca Falls",
    "sg:classifiers":[
        {
            "category":"Manufacturing",
            "subcategory":"Food",
            "type":"Manufacturing & Wholesale Goods"
        }
    ],
    "sg:phone":"+1 315 549 8326",
    "sg:postcode":"13148",
    "sg:province":"NY",
    "sg:tags":[
        "winery"
    ],
    "sg:website":"www.swedishhill.com",
    "wof:name":"Swedish Hill Vineyard & Winery",
    "wof:placetype":"venue"
},
  "geometry": {"coordinates":[-76.810767,42.803695],"type":"Point"}
}