{
  "type": "Feature",
  "properties": {
    "iso:country":"US",
    "sg:address":"420 E 54 St",
    "sg:city":"New York",
    "sg:classifiers":[
        {
            "category":"Organizations",
            "subcategory":"Membership Organization",
            "type":"Services"
        }
    ],
    "sg:phone":"+1 212 688 5858",
    "sg:postcode":"10022",
    "sg:province":"NY",
    "wof:name":"Macklowe Organization",
    "wof:placetype":"venue"
},
  "geometry": {"coordinates":[-73.96248,40.755578],"type":"Point"}
}