{
  "type": "Feature",
  "properties": {
    "addr:full":"8345 Vietor Ave Apt 3A Elmhurst NY 11373",
    "addr:housenumber":"8345",
    "addr:postcode":"11373",
    "addr:street":"Vietor Ave Apt 3A",
    "iso:country":"US",
    "sg:address":"8345 Vietor Ave Apt 3A",
    "sg:city":"Elmhurst",
    "sg:classifiers":[
        {
            "category":"Professional",
            "subcategory":"Business Services",
            "type":"Services"
        }
    ],
    "sg:phone":"+1 718 424 4754",
    "sg:postcode":"11373",
    "sg:province":"NY",
    "sg:tags":[
        "inspection"
    ],
    "wof:name":"Kay Home Inspections",
    "wof:placetype":"venue"
},
  "geometry": {"coordinates":[-73.88134700000001,40.743059],"type":"Point"}
}