{
  "type": "Feature",
  "properties": {
    "addr:full":"179 E 3 St New York NY 10009",
    "addr:housenumber":"179;3",
    "addr:postcode":"10009",
    "addr:street":"E",
    "iso:country":"US",
    "sg:address":"179 E 3 St",
    "sg:city":"New York",
    "sg:classifiers":[
        {
            "category":"Professional",
            "subcategory":"Business Services",
            "type":"Services"
        },
        {
            "category":"Shopping",
            "subcategory":"Musical Instruments",
            "type":"Retail Goods"
        }
    ],
    "sg:phone":"+1 212 420 0283",
    "sg:postcode":"10009",
    "sg:province":"NY",
    "sg:tags":[
        "recording",
        "music",
        "studio",
        "dealer"
    ],
    "sg:website":"www.jambetta.com",
    "wof:name":"Jam Betta Music",
    "wof:placetype":"venue"
},
  "geometry": {"coordinates":[-73.98384,40.723243],"type":"Point"}
}