{
  "type": "Feature",
  "properties": {
    "addr:full":"369 E Main St Ste 6 East Islip NY 11730",
    "addr:housenumber":"369",
    "addr:postcode":"11730",
    "addr:street":"E Main St Ste 6",
    "iso:country":"US",
    "sg:address":"369 E Main St Ste 6",
    "sg:city":"East Islip",
    "sg:classifiers":[
        {
            "category":"Shopping",
            "subcategory":"Optician",
            "type":"Retail Goods"
        }
    ],
    "sg:phone":"+1 631 277 7446",
    "sg:postcode":"11730",
    "sg:province":"NY",
    "sg:tags":[
        "eyewear"
    ],
    "wof:name":"Island Optical Center",
    "wof:placetype":"venue"
},
  "geometry": {"coordinates":[-73.174401,40.735484],"type":"Point"}
}