{
  "type": "Feature",
  "properties": {
    "addr:full":"25 Hutcheson Pl Lynbrook NY 11563",
    "addr:housenumber":"25",
    "addr:postcode":"11563",
    "addr:street":"Hutcheson Pl",
    "iso:country":"US",
    "sg:address":"25 Hutcheson Pl",
    "sg:city":"Lynbrook",
    "sg:classifiers":[
        {
            "category":"Professional",
            "type":"Services"
        }
    ],
    "sg:phone":"+1   ",
    "sg:postcode":"11563",
    "sg:province":"NY",
    "wof:name":"Karella Corp",
    "wof:placetype":"venue"
},
  "geometry": {"coordinates":[-73.66228099999999,40.657588],"type":"Point"}
}