{
  "type": "Feature",
  "properties": {
    "addr:full":"56 Goodrich Rd Owego NY 13827",
    "addr:housenumber":"56",
    "addr:postcode":"13827",
    "addr:street":"Goodrich Rd",
    "iso:country":"US",
    "sg:address":"56 Goodrich Rd",
    "sg:city":"Owego",
    "sg:classifiers":[
        {
            "category":"Farming",
            "subcategory":"Livestock Farm",
            "type":"Manufacturing & Wholesale Goods"
        }
    ],
    "sg:phone":"+1 607 687 4644",
    "sg:postcode":"13827",
    "sg:province":"NY",
    "sg:tags":[
        "beef",
        "feedlot",
        "cattle"
    ],
    "wof:name":"Spencer Hunt",
    "wof:placetype":"venue"
},
  "geometry": {"coordinates":[-76.286199,42.098288],"type":"Point"}
}