{
  "type": "Feature",
  "properties": {
    "iso:country":"US",
    "sg:address":"7413 County House Rd",
    "sg:city":"Auburn",
    "sg:classifiers":[
        {
            "category":"Government",
            "subcategory":"Office",
            "type":"Public Place"
        }
    ],
    "sg:phone":"+1 315 252 0793",
    "sg:postcode":"13021",
    "sg:province":"NY",
    "wof:name":"Cayuga Soil & Water Consrvtn",
    "wof:placetype":"venue"
},
  "geometry": {"coordinates":[-76.54108600000001,42.978702],"type":"Point"}
}