{
  "type": "Feature",
  "properties": {
    "addr:full":"831 State St Schenectady NY 12307",
    "addr:housenumber":"831",
    "addr:postcode":"12307",
    "addr:street":"State St",
    "iso:country":"US",
    "sg:address":"831 State St",
    "sg:city":"Schenectady",
    "sg:classifiers":[
        {
            "category":"Professional",
            "subcategory":"Research",
            "type":"Services"
        }
    ],
    "sg:phone":"+1 518 785 5047",
    "sg:postcode":"12307",
    "sg:province":"NY",
    "sg:tags":[
        "electronic"
    ],
    "wof:name":"Electro Magnetic Technology",
    "wof:placetype":"venue"
},
  "geometry": {"coordinates":[-73.933155,42.806323],"type":"Point"}
}