{
  "type": "Feature",
  "properties": {
    "iso:country":"US",
    "sg:address":"454 Evans St",
    "sg:city":"Buffalo",
    "sg:classifiers":[
        {
            "category":"Personal",
            "subcategory":"Shoe Repair & Shine",
            "type":"Services"
        }
    ],
    "sg:phone":"+1 716 633 6608",
    "sg:postcode":"14221",
    "sg:province":"NY",
    "sg:tags":[
        "repairing",
        "boot"
    ],
    "wof:name":"Joe's Evan Sheridan Shoe Repair",
    "wof:placetype":"venue"
},
  "geometry": {"coordinates":[-78.739529,42.977201],"type":"Point"}
}