{
  "type": "Feature",
  "properties": {
    "addr:full":"62 Charles St New York NY 10014",
    "addr:housenumber":"62",
    "addr:postcode":"10014",
    "addr:street":"Charles St",
    "iso:country":"US",
    "sg:address":"62 Charles St",
    "sg:city":"New York",
    "sg:classifiers":[
        {
            "category":"Retail",
            "subcategory":"Repair Shop",
            "type":"Services"
        }
    ],
    "sg:phone":"+1 646 237 9665",
    "sg:postcode":"10014",
    "sg:province":"NY",
    "sg:tags":[
        "lock",
        "locksmith"
    ],
    "wof:name":"Accurate 24 Hours Emergency",
    "wof:placetype":"venue"
},
  "geometry": {"coordinates":[-74.00197199999999,40.73507],"type":"Point"}
}