{
  "type": "Feature",
  "properties": {
    "addr:full":"20 Middlebush Rd Wappingers Falls NY 12590",
    "addr:housenumber":"20",
    "addr:postcode":"12590",
    "addr:street":"Middlebush Rd",
    "iso:country":"US",
    "sg:address":"20 Middlebush Rd",
    "sg:city":"Wappingers Falls",
    "sg:classifiers":[
        {
            "category":"Government",
            "subcategory":"Office",
            "type":"Public Place"
        }
    ],
    "sg:phone":"+1 845 297 1030",
    "sg:postcode":"12590",
    "sg:province":"NY",
    "sg:tags":[
        "village"
    ],
    "wof:name":"Wappinger Animal Shelter",
    "wof:placetype":"venue"
},
  "geometry": {"coordinates":[-73.922172,41.585938],"type":"Point"}
}