{
  "type": "Feature",
  "properties": {
    "iso:country":"US",
    "sg:address":"6351 Inducon Dr E",
    "sg:city":"Sanborn",
    "sg:classifiers":[
        {
            "category":"Wholesale",
            "subcategory":"Durable Goods & Equipment",
            "type":"Manufacturing & Wholesale Goods"
        }
    ],
    "sg:phone":"+1 716 284 3769",
    "sg:postcode":"14132",
    "sg:province":"NY",
    "sg:tags":[
        "biochemical",
        "product",
        "specialty"
    ],
    "sg:website":"www.unitedbiochemicals.com",
    "wof:name":"United Biochemicals",
    "wof:placetype":"venue"
},
  "geometry": {"coordinates":[-78.917704,43.113272],"type":"Point"}
}