{
  "type": "Feature",
  "properties": {
    "addr:full":"106 Old Country Rd Mineola NY 11501",
    "addr:housenumber":"106",
    "addr:postcode":"11501",
    "addr:street":"Old Country Rd",
    "iso:country":"US",
    "sg:address":"106 Old Country Rd",
    "sg:city":"Mineola",
    "sg:classifiers":[
        {
            "category":"Food & Beverages",
            "subcategory":"Specialty",
            "type":"Retail Goods"
        }
    ],
    "sg:phone":"+1 516 739 3319",
    "sg:postcode":"11501",
    "sg:province":"NY",
    "sg:tags":[
        "tea",
        "coffee"
    ],
    "sg:website":"www.starbucks.com",
    "wof:name":"Starbucks",
    "wof:placetype":"venue"
},
  "geometry": {"coordinates":[-73.629406,40.740756],"type":"Point"}
}