{
  "type": "Feature",
  "properties": {
    "addr:full":"1440 61st St Brooklyn NY 11219",
    "addr:housenumber":"1440",
    "addr:postcode":"11219",
    "addr:street":"61St St",
    "iso:country":"US",
    "sg:address":"1440 61st St",
    "sg:city":"Brooklyn",
    "sg:classifiers":[
        {
            "category":"Banks & Credit Unions",
            "subcategory":"Investment Brokerage",
            "type":"Services"
        }
    ],
    "sg:phone":"+1 718 633 9500",
    "sg:postcode":"11219",
    "sg:province":"NY",
    "sg:tags":[
        "consultant",
        "planning",
        "financial"
    ],
    "wof:name":"R S Palastro Planning Svc",
    "wof:placetype":"venue"
},
  "geometry": {"coordinates":[-73.99549399999999,40.626038],"type":"Point"}
}