{
  "type": "Feature",
  "properties": {
    "addr:full":"125 Belzano Rd Johnstown NY 12095",
    "addr:housenumber":"125",
    "addr:postcode":"12095",
    "addr:street":"Belzano Rd",
    "iso:country":"US",
    "sg:address":"125 Belzano Rd",
    "sg:city":"Johnstown",
    "sg:classifiers":[
        {
            "category":"Wholesale",
            "subcategory":"Construction Materials",
            "type":"Manufacturing & Wholesale Goods"
        }
    ],
    "sg:phone":"+1 518 773 5109",
    "sg:postcode":"12095",
    "sg:province":"NY",
    "sg:tags":[
        "glass"
    ],
    "wof:name":"Empire Architectural Systems",
    "wof:placetype":"venue"
},
  "geometry": {"coordinates":[-74.34268400000001,43.019404],"type":"Point"}
}