{
  "type": "Feature",
  "properties": {
    "iso:country":"US",
    "sg:address":"437 Warren Street",
    "sg:city":"Hudson",
    "sg:classifiers":[
        {
            "category":"Arts & Performance",
            "subcategory":"Arts Center",
            "type":"Entertainment"
        }
    ],
    "sg:phone":"+1 917 456 7496",
    "sg:postcode":"12534",
    "sg:province":"NY",
    "sg:website":"www.posiekviat.com",
    "wof:name":"Posie Kviat Gallery",
    "wof:placetype":"venue"
},
  "geometry": {"coordinates":[-73.78760699999999,42.249987],"type":"Point"}
}