{
  "type": "Feature",
  "properties": {
    "iso:country":"US",
    "sg:address":"130 Thompson St",
    "sg:city":"New York",
    "sg:classifiers":[
        {
            "category":"Shopping",
            "subcategory":"Jewelry",
            "type":"Retail Goods"
        }
    ],
    "sg:phone":"+1 212 387 7980",
    "sg:postcode":"10012",
    "sg:province":"NY",
    "sg:tags":[
        "jeweler"
    ],
    "wof:name":"Gaia Joias",
    "wof:placetype":"venue"
},
  "geometry": {"coordinates":[-74.000722,40.727001],"type":"Point"}
}