{
  "type": "Feature",
  "properties": {
    "addr:full":"120 Essex St New York NY 10002",
    "addr:housenumber":"120",
    "addr:postcode":"10002",
    "addr:street":"Essex St",
    "iso:country":"US",
    "sg:address":"120 Essex St",
    "sg:city":"New York",
    "sg:classifiers":[
        {
            "category":"Restaurant",
            "type":"Food & Drink"
        }
    ],
    "sg:phone":"+1 212 533 9616",
    "sg:postcode":"10002",
    "sg:province":"NY",
    "sg:website":"www.essexnyc.com",
    "wof:name":"Essex Restaurant",
    "wof:placetype":"venue"
},
  "geometry": {"coordinates":[-73.98780499999999,40.718954],"type":"Point"}
}