{
  "type": "Feature",
  "properties": {
    "addr:full":"8 Depot Sq Tuckahoe NY 10707",
    "addr:housenumber":"8",
    "addr:postcode":"10707",
    "addr:street":"Depot Sq",
    "iso:country":"US",
    "sg:address":"8 Depot Sq",
    "sg:city":"Tuckahoe",
    "sg:classifiers":[
        {
            "category":"Real Estate",
            "subcategory":"Real Estate Operator",
            "type":"Services"
        }
    ],
    "sg:phone":"+1 914 793 5050",
    "sg:postcode":"10707",
    "sg:province":"NY",
    "sg:tags":[
        "a",
        "manager",
        "shopping",
        "center"
    ],
    "wof:name":"Poughkeepsie Shopping Center",
    "wof:placetype":"venue"
},
  "geometry": {"coordinates":[-73.82788600000001,40.950183],"type":"Point"}
}