{
  "type": "Feature",
  "properties": {
    "iso:country":"US",
    "sg:address":"325 Alden Rd",
    "sg:city":"Yorktown Heights",
    "sg:classifiers":[
        {
            "category":"Professional",
            "subcategory":"Management & Consulting",
            "type":"Services"
        }
    ],
    "sg:phone":"+1 914 245 1874",
    "sg:postcode":"10598",
    "sg:province":"NY",
    "sg:tags":[
        "consultant",
        "security",
        "system"
    ],
    "wof:name":"Cell Co",
    "wof:placetype":"venue"
},
  "geometry": {"coordinates":[-73.78803000000001,41.302311],"type":"Point"}
}