{
  "type": "Feature",
  "properties": {
    "addr:full":"35 5th Ave New York NY 10003",
    "addr:housenumber":"35",
    "addr:postcode":"10003",
    "addr:street":"5Th Ave",
    "iso:country":"US",
    "sg:address":"35 5th Ave",
    "sg:city":"New York",
    "sg:classifiers":[
        {
            "category":"Restaurant",
            "type":"Food & Drink"
        }
    ],
    "sg:phone":"+1   ",
    "sg:postcode":"10003",
    "sg:province":"NY",
    "sg:tags":[
        "eating"
    ],
    "wof:name":"Aramark",
    "wof:placetype":"venue"
},
  "geometry": {"coordinates":[-73.99504899999999,40.734034],"type":"Point"}
}