{
  "type": "Feature",
  "properties": {
    "addr:full":"23520 147th Avenue Jamaica NY 11422",
    "addr:housenumber":"23520",
    "addr:postcode":"11422",
    "addr:street":"147Th Avenue",
    "iso:country":"US",
    "sg:address":"23520 147th Avenue",
    "sg:city":"Jamaica",
    "sg:classifiers":[
        {
            "category":"Health Services",
            "subcategory":"Doctor",
            "type":"Services"
        }
    ],
    "sg:phone":"+1 718 712 2200",
    "sg:postcode":"11422",
    "sg:province":"NY",
    "wof:name":"Nazarian H MD",
    "wof:placetype":"venue"
},
  "geometry": {"coordinates":[-73.746116,40.657421],"type":"Point"}
}