{
  "type": "Feature",
  "properties": {
    "iso:country":"US",
    "sg:address":"120 Dix Ave",
    "sg:city":"Glens Falls",
    "sg:classifiers":[
        {
            "category":"Local Transit",
            "type":"Transportation"
        }
    ],
    "sg:phone":"+1 518 792 1117",
    "sg:postcode":"12801",
    "sg:province":"NY",
    "sg:tags":[
        "ambulance"
    ],
    "wof:name":"Empire Ambulance",
    "wof:placetype":"venue"
},
  "geometry": {"coordinates":[-73.63143100000001,43.318114],"type":"Point"}
}