{
  "type": "Feature",
  "properties": {
    "iso:country":"US",
    "sg:address":"12 E 4th St",
    "sg:city":"Dunkirk",
    "sg:classifiers":[
        {
            "category":"Real Estate",
            "subcategory":"Surveying",
            "type":"Services"
        }
    ],
    "sg:phone":"+1 716 366 1990",
    "sg:postcode":"14048",
    "sg:province":"NY",
    "wof:name":"Woodbury Surveying",
    "wof:placetype":"venue"
},
  "geometry": {"coordinates":[-79.334012,42.483247],"type":"Point"}
}