{
  "type": "Feature",
  "properties": {
    "addr:full":"22 Grace Ave Great Neck NY 11021",
    "addr:housenumber":"22",
    "addr:postcode":"11021",
    "addr:street":"Grace Ave",
    "iso:country":"US",
    "sg:address":"22 Grace Ave",
    "sg:city":"Great Neck",
    "sg:classifiers":[
        {
            "category":"Banks & Credit Unions",
            "subcategory":"Bank",
            "type":"Services"
        }
    ],
    "sg:phone":"+1 516 935 9935",
    "sg:postcode":"11021",
    "sg:province":"NY",
    "wof:name":"Chase",
    "wof:placetype":"venue"
},
  "geometry": {"coordinates":[-73.727617,40.788472],"type":"Point"}
}