{
  "type": "Feature",
  "properties": {
    "iso:country":"US",
    "sg:address":"551 W 204th St",
    "sg:city":"New York",
    "sg:classifiers":[
        {
            "category":"Professional",
            "type":"Services"
        }
    ],
    "sg:phone":"+1 212 942 4342",
    "sg:postcode":"10034",
    "sg:province":"NY",
    "sg:tags":[
        "establishment"
    ],
    "wof:name":"B & B Management Co",
    "wof:placetype":"venue"
},
  "geometry": {"coordinates":[-73.92061099999999,40.863113],"type":"Point"}
}