{
  "type": "Feature",
  "properties": {
    "addr:full":"52 Columbia St Islip NY 11751",
    "addr:housenumber":"52",
    "addr:postcode":"11751",
    "addr:street":"Columbia St",
    "iso:country":"US",
    "sg:address":"52 Columbia St",
    "sg:city":"Islip",
    "sg:classifiers":[
        {
            "category":"Building & Trades",
            "subcategory":"Plumbing",
            "type":"Services"
        }
    ],
    "sg:phone":"+1 631 859 8800",
    "sg:postcode":"11751",
    "sg:province":"NY",
    "sg:tags":[
        "conditioning",
        "air",
        "system",
        "contractor"
    ],
    "sg:website":"www.integratedhvac.com",
    "wof:name":"Integrated Hvac Syst & Svc Inc",
    "wof:placetype":"venue"
},
  "geometry": {"coordinates":[-73.211922,40.732669],"type":"Point"}
}