{
  "type": "Feature",
  "properties": {
    "iso:country":"US",
    "sg:address":"37 Main St",
    "sg:city":"Chatham",
    "sg:classifiers":[
        {
            "category":"Shopping",
            "subcategory":"Shoes",
            "type":"Retail Goods"
        }
    ],
    "sg:phone":"+1 518 392 2541",
    "sg:postcode":"12037",
    "sg:province":"NY",
    "wof:name":"Browns Emporium Inc",
    "wof:placetype":"venue"
},
  "geometry": {"coordinates":[-73.595618,42.362861],"type":"Point"}
}