{
  "type": "Feature",
  "properties": {
    "addr:full":"1645 Saint Johns Place Brooklyn NY 11233",
    "addr:housenumber":"1645",
    "addr:postcode":"11233",
    "addr:street":"Saint Johns Place",
    "iso:country":"US",
    "sg:address":"1645 Saint Johns Place",
    "sg:city":"Brooklyn",
    "sg:classifiers":[
        {
            "category":"Restaurant",
            "type":"Food & Drink"
        }
    ],
    "sg:phone":"+1 718 778 6392",
    "sg:postcode":"11233",
    "sg:province":"NY",
    "sg:tags":[
        "chinese"
    ],
    "wof:name":"China King",
    "wof:placetype":"venue"
},
  "geometry": {"coordinates":[-73.922544,40.670122],"type":"Point"}
}