{
  "type": "Feature",
  "properties": {
    "addr:full":"333 Humboldt St Rochester NY 14610",
    "addr:housenumber":"333",
    "addr:postcode":"14610",
    "addr:street":"Humboldt St",
    "iso:country":"US",
    "sg:address":"333 Humboldt St",
    "sg:city":"Rochester",
    "sg:classifiers":[
        {
            "category":"Health Services",
            "subcategory":"Clinic",
            "type":"Services"
        }
    ],
    "sg:phone":"+1 585 922 1000",
    "sg:postcode":"14610",
    "sg:province":"NY",
    "sg:tags":[
        "home",
        "care"
    ],
    "wof:name":"Viahealth Home Care Inc",
    "wof:placetype":"venue"
},
  "geometry": {"coordinates":[-77.55953,43.153687],"type":"Point"}
}