{
  "type": "Feature",
  "properties": {
    "iso:country":"US",
    "sg:address":"93 Mystic Dr",
    "sg:city":"Ossining",
    "sg:classifiers":[
        {
            "category":"Professional",
            "subcategory":"Management & Consulting",
            "type":"Services"
        }
    ],
    "sg:phone":"+1   ",
    "sg:postcode":"10562",
    "sg:province":"NY",
    "sg:tags":[
        "software"
    ],
    "wof:name":"Creationware Inc",
    "wof:placetype":"venue"
},
  "geometry": {"coordinates":[-73.87167599999999,41.181138],"type":"Point"}
}