{
  "type": "Feature",
  "properties": {
    "addr:full":"383 Bleecker St New York NY 10014",
    "addr:housenumber":"383",
    "addr:postcode":"10014",
    "addr:street":"Bleecker St",
    "iso:country":"US",
    "sg:address":"383 Bleecker St",
    "sg:city":"New York",
    "sg:classifiers":[
        {
            "category":"Shopping",
            "subcategory":"Clothing, Apparel, & Fashions",
            "type":"Retail Goods"
        }
    ],
    "sg:phone":"+1 212 206 1844",
    "sg:postcode":"10014",
    "sg:province":"NY",
    "wof:name":"L'Uomo",
    "wof:placetype":"venue"
},
  "geometry": {"coordinates":[-74.00474699999999,40.73466],"type":"Point"}
}