{
  "type": "Feature",
  "properties": {
    "addr:full":"5508 12th Ave Brooklyn NY 11219",
    "addr:housenumber":"5508",
    "addr:postcode":"11219",
    "addr:street":"12Th Ave",
    "iso:country":"US",
    "sg:address":"5508 12th Ave",
    "sg:city":"Brooklyn",
    "sg:classifiers":[
        {
            "category":"Organizations",
            "subcategory":"Religious Organization",
            "type":"Services"
        }
    ],
    "sg:phone":"+1 718 435 4894",
    "sg:postcode":"11219",
    "sg:province":"NY",
    "sg:tags":[
        "clergy"
    ],
    "wof:name":"Shimshon Bender",
    "wof:placetype":"venue"
},
  "geometry": {"coordinates":[-73.99842,40.632527],"type":"Point"}
}