{
  "type": "Feature",
  "properties": {
    "iso:country":"US",
    "sg:address":"233 7th St Ste 101",
    "sg:city":"Garden City",
    "sg:classifiers":[
        {
            "category":"Health Services",
            "subcategory":"Doctor",
            "type":"Services"
        }
    ],
    "sg:phone":"+1 516 742 5344",
    "sg:postcode":"11530",
    "sg:province":"NY",
    "wof:name":"Montoni Vincenzo DO",
    "wof:placetype":"venue"
},
  "geometry": {"coordinates":[-73.63207800000001,40.725838],"type":"Point"}
}