{
  "type": "Feature",
  "properties": {
    "addr:full":"221 River St Troy NY 12180",
    "addr:housenumber":"221",
    "addr:postcode":"12180",
    "addr:street":"River St",
    "iso:country":"US",
    "sg:address":"221 River St",
    "sg:city":"Troy",
    "sg:classifiers":[
        {
            "category":"Professional",
            "subcategory":"Lawyer & Legal Services",
            "type":"Services"
        }
    ],
    "sg:phone":"+1 518 273 0000",
    "sg:postcode":"12180",
    "sg:province":"NY",
    "sg:tags":[
        "attorney"
    ],
    "wof:name":"Seymour Fox Law Offices",
    "wof:placetype":"venue"
},
  "geometry": {"coordinates":[-73.69012499999999,42.732605],"type":"Point"}
}