{
  "type": "Feature",
  "properties": {
    "iso:country":"US",
    "sg:address":"159 N Allen St",
    "sg:city":"Albany",
    "sg:classifiers":[
        {
            "category":"Wholesale",
            "subcategory":"Groceries",
            "type":"Manufacturing & Wholesale Goods"
        }
    ],
    "sg:phone":"+1 518 435 0466",
    "sg:postcode":"12206",
    "sg:province":"NY",
    "sg:tags":[
        "general"
    ],
    "wof:name":"Stop One Market",
    "wof:placetype":"venue"
},
  "geometry": {"coordinates":[-73.78666,42.671305],"type":"Point"}
}