{
  "type": "Feature",
  "properties": {
    "addr:full":"23 Hillside Ave Glen Head NY 11545",
    "addr:housenumber":"23",
    "addr:postcode":"11545",
    "addr:street":"Hillside Ave Glen",
    "iso:country":"US",
    "sg:address":"23 Hillside Ave",
    "sg:city":"Glen Head",
    "sg:classifiers":[
        {
            "category":"Shopping",
            "subcategory":"Gifts & Souvenirs",
            "type":"Retail Goods"
        }
    ],
    "sg:phone":"+1   ",
    "sg:postcode":"11545",
    "sg:province":"NY",
    "wof:name":"Bakowski S Gift Shop",
    "wof:placetype":"venue"
},
  "geometry": {"coordinates":[-73.61710600000001,40.837863],"type":"Point"}
}