{
  "type": "Feature",
  "properties": {
    "iso:country":"US",
    "sg:address":"6135 Junction Blvd",
    "sg:city":"Elmhurst",
    "sg:classifiers":[
        {
            "category":"Building & Trades",
            "subcategory":"Construction",
            "type":"Services"
        }
    ],
    "sg:phone":"+1 718 275 3476",
    "sg:postcode":"11373",
    "sg:province":"NY",
    "sg:tags":[
        "contractor"
    ],
    "wof:name":"Bovis Lend Lease",
    "wof:placetype":"venue"
},
  "geometry": {"coordinates":[-73.863957,40.733393],"type":"Point"}
}