{
  "type": "Feature",
  "properties": {
    "addr:full":"1546 47th St Brooklyn NY 11219",
    "addr:housenumber":"1546",
    "addr:postcode":"11219",
    "addr:street":"47Th St",
    "iso:country":"US",
    "sg:address":"1546 47th St",
    "sg:city":"Brooklyn",
    "sg:classifiers":[
        {
            "category":"Organizations",
            "subcategory":"Religious Organization",
            "type":"Services"
        }
    ],
    "sg:phone":"+1   ",
    "sg:postcode":"11219",
    "sg:province":"NY",
    "wof:name":"Parsonage",
    "wof:placetype":"venue"
},
  "geometry": {"coordinates":[-73.985176,40.632722],"type":"Point"}
}