{
  "type": "Feature",
  "properties": {
    "iso:country":"US",
    "sg:address":"735 Argyle Rd",
    "sg:city":"Brooklyn",
    "sg:classifiers":[
        {
            "category":"Wholesale",
            "subcategory":"Stationery",
            "type":"Manufacturing & Wholesale Goods"
        },
        {
            "category":"Manufacturing",
            "subcategory":"Printing",
            "type":"Manufacturing & Wholesale Goods"
        }
    ],
    "sg:phone":"+1 718 421 7000",
    "sg:postcode":"11230",
    "sg:province":"NY",
    "sg:tags":[
        "map",
        "publishing"
    ],
    "wof:name":"Gentle Giant Publishing Inc",
    "wof:placetype":"venue"
},
  "geometry": {"coordinates":[-73.964196,40.630596],"type":"Point"}
}