{
  "type": "Feature",
  "properties": {
    "iso:country":"US",
    "sg:address":"707 E Garden St",
    "sg:city":"Rome",
    "sg:classifiers":[
        {
            "category":"Social Services",
            "type":"Services"
        }
    ],
    "sg:phone":"+1 315 337 0912",
    "sg:postcode":"13440",
    "sg:province":"NY",
    "sg:tags":[
        "human"
    ],
    "wof:name":"Bert D Desha",
    "wof:placetype":"venue"
},
  "geometry": {"coordinates":[-75.44035599999999,43.211914],"type":"Point"}
}