{
  "type": "Feature",
  "properties": {
    "addr:full":"1098 W State Rd Cortland NY 13045",
    "addr:housenumber":"1098",
    "addr:postcode":"13045",
    "addr:street":"W State Rd",
    "iso:country":"US",
    "sg:address":"1098 W State Rd",
    "sg:city":"Cortland",
    "sg:classifiers":[
        {
            "category":"Restaurant",
            "type":"Food & Drink"
        }
    ],
    "sg:phone":"+1   ",
    "sg:postcode":"13045",
    "sg:province":"NY",
    "sg:tags":[
        "eating"
    ],
    "wof:name":"Koffee Kup Restaurant",
    "wof:placetype":"venue"
},
  "geometry": {"coordinates":[-76.200135,42.511635],"type":"Point"}
}