{
  "type": "Feature",
  "properties": {
    "iso:country":"US",
    "sg:address":"54 E Main St",
    "sg:city":"Norwich",
    "sg:classifiers":[
        {
            "category":"Food & Beverages",
            "subcategory":"Groceries & Convenience Stores",
            "type":"Retail Goods"
        }
    ],
    "sg:phone":"+1 607 336 4244",
    "sg:postcode":"13815",
    "sg:province":"NY",
    "sg:tags":[
        "grocer"
    ],
    "wof:name":"Tops Friendly Market",
    "wof:placetype":"venue"
},
  "geometry": {"coordinates":[-75.520309,42.531412],"type":"Point"}
}