{
  "type": "Feature",
  "properties": {
    "iso:country":"US",
    "sg:address":"5 Hibbard St",
    "sg:city":"Amsterdam",
    "sg:classifiers":[
        {
            "category":"Professional",
            "subcategory":"Lawyer & Legal Services",
            "type":"Services"
        }
    ],
    "sg:phone":"+1 518 842 5640",
    "sg:postcode":"12010",
    "sg:province":"NY",
    "sg:tags":[
        "attorney"
    ],
    "wof:name":"Frederick A Partyka Law Office",
    "wof:placetype":"venue"
},
  "geometry": {"coordinates":[-74.181366,42.936284],"type":"Point"}
}