{
  "type": "Feature",
  "properties": {
    "addr:full":"513 Kennicut Hill Rd Mahopac NY 10541",
    "addr:housenumber":"513",
    "addr:postcode":"10541",
    "addr:street":"Kennicut Hill Rd",
    "iso:country":"US",
    "sg:address":"513 Kennicut Hill Rd",
    "sg:city":"Mahopac",
    "sg:classifiers":[
        {
            "category":"Social Services",
            "subcategory":"Child Care",
            "type":"Services"
        }
    ],
    "sg:phone":"+1   ",
    "sg:postcode":"10541",
    "sg:province":"NY",
    "sg:tags":[
        "day"
    ],
    "wof:name":"Cousinss Home Day Care",
    "wof:placetype":"venue"
},
  "geometry": {"coordinates":[-73.73416,41.368788],"type":"Point"}
}