{
  "type": "Feature",
  "properties": {
    "addr:full":"8502 Farmgate Path Cicero NY 13039",
    "addr:housenumber":"8502",
    "addr:postcode":"13039",
    "addr:street":"Farmgate Path",
    "iso:country":"US",
    "sg:address":"8502 Farmgate Path",
    "sg:city":"Cicero",
    "sg:classifiers":[
        {
            "category":"Education",
            "subcategory":"Dance Studio",
            "type":"Public Place"
        }
    ],
    "sg:phone":"+1 315 699 2355",
    "sg:postcode":"13039",
    "sg:province":"NY",
    "wof:name":"C M C Dance Company",
    "wof:placetype":"venue"
},
  "geometry": {"coordinates":[-76.08280999999999,43.186467],"type":"Point"}
}