{
  "type": "Feature",
  "properties": {
    "iso:country":"US",
    "sg:address":"134 Ave C",
    "sg:city":"New York",
    "sg:classifiers":[
        {
            "category":"Banks & Credit Unions",
            "subcategory":"Bank",
            "type":"Services"
        }
    ],
    "sg:phone":"+1 212 598 0022",
    "sg:postcode":"10009",
    "sg:province":"NY",
    "wof:name":"Lower East Side People's CU",
    "wof:placetype":"venue"
},
  "geometry": {"coordinates":[-73.978077,40.724954],"type":"Point"}
}