{
  "type": "Feature",
  "properties": {
    "addr:full":"520 8th Avenue New York NY 10018",
    "addr:housenumber":"520",
    "addr:postcode":"10018",
    "addr:street":"8Th Avenue",
    "iso:country":"US",
    "sg:address":"520 8th Avenue",
    "sg:city":"New York",
    "sg:classifiers":[
        {
            "category":"Education",
            "subcategory":"Special Training",
            "type":"Public Place"
        },
        {
            "category":"Education",
            "subcategory":"School",
            "type":"Public Place"
        }
    ],
    "sg:phone":"+1 212 714 2845",
    "sg:postcode":"10018",
    "sg:province":"NY",
    "sg:tags":[
        "high",
        "middle",
        "specialty",
        "elementary"
    ],
    "wof:name":"Lucid Ny",
    "wof:placetype":"venue"
},
  "geometry": {"coordinates":[-73.992514,40.75345],"type":"Point"}
}