{
  "type": "Feature",
  "properties": {
    "iso:country":"US",
    "sg:address":"2233 Yellow Tavern Rd",
    "sg:city":"Waterloo",
    "sg:classifiers":[
        {
            "category":"Organizations",
            "subcategory":"Religious Organization",
            "type":"Services"
        }
    ],
    "sg:phone":"+1 315 549 0140",
    "sg:postcode":"13165",
    "sg:province":"NY",
    "sg:tags":[
        "church"
    ],
    "wof:name":"Fayette Mennonite Church",
    "wof:placetype":"venue"
},
  "geometry": {"coordinates":[-76.884052,42.849379],"type":"Point"}
}