{
  "type": "Feature",
  "properties": {
    "addr:full":"48-15 Queens Blvd Woodside NY 11377",
    "addr:housenumber":"48-15",
    "addr:postcode":"11377",
    "addr:street":"Queens Blvd",
    "iso:country":"US",
    "sg:address":"48-15 Queens Blvd",
    "sg:city":"Woodside",
    "sg:classifiers":[
        {
            "category":"Health Services",
            "subcategory":"Optometrist",
            "type":"Services"
        }
    ],
    "sg:phone":"+1 718 205 9760",
    "sg:postcode":"11377",
    "sg:province":"NY",
    "wof:name":"Pearle Vision",
    "wof:placetype":"venue"
},
  "geometry": {"coordinates":[-73.91677,40.743114],"type":"Point"}
}