{
  "type": "Feature",
  "properties": {
    "iso:country":"US",
    "sg:address":"9 Gerhard Rd",
    "sg:city":"Plainview",
    "sg:classifiers":[
        {
            "category":"Professional",
            "subcategory":"Management & Consulting",
            "type":"Services"
        }
    ],
    "sg:phone":"+1 516 433 9000",
    "sg:postcode":"11803",
    "sg:province":"NY",
    "sg:tags":[
        "real estate"
    ],
    "wof:name":"Concorde Real Estate Services",
    "wof:placetype":"venue"
},
  "geometry": {"coordinates":[-73.47755600000001,40.772539],"type":"Point"}
}