{
  "type": "Feature",
  "properties": {
    "iso:country":"US",
    "sg:address":"8 Tower St",
    "sg:city":"Red Hook",
    "sg:classifiers":[
        {
            "category":"Building & Trades",
            "subcategory":"Plumbing",
            "type":"Services"
        }
    ],
    "sg:phone":"+1 845 758 3191",
    "sg:postcode":"12571",
    "sg:province":"NY",
    "sg:tags":[
        "tank",
        "septic"
    ],
    "wof:name":"Marvin A Brial Septic Svc",
    "wof:placetype":"venue"
},
  "geometry": {"coordinates":[-73.869462,41.99445],"type":"Point"}
}