{
  "type": "Feature",
  "properties": {
    "addr:full":"6341 Dutch Street Rd Wolcott NY 14590",
    "addr:housenumber":"6341",
    "addr:postcode":"14590",
    "addr:street":"Dutch Street Rd",
    "iso:country":"US",
    "sg:address":"6341 Dutch Street Rd",
    "sg:city":"Wolcott",
    "sg:classifiers":[
        {
            "category":"Farming",
            "subcategory":"Farm",
            "type":"Manufacturing & Wholesale Goods"
        }
    ],
    "sg:phone":"+1 315 594 1060",
    "sg:postcode":"14590",
    "sg:province":"NY",
    "wof:name":"Cahoon Farms",
    "wof:placetype":"venue"
},
  "geometry": {"coordinates":[-76.86176500000001,43.233117],"type":"Point"}
}