{
  "type": "Feature",
  "properties": {
    "iso:country":"US",
    "sg:address":"5692 Pittsford Palmyra Rd",
    "sg:city":"Pittsford",
    "sg:classifiers":[
        {
            "category":"Wholesale",
            "subcategory":"Construction Materials",
            "type":"Manufacturing & Wholesale Goods"
        },
        {
            "category":"Building & Trades",
            "subcategory":"Construction",
            "type":"Services"
        }
    ],
    "sg:phone":"+1 585 248 3647",
    "sg:postcode":"14534",
    "sg:province":"NY",
    "sg:tags":[
        "fence-sales",
        "fence-wholesale",
        "manufacturer",
        "contractor"
    ],
    "wof:name":"K 9 Containment Distributing",
    "wof:placetype":"venue"
},
  "geometry": {"coordinates":[-77.487679,43.079021],"type":"Point"}
}