{
  "type": "Feature",
  "properties": {
    "iso:country":"US",
    "sg:address":"970 Payne Ave",
    "sg:city":"North Tonawanda",
    "sg:classifiers":[
        {
            "category":"Personal",
            "subcategory":"Beauty Salon",
            "type":"Services"
        }
    ],
    "sg:phone":"+1 716 695 6985",
    "sg:postcode":"14120",
    "sg:province":"NY",
    "sg:tags":[
        "manicuring"
    ],
    "wof:name":"N T Nails",
    "wof:placetype":"venue"
},
  "geometry": {"coordinates":[-78.87754099999999,43.049726],"type":"Point"}
}