{
  "type": "Feature",
  "properties": {
    "addr:full":"2 Ketcham Pl Melville NY 11747",
    "addr:housenumber":"2",
    "addr:postcode":"11747",
    "addr:street":"Ketcham Pl",
    "iso:country":"US",
    "sg:address":"2 Ketcham Pl",
    "sg:city":"Melville",
    "sg:classifiers":[
        {
            "category":"Utilities",
            "subcategory":"Mobile Phone",
            "type":"Services"
        }
    ],
    "sg:phone":"+1 631 385 0970",
    "sg:postcode":"11747",
    "sg:province":"NY",
    "sg:tags":[
        "telephone",
        "cellular"
    ],
    "wof:name":"Cellular America",
    "wof:placetype":"venue"
},
  "geometry": {"coordinates":[-73.412857,40.802794],"type":"Point"}
}