{
  "type": "Feature",
  "properties": {
    "addr:full":"3541 72nd St Jackson Heights NY 11372",
    "addr:housenumber":"3541",
    "addr:postcode":"11372",
    "addr:street":"72Nd St",
    "iso:country":"US",
    "sg:address":"3541 72nd St",
    "sg:city":"Jackson Heights",
    "sg:classifiers":[
        {
            "category":"Shopping",
            "subcategory":"Computers & Home Electronics",
            "type":"Retail Goods"
        }
    ],
    "sg:phone":"+1 718 426 8555",
    "sg:postcode":"11372",
    "sg:province":"NY",
    "sg:website":"www.collegiumsound.com",
    "wof:name":"Collegium Sound Inc",
    "wof:placetype":"venue"
},
  "geometry": {"coordinates":[-73.893799,40.750401],"type":"Point"}
}