{
  "type": "Feature",
  "properties": {
    "addr:full":"418 Lafayette St New York NY 10003",
    "addr:housenumber":"418",
    "addr:postcode":"10003",
    "addr:street":"Lafayette St",
    "iso:country":"US",
    "sg:address":"418 Lafayette St",
    "sg:city":"New York",
    "sg:classifiers":[
        {
            "category":"Health Services",
            "subcategory":"Doctor",
            "type":"Services"
        }
    ],
    "sg:phone":"+1 212 992 9180",
    "sg:postcode":"10003",
    "sg:province":"NY",
    "sg:tags":[
        "dermatologist"
    ],
    "wof:name":"Jelinek J E MD",
    "wof:placetype":"venue"
},
  "geometry": {"coordinates":[-73.992302,40.728901],"type":"Point"}
}