{
  "type": "Feature",
  "properties": {
    "addr:full":"18 E 125th St New York NY 10035",
    "addr:housenumber":"18",
    "addr:postcode":"10035",
    "addr:street":"E 125Th St",
    "iso:country":"US",
    "sg:address":"18 E 125th St",
    "sg:city":"New York",
    "sg:classifiers":[
        {
            "category":"Food & Beverages",
            "subcategory":"Specialty",
            "type":"Retail Goods"
        }
    ],
    "sg:phone":"+1   ",
    "sg:postcode":"10035",
    "sg:province":"NY",
    "sg:tags":[
        "health",
        "store"
    ],
    "wof:name":"Solar Gardens",
    "wof:placetype":"venue"
},
  "geometry": {"coordinates":[-73.941197,40.805957],"type":"Point"}
}