{
  "type": "Feature",
  "properties": {
    "iso:country":"US",
    "sg:address":"1296 Jackson Rd",
    "sg:city":"Webster",
    "sg:classifiers":[
        {
            "category":"Insurance",
            "subcategory":"Hazard Insurance",
            "type":"Services"
        }
    ],
    "sg:phone":"+1 585 217 9176",
    "sg:postcode":"14580",
    "sg:province":"NY",
    "wof:name":"Robert C Wright",
    "wof:placetype":"venue"
},
  "geometry": {"coordinates":[-77.443305,43.186723],"type":"Point"}
}