{
  "type": "Feature",
  "properties": {
    "addr:full":"1809 Gravesend Neck Rd Brooklyn NY 11229",
    "addr:housenumber":"1809",
    "addr:postcode":"11229",
    "addr:street":"Gravesend Neck Rd",
    "iso:country":"US",
    "sg:address":"1809 Gravesend Neck Rd",
    "sg:city":"Brooklyn",
    "sg:classifiers":[
        {
            "category":"Organizations",
            "subcategory":"Labor Organization",
            "type":"Services"
        }
    ],
    "sg:phone":"+1   ",
    "sg:postcode":"11229",
    "sg:province":"NY",
    "wof:name":"Local 3 Prmnt Dist Orgnization",
    "wof:placetype":"venue"
},
  "geometry": {"coordinates":[-73.952113,40.596191],"type":"Point"}
}