{
  "type": "Feature",
  "properties": {
    "addr:full":"163 Main St East Aurora NY 14052",
    "addr:housenumber":"163",
    "addr:postcode":"14052",
    "addr:street":"Main St",
    "iso:country":"US",
    "sg:address":"163 Main St",
    "sg:city":"East Aurora",
    "sg:classifiers":[
        {
            "category":"Food & Beverages",
            "subcategory":"Liquor & Beverages",
            "type":"Retail Goods"
        }
    ],
    "sg:phone":"+1   ",
    "sg:postcode":"14052",
    "sg:province":"NY",
    "sg:tags":[
        "store"
    ],
    "wof:name":"Reeds Liquor Store Inc",
    "wof:placetype":"venue"
},
  "geometry": {"coordinates":[-78.62817,42.767689],"type":"Point"}
}