{
  "type": "Feature",
  "properties": {
    "iso:country":"US",
    "sg:address":"12 Plaza Pl",
    "sg:city":"Bronx",
    "sg:classifiers":[
        {
            "category":"Personal",
            "subcategory":"Beauty Salon",
            "type":"Services"
        }
    ],
    "sg:phone":"+1 718 822 8289",
    "sg:postcode":"10465",
    "sg:province":"NY",
    "wof:name":"Beauty Barn",
    "wof:placetype":"venue"
},
  "geometry": {"coordinates":[-73.80865,40.813461],"type":"Point"}
}