{
  "type": "Feature",
  "properties": {
    "iso:country":"US",
    "sg:address":"8 Tucker Pond Ct",
    "sg:city":"Troy",
    "sg:classifiers":[
        {
            "category":"Utilities",
            "subcategory":"Cable",
            "type":"Services"
        }
    ],
    "sg:phone":"+1   ",
    "sg:postcode":"12182",
    "sg:province":"NY",
    "sg:tags":[
        "television"
    ],
    "wof:name":"Pro Cable Services",
    "wof:placetype":"venue"
},
  "geometry": {"coordinates":[-73.609399,42.807263],"type":"Point"}
}