{
  "type": "Feature",
  "properties": {
    "addr:full":"268 Smith St Brooklyn NY 11231",
    "addr:housenumber":"268",
    "addr:postcode":"11231",
    "addr:street":"Smith St",
    "iso:country":"US",
    "sg:address":"268 Smith St",
    "sg:city":"Brooklyn",
    "sg:classifiers":[
        {
            "category":"Organizations",
            "subcategory":"Non-profit Organization",
            "type":"Services"
        }
    ],
    "sg:phone":"+1   ",
    "sg:postcode":"11231",
    "sg:province":"NY",
    "sg:tags":[
        "development",
        "shop",
        "agency",
        "community",
        "thrift"
    ],
    "wof:name":"Treasures Thrift Shop",
    "wof:placetype":"venue"
},
  "geometry": {"coordinates":[-73.993438,40.68252],"type":"Point"}
}