{
  "type": "Feature",
  "properties": {
    "addr:full":"105 Castle Rd Syracuse NY 13212",
    "addr:housenumber":"105",
    "addr:postcode":"13212",
    "addr:street":"Castle Rd",
    "iso:country":"US",
    "sg:address":"105 Castle Rd",
    "sg:city":"Syracuse",
    "sg:classifiers":[
        {
            "category":"Building & Trades",
            "subcategory":"Construction",
            "type":"Services"
        }
    ],
    "sg:phone":"+1 315 452 0483",
    "sg:postcode":"13212",
    "sg:province":"NY",
    "sg:tags":[
        "house"
    ],
    "wof:name":"Bryan Construction",
    "wof:placetype":"venue"
},
  "geometry": {"coordinates":[-76.15436,43.125937],"type":"Point"}
}