{
  "type": "Feature",
  "properties": {
    "addr:full":"214 Filon Ave Rochester NY 14622",
    "addr:housenumber":"214",
    "addr:postcode":"14622",
    "addr:street":"Filon Ave",
    "iso:country":"US",
    "sg:address":"214 Filon Ave",
    "sg:city":"Rochester",
    "sg:classifiers":[
        {
            "category":"Real Estate",
            "subcategory":"Real Estate Agent",
            "type":"Services"
        }
    ],
    "sg:phone":"+1 585 323 2635",
    "sg:postcode":"14622",
    "sg:province":"NY",
    "wof:name":"Brooklyn Sports Management",
    "wof:placetype":"venue"
},
  "geometry": {"coordinates":[-77.54781,43.221493],"type":"Point"}
}