{
  "type": "Feature",
  "properties": {
    "addr:full":"396 Broadway Kingston NY 12401",
    "addr:housenumber":"396",
    "addr:postcode":"12401",
    "addr:street":"Broadway",
    "iso:country":"US",
    "sg:address":"396 Broadway",
    "sg:city":"Kingston",
    "sg:classifiers":[
        {
            "category":"Professional",
            "type":"Services"
        }
    ],
    "sg:phone":"+1 845 331 2880",
    "sg:postcode":"12401",
    "sg:province":"NY",
    "sg:tags":[
        "establishment"
    ],
    "wof:name":"Jzanus LTD",
    "wof:placetype":"venue"
},
  "geometry": {"coordinates":[-73.99605699999999,41.926558],"type":"Point"}
}