{
  "type": "Feature",
  "properties": {
    "iso:country":"US",
    "sg:address":"1231 Hawthorne Dr E",
    "sg:city":"Wantagh",
    "sg:classifiers":[
        {
            "category":"Building & Trades",
            "subcategory":"Landscaping Services",
            "type":"Services"
        }
    ],
    "sg:phone":"+1 516 826 8280",
    "sg:postcode":"11793",
    "sg:province":"NY",
    "sg:tags":[
        "landscape",
        "contractor"
    ],
    "wof:name":"O'Connor Landscaping Svc Corp",
    "wof:placetype":"venue"
},
  "geometry": {"coordinates":[-73.502241,40.691598],"type":"Point"}
}