{
  "type": "Feature",
  "properties": {
    "addr:full":"224 Church St Poughkeepsie NY 12601",
    "addr:housenumber":"224",
    "addr:postcode":"12601",
    "addr:street":"Church St",
    "iso:country":"US",
    "sg:address":"224 Church St",
    "sg:city":"Poughkeepsie",
    "sg:classifiers":[
        {
            "category":"Professional",
            "subcategory":"Lawyer & Legal Services",
            "type":"Services"
        }
    ],
    "sg:phone":"+1 845 471 4221",
    "sg:postcode":"12601",
    "sg:province":"NY",
    "sg:tags":[
        "attorney"
    ],
    "wof:name":"Roland E Butts",
    "wof:placetype":"venue"
},
  "geometry": {"coordinates":[-73.92463499999999,41.700154],"type":"Point"}
}