{
  "type": "Feature",
  "properties": {
    "iso:country":"US",
    "sg:address":"615 West Ave",
    "sg:city":"Medina",
    "sg:classifiers":[
        {
            "category":"Recreation",
            "type":"Entertainment"
        },
        {
            "category":"Organizations",
            "subcategory":"Community Association",
            "type":"Services"
        }
    ],
    "sg:phone":"+1 585 798 4544",
    "sg:postcode":"14103",
    "sg:province":"NY",
    "sg:tags":[
        "club",
        "membership",
        "sport"
    ],
    "wof:name":"Senior Citizens Center",
    "wof:placetype":"venue"
},
  "geometry": {"coordinates":[-78.388712,43.217898],"type":"Point"}
}