{
  "type": "Feature",
  "properties": {
    "addr:full":"12 W Main St Elmsford NY 10523",
    "addr:housenumber":"12",
    "addr:postcode":"10523",
    "addr:street":"W Main St",
    "iso:country":"US",
    "sg:address":"12 W Main St",
    "sg:city":"Elmsford",
    "sg:classifiers":[
        {
            "category":"Restaurant",
            "type":"Food & Drink"
        }
    ],
    "sg:menulink":"http://www.allmenus.com/ny/greenburgh/261623-rinis-restaurant/menu/",
    "sg:phone":"+1 914 592 6799",
    "sg:postcode":"10523",
    "sg:province":"NY",
    "wof:name":"Rinis Restaurant",
    "wof:placetype":"venue"
},
  "geometry": {"coordinates":[-73.822014,41.055751],"type":"Point"}
}