{
  "type": "Feature",
  "properties": {
    "addr:full":"10 Sage Ests Albany NY 12204",
    "addr:housenumber":"10",
    "addr:postcode":"12204",
    "addr:street":"Sage Ests",
    "iso:country":"US",
    "sg:address":"10 Sage Ests",
    "sg:city":"Albany",
    "sg:classifiers":[
        {
            "category":"Organizations",
            "subcategory":"Religious Organization",
            "type":"Services"
        }
    ],
    "sg:phone":"+1   ",
    "sg:postcode":"12204",
    "sg:province":"NY",
    "wof:name":"Christan Partners LP",
    "wof:placetype":"venue"
},
  "geometry": {"coordinates":[-73.73480499999999,42.694163],"type":"Point"}
}