{
  "type": "Feature",
  "properties": {
    "iso:country":"US",
    "sg:address":"453 New York Ave",
    "sg:city":"Huntington",
    "sg:classifiers":[
        {
            "category":"Health Services",
            "subcategory":"Health Practitioner",
            "type":"Services"
        },
        {
            "category":"Health Services",
            "subcategory":"Chiropractor",
            "type":"Services"
        }
    ],
    "sg:phone":"+1 631 673 4840",
    "sg:postcode":"11743",
    "sg:province":"NY",
    "sg:tags":[
        "acupuncture"
    ],
    "wof:name":"Connor Jeanne M Chirprctr",
    "wof:placetype":"venue"
},
  "geometry": {"coordinates":[-73.423401,40.866402],"type":"Point"}
}