{
  "type": "Feature",
  "properties": {
    "addr:full":"60 Sutton Pl S New York NY 10022",
    "addr:housenumber":"60",
    "addr:postcode":"10022",
    "addr:street":"Sutton Pl S",
    "iso:country":"US",
    "sg:address":"60 Sutton Pl S",
    "sg:city":"New York",
    "sg:classifiers":[
        {
            "category":"Health Services",
            "subcategory":"Doctor",
            "type":"Services"
        }
    ],
    "sg:phone":"+1 212 838 2325",
    "sg:postcode":"10022",
    "sg:province":"NY",
    "sg:tags":[
        "physician",
        "surgeon"
    ],
    "wof:name":"Wayne Myers MD",
    "wof:placetype":"venue"
},
  "geometry": {"coordinates":[-73.962234,40.755402],"type":"Point"}
}