{
  "type": "Feature",
  "properties": {
    "iso:country":"US",
    "sg:address":"223 Dosoris Ln",
    "sg:city":"Glen Cove",
    "sg:classifiers":[
        {
            "category":"Personal",
            "subcategory":"Barber",
            "type":"Services"
        }
    ],
    "sg:phone":"+1 516 674 8530",
    "sg:postcode":"11542",
    "sg:province":"NY",
    "wof:name":"Yan's Barber Palace",
    "wof:placetype":"venue"
},
  "geometry": {"coordinates":[-73.63063099999999,40.883323],"type":"Point"}
}