{
  "type": "Feature",
  "properties": {
    "iso:country":"US",
    "sg:address":"575 Soundview Avenue",
    "sg:city":"Bronx",
    "sg:classifiers":[
        {
            "category":"Social Services",
            "subcategory":"Child Care",
            "type":"Services"
        }
    ],
    "sg:phone":"+1 718 991 1500",
    "sg:postcode":"10473",
    "sg:province":"NY",
    "sg:tags":[
        "day"
    ],
    "wof:name":"Seabury Day Care Corporation",
    "wof:placetype":"venue"
},
  "geometry": {"coordinates":[-73.861512,40.816813],"type":"Point"}
}