{
  "type": "Feature",
  "properties": {
    "iso:country":"US",
    "sg:address":"60 Fifth Avenue",
    "sg:city":"New York",
    "sg:classifiers":[
        {
            "category":"Arts & Performance",
            "subcategory":"Art Gallery",
            "type":"Entertainment"
        }
    ],
    "sg:phone":"+1 212 206 5549",
    "sg:postcode":"10079",
    "sg:province":"NY",
    "sg:website":"www.forbesgalleries.com",
    "wof:name":"Forbes Magazine Galleries",
    "wof:placetype":"venue"
},
  "geometry": {"coordinates":[-73.994321,40.735022],"type":"Point"}
}