{
  "type": "Feature",
  "properties": {
    "addr:full":"142 E 16 St New York NY 10003",
    "addr:housenumber":"142;16",
    "addr:postcode":"10003",
    "addr:street":"E",
    "iso:country":"US",
    "sg:address":"142 E 16 St",
    "sg:city":"New York",
    "sg:classifiers":[
        {
            "category":"Professional",
            "subcategory":"Lawyer & Legal Services",
            "type":"Services"
        }
    ],
    "sg:phone":"+1 212 477 6600",
    "sg:postcode":"10003",
    "sg:province":"NY",
    "sg:tags":[
        "attorney"
    ],
    "wof:name":"Julia Pamela Heit Attorney",
    "wof:placetype":"venue"
},
  "geometry": {"coordinates":[-73.98656800000001,40.73473],"type":"Point"}
}