{
  "type": "Feature",
  "properties": {
    "addr:full":"383 Monroe St Honeoye Falls NY 14472",
    "addr:housenumber":"383",
    "addr:postcode":"14472",
    "addr:street":"Monroe St",
    "iso:country":"US",
    "sg:address":"383 Monroe St",
    "sg:city":"Honeoye Falls",
    "sg:classifiers":[
        {
            "category":"Retail",
            "subcategory":"Veterinary Services",
            "type":"Services"
        }
    ],
    "sg:phone":"+1 585 624 1088",
    "sg:postcode":"14472",
    "sg:province":"NY",
    "wof:name":"Guild Phillip V Dvm",
    "wof:placetype":"venue"
},
  "geometry": {"coordinates":[-77.610237,42.959866],"type":"Point"}
}