{
  "type": "Feature",
  "properties": {
    "addr:full":"13550 Bloomingdale Rd Akron NY 14001",
    "addr:housenumber":"13550",
    "addr:postcode":"14001",
    "addr:street":"Bloomingdale Rd",
    "iso:country":"US",
    "sg:address":"13550 Bloomingdale Rd",
    "sg:city":"Akron",
    "sg:classifiers":[
        {
            "category":"Wholesale",
            "subcategory":"Farm Supplies",
            "type":"Manufacturing & Wholesale Goods"
        }
    ],
    "sg:phone":"+1 716 542 9922",
    "sg:postcode":"14001",
    "sg:province":"NY",
    "sg:tags":[
        "feed"
    ],
    "wof:name":"Akron Ag Products",
    "wof:placetype":"venue"
},
  "geometry": {"coordinates":[-78.48214900000001,43.028785],"type":"Point"}
}