{
  "type": "Feature",
  "properties": {
    "iso:country":"US",
    "sg:address":"47 Pilling St",
    "sg:city":"Brooklyn",
    "sg:classifiers":[
        {
            "category":"Banks & Credit Unions",
            "subcategory":"Financial Services",
            "type":"Services"
        }
    ],
    "sg:phone":"+1 718 455 8056",
    "sg:postcode":"11207",
    "sg:province":"NY",
    "sg:tags":[
        "company",
        "holding"
    ],
    "wof:name":"Cali & Berthel Holding Corp",
    "wof:placetype":"venue"
},
  "geometry": {"coordinates":[-73.908841,40.68249],"type":"Point"}
}