{
  "type": "Feature",
  "properties": {
    "addr:full":"963 Route 6 Mahopac NY 10541",
    "addr:housenumber":"963",
    "addr:postcode":"10541",
    "addr:street":"Route 6",
    "iso:country":"US",
    "sg:address":"963 Route 6",
    "sg:city":"Mahopac",
    "sg:classifiers":[
        {
            "category":"Professional",
            "subcategory":"Lawyer & Legal Services",
            "type":"Services"
        }
    ],
    "sg:phone":"+1 845 628 4000",
    "sg:postcode":"10541",
    "sg:province":"NY",
    "wof:name":"Canfield Christopher M Atty",
    "wof:placetype":"venue"
},
  "geometry": {"coordinates":[-73.747136,41.355761],"type":"Point"}
}