{
  "type": "Feature",
  "properties": {
    "iso:country":"US",
    "sg:address":"4744 Clinton St",
    "sg:city":"Buffalo",
    "sg:classifiers":[
        {
            "category":"Retail",
            "subcategory":"Auto Repair",
            "type":"Services"
        }
    ],
    "sg:phone":"+1 716 668 9110",
    "sg:postcode":"14224",
    "sg:province":"NY",
    "sg:tags":[
        "shop",
        "collision"
    ],
    "wof:name":"Kling Bros Auto Service",
    "wof:placetype":"venue"
},
  "geometry": {"coordinates":[-78.698142,42.859914],"type":"Point"}
}