{
  "type": "Feature",
  "properties": {
    "addr:full":"3311 Church Ave Brooklyn NY 11203",
    "addr:housenumber":"3311",
    "addr:postcode":"11203",
    "addr:street":"Church Ave",
    "iso:country":"US",
    "sg:address":"3311 Church Ave",
    "sg:city":"Brooklyn",
    "sg:classifiers":[
        {
            "category":"Professional",
            "subcategory":"Management & Consulting",
            "type":"Services"
        }
    ],
    "sg:phone":"+1 718 856 2500",
    "sg:postcode":"11203",
    "sg:province":"NY",
    "sg:tags":[
        "consultant",
        "shipping"
    ],
    "wof:name":"Excelsior Properties Inc",
    "wof:placetype":"venue"
},
  "geometry": {"coordinates":[-73.945787,40.651074],"type":"Point"}
}