{
  "type": "Feature",
  "properties": {
    "iso:country":"US",
    "sg:address":"362 Main St W",
    "sg:city":"Rochester",
    "sg:classifiers":[
        {
            "category":"Autos & Motor Vehicles",
            "subcategory":"Fuel & Gas Station",
            "type":"Retail Goods"
        }
    ],
    "sg:phone":"+1   ",
    "sg:postcode":"14608",
    "sg:province":"NY",
    "sg:tags":[
        "station",
        "gasoline"
    ],
    "wof:name":"Palero",
    "wof:placetype":"venue"
},
  "geometry": {"coordinates":[-77.62421000000001,43.153118],"type":"Point"}
}