{
  "type": "Feature",
  "properties": {
    "iso:country":"US",
    "sg:address":"95 Harriman Woods Dr",
    "sg:city":"Harriman",
    "sg:classifiers":[
        {
            "category":"Professional",
            "subcategory":"Advertising",
            "type":"Services"
        }
    ],
    "sg:phone":"+1 845 783 3723",
    "sg:postcode":"10926",
    "sg:province":"NY",
    "sg:tags":[
        "agency"
    ],
    "wof:name":"Newage Advertising",
    "wof:placetype":"venue"
},
  "geometry": {"coordinates":[-74.155012,41.308876],"type":"Point"}
}