{
  "type": "Feature",
  "properties": {
    "addr:full":"6 Mott St Staten Island NY 10312",
    "addr:housenumber":"6",
    "addr:postcode":"10312",
    "addr:street":"Mott St",
    "iso:country":"US",
    "sg:address":"6 Mott St",
    "sg:city":"Staten Island",
    "sg:classifiers":[
        {
            "category":"Professional",
            "type":"Services"
        }
    ],
    "sg:phone":"+1 718 356 2782",
    "sg:postcode":"10312",
    "sg:province":"NY",
    "sg:tags":[
        "establishment"
    ],
    "wof:name":"Voisys System Corp",
    "wof:placetype":"venue"
},
  "geometry": {"coordinates":[-74.173749,40.5467],"type":"Point"}
}