{
  "type": "Feature",
  "properties": {
    "addr:full":"182 Main St Huntington NY 11743",
    "addr:housenumber":"182",
    "addr:postcode":"11743",
    "addr:street":"Main St",
    "iso:country":"US",
    "sg:address":"182 Main St",
    "sg:city":"Huntington",
    "sg:classifiers":[
        {
            "category":"Health Services",
            "subcategory":"Chiropractor",
            "type":"Services"
        }
    ],
    "sg:phone":"+1 631 673 2900",
    "sg:postcode":"11743",
    "sg:province":"NY",
    "wof:name":"Picard Daniel DC",
    "wof:placetype":"venue"
},
  "geometry": {"coordinates":[-73.424797,40.871399],"type":"Point"}
}