{
  "type": "Feature",
  "properties": {
    "addr:full":"11 Racquet Rd Newburgh NY 12550",
    "addr:housenumber":"11",
    "addr:postcode":"12550",
    "addr:street":"Racquet Rd",
    "iso:country":"US",
    "sg:address":"11 Racquet Rd",
    "sg:city":"Newburgh",
    "sg:classifiers":[
        {
            "category":"Banks & Credit Unions",
            "subcategory":"Investment Brokerage",
            "type":"Services"
        }
    ],
    "sg:phone":"+1 845 567 3930",
    "sg:postcode":"12550",
    "sg:province":"NY",
    "sg:tags":[
        "advisory",
        "financial"
    ],
    "wof:name":"New Horizon Asset Management",
    "wof:placetype":"venue"
},
  "geometry": {"coordinates":[-74.115731,41.523694],"type":"Point"}
}