{
  "type": "Feature",
  "properties": {
    "addr:full":"818 Franklin Ave Brooklyn NY 11225",
    "addr:housenumber":"818",
    "addr:postcode":"11225",
    "addr:street":"Franklin Ave",
    "iso:country":"US",
    "sg:address":"818 Franklin Ave",
    "sg:city":"Brooklyn",
    "sg:classifiers":[
        {
            "category":"Restaurant",
            "type":"Food & Drink"
        }
    ],
    "sg:phone":"+1   ",
    "sg:postcode":"11225",
    "sg:province":"NY",
    "sg:tags":[
        "eating"
    ],
    "wof:name":"Wing Zing Restaurant Corp",
    "wof:placetype":"venue"
},
  "geometry": {"coordinates":[-73.958291,40.670066],"type":"Point"}
}