{
  "type": "Feature",
  "properties": {
    "iso:country":"US",
    "sg:address":"3150 Schoolview Rd",
    "sg:city":"Eden",
    "sg:classifiers":[
        {
            "category":"Education",
            "subcategory":"Special Training",
            "type":"Public Place"
        }
    ],
    "sg:phone":"+1 716 992 3413",
    "sg:postcode":"14057",
    "sg:province":"NY",
    "sg:tags":[
        "center"
    ],
    "wof:name":"Board Of Cooperative Edu",
    "wof:placetype":"venue"
},
  "geometry": {"coordinates":[-78.87173199999999,42.660675],"type":"Point"}
}