{
  "type": "Feature",
  "properties": {
    "addr:full":"82 Church St East Aurora NY 14052",
    "addr:housenumber":"82",
    "addr:postcode":"14052",
    "addr:street":"Church St",
    "iso:country":"US",
    "sg:address":"82 Church St",
    "sg:city":"East Aurora",
    "sg:classifiers":[
        {
            "category":"Wholesale",
            "subcategory":"Stationery",
            "type":"Manufacturing & Wholesale Goods"
        }
    ],
    "sg:phone":"+1 716 652 4442",
    "sg:postcode":"14052",
    "sg:province":"NY",
    "sg:tags":[
        "paper"
    ],
    "wof:name":"A&L Box Co",
    "wof:placetype":"venue"
},
  "geometry": {"coordinates":[-78.610574,42.771893],"type":"Point"}
}