{
  "type": "Feature",
  "properties": {
    "addr:full":"524 E 187th St Bronx NY 10458",
    "addr:housenumber":"524",
    "addr:postcode":"10458",
    "addr:street":"E 187Th St",
    "iso:country":"US",
    "sg:address":"524 E 187th St",
    "sg:city":"Bronx",
    "sg:classifiers":[
        {
            "category":"Organizations",
            "subcategory":"Community Association",
            "type":"Services"
        }
    ],
    "sg:phone":"+1 718 231 6165",
    "sg:postcode":"10458",
    "sg:province":"NY",
    "sg:tags":[
        "military"
    ],
    "wof:name":"American Legion",
    "wof:placetype":"venue"
},
  "geometry": {"coordinates":[-73.89077399999999,40.857306],"type":"Point"}
}