{
  "type": "Feature",
  "properties": {
    "iso:country":"US",
    "sg:address":"449 N Queens Ave",
    "sg:city":"Massapequa",
    "sg:classifiers":[
        {
            "category":"Building & Trades",
            "subcategory":"Construction",
            "type":"Services"
        }
    ],
    "sg:phone":"+1 516 797 0120",
    "sg:postcode":"11758",
    "sg:province":"NY",
    "sg:tags":[
        "home",
        "general",
        "remodeling",
        "family",
        "contractor"
    ],
    "wof:name":"Vislocky Construction Corp",
    "wof:placetype":"venue"
},
  "geometry": {"coordinates":[-73.47707200000001,40.695664],"type":"Point"}
}