{
  "type": "Feature",
  "properties": {
    "iso:country":"US",
    "sg:address":"144 Main St",
    "sg:city":"S Glens Falls",
    "sg:classifiers":[
        {
            "category":"Education",
            "subcategory":"School",
            "type":"Public Place"
        }
    ],
    "sg:phone":"+1 518 792 1745",
    "sg:postcode":"12803",
    "sg:province":"NY",
    "wof:name":"Headstart Corinth S Glens Flls",
    "wof:placetype":"venue"
},
  "geometry": {"coordinates":[-73.633719,43.297246],"type":"Point"}
}