{
  "type": "Feature",
  "properties": {
    "addr:full":"233 7th St Garden City NY 11530",
    "addr:housenumber":"233",
    "addr:postcode":"11530",
    "addr:street":"7Th St",
    "iso:country":"US",
    "sg:address":"233 7th St",
    "sg:city":"Garden City",
    "sg:classifiers":[
        {
            "category":"Professional",
            "subcategory":"Accounting & Tax Preparation",
            "type":"Services"
        }
    ],
    "sg:phone":"+1 516 747 1991",
    "sg:postcode":"11530",
    "sg:province":"NY",
    "wof:name":"Gallo Cono J & Co CPA",
    "wof:placetype":"venue"
},
  "geometry": {"coordinates":[-73.634011,40.725325],"type":"Point"}
}