{
  "type": "Feature",
  "properties": {
    "iso:country":"US",
    "sg:address":"192 Lexington Ave",
    "sg:city":"New York",
    "sg:classifiers":[
        {
            "category":"Professional",
            "subcategory":"Business Services",
            "type":"Services"
        }
    ],
    "sg:phone":"+1 212 686 4576",
    "sg:postcode":"10016",
    "sg:province":"NY",
    "sg:tags":[
        "interior",
        "design"
    ],
    "wof:name":"Owen & Mandolfo Inc",
    "wof:placetype":"venue"
},
  "geometry": {"coordinates":[-73.98098,40.744689],"type":"Point"}
}