{
  "type": "Feature",
  "properties": {
    "addr:full":"27 15th St Brooklyn NY 11215",
    "addr:housenumber":"27",
    "addr:postcode":"11215",
    "addr:street":"15Th St",
    "iso:country":"US",
    "sg:address":"27 15th St",
    "sg:city":"Brooklyn",
    "sg:classifiers":[
        {
            "category":"Manufacturing",
            "subcategory":"Signs",
            "type":"Manufacturing & Wholesale Goods"
        }
    ],
    "sg:phone":"+1   ",
    "sg:postcode":"11215",
    "sg:province":"NY",
    "sg:tags":[
        "specialty",
        "merchandise",
        "mfg"
    ],
    "wof:name":"Voorhees Reports",
    "wof:placetype":"venue"
},
  "geometry": {"coordinates":[-73.99411499999999,40.667988],"type":"Point"}
}