{
  "type": "Feature",
  "properties": {
    "iso:country":"US",
    "sg:address":"6 Automation Ln",
    "sg:city":"Albany",
    "sg:classifiers":[
        {
            "category":"Professional",
            "subcategory":"Lawyer & Legal Services",
            "type":"Services"
        }
    ],
    "sg:phone":"+1 518 489 9985",
    "sg:postcode":"12205",
    "sg:province":"NY",
    "sg:tags":[
        "attorney"
    ],
    "wof:name":"Shatz Schwartz & Fentin",
    "wof:placetype":"venue"
},
  "geometry": {"coordinates":[-73.806817,42.720361],"type":"Point"}
}