{
  "type": "Feature",
  "properties": {
    "iso:country":"US",
    "sg:address":"12 Nottingham Ct",
    "sg:city":"Nesconset",
    "sg:classifiers":[
        {
            "category":"Wholesale",
            "subcategory":"Construction Materials",
            "type":"Manufacturing & Wholesale Goods"
        }
    ],
    "sg:phone":"+1 631 979 9719",
    "sg:postcode":"11767",
    "sg:province":"NY",
    "sg:tags":[
        "supply",
        "kitchen",
        "cabinet"
    ],
    "wof:name":"Impressive Kitchen and More",
    "wof:placetype":"venue"
},
  "geometry": {"coordinates":[-73.144919,40.846819],"type":"Point"}
}