{
  "type": "Feature",
  "properties": {
    "iso:country":"US",
    "sg:address":"8767 Andrus Rd",
    "sg:city":"Kirkville",
    "sg:classifiers":[
        {
            "category":"Building & Trades",
            "subcategory":"Construction",
            "type":"Services"
        }
    ],
    "sg:phone":"+1 315 687 3885",
    "sg:postcode":"13082",
    "sg:province":"NY",
    "sg:tags":[
        "house",
        "carpentry",
        "contractor"
    ],
    "wof:name":"Chris Pecht Contracting",
    "wof:placetype":"venue"
},
  "geometry": {"coordinates":[-75.925451,43.071295],"type":"Point"}
}