{
  "type": "Feature",
  "properties": {
    "addr:full":"135 E Bank St Albion NY 14411",
    "addr:housenumber":"135",
    "addr:postcode":"14411",
    "addr:street":"E Bank St",
    "iso:country":"US",
    "sg:address":"135 E Bank St",
    "sg:city":"Albion",
    "sg:classifiers":[
        {
            "category":"Personal",
            "subcategory":"Beauty Salon",
            "type":"Services"
        }
    ],
    "sg:phone":"+1 585 589 2116",
    "sg:postcode":"14411",
    "sg:province":"NY",
    "wof:name":"Heads Up",
    "wof:placetype":"venue"
},
  "geometry": {"coordinates":[-78.19113400000001,43.247874],"type":"Point"}
}