{
  "type": "Feature",
  "properties": {
    "iso:country":"US",
    "sg:address":"14 Bell Flower Rd",
    "sg:city":"Ballston Spa",
    "sg:classifiers":[
        {
            "category":"Building & Trades",
            "subcategory":"Electrical",
            "type":"Services"
        }
    ],
    "sg:phone":"+1 518 899 7329",
    "sg:postcode":"12020",
    "sg:province":"NY",
    "sg:tags":[
        "electric",
        "contractor"
    ],
    "wof:name":"Wiring Concepts",
    "wof:placetype":"venue"
},
  "geometry": {"coordinates":[-73.780818,42.962737],"type":"Point"}
}