{
  "type": "Feature",
  "properties": {
    "addr:full":"720 Prospect Avenue Bronx NY 10455",
    "addr:housenumber":"720",
    "addr:postcode":"10455",
    "addr:street":"Prospect Avenue",
    "iso:country":"US",
    "sg:address":"720 Prospect Avenue",
    "sg:city":"Bronx",
    "sg:classifiers":[
        {
            "category":"Building & Trades",
            "subcategory":"Pest Control",
            "type":"Services"
        }
    ],
    "sg:phone":"+1 718 742 4400",
    "sg:postcode":"10455",
    "sg:province":"NY",
    "wof:name":"Advantage Pest Control Company",
    "wof:placetype":"venue"
},
  "geometry": {"coordinates":[-73.902643,40.816863],"type":"Point"}
}