{
  "type": "Feature",
  "properties": {
    "addr:full":"595 New Loudon Rd Latham NY 12110",
    "addr:housenumber":"595",
    "addr:postcode":"12110",
    "addr:street":"New Loudon Rd",
    "iso:country":"US",
    "sg:address":"595 New Loudon Rd",
    "sg:city":"Latham",
    "sg:classifiers":[
        {
            "category":"Wholesale",
            "subcategory":"Home Furnishings",
            "type":"Manufacturing & Wholesale Goods"
        },
        {
            "category":"Professional",
            "subcategory":"Management & Consulting",
            "type":"Services"
        }
    ],
    "sg:phone":"+1 518 220 9436",
    "sg:postcode":"12110",
    "sg:province":"NY",
    "sg:tags":[
        "curtain",
        "fixture",
        "drapery"
    ],
    "sg:website":"www.consultjna.com",
    "wof:name":"Jamie Northrop Associates",
    "wof:placetype":"venue"
},
  "geometry": {"coordinates":[-73.76181099999999,42.731144],"type":"Point"}
}