{
  "type": "Feature",
  "properties": {
    "iso:country":"US",
    "sg:address":"8171 Main St",
    "sg:city":"Williamsville",
    "sg:classifiers":[
        {
            "category":"Restaurant",
            "type":"Food & Drink"
        }
    ],
    "sg:phone":"+1 716 626 5881",
    "sg:postcode":"14221",
    "sg:province":"NY",
    "wof:name":"Wendy's",
    "wof:placetype":"venue"
},
  "geometry": {"coordinates":[-78.69554100000001,42.965179],"type":"Point"}
}