{
  "type": "Feature",
  "properties": {
    "iso:country":"US",
    "sg:address":"2 James St",
    "sg:city":"Auburn",
    "sg:classifiers":[
        {
            "category":"Health Services",
            "subcategory":"Doctor",
            "type":"Services"
        }
    ],
    "sg:phone":"+1 315 252 7259",
    "sg:postcode":"13021",
    "sg:province":"NY",
    "wof:name":"Michael A Iacovino DDS PC",
    "wof:placetype":"venue"
},
  "geometry": {"coordinates":[-76.57137299999999,42.929151],"type":"Point"}
}