{
  "type": "Feature",
  "properties": {
    "iso:country":"US",
    "sg:address":"10 N Main St",
    "sg:city":"Voorheesville",
    "sg:classifiers":[
        {
            "category":"Professional",
            "subcategory":"Management & Consulting",
            "type":"Services"
        }
    ],
    "sg:phone":"+1 518 765 2453",
    "sg:postcode":"12186",
    "sg:province":"NY",
    "sg:tags":[
        "home",
        "demonstration"
    ],
    "wof:name":"Pampered Chef",
    "wof:placetype":"venue"
},
  "geometry": {"coordinates":[-73.92775899999999,42.65874],"type":"Point"}
}