{
  "type": "Feature",
  "properties": {
    "addr:full":"66 E Jefryn Blvd Deer Park NY 11729",
    "addr:housenumber":"66",
    "addr:postcode":"11729",
    "addr:street":"E Jefryn Blvd",
    "iso:country":"US",
    "sg:address":"66 E Jefryn Blvd",
    "sg:city":"Deer Park",
    "sg:classifiers":[
        {
            "category":"Manufacturing",
            "subcategory":"Tools & Machinery",
            "type":"Manufacturing & Wholesale Goods"
        }
    ],
    "sg:phone":"+1   ",
    "sg:postcode":"11729",
    "sg:province":"NY",
    "sg:tags":[
        "machine",
        "shop"
    ],
    "wof:name":"Extroma Corp",
    "wof:placetype":"venue"
},
  "geometry": {"coordinates":[-73.299572,40.756654],"type":"Point"}
}