{
  "type": "Feature",
  "properties": {
    "iso:country":"US",
    "sg:address":"3136 Watkins Rd",
    "sg:city":"Horseheads",
    "sg:classifiers":[
        {
            "category":"Farming",
            "subcategory":"Nursery",
            "type":"Manufacturing & Wholesale Goods"
        }
    ],
    "sg:phone":"+1 607 796 6296",
    "sg:postcode":"14845",
    "sg:province":"NY",
    "sg:tags":[
        "greenhouse"
    ],
    "wof:name":"Sonora's Gardens",
    "wof:placetype":"venue"
},
  "geometry": {"coordinates":[-76.834892,42.189352],"type":"Point"}
}