{
  "type": "Feature",
  "properties": {
    "addr:full":"96 Fort Greene Pl Brooklyn NY 11217",
    "addr:housenumber":"96",
    "addr:postcode":"11217",
    "addr:street":"Fort Greene Pl",
    "iso:country":"US",
    "sg:address":"96 Fort Greene Pl",
    "sg:city":"Brooklyn",
    "sg:classifiers":[
        {
            "category":"Social Services",
            "subcategory":"Child Care",
            "type":"Services"
        }
    ],
    "sg:phone":"+1 718 596 7912",
    "sg:postcode":"11217",
    "sg:province":"NY",
    "sg:tags":[
        "day"
    ],
    "wof:name":"Carosel Children's Center the",
    "wof:placetype":"venue"
},
  "geometry": {"coordinates":[-73.976303,40.6852],"type":"Point"}
}