{
  "type": "Feature",
  "properties": {
    "addr:full":"3260 Henry Hudson Pkwy E Bronx NY 10463",
    "addr:housenumber":"3260",
    "addr:postcode":"10463",
    "addr:street":"Henry Hudson Pkwy E",
    "iso:country":"US",
    "sg:address":"3260 Henry Hudson Pkwy E",
    "sg:city":"Bronx",
    "sg:classifiers":[
        {
            "category":"Social Services",
            "subcategory":"Adult Care",
            "type":"Services"
        }
    ],
    "sg:phone":"+1 718 549 1700",
    "sg:postcode":"10463",
    "sg:province":"NY",
    "sg:tags":[
        "home",
        "nursing"
    ],
    "wof:name":"Baptist Home For The Aged Inc",
    "wof:placetype":"venue"
},
  "geometry": {"coordinates":[-73.912514,40.886022],"type":"Point"}
}