{
  "type": "Feature",
  "properties": {
    "addr:full":"509 Van Siclen Ave Brooklyn NY 11207",
    "addr:housenumber":"509",
    "addr:postcode":"11207",
    "addr:street":"Van Siclen Ave",
    "iso:country":"US",
    "sg:address":"509 Van Siclen Ave",
    "sg:city":"Brooklyn",
    "sg:classifiers":[
        {
            "category":"Organizations",
            "subcategory":"Religious Organization",
            "type":"Services"
        }
    ],
    "sg:phone":"+1 718 342 7461",
    "sg:postcode":"11207",
    "sg:province":"NY",
    "sg:tags":[
        "church"
    ],
    "wof:name":"Fellowship Baptist Church",
    "wof:placetype":"venue"
},
  "geometry": {"coordinates":[-73.88928199999999,40.668656],"type":"Point"}
}