{
  "type": "Feature",
  "properties": {
    "iso:country":"US",
    "sg:address":"523 Cedar St",
    "sg:city":"West Hempstead",
    "sg:classifiers":[
        {
            "category":"Education",
            "subcategory":"Special Training",
            "type":"Public Place"
        }
    ],
    "sg:phone":"+1 516 292 7538",
    "sg:postcode":"11552",
    "sg:province":"NY",
    "sg:tags":[
        "school",
        "driving"
    ],
    "wof:name":"Driving Instructoy Inc",
    "wof:placetype":"venue"
},
  "geometry": {"coordinates":[-73.642197,40.699501],"type":"Point"}
}