{
  "type": "Feature",
  "properties": {
    "addr:full":"1217 Jackson Ave Long Island City NY 11101",
    "addr:housenumber":"1217",
    "addr:postcode":"11101",
    "addr:street":"Jackson Ave",
    "iso:country":"US",
    "sg:address":"1217 Jackson Ave",
    "sg:city":"Long Island City",
    "sg:classifiers":[
        {
            "category":"Food & Beverages",
            "subcategory":"Candy",
            "type":"Retail Goods"
        }
    ],
    "sg:phone":"+1 718 361 1112",
    "sg:postcode":"11101",
    "sg:province":"NY",
    "sg:tags":[
        "store"
    ],
    "wof:name":"Sunrise Wholesaler Inc",
    "wof:placetype":"venue"
},
  "geometry": {"coordinates":[-73.950104,40.743999],"type":"Point"}
}