{
  "type": "Feature",
  "properties": {
    "addr:full":"154 Forest Valley Rd Pleasant Valley NY 12569",
    "addr:housenumber":"154",
    "addr:postcode":"12569",
    "addr:street":"Forest Valley Rd",
    "iso:country":"US",
    "sg:address":"154 Forest Valley Rd",
    "sg:city":"Pleasant Valley",
    "sg:classifiers":[
        {
            "category":"Real Estate",
            "subcategory":"Real Estate Agent",
            "type":"Services"
        }
    ],
    "sg:phone":"+1 845 635 4383",
    "sg:postcode":"12569",
    "sg:province":"NY",
    "wof:name":"Brant Property Management LLC",
    "wof:placetype":"venue"
},
  "geometry": {"coordinates":[-73.81733800000001,41.743104],"type":"Point"}
}