{
  "type": "Feature",
  "properties": {
    "addr:full":"38 Broad St Fishkill NY 12524",
    "addr:housenumber":"38",
    "addr:postcode":"12524",
    "addr:street":"Broad St",
    "iso:country":"US",
    "sg:address":"38 Broad St",
    "sg:city":"Fishkill",
    "sg:classifiers":[
        {
            "category":"Education",
            "subcategory":"Preschool",
            "type":"Public Place"
        }
    ],
    "sg:phone":"+1 845 896 9810",
    "sg:postcode":"12524",
    "sg:province":"NY",
    "sg:tags":[
        "school",
        "nursery"
    ],
    "sg:website":"http://www.fishkill.org",
    "wof:name":"Stepping Stones Pre-School",
    "wof:placetype":"venue"
},
  "geometry": {"coordinates":[-73.90195199999999,41.533739],"type":"Point"}
}