{
  "type": "Feature",
  "properties": {
    "addr:full":"118 E 116th St New York NY 10029",
    "addr:housenumber":"118",
    "addr:postcode":"10029",
    "addr:street":"E 116Th St",
    "iso:country":"US",
    "sg:address":"118 E 116th St",
    "sg:city":"New York",
    "sg:classifiers":[
        {
            "category":"Deli",
            "type":"Food & Drink"
        },
        {
            "category":"Food & Beverages",
            "subcategory":"Bakery",
            "type":"Retail Goods"
        }
    ],
    "sg:phone":"+1 212 369 6798",
    "sg:postcode":"10029",
    "sg:province":"NY",
    "sg:tags":[
        "sandwich"
    ],
    "wof:name":"United Deli Corporation",
    "wof:placetype":"venue"
},
  "geometry": {"coordinates":[-73.94261,40.798887],"type":"Point"}
}