{
  "type": "Feature",
  "properties": {
    "addr:full":"150 Main St Port Washington NY 11050",
    "addr:housenumber":"150",
    "addr:postcode":"11050",
    "addr:street":"Main St",
    "iso:country":"US",
    "sg:address":"150 Main St",
    "sg:city":"Port Washington",
    "sg:classifiers":[
        {
            "category":"Banks & Credit Unions",
            "subcategory":"Investment Brokerage",
            "type":"Services"
        }
    ],
    "sg:phone":"+1 516 944 3317",
    "sg:postcode":"11050",
    "sg:province":"NY",
    "sg:tags":[
        "retirement",
        "planning"
    ],
    "wof:name":"Whitmore Retirement Solutions",
    "wof:placetype":"venue"
},
  "geometry": {"coordinates":[-73.691236,40.830321],"type":"Point"}
}