{
  "type": "Feature",
  "properties": {
    "addr:full":"141 Washington Ave Endicott NY 13760",
    "addr:housenumber":"141",
    "addr:postcode":"13760",
    "addr:street":"Washington Ave",
    "iso:country":"US",
    "sg:address":"141 Washington Ave",
    "sg:city":"Endicott",
    "sg:classifiers":[
        {
            "category":"Banks & Credit Unions",
            "subcategory":"Bank",
            "type":"Services"
        }
    ],
    "sg:phone":"+1 607 786 5403",
    "sg:postcode":"13760",
    "sg:province":"NY",
    "sg:tags":[
        "federal"
    ],
    "wof:name":"Horizons Federal Credit Union",
    "wof:placetype":"venue"
},
  "geometry": {"coordinates":[-76.048007,42.101411],"type":"Point"}
}