{
  "type": "Feature",
  "properties": {
    "addr:full":"12302 Jamaica Ave Richmond Hill NY 11418",
    "addr:housenumber":"12302",
    "addr:postcode":"11418",
    "addr:street":"Jamaica Ave",
    "iso:country":"US",
    "sg:address":"12302 Jamaica Ave",
    "sg:city":"Richmond Hill",
    "sg:classifiers":[
        {
            "category":"Building & Trades",
            "subcategory":"Locksmith",
            "type":"Services"
        }
    ],
    "sg:phone":"+1 347 392 3551",
    "sg:postcode":"11418",
    "sg:province":"NY",
    "sg:tags":[
        "key"
    ],
    "wof:name":"24 Hour Anytime Emergency Richmond Loc",
    "wof:placetype":"venue"
},
  "geometry": {"coordinates":[-73.827197,40.700546],"type":"Point"}
}