{
  "type": "Feature",
  "properties": {
    "addr:full":"7521 Prospect Rd Westfield NY 14787",
    "addr:housenumber":"7521",
    "addr:postcode":"14787",
    "addr:street":"Prospect Rd",
    "iso:country":"US",
    "sg:address":"7521 Prospect Rd",
    "sg:city":"Westfield",
    "sg:classifiers":[
        {
            "category":"Home & Garden",
            "subcategory":"Garden Supply",
            "type":"Retail Goods"
        }
    ],
    "sg:phone":"+1 716 326 4671",
    "sg:postcode":"14787",
    "sg:province":"NY",
    "sg:tags":[
        "lawn",
        "mower"
    ],
    "wof:name":"LA Porte Farm Equipment Inc",
    "wof:placetype":"venue"
},
  "geometry": {"coordinates":[-79.548529,42.334154],"type":"Point"}
}