{
  "type": "Feature",
  "properties": {
    "iso:country":"US",
    "sg:address":"2048 State St",
    "sg:city":"Schenectady",
    "sg:classifiers":[
        {
            "category":"Autos & Motor Vehicles",
            "subcategory":"Automobile Sales",
            "type":"Retail Goods"
        }
    ],
    "sg:phone":"+1 518 372 8771",
    "sg:postcode":"12304",
    "sg:province":"NY",
    "sg:tags":[
        "car",
        "dealer"
    ],
    "wof:name":"JAMACO Used Cars",
    "wof:placetype":"venue"
},
  "geometry": {"coordinates":[-73.898359,42.775399],"type":"Point"}
}