{
  "type": "Feature",
  "properties": {
    "addr:full":"372 Columbia St Brooklyn NY 11231",
    "addr:housenumber":"372",
    "addr:postcode":"11231",
    "addr:street":"Columbia St",
    "iso:country":"US",
    "sg:address":"372 Columbia St",
    "sg:city":"Brooklyn",
    "sg:phone":"+1 718 522 5400",
    "sg:postcode":"11231",
    "sg:province":"NY",
    "sg:tags":[
        "oil"
    ],
    "wof:name":"Consumer Fuel Oil Corp",
    "wof:placetype":"venue"
},
  "geometry": {"coordinates":[-74.005456,40.679558],"type":"Point"}
}