{
  "type": "Feature",
  "properties": {
    "iso:country":"US",
    "sg:address":"4046 Main Street",
    "sg:city":"Flushing",
    "sg:classifiers":[
        {
            "category":"Bakery",
            "type":"Food & Drink"
        }
    ],
    "sg:phone":"+1 718 359 6655",
    "sg:postcode":"11354",
    "sg:province":"NY",
    "wof:name":"Mayflower Cafe & Bakery",
    "wof:placetype":"venue"
},
  "geometry": {"coordinates":[-73.82977200000001,40.75851],"type":"Point"}
}