{
  "type": "Feature",
  "properties": {
    "iso:country":"US",
    "sg:address":"44 Hudson Ave",
    "sg:city":"Colonie",
    "sg:classifiers":[
        {
            "category":"Building & Trades",
            "subcategory":"Cleaning & Sanitation",
            "type":"Services"
        }
    ],
    "sg:phone":"+1 518 453 0892",
    "sg:postcode":"12205",
    "sg:province":"NY",
    "sg:tags":[
        "janitor"
    ],
    "wof:name":"Nightime Clean",
    "wof:placetype":"venue"
},
  "geometry": {"coordinates":[-73.817508,42.699248],"type":"Point"}
}