{
  "type": "Feature",
  "properties": {
    "addr:full":"4960 Transit Rd Depew NY 14043",
    "addr:housenumber":"4960",
    "addr:postcode":"14043",
    "addr:street":"Transit Rd",
    "iso:country":"US",
    "sg:address":"4960 Transit Rd",
    "sg:city":"Depew",
    "sg:classifiers":[
        {
            "category":"Professional",
            "type":"Services"
        }
    ],
    "sg:phone":"+1 716 684 6500",
    "sg:postcode":"14043",
    "sg:province":"NY",
    "sg:tags":[
        "establishment"
    ],
    "wof:name":"Master Chong's World Class",
    "wof:placetype":"venue"
},
  "geometry": {"coordinates":[-78.69699199999999,42.884019],"type":"Point"}
}