{
  "type": "Feature",
  "properties": {
    "addr:full":"846 Prospect Pl Brooklyn NY 11216",
    "addr:housenumber":"846",
    "addr:postcode":"11216",
    "addr:street":"Prospect Pl",
    "iso:country":"US",
    "sg:address":"846 Prospect Pl",
    "sg:city":"Brooklyn",
    "sg:classifiers":[
        {
            "category":"Restaurant",
            "type":"Food & Drink"
        }
    ],
    "sg:phone":"+1   ",
    "sg:postcode":"11216",
    "sg:province":"NY",
    "sg:tags":[
        "eating"
    ],
    "wof:name":"CJS Coffee Shop",
    "wof:placetype":"venue"
},
  "geometry": {"coordinates":[-73.94844500000001,40.674167],"type":"Point"}
}