{
  "type": "Feature",
  "properties": {
    "iso:country":"US",
    "sg:address":"160 Genesee St",
    "sg:city":"Auburn",
    "sg:classifiers":[
        {
            "category":"Government",
            "subcategory":"Office",
            "type":"Public Place"
        }
    ],
    "sg:phone":"+1 315 253 1451",
    "sg:postcode":"13021",
    "sg:province":"NY",
    "sg:tags":[
        "county",
        "department",
        "health"
    ],
    "wof:name":"Cayuga County Health Dept",
    "wof:placetype":"venue"
},
  "geometry": {"coordinates":[-76.570662,42.929366],"type":"Point"}
}