{
  "type": "Feature",
  "properties": {
    "iso:country":"US",
    "sg:address":"24 Roe Ave",
    "sg:city":"Patchogue",
    "sg:classifiers":[
        {
            "category":"Building & Trades",
            "subcategory":"Construction",
            "type":"Services"
        }
    ],
    "sg:phone":"+1 631 207 1057",
    "sg:postcode":"11772",
    "sg:province":"NY",
    "sg:tags":[
        "general",
        "contractor"
    ],
    "wof:name":"Jo Dans Painting & Paper",
    "wof:placetype":"venue"
},
  "geometry": {"coordinates":[-72.989002,40.764802],"type":"Point"}
}