{
  "type": "Feature",
  "properties": {
    "iso:country":"US",
    "sg:address":"28 Marion Pl",
    "sg:city":"Saratoga Springs",
    "sg:classifiers":[
        {
            "category":"Manufacturing",
            "subcategory":"Printing",
            "type":"Manufacturing & Wholesale Goods"
        }
    ],
    "sg:phone":"+1   ",
    "sg:postcode":"12866",
    "sg:province":"NY",
    "sg:tags":[
        "business"
    ],
    "wof:name":"Saratoga Media Group Inc",
    "wof:placetype":"venue"
},
  "geometry": {"coordinates":[-73.777331,43.082429],"type":"Point"}
}