{
  "type": "Feature",
  "properties": {
    "addr:full":"286 Farragut Ave Hastings On Hdsn NY 10706",
    "addr:housenumber":"286",
    "addr:postcode":"10706",
    "addr:street":"Farragut Ave",
    "iso:country":"US",
    "sg:address":"286 Farragut Ave",
    "sg:city":"Hastings On Hdsn",
    "sg:classifiers":[
        {
            "category":"Shopping",
            "subcategory":"Gifts & Souvenirs",
            "type":"Retail Goods"
        }
    ],
    "sg:phone":"+1 914 478 7710",
    "sg:postcode":"10706",
    "sg:province":"NY",
    "sg:tags":[
        "shop"
    ],
    "wof:name":"Farraguts Stationery Store",
    "wof:placetype":"venue"
},
  "geometry": {"coordinates":[-73.871866,40.986453],"type":"Point"}
}