{
  "type": "Feature",
  "properties": {
    "addr:full":"5712 Woodside Avenue Woodside NY 11377",
    "addr:housenumber":"5712",
    "addr:postcode":"11377",
    "addr:street":"Woodside Avenue",
    "iso:country":"US",
    "sg:address":"5712 Woodside Avenue",
    "sg:city":"Woodside",
    "sg:classifiers":[
        {
            "category":"Personal",
            "subcategory":"Barber",
            "type":"Services"
        }
    ],
    "sg:phone":"+1 718 672 1633",
    "sg:postcode":"11377",
    "sg:province":"NY",
    "wof:name":"At the Buzzer",
    "wof:placetype":"venue"
},
  "geometry": {"coordinates":[-73.906969,40.745666],"type":"Point"}
}