{
  "type": "Feature",
  "properties": {
    "addr:full":"25 Willoughby St Brooklyn NY 11201",
    "addr:housenumber":"25",
    "addr:postcode":"11201",
    "addr:street":"Willoughby St",
    "iso:country":"US",
    "sg:address":"25 Willoughby St",
    "sg:city":"Brooklyn",
    "sg:classifiers":[
        {
            "category":"Professional",
            "subcategory":"Detective & Security Services",
            "type":"Services"
        }
    ],
    "sg:phone":"+1 718 855 7400",
    "sg:postcode":"11201",
    "sg:province":"NY",
    "sg:tags":[
        "car",
        "armored"
    ],
    "wof:name":"Cps Armor Inc",
    "wof:placetype":"venue"
},
  "geometry": {"coordinates":[-73.987982,40.69225],"type":"Point"}
}