{
  "type": "Feature",
  "properties": {
    "addr:full":"95 Lake St White Plains NY 10604",
    "addr:housenumber":"95",
    "addr:postcode":"10604",
    "addr:street":"Lake St",
    "iso:country":"US",
    "sg:address":"95 Lake St",
    "sg:city":"White Plains",
    "sg:classifiers":[
        {
            "category":"Government",
            "subcategory":"Fire Station",
            "type":"Public Place"
        }
    ],
    "sg:phone":"+1 914 684 8823",
    "sg:postcode":"10604",
    "sg:province":"NY",
    "sg:tags":[
        "department"
    ],
    "wof:name":"West Harrison Fire Dept",
    "wof:placetype":"venue"
},
  "geometry": {"coordinates":[-73.757321,41.039173],"type":"Point"}
}