{
  "type": "Feature",
  "properties": {
    "addr:full":"20 Hanwell Pl Depew NY 14043",
    "addr:housenumber":"20",
    "addr:postcode":"14043",
    "addr:street":"Hanwell Pl",
    "iso:country":"US",
    "sg:address":"20 Hanwell Pl",
    "sg:city":"Depew",
    "sg:classifiers":[
        {
            "category":"Retail",
            "subcategory":"Car Wash",
            "type":"Services"
        }
    ],
    "sg:phone":"+1 716 681 2426",
    "sg:postcode":"14043",
    "sg:province":"NY",
    "sg:tags":[
        "polishing",
        "washing"
    ],
    "wof:name":"Splash N Dash Car Wash",
    "wof:placetype":"venue"
},
  "geometry": {"coordinates":[-78.695637,42.925849],"type":"Point"}
}