{
  "type": "Feature",
  "properties": {
    "iso:country":"US",
    "sg:address":"314 1st St",
    "sg:city":"Liverpool",
    "sg:classifiers":[
        {
            "category":"Organizations",
            "subcategory":"Professional Association",
            "type":"Services"
        }
    ],
    "sg:phone":"+1 315 457 3895",
    "sg:postcode":"13088",
    "sg:province":"NY",
    "sg:tags":[
        "executive",
        "business"
    ],
    "wof:name":"Greater Liverpool Chamber-Comm",
    "wof:placetype":"venue"
},
  "geometry": {"coordinates":[-76.20840800000001,43.10215],"type":"Point"}
}