{
  "type": "Feature",
  "properties": {
    "iso:country":"US",
    "sg:address":"389 Brower Ave",
    "sg:city":"Rockville Centre",
    "sg:classifiers":[
        {
            "category":"Professional",
            "subcategory":"Lawyer & Legal Services",
            "type":"Services"
        }
    ],
    "sg:phone":"+1 516 536 1909",
    "sg:postcode":"11570",
    "sg:province":"NY",
    "wof:name":"Gold Allen S ESQ",
    "wof:placetype":"venue"
},
  "geometry": {"coordinates":[-73.627296,40.670898],"type":"Point"}
}