{
  "type": "Feature",
  "properties": {
    "addr:full":"140 Bedford Rd Pleasantville NY 10570",
    "addr:housenumber":"140",
    "addr:postcode":"10570",
    "addr:street":"Bedford Rd",
    "iso:country":"US",
    "sg:address":"140 Bedford Rd",
    "sg:city":"Pleasantville",
    "sg:classifiers":[
        {
            "category":"Health Services",
            "subcategory":"Chiropractor",
            "type":"Services"
        }
    ],
    "sg:phone":"+1   ",
    "sg:postcode":"10570",
    "sg:province":"NY",
    "sg:tags":[
        "food"
    ],
    "wof:name":"Plesantville Fmly Chiropractic",
    "wof:placetype":"venue"
},
  "geometry": {"coordinates":[-73.77874,41.140881],"type":"Point"}
}