{
  "type": "Feature",
  "properties": {
    "iso:country":"US",
    "sg:address":"124 Holcomb Rd",
    "sg:city":"Port Crane",
    "sg:classifiers":[
        {
            "category":"Retail",
            "subcategory":"Animal Services",
            "type":"Services"
        }
    ],
    "sg:phone":"+1 607 693 5091",
    "sg:postcode":"13833",
    "sg:province":"NY",
    "wof:name":"Wildwood Farm Boarding Stables",
    "wof:placetype":"venue"
},
  "geometry": {"coordinates":[-75.705153,42.227084],"type":"Point"}
}