{
  "type": "Feature",
  "properties": {
    "addr:full":"319 Jerusalem Ave Hicksville NY 11801",
    "addr:housenumber":"319",
    "addr:postcode":"11801",
    "addr:street":"Jerusalem Ave",
    "iso:country":"US",
    "sg:address":"319 Jerusalem Ave",
    "sg:city":"Hicksville",
    "sg:classifiers":[
        {
            "category":"Sports & Exercise",
            "subcategory":"Gym",
            "type":"Entertainment"
        }
    ],
    "sg:phone":"+1 516 433 8367",
    "sg:postcode":"11801",
    "sg:province":"NY",
    "sg:tags":[
        "facility",
        "physical",
        "fitness"
    ],
    "wof:name":"Curves For Women",
    "wof:placetype":"venue"
},
  "geometry": {"coordinates":[-73.520798,40.755798],"type":"Point"}
}