{
  "type": "Feature",
  "properties": {
    "addr:full":"243 Taylor St Staten Island NY 10310",
    "addr:housenumber":"243",
    "addr:postcode":"10310",
    "addr:street":"Taylor St",
    "iso:country":"US",
    "sg:address":"243 Taylor St",
    "sg:city":"Staten Island",
    "sg:classifiers":[
        {
            "category":"Organizations",
            "subcategory":"Religious Organization",
            "type":"Services"
        }
    ],
    "sg:phone":"+1 718 442 2782",
    "sg:postcode":"10310",
    "sg:province":"NY",
    "sg:tags":[
        "clergy"
    ],
    "wof:name":"Ralph Ritter",
    "wof:placetype":"venue"
},
  "geometry": {"coordinates":[-74.122851,40.633316],"type":"Point"}
}