{
  "type": "Feature",
  "properties": {
    "addr:full":"1909 Coney Island Ave Brooklyn NY 11230",
    "addr:housenumber":"1909",
    "addr:postcode":"11230",
    "addr:street":"Coney Island Ave",
    "iso:country":"US",
    "sg:address":"1909 Coney Island Ave",
    "sg:city":"Brooklyn",
    "sg:classifiers":[
        {
            "category":"Bars & Pubs",
            "subcategory":"Nightclub",
            "type":"Food & Drink"
        }
    ],
    "sg:phone":"+1 718 928 7550",
    "sg:postcode":"11230",
    "sg:province":"NY",
    "sg:tags":[
        "nightlife"
    ],
    "wof:name":"Mezuzah Lounge Inc",
    "wof:placetype":"venue"
},
  "geometry": {"coordinates":[-73.96228600000001,40.610783],"type":"Point"}
}