{
  "type": "Feature",
  "properties": {
    "addr:full":"191 State Hwy 164 Patterson NY 12563",
    "addr:housenumber":"191",
    "addr:postcode":"12563",
    "addr:street":"State Hwy 164",
    "iso:country":"US",
    "sg:address":"191 State Hwy 164",
    "sg:city":"Patterson",
    "sg:classifiers":[
        {
            "category":"Building & Trades",
            "subcategory":"Landscaping Services",
            "type":"Services"
        }
    ],
    "sg:phone":"+1 845 878 0037",
    "sg:postcode":"12563",
    "sg:province":"NY",
    "sg:tags":[
        "lawn",
        "maintenance",
        "grounds"
    ],
    "wof:name":"Ramsdell Lawn & Landscp Mgmt",
    "wof:placetype":"venue"
},
  "geometry": {"coordinates":[-73.58072799999999,41.473573],"type":"Point"}
}