{
  "type": "Feature",
  "properties": {
    "iso:country":"US",
    "sg:address":"3174 Amsterdam Rd",
    "sg:city":"Scotia",
    "sg:classifiers":[
        {
            "category":"Retail",
            "subcategory":"Auto Repair",
            "type":"Services"
        }
    ],
    "sg:phone":"+1 518 370 0689",
    "sg:postcode":"12302",
    "sg:province":"NY",
    "sg:tags":[
        "body",
        "automotive",
        "painting",
        "automobile"
    ],
    "wof:name":"Cliff's Body Shop",
    "wof:placetype":"venue"
},
  "geometry": {"coordinates":[-74.01269499999999,42.856768],"type":"Point"}
}