{
  "type": "Feature",
  "properties": {
    "iso:country":"US",
    "sg:address":"10 Clove Lake Pl",
    "sg:city":"Staten Island",
    "sg:classifiers":[
        {
            "category":"Building & Trades",
            "subcategory":"Construction",
            "type":"Services"
        }
    ],
    "sg:phone":"+1 718 390 0629",
    "sg:postcode":"10310",
    "sg:province":"NY",
    "sg:tags":[
        "carpenter"
    ],
    "wof:name":"Painting 700",
    "wof:placetype":"venue"
},
  "geometry": {"coordinates":[-74.117214,40.628046],"type":"Point"}
}