{
  "type": "Feature",
  "properties": {
    "addr:full":"22216 S Conduit Avenue Jamaica NY 11413",
    "addr:housenumber":"22216",
    "addr:postcode":"11413",
    "addr:street":"S Conduit Avenue",
    "iso:country":"US",
    "sg:address":"22216 S Conduit Avenue",
    "sg:city":"Jamaica",
    "sg:classifiers":[
        {
            "category":"Shopping",
            "subcategory":"Pawn Shop",
            "type":"Retail Goods"
        }
    ],
    "sg:phone":"+1 718 949 7296",
    "sg:postcode":"11413",
    "sg:province":"NY",
    "wof:name":"Metropolitan Pawn Brokers",
    "wof:placetype":"venue"
},
  "geometry": {"coordinates":[-73.75566999999999,40.665392],"type":"Point"}
}