{
  "type": "Feature",
  "properties": {
    "addr:full":"8118 Flagpole Cir Manlius NY 13104",
    "addr:housenumber":"8118",
    "addr:postcode":"13104",
    "addr:street":"Flagpole Cir",
    "iso:country":"US",
    "sg:address":"8118 Flagpole Cir",
    "sg:city":"Manlius",
    "sg:classifiers":[
        {
            "category":"Home & Garden",
            "subcategory":"Carpets & Floor Coverings",
            "type":"Retail Goods"
        }
    ],
    "sg:phone":"+1 315 278 5617",
    "sg:postcode":"13104",
    "sg:province":"NY",
    "sg:tags":[
        "installation",
        "rug"
    ],
    "wof:name":"Straight Edge Carpet",
    "wof:placetype":"venue"
},
  "geometry": {"coordinates":[-75.96377099999999,42.999685],"type":"Point"}
}