{
  "type": "Feature",
  "properties": {
    "iso:country":"US",
    "sg:address":"125 E Perry Ave",
    "sg:city":"Silver Springs",
    "sg:classifiers":[
        {
            "category":"Real Estate",
            "subcategory":"Real Estate Operator",
            "type":"Services"
        }
    ],
    "sg:phone":"+1 585 493 3162",
    "sg:postcode":"14550",
    "sg:province":"NY",
    "sg:tags":[
        "apartment"
    ],
    "wof:name":"Meadowview Assoc",
    "wof:placetype":"venue"
},
  "geometry": {"coordinates":[-78.07659700000001,42.662628],"type":"Point"}
}