{
  "type": "Feature",
  "properties": {
    "addr:full":"446 Main St New York Mills NY 13417",
    "addr:housenumber":"446",
    "addr:postcode":"13417",
    "addr:street":"Main St",
    "iso:country":"US",
    "sg:address":"446 Main St",
    "sg:city":"New York Mills",
    "sg:classifiers":[
        {
            "category":"Restaurant",
            "type":"Food & Drink"
        }
    ],
    "sg:phone":"+1 315 736 5030",
    "sg:postcode":"13417",
    "sg:province":"NY",
    "sg:tags":[
        "banquet",
        "rooms"
    ],
    "wof:name":"Roselawn Banquet House",
    "wof:placetype":"venue"
},
  "geometry": {"coordinates":[-75.294118,43.10261],"type":"Point"}
}