{
  "type": "Feature",
  "properties": {
    "addr:full":"28 Meier Pl Bay Shore NY 11706",
    "addr:housenumber":"28",
    "addr:postcode":"11706",
    "addr:street":"Meier Pl",
    "iso:country":"US",
    "sg:address":"28 Meier Pl",
    "sg:city":"Bay Shore",
    "sg:classifiers":[
        {
            "category":"Building & Trades",
            "subcategory":"Electrical",
            "type":"Services"
        }
    ],
    "sg:phone":"+1 631 665 1969",
    "sg:postcode":"11706",
    "sg:province":"NY",
    "sg:tags":[
        "electrical",
        "contractor"
    ],
    "wof:name":"Donald E McCarthy",
    "wof:placetype":"venue"
},
  "geometry": {"coordinates":[-73.254164,40.743596],"type":"Point"}
}