{
  "type": "Feature",
  "properties": {
    "addr:full":"7416A Grand Ave Elmhurst NY 11373",
    "addr:housenumber":"7416a",
    "addr:postcode":"11373",
    "addr:street":"Grand Ave",
    "iso:country":"US",
    "sg:address":"7416A Grand Ave",
    "sg:city":"Elmhurst",
    "sg:classifiers":[
        {
            "category":"Autos & Motor Vehicles",
            "subcategory":"Fuel & Gas Station",
            "type":"Retail Goods"
        },
        {
            "category":"Building & Trades",
            "subcategory":"Construction",
            "type":"Services"
        }
    ],
    "sg:phone":"+1 718 326 4757",
    "sg:postcode":"11373",
    "sg:province":"NY",
    "sg:tags":[
        "asbestos",
        "detection",
        "burning",
        "lead",
        "removal"
    ],
    "wof:name":"Abatek Asbestos Lead & Mold Removal Corp",
    "wof:placetype":"venue"
},
  "geometry": {"coordinates":[-73.88768,40.730175],"type":"Point"}
}