{
  "type": "Feature",
  "properties": {
    "addr:full":"51 43rd St Brooklyn NY 11232",
    "addr:housenumber":"51",
    "addr:postcode":"11232",
    "addr:street":"43Rd St",
    "iso:country":"US",
    "sg:address":"51 43rd St",
    "sg:city":"Brooklyn",
    "sg:classifiers":[
        {
            "category":"Travel",
            "subcategory":"Travel Agent",
            "type":"Entertainment"
        }
    ],
    "sg:phone":"+1   ",
    "sg:postcode":"11232",
    "sg:province":"NY",
    "sg:tags":[
        "agency"
    ],
    "wof:name":"J & B Travel Inc",
    "wof:placetype":"venue"
},
  "geometry": {"coordinates":[-74.015468,40.654769],"type":"Point"}
}