{
  "type": "Feature",
  "properties": {
    "iso:country":"US",
    "sg:address":"75 Market St",
    "sg:city":"Poughkeepsie",
    "sg:classifiers":[
        {
            "category":"Social Services",
            "type":"Services"
        },
        {
            "category":"Professional",
            "subcategory":"Employment Agencies",
            "type":"Services"
        },
        {
            "category":"Organizations",
            "subcategory":"Community Association",
            "type":"Services"
        }
    ],
    "sg:phone":"+1 845 471 1900",
    "sg:postcode":"12601",
    "sg:province":"NY",
    "sg:tags":[
        "employer"
    ],
    "sg:website":"http://www.unitedwaydutchess.org",
    "wof:name":"United Way Of Dutchess County",
    "wof:placetype":"venue"
},
  "geometry": {"coordinates":[-73.929749,41.701908],"type":"Point"}
}