{
  "type": "Feature",
  "properties": {
    "addr:full":"80 Merrick Rd Amityville NY 11701",
    "addr:housenumber":"80",
    "addr:postcode":"11701",
    "addr:street":"Merrick Rd",
    "iso:country":"US",
    "sg:address":"80 Merrick Rd",
    "sg:city":"Amityville",
    "sg:classifiers":[
        {
            "category":"Health Services",
            "subcategory":"Chiropractor",
            "type":"Services"
        }
    ],
    "sg:phone":"+1 631 841 5840",
    "sg:postcode":"11701",
    "sg:province":"NY",
    "wof:name":"New York Spine Ctr",
    "wof:placetype":"venue"
},
  "geometry": {"coordinates":[-73.418435,40.671444],"type":"Point"}
}