{
  "type": "Feature",
  "properties": {
    "iso:country":"US",
    "sg:address":"134 Langley Hill Rd",
    "sg:city":"Greenwich",
    "sg:classifiers":[
        {
            "category":"Building & Trades",
            "subcategory":"Construction",
            "type":"Services"
        }
    ],
    "sg:phone":"+1 518 692 7290",
    "sg:postcode":"12834",
    "sg:province":"NY",
    "sg:tags":[
        "making",
        "cabinet"
    ],
    "wof:name":"Dvs Countertops and Cabinets",
    "wof:placetype":"venue"
},
  "geometry": {"coordinates":[-73.44614,43.12981],"type":"Point"}
}