{
  "type": "Feature",
  "properties": {
    "addr:full":"55 Avenue A New York NY 10009",
    "addr:housenumber":"55",
    "addr:postcode":"10009",
    "addr:street":"Avenue A",
    "iso:country":"US",
    "sg:address":"55 Avenue A",
    "sg:city":"New York",
    "sg:classifiers":[
        {
            "category":"Banks & Credit Unions",
            "subcategory":"Bank",
            "type":"Services"
        }
    ],
    "sg:phone":"+1 212 478 3080",
    "sg:postcode":"10009",
    "sg:province":"NY",
    "wof:name":"Independence Community Bank",
    "wof:placetype":"venue"
},
  "geometry": {"coordinates":[-73.985083,40.724129],"type":"Point"}
}