{
  "type": "Feature",
  "properties": {
    "iso:country":"US",
    "sg:address":"280 Broadway",
    "sg:city":"Bethpage",
    "sg:classifiers":[
        {
            "category":"Banks & Credit Unions",
            "subcategory":"Bank",
            "type":"Services"
        }
    ],
    "sg:phone":"+1 516 681 6299",
    "sg:postcode":"11714",
    "sg:province":"NY",
    "sg:tags":[
        "financing"
    ],
    "wof:name":"RMS Funding Corp",
    "wof:placetype":"venue"
},
  "geometry": {"coordinates":[-73.479657,40.740351],"type":"Point"}
}