{
  "type": "Feature",
  "properties": {
    "addr:full":"110 Route 22 Brewster NY 10509",
    "addr:housenumber":"110",
    "addr:postcode":"10509",
    "addr:street":"Route 22",
    "iso:country":"US",
    "sg:address":"110 Route 22",
    "sg:city":"Brewster",
    "sg:classifiers":[
        {
            "category":"Retail",
            "subcategory":"Auto Repair",
            "type":"Services"
        }
    ],
    "sg:phone":"+1 845 276 2010",
    "sg:postcode":"10509",
    "sg:province":"NY",
    "wof:name":"Mike's Auto Body",
    "wof:placetype":"venue"
},
  "geometry": {"coordinates":[-73.652,41.358299],"type":"Point"}
}