{
  "type": "Feature",
  "properties": {
    "addr:full":"5846 Main St Flushing NY 11355",
    "addr:housenumber":"5846",
    "addr:postcode":"11355",
    "addr:street":"Main St",
    "iso:country":"US",
    "sg:address":"5846 Main St",
    "sg:city":"Flushing",
    "sg:classifiers":[
        {
            "category":"Shopping",
            "subcategory":"Mobile Phones",
            "type":"Retail Goods"
        }
    ],
    "sg:phone":"+1 718 321 0300",
    "sg:postcode":"11355",
    "sg:province":"NY",
    "wof:name":"Get 1 Wireless",
    "wof:placetype":"venue"
},
  "geometry": {"coordinates":[-73.825946,40.744371],"type":"Point"}
}