{
  "type": "Feature",
  "properties": {
    "addr:full":"25 Egypt Ln Locust Valley NY 11560",
    "addr:housenumber":"25",
    "addr:postcode":"11560",
    "addr:street":"Egypt Ln",
    "iso:country":"US",
    "sg:address":"25 Egypt Ln",
    "sg:city":"Locust Valley",
    "sg:classifiers":[
        {
            "category":"Education",
            "subcategory":"Special Training",
            "type":"Public Place"
        }
    ],
    "sg:phone":"+1 516 759 3311",
    "sg:postcode":"11560",
    "sg:province":"NY",
    "sg:tags":[
        "educational"
    ],
    "wof:name":"Locust Valley Adult Education",
    "wof:placetype":"venue"
},
  "geometry": {"coordinates":[-73.583592,40.892027],"type":"Point"}
}