{
  "type": "Feature",
  "properties": {
    "addr:full":"280 Park Ave S New York NY 10010",
    "addr:housenumber":"280",
    "addr:postcode":"10010",
    "addr:street":"Park Ave S",
    "iso:country":"US",
    "sg:address":"280 Park Ave S",
    "sg:city":"New York",
    "sg:classifiers":[
        {
            "category":"Professional",
            "type":"Services"
        }
    ],
    "sg:phone":"+1   ",
    "sg:postcode":"10010",
    "sg:province":"NY",
    "sg:tags":[
        "publishing"
    ],
    "wof:name":"Point E Publishing",
    "wof:placetype":"venue"
},
  "geometry": {"coordinates":[-73.987143,40.739146],"type":"Point"}
}