{
  "type": "Feature",
  "properties": {
    "addr:full":"34 3rd Ave Hadley NY 12835",
    "addr:housenumber":"34",
    "addr:postcode":"12835",
    "addr:street":"3Rd Ave",
    "iso:country":"US",
    "sg:address":"34 3rd Ave",
    "sg:city":"Hadley",
    "sg:classifiers":[
        {
            "category":"Shopping",
            "subcategory":"Gifts & Souvenirs",
            "type":"Retail Goods"
        }
    ],
    "sg:phone":"+1   ",
    "sg:postcode":"12835",
    "sg:province":"NY",
    "wof:name":"J Gilbert Trains & Coin",
    "wof:placetype":"venue"
},
  "geometry": {"coordinates":[-73.866528,43.3183],"type":"Point"}
}