{
  "type": "Feature",
  "properties": {
    "addr:full":"239 Elizabeth St New York NY 10012",
    "addr:housenumber":"239",
    "addr:postcode":"10012",
    "addr:street":"Elizabeth St",
    "iso:country":"US",
    "sg:address":"239 Elizabeth St",
    "sg:city":"New York",
    "sg:classifiers":[
        {
            "category":"Building & Trades",
            "subcategory":"Plumbing",
            "type":"Services"
        }
    ],
    "sg:phone":"+1 212 941 6867",
    "sg:postcode":"10012",
    "sg:province":"NY",
    "sg:tags":[
        "heating",
        "contractor"
    ],
    "wof:name":"Acme Mechanical Contractors",
    "wof:placetype":"venue"
},
  "geometry": {"coordinates":[-73.99364,40.724095],"type":"Point"}
}