{
  "type": "Feature",
  "properties": {
    "addr:full":"3220 3rd Avenue Bronx NY 10451",
    "addr:housenumber":"3220",
    "addr:postcode":"10451",
    "addr:street":"3Rd Avenue",
    "iso:country":"US",
    "sg:address":"3220 3rd Avenue",
    "sg:city":"Bronx",
    "sg:classifiers":[
        {
            "category":"Food & Beverages",
            "subcategory":"Groceries & Convenience Stores",
            "type":"Retail Goods"
        }
    ],
    "sg:phone":"+1 718 993 8623",
    "sg:postcode":"10451",
    "sg:province":"NY",
    "wof:name":"Compare Supermarket",
    "wof:placetype":"venue"
},
  "geometry": {"coordinates":[-73.90884200000001,40.823563],"type":"Point"}
}