{
  "type": "Feature",
  "properties": {
    "addr:full":"30 Front St Ballston Spa NY 12020",
    "addr:housenumber":"30",
    "addr:postcode":"12020",
    "addr:street":"Front St",
    "iso:country":"US",
    "sg:address":"30 Front St",
    "sg:city":"Ballston Spa",
    "sg:classifiers":[
        {
            "category":"Shopping",
            "subcategory":"Clothing, Apparel, & Fashions",
            "type":"Retail Goods"
        }
    ],
    "sg:phone":"+1 518 884 9742",
    "sg:postcode":"12020",
    "sg:province":"NY",
    "wof:name":"C J Outfitter",
    "wof:placetype":"venue"
},
  "geometry": {"coordinates":[-73.84982100000001,43.002617],"type":"Point"}
}