{
  "type": "Feature",
  "properties": {
    "iso:country":"US",
    "sg:address":"162 Mott St",
    "sg:city":"New York",
    "sg:classifiers":[
        {
            "category":"Food & Beverages",
            "subcategory":"Groceries & Convenience Stores",
            "type":"Retail Goods"
        }
    ],
    "sg:phone":"+1 212 965 0692",
    "sg:postcode":"10013",
    "sg:province":"NY",
    "sg:tags":[
        "grocer"
    ],
    "wof:name":"Grand Win Supermarket Inc",
    "wof:placetype":"venue"
},
  "geometry": {"coordinates":[-73.996201,40.7197],"type":"Point"}
}