{
  "type": "Feature",
  "properties": {
    "iso:country":"US",
    "sg:address":"433 Franklin St",
    "sg:city":"Buffalo",
    "sg:classifiers":[
        {
            "category":"Travel",
            "subcategory":"Campground",
            "type":"Entertainment"
        }
    ],
    "sg:phone":"+1 716 608 7793",
    "sg:postcode":"14202",
    "sg:province":"NY",
    "sg:tags":[
        "charity"
    ],
    "wof:name":"Mary Glen Camp Inc",
    "wof:placetype":"venue"
},
  "geometry": {"coordinates":[-78.872316,42.898936],"type":"Point"}
}