{
  "type": "Feature",
  "properties": {
    "iso:country":"US",
    "sg:address":"2001 5th Ave",
    "sg:city":"Troy",
    "sg:classifiers":[
        {
            "category":"Health Services",
            "subcategory":"Doctor",
            "type":"Services"
        }
    ],
    "sg:phone":"+1 518 274 9126",
    "sg:postcode":"12180",
    "sg:province":"NY",
    "sg:tags":[
        "physician",
        "surgeon",
        "clinic",
        "medical"
    ],
    "wof:name":"Capital Healthcare Associates",
    "wof:placetype":"venue"
},
  "geometry": {"coordinates":[-73.68682099999999,42.734096],"type":"Point"}
}