{
  "type": "Feature",
  "properties": {
    "iso:country":"US",
    "sg:address":"237 W 37th St",
    "sg:city":"New York",
    "sg:classifiers":[
        {
            "category":"Manufacturing",
            "subcategory":"Apparel",
            "type":"Manufacturing & Wholesale Goods"
        }
    ],
    "sg:phone":"+1   ",
    "sg:postcode":"10018",
    "sg:province":"NY",
    "wof:name":"Ervingeoffrey",
    "wof:placetype":"venue"
},
  "geometry": {"coordinates":[-73.991253,40.753716],"type":"Point"}
}