{
  "type": "Feature",
  "properties": {
    "iso:country":"US",
    "sg:address":"452 Ridge Rd W",
    "sg:city":"Rochester",
    "sg:classifiers":[
        {
            "category":"Professional",
            "subcategory":"Engineering",
            "type":"Services"
        }
    ],
    "sg:phone":"+1 585 663 0710",
    "sg:postcode":"14420",
    "sg:province":"NY",
    "sg:tags":[
        "engineer"
    ],
    "sg:website":"www.optimation.com",
    "wof:name":"Optimation Technology Inc",
    "wof:placetype":"venue"
},
  "geometry": {"coordinates":[-77.640327,43.201135],"type":"Point"}
}