{
  "type": "Feature",
  "properties": {
    "addr:full":"1295 Northern Blvd Ste 17 Manhasset NY 11030",
    "addr:housenumber":"1295",
    "addr:postcode":"11030",
    "addr:street":"Northern Blvd Ste 17",
    "iso:country":"US",
    "sg:address":"1295 Northern Blvd Ste 17",
    "sg:city":"Manhasset",
    "sg:classifiers":[
        {
            "category":"Professional",
            "subcategory":"Lawyer & Legal Services",
            "type":"Services"
        }
    ],
    "sg:phone":"+1 516 365 9281",
    "sg:postcode":"11030",
    "sg:province":"NY",
    "wof:name":"Di Conza Peter J Jr PC Atty",
    "wof:placetype":"venue"
},
  "geometry": {"coordinates":[-73.69899700000001,40.7925],"type":"Point"}
}