{
  "type": "Feature",
  "properties": {
    "addr:full":"110 Wall Street New York NY 10005",
    "addr:housenumber":"110",
    "addr:postcode":"10005",
    "addr:street":"Wall Street",
    "iso:country":"US",
    "sg:address":"110 Wall Street",
    "sg:city":"New York",
    "sg:classifiers":[
        {
            "category":"Professional",
            "subcategory":"Employment Agencies",
            "type":"Services"
        }
    ],
    "sg:phone":"+1 646 595 1660",
    "sg:postcode":"10005",
    "sg:province":"NY",
    "wof:name":"Act",
    "wof:placetype":"venue"
},
  "geometry": {"coordinates":[-74.006674,40.704619],"type":"Point"}
}