{
  "type": "Feature",
  "properties": {
    "addr:full":"7976 Oak Brook Cir Pittsford NY 14534",
    "addr:housenumber":"7976",
    "addr:postcode":"14534",
    "addr:street":"Oak Brook Cir",
    "iso:country":"US",
    "sg:address":"7976 Oak Brook Cir",
    "sg:city":"Pittsford",
    "sg:classifiers":[
        {
            "category":"Health Services",
            "subcategory":"Optometrist",
            "type":"Services"
        }
    ],
    "sg:phone":"+1   ",
    "sg:postcode":"14534",
    "sg:province":"NY",
    "wof:name":"Eye Are Center The",
    "wof:placetype":"venue"
},
  "geometry": {"coordinates":[-77.478554,43.024068],"type":"Point"}
}