{
  "type": "Feature",
  "properties": {
    "iso:country":"US",
    "sg:address":"2000 Teall Ave",
    "sg:city":"Syracuse",
    "sg:classifiers":[
        {
            "category":"Professional",
            "subcategory":"Lawyer & Legal Services",
            "type":"Services"
        }
    ],
    "sg:phone":"+1 315 437 0661",
    "sg:postcode":"13206",
    "sg:province":"NY",
    "sg:tags":[
        "attorney"
    ],
    "wof:name":"Philip Tripolone",
    "wof:placetype":"venue"
},
  "geometry": {"coordinates":[-76.123458,43.079642],"type":"Point"}
}