{
  "type": "Feature",
  "properties": {
    "iso:country":"US",
    "sg:address":"1879 Lyndon Blvd",
    "sg:city":"Falconer",
    "sg:classifiers":[
        {
            "category":"Building & Trades",
            "subcategory":"Construction",
            "type":"Services"
        }
    ],
    "sg:phone":"+1 716 664 4416",
    "sg:postcode":"14733",
    "sg:province":"NY",
    "sg:tags":[
        "general",
        "contractor"
    ],
    "wof:name":"Universal Construction",
    "wof:placetype":"venue"
},
  "geometry": {"coordinates":[-79.18499300000001,42.113714],"type":"Point"}
}