{
  "type": "Feature",
  "properties": {
    "iso:country":"US",
    "sg:address":"75 Pulaski St",
    "sg:city":"Auburn",
    "sg:classifiers":[
        {
            "category":"Shopping",
            "subcategory":"Bicycles & Sporting Goods",
            "type":"Retail Goods"
        }
    ],
    "sg:phone":"+1 315 255 0513",
    "sg:postcode":"13021",
    "sg:province":"NY",
    "sg:tags":[
        "apparel",
        "bowling",
        "accessory"
    ],
    "wof:name":"Strike One Pro Shop",
    "wof:placetype":"venue"
},
  "geometry": {"coordinates":[-76.577438,42.940995],"type":"Point"}
}