{
  "type": "Feature",
  "properties": {
    "addr:full":"1355 1 Ave New York NY 10021",
    "addr:housenumber":"1355",
    "addr:postcode":"10021",
    "addr:street":"1 Ave",
    "iso:country":"US",
    "sg:address":"1355 1 Ave",
    "sg:city":"New York",
    "sg:classifiers":[
        {
            "category":"Banks & Credit Unions",
            "subcategory":"Bank",
            "type":"Services"
        }
    ],
    "sg:phone":"+1 212 288 2005",
    "sg:postcode":"10021",
    "sg:province":"NY",
    "sg:tags":[
        "federal",
        "savings"
    ],
    "wof:name":"Fourth Federal Savings Bank",
    "wof:placetype":"venue"
},
  "geometry": {"coordinates":[-73.95695499999999,40.766493],"type":"Point"}
}