{
  "type": "Feature",
  "properties": {
    "addr:full":"4 Maple St Croton On Hudson NY 10520",
    "addr:housenumber":"4",
    "addr:postcode":"10520",
    "addr:street":"Maple St",
    "iso:country":"US",
    "sg:address":"4 Maple St",
    "sg:city":"Croton On Hudson",
    "sg:classifiers":[
        {
            "category":"Restaurant",
            "type":"Food & Drink"
        }
    ],
    "sg:phone":"+1 914 271 8104",
    "sg:postcode":"10520",
    "sg:province":"NY",
    "wof:name":"Capriccio Pizza",
    "wof:placetype":"venue"
},
  "geometry": {"coordinates":[-73.885425,41.201822],"type":"Point"}
}