{
  "type": "Feature",
  "properties": {
    "addr:full":"676 Flushing Ave Brooklyn NY 11206",
    "addr:housenumber":"676",
    "addr:postcode":"11206",
    "addr:street":"Flushing Ave",
    "iso:country":"US",
    "sg:address":"676 Flushing Ave",
    "sg:city":"Brooklyn",
    "sg:phone":"+1 718 388 3135",
    "sg:postcode":"11206",
    "sg:province":"NY",
    "sg:tags":[
        "equipment",
        "commercial"
    ],
    "wof:name":"Old Reliable Store Fixture Co",
    "wof:placetype":"venue"
},
  "geometry": {"coordinates":[-73.944985,40.700275],"type":"Point"}
}