{
  "type": "Feature",
  "properties": {
    "iso:country":"US",
    "sg:address":"727 Bedford Rd",
    "sg:city":"Mount Kisco",
    "sg:classifiers":[
        {
            "category":"Restaurant",
            "type":"Food & Drink"
        }
    ],
    "sg:phone":"+1   ",
    "sg:postcode":"10549",
    "sg:province":"NY",
    "sg:tags":[
        "eating"
    ],
    "wof:name":"J & M Fine Foods Inc",
    "wof:placetype":"venue"
},
  "geometry": {"coordinates":[-73.667365,41.197473],"type":"Point"}
}