{
  "type": "Feature",
  "properties": {
    "addr:full":"45 S Broadway Yonkers NY 10701",
    "addr:housenumber":"45",
    "addr:postcode":"10701",
    "addr:street":"S Broadway",
    "iso:country":"US",
    "sg:address":"45 S Broadway",
    "sg:city":"Yonkers",
    "sg:classifiers":[
        {
            "category":"Building & Trades",
            "subcategory":"Plumbing",
            "type":"Services"
        }
    ],
    "sg:phone":"+1 914 966 8800",
    "sg:postcode":"10701",
    "sg:province":"NY",
    "sg:tags":[
        "air",
        "heating",
        "conditioning",
        "contractor"
    ],
    "wof:name":"Byrne Heating and AC LLC",
    "wof:placetype":"venue"
},
  "geometry": {"coordinates":[-73.89891799999999,40.931711],"type":"Point"}
}