{
  "type": "Feature",
  "properties": {
    "addr:full":"901 Lodi St Syracuse NY 13203",
    "addr:housenumber":"901",
    "addr:postcode":"13203",
    "addr:street":"Lodi St",
    "iso:country":"US",
    "sg:address":"901 Lodi St",
    "sg:city":"Syracuse",
    "sg:classifiers":[
        {
            "category":"Professional",
            "subcategory":"Accounting & Tax Preparation",
            "type":"Services"
        }
    ],
    "sg:phone":"+1 315 424 1145",
    "sg:postcode":"13203",
    "sg:province":"NY",
    "sg:tags":[
        "accountant"
    ],
    "wof:name":"Bush & Germain PC",
    "wof:placetype":"venue"
},
  "geometry": {"coordinates":[-76.142579,43.057508],"type":"Point"}
}