{
  "type": "Feature",
  "properties": {
    "iso:country":"US",
    "sg:address":"7023 15th Ave",
    "sg:city":"Brooklyn",
    "sg:classifiers":[
        {
            "category":"Building & Trades",
            "subcategory":"Construction",
            "type":"Services"
        }
    ],
    "sg:phone":"+1 212 921 7583",
    "sg:postcode":"11228",
    "sg:province":"NY",
    "sg:tags":[
        "roofing",
        "contractor"
    ],
    "wof:name":"Roman Roofing",
    "wof:placetype":"venue"
},
  "geometry": {"coordinates":[-74.000497,40.620003],"type":"Point"}
}