{
  "type": "Feature",
  "properties": {
    "addr:full":"831 Starin Ave Buffalo NY 14223",
    "addr:housenumber":"831",
    "addr:postcode":"14223",
    "addr:street":"Starin Ave",
    "iso:country":"US",
    "sg:address":"831 Starin Ave",
    "sg:city":"Buffalo",
    "sg:classifiers":[
        {
            "category":"Professional",
            "subcategory":"Accounting & Tax Preparation",
            "type":"Services"
        }
    ],
    "sg:phone":"+1   ",
    "sg:postcode":"14223",
    "sg:province":"NY",
    "wof:name":"Norbert Schechter CPA",
    "wof:placetype":"venue"
},
  "geometry": {"coordinates":[-78.843844,42.961269],"type":"Point"}
}