{
  "type": "Feature",
  "properties": {
    "addr:full":"2920 Ave J Brooklyn NY 11210",
    "addr:postcode":"11210",
    "addr:street":"2920 Ave J",
    "iso:country":"US",
    "sg:address":"2920 Ave J",
    "sg:city":"Brooklyn",
    "sg:classifiers":[
        {
            "category":"Organizations",
            "subcategory":"Religious Organization",
            "type":"Services"
        }
    ],
    "sg:phone":"+1 718 252 4502",
    "sg:postcode":"11210",
    "sg:province":"NY",
    "wof:name":"Congregation Poaleh Agudath",
    "wof:placetype":"venue"
},
  "geometry": {"coordinates":[-73.947018,40.626678],"type":"Point"}
}