{
  "type": "Feature",
  "properties": {
    "addr:full":"420 Clinton Ave Brooklyn NY 11238",
    "addr:housenumber":"420",
    "addr:postcode":"11238",
    "addr:street":"Clinton Ave",
    "iso:country":"US",
    "sg:address":"420 Clinton Ave",
    "sg:city":"Brooklyn",
    "sg:classifiers":[
        {
            "category":"Building & Trades",
            "subcategory":"Construction",
            "type":"Services"
        }
    ],
    "sg:phone":"+1 718 230 0685",
    "sg:postcode":"11238",
    "sg:province":"NY",
    "sg:tags":[
        "house"
    ],
    "wof:name":"Supreme Renovations",
    "wof:placetype":"venue"
},
  "geometry": {"coordinates":[-73.96722699999999,40.684954],"type":"Point"}
}