{
  "type": "Feature",
  "properties": {
    "iso:country":"US",
    "sg:address":"180 Momrow Rd",
    "sg:city":"Sand Lake",
    "sg:classifiers":[
        {
            "category":"Building & Trades",
            "subcategory":"Construction",
            "type":"Services"
        }
    ],
    "sg:phone":"+1 518 674 5123",
    "sg:postcode":"12153",
    "sg:province":"NY",
    "sg:tags":[
        "floor",
        "laying",
        "contractor"
    ],
    "wof:name":"Darrin M Snyder",
    "wof:placetype":"venue"
},
  "geometry": {"coordinates":[-73.494867,42.621198],"type":"Point"}
}