{
  "type": "Feature",
  "properties": {
    "iso:country":"US",
    "sg:address":"3100 3rd Ave",
    "sg:city":"Bronx",
    "sg:classifiers":[
        {
            "category":"Health Services",
            "subcategory":"Doctor",
            "type":"Services"
        }
    ],
    "sg:phone":"+1 718 665 7845",
    "sg:postcode":"10451",
    "sg:province":"NY",
    "sg:tags":[
        "physician",
        "surgeon"
    ],
    "wof:name":"John Osei-Tutu MD",
    "wof:placetype":"venue"
},
  "geometry": {"coordinates":[-73.911745,40.822106],"type":"Point"}
}