{
  "type": "Feature",
  "properties": {
    "addr:full":"491 Kings Hwy Valley Cottage NY 10989",
    "addr:housenumber":"491",
    "addr:postcode":"10989",
    "addr:street":"Kings Hwy Valley",
    "iso:country":"US",
    "sg:address":"491 Kings Hwy",
    "sg:city":"Valley Cottage",
    "sg:classifiers":[
        {
            "category":"Professional",
            "type":"Services"
        }
    ],
    "sg:phone":"+1 845 267 3278",
    "sg:postcode":"10989",
    "sg:province":"NY",
    "sg:tags":[
        "establishment"
    ],
    "wof:name":"Valley Rc",
    "wof:placetype":"venue"
},
  "geometry": {"coordinates":[-73.94972,41.119998],"type":"Point"}
}