{
  "type": "Feature",
  "properties": {
    "addr:full":"1171 65th St Brooklyn NY 11219",
    "addr:housenumber":"1171",
    "addr:postcode":"11219",
    "addr:street":"65Th St",
    "iso:country":"US",
    "sg:address":"1171 65th St",
    "sg:city":"Brooklyn",
    "sg:classifiers":[
        {
            "category":"Building & Trades",
            "subcategory":"Cleaning & Sanitation",
            "type":"Services"
        }
    ],
    "sg:phone":"+1 718 837 3493",
    "sg:postcode":"11219",
    "sg:province":"NY",
    "sg:tags":[
        "maintenance"
    ],
    "wof:name":"Filix Torres",
    "wof:placetype":"venue"
},
  "geometry": {"coordinates":[-74.00487099999999,40.628322],"type":"Point"}
}