{
  "type": "Feature",
  "properties": {
    "addr:full":"603 E Main St Bay Shore NY 11706",
    "addr:housenumber":"603",
    "addr:postcode":"11706",
    "addr:street":"E Main St",
    "iso:country":"US",
    "sg:address":"603 E Main St",
    "sg:city":"Bay Shore",
    "sg:classifiers":[
        {
            "category":"Cinema",
            "subcategory":"Movie Rental",
            "type":"Entertainment"
        }
    ],
    "sg:phone":"+1 631 666 0089",
    "sg:postcode":"11706",
    "sg:province":"NY",
    "sg:tags":[
        "video",
        "game",
        "disc",
        "leasing",
        "tape"
    ],
    "sg:website":"www.blockbuster.com",
    "wof:name":"Blockbuster Video",
    "wof:placetype":"venue"
},
  "geometry": {"coordinates":[-73.231003,40.727402],"type":"Point"}
}