{
  "type": "Feature",
  "properties": {
    "addr:full":"9224 3rd Avenue Brooklyn NY 11209",
    "addr:housenumber":"9224",
    "addr:postcode":"11209",
    "addr:street":"3Rd Avenue",
    "iso:country":"US",
    "sg:address":"9224 3rd Avenue",
    "sg:city":"Brooklyn",
    "sg:classifiers":[
        {
            "category":"Restaurant",
            "type":"Food & Drink"
        }
    ],
    "sg:phone":"+1 718 745 7999",
    "sg:postcode":"11209",
    "sg:province":"NY",
    "sg:website":"www.deliaslounge.com",
    "wof:name":"Delia's Lounge & Cafe",
    "wof:placetype":"venue"
},
  "geometry": {"coordinates":[-74.033097,40.61882],"type":"Point"}
}