{
  "type": "Feature",
  "properties": {
    "addr:full":"420 Malcolm X Blvd New York NY 10037",
    "addr:housenumber":"420",
    "addr:postcode":"10037",
    "addr:street":"Malcolm X Blvd",
    "iso:country":"US",
    "sg:address":"420 Malcolm X Blvd",
    "sg:city":"New York",
    "sg:classifiers":[
        {
            "category":"Personal",
            "subcategory":"Beauty Salon",
            "type":"Services"
        }
    ],
    "sg:phone":"+1 917 507 0917",
    "sg:postcode":"10037",
    "sg:province":"NY",
    "sg:tags":[
        "hair"
    ],
    "wof:name":"Hair Solutions Nyc",
    "wof:placetype":"venue"
},
  "geometry": {"coordinates":[-73.942629,40.811564],"type":"Point"}
}