{
  "type": "Feature",
  "properties": {
    "iso:country":"US",
    "sg:address":"2111 Bellmore Ave",
    "sg:city":"Bellmore",
    "sg:classifiers":[
        {
            "category":"Retail",
            "subcategory":"Pet Boarding",
            "type":"Services"
        }
    ],
    "sg:phone":"+1 516 781 4199",
    "sg:postcode":"11710",
    "sg:province":"NY",
    "sg:tags":[
        "boarding/pet",
        "sitting"
    ],
    "wof:name":"Prim & Proper Grooming Salon",
    "wof:placetype":"venue"
},
  "geometry": {"coordinates":[-73.528198,40.674801],"type":"Point"}
}