{
  "type": "Feature",
  "properties": {
    "iso:country":"US",
    "sg:address":"24 Longdale Ave",
    "sg:city":"White Plains",
    "sg:classifiers":[
        {
            "category":"Building & Trades",
            "subcategory":"Landscaping Services",
            "type":"Services"
        }
    ],
    "sg:phone":"+1 914 949 2084",
    "sg:postcode":"10607",
    "sg:province":"NY",
    "sg:tags":[
        "landscape",
        "contractor"
    ],
    "wof:name":"Chavez Landscaping",
    "wof:placetype":"venue"
},
  "geometry": {"coordinates":[-73.792162,41.042982],"type":"Point"}
}