{
  "type": "Feature",
  "properties": {
    "addr:full":"53 Mariner Way Monsey NY 10952",
    "addr:housenumber":"53",
    "addr:postcode":"10952",
    "addr:street":"Mariner Way",
    "iso:country":"US",
    "sg:address":"53 Mariner Way",
    "sg:city":"Monsey",
    "sg:classifiers":[
        {
            "category":"Wholesale",
            "subcategory":"Non-durable Goods",
            "type":"Manufacturing & Wholesale Goods"
        }
    ],
    "sg:phone":"+1 845 354 8758",
    "sg:postcode":"10952",
    "sg:province":"NY",
    "wof:name":"Mariner Trading Inc",
    "wof:placetype":"venue"
},
  "geometry": {"coordinates":[-74.07098999999999,41.141555],"type":"Point"}
}