{
  "type": "Feature",
  "properties": {
    "addr:full":"1836 Davis St Elmira NY 14901",
    "addr:housenumber":"1836",
    "addr:postcode":"14901",
    "addr:street":"Davis St",
    "iso:country":"US",
    "sg:address":"1836 Davis St",
    "sg:city":"Elmira",
    "sg:classifiers":[
        {
            "category":"Personal",
            "subcategory":"Beauty Salon",
            "type":"Services"
        }
    ],
    "sg:phone":"+1 607 732 8460",
    "sg:postcode":"14901",
    "sg:province":"NY",
    "wof:name":"Michael's Hair Fashions",
    "wof:placetype":"venue"
},
  "geometry": {"coordinates":[-76.826418,42.11141],"type":"Point"}
}