{
  "type": "Feature",
  "properties": {
    "addr:full":"116 Main St Oneonta NY 13820",
    "addr:housenumber":"116",
    "addr:postcode":"13820",
    "addr:street":"Main St",
    "iso:country":"US",
    "sg:address":"116 Main St",
    "sg:city":"Oneonta",
    "sg:classifiers":[
        {
            "category":"Personal",
            "subcategory":"Beauty Salon",
            "type":"Services"
        }
    ],
    "sg:phone":"+1 607 432 2791",
    "sg:postcode":"13820",
    "sg:province":"NY",
    "sg:tags":[
        "manicuring"
    ],
    "wof:name":"Magic Nails",
    "wof:placetype":"venue"
},
  "geometry": {"coordinates":[-75.063811,42.451635],"type":"Point"}
}