{
  "type": "Feature",
  "properties": {
    "iso:country":"US",
    "sg:address":"20 E Bayard St",
    "sg:city":"Seneca Falls",
    "sg:classifiers":[
        {
            "category":"Food & Beverages",
            "subcategory":"Groceries & Convenience Stores",
            "type":"Retail Goods"
        }
    ],
    "sg:phone":"+1 315 568 1798",
    "sg:postcode":"13148",
    "sg:province":"NY",
    "sg:tags":[
        "grocer"
    ],
    "wof:name":"Seneca Falls IGA",
    "wof:placetype":"venue"
},
  "geometry": {"coordinates":[-76.79605599999999,42.908604],"type":"Point"}
}