{
  "type": "Feature",
  "properties": {
    "addr:full":"117 Griffing Ave Riverhead NY 11901",
    "addr:housenumber":"117",
    "addr:postcode":"11901",
    "addr:street":"Griffing Ave",
    "iso:country":"US",
    "sg:address":"117 Griffing Ave",
    "sg:city":"Riverhead",
    "sg:classifiers":[
        {
            "category":"Museum",
            "type":"Entertainment"
        }
    ],
    "sg:phone":"+1 516 250 9405",
    "sg:postcode":"11901",
    "sg:province":"NY",
    "sg:tags":[
        "organization",
        "arts",
        "information"
    ],
    "wof:name":"Long Island Academy-Fine Art",
    "wof:placetype":"venue"
},
  "geometry": {"coordinates":[-72.664688,40.918132],"type":"Point"}
}