{
  "type": "Feature",
  "properties": {
    "iso:country":"US",
    "sg:address":"931 N Salina St",
    "sg:city":"Syracuse",
    "sg:classifiers":[
        {
            "category":"Retail",
            "subcategory":"Auto Repair",
            "type":"Services"
        }
    ],
    "sg:phone":"+1 315 422 8681",
    "sg:postcode":"13208",
    "sg:province":"NY",
    "sg:tags":[
        "body",
        "automobile",
        "painting"
    ],
    "wof:name":"Dick's Collision",
    "wof:placetype":"venue"
},
  "geometry": {"coordinates":[-76.155861,43.063758],"type":"Point"}
}