{
  "type": "Feature",
  "properties": {
    "iso:country":"US",
    "sg:address":"4511 Park Ave",
    "sg:city":"Bronx",
    "sg:classifiers":[
        {
            "category":"Organizations",
            "subcategory":"Religious Organization",
            "type":"Services"
        }
    ],
    "sg:phone":"+1 718 563 2777",
    "sg:postcode":"10457",
    "sg:province":"NY",
    "sg:tags":[
        "church"
    ],
    "wof:name":"Sardis Baptist Church",
    "wof:placetype":"venue"
},
  "geometry": {"coordinates":[-73.894987,40.855653],"type":"Point"}
}