{
  "type": "Feature",
  "properties": {
    "addr:full":"133 W 71 St New York NY 10023",
    "addr:housenumber":"133",
    "addr:postcode":"10023",
    "addr:street":"W 71 St",
    "iso:country":"US",
    "sg:address":"133 W 71 St",
    "sg:city":"New York",
    "sg:classifiers":[
        {
            "category":"Professional",
            "subcategory":"Management & Consulting",
            "type":"Services"
        }
    ],
    "sg:phone":"+1 212 787 2443",
    "sg:postcode":"10023",
    "sg:province":"NY",
    "sg:tags":[
        "fuel"
    ],
    "wof:name":"Hubbard Levine Management",
    "wof:placetype":"venue"
},
  "geometry": {"coordinates":[-73.98030799999999,40.777351],"type":"Point"}
}