{
  "type": "Feature",
  "properties": {
    "addr:full":"4917 8th Ave Brooklyn NY 11220",
    "addr:housenumber":"4917",
    "addr:postcode":"11220",
    "addr:street":"8Th Ave",
    "iso:country":"US",
    "sg:address":"4917 8th Ave",
    "sg:city":"Brooklyn",
    "sg:classifiers":[
        {
            "category":"Cinema",
            "subcategory":"Movie Rental",
            "type":"Entertainment"
        }
    ],
    "sg:phone":"+1 718 853 8181",
    "sg:postcode":"11220",
    "sg:province":"NY",
    "sg:tags":[
        "leasing",
        "video",
        "disc",
        "tape"
    ],
    "wof:name":"S W Trading",
    "wof:placetype":"venue"
},
  "geometry": {"coordinates":[-74.003581,40.641161],"type":"Point"}
}