{
  "type": "Feature",
  "properties": {
    "addr:full":"405 Van Brunt St Brooklyn NY 11231",
    "addr:housenumber":"405",
    "addr:postcode":"11231",
    "addr:street":"Van Brunt St",
    "iso:country":"US",
    "sg:address":"405 Van Brunt St",
    "sg:city":"Brooklyn",
    "sg:classifiers":[
        {
            "category":"Building & Trades",
            "subcategory":"Construction",
            "type":"Services"
        }
    ],
    "sg:phone":"+1 718 788 2625",
    "sg:postcode":"11231",
    "sg:province":"NY",
    "sg:tags":[
        "house"
    ],
    "wof:name":"Everlast Custom Construction",
    "wof:placetype":"venue"
},
  "geometry": {"coordinates":[-74.01542499999999,40.675199],"type":"Point"}
}