{
  "type": "Feature",
  "properties": {
    "iso:country":"US",
    "sg:address":"9 Shady Tree Ln",
    "sg:city":"Port Jefferson",
    "sg:classifiers":[
        {
            "category":"Building & Trades",
            "subcategory":"Construction",
            "type":"Services"
        }
    ],
    "sg:phone":"+1 631 473 2811",
    "sg:postcode":"11777",
    "sg:province":"NY",
    "sg:tags":[
        "hanging",
        "contractor"
    ],
    "wof:name":"Hue Painting Co Inc",
    "wof:placetype":"venue"
},
  "geometry": {"coordinates":[-73.043808,40.942871],"type":"Point"}
}