{
  "type": "Feature",
  "properties": {
    "iso:country":"US",
    "sg:address":"124 Renwick St",
    "sg:city":"Newburgh",
    "sg:classifiers":[
        {
            "category":"Deli",
            "type":"Food & Drink"
        }
    ],
    "sg:phone":"+1 845 568 5808",
    "sg:postcode":"12550",
    "sg:province":"NY",
    "wof:name":"I & M 5 Deli & Grocery",
    "wof:placetype":"venue"
},
  "geometry": {"coordinates":[-74.013199,41.494701],"type":"Point"}
}