{
  "type": "Feature",
  "properties": {
    "iso:country":"US",
    "sg:address":"1812 East Ave",
    "sg:city":"Rochester",
    "sg:classifiers":[
        {
            "category":"Personal",
            "subcategory":"Beauty Salon",
            "type":"Services"
        }
    ],
    "sg:phone":"+1 585 271 8480",
    "sg:postcode":"14610",
    "sg:province":"NY",
    "wof:name":"Raphael Hair Design",
    "wof:placetype":"venue"
},
  "geometry": {"coordinates":[-77.556974,43.146081],"type":"Point"}
}