{
  "type": "Feature",
  "properties": {
    "iso:country":"US",
    "sg:address":"1789 Co Rd 50",
    "sg:city":"Arkport",
    "sg:classifiers":[
        {
            "category":"Retail",
            "subcategory":"Auto Repair",
            "type":"Services"
        }
    ],
    "sg:phone":"+1   ",
    "sg:postcode":"14807",
    "sg:province":"NY",
    "sg:tags":[
        "body"
    ],
    "wof:name":"R J Cars Inc",
    "wof:placetype":"venue"
},
  "geometry": {"coordinates":[-77.628298,42.455225],"type":"Point"}
}