{
  "type": "Feature",
  "properties": {
    "addr:full":"99 South 6th Street Brooklyn NY 11211",
    "addr:housenumber":"99",
    "addr:postcode":"11211",
    "addr:street":"South 6Th Street",
    "iso:country":"US",
    "sg:address":"99 South 6th Street",
    "sg:city":"Brooklyn",
    "sg:classifiers":[
        {
            "category":"Shopping",
            "subcategory":"Bicycles & Sporting Goods",
            "type":"Retail Goods"
        }
    ],
    "sg:phone":"+1 917 720 0992",
    "sg:postcode":"11211",
    "sg:province":"NY",
    "sg:tags":[
        "bike"
    ],
    "wof:name":"Traif Bike Geschaft",
    "wof:placetype":"venue"
},
  "geometry": {"coordinates":[-73.96512199999999,40.710945],"type":"Point"}
}