{
  "type": "Feature",
  "properties": {
    "iso:country":"US",
    "sg:address":"266 S 4th Ave",
    "sg:city":"Mt Vernon",
    "sg:classifiers":[
        {
            "category":"Retail",
            "subcategory":"Self-service Laundry",
            "type":"Services"
        }
    ],
    "sg:phone":"+1 914 668 4747",
    "sg:postcode":"10550",
    "sg:province":"NY",
    "wof:name":"Around The Corner Laundry",
    "wof:placetype":"venue"
},
  "geometry": {"coordinates":[-73.83486499999999,40.905974],"type":"Point"}
}