{
  "type": "Feature",
  "properties": {
    "iso:country":"US",
    "sg:address":"15 Briarwood Rd",
    "sg:city":"Wyandanch",
    "sg:classifiers":[
        {
            "category":"Professional",
            "subcategory":"Computer Services",
            "type":"Services"
        }
    ],
    "sg:phone":"+1 631 643 5516",
    "sg:postcode":"11798",
    "sg:province":"NY",
    "sg:tags":[
        "consultant",
        "designer"
    ],
    "wof:name":"Microrays Inc",
    "wof:placetype":"venue"
},
  "geometry": {"coordinates":[-73.386124,40.758025],"type":"Point"}
}