{
  "type": "Feature",
  "properties": {
    "addr:full":"111 Hollister Way Burnt Hills NY 12027",
    "addr:housenumber":"111",
    "addr:postcode":"12027",
    "addr:street":"Hollister Way",
    "iso:country":"US",
    "sg:address":"111 Hollister Way",
    "sg:city":"Burnt Hills",
    "sg:classifiers":[
        {
            "category":"Manufacturing",
            "subcategory":"Tools & Machinery",
            "type":"Manufacturing & Wholesale Goods"
        }
    ],
    "sg:phone":"+1 518 399 2706",
    "sg:postcode":"12027",
    "sg:province":"NY",
    "sg:tags":[
        "turbine"
    ],
    "wof:name":"International Turbine Support",
    "wof:placetype":"venue"
},
  "geometry": {"coordinates":[-73.891507,42.902084],"type":"Point"}
}