{
  "type": "Feature",
  "properties": {
    "addr:full":"3417 Broadway Astoria NY 11106",
    "addr:housenumber":"3417",
    "addr:postcode":"11106",
    "addr:street":"Broadway",
    "iso:country":"US",
    "sg:address":"3417 Broadway",
    "sg:city":"Astoria",
    "sg:classifiers":[
        {
            "category":"Retail",
            "subcategory":"Laundry & Dry Cleaning",
            "type":"Services"
        }
    ],
    "sg:phone":"+1 718 274 8907",
    "sg:postcode":"11106",
    "sg:province":"NY",
    "wof:name":"Old Neighbors Laundry Dry Cleaning and Delivery",
    "wof:placetype":"venue"
},
  "geometry": {"coordinates":[-73.922231,40.760627],"type":"Point"}
}