{
  "type": "Feature",
  "properties": {
    "addr:full":"361 Central Park Ave Yonkers NY 10704",
    "addr:housenumber":"361",
    "addr:postcode":"10704",
    "addr:street":"Central Park Ave",
    "iso:country":"US",
    "sg:address":"361 Central Park Ave",
    "sg:city":"Yonkers",
    "sg:classifiers":[
        {
            "category":"Building & Trades",
            "subcategory":"Construction",
            "type":"Services"
        }
    ],
    "sg:phone":"+1 914 709 1779",
    "sg:postcode":"10704",
    "sg:province":"NY",
    "sg:tags":[
        "general",
        "contractor"
    ],
    "wof:name":"H Y M Construction Corp",
    "wof:placetype":"venue"
},
  "geometry": {"coordinates":[-73.873541,40.915033],"type":"Point"}
}