{
  "type": "Feature",
  "properties": {
    "iso:country":"US",
    "sg:address":"167 Saw Mill River Rd",
    "sg:city":"Yonkers",
    "sg:classifiers":[
        {
            "category":"Freight",
            "type":"Transportation"
        }
    ],
    "sg:phone":"+1 914 969 1917",
    "sg:postcode":"10701",
    "sg:province":"NY",
    "sg:tags":[
        "delivery"
    ],
    "wof:name":"Easton Delivery Svc",
    "wof:placetype":"venue"
},
  "geometry": {"coordinates":[-73.880931,40.942569],"type":"Point"}
}