{
  "type": "Feature",
  "properties": {
    "iso:country":"US",
    "sg:address":"18 S Broadway",
    "sg:city":"Nyack",
    "sg:classifiers":[
        {
            "category":"Place Of Worship",
            "subcategory":"Church",
            "type":"Public Place"
        },
        {
            "category":"Place Of Worship",
            "type":"Public Place"
        }
    ],
    "sg:phone":"+1 845 358 5518",
    "sg:postcode":"10960",
    "sg:province":"NY",
    "sg:tags":[
        "churches-christian-reformed",
        "churches-reformed"
    ],
    "wof:name":"The First Reformed Church Of Nyak Inc",
    "wof:placetype":"venue"
},
  "geometry": {"coordinates":[-73.91843,41.090321],"type":"Point"}
}