{
  "type": "Feature",
  "properties": {
    "addr:full":"1287 Herkimer Street Brooklyn NY 11233",
    "addr:housenumber":"1287",
    "addr:postcode":"11233",
    "addr:street":"Herkimer Street",
    "iso:country":"US",
    "sg:address":"1287 Herkimer Street",
    "sg:city":"Brooklyn",
    "sg:classifiers":[
        {
            "category":"Restaurant",
            "type":"Food & Drink"
        }
    ],
    "sg:phone":"+1 718 385 5681",
    "sg:postcode":"11233",
    "sg:province":"NY",
    "wof:name":"Scaddies International Cuisine",
    "wof:placetype":"venue"
},
  "geometry": {"coordinates":[-73.910826,40.6774],"type":"Point"}
}