{
  "type": "Feature",
  "properties": {
    "addr:full":"9 Huntington Rd Port Washington NY 11050",
    "addr:housenumber":"9",
    "addr:postcode":"11050",
    "addr:street":"Huntington Rd",
    "iso:country":"US",
    "sg:address":"9 Huntington Rd",
    "sg:city":"Port Washington",
    "sg:classifiers":[
        {
            "category":"Insurance",
            "subcategory":"Insurance Agent",
            "type":"Services"
        }
    ],
    "sg:phone":"+1 516 767 2594",
    "sg:postcode":"11050",
    "sg:province":"NY",
    "sg:tags":[
        "broker"
    ],
    "wof:name":"Sound View Financial Services",
    "wof:placetype":"venue"
},
  "geometry": {"coordinates":[-73.69950300000001,40.822058],"type":"Point"}
}