{
  "type": "Feature",
  "properties": {
    "addr:full":"520 Hampton Rd Southampton NY 11968",
    "addr:housenumber":"520",
    "addr:postcode":"11968",
    "addr:street":"Hampton Rd",
    "iso:country":"US",
    "sg:address":"520 Hampton Rd",
    "sg:city":"Southampton",
    "sg:classifiers":[
        {
            "category":"Real Estate",
            "subcategory":"Real Estate Operator",
            "type":"Services"
        }
    ],
    "sg:phone":"+1 631 287 1028",
    "sg:postcode":"11968",
    "sg:province":"NY",
    "sg:tags":[
        "condominium"
    ],
    "wof:name":"Farrington Close Condos",
    "wof:placetype":"venue"
},
  "geometry": {"coordinates":[-72.37567900000001,40.895074],"type":"Point"}
}