{
  "type": "Feature",
  "properties": {
    "iso:country":"US",
    "sg:address":"716 Hawley Ave",
    "sg:city":"Syracuse",
    "sg:classifiers":[
        {
            "category":"Government",
            "subcategory":"Police Station",
            "type":"Public Place"
        }
    ],
    "sg:phone":"+1 315 472 5058",
    "sg:postcode":"13203",
    "sg:province":"NY",
    "sg:tags":[
        "department"
    ],
    "wof:name":"Syracuse Police Dept",
    "wof:placetype":"venue"
},
  "geometry": {"coordinates":[-76.132171,43.055173],"type":"Point"}
}