{
  "type": "Feature",
  "properties": {
    "addr:full":"2395 Kenmore Ave Tonawanda NY 14150",
    "addr:housenumber":"2395",
    "addr:postcode":"14150",
    "addr:street":"Kenmore Ave",
    "iso:country":"US",
    "sg:address":"2395 Kenmore Ave",
    "sg:city":"Tonawanda",
    "sg:classifiers":[
        {
            "category":"Autos & Motor Vehicles",
            "subcategory":"Automobile Sales",
            "type":"Retail Goods"
        }
    ],
    "sg:phone":"+1   ",
    "sg:postcode":"14150",
    "sg:province":"NY",
    "wof:name":"General Motors",
    "wof:placetype":"venue"
},
  "geometry": {"coordinates":[-78.902406,42.969119],"type":"Point"}
}