{
  "type": "Feature",
  "properties": {
    "addr:full":"1023 Nostrand Ave Brooklyn NY 11225",
    "addr:housenumber":"1023",
    "addr:postcode":"11225",
    "addr:street":"Nostrand Ave",
    "iso:country":"US",
    "sg:address":"1023 Nostrand Ave",
    "sg:city":"Brooklyn",
    "sg:classifiers":[
        {
            "category":"Personal",
            "subcategory":"Beauty Salon",
            "type":"Services"
        }
    ],
    "sg:phone":"+1 718 773 8428",
    "sg:postcode":"11225",
    "sg:province":"NY",
    "sg:tags":[
        "shop"
    ],
    "wof:name":"Julie's Beauty Haven",
    "wof:placetype":"venue"
},
  "geometry": {"coordinates":[-73.950857,40.663628],"type":"Point"}
}