{
  "type": "Feature",
  "properties": {
    "iso:country":"US",
    "sg:address":"161 E 170th St",
    "sg:city":"Bronx",
    "sg:classifiers":[
        {
            "category":"Shopping",
            "subcategory":"Gifts & Souvenirs",
            "type":"Retail Goods"
        }
    ],
    "sg:phone":"+1 718 537 2565",
    "sg:postcode":"10452",
    "sg:province":"NY",
    "sg:tags":[
        "collectible"
    ],
    "wof:name":"Adam's Comics & Cards",
    "wof:placetype":"venue"
},
  "geometry": {"coordinates":[-73.913916,40.838927],"type":"Point"}
}