{
  "type": "Feature",
  "properties": {
    "addr:full":"8001 Metropolitan Ave Middle Village NY 11379",
    "addr:housenumber":"8001",
    "addr:postcode":"11379",
    "addr:street":"Metropolitan Ave",
    "iso:country":"US",
    "sg:address":"8001 Metropolitan Ave",
    "sg:city":"Middle Village",
    "sg:classifiers":[
        {
            "category":"Retail",
            "subcategory":"Funeral Services",
            "type":"Services"
        }
    ],
    "sg:phone":"+1 718 326 2033",
    "sg:postcode":"11379",
    "sg:province":"NY",
    "sg:tags":[
        "cemetery"
    ],
    "wof:name":"St Mary Star of the Sea Cemetery",
    "wof:placetype":"venue"
},
  "geometry": {"coordinates":[-73.871399,40.713402],"type":"Point"}
}