{
  "type": "Feature",
  "properties": {
    "iso:country":"US",
    "sg:address":"1230 Oakpoint Ave",
    "sg:city":"Bronx",
    "sg:classifiers":[
        {
            "category":"Wholesale",
            "subcategory":"Fruits & Vegetables",
            "type":"Manufacturing & Wholesale Goods"
        }
    ],
    "sg:phone":"+1 718 328 6300",
    "sg:postcode":"10474",
    "sg:province":"NY",
    "sg:tags":[
        "veggie"
    ],
    "wof:name":"A & G Produce Imports",
    "wof:placetype":"venue"
},
  "geometry": {"coordinates":[-73.888526,40.809682],"type":"Point"}
}