{
  "type": "Feature",
  "properties": {
    "addr:full":"2456 Ocean Pkwy Brooklyn NY 11235",
    "addr:housenumber":"2456",
    "addr:postcode":"11235",
    "addr:street":"Ocean Pkwy",
    "iso:country":"US",
    "sg:address":"2456 Ocean Pkwy",
    "sg:city":"Brooklyn",
    "sg:classifiers":[
        {
            "category":"Building & Trades",
            "subcategory":"Construction",
            "type":"Services"
        }
    ],
    "sg:phone":"+1 718 491 8685",
    "sg:postcode":"11235",
    "sg:province":"NY",
    "sg:tags":[
        "general",
        "contractor"
    ],
    "wof:name":"Beacon Tower Contracting",
    "wof:placetype":"venue"
},
  "geometry": {"coordinates":[-73.965452,40.59017],"type":"Point"}
}