{
  "type": "Feature",
  "properties": {
    "addr:full":"130 Main St E Rochester NY 14604",
    "addr:housenumber":"130",
    "addr:postcode":"14604",
    "addr:street":"Main St E",
    "iso:country":"US",
    "sg:address":"130 Main St E",
    "sg:city":"Rochester",
    "sg:classifiers":[
        {
            "category":"Real Estate",
            "subcategory":"Developer",
            "type":"Services"
        }
    ],
    "sg:phone":"+1 585 327 5155",
    "sg:postcode":"14604",
    "sg:province":"NY",
    "wof:name":"Renaissance Square Corp",
    "wof:placetype":"venue"
},
  "geometry": {"coordinates":[-77.608541,43.156749],"type":"Point"}
}