{
  "type": "Feature",
  "properties": {
    "addr:full":"512 Wolfs Ln Pelham NY 10803",
    "addr:housenumber":"512",
    "addr:postcode":"10803",
    "addr:street":"Wolfs Ln",
    "iso:country":"US",
    "sg:address":"512 Wolfs Ln",
    "sg:city":"Pelham",
    "sg:classifiers":[
        {
            "category":"Restaurant",
            "type":"Food & Drink"
        }
    ],
    "sg:phone":"+1   ",
    "sg:postcode":"10803",
    "sg:province":"NY",
    "sg:tags":[
        "eating"
    ],
    "wof:name":"Thai At Home",
    "wof:placetype":"venue"
},
  "geometry": {"coordinates":[-73.81295799999999,40.900011],"type":"Point"}
}