{
  "type": "Feature",
  "properties": {
    "iso:country":"US",
    "sg:address":"310 E 6th St",
    "sg:city":"New York",
    "sg:classifiers":[
        {
            "category":"Arts & Performance",
            "subcategory":"Music",
            "type":"Entertainment"
        },
        {
            "category":"Restaurant",
            "type":"Food & Drink"
        }
    ],
    "sg:phone":"+1 212 505 8056",
    "sg:postcode":"10003",
    "sg:province":"NY",
    "sg:tags":[
        "indian",
        "venue"
    ],
    "sg:website":"www.facebook.com/tajrestaurant",
    "wof:name":"Taj Restaurant",
    "wof:placetype":"venue"
},
  "geometry": {"coordinates":[-73.987939,40.727045],"type":"Point"}
}