{
  "type": "Feature",
  "properties": {
    "iso:country":"US",
    "sg:address":"1141 S Parkwood Dr",
    "sg:city":"Clifton Park",
    "sg:classifiers":[
        {
            "category":"Professional",
            "subcategory":"Management & Consulting",
            "type":"Services"
        }
    ],
    "sg:phone":"+1   ",
    "sg:postcode":"12065",
    "sg:province":"NY",
    "wof:name":"Netcore Consulting",
    "wof:placetype":"venue"
},
  "geometry": {"coordinates":[-73.775014,42.871755],"type":"Point"}
}