{
  "type": "Feature",
  "properties": {
    "iso:country":"US",
    "sg:address":"25 Central Park W",
    "sg:city":"New York",
    "sg:classifiers":[
        {
            "category":"Shopping",
            "subcategory":"Pharmacy",
            "type":"Retail Goods"
        }
    ],
    "sg:phone":"+1 212 247 8080",
    "sg:postcode":"10023",
    "sg:province":"NY",
    "sg:tags":[
        "drug",
        "store"
    ],
    "wof:name":"Jaros Drugs Inc",
    "wof:placetype":"venue"
},
  "geometry": {"coordinates":[-73.980405,40.770149],"type":"Point"}
}