{
  "type": "Feature",
  "properties": {
    "addr:full":"3385 Broadway New York NY 10031",
    "addr:housenumber":"3385",
    "addr:postcode":"10031",
    "addr:street":"Broadway",
    "iso:country":"US",
    "sg:address":"3385 Broadway",
    "sg:city":"New York",
    "sg:classifiers":[
        {
            "category":"Restaurant",
            "type":"Food & Drink"
        }
    ],
    "sg:menulink":"http://www.allmenus.com/ny/new-york/48749-tres-pasos-mexican-kitchen/menu/",
    "sg:phone":"+1 212 281 2814",
    "sg:postcode":"10031",
    "sg:province":"NY",
    "sg:tags":[
        "mexican"
    ],
    "wof:name":"Tres Pasos Mexican Kitchen",
    "wof:placetype":"venue"
},
  "geometry": {"coordinates":[-73.95405700000001,40.82168],"type":"Point"}
}