{
  "type": "Feature",
  "properties": {
    "addr:full":"35 Gravel Hill Rd Hampton Bays NY 11946",
    "addr:housenumber":"35",
    "addr:postcode":"11946",
    "addr:street":"Gravel Hill Rd",
    "iso:country":"US",
    "sg:address":"35 Gravel Hill Rd",
    "sg:city":"Hampton Bays",
    "sg:classifiers":[
        {
            "category":"Real Estate",
            "subcategory":"Real Estate Agent",
            "type":"Services"
        }
    ],
    "sg:phone":"+1 631 728 5200",
    "sg:postcode":"11946",
    "sg:province":"NY",
    "sg:tags":[
        "appraiser"
    ],
    "wof:name":"Tufano & Assoc Inc",
    "wof:placetype":"venue"
},
  "geometry": {"coordinates":[-72.51017299999999,40.877302],"type":"Point"}
}