{
  "type": "Feature",
  "properties": {
    "iso:country":"US",
    "sg:address":"520 4th St",
    "sg:city":"Troy",
    "sg:classifiers":[
        {
            "category":"Professional",
            "type":"Services"
        }
    ],
    "sg:phone":"+1 518 272 7327",
    "sg:postcode":"12180",
    "sg:province":"NY",
    "sg:tags":[
        "establishment"
    ],
    "wof:name":"Ascota Productions",
    "wof:placetype":"venue"
},
  "geometry": {"coordinates":[-73.694187,42.713838],"type":"Point"}
}