{
  "type": "Feature",
  "properties": {
    "iso:country":"US",
    "sg:address":"214 Sterling St",
    "sg:city":"Watertown",
    "sg:classifiers":[
        {
            "category":"Retail",
            "subcategory":"Funeral Services",
            "type":"Services"
        }
    ],
    "sg:phone":"+1 315 782 0830",
    "sg:postcode":"13601",
    "sg:province":"NY",
    "sg:tags":[
        "director",
        "home"
    ],
    "wof:name":"Cummings Funeral Service Inc",
    "wof:placetype":"venue"
},
  "geometry": {"coordinates":[-75.90828500000001,43.97217],"type":"Point"}
}