{
  "type": "Feature",
  "properties": {
    "iso:country":"US",
    "sg:address":"13 Cornish Rd",
    "sg:city":"Carmel",
    "sg:classifiers":[
        {
            "category":"Building & Trades",
            "subcategory":"Construction",
            "type":"Services"
        }
    ],
    "sg:phone":"+1 845 225 4243",
    "sg:postcode":"10512",
    "sg:province":"NY",
    "sg:tags":[
        "sheet",
        "work",
        "metal",
        "dry wall",
        "contractor"
    ],
    "wof:name":"John J Carl Associates",
    "wof:placetype":"venue"
},
  "geometry": {"coordinates":[-73.69686900000001,41.419231],"type":"Point"}
}