{
  "type": "Feature",
  "properties": {
    "iso:country":"US",
    "sg:address":"2129 E 65th St",
    "sg:city":"Brooklyn",
    "sg:classifiers":[
        {
            "category":"Retail",
            "subcategory":"Repair Shop",
            "type":"Services"
        }
    ],
    "sg:phone":"+1 718 444 9066",
    "sg:postcode":"11234",
    "sg:province":"NY",
    "sg:tags":[
        "lock",
        "locksmith"
    ],
    "wof:name":"Olympic Locksmiths",
    "wof:placetype":"venue"
},
  "geometry": {"coordinates":[-73.91022,40.615749],"type":"Point"}
}