{
  "type": "Feature",
  "properties": {
    "addr:full":"1661 S Ivy Trl Baldwinsville NY 13027",
    "addr:housenumber":"1661",
    "addr:postcode":"13027",
    "addr:street":"S Ivy Trl",
    "iso:country":"US",
    "sg:address":"1661 S Ivy Trl",
    "sg:city":"Baldwinsville",
    "sg:classifiers":[
        {
            "category":"Real Estate",
            "subcategory":"Real Estate Agent",
            "type":"Services"
        }
    ],
    "sg:phone":"+1 315 638 3353",
    "sg:postcode":"13027",
    "sg:province":"NY",
    "wof:name":"Falcone Enterprises",
    "wof:placetype":"venue"
},
  "geometry": {"coordinates":[-76.390762,43.163872],"type":"Point"}
}