{
  "type": "Feature",
  "properties": {
    "iso:country":"US",
    "sg:address":"23 Circle Dr",
    "sg:city":"Cortland",
    "sg:classifiers":[
        {
            "category":"Real Estate",
            "subcategory":"Real Estate Agent",
            "type":"Services"
        }
    ],
    "sg:phone":"+1 607 756 2570",
    "sg:postcode":"13045",
    "sg:province":"NY",
    "wof:name":"Tupper Real Estate",
    "wof:placetype":"venue"
},
  "geometry": {"coordinates":[-76.1983,42.601384],"type":"Point"}
}