{
  "type": "Feature",
  "properties": {
    "addr:full":"12 Parkfield Rd Scarsdale NY 10583",
    "addr:housenumber":"12",
    "addr:postcode":"10583",
    "addr:street":"Parkfield Rd",
    "iso:country":"US",
    "sg:address":"12 Parkfield Rd",
    "sg:city":"Scarsdale",
    "sg:classifiers":[
        {
            "category":"Social Services",
            "type":"Services"
        },
        {
            "category":"Professional",
            "subcategory":"Employment Agencies",
            "type":"Services"
        }
    ],
    "sg:phone":"+1 914 723 4582",
    "sg:postcode":"10583",
    "sg:province":"NY",
    "sg:tags":[
        "workers'",
        "placement",
        "volunteer"
    ],
    "wof:name":"Kass Family Foundation Inc",
    "wof:placetype":"venue"
},
  "geometry": {"coordinates":[-73.799581,41.003744],"type":"Point"}
}