{
  "type": "Feature",
  "properties": {
    "iso:country":"US",
    "sg:address":"26 Broadway",
    "sg:city":"New York",
    "sg:classifiers":[
        {
            "category":"Health Services",
            "subcategory":"Optometrist",
            "type":"Services"
        }
    ],
    "sg:phone":"+1 212 590 1983",
    "sg:postcode":"10004",
    "sg:province":"NY",
    "wof:name":"Total Optometric Eyecare Associates",
    "wof:placetype":"venue"
},
  "geometry": {"coordinates":[-74.013122,40.704986],"type":"Point"}
}