{
  "type": "Feature",
  "properties": {
    "iso:country":"US",
    "sg:address":"921 Port Washington Blvd",
    "sg:city":"Port Washington",
    "sg:classifiers":[
        {
            "category":"Social Services",
            "type":"Services"
        }
    ],
    "sg:phone":"+1 516 883 6468",
    "sg:postcode":"11050",
    "sg:province":"NY",
    "sg:tags":[
        "counselor",
        "marriage",
        "family"
    ],
    "wof:name":"Berman & Berman",
    "wof:placetype":"venue"
},
  "geometry": {"coordinates":[-73.68380399999999,40.82949],"type":"Point"}
}