{
  "type": "Feature",
  "properties": {
    "addr:full":"149 Commack Rd Ste A Commack NY 11725",
    "addr:housenumber":"149",
    "addr:postcode":"11725",
    "addr:street":"Commack Rd Ste A",
    "iso:country":"US",
    "sg:address":"149 Commack Rd Ste A",
    "sg:city":"Commack",
    "sg:classifiers":[
        {
            "category":"Health Services",
            "subcategory":"Doctor",
            "type":"Services"
        }
    ],
    "sg:phone":"+1 631 462 2200",
    "sg:postcode":"11725",
    "sg:province":"NY",
    "wof:name":"Condon Edward MD",
    "wof:placetype":"venue"
},
  "geometry": {"coordinates":[-73.29455900000001,40.839039],"type":"Point"}
}