{
  "type": "Feature",
  "properties": {
    "addr:full":"11502 Liberty Avenue Jamaica NY 11419",
    "addr:housenumber":"11502",
    "addr:postcode":"11419",
    "addr:street":"Liberty Avenue",
    "iso:country":"US",
    "sg:address":"11502 Liberty Avenue",
    "sg:city":"Jamaica",
    "sg:classifiers":[
        {
            "category":"Shopping",
            "subcategory":"Pharmacy",
            "type":"Retail Goods"
        }
    ],
    "sg:phone":"+1 718 529 5500",
    "sg:postcode":"11419",
    "sg:province":"NY",
    "sg:tags":[
        "drugstore"
    ],
    "wof:name":"Master Compounding Pharmacy",
    "wof:placetype":"venue"
},
  "geometry": {"coordinates":[-73.827607,40.685645],"type":"Point"}
}