{
  "type": "Feature",
  "properties": {
    "addr:full":"3118 Fulton St Brooklyn NY 11208",
    "addr:housenumber":"3118",
    "addr:postcode":"11208",
    "addr:street":"Fulton St",
    "iso:country":"US",
    "sg:address":"3118 Fulton St",
    "sg:city":"Brooklyn",
    "sg:classifiers":[
        {
            "category":"Shopping",
            "subcategory":"Discount & Variety Stores",
            "type":"Retail Goods"
        }
    ],
    "sg:phone":"+1   ",
    "sg:postcode":"11208",
    "sg:province":"NY",
    "wof:name":"Fulton Bargain Center Inc",
    "wof:placetype":"venue"
},
  "geometry": {"coordinates":[-73.879334,40.681514],"type":"Point"}
}