{
  "type": "Feature",
  "properties": {
    "addr:full":"214 Lehrer Ave Elmont NY 11003",
    "addr:housenumber":"214",
    "addr:postcode":"11003",
    "addr:street":"Lehrer Ave",
    "iso:country":"US",
    "sg:address":"214 Lehrer Ave",
    "sg:city":"Elmont",
    "sg:classifiers":[
        {
            "category":"Building & Trades",
            "subcategory":"Construction",
            "type":"Services"
        }
    ],
    "sg:phone":"+1 516 437 4247",
    "sg:postcode":"11003",
    "sg:province":"NY",
    "sg:tags":[
        "painting",
        "painter",
        "contractor"
    ],
    "wof:name":"National Painting Co",
    "wof:placetype":"venue"
},
  "geometry": {"coordinates":[-73.696787,40.702868],"type":"Point"}
}