{
  "type": "Feature",
  "properties": {
    "addr:full":"845 Lexington Avenue New York NY 10021",
    "addr:housenumber":"845",
    "addr:postcode":"10021",
    "addr:street":"Lexington Avenue",
    "iso:country":"US",
    "sg:address":"845 Lexington Avenue",
    "sg:city":"New York",
    "sg:classifiers":[
        {
            "category":"Building & Trades",
            "subcategory":"Construction",
            "type":"Services"
        }
    ],
    "sg:phone":"+1 917 432 0310",
    "sg:postcode":"10021",
    "sg:province":"NY",
    "sg:tags":[
        "contractor"
    ],
    "wof:name":"Reiken Construction Management",
    "wof:placetype":"venue"
},
  "geometry": {"coordinates":[-73.965808,40.765434],"type":"Point"}
}