{
  "type": "Feature",
  "properties": {
    "addr:full":"1 Suffolk Sq Central Islip NY 11749",
    "addr:housenumber":"1",
    "addr:postcode":"11749",
    "addr:street":"Suffolk Sq",
    "iso:country":"US",
    "sg:address":"1 Suffolk Sq",
    "sg:city":"Central Islip",
    "sg:classifiers":[
        {
            "category":"Professional",
            "subcategory":"Lawyer & Legal Services",
            "type":"Services"
        }
    ],
    "sg:phone":"+1 631 234 1154",
    "sg:postcode":"11749",
    "sg:province":"NY",
    "wof:name":"Mishkin Scott Michael PC",
    "wof:placetype":"venue"
},
  "geometry": {"coordinates":[-73.200746,40.790648],"type":"Point"}
}