{
  "type": "Feature",
  "properties": {
    "addr:full":"90-10 Grand Central Pkwy New York NY 10013",
    "addr:housenumber":"90-10",
    "addr:postcode":"10013",
    "addr:street":"Grand Central Pkwy",
    "iso:country":"US",
    "sg:address":"90-10 Grand Central Pkwy",
    "sg:city":"New York",
    "sg:classifiers":[
        {
            "category":"Airline",
            "type":"Transportation"
        }
    ],
    "sg:phone":"+1 212 651 5454",
    "sg:postcode":"10013",
    "sg:province":"NY",
    "sg:tags":[
        "airport"
    ],
    "wof:name":"Airesearch Aviation Co",
    "wof:placetype":"venue"
},
  "geometry": {"coordinates":[-73.834873,40.719304],"type":"Point"}
}