{
  "type": "Feature",
  "properties": {
    "iso:country":"US",
    "sg:address":"1402 Co Rd 28",
    "sg:city":"Lisbon",
    "sg:classifiers":[
        {
            "category":"Farming",
            "subcategory":"Dairy Farm",
            "type":"Manufacturing & Wholesale Goods"
        }
    ],
    "sg:phone":"+1 315 393 3675",
    "sg:postcode":"13658",
    "sg:province":"NY",
    "wof:name":"Fletcher Farms",
    "wof:placetype":"venue"
},
  "geometry": {"coordinates":[-75.301146,44.766383],"type":"Point"}
}