{
  "type": "Feature",
  "properties": {
    "iso:country":"US",
    "sg:address":"111 N Wellwood Ave",
    "sg:city":"Lindenhurst",
    "sg:classifiers":[
        {
            "category":"Bars & Pubs",
            "type":"Food & Drink"
        }
    ],
    "sg:phone":"+1   ",
    "sg:postcode":"11757",
    "sg:province":"NY",
    "sg:tags":[
        "drinking"
    ],
    "wof:name":"Frank & Irene",
    "wof:placetype":"venue"
},
  "geometry": {"coordinates":[-73.37427099999999,40.687467],"type":"Point"}
}