{
  "type": "Feature",
  "properties": {
    "addr:full":"7118 Kissena Boulevard Flushing NY 11367",
    "addr:housenumber":"7118",
    "addr:postcode":"11367",
    "addr:street":"Kissena Boulevard",
    "iso:country":"US",
    "sg:address":"7118 Kissena Boulevard",
    "sg:city":"Flushing",
    "sg:classifiers":[
        {
            "category":"Shopping",
            "subcategory":"Pharmacy",
            "type":"Retail Goods"
        }
    ],
    "sg:phone":"+1 718 793 3400",
    "sg:postcode":"11367",
    "sg:province":"NY",
    "sg:tags":[
        "drugstore"
    ],
    "wof:name":"Rite Aid Pharmacies",
    "wof:placetype":"venue"
},
  "geometry": {"coordinates":[-73.815352,40.729119],"type":"Point"}
}