{
  "type": "Feature",
  "properties": {
    "iso:country":"US",
    "sg:address":"868 Coney Island Ave",
    "sg:city":"Brooklyn",
    "sg:classifiers":[
        {
            "category":"Insurance",
            "subcategory":"Insurance Agent",
            "type":"Services"
        }
    ],
    "sg:phone":"+1 718 940 0000",
    "sg:postcode":"11218",
    "sg:province":"NY",
    "wof:name":"Raja Insurance Agency",
    "wof:placetype":"venue"
},
  "geometry": {"coordinates":[-73.967776,40.635563],"type":"Point"}
}