{
  "type": "Feature",
  "properties": {
    "iso:country":"US",
    "sg:address":"410 Bolt Rd",
    "sg:city":"Scotia",
    "sg:classifiers":[
        {
            "category":"Building & Trades",
            "subcategory":"Construction",
            "type":"Services"
        }
    ],
    "sg:phone":"+1 518 384 3347",
    "sg:postcode":"12302",
    "sg:province":"NY",
    "sg:tags":[
        "contractor",
        "painter",
        "hanging"
    ],
    "wof:name":"C & C Painting & Restoration",
    "wof:placetype":"venue"
},
  "geometry": {"coordinates":[-73.97902499999999,42.892489],"type":"Point"}
}