{
  "type": "Feature",
  "properties": {
    "iso:country":"US",
    "sg:address":"529 S Roberts Rd",
    "sg:city":"Dunkirk",
    "sg:classifiers":[
        {
            "category":"Transit Center",
            "subcategory":"Freight",
            "type":"Transportation"
        },
        {
            "category":"Freight",
            "type":"Transportation"
        }
    ],
    "sg:phone":"+1 716 366 3495",
    "sg:postcode":"14048",
    "sg:province":"NY",
    "sg:tags":[
        "trucking-motor",
        "trucking"
    ],
    "wof:name":"Kkg Inc",
    "wof:placetype":"venue"
},
  "geometry": {"coordinates":[-79.315944,42.484359],"type":"Point"}
}