{
  "type": "Feature",
  "properties": {
    "iso:country":"US",
    "sg:address":"375 Little East Neck Rd N",
    "sg:city":"West Babylon",
    "sg:classifiers":[
        {
            "category":"Personal",
            "subcategory":"Beauty Salon",
            "type":"Services"
        }
    ],
    "sg:phone":"+1 631 893 9393",
    "sg:postcode":"11704",
    "sg:province":"NY",
    "sg:tags":[
        "shop",
        "manicuring"
    ],
    "wof:name":"Village Nails & Spa",
    "wof:placetype":"venue"
},
  "geometry": {"coordinates":[-73.34358400000001,40.70356],"type":"Point"}
}