{
  "type": "Feature",
  "properties": {
    "addr:full":"12 W 12 St New York NY 10011",
    "addr:housenumber":"12",
    "addr:postcode":"10011",
    "addr:street":"W 12 St",
    "iso:country":"US",
    "sg:address":"12 W 12 St",
    "sg:city":"New York",
    "sg:classifiers":[
        {
            "category":"Social Services",
            "subcategory":"Child Care",
            "type":"Services"
        }
    ],
    "sg:phone":"+1 212 691 3432",
    "sg:postcode":"10011",
    "sg:province":"NY",
    "sg:tags":[
        "kindergarten",
        "academic",
        "school"
    ],
    "sg:website":"www.fpcns.org",
    "wof:name":"First Presbyterian Nursery",
    "wof:placetype":"venue"
},
  "geometry": {"coordinates":[-73.997587,40.735825],"type":"Point"}
}