{
  "type": "Feature",
  "properties": {
    "addr:full":"380 2nd Ave Rm 306 New York NY 10010",
    "addr:housenumber":"380;306",
    "addr:postcode":"10010",
    "addr:street":"2Nd Ave Rm",
    "iso:country":"US",
    "sg:address":"380 2nd Ave Rm 306",
    "sg:city":"New York",
    "sg:classifiers":[
        {
            "category":"Health Services",
            "subcategory":"Doctor",
            "type":"Services"
        }
    ],
    "sg:phone":"+1 212 375 1438",
    "sg:postcode":"10010",
    "sg:province":"NY",
    "wof:name":"Spine & Joint Services",
    "wof:placetype":"venue"
},
  "geometry": {"coordinates":[-73.981233,40.737129],"type":"Point"}
}