{
  "type": "Feature",
  "properties": {
    "addr:full":"1600 Linwood Ave Niagara Falls NY 14305",
    "addr:housenumber":"1600",
    "addr:postcode":"14305",
    "addr:street":"Linwood Ave",
    "iso:country":"US",
    "sg:address":"1600 Linwood Ave",
    "sg:city":"Niagara Falls",
    "sg:classifiers":[
        {
            "category":"Shopping",
            "subcategory":"Clothing, Apparel, & Fashions",
            "type":"Retail Goods"
        }
    ],
    "sg:phone":"+1   ",
    "sg:postcode":"14305",
    "sg:province":"NY",
    "wof:name":"Sasstique",
    "wof:placetype":"venue"
},
  "geometry": {"coordinates":[-79.041478,43.103525],"type":"Point"}
}