{
  "type": "Feature",
  "properties": {
    "addr:full":"144 Buckshollow Rd Mahopac NY 10541",
    "addr:housenumber":"144",
    "addr:postcode":"10541",
    "addr:street":"Buckshollow Rd",
    "iso:country":"US",
    "sg:address":"144 Buckshollow Rd",
    "sg:city":"Mahopac",
    "sg:classifiers":[
        {
            "category":"Personal",
            "subcategory":"Day Spa",
            "type":"Services"
        }
    ],
    "sg:phone":"+1 845 628 8888",
    "sg:postcode":"10541",
    "sg:province":"NY",
    "wof:name":"Mahopac Automobile Spa",
    "wof:placetype":"venue"
},
  "geometry": {"coordinates":[-73.744364,41.361581],"type":"Point"}
}