{
  "type": "Feature",
  "properties": {
    "addr:full":"1370 Broadway Rm 503 New York NY 10018",
    "addr:housenumber":"1370;503",
    "addr:postcode":"10018",
    "addr:street":"Broadway Rm",
    "iso:country":"US",
    "sg:address":"1370 Broadway Rm 503",
    "sg:city":"New York",
    "sg:classifiers":[
        {
            "category":"Shopping",
            "subcategory":"Stationery & Office Supplies",
            "type":"Retail Goods"
        }
    ],
    "sg:phone":"+1 212 402 2650",
    "sg:postcode":"10018",
    "sg:province":"NY",
    "sg:tags":[
        "equipment"
    ],
    "wof:name":"Digital Products Inc",
    "wof:placetype":"venue"
},
  "geometry": {"coordinates":[-73.987313,40.752131],"type":"Point"}
}