{
  "type": "Feature",
  "properties": {
    "iso:country":"US",
    "sg:address":"203 Parkside Ave",
    "sg:city":"Brooklyn",
    "sg:classifiers":[
        {
            "category":"Retail",
            "subcategory":"Self-service Laundry",
            "type":"Services"
        }
    ],
    "sg:phone":"+1 718 703 1170",
    "sg:postcode":"11226",
    "sg:province":"NY",
    "wof:name":"Colors & Suds Inc",
    "wof:placetype":"venue"
},
  "geometry": {"coordinates":[-73.961431,40.655046],"type":"Point"}
}