{
  "type": "Feature",
  "properties": {
    "iso:country":"US",
    "sg:address":"25 W 51st St Frnt 4",
    "sg:city":"New York",
    "sg:classifiers":[
        {
            "category":"Banks & Credit Unions",
            "subcategory":"Bank",
            "type":"Services"
        },
        {
            "category":"Banks & Credit Unions",
            "subcategory":"Financial Services",
            "type":"Services"
        }
    ],
    "sg:phone":"+1 212 586 0830",
    "sg:postcode":"10019",
    "sg:province":"NY",
    "sg:tags":[
        "broker",
        "mortgage"
    ],
    "sg:website":"www.bankofamerica.com",
    "wof:name":"Bank of America",
    "wof:placetype":"venue"
},
  "geometry": {"coordinates":[-73.97932400000001,40.760419],"type":"Point"}
}