{
  "type": "Feature",
  "properties": {
    "addr:full":"2233 Nostrand Ave Brooklyn NY 11210",
    "addr:housenumber":"2233",
    "addr:postcode":"11210",
    "addr:street":"Nostrand Ave",
    "iso:country":"US",
    "sg:address":"2233 Nostrand Ave",
    "sg:city":"Brooklyn",
    "sg:classifiers":[
        {
            "category":"Health Services",
            "subcategory":"Doctor",
            "type":"Services"
        }
    ],
    "sg:phone":"+1 718 258 3777",
    "sg:postcode":"11210",
    "sg:province":"NY",
    "wof:name":"Petrosova Inna",
    "wof:placetype":"venue"
},
  "geometry": {"coordinates":[-73.947231,40.630175],"type":"Point"}
}