{
  "type": "Feature",
  "properties": {
    "iso:country":"US",
    "sg:address":"786 Burrell Rd",
    "sg:city":"Little Falls",
    "sg:classifiers":[
        {
            "category":"Farming",
            "subcategory":"Farm",
            "type":"Manufacturing & Wholesale Goods"
        }
    ],
    "sg:phone":"+1 315 823 1656",
    "sg:postcode":"13365",
    "sg:province":"NY",
    "sg:tags":[
        "crop",
        "general"
    ],
    "wof:name":"Keiper Farm",
    "wof:placetype":"venue"
},
  "geometry": {"coordinates":[-74.848709,43.090353],"type":"Point"}
}