{
  "type": "Feature",
  "properties": {
    "addr:full":"420 Highland Ave Exd Middletown NY 10940",
    "addr:housenumber":"420",
    "addr:postcode":"10940",
    "addr:street":"Highland Ave Exd",
    "iso:country":"US",
    "sg:address":"420 Highland Ave Exd",
    "sg:city":"Middletown",
    "sg:classifiers":[
        {
            "category":"Recreation",
            "subcategory":"Arcade",
            "type":"Entertainment"
        }
    ],
    "sg:phone":"+1 845 343 5466",
    "sg:postcode":"10940",
    "sg:province":"NY",
    "sg:tags":[
        "casino"
    ],
    "wof:name":"A First Class Limousine",
    "wof:placetype":"venue"
},
  "geometry": {"coordinates":[-74.403274,41.471926],"type":"Point"}
}