{
  "type": "Feature",
  "properties": {
    "iso:country":"US",
    "sg:address":"400 S 2nd St",
    "sg:city":"Brooklyn",
    "sg:classifiers":[
        {
            "category":"Manufacturing",
            "subcategory":"Apparel",
            "type":"Manufacturing & Wholesale Goods"
        }
    ],
    "sg:phone":"+1 718 218 7603",
    "sg:postcode":"11211",
    "sg:province":"NY",
    "sg:tags":[
        "sportswear"
    ],
    "wof:name":"Young Style Inc",
    "wof:placetype":"venue"
},
  "geometry": {"coordinates":[-73.951559,40.70942],"type":"Point"}
}