{
  "type": "Feature",
  "properties": {
    "addr:full":"184 State Hwy 48 Fulton NY 13069",
    "addr:housenumber":"184",
    "addr:postcode":"13069",
    "addr:street":"State Hwy 48",
    "iso:country":"US",
    "sg:address":"184 State Hwy 48",
    "sg:city":"Fulton",
    "sg:classifiers":[
        {
            "category":"Professional",
            "type":"Services"
        }
    ],
    "sg:phone":"+1   ",
    "sg:postcode":"13069",
    "sg:province":"NY",
    "wof:name":"County Line Choppers",
    "wof:placetype":"venue"
},
  "geometry": {"coordinates":[-76.42400499999999,43.327408],"type":"Point"}
}