{
  "type": "Feature",
  "properties": {
    "iso:country":"US",
    "sg:address":"25 Halstead Rise",
    "sg:city":"Fairport",
    "sg:classifiers":[
        {
            "category":"Wholesale",
            "subcategory":"Electrical",
            "type":"Manufacturing & Wholesale Goods"
        }
    ],
    "sg:phone":"+1 585 223 8337",
    "sg:postcode":"14450",
    "sg:province":"NY",
    "sg:tags":[
        "electronic"
    ],
    "wof:name":"James H Ross Assoc Inc",
    "wof:placetype":"venue"
},
  "geometry": {"coordinates":[-77.4281,43.066559],"type":"Point"}
}