{
  "type": "Feature",
  "properties": {
    "addr:full":"174 Court Street Cobble Hill NY 11201",
    "addr:housenumber":"174",
    "addr:postcode":"11201",
    "addr:street":"Court Street",
    "iso:country":"US",
    "sg:address":"174 Court Street",
    "sg:city":"Cobble Hill",
    "sg:classifiers":[
        {
            "category":"Shopping",
            "subcategory":"Clothing, Apparel, & Fashions",
            "type":"Retail Goods"
        }
    ],
    "sg:phone":"+1 718 923 5777",
    "sg:postcode":"11201",
    "sg:province":"NY",
    "wof:name":"Diane T",
    "wof:placetype":"venue"
},
  "geometry": {"coordinates":[-73.993324,40.688141],"type":"Point"}
}