{
  "type": "Feature",
  "properties": {
    "iso:country":"US",
    "sg:address":"434 Cherry Ln",
    "sg:city":"Lewiston",
    "sg:classifiers":[
        {
            "category":"Building & Trades",
            "subcategory":"Construction",
            "type":"Services"
        }
    ],
    "sg:phone":"+1 716 754 8511",
    "sg:postcode":"14092",
    "sg:province":"NY",
    "sg:tags":[
        "house"
    ],
    "wof:name":"Pasquale Construction Inc",
    "wof:placetype":"venue"
},
  "geometry": {"coordinates":[-79.044647,43.18588],"type":"Point"}
}