{
  "type": "Feature",
  "properties": {
    "iso:country":"US",
    "sg:address":"9413 63rd Drive",
    "sg:city":"Rego Park",
    "sg:classifiers":[
        {
            "category":"Building & Trades",
            "subcategory":"Locksmith",
            "type":"Services"
        }
    ],
    "sg:phone":"+1 718 785 4704",
    "sg:postcode":"11374",
    "sg:province":"NY",
    "sg:tags":[
        "key"
    ],
    "wof:name":"A and A Locksmith of Rego Park",
    "wof:placetype":"venue"
},
  "geometry": {"coordinates":[-73.86314900000001,40.729071],"type":"Point"}
}