{
  "type": "Feature",
  "properties": {
    "iso:country":"US",
    "sg:address":"1160 Co Rd 122",
    "sg:city":"Gloversville",
    "sg:classifiers":[
        {
            "category":"Building & Trades",
            "subcategory":"Construction",
            "type":"Services"
        }
    ],
    "sg:phone":"+1 518 725 6515",
    "sg:postcode":"12078",
    "sg:province":"NY",
    "sg:tags":[
        "residential"
    ],
    "wof:name":"Petrie Construction",
    "wof:placetype":"venue"
},
  "geometry": {"coordinates":[-74.339663,43.077531],"type":"Point"}
}