{
  "type": "Feature",
  "properties": {
    "iso:country":"US",
    "sg:address":"1460 E Henrietta Rd",
    "sg:city":"Rochester",
    "sg:classifiers":[
        {
            "category":"Shopping",
            "subcategory":"Bicycles & Sporting Goods",
            "type":"Retail Goods"
        }
    ],
    "sg:phone":"+1   ",
    "sg:postcode":"14623",
    "sg:province":"NY",
    "wof:name":"Jim Mays Pro Shop",
    "wof:placetype":"venue"
},
  "geometry": {"coordinates":[-77.610586,43.091408],"type":"Point"}
}