{
  "type": "Feature",
  "properties": {
    "addr:full":"26 Homestead Rd E Clinton NY 13323",
    "addr:housenumber":"26",
    "addr:postcode":"13323",
    "addr:street":"Homestead Rd E",
    "iso:country":"US",
    "sg:address":"26 Homestead Rd E",
    "sg:city":"Clinton",
    "sg:classifiers":[
        {
            "category":"Social Services",
            "subcategory":"Adult Care",
            "type":"Services"
        }
    ],
    "sg:phone":"+1 315 724 0854",
    "sg:postcode":"13323",
    "sg:province":"NY",
    "sg:tags":[
        "home",
        "group"
    ],
    "wof:name":"Rome DDSO",
    "wof:placetype":"venue"
},
  "geometry": {"coordinates":[-75.348493,43.088409],"type":"Point"}
}