{
  "type": "Feature",
  "properties": {
    "iso:country":"US",
    "sg:address":"4 Winans St",
    "sg:city":"Larchmont",
    "sg:classifiers":[
        {
            "category":"Building & Trades",
            "subcategory":"Plumbing",
            "type":"Services"
        }
    ],
    "sg:phone":"+1 914 834 1206",
    "sg:postcode":"10538",
    "sg:province":"NY",
    "sg:tags":[
        "plumbing",
        "contractor"
    ],
    "wof:name":"Larchmont Plumbing and Heating",
    "wof:placetype":"venue"
},
  "geometry": {"coordinates":[-73.762529,40.923645],"type":"Point"}
}