{
  "type": "Feature",
  "properties": {
    "addr:full":"20 Mary St Palatine Bridge NY 13428",
    "addr:housenumber":"20",
    "addr:postcode":"13428",
    "addr:street":"Mary St",
    "iso:country":"US",
    "sg:address":"20 Mary St",
    "sg:city":"Palatine Bridge",
    "sg:classifiers":[
        {
            "category":"Real Estate",
            "subcategory":"Real Estate Operator",
            "type":"Services"
        }
    ],
    "sg:phone":"+1 518 673 2498",
    "sg:postcode":"13428",
    "sg:province":"NY",
    "sg:tags":[
        "apartment"
    ],
    "wof:name":"Brooksideplace Apartments",
    "wof:placetype":"venue"
},
  "geometry": {"coordinates":[-74.588311,42.91537],"type":"Point"}
}