{
  "type": "Feature",
  "properties": {
    "addr:full":"717 Post Rd Scarsdale NY 10583",
    "addr:housenumber":"717",
    "addr:postcode":"10583",
    "addr:street":"Post Rd",
    "iso:country":"US",
    "sg:address":"717 Post Rd",
    "sg:city":"Scarsdale",
    "sg:classifiers":[
        {
            "category":"Professional",
            "subcategory":"Business Services",
            "type":"Services"
        }
    ],
    "sg:phone":"+1 914 723 2223",
    "sg:postcode":"10583",
    "sg:province":"NY",
    "sg:tags":[
        "packaging"
    ],
    "wof:name":"Pak Mail Ctr",
    "wof:placetype":"venue"
},
  "geometry": {"coordinates":[-73.806467,40.970405],"type":"Point"}
}