{
  "type": "Feature",
  "properties": {
    "addr:full":"1 Penn Plz New York NY 10119",
    "addr:housenumber":"1",
    "addr:postcode":"10119",
    "addr:street":"Penn Plz",
    "iso:country":"US",
    "sg:address":"1 Penn Plz",
    "sg:city":"New York",
    "sg:classifiers":[
        {
            "category":"Professional",
            "subcategory":"Lawyer & Legal Services",
            "type":"Services"
        }
    ],
    "sg:phone":"+1 212 643 6400",
    "sg:postcode":"10119",
    "sg:province":"NY",
    "wof:name":"Goldsmith Charles M",
    "wof:placetype":"venue"
},
  "geometry": {"coordinates":[-73.992104,40.751598],"type":"Point"}
}