{
  "type": "Feature",
  "properties": {
    "iso:country":"US",
    "sg:address":"8312 12th Ave",
    "sg:city":"Brooklyn",
    "sg:classifiers":[
        {
            "category":"Health Services",
            "subcategory":"Clinic",
            "type":"Services"
        }
    ],
    "sg:phone":"+1 718 745 7552",
    "sg:postcode":"11228",
    "sg:province":"NY",
    "sg:tags":[
        "counseling",
        "mental"
    ],
    "sg:website":"www.albanofischetti.com",
    "wof:name":"Albano-Fischetti Consultation Center",
    "wof:placetype":"venue"
},
  "geometry": {"coordinates":[-74.014702,40.616901],"type":"Point"}
}