{
  "type": "Feature",
  "properties": {
    "iso:country":"US",
    "sg:address":"255 Glenville Rd",
    "sg:city":"Greenwich",
    "sg:classifiers":[
        {
            "category":"Professional",
            "subcategory":"Art Services",
            "type":"Services"
        }
    ],
    "sg:phone":"+1 203 532 9500",
    "sg:postcode":"06831",
    "sg:province":"NY",
    "sg:tags":[
        "graphic",
        "designer"
    ],
    "wof:name":"Wordgraphics",
    "wof:placetype":"venue"
},
  "geometry": {"coordinates":[-73.66449799999999,41.038385],"type":"Point"}
}