{
  "type": "Feature",
  "properties": {
    "iso:country":"US",
    "sg:address":"100 Lauman Ln",
    "sg:city":"Hicksville",
    "sg:classifiers":[
        {
            "category":"Manufacturing",
            "subcategory":"Glass & Minerals",
            "type":"Manufacturing & Wholesale Goods"
        }
    ],
    "sg:phone":"+1 516 827 5801",
    "sg:postcode":"11801",
    "sg:province":"NY",
    "sg:tags":[
        "granite",
        "product"
    ],
    "wof:name":"Stone Edge Marble & Granite",
    "wof:placetype":"venue"
},
  "geometry": {"coordinates":[-73.501555,40.743681],"type":"Point"}
}