{
  "type": "Feature",
  "properties": {
    "iso:country":"US",
    "sg:address":"56 Lucas Ave",
    "sg:city":"Kingston",
    "sg:classifiers":[
        {
            "category":"Health Services",
            "subcategory":"Doctor",
            "type":"Services"
        }
    ],
    "sg:phone":"+1 845 339 1619",
    "sg:postcode":"12401",
    "sg:province":"NY",
    "sg:tags":[
        "dentist"
    ],
    "wof:name":"Maureen K Viglielmo DDS",
    "wof:placetype":"venue"
},
  "geometry": {"coordinates":[-74.024537,41.932968],"type":"Point"}
}