{
  "type": "Feature",
  "properties": {
    "addr:full":"513 Lagrange St Vestal NY 13850",
    "addr:housenumber":"513",
    "addr:postcode":"13850",
    "addr:street":"Lagrange St",
    "iso:country":"US",
    "sg:address":"513 Lagrange St",
    "sg:city":"Vestal",
    "sg:classifiers":[
        {
            "category":"Bars & Pubs",
            "type":"Food & Drink"
        }
    ],
    "sg:phone":"+1   ",
    "sg:postcode":"13850",
    "sg:province":"NY",
    "sg:tags":[
        "drinking"
    ],
    "wof:name":"Terrys Tavern Inc",
    "wof:placetype":"venue"
},
  "geometry": {"coordinates":[-76.044724,42.08212],"type":"Point"}
}