{
  "type": "Feature",
  "properties": {
    "addr:full":"4 Farment Dr Fairport NY 14450",
    "addr:housenumber":"4",
    "addr:postcode":"14450",
    "addr:street":"Farment Dr",
    "iso:country":"US",
    "sg:address":"4 Farment Dr",
    "sg:city":"Fairport",
    "sg:classifiers":[
        {
            "category":"Building & Trades",
            "subcategory":"Plumbing",
            "type":"Services"
        }
    ],
    "sg:phone":"+1 585 388 0331",
    "sg:postcode":"14450",
    "sg:province":"NY",
    "sg:tags":[
        "contractor"
    ],
    "wof:name":"Nguyen Manh Plumbing Contr",
    "wof:placetype":"venue"
},
  "geometry": {"coordinates":[-77.433537,43.112107],"type":"Point"}
}