{
  "type": "Feature",
  "properties": {
    "iso:country":"US",
    "sg:address":"53 School St",
    "sg:city":"Richville",
    "sg:classifiers":[
        {
            "category":"Insurance",
            "subcategory":"Insurance Agent",
            "type":"Services"
        }
    ],
    "sg:phone":"+1 315 287 9498",
    "sg:postcode":"13681",
    "sg:province":"NY",
    "wof:name":"Tompkins-Seneca-Tioga Workers",
    "wof:placetype":"venue"
},
  "geometry": {"coordinates":[-75.39684200000001,44.416433],"type":"Point"}
}