{
  "type": "Feature",
  "properties": {
    "addr:full":"217 E 10th St New York NY 10003",
    "addr:housenumber":"217",
    "addr:postcode":"10003",
    "addr:street":"E 10Th St",
    "iso:country":"US",
    "sg:address":"217 E 10th St",
    "sg:city":"New York",
    "sg:classifiers":[
        {
            "category":"Education",
            "subcategory":"Special Training",
            "type":"Public Place"
        }
    ],
    "sg:phone":"+1 212 777 3222",
    "sg:postcode":"10003",
    "sg:province":"NY",
    "sg:tags":[
        "tutoring"
    ],
    "sg:website":"finalcutproclasses.com",
    "wof:name":"Final Cut Pro Classes",
    "wof:placetype":"venue"
},
  "geometry": {"coordinates":[-73.985687,40.729579],"type":"Point"}
}