{
  "type": "Feature",
  "properties": {
    "addr:full":"190 Nassau Avenue Brooklyn NY 11222",
    "addr:housenumber":"190",
    "addr:postcode":"11222",
    "addr:street":"Nassau Avenue",
    "iso:country":"US",
    "sg:address":"190 Nassau Avenue",
    "sg:city":"Brooklyn",
    "sg:classifiers":[
        {
            "category":"Restaurant",
            "type":"Food & Drink"
        }
    ],
    "sg:phone":"+1 718 782 2700",
    "sg:postcode":"11222",
    "sg:province":"NY",
    "sg:tags":[
        "polish"
    ],
    "wof:name":"Northside Bakery",
    "wof:placetype":"venue"
},
  "geometry": {"coordinates":[-73.945572,40.725315],"type":"Point"}
}