{
  "type": "Feature",
  "properties": {
    "iso:country":"US",
    "sg:address":"672 Central Ave",
    "sg:city":"Cedarhurst",
    "sg:classifiers":[
        {
            "category":"Deli",
            "type":"Food & Drink"
        }
    ],
    "sg:phone":"+1 516 295 2769",
    "sg:postcode":"11516",
    "sg:province":"NY",
    "wof:name":"Tamburino's Deli",
    "wof:placetype":"venue"
},
  "geometry": {"coordinates":[-73.7201,40.624199],"type":"Point"}
}