{
  "type": "Feature",
  "properties": {
    "addr:full":"1021 9th Ave Watervliet NY 12189",
    "addr:housenumber":"1021",
    "addr:postcode":"12189",
    "addr:street":"9Th Ave",
    "iso:country":"US",
    "sg:address":"1021 9th Ave",
    "sg:city":"Watervliet",
    "sg:classifiers":[
        {
            "category":"Organizations",
            "subcategory":"Community Association",
            "type":"Services"
        }
    ],
    "sg:phone":"+1   ",
    "sg:postcode":"12189",
    "sg:province":"NY",
    "wof:name":"Aoh",
    "wof:placetype":"venue"
},
  "geometry": {"coordinates":[-73.711978,42.721717],"type":"Point"}
}