{
  "type": "Feature",
  "properties": {
    "addr:full":"21 Washington St Castile NY 14427",
    "addr:housenumber":"21",
    "addr:postcode":"14427",
    "addr:street":"Washington St",
    "iso:country":"US",
    "sg:address":"21 Washington St",
    "sg:city":"Castile",
    "sg:classifiers":[
        {
            "category":"Professional",
            "subcategory":"Business Services",
            "type":"Services"
        }
    ],
    "sg:phone":"+1   ",
    "sg:postcode":"14427",
    "sg:province":"NY",
    "wof:name":"Classic Interiors",
    "wof:placetype":"venue"
},
  "geometry": {"coordinates":[-78.049404,42.634496],"type":"Point"}
}