{
  "type": "Feature",
  "properties": {
    "addr:full":"743 8 Ave New York NY 10036",
    "addr:housenumber":"743",
    "addr:postcode":"10036",
    "addr:street":"8 Ave",
    "iso:country":"US",
    "sg:address":"743 8 Ave",
    "sg:city":"New York",
    "sg:classifiers":[
        {
            "category":"Communications",
            "subcategory":"Film & Video Production",
            "type":"Services"
        }
    ],
    "sg:phone":"+1 212 245 9504",
    "sg:postcode":"10036",
    "sg:province":"NY",
    "sg:tags":[
        "motion",
        "picture"
    ],
    "wof:name":"Fazil Studios",
    "wof:placetype":"venue"
},
  "geometry": {"coordinates":[-73.989791,40.757234],"type":"Point"}
}