{
  "type": "Feature",
  "properties": {
    "addr:full":"4 Carondelet Dr Watervliet NY 12189",
    "addr:housenumber":"4",
    "addr:postcode":"12189",
    "addr:street":"Carondelet Dr",
    "iso:country":"US",
    "sg:address":"4 Carondelet Dr",
    "sg:city":"Watervliet",
    "sg:classifiers":[
        {
            "category":"Health Services",
            "subcategory":"Nursing And Care Facility",
            "type":"Services"
        }
    ],
    "sg:phone":"+1 518 785 0050",
    "sg:postcode":"12189",
    "sg:province":"NY",
    "sg:tags":[
        "home",
        "retirement",
        "community"
    ],
    "wof:name":"Cabrini Acres Senior Apartment",
    "wof:placetype":"venue"
},
  "geometry": {"coordinates":[-73.7337,42.733143],"type":"Point"}
}