{
  "type": "Feature",
  "properties": {
    "addr:full":"4188 Austin Blvd Island Park NY 11558",
    "addr:housenumber":"4188",
    "addr:postcode":"11558",
    "addr:street":"Austin Blvd;Park",
    "iso:country":"US",
    "sg:address":"4188 Austin Blvd",
    "sg:city":"Island Park",
    "sg:classifiers":[
        {
            "category":"Autos & Motor Vehicles",
            "subcategory":"Auto Supplies",
            "type":"Retail Goods"
        }
    ],
    "sg:phone":"+1 516 889 1375",
    "sg:postcode":"11558",
    "sg:province":"NY",
    "sg:tags":[
        "equipment",
        "racing",
        "car",
        "automobile"
    ],
    "wof:name":"Mean Street Custom Automotive",
    "wof:placetype":"venue"
},
  "geometry": {"coordinates":[-73.648473,40.607089],"type":"Point"}
}