{
  "type": "Feature",
  "properties": {
    "iso:country":"US",
    "sg:address":"898 Rte 109",
    "sg:city":"Lindenhurst",
    "sg:classifiers":[
        {
            "category":"Building & Trades",
            "subcategory":"Construction",
            "type":"Services"
        }
    ],
    "sg:phone":"+1 631 956 6105",
    "sg:postcode":"11757",
    "sg:province":"NY",
    "sg:tags":[
        "maintenance",
        "contractor"
    ],
    "wof:name":"All Phases Of Maintenance",
    "wof:placetype":"venue"
},
  "geometry": {"coordinates":[-73.388237,40.715114],"type":"Point"}
}