{
  "type": "Feature",
  "properties": {
    "addr:full":"1698 Lyell Ave Rochester NY 14606",
    "addr:housenumber":"1698",
    "addr:postcode":"14606",
    "addr:street":"Lyell Ave",
    "iso:country":"US",
    "sg:address":"1698 Lyell Ave",
    "sg:city":"Rochester",
    "sg:classifiers":[
        {
            "category":"Professional",
            "subcategory":"Advertising",
            "type":"Services"
        }
    ],
    "sg:phone":"+1 585 254 8050",
    "sg:postcode":"14606",
    "sg:province":"NY",
    "sg:tags":[
        "mailing",
        "shipping"
    ],
    "wof:name":"UPS Freight Svc",
    "wof:placetype":"venue"
},
  "geometry": {"coordinates":[-77.671369,43.164772],"type":"Point"}
}