{
  "type": "Feature",
  "properties": {
    "addr:full":"825 Fairport Rd East Rochester NY 14445",
    "addr:housenumber":"825",
    "addr:postcode":"14445",
    "addr:street":"Fairport Rd",
    "iso:country":"US",
    "sg:address":"825 Fairport Rd",
    "sg:city":"East Rochester",
    "sg:classifiers":[
        {
            "category":"Shopping",
            "type":"Retail Goods"
        }
    ],
    "sg:phone":"+1   ",
    "sg:postcode":"14445",
    "sg:province":"NY",
    "sg:tags":[
        "merchandise"
    ],
    "sg:website":"www.pettispools.com",
    "wof:name":"Pettis Pools & Patio",
    "wof:placetype":"venue"
},
  "geometry": {"coordinates":[-77.485708,43.103955],"type":"Point"}
}