{
  "type": "Feature",
  "properties": {
    "iso:country":"US",
    "sg:address":"3401 Erie Blvd E",
    "sg:city":"De Witt",
    "sg:classifiers":[
        {
            "category":"Personal",
            "subcategory":"Beauty Salon",
            "type":"Services"
        }
    ],
    "sg:phone":"+1 315 446 7710",
    "sg:postcode":"13214",
    "sg:province":"NY",
    "sg:tags":[
        "shop"
    ],
    "wof:name":"Continental Coiffures",
    "wof:placetype":"venue"
},
  "geometry": {"coordinates":[-76.06994400000001,43.047261],"type":"Point"}
}