{
  "type": "Feature",
  "properties": {
    "addr:full":"237 Willis Ave Bronx NY 10454",
    "addr:housenumber":"237",
    "addr:postcode":"10454",
    "addr:street":"Willis Ave",
    "iso:country":"US",
    "sg:address":"237 Willis Ave",
    "sg:city":"Bronx",
    "sg:classifiers":[
        {
            "category":"Restaurant",
            "type":"Food & Drink"
        }
    ],
    "sg:phone":"+1 718 292 9399",
    "sg:postcode":"10454",
    "sg:province":"NY",
    "sg:tags":[
        "mexican"
    ],
    "wof:name":"Santa Clarita",
    "wof:placetype":"venue"
},
  "geometry": {"coordinates":[-73.922873,40.809135],"type":"Point"}
}