{
  "type": "Feature",
  "properties": {
    "addr:full":"228 4th Ave Pelham NY 10803",
    "addr:housenumber":"228",
    "addr:postcode":"10803",
    "addr:street":"4Th Ave",
    "iso:country":"US",
    "sg:address":"228 4th Ave",
    "sg:city":"Pelham",
    "sg:classifiers":[
        {
            "category":"Insurance",
            "subcategory":"Life Insurance",
            "type":"Services"
        }
    ],
    "sg:phone":"+1 914 632 2369",
    "sg:postcode":"10803",
    "sg:province":"NY",
    "sg:tags":[
        "carrier"
    ],
    "wof:name":"Elder Dynamics Inc",
    "wof:placetype":"venue"
},
  "geometry": {"coordinates":[-73.808638,40.915102],"type":"Point"}
}