{
  "type": "Feature",
  "properties": {
    "addr:full":"215 E 79 St New York NY 10075",
    "addr:housenumber":"215;79",
    "addr:postcode":"10075",
    "addr:street":"E;St",
    "iso:country":"US",
    "sg:address":"215 E 79 St",
    "sg:city":"New York",
    "sg:classifiers":[
        {
            "category":"Health Services",
            "subcategory":"Doctor",
            "type":"Services"
        }
    ],
    "sg:phone":"+1 212 628 9249",
    "sg:postcode":"10075",
    "sg:province":"NY",
    "sg:tags":[
        "physician",
        "surgeon"
    ],
    "wof:name":"Judith Wenger MD PC",
    "wof:placetype":"venue"
},
  "geometry": {"coordinates":[-73.955527,40.773686],"type":"Point"}
}