{
  "type": "Feature",
  "properties": {
    "addr:full":"272 New Dorp Ln New York NY 10019",
    "addr:housenumber":"272",
    "addr:postcode":"10019",
    "addr:street":"New Dorp Ln",
    "iso:country":"US",
    "sg:address":"272 New Dorp Ln",
    "sg:city":"New York",
    "sg:classifiers":[
        {
            "category":"Arena",
            "subcategory":"Sports Club",
            "type":"Entertainment"
        }
    ],
    "sg:phone":"+1 718 979 5400",
    "sg:postcode":"10019",
    "sg:province":"NY",
    "sg:tags":[
        "martial art"
    ],
    "wof:name":"Dragon Kim's Karate USA",
    "wof:placetype":"venue"
},
  "geometry": {"coordinates":[-73.985901,40.765499],"type":"Point"}
}