{
  "type": "Feature",
  "properties": {
    "iso:country":"US",
    "sg:address":"1466 Altamont Ave",
    "sg:city":"Schenectady",
    "sg:classifiers":[
        {
            "category":"Health Services",
            "subcategory":"Doctor",
            "type":"Services"
        }
    ],
    "sg:phone":"+1 518 355 3303",
    "sg:postcode":"12303",
    "sg:province":"NY",
    "sg:tags":[
        "dentist"
    ],
    "wof:name":"Allen Shawn",
    "wof:placetype":"venue"
},
  "geometry": {"coordinates":[-73.94457800000001,42.785295],"type":"Point"}
}