{
  "type": "Feature",
  "properties": {
    "addr:full":"1780 Hylan Blvd Staten Island NY 10305",
    "addr:housenumber":"1780",
    "addr:postcode":"10305",
    "addr:street":"Hylan Blvd",
    "iso:country":"US",
    "sg:address":"1780 Hylan Blvd",
    "sg:city":"Staten Island",
    "sg:classifiers":[
        {
            "category":"Restaurant",
            "type":"Food & Drink"
        }
    ],
    "sg:phone":"+1   ",
    "sg:postcode":"10305",
    "sg:province":"NY",
    "sg:tags":[
        "eating"
    ],
    "wof:name":"Altieri Catering",
    "wof:placetype":"venue"
},
  "geometry": {"coordinates":[-74.093087,40.585497],"type":"Point"}
}