{
  "type": "Feature",
  "properties": {
    "iso:country":"US",
    "sg:address":"2915 Old Rte 9w",
    "sg:city":"New Windsor",
    "sg:classifiers":[
        {
            "category":"Restaurant",
            "type":"Food & Drink"
        }
    ],
    "sg:phone":"+1 845 565 9353",
    "sg:postcode":"12553",
    "sg:province":"NY",
    "sg:tags":[
        "delicatessen"
    ],
    "wof:name":"Maio's Delicatessen",
    "wof:placetype":"venue"
},
  "geometry": {"coordinates":[-74.016125,41.472095],"type":"Point"}
}