{
  "type": "Feature",
  "properties": {
    "iso:country":"US",
    "sg:address":"2714 E 19th St",
    "sg:city":"Brooklyn",
    "sg:classifiers":[
        {
            "category":"Utilities",
            "subcategory":"Telephone",
            "type":"Services"
        }
    ],
    "sg:phone":"+1   ",
    "sg:postcode":"11235",
    "sg:province":"NY",
    "sg:tags":[
        "communication"
    ],
    "wof:name":"Apollo Communications LLC",
    "wof:placetype":"venue"
},
  "geometry": {"coordinates":[-73.949978,40.585093],"type":"Point"}
}