{
  "type": "Feature",
  "properties": {
    "addr:full":"409 Marcellus St Syracuse NY 13204",
    "addr:housenumber":"409",
    "addr:postcode":"13204",
    "addr:street":"Marcellus St",
    "iso:country":"US",
    "sg:address":"409 Marcellus St",
    "sg:city":"Syracuse",
    "sg:classifiers":[
        {
            "category":"Building & Trades",
            "subcategory":"Plumbing",
            "type":"Services"
        }
    ],
    "sg:phone":"+1 315 475 1123",
    "sg:postcode":"13204",
    "sg:province":"NY",
    "sg:tags":[
        "boiler",
        "cleaning"
    ],
    "wof:name":"Mack Brothers Boiler & Sheet",
    "wof:placetype":"venue"
},
  "geometry": {"coordinates":[-76.1651,43.046105],"type":"Point"}
}