{
  "type": "Feature",
  "properties": {
    "addr:full":"1322 Hyde Park Blvd Niagara Falls NY 14301",
    "addr:housenumber":"1322",
    "addr:postcode":"14301",
    "addr:street":"Hyde Park Blvd",
    "iso:country":"US",
    "sg:address":"1322 Hyde Park Blvd",
    "sg:city":"Niagara Falls",
    "sg:classifiers":[
        {
            "category":"Autos & Motor Vehicles",
            "subcategory":"Automobile Sales",
            "type":"Retail Goods"
        }
    ],
    "sg:phone":"+1 716 297 6189",
    "sg:postcode":"14301",
    "sg:province":"NY",
    "sg:tags":[
        "car",
        "dealer"
    ],
    "wof:name":"K W Cycle & Auto",
    "wof:placetype":"venue"
},
  "geometry": {"coordinates":[-79.02692,43.100918],"type":"Point"}
}