{
  "type": "Feature",
  "properties": {
    "addr:full":"46th St and 6th Ave New York NY 10036",
    "addr:postcode":"10036",
    "addr:street":"46Th St;6Th Ave",
    "iso:country":"US",
    "sg:address":"46th St and 6th Ave",
    "sg:city":"New York",
    "sg:classifiers":[
        {
            "category":"Food Court",
            "type":"Food & Drink"
        },
        {
            "category":"Restaurant",
            "type":"Food & Drink"
        }
    ],
    "sg:postcode":"10036",
    "sg:province":"NY",
    "sg:tags":[
        "pakistani",
        "indian",
        "stand"
    ],
    "wof:name":"Biryani Cart",
    "wof:placetype":"venue"
},
  "geometry": {"coordinates":[-73.982229,40.757382],"type":"Point"}
}