{
  "type": "Feature",
  "properties": {
    "addr:full":"147 Serrano Ave Hawthorne NY 10532",
    "addr:housenumber":"147",
    "addr:postcode":"10532",
    "addr:street":"Serrano Ave",
    "iso:country":"US",
    "sg:address":"147 Serrano Ave",
    "sg:city":"Hawthorne",
    "sg:classifiers":[
        {
            "category":"Professional",
            "subcategory":"Business Services",
            "type":"Services"
        },
        {
            "category":"Building & Trades",
            "subcategory":"Construction",
            "type":"Services"
        }
    ],
    "sg:phone":"+1 914 741 2879",
    "sg:postcode":"10532",
    "sg:province":"NY",
    "sg:tags":[
        "house",
        "general",
        "contractor"
    ],
    "wof:name":"Multi Maintenance",
    "wof:placetype":"venue"
},
  "geometry": {"coordinates":[-73.804503,41.10058],"type":"Point"}
}