{
  "type": "Feature",
  "properties": {
    "addr:full":"3418 Irwin Ave Bronx NY 10463",
    "addr:housenumber":"3418",
    "addr:postcode":"10463",
    "addr:street":"Irwin Ave",
    "iso:country":"US",
    "sg:address":"3418 Irwin Ave",
    "sg:city":"Bronx",
    "sg:classifiers":[
        {
            "category":"Building & Trades",
            "subcategory":"Construction",
            "type":"Services"
        }
    ],
    "sg:phone":"+1 718 601 7188",
    "sg:postcode":"10463",
    "sg:province":"NY",
    "sg:tags":[
        "resurfacing",
        "laying",
        "refinishing",
        "floor"
    ],
    "wof:name":"All Stone Floor Care",
    "wof:placetype":"venue"
},
  "geometry": {"coordinates":[-73.904785,40.885055],"type":"Point"}
}