{
  "type": "Feature",
  "properties": {
    "addr:full":"424 E 82nd Street New York NY 10028",
    "addr:housenumber":"424",
    "addr:postcode":"10028",
    "addr:street":"E 82Nd Street",
    "iso:country":"US",
    "sg:address":"424 E 82nd Street",
    "sg:city":"New York",
    "sg:classifiers":[
        {
            "category":"Retail",
            "subcategory":"Laundry & Dry Cleaning",
            "type":"Services"
        }
    ],
    "sg:phone":"+1 212 737 8450",
    "sg:postcode":"10028",
    "sg:province":"NY",
    "wof:name":"Crown Cleaners",
    "wof:placetype":"venue"
},
  "geometry": {"coordinates":[-73.950777,40.773933],"type":"Point"}
}