{
  "type": "Feature",
  "properties": {
    "iso:country":"US",
    "sg:address":"285 18th St",
    "sg:city":"Brooklyn",
    "sg:classifiers":[
        {
            "category":"Shopping",
            "subcategory":"Stationery & Office Supplies",
            "type":"Retail Goods"
        }
    ],
    "sg:phone":"+1 718 369 0131",
    "sg:postcode":"11215",
    "sg:province":"NY",
    "sg:tags":[
        "repairing",
        "pencil",
        "pen"
    ],
    "wof:name":"J J Pen Vending Co",
    "wof:placetype":"venue"
},
  "geometry": {"coordinates":[-73.99055300000001,40.662657],"type":"Point"}
}