{
  "type": "Feature",
  "properties": {
    "addr:full":"62 Jane St New York NY 10014",
    "addr:housenumber":"62",
    "addr:postcode":"10014",
    "addr:street":"Jane St",
    "iso:country":"US",
    "sg:address":"62 Jane St",
    "sg:city":"New York",
    "sg:classifiers":[
        {
            "category":"Professional",
            "type":"Services"
        }
    ],
    "sg:phone":"+1   ",
    "sg:postcode":"10014",
    "sg:province":"NY",
    "wof:name":"Harry Lorayne Inc",
    "wof:placetype":"venue"
},
  "geometry": {"coordinates":[-74.006137,40.738064],"type":"Point"}
}