{
  "type": "Feature",
  "properties": {
    "addr:full":"46 Van Wyck Rd Blauvelt NY 10913",
    "addr:housenumber":"46",
    "addr:postcode":"10913",
    "addr:street":"Van Wyck Rd",
    "iso:country":"US",
    "sg:address":"46 Van Wyck Rd",
    "sg:city":"Blauvelt",
    "sg:classifiers":[
        {
            "category":"Organizations",
            "subcategory":"Community Association",
            "type":"Services"
        }
    ],
    "sg:phone":"+1 845 359 9766",
    "sg:postcode":"10913",
    "sg:province":"NY",
    "sg:tags":[
        "fraternal"
    ],
    "wof:name":"Sons Of Italy",
    "wof:placetype":"venue"
},
  "geometry": {"coordinates":[-73.97081,41.05704],"type":"Point"}
}