{
  "type": "Feature",
  "properties": {
    "addr:full":"914 Atlantic Ave Baldwin NY 11510",
    "addr:housenumber":"914",
    "addr:postcode":"11510",
    "addr:street":"Atlantic Ave",
    "iso:country":"US",
    "sg:address":"914 Atlantic Ave",
    "sg:city":"Baldwin",
    "sg:classifiers":[
        {
            "category":"Health Services",
            "subcategory":"Health Practitioner",
            "type":"Services"
        }
    ],
    "sg:phone":"+1 516 705 5625",
    "sg:postcode":"11510",
    "sg:province":"NY",
    "sg:tags":[
        "psychologist"
    ],
    "wof:name":"Sleep Center",
    "wof:placetype":"venue"
},
  "geometry": {"coordinates":[-73.606506,40.639895],"type":"Point"}
}