{
  "type": "Feature",
  "properties": {
    "addr:full":"614 Stone Rd Rochester NY 14616",
    "addr:housenumber":"614",
    "addr:postcode":"14616",
    "addr:street":"Stone Rd",
    "iso:country":"US",
    "sg:address":"614 Stone Rd",
    "sg:city":"Rochester",
    "sg:classifiers":[
        {
            "category":"Food & Beverages",
            "subcategory":"Bakery",
            "type":"Retail Goods"
        }
    ],
    "sg:phone":"+1 585 663 7634",
    "sg:postcode":"14616",
    "sg:province":"NY",
    "sg:tags":[
        "baker"
    ],
    "wof:name":"Jackson's Bakery Inc",
    "wof:placetype":"venue"
},
  "geometry": {"coordinates":[-77.64196200000001,43.223177],"type":"Point"}
}