{
  "type": "Feature",
  "properties": {
    "addr:full":"4 Lyon Pl White Plains NY 10601",
    "addr:housenumber":"4",
    "addr:postcode":"10601",
    "addr:street":"Lyon Pl",
    "iso:country":"US",
    "sg:address":"4 Lyon Pl",
    "sg:city":"White Plains",
    "sg:classifiers":[
        {
            "category":"Personal",
            "subcategory":"Beauty Salon",
            "type":"Services"
        }
    ],
    "sg:phone":"+1   ",
    "sg:postcode":"10601",
    "sg:province":"NY",
    "sg:tags":[
        "shop"
    ],
    "wof:name":"Mane Illusion",
    "wof:placetype":"venue"
},
  "geometry": {"coordinates":[-73.76232400000001,41.029276],"type":"Point"}
}