{
  "type": "Feature",
  "properties": {
    "addr:full":"180 Mosel Ave Staten Island NY 10304",
    "addr:housenumber":"180",
    "addr:postcode":"10304",
    "addr:street":"Mosel Ave",
    "iso:country":"US",
    "sg:address":"180 Mosel Ave",
    "sg:city":"Staten Island",
    "sg:classifiers":[
        {
            "category":"Professional",
            "subcategory":"Computer Services",
            "type":"Services"
        }
    ],
    "sg:phone":"+1   ",
    "sg:postcode":"10304",
    "sg:province":"NY",
    "sg:tags":[
        "datum"
    ],
    "wof:name":"Linean LLC",
    "wof:placetype":"venue"
},
  "geometry": {"coordinates":[-74.078447,40.612457],"type":"Point"}
}