{
  "type": "Feature",
  "properties": {
    "addr:full":"10 Ave X Brooklyn NY 11223",
    "addr:postcode":"11223",
    "addr:street":"10 Ave X",
    "iso:country":"US",
    "sg:address":"10 Ave X",
    "sg:city":"Brooklyn",
    "sg:classifiers":[
        {
            "category":"Building & Trades",
            "subcategory":"Construction",
            "type":"Services"
        }
    ],
    "sg:phone":"+1 718 336 7960",
    "sg:postcode":"11223",
    "sg:province":"NY",
    "sg:tags":[
        "contractor"
    ],
    "wof:name":"Gravesend Contracting Corp",
    "wof:placetype":"venue"
},
  "geometry": {"coordinates":[-73.983074,40.589042],"type":"Point"}
}