{
  "type": "Feature",
  "properties": {
    "addr:full":"11 Oval Drive Islandia NY 10079",
    "addr:housenumber":"11",
    "addr:postcode":"10079",
    "addr:street":"Oval Drive",
    "iso:country":"US",
    "sg:address":"11 Oval Drive",
    "sg:city":"Islandia",
    "sg:classifiers":[
        {
            "category":"Banks & Credit Unions",
            "subcategory":"Bank",
            "type":"Services"
        }
    ],
    "sg:phone":"+1 888 882 3837",
    "sg:postcode":"10079",
    "sg:province":"NY",
    "sg:website":"www.everbank.com",
    "wof:name":"Everbank.com",
    "wof:placetype":"venue"
},
  "geometry": {"coordinates":[-73.189697,40.8041],"type":"Point"}
}