{
  "type": "Feature",
  "properties": {
    "iso:country":"US",
    "name:eng_x_preferred":[
        "Church Av"
    ],
    "wof:name":"Church Av Station",
    "wof:placetype":"venue"
},
  "geometry": {"coordinates":[-73.97967800000001,40.644041],"type":"Point"}
}