{
  "type": "Feature",
  "properties": {
    "addr:full":"831 Manhattan Ave Brooklyn NY 11222",
    "addr:housenumber":"831",
    "addr:postcode":"11222",
    "addr:street":"Manhattan Ave",
    "iso:country":"US",
    "sg:address":"831 Manhattan Ave",
    "sg:city":"Brooklyn",
    "sg:classifiers":[
        {
            "category":"Travel",
            "subcategory":"Travel Agent",
            "type":"Entertainment"
        }
    ],
    "sg:phone":"+1   ",
    "sg:postcode":"11222",
    "sg:province":"NY",
    "sg:tags":[
        "agency"
    ],
    "wof:name":"Greenpoint Travel",
    "wof:placetype":"venue"
},
  "geometry": {"coordinates":[-73.953513,40.728288],"type":"Point"}
}