{
  "type": "Feature",
  "properties": {
    "addr:full":"21925 Club House Dr Alexandria Bay NY 13640",
    "addr:housenumber":"21925",
    "addr:postcode":"13640",
    "addr:street":"Club House Dr",
    "iso:country":"US",
    "sg:address":"21925 Club House Dr",
    "sg:city":"Alexandria Bay",
    "sg:classifiers":[
        {
            "category":"Real Estate",
            "subcategory":"Developer",
            "type":"Services"
        }
    ],
    "sg:phone":"+1 315 482 5297",
    "sg:postcode":"13640",
    "sg:province":"NY",
    "wof:name":"Wellesley Island East",
    "wof:placetype":"venue"
},
  "geometry": {"coordinates":[-75.937091,44.34912],"type":"Point"}
}