{
  "type": "Feature",
  "properties": {
    "iso:country":"US",
    "sg:address":"13291 Henskee Rd",
    "sg:city":"Alden",
    "sg:classifiers":[
        {
            "category":"Insurance",
            "subcategory":"Insurance Agent",
            "type":"Services"
        }
    ],
    "sg:phone":"+1 716 937 7270",
    "sg:postcode":"14004",
    "sg:province":"NY",
    "wof:name":"Vic Wojnowski Insurance",
    "wof:placetype":"venue"
},
  "geometry": {"coordinates":[-78.479129,42.878229],"type":"Point"}
}