{
  "type": "Feature",
  "properties": {
    "addr:full":"33 Parkview Manor Cir Honeoye Falls NY 14472",
    "addr:housenumber":"33",
    "addr:postcode":"14472",
    "addr:street":"Parkview Manor Cir",
    "iso:country":"US",
    "sg:address":"33 Parkview Manor Cir",
    "sg:city":"Honeoye Falls",
    "sg:classifiers":[
        {
            "category":"Manufacturing",
            "subcategory":"Metals",
            "type":"Manufacturing & Wholesale Goods"
        }
    ],
    "sg:phone":"+1   ",
    "sg:postcode":"14472",
    "sg:province":"NY",
    "sg:tags":[
        "fabrication",
        "structural"
    ],
    "wof:name":"Great Lakes Wireless Talk",
    "wof:placetype":"venue"
},
  "geometry": {"coordinates":[-77.551722,43.00762],"type":"Point"}
}