{
  "type": "Feature",
  "properties": {
    "iso:country":"US",
    "sg:address":"315 E Seneca St",
    "sg:city":"Manlius",
    "sg:classifiers":[
        {
            "category":"Professional",
            "subcategory":"Business Services",
            "type":"Services"
        }
    ],
    "sg:phone":"+1 315 682 5840",
    "sg:postcode":"13104",
    "sg:province":"NY",
    "sg:tags":[
        "packaging"
    ],
    "wof:name":"Retail Details Inc",
    "wof:placetype":"venue"
},
  "geometry": {"coordinates":[-75.975928,43.002081],"type":"Point"}
}