{
  "type": "Feature",
  "properties": {
    "addr:full":"30 Governor Dr Newburgh NY 12550",
    "addr:housenumber":"30",
    "addr:postcode":"12550",
    "addr:street":"Governor Dr",
    "iso:country":"US",
    "sg:address":"30 Governor Dr",
    "sg:city":"Newburgh",
    "sg:classifiers":[
        {
            "category":"Restaurant",
            "type":"Food & Drink"
        }
    ],
    "sg:phone":"+1 845 567 2720",
    "sg:postcode":"12550",
    "sg:province":"NY",
    "sg:tags":[
        "shop",
        "coffee"
    ],
    "wof:name":"Sleepy Hollow Coffee Roasters",
    "wof:placetype":"venue"
},
  "geometry": {"coordinates":[-74.12070300000001,41.511365],"type":"Point"}
}