{
  "type": "Feature",
  "properties": {
    "iso:country":"US",
    "sg:address":"161 Fort Washington Ave",
    "sg:city":"New York",
    "sg:classifiers":[
        {
            "category":"Health Services",
            "subcategory":"Doctor",
            "type":"Services"
        }
    ],
    "sg:phone":"+1 212 694 5329",
    "sg:postcode":"10032",
    "sg:province":"NY",
    "wof:name":"Reilly Kevin B Md",
    "wof:placetype":"venue"
},
  "geometry": {"coordinates":[-73.943038,40.840713],"type":"Point"}
}