{
  "type": "Feature",
  "properties": {
    "addr:full":"5645 Main Street Flushing NY 11355",
    "addr:housenumber":"5645",
    "addr:postcode":"11355",
    "addr:street":"Main Street",
    "iso:country":"US",
    "sg:address":"5645 Main Street",
    "sg:city":"Flushing",
    "sg:classifiers":[
        {
            "category":"Sports & Exercise",
            "subcategory":"Gym",
            "type":"Entertainment"
        }
    ],
    "sg:phone":"+1 718 886 5916",
    "sg:postcode":"11355",
    "sg:province":"NY",
    "sg:tags":[
        "trainer"
    ],
    "wof:name":"Ny Presbyterian Healthcare",
    "wof:placetype":"venue"
},
  "geometry": {"coordinates":[-73.825987,40.747279],"type":"Point"}
}