{
  "type": "Feature",
  "properties": {
    "iso:country":"US",
    "sg:address":"2311 Ave Z",
    "sg:city":"Brooklyn",
    "sg:classifiers":[
        {
            "category":"Shopping",
            "subcategory":"Beauty & Cosmetics",
            "type":"Retail Goods"
        }
    ],
    "sg:phone":"+1   ",
    "sg:postcode":"11235",
    "sg:province":"NY",
    "sg:tags":[
        "merchandise"
    ],
    "wof:name":"Elisseeva Olga & N B Inc",
    "wof:placetype":"venue"
},
  "geometry": {"coordinates":[-73.945616,40.588997],"type":"Point"}
}