{
  "type": "Feature",
  "properties": {
    "addr:full":"319 Hooper St Brooklyn NY 11211",
    "addr:housenumber":"319",
    "addr:postcode":"11211",
    "addr:street":"Hooper St",
    "iso:country":"US",
    "sg:address":"319 Hooper St",
    "sg:city":"Brooklyn",
    "sg:classifiers":[
        {
            "category":"Health Services",
            "subcategory":"Doctor",
            "type":"Services"
        }
    ],
    "sg:phone":"+1 718 486 7116",
    "sg:postcode":"11211",
    "sg:province":"NY",
    "wof:name":"Bhatti Muhammed MD",
    "wof:placetype":"venue"
},
  "geometry": {"coordinates":[-73.9534,40.708199],"type":"Point"}
}