{
  "type": "Feature",
  "properties": {
    "iso:country":"US",
    "sg:address":"7062 Albro Rd",
    "sg:city":"Bliss",
    "sg:classifiers":[
        {
            "category":"Farming",
            "subcategory":"Dairy Farm",
            "type":"Manufacturing & Wholesale Goods"
        }
    ],
    "sg:phone":"+1 585 493 5460",
    "sg:postcode":"14024",
    "sg:province":"NY",
    "wof:name":"Dan Albro Farm",
    "wof:placetype":"venue"
},
  "geometry": {"coordinates":[-78.170287,42.556907],"type":"Point"}
}