{
  "type": "Feature",
  "properties": {
    "addr:full":"2905 Broadway New York NY 10025",
    "addr:housenumber":"2905",
    "addr:postcode":"10025",
    "addr:street":"Broadway",
    "iso:country":"US",
    "sg:address":"2905 Broadway",
    "sg:city":"New York",
    "sg:classifiers":[
        {
            "category":"Home & Garden",
            "subcategory":"Hardware",
            "type":"Retail Goods"
        },
        {
            "category":"Building & Trades",
            "subcategory":"Locksmith",
            "type":"Services"
        }
    ],
    "sg:phone":"+1 212 662 2150",
    "sg:postcode":"10025",
    "sg:province":"NY",
    "sg:tags":[
        "store",
        "key"
    ],
    "wof:name":"University Hardware",
    "wof:placetype":"venue"
},
  "geometry": {"coordinates":[-73.96534699999999,40.80642],"type":"Point"}
}