{
  "type": "Feature",
  "properties": {
    "iso:country":"US",
    "sg:address":"14 Bishop Ln",
    "sg:city":"Holbrook",
    "sg:classifiers":[
        {
            "category":"Building & Trades",
            "subcategory":"Landscaping Services",
            "type":"Services"
        }
    ],
    "sg:phone":"+1 631 563 7842",
    "sg:postcode":"11741",
    "sg:province":"NY",
    "wof:name":"Lcc Landscape",
    "wof:placetype":"venue"
},
  "geometry": {"coordinates":[-73.070943,40.782209],"type":"Point"}
}