{
  "type": "Feature",
  "properties": {
    "iso:country":"US",
    "sg:address":"1255 Grand Ave",
    "sg:city":"North Baldwin",
    "sg:classifiers":[
        {
            "category":"Restaurant",
            "type":"Food & Drink"
        }
    ],
    "sg:phone":"+1 516 546 4810",
    "sg:postcode":"11510",
    "sg:province":"NY",
    "wof:name":"McDonald's Restrnt",
    "wof:placetype":"venue"
},
  "geometry": {"coordinates":[-73.614799,40.681198],"type":"Point"}
}