{
  "type": "Feature",
  "properties": {
    "addr:full":"600 E 180th St Bronx NY 10457",
    "addr:housenumber":"600",
    "addr:postcode":"10457",
    "addr:street":"E 180Th St",
    "iso:country":"US",
    "sg:address":"600 E 180th St",
    "sg:city":"Bronx",
    "sg:classifiers":[
        {
            "category":"Food & Beverages",
            "subcategory":"Groceries & Convenience Stores",
            "type":"Retail Goods"
        }
    ],
    "sg:phone":"+1 718 367 2411",
    "sg:postcode":"10457",
    "sg:province":"NY",
    "sg:tags":[
        "grocer"
    ],
    "wof:name":"William Grocery Store",
    "wof:placetype":"venue"
},
  "geometry": {"coordinates":[-73.892325,40.849851],"type":"Point"}
}