{
  "type": "Feature",
  "properties": {
    "iso:country":"US",
    "sg:address":"6516 14th Avenue",
    "sg:city":"Brooklyn",
    "sg:classifiers":[
        {
            "category":"Cinema",
            "subcategory":"Movie Rental",
            "type":"Entertainment"
        }
    ],
    "sg:phone":"+1 718 236 8193",
    "sg:postcode":"11219",
    "sg:province":"NY",
    "sg:tags":[
        "game",
        "video"
    ],
    "wof:name":"New York Int'l Video",
    "wof:placetype":"venue"
},
  "geometry": {"coordinates":[-73.99980600000001,40.62438],"type":"Point"}
}