{
  "type": "Feature",
  "properties": {
    "addr:full":"18 W 45 St New York NY 10036",
    "addr:housenumber":"18",
    "addr:postcode":"10036",
    "addr:street":"W 45 St",
    "iso:country":"US",
    "sg:address":"18 W 45 St",
    "sg:city":"New York",
    "sg:classifiers":[
        {
            "category":"Professional",
            "subcategory":"Printing & Photocopies",
            "type":"Services"
        }
    ],
    "sg:phone":"+1 212 354 0400",
    "sg:postcode":"10036",
    "sg:province":"NY",
    "wof:name":"Kolcorp Industries Ltd",
    "wof:placetype":"venue"
},
  "geometry": {"coordinates":[-73.98233999999999,40.756478],"type":"Point"}
}