{
  "type": "Feature",
  "properties": {
    "iso:country":"US",
    "sg:address":"459 W 149th St",
    "sg:city":"New York",
    "sg:classifiers":[
        {
            "category":"Organizations",
            "subcategory":"Religious Organization",
            "type":"Services"
        }
    ],
    "sg:phone":"+1 212 926 5883",
    "sg:postcode":"10031",
    "sg:province":"NY",
    "sg:tags":[
        "clergy"
    ],
    "wof:name":"Eric A Joseph",
    "wof:placetype":"venue"
},
  "geometry": {"coordinates":[-73.945536,40.827745],"type":"Point"}
}