{
  "type": "Feature",
  "properties": {
    "addr:full":"1257 Castleton Avenue Staten Island NY 10310",
    "addr:housenumber":"1257",
    "addr:postcode":"10310",
    "addr:street":"Castleton Avenue",
    "iso:country":"US",
    "sg:address":"1257 Castleton Avenue",
    "sg:city":"Staten Island",
    "sg:classifiers":[
        {
            "category":"Retail",
            "subcategory":"Repair Shop",
            "type":"Services"
        }
    ],
    "sg:phone":"+1 718 448 2739",
    "sg:postcode":"10310",
    "sg:province":"NY",
    "sg:tags":[
        "reupholstery",
        "furniture"
    ],
    "wof:name":"Sav-Mor Interiors Company",
    "wof:placetype":"venue"
},
  "geometry": {"coordinates":[-74.12457999999999,40.633854],"type":"Point"}
}