{
  "type": "Feature",
  "properties": {
    "addr:full":"712 5th Ave Fl 30 New York NY 10019",
    "addr:housenumber":"712;30",
    "addr:postcode":"10019",
    "addr:street":"5Th Ave Fl",
    "iso:country":"US",
    "sg:address":"712 5th Ave Fl 30",
    "sg:city":"New York",
    "sg:classifiers":[
        {
            "category":"Professional",
            "subcategory":"Lawyer & Legal Services",
            "type":"Services"
        }
    ],
    "sg:phone":"+1 212 801 3420",
    "sg:postcode":"10019",
    "sg:province":"NY",
    "wof:name":"Debandt Van Heck & Lagae",
    "wof:placetype":"venue"
},
  "geometry": {"coordinates":[-73.974602,40.7621],"type":"Point"}
}