{
  "type": "Feature",
  "properties": {
    "addr:full":"361 7th Ave Brooklyn NY 11215",
    "addr:housenumber":"361",
    "addr:postcode":"11215",
    "addr:street":"7Th Ave",
    "iso:country":"US",
    "sg:address":"361 7th Ave",
    "sg:city":"Brooklyn",
    "sg:classifiers":[
        {
            "category":"Restaurant",
            "type":"Food & Drink"
        }
    ],
    "sg:phone":"+1 718 499 2288",
    "sg:postcode":"11215",
    "sg:province":"NY",
    "wof:name":"Kiku King",
    "wof:placetype":"venue"
},
  "geometry": {"coordinates":[-73.98215500000001,40.665802],"type":"Point"}
}