{
  "type": "Feature",
  "properties": {
    "iso:country":"US",
    "sg:address":"4377 Bronx Blvd Rm 302",
    "sg:city":"Bronx",
    "sg:classifiers":[
        {
            "category":"Professional",
            "subcategory":"Accounting & Tax Preparation",
            "type":"Services"
        },
        {
            "category":"Professional",
            "subcategory":"Employment Agencies",
            "type":"Services"
        }
    ],
    "sg:phone":"+1 718 519 7372",
    "sg:postcode":"10466",
    "sg:province":"NY",
    "sg:tags":[
        "bookkeeping",
        "opportunity"
    ],
    "wof:name":"The Fleurantin Corp",
    "wof:placetype":"venue"
},
  "geometry": {"coordinates":[-73.858251,40.899155],"type":"Point"}
}