{
  "type": "Feature",
  "properties": {
    "addr:full":"100 de Kruif Pl Apt 18H Bronx NY 10475",
    "addr:housenumber":"100",
    "addr:postcode":"10475",
    "addr:street":"De Kruif Pl Apt 18H",
    "iso:country":"US",
    "sg:address":"100 de Kruif Pl Apt 18H",
    "sg:city":"Bronx",
    "sg:classifiers":[
        {
            "category":"Building & Trades",
            "subcategory":"Construction",
            "type":"Services"
        }
    ],
    "sg:phone":"+1 646 302 9160",
    "sg:postcode":"10475",
    "sg:province":"NY",
    "sg:tags":[
        "system",
        "contractor",
        "air conditioning"
    ],
    "wof:name":"Sampson Heat & A/C",
    "wof:placetype":"venue"
},
  "geometry": {"coordinates":[-73.82914700000001,40.875431],"type":"Point"}
}