{
  "type": "Feature",
  "properties": {
    "addr:full":"350 Metro Park Rochester NY 14623",
    "addr:housenumber":"350",
    "addr:postcode":"14623",
    "addr:street":"Metro Park",
    "iso:country":"US",
    "sg:address":"350 Metro Park",
    "sg:city":"Rochester",
    "sg:classifiers":[
        {
            "category":"Manufacturing",
            "subcategory":"Electronics",
            "type":"Manufacturing & Wholesale Goods"
        }
    ],
    "sg:phone":"+1   ",
    "sg:postcode":"14623",
    "sg:province":"NY",
    "sg:tags":[
        "electronic",
        "component",
        "mfg"
    ],
    "wof:name":"Tyco Electronics Corporation",
    "wof:placetype":"venue"
},
  "geometry": {"coordinates":[-77.622674,43.097074],"type":"Point"}
}