{
  "type": "Feature",
  "properties": {
    "addr:full":"108 12th Ave North Tonawanda NY 14120",
    "addr:housenumber":"108",
    "addr:postcode":"14120",
    "addr:street":"12Th Ave",
    "iso:country":"US",
    "sg:address":"108 12th Ave",
    "sg:city":"North Tonawanda",
    "sg:classifiers":[
        {
            "category":"Manufacturing",
            "subcategory":"Toys & Sporting Goods",
            "type":"Manufacturing & Wholesale Goods"
        },
        {
            "category":"Wholesale",
            "subcategory":"Non-durable Goods",
            "type":"Manufacturing & Wholesale Goods"
        }
    ],
    "sg:phone":"+1 716 692 1681",
    "sg:postcode":"14120",
    "sg:province":"NY",
    "sg:tags":[
        "game",
        "paper",
        "novelty",
        "gift",
        "supply"
    ],
    "wof:name":"Hein Sales & Distributing Co",
    "wof:placetype":"venue"
},
  "geometry": {"coordinates":[-78.88121700000001,43.045365],"type":"Point"}
}