{
  "type": "Feature",
  "properties": {
    "addr:full":"431 River St Rochester NY 14612",
    "addr:housenumber":"431",
    "addr:postcode":"14612",
    "addr:street":"River St",
    "iso:country":"US",
    "sg:address":"431 River St",
    "sg:city":"Rochester",
    "sg:classifiers":[
        {
            "category":"Restaurant",
            "type":"Food & Drink"
        }
    ],
    "sg:phone":"+1   ",
    "sg:postcode":"14612",
    "sg:province":"NY",
    "sg:tags":[
        "eating"
    ],
    "wof:name":"Scuttlebutts Inc",
    "wof:placetype":"venue"
},
  "geometry": {"coordinates":[-77.611907,43.249568],"type":"Point"}
}