{
  "type": "Feature",
  "properties": {
    "iso:country":"US",
    "sg:address":"158 Bennington Rd",
    "sg:city":"Buffalo",
    "sg:classifiers":[
        {
            "category":"Restaurant",
            "type":"Food & Drink"
        }
    ],
    "sg:phone":"+1   ",
    "sg:postcode":"14226",
    "sg:province":"NY",
    "sg:tags":[
        "eating"
    ],
    "wof:name":"Eddies Spaghetti House",
    "wof:placetype":"venue"
},
  "geometry": {"coordinates":[-78.770224,42.951192],"type":"Point"}
}