{
  "type": "Feature",
  "properties": {
    "addr:full":"112 W 18 St New York NY 10011",
    "addr:housenumber":"112",
    "addr:postcode":"10011",
    "addr:street":"W 18 St",
    "iso:country":"US",
    "sg:address":"112 W 18 St",
    "sg:city":"New York",
    "sg:classifiers":[
        {
            "category":"Professional",
            "subcategory":"Lawyer & Legal Services",
            "type":"Services"
        }
    ],
    "sg:phone":"+1   ",
    "sg:postcode":"10011",
    "sg:province":"NY",
    "wof:name":"Denise Carter Rubin ATT",
    "wof:placetype":"venue"
},
  "geometry": {"coordinates":[-73.997635,40.740844],"type":"Point"}
}