{
  "type": "Feature",
  "properties": {
    "addr:full":"228 Trippany Rd Massena NY 13662",
    "addr:housenumber":"228",
    "addr:postcode":"13662",
    "addr:street":"Trippany Rd",
    "iso:country":"US",
    "sg:address":"228 Trippany Rd",
    "sg:city":"Massena",
    "sg:classifiers":[
        {
            "category":"Travel",
            "subcategory":"Hotels & Motels",
            "type":"Entertainment"
        }
    ],
    "sg:phone":"+1 315 769 9497",
    "sg:postcode":"13662",
    "sg:province":"NY",
    "wof:name":"Bob's Motel",
    "wof:placetype":"venue"
},
  "geometry": {"coordinates":[-74.81442300000001,44.954201],"type":"Point"}
}