{
  "type": "Feature",
  "properties": {
    "addr:full":"821 2nd Ave New York NY 10017",
    "addr:housenumber":"821",
    "addr:postcode":"10017",
    "addr:street":"2Nd Ave",
    "iso:country":"US",
    "sg:address":"821 2nd Ave",
    "sg:city":"New York",
    "sg:classifiers":[
        {
            "category":"Restaurant",
            "type":"Food & Drink"
        }
    ],
    "sg:phone":"+1 212 490 4500",
    "sg:postcode":"10017",
    "sg:province":"NY",
    "sg:website":"sushitimenyc.com",
    "wof:name":"Sushi Time",
    "wof:placetype":"venue"
},
  "geometry": {"coordinates":[-73.971497,40.750999],"type":"Point"}
}