{
  "type": "Feature",
  "properties": {
    "addr:full":"440 Watkins St Brooklyn NY 11212",
    "addr:housenumber":"440",
    "addr:postcode":"11212",
    "addr:street":"Watkins St",
    "iso:country":"US",
    "sg:address":"440 Watkins St",
    "sg:city":"Brooklyn",
    "sg:classifiers":[
        {
            "category":"Professional",
            "subcategory":"Detective & Security Services",
            "type":"Services"
        }
    ],
    "sg:phone":"+1 718 782 1002",
    "sg:postcode":"11212",
    "sg:province":"NY",
    "sg:tags":[
        "guard",
        "patrol"
    ],
    "wof:name":"Cambridge Security Svc",
    "wof:placetype":"venue"
},
  "geometry": {"coordinates":[-73.906054,40.662634],"type":"Point"}
}