{
  "type": "Feature",
  "properties": {
    "addr:full":"514 W Merrick Rd Valley Stream NY 11580",
    "addr:housenumber":"514",
    "addr:postcode":"11580",
    "addr:street":"W Merrick Rd",
    "iso:country":"US",
    "sg:address":"514 W Merrick Rd",
    "sg:city":"Valley Stream",
    "sg:classifiers":[
        {
            "category":"Health Services",
            "subcategory":"Doctor",
            "type":"Services"
        }
    ],
    "sg:phone":"+1 516 561 1881",
    "sg:postcode":"11580",
    "sg:province":"NY",
    "sg:tags":[
        "orthodontist"
    ],
    "wof:name":"Mittler William DDS",
    "wof:placetype":"venue"
},
  "geometry": {"coordinates":[-73.71369900000001,40.6689],"type":"Point"}
}