{
  "type": "Feature",
  "properties": {
    "addr:full":"114 Van Guysling Ave Schenectady NY 12305",
    "addr:housenumber":"114",
    "addr:postcode":"12305",
    "addr:street":"Van Guysling Ave",
    "iso:country":"US",
    "sg:address":"114 Van Guysling Ave",
    "sg:city":"Schenectady",
    "sg:classifiers":[
        {
            "category":"Manufacturing",
            "subcategory":"Metals",
            "type":"Manufacturing & Wholesale Goods"
        },
        {
            "category":"Building & Trades",
            "subcategory":"Construction",
            "type":"Services"
        }
    ],
    "sg:phone":"+1 518 393 7755",
    "sg:postcode":"12305",
    "sg:province":"NY",
    "sg:tags":[
        "fire",
        "welding",
        "escape"
    ],
    "wof:name":"Armando & Sons General Welding",
    "wof:placetype":"venue"
},
  "geometry": {"coordinates":[-73.947796,42.806357],"type":"Point"}
}