{
  "type": "Feature",
  "properties": {
    "iso:country":"US",
    "sg:address":"325 E Orvis St",
    "sg:city":"Massena",
    "sg:classifiers":[
        {
            "category":"Travel",
            "subcategory":"Hotels & Motels",
            "type":"Entertainment"
        }
    ],
    "sg:phone":"+1 315 764 5751",
    "sg:postcode":"13662",
    "sg:province":"NY",
    "wof:name":"Blue Spruce Motel",
    "wof:placetype":"venue"
},
  "geometry": {"coordinates":[-74.87302,44.934855],"type":"Point"}
}