{
  "type": "Feature",
  "properties": {
    "addr:full":"6618 Avenue U Brooklyn NY 11234",
    "addr:housenumber":"6618",
    "addr:postcode":"11234",
    "addr:street":"Avenue U",
    "iso:country":"US",
    "sg:address":"6618 Avenue U",
    "sg:city":"Brooklyn",
    "sg:classifiers":[
        {
            "category":"Shopping",
            "subcategory":"Stationery & Office Supplies",
            "type":"Retail Goods"
        }
    ],
    "sg:phone":"+1 718 251 3790",
    "sg:postcode":"11234",
    "sg:province":"NY",
    "sg:tags":[
        "equipment"
    ],
    "wof:name":"Mohini Enterprise Inc",
    "wof:placetype":"venue"
},
  "geometry": {"coordinates":[-73.9104,40.6175],"type":"Point"}
}