{
  "type": "Feature",
  "properties": {
    "iso:country":"US",
    "sg:address":"26 Ranick Rd",
    "sg:city":"Hauppauge",
    "sg:classifiers":[
        {
            "category":"Shopping",
            "subcategory":"Mobile Phones",
            "type":"Retail Goods"
        }
    ],
    "sg:phone":"+1 631 582 7052",
    "sg:postcode":"11788",
    "sg:province":"NY",
    "wof:name":"Abm Wireless",
    "wof:placetype":"venue"
},
  "geometry": {"coordinates":[-73.228841,40.810081],"type":"Point"}
}