{
  "type": "Feature",
  "properties": {
    "iso:country":"US",
    "sg:address":"397 Laurel Rd",
    "sg:city":"Rockville Centre",
    "sg:classifiers":[
        {
            "category":"Health Services",
            "subcategory":"Doctor",
            "type":"Services"
        }
    ],
    "sg:phone":"+1 516 678 3982",
    "sg:postcode":"11570",
    "sg:province":"NY",
    "sg:tags":[
        "medical"
    ],
    "wof:name":"Redrose Consult Grp",
    "wof:placetype":"venue"
},
  "geometry": {"coordinates":[-73.624887,40.67827],"type":"Point"}
}