{
  "type": "Feature",
  "properties": {
    "addr:full":"212 E 181st St Bronx NY 10457",
    "addr:housenumber":"212",
    "addr:postcode":"10457",
    "addr:street":"E 181St St",
    "iso:country":"US",
    "sg:address":"212 E 181st St",
    "sg:city":"Bronx",
    "sg:classifiers":[
        {
            "category":"Food & Beverages",
            "subcategory":"Groceries & Convenience Stores",
            "type":"Retail Goods"
        }
    ],
    "sg:phone":"+1 800 303 0715",
    "sg:postcode":"10457",
    "sg:province":"NY",
    "wof:name":"Gye-Nyame African Market",
    "wof:placetype":"venue"
},
  "geometry": {"coordinates":[-73.90114699999999,40.854317],"type":"Point"}
}