{
  "type": "Feature",
  "properties": {
    "iso:country":"US",
    "sg:address":"115 Railroad St",
    "sg:city":"Warners",
    "sg:classifiers":[
        {
            "category":"Professional",
            "subcategory":"Management & Consulting",
            "type":"Services"
        }
    ],
    "sg:phone":"+1 315 685 5096",
    "sg:postcode":"13164",
    "sg:province":"NY",
    "sg:tags":[
        "agricultural",
        "consultant"
    ],
    "sg:website":"www.growmark.com",
    "wof:name":"Growmark Inc",
    "wof:placetype":"venue"
},
  "geometry": {"coordinates":[-76.328199,43.085422],"type":"Point"}
}