{
  "type": "Feature",
  "properties": {
    "addr:full":"22 Watkins Ave Oneonta NY 13820",
    "addr:housenumber":"22",
    "addr:postcode":"13820",
    "addr:street":"Watkins Ave",
    "iso:country":"US",
    "sg:address":"22 Watkins Ave",
    "sg:city":"Oneonta",
    "sg:classifiers":[
        {
            "category":"Insurance",
            "subcategory":"Insurance Agent",
            "type":"Services"
        }
    ],
    "sg:phone":"+1 607 432 2022",
    "sg:postcode":"13820",
    "sg:province":"NY",
    "sg:website":"www.gbrobertsagency.com",
    "wof:name":"Gordon B Roberts Agency Inc",
    "wof:placetype":"venue"
},
  "geometry": {"coordinates":[-75.066998,42.451209],"type":"Point"}
}