{
  "type": "Feature",
  "properties": {
    "iso:country":"US",
    "sg:address":"541 Cedarwood Dr",
    "sg:city":"Cedarhurst",
    "sg:classifiers":[
        {
            "category":"Building & Trades",
            "subcategory":"Construction",
            "type":"Services"
        }
    ],
    "sg:phone":"+1 516 569 3377",
    "sg:postcode":"11516",
    "sg:province":"NY",
    "sg:tags":[
        "home",
        "contractor",
        "commercial",
        "general"
    ],
    "wof:name":"K & R Construction Corp",
    "wof:placetype":"venue"
},
  "geometry": {"coordinates":[-73.73228899999999,40.632937],"type":"Point"}
}