{
  "type": "Feature",
  "properties": {
    "addr:full":"153 E 53rd Street New York NY 10022",
    "addr:housenumber":"153",
    "addr:postcode":"10022",
    "addr:street":"E 53Rd Street",
    "iso:country":"US",
    "sg:address":"153 E 53rd Street",
    "sg:city":"New York",
    "sg:classifiers":[
        {
            "category":"Professional",
            "subcategory":"Lawyer & Legal Services",
            "type":"Services"
        }
    ],
    "sg:phone":"+1 212 896 6500",
    "sg:postcode":"10022",
    "sg:province":"NY",
    "sg:website":"www.howrey.com",
    "wof:name":"Howrey Llp",
    "wof:placetype":"venue"
},
  "geometry": {"coordinates":[-73.970918,40.75835],"type":"Point"}
}