{
  "type": "Feature",
  "properties": {
    "addr:full":"419 E Main St Ste 303 Middletown NY 10940",
    "addr:housenumber":"419",
    "addr:postcode":"10940",
    "addr:street":"E Main St Ste 303",
    "iso:country":"US",
    "sg:address":"419 E Main St Ste 303",
    "sg:city":"Middletown",
    "sg:classifiers":[
        {
            "category":"Health Services",
            "subcategory":"Doctor",
            "type":"Services"
        },
        {
            "category":"Health Services",
            "subcategory":"Hospital",
            "type":"Services"
        }
    ],
    "sg:phone":"+1 845 343 8666",
    "sg:postcode":"10940",
    "sg:province":"NY",
    "sg:tags":[
        "physician",
        "cardiology",
        "thoracic",
        "surgeons",
        "surgery",
        "surgeon",
        "cardiovascular"
    ],
    "wof:name":"Valley Columbia Heart Center",
    "wof:placetype":"venue"
},
  "geometry": {"coordinates":[-74.393574,41.44441],"type":"Point"}
}