{
  "type": "Feature",
  "properties": {
    "addr:full":"128 Fort Washington Avenue New York NY 10032",
    "addr:housenumber":"128",
    "addr:postcode":"10032",
    "addr:street":"Fort Washington Avenue",
    "iso:country":"US",
    "sg:address":"128 Fort Washington Avenue",
    "sg:city":"New York",
    "sg:classifiers":[
        {
            "category":"Health Services",
            "subcategory":"Dentist",
            "type":"Services"
        }
    ],
    "sg:phone":"+1 212 928 1000",
    "sg:postcode":"10032",
    "sg:province":"NY",
    "wof:name":"Columbia Dental North DMD",
    "wof:placetype":"venue"
},
  "geometry": {"coordinates":[-73.943241,40.839637],"type":"Point"}
}