{
  "type": "Feature",
  "properties": {
    "addr:full":"3 Tompkins St Cortland NY 13045",
    "addr:housenumber":"3",
    "addr:postcode":"13045",
    "addr:street":"Tompkins St",
    "iso:country":"US",
    "sg:address":"3 Tompkins St",
    "sg:city":"Cortland",
    "sg:classifiers":[
        {
            "category":"Personal",
            "subcategory":"Shoe Repair & Shine",
            "type":"Services"
        }
    ],
    "sg:phone":"+1 607 753 7080",
    "sg:postcode":"13045",
    "sg:province":"NY",
    "sg:tags":[
        "repairing",
        "parlor",
        "boot",
        "shoes"
    ],
    "wof:name":"Mid-City Shoe Repair",
    "wof:placetype":"venue"
},
  "geometry": {"coordinates":[-76.180328,42.597484],"type":"Point"}
}