{
  "type": "Feature",
  "properties": {
    "addr:full":"240 Smith St Farmingdale NY 11735",
    "addr:housenumber":"240",
    "addr:postcode":"11735",
    "addr:street":"Smith St",
    "iso:country":"US",
    "sg:address":"240 Smith St",
    "sg:city":"Farmingdale",
    "sg:classifiers":[
        {
            "category":"Wholesale",
            "subcategory":"Apparel",
            "type":"Manufacturing & Wholesale Goods"
        }
    ],
    "sg:phone":"+1 516 753 2200",
    "sg:postcode":"11735",
    "sg:province":"NY",
    "sg:tags":[
        "t"
    ],
    "wof:name":"Kayman T-Shirts Whol Dist",
    "wof:placetype":"venue"
},
  "geometry": {"coordinates":[-73.403173,40.757201],"type":"Point"}
}