{
  "type": "Feature",
  "properties": {
    "addr:full":"85 Fawn Ln E Centereach NY 11720",
    "addr:housenumber":"85",
    "addr:postcode":"11720",
    "addr:street":"Fawn Ln E Centereach",
    "iso:country":"US",
    "sg:address":"85 Fawn Ln E",
    "sg:city":"Centereach",
    "sg:classifiers":[
        {
            "category":"Professional",
            "type":"Services"
        }
    ],
    "sg:phone":"+1   ",
    "sg:postcode":"11720",
    "sg:province":"NY",
    "wof:name":"Mjd Products & Service",
    "wof:placetype":"venue"
},
  "geometry": {"coordinates":[-73.070515,40.899165],"type":"Point"}
}