{
  "type": "Feature",
  "properties": {
    "addr:full":"11 Munsell Rd Medford NY 11763",
    "addr:housenumber":"11",
    "addr:postcode":"11763",
    "addr:street":"Munsell Rd",
    "iso:country":"US",
    "sg:address":"11 Munsell Rd",
    "sg:city":"Medford",
    "sg:classifiers":[
        {
            "category":"Autos & Motor Vehicles",
            "subcategory":"Automobile Sales",
            "type":"Retail Goods"
        }
    ],
    "sg:phone":"+1   ",
    "sg:postcode":"11763",
    "sg:province":"NY",
    "sg:tags":[
        "used"
    ],
    "wof:name":"D & B Auto Exchange",
    "wof:placetype":"venue"
},
  "geometry": {"coordinates":[-72.96159,40.811605],"type":"Point"}
}