{
  "type": "Feature",
  "properties": {
    "iso:country":"US",
    "sg:address":"1232 Hylan Blvd",
    "sg:city":"Staten Island",
    "sg:classifiers":[
        {
            "category":"Insurance",
            "subcategory":"Insurance Agent",
            "type":"Services"
        }
    ],
    "sg:phone":"+1 718 876 7300",
    "sg:postcode":"10305",
    "sg:province":"NY",
    "wof:name":"Allstate Insurance Co",
    "wof:placetype":"venue"
},
  "geometry": {"coordinates":[-74.085875,40.59589],"type":"Point"}
}