{
  "type": "Feature",
  "properties": {
    "addr:full":"16 Rocky Rd Cold Spring NY 10516",
    "addr:housenumber":"16",
    "addr:postcode":"10516",
    "addr:street":"Rocky Rd",
    "iso:country":"US",
    "sg:address":"16 Rocky Rd",
    "sg:city":"Cold Spring",
    "sg:classifiers":[
        {
            "category":"Professional",
            "subcategory":"Art Services",
            "type":"Services"
        }
    ],
    "sg:phone":"+1   ",
    "sg:postcode":"10516",
    "sg:province":"NY",
    "sg:tags":[
        "commercial",
        "design"
    ],
    "wof:name":"Suzanne Ball Design Inc",
    "wof:placetype":"venue"
},
  "geometry": {"coordinates":[-73.93285400000001,41.442312],"type":"Point"}
}