{
  "type": "Feature",
  "properties": {
    "addr:full":"1321 Grand Ave North Baldwin NY 11510",
    "addr:housenumber":"1321",
    "addr:postcode":"11510",
    "addr:street":"Grand Ave North",
    "iso:country":"US",
    "sg:address":"1321 Grand Ave",
    "sg:city":"North Baldwin",
    "sg:classifiers":[
        {
            "category":"Restaurant",
            "type":"Food & Drink"
        }
    ],
    "sg:phone":"+1 516 377 8866",
    "sg:postcode":"11510",
    "sg:province":"NY",
    "wof:name":"Rocco's & Pizzeria Restaurant",
    "wof:placetype":"venue"
},
  "geometry": {"coordinates":[-73.614197,40.6782],"type":"Point"}
}