{
  "type": "Feature",
  "properties": {
    "iso:country":"US",
    "sg:address":"3 W Madison Ave",
    "sg:city":"Johnstown",
    "sg:classifiers":[
        {
            "category":"Manufacturing",
            "subcategory":"Printing",
            "type":"Manufacturing & Wholesale Goods"
        }
    ],
    "sg:phone":"+1   ",
    "sg:postcode":"12095",
    "sg:province":"NY",
    "sg:tags":[
        "periodical"
    ],
    "wof:name":"North American Vegetarian Soc",
    "wof:placetype":"venue"
},
  "geometry": {"coordinates":[-74.371104,43.001488],"type":"Point"}
}