{
  "type": "Feature",
  "properties": {
    "addr:full":"56 S Portage St Westfield NY 14787",
    "addr:housenumber":"56",
    "addr:postcode":"14787",
    "addr:street":"S Portage St",
    "iso:country":"US",
    "sg:address":"56 S Portage St",
    "sg:city":"Westfield",
    "sg:classifiers":[
        {
            "category":"Health Services",
            "subcategory":"Chiropractor",
            "type":"Services"
        }
    ],
    "sg:phone":"+1 716 326 4625",
    "sg:postcode":"14787",
    "sg:province":"NY",
    "wof:name":"Jeffrey W Gerould DC",
    "wof:placetype":"venue"
},
  "geometry": {"coordinates":[-79.577336,42.320358],"type":"Point"}
}