{
  "type": "Feature",
  "properties": {
    "iso:country":"US",
    "sg:address":"473 Wortman Ave",
    "sg:city":"Brooklyn",
    "sg:classifiers":[
        {
            "category":"Manufacturing",
            "subcategory":"Rubber & Plastics",
            "type":"Manufacturing & Wholesale Goods"
        }
    ],
    "sg:phone":"+1 718 272 9210",
    "sg:postcode":"11208",
    "sg:province":"NY",
    "wof:name":"Bell Molding Inc",
    "wof:placetype":"venue"
},
  "geometry": {"coordinates":[-73.87658399999999,40.660564],"type":"Point"}
}