{
  "type": "Feature",
  "properties": {
    "addr:full":"633 Olmstead Ave Bronx NY 10473",
    "addr:housenumber":"633",
    "addr:postcode":"10473",
    "addr:street":"Olmstead Ave",
    "iso:country":"US",
    "sg:address":"633 Olmstead Ave",
    "sg:city":"Bronx",
    "sg:classifiers":[
        {
            "category":"Real Estate",
            "subcategory":"Real Estate Agent",
            "type":"Services"
        },
        {
            "category":"Real Estate",
            "subcategory":"Real Estate Operator",
            "type":"Services"
        }
    ],
    "sg:phone":"+1 718 829 6912",
    "sg:postcode":"10473",
    "sg:province":"NY",
    "sg:tags":[
        "building",
        "apartment",
        "management",
        "owner",
        "cooperative"
    ],
    "wof:name":"Jamie Towers Housing Co Inc",
    "wof:placetype":"venue"
},
  "geometry": {"coordinates":[-73.85153,40.820014],"type":"Point"}
}