{
  "type": "Feature",
  "properties": {
    "addr:full":"131 Maple Ave Haverstraw NY 10927",
    "addr:housenumber":"131",
    "addr:postcode":"10927",
    "addr:street":"Maple Ave",
    "iso:country":"US",
    "sg:address":"131 Maple Ave",
    "sg:city":"Haverstraw",
    "sg:classifiers":[
        {
            "category":"Real Estate",
            "subcategory":"Real Estate Agent",
            "type":"Services"
        }
    ],
    "sg:phone":"+1 845 942 2300",
    "sg:postcode":"10927",
    "sg:province":"NY",
    "wof:name":"Westside Realty & Construction",
    "wof:placetype":"venue"
},
  "geometry": {"coordinates":[-73.962262,41.193441],"type":"Point"}
}