{
  "type": "Feature",
  "properties": {
    "addr:full":"147 Warren St Brooklyn NY 11201",
    "addr:housenumber":"147",
    "addr:postcode":"11201",
    "addr:street":"Warren St",
    "iso:country":"US",
    "sg:address":"147 Warren St",
    "sg:city":"Brooklyn",
    "sg:classifiers":[
        {
            "category":"Real Estate",
            "subcategory":"Real Estate Agent",
            "type":"Services"
        }
    ],
    "sg:phone":"+1 718 625 1550",
    "sg:postcode":"11201",
    "sg:province":"NY",
    "wof:name":"J J Lobosco",
    "wof:placetype":"venue"
},
  "geometry": {"coordinates":[-73.996028,40.687608],"type":"Point"}
}