{
  "type": "Feature",
  "properties": {
    "addr:full":"565 Broad Hollow Rd Farmingdale NY 11735",
    "addr:housenumber":"565",
    "addr:postcode":"11735",
    "addr:street":"Broad Hollow Rd",
    "iso:country":"US",
    "sg:address":"565 Broad Hollow Rd",
    "sg:city":"Farmingdale",
    "sg:classifiers":[
        {
            "category":"Freight",
            "type":"Transportation"
        }
    ],
    "sg:phone":"+1 516 843 8185",
    "sg:postcode":"11735",
    "sg:province":"NY",
    "sg:tags":[
        "trucking"
    ],
    "wof:name":"E & F Trucking",
    "wof:placetype":"venue"
},
  "geometry": {"coordinates":[-73.425957,40.719573],"type":"Point"}
}