{
  "type": "Feature",
  "properties": {
    "addr:full":"268 N Broadway Hicksville NY 11801",
    "addr:housenumber":"268",
    "addr:postcode":"11801",
    "addr:street":"N Broadway",
    "iso:country":"US",
    "sg:address":"268 N Broadway",
    "sg:city":"Hicksville",
    "sg:classifiers":[
        {
            "category":"Health Services",
            "subcategory":"Doctor",
            "type":"Services"
        }
    ],
    "sg:phone":"+1 516 433 3324",
    "sg:postcode":"11801",
    "sg:province":"NY",
    "sg:tags":[
        "podiatrist"
    ],
    "wof:name":"Hicksville Foot Care Center",
    "wof:placetype":"venue"
},
  "geometry": {"coordinates":[-73.5299,40.777302],"type":"Point"}
}