{
  "type": "Feature",
  "properties": {
    "addr:full":"570 Albany St Little Falls NY 13365",
    "addr:housenumber":"570",
    "addr:postcode":"13365",
    "addr:street":"Albany St",
    "iso:country":"US",
    "sg:address":"570 Albany St",
    "sg:city":"Little Falls",
    "sg:classifiers":[
        {
            "category":"Restaurant",
            "type":"Food & Drink"
        }
    ],
    "sg:menulink":"http://www.allmenus.com/ny/little-falls/144671-subway/menu/",
    "sg:phone":"+1 315 823 0103",
    "sg:postcode":"13365",
    "sg:province":"NY",
    "sg:tags":[
        "american",
        "sandwich"
    ],
    "wof:name":"Subway",
    "wof:placetype":"venue"
},
  "geometry": {"coordinates":[-74.85643,43.043726],"type":"Point"}
}