{
  "type": "Feature",
  "properties": {
    "addr:full":"1191 Forest Ave Staten Island NY 10310",
    "addr:housenumber":"1191",
    "addr:postcode":"10310",
    "addr:street":"Forest Ave",
    "iso:country":"US",
    "sg:address":"1191 Forest Ave",
    "sg:city":"Staten Island",
    "sg:classifiers":[
        {
            "category":"Real Estate",
            "subcategory":"Real Estate Agent",
            "type":"Services"
        }
    ],
    "sg:phone":"+1 718 355 5248",
    "sg:postcode":"10310",
    "sg:province":"NY",
    "wof:name":"Home Finders USA",
    "wof:placetype":"venue"
},
  "geometry": {"coordinates":[-74.129627,40.626577],"type":"Point"}
}