{
  "type": "Feature",
  "properties": {
    "addr:full":"11 Orchard Ln Woodstock NY 12498",
    "addr:housenumber":"11",
    "addr:postcode":"12498",
    "addr:street":"Orchard Ln",
    "iso:country":"US",
    "sg:address":"11 Orchard Ln",
    "sg:city":"Woodstock",
    "sg:classifiers":[
        {
            "category":"Health Services",
            "subcategory":"Chiropractor",
            "type":"Services"
        }
    ],
    "sg:phone":"+1 845 679 6037",
    "sg:postcode":"12498",
    "sg:province":"NY",
    "wof:name":"Mary Smith DC",
    "wof:placetype":"venue"
},
  "geometry": {"coordinates":[-74.12621900000001,42.041117],"type":"Point"}
}