{
  "type": "Feature",
  "properties": {
    "iso:country":"US",
    "sg:address":"54 Jane Rd",
    "sg:city":"Hauppauge",
    "sg:classifiers":[
        {
            "category":"Manufacturing",
            "subcategory":"Printing",
            "type":"Manufacturing & Wholesale Goods"
        }
    ],
    "sg:phone":"+1   ",
    "sg:postcode":"11788",
    "sg:province":"NY",
    "sg:tags":[
        "dist",
        "business",
        "form"
    ],
    "wof:name":"LIBF Systems Inc",
    "wof:placetype":"venue"
},
  "geometry": {"coordinates":[-73.206851,40.805609],"type":"Point"}
}