{
  "type": "Feature",
  "properties": {
    "iso:country":"US",
    "sg:address":"203 Moran Rd",
    "sg:city":"Greene",
    "sg:phone":"+1 607 656 4377",
    "sg:postcode":"13778",
    "sg:province":"NY",
    "wof:name":"Silo Restaurant & Carriage House Guest Rooms",
    "wof:placetype":"venue"
},
  "geometry": {"coordinates":[-75.66808399999999,42.31941],"type":"Point"}
}