{
  "type": "Feature",
  "properties": {
    "addr:full":"2 Delancey St New York NY 10002",
    "addr:housenumber":"2",
    "addr:postcode":"10002",
    "addr:street":"Delancey St",
    "iso:country":"US",
    "sg:address":"2 Delancey St",
    "sg:city":"New York",
    "sg:classifiers":[
        {
            "category":"Restaurant",
            "type":"Food & Drink"
        },
        {
            "category":"Home & Garden",
            "subcategory":"Home Furnishings",
            "type":"Retail Goods"
        }
    ],
    "sg:phone":"+1 212 254 9720",
    "sg:postcode":"10002",
    "sg:province":"NY",
    "sg:tags":[
        "bath",
        "kitchen"
    ],
    "wof:name":"Bowery Restaurant Supply Co",
    "wof:placetype":"venue"
},
  "geometry": {"coordinates":[-73.99389600000001,40.7202],"type":"Point"}
}