{
  "type": "Feature",
  "properties": {
    "addr:full":"2441 Boston Road Bronx NY 10467",
    "addr:housenumber":"2441",
    "addr:postcode":"10467",
    "addr:street":"Boston Road",
    "iso:country":"US",
    "sg:address":"2441 Boston Road",
    "sg:city":"Bronx",
    "sg:classifiers":[
        {
            "category":"Autos & Motor Vehicles",
            "subcategory":"Auto Supplies",
            "type":"Retail Goods"
        }
    ],
    "sg:phone":"+1 718 881 6457",
    "sg:postcode":"10467",
    "sg:province":"NY",
    "sg:tags":[
        "tire"
    ],
    "sg:website":"www.straussauto.com",
    "wof:name":"Strauss Discount Auto",
    "wof:placetype":"venue"
},
  "geometry": {"coordinates":[-73.866496,40.862416],"type":"Point"}
}