{
  "type": "Feature",
  "properties": {
    "addr:full":"1 Foxcare Dr Oneonta NY 13820",
    "addr:housenumber":"1",
    "addr:postcode":"13820",
    "addr:street":"Foxcare Dr",
    "iso:country":"US",
    "sg:address":"1 Foxcare Dr",
    "sg:city":"Oneonta",
    "sg:classifiers":[
        {
            "category":"Wholesale",
            "subcategory":"Drugs",
            "type":"Manufacturing & Wholesale Goods"
        },
        {
            "category":"Shopping",
            "subcategory":"Pharmacy",
            "type":"Retail Goods"
        }
    ],
    "sg:phone":"+1 607 431 5959",
    "sg:postcode":"13820",
    "sg:province":"NY",
    "wof:name":"Foxcare Pharmacy",
    "wof:placetype":"venue"
},
  "geometry": {"coordinates":[-75.033265,42.456921],"type":"Point"}
}