{
  "type": "Feature",
  "properties": {
    "addr:full":"1430 2nd Avenue New York NY 10021",
    "addr:housenumber":"1430",
    "addr:postcode":"10021",
    "addr:street":"2Nd Avenue",
    "iso:country":"US",
    "sg:address":"1430 2nd Avenue",
    "sg:city":"New York",
    "sg:classifiers":[
        {
            "category":"Health Services",
            "subcategory":"Doctor",
            "type":"Services"
        }
    ],
    "sg:phone":"+1 212 434 3405",
    "sg:postcode":"10021",
    "sg:province":"NY",
    "wof:name":"Silver Jonathan M MD",
    "wof:placetype":"venue"
},
  "geometry": {"coordinates":[-73.957121,40.770445],"type":"Point"}
}