{
  "type": "Feature",
  "properties": {
    "addr:full":"44 W 18th St Ste 8D Suite 401 New York NY 10011",
    "addr:housenumber":"44;401",
    "addr:postcode":"10011",
    "addr:street":"W 18Th St Ste 8D Suite",
    "iso:country":"US",
    "sg:address":"44 W 18th St Ste 8D Suite 401",
    "sg:city":"New York",
    "sg:classifiers":[
        {
            "category":"Retail",
            "subcategory":"Portrait Studio",
            "type":"Services"
        },
        {
            "category":"Professional",
            "subcategory":"Art Services",
            "type":"Services"
        }
    ],
    "sg:phone":"+1 212 647 0336",
    "sg:postcode":"10011",
    "sg:province":"NY",
    "sg:tags":[
        "photographer",
        "photography",
        "store"
    ],
    "wof:name":"Monaco Reps",
    "wof:placetype":"venue"
},
  "geometry": {"coordinates":[-73.993996,40.739421],"type":"Point"}
}