{
  "type": "Feature",
  "properties": {
    "addr:full":"14 Shadyside Ave Nyack NY 10960",
    "addr:housenumber":"14",
    "addr:postcode":"10960",
    "addr:street":"Shadyside Ave",
    "iso:country":"US",
    "sg:address":"14 Shadyside Ave",
    "sg:city":"Nyack",
    "sg:classifiers":[
        {
            "category":"Banks & Credit Unions",
            "subcategory":"Investment Brokerage",
            "type":"Services"
        }
    ],
    "sg:phone":"+1 845 348 8857",
    "sg:postcode":"10960",
    "sg:province":"NY",
    "sg:tags":[
        "stock",
        "bond"
    ],
    "wof:name":"See All Security Inc",
    "wof:placetype":"venue"
},
  "geometry": {"coordinates":[-73.92401,41.075814],"type":"Point"}
}