{
  "type": "Feature",
  "properties": {
    "iso:country":"US",
    "sg:address":"885 Jones Rd",
    "sg:city":"Vestal",
    "sg:classifiers":[
        {
            "category":"Shopping",
            "subcategory":"Catalog Store",
            "type":"Retail Goods"
        }
    ],
    "sg:phone":"+1   ",
    "sg:postcode":"13850",
    "sg:province":"NY",
    "sg:tags":[
        "mail",
        "educational",
        "toy",
        "game"
    ],
    "wof:name":"Hands On and Beyond",
    "wof:placetype":"venue"
},
  "geometry": {"coordinates":[-76.075098,42.056549],"type":"Point"}
}