{
  "type": "Feature",
  "properties": {
    "addr:full":"1023 Center St Horseheads NY 14845",
    "addr:housenumber":"1023",
    "addr:postcode":"14845",
    "addr:street":"Center St",
    "iso:country":"US",
    "sg:address":"1023 Center St",
    "sg:city":"Horseheads",
    "sg:classifiers":[
        {
            "category":"Bagels",
            "type":"Food & Drink"
        },
        {
            "category":"Coffee & Tea",
            "type":"Food & Drink"
        },
        {
            "category":"Food & Beverages",
            "subcategory":"Bakery",
            "type":"Retail Goods"
        },
        {
            "category":"Bakery",
            "type":"Food & Drink"
        },
        {
            "category":"Donuts",
            "type":"Food & Drink"
        }
    ],
    "sg:menulink":"http://www.allmenus.com/ny/horseheads/138429-dunkin-donuts/menu/",
    "sg:phone":"+1 845 336 5241",
    "sg:postcode":"14845",
    "sg:province":"NY",
    "sg:tags":[
        "coffee",
        "tea",
        "american",
        "bagel",
        "bakery",
        "pastry"
    ],
    "wof:name":"Dunkin' Donuts",
    "wof:placetype":"venue"
},
  "geometry": {"coordinates":[-76.822146,42.156858],"type":"Point"}
}