{
  "type": "Feature",
  "properties": {
    "addr:full":"261 Taurus Rd Schenectady NY 12304",
    "addr:housenumber":"261",
    "addr:postcode":"12304",
    "addr:street":"Taurus Rd",
    "iso:country":"US",
    "sg:address":"261 Taurus Rd",
    "sg:city":"Schenectady",
    "sg:classifiers":[
        {
            "category":"Building & Trades",
            "subcategory":"Construction",
            "type":"Services"
        }
    ],
    "sg:phone":"+1 518 377 0644",
    "sg:postcode":"12304",
    "sg:province":"NY",
    "sg:tags":[
        "project"
    ],
    "wof:name":"Schenectady Light Opera Set",
    "wof:placetype":"venue"
},
  "geometry": {"coordinates":[-73.88672099999999,42.776778],"type":"Point"}
}