{
  "type": "Feature",
  "properties": {
    "addr:full":"35 Overlook Rd Ossining NY 10562",
    "addr:housenumber":"35",
    "addr:postcode":"10562",
    "addr:street":"Overlook Rd",
    "iso:country":"US",
    "sg:address":"35 Overlook Rd",
    "sg:city":"Ossining",
    "sg:classifiers":[
        {
            "category":"Manufacturing",
            "subcategory":"Metals",
            "type":"Manufacturing & Wholesale Goods"
        }
    ],
    "sg:phone":"+1   ",
    "sg:postcode":"10562",
    "sg:province":"NY",
    "sg:tags":[
        "mfg",
        "drive",
        "gear"
    ],
    "wof:name":"Wedgtrac Corporation",
    "wof:placetype":"venue"
},
  "geometry": {"coordinates":[-73.817061,41.203617],"type":"Point"}
}