{
  "type": "Feature",
  "properties": {
    "addr:full":"110 Kingsland Ave Brooklyn NY 11222",
    "addr:housenumber":"110",
    "addr:postcode":"11222",
    "addr:street":"Kingsland Ave",
    "iso:country":"US",
    "sg:address":"110 Kingsland Ave",
    "sg:city":"Brooklyn",
    "sg:classifiers":[
        {
            "category":"Professional",
            "type":"Services"
        },
        {
            "category":"Food & Beverages",
            "subcategory":"Meat & Fish",
            "type":"Retail Goods"
        },
        {
            "category":"Food & Beverages",
            "subcategory":"Groceries & Convenience Stores",
            "type":"Retail Goods"
        }
    ],
    "sg:phone":"+1 718 387 6349",
    "sg:postcode":"11222",
    "sg:province":"NY",
    "sg:tags":[
        "shop",
        "caterer"
    ],
    "wof:name":"George's Homestyle Catering",
    "wof:placetype":"venue"
},
  "geometry": {"coordinates":[-73.94059799999999,40.720299],"type":"Point"}
}