{
  "type": "Feature",
  "properties": {
    "addr:full":"99 Maple Ave Bay Shore NY 11706",
    "addr:housenumber":"99",
    "addr:postcode":"11706",
    "addr:street":"Maple Ave",
    "iso:country":"US",
    "sg:address":"99 Maple Ave",
    "sg:city":"Bay Shore",
    "sg:classifiers":[
        {
            "category":"Recreation",
            "subcategory":"Boat Charter",
            "type":"Entertainment"
        },
        {
            "category":"Local Transit",
            "type":"Transportation"
        }
    ],
    "sg:phone":"+1 631 665 3600",
    "sg:postcode":"11706",
    "sg:province":"NY",
    "sg:tags":[
        "boating",
        "public"
    ],
    "wof:name":"Fire Island Cruises Inc",
    "wof:placetype":"venue"
},
  "geometry": {"coordinates":[-73.238998,40.713699],"type":"Point"}
}