{
  "type": "Feature",
  "properties": {
    "addr:full":"1180 State Hwy 32 Wallkill NY 12589",
    "addr:housenumber":"1180",
    "addr:postcode":"12589",
    "addr:street":"State Hwy 32",
    "iso:country":"US",
    "sg:address":"1180 State Hwy 32",
    "sg:city":"Wallkill",
    "sg:classifiers":[
        {
            "category":"Home & Garden",
            "subcategory":"Building Materials",
            "type":"Retail Goods"
        }
    ],
    "sg:phone":"+1 845 566 9329",
    "sg:postcode":"12589",
    "sg:province":"NY",
    "wof:name":"Smart Building Products & Svc",
    "wof:placetype":"venue"
},
  "geometry": {"coordinates":[-74.07562799999999,41.612719],"type":"Point"}
}