{
  "type": "Feature",
  "properties": {
    "iso:country":"US",
    "sg:address":"5556 Vardon Dr",
    "sg:city":"Canandaigua",
    "sg:classifiers":[
        {
            "category":"Restaurant",
            "type":"Food & Drink"
        }
    ],
    "sg:phone":"+1   ",
    "sg:postcode":"14424",
    "sg:province":"NY",
    "sg:tags":[
        "eating"
    ],
    "wof:name":"Uhlen Chick Associates Inc",
    "wof:placetype":"venue"
},
  "geometry": {"coordinates":[-77.344475,42.749621],"type":"Point"}
}