{
  "type": "Feature",
  "properties": {
    "addr:full":"138 E Market St Rhinebeck NY 12572",
    "addr:housenumber":"138",
    "addr:postcode":"12572",
    "addr:street":"E Market St",
    "iso:country":"US",
    "sg:address":"138 E Market St",
    "sg:city":"Rhinebeck",
    "sg:classifiers":[
        {
            "category":"Social Services",
            "type":"Services"
        }
    ],
    "sg:phone":"+1 845 876 3599",
    "sg:postcode":"12572",
    "sg:province":"NY",
    "wof:name":"Young Life",
    "wof:placetype":"venue"
},
  "geometry": {"coordinates":[-73.90326,41.927233],"type":"Point"}
}