{
  "type": "Feature",
  "properties": {
    "addr:full":"112 W Main St Johnstown NY 12095",
    "addr:housenumber":"112",
    "addr:postcode":"12095",
    "addr:street":"W Main St",
    "iso:country":"US",
    "sg:address":"112 W Main St",
    "sg:city":"Johnstown",
    "sg:classifiers":[
        {
            "category":"Shopping",
            "subcategory":"Gifts & Souvenirs",
            "type":"Retail Goods"
        }
    ],
    "sg:phone":"+1 518 762 7018",
    "sg:postcode":"12095",
    "sg:province":"NY",
    "sg:tags":[
        "shop",
        "stationery",
        "news"
    ],
    "wof:name":"Thomas' Hallmark",
    "wof:placetype":"venue"
},
  "geometry": {"coordinates":[-74.373412,43.006302],"type":"Point"}
}