{
  "type": "Feature",
  "properties": {
    "addr:full":"2205 George Urban Blvd Depew NY 14043",
    "addr:housenumber":"2205",
    "addr:postcode":"14043",
    "addr:street":"George Urban Blvd",
    "iso:country":"US",
    "sg:address":"2205 George Urban Blvd",
    "sg:city":"Depew",
    "sg:classifiers":[
        {
            "category":"Manufacturing",
            "subcategory":"Tools & Machinery",
            "type":"Manufacturing & Wholesale Goods"
        }
    ],
    "sg:phone":"+1 716 856 5005",
    "sg:postcode":"14043",
    "sg:province":"NY",
    "sg:tags":[
        "appliance"
    ],
    "sg:website":"www.apwagner.com",
    "wof:name":"A P Wagner Inc",
    "wof:placetype":"venue"
},
  "geometry": {"coordinates":[-78.726733,42.918645],"type":"Point"}
}