{
  "type": "Feature",
  "properties": {
    "addr:full":"2013 7th Ave New York NY 10027",
    "addr:housenumber":"2013",
    "addr:postcode":"10027",
    "addr:street":"7Th Ave",
    "iso:country":"US",
    "sg:address":"2013 7th Ave",
    "sg:city":"New York",
    "sg:classifiers":[
        {
            "category":"Education",
            "subcategory":"Vocational School",
            "type":"Public Place"
        }
    ],
    "sg:phone":"+1 212 665 9444",
    "sg:postcode":"10027",
    "sg:province":"NY",
    "sg:tags":[
        "processing",
        "datum"
    ],
    "wof:name":"Jericho Computer Learning Ctr",
    "wof:placetype":"venue"
},
  "geometry": {"coordinates":[-73.950362,40.805958],"type":"Point"}
}