{
  "type": "Feature",
  "properties": {
    "iso:country":"US",
    "sg:address":"256 Nulls Rd",
    "sg:city":"Little Falls",
    "sg:classifiers":[
        {
            "category":"Building & Trades",
            "subcategory":"Construction",
            "type":"Services"
        }
    ],
    "sg:phone":"+1 315 823 3636",
    "sg:postcode":"13365",
    "sg:province":"NY",
    "sg:tags":[
        "house"
    ],
    "wof:name":"Holliday Contracting & Custom",
    "wof:placetype":"venue"
},
  "geometry": {"coordinates":[-74.87106,42.991702],"type":"Point"}
}