{
  "type": "Feature",
  "properties": {
    "iso:country":"US",
    "sg:address":"1381 Co Rd 18",
    "sg:city":"Oxford",
    "sg:classifiers":[
        {
            "category":"Professional",
            "type":"Services"
        }
    ],
    "sg:phone":"+1 607 334 4323",
    "sg:postcode":"13830",
    "sg:province":"NY",
    "sg:tags":[
        "farm",
        "dairy"
    ],
    "wof:name":"Aaris Art Assoc",
    "wof:placetype":"venue"
},
  "geometry": {"coordinates":[-75.63646900000001,42.524424],"type":"Point"}
}