{
  "type": "Feature",
  "properties": {
    "addr:full":"3 Townline Cir Rochester NY 14623",
    "addr:housenumber":"3",
    "addr:postcode":"14623",
    "addr:street":"Townline Cir",
    "iso:country":"US",
    "sg:address":"3 Townline Cir",
    "sg:city":"Rochester",
    "sg:classifiers":[
        {
            "category":"Real Estate",
            "subcategory":"Real Estate Operator",
            "type":"Services"
        }
    ],
    "sg:phone":"+1 585 427 7390",
    "sg:postcode":"14623",
    "sg:province":"NY",
    "sg:tags":[
        "apartment"
    ],
    "wof:name":"Securities Properties",
    "wof:placetype":"venue"
},
  "geometry": {"coordinates":[-77.628258,43.094205],"type":"Point"}
}