{
  "type": "Feature",
  "properties": {
    "addr:full":"1518 State Rte 54 Penn Yan NY 14527",
    "addr:housenumber":"1518",
    "addr:postcode":"14527",
    "addr:street":"State Rte 54",
    "iso:country":"US",
    "sg:address":"1518 State Rte 54",
    "sg:city":"Penn Yan",
    "sg:classifiers":[
        {
            "category":"Wholesale",
            "subcategory":"Furniture",
            "type":"Manufacturing & Wholesale Goods"
        },
        {
            "category":"Building & Trades",
            "subcategory":"Construction",
            "type":"Services"
        }
    ],
    "sg:phone":"+1 315 536 8581",
    "sg:postcode":"14527",
    "sg:province":"NY",
    "sg:tags":[
        "woodworker"
    ],
    "wof:name":"Tim's Woodworking",
    "wof:placetype":"venue"
},
  "geometry": {"coordinates":[-77.00478,42.679851],"type":"Point"}
}