{
  "type": "Feature",
  "properties": {
    "addr:full":"30 Roslyn Rd Roslyn Heights NY 11577",
    "addr:housenumber":"30",
    "addr:postcode":"11577",
    "addr:street":"Roslyn Rd",
    "iso:country":"US",
    "sg:address":"30 Roslyn Rd",
    "sg:city":"Roslyn Heights",
    "sg:classifiers":[
        {
            "category":"Shopping",
            "type":"Retail Goods"
        }
    ],
    "sg:phone":"+1   ",
    "sg:postcode":"11577",
    "sg:province":"NY",
    "sg:tags":[
        "merchandise"
    ],
    "wof:name":"Audible Solutions Inc",
    "wof:placetype":"venue"
},
  "geometry": {"coordinates":[-73.64174800000001,40.79284],"type":"Point"}
}