{
  "type": "Feature",
  "properties": {
    "iso:country":"US",
    "sg:address":"515 W 27th St",
    "sg:city":"New York",
    "sg:classifiers":[
        {
            "category":"Recreation",
            "subcategory":"Dance Hall",
            "type":"Entertainment"
        }
    ],
    "sg:phone":"+1 212 629 3333",
    "sg:postcode":"10001",
    "sg:province":"NY",
    "sg:tags":[
        "club"
    ],
    "wof:name":"Bungalow 8",
    "wof:placetype":"venue"
},
  "geometry": {"coordinates":[-74.004204,40.7509],"type":"Point"}
}