{
  "type": "Feature",
  "properties": {
    "addr:full":"6 Oakley Ave Mount Vernon NY 10550",
    "addr:housenumber":"6",
    "addr:postcode":"10550",
    "addr:street":"Oakley Ave",
    "iso:country":"US",
    "sg:address":"6 Oakley Ave",
    "sg:city":"Mount Vernon",
    "sg:classifiers":[
        {
            "category":"Retail",
            "subcategory":"Laundry & Dry Cleaning",
            "type":"Services"
        }
    ],
    "sg:phone":"+1   ",
    "sg:postcode":"10550",
    "sg:province":"NY",
    "sg:tags":[
        "drycleaning",
        "plant"
    ],
    "wof:name":"Circle Valet Cleaners",
    "wof:placetype":"venue"
},
  "geometry": {"coordinates":[-73.837463,40.916157],"type":"Point"}
}