{
  "type": "Feature",
  "properties": {
    "iso:country":"US",
    "sg:address":"681 5th Ave",
    "sg:city":"New York",
    "sg:classifiers":[
        {
            "category":"Wholesale",
            "subcategory":"Apparel",
            "type":"Manufacturing & Wholesale Goods"
        }
    ],
    "sg:phone":"+1 212 371 2121",
    "sg:postcode":"10022",
    "sg:province":"NY",
    "sg:tags":[
        "clothing"
    ],
    "wof:name":"Zanella Ltd",
    "wof:placetype":"venue"
},
  "geometry": {"coordinates":[-73.975505,40.760648],"type":"Point"}
}