{
  "type": "Feature",
  "properties": {
    "addr:full":"1371 Forest Ave Staten Island NY 10302",
    "addr:housenumber":"1371",
    "addr:postcode":"10302",
    "addr:street":"Forest Ave",
    "iso:country":"US",
    "sg:address":"1371 Forest Ave",
    "sg:city":"Staten Island",
    "sg:classifiers":[
        {
            "category":"Bars & Pubs",
            "type":"Food & Drink"
        }
    ],
    "sg:phone":"+1   ",
    "sg:postcode":"10302",
    "sg:province":"NY",
    "sg:tags":[
        "drinking"
    ],
    "wof:name":"Deweys",
    "wof:placetype":"venue"
},
  "geometry": {"coordinates":[-74.135267,40.62556],"type":"Point"}
}