{
  "type": "Feature",
  "properties": {
    "iso:country":"US",
    "sg:address":"3611 14th avenue",
    "sg:city":"Brooklyn",
    "sg:classifiers":[
        {
            "category":"Professional",
            "subcategory":"Computer Services",
            "type":"Services"
        }
    ],
    "sg:postcode":"11218",
    "sg:province":"NY",
    "sg:tags":[
        "garment-bags-suit-bags-garment-covers"
    ],
    "sg:website":"http://www.basicltd.com/",
    "wof:name":"Basic ltd.",
    "wof:placetype":"venue"
},
  "geometry": {"coordinates":[-73.982816,40.640426],"type":"Point"}
}