{
  "type": "Feature",
  "properties": {
    "addr:full":"215 Ridgewood Ave Brooklyn NY 11208",
    "addr:housenumber":"215",
    "addr:postcode":"11208",
    "addr:street":"Ridgewood Ave",
    "iso:country":"US",
    "sg:address":"215 Ridgewood Ave",
    "sg:city":"Brooklyn",
    "sg:classifiers":[
        {
            "category":"Retail",
            "subcategory":"Self-service Laundry",
            "type":"Services"
        }
    ],
    "sg:phone":"+1   ",
    "sg:postcode":"11208",
    "sg:province":"NY",
    "sg:tags":[
        "coin"
    ],
    "wof:name":"Cypress Laundromat",
    "wof:placetype":"venue"
},
  "geometry": {"coordinates":[-73.88164399999999,40.68327],"type":"Point"}
}