{
  "type": "Feature",
  "properties": {
    "iso:country":"US",
    "sg:address":"533 Dutchess Tpke",
    "sg:city":"Poughkeepsie",
    "sg:classifiers":[
        {
            "category":"Communications",
            "subcategory":"Radio Station",
            "type":"Services"
        }
    ],
    "sg:phone":"+1 845 454 3342",
    "sg:postcode":"12603",
    "sg:province":"NY",
    "sg:tags":[
        "company",
        "broadcasting"
    ],
    "wof:name":"Vertex Radio Sales & Svc",
    "wof:placetype":"venue"
},
  "geometry": {"coordinates":[-73.854309,41.717985],"type":"Point"}
}