{
  "type": "Feature",
  "properties": {
    "iso:country":"US",
    "sg:address":"1628 60th St",
    "sg:city":"Brooklyn",
    "sg:classifiers":[
        {
            "category":"Health Services",
            "subcategory":"Clinic",
            "type":"Services"
        }
    ],
    "sg:phone":"+1 718 564 0608",
    "sg:postcode":"11204",
    "sg:province":"NY",
    "sg:tags":[
        "information",
        "alcoholism",
        "treatment"
    ],
    "wof:name":"Prime Therapy",
    "wof:placetype":"venue"
},
  "geometry": {"coordinates":[-73.991241,40.624425],"type":"Point"}
}