{
  "type": "Feature",
  "properties": {
    "iso:country":"US",
    "sg:address":"491 Ontario St",
    "sg:city":"Buffalo",
    "sg:classifiers":[
        {
            "category":"Manufacturing",
            "subcategory":"Food",
            "type":"Manufacturing & Wholesale Goods"
        }
    ],
    "sg:phone":"+1 716 873 1557",
    "sg:postcode":"14207",
    "sg:province":"NY",
    "sg:tags":[
        "brewer"
    ],
    "wof:name":"Flying Bison Brewing Co",
    "wof:placetype":"venue"
},
  "geometry": {"coordinates":[-78.896747,42.95709],"type":"Point"}
}