{
  "type": "Feature",
  "properties": {
    "iso:country":"US",
    "sg:address":"100 W 93rd St",
    "sg:city":"New York",
    "sg:classifiers":[
        {
            "category":"Real Estate",
            "subcategory":"Real Estate Services",
            "type":"Services"
        }
    ],
    "sg:phone":"+1 646 596 9899",
    "sg:postcode":"10025",
    "sg:province":"NY",
    "sg:tags":[
        "management",
        "property"
    ],
    "wof:name":"Fillmore Real Estate",
    "wof:placetype":"venue"
},
  "geometry": {"coordinates":[-73.96898899999999,40.790803],"type":"Point"}
}