{
  "type": "Feature",
  "properties": {
    "iso:country":"US",
    "sg:address":"3604 Vestal Pkwy E",
    "sg:city":"Vestal",
    "sg:classifiers":[
        {
            "category":"Restaurant",
            "type":"Food & Drink"
        }
    ],
    "sg:phone":"+1   ",
    "sg:postcode":"13850",
    "sg:province":"NY",
    "sg:tags":[
        "eating"
    ],
    "wof:name":"Friendlys",
    "wof:placetype":"venue"
},
  "geometry": {"coordinates":[-75.988327,42.096577],"type":"Point"}
}