{
  "type": "Feature",
  "properties": {
    "addr:full":"3 Main St Willsboro NY 12996",
    "addr:housenumber":"3",
    "addr:postcode":"12996",
    "addr:street":"Main St",
    "iso:country":"US",
    "sg:address":"3 Main St",
    "sg:city":"Willsboro",
    "sg:classifiers":[
        {
            "category":"Coffee & Tea",
            "type":"Food & Drink"
        },
        {
            "category":"Restaurant",
            "type":"Food & Drink"
        }
    ],
    "sg:phone":"+1 518 963 7417",
    "sg:postcode":"12996",
    "sg:province":"NY",
    "sg:tags":[
        "lunch",
        "brunch",
        "cafeteria",
        "espresso",
        "breakfast"
    ],
    "sg:website":"http://www.turtleislandcafe.com",
    "wof:name":"Turtle Island Cafe",
    "wof:placetype":"venue"
},
  "geometry": {"coordinates":[-73.391167,44.36384],"type":"Point"}
}