{
  "type": "Feature",
  "properties": {
    "addr:full":"3518 Linden Pl Flushing NY 11354",
    "addr:housenumber":"3518",
    "addr:postcode":"11354",
    "addr:street":"Linden Pl",
    "iso:country":"US",
    "sg:address":"3518 Linden Pl",
    "sg:city":"Flushing",
    "sg:classifiers":[
        {
            "category":"Education",
            "subcategory":"Special Training",
            "type":"Public Place"
        }
    ],
    "sg:phone":"+1 718 961 9255",
    "sg:postcode":"11354",
    "sg:province":"NY",
    "sg:tags":[
        "school",
        "specialty"
    ],
    "wof:name":"Korean Traditional Music Institute",
    "wof:placetype":"venue"
},
  "geometry": {"coordinates":[-73.830645,40.764583],"type":"Point"}
}