{
  "type": "Feature",
  "properties": {
    "iso:country":"US",
    "sg:address":"734 Stanton Ave",
    "sg:city":"Baldwin",
    "sg:classifiers":[
        {
            "category":"Shopping",
            "subcategory":"Used Merchandise",
            "type":"Retail Goods"
        }
    ],
    "sg:phone":"+1   ",
    "sg:postcode":"11510",
    "sg:province":"NY",
    "wof:name":"Nb s Antiques & Collectibles",
    "wof:placetype":"venue"
},
  "geometry": {"coordinates":[-73.610353,40.669197],"type":"Point"}
}