{
  "type": "Feature",
  "properties": {
    "iso:country":"US",
    "sg:address":"3 3rd Ave",
    "sg:city":"Farmingdale",
    "sg:classifiers":[
        {
            "category":"Retail",
            "subcategory":"Laundry & Dry Cleaning",
            "type":"Services"
        }
    ],
    "sg:phone":"+1 516 249 3680",
    "sg:postcode":"11735",
    "sg:province":"NY",
    "sg:tags":[
        "commercial"
    ],
    "wof:name":"Cjc Dry Cleaners",
    "wof:placetype":"venue"
},
  "geometry": {"coordinates":[-73.44492200000001,40.713676],"type":"Point"}
}