{
  "type": "Feature",
  "properties": {
    "addr:full":"2203 Astoria Blvd Astoria NY 11102",
    "addr:housenumber":"2203",
    "addr:postcode":"11102",
    "addr:street":"Astoria Blvd",
    "iso:country":"US",
    "sg:address":"2203 Astoria Blvd",
    "sg:city":"Astoria",
    "sg:classifiers":[
        {
            "category":"Insurance",
            "subcategory":"Insurance Agent",
            "type":"Services"
        },
        {
            "category":"Insurance",
            "subcategory":"Hazard Insurance",
            "type":"Services"
        },
        {
            "category":"Insurance",
            "subcategory":"Title Insurance",
            "type":"Services"
        },
        {
            "category":"Insurance",
            "subcategory":"Life Insurance",
            "type":"Services"
        }
    ],
    "sg:phone":"+1 718 204 7333",
    "sg:postcode":"11102",
    "sg:province":"NY",
    "sg:tags":[
        "business",
        "auto",
        "commercial",
        "homeowner",
        "motorcycle",
        "renter"
    ],
    "sg:website":"http://www.allstate.com/carlaabonia",
    "wof:name":"Allstate Insurance Company - Carla Abonia",
    "wof:placetype":"venue"
},
  "geometry": {"coordinates":[-73.925247,40.771994],"type":"Point"}
}