{
  "type": "Feature",
  "properties": {
    "iso:country":"US",
    "sg:address":"8580 Mill St",
    "sg:city":"Lodi",
    "sg:classifiers":[
        {
            "category":"Shopping",
            "type":"Retail Goods"
        }
    ],
    "sg:phone":"+1   ",
    "sg:postcode":"14860",
    "sg:province":"NY",
    "sg:tags":[
        "merchandise"
    ],
    "wof:name":"Environ Air",
    "wof:placetype":"venue"
},
  "geometry": {"coordinates":[-76.829644,42.611589],"type":"Point"}
}