{
  "type": "Feature",
  "properties": {
    "iso:country":"US",
    "sg:address":"309 Woodbury Rd",
    "sg:city":"Hicksville",
    "sg:classifiers":[
        {
            "category":"Building & Trades",
            "subcategory":"Plumbing",
            "type":"Services"
        }
    ],
    "sg:phone":"+1 516 526 6986",
    "sg:postcode":"11801",
    "sg:province":"NY",
    "sg:tags":[
        "conditioning",
        "air",
        "system",
        "contractor"
    ],
    "wof:name":"All Pro Airconditioning & Htng",
    "wof:placetype":"venue"
},
  "geometry": {"coordinates":[-73.508752,40.778273],"type":"Point"}
}