{
  "type": "Feature",
  "properties": {
    "addr:full":"110 E 59th St Ste 10B New York NY 10022",
    "addr:housenumber":"110;10b",
    "addr:postcode":"10022",
    "addr:street":"E 59Th St Ste",
    "iso:country":"US",
    "sg:address":"110 E 59th St Ste 10B",
    "sg:city":"New York",
    "sg:classifiers":[
        {
            "category":"Health Services",
            "subcategory":"Doctor",
            "type":"Services"
        }
    ],
    "sg:phone":"+1 212 583 2930",
    "sg:postcode":"10022",
    "sg:province":"NY",
    "sg:website":"www.kidneydoctor.us",
    "wof:name":"Joshua Schwimmer, MD, FACP, FASN",
    "wof:placetype":"venue"
},
  "geometry": {"coordinates":[-73.969255,40.762656],"type":"Point"}
}