{
  "type": "Feature",
  "properties": {
    "addr:full":"54 Bay St Long Beach NY 11561",
    "addr:housenumber":"54",
    "addr:postcode":"11561",
    "addr:street":"Bay St",
    "iso:country":"US",
    "sg:address":"54 Bay St",
    "sg:city":"Long Beach",
    "sg:classifiers":[
        {
            "category":"Bars & Pubs",
            "type":"Food & Drink"
        }
    ],
    "sg:phone":"+1   ",
    "sg:postcode":"11561",
    "sg:province":"NY",
    "sg:tags":[
        "drinking"
    ],
    "wof:name":"Kleen A Tap",
    "wof:placetype":"venue"
},
  "geometry": {"coordinates":[-73.703892,40.588593],"type":"Point"}
}