{
  "type": "Feature",
  "properties": {
    "addr:full":"2225 Voorhies Ave Brooklyn NY 11235",
    "addr:housenumber":"2225",
    "addr:postcode":"11235",
    "addr:street":"Voorhies Ave",
    "iso:country":"US",
    "sg:address":"2225 Voorhies Ave",
    "sg:city":"Brooklyn",
    "sg:classifiers":[
        {
            "category":"Bars & Pubs",
            "type":"Food & Drink"
        }
    ],
    "sg:phone":"+1   ",
    "sg:postcode":"11235",
    "sg:province":"NY",
    "sg:tags":[
        "tavern"
    ],
    "wof:name":"Heart Tavern",
    "wof:placetype":"venue"
},
  "geometry": {"coordinates":[-73.945956,40.586661],"type":"Point"}
}