{
  "type": "Feature",
  "properties": {
    "iso:country":"US",
    "sg:address":"173 Mulberry St",
    "sg:city":"New York",
    "sg:classifiers":[
        {
            "category":"Restaurant",
            "type":"Food & Drink"
        }
    ],
    "sg:menulink":"http://www.allmenus.com/ny/new-york/253028-lunella-ristornate/menu/",
    "sg:phone":"+1 212 966 6639",
    "sg:postcode":"10013",
    "sg:province":"NY",
    "sg:tags":[
        "italian"
    ],
    "wof:name":"Lunella Ristornate",
    "wof:placetype":"venue"
},
  "geometry": {"coordinates":[-73.997215,40.720094],"type":"Point"}
}