{
  "type": "Feature",
  "properties": {
    "addr:full":"2381 Hylan Blvd Staten Island NY 10306",
    "addr:housenumber":"2381",
    "addr:postcode":"10306",
    "addr:street":"Hylan Blvd",
    "iso:country":"US",
    "sg:address":"2381 Hylan Blvd",
    "sg:city":"Staten Island",
    "sg:classifiers":[
        {
            "category":"Building & Trades",
            "subcategory":"Landscaping Services",
            "type":"Services"
        }
    ],
    "sg:phone":"+1 718 370 3101",
    "sg:postcode":"10306",
    "sg:province":"NY",
    "sg:tags":[
        "landscape",
        "contractor"
    ],
    "wof:name":"Care Green Landscaping",
    "wof:placetype":"venue"
},
  "geometry": {"coordinates":[-74.106694,40.573733],"type":"Point"}
}