{
  "type": "Feature",
  "properties": {
    "iso:country":"US",
    "sg:address":"2235 Clove Road",
    "sg:city":"Staten Island",
    "sg:classifiers":[
        {
            "category":"Health Services",
            "subcategory":"Doctor",
            "type":"Services"
        }
    ],
    "sg:phone":"+1 718 815 8100",
    "sg:postcode":"10305",
    "sg:province":"NY",
    "wof:name":"New York Surgical Associates",
    "wof:placetype":"venue"
},
  "geometry": {"coordinates":[-74.08113,40.599961],"type":"Point"}
}