{
  "type": "Feature",
  "properties": {
    "addr:full":"92 Wythe Ave Brooklyn NY 11211",
    "addr:housenumber":"92",
    "addr:postcode":"11211",
    "addr:street":"Wythe Ave",
    "iso:country":"US",
    "sg:address":"92 Wythe Ave",
    "sg:city":"Brooklyn",
    "sg:classifiers":[
        {
            "category":"Arts & Performance",
            "subcategory":"Art Gallery",
            "type":"Entertainment"
        }
    ],
    "sg:postcode":"11211",
    "sg:province":"NY",
    "sg:website":"www.causeycontemporary.com",
    "wof:name":"Causey Contemporary",
    "wof:placetype":"venue"
},
  "geometry": {"coordinates":[-73.958213,40.721609],"type":"Point"}
}