{
  "type": "Feature",
  "properties": {
    "addr:full":"839 State St Watertown NY 13601",
    "addr:housenumber":"839",
    "addr:postcode":"13601",
    "addr:street":"State St",
    "iso:country":"US",
    "sg:address":"839 State St",
    "sg:city":"Watertown",
    "sg:classifiers":[
        {
            "category":"Personal",
            "subcategory":"Beauty Salon",
            "type":"Services"
        }
    ],
    "sg:phone":"+1 315 786 7191",
    "sg:postcode":"13601",
    "sg:province":"NY",
    "wof:name":"Autumn Parisian Peel",
    "wof:placetype":"venue"
},
  "geometry": {"coordinates":[-75.897777,43.97164],"type":"Point"}
}