{
  "type": "Feature",
  "properties": {
    "addr:full":"2648 S Salina St Syracuse NY 13205",
    "addr:housenumber":"2648",
    "addr:postcode":"13205",
    "addr:street":"S Salina St",
    "iso:country":"US",
    "sg:address":"2648 S Salina St",
    "sg:city":"Syracuse",
    "sg:classifiers":[
        {
            "category":"Home & Garden",
            "subcategory":"Furniture",
            "type":"Retail Goods"
        }
    ],
    "sg:phone":"+1 315 475 2000",
    "sg:postcode":"13205",
    "sg:province":"NY",
    "wof:name":"Dunk & Bright Furniture Co Inc",
    "wof:placetype":"venue"
},
  "geometry": {"coordinates":[-76.14383599999999,43.022328],"type":"Point"}
}