{
  "type": "Feature",
  "properties": {
    "iso:country":"US",
    "sg:address":"2833 Ridge Rd W",
    "sg:city":"Rochester",
    "sg:classifiers":[
        {
            "category":"Utilities",
            "subcategory":"Mobile Phone",
            "type":"Services"
        }
    ],
    "sg:phone":"+1 585 723 2150",
    "sg:postcode":"14626",
    "sg:province":"NY",
    "sg:tags":[
        "telephone",
        "cellular"
    ],
    "wof:name":"Quintex Cellular",
    "wof:placetype":"venue"
},
  "geometry": {"coordinates":[-77.704104,43.21012],"type":"Point"}
}