{
  "type": "Feature",
  "properties": {
    "iso:country":"US",
    "sg:address":"145 Hook Creek Blvd",
    "sg:city":"Valley Stream",
    "sg:classifiers":[
        {
            "category":"Freight",
            "type":"Transportation"
        }
    ],
    "sg:phone":"+1   ",
    "sg:postcode":"11580",
    "sg:province":"NY",
    "sg:tags":[
        "courier",
        "air"
    ],
    "wof:name":"Danzas Aei Inc",
    "wof:placetype":"venue"
},
  "geometry": {"coordinates":[-73.725866,40.678528],"type":"Point"}
}