{
  "type": "Feature",
  "properties": {
    "iso:country":"US",
    "sg:address":"9 Babylon Rd",
    "sg:city":"Mastic Beach",
    "sg:classifiers":[
        {
            "category":"Building & Trades",
            "subcategory":"Plumbing",
            "type":"Services"
        }
    ],
    "sg:phone":"+1 631 399 3413",
    "sg:postcode":"11951",
    "sg:province":"NY",
    "sg:tags":[
        "contractor"
    ],
    "wof:name":"A&R Sprinkler Systems",
    "wof:placetype":"venue"
},
  "geometry": {"coordinates":[-72.854591,40.75064],"type":"Point"}
}