{
  "type": "Feature",
  "properties": {
    "addr:full":"407 W 42nd St New York NY 10036",
    "addr:housenumber":"407",
    "addr:postcode":"10036",
    "addr:street":"W 42Nd St",
    "iso:country":"US",
    "sg:address":"407 W 42nd St",
    "sg:city":"New York",
    "sg:classifiers":[
        {
            "category":"Cafe",
            "type":"Food & Drink"
        },
        {
            "category":"Restaurant",
            "type":"Food & Drink"
        }
    ],
    "sg:menulink":"http://www.allmenus.com/ny/new-york/3096-west-bank-cafe/menu/",
    "sg:phone":"+1 212 695 6909",
    "sg:postcode":"10036",
    "sg:province":"NY",
    "sg:tags":[
        "american"
    ],
    "wof:name":"West Bank Cafe",
    "wof:placetype":"venue"
},
  "geometry": {"coordinates":[-73.992947,40.758552],"type":"Point"}
}