{
  "type": "Feature",
  "properties": {
    "iso:country":"US",
    "sg:address":"11 Wilmot Ter",
    "sg:city":"Poughkeepsie",
    "sg:classifiers":[
        {
            "category":"Organizations",
            "subcategory":"Religious Organization",
            "type":"Services"
        }
    ],
    "sg:phone":"+1 845 454 2559",
    "sg:postcode":"12603",
    "sg:province":"NY",
    "sg:tags":[
        "clergy"
    ],
    "wof:name":"Eric Kaye",
    "wof:placetype":"venue"
},
  "geometry": {"coordinates":[-73.918385,41.680991],"type":"Point"}
}