{
  "type": "Feature",
  "properties": {
    "addr:full":"11090 Weaver Rd Delevan NY 14042",
    "addr:housenumber":"11090",
    "addr:postcode":"14042",
    "addr:street":"Weaver Rd",
    "iso:country":"US",
    "sg:address":"11090 Weaver Rd",
    "sg:city":"Delevan",
    "sg:classifiers":[
        {
            "category":"Building & Trades",
            "subcategory":"Construction",
            "type":"Services"
        }
    ],
    "sg:phone":"+1 716 492 2086",
    "sg:postcode":"14042",
    "sg:province":"NY",
    "sg:tags":[
        "nonresidential"
    ],
    "wof:name":"Fielder Construction",
    "wof:placetype":"venue"
},
  "geometry": {"coordinates":[-78.465777,42.488148],"type":"Point"}
}