{
  "type": "Feature",
  "properties": {
    "iso:country":"US",
    "sg:address":"60 State St",
    "sg:city":"Seneca Falls",
    "sg:classifiers":[
        {
            "category":"Personal",
            "type":"Services"
        }
    ],
    "sg:phone":"+1 315 568 2703",
    "sg:postcode":"13148",
    "sg:province":"NY",
    "sg:tags":[
        "executive",
        "business"
    ],
    "wof:name":"Seneca Falls Heritage Area Vis",
    "wof:placetype":"venue"
},
  "geometry": {"coordinates":[-76.797738,42.912836],"type":"Point"}
}