{
  "type": "Feature",
  "properties": {
    "addr:full":"216 Crippen Ave Syracuse NY 13205",
    "addr:housenumber":"216",
    "addr:postcode":"13205",
    "addr:street":"Crippen Ave",
    "iso:country":"US",
    "sg:address":"216 Crippen Ave",
    "sg:city":"Syracuse",
    "sg:classifiers":[
        {
            "category":"Real Estate",
            "subcategory":"Real Estate Operator",
            "type":"Services"
        }
    ],
    "sg:phone":"+1 315 498 5564",
    "sg:postcode":"13205",
    "sg:province":"NY",
    "sg:tags":[
        "building",
        "apartment"
    ],
    "wof:name":"Crippen Apartments",
    "wof:placetype":"venue"
},
  "geometry": {"coordinates":[-76.144779,43.00446],"type":"Point"}
}