{
  "type": "Feature",
  "properties": {
    "addr:full":"229 E 79th Street New York NY 10021",
    "addr:housenumber":"229",
    "addr:postcode":"10021",
    "addr:street":"E 79Th Street",
    "iso:country":"US",
    "sg:address":"229 E 79th Street",
    "sg:city":"New York",
    "sg:classifiers":[
        {
            "category":"Health Services",
            "subcategory":"Doctor",
            "type":"Services"
        }
    ],
    "sg:phone":"+1 212 717 6040",
    "sg:postcode":"10021",
    "sg:province":"NY",
    "wof:name":"Orbuch Laurence MD",
    "wof:placetype":"venue"
},
  "geometry": {"coordinates":[-73.956642,40.773998],"type":"Point"}
}