{
  "type": "Feature",
  "properties": {
    "addr:full":"64 W 48th St Ste 1007A New York NY 10036",
    "addr:housenumber":"64",
    "addr:postcode":"10036",
    "addr:street":"W 48Th St Ste 1007A",
    "iso:country":"US",
    "sg:address":"64 W 48th St Ste 1007A",
    "sg:city":"New York",
    "sg:classifiers":[
        {
            "category":"Shopping",
            "subcategory":"Jewelry",
            "type":"Retail Goods"
        }
    ],
    "sg:phone":"+1 212 302 3004",
    "sg:postcode":"10036",
    "sg:province":"NY",
    "wof:name":"G V Setting",
    "wof:placetype":"venue"
},
  "geometry": {"coordinates":[-73.980878,40.758195],"type":"Point"}
}