{
  "type": "Feature",
  "properties": {
    "addr:full":"8 N Walnut St Nunda NY 14517",
    "addr:housenumber":"8",
    "addr:postcode":"14517",
    "addr:street":"N Walnut St",
    "iso:country":"US",
    "sg:address":"8 N Walnut St",
    "sg:city":"Nunda",
    "sg:classifiers":[
        {
            "category":"Health Services",
            "subcategory":"Nursing And Care Facility",
            "type":"Services"
        }
    ],
    "sg:phone":"+1 585 468 5915",
    "sg:postcode":"14517",
    "sg:province":"NY",
    "sg:tags":[
        "residential"
    ],
    "wof:name":"Walnut Ira",
    "wof:placetype":"venue"
},
  "geometry": {"coordinates":[-77.93387199999999,42.57879],"type":"Point"}
}