{
  "type": "Feature",
  "properties": {
    "addr:full":"75 Howell St Rochester NY 14607",
    "addr:housenumber":"75",
    "addr:postcode":"14607",
    "addr:street":"Howell St",
    "iso:country":"US",
    "sg:address":"75 Howell St",
    "sg:city":"Rochester",
    "sg:classifiers":[
        {
            "category":"Retail",
            "subcategory":"Animal Services",
            "type":"Services"
        }
    ],
    "sg:phone":"+1 585 325 3647",
    "sg:postcode":"14607",
    "sg:province":"NY",
    "sg:website":"www.dogsatplay.com",
    "wof:name":"Dogs At Play",
    "wof:placetype":"venue"
},
  "geometry": {"coordinates":[-77.601867,43.151097],"type":"Point"}
}