{
  "type": "Feature",
  "properties": {
    "iso:country":"US",
    "sg:address":"415 E 12th St",
    "sg:city":"New York",
    "sg:classifiers":[
        {
            "category":"Shopping",
            "subcategory":"Music",
            "type":"Retail Goods"
        }
    ],
    "sg:phone":"+1 212 780 9166",
    "sg:postcode":"10009",
    "sg:province":"NY",
    "sg:tags":[
        "record",
        "vinyl",
        "dvd's"
    ],
    "sg:website":"www.academylps.com",
    "wof:name":"Academy LPs",
    "wof:placetype":"venue"
},
  "geometry": {"coordinates":[-73.98320200000001,40.72987],"type":"Point"}
}