{
  "type": "Feature",
  "properties": {
    "iso:country":"US",
    "sg:address":"49 William St",
    "sg:city":"Dansville",
    "sg:classifiers":[
        {
            "category":"Real Estate",
            "subcategory":"Real Estate Operator",
            "type":"Services"
        }
    ],
    "sg:phone":"+1 585 335 3790",
    "sg:postcode":"14437",
    "sg:province":"NY",
    "sg:tags":[
        "apartment"
    ],
    "wof:name":"Bernard Housing & Apartment",
    "wof:placetype":"venue"
},
  "geometry": {"coordinates":[-77.690725,42.567291],"type":"Point"}
}