{
  "type": "Feature",
  "properties": {
    "addr:full":"17 Battery Pl New York NY 10004",
    "addr:housenumber":"17",
    "addr:postcode":"10004",
    "addr:street":"Battery Pl",
    "iso:country":"US",
    "sg:address":"17 Battery Pl",
    "sg:city":"New York",
    "sg:classifiers":[
        {
            "category":"Shopping",
            "subcategory":"Pharmacy",
            "type":"Retail Goods"
        }
    ],
    "sg:phone":"+1 212 248 3922",
    "sg:postcode":"10004",
    "sg:province":"NY",
    "sg:tags":[
        "drugstore"
    ],
    "wof:name":"Duane Reade Drugs",
    "wof:placetype":"venue"
},
  "geometry": {"coordinates":[-74.01617899999999,40.705047],"type":"Point"}
}