{
  "type": "Feature",
  "properties": {
    "iso:country":"US",
    "sg:address":"131 Auser Rd",
    "sg:city":"Esperance",
    "sg:classifiers":[
        {
            "category":"Building & Trades",
            "subcategory":"Construction",
            "type":"Services"
        }
    ],
    "sg:phone":"+1 518 875 6187",
    "sg:postcode":"12066",
    "sg:province":"NY",
    "sg:tags":[
        "contractor"
    ],
    "wof:name":"L R Companyy",
    "wof:placetype":"venue"
},
  "geometry": {"coordinates":[-74.31617799999999,42.790391],"type":"Point"}
}