{
  "type": "Feature",
  "properties": {
    "addr:full":"45 Benedict Ave Tarrytown NY 10591",
    "addr:housenumber":"45",
    "addr:postcode":"10591",
    "addr:street":"Benedict Ave",
    "iso:country":"US",
    "sg:address":"45 Benedict Ave",
    "sg:city":"Tarrytown",
    "sg:classifiers":[
        {
            "category":"Professional",
            "subcategory":"Lawyer & Legal Services",
            "type":"Services"
        }
    ],
    "sg:phone":"+1 914 631 1266",
    "sg:postcode":"10591",
    "sg:province":"NY",
    "sg:tags":[
        "attorney"
    ],
    "wof:name":"Plunkett & Jaffe",
    "wof:placetype":"venue"
},
  "geometry": {"coordinates":[-73.857326,41.071374],"type":"Point"}
}