{
  "type": "Feature",
  "properties": {
    "iso:country":"US",
    "sg:address":"129 Main St Ste B",
    "sg:city":"Irvington",
    "sg:classifiers":[
        {
            "category":"Wholesale",
            "subcategory":"Books, Periodicals, & Newspapers",
            "type":"Manufacturing & Wholesale Goods"
        }
    ],
    "sg:phone":"+1 914 478 6425",
    "sg:postcode":"10533",
    "sg:province":"NY",
    "sg:tags":[
        "publisher",
        "book"
    ],
    "sg:website":"http://www.hylaspublishing.com",
    "wof:name":"Hydra",
    "wof:placetype":"venue"
},
  "geometry": {"coordinates":[-73.865883,41.038923],"type":"Point"}
}