{
  "type": "Feature",
  "properties": {
    "iso:country":"US",
    "sg:address":"1420 Mohawk Rd",
    "sg:city":"Mohegan Lake",
    "sg:classifiers":[
        {
            "category":"Wholesale",
            "subcategory":"Chemicals & Plastics",
            "type":"Manufacturing & Wholesale Goods"
        }
    ],
    "sg:phone":"+1 914 526 4843",
    "sg:postcode":"10547",
    "sg:province":"NY",
    "sg:tags":[
        "import",
        "spec"
    ],
    "wof:name":"Alembic Inc",
    "wof:placetype":"venue"
},
  "geometry": {"coordinates":[-73.8456,41.326616],"type":"Point"}
}