{
  "type": "Feature",
  "properties": {
    "addr:full":"Houston St and West St Pier 40 Manhattan NY 10014",
    "addr:postcode":"10014",
    "addr:street":"Houston St;St",
    "iso:country":"US",
    "sg:address":"Houston St and West St Pier 40",
    "sg:city":"Manhattan",
    "sg:classifiers":[
        {
            "category":"Recreation",
            "subcategory":"Boat Charter",
            "type":"Entertainment"
        }
    ],
    "sg:phone":"+1 917 929 3670",
    "sg:postcode":"10014",
    "sg:province":"NY",
    "sg:tags":[
        "boating"
    ],
    "sg:website":"www.villagecommunityboathouse.org",
    "wof:name":"Village Community Boathouse",
    "wof:placetype":"venue"
},
  "geometry": {"coordinates":[-74.010548,40.729109],"type":"Point"}
}