{
  "type": "Feature",
  "properties": {
    "iso:country":"US",
    "sg:address":"47 Centre View Dr",
    "sg:city":"Oyster Bay",
    "sg:classifiers":[
        {
            "category":"Government",
            "subcategory":"Office",
            "type":"Public Place"
        },
        {
            "category":"Building & Trades",
            "subcategory":"Construction",
            "type":"Services"
        }
    ],
    "sg:phone":"+1 516 624 8000",
    "sg:postcode":"11771",
    "sg:province":"NY",
    "sg:tags":[
        "development",
        "contractor"
    ],
    "wof:name":"J M S Development Corp",
    "wof:placetype":"venue"
},
  "geometry": {"coordinates":[-73.53710599999999,40.866525],"type":"Point"}
}