{
  "type": "Feature",
  "properties": {
    "addr:full":"3555 Bruckner Blvd Bronx NY 10461",
    "addr:housenumber":"3555",
    "addr:postcode":"10461",
    "addr:street":"Bruckner Blvd",
    "iso:country":"US",
    "sg:address":"3555 Bruckner Blvd",
    "sg:city":"Bronx",
    "sg:classifiers":[
        {
            "category":"Airline",
            "type":"Transportation"
        }
    ],
    "sg:phone":"+1 718 518 1185",
    "sg:postcode":"10461",
    "sg:province":"NY",
    "sg:tags":[
        "cargo",
        "air"
    ],
    "wof:name":"CJM Transport Inc",
    "wof:placetype":"venue"
},
  "geometry": {"coordinates":[-73.827307,40.847045],"type":"Point"}
}