{
  "type": "Feature",
  "properties": {
    "iso:country":"US",
    "sg:address":"210 N Nanticoke Ave",
    "sg:city":"Endicott",
    "sg:classifiers":[
        {
            "category":"Home & Garden",
            "subcategory":"Building Materials",
            "type":"Retail Goods"
        },
        {
            "category":"Building & Trades",
            "subcategory":"Construction",
            "type":"Services"
        }
    ],
    "sg:phone":"+1 607 785 8656",
    "sg:postcode":"13760",
    "sg:province":"NY",
    "sg:tags":[
        "c",
        "windows",
        "window",
        "contractor",
        "siding",
        "replacement"
    ],
    "wof:name":"Howard Quality Win & Siding Co",
    "wof:placetype":"venue"
},
  "geometry": {"coordinates":[-76.065506,42.099707],"type":"Point"}
}