{
  "type": "Feature",
  "properties": {
    "iso:country":"US",
    "sg:address":"2751 Amsdell Rd",
    "sg:city":"Hamburg",
    "sg:classifiers":[
        {
            "category":"Education",
            "subcategory":"School",
            "type":"Public Place"
        }
    ],
    "sg:phone":"+1 716 926 1730",
    "sg:postcode":"14075",
    "sg:province":"NY",
    "sg:tags":[
        "middle"
    ],
    "wof:name":"Frontier Middle School",
    "wof:placetype":"venue"
},
  "geometry": {"coordinates":[-78.896252,42.738654],"type":"Point"}
}