{
  "type": "Feature",
  "properties": {
    "addr:full":"4892 Broadway New York NY 10034",
    "addr:housenumber":"4892",
    "addr:postcode":"10034",
    "addr:street":"Broadway",
    "iso:country":"US",
    "sg:address":"4892 Broadway",
    "sg:city":"New York",
    "sg:classifiers":[
        {
            "category":"Home & Garden",
            "subcategory":"Carpets & Floor Coverings",
            "type":"Retail Goods"
        }
    ],
    "sg:phone":"+1 212 569 3401",
    "sg:postcode":"10034",
    "sg:province":"NY",
    "sg:tags":[
        "dealer",
        "rug"
    ],
    "wof:name":"Imperial Carpet Inc",
    "wof:placetype":"venue"
},
  "geometry": {"coordinates":[-73.921488,40.867479],"type":"Point"}
}