{
  "type": "Feature",
  "properties": {
    "addr:full":"151 S Broadway White Plains NY 10605",
    "addr:housenumber":"151",
    "addr:postcode":"10605",
    "addr:street":"S Broadway",
    "iso:country":"US",
    "sg:address":"151 S Broadway",
    "sg:city":"White Plains",
    "sg:classifiers":[
        {
            "category":"Professional",
            "type":"Services"
        }
    ],
    "sg:phone":"+1 914 686 8050",
    "sg:postcode":"10605",
    "sg:province":"NY",
    "sg:tags":[
        "establishment"
    ],
    "wof:name":"Ameri Group Co",
    "wof:placetype":"venue"
},
  "geometry": {"coordinates":[-73.761505,41.026404],"type":"Point"}
}