{
  "type": "Feature",
  "properties": {
    "iso:country":"US",
    "sg:address":"20 E 1st St",
    "sg:city":"Mount Vernon",
    "sg:classifiers":[
        {
            "category":"Building & Trades",
            "subcategory":"Construction",
            "type":"Services"
        }
    ],
    "sg:phone":"+1 914 663 1495",
    "sg:postcode":"10550",
    "sg:province":"NY",
    "sg:tags":[
        "carpentry",
        "carpenter",
        "contractor"
    ],
    "wof:name":"Reno Construction",
    "wof:placetype":"venue"
},
  "geometry": {"coordinates":[-73.83710499999999,40.911729],"type":"Point"}
}