{
  "type": "Feature",
  "properties": {
    "addr:full":"551 5th Ave New York NY 10017",
    "addr:housenumber":"551",
    "addr:postcode":"10017",
    "addr:street":"5Th Ave",
    "iso:country":"US",
    "sg:address":"551 5th Ave",
    "sg:city":"New York",
    "sg:classifiers":[
        {
            "category":"Professional",
            "subcategory":"Management & Consulting",
            "type":"Services"
        }
    ],
    "sg:phone":"+1 212 867 0228",
    "sg:postcode":"10017",
    "sg:province":"NY",
    "sg:tags":[
        "marketing",
        "consultant"
    ],
    "wof:name":"Beaumont Group",
    "wof:placetype":"venue"
},
  "geometry": {"coordinates":[-73.979016,40.755891],"type":"Point"}
}