{
  "type": "Feature",
  "properties": {
    "addr:full":"1407 Richmond Ave Staten Island NY 10314",
    "addr:housenumber":"1407",
    "addr:postcode":"10314",
    "addr:street":"Richmond Ave",
    "iso:country":"US",
    "sg:address":"1407 Richmond Ave",
    "sg:city":"Staten Island",
    "sg:classifiers":[
        {
            "category":"Restaurant",
            "type":"Food & Drink"
        }
    ],
    "sg:phone":"+1 718 761 2142",
    "sg:postcode":"10314",
    "sg:province":"NY",
    "wof:name":"Cozy Cocos Inc",
    "wof:placetype":"venue"
},
  "geometry": {"coordinates":[-74.15858799999999,40.613148],"type":"Point"}
}