{
  "type": "Feature",
  "properties": {
    "addr:full":"1731 Boston Road Bronx NY 10460",
    "addr:housenumber":"1731",
    "addr:postcode":"10460",
    "addr:street":"Boston Road",
    "iso:country":"US",
    "sg:address":"1731 Boston Road",
    "sg:city":"Bronx",
    "sg:classifiers":[
        {
            "category":"Personal",
            "subcategory":"Nail Salon",
            "type":"Services"
        }
    ],
    "sg:phone":"+1 718 991 8663",
    "sg:postcode":"10460",
    "sg:province":"NY",
    "wof:name":"Kathy's Nail",
    "wof:placetype":"venue"
},
  "geometry": {"coordinates":[-73.888127,40.837325],"type":"Point"}
}