{
  "type": "Feature",
  "properties": {
    "addr:full":"525 Townline Rd Hauppauge NY 11788",
    "addr:housenumber":"525",
    "addr:postcode":"11788",
    "addr:street":"Townline Rd",
    "iso:country":"US",
    "sg:address":"525 Townline Rd",
    "sg:city":"Hauppauge",
    "sg:classifiers":[
        {
            "category":"Health Services",
            "subcategory":"Doctor",
            "type":"Services"
        },
        {
            "category":"Health Services",
            "subcategory":"Clinic",
            "type":"Services"
        }
    ],
    "sg:phone":"+1 631 361 8760",
    "sg:postcode":"11788",
    "sg:province":"NY",
    "sg:tags":[
        "counseling",
        "mental"
    ],
    "wof:name":"Haegele Theodore H PHD",
    "wof:placetype":"venue"
},
  "geometry": {"coordinates":[-73.206596,40.825298],"type":"Point"}
}