{
  "type": "Feature",
  "properties": {
    "addr:full":"40 Ludlam Ave Bayville NY 11709",
    "addr:housenumber":"40",
    "addr:postcode":"11709",
    "addr:street":"Ludlam Ave",
    "iso:country":"US",
    "sg:address":"40 Ludlam Ave",
    "sg:city":"Bayville",
    "sg:classifiers":[
        {
            "category":"Retail",
            "subcategory":"Repair Shop",
            "type":"Services"
        }
    ],
    "sg:phone":"+1   ",
    "sg:postcode":"11709",
    "sg:province":"NY",
    "sg:tags":[
        "equipment",
        "marine",
        "boat",
        "supply"
    ],
    "wof:name":"Bridge Marina",
    "wof:placetype":"venue"
},
  "geometry": {"coordinates":[-73.548891,40.904468],"type":"Point"}
}