{
  "type": "Feature",
  "properties": {
    "addr:full":"957 Westchester Ave Bronx NY 10459",
    "addr:housenumber":"957",
    "addr:postcode":"10459",
    "addr:street":"Westchester Ave",
    "iso:country":"US",
    "sg:address":"957 Westchester Ave",
    "sg:city":"Bronx",
    "sg:classifiers":[
        {
            "category":"Health Services",
            "subcategory":"Doctor",
            "type":"Services"
        }
    ],
    "sg:phone":"+1 718 328 2874",
    "sg:postcode":"10459",
    "sg:province":"NY",
    "sg:tags":[
        "dentist"
    ],
    "wof:name":"City Dental Laboratory",
    "wof:placetype":"venue"
},
  "geometry": {"coordinates":[-73.896587,40.822236],"type":"Point"}
}