{
  "type": "Feature",
  "properties": {
    "iso:country":"US",
    "sg:address":"6310 Fly Rd",
    "sg:city":"East Syracuse",
    "sg:classifiers":[
        {
            "category":"Shopping",
            "subcategory":"Computers & Home Electronics",
            "type":"Retail Goods"
        }
    ],
    "sg:phone":"+1 315 434 9787",
    "sg:postcode":"13057",
    "sg:province":"NY",
    "sg:tags":[
        "software"
    ],
    "sg:website":"www.cadimensions.com",
    "wof:name":"Cadimensions Inc",
    "wof:placetype":"venue"
},
  "geometry": {"coordinates":[-76.057956,43.074125],"type":"Point"}
}