{
  "type": "Feature",
  "properties": {
    "addr:full":"220 Waterford Rd Oakdale NY 11769",
    "addr:housenumber":"220",
    "addr:postcode":"11769",
    "addr:street":"Waterford Rd",
    "iso:country":"US",
    "sg:address":"220 Waterford Rd",
    "sg:city":"Oakdale",
    "sg:classifiers":[
        {
            "category":"Building & Trades",
            "subcategory":"Construction",
            "type":"Services"
        }
    ],
    "sg:phone":"+1 631 567 6591",
    "sg:postcode":"11769",
    "sg:province":"NY",
    "sg:tags":[
        "altering",
        "remodeling",
        "contractor"
    ],
    "wof:name":"The Home Mechanic Inc",
    "wof:placetype":"venue"
},
  "geometry": {"coordinates":[-73.12488500000001,40.748364],"type":"Point"}
}