{
  "type": "Feature",
  "properties": {
    "iso:country":"US",
    "sg:address":"1096 Waterloo Geneva Rd",
    "sg:city":"Waterloo",
    "sg:classifiers":[
        {
            "category":"Personal",
            "subcategory":"Beauty Salon",
            "type":"Services"
        }
    ],
    "sg:phone":"+1 315 539 4287",
    "sg:postcode":"13165",
    "sg:province":"NY",
    "wof:name":"Kimberly's Creations",
    "wof:placetype":"venue"
},
  "geometry": {"coordinates":[-76.891289,42.899932],"type":"Point"}
}