{
  "type": "Feature",
  "properties": {
    "addr:full":"1026 41st Ave Long Island City NY 11101",
    "addr:housenumber":"1026",
    "addr:postcode":"11101",
    "addr:street":"41St Ave",
    "iso:country":"US",
    "sg:address":"1026 41st Ave",
    "sg:city":"Long Island City",
    "sg:classifiers":[
        {
            "category":"Social Services",
            "subcategory":"Child Care",
            "type":"Services"
        }
    ],
    "sg:phone":"+1 718 784 2080",
    "sg:postcode":"11101",
    "sg:province":"NY",
    "sg:tags":[
        "day"
    ],
    "wof:name":"Queensbridge Play Schl",
    "wof:placetype":"venue"
},
  "geometry": {"coordinates":[-73.945297,40.755299],"type":"Point"}
}