{
  "type": "Feature",
  "properties": {
    "addr:full":"9 Sumner Ave Brooklyn NY 11206",
    "addr:housenumber":"9",
    "addr:postcode":"11206",
    "addr:street":"Sumner Ave",
    "iso:country":"US",
    "sg:address":"9 Sumner Ave",
    "sg:city":"Brooklyn",
    "sg:classifiers":[
        {
            "category":"Personal",
            "subcategory":"Beauty Salon",
            "type":"Services"
        }
    ],
    "sg:phone":"+1   ",
    "sg:postcode":"11206",
    "sg:province":"NY",
    "sg:tags":[
        "shop"
    ],
    "wof:name":"Sumner Beauty Salon",
    "wof:placetype":"venue"
},
  "geometry": {"coordinates":[-73.94130800000001,40.699292],"type":"Point"}
}