{
  "type": "Feature",
  "properties": {
    "addr:full":"39 Radio Ave Miller Place NY 11764",
    "addr:housenumber":"39",
    "addr:postcode":"11764",
    "addr:street":"Radio Ave",
    "iso:country":"US",
    "sg:address":"39 Radio Ave",
    "sg:city":"Miller Place",
    "sg:classifiers":[
        {
            "category":"Building & Trades",
            "subcategory":"Electrical",
            "type":"Services"
        },
        {
            "category":"Shopping",
            "type":"Retail Goods"
        }
    ],
    "sg:phone":"+1 631 821 3800",
    "sg:postcode":"11764",
    "sg:province":"NY",
    "sg:tags":[
        "equipment",
        "specialization",
        "supply",
        "communication",
        "telephone",
        "also",
        "wholesale"
    ],
    "wof:name":"P M Communications Corp",
    "wof:placetype":"venue"
},
  "geometry": {"coordinates":[-72.96845399999999,40.942938],"type":"Point"}
}