{
  "type": "Feature",
  "properties": {
    "iso:country":"US",
    "sg:address":"4904 16th Ave",
    "sg:city":"Brooklyn",
    "sg:classifiers":[
        {
            "category":"Shopping",
            "type":"Retail Goods"
        },
        {
            "category":"Shopping",
            "subcategory":"Books",
            "type":"Retail Goods"
        }
    ],
    "sg:phone":"+1 718 851 7766",
    "sg:postcode":"11204",
    "sg:province":"NY",
    "sg:tags":[
        "religious"
    ],
    "wof:name":"Frankel's Hebrew Book Store",
    "wof:placetype":"venue"
},
  "geometry": {"coordinates":[-73.98613400000001,40.630547],"type":"Point"}
}