{
  "type": "Feature",
  "properties": {
    "iso:country":"US",
    "sg:address":"202 W 14 St",
    "sg:city":"New York",
    "sg:classifiers":[
        {
            "category":"Restaurant",
            "type":"Food & Drink"
        }
    ],
    "sg:phone":"+1   ",
    "sg:postcode":"10011",
    "sg:province":"NY",
    "sg:tags":[
        "eating"
    ],
    "wof:name":"Caswel Penterprises Ltd",
    "wof:placetype":"venue"
},
  "geometry": {"coordinates":[-74.002516,40.739663],"type":"Point"}
}