{
  "type": "Feature",
  "properties": {
    "addr:full":"89 Canal St Manhattan NY 10002",
    "addr:housenumber":"89",
    "addr:postcode":"10002",
    "addr:street":"Canal St",
    "iso:country":"US",
    "sg:address":"89 Canal St",
    "sg:city":"Manhattan",
    "sg:classifiers":[
        {
            "category":"Restaurant",
            "type":"Food & Drink"
        }
    ],
    "sg:postcode":"10002",
    "sg:province":"NY",
    "sg:tags":[
        "flavor",
        "local"
    ],
    "sg:website":"www.soundwalk.com/#/TOURS/chinat...",
    "wof:name":"Soundwalk: Chinatown",
    "wof:placetype":"venue"
},
  "geometry": {"coordinates":[-73.99344000000001,40.715382],"type":"Point"}
}