{
  "type": "Feature",
  "properties": {
    "addr:full":"5240 39th Dr Ste 1 Woodside NY 11377",
    "addr:housenumber":"5240",
    "addr:postcode":"11377",
    "addr:street":"39Th Dr Ste 1",
    "iso:country":"US",
    "sg:address":"5240 39th Dr Ste 1",
    "sg:city":"Woodside",
    "sg:classifiers":[
        {
            "category":"Real Estate",
            "subcategory":"Real Estate Operator",
            "type":"Services"
        }
    ],
    "sg:phone":"+1 718 651 8625",
    "sg:postcode":"11377",
    "sg:province":"NY",
    "sg:tags":[
        "apartment"
    ],
    "wof:name":"Section 2",
    "wof:placetype":"venue"
},
  "geometry": {"coordinates":[-73.911762,40.748695],"type":"Point"}
}