{
  "type": "Feature",
  "properties": {
    "iso:country":"US",
    "sg:address":"277 Maple Ave",
    "sg:city":"Smithtown",
    "sg:classifiers":[
        {
            "category":"Shopping",
            "subcategory":"Hobbies, Toys, & Games",
            "type":"Retail Goods"
        }
    ],
    "sg:phone":"+1   ",
    "sg:postcode":"11787",
    "sg:province":"NY",
    "wof:name":"Truck City Toys",
    "wof:placetype":"venue"
},
  "geometry": {"coordinates":[-73.194924,40.839248],"type":"Point"}
}