{
  "type": "Feature",
  "properties": {
    "addr:full":"4315 Queens Street Long Island City NY 11101",
    "addr:housenumber":"4315",
    "addr:postcode":"11101",
    "addr:street":"Queens Street",
    "iso:country":"US",
    "sg:address":"4315 Queens Street",
    "sg:city":"Long Island City",
    "sg:classifiers":[
        {
            "category":"Personal",
            "type":"Services"
        }
    ],
    "sg:phone":"+1 718 349 2070",
    "sg:postcode":"11101",
    "sg:province":"NY",
    "sg:tags":[
        "sewing",
        "alteration"
    ],
    "wof:name":"Primo Coat Corporation",
    "wof:placetype":"venue"
},
  "geometry": {"coordinates":[-73.93922600000001,40.747177],"type":"Point"}
}