{
  "type": "Feature",
  "properties": {
    "addr:full":"1630 Kennedy Rd Webster NY 14580",
    "addr:housenumber":"1630",
    "addr:postcode":"14580",
    "addr:street":"Kennedy Rd",
    "iso:country":"US",
    "sg:address":"1630 Kennedy Rd",
    "sg:city":"Webster",
    "sg:classifiers":[
        {
            "category":"Building & Trades",
            "subcategory":"Landscaping Services",
            "type":"Services"
        }
    ],
    "sg:phone":"+1 585 872 3233",
    "sg:postcode":"14580",
    "sg:province":"NY",
    "sg:tags":[
        "landscape",
        "contractor"
    ],
    "wof:name":"Woodgate Landscaping",
    "wof:placetype":"venue"
},
  "geometry": {"coordinates":[-77.39818699999999,43.174134],"type":"Point"}
}