{
  "type": "Feature",
  "properties": {
    "iso:country":"US",
    "sg:address":"7 Forest Rd",
    "sg:city":"Burnt Hills",
    "sg:classifiers":[
        {
            "category":"Organizations",
            "subcategory":"Membership Organization",
            "type":"Services"
        }
    ],
    "sg:phone":"+1 518 399 7248",
    "sg:postcode":"12027",
    "sg:province":"NY",
    "sg:tags":[
        "animal"
    ],
    "wof:name":"Equability Inc",
    "wof:placetype":"venue"
},
  "geometry": {"coordinates":[-73.88815099999999,42.922157],"type":"Point"}
}