{
  "type": "Feature",
  "properties": {
    "addr:full":"28 S Mall Plainview NY 11803",
    "addr:housenumber":"28",
    "addr:postcode":"11803",
    "addr:street":"S Mall",
    "iso:country":"US",
    "sg:address":"28 S Mall",
    "sg:city":"Plainview",
    "sg:classifiers":[
        {
            "category":"Shopping",
            "subcategory":"Computers & Home Electronics",
            "type":"Retail Goods"
        }
    ],
    "sg:phone":"+1 516 293 7441",
    "sg:postcode":"11803",
    "sg:province":"NY",
    "sg:tags":[
        "equipment",
        "electronic",
        "supply"
    ],
    "wof:name":"Landmark Electronics LTD",
    "wof:placetype":"venue"
},
  "geometry": {"coordinates":[-73.452836,40.78341],"type":"Point"}
}