{
  "type": "Feature",
  "properties": {
    "addr:full":"563 Van Nest Ave Bronx NY 10460",
    "addr:housenumber":"563",
    "addr:postcode":"10460",
    "addr:street":"Van Nest Ave",
    "iso:country":"US",
    "sg:address":"563 Van Nest Ave",
    "sg:city":"Bronx",
    "sg:classifiers":[
        {
            "category":"Personal",
            "type":"Services"
        }
    ],
    "sg:phone":"+1 718 864 3174",
    "sg:postcode":"10460",
    "sg:province":"NY",
    "sg:tags":[
        "party",
        "planning",
        "event"
    ],
    "wof:name":"My Two Diamonds Day Care",
    "wof:placetype":"venue"
},
  "geometry": {"coordinates":[-73.869013,40.841854],"type":"Point"}
}