{
  "type": "Feature",
  "properties": {
    "addr:full":"63 Fort Washington Ave New York NY 10032",
    "addr:housenumber":"63",
    "addr:postcode":"10032",
    "addr:street":"Fort Washington Ave",
    "iso:country":"US",
    "sg:address":"63 Fort Washington Ave",
    "sg:city":"New York",
    "sg:classifiers":[
        {
            "category":"Building & Trades",
            "subcategory":"Pest Control",
            "type":"Services"
        }
    ],
    "sg:phone":"+1 646 434 2051",
    "sg:postcode":"10032",
    "sg:province":"NY",
    "wof:name":"Pest Control Now Of New York",
    "wof:placetype":"venue"
},
  "geometry": {"coordinates":[-73.94424600000001,40.837286],"type":"Point"}
}