{
  "type": "Feature",
  "properties": {
    "addr:full":"446 Avenue of the Americ New York NY 10011",
    "addr:housenumber":"446",
    "addr:postcode":"10011",
    "addr:street":"Avenue Of The",
    "iso:country":"US",
    "sg:address":"446 Avenue of the Americ",
    "sg:city":"New York",
    "sg:classifiers":[
        {
            "category":"Arts & Performance",
            "subcategory":"Art Gallery",
            "type":"Entertainment"
        }
    ],
    "sg:phone":"+1 212 529 1312",
    "sg:postcode":"10011",
    "sg:province":"NY",
    "wof:name":"O J Art Gallery",
    "wof:placetype":"venue"
},
  "geometry": {"coordinates":[-73.998441,40.734936],"type":"Point"}
}