{
  "type": "Feature",
  "properties": {
    "addr:full":"929 Prospect Avenue Bronx NY 10459",
    "addr:housenumber":"929",
    "addr:postcode":"10459",
    "addr:street":"Prospect Avenue",
    "iso:country":"US",
    "sg:address":"929 Prospect Avenue",
    "sg:city":"Bronx",
    "sg:classifiers":[
        {
            "category":"Bakery",
            "type":"Food & Drink"
        }
    ],
    "sg:phone":"+1 718 328 1280",
    "sg:postcode":"10459",
    "sg:province":"NY",
    "wof:name":"Mi Gente",
    "wof:placetype":"venue"
},
  "geometry": {"coordinates":[-73.900812,40.821983],"type":"Point"}
}