{
  "type": "Feature",
  "properties": {
    "iso:country":"US",
    "sg:address":"53 Saddleback Trl",
    "sg:city":"Rochester",
    "sg:classifiers":[
        {
            "category":"Professional",
            "subcategory":"Lawyer & Legal Services",
            "type":"Services"
        }
    ],
    "sg:phone":"+1   ",
    "sg:postcode":"14624",
    "sg:province":"NY",
    "wof:name":"Patk J Pietropaoli Atty",
    "wof:placetype":"venue"
},
  "geometry": {"coordinates":[-77.734988,43.118062],"type":"Point"}
}