{
  "type": "Feature",
  "properties": {
    "addr:full":"700 Morris Ave Bronx NY 10451",
    "addr:housenumber":"700",
    "addr:postcode":"10451",
    "addr:street":"Morris Ave",
    "iso:country":"US",
    "sg:address":"700 Morris Ave",
    "sg:city":"Bronx",
    "sg:classifiers":[
        {
            "category":"Shopping",
            "subcategory":"Computers & Home Electronics",
            "type":"Retail Goods"
        }
    ],
    "sg:phone":"+1 800 287 8890",
    "sg:postcode":"10451",
    "sg:province":"NY",
    "wof:name":"Urban Satellite Cable Corp",
    "wof:placetype":"venue"
},
  "geometry": {"coordinates":[-73.921036,40.820771],"type":"Point"}
}