{
  "type": "Feature",
  "properties": {
    "iso:country":"US",
    "sg:address":"6263 State Hwy 31",
    "sg:city":"Cicero",
    "sg:classifiers":[
        {
            "category":"Real Estate",
            "subcategory":"Real Estate Agent",
            "type":"Services"
        }
    ],
    "sg:phone":"+1 315 752 0320",
    "sg:postcode":"13039",
    "sg:province":"NY",
    "wof:name":"Coldwell Banker Prime Prpts",
    "wof:placetype":"venue"
},
  "geometry": {"coordinates":[-76.08771400000001,43.176911],"type":"Point"}
}