{
  "type": "Feature",
  "properties": {
    "addr:full":"194 W Falls Rd West Falls NY 14170",
    "addr:housenumber":"194",
    "addr:postcode":"14170",
    "addr:street":"W Falls Rd",
    "iso:country":"US",
    "sg:address":"194 W Falls Rd",
    "sg:city":"West Falls",
    "sg:classifiers":[
        {
            "category":"Shopping",
            "subcategory":"Used Merchandise",
            "type":"Retail Goods"
        }
    ],
    "sg:phone":"+1   ",
    "sg:postcode":"14170",
    "sg:province":"NY",
    "wof:name":"Larry Welshans",
    "wof:placetype":"venue"
},
  "geometry": {"coordinates":[-78.66732,42.717303],"type":"Point"}
}