{
  "type": "Feature",
  "properties": {
    "iso:country":"US",
    "sg:address":"348 Willis Ave",
    "sg:city":"Mineola",
    "sg:classifiers":[
        {
            "category":"Arts & Performance",
            "subcategory":"Theater",
            "type":"Entertainment"
        }
    ],
    "sg:phone":"+1 516 747 5100",
    "sg:postcode":"11501",
    "sg:province":"NY",
    "sg:tags":[
        "band",
        "orchestra",
        "group"
    ],
    "wof:name":"Greg Raffa Orchestras",
    "wof:placetype":"venue"
},
  "geometry": {"coordinates":[-73.642499,40.751667],"type":"Point"}
}