{
  "type": "Feature",
  "properties": {
    "addr:full":"3904 Fuller Hollow Rd Vestal NY 13850",
    "addr:housenumber":"3904",
    "addr:postcode":"13850",
    "addr:street":"Fuller Hollow Rd",
    "iso:country":"US",
    "sg:address":"3904 Fuller Hollow Rd",
    "sg:city":"Vestal",
    "sg:classifiers":[
        {
            "category":"Health Services",
            "subcategory":"Doctor",
            "type":"Services"
        }
    ],
    "sg:phone":"+1 607 771 6507",
    "sg:postcode":"13850",
    "sg:province":"NY",
    "sg:tags":[
        "medical"
    ],
    "wof:name":"Natwar Pareek MD",
    "wof:placetype":"venue"
},
  "geometry": {"coordinates":[-75.978319,42.06889],"type":"Point"}
}