{
  "type": "Feature",
  "properties": {
    "addr:full":"1575 Rte 112 Port Jeffrsn Sta NY 11776",
    "addr:housenumber":"1575",
    "addr:postcode":"11776",
    "addr:street":"Rte 112 Port Jeffrsn Sta",
    "iso:country":"US",
    "sg:address":"1575 Rte 112",
    "sg:city":"Port Jeffrsn Sta",
    "sg:classifiers":[
        {
            "category":"Manufacturing",
            "subcategory":"Signs",
            "type":"Manufacturing & Wholesale Goods"
        }
    ],
    "sg:phone":"+1 631 331 6420",
    "sg:postcode":"11776",
    "sg:province":"NY",
    "wof:name":"CVL Signs",
    "wof:placetype":"venue"
},
  "geometry": {"coordinates":[-73.02959799999999,40.910207],"type":"Point"}
}