{
  "type": "Feature",
  "properties": {
    "iso:country":"US",
    "sg:address":"93 S Pearl St",
    "sg:city":"Pearl River",
    "sg:classifiers":[
        {
            "category":"Insurance",
            "subcategory":"Insurance Agent",
            "type":"Services"
        }
    ],
    "sg:phone":"+1 845 735 5550",
    "sg:postcode":"10965",
    "sg:province":"NY",
    "wof:name":"Hank Garvin",
    "wof:placetype":"venue"
},
  "geometry": {"coordinates":[-74.024593,41.055999],"type":"Point"}
}