{
  "type": "Feature",
  "properties": {
    "addr:full":"2553 E 14th St Brooklyn NY 11235",
    "addr:housenumber":"2553",
    "addr:postcode":"11235",
    "addr:street":"E 14Th St",
    "iso:country":"US",
    "sg:address":"2553 E 14th St",
    "sg:city":"Brooklyn",
    "sg:classifiers":[
        {
            "category":"Personal",
            "type":"Services"
        }
    ],
    "sg:phone":"+1 718 368 0438",
    "sg:postcode":"11235",
    "sg:province":"NY",
    "sg:tags":[
        "image",
        "consultants-personal"
    ],
    "wof:name":"Vinny's Tattoo & Body Piercing Inc",
    "wof:placetype":"venue"
},
  "geometry": {"coordinates":[-73.955462,40.588844],"type":"Point"}
}