{
  "type": "Feature",
  "properties": {
    "iso:country":"US",
    "sg:address":"1175 Sunrise Hwy",
    "sg:city":"Copiague",
    "sg:classifiers":[
        {
            "category":"Wholesale",
            "subcategory":"Construction Materials",
            "type":"Manufacturing & Wholesale Goods"
        },
        {
            "category":"Home & Garden",
            "subcategory":"Building Materials",
            "type":"Retail Goods"
        }
    ],
    "sg:phone":"+1 631 842 7444",
    "sg:postcode":"11726",
    "sg:province":"NY",
    "sg:tags":[
        "lumber"
    ],
    "wof:name":"Maverick Building Supply Inc",
    "wof:placetype":"venue"
},
  "geometry": {"coordinates":[-73.402877,40.690707],"type":"Point"}
}