{
  "type": "Feature",
  "properties": {
    "iso:country":"US",
    "sg:address":"250 Broome St",
    "sg:city":"New York",
    "sg:classifiers":[
        {
            "category":"Wholesale",
            "subcategory":"Groceries",
            "type":"Manufacturing & Wholesale Goods"
        }
    ],
    "sg:phone":"+1 212 353 9621",
    "sg:postcode":"10002",
    "sg:province":"NY",
    "sg:tags":[
        "general"
    ],
    "wof:name":"Diane Miu",
    "wof:placetype":"venue"
},
  "geometry": {"coordinates":[-73.989958,40.718094],"type":"Point"}
}