{
  "type": "Feature",
  "properties": {
    "iso:country":"US",
    "sg:address":"23 Green St",
    "sg:city":"Huntington",
    "sg:classifiers":[
        {
            "category":"Banks & Credit Unions",
            "subcategory":"Investment Brokerage",
            "type":"Services"
        }
    ],
    "sg:phone":"+1 631 427 6200",
    "sg:postcode":"11743",
    "sg:province":"NY",
    "sg:tags":[
        "consultant",
        "planning",
        "financial"
    ],
    "wof:name":"Brighton Financial Group",
    "wof:placetype":"venue"
},
  "geometry": {"coordinates":[-73.428387,40.869831],"type":"Point"}
}