{
  "type": "Feature",
  "properties": {
    "iso:country":"US",
    "sg:address":"231 S Wellwood Ave",
    "sg:city":"Lindenhurst",
    "sg:classifiers":[
        {
            "category":"Food & Beverages",
            "subcategory":"Meat & Fish",
            "type":"Retail Goods"
        }
    ],
    "sg:phone":"+1 631 226 2216",
    "sg:postcode":"11757",
    "sg:province":"NY",
    "wof:name":"Joe's Gourmet Meats",
    "wof:placetype":"venue"
},
  "geometry": {"coordinates":[-73.372349,40.685886],"type":"Point"}
}