{
  "type": "Feature",
  "properties": {
    "iso:country":"US",
    "sg:address":"130 Main St",
    "sg:city":"Cornwall",
    "sg:classifiers":[
        {
            "category":"Education",
            "subcategory":"School",
            "type":"Public Place"
        }
    ],
    "sg:phone":"+1 845 534 8039",
    "sg:postcode":"12518",
    "sg:province":"NY",
    "wof:name":"Cornwall Central School Dist",
    "wof:placetype":"venue"
},
  "geometry": {"coordinates":[-74.02904100000001,41.442997],"type":"Point"}
}