{
  "type": "Feature",
  "properties": {
    "iso:country":"US",
    "sg:address":"7310 37th Ave",
    "sg:city":"Jackson Heights",
    "sg:classifiers":[
        {
            "category":"Food & Beverages",
            "subcategory":"Candy",
            "type":"Retail Goods"
        }
    ],
    "sg:phone":"+1 718 505 2680",
    "sg:postcode":"11372",
    "sg:province":"NY",
    "sg:tags":[
        "dessert",
        "store"
    ],
    "wof:name":"Maharaja Sweets & Snacks",
    "wof:placetype":"venue"
},
  "geometry": {"coordinates":[-73.892197,40.748798],"type":"Point"}
}