{
  "type": "Feature",
  "properties": {
    "addr:full":"186 Main St New Paltz NY 12561",
    "addr:housenumber":"186",
    "addr:postcode":"12561",
    "addr:street":"Main St",
    "iso:country":"US",
    "sg:address":"186 Main St",
    "sg:city":"New Paltz",
    "sg:classifiers":[
        {
            "category":"Food & Beverages",
            "subcategory":"Groceries & Convenience Stores",
            "type":"Retail Goods"
        }
    ],
    "sg:phone":"+1   ",
    "sg:postcode":"12561",
    "sg:province":"NY",
    "sg:tags":[
        "convenient",
        "independent"
    ],
    "sg:website":"www.convenientfoodmart.com",
    "wof:name":"Convenient Food Mart",
    "wof:placetype":"venue"
},
  "geometry": {"coordinates":[-74.07864600000001,41.746044],"type":"Point"}
}