{
  "type": "Feature",
  "properties": {
    "addr:full":"6838 Main St Flushing NY 11367",
    "addr:housenumber":"6838",
    "addr:postcode":"11367",
    "addr:street":"Main St",
    "iso:country":"US",
    "sg:address":"6838 Main St",
    "sg:city":"Flushing",
    "sg:classifiers":[
        {
            "category":"Bakery",
            "type":"Food & Drink"
        }
    ],
    "sg:phone":"+1 718 263 8000",
    "sg:postcode":"11367",
    "sg:province":"NY",
    "wof:name":"Queens Pita",
    "wof:placetype":"venue"
},
  "geometry": {"coordinates":[-73.824997,40.732101],"type":"Point"}
}