{
  "type": "Feature",
  "properties": {
    "addr:full":"93 Benson Dr Montauk NY 11954",
    "addr:housenumber":"93",
    "addr:postcode":"11954",
    "addr:street":"Benson Dr",
    "iso:country":"US",
    "sg:address":"93 Benson Dr",
    "sg:city":"Montauk",
    "sg:classifiers":[
        {
            "category":"Wholesale",
            "subcategory":"Hardware",
            "type":"Manufacturing & Wholesale Goods"
        }
    ],
    "sg:phone":"+1 631 668 9380",
    "sg:postcode":"11954",
    "sg:province":"NY",
    "sg:tags":[
        "refrigeration"
    ],
    "wof:name":"Sprague & Ceslow Enterprises",
    "wof:placetype":"venue"
},
  "geometry": {"coordinates":[-71.912983,41.045437],"type":"Point"}
}