{
  "type": "Feature",
  "properties": {
    "iso:country":"US",
    "sg:address":"75 Frost St",
    "sg:city":"Westbury",
    "sg:classifiers":[
        {
            "category":"Utilities",
            "subcategory":"Telephone",
            "type":"Services"
        }
    ],
    "sg:phone":"+1   ",
    "sg:postcode":"11590",
    "sg:province":"NY",
    "sg:tags":[
        "communications"
    ],
    "wof:name":"Sprint",
    "wof:placetype":"venue"
},
  "geometry": {"coordinates":[-73.553944,40.760095],"type":"Point"}
}