{
  "type": "Feature",
  "properties": {
    "addr:full":"16 E 34 St New York NY 10016",
    "addr:housenumber":"16;34",
    "addr:postcode":"10016",
    "addr:street":"E;St",
    "iso:country":"US",
    "sg:address":"16 E 34 St",
    "sg:city":"New York",
    "sg:classifiers":[
        {
            "category":"Wholesale",
            "subcategory":"Apparel",
            "type":"Manufacturing & Wholesale Goods"
        }
    ],
    "sg:phone":"+1 212 592 9300",
    "sg:postcode":"10016",
    "sg:province":"NY",
    "sg:tags":[
        "child",
        "clothes"
    ],
    "wof:name":"Sorce LLC",
    "wof:placetype":"venue"
},
  "geometry": {"coordinates":[-73.98346600000001,40.747962],"type":"Point"}
}