{
  "type": "Feature",
  "properties": {
    "addr:full":"119 Mansion St Coxsackie NY 12051",
    "addr:housenumber":"119",
    "addr:postcode":"12051",
    "addr:street":"Mansion St",
    "iso:country":"US",
    "sg:address":"119 Mansion St",
    "sg:city":"Coxsackie",
    "sg:classifiers":[
        {
            "category":"Government",
            "subcategory":"Police Station",
            "type":"Public Place"
        }
    ],
    "sg:phone":"+1 518 731 8121",
    "sg:postcode":"12051",
    "sg:province":"NY",
    "sg:tags":[
        "department"
    ],
    "wof:name":"Police Department",
    "wof:placetype":"venue"
},
  "geometry": {"coordinates":[-73.807683,42.355381],"type":"Point"}
}