{
  "type": "Feature",
  "properties": {
    "addr:full":"510 Broome St New York NY 10013",
    "addr:housenumber":"510",
    "addr:postcode":"10013",
    "addr:street":"Broome St",
    "iso:country":"US",
    "sg:address":"510 Broome St",
    "sg:city":"New York",
    "sg:classifiers":[
        {
            "category":"Shopping",
            "subcategory":"Clothing, Apparel, & Fashions",
            "type":"Retail Goods"
        }
    ],
    "sg:phone":"+1   ",
    "sg:postcode":"10013",
    "sg:province":"NY",
    "sg:tags":[
        "family"
    ],
    "wof:name":"Mavi Jeans",
    "wof:placetype":"venue"
},
  "geometry": {"coordinates":[-74.003342,40.723554],"type":"Point"}
}