{
  "type": "Feature",
  "properties": {
    "addr:full":"89 Oyster Bay Rd Locust Valley NY 11560",
    "addr:housenumber":"89",
    "addr:postcode":"11560",
    "addr:street":"Oyster Bay Rd",
    "iso:country":"US",
    "sg:address":"89 Oyster Bay Rd",
    "sg:city":"Locust Valley",
    "sg:classifiers":[
        {
            "category":"Home & Garden",
            "subcategory":"Building Materials",
            "type":"Retail Goods"
        }
    ],
    "sg:phone":"+1 516 671 9303",
    "sg:postcode":"11560",
    "sg:province":"NY",
    "sg:tags":[
        "center"
    ],
    "wof:name":"Babinski Building Consultants",
    "wof:placetype":"venue"
},
  "geometry": {"coordinates":[-73.581564,40.878777],"type":"Point"}
}