{
  "type": "Feature",
  "properties": {
    "addr:full":"19 Manor Rd Medford NY 11763",
    "addr:housenumber":"19",
    "addr:postcode":"11763",
    "addr:street":"Manor Rd",
    "iso:country":"US",
    "sg:address":"19 Manor Rd",
    "sg:city":"Medford",
    "sg:classifiers":[
        {
            "category":"Retail",
            "subcategory":"Auto Rental",
            "type":"Services"
        }
    ],
    "sg:phone":"+1 631 345 0115",
    "sg:postcode":"11763",
    "sg:province":"NY",
    "sg:tags":[
        "renting",
        "truck",
        "leasing"
    ],
    "wof:name":"U-Haul Co",
    "wof:placetype":"venue"
},
  "geometry": {"coordinates":[-72.96614,40.818046],"type":"Point"}
}