{
  "type": "Feature",
  "properties": {
    "addr:full":"2428 E River Rd Grand Island NY 14072",
    "addr:housenumber":"2428",
    "addr:postcode":"14072",
    "addr:street":"E River Rd",
    "iso:country":"US",
    "sg:address":"2428 E River Rd",
    "sg:city":"Grand Island",
    "sg:classifiers":[
        {
            "category":"Shopping",
            "subcategory":"Bicycles & Sporting Goods",
            "type":"Retail Goods"
        }
    ],
    "sg:phone":"+1   ",
    "sg:postcode":"14072",
    "sg:province":"NY",
    "wof:name":"Skate Able",
    "wof:placetype":"venue"
},
  "geometry": {"coordinates":[-78.91581100000001,43.013734],"type":"Point"}
}