{
  "type": "Feature",
  "properties": {
    "iso:country":"US",
    "sg:address":"1 Washington Square Vlg Apt 15E",
    "sg:city":"New York",
    "sg:classifiers":[
        {
            "category":"Education",
            "subcategory":"University",
            "type":"Public Place"
        }
    ],
    "sg:phone":"+1 212 998 5910",
    "sg:postcode":"10012",
    "sg:province":"NY",
    "sg:tags":[
        "college"
    ],
    "sg:website":"www.nyu.edu",
    "wof:name":"New York University",
    "wof:placetype":"venue"
},
  "geometry": {"coordinates":[-73.997263,40.728104],"type":"Point"}
}