{
  "type": "Feature",
  "properties": {
    "addr:full":"3882 Merrick Rd Seaford NY 11783",
    "addr:housenumber":"3882",
    "addr:postcode":"11783",
    "addr:street":"Merrick Rd",
    "iso:country":"US",
    "sg:address":"3882 Merrick Rd",
    "sg:city":"Seaford",
    "sg:classifiers":[
        {
            "category":"Restaurant",
            "type":"Food & Drink"
        }
    ],
    "sg:menulink":"http://www.allmenus.com/ny/seaford/93620-bada-bing/menu/",
    "sg:phone":"+1 516 781 1005",
    "sg:postcode":"11783",
    "sg:province":"NY",
    "sg:tags":[
        "american",
        "pizza"
    ],
    "wof:name":"Bada Bing",
    "wof:placetype":"venue"
},
  "geometry": {"coordinates":[-73.487639,40.666026],"type":"Point"}
}