{
  "type": "Feature",
  "properties": {
    "addr:full":"10 Sunrise Mall Massapequa NY 11758",
    "addr:housenumber":"10",
    "addr:postcode":"11758",
    "addr:street":"Sunrise Mall",
    "iso:country":"US",
    "sg:address":"10 Sunrise Mall",
    "sg:city":"Massapequa",
    "sg:classifiers":[
        {
            "category":"Shopping",
            "subcategory":"Clothing, Apparel, & Fashions",
            "type":"Retail Goods"
        }
    ],
    "sg:phone":"+1   ",
    "sg:postcode":"11758",
    "sg:province":"NY",
    "sg:tags":[
        "shoes",
        "uniform"
    ],
    "wof:name":"Life Uniform 290",
    "wof:placetype":"venue"
},
  "geometry": {"coordinates":[-73.435231,40.679429],"type":"Point"}
}