{
  "type": "Feature",
  "properties": {
    "addr:full":"1744 E 3rd St Brooklyn NY 11223",
    "addr:housenumber":"1744",
    "addr:postcode":"11223",
    "addr:street":"E 3Rd St",
    "iso:country":"US",
    "sg:address":"1744 E 3rd St",
    "sg:city":"Brooklyn",
    "sg:classifiers":[
        {
            "category":"Real Estate",
            "subcategory":"Real Estate Agent",
            "type":"Services"
        }
    ],
    "sg:phone":"+1 718 645 3376",
    "sg:postcode":"11223",
    "sg:province":"NY",
    "wof:name":"1880 E 4st Realty Corporation",
    "wof:placetype":"venue"
},
  "geometry": {"coordinates":[-73.970769,40.608324],"type":"Point"}
}