{
  "type": "Feature",
  "properties": {
    "addr:full":"1001 Howard St Peekskill NY 10566",
    "addr:housenumber":"1001",
    "addr:postcode":"10566",
    "addr:street":"Howard St",
    "iso:country":"US",
    "sg:address":"1001 Howard St",
    "sg:city":"Peekskill",
    "sg:classifiers":[
        {
            "category":"Social Services",
            "subcategory":"Child Care",
            "type":"Services"
        }
    ],
    "sg:phone":"+1 914 737 9121",
    "sg:postcode":"10566",
    "sg:province":"NY",
    "wof:name":"St Peter's Day Care Ctr",
    "wof:placetype":"venue"
},
  "geometry": {"coordinates":[-73.91723399999999,41.292967],"type":"Point"}
}