{
  "type": "Feature",
  "properties": {
    "addr:full":"3032 Avenue U Brooklyn NY 11229",
    "addr:housenumber":"3032",
    "addr:postcode":"11229",
    "addr:street":"Avenue U",
    "iso:country":"US",
    "sg:address":"3032 Avenue U",
    "sg:city":"Brooklyn",
    "sg:classifiers":[
        {
            "category":"Shopping",
            "subcategory":"Shoes",
            "type":"Retail Goods"
        }
    ],
    "sg:phone":"+1 718 891 5088",
    "sg:postcode":"11229",
    "sg:province":"NY",
    "sg:tags":[
        "store"
    ],
    "wof:name":"Not Just Kicks",
    "wof:placetype":"venue"
},
  "geometry": {"coordinates":[-73.937691,40.600781],"type":"Point"}
}