{
  "type": "Feature",
  "properties": {
    "iso:country":"US",
    "sg:address":"37 Sunset Blvd",
    "sg:city":"Angola",
    "sg:classifiers":[
        {
            "category":"Building & Trades",
            "subcategory":"Electrical",
            "type":"Services"
        }
    ],
    "sg:phone":"+1 716 549 2548",
    "sg:postcode":"14006",
    "sg:province":"NY",
    "sg:tags":[
        "electrical"
    ],
    "wof:name":"Tom Nolan Wiring",
    "wof:placetype":"venue"
},
  "geometry": {"coordinates":[-79.03505800000001,42.643305],"type":"Point"}
}