{
  "type": "Feature",
  "properties": {
    "iso:country":"US",
    "sg:address":"5539 Western Tpke",
    "sg:city":"Duanesburg",
    "sg:classifiers":[
        {
            "category":"Manufacturing",
            "subcategory":"Printing",
            "type":"Manufacturing & Wholesale Goods"
        }
    ],
    "sg:phone":"+1   ",
    "sg:postcode":"12056",
    "sg:province":"NY",
    "sg:tags":[
        "offset"
    ],
    "wof:name":"Scotts Printing Company",
    "wof:placetype":"venue"
},
  "geometry": {"coordinates":[-74.14391500000001,42.763973],"type":"Point"}
}