{
  "type": "Feature",
  "properties": {
    "iso:country":"US",
    "sg:address":"52 Main St",
    "sg:city":"East Hampton",
    "sg:classifiers":[
        {
            "category":"Food & Beverages",
            "subcategory":"Candy",
            "type":"Retail Goods"
        }
    ],
    "sg:phone":"+1   ",
    "sg:postcode":"11937",
    "sg:province":"NY",
    "wof:name":"Nuts About Chocolate",
    "wof:placetype":"venue"
},
  "geometry": {"coordinates":[-72.185907,40.962697],"type":"Point"}
}