{
  "type": "Feature",
  "properties": {
    "addr:full":"161 Croton Ave Ossining NY 10562",
    "addr:housenumber":"161",
    "addr:postcode":"10562",
    "addr:street":"Croton Ave",
    "iso:country":"US",
    "sg:address":"161 Croton Ave",
    "sg:city":"Ossining",
    "sg:classifiers":[
        {
            "category":"Retail",
            "subcategory":"Repair Shop",
            "type":"Services"
        }
    ],
    "sg:phone":"+1 914 762 3162",
    "sg:postcode":"10562",
    "sg:province":"NY",
    "sg:tags":[
        "welding"
    ],
    "wof:name":"Roberto Ralph Inc",
    "wof:placetype":"venue"
},
  "geometry": {"coordinates":[-73.85016299999999,41.16707],"type":"Point"}
}