{
  "type": "Feature",
  "properties": {
    "addr:full":"16424 69th Ave Fresh Meadows NY 11365",
    "addr:housenumber":"16424",
    "addr:postcode":"11365",
    "addr:street":"69Th Ave",
    "iso:country":"US",
    "sg:address":"16424 69th Ave",
    "sg:city":"Fresh Meadows",
    "sg:classifiers":[
        {
            "category":"Food & Beverages",
            "subcategory":"Liquor & Beverages",
            "type":"Retail Goods"
        }
    ],
    "sg:phone":"+1 718 591 4108",
    "sg:postcode":"11365",
    "sg:province":"NY",
    "sg:tags":[
        "beer",
        "spirit",
        "wine"
    ],
    "wof:name":"J R Discount Liquor Store",
    "wof:placetype":"venue"
},
  "geometry": {"coordinates":[-73.80410000000001,40.733002],"type":"Point"}
}