{
  "type": "Feature",
  "properties": {
    "addr:full":"180 Broadway New York NY 10038",
    "addr:housenumber":"180",
    "addr:postcode":"10038",
    "addr:street":"Broadway",
    "iso:country":"US",
    "sg:address":"180 Broadway",
    "sg:city":"New York",
    "sg:classifiers":[
        {
            "category":"Communications",
            "type":"Services"
        }
    ],
    "sg:phone":"+1 212 406 0636",
    "sg:postcode":"10038",
    "sg:province":"NY",
    "wof:name":"Network Communications",
    "wof:placetype":"venue"
},
  "geometry": {"coordinates":[-74.009625,40.710063],"type":"Point"}
}