{
  "type": "Feature",
  "properties": {
    "iso:country":"US",
    "sg:address":"1707 Rt 6",
    "sg:city":"Carmel",
    "sg:classifiers":[
        {
            "category":"Personal",
            "type":"Services"
        }
    ],
    "sg:phone":"+1 845 226 2003",
    "sg:postcode":"10512",
    "sg:province":"NY",
    "sg:tags":[
        "party",
        "planning",
        "event"
    ],
    "sg:website":"www.rentakidsparty.com/",
    "wof:name":"Just 4 Fun Entertainment",
    "wof:placetype":"venue"
},
  "geometry": {"coordinates":[-73.67248600000001,41.417235],"type":"Point"}
}