{
  "type": "Feature",
  "properties": {
    "iso:country":"US",
    "sg:address":"107 W Main St",
    "sg:city":"East Islip",
    "sg:classifiers":[
        {
            "category":"Health Services",
            "subcategory":"Doctor",
            "type":"Services"
        }
    ],
    "sg:phone":"+1 631 581 1188",
    "sg:postcode":"11730",
    "sg:province":"NY",
    "sg:tags":[
        "surgeon",
        "oral"
    ],
    "wof:name":"Sheren Kevin DDS",
    "wof:placetype":"venue"
},
  "geometry": {"coordinates":[-73.195503,40.730301],"type":"Point"}
}