{
  "type": "Feature",
  "properties": {
    "addr:full":"3 Campus Dr Pleasantville NY 10570",
    "addr:housenumber":"3",
    "addr:postcode":"10570",
    "addr:street":"Campus Dr",
    "iso:country":"US",
    "sg:address":"3 Campus Dr",
    "sg:city":"Pleasantville",
    "sg:classifiers":[
        {
            "category":"Professional",
            "subcategory":"Management & Consulting",
            "type":"Services"
        }
    ],
    "sg:phone":"+1 914 741 5511",
    "sg:postcode":"10570",
    "sg:province":"NY",
    "sg:tags":[
        "public",
        "relations"
    ],
    "wof:name":"Robert I Schwab & Son Inc",
    "wof:placetype":"venue"
},
  "geometry": {"coordinates":[-73.77801599999999,41.144735],"type":"Point"}
}