{
  "type": "Feature",
  "properties": {
    "addr:full":"190 Hemmer Rd Jeffersonville NY 12791",
    "addr:housenumber":"190",
    "addr:postcode":"12791",
    "addr:street":"Hemmer Rd",
    "iso:country":"US",
    "sg:address":"190 Hemmer Rd",
    "sg:city":"Jeffersonville",
    "sg:classifiers":[
        {
            "category":"Recreation",
            "type":"Entertainment"
        }
    ],
    "sg:phone":"+1 845 482 3993",
    "sg:postcode":"12791",
    "sg:province":"NY",
    "sg:tags":[
        "riding",
        "academy"
    ],
    "wof:name":"Bridle Hill Farm",
    "wof:placetype":"venue"
},
  "geometry": {"coordinates":[-74.92285699999999,41.802436],"type":"Point"}
}