{
  "type": "Feature",
  "properties": {
    "addr:full":"477 Willis Ave Bronx NY 10455",
    "addr:housenumber":"477",
    "addr:postcode":"10455",
    "addr:street":"Willis Ave",
    "iso:country":"US",
    "sg:address":"477 Willis Ave",
    "sg:city":"Bronx",
    "sg:classifiers":[
        {
            "category":"Health Services",
            "subcategory":"Health Practitioner",
            "type":"Services"
        }
    ],
    "sg:phone":"+1 718 292 4640",
    "sg:postcode":"10455",
    "sg:province":"NY",
    "sg:tags":[
        "gambling",
        "addiction-information",
        "treatment"
    ],
    "sg:website":"http://www.narcofreedom.com",
    "wof:name":"Narco Freedom Nfi Mmtp",
    "wof:placetype":"venue"
},
  "geometry": {"coordinates":[-73.919017,40.814394],"type":"Point"}
}