{
  "type": "Feature",
  "properties": {
    "iso:country":"US",
    "sg:address":"145 W 62 St",
    "sg:city":"New York",
    "sg:classifiers":[
        {
            "category":"Retail",
            "subcategory":"Repair Shop",
            "type":"Services"
        }
    ],
    "sg:phone":"+1 917 464 2544",
    "sg:postcode":"10023",
    "sg:province":"NY",
    "sg:tags":[
        "lock",
        "locksmith"
    ],
    "wof:name":"24 Hour Emergency Locksmith",
    "wof:placetype":"venue"
},
  "geometry": {"coordinates":[-73.98526,40.771842],"type":"Point"}
}