{
  "type": "Feature",
  "properties": {
    "iso:country":"US",
    "sg:address":"74 Moeller St",
    "sg:city":"Binghamton",
    "sg:classifiers":[
        {
            "category":"Building & Trades",
            "subcategory":"Construction",
            "type":"Services"
        }
    ],
    "sg:phone":"+1 607 723 1925",
    "sg:postcode":"13904",
    "sg:province":"NY",
    "sg:tags":[
        "general",
        "contractor"
    ],
    "wof:name":"Direnzo Bros Construction",
    "wof:placetype":"venue"
},
  "geometry": {"coordinates":[-75.886668,42.111436],"type":"Point"}
}