{
  "type": "Feature",
  "properties": {
    "iso:country":"US",
    "sg:address":"2111 Broadway",
    "sg:city":"New York",
    "sg:classifiers":[
        {
            "category":"Personal",
            "subcategory":"Beauty Salon",
            "type":"Services"
        }
    ],
    "sg:phone":"+1   ",
    "sg:postcode":"10023",
    "sg:province":"NY",
    "sg:tags":[
        "shop"
    ],
    "wof:name":"Ansonia Beauty & More Inc",
    "wof:placetype":"venue"
},
  "geometry": {"coordinates":[-73.98168099999999,40.779885],"type":"Point"}
}