{
  "type": "Feature",
  "properties": {
    "iso:country":"US",
    "sg:address":"140 E Main St Ste 9",
    "sg:city":"Huntington",
    "sg:classifiers":[
        {
            "category":"Communications",
            "subcategory":"Film & Video Production",
            "type":"Services"
        }
    ],
    "sg:phone":"+1 631 385 8055",
    "sg:postcode":"11743",
    "sg:province":"NY",
    "sg:tags":[
        "tv",
        "radio",
        "services-commercial",
        "companies-film"
    ],
    "wof:name":"Steel Canyon Studios, Ltd.",
    "wof:placetype":"venue"
},
  "geometry": {"coordinates":[-73.404411,40.879829],"type":"Point"}
}