{
  "type": "Feature",
  "properties": {
    "iso:country":"US",
    "sg:address":"6736 80th St",
    "sg:city":"Middle Village",
    "sg:classifiers":[
        {
            "category":"Personal",
            "type":"Services"
        }
    ],
    "sg:phone":"+1 212 365 8367",
    "sg:postcode":"11379",
    "sg:province":"NY",
    "sg:tags":[
        "mover"
    ],
    "sg:website":"www.empiremoving.com",
    "wof:name":"Go Empire Movers",
    "wof:placetype":"venue"
},
  "geometry": {"coordinates":[-73.871465,40.712268],"type":"Point"}
}