{
  "type": "Feature",
  "properties": {
    "iso:country":"US",
    "sg:address":"365 Kingston Ave",
    "sg:city":"Brooklyn",
    "sg:classifiers":[
        {
            "category":"Autos & Motor Vehicles",
            "subcategory":"Automobile Sales",
            "type":"Retail Goods"
        }
    ],
    "sg:phone":"+1   ",
    "sg:postcode":"11213",
    "sg:province":"NY",
    "sg:tags":[
        "used"
    ],
    "wof:name":"Leasing Direct",
    "wof:placetype":"venue"
},
  "geometry": {"coordinates":[-73.942437,40.666055],"type":"Point"}
}