{
  "type": "Feature",
  "properties": {
    "addr:full":"111 N Main St Elmira NY 14901",
    "addr:housenumber":"111",
    "addr:postcode":"14901",
    "addr:street":"N Main St",
    "iso:country":"US",
    "sg:address":"111 N Main St",
    "sg:city":"Elmira",
    "sg:classifiers":[
        {
            "category":"Communications",
            "subcategory":"Radio Station",
            "type":"Services"
        }
    ],
    "sg:phone":"+1 607 732 2484",
    "sg:postcode":"14901",
    "sg:province":"NY",
    "sg:tags":[
        "company",
        "broadcasting"
    ],
    "wof:name":"WREQ",
    "wof:placetype":"venue"
},
  "geometry": {"coordinates":[-76.807393,42.087954],"type":"Point"}
}