{
  "type": "Feature",
  "properties": {
    "iso:country":"US",
    "sg:address":"590 Flatbush Ave",
    "sg:city":"Brooklyn",
    "sg:classifiers":[
        {
            "category":"Freight",
            "type":"Transportation"
        }
    ],
    "sg:phone":"+1   ",
    "sg:postcode":"11225",
    "sg:province":"NY",
    "sg:tags":[
        "operator",
        "local",
        "trucking"
    ],
    "wof:name":"Tak Trucking Inc",
    "wof:placetype":"venue"
},
  "geometry": {"coordinates":[-73.96051799999999,40.658778],"type":"Point"}
}