{
  "type": "Feature",
  "properties": {
    "addr:full":"100 Quentin Roosvlt Blvd Ste 508 Garden City NY 11530",
    "addr:housenumber":"100",
    "addr:postcode":"11530",
    "addr:street":"Quentin Roosvlt Blvd Ste 508",
    "iso:country":"US",
    "sg:address":"100 Quentin Roosvlt Blvd Ste 508",
    "sg:city":"Garden City",
    "sg:classifiers":[
        {
            "category":"Health Services",
            "subcategory":"Optometrist",
            "type":"Services"
        },
        {
            "category":"Shopping",
            "subcategory":"Optician",
            "type":"Retail Goods"
        }
    ],
    "sg:phone":"+1 516 487 5730",
    "sg:postcode":"11530",
    "sg:province":"NY",
    "sg:tags":[
        "eyewear"
    ],
    "wof:name":"Sterling Optical",
    "wof:placetype":"venue"
},
  "geometry": {"coordinates":[-73.604797,40.729401],"type":"Point"}
}