{
  "type": "Feature",
  "properties": {
    "addr:full":"400 Jefferson Rd Rochester NY 14623",
    "addr:housenumber":"400",
    "addr:postcode":"14623",
    "addr:street":"Jefferson Rd",
    "iso:country":"US",
    "sg:address":"400 Jefferson Rd",
    "sg:city":"Rochester",
    "sg:classifiers":[
        {
            "category":"Banks & Credit Unions",
            "subcategory":"Bank",
            "type":"Services"
        },
        {
            "category":"Shopping",
            "subcategory":"Used Merchandise",
            "type":"Retail Goods"
        }
    ],
    "sg:phone":"+1 585 730 6150",
    "sg:postcode":"14623",
    "sg:province":"NY",
    "sg:tags":[
        "resale",
        "shop",
        "second",
        "hand"
    ],
    "sg:website":"http://www.rmsyr.org",
    "wof:name":"Rescue Mission",
    "wof:placetype":"venue"
},
  "geometry": {"coordinates":[-77.642275,43.089613],"type":"Point"}
}