{
  "type": "Feature",
  "properties": {
    "addr:full":"415 Withers St Brooklyn NY 11222",
    "addr:housenumber":"415",
    "addr:postcode":"11222",
    "addr:street":"Withers St",
    "iso:country":"US",
    "sg:address":"415 Withers St",
    "sg:city":"Brooklyn",
    "sg:classifiers":[
        {
            "category":"Building & Trades",
            "subcategory":"Construction",
            "type":"Services"
        }
    ],
    "sg:phone":"+1 718 388 2287",
    "sg:postcode":"11222",
    "sg:province":"NY",
    "sg:tags":[
        "woodworker"
    ],
    "wof:name":"E C Wood & Co",
    "wof:placetype":"venue"
},
  "geometry": {"coordinates":[-73.936632,40.718947],"type":"Point"}
}