{
  "type": "Feature",
  "properties": {
    "iso:country":"US",
    "sg:address":"4 Metrotech Center",
    "sg:city":"Brooklyn",
    "sg:classifiers":[
        {
            "category":"Health Services",
            "subcategory":"Dentist",
            "type":"Services"
        }
    ],
    "sg:phone":"+1 718 403 0700",
    "sg:postcode":"11201",
    "sg:province":"NY",
    "wof:name":"Hanson Place Dental Associates",
    "wof:placetype":"venue"
},
  "geometry": {"coordinates":[-73.98477699999999,40.693651],"type":"Point"}
}