{
  "type": "Feature",
  "properties": {
    "addr:full":"281 3rd Ave Brooklyn NY 11215",
    "addr:housenumber":"281",
    "addr:postcode":"11215",
    "addr:street":"3Rd Ave",
    "iso:country":"US",
    "sg:address":"281 3rd Ave",
    "sg:city":"Brooklyn",
    "sg:classifiers":[
        {
            "category":"Personal",
            "subcategory":"Beauty Salon",
            "type":"Services"
        }
    ],
    "sg:phone":"+1 646 203 2771",
    "sg:postcode":"11215",
    "sg:province":"NY",
    "sg:tags":[
        "hair"
    ],
    "wof:name":"Taylour Monet Salon",
    "wof:placetype":"venue"
},
  "geometry": {"coordinates":[-73.985974,40.677349],"type":"Point"}
}