{
  "type": "Feature",
  "properties": {
    "addr:full":"131 W Kingsbridge Road Bronx NY 10468",
    "addr:housenumber":"131",
    "addr:postcode":"10468",
    "addr:street":"W Kingsbridge Road",
    "iso:country":"US",
    "sg:address":"131 W Kingsbridge Road",
    "sg:city":"Bronx",
    "sg:classifiers":[
        {
            "category":"Restaurant",
            "type":"Food & Drink"
        }
    ],
    "sg:phone":"+1 718 549 0050",
    "sg:postcode":"10468",
    "sg:province":"NY",
    "sg:tags":[
        "pizza"
    ],
    "sg:website":"www.kingspizza.com",
    "wof:name":"King's Pizza",
    "wof:placetype":"venue"
},
  "geometry": {"coordinates":[-73.90316300000001,40.869144],"type":"Point"}
}