{
  "type": "Feature",
  "properties": {
    "iso:country":"US",
    "sg:address":"4 Preston St",
    "sg:city":"Port Washington",
    "sg:classifiers":[
        {
            "category":"Professional",
            "subcategory":"Computer Services",
            "type":"Services"
        }
    ],
    "sg:phone":"+1 516 883 1930",
    "sg:postcode":"11050",
    "sg:province":"NY",
    "sg:tags":[
        "internet"
    ],
    "wof:name":"Internet Services",
    "wof:placetype":"venue"
},
  "geometry": {"coordinates":[-73.694372,40.827909],"type":"Point"}
}