{
  "type": "Feature",
  "properties": {
    "iso:country":"US",
    "sg:address":"7 North St",
    "sg:city":"Staten Island",
    "sg:classifiers":[
        {
            "category":"Transit Center",
            "subcategory":"Passenger",
            "type":"Transportation"
        }
    ],
    "sg:phone":"+1 718 442 7000",
    "sg:postcode":"10302",
    "sg:province":"NY",
    "sg:website":"www.atlanticexpress.com",
    "wof:name":"Atlantic Express Coachways",
    "wof:placetype":"venue"
},
  "geometry": {"coordinates":[-74.13434100000001,40.641351],"type":"Point"}
}