{
  "type": "Feature",
  "properties": {
    "addr:full":"3874 S Park Ave Buffalo NY 14219",
    "addr:housenumber":"3874",
    "addr:postcode":"14219",
    "addr:street":"S Park Ave",
    "iso:country":"US",
    "sg:address":"3874 S Park Ave",
    "sg:city":"Buffalo",
    "sg:classifiers":[
        {
            "category":"Shopping",
            "subcategory":"Jewelry",
            "type":"Retail Goods"
        }
    ],
    "sg:phone":"+1 716 824 7948",
    "sg:postcode":"14219",
    "sg:province":"NY",
    "sg:tags":[
        "jeweler"
    ],
    "wof:name":"Cal's Jewelry",
    "wof:placetype":"venue"
},
  "geometry": {"coordinates":[-78.82378300000001,42.793106],"type":"Point"}
}