{
  "type": "Feature",
  "properties": {
    "addr:full":"2800 Millersport Hwy Getzville NY 14068",
    "addr:postcode":"2800;14068",
    "addr:street":"Millersport Hwy",
    "iso:country":"US",
    "sg:address":"2800 Millersport Hwy",
    "sg:city":"Getzville",
    "sg:classifiers":[
        {
            "category":"Home & Garden",
            "subcategory":"Building Materials",
            "type":"Retail Goods"
        },
        {
            "category":"Professional",
            "subcategory":"Art Services",
            "type":"Services"
        },
        {
            "category":"Train Station",
            "subcategory":"Rail",
            "type":"Transportation"
        },
        {
            "category":"Building & Trades",
            "subcategory":"Construction",
            "type":"Services"
        }
    ],
    "sg:phone":"+1 716 688 2034",
    "sg:postcode":"14068",
    "sg:province":"NY",
    "sg:tags":[
        "ornamental",
        "fence",
        "work",
        "metal",
        "rails",
        "accessory",
        "railing",
        "contractor",
        "stairway",
        "fence-sales"
    ],
    "sg:website":"http://www.oldutchman.com",
    "wof:name":"Old Dutchman's Wrought Iron Co",
    "wof:placetype":"venue"
},
  "geometry": {"coordinates":[-78.761708,43.02196],"type":"Point"}
}