{
  "type": "Feature",
  "properties": {
    "iso:country":"US",
    "sg:address":"123 Longview Ave",
    "sg:city":"Buffalo",
    "sg:classifiers":[
        {
            "category":"Professional",
            "subcategory":"Business Services",
            "type":"Services"
        }
    ],
    "sg:phone":"+1 716 597 0708",
    "sg:postcode":"14211",
    "sg:province":"NY",
    "sg:tags":[
        "fund",
        "promotion",
        "raising"
    ],
    "wof:name":"4 Brothers Productions LLC",
    "wof:placetype":"venue"
},
  "geometry": {"coordinates":[-78.835351,42.92007],"type":"Point"}
}