{
  "type": "Feature",
  "properties": {
    "addr:full":"38 E 32 St New York NY 10016",
    "addr:housenumber":"38;32",
    "addr:postcode":"10016",
    "addr:street":"E;St",
    "iso:country":"US",
    "sg:address":"38 E 32 St",
    "sg:city":"New York",
    "sg:classifiers":[
        {
            "category":"Retail",
            "subcategory":"Photofinishing",
            "type":"Services"
        }
    ],
    "sg:phone":"+1 212 725 3039",
    "sg:postcode":"10016",
    "sg:province":"NY",
    "sg:tags":[
        "photo",
        "finishing"
    ],
    "wof:name":"Newport International Film",
    "wof:placetype":"venue"
},
  "geometry": {"coordinates":[-73.982519,40.745844],"type":"Point"}
}