{
  "type": "Feature",
  "properties": {
    "addr:full":"2004 Co Rte 1 Oswego NY 13126",
    "addr:housenumber":"2004",
    "addr:postcode":"13126",
    "addr:street":"Co Rte 1",
    "iso:country":"US",
    "sg:address":"2004 Co Rte 1",
    "sg:city":"Oswego",
    "sg:classifiers":[
        {
            "category":"Food & Beverages",
            "subcategory":"Groceries & Convenience Stores",
            "type":"Retail Goods"
        }
    ],
    "sg:phone":"+1 315 343 0950",
    "sg:postcode":"13126",
    "sg:province":"NY",
    "wof:name":"KTM Mini Market",
    "wof:placetype":"venue"
},
  "geometry": {"coordinates":[-76.449319,43.486531],"type":"Point"}
}