{
  "type": "Feature",
  "properties": {
    "iso:country":"US",
    "sg:address":"1 Harloquin Dr",
    "sg:city":"Smithtown",
    "sg:classifiers":[
        {
            "category":"Social Services",
            "subcategory":"Child Care",
            "type":"Services"
        }
    ],
    "sg:phone":"+1   ",
    "sg:postcode":"11787",
    "sg:province":"NY",
    "sg:tags":[
        "day"
    ],
    "wof:name":"Azc Grow With ME Inc",
    "wof:placetype":"venue"
},
  "geometry": {"coordinates":[-73.21035500000001,40.851003],"type":"Point"}
}