{
  "type": "Feature",
  "properties": {
    "addr:full":"342 Knickerbocker Ave Brooklyn NY 11237",
    "addr:housenumber":"342",
    "addr:postcode":"11237",
    "addr:street":"Knickerbocker Ave",
    "iso:country":"US",
    "sg:address":"342 Knickerbocker Ave",
    "sg:city":"Brooklyn",
    "sg:classifiers":[
        {
            "category":"Utilities",
            "subcategory":"Mobile Phone",
            "type":"Services"
        }
    ],
    "sg:phone":"+1 718 602 1235",
    "sg:postcode":"11237",
    "sg:province":"NY",
    "sg:tags":[
        "telephone",
        "cellular"
    ],
    "wof:name":"Got Mobile",
    "wof:placetype":"venue"
},
  "geometry": {"coordinates":[-73.921779,40.700693],"type":"Point"}
}