{
  "type": "Feature",
  "properties": {
    "addr:full":"38 Avenue of The Americas New York NY 10013",
    "addr:housenumber":"38",
    "addr:postcode":"10013",
    "addr:street":"Avenue Of The Americas",
    "iso:country":"US",
    "sg:address":"38 Avenue of The Americas",
    "sg:city":"New York",
    "sg:classifiers":[
        {
            "category":"Restaurant",
            "type":"Food & Drink"
        }
    ],
    "sg:menulink":"http://www.allmenus.com/ny/new-york/251578-awash-ethiopian-restaurnt/menu/",
    "sg:phone":"+1 212 982 9589",
    "sg:postcode":"10013",
    "sg:province":"NY",
    "sg:tags":[
        "ethiopian"
    ],
    "wof:name":"Awash Ethiopian Restaurnt",
    "wof:placetype":"venue"
},
  "geometry": {"coordinates":[-74.00526499999999,40.721304],"type":"Point"}
}