{
  "type": "Feature",
  "properties": {
    "iso:country":"US",
    "sg:address":"701 Main St",
    "sg:city":"Port Jefferson",
    "sg:classifiers":[
        {
            "category":"Real Estate",
            "subcategory":"Real Estate Agent",
            "type":"Services"
        }
    ],
    "sg:phone":"+1 631 473 4666",
    "sg:postcode":"11777",
    "sg:province":"NY",
    "wof:name":"Rankin Realty Co Inc",
    "wof:placetype":"venue"
},
  "geometry": {"coordinates":[-73.066744,40.943048],"type":"Point"}
}