{
  "type": "Feature",
  "properties": {
    "iso:country":"US",
    "sg:address":"94 Demars Blvd",
    "sg:city":"Tupper Lake",
    "sg:classifiers":[
        {
            "category":"Shopping",
            "subcategory":"Pharmacy",
            "type":"Retail Goods"
        }
    ],
    "sg:phone":"+1   ",
    "sg:postcode":"12986",
    "sg:province":"NY",
    "sg:tags":[
        "drug",
        "store"
    ],
    "wof:name":"Kinney Drug 39",
    "wof:placetype":"venue"
},
  "geometry": {"coordinates":[-74.463212,44.226],"type":"Point"}
}