{
  "type": "Feature",
  "properties": {
    "addr:full":"248 E 167th St Bronx NY 10456",
    "addr:housenumber":"248",
    "addr:postcode":"10456",
    "addr:street":"E 167Th St",
    "iso:country":"US",
    "sg:address":"248 E 167th St",
    "sg:city":"Bronx",
    "sg:classifiers":[
        {
            "category":"Cinema",
            "subcategory":"Movie Rental",
            "type":"Entertainment"
        }
    ],
    "sg:phone":"+1   ",
    "sg:postcode":"10456",
    "sg:province":"NY",
    "sg:tags":[
        "video",
        "tape"
    ],
    "wof:name":"Eric Beepers & Cellulars Corp",
    "wof:placetype":"venue"
},
  "geometry": {"coordinates":[-73.915857,40.833839],"type":"Point"}
}