{
  "type": "Feature",
  "properties": {
    "addr:full":"1462 E 10th St Brooklyn NY 11230",
    "addr:housenumber":"1462",
    "addr:postcode":"11230",
    "addr:street":"E 10Th St",
    "iso:country":"US",
    "sg:address":"1462 E 10th St",
    "sg:city":"Brooklyn",
    "sg:classifiers":[
        {
            "category":"Organizations",
            "subcategory":"Professional Association",
            "type":"Services"
        }
    ],
    "sg:phone":"+1   ",
    "sg:postcode":"11230",
    "sg:province":"NY",
    "sg:tags":[
        "business"
    ],
    "wof:name":"Construction For Commerce Inc",
    "wof:placetype":"venue"
},
  "geometry": {"coordinates":[-73.964169,40.614105],"type":"Point"}
}