{
  "type": "Feature",
  "properties": {
    "addr:full":"1026 Ave of the Americas New York NY 10018",
    "addr:housenumber":"1026",
    "addr:postcode":"10018",
    "addr:street":"Ave Of The Americas",
    "iso:country":"US",
    "sg:address":"1026 Ave of the Americas",
    "sg:city":"New York",
    "sg:classifiers":[
        {
            "category":"Shopping",
            "type":"Retail Goods"
        }
    ],
    "sg:phone":"+1   ",
    "sg:postcode":"10018",
    "sg:province":"NY",
    "sg:tags":[
        "merchandise"
    ],
    "wof:name":"Michael J Schumacher",
    "wof:placetype":"venue"
},
  "geometry": {"coordinates":[-73.985539,40.752692],"type":"Point"}
}