{
  "type": "Feature",
  "properties": {
    "iso:country":"US",
    "sg:address":"153 E 53 St",
    "sg:city":"New York",
    "sg:classifiers":[
        {
            "category":"Restaurant",
            "type":"Food & Drink"
        }
    ],
    "sg:phone":"+1 212 751 0575",
    "sg:postcode":"10022",
    "sg:province":"NY",
    "wof:name":"Cucina Restaurant",
    "wof:placetype":"venue"
},
  "geometry": {"coordinates":[-73.96969799999999,40.757955],"type":"Point"}
}