{
  "type": "Feature",
  "properties": {
    "addr:full":"6915 Austin St Forest Hills NY 11375",
    "addr:housenumber":"6915",
    "addr:postcode":"11375",
    "addr:street":"Austin St",
    "iso:country":"US",
    "sg:address":"6915 Austin St",
    "sg:city":"Forest Hills",
    "sg:classifiers":[
        {
            "category":"Health Services",
            "subcategory":"Chiropractor",
            "type":"Services"
        }
    ],
    "sg:phone":"+1 718 896 3113",
    "sg:postcode":"11375",
    "sg:province":"NY",
    "wof:name":"Lambert Ronald J Dr",
    "wof:placetype":"venue"
},
  "geometry": {"coordinates":[-73.84886899999999,40.721718],"type":"Point"}
}