{
  "type": "Feature",
  "properties": {
    "addr:full":"550 Center Rd Buffalo NY 14224",
    "addr:housenumber":"550",
    "addr:postcode":"14224",
    "addr:street":"Center Rd",
    "iso:country":"US",
    "sg:address":"550 Center Rd",
    "sg:city":"Buffalo",
    "sg:classifiers":[
        {
            "category":"Health Services",
            "subcategory":"Doctor",
            "type":"Services"
        }
    ],
    "sg:phone":"+1   ",
    "sg:postcode":"14224",
    "sg:province":"NY",
    "sg:tags":[
        "medical"
    ],
    "wof:name":"F K Augustine MD",
    "wof:placetype":"venue"
},
  "geometry": {"coordinates":[-78.761844,42.83956],"type":"Point"}
}