{
  "type": "Feature",
  "properties": {
    "addr:full":"13625 Maple Avenue Flushing NY 11355",
    "addr:housenumber":"13625",
    "addr:postcode":"11355",
    "addr:street":"Maple Avenue",
    "iso:country":"US",
    "sg:address":"13625 Maple Avenue",
    "sg:city":"Flushing",
    "sg:classifiers":[
        {
            "category":"Health Services",
            "subcategory":"Dentist",
            "type":"Services"
        }
    ],
    "sg:phone":"+1 718 961 1234",
    "sg:postcode":"11355",
    "sg:province":"NY",
    "wof:name":"Hsieh Pofu DDS",
    "wof:placetype":"venue"
},
  "geometry": {"coordinates":[-73.826722,40.756012],"type":"Point"}
}