{
  "type": "Feature",
  "properties": {
    "iso:country":"US",
    "sg:address":"81 Salem Ridge Dr",
    "sg:city":"Huntington",
    "sg:classifiers":[
        {
            "category":"Wholesale",
            "subcategory":"Toys & Hobbies",
            "type":"Manufacturing & Wholesale Goods"
        }
    ],
    "sg:phone":"+1 212 929 0040",
    "sg:postcode":"11743",
    "sg:province":"NY",
    "sg:tags":[
        "supply"
    ],
    "wof:name":"Lamor Corp",
    "wof:placetype":"venue"
},
  "geometry": {"coordinates":[-73.380174,40.881211],"type":"Point"}
}