{
  "type": "Feature",
  "properties": {
    "iso:country":"US",
    "sg:address":"1910 Seneca St",
    "sg:city":"Buffalo",
    "sg:classifiers":[
        {
            "category":"Social Services",
            "type":"Services"
        }
    ],
    "sg:phone":"+1 716 822 8017",
    "sg:postcode":"14210",
    "sg:province":"NY",
    "wof:name":"Franciscan Center Inc",
    "wof:placetype":"venue"
},
  "geometry": {"coordinates":[-78.81366,42.858829],"type":"Point"}
}