{
  "type": "Feature",
  "properties": {
    "addr:full":"189 Michigan Hollow Rd Spencer NY 14883",
    "addr:housenumber":"189",
    "addr:postcode":"14883",
    "addr:street":"Michigan Hollow Rd",
    "iso:country":"US",
    "sg:address":"189 Michigan Hollow Rd",
    "sg:city":"Spencer",
    "sg:classifiers":[
        {
            "category":"Retail",
            "subcategory":"Repair Shop",
            "type":"Services"
        }
    ],
    "sg:phone":"+1 607 589 4971",
    "sg:postcode":"14883",
    "sg:province":"NY",
    "sg:tags":[
        "related"
    ],
    "wof:name":"Jerry Olaf Enterprize",
    "wof:placetype":"venue"
},
  "geometry": {"coordinates":[-76.50383100000001,42.261094],"type":"Point"}
}