{
  "type": "Feature",
  "properties": {
    "iso:country":"US",
    "sg:address":"20 Bryant Ave",
    "sg:city":"Roslyn",
    "sg:classifiers":[
        {
            "category":"Freight",
            "type":"Transportation"
        },
        {
            "category":"Wholesale",
            "subcategory":"Farm Supplies",
            "type":"Manufacturing & Wholesale Goods"
        }
    ],
    "sg:phone":"+1 516 625 2683",
    "sg:postcode":"11576",
    "sg:province":"NY",
    "sg:tags":[
        "health",
        "product",
        "domestic",
        "animal",
        "foreign"
    ],
    "wof:name":"World Wide Pet Transport Ltd",
    "wof:placetype":"venue"
},
  "geometry": {"coordinates":[-73.646586,40.803753],"type":"Point"}
}