{
  "type": "Feature",
  "properties": {
    "addr:full":"150 Greaves Ln Staten Island NY 10308",
    "addr:housenumber":"150",
    "addr:postcode":"10308",
    "addr:street":"Greaves Ln",
    "iso:country":"US",
    "sg:address":"150 Greaves Ln",
    "sg:city":"Staten Island",
    "sg:classifiers":[
        {
            "category":"Banks & Credit Unions",
            "subcategory":"Investment Brokerage",
            "type":"Services"
        }
    ],
    "sg:phone":"+1 718 494 0046",
    "sg:postcode":"10308",
    "sg:province":"NY",
    "sg:tags":[
        "consultant",
        "planning",
        "financial"
    ],
    "wof:name":"AIG Royal Alliance",
    "wof:placetype":"venue"
},
  "geometry": {"coordinates":[-74.142048,40.554123],"type":"Point"}
}