{
  "type": "Feature",
  "properties": {
    "addr:full":"420 E 61st St New York NY 10065",
    "addr:housenumber":"420",
    "addr:postcode":"10065",
    "addr:street":"E 61St St",
    "iso:country":"US",
    "sg:address":"420 E 61st St",
    "sg:city":"New York",
    "sg:classifiers":[
        {
            "category":"Professional",
            "subcategory":"Secretarial Services",
            "type":"Services"
        }
    ],
    "sg:phone":"+1   ",
    "sg:postcode":"10065",
    "sg:province":"NY",
    "sg:tags":[
        "reporting"
    ],
    "wof:name":"Tsg Reporting",
    "wof:placetype":"venue"
},
  "geometry": {"coordinates":[-73.959194,40.76004],"type":"Point"}
}