{
  "type": "Feature",
  "properties": {
    "iso:country":"US",
    "sg:address":"247 W 38th St",
    "sg:city":"New York",
    "sg:classifiers":[
        {
            "category":"Arts & Performance",
            "subcategory":"Theater",
            "type":"Entertainment"
        }
    ],
    "sg:phone":"+1 212 929 2339",
    "sg:postcode":"10018",
    "sg:province":"NY",
    "sg:tags":[
        "talent",
        "agency",
        "casting"
    ],
    "wof:name":"Charles Rosen Casting Inc",
    "wof:placetype":"venue"
},
  "geometry": {"coordinates":[-73.990585,40.754213],"type":"Point"}
}