{
  "type": "Feature",
  "properties": {
    "iso:country":"US",
    "sg:address":"1835 Maple Rd Ste 1",
    "sg:city":"Buffalo",
    "sg:classifiers":[
        {
            "category":"Health Services",
            "subcategory":"Doctor",
            "type":"Services"
        }
    ],
    "sg:phone":"+1 716 634 5410",
    "sg:postcode":"14221",
    "sg:province":"NY",
    "sg:tags":[
        "medicine",
        "physician",
        "surgeon",
        "internal",
        "surgeons"
    ],
    "wof:name":"William Hartrich Md",
    "wof:placetype":"venue"
},
  "geometry": {"coordinates":[-78.718976,42.991015],"type":"Point"}
}