{
  "type": "Feature",
  "properties": {
    "iso:country":"US",
    "sg:address":"10622 Guy R Brewer Blvd",
    "sg:city":"Jamaica",
    "sg:classifiers":[
        {
            "category":"Shopping",
            "subcategory":"Crafts & Fabrics",
            "type":"Retail Goods"
        }
    ],
    "sg:phone":"+1 718 526 3987",
    "sg:postcode":"11433",
    "sg:province":"NY",
    "sg:tags":[
        "art"
    ],
    "wof:name":"Hallie's Gallery",
    "wof:placetype":"venue"
},
  "geometry": {"coordinates":[-73.79345499999999,40.69931],"type":"Point"}
}