{
  "type": "Feature",
  "properties": {
    "addr:full":"259 4th Ave Brooklyn NY 11215",
    "addr:housenumber":"259",
    "addr:postcode":"11215",
    "addr:street":"4Th Ave",
    "iso:country":"US",
    "sg:address":"259 4th Ave",
    "sg:city":"Brooklyn",
    "sg:classifiers":[
        {
            "category":"Building & Trades",
            "subcategory":"Plumbing",
            "type":"Services"
        }
    ],
    "sg:phone":"+1 646 235 8577",
    "sg:postcode":"11215",
    "sg:province":"NY",
    "sg:tags":[
        "conditioning",
        "air",
        "system",
        "contractor"
    ],
    "wof:name":"AAA Hi-Land AC",
    "wof:placetype":"venue"
},
  "geometry": {"coordinates":[-73.983965,40.676016],"type":"Point"}
}