{
  "type": "Feature",
  "properties": {
    "addr:full":"128 Carleton Ave E Islip NY 11751",
    "addr:housenumber":"128",
    "addr:postcode":"11751",
    "addr:street":"Carleton Ave E",
    "iso:country":"US",
    "sg:address":"128 Carleton Ave E",
    "sg:city":"Islip",
    "sg:classifiers":[
        {
            "category":"Communications",
            "subcategory":"Newspaper",
            "type":"Services"
        }
    ],
    "sg:phone":"+1 631 581 1930",
    "sg:postcode":"11751",
    "sg:province":"NY",
    "sg:tags":[
        "print",
        "medium"
    ],
    "wof:name":"New York Jury Verdict",
    "wof:placetype":"venue"
},
  "geometry": {"coordinates":[-73.212997,40.735802],"type":"Point"}
}