{
  "type": "Feature",
  "properties": {
    "addr:full":"111 Crown Point Ln Williamsville NY 14221",
    "addr:housenumber":"111",
    "addr:postcode":"14221",
    "addr:street":"Crown Point Ln",
    "iso:country":"US",
    "sg:address":"111 Crown Point Ln",
    "sg:city":"Williamsville",
    "sg:classifiers":[
        {
            "category":"Building & Trades",
            "subcategory":"Construction",
            "type":"Services"
        }
    ],
    "sg:phone":"+1 716 636 7946",
    "sg:postcode":"14221",
    "sg:province":"NY",
    "sg:tags":[
        "designer",
        "dealer",
        "pool",
        "swimming"
    ],
    "wof:name":"Chapelwood Pool Club Inc",
    "wof:placetype":"venue"
},
  "geometry": {"coordinates":[-78.72383000000001,43.008176],"type":"Point"}
}