{
  "type": "Feature",
  "properties": {
    "iso:country":"US",
    "sg:address":"3881 N Buffalo St",
    "sg:city":"Orchard Park",
    "sg:classifiers":[
        {
            "category":"Professional",
            "subcategory":"Accounting & Tax Preparation",
            "type":"Services"
        }
    ],
    "sg:phone":"+1 716 662 0198",
    "sg:postcode":"14127",
    "sg:province":"NY",
    "sg:tags":[
        "return",
        "filing"
    ],
    "wof:name":"Butzek Tax Svce",
    "wof:placetype":"venue"
},
  "geometry": {"coordinates":[-78.74533700000001,42.775499],"type":"Point"}
}