{
  "type": "Feature",
  "properties": {
    "addr:full":"733 3 Ave New York NY 10017",
    "addr:housenumber":"733",
    "addr:postcode":"10017",
    "addr:street":"3 Ave",
    "iso:country":"US",
    "sg:address":"733 3 Ave",
    "sg:city":"New York",
    "sg:classifiers":[
        {
            "category":"Wholesale",
            "subcategory":"Drugs",
            "type":"Manufacturing & Wholesale Goods"
        }
    ],
    "sg:phone":"+1 212 419 0958",
    "sg:postcode":"10017",
    "sg:province":"NY",
    "sg:tags":[
        "professional",
        "product"
    ],
    "wof:name":"Colomer USA Inc",
    "wof:placetype":"venue"
},
  "geometry": {"coordinates":[-73.974935,40.7501],"type":"Point"}
}