{
  "type": "Feature",
  "properties": {
    "addr:full":"219 Pine Blvd Newark NY 14513",
    "addr:housenumber":"219",
    "addr:postcode":"14513",
    "addr:street":"Pine Blvd",
    "iso:country":"US",
    "sg:address":"219 Pine Blvd",
    "sg:city":"Newark",
    "sg:classifiers":[
        {
            "category":"Shopping",
            "subcategory":"Computers & Home Electronics",
            "type":"Retail Goods"
        }
    ],
    "sg:phone":"+1   ",
    "sg:postcode":"14513",
    "sg:province":"NY",
    "wof:name":"Lone Wolf Computers Inc",
    "wof:placetype":"venue"
},
  "geometry": {"coordinates":[-77.086854,43.039498],"type":"Point"}
}