{
  "type": "Feature",
  "properties": {
    "addr:full":"88 Partition St Saugerties NY 12477",
    "addr:housenumber":"88",
    "addr:postcode":"12477",
    "addr:street":"Partition St",
    "iso:country":"US",
    "sg:address":"88 Partition St",
    "sg:city":"Saugerties",
    "sg:classifiers":[
        {
            "category":"Restaurant",
            "type":"Food & Drink"
        }
    ],
    "sg:phone":"+1   ",
    "sg:postcode":"12477",
    "sg:province":"NY",
    "sg:tags":[
        "eating"
    ],
    "wof:name":"Pantry Cafe Corp",
    "wof:placetype":"venue"
},
  "geometry": {"coordinates":[-73.952365,42.077638],"type":"Point"}
}