{
  "type": "Feature",
  "properties": {
    "iso:country":"US",
    "sg:address":"893 Walton Ave",
    "sg:city":"Bronx",
    "sg:classifiers":[
        {
            "category":"Professional",
            "subcategory":"Business Services",
            "type":"Services"
        }
    ],
    "sg:phone":"+1 718 293 5252",
    "sg:postcode":"10452",
    "sg:province":"NY",
    "sg:tags":[
        "liquidator"
    ],
    "wof:name":"Court House Wine & Liquors",
    "wof:placetype":"venue"
},
  "geometry": {"coordinates":[-73.922526,40.829981],"type":"Point"}
}