{
  "type": "Feature",
  "properties": {
    "iso:country":"US",
    "sg:address":"2213 Indian Neck Ln",
    "sg:city":"Peconic",
    "sg:classifiers":[
        {
            "category":"Health Services",
            "subcategory":"Doctor",
            "type":"Services"
        }
    ],
    "sg:phone":"+1 631 689 5664",
    "sg:postcode":"11958",
    "sg:province":"NY",
    "sg:tags":[
        "medical"
    ],
    "wof:name":"Joanne Woodle MD",
    "wof:placetype":"venue"
},
  "geometry": {"coordinates":[-72.455141,41.031555],"type":"Point"}
}