{
  "type": "Feature",
  "properties": {
    "iso:country":"US",
    "sg:address":"3 Kelmik Dr",
    "sg:city":"Saratoga Springs",
    "sg:classifiers":[
        {
            "category":"Real Estate",
            "subcategory":"Real Estate Agent",
            "type":"Services"
        }
    ],
    "sg:phone":"+1 518 587 2221",
    "sg:postcode":"12866",
    "sg:province":"NY",
    "wof:name":"Jane Ernst",
    "wof:placetype":"venue"
},
  "geometry": {"coordinates":[-73.84621799999999,43.071279],"type":"Point"}
}