{
  "type": "Feature",
  "properties": {
    "addr:full":"6180 Transit Rd Depew NY 14043",
    "addr:housenumber":"6180",
    "addr:postcode":"14043",
    "addr:street":"Transit Rd",
    "iso:country":"US",
    "sg:address":"6180 Transit Rd",
    "sg:city":"Depew",
    "sg:classifiers":[
        {
            "category":"Health Services",
            "subcategory":"Doctor",
            "type":"Services"
        }
    ],
    "sg:phone":"+1   ",
    "sg:postcode":"14043",
    "sg:province":"NY",
    "sg:tags":[
        "dentist"
    ],
    "wof:name":"R A Brunea DDS",
    "wof:placetype":"venue"
},
  "geometry": {"coordinates":[-78.696912,42.923829],"type":"Point"}
}