{
  "type": "Feature",
  "properties": {
    "addr:full":"2410 Co Rd 47 Winthrop NY 13697",
    "addr:housenumber":"2410;47",
    "addr:postcode":"13697",
    "addr:street":"Co Rd",
    "iso:country":"US",
    "sg:address":"2410 Co Rd 47",
    "sg:city":"Winthrop",
    "sg:classifiers":[
        {
            "category":"Manufacturing",
            "subcategory":"Wood Products",
            "type":"Manufacturing & Wholesale Goods"
        }
    ],
    "sg:phone":"+1   ",
    "sg:postcode":"13697",
    "sg:province":"NY",
    "sg:tags":[
        "mfg"
    ],
    "wof:name":"Lanpher Cedar Products",
    "wof:placetype":"venue"
},
  "geometry": {"coordinates":[-74.893815,44.761379],"type":"Point"}
}