{
  "type": "Feature",
  "properties": {
    "iso:country":"US",
    "sg:address":"17 Collins Pl",
    "sg:city":"Albany",
    "sg:classifiers":[
        {
            "category":"Food & Beverages",
            "subcategory":"Groceries & Convenience Stores",
            "type":"Retail Goods"
        }
    ],
    "sg:phone":"+1   ",
    "sg:postcode":"12208",
    "sg:province":"NY",
    "wof:name":"V & D Grocery",
    "wof:placetype":"venue"
},
  "geometry": {"coordinates":[-73.814823,42.656538],"type":"Point"}
}