{
  "type": "Feature",
  "properties": {
    "addr:full":"238 Route 9W Haverstraw NY 10927",
    "addr:housenumber":"238",
    "addr:postcode":"10927",
    "addr:street":"Route 9W",
    "iso:country":"US",
    "sg:address":"238 Route 9W",
    "sg:city":"Haverstraw",
    "sg:classifiers":[
        {
            "category":"Professional",
            "subcategory":"Accounting & Tax Preparation",
            "type":"Services"
        },
        {
            "category":"Banks & Credit Unions",
            "subcategory":"Financial Services",
            "type":"Services"
        }
    ],
    "sg:phone":"+1 845 947 1068",
    "sg:postcode":"10927",
    "sg:province":"NY",
    "sg:tags":[
        "return",
        "preparation-business",
        "taxes-consultants",
        "loan",
        "reporting",
        "representative",
        "alternative",
        "bookkeeping"
    ],
    "sg:website":"http://www.hrblock.com",
    "wof:name":"H&R Block",
    "wof:placetype":"venue"
},
  "geometry": {"coordinates":[-73.98336,41.200768],"type":"Point"}
}