{
  "type": "Feature",
  "properties": {
    "addr:full":"602 Winsor Ave Elmira NY 14905",
    "addr:housenumber":"602",
    "addr:postcode":"14905",
    "addr:street":"Winsor Ave",
    "iso:country":"US",
    "sg:address":"602 Winsor Ave",
    "sg:city":"Elmira",
    "sg:classifiers":[
        {
            "category":"Professional",
            "subcategory":"Detective & Security Services",
            "type":"Services"
        }
    ],
    "sg:phone":"+1 607 733 3563",
    "sg:postcode":"14905",
    "sg:province":"NY",
    "sg:tags":[
        "information",
        "bureau"
    ],
    "wof:name":"Mensch's Tax Service",
    "wof:placetype":"venue"
},
  "geometry": {"coordinates":[-76.818376,42.083699],"type":"Point"}
}