{
  "type": "Feature",
  "properties": {
    "addr:full":"775 Flynn Rd Rochester NY 14612",
    "addr:housenumber":"775",
    "addr:postcode":"14612",
    "addr:street":"Flynn Rd",
    "iso:country":"US",
    "sg:address":"775 Flynn Rd",
    "sg:city":"Rochester",
    "sg:classifiers":[
        {
            "category":"Building & Trades",
            "subcategory":"Landscaping Services",
            "type":"Services"
        }
    ],
    "sg:phone":"+1 585 530 9567",
    "sg:postcode":"14612",
    "sg:province":"NY",
    "sg:tags":[
        "landscape",
        "contractor"
    ],
    "wof:name":"Curb Appeal",
    "wof:placetype":"venue"
},
  "geometry": {"coordinates":[-77.714996,43.273327],"type":"Point"}
}