{
  "type": "Feature",
  "properties": {
    "addr:full":"23 Main St Oakfield NY 14125",
    "addr:housenumber":"23",
    "addr:postcode":"14125",
    "addr:street":"Main St",
    "iso:country":"US",
    "sg:address":"23 Main St",
    "sg:city":"Oakfield",
    "sg:classifiers":[
        {
            "category":"Manufacturing",
            "subcategory":"Toys & Sporting Goods",
            "type":"Manufacturing & Wholesale Goods"
        }
    ],
    "sg:phone":"+1   ",
    "sg:postcode":"14125",
    "sg:province":"NY",
    "sg:tags":[
        "mfg"
    ],
    "wof:name":"Country Come Home",
    "wof:placetype":"venue"
},
  "geometry": {"coordinates":[-78.272904,43.067952],"type":"Point"}
}