{
  "type": "Feature",
  "properties": {
    "iso:country":"US",
    "sg:address":"322 E Main St",
    "sg:city":"Bay Shore",
    "sg:classifiers":[
        {
            "category":"Health Services",
            "subcategory":"Medical Lab",
            "type":"Services"
        }
    ],
    "sg:phone":"+1 631 969 0215",
    "sg:postcode":"11706",
    "sg:province":"NY",
    "sg:tags":[
        "laboratory"
    ],
    "wof:name":"Sunrise Medical Labs Inc",
    "wof:placetype":"venue"
},
  "geometry": {"coordinates":[-73.23948300000001,40.725111],"type":"Point"}
}