{
  "type": "Feature",
  "properties": {
    "addr:full":"1418 3rd Ave Frnt New York NY 10028",
    "addr:housenumber":"1418",
    "addr:postcode":"10028",
    "addr:street":"3Rd Ave",
    "iso:country":"US",
    "sg:address":"1418 3rd Ave Frnt",
    "sg:city":"New York",
    "sg:classifiers":[
        {
            "category":"Restaurant",
            "type":"Food & Drink"
        }
    ],
    "sg:phone":"+1 212 794 1080",
    "sg:postcode":"10028",
    "sg:province":"NY",
    "wof:name":"Lorenzo & Marias Kitchen",
    "wof:placetype":"venue"
},
  "geometry": {"coordinates":[-73.956596,40.7752],"type":"Point"}
}