{
  "type": "Feature",
  "properties": {
    "addr:full":"139 Oceanview Pl Staten Island NY 10308",
    "addr:housenumber":"139",
    "addr:postcode":"10308",
    "addr:street":"Oceanview Pl",
    "iso:country":"US",
    "sg:address":"139 Oceanview Pl",
    "sg:city":"Staten Island",
    "sg:classifiers":[
        {
            "category":"Wholesale",
            "subcategory":"Electrical",
            "type":"Manufacturing & Wholesale Goods"
        }
    ],
    "sg:phone":"+1 718 605 2222",
    "sg:postcode":"10308",
    "sg:province":"NY",
    "sg:tags":[
        "alarm",
        "burglar",
        "system"
    ],
    "wof:name":"MPG Security",
    "wof:placetype":"venue"
},
  "geometry": {"coordinates":[-74.15373599999999,40.541557],"type":"Point"}
}