{
  "type": "Feature",
  "properties": {
    "addr:full":"330 Manida Street Bronx NY 10474",
    "addr:housenumber":"330",
    "addr:postcode":"10474",
    "addr:street":"Manida Street",
    "iso:country":"US",
    "sg:address":"330 Manida Street",
    "sg:city":"Bronx",
    "sg:classifiers":[
        {
            "category":"Restaurant",
            "type":"Food & Drink"
        },
        {
            "category":"Food & Beverages",
            "subcategory":"Meat & Fish",
            "type":"Retail Goods"
        }
    ],
    "sg:phone":"+1 718 893 9411",
    "sg:postcode":"10474",
    "sg:province":"NY",
    "sg:tags":[
        "seafood",
        "market"
    ],
    "wof:name":"Maritime Fish Prod",
    "wof:placetype":"venue"
},
  "geometry": {"coordinates":[-73.886557,40.808107],"type":"Point"}
}