{
  "type": "Feature",
  "properties": {
    "iso:country":"US",
    "sg:address":"405 N Madison Ave",
    "sg:city":"Watkins Glen",
    "sg:classifiers":[
        {
            "category":"Government",
            "subcategory":"Office",
            "type":"Public Place"
        }
    ],
    "sg:phone":"+1 607 535 7935",
    "sg:postcode":"14891",
    "sg:province":"NY",
    "sg:tags":[
        "general"
    ],
    "wof:name":"Watkins Glen Electric Dept",
    "wof:placetype":"venue"
},
  "geometry": {"coordinates":[-76.877227,42.385827],"type":"Point"}
}