{
  "type": "Feature",
  "properties": {
    "addr:full":"55 W 45th St Frnt New York NY 10036",
    "addr:housenumber":"55",
    "addr:postcode":"10036",
    "addr:street":"W 45Th St",
    "iso:country":"US",
    "sg:address":"55 W 45th St Frnt",
    "sg:city":"New York",
    "sg:classifiers":[
        {
            "category":"Professional",
            "subcategory":"Printing & Photocopies",
            "type":"Services"
        }
    ],
    "sg:phone":"+1 212 221 1190",
    "sg:postcode":"10036",
    "sg:province":"NY",
    "sg:website":"www.marcophotoservice.com",
    "wof:name":"Marco Photo Service Inc",
    "wof:placetype":"venue"
},
  "geometry": {"coordinates":[-73.99099699999999,40.7607],"type":"Point"}
}