{
  "type": "Feature",
  "properties": {
    "iso:country":"US",
    "sg:address":"13 Xavier Dr",
    "sg:city":"Yonkers",
    "sg:classifiers":[
        {
            "category":"Retail",
            "subcategory":"Photofinishing",
            "type":"Services"
        }
    ],
    "sg:phone":"+1   ",
    "sg:postcode":"10704",
    "sg:province":"NY",
    "sg:tags":[
        "laboratory"
    ],
    "wof:name":"Cross County Photo Express",
    "wof:placetype":"venue"
},
  "geometry": {"coordinates":[-73.852107,40.929411],"type":"Point"}
}