{
  "type": "Feature",
  "properties": {
    "addr:full":"1257 Niagara Falls Blvd Buffalo NY 14226",
    "addr:housenumber":"1257",
    "addr:postcode":"14226",
    "addr:street":"Niagara Falls Blvd",
    "iso:country":"US",
    "sg:address":"1257 Niagara Falls Blvd",
    "sg:city":"Buffalo",
    "sg:classifiers":[
        {
            "category":"Shopping",
            "subcategory":"Clothing, Apparel, & Fashions",
            "type":"Retail Goods"
        }
    ],
    "sg:phone":"+1 716 836 0622",
    "sg:postcode":"14226",
    "sg:province":"NY",
    "sg:tags":[
        "infant",
        "wear"
    ],
    "sg:website":"www.gymboree.com",
    "wof:name":"Gymboree",
    "wof:placetype":"venue"
},
  "geometry": {"coordinates":[-78.822535,42.988933],"type":"Point"}
}