{
  "type": "Feature",
  "properties": {
    "addr:full":"571 N Main St Brewster NY 10509",
    "addr:housenumber":"571",
    "addr:postcode":"10509",
    "addr:street":"N Main St",
    "iso:country":"US",
    "sg:address":"571 N Main St",
    "sg:city":"Brewster",
    "sg:classifiers":[
        {
            "category":"Manufacturing",
            "subcategory":"Signs",
            "type":"Manufacturing & Wholesale Goods"
        }
    ],
    "sg:phone":"+1   ",
    "sg:postcode":"10509",
    "sg:province":"NY",
    "sg:tags":[
        "specialty",
        "mfg"
    ],
    "wof:name":"Design-A-Sign",
    "wof:placetype":"venue"
},
  "geometry": {"coordinates":[-73.61827099999999,41.402736],"type":"Point"}
}