{
  "type": "Feature",
  "properties": {
    "addr:full":"4062 Main St Williamson NY 14589",
    "addr:housenumber":"4062",
    "addr:postcode":"14589",
    "addr:street":"Main St",
    "iso:country":"US",
    "sg:address":"4062 Main St",
    "sg:city":"Williamson",
    "sg:classifiers":[
        {
            "category":"Insurance",
            "subcategory":"Insurance Agent",
            "type":"Services"
        }
    ],
    "sg:phone":"+1 315 589 8429",
    "sg:postcode":"14589",
    "sg:province":"NY",
    "wof:name":"Farm Family Insurance Co",
    "wof:placetype":"venue"
},
  "geometry": {"coordinates":[-77.186313,43.223845],"type":"Point"}
}