{
  "type": "Feature",
  "properties": {
    "addr:full":"252 Union Ave Harrison NY 10528",
    "addr:housenumber":"252",
    "addr:postcode":"10528",
    "addr:street":"Union Ave",
    "iso:country":"US",
    "sg:address":"252 Union Ave",
    "sg:city":"Harrison",
    "sg:classifiers":[
        {
            "category":"Professional",
            "subcategory":"Business Services",
            "type":"Services"
        }
    ],
    "sg:phone":"+1 914 777 2910",
    "sg:postcode":"10528",
    "sg:province":"NY",
    "sg:tags":[
        "recording",
        "studio"
    ],
    "wof:name":"Melon Records",
    "wof:placetype":"venue"
},
  "geometry": {"coordinates":[-73.74059200000001,40.980833],"type":"Point"}
}