{
  "type": "Feature",
  "properties": {
    "addr:full":"224 Harrison St Syracuse NY 13202",
    "addr:housenumber":"224",
    "addr:postcode":"13202",
    "addr:street":"Harrison St",
    "iso:country":"US",
    "sg:address":"224 Harrison St",
    "sg:city":"Syracuse",
    "sg:classifiers":[
        {
            "category":"Social Services",
            "type":"Services"
        }
    ],
    "sg:phone":"+1 315 428 9034",
    "sg:postcode":"13202",
    "sg:province":"NY",
    "sg:tags":[
        "counseling"
    ],
    "wof:name":"Christian Based Counseling Svc",
    "wof:placetype":"venue"
},
  "geometry": {"coordinates":[-76.148915,43.0442],"type":"Point"}
}