{
  "type": "Feature",
  "properties": {
    "addr:full":"2107 Beverly Rd Brooklyn NY 11226",
    "addr:housenumber":"2107",
    "addr:postcode":"11226",
    "addr:street":"Beverly Rd",
    "iso:country":"US",
    "sg:address":"2107 Beverly Rd",
    "sg:city":"Brooklyn",
    "sg:classifiers":[
        {
            "category":"Building & Trades",
            "subcategory":"Construction",
            "type":"Services"
        }
    ],
    "sg:phone":"+1 718 703 1938",
    "sg:postcode":"11226",
    "sg:province":"NY",
    "sg:tags":[
        "general",
        "contractor"
    ],
    "wof:name":"Uddin Construction",
    "wof:placetype":"venue"
},
  "geometry": {"coordinates":[-73.958214,40.645118],"type":"Point"}
}