{
  "type": "Feature",
  "properties": {
    "iso:country":"US",
    "sg:address":"4269 Albany Post Rd",
    "sg:city":"Hyde Park",
    "sg:classifiers":[
        {
            "category":"Manufacturing",
            "subcategory":"Food",
            "type":"Manufacturing & Wholesale Goods"
        }
    ],
    "sg:phone":"+1   ",
    "sg:postcode":"12538",
    "sg:province":"NY",
    "sg:tags":[
        "product",
        "mfg"
    ],
    "wof:name":"Dunkin Donuts",
    "wof:placetype":"venue"
},
  "geometry": {"coordinates":[-73.934729,41.788343],"type":"Point"}
}