{
  "type": "Feature",
  "properties": {
    "iso:country":"US",
    "sg:address":"8723 4th Ave",
    "sg:city":"Brooklyn",
    "sg:classifiers":[
        {
            "category":"Organizations",
            "subcategory":"Professional Association",
            "type":"Services"
        }
    ],
    "sg:phone":"+1 718 833 2526",
    "sg:postcode":"11209",
    "sg:province":"NY",
    "wof:name":"Arab Americanhuman Rights Assn",
    "wof:placetype":"venue"
},
  "geometry": {"coordinates":[-74.028811,40.621514],"type":"Point"}
}