{
  "type": "Feature",
  "properties": {
    "addr:full":"8 Elm St New Canaan NY 06840",
    "addr:housenumber":"8",
    "addr:postcode":"06840",
    "addr:street":"Elm St",
    "iso:country":"US",
    "sg:address":"8 Elm St",
    "sg:city":"New Canaan",
    "sg:classifiers":[
        {
            "category":"Shopping",
            "subcategory":"Clothing, Apparel, & Fashions",
            "type":"Retail Goods"
        }
    ],
    "sg:phone":"+1 203 966 9961",
    "sg:postcode":"06840",
    "sg:province":"NY",
    "sg:tags":[
        "handbag",
        "leather",
        "belt",
        "jewelry",
        "luggage"
    ],
    "wof:name":"Taylors Luggage Inc",
    "wof:placetype":"venue"
},
  "geometry": {"coordinates":[-73.493202,41.146839],"type":"Point"}
}