{
  "type": "Feature",
  "properties": {
    "addr:full":"136 Main Rd Amagansett NY 11901",
    "addr:housenumber":"136",
    "addr:postcode":"11901",
    "addr:street":"Main Rd",
    "iso:country":"US",
    "sg:address":"136 Main Rd",
    "sg:city":"Amagansett",
    "sg:classifiers":[
        {
            "category":"Shopping",
            "subcategory":"Clothing, Apparel, & Fashions",
            "type":"Retail Goods"
        }
    ],
    "sg:phone":"+1 631 267 3627",
    "sg:postcode":"11901",
    "sg:province":"NY",
    "sg:tags":[
        "item",
        "boutique"
    ],
    "wof:name":"Crazy Monkey",
    "wof:placetype":"venue"
},
  "geometry": {"coordinates":[-72.621145,40.946582],"type":"Point"}
}