{
  "type": "Feature",
  "properties": {
    "addr:full":"14 Horatio St New York NY 10014",
    "addr:housenumber":"14",
    "addr:postcode":"10014",
    "addr:street":"Horatio St",
    "iso:country":"US",
    "sg:address":"14 Horatio St",
    "sg:city":"New York",
    "sg:classifiers":[
        {
            "category":"Real Estate",
            "subcategory":"Real Estate Operator",
            "type":"Services"
        }
    ],
    "sg:phone":"+1 212 989 8568",
    "sg:postcode":"10014",
    "sg:province":"NY",
    "sg:tags":[
        "building",
        "apartment"
    ],
    "wof:name":"Vangogh Apts",
    "wof:placetype":"venue"
},
  "geometry": {"coordinates":[-74.003197,40.738701],"type":"Point"}
}