{
  "type": "Feature",
  "properties": {
    "addr:full":"1425 Park Ave New Hyde Park NY 11040",
    "addr:housenumber":"1425",
    "addr:postcode":"11040",
    "addr:street":"Park Ave",
    "iso:country":"US",
    "sg:address":"1425 Park Ave",
    "sg:city":"New Hyde Park",
    "sg:classifiers":[
        {
            "category":"Health Services",
            "subcategory":"Doctor",
            "type":"Services"
        }
    ],
    "sg:phone":"+1 516 352 4957",
    "sg:postcode":"11040",
    "sg:province":"NY",
    "sg:tags":[
        "dentist"
    ],
    "wof:name":"Frederick Marion DDS",
    "wof:placetype":"venue"
},
  "geometry": {"coordinates":[-73.681192,40.734957],"type":"Point"}
}