{
  "type": "Feature",
  "properties": {
    "iso:country":"US",
    "sg:address":"3295 Lake To Lake Rd",
    "sg:city":"Stanley",
    "sg:classifiers":[
        {
            "category":"Building & Trades",
            "subcategory":"Electrical",
            "type":"Services"
        }
    ],
    "sg:phone":"+1 585 526 7011",
    "sg:postcode":"14561",
    "sg:province":"NY",
    "sg:tags":[
        "electric",
        "contractor"
    ],
    "wof:name":"John D Burnett",
    "wof:placetype":"venue"
},
  "geometry": {"coordinates":[-77.170886,42.811023],"type":"Point"}
}