{
  "type": "Feature",
  "properties": {
    "addr:full":"65 Emerson Pl Brooklyn NY 11205",
    "addr:housenumber":"65",
    "addr:postcode":"11205",
    "addr:street":"Emerson Pl",
    "iso:country":"US",
    "sg:address":"65 Emerson Pl",
    "sg:city":"Brooklyn",
    "sg:classifiers":[
        {
            "category":"Wholesale",
            "subcategory":"Scrap",
            "type":"Manufacturing & Wholesale Goods"
        }
    ],
    "sg:phone":"+1 718 622 1799",
    "sg:postcode":"11205",
    "sg:province":"NY",
    "sg:tags":[
        "recycling",
        "center"
    ],
    "wof:name":"Emerson Recycling Corp",
    "wof:placetype":"venue"
},
  "geometry": {"coordinates":[-73.96217900000001,40.694158],"type":"Point"}
}