{
  "type": "Feature",
  "properties": {
    "addr:full":"28 Potter Ave New Rochelle NY 10801",
    "addr:housenumber":"28",
    "addr:postcode":"10801",
    "addr:street":"Potter Ave",
    "iso:country":"US",
    "sg:address":"28 Potter Ave",
    "sg:city":"New Rochelle",
    "sg:classifiers":[
        {
            "category":"Building & Trades",
            "subcategory":"Construction",
            "type":"Services"
        }
    ],
    "sg:phone":"+1 914 633 7799",
    "sg:postcode":"10801",
    "sg:province":"NY",
    "sg:tags":[
        "maker",
        "cabinet"
    ],
    "wof:name":"Ger Industries",
    "wof:placetype":"venue"
},
  "geometry": {"coordinates":[-73.772846,40.927582],"type":"Point"}
}