{
  "type": "Feature",
  "properties": {
    "iso:country":"US",
    "sg:address":"267 Hoosick St",
    "sg:city":"Troy",
    "sg:classifiers":[
        {
            "category":"Social Services",
            "type":"Services"
        }
    ],
    "sg:phone":"+1 518 273 3209",
    "sg:postcode":"12180",
    "sg:province":"NY",
    "sg:tags":[
        "worker"
    ],
    "wof:name":"Catherine Gayron Lcsw",
    "wof:placetype":"venue"
},
  "geometry": {"coordinates":[-73.670678,42.738458],"type":"Point"}
}