{
  "type": "Feature",
  "properties": {
    "addr:full":"140 Charlton Rd Ballston Lake NY 12019",
    "addr:housenumber":"140",
    "addr:postcode":"12019",
    "addr:street":"Charlton Rd",
    "iso:country":"US",
    "sg:address":"140 Charlton Rd",
    "sg:city":"Ballston Lake",
    "sg:classifiers":[
        {
            "category":"Farming",
            "subcategory":"Orchard",
            "type":"Manufacturing & Wholesale Goods"
        }
    ],
    "sg:phone":"+1 518 399 3427",
    "sg:postcode":"12019",
    "sg:province":"NY",
    "sg:tags":[
        "fruit",
        "tree"
    ],
    "wof:name":"Charelton Rd Orchard",
    "wof:placetype":"venue"
},
  "geometry": {"coordinates":[-73.936926,42.904453],"type":"Point"}
}