{
  "type": "Feature",
  "properties": {
    "addr:full":"14 Smart Ave Apt 1 Yonkers NY 10704",
    "addr:housenumber":"14;1",
    "addr:postcode":"10704",
    "addr:street":"Smart Ave Apt",
    "iso:country":"US",
    "sg:address":"14 Smart Ave Apt 1",
    "sg:city":"Yonkers",
    "sg:classifiers":[
        {
            "category":"Health Services",
            "subcategory":"Clinic",
            "type":"Services"
        }
    ],
    "sg:phone":"+1 914 424 8734",
    "sg:postcode":"10704",
    "sg:province":"NY",
    "sg:tags":[
        "welfare"
    ],
    "wof:name":"Designation To Health",
    "wof:placetype":"venue"
},
  "geometry": {"coordinates":[-73.86079700000001,40.933663],"type":"Point"}
}