{
  "type": "Feature",
  "properties": {
    "iso:country":"US",
    "sg:address":"187 Wolf Rd",
    "sg:city":"Albany",
    "sg:classifiers":[
        {
            "category":"Professional",
            "subcategory":"Lawyer & Legal Services",
            "type":"Services"
        }
    ],
    "sg:phone":"+1 518 463 2251",
    "sg:postcode":"12205",
    "sg:province":"NY",
    "wof:name":"DAgostino Hblock Fnnery Jeram",
    "wof:placetype":"venue"
},
  "geometry": {"coordinates":[-73.800769,42.72335],"type":"Point"}
}