{
  "type": "Feature",
  "properties": {
    "iso:country":"US",
    "sg:address":"304 Ditmas Ave",
    "sg:city":"Brooklyn",
    "sg:classifiers":[
        {
            "category":"Food & Beverages",
            "subcategory":"Groceries & Convenience Stores",
            "type":"Retail Goods"
        }
    ],
    "sg:phone":"+1 718 853 8053",
    "sg:postcode":"11218",
    "sg:province":"NY",
    "wof:name":"Krakus Deli",
    "wof:placetype":"venue"
},
  "geometry": {"coordinates":[-73.975899,40.6357],"type":"Point"}
}