{
  "type": "Feature",
  "properties": {
    "iso:country":"US",
    "sg:address":"1340 West Ave",
    "sg:city":"Buffalo",
    "sg:classifiers":[
        {
            "category":"Manufacturing",
            "subcategory":"Tools & Machinery",
            "type":"Manufacturing & Wholesale Goods"
        }
    ],
    "sg:phone":"+1 716 882 5370",
    "sg:postcode":"14213",
    "sg:province":"NY",
    "wof:name":"Metal Binding Inc",
    "wof:placetype":"venue"
},
  "geometry": {"coordinates":[-78.895833,42.926901],"type":"Point"}
}