{
  "type": "Feature",
  "properties": {
    "addr:full":"742 Kirkwood Dr Grand Island NY 14072",
    "addr:housenumber":"742",
    "addr:postcode":"14072",
    "addr:street":"Kirkwood Dr",
    "iso:country":"US",
    "sg:address":"742 Kirkwood Dr",
    "sg:city":"Grand Island",
    "sg:classifiers":[
        {
            "category":"Manufacturing",
            "subcategory":"Food",
            "type":"Manufacturing & Wholesale Goods"
        }
    ],
    "sg:phone":"+1   ",
    "sg:postcode":"14072",
    "sg:province":"NY",
    "sg:tags":[
        "mfg"
    ],
    "wof:name":"Orchids Italian Cookies",
    "wof:placetype":"venue"
},
  "geometry": {"coordinates":[-78.918172,43.048604],"type":"Point"}
}