{
  "type": "Feature",
  "properties": {
    "addr:full":"765 Yonkers Ave Yonkers NY 10704",
    "addr:housenumber":"765",
    "addr:postcode":"10704",
    "addr:street":"Yonkers Ave",
    "iso:country":"US",
    "sg:address":"765 Yonkers Ave",
    "sg:city":"Yonkers",
    "sg:classifiers":[
        {
            "category":"Food & Beverages",
            "subcategory":"Liquor & Beverages",
            "type":"Retail Goods"
        }
    ],
    "sg:phone":"+1 914 965 3200",
    "sg:postcode":"10704",
    "sg:province":"NY",
    "wof:name":"Raceway Wine & Liquor Discount",
    "wof:placetype":"venue"
},
  "geometry": {"coordinates":[-73.86498400000001,40.923395],"type":"Point"}
}