{
  "type": "Feature",
  "properties": {
    "addr:full":"505 Prentice Rd Vestal NY 13850",
    "addr:housenumber":"505",
    "addr:postcode":"13850",
    "addr:street":"Prentice Rd",
    "iso:country":"US",
    "sg:address":"505 Prentice Rd",
    "sg:city":"Vestal",
    "sg:classifiers":[
        {
            "category":"Manufacturing",
            "subcategory":"Metals",
            "type":"Manufacturing & Wholesale Goods"
        }
    ],
    "sg:phone":"+1 607 797 1196",
    "sg:postcode":"13850",
    "sg:province":"NY",
    "sg:tags":[
        "forming"
    ],
    "sg:website":"www.bhvfab.com",
    "wof:name":"Bhv Sheet Metal Fabricators Of",
    "wof:placetype":"venue"
},
  "geometry": {"coordinates":[-75.99094100000001,42.114096],"type":"Point"}
}