{
  "type": "Feature",
  "properties": {
    "addr:full":"1400 Poulson St Wantagh NY 11793",
    "addr:housenumber":"1400",
    "addr:postcode":"11793",
    "addr:street":"Poulson St",
    "iso:country":"US",
    "sg:address":"1400 Poulson St",
    "sg:city":"Wantagh",
    "sg:classifiers":[
        {
            "category":"Organizations",
            "subcategory":"Religious Organization",
            "type":"Services"
        }
    ],
    "sg:phone":"+1 516 221 2515",
    "sg:postcode":"11793",
    "sg:province":"NY",
    "sg:tags":[
        "clergy"
    ],
    "wof:name":"Pual C Cochran",
    "wof:placetype":"venue"
},
  "geometry": {"coordinates":[-73.499863,40.68725],"type":"Point"}
}