{
  "type": "Feature",
  "properties": {
    "addr:full":"13625 37th Ave Flushing NY 11354",
    "addr:housenumber":"13625",
    "addr:postcode":"11354",
    "addr:street":"37Th Ave",
    "iso:country":"US",
    "sg:address":"13625 37th Ave",
    "sg:city":"Flushing",
    "sg:classifiers":[
        {
            "category":"Manufacturing",
            "subcategory":"Buildings",
            "type":"Manufacturing & Wholesale Goods"
        },
        {
            "category":"Building & Trades",
            "subcategory":"Construction",
            "type":"Services"
        }
    ],
    "sg:phone":"+1 718 606 3600",
    "sg:postcode":"11354",
    "sg:province":"NY",
    "sg:tags":[
        "home",
        "builder",
        "road",
        "contractor"
    ],
    "wof:name":"Pavers and Road Builders Benef",
    "wof:placetype":"venue"
},
  "geometry": {"coordinates":[-73.83286699999999,40.760895],"type":"Point"}
}