{
  "type": "Feature",
  "properties": {
    "addr:full":"133 W 19th Street New York NY 10011",
    "addr:housenumber":"133",
    "addr:postcode":"10011",
    "addr:street":"W 19Th Street",
    "iso:country":"US",
    "sg:address":"133 W 19th Street",
    "sg:city":"New York",
    "sg:classifiers":[
        {
            "category":"Arts & Performance",
            "subcategory":"Art Gallery",
            "type":"Entertainment"
        }
    ],
    "sg:phone":"+1 212 989 7870",
    "sg:postcode":"10011",
    "sg:province":"NY",
    "wof:name":"Woo Art",
    "wof:placetype":"venue"
},
  "geometry": {"coordinates":[-73.99557,40.740751],"type":"Point"}
}