{
  "type": "Feature",
  "properties": {
    "iso:country":"US",
    "sg:address":"119 N Park Ave Ste 306",
    "sg:city":"Rockville Centre",
    "sg:classifiers":[
        {
            "category":"Professional",
            "subcategory":"Accounting & Tax Preparation",
            "type":"Services"
        }
    ],
    "sg:phone":"+1 516 536 0824",
    "sg:postcode":"11570",
    "sg:province":"NY",
    "sg:tags":[
        "accountant"
    ],
    "wof:name":"Turkowitz Herbert CPA",
    "wof:placetype":"venue"
},
  "geometry": {"coordinates":[-73.644246,40.660254],"type":"Point"}
}