{
  "type": "Feature",
  "properties": {
    "addr:full":"1843 US Hwy 9 Keeseville NY 12944",
    "addr:housenumber":"1843",
    "addr:postcode":"12944",
    "addr:street":"Us Hwy 9 Keeseville",
    "iso:country":"US",
    "sg:address":"1843 US Hwy 9",
    "sg:city":"Keeseville",
    "sg:classifiers":[
        {
            "category":"Farming",
            "subcategory":"Dairy Farm",
            "type":"Manufacturing & Wholesale Goods"
        }
    ],
    "sg:phone":"+1 518 834 9612",
    "sg:postcode":"12944",
    "sg:province":"NY",
    "wof:name":"Mc Lean's Dairy Bar",
    "wof:placetype":"venue"
},
  "geometry": {"coordinates":[-73.473809,44.51128],"type":"Point"}
}