{
  "type": "Feature",
  "properties": {
    "addr:full":"127 E 46th St New York NY 10017",
    "addr:housenumber":"127",
    "addr:postcode":"10017",
    "addr:street":"E 46Th St",
    "iso:country":"US",
    "sg:address":"127 E 46th St",
    "sg:city":"New York",
    "sg:classifiers":[
        {
            "category":"Parking",
            "type":"Transportation"
        }
    ],
    "sg:phone":"+1 212 697 4988",
    "sg:postcode":"10017",
    "sg:province":"NY",
    "sg:tags":[
        "garage"
    ],
    "wof:name":"Kinney System Inc",
    "wof:placetype":"venue"
},
  "geometry": {"coordinates":[-73.972588,40.753318],"type":"Point"}
}