{
  "type": "Feature",
  "properties": {
    "addr:full":"7598 Co Rd 153 Interlaken NY 14847",
    "addr:housenumber":"7598",
    "addr:postcode":"14847",
    "addr:street":"Co Rd 153",
    "iso:country":"US",
    "sg:address":"7598 Co Rd 153",
    "sg:city":"Interlaken",
    "sg:classifiers":[
        {
            "category":"Professional",
            "type":"Services"
        }
    ],
    "sg:phone":"+1 607 532 8201",
    "sg:postcode":"14847",
    "sg:province":"NY",
    "sg:tags":[
        "establishment"
    ],
    "wof:name":"Transcendental Meditation",
    "wof:placetype":"venue"
},
  "geometry": {"coordinates":[-76.697546,42.656293],"type":"Point"}
}