{
  "type": "Feature",
  "properties": {
    "addr:full":"367 Old Mamaroneck Rd White Plains NY 10605",
    "addr:housenumber":"367",
    "addr:postcode":"10605",
    "addr:street":"Old Mamaroneck Rd",
    "iso:country":"US",
    "sg:address":"367 Old Mamaroneck Rd",
    "sg:city":"White Plains",
    "sg:classifiers":[
        {
            "category":"Building & Trades",
            "subcategory":"Landscaping Services",
            "type":"Services"
        }
    ],
    "sg:phone":"+1 914 761 2430",
    "sg:postcode":"10605",
    "sg:province":"NY",
    "wof:name":"Mg Landscaping",
    "wof:placetype":"venue"
},
  "geometry": {"coordinates":[-73.763604,40.999323],"type":"Point"}
}