{
  "type": "Feature",
  "properties": {
    "addr:full":"2366 Coney Island Avenue Brooklyn NY 11223",
    "addr:housenumber":"2366",
    "addr:postcode":"11223",
    "addr:street":"Coney Island Avenue",
    "iso:country":"US",
    "sg:address":"2366 Coney Island Avenue",
    "sg:city":"Brooklyn",
    "sg:classifiers":[
        {
            "category":"Retail",
            "subcategory":"Auto Repair",
            "type":"Services"
        }
    ],
    "sg:phone":"+1 718 339 8193",
    "sg:postcode":"11223",
    "sg:province":"NY",
    "wof:name":"McGready Auto Service",
    "wof:placetype":"venue"
},
  "geometry": {"coordinates":[-73.961427,40.600171],"type":"Point"}
}