{
  "type": "Feature",
  "properties": {
    "addr:full":"336 Utica Ave Brooklyn NY 11213",
    "addr:housenumber":"336",
    "addr:postcode":"11213",
    "addr:street":"Utica Ave",
    "iso:country":"US",
    "sg:address":"336 Utica Ave",
    "sg:city":"Brooklyn",
    "sg:classifiers":[
        {
            "category":"Building & Trades",
            "subcategory":"Plumbing",
            "type":"Services"
        },
        {
            "category":"Building & Trades",
            "subcategory":"Construction",
            "type":"Services"
        }
    ],
    "sg:phone":"+1 718 799 5841",
    "sg:postcode":"11213",
    "sg:province":"NY",
    "sg:tags":[
        "air",
        "heating",
        "conditioning/hvac"
    ],
    "sg:website":"www.uticaplumbingandheating.info",
    "wof:name":"Utica Plumbing and Heating",
    "wof:placetype":"venue"
},
  "geometry": {"coordinates":[-73.931376,40.666461],"type":"Point"}
}