{
  "type": "Feature",
  "properties": {
    "addr:full":"1166 Upper Front St Binghamton NY 13905",
    "addr:housenumber":"1166",
    "addr:postcode":"13905",
    "addr:street":"Upper Front St",
    "iso:country":"US",
    "sg:address":"1166 Upper Front St",
    "sg:city":"Binghamton",
    "sg:classifiers":[
        {
            "category":"Restaurant",
            "type":"Food & Drink"
        }
    ],
    "sg:phone":"+1   ",
    "sg:postcode":"13905",
    "sg:province":"NY",
    "sg:tags":[
        "eating"
    ],
    "wof:name":"Margaritas Mexican Grill",
    "wof:placetype":"venue"
},
  "geometry": {"coordinates":[-75.897115,42.153644],"type":"Point"}
}