{
  "type": "Feature",
  "properties": {
    "addr:full":"1818 Falmouth Ave New Hyde Park NY 11040",
    "addr:housenumber":"1818",
    "addr:postcode":"11040",
    "addr:street":"Falmouth Ave",
    "iso:country":"US",
    "sg:address":"1818 Falmouth Ave",
    "sg:city":"New Hyde Park",
    "sg:classifiers":[
        {
            "category":"Retail",
            "subcategory":"Auto Rental",
            "type":"Services"
        }
    ],
    "sg:phone":"+1 516 328 8709",
    "sg:postcode":"11040",
    "sg:province":"NY",
    "sg:tags":[
        "renting",
        "car",
        "automobile"
    ],
    "wof:name":"Personal Auto Rental",
    "wof:placetype":"venue"
},
  "geometry": {"coordinates":[-73.67289700000001,40.743099],"type":"Point"}
}