{
  "type": "Feature",
  "properties": {
    "addr:full":"29 Delview Ter S Delhi NY 13753",
    "addr:housenumber":"29",
    "addr:postcode":"13753",
    "addr:street":"Delview Ter S",
    "iso:country":"US",
    "sg:address":"29 Delview Ter S",
    "sg:city":"Delhi",
    "sg:classifiers":[
        {
            "category":"Real Estate",
            "subcategory":"Surveying",
            "type":"Services"
        }
    ],
    "sg:phone":"+1   ",
    "sg:postcode":"13753",
    "sg:province":"NY",
    "wof:name":"Victor Iwanow",
    "wof:placetype":"venue"
},
  "geometry": {"coordinates":[-74.910657,42.283933],"type":"Point"}
}