{
  "type": "Feature",
  "properties": {
    "iso:country":"US",
    "sg:address":"122 Bloomfield Ave",
    "sg:city":"Buffalo",
    "sg:classifiers":[
        {
            "category":"Freight",
            "type":"Transportation"
        }
    ],
    "sg:phone":"+1 716 826 5849",
    "sg:postcode":"14220",
    "sg:province":"NY",
    "sg:tags":[
        "delivery"
    ],
    "wof:name":"Allman Services",
    "wof:placetype":"venue"
},
  "geometry": {"coordinates":[-78.817485,42.845333],"type":"Point"}
}