{
  "type": "Feature",
  "properties": {
    "iso:country":"US",
    "sg:address":"110 Village Sq",
    "sg:city":"Painted Post",
    "sg:classifiers":[
        {
            "category":"Professional",
            "type":"Services"
        }
    ],
    "sg:phone":"+1 607 962 1027",
    "sg:postcode":"14870",
    "sg:province":"NY",
    "wof:name":"Equifax Payment Svc",
    "wof:placetype":"venue"
},
  "geometry": {"coordinates":[-77.093378,42.159178],"type":"Point"}
}