{
  "type": "Feature",
  "properties": {
    "addr:full":"923 E 174th St Bronx NY 10460",
    "addr:housenumber":"923",
    "addr:postcode":"10460",
    "addr:street":"E 174Th St",
    "iso:country":"US",
    "sg:address":"923 E 174th St",
    "sg:city":"Bronx",
    "sg:classifiers":[
        {
            "category":"Food & Beverages",
            "subcategory":"Candy",
            "type":"Retail Goods"
        }
    ],
    "sg:phone":"+1 718 893 5336",
    "sg:postcode":"10460",
    "sg:province":"NY",
    "sg:tags":[
        "confectionery"
    ],
    "wof:name":"Super Candy Store",
    "wof:placetype":"venue"
},
  "geometry": {"coordinates":[-73.886932,40.837194],"type":"Point"}
}