{
  "type": "Feature",
  "properties": {
    "addr:full":"21 Washington Ave Bay Shore NY 11706",
    "addr:housenumber":"21",
    "addr:postcode":"11706",
    "addr:street":"Washington Ave",
    "iso:country":"US",
    "sg:address":"21 Washington Ave",
    "sg:city":"Bay Shore",
    "sg:classifiers":[
        {
            "category":"Building & Trades",
            "subcategory":"Cleaning & Sanitation",
            "type":"Services"
        },
        {
            "category":"Professional",
            "type":"Services"
        }
    ],
    "sg:phone":"+1 631 254 6190",
    "sg:postcode":"11706",
    "sg:province":"NY",
    "sg:tags":[
        "establishment",
        "chimney"
    ],
    "wof:name":"Flue Season Inc",
    "wof:placetype":"venue"
},
  "geometry": {"coordinates":[-73.290007,40.767736],"type":"Point"}
}