{
  "type": "Feature",
  "properties": {
    "addr:full":"29 Elk St Albany NY 12207",
    "addr:housenumber":"29",
    "addr:postcode":"12207",
    "addr:street":"Elk St",
    "iso:country":"US",
    "sg:address":"29 Elk St",
    "sg:city":"Albany",
    "sg:classifiers":[
        {
            "category":"Organizations",
            "subcategory":"Community Association",
            "type":"Services"
        }
    ],
    "sg:phone":"+1 518 434 1583",
    "sg:postcode":"12207",
    "sg:province":"NY",
    "wof:name":"New York Prks Cnsrvtion Assocs",
    "wof:placetype":"venue"
},
  "geometry": {"coordinates":[-73.754144,42.652866],"type":"Point"}
}