{
  "type": "Feature",
  "properties": {
    "addr:full":"5502 16th Ave Brooklyn NY 11204",
    "addr:housenumber":"5502",
    "addr:postcode":"11204",
    "addr:street":"16Th Ave",
    "iso:country":"US",
    "sg:address":"5502 16th Ave",
    "sg:city":"Brooklyn",
    "sg:classifiers":[
        {
            "category":"Food & Beverages",
            "subcategory":"Meat & Fish",
            "type":"Retail Goods"
        }
    ],
    "sg:phone":"+1   ",
    "sg:postcode":"11204",
    "sg:province":"NY",
    "wof:name":"Illes Kosher Poultry",
    "wof:placetype":"venue"
},
  "geometry": {"coordinates":[-73.98963999999999,40.627175],"type":"Point"}
}