{
  "type": "Feature",
  "properties": {
    "addr:full":"96 Walker St New York NY 10013",
    "addr:housenumber":"96",
    "addr:postcode":"10013",
    "addr:street":"Walker St",
    "iso:country":"US",
    "sg:address":"96 Walker St",
    "sg:city":"New York",
    "sg:classifiers":[
        {
            "category":"Restaurant",
            "type":"Food & Drink"
        }
    ],
    "sg:phone":"+1   ",
    "sg:postcode":"10013",
    "sg:province":"NY",
    "sg:tags":[
        "eating"
    ],
    "wof:name":"City Garden Express Resteraunt",
    "wof:placetype":"venue"
},
  "geometry": {"coordinates":[-74.001831,40.718309],"type":"Point"}
}