{
  "type": "Feature",
  "properties": {
    "addr:full":"18 Cami Ln Morrisonville NY 12962",
    "addr:housenumber":"18",
    "addr:postcode":"12962",
    "addr:street":"Cami Ln",
    "iso:country":"US",
    "sg:address":"18 Cami Ln",
    "sg:city":"Morrisonville",
    "sg:classifiers":[
        {
            "category":"Manufacturing",
            "subcategory":"Lumber",
            "type":"Manufacturing & Wholesale Goods"
        }
    ],
    "sg:phone":"+1 518 643 2031",
    "sg:postcode":"12962",
    "sg:province":"NY",
    "sg:tags":[
        "logging"
    ],
    "wof:name":"Herman Gehrke Logging",
    "wof:placetype":"venue"
},
  "geometry": {"coordinates":[-73.58819800000001,44.641904],"type":"Point"}
}