{
  "type": "Feature",
  "properties": {
    "addr:full":"411 Main St Boonville NY 13309",
    "addr:housenumber":"411",
    "addr:postcode":"13309",
    "addr:street":"Main St",
    "iso:country":"US",
    "sg:address":"411 Main St",
    "sg:city":"Boonville",
    "sg:classifiers":[
        {
            "category":"Autos & Motor Vehicles",
            "subcategory":"Auto Supplies",
            "type":"Retail Goods"
        }
    ],
    "sg:phone":"+1 315 942 2833",
    "sg:postcode":"13309",
    "sg:province":"NY",
    "sg:tags":[
        "automobile",
        "parts"
    ],
    "wof:name":"Boonville Auto Parts",
    "wof:placetype":"venue"
},
  "geometry": {"coordinates":[-75.329874,43.481572],"type":"Point"}
}