{
  "type": "Feature",
  "properties": {
    "iso:country":"US",
    "sg:address":"1 Ferris St",
    "sg:city":"Corning",
    "sg:classifiers":[
        {
            "category":"Shopping",
            "subcategory":"Discount & Variety Stores",
            "type":"Retail Goods"
        }
    ],
    "sg:phone":"+1   ",
    "sg:postcode":"14830",
    "sg:province":"NY",
    "wof:name":"Super Dollar Store",
    "wof:placetype":"venue"
},
  "geometry": {"coordinates":[-77.059888,42.149924],"type":"Point"}
}