{
  "type": "Feature",
  "properties": {
    "iso:country":"US",
    "sg:address":"61 John Muir Dr",
    "sg:city":"Buffalo",
    "sg:classifiers":[
        {
            "category":"Manufacturing",
            "subcategory":"Printing",
            "type":"Manufacturing & Wholesale Goods"
        }
    ],
    "sg:phone":"+1 716 639 0283",
    "sg:postcode":"14228",
    "sg:province":"NY",
    "sg:tags":[
        "publisher"
    ],
    "wof:name":"White Directory Publishing",
    "wof:placetype":"venue"
},
  "geometry": {"coordinates":[-78.773831,43.011312],"type":"Point"}
}