{
  "type": "Feature",
  "properties": {
    "addr:full":"70 McLean Ave Yonkers NY 10705",
    "addr:housenumber":"70",
    "addr:postcode":"10705",
    "addr:street":"Mclean Ave",
    "iso:country":"US",
    "sg:address":"70 McLean Ave",
    "sg:city":"Yonkers",
    "sg:classifiers":[
        {
            "category":"Restaurant",
            "type":"Food & Drink"
        }
    ],
    "sg:phone":"+1 914 378 1400",
    "sg:postcode":"10705",
    "sg:province":"NY",
    "wof:name":"Pizza Barn",
    "wof:placetype":"venue"
},
  "geometry": {"coordinates":[-73.894274,40.918831],"type":"Point"}
}