{
  "type": "Feature",
  "properties": {
    "iso:country":"US",
    "sg:address":"185 Varick St",
    "sg:city":"New York",
    "sg:classifiers":[
        {
            "category":"Real Estate",
            "subcategory":"Architect",
            "type":"Services"
        },
        {
            "category":"Professional",
            "type":"Services"
        }
    ],
    "sg:phone":"+1 212 242 2220",
    "sg:postcode":"10014",
    "sg:province":"NY",
    "sg:tags":[
        "establishment",
        "architectural"
    ],
    "wof:name":"Front Inc",
    "wof:placetype":"venue"
},
  "geometry": {"coordinates":[-74.00557999999999,40.727256],"type":"Point"}
}