{
  "type": "Feature",
  "properties": {
    "addr:full":"7 W 45th St Fl 10 Manhattan NY 10036",
    "addr:housenumber":"7;10",
    "addr:postcode":"10036",
    "addr:street":"W 45Th St Fl",
    "iso:country":"US",
    "sg:address":"7 W 45th St Fl 10",
    "sg:city":"Manhattan",
    "sg:classifiers":[
        {
            "category":"Shopping",
            "subcategory":"Jewelry",
            "type":"Retail Goods"
        }
    ],
    "sg:phone":"+1 877 678 6786",
    "sg:postcode":"10036",
    "sg:province":"NY",
    "sg:website":"www.hansadiamonds.com",
    "wof:name":"Hansa Diamonds",
    "wof:placetype":"venue"
},
  "geometry": {"coordinates":[-73.98006599999999,40.75591],"type":"Point"}
}