{
  "type": "Feature",
  "properties": {
    "iso:country":"US",
    "sg:address":"411 Powells Ln",
    "sg:city":"Westbury",
    "sg:classifiers":[
        {
            "category":"Health Services",
            "subcategory":"Nursing And Care Facility",
            "type":"Services"
        }
    ],
    "sg:phone":"+1 516 334 0029",
    "sg:postcode":"11590",
    "sg:province":"NY",
    "sg:tags":[
        "residential"
    ],
    "wof:name":"Aok Concepts Unltd",
    "wof:placetype":"venue"
},
  "geometry": {"coordinates":[-73.57663100000001,40.763925],"type":"Point"}
}