{
  "type": "Feature",
  "properties": {
    "iso:country":"US",
    "sg:address":"341 Scholes St",
    "sg:city":"Brooklyn",
    "sg:classifiers":[
        {
            "category":"Manufacturing",
            "subcategory":"Apparel",
            "type":"Manufacturing & Wholesale Goods"
        }
    ],
    "sg:phone":"+1   ",
    "sg:postcode":"11206",
    "sg:province":"NY",
    "sg:tags":[
        "clothing",
        "mfg"
    ],
    "wof:name":"Tommy G Products Incorporated",
    "wof:placetype":"venue"
},
  "geometry": {"coordinates":[-73.933633,40.709957],"type":"Point"}
}