{
  "type": "Feature",
  "properties": {
    "iso:country":"US",
    "sg:address":"5105 New Utrecht Ave",
    "sg:city":"Brooklyn",
    "sg:classifiers":[
        {
            "category":"Shopping",
            "subcategory":"Shoes",
            "type":"Retail Goods"
        }
    ],
    "sg:phone":"+1 718 853 5047",
    "sg:postcode":"11219",
    "sg:province":"NY",
    "sg:tags":[
        "store"
    ],
    "wof:name":"H & H Shoe Plaza Inc",
    "wof:placetype":"venue"
},
  "geometry": {"coordinates":[-73.994775,40.634858],"type":"Point"}
}