{
  "type": "Feature",
  "properties": {
    "addr:full":"4170 State Hwy 8 New Berlin NY 13411",
    "addr:housenumber":"4170",
    "addr:postcode":"13411",
    "addr:street":"State Hwy 8",
    "iso:country":"US",
    "sg:address":"4170 State Hwy 8",
    "sg:city":"New Berlin",
    "sg:classifiers":[
        {
            "category":"Sports & Exercise",
            "subcategory":"Golf",
            "type":"Entertainment"
        }
    ],
    "sg:phone":"+1   ",
    "sg:postcode":"13411",
    "sg:province":"NY",
    "sg:tags":[
        "course",
        "drinking",
        "eating",
        "public"
    ],
    "wof:name":"Riverbend Golf Course",
    "wof:placetype":"venue"
},
  "geometry": {"coordinates":[-75.338994,42.573862],"type":"Point"}
}