{
  "type": "Feature",
  "properties": {
    "iso:country":"US",
    "sg:address":"100 River Rd",
    "sg:city":"Harriman",
    "sg:classifiers":[
        {
            "category":"Health Services",
            "subcategory":"Doctor",
            "type":"Services"
        }
    ],
    "sg:phone":"+1 845 783 4325",
    "sg:postcode":"10926",
    "sg:province":"NY",
    "sg:tags":[
        "physician",
        "surgeon"
    ],
    "wof:name":"Harriman Primary Care",
    "wof:placetype":"venue"
},
  "geometry": {"coordinates":[-74.143106,41.312812],"type":"Point"}
}