{
  "type": "Feature",
  "properties": {
    "addr:full":"23 W Market St Corning NY 14830",
    "addr:housenumber":"23",
    "addr:postcode":"14830",
    "addr:street":"W Market St",
    "iso:country":"US",
    "sg:address":"23 W Market St",
    "sg:city":"Corning",
    "sg:classifiers":[
        {
            "category":"Travel",
            "subcategory":"Travel Agent",
            "type":"Entertainment"
        },
        {
            "category":"Banks & Credit Unions",
            "subcategory":"Bank",
            "type":"Services"
        }
    ],
    "sg:phone":"+1 607 936 7100",
    "sg:postcode":"14830",
    "sg:province":"NY",
    "sg:tags":[
        "agency",
        "other",
        "card",
        "plan"
    ],
    "wof:name":"American Express",
    "wof:placetype":"venue"
},
  "geometry": {"coordinates":[-77.056027,42.143721],"type":"Point"}
}