{
  "type": "Feature",
  "properties": {
    "addr:full":"9438 46th Ave Elmhurst NY 11373",
    "addr:housenumber":"9438",
    "addr:postcode":"11373",
    "addr:street":"46Th Ave",
    "iso:country":"US",
    "sg:address":"9438 46th Ave",
    "sg:city":"Elmhurst",
    "sg:classifiers":[
        {
            "category":"Retail",
            "subcategory":"Repair Shop",
            "type":"Services"
        }
    ],
    "sg:phone":"+1 718 393 1453",
    "sg:postcode":"11373",
    "sg:province":"NY",
    "sg:tags":[
        "reupholstery",
        "furniture"
    ],
    "wof:name":"Ada Decorations",
    "wof:placetype":"venue"
},
  "geometry": {"coordinates":[-73.869113,40.743376],"type":"Point"}
}