{
  "type": "Feature",
  "properties": {
    "iso:country":"US",
    "sg:address":"1704 State St",
    "sg:city":"Watertown",
    "sg:classifiers":[
        {
            "category":"Organizations",
            "subcategory":"Non-profit Organization",
            "type":"Services"
        },
        {
            "category":"Social Services",
            "subcategory":"Adult Care",
            "type":"Services"
        }
    ],
    "sg:phone":"+1 315 788 7430",
    "sg:postcode":"13601",
    "sg:province":"NY",
    "sg:tags":[
        "home"
    ],
    "sg:website":"www.nnychildrenshome.com",
    "wof:name":"Children's Home Jefferson Cnty",
    "wof:placetype":"venue"
},
  "geometry": {"coordinates":[-75.88146,43.967262],"type":"Point"}
}