{
  "type": "Feature",
  "properties": {
    "iso:country":"US",
    "sg:address":"2000 Hillside Ave",
    "sg:city":"New Hyde Park",
    "sg:classifiers":[
        {
            "category":"Retail",
            "subcategory":"Funeral Services",
            "type":"Services"
        }
    ],
    "sg:phone":"+1 516 352 3434",
    "sg:postcode":"11040",
    "sg:province":"NY",
    "sg:tags":[
        "cemetery"
    ],
    "wof:name":"Stutzmann R & Son Inc",
    "wof:placetype":"venue"
},
  "geometry": {"coordinates":[-73.675797,40.751099],"type":"Point"}
}