{
  "type": "Feature",
  "properties": {
    "addr:full":"310 Richmond Hill Road Staten Island NY 10314",
    "addr:housenumber":"310",
    "addr:postcode":"10314",
    "addr:street":"Richmond Hill Road",
    "iso:country":"US",
    "sg:address":"310 Richmond Hill Road",
    "sg:city":"Staten Island",
    "sg:classifiers":[
        {
            "category":"Health Services",
            "subcategory":"Dentist",
            "type":"Services"
        }
    ],
    "sg:phone":"+1 718 494 5448",
    "sg:postcode":"10314",
    "sg:province":"NY",
    "wof:name":"Wisecare Oral Surgery Group",
    "wof:placetype":"venue"
},
  "geometry": {"coordinates":[-74.157662,40.583235],"type":"Point"}
}