{
  "type": "Feature",
  "properties": {
    "addr:full":"8703 Queens Blvd Elmhurst NY 11373",
    "addr:housenumber":"8703",
    "addr:postcode":"11373",
    "addr:street":"Queens Blvd",
    "iso:country":"US",
    "sg:address":"8703 Queens Blvd",
    "sg:city":"Elmhurst",
    "sg:classifiers":[
        {
            "category":"Banks & Credit Unions",
            "subcategory":"Bank",
            "type":"Services"
        }
    ],
    "sg:phone":"+1 718 592 1001",
    "sg:postcode":"11373",
    "sg:province":"NY",
    "sg:website":"hsbc.com",
    "wof:name":"HSBC Bank",
    "wof:placetype":"venue"
},
  "geometry": {"coordinates":[-73.87584099999999,40.735734],"type":"Point"}
}