{
  "type": "Feature",
  "properties": {
    "addr:full":"15 Kenmont Dr Camillus NY 13031",
    "addr:housenumber":"15",
    "addr:postcode":"13031",
    "addr:street":"Kenmont Dr",
    "iso:country":"US",
    "sg:address":"15 Kenmont Dr",
    "sg:city":"Camillus",
    "sg:classifiers":[
        {
            "category":"Organizations",
            "subcategory":"Community Association",
            "type":"Services"
        }
    ],
    "sg:phone":"+1   ",
    "sg:postcode":"13031",
    "sg:province":"NY",
    "wof:name":"Alpha & Omega",
    "wof:placetype":"venue"
},
  "geometry": {"coordinates":[-76.274473,43.043805],"type":"Point"}
}