{
  "type": "Feature",
  "properties": {
    "iso:country":"US",
    "sg:address":"102 Custer Ave",
    "sg:city":"Williston Park",
    "sg:classifiers":[
        {
            "category":"Restaurant",
            "type":"Food & Drink"
        }
    ],
    "sg:phone":"+1   ",
    "sg:postcode":"11596",
    "sg:province":"NY",
    "sg:tags":[
        "eating"
    ],
    "wof:name":"Baskin-Robbins",
    "wof:placetype":"venue"
},
  "geometry": {"coordinates":[-73.64260400000001,40.755086],"type":"Point"}
}