{
  "type": "Feature",
  "properties": {
    "iso:country":"US",
    "sg:address":"753 Holt Rd",
    "sg:city":"Webster",
    "sg:classifiers":[
        {
            "category":"Insurance",
            "subcategory":"Insurance Agent",
            "type":"Services"
        }
    ],
    "sg:phone":"+1 585 217 8840",
    "sg:postcode":"14580",
    "sg:province":"NY",
    "wof:name":"Regional Claim Services Inc",
    "wof:placetype":"venue"
},
  "geometry": {"coordinates":[-77.446702,43.223468],"type":"Point"}
}