{
  "type": "Feature",
  "properties": {
    "addr:full":"3766 Broadway New York NY 10032",
    "addr:housenumber":"3766",
    "addr:postcode":"10032",
    "addr:street":"Broadway",
    "iso:country":"US",
    "sg:address":"3766 Broadway",
    "sg:city":"New York",
    "sg:classifiers":[
        {
            "category":"Professional",
            "subcategory":"Employment Agencies",
            "type":"Services"
        }
    ],
    "sg:phone":"+1 212 234 4899",
    "sg:postcode":"10032",
    "sg:province":"NY",
    "wof:name":"Escala Employment Agency",
    "wof:placetype":"venue"
},
  "geometry": {"coordinates":[-73.944929,40.833513],"type":"Point"}
}