{
  "type": "Feature",
  "properties": {
    "addr:full":"122 W 18 St New York NY 10011",
    "addr:housenumber":"122",
    "addr:postcode":"10011",
    "addr:street":"W 18 St",
    "iso:country":"US",
    "sg:address":"122 W 18 St",
    "sg:city":"New York",
    "sg:classifiers":[
        {
            "category":"Manufacturing",
            "subcategory":"Furniture",
            "type":"Manufacturing & Wholesale Goods"
        }
    ],
    "sg:phone":"+1   ",
    "sg:postcode":"10011",
    "sg:province":"NY",
    "sg:tags":[
        "mfg"
    ],
    "wof:name":"Carlyle Custom Convertibles",
    "wof:placetype":"venue"
},
  "geometry": {"coordinates":[-73.997415,40.740722],"type":"Point"}
}