{
  "type": "Feature",
  "properties": {
    "addr:full":"402 E 53 St New York NY 10022",
    "addr:housenumber":"402;53",
    "addr:postcode":"10022",
    "addr:street":"E",
    "iso:country":"US",
    "sg:address":"402 E 53 St",
    "sg:city":"New York",
    "sg:classifiers":[
        {
            "category":"Shopping",
            "subcategory":"Florist",
            "type":"Retail Goods"
        }
    ],
    "sg:phone":"+1   ",
    "sg:postcode":"10022",
    "sg:province":"NY",
    "wof:name":"Spitz & Peck Florists Inc",
    "wof:placetype":"venue"
},
  "geometry": {"coordinates":[-73.96325,40.755022],"type":"Point"}
}