{
  "type": "Feature",
  "properties": {
    "addr:full":"89 Brookhaven Ave Riverhead NY 11901",
    "addr:housenumber":"89",
    "addr:postcode":"11901",
    "addr:street":"Brookhaven Ave",
    "iso:country":"US",
    "sg:address":"89 Brookhaven Ave",
    "sg:city":"Riverhead",
    "sg:classifiers":[
        {
            "category":"Home & Garden",
            "subcategory":"Carpets & Floor Coverings",
            "type":"Retail Goods"
        }
    ],
    "sg:phone":"+1 631 369 2960",
    "sg:postcode":"11901",
    "sg:province":"NY",
    "sg:tags":[
        "flooring",
        "contractor"
    ],
    "wof:name":"Twin Fork Flooring",
    "wof:placetype":"venue"
},
  "geometry": {"coordinates":[-72.629189,40.904759],"type":"Point"}
}