{
  "type": "Feature",
  "properties": {
    "addr:full":"9707 63rd Road Rego Park NY 11374",
    "addr:housenumber":"9707",
    "addr:postcode":"11374",
    "addr:street":"63Rd Road",
    "iso:country":"US",
    "sg:address":"9707 63rd Road",
    "sg:city":"Rego Park",
    "sg:classifiers":[
        {
            "category":"Real Estate",
            "subcategory":"Real Estate Services",
            "type":"Services"
        },
        {
            "category":"Real Estate",
            "subcategory":"Real Estate Operator",
            "type":"Services"
        }
    ],
    "sg:phone":"+1 718 275 1500",
    "sg:postcode":"11374",
    "sg:province":"NY",
    "sg:tags":[
        "apartment",
        "property",
        "management"
    ],
    "wof:name":"Park City 3 & 4 Apartmnts",
    "wof:placetype":"venue"
},
  "geometry": {"coordinates":[-73.86078500000001,40.730995],"type":"Point"}
}