{
  "type": "Feature",
  "properties": {
    "addr:full":"37 Greenpoint Ave Brooklyn NY 11222",
    "addr:housenumber":"37",
    "addr:postcode":"11222",
    "addr:street":"Greenpoint Ave",
    "iso:country":"US",
    "sg:address":"37 Greenpoint Ave",
    "sg:city":"Brooklyn",
    "sg:classifiers":[
        {
            "category":"Retail",
            "subcategory":"Portrait Studio",
            "type":"Services"
        }
    ],
    "sg:phone":"+1 718 389 9228",
    "sg:postcode":"11222",
    "sg:province":"NY",
    "sg:tags":[
        "photography",
        "store"
    ],
    "wof:name":"Lighting Works Inc",
    "wof:placetype":"venue"
},
  "geometry": {"coordinates":[-73.95050000000001,40.726898],"type":"Point"}
}