{
  "type": "Feature",
  "properties": {
    "iso:country":"US",
    "sg:address":"52 Route 17K Ste 201",
    "sg:city":"Newburgh",
    "sg:classifiers":[
        {
            "category":"Banks & Credit Unions",
            "subcategory":"Bank",
            "type":"Services"
        }
    ],
    "sg:phone":"+1 845 562 6766",
    "sg:postcode":"12550",
    "sg:province":"NY",
    "sg:tags":[
        "saving",
        "commercial"
    ],
    "sg:website":"http://www.riversidebankhv.com",
    "wof:name":"Riverside Bank (Inc)",
    "wof:placetype":"venue"
},
  "geometry": {"coordinates":[-74.062996,41.503994],"type":"Point"}
}