{
  "type": "Feature",
  "properties": {
    "addr:full":"7017 Bear Swamp Rd Williamson NY 14589",
    "addr:housenumber":"7017",
    "addr:postcode":"14589",
    "addr:street":"Bear Swamp Rd",
    "iso:country":"US",
    "sg:address":"7017 Bear Swamp Rd",
    "sg:city":"Williamson",
    "sg:classifiers":[
        {
            "category":"Farming",
            "subcategory":"Orchard",
            "type":"Manufacturing & Wholesale Goods"
        }
    ],
    "sg:phone":"+1 315 589 9370",
    "sg:postcode":"14589",
    "sg:province":"NY",
    "sg:tags":[
        "fruit",
        "tree"
    ],
    "wof:name":"Hermenet Fruit Farm",
    "wof:placetype":"venue"
},
  "geometry": {"coordinates":[-77.165318,43.251515],"type":"Point"}
}