{
  "type": "Feature",
  "properties": {
    "addr:full":"209 Clinton Ave Brooklyn NY 11205",
    "addr:housenumber":"209",
    "addr:postcode":"11205",
    "addr:street":"Clinton Ave",
    "iso:country":"US",
    "sg:address":"209 Clinton Ave",
    "sg:city":"Brooklyn",
    "sg:classifiers":[
        {
            "category":"Real Estate",
            "subcategory":"Real Estate Agent",
            "type":"Services"
        }
    ],
    "sg:phone":"+1 718 797 2200",
    "sg:postcode":"11205",
    "sg:province":"NY",
    "wof:name":"Clinton Hill Sales Office",
    "wof:placetype":"venue"
},
  "geometry": {"coordinates":[-73.96880899999999,40.693121],"type":"Point"}
}