{
  "type": "Feature",
  "properties": {
    "addr:full":"2044 Williamsbridge Rd Bronx NY 10461",
    "addr:housenumber":"2044",
    "addr:postcode":"10461",
    "addr:street":"Williamsbridge Rd",
    "iso:country":"US",
    "sg:address":"2044 Williamsbridge Rd",
    "sg:city":"Bronx",
    "sg:classifiers":[
        {
            "category":"Insurance",
            "subcategory":"Insurance Agent",
            "type":"Services"
        }
    ],
    "sg:phone":"+1 718 823 9100",
    "sg:postcode":"10461",
    "sg:province":"NY",
    "sg:tags":[
        "real estate"
    ],
    "wof:name":"Patrick J Cavallo Agency",
    "wof:placetype":"venue"
},
  "geometry": {"coordinates":[-73.854966,40.854917],"type":"Point"}
}