{
  "type": "Feature",
  "properties": {
    "iso:country":"US",
    "sg:address":"5 Rutland Rd",
    "sg:city":"Great Neck",
    "sg:classifiers":[
        {
            "category":"Real Estate",
            "subcategory":"Developer",
            "type":"Services"
        }
    ],
    "sg:phone":"+1 516 829 3127",
    "sg:postcode":"11020",
    "sg:province":"NY",
    "sg:tags":[
        "building",
        "operator",
        "a",
        "nonresidential"
    ],
    "wof:name":"J & D Enterprises",
    "wof:placetype":"venue"
},
  "geometry": {"coordinates":[-73.720668,40.777567],"type":"Point"}
}