{
  "type": "Feature",
  "properties": {
    "iso:country":"US",
    "sg:address":"611 Glen St",
    "sg:city":"Glens Falls",
    "sg:classifiers":[
        {
            "category":"Professional",
            "subcategory":"Lawyer & Legal Services",
            "type":"Services"
        }
    ],
    "sg:phone":"+1 518 793 6604",
    "sg:postcode":"12801",
    "sg:province":"NY",
    "sg:tags":[
        "attorney"
    ],
    "wof:name":"Queensbury Abstract",
    "wof:placetype":"venue"
},
  "geometry": {"coordinates":[-73.660715,43.322341],"type":"Point"}
}