{
  "type": "Feature",
  "properties": {
    "iso:country":"US",
    "sg:address":"653 Byron Ave",
    "sg:city":"Franklin Square",
    "sg:classifiers":[
        {
            "category":"Building & Trades",
            "subcategory":"Construction",
            "type":"Services"
        }
    ],
    "sg:phone":"+1 516 483 0303",
    "sg:postcode":"11010",
    "sg:province":"NY",
    "sg:tags":[
        "contractor"
    ],
    "wof:name":"K2k Contracting",
    "wof:placetype":"venue"
},
  "geometry": {"coordinates":[-73.668611,40.691003],"type":"Point"}
}