{
  "type": "Feature",
  "properties": {
    "iso:country":"US",
    "sg:address":"11 Lake St",
    "sg:city":"White Plains",
    "sg:classifiers":[
        {
            "category":"Professional",
            "subcategory":"Computer Services",
            "type":"Services"
        }
    ],
    "sg:phone":"+1   ",
    "sg:postcode":"10603",
    "sg:province":"NY",
    "sg:tags":[
        "programing",
        "custom"
    ],
    "wof:name":"Ba Insight",
    "wof:placetype":"venue"
},
  "geometry": {"coordinates":[-73.764428,41.03628],"type":"Point"}
}