{
  "type": "Feature",
  "properties": {
    "addr:full":"574 5th Ave New York NY 10036",
    "addr:housenumber":"574",
    "addr:postcode":"10036",
    "addr:street":"5Th Ave",
    "iso:country":"US",
    "sg:address":"574 5th Ave",
    "sg:city":"New York",
    "sg:classifiers":[
        {
            "category":"Professional",
            "subcategory":"Lawyer & Legal Services",
            "type":"Services"
        }
    ],
    "sg:phone":"+1 212 755 0006",
    "sg:postcode":"10036",
    "sg:province":"NY",
    "wof:name":"Shuffman David K Atty",
    "wof:placetype":"venue"
},
  "geometry": {"coordinates":[-73.97905799999999,40.75658],"type":"Point"}
}