{
  "type": "Feature",
  "properties": {
    "addr:full":"412 Wellwood Dr Shirley NY 11967",
    "addr:housenumber":"412",
    "addr:postcode":"11967",
    "addr:street":"Wellwood Dr",
    "iso:country":"US",
    "sg:address":"412 Wellwood Dr",
    "sg:city":"Shirley",
    "sg:classifiers":[
        {
            "category":"Insurance",
            "subcategory":"Hazard Insurance",
            "type":"Services"
        }
    ],
    "sg:phone":"+1 631 924 4787",
    "sg:postcode":"11967",
    "sg:province":"NY",
    "sg:tags":[
        "commercial",
        "business"
    ],
    "sg:website":"http://www.farmers.com",
    "wof:name":"Farmers Insurance Group",
    "wof:placetype":"venue"
},
  "geometry": {"coordinates":[-72.879643,40.834222],"type":"Point"}
}