{
  "type": "Feature",
  "properties": {
    "addr:full":"421 Seventh Avenue 4th Floor New York NY 10001",
    "addr:housenumber":"421",
    "addr:postcode":"10001",
    "addr:street":"Avenue 4Th Floor",
    "iso:country":"US",
    "sg:address":"421 Seventh Avenue 4th Floor",
    "sg:city":"New York",
    "sg:classifiers":[
        {
            "category":"Communications",
            "type":"Services"
        }
    ],
    "sg:phone":"+1 646 289 3660",
    "sg:postcode":"10001",
    "sg:province":"NY",
    "sg:tags":[
        "medium",
        "mass"
    ],
    "wof:name":"IGC ACQUISITIONS INC",
    "wof:placetype":"venue"
},
  "geometry": {"coordinates":[-73.990644,40.750298],"type":"Point"}
}