{
  "type": "Feature",
  "properties": {
    "iso:country":"US",
    "sg:address":"3 Bridge St",
    "sg:city":"Yonkers",
    "sg:classifiers":[
        {
            "category":"Professional",
            "subcategory":"Management & Consulting",
            "type":"Services"
        }
    ],
    "sg:phone":"+1 914 965 8200",
    "sg:postcode":"10705",
    "sg:province":"NY",
    "sg:tags":[
        "fire",
        "consultant",
        "protection"
    ],
    "wof:name":"All Hands Svc",
    "wof:placetype":"venue"
},
  "geometry": {"coordinates":[-73.90420399999999,40.924662],"type":"Point"}
}