{
  "type": "Feature",
  "properties": {
    "iso:country":"US",
    "sg:address":"2018 Bay Blvd",
    "sg:city":"Atlantic Beach",
    "sg:classifiers":[
        {
            "category":"Building & Trades",
            "subcategory":"Construction",
            "type":"Services"
        }
    ],
    "sg:phone":"+1 631 724 8288",
    "sg:postcode":"11509",
    "sg:province":"NY",
    "sg:tags":[
        "company"
    ],
    "wof:name":"Ocean Marine Construction Inc",
    "wof:placetype":"venue"
},
  "geometry": {"coordinates":[-73.735591,40.591488],"type":"Point"}
}