{
  "type": "Feature",
  "properties": {
    "addr:full":"55 Washington St Brooklyn NY 11201",
    "addr:housenumber":"55",
    "addr:postcode":"11201",
    "addr:street":"Washington St",
    "iso:country":"US",
    "sg:address":"55 Washington St",
    "sg:city":"Brooklyn",
    "sg:classifiers":[
        {
            "category":"Building & Trades",
            "subcategory":"Electrical",
            "type":"Services"
        }
    ],
    "sg:phone":"+1 212 337 0929",
    "sg:postcode":"11201",
    "sg:province":"NY",
    "sg:tags":[
        "contractor"
    ],
    "wof:name":"Ae Greyson & Co Inc",
    "wof:placetype":"venue"
},
  "geometry": {"coordinates":[-73.989524,40.703046],"type":"Point"}
}