{
  "type": "Feature",
  "properties": {
    "addr:full":"289 Washington St Newburgh NY 12550",
    "addr:housenumber":"289",
    "addr:postcode":"12550",
    "addr:street":"Washington St",
    "iso:country":"US",
    "sg:address":"289 Washington St",
    "sg:city":"Newburgh",
    "sg:classifiers":[
        {
            "category":"Taxi",
            "type":"Transportation"
        }
    ],
    "sg:phone":"+1   ",
    "sg:postcode":"12550",
    "sg:province":"NY",
    "sg:tags":[
        "taxicab"
    ],
    "wof:name":"Lamaquina Star Taxi",
    "wof:placetype":"venue"
},
  "geometry": {"coordinates":[-74.02070999999999,41.498948],"type":"Point"}
}