{
  "type": "Feature",
  "properties": {
    "addr:full":"327 E Lake Rd Penn Yan NY 14527",
    "addr:housenumber":"327",
    "addr:postcode":"14527",
    "addr:street":"E Lake Rd",
    "iso:country":"US",
    "sg:address":"327 E Lake Rd",
    "sg:city":"Penn Yan",
    "sg:classifiers":[
        {
            "category":"Building & Trades",
            "subcategory":"Landscaping Services",
            "type":"Services"
        }
    ],
    "sg:phone":"+1 315 536 1193",
    "sg:postcode":"14527",
    "sg:province":"NY",
    "sg:tags":[
        "lawn",
        "maintenance",
        "grounds"
    ],
    "wof:name":"Clancy's Lawn Care",
    "wof:placetype":"venue"
},
  "geometry": {"coordinates":[-77.070696,42.631459],"type":"Point"}
}