{
  "type": "Feature",
  "properties": {
    "addr:full":"46 Gabriel Rd Corinth NY 12822",
    "addr:housenumber":"46",
    "addr:postcode":"12822",
    "addr:street":"Gabriel Rd",
    "iso:country":"US",
    "sg:address":"46 Gabriel Rd",
    "sg:city":"Corinth",
    "sg:classifiers":[
        {
            "category":"Retail",
            "subcategory":"Auto Repair",
            "type":"Services"
        }
    ],
    "sg:phone":"+1 518 654 9545",
    "sg:postcode":"12822",
    "sg:province":"NY",
    "sg:tags":[
        "repairing",
        "automobile"
    ],
    "wof:name":"Tubbs Garage",
    "wof:placetype":"venue"
},
  "geometry": {"coordinates":[-73.81573899999999,43.233326],"type":"Point"}
}