{
  "type": "Feature",
  "properties": {
    "addr:full":"119 Jackson St Ste 9 Hempstead NY 11550",
    "addr:housenumber":"119",
    "addr:postcode":"11550",
    "addr:street":"Jackson St Ste 9",
    "iso:country":"US",
    "sg:address":"119 Jackson St Ste 9",
    "sg:city":"Hempstead",
    "sg:classifiers":[
        {
            "category":"Personal",
            "type":"Services"
        }
    ],
    "sg:phone":"+1 516 486 2663",
    "sg:postcode":"11550",
    "sg:province":"NY",
    "sg:tags":[
        "local"
    ],
    "sg:website":"www.affordablebailbondsnewyork.com",
    "wof:name":"Affordable Bail Bonds",
    "wof:placetype":"venue"
},
  "geometry": {"coordinates":[-73.627202,40.710032],"type":"Point"}
}