{
  "type": "Feature",
  "properties": {
    "addr:full":"650 Stewart Ave Garden City NY 11530",
    "addr:housenumber":"650",
    "addr:postcode":"11530",
    "addr:street":"Stewart Ave",
    "iso:country":"US",
    "sg:address":"650 Stewart Ave",
    "sg:city":"Garden City",
    "sg:classifiers":[
        {
            "category":"Professional",
            "subcategory":"Employment Agencies",
            "type":"Services"
        }
    ],
    "sg:phone":"+1 516 228 8126",
    "sg:postcode":"11530",
    "sg:province":"NY",
    "sg:website":"www.randstad.com",
    "wof:name":"Randstad",
    "wof:placetype":"venue"
},
  "geometry": {"coordinates":[-73.610468,40.731804],"type":"Point"}
}