{
  "type": "Feature",
  "properties": {
    "addr:full":"133 W 19th St New York NY 10011",
    "addr:housenumber":"133",
    "addr:postcode":"10011",
    "addr:street":"W 19Th St",
    "iso:country":"US",
    "sg:address":"133 W 19th St",
    "sg:city":"New York",
    "sg:classifiers":[
        {
            "category":"Communications",
            "subcategory":"Newspaper",
            "type":"Services"
        },
        {
            "category":"Communications",
            "type":"Services"
        }
    ],
    "sg:phone":"+1 212 727 1500",
    "sg:postcode":"10011",
    "sg:province":"NY",
    "sg:tags":[
        "medium",
        "mass",
        "advertising"
    ],
    "sg:website":"www.tobinproductions.com",
    "wof:name":"Tobin Productions",
    "wof:placetype":"venue"
},
  "geometry": {"coordinates":[-73.995874,40.741215],"type":"Point"}
}