{
  "type": "Feature",
  "properties": {
    "addr:full":"347 Edison Street Staten Island NY 10306",
    "addr:housenumber":"347",
    "addr:postcode":"10306",
    "addr:street":"Edison Street",
    "iso:country":"US",
    "sg:address":"347 Edison Street",
    "sg:city":"Staten Island",
    "sg:classifiers":[
        {
            "category":"Health Services",
            "subcategory":"Hospital",
            "type":"Services"
        }
    ],
    "sg:phone":"+1 718 980 5098",
    "sg:postcode":"10306",
    "sg:province":"NY",
    "sg:website":"www.siuh.edu",
    "wof:name":"Staten Island University Hospital",
    "wof:placetype":"venue"
},
  "geometry": {"coordinates":[-74.112792,40.573174],"type":"Point"}
}