{
  "type": "Feature",
  "properties": {
    "iso:country":"US",
    "sg:address":"1016 McLean Ave",
    "sg:city":"Yonkers",
    "sg:classifiers":[
        {
            "category":"Wholesale",
            "subcategory":"Dairy",
            "type":"Manufacturing & Wholesale Goods"
        }
    ],
    "sg:phone":"+1 914 237 2389",
    "sg:postcode":"10704",
    "sg:province":"NY",
    "sg:tags":[
        "cheese"
    ],
    "wof:name":"Avitable Bros",
    "wof:placetype":"venue"
},
  "geometry": {"coordinates":[-73.864013,40.902608],"type":"Point"}
}