{
  "type": "Feature",
  "properties": {
    "addr:full":"6 Market St Alexandria Bay NY 13607",
    "addr:housenumber":"6",
    "addr:postcode":"13607",
    "addr:street":"Market St",
    "iso:country":"US",
    "sg:address":"6 Market St",
    "sg:city":"Alexandria Bay",
    "sg:classifiers":[
        {
            "category":"Government",
            "subcategory":"Office",
            "type":"Public Place"
        }
    ],
    "sg:phone":"+1 315 482 4586",
    "sg:postcode":"13607",
    "sg:province":"NY",
    "sg:tags":[
        "village"
    ],
    "wof:name":"Alexandria Township Historical",
    "wof:placetype":"venue"
},
  "geometry": {"coordinates":[-75.918362,44.337027],"type":"Point"}
}