{
  "type": "Feature",
  "properties": {
    "addr:full":"23 Carriage Ln Roslyn Heights NY 11577",
    "addr:housenumber":"23",
    "addr:postcode":"11577",
    "addr:street":"Carriage Ln",
    "iso:country":"US",
    "sg:address":"23 Carriage Ln",
    "sg:city":"Roslyn Heights",
    "sg:classifiers":[
        {
            "category":"Professional",
            "subcategory":"Lawyer & Legal Services",
            "type":"Services"
        }
    ],
    "sg:phone":"+1 516 621 1327",
    "sg:postcode":"11577",
    "sg:province":"NY",
    "wof:name":"Kreitzman & Mortensen",
    "wof:placetype":"venue"
},
  "geometry": {"coordinates":[-73.637299,40.7799],"type":"Point"}
}