{
  "type": "Feature",
  "properties": {
    "iso:country":"US",
    "sg:address":"221 Cold Spring Rd",
    "sg:city":"Hudson",
    "sg:classifiers":[
        {
            "category":"Building & Trades",
            "subcategory":"Landscaping Services",
            "type":"Services"
        }
    ],
    "sg:phone":"+1 518 828 7977",
    "sg:postcode":"12534",
    "sg:province":"NY",
    "wof:name":"Dons Lawn & Landscaping Inc",
    "wof:placetype":"venue"
},
  "geometry": {"coordinates":[-73.802694,42.166897],"type":"Point"}
}