{
  "type": "Feature",
  "properties": {
    "addr:full":"3321 State Hwy 9h Valatie NY 12184",
    "addr:housenumber":"3321",
    "addr:postcode":"12184",
    "addr:street":"State Hwy",
    "iso:country":"US",
    "sg:address":"3321 State Hwy 9h",
    "sg:city":"Valatie",
    "sg:classifiers":[
        {
            "category":"Wholesale",
            "subcategory":"Groceries",
            "type":"Manufacturing & Wholesale Goods"
        }
    ],
    "sg:phone":"+1 518 784 2511",
    "sg:postcode":"12184",
    "sg:province":"NY",
    "sg:tags":[
        "food",
        "product"
    ],
    "wof:name":"Country Value Foods",
    "wof:placetype":"venue"
},
  "geometry": {"coordinates":[-73.690743,42.414184],"type":"Point"}
}