{
  "type": "Feature",
  "properties": {
    "addr:full":"167 E 84th St New York NY 10028",
    "addr:housenumber":"167",
    "addr:postcode":"10028",
    "addr:street":"E 84Th St",
    "iso:country":"US",
    "sg:address":"167 E 84th St",
    "sg:city":"New York",
    "sg:classifiers":[
        {
            "category":"Parking",
            "type":"Transportation"
        }
    ],
    "sg:phone":"+1 212 628 4550",
    "sg:postcode":"10028",
    "sg:province":"NY",
    "sg:tags":[
        "garage"
    ],
    "wof:name":"Evans Tower Garage",
    "wof:placetype":"venue"
},
  "geometry": {"coordinates":[-73.95540200000001,40.777845],"type":"Point"}
}