{
  "type": "Feature",
  "properties": {
    "iso:country":"US",
    "sg:address":"943 48th St",
    "sg:city":"Brooklyn",
    "sg:classifiers":[
        {
            "category":"Health Services",
            "subcategory":"Doctor",
            "type":"Services"
        }
    ],
    "sg:phone":"+1 718 853 1535",
    "sg:postcode":"11219",
    "sg:province":"NY",
    "wof:name":"Dor Nathan MD",
    "wof:placetype":"venue"
},
  "geometry": {"coordinates":[-73.999199,40.640301],"type":"Point"}
}