{
  "type": "Feature",
  "properties": {
    "iso:country":"US",
    "sg:address":"339 S Salina St",
    "sg:city":"Syracuse",
    "sg:classifiers":[
        {
            "category":"Shopping",
            "subcategory":"Clothing, Apparel, & Fashions",
            "type":"Retail Goods"
        }
    ],
    "sg:phone":"+1 315 423 0426",
    "sg:postcode":"13202",
    "sg:province":"NY",
    "sg:tags":[
        "sportswear"
    ],
    "wof:name":"DMZ",
    "wof:placetype":"venue"
},
  "geometry": {"coordinates":[-76.152152,43.047675],"type":"Point"}
}