{
  "type": "Feature",
  "properties": {
    "addr:full":"19 Degnon Blvd Islip NY 11706",
    "addr:housenumber":"19",
    "addr:postcode":"11706",
    "addr:street":"Degnon Blvd",
    "iso:country":"US",
    "sg:address":"19 Degnon Blvd",
    "sg:city":"Islip",
    "sg:classifiers":[
        {
            "category":"Wholesale",
            "subcategory":"Sporting Goods",
            "type":"Manufacturing & Wholesale Goods"
        }
    ],
    "sg:phone":"+1 631 224 9675",
    "sg:postcode":"11706",
    "sg:province":"NY",
    "wof:name":"L&L Wholesale Bait Inc",
    "wof:placetype":"venue"
},
  "geometry": {"coordinates":[-73.225448,40.726776],"type":"Point"}
}