{
  "type": "Feature",
  "properties": {
    "iso:country":"US",
    "sg:address":"8083 E Floyd Rd",
    "sg:city":"Rome",
    "sg:classifiers":[
        {
            "category":"Travel",
            "subcategory":"Hotels & Motels",
            "type":"Entertainment"
        }
    ],
    "sg:phone":"+1 315 865 6190",
    "sg:postcode":"13440",
    "sg:province":"NY",
    "sg:tags":[
        "operation"
    ],
    "wof:name":"Belle Maison Farms",
    "wof:placetype":"venue"
},
  "geometry": {"coordinates":[-75.34370800000001,43.254951],"type":"Point"}
}