{
  "type": "Feature",
  "properties": {
    "addr:full":"397 Garretson Ave Staten Island NY 10305",
    "addr:housenumber":"397",
    "addr:postcode":"10305",
    "addr:street":"Garretson Ave",
    "iso:country":"US",
    "sg:address":"397 Garretson Ave",
    "sg:city":"Staten Island",
    "sg:classifiers":[
        {
            "category":"Building & Trades",
            "subcategory":"Construction",
            "type":"Services"
        }
    ],
    "sg:phone":"+1 718 667 6370",
    "sg:postcode":"10305",
    "sg:province":"NY",
    "sg:tags":[
        "general",
        "contractor"
    ],
    "wof:name":"Famous of NY Cnstr & Roofg",
    "wof:placetype":"venue"
},
  "geometry": {"coordinates":[-74.088874,40.585881],"type":"Point"}
}