{
  "type": "Feature",
  "properties": {
    "iso:country":"US",
    "sg:address":"1301 Avenue J",
    "sg:city":"Brooklyn",
    "sg:classifiers":[
        {
            "category":"Health Services",
            "subcategory":"Optometrist",
            "type":"Services"
        }
    ],
    "sg:phone":"+1 718 284 1921",
    "sg:postcode":"11230",
    "sg:province":"NY",
    "sg:website":"www.klmeyecare.com",
    "wof:name":"Brooklyn Eye Surgery Center",
    "wof:placetype":"venue"
},
  "geometry": {"coordinates":[-73.962959,40.625112],"type":"Point"}
}