{
  "type": "Feature",
  "properties": {
    "iso:country":"US",
    "sg:address":"509 Rte 22",
    "sg:city":"Purdys",
    "sg:classifiers":[
        {
            "category":"Social Services",
            "type":"Services"
        }
    ],
    "sg:phone":"+1 914 669 9012",
    "sg:postcode":"10578",
    "sg:province":"NY",
    "sg:tags":[
        "employee",
        "assistance",
        "program"
    ],
    "wof:name":"Your HR Connection",
    "wof:placetype":"venue"
},
  "geometry": {"coordinates":[-73.660724,41.319472],"type":"Point"}
}