{
  "type": "Feature",
  "properties": {
    "addr:full":"485 N Broadway Yonkers NY 10701",
    "addr:housenumber":"485",
    "addr:postcode":"10701",
    "addr:street":"N Broadway",
    "iso:country":"US",
    "sg:address":"485 N Broadway",
    "sg:city":"Yonkers",
    "sg:classifiers":[
        {
            "category":"Organizations",
            "subcategory":"Religious Organization",
            "type":"Services"
        }
    ],
    "sg:phone":"+1 914 963 5549",
    "sg:postcode":"10701",
    "sg:province":"NY",
    "sg:tags":[
        "church"
    ],
    "wof:name":"St Marys Carpatho-Russian Chr",
    "wof:placetype":"venue"
},
  "geometry": {"coordinates":[-73.89178699999999,40.95048],"type":"Point"}
}