{
  "type": "Feature",
  "properties": {
    "addr:full":"192 9th St Troy NY 12180",
    "addr:housenumber":"192",
    "addr:postcode":"12180",
    "addr:street":"9Th St",
    "iso:country":"US",
    "sg:address":"192 9th St",
    "sg:city":"Troy",
    "sg:classifiers":[
        {
            "category":"Organizations",
            "subcategory":"Religious Organization",
            "type":"Services"
        }
    ],
    "sg:phone":"+1 518 272 7848",
    "sg:postcode":"12180",
    "sg:province":"NY",
    "sg:tags":[
        "church"
    ],
    "wof:name":"Redemption Church",
    "wof:placetype":"venue"
},
  "geometry": {"coordinates":[-73.68086099999999,42.738492],"type":"Point"}
}