{
  "type": "Feature",
  "properties": {
    "addr:full":"22 Market St Beacon NY 12590",
    "addr:housenumber":"22",
    "addr:postcode":"12590",
    "addr:street":"Market St",
    "iso:country":"US",
    "sg:address":"22 Market St",
    "sg:city":"Beacon",
    "sg:classifiers":[
        {
            "category":"Government",
            "subcategory":"Office",
            "type":"Public Place"
        }
    ],
    "sg:phone":"+1 845 486 2060",
    "sg:postcode":"12590",
    "sg:province":"NY",
    "sg:tags":[
        "executive"
    ],
    "wof:name":"Veterans Affairs of Dutchess",
    "wof:placetype":"venue"
},
  "geometry": {"coordinates":[-73.92009400000001,41.598423],"type":"Point"}
}