{
  "type": "Feature",
  "properties": {
    "addr:full":"2501 Cherry Hill Dr Poughkeepsie NY 12603",
    "addr:housenumber":"2501",
    "addr:postcode":"12603",
    "addr:street":"Cherry Hill Dr",
    "iso:country":"US",
    "sg:address":"2501 Cherry Hill Dr",
    "sg:city":"Poughkeepsie",
    "sg:classifiers":[
        {
            "category":"Real Estate",
            "subcategory":"Real Estate Services",
            "type":"Services"
        },
        {
            "category":"Real Estate",
            "subcategory":"Real Estate Agent",
            "type":"Services"
        }
    ],
    "sg:phone":"+1 914 964 6784",
    "sg:postcode":"12603",
    "sg:province":"NY",
    "sg:tags":[
        "buyer",
        "broker"
    ],
    "wof:name":"Falco Realty Inc",
    "wof:placetype":"venue"
},
  "geometry": {"coordinates":[-73.882974,41.704225],"type":"Point"}
}