{
  "type": "Feature",
  "properties": {
    "iso:country":"US",
    "sg:address":"77 Wynsum Ave",
    "sg:city":"Merrick",
    "sg:classifiers":[
        {
            "category":"Building & Trades",
            "subcategory":"Construction",
            "type":"Services"
        }
    ],
    "sg:phone":"+1 516 868 2748",
    "sg:postcode":"11566",
    "sg:province":"NY",
    "sg:tags":[
        "carpentry",
        "contractor"
    ],
    "wof:name":"Raymond Fico",
    "wof:placetype":"venue"
},
  "geometry": {"coordinates":[-73.54604500000001,40.660848],"type":"Point"}
}