{
  "type": "Feature",
  "properties": {
    "iso:country":"US",
    "sg:address":"171 Milbar Blvd",
    "sg:city":"Farmingdale",
    "sg:classifiers":[
        {
            "category":"Wholesale",
            "subcategory":"Medical Equipment & Supplies",
            "type":"Manufacturing & Wholesale Goods"
        }
    ],
    "sg:phone":"+1 631 293 8881",
    "sg:postcode":"11735",
    "sg:province":"NY",
    "sg:tags":[
        "health"
    ],
    "wof:name":"National Health Supply Corp",
    "wof:placetype":"venue"
},
  "geometry": {"coordinates":[-73.42108899999999,40.75021],"type":"Point"}
}