{
  "type": "Feature",
  "properties": {
    "iso:country":"US",
    "sg:address":"18 Violet Ave",
    "sg:city":"Hicksville",
    "sg:classifiers":[
        {
            "category":"Bakery",
            "type":"Food & Drink"
        }
    ],
    "sg:phone":"+1 516 933 9211",
    "sg:postcode":"11801",
    "sg:province":"NY",
    "wof:name":"Castellano Bread Dist",
    "wof:placetype":"venue"
},
  "geometry": {"coordinates":[-73.523651,40.778679],"type":"Point"}
}