{
  "type": "Feature",
  "properties": {
    "iso:country":"US",
    "sg:address":"301 Mill Rd",
    "sg:city":"Hewlett",
    "sg:classifiers":[
        {
            "category":"Shopping",
            "type":"Retail Goods"
        }
    ],
    "sg:phone":"+1 516 295 2722",
    "sg:postcode":"11557",
    "sg:province":"NY",
    "sg:tags":[
        "stamp",
        "collector",
        "for"
    ],
    "wof:name":"Interpost",
    "wof:placetype":"venue"
},
  "geometry": {"coordinates":[-73.70231099999999,40.640487],"type":"Point"}
}