{
  "type": "Feature",
  "properties": {
    "addr:full":"6115 5th Ave Brooklyn NY 11220",
    "addr:housenumber":"6115",
    "addr:postcode":"11220",
    "addr:street":"5Th Ave",
    "iso:country":"US",
    "sg:address":"6115 5th Ave",
    "sg:city":"Brooklyn",
    "sg:classifiers":[
        {
            "category":"Restaurant",
            "type":"Food & Drink"
        }
    ],
    "sg:phone":"+1 718 492 5755",
    "sg:postcode":"11220",
    "sg:province":"NY",
    "sg:tags":[
        "deli",
        "delicatessen"
    ],
    "wof:name":"Deli Store",
    "wof:placetype":"venue"
},
  "geometry": {"coordinates":[-74.016998,40.6385],"type":"Point"}
}