{
  "type": "Feature",
  "properties": {
    "addr:full":"164 Commack Rd Ste 6 Commack NY 11725",
    "addr:housenumber":"164",
    "addr:postcode":"11725",
    "addr:street":"Commack Rd Ste 6",
    "iso:country":"US",
    "sg:address":"164 Commack Rd Ste 6",
    "sg:city":"Commack",
    "sg:classifiers":[
        {
            "category":"Health Services",
            "subcategory":"Dentist",
            "type":"Services"
        }
    ],
    "sg:phone":"+1 631 499 0531",
    "sg:postcode":"11725",
    "sg:province":"NY",
    "sg:tags":[
        "orthodontist"
    ],
    "wof:name":"Green James A Dr",
    "wof:placetype":"venue"
},
  "geometry": {"coordinates":[-73.294403,40.835098],"type":"Point"}
}