{
  "type": "Feature",
  "properties": {
    "iso:country":"US",
    "sg:address":"204 S Main St",
    "sg:city":"New City",
    "sg:classifiers":[
        {
            "category":"Shopping",
            "subcategory":"Clothing, Apparel, & Fashions",
            "type":"Retail Goods"
        }
    ],
    "sg:phone":"+1   ",
    "sg:postcode":"10956",
    "sg:province":"NY",
    "wof:name":"Strawberry",
    "wof:placetype":"venue"
},
  "geometry": {"coordinates":[-73.99038299999999,41.141246],"type":"Point"}
}