{
  "type": "Feature",
  "properties": {
    "addr:full":"39 Main St Oneonta NY 13820",
    "addr:housenumber":"39",
    "addr:postcode":"13820",
    "addr:street":"Main St",
    "iso:country":"US",
    "sg:address":"39 Main St",
    "sg:city":"Oneonta",
    "sg:classifiers":[
        {
            "category":"Shopping",
            "subcategory":"Discount & Variety Stores",
            "type":"Retail Goods"
        }
    ],
    "sg:phone":"+1   ",
    "sg:postcode":"13820",
    "sg:province":"NY",
    "sg:tags":[
        "grocery",
        "merchandise",
        "general"
    ],
    "wof:name":"Country Store",
    "wof:placetype":"venue"
},
  "geometry": {"coordinates":[-75.063976,42.448539],"type":"Point"}
}