{
  "type": "Feature",
  "properties": {
    "iso:country":"US",
    "sg:address":"2788 Park Ave",
    "sg:city":"Baldwin",
    "sg:classifiers":[
        {
            "category":"Arena",
            "subcategory":"Sports Club",
            "type":"Entertainment"
        }
    ],
    "sg:phone":"+1 516 236 4906",
    "sg:postcode":"11510",
    "sg:province":"NY",
    "sg:tags":[
        "soccer"
    ],
    "wof:name":"Bg Soccer Toors",
    "wof:placetype":"venue"
},
  "geometry": {"coordinates":[-73.609683,40.641907],"type":"Point"}
}