{
  "type": "Feature",
  "properties": {
    "iso:country":"US",
    "sg:address":"18 E 64th Street",
    "sg:city":"New York",
    "sg:classifiers":[
        {
            "category":"Real Estate",
            "subcategory":"Real Estate Services",
            "type":"Services"
        }
    ],
    "sg:phone":"+1 212 753 3991",
    "sg:postcode":"10021",
    "sg:province":"NY",
    "wof:name":"Burton Wallack Rl Est",
    "wof:placetype":"venue"
},
  "geometry": {"coordinates":[-73.96982300000001,40.766977],"type":"Point"}
}