{
  "type": "Feature",
  "properties": {
    "addr:full":"1111 Rich Rd Oneonta NY 13820",
    "addr:housenumber":"1111",
    "addr:postcode":"13820",
    "addr:street":"Rich Rd",
    "iso:country":"US",
    "sg:address":"1111 Rich Rd",
    "sg:city":"Oneonta",
    "sg:classifiers":[
        {
            "category":"Manufacturing",
            "subcategory":"Lumber",
            "type":"Manufacturing & Wholesale Goods"
        }
    ],
    "sg:phone":"+1 607 432 8963",
    "sg:postcode":"13820",
    "sg:province":"NY",
    "sg:tags":[
        "timberland",
        "timber"
    ],
    "wof:name":"Fred J Hungerford",
    "wof:placetype":"venue"
},
  "geometry": {"coordinates":[-75.08889600000001,42.402966],"type":"Point"}
}