{
  "type": "Feature",
  "properties": {
    "addr:full":"468 Piermont Ave Piermont NY 10968",
    "addr:housenumber":"468",
    "addr:postcode":"10968",
    "addr:street":"Piermont Ave",
    "iso:country":"US",
    "sg:address":"468 Piermont Ave",
    "sg:city":"Piermont",
    "sg:classifiers":[
        {
            "category":"Real Estate",
            "subcategory":"Real Estate Services",
            "type":"Services"
        },
        {
            "category":"Real Estate",
            "subcategory":"Real Estate Agent",
            "type":"Services"
        }
    ],
    "sg:phone":"+1 845 359 3218",
    "sg:postcode":"10968",
    "sg:province":"NY",
    "sg:tags":[
        "management"
    ],
    "wof:name":"Vslj Realty",
    "wof:placetype":"venue"
},
  "geometry": {"coordinates":[-73.915998,41.039596],"type":"Point"}
}