{
  "type": "Feature",
  "properties": {
    "iso:country":"US",
    "sg:address":"8 Manetto Hill Rd",
    "sg:city":"Plainview",
    "sg:classifiers":[
        {
            "category":"Professional",
            "subcategory":"Business Services",
            "type":"Services"
        }
    ],
    "sg:phone":"+1 516 433 6440",
    "sg:postcode":"11803",
    "sg:province":"NY",
    "sg:tags":[
        "protection",
        "fabric",
        "care"
    ],
    "wof:name":"Fiber Seal of Long Island",
    "wof:placetype":"venue"
},
  "geometry": {"coordinates":[-73.46715399999999,40.77701],"type":"Point"}
}