{
  "type": "Feature",
  "properties": {
    "addr:full":"384 Grand St Manhattan NY 10002",
    "addr:housenumber":"384",
    "addr:postcode":"10002",
    "addr:street":"Grand St",
    "iso:country":"US",
    "sg:address":"384 Grand St",
    "sg:city":"Manhattan",
    "sg:classifiers":[
        {
            "category":"Restaurant",
            "type":"Food & Drink"
        }
    ],
    "sg:postcode":"10002",
    "sg:province":"NY",
    "sg:tags":[
        "mexican"
    ],
    "sg:website":"www.laflacanyc.com",
    "wof:name":"La Flaca",
    "wof:placetype":"venue"
},
  "geometry": {"coordinates":[-73.987695,40.716417],"type":"Point"}
}