{
  "type": "Feature",
  "properties": {
    "addr:full":"104 Johnson St East Syracuse NY 13057",
    "addr:housenumber":"104",
    "addr:postcode":"13057",
    "addr:street":"Johnson St",
    "iso:country":"US",
    "sg:address":"104 Johnson St",
    "sg:city":"East Syracuse",
    "sg:classifiers":[
        {
            "category":"Retail",
            "subcategory":"Repair Shop",
            "type":"Services"
        }
    ],
    "sg:phone":"+1   ",
    "sg:postcode":"13057",
    "sg:province":"NY",
    "sg:tags":[
        "pipe",
        "organs",
        "mfg"
    ],
    "wof:name":"Kerner Merch Pipe Organ Bldrs",
    "wof:placetype":"venue"
},
  "geometry": {"coordinates":[-76.071564,43.059157],"type":"Point"}
}