{
  "type": "Feature",
  "properties": {
    "addr:full":"2446 Western Ave Guilderland NY 12084",
    "addr:housenumber":"2446",
    "addr:postcode":"12084",
    "addr:street":"Western Ave",
    "iso:country":"US",
    "sg:address":"2446 Western Ave",
    "sg:city":"Guilderland",
    "sg:classifiers":[
        {
            "category":"Autos & Motor Vehicles",
            "subcategory":"Auto Supplies",
            "type":"Retail Goods"
        },
        {
            "category":"Retail",
            "subcategory":"Auto Repair",
            "type":"Services"
        }
    ],
    "sg:phone":"+1 518 452 8457",
    "sg:postcode":"12084",
    "sg:province":"NY",
    "sg:tags":[
        "automotive",
        "lube",
        "oil",
        "tune"
    ],
    "sg:website":"http://www.valvoline.com",
    "wof:name":"Valvoline Instant Oil Change",
    "wof:placetype":"venue"
},
  "geometry": {"coordinates":[-73.894943,42.699039],"type":"Point"}
}