{
  "type": "Feature",
  "properties": {
    "addr:full":"22412 Merrick Blvd Springfield Gardens NY 11413",
    "addr:housenumber":"22412",
    "addr:postcode":"11413",
    "addr:street":"Merrick Blvd",
    "iso:country":"US",
    "sg:address":"22412 Merrick Blvd",
    "sg:city":"Springfield Gardens",
    "sg:classifiers":[
        {
            "category":"Health Services",
            "subcategory":"Doctor",
            "type":"Services"
        }
    ],
    "sg:phone":"+1 718 949 6433",
    "sg:postcode":"11413",
    "sg:province":"NY",
    "sg:tags":[
        "podiatrist"
    ],
    "wof:name":"Akuoku Samuel Dr",
    "wof:placetype":"venue"
},
  "geometry": {"coordinates":[-73.74539900000001,40.677601],"type":"Point"}
}