{
  "type": "Feature",
  "properties": {
    "iso:country":"US",
    "sg:address":"18306 Hillside Ave",
    "sg:city":"Jamaica",
    "sg:classifiers":[
        {
            "category":"Shopping",
            "subcategory":"Clothing, Apparel, & Fashions",
            "type":"Retail Goods"
        },
        {
            "category":"Retail",
            "subcategory":"Laundry & Dry Cleaning",
            "type":"Services"
        }
    ],
    "sg:phone":"+1 718 558 4285",
    "sg:postcode":"11432",
    "sg:province":"NY",
    "sg:tags":[
        "cleaner",
        "alterations-clothing",
        "commercial"
    ],
    "wof:name":"Well Dressed Cleaners",
    "wof:placetype":"venue"
},
  "geometry": {"coordinates":[-73.781891,40.713144],"type":"Point"}
}