{
  "type": "Feature",
  "properties": {
    "iso:country":"US",
    "sg:address":"4410 Lakeshore Dr",
    "sg:city":"Canandaigua",
    "sg:classifiers":[
        {
            "category":"Retail",
            "subcategory":"Veterinary Services",
            "type":"Services"
        }
    ],
    "sg:phone":"+1 585 394 3340",
    "sg:postcode":"14424",
    "sg:province":"NY",
    "sg:tags":[
        "veterinarian",
        "specialty"
    ],
    "wof:name":"Monroe Veterinary Associates",
    "wof:placetype":"venue"
},
  "geometry": {"coordinates":[-77.24597,42.872187],"type":"Point"}
}