{
  "type": "Feature",
  "properties": {
    "addr:full":"150 Spring St 2nd Fl New York NY 10012",
    "addr:housenumber":"150",
    "addr:postcode":"10012",
    "addr:street":"Spring St",
    "iso:country":"US",
    "sg:address":"150 Spring St 2nd Fl",
    "sg:city":"New York",
    "sg:classifiers":[
        {
            "category":"Personal",
            "subcategory":"Hair Removal",
            "type":"Services"
        },
        {
            "category":"Personal",
            "subcategory":"Skin Care",
            "type":"Services"
        }
    ],
    "sg:phone":"+1 212 219 1990",
    "sg:postcode":"10012",
    "sg:province":"NY",
    "sg:tags":[
        "laser"
    ],
    "sg:website":"www.lasertouchsoho.com",
    "wof:name":"LaserTouch SoHo",
    "wof:placetype":"venue"
},
  "geometry": {"coordinates":[-74.00146599999999,40.724228],"type":"Point"}
}