{
  "type": "Feature",
  "properties": {
    "addr:full":"90 S Remsen Ave Wappingers Falls NY 12590",
    "addr:housenumber":"90",
    "addr:postcode":"12590",
    "addr:street":"S Remsen Ave",
    "iso:country":"US",
    "sg:address":"90 S Remsen Ave",
    "sg:city":"Wappingers Falls",
    "sg:classifiers":[
        {
            "category":"Organizations",
            "subcategory":"Membership Organization",
            "type":"Services"
        }
    ],
    "sg:phone":"+1 845 297 0421",
    "sg:postcode":"12590",
    "sg:province":"NY",
    "sg:tags":[
        "athletic"
    ],
    "wof:name":"Wappingers Pop Warner Football",
    "wof:placetype":"venue"
},
  "geometry": {"coordinates":[-73.9174,41.590776],"type":"Point"}
}