{
  "type": "Feature",
  "properties": {
    "addr:full":"60 N Main St Pittsford NY 14534",
    "addr:housenumber":"60",
    "addr:postcode":"14534",
    "addr:street":"N Main St",
    "iso:country":"US",
    "sg:address":"60 N Main St",
    "sg:city":"Pittsford",
    "sg:classifiers":[
        {
            "category":"Restaurant",
            "type":"Food & Drink"
        }
    ],
    "sg:phone":"+1   ",
    "sg:postcode":"14534",
    "sg:province":"NY",
    "sg:tags":[
        "drinking",
        "eating"
    ],
    "wof:name":"Pittsford Pub",
    "wof:placetype":"venue"
},
  "geometry": {"coordinates":[-77.514104,43.093768],"type":"Point"}
}