{
  "type": "Feature",
  "properties": {
    "iso:country":"US",
    "sg:address":"397 Malcolm X Blvd",
    "sg:city":"New York",
    "sg:classifiers":[
        {
            "category":"Deli",
            "type":"Food & Drink"
        }
    ],
    "sg:phone":"+1 212 996 5758",
    "sg:postcode":"10027",
    "sg:province":"NY",
    "wof:name":"Stop 2 Discount Deli",
    "wof:placetype":"venue"
},
  "geometry": {"coordinates":[-73.94349699999999,40.810799],"type":"Point"}
}