{
  "type": "Feature",
  "properties": {
    "iso:country":"US",
    "sg:address":"288 8th Ave",
    "sg:city":"New York",
    "sg:classifiers":[
        {
            "category":"Restaurant",
            "type":"Food & Drink"
        }
    ],
    "sg:menulink":"http://www.allmenus.com/ny/new-york/141451-hong-kong-and-sharaku/menu/",
    "sg:phone":"+1 212 627 8388",
    "sg:postcode":"10001",
    "sg:province":"NY",
    "sg:tags":[
        "asian",
        "chinese"
    ],
    "wof:name":"Hong Kong and Sharaku",
    "wof:placetype":"venue"
},
  "geometry": {"coordinates":[-73.99737399999999,40.746071],"type":"Point"}
}