{
  "type": "Feature",
  "properties": {
    "iso:country":"US",
    "sg:address":"4000 Summit Circle Dr",
    "sg:city":"Rochester",
    "sg:classifiers":[
        {
            "category":"Social Services",
            "subcategory":"Adult Care",
            "type":"Services"
        }
    ],
    "sg:phone":"+1   ",
    "sg:postcode":"14618",
    "sg:province":"NY",
    "sg:tags":[
        "residential"
    ],
    "wof:name":"Wolk Manor",
    "wof:placetype":"venue"
},
  "geometry": {"coordinates":[-77.581177,43.104238],"type":"Point"}
}