{
  "type": "Feature",
  "properties": {
    "iso:country":"US",
    "sg:address":"310 New Dorp Ln",
    "sg:city":"Staten Island",
    "sg:classifiers":[
        {
            "category":"Shopping",
            "subcategory":"Florist",
            "type":"Retail Goods"
        }
    ],
    "sg:phone":"+1   ",
    "sg:postcode":"10306",
    "sg:province":"NY",
    "wof:name":"Staten Island Florist & Gifts",
    "wof:placetype":"venue"
},
  "geometry": {"coordinates":[-74.113123,40.572377],"type":"Point"}
}