{
  "type": "Feature",
  "properties": {
    "iso:country":"US",
    "sg:address":"544 Grand Ave",
    "sg:city":"Lindenhurst",
    "sg:classifiers":[
        {
            "category":"Building & Trades",
            "subcategory":"Construction",
            "type":"Services"
        }
    ],
    "sg:phone":"+1 631 888 1128",
    "sg:postcode":"11757",
    "sg:province":"NY",
    "sg:tags":[
        "house"
    ],
    "wof:name":"P Dobrzyn Construction",
    "wof:placetype":"venue"
},
  "geometry": {"coordinates":[-73.36505,40.705334],"type":"Point"}
}