{
  "type": "Feature",
  "properties": {
    "addr:full":"251 N 8th Street Brooklyn NY 11211",
    "addr:housenumber":"251",
    "addr:postcode":"11211",
    "addr:street":"N 8Th Street",
    "iso:country":"US",
    "sg:address":"251 N 8th Street",
    "sg:city":"Brooklyn",
    "sg:classifiers":[
        {
            "category":"Arts & Performance",
            "subcategory":"Art Gallery",
            "type":"Entertainment"
        },
        {
            "category":"Shopping",
            "subcategory":"Crafts & Fabrics",
            "type":"Retail Goods"
        }
    ],
    "sg:phone":"+1 718 599 7997",
    "sg:postcode":"11211",
    "sg:province":"NY",
    "sg:tags":[
        "consultant",
        "galleries",
        "instruction"
    ],
    "wof:name":"Williamsburg Art Nexus",
    "wof:placetype":"venue"
},
  "geometry": {"coordinates":[-73.953791,40.716309],"type":"Point"}
}