{
  "type": "Feature",
  "properties": {
    "addr:full":"348 Central Ave Lawrence NY 11559",
    "addr:housenumber":"348",
    "addr:postcode":"11559",
    "addr:street":"Central Ave",
    "iso:country":"US",
    "sg:address":"348 Central Ave",
    "sg:city":"Lawrence",
    "sg:classifiers":[
        {
            "category":"Shopping",
            "subcategory":"Used Merchandise",
            "type":"Retail Goods"
        }
    ],
    "sg:phone":"+1   ",
    "sg:postcode":"11559",
    "sg:province":"NY",
    "sg:tags":[
        "store"
    ],
    "wof:name":"American Cancer Soc Thrift Sp",
    "wof:placetype":"venue"
},
  "geometry": {"coordinates":[-73.72844499999999,40.618418],"type":"Point"}
}