{
  "type": "Feature",
  "properties": {
    "addr:full":"173 Froehlich Farm Blvd Woodbury NY 11797",
    "addr:housenumber":"173",
    "addr:postcode":"11797",
    "addr:street":"Froehlich Farm Blvd",
    "iso:country":"US",
    "sg:address":"173 Froehlich Farm Blvd",
    "sg:city":"Woodbury",
    "sg:classifiers":[
        {
            "category":"Health Services",
            "subcategory":"Doctor",
            "type":"Services"
        }
    ],
    "sg:phone":"+1 516 682 8288",
    "sg:postcode":"11797",
    "sg:province":"NY",
    "sg:tags":[
        "physician",
        "surgeon"
    ],
    "wof:name":"Ward & April Otolaryngology",
    "wof:placetype":"venue"
},
  "geometry": {"coordinates":[-73.477572,40.800605],"type":"Point"}
}