{
  "type": "Feature",
  "properties": {
    "addr:full":"7743 Maple Street Rd Basom NY 14013",
    "addr:housenumber":"7743",
    "addr:postcode":"14013",
    "addr:street":"Maple Street Rd",
    "iso:country":"US",
    "sg:address":"7743 Maple Street Rd",
    "sg:city":"Basom",
    "sg:classifiers":[
        {
            "category":"Real Estate",
            "subcategory":"Real Estate Operator",
            "type":"Services"
        }
    ],
    "sg:phone":"+1 585 762 8820",
    "sg:postcode":"14013",
    "sg:province":"NY",
    "sg:tags":[
        "hog",
        "c",
        "lessor",
        "farm",
        "chicken",
        "property",
        "or",
        "feedlot"
    ],
    "wof:name":"O K Farms",
    "wof:placetype":"venue"
},
  "geometry": {"coordinates":[-78.335955,43.041361],"type":"Point"}
}