{
  "type": "Feature",
  "properties": {
    "iso:country":"US",
    "sg:address":"251 E Houston St",
    "sg:city":"New York",
    "sg:classifiers":[
        {
            "category":"Shopping",
            "subcategory":"Gifts & Souvenirs",
            "type":"Retail Goods"
        }
    ],
    "sg:phone":"+1   ",
    "sg:postcode":"10002",
    "sg:province":"NY",
    "sg:tags":[
        "shop"
    ],
    "wof:name":"Alphabets",
    "wof:placetype":"venue"
},
  "geometry": {"coordinates":[-73.984917,40.721745],"type":"Point"}
}