{
  "type": "Feature",
  "properties": {
    "addr:full":"4356 Millwood Cir Liverpool NY 13090",
    "addr:housenumber":"4356",
    "addr:postcode":"13090",
    "addr:street":"Millwood Cir",
    "iso:country":"US",
    "sg:address":"4356 Millwood Cir",
    "sg:city":"Liverpool",
    "sg:classifiers":[
        {
            "category":"Autos & Motor Vehicles",
            "subcategory":"Motorcycle Sales",
            "type":"Retail Goods"
        }
    ],
    "sg:phone":"+1 315 676 5868",
    "sg:postcode":"13090",
    "sg:province":"NY",
    "sg:tags":[
        "scooter"
    ],
    "wof:name":"Racers Edge",
    "wof:placetype":"venue"
},
  "geometry": {"coordinates":[-76.21135099999999,43.1455],"type":"Point"}
}