{
  "type": "Feature",
  "properties": {
    "addr:full":"1038 Peninsula Blvd Woodmere NY 11598",
    "addr:housenumber":"1038",
    "addr:postcode":"11598",
    "addr:street":"Peninsula Blvd",
    "iso:country":"US",
    "sg:address":"1038 Peninsula Blvd",
    "sg:city":"Woodmere",
    "sg:classifiers":[
        {
            "category":"Banks & Credit Unions",
            "subcategory":"Bank",
            "type":"Services"
        }
    ],
    "sg:phone":"+1 516 569 0426",
    "sg:postcode":"11598",
    "sg:province":"NY",
    "sg:tags":[
        "mortgage",
        "loan",
        "broker",
        "real estate"
    ],
    "wof:name":"Concord Consultants",
    "wof:placetype":"venue"
},
  "geometry": {"coordinates":[-73.7127,40.6404],"type":"Point"}
}