{
  "type": "Feature",
  "properties": {
    "iso:country":"US",
    "sg:address":"25 Lefferts Ave",
    "sg:city":"Brooklyn",
    "sg:classifiers":[
        {
            "category":"Building & Trades",
            "subcategory":"Construction",
            "type":"Services"
        }
    ],
    "sg:phone":"+1 347 663 2927",
    "sg:postcode":"11225",
    "sg:province":"NY",
    "sg:tags":[
        "contractor"
    ],
    "wof:name":"Dnk Contracting",
    "wof:placetype":"venue"
},
  "geometry": {"coordinates":[-73.96038900000001,40.661901],"type":"Point"}
}