{
  "type": "Feature",
  "properties": {
    "iso:country":"US",
    "sg:address":"85 Route 111",
    "sg:city":"Smithtown",
    "sg:classifiers":[
        {
            "category":"Personal",
            "subcategory":"Barber",
            "type":"Services"
        }
    ],
    "sg:phone":"+1 631 979 2898",
    "sg:postcode":"11787",
    "sg:province":"NY",
    "wof:name":"Alex's Barber Shop",
    "wof:placetype":"venue"
},
  "geometry": {"coordinates":[-73.18759900000001,40.8522],"type":"Point"}
}