{
  "type": "Feature",
  "properties": {
    "iso:country":"US",
    "sg:address":"644 Bushwick Ave",
    "sg:city":"Brooklyn",
    "sg:classifiers":[
        {
            "category":"Autos & Motor Vehicles",
            "subcategory":"Fuel & Gas Station",
            "type":"Retail Goods"
        }
    ],
    "sg:phone":"+1 718 919 3022",
    "sg:postcode":"11221",
    "sg:province":"NY",
    "wof:name":"Faith Energy Inc",
    "wof:placetype":"venue"
},
  "geometry": {"coordinates":[-73.93313999999999,40.697637],"type":"Point"}
}