{
  "type": "Feature",
  "properties": {
    "addr:full":"1228 Teall Ave Syracuse NY 13206",
    "addr:housenumber":"1228",
    "addr:postcode":"13206",
    "addr:street":"Teall Ave",
    "iso:country":"US",
    "sg:address":"1228 Teall Ave",
    "sg:city":"Syracuse",
    "sg:classifiers":[
        {
            "category":"Organizations",
            "subcategory":"Religious Organization",
            "type":"Services"
        }
    ],
    "sg:phone":"+1 315 479 5472",
    "sg:postcode":"13206",
    "sg:province":"NY",
    "wof:name":"Reformed Church Of Syracuse",
    "wof:placetype":"venue"
},
  "geometry": {"coordinates":[-76.12254799999999,43.064093],"type":"Point"}
}