{
  "type": "Feature",
  "properties": {
    "iso:country":"US",
    "sg:address":"15 Eastern Pkwy",
    "sg:city":"Brooklyn",
    "sg:classifiers":[
        {
            "category":"Real Estate",
            "subcategory":"Real Estate Operator",
            "type":"Services"
        }
    ],
    "sg:phone":"+1 718 622 2332",
    "sg:postcode":"11238",
    "sg:province":"NY",
    "sg:tags":[
        "apartment"
    ],
    "wof:name":"Museum Court Apartment Corp",
    "wof:placetype":"venue"
},
  "geometry": {"coordinates":[-73.967911,40.672959],"type":"Point"}
}