{
  "type": "Feature",
  "properties": {
    "addr:full":"4 Elizabeth St Baldwinsville NY 13027",
    "addr:housenumber":"4",
    "addr:postcode":"13027",
    "addr:street":"Elizabeth St",
    "iso:country":"US",
    "sg:address":"4 Elizabeth St",
    "sg:city":"Baldwinsville",
    "sg:classifiers":[
        {
            "category":"Health Services",
            "subcategory":"Clinic",
            "type":"Services"
        }
    ],
    "sg:phone":"+1 315 263 1230",
    "sg:postcode":"13027",
    "sg:province":"NY",
    "wof:name":"Baldwinsville Therapheutic",
    "wof:placetype":"venue"
},
  "geometry": {"coordinates":[-76.330336,43.160409],"type":"Point"}
}