{
  "type": "Feature",
  "properties": {
    "addr:full":"888 Grand Concourse Bronx NY 10451",
    "addr:housenumber":"888",
    "addr:postcode":"10451",
    "addr:street":"Grand Concourse",
    "iso:country":"US",
    "sg:address":"888 Grand Concourse",
    "sg:city":"Bronx",
    "sg:classifiers":[
        {
            "category":"Professional",
            "subcategory":"Lawyer & Legal Services",
            "type":"Services"
        }
    ],
    "sg:phone":"+1   ",
    "sg:postcode":"10451",
    "sg:province":"NY",
    "wof:name":"Martin Galvin Atty",
    "wof:placetype":"venue"
},
  "geometry": {"coordinates":[-73.922877,40.826119],"type":"Point"}
}