{
  "type": "Feature",
  "properties": {
    "addr:full":"746 Sand Hill Rd Gardiner NY 12525",
    "addr:housenumber":"746",
    "addr:postcode":"12525",
    "addr:street":"Sand Hill Rd",
    "iso:country":"US",
    "sg:address":"746 Sand Hill Rd",
    "sg:city":"Gardiner",
    "sg:classifiers":[
        {
            "category":"Shopping",
            "type":"Retail Goods"
        }
    ],
    "sg:phone":"+1   ",
    "sg:postcode":"12525",
    "sg:province":"NY",
    "sg:tags":[
        "merchandise"
    ],
    "wof:name":"Hudson Valley Equine Supply",
    "wof:placetype":"venue"
},
  "geometry": {"coordinates":[-74.171311,41.645079],"type":"Point"}
}