{
  "type": "Feature",
  "properties": {
    "addr:full":"4821 Tomson Ave Niagara Falls NY 14304",
    "addr:housenumber":"4821",
    "addr:postcode":"14304",
    "addr:street":"Tomson Ave",
    "iso:country":"US",
    "sg:address":"4821 Tomson Ave",
    "sg:city":"Niagara Falls",
    "sg:classifiers":[
        {
            "category":"Building & Trades",
            "subcategory":"Plumbing",
            "type":"Services"
        }
    ],
    "sg:phone":"+1 716 283 4833",
    "sg:postcode":"14304",
    "sg:province":"NY",
    "sg:tags":[
        "control",
        "air",
        "pollution"
    ],
    "sg:website":"www.airtraccorp.com",
    "wof:name":"Air Trac Corp",
    "wof:placetype":"venue"
},
  "geometry": {"coordinates":[-79.00027,43.090319],"type":"Point"}
}