{
  "type": "Feature",
  "properties": {
    "addr:full":"1981 Broad Hollow Rd Farmingdale NY 11735",
    "addr:housenumber":"1981",
    "addr:postcode":"11735",
    "addr:street":"Broad Hollow Rd",
    "iso:country":"US",
    "sg:address":"1981 Broad Hollow Rd",
    "sg:city":"Farmingdale",
    "sg:classifiers":[
        {
            "category":"Restaurant",
            "type":"Food & Drink"
        }
    ],
    "sg:phone":"+1   ",
    "sg:postcode":"11735",
    "sg:province":"NY",
    "sg:tags":[
        "eating"
    ],
    "wof:name":"Taco Bell",
    "wof:placetype":"venue"
},
  "geometry": {"coordinates":[-73.422417,40.745715],"type":"Point"}
}