{
  "type": "Feature",
  "properties": {
    "addr:full":"604 Route 303 Blauvelt NY 10913",
    "addr:housenumber":"604",
    "addr:postcode":"10913",
    "addr:street":"Route 303",
    "iso:country":"US",
    "sg:address":"604 Route 303",
    "sg:city":"Blauvelt",
    "sg:classifiers":[
        {
            "category":"Utilities",
            "subcategory":"Telephone",
            "type":"Services"
        },
        {
            "category":"Manufacturing",
            "subcategory":"Electronics",
            "type":"Manufacturing & Wholesale Goods"
        }
    ],
    "sg:phone":"+1 845 398 7651",
    "sg:postcode":"10913",
    "sg:province":"NY",
    "sg:tags":[
        "equipment",
        "telecommunications-equipment",
        "system",
        "supply"
    ],
    "wof:name":"Millennium Wireless Srvces",
    "wof:placetype":"venue"
},
  "geometry": {"coordinates":[-73.95012699999999,41.068512],"type":"Point"}
}