{
  "type": "Feature",
  "properties": {
    "iso:country":"US",
    "sg:address":"2921 Pilgrimport Rd",
    "sg:city":"Lyons",
    "sg:classifiers":[
        {
            "category":"Travel",
            "subcategory":"Campground",
            "type":"Entertainment"
        }
    ],
    "sg:phone":"+1 315 946 4436",
    "sg:postcode":"14489",
    "sg:province":"NY",
    "wof:name":"Nor-Win Farm & Campsites Inc",
    "wof:placetype":"venue"
},
  "geometry": {"coordinates":[-76.97028899999999,43.109748],"type":"Point"}
}