{
  "type": "Feature",
  "properties": {
    "addr:full":"441 Allen St Jamestown NY 14701",
    "addr:housenumber":"441",
    "addr:postcode":"14701",
    "addr:street":"Allen St",
    "iso:country":"US",
    "sg:address":"441 Allen St",
    "sg:city":"Jamestown",
    "sg:classifiers":[
        {
            "category":"Restaurant",
            "type":"Food & Drink"
        }
    ],
    "sg:phone":"+1 716 488 1419",
    "sg:postcode":"14701",
    "sg:province":"NY",
    "sg:tags":[
        "eating"
    ],
    "wof:name":"Stravato's Grill",
    "wof:placetype":"venue"
},
  "geometry": {"coordinates":[-79.226192,42.096341],"type":"Point"}
}