{
  "type": "Feature",
  "properties": {
    "addr:full":"East River Plaza 517 E 117th St Manhattan NY 10035",
    "addr:housenumber":"517",
    "addr:postcode":"10035",
    "addr:street":"E 117Th St",
    "iso:country":"US",
    "sg:address":"East River Plaza 517 E 117th St",
    "sg:city":"Manhattan",
    "sg:classifiers":[
        {
            "category":"Home & Garden",
            "subcategory":"Furniture",
            "type":"Retail Goods"
        }
    ],
    "sg:phone":"+1 646 400 6180",
    "sg:postcode":"10035",
    "sg:province":"NY",
    "sg:tags":[
        "store"
    ],
    "sg:website":"www.mybobs.com",
    "wof:name":"Bob's Discount Furniture",
    "wof:placetype":"venue"
},
  "geometry": {"coordinates":[-73.93194099999999,40.795418],"type":"Point"}
}