{
  "type": "Feature",
  "properties": {
    "addr:full":"256 5th Ave New York NY 10001",
    "addr:housenumber":"256",
    "addr:postcode":"10001",
    "addr:street":"5Th Ave",
    "iso:country":"US",
    "sg:address":"256 5th Ave",
    "sg:city":"New York",
    "sg:classifiers":[
        {
            "category":"Professional",
            "subcategory":"Business Services",
            "type":"Services"
        }
    ],
    "sg:phone":"+1 212 481 1313",
    "sg:postcode":"10001",
    "sg:province":"NY",
    "sg:tags":[
        "appraiser"
    ],
    "wof:name":"Appraisal Advisory Group LTD",
    "wof:placetype":"venue"
},
  "geometry": {"coordinates":[-73.987036,40.745112],"type":"Point"}
}