{
  "type": "Feature",
  "properties": {
    "addr:full":"525 E New York Ave Brooklyn NY 11225",
    "addr:housenumber":"525",
    "addr:postcode":"11225",
    "addr:street":"E New York Ave",
    "iso:country":"US",
    "sg:address":"525 E New York Ave",
    "sg:city":"Brooklyn",
    "sg:classifiers":[
        {
            "category":"Building & Trades",
            "subcategory":"Construction",
            "type":"Services"
        }
    ],
    "sg:phone":"+1 347 529 2529",
    "sg:postcode":"11225",
    "sg:province":"NY",
    "sg:tags":[
        "contractor"
    ],
    "wof:name":"MAT INC",
    "wof:placetype":"venue"
},
  "geometry": {"coordinates":[-73.94529,40.662035],"type":"Point"}
}