{
  "type": "Feature",
  "properties": {
    "iso:country":"US",
    "sg:address":"625 Ovington Ave",
    "sg:city":"Brooklyn",
    "sg:classifiers":[
        {
            "category":"Health Services",
            "subcategory":"Doctor",
            "type":"Services"
        }
    ],
    "sg:phone":"+1 718 833 6161",
    "sg:postcode":"11209",
    "sg:province":"NY",
    "sg:tags":[
        "medical"
    ],
    "wof:name":"Donald Martinelli MD",
    "wof:placetype":"venue"
},
  "geometry": {"coordinates":[-74.018247,40.631311],"type":"Point"}
}