{
  "type": "Feature",
  "properties": {
    "iso:country":"US",
    "sg:address":"15051 Northern Boulevard",
    "sg:city":"Flushing",
    "sg:classifiers":[
        {
            "category":"Restaurant",
            "type":"Food & Drink"
        }
    ],
    "sg:phone":"+1 718 321 8400",
    "sg:postcode":"11354",
    "sg:province":"NY",
    "wof:name":"Ho Hansol Corporation",
    "wof:placetype":"venue"
},
  "geometry": {"coordinates":[-73.81299,40.765176],"type":"Point"}
}