{
  "type": "Feature",
  "properties": {
    "iso:country":"US",
    "sg:address":"49 E Genesee St",
    "sg:city":"Baldwinsville",
    "sg:classifiers":[
        {
            "category":"Restaurant",
            "type":"Food & Drink"
        }
    ],
    "sg:menulink":"http://www.allmenus.com/ny/lysander/169790-burger-king/menu/",
    "sg:phone":"+1 315 635 9088",
    "sg:postcode":"13027",
    "sg:province":"NY",
    "sg:tags":[
        "burger",
        "american"
    ],
    "wof:name":"Burger King",
    "wof:placetype":"venue"
},
  "geometry": {"coordinates":[-76.326881,43.159126],"type":"Point"}
}