{
  "type": "Feature",
  "properties": {
    "iso:country":"US",
    "sg:address":"1871 Saunders Settlement Rd",
    "sg:city":"Niagara Falls",
    "sg:classifiers":[
        {
            "category":"Professional",
            "subcategory":"Computer Services",
            "type":"Services"
        }
    ],
    "sg:phone":"+1 716 297 5292",
    "sg:postcode":"14304",
    "sg:province":"NY",
    "sg:tags":[
        "internet"
    ],
    "wof:name":"Find It Quick Inc",
    "wof:placetype":"venue"
},
  "geometry": {"coordinates":[-78.965023,43.139016],"type":"Point"}
}