{
  "type": "Feature",
  "properties": {
    "iso:country":"US",
    "sg:address":"10439 Miller Rd",
    "sg:city":"Utica",
    "sg:classifiers":[
        {
            "category":"Building & Trades",
            "subcategory":"Construction",
            "type":"Services"
        }
    ],
    "sg:phone":"+1 315 732 8993",
    "sg:postcode":"13502",
    "sg:province":"NY",
    "sg:tags":[
        "contractor"
    ],
    "wof:name":"J K Siding",
    "wof:placetype":"venue"
},
  "geometry": {"coordinates":[-75.195032,43.173931],"type":"Point"}
}