{
  "type": "Feature",
  "properties": {
    "addr:full":"55 Motor Ave Farmingdale NY 11735",
    "addr:housenumber":"55",
    "addr:postcode":"11735",
    "addr:street":"Motor Ave",
    "iso:country":"US",
    "sg:address":"55 Motor Ave",
    "sg:city":"Farmingdale",
    "sg:classifiers":[
        {
            "category":"Building & Trades",
            "subcategory":"Construction",
            "type":"Services"
        }
    ],
    "sg:phone":"+1 631 842 4444",
    "sg:postcode":"11735",
    "sg:province":"NY",
    "sg:tags":[
        "rigging",
        "heavy",
        "industrial",
        "moving",
        "equipment"
    ],
    "wof:name":"Able Rigging Contractors Inc",
    "wof:placetype":"venue"
},
  "geometry": {"coordinates":[-73.44650300000001,40.725148],"type":"Point"}
}