{
  "type": "Feature",
  "properties": {
    "addr:full":"741 Main St East Aurora NY 14052",
    "addr:housenumber":"741",
    "addr:postcode":"14052",
    "addr:street":"Main St",
    "iso:country":"US",
    "sg:address":"741 Main St",
    "sg:city":"East Aurora",
    "sg:classifiers":[
        {
            "category":"Retail",
            "subcategory":"Auto Repair",
            "type":"Services"
        }
    ],
    "sg:phone":"+1 716 652 1241",
    "sg:postcode":"14052",
    "sg:province":"NY",
    "sg:tags":[
        "repairing",
        "automobile"
    ],
    "wof:name":"Erie 2 Boces Auto Tech Program",
    "wof:placetype":"venue"
},
  "geometry": {"coordinates":[-78.606718,42.767732],"type":"Point"}
}