{
  "type": "Feature",
  "properties": {
    "addr:full":"4114 Mapleton Rd Lockport NY 14094",
    "addr:housenumber":"4114",
    "addr:postcode":"14094",
    "addr:street":"Mapleton Rd",
    "iso:country":"US",
    "sg:address":"4114 Mapleton Rd",
    "sg:city":"Lockport",
    "sg:classifiers":[
        {
            "category":"Building & Trades",
            "subcategory":"Construction",
            "type":"Services"
        }
    ],
    "sg:phone":"+1 716 625 8632",
    "sg:postcode":"14094",
    "sg:province":"NY",
    "sg:tags":[
        "system",
        "specialty",
        "heating",
        "contractor",
        "ventilating",
        "air conditioning"
    ],
    "sg:website":"http://www.bennetthvac.com",
    "wof:name":"Bennett Heating & Cooling",
    "wof:placetype":"venue"
},
  "geometry": {"coordinates":[-78.82422699999999,43.122348],"type":"Point"}
}