{
  "type": "Feature",
  "properties": {
    "iso:country":"US",
    "sg:address":"138 W 15th St",
    "sg:city":"New York",
    "sg:classifiers":[
        {
            "category":"Shopping",
            "subcategory":"Books",
            "type":"Retail Goods"
        }
    ],
    "sg:phone":"+1 212 242 8945",
    "sg:postcode":"10011",
    "sg:province":"NY",
    "sg:tags":[
        "bookstore"
    ],
    "wof:name":"Rudolf Steiner Bookstore An",
    "wof:placetype":"venue"
},
  "geometry": {"coordinates":[-73.99839799999999,40.738998],"type":"Point"}
}