{
  "type": "Feature",
  "properties": {
    "addr:full":"7421 18th Ave Brooklyn NY 11204",
    "addr:housenumber":"7421",
    "addr:postcode":"11204",
    "addr:street":"18Th Ave",
    "iso:country":"US",
    "sg:address":"7421 18th Ave",
    "sg:city":"Brooklyn",
    "sg:classifiers":[
        {
            "category":"Health Services",
            "subcategory":"Doctor",
            "type":"Services"
        },
        {
            "category":"Recreation",
            "subcategory":"Amusement Park",
            "type":"Entertainment"
        },
        {
            "category":"Arena",
            "subcategory":"Sports Club",
            "type":"Entertainment"
        }
    ],
    "sg:phone":"+1 718 621 5425",
    "sg:postcode":"11204",
    "sg:province":"NY",
    "sg:tags":[
        "martial art"
    ],
    "sg:website":"www.championstkd.com",
    "wof:name":"Champions Tae Kwon Do",
    "wof:placetype":"venue"
},
  "geometry": {"coordinates":[-73.995349,40.613777],"type":"Point"}
}