{
  "type": "Feature",
  "properties": {
    "addr:full":"114 Eldridge St New York NY 10002",
    "addr:housenumber":"114",
    "addr:postcode":"10002",
    "addr:street":"Eldridge St",
    "iso:country":"US",
    "sg:address":"114 Eldridge St",
    "sg:city":"New York",
    "sg:classifiers":[
        {
            "category":"Wholesale",
            "subcategory":"Seafood",
            "type":"Manufacturing & Wholesale Goods"
        }
    ],
    "sg:phone":"+1 212 925 2036",
    "sg:postcode":"10002",
    "sg:province":"NY",
    "sg:tags":[
        "frozen"
    ],
    "wof:name":"Grand China Trading Inc",
    "wof:placetype":"venue"
},
  "geometry": {"coordinates":[-73.99188599999999,40.718016],"type":"Point"}
}