{
  "type": "Feature",
  "properties": {
    "iso:country":"US",
    "sg:address":"2496 Marion Avenue",
    "sg:city":"Bronx",
    "sg:classifiers":[
        {
            "category":"Organizations",
            "subcategory":"Religious Organization",
            "type":"Services"
        }
    ],
    "sg:phone":"+1 718 933 4400",
    "sg:postcode":"10458",
    "sg:province":"NY",
    "sg:website":"www.ladyofmercychurch.com",
    "wof:name":"Our Lady of Mercy Church",
    "wof:placetype":"venue"
},
  "geometry": {"coordinates":[-73.893686,40.860527],"type":"Point"}
}