{
  "type": "Feature",
  "properties": {
    "addr:full":"8 Hillside Close White Plains NY 10603",
    "addr:housenumber":"8",
    "addr:postcode":"10603",
    "addr:street":"Hillside Close",
    "iso:country":"US",
    "sg:address":"8 Hillside Close",
    "sg:city":"White Plains",
    "sg:classifiers":[
        {
            "category":"Organizations",
            "subcategory":"Religious Organization",
            "type":"Services"
        }
    ],
    "sg:phone":"+1 914 761 4887",
    "sg:postcode":"10603",
    "sg:province":"NY",
    "sg:tags":[
        "clergy"
    ],
    "wof:name":"Mc Kinney Landscaping Corp",
    "wof:placetype":"venue"
},
  "geometry": {"coordinates":[-73.789888,41.049099],"type":"Point"}
}