{
  "type": "Feature",
  "properties": {
    "addr:full":"249 Nassau Ave Brooklyn NY 11222",
    "addr:housenumber":"249",
    "addr:postcode":"11222",
    "addr:street":"Nassau Ave",
    "iso:country":"US",
    "sg:address":"249 Nassau Ave",
    "sg:city":"Brooklyn",
    "sg:classifiers":[
        {
            "category":"Home & Garden",
            "subcategory":"Building Materials",
            "type":"Retail Goods"
        }
    ],
    "sg:phone":"+1 718 383 0578",
    "sg:postcode":"11222",
    "sg:province":"NY",
    "sg:tags":[
        "plumbing",
        "fixture",
        "supply"
    ],
    "wof:name":"Eddies Plumbing Supplies",
    "wof:placetype":"venue"
},
  "geometry": {"coordinates":[-73.941956,40.725845],"type":"Point"}
}