{
  "type": "Feature",
  "properties": {
    "addr:full":"197 Medford Ave Patchogue NY 11772",
    "addr:housenumber":"197",
    "addr:postcode":"11772",
    "addr:street":"Medford Ave",
    "iso:country":"US",
    "sg:address":"197 Medford Ave",
    "sg:city":"Patchogue",
    "sg:classifiers":[
        {
            "category":"Personal",
            "subcategory":"Barber",
            "type":"Services"
        }
    ],
    "sg:phone":"+1 631 758 8849",
    "sg:postcode":"11772",
    "sg:province":"NY",
    "sg:tags":[
        "shop"
    ],
    "wof:name":"Carl's Barber Shop",
    "wof:placetype":"venue"
},
  "geometry": {"coordinates":[-73.007533,40.773001],"type":"Point"}
}