{
  "type": "Feature",
  "properties": {
    "addr:full":"852 Commerce St Thornwood NY 10594",
    "addr:housenumber":"852",
    "addr:postcode":"10594",
    "addr:street":"Commerce St",
    "iso:country":"US",
    "sg:address":"852 Commerce St",
    "sg:city":"Thornwood",
    "sg:classifiers":[
        {
            "category":"Arts & Performance",
            "subcategory":"Arts Center",
            "type":"Entertainment"
        }
    ],
    "sg:phone":"+1 914 769 5088",
    "sg:postcode":"10594",
    "sg:province":"NY",
    "sg:tags":[
        "performing"
    ],
    "wof:name":"Gotta Dance",
    "wof:placetype":"venue"
},
  "geometry": {"coordinates":[-73.7817,41.1217],"type":"Point"}
}