{
  "type": "Feature",
  "properties": {
    "addr:full":"180 Perry St Buffalo NY 14204",
    "addr:housenumber":"180",
    "addr:postcode":"14204",
    "addr:street":"Perry St",
    "iso:country":"US",
    "sg:address":"180 Perry St",
    "sg:city":"Buffalo",
    "sg:classifiers":[
        {
            "category":"Manufacturing",
            "subcategory":"Printing",
            "type":"Manufacturing & Wholesale Goods"
        }
    ],
    "sg:phone":"+1 716 853 4480",
    "sg:postcode":"14204",
    "sg:province":"NY",
    "sg:tags":[
        "printer"
    ],
    "wof:name":"Ansel Press Inc",
    "wof:placetype":"venue"
},
  "geometry": {"coordinates":[-78.870825,42.875002],"type":"Point"}
}