{
  "type": "Feature",
  "properties": {
    "iso:country":"US",
    "sg:address":"300 Ormond St",
    "sg:city":"Rochester",
    "sg:classifiers":[
        {
            "category":"Professional",
            "subcategory":"Printing & Photocopies",
            "type":"Services"
        }
    ],
    "sg:phone":"+1 585 454 2950",
    "sg:postcode":"14605",
    "sg:province":"NY",
    "sg:tags":[
        "medal",
        "plaque",
        "trophies"
    ],
    "sg:website":"http://www.adflexcorp.com",
    "wof:name":"Adflex Corporation",
    "wof:placetype":"venue"
},
  "geometry": {"coordinates":[-77.60547699999999,43.16377],"type":"Point"}
}