{
  "type": "Feature",
  "properties": {
    "iso:country":"US",
    "sg:address":"73 Adirondack Dr",
    "sg:city":"Selden",
    "sg:classifiers":[
        {
            "category":"Building & Trades",
            "subcategory":"Construction",
            "type":"Services"
        }
    ],
    "sg:phone":"+1 631 736 0008",
    "sg:postcode":"11784",
    "sg:province":"NY",
    "sg:tags":[
        "general",
        "contractor"
    ],
    "wof:name":"Mc Croy Brothers Contracting",
    "wof:placetype":"venue"
},
  "geometry": {"coordinates":[-73.029054,40.862998],"type":"Point"}
}