{
  "type": "Feature",
  "properties": {
    "addr:full":"50 George St Inwood NY 11030",
    "addr:housenumber":"50",
    "addr:postcode":"11030",
    "addr:street":"George St",
    "iso:country":"US",
    "sg:address":"50 George St",
    "sg:city":"Inwood",
    "sg:classifiers":[
        {
            "category":"Bus Charters",
            "type":"Transportation"
        },
        {
            "category":"Local Transit",
            "type":"Transportation"
        }
    ],
    "sg:phone":"+1 718 327 8500",
    "sg:postcode":"11030",
    "sg:province":"NY",
    "sg:tags":[
        "line"
    ],
    "wof:name":"Brent Bus Svce Inc",
    "wof:placetype":"venue"
},
  "geometry": {"coordinates":[-73.69659299999999,40.794651],"type":"Point"}
}