{
  "type": "Feature",
  "properties": {
    "addr:full":"97 Greenport Ave Medford NY 11763",
    "addr:housenumber":"97",
    "addr:postcode":"11763",
    "addr:street":"Greenport Ave",
    "iso:country":"US",
    "sg:address":"97 Greenport Ave",
    "sg:city":"Medford",
    "sg:classifiers":[
        {
            "category":"Building & Trades",
            "subcategory":"Cleaning & Sanitation",
            "type":"Services"
        }
    ],
    "sg:phone":"+1 631 758 1179",
    "sg:postcode":"11763",
    "sg:province":"NY",
    "sg:tags":[
        "janitor"
    ],
    "wof:name":"Dees Dust Buster",
    "wof:placetype":"venue"
},
  "geometry": {"coordinates":[-72.995394,40.809006],"type":"Point"}
}