{
  "type": "Feature",
  "properties": {
    "iso:country":"US",
    "sg:address":"11 Wilton Rd",
    "sg:city":"Port Chester",
    "sg:classifiers":[
        {
            "category":"Building & Trades",
            "subcategory":"Construction",
            "type":"Services"
        }
    ],
    "sg:phone":"+1 914 937 2672",
    "sg:postcode":"10573",
    "sg:province":"NY",
    "sg:tags":[
        "shop",
        "beauty",
        "contractor"
    ],
    "wof:name":"Event Productions Ltd",
    "wof:placetype":"venue"
},
  "geometry": {"coordinates":[-73.685316,41.010763],"type":"Point"}
}