{
  "type": "Feature",
  "properties": {
    "addr:full":"1255 E 37th St Brooklyn NY 11210",
    "addr:housenumber":"1255",
    "addr:postcode":"11210",
    "addr:street":"E 37Th St",
    "iso:country":"US",
    "sg:address":"1255 E 37th St",
    "sg:city":"Brooklyn",
    "sg:classifiers":[
        {
            "category":"Local Transit",
            "type":"Transportation"
        }
    ],
    "sg:phone":"+1   ",
    "sg:postcode":"11210",
    "sg:province":"NY",
    "sg:tags":[
        "passenger"
    ],
    "wof:name":"Astro Ambulette Corp",
    "wof:placetype":"venue"
},
  "geometry": {"coordinates":[-73.94015400000001,40.627179],"type":"Point"}
}