{
  "type": "Feature",
  "properties": {
    "addr:full":"20 S Skaneateles St Jordan NY 13080",
    "addr:housenumber":"20",
    "addr:postcode":"13080",
    "addr:street":"S Skaneateles St",
    "iso:country":"US",
    "sg:address":"20 S Skaneateles St",
    "sg:city":"Jordan",
    "sg:classifiers":[
        {
            "category":"Professional",
            "subcategory":"Accounting & Tax Preparation",
            "type":"Services"
        }
    ],
    "sg:phone":"+1 315 689 3525",
    "sg:postcode":"13080",
    "sg:province":"NY",
    "sg:tags":[
        "bookkeeping",
        "general"
    ],
    "wof:name":"Bcw Assoc",
    "wof:placetype":"venue"
},
  "geometry": {"coordinates":[-76.467348,43.063112],"type":"Point"}
}