{
  "type": "Feature",
  "properties": {
    "iso:country":"US",
    "sg:address":"8403 18th Ave",
    "sg:city":"Brooklyn",
    "sg:classifiers":[
        {
            "category":"Education",
            "subcategory":"Music School",
            "type":"Public Place"
        }
    ],
    "sg:phone":"+1 718 259 4468",
    "sg:postcode":"11214",
    "sg:province":"NY",
    "sg:tags":[
        "instrument",
        "teacher",
        "musical"
    ],
    "sg:website":"www.maggiomusiccenter.com/",
    "wof:name":"Maggio Music Center",
    "wof:placetype":"venue"
},
  "geometry": {"coordinates":[-74.00129800000001,40.608355],"type":"Point"}
}