{
  "type": "Feature",
  "properties": {
    "addr:full":"555 5th Ave New York NY 10017",
    "addr:housenumber":"555",
    "addr:postcode":"10017",
    "addr:street":"5Th Ave",
    "iso:country":"US",
    "sg:address":"555 5th Ave",
    "sg:city":"New York",
    "sg:classifiers":[
        {
            "category":"Wholesale",
            "subcategory":"Jewelry",
            "type":"Manufacturing & Wholesale Goods"
        }
    ],
    "sg:phone":"+1 212 682 2999",
    "sg:postcode":"10017",
    "sg:province":"NY",
    "sg:tags":[
        "diamond",
        "fine",
        "store"
    ],
    "wof:name":"Howard Engle Inc",
    "wof:placetype":"venue"
},
  "geometry": {"coordinates":[-73.979074,40.755786],"type":"Point"}
}