{
  "type": "Feature",
  "properties": {
    "addr:full":"1046 Southern Blvd Bronx NY 10459",
    "addr:housenumber":"1046",
    "addr:postcode":"10459",
    "addr:street":"Southern Blvd",
    "iso:country":"US",
    "sg:address":"1046 Southern Blvd",
    "sg:city":"Bronx",
    "sg:classifiers":[
        {
            "category":"Banks & Credit Unions",
            "subcategory":"Bank",
            "type":"Services"
        }
    ],
    "sg:phone":"+1 347 748 7135",
    "sg:postcode":"10459",
    "sg:province":"NY",
    "sg:tags":[
        "commercial",
        "saving"
    ],
    "sg:website":"http://www.bpop.com",
    "wof:name":"Banco Popular",
    "wof:placetype":"venue"
},
  "geometry": {"coordinates":[-73.891711,40.824358],"type":"Point"}
}