{
  "type": "Feature",
  "properties": {
    "iso:country":"US",
    "sg:address":"1050 East Ave",
    "sg:city":"Rochester",
    "sg:classifiers":[
        {
            "category":"Arts & Performance",
            "subcategory":"Theater",
            "type":"Entertainment"
        }
    ],
    "sg:phone":"+1   ",
    "sg:postcode":"14607",
    "sg:province":"NY",
    "sg:tags":[
        "group"
    ],
    "sg:website":"www.rossings.org",
    "wof:name":"Rochester Oratorio Society",
    "wof:placetype":"venue"
},
  "geometry": {"coordinates":[-77.57538099999999,43.15048],"type":"Point"}
}