{
  "type": "Feature",
  "properties": {
    "addr:full":"402 Graham Ave Brooklyn NY 11211",
    "addr:housenumber":"402",
    "addr:postcode":"11211",
    "addr:street":"Graham Ave",
    "iso:country":"US",
    "sg:address":"402 Graham Ave",
    "sg:city":"Brooklyn",
    "sg:classifiers":[
        {
            "category":"Education",
            "subcategory":"School",
            "type":"Public Place"
        }
    ],
    "sg:phone":"+1 718 383 2491",
    "sg:postcode":"11211",
    "sg:province":"NY",
    "wof:name":"Educate Inc",
    "wof:placetype":"venue"
},
  "geometry": {"coordinates":[-73.94455499999999,40.716768],"type":"Point"}
}