{
  "type": "Feature",
  "properties": {
    "iso:country":"US",
    "sg:address":"255 Ave of the Americas",
    "sg:city":"New York",
    "sg:classifiers":[
        {
            "category":"Professional",
            "type":"Services"
        }
    ],
    "sg:phone":"+1 212 627 2570",
    "sg:postcode":"10014",
    "sg:province":"NY",
    "sg:tags":[
        "establishment"
    ],
    "wof:name":"BLE Inc",
    "wof:placetype":"venue"
},
  "geometry": {"coordinates":[-74.00220299999999,40.729654],"type":"Point"}
}