{
  "type": "Feature",
  "properties": {
    "addr:full":"3335 Hempstead Tpke Levittown NY 11756",
    "addr:housenumber":"3335",
    "addr:postcode":"11756",
    "addr:street":"Hempstead Tpke",
    "iso:country":"US",
    "sg:address":"3335 Hempstead Tpke",
    "sg:city":"Levittown",
    "sg:classifiers":[
        {
            "category":"Food & Beverages",
            "subcategory":"Groceries & Convenience Stores",
            "type":"Retail Goods"
        }
    ],
    "sg:phone":"+1 516 731 5287",
    "sg:postcode":"11756",
    "sg:province":"NY",
    "wof:name":"Waldbaums",
    "wof:placetype":"venue"
},
  "geometry": {"coordinates":[-73.513603,40.726101],"type":"Point"}
}