{
  "type": "Feature",
  "properties": {
    "addr:full":"3451 Junction Blvd Jackson Heights NY 11372",
    "addr:housenumber":"3451",
    "addr:postcode":"11372",
    "addr:street":"Junction Blvd",
    "iso:country":"US",
    "sg:address":"3451 Junction Blvd",
    "sg:city":"Jackson Heights",
    "sg:classifiers":[
        {
            "category":"Restaurant",
            "type":"Food & Drink"
        }
    ],
    "sg:phone":"+1 718 898 0668",
    "sg:postcode":"11372",
    "sg:province":"NY",
    "sg:tags":[
        "chinese"
    ],
    "wof:name":"Top of China",
    "wof:placetype":"venue"
},
  "geometry": {"coordinates":[-73.871803,40.7537],"type":"Point"}
}