{
  "type": "Feature",
  "properties": {
    "addr:full":"300 Rte 109 Farmingdale NY 11735",
    "addr:housenumber":"300",
    "addr:postcode":"11735",
    "addr:street":"Rte 109",
    "iso:country":"US",
    "sg:address":"300 Rte 109",
    "sg:city":"Farmingdale",
    "sg:classifiers":[
        {
            "category":"Wholesale",
            "subcategory":"Electrical",
            "type":"Manufacturing & Wholesale Goods"
        }
    ],
    "sg:phone":"+1 631 752 9824",
    "sg:postcode":"11735",
    "sg:province":"NY",
    "sg:tags":[
        "equipment",
        "lighting",
        "system"
    ],
    "wof:name":"Farralane Lighting Audio",
    "wof:placetype":"venue"
},
  "geometry": {"coordinates":[-73.42522099999999,40.722569],"type":"Point"}
}