{
  "type": "Feature",
  "properties": {
    "addr:full":"862 State Hwy 6n Mahopac NY 10541",
    "addr:housenumber":"862",
    "addr:postcode":"10541",
    "addr:street":"State Hwy",
    "iso:country":"US",
    "sg:address":"862 State Hwy 6n",
    "sg:city":"Mahopac",
    "sg:classifiers":[
        {
            "category":"Recreation",
            "type":"Entertainment"
        }
    ],
    "sg:phone":"+1 845 628 5425",
    "sg:postcode":"10541",
    "sg:province":"NY",
    "sg:tags":[
        "martial",
        "arts",
        "instruction"
    ],
    "wof:name":"Yasuragi Center",
    "wof:placetype":"venue"
},
  "geometry": {"coordinates":[-73.74373,41.3722],"type":"Point"}
}