{
  "type": "Feature",
  "properties": {
    "iso:country":"US",
    "sg:address":"10 Ten Eyck St",
    "sg:city":"Brooklyn",
    "sg:classifiers":[
        {
            "category":"Organizations",
            "subcategory":"Religious Organization",
            "type":"Services"
        }
    ],
    "sg:phone":"+1 718 599 7956",
    "sg:postcode":"11206",
    "sg:province":"NY",
    "wof:name":"Broadway Spanish Congregation of Jehova's Witness",
    "wof:placetype":"venue"
},
  "geometry": {"coordinates":[-73.95030199999999,40.709499],"type":"Point"}
}