{
  "type": "Feature",
  "properties": {
    "iso:country":"US",
    "sg:address":"287 Warner Ave",
    "sg:city":"Roslyn Heights",
    "sg:classifiers":[
        {
            "category":"Food & Beverages",
            "subcategory":"Groceries & Convenience Stores",
            "type":"Retail Goods"
        }
    ],
    "sg:phone":"+1 516 484 2100",
    "sg:postcode":"11577",
    "sg:province":"NY",
    "wof:name":"Glatt Mart International Food Corp",
    "wof:placetype":"venue"
},
  "geometry": {"coordinates":[-73.64448299999999,40.791981],"type":"Point"}
}