{
  "type": "Feature",
  "properties": {
    "addr:full":"1525 Myrtle Avenue Brooklyn NY 11237",
    "addr:housenumber":"1525",
    "addr:postcode":"11237",
    "addr:street":"Myrtle Avenue",
    "iso:country":"US",
    "sg:address":"1525 Myrtle Avenue",
    "sg:city":"Brooklyn",
    "sg:classifiers":[
        {
            "category":"Food & Beverages",
            "subcategory":"Groceries & Convenience Stores",
            "type":"Retail Goods"
        }
    ],
    "sg:phone":"+1 718 366 6831",
    "sg:postcode":"11237",
    "sg:province":"NY",
    "wof:name":"Jasco Mart",
    "wof:placetype":"venue"
},
  "geometry": {"coordinates":[-73.914469,40.699322],"type":"Point"}
}