{
  "type": "Feature",
  "properties": {
    "addr:full":"125 Dolson Ave Middletown NY 10940",
    "addr:housenumber":"125",
    "addr:postcode":"10940",
    "addr:street":"Dolson Ave",
    "iso:country":"US",
    "sg:address":"125 Dolson Ave",
    "sg:city":"Middletown",
    "sg:classifiers":[
        {
            "category":"Autos & Motor Vehicles",
            "subcategory":"Auto Supplies",
            "type":"Retail Goods"
        }
    ],
    "sg:phone":"+1 845 343 1493",
    "sg:postcode":"10940",
    "sg:province":"NY",
    "sg:tags":[
        "tire"
    ],
    "wof:name":"Middletown Goodyear",
    "wof:placetype":"venue"
},
  "geometry": {"coordinates":[-74.422346,41.432385],"type":"Point"}
}