{
  "type": "Feature",
  "properties": {
    "iso:country":"US",
    "sg:address":"10 Hamilton Ave",
    "sg:city":"Monticello",
    "sg:classifiers":[
        {
            "category":"Professional",
            "subcategory":"Lawyer & Legal Services",
            "type":"Services"
        }
    ],
    "sg:phone":"+1 845 794 5110",
    "sg:postcode":"12701",
    "sg:province":"NY",
    "sg:tags":[
        "attorney",
        "practice"
    ],
    "wof:name":"Cooke Edward M",
    "wof:placetype":"venue"
},
  "geometry": {"coordinates":[-74.68163,41.655563],"type":"Point"}
}