{
  "type": "Feature",
  "properties": {
    "addr:full":"2809 Steinway St Astoria NY 11103",
    "addr:housenumber":"2809",
    "addr:postcode":"11103",
    "addr:street":"Steinway St",
    "iso:country":"US",
    "sg:address":"2809 Steinway St",
    "sg:city":"Astoria",
    "sg:classifiers":[
        {
            "category":"Home & Garden",
            "subcategory":"Hardware",
            "type":"Retail Goods"
        }
    ],
    "sg:phone":"+1 718 728 3020",
    "sg:postcode":"11103",
    "sg:province":"NY",
    "sg:tags":[
        "store"
    ],
    "wof:name":"Straus Paint & Hardware Co",
    "wof:placetype":"venue"
},
  "geometry": {"coordinates":[-73.913803,40.765099],"type":"Point"}
}