{
  "type": "Feature",
  "properties": {
    "iso:country":"US",
    "sg:address":"325 Sebonac Rd",
    "sg:city":"Southampton",
    "sg:classifiers":[
        {
            "category":"Airline",
            "type":"Transportation"
        }
    ],
    "sg:phone":"+1   ",
    "sg:postcode":"11968",
    "sg:province":"NY",
    "sg:tags":[
        "nonscheduled",
        "air"
    ],
    "wof:name":"Mariner Sail Charters",
    "wof:placetype":"venue"
},
  "geometry": {"coordinates":[-72.431518,40.901297],"type":"Point"}
}