{
  "type": "Feature",
  "properties": {
    "addr:full":"236 Larkfield Rd East Northport NY 11731",
    "addr:housenumber":"236",
    "addr:postcode":"11731",
    "addr:street":"Larkfield Rd",
    "iso:country":"US",
    "sg:address":"236 Larkfield Rd",
    "sg:city":"East Northport",
    "sg:classifiers":[
        {
            "category":"Retail",
            "subcategory":"Auto Repair",
            "type":"Services"
        }
    ],
    "sg:phone":"+1 631 757 4804",
    "sg:postcode":"11731",
    "sg:province":"NY",
    "sg:tags":[
        "repairing",
        "automobile"
    ],
    "wof:name":"Gary's Automotive",
    "wof:placetype":"venue"
},
  "geometry": {"coordinates":[-73.324507,40.875982],"type":"Point"}
}