{
  "type": "Feature",
  "properties": {
    "iso:country":"US",
    "sg:address":"13 South St",
    "sg:city":"Geneseo",
    "sg:classifiers":[
        {
            "category":"Government",
            "subcategory":"Post Office",
            "type":"Public Place"
        }
    ],
    "sg:phone":"+1   ",
    "sg:postcode":"14454",
    "sg:province":"NY",
    "sg:tags":[
        "postal",
        "us"
    ],
    "wof:name":"US Post Office",
    "wof:placetype":"venue"
},
  "geometry": {"coordinates":[-77.816154,42.793378],"type":"Point"}
}