{
  "type": "Feature",
  "properties": {
    "addr:full":"5844 Transit Rd Depew NY 14043",
    "addr:housenumber":"5844",
    "addr:postcode":"14043",
    "addr:street":"Transit Rd",
    "iso:country":"US",
    "sg:address":"5844 Transit Rd",
    "sg:city":"Depew",
    "sg:classifiers":[
        {
            "category":"Shopping",
            "subcategory":"Used Merchandise",
            "type":"Retail Goods"
        }
    ],
    "sg:phone":"+1 716 681 7296",
    "sg:postcode":"14043",
    "sg:province":"NY",
    "sg:tags":[
        "pawnbroker"
    ],
    "wof:name":"Cash & Go Pawn",
    "wof:placetype":"venue"
},
  "geometry": {"coordinates":[-78.69699,42.913973],"type":"Point"}
}