{
  "type": "Feature",
  "properties": {
    "addr:full":"322 Lexington Ave New York NY 10016",
    "addr:housenumber":"322",
    "addr:postcode":"10016",
    "addr:street":"Lexington Ave",
    "iso:country":"US",
    "sg:address":"322 Lexington Ave",
    "sg:city":"New York",
    "sg:classifiers":[
        {
            "category":"Shopping",
            "subcategory":"Florist",
            "type":"Retail Goods"
        }
    ],
    "sg:phone":"+1   ",
    "sg:postcode":"10016",
    "sg:province":"NY",
    "wof:name":"Flowers By Angelo LTD",
    "wof:placetype":"venue"
},
  "geometry": {"coordinates":[-73.977653,40.7493],"type":"Point"}
}