{
  "type": "Feature",
  "properties": {
    "iso:country":"US",
    "sg:address":"7490 Fisher Rd",
    "sg:city":"Ontario",
    "sg:classifiers":[
        {
            "category":"Professional",
            "subcategory":"Management & Consulting",
            "type":"Services"
        }
    ],
    "sg:phone":"+1   ",
    "sg:postcode":"14519",
    "sg:province":"NY",
    "wof:name":"Gambit",
    "wof:placetype":"venue"
},
  "geometry": {"coordinates":[-77.252117,43.268948],"type":"Point"}
}