{
  "type": "Feature",
  "properties": {
    "iso:country":"US",
    "sg:address":"3799 Ransom Rd",
    "sg:city":"Jamesville",
    "sg:classifiers":[
        {
            "category":"Building & Trades",
            "subcategory":"Construction",
            "type":"Services"
        }
    ],
    "sg:phone":"+1 315 427 4724",
    "sg:postcode":"13078",
    "sg:province":"NY",
    "sg:tags":[
        "house"
    ],
    "wof:name":"Woodruff Construction",
    "wof:placetype":"venue"
},
  "geometry": {"coordinates":[-76.049252,42.95462],"type":"Point"}
}