{
  "type": "Feature",
  "properties": {
    "iso:country":"US",
    "sg:address":"118 N Main St",
    "sg:city":"Oneida",
    "sg:classifiers":[
        {
            "category":"Restaurant",
            "type":"Food & Drink"
        }
    ],
    "sg:phone":"+1 315 361 4441",
    "sg:postcode":"13421",
    "sg:province":"NY",
    "sg:tags":[
        "eating"
    ],
    "wof:name":"Sweet Temptations Cafe",
    "wof:placetype":"venue"
},
  "geometry": {"coordinates":[-75.653319,43.097262],"type":"Point"}
}