{
  "type": "Feature",
  "properties": {
    "addr:full":"2102 Mecklenburg Rd Ithaca NY 14850",
    "addr:housenumber":"2102",
    "addr:postcode":"14850",
    "addr:street":"Mecklenburg Rd",
    "iso:country":"US",
    "sg:address":"2102 Mecklenburg Rd",
    "sg:city":"Ithaca",
    "sg:classifiers":[
        {
            "category":"Food & Beverages",
            "subcategory":"Groceries & Convenience Stores",
            "type":"Retail Goods"
        }
    ],
    "sg:phone":"+1 607 273 6015",
    "sg:postcode":"14850",
    "sg:province":"NY",
    "sg:tags":[
        "grocer"
    ],
    "wof:name":"Valley Corners Grocers",
    "wof:placetype":"venue"
},
  "geometry": {"coordinates":[-76.631264,42.451043],"type":"Point"}
}