{
  "type": "Feature",
  "properties": {
    "addr:full":"170 Church St Amsterdam NY 12010",
    "addr:housenumber":"170",
    "addr:postcode":"12010",
    "addr:street":"Church St",
    "iso:country":"US",
    "sg:address":"170 Church St",
    "sg:city":"Amsterdam",
    "sg:classifiers":[
        {
            "category":"Autos & Motor Vehicles",
            "subcategory":"Fuel & Gas Station",
            "type":"Retail Goods"
        }
    ],
    "sg:phone":"+1 518 842 3360",
    "sg:postcode":"12010",
    "sg:province":"NY",
    "sg:tags":[
        "oil"
    ],
    "wof:name":"Citgo",
    "wof:placetype":"venue"
},
  "geometry": {"coordinates":[-74.178202,42.937115],"type":"Point"}
}