{
  "type": "Feature",
  "properties": {
    "addr:full":"7226 Amboy Rd Staten Island NY 10307",
    "addr:housenumber":"7226",
    "addr:postcode":"10307",
    "addr:street":"Amboy Rd",
    "iso:country":"US",
    "sg:address":"7226 Amboy Rd",
    "sg:city":"Staten Island",
    "sg:classifiers":[
        {
            "category":"Restaurant",
            "type":"Food & Drink"
        }
    ],
    "sg:menulink":"http://www.allmenus.com/ny/staten-island/43390-chef-hong/menu/",
    "sg:phone":"+1 718 227 0100",
    "sg:postcode":"10307",
    "sg:province":"NY",
    "sg:tags":[
        "asian",
        "chinese"
    ],
    "wof:name":"Chef Hong",
    "wof:placetype":"venue"
},
  "geometry": {"coordinates":[-74.238884,40.512446],"type":"Point"}
}