{
  "type": "Feature",
  "properties": {
    "iso:country":"US",
    "sg:address":"191 Wiltsie Bridge Rd",
    "sg:city":"Ancramdale",
    "sg:classifiers":[
        {
            "category":"Shopping",
            "subcategory":"Antiques",
            "type":"Retail Goods"
        },
        {
            "category":"Professional",
            "subcategory":"Art Services",
            "type":"Services"
        }
    ],
    "sg:phone":"+1 518 329 0443",
    "sg:postcode":"12503",
    "sg:province":"NY",
    "sg:tags":[
        "repair",
        "restoration",
        "reproduction"
    ],
    "wof:name":"Crown Antiques",
    "wof:placetype":"venue"
},
  "geometry": {"coordinates":[-73.57849899999999,42.069289],"type":"Point"}
}