{
  "type": "Feature",
  "properties": {
    "iso:country":"US",
    "sg:address":"1152 E River Rd",
    "sg:city":"Grand Island",
    "sg:classifiers":[
        {
            "category":"Retail",
            "subcategory":"Repair Shop",
            "type":"Services"
        }
    ],
    "sg:phone":"+1 716 874 7668",
    "sg:postcode":"14072",
    "sg:province":"NY",
    "sg:tags":[
        "welding"
    ],
    "wof:name":"Henco Welding & Fabrication",
    "wof:placetype":"venue"
},
  "geometry": {"coordinates":[-78.944455,42.994981],"type":"Point"}
}