{
  "type": "Feature",
  "properties": {
    "addr:full":"3422 Foster Valley Rd Owego NY 13827",
    "addr:housenumber":"3422",
    "addr:postcode":"13827",
    "addr:street":"Foster Valley Rd",
    "iso:country":"US",
    "sg:address":"3422 Foster Valley Rd",
    "sg:city":"Owego",
    "sg:classifiers":[
        {
            "category":"Building & Trades",
            "subcategory":"Construction",
            "type":"Services"
        }
    ],
    "sg:phone":"+1 607 785 6975",
    "sg:postcode":"13827",
    "sg:province":"NY",
    "sg:tags":[
        "excavation",
        "contractor"
    ],
    "wof:name":"Wanck S Dozer Work Plus",
    "wof:placetype":"venue"
},
  "geometry": {"coordinates":[-76.14380800000001,42.164825],"type":"Point"}
}