{
  "type": "Feature",
  "properties": {
    "iso:country":"US",
    "sg:address":"1128 E Bluff Dr",
    "sg:city":"Penn Yan",
    "sg:classifiers":[
        {
            "category":"Banks & Credit Unions",
            "subcategory":"Investment Brokerage",
            "type":"Services"
        }
    ],
    "sg:phone":"+1 315 536 7895",
    "sg:postcode":"14527",
    "sg:province":"NY",
    "sg:tags":[
        "advisory"
    ],
    "wof:name":"Independent Investors Forum",
    "wof:placetype":"venue"
},
  "geometry": {"coordinates":[-77.11617,42.520288],"type":"Point"}
}