{
  "type": "Feature",
  "properties": {
    "iso:country":"US",
    "sg:address":"74 Island Dr",
    "sg:city":"Rye",
    "sg:classifiers":[
        {
            "category":"Banks & Credit Unions",
            "subcategory":"Investment Brokerage",
            "type":"Services"
        }
    ],
    "sg:phone":"+1 914 967 2208",
    "sg:postcode":"10580",
    "sg:province":"NY",
    "sg:tags":[
        "security"
    ],
    "wof:name":"Marvin H Davidson Co Inc",
    "wof:placetype":"venue"
},
  "geometry": {"coordinates":[-73.658795,40.979916],"type":"Point"}
}