{
  "type": "Feature",
  "properties": {
    "addr:full":"470 Cayuga Rd Buffalo NY 14225",
    "addr:housenumber":"470",
    "addr:postcode":"14225",
    "addr:street":"Cayuga Rd",
    "iso:country":"US",
    "sg:address":"470 Cayuga Rd",
    "sg:city":"Buffalo",
    "sg:classifiers":[
        {
            "category":"Wholesale",
            "subcategory":"Furniture",
            "type":"Manufacturing & Wholesale Goods"
        }
    ],
    "sg:phone":"+1 716 633 5600",
    "sg:postcode":"14225",
    "sg:province":"NY",
    "sg:website":"www.millingtonlockwood.com",
    "wof:name":"Millington Lockwood Inc",
    "wof:placetype":"venue"
},
  "geometry": {"coordinates":[-78.744528,42.94327],"type":"Point"}
}