{
  "type": "Feature",
  "properties": {
    "addr:full":"777 Nepperhan Ave Yonkers NY 10703",
    "addr:housenumber":"777",
    "addr:postcode":"10703",
    "addr:street":"Nepperhan Ave",
    "iso:country":"US",
    "sg:address":"777 Nepperhan Ave",
    "sg:city":"Yonkers",
    "sg:classifiers":[
        {
            "category":"Restaurant",
            "type":"Food & Drink"
        }
    ],
    "sg:phone":"+1 914 476 2777",
    "sg:postcode":"10703",
    "sg:province":"NY",
    "wof:name":"Seven's Lunchonette",
    "wof:placetype":"venue"
},
  "geometry": {"coordinates":[-73.880173,40.949271],"type":"Point"}
}