{
  "type": "Feature",
  "properties": {
    "addr:full":"57 Clark St Brooklyn NY 11201",
    "addr:housenumber":"57",
    "addr:postcode":"11201",
    "addr:street":"Clark St",
    "iso:country":"US",
    "sg:address":"57 Clark St",
    "sg:city":"Brooklyn",
    "sg:classifiers":[
        {
            "category":"Shopping",
            "subcategory":"Pets & Pet Supplies",
            "type":"Retail Goods"
        }
    ],
    "sg:phone":"+1 718 852 7208",
    "sg:postcode":"11201",
    "sg:province":"NY",
    "sg:tags":[
        "store",
        "groomers"
    ],
    "wof:name":"Clark Pet Store",
    "wof:placetype":"venue"
},
  "geometry": {"coordinates":[-73.993621,40.697751],"type":"Point"}
}