{
  "type": "Feature",
  "properties": {
    "addr:full":"135 Madison Ave Albany NY 12202",
    "addr:housenumber":"135",
    "addr:postcode":"12202",
    "addr:street":"Madison Ave",
    "iso:country":"US",
    "sg:address":"135 Madison Ave",
    "sg:city":"Albany",
    "sg:classifiers":[
        {
            "category":"Real Estate",
            "subcategory":"Real Estate Agent",
            "type":"Services"
        }
    ],
    "sg:phone":"+1 518 463 5253",
    "sg:postcode":"12202",
    "sg:province":"NY",
    "wof:name":"Koreman Realty Inc",
    "wof:placetype":"venue"
},
  "geometry": {"coordinates":[-73.756291,42.646229],"type":"Point"}
}