{
  "type": "Feature",
  "properties": {
    "addr:full":"498 Pawling Ave Troy NY 12180",
    "addr:housenumber":"498",
    "addr:postcode":"12180",
    "addr:street":"Pawling Ave",
    "iso:country":"US",
    "sg:address":"498 Pawling Ave",
    "sg:city":"Troy",
    "sg:classifiers":[
        {
            "category":"Personal",
            "subcategory":"Beauty Salon",
            "type":"Services"
        }
    ],
    "sg:phone":"+1 518 273 0990",
    "sg:postcode":"12180",
    "sg:province":"NY",
    "wof:name":"Joesephoriai II The Hair Sln",
    "wof:placetype":"venue"
},
  "geometry": {"coordinates":[-73.662243,42.707702],"type":"Point"}
}