{
  "type": "Feature",
  "properties": {
    "addr:full":"811 W Jericho Tpke Ste 203E Smithtown NY 11787",
    "addr:housenumber":"811",
    "addr:postcode":"11787",
    "addr:street":"W Jericho Tpke Ste 203E",
    "iso:country":"US",
    "sg:address":"811 W Jericho Tpke Ste 203E",
    "sg:city":"Smithtown",
    "sg:classifiers":[
        {
            "category":"Professional",
            "subcategory":"Lawyer & Legal Services",
            "type":"Services"
        }
    ],
    "sg:phone":"+1 631 265 9015",
    "sg:postcode":"11787",
    "sg:province":"NY",
    "wof:name":"Scagluso Frank S ESQ",
    "wof:placetype":"venue"
},
  "geometry": {"coordinates":[-73.2397,40.847301],"type":"Point"}
}