{
  "type": "Feature",
  "properties": {
    "addr:full":"57 W 38th Street Fl 7 New York NY 10018",
    "addr:housenumber":"57;7",
    "addr:postcode":"new;10018",
    "addr:street":"W 38Th Street",
    "iso:country":"US",
    "sg:address":"57 W 38th Street Fl 7",
    "sg:city":"New York",
    "sg:classifiers":[
        {
            "category":"Professional",
            "subcategory":"Lawyer & Legal Services",
            "type":"Services"
        }
    ],
    "sg:phone":"+1 212 686 5550",
    "sg:postcode":"10018",
    "sg:province":"NY",
    "sg:tags":[
        "personal",
        "injury"
    ],
    "wof:name":"Antin & Ehrlich",
    "wof:placetype":"venue"
},
  "geometry": {"coordinates":[-73.98453499999999,40.751719],"type":"Point"}
}