{
  "type": "Feature",
  "properties": {
    "iso:country":"US",
    "sg:address":"1120 Westchester Avenue",
    "sg:city":"Bronx",
    "sg:classifiers":[
        {
            "category":"Retail",
            "subcategory":"Laundry & Dry Cleaning",
            "type":"Services"
        }
    ],
    "sg:phone":"+1 718 328 3405",
    "sg:postcode":"10459",
    "sg:province":"NY",
    "wof:name":"Bethel Cleaners",
    "wof:placetype":"venue"
},
  "geometry": {"coordinates":[-73.889754,40.825638],"type":"Point"}
}