{
  "type": "Feature",
  "properties": {
    "addr:full":"50 Glen St Glen Cove NY 11542",
    "addr:housenumber":"50",
    "addr:postcode":"11542",
    "addr:street":"Glen St",
    "iso:country":"US",
    "sg:address":"50 Glen St",
    "sg:city":"Glen Cove",
    "sg:classifiers":[
        {
            "category":"Professional",
            "subcategory":"Lawyer & Legal Services",
            "type":"Services"
        }
    ],
    "sg:phone":"+1 516 676 4114",
    "sg:postcode":"11542",
    "sg:province":"NY",
    "sg:tags":[
        "attorney"
    ],
    "wof:name":"Stuart R Jablonski",
    "wof:placetype":"venue"
},
  "geometry": {"coordinates":[-73.630686,40.863892],"type":"Point"}
}