{
  "type": "Feature",
  "properties": {
    "addr:full":"1495 E 19th St Brooklyn NY 11230",
    "addr:housenumber":"1495",
    "addr:postcode":"11230",
    "addr:street":"E 19Th St",
    "iso:country":"US",
    "sg:address":"1495 E 19th St",
    "sg:city":"Brooklyn",
    "sg:classifiers":[
        {
            "category":"Professional",
            "subcategory":"Accounting & Tax Preparation",
            "type":"Services"
        }
    ],
    "sg:phone":"+1   ",
    "sg:postcode":"11230",
    "sg:province":"NY",
    "sg:tags":[
        "accountant",
        "public",
        "certified"
    ],
    "wof:name":"Joseph M Fertig CPA",
    "wof:placetype":"venue"
},
  "geometry": {"coordinates":[-73.955541,40.615702],"type":"Point"}
}