{
  "type": "Feature",
  "properties": {
    "addr:full":"120 Genesee St Auburn NY 13021",
    "addr:housenumber":"120",
    "addr:postcode":"13021",
    "addr:street":"Genesee St",
    "iso:country":"US",
    "sg:address":"120 Genesee St",
    "sg:city":"Auburn",
    "sg:classifiers":[
        {
            "category":"Organizations",
            "subcategory":"Membership Organization",
            "type":"Services"
        }
    ],
    "sg:phone":"+1 315 253 6205",
    "sg:postcode":"13021",
    "sg:province":"NY",
    "wof:name":"Samuel Foundation Inc",
    "wof:placetype":"venue"
},
  "geometry": {"coordinates":[-76.568697,42.930382],"type":"Point"}
}