{
  "type": "Feature",
  "properties": {
    "iso:country":"US",
    "sg:address":"200 Jericho Tpke",
    "sg:city":"Jericho",
    "sg:classifiers":[
        {
            "category":"Cinema",
            "subcategory":"Drive-in Theater",
            "type":"Entertainment"
        }
    ],
    "sg:phone":"+1 516 803 2300",
    "sg:postcode":"11753",
    "sg:province":"NY",
    "sg:tags":[
        "cable",
        "woman",
        "program",
        "for",
        "produce"
    ],
    "wof:name":"Womens Entertainment",
    "wof:placetype":"venue"
},
  "geometry": {"coordinates":[-73.541777,40.790766],"type":"Point"}
}