{
  "type": "Feature",
  "properties": {
    "addr:full":"1501 Hylan Blvd Staten Island NY 10305",
    "addr:housenumber":"1501",
    "addr:postcode":"10305",
    "addr:street":"Hylan Blvd",
    "iso:country":"US",
    "sg:address":"1501 Hylan Blvd",
    "sg:city":"Staten Island",
    "sg:classifiers":[
        {
            "category":"Banks & Credit Unions",
            "subcategory":"Bank",
            "type":"Services"
        }
    ],
    "sg:phone":"+1 718 351 5593",
    "sg:postcode":"10305",
    "sg:province":"NY",
    "sg:tags":[
        "loan",
        "real estate"
    ],
    "wof:name":"First Suffolk Mortgage Corp",
    "wof:placetype":"venue"
},
  "geometry": {"coordinates":[-74.087699,40.591907],"type":"Point"}
}