{
  "type": "Feature",
  "properties": {
    "iso:country":"US",
    "sg:address":"215 Klein Rd",
    "sg:city":"Buffalo",
    "sg:classifiers":[
        {
            "category":"Organizations",
            "subcategory":"Non-profit Organization",
            "type":"Services"
        },
        {
            "category":"Health Services",
            "subcategory":"Doctor",
            "type":"Services"
        }
    ],
    "sg:phone":"+1 716 568 6100",
    "sg:postcode":"14221",
    "sg:province":"NY",
    "sg:tags":[
        "medical",
        "surgery",
        "center"
    ],
    "wof:name":"Millard Fillmore Surgery Ctr",
    "wof:placetype":"venue"
},
  "geometry": {"coordinates":[-78.72416800000001,43.000192],"type":"Point"}
}