{
  "type": "Feature",
  "properties": {
    "iso:country":"US",
    "sg:address":"1034 Montauk Hwy",
    "sg:city":"Copiague",
    "sg:classifiers":[
        {
            "category":"Professional",
            "subcategory":"Art Services",
            "type":"Services"
        }
    ],
    "sg:phone":"+1 631 842 0310",
    "sg:postcode":"11726",
    "sg:province":"NY",
    "sg:tags":[
        "photographer"
    ],
    "wof:name":"Photo Designs Inc",
    "wof:placetype":"venue"
},
  "geometry": {"coordinates":[-73.390011,40.669531],"type":"Point"}
}