{
  "type": "Feature",
  "properties": {
    "iso:country":"US",
    "sg:address":"1603 Bushwick Ave",
    "sg:city":"Brooklyn",
    "sg:classifiers":[
        {
            "category":"Shopping",
            "subcategory":"Florist",
            "type":"Retail Goods"
        }
    ],
    "sg:phone":"+1 718 455 3052",
    "sg:postcode":"11207",
    "sg:province":"NY",
    "sg:tags":[
        "sup"
    ],
    "wof:name":"Conway Landscaping & Nursery",
    "wof:placetype":"venue"
},
  "geometry": {"coordinates":[-73.90409699999999,40.681505],"type":"Point"}
}