{
  "type": "Feature",
  "properties": {
    "addr:full":"362 15th St Brooklyn NY 11215",
    "addr:housenumber":"362",
    "addr:postcode":"11215",
    "addr:street":"15Th St",
    "iso:country":"US",
    "sg:address":"362 15th St",
    "sg:city":"Brooklyn",
    "sg:classifiers":[
        {
            "category":"Restaurant",
            "type":"Food & Drink"
        }
    ],
    "sg:phone":"+1 718 499 0555",
    "sg:postcode":"11215",
    "sg:province":"NY",
    "wof:name":"Olive Vine",
    "wof:placetype":"venue"
},
  "geometry": {"coordinates":[-73.982488,40.662216],"type":"Point"}
}