{
  "type": "Feature",
  "properties": {
    "addr:full":"21 Clinton St New York NY 10002",
    "addr:housenumber":"21",
    "addr:postcode":"10002",
    "addr:street":"Clinton St",
    "iso:country":"US",
    "sg:address":"21 Clinton St",
    "sg:city":"New York",
    "sg:classifiers":[
        {
            "category":"Food & Beverages",
            "subcategory":"Candy",
            "type":"Retail Goods"
        },
        {
            "category":"Bars & Pubs",
            "subcategory":"Wine Bar",
            "type":"Food & Drink"
        }
    ],
    "sg:phone":"+1 212 677 7417",
    "sg:postcode":"10002",
    "sg:province":"NY",
    "sg:tags":[
        "dessert"
    ],
    "sg:website":"www.cocoabarnyc.com",
    "wof:name":"Cocoa Bar",
    "wof:placetype":"venue"
},
  "geometry": {"coordinates":[-73.98424,40.720673],"type":"Point"}
}