{
  "type": "Feature",
  "properties": {
    "addr:full":"945 McLean Ave Yonkers NY 10704",
    "addr:housenumber":"945",
    "addr:postcode":"10704",
    "addr:street":"Mclean Ave",
    "iso:country":"US",
    "sg:address":"945 McLean Ave",
    "sg:city":"Yonkers",
    "sg:classifiers":[
        {
            "category":"Food & Beverages",
            "subcategory":"Groceries & Convenience Stores",
            "type":"Retail Goods"
        }
    ],
    "sg:phone":"+1 914 237 5432",
    "sg:postcode":"10704",
    "sg:province":"NY",
    "sg:tags":[
        "grocer"
    ],
    "wof:name":"Irish Food Ctr Inc",
    "wof:placetype":"venue"
},
  "geometry": {"coordinates":[-73.86728599999999,40.903808],"type":"Point"}
}