{
  "type": "Feature",
  "properties": {
    "addr:full":"20 Eastview Dr Watervliet NY 12189",
    "addr:housenumber":"20",
    "addr:postcode":"12189",
    "addr:street":"Eastview Dr",
    "iso:country":"US",
    "sg:address":"20 Eastview Dr",
    "sg:city":"Watervliet",
    "sg:classifiers":[
        {
            "category":"Real Estate",
            "subcategory":"Real Estate Operator",
            "type":"Services"
        }
    ],
    "sg:phone":"+1 518 274 2600",
    "sg:postcode":"12189",
    "sg:province":"NY",
    "sg:tags":[
        "apartment"
    ],
    "sg:website":"www.sunrisemc.com",
    "wof:name":"Highland Club Apartments",
    "wof:placetype":"venue"
},
  "geometry": {"coordinates":[-73.719251,42.735475],"type":"Point"}
}