{
  "type": "Feature",
  "properties": {
    "iso:country":"US",
    "sg:address":"20 Stevenson Rd",
    "sg:city":"Cambridge",
    "sg:classifiers":[
        {
            "category":"Farming",
            "subcategory":"Farm",
            "type":"Manufacturing & Wholesale Goods"
        }
    ],
    "sg:phone":"+1 518 677 5111",
    "sg:postcode":"12816",
    "sg:province":"NY",
    "sg:tags":[
        "crop",
        "general"
    ],
    "wof:name":"Haven Hill Farm",
    "wof:placetype":"venue"
},
  "geometry": {"coordinates":[-73.42721899999999,43.047301],"type":"Point"}
}