{
  "type": "Feature",
  "properties": {
    "addr:full":"57 Maple Rd East Aurora NY 14052",
    "addr:housenumber":"57",
    "addr:postcode":"14052",
    "addr:street":"Maple Rd",
    "iso:country":"US",
    "sg:address":"57 Maple Rd",
    "sg:city":"East Aurora",
    "sg:classifiers":[
        {
            "category":"Banks & Credit Unions",
            "subcategory":"Financial Services",
            "type":"Services"
        }
    ],
    "sg:phone":"+1 716 652 5703",
    "sg:postcode":"14052",
    "sg:province":"NY",
    "sg:tags":[
        "investment",
        "closed"
    ],
    "wof:name":"Winstrom",
    "wof:placetype":"venue"
},
  "geometry": {"coordinates":[-78.621045,42.770647],"type":"Point"}
}