{
  "type": "Feature",
  "properties": {
    "addr:full":"328 Atlantic Ave Brooklyn NY 11201",
    "addr:housenumber":"328",
    "addr:postcode":"11201",
    "addr:street":"Atlantic Ave",
    "iso:country":"US",
    "sg:address":"328 Atlantic Ave",
    "sg:city":"Brooklyn",
    "sg:classifiers":[
        {
            "category":"Building & Trades",
            "subcategory":"Construction",
            "type":"Services"
        }
    ],
    "sg:phone":"+1 718 875 6744",
    "sg:postcode":"11201",
    "sg:province":"NY",
    "sg:tags":[
        "general",
        "contractor"
    ],
    "wof:name":"Frank Parlamis Inc",
    "wof:placetype":"venue"
},
  "geometry": {"coordinates":[-73.98813,40.688268],"type":"Point"}
}