{
  "type": "Feature",
  "properties": {
    "addr:full":"203 Avenue T Brooklyn NY 11223",
    "addr:housenumber":"203",
    "addr:postcode":"11223",
    "addr:street":"Avenue T",
    "iso:country":"US",
    "sg:address":"203 Avenue T",
    "sg:city":"Brooklyn",
    "sg:classifiers":[
        {
            "category":"Shopping",
            "subcategory":"Computers & Home Electronics",
            "type":"Retail Goods"
        }
    ],
    "sg:phone":"+1 718 339 8099",
    "sg:postcode":"11223",
    "sg:province":"NY",
    "wof:name":"L T Digital Way",
    "wof:placetype":"venue"
},
  "geometry": {"coordinates":[-73.97749,40.59882],"type":"Point"}
}