{
  "type": "Feature",
  "properties": {
    "addr:full":"4806 Broadway Astoria NY 11103",
    "addr:housenumber":"4806",
    "addr:postcode":"11103",
    "addr:street":"Broadway",
    "iso:country":"US",
    "sg:address":"4806 Broadway",
    "sg:city":"Astoria",
    "sg:classifiers":[
        {
            "category":"Restaurant",
            "type":"Food & Drink"
        }
    ],
    "sg:menulink":"http://www.allmenus.com/ny/queens/23266-new-wing-shing/menu/",
    "sg:phone":"+1 718 956 9988",
    "sg:postcode":"11103",
    "sg:province":"NY",
    "sg:tags":[
        "asian",
        "chinese"
    ],
    "wof:name":"New Wing Shing",
    "wof:placetype":"venue"
},
  "geometry": {"coordinates":[-73.91257899999999,40.755961],"type":"Point"}
}