{
  "type": "Feature",
  "properties": {
    "addr:full":"70 Frankfort St Rochester NY 14608",
    "addr:housenumber":"70",
    "addr:postcode":"14608",
    "addr:street":"Frankfort St",
    "iso:country":"US",
    "sg:address":"70 Frankfort St",
    "sg:city":"Rochester",
    "sg:classifiers":[
        {
            "category":"Retail",
            "subcategory":"Auto Repair",
            "type":"Services"
        }
    ],
    "sg:phone":"+1 585 325 4557",
    "sg:postcode":"14608",
    "sg:province":"NY",
    "sg:tags":[
        "repairing",
        "automobile"
    ],
    "wof:name":"Michael's Automotive Tech Ctr",
    "wof:placetype":"venue"
},
  "geometry": {"coordinates":[-77.622153,43.162429],"type":"Point"}
}