{
  "type": "Feature",
  "properties": {
    "iso:country":"US",
    "sg:address":"406 Franklin St",
    "sg:city":"Buffalo",
    "sg:classifiers":[
        {
            "category":"Health Services",
            "subcategory":"Clinic",
            "type":"Services"
        }
    ],
    "sg:phone":"+1 716 854 2012",
    "sg:postcode":"14202",
    "sg:province":"NY",
    "sg:tags":[
        "holistic",
        "practitioner"
    ],
    "wof:name":"Maria Herod Nd",
    "wof:placetype":"venue"
},
  "geometry": {"coordinates":[-78.873401,42.896034],"type":"Point"}
}