{
  "type": "Feature",
  "properties": {
    "iso:country":"US",
    "sg:address":"4250 Ridge Lea Rd Ste 69",
    "sg:city":"Buffalo",
    "sg:classifiers":[
        {
            "category":"Professional",
            "subcategory":"Computer Services",
            "type":"Services"
        }
    ],
    "sg:phone":"+1 716 831 9716",
    "sg:postcode":"14226",
    "sg:province":"NY",
    "sg:tags":[
        "web",
        "designer",
        "publisher",
        "consultant",
        "system",
        "hosting",
        "design",
        "site",
        "developer",
        "software"
    ],
    "sg:website":"http://www.mainstreethost.com",
    "wof:name":"Main Street Host",
    "wof:placetype":"venue"
},
  "geometry": {"coordinates":[-78.81431000000001,43.000118],"type":"Point"}
}