{
  "type": "Feature",
  "properties": {
    "iso:country":"US",
    "sg:address":"4702 Merrick Rd",
    "sg:city":"Massapequa",
    "sg:classifiers":[
        {
            "category":"Place Of Worship",
            "subcategory":"Monastery",
            "type":"Public Place"
        }
    ],
    "sg:phone":"+1 516 541 5800",
    "sg:postcode":"11758",
    "sg:province":"NY",
    "sg:tags":[
        "convent"
    ],
    "wof:name":"Sisters Of St Dominic",
    "wof:placetype":"venue"
},
  "geometry": {"coordinates":[-73.461095,40.666409],"type":"Point"}
}