{
  "type": "Feature",
  "properties": {
    "addr:full":"1476 Pleasantville Rd Briarcliff Manor NY 10510",
    "addr:housenumber":"1476",
    "addr:postcode":"10510",
    "addr:street":"Pleasantville Rd",
    "iso:country":"US",
    "sg:address":"1476 Pleasantville Rd",
    "sg:city":"Briarcliff Manor",
    "sg:classifiers":[
        {
            "category":"Wholesale",
            "subcategory":"Books, Periodicals, & Newspapers",
            "type":"Manufacturing & Wholesale Goods"
        }
    ],
    "sg:phone":"+1 914 762 3466",
    "sg:postcode":"10510",
    "sg:province":"NY",
    "sg:tags":[
        "bilingual"
    ],
    "wof:name":"Edinova Publishing Co",
    "wof:placetype":"venue"
},
  "geometry": {"coordinates":[-73.83516299999999,41.15678],"type":"Point"}
}