{
  "type": "Feature",
  "properties": {
    "addr:full":"8004 Thompson Rd Cicero NY 13039",
    "addr:housenumber":"8004",
    "addr:postcode":"13039",
    "addr:street":"Thompson Rd",
    "iso:country":"US",
    "sg:address":"8004 Thompson Rd",
    "sg:city":"Cicero",
    "sg:classifiers":[
        {
            "category":"Personal",
            "subcategory":"Beauty Salon",
            "type":"Services"
        }
    ],
    "sg:phone":"+1 315 699 4449",
    "sg:postcode":"13039",
    "sg:province":"NY",
    "wof:name":"Mirror Image",
    "wof:placetype":"venue"
},
  "geometry": {"coordinates":[-76.092153,43.157117],"type":"Point"}
}