{
  "type": "Feature",
  "properties": {
    "iso:country":"US",
    "sg:address":"120 Eton Rd",
    "sg:city":"Thornwood",
    "sg:classifiers":[
        {
            "category":"Building & Trades",
            "subcategory":"Landscaping Services",
            "type":"Services"
        }
    ],
    "sg:phone":"+1 914 741 2094",
    "sg:postcode":"10594",
    "sg:province":"NY",
    "wof:name":"Strazza Masonry & Landscaping",
    "wof:placetype":"venue"
},
  "geometry": {"coordinates":[-73.754165,41.122098],"type":"Point"}
}