{
  "type": "Feature",
  "properties": {
    "addr:full":"861 E 149th St Bronx NY 10455",
    "addr:housenumber":"861",
    "addr:postcode":"10455",
    "addr:street":"E 149Th St",
    "iso:country":"US",
    "sg:address":"861 E 149th St",
    "sg:city":"Bronx",
    "sg:classifiers":[
        {
            "category":"Education",
            "subcategory":"Special Training",
            "type":"Public Place"
        }
    ],
    "sg:phone":"+1 718 402 6697",
    "sg:postcode":"10455",
    "sg:province":"NY",
    "sg:tags":[
        "program"
    ],
    "wof:name":"Neighborhood Empowerment Ctr",
    "wof:placetype":"venue"
},
  "geometry": {"coordinates":[-73.903683,40.811901],"type":"Point"}
}