{
  "type": "Feature",
  "properties": {
    "addr:full":"3178 Lydia Ln Bellmore NY 11710",
    "addr:housenumber":"3178",
    "addr:postcode":"11710",
    "addr:street":"Lydia Ln",
    "iso:country":"US",
    "sg:address":"3178 Lydia Ln",
    "sg:city":"Bellmore",
    "sg:classifiers":[
        {
            "category":"Professional",
            "subcategory":"Advertising",
            "type":"Services"
        }
    ],
    "sg:phone":"+1 516 826 1368",
    "sg:postcode":"11710",
    "sg:province":"NY",
    "sg:tags":[
        "promotion",
        "sale"
    ],
    "wof:name":"Positive Logic Inc",
    "wof:placetype":"venue"
},
  "geometry": {"coordinates":[-73.522221,40.644238],"type":"Point"}
}