{
  "type": "Feature",
  "properties": {
    "addr:full":"3004 Beechnut Ave Medford NY 11763",
    "addr:housenumber":"3004",
    "addr:postcode":"11763",
    "addr:street":"Beechnut Ave",
    "iso:country":"US",
    "sg:address":"3004 Beechnut Ave",
    "sg:city":"Medford",
    "sg:classifiers":[
        {
            "category":"Building & Trades",
            "subcategory":"Construction",
            "type":"Services"
        }
    ],
    "sg:phone":"+1 631 289 4147",
    "sg:postcode":"11763",
    "sg:province":"NY",
    "sg:tags":[
        "carpenter"
    ],
    "wof:name":"Ed Cuccia Custom Carpentry",
    "wof:placetype":"venue"
},
  "geometry": {"coordinates":[-72.98661,40.831172],"type":"Point"}
}