{
  "type": "Feature",
  "properties": {
    "addr:full":"795 Co Rd 106 Amsterdam NY 12010",
    "addr:housenumber":"795;106",
    "addr:postcode":"12010",
    "addr:street":"Co Rd",
    "iso:country":"US",
    "sg:address":"795 Co Rd 106",
    "sg:city":"Amsterdam",
    "sg:classifiers":[
        {
            "category":"Home & Garden",
            "subcategory":"Building Materials",
            "type":"Retail Goods"
        }
    ],
    "sg:phone":"+1 518 883 3082",
    "sg:postcode":"12010",
    "sg:province":"NY",
    "sg:tags":[
        "equipment",
        "electrical"
    ],
    "wof:name":"Welding Electro Technolgies",
    "wof:placetype":"venue"
},
  "geometry": {"coordinates":[-74.217314,43.043264],"type":"Point"}
}