{
  "type": "Feature",
  "properties": {
    "iso:country":"US",
    "sg:address":"250 Osborne Rd",
    "sg:city":"Albany",
    "sg:classifiers":[
        {
            "category":"Professional",
            "subcategory":"Lawyer & Legal Services",
            "type":"Services"
        }
    ],
    "sg:phone":"+1 518 435 9200",
    "sg:postcode":"12205",
    "sg:province":"NY",
    "sg:tags":[
        "attorney"
    ],
    "wof:name":"Tischler Wade & Burstein",
    "wof:placetype":"venue"
},
  "geometry": {"coordinates":[-73.778284,42.705791],"type":"Point"}
}