{
  "type": "Feature",
  "properties": {
    "iso:country":"US",
    "sg:address":"655 State Hwy 318",
    "sg:city":"Waterloo",
    "sg:classifiers":[
        {
            "category":"Shopping",
            "subcategory":"Shoes",
            "type":"Retail Goods"
        }
    ],
    "sg:phone":"+1 315 539 8039",
    "sg:postcode":"13165",
    "sg:province":"NY",
    "sg:website":"www.journeys.com",
    "wof:name":"Journeys",
    "wof:placetype":"venue"
},
  "geometry": {"coordinates":[-76.91418299999999,42.954489],"type":"Point"}
}