{
  "type": "Feature",
  "properties": {
    "addr:full":"770 Beck Street Bronx NY 10455",
    "addr:housenumber":"770",
    "addr:postcode":"10455",
    "addr:street":"Beck Street",
    "iso:country":"US",
    "sg:address":"770 Beck Street",
    "sg:city":"Bronx",
    "sg:classifiers":[
        {
            "category":"Education",
            "subcategory":"School",
            "type":"Public Place"
        }
    ],
    "sg:phone":"+1 718 842 3252",
    "sg:postcode":"10455",
    "sg:province":"NY",
    "wof:name":"Bronx Organization For the Learning Disabled",
    "wof:placetype":"venue"
},
  "geometry": {"coordinates":[-73.89819900000001,40.816671],"type":"Point"}
}