{
  "type": "Feature",
  "properties": {
    "addr:full":"880 W Beech St Long Beach NY 11561",
    "addr:housenumber":"880",
    "addr:postcode":"11561",
    "addr:street":"W Beech St",
    "iso:country":"US",
    "sg:address":"880 W Beech St",
    "sg:city":"Long Beach",
    "sg:classifiers":[
        {
            "category":"Real Estate",
            "subcategory":"Real Estate Agent",
            "type":"Services"
        }
    ],
    "sg:phone":"+1 516 889 7500",
    "sg:postcode":"11561",
    "sg:province":"NY",
    "wof:name":"Coldwell Banker",
    "wof:placetype":"venue"
},
  "geometry": {"coordinates":[-73.69000699999999,40.585943],"type":"Point"}
}