{
  "type": "Feature",
  "properties": {
    "iso:country":"US",
    "sg:address":"61 Aero Dr",
    "sg:city":"Buffalo",
    "sg:classifiers":[
        {
            "category":"Manufacturing",
            "subcategory":"Tools & Machinery",
            "type":"Manufacturing & Wholesale Goods"
        }
    ],
    "sg:phone":"+1 716 565 1153",
    "sg:postcode":"14225",
    "sg:province":"NY",
    "sg:tags":[
        "compressor"
    ],
    "wof:name":"Curtis East Inc",
    "wof:placetype":"venue"
},
  "geometry": {"coordinates":[-78.735922,42.949975],"type":"Point"}
}