{
  "type": "Feature",
  "properties": {
    "iso:country":"US",
    "sg:address":"19 Straw Ln",
    "sg:city":"Central Islip",
    "sg:classifiers":[
        {
            "category":"Building & Trades",
            "subcategory":"Construction",
            "type":"Services"
        }
    ],
    "sg:phone":"+1 631 582 8908",
    "sg:postcode":"11749",
    "sg:province":"NY",
    "sg:tags":[
        "house"
    ],
    "wof:name":"Donald J Cooper Enterprise",
    "wof:placetype":"venue"
},
  "geometry": {"coordinates":[-73.17089900000001,40.802491],"type":"Point"}
}