{
  "type": "Feature",
  "properties": {
    "addr:full":"24 School St Dansville NY 14437",
    "addr:housenumber":"24",
    "addr:postcode":"14437",
    "addr:street":"School St",
    "iso:country":"US",
    "sg:address":"24 School St",
    "sg:city":"Dansville",
    "sg:classifiers":[
        {
            "category":"Social Services",
            "type":"Services"
        }
    ],
    "sg:phone":"+1 585 335 7165",
    "sg:postcode":"14437",
    "sg:province":"NY",
    "sg:tags":[
        "youth",
        "organization",
        "center"
    ],
    "wof:name":"Dansville Little League",
    "wof:placetype":"venue"
},
  "geometry": {"coordinates":[-77.694378,42.556526],"type":"Point"}
}