{
  "type": "Feature",
  "properties": {
    "addr:full":"113 Ontario Pl Liverpool NY 13088",
    "addr:housenumber":"113",
    "addr:postcode":"13088",
    "addr:street":"Ontario Pl",
    "iso:country":"US",
    "sg:address":"113 Ontario Pl",
    "sg:city":"Liverpool",
    "sg:classifiers":[
        {
            "category":"Manufacturing",
            "subcategory":"Tools & Machinery",
            "type":"Manufacturing & Wholesale Goods"
        }
    ],
    "sg:phone":"+1 315 457 6201",
    "sg:postcode":"13088",
    "sg:province":"NY",
    "sg:website":"http://www.toolrecylers.com",
    "wof:name":"Tool Recyclers",
    "wof:placetype":"venue"
},
  "geometry": {"coordinates":[-76.194479,43.105932],"type":"Point"}
}