{
  "type": "Feature",
  "properties": {
    "iso:country":"US",
    "sg:address":"452 Broad St",
    "sg:city":"Tonawanda",
    "sg:classifiers":[
        {
            "category":"Utilities",
            "subcategory":"Telephone",
            "type":"Services"
        }
    ],
    "sg:phone":"+1 716 692 4467",
    "sg:postcode":"14150",
    "sg:province":"NY",
    "sg:tags":[
        "web",
        "design",
        "site",
        "communication"
    ],
    "wof:name":"Great American Craft Show",
    "wof:placetype":"venue"
},
  "geometry": {"coordinates":[-78.892008,43.013943],"type":"Point"}
}