{
  "type": "Feature",
  "properties": {
    "addr:full":"650 West Ave Lockport NY 14094",
    "addr:housenumber":"650",
    "addr:postcode":"14094",
    "addr:street":"West Ave",
    "iso:country":"US",
    "sg:address":"650 West Ave",
    "sg:city":"Lockport",
    "sg:classifiers":[
        {
            "category":"Local Transit",
            "type":"Transportation"
        }
    ],
    "sg:phone":"+1 716 433 0699",
    "sg:postcode":"14094",
    "sg:province":"NY",
    "sg:tags":[
        "limousine"
    ],
    "sg:website":"www.timkeylimo.com",
    "wof:name":"Timkey Enterprise",
    "wof:placetype":"venue"
},
  "geometry": {"coordinates":[-78.720118,43.165651],"type":"Point"}
}