{
  "type": "Feature",
  "properties": {
    "addr:full":"6890 Byron Holley Rd Byron NY 14422",
    "addr:housenumber":"6890",
    "addr:postcode":"14422",
    "addr:street":"Byron Holley Rd",
    "iso:country":"US",
    "sg:address":"6890 Byron Holley Rd",
    "sg:city":"Byron",
    "sg:classifiers":[
        {
            "category":"Food & Beverages",
            "subcategory":"Groceries & Convenience Stores",
            "type":"Retail Goods"
        }
    ],
    "sg:phone":"+1 585 548 7576",
    "sg:postcode":"14422",
    "sg:province":"NY",
    "wof:name":"Arrow Mart",
    "wof:placetype":"venue"
},
  "geometry": {"coordinates":[-78.06432700000001,43.078898],"type":"Point"}
}