{
  "type": "Feature",
  "properties": {
    "addr:full":"1280 Main St Buffalo NY 14209",
    "addr:housenumber":"1280",
    "addr:postcode":"14209",
    "addr:street":"Main St",
    "iso:country":"US",
    "sg:address":"1280 Main St",
    "sg:city":"Buffalo",
    "sg:classifiers":[
        {
            "category":"Shopping",
            "subcategory":"Pharmacy",
            "type":"Retail Goods"
        }
    ],
    "sg:phone":"+1 716 883 4517",
    "sg:postcode":"14209",
    "sg:province":"NY",
    "sg:tags":[
        "drugstore"
    ],
    "sg:website":"www.ecmc.edu",
    "wof:name":"Drug Treatment-Ecmc Outpatient Clinic",
    "wof:placetype":"venue"
},
  "geometry": {"coordinates":[-78.866798,42.908298],"type":"Point"}
}