{
  "type": "Feature",
  "properties": {
    "iso:country":"US",
    "sg:address":"450 W John St",
    "sg:city":"Hicksville",
    "sg:classifiers":[
        {
            "category":"Wholesale",
            "subcategory":"Non-durable Goods",
            "type":"Manufacturing & Wholesale Goods"
        }
    ],
    "sg:phone":"+1 516 365 8867",
    "sg:postcode":"11801",
    "sg:province":"NY",
    "wof:name":"Siamese Imports Co",
    "wof:placetype":"venue"
},
  "geometry": {"coordinates":[-73.54146900000001,40.766504],"type":"Point"}
}