{
  "type": "Feature",
  "properties": {
    "addr:full":"213 Front St Hempstead NY 11550",
    "addr:housenumber":"213",
    "addr:postcode":"11550",
    "addr:street":"Front St",
    "iso:country":"US",
    "sg:address":"213 Front St",
    "sg:city":"Hempstead",
    "sg:classifiers":[
        {
            "category":"Restaurant",
            "type":"Food & Drink"
        }
    ],
    "sg:phone":"+1 516 483 1060",
    "sg:postcode":"11550",
    "sg:province":"NY",
    "sg:tags":[
        "caterer"
    ],
    "wof:name":"Riddick S Kitchen & Catering",
    "wof:placetype":"venue"
},
  "geometry": {"coordinates":[-73.629846,40.704395],"type":"Point"}
}