{
  "type": "Feature",
  "properties": {
    "addr:full":"321 Railroad Ave Peekskill NY 10566",
    "addr:housenumber":"321",
    "addr:postcode":"10566",
    "addr:street":"Railroad Ave",
    "iso:country":"US",
    "sg:address":"321 Railroad Ave",
    "sg:city":"Peekskill",
    "sg:classifiers":[
        {
            "category":"Retail",
            "subcategory":"Laundry & Dry Cleaning",
            "type":"Services"
        }
    ],
    "sg:phone":"+1 914 734 2505",
    "sg:postcode":"10566",
    "sg:province":"NY",
    "sg:tags":[
        "cleaners"
    ],
    "wof:name":"His Her Cleaners",
    "wof:placetype":"venue"
},
  "geometry": {"coordinates":[-73.930132,41.285532],"type":"Point"}
}