{
  "type": "Feature",
  "properties": {
    "addr:full":"403 S Lackawanna St Wayland NY 14572",
    "addr:housenumber":"403",
    "addr:postcode":"14572",
    "addr:street":"S Lackawanna St",
    "iso:country":"US",
    "sg:address":"403 S Lackawanna St",
    "sg:city":"Wayland",
    "sg:classifiers":[
        {
            "category":"Shopping",
            "subcategory":"Florist",
            "type":"Retail Goods"
        }
    ],
    "sg:phone":"+1 585 728 2450",
    "sg:postcode":"14572",
    "sg:province":"NY",
    "wof:name":"Floral Creations",
    "wof:placetype":"venue"
},
  "geometry": {"coordinates":[-77.590149,42.562989],"type":"Point"}
}