{
  "type": "Feature",
  "properties": {
    "addr:full":"28 Ronalds Ave New Rochelle NY 10801",
    "addr:housenumber":"28",
    "addr:postcode":"10801",
    "addr:street":"Ronalds Ave",
    "iso:country":"US",
    "sg:address":"28 Ronalds Ave",
    "sg:city":"New Rochelle",
    "sg:classifiers":[
        {
            "category":"Building & Trades",
            "subcategory":"Plumbing",
            "type":"Services"
        }
    ],
    "sg:phone":"+1 914 632 8811",
    "sg:postcode":"10801",
    "sg:province":"NY",
    "sg:tags":[
        "household",
        "contractor"
    ],
    "wof:name":"Star Temp Refrigeration",
    "wof:placetype":"venue"
},
  "geometry": {"coordinates":[-73.798469,40.901788],"type":"Point"}
}