{
  "type": "Feature",
  "properties": {
    "addr:full":"7523 Townline Rd Victor NY 14564",
    "addr:housenumber":"7523",
    "addr:postcode":"14564",
    "addr:street":"Townline Rd",
    "iso:country":"US",
    "sg:address":"7523 Townline Rd",
    "sg:city":"Victor",
    "sg:classifiers":[
        {
            "category":"Real Estate",
            "subcategory":"Real Estate Services",
            "type":"Services"
        },
        {
            "category":"Real Estate",
            "subcategory":"Real Estate Agent",
            "type":"Services"
        }
    ],
    "sg:phone":"+1 585 924 4393",
    "sg:postcode":"14564",
    "sg:province":"NY",
    "sg:tags":[
        "management"
    ],
    "wof:name":"Glamack Realtors",
    "wof:placetype":"venue"
},
  "geometry": {"coordinates":[-77.44948599999999,42.943537],"type":"Point"}
}