{
  "type": "Feature",
  "properties": {
    "addr:full":"656 Broadway St Buffalo NY 14212",
    "addr:housenumber":"656",
    "addr:postcode":"14212",
    "addr:street":"Broadway St",
    "iso:country":"US",
    "sg:address":"656 Broadway St",
    "sg:city":"Buffalo",
    "sg:classifiers":[
        {
            "category":"Personal",
            "subcategory":"Beauty Salon",
            "type":"Services"
        }
    ],
    "sg:phone":"+1 716 855 2240",
    "sg:postcode":"14212",
    "sg:province":"NY",
    "wof:name":"Britton's Beauty Salon",
    "wof:placetype":"venue"
},
  "geometry": {"coordinates":[-78.84965,42.890767],"type":"Point"}
}