{
  "type": "Feature",
  "properties": {
    "iso:country":"US",
    "sg:address":"600 Middle Country Rd",
    "sg:city":"Selden",
    "sg:classifiers":[
        {
            "category":"Education",
            "subcategory":"Dance Studio",
            "type":"Public Place"
        }
    ],
    "sg:phone":"+1 631 698 2909",
    "sg:postcode":"11784",
    "sg:province":"NY",
    "sg:tags":[
        "instruction",
        "dancing"
    ],
    "wof:name":"Reflections Dance Academy LTD",
    "wof:placetype":"venue"
},
  "geometry": {"coordinates":[-73.03406699999999,40.866679],"type":"Point"}
}