{
  "type": "Feature",
  "properties": {
    "iso:country":"US",
    "sg:address":"3417 28th Ave",
    "sg:city":"Astoria",
    "sg:classifiers":[
        {
            "category":"Food & Beverages",
            "subcategory":"Groceries & Convenience Stores",
            "type":"Retail Goods"
        }
    ],
    "sg:phone":"+1 718 726 4573",
    "sg:postcode":"11103",
    "sg:province":"NY",
    "wof:name":"Wandy's Market Inc",
    "wof:placetype":"venue"
},
  "geometry": {"coordinates":[-73.917297,40.7673],"type":"Point"}
}