{
  "type": "Feature",
  "properties": {
    "iso:country":"US",
    "sg:address":"145 Peachtree Dr",
    "sg:city":"East Norwich",
    "sg:classifiers":[
        {
            "category":"Building & Trades",
            "subcategory":"Electrical",
            "type":"Services"
        }
    ],
    "sg:phone":"+1 516 741 7713",
    "sg:postcode":"11732",
    "sg:province":"NY",
    "sg:tags":[
        "electrical",
        "contractor"
    ],
    "wof:name":"Tricom Electrical Contracting",
    "wof:placetype":"venue"
},
  "geometry": {"coordinates":[-73.53311600000001,40.853866],"type":"Point"}
}