{
  "type": "Feature",
  "properties": {
    "iso:country":"US",
    "sg:address":"12 Park Ln",
    "sg:city":"Kerhonkson",
    "sg:classifiers":[
        {
            "category":"Professional",
            "subcategory":"Management & Consulting",
            "type":"Services"
        }
    ],
    "sg:phone":"+1   ",
    "sg:postcode":"12446",
    "sg:province":"NY",
    "wof:name":"Technical Research Reports",
    "wof:placetype":"venue"
},
  "geometry": {"coordinates":[-74.28113399999999,41.744813],"type":"Point"}
}