{
  "type": "Feature",
  "properties": {
    "iso:country":"US",
    "sg:address":"2570 86th St",
    "sg:city":"Brooklyn",
    "sg:classifiers":[
        {
            "category":"Health Services",
            "subcategory":"Doctor",
            "type":"Services"
        }
    ],
    "sg:phone":"+1 347 492 5982",
    "sg:postcode":"11214",
    "sg:province":"NY",
    "wof:name":"First Choice Home Care",
    "wof:placetype":"venue"
},
  "geometry": {"coordinates":[-73.985429,40.596677],"type":"Point"}
}