{
  "type": "Feature",
  "properties": {
    "addr:full":"1 Ayre Dr Albany NY 12203",
    "addr:housenumber":"1",
    "addr:postcode":"12203",
    "addr:street":"Ayre Dr",
    "iso:country":"US",
    "sg:address":"1 Ayre Dr",
    "sg:city":"Albany",
    "sg:classifiers":[
        {
            "category":"Education",
            "subcategory":"Special Training",
            "type":"Public Place"
        }
    ],
    "sg:phone":"+1 518 438 5389",
    "sg:postcode":"12203",
    "sg:province":"NY",
    "sg:tags":[
        "instruction",
        "music"
    ],
    "wof:name":"Joyce Stanton Piano Studio",
    "wof:placetype":"venue"
},
  "geometry": {"coordinates":[-73.833957,42.677268],"type":"Point"}
}