{
  "type": "Feature",
  "properties": {
    "addr:full":"142-20 84th Dr Queens NY 11435",
    "addr:housenumber":"142-20",
    "addr:postcode":"11435",
    "addr:street":"84Th Dr",
    "iso:country":"US",
    "sg:address":"142-20 84th Dr",
    "sg:city":"Queens",
    "sg:classifiers":[
        {
            "category":"Building & Trades",
            "subcategory":"Locksmith",
            "type":"Services"
        }
    ],
    "sg:phone":"+1 718 989 0252",
    "sg:postcode":"11435",
    "sg:province":"NY",
    "sg:tags":[
        "key"
    ],
    "sg:website":"www.emergency-queens-locksmith.com/",
    "wof:name":"Emergency Queens Locksmith",
    "wof:placetype":"venue"
},
  "geometry": {"coordinates":[-73.814272,40.710665],"type":"Point"}
}