{
  "type": "Feature",
  "properties": {
    "iso:country":"US",
    "sg:address":"68 E 86 St",
    "sg:city":"New York",
    "sg:classifiers":[
        {
            "category":"Professional",
            "type":"Services"
        }
    ],
    "sg:phone":"+1 212 288 7807",
    "sg:postcode":"10028",
    "sg:province":"NY",
    "sg:tags":[
        "establishment"
    ],
    "wof:name":"Nikolayevsky Co LTD",
    "wof:placetype":"venue"
},
  "geometry": {"coordinates":[-73.95772599999999,40.780385],"type":"Point"}
}