{
  "type": "Feature",
  "properties": {
    "iso:country":"US",
    "sg:address":"5 S Broadway",
    "sg:city":"Yonkers",
    "sg:classifiers":[
        {
            "category":"Shopping",
            "subcategory":"Discount & Variety Stores",
            "type":"Retail Goods"
        }
    ],
    "sg:phone":"+1 914 375 0539",
    "sg:postcode":"10701",
    "sg:province":"NY",
    "sg:tags":[
        "merchandise",
        "general"
    ],
    "wof:name":"Dollar Pride",
    "wof:placetype":"venue"
},
  "geometry": {"coordinates":[-73.898399,40.933519],"type":"Point"}
}