{
  "type": "Feature",
  "properties": {
    "addr:full":"110 Broadway Monticello NY 12701",
    "addr:housenumber":"110",
    "addr:postcode":"12701",
    "addr:street":"Broadway",
    "iso:country":"US",
    "sg:address":"110 Broadway",
    "sg:city":"Monticello",
    "sg:classifiers":[
        {
            "category":"Taxi",
            "type":"Transportation"
        }
    ],
    "sg:phone":"+1 845 794 7777",
    "sg:postcode":"12701",
    "sg:province":"NY",
    "wof:name":"Alman Monti Taxi Corp Alm",
    "wof:placetype":"venue"
},
  "geometry": {"coordinates":[-74.679393,41.653099],"type":"Point"}
}