{
  "type": "Feature",
  "properties": {
    "iso:country":"US",
    "sg:address":"23217 Merrick Blvd",
    "sg:city":"Springfield Gardens",
    "sg:classifiers":[
        {
            "category":"Retail",
            "subcategory":"Laundry & Dry Cleaning",
            "type":"Services"
        }
    ],
    "sg:phone":"+1 718 525 7487",
    "sg:postcode":"11413",
    "sg:province":"NY",
    "wof:name":"Purr-Fect Cleaners of Laurelton",
    "wof:placetype":"venue"
},
  "geometry": {"coordinates":[-73.73699999999999,40.675098],"type":"Point"}
}