{
  "type": "Feature",
  "properties": {
    "addr:full":"309 Chestnut Ave Mamaroneck NY 10543",
    "addr:housenumber":"309",
    "addr:postcode":"10543",
    "addr:street":"Chestnut Ave",
    "iso:country":"US",
    "sg:address":"309 Chestnut Ave",
    "sg:city":"Mamaroneck",
    "sg:classifiers":[
        {
            "category":"Building & Trades",
            "subcategory":"Construction",
            "type":"Services"
        }
    ],
    "sg:phone":"+1 914 798 8121",
    "sg:postcode":"10543",
    "sg:province":"NY",
    "sg:tags":[
        "house"
    ],
    "wof:name":"Fine Homes of Westchester Inc",
    "wof:placetype":"venue"
},
  "geometry": {"coordinates":[-73.73376,40.967594],"type":"Point"}
}