{
  "type": "Feature",
  "properties": {
    "addr:full":"1325 Southern Blvd Bronx NY 10459",
    "addr:housenumber":"1325",
    "addr:postcode":"10459",
    "addr:street":"Southern Blvd",
    "iso:country":"US",
    "sg:address":"1325 Southern Blvd",
    "sg:city":"Bronx",
    "sg:classifiers":[
        {
            "category":"Wholesale",
            "subcategory":"Fruits & Vegetables",
            "type":"Manufacturing & Wholesale Goods"
        }
    ],
    "sg:phone":"+1 718 542 4807",
    "sg:postcode":"10459",
    "sg:province":"NY",
    "sg:tags":[
        "veggie"
    ],
    "wof:name":"Auroa Grocery & Market Corp",
    "wof:placetype":"venue"
},
  "geometry": {"coordinates":[-73.891989,40.830555],"type":"Point"}
}