{
  "type": "Feature",
  "properties": {
    "addr:full":"441 Lexington Ave New York NY 10017",
    "addr:housenumber":"441",
    "addr:postcode":"10017",
    "addr:street":"Lexington Ave",
    "iso:country":"US",
    "sg:address":"441 Lexington Ave",
    "sg:city":"New York",
    "sg:classifiers":[
        {
            "category":"Parking",
            "type":"Transportation"
        }
    ],
    "sg:phone":"+1 212 503 0900",
    "sg:postcode":"10017",
    "sg:province":"NY",
    "sg:tags":[
        "garage"
    ],
    "wof:name":"Meyers Parking System Inc",
    "wof:placetype":"venue"
},
  "geometry": {"coordinates":[-73.97465099999999,40.753206],"type":"Point"}
}