{
  "type": "Feature",
  "properties": {
    "addr:full":"500 Jordan Rd Troy NY 12180",
    "addr:housenumber":"500",
    "addr:postcode":"12180",
    "addr:street":"Jordan Rd",
    "iso:country":"US",
    "sg:address":"500 Jordan Rd",
    "sg:city":"Troy",
    "sg:classifiers":[
        {
            "category":"Insurance",
            "subcategory":"Hazard Insurance",
            "type":"Services"
        }
    ],
    "sg:phone":"+1 518 285 2000",
    "sg:postcode":"12180",
    "sg:province":"NY",
    "sg:tags":[
        "commercial",
        "business"
    ],
    "sg:website":"http://www.metlife.com",
    "wof:name":"Metlife",
    "wof:placetype":"venue"
},
  "geometry": {"coordinates":[-73.699806,42.68258],"type":"Point"}
}