{
  "type": "Feature",
  "properties": {
    "addr:full":"909 3 Ave New York NY 10022",
    "addr:housenumber":"909",
    "addr:postcode":"10022",
    "addr:street":"3 Ave",
    "iso:country":"US",
    "sg:address":"909 3 Ave",
    "sg:city":"New York",
    "sg:classifiers":[
        {
            "category":"Professional",
            "subcategory":"Management & Consulting",
            "type":"Services"
        }
    ],
    "sg:phone":"+1 212 652 6600",
    "sg:postcode":"10022",
    "sg:province":"NY",
    "sg:tags":[
        "computer",
        "business",
        "programing",
        "custom"
    ],
    "wof:name":"Comverse Network Systems",
    "wof:placetype":"venue"
},
  "geometry": {"coordinates":[-73.97076,40.755825],"type":"Point"}
}