{
  "type": "Feature",
  "properties": {
    "addr:full":"9 Hilltop Dr Pittsford NY 14534",
    "addr:housenumber":"9",
    "addr:postcode":"14534",
    "addr:street":"Hilltop Dr",
    "iso:country":"US",
    "sg:address":"9 Hilltop Dr",
    "sg:city":"Pittsford",
    "sg:classifiers":[
        {
            "category":"Mining & Drilling",
            "type":"Manufacturing & Wholesale Goods"
        }
    ],
    "sg:phone":"+1 585 385 7438",
    "sg:postcode":"14534",
    "sg:province":"NY",
    "sg:tags":[
        "sand",
        "industrial"
    ],
    "wof:name":"Hider Prototype",
    "wof:placetype":"venue"
},
  "geometry": {"coordinates":[-77.515142,43.078339],"type":"Point"}
}