{
  "type": "Feature",
  "properties": {
    "iso:country":"US",
    "sg:address":"242 Wythe Ave",
    "sg:city":"Brooklyn",
    "sg:classifiers":[
        {
            "category":"Professional",
            "subcategory":"Management & Consulting",
            "type":"Services"
        }
    ],
    "sg:phone":"+1 718 599 3740",
    "sg:postcode":"11211",
    "sg:province":"NY",
    "sg:tags":[
        "counselor",
        "public",
        "relations"
    ],
    "sg:website":"www.plusonemusic.net",
    "wof:name":"Plus One",
    "wof:placetype":"venue"
},
  "geometry": {"coordinates":[-73.962577,40.717725],"type":"Point"}
}