{
  "type": "Feature",
  "properties": {
    "addr:full":"494 Hempstead Tpke West Hempstead NY 11552",
    "addr:housenumber":"494",
    "addr:postcode":"11552",
    "addr:street":"Hempstead Tpke West",
    "iso:country":"US",
    "sg:address":"494 Hempstead Tpke",
    "sg:city":"West Hempstead",
    "sg:classifiers":[
        {
            "category":"Restaurant",
            "type":"Food & Drink"
        }
    ],
    "sg:menulink":"http://www.allmenus.com/ny/west-hempstead/107259-soup-man/menu/",
    "sg:phone":"+1 516 483 1350",
    "sg:postcode":"11552",
    "sg:province":"NY",
    "sg:tags":[
        "soup",
        "american",
        "salad"
    ],
    "wof:name":"Soup Man",
    "wof:placetype":"venue"
},
  "geometry": {"coordinates":[-73.65697900000001,40.705586],"type":"Point"}
}