{
  "type": "Feature",
  "properties": {
    "iso:country":"US",
    "sg:address":"8347 State Hwy 42",
    "sg:city":"Woodbourne",
    "sg:classifiers":[
        {
            "category":"Retail",
            "subcategory":"Repair Shop",
            "type":"Services"
        }
    ],
    "sg:phone":"+1 845 436 0183",
    "sg:postcode":"12788",
    "sg:province":"NY",
    "sg:tags":[
        "lock",
        "locksmith"
    ],
    "wof:name":"Hummel's Automotive Lock-Out",
    "wof:placetype":"venue"
},
  "geometry": {"coordinates":[-74.60187999999999,41.778201],"type":"Point"}
}