{
  "type": "Feature",
  "properties": {
    "addr:full":"252 Lafayette St Copiague NY 11726",
    "addr:housenumber":"252",
    "addr:postcode":"11726",
    "addr:street":"Lafayette St",
    "iso:country":"US",
    "sg:address":"252 Lafayette St",
    "sg:city":"Copiague",
    "sg:classifiers":[
        {
            "category":"Shopping",
            "subcategory":"Clothing, Apparel, & Fashions",
            "type":"Retail Goods"
        }
    ],
    "sg:phone":"+1 516 330 5647",
    "sg:postcode":"11726",
    "sg:province":"NY",
    "sg:tags":[
        "accessory",
        "clothing",
        "store",
        "women's"
    ],
    "wof:name":"Burnthebee",
    "wof:placetype":"venue"
},
  "geometry": {"coordinates":[-73.400857,40.675451],"type":"Point"}
}