{
  "type": "Feature",
  "properties": {
    "addr:full":"28 Knollwood Dr Rochester NY 14618",
    "addr:housenumber":"28",
    "addr:postcode":"14618",
    "addr:street":"Knollwood Dr",
    "iso:country":"US",
    "sg:address":"28 Knollwood Dr",
    "sg:city":"Rochester",
    "sg:classifiers":[
        {
            "category":"Health Services",
            "subcategory":"Doctor",
            "type":"Services"
        }
    ],
    "sg:phone":"+1 585 442 3411",
    "sg:postcode":"14618",
    "sg:province":"NY",
    "sg:tags":[
        "physician",
        "surgeon"
    ],
    "wof:name":"Retina Associates",
    "wof:placetype":"venue"
},
  "geometry": {"coordinates":[-77.529445,43.12069],"type":"Point"}
}