{
  "type": "Feature",
  "properties": {
    "iso:country":"US",
    "sg:address":"387 Main St",
    "sg:city":"East Aurora",
    "sg:classifiers":[
        {
            "category":"Real Estate",
            "subcategory":"Real Estate Agent",
            "type":"Services"
        }
    ],
    "sg:phone":"+1 716 652 6122",
    "sg:postcode":"14052",
    "sg:province":"NY",
    "wof:name":"Western New York Metro Rose",
    "wof:placetype":"venue"
},
  "geometry": {"coordinates":[-78.620563,42.767998],"type":"Point"}
}