{
  "type": "Feature",
  "properties": {
    "addr:full":"784 Main St Poughkeepsie NY 12603",
    "addr:housenumber":"784",
    "addr:postcode":"12603",
    "addr:street":"Main St",
    "iso:country":"US",
    "sg:address":"784 Main St",
    "sg:city":"Poughkeepsie",
    "sg:classifiers":[
        {
            "category":"Personal",
            "subcategory":"Beauty Salon",
            "type":"Services"
        }
    ],
    "sg:phone":"+1 845 483 7772",
    "sg:postcode":"12603",
    "sg:province":"NY",
    "sg:tags":[
        "shop"
    ],
    "wof:name":"Nails 4U",
    "wof:placetype":"venue"
},
  "geometry": {"coordinates":[-73.902029,41.696167],"type":"Point"}
}