{
  "type": "Feature",
  "properties": {
    "addr:full":"794 Madison Ave New York NY 10065",
    "addr:housenumber":"794",
    "addr:postcode":"10065",
    "addr:street":"Madison Ave",
    "iso:country":"US",
    "sg:address":"794 Madison Ave",
    "sg:city":"New York",
    "sg:classifiers":[
        {
            "category":"Shopping",
            "subcategory":"Clothing, Apparel, & Fashions",
            "type":"Retail Goods"
        }
    ],
    "sg:phone":"+1 212 439 7777",
    "sg:postcode":"10065",
    "sg:province":"NY",
    "wof:name":"Creed Boutique Llc",
    "wof:placetype":"venue"
},
  "geometry": {"coordinates":[-73.967792,40.768853],"type":"Point"}
}