{
  "type": "Feature",
  "properties": {
    "iso:country":"US",
    "sg:address":"111 Sydney Ave",
    "sg:city":"Malverne",
    "sg:classifiers":[
        {
            "category":"Utilities",
            "subcategory":"Telephone",
            "type":"Services"
        }
    ],
    "sg:phone":"+1 516 593 1863",
    "sg:postcode":"11565",
    "sg:province":"NY",
    "sg:tags":[
        "telecommunication"
    ],
    "wof:name":"Custom Telecard Inc",
    "wof:placetype":"venue"
},
  "geometry": {"coordinates":[-73.672168,40.679228],"type":"Point"}
}