{
  "type": "Feature",
  "properties": {
    "addr:full":"699 E 187th St Bronx NY 10458",
    "addr:housenumber":"699",
    "addr:postcode":"10458",
    "addr:street":"E 187Th St",
    "iso:country":"US",
    "sg:address":"699 E 187th St",
    "sg:city":"Bronx",
    "sg:classifiers":[
        {
            "category":"Restaurant",
            "type":"Food & Drink"
        }
    ],
    "sg:phone":"+1 800 925 4907",
    "sg:postcode":"10458",
    "sg:province":"NY",
    "sg:tags":[
        "mexican"
    ],
    "wof:name":"La Guadalupana Mexican Restaurant",
    "wof:placetype":"venue"
},
  "geometry": {"coordinates":[-73.884396,40.854293],"type":"Point"}
}