{
  "type": "Feature",
  "properties": {
    "addr:full":"1344 Peru South Lansing Rd Groton NY 13073",
    "addr:housenumber":"1344",
    "addr:postcode":"13073",
    "addr:street":"Peru South Lansing Rd",
    "iso:country":"US",
    "sg:address":"1344 Peru South Lansing Rd",
    "sg:city":"Groton",
    "sg:classifiers":[
        {
            "category":"Manufacturing",
            "subcategory":"Buildings",
            "type":"Manufacturing & Wholesale Goods"
        }
    ],
    "sg:phone":"+1 607 898 4653",
    "sg:postcode":"13073",
    "sg:province":"NY",
    "sg:tags":[
        "home",
        "builder"
    ],
    "wof:name":"Constance Vormwald",
    "wof:placetype":"venue"
},
  "geometry": {"coordinates":[-76.367836,42.548009],"type":"Point"}
}