{
  "type": "Feature",
  "properties": {
    "iso:country":"US",
    "sg:address":"225 Marcus Blvd",
    "sg:city":"Hauppauge",
    "sg:classifiers":[
        {
            "category":"Manufacturing",
            "subcategory":"Electronics",
            "type":"Manufacturing & Wholesale Goods"
        }
    ],
    "sg:phone":"+1 631 273 0911",
    "sg:postcode":"11788",
    "sg:province":"NY",
    "sg:tags":[
        "semiconductor",
        "related",
        "devices"
    ],
    "wof:name":"Pall Corp",
    "wof:placetype":"venue"
},
  "geometry": {"coordinates":[-73.247195,40.814966],"type":"Point"}
}