{
  "type": "Feature",
  "properties": {
    "iso:country":"US",
    "sg:address":"733 Cherry Valley Hill Rd",
    "sg:city":"Maine",
    "sg:classifiers":[
        {
            "category":"Building & Trades",
            "subcategory":"Construction",
            "type":"Services"
        }
    ],
    "sg:phone":"+1 607 692 4105",
    "sg:postcode":"13802",
    "sg:province":"NY",
    "sg:tags":[
        "contractor"
    ],
    "wof:name":"Barnes Construction",
    "wof:placetype":"venue"
},
  "geometry": {"coordinates":[-76.01094500000001,42.286648],"type":"Point"}
}