{
  "type": "Feature",
  "properties": {
    "iso:country":"US",
    "sg:address":"29 N Broad St",
    "sg:city":"Norwich",
    "sg:classifiers":[
        {
            "category":"Bars & Pubs",
            "type":"Food & Drink"
        }
    ],
    "sg:phone":"+1 607 336 5050",
    "sg:postcode":"13815",
    "sg:province":"NY",
    "wof:name":"Broad Street Tavern",
    "wof:placetype":"venue"
},
  "geometry": {"coordinates":[-75.5239,42.532626],"type":"Point"}
}