{
  "type": "Feature",
  "properties": {
    "addr:full":"6723 11th Ave Brooklyn NY 11219",
    "addr:housenumber":"6723",
    "addr:postcode":"11219",
    "addr:street":"11Th Ave",
    "iso:country":"US",
    "sg:address":"6723 11th Ave",
    "sg:city":"Brooklyn",
    "sg:classifiers":[
        {
            "category":"Organizations",
            "subcategory":"Religious Organization",
            "type":"Services"
        }
    ],
    "sg:phone":"+1 718 232 2884",
    "sg:postcode":"11219",
    "sg:province":"NY",
    "sg:tags":[
        "clergy"
    ],
    "wof:name":"Conrad Gatdula",
    "wof:placetype":"venue"
},
  "geometry": {"coordinates":[-74.007656,40.626913],"type":"Point"}
}