{
  "type": "Feature",
  "properties": {
    "iso:country":"US",
    "sg:address":"38 Jamaica Walk",
    "sg:city":"Far Rockaway",
    "sg:classifiers":[
        {
            "category":"Manufacturing",
            "subcategory":"Apparel",
            "type":"Manufacturing & Wholesale Goods"
        }
    ],
    "sg:phone":"+1   ",
    "sg:postcode":"11697",
    "sg:province":"NY",
    "sg:tags":[
        "embroidery"
    ],
    "wof:name":"Added Touch Embroidery",
    "wof:placetype":"venue"
},
  "geometry": {"coordinates":[-73.919628,40.557954],"type":"Point"}
}