{
  "type": "Feature",
  "properties": {
    "iso:country":"US",
    "sg:address":"6 Canal St",
    "sg:city":"Center Moriches",
    "sg:classifiers":[
        {
            "category":"Building & Trades",
            "subcategory":"Construction",
            "type":"Services"
        }
    ],
    "sg:phone":"+1 631 874 0223",
    "sg:postcode":"11934",
    "sg:province":"NY",
    "sg:tags":[
        "contractor"
    ],
    "wof:name":"Sunshine Daydream Pools",
    "wof:placetype":"venue"
},
  "geometry": {"coordinates":[-72.795404,40.799218],"type":"Point"}
}