{
  "type": "Feature",
  "properties": {
    "iso:country":"US",
    "sg:address":"112 E Post Rd",
    "sg:city":"White Plains",
    "sg:classifiers":[
        {
            "category":"Government",
            "subcategory":"Office",
            "type":"Public Place"
        }
    ],
    "sg:phone":"+1 914 995 5534",
    "sg:postcode":"10601",
    "sg:province":"NY",
    "wof:name":"Westchester Heap Program",
    "wof:placetype":"venue"
},
  "geometry": {"coordinates":[-73.76710300000001,41.02805],"type":"Point"}
}