{
  "type": "Feature",
  "properties": {
    "iso:country":"US",
    "sg:address":"2463 Long Beach Rd",
    "sg:city":"Oceanside",
    "sg:classifiers":[
        {
            "category":"Building & Trades",
            "subcategory":"Construction",
            "type":"Services"
        }
    ],
    "sg:phone":"+1 516 766 9009",
    "sg:postcode":"11572",
    "sg:province":"NY",
    "sg:tags":[
        "general",
        "contractor"
    ],
    "wof:name":"Cibellis Contraction Inc",
    "wof:placetype":"venue"
},
  "geometry": {"coordinates":[-73.63826299999999,40.64662],"type":"Point"}
}