{
  "type": "Feature",
  "properties": {
    "iso:country":"US",
    "sg:address":"9 Mill St",
    "sg:city":"Port Chester",
    "sg:classifiers":[
        {
            "category":"Retail",
            "subcategory":"Auto Repair",
            "type":"Services"
        }
    ],
    "sg:phone":"+1 914 939 4632",
    "sg:postcode":"10573",
    "sg:province":"NY",
    "sg:tags":[
        "automobile",
        "lubrication"
    ],
    "wof:name":"Milbridge Service Station",
    "wof:placetype":"venue"
},
  "geometry": {"coordinates":[-73.65906,41.004118],"type":"Point"}
}