{
  "type": "Feature",
  "properties": {
    "addr:full":"68 Lincoln Ave Sayville NY 11782",
    "addr:housenumber":"68",
    "addr:postcode":"11782",
    "addr:street":"Lincoln Ave",
    "iso:country":"US",
    "sg:address":"68 Lincoln Ave",
    "sg:city":"Sayville",
    "sg:classifiers":[
        {
            "category":"Food & Beverages",
            "subcategory":"Specialty",
            "type":"Retail Goods"
        }
    ],
    "sg:phone":"+1 631 567 8577",
    "sg:postcode":"11782",
    "sg:province":"NY",
    "sg:tags":[
        "health",
        "diet"
    ],
    "wof:name":"Shaklee Distributor",
    "wof:placetype":"venue"
},
  "geometry": {"coordinates":[-73.081715,40.739],"type":"Point"}
}