{
  "type": "Feature",
  "properties": {
    "iso:country":"US",
    "sg:address":"1025 Rutland Rd",
    "sg:city":"Brooklyn",
    "sg:classifiers":[
        {
            "category":"Shopping",
            "subcategory":"Clothing, Apparel, & Fashions",
            "type":"Retail Goods"
        }
    ],
    "sg:phone":"+1 718 771 8110",
    "sg:postcode":"11212",
    "sg:province":"NY",
    "sg:tags":[
        "designer"
    ],
    "wof:name":"Simon's Furniture",
    "wof:placetype":"venue"
},
  "geometry": {"coordinates":[-73.925817,40.663057],"type":"Point"}
}