{
  "type": "Feature",
  "properties": {
    "addr:full":"80 Roslyn Rd Roslyn Heights NY 11577",
    "addr:housenumber":"80",
    "addr:postcode":"11577",
    "addr:street":"Roslyn Rd",
    "iso:country":"US",
    "sg:address":"80 Roslyn Rd",
    "sg:city":"Roslyn Heights",
    "sg:classifiers":[
        {
            "category":"Personal",
            "subcategory":"Shoe Repair & Shine",
            "type":"Services"
        }
    ],
    "sg:phone":"+1   ",
    "sg:postcode":"11577",
    "sg:province":"NY",
    "sg:tags":[
        "parlor"
    ],
    "wof:name":"Michaels Shoe Repair",
    "wof:placetype":"venue"
},
  "geometry": {"coordinates":[-73.640658,40.791625],"type":"Point"}
}