{
  "type": "Feature",
  "properties": {
    "iso:country":"US",
    "sg:address":"40 Pine St",
    "sg:city":"Saranac Lake",
    "sg:classifiers":[
        {
            "category":"Building & Trades",
            "subcategory":"Construction",
            "type":"Services"
        }
    ],
    "sg:phone":"+1 518 891 8123",
    "sg:postcode":"12983",
    "sg:province":"NY",
    "sg:tags":[
        "new",
        "renovation",
        "residential"
    ],
    "wof:name":"Cascade Builders Corporation",
    "wof:placetype":"venue"
},
  "geometry": {"coordinates":[-74.124278,44.328067],"type":"Point"}
}