{
  "type": "Feature",
  "properties": {
    "iso:country":"US",
    "sg:address":"95 Glenmore Dr",
    "sg:city":"New Rochelle",
    "sg:classifiers":[
        {
            "category":"Education",
            "subcategory":"School",
            "type":"Public Place"
        }
    ],
    "sg:phone":"+1 914 576 4460",
    "sg:postcode":"10801",
    "sg:province":"NY",
    "sg:website":"www.nred.org",
    "wof:name":"Daniel Webster Elementary Schl",
    "wof:placetype":"venue"
},
  "geometry": {"coordinates":[-73.79694000000001,40.919109],"type":"Point"}
}