{
  "type": "Feature",
  "properties": {
    "addr:full":"40 Nostrand Avenue Brooklyn NY 11205",
    "addr:housenumber":"40",
    "addr:postcode":"11205",
    "addr:street":"Nostrand Avenue",
    "iso:country":"US",
    "sg:address":"40 Nostrand Avenue",
    "sg:city":"Brooklyn",
    "sg:classifiers":[
        {
            "category":"Restaurant",
            "type":"Food & Drink"
        }
    ],
    "sg:phone":"+1 718 875 3124",
    "sg:postcode":"11205",
    "sg:province":"NY",
    "wof:name":"Fook Hing Kitchen",
    "wof:placetype":"venue"
},
  "geometry": {"coordinates":[-73.95331899999999,40.698339],"type":"Point"}
}