{
  "type": "Feature",
  "properties": {
    "addr:full":"16 Tobey Village Rd Pittsford NY 14534",
    "addr:housenumber":"16",
    "addr:postcode":"14534",
    "addr:street":"Tobey Village Rd",
    "iso:country":"US",
    "sg:address":"16 Tobey Village Rd",
    "sg:city":"Pittsford",
    "sg:classifiers":[
        {
            "category":"Shopping",
            "subcategory":"Computers & Home Electronics",
            "type":"Retail Goods"
        }
    ],
    "sg:phone":"+1 585 383 1290",
    "sg:postcode":"14534",
    "sg:province":"NY",
    "sg:tags":[
        "software"
    ],
    "wof:name":"Real Time Enterprises Inc",
    "wof:placetype":"venue"
},
  "geometry": {"coordinates":[-77.54357899999999,43.085372],"type":"Point"}
}