{
  "type": "Feature",
  "properties": {
    "iso:country":"US",
    "sg:address":"704 S Crouse Ave",
    "sg:city":"Syracuse",
    "sg:classifiers":[
        {
            "category":"Restaurant",
            "type":"Food & Drink"
        }
    ],
    "sg:phone":"+1   ",
    "sg:postcode":"13210",
    "sg:province":"NY",
    "sg:tags":[
        "eating"
    ],
    "wof:name":"Pizza Jerks",
    "wof:placetype":"venue"
},
  "geometry": {"coordinates":[-76.13670999999999,43.042316],"type":"Point"}
}