{
  "type": "Feature",
  "properties": {
    "addr:full":"81 S Main St Portville NY 14770",
    "addr:housenumber":"81",
    "addr:postcode":"14770",
    "addr:street":"S Main St",
    "iso:country":"US",
    "sg:address":"81 S Main St",
    "sg:city":"Portville",
    "sg:classifiers":[
        {
            "category":"Food & Beverages",
            "subcategory":"Groceries & Convenience Stores",
            "type":"Retail Goods"
        }
    ],
    "sg:phone":"+1 716 933 8411",
    "sg:postcode":"14770",
    "sg:province":"NY",
    "sg:tags":[
        "grocer",
        "super",
        "supermarket"
    ],
    "wof:name":"Service Store Park & Shop",
    "wof:placetype":"venue"
},
  "geometry": {"coordinates":[-78.33775300000001,42.034168],"type":"Point"}
}