{
  "type": "Feature",
  "properties": {
    "iso:country":"US",
    "sg:address":"100 W 89 St",
    "sg:city":"New York",
    "sg:classifiers":[
        {
            "category":"Professional",
            "type":"Services"
        }
    ],
    "sg:phone":"+1 212 580 2230",
    "sg:postcode":"10024",
    "sg:province":"NY",
    "sg:tags":[
        "establishment"
    ],
    "wof:name":"Ed Brooks Management",
    "wof:placetype":"venue"
},
  "geometry": {"coordinates":[-73.973607,40.789615],"type":"Point"}
}