{
  "type": "Feature",
  "properties": {
    "iso:country":"US",
    "sg:address":"405 Jericho Tpke",
    "sg:city":"New Hyde Park",
    "sg:classifiers":[
        {
            "category":"Retail",
            "subcategory":"Laundry & Dry Cleaning",
            "type":"Services"
        }
    ],
    "sg:phone":"+1 516 775 5344",
    "sg:postcode":"11040",
    "sg:province":"NY",
    "sg:tags":[
        "cleaners"
    ],
    "wof:name":"T & S Cleaners",
    "wof:placetype":"venue"
},
  "geometry": {"coordinates":[-73.690101,40.731587],"type":"Point"}
}