{
  "type": "Feature",
  "properties": {
    "iso:country":"US",
    "sg:address":"173 Smithtown Blvd",
    "sg:city":"Nesconset",
    "sg:classifiers":[
        {
            "category":"Fast Food",
            "type":"Food & Drink"
        },
        {
            "category":"Restaurant",
            "type":"Food & Drink"
        },
        {
            "category":"Food & Beverages",
            "subcategory":"Groceries & Convenience Stores",
            "type":"Retail Goods"
        }
    ],
    "sg:phone":"+1 631 240 7756",
    "sg:postcode":"11767",
    "sg:province":"NY",
    "sg:tags":[
        "shop",
        "american",
        "sandwich",
        "take"
    ],
    "sg:website":"http://www.subway.com",
    "wof:name":"Subway",
    "wof:placetype":"venue"
},
  "geometry": {"coordinates":[-73.156284,40.836554],"type":"Point"}
}