{
  "type": "Feature",
  "properties": {
    "addr:full":"320 Saw Mill River Rd Yonkers NY 10701",
    "addr:housenumber":"320",
    "addr:postcode":"10701",
    "addr:street":"Saw Mill River Rd",
    "iso:country":"US",
    "sg:address":"320 Saw Mill River Rd",
    "sg:city":"Yonkers",
    "sg:classifiers":[
        {
            "category":"Professional",
            "subcategory":"Computer Services",
            "type":"Services"
        }
    ],
    "sg:phone":"+1 914 375 0005",
    "sg:postcode":"10701",
    "sg:province":"NY",
    "sg:tags":[
        "website",
        "design"
    ],
    "wof:name":"Grove Management",
    "wof:placetype":"venue"
},
  "geometry": {"coordinates":[-73.876537,40.947608],"type":"Point"}
}