{
  "type": "Feature",
  "properties": {
    "addr:full":"4 Eton Pl Plainview NY 11803",
    "addr:housenumber":"4",
    "addr:postcode":"11803",
    "addr:street":"Eton Pl",
    "iso:country":"US",
    "sg:address":"4 Eton Pl",
    "sg:city":"Plainview",
    "sg:classifiers":[
        {
            "category":"Professional",
            "subcategory":"Business Services",
            "type":"Services"
        }
    ],
    "sg:phone":"+1 516 349 8553",
    "sg:postcode":"11803",
    "sg:province":"NY",
    "wof:name":"Flash Construction Inc",
    "wof:placetype":"venue"
},
  "geometry": {"coordinates":[-73.48197500000001,40.792479],"type":"Point"}
}