{
  "type": "Feature",
  "properties": {
    "addr:full":"680 Central Ave Cedarhurst NY 11516",
    "addr:housenumber":"680",
    "addr:postcode":"11516",
    "addr:street":"Central Ave",
    "iso:country":"US",
    "sg:address":"680 Central Ave",
    "sg:city":"Cedarhurst",
    "sg:classifiers":[
        {
            "category":"Shopping",
            "subcategory":"Clothing, Apparel, & Fashions",
            "type":"Retail Goods"
        }
    ],
    "sg:phone":"+1 516 295 0946",
    "sg:postcode":"11516",
    "sg:province":"NY",
    "sg:tags":[
        "children's",
        "clothing"
    ],
    "sg:website":"www.dennyschildrenswear.com",
    "wof:name":"Dennys Children Wear",
    "wof:placetype":"venue"
},
  "geometry": {"coordinates":[-73.719803,40.624401],"type":"Point"}
}