{
  "type": "Feature",
  "properties": {
    "addr:full":"697 Middle Neck Rd Great Neck NY 11023",
    "addr:housenumber":"697",
    "addr:postcode":"11023",
    "addr:street":"Middle Neck Rd",
    "iso:country":"US",
    "sg:address":"697 Middle Neck Rd",
    "sg:city":"Great Neck",
    "sg:classifiers":[
        {
            "category":"Home & Garden",
            "subcategory":"Home Furnishings",
            "type":"Retail Goods"
        }
    ],
    "sg:phone":"+1   ",
    "sg:postcode":"11023",
    "sg:province":"NY",
    "sg:tags":[
        "crystal",
        "glassware",
        "gift"
    ],
    "wof:name":"Janets Collection",
    "wof:placetype":"venue"
},
  "geometry": {"coordinates":[-73.735558,40.803809],"type":"Point"}
}