{
  "type": "Feature",
  "properties": {
    "iso:country":"US",
    "sg:address":"2114 Genesee St",
    "sg:city":"Utica",
    "sg:classifiers":[
        {
            "category":"Health Services",
            "subcategory":"Doctor",
            "type":"Services"
        }
    ],
    "sg:phone":"+1   ",
    "sg:postcode":"13502",
    "sg:province":"NY",
    "wof:name":"Mohsan Saleh",
    "wof:placetype":"venue"
},
  "geometry": {"coordinates":[-75.265992,43.084323],"type":"Point"}
}