{
  "type": "Feature",
  "properties": {
    "addr:full":"1201 Hylan Blvd Staten Island NY 10305",
    "addr:housenumber":"1201",
    "addr:postcode":"10305",
    "addr:street":"Hylan Blvd",
    "iso:country":"US",
    "sg:address":"1201 Hylan Blvd",
    "sg:city":"Staten Island",
    "sg:classifiers":[
        {
            "category":"Real Estate",
            "subcategory":"Real Estate Agent",
            "type":"Services"
        }
    ],
    "sg:phone":"+1 718 981 9991",
    "sg:postcode":"10305",
    "sg:province":"NY",
    "wof:name":"Millinnium Realty Corp",
    "wof:placetype":"venue"
},
  "geometry": {"coordinates":[-74.083139,40.598224],"type":"Point"}
}