{
  "type": "Feature",
  "properties": {
    "iso:country":"US",
    "sg:address":"12 Mercer St",
    "sg:city":"Manhattan",
    "sg:classifiers":[
        {
            "category":"Professional",
            "subcategory":"Printing & Photocopies",
            "type":"Services"
        }
    ],
    "sg:phone":"+1 212 254 7200",
    "sg:postcode":"10013",
    "sg:province":"NY",
    "sg:website":"www.uscolorlab.com",
    "wof:name":"US Color Lab",
    "wof:placetype":"venue"
},
  "geometry": {"coordinates":[-74.00215900000001,40.720368],"type":"Point"}
}