{
  "type": "Feature",
  "properties": {
    "addr:full":"2 Fairground Rd Monticello NY 12701",
    "addr:housenumber":"2",
    "addr:postcode":"12701",
    "addr:street":"Fairground Rd",
    "iso:country":"US",
    "sg:address":"2 Fairground Rd",
    "sg:city":"Monticello",
    "sg:classifiers":[
        {
            "category":"Manufacturing",
            "subcategory":"Food",
            "type":"Manufacturing & Wholesale Goods"
        }
    ],
    "sg:phone":"+1 845 796 4160",
    "sg:postcode":"12701",
    "sg:province":"NY",
    "sg:tags":[
        "winery"
    ],
    "wof:name":"Allied Wine Corp",
    "wof:placetype":"venue"
},
  "geometry": {"coordinates":[-74.68668700000001,41.646253],"type":"Point"}
}