{
  "type": "Feature",
  "properties": {
    "iso:country":"US",
    "sg:address":"408 E 11 St",
    "sg:city":"New York",
    "sg:classifiers":[
        {
            "category":"Building & Trades",
            "subcategory":"Construction",
            "type":"Services"
        }
    ],
    "sg:phone":"+1 212 475 2909",
    "sg:postcode":"10009",
    "sg:province":"NY",
    "sg:tags":[
        "tile",
        "dealer"
    ],
    "wof:name":"Bella Tile Co Inc",
    "wof:placetype":"venue"
},
  "geometry": {"coordinates":[-73.981964,40.728457],"type":"Point"}
}