{
  "type": "Feature",
  "properties": {
    "iso:country":"US",
    "sg:address":"187 W Main St",
    "sg:city":"Webster",
    "sg:classifiers":[
        {
            "category":"Sports & Exercise",
            "subcategory":"Gym",
            "type":"Entertainment"
        }
    ],
    "sg:phone":"+1 585 265 4530",
    "sg:postcode":"14580",
    "sg:province":"NY",
    "sg:tags":[
        "club",
        "health",
        "studio",
        "gymnasium"
    ],
    "wof:name":"World Gym Webster",
    "wof:placetype":"venue"
},
  "geometry": {"coordinates":[-77.43686599999999,43.211575],"type":"Point"}
}