{
  "type": "Feature",
  "properties": {
    "iso:country":"US",
    "sg:address":"370 Yale Rd",
    "sg:city":"Garden City",
    "sg:classifiers":[
        {
            "category":"Building & Trades",
            "subcategory":"Construction",
            "type":"Services"
        }
    ],
    "sg:phone":"+1 718 229 2667",
    "sg:postcode":"11530",
    "sg:province":"NY",
    "sg:tags":[
        "contractor"
    ],
    "wof:name":"A To Z Contracting",
    "wof:placetype":"venue"
},
  "geometry": {"coordinates":[-73.665307,40.717244],"type":"Point"}
}