{
  "type": "Feature",
  "properties": {
    "addr:full":"2112 Cortelyou Rd Brooklyn NY 11226",
    "addr:housenumber":"2112",
    "addr:postcode":"11226",
    "addr:street":"Cortelyou Rd",
    "iso:country":"US",
    "sg:address":"2112 Cortelyou Rd",
    "sg:city":"Brooklyn",
    "sg:classifiers":[
        {
            "category":"Retail",
            "subcategory":"Auto Repair",
            "type":"Services"
        }
    ],
    "sg:phone":"+1 718 851 5090",
    "sg:postcode":"11226",
    "sg:province":"NY",
    "sg:website":"www.brooklyn-towing.com",
    "wof:name":"Brooklyn Emergency Towing",
    "wof:placetype":"venue"
},
  "geometry": {"coordinates":[-73.95826599999999,40.643832],"type":"Point"}
}