{
  "type": "Feature",
  "properties": {
    "addr:full":"2488 Browncroft Blvd Rochester NY 14625",
    "addr:housenumber":"2488",
    "addr:postcode":"14625",
    "addr:street":"Browncroft Blvd",
    "iso:country":"US",
    "sg:address":"2488 Browncroft Blvd",
    "sg:city":"Rochester",
    "sg:classifiers":[
        {
            "category":"Real Estate",
            "subcategory":"Real Estate Agent",
            "type":"Services"
        }
    ],
    "sg:phone":"+1 585 381 6141",
    "sg:postcode":"14625",
    "sg:province":"NY",
    "wof:name":"Century 21",
    "wof:placetype":"venue"
},
  "geometry": {"coordinates":[-77.505883,43.153735],"type":"Point"}
}