{
  "type": "Feature",
  "properties": {
    "iso:country":"US",
    "sg:address":"58 Palisade Ave",
    "sg:city":"Yonkers",
    "sg:classifiers":[
        {
            "category":"Retail",
            "subcategory":"Laundry & Dry Cleaning",
            "type":"Services"
        }
    ],
    "sg:phone":"+1 914 969 1999",
    "sg:postcode":"10701",
    "sg:province":"NY",
    "sg:tags":[
        "cleaners",
        "rug",
        "carpet"
    ],
    "wof:name":"L & M Rug Cleaners",
    "wof:placetype":"venue"
},
  "geometry": {"coordinates":[-73.894769,40.934914],"type":"Point"}
}