{
  "type": "Feature",
  "properties": {
    "addr:full":"490 McDonald Ave Brooklyn NY 11218",
    "addr:housenumber":"490",
    "addr:postcode":"11218",
    "addr:street":"Mcdonald Ave",
    "iso:country":"US",
    "sg:address":"490 McDonald Ave",
    "sg:city":"Brooklyn",
    "sg:classifiers":[
        {
            "category":"Travel",
            "subcategory":"Travel Agent",
            "type":"Entertainment"
        }
    ],
    "sg:phone":"+1   ",
    "sg:postcode":"11218",
    "sg:province":"NY",
    "sg:tags":[
        "agency"
    ],
    "wof:name":"Nipun Travel & Tours",
    "wof:placetype":"venue"
},
  "geometry": {"coordinates":[-73.979203,40.641238],"type":"Point"}
}