{
  "type": "Feature",
  "properties": {
    "addr:full":"2306 1 Ave New York NY 10035",
    "addr:housenumber":"2306",
    "addr:postcode":"10035",
    "addr:street":"1 Ave",
    "iso:country":"US",
    "sg:address":"2306 1 Ave",
    "sg:city":"New York",
    "sg:classifiers":[
        {
            "category":"Manufacturing",
            "subcategory":"Food",
            "type":"Manufacturing & Wholesale Goods"
        }
    ],
    "sg:phone":"+1   ",
    "sg:postcode":"10035",
    "sg:province":"NY",
    "sg:tags":[
        "equipment",
        "bakery"
    ],
    "wof:name":"Nightingale Food Enterprises",
    "wof:placetype":"venue"
},
  "geometry": {"coordinates":[-73.93491299999999,40.796679],"type":"Point"}
}