{
  "type": "Feature",
  "properties": {
    "addr:full":"2 Cooper Ave Huntington Station NY 11746",
    "addr:housenumber":"2",
    "addr:postcode":"11746",
    "addr:street":"Cooper Ave Huntington",
    "iso:country":"US",
    "sg:address":"2 Cooper Ave",
    "sg:city":"Huntington Station",
    "sg:classifiers":[
        {
            "category":"Professional",
            "subcategory":"Art Services",
            "type":"Services"
        }
    ],
    "sg:phone":"+1 631 385 7200",
    "sg:postcode":"11746",
    "sg:province":"NY",
    "sg:tags":[
        "commercial",
        "design"
    ],
    "wof:name":"Painted Pieces D Signers",
    "wof:placetype":"venue"
},
  "geometry": {"coordinates":[-73.37711899999999,40.835892],"type":"Point"}
}