{
  "type": "Feature",
  "properties": {
    "iso:country":"US",
    "sg:address":"15947 102nd St",
    "sg:city":"Howard Beach",
    "sg:classifiers":[
        {
            "category":"Retail",
            "subcategory":"Auto Repair",
            "type":"Services"
        }
    ],
    "sg:phone":"+1 718 441 4672",
    "sg:postcode":"11414",
    "sg:province":"NY",
    "wof:name":"Gary's Auto Repr",
    "wof:placetype":"venue"
},
  "geometry": {"coordinates":[-73.831001,40.659],"type":"Point"}
}