{
  "type": "Feature",
  "properties": {
    "iso:country":"US",
    "sg:address":"160 Long Island Ave",
    "sg:city":"Holtsville",
    "sg:classifiers":[
        {
            "category":"Building & Trades",
            "subcategory":"Equipment Rental",
            "type":"Services"
        }
    ],
    "sg:phone":"+1 631 758 6600",
    "sg:postcode":"11742",
    "sg:province":"NY",
    "wof:name":"Affatatl Paving",
    "wof:placetype":"venue"
},
  "geometry": {"coordinates":[-73.04114800000001,40.814817],"type":"Point"}
}