{
  "type": "Feature",
  "properties": {
    "iso:country":"US",
    "sg:address":"71 Lyell Ave",
    "sg:city":"Spencerport",
    "sg:classifiers":[
        {
            "category":"Organizations",
            "subcategory":"Labor Organization",
            "type":"Services"
        }
    ],
    "sg:phone":"+1 585 352 4160",
    "sg:postcode":"14559",
    "sg:province":"NY",
    "wof:name":"Spencerport Teachers Assn",
    "wof:placetype":"venue"
},
  "geometry": {"coordinates":[-77.793812,43.188999],"type":"Point"}
}