{
  "type": "Feature",
  "properties": {
    "addr:full":"22-55 31st St Ste 200 Astoria NY 11105",
    "addr:housenumber":"22-55",
    "addr:postcode":"11105",
    "addr:street":"31St St Ste 200",
    "iso:country":"US",
    "sg:address":"22-55 31st St Ste 200",
    "sg:city":"Astoria",
    "sg:classifiers":[
        {
            "category":"Personal",
            "subcategory":"Massage",
            "type":"Services"
        },
        {
            "category":"Sports & Exercise",
            "subcategory":"Gym",
            "type":"Entertainment"
        },
        {
            "category":"Personal",
            "subcategory":"Day Spa",
            "type":"Services"
        }
    ],
    "sg:phone":"+1 347 345 6095",
    "sg:postcode":"11105",
    "sg:province":"NY",
    "sg:tags":[
        "yoga"
    ],
    "sg:website":"www.yogaastoria.com",
    "wof:name":"Creative Vibrations Yoga Studio & Ayurvedic Spa",
    "wof:placetype":"venue"
},
  "geometry": {"coordinates":[-73.911866,40.774797],"type":"Point"}
}