{
  "type": "Feature",
  "properties": {
    "iso:country":"US",
    "sg:address":"28 Graham Ave",
    "sg:city":"Brooklyn",
    "sg:classifiers":[
        {
            "category":"Shopping",
            "subcategory":"Optical Goods",
            "type":"Retail Goods"
        }
    ],
    "sg:phone":"+1 718 486 0117",
    "sg:postcode":"11206",
    "sg:province":"NY",
    "sg:tags":[
        "optician"
    ],
    "wof:name":"General Vision Express",
    "wof:placetype":"venue"
},
  "geometry": {"coordinates":[-73.942381,40.702346],"type":"Point"}
}