{
  "type": "Feature",
  "properties": {
    "iso:country":"US",
    "sg:address":"27 Washington Ave",
    "sg:city":"Port Jefferson Station",
    "sg:classifiers":[
        {
            "category":"Utilities",
            "subcategory":"Telephone",
            "type":"Services"
        }
    ],
    "sg:phone":"+1   ",
    "sg:postcode":"11776",
    "sg:province":"NY",
    "sg:tags":[
        "wireless",
        "communications"
    ],
    "wof:name":"Ace Communications of LI Inc",
    "wof:placetype":"venue"
},
  "geometry": {"coordinates":[-73.064555,40.920127],"type":"Point"}
}