{
  "type": "Feature",
  "properties": {
    "iso:country":"US",
    "sg:address":"670 Parkside Ave",
    "sg:city":"Brooklyn",
    "sg:classifiers":[
        {
            "category":"Professional",
            "subcategory":"Computer Services",
            "type":"Services"
        }
    ],
    "sg:phone":"+1 800 281 4851",
    "sg:postcode":"11226",
    "sg:province":"NY",
    "sg:tags":[
        "stereo",
        "installation"
    ],
    "wof:name":"Car Stereo international",
    "wof:placetype":"venue"
},
  "geometry": {"coordinates":[-73.951061,40.65606],"type":"Point"}
}