{
  "type": "Feature",
  "properties": {
    "addr:full":"391 N Country Rd Smithtown NY 11787",
    "addr:housenumber":"391",
    "addr:postcode":"11787",
    "addr:street":"N Country Rd",
    "iso:country":"US",
    "sg:address":"391 N Country Rd",
    "sg:city":"Smithtown",
    "sg:classifiers":[
        {
            "category":"Professional",
            "subcategory":"Research",
            "type":"Services"
        }
    ],
    "sg:phone":"+1 631 366 5220",
    "sg:postcode":"11787",
    "sg:province":"NY",
    "sg:tags":[
        "laboratory"
    ],
    "wof:name":"Apex Laboratory",
    "wof:placetype":"venue"
},
  "geometry": {"coordinates":[-73.17203600000001,40.871212],"type":"Point"}
}