{
  "type": "Feature",
  "properties": {
    "addr:full":"217 W Merrick Rd Valley Stream NY 11580",
    "addr:housenumber":"217",
    "addr:postcode":"11580",
    "addr:street":"W Merrick Rd",
    "iso:country":"US",
    "sg:address":"217 W Merrick Rd",
    "sg:city":"Valley Stream",
    "sg:classifiers":[
        {
            "category":"Restaurant",
            "type":"Food & Drink"
        }
    ],
    "sg:menulink":"http://www.allmenus.com/ny/valley-stream/210488-kfc---kentucky-fried-chicken/menu/",
    "sg:phone":"+1 516 825 1067",
    "sg:postcode":"11580",
    "sg:province":"NY",
    "sg:tags":[
        "american",
        "chicken"
    ],
    "wof:name":"KFC - Kentucky Fried Chicken",
    "wof:placetype":"venue"
},
  "geometry": {"coordinates":[-73.705539,40.666979],"type":"Point"}
}