{
  "type": "Feature",
  "properties": {
    "addr:full":"11220 Jamaica Ave Richmond Hill NY 11418",
    "addr:housenumber":"11220",
    "addr:postcode":"11418",
    "addr:street":"Jamaica Ave",
    "iso:country":"US",
    "sg:address":"11220 Jamaica Ave",
    "sg:city":"Richmond Hill",
    "sg:classifiers":[
        {
            "category":"Shopping",
            "subcategory":"Mobile Phones",
            "type":"Retail Goods"
        }
    ],
    "sg:phone":"+1 718 441 2230",
    "sg:postcode":"11418",
    "sg:province":"NY",
    "wof:name":"MetroPCS",
    "wof:placetype":"venue"
},
  "geometry": {"coordinates":[-73.836136,40.697373],"type":"Point"}
}