{
  "type": "Feature",
  "properties": {
    "addr:full":"150 Central Ave Ilion NY 13357",
    "addr:housenumber":"150",
    "addr:postcode":"13357",
    "addr:street":"Central Ave",
    "iso:country":"US",
    "sg:address":"150 Central Ave",
    "sg:city":"Ilion",
    "sg:classifiers":[
        {
            "category":"Health Services",
            "subcategory":"Doctor",
            "type":"Services"
        }
    ],
    "sg:phone":"+1 315 894 5582",
    "sg:postcode":"13357",
    "sg:province":"NY",
    "sg:tags":[
        "physician",
        "family",
        "practice",
        "surgeons",
        "medicine",
        "surgeon"
    ],
    "wof:name":"Mohawk Valley Health Care Pc",
    "wof:placetype":"venue"
},
  "geometry": {"coordinates":[-75.03246,43.018935],"type":"Point"}
}