{
  "type": "Feature",
  "properties": {
    "iso:country":"US",
    "sg:address":"113 Court St",
    "sg:city":"Brooklyn",
    "sg:classifiers":[
        {
            "category":"Restaurant",
            "type":"Food & Drink"
        }
    ],
    "sg:phone":"+1 718 237 8898",
    "sg:postcode":"11201",
    "sg:province":"NY",
    "sg:tags":[
        "mexican"
    ],
    "wof:name":"Court Street Fresco Tortilla",
    "wof:placetype":"venue"
},
  "geometry": {"coordinates":[-73.991788,40.690604],"type":"Point"}
}