{
  "type": "Feature",
  "properties": {
    "iso:country":"US",
    "sg:address":"4054 Nesconset Hwy",
    "sg:city":"East Setauket",
    "sg:classifiers":[
        {
            "category":"Food & Beverages",
            "subcategory":"Groceries & Convenience Stores",
            "type":"Retail Goods"
        }
    ],
    "sg:phone":"+1 631 476 3664",
    "sg:postcode":"11733",
    "sg:province":"NY",
    "wof:name":"Waldbaums Supermarkets Pharmacy",
    "wof:placetype":"venue"
},
  "geometry": {"coordinates":[-73.085999,40.895802],"type":"Point"}
}