{
  "type": "Feature",
  "properties": {
    "addr:full":"664 Columbus Ave Thornwood NY 10594",
    "addr:housenumber":"664",
    "addr:postcode":"10594",
    "addr:street":"Columbus Ave",
    "iso:country":"US",
    "sg:address":"664 Columbus Ave",
    "sg:city":"Thornwood",
    "sg:classifiers":[
        {
            "category":"Personal",
            "subcategory":"Nail Salon",
            "type":"Services"
        }
    ],
    "sg:phone":"+1 914 747 5900",
    "sg:postcode":"10594",
    "sg:province":"NY",
    "wof:name":"Angel Tips Inc",
    "wof:placetype":"venue"
},
  "geometry": {"coordinates":[-73.77109,41.115056],"type":"Point"}
}