{
  "type": "Feature",
  "properties": {
    "addr:full":"192 Burroughs Dr Amherst NY 14226",
    "addr:housenumber":"192",
    "addr:postcode":"14226",
    "addr:street":"Burroughs Dr",
    "iso:country":"US",
    "sg:address":"192 Burroughs Dr",
    "sg:city":"Amherst",
    "sg:classifiers":[
        {
            "category":"Professional",
            "subcategory":"Management & Consulting",
            "type":"Services"
        }
    ],
    "sg:phone":"+1 716 839 0385",
    "sg:postcode":"14226",
    "sg:province":"NY",
    "sg:tags":[
        "consultant",
        "business"
    ],
    "wof:name":"Breakthrough Coaching",
    "wof:placetype":"venue"
},
  "geometry": {"coordinates":[-78.778604,42.964459],"type":"Point"}
}