{
  "type": "Feature",
  "properties": {
    "iso:country":"US",
    "sg:address":"222 E 93rd St",
    "sg:city":"New York",
    "sg:classifiers":[
        {
            "category":"Real Estate",
            "subcategory":"Real Estate Operator",
            "type":"Services"
        }
    ],
    "sg:phone":"+1 212 348 4200",
    "sg:postcode":"10128",
    "sg:province":"NY",
    "sg:tags":[
        "apartment"
    ],
    "wof:name":"Ruppert Housing Company",
    "wof:placetype":"venue"
},
  "geometry": {"coordinates":[-73.950203,40.783001],"type":"Point"}
}