{
  "type": "Feature",
  "properties": {
    "addr:full":"14 Franklin St Rochester NY 14604",
    "addr:housenumber":"14",
    "addr:postcode":"14604",
    "addr:street":"Franklin St",
    "iso:country":"US",
    "sg:address":"14 Franklin St",
    "sg:city":"Rochester",
    "sg:classifiers":[
        {
            "category":"Professional",
            "subcategory":"Management & Consulting",
            "type":"Services"
        }
    ],
    "sg:phone":"+1 585 454 6950",
    "sg:postcode":"14604",
    "sg:province":"NY",
    "sg:tags":[
        "consultant"
    ],
    "wof:name":"Dealflo Advisors",
    "wof:placetype":"venue"
},
  "geometry": {"coordinates":[-77.60459,43.157891],"type":"Point"}
}