{
  "type": "Feature",
  "properties": {
    "addr:full":"1252 Washington St Peekskill NY 10566",
    "addr:housenumber":"1252",
    "addr:postcode":"10566",
    "addr:street":"Washington St",
    "iso:country":"US",
    "sg:address":"1252 Washington St",
    "sg:city":"Peekskill",
    "sg:classifiers":[
        {
            "category":"Building & Trades",
            "subcategory":"Construction",
            "type":"Services"
        }
    ],
    "sg:phone":"+1 914 645 3692",
    "sg:postcode":"10566",
    "sg:province":"NY",
    "sg:tags":[
        "tile",
        "dealer"
    ],
    "wof:name":"Title Pro",
    "wof:placetype":"venue"
},
  "geometry": {"coordinates":[-73.92906000000001,41.268987],"type":"Point"}
}