{
  "type": "Feature",
  "properties": {
    "iso:country":"US",
    "sg:address":"165 Jefferson Hts",
    "sg:city":"Catskill",
    "sg:classifiers":[
        {
            "category":"Shopping",
            "subcategory":"Pharmacy",
            "type":"Retail Goods"
        }
    ],
    "sg:phone":"+1 518 943 2441",
    "sg:postcode":"12414",
    "sg:province":"NY",
    "sg:tags":[
        "drugstore"
    ],
    "wof:name":"Jefferson Hgts Pharmacy",
    "wof:placetype":"venue"
},
  "geometry": {"coordinates":[-73.878899,42.231998],"type":"Point"}
}