{
  "type": "Feature",
  "properties": {
    "addr:full":"234 W 14th St New York NY 10011",
    "addr:housenumber":"234",
    "addr:postcode":"10011",
    "addr:street":"W 14Th St",
    "iso:country":"US",
    "sg:address":"234 W 14th St",
    "sg:city":"New York",
    "sg:classifiers":[
        {
            "category":"Bars & Pubs",
            "type":"Food & Drink"
        }
    ],
    "sg:menulink":"http://www.allmenus.com/ny/new-york/249559-woody-mchales-bar--grill/menu/",
    "sg:phone":"+1 212 206 0430",
    "sg:postcode":"10011",
    "sg:province":"NY",
    "sg:tags":[
        "american"
    ],
    "wof:name":"Woody McHale's Bar & Grill",
    "wof:placetype":"venue"
},
  "geometry": {"coordinates":[-74.0016,40.73905],"type":"Point"}
}