{
  "type": "Feature",
  "properties": {
    "addr:full":"1230 Central Ave Albany NY 12205",
    "addr:housenumber":"1230",
    "addr:postcode":"12205",
    "addr:street":"Central Ave",
    "iso:country":"US",
    "sg:address":"1230 Central Ave",
    "sg:city":"Albany",
    "sg:classifiers":[
        {
            "category":"Building & Trades",
            "subcategory":"Construction",
            "type":"Services"
        }
    ],
    "sg:phone":"+1 518 292 0567",
    "sg:postcode":"12205",
    "sg:province":"NY",
    "sg:tags":[
        "waterproofing",
        "contractor"
    ],
    "wof:name":"Adirondack Waterproofing",
    "wof:placetype":"venue"
},
  "geometry": {"coordinates":[-73.808492,42.696061],"type":"Point"}
}