{
  "type": "Feature",
  "properties": {
    "iso:country":"US",
    "sg:address":"231 Church St",
    "sg:city":"Poughkeepsie",
    "sg:classifiers":[
        {
            "category":"Health Services",
            "subcategory":"Clinic",
            "type":"Services"
        }
    ],
    "sg:phone":"+1 845 452 8250",
    "sg:postcode":"12601",
    "sg:province":"NY",
    "sg:tags":[
        "welfare"
    ],
    "wof:name":"St Anthony Counseling And Health Center Inc",
    "wof:placetype":"venue"
},
  "geometry": {"coordinates":[-73.924469,41.70023],"type":"Point"}
}