{
  "type": "Feature",
  "properties": {
    "addr:full":"302 W 38th St New York NY 10018",
    "addr:housenumber":"302",
    "addr:postcode":"10018",
    "addr:street":"W 38Th St",
    "iso:country":"US",
    "sg:address":"302 W 38th St",
    "sg:city":"New York",
    "sg:classifiers":[
        {
            "category":"Restaurant",
            "type":"Food & Drink"
        }
    ],
    "sg:menulink":"http://www.allmenus.com/ny/new-york/6919-las-poblanitas-restaurant-mexicano/menu/",
    "sg:phone":"+1 212 629 0090",
    "sg:postcode":"10018",
    "sg:province":"NY",
    "sg:tags":[
        "mexican"
    ],
    "wof:name":"Las Poblanitas Restaurant Mexicano",
    "wof:placetype":"venue"
},
  "geometry": {"coordinates":[-73.991882,40.754816],"type":"Point"}
}