{
  "type": "Feature",
  "properties": {
    "addr:full":"402 Meriline Ave Schenectady NY 12302",
    "addr:housenumber":"402",
    "addr:postcode":"12302",
    "addr:street":"Meriline Ave",
    "iso:country":"US",
    "sg:address":"402 Meriline Ave",
    "sg:city":"Schenectady",
    "sg:classifiers":[
        {
            "category":"Bars & Pubs",
            "type":"Food & Drink"
        },
        {
            "category":"Restaurant",
            "type":"Food & Drink"
        }
    ],
    "sg:phone":"+1 518 372 0063",
    "sg:postcode":"12302",
    "sg:province":"NY",
    "sg:tags":[
        "tavern"
    ],
    "wof:name":"Jimmy Dee's Tavern",
    "wof:placetype":"venue"
},
  "geometry": {"coordinates":[-73.97260300000001,42.8382],"type":"Point"}
}