{
  "type": "Feature",
  "properties": {
    "iso:country":"US",
    "sg:address":"127 Springtown Rd",
    "sg:city":"New Paltz",
    "sg:classifiers":[
        {
            "category":"Social Services",
            "type":"Services"
        }
    ],
    "sg:phone":"+1 845 256 1515",
    "sg:postcode":"12561",
    "sg:province":"NY",
    "sg:tags":[
        "counselor",
        "marriage",
        "family"
    ],
    "wof:name":"Susan Piowaty",
    "wof:placetype":"venue"
},
  "geometry": {"coordinates":[-74.09356,41.769095],"type":"Point"}
}