{
  "type": "Feature",
  "properties": {
    "iso:country":"US",
    "sg:address":"1820 Avenue M",
    "sg:city":"Brooklyn",
    "sg:classifiers":[
        {
            "category":"Shopping",
            "type":"Retail Goods"
        }
    ],
    "sg:phone":"+1 718 339 2237",
    "sg:postcode":"11230",
    "sg:province":"NY",
    "sg:tags":[
        "merchandise"
    ],
    "wof:name":"J Goldring Jewellers",
    "wof:placetype":"venue"
},
  "geometry": {"coordinates":[-73.95668000000001,40.618362],"type":"Point"}
}