{
  "type": "Feature",
  "properties": {
    "iso:country":"US",
    "sg:address":"34 Cherry St",
    "sg:city":"Greene",
    "sg:classifiers":[
        {
            "category":"Government",
            "subcategory":"Office",
            "type":"Public Place"
        }
    ],
    "sg:phone":"+1 607 656 8311",
    "sg:postcode":"13778",
    "sg:province":"NY",
    "sg:tags":[
        "village"
    ],
    "wof:name":"Greene Village Electric Power",
    "wof:placetype":"venue"
},
  "geometry": {"coordinates":[-75.76502499999999,42.329854],"type":"Point"}
}