{
  "type": "Feature",
  "properties": {
    "addr:full":"3956 Victory Blvd Staten Island NY 10314",
    "addr:housenumber":"3956",
    "addr:postcode":"10314",
    "addr:street":"Victory Blvd",
    "iso:country":"US",
    "sg:address":"3956 Victory Blvd",
    "sg:city":"Staten Island",
    "sg:classifiers":[
        {
            "category":"Insurance",
            "subcategory":"Insurance Agent",
            "type":"Services"
        }
    ],
    "sg:phone":"+1 718 477 2070",
    "sg:postcode":"10314",
    "sg:province":"NY",
    "wof:name":"Csi-Cs Brokerage Agcy Intl Inc",
    "wof:placetype":"venue"
},
  "geometry": {"coordinates":[-74.18692900000001,40.5939],"type":"Point"}
}