{
  "type": "Feature",
  "properties": {
    "iso:country":"US",
    "sg:address":"5110 Fort Hamilton Pkwy",
    "sg:city":"Brooklyn",
    "sg:classifiers":[
        {
            "category":"Food & Beverages",
            "subcategory":"Groceries & Convenience Stores",
            "type":"Retail Goods"
        }
    ],
    "sg:phone":"+1   ",
    "sg:postcode":"11219",
    "sg:province":"NY",
    "wof:name":"Kosher Groceries Inc",
    "wof:placetype":"venue"
},
  "geometry": {"coordinates":[-73.99979999999999,40.637041],"type":"Point"}
}