{
  "type": "Feature",
  "properties": {
    "addr:full":"2 Graham Rd W Ithaca NY 14850",
    "addr:housenumber":"2",
    "addr:postcode":"14850",
    "addr:street":"Graham Rd W",
    "iso:country":"US",
    "sg:address":"2 Graham Rd W",
    "sg:city":"Ithaca",
    "sg:classifiers":[
        {
            "category":"Banks & Credit Unions",
            "subcategory":"Investment Brokerage",
            "type":"Services"
        }
    ],
    "sg:phone":"+1 607 266 8200",
    "sg:postcode":"14850",
    "sg:province":"NY",
    "sg:tags":[
        "security"
    ],
    "wof:name":"A G Edwards 446",
    "wof:placetype":"venue"
},
  "geometry": {"coordinates":[-76.48777,42.48608],"type":"Point"}
}