{
  "type": "Feature",
  "properties": {
    "addr:full":"291 Central Park West Manhattan NY 10024",
    "addr:housenumber":"291",
    "addr:postcode":"10024",
    "addr:street":"Central Park West",
    "iso:country":"US",
    "sg:address":"291 Central Park West",
    "sg:city":"Manhattan",
    "sg:classifiers":[
        {
            "category":"Personal",
            "type":"Services"
        }
    ],
    "sg:phone":"+1 347 875 3031",
    "sg:postcode":"10024",
    "sg:province":"NY",
    "sg:tags":[
        "home"
    ],
    "sg:website":"www.upperwestpestcontrol.com",
    "wof:name":"Upper West Pest Control",
    "wof:placetype":"venue"
},
  "geometry": {"coordinates":[-73.96801000000001,40.787462],"type":"Point"}
}