{
  "type": "Feature",
  "properties": {
    "addr:full":"127 East 56th St, 6th Floor Manhattan NY 10022",
    "addr:housenumber":"127;6th",
    "addr:postcode":"10022",
    "addr:street":"East 56Th St;Floor",
    "iso:country":"US",
    "sg:address":"127 East 56th St, 6th Floor",
    "sg:city":"Manhattan",
    "sg:classifiers":[
        {
            "category":"Health Services",
            "subcategory":"Chiropractor",
            "type":"Services"
        }
    ],
    "sg:phone":"+1 212 967 1620",
    "sg:postcode":"10022",
    "sg:province":"NY",
    "sg:website":"www.chiropracticforprevention.com",
    "wof:name":"Dr Melissa Kanes",
    "wof:placetype":"venue"
},
  "geometry": {"coordinates":[-73.97,40.760662],"type":"Point"}
}