{
  "type": "Feature",
  "properties": {
    "iso:country":"US",
    "sg:address":"207 N Long Beach Rd",
    "sg:city":"Rockville Centre",
    "sg:classifiers":[
        {
            "category":"Personal",
            "subcategory":"Beauty Salon",
            "type":"Services"
        }
    ],
    "sg:phone":"+1 516 536 8499",
    "sg:postcode":"11570",
    "sg:province":"NY",
    "sg:tags":[
        "nail",
        "shop"
    ],
    "sg:website":"www.romannails.com",
    "wof:name":"Roman Nails",
    "wof:placetype":"venue"
},
  "geometry": {"coordinates":[-73.62930299999999,40.6609],"type":"Point"}
}