{
  "type": "Feature",
  "properties": {
    "iso:country":"US",
    "sg:address":"250 William Ave",
    "sg:city":"Bronx",
    "sg:classifiers":[
        {
            "category":"Professional",
            "subcategory":"Business Services",
            "type":"Services"
        }
    ],
    "sg:phone":"+1 914 760 3934",
    "sg:postcode":"10464",
    "sg:province":"NY",
    "sg:tags":[
        "interior",
        "design"
    ],
    "wof:name":"All Under One Roof",
    "wof:placetype":"venue"
},
  "geometry": {"coordinates":[-73.787888,40.845033],"type":"Point"}
}