{
  "type": "Feature",
  "properties": {
    "iso:country":"US",
    "sg:address":"550 South Broadway",
    "sg:city":"Hicksville",
    "sg:classifiers":[
        {
            "category":"Restaurant",
            "type":"Food & Drink"
        }
    ],
    "sg:phone":"+1 516 470 9547",
    "sg:postcode":"11801",
    "sg:province":"NY",
    "sg:tags":[
        "japanese"
    ],
    "wof:name":"Miyako Hibachi Sushi Bar",
    "wof:placetype":"venue"
},
  "geometry": {"coordinates":[-73.510002,40.756134],"type":"Point"}
}