{
  "type": "Feature",
  "properties": {
    "addr:full":"34 Andony Ln Rochester NY 14624",
    "addr:housenumber":"34",
    "addr:postcode":"14624",
    "addr:street":"Andony Ln",
    "iso:country":"US",
    "sg:address":"34 Andony Ln",
    "sg:city":"Rochester",
    "sg:classifiers":[
        {
            "category":"Shopping",
            "subcategory":"Hobbies, Toys, & Games",
            "type":"Retail Goods"
        }
    ],
    "sg:phone":"+1 585 889 8768",
    "sg:postcode":"14624",
    "sg:province":"NY",
    "sg:tags":[
        "supply"
    ],
    "wof:name":"Craft Day Creations",
    "wof:placetype":"venue"
},
  "geometry": {"coordinates":[-77.766632,43.103567],"type":"Point"}
}