{
  "type": "Feature",
  "properties": {
    "addr:full":"55 Pioneer St Cooperstown NY 13326",
    "addr:housenumber":"55",
    "addr:postcode":"13326",
    "addr:street":"Pioneer St",
    "iso:country":"US",
    "sg:address":"55 Pioneer St",
    "sg:city":"Cooperstown",
    "sg:classifiers":[
        {
            "category":"Shopping",
            "type":"Retail Goods"
        }
    ],
    "sg:phone":"+1 607 547 8671",
    "sg:postcode":"13326",
    "sg:province":"NY",
    "sg:tags":[
        "art",
        "painting",
        "gallery",
        "dealer"
    ],
    "wof:name":"Smithy-Pioneer Gallery Inc",
    "wof:placetype":"venue"
},
  "geometry": {"coordinates":[-74.92450700000001,42.699593],"type":"Point"}
}