{
  "type": "Feature",
  "properties": {
    "addr:full":"12 Duncan Ln Huntington NY 11743",
    "addr:housenumber":"12",
    "addr:postcode":"11743",
    "addr:street":"Duncan Ln",
    "iso:country":"US",
    "sg:address":"12 Duncan Ln",
    "sg:city":"Huntington",
    "sg:classifiers":[
        {
            "category":"Insurance",
            "subcategory":"Life Insurance",
            "type":"Services"
        }
    ],
    "sg:phone":"+1 631 424 3475",
    "sg:postcode":"11743",
    "sg:province":"NY",
    "sg:tags":[
        "carrier"
    ],
    "wof:name":"Great Life Lawnscape",
    "wof:placetype":"venue"
},
  "geometry": {"coordinates":[-73.408946,40.888053],"type":"Point"}
}