{
  "type": "Feature",
  "properties": {
    "iso:country":"US",
    "sg:address":"24 Kelsey Rd",
    "sg:city":"Poughkeepsie",
    "sg:classifiers":[
        {
            "category":"Building & Trades",
            "subcategory":"Construction",
            "type":"Services"
        }
    ],
    "sg:phone":"+1 845 471 0275",
    "sg:postcode":"12601",
    "sg:province":"NY",
    "sg:tags":[
        "residential",
        "general",
        "commercial",
        "contractor"
    ],
    "wof:name":"J A M Builders",
    "wof:placetype":"venue"
},
  "geometry": {"coordinates":[-73.91870299999999,41.715827],"type":"Point"}
}