{
  "type": "Feature",
  "properties": {
    "addr:full":"64 Lafayette Ave Ste B Brooklyn NY 11217",
    "addr:housenumber":"64",
    "addr:postcode":"11217",
    "addr:street":"Lafayette Ave Ste B",
    "iso:country":"US",
    "sg:address":"64 Lafayette Ave Ste B",
    "sg:city":"Brooklyn",
    "sg:classifiers":[
        {
            "category":"Shopping",
            "subcategory":"Bicycles & Sporting Goods",
            "type":"Retail Goods"
        },
        {
            "category":"Sports & Exercise",
            "subcategory":"Bicycle Rental",
            "type":"Entertainment"
        },
        {
            "category":"Parking",
            "subcategory":"Bicycle",
            "type":"Transportation"
        }
    ],
    "sg:phone":"+1 718 643 6798",
    "sg:postcode":"11217",
    "sg:province":"NY",
    "sg:tags":[
        "shop",
        "system",
        "bicycles-repair",
        "bike",
        "security",
        "rack",
        "bicycles-renting"
    ],
    "wof:name":"Bespoke Bicycles Incorporated",
    "wof:placetype":"venue"
},
  "geometry": {"coordinates":[-73.975455,40.686964],"type":"Point"}
}