{
  "type": "Feature",
  "properties": {
    "iso:country":"US",
    "sg:address":"2 Hillside Pl",
    "sg:city":"Ilion",
    "sg:classifiers":[
        {
            "category":"Building & Trades",
            "subcategory":"Plumbing",
            "type":"Services"
        },
        {
            "category":"Building & Trades",
            "subcategory":"Construction",
            "type":"Services"
        },
        {
            "category":"Building & Trades",
            "subcategory":"Electrical",
            "type":"Services"
        }
    ],
    "sg:phone":"+1 315 219 7970",
    "sg:postcode":"13357",
    "sg:province":"NY",
    "sg:tags":[
        "roofing",
        "plumber",
        "industrial",
        "electric",
        "contractor",
        "contractors-commercial",
        "clean",
        "boilers-repair"
    ],
    "wof:name":"bowman electric/plumbing/heating",
    "wof:placetype":"venue"
},
  "geometry": {"coordinates":[-75.04203800000001,43.011669],"type":"Point"}
}