{
  "type": "Feature",
  "properties": {
    "addr:full":"15 Bridge St Carthage NY 13619",
    "addr:housenumber":"15",
    "addr:postcode":"13619",
    "addr:street":"Bridge St",
    "iso:country":"US",
    "sg:address":"15 Bridge St",
    "sg:city":"Carthage",
    "sg:classifiers":[
        {
            "category":"Bars & Pubs",
            "type":"Food & Drink"
        }
    ],
    "sg:phone":"+1   ",
    "sg:postcode":"13619",
    "sg:province":"NY",
    "sg:tags":[
        "drinking",
        "eating"
    ],
    "wof:name":"Keddys Bar",
    "wof:placetype":"venue"
},
  "geometry": {"coordinates":[-75.61545599999999,43.973767],"type":"Point"}
}