{
  "type": "Feature",
  "properties": {
    "addr:full":"185 Day Hollow Rd Owego NY 13827",
    "addr:housenumber":"185",
    "addr:postcode":"13827",
    "addr:street":"Day Hollow Rd",
    "iso:country":"US",
    "sg:address":"185 Day Hollow Rd",
    "sg:city":"Owego",
    "sg:classifiers":[
        {
            "category":"Place Of Worship",
            "subcategory":"Church",
            "type":"Public Place"
        },
        {
            "category":"Place Of Worship",
            "type":"Public Place"
        }
    ],
    "sg:phone":"+1 607 687 3261",
    "sg:postcode":"13827",
    "sg:province":"NY",
    "sg:tags":[
        "churches-interdenominational",
        "churches-various",
        "denomination"
    ],
    "wof:name":"Lakeview Chapel Of The Christian & Missionary Alliance",
    "wof:placetype":"venue"
},
  "geometry": {"coordinates":[-76.218777,42.095942],"type":"Point"}
}