{
  "type": "Feature",
  "properties": {
    "addr:full":"37 Brandywine St Binghamton NY 13901",
    "addr:housenumber":"37",
    "addr:postcode":"13901",
    "addr:street":"Brandywine St",
    "iso:country":"US",
    "sg:address":"37 Brandywine St",
    "sg:city":"Binghamton",
    "sg:classifiers":[
        {
            "category":"Shopping",
            "type":"Retail Goods"
        }
    ],
    "sg:phone":"+1   ",
    "sg:postcode":"13901",
    "sg:province":"NY",
    "sg:tags":[
        "merchandise"
    ],
    "wof:name":"Ecklund Systems For Business",
    "wof:placetype":"venue"
},
  "geometry": {"coordinates":[-75.899221,42.111429],"type":"Point"}
}