{
  "type": "Feature",
  "properties": {
    "addr:full":"177 Fort Washington Ave New York NY 10032",
    "addr:housenumber":"177",
    "addr:postcode":"10032",
    "addr:street":"Fort Washington Ave",
    "iso:country":"US",
    "sg:address":"177 Fort Washington Ave",
    "sg:city":"New York",
    "sg:classifiers":[
        {
            "category":"Health Services",
            "subcategory":"Doctor",
            "type":"Services"
        }
    ],
    "sg:phone":"+1 212 305 9875",
    "sg:postcode":"10032",
    "sg:province":"NY",
    "sg:tags":[
        "physician",
        "surgeon"
    ],
    "wof:name":"Columbia Presybyterian",
    "wof:placetype":"venue"
},
  "geometry": {"coordinates":[-73.942637,40.841232],"type":"Point"}
}