{
  "type": "Feature",
  "properties": {
    "addr:full":"316 Columbus Ave New York NY 10023",
    "addr:housenumber":"316",
    "addr:postcode":"10023",
    "addr:street":"Columbus Ave",
    "iso:country":"US",
    "sg:address":"316 Columbus Ave",
    "sg:city":"New York",
    "sg:classifiers":[
        {
            "category":"Restaurant",
            "type":"Food & Drink"
        }
    ],
    "sg:menulink":"http://www.allmenus.com/ny/new-york/7003-pappardella/menu/",
    "sg:phone":"+1 212 595 7996",
    "sg:postcode":"10023",
    "sg:province":"NY",
    "sg:tags":[
        "italian"
    ],
    "wof:name":"Pappardella",
    "wof:placetype":"venue"
},
  "geometry": {"coordinates":[-73.977424,40.779287],"type":"Point"}
}