{
  "type": "Feature",
  "properties": {
    "iso:country":"US",
    "sg:address":"445 Park Ave",
    "sg:city":"New York",
    "sg:classifiers":[
        {
            "category":"Food & Beverages",
            "subcategory":"Groceries & Convenience Stores",
            "type":"Retail Goods"
        }
    ],
    "sg:phone":"+1 212 829 4340",
    "sg:postcode":"10022",
    "sg:province":"NY",
    "sg:tags":[
        "market"
    ],
    "wof:name":"Markets Corp",
    "wof:placetype":"venue"
},
  "geometry": {"coordinates":[-73.970809,40.761349],"type":"Point"}
}