{
  "type": "Feature",
  "properties": {
    "addr:full":"107 E 88 St New York NY 10128",
    "addr:housenumber":"107;88",
    "addr:postcode":"10128",
    "addr:street":"E;St",
    "iso:country":"US",
    "sg:address":"107 E 88 St",
    "sg:city":"New York",
    "sg:classifiers":[
        {
            "category":"Organizations",
            "subcategory":"Religious Organization",
            "type":"Services"
        }
    ],
    "sg:phone":"+1 212 534 5704",
    "sg:postcode":"10128",
    "sg:province":"NY",
    "sg:tags":[
        "clergy"
    ],
    "wof:name":"Rudolf Kiviranna",
    "wof:placetype":"venue"
},
  "geometry": {"coordinates":[-73.954769,40.780963],"type":"Point"}
}