{
  "type": "Feature",
  "properties": {
    "addr:full":"116 W 62 St New York NY 10023",
    "addr:housenumber":"116",
    "addr:postcode":"10023",
    "addr:street":"W 62 St",
    "iso:country":"US",
    "sg:address":"116 W 62 St",
    "sg:city":"New York",
    "sg:classifiers":[
        {
            "category":"Professional",
            "type":"Services"
        }
    ],
    "sg:phone":"+1 212 753 8041",
    "sg:postcode":"10023",
    "sg:province":"NY",
    "sg:tags":[
        "establishment"
    ],
    "wof:name":"Cogedipresse Inc",
    "wof:placetype":"venue"
},
  "geometry": {"coordinates":[-73.98593200000001,40.772044],"type":"Point"}
}