{
  "type": "Feature",
  "properties": {
    "iso:country":"US",
    "sg:address":"4487 Lake Ave",
    "sg:city":"Lockport",
    "sg:classifiers":[
        {
            "category":"Professional",
            "type":"Services"
        }
    ],
    "sg:phone":"+1 716 478 0271",
    "sg:postcode":"14094",
    "sg:province":"NY",
    "sg:tags":[
        "establishment"
    ],
    "wof:name":"Agro Fresh",
    "wof:placetype":"venue"
},
  "geometry": {"coordinates":[-78.67613299999999,43.188741],"type":"Point"}
}