{
  "type": "Feature",
  "properties": {
    "addr:full":"90 E 42nd St New York NY 10017",
    "addr:housenumber":"90",
    "addr:postcode":"10017",
    "addr:street":"E 42Nd St",
    "iso:country":"US",
    "sg:address":"90 E 42nd St",
    "sg:city":"New York",
    "sg:classifiers":[
        {
            "category":"Restaurant",
            "type":"Food & Drink"
        }
    ],
    "sg:phone":"+1 212 286 9600",
    "sg:postcode":"10017",
    "sg:province":"NY",
    "sg:tags":[
        "traditional",
        "american",
        "brunch",
        "breakfast"
    ],
    "sg:website":"www.pershingsquare.com",
    "wof:name":"Pershing Square",
    "wof:placetype":"venue"
},
  "geometry": {"coordinates":[-73.97788799999999,40.752218],"type":"Point"}
}