{
  "type": "Feature",
  "properties": {
    "iso:country":"US",
    "sg:address":"213 W 35 St",
    "sg:city":"New York",
    "sg:classifiers":[
        {
            "category":"Utilities",
            "subcategory":"Telephone",
            "type":"Services"
        }
    ],
    "sg:phone":"+1   ",
    "sg:postcode":"10001",
    "sg:province":"NY",
    "sg:tags":[
        "whole",
        "woman",
        "clothing",
        "man"
    ],
    "wof:name":"Lotlesscom Inc",
    "wof:placetype":"venue"
},
  "geometry": {"coordinates":[-73.992678,40.752773],"type":"Point"}
}