{
  "type": "Feature",
  "properties": {
    "addr:full":"6040 Sheridan Dr Buffalo NY 14221",
    "addr:housenumber":"6040",
    "addr:postcode":"14221",
    "addr:street":"Sheridan Dr",
    "iso:country":"US",
    "sg:address":"6040 Sheridan Dr",
    "sg:city":"Buffalo",
    "sg:classifiers":[
        {
            "category":"Personal",
            "subcategory":"Beauty Salon",
            "type":"Services"
        }
    ],
    "sg:phone":"+1 716 631 3988",
    "sg:postcode":"14221",
    "sg:province":"NY",
    "sg:website":"www.heavensalon.com",
    "wof:name":"Heaven Salon & Night Spa",
    "wof:placetype":"venue"
},
  "geometry": {"coordinates":[-78.70560500000001,42.978105],"type":"Point"}
}