{
  "type": "Feature",
  "properties": {
    "iso:country":"US",
    "sg:address":"336 Northrup Ave",
    "sg:city":"Mamaroneck",
    "sg:classifiers":[
        {
            "category":"Building & Trades",
            "subcategory":"Construction",
            "type":"Services"
        }
    ],
    "sg:phone":"+1 914 698 5060",
    "sg:postcode":"10543",
    "sg:province":"NY",
    "sg:tags":[
        "driveway",
        "sealcoating",
        "paving",
        "asphalt",
        "contractor"
    ],
    "wof:name":"Bilt Rite Driveway Corp",
    "wof:placetype":"venue"
},
  "geometry": {"coordinates":[-73.743751,40.952354],"type":"Point"}
}