{
  "type": "Feature",
  "properties": {
    "addr:full":"416 Elmira Rd Ithaca NY 14850",
    "addr:housenumber":"416",
    "addr:postcode":"14850",
    "addr:street":"Elmira Rd",
    "iso:country":"US",
    "sg:address":"416 Elmira Rd",
    "sg:city":"Ithaca",
    "sg:classifiers":[
        {
            "category":"Government",
            "subcategory":"Office",
            "type":"Public Place"
        }
    ],
    "sg:phone":"+1 607 277 1593",
    "sg:postcode":"14850",
    "sg:province":"NY",
    "sg:tags":[
        "state",
        "resource"
    ],
    "sg:website":"www.wcb.state.ny.us",
    "wof:name":"Workers' Compensation Board",
    "wof:placetype":"venue"
},
  "geometry": {"coordinates":[-76.52322599999999,42.417786],"type":"Point"}
}