{
  "type": "Feature",
  "properties": {
    "addr:full":"264 Bushwick Ave Brooklyn NY 11206",
    "addr:housenumber":"264",
    "addr:postcode":"11206",
    "addr:street":"Bushwick Ave",
    "iso:country":"US",
    "sg:address":"264 Bushwick Ave",
    "sg:city":"Brooklyn",
    "sg:classifiers":[
        {
            "category":"Retail",
            "subcategory":"Funeral Services",
            "type":"Services"
        }
    ],
    "sg:phone":"+1   ",
    "sg:postcode":"11206",
    "sg:province":"NY",
    "sg:tags":[
        "home"
    ],
    "wof:name":"Funeral Directors",
    "wof:placetype":"venue"
},
  "geometry": {"coordinates":[-73.939875,40.707583],"type":"Point"}
}