{
  "type": "Feature",
  "properties": {
    "addr:full":"12390 State Hwy 39 Sardinia NY 14134",
    "addr:housenumber":"12390",
    "addr:postcode":"14134",
    "addr:street":"State Hwy 39",
    "iso:country":"US",
    "sg:address":"12390 State Hwy 39",
    "sg:city":"Sardinia",
    "sg:classifiers":[
        {
            "category":"Building & Trades",
            "subcategory":"Construction",
            "type":"Services"
        }
    ],
    "sg:phone":"+1 716 496 7526",
    "sg:postcode":"14134",
    "sg:province":"NY",
    "sg:tags":[
        "marking",
        "maintenance",
        "parking"
    ],
    "wof:name":"Sardinia Town Highway Dept",
    "wof:placetype":"venue"
},
  "geometry": {"coordinates":[-78.528339,42.526472],"type":"Point"}
}