{
  "type": "Feature",
  "properties": {
    "iso:country":"US",
    "sg:address":"1040 Park Pl",
    "sg:city":"Brooklyn",
    "sg:classifiers":[
        {
            "category":"Manufacturing",
            "subcategory":"Printing",
            "type":"Manufacturing & Wholesale Goods"
        }
    ],
    "sg:phone":"+1   ",
    "sg:postcode":"11213",
    "sg:province":"NY",
    "sg:tags":[
        "periodical"
    ],
    "wof:name":"Attitude Dancer S Monthly",
    "wof:placetype":"venue"
},
  "geometry": {"coordinates":[-73.94305799999999,40.67298],"type":"Point"}
}