{
  "type": "Feature",
  "properties": {
    "iso:country":"US",
    "sg:address":"966 Oaks Dr",
    "sg:city":"Franklin Square",
    "sg:classifiers":[
        {
            "category":"Farming",
            "subcategory":"Livestock Farm",
            "type":"Manufacturing & Wholesale Goods"
        }
    ],
    "sg:phone":"+1 516 352 6230",
    "sg:postcode":"11010",
    "sg:province":"NY",
    "sg:tags":[
        "specialty",
        "animal"
    ],
    "wof:name":"Empire Short Faced Tumble",
    "wof:placetype":"venue"
},
  "geometry": {"coordinates":[-73.678011,40.694503],"type":"Point"}
}