{
  "type": "Feature",
  "properties": {
    "iso:country":"US",
    "sg:address":"111 W 116th St",
    "sg:city":"New York",
    "sg:classifiers":[
        {
            "category":"Shopping",
            "subcategory":"Shoes",
            "type":"Retail Goods"
        }
    ],
    "sg:phone":"+1 212 316 9480",
    "sg:postcode":"10026",
    "sg:province":"NY",
    "sg:tags":[
        "store"
    ],
    "wof:name":"TC 116 06 Corporation",
    "wof:placetype":"venue"
},
  "geometry": {"coordinates":[-73.950121,40.80237],"type":"Point"}
}