{
  "type": "Feature",
  "properties": {
    "addr:full":"224 E 87th St New York NY 10128",
    "addr:housenumber":"224",
    "addr:postcode":"10128",
    "addr:street":"E 87Th St",
    "iso:country":"US",
    "sg:address":"224 E 87th St",
    "sg:city":"New York",
    "sg:classifiers":[
        {
            "category":"Building & Trades",
            "subcategory":"Construction",
            "type":"Services"
        },
        {
            "category":"Building & Trades",
            "subcategory":"Locksmith",
            "type":"Services"
        }
    ],
    "sg:phone":"+1 212 799 9490",
    "sg:postcode":"10128",
    "sg:province":"NY",
    "sg:tags":[
        "key",
        "painter"
    ],
    "wof:name":"Prompt Locksmith",
    "wof:placetype":"venue"
},
  "geometry": {"coordinates":[-73.952904,40.779099],"type":"Point"}
}