{
  "type": "Feature",
  "properties": {
    "iso:country":"US",
    "sg:address":"2375 86th St",
    "sg:city":"Brooklyn",
    "sg:classifiers":[
        {
            "category":"Home & Garden",
            "subcategory":"Hardware",
            "type":"Retail Goods"
        }
    ],
    "sg:phone":"+1   ",
    "sg:postcode":"11214",
    "sg:province":"NY",
    "wof:name":"Watson Elec Plbg & Hdwr Su",
    "wof:placetype":"venue"
},
  "geometry": {"coordinates":[-73.98957799999999,40.599494],"type":"Point"}
}