{
  "type": "Feature",
  "properties": {
    "addr:full":"2612 Broadway New York NY 10025",
    "addr:housenumber":"2612",
    "addr:postcode":"10025",
    "addr:street":"Broadway",
    "iso:country":"US",
    "sg:address":"2612 Broadway",
    "sg:city":"New York",
    "sg:classifiers":[
        {
            "category":"Real Estate",
            "subcategory":"Real Estate Agent",
            "type":"Services"
        }
    ],
    "sg:phone":"+1 212 689 6900",
    "sg:postcode":"10025",
    "sg:province":"NY",
    "wof:name":"Marion Inc",
    "wof:placetype":"venue"
},
  "geometry": {"coordinates":[-73.97054300000001,40.79614],"type":"Point"}
}