{
  "type": "Feature",
  "properties": {
    "iso:country":"US",
    "sg:address":"3 William St",
    "sg:city":"Yaphank",
    "sg:classifiers":[
        {
            "category":"Building & Trades",
            "subcategory":"Construction",
            "type":"Services"
        }
    ],
    "sg:phone":"+1 631 924 3715",
    "sg:postcode":"11949",
    "sg:province":"NY",
    "sg:tags":[
        "home",
        "improvement"
    ],
    "wof:name":"D & L Bathroom Remodeling",
    "wof:placetype":"venue"
},
  "geometry": {"coordinates":[-72.803444,40.851487],"type":"Point"}
}