{
  "type": "Feature",
  "properties": {
    "addr:full":"18 E Cayuga St Oswego NY 13126",
    "addr:housenumber":"18",
    "addr:postcode":"13126",
    "addr:street":"E Cayuga St",
    "iso:country":"US",
    "sg:address":"18 E Cayuga St",
    "sg:city":"Oswego",
    "sg:classifiers":[
        {
            "category":"Social Services",
            "type":"Services"
        }
    ],
    "sg:phone":"+1 315 342 1544",
    "sg:postcode":"13126",
    "sg:province":"NY",
    "sg:tags":[
        "individual",
        "family"
    ],
    "wof:name":"Services To Aid Families",
    "wof:placetype":"venue"
},
  "geometry": {"coordinates":[-76.50800099999999,43.458914],"type":"Point"}
}