{
  "type": "Feature",
  "properties": {
    "addr:full":"1260 Franklin Ave Bronx NY 10456",
    "addr:housenumber":"1260",
    "addr:postcode":"10456",
    "addr:street":"Franklin Ave",
    "iso:country":"US",
    "sg:address":"1260 Franklin Ave",
    "sg:city":"Bronx",
    "sg:classifiers":[
        {
            "category":"Education",
            "subcategory":"School",
            "type":"Public Place"
        }
    ],
    "sg:phone":"+1 718 589 3058",
    "sg:postcode":"10456",
    "sg:province":"NY",
    "wof:name":"Bronx Elementary School 63",
    "wof:placetype":"venue"
},
  "geometry": {"coordinates":[-73.90184000000001,40.831635],"type":"Point"}
}