{
  "type": "Feature",
  "properties": {
    "addr:full":"7600 Jericho Tpke Woodbury NY 11797",
    "addr:housenumber":"7600",
    "addr:postcode":"11797",
    "addr:street":"Jericho Tpke",
    "iso:country":"US",
    "sg:address":"7600 Jericho Tpke",
    "sg:city":"Woodbury",
    "sg:classifiers":[
        {
            "category":"Professional",
            "subcategory":"Employment Agencies",
            "type":"Services"
        }
    ],
    "sg:phone":"+1 516 364 1460",
    "sg:postcode":"11797",
    "sg:province":"NY",
    "wof:name":"PCA",
    "wof:placetype":"venue"
},
  "geometry": {"coordinates":[-73.488069,40.812408],"type":"Point"}
}