{
  "type": "Feature",
  "properties": {
    "addr:full":"170 Forest Ave Glen Cove NY 11542",
    "addr:housenumber":"170",
    "addr:postcode":"11542",
    "addr:street":"Forest Ave",
    "iso:country":"US",
    "sg:address":"170 Forest Ave",
    "sg:city":"Glen Cove",
    "sg:classifiers":[
        {
            "category":"Home & Garden",
            "subcategory":"Building Materials",
            "type":"Retail Goods"
        }
    ],
    "sg:phone":"+1 516 671 6598",
    "sg:postcode":"11542",
    "sg:province":"NY",
    "sg:tags":[
        "wallpaper"
    ],
    "wof:name":"Aboff's Paints & Wallcoverings",
    "wof:placetype":"venue"
},
  "geometry": {"coordinates":[-73.61454999999999,40.874784],"type":"Point"}
}