{
  "type": "Feature",
  "properties": {
    "addr:full":"450 Park Ave New York NY 10022",
    "addr:housenumber":"450",
    "addr:postcode":"10022",
    "addr:street":"Park Ave",
    "iso:country":"US",
    "sg:address":"450 Park Ave",
    "sg:city":"New York",
    "sg:classifiers":[
        {
            "category":"Professional",
            "subcategory":"Management & Consulting",
            "type":"Services"
        }
    ],
    "sg:phone":"+1 212 688 8534",
    "sg:postcode":"10022",
    "sg:province":"NY",
    "sg:tags":[
        "fuel"
    ],
    "wof:name":"Normandy Asset Management",
    "wof:placetype":"venue"
},
  "geometry": {"coordinates":[-73.971121,40.761096],"type":"Point"}
}