{
  "type": "Feature",
  "properties": {
    "addr:full":"10259 Jamaica Ave Richmond Hill NY 11418",
    "addr:housenumber":"10259",
    "addr:postcode":"11418",
    "addr:street":"Jamaica Ave",
    "iso:country":"US",
    "sg:address":"10259 Jamaica Ave",
    "sg:city":"Richmond Hill",
    "sg:classifiers":[
        {
            "category":"Restaurant",
            "type":"Food & Drink"
        }
    ],
    "sg:menulink":"http://www.allmenus.com/ny/queens/52590-hong-kong-chinese-restaurant/menu/",
    "sg:phone":"+1 718 846 3300",
    "sg:postcode":"11418",
    "sg:province":"NY",
    "sg:tags":[
        "asian",
        "chinese"
    ],
    "wof:name":"Hong Kong Chinese Restaurant",
    "wof:placetype":"venue"
},
  "geometry": {"coordinates":[-73.84342100000001,40.695189],"type":"Point"}
}