{
  "type": "Feature",
  "properties": {
    "iso:country":"US",
    "sg:address":"120 E Washington St",
    "sg:city":"Syracuse",
    "sg:classifiers":[
        {
            "category":"Health Services",
            "subcategory":"Podiatrist",
            "type":"Services"
        }
    ],
    "sg:phone":"+1 315 422 0453",
    "sg:postcode":"13210",
    "sg:province":"NY",
    "wof:name":"Levy & Levy",
    "wof:placetype":"venue"
},
  "geometry": {"coordinates":[-76.150796,43.049478],"type":"Point"}
}