{
  "type": "Feature",
  "properties": {
    "addr:full":"132 Sunset Rd Blauvelt NY 10913",
    "addr:housenumber":"132",
    "addr:postcode":"10913",
    "addr:street":"Sunset Rd",
    "iso:country":"US",
    "sg:address":"132 Sunset Rd",
    "sg:city":"Blauvelt",
    "sg:classifiers":[
        {
            "category":"Building & Trades",
            "subcategory":"Construction",
            "type":"Services"
        }
    ],
    "sg:phone":"+1 845 359 3158",
    "sg:postcode":"10913",
    "sg:province":"NY",
    "sg:tags":[
        "excavating",
        "contractor"
    ],
    "wof:name":"ONeill Trenchwork & Excvtg",
    "wof:placetype":"venue"
},
  "geometry": {"coordinates":[-73.970308,41.068464],"type":"Point"}
}