{
  "type": "Feature",
  "properties": {
    "iso:country":"US",
    "sg:address":"36 Harriet Pl",
    "sg:city":"Lynbrook",
    "sg:classifiers":[
        {
            "category":"Building & Trades",
            "subcategory":"Electrical",
            "type":"Services"
        }
    ],
    "sg:phone":"+1 516 887 1000",
    "sg:postcode":"11563",
    "sg:province":"NY",
    "sg:tags":[
        "fire",
        "burglar",
        "alarm",
        "installation",
        "central"
    ],
    "wof:name":"Allied Central Station Alarms",
    "wof:placetype":"venue"
},
  "geometry": {"coordinates":[-73.66427400000001,40.657099],"type":"Point"}
}