{
  "type": "Feature",
  "properties": {
    "addr:full":"74 Grand Ave Massapequa NY 11758",
    "addr:housenumber":"74",
    "addr:postcode":"11758",
    "addr:street":"Grand Ave",
    "iso:country":"US",
    "sg:address":"74 Grand Ave",
    "sg:city":"Massapequa",
    "sg:classifiers":[
        {
            "category":"Real Estate",
            "subcategory":"Real Estate Services",
            "type":"Services"
        }
    ],
    "sg:phone":"+1 516 799 8449",
    "sg:postcode":"11758",
    "sg:province":"NY",
    "sg:tags":[
        "abstract",
        "title"
    ],
    "wof:name":"Universal Settlement Services",
    "wof:placetype":"venue"
},
  "geometry": {"coordinates":[-73.474176,40.6776],"type":"Point"}
}