{
  "type": "Feature",
  "properties": {
    "addr:full":"1502 Reckson Plz Uniondale NY 11556",
    "addr:housenumber":"1502",
    "addr:postcode":"11556",
    "addr:street":"Reckson Plz",
    "iso:country":"US",
    "sg:address":"1502 Reckson Plz",
    "sg:city":"Uniondale",
    "sg:classifiers":[
        {
            "category":"Banks & Credit Unions",
            "subcategory":"Investment Brokerage",
            "type":"Services"
        }
    ],
    "sg:phone":"+1 516 227 6600",
    "sg:postcode":"11556",
    "sg:province":"NY",
    "sg:tags":[
        "consultant",
        "financing"
    ],
    "sg:website":"www.openlinkfinancial.com",
    "wof:name":"Open Link Financial Inc",
    "wof:placetype":"venue"
},
  "geometry": {"coordinates":[-73.586816,40.720127],"type":"Point"}
}