{
  "type": "Feature",
  "properties": {
    "addr:full":"2543 E Tremont Ave Bronx NY 10461",
    "addr:housenumber":"2543",
    "addr:postcode":"10461",
    "addr:street":"E Tremont Ave",
    "iso:country":"US",
    "sg:address":"2543 E Tremont Ave",
    "sg:city":"Bronx",
    "sg:classifiers":[
        {
            "category":"Autos & Motor Vehicles",
            "subcategory":"Automobile Sales",
            "type":"Retail Goods"
        }
    ],
    "sg:phone":"+1 718 823 6000",
    "sg:postcode":"10461",
    "sg:province":"NY",
    "sg:tags":[
        "car"
    ],
    "wof:name":"Bronx Hyundai Sales",
    "wof:placetype":"venue"
},
  "geometry": {"coordinates":[-73.84929700000001,40.8428],"type":"Point"}
}