{
  "type": "Feature",
  "properties": {
    "iso:country":"US",
    "sg:address":"4893 W Main St",
    "sg:city":"Fredonia",
    "sg:classifiers":[
        {
            "category":"Retail",
            "subcategory":"Animal Services",
            "type":"Services"
        }
    ],
    "sg:phone":"+1 716 672 8882",
    "sg:postcode":"14063",
    "sg:province":"NY",
    "wof:name":"Fredonia Pet Parlor",
    "wof:placetype":"venue"
},
  "geometry": {"coordinates":[-79.378491,42.419081],"type":"Point"}
}