{
  "type": "Feature",
  "properties": {
    "addr:full":"854 State Hwy 13 Cortland NY 13045",
    "addr:housenumber":"854",
    "addr:postcode":"13045",
    "addr:street":"State Hwy 13",
    "iso:country":"US",
    "sg:address":"854 State Hwy 13",
    "sg:city":"Cortland",
    "sg:classifiers":[
        {
            "category":"Wholesale",
            "subcategory":"Apparel",
            "type":"Manufacturing & Wholesale Goods"
        }
    ],
    "sg:phone":"+1 607 756 2052",
    "sg:postcode":"13045",
    "sg:province":"NY",
    "sg:tags":[
        "sportswear"
    ],
    "wof:name":"Olympia Sport",
    "wof:placetype":"venue"
},
  "geometry": {"coordinates":[-76.22148799999999,42.566018],"type":"Point"}
}