{
  "type": "Feature",
  "properties": {
    "addr:full":"143 N Toll St Schenectady NY 12302",
    "addr:housenumber":"143",
    "addr:postcode":"12302",
    "addr:street":"N Toll St",
    "iso:country":"US",
    "sg:address":"143 N Toll St",
    "sg:city":"Schenectady",
    "sg:classifiers":[
        {
            "category":"Professional",
            "subcategory":"Computer Services",
            "type":"Services"
        }
    ],
    "sg:phone":"+1   ",
    "sg:postcode":"12302",
    "sg:province":"NY",
    "wof:name":"M & P Computers",
    "wof:placetype":"venue"
},
  "geometry": {"coordinates":[-73.97070100000001,42.833983],"type":"Point"}
}