{
  "type": "Feature",
  "properties": {
    "iso:country":"US",
    "sg:address":"5566 Armor Rd",
    "sg:city":"Orchard Park",
    "sg:classifiers":[
        {
            "category":"Health Services",
            "subcategory":"Doctor",
            "type":"Services"
        }
    ],
    "sg:phone":"+1   ",
    "sg:postcode":"14127",
    "sg:province":"NY",
    "wof:name":"Ronald T Tedesco DDS PC",
    "wof:placetype":"venue"
},
  "geometry": {"coordinates":[-78.775756,42.746406],"type":"Point"}
}