{
  "type": "Feature",
  "properties": {
    "addr:full":"4564 Bronx Blvd Bronx NY 10470",
    "addr:housenumber":"4564",
    "addr:postcode":"10470",
    "addr:street":"Bronx Blvd",
    "iso:country":"US",
    "sg:address":"4564 Bronx Blvd",
    "sg:city":"Bronx",
    "sg:classifiers":[
        {
            "category":"Professional",
            "subcategory":"Accounting & Tax Preparation",
            "type":"Services"
        }
    ],
    "sg:phone":"+1 718 653 3826",
    "sg:postcode":"10470",
    "sg:province":"NY",
    "sg:tags":[
        "bookkeeping",
        "general"
    ],
    "wof:name":"Fitz Beaumont Accountant",
    "wof:placetype":"venue"
},
  "geometry": {"coordinates":[-73.85554999999999,40.902209],"type":"Point"}
}