{
  "type": "Feature",
  "properties": {
    "iso:country":"US",
    "sg:address":"1229 Broadway Ste 208",
    "sg:city":"Hewlett",
    "sg:classifiers":[
        {
            "category":"Health Services",
            "subcategory":"Doctor",
            "type":"Services"
        }
    ],
    "sg:phone":"+1 516 374 0011",
    "sg:postcode":"11557",
    "sg:province":"NY",
    "wof:name":"Vaysman Alexander MD",
    "wof:placetype":"venue"
},
  "geometry": {"coordinates":[-73.701947,40.637359],"type":"Point"}
}