{
  "type": "Feature",
  "properties": {
    "addr:full":"70 Virginia Rd White Plains NY 10603",
    "addr:housenumber":"70",
    "addr:postcode":"10603",
    "addr:street":"Virginia Rd",
    "iso:country":"US",
    "sg:address":"70 Virginia Rd",
    "sg:city":"White Plains",
    "sg:classifiers":[
        {
            "category":"Professional",
            "subcategory":"Management & Consulting",
            "type":"Services"
        }
    ],
    "sg:phone":"+1 914 686 5782",
    "sg:postcode":"10603",
    "sg:province":"NY",
    "wof:name":"Samson Management",
    "wof:placetype":"venue"
},
  "geometry": {"coordinates":[-73.774782,41.062794],"type":"Point"}
}