{
  "type": "Feature",
  "properties": {
    "addr:full":"2 Consulate Dr Apt 2C Tuckahoe NY 10707",
    "addr:housenumber":"2c",
    "addr:postcode":"10707",
    "addr:street":"Consulate Dr Apt",
    "iso:country":"US",
    "sg:address":"2 Consulate Dr Apt 2C",
    "sg:city":"Tuckahoe",
    "sg:classifiers":[
        {
            "category":"Professional",
            "subcategory":"Business Services",
            "type":"Services"
        }
    ],
    "sg:phone":"+1 914 961 7655",
    "sg:postcode":"10707",
    "sg:province":"NY",
    "sg:tags":[
        "consultant",
        "coach"
    ],
    "wof:name":"C Hopkins Consulting Inc",
    "wof:placetype":"venue"
},
  "geometry": {"coordinates":[-73.826109,40.953253],"type":"Point"}
}