{
  "type": "Feature",
  "properties": {
    "addr:full":"273 Hawkins Ave Ronkonkoma NY 11779",
    "addr:housenumber":"273",
    "addr:postcode":"11779",
    "addr:street":"Hawkins Ave",
    "iso:country":"US",
    "sg:address":"273 Hawkins Ave",
    "sg:city":"Ronkonkoma",
    "sg:classifiers":[
        {
            "category":"Real Estate",
            "subcategory":"Real Estate Agent",
            "type":"Services"
        }
    ],
    "sg:phone":"+1 631 737 0504",
    "sg:postcode":"11779",
    "sg:province":"NY",
    "wof:name":"Park Ridge Realty Associates",
    "wof:placetype":"venue"
},
  "geometry": {"coordinates":[-73.107755,40.818203],"type":"Point"}
}