{
  "type": "Feature",
  "properties": {
    "iso:country":"US",
    "sg:address":"6727 Amboy Rd",
    "sg:city":"Staten Island",
    "sg:classifiers":[
        {
            "category":"Building & Trades",
            "subcategory":"Pest Control",
            "type":"Services"
        }
    ],
    "sg:phone":"+1 718 966 1234",
    "sg:postcode":"10309",
    "sg:province":"NY",
    "wof:name":"Unlimited Pest Elimination",
    "wof:placetype":"venue"
},
  "geometry": {"coordinates":[-74.228661,40.519723],"type":"Point"}
}