{
  "type": "Feature",
  "properties": {
    "iso:country":"US",
    "sg:address":"2 University Pl",
    "sg:city":"Albany",
    "sg:classifiers":[
        {
            "category":"Government",
            "subcategory":"Office",
            "type":"Public Place"
        }
    ],
    "sg:phone":"+1 518 458 6731",
    "sg:postcode":"12203",
    "sg:province":"NY",
    "sg:tags":[
        "state",
        "program"
    ],
    "wof:name":"Public Water Supply Bureau",
    "wof:placetype":"venue"
},
  "geometry": {"coordinates":[-73.821028,42.678622],"type":"Point"}
}