{
  "type": "Feature",
  "properties": {
    "iso:country":"US",
    "sg:address":"222 Main St",
    "sg:city":"Saugerties",
    "sg:classifiers":[
        {
            "category":"Home & Garden",
            "subcategory":"Furniture",
            "type":"Retail Goods"
        }
    ],
    "sg:phone":"+1   ",
    "sg:postcode":"12477",
    "sg:province":"NY",
    "sg:tags":[
        "store"
    ],
    "wof:name":"Saugerties Furniture Mart",
    "wof:placetype":"venue"
},
  "geometry": {"coordinates":[-73.952772,42.077579],"type":"Point"}
}