{
  "type": "Feature",
  "properties": {
    "addr:full":"206 E 90 St New York NY 10128",
    "addr:housenumber":"206;90",
    "addr:postcode":"10128",
    "addr:street":"E;St",
    "iso:country":"US",
    "sg:address":"206 E 90 St",
    "sg:city":"New York",
    "sg:classifiers":[
        {
            "category":"Manufacturing",
            "subcategory":"Printing",
            "type":"Manufacturing & Wholesale Goods"
        }
    ],
    "sg:phone":"+1 646 307 4784",
    "sg:postcode":"10128",
    "sg:province":"NY",
    "sg:tags":[
        "cards",
        "business"
    ],
    "wof:name":"Macys Auto Club",
    "wof:placetype":"venue"
},
  "geometry": {"coordinates":[-73.95002100000001,40.780429],"type":"Point"}
}