{
  "type": "Feature",
  "properties": {
    "iso:country":"US",
    "sg:address":"47 Gleneida Ave",
    "sg:city":"Carmel",
    "sg:classifiers":[
        {
            "category":"Building & Trades",
            "subcategory":"Construction",
            "type":"Services"
        },
        {
            "category":"Real Estate",
            "subcategory":"Architect",
            "type":"Services"
        }
    ],
    "sg:phone":"+1 845 228 2333",
    "sg:postcode":"10512",
    "sg:province":"NY",
    "sg:tags":[
        "contractor"
    ],
    "wof:name":"Mission Arts Design Group Inc",
    "wof:placetype":"venue"
},
  "geometry": {"coordinates":[-73.67910000000001,41.426601],"type":"Point"}
}