{
  "type": "Feature",
  "properties": {
    "addr:full":"200 E 94th St New York NY 10128",
    "addr:housenumber":"200",
    "addr:postcode":"10128",
    "addr:street":"E 94Th St",
    "iso:country":"US",
    "sg:address":"200 E 94th St",
    "sg:city":"New York",
    "sg:classifiers":[
        {
            "category":"Professional",
            "subcategory":"Lawyer & Legal Services",
            "type":"Services"
        }
    ],
    "sg:phone":"+1 212 360 0006",
    "sg:postcode":"10128",
    "sg:province":"NY",
    "wof:name":"Suyon Yi",
    "wof:placetype":"venue"
},
  "geometry": {"coordinates":[-73.95034,40.783763],"type":"Point"}
}