{
  "type": "Feature",
  "properties": {
    "addr:full":"109 Wall St Schuylerville NY 12824",
    "addr:housenumber":"109",
    "addr:postcode":"12824",
    "addr:street":"Wall St",
    "iso:country":"US",
    "sg:address":"109 Wall St",
    "sg:city":"Schuylerville",
    "sg:classifiers":[
        {
            "category":"Professional",
            "type":"Services"
        }
    ],
    "sg:phone":"+1 518 584 3481",
    "sg:postcode":"12824",
    "sg:province":"NY",
    "sg:tags":[
        "establishment"
    ],
    "wof:name":"Northern Instrumentation",
    "wof:placetype":"venue"
},
  "geometry": {"coordinates":[-73.714483,43.512456],"type":"Point"}
}