{
  "type": "Feature",
  "properties": {
    "iso:country":"US",
    "sg:address":"138 Garrow St Exd",
    "sg:city":"Auburn",
    "sg:classifiers":[
        {
            "category":"Recreation",
            "type":"Entertainment"
        }
    ],
    "sg:phone":"+1 315 253 2916",
    "sg:postcode":"13021",
    "sg:province":"NY",
    "sg:tags":[
        "amusement"
    ],
    "wof:name":"Funtime Attractions",
    "wof:placetype":"venue"
},
  "geometry": {"coordinates":[-76.575845,42.914179],"type":"Point"}
}