{
  "type": "Feature",
  "properties": {
    "addr:full":"39 Windsor Ave Mineola NY 11501",
    "addr:housenumber":"39",
    "addr:postcode":"11501",
    "addr:street":"Windsor Ave",
    "iso:country":"US",
    "sg:address":"39 Windsor Ave",
    "sg:city":"Mineola",
    "sg:classifiers":[
        {
            "category":"Professional",
            "subcategory":"Management & Consulting",
            "type":"Services"
        }
    ],
    "sg:phone":"+1 516 746 1640",
    "sg:postcode":"11501",
    "sg:province":"NY",
    "sg:tags":[
        "coffee",
        "brewing",
        "devices"
    ],
    "wof:name":"Cory Ara Refreshment Svc",
    "wof:placetype":"venue"
},
  "geometry": {"coordinates":[-73.63452100000001,40.753032],"type":"Point"}
}