{
  "type": "Feature",
  "properties": {
    "addr:full":"320 Montauk Hwy Lindenhurst NY 11757",
    "addr:housenumber":"320",
    "addr:postcode":"11757",
    "addr:street":"Montauk Hwy",
    "iso:country":"US",
    "sg:address":"320 Montauk Hwy",
    "sg:city":"Lindenhurst",
    "sg:classifiers":[
        {
            "category":"Restaurant",
            "type":"Food & Drink"
        }
    ],
    "sg:menulink":"http://www.allmenus.com/ny/babylon/210515-kfc---kentucky-fried-chicken/menu/",
    "sg:phone":"+1 631 225 9482",
    "sg:postcode":"11757",
    "sg:province":"NY",
    "sg:tags":[
        "american",
        "chicken"
    ],
    "wof:name":"KFC - Kentucky Fried Chicken",
    "wof:placetype":"venue"
},
  "geometry": {"coordinates":[-73.370704,40.675483],"type":"Point"}
}