{
  "type": "Feature",
  "properties": {
    "addr:full":"7627 State Hwy 298 Kirkville NY 13082",
    "addr:housenumber":"7627",
    "addr:postcode":"13082",
    "addr:street":"State Hwy 298",
    "iso:country":"US",
    "sg:address":"7627 State Hwy 298",
    "sg:city":"Kirkville",
    "sg:classifiers":[
        {
            "category":"Shopping",
            "subcategory":"Bicycles & Sporting Goods",
            "type":"Retail Goods"
        }
    ],
    "sg:phone":"+1   ",
    "sg:postcode":"13082",
    "sg:province":"NY",
    "wof:name":"Cookies Bait & Tackle",
    "wof:placetype":"venue"
},
  "geometry": {"coordinates":[-75.976102,43.147202],"type":"Point"}
}