{
  "type": "Feature",
  "properties": {
    "addr:full":"1 Merriman St Rochester NY 14607",
    "addr:housenumber":"1",
    "addr:postcode":"14607",
    "addr:street":"Merriman St",
    "iso:country":"US",
    "sg:address":"1 Merriman St",
    "sg:city":"Rochester",
    "sg:classifiers":[
        {
            "category":"Utilities",
            "subcategory":"Telephone",
            "type":"Services"
        }
    ],
    "sg:phone":"+1   ",
    "sg:postcode":"14607",
    "sg:province":"NY",
    "sg:tags":[
        "communications"
    ],
    "wof:name":"AT&T",
    "wof:placetype":"venue"
},
  "geometry": {"coordinates":[-77.58234899999999,43.155117],"type":"Point"}
}