{
  "type": "Feature",
  "properties": {
    "iso:country":"US",
    "sg:address":"4233 Inverrary Dr",
    "sg:city":"Liverpool",
    "sg:classifiers":[
        {
            "category":"Professional",
            "subcategory":"Business Services",
            "type":"Services"
        }
    ],
    "sg:phone":"+1 315 652 1442",
    "sg:postcode":"13090",
    "sg:province":"NY",
    "sg:tags":[
        "interior",
        "consultant",
        "design",
        "decorator"
    ],
    "wof:name":"Dorothy's Window Decor",
    "wof:placetype":"venue"
},
  "geometry": {"coordinates":[-76.219787,43.162885],"type":"Point"}
}