{
  "type": "Feature",
  "properties": {
    "iso:country":"US",
    "sg:address":"10 Bay St",
    "sg:city":"Staten Island",
    "sg:classifiers":[
        {
            "category":"Professional",
            "type":"Services"
        }
    ],
    "sg:phone":"+1 718 720 0809",
    "sg:postcode":"10301",
    "sg:province":"NY",
    "sg:tags":[
        "establishment"
    ],
    "sg:website":"www.baystreetlanding.com",
    "wof:name":"BSL Owners Corp",
    "wof:placetype":"venue"
},
  "geometry": {"coordinates":[-74.075951,40.6414],"type":"Point"}
}