{
  "type": "Feature",
  "properties": {
    "addr:full":"124 Dell St Syracuse NY 13210",
    "addr:housenumber":"124",
    "addr:postcode":"13210",
    "addr:street":"Dell St",
    "iso:country":"US",
    "sg:address":"124 Dell St",
    "sg:city":"Syracuse",
    "sg:classifiers":[
        {
            "category":"Shopping",
            "subcategory":"Clothing, Apparel, & Fashions",
            "type":"Retail Goods"
        }
    ],
    "sg:phone":"+1 315 476 2884",
    "sg:postcode":"13210",
    "sg:province":"NY",
    "sg:tags":[
        "tailor"
    ],
    "wof:name":"Westcott Alterations",
    "wof:placetype":"venue"
},
  "geometry": {"coordinates":[-76.11949,43.041884],"type":"Point"}
}