{
  "type": "Feature",
  "properties": {
    "addr:full":"27 Brooklyn Ave Brooklyn NY 11216",
    "addr:housenumber":"27",
    "addr:postcode":"11216",
    "addr:street":"Brooklyn Ave",
    "iso:country":"US",
    "sg:address":"27 Brooklyn Ave",
    "sg:city":"Brooklyn",
    "sg:classifiers":[
        {
            "category":"Wholesale",
            "subcategory":"Electrical",
            "type":"Manufacturing & Wholesale Goods"
        }
    ],
    "sg:phone":"+1 718 522 3196",
    "sg:postcode":"11216",
    "sg:province":"NY",
    "sg:tags":[
        "radio"
    ],
    "wof:name":"A W Electronics Inc",
    "wof:placetype":"venue"
},
  "geometry": {"coordinates":[-73.94405999999999,40.678439],"type":"Point"}
}