{
  "type": "Feature",
  "properties": {
    "addr:full":"22 Research Way East Setauket NY 11733",
    "addr:housenumber":"22",
    "addr:postcode":"11733",
    "addr:street":"Research Way East",
    "iso:country":"US",
    "sg:address":"22 Research Way",
    "sg:city":"East Setauket",
    "sg:classifiers":[
        {
            "category":"Professional",
            "subcategory":"Advertising",
            "type":"Services"
        }
    ],
    "sg:phone":"+1   ",
    "sg:postcode":"11733",
    "sg:province":"NY",
    "sg:tags":[
        "travel",
        "agency"
    ],
    "wof:name":"Todd Travel Promotions",
    "wof:placetype":"venue"
},
  "geometry": {"coordinates":[-73.087433,40.905817],"type":"Point"}
}