{
  "type": "Feature",
  "properties": {
    "addr:full":"110 E End Ave New York NY 10028",
    "addr:housenumber":"110",
    "addr:postcode":"10028",
    "addr:street":"E End Ave",
    "iso:country":"US",
    "sg:address":"110 E End Ave",
    "sg:city":"New York",
    "sg:classifiers":[
        {
            "category":"Health Services",
            "subcategory":"Doctor",
            "type":"Services"
        }
    ],
    "sg:phone":"+1 212 288 6164",
    "sg:postcode":"10028",
    "sg:province":"NY",
    "sg:tags":[
        "physician",
        "surgeon"
    ],
    "wof:name":"Robert J Mitchell MD",
    "wof:placetype":"venue"
},
  "geometry": {"coordinates":[-73.945527,40.773938],"type":"Point"}
}