{
  "type": "Feature",
  "properties": {
    "iso:country":"US",
    "sg:address":"150 Rodney St",
    "sg:city":"Brooklyn",
    "sg:classifiers":[
        {
            "category":"Retail",
            "subcategory":"Funeral Services",
            "type":"Services"
        }
    ],
    "sg:phone":"+1   ",
    "sg:postcode":"11211",
    "sg:province":"NY",
    "wof:name":"Chevra Kadisha Dsatmar Inc",
    "wof:placetype":"venue"
},
  "geometry": {"coordinates":[-73.961207,40.704211],"type":"Point"}
}