{
  "type": "Feature",
  "properties": {
    "iso:country":"US",
    "sg:address":"11 Holly Hill Ln",
    "sg:city":"Katonah",
    "sg:classifiers":[
        {
            "category":"Health Services",
            "subcategory":"Doctor",
            "type":"Services"
        }
    ],
    "sg:phone":"+1 914 232 2498",
    "sg:postcode":"10536",
    "sg:province":"NY",
    "sg:tags":[
        "medical"
    ],
    "wof:name":"George Ferrigno Dr",
    "wof:placetype":"venue"
},
  "geometry": {"coordinates":[-73.63217,41.280695],"type":"Point"}
}