{
  "type": "Feature",
  "properties": {
    "iso:country":"US",
    "sg:address":"219 Sunnyside Rd",
    "sg:city":"Schenectady",
    "sg:classifiers":[
        {
            "category":"Shopping",
            "subcategory":"Bicycles & Sporting Goods",
            "type":"Retail Goods"
        }
    ],
    "sg:phone":"+1   ",
    "sg:postcode":"12302",
    "sg:province":"NY",
    "wof:name":"Joes Sport Shop",
    "wof:placetype":"venue"
},
  "geometry": {"coordinates":[-73.93230699999999,42.835032],"type":"Point"}
}