{
  "type": "Feature",
  "properties": {
    "addr:full":"529 Woodmere Blvd Woodmere NY 11598",
    "addr:housenumber":"529",
    "addr:postcode":"11598",
    "addr:street":"Woodmere Blvd",
    "iso:country":"US",
    "sg:address":"529 Woodmere Blvd",
    "sg:city":"Woodmere",
    "sg:classifiers":[
        {
            "category":"Autos & Motor Vehicles",
            "subcategory":"Auto Supplies",
            "type":"Retail Goods"
        }
    ],
    "sg:phone":"+1   ",
    "sg:postcode":"11598",
    "sg:province":"NY",
    "sg:tags":[
        "automotive",
        "product",
        "industrial"
    ],
    "wof:name":"Lr Abrasive Products Mfg Inc",
    "wof:placetype":"venue"
},
  "geometry": {"coordinates":[-73.721895,40.639136],"type":"Point"}
}