{
  "type": "Feature",
  "properties": {
    "addr:full":"747 3 Ave New York NY 10017",
    "addr:housenumber":"747",
    "addr:postcode":"10017",
    "addr:street":"3 Ave",
    "iso:country":"US",
    "sg:address":"747 3 Ave",
    "sg:city":"New York",
    "sg:classifiers":[
        {
            "category":"Communications",
            "subcategory":"News Services",
            "type":"Services"
        }
    ],
    "sg:phone":"+1 212 508 5460",
    "sg:postcode":"10017",
    "sg:province":"NY",
    "wof:name":"Kyodo News",
    "wof:placetype":"venue"
},
  "geometry": {"coordinates":[-73.974935,40.7501],"type":"Point"}
}