{
  "type": "Feature",
  "properties": {
    "iso:country":"US",
    "sg:address":"565 Hall Rd",
    "sg:city":"Jamestown",
    "sg:classifiers":[
        {
            "category":"Shopping",
            "subcategory":"Computers & Home Electronics",
            "type":"Retail Goods"
        }
    ],
    "sg:phone":"+1 716 569 3032",
    "sg:postcode":"14701",
    "sg:province":"NY",
    "sg:tags":[
        "equipment",
        "dealer"
    ],
    "wof:name":"Micro Systems Software",
    "wof:placetype":"venue"
},
  "geometry": {"coordinates":[-79.20600899999999,42.008639],"type":"Point"}
}