{
  "type": "Feature",
  "properties": {
    "addr:full":"132 Main St Nanuet NY 10954",
    "addr:housenumber":"132",
    "addr:postcode":"10954",
    "addr:street":"Main St",
    "iso:country":"US",
    "sg:address":"132 Main St",
    "sg:city":"Nanuet",
    "sg:phone":"+1 845 623 9600",
    "sg:postcode":"10954",
    "sg:province":"NY",
    "sg:website":"http://www.nanuethotel.com",
    "wof:name":"Nanuet Hotel & Restaurant",
    "wof:placetype":"venue"
},
  "geometry": {"coordinates":[-74.012783,41.092038],"type":"Point"}
}