{
  "type": "Feature",
  "properties": {
    "addr:full":"10422 Northern Boulevard Corona NY 11368",
    "addr:housenumber":"10422",
    "addr:postcode":"11368",
    "addr:street":"Northern Boulevard",
    "iso:country":"US",
    "sg:address":"10422 Northern Boulevard",
    "sg:city":"Corona",
    "sg:classifiers":[
        {
            "category":"Building & Trades",
            "subcategory":"Locksmith",
            "type":"Services"
        }
    ],
    "sg:phone":"+1 718 247 0409",
    "sg:postcode":"11368",
    "sg:province":"NY",
    "sg:tags":[
        "key"
    ],
    "wof:name":"ABC Locksmith 24 Hours",
    "wof:placetype":"venue"
},
  "geometry": {"coordinates":[-73.86385199999999,40.757607],"type":"Point"}
}