{
  "type": "Feature",
  "properties": {
    "iso:country":"US",
    "sg:address":"610 State Hwy 9b",
    "sg:city":"Champlain",
    "sg:classifiers":[
        {
            "category":"Building & Trades",
            "subcategory":"Construction",
            "type":"Services"
        }
    ],
    "sg:phone":"+1 518 298 4561",
    "sg:postcode":"12919",
    "sg:province":"NY",
    "sg:tags":[
        "house"
    ],
    "wof:name":"Gerri Trombley Construction",
    "wof:placetype":"venue"
},
  "geometry": {"coordinates":[-73.374098,44.956902],"type":"Point"}
}