{
  "type": "Feature",
  "properties": {
    "addr:full":"222 Tompkins Ave Brooklyn NY 11216",
    "addr:housenumber":"222",
    "addr:postcode":"11216",
    "addr:street":"Tompkins Ave",
    "iso:country":"US",
    "sg:address":"222 Tompkins Ave",
    "sg:city":"Brooklyn",
    "sg:classifiers":[
        {
            "category":"Organizations",
            "subcategory":"Religious Organization",
            "type":"Services"
        }
    ],
    "sg:phone":"+1 718 388 3900",
    "sg:postcode":"11216",
    "sg:province":"NY",
    "wof:name":"Mount Pisgah Baptist Church",
    "wof:placetype":"venue"
},
  "geometry": {"coordinates":[-73.94564099999999,40.692032],"type":"Point"}
}