{
  "type": "Feature",
  "properties": {
    "addr:full":"55 Clinton St New York NY 10002",
    "addr:housenumber":"55",
    "addr:postcode":"10002",
    "addr:street":"Clinton St",
    "iso:country":"US",
    "sg:address":"55 Clinton St",
    "sg:city":"New York",
    "sg:classifiers":[
        {
            "category":"Shopping",
            "subcategory":"Clothing, Apparel, & Fashions",
            "type":"Retail Goods"
        }
    ],
    "sg:phone":"+1 212 260 7591",
    "sg:postcode":"10002",
    "sg:province":"NY",
    "sg:tags":[
        "clothing",
        "women's"
    ],
    "sg:website":"www.tomscottnyc.com",
    "wof:name":"Tom Scott",
    "wof:placetype":"venue"
},
  "geometry": {"coordinates":[-73.985043,40.719696],"type":"Point"}
}