{
  "type": "Feature",
  "properties": {
    "addr:full":"5674 Scotch Ridge Rd Duanesburg NY 12056",
    "addr:housenumber":"5674",
    "addr:postcode":"12056",
    "addr:street":"Scotch Ridge Rd",
    "iso:country":"US",
    "sg:address":"5674 Scotch Ridge Rd",
    "sg:city":"Duanesburg",
    "sg:classifiers":[
        {
            "category":"Building & Trades",
            "subcategory":"Equipment Rental",
            "type":"Services"
        }
    ],
    "sg:phone":"+1   ",
    "sg:postcode":"12056",
    "sg:province":"NY",
    "wof:name":"Ridge Rentals LLC",
    "wof:placetype":"venue"
},
  "geometry": {"coordinates":[-74.139841,42.780571],"type":"Point"}
}