{
  "type": "Feature",
  "properties": {
    "iso:country":"US",
    "sg:address":"784 Central Park Ave",
    "sg:city":"Scarsdale",
    "sg:classifiers":[
        {
            "category":"Real Estate",
            "subcategory":"Real Estate Agent",
            "type":"Services"
        }
    ],
    "sg:phone":"+1 845 265 4739",
    "sg:postcode":"10583",
    "sg:province":"NY",
    "sg:tags":[
        "operator",
        "property",
        "commercial"
    ],
    "wof:name":"Panevan Corp",
    "wof:placetype":"venue"
},
  "geometry": {"coordinates":[-73.817763,40.996535],"type":"Point"}
}