{
  "type": "Feature",
  "properties": {
    "addr:full":"20 Iroquois St Niagara Falls NY 14303",
    "addr:housenumber":"20",
    "addr:postcode":"14303",
    "addr:street":"Iroquois St",
    "iso:country":"US",
    "sg:address":"20 Iroquois St",
    "sg:city":"Niagara Falls",
    "sg:classifiers":[
        {
            "category":"Professional",
            "type":"Services"
        }
    ],
    "sg:phone":"+1 716 278 0015",
    "sg:postcode":"14303",
    "sg:province":"NY",
    "sg:tags":[
        "establishment"
    ],
    "wof:name":"Bioconvergence",
    "wof:placetype":"venue"
},
  "geometry": {"coordinates":[-79.014742,43.079039],"type":"Point"}
}