{
  "type": "Feature",
  "properties": {
    "addr:full":"830 Willis Ave Albertson NY 11507",
    "addr:housenumber":"830",
    "addr:postcode":"11507",
    "addr:street":"Willis Ave",
    "iso:country":"US",
    "sg:address":"830 Willis Ave",
    "sg:city":"Albertson",
    "sg:classifiers":[
        {
            "category":"Real Estate",
            "subcategory":"Real Estate Agent",
            "type":"Services"
        }
    ],
    "sg:phone":"+1 516 294 1159",
    "sg:postcode":"11507",
    "sg:province":"NY",
    "sg:website":"www.depintorealtors.com",
    "wof:name":"De Pinto Realty",
    "wof:placetype":"venue"
},
  "geometry": {"coordinates":[-73.647492,40.766528],"type":"Point"}
}