{
  "type": "Feature",
  "properties": {
    "addr:full":"500 Grand Island Blvd Tonawanda NY 14150",
    "addr:housenumber":"500",
    "addr:postcode":"14150",
    "addr:street":"Grand Island Blvd",
    "iso:country":"US",
    "sg:address":"500 Grand Island Blvd",
    "sg:city":"Tonawanda",
    "sg:classifiers":[
        {
            "category":"Freight",
            "type":"Transportation"
        }
    ],
    "sg:phone":"+1   ",
    "sg:postcode":"14150",
    "sg:province":"NY",
    "sg:tags":[
        "distance",
        "long",
        "trucking"
    ],
    "wof:name":"White Star Trucking Lines Inc",
    "wof:placetype":"venue"
},
  "geometry": {"coordinates":[-78.917654,42.987916],"type":"Point"}
}