{
  "type": "Feature",
  "properties": {
    "addr:full":"1816 Church Ave Brooklyn NY 11226",
    "addr:housenumber":"1816",
    "addr:postcode":"11226",
    "addr:street":"Church Ave",
    "iso:country":"US",
    "sg:address":"1816 Church Ave",
    "sg:city":"Brooklyn",
    "sg:classifiers":[
        {
            "category":"Personal",
            "subcategory":"Barber",
            "type":"Services"
        }
    ],
    "sg:phone":"+1   ",
    "sg:postcode":"11226",
    "sg:province":"NY",
    "sg:tags":[
        "shop"
    ],
    "wof:name":"Windsor Barber Shop",
    "wof:placetype":"venue"
},
  "geometry": {"coordinates":[-73.962262,40.649665],"type":"Point"}
}