{
  "type": "Feature",
  "properties": {
    "addr:full":"177 2nd Ave Brooklyn NY 11215",
    "addr:housenumber":"177",
    "addr:postcode":"11215",
    "addr:street":"2Nd Ave",
    "iso:country":"US",
    "sg:address":"177 2nd Ave",
    "sg:city":"Brooklyn",
    "sg:classifiers":[
        {
            "category":"Building & Trades",
            "subcategory":"Plumbing",
            "type":"Services"
        }
    ],
    "sg:phone":"+1 718 369 7575",
    "sg:postcode":"11215",
    "sg:province":"NY",
    "sg:tags":[
        "conditioning",
        "contractor"
    ],
    "wof:name":"Access Plumbing Corp",
    "wof:placetype":"venue"
},
  "geometry": {"coordinates":[-73.995504,40.670069],"type":"Point"}
}