{
  "type": "Feature",
  "properties": {
    "addr:full":"11 Deepwells Ln Saint James NY 11780",
    "addr:housenumber":"11",
    "addr:postcode":"11780",
    "addr:street":"Deepwells Ln",
    "iso:country":"US",
    "sg:address":"11 Deepwells Ln",
    "sg:city":"Saint James",
    "sg:classifiers":[
        {
            "category":"Building & Trades",
            "subcategory":"Plumbing",
            "type":"Services"
        }
    ],
    "sg:phone":"+1 631 584 7339",
    "sg:postcode":"11780",
    "sg:province":"NY",
    "wof:name":"Branch Plumbing & Heating",
    "wof:placetype":"venue"
},
  "geometry": {"coordinates":[-73.162003,40.884499],"type":"Point"}
}