{
  "type": "Feature",
  "properties": {
    "addr:full":"45 W Main St Little Falls NY 13365",
    "addr:housenumber":"45",
    "addr:postcode":"13365",
    "addr:street":"W Main St",
    "iso:country":"US",
    "sg:address":"45 W Main St",
    "sg:city":"Little Falls",
    "sg:classifiers":[
        {
            "category":"Health Services",
            "subcategory":"Optometrist",
            "type":"Services"
        }
    ],
    "sg:phone":"+1   ",
    "sg:postcode":"13365",
    "sg:province":"NY",
    "sg:tags":[
        "optical",
        "good"
    ],
    "wof:name":"Theodore Wind",
    "wof:placetype":"venue"
},
  "geometry": {"coordinates":[-74.861368,43.042348],"type":"Point"}
}