{
  "type": "Feature",
  "properties": {
    "iso:country":"US",
    "sg:address":"82 Cove Rd",
    "sg:city":"Oyster Bay",
    "sg:classifiers":[
        {
            "category":"Professional",
            "subcategory":"Employment Agencies",
            "type":"Services"
        }
    ],
    "sg:phone":"+1   ",
    "sg:postcode":"11771",
    "sg:province":"NY",
    "wof:name":"Custom Word Processing Inc",
    "wof:placetype":"venue"
},
  "geometry": {"coordinates":[-73.512096,40.871254],"type":"Point"}
}