{
  "type": "Feature",
  "properties": {
    "iso:country":"US",
    "sg:address":"1 Boxwood Dr",
    "sg:city":"Great Neck",
    "sg:classifiers":[
        {
            "category":"Wholesale",
            "subcategory":"Furniture",
            "type":"Manufacturing & Wholesale Goods"
        }
    ],
    "sg:phone":"+1 516 487 7270",
    "sg:postcode":"11021",
    "sg:province":"NY",
    "sg:tags":[
        "institutional"
    ],
    "wof:name":"I Hyman Corp",
    "wof:placetype":"venue"
},
  "geometry": {"coordinates":[-73.738844,40.78387],"type":"Point"}
}