{
  "type": "Feature",
  "properties": {
    "iso:country":"US",
    "sg:address":"24 W 85 St",
    "sg:city":"New York",
    "sg:classifiers":[
        {
            "category":"Health Services",
            "subcategory":"Doctor",
            "type":"Services"
        }
    ],
    "sg:phone":"+1 212 873 0191",
    "sg:postcode":"10024",
    "sg:province":"NY",
    "sg:tags":[
        "physician",
        "surgeon"
    ],
    "wof:name":"Eduardo D Leonardo MD",
    "wof:placetype":"venue"
},
  "geometry": {"coordinates":[-73.97262000000001,40.785689],"type":"Point"}
}