{
  "type": "Feature",
  "properties": {
    "iso:country":"US",
    "sg:address":"731 Central Park Ave",
    "sg:city":"Scarsdale",
    "sg:classifiers":[
        {
            "category":"Shopping",
            "subcategory":"Clothing, Apparel, & Fashions",
            "type":"Retail Goods"
        }
    ],
    "sg:phone":"+1 914 725 7964",
    "sg:postcode":"10583",
    "sg:province":"NY",
    "wof:name":"Men's Wearhouse",
    "wof:placetype":"venue"
},
  "geometry": {"coordinates":[-73.81623399999999,40.998615],"type":"Point"}
}