{
  "type": "Feature",
  "properties": {
    "addr:full":"2 S Clinton St Syracuse NY 13202",
    "addr:housenumber":"2",
    "addr:postcode":"13202",
    "addr:street":"S Clinton St",
    "iso:country":"US",
    "sg:address":"2 S Clinton St",
    "sg:city":"Syracuse",
    "sg:classifiers":[
        {
            "category":"Professional",
            "subcategory":"Credit Reporting & Collection",
            "type":"Services"
        }
    ],
    "sg:phone":"+1   ",
    "sg:postcode":"13202",
    "sg:province":"NY",
    "wof:name":"Bennett Funding Group",
    "wof:placetype":"venue"
},
  "geometry": {"coordinates":[-76.15353899999999,43.050542],"type":"Point"}
}