{
  "type": "Feature",
  "properties": {
    "addr:full":"22 Corporate Woods Blvd Albany NY 12211",
    "addr:housenumber":"22",
    "addr:postcode":"12211",
    "addr:street":"Corporate Woods Blvd",
    "iso:country":"US",
    "sg:address":"22 Corporate Woods Blvd",
    "sg:city":"Albany",
    "sg:classifiers":[
        {
            "category":"Insurance",
            "subcategory":"Insurance Agent",
            "type":"Services"
        }
    ],
    "sg:phone":"+1 518 426 7748",
    "sg:postcode":"12211",
    "sg:province":"NY",
    "sg:website":"www.aflacny.com",
    "wof:name":"Aflac",
    "wof:placetype":"venue"
},
  "geometry": {"coordinates":[-73.762563,42.680248],"type":"Point"}
}