{
  "type": "Feature",
  "properties": {
    "addr:full":"625 Avenue of the Americas Fl 2 New York NY 10011",
    "addr:housenumber":"625;2",
    "addr:postcode":"10011",
    "addr:street":"Avenue Of The Americas Fl",
    "iso:country":"US",
    "sg:address":"625 Avenue of the Americas Fl 2",
    "sg:city":"New York",
    "sg:classifiers":[
        {
            "category":"Professional",
            "subcategory":"Employment Agencies",
            "type":"Services"
        }
    ],
    "sg:phone":"+1 212 645 4545",
    "sg:postcode":"10011",
    "sg:province":"NY",
    "wof:name":"S V P",
    "wof:placetype":"venue"
},
  "geometry": {"coordinates":[-73.99491399999999,40.740257],"type":"Point"}
}