{
  "type": "Feature",
  "properties": {
    "iso:country":"US",
    "sg:address":"573 Atlantic Ave",
    "sg:city":"Oceanside",
    "sg:classifiers":[
        {
            "category":"Retail",
            "subcategory":"Pet Boarding",
            "type":"Services"
        }
    ],
    "sg:phone":"+1 516 766 7647",
    "sg:postcode":"11572",
    "sg:province":"NY",
    "sg:tags":[
        "boarding/pet",
        "sitting"
    ],
    "sg:website":"www.snipdoggydog.com",
    "wof:name":"Snip Doggy Dog",
    "wof:placetype":"venue"
},
  "geometry": {"coordinates":[-73.657402,40.640701],"type":"Point"}
}