{
  "type": "Feature",
  "properties": {
    "iso:country":"US",
    "sg:address":"2715 Main St",
    "sg:city":"Buffalo",
    "sg:classifiers":[
        {
            "category":"Retail",
            "subcategory":"Veterinary Services",
            "type":"Services"
        }
    ],
    "sg:phone":"+1 716 835 3369",
    "sg:postcode":"14214",
    "sg:province":"NY",
    "sg:tags":[
        "veterinarian"
    ],
    "wof:name":"Central Park Animal Hospital",
    "wof:placetype":"venue"
},
  "geometry": {"coordinates":[-78.838097,42.9403],"type":"Point"}
}