{
  "type": "Feature",
  "properties": {
    "iso:country":"US",
    "sg:address":"67 Otis St",
    "sg:city":"West Babylon",
    "sg:classifiers":[
        {
            "category":"Building & Trades",
            "subcategory":"Construction",
            "type":"Services"
        }
    ],
    "sg:phone":"+1 631 491 4900",
    "sg:postcode":"11704",
    "sg:province":"NY",
    "sg:tags":[
        "nonresidential",
        "dry wall",
        "contract",
        "contractor"
    ],
    "wof:name":"Swayze Maintenance Corp",
    "wof:placetype":"venue"
},
  "geometry": {"coordinates":[-73.37513199999999,40.7407],"type":"Point"}
}