{
  "type": "Feature",
  "properties": {
    "addr:full":"42-81 Hunter St Queens NY 11101",
    "addr:housenumber":"42-81",
    "addr:postcode":"11101",
    "addr:street":"Hunter St",
    "iso:country":"US",
    "sg:address":"42-81 Hunter St",
    "sg:city":"Queens",
    "sg:classifiers":[
        {
            "category":"Professional",
            "type":"Services"
        },
        {
            "category":"Shopping",
            "subcategory":"Party Supplies",
            "type":"Retail Goods"
        },
        {
            "category":"Personal",
            "type":"Services"
        }
    ],
    "sg:phone":"+1 646 336 1980",
    "sg:postcode":"11101",
    "sg:province":"NY",
    "sg:tags":[
        "planning",
        "event",
        "caterer"
    ],
    "sg:website":"chefandco.com/",
    "wof:name":"Chef & Company",
    "wof:placetype":"venue"
},
  "geometry": {"coordinates":[-73.94068300000001,40.748335],"type":"Point"}
}