{
  "type": "Feature",
  "properties": {
    "iso:country":"US",
    "sg:address":"16 Elmwood Ave",
    "sg:city":"Johnstown",
    "sg:classifiers":[
        {
            "category":"Personal",
            "subcategory":"Barber",
            "type":"Services"
        }
    ],
    "sg:phone":"+1 518 762 7851",
    "sg:postcode":"12095",
    "sg:province":"NY",
    "wof:name":"Man's World Barber Salon",
    "wof:placetype":"venue"
},
  "geometry": {"coordinates":[-74.37093,43.022895],"type":"Point"}
}