{
  "type": "Feature",
  "properties": {
    "addr:full":"3541 Hempstead Tpke Levittown NY 11756",
    "addr:housenumber":"3541",
    "addr:postcode":"11756",
    "addr:street":"Hempstead Tpke",
    "iso:country":"US",
    "sg:address":"3541 Hempstead Tpke",
    "sg:city":"Levittown",
    "sg:classifiers":[
        {
            "category":"Shopping",
            "subcategory":"Gifts & Souvenirs",
            "type":"Retail Goods"
        }
    ],
    "sg:phone":"+1 516 520 6300",
    "sg:postcode":"11756",
    "sg:province":"NY",
    "sg:tags":[
        "party",
        "supply"
    ],
    "sg:website":"www.partycity.com",
    "wof:name":"Party City",
    "wof:placetype":"venue"
},
  "geometry": {"coordinates":[-73.505134,40.725631],"type":"Point"}
}