{
  "type": "Feature",
  "properties": {
    "addr:full":"40 Mahopac Ave Amawalk NY 10501",
    "addr:housenumber":"40",
    "addr:postcode":"10501",
    "addr:street":"Mahopac Ave",
    "iso:country":"US",
    "sg:address":"40 Mahopac Ave",
    "sg:city":"Amawalk",
    "sg:classifiers":[
        {
            "category":"Health Services",
            "subcategory":"Clinic",
            "type":"Services"
        }
    ],
    "sg:phone":"+1 914 245 4949",
    "sg:postcode":"10501",
    "sg:province":"NY",
    "sg:tags":[
        "welfare"
    ],
    "wof:name":"Mehnert & Associates",
    "wof:placetype":"venue"
},
  "geometry": {"coordinates":[-73.766037,41.29438],"type":"Point"}
}