{
  "type": "Feature",
  "properties": {
    "addr:full":"423 W 46th St New York NY 10036",
    "addr:housenumber":"423",
    "addr:postcode":"10036",
    "addr:street":"W 46Th St",
    "iso:country":"US",
    "sg:address":"423 W 46th St",
    "sg:city":"New York",
    "sg:classifiers":[
        {
            "category":"Social Services",
            "subcategory":"Child Care",
            "type":"Services"
        }
    ],
    "sg:phone":"+1 212 258 2208",
    "sg:postcode":"10036",
    "sg:province":"NY",
    "sg:tags":[
        "day"
    ],
    "wof:name":"St Clements After School & Day Care",
    "wof:placetype":"venue"
},
  "geometry": {"coordinates":[-73.993103,40.761799],"type":"Point"}
}