{
  "type": "Feature",
  "properties": {
    "addr:full":"545 Scarsdale Rd Tuckahoe NY 10707",
    "addr:housenumber":"545",
    "addr:postcode":"10707",
    "addr:street":"Scarsdale Rd",
    "iso:country":"US",
    "sg:address":"545 Scarsdale Rd",
    "sg:city":"Tuckahoe",
    "sg:classifiers":[
        {
            "category":"Organizations",
            "subcategory":"Religious Organization",
            "type":"Services"
        }
    ],
    "sg:phone":"+1 914 793 3663",
    "sg:postcode":"10707",
    "sg:province":"NY",
    "sg:tags":[
        "church"
    ],
    "wof:name":"Orthodox Christian Education",
    "wof:placetype":"venue"
},
  "geometry": {"coordinates":[-73.823502,40.968889],"type":"Point"}
}