{
  "type": "Feature",
  "properties": {
    "iso:country":"US",
    "sg:address":"11 Hanover Sq Fl 14",
    "sg:city":"New York",
    "sg:classifiers":[
        {
            "category":"Communications",
            "subcategory":"Newspaper",
            "type":"Services"
        }
    ],
    "sg:phone":"+1 212 482 4818",
    "sg:postcode":"10005",
    "sg:province":"NY",
    "sg:tags":[
        "print",
        "medium"
    ],
    "sg:website":"www.irishecho.com",
    "wof:name":"Irish Echo Newspaper",
    "wof:placetype":"venue"
},
  "geometry": {"coordinates":[-74.34965699999999,40.704654],"type":"Point"}
}