{
  "type": "Feature",
  "properties": {
    "addr:full":"48 N Church St Goshen NY 10924",
    "addr:housenumber":"48",
    "addr:postcode":"10924",
    "addr:street":"N Church St",
    "iso:country":"US",
    "sg:address":"48 N Church St",
    "sg:city":"Goshen",
    "sg:classifiers":[
        {
            "category":"Banks & Credit Unions",
            "subcategory":"Bank",
            "type":"Services"
        }
    ],
    "sg:phone":"+1 845 294 9085",
    "sg:postcode":"10924",
    "sg:province":"NY",
    "sg:tags":[
        "loan",
        "real estate"
    ],
    "wof:name":"First Greenwich Funding",
    "wof:placetype":"venue"
},
  "geometry": {"coordinates":[-74.32489700000001,41.402654],"type":"Point"}
}