{
  "type": "Feature",
  "properties": {
    "addr:full":"436 Hamilton St Geneva NY 14456",
    "addr:housenumber":"436",
    "addr:postcode":"14456",
    "addr:street":"Hamilton St",
    "iso:country":"US",
    "sg:address":"436 Hamilton St",
    "sg:city":"Geneva",
    "sg:classifiers":[
        {
            "category":"Restaurant",
            "type":"Food & Drink"
        }
    ],
    "sg:phone":"+1   ",
    "sg:postcode":"14456",
    "sg:province":"NY",
    "sg:tags":[
        "eating"
    ],
    "wof:name":"Burger King",
    "wof:placetype":"venue"
},
  "geometry": {"coordinates":[-77.001136,42.857535],"type":"Point"}
}