{
  "type": "Feature",
  "properties": {
    "iso:country":"US",
    "sg:address":"16 Sands Point Rd",
    "sg:city":"Monsey",
    "sg:classifiers":[
        {
            "category":"Shopping",
            "subcategory":"Pharmacy",
            "type":"Retail Goods"
        }
    ],
    "sg:phone":"+1   ",
    "sg:postcode":"10952",
    "sg:province":"NY",
    "wof:name":"Norman P Forgash Assoc In",
    "wof:placetype":"venue"
},
  "geometry": {"coordinates":[-74.07584199999999,41.124334],"type":"Point"}
}