{
  "type": "Feature",
  "properties": {
    "addr:full":"7 Main St Tappan NY 10983",
    "addr:housenumber":"7",
    "addr:postcode":"10983",
    "addr:street":"Main St",
    "iso:country":"US",
    "sg:address":"7 Main St",
    "sg:city":"Tappan",
    "sg:classifiers":[
        {
            "category":"Government",
            "subcategory":"Office",
            "type":"Public Place"
        }
    ],
    "sg:phone":"+1 845 359 4905",
    "sg:postcode":"10983",
    "sg:province":"NY",
    "sg:tags":[
        "management"
    ],
    "wof:name":"Jhs Landscaping Home Impr Ment",
    "wof:placetype":"venue"
},
  "geometry": {"coordinates":[-73.950356,41.018761],"type":"Point"}
}