{
  "type": "Feature",
  "properties": {
    "addr:full":"28 Bayview Rd Sag Harbor NY 11963",
    "addr:housenumber":"28",
    "addr:postcode":"11963",
    "addr:street":"Bayview Rd",
    "iso:country":"US",
    "sg:address":"28 Bayview Rd",
    "sg:city":"Sag Harbor",
    "sg:classifiers":[
        {
            "category":"Building & Trades",
            "subcategory":"Landscaping Services",
            "type":"Services"
        }
    ],
    "sg:phone":"+1 631 725 3308",
    "sg:postcode":"11963",
    "sg:province":"NY",
    "wof:name":"Green Heaven Lawn Care",
    "wof:placetype":"venue"
},
  "geometry": {"coordinates":[-72.31554800000001,40.992718],"type":"Point"}
}