{
  "type": "Feature",
  "properties": {
    "iso:country":"US",
    "sg:address":"2101 Mott Ave",
    "sg:city":"Far Rockaway",
    "sg:classifiers":[
        {
            "category":"Shopping",
            "subcategory":"Jewelry",
            "type":"Retail Goods"
        }
    ],
    "sg:phone":"+1 718 337 0747",
    "sg:postcode":"11691",
    "sg:province":"NY",
    "wof:name":"Mott Jewelry Inc",
    "wof:placetype":"venue"
},
  "geometry": {"coordinates":[-73.75369999999999,40.6045],"type":"Point"}
}