{
  "type": "Feature",
  "properties": {
    "addr:full":"3715 Riverdale Ave Bronx NY 10463",
    "addr:housenumber":"3715",
    "addr:postcode":"10463",
    "addr:street":"Riverdale Ave",
    "iso:country":"US",
    "sg:address":"3715 Riverdale Ave",
    "sg:city":"Bronx",
    "sg:classifiers":[
        {
            "category":"Personal",
            "subcategory":"Barber",
            "type":"Services"
        }
    ],
    "sg:phone":"+1   ",
    "sg:postcode":"10463",
    "sg:province":"NY",
    "sg:tags":[
        "shop"
    ],
    "wof:name":"Unisex",
    "wof:placetype":"venue"
},
  "geometry": {"coordinates":[-73.907282,40.887031],"type":"Point"}
}