{
  "type": "Feature",
  "properties": {
    "addr:full":"41 Mechanic St Port Jervis NY 12771",
    "addr:housenumber":"41",
    "addr:postcode":"12771",
    "addr:street":"Mechanic St",
    "iso:country":"US",
    "sg:address":"41 Mechanic St",
    "sg:city":"Port Jervis",
    "sg:classifiers":[
        {
            "category":"Shopping",
            "subcategory":"Computers & Home Electronics",
            "type":"Retail Goods"
        }
    ],
    "sg:phone":"+1 845 858 8809",
    "sg:postcode":"12771",
    "sg:province":"NY",
    "sg:website":"www.ariind.com",
    "wof:name":"Advanced Recovery Inc",
    "wof:placetype":"venue"
},
  "geometry": {"coordinates":[-74.70222,41.381624],"type":"Point"}
}