{
  "type": "Feature",
  "properties": {
    "addr:full":"10 Ward Rd North Tonawanda NY 14120",
    "addr:housenumber":"10",
    "addr:postcode":"14120",
    "addr:street":"Ward Rd",
    "iso:country":"US",
    "sg:address":"10 Ward Rd",
    "sg:city":"North Tonawanda",
    "sg:classifiers":[
        {
            "category":"Manufacturing",
            "subcategory":"Tools & Machinery",
            "type":"Manufacturing & Wholesale Goods"
        }
    ],
    "sg:phone":"+1 716 693 3713",
    "sg:postcode":"14120",
    "sg:province":"NY",
    "sg:tags":[
        "machine",
        "shop"
    ],
    "wof:name":"Tonawanda Machine & Fbrctng",
    "wof:placetype":"venue"
},
  "geometry": {"coordinates":[-78.88924799999999,43.054742],"type":"Point"}
}