{
  "type": "Feature",
  "properties": {
    "addr:full":"339 Flatbush Ave Brooklyn NY 11217",
    "addr:housenumber":"339",
    "addr:postcode":"11217",
    "addr:street":"Flatbush Ave",
    "iso:country":"US",
    "sg:address":"339 Flatbush Ave",
    "sg:city":"Brooklyn",
    "sg:classifiers":[
        {
            "category":"Real Estate",
            "subcategory":"Real Estate Agent",
            "type":"Services"
        }
    ],
    "sg:phone":"+1 718 638 1444",
    "sg:postcode":"11217",
    "sg:province":"NY",
    "wof:name":"Goldwin Real Estate Inc",
    "wof:placetype":"venue"
},
  "geometry": {"coordinates":[-73.97287,40.677971],"type":"Point"}
}