{
  "type": "Feature",
  "properties": {
    "addr:full":"109 W 45th St New York NY 10036",
    "addr:housenumber":"109",
    "addr:postcode":"10036",
    "addr:street":"W 45Th St",
    "iso:country":"US",
    "sg:address":"109 W 45th St",
    "sg:city":"New York",
    "sg:classifiers":[
        {
            "category":"Restaurant",
            "type":"Food & Drink"
        }
    ],
    "sg:phone":"+1 212 944 8484",
    "sg:postcode":"10036",
    "sg:province":"NY",
    "sg:tags":[
        "traditional",
        "american"
    ],
    "sg:website":"dunhillcafenyc.com",
    "wof:name":"Dunhill Cafe & Caterers",
    "wof:placetype":"venue"
},
  "geometry": {"coordinates":[-73.983209,40.757218],"type":"Point"}
}