{
  "type": "Feature",
  "properties": {
    "iso:country":"US",
    "sg:address":"32 Westside Ave",
    "sg:city":"Haverstraw",
    "sg:classifiers":[
        {
            "category":"Wholesale",
            "subcategory":"Apparel",
            "type":"Manufacturing & Wholesale Goods"
        }
    ],
    "sg:phone":"+1 845 942 4191",
    "sg:postcode":"10927",
    "sg:province":"NY",
    "sg:tags":[
        "clothing"
    ],
    "wof:name":"Keio Apparel",
    "wof:placetype":"venue"
},
  "geometry": {"coordinates":[-73.972787,41.200863],"type":"Point"}
}