{
  "type": "Feature",
  "properties": {
    "addr:full":"709 Bedford Rd Bedford Hills NY 10507",
    "addr:housenumber":"709",
    "addr:postcode":"10507",
    "addr:street":"Bedford Rd",
    "iso:country":"US",
    "sg:address":"709 Bedford Rd",
    "sg:city":"Bedford Hills",
    "sg:classifiers":[
        {
            "category":"Shopping",
            "subcategory":"Bicycles & Sporting Goods",
            "type":"Retail Goods"
        }
    ],
    "sg:phone":"+1 914 242 7341",
    "sg:postcode":"10507",
    "sg:province":"NY",
    "sg:tags":[
        "equipment",
        "exercise"
    ],
    "wof:name":"Total Fitness LLC",
    "wof:placetype":"venue"
},
  "geometry": {"coordinates":[-73.713517,41.225884],"type":"Point"}
}