{
  "type": "Feature",
  "properties": {
    "addr:full":"3576 Galway Rd Ballston Spa NY 12020",
    "addr:housenumber":"3576",
    "addr:postcode":"12020",
    "addr:street":"Galway Rd",
    "iso:country":"US",
    "sg:address":"3576 Galway Rd",
    "sg:city":"Ballston Spa",
    "sg:classifiers":[
        {
            "category":"Building & Trades",
            "subcategory":"Construction",
            "type":"Services"
        }
    ],
    "sg:phone":"+1 518 885 4309",
    "sg:postcode":"12020",
    "sg:province":"NY",
    "sg:tags":[
        "excavation",
        "contractor"
    ],
    "wof:name":"Northeast Excavating",
    "wof:placetype":"venue"
},
  "geometry": {"coordinates":[-73.898601,43.027651],"type":"Point"}
}