{
  "type": "Feature",
  "properties": {
    "addr:full":"300 Garden City Plz Fl 5 Garden City NY 11530",
    "addr:housenumber":"300;5",
    "addr:postcode":"11530",
    "addr:street":"Garden;Plz Fl",
    "iso:country":"US",
    "sg:address":"300 Garden City Plz Fl 5",
    "sg:city":"Garden City",
    "sg:classifiers":[
        {
            "category":"Professional",
            "subcategory":"Lawyer & Legal Services",
            "type":"Services"
        }
    ],
    "sg:phone":"+1 516 746 8000",
    "sg:postcode":"11530",
    "sg:province":"NY",
    "wof:name":"Jaspan Schlesinger Silverman & Hoffman Llp",
    "wof:placetype":"venue"
},
  "geometry": {"coordinates":[-73.611603,40.735298],"type":"Point"}
}