{
  "type": "Feature",
  "properties": {
    "addr:full":"195 Bridgetown St Staten Island NY 10314",
    "addr:housenumber":"195",
    "addr:postcode":"10314",
    "addr:street":"Bridgetown St",
    "iso:country":"US",
    "sg:address":"195 Bridgetown St",
    "sg:city":"Staten Island",
    "sg:classifiers":[
        {
            "category":"Health Services",
            "subcategory":"Dentist",
            "type":"Services"
        }
    ],
    "sg:phone":"+1 718 761 7316",
    "sg:postcode":"10314",
    "sg:province":"NY",
    "sg:tags":[
        "orthodontist",
        "pediatric"
    ],
    "sg:website":"www.sikidsdentist.com",
    "wof:name":"Skurnick Sara DMD",
    "wof:placetype":"venue"
},
  "geometry": {"coordinates":[-74.15660099999999,40.583099],"type":"Point"}
}