{
  "type": "Feature",
  "properties": {
    "iso:country":"US",
    "sg:address":"67 Sands St",
    "sg:city":"Brooklyn",
    "sg:classifiers":[
        {
            "category":"Parking",
            "type":"Transportation"
        }
    ],
    "sg:phone":"+1 718 643 6127",
    "sg:postcode":"11201",
    "sg:province":"NY",
    "sg:tags":[
        "garage"
    ],
    "wof:name":"Impark Sand St",
    "wof:placetype":"venue"
},
  "geometry": {"coordinates":[-73.988297,40.700032],"type":"Point"}
}