{
  "type": "Feature",
  "properties": {
    "iso:country":"US",
    "sg:address":"24 Liner Rd",
    "sg:city":"Newburgh",
    "sg:classifiers":[
        {
            "category":"Retail",
            "subcategory":"Auto Repair",
            "type":"Services"
        }
    ],
    "sg:phone":"+1 845 561 7400",
    "sg:postcode":"12553",
    "sg:province":"NY",
    "sg:tags":[
        "repairing",
        "automobile"
    ],
    "wof:name":"Safelite Auto Glass",
    "wof:placetype":"venue"
},
  "geometry": {"coordinates":[-74.07728899999999,41.493887],"type":"Point"}
}