{
  "type": "Feature",
  "properties": {
    "addr:full":"211 Utica Ave Brooklyn NY 11213",
    "addr:housenumber":"211",
    "addr:postcode":"11213",
    "addr:street":"Utica Ave",
    "iso:country":"US",
    "sg:address":"211 Utica Ave",
    "sg:city":"Brooklyn",
    "sg:classifiers":[
        {
            "category":"Deli",
            "type":"Food & Drink"
        },
        {
            "category":"Food & Beverages",
            "subcategory":"Bakery",
            "type":"Retail Goods"
        }
    ],
    "sg:phone":"+1 718 363 0203",
    "sg:postcode":"11213",
    "sg:province":"NY",
    "sg:tags":[
        "sandwich"
    ],
    "wof:name":"King Frank Deli",
    "wof:placetype":"venue"
},
  "geometry": {"coordinates":[-73.930673,40.67154],"type":"Point"}
}