{
  "type": "Feature",
  "properties": {
    "addr:full":"586 Oakley Ave Elmont NY 11003",
    "addr:housenumber":"586",
    "addr:postcode":"11003",
    "addr:street":"Oakley Ave",
    "iso:country":"US",
    "sg:address":"586 Oakley Ave",
    "sg:city":"Elmont",
    "sg:classifiers":[
        {
            "category":"Wholesale",
            "subcategory":"Non-durable Goods",
            "type":"Manufacturing & Wholesale Goods"
        }
    ],
    "sg:phone":"+1 516 488 4754",
    "sg:postcode":"11003",
    "sg:province":"NY",
    "wof:name":"Tai Shing Trading Inc",
    "wof:placetype":"venue"
},
  "geometry": {"coordinates":[-73.693342,40.692021],"type":"Point"}
}