{
  "type": "Feature",
  "properties": {
    "iso:country":"US",
    "sg:address":"3 Boland Rd",
    "sg:city":"Binghamton",
    "sg:classifiers":[
        {
            "category":"Organizations",
            "subcategory":"Non-profit Organization",
            "type":"Services"
        }
    ],
    "sg:phone":"+1 607 722 0889",
    "sg:postcode":"13905",
    "sg:province":"NY",
    "sg:tags":[
        "information",
        "alcoholism",
        "treatment"
    ],
    "wof:name":"Al-Anon",
    "wof:placetype":"venue"
},
  "geometry": {"coordinates":[-75.90576900000001,42.137241],"type":"Point"}
}