{
  "type": "Feature",
  "properties": {
    "addr:full":"661 E 2nd St Brooklyn NY 11218",
    "addr:housenumber":"661",
    "addr:postcode":"11218",
    "addr:street":"E 2Nd St",
    "iso:country":"US",
    "sg:address":"661 E 2nd St",
    "sg:city":"Brooklyn",
    "sg:classifiers":[
        {
            "category":"Building & Trades",
            "subcategory":"Construction",
            "type":"Services"
        }
    ],
    "sg:phone":"+1 718 972 0538",
    "sg:postcode":"11218",
    "sg:province":"NY",
    "sg:tags":[
        "house"
    ],
    "wof:name":"Sharma General Construction",
    "wof:placetype":"venue"
},
  "geometry": {"coordinates":[-73.976472,40.634079],"type":"Point"}
}