{
  "type": "Feature",
  "properties": {
    "iso:country":"US",
    "sg:address":"15 Nautilus Ave",
    "sg:city":"Northport",
    "sg:classifiers":[
        {
            "category":"Arts & Performance",
            "subcategory":"Theater",
            "type":"Entertainment"
        }
    ],
    "sg:phone":"+1   ",
    "sg:postcode":"11768",
    "sg:province":"NY",
    "sg:tags":[
        "group"
    ],
    "wof:name":"Long Island Masterworks Chorus",
    "wof:placetype":"venue"
},
  "geometry": {"coordinates":[-73.343968,40.910351],"type":"Point"}
}