{
  "type": "Feature",
  "properties": {
    "iso:country":"US",
    "sg:address":"4251 Old Route 22",
    "sg:city":"Brewster",
    "sg:classifiers":[
        {
            "category":"Real Estate",
            "subcategory":"Real Estate Services",
            "type":"Services"
        },
        {
            "category":"Banks & Credit Unions",
            "subcategory":"Financial Services",
            "type":"Services"
        }
    ],
    "sg:phone":"+1 845 207 9800",
    "sg:postcode":"10509",
    "sg:province":"NY",
    "sg:tags":[
        "loan",
        "processing",
        "broker",
        "mortgage"
    ],
    "wof:name":"Metropolitan Life Home Loans",
    "wof:placetype":"venue"
},
  "geometry": {"coordinates":[-73.581383,41.472602],"type":"Point"}
}