{
  "type": "Feature",
  "properties": {
    "addr:full":"5 Pleasant Valley Rd Eastport NY 11941",
    "addr:housenumber":"5",
    "addr:postcode":"11941",
    "addr:street":"Pleasant Valley Rd",
    "iso:country":"US",
    "sg:address":"5 Pleasant Valley Rd",
    "sg:city":"Eastport",
    "sg:classifiers":[
        {
            "category":"Building & Trades",
            "subcategory":"Electrical",
            "type":"Services"
        }
    ],
    "sg:phone":"+1 631 325 0819",
    "sg:postcode":"11941",
    "sg:province":"NY",
    "sg:tags":[
        "electrician",
        "electric",
        "contractor"
    ],
    "wof:name":"Eastport Electric",
    "wof:placetype":"venue"
},
  "geometry": {"coordinates":[-72.722099,40.825001],"type":"Point"}
}