{
  "type": "Feature",
  "properties": {
    "addr:full":"325 Fayette Ave Mamaroneck NY 10543",
    "addr:housenumber":"325",
    "addr:postcode":"10543",
    "addr:street":"Fayette Ave",
    "iso:country":"US",
    "sg:address":"325 Fayette Ave",
    "sg:city":"Mamaroneck",
    "sg:classifiers":[
        {
            "category":"Manufacturing",
            "subcategory":"Printing",
            "type":"Manufacturing & Wholesale Goods"
        }
    ],
    "sg:phone":"+1   ",
    "sg:postcode":"10543",
    "sg:province":"NY",
    "sg:tags":[
        "publishes",
        "comic",
        "book"
    ],
    "sg:website":"www.archiecomics.com",
    "wof:name":"Archie Comics Publishers Inc",
    "wof:placetype":"venue"
},
  "geometry": {"coordinates":[-73.74373799999999,40.95152],"type":"Point"}
}