{
  "type": "Feature",
  "properties": {
    "iso:country":"US",
    "sg:address":"2731 Snake Hill Rd",
    "sg:city":"Walton",
    "sg:classifiers":[
        {
            "category":"Farming",
            "subcategory":"Livestock Farm",
            "type":"Manufacturing & Wholesale Goods"
        }
    ],
    "sg:phone":"+1 607 829 8313",
    "sg:postcode":"13856",
    "sg:province":"NY",
    "sg:tags":[
        "ranch"
    ],
    "wof:name":"Arabia Farms",
    "wof:placetype":"venue"
},
  "geometry": {"coordinates":[-75.05342,42.300522],"type":"Point"}
}