{
  "type": "Feature",
  "properties": {
    "addr:full":"90 Glenwood Ave Point Lookout NY 11569",
    "addr:housenumber":"90",
    "addr:postcode":"11569",
    "addr:street":"Glenwood Ave",
    "iso:country":"US",
    "sg:address":"90 Glenwood Ave",
    "sg:city":"Point Lookout",
    "sg:classifiers":[
        {
            "category":"Organizations",
            "subcategory":"Religious Organization",
            "type":"Services"
        }
    ],
    "sg:phone":"+1 516 897 0931",
    "sg:postcode":"11569",
    "sg:province":"NY",
    "sg:tags":[
        "monastery",
        "convent"
    ],
    "wof:name":"Ursuline Sisters",
    "wof:placetype":"venue"
},
  "geometry": {"coordinates":[-73.579711,40.592093],"type":"Point"}
}