{
  "type": "Feature",
  "properties": {
    "addr:full":"979 Sunrise Mall Massapequa NY 11758",
    "addr:housenumber":"979",
    "addr:postcode":"11758",
    "addr:street":"Sunrise Mall",
    "iso:country":"US",
    "sg:address":"979 Sunrise Mall",
    "sg:city":"Massapequa",
    "sg:classifiers":[
        {
            "category":"Shopping",
            "subcategory":"Clothing, Apparel, & Fashions",
            "type":"Retail Goods"
        }
    ],
    "sg:phone":"+1 516 795 2224",
    "sg:postcode":"11758",
    "sg:province":"NY",
    "sg:tags":[
        "item",
        "boutique"
    ],
    "sg:website":"www.claires.com",
    "wof:name":"Claire's Boutique",
    "wof:placetype":"venue"
},
  "geometry": {"coordinates":[-73.433381,40.685591],"type":"Point"}
}