{
  "type": "Feature",
  "properties": {
    "addr:full":"136 Sunnyside Park Rd Syracuse NY 13214",
    "addr:housenumber":"136",
    "addr:postcode":"13214",
    "addr:street":"Sunnyside Park Rd",
    "iso:country":"US",
    "sg:address":"136 Sunnyside Park Rd",
    "sg:city":"Syracuse",
    "sg:classifiers":[
        {
            "category":"Education",
            "subcategory":"School",
            "type":"Public Place"
        },
        {
            "category":"Sports & Exercise",
            "subcategory":"Playing Field",
            "type":"Entertainment"
        }
    ],
    "sg:phone":"+1 315 446 8410",
    "sg:postcode":"13214",
    "sg:province":"NY",
    "sg:tags":[
        "personal",
        "development"
    ],
    "wof:name":"Ivey League Modeling",
    "wof:placetype":"venue"
},
  "geometry": {"coordinates":[-76.093166,43.043134],"type":"Point"}
}