{
  "type": "Feature",
  "properties": {
    "addr:full":"201 S Montgomery St Walden NY 12586",
    "addr:housenumber":"201",
    "addr:postcode":"12586",
    "addr:street":"S Montgomery St",
    "iso:country":"US",
    "sg:address":"201 S Montgomery St",
    "sg:city":"Walden",
    "sg:classifiers":[
        {
            "category":"Building & Trades",
            "subcategory":"Construction",
            "type":"Services"
        }
    ],
    "sg:phone":"+1 845 778 6378",
    "sg:postcode":"12586",
    "sg:province":"NY",
    "sg:tags":[
        "home",
        "builder"
    ],
    "wof:name":"Beazer Homes",
    "wof:placetype":"venue"
},
  "geometry": {"coordinates":[-74.19959799999999,41.556205],"type":"Point"}
}