{
  "type": "Feature",
  "properties": {
    "iso:country":"US",
    "sg:address":"508 Old Post Rd",
    "sg:city":"Port Jefferson",
    "sg:classifiers":[
        {
            "category":"Building & Trades",
            "subcategory":"Electrical",
            "type":"Services"
        }
    ],
    "sg:phone":"+1 631 474 0626",
    "sg:postcode":"11777",
    "sg:province":"NY",
    "sg:tags":[
        "electrical",
        "contractor"
    ],
    "wof:name":"CK Electric Co",
    "wof:placetype":"venue"
},
  "geometry": {"coordinates":[-73.080691,40.939218],"type":"Point"}
}