{
  "type": "Feature",
  "properties": {
    "addr:full":"16 Ellicott Pl Depew NY 14043",
    "addr:housenumber":"16",
    "addr:postcode":"14043",
    "addr:street":"Ellicott Pl",
    "iso:country":"US",
    "sg:address":"16 Ellicott Pl",
    "sg:city":"Depew",
    "sg:classifiers":[
        {
            "category":"Restaurant",
            "type":"Food & Drink"
        }
    ],
    "sg:phone":"+1 716 684 5404",
    "sg:postcode":"14043",
    "sg:province":"NY",
    "wof:name":"Ellicott Manor",
    "wof:placetype":"venue"
},
  "geometry": {"coordinates":[-78.682222,42.913997],"type":"Point"}
}