{
  "type": "Feature",
  "properties": {
    "iso:country":"US",
    "sg:address":"12010 Queens Blvd",
    "sg:city":"Kew Gardens",
    "sg:classifiers":[
        {
            "category":"Restaurant",
            "type":"Food & Drink"
        }
    ],
    "sg:phone":"+1 718 268 2288",
    "sg:postcode":"11415",
    "sg:province":"NY",
    "sg:tags":[
        "japanese"
    ],
    "wof:name":"Tasty Smooth Sushi",
    "wof:placetype":"venue"
},
  "geometry": {"coordinates":[-73.8302,40.713699],"type":"Point"}
}