{
  "type": "Feature",
  "properties": {
    "iso:country":"US",
    "sg:address":"100 Greene St",
    "sg:city":"New York",
    "sg:classifiers":[
        {
            "category":"Shopping",
            "subcategory":"Clothing, Apparel, & Fashions",
            "type":"Retail Goods"
        }
    ],
    "sg:phone":"+1 212 343 2300",
    "sg:postcode":"10012",
    "sg:province":"NY",
    "sg:tags":[
        "clothing",
        "women's"
    ],
    "sg:website":"www.jillstuart.com/",
    "wof:name":"Jill Stuart",
    "wof:placetype":"venue"
},
  "geometry": {"coordinates":[-73.999664,40.724238],"type":"Point"}
}