{
  "type": "Feature",
  "properties": {
    "addr:full":"1188 York Ave New York NY 10065",
    "addr:housenumber":"1188",
    "addr:postcode":"10065",
    "addr:street":"York Ave",
    "iso:country":"US",
    "sg:address":"1188 York Ave",
    "sg:city":"New York",
    "sg:classifiers":[
        {
            "category":"Professional",
            "subcategory":"Research",
            "type":"Services"
        }
    ],
    "sg:phone":"+1   ",
    "sg:postcode":"10065",
    "sg:province":"NY",
    "sg:tags":[
        "commercial",
        "physical"
    ],
    "wof:name":"Population Counsel",
    "wof:placetype":"venue"
},
  "geometry": {"coordinates":[-73.957888,40.761175],"type":"Point"}
}