{
  "type": "Feature",
  "properties": {
    "iso:country":"US",
    "sg:address":"150 W 25th St",
    "sg:city":"New York",
    "sg:classifiers":[
        {
            "category":"Professional",
            "subcategory":"Art Services",
            "type":"Services"
        }
    ],
    "sg:phone":"+1   ",
    "sg:postcode":"10001",
    "sg:province":"NY",
    "sg:tags":[
        "commercial",
        "design"
    ],
    "wof:name":"Studio 110",
    "wof:placetype":"venue"
},
  "geometry": {"coordinates":[-73.99364799999999,40.744707],"type":"Point"}
}