{
  "type": "Feature",
  "properties": {
    "addr:full":"453 W 36th St New York NY 10018",
    "addr:housenumber":"453",
    "addr:postcode":"10018",
    "addr:street":"W 36Th St",
    "iso:country":"US",
    "sg:address":"453 W 36th St",
    "sg:city":"New York",
    "sg:classifiers":[
        {
            "category":"Building & Trades",
            "subcategory":"Locksmith",
            "type":"Services"
        }
    ],
    "sg:phone":"+1 212 634 6104",
    "sg:postcode":"10018",
    "sg:province":"NY",
    "sg:tags":[
        "key"
    ],
    "wof:name":"24 Hr Locksmith Available",
    "wof:placetype":"venue"
},
  "geometry": {"coordinates":[-73.997398,40.755501],"type":"Point"}
}