{
  "type": "Feature",
  "properties": {
    "addr:full":"33 Front St Port Jervis NY 12771",
    "addr:housenumber":"33",
    "addr:postcode":"12771",
    "addr:street":"Front St",
    "iso:country":"US",
    "sg:address":"33 Front St",
    "sg:city":"Port Jervis",
    "sg:classifiers":[
        {
            "category":"Professional",
            "subcategory":"Employment Agencies",
            "type":"Services"
        }
    ],
    "sg:phone":"+1 845 858 8660",
    "sg:postcode":"12771",
    "sg:province":"NY",
    "sg:tags":[
        "help",
        "contractor"
    ],
    "wof:name":"Onesource Staffing Solutions",
    "wof:placetype":"venue"
},
  "geometry": {"coordinates":[-74.692802,41.373756],"type":"Point"}
}