{
  "type": "Feature",
  "properties": {
    "iso:country":"US",
    "sg:address":"147 W 58th Street",
    "sg:city":"New York",
    "sg:classifiers":[
        {
            "category":"Health Services",
            "subcategory":"Dentist",
            "type":"Services"
        }
    ],
    "sg:phone":"+1 212 245 0055",
    "sg:postcode":"10019",
    "sg:province":"NY",
    "wof:name":"Zimmerman R DDS",
    "wof:placetype":"venue"
},
  "geometry": {"coordinates":[-73.978802,40.765769],"type":"Point"}
}