{
  "type": "Feature",
  "properties": {
    "iso:country":"US",
    "sg:address":"12 Harrison St",
    "sg:city":"New York",
    "sg:classifiers":[
        {
            "category":"Shopping",
            "subcategory":"Computers & Home Electronics",
            "type":"Retail Goods"
        }
    ],
    "sg:phone":"+1 212 431 5152",
    "sg:postcode":"10013",
    "sg:province":"NY",
    "sg:tags":[
        "equipment",
        "dealer"
    ],
    "wof:name":"Ken Brown's Comical Commodity",
    "wof:placetype":"venue"
},
  "geometry": {"coordinates":[-74.009467,40.718786],"type":"Point"}
}