{
  "type": "Feature",
  "properties": {
    "addr:full":"24 Amity Pl Massapequa NY 11758",
    "addr:housenumber":"24",
    "addr:postcode":"11758",
    "addr:street":"Amity Pl",
    "iso:country":"US",
    "sg:address":"24 Amity Pl",
    "sg:city":"Massapequa",
    "sg:classifiers":[
        {
            "category":"Shopping",
            "type":"Retail Goods"
        }
    ],
    "sg:phone":"+1 516 541 6608",
    "sg:postcode":"11758",
    "sg:province":"NY",
    "sg:tags":[
        "wedding",
        "graphic",
        "computer",
        "supply"
    ],
    "wof:name":"Digital Vista Inc",
    "wof:placetype":"venue"
},
  "geometry": {"coordinates":[-73.445418,40.656921],"type":"Point"}
}