{
  "type": "Feature",
  "properties": {
    "addr:full":"1759 Middle Country Rd Centereach NY 11720",
    "addr:housenumber":"1759",
    "addr:postcode":"11720",
    "addr:street":"Middle Country Rd",
    "iso:country":"US",
    "sg:address":"1759 Middle Country Rd",
    "sg:city":"Centereach",
    "sg:classifiers":[
        {
            "category":"Retail",
            "subcategory":"Auto Repair",
            "type":"Services"
        }
    ],
    "sg:phone":"+1 631 588 3233",
    "sg:postcode":"11720",
    "sg:province":"NY",
    "sg:tags":[
        "transmission"
    ],
    "sg:website":"www.aamco.com",
    "wof:name":"AAMCO Transmissions",
    "wof:placetype":"venue"
},
  "geometry": {"coordinates":[-73.070971,40.860285],"type":"Point"}
}