{
  "type": "Feature",
  "properties": {
    "addr:full":"397 Greenwich Street New York NY 10013",
    "addr:housenumber":"397",
    "addr:postcode":"10013",
    "addr:street":"Greenwich Street",
    "iso:country":"US",
    "sg:address":"397 Greenwich Street",
    "sg:city":"New York",
    "sg:classifiers":[
        {
            "category":"Food & Beverages",
            "subcategory":"Bakery",
            "type":"Retail Goods"
        }
    ],
    "sg:phone":"+1 212 334 0472",
    "sg:postcode":"10013",
    "sg:province":"NY",
    "sg:tags":[
        "sandwich"
    ],
    "wof:name":"Wichcraft Operating",
    "wof:placetype":"venue"
},
  "geometry": {"coordinates":[-74.010104,40.720098],"type":"Point"}
}