{
  "type": "Feature",
  "properties": {
    "addr:full":"Albany Tpke Central Valley NY 10917",
    "addr:postcode":"10917",
    "addr:street":"Albany Tpke Central",
    "iso:country":"US",
    "sg:address":"Albany Tpke",
    "sg:city":"Central Valley",
    "sg:classifiers":[
        {
            "category":"Restaurant",
            "type":"Food & Drink"
        }
    ],
    "sg:phone":"+1 845 928 6689",
    "sg:postcode":"10917",
    "sg:province":"NY",
    "sg:tags":[
        "japanese"
    ],
    "wof:name":"Gasho of Japan",
    "wof:placetype":"venue"
},
  "geometry": {"coordinates":[-74.121101,41.3274],"type":"Point"}
}