{
  "type": "Feature",
  "properties": {
    "addr:full":"14016 State Rte 31 Albion NY 14411",
    "addr:housenumber":"14016",
    "addr:postcode":"14411",
    "addr:street":"State Rte 31",
    "iso:country":"US",
    "sg:address":"14016 State Rte 31",
    "sg:city":"Albion",
    "sg:classifiers":[
        {
            "category":"Government",
            "subcategory":"Office",
            "type":"Public Place"
        }
    ],
    "sg:phone":"+1 585 589 7177",
    "sg:postcode":"14411",
    "sg:province":"NY",
    "wof:name":"Orleans Fraud Hot Line",
    "wof:placetype":"venue"
},
  "geometry": {"coordinates":[-78.208967,43.240664],"type":"Point"}
}