{
  "type": "Feature",
  "properties": {
    "addr:full":"1 Clubhouse Dr Commack NY 11725",
    "addr:housenumber":"1",
    "addr:postcode":"11725",
    "addr:street":"Clubhouse Dr",
    "iso:country":"US",
    "sg:address":"1 Clubhouse Dr",
    "sg:city":"Commack",
    "sg:classifiers":[
        {
            "category":"Sports & Exercise",
            "subcategory":"Golf",
            "type":"Entertainment"
        }
    ],
    "sg:phone":"+1 631 462 6920",
    "sg:postcode":"11725",
    "sg:province":"NY",
    "sg:website":"www.hamletgolfandcountryclub.com",
    "wof:name":"Hamlet Golf & Country Club Gatehouse",
    "wof:placetype":"venue"
},
  "geometry": {"coordinates":[-73.298897,40.8256],"type":"Point"}
}