{
  "type": "Feature",
  "properties": {
    "addr:full":"61 Rowland St Ballston Spa NY 12020",
    "addr:housenumber":"61",
    "addr:postcode":"12020",
    "addr:street":"Rowland St",
    "iso:country":"US",
    "sg:address":"61 Rowland St",
    "sg:city":"Ballston Spa",
    "sg:classifiers":[
        {
            "category":"Professional",
            "subcategory":"Accounting & Tax Preparation",
            "type":"Services"
        }
    ],
    "sg:phone":"+1 518 885 8048",
    "sg:postcode":"12020",
    "sg:province":"NY",
    "sg:tags":[
        "bookkeeping",
        "general"
    ],
    "wof:name":"J & M Bookkeeping",
    "wof:placetype":"venue"
},
  "geometry": {"coordinates":[-73.84859400000001,43.0145],"type":"Point"}
}