{
  "type": "Feature",
  "properties": {
    "addr:full":"5051 Broadway Woodside NY 11377",
    "addr:housenumber":"5051",
    "addr:postcode":"11377",
    "addr:street":"Broadway",
    "iso:country":"US",
    "sg:address":"5051 Broadway",
    "sg:city":"Woodside",
    "sg:classifiers":[
        {
            "category":"Government",
            "subcategory":"Office",
            "type":"Public Place"
        }
    ],
    "sg:phone":"+1 718 278 5510",
    "sg:postcode":"11377",
    "sg:province":"NY",
    "sg:tags":[
        "township",
        "government-city",
        "village"
    ],
    "wof:name":"Woodside Queens Housing",
    "wof:placetype":"venue"
},
  "geometry": {"coordinates":[-73.896435,40.748825],"type":"Point"}
}