{
  "type": "Feature",
  "properties": {
    "iso:country":"US",
    "sg:address":"69 Adam St",
    "sg:city":"Lockport",
    "sg:classifiers":[
        {
            "category":"Shopping",
            "subcategory":"Gifts & Souvenirs",
            "type":"Retail Goods"
        }
    ],
    "sg:phone":"+1   ",
    "sg:postcode":"14094",
    "sg:province":"NY",
    "wof:name":"Justs Creations",
    "wof:placetype":"venue"
},
  "geometry": {"coordinates":[-78.67983700000001,43.175464],"type":"Point"}
}