{
  "type": "Feature",
  "properties": {
    "addr:full":"505 S 8th Ave Mt Vernon NY 10550",
    "addr:housenumber":"505",
    "addr:postcode":"10550",
    "addr:street":"S 8Th Ave",
    "iso:country":"US",
    "sg:address":"505 S 8th Ave",
    "sg:city":"Mt Vernon",
    "sg:classifiers":[
        {
            "category":"Insurance",
            "subcategory":"Insurance Agent",
            "type":"Services"
        }
    ],
    "sg:phone":"+1 914 664 9798",
    "sg:postcode":"10550",
    "sg:province":"NY",
    "wof:name":"Essential Things",
    "wof:placetype":"venue"
},
  "geometry": {"coordinates":[-73.835301,40.896497],"type":"Point"}
}