{
  "type": "Feature",
  "properties": {
    "iso:country":"US",
    "sg:address":"421 Court St",
    "sg:city":"Brooklyn",
    "sg:classifiers":[
        {
            "category":"Shopping",
            "subcategory":"Clothing, Apparel, & Fashions",
            "type":"Retail Goods"
        },
        {
            "category":"Shopping",
            "subcategory":"Stationery & Office Supplies",
            "type":"Retail Goods"
        },
        {
            "category":"Shopping",
            "subcategory":"Jewelry",
            "type":"Retail Goods"
        },
        {
            "category":"Shopping",
            "subcategory":"Gifts & Souvenirs",
            "type":"Retail Goods"
        }
    ],
    "sg:phone":"+1 718 797 0679",
    "sg:postcode":"11231",
    "sg:province":"NY",
    "sg:tags":[
        "shop",
        "men's",
        "clothing",
        "store",
        "women's"
    ],
    "sg:website":"www.serimony.com",
    "wof:name":"Serimony",
    "wof:placetype":"venue"
},
  "geometry": {"coordinates":[-73.997299,40.6791],"type":"Point"}
}