{
  "type": "Feature",
  "properties": {
    "iso:country":"US",
    "sg:address":"1810 New York Ave",
    "sg:city":"Huntington Station",
    "sg:classifiers":[
        {
            "category":"Shopping",
            "subcategory":"Stationery & Office Supplies",
            "type":"Retail Goods"
        }
    ],
    "sg:phone":"+1 631 271 8049",
    "sg:postcode":"11746",
    "sg:province":"NY",
    "sg:tags":[
        "equipment"
    ],
    "wof:name":"Multi Services Stationary Inc",
    "wof:placetype":"venue"
},
  "geometry": {"coordinates":[-73.412069,40.838041],"type":"Point"}
}