{
  "type": "Feature",
  "properties": {
    "addr:full":"860 Liberty Ave Brooklyn NY 11208",
    "addr:housenumber":"860",
    "addr:postcode":"11208",
    "addr:street":"Liberty Ave",
    "iso:country":"US",
    "sg:address":"860 Liberty Ave",
    "sg:city":"Brooklyn",
    "sg:classifiers":[
        {
            "category":"Organizations",
            "subcategory":"Religious Organization",
            "type":"Services"
        }
    ],
    "sg:phone":"+1 718 235 5976",
    "sg:postcode":"11208",
    "sg:province":"NY",
    "sg:tags":[
        "church"
    ],
    "wof:name":"Iglesia Biblica Christiana",
    "wof:placetype":"venue"
},
  "geometry": {"coordinates":[-73.878361,40.676971],"type":"Point"}
}