{
  "type": "Feature",
  "properties": {
    "addr:full":"5537 Myrtle Ave Ridgewood NY 11385",
    "addr:housenumber":"5537",
    "addr:postcode":"11385",
    "addr:street":"Myrtle Ave",
    "iso:country":"US",
    "sg:address":"5537 Myrtle Ave",
    "sg:city":"Ridgewood",
    "sg:classifiers":[
        {
            "category":"Restaurant",
            "type":"Food & Drink"
        }
    ],
    "sg:phone":"+1 718 497 1000",
    "sg:postcode":"11385",
    "sg:province":"NY",
    "sg:tags":[
        "mexican"
    ],
    "wof:name":"Los Hermanos Restaurant Corp",
    "wof:placetype":"venue"
},
  "geometry": {"coordinates":[-73.907239,40.700138],"type":"Point"}
}