{
  "type": "Feature",
  "properties": {
    "addr:full":"19 W 36th St Fl 4 New York NY 10018",
    "addr:housenumber":"19;4",
    "addr:postcode":"10018",
    "addr:street":"W 36Th St",
    "iso:country":"US",
    "sg:address":"19 W 36th St Fl 4",
    "sg:city":"New York",
    "sg:classifiers":[
        {
            "category":"Manufacturing",
            "subcategory":"Leather Goods",
            "type":"Manufacturing & Wholesale Goods"
        }
    ],
    "sg:phone":"+1 212 244 0467",
    "sg:postcode":"10018",
    "sg:province":"NY",
    "wof:name":"Gamani Design Inc",
    "wof:placetype":"venue"
},
  "geometry": {"coordinates":[-73.98429899999999,40.750099],"type":"Point"}
}