{
  "type": "Feature",
  "properties": {
    "addr:full":"316 E 103rd St New York NY 10029",
    "addr:housenumber":"316",
    "addr:postcode":"10029",
    "addr:street":"E 103Rd St",
    "iso:country":"US",
    "sg:address":"316 E 103rd St",
    "sg:city":"New York",
    "sg:classifiers":[
        {
            "category":"Government",
            "subcategory":"Office",
            "type":"Public Place"
        }
    ],
    "sg:phone":"+1 212 306 3000",
    "sg:postcode":"10029",
    "sg:province":"NY",
    "sg:tags":[
        "project",
        "housing"
    ],
    "wof:name":"Metro North Apartments",
    "wof:placetype":"venue"
},
  "geometry": {"coordinates":[-73.94180900000001,40.787789],"type":"Point"}
}