{
  "type": "Feature",
  "properties": {
    "addr:full":"950 Portion Rd Ronkonkoma NY 11779",
    "addr:housenumber":"950",
    "addr:postcode":"11779",
    "addr:street":"Portion Rd",
    "iso:country":"US",
    "sg:address":"950 Portion Rd",
    "sg:city":"Ronkonkoma",
    "sg:classifiers":[
        {
            "category":"Autos & Motor Vehicles",
            "subcategory":"Fuel & Gas Station",
            "type":"Retail Goods"
        }
    ],
    "sg:phone":"+1 631 737 8724",
    "sg:postcode":"11779",
    "sg:province":"NY",
    "wof:name":"5 Star Mobil SVC Station",
    "wof:placetype":"venue"
},
  "geometry": {"coordinates":[-73.285803,40.834366],"type":"Point"}
}