{
  "type": "Feature",
  "properties": {
    "addr:full":"91 Main St Cold Spring NY 10516",
    "addr:housenumber":"91",
    "addr:postcode":"10516",
    "addr:street":"Main St",
    "iso:country":"US",
    "sg:address":"91 Main St",
    "sg:city":"Cold Spring",
    "sg:classifiers":[
        {
            "category":"Shopping",
            "subcategory":"Clothing, Apparel, & Fashions",
            "type":"Retail Goods"
        }
    ],
    "sg:phone":"+1   ",
    "sg:postcode":"10516",
    "sg:province":"NY",
    "wof:name":"St Claire",
    "wof:placetype":"venue"
},
  "geometry": {"coordinates":[-73.95738299999999,41.418273],"type":"Point"}
}