{
  "type": "Feature",
  "properties": {
    "addr:full":"1823 Hobart Ave Bronx NY 10461",
    "addr:housenumber":"1823",
    "addr:postcode":"10461",
    "addr:street":"Hobart Ave",
    "iso:country":"US",
    "sg:address":"1823 Hobart Ave",
    "sg:city":"Bronx",
    "sg:classifiers":[
        {
            "category":"Banks & Credit Unions",
            "subcategory":"Financial Services",
            "type":"Services"
        }
    ],
    "sg:phone":"+1 347 810 0444",
    "sg:postcode":"10461",
    "sg:province":"NY",
    "sg:tags":[
        "broker",
        "mortgage"
    ],
    "wof:name":"Imperial Mortgage Corporation",
    "wof:placetype":"venue"
},
  "geometry": {"coordinates":[-73.83159000000001,40.848017],"type":"Point"}
}