{
  "type": "Feature",
  "properties": {
    "addr:full":"1562 62nd St Brooklyn NY 11219",
    "addr:housenumber":"1562",
    "addr:postcode":"11219",
    "addr:street":"62Nd St",
    "iso:country":"US",
    "sg:address":"1562 62nd St",
    "sg:city":"Brooklyn",
    "sg:classifiers":[
        {
            "category":"Building & Trades",
            "subcategory":"Plumbing",
            "type":"Services"
        }
    ],
    "sg:phone":"+1 718 236 3159",
    "sg:postcode":"11219",
    "sg:province":"NY",
    "sg:tags":[
        "repair",
        "contractor"
    ],
    "wof:name":"G & T Mechanical Company Inc",
    "wof:placetype":"venue"
},
  "geometry": {"coordinates":[-73.99423400000001,40.624496],"type":"Point"}
}