{
  "type": "Feature",
  "properties": {
    "addr:full":"2568 Walden Ave Buffalo NY 14225",
    "addr:housenumber":"2568",
    "addr:postcode":"14225",
    "addr:street":"Walden Ave",
    "iso:country":"US",
    "sg:address":"2568 Walden Ave",
    "sg:city":"Buffalo",
    "sg:classifiers":[
        {
            "category":"Health Services",
            "subcategory":"Medical Lab",
            "type":"Services"
        }
    ],
    "sg:phone":"+1 716 206 0993",
    "sg:postcode":"14225",
    "sg:province":"NY",
    "sg:tags":[
        "laboratories-pathological",
        "laboratory"
    ],
    "wof:name":"Healthelink",
    "wof:placetype":"venue"
},
  "geometry": {"coordinates":[-78.738212,42.908871],"type":"Point"}
}