{
  "type": "Feature",
  "properties": {
    "addr:full":"1399 Rockaway Pkwy Brooklyn NY 11236",
    "addr:housenumber":"1399",
    "addr:postcode":"11236",
    "addr:street":"Rockaway Pkwy",
    "iso:country":"US",
    "sg:address":"1399 Rockaway Pkwy",
    "sg:city":"Brooklyn",
    "sg:classifiers":[
        {
            "category":"Shopping",
            "subcategory":"Jewelry",
            "type":"Retail Goods"
        }
    ],
    "sg:phone":"+1   ",
    "sg:postcode":"11236",
    "sg:province":"NY",
    "wof:name":"Priscilla Jewelry",
    "wof:placetype":"venue"
},
  "geometry": {"coordinates":[-73.90249799999999,40.64547],"type":"Point"}
}