{
  "type": "Feature",
  "properties": {
    "iso:country":"US",
    "sg:address":"578 5th Ave",
    "sg:city":"New York",
    "sg:classifiers":[
        {
            "category":"Shopping",
            "subcategory":"Jewelry",
            "type":"Retail Goods"
        }
    ],
    "sg:phone":"+1 212 768 3740",
    "sg:postcode":"10036",
    "sg:province":"NY",
    "sg:tags":[
        "jeweler"
    ],
    "wof:name":"Ferrigini",
    "wof:placetype":"venue"
},
  "geometry": {"coordinates":[-73.979024,40.756032],"type":"Point"}
}