{
  "type": "Feature",
  "properties": {
    "addr:full":"56 Church St Port Jervis NY 12771",
    "addr:housenumber":"56",
    "addr:postcode":"12771",
    "addr:street":"Church St",
    "iso:country":"US",
    "sg:address":"56 Church St",
    "sg:city":"Port Jervis",
    "sg:classifiers":[
        {
            "category":"Health Services",
            "subcategory":"Doctor",
            "type":"Services"
        }
    ],
    "sg:phone":"+1 845 856 4346",
    "sg:postcode":"12771",
    "sg:province":"NY",
    "sg:tags":[
        "physician",
        "surgeon"
    ],
    "wof:name":"Twin Rivers Gastroenterology",
    "wof:placetype":"venue"
},
  "geometry": {"coordinates":[-74.684038,41.374652],"type":"Point"}
}