{
  "type": "Feature",
  "properties": {
    "iso:country":"US",
    "sg:address":"2055 Middle Country Rd",
    "sg:city":"Centereach",
    "sg:classifiers":[
        {
            "category":"Restaurant",
            "type":"Food & Drink"
        }
    ],
    "sg:menulink":"http://www.allmenus.com/ny/brookhaven/209488-meson-ole!/menu/",
    "sg:phone":"+1 631 737 3346",
    "sg:postcode":"11720",
    "sg:province":"NY",
    "sg:tags":[
        "mexican"
    ],
    "wof:name":"Meson Ole!",
    "wof:placetype":"venue"
},
  "geometry": {"coordinates":[-73.08414399999999,40.858439],"type":"Point"}
}