{
  "type": "Feature",
  "properties": {
    "addr:full":"215 E 161st St Bronx NY 10451",
    "addr:housenumber":"215",
    "addr:postcode":"10451",
    "addr:street":"E 161St St",
    "iso:country":"US",
    "sg:address":"215 E 161st St",
    "sg:city":"Bronx",
    "sg:classifiers":[
        {
            "category":"Social Services",
            "type":"Services"
        }
    ],
    "sg:phone":"+1 718 681 3600",
    "sg:postcode":"10451",
    "sg:province":"NY",
    "wof:name":"New York Cy Crmnal Jstice Agcy",
    "wof:placetype":"venue"
},
  "geometry": {"coordinates":[-73.92075800000001,40.826414],"type":"Point"}
}