{
  "type": "Feature",
  "properties": {
    "iso:country":"US",
    "sg:address":"25 Meadow Ct",
    "sg:city":"Manorville",
    "sg:classifiers":[
        {
            "category":"Building & Trades",
            "subcategory":"Construction",
            "type":"Services"
        }
    ],
    "sg:phone":"+1 631 874 3792",
    "sg:postcode":"11949",
    "sg:province":"NY",
    "sg:tags":[
        "general",
        "contractor"
    ],
    "wof:name":"All Angles Construction",
    "wof:placetype":"venue"
},
  "geometry": {"coordinates":[-72.765559,40.833946],"type":"Point"}
}