{
  "type": "Feature",
  "properties": {
    "iso:country":"US",
    "sg:address":"9 Gunther Pl",
    "sg:city":"Bellmore",
    "sg:classifiers":[
        {
            "category":"Professional",
            "subcategory":"Management & Consulting",
            "type":"Services"
        }
    ],
    "sg:phone":"+1   ",
    "sg:postcode":"11710",
    "sg:province":"NY",
    "wof:name":"Divine Directions",
    "wof:placetype":"venue"
},
  "geometry": {"coordinates":[-73.525946,40.673934],"type":"Point"}
}