{
  "type": "Feature",
  "properties": {
    "iso:country":"US",
    "sg:address":"355 Willis Ave",
    "sg:city":"Hawthorne",
    "sg:classifiers":[
        {
            "category":"Building & Trades",
            "subcategory":"Construction",
            "type":"Services"
        }
    ],
    "sg:phone":"+1 914 747 3029",
    "sg:postcode":"10532",
    "sg:province":"NY",
    "sg:tags":[
        "contractor"
    ],
    "wof:name":"Spectrum Construction Co",
    "wof:placetype":"venue"
},
  "geometry": {"coordinates":[-73.791955,41.108085],"type":"Point"}
}