{
  "type": "Feature",
  "properties": {
    "addr:full":"161 W 4th St New York NY 10014",
    "addr:housenumber":"161",
    "addr:postcode":"10014",
    "addr:street":"W 4Th St",
    "iso:country":"US",
    "sg:address":"161 W 4th St",
    "sg:city":"New York",
    "sg:classifiers":[
        {
            "category":"Shopping",
            "subcategory":"Clothing, Apparel, & Fashions",
            "type":"Retail Goods"
        }
    ],
    "sg:phone":"+1 212 462 0019",
    "sg:postcode":"10014",
    "sg:province":"NY",
    "sg:tags":[
        "lingerie"
    ],
    "wof:name":"Tic Tac Toe",
    "wof:placetype":"venue"
},
  "geometry": {"coordinates":[-74.001189,40.732085],"type":"Point"}
}