{
  "type": "Feature",
  "properties": {
    "addr:full":"134 W 29th St New York NY 10001",
    "addr:housenumber":"134",
    "addr:postcode":"10001",
    "addr:street":"W 29Th St",
    "iso:country":"US",
    "sg:address":"134 W 29th St",
    "sg:city":"New York",
    "sg:classifiers":[
        {
            "category":"Professional",
            "subcategory":"Computer Services",
            "type":"Services"
        }
    ],
    "sg:phone":"+1 212 563 4747",
    "sg:postcode":"10001",
    "sg:province":"NY",
    "sg:tags":[
        "consulting",
        "h",
        "customized",
        "including",
        "internet",
        "software"
    ],
    "sg:website":"www.acyberhosting.com",
    "wof:name":"Applied Cybernetics Intl",
    "wof:placetype":"venue"
},
  "geometry": {"coordinates":[-73.992199,40.747374],"type":"Point"}
}