{
  "type": "Feature",
  "properties": {
    "addr:full":"1029 63rd St Brooklyn NY 11219",
    "addr:housenumber":"1029",
    "addr:postcode":"11219",
    "addr:street":"63Rd St",
    "iso:country":"US",
    "sg:address":"1029 63rd St",
    "sg:city":"Brooklyn",
    "sg:classifiers":[
        {
            "category":"Health Services",
            "subcategory":"Doctor",
            "type":"Services"
        }
    ],
    "sg:phone":"+1 718 630 5881",
    "sg:postcode":"11219",
    "sg:province":"NY",
    "sg:tags":[
        "medical"
    ],
    "wof:name":"Zou Wen Fang",
    "wof:placetype":"venue"
},
  "geometry": {"coordinates":[-74.005149,40.630242],"type":"Point"}
}