{
  "type": "Feature",
  "properties": {
    "iso:country":"US",
    "sg:address":"15 E 30 St",
    "sg:city":"New York",
    "sg:classifiers":[
        {
            "category":"Recreation",
            "type":"Entertainment"
        }
    ],
    "sg:phone":"+1 212 481 2553",
    "sg:postcode":"10016",
    "sg:province":"NY",
    "sg:tags":[
        "martial",
        "arts",
        "instruction"
    ],
    "sg:website":"www.ahntaichi.com",
    "wof:name":"Ahn Tai Chi Studio",
    "wof:placetype":"venue"
},
  "geometry": {"coordinates":[-73.98560500000001,40.745783],"type":"Point"}
}