{
  "type": "Feature",
  "properties": {
    "iso:country":"US",
    "sg:address":"85 Tower Rd",
    "sg:city":"White Plains",
    "sg:classifiers":[
        {
            "category":"Sports & Exercise",
            "subcategory":"Race Track",
            "type":"Entertainment"
        }
    ],
    "sg:phone":"+1 914 682 6778",
    "sg:postcode":"10604",
    "sg:province":"NY",
    "wof:name":"Newman Racing",
    "wof:placetype":"venue"
},
  "geometry": {"coordinates":[-73.715205,41.061394],"type":"Point"}
}