{
  "type": "Feature",
  "properties": {
    "iso:country":"US",
    "sg:address":"131 Pine Tree Rd",
    "sg:city":"Monroe",
    "sg:classifiers":[
        {
            "category":"Professional",
            "subcategory":"Business Services",
            "type":"Services"
        }
    ],
    "sg:phone":"+1 845 783 4086",
    "sg:postcode":"10950",
    "sg:province":"NY",
    "sg:tags":[
        "inspection"
    ],
    "wof:name":"Home Advantage Inspection Serv",
    "wof:placetype":"venue"
},
  "geometry": {"coordinates":[-74.17519799999999,41.305649],"type":"Point"}
}