{
  "type": "Feature",
  "properties": {
    "iso:country":"US",
    "sg:address":"1810 Shore Pkwy N",
    "sg:city":"Brooklyn",
    "sg:classifiers":[
        {
            "category":"Autos & Motor Vehicles",
            "subcategory":"Automobile Sales",
            "type":"Retail Goods"
        }
    ],
    "sg:phone":"+1 718 258 5100",
    "sg:postcode":"11214",
    "sg:province":"NY",
    "sg:tags":[
        "car",
        "dealer"
    ],
    "wof:name":"Sovereign Motor Cars LTD",
    "wof:placetype":"venue"
},
  "geometry": {"coordinates":[-73.99436,40.592295],"type":"Point"}
}