{
  "type": "Feature",
  "properties": {
    "addr:full":"143 Riverhead Rd Westhampton Beach NY 11978",
    "addr:housenumber":"143",
    "addr:postcode":"11978",
    "addr:street":"Riverhead Rd",
    "iso:country":"US",
    "sg:address":"143 Riverhead Rd",
    "sg:city":"Westhampton Beach",
    "sg:classifiers":[
        {
            "category":"Shopping",
            "subcategory":"Mobile Phones",
            "type":"Retail Goods"
        }
    ],
    "sg:phone":"+1 631 288 2533",
    "sg:postcode":"11978",
    "sg:province":"NY",
    "wof:name":"Westhampton Wireless Inc",
    "wof:placetype":"venue"
},
  "geometry": {"coordinates":[-72.647003,40.8302],"type":"Point"}
}