{
  "type": "Feature",
  "properties": {
    "addr:full":"111 W Sandford Blvd Mt Vernon NY 10550",
    "addr:housenumber":"111",
    "addr:postcode":"10550",
    "addr:street":"W Sandford Blvd",
    "iso:country":"US",
    "sg:address":"111 W Sandford Blvd",
    "sg:city":"Mt Vernon",
    "sg:classifiers":[
        {
            "category":"Autos & Motor Vehicles",
            "subcategory":"Automobile Sales",
            "type":"Retail Goods"
        }
    ],
    "sg:phone":"+1 914 663 4200",
    "sg:postcode":"10550",
    "sg:province":"NY",
    "sg:tags":[
        "car",
        "dealer"
    ],
    "wof:name":"Epic Auto Sales Inc",
    "wof:placetype":"venue"
},
  "geometry": {"coordinates":[-73.83622200000001,40.898652],"type":"Point"}
}