{
  "type": "Feature",
  "properties": {
    "addr:full":"35 Wyoming St Commack NY 11725",
    "addr:housenumber":"35",
    "addr:postcode":"11725",
    "addr:street":"Wyoming St",
    "iso:country":"US",
    "sg:address":"35 Wyoming St",
    "sg:city":"Commack",
    "sg:classifiers":[
        {
            "category":"Wholesale",
            "subcategory":"Electrical",
            "type":"Manufacturing & Wholesale Goods"
        }
    ],
    "sg:phone":"+1 631 499 2355",
    "sg:postcode":"11725",
    "sg:province":"NY",
    "sg:tags":[
        "alarm",
        "burglar",
        "system"
    ],
    "wof:name":"Alert Alarm Systems",
    "wof:placetype":"venue"
},
  "geometry": {"coordinates":[-73.28654299999999,40.833265],"type":"Point"}
}