{
  "type": "Feature",
  "properties": {
    "iso:country":"US",
    "sg:address":"8250 Gulf Rd",
    "sg:city":"Le Roy",
    "sg:classifiers":[
        {
            "category":"Mining & Drilling",
            "type":"Manufacturing & Wholesale Goods"
        }
    ],
    "sg:phone":"+1 585 768 7295",
    "sg:postcode":"14482",
    "sg:province":"NY",
    "sg:tags":[
        "stone"
    ],
    "sg:website":"www.dolomitegroup.com",
    "wof:name":"Dolomite Products Co Inc",
    "wof:placetype":"venue"
},
  "geometry": {"coordinates":[-77.93799199999999,42.992259],"type":"Point"}
}