{
  "type": "Feature",
  "properties": {
    "iso:country":"US",
    "sg:address":"460 W 42nd St",
    "sg:city":"New York",
    "sg:classifiers":[
        {
            "category":"Freight",
            "type":"Transportation"
        }
    ],
    "sg:phone":"+1   ",
    "sg:postcode":"10036",
    "sg:province":"NY",
    "sg:tags":[
        "arrangement"
    ],
    "wof:name":"Crosstrade",
    "wof:placetype":"venue"
},
  "geometry": {"coordinates":[-73.99501600000001,40.759286],"type":"Point"}
}