{
  "type": "Feature",
  "properties": {
    "addr:full":"860 Walden Ave Buffalo NY 14211",
    "addr:housenumber":"860",
    "addr:postcode":"14211",
    "addr:street":"Walden Ave",
    "iso:country":"US",
    "sg:address":"860 Walden Ave",
    "sg:city":"Buffalo",
    "sg:classifiers":[
        {
            "category":"Restaurant",
            "type":"Food & Drink"
        }
    ],
    "sg:phone":"+1 716 894 8424",
    "sg:postcode":"14211",
    "sg:province":"NY",
    "sg:tags":[
        "pizza"
    ],
    "wof:name":"Poplar Pizza",
    "wof:placetype":"venue"
},
  "geometry": {"coordinates":[-78.804703,42.905998],"type":"Point"}
}