{
  "type": "Feature",
  "properties": {
    "addr:full":"150 Kisor Rd Highland NY 12528",
    "addr:housenumber":"150",
    "addr:postcode":"12528",
    "addr:street":"Kisor Rd",
    "iso:country":"US",
    "sg:address":"150 Kisor Rd",
    "sg:city":"Highland",
    "sg:classifiers":[
        {
            "category":"Professional",
            "subcategory":"Business Services",
            "type":"Services"
        }
    ],
    "sg:phone":"+1 845 691 2888",
    "sg:postcode":"12528",
    "sg:province":"NY",
    "sg:tags":[
        "arbitration"
    ],
    "wof:name":"Boughton Place Inc",
    "wof:placetype":"venue"
},
  "geometry": {"coordinates":[-74.00900799999999,41.738019],"type":"Point"}
}