{
  "type": "Feature",
  "properties": {
    "addr:full":"7346 Amboy Rd Staten Island NY 10307",
    "addr:housenumber":"7346",
    "addr:postcode":"10307",
    "addr:street":"Amboy Rd",
    "iso:country":"US",
    "sg:address":"7346 Amboy Rd",
    "sg:city":"Staten Island",
    "sg:classifiers":[
        {
            "category":"Banks & Credit Unions",
            "subcategory":"Investment Brokerage",
            "type":"Services"
        }
    ],
    "sg:phone":"+1 718 227 1731",
    "sg:postcode":"10307",
    "sg:province":"NY",
    "sg:tags":[
        "consultant",
        "planning",
        "financial"
    ],
    "sg:website":"www.thethinkingmind.com",
    "wof:name":"George Stern & Assoc",
    "wof:placetype":"venue"
},
  "geometry": {"coordinates":[-74.24241000000001,40.510593],"type":"Point"}
}