{
  "type": "Feature",
  "properties": {
    "addr:full":"47 Industrial Avenue US Hwy 46 New York NY 10001",
    "addr:housenumber":"47",
    "addr:postcode":"10001",
    "addr:street":"Industrial Avenue Us Hwy 46",
    "iso:country":"US",
    "sg:address":"47 Industrial Avenue US Hwy 46",
    "sg:city":"New York",
    "sg:classifiers":[
        {
            "category":"Communications",
            "subcategory":"Television Station",
            "type":"Services"
        }
    ],
    "sg:phone":"+1 212 233 6240",
    "sg:postcode":"10001",
    "sg:province":"NY",
    "wof:name":"W N J U-T V Broadcasting Corp Channel 47",
    "wof:placetype":"venue"
},
  "geometry": {"coordinates":[-73.977405,40.755504],"type":"Point"}
}