{
  "type": "Feature",
  "properties": {
    "addr:full":"13 Hickory Rd Bayville NY 11709",
    "addr:housenumber":"13",
    "addr:postcode":"11709",
    "addr:street":"Hickory Rd",
    "iso:country":"US",
    "sg:address":"13 Hickory Rd",
    "sg:city":"Bayville",
    "sg:classifiers":[
        {
            "category":"Professional",
            "subcategory":"Art Services",
            "type":"Services"
        }
    ],
    "sg:phone":"+1 516 624 7711",
    "sg:postcode":"11709",
    "sg:province":"NY",
    "sg:tags":[
        "graphic",
        "designer"
    ],
    "wof:name":"Creative Design Studio",
    "wof:placetype":"venue"
},
  "geometry": {"coordinates":[-73.57693500000001,40.904401],"type":"Point"}
}