{
  "type": "Feature",
  "properties": {
    "addr:full":"176 Lake Ave Saint James NY 11780",
    "addr:housenumber":"176",
    "addr:postcode":"11780",
    "addr:street":"Lake Ave",
    "iso:country":"US",
    "sg:address":"176 Lake Ave",
    "sg:city":"Saint James",
    "sg:classifiers":[
        {
            "category":"Organizations",
            "subcategory":"Religious Organization",
            "type":"Services"
        }
    ],
    "sg:phone":"+1 631 584 5789",
    "sg:postcode":"11780",
    "sg:province":"NY",
    "wof:name":"Knights of Notre Dame Des",
    "wof:placetype":"venue"
},
  "geometry": {"coordinates":[-73.15545899999999,40.870117],"type":"Point"}
}