{
  "type": "Feature",
  "properties": {
    "addr:full":"58 N Centre Ave Rockville Centre NY 11570",
    "addr:housenumber":"58",
    "addr:postcode":"11570",
    "addr:street":"N Centre Ave",
    "iso:country":"US",
    "sg:address":"58 N Centre Ave",
    "sg:city":"Rockville Centre",
    "sg:classifiers":[
        {
            "category":"Government",
            "subcategory":"Fire Station",
            "type":"Public Place"
        }
    ],
    "sg:phone":"+1 516 678 9320",
    "sg:postcode":"11570",
    "sg:province":"NY",
    "sg:tags":[
        "department"
    ],
    "wof:name":"Rockville Fire Dept Chief",
    "wof:placetype":"venue"
},
  "geometry": {"coordinates":[-73.649776,40.66003],"type":"Point"}
}