{
  "type": "Feature",
  "properties": {
    "iso:country":"US",
    "sg:address":"760 Blue Cut Rd",
    "sg:city":"Newark",
    "sg:classifiers":[
        {
            "category":"Building & Trades",
            "subcategory":"Plumbing",
            "type":"Services"
        }
    ],
    "sg:phone":"+1 315 331 4585",
    "sg:postcode":"14513",
    "sg:province":"NY",
    "sg:tags":[
        "contractor"
    ],
    "wof:name":"Gabbard Enterprises",
    "wof:placetype":"venue"
},
  "geometry": {"coordinates":[-77.074383,43.044116],"type":"Point"}
}