{
  "type": "Feature",
  "properties": {
    "iso:country":"US",
    "sg:address":"233 White Rd",
    "sg:city":"Glen Spey",
    "sg:classifiers":[
        {
            "category":"Manufacturing",
            "subcategory":"Signs",
            "type":"Manufacturing & Wholesale Goods"
        }
    ],
    "sg:phone":"+1   ",
    "sg:postcode":"12737",
    "sg:province":"NY",
    "sg:tags":[
        "specialty",
        "mfg"
    ],
    "wof:name":"Finehand Signs",
    "wof:placetype":"venue"
},
  "geometry": {"coordinates":[-74.77936699999999,41.459879],"type":"Point"}
}