{
  "type": "Feature",
  "properties": {
    "addr:full":"1901 Emmons Ave Brooklyn NY 11235",
    "addr:housenumber":"1901",
    "addr:postcode":"11235",
    "addr:street":"Emmons Ave",
    "iso:country":"US",
    "sg:address":"1901 Emmons Ave",
    "sg:city":"Brooklyn",
    "sg:classifiers":[
        {
            "category":"Wholesale",
            "subcategory":"Auto Parts",
            "type":"Manufacturing & Wholesale Goods"
        }
    ],
    "sg:phone":"+1 718 907 0092",
    "sg:postcode":"11235",
    "sg:province":"NY",
    "sg:tags":[
        "automobile",
        "wrecking"
    ],
    "wof:name":"Top Dollar Salvage",
    "wof:placetype":"venue"
},
  "geometry": {"coordinates":[-73.948426,40.583667],"type":"Point"}
}