{
  "type": "Feature",
  "properties": {
    "addr:full":"20 Columbia St Hudson NY 12534",
    "addr:housenumber":"20",
    "addr:postcode":"12534",
    "addr:street":"Columbia St",
    "iso:country":"US",
    "sg:address":"20 Columbia St",
    "sg:city":"Hudson",
    "sg:classifiers":[
        {
            "category":"Real Estate",
            "subcategory":"Real Estate Operator",
            "type":"Services"
        }
    ],
    "sg:phone":"+1 512 828 4700",
    "sg:postcode":"12534",
    "sg:province":"NY",
    "sg:tags":[
        "apartment"
    ],
    "wof:name":"Schuyler Court Apartments",
    "wof:placetype":"venue"
},
  "geometry": {"coordinates":[-73.79474999999999,42.256839],"type":"Point"}
}