{
  "type": "Feature",
  "properties": {
    "iso:country":"US",
    "sg:address":"10905 Downer Hill Rd",
    "sg:city":"Remsen",
    "sg:classifiers":[
        {
            "category":"Building & Trades",
            "subcategory":"Construction",
            "type":"Services"
        }
    ],
    "sg:phone":"+1 315 896 6152",
    "sg:postcode":"13438",
    "sg:province":"NY",
    "sg:tags":[
        "excavation",
        "contractor"
    ],
    "wof:name":"Patrick Nolan",
    "wof:placetype":"venue"
},
  "geometry": {"coordinates":[-75.164923,43.272048],"type":"Point"}
}