{
  "type": "Feature",
  "properties": {
    "iso:country":"US",
    "sg:address":"20 Branch Road",
    "sg:city":"Brewster",
    "sg:classifiers":[
        {
            "category":"Personal",
            "type":"Services"
        }
    ],
    "sg:phone":"+1 845 278 4020",
    "sg:postcode":"10509",
    "sg:province":"NY",
    "sg:tags":[
        "mover"
    ],
    "sg:website":"murphymovers.com",
    "wof:name":"Murphy John C Moving & Storage",
    "wof:placetype":"venue"
},
  "geometry": {"coordinates":[-73.578563,41.38619],"type":"Point"}
}