{
  "type": "Feature",
  "properties": {
    "iso:country":"US",
    "sg:address":"900 4th Ave",
    "sg:city":"Brooklyn",
    "sg:classifiers":[
        {
            "category":"Health Services",
            "subcategory":"Doctor",
            "type":"Services"
        }
    ],
    "sg:phone":"+1 718 768 8285",
    "sg:postcode":"11232",
    "sg:province":"NY",
    "sg:tags":[
        "physician",
        "surgeon"
    ],
    "wof:name":"Brooklyn Garant Svce Inc",
    "wof:placetype":"venue"
},
  "geometry": {"coordinates":[-74.002899,40.655998],"type":"Point"}
}