{
  "type": "Feature",
  "properties": {
    "addr:full":"465 N State Rd Briarcliff Manor NY 10510",
    "addr:housenumber":"465",
    "addr:postcode":"10510",
    "addr:street":"N State Rd",
    "iso:country":"US",
    "sg:address":"465 N State Rd",
    "sg:city":"Briarcliff Manor",
    "sg:classifiers":[
        {
            "category":"Health Services",
            "subcategory":"Doctor",
            "type":"Services"
        }
    ],
    "sg:phone":"+1 914 762 5810",
    "sg:postcode":"10510",
    "sg:province":"NY",
    "sg:tags":[
        "physician",
        "surgeon"
    ],
    "wof:name":"Fass Zimmerman & KATZ",
    "wof:placetype":"venue"
},
  "geometry": {"coordinates":[-73.825136,41.160573],"type":"Point"}
}