{
  "type": "Feature",
  "properties": {
    "addr:full":"950 E 6 St New York NY 10009",
    "addr:housenumber":"950;6",
    "addr:postcode":"10009",
    "addr:street":"E;St",
    "iso:country":"US",
    "sg:address":"950 E 6 St",
    "sg:city":"New York",
    "sg:classifiers":[
        {
            "category":"Professional",
            "subcategory":"Advertising",
            "type":"Services"
        }
    ],
    "sg:phone":"+1 212 279 5759",
    "sg:postcode":"10009",
    "sg:province":"NY",
    "sg:tags":[
        "counselor"
    ],
    "wof:name":"Bromley",
    "wof:placetype":"venue"
},
  "geometry": {"coordinates":[-73.97497799999999,40.721568],"type":"Point"}
}