{
  "type": "Feature",
  "properties": {
    "iso:country":"US",
    "sg:address":"39 Wittenberg Rd",
    "sg:city":"Bearsville",
    "sg:classifiers":[
        {
            "category":"Building & Trades",
            "subcategory":"Construction",
            "type":"Services"
        }
    ],
    "sg:phone":"+1 845 679 9121",
    "sg:postcode":"12409",
    "sg:province":"NY",
    "sg:tags":[
        "painter"
    ],
    "wof:name":"M Handschuh Painting & Contr",
    "wof:placetype":"venue"
},
  "geometry": {"coordinates":[-74.158767,42.038013],"type":"Point"}
}