{
  "type": "Feature",
  "properties": {
    "addr:full":"25 South St Marcellus NY 13108",
    "addr:housenumber":"25",
    "addr:postcode":"13108",
    "addr:street":"South St",
    "iso:country":"US",
    "sg:address":"25 South St",
    "sg:city":"Marcellus",
    "sg:classifiers":[
        {
            "category":"Real Estate",
            "subcategory":"Real Estate Services",
            "type":"Services"
        }
    ],
    "sg:phone":"+1 315 673 2406",
    "sg:postcode":"13108",
    "sg:province":"NY",
    "sg:tags":[
        "management"
    ],
    "wof:name":"Cny Management Corp",
    "wof:placetype":"venue"
},
  "geometry": {"coordinates":[-76.340346,42.979583],"type":"Point"}
}