{
  "type": "Feature",
  "properties": {
    "addr:full":"5700 Arlington Ave Bronx NY 10471",
    "addr:housenumber":"5700",
    "addr:postcode":"10471",
    "addr:street":"Arlington Ave",
    "iso:country":"US",
    "sg:address":"5700 Arlington Ave",
    "sg:city":"Bronx",
    "sg:classifiers":[
        {
            "category":"Retail",
            "subcategory":"Repair Shop",
            "type":"Services"
        }
    ],
    "sg:phone":"+1 718 548 9150",
    "sg:postcode":"10471",
    "sg:province":"NY",
    "sg:tags":[
        "oil",
        "burner"
    ],
    "wof:name":"Kinetic Energy Mgmt & Conslnts",
    "wof:placetype":"venue"
},
  "geometry": {"coordinates":[-73.906744,40.907089],"type":"Point"}
}