{
  "type": "Feature",
  "properties": {
    "iso:country":"US",
    "sg:address":"49 Front St",
    "sg:city":"Ballston Spa",
    "sg:classifiers":[
        {
            "category":"Organizations",
            "subcategory":"Community Association",
            "type":"Services"
        }
    ],
    "sg:phone":"+1 518 885 1045",
    "sg:postcode":"12020",
    "sg:province":"NY",
    "sg:tags":[
        "environmental",
        "org"
    ],
    "wof:name":"C A Smith LLC",
    "wof:placetype":"venue"
},
  "geometry": {"coordinates":[-73.850261,43.002517],"type":"Point"}
}