{
  "type": "Feature",
  "properties": {
    "addr:full":"78 W 36 St New York NY 10018",
    "addr:housenumber":"78",
    "addr:postcode":"10018",
    "addr:street":"W 36 St",
    "iso:country":"US",
    "sg:address":"78 W 36 St",
    "sg:city":"New York",
    "sg:classifiers":[
        {
            "category":"Manufacturing",
            "subcategory":"Printing",
            "type":"Manufacturing & Wholesale Goods"
        }
    ],
    "sg:phone":"+1 212 967 1290",
    "sg:postcode":"10018",
    "sg:province":"NY",
    "sg:tags":[
        "printer"
    ],
    "wof:name":"Marlo Color Copies & Printing",
    "wof:placetype":"venue"
},
  "geometry": {"coordinates":[-73.984949,40.749941],"type":"Point"}
}