{
  "type": "Feature",
  "properties": {
    "addr:full":"359 Collfield Ave Staten Island NY 10314",
    "addr:housenumber":"359",
    "addr:postcode":"10314",
    "addr:street":"Collfield Ave",
    "iso:country":"US",
    "sg:address":"359 Collfield Ave",
    "sg:city":"Staten Island",
    "sg:classifiers":[
        {
            "category":"Shopping",
            "subcategory":"Clothing, Apparel, & Fashions",
            "type":"Retail Goods"
        }
    ],
    "sg:phone":"+1   ",
    "sg:postcode":"10314",
    "sg:province":"NY",
    "wof:name":"F & S Custom Tailors",
    "wof:placetype":"venue"
},
  "geometry": {"coordinates":[-74.14368399999999,40.613262],"type":"Point"}
}