{
  "type": "Feature",
  "properties": {
    "addr:full":"1080 McDonald Ave Brooklyn NY 11230",
    "addr:housenumber":"1080",
    "addr:postcode":"11230",
    "addr:street":"Mcdonald Ave",
    "iso:country":"US",
    "sg:address":"1080 McDonald Ave",
    "sg:city":"Brooklyn",
    "sg:classifiers":[
        {
            "category":"Utilities",
            "subcategory":"Mobile Phone",
            "type":"Services"
        }
    ],
    "sg:phone":"+1 718 252 0449",
    "sg:postcode":"11230",
    "sg:province":"NY",
    "sg:tags":[
        "telephone",
        "cellular"
    ],
    "wof:name":"Supermarket Cellular",
    "wof:placetype":"venue"
},
  "geometry": {"coordinates":[-73.976601,40.627355],"type":"Point"}
}