{
  "type": "Feature",
  "properties": {
    "iso:country":"US",
    "sg:address":"7393 Utica Blvd",
    "sg:city":"Lowville",
    "sg:classifiers":[
        {
            "category":"Autos & Motor Vehicles",
            "subcategory":"Automobile Sales",
            "type":"Retail Goods"
        }
    ],
    "sg:phone":"+1 315 376 6568",
    "sg:postcode":"13367",
    "sg:province":"NY",
    "sg:tags":[
        "car",
        "dealer"
    ],
    "wof:name":"Essenlohr Motors Inc",
    "wof:placetype":"venue"
},
  "geometry": {"coordinates":[-75.479981,43.775974],"type":"Point"}
}