{
  "type": "Feature",
  "properties": {
    "addr:full":"1276 50th St Brooklyn NY 11219",
    "addr:housenumber":"1276",
    "addr:postcode":"11219",
    "addr:street":"50Th St",
    "iso:country":"US",
    "sg:address":"1276 50th St",
    "sg:city":"Brooklyn",
    "sg:classifiers":[
        {
            "category":"Manufacturing",
            "subcategory":"Printing",
            "type":"Manufacturing & Wholesale Goods"
        }
    ],
    "sg:phone":"+1   ",
    "sg:postcode":"11219",
    "sg:province":"NY",
    "sg:tags":[
        "corrugated",
        "on",
        "cardboard"
    ],
    "wof:name":"M&M Chopp Printing Industries",
    "wof:placetype":"venue"
},
  "geometry": {"coordinates":[-73.99401,40.635411],"type":"Point"}
}