{
  "type": "Feature",
  "properties": {
    "addr:full":"3780 Broadway New York NY 10032",
    "addr:housenumber":"3780",
    "addr:postcode":"10032",
    "addr:street":"Broadway",
    "iso:country":"US",
    "sg:address":"3780 Broadway",
    "sg:city":"New York",
    "sg:classifiers":[
        {
            "category":"Real Estate",
            "subcategory":"Real Estate Agent",
            "type":"Services"
        }
    ],
    "sg:phone":"+1 212 781 7971",
    "sg:postcode":"10032",
    "sg:province":"NY",
    "wof:name":"JSA Realty Corp",
    "wof:placetype":"venue"
},
  "geometry": {"coordinates":[-73.94442600000001,40.83468],"type":"Point"}
}