{
  "type": "Feature",
  "properties": {
    "addr:full":"212 E 9th St New York NY 10003",
    "addr:housenumber":"212",
    "addr:postcode":"10003",
    "addr:street":"E 9Th St",
    "iso:country":"US",
    "sg:address":"212 E 9th St",
    "sg:city":"New York",
    "sg:classifiers":[
        {
            "category":"Wholesale",
            "subcategory":"Stationery",
            "type":"Manufacturing & Wholesale Goods"
        }
    ],
    "sg:phone":"+1 212 614 3226",
    "sg:postcode":"10003",
    "sg:province":"NY",
    "sg:tags":[
        "himalayan/nepalese"
    ],
    "wof:name":"Tsampa",
    "wof:placetype":"venue"
},
  "geometry": {"coordinates":[-73.988602,40.729599],"type":"Point"}
}