{
  "type": "Feature",
  "properties": {
    "iso:country":"US",
    "sg:address":"20 Sinclair Dr",
    "sg:city":"Greenlawn",
    "sg:classifiers":[
        {
            "category":"Building & Trades",
            "subcategory":"Construction",
            "type":"Services"
        }
    ],
    "sg:phone":"+1 631 757 3010",
    "sg:postcode":"11740",
    "sg:province":"NY",
    "sg:tags":[
        "house"
    ],
    "wof:name":"Peter M Thun Contractor",
    "wof:placetype":"venue"
},
  "geometry": {"coordinates":[-73.361104,40.855224],"type":"Point"}
}