{
  "type": "Feature",
  "properties": {
    "iso:country":"US",
    "sg:address":"195 Derby Rd",
    "sg:city":"Middletown",
    "sg:classifiers":[
        {
            "category":"Wholesale",
            "subcategory":"Durable Goods & Equipment",
            "type":"Manufacturing & Wholesale Goods"
        }
    ],
    "sg:phone":"+1 845 386 4403",
    "sg:postcode":"10940",
    "sg:province":"NY",
    "wof:name":"American Antiques & Fine Arts",
    "wof:placetype":"venue"
},
  "geometry": {"coordinates":[-74.44626,41.486914],"type":"Point"}
}