{
  "type": "Feature",
  "properties": {
    "iso:country":"US",
    "sg:address":"436 New Scotland Ave",
    "sg:city":"Albany",
    "sg:classifiers":[
        {
            "category":"Professional",
            "type":"Services"
        }
    ],
    "sg:phone":"+1 518 489 3418",
    "sg:postcode":"12208",
    "sg:province":"NY",
    "sg:tags":[
        "establishment"
    ],
    "wof:name":"Pro-Tech Corp",
    "wof:placetype":"venue"
},
  "geometry": {"coordinates":[-73.794012,42.654086],"type":"Point"}
}