{
  "type": "Feature",
  "properties": {
    "iso:country":"US",
    "sg:address":"4260 White Plains Rd",
    "sg:city":"Bronx",
    "sg:classifiers":[
        {
            "category":"Professional",
            "subcategory":"Computer Services",
            "type":"Services"
        }
    ],
    "sg:phone":"+1   ",
    "sg:postcode":"10466",
    "sg:province":"NY",
    "sg:tags":[
        "prepackaged",
        "software"
    ],
    "wof:name":"Ozzi-D Computers",
    "wof:placetype":"venue"
},
  "geometry": {"coordinates":[-73.856154,40.895416],"type":"Point"}
}