{
  "type": "Feature",
  "properties": {
    "iso:country":"US",
    "sg:address":"223 Katonah Ave",
    "sg:city":"Katonah",
    "sg:classifiers":[
        {
            "category":"Recreation",
            "type":"Entertainment"
        }
    ],
    "sg:phone":"+1 914 232 3441",
    "sg:postcode":"10536",
    "sg:province":"NY",
    "sg:tags":[
        "instruction",
        "yoga"
    ],
    "wof:name":"Golden Temple Yoga Studio",
    "wof:placetype":"venue"
},
  "geometry": {"coordinates":[-73.683977,41.256308],"type":"Point"}
}