{
  "type": "Feature",
  "properties": {
    "iso:country":"US",
    "sg:address":"28 Mulberry St",
    "sg:city":"Clinton",
    "sg:classifiers":[
        {
            "category":"Professional",
            "subcategory":"Computer Services",
            "type":"Services"
        }
    ],
    "sg:phone":"+1 315 853 1070",
    "sg:postcode":"13323",
    "sg:province":"NY",
    "sg:tags":[
        "consultant",
        "designer"
    ],
    "wof:name":"Community Computer Systems Inc",
    "wof:placetype":"venue"
},
  "geometry": {"coordinates":[-75.37468699999999,43.046828],"type":"Point"}
}