{
  "type": "Feature",
  "properties": {
    "addr:full":"352 Kenmore Ave Buffalo NY 14223",
    "addr:housenumber":"352",
    "addr:postcode":"14223",
    "addr:street":"Kenmore Ave",
    "iso:country":"US",
    "sg:address":"352 Kenmore Ave",
    "sg:city":"Buffalo",
    "sg:classifiers":[
        {
            "category":"Organizations",
            "subcategory":"Religious Organization",
            "type":"Services"
        }
    ],
    "sg:phone":"+1 716 833 6598",
    "sg:postcode":"14223",
    "sg:province":"NY",
    "wof:name":"North Buffalo Community Church",
    "wof:placetype":"venue"
},
  "geometry": {"coordinates":[-78.831047,42.95801],"type":"Point"}
}