{
  "type": "Feature",
  "properties": {
    "addr:full":"16 Penn Ln Glenmont NY 12077",
    "addr:housenumber":"16",
    "addr:postcode":"12077",
    "addr:street":"Penn Ln",
    "iso:country":"US",
    "sg:address":"16 Penn Ln",
    "sg:city":"Glenmont",
    "sg:classifiers":[
        {
            "category":"Building & Trades",
            "subcategory":"Cleaning & Sanitation",
            "type":"Services"
        }
    ],
    "sg:phone":"+1 518 728 4259",
    "sg:postcode":"12077",
    "sg:province":"NY",
    "sg:tags":[
        "carpet"
    ],
    "wof:name":"CAPITAL DISTRICT CARPET CLEANERS",
    "wof:placetype":"venue"
},
  "geometry": {"coordinates":[-73.80209499999999,42.600493],"type":"Point"}
}