{
  "type": "Feature",
  "properties": {
    "addr:full":"184 N Portage St Westfield NY 14787",
    "addr:housenumber":"184",
    "addr:postcode":"14787",
    "addr:street":"N Portage St",
    "iso:country":"US",
    "sg:address":"184 N Portage St",
    "sg:city":"Westfield",
    "sg:classifiers":[
        {
            "category":"Autos & Motor Vehicles",
            "subcategory":"Fuel & Gas Station",
            "type":"Retail Goods"
        }
    ],
    "sg:phone":"+1 716 326 2869",
    "sg:postcode":"14787",
    "sg:province":"NY",
    "sg:tags":[
        "oil"
    ],
    "wof:name":"Wade's Keystone Mini Mart",
    "wof:placetype":"venue"
},
  "geometry": {"coordinates":[-79.58792699999999,42.332112],"type":"Point"}
}