{
  "type": "Feature",
  "properties": {
    "addr:full":"52 Kenmare St New York NY 10012",
    "addr:housenumber":"52",
    "addr:postcode":"10012",
    "addr:street":"Kenmare St",
    "iso:country":"US",
    "sg:address":"52 Kenmare St",
    "sg:city":"New York",
    "sg:classifiers":[
        {
            "category":"Home & Garden",
            "subcategory":"Hardware",
            "type":"Retail Goods"
        }
    ],
    "sg:phone":"+1 212 219 0349",
    "sg:postcode":"10012",
    "sg:province":"NY",
    "sg:tags":[
        "store"
    ],
    "wof:name":"Mott Hardware Inc",
    "wof:placetype":"venue"
},
  "geometry": {"coordinates":[-73.995499,40.720901],"type":"Point"}
}