{
  "type": "Feature",
  "properties": {
    "iso:country":"US",
    "sg:address":"134 E Main St",
    "sg:city":"Mount Kisco",
    "sg:classifiers":[
        {
            "category":"Autos & Motor Vehicles",
            "subcategory":"Fuel & Gas Station",
            "type":"Retail Goods"
        }
    ],
    "sg:phone":"+1 914 241 8716",
    "sg:postcode":"10549",
    "sg:province":"NY",
    "wof:name":"S & R Ati Svce Sta",
    "wof:placetype":"venue"
},
  "geometry": {"coordinates":[-73.7276,41.204899],"type":"Point"}
}