{
  "type": "Feature",
  "properties": {
    "addr:full":"501 Burnside Ave Inwood NY 11096",
    "addr:housenumber":"501",
    "addr:postcode":"11096",
    "addr:street":"Burnside Ave",
    "iso:country":"US",
    "sg:address":"501 Burnside Ave",
    "sg:city":"Inwood",
    "sg:classifiers":[
        {
            "category":"Shopping",
            "subcategory":"Clothing, Apparel, & Fashions",
            "type":"Retail Goods"
        }
    ],
    "sg:phone":"+1 516 239 3007",
    "sg:postcode":"11096",
    "sg:province":"NY",
    "wof:name":"Best Fashions",
    "wof:placetype":"venue"
},
  "geometry": {"coordinates":[-73.746364,40.622303],"type":"Point"}
}