{
  "type": "Feature",
  "properties": {
    "addr:full":"100 Co Op City Blvd Bronx NY 10475",
    "addr:housenumber":"100",
    "addr:postcode":"10475",
    "addr:street":"Co Op City Blvd",
    "iso:country":"US",
    "sg:address":"100 Co Op City Blvd",
    "sg:city":"Bronx",
    "sg:classifiers":[
        {
            "category":"Organizations",
            "subcategory":"Religious Organization",
            "type":"Services"
        }
    ],
    "sg:phone":"+1 718 671 8882",
    "sg:postcode":"10475",
    "sg:province":"NY",
    "sg:tags":[
        "synagogue"
    ],
    "wof:name":"Sephardic Shaare Rahamim",
    "wof:placetype":"venue"
},
  "geometry": {"coordinates":[-73.825889,40.8705],"type":"Point"}
}