{
  "type": "Feature",
  "properties": {
    "addr:full":"44 W 18 St New York NY 10011",
    "addr:housenumber":"44",
    "addr:postcode":"10011",
    "addr:street":"W 18 St",
    "iso:country":"US",
    "sg:address":"44 W 18 St",
    "sg:city":"New York",
    "sg:classifiers":[
        {
            "category":"Shopping",
            "subcategory":"Optical Goods",
            "type":"Retail Goods"
        }
    ],
    "sg:phone":"+1   ",
    "sg:postcode":"10011",
    "sg:province":"NY",
    "sg:tags":[
        "eyeglasses"
    ],
    "wof:name":"Sterling Vision",
    "wof:placetype":"venue"
},
  "geometry": {"coordinates":[-73.993987,40.739201],"type":"Point"}
}