{
  "type": "Feature",
  "properties": {
    "iso:country":"US",
    "sg:address":"7580 Hurdville Rd",
    "sg:city":"Arcade",
    "sg:classifiers":[
        {
            "category":"Manufacturing",
            "subcategory":"Glass & Minerals",
            "type":"Manufacturing & Wholesale Goods"
        }
    ],
    "sg:phone":"+1 716 496 5333",
    "sg:postcode":"14009",
    "sg:province":"NY",
    "sg:tags":[
        "ready"
    ],
    "wof:name":"Arcade Ready-Mix Concrete Inc",
    "wof:placetype":"venue"
},
  "geometry": {"coordinates":[-78.457532,42.536974],"type":"Point"}
}