{
  "type": "Feature",
  "properties": {
    "addr:full":"91 Highland Rd Scarsdale NY 10583",
    "addr:housenumber":"91",
    "addr:postcode":"10583",
    "addr:street":"Highland Rd",
    "iso:country":"US",
    "sg:address":"91 Highland Rd",
    "sg:city":"Scarsdale",
    "sg:classifiers":[
        {
            "category":"Professional",
            "subcategory":"Business Services",
            "type":"Services"
        }
    ],
    "sg:phone":"+1 914 723 4464",
    "sg:postcode":"10583",
    "sg:province":"NY",
    "sg:tags":[
        "consulting",
        "management"
    ],
    "wof:name":"Silicon Alley Breakfast Club",
    "wof:placetype":"venue"
},
  "geometry": {"coordinates":[-73.828559,40.99711],"type":"Point"}
}