{
  "type": "Feature",
  "properties": {
    "iso:country":"US",
    "sg:address":"2820 Merrick Rd",
    "sg:city":"Bellmore",
    "sg:classifiers":[
        {
            "category":"Autos & Motor Vehicles",
            "subcategory":"Boat Sales",
            "type":"Retail Goods"
        }
    ],
    "sg:phone":"+1 516 221 3005",
    "sg:postcode":"11710",
    "sg:province":"NY",
    "sg:tags":[
        "dealer",
        "sales"
    ],
    "wof:name":"American Boat Listing",
    "wof:placetype":"venue"
},
  "geometry": {"coordinates":[-73.5222,40.664319],"type":"Point"}
}