{
  "type": "Feature",
  "properties": {
    "iso:country":"US",
    "sg:address":"312 Wolf Rd",
    "sg:city":"Latham",
    "sg:classifiers":[
        {
            "category":"Government",
            "subcategory":"Police Station",
            "type":"Public Place"
        }
    ],
    "sg:phone":"+1 518 783 2754",
    "sg:postcode":"12110",
    "sg:province":"NY",
    "sg:tags":[
        "department"
    ],
    "sg:website":"www.colonie.org",
    "wof:name":"Police Dept-Investigations",
    "wof:placetype":"venue"
},
  "geometry": {"coordinates":[-73.79109099999999,42.737885],"type":"Point"}
}