{
  "type": "Feature",
  "properties": {
    "addr:full":"309 Woodbury Rd Hicksville NY 11801",
    "addr:housenumber":"309",
    "addr:postcode":"11801",
    "addr:street":"Woodbury Rd",
    "iso:country":"US",
    "sg:address":"309 Woodbury Rd",
    "sg:city":"Hicksville",
    "sg:classifiers":[
        {
            "category":"Health Services",
            "subcategory":"Chiropractor",
            "type":"Services"
        }
    ],
    "sg:phone":"+1   ",
    "sg:postcode":"11801",
    "sg:province":"NY",
    "wof:name":"Goldman Stephen Dr",
    "wof:placetype":"venue"
},
  "geometry": {"coordinates":[-73.508752,40.778273],"type":"Point"}
}