{
  "type": "Feature",
  "properties": {
    "iso:country":"US",
    "sg:address":"30 Wallins Corners Rd",
    "sg:city":"Amsterdam",
    "sg:classifiers":[
        {
            "category":"Food & Beverages",
            "subcategory":"Groceries & Convenience Stores",
            "type":"Retail Goods"
        }
    ],
    "sg:phone":"+1   ",
    "sg:postcode":"12010",
    "sg:province":"NY",
    "wof:name":"Mini Kwik Inc",
    "wof:placetype":"venue"
},
  "geometry": {"coordinates":[-74.17218200000001,42.972119],"type":"Point"}
}