{
  "type": "Feature",
  "properties": {
    "addr:full":"6214 10th Ave Brooklyn NY 11219",
    "addr:housenumber":"6214",
    "addr:postcode":"11219",
    "addr:street":"10Th Ave",
    "iso:country":"US",
    "sg:address":"6214 10th Ave",
    "sg:city":"Brooklyn",
    "sg:classifiers":[
        {
            "category":"Wholesale",
            "subcategory":"Computers",
            "type":"Manufacturing & Wholesale Goods"
        }
    ],
    "sg:phone":"+1 718 836 1433",
    "sg:postcode":"11219",
    "sg:province":"NY",
    "wof:name":"Yr Soft Inc",
    "wof:placetype":"venue"
},
  "geometry": {"coordinates":[-74.006916,40.631259],"type":"Point"}
}