{
  "type": "Feature",
  "properties": {
    "addr:full":"355 Food Center Dr Bronx NY 10474",
    "addr:housenumber":"355",
    "addr:postcode":"10474",
    "addr:street":"Food Center Dr",
    "iso:country":"US",
    "sg:address":"355 Food Center Dr",
    "sg:city":"Bronx",
    "sg:classifiers":[
        {
            "category":"Wholesale",
            "subcategory":"Meat",
            "type":"Manufacturing & Wholesale Goods"
        }
    ],
    "sg:phone":"+1 718 842 4447",
    "sg:postcode":"10474",
    "sg:province":"NY",
    "sg:website":"www.rosenlamb.com",
    "wof:name":"B Rosen & Sons Inc",
    "wof:placetype":"venue"
},
  "geometry": {"coordinates":[-73.87206399999999,40.8093],"type":"Point"}
}