{
  "type": "Feature",
  "properties": {
    "iso:country":"US",
    "sg:address":"447 E Boston Post Rd",
    "sg:city":"Mamaroneck",
    "sg:classifiers":[
        {
            "category":"Insurance",
            "subcategory":"Insurance Agent",
            "type":"Services"
        }
    ],
    "sg:phone":"+1 914 381 2066",
    "sg:postcode":"10543",
    "sg:province":"NY",
    "sg:website":"www.pantaenius.com",
    "wof:name":"Pantaenius America LTD",
    "wof:placetype":"venue"
},
  "geometry": {"coordinates":[-73.730262,40.950121],"type":"Point"}
}