{
  "type": "Feature",
  "properties": {
    "iso:country":"US",
    "sg:address":"2783 Merrick Rd",
    "sg:city":"Bellmore",
    "sg:classifiers":[
        {
            "category":"Shopping",
            "type":"Retail Goods"
        }
    ],
    "sg:phone":"+1   ",
    "sg:postcode":"11710",
    "sg:province":"NY",
    "sg:tags":[
        "repair",
        "merchandise"
    ],
    "wof:name":"Neo Art & Frame",
    "wof:placetype":"venue"
},
  "geometry": {"coordinates":[-73.52292,40.664324],"type":"Point"}
}