{
  "type": "Feature",
  "properties": {
    "addr:full":"435 Austin Pl Bronx NY 10455",
    "addr:housenumber":"435",
    "addr:postcode":"10455",
    "addr:street":"Austin Pl",
    "iso:country":"US",
    "sg:address":"435 Austin Pl",
    "sg:city":"Bronx",
    "sg:classifiers":[
        {
            "category":"Local Transit",
            "type":"Transportation"
        }
    ],
    "sg:phone":"+1 718 402 6990",
    "sg:postcode":"10455",
    "sg:province":"NY",
    "sg:tags":[
        "bus",
        "line"
    ],
    "wof:name":"Leonardo Transportation",
    "wof:placetype":"venue"
},
  "geometry": {"coordinates":[-73.904403,40.809998],"type":"Point"}
}