{
  "type": "Feature",
  "properties": {
    "iso:country":"US",
    "sg:address":"25 Willowdale Ave Ofc",
    "sg:city":"Port Washington",
    "sg:classifiers":[
        {
            "category":"Communications",
            "subcategory":"Newspaper",
            "type":"Services"
        }
    ],
    "sg:phone":"+1 516 767 2500",
    "sg:postcode":"11050",
    "sg:province":"NY",
    "sg:tags":[
        "print",
        "medium"
    ],
    "wof:name":"The Music & Sound Retailer",
    "wof:placetype":"venue"
},
  "geometry": {"coordinates":[-73.6875,40.8251],"type":"Point"}
}