{
  "type": "Feature",
  "properties": {
    "addr:full":"32 Triangle Center Yorktown Heights NY 10598",
    "addr:housenumber":"32",
    "addr:postcode":"10598",
    "addr:street":"Triangle;Yorktown Heights",
    "iso:country":"US",
    "sg:address":"32 Triangle Center",
    "sg:city":"Yorktown Heights",
    "sg:classifiers":[
        {
            "category":"Shopping",
            "subcategory":"Jewelry",
            "type":"Retail Goods"
        }
    ],
    "sg:phone":"+1   ",
    "sg:postcode":"10598",
    "sg:province":"NY",
    "wof:name":"Genesis Jewelers",
    "wof:placetype":"venue"
},
  "geometry": {"coordinates":[-73.808335,41.295488],"type":"Point"}
}