{
  "type": "Feature",
  "properties": {
    "iso:country":"US",
    "sg:address":"11 Penn Plaza",
    "sg:city":"New York",
    "sg:classifiers":[
        {
            "category":"Professional",
            "subcategory":"Computer Services",
            "type":"Services"
        }
    ],
    "sg:phone":"+1 516 874 3939",
    "sg:postcode":"10001",
    "sg:province":"NY",
    "sg:tags":[
        "social-commerce",
        "social-ecommerce",
        "ecommerce",
        "social",
        "auctions",
        "ebay",
        "paypal",
        "adaptive-payments",
        "tc50",
        "techcrunch50",
        "demopit",
        "swoopo",
        "online-auctions",
        "craigslist",
        "cataloging",
        "inventory",
        "barcode",
        "collections"
    ],
    "sg:website":"http://www.StuffBuff.com",
    "wof:name":"StuffBuff",
    "wof:placetype":"venue"
},
  "geometry": {"coordinates":[-73.991563,40.749705],"type":"Point"}
}