{
  "type": "Feature",
  "properties": {
    "iso:country":"US",
    "sg:address":"640 Melrose Avenue",
    "sg:city":"Bronx",
    "sg:classifiers":[
        {
            "category":"Restaurant",
            "type":"Food & Drink"
        }
    ],
    "sg:phone":"+1 718 585 5858",
    "sg:postcode":"10455",
    "sg:province":"NY",
    "wof:name":"Melrose Chicken Corporation",
    "wof:placetype":"venue"
},
  "geometry": {"coordinates":[-73.916554,40.818425],"type":"Point"}
}