{
  "type": "Feature",
  "properties": {
    "addr:full":"1099 Poplar Ridge Rd Aurora NY 13026",
    "addr:housenumber":"1099",
    "addr:postcode":"13026",
    "addr:street":"Poplar Ridge Rd",
    "iso:country":"US",
    "sg:address":"1099 Poplar Ridge Rd",
    "sg:city":"Aurora",
    "sg:classifiers":[
        {
            "category":"Government",
            "subcategory":"Office",
            "type":"Public Place"
        }
    ],
    "sg:phone":"+1 315 364 5529",
    "sg:postcode":"13026",
    "sg:province":"NY",
    "sg:tags":[
        "town"
    ],
    "wof:name":"Highway Dept",
    "wof:placetype":"venue"
},
  "geometry": {"coordinates":[-76.664478,42.735241],"type":"Point"}
}