{
  "type": "Feature",
  "properties": {
    "addr:full":"1711 3rd Ave New York NY 10029",
    "addr:housenumber":"1711",
    "addr:postcode":"10029",
    "addr:street":"3Rd Ave",
    "iso:country":"US",
    "sg:address":"1711 3rd Ave",
    "sg:city":"New York",
    "sg:classifiers":[
        {
            "category":"Place Of Worship",
            "subcategory":"Mosque",
            "type":"Public Place"
        }
    ],
    "sg:phone":"+1 212 722 5234",
    "sg:postcode":"10029",
    "sg:province":"NY",
    "wof:name":"Islamic Cultural Center of New York",
    "wof:placetype":"venue"
},
  "geometry": {"coordinates":[-73.948601,40.7859],"type":"Point"}
}