{
  "type": "Feature",
  "properties": {
    "addr:full":"342 Kings Hwy Brooklyn NY 11223",
    "addr:housenumber":"342",
    "addr:postcode":"11223",
    "addr:street":"Kings Hwy",
    "iso:country":"US",
    "sg:address":"342 Kings Hwy",
    "sg:city":"Brooklyn",
    "sg:classifiers":[
        {
            "category":"Shopping",
            "subcategory":"Photographic Equipment",
            "type":"Retail Goods"
        }
    ],
    "sg:phone":"+1   ",
    "sg:postcode":"11223",
    "sg:province":"NY",
    "sg:tags":[
        "photography",
        "camera",
        "supply"
    ],
    "sg:website":"www.ccicameracity.com",
    "wof:name":"Camera City Inc",
    "wof:placetype":"venue"
},
  "geometry": {"coordinates":[-73.97745500000001,40.604767],"type":"Point"}
}