{
  "type": "Feature",
  "properties": {
    "addr:full":"2673 Atlantic Ave Brooklyn NY 11207",
    "addr:housenumber":"2673",
    "addr:postcode":"11207",
    "addr:street":"Atlantic Ave",
    "iso:country":"US",
    "sg:address":"2673 Atlantic Ave",
    "sg:city":"Brooklyn",
    "sg:classifiers":[
        {
            "category":"Social Services",
            "type":"Services"
        }
    ],
    "sg:phone":"+1 718 566 0305",
    "sg:postcode":"11207",
    "sg:province":"NY",
    "sg:tags":[
        "organization",
        "welfare"
    ],
    "wof:name":"Brooklyn Bureau-Comm Svc",
    "wof:placetype":"venue"
},
  "geometry": {"coordinates":[-73.89504700000001,40.675969],"type":"Point"}
}