{
  "type": "Feature",
  "properties": {
    "addr:full":"2050 Cicero Ave Bronx NY 10473",
    "addr:housenumber":"2050",
    "addr:postcode":"10473",
    "addr:street":"Cicero Ave",
    "iso:country":"US",
    "sg:address":"2050 Cicero Ave",
    "sg:city":"Bronx",
    "sg:classifiers":[
        {
            "category":"Travel",
            "subcategory":"Travel Agent",
            "type":"Entertainment"
        }
    ],
    "sg:phone":"+1   ",
    "sg:postcode":"10473",
    "sg:province":"NY",
    "sg:tags":[
        "agency"
    ],
    "wof:name":"Lgf Travel",
    "wof:placetype":"venue"
},
  "geometry": {"coordinates":[-73.852434,40.816851],"type":"Point"}
}