{
  "type": "Feature",
  "properties": {
    "addr:full":"488 Madison Ave New York NY 10022",
    "addr:housenumber":"488",
    "addr:postcode":"10022",
    "addr:street":"Madison Ave",
    "iso:country":"US",
    "sg:address":"488 Madison Ave",
    "sg:city":"New York",
    "sg:classifiers":[
        {
            "category":"Professional",
            "subcategory":"Lawyer & Legal Services",
            "type":"Services"
        }
    ],
    "sg:phone":"+1 212 583 9500",
    "sg:postcode":"10022",
    "sg:province":"NY",
    "sg:website":"bwp-law.com",
    "wof:name":"Pechman Louis Atty",
    "wof:placetype":"venue"
},
  "geometry": {"coordinates":[-73.974701,40.758999],"type":"Point"}
}