{
  "type": "Feature",
  "properties": {
    "iso:country":"US",
    "sg:address":"147 Collenton Dr",
    "sg:city":"Rochester",
    "sg:classifiers":[
        {
            "category":"Building & Trades",
            "subcategory":"Construction",
            "type":"Services"
        }
    ],
    "sg:phone":"+1 585 227 2468",
    "sg:postcode":"14626",
    "sg:province":"NY",
    "sg:tags":[
        "hanging",
        "contractor"
    ],
    "wof:name":"Philip Dianto Painting",
    "wof:placetype":"venue"
},
  "geometry": {"coordinates":[-77.723114,43.24423],"type":"Point"}
}