{
  "type": "Feature",
  "properties": {
    "iso:country":"US",
    "sg:address":"36 Elm St",
    "sg:city":"Norwood",
    "sg:classifiers":[
        {
            "category":"Shopping",
            "subcategory":"Hobbies, Toys, & Games",
            "type":"Retail Goods"
        }
    ],
    "sg:phone":"+1   ",
    "sg:postcode":"13668",
    "sg:province":"NY",
    "wof:name":"Keller Country",
    "wof:placetype":"venue"
},
  "geometry": {"coordinates":[-74.99889899999999,44.745206],"type":"Point"}
}