{
  "type": "Feature",
  "properties": {
    "iso:country":"US",
    "sg:address":"7 East Ave",
    "sg:city":"Fairport",
    "sg:classifiers":[
        {
            "category":"Real Estate",
            "subcategory":"Real Estate Services",
            "type":"Services"
        },
        {
            "category":"Real Estate",
            "subcategory":"Real Estate Agent",
            "type":"Services"
        }
    ],
    "sg:phone":"+1 585 377 8540",
    "sg:postcode":"14450",
    "sg:province":"NY",
    "sg:tags":[
        "management"
    ],
    "sg:website":"http://www.lilliputdollhouses.com",
    "wof:name":"Lilliput Dollhouses Miniatures",
    "wof:placetype":"venue"
},
  "geometry": {"coordinates":[-77.441305,43.105673],"type":"Point"}
}