{
  "type": "Feature",
  "properties": {
    "addr:full":"1061 Northern Blvd Roslyn NY 11576",
    "addr:housenumber":"1061",
    "addr:postcode":"11576",
    "addr:street":"Northern Blvd",
    "iso:country":"US",
    "sg:address":"1061 Northern Blvd",
    "sg:city":"Roslyn",
    "sg:classifiers":[
        {
            "category":"Personal",
            "type":"Services"
        },
        {
            "category":"Retail",
            "subcategory":"Auto Repair",
            "type":"Services"
        }
    ],
    "sg:phone":"+1 516 627 7630",
    "sg:postcode":"11576",
    "sg:province":"NY",
    "sg:tags":[
        "towing"
    ],
    "wof:name":"Schmidt Charles & Son Inc",
    "wof:placetype":"venue"
},
  "geometry": {"coordinates":[-73.663597,40.7985],"type":"Point"}
}