{
  "type": "Feature",
  "properties": {
    "addr:full":"19 W 26th St New York NY 10010",
    "addr:housenumber":"19",
    "addr:postcode":"10010",
    "addr:street":"W 26Th St",
    "iso:country":"US",
    "sg:address":"19 W 26th St",
    "sg:city":"New York",
    "sg:classifiers":[
        {
            "category":"Professional",
            "type":"Services"
        }
    ],
    "sg:phone":"+1 212 683 7677",
    "sg:postcode":"10010",
    "sg:province":"NY",
    "sg:tags":[
        "establishment"
    ],
    "wof:name":"Chingtien Co",
    "wof:placetype":"venue"
},
  "geometry": {"coordinates":[-73.99104800000001,40.744683],"type":"Point"}
}