{
  "type": "Feature",
  "properties": {
    "addr:full":"523 Orchard Ct Mahopac NY 10541",
    "addr:housenumber":"523",
    "addr:postcode":"10541",
    "addr:street":"Orchard Ct",
    "iso:country":"US",
    "sg:address":"523 Orchard Ct",
    "sg:city":"Mahopac",
    "sg:classifiers":[
        {
            "category":"Building & Trades",
            "subcategory":"Electrical",
            "type":"Services"
        }
    ],
    "sg:phone":"+1 845 628 7850",
    "sg:postcode":"10541",
    "sg:province":"NY",
    "sg:tags":[
        "electrical",
        "contractor"
    ],
    "wof:name":"Dart Electric Inc",
    "wof:placetype":"venue"
},
  "geometry": {"coordinates":[-73.729039,41.369409],"type":"Point"}
}