{
  "type": "Feature",
  "properties": {
    "iso:country":"US",
    "sg:address":"27 Horton Ave",
    "sg:city":"New Rochelle",
    "sg:classifiers":[
        {
            "category":"Building & Trades",
            "subcategory":"Construction",
            "type":"Services"
        }
    ],
    "sg:phone":"+1 914 699 2400",
    "sg:postcode":"10801",
    "sg:province":"NY",
    "sg:tags":[
        "contractor"
    ],
    "wof:name":"Universal Builders Supply",
    "wof:placetype":"venue"
},
  "geometry": {"coordinates":[-73.788252,40.920183],"type":"Point"}
}