{
  "type": "Feature",
  "properties": {
    "iso:country":"US",
    "sg:address":"304 Larkfield Rd",
    "sg:city":"East Northport",
    "sg:classifiers":[
        {
            "category":"Autos & Motor Vehicles",
            "subcategory":"Fuel & Gas Station",
            "type":"Retail Goods"
        }
    ],
    "sg:phone":"+1 631 368 9651",
    "sg:postcode":"11731",
    "sg:province":"NY",
    "wof:name":"Gosman Bros Svce Center",
    "wof:placetype":"venue"
},
  "geometry": {"coordinates":[-73.320702,40.864101],"type":"Point"}
}