{
  "type": "Feature",
  "properties": {
    "addr:full":"1206 Ave U Brooklyn NY 11229",
    "addr:housenumber":"1206",
    "addr:postcode":"11229",
    "addr:street":"Ave U",
    "iso:country":"US",
    "sg:address":"1206 Ave U",
    "sg:city":"Brooklyn",
    "sg:classifiers":[
        {
            "category":"Personal",
            "subcategory":"Beauty Salon",
            "type":"Services"
        }
    ],
    "sg:phone":"+1 718 787 4666",
    "sg:postcode":"11229",
    "sg:province":"NY",
    "wof:name":"Eddie's Hair Salon",
    "wof:placetype":"venue"
},
  "geometry": {"coordinates":[-73.95933599999999,40.598429],"type":"Point"}
}