{
  "type": "Feature",
  "properties": {
    "addr:full":"33 E Main St Angelica NY 14709",
    "addr:housenumber":"33",
    "addr:postcode":"14709",
    "addr:street":"E Main St",
    "iso:country":"US",
    "sg:address":"33 E Main St",
    "sg:city":"Angelica",
    "sg:classifiers":[
        {
            "category":"Wholesale",
            "subcategory":"Furniture",
            "type":"Manufacturing & Wholesale Goods"
        }
    ],
    "sg:phone":"+1 585 466 3112",
    "sg:postcode":"14709",
    "sg:province":"NY",
    "wof:name":"Chin Gu & Co",
    "wof:placetype":"venue"
},
  "geometry": {"coordinates":[-78.014346,42.305693],"type":"Point"}
}