{
  "type": "Feature",
  "properties": {
    "addr:full":"2991 Broadway New York NY 10027",
    "addr:housenumber":"2991",
    "addr:postcode":"10027",
    "addr:street":"Broadway",
    "iso:country":"US",
    "sg:address":"2991 Broadway",
    "sg:city":"New York",
    "sg:classifiers":[
        {
            "category":"Restaurant",
            "type":"Food & Drink"
        }
    ],
    "sg:phone":"+1   ",
    "sg:postcode":"10027",
    "sg:province":"NY",
    "sg:tags":[
        "lounge",
        "cocktail"
    ],
    "wof:name":"West End Cafe",
    "wof:placetype":"venue"
},
  "geometry": {"coordinates":[-73.962058,40.810535],"type":"Point"}
}