{
  "type": "Feature",
  "properties": {
    "addr:full":"1223 E 72nd St Brooklyn NY 11234",
    "addr:housenumber":"1223",
    "addr:postcode":"11234",
    "addr:street":"E 72Nd St",
    "iso:country":"US",
    "sg:address":"1223 E 72nd St",
    "sg:city":"Brooklyn",
    "sg:classifiers":[
        {
            "category":"Shopping",
            "subcategory":"Gifts & Souvenirs",
            "type":"Retail Goods"
        }
    ],
    "sg:phone":"+1   ",
    "sg:postcode":"11234",
    "sg:province":"NY",
    "wof:name":"Merville Gift Bakers",
    "wof:placetype":"venue"
},
  "geometry": {"coordinates":[-73.912493,40.625446],"type":"Point"}
}