{
  "type": "Feature",
  "properties": {
    "addr:full":"30 Central Park South Manhattan NY 10019",
    "addr:housenumber":"30",
    "addr:postcode":"10019",
    "addr:street":"Central Park South",
    "iso:country":"US",
    "sg:address":"30 Central Park South",
    "sg:city":"Manhattan",
    "sg:classifiers":[
        {
            "category":"Health Services",
            "subcategory":"Dentist",
            "type":"Services"
        }
    ],
    "sg:phone":"+1 212 702 8675",
    "sg:postcode":"10019",
    "sg:province":"NY",
    "wof:name":"Maiko Tomizawa, DDS",
    "wof:placetype":"venue"
},
  "geometry": {"coordinates":[-73.975173,40.764822],"type":"Point"}
}