{
  "type": "Feature",
  "properties": {
    "iso:country":"US",
    "sg:address":"2285 Crompond Rd",
    "sg:city":"Cortlandt Manor",
    "sg:classifiers":[
        {
            "category":"Retail",
            "subcategory":"Auto Repair",
            "type":"Services"
        }
    ],
    "sg:phone":"+1 914 737 0500",
    "sg:postcode":"10567",
    "sg:province":"NY",
    "sg:tags":[
        "repairing",
        "automobile"
    ],
    "wof:name":"A A Auto Tech Ctr",
    "wof:placetype":"venue"
},
  "geometry": {"coordinates":[-73.881314,41.292407],"type":"Point"}
}