{
  "type": "Feature",
  "properties": {
    "addr:full":"6655 Old Thompson Rd Syracuse NY 13211",
    "addr:housenumber":"6655",
    "addr:postcode":"13211",
    "addr:street":"Old Thompson Rd",
    "iso:country":"US",
    "sg:address":"6655 Old Thompson Rd",
    "sg:city":"Syracuse",
    "sg:classifiers":[
        {
            "category":"Sports & Exercise",
            "subcategory":"Golf",
            "type":"Entertainment"
        }
    ],
    "sg:phone":"+1 315 463 1831",
    "sg:postcode":"13211",
    "sg:province":"NY",
    "sg:tags":[
        "course",
        "public"
    ],
    "wof:name":"Brooklawn Golf Course",
    "wof:placetype":"venue"
},
  "geometry": {"coordinates":[-76.09592600000001,43.095095],"type":"Point"}
}