{
  "type": "Feature",
  "properties": {
    "addr:full":"2059 Connecticut Ave Niagara Falls NY 14305",
    "addr:housenumber":"2059",
    "addr:postcode":"14305",
    "addr:street":"Connecticut Ave",
    "iso:country":"US",
    "sg:address":"2059 Connecticut Ave",
    "sg:city":"Niagara Falls",
    "sg:classifiers":[
        {
            "category":"Building & Trades",
            "subcategory":"Construction",
            "type":"Services"
        }
    ],
    "sg:phone":"+1 716 282 7235",
    "sg:postcode":"14305",
    "sg:province":"NY",
    "sg:tags":[
        "painter"
    ],
    "wof:name":"Ec Naughton Painting",
    "wof:placetype":"venue"
},
  "geometry": {"coordinates":[-79.03653799999999,43.119163],"type":"Point"}
}