{
  "type": "Feature",
  "properties": {
    "iso:country":"US",
    "sg:address":"144 Sherman Ave",
    "sg:city":"New York",
    "sg:classifiers":[
        {
            "category":"Food & Beverages",
            "subcategory":"Groceries & Convenience Stores",
            "type":"Retail Goods"
        }
    ],
    "sg:phone":"+1 212 942 0701",
    "sg:postcode":"10034",
    "sg:province":"NY",
    "wof:name":"Henriquez Minimarket",
    "wof:placetype":"venue"
},
  "geometry": {"coordinates":[-73.92198399999999,40.865134],"type":"Point"}
}