{
  "type": "Feature",
  "properties": {
    "addr:full":"104 Jefferson Ave North Bellmore NY 11710",
    "addr:housenumber":"104",
    "addr:postcode":"11710",
    "addr:street":"Jefferson Ave North",
    "iso:country":"US",
    "sg:address":"104 Jefferson Ave",
    "sg:city":"North Bellmore",
    "sg:classifiers":[
        {
            "category":"Building & Trades",
            "subcategory":"Construction",
            "type":"Services"
        }
    ],
    "sg:phone":"+1 516 557 2755",
    "sg:postcode":"11710",
    "sg:province":"NY",
    "sg:tags":[
        "contractor"
    ],
    "wof:name":"Odd Job",
    "wof:placetype":"venue"
},
  "geometry": {"coordinates":[-73.535596,40.676596],"type":"Point"}
}