{
  "type": "Feature",
  "properties": {
    "iso:country":"US",
    "sg:address":"1327 County Line Rd",
    "sg:city":"Darien Center",
    "sg:classifiers":[
        {
            "category":"Building & Trades",
            "subcategory":"Landscaping Services",
            "type":"Services"
        }
    ],
    "sg:phone":"+1 585 937 7741",
    "sg:postcode":"14040",
    "sg:province":"NY",
    "sg:tags":[
        "electrical",
        "contractor"
    ],
    "wof:name":"Spring Creek Construction",
    "wof:placetype":"venue"
},
  "geometry": {"coordinates":[-78.39036299999999,42.868358],"type":"Point"}
}