{
  "type": "Feature",
  "properties": {
    "addr:full":"7 Dalston Cir. Lynbrook NY 11563",
    "addr:housenumber":"7",
    "addr:postcode":"11563",
    "addr:street":"Dalston Cir.",
    "iso:country":"US",
    "sg:address":"7 Dalston Cir.",
    "sg:city":"Lynbrook",
    "sg:classifiers":[
        {
            "category":"Building & Trades",
            "subcategory":"Construction",
            "type":"Services"
        }
    ],
    "sg:phone":"+1 516 849 3469",
    "sg:postcode":"11563",
    "sg:province":"NY",
    "sg:tags":[
        "roofing",
        "industrial",
        "contractors-commercial"
    ],
    "wof:name":"Brothers Roofing Company",
    "wof:placetype":"venue"
},
  "geometry": {"coordinates":[-73.672112,40.668598],"type":"Point"}
}