{
  "type": "Feature",
  "properties": {
    "addr:full":"501 Frank Sottile Blvd Kingston NY 12401",
    "addr:housenumber":"501",
    "addr:postcode":"12401",
    "addr:street":"Frank Sottile Blvd",
    "iso:country":"US",
    "sg:address":"501 Frank Sottile Blvd",
    "sg:city":"Kingston",
    "sg:phone":"+1 845 336 0485",
    "sg:postcode":"12401",
    "sg:province":"NY",
    "sg:website":"http://www.petsmart.com",
    "wof:name":"PetSmart",
    "wof:placetype":"venue"
},
  "geometry": {"coordinates":[-73.985862,41.970255],"type":"Point"}
}