{
  "type": "Feature",
  "properties": {
    "addr:full":"23 Buckout Rd White Plains NY 10604",
    "addr:housenumber":"23",
    "addr:postcode":"10604",
    "addr:street":"Buckout Rd",
    "iso:country":"US",
    "sg:address":"23 Buckout Rd",
    "sg:city":"White Plains",
    "sg:classifiers":[
        {
            "category":"Building & Trades",
            "subcategory":"Landscaping Services",
            "type":"Services"
        }
    ],
    "sg:phone":"+1 914 761 7648",
    "sg:postcode":"10604",
    "sg:province":"NY",
    "sg:tags":[
        "ho",
        "landscape"
    ],
    "wof:name":"Espaces Verts Inc",
    "wof:placetype":"venue"
},
  "geometry": {"coordinates":[-73.737315,41.054152],"type":"Point"}
}