{
  "type": "Feature",
  "properties": {
    "addr:full":"81 Union Center Rd Ulster Park NY 12487",
    "addr:housenumber":"81",
    "addr:postcode":"12487",
    "addr:street":"Union Center Rd",
    "iso:country":"US",
    "sg:address":"81 Union Center Rd",
    "sg:city":"Ulster Park",
    "sg:classifiers":[
        {
            "category":"Building & Trades",
            "subcategory":"Construction",
            "type":"Services"
        }
    ],
    "sg:phone":"+1 845 338 0069",
    "sg:postcode":"12487",
    "sg:province":"NY",
    "sg:tags":[
        "excavation",
        "contractor"
    ],
    "wof:name":"C P S Excavating Co Inc",
    "wof:placetype":"venue"
},
  "geometry": {"coordinates":[-74.018294,41.869959],"type":"Point"}
}