{
  "type": "Feature",
  "properties": {
    "addr:full":"310 W 56th St New York NY 10019",
    "addr:housenumber":"310",
    "addr:postcode":"10019",
    "addr:street":"W 56Th St",
    "iso:country":"US",
    "sg:address":"310 W 56th St",
    "sg:city":"New York",
    "sg:classifiers":[
        {
            "category":"Health Services",
            "subcategory":"Doctor",
            "type":"Services"
        }
    ],
    "sg:phone":"+1 212 262 2049",
    "sg:postcode":"10019",
    "sg:province":"NY",
    "wof:name":"Narula Rajiv MD",
    "wof:placetype":"venue"
},
  "geometry": {"coordinates":[-73.983704,40.766102],"type":"Point"}
}