{
  "type": "Feature",
  "properties": {
    "addr:full":"199 Brower Ave Rockville Centre NY 11570",
    "addr:housenumber":"199",
    "addr:postcode":"11570",
    "addr:street":"Brower Ave",
    "iso:country":"US",
    "sg:address":"199 Brower Ave",
    "sg:city":"Rockville Centre",
    "sg:classifiers":[
        {
            "category":"Building & Trades",
            "subcategory":"Cleaning & Sanitation",
            "type":"Services"
        }
    ],
    "sg:phone":"+1 516 678 0878",
    "sg:postcode":"11570",
    "sg:province":"NY",
    "sg:tags":[
        "carpet"
    ],
    "wof:name":"Steprac Carpet Cleaning Inc",
    "wof:placetype":"venue"
},
  "geometry": {"coordinates":[-73.631989,40.665223],"type":"Point"}
}