{
  "type": "Feature",
  "properties": {
    "addr:full":"369 W 35 St New York NY 10001",
    "addr:housenumber":"369",
    "addr:postcode":"10001",
    "addr:street":"W 35 St",
    "iso:country":"US",
    "sg:address":"369 W 35 St",
    "sg:city":"New York",
    "sg:classifiers":[
        {
            "category":"Professional",
            "type":"Services"
        }
    ],
    "sg:phone":"+1   ",
    "sg:postcode":"10001",
    "sg:province":"NY",
    "wof:name":"Igor Doran",
    "wof:placetype":"venue"
},
  "geometry": {"coordinates":[-73.994287,40.753287],"type":"Point"}
}