{
  "type": "Feature",
  "properties": {
    "iso:country":"US",
    "sg:address":"12420 Liberty Ave",
    "sg:city":"South Richmond Hill",
    "sg:classifiers":[
        {
            "category":"Food & Beverages",
            "subcategory":"Groceries & Convenience Stores",
            "type":"Retail Goods"
        }
    ],
    "sg:phone":"+1 718 848 8335",
    "sg:postcode":"11419",
    "sg:province":"NY",
    "wof:name":"N & R Corp",
    "wof:placetype":"venue"
},
  "geometry": {"coordinates":[-73.81950399999999,40.687901],"type":"Point"}
}