{
  "type": "Feature",
  "properties": {
    "addr:full":"21 Snyder Ave Brooklyn NY 11226",
    "addr:housenumber":"21",
    "addr:postcode":"11226",
    "addr:street":"Snyder Ave",
    "iso:country":"US",
    "sg:address":"21 Snyder Ave",
    "sg:city":"Brooklyn",
    "sg:classifiers":[
        {
            "category":"Health Services",
            "subcategory":"Doctor",
            "type":"Services"
        }
    ],
    "sg:phone":"+1 718 826 2942",
    "sg:postcode":"11226",
    "sg:province":"NY",
    "sg:website":"www.cwha.org",
    "wof:name":"Caribbean Women's Health Association",
    "wof:placetype":"venue"
},
  "geometry": {"coordinates":[-73.95735500000001,40.648585],"type":"Point"}
}