{
  "type": "Feature",
  "properties": {
    "addr:full":"67 Aspen Cir Albany NY 12208",
    "addr:housenumber":"67",
    "addr:postcode":"12208",
    "addr:street":"Aspen Cir",
    "iso:country":"US",
    "sg:address":"67 Aspen Cir",
    "sg:city":"Albany",
    "sg:classifiers":[
        {
            "category":"Restaurant",
            "type":"Food & Drink"
        },
        {
            "category":"Food & Beverages",
            "subcategory":"Groceries & Convenience Stores",
            "type":"Retail Goods"
        }
    ],
    "sg:phone":"+1 518 786 7827",
    "sg:postcode":"12208",
    "sg:province":"NY",
    "sg:tags":[
        "shop",
        "sandwich"
    ],
    "wof:name":"Tylaina Subs Inc.",
    "wof:placetype":"venue"
},
  "geometry": {"coordinates":[-73.819,42.664323],"type":"Point"}
}