{
  "type": "Feature",
  "properties": {
    "addr:full":"68 78th St Middle Village NY 11379",
    "addr:housenumber":"68",
    "addr:postcode":"11379",
    "addr:street":"78Th St",
    "iso:country":"US",
    "sg:address":"68 78th St",
    "sg:city":"Middle Village",
    "sg:classifiers":[
        {
            "category":"Utilities",
            "subcategory":"Fuel Oil & Lpg",
            "type":"Services"
        }
    ],
    "sg:phone":"+1   ",
    "sg:postcode":"11379",
    "sg:province":"NY",
    "wof:name":"Ever-Riye Fuel",
    "wof:placetype":"venue"
},
  "geometry": {"coordinates":[-73.883653,40.72815],"type":"Point"}
}