{
  "type": "Feature",
  "properties": {
    "iso:country":"US",
    "sg:address":"395 Fort Salonga Rd",
    "sg:city":"Northport",
    "sg:classifiers":[
        {
            "category":"Shopping",
            "type":"Retail Goods"
        }
    ],
    "sg:phone":"+1 631 754 1919",
    "sg:postcode":"11768",
    "sg:province":"NY",
    "sg:tags":[
        "pet",
        "shop"
    ],
    "wof:name":"Town & Country Pet Food",
    "wof:placetype":"venue"
},
  "geometry": {"coordinates":[-73.341309,40.891937],"type":"Point"}
}