{
  "type": "Feature",
  "properties": {
    "addr:full":"121 Dyckman St New York NY 10040",
    "addr:housenumber":"121",
    "addr:postcode":"10040",
    "addr:street":"Dyckman St",
    "iso:country":"US",
    "sg:address":"121 Dyckman St",
    "sg:city":"New York",
    "sg:classifiers":[
        {
            "category":"Travel",
            "subcategory":"Travel Agent",
            "type":"Entertainment"
        }
    ],
    "sg:phone":"+1 212 569 6669",
    "sg:postcode":"10040",
    "sg:province":"NY",
    "sg:tags":[
        "agency",
        "bureau"
    ],
    "wof:name":"Mony Travel Svc",
    "wof:placetype":"venue"
},
  "geometry": {"coordinates":[-73.924922,40.861821],"type":"Point"}
}