{
  "type": "Feature",
  "properties": {
    "iso:country":"US",
    "sg:address":"21 Aviation Rd",
    "sg:city":"Albany",
    "sg:classifiers":[
        {
            "category":"Organizations",
            "subcategory":"Professional Association",
            "type":"Services"
        }
    ],
    "sg:phone":"+1 518 446 1483",
    "sg:postcode":"12205",
    "sg:province":"NY",
    "sg:tags":[
        "hospice",
        "health",
        "for",
        "care"
    ],
    "wof:name":"Hospice and Palliative Care As",
    "wof:placetype":"venue"
},
  "geometry": {"coordinates":[-73.80292300000001,42.715975],"type":"Point"}
}