{
  "type": "Feature",
  "properties": {
    "addr:full":"2655 Richmond Avenue Staten Island NY 10314",
    "addr:housenumber":"2655",
    "addr:postcode":"10314",
    "addr:street":"Richmond Avenue",
    "iso:country":"US",
    "sg:address":"2655 Richmond Avenue",
    "sg:city":"Staten Island",
    "sg:classifiers":[
        {
            "category":"Shopping",
            "subcategory":"Department Store",
            "type":"Retail Goods"
        }
    ],
    "sg:phone":"+1 718 761 3000",
    "sg:postcode":"10314",
    "sg:province":"NY",
    "wof:name":"T-Mobile",
    "wof:placetype":"venue"
},
  "geometry": {"coordinates":[-74.16469186090001,40.581413538],"type":"Point"}
}