{
  "type": "Feature",
  "properties": {
    "addr:full":"11 Cass Ct Ballston Lake NY 12019",
    "addr:housenumber":"11",
    "addr:postcode":"12019",
    "addr:street":"Cass Ct",
    "iso:country":"US",
    "sg:address":"11 Cass Ct",
    "sg:city":"Ballston Lake",
    "sg:classifiers":[
        {
            "category":"Manufacturing",
            "subcategory":"Printing",
            "type":"Manufacturing & Wholesale Goods"
        }
    ],
    "sg:phone":"+1 518 899 5047",
    "sg:postcode":"12019",
    "sg:province":"NY",
    "sg:tags":[
        "publisher"
    ],
    "wof:name":"CTB Mc Graw-Hill",
    "wof:placetype":"venue"
},
  "geometry": {"coordinates":[-73.81370200000001,42.931644],"type":"Point"}
}