{
  "type": "Feature",
  "properties": {
    "iso:country":"US",
    "sg:address":"84 Bowery Street",
    "sg:city":"New York",
    "sg:classifiers":[
        {
            "category":"Shopping",
            "subcategory":"Jewelry",
            "type":"Retail Goods"
        }
    ],
    "sg:phone":"+1 212 966 1136",
    "sg:postcode":"10013",
    "sg:province":"NY",
    "wof:name":"Paisano Watch and Jewelry",
    "wof:placetype":"venue"
},
  "geometry": {"coordinates":[-73.995896,40.717134],"type":"Point"}
}