{
  "type": "Feature",
  "properties": {
    "addr:full":"750 3rd Avenue New York NY 10017",
    "addr:housenumber":"750",
    "addr:postcode":"10017",
    "addr:street":"3Rd Avenue",
    "iso:country":"US",
    "sg:address":"750 3rd Avenue",
    "sg:city":"New York",
    "sg:classifiers":[
        {
            "category":"Professional",
            "subcategory":"Lawyer & Legal Services",
            "type":"Services"
        }
    ],
    "sg:phone":"+1 212 983 1999",
    "sg:postcode":"10017",
    "sg:province":"NY",
    "sg:tags":[
        "divorce",
        "law",
        "family"
    ],
    "wof:name":"Rothman Bernard",
    "wof:placetype":"venue"
},
  "geometry": {"coordinates":[-73.972273,40.753762],"type":"Point"}
}