{
  "type": "Feature",
  "properties": {
    "addr:full":"650 Waring Ave Bronx NY 10467",
    "addr:housenumber":"650",
    "addr:postcode":"10467",
    "addr:street":"Waring Ave",
    "iso:country":"US",
    "sg:address":"650 Waring Ave",
    "sg:city":"Bronx",
    "sg:classifiers":[
        {
            "category":"Education",
            "subcategory":"School",
            "type":"Public Place"
        }
    ],
    "sg:phone":"+1 718 652 4959",
    "sg:postcode":"10467",
    "sg:province":"NY",
    "wof:name":"Public School 96",
    "wof:placetype":"venue"
},
  "geometry": {"coordinates":[-73.86849599999999,40.861363],"type":"Point"}
}