{
  "type": "Feature",
  "properties": {
    "addr:full":"922 Cortelyou Rd Brooklyn NY 11218",
    "addr:housenumber":"922",
    "addr:postcode":"11218",
    "addr:street":"Cortelyou Rd",
    "iso:country":"US",
    "sg:address":"922 Cortelyou Rd",
    "sg:city":"Brooklyn",
    "sg:classifiers":[
        {
            "category":"Building & Trades",
            "subcategory":"Construction",
            "type":"Services"
        }
    ],
    "sg:phone":"+1 718 941 4048",
    "sg:postcode":"11218",
    "sg:province":"NY",
    "sg:tags":[
        "contractor"
    ],
    "wof:name":"Irg Construction",
    "wof:placetype":"venue"
},
  "geometry": {"coordinates":[-73.968897,40.638916],"type":"Point"}
}