{
  "type": "Feature",
  "properties": {
    "addr:full":"552 W 43rd St New York NY 10036",
    "addr:housenumber":"552",
    "addr:postcode":"10036",
    "addr:street":"W 43Rd St",
    "iso:country":"US",
    "sg:address":"552 W 43rd St",
    "sg:city":"New York",
    "sg:classifiers":[
        {
            "category":"Communications",
            "subcategory":"Film & Video Production",
            "type":"Services"
        }
    ],
    "sg:phone":"+1 212 594 2521",
    "sg:postcode":"10036",
    "sg:province":"NY",
    "sg:tags":[
        "motion"
    ],
    "wof:name":"Agl International Inc",
    "wof:placetype":"venue"
},
  "geometry": {"coordinates":[-73.99715,40.76104],"type":"Point"}
}