{
  "type": "Feature",
  "properties": {
    "addr:full":"5256 Sunrise Hwy Massapequa Park NY 11762",
    "addr:housenumber":"5256",
    "addr:postcode":"11762",
    "addr:street":"Sunrise Hwy",
    "iso:country":"US",
    "sg:address":"5256 Sunrise Hwy",
    "sg:city":"Massapequa Park",
    "sg:classifiers":[
        {
            "category":"Utilities",
            "subcategory":"Mobile Phone",
            "type":"Services"
        }
    ],
    "sg:phone":"+1 516 798 0721",
    "sg:postcode":"11762",
    "sg:province":"NY",
    "sg:tags":[
        "telephone",
        "cellular"
    ],
    "wof:name":"Nextel Communications Inc",
    "wof:placetype":"venue"
},
  "geometry": {"coordinates":[-73.44268700000001,40.678177],"type":"Point"}
}