{
  "type": "Feature",
  "properties": {
    "iso:country":"US",
    "sg:address":"90 Alpha Plz",
    "sg:city":"Hicksville",
    "sg:classifiers":[
        {
            "category":"Building & Trades",
            "subcategory":"Construction",
            "type":"Services"
        }
    ],
    "sg:phone":"+1 516 735 5178",
    "sg:postcode":"11801",
    "sg:province":"NY",
    "sg:tags":[
        "siding",
        "contractor"
    ],
    "wof:name":"New World Siding",
    "wof:placetype":"venue"
},
  "geometry": {"coordinates":[-73.545136,40.765616],"type":"Point"}
}