{
  "type": "Feature",
  "properties": {
    "addr:full":"210 W 94 St New York NY 10025",
    "addr:housenumber":"210",
    "addr:postcode":"10025",
    "addr:street":"W 94 St",
    "iso:country":"US",
    "sg:address":"210 W 94 St",
    "sg:city":"New York",
    "sg:classifiers":[
        {
            "category":"Food & Beverages",
            "subcategory":"Groceries & Convenience Stores",
            "type":"Retail Goods"
        }
    ],
    "sg:phone":"+1   ",
    "sg:postcode":"10025",
    "sg:province":"NY",
    "wof:name":"Shop & Save Food Market",
    "wof:placetype":"venue"
},
  "geometry": {"coordinates":[-73.97255,40.793162],"type":"Point"}
}