{
  "type": "Feature",
  "properties": {
    "addr:full":"176 Franklin St Franklin Square NY 11010",
    "addr:housenumber":"176",
    "addr:postcode":"11010",
    "addr:street":"Franklin St",
    "iso:country":"US",
    "sg:address":"176 Franklin St",
    "sg:city":"Franklin Square",
    "sg:classifiers":[
        {
            "category":"Retail",
            "subcategory":"Repair Shop",
            "type":"Services"
        }
    ],
    "sg:phone":"+1 516 616 1961",
    "sg:postcode":"11010",
    "sg:province":"NY",
    "sg:tags":[
        "television",
        "radio"
    ],
    "wof:name":"A Young Electronics",
    "wof:placetype":"venue"
},
  "geometry": {"coordinates":[-73.67428,40.710239],"type":"Point"}
}