{
  "type": "Feature",
  "properties": {
    "addr:full":"356 E 51st St New York NY 10022",
    "addr:housenumber":"356",
    "addr:postcode":"10022",
    "addr:street":"E 51St St",
    "iso:country":"US",
    "sg:address":"356 E 51st St",
    "sg:city":"New York",
    "sg:classifiers":[
        {
            "category":"Restaurant",
            "type":"Food & Drink"
        }
    ],
    "sg:phone":"+1 212 230 1117",
    "sg:postcode":"10022",
    "sg:province":"NY",
    "sg:tags":[
        "french"
    ],
    "wof:name":"Deux Amis",
    "wof:placetype":"venue"
},
  "geometry": {"coordinates":[-73.966003,40.754501],"type":"Point"}
}