{
  "type": "Feature",
  "properties": {
    "iso:country":"US",
    "sg:address":"987 Steele Blvd",
    "sg:city":"Baldwin",
    "sg:classifiers":[
        {
            "category":"Autos & Motor Vehicles",
            "subcategory":"Fuel & Gas Station",
            "type":"Retail Goods"
        }
    ],
    "sg:phone":"+1 516 223 8888",
    "sg:postcode":"11510",
    "sg:province":"NY",
    "sg:tags":[
        "oil"
    ],
    "wof:name":"Baldwin Service Station",
    "wof:placetype":"venue"
},
  "geometry": {"coordinates":[-73.605487,40.638143],"type":"Point"}
}