{
  "type": "Feature",
  "properties": {
    "iso:country":"US",
    "sg:address":"238 E 20th Rd",
    "sg:city":"Far Rockaway",
    "sg:classifiers":[
        {
            "category":"Health Services",
            "subcategory":"Doctor",
            "type":"Services"
        }
    ],
    "sg:phone":"+1 718 868 3131",
    "sg:postcode":"11693",
    "sg:province":"NY",
    "sg:tags":[
        "physician"
    ],
    "wof:name":"South Island Medical Assoc PC",
    "wof:placetype":"venue"
},
  "geometry": {"coordinates":[-73.82008399999999,40.598745],"type":"Point"}
}