{
  "type": "Feature",
  "properties": {
    "iso:country":"US",
    "sg:address":"4 Richard Somers Rd",
    "sg:city":"Granite Springs",
    "sg:classifiers":[
        {
            "category":"Professional",
            "subcategory":"Management & Consulting",
            "type":"Services"
        }
    ],
    "sg:phone":"+1 914 954 6647",
    "sg:postcode":"10527",
    "sg:province":"NY",
    "sg:tags":[
        "construction"
    ],
    "wof:name":"Topper Innovations Llc",
    "wof:placetype":"venue"
},
  "geometry": {"coordinates":[-73.75176,41.312481],"type":"Point"}
}