{
  "type": "Feature",
  "properties": {
    "iso:country":"US",
    "sg:address":"190 Beechwood Ave",
    "sg:city":"Poughkeepsie",
    "sg:classifiers":[
        {
            "category":"Shopping",
            "subcategory":"Used Merchandise",
            "type":"Retail Goods"
        }
    ],
    "sg:phone":"+1   ",
    "sg:postcode":"12601",
    "sg:province":"NY",
    "sg:tags":[
        "computer"
    ],
    "wof:name":"Pcse Inc",
    "wof:placetype":"venue"
},
  "geometry": {"coordinates":[-73.925426,41.672754],"type":"Point"}
}