{
  "type": "Feature",
  "properties": {
    "iso:country":"US",
    "sg:address":"8 W 58th Street",
    "sg:city":"New York",
    "sg:classifiers":[
        {
            "category":"Restaurant",
            "type":"Food & Drink"
        }
    ],
    "sg:phone":"+1 212 750 7474",
    "sg:postcode":"10019",
    "sg:province":"NY",
    "wof:name":"Jack's Fifth",
    "wof:placetype":"venue"
},
  "geometry": {"coordinates":[-73.974673,40.76427],"type":"Point"}
}