{
  "type": "Feature",
  "properties": {
    "addr:full":"149 Whitney St Rochester NY 14606",
    "addr:housenumber":"149",
    "addr:postcode":"14606",
    "addr:street":"Whitney St",
    "iso:country":"US",
    "sg:address":"149 Whitney St",
    "sg:city":"Rochester",
    "sg:classifiers":[
        {
            "category":"Professional",
            "subcategory":"Art Services",
            "type":"Services"
        }
    ],
    "sg:phone":"+1 585 586 2905",
    "sg:postcode":"14606",
    "sg:province":"NY",
    "sg:tags":[
        "graphic",
        "designer"
    ],
    "wof:name":"Casella Design",
    "wof:placetype":"venue"
},
  "geometry": {"coordinates":[-77.636718,43.160005],"type":"Point"}
}