{
  "type": "Feature",
  "properties": {
    "iso:country":"US",
    "sg:address":"1010 Wayne St",
    "sg:city":"Olean",
    "sg:classifiers":[
        {
            "category":"Social Services",
            "subcategory":"Child Care",
            "type":"Services"
        }
    ],
    "sg:phone":"+1   ",
    "sg:postcode":"14760",
    "sg:province":"NY",
    "sg:tags":[
        "day"
    ],
    "wof:name":"Child Care Resources",
    "wof:placetype":"venue"
},
  "geometry": {"coordinates":[-78.442221,42.085201],"type":"Point"}
}