{
  "type": "Feature",
  "properties": {
    "iso:country":"US",
    "sg:address":"20 Kensico Rd",
    "sg:city":"Thornwood",
    "sg:classifiers":[
        {
            "category":"Autos & Motor Vehicles",
            "subcategory":"Fuel & Gas Station",
            "type":"Retail Goods"
        }
    ],
    "sg:phone":"+1   ",
    "sg:postcode":"10594",
    "sg:province":"NY",
    "sg:tags":[
        "station",
        "gasoline"
    ],
    "wof:name":"Citgo",
    "wof:placetype":"venue"
},
  "geometry": {"coordinates":[-73.77833,41.12327],"type":"Point"}
}