{
  "type": "Feature",
  "properties": {
    "addr:full":"1621 Lexington Avenue New York NY 10029",
    "addr:housenumber":"1621",
    "addr:postcode":"10029",
    "addr:street":"Lexington Avenue",
    "iso:country":"US",
    "sg:address":"1621 Lexington Avenue",
    "sg:city":"New York",
    "sg:classifiers":[
        {
            "category":"Food & Beverages",
            "subcategory":"Ethnic Foods",
            "type":"Retail Goods"
        },
        {
            "category":"Food & Beverages",
            "subcategory":"Groceries & Convenience Stores",
            "type":"Retail Goods"
        }
    ],
    "sg:phone":"+1 212 987 8364",
    "sg:postcode":"10029",
    "sg:province":"NY",
    "wof:name":"El Tepeyac Grocery",
    "wof:placetype":"venue"
},
  "geometry": {"coordinates":[-73.94798400000001,40.789873],"type":"Point"}
}