{
  "type": "Feature",
  "properties": {
    "addr:full":"1830 Lexington Ave New York NY 10029",
    "addr:housenumber":"1830",
    "addr:postcode":"10029",
    "addr:street":"Lexington Ave",
    "iso:country":"US",
    "sg:address":"1830 Lexington Ave",
    "sg:city":"New York",
    "sg:classifiers":[
        {
            "category":"Wholesale",
            "subcategory":"Non-durable Goods",
            "type":"Manufacturing & Wholesale Goods"
        }
    ],
    "sg:phone":"+1 212 426 3168",
    "sg:postcode":"10029",
    "sg:province":"NY",
    "wof:name":"Yi Xing Trading Inc",
    "wof:placetype":"venue"
},
  "geometry": {"coordinates":[-73.943392,40.796195],"type":"Point"}
}