{
  "type": "Feature",
  "properties": {
    "addr:full":"52 E Fordham Rd Bronx NY 10468",
    "addr:housenumber":"52",
    "addr:postcode":"10468",
    "addr:street":"E Fordham Rd",
    "iso:country":"US",
    "sg:address":"52 E Fordham Rd",
    "sg:city":"Bronx",
    "sg:classifiers":[
        {
            "category":"Shopping",
            "subcategory":"Clothing, Apparel, & Fashions",
            "type":"Retail Goods"
        }
    ],
    "sg:phone":"+1   ",
    "sg:postcode":"10468",
    "sg:province":"NY",
    "sg:tags":[
        "uniform",
        "sportswear",
        "intimate"
    ],
    "wof:name":"Pandora",
    "wof:placetype":"venue"
},
  "geometry": {"coordinates":[-73.900006,40.862289],"type":"Point"}
}