{
  "type": "Feature",
  "properties": {
    "addr:full":"1700 Western Ave Albany NY 12203",
    "addr:housenumber":"1700",
    "addr:postcode":"12203",
    "addr:street":"Western Ave",
    "iso:country":"US",
    "sg:address":"1700 Western Ave",
    "sg:city":"Albany",
    "sg:classifiers":[
        {
            "category":"Organizations",
            "subcategory":"Community Association",
            "type":"Services"
        }
    ],
    "sg:phone":"+1   ",
    "sg:postcode":"12203",
    "sg:province":"NY",
    "wof:name":"Nfl Alumni Albany Chapter",
    "wof:placetype":"venue"
},
  "geometry": {"coordinates":[-73.85774000000001,42.687545],"type":"Point"}
}