{
  "type": "Feature",
  "properties": {
    "iso:country":"US",
    "sg:address":"31 Kent Dr",
    "sg:city":"Victor",
    "sg:classifiers":[
        {
            "category":"Shopping",
            "subcategory":"Crafts & Fabrics",
            "type":"Retail Goods"
        }
    ],
    "sg:phone":"+1   ",
    "sg:postcode":"14564",
    "sg:province":"NY",
    "sg:tags":[
        "sewing"
    ],
    "wof:name":"Healthylivinglifestylecom",
    "wof:placetype":"venue"
},
  "geometry": {"coordinates":[-77.399109,42.982655],"type":"Point"}
}