{
  "type": "Feature",
  "properties": {
    "addr:full":"2095 E Henrietta Rd Rochester NY 14623",
    "addr:housenumber":"2095",
    "addr:postcode":"14623",
    "addr:street":"E Henrietta Rd",
    "iso:country":"US",
    "sg:address":"2095 E Henrietta Rd",
    "sg:city":"Rochester",
    "sg:classifiers":[
        {
            "category":"Restaurant",
            "type":"Food & Drink"
        }
    ],
    "sg:menulink":"http://www.allmenus.com/ny/henrietta/18572-dominos-pizza/menu/",
    "sg:phone":"+1 585 359 3330",
    "sg:postcode":"14623",
    "sg:province":"NY",
    "sg:tags":[
        "american",
        "wing",
        "pizza"
    ],
    "wof:name":"Domino's Pizza",
    "wof:placetype":"venue"
},
  "geometry": {"coordinates":[-77.606751,43.076816],"type":"Point"}
}