{
  "type": "Feature",
  "properties": {
    "iso:country":"US",
    "sg:address":"424 East 92nd St",
    "sg:city":"Manhattan",
    "sg:classifiers":[
        {
            "category":"Retail",
            "subcategory":"Veterinary Services",
            "type":"Services"
        }
    ],
    "sg:phone":"+1 212 876 7700",
    "sg:postcode":"10128",
    "sg:province":"NY",
    "sg:tags":[
        "veterinarian"
    ],
    "wof:name":"Dr. Nicole V. Coates",
    "wof:placetype":"venue"
},
  "geometry": {"coordinates":[-73.945684,40.780045],"type":"Point"}
}