{
  "type": "Feature",
  "properties": {
    "iso:country":"US",
    "sg:address":"1511 Wilkinson Ave",
    "sg:city":"Bronx",
    "sg:classifiers":[
        {
            "category":"Professional",
            "type":"Services"
        }
    ],
    "sg:phone":"+1 718 822 8208",
    "sg:postcode":"10461",
    "sg:province":"NY",
    "sg:tags":[
        "establishment"
    ],
    "wof:name":"E R Bar Inc",
    "wof:placetype":"venue"
},
  "geometry": {"coordinates":[-73.84268,40.852915],"type":"Point"}
}