{
  "type": "Feature",
  "properties": {
    "addr:full":"577 Marcy Ave Brooklyn NY 11206",
    "addr:housenumber":"577",
    "addr:postcode":"11206",
    "addr:street":"Marcy Ave",
    "iso:country":"US",
    "sg:address":"577 Marcy Ave",
    "sg:city":"Brooklyn",
    "sg:classifiers":[
        {
            "category":"Autos & Motor Vehicles",
            "subcategory":"Fuel & Gas Station",
            "type":"Retail Goods"
        }
    ],
    "sg:phone":"+1   ",
    "sg:postcode":"11206",
    "sg:province":"NY",
    "sg:tags":[
        "station",
        "gasoline"
    ],
    "wof:name":"Amoco",
    "wof:placetype":"venue"
},
  "geometry": {"coordinates":[-73.94906,40.694637],"type":"Point"}
}