{
  "type": "Feature",
  "properties": {
    "iso:country":"US",
    "sg:address":"586 E 187th Street",
    "sg:city":"Bronx",
    "sg:classifiers":[
        {
            "category":"Shopping",
            "subcategory":"Bicycles & Sporting Goods",
            "type":"Retail Goods"
        }
    ],
    "sg:phone":"+1 718 367 5508",
    "sg:postcode":"10458",
    "sg:province":"NY",
    "sg:website":"www.bgclothes.com",
    "wof:name":"B & G Clothes",
    "wof:placetype":"venue"
},
  "geometry": {"coordinates":[-73.888093,40.855776],"type":"Point"}
}