{
  "type": "Feature",
  "properties": {
    "addr:full":"214 Holbrook Rd Holbrook NY 11741",
    "addr:housenumber":"214",
    "addr:postcode":"11741",
    "addr:street":"Holbrook Rd",
    "iso:country":"US",
    "sg:address":"214 Holbrook Rd",
    "sg:city":"Holbrook",
    "sg:classifiers":[
        {
            "category":"Building & Trades",
            "subcategory":"Plumbing",
            "type":"Services"
        }
    ],
    "sg:phone":"+1 631 467 2515",
    "sg:postcode":"11741",
    "sg:province":"NY",
    "sg:tags":[
        "plumber",
        "industrial",
        "contractors-commercial"
    ],
    "wof:name":"Classic Plumbing Heating",
    "wof:placetype":"venue"
},
  "geometry": {"coordinates":[-73.079063,40.816341],"type":"Point"}
}