{
  "type": "Feature",
  "properties": {
    "addr:full":"40 E 19th St Manhattan NY 10003",
    "addr:housenumber":"40",
    "addr:postcode":"10003",
    "addr:street":"E 19Th St",
    "iso:country":"US",
    "sg:address":"40 E 19th St",
    "sg:city":"Manhattan",
    "sg:classifiers":[
        {
            "category":"Real Estate",
            "subcategory":"Real Estate Operator",
            "type":"Services"
        },
        {
            "category":"Home & Garden",
            "subcategory":"Home Furnishings",
            "type":"Retail Goods"
        },
        {
            "category":"Home & Garden",
            "subcategory":"Furniture",
            "type":"Retail Goods"
        }
    ],
    "sg:phone":"+1 212 796 6926",
    "sg:postcode":"10003",
    "sg:province":"NY",
    "sg:tags":[
        "decor",
        "apartment",
        "store"
    ],
    "sg:website":"www.modani.com",
    "wof:name":"Modern Furniture Store",
    "wof:placetype":"venue"
},
  "geometry": {"coordinates":[-73.989148,40.737922],"type":"Point"}
}