{
  "type": "Feature",
  "properties": {
    "iso:country":"US",
    "sg:address":"797 Bushwick Ave",
    "sg:city":"Brooklyn",
    "sg:classifiers":[
        {
            "category":"Health Services",
            "subcategory":"Clinic",
            "type":"Services"
        }
    ],
    "sg:phone":"+1 718 574 1200",
    "sg:postcode":"11221",
    "sg:province":"NY",
    "sg:tags":[
        "outpatient"
    ],
    "sg:website":"http://www.ci.nyc.ny.us",
    "wof:name":"Community Health Clinic",
    "wof:placetype":"venue"
},
  "geometry": {"coordinates":[-73.928284,40.695129],"type":"Point"}
}