{
  "type": "Feature",
  "properties": {
    "addr:full":"159 E 8th St New York NY 10003",
    "addr:housenumber":"159",
    "addr:postcode":"10003",
    "addr:street":"E 8Th St",
    "iso:country":"US",
    "sg:address":"159 E 8th St",
    "sg:city":"New York",
    "sg:classifiers":[
        {
            "category":"Building & Trades",
            "subcategory":"Locksmith",
            "type":"Services"
        }
    ],
    "sg:phone":"+1 212 918 8587",
    "sg:postcode":"10003",
    "sg:province":"NY",
    "sg:tags":[
        "key"
    ],
    "wof:name":"8th Av Available Towing Towing",
    "wof:placetype":"venue"
},
  "geometry": {"coordinates":[-73.990306,40.729866],"type":"Point"}
}