{
  "type": "Feature",
  "properties": {
    "addr:full":"147 W 35 St New York NY 10001",
    "addr:housenumber":"147",
    "addr:postcode":"10001",
    "addr:street":"W 35 St",
    "iso:country":"US",
    "sg:address":"147 W 35 St",
    "sg:city":"New York",
    "sg:classifiers":[
        {
            "category":"Wholesale",
            "subcategory":"Apparel",
            "type":"Manufacturing & Wholesale Goods"
        }
    ],
    "sg:phone":"+1 212 869 2880",
    "sg:postcode":"10001",
    "sg:province":"NY",
    "sg:tags":[
        "textile",
        "importer"
    ],
    "wof:name":"Asian Silk & Textile Exchange",
    "wof:placetype":"venue"
},
  "geometry": {"coordinates":[-73.989322,40.751291],"type":"Point"}
}