{
  "type": "Feature",
  "properties": {
    "addr:full":"22 Vorndran Dr Wappingers Falls NY 12590",
    "addr:housenumber":"22",
    "addr:postcode":"12590",
    "addr:street":"Vorndran Dr",
    "iso:country":"US",
    "sg:address":"22 Vorndran Dr",
    "sg:city":"Wappingers Falls",
    "sg:classifiers":[
        {
            "category":"Communications",
            "type":"Services"
        }
    ],
    "sg:phone":"+1   ",
    "sg:postcode":"12590",
    "sg:province":"NY",
    "sg:tags":[
        "communication"
    ],
    "wof:name":"Los Communications",
    "wof:placetype":"venue"
},
  "geometry": {"coordinates":[-73.856471,41.589381],"type":"Point"}
}