{
  "type": "Feature",
  "properties": {
    "addr:full":"3240 Rawlins Ave Bronx NY 10465",
    "addr:housenumber":"3240",
    "addr:postcode":"10465",
    "addr:street":"Rawlins Ave",
    "iso:country":"US",
    "sg:address":"3240 Rawlins Ave",
    "sg:city":"Bronx",
    "sg:classifiers":[
        {
            "category":"Professional",
            "type":"Services"
        }
    ],
    "sg:phone":"+1   ",
    "sg:postcode":"10465",
    "sg:province":"NY",
    "wof:name":"Tool Time of NY Inc",
    "wof:placetype":"venue"
},
  "geometry": {"coordinates":[-73.819667,40.838021],"type":"Point"}
}