{
  "type": "Feature",
  "properties": {
    "addr:full":"1011 Gravel Rd Webster NY 14580",
    "addr:housenumber":"1011",
    "addr:postcode":"14580",
    "addr:street":"Gravel Rd",
    "iso:country":"US",
    "sg:address":"1011 Gravel Rd",
    "sg:city":"Webster",
    "sg:classifiers":[
        {
            "category":"Professional",
            "subcategory":"Accounting & Tax Preparation",
            "type":"Services"
        }
    ],
    "sg:phone":"+1   ",
    "sg:postcode":"14580",
    "sg:province":"NY",
    "sg:tags":[
        "return"
    ],
    "wof:name":"Tripi Joseph A CPA",
    "wof:placetype":"venue"
},
  "geometry": {"coordinates":[-77.496235,43.204776],"type":"Point"}
}