{
  "type": "Feature",
  "properties": {
    "addr:full":"145 W 86th St New York NY 10024",
    "addr:housenumber":"145",
    "addr:postcode":"10024",
    "addr:street":"W 86Th St",
    "iso:country":"US",
    "sg:address":"145 W 86th St",
    "sg:city":"New York",
    "sg:classifiers":[
        {
            "category":"Health Services",
            "subcategory":"Doctor",
            "type":"Services"
        }
    ],
    "sg:phone":"+1 212 249 4646",
    "sg:postcode":"10024",
    "sg:province":"NY",
    "sg:tags":[
        "throat",
        "ear",
        "nose"
    ],
    "wof:name":"Daniel J Pender, MD",
    "wof:placetype":"venue"
},
  "geometry": {"coordinates":[-73.97343100000001,40.787047],"type":"Point"}
}