{
  "type": "Feature",
  "properties": {
    "iso:country":"US",
    "sg:address":"620 South Ave",
    "sg:city":"Rochester",
    "sg:classifiers":[
        {
            "category":"Wholesale",
            "subcategory":"Construction Materials",
            "type":"Manufacturing & Wholesale Goods"
        }
    ],
    "sg:phone":"+1 585 244 2501",
    "sg:postcode":"14620",
    "sg:province":"NY",
    "sg:tags":[
        "trim",
        "metal",
        "door",
        "sash"
    ],
    "wof:name":"Architectural Products Co",
    "wof:placetype":"venue"
},
  "geometry": {"coordinates":[-77.604707,43.143707],"type":"Point"}
}