{
  "type": "Feature",
  "properties": {
    "addr:full":"301 N Washington St Herkimer NY 13350",
    "addr:housenumber":"301",
    "addr:postcode":"13350",
    "addr:street":"N Washington St",
    "iso:country":"US",
    "sg:address":"301 N Washington St",
    "sg:city":"Herkimer",
    "sg:classifiers":[
        {
            "category":"Government",
            "subcategory":"Court House",
            "type":"Public Place"
        }
    ],
    "sg:phone":"+1 315 867 1171",
    "sg:postcode":"13350",
    "sg:province":"NY",
    "sg:tags":[
        "county"
    ],
    "wof:name":"Herkimer County Court Judge",
    "wof:placetype":"venue"
},
  "geometry": {"coordinates":[-74.98804699999999,43.029818],"type":"Point"}
}