{
  "type": "Feature",
  "properties": {
    "addr:full":"203 E 26th St New York NY 10010",
    "addr:housenumber":"203",
    "addr:postcode":"10010",
    "addr:street":"E 26Th St",
    "iso:country":"US",
    "sg:address":"203 E 26th St",
    "sg:city":"New York",
    "sg:classifiers":[
        {
            "category":"Retail",
            "subcategory":"Repair Shop",
            "type":"Services"
        }
    ],
    "sg:phone":"+1 917 546 1592",
    "sg:postcode":"10010",
    "sg:province":"NY",
    "sg:tags":[
        "lock",
        "locksmith"
    ],
    "wof:name":"Emergency 24 Hr Locksmith",
    "wof:placetype":"venue"
},
  "geometry": {"coordinates":[-73.980324,40.740209],"type":"Point"}
}