{
  "type": "Feature",
  "properties": {
    "addr:full":"77 Center St Chatham NY 12037",
    "addr:housenumber":"77",
    "addr:postcode":"12037",
    "addr:street":"Center St",
    "iso:country":"US",
    "sg:address":"77 Center St",
    "sg:city":"Chatham",
    "sg:classifiers":[
        {
            "category":"Home & Garden",
            "subcategory":"Mobile Homes",
            "type":"Retail Goods"
        }
    ],
    "sg:phone":"+1 518 392 4774",
    "sg:postcode":"12037",
    "sg:province":"NY",
    "wof:name":"Golden Acres Mobile Sales & Ct",
    "wof:placetype":"venue"
},
  "geometry": {"coordinates":[-73.59963500000001,42.36757],"type":"Point"}
}