{
  "type": "Feature",
  "properties": {
    "addr:full":"345 W 55 St New York NY 10019",
    "addr:housenumber":"345",
    "addr:postcode":"10019",
    "addr:street":"W 55 St",
    "iso:country":"US",
    "sg:address":"345 W 55 St",
    "sg:city":"New York",
    "sg:classifiers":[
        {
            "category":"Professional",
            "subcategory":"Management & Consulting",
            "type":"Services"
        }
    ],
    "sg:phone":"+1 212 956 1016",
    "sg:postcode":"10019",
    "sg:province":"NY",
    "sg:tags":[
        "consultant"
    ],
    "wof:name":"Danbury Consulting Group",
    "wof:placetype":"venue"
},
  "geometry": {"coordinates":[-73.985658,40.766144],"type":"Point"}
}