{
  "type": "Feature",
  "properties": {
    "iso:country":"US",
    "sg:address":"1250 North Ave",
    "sg:city":"New Rochelle",
    "sg:classifiers":[
        {
            "category":"Sports & Exercise",
            "subcategory":"Gym",
            "type":"Entertainment"
        }
    ],
    "sg:phone":"+1   ",
    "sg:postcode":"10804",
    "sg:province":"NY",
    "sg:tags":[
        "fitness",
        "physical",
        "facility"
    ],
    "wof:name":"Divine Designs Fitness Inc",
    "wof:placetype":"venue"
},
  "geometry": {"coordinates":[-73.79539,40.944587],"type":"Point"}
}