{
  "type": "Feature",
  "properties": {
    "addr:full":"49 Walnut St Southampton NY 11968",
    "addr:housenumber":"49",
    "addr:postcode":"11968",
    "addr:street":"Walnut St",
    "iso:country":"US",
    "sg:address":"49 Walnut St",
    "sg:city":"Southampton",
    "sg:classifiers":[
        {
            "category":"Professional",
            "subcategory":"Lawyer & Legal Services",
            "type":"Services"
        }
    ],
    "sg:phone":"+1 631 283 7775",
    "sg:postcode":"11968",
    "sg:province":"NY",
    "sg:tags":[
        "attorney"
    ],
    "wof:name":"William F Bates",
    "wof:placetype":"venue"
},
  "geometry": {"coordinates":[-72.387028,40.885384],"type":"Point"}
}