{
  "type": "Feature",
  "properties": {
    "addr:full":"3802 State Hwy 52 Youngsville NY 12726",
    "addr:housenumber":"3802",
    "addr:postcode":"12726",
    "addr:street":"State Hwy 52",
    "iso:country":"US",
    "sg:address":"3802 State Hwy 52",
    "sg:city":"Youngsville",
    "sg:classifiers":[
        {
            "category":"Autos & Motor Vehicles",
            "subcategory":"Recreational Vehicle Sales",
            "type":"Retail Goods"
        }
    ],
    "sg:phone":"+1 845 292 5943",
    "sg:postcode":"12726",
    "sg:province":"NY",
    "sg:tags":[
        "travel",
        "trailer"
    ],
    "wof:name":"Price-Rite Boat & Camper Sales",
    "wof:placetype":"venue"
},
  "geometry": {"coordinates":[-74.980372,41.658714],"type":"Point"}
}