{
  "type": "Feature",
  "properties": {
    "iso:country":"US",
    "sg:address":"5797 State Hwy 362",
    "sg:city":"Bliss",
    "sg:classifiers":[
        {
            "category":"Farming",
            "subcategory":"Aquatic Farm",
            "type":"Manufacturing & Wholesale Goods"
        }
    ],
    "sg:phone":"+1 585 322 7322",
    "sg:postcode":"14024",
    "sg:province":"NY",
    "sg:tags":[
        "fish"
    ],
    "wof:name":"Browns Trout Hatchery",
    "wof:placetype":"venue"
},
  "geometry": {"coordinates":[-78.259522,42.614193],"type":"Point"}
}