{
  "type": "Feature",
  "properties": {
    "addr:full":"3489 State Hwy 394 Randolph NY 14772",
    "addr:housenumber":"3489",
    "addr:postcode":"14772",
    "addr:street":"State Hwy 394",
    "iso:country":"US",
    "sg:address":"3489 State Hwy 394",
    "sg:city":"Randolph",
    "sg:classifiers":[
        {
            "category":"Building & Trades",
            "subcategory":"Construction",
            "type":"Services"
        }
    ],
    "sg:phone":"+1 716 358 6647",
    "sg:postcode":"14772",
    "sg:province":"NY",
    "sg:tags":[
        "water",
        "well",
        "drilling"
    ],
    "wof:name":"Jones Well Drilling Inc",
    "wof:placetype":"venue"
},
  "geometry": {"coordinates":[-78.930594,42.151536],"type":"Point"}
}