{
  "type": "Feature",
  "properties": {
    "iso:country":"US",
    "sg:address":"14 McEchron Ln",
    "sg:city":"Queensbury",
    "sg:classifiers":[
        {
            "category":"Building & Trades",
            "subcategory":"Construction",
            "type":"Services"
        }
    ],
    "sg:phone":"+1 518 361 0747",
    "sg:postcode":"12804",
    "sg:province":"NY",
    "sg:tags":[
        "excavating",
        "contractor"
    ],
    "wof:name":"Benjamin Enterprises",
    "wof:placetype":"venue"
},
  "geometry": {"coordinates":[-73.718543,43.318693],"type":"Point"}
}