{
  "type": "Feature",
  "properties": {
    "iso:country":"US",
    "sg:address":"27 Brooks Ln",
    "sg:city":"Catskill",
    "sg:classifiers":[
        {
            "category":"Restaurant",
            "type":"Food & Drink"
        }
    ],
    "sg:phone":"+1   ",
    "sg:postcode":"12414",
    "sg:province":"NY",
    "sg:tags":[
        "eating"
    ],
    "wof:name":"Catskill Golf Club",
    "wof:placetype":"venue"
},
  "geometry": {"coordinates":[-73.883335,42.243249],"type":"Point"}
}