{
  "type": "Feature",
  "properties": {
    "iso:country":"US",
    "sg:address":"55 Pearl St",
    "sg:city":"New Hartford",
    "sg:classifiers":[
        {
            "category":"Wholesale",
            "subcategory":"Machinery & Supplies",
            "type":"Manufacturing & Wholesale Goods"
        }
    ],
    "sg:phone":"+1 315 734 1573",
    "sg:postcode":"13413",
    "sg:province":"NY",
    "sg:tags":[
        "graphic",
        "art"
    ],
    "wof:name":"Ad Tech-Graph Inc",
    "wof:placetype":"venue"
},
  "geometry": {"coordinates":[-75.287206,43.06855],"type":"Point"}
}