{
  "type": "Feature",
  "properties": {
    "addr:full":"1 S Division St Peekskill NY 10566",
    "addr:housenumber":"1",
    "addr:postcode":"10566",
    "addr:street":"S Division St",
    "iso:country":"US",
    "sg:address":"1 S Division St",
    "sg:city":"Peekskill",
    "sg:classifiers":[
        {
            "category":"Organizations",
            "subcategory":"Professional Association",
            "type":"Services"
        }
    ],
    "sg:phone":"+1 914 737 3600",
    "sg:postcode":"10566",
    "sg:province":"NY",
    "sg:tags":[
        "business",
        "trade"
    ],
    "wof:name":"Chamber Of Commerce",
    "wof:placetype":"venue"
},
  "geometry": {"coordinates":[-73.915429,41.288449],"type":"Point"}
}