{
  "type": "Feature",
  "properties": {
    "iso:country":"US",
    "sg:address":"139 N 10th St",
    "sg:city":"Brooklyn",
    "sg:classifiers":[
        {
            "category":"Manufacturing",
            "subcategory":"Metals",
            "type":"Manufacturing & Wholesale Goods"
        }
    ],
    "sg:phone":"+1 718 384 5751",
    "sg:postcode":"11211",
    "sg:province":"NY",
    "sg:tags":[
        "installs",
        "work",
        "sheet",
        "install",
        "mfg"
    ],
    "wof:name":"F & W Mechanical Co",
    "wof:placetype":"venue"
},
  "geometry": {"coordinates":[-73.956468,40.719815],"type":"Point"}
}