{
  "type": "Feature",
  "properties": {
    "iso:country":"US",
    "sg:address":"1320 Lincoln Ave",
    "sg:city":"Holbrook",
    "sg:classifiers":[
        {
            "category":"Building & Trades",
            "subcategory":"Electrical",
            "type":"Services"
        }
    ],
    "sg:phone":"+1 631 585 3100",
    "sg:postcode":"11741",
    "sg:province":"NY",
    "sg:tags":[
        "lighting",
        "landscape"
    ],
    "wof:name":"Alessandro Landscape & Design",
    "wof:placetype":"venue"
},
  "geometry": {"coordinates":[-73.084048,40.779944],"type":"Point"}
}