{
  "type": "Feature",
  "properties": {
    "iso:country":"US",
    "sg:address":"310 Broadway",
    "sg:city":"Huntington Station",
    "sg:classifiers":[
        {
            "category":"Building & Trades",
            "subcategory":"Plumbing",
            "type":"Services"
        }
    ],
    "sg:phone":"+1 631 421 5775",
    "sg:postcode":"11746",
    "sg:province":"NY",
    "sg:website":"www.huntingtonplumbingsupply.com",
    "wof:name":"Huntington Plumbing Supply Co",
    "wof:placetype":"venue"
},
  "geometry": {"coordinates":[-73.39980300000001,40.857601],"type":"Point"}
}