{
  "type": "Feature",
  "properties": {
    "iso:country":"US",
    "sg:address":"1 Park Ave",
    "sg:city":"Manhasset",
    "sg:classifiers":[
        {
            "category":"Insurance",
            "subcategory":"Insurance Agent",
            "type":"Services"
        },
        {
            "category":"Insurance",
            "subcategory":"Hazard Insurance",
            "type":"Services"
        },
        {
            "category":"Insurance",
            "subcategory":"Title Insurance",
            "type":"Services"
        },
        {
            "category":"Insurance",
            "subcategory":"Life Insurance",
            "type":"Services"
        }
    ],
    "sg:phone":"+1 516 439 5420",
    "sg:postcode":"11030",
    "sg:province":"NY",
    "sg:tags":[
        "business",
        "auto",
        "commercial",
        "homeowner",
        "motorcycle",
        "renter"
    ],
    "wof:name":"Allstate Insurance Company - Onkar (Bobby) Singh",
    "wof:placetype":"venue"
},
  "geometry": {"coordinates":[-73.69944,40.79678],"type":"Point"}
}