{
  "type": "Feature",
  "properties": {
    "addr:full":"953 Broadway Thornwood NY 10594",
    "addr:housenumber":"953",
    "addr:postcode":"10594",
    "addr:street":"Broadway",
    "iso:country":"US",
    "sg:address":"953 Broadway",
    "sg:city":"Thornwood",
    "sg:classifiers":[
        {
            "category":"Retail",
            "subcategory":"Auto Repair",
            "type":"Services"
        }
    ],
    "sg:phone":"+1 914 769 3440",
    "sg:postcode":"10594",
    "sg:province":"NY",
    "wof:name":"A & A Transmissions",
    "wof:placetype":"venue"
},
  "geometry": {"coordinates":[-73.780197,41.126301],"type":"Point"}
}