{
  "type": "Feature",
  "properties": {
    "iso:country":"US",
    "sg:address":"2406 Maria Blvd",
    "sg:city":"Binghamton",
    "sg:classifiers":[
        {
            "category":"Organizations",
            "subcategory":"Religious Organization",
            "type":"Services"
        }
    ],
    "sg:phone":"+1 607 722 5900",
    "sg:postcode":"13903",
    "sg:province":"NY",
    "wof:name":"International Catholic De",
    "wof:placetype":"venue"
},
  "geometry": {"coordinates":[-75.86653800000001,42.090359],"type":"Point"}
}