{
  "type": "Feature",
  "properties": {
    "addr:full":"3 Baldwin Ave North Baldwin NY 11510",
    "addr:housenumber":"3",
    "addr:postcode":"11510",
    "addr:street":"Baldwin Ave North",
    "iso:country":"US",
    "sg:address":"3 Baldwin Ave",
    "sg:city":"North Baldwin",
    "sg:classifiers":[
        {
            "category":"Autos & Motor Vehicles",
            "subcategory":"Boat Sales",
            "type":"Retail Goods"
        }
    ],
    "sg:phone":"+1 516 868 9404",
    "sg:postcode":"11510",
    "sg:province":"NY",
    "sg:tags":[
        "equipment",
        "marine",
        "supply"
    ],
    "wof:name":"Star Marine Contracting Co",
    "wof:placetype":"venue"
},
  "geometry": {"coordinates":[-73.61822600000001,40.659388],"type":"Point"}
}