{
  "type": "Feature",
  "properties": {
    "addr:full":"94 Prince St New York NY 10012",
    "addr:housenumber":"94",
    "addr:postcode":"10012",
    "addr:street":"Prince St",
    "iso:country":"US",
    "sg:address":"94 Prince St",
    "sg:city":"New York",
    "sg:classifiers":[
        {
            "category":"Food Court",
            "type":"Food & Drink"
        }
    ],
    "sg:postcode":"10012",
    "sg:province":"NY",
    "sg:tags":[
        "stand"
    ],
    "wof:name":"Soup Kiosk",
    "wof:placetype":"venue"
},
  "geometry": {"coordinates":[-73.998639,40.724652],"type":"Point"}
}