{
  "type": "Feature",
  "properties": {
    "addr:full":"3415 Olinville Ave Bronx NY 10467",
    "addr:housenumber":"3415",
    "addr:postcode":"10467",
    "addr:street":"Olinville Ave",
    "iso:country":"US",
    "sg:address":"3415 Olinville Ave",
    "sg:city":"Bronx",
    "sg:classifiers":[
        {
            "category":"Education",
            "subcategory":"Special Training",
            "type":"Public Place"
        }
    ],
    "sg:phone":"+1 718 652 6256",
    "sg:postcode":"10467",
    "sg:province":"NY",
    "sg:tags":[
        "cultural",
        "art",
        "school"
    ],
    "wof:name":"Mind-Builders Creative Art Ctr",
    "wof:placetype":"venue"
},
  "geometry": {"coordinates":[-73.86815900000001,40.876816],"type":"Point"}
}