{
  "type": "Feature",
  "properties": {
    "iso:country":"US",
    "sg:address":"757 Lick St",
    "sg:city":"Groton",
    "sg:classifiers":[
        {
            "category":"Shopping",
            "subcategory":"Used Merchandise",
            "type":"Retail Goods"
        }
    ],
    "sg:phone":"+1   ",
    "sg:postcode":"13073",
    "sg:province":"NY",
    "sg:tags":[
        "rental",
        "trailer",
        "utility"
    ],
    "wof:name":"Surplus Depot The",
    "wof:placetype":"venue"
},
  "geometry": {"coordinates":[-76.343677,42.599957],"type":"Point"}
}