{
  "type": "Feature",
  "properties": {
    "iso:country":"US",
    "sg:address":"110 Airport Rd",
    "sg:city":"Wappingers Falls",
    "sg:classifiers":[
        {
            "category":"Professional",
            "type":"Services"
        }
    ],
    "sg:phone":"+1 845 463 3400",
    "sg:postcode":"12590",
    "sg:province":"NY",
    "sg:tags":[
        "establishment"
    ],
    "wof:name":"Rush Order",
    "wof:placetype":"venue"
},
  "geometry": {"coordinates":[-73.862861,41.636157],"type":"Point"}
}