{
  "type": "Feature",
  "properties": {
    "iso:country":"US",
    "sg:address":"55 W 83 St",
    "sg:city":"New York",
    "sg:classifiers":[
        {
            "category":"Retail",
            "subcategory":"Repair Shop",
            "type":"Services"
        }
    ],
    "sg:phone":"+1 646 224 0800",
    "sg:postcode":"10024",
    "sg:province":"NY",
    "sg:tags":[
        "lock",
        "locksmith"
    ],
    "wof:name":"Locksmith 24 Hour",
    "wof:placetype":"venue"
},
  "geometry": {"coordinates":[-73.972376,40.783943],"type":"Point"}
}