{
  "type": "Feature",
  "properties": {
    "iso:country":"US",
    "sg:address":"2657 W Henrietta Rd",
    "sg:city":"Rochester",
    "sg:classifiers":[
        {
            "category":"Social Services",
            "subcategory":"Job Training",
            "type":"Services"
        }
    ],
    "sg:phone":"+1 585 424 7442",
    "sg:postcode":"14623",
    "sg:province":"NY",
    "sg:tags":[
        "retardation",
        "disabled",
        "mental",
        "dev"
    ],
    "wof:name":"Crittenden Day Treatment",
    "wof:placetype":"venue"
},
  "geometry": {"coordinates":[-77.629458,43.102684],"type":"Point"}
}