{
  "type": "Feature",
  "properties": {
    "addr:full":"109 Kimball Ave Penn Yan NY 14527",
    "addr:housenumber":"109",
    "addr:postcode":"14527",
    "addr:street":"Kimball Ave",
    "iso:country":"US",
    "sg:address":"109 Kimball Ave",
    "sg:city":"Penn Yan",
    "sg:classifiers":[
        {
            "category":"Sports & Exercise",
            "subcategory":"Gym",
            "type":"Entertainment"
        }
    ],
    "sg:phone":"+1 315 531 9200",
    "sg:postcode":"14527",
    "sg:province":"NY",
    "sg:tags":[
        "club",
        "health",
        "studio",
        "gymnasium"
    ],
    "wof:name":"Curves",
    "wof:placetype":"venue"
},
  "geometry": {"coordinates":[-77.056166,42.654847],"type":"Point"}
}