{
  "type": "Feature",
  "properties": {
    "addr:full":"215 Park Avenue New York NY 10017",
    "addr:housenumber":"215",
    "addr:postcode":"10017",
    "addr:street":"Park Avenue",
    "iso:country":"US",
    "sg:address":"215 Park Avenue",
    "sg:city":"New York",
    "sg:classifiers":[
        {
            "category":"Education",
            "subcategory":"University",
            "type":"Public Place"
        }
    ],
    "sg:phone":"+1 212 529 3005",
    "sg:postcode":"10017",
    "sg:province":"NY",
    "sg:tags":[
        "college"
    ],
    "wof:name":"International College",
    "wof:placetype":"venue"
},
  "geometry": {"coordinates":[-73.975983,40.754074],"type":"Point"}
}