{
  "type": "Feature",
  "properties": {
    "addr:full":"21 3rd St Rye NY 10580",
    "addr:housenumber":"21",
    "addr:postcode":"10580",
    "addr:street":"3Rd St",
    "iso:country":"US",
    "sg:address":"21 3rd St",
    "sg:city":"Rye",
    "sg:classifiers":[
        {
            "category":"Government",
            "subcategory":"Court House",
            "type":"Public Place"
        }
    ],
    "sg:phone":"+1 914 967 1599",
    "sg:postcode":"10580",
    "sg:province":"NY",
    "sg:tags":[
        "city"
    ],
    "wof:name":"Rye City Court",
    "wof:placetype":"venue"
},
  "geometry": {"coordinates":[-73.68283599999999,40.98508],"type":"Point"}
}