{
  "type": "Feature",
  "properties": {
    "iso:country":"US",
    "sg:address":"2096 Merrick Ave N",
    "sg:city":"Merrick",
    "sg:classifiers":[
        {
            "category":"Retail",
            "subcategory":"Repair Shop",
            "type":"Services"
        }
    ],
    "sg:phone":"+1 516 481 5665",
    "sg:postcode":"11566",
    "sg:province":"NY",
    "sg:tags":[
        "refrigerating"
    ],
    "wof:name":"Advanced Cooling System",
    "wof:placetype":"venue"
},
  "geometry": {"coordinates":[-73.55383,40.667751],"type":"Point"}
}