{
  "type": "Feature",
  "properties": {
    "iso:country":"US",
    "sg:address":"27 Colehamer Ave",
    "sg:city":"Troy",
    "sg:classifiers":[
        {
            "category":"Building & Trades",
            "subcategory":"Construction",
            "type":"Services"
        }
    ],
    "sg:phone":"+1 518 279 9668",
    "sg:postcode":"12180",
    "sg:province":"NY",
    "sg:tags":[
        "carpentry",
        "contractor"
    ],
    "wof:name":"Tod Ward Carpentry",
    "wof:placetype":"venue"
},
  "geometry": {"coordinates":[-73.62060700000001,42.724716],"type":"Point"}
}