{
  "type": "Feature",
  "properties": {
    "addr:full":"542 W 27th St New York NY 10184",
    "addr:housenumber":"542",
    "addr:postcode":"10184",
    "addr:street":"W 27Th St",
    "iso:country":"US",
    "sg:address":"542 W 27th St",
    "sg:city":"New York",
    "sg:classifiers":[
        {
            "category":"Bars & Pubs",
            "type":"Food & Drink"
        }
    ],
    "sg:phone":"+1 212 273 3700",
    "sg:postcode":"10184",
    "sg:province":"NY",
    "sg:website":"www.homeguesthouse.com",
    "wof:name":"Guest House",
    "wof:placetype":"venue"
},
  "geometry": {"coordinates":[-74.003758,40.750817],"type":"Point"}
}