{
  "type": "Feature",
  "properties": {
    "iso:country":"US",
    "sg:address":"2 Cope Cir",
    "sg:city":"Rye",
    "sg:classifiers":[
        {
            "category":"Real Estate",
            "subcategory":"Real Estate Services",
            "type":"Services"
        },
        {
            "category":"Real Estate",
            "subcategory":"Real Estate Agent",
            "type":"Services"
        }
    ],
    "sg:phone":"+1 914 967 8112",
    "sg:postcode":"10580",
    "sg:province":"NY",
    "sg:tags":[
        "management"
    ],
    "wof:name":"Evergreen Real Estate Inv",
    "wof:placetype":"venue"
},
  "geometry": {"coordinates":[-73.679022,40.991474],"type":"Point"}
}