{
  "type": "Feature",
  "properties": {
    "addr:full":"216 Crestwood Ave Tuckahoe NY 10707",
    "addr:housenumber":"216",
    "addr:postcode":"10707",
    "addr:street":"Crestwood Ave",
    "iso:country":"US",
    "sg:address":"216 Crestwood Ave",
    "sg:city":"Tuckahoe",
    "sg:classifiers":[
        {
            "category":"Manufacturing",
            "subcategory":"Retail Goods",
            "type":"Manufacturing & Wholesale Goods"
        }
    ],
    "sg:phone":"+1   ",
    "sg:postcode":"10707",
    "sg:province":"NY",
    "sg:tags":[
        "product",
        "mfg"
    ],
    "wof:name":"Moments To Treasure",
    "wof:placetype":"venue"
},
  "geometry": {"coordinates":[-73.822243,40.964926],"type":"Point"}
}