{
  "type": "Feature",
  "properties": {
    "iso:country":"US",
    "sg:address":"6 Tracy St",
    "sg:city":"Rensselaer",
    "sg:classifiers":[
        {
            "category":"Utilities",
            "subcategory":"Refuse",
            "type":"Services"
        }
    ],
    "sg:phone":"+1 518 689 0107",
    "sg:postcode":"12144",
    "sg:province":"NY",
    "sg:tags":[
        "disposal",
        "waste"
    ],
    "wof:name":"Hannan's Waste Disposal",
    "wof:placetype":"venue"
},
  "geometry": {"coordinates":[-73.73491,42.656067],"type":"Point"}
}