{
  "type": "Feature",
  "properties": {
    "addr:full":"536 3rd Avenue Brooklyn NY 11215",
    "addr:housenumber":"536",
    "addr:postcode":"11215",
    "addr:street":"3Rd Avenue",
    "iso:country":"US",
    "sg:address":"536 3rd Avenue",
    "sg:city":"Brooklyn",
    "sg:classifiers":[
        {
            "category":"Restaurant",
            "type":"Food & Drink"
        }
    ],
    "sg:phone":"+1 718 788 1846",
    "sg:postcode":"11215",
    "sg:province":"NY",
    "sg:website":"number1delinyc.com",
    "wof:name":"Number One Deli",
    "wof:placetype":"venue"
},
  "geometry": {"coordinates":[-73.993191,40.669062],"type":"Point"}
}