{
  "type": "Feature",
  "properties": {
    "addr:full":"313 Clear View Ln Massapequa NY 11758",
    "addr:housenumber":"313",
    "addr:postcode":"11758",
    "addr:street":"Clear View Ln",
    "iso:country":"US",
    "sg:address":"313 Clear View Ln",
    "sg:city":"Massapequa",
    "sg:classifiers":[
        {
            "category":"Professional",
            "subcategory":"Secretarial Services",
            "type":"Services"
        }
    ],
    "sg:phone":"+1 516 797 7626",
    "sg:postcode":"11758",
    "sg:province":"NY",
    "sg:tags":[
        "resume"
    ],
    "wof:name":"Resume Specialists",
    "wof:placetype":"venue"
},
  "geometry": {"coordinates":[-73.465639,40.65027],"type":"Point"}
}