{
  "type": "Feature",
  "properties": {
    "addr:full":"624 Portion Rd Ronkonkoma NY 11779",
    "addr:housenumber":"624",
    "addr:postcode":"11779",
    "addr:street":"Portion Rd",
    "iso:country":"US",
    "sg:address":"624 Portion Rd",
    "sg:city":"Ronkonkoma",
    "sg:phone":"+1 631 588 8798",
    "sg:postcode":"11779",
    "sg:province":"NY",
    "sg:tags":[
        "gas"
    ],
    "wof:name":"Ameri Gas Inc",
    "wof:placetype":"venue"
},
  "geometry": {"coordinates":[-73.08590700000001,40.831506],"type":"Point"}
}