{
  "type": "Feature",
  "properties": {
    "iso:country":"US",
    "sg:address":"112 W Court Dr",
    "sg:city":"Centereach",
    "sg:classifiers":[
        {
            "category":"Freight",
            "type":"Transportation"
        }
    ],
    "sg:phone":"+1 631 467 0230",
    "sg:postcode":"11720",
    "sg:province":"NY",
    "sg:tags":[
        "trucking"
    ],
    "wof:name":"Expedited Fleet Systems Inc",
    "wof:placetype":"venue"
},
  "geometry": {"coordinates":[-73.09101099999999,40.879946],"type":"Point"}
}