{
  "type": "Feature",
  "properties": {
    "addr:full":"74 S Central Ave Spring Valley NY 10954",
    "addr:housenumber":"74",
    "addr:postcode":"10954",
    "addr:street":"S Central Ave",
    "iso:country":"US",
    "sg:address":"74 S Central Ave",
    "sg:city":"Spring Valley",
    "sg:classifiers":[
        {
            "category":"Food & Beverages",
            "subcategory":"Bakery",
            "type":"Retail Goods"
        }
    ],
    "sg:phone":"+1   ",
    "sg:postcode":"10954",
    "sg:province":"NY",
    "wof:name":"Eben Ezer Inc",
    "wof:placetype":"venue"
},
  "geometry": {"coordinates":[-74.039568,41.105871],"type":"Point"}
}