{
  "type": "Feature",
  "properties": {
    "iso:country":"US",
    "sg:address":"38 Laurel Rd",
    "sg:city":"East Northport",
    "sg:classifiers":[
        {
            "category":"Building & Trades",
            "subcategory":"Construction",
            "type":"Services"
        }
    ],
    "sg:phone":"+1 631 724 1300",
    "sg:postcode":"11731",
    "sg:province":"NY",
    "sg:tags":[
        "ceiling"
    ],
    "wof:name":"Austin Interiors",
    "wof:placetype":"venue"
},
  "geometry": {"coordinates":[-73.32600100000001,40.882421],"type":"Point"}
}