{
  "type": "Feature",
  "properties": {
    "addr:full":"1265 Clove Road Staten Island NY 10301",
    "addr:housenumber":"1265",
    "addr:postcode":"10301",
    "addr:street":"Clove Road",
    "iso:country":"US",
    "sg:address":"1265 Clove Road",
    "sg:city":"Staten Island",
    "sg:classifiers":[
        {
            "category":"Health Services",
            "subcategory":"Doctor",
            "type":"Services"
        }
    ],
    "sg:phone":"+1 718 727 9729",
    "sg:postcode":"10301",
    "sg:province":"NY",
    "wof:name":"Parekh H MD",
    "wof:placetype":"venue"
},
  "geometry": {"coordinates":[-74.103026,40.615987],"type":"Point"}
}