{
  "type": "Feature",
  "properties": {
    "addr:full":"The Center for Special Dentistry 425 Madison Ave, Ste 500 New York NY 10017",
    "addr:housenumber":"425;500",
    "addr:postcode":"10017",
    "addr:street":"Madison Ave Ste",
    "iso:country":"US",
    "sg:address":"The Center for Special Dentistry 425 Madison Ave, Ste 500",
    "sg:city":"New York",
    "sg:classifiers":[
        {
            "category":"Health Services",
            "subcategory":"Doctor",
            "type":"Services"
        },
        {
            "category":"Health Services",
            "subcategory":"Dentist",
            "type":"Services"
        }
    ],
    "sg:phone":"+1 212 758 1000",
    "sg:postcode":"10017",
    "sg:province":"NY",
    "sg:tags":[
        "surgeon",
        "oral",
        "orthodontist"
    ],
    "sg:website":"www.nycdentist.com",
    "wof:name":"Jeffrey Dorfman, DMD",
    "wof:placetype":"venue"
},
  "geometry": {"coordinates":[-73.975905,40.756962],"type":"Point"}
}