{
  "type": "Feature",
  "properties": {
    "addr:full":"8152 Kirkville Rd Kirkville NY 13082",
    "addr:housenumber":"8152",
    "addr:postcode":"13082",
    "addr:street":"Kirkville Rd",
    "iso:country":"US",
    "sg:address":"8152 Kirkville Rd",
    "sg:city":"Kirkville",
    "sg:classifiers":[
        {
            "category":"Building & Trades",
            "subcategory":"Plumbing",
            "type":"Services"
        }
    ],
    "sg:phone":"+1 315 656 3884",
    "sg:postcode":"13082",
    "sg:province":"NY",
    "sg:tags":[
        "control",
        "air",
        "pollution"
    ],
    "sg:website":"www.dfbrandt.com",
    "wof:name":"D F Brandt Inc",
    "wof:placetype":"venue"
},
  "geometry": {"coordinates":[-75.969909,43.085094],"type":"Point"}
}