{
  "type": "Feature",
  "properties": {
    "addr:full":"1018 Waverly Ave Holtsville NY 11742",
    "addr:housenumber":"1018",
    "addr:postcode":"11742",
    "addr:street":"Waverly Ave",
    "iso:country":"US",
    "sg:address":"1018 Waverly Ave",
    "sg:city":"Holtsville",
    "sg:classifiers":[
        {
            "category":"Shopping",
            "subcategory":"Stationery & Office Supplies",
            "type":"Retail Goods"
        }
    ],
    "sg:phone":"+1   ",
    "sg:postcode":"11742",
    "sg:province":"NY",
    "wof:name":"Card Lodge Stationery",
    "wof:placetype":"venue"
},
  "geometry": {"coordinates":[-73.045391,40.818082],"type":"Point"}
}