{
  "type": "Feature",
  "properties": {
    "addr:full":"1401 Tanger Mall Dr Riverhead NY 11901",
    "addr:housenumber":"1401",
    "addr:postcode":"11901",
    "addr:street":"Tanger Mall Dr",
    "iso:country":"US",
    "sg:address":"1401 Tanger Mall Dr",
    "sg:city":"Riverhead",
    "sg:classifiers":[
        {
            "category":"Food & Beverages",
            "subcategory":"Candy",
            "type":"Retail Goods"
        }
    ],
    "sg:phone":"+1 631 369 3536",
    "sg:postcode":"11901",
    "sg:province":"NY",
    "sg:tags":[
        "confectionery"
    ],
    "wof:name":"Candies Inc.",
    "wof:placetype":"venue"
},
  "geometry": {"coordinates":[-72.714727,40.919672],"type":"Point"}
}