{
  "type": "Feature",
  "properties": {
    "addr:full":"17518 147th Ave Jamaica NY 11434",
    "addr:housenumber":"17518",
    "addr:postcode":"11434",
    "addr:street":"147Th Ave",
    "iso:country":"US",
    "sg:address":"17518 147th Ave",
    "sg:city":"Jamaica",
    "sg:classifiers":[
        {
            "category":"Shopping",
            "subcategory":"Stationery & Office Supplies",
            "type":"Retail Goods"
        }
    ],
    "sg:phone":"+1 718 244 8790",
    "sg:postcode":"11434",
    "sg:province":"NY",
    "sg:tags":[
        "packing",
        "room",
        "shipping",
        "materials-shipping"
    ],
    "wof:name":"Nyc Itex Corp",
    "wof:placetype":"venue"
},
  "geometry": {"coordinates":[-73.770765,40.661142],"type":"Point"}
}