{
  "type": "Feature",
  "properties": {
    "addr:full":"4398 Ridge Chapel Rd Marion NY 14505",
    "addr:housenumber":"4398",
    "addr:postcode":"14505",
    "addr:street":"Ridge Chapel Rd",
    "iso:country":"US",
    "sg:address":"4398 Ridge Chapel Rd",
    "sg:city":"Marion",
    "sg:classifiers":[
        {
            "category":"Shopping",
            "subcategory":"Used Merchandise",
            "type":"Retail Goods"
        },
        {
            "category":"Home & Garden",
            "subcategory":"Furniture",
            "type":"Retail Goods"
        }
    ],
    "sg:phone":"+1 315 926 5689",
    "sg:postcode":"14505",
    "sg:province":"NY",
    "sg:tags":[
        "household",
        "appliance"
    ],
    "wof:name":"Boerman's Upholstery Shop",
    "wof:placetype":"venue"
},
  "geometry": {"coordinates":[-77.216532,43.16319],"type":"Point"}
}