{
  "type": "Feature",
  "properties": {
    "addr:full":"11 E Hawthorne Ave Valley Stream NY 11580",
    "addr:housenumber":"11",
    "addr:postcode":"11580",
    "addr:street":"E Hawthorne Ave",
    "iso:country":"US",
    "sg:address":"11 E Hawthorne Ave",
    "sg:city":"Valley Stream",
    "sg:classifiers":[
        {
            "category":"Wholesale",
            "subcategory":"Medical Equipment & Supplies",
            "type":"Manufacturing & Wholesale Goods"
        },
        {
            "category":"Manufacturing",
            "subcategory":"Tools & Machinery",
            "type":"Manufacturing & Wholesale Goods"
        }
    ],
    "sg:phone":"+1 516 872 7211",
    "sg:postcode":"11580",
    "sg:province":"NY",
    "sg:tags":[
        "instrument",
        "surgical"
    ],
    "wof:name":"Inter-Med Technologies LLC",
    "wof:placetype":"venue"
},
  "geometry": {"coordinates":[-73.69866500000001,40.6607],"type":"Point"}
}