{
  "type": "Feature",
  "properties": {
    "addr:full":"120 Lexington Ave New York NY 10016",
    "addr:housenumber":"120",
    "addr:postcode":"10016",
    "addr:street":"Lexington Ave",
    "iso:country":"US",
    "sg:address":"120 Lexington Ave",
    "sg:city":"New York",
    "sg:classifiers":[
        {
            "category":"Restaurant",
            "type":"Food & Drink"
        }
    ],
    "sg:menulink":"http://www.allmenus.com/ny/new-york/56994-chinese-mirch/menu/",
    "sg:phone":"+1 212 532 3663",
    "sg:postcode":"10016",
    "sg:province":"NY",
    "sg:tags":[
        "asian",
        "chinese"
    ],
    "wof:name":"Chinese Mirch",
    "wof:placetype":"venue"
},
  "geometry": {"coordinates":[-73.982589,40.742848],"type":"Point"}
}