{
  "type": "Feature",
  "properties": {
    "addr:full":"642 Saratoga Rd Scotia NY 12302",
    "addr:housenumber":"642",
    "addr:postcode":"12302",
    "addr:street":"Saratoga Rd",
    "iso:country":"US",
    "sg:address":"642 Saratoga Rd",
    "sg:city":"Scotia",
    "sg:classifiers":[
        {
            "category":"Autos & Motor Vehicles",
            "subcategory":"Automobile Sales",
            "type":"Retail Goods"
        }
    ],
    "sg:phone":"+1 518 399 8393",
    "sg:postcode":"12302",
    "sg:province":"NY",
    "sg:tags":[
        "car",
        "dealer"
    ],
    "sg:website":"www.foggsautomotive.com",
    "wof:name":"Foggs Automotive",
    "wof:placetype":"venue"
},
  "geometry": {"coordinates":[-73.90898,42.898714],"type":"Point"}
}