{
  "type": "Feature",
  "properties": {
    "iso:country":"US",
    "sg:address":"115 Duesler Rd",
    "sg:city":"Fort Plain",
    "sg:classifiers":[
        {
            "category":"Freight",
            "type":"Transportation"
        }
    ],
    "sg:phone":"+1   ",
    "sg:postcode":"13339",
    "sg:province":"NY",
    "sg:tags":[
        "operator",
        "local",
        "trucking"
    ],
    "wof:name":"Vanvalkenburgh Trucking",
    "wof:placetype":"venue"
},
  "geometry": {"coordinates":[-74.638335,42.918037],"type":"Point"}
}