{
  "type": "Feature",
  "properties": {
    "iso:country":"US",
    "sg:address":"2147 Ridge Rd W",
    "sg:city":"Rochester",
    "sg:classifiers":[
        {
            "category":"Shopping",
            "subcategory":"Jewelry",
            "type":"Retail Goods"
        }
    ],
    "sg:phone":"+1 585 225 5445",
    "sg:postcode":"14626",
    "sg:province":"NY",
    "sg:tags":[
        "jeweler"
    ],
    "wof:name":"Source Fine Jewelers",
    "wof:placetype":"venue"
},
  "geometry": {"coordinates":[-77.684524,43.207922],"type":"Point"}
}