{
  "type": "Feature",
  "properties": {
    "iso:country":"US",
    "sg:address":"549 Oliver St",
    "sg:city":"North Tonawanda",
    "sg:classifiers":[
        {
            "category":"Retail",
            "subcategory":"Funeral Services",
            "type":"Services"
        }
    ],
    "sg:phone":"+1 716 692 0271",
    "sg:postcode":"14120",
    "sg:province":"NY",
    "sg:tags":[
        "home"
    ],
    "wof:name":"Saber Funeral Home",
    "wof:placetype":"venue"
},
  "geometry": {"coordinates":[-78.878435,43.037336],"type":"Point"}
}