{
  "type": "Feature",
  "properties": {
    "addr:full":"17520 Hillside Ave Ste 1 Jamaica NY 11432",
    "addr:housenumber":"17520",
    "addr:postcode":"11432",
    "addr:street":"Hillside Ave Ste 1",
    "iso:country":"US",
    "sg:address":"17520 Hillside Ave Ste 1",
    "sg:city":"Jamaica",
    "sg:classifiers":[
        {
            "category":"Health Services",
            "subcategory":"Doctor",
            "type":"Services"
        }
    ],
    "sg:phone":"+1 718 298 9500",
    "sg:postcode":"11432",
    "sg:province":"NY",
    "sg:tags":[
        "physician",
        "family",
        "practice",
        "surgeons",
        "medicine"
    ],
    "wof:name":"Tomas M Pattugalan Md Pc",
    "wof:placetype":"venue"
},
  "geometry": {"coordinates":[-73.781891,40.713144],"type":"Point"}
}