{
  "type": "Feature",
  "properties": {
    "addr:full":"23 Pell St New York NY 10038",
    "addr:housenumber":"23",
    "addr:postcode":"10038",
    "addr:street":"Pell St",
    "iso:country":"US",
    "sg:address":"23 Pell St",
    "sg:city":"New York",
    "sg:classifiers":[
        {
            "category":"Restaurant",
            "type":"Food & Drink"
        }
    ],
    "sg:phone":"+1 212 285 0668",
    "sg:postcode":"10038",
    "sg:province":"NY",
    "sg:tags":[
        "chinese"
    ],
    "wof:name":"Shanghai Gourmet",
    "wof:placetype":"venue"
},
  "geometry": {"coordinates":[-73.998302,40.714748],"type":"Point"}
}