{
  "type": "Feature",
  "properties": {
    "addr:full":"337 3rd Ave New York NY 10010",
    "addr:housenumber":"337",
    "addr:postcode":"10010",
    "addr:street":"3Rd Ave",
    "iso:country":"US",
    "sg:address":"337 3rd Ave",
    "sg:city":"New York",
    "sg:classifiers":[
        {
            "category":"Bars & Pubs",
            "type":"Food & Drink"
        },
        {
            "category":"Bars & Pubs",
            "subcategory":"Sports Bar",
            "type":"Food & Drink"
        }
    ],
    "sg:phone":"+1 212 532 2929",
    "sg:postcode":"10010",
    "sg:province":"NY",
    "sg:website":"www.thehairymonknyc.com",
    "wof:name":"The Hairy Monk",
    "wof:placetype":"venue"
},
  "geometry": {"coordinates":[-73.98225100000001,40.740017],"type":"Point"}
}