{
  "type": "Feature",
  "properties": {
    "addr:full":"8503 Rochester Rd Gasport NY 14067",
    "addr:housenumber":"8503",
    "addr:postcode":"14067",
    "addr:street":"Rochester Rd",
    "iso:country":"US",
    "sg:address":"8503 Rochester Rd",
    "sg:city":"Gasport",
    "sg:classifiers":[
        {
            "category":"Restaurant",
            "type":"Food & Drink"
        }
    ],
    "sg:phone":"+1 716 772 7299",
    "sg:postcode":"14067",
    "sg:province":"NY",
    "wof:name":"Greenlief's",
    "wof:placetype":"venue"
},
  "geometry": {"coordinates":[-78.561058,43.197844],"type":"Point"}
}