{
  "type": "Feature",
  "properties": {
    "addr:full":"21 E 40th Street New York NY 10016",
    "addr:housenumber":"21",
    "addr:postcode":"10016",
    "addr:street":"E 40Th Street",
    "iso:country":"US",
    "sg:address":"21 E 40th Street",
    "sg:city":"New York",
    "sg:classifiers":[
        {
            "category":"Banks & Credit Unions",
            "subcategory":"Investment Brokerage",
            "type":"Services"
        }
    ],
    "sg:phone":"+1 212 683 5326",
    "sg:postcode":"10016",
    "sg:province":"NY",
    "sg:tags":[
        "investing"
    ],
    "wof:name":"Emdin and Russell Llp",
    "wof:placetype":"venue"
},
  "geometry": {"coordinates":[-73.980189,40.751507],"type":"Point"}
}