{
  "type": "Feature",
  "properties": {
    "iso:country":"US",
    "sg:address":"8 Bluff Cir",
    "sg:city":"Hauppauge",
    "sg:classifiers":[
        {
            "category":"Building & Trades",
            "subcategory":"Construction",
            "type":"Services"
        }
    ],
    "sg:phone":"+1 631 265 7601",
    "sg:postcode":"11788",
    "sg:province":"NY",
    "sg:tags":[
        "concrete",
        "contractor"
    ],
    "wof:name":"A L C Enterprises Inc",
    "wof:placetype":"venue"
},
  "geometry": {"coordinates":[-73.16456100000001,40.825686],"type":"Point"}
}