{
  "type": "Feature",
  "properties": {
    "addr:full":"6107 17th Ave Brooklyn NY 11204",
    "addr:housenumber":"6107",
    "addr:postcode":"11204",
    "addr:street":"17Th Ave",
    "iso:country":"US",
    "sg:address":"6107 17th Ave",
    "sg:city":"Brooklyn",
    "sg:classifiers":[
        {
            "category":"Professional",
            "subcategory":"Detective & Security Services",
            "type":"Services"
        }
    ],
    "sg:phone":"+1 718 232 6722",
    "sg:postcode":"11204",
    "sg:province":"NY",
    "sg:tags":[
        "investigator"
    ],
    "wof:name":"C Bellucci & Co",
    "wof:placetype":"venue"
},
  "geometry": {"coordinates":[-73.990588,40.62222],"type":"Point"}
}