{
  "type": "Feature",
  "properties": {
    "iso:country":"US",
    "sg:address":"69 Fuller Rd",
    "sg:city":"Albany",
    "sg:classifiers":[
        {
            "category":"Education",
            "subcategory":"Dance Studio",
            "type":"Public Place"
        }
    ],
    "sg:phone":"+1 518 459 2623",
    "sg:postcode":"12205",
    "sg:province":"NY",
    "sg:tags":[
        "instruction",
        "dancing"
    ],
    "wof:name":"Lorraine Michaels Dance Center",
    "wof:placetype":"venue"
},
  "geometry": {"coordinates":[-73.82589400000001,42.697718],"type":"Point"}
}