{
  "type": "Feature",
  "properties": {
    "addr:full":"540 E Meadow Ave East Meadow NY 11554",
    "addr:housenumber":"540",
    "addr:postcode":"11554",
    "addr:street":"E Meadow Ave",
    "iso:country":"US",
    "sg:address":"540 E Meadow Ave",
    "sg:city":"East Meadow",
    "sg:classifiers":[
        {
            "category":"Professional",
            "subcategory":"Business Services",
            "type":"Services"
        }
    ],
    "sg:phone":"+1 516 486 1163",
    "sg:postcode":"11554",
    "sg:province":"NY",
    "sg:tags":[
        "organizing"
    ],
    "wof:name":"Organize Anything LTD",
    "wof:placetype":"venue"
},
  "geometry": {"coordinates":[-73.555485,40.710975],"type":"Point"}
}