{
  "type": "Feature",
  "properties": {
    "addr:full":"801 2nd Avenue Lbby New York NY 10017",
    "addr:housenumber":"801",
    "addr:postcode":"10017",
    "addr:street":"2Nd Avenue",
    "iso:country":"US",
    "sg:address":"801 2nd Avenue Lbby",
    "sg:city":"New York",
    "sg:classifiers":[
        {
            "category":"Communications",
            "subcategory":"Newspaper",
            "type":"Services"
        }
    ],
    "sg:phone":"+1 212 681 7001",
    "sg:postcode":"10017",
    "sg:province":"NY",
    "sg:tags":[
        "magazine"
    ],
    "wof:name":"Agency Cultural & Technical Cooperation Permanent Observers",
    "wof:placetype":"venue"
},
  "geometry": {"coordinates":[-73.972352,40.749777],"type":"Point"}
}