{
  "type": "Feature",
  "properties": {
    "iso:country":"US",
    "sg:address":"51 Hempstead St",
    "sg:city":"Sag Harbor",
    "sg:classifiers":[
        {
            "category":"Professional",
            "subcategory":"Research",
            "type":"Services"
        }
    ],
    "sg:phone":"+1 631 725 1921",
    "sg:postcode":"11963",
    "sg:province":"NY",
    "sg:tags":[
        "environmental",
        "ecological"
    ],
    "wof:name":"Friends Of Havens Beach",
    "wof:placetype":"venue"
},
  "geometry": {"coordinates":[-72.283632,40.997277],"type":"Point"}
}