{
  "type": "Feature",
  "properties": {
    "addr:full":"27 Jackson Ave Long Island City NY 11101",
    "addr:housenumber":"27",
    "addr:postcode":"11101",
    "addr:street":"Jackson Ave",
    "iso:country":"US",
    "sg:address":"27 Jackson Ave",
    "sg:city":"Long Island City",
    "sg:classifiers":[
        {
            "category":"Restaurant",
            "type":"Food & Drink"
        }
    ],
    "sg:phone":"+1   ",
    "sg:postcode":"11101",
    "sg:province":"NY",
    "sg:tags":[
        "italian"
    ],
    "wof:name":"Manducatis Restrnt",
    "wof:placetype":"venue"
},
  "geometry": {"coordinates":[-73.940335,40.747879],"type":"Point"}
}