{
  "type": "Feature",
  "properties": {
    "iso:country":"US",
    "sg:address":"231 Sweeney Rd",
    "sg:city":"Potsdam",
    "sg:classifiers":[
        {
            "category":"Social Services",
            "type":"Services"
        }
    ],
    "sg:phone":"+1 315 265 3398",
    "sg:postcode":"13676",
    "sg:province":"NY",
    "sg:tags":[
        "organization",
        "welfare"
    ],
    "wof:name":"Reach For Help Counseling Svc",
    "wof:placetype":"venue"
},
  "geometry": {"coordinates":[-75.01049999999999,44.619335],"type":"Point"}
}