{
  "type": "Feature",
  "properties": {
    "addr:full":"3 Burns Ave Hicksville NY 11801",
    "addr:housenumber":"3",
    "addr:postcode":"11801",
    "addr:street":"Burns Ave",
    "iso:country":"US",
    "sg:address":"3 Burns Ave",
    "sg:city":"Hicksville",
    "sg:classifiers":[
        {
            "category":"Building & Trades",
            "subcategory":"Construction",
            "type":"Services"
        }
    ],
    "sg:phone":"+1 516 932 1414",
    "sg:postcode":"11801",
    "sg:province":"NY",
    "sg:tags":[
        "insulation",
        "heat",
        "contractor"
    ],
    "wof:name":"TELECOMMUNICATIONS Co",
    "wof:placetype":"venue"
},
  "geometry": {"coordinates":[-73.536056,40.767792],"type":"Point"}
}