{
  "type": "Feature",
  "properties": {
    "addr:full":"2921 James St Syracuse NY 13206",
    "addr:housenumber":"2921",
    "addr:postcode":"13206",
    "addr:street":"James St",
    "iso:country":"US",
    "sg:address":"2921 James St",
    "sg:city":"Syracuse",
    "sg:classifiers":[
        {
            "category":"Restaurant",
            "type":"Food & Drink"
        }
    ],
    "sg:menulink":"http://www.allmenus.com/ny/syracuse/80721-papa-johns-pizza/menu/",
    "sg:phone":"+1 315 463 7272",
    "sg:postcode":"13206",
    "sg:province":"NY",
    "sg:tags":[
        "american",
        "pizza"
    ],
    "wof:name":"Papa John's Pizza",
    "wof:placetype":"venue"
},
  "geometry": {"coordinates":[-76.106148,43.068852],"type":"Point"}
}