{
  "type": "Feature",
  "properties": {
    "addr:full":"8375 Wickham Blvd Sodus Point NY 14555",
    "addr:housenumber":"8375",
    "addr:postcode":"14555",
    "addr:street":"Wickham Blvd",
    "iso:country":"US",
    "sg:address":"8375 Wickham Blvd",
    "sg:city":"Sodus Point",
    "sg:classifiers":[
        {
            "category":"Travel",
            "subcategory":"Hotels & Motels",
            "type":"Entertainment"
        }
    ],
    "sg:phone":"+1 315 483 2100",
    "sg:postcode":"14555",
    "sg:province":"NY",
    "sg:tags":[
        "breakfast",
        "accommodation",
        "bed"
    ],
    "wof:name":"Carriage House Inn B & B",
    "wof:placetype":"venue"
},
  "geometry": {"coordinates":[-76.983891,43.271826],"type":"Point"}
}