{
  "type": "Feature",
  "properties": {
    "iso:country":"US",
    "sg:address":"1637 York Ave",
    "sg:city":"New York",
    "sg:classifiers":[
        {
            "category":"Shopping",
            "subcategory":"Pharmacy",
            "type":"Retail Goods"
        }
    ],
    "sg:phone":"+1 212 534 2000",
    "sg:postcode":"10028",
    "sg:province":"NY",
    "wof:name":"Gristede's Pharmacy",
    "wof:placetype":"venue"
},
  "geometry": {"coordinates":[-73.946776,40.77649],"type":"Point"}
}