{
  "type": "Feature",
  "properties": {
    "iso:country":"US",
    "sg:address":"444 E 75th St",
    "sg:city":"New York",
    "sg:classifiers":[
        {
            "category":"Health Services",
            "subcategory":"Doctor",
            "type":"Services"
        }
    ],
    "sg:phone":"+1 212 249 0072",
    "sg:postcode":"10021",
    "sg:province":"NY",
    "wof:name":"Feinberg Richard MD",
    "wof:placetype":"venue"
},
  "geometry": {"coordinates":[-73.953598,40.769299],"type":"Point"}
}