{
  "type": "Feature",
  "properties": {
    "addr:full":"261 Bayview Ave Amityville NY 11701",
    "addr:housenumber":"261",
    "addr:postcode":"11701",
    "addr:street":"Bayview Ave",
    "iso:country":"US",
    "sg:address":"261 Bayview Ave",
    "sg:city":"Amityville",
    "sg:classifiers":[
        {
            "category":"Building & Trades",
            "subcategory":"Construction",
            "type":"Services"
        }
    ],
    "sg:phone":"+1 631 264 4395",
    "sg:postcode":"11701",
    "sg:province":"NY",
    "sg:tags":[
        "residential"
    ],
    "wof:name":"Paul Wildfeir Home Improvs",
    "wof:placetype":"venue"
},
  "geometry": {"coordinates":[-73.40957899999999,40.678391],"type":"Point"}
}