{
  "type": "Feature",
  "properties": {
    "addr:full":"31 Paul Rd Rochester NY 14624",
    "addr:housenumber":"31",
    "addr:postcode":"14624",
    "addr:street":"Paul Rd",
    "iso:country":"US",
    "sg:address":"31 Paul Rd",
    "sg:city":"Rochester",
    "sg:classifiers":[
        {
            "category":"Restaurant",
            "type":"Food & Drink"
        }
    ],
    "sg:phone":"+1 585 235 3630",
    "sg:postcode":"14624",
    "sg:province":"NY",
    "sg:tags":[
        "banquet",
        "rooms"
    ],
    "wof:name":"River's Edge Rstrnt & Party Hs",
    "wof:placetype":"venue"
},
  "geometry": {"coordinates":[-77.674601,43.109137],"type":"Point"}
}