{
  "type": "Feature",
  "properties": {
    "addr:full":"6812 3rd Ave Brooklyn NY 11220",
    "addr:housenumber":"6812",
    "addr:postcode":"11220",
    "addr:street":"3Rd Ave",
    "iso:country":"US",
    "sg:address":"6812 3rd Ave",
    "sg:city":"Brooklyn",
    "sg:classifiers":[
        {
            "category":"Building & Trades",
            "subcategory":"Construction",
            "type":"Services"
        }
    ],
    "sg:phone":"+1 718 238 4700",
    "sg:postcode":"11220",
    "sg:province":"NY",
    "sg:tags":[
        "contractor"
    ],
    "wof:name":"John Michaels Contracting",
    "wof:placetype":"venue"
},
  "geometry": {"coordinates":[-74.026096,40.635809],"type":"Point"}
}