{
  "type": "Feature",
  "properties": {
    "addr:full":"1478 Oakfield Ave Wantagh NY 11793",
    "addr:housenumber":"1478",
    "addr:postcode":"11793",
    "addr:street":"Oakfield Ave",
    "iso:country":"US",
    "sg:address":"1478 Oakfield Ave",
    "sg:city":"Wantagh",
    "sg:classifiers":[
        {
            "category":"Restaurant",
            "type":"Food & Drink"
        }
    ],
    "sg:phone":"+1 516 783 8886",
    "sg:postcode":"11793",
    "sg:province":"NY",
    "wof:name":"Number 1 Son Noodle & Chinese",
    "wof:placetype":"venue"
},
  "geometry": {"coordinates":[-73.52203900000001,40.684088],"type":"Point"}
}