{
  "type": "Feature",
  "properties": {
    "addr:full":"2065 86th St Brooklyn NY 11214",
    "addr:housenumber":"2065",
    "addr:postcode":"11214",
    "addr:street":"86Th St",
    "iso:country":"US",
    "sg:address":"2065 86th St",
    "sg:city":"Brooklyn",
    "sg:classifiers":[
        {
            "category":"Restaurant",
            "type":"Food & Drink"
        }
    ],
    "sg:phone":"+1 718 449 6478",
    "sg:postcode":"11214",
    "sg:province":"NY",
    "wof:name":"Eat Fish LTD",
    "wof:placetype":"venue"
},
  "geometry": {"coordinates":[-73.996093,40.603401],"type":"Point"}
}