{
  "type": "Feature",
  "properties": {
    "addr:full":"94 W Islip Rd West Islip NY 11795",
    "addr:housenumber":"94",
    "addr:postcode":"11795",
    "addr:street":"W Islip Rd",
    "iso:country":"US",
    "sg:address":"94 W Islip Rd",
    "sg:city":"West Islip",
    "sg:classifiers":[
        {
            "category":"Retail",
            "subcategory":"Repair Shop",
            "type":"Services"
        }
    ],
    "sg:phone":"+1   ",
    "sg:postcode":"11795",
    "sg:province":"NY",
    "sg:tags":[
        "equipment",
        "mfg"
    ],
    "wof:name":"Tap-Rite Beer Line Cleaning",
    "wof:placetype":"venue"
},
  "geometry": {"coordinates":[-73.31639800000001,40.690585],"type":"Point"}
}