{
  "type": "Feature",
  "properties": {
    "iso:country":"US",
    "sg:address":"305 Maple St",
    "sg:city":"Endicott",
    "sg:classifiers":[
        {
            "category":"Organizations",
            "subcategory":"Community Association",
            "type":"Services"
        }
    ],
    "sg:phone":"+1 607 785 1700",
    "sg:postcode":"13760",
    "sg:province":"NY",
    "wof:name":"Square Deal Home Owners",
    "wof:placetype":"venue"
},
  "geometry": {"coordinates":[-76.071082,42.098359],"type":"Point"}
}