{
  "type": "Feature",
  "properties": {
    "addr:full":"800 Starbuck Ave Ste A-5 Watertown NY 13601",
    "addr:housenumber":"800",
    "addr:postcode":"13601",
    "addr:street":"Starbuck Ave Ste A-5",
    "iso:country":"US",
    "sg:address":"800 Starbuck Ave Ste A-5",
    "sg:city":"Watertown",
    "sg:classifiers":[
        {
            "category":"Health Services",
            "subcategory":"Clinic",
            "type":"Services"
        },
        {
            "category":"Health Services",
            "subcategory":"Nursing And Care Facility",
            "type":"Services"
        },
        {
            "category":"Health Services",
            "subcategory":"Health Practitioner",
            "type":"Services"
        }
    ],
    "sg:phone":"+1 315 755 2500",
    "sg:postcode":"13601",
    "sg:province":"NY",
    "sg:tags":[
        "home",
        "medical",
        "eldercare-home",
        "welfare"
    ],
    "wof:name":"Nny Rural Healthcare Alliance",
    "wof:placetype":"venue"
},
  "geometry": {"coordinates":[-75.895042,43.98558],"type":"Point"}
}