{
  "type": "Feature",
  "properties": {
    "iso:country":"US",
    "sg:address":"3795 River Rd",
    "sg:city":"Youngstown",
    "sg:classifiers":[
        {
            "category":"Wholesale",
            "subcategory":"Stationery",
            "type":"Manufacturing & Wholesale Goods"
        }
    ],
    "sg:phone":"+1 716 745 3207",
    "sg:postcode":"14174",
    "sg:province":"NY",
    "sg:tags":[
        "business",
        "form",
        "system"
    ],
    "wof:name":"Rooney Business Forms",
    "wof:placetype":"venue"
},
  "geometry": {"coordinates":[-79.051598,43.236512],"type":"Point"}
}