{
  "type": "Feature",
  "properties": {
    "iso:country":"US",
    "sg:address":"40 Burham Dr",
    "sg:city":"Smithtown",
    "sg:classifiers":[
        {
            "category":"Restaurant",
            "type":"Food & Drink"
        }
    ],
    "sg:phone":"+1 631 979 0431",
    "sg:postcode":"11787",
    "sg:province":"NY",
    "sg:tags":[
        "eating"
    ],
    "wof:name":"Kids Edible Creations Inc",
    "wof:placetype":"venue"
},
  "geometry": {"coordinates":[-73.212608,40.880102],"type":"Point"}
}