{
  "type": "Feature",
  "properties": {
    "addr:full":"8495 Smokey Hollow Rd Baldwinsville NY 13027",
    "addr:housenumber":"8495",
    "addr:postcode":"13027",
    "addr:street":"Smokey Hollow Rd",
    "iso:country":"US",
    "sg:address":"8495 Smokey Hollow Rd",
    "sg:city":"Baldwinsville",
    "sg:classifiers":[
        {
            "category":"Shopping",
            "subcategory":"Catalog Store",
            "type":"Retail Goods"
        }
    ],
    "sg:phone":"+1 315 635 0890",
    "sg:postcode":"13027",
    "sg:province":"NY",
    "sg:tags":[
        "mail",
        "order",
        "online"
    ],
    "wof:name":"Bridges Enterprise",
    "wof:placetype":"venue"
},
  "geometry": {"coordinates":[-76.340811,43.183443],"type":"Point"}
}