{
  "type": "Feature",
  "properties": {
    "iso:country":"US",
    "sg:address":"201 State Hwy 303",
    "sg:city":"Valley Cottage",
    "sg:classifiers":[
        {
            "category":"Retail",
            "subcategory":"Auto Repair",
            "type":"Services"
        }
    ],
    "sg:phone":"+1 845 268 3500",
    "sg:postcode":"10989",
    "sg:province":"NY",
    "sg:tags":[
        "repairing",
        "automobile"
    ],
    "wof:name":"Stiloski Automotive Corp",
    "wof:placetype":"venue"
},
  "geometry": {"coordinates":[-73.941374,41.125515],"type":"Point"}
}