{
  "type": "Feature",
  "properties": {
    "addr:full":"106 W 43rd St New York NY 10036",
    "addr:housenumber":"106",
    "addr:postcode":"10036",
    "addr:street":"W 43Rd St",
    "iso:country":"US",
    "sg:address":"106 W 43rd St",
    "sg:city":"New York",
    "sg:classifiers":[
        {
            "category":"Restaurant",
            "type":"Food & Drink"
        }
    ],
    "sg:menulink":"http://www.allmenus.com/ny/new-york/52632-teriyaki-boy/menu/",
    "sg:phone":"+1 212 764 0200",
    "sg:postcode":"10036",
    "sg:province":"NY",
    "sg:tags":[
        "japanese",
        "asian"
    ],
    "wof:name":"Teriyaki Boy",
    "wof:placetype":"venue"
},
  "geometry": {"coordinates":[-73.984309,40.75554],"type":"Point"}
}