{
  "type": "Feature",
  "properties": {
    "addr:full":"67 34th St Brooklyn NY 11232",
    "addr:housenumber":"67",
    "addr:postcode":"11232",
    "addr:street":"34Th St",
    "iso:country":"US",
    "sg:address":"67 34th St",
    "sg:city":"Brooklyn",
    "sg:classifiers":[
        {
            "category":"Manufacturing",
            "subcategory":"Paper Products",
            "type":"Manufacturing & Wholesale Goods"
        }
    ],
    "sg:phone":"+1   ",
    "sg:postcode":"11232",
    "sg:province":"NY",
    "sg:tags":[
        "p",
        "mfg",
        "bag"
    ],
    "wof:name":"Plastic Man The",
    "wof:placetype":"venue"
},
  "geometry": {"coordinates":[-74.006291,40.657542],"type":"Point"}
}