{
  "type": "Feature",
  "properties": {
    "iso:country":"US",
    "sg:address":"254 Quentin Rd Apt 5C",
    "sg:city":"Brooklyn",
    "sg:classifiers":[
        {
            "category":"Home & Garden",
            "subcategory":"Furniture",
            "type":"Retail Goods"
        }
    ],
    "sg:phone":"+1 718 513 4002",
    "sg:postcode":"11223",
    "sg:province":"NY",
    "sg:tags":[
        "store"
    ],
    "wof:name":"Ag Distributors Incorporated",
    "wof:placetype":"venue"
},
  "geometry": {"coordinates":[-73.97680099999999,40.606061],"type":"Point"}
}