{
  "type": "Feature",
  "properties": {
    "iso:country":"US",
    "sg:address":"731 White Plains Rd",
    "sg:city":"Scarsdale",
    "sg:classifiers":[
        {
            "category":"Personal",
            "subcategory":"Beauty Salon",
            "type":"Services"
        }
    ],
    "sg:phone":"+1 914 472 3917",
    "sg:postcode":"10583",
    "sg:province":"NY",
    "sg:website":"www.salonshin.com",
    "wof:name":"Salon Shin",
    "wof:placetype":"venue"
},
  "geometry": {"coordinates":[-73.80425099999999,40.972671],"type":"Point"}
}