{
  "type": "Feature",
  "properties": {
    "iso:country":"US",
    "sg:address":"342 Vine St",
    "sg:city":"Syracuse",
    "sg:classifiers":[
        {
            "category":"Organizations",
            "subcategory":"Religious Organization",
            "type":"Services"
        }
    ],
    "sg:phone":"+1 315 479 6689",
    "sg:postcode":"13203",
    "sg:province":"NY",
    "sg:tags":[
        "church"
    ],
    "wof:name":"Saint Vincent De Paul Church",
    "wof:placetype":"venue"
},
  "geometry": {"coordinates":[-76.125573,43.05456],"type":"Point"}
}