{
  "type": "Feature",
  "properties": {
    "iso:country":"US",
    "sg:address":"205 Oser Ave",
    "sg:city":"Hauppauge",
    "sg:classifiers":[
        {
            "category":"Banks & Credit Unions",
            "subcategory":"Investment Brokerage",
            "type":"Services"
        },
        {
            "category":"Banks & Credit Unions",
            "subcategory":"Financial Services",
            "type":"Services"
        }
    ],
    "sg:phone":"+1 631 851 0918",
    "sg:postcode":"11788",
    "sg:province":"NY",
    "sg:tags":[
        "advisory",
        "planner"
    ],
    "wof:name":"American Capital Partners",
    "wof:placetype":"venue"
},
  "geometry": {"coordinates":[-73.25366,40.816624],"type":"Point"}
}