{
  "type": "Feature",
  "properties": {
    "addr:full":"75 Bayview Ave Amityville NY 11701",
    "addr:housenumber":"75",
    "addr:postcode":"11701",
    "addr:street":"Bayview Ave",
    "iso:country":"US",
    "sg:address":"75 Bayview Ave",
    "sg:city":"Amityville",
    "sg:classifiers":[
        {
            "category":"Wholesale",
            "subcategory":"Electrical",
            "type":"Manufacturing & Wholesale Goods"
        }
    ],
    "sg:phone":"+1 631 264 0700",
    "sg:postcode":"11701",
    "sg:province":"NY",
    "sg:tags":[
        "fire",
        "alarm",
        "system"
    ],
    "wof:name":"Alarmlock Corp",
    "wof:placetype":"venue"
},
  "geometry": {"coordinates":[-73.40945600000001,40.670508],"type":"Point"}
}