{
  "type": "Feature",
  "properties": {
    "addr:full":"5 Catalina Dr Great Neck NY 11024",
    "addr:housenumber":"5",
    "addr:postcode":"11024",
    "addr:street":"Catalina Dr",
    "iso:country":"US",
    "sg:address":"5 Catalina Dr",
    "sg:city":"Great Neck",
    "sg:classifiers":[
        {
            "category":"Real Estate",
            "subcategory":"Architect",
            "type":"Services"
        }
    ],
    "sg:phone":"+1 516 466 1333",
    "sg:postcode":"11024",
    "sg:province":"NY",
    "wof:name":"United Construction",
    "wof:placetype":"venue"
},
  "geometry": {"coordinates":[-73.74296099999999,40.81551],"type":"Point"}
}