{
  "type": "Feature",
  "properties": {
    "addr:full":"321 State Hwy 59 Tallman NY 10901",
    "addr:housenumber":"321",
    "addr:postcode":"10901",
    "addr:street":"State Hwy 59",
    "iso:country":"US",
    "sg:address":"321 State Hwy 59",
    "sg:city":"Tallman",
    "sg:classifiers":[
        {
            "category":"Wholesale",
            "subcategory":"Jewelry",
            "type":"Manufacturing & Wholesale Goods"
        }
    ],
    "sg:phone":"+1 845 362 3800",
    "sg:postcode":"10901",
    "sg:province":"NY",
    "sg:tags":[
        "import",
        "pearl"
    ],
    "wof:name":"Panoply Trading Corp",
    "wof:placetype":"venue"
},
  "geometry": {"coordinates":[-74.09838499999999,41.110788],"type":"Point"}
}