{
  "type": "Feature",
  "properties": {
    "iso:country":"US",
    "sg:address":"1 W William St",
    "sg:city":"Corning",
    "sg:classifiers":[
        {
            "category":"Personal",
            "subcategory":"Beauty Salon",
            "type":"Services"
        }
    ],
    "sg:phone":"+1 607 937 6072",
    "sg:postcode":"14830",
    "sg:province":"NY",
    "wof:name":"Classic Hair Care",
    "wof:placetype":"venue"
},
  "geometry": {"coordinates":[-77.06187199999999,42.149918],"type":"Point"}
}