{
  "type": "Feature",
  "properties": {
    "addr:full":"46 Audrey Ave Oyster Bay NY 11771",
    "addr:housenumber":"46",
    "addr:postcode":"11771",
    "addr:street":"Audrey Ave",
    "iso:country":"US",
    "sg:address":"46 Audrey Ave",
    "sg:city":"Oyster Bay",
    "sg:classifiers":[
        {
            "category":"Restaurant",
            "type":"Food & Drink"
        }
    ],
    "sg:menulink":"http://www.allmenus.com/ny/oyster-bay/38292-canterbury-ales/menu/",
    "sg:phone":"+1 516 922 3614",
    "sg:postcode":"11771",
    "sg:province":"NY",
    "sg:tags":[
        "american"
    ],
    "wof:name":"Canterbury Ales",
    "wof:placetype":"venue"
},
  "geometry": {"coordinates":[-73.532287,40.873507],"type":"Point"}
}