{
  "type": "Feature",
  "properties": {
    "addr:full":"263 7th Ave Suite 2B Brooklyn NY 11215",
    "addr:housenumber":"263",
    "addr:postcode":"11215",
    "addr:street":"7Th Ave Suite 2B",
    "iso:country":"US",
    "sg:address":"263 7th Ave Suite 2B",
    "sg:city":"Brooklyn",
    "sg:classifiers":[
        {
            "category":"Health Services",
            "subcategory":"Health Practitioner",
            "type":"Services"
        }
    ],
    "sg:phone":"+1 718 689 3737",
    "sg:postcode":"11215",
    "sg:province":"NY",
    "sg:tags":[
        "acupuncture",
        "medicine",
        "alternative",
        "holistic"
    ],
    "sg:website":"http://www.acuherbnewyork.com",
    "wof:name":"Ming-Liang Jiang L.A.c.",
    "wof:placetype":"venue"
},
  "geometry": {"coordinates":[-73.97996000000001,40.66883],"type":"Point"}
}