{
  "type": "Feature",
  "properties": {
    "iso:country":"US",
    "sg:address":"17231 Roosevelt Hwy",
    "sg:city":"Kendall",
    "sg:classifiers":[
        {
            "category":"Manufacturing",
            "subcategory":"Tools & Machinery",
            "type":"Manufacturing & Wholesale Goods"
        }
    ],
    "sg:phone":"+1   ",
    "sg:postcode":"14476",
    "sg:province":"NY",
    "sg:tags":[
        "machine",
        "shop"
    ],
    "wof:name":"D M D Machining Technologies",
    "wof:placetype":"venue"
},
  "geometry": {"coordinates":[-78.01418,43.318619],"type":"Point"}
}