{
  "type": "Feature",
  "properties": {
    "iso:country":"US",
    "sg:address":"740 Broadway",
    "sg:city":"New York",
    "sg:classifiers":[
        {
            "category":"Health Services",
            "subcategory":"Clinic",
            "type":"Services"
        }
    ],
    "sg:phone":"+1 212 280 1031",
    "sg:postcode":"10003",
    "sg:province":"NY",
    "sg:tags":[
        "program",
        "rehabilitation",
        "drug"
    ],
    "wof:name":"Chelsea Tribeca Institute",
    "wof:placetype":"venue"
},
  "geometry": {"coordinates":[-73.99299000000001,40.729706],"type":"Point"}
}