{
  "type": "Feature",
  "properties": {
    "iso:country":"US",
    "sg:address":"136 Lawrence St",
    "sg:city":"Brooklyn",
    "sg:classifiers":[
        {
            "category":"Manufacturing",
            "subcategory":"Apparel",
            "type":"Manufacturing & Wholesale Goods"
        }
    ],
    "sg:phone":"+1   ",
    "sg:postcode":"11201",
    "sg:province":"NY",
    "sg:tags":[
        "outerwear",
        "mfg"
    ],
    "wof:name":"Sandra Paez Inc",
    "wof:placetype":"venue"
},
  "geometry": {"coordinates":[-73.986401,40.691167],"type":"Point"}
}