{
  "type": "Feature",
  "properties": {
    "iso:country":"US",
    "sg:address":"143 Pine St",
    "sg:city":"Corning",
    "sg:classifiers":[
        {
            "category":"Professional",
            "subcategory":"Lawyer & Legal Services",
            "type":"Services"
        }
    ],
    "sg:phone":"+1   ",
    "sg:postcode":"14830",
    "sg:province":"NY",
    "wof:name":"Attoney Esgrow & Gerweg",
    "wof:placetype":"venue"
},
  "geometry": {"coordinates":[-77.054928,42.142214],"type":"Point"}
}