{
  "type": "Feature",
  "properties": {
    "addr:full":"1256 Pleasant Rd Wantagh NY 11793",
    "addr:housenumber":"1256",
    "addr:postcode":"11793",
    "addr:street":"Pleasant Rd",
    "iso:country":"US",
    "sg:address":"1256 Pleasant Rd",
    "sg:city":"Wantagh",
    "sg:classifiers":[
        {
            "category":"Food & Beverages",
            "subcategory":"Groceries & Convenience Stores",
            "type":"Retail Goods"
        }
    ],
    "sg:phone":"+1   ",
    "sg:postcode":"11793",
    "sg:province":"NY",
    "wof:name":"Nesconset Deli Inc",
    "wof:placetype":"venue"
},
  "geometry": {"coordinates":[-73.500355,40.691415],"type":"Point"}
}