{
  "type": "Feature",
  "properties": {
    "addr:full":"1280 Montauk Hwy Oakdale NY 11769",
    "addr:housenumber":"1280",
    "addr:postcode":"11769",
    "addr:street":"Montauk Hwy",
    "iso:country":"US",
    "sg:address":"1280 Montauk Hwy",
    "sg:city":"Oakdale",
    "sg:classifiers":[
        {
            "category":"Shopping",
            "subcategory":"Gifts & Souvenirs",
            "type":"Retail Goods"
        }
    ],
    "sg:phone":"+1 631 589 8383",
    "sg:postcode":"11769",
    "sg:province":"NY",
    "sg:tags":[
        "basket",
        "fruit"
    ],
    "wof:name":"Busy Bee Florist",
    "wof:placetype":"venue"
},
  "geometry": {"coordinates":[-73.131829,40.742304],"type":"Point"}
}