{
  "type": "Feature",
  "properties": {
    "iso:country":"US",
    "sg:address":"1259 Clay Ave",
    "sg:city":"Bronx",
    "sg:classifiers":[
        {
            "category":"Professional",
            "type":"Services"
        }
    ],
    "sg:phone":"+1 718 410 7620",
    "sg:postcode":"10456",
    "sg:province":"NY",
    "sg:tags":[
        "establishment"
    ],
    "wof:name":"Bozart Associates",
    "wof:placetype":"venue"
},
  "geometry": {"coordinates":[-73.91003000000001,40.833337],"type":"Point"}
}