{
  "type": "Feature",
  "properties": {
    "iso:country":"US",
    "sg:address":"860 Linden Ave",
    "sg:city":"Rochester",
    "sg:classifiers":[
        {
            "category":"Professional",
            "subcategory":"Business Services",
            "type":"Services"
        }
    ],
    "sg:phone":"+1 585 385 9910",
    "sg:postcode":"14625",
    "sg:province":"NY",
    "sg:tags":[
        "labeling"
    ],
    "wof:name":"Page Ii Packaging Inc",
    "wof:placetype":"venue"
},
  "geometry": {"coordinates":[-77.49753800000001,43.119684],"type":"Point"}
}