{
  "type": "Feature",
  "properties": {
    "addr:full":"847 53rd St Brooklyn NY 11220",
    "addr:housenumber":"847",
    "addr:postcode":"11220",
    "addr:street":"53Rd St",
    "iso:country":"US",
    "sg:address":"847 53rd St",
    "sg:city":"Brooklyn",
    "sg:classifiers":[
        {
            "category":"Professional",
            "type":"Services"
        }
    ],
    "sg:phone":"+1   ",
    "sg:postcode":"11220",
    "sg:province":"NY",
    "wof:name":"Love 99 Inc",
    "wof:placetype":"venue"
},
  "geometry": {"coordinates":[-74.003991,40.638787],"type":"Point"}
}