{
  "type": "Feature",
  "properties": {
    "addr:full":"1555 Islip Ave Central Islip NY 11722",
    "addr:housenumber":"1555",
    "addr:postcode":"11722",
    "addr:street":"Islip Ave",
    "iso:country":"US",
    "sg:address":"1555 Islip Ave",
    "sg:city":"Central Islip",
    "sg:classifiers":[
        {
            "category":"Retail",
            "subcategory":"Laundry & Dry Cleaning",
            "type":"Services"
        }
    ],
    "sg:phone":"+1   ",
    "sg:postcode":"11722",
    "sg:province":"NY",
    "sg:tags":[
        "coin",
        "power"
    ],
    "wof:name":"Laundry World Ltd",
    "wof:placetype":"venue"
},
  "geometry": {"coordinates":[-73.217179,40.780786],"type":"Point"}
}