{
  "type": "Feature",
  "properties": {
    "iso:country":"US",
    "sg:address":"24 Old Albany Post Rd",
    "sg:city":"Croton On Hudson",
    "sg:classifiers":[
        {
            "category":"Health Services",
            "subcategory":"Health Practitioner",
            "type":"Services"
        }
    ],
    "sg:phone":"+1 914 737 2701",
    "sg:postcode":"10520",
    "sg:province":"NY",
    "sg:tags":[
        "therapist",
        "physical"
    ],
    "wof:name":"Fair Mountain Physical Therapy",
    "wof:placetype":"venue"
},
  "geometry": {"coordinates":[-73.917062,41.236244],"type":"Point"}
}