{
  "type": "Feature",
  "properties": {
    "addr:full":"41 Entrance Way Mahopac NY 10541",
    "addr:housenumber":"41",
    "addr:postcode":"10541",
    "addr:street":"Entrance Way",
    "iso:country":"US",
    "sg:address":"41 Entrance Way",
    "sg:city":"Mahopac",
    "sg:phone":"+1 845 621 0859",
    "sg:postcode":"10541",
    "sg:province":"NY",
    "sg:tags":[
        "oil"
    ],
    "wof:name":"Northern Fuel Corp",
    "wof:placetype":"venue"
},
  "geometry": {"coordinates":[-73.78913799999999,41.371739],"type":"Point"}
}