{
  "type": "Feature",
  "properties": {
    "addr:full":"900 Jericho Tpke New Hyde Park NY 11040",
    "addr:housenumber":"900",
    "addr:postcode":"11040",
    "addr:street":"Jericho Tpke;Hyde Park",
    "iso:country":"US",
    "sg:address":"900 Jericho Tpke",
    "sg:city":"New Hyde Park",
    "sg:classifiers":[
        {
            "category":"Food & Beverages",
            "subcategory":"Liquor & Beverages",
            "type":"Retail Goods"
        }
    ],
    "sg:phone":"+1   ",
    "sg:postcode":"11040",
    "sg:province":"NY",
    "sg:tags":[
        "alcoholic"
    ],
    "wof:name":"Vinjim Liquors Inc",
    "wof:placetype":"venue"
},
  "geometry": {"coordinates":[-73.685863,40.732431],"type":"Point"}
}