{
  "type": "Feature",
  "properties": {
    "iso:country":"US",
    "sg:address":"480 Park Ave",
    "sg:city":"New York",
    "sg:classifiers":[
        {
            "category":"Professional",
            "subcategory":"Lawyer & Legal Services",
            "type":"Services"
        }
    ],
    "sg:phone":"+1 212 758 4200",
    "sg:postcode":"10022",
    "sg:province":"NY",
    "sg:tags":[
        "attorney"
    ],
    "wof:name":"Brookman & Brookman",
    "wof:placetype":"venue"
},
  "geometry": {"coordinates":[-73.96994599999999,40.762805],"type":"Point"}
}