{
  "type": "Feature",
  "properties": {
    "iso:country":"US",
    "sg:address":"4730 Onondaga Blvd",
    "sg:city":"Syracuse",
    "sg:classifiers":[
        {
            "category":"Shopping",
            "subcategory":"Shoes",
            "type":"Retail Goods"
        }
    ],
    "sg:phone":"+1   ",
    "sg:postcode":"13219",
    "sg:province":"NY",
    "sg:tags":[
        "family"
    ],
    "wof:name":"Rochester Shoe Store Inc",
    "wof:placetype":"venue"
},
  "geometry": {"coordinates":[-76.194176,43.032117],"type":"Point"}
}