{
  "type": "Feature",
  "properties": {
    "iso:country":"US",
    "sg:address":"31 State St",
    "sg:city":"Saranac Lake",
    "sg:classifiers":[
        {
            "category":"Recreation",
            "subcategory":"Marina",
            "type":"Entertainment"
        }
    ],
    "sg:phone":"+1 518 891 4780",
    "sg:postcode":"12983",
    "sg:province":"NY",
    "sg:tags":[
        "repairing",
        "boat"
    ],
    "wof:name":"Ampersand Garden Boat Shop",
    "wof:placetype":"venue"
},
  "geometry": {"coordinates":[-74.15499699999999,44.316998],"type":"Point"}
}