{
  "type": "Feature",
  "properties": {
    "addr:full":"2830 North Rd Vernon Center NY 13477",
    "addr:housenumber":"2830",
    "addr:postcode":"13477",
    "addr:street":"North Rd",
    "iso:country":"US",
    "sg:address":"2830 North Rd",
    "sg:city":"Vernon Center",
    "sg:classifiers":[
        {
            "category":"Building & Trades",
            "subcategory":"Construction",
            "type":"Services"
        }
    ],
    "sg:phone":"+1 315 853 3107",
    "sg:postcode":"13477",
    "sg:province":"NY",
    "sg:tags":[
        "roofing",
        "contractor"
    ],
    "wof:name":"Scalzo General Contracting",
    "wof:placetype":"venue"
},
  "geometry": {"coordinates":[-75.517183,42.986563],"type":"Point"}
}