{
  "type": "Feature",
  "properties": {
    "iso:country":"US",
    "sg:address":"25 Rockledge Rd Ste M",
    "sg:city":"Hartsdale",
    "sg:classifiers":[
        {
            "category":"Retail",
            "subcategory":"Repair Shop",
            "type":"Services"
        }
    ],
    "sg:phone":"+1 914 723 8669",
    "sg:postcode":"10530",
    "sg:province":"NY",
    "sg:tags":[
        "small",
        "major",
        "appliance",
        "refinishing"
    ],
    "wof:name":"Arnie's Repr Svce",
    "wof:placetype":"venue"
},
  "geometry": {"coordinates":[-73.795345,41.013332],"type":"Point"}
}