{
  "type": "Feature",
  "properties": {
    "addr:full":"3080 W Main Street Rd Batavia NY 14020",
    "addr:housenumber":"3080",
    "addr:postcode":"14020",
    "addr:street":"W Main Street Rd",
    "iso:country":"US",
    "sg:address":"3080 W Main Street Rd",
    "sg:city":"Batavia",
    "sg:classifiers":[
        {
            "category":"Shopping",
            "type":"Retail Goods"
        }
    ],
    "sg:phone":"+1 585 762 6510",
    "sg:postcode":"14020",
    "sg:province":"NY",
    "sg:tags":[
        "cosmetic",
        "perfume"
    ],
    "wof:name":"Avon",
    "wof:placetype":"venue"
},
  "geometry": {"coordinates":[-78.26561,43.00021],"type":"Point"}
}