{
  "type": "Feature",
  "properties": {
    "iso:country":"US",
    "sg:address":"29 East Broadway",
    "sg:city":"Manhattan",
    "sg:classifiers":[
        {
            "category":"Shopping",
            "subcategory":"Books",
            "type":"Retail Goods"
        }
    ],
    "sg:phone":"+1 212 962 3634",
    "sg:postcode":"10002",
    "sg:province":"NY",
    "sg:tags":[
        "bookstore"
    ],
    "wof:name":"Oriental Books & Stationery Co., Inc.",
    "wof:placetype":"venue"
},
  "geometry": {"coordinates":[-73.996619,40.713287],"type":"Point"}
}