{
  "type": "Feature",
  "properties": {
    "addr:full":"727 Maple Rd Buffalo NY 14221",
    "addr:housenumber":"727",
    "addr:postcode":"14221",
    "addr:street":"Maple Rd",
    "iso:country":"US",
    "sg:address":"727 Maple Rd",
    "sg:city":"Buffalo",
    "sg:classifiers":[
        {
            "category":"Food & Beverages",
            "subcategory":"Groceries & Convenience Stores",
            "type":"Retail Goods"
        }
    ],
    "sg:phone":"+1   ",
    "sg:postcode":"14221",
    "sg:province":"NY",
    "sg:tags":[
        "station",
        "gasoline"
    ],
    "wof:name":"Robo",
    "wof:placetype":"venue"
},
  "geometry": {"coordinates":[-78.760723,42.991057],"type":"Point"}
}