{
  "type": "Feature",
  "properties": {
    "addr:full":"142 98th St Brooklyn NY 11209",
    "addr:housenumber":"142",
    "addr:postcode":"11209",
    "addr:street":"98Th St",
    "iso:country":"US",
    "sg:address":"142 98th St",
    "sg:city":"Brooklyn",
    "sg:classifiers":[
        {
            "category":"Professional",
            "subcategory":"Lawyer & Legal Services",
            "type":"Services"
        }
    ],
    "sg:phone":"+1   ",
    "sg:postcode":"11209",
    "sg:province":"NY",
    "wof:name":"Star Medical Offices PC",
    "wof:placetype":"venue"
},
  "geometry": {"coordinates":[-74.03628399999999,40.614741],"type":"Point"}
}