{
  "type": "Feature",
  "properties": {
    "addr:full":"100 Van Patten Ln Albany NY 12203",
    "addr:housenumber":"100",
    "addr:postcode":"12203",
    "addr:street":"Van Patten Ln",
    "iso:country":"US",
    "sg:address":"100 Van Patten Ln",
    "sg:city":"Albany",
    "sg:classifiers":[
        {
            "category":"Building & Trades",
            "subcategory":"Plumbing",
            "type":"Services"
        }
    ],
    "sg:phone":"+1 518 456 0020",
    "sg:postcode":"12203",
    "sg:province":"NY",
    "sg:tags":[
        "contractor"
    ],
    "wof:name":"E H Laier & Sons",
    "wof:placetype":"venue"
},
  "geometry": {"coordinates":[-73.864932,42.693645],"type":"Point"}
}