{
  "type": "Feature",
  "properties": {
    "iso:country":"US",
    "sg:address":"278 Burnside Ave",
    "sg:city":"Lawrence",
    "sg:classifiers":[
        {
            "category":"Restaurant",
            "type":"Food & Drink"
        }
    ],
    "sg:phone":"+1 516 239 2227",
    "sg:postcode":"11559",
    "sg:province":"NY",
    "sg:tags":[
        "pizza"
    ],
    "wof:name":"Mauro's Pizzeria & Restrnt",
    "wof:placetype":"venue"
},
  "geometry": {"coordinates":[-73.737999,40.623699],"type":"Point"}
}