{
  "type": "Feature",
  "properties": {
    "addr:full":"10 Executive Blvd Farmingdale NY 11735",
    "addr:housenumber":"10",
    "addr:postcode":"11735",
    "addr:street":"Executive Blvd",
    "iso:country":"US",
    "sg:address":"10 Executive Blvd",
    "sg:city":"Farmingdale",
    "sg:classifiers":[
        {
            "category":"Food & Beverages",
            "subcategory":"Specialty",
            "type":"Retail Goods"
        }
    ],
    "sg:phone":"+1 516 756 0555",
    "sg:postcode":"11735",
    "sg:province":"NY",
    "sg:tags":[
        "vitamin"
    ],
    "wof:name":"Natural Organics",
    "wof:placetype":"venue"
},
  "geometry": {"coordinates":[-73.428134,40.719127],"type":"Point"}
}