{
  "type": "Feature",
  "properties": {
    "iso:country":"US",
    "sg:address":"393 Clinton St",
    "sg:city":"Hempstead",
    "sg:classifiers":[
        {
            "category":"Education",
            "subcategory":"Music School",
            "type":"Public Place"
        }
    ],
    "sg:phone":"+1 516 564 7528",
    "sg:postcode":"11550",
    "sg:province":"NY",
    "sg:tags":[
        "instrument",
        "teacher",
        "musical"
    ],
    "wof:name":"Mundo.Com Inc",
    "wof:placetype":"venue"
},
  "geometry": {"coordinates":[-73.62090499999999,40.717926],"type":"Point"}
}