{
  "type": "Feature",
  "properties": {
    "addr:full":"State University of New York 33 W 42nd St New York NY 10036",
    "addr:housenumber":"33",
    "addr:postcode":"10036",
    "addr:street":"W 42Nd St",
    "iso:country":"US",
    "sg:address":"State University of New York 33 W 42nd St",
    "sg:city":"New York",
    "sg:classifiers":[
        {
            "category":"Health Services",
            "subcategory":"Optometrist",
            "type":"Services"
        },
        {
            "category":"Education",
            "subcategory":"University",
            "type":"Public Place"
        }
    ],
    "sg:phone":"+1 212 938 4000",
    "sg:postcode":"10036",
    "sg:province":"NY",
    "sg:tags":[
        "college"
    ],
    "sg:website":"www.sunyopt.edu",
    "wof:name":"College of Optometry",
    "wof:placetype":"venue"
},
  "geometry": {"coordinates":[-73.982692,40.754269],"type":"Point"}
}