{
  "type": "Feature",
  "properties": {
    "iso:country":"US",
    "sg:address":"4707 Arthur Kill Rd",
    "sg:city":"Staten Island",
    "sg:classifiers":[
        {
            "category":"Retail",
            "subcategory":"Pet Boarding",
            "type":"Services"
        }
    ],
    "sg:phone":"+1 718 984 9663",
    "sg:postcode":"10309",
    "sg:province":"NY",
    "sg:tags":[
        "boarding/pet",
        "sitting"
    ],
    "sg:website":"www.campbowwow.com/statenisland",
    "wof:name":"Camp Bow Wow Staten Island",
    "wof:placetype":"venue"
},
  "geometry": {"coordinates":[-74.23936500000001,40.52779],"type":"Point"}
}