{
  "type": "Feature",
  "properties": {
    "addr:full":"198 E Boston Post Rd Mamaroneck NY 10543",
    "addr:housenumber":"198",
    "addr:postcode":"10543",
    "addr:street":"E Boston Post Rd",
    "iso:country":"US",
    "sg:address":"198 E Boston Post Rd",
    "sg:city":"Mamaroneck",
    "sg:classifiers":[
        {
            "category":"Local Transit",
            "type":"Transportation"
        }
    ],
    "sg:phone":"+1 914 381 8585",
    "sg:postcode":"10543",
    "sg:province":"NY",
    "sg:tags":[
        "limousine"
    ],
    "wof:name":"Dolphin Limousines LLC",
    "wof:placetype":"venue"
},
  "geometry": {"coordinates":[-73.731994,40.949239],"type":"Point"}
}