{
  "type": "Feature",
  "properties": {
    "addr:full":"84 Hawthorne Ave Buffalo NY 14223",
    "addr:housenumber":"84",
    "addr:postcode":"14223",
    "addr:street":"Hawthorne Ave",
    "iso:country":"US",
    "sg:address":"84 Hawthorne Ave",
    "sg:city":"Buffalo",
    "sg:classifiers":[
        {
            "category":"Government",
            "subcategory":"Fire Station",
            "type":"Public Place"
        }
    ],
    "sg:phone":"+1 716 838 1219",
    "sg:postcode":"14223",
    "sg:province":"NY",
    "sg:tags":[
        "department"
    ],
    "wof:name":"Kenilworth Fire Dept",
    "wof:placetype":"venue"
},
  "geometry": {"coordinates":[-78.825981,42.958727],"type":"Point"}
}