{
  "type": "Feature",
  "properties": {
    "addr:full":"1572 149th St Whitestone NY 11357",
    "addr:housenumber":"1572",
    "addr:postcode":"11357",
    "addr:street":"149Th St",
    "iso:country":"US",
    "sg:address":"1572 149th St",
    "sg:city":"Whitestone",
    "sg:classifiers":[
        {
            "category":"Deli",
            "type":"Food & Drink"
        }
    ],
    "sg:phone":"+1 718 746 0583",
    "sg:postcode":"11357",
    "sg:province":"NY",
    "wof:name":"Varsi Deli",
    "wof:placetype":"venue"
},
  "geometry": {"coordinates":[-73.816597,40.785198],"type":"Point"}
}