{
  "type": "Feature",
  "properties": {
    "addr:full":"638 Albany Shaker Rd Albany NY 12211",
    "addr:housenumber":"638",
    "addr:postcode":"12211",
    "addr:street":"Albany Shaker Rd",
    "iso:country":"US",
    "sg:address":"638 Albany Shaker Rd",
    "sg:city":"Albany",
    "sg:classifiers":[
        {
            "category":"Professional",
            "subcategory":"Advertising",
            "type":"Services"
        }
    ],
    "sg:phone":"+1 518 446 1091",
    "sg:postcode":"12211",
    "sg:province":"NY",
    "sg:tags":[
        "counselor"
    ],
    "sg:website":"www.rueckertadvertising.com",
    "wof:name":"Rueckert Advertising",
    "wof:placetype":"venue"
},
  "geometry": {"coordinates":[-73.79482299999999,42.727275],"type":"Point"}
}