{
  "type": "Feature",
  "properties": {
    "iso:country":"US",
    "sg:address":"2 Cortland St",
    "sg:city":"Marathon",
    "sg:classifiers":[
        {
            "category":"Restaurant",
            "type":"Food & Drink"
        }
    ],
    "sg:phone":"+1 607 849 6655",
    "sg:postcode":"13803",
    "sg:province":"NY",
    "wof:name":"Kathy's Diner",
    "wof:placetype":"venue"
},
  "geometry": {"coordinates":[-76.03283399999999,42.442243],"type":"Point"}
}