{
  "type": "Feature",
  "properties": {
    "iso:country":"US",
    "sg:address":"175 Post Rd",
    "sg:city":"Old Westbury",
    "sg:classifiers":[
        {
            "category":"Shopping",
            "subcategory":"Bicycles & Sporting Goods",
            "type":"Retail Goods"
        }
    ],
    "sg:phone":"+1 516 625 1422",
    "sg:postcode":"11568",
    "sg:province":"NY",
    "sg:tags":[
        "equipment",
        "golf",
        "supply"
    ],
    "wof:name":"Timothy M Shifflett Inc",
    "wof:placetype":"venue"
},
  "geometry": {"coordinates":[-73.58772,40.787783],"type":"Point"}
}