{
  "type": "Feature",
  "properties": {
    "addr:full":"311 Richfield Blvd Mattydale NY 13211",
    "addr:housenumber":"311",
    "addr:postcode":"13211",
    "addr:street":"Richfield Blvd",
    "iso:country":"US",
    "sg:address":"311 Richfield Blvd",
    "sg:city":"Mattydale",
    "sg:classifiers":[
        {
            "category":"Real Estate",
            "subcategory":"Real Estate Agent",
            "type":"Services"
        }
    ],
    "sg:phone":"+1 315 455 3176",
    "sg:postcode":"13211",
    "sg:province":"NY",
    "wof:name":"PHH Mortgage Svc",
    "wof:placetype":"venue"
},
  "geometry": {"coordinates":[-76.155913,43.095101],"type":"Point"}
}