{
  "type": "Feature",
  "properties": {
    "addr:full":"18 Newbridge Rd Hicksville NY 11801",
    "addr:housenumber":"18",
    "addr:postcode":"11801",
    "addr:street":"Newbridge Rd",
    "iso:country":"US",
    "sg:address":"18 Newbridge Rd",
    "sg:city":"Hicksville",
    "sg:classifiers":[
        {
            "category":"Shopping",
            "subcategory":"Gifts & Souvenirs",
            "type":"Retail Goods"
        }
    ],
    "sg:phone":"+1 516 681 1832",
    "sg:postcode":"11801",
    "sg:province":"NY",
    "sg:tags":[
        "basket",
        "parcel"
    ],
    "wof:name":"Basket Master",
    "wof:placetype":"venue"
},
  "geometry": {"coordinates":[-73.527632,40.767594],"type":"Point"}
}