{
  "type": "Feature",
  "properties": {
    "iso:country":"US",
    "sg:address":"1517 Main St",
    "sg:city":"Niagara Falls",
    "sg:classifiers":[
        {
            "category":"Shopping",
            "type":"Retail Goods"
        }
    ],
    "sg:phone":"+1 716 284 8875",
    "sg:postcode":"14305",
    "sg:province":"NY",
    "sg:tags":[
        "picture",
        "frame"
    ],
    "wof:name":"Main Custom Picture Framing",
    "wof:placetype":"venue"
},
  "geometry": {"coordinates":[-79.05237200000001,43.103443],"type":"Point"}
}