{
  "type": "Feature",
  "properties": {
    "iso:country":"US",
    "sg:address":"77 S West St",
    "sg:city":"Homer",
    "sg:classifiers":[
        {
            "category":"Banks & Credit Unions",
            "subcategory":"Bank",
            "type":"Services"
        }
    ],
    "sg:phone":"+1 607 749 7251",
    "sg:postcode":"13077",
    "sg:province":"NY",
    "sg:tags":[
        "loan",
        "real estate"
    ],
    "wof:name":"Countrywide Home Loans",
    "wof:placetype":"venue"
},
  "geometry": {"coordinates":[-76.19180900000001,42.62955],"type":"Point"}
}