{
  "type": "Feature",
  "properties": {
    "iso:country":"US",
    "sg:address":"3445 Big Ridge Rd",
    "sg:city":"Spencerport",
    "sg:classifiers":[
        {
            "category":"Shopping",
            "subcategory":"Musical Instruments",
            "type":"Retail Goods"
        }
    ],
    "sg:phone":"+1 585 352 0119",
    "sg:postcode":"14559",
    "sg:province":"NY",
    "wof:name":"Kidtarz",
    "wof:placetype":"venue"
},
  "geometry": {"coordinates":[-77.77333900000001,43.1947],"type":"Point"}
}