{
  "type": "Feature",
  "properties": {
    "iso:country":"US",
    "sg:address":"119 W 57th Street",
    "sg:city":"New York",
    "sg:classifiers":[
        {
            "category":"Health Services",
            "subcategory":"Dentist",
            "type":"Services"
        }
    ],
    "sg:phone":"+1 212 581 0986",
    "sg:postcode":"10019",
    "sg:province":"NY",
    "wof:name":"Mid-Manhattan Dental PC",
    "wof:placetype":"venue"
},
  "geometry": {"coordinates":[-73.97771299999999,40.764561],"type":"Point"}
}