{
  "type": "Feature",
  "properties": {
    "iso:country":"US",
    "sg:address":"1599 Lexington Avenue",
    "sg:city":"New York",
    "sg:classifiers":[
        {
            "category":"Autos & Motor Vehicles",
            "subcategory":"Fuel & Gas Station",
            "type":"Retail Goods"
        }
    ],
    "sg:phone":"+1 212 289 7399",
    "sg:postcode":"10029",
    "sg:province":"NY",
    "wof:name":"1599 Lexington Av Svce Sta",
    "wof:placetype":"venue"
},
  "geometry": {"coordinates":[-73.943382,40.791007],"type":"Point"}
}