{
  "type": "Feature",
  "properties": {
    "addr:full":"77 Hillside Rd Penfield NY 14526",
    "addr:housenumber":"77",
    "addr:postcode":"14526",
    "addr:street":"Hillside Rd",
    "iso:country":"US",
    "sg:address":"77 Hillside Rd",
    "sg:city":"Penfield",
    "sg:classifiers":[
        {
            "category":"Organizations",
            "subcategory":"Religious Organization",
            "type":"Services"
        }
    ],
    "sg:phone":"+1 585 872 7920",
    "sg:postcode":"14526",
    "sg:province":"NY",
    "wof:name":"Healing Rooms Of Rochester NY",
    "wof:placetype":"venue"
},
  "geometry": {"coordinates":[-77.46076100000001,43.127443],"type":"Point"}
}