{
  "type": "Feature",
  "properties": {
    "addr:full":"31 Mahan St West Babylon NY 11704",
    "addr:housenumber":"31",
    "addr:postcode":"11704",
    "addr:street":"Mahan St",
    "iso:country":"US",
    "sg:address":"31 Mahan St",
    "sg:city":"West Babylon",
    "sg:classifiers":[
        {
            "category":"Professional",
            "type":"Services"
        }
    ],
    "sg:phone":"+1 631 253 4864",
    "sg:postcode":"11704",
    "sg:province":"NY",
    "sg:tags":[
        "establishment"
    ],
    "wof:name":"Paquet Assocs",
    "wof:placetype":"venue"
},
  "geometry": {"coordinates":[-73.375339,40.734409],"type":"Point"}
}