{
  "type": "Feature",
  "properties": {
    "iso:country":"US",
    "sg:address":"33 Brigham St",
    "sg:city":"Kingston",
    "sg:classifiers":[
        {
            "category":"Building & Trades",
            "subcategory":"Construction",
            "type":"Services"
        }
    ],
    "sg:phone":"+1 845 336 4731",
    "sg:postcode":"12401",
    "sg:province":"NY",
    "sg:tags":[
        "contractor",
        "carpenter",
        "carpentry"
    ],
    "wof:name":"Lund Construction",
    "wof:placetype":"venue"
},
  "geometry": {"coordinates":[-73.96822400000001,41.955001],"type":"Point"}
}