{
  "type": "Feature",
  "properties": {
    "addr:full":"133 Convent Ave New York NY 10031",
    "addr:housenumber":"133",
    "addr:postcode":"10031",
    "addr:street":"Convent Ave",
    "iso:country":"US",
    "sg:address":"133 Convent Ave",
    "sg:city":"New York",
    "sg:classifiers":[
        {
            "category":"Social Services",
            "subcategory":"Child Care",
            "type":"Services"
        }
    ],
    "sg:phone":"+1 212 650 8616",
    "sg:postcode":"10031",
    "sg:province":"NY",
    "sg:tags":[
        "day"
    ],
    "wof:name":"Child Development Center",
    "wof:placetype":"venue"
},
  "geometry": {"coordinates":[-73.951453,40.817889],"type":"Point"}
}