{
  "type": "Feature",
  "properties": {
    "addr:full":"172 South St New York NY 10038",
    "addr:housenumber":"172",
    "addr:postcode":"10038",
    "addr:street":"South St",
    "iso:country":"US",
    "sg:address":"172 South St",
    "sg:city":"New York",
    "sg:classifiers":[
        {
            "category":"Food & Beverages",
            "subcategory":"Groceries & Convenience Stores",
            "type":"Retail Goods"
        }
    ],
    "sg:phone":"+1 718 273 7027",
    "sg:postcode":"10038",
    "sg:province":"NY",
    "sg:tags":[
        "grocer"
    ],
    "wof:name":"Jasmin Food Market Inc",
    "wof:placetype":"venue"
},
  "geometry": {"coordinates":[-73.999979,40.708526],"type":"Point"}
}