{
  "type": "Feature",
  "properties": {
    "iso:country":"US",
    "sg:address":"5012 New Utrecht Ave",
    "sg:city":"Brooklyn",
    "sg:classifiers":[
        {
            "category":"Retail",
            "subcategory":"Laundry & Dry Cleaning",
            "type":"Services"
        }
    ],
    "sg:phone":"+1 718 438 4243",
    "sg:postcode":"11219",
    "sg:province":"NY",
    "wof:name":"Moishe's Dry Cleaners",
    "wof:placetype":"venue"
},
  "geometry": {"coordinates":[-73.995003,40.6353],"type":"Point"}
}