{
  "type": "Feature",
  "properties": {
    "addr:full":"454 Locust Ave Amsterdam NY 12010",
    "addr:housenumber":"454",
    "addr:postcode":"12010",
    "addr:street":"Locust Ave",
    "iso:country":"US",
    "sg:address":"454 Locust Ave",
    "sg:city":"Amsterdam",
    "sg:classifiers":[
        {
            "category":"Retail",
            "subcategory":"Portrait Studio",
            "type":"Services"
        }
    ],
    "sg:phone":"+1 518 842 5090",
    "sg:postcode":"12010",
    "sg:province":"NY",
    "sg:tags":[
        "photography"
    ],
    "wof:name":"Images By DC",
    "wof:placetype":"venue"
},
  "geometry": {"coordinates":[-74.176885,42.957474],"type":"Point"}
}