{
  "type": "Feature",
  "properties": {
    "iso:country":"US",
    "sg:address":"38 Kinsey Pl",
    "sg:city":"Staten Island",
    "sg:classifiers":[
        {
            "category":"Building & Trades",
            "subcategory":"Construction",
            "type":"Services"
        }
    ],
    "sg:phone":"+1 718 720 6966",
    "sg:postcode":"10303",
    "sg:province":"NY",
    "sg:tags":[
        "excavating",
        "contractor"
    ],
    "sg:website":"www.difazioconstruction.com",
    "wof:name":"Di Fazio & Sons Contractors",
    "wof:placetype":"venue"
},
  "geometry": {"coordinates":[-74.17033600000001,40.628575],"type":"Point"}
}