{
  "type": "Feature",
  "properties": {
    "addr:full":"5 S Moger Ave Mount Kisco NY 10549",
    "addr:housenumber":"5",
    "addr:postcode":"10549",
    "addr:street":"S Moger Ave",
    "iso:country":"US",
    "sg:address":"5 S Moger Ave",
    "sg:city":"Mount Kisco",
    "sg:classifiers":[
        {
            "category":"Shopping",
            "subcategory":"Optician",
            "type":"Retail Goods"
        }
    ],
    "sg:phone":"+1 914 241 0625",
    "sg:postcode":"10549",
    "sg:province":"NY",
    "sg:tags":[
        "eyewear"
    ],
    "sg:website":"www.lenscrafters.com",
    "wof:name":"LensCrafters",
    "wof:placetype":"venue"
},
  "geometry": {"coordinates":[-73.728058,41.208273],"type":"Point"}
}