{
  "type": "Feature",
  "properties": {
    "addr:full":"30 Church St Rochester NY 14614",
    "addr:housenumber":"30",
    "addr:postcode":"14614",
    "addr:street":"Church St",
    "iso:country":"US",
    "sg:address":"30 Church St",
    "sg:city":"Rochester",
    "sg:classifiers":[
        {
            "category":"Government",
            "subcategory":"Office",
            "type":"Public Place"
        }
    ],
    "sg:phone":"+1 585 428 6903",
    "sg:postcode":"14614",
    "sg:province":"NY",
    "sg:tags":[
        "village"
    ],
    "wof:name":"Technical Services",
    "wof:placetype":"venue"
},
  "geometry": {"coordinates":[-77.614859,43.15681],"type":"Point"}
}