{
  "type": "Feature",
  "properties": {
    "iso:country":"US",
    "sg:address":"1010 James St",
    "sg:city":"Syracuse",
    "sg:classifiers":[
        {
            "category":"Building & Trades",
            "subcategory":"Construction",
            "type":"Services"
        }
    ],
    "sg:phone":"+1 315 424 0200",
    "sg:postcode":"13203",
    "sg:province":"NY",
    "sg:tags":[
        "contractor",
        "apartment",
        "renovation",
        "general"
    ],
    "wof:name":"Lonesco Construction Co Inc",
    "wof:placetype":"venue"
},
  "geometry": {"coordinates":[-76.131629,43.060479],"type":"Point"}
}