{
  "type": "Feature",
  "properties": {
    "addr:full":"155 E 72 St New York NY 10021",
    "addr:housenumber":"155;72",
    "addr:postcode":"10021",
    "addr:street":"E;St",
    "iso:country":"US",
    "sg:address":"155 E 72 St",
    "sg:city":"New York",
    "sg:classifiers":[
        {
            "category":"Health Services",
            "subcategory":"Doctor",
            "type":"Services"
        }
    ],
    "sg:phone":"+1 212 988 6870",
    "sg:postcode":"10021",
    "sg:province":"NY",
    "sg:tags":[
        "physician",
        "surgeon"
    ],
    "wof:name":"Patricia Mclaughlin DO",
    "wof:placetype":"venue"
},
  "geometry": {"coordinates":[-73.96086,40.769978],"type":"Point"}
}