{
  "type": "Feature",
  "properties": {
    "iso:country":"US",
    "sg:address":"6 W Clark St",
    "sg:city":"Ilion",
    "sg:classifiers":[
        {
            "category":"Personal",
            "subcategory":"Beauty Salon",
            "type":"Services"
        }
    ],
    "sg:phone":"+1 315 894 1400",
    "sg:postcode":"13357",
    "sg:province":"NY",
    "wof:name":"Heads R Turning",
    "wof:placetype":"venue"
},
  "geometry": {"coordinates":[-75.035095,43.016354],"type":"Point"}
}