{
  "type": "Feature",
  "properties": {
    "addr:full":"1486 Needham Ave Bronx NY 10469",
    "addr:housenumber":"1486",
    "addr:postcode":"10469",
    "addr:street":"Needham Ave",
    "iso:country":"US",
    "sg:address":"1486 Needham Ave",
    "sg:city":"Bronx",
    "sg:classifiers":[
        {
            "category":"Social Services",
            "subcategory":"Child Care",
            "type":"Services"
        }
    ],
    "sg:phone":"+1   ",
    "sg:postcode":"10469",
    "sg:province":"NY",
    "sg:tags":[
        "day"
    ],
    "wof:name":"Davis Christian Fmly Day Care",
    "wof:placetype":"venue"
},
  "geometry": {"coordinates":[-73.849366,40.879221],"type":"Point"}
}