{
  "type": "Feature",
  "properties": {
    "addr:full":"2445 Walton Ave Bronx NY 10468",
    "addr:housenumber":"2445",
    "addr:postcode":"10468",
    "addr:street":"Walton Ave",
    "iso:country":"US",
    "sg:address":"2445 Walton Ave",
    "sg:city":"Bronx",
    "sg:classifiers":[
        {
            "category":"Building & Trades",
            "subcategory":"Construction",
            "type":"Services"
        }
    ],
    "sg:phone":"+1 718 367 0846",
    "sg:postcode":"10468",
    "sg:province":"NY",
    "sg:tags":[
        "residential"
    ],
    "wof:name":"Garcia Construction",
    "wof:placetype":"venue"
},
  "geometry": {"coordinates":[-73.901206,40.860656],"type":"Point"}
}