{
  "type": "Feature",
  "properties": {
    "addr:full":"182 Plainview Rd Hicksville NY 11801",
    "addr:housenumber":"182",
    "addr:postcode":"11801",
    "addr:street":"Plainview Rd",
    "iso:country":"US",
    "sg:address":"182 Plainview Rd",
    "sg:city":"Hicksville",
    "sg:classifiers":[
        {
            "category":"Shopping",
            "subcategory":"Gifts & Souvenirs",
            "type":"Retail Goods"
        }
    ],
    "sg:phone":"+1   ",
    "sg:postcode":"11801",
    "sg:province":"NY",
    "wof:name":"Judith K Lombardi Inc",
    "wof:placetype":"venue"
},
  "geometry": {"coordinates":[-73.514624,40.768612],"type":"Point"}
}