{
  "type": "Feature",
  "properties": {
    "iso:country":"US",
    "sg:address":"320 Fayette St",
    "sg:city":"Manlius",
    "sg:classifiers":[
        {
            "category":"Shopping",
            "type":"Retail Goods"
        },
        {
            "category":"Home & Garden",
            "subcategory":"Carpets & Floor Coverings",
            "type":"Retail Goods"
        }
    ],
    "sg:phone":"+1 315 682 6263",
    "sg:postcode":"13104",
    "sg:province":"NY",
    "sg:tags":[
        "dealer",
        "merchandise",
        "rug"
    ],
    "wof:name":"Valley Carpet of Manlius",
    "wof:placetype":"venue"
},
  "geometry": {"coordinates":[-75.984291,43.005814],"type":"Point"}
}