{
  "type": "Feature",
  "properties": {
    "addr:full":"612 Van Cortlandt Park Ave Yonkers NY 10705",
    "addr:housenumber":"612",
    "addr:postcode":"10705",
    "addr:street":"Van Cortlandt Park Ave",
    "iso:country":"US",
    "sg:address":"612 Van Cortlandt Park Ave",
    "sg:city":"Yonkers",
    "sg:classifiers":[
        {
            "category":"Wholesale",
            "subcategory":"Non-durable Goods",
            "type":"Manufacturing & Wholesale Goods"
        }
    ],
    "sg:phone":"+1 914 375 5936",
    "sg:postcode":"10705",
    "sg:province":"NY",
    "wof:name":"North America Export",
    "wof:placetype":"venue"
},
  "geometry": {"coordinates":[-73.891532,40.911615],"type":"Point"}
}