{
  "type": "Feature",
  "properties": {
    "addr:full":"123 Wolfs Ln Pelham NY 10803",
    "addr:housenumber":"123",
    "addr:postcode":"10803",
    "addr:street":"Wolfs Ln",
    "iso:country":"US",
    "sg:address":"123 Wolfs Ln",
    "sg:city":"Pelham",
    "sg:classifiers":[
        {
            "category":"Health Services",
            "subcategory":"Doctor",
            "type":"Services"
        }
    ],
    "sg:phone":"+1 914 738 8356",
    "sg:postcode":"10803",
    "sg:province":"NY",
    "sg:tags":[
        "dentist"
    ],
    "wof:name":"Michael Prisco DDS",
    "wof:placetype":"venue"
},
  "geometry": {"coordinates":[-73.812066,40.905666],"type":"Point"}
}