{
  "type": "Feature",
  "properties": {
    "iso:country":"US",
    "sg:address":"3571 Taylor Valley Rd",
    "sg:city":"Cincinnatus",
    "sg:classifiers":[
        {
            "category":"Manufacturing",
            "subcategory":"Lumber",
            "type":"Manufacturing & Wholesale Goods"
        }
    ],
    "sg:phone":"+1 607 863 4287",
    "sg:postcode":"13040",
    "sg:province":"NY",
    "sg:tags":[
        "company",
        "logging"
    ],
    "wof:name":"Elwood Logging",
    "wof:placetype":"venue"
},
  "geometry": {"coordinates":[-75.914959,42.575612],"type":"Point"}
}