{
  "type": "Feature",
  "properties": {
    "addr:full":"12333 83rd Ave Kew Gardens NY 11415",
    "addr:housenumber":"12333",
    "addr:postcode":"11415",
    "addr:street":"83Rd Ave",
    "iso:country":"US",
    "sg:address":"12333 83rd Ave",
    "sg:city":"Kew Gardens",
    "sg:classifiers":[
        {
            "category":"Professional",
            "subcategory":"Lawyer & Legal Services",
            "type":"Services"
        }
    ],
    "sg:phone":"+1 718 263 6812",
    "sg:postcode":"11415",
    "sg:province":"NY",
    "wof:name":"Agate Augustus C Atty",
    "wof:placetype":"venue"
},
  "geometry": {"coordinates":[-73.827499,40.711201],"type":"Point"}
}