{
  "type": "Feature",
  "properties": {
    "iso:country":"US",
    "sg:address":"192 Main Ave",
    "sg:city":"Wynantskill",
    "sg:classifiers":[
        {
            "category":"Food & Beverages",
            "subcategory":"Groceries & Convenience Stores",
            "type":"Retail Goods"
        }
    ],
    "sg:phone":"+1 518 283 4596",
    "sg:postcode":"12198",
    "sg:province":"NY",
    "sg:website":"www.stewartsicecream.com",
    "wof:name":"Stewart's Shop",
    "wof:placetype":"venue"
},
  "geometry": {"coordinates":[-73.638943,42.695514],"type":"Point"}
}