{
  "type": "Feature",
  "properties": {
    "addr:full":"628 W 52nd St New York NY 10019",
    "addr:housenumber":"628",
    "addr:postcode":"10019",
    "addr:street":"W 52Nd St",
    "iso:country":"US",
    "sg:address":"628 W 52nd St",
    "sg:city":"New York",
    "sg:classifiers":[
        {
            "category":"Retail",
            "subcategory":"Repair Shop",
            "type":"Services"
        }
    ],
    "sg:phone":"+1 212 265 5339",
    "sg:postcode":"10019",
    "sg:province":"NY",
    "sg:tags":[
        "lock",
        "locksmith"
    ],
    "wof:name":"AA1 Emergency Locksmith",
    "wof:placetype":"venue"
},
  "geometry": {"coordinates":[-73.99525300000001,40.767653],"type":"Point"}
}