{
  "type": "Feature",
  "properties": {
    "iso:country":"US",
    "sg:address":"617 N Rte 62",
    "sg:city":"Kennedy",
    "sg:classifiers":[
        {
            "category":"Autos & Motor Vehicles",
            "subcategory":"Automobile Sales",
            "type":"Retail Goods"
        }
    ],
    "sg:phone":"+1   ",
    "sg:postcode":"14747",
    "sg:province":"NY",
    "sg:tags":[
        "car",
        "used",
        "dealer"
    ],
    "wof:name":"Kennedy Auto Resale Center",
    "wof:placetype":"venue"
},
  "geometry": {"coordinates":[-79.102318,42.216561],"type":"Point"}
}