{
  "type": "Feature",
  "properties": {
    "iso:country":"US",
    "sg:address":"115 N Ocean Ave",
    "sg:city":"Freeport",
    "sg:classifiers":[
        {
            "category":"Building & Trades",
            "subcategory":"Construction",
            "type":"Services"
        }
    ],
    "sg:phone":"+1 516 771 7170",
    "sg:postcode":"11520",
    "sg:province":"NY",
    "sg:tags":[
        "home",
        "improvement"
    ],
    "wof:name":"John Lopinto Home Improvement",
    "wof:placetype":"venue"
},
  "geometry": {"coordinates":[-73.58788199999999,40.660355],"type":"Point"}
}