{
  "type": "Feature",
  "properties": {
    "iso:country":"US",
    "sg:address":"34 Wyoming Ave",
    "sg:city":"Long Beach",
    "sg:classifiers":[
        {
            "category":"Building & Trades",
            "subcategory":"Construction",
            "type":"Services"
        }
    ],
    "sg:phone":"+1 516 431 1079",
    "sg:postcode":"11561",
    "sg:province":"NY",
    "sg:tags":[
        "home",
        "improvement"
    ],
    "wof:name":"Fruntzi Construction",
    "wof:placetype":"venue"
},
  "geometry": {"coordinates":[-73.69134699999999,40.585542],"type":"Point"}
}