{
  "type": "Feature",
  "properties": {
    "addr:full":"2724 Erie Blvd E Syracuse NY 13224",
    "addr:housenumber":"2724",
    "addr:postcode":"13224",
    "addr:street":"Erie Blvd E",
    "iso:country":"US",
    "sg:address":"2724 Erie Blvd E",
    "sg:city":"Syracuse",
    "sg:classifiers":[
        {
            "category":"Restaurant",
            "type":"Food & Drink"
        }
    ],
    "sg:menulink":"http://www.allmenus.com/ny/syracuse/256061-erawan/menu/",
    "sg:phone":"+1 315 445 8152",
    "sg:postcode":"13224",
    "sg:province":"NY",
    "sg:tags":[
        "thai",
        "asian"
    ],
    "wof:name":"Erawan",
    "wof:placetype":"venue"
},
  "geometry": {"coordinates":[-76.096433,43.054407],"type":"Point"}
}