{
  "type": "Feature",
  "properties": {
    "iso:country":"US",
    "sg:address":"755 Park Ave",
    "sg:city":"Huntington",
    "sg:classifiers":[
        {
            "category":"Professional",
            "subcategory":"Lawyer & Legal Services",
            "type":"Services"
        }
    ],
    "sg:phone":"+1 631 784 7755",
    "sg:postcode":"11743",
    "sg:province":"NY",
    "wof:name":"Freilcher Harlan Attorney at Law",
    "wof:placetype":"venue"
},
  "geometry": {"coordinates":[-73.395732,40.859372],"type":"Point"}
}