{
  "type": "Feature",
  "properties": {
    "iso:country":"US",
    "sg:address":"6702 Fort Hamilton Parkway",
    "sg:city":"Brooklyn",
    "sg:classifiers":[
        {
            "category":"Shopping",
            "subcategory":"Pharmacy",
            "type":"Retail Goods"
        }
    ],
    "sg:phone":"+1 718 238 8546",
    "sg:postcode":"11219",
    "sg:province":"NY",
    "sg:tags":[
        "drugstore"
    ],
    "wof:name":"Cvs Pharmacy",
    "wof:placetype":"venue"
},
  "geometry": {"coordinates":[-74.01097799999999,40.629602],"type":"Point"}
}