{
  "type": "Feature",
  "properties": {
    "iso:country":"US",
    "sg:address":"9301 Co Rd 76",
    "sg:city":"Hammondsport",
    "sg:classifiers":[
        {
            "category":"Manufacturing",
            "subcategory":"Food",
            "type":"Manufacturing & Wholesale Goods"
        }
    ],
    "sg:phone":"+1 607 868 4241",
    "sg:postcode":"14840",
    "sg:province":"NY",
    "sg:tags":[
        "winery"
    ],
    "sg:website":"www.heronhill.com",
    "wof:name":"Heron Hill Vineyards",
    "wof:placetype":"venue"
},
  "geometry": {"coordinates":[-77.20496300000001,42.458534],"type":"Point"}
}