{
  "type": "Feature",
  "properties": {
    "addr:full":"150 N Mac Questen Pkwy Mt Vernon NY 10550",
    "addr:housenumber":"150",
    "addr:postcode":"10550",
    "addr:street":"N Mac Questen Pkwy",
    "iso:country":"US",
    "sg:address":"150 N Mac Questen Pkwy",
    "sg:city":"Mt Vernon",
    "sg:classifiers":[
        {
            "category":"Professional",
            "subcategory":"Management & Consulting",
            "type":"Services"
        }
    ],
    "sg:phone":"+1 914 663 6800",
    "sg:postcode":"10550",
    "sg:province":"NY",
    "sg:tags":[
        "break",
        "coffee",
        "supply"
    ],
    "wof:name":"Luv A Cup Coffee Svc LTD",
    "wof:placetype":"venue"
},
  "geometry": {"coordinates":[-73.847247,40.914568],"type":"Point"}
}