{
  "type": "Feature",
  "properties": {
    "iso:country":"US",
    "sg:address":"2222 Falls St",
    "sg:city":"Niagara Falls",
    "sg:classifiers":[
        {
            "category":"Manufacturing",
            "subcategory":"Printing",
            "type":"Manufacturing & Wholesale Goods"
        }
    ],
    "sg:phone":"+1   ",
    "sg:postcode":"14303",
    "sg:province":"NY",
    "sg:tags":[
        "commercial",
        "lithographic"
    ],
    "wof:name":"Mc Gill-Bowen Prntng",
    "wof:placetype":"venue"
},
  "geometry": {"coordinates":[-79.03472499999999,43.086882],"type":"Point"}
}