{
  "type": "Feature",
  "properties": {
    "iso:country":"US",
    "sg:address":"227 E 50 St",
    "sg:city":"New York",
    "sg:classifiers":[
        {
            "category":"Personal",
            "subcategory":"Beauty Salon",
            "type":"Services"
        }
    ],
    "sg:phone":"+1 212 605 7506",
    "sg:postcode":"10022",
    "sg:province":"NY",
    "sg:tags":[
        "spa",
        "day"
    ],
    "wof:name":"Elena's Classic Spa Inc",
    "wof:placetype":"venue"
},
  "geometry": {"coordinates":[-73.968934,40.755194],"type":"Point"}
}