{
  "type": "Feature",
  "properties": {
    "iso:country":"US",
    "sg:address":"223 Main St",
    "sg:city":"Goshen",
    "sg:classifiers":[
        {
            "category":"Organizations",
            "subcategory":"Community Association",
            "type":"Services"
        }
    ],
    "sg:phone":"+1 845 294 5015",
    "sg:postcode":"10924",
    "sg:province":"NY",
    "sg:tags":[
        "fraternal"
    ],
    "wof:name":"Masonic Lodge",
    "wof:placetype":"venue"
},
  "geometry": {"coordinates":[-74.319845,41.403706],"type":"Point"}
}