{
  "type": "Feature",
  "properties": {
    "addr:full":"88 Dewey Ave Batavia NY 14020",
    "addr:housenumber":"88",
    "addr:postcode":"14020",
    "addr:street":"Dewey Ave",
    "iso:country":"US",
    "sg:address":"88 Dewey Ave",
    "sg:city":"Batavia",
    "sg:classifiers":[
        {
            "category":"Real Estate",
            "subcategory":"Real Estate Operator",
            "type":"Services"
        }
    ],
    "sg:phone":"+1 585 343 0205",
    "sg:postcode":"14020",
    "sg:province":"NY",
    "sg:tags":[
        "building",
        "apartment"
    ],
    "wof:name":"Birchwood Village",
    "wof:placetype":"venue"
},
  "geometry": {"coordinates":[-78.205569,42.996513],"type":"Point"}
}