{
  "type": "Feature",
  "properties": {
    "addr:full":"2540 Vestal Pkwy W Vestal NY 13850",
    "addr:housenumber":"2540",
    "addr:postcode":"13850",
    "addr:street":"Vestal Pkwy W",
    "iso:country":"US",
    "sg:address":"2540 Vestal Pkwy W",
    "sg:city":"Vestal",
    "sg:classifiers":[
        {
            "category":"Coffee & Tea",
            "type":"Food & Drink"
        }
    ],
    "sg:menulink":"http://www.allmenus.com/ny/vestal/113598-starbucks-coffee/menu/",
    "sg:phone":"+1 607 797 0846",
    "sg:postcode":"13850",
    "sg:province":"NY",
    "sg:tags":[
        "american"
    ],
    "wof:name":"Starbucks Coffee",
    "wof:placetype":"venue"
},
  "geometry": {"coordinates":[-76.102367,42.06866],"type":"Point"}
}