{
  "type": "Feature",
  "properties": {
    "addr:full":"1597 Westchester Ave Bronx NY 10472",
    "addr:housenumber":"1597",
    "addr:postcode":"10472",
    "addr:street":"Westchester Ave",
    "iso:country":"US",
    "sg:address":"1597 Westchester Ave",
    "sg:city":"Bronx",
    "sg:classifiers":[
        {
            "category":"Personal",
            "subcategory":"Beauty Salon",
            "type":"Services"
        }
    ],
    "sg:phone":"+1 718 378 0903",
    "sg:postcode":"10472",
    "sg:province":"NY",
    "wof:name":"Last Style Salon",
    "wof:placetype":"venue"
},
  "geometry": {"coordinates":[-73.876075,40.829098],"type":"Point"}
}