{
  "type": "Feature",
  "properties": {
    "iso:country":"US",
    "sg:address":"8 Gene Ct",
    "sg:city":"Hopewell Junction",
    "sg:classifiers":[
        {
            "category":"Professional",
            "subcategory":"Lawyer & Legal Services",
            "type":"Services"
        }
    ],
    "sg:phone":"+1   ",
    "sg:postcode":"12533",
    "sg:province":"NY",
    "wof:name":"Cubeta Consulting Firm",
    "wof:placetype":"venue"
},
  "geometry": {"coordinates":[-73.811759,41.567243],"type":"Point"}
}