{
  "type": "Feature",
  "properties": {
    "addr:full":"4387 3rd Ave Bronx NY 10457",
    "addr:housenumber":"4387",
    "addr:postcode":"10457",
    "addr:street":"3Rd Ave",
    "iso:country":"US",
    "sg:address":"4387 3rd Ave",
    "sg:city":"Bronx",
    "sg:classifiers":[
        {
            "category":"Autos & Motor Vehicles",
            "subcategory":"Automobile Sales",
            "type":"Retail Goods"
        }
    ],
    "sg:phone":"+1 718 295 9679",
    "sg:postcode":"10457",
    "sg:province":"NY",
    "sg:tags":[
        "car",
        "dealer"
    ],
    "wof:name":"Edward's Auto Sales",
    "wof:placetype":"venue"
},
  "geometry": {"coordinates":[-73.893626,40.851249],"type":"Point"}
}