{
  "type": "Feature",
  "properties": {
    "addr:full":"315 W Montauk Hwy Lindenhurst NY 11757",
    "addr:housenumber":"315",
    "addr:postcode":"11757",
    "addr:street":"W Montauk Hwy",
    "iso:country":"US",
    "sg:address":"315 W Montauk Hwy",
    "sg:city":"Lindenhurst",
    "sg:classifiers":[
        {
            "category":"Education",
            "subcategory":"School",
            "type":"Public Place"
        }
    ],
    "sg:phone":"+1 631 226 6409",
    "sg:postcode":"11757",
    "sg:province":"NY",
    "wof:name":"Ew Bower Elementary School",
    "wof:placetype":"venue"
},
  "geometry": {"coordinates":[-73.370796,40.675461],"type":"Point"}
}