{
  "type": "Feature",
  "properties": {
    "addr:full":"105 Guyon Ave Staten Island NY 10306",
    "addr:housenumber":"105",
    "addr:postcode":"10306",
    "addr:street":"Guyon Ave",
    "iso:country":"US",
    "sg:address":"105 Guyon Ave",
    "sg:city":"Staten Island",
    "sg:classifiers":[
        {
            "category":"Food & Beverages",
            "subcategory":"Groceries & Convenience Stores",
            "type":"Retail Goods"
        }
    ],
    "sg:phone":"+1   ",
    "sg:postcode":"10306",
    "sg:province":"NY",
    "wof:name":"Oakwood Station Groceries Inc",
    "wof:placetype":"venue"
},
  "geometry": {"coordinates":[-74.12973,40.565311],"type":"Point"}
}