{
  "type": "Feature",
  "properties": {
    "addr:full":"10713 Northern Boulevard Corona NY 11368",
    "addr:housenumber":"10713",
    "addr:postcode":"11368",
    "addr:street":"Northern Boulevard",
    "iso:country":"US",
    "sg:address":"10713 Northern Boulevard",
    "sg:city":"Corona",
    "sg:classifiers":[
        {
            "category":"Real Estate",
            "subcategory":"Architect",
            "type":"Services"
        }
    ],
    "sg:phone":"+1 718 507 9200",
    "sg:postcode":"11368",
    "sg:province":"NY",
    "wof:name":"Ko Jae Y Associates",
    "wof:placetype":"venue"
},
  "geometry": {"coordinates":[-73.860692,40.756212],"type":"Point"}
}