{
  "type": "Feature",
  "properties": {
    "iso:country":"US",
    "sg:address":"186 Spring Tree Ln",
    "sg:city":"Rochester",
    "sg:classifiers":[
        {
            "category":"Autos & Motor Vehicles",
            "subcategory":"Automobile Sales",
            "type":"Retail Goods"
        }
    ],
    "sg:phone":"+1   ",
    "sg:postcode":"14612",
    "sg:province":"NY",
    "wof:name":"Prestige Auto Sales",
    "wof:placetype":"venue"
},
  "geometry": {"coordinates":[-77.722189,43.2517],"type":"Point"}
}