{
  "type": "Feature",
  "properties": {
    "addr:full":"2393 Broadway New York NY 10024",
    "addr:housenumber":"2393",
    "addr:postcode":"10024",
    "addr:street":"Broadway",
    "iso:country":"US",
    "sg:address":"2393 Broadway",
    "sg:city":"New York",
    "sg:classifiers":[
        {
            "category":"Restaurant",
            "type":"Food & Drink"
        }
    ],
    "sg:phone":"+1 212 877 7714",
    "sg:postcode":"10024",
    "sg:province":"NY",
    "sg:tags":[
        "barbecue"
    ],
    "wof:name":"Chicken Fair Inc",
    "wof:placetype":"venue"
},
  "geometry": {"coordinates":[-73.975813,40.789154],"type":"Point"}
}