{
  "type": "Feature",
  "properties": {
    "addr:full":"103 N McKinley Ave Endicott NY 13760",
    "addr:housenumber":"103",
    "addr:postcode":"13760",
    "addr:street":"N Mckinley Ave",
    "iso:country":"US",
    "sg:address":"103 N McKinley Ave",
    "sg:city":"Endicott",
    "sg:classifiers":[
        {
            "category":"Retail",
            "subcategory":"Auto Repair",
            "type":"Services"
        }
    ],
    "sg:phone":"+1   ",
    "sg:postcode":"13760",
    "sg:province":"NY",
    "sg:tags":[
        "glass",
        "replacement"
    ],
    "wof:name":"Tint Cndition Prof Win Tinting",
    "wof:placetype":"venue"
},
  "geometry": {"coordinates":[-76.045243,42.111122],"type":"Point"}
}