{
  "type": "Feature",
  "properties": {
    "addr:full":"2 Pine West Plz Albany NY 12205",
    "addr:housenumber":"2",
    "addr:postcode":"12205",
    "addr:street":"Pine West Plz",
    "iso:country":"US",
    "sg:address":"2 Pine West Plz",
    "sg:city":"Albany",
    "sg:classifiers":[
        {
            "category":"Insurance",
            "subcategory":"Hazard Insurance",
            "type":"Services"
        }
    ],
    "sg:phone":"+1 518 452 2891",
    "sg:postcode":"12205",
    "sg:province":"NY",
    "sg:tags":[
        "commercial",
        "business"
    ],
    "wof:name":"Comp Solutions Inc",
    "wof:placetype":"venue"
},
  "geometry": {"coordinates":[-73.862968,42.709801],"type":"Point"}
}