{
  "type": "Feature",
  "properties": {
    "addr:full":"57 Jay Street 2nd Floor Brooklyn NY 11201",
    "addr:housenumber":"57",
    "addr:postcode":"11201",
    "addr:street":"Jay Street 2Nd Floor",
    "iso:country":"US",
    "sg:address":"57 Jay Street 2nd Floor",
    "sg:city":"Brooklyn",
    "sg:classifiers":[
        {
            "category":"Retail",
            "subcategory":"Event Space",
            "type":"Services"
        },
        {
            "category":"Professional",
            "subcategory":"Art Services",
            "type":"Services"
        }
    ],
    "sg:phone":"+1 347 651 0376",
    "sg:postcode":"11201",
    "sg:province":"NY",
    "sg:tags":[
        "photographer",
        "venue"
    ],
    "sg:website":"www.rrphotostudios.com",
    "wof:name":"RR Photo Studios",
    "wof:placetype":"venue"
},
  "geometry": {"coordinates":[-73.986552,40.70298],"type":"Point"}
}