{
  "type": "Feature",
  "properties": {
    "iso:country":"US",
    "sg:address":"379 Clive Ave",
    "sg:city":"Oceanside",
    "sg:classifiers":[
        {
            "category":"Communications",
            "type":"Services"
        }
    ],
    "sg:phone":"+1 516 766 8130",
    "sg:postcode":"11572",
    "sg:province":"NY",
    "sg:tags":[
        "web",
        "design"
    ],
    "wof:name":"Edi Options Inc",
    "wof:placetype":"venue"
},
  "geometry": {"coordinates":[-73.625,40.6394],"type":"Point"}
}