{
  "type": "Feature",
  "properties": {
    "addr:full":"1 Christian Hill Rd Morrisville NY 13408",
    "addr:housenumber":"1",
    "addr:postcode":"13408",
    "addr:street":"Christian Hill Rd",
    "iso:country":"US",
    "sg:address":"1 Christian Hill Rd",
    "sg:city":"Morrisville",
    "sg:classifiers":[
        {
            "category":"Government",
            "subcategory":"Police Station",
            "type":"Public Place"
        }
    ],
    "sg:phone":"+1 315 684 9550",
    "sg:postcode":"13408",
    "sg:province":"NY",
    "sg:tags":[
        "state"
    ],
    "wof:name":"State Police Dept",
    "wof:placetype":"venue"
},
  "geometry": {"coordinates":[-75.634331,42.898925],"type":"Point"}
}