{
  "type": "Feature",
  "properties": {
    "iso:country":"US",
    "sg:address":"615 Grand Blvd",
    "sg:city":"Deer Park",
    "sg:classifiers":[
        {
            "category":"Banks & Credit Unions",
            "subcategory":"Bank",
            "type":"Services"
        }
    ],
    "sg:phone":"+1 516 935 9935",
    "sg:postcode":"11729",
    "sg:province":"NY",
    "wof:name":"Chase",
    "wof:placetype":"venue"
},
  "geometry": {"coordinates":[-73.31856000000001,40.759307],"type":"Point"}
}