{
  "type": "Feature",
  "properties": {
    "addr:full":"549 Clarissa St Rochester NY 14608",
    "addr:housenumber":"549",
    "addr:postcode":"14608",
    "addr:street":"Clarissa St",
    "iso:country":"US",
    "sg:address":"549 Clarissa St",
    "sg:city":"Rochester",
    "sg:classifiers":[
        {
            "category":"Social Services",
            "type":"Services"
        }
    ],
    "sg:phone":"+1 585 546 6490",
    "sg:postcode":"14608",
    "sg:province":"NY",
    "sg:tags":[
        "organization",
        "welfare"
    ],
    "wof:name":"Southwest Nutrition Ctr",
    "wof:placetype":"venue"
},
  "geometry": {"coordinates":[-77.618666,43.145831],"type":"Point"}
}