{
  "type": "Feature",
  "properties": {
    "addr:full":"6 Waterview Rd Island Park NY 11558",
    "addr:housenumber":"6",
    "addr:postcode":"11558",
    "addr:street":"Waterview Rd",
    "iso:country":"US",
    "sg:address":"6 Waterview Rd",
    "sg:city":"Island Park",
    "sg:classifiers":[
        {
            "category":"Restaurant",
            "type":"Food & Drink"
        }
    ],
    "sg:phone":"+1 516 431 8700",
    "sg:postcode":"11558",
    "sg:province":"NY",
    "sg:website":"www.paddymcgeesfishhouse.com",
    "wof:name":"Paddy McGees",
    "wof:placetype":"venue"
},
  "geometry": {"coordinates":[-73.651398,40.596298],"type":"Point"}
}