{
  "type": "Feature",
  "properties": {
    "iso:country":"US",
    "sg:address":"1 Monument Sq",
    "sg:city":"Troy",
    "sg:classifiers":[
        {
            "category":"Government",
            "subcategory":"Office",
            "type":"Public Place"
        }
    ],
    "sg:phone":"+1 518 270 4409",
    "sg:postcode":"12180",
    "sg:province":"NY",
    "sg:tags":[
        "city",
        "taxation"
    ],
    "wof:name":"Troy Comptroller",
    "wof:placetype":"venue"
},
  "geometry": {"coordinates":[-73.691754,42.731685],"type":"Point"}
}