{
  "type": "Feature",
  "properties": {
    "iso:country":"US",
    "sg:address":"100 Main St",
    "sg:city":"Oneonta",
    "sg:classifiers":[
        {
            "category":"Shopping",
            "subcategory":"Books",
            "type":"Retail Goods"
        }
    ],
    "sg:phone":"+1 607 432 1969",
    "sg:postcode":"13820",
    "sg:province":"NY",
    "sg:tags":[
        "dealer"
    ],
    "wof:name":"Book Shoppe",
    "wof:placetype":"venue"
},
  "geometry": {"coordinates":[-75.063886,42.451341],"type":"Point"}
}