{
  "type": "Feature",
  "properties": {
    "addr:full":"8018 20th Avenue Brooklyn NY 11214",
    "addr:housenumber":"8018",
    "addr:postcode":"11214",
    "addr:street":"20Th Avenue",
    "iso:country":"US",
    "sg:address":"8018 20th Avenue",
    "sg:city":"Brooklyn",
    "sg:classifiers":[
        {
            "category":"Wholesale",
            "subcategory":"Fruits & Vegetables",
            "type":"Manufacturing & Wholesale Goods"
        }
    ],
    "sg:phone":"+1 718 234 5466",
    "sg:postcode":"11214",
    "sg:province":"NY",
    "sg:tags":[
        "veggie"
    ],
    "wof:name":"Jacob's Village Farm Corporation",
    "wof:placetype":"venue"
},
  "geometry": {"coordinates":[-73.995288,40.607608],"type":"Point"}
}