{
  "type": "Feature",
  "properties": {
    "addr:full":"19 Harness Rd Saint James NY 11780",
    "addr:housenumber":"19",
    "addr:postcode":"11780",
    "addr:street":"Harness Rd",
    "iso:country":"US",
    "sg:address":"19 Harness Rd",
    "sg:city":"Saint James",
    "sg:classifiers":[
        {
            "category":"Professional",
            "subcategory":"Engineering",
            "type":"Services"
        }
    ],
    "sg:phone":"+1 631 218 3555",
    "sg:postcode":"11780",
    "sg:province":"NY",
    "sg:tags":[
        "repair",
        "machinery",
        "rebuilding"
    ],
    "wof:name":"Field Service Mechanical Co",
    "wof:placetype":"venue"
},
  "geometry": {"coordinates":[-73.176389,40.873578],"type":"Point"}
}