{
  "type": "Feature",
  "properties": {
    "iso:country":"US",
    "sg:address":"187 Plains Rd",
    "sg:city":"Walden",
    "sg:classifiers":[
        {
            "category":"Real Estate",
            "subcategory":"Real Estate Agent",
            "type":"Services"
        }
    ],
    "sg:phone":"+1 845 778 7450",
    "sg:postcode":"12586",
    "sg:province":"NY",
    "sg:tags":[
        "appraiser"
    ],
    "wof:name":"Appalachian Appraisal Services",
    "wof:placetype":"venue"
},
  "geometry": {"coordinates":[-74.14294099999999,41.582584],"type":"Point"}
}