{
  "type": "Feature",
  "properties": {
    "iso:country":"US",
    "sg:address":"20 Aviation Rd Ste 1",
    "sg:city":"Albany",
    "sg:classifiers":[
        {
            "category":"Real Estate",
            "subcategory":"Real Estate Services",
            "type":"Services"
        },
        {
            "category":"Real Estate",
            "subcategory":"Real Estate Agent",
            "type":"Services"
        }
    ],
    "sg:phone":"+1 518 458 7000",
    "sg:postcode":"12205",
    "sg:province":"NY",
    "sg:tags":[
        "information",
        "consultant",
        "broker",
        "buyer",
        "referral"
    ],
    "sg:website":"http://realtyusa.com",
    "wof:name":"Realty Usa-Commercial Div",
    "wof:placetype":"venue"
},
  "geometry": {"coordinates":[-73.80441999999999,42.715032],"type":"Point"}
}