{
  "type": "Feature",
  "properties": {
    "iso:country":"US",
    "sg:address":"9519 Old Creek Rd",
    "sg:city":"Batavia",
    "sg:classifiers":[
        {
            "category":"Retail",
            "subcategory":"Repair Shop",
            "type":"Services"
        }
    ],
    "sg:phone":"+1   ",
    "sg:postcode":"14020",
    "sg:province":"NY",
    "wof:name":"Old Creek Upholstery",
    "wof:placetype":"venue"
},
  "geometry": {"coordinates":[-78.189234,42.953972],"type":"Point"}
}