{
  "type": "Feature",
  "properties": {
    "addr:full":"257 Saw Mill River Rd Elmsford NY 10523",
    "addr:housenumber":"257",
    "addr:postcode":"10523",
    "addr:street":"Saw Mill River Rd",
    "iso:country":"US",
    "sg:address":"257 Saw Mill River Rd",
    "sg:city":"Elmsford",
    "sg:classifiers":[
        {
            "category":"Bars & Pubs",
            "type":"Food & Drink"
        }
    ],
    "sg:phone":"+1   ",
    "sg:postcode":"10523",
    "sg:province":"NY",
    "sg:tags":[
        "bar"
    ],
    "wof:name":"Nats Place",
    "wof:placetype":"venue"
},
  "geometry": {"coordinates":[-73.814643,41.062478],"type":"Point"}
}