{
  "type": "Feature",
  "properties": {
    "addr:full":"8063 Jericho Tpke Woodbury NY 11797",
    "addr:housenumber":"8063",
    "addr:postcode":"11797",
    "addr:street":"Jericho Tpke",
    "iso:country":"US",
    "sg:address":"8063 Jericho Tpke",
    "sg:city":"Woodbury",
    "sg:classifiers":[
        {
            "category":"Professional",
            "type":"Services"
        }
    ],
    "sg:phone":"+1 516 692 9669",
    "sg:postcode":"11797",
    "sg:province":"NY",
    "sg:tags":[
        "establishment"
    ],
    "wof:name":"Turnwood Associates LLC",
    "wof:placetype":"venue"
},
  "geometry": {"coordinates":[-73.474874,40.814775],"type":"Point"}
}