{
  "type": "Feature",
  "properties": {
    "iso:country":"US",
    "sg:address":"6802 Myrtle Ave",
    "sg:city":"Glendale",
    "sg:classifiers":[
        {
            "category":"Shopping",
            "subcategory":"Pharmacy",
            "type":"Retail Goods"
        }
    ],
    "sg:phone":"+1 718 456 1165",
    "sg:postcode":"11385",
    "sg:province":"NY",
    "sg:tags":[
        "drugstore"
    ],
    "sg:website":"www.cvs.com",
    "wof:name":"CVS pharmacy",
    "wof:placetype":"venue"
},
  "geometry": {"coordinates":[-73.884173,40.701536],"type":"Point"}
}