{
  "type": "Feature",
  "properties": {
    "addr:full":"121 Maple St Croton On Hudson NY 10520",
    "addr:housenumber":"121",
    "addr:postcode":"10520",
    "addr:street":"Maple St",
    "iso:country":"US",
    "sg:address":"121 Maple St",
    "sg:city":"Croton On Hudson",
    "sg:classifiers":[
        {
            "category":"Restaurant",
            "type":"Food & Drink"
        }
    ],
    "sg:phone":"+1 914 271 3850",
    "sg:postcode":"10520",
    "sg:province":"NY",
    "sg:tags":[
        "parlor",
        "ice",
        "cream"
    ],
    "wof:name":"Blue Pig Ice Cream Factory",
    "wof:placetype":"venue"
},
  "geometry": {"coordinates":[-73.880847,41.209913],"type":"Point"}
}