{
  "type": "Feature",
  "properties": {
    "iso:country":"US",
    "sg:address":"92 Fulton St",
    "sg:city":"New York",
    "sg:classifiers":[
        {
            "category":"Wholesale",
            "subcategory":"Office Equipment",
            "type":"Manufacturing & Wholesale Goods"
        }
    ],
    "sg:phone":"+1 212 385 4555",
    "sg:postcode":"10038",
    "sg:province":"NY",
    "sg:tags":[
        "dictating",
        "machine",
        "supply"
    ],
    "wof:name":"Central Dictating Systems",
    "wof:placetype":"venue"
},
  "geometry": {"coordinates":[-74.00601,40.709185],"type":"Point"}
}