{
  "type": "Feature",
  "properties": {
    "addr:full":"112 E Woodside Ave Patchogue NY 11772",
    "addr:housenumber":"112",
    "addr:postcode":"11772",
    "addr:street":"E Woodside Ave",
    "iso:country":"US",
    "sg:address":"112 E Woodside Ave",
    "sg:city":"Patchogue",
    "sg:classifiers":[
        {
            "category":"Manufacturing",
            "subcategory":"Apparel",
            "type":"Manufacturing & Wholesale Goods"
        }
    ],
    "sg:phone":"+1   ",
    "sg:postcode":"11772",
    "sg:province":"NY",
    "sg:tags":[
        "product",
        "mfg"
    ],
    "wof:name":"Brec Rentals",
    "wof:placetype":"venue"
},
  "geometry": {"coordinates":[-72.99717200000001,40.794752],"type":"Point"}
}