{
  "type": "Feature",
  "properties": {
    "iso:country":"US",
    "sg:address":"752 Willoughby Avenue",
    "sg:city":"Brooklyn",
    "sg:classifiers":[
        {
            "category":"Health Services",
            "subcategory":"Health Practitioner",
            "type":"Services"
        }
    ],
    "sg:phone":"+1 718 443 8195",
    "sg:postcode":"11206",
    "sg:province":"NY",
    "sg:tags":[
        "therapy",
        "physical"
    ],
    "sg:website":"www.qualitycarephysicaltherapy.com",
    "wof:name":"Quality Care Physical Therapy",
    "wof:placetype":"venue"
},
  "geometry": {"coordinates":[-73.938954,40.695032],"type":"Point"}
}