{
  "type": "Feature",
  "properties": {
    "addr:full":"256 E Fordham Rd Bronx NY 10458",
    "addr:housenumber":"256",
    "addr:postcode":"10458",
    "addr:street":"E Fordham Rd",
    "iso:country":"US",
    "sg:address":"256 E Fordham Rd",
    "sg:city":"Bronx",
    "sg:classifiers":[
        {
            "category":"Shopping",
            "subcategory":"Jewelry",
            "type":"Retail Goods"
        }
    ],
    "sg:phone":"+1 718 295 2266",
    "sg:postcode":"10458",
    "sg:province":"NY",
    "sg:tags":[
        "platinum",
        "silver",
        "gold"
    ],
    "wof:name":"Planet Gold Corp",
    "wof:placetype":"venue"
},
  "geometry": {"coordinates":[-73.894943,40.862016],"type":"Point"}
}