{
  "type": "Feature",
  "properties": {
    "addr:full":"350 W 22nd St Bsmt New York NY 10011",
    "addr:housenumber":"350",
    "addr:postcode":"10011",
    "addr:street":"W 22Nd St",
    "iso:country":"US",
    "sg:address":"350 W 22nd St Bsmt",
    "sg:city":"New York",
    "sg:classifiers":[
        {
            "category":"Banks & Credit Unions",
            "subcategory":"Bank",
            "type":"Services"
        }
    ],
    "sg:phone":"+1 212 924 7022",
    "sg:postcode":"10011",
    "sg:province":"NY",
    "wof:name":"Wells Fargo Armored Svce Corp",
    "wof:placetype":"venue"
},
  "geometry": {"coordinates":[-74.000603,40.7453],"type":"Point"}
}