{
  "type": "Feature",
  "properties": {
    "addr:full":"405 Amsterdam Ave New York NY 10024",
    "addr:housenumber":"405",
    "addr:postcode":"10024",
    "addr:street":"Amsterdam Ave",
    "iso:country":"US",
    "sg:address":"405 Amsterdam Ave",
    "sg:city":"New York",
    "sg:classifiers":[
        {
            "category":"Restaurant",
            "type":"Food & Drink"
        }
    ],
    "sg:menulink":"http://www.allmenus.com/ny/new-york/2421-great-burrito/menu/",
    "sg:phone":"+1 212 724 5151",
    "sg:postcode":"10024",
    "sg:province":"NY",
    "sg:tags":[
        "mexican"
    ],
    "wof:name":"Great Burrito",
    "wof:placetype":"venue"
},
  "geometry": {"coordinates":[-73.978103,40.783454],"type":"Point"}
}