{
  "type": "Feature",
  "properties": {
    "addr:full":"222 Mac Arthur Ave New Windsor NY 12553",
    "addr:housenumber":"222",
    "addr:postcode":"12553",
    "addr:street":"Mac Arthur Ave",
    "iso:country":"US",
    "sg:address":"222 Mac Arthur Ave",
    "sg:city":"New Windsor",
    "sg:classifiers":[
        {
            "category":"Manufacturing",
            "subcategory":"Printing",
            "type":"Manufacturing & Wholesale Goods"
        }
    ],
    "sg:phone":"+1 845 561 4762",
    "sg:postcode":"12553",
    "sg:province":"NY",
    "sg:tags":[
        "commercial"
    ],
    "wof:name":"Commercial Offset Printers Inc",
    "wof:placetype":"venue"
},
  "geometry": {"coordinates":[-74.03226600000001,41.481007],"type":"Point"}
}