{
  "type": "Feature",
  "properties": {
    "addr:full":"240 Main St Huntington NY 11743",
    "addr:housenumber":"240",
    "addr:postcode":"11743",
    "addr:street":"Main St",
    "iso:country":"US",
    "sg:address":"240 Main St",
    "sg:city":"Huntington",
    "sg:classifiers":[
        {
            "category":"Organizations",
            "subcategory":"Religious Organization",
            "type":"Services"
        }
    ],
    "sg:phone":"+1 631 421 3663",
    "sg:postcode":"11743",
    "sg:province":"NY",
    "sg:tags":[
        "place",
        "worship",
        "church"
    ],
    "wof:name":"Central Presbyterian Church",
    "wof:placetype":"venue"
},
  "geometry": {"coordinates":[-73.42495700000001,40.871449],"type":"Point"}
}