{
  "type": "Feature",
  "properties": {
    "addr:full":"568 W 161st St New York NY 10032",
    "addr:housenumber":"568",
    "addr:postcode":"10032",
    "addr:street":"W 161St St",
    "iso:country":"US",
    "sg:address":"568 W 161st St",
    "sg:city":"New York",
    "sg:classifiers":[
        {
            "category":"Professional",
            "subcategory":"Computer Services",
            "type":"Services"
        }
    ],
    "sg:phone":"+1   ",
    "sg:postcode":"10032",
    "sg:province":"NY",
    "sg:tags":[
        "related"
    ],
    "wof:name":"Shellworks",
    "wof:placetype":"venue"
},
  "geometry": {"coordinates":[-73.94159999999999,40.83566],"type":"Point"}
}