{
  "type": "Feature",
  "properties": {
    "iso:country":"US",
    "sg:address":"546 Oliver St",
    "sg:city":"North Tonawanda",
    "sg:classifiers":[
        {
            "category":"Building & Trades",
            "subcategory":"Electrical",
            "type":"Services"
        }
    ],
    "sg:phone":"+1 716 692 0550",
    "sg:postcode":"14120",
    "sg:province":"NY",
    "sg:tags":[
        "electrical",
        "contractor"
    ],
    "wof:name":"Ronald F Rojek",
    "wof:placetype":"venue"
},
  "geometry": {"coordinates":[-78.878607,43.037353],"type":"Point"}
}