{
  "type": "Feature",
  "properties": {
    "iso:country":"US",
    "sg:address":"1211 6 Ave",
    "sg:city":"New York",
    "sg:classifiers":[
        {
            "category":"Professional",
            "subcategory":"Advertising",
            "type":"Services"
        }
    ],
    "sg:phone":"+1 212 852 7477",
    "sg:postcode":"10036",
    "sg:province":"NY",
    "sg:tags":[
        "agency"
    ],
    "wof:name":"TV Guide",
    "wof:placetype":"venue"
},
  "geometry": {"coordinates":[-73.98362299999999,40.755516],"type":"Point"}
}