{
  "type": "Feature",
  "properties": {
    "addr:full":"226 E 54th St Ste 606 New York NY 10022",
    "addr:housenumber":"226;606",
    "addr:postcode":"10022",
    "addr:street":"E 54Th St Ste",
    "iso:country":"US",
    "sg:address":"226 E 54th St Ste 606",
    "sg:city":"New York",
    "sg:classifiers":[
        {
            "category":"Banks & Credit Unions",
            "subcategory":"Investment Brokerage",
            "type":"Services"
        }
    ],
    "sg:phone":"+1 718 285 9598",
    "sg:postcode":"10022",
    "sg:province":"NY",
    "sg:tags":[
        "investing"
    ],
    "sg:website":"www.nationalcurrencyresources.com",
    "wof:name":"National Currency Resources",
    "wof:placetype":"venue"
},
  "geometry": {"coordinates":[-73.968332,40.758069],"type":"Point"}
}