{
  "type": "Feature",
  "properties": {
    "iso:country":"US",
    "sg:address":"2059 Military Rd",
    "sg:city":"Niagara Falls",
    "sg:classifiers":[
        {
            "category":"Personal",
            "subcategory":"Barber",
            "type":"Services"
        }
    ],
    "sg:phone":"+1 716 297 9265",
    "sg:postcode":"14304",
    "sg:province":"NY",
    "wof:name":"Gayle's Barber Shop",
    "wof:placetype":"venue"
},
  "geometry": {"coordinates":[-78.975151,43.097248],"type":"Point"}
}