{
  "type": "Feature",
  "properties": {
    "iso:country":"US",
    "sg:address":"85 Hogan Point Rd",
    "sg:city":"Hilton",
    "sg:classifiers":[
        {
            "category":"Real Estate",
            "subcategory":"Developer",
            "type":"Services"
        }
    ],
    "sg:phone":"+1 585 392 8386",
    "sg:postcode":"14468",
    "sg:province":"NY",
    "sg:tags":[
        "cemetery"
    ],
    "wof:name":"Parma Union Cemetery Corp",
    "wof:placetype":"venue"
},
  "geometry": {"coordinates":[-77.737728,43.304145],"type":"Point"}
}