{
  "type": "Feature",
  "properties": {
    "iso:country":"US",
    "sg:address":"770 Broadway",
    "sg:city":"New York",
    "sg:classifiers":[
        {
            "category":"Professional",
            "subcategory":"Research",
            "type":"Services"
        }
    ],
    "sg:phone":"+1 646 654 5000",
    "sg:postcode":"10003",
    "sg:province":"NY",
    "sg:tags":[
        "marketing",
        "analysis",
        "information"
    ],
    "wof:name":"AC Nielson",
    "wof:placetype":"venue"
},
  "geometry": {"coordinates":[-73.992407,40.730591],"type":"Point"}
}