{
  "type": "Feature",
  "properties": {
    "addr:full":"20 Maine Dr Newburgh NY 12550",
    "addr:housenumber":"20",
    "addr:postcode":"12550",
    "addr:street":"Maine Dr",
    "iso:country":"US",
    "sg:address":"20 Maine Dr",
    "sg:city":"Newburgh",
    "sg:classifiers":[
        {
            "category":"Manufacturing",
            "subcategory":"Jewelry",
            "type":"Manufacturing & Wholesale Goods"
        }
    ],
    "sg:phone":"+1 845 569 0637",
    "sg:postcode":"12550",
    "sg:province":"NY",
    "sg:tags":[
        "finding",
        "jeweler",
        "material",
        "supply",
        "mfg"
    ],
    "wof:name":"Uniquely K Customs Gems",
    "wof:placetype":"venue"
},
  "geometry": {"coordinates":[-74.02861,41.537411],"type":"Point"}
}