{
  "type": "Feature",
  "properties": {
    "iso:country":"US",
    "sg:address":"21 High St",
    "sg:city":"Tupper Lake",
    "sg:classifiers":[
        {
            "category":"Government",
            "subcategory":"Fire Station",
            "type":"Public Place"
        }
    ],
    "sg:phone":"+1 518 359 2111",
    "sg:postcode":"12986",
    "sg:province":"NY",
    "sg:tags":[
        "department"
    ],
    "wof:name":"Tupper Lake Fire Dept",
    "wof:placetype":"venue"
},
  "geometry": {"coordinates":[-74.46460399999999,44.222323],"type":"Point"}
}