{
  "type": "Feature",
  "properties": {
    "addr:full":"1 Depot Sq Ossining NY 10516",
    "addr:housenumber":"1",
    "addr:postcode":"10516",
    "addr:street":"Depot Sq",
    "iso:country":"US",
    "sg:address":"1 Depot Sq",
    "sg:city":"Ossining",
    "sg:classifiers":[
        {
            "category":"Professional",
            "subcategory":"Business Services",
            "type":"Services"
        }
    ],
    "sg:phone":"+1   ",
    "sg:postcode":"10516",
    "sg:province":"NY",
    "wof:name":"D C Mood Creations Ltd",
    "wof:placetype":"venue"
},
  "geometry": {"coordinates":[-73.95998299999999,41.417674],"type":"Point"}
}