{
  "type": "Feature",
  "properties": {
    "addr:full":"1901 Main St Buffalo NY 14208",
    "addr:housenumber":"1901",
    "addr:postcode":"14208",
    "addr:street":"Main St",
    "iso:country":"US",
    "sg:address":"1901 Main St",
    "sg:city":"Buffalo",
    "sg:classifiers":[
        {
            "category":"Health Services",
            "subcategory":"Clinic",
            "type":"Services"
        }
    ],
    "sg:phone":"+1 716 887 9380",
    "sg:postcode":"14208",
    "sg:province":"NY",
    "sg:website":"www.healthnowneny.com",
    "wof:name":"Healthnow",
    "wof:placetype":"venue"
},
  "geometry": {"coordinates":[-78.85397399999999,42.925353],"type":"Point"}
}