{
  "type": "Feature",
  "properties": {
    "addr:full":"39 Bay Knoll Rd Rochester NY 14622",
    "addr:housenumber":"39",
    "addr:postcode":"14622",
    "addr:street":"Bay Knoll Rd",
    "iso:country":"US",
    "sg:address":"39 Bay Knoll Rd",
    "sg:city":"Rochester",
    "sg:classifiers":[
        {
            "category":"Personal",
            "subcategory":"Beauty Salon",
            "type":"Services"
        }
    ],
    "sg:phone":"+1   ",
    "sg:postcode":"14622",
    "sg:province":"NY",
    "sg:tags":[
        "shop"
    ],
    "wof:name":"Nails By Mary",
    "wof:placetype":"venue"
},
  "geometry": {"coordinates":[-77.54656900000001,43.206481],"type":"Point"}
}