{
  "type": "Feature",
  "properties": {
    "iso:country":"US",
    "sg:address":"560 S Broadway",
    "sg:city":"Hicksville",
    "sg:classifiers":[
        {
            "category":"Health Services",
            "subcategory":"Medical Lab",
            "type":"Services"
        }
    ],
    "sg:phone":"+1 516 681 5731",
    "sg:postcode":"11801",
    "sg:province":"NY",
    "sg:tags":[
        "laboratory"
    ],
    "wof:name":"Diagnostic Imaging Group",
    "wof:placetype":"venue"
},
  "geometry": {"coordinates":[-73.50944200000001,40.75565],"type":"Point"}
}