{
  "type": "Feature",
  "properties": {
    "addr:full":"36 Main St Tarrytown NY 10591",
    "addr:housenumber":"36",
    "addr:postcode":"10591",
    "addr:street":"Main St",
    "iso:country":"US",
    "sg:address":"36 Main St",
    "sg:city":"Tarrytown",
    "sg:classifiers":[
        {
            "category":"Banks & Credit Unions",
            "subcategory":"Bank",
            "type":"Services"
        },
        {
            "category":"Shopping",
            "subcategory":"Antiques",
            "type":"Retail Goods"
        },
        {
            "category":"Shopping",
            "subcategory":"Used Merchandise",
            "type":"Retail Goods"
        }
    ],
    "sg:phone":"+1 914 631 0470",
    "sg:postcode":"10591",
    "sg:province":"NY",
    "sg:tags":[
        "shop",
        "resale",
        "second",
        "hand"
    ],
    "wof:name":"The Cherry Door",
    "wof:placetype":"venue"
},
  "geometry": {"coordinates":[-73.859965,41.076628],"type":"Point"}
}