{
  "type": "Feature",
  "properties": {
    "addr:full":"692 W Wyngate Dr Valley Stream NY 11580",
    "addr:housenumber":"692",
    "addr:postcode":"11580",
    "addr:street":"W Wyngate Dr",
    "iso:country":"US",
    "sg:address":"692 W Wyngate Dr",
    "sg:city":"Valley Stream",
    "sg:classifiers":[
        {
            "category":"Professional",
            "subcategory":"Lawyer & Legal Services",
            "type":"Services"
        }
    ],
    "sg:phone":"+1   ",
    "sg:postcode":"11580",
    "sg:province":"NY",
    "wof:name":"Ambrosino & Assoc",
    "wof:placetype":"venue"
},
  "geometry": {"coordinates":[-73.688856,40.690752],"type":"Point"}
}