{
  "type": "Feature",
  "properties": {
    "iso:country":"US",
    "sg:address":"87 Mineola Blvd",
    "sg:city":"Mineola",
    "sg:classifiers":[
        {
            "category":"Shopping",
            "subcategory":"Gifts & Souvenirs",
            "type":"Retail Goods"
        }
    ],
    "sg:phone":"+1   ",
    "sg:postcode":"11501",
    "sg:province":"NY",
    "sg:tags":[
        "cards"
    ],
    "wof:name":"Mineola Cards & Gifts",
    "wof:placetype":"venue"
},
  "geometry": {"coordinates":[-73.640278,40.741325],"type":"Point"}
}