{
  "type": "Feature",
  "properties": {
    "addr:full":"449 Biscayne Dr Rochester NY 14612",
    "addr:housenumber":"449",
    "addr:postcode":"14612",
    "addr:street":"Biscayne Dr",
    "iso:country":"US",
    "sg:address":"449 Biscayne Dr",
    "sg:city":"Rochester",
    "sg:classifiers":[
        {
            "category":"Personal",
            "subcategory":"Beauty Salon",
            "type":"Services"
        }
    ],
    "sg:phone":"+1   ",
    "sg:postcode":"14612",
    "sg:province":"NY",
    "sg:tags":[
        "shop"
    ],
    "wof:name":"Mojos Magical Image Maker",
    "wof:placetype":"venue"
},
  "geometry": {"coordinates":[-77.63175699999999,43.250906],"type":"Point"}
}