{
  "type": "Feature",
  "properties": {
    "addr:full":"614 W 138th St New York NY 10031",
    "addr:housenumber":"614",
    "addr:postcode":"10031",
    "addr:street":"W 138Th St",
    "iso:country":"US",
    "sg:address":"614 W 138th St",
    "sg:city":"New York",
    "sg:classifiers":[
        {
            "category":"Professional",
            "type":"Services"
        }
    ],
    "sg:phone":"+1   ",
    "sg:postcode":"10031",
    "sg:province":"NY",
    "wof:name":"New York Novelties Inc",
    "wof:placetype":"venue"
},
  "geometry": {"coordinates":[-73.955551,40.822697],"type":"Point"}
}