{
  "type": "Feature",
  "properties": {
    "iso:country":"US",
    "sg:address":"2607 State Hwy 295",
    "sg:city":"Canaan",
    "sg:classifiers":[
        {
            "category":"Building & Trades",
            "subcategory":"Electrical",
            "type":"Services"
        }
    ],
    "sg:phone":"+1 518 781 4623",
    "sg:postcode":"12029",
    "sg:province":"NY",
    "sg:tags":[
        "electrical",
        "contractor"
    ],
    "wof:name":"Fred Munch Electric Inc",
    "wof:placetype":"venue"
},
  "geometry": {"coordinates":[-73.410804,42.393393],"type":"Point"}
}