{
  "type": "Feature",
  "properties": {
    "addr:full":"1350 Avenue of the Americ New York NY 10019",
    "addr:housenumber":"1350",
    "addr:postcode":"10019",
    "addr:street":"Avenue Of The",
    "iso:country":"US",
    "sg:address":"1350 Avenue of the Americ",
    "sg:city":"New York",
    "sg:classifiers":[
        {
            "category":"Professional",
            "subcategory":"Lawyer & Legal Services",
            "type":"Services"
        }
    ],
    "sg:phone":"+1 212 541 6222",
    "sg:postcode":"10019",
    "sg:province":"NY",
    "wof:name":"Schloss Bruce M ESQ",
    "wof:placetype":"venue"
},
  "geometry": {"coordinates":[-73.97825400000001,40.762856],"type":"Point"}
}