{
  "type": "Feature",
  "properties": {
    "iso:country":"US",
    "sg:address":"245 Rte 25A",
    "sg:city":"Rocky Point",
    "sg:classifiers":[
        {
            "category":"Food & Beverages",
            "subcategory":"Groceries & Convenience Stores",
            "type":"Retail Goods"
        }
    ],
    "sg:phone":"+1 631 744 1652",
    "sg:postcode":"11778",
    "sg:province":"NY",
    "sg:tags":[
        "grocer"
    ],
    "wof:name":"Waldbaum's Supermarket",
    "wof:placetype":"venue"
},
  "geometry": {"coordinates":[-72.952185,40.944931],"type":"Point"}
}