{
  "type": "Feature",
  "properties": {
    "addr:full":"702 Heritage Dr Rochester NY 14615",
    "addr:housenumber":"702",
    "addr:postcode":"14615",
    "addr:street":"Heritage Dr",
    "iso:country":"US",
    "sg:address":"702 Heritage Dr",
    "sg:city":"Rochester",
    "sg:classifiers":[
        {
            "category":"Retail",
            "subcategory":"Repair Shop",
            "type":"Services"
        }
    ],
    "sg:phone":"+1 585 663 5610",
    "sg:postcode":"14615",
    "sg:province":"NY",
    "sg:tags":[
        "appliance"
    ],
    "wof:name":"A-Nick's Refrigeration Svc",
    "wof:placetype":"venue"
},
  "geometry": {"coordinates":[-77.66566899999999,43.238213],"type":"Point"}
}