{
  "type": "Feature",
  "properties": {
    "addr:full":"202 W 36th St New York NY 10018",
    "addr:housenumber":"202",
    "addr:postcode":"10018",
    "addr:street":"W 36Th St",
    "iso:country":"US",
    "sg:address":"202 W 36th St",
    "sg:city":"New York",
    "sg:classifiers":[
        {
            "category":"Restaurant",
            "type":"Food & Drink"
        }
    ],
    "sg:phone":"+1 212 967 9444",
    "sg:postcode":"10018",
    "sg:province":"NY",
    "wof:name":"Cosi Sandwich Shop",
    "wof:placetype":"venue"
},
  "geometry": {"coordinates":[-73.991798,40.7533],"type":"Point"}
}