{
  "type": "Feature",
  "properties": {
    "addr:full":"2429 Vestal Pkwy E Vestal NY 13850",
    "addr:housenumber":"2429",
    "addr:postcode":"13850",
    "addr:street":"Vestal Pkwy E",
    "iso:country":"US",
    "sg:address":"2429 Vestal Pkwy E",
    "sg:city":"Vestal",
    "sg:classifiers":[
        {
            "category":"Shopping",
            "subcategory":"Shoes",
            "type":"Retail Goods"
        }
    ],
    "sg:phone":"+1 607 770 6335",
    "sg:postcode":"13850",
    "sg:province":"NY",
    "wof:name":"Payless Shoe Source",
    "wof:placetype":"venue"
},
  "geometry": {"coordinates":[-76.011156,42.094632],"type":"Point"}
}