{
  "type": "Feature",
  "properties": {
    "addr:full":"12223 Guy R Brewer Blvd Jamaica NY 11434",
    "addr:housenumber":"12223",
    "addr:postcode":"11434",
    "addr:street":"Guy R Brewer Blvd",
    "iso:country":"US",
    "sg:address":"12223 Guy R Brewer Blvd",
    "sg:city":"Jamaica",
    "sg:classifiers":[
        {
            "category":"Food & Beverages",
            "subcategory":"Groceries & Convenience Stores",
            "type":"Retail Goods"
        }
    ],
    "sg:phone":"+1 800 894 9535",
    "sg:postcode":"11434",
    "sg:province":"NY",
    "wof:name":"Morel Grocery",
    "wof:placetype":"venue"
},
  "geometry": {"coordinates":[-73.779884,40.679278],"type":"Point"}
}