{
  "type": "Feature",
  "properties": {
    "addr:full":"Sock Drawer Green Acres 2034 Green Acres Mall Valley Stream NY 11581",
    "addr:housenumber":"2034",
    "addr:postcode":"11581",
    "addr:street":"Green;Mall",
    "iso:country":"US",
    "sg:address":"Sock Drawer Green Acres 2034 Green Acres Mall",
    "sg:city":"Valley Stream",
    "sg:classifiers":[
        {
            "category":"Shopping",
            "subcategory":"Clothing, Apparel, & Fashions",
            "type":"Retail Goods"
        }
    ],
    "sg:phone":"+1 516 782 5349",
    "sg:postcode":"11581",
    "sg:province":"NY",
    "sg:tags":[
        "children's",
        "men's",
        "clothing",
        "women's"
    ],
    "sg:website":"www.sockdraweronline.com",
    "wof:name":"SockDrawerOnline.com",
    "wof:placetype":"venue"
},
  "geometry": {"coordinates":[-73.719645,40.662935],"type":"Point"}
}