{
  "type": "Feature",
  "properties": {
    "iso:country":"US",
    "sg:address":"32 Fairway Ave",
    "sg:city":"Liberty",
    "sg:classifiers":[
        {
            "category":"Wholesale",
            "subcategory":"Electrical",
            "type":"Manufacturing & Wholesale Goods"
        }
    ],
    "sg:phone":"+1 845 292 6010",
    "sg:postcode":"12754",
    "sg:province":"NY",
    "sg:tags":[
        "alarm",
        "burglar",
        "system"
    ],
    "wof:name":"Liberty Telecomm Security",
    "wof:placetype":"venue"
},
  "geometry": {"coordinates":[-74.762061,41.800571],"type":"Point"}
}