{
  "type": "Feature",
  "properties": {
    "addr:full":"8 S 4th Ave Mount Vernon NY 10550",
    "addr:housenumber":"8",
    "addr:postcode":"10550",
    "addr:street":"S 4Th Ave",
    "iso:country":"US",
    "sg:address":"8 S 4th Ave",
    "sg:city":"Mount Vernon",
    "sg:classifiers":[
        {
            "category":"Shopping",
            "subcategory":"Discount & Variety Stores",
            "type":"Retail Goods"
        }
    ],
    "sg:phone":"+1   ",
    "sg:postcode":"10550",
    "sg:province":"NY",
    "sg:tags":[
        "merchandise",
        "general"
    ],
    "wof:name":"Chass",
    "wof:placetype":"venue"
},
  "geometry": {"coordinates":[-73.836241,40.909248],"type":"Point"}
}