{
  "type": "Feature",
  "properties": {
    "addr:full":"1993 Deer Park Ave Deer Park NY 11729",
    "addr:housenumber":"1993",
    "addr:postcode":"11729",
    "addr:street":"Deer Park Ave",
    "iso:country":"US",
    "sg:address":"1993 Deer Park Ave",
    "sg:city":"Deer Park",
    "sg:classifiers":[
        {
            "category":"Health Services",
            "subcategory":"Doctor",
            "type":"Services"
        }
    ],
    "sg:phone":"+1 631 242 4031",
    "sg:postcode":"11729",
    "sg:province":"NY",
    "sg:tags":[
        "physician",
        "surgeon"
    ],
    "wof:name":"Masoom Qadeer MD",
    "wof:placetype":"venue"
},
  "geometry": {"coordinates":[-73.33148799999999,40.766926],"type":"Point"}
}