{
  "type": "Feature",
  "properties": {
    "iso:country":"US",
    "sg:address":"44 Schilly Rd",
    "sg:city":"Central Square",
    "sg:classifiers":[
        {
            "category":"Education",
            "subcategory":"School",
            "type":"Public Place"
        }
    ],
    "sg:phone":"+1 315 668 4231",
    "sg:postcode":"13036",
    "sg:province":"NY",
    "sg:website":"www.cssd.org",
    "wof:name":"Paul V Moore High School",
    "wof:placetype":"venue"
},
  "geometry": {"coordinates":[-76.21229200000001,43.317614],"type":"Point"}
}