{
  "type": "Feature",
  "properties": {
    "iso:country":"US",
    "sg:address":"171 Grand St",
    "sg:city":"White Plains",
    "sg:classifiers":[
        {
            "category":"Home & Garden",
            "subcategory":"Home Furnishings",
            "type":"Retail Goods"
        }
    ],
    "sg:phone":"+1   ",
    "sg:postcode":"10601",
    "sg:province":"NY",
    "sg:tags":[
        "housewares"
    ],
    "wof:name":"Martin Schenke Inc",
    "wof:placetype":"venue"
},
  "geometry": {"coordinates":[-73.767768,41.029343],"type":"Point"}
}