{
  "type": "Feature",
  "properties": {
    "iso:country":"US",
    "sg:address":"190 Miller Pl",
    "sg:city":"Hicksville",
    "sg:classifiers":[
        {
            "category":"Autos & Motor Vehicles",
            "subcategory":"Auto Supplies",
            "type":"Retail Goods"
        }
    ],
    "sg:phone":"+1 516 433 1217",
    "sg:postcode":"11801",
    "sg:province":"NY",
    "sg:tags":[
        "automobile",
        "part",
        "accessory"
    ],
    "sg:website":"http://www.partsauthority.com",
    "wof:name":"Clearway",
    "wof:placetype":"venue"
},
  "geometry": {"coordinates":[-73.516575,40.784016],"type":"Point"}
}