{
  "type": "Feature",
  "properties": {
    "addr:full":"291 3rd Avenue Brooklyn NY 11215",
    "addr:housenumber":"291",
    "addr:postcode":"11215",
    "addr:street":"3Rd Avenue",
    "iso:country":"US",
    "sg:address":"291 3rd Avenue",
    "sg:city":"Brooklyn",
    "sg:classifiers":[
        {
            "category":"Restaurant",
            "type":"Food & Drink"
        }
    ],
    "sg:phone":"+1 718 624 0010",
    "sg:postcode":"11215",
    "sg:province":"NY",
    "sg:tags":[
        "pizza"
    ],
    "wof:name":"Tuscano's Pizzeria",
    "wof:placetype":"venue"
},
  "geometry": {"coordinates":[-73.986643,40.676548],"type":"Point"}
}