{
  "type": "Feature",
  "properties": {
    "addr:full":"19 E 26th St New York NY 10010",
    "addr:housenumber":"19",
    "addr:postcode":"10010",
    "addr:street":"E 26Th St",
    "iso:country":"US",
    "sg:address":"19 E 26th St",
    "sg:city":"New York",
    "sg:classifiers":[
        {
            "category":"Shopping",
            "subcategory":"Discount & Variety Stores",
            "type":"Retail Goods"
        }
    ],
    "sg:phone":"+1   ",
    "sg:postcode":"10010",
    "sg:province":"NY",
    "sg:tags":[
        "merchandise",
        "general"
    ],
    "wof:name":"Andrea By Sadek",
    "wof:placetype":"venue"
},
  "geometry": {"coordinates":[-73.98733799999999,40.743274],"type":"Point"}
}