{
  "type": "Feature",
  "properties": {
    "iso:country":"US",
    "sg:address":"16 Shore Cliff Pl",
    "sg:city":"Great Neck",
    "sg:classifiers":[
        {
            "category":"Banks & Credit Unions",
            "subcategory":"Investment Brokerage",
            "type":"Services"
        }
    ],
    "sg:phone":"+1 516 498 1727",
    "sg:postcode":"11023",
    "sg:province":"NY",
    "sg:tags":[
        "advisory"
    ],
    "wof:name":"Harbor Hills Capital LLC",
    "wof:placetype":"venue"
},
  "geometry": {"coordinates":[-73.75137599999999,40.787052],"type":"Point"}
}