{
  "type": "Feature",
  "properties": {
    "iso:country":"US",
    "sg:address":"25 Ryder Ave",
    "sg:city":"Huntington Station",
    "sg:classifiers":[
        {
            "category":"Recreation",
            "type":"Entertainment"
        }
    ],
    "sg:phone":"+1 631 586 5511",
    "sg:postcode":"11746",
    "sg:province":"NY",
    "wof:name":"Gillen Fishing Corporation",
    "wof:placetype":"venue"
},
  "geometry": {"coordinates":[-73.3506,40.783069],"type":"Point"}
}