{
  "type": "Feature",
  "properties": {
    "iso:country":"US",
    "sg:address":"3727 Nostrand Avenue",
    "sg:city":"Brooklyn",
    "sg:classifiers":[
        {
            "category":"Home & Garden",
            "subcategory":"Furniture",
            "type":"Retail Goods"
        }
    ],
    "sg:phone":"+1 718 769 7087",
    "sg:postcode":"11235",
    "sg:province":"NY",
    "sg:tags":[
        "store"
    ],
    "sg:website":"www.homedecorfurniture.com",
    "wof:name":"Home Decor Furniture & Lighting",
    "wof:placetype":"venue"
},
  "geometry": {"coordinates":[-73.94017599999999,40.592736],"type":"Point"}
}