{
  "type": "Feature",
  "properties": {
    "iso:country":"US",
    "sg:address":"148 Madison Ave",
    "sg:city":"New York",
    "sg:classifiers":[
        {
            "category":"Shopping",
            "subcategory":"Department Store",
            "type":"Retail Goods"
        }
    ],
    "sg:phone":"+1 212 561 3320",
    "sg:postcode":"10016",
    "sg:province":"NY",
    "wof:name":"Giggle",
    "wof:placetype":"venue"
},
  "geometry": {"coordinates":[-73.984073,40.746463],"type":"Point"}
}