{
  "type": "Feature",
  "properties": {
    "addr:full":"10 Heather Ln Elmsford NY 10523",
    "addr:housenumber":"10",
    "addr:postcode":"10523",
    "addr:street":"Heather Ln",
    "iso:country":"US",
    "sg:address":"10 Heather Ln",
    "sg:city":"Elmsford",
    "sg:classifiers":[
        {
            "category":"Professional",
            "subcategory":"Accounting & Tax Preparation",
            "type":"Services"
        }
    ],
    "sg:phone":"+1 914 592 1883",
    "sg:postcode":"10523",
    "sg:province":"NY",
    "sg:tags":[
        "payroll"
    ],
    "wof:name":"Knollwood Financial Svcs",
    "wof:placetype":"venue"
},
  "geometry": {"coordinates":[-73.80274799999999,41.062048],"type":"Point"}
}