{
  "type": "Feature",
  "properties": {
    "addr:full":"17 7th Ave Brooklyn NY 11217",
    "addr:housenumber":"17",
    "addr:postcode":"11217",
    "addr:street":"7Th Ave",
    "iso:country":"US",
    "sg:address":"17 7th Ave",
    "sg:city":"Brooklyn",
    "sg:classifiers":[
        {
            "category":"Health Services",
            "subcategory":"Health Practitioner",
            "type":"Services"
        }
    ],
    "sg:phone":"+1 718 638 0168",
    "sg:postcode":"11217",
    "sg:province":"NY",
    "sg:tags":[
        "pathologist",
        "speech"
    ],
    "wof:name":"Karen Louick",
    "wof:placetype":"venue"
},
  "geometry": {"coordinates":[-73.973325,40.67761],"type":"Point"}
}