{
  "type": "Feature",
  "properties": {
    "addr:full":"245 Canal St Frnt 1 New York NY 10013",
    "addr:housenumber":"245;1",
    "addr:postcode":"10013",
    "addr:street":"Canal St Frnt",
    "iso:country":"US",
    "sg:address":"245 Canal St Frnt 1",
    "sg:city":"New York",
    "sg:classifiers":[
        {
            "category":"Banks & Credit Unions",
            "subcategory":"Bank",
            "type":"Services"
        }
    ],
    "sg:phone":"+1 212 625 9854",
    "sg:postcode":"10013",
    "sg:province":"NY",
    "sg:website":"www.unitedcommercialbank.com",
    "wof:name":"United Commercial Bank",
    "wof:placetype":"venue"
},
  "geometry": {"coordinates":[-74.846715,40.718362],"type":"Point"}
}