{
  "type": "Feature",
  "properties": {
    "iso:country":"US",
    "sg:address":"156 Engineers Dr",
    "sg:city":"Hicksville",
    "sg:classifiers":[
        {
            "category":"Manufacturing",
            "subcategory":"Printing",
            "type":"Manufacturing & Wholesale Goods"
        }
    ],
    "sg:phone":"+1   ",
    "sg:postcode":"11801",
    "sg:province":"NY",
    "sg:tags":[
        "publishes",
        "classified",
        "advertising",
        "periodical"
    ],
    "wof:name":"Trader Publishing Company",
    "wof:placetype":"venue"
},
  "geometry": {"coordinates":[-73.50112300000001,40.744965],"type":"Point"}
}