{
  "type": "Feature",
  "properties": {
    "addr:full":"15 E 32nd St 12th Fl New York NY 10016",
    "addr:housenumber":"15",
    "addr:postcode":"10016",
    "addr:street":"E 32Nd St;Fl",
    "iso:country":"US",
    "sg:address":"15 E 32nd St 12th Fl",
    "sg:city":"New York",
    "sg:classifiers":[
        {
            "category":"Communications",
            "subcategory":"Newspaper",
            "type":"Services"
        }
    ],
    "sg:postcode":"10016",
    "sg:province":"NY",
    "sg:tags":[
        "print",
        "medium"
    ],
    "sg:website":"www.saveur.com",
    "wof:name":"Saveur Magazine",
    "wof:placetype":"venue"
},
  "geometry": {"coordinates":[-73.984495,40.746723],"type":"Point"}
}