{
  "type": "Feature",
  "properties": {
    "iso:country":"US",
    "sg:address":"70 W Broadway",
    "sg:city":"Salem",
    "sg:classifiers":[
        {
            "category":"Professional",
            "subcategory":"Business Services",
            "type":"Services"
        }
    ],
    "sg:phone":"+1 518 854 3389",
    "sg:postcode":"12865",
    "sg:province":"NY",
    "sg:tags":[
        "house",
        "construction"
    ],
    "wof:name":"Restorations Unlimited",
    "wof:placetype":"venue"
},
  "geometry": {"coordinates":[-73.333163,43.17089],"type":"Point"}
}