{
  "type": "Feature",
  "properties": {
    "iso:country":"US",
    "sg:address":"35 Trade Zone Dr",
    "sg:city":"Ronkonkoma",
    "sg:classifiers":[
        {
            "category":"Recreation",
            "type":"Entertainment"
        }
    ],
    "sg:phone":"+1 631 981 2218",
    "sg:postcode":"11779",
    "sg:province":"NY",
    "sg:tags":[
        "amusement"
    ],
    "wof:name":"Demonte Motor Sports Corp",
    "wof:placetype":"venue"
},
  "geometry": {"coordinates":[-73.090416,40.782933],"type":"Point"}
}