{
  "type": "Feature",
  "properties": {
    "addr:full":"200 Lark Dr Albany NY 12210",
    "addr:housenumber":"200",
    "addr:postcode":"12210",
    "addr:street":"Lark Dr",
    "iso:country":"US",
    "sg:address":"200 Lark Dr",
    "sg:city":"Albany",
    "sg:classifiers":[
        {
            "category":"Real Estate",
            "subcategory":"Real Estate Operator",
            "type":"Services"
        }
    ],
    "sg:phone":"+1 518 463 8356",
    "sg:postcode":"12210",
    "sg:province":"NY",
    "sg:tags":[
        "apartment"
    ],
    "wof:name":"Capital Woods Apartments",
    "wof:placetype":"venue"
},
  "geometry": {"coordinates":[-73.752692,42.664873],"type":"Point"}
}