{
  "type": "Feature",
  "properties": {
    "addr:full":"95 Lexington Ave New York NY 10016",
    "addr:housenumber":"95",
    "addr:postcode":"10016",
    "addr:street":"Lexington Ave",
    "iso:country":"US",
    "sg:address":"95 Lexington Ave",
    "sg:city":"New York",
    "sg:classifiers":[
        {
            "category":"Professional",
            "subcategory":"Art Services",
            "type":"Services"
        }
    ],
    "sg:phone":"+1   ",
    "sg:postcode":"10016",
    "sg:province":"NY",
    "sg:tags":[
        "commercial",
        "design"
    ],
    "wof:name":"Sherpa Productions",
    "wof:placetype":"venue"
},
  "geometry": {"coordinates":[-73.983149,40.74144],"type":"Point"}
}