{
  "type": "Feature",
  "properties": {
    "addr:full":"474 Sunrise Hwy Amityville NY 11701",
    "addr:housenumber":"474",
    "addr:postcode":"11701",
    "addr:street":"Sunrise Hwy",
    "iso:country":"US",
    "sg:address":"474 Sunrise Hwy",
    "sg:city":"Amityville",
    "sg:classifiers":[
        {
            "category":"Organizations",
            "subcategory":"Religious Organization",
            "type":"Services"
        }
    ],
    "sg:phone":"+1 631 789 0443",
    "sg:postcode":"11701",
    "sg:province":"NY",
    "wof:name":"Outreach Ministries",
    "wof:placetype":"venue"
},
  "geometry": {"coordinates":[-73.41127400000001,40.688679],"type":"Point"}
}