{
  "type": "Feature",
  "properties": {
    "addr:full":"88 Silver St Rochester NY 14611",
    "addr:housenumber":"88",
    "addr:postcode":"14611",
    "addr:street":"Silver St",
    "iso:country":"US",
    "sg:address":"88 Silver St",
    "sg:city":"Rochester",
    "sg:classifiers":[
        {
            "category":"Building & Trades",
            "subcategory":"Landscaping Services",
            "type":"Services"
        }
    ],
    "sg:phone":"+1 585 507 4484",
    "sg:postcode":"14611",
    "sg:province":"NY",
    "sg:tags":[
        "lawn",
        "tree",
        "arborist",
        "maintenance"
    ],
    "sg:website":"http://www-davey-com.netsolads.com/home/local-arborist/rochester-new-york.aspx?_nsag=45592",
    "wof:name":"The Davey Tree Expert Company",
    "wof:placetype":"venue"
},
  "geometry": {"coordinates":[-77.633652,43.153487],"type":"Point"}
}