{
  "type": "Feature",
  "properties": {
    "iso:country":"US",
    "sg:address":"804 Clinton Ave N",
    "sg:city":"Rochester",
    "sg:classifiers":[
        {
            "category":"Restaurant",
            "type":"Food & Drink"
        }
    ],
    "sg:phone":"+1 585 262 3888",
    "sg:postcode":"14605",
    "sg:province":"NY",
    "wof:name":"Wang's",
    "wof:placetype":"venue"
},
  "geometry": {"coordinates":[-77.612713,43.173338],"type":"Point"}
}