{
  "type": "Feature",
  "properties": {
    "addr:full":"220 Beech St Lawrence NY 11580",
    "addr:housenumber":"220",
    "addr:postcode":"11580",
    "addr:street":"Beech St",
    "iso:country":"US",
    "sg:address":"220 Beech St",
    "sg:city":"Lawrence",
    "sg:classifiers":[
        {
            "category":"Health Services",
            "subcategory":"Doctor",
            "type":"Services"
        }
    ],
    "sg:phone":"+1 516 371 5854",
    "sg:postcode":"11580",
    "sg:province":"NY",
    "sg:tags":[
        "medical"
    ],
    "wof:name":"Yonah Hamlet MD",
    "wof:placetype":"venue"
},
  "geometry": {"coordinates":[-73.726342,40.670306],"type":"Point"}
}