{
  "type": "Feature",
  "properties": {
    "addr:full":"1560 Jerome Ave Bronx NY 10452",
    "addr:housenumber":"1560",
    "addr:postcode":"10452",
    "addr:street":"Jerome Ave",
    "iso:country":"US",
    "sg:address":"1560 Jerome Ave",
    "sg:city":"Bronx",
    "sg:classifiers":[
        {
            "category":"Retail",
            "subcategory":"Auto Repair",
            "type":"Services"
        }
    ],
    "sg:phone":"+1 718 716 4119",
    "sg:postcode":"10452",
    "sg:province":"NY",
    "sg:tags":[
        "wrecker"
    ],
    "wof:name":"ABC Towing",
    "wof:placetype":"venue"
},
  "geometry": {"coordinates":[-73.91580999999999,40.842538],"type":"Point"}
}