{
  "type": "Feature",
  "properties": {
    "iso:country":"US",
    "sg:address":"26 Norwood Rd",
    "sg:city":"Hampton Bays",
    "sg:classifiers":[
        {
            "category":"Building & Trades",
            "subcategory":"Construction",
            "type":"Services"
        }
    ],
    "sg:phone":"+1 631 728 5852",
    "sg:postcode":"11946",
    "sg:province":"NY",
    "sg:tags":[
        "painter"
    ],
    "wof:name":"J Benavides Painting",
    "wof:placetype":"venue"
},
  "geometry": {"coordinates":[-72.55163899999999,40.861024],"type":"Point"}
}