{
  "type": "Feature",
  "properties": {
    "iso:country":"US",
    "sg:address":"125 Kenmore Ave",
    "sg:city":"Syracuse",
    "sg:classifiers":[
        {
            "category":"Wholesale",
            "subcategory":"Vending Machines",
            "type":"Manufacturing & Wholesale Goods"
        }
    ],
    "sg:phone":"+1   ",
    "sg:postcode":"13205",
    "sg:province":"NY",
    "sg:tags":[
        "company"
    ],
    "wof:name":"Laurean Snacks",
    "wof:placetype":"venue"
},
  "geometry": {"coordinates":[-76.152,43.013805],"type":"Point"}
}