{
  "type": "Feature",
  "properties": {
    "addr:full":"NYU Hospital for Joint Diseases 301 E 17th St Ste 400 Manhattan NY 10003",
    "addr:housenumber":"301",
    "addr:postcode":"10003",
    "addr:street":"E 17Th St Ste 400",
    "iso:country":"US",
    "sg:address":"NYU Hospital for Joint Diseases 301 E 17th St Ste 400",
    "sg:city":"Manhattan",
    "sg:classifiers":[
        {
            "category":"Health Services",
            "subcategory":"Doctor",
            "type":"Services"
        }
    ],
    "sg:phone":"+1 212 598 6697",
    "sg:postcode":"10003",
    "sg:province":"NY",
    "sg:tags":[
        "orthopedist"
    ],
    "sg:website":"www.med.nyu.edu/clinicians/lees2...",
    "wof:name":"Steve K. Lee, M.D.",
    "wof:placetype":"venue"
},
  "geometry": {"coordinates":[-73.983504,40.734266],"type":"Point"}
}