{
  "type": "Feature",
  "properties": {
    "addr:full":"2829 White Plains Rd Bronx NY 10467",
    "addr:housenumber":"2829",
    "addr:postcode":"10467",
    "addr:street":"White Plains Rd",
    "iso:country":"US",
    "sg:address":"2829 White Plains Rd",
    "sg:city":"Bronx",
    "sg:classifiers":[
        {
            "category":"Retail",
            "subcategory":"Laundry & Dry Cleaning",
            "type":"Services"
        }
    ],
    "sg:phone":"+1   ",
    "sg:postcode":"10467",
    "sg:province":"NY",
    "sg:tags":[
        "garment",
        "agent"
    ],
    "wof:name":"Majesty Cleaners",
    "wof:placetype":"venue"
},
  "geometry": {"coordinates":[-73.867358,40.867516],"type":"Point"}
}