{
  "type": "Feature",
  "properties": {
    "iso:country":"US",
    "sg:address":"61 Lake Ave",
    "sg:city":"Saratoga Springs",
    "sg:classifiers":[
        {
            "category":"Museum",
            "type":"Entertainment"
        }
    ],
    "sg:phone":"+1   ",
    "sg:postcode":"12866",
    "sg:province":"NY",
    "sg:tags":[
        "gallery"
    ],
    "wof:name":"NY State Military Heritg Inst",
    "wof:placetype":"venue"
},
  "geometry": {"coordinates":[-73.782195,43.082752],"type":"Point"}
}