{
  "type": "Feature",
  "properties": {
    "addr:full":"231 W 116th Street New York NY 10026",
    "addr:housenumber":"231",
    "addr:postcode":"10026",
    "addr:street":"W 116Th Street",
    "iso:country":"US",
    "sg:address":"231 W 116th Street",
    "sg:city":"New York",
    "sg:classifiers":[
        {
            "category":"Restaurant",
            "type":"Food & Drink"
        }
    ],
    "sg:phone":"+1 212 663 0717",
    "sg:postcode":"10026",
    "sg:province":"NY",
    "wof:name":"Dibiterie Cheikh Restaurant",
    "wof:placetype":"venue"
},
  "geometry": {"coordinates":[-73.95353900000001,40.803665],"type":"Point"}
}