{
  "type": "Feature",
  "properties": {
    "iso:country":"US",
    "sg:address":"353 Lang Blvd",
    "sg:city":"Grand Island",
    "sg:classifiers":[
        {
            "category":"Freight",
            "type":"Transportation"
        }
    ],
    "sg:phone":"+1 716 773 7301",
    "sg:postcode":"14072",
    "sg:province":"NY",
    "sg:tags":[
        "broker",
        "customs"
    ],
    "wof:name":"Danasons Border Svc Inc",
    "wof:placetype":"venue"
},
  "geometry": {"coordinates":[-78.97836599999999,43.033667],"type":"Point"}
}