{
  "type": "Feature",
  "properties": {
    "addr:full":"252 Central Ave Buffalo NY 14206",
    "addr:housenumber":"252",
    "addr:postcode":"14206",
    "addr:street":"Central Ave",
    "iso:country":"US",
    "sg:address":"252 Central Ave",
    "sg:city":"Buffalo",
    "sg:classifiers":[
        {
            "category":"Arena",
            "subcategory":"Sports Club",
            "type":"Entertainment"
        }
    ],
    "sg:phone":"+1 716 675 0899",
    "sg:postcode":"14206",
    "sg:province":"NY",
    "sg:tags":[
        "martial art",
        "instruction"
    ],
    "sg:website":"http://www.horizonma.com",
    "wof:name":"Horizon Martial Arts Inc",
    "wof:placetype":"venue"
},
  "geometry": {"coordinates":[-78.81527199999999,42.892326],"type":"Point"}
}