{
  "type": "Feature",
  "properties": {
    "iso:country":"US",
    "sg:address":"203 Curtis Pkwy",
    "sg:city":"Buffalo",
    "sg:classifiers":[
        {
            "category":"Health Services",
            "subcategory":"Doctor",
            "type":"Services"
        }
    ],
    "sg:phone":"+1   ",
    "sg:postcode":"14223",
    "sg:province":"NY",
    "wof:name":"J V Lucchese Sr DDS",
    "wof:placetype":"venue"
},
  "geometry": {"coordinates":[-78.827207,42.977837],"type":"Point"}
}