{
  "type": "Feature",
  "properties": {
    "iso:country":"US",
    "sg:address":"572 Walt Whitman Rd",
    "sg:city":"Melville",
    "sg:classifiers":[
        {
            "category":"Professional",
            "subcategory":"Engineering",
            "type":"Services"
        },
        {
            "category":"Real Estate",
            "subcategory":"Surveying",
            "type":"Services"
        }
    ],
    "sg:phone":"+1 631 427 5665",
    "sg:postcode":"11747",
    "sg:province":"NY",
    "sg:tags":[
        "civil",
        "surveyor",
        "engineer"
    ],
    "sg:website":"www.nelsonpope.com",
    "wof:name":"Nelson & Pope LLP",
    "wof:placetype":"venue"
},
  "geometry": {"coordinates":[-73.409943,40.807441],"type":"Point"}
}