{
  "type": "Feature",
  "properties": {
    "iso:country":"US",
    "sg:address":"25 Hoffman St",
    "sg:city":"Auburn",
    "sg:classifiers":[
        {
            "category":"Wholesale",
            "subcategory":"Machinery & Supplies",
            "type":"Manufacturing & Wholesale Goods"
        }
    ],
    "sg:phone":"+1 315 252 0556",
    "sg:postcode":"13021",
    "sg:province":"NY",
    "wof:name":"Auburn Irrigations",
    "wof:placetype":"venue"
},
  "geometry": {"coordinates":[-76.557632,42.931607],"type":"Point"}
}