{
  "type": "Feature",
  "properties": {
    "addr:full":"186 Clinton St Hempstead NY 11550",
    "addr:housenumber":"186",
    "addr:postcode":"11550",
    "addr:street":"Clinton St",
    "iso:country":"US",
    "sg:address":"186 Clinton St",
    "sg:city":"Hempstead",
    "sg:classifiers":[
        {
            "category":"Banks & Credit Unions",
            "subcategory":"Financial Services",
            "type":"Services"
        }
    ],
    "sg:phone":"+1 516 750 5817",
    "sg:postcode":"11550",
    "sg:province":"NY",
    "sg:tags":[
        "broker",
        "mortgage"
    ],
    "wof:name":"Apex Mortgage",
    "wof:placetype":"venue"
},
  "geometry": {"coordinates":[-73.620364,40.711837],"type":"Point"}
}