{
  "type": "Feature",
  "properties": {
    "addr:full":"1322 Huckleberry Ln Hewlett NY 11557",
    "addr:housenumber":"1322",
    "addr:postcode":"11557",
    "addr:street":"Huckleberry Ln",
    "iso:country":"US",
    "sg:address":"1322 Huckleberry Ln",
    "sg:city":"Hewlett",
    "sg:classifiers":[
        {
            "category":"Professional",
            "subcategory":"Accounting & Tax Preparation",
            "type":"Services"
        }
    ],
    "sg:phone":"+1   ",
    "sg:postcode":"11557",
    "sg:province":"NY",
    "wof:name":"Burt Laskin",
    "wof:placetype":"venue"
},
  "geometry": {"coordinates":[-73.682931,40.640138],"type":"Point"}
}