{
  "type": "Feature",
  "properties": {
    "iso:country":"US",
    "sg:address":"7873 W Thomas St",
    "sg:city":"Rome",
    "sg:classifiers":[
        {
            "category":"Autos & Motor Vehicles",
            "subcategory":"Auto Supplies",
            "type":"Retail Goods"
        }
    ],
    "sg:phone":"+1 315 338 9878",
    "sg:postcode":"13440",
    "sg:province":"NY",
    "sg:tags":[
        "equipment",
        "racing",
        "car",
        "automobile"
    ],
    "wof:name":"Dehimer Racing Enterprises Inc",
    "wof:placetype":"venue"
},
  "geometry": {"coordinates":[-75.47599099999999,43.243719],"type":"Point"}
}