{
  "type": "Feature",
  "properties": {
    "iso:country":"US",
    "sg:address":"6481 Main St",
    "sg:city":"Portland",
    "sg:classifiers":[
        {
            "category":"Professional",
            "type":"Services"
        }
    ],
    "sg:phone":"+1 716 792 9296",
    "sg:postcode":"14769",
    "sg:province":"NY",
    "sg:tags":[
        "establishment"
    ],
    "wof:name":"Portland Station 1",
    "wof:placetype":"venue"
},
  "geometry": {"coordinates":[-79.47758,42.375395],"type":"Point"}
}