{
  "type": "Feature",
  "properties": {
    "iso:country":"US",
    "sg:address":"300 Mercer St",
    "sg:city":"New York",
    "sg:classifiers":[
        {
            "category":"Banks & Credit Unions",
            "subcategory":"Investment Brokerage",
            "type":"Services"
        }
    ],
    "sg:phone":"+1 212 260 0906",
    "sg:postcode":"10003",
    "sg:province":"NY",
    "sg:tags":[
        "security"
    ],
    "wof:name":"Robert Blatt M D",
    "wof:placetype":"venue"
},
  "geometry": {"coordinates":[-73.993495,40.730421],"type":"Point"}
}