{
  "type": "Feature",
  "properties": {
    "addr:full":"413 Pennsylvania Ave Brooklyn NY 11207",
    "addr:housenumber":"413",
    "addr:postcode":"11207",
    "addr:street":"Pennsylvania Ave",
    "iso:country":"US",
    "sg:address":"413 Pennsylvania Ave",
    "sg:city":"Brooklyn",
    "sg:classifiers":[
        {
            "category":"Building & Trades",
            "subcategory":"Construction",
            "type":"Services"
        }
    ],
    "sg:phone":"+1 718 495 5920",
    "sg:postcode":"11207",
    "sg:province":"NY",
    "sg:tags":[
        "general",
        "contractor"
    ],
    "wof:name":"New York Penn Construction",
    "wof:placetype":"venue"
},
  "geometry": {"coordinates":[-73.89447699999999,40.666894],"type":"Point"}
}