{
  "type": "Feature",
  "properties": {
    "iso:country":"US",
    "sg:address":"136 Seneca St",
    "sg:city":"Buffalo",
    "sg:classifiers":[
        {
            "category":"Shopping",
            "subcategory":"Used Merchandise",
            "type":"Retail Goods"
        }
    ],
    "sg:phone":"+1   ",
    "sg:postcode":"14203",
    "sg:province":"NY",
    "sg:tags":[
        "shop",
        "pawn"
    ],
    "wof:name":"Browns Pawn Shop",
    "wof:placetype":"venue"
},
  "geometry": {"coordinates":[-78.870811,42.879795],"type":"Point"}
}