{
  "type": "Feature",
  "properties": {
    "addr:full":"20413 Jamaica Ave Hollis NY 11423",
    "addr:housenumber":"20413",
    "addr:postcode":"11423",
    "addr:street":"Jamaica Ave",
    "iso:country":"US",
    "sg:address":"20413 Jamaica Ave",
    "sg:city":"Hollis",
    "sg:classifiers":[
        {
            "category":"Real Estate",
            "subcategory":"Real Estate Services",
            "type":"Services"
        },
        {
            "category":"Real Estate",
            "subcategory":"Developer",
            "type":"Services"
        },
        {
            "category":"Real Estate",
            "subcategory":"Real Estate Agent",
            "type":"Services"
        }
    ],
    "sg:phone":"+1 718 736 8309",
    "sg:postcode":"11423",
    "sg:province":"NY",
    "sg:tags":[
        "buyer",
        "broker"
    ],
    "wof:name":"Hinterland Development Inc",
    "wof:placetype":"venue"
},
  "geometry": {"coordinates":[-73.75616100000001,40.713509],"type":"Point"}
}