{
  "type": "Feature",
  "properties": {
    "addr:full":"4510 White Plains Rd Bronx NY 10470",
    "addr:housenumber":"4510",
    "addr:postcode":"10470",
    "addr:street":"White Plains Rd",
    "iso:country":"US",
    "sg:address":"4510 White Plains Rd",
    "sg:city":"Bronx",
    "sg:classifiers":[
        {
            "category":"Manufacturing",
            "subcategory":"Motor Vehicles & Parts",
            "type":"Manufacturing & Wholesale Goods"
        }
    ],
    "sg:phone":"+1 718 325 7700",
    "sg:postcode":"10470",
    "sg:province":"NY",
    "sg:tags":[
        "shoulder",
        "pad"
    ],
    "wof:name":"Mona Slide Fastners Inc",
    "wof:placetype":"venue"
},
  "geometry": {"coordinates":[-73.851597,40.9018],"type":"Point"}
}