{
  "type": "Feature",
  "properties": {
    "iso:country":"US",
    "sg:address":"660 Redman Rd",
    "sg:city":"Hamlin",
    "sg:classifiers":[
        {
            "category":"Sports & Exercise",
            "subcategory":"Golf",
            "type":"Entertainment"
        }
    ],
    "sg:phone":"+1 585 964 2903",
    "sg:postcode":"14464",
    "sg:province":"NY",
    "sg:tags":[
        "course"
    ],
    "wof:name":"Ozzie's Corner Maintenance Shp",
    "wof:placetype":"venue"
},
  "geometry": {"coordinates":[-77.965154,43.348983],"type":"Point"}
}