{
  "type": "Feature",
  "properties": {
    "addr:full":"2704 80th Ave New Hyde Park NY 11040",
    "addr:housenumber":"2704",
    "addr:postcode":"11040",
    "addr:street":"80Th Ave",
    "iso:country":"US",
    "sg:address":"2704 80th Ave",
    "sg:city":"New Hyde Park",
    "sg:classifiers":[
        {
            "category":"Building & Trades",
            "subcategory":"Electrical",
            "type":"Services"
        }
    ],
    "sg:phone":"+1 516 358 7212",
    "sg:postcode":"11040",
    "sg:province":"NY",
    "sg:tags":[
        "electrical",
        "contractor"
    ],
    "wof:name":"Morr El Electric Corp",
    "wof:placetype":"venue"
},
  "geometry": {"coordinates":[-73.698532,40.747499],"type":"Point"}
}