{
  "type": "Feature",
  "properties": {
    "addr:full":"196 Joralemon St Brooklyn NY 11201",
    "addr:housenumber":"196",
    "addr:postcode":"11201",
    "addr:street":"Joralemon St",
    "iso:country":"US",
    "sg:address":"196 Joralemon St",
    "sg:city":"Brooklyn",
    "sg:classifiers":[
        {
            "category":"Shopping",
            "subcategory":"Jewelry",
            "type":"Retail Goods"
        }
    ],
    "sg:phone":"+1   ",
    "sg:postcode":"11201",
    "sg:province":"NY",
    "sg:tags":[
        "repair"
    ],
    "wof:name":"Jewels By Satnick Ltd",
    "wof:placetype":"venue"
},
  "geometry": {"coordinates":[-73.99229,40.692714],"type":"Point"}
}