{
  "type": "Feature",
  "properties": {
    "addr:full":"285 Lexington Ave New York NY 10016",
    "addr:housenumber":"285",
    "addr:postcode":"10016",
    "addr:street":"Lexington Ave",
    "iso:country":"US",
    "sg:address":"285 Lexington Ave",
    "sg:city":"New York",
    "sg:classifiers":[
        {
            "category":"Health Services",
            "subcategory":"Doctor",
            "type":"Services"
        }
    ],
    "sg:phone":"+1 212 532 8508",
    "sg:postcode":"10016",
    "sg:province":"NY",
    "sg:tags":[
        "physician",
        "surgeon",
        "medical"
    ],
    "wof:name":"Jeffrey Glasser MD",
    "wof:placetype":"venue"
},
  "geometry": {"coordinates":[-73.9785,40.747854],"type":"Point"}
}