{
  "type": "Feature",
  "properties": {
    "addr:full":"485 Falconer St Jamestown NY 14701",
    "addr:housenumber":"485",
    "addr:postcode":"14701",
    "addr:street":"Falconer St",
    "iso:country":"US",
    "sg:address":"485 Falconer St",
    "sg:city":"Jamestown",
    "sg:classifiers":[
        {
            "category":"Recreation",
            "type":"Entertainment"
        }
    ],
    "sg:phone":"+1 716 665 4710",
    "sg:postcode":"14701",
    "sg:province":"NY",
    "sg:tags":[
        "parks"
    ],
    "wof:name":"Diethrick Park",
    "wof:placetype":"venue"
},
  "geometry": {"coordinates":[-79.218019,42.113147],"type":"Point"}
}