{
  "type": "Feature",
  "properties": {
    "addr:full":"200 W 57th St Ste 1402 New York NY 10019",
    "addr:housenumber":"200",
    "addr:postcode":"10019",
    "addr:street":"W 57Th St Ste 1402",
    "iso:country":"US",
    "sg:address":"200 W 57th St Ste 1402",
    "sg:city":"New York",
    "sg:classifiers":[
        {
            "category":"Health Services",
            "subcategory":"Doctor",
            "type":"Services"
        }
    ],
    "sg:phone":"+1 212 262 9285",
    "sg:postcode":"10019",
    "sg:province":"NY",
    "wof:name":"Horowitz Mark MD",
    "wof:placetype":"venue"
},
  "geometry": {"coordinates":[-73.980003,40.765499],"type":"Point"}
}