{
  "type": "Feature",
  "properties": {
    "addr:full":"4742 Sabre Ln Manlius NY 13104",
    "addr:housenumber":"4742",
    "addr:postcode":"13104",
    "addr:street":"Sabre Ln",
    "iso:country":"US",
    "sg:address":"4742 Sabre Ln",
    "sg:city":"Manlius",
    "sg:classifiers":[
        {
            "category":"Insurance",
            "subcategory":"Insurance Agent",
            "type":"Services"
        }
    ],
    "sg:phone":"+1 315 682 2436",
    "sg:postcode":"13104",
    "sg:province":"NY",
    "sg:tags":[
        "consultant"
    ],
    "wof:name":"Creative Capital",
    "wof:placetype":"venue"
},
  "geometry": {"coordinates":[-75.967484,42.999176],"type":"Point"}
}