{
  "type": "Feature",
  "properties": {
    "addr:full":"442 Ave U Brooklyn NY 11223",
    "addr:housenumber":"442",
    "addr:postcode":"11223",
    "addr:street":"Ave U",
    "iso:country":"US",
    "sg:address":"442 Ave U",
    "sg:city":"Brooklyn",
    "sg:classifiers":[
        {
            "category":"Freight",
            "type":"Transportation"
        }
    ],
    "sg:phone":"+1   ",
    "sg:postcode":"11223",
    "sg:province":"NY",
    "sg:tags":[
        "domestic",
        "sea"
    ],
    "wof:name":"Ralph Shaalo Enterprises",
    "wof:placetype":"venue"
},
  "geometry": {"coordinates":[-73.96684999999999,40.597683],"type":"Point"}
}