{
  "type": "Feature",
  "properties": {
    "iso:country":"US",
    "sg:address":"711 Medford Ave",
    "sg:city":"Patchogue",
    "sg:classifiers":[
        {
            "category":"Professional",
            "type":"Services"
        },
        {
            "category":"Restaurant",
            "type":"Food & Drink"
        }
    ],
    "sg:phone":"+1 631 654 5180",
    "sg:postcode":"11772",
    "sg:province":"NY",
    "sg:tags":[
        "pizza",
        "caterer"
    ],
    "wof:name":"Royal Pizzeria",
    "wof:placetype":"venue"
},
  "geometry": {"coordinates":[-73.009201,40.786598],"type":"Point"}
}