{
  "type": "Feature",
  "properties": {
    "addr:full":"13585 State Hwy 37 Massena NY 13662",
    "addr:housenumber":"13585",
    "addr:postcode":"13662",
    "addr:street":"State Hwy 37",
    "iso:country":"US",
    "sg:address":"13585 State Hwy 37",
    "sg:city":"Massena",
    "sg:classifiers":[
        {
            "category":"Autos & Motor Vehicles",
            "subcategory":"Automobile Sales",
            "type":"Retail Goods"
        }
    ],
    "sg:phone":"+1 315 769 7373",
    "sg:postcode":"13662",
    "sg:province":"NY",
    "sg:tags":[
        "car",
        "dealer"
    ],
    "wof:name":"Bylow's Auto Sales",
    "wof:placetype":"venue"
},
  "geometry": {"coordinates":[-75.088683,44.898009],"type":"Point"}
}