{
  "type": "Feature",
  "properties": {
    "iso:country":"US",
    "sg:address":"1535 Broadway",
    "sg:city":"New York",
    "sg:classifiers":[
        {
            "category":"Travel",
            "subcategory":"Hotels & Motels",
            "type":"Entertainment"
        }
    ],
    "sg:phone":"+1 212 398 1900",
    "sg:postcode":"10036",
    "sg:province":"NY",
    "sg:website":"www.marriott.com",
    "wof:name":"New York Marriott Marquis",
    "wof:placetype":"venue"
},
  "geometry": {"coordinates":[-73.985517,40.758408],"type":"Point"}
}