{
  "type": "Feature",
  "properties": {
    "iso:country":"US",
    "sg:address":"19 Maiden Ln",
    "sg:city":"Cohoes",
    "sg:classifiers":[
        {
            "category":"Building & Trades",
            "subcategory":"Construction",
            "type":"Services"
        }
    ],
    "sg:phone":"+1 518 237 2187",
    "sg:postcode":"12047",
    "sg:province":"NY",
    "sg:tags":[
        "contractor"
    ],
    "wof:name":"Quality Roofing & Remodeling",
    "wof:placetype":"venue"
},
  "geometry": {"coordinates":[-73.71006800000001,42.783381],"type":"Point"}
}