{
  "type": "Feature",
  "properties": {
    "addr:full":"1214 Nostrand Ave Brooklyn NY 11225",
    "addr:housenumber":"1214",
    "addr:postcode":"11225",
    "addr:street":"Nostrand Ave",
    "iso:country":"US",
    "sg:address":"1214 Nostrand Ave",
    "sg:city":"Brooklyn",
    "sg:classifiers":[
        {
            "category":"Professional",
            "subcategory":"Advertising",
            "type":"Services"
        }
    ],
    "sg:phone":"+1 718 467 2130",
    "sg:postcode":"11225",
    "sg:province":"NY",
    "sg:tags":[
        "distribution"
    ],
    "wof:name":"Nettel Distribution",
    "wof:placetype":"venue"
},
  "geometry": {"coordinates":[-73.95034099999999,40.657337],"type":"Point"}
}