{
  "type": "Feature",
  "properties": {
    "iso:country":"US",
    "sg:address":"1823 South Rd",
    "sg:city":"Wappingers Falls",
    "sg:classifiers":[
        {
            "category":"Professional",
            "subcategory":"Lawyer & Legal Services",
            "type":"Services"
        }
    ],
    "sg:phone":"+1 845 485 3377",
    "sg:postcode":"12590",
    "sg:province":"NY",
    "wof:name":"Ernest L. Harris Attorney At Law",
    "wof:placetype":"venue"
},
  "geometry": {"coordinates":[-73.914143,41.613604],"type":"Point"}
}