{
  "type": "Feature",
  "properties": {
    "addr:full":"85 Broadview Ave Kings Park NY 11754",
    "addr:housenumber":"85",
    "addr:postcode":"11754",
    "addr:street":"Broadview Ave",
    "iso:country":"US",
    "sg:address":"85 Broadview Ave",
    "sg:city":"Kings Park",
    "sg:classifiers":[
        {
            "category":"Professional",
            "subcategory":"Lawyer & Legal Services",
            "type":"Services"
        }
    ],
    "sg:phone":"+1 631 269 5095",
    "sg:postcode":"11754",
    "sg:province":"NY",
    "sg:tags":[
        "attorney"
    ],
    "wof:name":"Lisa S Fine PC Law Offices",
    "wof:placetype":"venue"
},
  "geometry": {"coordinates":[-73.25367199999999,40.901561],"type":"Point"}
}