{
  "type": "Feature",
  "properties": {
    "addr:full":"1930 Patterson Avenue Bronx NY 10473",
    "addr:housenumber":"1930",
    "addr:postcode":"10473",
    "addr:street":"Patterson Avenue",
    "iso:country":"US",
    "sg:address":"1930 Patterson Avenue",
    "sg:city":"Bronx",
    "sg:classifiers":[
        {
            "category":"Restaurant",
            "type":"Food & Drink"
        }
    ],
    "sg:phone":"+1 718 589 1875",
    "sg:postcode":"10473",
    "sg:province":"NY",
    "sg:tags":[
        "mexican"
    ],
    "wof:name":"El Rincon Restaurant",
    "wof:placetype":"venue"
},
  "geometry": {"coordinates":[-73.855721,40.813523],"type":"Point"}
}