{
  "type": "Feature",
  "properties": {
    "iso:country":"US",
    "sg:address":"5310 Church Ave",
    "sg:city":"Brooklyn",
    "sg:classifiers":[
        {
            "category":"Personal",
            "subcategory":"Nail Salon",
            "type":"Services"
        }
    ],
    "sg:phone":"+1 718 345 1862",
    "sg:postcode":"11203",
    "sg:province":"NY",
    "wof:name":"Fancy Nail Salon Inc",
    "wof:placetype":"venue"
},
  "geometry": {"coordinates":[-73.927397,40.65219],"type":"Point"}
}