{
  "type": "Feature",
  "properties": {
    "addr:full":"9 Elm Pl Amityville NY 11701",
    "addr:housenumber":"9",
    "addr:postcode":"11701",
    "addr:street":"Elm Pl",
    "iso:country":"US",
    "sg:address":"9 Elm Pl",
    "sg:city":"Amityville",
    "sg:classifiers":[
        {
            "category":"Retail",
            "subcategory":"Auto Repair",
            "type":"Services"
        }
    ],
    "sg:phone":"+1 631 842 2922",
    "sg:postcode":"11701",
    "sg:province":"NY",
    "sg:tags":[
        "wrecker"
    ],
    "wof:name":"Bang's Towing",
    "wof:placetype":"venue"
},
  "geometry": {"coordinates":[-73.41370999999999,40.6827],"type":"Point"}
}