{
  "type": "Feature",
  "properties": {
    "addr:full":"239 Genesee St Utica NY 13501",
    "addr:housenumber":"239",
    "addr:postcode":"13501",
    "addr:street":"Genesee St",
    "iso:country":"US",
    "sg:address":"239 Genesee St",
    "sg:city":"Utica",
    "sg:classifiers":[
        {
            "category":"Communications",
            "subcategory":"Radio Station",
            "type":"Services"
        }
    ],
    "sg:phone":"+1 315 733 5477",
    "sg:postcode":"13501",
    "sg:province":"NY",
    "sg:tags":[
        "company",
        "broadcasting"
    ],
    "sg:website":"www.cnykiss.com",
    "wof:name":"KISS",
    "wof:placetype":"venue"
},
  "geometry": {"coordinates":[-75.23370199999999,43.100111],"type":"Point"}
}