{
  "type": "Feature",
  "properties": {
    "addr:full":"6724 14th Ave Brooklyn NY 11219",
    "addr:housenumber":"6724",
    "addr:postcode":"11219",
    "addr:street":"14Th Ave",
    "iso:country":"US",
    "sg:address":"6724 14th Ave",
    "sg:city":"Brooklyn",
    "sg:classifiers":[
        {
            "category":"Food & Beverages",
            "subcategory":"Groceries & Convenience Stores",
            "type":"Retail Goods"
        }
    ],
    "sg:phone":"+1   ",
    "sg:postcode":"11219",
    "sg:province":"NY",
    "wof:name":"Platinum Deli & Grocery",
    "wof:placetype":"venue"
},
  "geometry": {"coordinates":[-74.001135,40.623047],"type":"Point"}
}