{
  "type": "Feature",
  "properties": {
    "addr:full":"34 Public Sq Watertown NY 13601",
    "addr:housenumber":"34",
    "addr:postcode":"13601",
    "addr:street":"Public Sq",
    "iso:country":"US",
    "sg:address":"34 Public Sq",
    "sg:city":"Watertown",
    "sg:classifiers":[
        {
            "category":"Banks & Credit Unions",
            "subcategory":"Investment Brokerage",
            "type":"Services"
        }
    ],
    "sg:phone":"+1 315 779 8045",
    "sg:postcode":"13601",
    "sg:province":"NY",
    "sg:tags":[
        "advisory"
    ],
    "wof:name":"Charles V Berkman",
    "wof:placetype":"venue"
},
  "geometry": {"coordinates":[-75.909392,43.974518],"type":"Point"}
}