{
  "type": "Feature",
  "properties": {
    "iso:country":"US",
    "name:eng_x_preferred":[
        "50 St"
    ],
    "wof:name":"50 St",
    "wof:placetype":"venue"
},
  "geometry": {"coordinates":[-73.99479100000001,40.63626],"type":"Point"}
}