{
  "type": "Feature",
  "properties": {
    "iso:country":"US",
    "sg:address":"1465 Geneva Loop Apt 9G",
    "sg:city":"Brooklyn",
    "sg:classifiers":[
        {
            "category":"Autos & Motor Vehicles",
            "subcategory":"Auto Supplies",
            "type":"Retail Goods"
        },
        {
            "category":"Utilities",
            "subcategory":"Telephone",
            "type":"Services"
        },
        {
            "category":"Retail",
            "subcategory":"Auto Repair",
            "type":"Services"
        }
    ],
    "sg:phone":"+1 718 942 0551",
    "sg:postcode":"11239",
    "sg:province":"NY",
    "sg:tags":[
        "automobile",
        "stereo",
        "radio",
        "system",
        "equipment"
    ],
    "wof:name":"G H Group",
    "wof:placetype":"venue"
},
  "geometry": {"coordinates":[-73.87979199999999,40.64621],"type":"Point"}
}