{
  "type": "Feature",
  "properties": {
    "addr:full":"100 Nassau Terminal Rd New Hyde Park NY 11040",
    "addr:housenumber":"100",
    "addr:postcode":"11040",
    "addr:street":"Terminal Rd",
    "iso:country":"US",
    "sg:address":"100 Nassau Terminal Rd",
    "sg:city":"New Hyde Park",
    "sg:classifiers":[
        {
            "category":"Freight",
            "type":"Transportation"
        }
    ],
    "sg:phone":"+1   ",
    "sg:postcode":"11040",
    "sg:province":"NY",
    "sg:tags":[
        "warehouse"
    ],
    "wof:name":"Ergonomic Group Inc",
    "wof:placetype":"venue"
},
  "geometry": {"coordinates":[-73.67402300000001,40.73371],"type":"Point"}
}