{
  "type": "Feature",
  "properties": {
    "addr:full":"1497 Myrtle Ave Brooklyn NY 11237",
    "addr:housenumber":"1497",
    "addr:postcode":"11237",
    "addr:street":"Myrtle Ave",
    "iso:country":"US",
    "sg:address":"1497 Myrtle Ave",
    "sg:city":"Brooklyn",
    "sg:classifiers":[
        {
            "category":"Real Estate",
            "subcategory":"Real Estate Agent",
            "type":"Services"
        }
    ],
    "sg:phone":"+1 718 497 0166",
    "sg:postcode":"11237",
    "sg:province":"NY",
    "wof:name":"Financial Success",
    "wof:placetype":"venue"
},
  "geometry": {"coordinates":[-73.915228,40.699198],"type":"Point"}
}