{
  "type": "Feature",
  "properties": {
    "iso:country":"US",
    "sg:address":"315 Lake Ave S",
    "sg:city":"Nesconset",
    "sg:classifiers":[
        {
            "category":"Real Estate",
            "subcategory":"Real Estate Agent",
            "type":"Services"
        }
    ],
    "sg:phone":"+1 631 724 4944",
    "sg:postcode":"11767",
    "sg:province":"NY",
    "sg:tags":[
        "inspection"
    ],
    "wof:name":"JSB Inc",
    "wof:placetype":"venue"
},
  "geometry": {"coordinates":[-73.151971,40.841978],"type":"Point"}
}