{
  "type": "Feature",
  "properties": {
    "iso:country":"US",
    "sg:address":"110 Walker Valley Rd",
    "sg:city":"Pine Bush",
    "sg:classifiers":[
        {
            "category":"Building & Trades",
            "subcategory":"Construction",
            "type":"Services"
        }
    ],
    "sg:phone":"+1 845 733 1785",
    "sg:postcode":"12566",
    "sg:province":"NY",
    "sg:tags":[
        "contractor"
    ],
    "wof:name":"Star Drywall",
    "wof:placetype":"venue"
},
  "geometry": {"coordinates":[-74.38265199999999,41.596559],"type":"Point"}
}