{
  "type": "Feature",
  "properties": {
    "iso:country":"US",
    "sg:address":"449 Champlain St",
    "sg:city":"Rochester",
    "sg:classifiers":[
        {
            "category":"Organizations",
            "subcategory":"Religious Organization",
            "type":"Services"
        }
    ],
    "sg:phone":"+1 585 235 4940",
    "sg:postcode":"14611",
    "sg:province":"NY",
    "sg:tags":[
        "clergy"
    ],
    "wof:name":"Carl D Nelson",
    "wof:placetype":"venue"
},
  "geometry": {"coordinates":[-77.63016,43.144682],"type":"Point"}
}