{
  "type": "Feature",
  "properties": {
    "addr:full":"480 E Utica St Buffalo NY 14208",
    "addr:housenumber":"480",
    "addr:postcode":"14208",
    "addr:street":"E Utica St",
    "iso:country":"US",
    "sg:address":"480 E Utica St",
    "sg:city":"Buffalo",
    "sg:classifiers":[
        {
            "category":"Organizations",
            "subcategory":"Religious Organization",
            "type":"Services"
        }
    ],
    "sg:phone":"+1 716 882 1356",
    "sg:postcode":"14208",
    "sg:province":"NY",
    "sg:tags":[
        "church"
    ],
    "wof:name":"White Rock Baptist Church",
    "wof:placetype":"venue"
},
  "geometry": {"coordinates":[-78.846805,42.911114],"type":"Point"}
}