{
  "type": "Feature",
  "properties": {
    "addr:full":"181 Gotham Ave Elmont NY 11003",
    "addr:housenumber":"181",
    "addr:postcode":"11003",
    "addr:street":"Gotham Ave",
    "iso:country":"US",
    "sg:address":"181 Gotham Ave",
    "sg:city":"Elmont",
    "sg:classifiers":[
        {
            "category":"Education",
            "subcategory":"School",
            "type":"Public Place"
        }
    ],
    "sg:phone":"+1 516 326 5540",
    "sg:postcode":"11003",
    "sg:province":"NY",
    "sg:website":"www.elmontschools.org",
    "wof:name":"Gotham Avenue School",
    "wof:placetype":"venue"
},
  "geometry": {"coordinates":[-73.71666500000001,40.704801],"type":"Point"}
}