{
  "type": "Feature",
  "properties": {
    "addr:full":"1200 E Jericho Tpke Huntington NY 11743",
    "addr:housenumber":"1200",
    "addr:postcode":"11743",
    "addr:street":"E Jericho Tpke",
    "iso:country":"US",
    "sg:address":"1200 E Jericho Tpke",
    "sg:city":"Huntington",
    "sg:classifiers":[
        {
            "category":"Bakery",
            "type":"Food & Drink"
        }
    ],
    "sg:menulink":"http://www.allmenus.com/ny/huntington/232823-a--g-bakery/menu/",
    "sg:phone":"+1 631 271 3450",
    "sg:postcode":"11743",
    "sg:province":"NY",
    "sg:tags":[
        "american",
        "pastry"
    ],
    "wof:name":"A & G Bakery",
    "wof:placetype":"venue"
},
  "geometry": {"coordinates":[-73.363924,40.833018],"type":"Point"}
}