{
  "type": "Feature",
  "properties": {
    "addr:full":"158 Dahlia St Schenectady NY 12306",
    "addr:housenumber":"158",
    "addr:postcode":"12306",
    "addr:street":"Dahlia St",
    "iso:country":"US",
    "sg:address":"158 Dahlia St",
    "sg:city":"Schenectady",
    "sg:classifiers":[
        {
            "category":"Professional",
            "subcategory":"Business Services",
            "type":"Services"
        }
    ],
    "sg:phone":"+1 518 346 6428",
    "sg:postcode":"12306",
    "sg:province":"NY",
    "sg:tags":[
        "retail",
        "novelty"
    ],
    "wof:name":"Brown Mark",
    "wof:placetype":"venue"
},
  "geometry": {"coordinates":[-73.976964,42.775571],"type":"Point"}
}