{
  "type": "Feature",
  "properties": {
    "addr:full":"8113 Dexter Pkwy Baldwinsville NY 13027",
    "addr:housenumber":"8113",
    "addr:postcode":"13027",
    "addr:street":"Dexter Pkwy",
    "iso:country":"US",
    "sg:address":"8113 Dexter Pkwy",
    "sg:city":"Baldwinsville",
    "sg:classifiers":[
        {
            "category":"Restaurant",
            "type":"Food & Drink"
        }
    ],
    "sg:phone":"+1 315 635 5133",
    "sg:postcode":"13027",
    "sg:province":"NY",
    "sg:tags":[
        "italian"
    ],
    "wof:name":"Tassone's Wine Garden Inc",
    "wof:placetype":"venue"
},
  "geometry": {"coordinates":[-76.34828899999999,43.165024],"type":"Point"}
}