{
  "type": "Feature",
  "properties": {
    "addr:full":"1274 49th St Brooklyn NY 11219",
    "addr:housenumber":"1274",
    "addr:postcode":"11219",
    "addr:street":"49Th St",
    "iso:country":"US",
    "sg:address":"1274 49th St",
    "sg:city":"Brooklyn",
    "sg:classifiers":[
        {
            "category":"Building & Trades",
            "subcategory":"Construction",
            "type":"Services"
        }
    ],
    "sg:phone":"+1 718 599 7084",
    "sg:postcode":"11219",
    "sg:province":"NY",
    "sg:tags":[
        "contractor"
    ],
    "wof:name":"C & F Construction Inc",
    "wof:placetype":"venue"
},
  "geometry": {"coordinates":[-73.993426,40.635969],"type":"Point"}
}