{
  "type": "Feature",
  "properties": {
    "iso:country":"US",
    "sg:address":"199 Gypsy Trail Rd",
    "sg:city":"Carmel",
    "sg:classifiers":[
        {
            "category":"Recreation",
            "type":"Entertainment"
        }
    ],
    "sg:phone":"+1 845 225 3650",
    "sg:postcode":"10512",
    "sg:province":"NY",
    "sg:tags":[
        "parks"
    ],
    "wof:name":"Putnam County Parks Dept",
    "wof:placetype":"venue"
},
  "geometry": {"coordinates":[-73.724177,41.489223],"type":"Point"}
}