{
  "type": "Feature",
  "properties": {
    "iso:country":"US",
    "sg:address":"477 7th Ave",
    "sg:city":"Brooklyn",
    "sg:classifiers":[
        {
            "category":"Home & Garden",
            "subcategory":"Home Furnishings",
            "type":"Retail Goods"
        }
    ],
    "sg:phone":"+1 718 768 2286",
    "sg:postcode":"11215",
    "sg:province":"NY",
    "sg:tags":[
        "building",
        "bath",
        "maintenance",
        "kitchen"
    ],
    "wof:name":"Kazmack Venetian Blind Mfg Co",
    "wof:placetype":"venue"
},
  "geometry": {"coordinates":[-73.98539700000001,40.662102],"type":"Point"}
}