{
  "type": "Feature",
  "properties": {
    "iso:country":"US",
    "sg:address":"11 Roman Ln",
    "sg:city":"Buffalo",
    "sg:classifiers":[
        {
            "category":"Shopping",
            "subcategory":"Computers & Home Electronics",
            "type":"Retail Goods"
        }
    ],
    "sg:phone":"+1   ",
    "sg:postcode":"14226",
    "sg:province":"NY",
    "wof:name":"Spectrum Sound & Lighting",
    "wof:placetype":"venue"
},
  "geometry": {"coordinates":[-78.796249,42.974786],"type":"Point"}
}