{
  "type": "Feature",
  "properties": {
    "addr:full":"239 E Kingsbridge Road Bronx NY 10458",
    "addr:housenumber":"239",
    "addr:postcode":"10458",
    "addr:street":"E Kingsbridge Road",
    "iso:country":"US",
    "sg:address":"239 E Kingsbridge Road",
    "sg:city":"Bronx",
    "sg:classifiers":[
        {
            "category":"Food & Beverages",
            "subcategory":"Groceries & Convenience Stores",
            "type":"Retail Goods"
        }
    ],
    "sg:phone":"+1 718 365 1990",
    "sg:postcode":"10458",
    "sg:province":"NY",
    "wof:name":"Medina Grocery",
    "wof:placetype":"venue"
},
  "geometry": {"coordinates":[-73.89387499999999,40.865116],"type":"Point"}
}