{
  "type": "Feature",
  "properties": {
    "addr:full":"3502 Clinton St Buffalo NY 14224",
    "addr:housenumber":"3502",
    "addr:postcode":"14224",
    "addr:street":"Clinton St",
    "iso:country":"US",
    "sg:address":"3502 Clinton St",
    "sg:city":"Buffalo",
    "sg:classifiers":[
        {
            "category":"Food & Beverages",
            "subcategory":"Groceries & Convenience Stores",
            "type":"Retail Goods"
        }
    ],
    "sg:phone":"+1 716 668 3100",
    "sg:postcode":"14224",
    "sg:province":"NY",
    "wof:name":"Unionmart",
    "wof:placetype":"venue"
},
  "geometry": {"coordinates":[-78.754677,42.855141],"type":"Point"}
}