{
  "type": "Feature",
  "properties": {
    "iso:country":"US",
    "sg:address":"10754 Alleghany Rd",
    "sg:city":"Darien Center",
    "sg:classifiers":[
        {
            "category":"Food & Beverages",
            "subcategory":"Groceries & Convenience Stores",
            "type":"Retail Goods"
        }
    ],
    "sg:phone":"+1   ",
    "sg:postcode":"14040",
    "sg:province":"NY",
    "wof:name":"Lorettas Red & White Store",
    "wof:placetype":"venue"
},
  "geometry": {"coordinates":[-78.388678,42.893136],"type":"Point"}
}