{
  "type": "Feature",
  "properties": {
    "addr:full":"5 W Main St Elmsford NY 10523",
    "addr:housenumber":"5",
    "addr:postcode":"10523",
    "addr:street":"W Main St",
    "iso:country":"US",
    "sg:address":"5 W Main St",
    "sg:city":"Elmsford",
    "sg:classifiers":[
        {
            "category":"Professional",
            "subcategory":"Advertising",
            "type":"Services"
        }
    ],
    "sg:phone":"+1 914 347 2200",
    "sg:postcode":"10523",
    "sg:province":"NY",
    "sg:tags":[
        "sampling",
        "market",
        "research"
    ],
    "wof:name":"Value Package",
    "wof:placetype":"venue"
},
  "geometry": {"coordinates":[-73.81986499999999,41.054932],"type":"Point"}
}