{
  "type": "Feature",
  "properties": {
    "addr:full":"476 Maple St Big Flats NY 14814",
    "addr:housenumber":"476",
    "addr:postcode":"14814",
    "addr:street":"Maple St",
    "iso:country":"US",
    "sg:address":"476 Maple St",
    "sg:city":"Big Flats",
    "sg:classifiers":[
        {
            "category":"Government",
            "subcategory":"Office",
            "type":"Public Place"
        }
    ],
    "sg:phone":"+1 607 562 8012",
    "sg:postcode":"14814",
    "sg:province":"NY",
    "sg:tags":[
        "department",
        "highway"
    ],
    "wof:name":"Big Flats Highway Department",
    "wof:placetype":"venue"
},
  "geometry": {"coordinates":[-76.93714799999999,42.141152],"type":"Point"}
}