{
  "type": "Feature",
  "properties": {
    "addr:full":"1414 Hancock St Brooklyn NY 11237",
    "addr:housenumber":"1414",
    "addr:postcode":"11237",
    "addr:street":"Hancock St",
    "iso:country":"US",
    "sg:address":"1414 Hancock St",
    "sg:city":"Brooklyn",
    "sg:classifiers":[
        {
            "category":"Freight",
            "type":"Transportation"
        }
    ],
    "sg:phone":"+1   ",
    "sg:postcode":"11237",
    "sg:province":"NY",
    "sg:tags":[
        "operator",
        "trucking"
    ],
    "wof:name":"Charles McNeil",
    "wof:placetype":"venue"
},
  "geometry": {"coordinates":[-73.906582,40.696643],"type":"Point"}
}