{
  "type": "Feature",
  "properties": {
    "addr:full":"455 Madison Ave New York NY 10022",
    "addr:housenumber":"455",
    "addr:postcode":"10022",
    "addr:street":"Madison Ave",
    "iso:country":"US",
    "sg:address":"455 Madison Ave",
    "sg:city":"New York",
    "sg:classifiers":[
        {
            "category":"Bars & Pubs",
            "subcategory":"Lounge",
            "type":"Food & Drink"
        }
    ],
    "sg:phone":"+1 212 303 7757",
    "sg:postcode":"10022",
    "sg:province":"NY",
    "wof:name":"Villard Bar & Lounge",
    "wof:placetype":"venue"
},
  "geometry": {"coordinates":[-73.975098,40.758499],"type":"Point"}
}