{
  "type": "Feature",
  "properties": {
    "iso:country":"US",
    "sg:address":"161 Consaul Rd",
    "sg:city":"Albany",
    "sg:classifiers":[
        {
            "category":"Real Estate",
            "subcategory":"Real Estate Agent",
            "type":"Services"
        }
    ],
    "sg:phone":"+1 518 365 4032",
    "sg:postcode":"12205",
    "sg:province":"NY",
    "wof:name":"Mpc Property Management LLC",
    "wof:placetype":"venue"
},
  "geometry": {"coordinates":[-73.85028800000001,42.74557],"type":"Point"}
}