{
  "type": "Feature",
  "properties": {
    "addr:full":"331 Thomas St Staten Island NY 10306",
    "addr:housenumber":"331",
    "addr:postcode":"10306",
    "addr:street":"Thomas St",
    "iso:country":"US",
    "sg:address":"331 Thomas St",
    "sg:city":"Staten Island",
    "sg:classifiers":[
        {
            "category":"Professional",
            "type":"Services"
        }
    ],
    "sg:phone":"+1 718 987 5406",
    "sg:postcode":"10306",
    "sg:province":"NY",
    "sg:tags":[
        "establishment"
    ],
    "wof:name":"Ladies Only",
    "wof:placetype":"venue"
},
  "geometry": {"coordinates":[-74.14044699999999,40.569627],"type":"Point"}
}