{
  "type": "Feature",
  "properties": {
    "iso:country":"US",
    "sg:address":"444 Livingston Ave",
    "sg:city":"Albany",
    "sg:classifiers":[
        {
            "category":"Professional",
            "subcategory":"Management & Consulting",
            "type":"Services"
        }
    ],
    "sg:phone":"+1 518 449 1235",
    "sg:postcode":"12206",
    "sg:province":"NY",
    "sg:tags":[
        "consultant"
    ],
    "wof:name":"Cha Cole Cabling & Consltng Co",
    "wof:placetype":"venue"
},
  "geometry": {"coordinates":[-73.764015,42.666609],"type":"Point"}
}