{
  "type": "Feature",
  "properties": {
    "addr:full":"177 Mulberry St. New York NY 10013",
    "addr:housenumber":"177",
    "addr:postcode":"10013",
    "addr:street":"Mulberry St.",
    "iso:country":"US",
    "sg:address":"177 Mulberry St.",
    "sg:city":"New York",
    "sg:classifiers":[
        {
            "category":"Restaurant",
            "type":"Food & Drink"
        }
    ],
    "sg:phone":"+1 212 925 8157",
    "sg:postcode":"10013",
    "sg:province":"NY",
    "sg:tags":[
        "french"
    ],
    "wof:name":"Patois",
    "wof:placetype":"venue"
},
  "geometry": {"coordinates":[-73.996844,40.720435],"type":"Point"}
}