{
  "type": "Feature",
  "properties": {
    "iso:country":"US",
    "sg:address":"226 W Fourth St",
    "sg:city":"New York",
    "sg:classifiers":[
        {
            "category":"Personal",
            "subcategory":"Day Spa",
            "type":"Services"
        }
    ],
    "sg:phone":"+1 212 929 0838",
    "sg:postcode":"10014",
    "sg:province":"NY",
    "sg:website":"heymandayspa.com",
    "wof:name":"Hey Man Day Spa",
    "wof:placetype":"venue"
},
  "geometry": {"coordinates":[-74.003145,40.733948],"type":"Point"}
}