{
  "type": "Feature",
  "properties": {
    "iso:country":"US",
    "sg:address":"8505 18th Avenue",
    "sg:city":"Brooklyn",
    "sg:classifiers":[
        {
            "category":"Restaurant",
            "type":"Food & Drink"
        }
    ],
    "sg:phone":"+1 718 234 1435",
    "sg:postcode":"11214",
    "sg:province":"NY",
    "wof:name":"New Dyker Restaurant",
    "wof:placetype":"venue"
},
  "geometry": {"coordinates":[-74.002073,40.607556],"type":"Point"}
}