{
  "type": "Feature",
  "properties": {
    "addr:full":"6 Eastover Dr East Northport NY 11731",
    "addr:housenumber":"6",
    "addr:postcode":"11731",
    "addr:street":"Eastover Dr",
    "iso:country":"US",
    "sg:address":"6 Eastover Dr",
    "sg:city":"East Northport",
    "sg:classifiers":[
        {
            "category":"Professional",
            "type":"Services"
        }
    ],
    "sg:phone":"+1 631 266 3126",
    "sg:postcode":"11731",
    "sg:province":"NY",
    "sg:tags":[
        "establishment"
    ],
    "wof:name":"BAC Inc",
    "wof:placetype":"venue"
},
  "geometry": {"coordinates":[-73.31144500000001,40.85841],"type":"Point"}
}