{
  "type": "Feature",
  "properties": {
    "iso:country":"US",
    "sg:address":"1105 Park Ave",
    "sg:city":"New York",
    "sg:classifiers":[
        {
            "category":"Health Services",
            "subcategory":"Doctor",
            "type":"Services"
        }
    ],
    "sg:phone":"+1 212 860 5400",
    "sg:postcode":"10128",
    "sg:province":"NY",
    "sg:tags":[
        "physician",
        "surgeon",
        "medical"
    ],
    "wof:name":"Samuel Guillory MD",
    "wof:placetype":"venue"
},
  "geometry": {"coordinates":[-73.95535700000001,40.782544],"type":"Point"}
}