{
  "type": "Feature",
  "properties": {
    "iso:country":"US",
    "sg:address":"7775 Kingdom Rd",
    "sg:city":"Baldwinsville",
    "sg:classifiers":[
        {
            "category":"Real Estate",
            "subcategory":"Real Estate Operator",
            "type":"Services"
        }
    ],
    "sg:phone":"+1 315 638 8454",
    "sg:postcode":"13027",
    "sg:province":"NY",
    "sg:tags":[
        "property",
        "lessor"
    ],
    "wof:name":"Toby Johnson",
    "wof:placetype":"venue"
},
  "geometry": {"coordinates":[-76.419877,43.148562],"type":"Point"}
}