{
  "type": "Feature",
  "properties": {
    "addr:full":"133-31 39th Ave Flushing Mall Flushing NY 11354",
    "addr:housenumber":"133-31",
    "addr:postcode":"11354",
    "addr:street":"39Th Ave;Mall",
    "iso:country":"US",
    "sg:address":"133-31 39th Ave Flushing Mall",
    "sg:city":"Flushing",
    "sg:classifiers":[
        {
            "category":"Food & Beverages",
            "subcategory":"Candy",
            "type":"Retail Goods"
        },
        {
            "category":"Food Court",
            "type":"Food & Drink"
        }
    ],
    "sg:postcode":"11354",
    "sg:province":"NY",
    "sg:tags":[
        "dessert",
        "stand"
    ],
    "wof:name":"Deli Manjoo",
    "wof:placetype":"venue"
},
  "geometry": {"coordinates":[-73.82959099999999,40.760389],"type":"Point"}
}