{
  "type": "Feature",
  "properties": {
    "addr:full":"626 Avenue U Brooklyn NY 11223",
    "addr:housenumber":"626",
    "addr:postcode":"11223",
    "addr:street":"Avenue U",
    "iso:country":"US",
    "sg:address":"626 Avenue U",
    "sg:city":"Brooklyn",
    "sg:classifiers":[
        {
            "category":"Banks & Credit Unions",
            "subcategory":"Financial Services",
            "type":"Services"
        }
    ],
    "sg:phone":"+1 718 336 4657",
    "sg:postcode":"11223",
    "sg:province":"NY",
    "sg:tags":[
        "broker",
        "mortgage"
    ],
    "wof:name":"Great Liberty Funding",
    "wof:placetype":"venue"
},
  "geometry": {"coordinates":[-73.964333,40.597845],"type":"Point"}
}