{
  "type": "Feature",
  "properties": {
    "addr:full":"509 Ralph Ave Brooklyn NY 11233",
    "addr:housenumber":"509",
    "addr:postcode":"11233",
    "addr:street":"Ralph Ave",
    "iso:country":"US",
    "sg:address":"509 Ralph Ave",
    "sg:city":"Brooklyn",
    "sg:classifiers":[
        {
            "category":"Shopping",
            "subcategory":"Pharmacy",
            "type":"Retail Goods"
        }
    ],
    "sg:phone":"+1 718 493 0288",
    "sg:postcode":"11233",
    "sg:province":"NY",
    "sg:tags":[
        "drugstore"
    ],
    "wof:name":"Gulshan Pharmacy Inc",
    "wof:placetype":"venue"
},
  "geometry": {"coordinates":[-73.922096,40.6721],"type":"Point"}
}