{
  "type": "Feature",
  "properties": {
    "addr:full":"35 Laurel Rd East Northport NY 11731",
    "addr:housenumber":"35",
    "addr:postcode":"11731",
    "addr:street":"Laurel Rd",
    "iso:country":"US",
    "sg:address":"35 Laurel Rd",
    "sg:city":"East Northport",
    "sg:classifiers":[
        {
            "category":"Banks & Credit Unions",
            "subcategory":"Bank",
            "type":"Services"
        }
    ],
    "sg:phone":"+1 631 261 1800",
    "sg:postcode":"11731",
    "sg:province":"NY",
    "sg:tags":[
        "loan",
        "mortgage",
        "real estate"
    ],
    "wof:name":"Genesis National Mortgage Corp",
    "wof:placetype":"venue"
},
  "geometry": {"coordinates":[-73.32615800000001,40.88241],"type":"Point"}
}