{
  "type": "Feature",
  "properties": {
    "addr:full":"13338 41st Road Flushing NY 11355",
    "addr:housenumber":"13338",
    "addr:postcode":"11355",
    "addr:street":"41St Road",
    "iso:country":"US",
    "sg:address":"13338 41st Road",
    "sg:city":"Flushing",
    "sg:classifiers":[
        {
            "category":"Shopping",
            "subcategory":"Pharmacy",
            "type":"Retail Goods"
        }
    ],
    "sg:phone":"+1 718 762 2883",
    "sg:postcode":"11355",
    "sg:province":"NY",
    "sg:tags":[
        "drugstore"
    ],
    "wof:name":"Merlin Drug",
    "wof:placetype":"venue"
},
  "geometry": {"coordinates":[-73.8304,40.756773],"type":"Point"}
}