{
  "type": "Feature",
  "properties": {
    "addr:full":"1580 Watson Ave Bronx NY 10472",
    "addr:housenumber":"1580",
    "addr:postcode":"10472",
    "addr:street":"Watson Ave",
    "iso:country":"US",
    "sg:address":"1580 Watson Ave",
    "sg:city":"Bronx",
    "sg:classifiers":[
        {
            "category":"Food & Beverages",
            "subcategory":"Groceries & Convenience Stores",
            "type":"Retail Goods"
        }
    ],
    "sg:phone":"+1 718 860 1086",
    "sg:postcode":"10472",
    "sg:province":"NY",
    "sg:tags":[
        "grocer"
    ],
    "wof:name":"Stop One Grocery",
    "wof:placetype":"venue"
},
  "geometry": {"coordinates":[-73.87672499999999,40.826277],"type":"Point"}
}