{
  "type": "Feature",
  "properties": {
    "iso:country":"US",
    "sg:address":"408 43rd St",
    "sg:city":"Copiague",
    "sg:classifiers":[
        {
            "category":"Professional",
            "subcategory":"Lawyer & Legal Services",
            "type":"Services"
        }
    ],
    "sg:phone":"+1 631 842 3100",
    "sg:postcode":"11726",
    "sg:province":"NY",
    "wof:name":"J & A Med Billing Collections",
    "wof:placetype":"venue"
},
  "geometry": {"coordinates":[-73.39518700000001,40.697609],"type":"Point"}
}