{
  "type": "Feature",
  "properties": {
    "addr:full":"1440 Old Country Road Riverhead NY 11901",
    "addr:housenumber":"1440",
    "addr:postcode":"11901",
    "addr:street":"Old Country Road",
    "iso:country":"US",
    "sg:address":"1440 Old Country Road",
    "sg:city":"Riverhead",
    "sg:classifiers":[
        {
            "category":"Home & Garden",
            "subcategory":"Carpets & Floor Coverings",
            "type":"Retail Goods"
        }
    ],
    "sg:phone":"+1 631 369 4297",
    "sg:postcode":"11901",
    "sg:province":"NY",
    "sg:tags":[
        "mattress"
    ],
    "sg:website":"www.sleepys.com/",
    "wof:name":"Sleepy's, The Mattress Professionals",
    "wof:placetype":"venue"
},
  "geometry": {"coordinates":[-72.70876,40.92365],"type":"Point"}
}