{
  "type": "Feature",
  "properties": {
    "iso:country":"US",
    "sg:address":"2122 Eggert Rd Ste 2",
    "sg:city":"Buffalo",
    "sg:classifiers":[
        {
            "category":"Wholesale",
            "subcategory":"Medical Equipment & Supplies",
            "type":"Manufacturing & Wholesale Goods"
        }
    ],
    "sg:phone":"+1 716 833 4488",
    "sg:postcode":"14226",
    "sg:province":"NY",
    "sg:tags":[
        "assistive",
        "aid",
        "device",
        "hearing"
    ],
    "wof:name":"Hearing Evaluation Svces Of Buffalo Inc",
    "wof:placetype":"venue"
},
  "geometry": {"coordinates":[-78.821156,42.979189],"type":"Point"}
}