{
  "type": "Feature",
  "properties": {
    "iso:country":"US",
    "sg:address":"88 University Pl",
    "sg:city":"New York",
    "sg:classifiers":[
        {
            "category":"Health Services",
            "subcategory":"Health Practitioner",
            "type":"Services"
        }
    ],
    "sg:phone":"+1 212 463 8519",
    "sg:postcode":"10003",
    "sg:province":"NY",
    "sg:tags":[
        "psychologist"
    ],
    "wof:name":"Emily Kuriloff",
    "wof:placetype":"venue"
},
  "geometry": {"coordinates":[-73.993055,40.733654],"type":"Point"}
}