{
  "type": "Feature",
  "properties": {
    "iso:country":"US",
    "sg:address":"1456 Independence Dr",
    "sg:city":"Derby",
    "sg:classifiers":[
        {
            "category":"Professional",
            "subcategory":"Business Services",
            "type":"Services"
        }
    ],
    "sg:phone":"+1 716 947 5234",
    "sg:postcode":"14047",
    "sg:province":"NY",
    "sg:tags":[
        "paralegal"
    ],
    "wof:name":"Hart Paralegal Assistance",
    "wof:placetype":"venue"
},
  "geometry": {"coordinates":[-78.98488399999999,42.702557],"type":"Point"}
}