{
  "type": "Feature",
  "properties": {
    "addr:full":"155 6 Ave New York NY 10013",
    "addr:housenumber":"155",
    "addr:postcode":"10013",
    "addr:street":"6 Ave",
    "iso:country":"US",
    "sg:address":"155 6 Ave",
    "sg:city":"New York",
    "sg:classifiers":[
        {
            "category":"Building & Trades",
            "subcategory":"Construction",
            "type":"Services"
        }
    ],
    "sg:phone":"+1 212 219 8822",
    "sg:postcode":"10013",
    "sg:province":"NY",
    "sg:tags":[
        "hanging",
        "contractor"
    ],
    "wof:name":"Elizabeth Dow Ltd",
    "wof:placetype":"venue"
},
  "geometry": {"coordinates":[-74.005109,40.719699],"type":"Point"}
}