{
  "type": "Feature",
  "properties": {
    "addr:full":"1109 Burke Ave Bronx NY 10469",
    "addr:housenumber":"1109",
    "addr:postcode":"10469",
    "addr:street":"Burke Ave",
    "iso:country":"US",
    "sg:address":"1109 Burke Ave",
    "sg:city":"Bronx",
    "sg:classifiers":[
        {
            "category":"Shopping",
            "subcategory":"Department Store",
            "type":"Retail Goods"
        }
    ],
    "sg:phone":"+1 718 652 3880",
    "sg:postcode":"10469",
    "sg:province":"NY",
    "sg:tags":[
        "shop"
    ],
    "wof:name":"Discount & Variety",
    "wof:placetype":"venue"
},
  "geometry": {"coordinates":[-73.854905,40.871289],"type":"Point"}
}