{
  "type": "Feature",
  "properties": {
    "iso:country":"US",
    "sg:address":"130 West 57th Street Suite 5A",
    "sg:city":"New York",
    "sg:classifiers":[
        {
            "category":"Professional",
            "subcategory":"Art Services",
            "type":"Services"
        }
    ],
    "sg:phone":"+1 212 741 6427",
    "sg:postcode":"10019",
    "sg:province":"NY",
    "sg:tags":[
        "photographer"
    ],
    "sg:website":"www.fifthavenuedigital.com/",
    "wof:name":"Fifth Avenue Digital",
    "wof:placetype":"venue"
},
  "geometry": {"coordinates":[-73.978629,40.764931],"type":"Point"}
}