{
  "type": "Feature",
  "properties": {
    "addr:full":"2610 E 18th St Ste 10 Brooklyn NY 11235",
    "addr:housenumber":"2610;10",
    "addr:postcode":"11235",
    "addr:street":"E 18Th St Ste",
    "iso:country":"US",
    "sg:address":"2610 E 18th St Ste 10",
    "sg:city":"Brooklyn",
    "sg:classifiers":[
        {
            "category":"Health Services",
            "subcategory":"Nursing And Care Facility",
            "type":"Services"
        },
        {
            "category":"Health Services",
            "subcategory":"Health Practitioner",
            "type":"Services"
        }
    ],
    "sg:phone":"+1 718 743 0960",
    "sg:postcode":"11235",
    "sg:province":"NY",
    "sg:tags":[
        "home",
        "eldercare-home"
    ],
    "wof:name":"Healthy Start Home Care A",
    "wof:placetype":"venue"
},
  "geometry": {"coordinates":[-73.951454,40.588056],"type":"Point"}
}