{
  "type": "Feature",
  "properties": {
    "addr:full":"845 1 Ave New York NY 10017",
    "addr:housenumber":"845",
    "addr:postcode":"10017",
    "addr:street":"1 Ave",
    "iso:country":"US",
    "sg:address":"845 1 Ave",
    "sg:city":"New York",
    "sg:classifiers":[
        {
            "category":"Parking",
            "type":"Transportation"
        }
    ],
    "sg:phone":"+1 212 813 0014",
    "sg:postcode":"10017",
    "sg:province":"NY",
    "sg:tags":[
        "garage"
    ],
    "wof:name":"Imperial",
    "wof:placetype":"venue"
},
  "geometry": {"coordinates":[-73.966616,40.753243],"type":"Point"}
}