{
  "type": "Feature",
  "properties": {
    "iso:country":"US",
    "sg:address":"89 W Bayberry Rd",
    "sg:city":"Islip",
    "sg:classifiers":[
        {
            "category":"Building & Trades",
            "subcategory":"Construction",
            "type":"Services"
        }
    ],
    "sg:phone":"+1 631 581 7456",
    "sg:postcode":"11751",
    "sg:province":"NY",
    "sg:tags":[
        "house"
    ],
    "wof:name":"Wildflower Construction",
    "wof:placetype":"venue"
},
  "geometry": {"coordinates":[-73.222696,40.711248],"type":"Point"}
}