{
  "type": "Feature",
  "properties": {
    "iso:country":"US",
    "sg:address":"201 N Union St",
    "sg:city":"Olean",
    "sg:classifiers":[
        {
            "category":"Professional",
            "subcategory":"Accounting & Tax Preparation",
            "type":"Services"
        }
    ],
    "sg:phone":"+1 716 375 5235",
    "sg:postcode":"14760",
    "sg:province":"NY",
    "sg:tags":[
        "bookkeeping",
        "general"
    ],
    "wof:name":"N H Accounting",
    "wof:placetype":"venue"
},
  "geometry": {"coordinates":[-78.429886,42.080026],"type":"Point"}
}