{
  "type": "Feature",
  "properties": {
    "iso:country":"US",
    "sg:address":"10 Rockefeller Plz",
    "sg:city":"New York",
    "sg:classifiers":[
        {
            "category":"Professional",
            "subcategory":"Management & Consulting",
            "type":"Services"
        }
    ],
    "sg:phone":"+1 212 956 5900",
    "sg:postcode":"10020",
    "sg:province":"NY",
    "sg:tags":[
        "public",
        "relations"
    ],
    "sg:website":"www.adams-pr.com",
    "wof:name":"Adams Unlimited",
    "wof:placetype":"venue"
},
  "geometry": {"coordinates":[-73.979129,40.758194],"type":"Point"}
}