{
  "type": "Feature",
  "properties": {
    "iso:country":"US",
    "sg:address":"345 7th Ave Fl 21",
    "sg:city":"New York",
    "sg:classifiers":[
        {
            "category":"Real Estate",
            "subcategory":"Real Estate Services",
            "type":"Services"
        }
    ],
    "sg:phone":"+1 212 268 0494",
    "sg:postcode":"10001",
    "sg:province":"NY",
    "sg:tags":[
        "management",
        "property"
    ],
    "wof:name":"Sandberg Management Corp",
    "wof:placetype":"venue"
},
  "geometry": {"coordinates":[-73.99279799999999,40.748001],"type":"Point"}
}