{
  "type": "Feature",
  "properties": {
    "addr:full":"74 E 79th St Apt 1C New York NY 10075",
    "addr:housenumber":"74",
    "addr:postcode":"10075",
    "addr:street":"E 79Th St Apt 1C",
    "iso:country":"US",
    "sg:address":"74 E 79th St Apt 1C",
    "sg:city":"New York",
    "sg:classifiers":[
        {
            "category":"Health Services",
            "subcategory":"Doctor",
            "type":"Services"
        }
    ],
    "sg:phone":"+1 212 988 1700",
    "sg:postcode":"10075",
    "sg:province":"NY",
    "wof:name":"Kesselman R Donna MD",
    "wof:placetype":"venue"
},
  "geometry": {"coordinates":[-73.961175,40.7756],"type":"Point"}
}