{
  "type": "Feature",
  "properties": {
    "addr:full":"4870 Broadway Depew NY 14043",
    "addr:housenumber":"4870",
    "addr:postcode":"14043",
    "addr:street":"Broadway",
    "iso:country":"US",
    "sg:address":"4870 Broadway",
    "sg:city":"Depew",
    "sg:classifiers":[
        {
            "category":"Restaurant",
            "type":"Food & Drink"
        }
    ],
    "sg:phone":"+1 716 683 9248",
    "sg:postcode":"14043",
    "sg:province":"NY",
    "sg:tags":[
        "style",
        "family"
    ],
    "wof:name":"Fifties Diner",
    "wof:placetype":"venue"
},
  "geometry": {"coordinates":[-78.694688,42.901829],"type":"Point"}
}