{
  "type": "Feature",
  "properties": {
    "iso:country":"US",
    "sg:address":"25-10 Bridge Plz S",
    "sg:city":"Long Island City",
    "sg:classifiers":[
        {
            "category":"Restaurant",
            "type":"Food & Drink"
        }
    ],
    "sg:phone":"+1 718 729 5428",
    "sg:postcode":"11101",
    "sg:province":"NY",
    "wof:name":"Sunny's Restaurant",
    "wof:placetype":"venue"
},
  "geometry": {"coordinates":[-73.94044700000001,40.751062],"type":"Point"}
}