{
  "type": "Feature",
  "properties": {
    "iso:country":"US",
    "sg:address":"3763 Delaware Ave",
    "sg:city":"Buffalo",
    "sg:classifiers":[
        {
            "category":"Shopping",
            "subcategory":"Florist",
            "type":"Retail Goods"
        }
    ],
    "sg:phone":"+1   ",
    "sg:postcode":"14217",
    "sg:province":"NY",
    "wof:name":"Wean Florist",
    "wof:placetype":"venue"
},
  "geometry": {"coordinates":[-78.87334199999999,42.988579],"type":"Point"}
}