{
  "type": "Feature",
  "properties": {
    "addr:full":"264 6th Ave Brooklyn NY 11215",
    "addr:housenumber":"264",
    "addr:postcode":"11215",
    "addr:street":"6Th Ave",
    "iso:country":"US",
    "sg:address":"264 6th Ave",
    "sg:city":"Brooklyn",
    "sg:classifiers":[
        {
            "category":"Real Estate",
            "subcategory":"Real Estate Agent",
            "type":"Services"
        }
    ],
    "sg:phone":"+1 718 788 6515",
    "sg:postcode":"11215",
    "sg:province":"NY",
    "sg:tags":[
        "report",
        "information"
    ],
    "wof:name":"Oak Tree Management Corp",
    "wof:placetype":"venue"
},
  "geometry": {"coordinates":[-73.979885,40.673049],"type":"Point"}
}