{
  "type": "Feature",
  "properties": {
    "addr:full":"5660 Sunrise Hwy Sayville NY 11782",
    "addr:housenumber":"5660",
    "addr:postcode":"11782",
    "addr:street":"Sunrise Hwy",
    "iso:country":"US",
    "sg:address":"5660 Sunrise Hwy",
    "sg:city":"Sayville",
    "sg:classifiers":[
        {
            "category":"Sports & Exercise",
            "subcategory":"Bowling",
            "type":"Entertainment"
        }
    ],
    "sg:phone":"+1   ",
    "sg:postcode":"11782",
    "sg:province":"NY",
    "sg:tags":[
        "drinking",
        "center"
    ],
    "wof:name":"AMF",
    "wof:placetype":"venue"
},
  "geometry": {"coordinates":[-73.072872,40.767141],"type":"Point"}
}