{
  "type": "Feature",
  "properties": {
    "addr:full":"405 91st St Brooklyn NY 11209",
    "addr:housenumber":"405",
    "addr:postcode":"11209",
    "addr:street":"91St St",
    "iso:country":"US",
    "sg:address":"405 91st St",
    "sg:city":"Brooklyn",
    "sg:classifiers":[
        {
            "category":"Cemetery",
            "type":"Public Place"
        },
        {
            "category":"Retail",
            "subcategory":"Funeral Services",
            "type":"Services"
        }
    ],
    "sg:phone":"+1 718 238 7200",
    "sg:postcode":"11209",
    "sg:province":"NY",
    "sg:tags":[
        "director",
        "embalmer",
        "crematory"
    ],
    "wof:name":"Ridge Chapels Inc",
    "wof:placetype":"venue"
},
  "geometry": {"coordinates":[-74.029792,40.619137],"type":"Point"}
}