{
  "type": "Feature",
  "properties": {
    "iso:country":"US",
    "sg:address":"59 Graham Ave",
    "sg:city":"Brooklyn",
    "sg:classifiers":[
        {
            "category":"Shopping",
            "subcategory":"Computers & Home Electronics",
            "type":"Retail Goods"
        }
    ],
    "sg:phone":"+1 718 302 6661",
    "sg:postcode":"11206",
    "sg:province":"NY",
    "sg:tags":[
        "game",
        "video"
    ],
    "wof:name":"Game City",
    "wof:placetype":"venue"
},
  "geometry": {"coordinates":[-73.942611,40.703145],"type":"Point"}
}