{
  "type": "Feature",
  "properties": {
    "addr:full":"2500 Victory Blvd Staten Island NY 10314",
    "addr:housenumber":"2500",
    "addr:postcode":"10314",
    "addr:street":"Victory Blvd",
    "iso:country":"US",
    "sg:address":"2500 Victory Blvd",
    "sg:city":"Staten Island",
    "sg:classifiers":[
        {
            "category":"Retail",
            "subcategory":"Laundry & Dry Cleaning",
            "type":"Services"
        }
    ],
    "sg:phone":"+1 718 761 8884",
    "sg:postcode":"10314",
    "sg:province":"NY",
    "wof:name":"Magic Touch Cleaners & Shirt Launderers",
    "wof:placetype":"venue"
},
  "geometry": {"coordinates":[-74.1465,40.610199],"type":"Point"}
}