{
  "type": "Feature",
  "properties": {
    "addr:full":"195 Canal St New York NY 10013",
    "addr:housenumber":"195",
    "addr:postcode":"10013",
    "addr:street":"Canal St",
    "iso:country":"US",
    "sg:address":"195 Canal St",
    "sg:city":"New York",
    "sg:classifiers":[
        {
            "category":"Professional",
            "subcategory":"Lawyer & Legal Services",
            "type":"Services"
        }
    ],
    "sg:phone":"+1 212 966 8282",
    "sg:postcode":"10013",
    "sg:province":"NY",
    "wof:name":"Liu Kai Yin Atty",
    "wof:placetype":"venue"
},
  "geometry": {"coordinates":[-73.99839799999999,40.7169],"type":"Point"}
}