{
  "type": "Feature",
  "properties": {
    "addr:full":"430 Burnet Ave Syracuse NY 13203",
    "addr:housenumber":"430",
    "addr:postcode":"13203",
    "addr:street":"Burnet Ave",
    "iso:country":"US",
    "sg:address":"430 Burnet Ave",
    "sg:city":"Syracuse",
    "sg:classifiers":[
        {
            "category":"Manufacturing",
            "subcategory":"Tools & Machinery",
            "type":"Manufacturing & Wholesale Goods"
        }
    ],
    "sg:phone":"+1   ",
    "sg:postcode":"13203",
    "sg:province":"NY",
    "sg:tags":[
        "industrial",
        "mfg"
    ],
    "wof:name":"L & G Machining Inc",
    "wof:placetype":"venue"
},
  "geometry": {"coordinates":[-76.139797,43.052128],"type":"Point"}
}