{
  "type": "Feature",
  "properties": {
    "iso:country":"US",
    "sg:address":"283 Boght Rd",
    "sg:city":"Watervliet",
    "sg:classifiers":[
        {
            "category":"Wholesale",
            "subcategory":"Farm Supplies",
            "type":"Manufacturing & Wholesale Goods"
        }
    ],
    "sg:phone":"+1 518 237 3001",
    "sg:postcode":"12189",
    "sg:province":"NY",
    "sg:tags":[
        "farming"
    ],
    "wof:name":"Cherry Hill Farm",
    "wof:placetype":"venue"
},
  "geometry": {"coordinates":[-73.728075,42.763314],"type":"Point"}
}