{
  "type": "Feature",
  "properties": {
    "addr:full":"105 Kisco Ave Mt Kisco NY 10549",
    "addr:housenumber":"105",
    "addr:postcode":"10549",
    "addr:street":"Kisco Ave Mt Kisco",
    "iso:country":"US",
    "sg:address":"105 Kisco Ave",
    "sg:city":"Mt Kisco",
    "sg:classifiers":[
        {
            "category":"Health Services",
            "subcategory":"Doctor",
            "type":"Services"
        }
    ],
    "sg:phone":"+1 845 278 5400",
    "sg:postcode":"10549",
    "sg:province":"NY",
    "sg:tags":[
        "physician",
        "surgeon"
    ],
    "wof:name":"Womens Medical Assoc",
    "wof:placetype":"venue"
},
  "geometry": {"coordinates":[-73.726162,41.214416],"type":"Point"}
}