{
  "type": "Feature",
  "properties": {
    "addr:full":"384 2 Ave New York NY 10010",
    "addr:housenumber":"384",
    "addr:postcode":"10010",
    "addr:street":"2 Ave",
    "iso:country":"US",
    "sg:address":"384 2 Ave",
    "sg:city":"New York",
    "sg:classifiers":[
        {
            "category":"Restaurant",
            "type":"Food & Drink"
        }
    ],
    "sg:phone":"+1   ",
    "sg:postcode":"10010",
    "sg:province":"NY",
    "sg:tags":[
        "eating"
    ],
    "wof:name":"390 Second Ram Ltd",
    "wof:placetype":"venue"
},
  "geometry": {"coordinates":[-73.981841,40.736602],"type":"Point"}
}