{
  "type": "Feature",
  "properties": {
    "addr:full":"220 Old Country Rd Mineola NY 11501",
    "addr:housenumber":"220",
    "addr:postcode":"11501",
    "addr:street":"Old Country Rd",
    "iso:country":"US",
    "sg:address":"220 Old Country Rd",
    "sg:city":"Mineola",
    "sg:classifiers":[
        {
            "category":"Professional",
            "subcategory":"Lawyer & Legal Services",
            "type":"Services"
        }
    ],
    "sg:phone":"+1 516 742 5600",
    "sg:postcode":"11501",
    "sg:province":"NY",
    "wof:name":"Parson & Wallenstein Atty",
    "wof:placetype":"venue"
},
  "geometry": {"coordinates":[-73.639099,40.746799],"type":"Point"}
}