{
  "type": "Feature",
  "properties": {
    "iso:country":"US",
    "sg:address":"2014 Crompond Rd",
    "sg:city":"Yorktown Heights",
    "sg:classifiers":[
        {
            "category":"Education",
            "subcategory":"School",
            "type":"Public Place"
        },
        {
            "category":"Education",
            "subcategory":"Special Training",
            "type":"Public Place"
        }
    ],
    "sg:phone":"+1 914 962 7222",
    "sg:postcode":"10598",
    "sg:province":"NY",
    "sg:tags":[
        "instruction",
        "music"
    ],
    "wof:name":"Northern Westchester Music Inc",
    "wof:placetype":"venue"
},
  "geometry": {"coordinates":[-73.78417,41.277495],"type":"Point"}
}