{
  "type": "Feature",
  "properties": {
    "iso:country":"US",
    "sg:address":"287 W Merrick Rd",
    "sg:city":"Valley Stream",
    "sg:classifiers":[
        {
            "category":"Wholesale",
            "subcategory":"Home Furnishings",
            "type":"Manufacturing & Wholesale Goods"
        },
        {
            "category":"Home & Garden",
            "subcategory":"Carpets & Floor Coverings",
            "type":"Retail Goods"
        }
    ],
    "sg:phone":"+1 516 872 5005",
    "sg:postcode":"11580",
    "sg:province":"NY",
    "sg:tags":[
        "rug"
    ],
    "wof:name":"Central Carpet Inc",
    "wof:placetype":"venue"
},
  "geometry": {"coordinates":[-73.707565,40.667662],"type":"Point"}
}