{
  "type": "Feature",
  "properties": {
    "addr:full":"936 Exchange St Rochester NY 14608",
    "addr:housenumber":"936",
    "addr:postcode":"14608",
    "addr:street":"Exchange St",
    "iso:country":"US",
    "sg:address":"936 Exchange St",
    "sg:city":"Rochester",
    "sg:classifiers":[
        {
            "category":"Organizations",
            "subcategory":"Non-profit Organization",
            "type":"Services"
        }
    ],
    "sg:phone":"+1 585 328 3380",
    "sg:postcode":"14608",
    "sg:province":"NY",
    "sg:website":"www.foodlinkny.org",
    "wof:name":"Foodlink",
    "wof:placetype":"venue"
},
  "geometry": {"coordinates":[-77.621084,43.138795],"type":"Point"}
}