{
  "type": "Feature",
  "properties": {
    "iso:country":"US",
    "sg:address":"148 Benedict Blvd",
    "sg:city":"Croton On Hudson",
    "sg:classifiers":[
        {
            "category":"Building & Trades",
            "subcategory":"Landscaping Services",
            "type":"Services"
        }
    ],
    "sg:phone":"+1 914 271 4483",
    "sg:postcode":"10520",
    "sg:province":"NY",
    "sg:tags":[
        "designer",
        "landscape"
    ],
    "wof:name":"Alive & Growing",
    "wof:placetype":"venue"
},
  "geometry": {"coordinates":[-73.878597,41.197354],"type":"Point"}
}