{
  "type": "Feature",
  "properties": {
    "iso:country":"US",
    "sg:address":"2858 State Hwy 9",
    "sg:city":"Ballston Spa",
    "sg:classifiers":[
        {
            "category":"Food & Beverages",
            "subcategory":"Groceries & Convenience Stores",
            "type":"Retail Goods"
        }
    ],
    "sg:phone":"+1 518 584 8543",
    "sg:postcode":"12020",
    "sg:province":"NY",
    "sg:tags":[
        "grocer"
    ],
    "wof:name":"De Lucia's Market",
    "wof:placetype":"venue"
},
  "geometry": {"coordinates":[-73.79073099999999,43.01702],"type":"Point"}
}