{
  "type": "Feature",
  "properties": {
    "addr:full":"87-02 Queens Blvd Queens NY 11373",
    "addr:housenumber":"87-02",
    "addr:postcode":"11373",
    "addr:street":"Queens Blvd",
    "iso:country":"US",
    "sg:address":"87-02 Queens Blvd",
    "sg:city":"Queens",
    "sg:classifiers":[
        {
            "category":"Real Estate",
            "subcategory":"Real Estate Services",
            "type":"Services"
        }
    ],
    "sg:phone":"+1 917 445 3999",
    "sg:postcode":"11373",
    "sg:province":"NY",
    "sg:website":"www.whypayrentny.com",
    "wof:name":"Why Pay Rent NY",
    "wof:placetype":"venue"
},
  "geometry": {"coordinates":[-73.876251,40.735252],"type":"Point"}
}