{
  "type": "Feature",
  "properties": {
    "addr:full":"4 Old Neck Ct Manorville NY 11949",
    "addr:housenumber":"4",
    "addr:postcode":"11949",
    "addr:street":"Old Neck Ct",
    "iso:country":"US",
    "sg:address":"4 Old Neck Ct",
    "sg:city":"Manorville",
    "sg:classifiers":[
        {
            "category":"Health Services",
            "subcategory":"Health Practitioner",
            "type":"Services"
        }
    ],
    "sg:phone":"+1 631 874 4443",
    "sg:postcode":"11949",
    "sg:province":"NY",
    "sg:tags":[
        "therapist",
        "physical"
    ],
    "wof:name":"C Gallagher Physical Therapist",
    "wof:placetype":"venue"
},
  "geometry": {"coordinates":[-72.759226,40.83447],"type":"Point"}
}