{
  "type": "Feature",
  "properties": {
    "iso:country":"US",
    "sg:address":"592 3rd Ave",
    "sg:city":"New York",
    "sg:classifiers":[
        {
            "category":"Restaurant",
            "type":"Food & Drink"
        }
    ],
    "sg:menulink":"http://www.allmenus.com/ny/new-york/7678-royal-pizza/menu/",
    "sg:phone":"+1 212 685 3619",
    "sg:postcode":"10016",
    "sg:province":"NY",
    "sg:tags":[
        "american",
        "pizza"
    ],
    "wof:name":"Royal Pizza",
    "wof:placetype":"venue"
},
  "geometry": {"coordinates":[-73.976286,40.748797],"type":"Point"}
}