{
  "type": "Feature",
  "properties": {
    "iso:country":"US",
    "sg:address":"833 Portion Rd",
    "sg:city":"Ronkonkoma",
    "sg:classifiers":[
        {
            "category":"Personal",
            "subcategory":"Beauty Salon",
            "type":"Services"
        }
    ],
    "sg:phone":"+1 631 467 3552",
    "sg:postcode":"11779",
    "sg:province":"NY",
    "sg:tags":[
        "nail",
        "manicuring"
    ],
    "wof:name":"Nina's Advance Nail Inc",
    "wof:placetype":"venue"
},
  "geometry": {"coordinates":[-73.076897,40.833801],"type":"Point"}
}