{
  "type": "Feature",
  "properties": {
    "addr:full":"75 Echo Ave New Rochelle NY 10801",
    "addr:housenumber":"75",
    "addr:postcode":"10801",
    "addr:street":"Echo Ave",
    "iso:country":"US",
    "sg:address":"75 Echo Ave",
    "sg:city":"New Rochelle",
    "sg:classifiers":[
        {
            "category":"Building & Trades",
            "subcategory":"Construction",
            "type":"Services"
        }
    ],
    "sg:phone":"+1 914 637 6226",
    "sg:postcode":"10801",
    "sg:province":"NY",
    "sg:tags":[
        "gen",
        "contract"
    ],
    "wof:name":"Hambal Construction Co Inc",
    "wof:placetype":"venue"
},
  "geometry": {"coordinates":[-73.774717,40.91143],"type":"Point"}
}