{
  "type": "Feature",
  "properties": {
    "addr:full":"337 Merrick Rd Lynbrook NY 11563",
    "addr:housenumber":"337",
    "addr:postcode":"11563",
    "addr:street":"Merrick Rd",
    "iso:country":"US",
    "sg:address":"337 Merrick Rd",
    "sg:city":"Lynbrook",
    "sg:classifiers":[
        {
            "category":"Insurance",
            "subcategory":"Insurance Agent",
            "type":"Services"
        }
    ],
    "sg:phone":"+1 516 561 8050",
    "sg:postcode":"11563",
    "sg:province":"NY",
    "wof:name":"Naifa",
    "wof:placetype":"venue"
},
  "geometry": {"coordinates":[-73.67172100000001,40.657145],"type":"Point"}
}