{
  "type": "Feature",
  "properties": {
    "addr:full":"140 W 58th Street New York NY 10019",
    "addr:housenumber":"140",
    "addr:postcode":"10019",
    "addr:street":"W 58Th Street",
    "iso:country":"US",
    "sg:address":"140 W 58th Street",
    "sg:city":"New York",
    "sg:classifiers":[
        {
            "category":"Health Services",
            "subcategory":"Dentist",
            "type":"Services"
        }
    ],
    "sg:phone":"+1 212 315 2666",
    "sg:postcode":"10019",
    "sg:province":"NY",
    "wof:name":"Kow Sui-Yee H DDS",
    "wof:placetype":"venue"
},
  "geometry": {"coordinates":[-73.97785500000001,40.765473],"type":"Point"}
}