{
  "type": "Feature",
  "properties": {
    "addr:full":"403 Abrahams Path Amagansett NY 11937",
    "addr:housenumber":"403",
    "addr:postcode":"11937",
    "addr:street":"Abrahams Path",
    "iso:country":"US",
    "sg:address":"403 Abrahams Path",
    "sg:city":"Amagansett",
    "sg:classifiers":[
        {
            "category":"Shopping",
            "type":"Retail Goods"
        }
    ],
    "sg:phone":"+1 631 267 7909",
    "sg:postcode":"11937",
    "sg:province":"NY",
    "sg:tags":[
        "art",
        "gallery",
        "dealer"
    ],
    "wof:name":"Artist's Woods",
    "wof:placetype":"venue"
},
  "geometry": {"coordinates":[-72.15480599999999,40.976413],"type":"Point"}
}