{
  "type": "Feature",
  "properties": {
    "addr:full":"5317 13th Avenue Brooklyn NY 11219",
    "addr:housenumber":"5317",
    "addr:postcode":"11219",
    "addr:street":"13Th Avenue",
    "iso:country":"US",
    "sg:address":"5317 13th Avenue",
    "sg:city":"Brooklyn",
    "sg:classifiers":[
        {
            "category":"Retail",
            "subcategory":"Auto Rental",
            "type":"Services"
        }
    ],
    "sg:phone":"+1 718 972 1900",
    "sg:postcode":"11219",
    "sg:province":"NY",
    "sg:tags":[
        "car"
    ],
    "wof:name":"Exclusive Auto Leasing",
    "wof:placetype":"venue"
},
  "geometry": {"coordinates":[-73.994798,40.632277],"type":"Point"}
}