{
  "type": "Feature",
  "properties": {
    "iso:country":"US",
    "sg:address":"205 Moonlawn Rd",
    "sg:city":"Troy",
    "sg:classifiers":[
        {
            "category":"Building & Trades",
            "subcategory":"Construction",
            "type":"Services"
        }
    ],
    "sg:phone":"+1 518 279 3445",
    "sg:postcode":"12180",
    "sg:province":"NY",
    "sg:tags":[
        "home",
        "general",
        "family",
        "contractor"
    ],
    "wof:name":"Phibbs General Contracting",
    "wof:placetype":"venue"
},
  "geometry": {"coordinates":[-73.59197399999999,42.751447],"type":"Point"}
}