{
  "type": "Feature",
  "properties": {
    "addr:full":"98 S Main St Manchester NY 14504",
    "addr:housenumber":"98",
    "addr:postcode":"14504",
    "addr:street":"S Main St",
    "iso:country":"US",
    "sg:address":"98 S Main St",
    "sg:city":"Manchester",
    "sg:classifiers":[
        {
            "category":"Freight",
            "type":"Transportation"
        }
    ],
    "sg:phone":"+1 585 289 4400",
    "sg:postcode":"14504",
    "sg:province":"NY",
    "sg:tags":[
        "commercial",
        "storage"
    ],
    "wof:name":"Manchester Mini Storage",
    "wof:placetype":"venue"
},
  "geometry": {"coordinates":[-77.23025199999999,42.963822],"type":"Point"}
}