{
  "type": "Feature",
  "properties": {
    "iso:country":"US",
    "sg:address":"261 5th Ave",
    "sg:city":"New York",
    "sg:classifiers":[
        {
            "category":"Wholesale",
            "subcategory":"Durable Goods & Equipment",
            "type":"Manufacturing & Wholesale Goods"
        }
    ],
    "sg:phone":"+1 212 889 4750",
    "sg:postcode":"10016",
    "sg:province":"NY",
    "sg:tags":[
        "exporter"
    ],
    "wof:name":"Continental Textile Corp",
    "wof:placetype":"venue"
},
  "geometry": {"coordinates":[-73.987066,40.744749],"type":"Point"}
}