{
  "type": "Feature",
  "properties": {
    "iso:country":"US",
    "sg:address":"296 Burnside Ave",
    "sg:city":"Lawrence",
    "sg:classifiers":[
        {
            "category":"Autos & Motor Vehicles",
            "subcategory":"Auto Supplies",
            "type":"Retail Goods"
        }
    ],
    "sg:phone":"+1   ",
    "sg:postcode":"11559",
    "sg:province":"NY",
    "wof:name":"Auto Barn",
    "wof:placetype":"venue"
},
  "geometry": {"coordinates":[-73.73787400000001,40.623362],"type":"Point"}
}