{
  "type": "Feature",
  "properties": {
    "iso:country":"US",
    "sg:address":"74 Glen Cove Ave",
    "sg:city":"Glen Cove",
    "sg:classifiers":[
        {
            "category":"Retail",
            "subcategory":"Auto Repair",
            "type":"Services"
        }
    ],
    "sg:phone":"+1 516 676 6222",
    "sg:postcode":"11542",
    "sg:province":"NY",
    "sg:tags":[
        "transmission"
    ],
    "wof:name":"Over The Counter Transmissions",
    "wof:placetype":"venue"
},
  "geometry": {"coordinates":[-73.634889,40.858621],"type":"Point"}
}