{
  "type": "Feature",
  "properties": {
    "addr:full":"1451 Rice Rd Elma NY 14059",
    "addr:housenumber":"1451",
    "addr:postcode":"14059",
    "addr:street":"Rice Rd",
    "iso:country":"US",
    "sg:address":"1451 Rice Rd",
    "sg:city":"Elma",
    "sg:classifiers":[
        {
            "category":"Organizations",
            "subcategory":"Religious Organization",
            "type":"Services"
        }
    ],
    "sg:phone":"+1 716 652 5474",
    "sg:postcode":"14059",
    "sg:province":"NY",
    "sg:tags":[
        "clergy"
    ],
    "wof:name":"Peter Le Valley",
    "wof:placetype":"venue"
},
  "geometry": {"coordinates":[-78.623214,42.822564],"type":"Point"}
}