{
  "type": "Feature",
  "properties": {
    "iso:country":"US",
    "sg:address":"100 Willow St",
    "sg:city":"Massena",
    "sg:classifiers":[
        {
            "category":"Freight",
            "type":"Transportation"
        }
    ],
    "sg:phone":"+1   ",
    "sg:postcode":"13662",
    "sg:province":"NY",
    "sg:tags":[
        "operator",
        "trucking"
    ],
    "wof:name":"C C Eastern Inc",
    "wof:placetype":"venue"
},
  "geometry": {"coordinates":[-74.880899,44.938148],"type":"Point"}
}