{
  "type": "Feature",
  "properties": {
    "addr:full":"156 W 22 St New York NY 10011",
    "addr:housenumber":"156",
    "addr:postcode":"10011",
    "addr:street":"W 22 St",
    "iso:country":"US",
    "sg:address":"156 W 22 St",
    "sg:city":"New York",
    "sg:classifiers":[
        {
            "category":"Home & Garden",
            "subcategory":"Building Materials",
            "type":"Retail Goods"
        }
    ],
    "sg:phone":"+1 212 861 2634",
    "sg:postcode":"10011",
    "sg:province":"NY",
    "sg:tags":[
        "glass",
        "leaded"
    ],
    "wof:name":"Bedford Downing Glass",
    "wof:placetype":"venue"
},
  "geometry": {"coordinates":[-73.99493699999999,40.742681],"type":"Point"}
}