{
  "type": "Feature",
  "properties": {
    "addr:full":"120 Franklin Ave Yonkers NY 10705",
    "addr:housenumber":"120",
    "addr:postcode":"10705",
    "addr:street":"Franklin Ave",
    "iso:country":"US",
    "sg:address":"120 Franklin Ave",
    "sg:city":"Yonkers",
    "sg:classifiers":[
        {
            "category":"Professional",
            "subcategory":"Management & Consulting",
            "type":"Services"
        }
    ],
    "sg:phone":"+1 914 969 4709",
    "sg:postcode":"10705",
    "sg:province":"NY",
    "sg:tags":[
        "consultant",
        "health",
        "care"
    ],
    "wof:name":"M R Consultants",
    "wof:placetype":"venue"
},
  "geometry": {"coordinates":[-73.905784,40.919434],"type":"Point"}
}