{
  "type": "Feature",
  "properties": {
    "addr:full":"124 Saratoga Rd Schenectady NY 12302",
    "addr:housenumber":"124",
    "addr:postcode":"12302",
    "addr:street":"Saratoga Rd",
    "iso:country":"US",
    "sg:address":"124 Saratoga Rd",
    "sg:city":"Schenectady",
    "sg:classifiers":[
        {
            "category":"Health Services",
            "subcategory":"Doctor",
            "type":"Services"
        }
    ],
    "sg:phone":"+1 518 399 7782",
    "sg:postcode":"12302",
    "sg:province":"NY",
    "sg:tags":[
        "podiatrist"
    ],
    "wof:name":"Mc Cabe Robert O DPM",
    "wof:placetype":"venue"
},
  "geometry": {"coordinates":[-73.934799,42.859901],"type":"Point"}
}