{
  "type": "Feature",
  "properties": {
    "iso:country":"US",
    "sg:address":"35 Werman Ct",
    "sg:city":"Plainview",
    "sg:classifiers":[
        {
            "category":"Building & Trades",
            "subcategory":"Construction",
            "type":"Services"
        }
    ],
    "sg:phone":"+1 516 293 1600",
    "sg:postcode":"11803",
    "sg:province":"NY",
    "sg:tags":[
        "glass",
        "contractor"
    ],
    "wof:name":"All Glass Storefront Solutions",
    "wof:placetype":"venue"
},
  "geometry": {"coordinates":[-73.451292,40.782634],"type":"Point"}
}