{
  "type": "Feature",
  "properties": {
    "iso:country":"US",
    "sg:address":"Columbus Cir",
    "sg:city":"New York",
    "sg:classifiers":[
        {
            "category":"Professional",
            "subcategory":"Business Services",
            "type":"Services"
        }
    ],
    "sg:postcode":"10023",
    "sg:province":"NY",
    "sg:tags":[
        "delivery",
        "courier"
    ],
    "sg:website":"www.fedex.com",
    "wof:name":"FedEx",
    "wof:placetype":"venue"
},
  "geometry": {"coordinates":[-73.981466,40.768143],"type":"Point"}
}