{
  "type": "Feature",
  "properties": {
    "addr:full":"152 Union Ave Brooklyn NY 11206",
    "addr:housenumber":"152",
    "addr:postcode":"11206",
    "addr:street":"Union Ave",
    "iso:country":"US",
    "sg:address":"152 Union Ave",
    "sg:city":"Brooklyn",
    "sg:classifiers":[
        {
            "category":"Autos & Motor Vehicles",
            "subcategory":"Fuel & Gas Station",
            "type":"Retail Goods"
        }
    ],
    "sg:phone":"+1 718 599 8601",
    "sg:postcode":"11206",
    "sg:province":"NY",
    "sg:website":"www.bp.com/heliospower/modularho...",
    "wof:name":"Ram Jan",
    "wof:placetype":"venue"
},
  "geometry": {"coordinates":[-73.95000899999999,40.70454],"type":"Point"}
}