{
  "type": "Feature",
  "properties": {
    "iso:country":"US",
    "sg:address":"2570 N Jerusalem Rd",
    "sg:city":"North Bellmore",
    "sg:classifiers":[
        {
            "category":"Communications",
            "type":"Services"
        }
    ],
    "sg:phone":"+1 516 804 8839",
    "sg:postcode":"11710",
    "sg:province":"NY",
    "sg:tags":[
        "web",
        "design"
    ],
    "wof:name":"Rey Tech Solutions",
    "wof:placetype":"venue"
},
  "geometry": {"coordinates":[-73.539545,40.705922],"type":"Point"}
}