{
  "type": "Feature",
  "properties": {
    "addr:full":"196 Vulcan St Buffalo NY 14207",
    "addr:housenumber":"196",
    "addr:postcode":"14207",
    "addr:street":"Vulcan St",
    "iso:country":"US",
    "sg:address":"196 Vulcan St",
    "sg:city":"Buffalo",
    "sg:classifiers":[
        {
            "category":"Wholesale",
            "subcategory":"Electrical",
            "type":"Manufacturing & Wholesale Goods"
        },
        {
            "category":"Shopping",
            "subcategory":"Computers & Home Electronics",
            "type":"Retail Goods"
        }
    ],
    "sg:phone":"+1 716 874 2690",
    "sg:postcode":"14207",
    "sg:province":"NY",
    "sg:tags":[
        "equipment",
        "parts",
        "electronic",
        "supply"
    ],
    "sg:website":"www.radioequip.com",
    "wof:name":"Radio Equipment Corporation",
    "wof:placetype":"venue"
},
  "geometry": {"coordinates":[-78.90607199999999,42.961054],"type":"Point"}
}