{
  "type": "Feature",
  "properties": {
    "iso:country":"US",
    "sg:address":"9 Plymouth Rd",
    "sg:city":"Fishkill",
    "sg:classifiers":[
        {
            "category":"Building & Trades",
            "subcategory":"Construction",
            "type":"Services"
        }
    ],
    "sg:phone":"+1 845 896 3839",
    "sg:postcode":"12524",
    "sg:province":"NY",
    "sg:tags":[
        "contractor"
    ],
    "wof:name":"Donikar Contractor",
    "wof:placetype":"venue"
},
  "geometry": {"coordinates":[-73.873586,41.549757],"type":"Point"}
}