{
  "type": "Feature",
  "properties": {
    "iso:country":"US",
    "sg:address":"104-05 107th St",
    "sg:city":"Ozone Park",
    "sg:classifiers":[
        {
            "category":"Personal",
            "subcategory":"Beauty Salon",
            "type":"Services"
        }
    ],
    "sg:phone":"+1 718 843 0484",
    "sg:postcode":"11417",
    "sg:province":"NY",
    "sg:tags":[
        "hair"
    ],
    "wof:name":"Celebrity Salon",
    "wof:placetype":"venue"
},
  "geometry": {"coordinates":[-73.836085,40.680753],"type":"Point"}
}