{
  "type": "Feature",
  "properties": {
    "iso:country":"US",
    "sg:address":"1836 E Main St",
    "sg:city":"Mohegan Lake",
    "sg:classifiers":[
        {
            "category":"Social Services",
            "type":"Services"
        }
    ],
    "sg:phone":"+1 914 528 6995",
    "sg:postcode":"10547",
    "sg:province":"NY",
    "sg:tags":[
        "organization",
        "welfare"
    ],
    "wof:name":"Sunshine Social Club",
    "wof:placetype":"venue"
},
  "geometry": {"coordinates":[-73.845905,41.327841],"type":"Point"}
}