{
  "type": "Feature",
  "properties": {
    "addr:full":"406 Ruth Rd Syracuse NY 13212",
    "addr:housenumber":"406",
    "addr:postcode":"13212",
    "addr:street":"Ruth Rd",
    "iso:country":"US",
    "sg:address":"406 Ruth Rd",
    "sg:city":"Syracuse",
    "sg:classifiers":[
        {
            "category":"Manufacturing",
            "subcategory":"Tools & Machinery",
            "type":"Manufacturing & Wholesale Goods"
        }
    ],
    "sg:phone":"+1   ",
    "sg:postcode":"13212",
    "sg:province":"NY",
    "sg:tags":[
        "short",
        "power",
        "for",
        "supply",
        "lamp",
        "arc",
        "spec",
        "manufacturer"
    ],
    "wof:name":"Premier Power Systems Inc",
    "wof:placetype":"venue"
},
  "geometry": {"coordinates":[-76.16144199999999,43.13393],"type":"Point"}
}