{
  "type": "Feature",
  "properties": {
    "iso:country":"US",
    "sg:address":"572 Horse Run Rd",
    "sg:city":"Little Genesee",
    "sg:classifiers":[
        {
            "category":"Organizations",
            "subcategory":"Religious Organization",
            "type":"Services"
        }
    ],
    "sg:phone":"+1 585 928 2224",
    "sg:postcode":"14754",
    "sg:province":"NY",
    "sg:tags":[
        "church"
    ],
    "wof:name":"Bolivar United Methodist",
    "wof:placetype":"venue"
},
  "geometry": {"coordinates":[-78.16431300000001,42.029629],"type":"Point"}
}