{
  "type": "Feature",
  "properties": {
    "iso:country":"US",
    "sg:address":"204 Christopher St",
    "sg:city":"Ronkonkoma",
    "sg:classifiers":[
        {
            "category":"Retail",
            "subcategory":"Auto Repair",
            "type":"Services"
        }
    ],
    "sg:phone":"+1   ",
    "sg:postcode":"11779",
    "sg:province":"NY",
    "sg:tags":[
        "passenger",
        "local",
        "transportation",
        "general"
    ],
    "wof:name":"Limo Tech Inc",
    "wof:placetype":"venue"
},
  "geometry": {"coordinates":[-73.137277,40.795629],"type":"Point"}
}