{
  "type": "Feature",
  "properties": {
    "iso:country":"US",
    "sg:address":"107 W 37th St",
    "sg:city":"New York",
    "sg:classifiers":[
        {
            "category":"Shopping",
            "subcategory":"Clothing, Apparel, & Fashions",
            "type":"Retail Goods"
        }
    ],
    "sg:phone":"+1 212 997 7668",
    "sg:postcode":"10018",
    "sg:province":"NY",
    "sg:tags":[
        "designer"
    ],
    "wof:name":"Madam Inc",
    "wof:placetype":"venue"
},
  "geometry": {"coordinates":[-73.987205,40.752087],"type":"Point"}
}