{
  "type": "Feature",
  "properties": {
    "addr:full":"8 Bowman Ave Mayville NY 14722",
    "addr:housenumber":"8",
    "addr:postcode":"14722",
    "addr:street":"Bowman Ave",
    "iso:country":"US",
    "sg:address":"8 Bowman Ave",
    "sg:city":"Mayville",
    "sg:classifiers":[
        {
            "category":"Real Estate",
            "subcategory":"Real Estate Agent",
            "type":"Services"
        }
    ],
    "sg:phone":"+1 716 357 2022",
    "sg:postcode":"14722",
    "sg:province":"NY",
    "wof:name":"Maple Group Real Estate",
    "wof:placetype":"venue"
},
  "geometry": {"coordinates":[-79.466075,42.208337],"type":"Point"}
}