{
  "type": "Feature",
  "properties": {
    "iso:country":"US",
    "sg:address":"534 Colvin Ave",
    "sg:city":"Buffalo",
    "sg:classifiers":[
        {
            "category":"Retail",
            "subcategory":"Car Wash",
            "type":"Services"
        },
        {
            "category":"Retail",
            "subcategory":"Auto Repair",
            "type":"Services"
        }
    ],
    "sg:phone":"+1 716 877 2860",
    "sg:postcode":"14216",
    "sg:province":"NY",
    "sg:tags":[
        "detailing"
    ],
    "wof:name":"Simons Colvin Automobile Detail",
    "wof:placetype":"venue"
},
  "geometry": {"coordinates":[-78.859095,42.955207],"type":"Point"}
}