{
  "type": "Feature",
  "properties": {
    "addr:full":"400 Argyle Rd Brooklyn NY 11218",
    "addr:housenumber":"400",
    "addr:postcode":"11218",
    "addr:street":"Argyle Rd",
    "iso:country":"US",
    "sg:address":"400 Argyle Rd",
    "sg:city":"Brooklyn",
    "sg:classifiers":[
        {
            "category":"Real Estate",
            "subcategory":"Real Estate Agent",
            "type":"Services"
        }
    ],
    "sg:phone":"+1 718 462 9125",
    "sg:postcode":"11218",
    "sg:province":"NY",
    "wof:name":"Argyle Hall",
    "wof:placetype":"venue"
},
  "geometry": {"coordinates":[-73.965988,40.639268],"type":"Point"}
}