{
  "type": "Feature",
  "properties": {
    "addr:full":"40 Route 17K Newburgh NY 12550",
    "addr:housenumber":"40",
    "addr:postcode":"12550",
    "addr:street":"Route 17K",
    "iso:country":"US",
    "sg:address":"40 Route 17K",
    "sg:city":"Newburgh",
    "sg:classifiers":[
        {
            "category":"Autos & Motor Vehicles",
            "subcategory":"Automobile Sales",
            "type":"Retail Goods"
        },
        {
            "category":"Retail",
            "subcategory":"Auto Repair",
            "type":"Services"
        }
    ],
    "sg:phone":"+1 845 561 3900",
    "sg:postcode":"12550",
    "sg:province":"NY",
    "sg:tags":[
        "car",
        "truck",
        "new"
    ],
    "sg:website":"www.fordvehicles.com",
    "wof:name":"Sunshine Ford Lincoln Mercury",
    "wof:placetype":"venue"
},
  "geometry": {"coordinates":[-74.05880000000001,41.503502],"type":"Point"}
}