{
  "type": "Feature",
  "properties": {
    "addr:full":"126 Union Ave Center Moriches NY 11934",
    "addr:housenumber":"126",
    "addr:postcode":"11934",
    "addr:street":"Union Ave Center",
    "iso:country":"US",
    "sg:address":"126 Union Ave",
    "sg:city":"Center Moriches",
    "sg:classifiers":[
        {
            "category":"Real Estate",
            "subcategory":"Surveying",
            "type":"Services"
        }
    ],
    "sg:phone":"+1   ",
    "sg:postcode":"11934",
    "sg:province":"NY",
    "wof:name":"Werler Paul W",
    "wof:placetype":"venue"
},
  "geometry": {"coordinates":[-72.79839699999999,40.787578],"type":"Point"}
}