{
  "type": "Feature",
  "properties": {
    "iso:country":"US",
    "sg:address":"201 Stuyvesant Dr",
    "sg:city":"Selden",
    "sg:classifiers":[
        {
            "category":"Building & Trades",
            "subcategory":"Construction",
            "type":"Services"
        }
    ],
    "sg:phone":"+1 631 331 6502",
    "sg:postcode":"11784",
    "sg:province":"NY",
    "sg:tags":[
        "carpet",
        "installation",
        "contractor"
    ],
    "wof:name":"Carpets Your Way",
    "wof:placetype":"venue"
},
  "geometry": {"coordinates":[-73.04666899999999,40.889454],"type":"Point"}
}