{
  "type": "Feature",
  "properties": {
    "addr:full":"1017 84th St Brooklyn NY 11228",
    "addr:housenumber":"1017",
    "addr:postcode":"11228",
    "addr:street":"84Th St",
    "iso:country":"US",
    "sg:address":"1017 84th St",
    "sg:city":"Brooklyn",
    "sg:classifiers":[
        {
            "category":"Organizations",
            "subcategory":"Religious Organization",
            "type":"Services"
        }
    ],
    "sg:phone":"+1 718 836 8612",
    "sg:postcode":"11228",
    "sg:province":"NY",
    "sg:tags":[
        "clergy"
    ],
    "wof:name":"Jeanne Warfield",
    "wof:placetype":"venue"
},
  "geometry": {"coordinates":[-74.017337,40.618164],"type":"Point"}
}