{
  "type": "Feature",
  "properties": {
    "addr:full":"14 Taylor Rd Elmsford NY 10523",
    "addr:housenumber":"14",
    "addr:postcode":"10523",
    "addr:street":"Taylor Rd",
    "iso:country":"US",
    "sg:address":"14 Taylor Rd",
    "sg:city":"Elmsford",
    "sg:classifiers":[
        {
            "category":"Professional",
            "subcategory":"Computer Services",
            "type":"Services"
        }
    ],
    "sg:phone":"+1 914 347 0118",
    "sg:postcode":"10523",
    "sg:province":"NY",
    "sg:tags":[
        "information",
        "consulting",
        "technology"
    ],
    "wof:name":"Exgen Technology Inc",
    "wof:placetype":"venue"
},
  "geometry": {"coordinates":[-73.802278,41.071069],"type":"Point"}
}