{
  "type": "Feature",
  "properties": {
    "addr:full":"42 Beeman St Canandaigua NY 14424",
    "addr:housenumber":"42",
    "addr:postcode":"14424",
    "addr:street":"Beeman St",
    "iso:country":"US",
    "sg:address":"42 Beeman St",
    "sg:city":"Canandaigua",
    "sg:classifiers":[
        {
            "category":"Airline",
            "type":"Transportation"
        },
        {
            "category":"Real Estate",
            "subcategory":"Surveying",
            "type":"Services"
        }
    ],
    "sg:phone":"+1 585 394 5110",
    "sg:postcode":"14424",
    "sg:province":"NY",
    "sg:tags":[
        "surveyor",
        "land",
        "surveyors-aerial",
        "engineer"
    ],
    "sg:website":"http://www.freeparr.com",
    "wof:name":"Freeland-Parrinello Land Surveyors",
    "wof:placetype":"venue"
},
  "geometry": {"coordinates":[-77.277976,42.885459],"type":"Point"}
}