{
  "type": "Feature",
  "properties": {
    "iso:country":"US",
    "sg:address":"717 William St",
    "sg:city":"Baldwin",
    "sg:classifiers":[
        {
            "category":"Restaurant",
            "type":"Food & Drink"
        }
    ],
    "sg:phone":"+1   ",
    "sg:postcode":"11510",
    "sg:province":"NY",
    "sg:tags":[
        "eating"
    ],
    "wof:name":"Jac-Lyn Ice Cream Products",
    "wof:placetype":"venue"
},
  "geometry": {"coordinates":[-73.611238,40.678678],"type":"Point"}
}