{
  "type": "Feature",
  "properties": {
    "iso:country":"US",
    "sg:address":"112 E 19 St",
    "sg:city":"New York",
    "sg:classifiers":[
        {
            "category":"Professional",
            "type":"Services"
        }
    ],
    "sg:phone":"+1 212 533 8984",
    "sg:postcode":"10003",
    "sg:province":"NY",
    "sg:tags":[
        "scientist"
    ],
    "wof:name":"Light Speed",
    "wof:placetype":"venue"
},
  "geometry": {"coordinates":[-73.98724199999999,40.737358],"type":"Point"}
}