{
  "type": "Feature",
  "properties": {
    "iso:country":"US",
    "sg:address":"824 Merrick Rd",
    "sg:city":"Baldwin",
    "sg:classifiers":[
        {
            "category":"Health Services",
            "subcategory":"Doctor",
            "type":"Services"
        }
    ],
    "sg:phone":"+1 516 223 0726",
    "sg:postcode":"11510",
    "sg:province":"NY",
    "sg:tags":[
        "dentist"
    ],
    "sg:website":"www.drdavidg.com",
    "wof:name":"David A Grossman DDS",
    "wof:placetype":"venue"
},
  "geometry": {"coordinates":[-73.61100399999999,40.650722],"type":"Point"}
}