{
  "type": "Feature",
  "properties": {
    "iso:country":"US",
    "sg:address":"68 Colonial Dr",
    "sg:city":"Horseheads",
    "sg:classifiers":[
        {
            "category":"Health Services",
            "subcategory":"Doctor",
            "type":"Services"
        }
    ],
    "sg:phone":"+1 607 739 0352",
    "sg:postcode":"14845",
    "sg:province":"NY",
    "sg:tags":[
        "physician",
        "surgeon"
    ],
    "wof:name":"Arnothealth Primary Care Locat",
    "wof:placetype":"venue"
},
  "geometry": {"coordinates":[-76.855835,42.16185],"type":"Point"}
}