{
  "type": "Feature",
  "properties": {
    "iso:country":"US",
    "sg:address":"4 Old Lake Rd",
    "sg:city":"Valley Cottage",
    "sg:classifiers":[
        {
            "category":"Wholesale",
            "subcategory":"Metals & Minerals",
            "type":"Manufacturing & Wholesale Goods"
        }
    ],
    "sg:phone":"+1 845 268 2527",
    "sg:postcode":"10989",
    "sg:province":"NY",
    "sg:tags":[
        "nail",
        "tack"
    ],
    "wof:name":"Nail Cottage LLC",
    "wof:placetype":"venue"
},
  "geometry": {"coordinates":[-73.948536,41.118739],"type":"Point"}
}