{
  "type": "Feature",
  "properties": {
    "addr:full":"85 Jerome Ave Staten Island NY 10305",
    "addr:housenumber":"85",
    "addr:postcode":"10305",
    "addr:street":"Jerome Ave",
    "iso:country":"US",
    "sg:address":"85 Jerome Ave",
    "sg:city":"Staten Island",
    "sg:classifiers":[
        {
            "category":"Social Services",
            "type":"Services"
        }
    ],
    "sg:phone":"+1 718 720 6110",
    "sg:postcode":"10305",
    "sg:province":"NY",
    "sg:tags":[
        "senior",
        "citizen"
    ],
    "wof:name":"Staten Island Community Svc",
    "wof:placetype":"venue"
},
  "geometry": {"coordinates":[-74.075926,40.59638],"type":"Point"}
}