{
  "type": "Feature",
  "properties": {
    "iso:country":"US",
    "sg:address":"102 Buffalo St",
    "sg:city":"Hamburg",
    "sg:classifiers":[
        {
            "category":"Education",
            "subcategory":"Library",
            "type":"Public Place"
        }
    ],
    "sg:phone":"+1 716 649 4415",
    "sg:postcode":"14075",
    "sg:province":"NY",
    "sg:tags":[
        "executive"
    ],
    "wof:name":"Buffalo- Erie County Pub Lib",
    "wof:placetype":"venue"
},
  "geometry": {"coordinates":[-78.829364,42.718032],"type":"Point"}
}