{
  "type": "Feature",
  "properties": {
    "iso:country":"US",
    "sg:address":"137 Orchard St",
    "sg:city":"New York",
    "sg:classifiers":[
        {
            "category":"Travel",
            "subcategory":"Travel Agent",
            "type":"Entertainment"
        }
    ],
    "sg:phone":"+1   ",
    "sg:postcode":"10002",
    "sg:province":"NY",
    "sg:tags":[
        "agency"
    ],
    "wof:name":"AVI Travel Svce",
    "wof:placetype":"venue"
},
  "geometry": {"coordinates":[-73.98958,40.71931],"type":"Point"}
}