{
  "type": "Feature",
  "properties": {
    "addr:full":"1700 Black River Blvd N Rome NY 13440",
    "addr:housenumber":"1700",
    "addr:postcode":"13440",
    "addr:street":"Black River Blvd N",
    "iso:country":"US",
    "sg:address":"1700 Black River Blvd N",
    "sg:city":"Rome",
    "sg:classifiers":[
        {
            "category":"Restaurant",
            "type":"Food & Drink"
        }
    ],
    "sg:menulink":"http://www.allmenus.com/ny/rome/170052-burger-king/menu/",
    "sg:phone":"+1 315 339 2660",
    "sg:postcode":"13440",
    "sg:province":"NY",
    "sg:tags":[
        "burger",
        "american"
    ],
    "wof:name":"Burger King",
    "wof:placetype":"venue"
},
  "geometry": {"coordinates":[-75.439469,43.230383],"type":"Point"}
}