{
  "type": "Feature",
  "properties": {
    "iso:country":"US",
    "sg:address":"120 de Kruif Pl",
    "sg:city":"Bronx",
    "sg:classifiers":[
        {
            "category":"Health Services",
            "subcategory":"Medical Lab",
            "type":"Services"
        }
    ],
    "sg:phone":"+1 718 320 7401",
    "sg:postcode":"10475",
    "sg:province":"NY",
    "sg:tags":[
        "laboratory"
    ],
    "wof:name":"Medical Village At Co Op City",
    "wof:placetype":"venue"
},
  "geometry": {"coordinates":[-73.829148,40.875216],"type":"Point"}
}