{
  "type": "Feature",
  "properties": {
    "addr:full":"473 E Main St Gouverneur NY 13642",
    "addr:housenumber":"473",
    "addr:postcode":"13642",
    "addr:street":"E Main St",
    "iso:country":"US",
    "sg:address":"473 E Main St",
    "sg:city":"Gouverneur",
    "sg:classifiers":[
        {
            "category":"Shopping",
            "subcategory":"Department Store",
            "type":"Retail Goods"
        }
    ],
    "sg:phone":"+1 315 287 2511",
    "sg:postcode":"13642",
    "sg:province":"NY",
    "wof:name":"Family Dollar Store",
    "wof:placetype":"venue"
},
  "geometry": {"coordinates":[-75.451774,44.342498],"type":"Point"}
}