{
  "type": "Feature",
  "properties": {
    "iso:country":"US",
    "sg:address":"85 Abeel St",
    "sg:city":"Kingston",
    "sg:classifiers":[
        {
            "category":"Shopping",
            "subcategory":"Jewelry",
            "type":"Retail Goods"
        }
    ],
    "sg:phone":"+1   ",
    "sg:postcode":"12401",
    "sg:province":"NY",
    "wof:name":"Kremlin Gems & Treasures",
    "wof:placetype":"venue"
},
  "geometry": {"coordinates":[-73.98654399999999,41.917],"type":"Point"}
}