{
  "type": "Feature",
  "properties": {
    "addr:full":"22 W 23rd St New York NY 10010",
    "addr:housenumber":"22",
    "addr:postcode":"10010",
    "addr:street":"W 23Rd St",
    "iso:country":"US",
    "sg:address":"22 W 23rd St",
    "sg:city":"New York",
    "sg:classifiers":[
        {
            "category":"Professional",
            "type":"Services"
        }
    ],
    "sg:phone":"+1 212 366 5033",
    "sg:postcode":"10010",
    "sg:province":"NY",
    "sg:website":"www.djdgolden.com",
    "wof:name":"Djd/Golden Advertising",
    "wof:placetype":"venue"
},
  "geometry": {"coordinates":[-73.990697,40.741689],"type":"Point"}
}