{
  "type": "Feature",
  "properties": {
    "addr:full":"558 W 44th Street New York NY 10036",
    "addr:housenumber":"558",
    "addr:postcode":"10036",
    "addr:street":"W 44Th Street",
    "iso:country":"US",
    "sg:address":"558 W 44th Street",
    "sg:city":"New York",
    "sg:classifiers":[
        {
            "category":"Building & Trades",
            "subcategory":"Plumbing",
            "type":"Services"
        }
    ],
    "sg:phone":"+1 718 927 4545",
    "sg:postcode":"10036",
    "sg:province":"NY",
    "wof:name":"Imp Plumbing & Heating Corporation",
    "wof:placetype":"venue"
},
  "geometry": {"coordinates":[-73.996743,40.761987],"type":"Point"}
}