{
  "type": "Feature",
  "properties": {
    "iso:country":"US",
    "sg:address":"770 Port Richmond Ave",
    "sg:city":"Staten Island",
    "sg:classifiers":[
        {
            "category":"Personal",
            "type":"Services"
        }
    ],
    "sg:phone":"+1 718 720 8945",
    "sg:postcode":"10302",
    "sg:province":"NY",
    "sg:tags":[
        "paying",
        "bill"
    ],
    "wof:name":"Staten Island Payment Ctr",
    "wof:placetype":"venue"
},
  "geometry": {"coordinates":[-74.14469800000001,40.625343],"type":"Point"}
}