{
  "type": "Feature",
  "properties": {
    "addr:full":"1250 Northrup Rd Penfield NY 14526",
    "addr:housenumber":"1250",
    "addr:postcode":"14526",
    "addr:street":"Northrup Rd",
    "iso:country":"US",
    "sg:address":"1250 Northrup Rd",
    "sg:city":"Penfield",
    "sg:classifiers":[
        {
            "category":"Building & Trades",
            "subcategory":"Landscaping Services",
            "type":"Services"
        }
    ],
    "sg:phone":"+1 585 872 2790",
    "sg:postcode":"14526",
    "sg:province":"NY",
    "sg:tags":[
        "builder",
        "patio",
        "landscape",
        "contractor"
    ],
    "sg:website":"http://www.naturesaccents.com",
    "wof:name":"Nature's Accents Inc",
    "wof:placetype":"venue"
},
  "geometry": {"coordinates":[-77.43912,43.172869],"type":"Point"}
}