{
  "type": "Feature",
  "properties": {
    "iso:country":"US",
    "sg:address":"5501 13th Ave",
    "sg:city":"Brooklyn",
    "sg:classifiers":[
        {
            "category":"Shopping",
            "subcategory":"News",
            "type":"Retail Goods"
        }
    ],
    "sg:phone":"+1   ",
    "sg:postcode":"11219",
    "sg:province":"NY",
    "sg:tags":[
        "newsstand"
    ],
    "wof:name":"Sams Newstand",
    "wof:placetype":"venue"
},
  "geometry": {"coordinates":[-73.996195,40.631105],"type":"Point"}
}