{
  "type": "Feature",
  "properties": {
    "iso:country":"US",
    "sg:address":"315 5th Ave",
    "sg:city":"New York",
    "sg:classifiers":[
        {
            "category":"Professional",
            "subcategory":"Management & Consulting",
            "type":"Services"
        }
    ],
    "sg:phone":"+1 212 683 4600",
    "sg:postcode":"10016",
    "sg:province":"NY",
    "sg:tags":[
        "marketing",
        "consultant"
    ],
    "wof:name":"Mintwave Limited",
    "wof:placetype":"venue"
},
  "geometry": {"coordinates":[-73.98573,40.746577],"type":"Point"}
}