{
  "type": "Feature",
  "properties": {
    "iso:country":"US",
    "sg:address":"132 Spruce St",
    "sg:city":"Cedarhurst",
    "sg:classifiers":[
        {
            "category":"Professional",
            "subcategory":"Lawyer & Legal Services",
            "type":"Services"
        }
    ],
    "sg:phone":"+1 516 295 2070",
    "sg:postcode":"11516",
    "sg:province":"NY",
    "wof:name":"Gabor Todd Atty",
    "wof:placetype":"venue"
},
  "geometry": {"coordinates":[-73.726097,40.621899],"type":"Point"}
}