{
  "type": "Feature",
  "properties": {
    "iso:country":"US",
    "sg:address":"145 W 52nd St",
    "sg:city":"New York",
    "sg:classifiers":[
        {
            "category":"Retail",
            "subcategory":"Auto Repair",
            "type":"Services"
        }
    ],
    "sg:phone":"+1 646 862 5603",
    "sg:postcode":"10019",
    "sg:province":"NY",
    "sg:tags":[
        "repairing",
        "automobile"
    ],
    "wof:name":"ACC Car Care Ctr",
    "wof:placetype":"venue"
},
  "geometry": {"coordinates":[-73.98134899999999,40.761872],"type":"Point"}
}