{
  "type": "Feature",
  "properties": {
    "iso:country":"US",
    "sg:address":"30 Ray St",
    "sg:city":"Niskayuna",
    "sg:classifiers":[
        {
            "category":"Shopping",
            "subcategory":"Used Merchandise",
            "type":"Retail Goods"
        }
    ],
    "sg:phone":"+1 518 372 2570",
    "sg:postcode":"12309",
    "sg:province":"NY",
    "sg:tags":[
        "antique"
    ],
    "wof:name":"House of Rose Antiques",
    "wof:placetype":"venue"
},
  "geometry": {"coordinates":[-73.894706,42.801921],"type":"Point"}
}