{
  "type": "Feature",
  "properties": {
    "addr:full":"305 E 180th St Bronx NY 10457",
    "addr:housenumber":"305",
    "addr:postcode":"10457",
    "addr:street":"E 180Th St",
    "iso:country":"US",
    "sg:address":"305 E 180th St",
    "sg:city":"Bronx",
    "sg:classifiers":[
        {
            "category":"Building & Trades",
            "subcategory":"Construction",
            "type":"Services"
        }
    ],
    "sg:phone":"+1 718 866 0059",
    "sg:postcode":"10457",
    "sg:province":"NY",
    "sg:tags":[
        "home",
        "improvement"
    ],
    "wof:name":"PBMC Home Improvement",
    "wof:placetype":"venue"
},
  "geometry": {"coordinates":[-73.89928500000001,40.852339],"type":"Point"}
}