{
  "type": "Feature",
  "properties": {
    "iso:country":"US",
    "sg:address":"1038 Nostrand Ave",
    "sg:city":"Brooklyn",
    "sg:classifiers":[
        {
            "category":"Manufacturing",
            "subcategory":"Printing",
            "type":"Manufacturing & Wholesale Goods"
        }
    ],
    "sg:phone":"+1 718 773 9557",
    "sg:postcode":"11225",
    "sg:province":"NY",
    "sg:tags":[
        "printer"
    ],
    "wof:name":"K G Printing",
    "wof:placetype":"venue"
},
  "geometry": {"coordinates":[-73.950895,40.662488],"type":"Point"}
}