{
  "type": "Feature",
  "properties": {
    "addr:full":"205 Allen St New York NY 10002",
    "addr:housenumber":"205",
    "addr:postcode":"10002",
    "addr:street":"Allen St",
    "iso:country":"US",
    "sg:address":"205 Allen St",
    "sg:city":"New York",
    "sg:classifiers":[
        {
            "category":"Restaurant",
            "type":"Food & Drink"
        }
    ],
    "sg:menulink":"http://www.allmenus.com/ny/new-york/82749-dominos-pizza/menu/",
    "sg:phone":"+1 212 677 7776",
    "sg:postcode":"10002",
    "sg:province":"NY",
    "sg:tags":[
        "american",
        "wing",
        "pizza"
    ],
    "wof:name":"Domino's Pizza",
    "wof:placetype":"venue"
},
  "geometry": {"coordinates":[-73.98894799999999,40.722496],"type":"Point"}
}