{
  "type": "Feature",
  "properties": {
    "addr:full":"2391 Arthur Ave Bronx NY 10458",
    "addr:housenumber":"2391",
    "addr:postcode":"10458",
    "addr:street":"Arthur Ave",
    "iso:country":"US",
    "sg:address":"2391 Arthur Ave",
    "sg:city":"Bronx",
    "sg:classifiers":[
        {
            "category":"Health Services",
            "subcategory":"Podiatrist",
            "type":"Services"
        }
    ],
    "sg:phone":"+1 718 563 3000",
    "sg:postcode":"10458",
    "sg:province":"NY",
    "wof:name":"A & M Footcare",
    "wof:placetype":"venue"
},
  "geometry": {"coordinates":[-73.888018,40.854989],"type":"Point"}
}