{
  "type": "Feature",
  "properties": {
    "iso:country":"US",
    "sg:address":"307 Keuka St",
    "sg:city":"Penn Yan",
    "sg:classifiers":[
        {
            "category":"Home & Garden",
            "subcategory":"Garden Supply",
            "type":"Retail Goods"
        }
    ],
    "sg:phone":"+1   ",
    "sg:postcode":"14527",
    "sg:province":"NY",
    "wof:name":"Hansen Nursery",
    "wof:placetype":"venue"
},
  "geometry": {"coordinates":[-77.058944,42.66257],"type":"Point"}
}