{
  "type": "Feature",
  "properties": {
    "addr:full":"525 Mill St Watertown NY 13601",
    "addr:housenumber":"525",
    "addr:postcode":"13601",
    "addr:street":"Mill St",
    "iso:country":"US",
    "sg:address":"525 Mill St",
    "sg:city":"Watertown",
    "sg:classifiers":[
        {
            "category":"Restaurant",
            "type":"Food & Drink"
        }
    ],
    "sg:menulink":"http://www.allmenus.com/ny/watertown/229201-jreck-subs/menu/",
    "sg:phone":"+1 315 782 6230",
    "sg:postcode":"13601",
    "sg:province":"NY",
    "sg:tags":[
        "wrap",
        "american",
        "sandwich"
    ],
    "wof:name":"Jreck Subs",
    "wof:placetype":"venue"
},
  "geometry": {"coordinates":[-75.90639899999999,43.980017],"type":"Point"}
}