{
  "type": "Feature",
  "properties": {
    "iso:country":"US",
    "sg:address":"35 Dartmouth Ave",
    "sg:city":"Buffalo",
    "sg:classifiers":[
        {
            "category":"Shopping",
            "subcategory":"Clothing, Apparel, & Fashions",
            "type":"Retail Goods"
        }
    ],
    "sg:phone":"+1   ",
    "sg:postcode":"14215",
    "sg:province":"NY",
    "sg:tags":[
        "boutique"
    ],
    "wof:name":"Sisters Boutique",
    "wof:placetype":"venue"
},
  "geometry": {"coordinates":[-78.82247,42.943983],"type":"Point"}
}