{
  "type": "Feature",
  "properties": {
    "addr:full":"185 Jordan Rd Troy NY 12180",
    "addr:housenumber":"185",
    "addr:postcode":"12180",
    "addr:street":"Jordan Rd",
    "iso:country":"US",
    "sg:address":"185 Jordan Rd",
    "sg:city":"Troy",
    "sg:classifiers":[
        {
            "category":"Professional",
            "subcategory":"Research",
            "type":"Services"
        }
    ],
    "sg:phone":"+1 518 203 0050",
    "sg:postcode":"12180",
    "sg:province":"NY",
    "sg:tags":[
        "environmental",
        "ecological"
    ],
    "wof:name":"Delta Environmental",
    "wof:placetype":"venue"
},
  "geometry": {"coordinates":[-73.692762,42.677062],"type":"Point"}
}