{
  "type": "Feature",
  "properties": {
    "addr:full":"2853 Co Rte 45 Fulton NY 13069",
    "addr:housenumber":"2853",
    "addr:postcode":"13069",
    "addr:street":"Co Rte 45",
    "iso:country":"US",
    "sg:address":"2853 Co Rte 45",
    "sg:city":"Fulton",
    "sg:classifiers":[
        {
            "category":"Building & Trades",
            "subcategory":"Construction",
            "type":"Services"
        }
    ],
    "sg:phone":"+1 315 598 7521",
    "sg:postcode":"13069",
    "sg:province":"NY",
    "sg:tags":[
        "sandblasting"
    ],
    "wof:name":"Triple D Bus Repair",
    "wof:placetype":"venue"
},
  "geometry": {"coordinates":[-76.38204500000001,43.386903],"type":"Point"}
}