{
  "type": "Feature",
  "properties": {
    "addr:full":"1390 3rd Ave Frnt 2 New York NY 10075",
    "addr:housenumber":"1390;2",
    "addr:postcode":"10075",
    "addr:street":"3Rd Ave Frnt",
    "iso:country":"US",
    "sg:address":"1390 3rd Ave Frnt 2",
    "sg:city":"New York",
    "sg:classifiers":[
        {
            "category":"Shopping",
            "subcategory":"Mobile Phones",
            "type":"Retail Goods"
        }
    ],
    "sg:phone":"+1 212 517 5777",
    "sg:postcode":"10075",
    "sg:province":"NY",
    "wof:name":"Unique Wireless",
    "wof:placetype":"venue"
},
  "geometry": {"coordinates":[-73.957415,40.774361],"type":"Point"}
}