{
  "type": "Feature",
  "properties": {
    "addr:full":"2204 Bellmore Ave Bellmore NY 11710",
    "addr:housenumber":"2204",
    "addr:postcode":"11710",
    "addr:street":"Bellmore Ave",
    "iso:country":"US",
    "sg:address":"2204 Bellmore Ave",
    "sg:city":"Bellmore",
    "sg:classifiers":[
        {
            "category":"Real Estate",
            "subcategory":"Real Estate Agent",
            "type":"Services"
        }
    ],
    "sg:phone":"+1 516 409 4663",
    "sg:postcode":"11710",
    "sg:province":"NY",
    "wof:name":"Premier Homefinders Inc",
    "wof:placetype":"venue"
},
  "geometry": {"coordinates":[-73.524753,40.670161],"type":"Point"}
}