{
  "type": "Feature",
  "properties": {
    "addr:full":"48 Scott Dr Troy NY 12180",
    "addr:housenumber":"48",
    "addr:postcode":"12180",
    "addr:street":"Scott Dr",
    "iso:country":"US",
    "sg:address":"48 Scott Dr",
    "sg:city":"Troy",
    "sg:classifiers":[
        {
            "category":"Home & Garden",
            "subcategory":"Furniture",
            "type":"Retail Goods"
        },
        {
            "category":"Wholesale",
            "subcategory":"Home Furnishings",
            "type":"Manufacturing & Wholesale Goods"
        }
    ],
    "sg:phone":"+1 518 279 0195",
    "sg:postcode":"12180",
    "sg:province":"NY",
    "sg:tags":[
        "equipment-wholesale",
        "kitchen",
        "equipment-household",
        "manufacturer",
        "cabinet"
    ],
    "wof:name":"P&B Custom Cabinetry & Millwor",
    "wof:placetype":"venue"
},
  "geometry": {"coordinates":[-73.63172900000001,42.76947],"type":"Point"}
}