{
  "type": "Feature",
  "properties": {
    "addr:full":"205 E 22 St New York NY 10010",
    "addr:housenumber":"205;22",
    "addr:postcode":"10010",
    "addr:street":"E",
    "iso:country":"US",
    "sg:address":"205 E 22 St",
    "sg:city":"New York",
    "sg:classifiers":[
        {
            "category":"Health Services",
            "subcategory":"Chiropractor",
            "type":"Services"
        }
    ],
    "sg:phone":"+1 212 686 2244",
    "sg:postcode":"10010",
    "sg:province":"NY",
    "wof:name":"Gramercy Park Chiropractic PC",
    "wof:placetype":"venue"
},
  "geometry": {"coordinates":[-73.98329699999999,40.738116],"type":"Point"}
}