{
  "type": "Feature",
  "properties": {
    "addr:full":"168 Madison Ave Fl 3 New York NY 10016",
    "addr:housenumber":"168;3",
    "addr:postcode":"10016",
    "addr:street":"Madison Ave Fl",
    "iso:country":"US",
    "sg:address":"168 Madison Ave Fl 3",
    "sg:city":"New York",
    "sg:classifiers":[
        {
            "category":"Health Services",
            "subcategory":"Dentist",
            "type":"Services"
        }
    ],
    "sg:phone":"+1 212 889 9200",
    "sg:postcode":"10016",
    "sg:province":"NY",
    "wof:name":"Leonid Agranat dentist",
    "wof:placetype":"venue"
},
  "geometry": {"coordinates":[-73.98362,40.747104],"type":"Point"}
}