{
  "type": "Feature",
  "properties": {
    "addr:full":"3 Trolley Rd Montrose NY 10548",
    "addr:housenumber":"3",
    "addr:postcode":"10548",
    "addr:street":"Trolley Rd",
    "iso:country":"US",
    "sg:address":"3 Trolley Rd",
    "sg:city":"Montrose",
    "sg:classifiers":[
        {
            "category":"Personal",
            "type":"Services"
        },
        {
            "category":"Retail",
            "subcategory":"Auto Repair",
            "type":"Services"
        }
    ],
    "sg:phone":"+1 914 737 1879",
    "sg:postcode":"10548",
    "sg:province":"NY",
    "sg:tags":[
        "body",
        "automobile",
        "towing",
        "painting",
        "repairing",
        "road",
        "service-automotive"
    ],
    "wof:name":"Malles Auto Body Co.",
    "wof:placetype":"venue"
},
  "geometry": {"coordinates":[-73.932857,41.253207],"type":"Point"}
}