{
  "type": "Feature",
  "properties": {
    "iso:country":"US",
    "sg:address":"11 Holley Crk",
    "sg:city":"Pittsford",
    "sg:classifiers":[
        {
            "category":"Professional",
            "subcategory":"Management & Consulting",
            "type":"Services"
        }
    ],
    "sg:phone":"+1 585 248 0459",
    "sg:postcode":"14534",
    "sg:province":"NY",
    "sg:tags":[
        "consultant"
    ],
    "wof:name":"David Terry",
    "wof:placetype":"venue"
},
  "geometry": {"coordinates":[-77.50823099999999,43.053579],"type":"Point"}
}