{
  "type": "Feature",
  "properties": {
    "addr:full":"614 W State St Ithaca NY 14850",
    "addr:housenumber":"614",
    "addr:postcode":"14850",
    "addr:street":"W State St",
    "iso:country":"US",
    "sg:address":"614 W State St",
    "sg:city":"Ithaca",
    "sg:classifiers":[
        {
            "category":"Professional",
            "subcategory":"Accounting & Tax Preparation",
            "type":"Services"
        }
    ],
    "sg:phone":"+1 607 273 6730",
    "sg:postcode":"14850",
    "sg:province":"NY",
    "sg:tags":[
        "accountant"
    ],
    "wof:name":"RCP Financial Svc",
    "wof:placetype":"venue"
},
  "geometry": {"coordinates":[-76.508572,42.43932],"type":"Point"}
}