{
  "type": "Feature",
  "properties": {
    "addr:full":"78 Butler St Brooklyn NY 11231",
    "addr:housenumber":"78",
    "addr:postcode":"11231",
    "addr:street":"Butler St",
    "iso:country":"US",
    "sg:address":"78 Butler St",
    "sg:city":"Brooklyn",
    "sg:classifiers":[
        {
            "category":"Building & Trades",
            "subcategory":"Construction",
            "type":"Services"
        }
    ],
    "sg:phone":"+1 718 797 5553",
    "sg:postcode":"11231",
    "sg:province":"NY",
    "sg:tags":[
        "company"
    ],
    "wof:name":"Dixie Construction Corp",
    "wof:placetype":"venue"
},
  "geometry": {"coordinates":[-73.990443,40.683467],"type":"Point"}
}