{
  "type": "Feature",
  "properties": {
    "addr:full":"204 E 23 St New York NY 10010",
    "addr:housenumber":"204;23",
    "addr:postcode":"10010",
    "addr:street":"E;St",
    "iso:country":"US",
    "sg:address":"204 E 23 St",
    "sg:city":"New York",
    "sg:classifiers":[
        {
            "category":"Organizations",
            "subcategory":"Community Association",
            "type":"Services"
        }
    ],
    "sg:phone":"+1 212 448 1240",
    "sg:postcode":"10010",
    "sg:province":"NY",
    "sg:tags":[
        "club"
    ],
    "wof:name":"Fire Bell Club Of Ny Inc",
    "wof:placetype":"venue"
},
  "geometry": {"coordinates":[-73.981011,40.737858],"type":"Point"}
}