{
  "type": "Feature",
  "properties": {
    "addr:full":"607 E Main St Endicott NY 13760",
    "addr:housenumber":"607",
    "addr:postcode":"13760",
    "addr:street":"E Main St",
    "iso:country":"US",
    "sg:address":"607 E Main St",
    "sg:city":"Endicott",
    "sg:classifiers":[
        {
            "category":"Health Services",
            "subcategory":"Chiropractor",
            "type":"Services"
        }
    ],
    "sg:phone":"+1   ",
    "sg:postcode":"13760",
    "sg:province":"NY",
    "wof:name":"Tri Cities",
    "wof:placetype":"venue"
},
  "geometry": {"coordinates":[-76.05697000000001,42.095074],"type":"Point"}
}