{
  "type": "Feature",
  "properties": {
    "addr:full":"875 W 181st St New York NY 10033",
    "addr:housenumber":"875",
    "addr:postcode":"10033",
    "addr:street":"W 181St St",
    "iso:country":"US",
    "sg:address":"875 W 181st St",
    "sg:city":"New York",
    "sg:classifiers":[
        {
            "category":"Real Estate",
            "subcategory":"Real Estate Agent",
            "type":"Services"
        }
    ],
    "sg:phone":"+1 917 521 8262",
    "sg:postcode":"10033",
    "sg:province":"NY",
    "sg:tags":[
        "cooperative"
    ],
    "wof:name":"875 West 181st Co-Op",
    "wof:placetype":"venue"
},
  "geometry": {"coordinates":[-73.940235,40.851326],"type":"Point"}
}