{
  "type": "Feature",
  "properties": {
    "iso:country":"US",
    "sg:address":"105 Dobbin St",
    "sg:city":"Brooklyn",
    "sg:classifiers":[
        {
            "category":"Building & Trades",
            "subcategory":"Construction",
            "type":"Services"
        }
    ],
    "sg:phone":"+1 718 383 9555",
    "sg:postcode":"11222",
    "sg:province":"NY",
    "sg:tags":[
        "contractor"
    ],
    "wof:name":"Ice Stone Work Inc",
    "wof:placetype":"venue"
},
  "geometry": {"coordinates":[-73.955017,40.725609],"type":"Point"}
}