{
  "type": "Feature",
  "properties": {
    "addr:full":"444 Willis Ave Bronx NY 10455",
    "addr:housenumber":"444",
    "addr:postcode":"10455",
    "addr:street":"Willis Ave",
    "iso:country":"US",
    "sg:address":"444 Willis Ave",
    "sg:city":"Bronx",
    "sg:classifiers":[
        {
            "category":"Manufacturing",
            "subcategory":"Tools & Machinery",
            "type":"Manufacturing & Wholesale Goods"
        }
    ],
    "sg:phone":"+1   ",
    "sg:postcode":"10455",
    "sg:province":"NY",
    "sg:tags":[
        "repair",
        "network",
        "maintenance"
    ],
    "wof:name":"Alley Net",
    "wof:placetype":"venue"
},
  "geometry": {"coordinates":[-73.919237,40.813924],"type":"Point"}
}