{
  "type": "Feature",
  "properties": {
    "addr:full":"972 Ave of the Americas Manhattan NY 10018",
    "addr:housenumber":"972",
    "addr:postcode":"10018",
    "addr:street":"Ave Of The Americas",
    "iso:country":"US",
    "sg:address":"972 Ave of the Americas",
    "sg:city":"Manhattan",
    "sg:classifiers":[
        {
            "category":"Fast Food",
            "type":"Food & Drink"
        }
    ],
    "sg:phone":"+1 212 714 9020",
    "sg:postcode":"10018",
    "sg:province":"NY",
    "wof:name":"McDonald's",
    "wof:placetype":"venue"
},
  "geometry": {"coordinates":[-73.986816,40.750821],"type":"Point"}
}