{
  "type": "Feature",
  "properties": {
    "iso:country":"US",
    "sg:address":"972 Ave of the Americas",
    "sg:city":"Manhattan",
    "sg:classifiers":[
        {
            "category":"Fast Food",
            "type":"Food & Drink"
        }
    ],
    "sg:phone":"+1 212 714 9020",
    "sg:postcode":"10018",
    "sg:province":"NY",
    "wof:name":"McDonald's",
    "wof:placetype":"venue"
},
  "geometry": {"coordinates":[-73.986726,40.750778],"type":"Point"}
}