{
  "type": "Feature",
  "properties": {
    "iso:country":"US",
    "sg:address":"147 Adams Ave",
    "sg:city":"Hempstead",
    "sg:classifiers":[
        {
            "category":"Retail",
            "subcategory":"Auto Repair",
            "type":"Services"
        }
    ],
    "sg:phone":"+1 516 483 0197",
    "sg:postcode":"11550",
    "sg:province":"NY",
    "sg:tags":[
        "body",
        "automobile",
        "towing",
        "painting"
    ],
    "wof:name":"Hempstead Auto Collision",
    "wof:placetype":"venue"
},
  "geometry": {"coordinates":[-73.626198,40.703899],"type":"Point"}
}