{
  "type": "Feature",
  "properties": {
    "addr:full":"183 Wilson St Brooklyn NY 11211",
    "addr:housenumber":"183",
    "addr:postcode":"11211",
    "addr:street":"Wilson St",
    "iso:country":"US",
    "sg:address":"183 Wilson St",
    "sg:city":"Brooklyn",
    "sg:classifiers":[
        {
            "category":"Wholesale",
            "subcategory":"Apparel",
            "type":"Manufacturing & Wholesale Goods"
        }
    ],
    "sg:phone":"+1 718 963 0783",
    "sg:postcode":"11211",
    "sg:province":"NY",
    "sg:tags":[
        "clothing"
    ],
    "wof:name":"Babyhues",
    "wof:placetype":"venue"
},
  "geometry": {"coordinates":[-73.959627,40.707252],"type":"Point"}
}