{
  "type": "Feature",
  "properties": {
    "iso:country":"US",
    "sg:address":"106 Blind Creek Dr",
    "sg:city":"Sandy Creek",
    "sg:classifiers":[
        {
            "category":"Building & Trades",
            "subcategory":"Construction",
            "type":"Services"
        }
    ],
    "sg:phone":"+1 315 387 5136",
    "sg:postcode":"13083",
    "sg:province":"NY",
    "sg:tags":[
        "house"
    ],
    "wof:name":"Jet Construction",
    "wof:placetype":"venue"
},
  "geometry": {"coordinates":[-76.15818299999999,43.65206],"type":"Point"}
}