{
  "type": "Feature",
  "properties": {
    "iso:country":"US",
    "sg:address":"154 Sloperville Dr",
    "sg:city":"Altmar",
    "sg:classifiers":[
        {
            "category":"Travel",
            "subcategory":"Hotels & Motels",
            "type":"Entertainment"
        }
    ],
    "sg:phone":"+1 315 298 6028",
    "sg:postcode":"13302",
    "sg:province":"NY",
    "sg:website":"www.stonehouseinnlodging.com",
    "wof:name":"Stone House Inn",
    "wof:placetype":"venue"
},
  "geometry": {"coordinates":[-75.963859,43.504516],"type":"Point"}
}