{
  "type": "Feature",
  "properties": {
    "addr:full":"517 Lafayette Ave Buffalo NY 14222",
    "addr:housenumber":"517",
    "addr:postcode":"14222",
    "addr:street":"Lafayette Ave",
    "iso:country":"US",
    "sg:address":"517 Lafayette Ave",
    "sg:city":"Buffalo",
    "sg:classifiers":[
        {
            "category":"Professional",
            "type":"Services"
        }
    ],
    "sg:phone":"+1 716 689 3245",
    "sg:postcode":"14222",
    "sg:province":"NY",
    "wof:name":"Vital Netwok Svc",
    "wof:placetype":"venue"
},
  "geometry": {"coordinates":[-78.879733,42.920224],"type":"Point"}
}