{
  "type": "Feature",
  "properties": {
    "addr:full":"424 Shaker Run Albany NY 12205",
    "addr:housenumber":"424",
    "addr:postcode":"12205",
    "addr:street":"Shaker Run",
    "iso:country":"US",
    "sg:address":"424 Shaker Run",
    "sg:city":"Albany",
    "sg:classifiers":[
        {
            "category":"Organizations",
            "subcategory":"Religious Organization",
            "type":"Services"
        }
    ],
    "sg:phone":"+1 518 456 8269",
    "sg:postcode":"12205",
    "sg:province":"NY",
    "sg:tags":[
        "clergy"
    ],
    "wof:name":"John Waldon",
    "wof:placetype":"venue"
},
  "geometry": {"coordinates":[-73.82370899999999,42.729698],"type":"Point"}
}