{
  "type": "Feature",
  "properties": {
    "addr:full":"1029 73rd Street Brooklyn NY 11228",
    "addr:housenumber":"1029",
    "addr:postcode":"11228",
    "addr:street":"73Rd Street",
    "iso:country":"US",
    "sg:address":"1029 73rd Street",
    "sg:city":"Brooklyn",
    "sg:classifiers":[
        {
            "category":"Building & Trades",
            "subcategory":"Plumbing",
            "type":"Services"
        }
    ],
    "sg:phone":"+1 718 491 3023",
    "sg:postcode":"11228",
    "sg:province":"NY",
    "wof:name":"Zw Plumbing & Heating Corporation",
    "wof:placetype":"venue"
},
  "geometry": {"coordinates":[-74.01202499999999,40.625124],"type":"Point"}
}