{
  "type": "Feature",
  "properties": {
    "iso:country":"US",
    "sg:address":"6917 5th Ave",
    "sg:city":"Brooklyn",
    "sg:classifiers":[
        {
            "category":"Shopping",
            "subcategory":"Catalog Store",
            "type":"Retail Goods"
        }
    ],
    "sg:phone":"+1   ",
    "sg:postcode":"11209",
    "sg:province":"NY",
    "sg:tags":[
        "blind",
        "mail",
        "carpet",
        "venetian",
        "order"
    ],
    "wof:name":"Haggar of New York Inc",
    "wof:placetype":"venue"
},
  "geometry": {"coordinates":[-74.02125700000001,40.632702],"type":"Point"}
}