{
  "type": "Feature",
  "properties": {
    "iso:country":"US",
    "sg:address":"1066 Ogden Ave",
    "sg:city":"Bronx",
    "sg:classifiers":[
        {
            "category":"Personal",
            "subcategory":"Beauty Salon",
            "type":"Services"
        }
    ],
    "sg:phone":"+1 718 410 2131",
    "sg:postcode":"10452",
    "sg:province":"NY",
    "sg:tags":[
        "hair"
    ],
    "wof:name":"Tati Y Tita Barber Shop",
    "wof:placetype":"venue"
},
  "geometry": {"coordinates":[-73.9282,40.834801],"type":"Point"}
}