{
  "type": "Feature",
  "properties": {
    "addr:full":"446 3rd Ave Pelham NY 10803",
    "addr:housenumber":"446",
    "addr:postcode":"10803",
    "addr:street":"3Rd Ave",
    "iso:country":"US",
    "sg:address":"446 3rd Ave",
    "sg:city":"Pelham",
    "sg:classifiers":[
        {
            "category":"Wholesale",
            "subcategory":"Electrical",
            "type":"Manufacturing & Wholesale Goods"
        }
    ],
    "sg:phone":"+1 914 738 2746",
    "sg:postcode":"10803",
    "sg:province":"NY",
    "sg:tags":[
        "alarm",
        "burglar",
        "system"
    ],
    "wof:name":"Guardian Security Corp",
    "wof:placetype":"venue"
},
  "geometry": {"coordinates":[-73.80797200000001,40.918197],"type":"Point"}
}