{
  "type": "Feature",
  "properties": {
    "iso:country":"US",
    "sg:address":"120 Stringham Rd",
    "sg:city":"Lagrangeville",
    "sg:classifiers":[
        {
            "category":"Recreation",
            "type":"Entertainment"
        }
    ],
    "sg:phone":"+1 845 452 1972",
    "sg:postcode":"12540",
    "sg:province":"NY",
    "sg:tags":[
        "center"
    ],
    "wof:name":"LA Grange Recreation Director",
    "wof:placetype":"venue"
},
  "geometry": {"coordinates":[-73.796949,41.660683],"type":"Point"}
}