{
  "type": "Feature",
  "properties": {
    "iso:country":"US",
    "sg:address":"727 University Ave",
    "sg:city":"Rochester",
    "sg:classifiers":[
        {
            "category":"Taxi",
            "type":"Transportation"
        }
    ],
    "sg:phone":"+1   ",
    "sg:postcode":"14607",
    "sg:province":"NY",
    "sg:tags":[
        "taxicab"
    ],
    "wof:name":"Peters Taxi",
    "wof:placetype":"venue"
},
  "geometry": {"coordinates":[-77.582576,43.15513],"type":"Point"}
}