{
  "type": "Feature",
  "properties": {
    "addr:full":"469 Dekalb Ave Brooklyn NY 11205",
    "addr:housenumber":"469",
    "addr:postcode":"11205",
    "addr:street":"Dekalb Ave",
    "iso:country":"US",
    "sg:address":"469 Dekalb Ave",
    "sg:city":"Brooklyn",
    "sg:classifiers":[
        {
            "category":"Professional",
            "subcategory":"Accounting & Tax Preparation",
            "type":"Services"
        }
    ],
    "sg:phone":"+1 718 230 0040",
    "sg:postcode":"11205",
    "sg:province":"NY",
    "sg:tags":[
        "return",
        "filing"
    ],
    "wof:name":"Ideal Tax Solutions LLC",
    "wof:placetype":"venue"
},
  "geometry": {"coordinates":[-73.957425,40.690747],"type":"Point"}
}