{
  "type": "Feature",
  "properties": {
    "addr:full":"44 Churchill Ln Smithtown NY 11787",
    "addr:housenumber":"44",
    "addr:postcode":"11787",
    "addr:street":"Churchill Ln",
    "iso:country":"US",
    "sg:address":"44 Churchill Ln",
    "sg:city":"Smithtown",
    "sg:classifiers":[
        {
            "category":"Building & Trades",
            "subcategory":"Plumbing",
            "type":"Services"
        }
    ],
    "sg:phone":"+1 631 864 1316",
    "sg:postcode":"11787",
    "sg:province":"NY",
    "sg:tags":[
        "plumber",
        "industrial",
        "contractors-commercial"
    ],
    "wof:name":"Miller Plumbing Company",
    "wof:placetype":"venue"
},
  "geometry": {"coordinates":[-73.248732,40.842931],"type":"Point"}
}