{
  "type": "Feature",
  "properties": {
    "addr:full":"170 E 3rd St Mount Vernon NY 10550",
    "addr:housenumber":"170",
    "addr:postcode":"10550",
    "addr:street":"E 3Rd St",
    "iso:country":"US",
    "sg:address":"170 E 3rd St",
    "sg:city":"Mount Vernon",
    "sg:classifiers":[
        {
            "category":"Personal",
            "subcategory":"Beauty Salon",
            "type":"Services"
        }
    ],
    "sg:phone":"+1 914 668 3165",
    "sg:postcode":"10550",
    "sg:province":"NY",
    "sg:tags":[
        "shop"
    ],
    "wof:name":"Trim Time Hair Salon",
    "wof:placetype":"venue"
},
  "geometry": {"coordinates":[-73.829094,40.90819],"type":"Point"}
}