{
  "type": "Feature",
  "properties": {
    "iso:country":"US",
    "sg:address":"1425 Main St",
    "sg:city":"Niagara Falls",
    "sg:classifiers":[
        {
            "category":"Government",
            "subcategory":"Office",
            "type":"Public Place"
        }
    ],
    "sg:phone":"+1 716 286 4926",
    "sg:postcode":"14305",
    "sg:province":"NY",
    "sg:tags":[
        "administrative",
        "program",
        "health"
    ],
    "wof:name":"Niagara Falls Humn Rights Comm",
    "wof:placetype":"venue"
},
  "geometry": {"coordinates":[-79.052024,43.102468],"type":"Point"}
}