{
  "type": "Feature",
  "properties": {
    "addr:full":"116 E Hoffman Ave Lindenhurst NY 11757",
    "addr:housenumber":"116",
    "addr:postcode":"11757",
    "addr:street":"E Hoffman Ave",
    "iso:country":"US",
    "sg:address":"116 E Hoffman Ave",
    "sg:city":"Lindenhurst",
    "sg:classifiers":[
        {
            "category":"Wholesale",
            "subcategory":"Electrical",
            "type":"Manufacturing & Wholesale Goods"
        }
    ],
    "sg:phone":"+1 631 957 1234",
    "sg:postcode":"11757",
    "sg:province":"NY",
    "sg:tags":[
        "sound",
        "equipment",
        "system"
    ],
    "wof:name":"Ashford Audio Prods Co Inc",
    "wof:placetype":"venue"
},
  "geometry": {"coordinates":[-73.36731399999999,40.689002],"type":"Point"}
}