{
  "type": "Feature",
  "properties": {
    "iso:country":"US",
    "sg:address":"138 Radio Ave",
    "sg:city":"Miller Place",
    "sg:classifiers":[
        {
            "category":"Social Services",
            "subcategory":"Child Care",
            "type":"Services"
        }
    ],
    "sg:phone":"+1 631 821 0474",
    "sg:postcode":"11764",
    "sg:province":"NY",
    "sg:tags":[
        "kindergarten",
        "academic",
        "school"
    ],
    "wof:name":"Step By Step Montessori Ctr",
    "wof:placetype":"venue"
},
  "geometry": {"coordinates":[-72.964552,40.926452],"type":"Point"}
}