{
  "type": "Feature",
  "properties": {
    "iso:country":"US",
    "sg:address":"290 Drewville Rd",
    "sg:city":"Carmel",
    "sg:classifiers":[
        {
            "category":"Organizations",
            "subcategory":"Membership Organization",
            "type":"Services"
        }
    ],
    "sg:phone":"+1 845 628 7669",
    "sg:postcode":"10512",
    "sg:province":"NY",
    "sg:tags":[
        "executive"
    ],
    "wof:name":"Putnam County Fish & Game Assn",
    "wof:placetype":"venue"
},
  "geometry": {"coordinates":[-73.694929,41.389145],"type":"Point"}
}