{
  "type": "Feature",
  "properties": {
    "addr:full":"3244 Lucerne St Bronx NY 10465",
    "addr:housenumber":"3244",
    "addr:postcode":"10465",
    "addr:street":"Lucerne St",
    "iso:country":"US",
    "sg:address":"3244 Lucerne St",
    "sg:city":"Bronx",
    "sg:classifiers":[
        {
            "category":"Building & Trades",
            "subcategory":"Construction",
            "type":"Services"
        }
    ],
    "sg:phone":"+1 718 430 9285",
    "sg:postcode":"10465",
    "sg:province":"NY",
    "sg:tags":[
        "woodworker"
    ],
    "wof:name":"Mc Donnell Woodworking",
    "wof:placetype":"venue"
},
  "geometry": {"coordinates":[-73.818472,40.842814],"type":"Point"}
}