{
  "type": "Feature",
  "properties": {
    "iso:country":"US",
    "sg:address":"425 Rabro Dr",
    "sg:city":"Hauppauge",
    "sg:classifiers":[
        {
            "category":"Manufacturing",
            "subcategory":"Electronics",
            "type":"Manufacturing & Wholesale Goods"
        }
    ],
    "sg:phone":"+1 631 273 9700",
    "sg:postcode":"11788",
    "sg:province":"NY",
    "sg:tags":[
        "equipment",
        "electronic",
        "supply"
    ],
    "sg:website":"www.rvsi.com",
    "wof:name":"RVSI Electronics Div",
    "wof:placetype":"venue"
},
  "geometry": {"coordinates":[-73.21502099999999,40.813167],"type":"Point"}
}