{
  "type": "Feature",
  "properties": {
    "iso:country":"US",
    "sg:address":"158 Church St",
    "sg:city":"Millbrook",
    "sg:classifiers":[
        {
            "category":"Health Services",
            "subcategory":"Nursing And Care Facility",
            "type":"Services"
        }
    ],
    "sg:phone":"+1 845 677 1400",
    "sg:postcode":"12545",
    "sg:province":"NY",
    "sg:tags":[
        "hospice"
    ],
    "wof:name":"Hospice Inc",
    "wof:placetype":"venue"
},
  "geometry": {"coordinates":[-73.693916,41.785343],"type":"Point"}
}