{
  "type": "Feature",
  "properties": {
    "addr:full":"836 Goodman St N Rochester NY 14609",
    "addr:housenumber":"836",
    "addr:postcode":"14609",
    "addr:street":"Goodman St N",
    "iso:country":"US",
    "sg:address":"836 Goodman St N",
    "sg:city":"Rochester",
    "sg:classifiers":[
        {
            "category":"Building & Trades",
            "subcategory":"Equipment Rental",
            "type":"Services"
        }
    ],
    "sg:phone":"+1 585 288 4130",
    "sg:postcode":"14609",
    "sg:province":"NY",
    "wof:name":"Rent-Way",
    "wof:placetype":"venue"
},
  "geometry": {"coordinates":[-77.579266,43.169822],"type":"Point"}
}