{
  "type": "Feature",
  "properties": {
    "iso:country":"US",
    "sg:address":"1177 Lincoln Ave",
    "sg:city":"Lockport",
    "sg:classifiers":[
        {
            "category":"Food & Beverages",
            "subcategory":"Liquor & Beverages",
            "type":"Retail Goods"
        }
    ],
    "sg:phone":"+1 716 439 1214",
    "sg:postcode":"14094",
    "sg:province":"NY",
    "wof:name":"Lincoln Square Wine & Spirits",
    "wof:placetype":"venue"
},
  "geometry": {"coordinates":[-78.66682,43.153273],"type":"Point"}
}