{
  "type": "Feature",
  "properties": {
    "addr:full":"22 State Hwy 59 Suffern NY 10901",
    "addr:housenumber":"22",
    "addr:postcode":"10901",
    "addr:street":"State Hwy 59",
    "iso:country":"US",
    "sg:address":"22 State Hwy 59",
    "sg:city":"Suffern",
    "sg:classifiers":[
        {
            "category":"Restaurant",
            "type":"Food & Drink"
        }
    ],
    "sg:phone":"+1 845 357 7767",
    "sg:postcode":"10901",
    "sg:province":"NY",
    "wof:name":"Nicky's Pizza & Heroes Shop",
    "wof:placetype":"venue"
},
  "geometry": {"coordinates":[-74.159485,41.121124],"type":"Point"}
}