{
  "type": "Feature",
  "properties": {
    "iso:country":"US",
    "sg:address":"35 Hicks Ln",
    "sg:city":"Great Neck",
    "sg:classifiers":[
        {
            "category":"Professional",
            "subcategory":"Advertising",
            "type":"Services"
        }
    ],
    "sg:phone":"+1   ",
    "sg:postcode":"11024",
    "sg:province":"NY",
    "wof:name":"New Earth Productions",
    "wof:placetype":"venue"
},
  "geometry": {"coordinates":[-73.730527,40.806491],"type":"Point"}
}