{
  "type": "Feature",
  "properties": {
    "addr:full":"425 Park Ave New York NY 10022",
    "addr:housenumber":"425",
    "addr:postcode":"10022",
    "addr:street":"Park Ave",
    "iso:country":"US",
    "sg:address":"425 Park Ave",
    "sg:city":"New York",
    "sg:classifiers":[
        {
            "category":"Professional",
            "subcategory":"Business Services",
            "type":"Services"
        }
    ],
    "sg:phone":"+1   ",
    "sg:postcode":"10022",
    "sg:province":"NY",
    "wof:name":"Pinci & Associates",
    "wof:placetype":"venue"
},
  "geometry": {"coordinates":[-73.97126299999999,40.760745],"type":"Point"}
}