{
  "type": "Feature",
  "properties": {
    "addr:full":"304 Mulberry St New York NY 10012",
    "addr:housenumber":"304",
    "addr:postcode":"10012",
    "addr:street":"Mulberry St",
    "iso:country":"US",
    "sg:address":"304 Mulberry St",
    "sg:city":"New York",
    "sg:classifiers":[
        {
            "category":"Building & Trades",
            "subcategory":"Construction",
            "type":"Services"
        }
    ],
    "sg:phone":"+1 212 219 0198",
    "sg:postcode":"10012",
    "sg:province":"NY",
    "sg:tags":[
        "house"
    ],
    "wof:name":"Naca Development Co Inc",
    "wof:placetype":"venue"
},
  "geometry": {"coordinates":[-73.99454799999999,40.725413],"type":"Point"}
}