{
  "type": "Feature",
  "properties": {
    "iso:country":"US",
    "sg:address":"16 E 41st St",
    "sg:city":"New York",
    "sg:classifiers":[
        {
            "category":"Health Services",
            "subcategory":"Dentist",
            "type":"Services"
        }
    ],
    "sg:phone":"+1 212 643 0474",
    "sg:postcode":"10017",
    "sg:province":"NY",
    "wof:name":"Kyung-Hee Chin",
    "wof:placetype":"venue"
},
  "geometry": {"coordinates":[-73.980575,40.752327],"type":"Point"}
}