{
  "type": "Feature",
  "properties": {
    "addr:full":"10 E 39 St New York NY 10016",
    "addr:housenumber":"10;39",
    "addr:postcode":"10016",
    "addr:street":"E;St",
    "iso:country":"US",
    "sg:address":"10 E 39 St",
    "sg:city":"New York",
    "sg:classifiers":[
        {
            "category":"Professional",
            "subcategory":"Management & Consulting",
            "type":"Services"
        }
    ],
    "sg:phone":"+1 917 783 5501",
    "sg:postcode":"10016",
    "sg:province":"NY",
    "sg:tags":[
        "consultant"
    ],
    "wof:name":"Denko Consulting",
    "wof:placetype":"venue"
},
  "geometry": {"coordinates":[-73.981196,40.751108],"type":"Point"}
}