{
  "type": "Feature",
  "properties": {
    "addr:full":"41 South St Patterson NY 12563",
    "addr:housenumber":"41",
    "addr:postcode":"12563",
    "addr:street":"South St",
    "iso:country":"US",
    "sg:address":"41 South St",
    "sg:city":"Patterson",
    "sg:classifiers":[
        {
            "category":"Building & Trades",
            "subcategory":"Construction",
            "type":"Services"
        }
    ],
    "sg:phone":"+1 845 878 4695",
    "sg:postcode":"12563",
    "sg:province":"NY",
    "sg:tags":[
        "general",
        "contractor"
    ],
    "wof:name":"A & M Contracting",
    "wof:placetype":"venue"
},
  "geometry": {"coordinates":[-73.605737,41.512617],"type":"Point"}
}