{
  "type": "Feature",
  "properties": {
    "addr:full":"4106 Junction Blvd Corona NY 11368",
    "addr:housenumber":"4106",
    "addr:postcode":"11368",
    "addr:street":"Junction Blvd",
    "iso:country":"US",
    "sg:address":"4106 Junction Blvd",
    "sg:city":"Corona",
    "sg:classifiers":[
        {
            "category":"Food & Beverages",
            "subcategory":"Groceries & Convenience Stores",
            "type":"Retail Goods"
        }
    ],
    "sg:phone":"+1 718 205 7150",
    "sg:postcode":"11368",
    "sg:province":"NY",
    "wof:name":"3 Star Grocery",
    "wof:placetype":"venue"
},
  "geometry": {"coordinates":[-73.868668,40.747374],"type":"Point"}
}