{
  "type": "Feature",
  "properties": {
    "addr:full":"2025 Continental Ave Bronx NY 10461",
    "addr:housenumber":"2025",
    "addr:postcode":"10461",
    "addr:street":"Continental Ave",
    "iso:country":"US",
    "sg:address":"2025 Continental Ave",
    "sg:city":"Bronx",
    "sg:classifiers":[
        {
            "category":"Building & Trades",
            "subcategory":"Electrical",
            "type":"Services"
        }
    ],
    "sg:phone":"+1 718 597 3937",
    "sg:postcode":"10461",
    "sg:province":"NY",
    "sg:tags":[
        "electric",
        "contractor"
    ],
    "wof:name":"June Electric Corp",
    "wof:placetype":"venue"
},
  "geometry": {"coordinates":[-73.83082899999999,40.85365],"type":"Point"}
}