{
  "type": "Feature",
  "properties": {
    "addr:full":"4515 New Utrecht Ave Brooklyn NY 11219",
    "addr:housenumber":"4515",
    "addr:postcode":"11219",
    "addr:street":"New Utrecht Ave",
    "iso:country":"US",
    "sg:address":"4515 New Utrecht Ave",
    "sg:city":"Brooklyn",
    "sg:classifiers":[
        {
            "category":"Home & Garden",
            "subcategory":"Furniture",
            "type":"Retail Goods"
        }
    ],
    "sg:phone":"+1 718 853 6900",
    "sg:postcode":"11219",
    "sg:province":"NY",
    "sg:tags":[
        "store"
    ],
    "sg:website":"www.regalfurniture.com",
    "wof:name":"Regal Furniture",
    "wof:placetype":"venue"
},
  "geometry": {"coordinates":[-73.99430099999999,40.639301],"type":"Point"}
}