{
  "type": "Feature",
  "properties": {
    "iso:country":"US",
    "sg:address":"5 Deerpath Dr",
    "sg:city":"Lancaster",
    "sg:classifiers":[
        {
            "category":"Travel",
            "subcategory":"Travel Agent",
            "type":"Entertainment"
        }
    ],
    "sg:phone":"+1 716 683 2399",
    "sg:postcode":"14086",
    "sg:province":"NY",
    "sg:tags":[
        "agency",
        "bureau"
    ],
    "wof:name":"Upstate New York Travel Inc",
    "wof:placetype":"venue"
},
  "geometry": {"coordinates":[-78.67859799999999,42.929997],"type":"Point"}
}