{
  "type": "Feature",
  "properties": {
    "addr:full":"3111 E Main St Endwell NY 13760",
    "addr:housenumber":"3111",
    "addr:postcode":"13760",
    "addr:street":"E Main St",
    "iso:country":"US",
    "sg:address":"3111 E Main St",
    "sg:city":"Endwell",
    "sg:classifiers":[
        {
            "category":"Government",
            "subcategory":"Office",
            "type":"Public Place"
        }
    ],
    "sg:phone":"+1 607 786 2997",
    "sg:postcode":"13760",
    "sg:province":"NY",
    "sg:tags":[
        "village"
    ],
    "wof:name":"Union Town Board",
    "wof:placetype":"venue"
},
  "geometry": {"coordinates":[-76.02656899999999,42.106305],"type":"Point"}
}