{
  "type": "Feature",
  "properties": {
    "iso:country":"US",
    "sg:address":"2879 Long Beach Rd",
    "sg:city":"Oceanside",
    "sg:classifiers":[
        {
            "category":"Autos & Motor Vehicles",
            "subcategory":"Fuel & Gas Station",
            "type":"Retail Goods"
        }
    ],
    "sg:phone":"+1 516 766 9885",
    "sg:postcode":"11572",
    "sg:province":"NY",
    "sg:tags":[
        "oil"
    ],
    "wof:name":"Three B Corp",
    "wof:placetype":"venue"
},
  "geometry": {"coordinates":[-73.640203,40.641709],"type":"Point"}
}