{
  "type": "Feature",
  "properties": {
    "iso:country":"US",
    "sg:address":"270 Spagnoli Rd",
    "sg:city":"Melville",
    "sg:classifiers":[
        {
            "category":"Manufacturing",
            "subcategory":"Tools & Machinery",
            "type":"Manufacturing & Wholesale Goods"
        }
    ],
    "sg:phone":"+1   ",
    "sg:postcode":"11747",
    "sg:province":"NY",
    "sg:tags":[
        "computer",
        "electronic",
        "mfg"
    ],
    "wof:name":"Nuwave Resources Inc",
    "wof:placetype":"venue"
},
  "geometry": {"coordinates":[-73.42613299999999,40.762539],"type":"Point"}
}