{
  "type": "Feature",
  "properties": {
    "iso:country":"US",
    "sg:address":"601 Vickers St",
    "sg:city":"Tonawanda",
    "sg:classifiers":[
        {
            "category":"Wholesale",
            "subcategory":"Auto Parts",
            "type":"Manufacturing & Wholesale Goods"
        }
    ],
    "sg:phone":"+1 716 694 0200",
    "sg:postcode":"14150",
    "sg:province":"NY",
    "sg:tags":[
        "automotive",
        "supply"
    ],
    "wof:name":"Middle Atlantic Whse Distr In",
    "wof:placetype":"venue"
},
  "geometry": {"coordinates":[-78.85603500000001,43.012155],"type":"Point"}
}