{
  "type": "Feature",
  "properties": {
    "addr:full":"1723 Emmons Ave Brooklyn NY 11235",
    "addr:housenumber":"1723",
    "addr:postcode":"11235",
    "addr:street":"Emmons Ave",
    "iso:country":"US",
    "sg:address":"1723 Emmons Ave",
    "sg:city":"Brooklyn",
    "sg:classifiers":[
        {
            "category":"Building & Trades",
            "subcategory":"Locksmith",
            "type":"Services"
        }
    ],
    "sg:phone":"+1 347 554 2808",
    "sg:postcode":"11235",
    "sg:province":"NY",
    "sg:tags":[
        "key"
    ],
    "wof:name":"12345 Lock Drive",
    "wof:placetype":"venue"
},
  "geometry": {"coordinates":[-73.951222,40.583548],"type":"Point"}
}