{
  "type": "Feature",
  "properties": {
    "addr:full":"45 Henry St New York NY 10002",
    "addr:housenumber":"45",
    "addr:postcode":"10002",
    "addr:street":"Henry St",
    "iso:country":"US",
    "sg:address":"45 Henry St",
    "sg:city":"New York",
    "sg:classifiers":[
        {
            "category":"Restaurant",
            "type":"Food & Drink"
        }
    ],
    "sg:phone":"+1 212 608 2303",
    "sg:postcode":"10002",
    "sg:province":"NY",
    "sg:tags":[
        "chinese"
    ],
    "wof:name":"Wu Qi Wen",
    "wof:placetype":"venue"
},
  "geometry": {"coordinates":[-73.994698,40.713001],"type":"Point"}
}