{
  "type": "Feature",
  "properties": {
    "addr:full":"Iavarrone Bros 1166 Wantagh Avenue Wantagh NY 11793",
    "addr:housenumber":"1166",
    "addr:postcode":"11793",
    "addr:street":"Wantagh Avenue",
    "iso:country":"US",
    "sg:address":"Iavarrone Bros 1166 Wantagh Avenue",
    "sg:city":"Wantagh",
    "sg:classifiers":[
        {
            "category":"Restaurant",
            "type":"Food & Drink"
        }
    ],
    "sg:phone":"+1 516 781 6400",
    "sg:postcode":"11793",
    "sg:province":"NY",
    "sg:tags":[
        "italian"
    ],
    "sg:website":"www.ibfoods.com/cafe/",
    "wof:name":"Backroom Trattoria",
    "wof:placetype":"venue"
},
  "geometry": {"coordinates":[-73.50750499999999,40.694685],"type":"Point"}
}