{
  "type": "Feature",
  "properties": {
    "addr:full":"1250 County Line Rd Schenectady NY 12306",
    "addr:housenumber":"1250",
    "addr:postcode":"12306",
    "addr:street":"County Line Rd",
    "iso:country":"US",
    "sg:address":"1250 County Line Rd",
    "sg:city":"Schenectady",
    "sg:classifiers":[
        {
            "category":"Organizations",
            "subcategory":"Religious Organization",
            "type":"Services"
        }
    ],
    "sg:phone":"+1 518 356 8154",
    "sg:postcode":"12306",
    "sg:province":"NY",
    "sg:tags":[
        "clergy"
    ],
    "wof:name":"Andrew Whitney",
    "wof:placetype":"venue"
},
  "geometry": {"coordinates":[-73.982404,42.754308],"type":"Point"}
}