{
  "type": "Feature",
  "properties": {
    "addr:full":"509 5th Ave Brooklyn NY 11215",
    "addr:housenumber":"509",
    "addr:postcode":"11215",
    "addr:street":"5Th Ave",
    "iso:country":"US",
    "sg:address":"509 5th Ave",
    "sg:city":"Brooklyn",
    "sg:classifiers":[
        {
            "category":"Shopping",
            "subcategory":"Clothing, Apparel, & Fashions",
            "type":"Retail Goods"
        }
    ],
    "sg:phone":"+1   ",
    "sg:postcode":"11215",
    "sg:province":"NY",
    "wof:name":"Mandee",
    "wof:placetype":"venue"
},
  "geometry": {"coordinates":[-73.98795699999999,40.667182],"type":"Point"}
}