{
  "type": "Feature",
  "properties": {
    "iso:country":"US",
    "sg:address":"38 Robeson Blvd",
    "sg:city":"Sag Harbor",
    "sg:classifiers":[
        {
            "category":"Professional",
            "type":"Services"
        }
    ],
    "sg:phone":"+1   ",
    "sg:postcode":"11963",
    "sg:province":"NY",
    "wof:name":"Bruce Milne",
    "wof:placetype":"venue"
},
  "geometry": {"coordinates":[-72.281622,40.99101],"type":"Point"}
}