{
  "type": "Feature",
  "properties": {
    "iso:country":"US",
    "sg:address":"887 Co Rte 6",
    "sg:city":"Germantown",
    "sg:classifiers":[
        {
            "category":"Shopping",
            "subcategory":"Bicycles & Sporting Goods",
            "type":"Retail Goods"
        }
    ],
    "sg:phone":"+1 518 537 6915",
    "sg:postcode":"12526",
    "sg:province":"NY",
    "wof:name":"Ron's Sports Shop",
    "wof:placetype":"venue"
},
  "geometry": {"coordinates":[-73.853126,42.083733],"type":"Point"}
}