{
  "type": "Feature",
  "properties": {
    "addr:full":"1632 N Forest Rd Buffalo NY 14221",
    "addr:housenumber":"1632",
    "addr:postcode":"14221",
    "addr:street":"N Forest Rd",
    "iso:country":"US",
    "sg:address":"1632 N Forest Rd",
    "sg:city":"Buffalo",
    "sg:classifiers":[
        {
            "category":"Arts & Performance",
            "subcategory":"Theater",
            "type":"Entertainment"
        }
    ],
    "sg:phone":"+1 716 688 1146",
    "sg:postcode":"14221",
    "sg:province":"NY",
    "sg:tags":[
        "group"
    ],
    "wof:name":"Frankfurters",
    "wof:placetype":"venue"
},
  "geometry": {"coordinates":[-78.760884,43.000913],"type":"Point"}
}