{
  "type": "Feature",
  "properties": {
    "iso:country":"US",
    "sg:address":"750 Lee Rd",
    "sg:city":"Rochester",
    "sg:classifiers":[
        {
            "category":"Retail",
            "subcategory":"Auto Repair",
            "type":"Services"
        }
    ],
    "sg:phone":"+1 585 458 0100",
    "sg:postcode":"14606",
    "sg:province":"NY",
    "sg:tags":[
        "body"
    ],
    "wof:name":"Cristo West Collision",
    "wof:placetype":"venue"
},
  "geometry": {"coordinates":[-77.68047,43.181216],"type":"Point"}
}