{
  "type": "Feature",
  "properties": {
    "addr:full":"1415 Old Northern Blvd Roslyn NY 11576",
    "addr:housenumber":"1415",
    "addr:postcode":"11576",
    "addr:street":"Old Northern Blvd",
    "iso:country":"US",
    "sg:address":"1415 Old Northern Blvd",
    "sg:city":"Roslyn",
    "sg:classifiers":[
        {
            "category":"Personal",
            "subcategory":"Beauty Salon",
            "type":"Services"
        }
    ],
    "sg:phone":"+1 516 621 5402",
    "sg:postcode":"11576",
    "sg:province":"NY",
    "sg:tags":[
        "treatment",
        "skin"
    ],
    "wof:name":"Marcia Personalized Skin Care",
    "wof:placetype":"venue"
},
  "geometry": {"coordinates":[-73.646608,40.802921],"type":"Point"}
}