{
  "type": "Feature",
  "properties": {
    "addr:full":"3739 74th St Jackson Heights NY 11372",
    "addr:housenumber":"3739",
    "addr:postcode":"11372",
    "addr:street":"74Th St",
    "iso:country":"US",
    "sg:address":"3739 74th St",
    "sg:city":"Jackson Heights",
    "sg:classifiers":[
        {
            "category":"Insurance",
            "subcategory":"Health Insurance",
            "type":"Services"
        }
    ],
    "sg:phone":"+1 718 672 2312",
    "sg:postcode":"11372",
    "sg:province":"NY",
    "sg:tags":[
        "market"
    ],
    "wof:name":"Gnc",
    "wof:placetype":"venue"
},
  "geometry": {"coordinates":[-73.891502,40.748001],"type":"Point"}
}