{
  "type": "Feature",
  "properties": {
    "addr:full":"40 Autumn Dr Slingerlands NY 12159",
    "addr:housenumber":"40",
    "addr:postcode":"12159",
    "addr:street":"Autumn Dr",
    "iso:country":"US",
    "sg:address":"40 Autumn Dr",
    "sg:city":"Slingerlands",
    "sg:classifiers":[
        {
            "category":"Real Estate",
            "subcategory":"Real Estate Operator",
            "type":"Services"
        }
    ],
    "sg:phone":"+1 518 482 8774",
    "sg:postcode":"12159",
    "sg:province":"NY",
    "sg:tags":[
        "residential",
        "retirement",
        "facility"
    ],
    "wof:name":"Beverwyck Retirement Community",
    "wof:placetype":"venue"
},
  "geometry": {"coordinates":[-73.838481,42.65854],"type":"Point"}
}