{
  "type": "Feature",
  "properties": {
    "iso:country":"US",
    "sg:address":"3065 Co Rte 2",
    "sg:city":"Pulaski",
    "sg:classifiers":[
        {
            "category":"Farming",
            "subcategory":"Farm",
            "type":"Manufacturing & Wholesale Goods"
        }
    ],
    "sg:phone":"+1 315 298 4902",
    "sg:postcode":"13142",
    "sg:province":"NY",
    "sg:tags":[
        "dairy",
        "crop",
        "general"
    ],
    "wof:name":"Mandigo Farm",
    "wof:placetype":"venue"
},
  "geometry": {"coordinates":[-76.107891,43.567481],"type":"Point"}
}