{
  "type": "Feature",
  "properties": {
    "addr:full":"200 Boscombe Avenue Staten Island NY 10309",
    "addr:housenumber":"200",
    "addr:postcode":"10309",
    "addr:street":"Boscombe Avenue",
    "iso:country":"US",
    "sg:address":"200 Boscombe Avenue",
    "sg:city":"Staten Island",
    "sg:classifiers":[
        {
            "category":"Place Of Worship",
            "subcategory":"Church",
            "type":"Public Place"
        },
        {
            "category":"Education",
            "subcategory":"School",
            "type":"Public Place"
        }
    ],
    "sg:phone":"+1 718 966 4500",
    "sg:postcode":"10309",
    "sg:province":"NY",
    "wof:name":"Gateway Cathedral",
    "wof:placetype":"venue"
},
  "geometry": {"coordinates":[-74.230011,40.524435],"type":"Point"}
}