{
  "type": "Feature",
  "properties": {
    "iso:country":"US",
    "sg:address":"53 Park Pl",
    "sg:city":"New York",
    "sg:classifiers":[
        {
            "category":"Building & Trades",
            "subcategory":"Construction",
            "type":"Services"
        }
    ],
    "sg:phone":"+1 212 943 0830",
    "sg:postcode":"10007",
    "sg:province":"NY",
    "sg:tags":[
        "contractor"
    ],
    "wof:name":"Keeler Paul J Assocs Inc",
    "wof:placetype":"venue"
},
  "geometry": {"coordinates":[-74.009804,40.713501],"type":"Point"}
}