{
  "type": "Feature",
  "properties": {
    "addr:full":"1223 Fort Hunter Rd Schenectady NY 12303",
    "addr:housenumber":"1223",
    "addr:postcode":"12303",
    "addr:street":"Fort Hunter Rd",
    "iso:country":"US",
    "sg:address":"1223 Fort Hunter Rd",
    "sg:city":"Schenectady",
    "sg:classifiers":[
        {
            "category":"Personal",
            "subcategory":"Beauty Salon",
            "type":"Services"
        }
    ],
    "sg:phone":"+1 518 356 0800",
    "sg:postcode":"12303",
    "sg:province":"NY",
    "wof:name":"Karizma Hair Studio",
    "wof:placetype":"venue"
},
  "geometry": {"coordinates":[-73.944406,42.758016],"type":"Point"}
}