{
  "type": "Feature",
  "properties": {
    "addr:full":"274 Retford Avenue Staten Island NY 10312",
    "addr:housenumber":"274",
    "addr:postcode":"10312",
    "addr:street":"Retford Avenue",
    "iso:country":"US",
    "sg:address":"274 Retford Avenue",
    "sg:city":"Staten Island",
    "sg:classifiers":[
        {
            "category":"Professional",
            "type":"Services"
        }
    ],
    "sg:phone":"+1 718 356 9094",
    "sg:postcode":"10312",
    "sg:province":"NY",
    "sg:tags":[
        "caterer"
    ],
    "sg:website":"www.simplyelegantcaterers.com",
    "wof:name":"Simply Elegant Caterers",
    "wof:placetype":"venue"
},
  "geometry": {"coordinates":[-74.156762,40.534015],"type":"Point"}
}