{
  "type": "Feature",
  "properties": {
    "iso:country":"US",
    "sg:address":"13 East Dr",
    "sg:city":"Woodbury",
    "sg:classifiers":[
        {
            "category":"Communications",
            "type":"Services"
        }
    ],
    "sg:phone":"+1 516 695 0440",
    "sg:postcode":"11797",
    "sg:province":"NY",
    "wof:name":"Cbz Media, Inc.",
    "wof:placetype":"venue"
},
  "geometry": {"coordinates":[-73.48508,40.800074],"type":"Point"}
}