{
  "type": "Feature",
  "properties": {
    "iso:country":"US",
    "sg:address":"2024 W Henrietta Rd",
    "sg:city":"Rochester",
    "sg:classifiers":[
        {
            "category":"Professional",
            "subcategory":"Accounting & Tax Preparation",
            "type":"Services"
        }
    ],
    "sg:phone":"+1 585 427 0850",
    "sg:postcode":"14623",
    "sg:province":"NY",
    "sg:tags":[
        "accountant",
        "public",
        "certified"
    ],
    "wof:name":"Stokes Visca & Co L L P",
    "wof:placetype":"venue"
},
  "geometry": {"coordinates":[-77.62466000000001,43.11028],"type":"Point"}
}