{
  "type": "Feature",
  "properties": {
    "addr:full":"449 Broad St Salamanca NY 14779",
    "addr:housenumber":"449",
    "addr:postcode":"14779",
    "addr:street":"Broad St",
    "iso:country":"US",
    "sg:address":"449 Broad St",
    "sg:city":"Salamanca",
    "sg:classifiers":[
        {
            "category":"Health Services",
            "subcategory":"Doctor",
            "type":"Services"
        }
    ],
    "sg:phone":"+1 716 945 4770",
    "sg:postcode":"14779",
    "sg:province":"NY",
    "sg:tags":[
        "physician",
        "surgeon"
    ],
    "wof:name":"Arun P Patel MD",
    "wof:placetype":"venue"
},
  "geometry": {"coordinates":[-78.732304,42.157577],"type":"Point"}
}