{
  "type": "Feature",
  "properties": {
    "addr:full":"214 Front St Owego NY 13827",
    "addr:housenumber":"214",
    "addr:postcode":"13827",
    "addr:street":"Front St",
    "iso:country":"US",
    "sg:address":"214 Front St",
    "sg:city":"Owego",
    "sg:classifiers":[
        {
            "category":"Shopping",
            "subcategory":"Gifts & Souvenirs",
            "type":"Retail Goods"
        }
    ],
    "sg:phone":"+1 607 687 2042",
    "sg:postcode":"13827",
    "sg:province":"NY",
    "sg:tags":[
        "shop"
    ],
    "wof:name":"Goat Boy",
    "wof:placetype":"venue"
},
  "geometry": {"coordinates":[-76.257122,42.104131],"type":"Point"}
}