{
  "type": "Feature",
  "properties": {
    "iso:country":"US",
    "sg:address":"211 High St",
    "sg:city":"Lockport",
    "sg:classifiers":[
        {
            "category":"Health Services",
            "subcategory":"Nursing And Care Facility",
            "type":"Services"
        }
    ],
    "sg:phone":"+1 716 433 8133",
    "sg:postcode":"14094",
    "sg:province":"NY",
    "sg:tags":[
        "for",
        "physically",
        "adult",
        "home",
        "impaired",
        "mentally"
    ],
    "wof:name":"Group Home",
    "wof:placetype":"venue"
},
  "geometry": {"coordinates":[-78.688035,43.164488],"type":"Point"}
}