{
  "type": "Feature",
  "properties": {
    "iso:country":"US",
    "sg:address":"349 W 87 St",
    "sg:city":"New York",
    "sg:classifiers":[
        {
            "category":"Retail",
            "subcategory":"Repair Shop",
            "type":"Services"
        }
    ],
    "sg:phone":"+1 646 224 0772",
    "sg:postcode":"10024",
    "sg:province":"NY",
    "sg:tags":[
        "lock",
        "locksmith"
    ],
    "wof:name":"AAA 24 Hour Number 1 Lcksmth",
    "wof:placetype":"venue"
},
  "geometry": {"coordinates":[-73.978898,40.790162],"type":"Point"}
}