{
  "type": "Feature",
  "properties": {
    "iso:country":"US",
    "sg:address":"581 9th Ave",
    "sg:city":"New York",
    "sg:classifiers":[
        {
            "category":"Organizations",
            "subcategory":"Religious Organization",
            "type":"Services"
        }
    ],
    "sg:phone":"+1 212 244 7640",
    "sg:postcode":"10036",
    "sg:province":"NY",
    "wof:name":"Origins Church",
    "wof:placetype":"venue"
},
  "geometry": {"coordinates":[-73.992868,40.758338],"type":"Point"}
}