{
  "type": "Feature",
  "properties": {
    "iso:country":"US",
    "sg:address":"1430 Broadway",
    "sg:city":"New York",
    "sg:classifiers":[
        {
            "category":"Shopping",
            "subcategory":"Tobacco",
            "type":"Retail Goods"
        }
    ],
    "sg:phone":"+1 212 221 0830",
    "sg:postcode":"10018",
    "sg:province":"NY",
    "sg:tags":[
        "shop"
    ],
    "wof:name":"Joshi Lobby Newstand",
    "wof:placetype":"venue"
},
  "geometry": {"coordinates":[-73.986707,40.75422],"type":"Point"}
}