{
  "type": "Feature",
  "properties": {
    "addr:full":"330 W 42nd St Fl 23 New York NY 10036",
    "addr:housenumber":"330;23",
    "addr:postcode":"10036",
    "addr:street":"W 42Nd St Fl",
    "iso:country":"US",
    "sg:address":"330 W 42nd St Fl 23",
    "sg:city":"New York",
    "sg:classifiers":[
        {
            "category":"Arts & Performance",
            "subcategory":"Arts Center",
            "type":"Entertainment"
        }
    ],
    "sg:phone":"+1 212 239 6200",
    "sg:postcode":"10036",
    "sg:province":"NY",
    "sg:tags":[
        "performing"
    ],
    "wof:name":"Shubert Organization",
    "wof:placetype":"venue"
},
  "geometry": {"coordinates":[-73.990601,40.757599],"type":"Point"}
}