{
  "type": "Feature",
  "properties": {
    "addr:full":"31 E 1st St Oswego NY 13126",
    "addr:housenumber":"31",
    "addr:postcode":"13126",
    "addr:street":"E 1St St",
    "iso:country":"US",
    "sg:address":"31 E 1st St",
    "sg:city":"Oswego",
    "sg:classifiers":[
        {
            "category":"Insurance",
            "subcategory":"Hazard Insurance",
            "type":"Services"
        }
    ],
    "sg:phone":"+1 315 342 4472",
    "sg:postcode":"13126",
    "sg:province":"NY",
    "sg:tags":[
        "commercial",
        "business"
    ],
    "wof:name":"Fitzgibbons Agency",
    "wof:placetype":"venue"
},
  "geometry": {"coordinates":[-76.508647,43.459163],"type":"Point"}
}