{
  "type": "Feature",
  "properties": {
    "iso:country":"US",
    "sg:address":"528 Oak St",
    "sg:city":"Syracuse",
    "sg:classifiers":[
        {
            "category":"Real Estate",
            "subcategory":"Architect",
            "type":"Services"
        }
    ],
    "sg:phone":"+1 315 474 6496",
    "sg:postcode":"13203",
    "sg:province":"NY",
    "wof:name":"Associated Architects-Syracuse",
    "wof:placetype":"venue"
},
  "geometry": {"coordinates":[-76.135554,43.060341],"type":"Point"}
}