{
  "type": "Feature",
  "properties": {
    "addr:full":"230 E 80th St New York NY 10021",
    "addr:housenumber":"230",
    "addr:postcode":"10021",
    "addr:street":"E 80Th St",
    "iso:country":"US",
    "sg:address":"230 E 80th St",
    "sg:city":"New York",
    "sg:classifiers":[
        {
            "category":"Food & Beverages",
            "subcategory":"Groceries & Convenience Stores",
            "type":"Retail Goods"
        }
    ],
    "sg:phone":"+1 212 288 2046",
    "sg:postcode":"10021",
    "sg:province":"NY",
    "wof:name":"Kohinoor Convenience Store",
    "wof:placetype":"venue"
},
  "geometry": {"coordinates":[-73.95610000000001,40.774601],"type":"Point"}
}