{
  "type": "Feature",
  "properties": {
    "addr:full":"4410 Ft. Hamilton Pkwy. Brooklyn NY 11219",
    "addr:postcode":"4410;11219",
    "addr:street":"Ft. Hamilton Pkwy.",
    "iso:country":"US",
    "sg:address":"4410 Ft. Hamilton Pkwy.",
    "sg:city":"Brooklyn",
    "sg:classifiers":[
        {
            "category":"Restaurant",
            "type":"Food & Drink"
        }
    ],
    "sg:phone":"+1 718 435 1014",
    "sg:postcode":"11219",
    "sg:province":"NY",
    "wof:name":"Best Coffee & Donut Shop",
    "wof:placetype":"venue"
},
  "geometry": {"coordinates":[-73.994634,40.640742],"type":"Point"}
}