{
  "type": "Feature",
  "properties": {
    "addr:full":"2607 Seneca Tpke Canastota NY 13032",
    "addr:housenumber":"2607",
    "addr:postcode":"13032",
    "addr:street":"Seneca Tpke",
    "iso:country":"US",
    "sg:address":"2607 Seneca Tpke",
    "sg:city":"Canastota",
    "sg:classifiers":[
        {
            "category":"Home & Garden",
            "subcategory":"Garden Supply",
            "type":"Retail Goods"
        }
    ],
    "sg:phone":"+1 315 697 4070",
    "sg:postcode":"13032",
    "sg:province":"NY",
    "sg:tags":[
        "nurseryman"
    ],
    "wof:name":"Tedd's Pondview Gardens",
    "wof:placetype":"venue"
},
  "geometry": {"coordinates":[-75.800926,43.062719],"type":"Point"}
}