{
  "type": "Feature",
  "properties": {
    "addr:full":"1929 3 Ave New York NY 10029",
    "addr:housenumber":"1929",
    "addr:postcode":"10029",
    "addr:street":"3 Ave",
    "iso:country":"US",
    "sg:address":"1929 3 Ave",
    "sg:city":"New York",
    "sg:classifiers":[
        {
            "category":"Shopping",
            "subcategory":"Discount & Variety Stores",
            "type":"Retail Goods"
        }
    ],
    "sg:phone":"+1 212 360 6484",
    "sg:postcode":"10029",
    "sg:province":"NY",
    "wof:name":"Dollar Choice Inc",
    "wof:placetype":"venue"
},
  "geometry": {"coordinates":[-73.94882699999999,40.785881],"type":"Point"}
}