{
  "type": "Feature",
  "properties": {
    "addr:full":"460 Park Avenue South  10th Floor New York NY 10016",
    "addr:housenumber":"460",
    "addr:postcode":"10016",
    "addr:street":"Park Avenue South 10Th Floor",
    "iso:country":"US",
    "sg:address":"460 Park Avenue South  10th Floor",
    "sg:city":"New York",
    "sg:classifiers":[
        {
            "category":"Professional",
            "subcategory":"Computer Services",
            "type":"Services"
        }
    ],
    "sg:phone":"+1 212 941 9041",
    "sg:postcode":"10016",
    "sg:province":"NY",
    "sg:website":"http://www.heartbeatexperts.com/",
    "wof:name":"Heartbeat Software ",
    "wof:placetype":"venue"
},
  "geometry": {"coordinates":[-73.983177,40.744561],"type":"Point"}
}