{
  "type": "Feature",
  "properties": {
    "addr:full":"3210 Old Rte 22 Patterson NY 10509",
    "addr:housenumber":"3210",
    "addr:postcode":"10509",
    "addr:street":"Old Rte 22",
    "iso:country":"US",
    "sg:address":"3210 Old Rte 22",
    "sg:city":"Patterson",
    "sg:classifiers":[
        {
            "category":"Shopping",
            "subcategory":"Used Merchandise",
            "type":"Retail Goods"
        }
    ],
    "sg:phone":"+1 845 878 7448",
    "sg:postcode":"10509",
    "sg:province":"NY",
    "sg:tags":[
        "antique"
    ],
    "wof:name":"Patterson Antiques",
    "wof:placetype":"venue"
},
  "geometry": {"coordinates":[-73.58202,41.461121],"type":"Point"}
}