{
  "type": "Feature",
  "properties": {
    "addr:full":"68 S Broadway Ave Nyack NY 10960",
    "addr:housenumber":"68",
    "addr:postcode":"10960",
    "addr:street":"S Broadway Ave",
    "iso:country":"US",
    "sg:address":"68 S Broadway Ave",
    "sg:city":"Nyack",
    "sg:classifiers":[
        {
            "category":"Real Estate",
            "subcategory":"Real Estate Agent",
            "type":"Services"
        }
    ],
    "sg:phone":"+1 845 358 8443",
    "sg:postcode":"10960",
    "sg:province":"NY",
    "sg:tags":[
        "inspection"
    ],
    "wof:name":"Excel Home Inspections",
    "wof:placetype":"venue"
},
  "geometry": {"coordinates":[-73.91927,41.087697],"type":"Point"}
}