{
  "type": "Feature",
  "properties": {
    "addr:full":"24-01 23rd Ave Astoria NY 11105",
    "addr:housenumber":"24-01",
    "addr:postcode":"11105",
    "addr:street":"23Rd Ave",
    "iso:country":"US",
    "sg:address":"24-01 23rd Ave",
    "sg:city":"Astoria",
    "sg:classifiers":[
        {
            "category":"Shopping",
            "subcategory":"Clothing, Apparel, & Fashions",
            "type":"Retail Goods"
        }
    ],
    "sg:phone":"+1 718 204 5031",
    "sg:postcode":"11105",
    "sg:province":"NY",
    "sg:tags":[
        "clothing",
        "women's"
    ],
    "sg:website":"www.kristeesny.com",
    "wof:name":"Kris Tees",
    "wof:placetype":"venue"
},
  "geometry": {"coordinates":[-73.917288,40.777487],"type":"Point"}
}