{
  "type": "Feature",
  "properties": {
    "addr:full":"25 Hammond Plz Beacon NY 12508",
    "addr:housenumber":"25",
    "addr:postcode":"12508",
    "addr:street":"Hammond Plz",
    "iso:country":"US",
    "sg:address":"25 Hammond Plz",
    "sg:city":"Beacon",
    "sg:classifiers":[
        {
            "category":"Organizations",
            "subcategory":"Labor Organization",
            "type":"Services"
        }
    ],
    "sg:phone":"+1 845 838 0291",
    "sg:postcode":"12508",
    "sg:province":"NY",
    "sg:tags":[
        "union"
    ],
    "wof:name":"Nyscopba",
    "wof:placetype":"venue"
},
  "geometry": {"coordinates":[-73.981819,41.505669],"type":"Point"}
}