{
  "type": "Feature",
  "properties": {
    "iso:country":"US",
    "sg:address":"5838 Main St",
    "sg:city":"Williamsville",
    "sg:classifiers":[
        {
            "category":"Education",
            "subcategory":"Special Training",
            "type":"Public Place"
        }
    ],
    "sg:phone":"+1 716 633 4565",
    "sg:postcode":"14221",
    "sg:province":"NY",
    "sg:tags":[
        "tutoring"
    ],
    "sg:website":"www.huntingtonlearning.com",
    "wof:name":"Huntington Learning Ctr",
    "wof:placetype":"venue"
},
  "geometry": {"coordinates":[-78.73460799999999,42.964509],"type":"Point"}
}