{
  "type": "Feature",
  "properties": {
    "iso:country":"US",
    "sg:address":"152 Henry St",
    "sg:city":"Binghamton",
    "sg:classifiers":[
        {
            "category":"Wholesale",
            "subcategory":"Groceries",
            "type":"Manufacturing & Wholesale Goods"
        }
    ],
    "sg:phone":"+1 607 724 1444",
    "sg:postcode":"13901",
    "sg:province":"NY",
    "sg:tags":[
        "baker"
    ],
    "wof:name":"Di Rienzo Brothers Bakery",
    "wof:placetype":"venue"
},
  "geometry": {"coordinates":[-75.903925,42.10233],"type":"Point"}
}