{
  "type": "Feature",
  "properties": {
    "iso:country":"US",
    "sg:address":"425 Madison Ave",
    "sg:city":"New York",
    "sg:classifiers":[
        {
            "category":"Manufacturing",
            "subcategory":"Printing",
            "type":"Manufacturing & Wholesale Goods"
        }
    ],
    "sg:phone":"+1 212 688 0085",
    "sg:postcode":"10017",
    "sg:province":"NY",
    "sg:tags":[
        "publisher"
    ],
    "wof:name":"Holiday House",
    "wof:placetype":"venue"
},
  "geometry": {"coordinates":[-73.976283,40.756648],"type":"Point"}
}