{
  "type": "Feature",
  "properties": {
    "iso:country":"US",
    "sg:address":"46 N Ocean Ave",
    "sg:city":"Freeport",
    "sg:classifiers":[
        {
            "category":"Government",
            "subcategory":"Office",
            "type":"Public Place"
        }
    ],
    "sg:phone":"+1 516 377 2200",
    "sg:postcode":"11520",
    "sg:province":"NY",
    "sg:tags":[
        "executive"
    ],
    "wof:name":"Village of Freeport",
    "wof:placetype":"venue"
},
  "geometry": {"coordinates":[-73.587368,40.659132],"type":"Point"}
}