{
  "type": "Feature",
  "properties": {
    "addr:full":"123 Wyckoff Ave Brooklyn NY 11237",
    "addr:housenumber":"123",
    "addr:postcode":"11237",
    "addr:street":"Wyckoff Ave",
    "iso:country":"US",
    "sg:address":"123 Wyckoff Ave",
    "sg:city":"Brooklyn",
    "sg:classifiers":[
        {
            "category":"Food & Beverages",
            "subcategory":"Groceries & Convenience Stores",
            "type":"Retail Goods"
        }
    ],
    "sg:phone":"+1 718 386 9412",
    "sg:postcode":"11237",
    "sg:province":"NY",
    "wof:name":"Tepeojuma Deli Grocery",
    "wof:placetype":"venue"
},
  "geometry": {"coordinates":[-73.919197,40.7043],"type":"Point"}
}