{
  "type": "Feature",
  "properties": {
    "iso:country":"US",
    "sg:address":"30 E Lake Stable Rd",
    "sg:city":"Tuxedo Park",
    "sg:classifiers":[
        {
            "category":"Personal",
            "type":"Services"
        }
    ],
    "sg:phone":"+1 845 351 3395",
    "sg:postcode":"10987",
    "sg:province":"NY",
    "sg:tags":[
        "program",
        "physical",
        "exercise",
        "fitness"
    ],
    "wof:name":"Tuxedo Dance & Fitness",
    "wof:placetype":"venue"
},
  "geometry": {"coordinates":[-74.194705,41.200101],"type":"Point"}
}