{
  "type": "Feature",
  "properties": {
    "addr:full":"805 Middle Neck Rd Great Neck NY 11024",
    "addr:housenumber":"805",
    "addr:postcode":"11024",
    "addr:street":"Middle Neck Rd",
    "iso:country":"US",
    "sg:address":"805 Middle Neck Rd",
    "sg:city":"Great Neck",
    "sg:classifiers":[
        {
            "category":"Food & Beverages",
            "subcategory":"Bakery",
            "type":"Retail Goods"
        }
    ],
    "sg:phone":"+1 516 487 9048",
    "sg:postcode":"11024",
    "sg:province":"NY",
    "sg:tags":[
        "grocery"
    ],
    "wof:name":"Sweet Temptation Desserts",
    "wof:placetype":"venue"
},
  "geometry": {"coordinates":[-73.735749,40.809129],"type":"Point"}
}