{
  "type": "Feature",
  "properties": {
    "iso:country":"US",
    "sg:address":"55 E 59 St",
    "sg:city":"New York",
    "sg:classifiers":[
        {
            "category":"Banks & Credit Unions",
            "subcategory":"Investment Brokerage",
            "type":"Services"
        }
    ],
    "sg:phone":"+1 212 326 9560",
    "sg:postcode":"10022",
    "sg:province":"NY",
    "wof:name":"Joho Capital",
    "wof:placetype":"venue"
},
  "geometry": {"coordinates":[-73.97021700000001,40.763229],"type":"Point"}
}