{
  "type": "Feature",
  "properties": {
    "addr:full":"32 E 23rd St New York NY 10010",
    "addr:housenumber":"32",
    "addr:postcode":"10010",
    "addr:street":"E 23Rd St",
    "iso:country":"US",
    "sg:address":"32 E 23rd St",
    "sg:city":"New York",
    "sg:classifiers":[
        {
            "category":"Deli",
            "type":"Food & Drink"
        }
    ],
    "sg:phone":"+1 212 677 4608",
    "sg:postcode":"10010",
    "sg:province":"NY",
    "wof:name":"Subway Sandwich Shop",
    "wof:placetype":"venue"
},
  "geometry": {"coordinates":[-73.987602,40.740601],"type":"Point"}
}