{
  "type": "Feature",
  "properties": {
    "addr:full":"2944 Route 112 Medford NY 11763",
    "addr:housenumber":"2944",
    "addr:postcode":"11763",
    "addr:street":"Route 112",
    "iso:country":"US",
    "sg:address":"2944 Route 112",
    "sg:city":"Medford",
    "sg:classifiers":[
        {
            "category":"Home & Garden",
            "subcategory":"Building Materials",
            "type":"Retail Goods"
        },
        {
            "category":"Building & Trades",
            "subcategory":"Construction",
            "type":"Services"
        }
    ],
    "sg:phone":"+1 631 698 6353",
    "sg:postcode":"11763",
    "sg:province":"NY",
    "sg:tags":[
        "concrete",
        "shape",
        "staining",
        "block",
        "contractor"
    ],
    "wof:name":"Empire Motor Sales Inc",
    "wof:placetype":"venue"
},
  "geometry": {"coordinates":[-72.995283,40.829579],"type":"Point"}
}