{
  "type": "Feature",
  "properties": {
    "iso:country":"US",
    "sg:address":"280 Suburban Ave",
    "sg:city":"Deer Park",
    "sg:classifiers":[
        {
            "category":"Professional",
            "subcategory":"Business Services",
            "type":"Services"
        }
    ],
    "sg:phone":"+1 631 243 0474",
    "sg:postcode":"11729",
    "sg:province":"NY",
    "sg:tags":[
        "packaging"
    ],
    "wof:name":"DASH Enterprises",
    "wof:placetype":"venue"
},
  "geometry": {"coordinates":[-73.303015,40.753194],"type":"Point"}
}