{
  "type": "Feature",
  "properties": {
    "addr:full":"470 Mamaroneck Ave Harrison NY 10528",
    "addr:housenumber":"470",
    "addr:postcode":"10528",
    "addr:street":"Mamaroneck Ave",
    "iso:country":"US",
    "sg:address":"470 Mamaroneck Ave",
    "sg:city":"Harrison",
    "sg:classifiers":[
        {
            "category":"Farming",
            "subcategory":"Nursery",
            "type":"Manufacturing & Wholesale Goods"
        }
    ],
    "sg:phone":"+1 914 698 7846",
    "sg:postcode":"10528",
    "sg:province":"NY",
    "sg:tags":[
        "stock",
        "grows",
        "garden"
    ],
    "wof:name":"Acorn Landscape & Garden Cntr",
    "wof:placetype":"venue"
},
  "geometry": {"coordinates":[-73.743028,40.974716],"type":"Point"}
}