{
  "type": "Feature",
  "properties": {
    "addr:full":"51 Highland Ave Elizaville NY 12523",
    "addr:housenumber":"51",
    "addr:postcode":"12523",
    "addr:street":"Highland Ave",
    "iso:country":"US",
    "sg:address":"51 Highland Ave",
    "sg:city":"Elizaville",
    "sg:classifiers":[
        {
            "category":"Freight",
            "type":"Transportation"
        }
    ],
    "sg:phone":"+1   ",
    "sg:postcode":"12523",
    "sg:province":"NY",
    "sg:tags":[
        "sand",
        "gravel",
        "truck",
        "hauling",
        "dump"
    ],
    "wof:name":"Stephen Bush Trucking Inc",
    "wof:placetype":"venue"
},
  "geometry": {"coordinates":[-73.797533,42.066639],"type":"Point"}
}