{
  "type": "Feature",
  "properties": {
    "addr:full":"18 Timber Ridge Dr Commack NY 11725",
    "addr:housenumber":"18",
    "addr:postcode":"11725",
    "addr:street":"Timber Ridge Dr",
    "iso:country":"US",
    "sg:address":"18 Timber Ridge Dr",
    "sg:city":"Commack",
    "sg:classifiers":[
        {
            "category":"Health Services",
            "subcategory":"Chiropractor",
            "type":"Services"
        }
    ],
    "sg:phone":"+1   ",
    "sg:postcode":"11725",
    "sg:province":"NY",
    "wof:name":"Richard Manoni",
    "wof:placetype":"venue"
},
  "geometry": {"coordinates":[-73.257698,40.865006],"type":"Point"}
}