{
  "type": "Feature",
  "properties": {
    "iso:country":"US",
    "sg:address":"3144 S Winton Rd",
    "sg:city":"Rochester",
    "sg:classifiers":[
        {
            "category":"Utilities",
            "subcategory":"Mobile Phone",
            "type":"Services"
        }
    ],
    "sg:phone":"+1 585 766 6575",
    "sg:postcode":"14623",
    "sg:province":"NY",
    "sg:tags":[
        "telephone",
        "cellular"
    ],
    "wof:name":"Cingular Wireless",
    "wof:placetype":"venue"
},
  "geometry": {"coordinates":[-77.581886,43.089896],"type":"Point"}
}