{
  "type": "Feature",
  "properties": {
    "iso:country":"US",
    "sg:address":"104 Pine Tree Ln",
    "sg:city":"Tappan",
    "sg:classifiers":[
        {
            "category":"Shopping",
            "subcategory":"Gifts & Souvenirs",
            "type":"Retail Goods"
        }
    ],
    "sg:phone":"+1   ",
    "sg:postcode":"10983",
    "sg:province":"NY",
    "wof:name":"Woller Decal & Specialty Co",
    "wof:placetype":"venue"
},
  "geometry": {"coordinates":[-73.942898,41.02949],"type":"Point"}
}