{
  "type": "Feature",
  "properties": {
    "addr:full":"1170 W Main St Riverhead NY 11901",
    "addr:housenumber":"1170",
    "addr:postcode":"11901",
    "addr:street":"W Main St",
    "iso:country":"US",
    "sg:address":"1170 W Main St",
    "sg:city":"Riverhead",
    "sg:classifiers":[
        {
            "category":"Sports & Exercise",
            "subcategory":"Bicycle Rental",
            "type":"Entertainment"
        }
    ],
    "sg:phone":"+1 631 208 1537",
    "sg:postcode":"11901",
    "sg:province":"NY",
    "sg:tags":[
        "wear"
    ],
    "sg:website":"www.pacsun.com",
    "wof:name":"PacSun",
    "wof:placetype":"venue"
},
  "geometry": {"coordinates":[-72.688481,40.915916],"type":"Point"}
}