{
  "type": "Feature",
  "properties": {
    "addr:full":"1220 Peninsula Blvd Hewlett NY 11557",
    "addr:housenumber":"1220",
    "addr:postcode":"11557",
    "addr:street":"Peninsula Blvd",
    "iso:country":"US",
    "sg:address":"1220 Peninsula Blvd",
    "sg:city":"Hewlett",
    "sg:classifiers":[
        {
            "category":"Shopping",
            "subcategory":"Pharmacy",
            "type":"Retail Goods"
        }
    ],
    "sg:phone":"+1 516 791 6663",
    "sg:postcode":"11557",
    "sg:province":"NY",
    "sg:tags":[
        "drugstore"
    ],
    "sg:website":"www.cvs.com",
    "wof:name":"Cvs/Pharmacy",
    "wof:placetype":"venue"
},
  "geometry": {"coordinates":[-73.70729799999999,40.642502],"type":"Point"}
}