{
  "type": "Feature",
  "properties": {
    "addr:full":"7602 3rd Ave Brooklyn NY 11209",
    "addr:housenumber":"7602",
    "addr:postcode":"11209",
    "addr:street":"3Rd Ave",
    "iso:country":"US",
    "sg:address":"7602 3rd Ave",
    "sg:city":"Brooklyn",
    "sg:classifiers":[
        {
            "category":"Utilities",
            "subcategory":"Mobile Phone",
            "type":"Services"
        }
    ],
    "sg:phone":"+1   ",
    "sg:postcode":"11209",
    "sg:province":"NY",
    "sg:tags":[
        "communication",
        "radiotelephone",
        "merchandise"
    ],
    "wof:name":"Cell 4 Sale",
    "wof:placetype":"venue"
},
  "geometry": {"coordinates":[-74.028447,40.63006],"type":"Point"}
}