{
  "type": "Feature",
  "properties": {
    "iso:country":"US",
    "sg:address":"7209 Broadway",
    "sg:city":"New York",
    "sg:classifiers":[
        {
            "category":"Restaurant",
            "type":"Food & Drink"
        }
    ],
    "sg:phone":"+1 718 476 6516",
    "sg:postcode":"11372",
    "sg:province":"NY",
    "sg:tags":[
        "pakistani",
        "indian"
    ],
    "wof:name":"Dera",
    "wof:placetype":"venue"
},
  "geometry": {"coordinates":[-73.893681,40.747639],"type":"Point"}
}