{
  "type": "Feature",
  "properties": {
    "addr:full":"2001 Route 112 Medford NY 11763",
    "addr:housenumber":"2001",
    "addr:postcode":"11763",
    "addr:street":"Route 112",
    "iso:country":"US",
    "sg:address":"2001 Route 112",
    "sg:city":"Medford",
    "sg:classifiers":[
        {
            "category":"Travel",
            "subcategory":"Hotels & Motels",
            "type":"Entertainment"
        }
    ],
    "sg:phone":"+1 631 475 9260",
    "sg:postcode":"11763",
    "sg:province":"NY",
    "sg:website":"www.112motel.com",
    "wof:name":"112 Motel",
    "wof:placetype":"venue"
},
  "geometry": {"coordinates":[-73.002669,40.808084],"type":"Point"}
}