{
  "type": "Feature",
  "properties": {
    "addr:full":"651 Fulton Street Brooklyn NY 11217",
    "addr:housenumber":"651",
    "addr:postcode":"11217",
    "addr:street":"Fulton Street",
    "iso:country":"US",
    "sg:address":"651 Fulton Street",
    "sg:city":"Brooklyn",
    "sg:classifiers":[
        {
            "category":"Arts & Performance",
            "subcategory":"Arts Center",
            "type":"Entertainment"
        }
    ],
    "sg:phone":"+1 718 636 4100",
    "sg:postcode":"11217",
    "sg:province":"NY",
    "sg:tags":[
        "performing"
    ],
    "sg:website":"www.bam.org",
    "wof:name":"BAM Harvey Theatre",
    "wof:placetype":"venue"
},
  "geometry": {"coordinates":[-73.9791,40.68818],"type":"Point"}
}