{
  "type": "Feature",
  "properties": {
    "addr:full":"403 Greenwich St New York NY 10013",
    "addr:housenumber":"403",
    "addr:postcode":"10013",
    "addr:street":"Greenwich St",
    "iso:country":"US",
    "sg:address":"403 Greenwich St",
    "sg:city":"New York",
    "sg:classifiers":[
        {
            "category":"Manufacturing",
            "subcategory":"Printing",
            "type":"Manufacturing & Wholesale Goods"
        }
    ],
    "sg:phone":"+1 212 219 1100",
    "sg:postcode":"10013",
    "sg:province":"NY",
    "sg:tags":[
        "printer"
    ],
    "wof:name":"Linden Forms & Systems Inc",
    "wof:placetype":"venue"
},
  "geometry": {"coordinates":[-74.009878,40.721249],"type":"Point"}
}