{
  "type": "Feature",
  "properties": {
    "iso:country":"US",
    "sg:address":"4621 Ridge Rd W",
    "sg:city":"Spencerport",
    "sg:classifiers":[
        {
            "category":"Home & Garden",
            "subcategory":"Building Materials",
            "type":"Retail Goods"
        }
    ],
    "sg:phone":"+1   ",
    "sg:postcode":"14559",
    "sg:province":"NY",
    "wof:name":"Assurance Glass",
    "wof:placetype":"venue"
},
  "geometry": {"coordinates":[-77.75551299999999,43.217708],"type":"Point"}
}