{
  "type": "Feature",
  "properties": {
    "iso:country":"US",
    "sg:address":"449 S Warren St",
    "sg:city":"Syracuse",
    "sg:classifiers":[
        {
            "category":"Banks & Credit Unions",
            "subcategory":"Bank",
            "type":"Services"
        }
    ],
    "sg:phone":"+1 315 422 3600",
    "sg:postcode":"13202",
    "sg:province":"NY",
    "wof:name":"M & T Bank",
    "wof:placetype":"venue"
},
  "geometry": {"coordinates":[-76.150727,43.046341],"type":"Point"}
}