{
  "type": "Feature",
  "properties": {
    "addr:full":"123 W 126th Street New York NY 10027",
    "addr:housenumber":"123",
    "addr:postcode":"10027",
    "addr:street":"W 126Th Street",
    "iso:country":"US",
    "sg:address":"123 W 126th Street",
    "sg:city":"New York",
    "sg:classifiers":[
        {
            "category":"Building & Trades",
            "subcategory":"Construction",
            "type":"Services"
        }
    ],
    "sg:phone":"+1 212 678 0045",
    "sg:postcode":"10027",
    "sg:province":"NY",
    "sg:tags":[
        "interior",
        "design"
    ],
    "wof:name":"W Property Resources",
    "wof:placetype":"venue"
},
  "geometry": {"coordinates":[-73.94624399999999,40.808835],"type":"Point"}
}