{
  "type": "Feature",
  "properties": {
    "iso:country":"US",
    "sg:address":"1947 Old Country Rd",
    "sg:city":"Riverhead",
    "sg:classifiers":[
        {
            "category":"Shopping",
            "subcategory":"Shoes",
            "type":"Retail Goods"
        }
    ],
    "sg:phone":"+1 631 369 3586",
    "sg:postcode":"11901",
    "sg:province":"NY",
    "sg:tags":[
        "store"
    ],
    "wof:name":"Chico's Fas Inc",
    "wof:placetype":"venue"
},
  "geometry": {"coordinates":[-72.716904,40.9226],"type":"Point"}
}