{
  "type": "Feature",
  "properties": {
    "iso:country":"US",
    "sg:address":"20 Northaven Ter",
    "sg:city":"Rochester",
    "sg:classifiers":[
        {
            "category":"Building & Trades",
            "subcategory":"Landscaping Services",
            "type":"Services"
        }
    ],
    "sg:phone":"+1 585 467 2312",
    "sg:postcode":"14621",
    "sg:province":"NY",
    "sg:tags":[
        "landscape"
    ],
    "wof:name":"Hummingbird Ldscp Snowplowing",
    "wof:placetype":"venue"
},
  "geometry": {"coordinates":[-77.58804000000001,43.187952],"type":"Point"}
}