{
  "type": "Feature",
  "properties": {
    "addr:full":"425 E 86th St New York NY 10028",
    "addr:housenumber":"425",
    "addr:postcode":"10028",
    "addr:street":"E 86Th St",
    "iso:country":"US",
    "sg:address":"425 E 86th St",
    "sg:city":"New York",
    "sg:classifiers":[
        {
            "category":"Real Estate",
            "subcategory":"Real Estate Operator",
            "type":"Services"
        }
    ],
    "sg:phone":"+1 212 410 2897",
    "sg:postcode":"10028",
    "sg:province":"NY",
    "sg:tags":[
        "apartment"
    ],
    "wof:name":"425 E 85 Apts Corp",
    "wof:placetype":"venue"
},
  "geometry": {"coordinates":[-73.94879899999999,40.7766],"type":"Point"}
}