{
  "type": "Feature",
  "properties": {
    "addr:full":"1945 7th Ave New York NY 10026",
    "addr:housenumber":"1945",
    "addr:postcode":"10026",
    "addr:street":"7Th Ave",
    "iso:country":"US",
    "sg:address":"1945 7th Ave",
    "sg:city":"New York",
    "sg:classifiers":[
        {
            "category":"Manufacturing",
            "subcategory":"Tools & Machinery",
            "type":"Manufacturing & Wholesale Goods"
        }
    ],
    "sg:phone":"+1   ",
    "sg:postcode":"10026",
    "sg:province":"NY",
    "sg:tags":[
        "photographic",
        "mfg"
    ],
    "wof:name":"Meg Henson & Jeffrey Scls Prod",
    "wof:placetype":"venue"
},
  "geometry": {"coordinates":[-73.951635,40.804257],"type":"Point"}
}