{
  "type": "Feature",
  "properties": {
    "addr:full":"2043 Wellwood Ave Farmingdale NY 11735",
    "addr:housenumber":"2043",
    "addr:postcode":"11735",
    "addr:street":"Wellwood Ave",
    "iso:country":"US",
    "sg:address":"2043 Wellwood Ave",
    "sg:city":"Farmingdale",
    "sg:classifiers":[
        {
            "category":"Retail",
            "subcategory":"Repair Shop",
            "type":"Services"
        }
    ],
    "sg:phone":"+1 516 753 6000",
    "sg:postcode":"11735",
    "sg:province":"NY",
    "sg:tags":[
        "lock",
        "locksmith"
    ],
    "wof:name":"Sentinel Locksmith",
    "wof:placetype":"venue"
},
  "geometry": {"coordinates":[-73.401642,40.749718],"type":"Point"}
}