{
  "type": "Feature",
  "properties": {
    "addr:full":"358 Somerville Ave Tonawanda NY 14150",
    "addr:housenumber":"358",
    "addr:postcode":"14150",
    "addr:street":"Somerville Ave",
    "iso:country":"US",
    "sg:address":"358 Somerville Ave",
    "sg:city":"Tonawanda",
    "sg:classifiers":[
        {
            "category":"Shopping",
            "subcategory":"Pharmacy",
            "type":"Retail Goods"
        }
    ],
    "sg:phone":"+1 716 876 3070",
    "sg:postcode":"14150",
    "sg:province":"NY",
    "wof:name":"Black Rock Pharmacy",
    "wof:placetype":"venue"
},
  "geometry": {"coordinates":[-78.83792099999999,42.989866],"type":"Point"}
}