{
  "type": "Feature",
  "properties": {
    "addr:full":"615 Viewland Dr Yorktown Heights NY 10598",
    "addr:housenumber":"615",
    "addr:postcode":"10598",
    "addr:street":"Viewland Dr",
    "iso:country":"US",
    "sg:address":"615 Viewland Dr",
    "sg:city":"Yorktown Heights",
    "sg:classifiers":[
        {
            "category":"Organizations",
            "subcategory":"Religious Organization",
            "type":"Services"
        }
    ],
    "sg:phone":"+1 914 962 9510",
    "sg:postcode":"10598",
    "sg:province":"NY",
    "sg:tags":[
        "clergy"
    ],
    "wof:name":"Robert E Johnson",
    "wof:placetype":"venue"
},
  "geometry": {"coordinates":[-73.797454,41.285761],"type":"Point"}
}