{
  "type": "Feature",
  "properties": {
    "iso:country":"US",
    "sg:address":"249 10 Ave",
    "sg:city":"New York",
    "sg:classifiers":[
        {
            "category":"Parking",
            "type":"Transportation"
        }
    ],
    "sg:phone":"+1   ",
    "sg:postcode":"10001",
    "sg:province":"NY",
    "sg:tags":[
        "automobile"
    ],
    "wof:name":"249 Parking Corp",
    "wof:placetype":"venue"
},
  "geometry": {"coordinates":[-74.003236,40.748974],"type":"Point"}
}