{
  "type": "Feature",
  "properties": {
    "addr:full":"40 Cedar Valley Rd Poughkeepsie NY 12603",
    "addr:housenumber":"40",
    "addr:postcode":"12603",
    "addr:street":"Cedar Valley Rd",
    "iso:country":"US",
    "sg:address":"40 Cedar Valley Rd",
    "sg:city":"Poughkeepsie",
    "sg:classifiers":[
        {
            "category":"Organizations",
            "subcategory":"Religious Organization",
            "type":"Services"
        }
    ],
    "sg:phone":"+1 845 473 8546",
    "sg:postcode":"12603",
    "sg:province":"NY",
    "sg:tags":[
        "clergy"
    ],
    "wof:name":"Brian Mc Weeney",
    "wof:placetype":"venue"
},
  "geometry": {"coordinates":[-73.87896000000001,41.667169],"type":"Point"}
}