{
  "type": "Feature",
  "properties": {
    "addr:full":"211 W 14 St New York NY 10011",
    "addr:housenumber":"211",
    "addr:postcode":"10011",
    "addr:street":"W 14 St",
    "iso:country":"US",
    "sg:address":"211 W 14 St",
    "sg:city":"New York",
    "sg:classifiers":[
        {
            "category":"Social Services",
            "type":"Services"
        }
    ],
    "sg:phone":"+1 212 727 4200",
    "sg:postcode":"10011",
    "sg:province":"NY",
    "sg:tags":[
        "organization",
        "welfare"
    ],
    "sg:website":"www.fedcap.org",
    "wof:name":"Fedcap Rehabilitation Svc",
    "wof:placetype":"venue"
},
  "geometry": {"coordinates":[-74.002267,40.739696],"type":"Point"}
}