{
  "type": "Feature",
  "properties": {
    "addr:full":"70 Greenwich Ave New York NY 10011",
    "addr:housenumber":"70",
    "addr:postcode":"10011",
    "addr:street":"Greenwich Ave",
    "iso:country":"US",
    "sg:address":"70 Greenwich Ave",
    "sg:city":"New York",
    "sg:classifiers":[
        {
            "category":"Real Estate",
            "subcategory":"Real Estate Agent",
            "type":"Services"
        }
    ],
    "sg:phone":"+1 212 979 8080",
    "sg:postcode":"10011",
    "sg:province":"NY",
    "wof:name":"Adams Real Estate Group Inc",
    "wof:placetype":"venue"
},
  "geometry": {"coordinates":[-74.00079100000001,40.736063],"type":"Point"}
}