{
  "type": "Feature",
  "properties": {
    "iso:country":"US",
    "sg:address":"540 N Main St",
    "sg:city":"Canandaigua",
    "sg:classifiers":[
        {
            "category":"Fast Food",
            "type":"Food & Drink"
        },
        {
            "category":"Restaurant",
            "type":"Food & Drink"
        },
        {
            "category":"Food & Beverages",
            "subcategory":"Groceries & Convenience Stores",
            "type":"Retail Goods"
        }
    ],
    "sg:phone":"+1 585 394 8670",
    "sg:postcode":"14424",
    "sg:province":"NY",
    "sg:tags":[
        "shop",
        "american",
        "sandwich",
        "take"
    ],
    "wof:name":"Subway",
    "wof:placetype":"venue"
},
  "geometry": {"coordinates":[-77.275674,42.879718],"type":"Point"}
}