{
  "type": "Feature",
  "properties": {
    "iso:country":"US",
    "sg:address":"231 Prospect Park West",
    "sg:city":"Brooklyn",
    "sg:classifiers":[
        {
            "category":"Communications",
            "subcategory":"Newspaper",
            "type":"Services"
        }
    ],
    "sg:postcode":"11215",
    "sg:province":"NY",
    "sg:tags":[
        "magazine"
    ],
    "wof:name":"Krupa Grocery News Stand - School Supplies",
    "wof:placetype":"venue"
},
  "geometry": {"coordinates":[-73.980799,40.659885],"type":"Point"}
}