{
  "type": "Feature",
  "properties": {
    "addr:full":"242 W Park Ave Long Beach NY 11561",
    "addr:housenumber":"242",
    "addr:postcode":"11561",
    "addr:street":"W Park Ave",
    "iso:country":"US",
    "sg:address":"242 W Park Ave",
    "sg:city":"Long Beach",
    "sg:classifiers":[
        {
            "category":"Real Estate",
            "subcategory":"Real Estate Agent",
            "type":"Services"
        }
    ],
    "sg:phone":"+1 516 897 2700",
    "sg:postcode":"11561",
    "sg:province":"NY",
    "sg:website":"www.thejoesinnonagroup.com",
    "wof:name":"Remax Shores: The Joe Sinnona Group",
    "wof:placetype":"venue"
},
  "geometry": {"coordinates":[-73.671032,40.588325],"type":"Point"}
}