{
  "type": "Feature",
  "properties": {
    "addr:full":"15 Hayes Ct Unit 203 Monroe NY 10950",
    "addr:housenumber":"15;203",
    "addr:postcode":"10950",
    "addr:street":"Hayes Ct Unit",
    "iso:country":"US",
    "sg:address":"15 Hayes Ct Unit 203",
    "sg:city":"Monroe",
    "sg:classifiers":[
        {
            "category":"Health Services",
            "subcategory":"Doctor",
            "type":"Services"
        },
        {
            "category":"Health Services",
            "subcategory":"Chiropractor",
            "type":"Services"
        }
    ],
    "sg:phone":"+1 845 782 6202",
    "sg:postcode":"10950",
    "sg:province":"NY",
    "wof:name":"Ron Bekemus D C",
    "wof:placetype":"venue"
},
  "geometry": {"coordinates":[-74.16637299999999,41.344431],"type":"Point"}
}