{
  "type": "Feature",
  "properties": {
    "addr:full":"333 Earle Ovington Blvd Fl 5 Uniondale NY 11553",
    "addr:housenumber":"333;5",
    "addr:postcode":"11553",
    "addr:street":"Earle Ovington Blvd Fl",
    "iso:country":"US",
    "sg:address":"333 Earle Ovington Blvd Fl 5",
    "sg:city":"Uniondale",
    "sg:classifiers":[
        {
            "category":"Professional",
            "subcategory":"Lawyer & Legal Services",
            "type":"Services"
        }
    ],
    "sg:phone":"+1 516 227 2260",
    "sg:postcode":"11553",
    "sg:province":"NY",
    "wof:name":"Callan Koster Brady & Brennan LLP",
    "wof:placetype":"venue"
},
  "geometry": {"coordinates":[-73.592955,40.725328],"type":"Point"}
}