{
  "type": "Feature",
  "properties": {
    "addr:full":"10409 Metropolitan Avenue Forest Hills NY 11375",
    "addr:housenumber":"10409",
    "addr:postcode":"11375",
    "addr:street":"Metropolitan Avenue",
    "iso:country":"US",
    "sg:address":"10409 Metropolitan Avenue",
    "sg:city":"Forest Hills",
    "sg:classifiers":[
        {
            "category":"Restaurant",
            "type":"Food & Drink"
        }
    ],
    "sg:phone":"+1 718 793 1550",
    "sg:postcode":"11375",
    "sg:province":"NY",
    "wof:name":"Hang Shing Kitchen",
    "wof:placetype":"venue"
},
  "geometry": {"coordinates":[-73.848602,40.7101],"type":"Point"}
}