{
  "type": "Feature",
  "properties": {
    "iso:country":"US",
    "sg:address":"56 Sleepy Valley Rd",
    "sg:city":"Warwick",
    "sg:classifiers":[
        {
            "category":"Health Services",
            "subcategory":"Health Practitioner",
            "type":"Services"
        }
    ],
    "sg:phone":"+1 845 986 7666",
    "sg:postcode":"10990",
    "sg:province":"NY",
    "sg:tags":[
        "psychologist"
    ],
    "wof:name":"Sondra Tuckfelt PHD",
    "wof:placetype":"venue"
},
  "geometry": {"coordinates":[-74.360907,41.274481],"type":"Point"}
}