{
  "type": "Feature",
  "properties": {
    "iso:country":"US",
    "sg:address":"142 Winthrop Ave",
    "sg:city":"Elmsford",
    "sg:classifiers":[
        {
            "category":"Building & Trades",
            "subcategory":"Construction",
            "type":"Services"
        }
    ],
    "sg:phone":"+1 866 592 2522",
    "sg:postcode":"10523",
    "sg:province":"NY",
    "sg:tags":[
        "painting",
        "contractor"
    ],
    "wof:name":"E-Z Painting, Inc.",
    "wof:placetype":"venue"
},
  "geometry": {"coordinates":[-73.81244,41.059596],"type":"Point"}
}