{
  "type": "Feature",
  "properties": {
    "iso:country":"US",
    "sg:address":"701 W Montauk Hwy",
    "sg:city":"Bay Shore",
    "sg:classifiers":[
        {
            "category":"Professional",
            "subcategory":"Management & Consulting",
            "type":"Services"
        }
    ],
    "sg:phone":"+1 631 206 1000",
    "sg:postcode":"11706",
    "sg:province":"NY",
    "sg:tags":[
        "marketing",
        "program"
    ],
    "wof:name":"Marketing Inc Of Islandia",
    "wof:placetype":"venue"
},
  "geometry": {"coordinates":[-73.274006,40.702638],"type":"Point"}
}