{
  "type": "Feature",
  "properties": {
    "iso:country":"US",
    "sg:address":"1 Schuyler St",
    "sg:city":"Belmont",
    "sg:classifiers":[
        {
            "category":"Government",
            "subcategory":"Office",
            "type":"Public Place"
        }
    ],
    "sg:phone":"+1 585 268 5423",
    "sg:postcode":"14813",
    "sg:province":"NY",
    "sg:tags":[
        "village"
    ],
    "wof:name":"Amity Town Office",
    "wof:placetype":"venue"
},
  "geometry": {"coordinates":[-78.033661,42.223192],"type":"Point"}
}