{
  "type": "Feature",
  "properties": {
    "iso:country":"US",
    "sg:address":"540 Smithtown Byp",
    "sg:city":"Smithtown",
    "sg:classifiers":[
        {
            "category":"Retail",
            "subcategory":"Laundry & Dry Cleaning",
            "type":"Services"
        }
    ],
    "sg:phone":"+1 631 724 2612",
    "sg:postcode":"11787",
    "sg:province":"NY",
    "sg:tags":[
        "laundries-self",
        "operated",
        "washer",
        "dryer",
        "coin"
    ],
    "wof:name":"Smithtown Laundromat",
    "wof:placetype":"venue"
},
  "geometry": {"coordinates":[-73.194935,40.831888],"type":"Point"}
}