{
  "type": "Feature",
  "properties": {
    "iso:country":"US",
    "sg:address":"170 Avenue S",
    "sg:city":"Brooklyn",
    "sg:classifiers":[
        {
            "category":"Health Services",
            "subcategory":"Doctor",
            "type":"Services"
        }
    ],
    "sg:phone":"+1 718 382 8282",
    "sg:postcode":"11223",
    "sg:province":"NY",
    "wof:name":"Gribenko Victor MD",
    "wof:placetype":"venue"
},
  "geometry": {"coordinates":[-73.979342,40.601031],"type":"Point"}
}