{
  "type": "Feature",
  "properties": {
    "addr:full":"2820 Middletown Rd Bronx NY 10461",
    "addr:housenumber":"2820",
    "addr:postcode":"10461",
    "addr:street":"Middletown Rd",
    "iso:country":"US",
    "sg:address":"2820 Middletown Rd",
    "sg:city":"Bronx",
    "sg:classifiers":[
        {
            "category":"Building & Trades",
            "subcategory":"Construction",
            "type":"Services"
        }
    ],
    "sg:phone":"+1 718 239 5003",
    "sg:postcode":"10461",
    "sg:province":"NY",
    "sg:tags":[
        "maintenance",
        "contractor"
    ],
    "wof:name":"F & H Maintenance",
    "wof:placetype":"venue"
},
  "geometry": {"coordinates":[-73.83643600000001,40.843322],"type":"Point"}
}