{
  "type": "Feature",
  "properties": {
    "iso:country":"US",
    "sg:address":"1216 11th St",
    "sg:city":"West Babylon",
    "sg:classifiers":[
        {
            "category":"Wholesale",
            "subcategory":"Hardware",
            "type":"Manufacturing & Wholesale Goods"
        }
    ],
    "sg:phone":"+1 631 888 4505",
    "sg:postcode":"11704",
    "sg:province":"NY",
    "sg:tags":[
        "plumbing",
        "gas",
        "burner"
    ],
    "wof:name":"Northeast Energy Corp",
    "wof:placetype":"venue"
},
  "geometry": {"coordinates":[-73.369968,40.72289],"type":"Point"}
}