{
  "type": "Feature",
  "properties": {
    "iso:country":"US",
    "sg:address":"81 3rd St",
    "sg:city":"Troy",
    "sg:classifiers":[
        {
            "category":"Personal",
            "subcategory":"Shoe Repair & Shine",
            "type":"Services"
        }
    ],
    "sg:phone":"+1 518 274 2431",
    "sg:postcode":"12180",
    "sg:province":"NY",
    "sg:tags":[
        "repairing",
        "parlor",
        "boot"
    ],
    "wof:name":"Troy Quick Shoe Repairing Co",
    "wof:placetype":"venue"
},
  "geometry": {"coordinates":[-73.69076699999999,42.729464],"type":"Point"}
}