{
  "type": "Feature",
  "properties": {
    "addr:full":"1593 Locust Ave Bohemia NY 11716",
    "addr:housenumber":"1593",
    "addr:postcode":"11716",
    "addr:street":"Locust Ave",
    "iso:country":"US",
    "sg:address":"1593 Locust Ave",
    "sg:city":"Bohemia",
    "sg:classifiers":[
        {
            "category":"Professional",
            "type":"Services"
        },
        {
            "category":"Wholesale",
            "subcategory":"Electrical",
            "type":"Manufacturing & Wholesale Goods"
        }
    ],
    "sg:phone":"+1 631 218 0876",
    "sg:postcode":"11716",
    "sg:province":"NY",
    "sg:tags":[
        "large",
        "industrial",
        "establishment",
        "sales",
        "power"
    ],
    "wof:name":"Support Power Inc",
    "wof:placetype":"venue"
},
  "geometry": {"coordinates":[-73.117626,40.785628],"type":"Point"}
}