{
  "type": "Feature",
  "properties": {
    "addr:full":"57 W 16th Street New York NY 10011",
    "addr:housenumber":"57",
    "addr:postcode":"10011",
    "addr:street":"W 16Th Street",
    "iso:country":"US",
    "sg:address":"57 W 16th Street",
    "sg:city":"New York",
    "sg:classifiers":[
        {
            "category":"Food & Beverages",
            "subcategory":"Candy",
            "type":"Retail Goods"
        }
    ],
    "sg:phone":"+1 212 691 1929",
    "sg:postcode":"10011",
    "sg:province":"NY",
    "sg:tags":[
        "store"
    ],
    "wof:name":"Shivkrupa",
    "wof:placetype":"venue"
},
  "geometry": {"coordinates":[-73.99449199999999,40.738099],"type":"Point"}
}