{
  "type": "Feature",
  "properties": {
    "addr:full":"2 Clara Barton Dr Albany NY 12208",
    "addr:housenumber":"2",
    "addr:postcode":"12208",
    "addr:street":"Clara Barton Dr",
    "iso:country":"US",
    "sg:address":"2 Clara Barton Dr",
    "sg:city":"Albany",
    "sg:classifiers":[
        {
            "category":"Health Services",
            "subcategory":"Health Practitioner",
            "type":"Services"
        }
    ],
    "sg:phone":"+1 518 207 2299",
    "sg:postcode":"12208",
    "sg:province":"NY",
    "sg:tags":[
        "therapist",
        "physical"
    ],
    "wof:name":"Community Care Physical Ther",
    "wof:placetype":"venue"
},
  "geometry": {"coordinates":[-73.77601799999999,42.647269],"type":"Point"}
}