{
  "type": "Feature",
  "properties": {
    "addr:full":"833 Michigan Ave Buffalo NY 14203",
    "addr:housenumber":"833",
    "addr:postcode":"14203",
    "addr:street":"Michigan Ave",
    "iso:country":"US",
    "sg:address":"833 Michigan Ave",
    "sg:city":"Buffalo",
    "sg:classifiers":[
        {
            "category":"Education",
            "subcategory":"School",
            "type":"Public Place"
        }
    ],
    "sg:phone":"+1 716 856 4390",
    "sg:postcode":"14203",
    "sg:province":"NY",
    "wof:name":"Aloma D Johnson",
    "wof:placetype":"venue"
},
  "geometry": {"coordinates":[-78.86447200000001,42.895232],"type":"Point"}
}