{
  "type": "Feature",
  "properties": {
    "addr:full":"261 W 47th St New York NY 10036",
    "addr:housenumber":"261",
    "addr:postcode":"10036",
    "addr:street":"W 47Th St",
    "iso:country":"US",
    "sg:address":"261 W 47th St",
    "sg:city":"New York",
    "sg:classifiers":[
        {
            "category":"Arts & Performance",
            "subcategory":"Arts Center",
            "type":"Entertainment"
        }
    ],
    "sg:phone":"+1 212 239 6200",
    "sg:postcode":"10036",
    "sg:province":"NY",
    "sg:tags":[
        "performing"
    ],
    "sg:website":"www.mtc-nyc.org/default.asp",
    "wof:name":"Samuel J Friedman Theatre",
    "wof:placetype":"venue"
},
  "geometry": {"coordinates":[-73.98671299999999,40.760481],"type":"Point"}
}