{
  "type": "Feature",
  "properties": {
    "iso:country":"US",
    "sg:address":"660 Main St",
    "sg:city":"Islip",
    "sg:classifiers":[
        {
            "category":"Banks & Credit Unions",
            "subcategory":"Bank",
            "type":"Services"
        }
    ],
    "sg:phone":"+1 631 581 7613",
    "sg:postcode":"11751",
    "sg:province":"NY",
    "wof:name":"State Farm Ins Cos",
    "wof:placetype":"venue"
},
  "geometry": {"coordinates":[-73.21060199999999,40.729599],"type":"Point"}
}