{
  "type": "Feature",
  "properties": {
    "iso:country":"US",
    "sg:address":"111 Ben Bar Cir",
    "sg:city":"Whitesboro",
    "sg:classifiers":[
        {
            "category":"Building & Trades",
            "subcategory":"Landscaping Services",
            "type":"Services"
        }
    ],
    "sg:phone":"+1 315 736 7383",
    "sg:postcode":"13492",
    "sg:province":"NY",
    "sg:tags":[
        "landscape"
    ],
    "wof:name":"All Seasons Landscaping",
    "wof:placetype":"venue"
},
  "geometry": {"coordinates":[-75.337756,43.103723],"type":"Point"}
}