{
  "type": "Feature",
  "properties": {
    "addr:full":"327 City Island Ave Bronx NY 10464",
    "addr:housenumber":"327",
    "addr:postcode":"10464",
    "addr:street":"City Island Ave",
    "iso:country":"US",
    "sg:address":"327 City Island Ave",
    "sg:city":"Bronx",
    "sg:classifiers":[
        {
            "category":"Professional",
            "subcategory":"Management & Consulting",
            "type":"Services"
        }
    ],
    "sg:phone":"+1 718 885 9657",
    "sg:postcode":"10464",
    "sg:province":"NY",
    "sg:tags":[
        "consultant"
    ],
    "wof:name":"Carl Stone",
    "wof:placetype":"venue"
},
  "geometry": {"coordinates":[-73.786641,40.847295],"type":"Point"}
}