{
  "type": "Feature",
  "properties": {
    "addr:full":"1944 Military Rd Niagara Falls NY 14304",
    "addr:housenumber":"1944",
    "addr:postcode":"14304",
    "addr:street":"Military Rd",
    "iso:country":"US",
    "sg:address":"1944 Military Rd",
    "sg:city":"Niagara Falls",
    "sg:classifiers":[
        {
            "category":"Shopping",
            "type":"Retail Goods"
        }
    ],
    "sg:phone":"+1   ",
    "sg:postcode":"14304",
    "sg:province":"NY",
    "sg:tags":[
        "merchandise"
    ],
    "wof:name":"Geoffrey Beene",
    "wof:placetype":"venue"
},
  "geometry": {"coordinates":[-78.97649800000001,43.098693],"type":"Point"}
}