{
  "type": "Feature",
  "properties": {
    "iso:country":"US",
    "sg:address":"230 Delaware Ave Ste 4",
    "sg:city":"Delmar",
    "sg:classifiers":[
        {
            "category":"Building & Trades",
            "subcategory":"Construction",
            "type":"Services"
        }
    ],
    "sg:phone":"+1 518 439 5173",
    "sg:postcode":"12054",
    "sg:province":"NY",
    "sg:tags":[
        "altering",
        "industrial",
        "remodeling",
        "contractors-commercial",
        "contractor"
    ],
    "wof:name":"Geurtze Builders",
    "wof:placetype":"venue"
},
  "geometry": {"coordinates":[-73.81848100000001,42.627392],"type":"Point"}
}