{
  "type": "Feature",
  "properties": {
    "addr:full":"8220 Krull Pkwy Niagara Falls NY 14304",
    "addr:postcode":"8220;14304",
    "addr:street":"Krull Pkwy",
    "iso:country":"US",
    "sg:address":"8220 Krull Pkwy",
    "sg:city":"Niagara Falls",
    "sg:classifiers":[
        {
            "category":"Building & Trades",
            "subcategory":"Construction",
            "type":"Services"
        }
    ],
    "sg:phone":"+1 716 283 6827",
    "sg:postcode":"14304",
    "sg:province":"NY",
    "sg:tags":[
        "hanging",
        "contractor"
    ],
    "wof:name":"Steves Painting",
    "wof:placetype":"venue"
},
  "geometry": {"coordinates":[-78.966578,43.088915],"type":"Point"}
}