{
  "type": "Feature",
  "properties": {
    "iso:country":"US",
    "sg:address":"170 Main St",
    "sg:city":"Esperance",
    "sg:classifiers":[
        {
            "category":"Professional",
            "subcategory":"Business Services",
            "type":"Services"
        },
        {
            "category":"Government",
            "subcategory":"Post Office",
            "type":"Public Place"
        }
    ],
    "sg:phone":"+1 800 275 8777",
    "sg:postcode":"12066",
    "sg:province":"NY",
    "sg:tags":[
        "mail",
        "shipping"
    ],
    "sg:website":"http://www.usps.com",
    "wof:name":"USPS - United States Post Office - Esperance Main Office",
    "wof:placetype":"venue"
},
  "geometry": {"coordinates":[-74.25938499999999,42.760371],"type":"Point"}
}