{
  "type": "Feature",
  "properties": {
    "addr:full":"11 Koch Pl Carle Place NY 11514",
    "addr:housenumber":"11",
    "addr:postcode":"11514",
    "addr:street":"Koch Pl;Place",
    "iso:country":"US",
    "sg:address":"11 Koch Pl",
    "sg:city":"Carle Place",
    "sg:classifiers":[
        {
            "category":"Building & Trades",
            "subcategory":"Construction",
            "type":"Services"
        }
    ],
    "sg:phone":"+1 516 997 9764",
    "sg:postcode":"11514",
    "sg:province":"NY",
    "sg:tags":[
        "contractor"
    ],
    "wof:name":"Thomas James Masonry Inc",
    "wof:placetype":"venue"
},
  "geometry": {"coordinates":[-73.603194,40.752429],"type":"Point"}
}