{
  "type": "Feature",
  "properties": {
    "addr:full":"1166 Manhattan Ave Brooklyn NY 11222",
    "addr:housenumber":"1166",
    "addr:postcode":"11222",
    "addr:street":"Manhattan Ave",
    "iso:country":"US",
    "sg:address":"1166 Manhattan Ave",
    "sg:city":"Brooklyn",
    "sg:classifiers":[
        {
            "category":"Building & Trades",
            "subcategory":"Construction",
            "type":"Services"
        }
    ],
    "sg:phone":"+1 718 349 3121",
    "sg:postcode":"11222",
    "sg:province":"NY",
    "sg:tags":[
        "contractor"
    ],
    "wof:name":"Ash Roofing Co",
    "wof:placetype":"venue"
},
  "geometry": {"coordinates":[-73.95522200000001,40.738515],"type":"Point"}
}