{
  "type": "Feature",
  "properties": {
    "iso:country":"US",
    "sg:address":"1529 Mill Rd",
    "sg:city":"East Aurora",
    "sg:classifiers":[
        {
            "category":"Real Estate",
            "subcategory":"Real Estate Operator",
            "type":"Services"
        }
    ],
    "sg:phone":"+1 716 652 9495",
    "sg:postcode":"14052",
    "sg:province":"NY",
    "sg:tags":[
        "building",
        "nonresidential"
    ],
    "wof:name":"Camp Longacres Inc",
    "wof:placetype":"venue"
},
  "geometry": {"coordinates":[-78.664812,42.724225],"type":"Point"}
}