{
  "type": "Feature",
  "properties": {
    "iso:country":"US",
    "sg:address":"1340 E 92nd St",
    "sg:city":"Brooklyn",
    "sg:classifiers":[
        {
            "category":"Retail",
            "subcategory":"Auto Repair",
            "type":"Services"
        }
    ],
    "sg:phone":"+1 718 531 5773",
    "sg:postcode":"11236",
    "sg:province":"NY",
    "wof:name":"Vinny's Auto Repair",
    "wof:placetype":"venue"
},
  "geometry": {"coordinates":[-73.900597,40.637501],"type":"Point"}
}