{
  "type": "Feature",
  "properties": {
    "iso:country":"US",
    "sg:address":"110 E Main St",
    "sg:city":"Allegany",
    "sg:classifiers":[
        {
            "category":"Real Estate",
            "subcategory":"Real Estate Operator",
            "type":"Services"
        }
    ],
    "sg:phone":"+1 716 373 2202",
    "sg:postcode":"14706",
    "sg:province":"NY",
    "sg:tags":[
        "apartment"
    ],
    "wof:name":"Emerald Hills Estates",
    "wof:placetype":"venue"
},
  "geometry": {"coordinates":[-78.48601499999999,42.08484],"type":"Point"}
}