{
  "type": "Feature",
  "properties": {
    "iso:country":"US",
    "sg:address":"939 Lester Ave S2",
    "sg:city":"Mamaroneck",
    "sg:classifiers":[
        {
            "category":"Autos & Motor Vehicles",
            "subcategory":"Auto Supplies",
            "type":"Retail Goods"
        }
    ],
    "sg:phone":"+1 914 315 6552",
    "sg:postcode":"10543",
    "sg:province":"NY",
    "sg:tags":[
        "automobile",
        "part"
    ],
    "wof:name":"Express Aeroparts & Serv",
    "wof:placetype":"venue"
},
  "geometry": {"coordinates":[-73.73623000000001,40.959344],"type":"Point"}
}