{
  "type": "Feature",
  "properties": {
    "iso:country":"US",
    "sg:address":"9 Technology Dr",
    "sg:city":"East Setauket",
    "sg:classifiers":[
        {
            "category":"Professional",
            "type":"Services"
        }
    ],
    "sg:phone":"+1 631 689 6606",
    "sg:postcode":"11733",
    "sg:province":"NY",
    "sg:tags":[
        "establishment"
    ],
    "wof:name":"Mark Goldberg Prosthetic",
    "wof:placetype":"venue"
},
  "geometry": {"coordinates":[-73.08647999999999,40.8985],"type":"Point"}
}