{
  "type": "Feature",
  "properties": {
    "iso:country":"US",
    "sg:address":"219 Mamaroneck Ave",
    "sg:city":"Mamaroneck",
    "sg:classifiers":[
        {
            "category":"Shopping",
            "subcategory":"Used Merchandise",
            "type":"Retail Goods"
        }
    ],
    "sg:phone":"+1 914 698 6280",
    "sg:postcode":"10543",
    "sg:province":"NY",
    "sg:tags":[
        "antique"
    ],
    "wof:name":"Den Of Antiquity",
    "wof:placetype":"venue"
},
  "geometry": {"coordinates":[-73.73436700000001,40.950797],"type":"Point"}
}