{
  "type": "Feature",
  "properties": {
    "addr:full":"774 Lafayette Ave Brooklyn NY 11221",
    "addr:housenumber":"774",
    "addr:postcode":"11221",
    "addr:street":"Lafayette Ave",
    "iso:country":"US",
    "sg:address":"774 Lafayette Ave",
    "sg:city":"Brooklyn",
    "sg:classifiers":[
        {
            "category":"Building & Trades",
            "subcategory":"Construction",
            "type":"Services"
        }
    ],
    "sg:phone":"+1 718 249 0572",
    "sg:postcode":"11221",
    "sg:province":"NY",
    "sg:tags":[
        "maintenance",
        "contractor"
    ],
    "wof:name":"Bogart's Maintenance Svc",
    "wof:placetype":"venue"
},
  "geometry": {"coordinates":[-73.939947,40.691103],"type":"Point"}
}