{
  "type": "Feature",
  "properties": {
    "iso:country":"US",
    "sg:address":"145 Summerfield St",
    "sg:city":"Scarsdale",
    "sg:classifiers":[
        {
            "category":"Retail",
            "subcategory":"Auto Repair",
            "type":"Services"
        }
    ],
    "sg:phone":"+1 914 723 0823",
    "sg:postcode":"10583",
    "sg:province":"NY",
    "sg:tags":[
        "repairing",
        "automobile"
    ],
    "wof:name":"Oneills Performance LTD",
    "wof:placetype":"venue"
},
  "geometry": {"coordinates":[-73.805831,40.977828],"type":"Point"}
}