{
  "type": "Feature",
  "properties": {
    "addr:full":"692 Knickerbocker Ave Brooklyn NY 11221",
    "addr:housenumber":"692",
    "addr:postcode":"11221",
    "addr:street":"Knickerbocker Ave",
    "iso:country":"US",
    "sg:address":"692 Knickerbocker Ave",
    "sg:city":"Brooklyn",
    "sg:classifiers":[
        {
            "category":"Shopping",
            "subcategory":"Clothing, Apparel, & Fashions",
            "type":"Retail Goods"
        }
    ],
    "sg:phone":"+1 718 453 7080",
    "sg:postcode":"11221",
    "sg:province":"NY",
    "wof:name":"Natalie Fashion",
    "wof:placetype":"venue"
},
  "geometry": {"coordinates":[-73.910489,40.694264],"type":"Point"}
}