{
  "type": "Feature",
  "properties": {
    "addr:full":"35 Galloway Rd Warwick NY 10990",
    "addr:housenumber":"35",
    "addr:postcode":"10990",
    "addr:street":"Galloway Rd",
    "iso:country":"US",
    "sg:address":"35 Galloway Rd",
    "sg:city":"Warwick",
    "sg:classifiers":[
        {
            "category":"Health Services",
            "subcategory":"Doctor",
            "type":"Services"
        }
    ],
    "sg:phone":"+1 845 986 4601",
    "sg:postcode":"10990",
    "sg:province":"NY",
    "sg:tags":[
        "dental",
        "clinic",
        "dentist"
    ],
    "wof:name":"Warwick Valley Dental",
    "wof:placetype":"venue"
},
  "geometry": {"coordinates":[-74.357231,41.25032],"type":"Point"}
}