{
  "type": "Feature",
  "properties": {
    "addr:full":"315 Hudson St New York NY 10013",
    "addr:housenumber":"315",
    "addr:postcode":"10013",
    "addr:street":"Hudson St",
    "iso:country":"US",
    "sg:address":"315 Hudson St",
    "sg:city":"New York",
    "sg:classifiers":[
        {
            "category":"Manufacturing",
            "subcategory":"Printing",
            "type":"Manufacturing & Wholesale Goods"
        }
    ],
    "sg:phone":"+1 212 675 7000",
    "sg:postcode":"10013",
    "sg:province":"NY",
    "sg:tags":[
        "publisher"
    ],
    "wof:name":"Amsco School Publication Inc",
    "wof:placetype":"venue"
},
  "geometry": {"coordinates":[-74.00757,40.726102],"type":"Point"}
}