{
  "type": "Feature",
  "properties": {
    "iso:country":"US",
    "sg:address":"10311 N Collins Rd",
    "sg:city":"North Collins",
    "sg:classifiers":[
        {
            "category":"Home & Garden",
            "subcategory":"Garden Supply",
            "type":"Retail Goods"
        }
    ],
    "sg:phone":"+1 716 337 2260",
    "sg:postcode":"14111",
    "sg:province":"NY",
    "sg:tags":[
        "nurseryman"
    ],
    "wof:name":"Lilac Creek Nursery Inc",
    "wof:placetype":"venue"
},
  "geometry": {"coordinates":[-78.94079000000001,42.605187],"type":"Point"}
}