{
  "type": "Feature",
  "properties": {
    "addr:full":"575 Lexington Ave New York NY 10022",
    "addr:housenumber":"575",
    "addr:postcode":"10022",
    "addr:street":"Lexington Ave",
    "iso:country":"US",
    "sg:address":"575 Lexington Ave",
    "sg:city":"New York",
    "sg:classifiers":[
        {
            "category":"Professional",
            "subcategory":"Management & Consulting",
            "type":"Services"
        }
    ],
    "sg:phone":"+1 212 691 4800",
    "sg:postcode":"10022",
    "sg:province":"NY",
    "sg:tags":[
        "consultant",
        "business"
    ],
    "wof:name":"EHS Partners",
    "wof:placetype":"venue"
},
  "geometry": {"coordinates":[-73.971451,40.757749],"type":"Point"}
}