{
  "type": "Feature",
  "properties": {
    "addr:full":"6200 Coleman Mills Rd Oriskany NY 13424",
    "addr:housenumber":"6200",
    "addr:postcode":"13424",
    "addr:street":"Coleman Mills Rd",
    "iso:country":"US",
    "sg:address":"6200 Coleman Mills Rd",
    "sg:city":"Oriskany",
    "sg:classifiers":[
        {
            "category":"Sports & Exercise",
            "subcategory":"Golf",
            "type":"Entertainment"
        }
    ],
    "sg:phone":"+1 315 339 4653",
    "sg:postcode":"13424",
    "sg:province":"NY",
    "sg:tags":[
        "course"
    ],
    "wof:name":"Spinella's Oriskany Hills Golf Club",
    "wof:placetype":"venue"
},
  "geometry": {"coordinates":[-75.377335,43.160623],"type":"Point"}
}