{
  "type": "Feature",
  "properties": {
    "iso:country":"US",
    "sg:address":"1221 Grand Ave",
    "sg:city":"Baldwin",
    "sg:classifiers":[
        {
            "category":"Restaurant",
            "type":"Food & Drink"
        }
    ],
    "sg:menulink":"http://www.allmenus.com/ny/baldwin/210435-kfc---kentucky-fried-chicken/menu/",
    "sg:phone":"+1 516 623 8656",
    "sg:postcode":"11510",
    "sg:province":"NY",
    "sg:tags":[
        "american",
        "chicken"
    ],
    "wof:name":"KFC - Kentucky Fried Chicken",
    "wof:placetype":"venue"
},
  "geometry": {"coordinates":[-73.61490999999999,40.68045],"type":"Point"}
}