{
  "type": "Feature",
  "properties": {
    "iso:country":"US",
    "sg:address":"1834 US Hwy 9",
    "sg:city":"Keeseville",
    "sg:classifiers":[
        {
            "category":"Food & Beverages",
            "subcategory":"Fruits & Vegetables",
            "type":"Retail Goods"
        }
    ],
    "sg:phone":"+1 518 834 7787",
    "sg:postcode":"12944",
    "sg:province":"NY",
    "sg:tags":[
        "farm",
        "market"
    ],
    "wof:name":"Alfred Santor Plants & Produce",
    "wof:placetype":"venue"
},
  "geometry": {"coordinates":[-73.47368899999999,44.511189],"type":"Point"}
}