{
  "type": "Feature",
  "properties": {
    "addr:full":"6 W 20th St New York NY 10011",
    "addr:housenumber":"6",
    "addr:postcode":"10011",
    "addr:street":"W 20Th St",
    "iso:country":"US",
    "sg:address":"6 W 20th St",
    "sg:city":"New York",
    "sg:classifiers":[
        {
            "category":"Retail",
            "subcategory":"Portrait Studio",
            "type":"Services"
        },
        {
            "category":"Professional",
            "subcategory":"Art Services",
            "type":"Services"
        }
    ],
    "sg:phone":"+1 212 989 2004",
    "sg:postcode":"10011",
    "sg:province":"NY",
    "sg:tags":[
        "photographer",
        "photography",
        "store"
    ],
    "wof:name":"Regan Ken Photgr",
    "wof:placetype":"venue"
},
  "geometry": {"coordinates":[-73.991096,40.7397],"type":"Point"}
}