{
  "type": "Feature",
  "properties": {
    "addr:full":"4634 White Plains Rd Bronx NY 10470",
    "addr:housenumber":"4634",
    "addr:postcode":"10470",
    "addr:street":"White Plains Rd",
    "iso:country":"US",
    "sg:address":"4634 White Plains Rd",
    "sg:city":"Bronx",
    "sg:classifiers":[
        {
            "category":"Professional",
            "subcategory":"Lawyer & Legal Services",
            "type":"Services"
        }
    ],
    "sg:phone":"+1 718 519 0828",
    "sg:postcode":"10470",
    "sg:province":"NY",
    "wof:name":"Methuselah Medical Servic",
    "wof:placetype":"venue"
},
  "geometry": {"coordinates":[-73.85062000000001,40.902908],"type":"Point"}
}