{
  "type": "Feature",
  "properties": {
    "iso:country":"US",
    "sg:address":"851 Kent Ave",
    "sg:city":"Brooklyn",
    "sg:classifiers":[
        {
            "category":"Home & Garden",
            "subcategory":"Building Materials",
            "type":"Retail Goods"
        }
    ],
    "sg:phone":"+1 718 384 6303",
    "sg:postcode":"11205",
    "sg:province":"NY",
    "sg:tags":[
        "equipment",
        "fixture",
        "lighting"
    ],
    "wof:name":"Baron Lighting",
    "wof:placetype":"venue"
},
  "geometry": {"coordinates":[-73.95915100000001,40.695063],"type":"Point"}
}