{
  "type": "Feature",
  "properties": {
    "addr:full":"241 New York Ave Huntington NY 11743",
    "addr:housenumber":"241",
    "addr:postcode":"11743",
    "addr:street":"New York Ave",
    "iso:country":"US",
    "sg:address":"241 New York Ave",
    "sg:city":"Huntington",
    "sg:classifiers":[
        {
            "category":"Restaurant",
            "type":"Food & Drink"
        }
    ],
    "sg:phone":"+1 631 549 5909",
    "sg:postcode":"11743",
    "sg:province":"NY",
    "wof:name":"Burger King",
    "wof:placetype":"venue"
},
  "geometry": {"coordinates":[-73.42440000000001,40.874699],"type":"Point"}
}