{
  "type": "Feature",
  "properties": {
    "iso:country":"US",
    "sg:address":"146 Wythe Ave",
    "sg:city":"Brooklyn",
    "sg:classifiers":[
        {
            "category":"Bars & Pubs",
            "type":"Food & Drink"
        }
    ],
    "sg:phone":"+1 718 388 5328",
    "sg:postcode":"11211",
    "sg:province":"NY",
    "sg:tags":[
        "tapa"
    ],
    "sg:website":"www.nitanitabk.com",
    "wof:name":"Nita Nita",
    "wof:placetype":"venue"
},
  "geometry": {"coordinates":[-73.95995600000001,40.720292],"type":"Point"}
}