{
  "type": "Feature",
  "properties": {
    "iso:country":"US",
    "sg:address":"331 Russell St",
    "sg:city":"Chittenango",
    "sg:classifiers":[
        {
            "category":"Health Services",
            "subcategory":"Nursing And Care Facility",
            "type":"Services"
        }
    ],
    "sg:phone":"+1 315 687 7255",
    "sg:postcode":"13037",
    "sg:province":"NY",
    "sg:tags":[
        "hospital",
        "skilled",
        "specialty"
    ],
    "wof:name":"Stonehdge Chttnango Nursing HM",
    "wof:placetype":"venue"
},
  "geometry": {"coordinates":[-75.86933500000001,43.049293],"type":"Point"}
}