{
  "type": "Feature",
  "properties": {
    "iso:country":"US",
    "sg:address":"9 Appaloosa Trl",
    "sg:city":"Centereach",
    "sg:classifiers":[
        {
            "category":"Wholesale",
            "subcategory":"Non-durable Goods",
            "type":"Manufacturing & Wholesale Goods"
        }
    ],
    "sg:phone":"+1 631 471 3868",
    "sg:postcode":"11720",
    "sg:province":"NY",
    "sg:tags":[
        "merchandise-wholesale"
    ],
    "wof:name":"Delaurentis Distributing Inc",
    "wof:placetype":"venue"
},
  "geometry": {"coordinates":[-73.074701,40.853499],"type":"Point"}
}