{
  "type": "Feature",
  "properties": {
    "addr:full":"333 Broadway Amityville NY 11701",
    "addr:housenumber":"333",
    "addr:postcode":"11701",
    "addr:street":"Broadway",
    "iso:country":"US",
    "sg:address":"333 Broadway",
    "sg:city":"Amityville",
    "sg:classifiers":[
        {
            "category":"Health Services",
            "subcategory":"Doctor",
            "type":"Services"
        }
    ],
    "sg:phone":"+1 631 789 2020",
    "sg:postcode":"11701",
    "sg:province":"NY",
    "sg:tags":[
        "physician",
        "medical",
        "surgeon"
    ],
    "wof:name":"Vinod Gulati MD",
    "wof:placetype":"venue"
},
  "geometry": {"coordinates":[-73.416865,40.681239],"type":"Point"}
}