{
  "type": "Feature",
  "properties": {
    "addr:full":"56 Kinghorn St Staten Island NY 10312",
    "addr:housenumber":"56",
    "addr:postcode":"10312",
    "addr:street":"Kinghorn St",
    "iso:country":"US",
    "sg:address":"56 Kinghorn St",
    "sg:city":"Staten Island",
    "sg:classifiers":[
        {
            "category":"Building & Trades",
            "subcategory":"Pest Control",
            "type":"Services"
        }
    ],
    "sg:phone":"+1 800 284 6266",
    "sg:postcode":"10312",
    "sg:province":"NY",
    "wof:name":"Central Exterminating Corp",
    "wof:placetype":"venue"
},
  "geometry": {"coordinates":[-74.15986700000001,40.53234],"type":"Point"}
}