{
  "type": "Feature",
  "properties": {
    "addr:full":"6913 20th Ave Brooklyn NY 11204",
    "addr:housenumber":"6913",
    "addr:postcode":"11204",
    "addr:street":"20Th Ave",
    "iso:country":"US",
    "sg:address":"6913 20th Ave",
    "sg:city":"Brooklyn",
    "sg:classifiers":[
        {
            "category":"Real Estate",
            "subcategory":"Architect",
            "type":"Services"
        }
    ],
    "sg:phone":"+1   ",
    "sg:postcode":"11204",
    "sg:province":"NY",
    "sg:tags":[
        "consulting",
        "architectural",
        "business",
        "eng"
    ],
    "wof:name":"DAlessandro & Associates",
    "wof:placetype":"venue"
},
  "geometry": {"coordinates":[-73.98869999999999,40.613704],"type":"Point"}
}