{
  "type": "Feature",
  "properties": {
    "addr:full":"55 Nesconset Hwy Port Jeffrsn Sta NY 11776",
    "addr:housenumber":"55",
    "addr:postcode":"11776",
    "addr:street":"Nesconset Hwy Port Jeffrsn Sta",
    "iso:country":"US",
    "sg:address":"55 Nesconset Hwy",
    "sg:city":"Port Jeffrsn Sta",
    "sg:classifiers":[
        {
            "category":"Professional",
            "type":"Services"
        }
    ],
    "sg:phone":"+1 631 474 7800",
    "sg:postcode":"11776",
    "sg:province":"NY",
    "sg:tags":[
        "establishment"
    ],
    "wof:name":"American Datagraph Inc",
    "wof:placetype":"venue"
},
  "geometry": {"coordinates":[-73.061089,40.912295],"type":"Point"}
}