{
  "type": "Feature",
  "properties": {
    "iso:country":"US",
    "sg:address":"88 Cuttermill Rd",
    "sg:city":"Great Neck",
    "sg:classifiers":[
        {
            "category":"Professional",
            "type":"Services"
        }
    ],
    "sg:phone":"+1 516 829 1702",
    "sg:postcode":"11021",
    "sg:province":"NY",
    "sg:tags":[
        "establishment"
    ],
    "wof:name":"Humboldt Associates",
    "wof:placetype":"venue"
},
  "geometry": {"coordinates":[-73.727766,40.787268],"type":"Point"}
}