{
  "type": "Feature",
  "properties": {
    "addr:full":"694 Central Ave Cedarhurst NY 11516",
    "addr:housenumber":"694",
    "addr:postcode":"11516",
    "addr:street":"Central Ave",
    "iso:country":"US",
    "sg:address":"694 Central Ave",
    "sg:city":"Cedarhurst",
    "sg:classifiers":[
        {
            "category":"Shopping",
            "subcategory":"Clothing, Apparel, & Fashions",
            "type":"Retail Goods"
        }
    ],
    "sg:phone":"+1 516 295 2304",
    "sg:postcode":"11516",
    "sg:province":"NY",
    "wof:name":"Bernard's Sister LTD",
    "wof:placetype":"venue"
},
  "geometry": {"coordinates":[-73.71914099999999,40.624959],"type":"Point"}
}