{
  "type": "Feature",
  "properties": {
    "iso:country":"US",
    "sg:address":"1197 Sherman Ave",
    "sg:city":"Bronx",
    "sg:classifiers":[
        {
            "category":"Organizations",
            "subcategory":"Religious Organization",
            "type":"Services"
        }
    ],
    "sg:phone":"+1 718 590 0867",
    "sg:postcode":"10456",
    "sg:province":"NY",
    "wof:name":"The Voice Of Patmos Church",
    "wof:placetype":"venue"
},
  "geometry": {"coordinates":[-73.916202,40.833574],"type":"Point"}
}