{
  "type": "Feature",
  "properties": {
    "iso:country":"US",
    "sg:address":"1660 Coney Island Ave",
    "sg:city":"Brooklyn",
    "sg:classifiers":[
        {
            "category":"Wholesale",
            "subcategory":"Electrical",
            "type":"Manufacturing & Wholesale Goods"
        }
    ],
    "sg:phone":"+1 718 376 6622",
    "sg:postcode":"11230",
    "sg:province":"NY",
    "sg:tags":[
        "fixture",
        "lighting",
        "supply"
    ],
    "wof:name":"Elm Lighting Inc",
    "wof:placetype":"venue"
},
  "geometry": {"coordinates":[-73.96375,40.616962],"type":"Point"}
}