{
  "type": "Feature",
  "properties": {
    "addr:full":"623 Lincoln Ave Brooklyn NY 11208",
    "addr:housenumber":"623",
    "addr:postcode":"11208",
    "addr:street":"Lincoln Ave",
    "iso:country":"US",
    "sg:address":"623 Lincoln Ave",
    "sg:city":"Brooklyn",
    "sg:phone":"+1 718 827 3679",
    "sg:postcode":"11208",
    "sg:province":"NY",
    "sg:tags":[
        "oil"
    ],
    "wof:name":"Jennings & Jennings Fuel Oil",
    "wof:placetype":"venue"
},
  "geometry": {"coordinates":[-73.86676300000001,40.674422],"type":"Point"}
}