{
  "type": "Feature",
  "properties": {
    "iso:country":"US",
    "sg:address":"217 E 60 St",
    "sg:city":"New York",
    "sg:classifiers":[
        {
            "category":"Wholesale",
            "subcategory":"Durable Goods & Equipment",
            "type":"Manufacturing & Wholesale Goods"
        }
    ],
    "sg:phone":"+1 212 421 6591",
    "sg:postcode":"10022",
    "sg:province":"NY",
    "sg:tags":[
        "antique"
    ],
    "wof:name":"David Duncan Ltd",
    "wof:placetype":"venue"
},
  "geometry": {"coordinates":[-73.964125,40.761453],"type":"Point"}
}