{
  "type": "Feature",
  "properties": {
    "addr:full":"13 Taylor St Oxford NY 13830",
    "addr:housenumber":"13",
    "addr:postcode":"13830",
    "addr:street":"Taylor St",
    "iso:country":"US",
    "sg:address":"13 Taylor St",
    "sg:city":"Oxford",
    "sg:classifiers":[
        {
            "category":"Organizations",
            "subcategory":"Religious Organization",
            "type":"Services"
        }
    ],
    "sg:phone":"+1 607 843 7043",
    "sg:postcode":"13830",
    "sg:province":"NY",
    "sg:tags":[
        "church"
    ],
    "wof:name":"Pilgrim Holiness Chr John Mssr",
    "wof:placetype":"venue"
},
  "geometry": {"coordinates":[-75.598782,42.443517],"type":"Point"}
}