{
  "type": "Feature",
  "properties": {
    "addr:full":"177 Wallabout St Brooklyn NY 11206",
    "addr:housenumber":"177",
    "addr:postcode":"11206",
    "addr:street":"Wallabout St",
    "iso:country":"US",
    "sg:address":"177 Wallabout St",
    "sg:city":"Brooklyn",
    "sg:classifiers":[
        {
            "category":"Organizations",
            "subcategory":"Religious Organization",
            "type":"Services"
        }
    ],
    "sg:phone":"+1 718 384 4297",
    "sg:postcode":"11206",
    "sg:province":"NY",
    "sg:tags":[
        "clergy"
    ],
    "wof:name":"Yakov C Deutsch",
    "wof:placetype":"venue"
},
  "geometry": {"coordinates":[-73.95285800000001,40.700299],"type":"Point"}
}