{
  "type": "Feature",
  "properties": {
    "iso:country":"US",
    "sg:address":"713 Colonial Dr",
    "sg:city":"Newark",
    "sg:classifiers":[
        {
            "category":"Shopping",
            "subcategory":"Music",
            "type":"Retail Goods"
        }
    ],
    "sg:phone":"+1   ",
    "sg:postcode":"14513",
    "sg:province":"NY",
    "wof:name":"Mezzo Music",
    "wof:placetype":"venue"
},
  "geometry": {"coordinates":[-77.108051,43.040354],"type":"Point"}
}