{
  "type": "Feature",
  "properties": {
    "iso:country":"US",
    "sg:address":"1165 Muckey Rd",
    "sg:city":"Marathon",
    "sg:classifiers":[
        {
            "category":"Travel",
            "subcategory":"Campground",
            "type":"Entertainment"
        }
    ],
    "sg:phone":"+1 607 849 3300",
    "sg:postcode":"13803",
    "sg:province":"NY",
    "wof:name":"Country Hills",
    "wof:placetype":"venue"
},
  "geometry": {"coordinates":[-76.079583,42.460516],"type":"Point"}
}