{
  "type": "Feature",
  "properties": {
    "addr:full":"41 W Main St Gowanda NY 14070",
    "addr:housenumber":"41",
    "addr:postcode":"14070",
    "addr:street":"W Main St",
    "iso:country":"US",
    "sg:address":"41 W Main St",
    "sg:city":"Gowanda",
    "sg:classifiers":[
        {
            "category":"Shopping",
            "subcategory":"Pharmacy",
            "type":"Retail Goods"
        }
    ],
    "sg:phone":"+1 716 532 8000",
    "sg:postcode":"14070",
    "sg:province":"NY",
    "wof:name":"Gowanda Pharmacy",
    "wof:placetype":"venue"
},
  "geometry": {"coordinates":[-78.936239,42.462964],"type":"Point"}
}