{
  "type": "Feature",
  "properties": {
    "addr:full":"70 New York Ave Smithtown NY 11787",
    "addr:housenumber":"70",
    "addr:postcode":"11787",
    "addr:street":"New York Ave",
    "iso:country":"US",
    "sg:address":"70 New York Ave",
    "sg:city":"Smithtown",
    "sg:classifiers":[
        {
            "category":"Organizations",
            "subcategory":"Religious Organization",
            "type":"Services"
        }
    ],
    "sg:phone":"+1 631 366 1000",
    "sg:postcode":"11787",
    "sg:province":"NY",
    "wof:name":"Youth With A Mission",
    "wof:placetype":"venue"
},
  "geometry": {"coordinates":[-73.199303,40.854],"type":"Point"}
}