{
  "type": "Feature",
  "properties": {
    "iso:country":"US",
    "sg:address":"2753 Brown Rd",
    "sg:city":"Newfane",
    "sg:classifiers":[
        {
            "category":"Building & Trades",
            "subcategory":"Construction",
            "type":"Services"
        }
    ],
    "sg:phone":"+1 716 778 7785",
    "sg:postcode":"14108",
    "sg:province":"NY",
    "sg:tags":[
        "contractor"
    ],
    "wof:name":"Schwartz T A Roofing & Sdng",
    "wof:placetype":"venue"
},
  "geometry": {"coordinates":[-78.668927,43.271347],"type":"Point"}
}