{
  "type": "Feature",
  "properties": {
    "addr:full":"890 Pulaski Hwy Goshen NY 10924",
    "addr:housenumber":"890",
    "addr:postcode":"10924",
    "addr:street":"Pulaski Hwy",
    "iso:country":"US",
    "sg:address":"890 Pulaski Hwy",
    "sg:city":"Goshen",
    "sg:classifiers":[
        {
            "category":"Professional",
            "subcategory":"Employment Agencies",
            "type":"Services"
        }
    ],
    "sg:phone":"+1 845 651 7100",
    "sg:postcode":"10924",
    "sg:province":"NY",
    "sg:tags":[
        "consultant",
        "outplacement"
    ],
    "wof:name":"Employment Service Dept",
    "wof:placetype":"venue"
},
  "geometry": {"coordinates":[-74.40003299999999,41.33877],"type":"Point"}
}