{
  "type": "Feature",
  "properties": {
    "iso:country":"US",
    "sg:address":"1228 Middle Country Rd",
    "sg:city":"Selden",
    "sg:classifiers":[
        {
            "category":"Food & Beverages",
            "subcategory":"Groceries & Convenience Stores",
            "type":"Retail Goods"
        }
    ],
    "sg:phone":"+1   ",
    "sg:postcode":"11784",
    "sg:province":"NY",
    "wof:name":"New Selden House Of Spice",
    "wof:placetype":"venue"
},
  "geometry": {"coordinates":[-73.055291,40.862721],"type":"Point"}
}