{
  "type": "Feature",
  "properties": {
    "iso:country":"US",
    "sg:address":"316 Wendhurst Dr",
    "sg:city":"Rochester",
    "sg:classifiers":[
        {
            "category":"Building & Trades",
            "subcategory":"Construction",
            "type":"Services"
        }
    ],
    "sg:phone":"+1 585 663 8673",
    "sg:postcode":"14616",
    "sg:province":"NY",
    "sg:tags":[
        "downspouts",
        "gutter",
        "contractor"
    ],
    "wof:name":"Northeastern Gutter Cleaning",
    "wof:placetype":"venue"
},
  "geometry": {"coordinates":[-77.636982,43.232654],"type":"Point"}
}