{
  "type": "Feature",
  "properties": {
    "iso:country":"US",
    "sg:address":"5 Fair Meadow Dr",
    "sg:city":"Brewster",
    "sg:classifiers":[
        {
            "category":"Organizations",
            "subcategory":"Professional Association",
            "type":"Services"
        }
    ],
    "sg:phone":"+1 845 279 4935",
    "sg:postcode":"10509",
    "sg:province":"NY",
    "wof:name":"Astrologers' Guild Of America",
    "wof:placetype":"venue"
},
  "geometry": {"coordinates":[-73.585801,41.382936],"type":"Point"}
}