{
  "type": "Feature",
  "properties": {
    "iso:country":"US",
    "sg:address":"1065 Sheridan Dr",
    "sg:city":"Tonawanda",
    "sg:classifiers":[
        {
            "category":"Restaurant",
            "type":"Food & Drink"
        }
    ],
    "sg:phone":"+1 716 332 1010",
    "sg:postcode":"14150",
    "sg:province":"NY",
    "sg:tags":[
        "pizza"
    ],
    "wof:name":"Palumbo's Pizzeria",
    "wof:placetype":"venue"
},
  "geometry": {"coordinates":[-78.89308800000001,42.980672],"type":"Point"}
}