{
  "type": "Feature",
  "properties": {
    "addr:full":"2498 Frederick Douglass Blvd New York NY 10030",
    "addr:housenumber":"2498",
    "addr:postcode":"10030",
    "addr:street":"Frederick Douglass Blvd",
    "iso:country":"US",
    "sg:address":"2498 Frederick Douglass Blvd",
    "sg:city":"New York",
    "sg:classifiers":[
        {
            "category":"Shopping",
            "subcategory":"Shoes",
            "type":"Retail Goods"
        }
    ],
    "sg:phone":"+1 212 281 1723",
    "sg:postcode":"10030",
    "sg:province":"NY",
    "sg:tags":[
        "store"
    ],
    "sg:website":"www.vaultharlem.com",
    "wof:name":"The Vault",
    "wof:placetype":"venue"
},
  "geometry": {"coordinates":[-73.946966,40.815439],"type":"Point"}
}