{
  "type": "Feature",
  "properties": {
    "iso:country":"US",
    "sg:address":"70 Locust Ave",
    "sg:city":"New Rochelle",
    "sg:classifiers":[
        {
            "category":"Real Estate",
            "subcategory":"Real Estate Agent",
            "type":"Services"
        }
    ],
    "sg:phone":"+1 914 633 7965",
    "sg:postcode":"10801",
    "sg:province":"NY",
    "wof:name":"60-70 Owners Corp",
    "wof:placetype":"venue"
},
  "geometry": {"coordinates":[-73.777807,40.908113],"type":"Point"}
}