{
  "type": "Feature",
  "properties": {
    "addr:full":"50 James Wilkinson Rd Rock Tavern NY 12575",
    "addr:housenumber":"50",
    "addr:postcode":"12575",
    "addr:street":"James Wilkinson Rd",
    "iso:country":"US",
    "sg:address":"50 James Wilkinson Rd",
    "sg:city":"Rock Tavern",
    "sg:classifiers":[
        {
            "category":"Building & Trades",
            "subcategory":"Plumbing",
            "type":"Services"
        }
    ],
    "sg:phone":"+1 845 496 7953",
    "sg:postcode":"12575",
    "sg:province":"NY",
    "sg:tags":[
        "contractor"
    ],
    "wof:name":"Green Plumbing Heating & Mech",
    "wof:placetype":"venue"
},
  "geometry": {"coordinates":[-74.181591,41.466238],"type":"Point"}
}