{
  "type": "Feature",
  "properties": {
    "addr:full":"809 Bloomingburg Rd Bloomingburg NY 12721",
    "addr:housenumber":"809",
    "addr:postcode":"12721",
    "addr:street":"Bloomingburg Rd",
    "iso:country":"US",
    "sg:address":"809 Bloomingburg Rd",
    "sg:city":"Bloomingburg",
    "sg:classifiers":[
        {
            "category":"Bars & Pubs",
            "type":"Food & Drink"
        }
    ],
    "sg:phone":"+1 845 733 6684",
    "sg:postcode":"12721",
    "sg:province":"NY",
    "wof:name":"Last Chance Restaurant",
    "wof:placetype":"venue"
},
  "geometry": {"coordinates":[-74.43110799999999,41.546632],"type":"Point"}
}