{
  "type": "Feature",
  "properties": {
    "addr:full":"1066 Maple St Genoa NY 13071",
    "addr:housenumber":"1066",
    "addr:postcode":"13071",
    "addr:street":"Maple St",
    "iso:country":"US",
    "sg:address":"1066 Maple St",
    "sg:city":"Genoa",
    "sg:classifiers":[
        {
            "category":"Building & Trades",
            "subcategory":"Construction",
            "type":"Services"
        }
    ],
    "sg:phone":"+1 315 497 9644",
    "sg:postcode":"13071",
    "sg:province":"NY",
    "sg:tags":[
        "house"
    ],
    "wof:name":"Ser Construction",
    "wof:placetype":"venue"
},
  "geometry": {"coordinates":[-76.53565399999999,42.668584],"type":"Point"}
}