{
  "type": "Feature",
  "properties": {
    "addr:full":"20 Gilbert Ave Smithtown NY 11787",
    "addr:housenumber":"20",
    "addr:postcode":"11787",
    "addr:street":"Gilbert Ave",
    "iso:country":"US",
    "sg:address":"20 Gilbert Ave",
    "sg:city":"Smithtown",
    "sg:classifiers":[
        {
            "category":"Banks & Credit Unions",
            "subcategory":"Investment Brokerage",
            "type":"Services"
        }
    ],
    "sg:phone":"+1 631 863 3100",
    "sg:postcode":"11787",
    "sg:province":"NY",
    "sg:tags":[
        "advisory",
        "financial"
    ],
    "wof:name":"Pointe Capital",
    "wof:placetype":"venue"
},
  "geometry": {"coordinates":[-73.170298,40.840072],"type":"Point"}
}