{
  "type": "Feature",
  "properties": {
    "addr:full":"6997 Woodchuck Hill Rd Fayetteville NY 13066",
    "addr:housenumber":"6997",
    "addr:postcode":"13066",
    "addr:street":"Woodchuck Hill Rd",
    "iso:country":"US",
    "sg:address":"6997 Woodchuck Hill Rd",
    "sg:city":"Fayetteville",
    "sg:classifiers":[
        {
            "category":"Real Estate",
            "subcategory":"Real Estate Operator",
            "type":"Services"
        }
    ],
    "sg:phone":"+1 315 451 0940",
    "sg:postcode":"13066",
    "sg:province":"NY",
    "sg:tags":[
        "building",
        "nonresidential"
    ],
    "wof:name":"Oswego Center Association",
    "wof:placetype":"venue"
},
  "geometry": {"coordinates":[-76.03384,43.010522],"type":"Point"}
}