{
  "type": "Feature",
  "properties": {
    "iso:country":"US",
    "sg:address":"405 Montauk Hwy",
    "sg:city":"Wainscott",
    "sg:classifiers":[
        {
            "category":"Building & Trades",
            "subcategory":"Construction",
            "type":"Services"
        },
        {
            "category":"Real Estate",
            "subcategory":"Real Estate Services",
            "type":"Services"
        },
        {
            "category":"Real Estate",
            "subcategory":"Surveying",
            "type":"Services"
        },
        {
            "category":"Banks & Credit Unions",
            "subcategory":"Financial Services",
            "type":"Services"
        },
        {
            "category":"Real Estate",
            "subcategory":"Architect",
            "type":"Services"
        }
    ],
    "sg:phone":"+1 631 537 8500",
    "sg:postcode":"11975",
    "sg:province":"NY",
    "sg:tags":[
        "architects'",
        "land",
        "consultant",
        "expediting",
        "builders'",
        "planning"
    ],
    "sg:website":"http://www.lps-hamptons.com",
    "wof:name":"Land Planning Services Ltd.",
    "wof:placetype":"venue"
},
  "geometry": {"coordinates":[-72.25402099999999,40.946339],"type":"Point"}
}