{
  "type": "Feature",
  "properties": {
    "iso:country":"US",
    "sg:address":"5206 State Highway 23",
    "sg:city":"Oneonta",
    "sg:classifiers":[
        {
            "category":"Travel",
            "subcategory":"Hotels & Motels",
            "type":"Entertainment"
        },
        {
            "category":"Retail",
            "subcategory":"Event Space",
            "type":"Services"
        },
        {
            "category":"Travel",
            "subcategory":"Resort",
            "type":"Entertainment"
        }
    ],
    "sg:phone":"+1 800 345 8082",
    "sg:postcode":"13820",
    "sg:province":"NY",
    "sg:tags":[
        "facility",
        "banquet",
        "reception",
        "lodging",
        "corporate",
        "hall"
    ],
    "sg:website":"http://ad.doubleclick.net/clk;223371278;47096201;d?http://www.holidayinn.com/redirect?path=hd&brandCode=hi&hotelCode=onhny&_PMID=99601036&cm_mmc=mdpr-_-yellowpages-_-hi-_-onhny",
    "wof:name":"Holiday Inn Oneonta-Cooperstown Area",
    "wof:placetype":"venue"
},
  "geometry": {"coordinates":[-75.02307500000001,42.44735],"type":"Point"}
}