{
  "type": "Feature",
  "properties": {
    "addr:full":"3488 Warners Rd Camillus NY 13031",
    "addr:housenumber":"3488",
    "addr:postcode":"13031",
    "addr:street":"Warners Rd",
    "iso:country":"US",
    "sg:address":"3488 Warners Rd",
    "sg:city":"Camillus",
    "sg:classifiers":[
        {
            "category":"Building & Trades",
            "subcategory":"Construction",
            "type":"Services"
        }
    ],
    "sg:phone":"+1 315 488 2775",
    "sg:postcode":"13031",
    "sg:province":"NY",
    "sg:tags":[
        "house"
    ],
    "wof:name":"Rocky Mountain Builders",
    "wof:placetype":"venue"
},
  "geometry": {"coordinates":[-76.270336,43.065784],"type":"Point"}
}