{
  "type": "Feature",
  "properties": {
    "iso:country":"US",
    "sg:address":"22 Center Ct",
    "sg:city":"Center Moriches",
    "sg:classifiers":[
        {
            "category":"Professional",
            "subcategory":"Computer Services",
            "type":"Services"
        }
    ],
    "sg:phone":"+1 631 874 3281",
    "sg:postcode":"11934",
    "sg:province":"NY",
    "sg:tags":[
        "repair"
    ],
    "wof:name":"A & M Electronics",
    "wof:placetype":"venue"
},
  "geometry": {"coordinates":[-72.804419,40.820819],"type":"Point"}
}