{
  "type": "Feature",
  "properties": {
    "iso:country":"US",
    "sg:address":"170 Great Neck Rd",
    "sg:city":"Great Neck",
    "sg:classifiers":[
        {
            "category":"Professional",
            "subcategory":"Detective & Security Services",
            "type":"Services"
        }
    ],
    "sg:phone":"+1 516 829 8282",
    "sg:postcode":"11021",
    "sg:province":"NY",
    "sg:tags":[
        "investigator"
    ],
    "wof:name":"JTB Investigation Svc",
    "wof:placetype":"venue"
},
  "geometry": {"coordinates":[-73.732078,40.781672],"type":"Point"}
}