{
  "type": "Feature",
  "properties": {
    "iso:country":"US",
    "sg:address":"27 Montclair Ave",
    "sg:city":"Smithtown",
    "sg:classifiers":[
        {
            "category":"Building & Trades",
            "subcategory":"Construction",
            "type":"Services"
        }
    ],
    "sg:phone":"+1 631 361 5121",
    "sg:postcode":"11780",
    "sg:province":"NY",
    "sg:tags":[
        "masonry",
        "contractor"
    ],
    "wof:name":"Vita & Yarusso Inc",
    "wof:placetype":"venue"
},
  "geometry": {"coordinates":[-73.164793,40.861906],"type":"Point"}
}