{
  "type": "Feature",
  "properties": {
    "addr:full":"500 Oak St Copiague NY 11726",
    "addr:housenumber":"500",
    "addr:postcode":"11726",
    "addr:street":"Oak St",
    "iso:country":"US",
    "sg:address":"500 Oak St",
    "sg:city":"Copiague",
    "sg:classifiers":[
        {
            "category":"Shopping",
            "subcategory":"Stationery & Office Supplies",
            "type":"Retail Goods"
        },
        {
            "category":"Shopping",
            "subcategory":"Gifts & Souvenirs",
            "type":"Retail Goods"
        }
    ],
    "sg:phone":"+1 631 691 5613",
    "sg:postcode":"11726",
    "sg:province":"NY",
    "sg:tags":[
        "stationer"
    ],
    "wof:name":"Flame Cards & Gifts Inc",
    "wof:placetype":"venue"
},
  "geometry": {"coordinates":[-73.39858,40.68007],"type":"Point"}
}