{
  "type": "Feature",
  "properties": {
    "addr:full":"1388 2nd Ave Manhattan NY 10021",
    "addr:housenumber":"1388",
    "addr:postcode":"10021",
    "addr:street":"2Nd Ave",
    "iso:country":"US",
    "sg:address":"1388 2nd Ave",
    "sg:city":"Manhattan",
    "sg:classifiers":[
        {
            "category":"Restaurant",
            "type":"Food & Drink"
        }
    ],
    "sg:phone":"+1 212 288 8066",
    "sg:postcode":"10021",
    "sg:province":"NY",
    "sg:tags":[
        "chinese"
    ],
    "wof:name":"Shanghai",
    "wof:placetype":"venue"
},
  "geometry": {"coordinates":[-73.95854,40.768293],"type":"Point"}
}