{
  "type": "Feature",
  "properties": {
    "addr:full":"293 S Union Rd Buffalo NY 14221",
    "addr:housenumber":"293",
    "addr:postcode":"14221",
    "addr:street":"S Union Rd",
    "iso:country":"US",
    "sg:address":"293 S Union Rd",
    "sg:city":"Buffalo",
    "sg:classifiers":[
        {
            "category":"Real Estate",
            "subcategory":"Real Estate Agent",
            "type":"Services"
        }
    ],
    "sg:phone":"+1 716 634 7432",
    "sg:postcode":"14221",
    "sg:province":"NY",
    "wof:name":"Deibel",
    "wof:placetype":"venue"
},
  "geometry": {"coordinates":[-78.754897,42.952741],"type":"Point"}
}