{
  "type": "Feature",
  "properties": {
    "iso:country":"US",
    "sg:address":"2539 Middle Country Rd Ste 5",
    "sg:city":"Centereach",
    "sg:classifiers":[
        {
            "category":"Health Services",
            "subcategory":"Doctor",
            "type":"Services"
        }
    ],
    "sg:phone":"+1 631 580 1740",
    "sg:postcode":"11720",
    "sg:province":"NY",
    "sg:tags":[
        "practice",
        "family"
    ],
    "wof:name":"Randall Michael L DO",
    "wof:placetype":"venue"
},
  "geometry": {"coordinates":[-73.102046,40.858726],"type":"Point"}
}