{
  "type": "Feature",
  "properties": {
    "addr:full":"137 E 55th St New York NY 10022",
    "addr:housenumber":"137",
    "addr:postcode":"10022",
    "addr:street":"E 55Th St",
    "iso:country":"US",
    "sg:address":"137 E 55th St",
    "sg:city":"New York",
    "sg:classifiers":[
        {
            "category":"Bars & Pubs",
            "subcategory":"Lounge",
            "type":"Food & Drink"
        }
    ],
    "sg:postcode":"10022",
    "sg:province":"NY",
    "wof:name":"Covet",
    "wof:placetype":"venue"
},
  "geometry": {"coordinates":[-73.96979,40.759523],"type":"Point"}
}