{
  "type": "Feature",
  "properties": {
    "addr:full":"305 Mountain Ave Cairo NY 12413",
    "addr:housenumber":"305",
    "addr:postcode":"12413",
    "addr:street":"Mountain Ave",
    "iso:country":"US",
    "sg:address":"305 Mountain Ave",
    "sg:city":"Cairo",
    "sg:classifiers":[
        {
            "category":"Recreation",
            "type":"Entertainment"
        }
    ],
    "sg:phone":"+1 518 622 3329",
    "sg:postcode":"12413",
    "sg:province":"NY",
    "sg:tags":[
        "stable"
    ],
    "wof:name":"Equine Edge",
    "wof:placetype":"venue"
},
  "geometry": {"coordinates":[-74.017538,42.284555],"type":"Point"}
}