{
  "type": "Feature",
  "properties": {
    "iso:country":"US",
    "sg:address":"209 Spring St",
    "sg:city":"Lawrence",
    "sg:classifiers":[
        {
            "category":"Building & Trades",
            "subcategory":"Landscaping Services",
            "type":"Services"
        }
    ],
    "sg:phone":"+1 516 239 6233",
    "sg:postcode":"11559",
    "sg:province":"NY",
    "wof:name":"Aurelio Afiero Sons Ldscpg Des",
    "wof:placetype":"venue"
},
  "geometry": {"coordinates":[-73.735083,40.621128],"type":"Point"}
}