{
  "type": "Feature",
  "properties": {
    "addr:full":"70 Roslyn Rd Roslyn Heights NY 11577",
    "addr:housenumber":"70",
    "addr:postcode":"11577",
    "addr:street":"Roslyn Rd",
    "iso:country":"US",
    "sg:address":"70 Roslyn Rd",
    "sg:city":"Roslyn Heights",
    "sg:classifiers":[
        {
            "category":"Wholesale",
            "subcategory":"Auto Parts",
            "type":"Manufacturing & Wholesale Goods"
        }
    ],
    "sg:phone":"+1 516 625 0680",
    "sg:postcode":"11577",
    "sg:province":"NY",
    "wof:name":"Gisele Kehl",
    "wof:placetype":"venue"
},
  "geometry": {"coordinates":[-73.640697,40.791452],"type":"Point"}
}