{
  "type": "Feature",
  "properties": {
    "iso:country":"US",
    "sg:address":"15 New St",
    "sg:city":"Huntington",
    "sg:classifiers":[
        {
            "category":"Restaurant",
            "type":"Food & Drink"
        }
    ],
    "sg:phone":"+1 631 421 7361",
    "sg:postcode":"11743",
    "sg:province":"NY",
    "sg:tags":[
        "house",
        "seafood",
        "steak",
        "italian"
    ],
    "wof:name":"Tello",
    "wof:placetype":"venue"
},
  "geometry": {"coordinates":[-73.427289,40.87053],"type":"Point"}
}