{
  "type": "Feature",
  "properties": {
    "iso:country":"US",
    "sg:address":"52 Sintsink Dr E",
    "sg:city":"Port Washington",
    "sg:classifiers":[
        {
            "category":"Building & Trades",
            "subcategory":"Construction",
            "type":"Services"
        }
    ],
    "sg:phone":"+1 516 767 1158",
    "sg:postcode":"11050",
    "sg:province":"NY",
    "sg:tags":[
        "general",
        "contractor"
    ],
    "wof:name":"A Ressa Contracting",
    "wof:placetype":"venue"
},
  "geometry": {"coordinates":[-73.706959,40.838913],"type":"Point"}
}