{
  "type": "Feature",
  "properties": {
    "iso:country":"US",
    "sg:address":"1430 Broadway Frnt 1",
    "sg:city":"New York",
    "sg:classifiers":[
        {
            "category":"Shopping",
            "subcategory":"Pharmacy",
            "type":"Retail Goods"
        }
    ],
    "sg:phone":"+1 212 768 4935",
    "sg:postcode":"10018",
    "sg:province":"NY",
    "sg:tags":[
        "drugstore"
    ],
    "wof:name":"Duanereade",
    "wof:placetype":"venue"
},
  "geometry": {"coordinates":[-73.986707,40.75422],"type":"Point"}
}