{
  "type": "Feature",
  "properties": {
    "addr:full":"522 6th Ave Brooklyn NY 11215",
    "addr:housenumber":"522",
    "addr:postcode":"11215",
    "addr:street":"6Th Ave",
    "iso:country":"US",
    "sg:address":"522 6th Ave",
    "sg:city":"Brooklyn",
    "sg:classifiers":[
        {
            "category":"Food & Beverages",
            "subcategory":"Groceries & Convenience Stores",
            "type":"Retail Goods"
        }
    ],
    "sg:phone":"+1 718 832 2732",
    "sg:postcode":"11215",
    "sg:province":"NY",
    "sg:tags":[
        "grocer"
    ],
    "wof:name":"Ny Food Ctr",
    "wof:placetype":"venue"
},
  "geometry": {"coordinates":[-73.98594799999999,40.66563],"type":"Point"}
}