{
  "type": "Feature",
  "properties": {
    "addr:full":"77 W 85 St New York NY 10024",
    "addr:housenumber":"77",
    "addr:postcode":"10024",
    "addr:street":"W 85 St",
    "iso:country":"US",
    "sg:address":"77 W 85 St",
    "sg:city":"New York",
    "sg:classifiers":[
        {
            "category":"Real Estate",
            "subcategory":"Real Estate Operator",
            "type":"Services"
        }
    ],
    "sg:phone":"+1 212 362 0475",
    "sg:postcode":"10024",
    "sg:province":"NY",
    "sg:tags":[
        "building",
        "apartment"
    ],
    "wof:name":"Mushekian Margaret",
    "wof:placetype":"venue"
},
  "geometry": {"coordinates":[-73.971368,40.785166],"type":"Point"}
}