{
  "type": "Feature",
  "properties": {
    "addr:full":"126 E 56 St New York NY 10022",
    "addr:housenumber":"126;56",
    "addr:postcode":"10022",
    "addr:street":"E;St",
    "iso:country":"US",
    "sg:address":"126 E 56 St",
    "sg:city":"New York",
    "sg:classifiers":[
        {
            "category":"Professional",
            "subcategory":"Lawyer & Legal Services",
            "type":"Services"
        }
    ],
    "sg:phone":"+1 212 755 0808",
    "sg:postcode":"10022",
    "sg:province":"NY",
    "wof:name":"Law Office of Mark Zimmett",
    "wof:placetype":"venue"
},
  "geometry": {"coordinates":[-73.970547,40.760681],"type":"Point"}
}