{
  "type": "Feature",
  "properties": {
    "iso:country":"US",
    "sg:address":"1218 Seneca St",
    "sg:city":"Buffalo",
    "sg:classifiers":[
        {
            "category":"Organizations",
            "subcategory":"Religious Organization",
            "type":"Services"
        }
    ],
    "sg:phone":"+1 716 825 6742",
    "sg:postcode":"14210",
    "sg:province":"NY",
    "sg:tags":[
        "church"
    ],
    "wof:name":"Seneca Street Untd Mthdst Chr",
    "wof:placetype":"venue"
},
  "geometry": {"coordinates":[-78.832409,42.869803],"type":"Point"}
}