{
  "type": "Feature",
  "properties": {
    "iso:country":"US",
    "sg:address":"757 Nostrand Ave",
    "sg:city":"Brooklyn",
    "sg:classifiers":[
        {
            "category":"Personal",
            "subcategory":"Barber",
            "type":"Services"
        }
    ],
    "sg:phone":"+1 718 773 9874",
    "sg:postcode":"11216",
    "sg:province":"NY",
    "wof:name":"Foreign Accent Unisex Barber",
    "wof:placetype":"venue"
},
  "geometry": {"coordinates":[-73.950332,40.670904],"type":"Point"}
}