{
  "type": "Feature",
  "properties": {
    "iso:country":"US",
    "sg:address":"27 Handsome Ave",
    "sg:city":"Sayville",
    "sg:classifiers":[
        {
            "category":"Organizations",
            "subcategory":"Religious Organization",
            "type":"Services"
        }
    ],
    "sg:phone":"+1 631 589 0042",
    "sg:postcode":"11782",
    "sg:province":"NY",
    "sg:tags":[
        "church"
    ],
    "wof:name":"St Lawrence The Martyr RC Chr",
    "wof:placetype":"venue"
},
  "geometry": {"coordinates":[-73.085904,40.73002],"type":"Point"}
}