{
  "type": "Feature",
  "properties": {
    "addr:full":"108 S Main St Canandaigua NY 14424",
    "addr:housenumber":"108",
    "addr:postcode":"14424",
    "addr:street":"S Main St",
    "iso:country":"US",
    "sg:address":"108 S Main St",
    "sg:city":"Canandaigua",
    "sg:classifiers":[
        {
            "category":"Professional",
            "subcategory":"Accounting & Tax Preparation",
            "type":"Services"
        }
    ],
    "sg:phone":"+1 585 394 7660",
    "sg:postcode":"14424",
    "sg:province":"NY",
    "sg:tags":[
        "accountant"
    ],
    "wof:name":"Parrish & Brassie LLP",
    "wof:placetype":"venue"
},
  "geometry": {"coordinates":[-77.28049799999999,42.886338],"type":"Point"}
}