{
  "type": "Feature",
  "properties": {
    "iso:country":"US",
    "sg:address":"14132 224th Street",
    "sg:city":"Springfield Gardens",
    "sg:classifiers":[
        {
            "category":"Taxi",
            "type":"Transportation"
        }
    ],
    "sg:phone":"+1 718 712 8933",
    "sg:postcode":"11413",
    "sg:province":"NY",
    "wof:name":"Laurelton Car Service",
    "wof:placetype":"venue"
},
  "geometry": {"coordinates":[-73.751739,40.669042],"type":"Point"}
}