{
  "type": "Feature",
  "properties": {
    "iso:country":"US",
    "sg:address":"8 Clinton St",
    "sg:city":"New York Mills",
    "sg:classifiers":[
        {
            "category":"Personal",
            "subcategory":"Beauty Salon",
            "type":"Services"
        }
    ],
    "sg:phone":"+1 315 736 4276",
    "sg:postcode":"13417",
    "sg:province":"NY",
    "wof:name":"Hairworld Niems Hair-Skin-Nail",
    "wof:placetype":"venue"
},
  "geometry": {"coordinates":[-75.298962,43.095285],"type":"Point"}
}