{
  "type": "Feature",
  "properties": {
    "addr:full":"133 5th Ave New York NY 10003",
    "addr:housenumber":"133",
    "addr:postcode":"10003",
    "addr:street":"5Th Ave",
    "iso:country":"US",
    "sg:address":"133 5th Ave",
    "sg:city":"New York",
    "sg:classifiers":[
        {
            "category":"Professional",
            "subcategory":"Management & Consulting",
            "type":"Services"
        }
    ],
    "sg:phone":"+1 212 358 0800",
    "sg:postcode":"10003",
    "sg:province":"NY",
    "sg:tags":[
        "counselor",
        "public",
        "relations"
    ],
    "sg:website":"www.cliffordpr.com",
    "wof:name":"Clifford Public Relations",
    "wof:placetype":"venue"
},
  "geometry": {"coordinates":[-73.99137399999999,40.739087],"type":"Point"}
}