{
  "type": "Feature",
  "properties": {
    "iso:country":"US",
    "sg:address":"46 Saratoga Blvd",
    "sg:city":"Island Park",
    "sg:classifiers":[
        {
            "category":"Wholesale",
            "subcategory":"Medical Equipment & Supplies",
            "type":"Manufacturing & Wholesale Goods"
        }
    ],
    "sg:phone":"+1 516 431 5700",
    "sg:postcode":"11558",
    "sg:province":"NY",
    "sg:tags":[
        "x"
    ],
    "wof:name":"Empire Rgs Inc",
    "wof:placetype":"venue"
},
  "geometry": {"coordinates":[-73.64682500000001,40.610192],"type":"Point"}
}