{
  "type": "Feature",
  "properties": {
    "addr:full":"454 Piermont Ave Piermont NY 10968",
    "addr:housenumber":"454",
    "addr:postcode":"10968",
    "addr:street":"Piermont Ave",
    "iso:country":"US",
    "sg:address":"454 Piermont Ave",
    "sg:city":"Piermont",
    "sg:classifiers":[
        {
            "category":"Shopping",
            "subcategory":"Used Merchandise",
            "type":"Retail Goods"
        },
        {
            "category":"Banks & Credit Unions",
            "subcategory":"Bank",
            "type":"Services"
        },
        {
            "category":"Organizations",
            "subcategory":"Non-profit Organization",
            "type":"Services"
        }
    ],
    "sg:phone":"+1 845 359 5753",
    "sg:postcode":"10968",
    "sg:province":"NY",
    "sg:tags":[
        "shop",
        "foundations-educational",
        "philanthropic",
        "hand",
        "resale",
        "second",
        "research",
        "charity"
    ],
    "wof:name":"Tappan Zee Thrift Shop",
    "wof:placetype":"venue"
},
  "geometry": {"coordinates":[-73.91600800000001,41.039511],"type":"Point"}
}