{
  "type": "Feature",
  "properties": {
    "addr:full":"255 47th St Brooklyn NY 11220",
    "addr:housenumber":"255",
    "addr:postcode":"11220",
    "addr:street":"47Th St",
    "iso:country":"US",
    "sg:address":"255 47th St",
    "sg:city":"Brooklyn",
    "sg:classifiers":[
        {
            "category":"Wholesale",
            "subcategory":"Home Furnishings",
            "type":"Manufacturing & Wholesale Goods"
        },
        {
            "category":"Wholesale",
            "subcategory":"Durable Goods & Equipment",
            "type":"Manufacturing & Wholesale Goods"
        }
    ],
    "sg:phone":"+1 718 439 5555",
    "sg:postcode":"11220",
    "sg:province":"NY",
    "sg:tags":[
        "linen",
        "importer",
        "drapery",
        "bedspread"
    ],
    "sg:website":"www.ramallahtrading.com",
    "wof:name":"Ramallah Trading Co Inc",
    "wof:placetype":"venue"
},
  "geometry": {"coordinates":[-74.01383800000001,40.650228],"type":"Point"}
}