{
  "type": "Feature",
  "properties": {
    "iso:country":"US",
    "sg:address":"68 Vernon Ave",
    "sg:city":"Mt Vernon",
    "sg:classifiers":[
        {
            "category":"Local Transit",
            "type":"Transportation"
        }
    ],
    "sg:phone":"+1 914 963 1448",
    "sg:postcode":"10553",
    "sg:province":"NY",
    "sg:tags":[
        "limousine"
    ],
    "wof:name":"All County Express Car & Limo",
    "wof:placetype":"venue"
},
  "geometry": {"coordinates":[-73.819081,40.90849],"type":"Point"}
}