{
  "type": "Feature",
  "properties": {
    "addr:full":"715 E Tremont Ave Bronx NY 10457",
    "addr:housenumber":"715",
    "addr:postcode":"10457",
    "addr:street":"E Tremont Ave",
    "iso:country":"US",
    "sg:address":"715 E Tremont Ave",
    "sg:city":"Bronx",
    "sg:classifiers":[
        {
            "category":"Shopping",
            "type":"Retail Goods"
        }
    ],
    "sg:phone":"+1 718 583 3350",
    "sg:postcode":"10457",
    "sg:province":"NY",
    "sg:tags":[
        "pet",
        "shop",
        "store"
    ],
    "wof:name":"J & J Pet Shop",
    "wof:placetype":"venue"
},
  "geometry": {"coordinates":[-73.890503,40.8452],"type":"Point"}
}