{
  "type": "Feature",
  "properties": {
    "iso:country":"US",
    "sg:address":"719 State Hwy 41",
    "sg:city":"Smithville Flats",
    "sg:classifiers":[
        {
            "category":"Building & Trades",
            "subcategory":"Construction",
            "type":"Services"
        }
    ],
    "sg:phone":"+1 607 727 9897",
    "sg:postcode":"13841",
    "sg:province":"NY",
    "sg:tags":[
        "home",
        "improvement"
    ],
    "wof:name":"T J Hill Fine Carpentry",
    "wof:placetype":"venue"
},
  "geometry": {"coordinates":[-75.878075,42.447205],"type":"Point"}
}