{
  "type": "Feature",
  "properties": {
    "iso:country":"US",
    "sg:address":"124 Tompkins Ave",
    "sg:city":"Beacon",
    "sg:classifiers":[
        {
            "category":"Real Estate",
            "subcategory":"Real Estate Operator",
            "type":"Services"
        }
    ],
    "sg:phone":"+1 845 831 6700",
    "sg:postcode":"12508",
    "sg:province":"NY",
    "sg:tags":[
        "apartment"
    ],
    "wof:name":"Tompkins Terrace Assoc Renting",
    "wof:placetype":"venue"
},
  "geometry": {"coordinates":[-73.981324,41.510486],"type":"Point"}
}