{
  "type": "Feature",
  "properties": {
    "iso:country":"US",
    "sg:address":"1967 Amsterdam Ave",
    "sg:city":"New York",
    "sg:classifiers":[
        {
            "category":"Food & Beverages",
            "subcategory":"Groceries & Convenience Stores",
            "type":"Retail Goods"
        }
    ],
    "sg:phone":"+1   ",
    "sg:postcode":"10032",
    "sg:province":"NY",
    "wof:name":"Dany Grocery Store",
    "wof:placetype":"venue"
},
  "geometry": {"coordinates":[-73.941649,40.833202],"type":"Point"}
}