{
  "type": "Feature",
  "properties": {
    "addr:full":"3003 Grand Concourse Bronx NY 10468",
    "addr:housenumber":"3003",
    "addr:postcode":"10468",
    "addr:street":"Grand Concourse",
    "iso:country":"US",
    "sg:address":"3003 Grand Concourse",
    "sg:city":"Bronx",
    "sg:classifiers":[
        {
            "category":"Health Services",
            "subcategory":"Doctor",
            "type":"Services"
        }
    ],
    "sg:phone":"+1   ",
    "sg:postcode":"10468",
    "sg:province":"NY",
    "wof:name":"Bedford Park Family Dentistry",
    "wof:placetype":"venue"
},
  "geometry": {"coordinates":[-73.88718,40.87334],"type":"Point"}
}