{
  "type": "Feature",
  "properties": {
    "addr:full":"336 E 54 St New York NY 10022",
    "addr:housenumber":"336;54",
    "addr:postcode":"10022",
    "addr:street":"E;St",
    "iso:country":"US",
    "sg:address":"336 E 54 St",
    "sg:city":"New York",
    "sg:classifiers":[
        {
            "category":"Retail",
            "subcategory":"Repair Shop",
            "type":"Services"
        }
    ],
    "sg:phone":"+1   ",
    "sg:postcode":"10022",
    "sg:province":"NY",
    "wof:name":"Al Con Locksmith",
    "wof:placetype":"venue"
},
  "geometry": {"coordinates":[-73.965023,40.756682],"type":"Point"}
}