{
  "type": "Feature",
  "properties": {
    "addr:full":"2564 Park Ave Bronx NY 10451",
    "addr:housenumber":"2564",
    "addr:postcode":"10451",
    "addr:street":"Park Ave",
    "iso:country":"US",
    "sg:address":"2564 Park Ave",
    "sg:city":"Bronx",
    "sg:classifiers":[
        {
            "category":"Freight",
            "type":"Transportation"
        }
    ],
    "sg:phone":"+1 718 292 3099",
    "sg:postcode":"10451",
    "sg:province":"NY",
    "sg:tags":[
        "mover"
    ],
    "wof:name":"New Yorker Storage Co Inc",
    "wof:placetype":"venue"
},
  "geometry": {"coordinates":[-73.928376,40.813431],"type":"Point"}
}