{
  "type": "Feature",
  "properties": {
    "addr:full":"109 E 153rd St Bronx NY 10451",
    "addr:housenumber":"109",
    "addr:postcode":"10451",
    "addr:street":"E 153Rd St",
    "iso:country":"US",
    "sg:address":"109 E 153rd St",
    "sg:city":"Bronx",
    "sg:classifiers":[
        {
            "category":"Food & Beverages",
            "subcategory":"Groceries & Convenience Stores",
            "type":"Retail Goods"
        }
    ],
    "sg:phone":"+1   ",
    "sg:postcode":"10451",
    "sg:province":"NY",
    "wof:name":"Paloma Grocery",
    "wof:placetype":"venue"
},
  "geometry": {"coordinates":[-73.927564,40.823462],"type":"Point"}
}