{
  "type": "Feature",
  "properties": {
    "iso:country":"US",
    "sg:address":"37 Main St",
    "sg:city":"Hempstead",
    "sg:classifiers":[
        {
            "category":"Personal",
            "subcategory":"Beauty Salon",
            "type":"Services"
        }
    ],
    "sg:phone":"+1   ",
    "sg:postcode":"11550",
    "sg:province":"NY",
    "sg:tags":[
        "shop"
    ],
    "wof:name":"Tiffanis Hairstylist",
    "wof:placetype":"venue"
},
  "geometry": {"coordinates":[-73.62412399999999,40.706954],"type":"Point"}
}