{
  "type": "Feature",
  "properties": {
    "addr:full":"60 E 8th St New York NY 10003",
    "addr:housenumber":"60",
    "addr:postcode":"10003",
    "addr:street":"E 8Th St",
    "iso:country":"US",
    "sg:address":"60 E 8th St",
    "sg:city":"New York",
    "sg:classifiers":[
        {
            "category":"Professional",
            "subcategory":"Lawyer & Legal Services",
            "type":"Services"
        }
    ],
    "sg:phone":"+1 212 832 0745",
    "sg:postcode":"10003",
    "sg:province":"NY",
    "wof:name":"Swiedler Alan M Atty",
    "wof:placetype":"venue"
},
  "geometry": {"coordinates":[-73.993139,40.730385],"type":"Point"}
}