{
  "type": "Feature",
  "properties": {
    "addr:full":"1270 5th Ave New York NY 10029",
    "addr:housenumber":"1270",
    "addr:postcode":"10029",
    "addr:street":"5Th Ave",
    "iso:country":"US",
    "sg:address":"1270 5th Ave",
    "sg:city":"New York",
    "sg:classifiers":[
        {
            "category":"Professional",
            "subcategory":"Management & Consulting",
            "type":"Services"
        }
    ],
    "sg:phone":"+1   ",
    "sg:postcode":"10029",
    "sg:province":"NY",
    "sg:tags":[
        "business"
    ],
    "wof:name":"Educatonal Research",
    "wof:placetype":"venue"
},
  "geometry": {"coordinates":[-73.94969399999999,40.796217],"type":"Point"}
}