{
  "type": "Feature",
  "properties": {
    "addr:full":"15 Hull St Brooklyn NY 11233",
    "addr:housenumber":"15",
    "addr:postcode":"11233",
    "addr:street":"Hull St",
    "iso:country":"US",
    "sg:address":"15 Hull St",
    "sg:city":"Brooklyn",
    "sg:classifiers":[
        {
            "category":"Organizations",
            "subcategory":"Religious Organization",
            "type":"Services"
        }
    ],
    "sg:phone":"+1 347 221 0570",
    "sg:postcode":"11233",
    "sg:province":"NY",
    "wof:name":"Full Gospel Tabernacle Of Faith Incorporated",
    "wof:placetype":"venue"
},
  "geometry": {"coordinates":[-73.917294,40.678957],"type":"Point"}
}