{
  "type": "Feature",
  "properties": {
    "addr:full":"86 Franklin Street New York NY 10013",
    "addr:housenumber":"86",
    "addr:postcode":"10013",
    "addr:street":"Franklin Street",
    "iso:country":"US",
    "sg:address":"86 Franklin Street",
    "sg:city":"New York",
    "sg:classifiers":[
        {
            "category":"Arts & Performance",
            "subcategory":"Arts Center",
            "type":"Entertainment"
        },
        {
            "category":"Cinema",
            "subcategory":"Movie Theater",
            "type":"Entertainment"
        }
    ],
    "sg:phone":"+1 212 941 8632",
    "sg:postcode":"10013",
    "sg:province":"NY",
    "sg:tags":[
        "performing"
    ],
    "sg:website":"www.sohorep.org",
    "wof:name":"Soho Repertory Theatre",
    "wof:placetype":"venue"
},
  "geometry": {"coordinates":[-74.004812,40.718043],"type":"Point"}
}