{
  "type": "Feature",
  "properties": {
    "iso:country":"US",
    "sg:address":"1237 Delaware Ave",
    "sg:city":"Buffalo",
    "sg:classifiers":[
        {
            "category":"Health Services",
            "subcategory":"Doctor",
            "type":"Services"
        }
    ],
    "sg:phone":"+1 716 884 5102",
    "sg:postcode":"14209",
    "sg:province":"NY",
    "sg:website":"www.clinicoffps.com",
    "wof:name":"Gromo Foundation for Medical Education and Research Inc",
    "wof:placetype":"venue"
},
  "geometry": {"coordinates":[-78.86841,42.917523],"type":"Point"}
}