{
  "type": "Feature",
  "properties": {
    "addr:full":"1146 Titus Ave Rochester NY 14617",
    "addr:housenumber":"1146",
    "addr:postcode":"14617",
    "addr:street":"Titus Ave",
    "iso:country":"US",
    "sg:address":"1146 Titus Ave",
    "sg:city":"Rochester",
    "sg:classifiers":[
        {
            "category":"Health Services",
            "subcategory":"Clinic",
            "type":"Services"
        }
    ],
    "sg:phone":"+1 585 266 7963",
    "sg:postcode":"14617",
    "sg:province":"NY",
    "sg:tags":[
        "spa",
        "medical"
    ],
    "wof:name":"Titus Medical Spa",
    "wof:placetype":"venue"
},
  "geometry": {"coordinates":[-77.58537,43.211035],"type":"Point"}
}