{
  "type": "Feature",
  "properties": {
    "addr:full":"3639 22nd St Astoria NY 11106",
    "addr:housenumber":"3639",
    "addr:postcode":"11106",
    "addr:street":"22Nd St",
    "iso:country":"US",
    "sg:address":"3639 22nd St",
    "sg:city":"Astoria",
    "sg:classifiers":[
        {
            "category":"Retail",
            "subcategory":"Auto Repair",
            "type":"Services"
        }
    ],
    "sg:phone":"+1 718 482 6818",
    "sg:postcode":"11106",
    "sg:province":"NY",
    "wof:name":"B M I Auto & Body Center",
    "wof:placetype":"venue"
},
  "geometry": {"coordinates":[-73.936798,40.758301],"type":"Point"}
}