{
  "type": "Feature",
  "properties": {
    "iso:country":"US",
    "sg:address":"15 Hollywood Dr",
    "sg:city":"Whitesboro",
    "sg:classifiers":[
        {
            "category":"Shopping",
            "subcategory":"Photographic Equipment",
            "type":"Retail Goods"
        }
    ],
    "sg:phone":"+1   ",
    "sg:postcode":"13492",
    "sg:province":"NY",
    "sg:tags":[
        "supply"
    ],
    "wof:name":"Foto Fair Inc",
    "wof:placetype":"venue"
},
  "geometry": {"coordinates":[-75.306214,43.109966],"type":"Point"}
}