{
  "type": "Feature",
  "properties": {
    "addr:full":"45 Colgate Ln Woodbury NY 11797",
    "addr:housenumber":"45",
    "addr:postcode":"11797",
    "addr:street":"Colgate Ln",
    "iso:country":"US",
    "sg:address":"45 Colgate Ln",
    "sg:city":"Woodbury",
    "sg:classifiers":[
        {
            "category":"Wholesale",
            "subcategory":"Machinery & Supplies",
            "type":"Manufacturing & Wholesale Goods"
        }
    ],
    "sg:phone":"+1 516 496 0967",
    "sg:postcode":"11797",
    "sg:province":"NY",
    "sg:tags":[
        "equipment",
        "industrial"
    ],
    "wof:name":"Dsa",
    "wof:placetype":"venue"
},
  "geometry": {"coordinates":[-73.479877,40.809443],"type":"Point"}
}