{
  "type": "Feature",
  "properties": {
    "addr:full":"1135 Fulton St Hewlett NY 11557",
    "addr:housenumber":"1135",
    "addr:postcode":"11557",
    "addr:street":"Fulton St",
    "iso:country":"US",
    "sg:address":"1135 Fulton St",
    "sg:city":"Hewlett",
    "sg:classifiers":[
        {
            "category":"Building & Trades",
            "subcategory":"Landscaping Services",
            "type":"Services"
        }
    ],
    "sg:phone":"+1 516 374 5759",
    "sg:postcode":"11557",
    "sg:province":"NY",
    "sg:tags":[
        "landscape"
    ],
    "wof:name":"Tavella Domenico",
    "wof:placetype":"venue"
},
  "geometry": {"coordinates":[-73.706363,40.636421],"type":"Point"}
}