{
  "type": "Feature",
  "properties": {
    "addr:full":"341 7th Ave New York NY 10001",
    "addr:housenumber":"341",
    "addr:postcode":"10001",
    "addr:street":"7Th Ave",
    "iso:country":"US",
    "sg:address":"341 7th Ave",
    "sg:city":"New York",
    "sg:classifiers":[
        {
            "category":"Deli",
            "type":"Food & Drink"
        }
    ],
    "sg:menulink":"http://www.allmenus.com/ny/new-york/7621-healthy-choice/menu/",
    "sg:phone":"+1 212 279 9221",
    "sg:postcode":"10001",
    "sg:province":"NY",
    "sg:tags":[
        "american"
    ],
    "wof:name":"Healthy Choice",
    "wof:placetype":"venue"
},
  "geometry": {"coordinates":[-73.992509,40.747824],"type":"Point"}
}