{
  "type": "Feature",
  "properties": {
    "iso:country":"US",
    "sg:address":"1270 Broadway",
    "sg:city":"New York",
    "sg:classifiers":[
        {
            "category":"Wholesale",
            "subcategory":"Apparel",
            "type":"Manufacturing & Wholesale Goods"
        },
        {
            "category":"Shopping",
            "subcategory":"Clothing, Apparel, & Fashions",
            "type":"Retail Goods"
        }
    ],
    "sg:phone":"+1 212 695 5946",
    "sg:postcode":"10001",
    "sg:province":"NY",
    "sg:tags":[
        "imported",
        "sportswear"
    ],
    "wof:name":"Kivini Sportswear LTD",
    "wof:placetype":"venue"
},
  "geometry": {"coordinates":[-73.988016,40.748645],"type":"Point"}
}