{
  "type": "Feature",
  "properties": {
    "iso:country":"US",
    "sg:address":"128 Ashford Ave",
    "sg:city":"Dobbs Ferry",
    "sg:classifiers":[
        {
            "category":"Health Services",
            "subcategory":"Doctor",
            "type":"Services"
        }
    ],
    "sg:phone":"+1 914 693 0055",
    "sg:postcode":"10522",
    "sg:province":"NY",
    "wof:name":"Westchester Weight Loss Center",
    "wof:placetype":"venue"
},
  "geometry": {"coordinates":[-73.862809,41.475613],"type":"Point"}
}