{
  "type": "Feature",
  "properties": {
    "addr:full":"7078 E Genesee St Fayetteville NY 13066",
    "addr:housenumber":"7078",
    "addr:postcode":"13066",
    "addr:street":"E Genesee St",
    "iso:country":"US",
    "sg:address":"7078 E Genesee St",
    "sg:city":"Fayetteville",
    "sg:classifiers":[
        {
            "category":"Health Services",
            "subcategory":"Clinic",
            "type":"Services"
        },
        {
            "category":"Health Services",
            "subcategory":"Doctor",
            "type":"Services"
        }
    ],
    "sg:phone":"+1 315 637 2722",
    "sg:postcode":"13066",
    "sg:province":"NY",
    "sg:tags":[
        "physician",
        "surgeon",
        "specialty",
        "outpatient"
    ],
    "wof:name":"Living Proof Longevity Center",
    "wof:placetype":"venue"
},
  "geometry": {"coordinates":[-76.034583,43.028398],"type":"Point"}
}