{
  "type": "Feature",
  "properties": {
    "addr:full":"283 Whitehall Rd S Garden City NY 11530",
    "addr:housenumber":"283",
    "addr:postcode":"11530",
    "addr:street":"Whitehall Rd S",
    "iso:country":"US",
    "sg:address":"283 Whitehall Rd S",
    "sg:city":"Garden City",
    "sg:classifiers":[
        {
            "category":"Shopping",
            "subcategory":"Optician",
            "type":"Retail Goods"
        }
    ],
    "sg:phone":"+1 516 486 2020",
    "sg:postcode":"11530",
    "sg:province":"NY",
    "sg:tags":[
        "eyewear"
    ],
    "wof:name":"Plaza Marine",
    "wof:placetype":"venue"
},
  "geometry": {"coordinates":[-73.656628,40.714228],"type":"Point"}
}