{
  "type": "Feature",
  "properties": {
    "iso:country":"US",
    "sg:address":"593 Coney Island Ave",
    "sg:city":"Brooklyn",
    "sg:classifiers":[
        {
            "category":"Retail",
            "subcategory":"Animal Services",
            "type":"Services"
        }
    ],
    "sg:phone":"+1 718 684 5568",
    "sg:postcode":"11218",
    "sg:province":"NY",
    "sg:tags":[
        "pet"
    ],
    "sg:website":"www.nydogsworld.com",
    "wof:name":"It's a Dog's World",
    "wof:placetype":"venue"
},
  "geometry": {"coordinates":[-73.96973699999999,40.64279],"type":"Point"}
}