{
  "type": "Feature",
  "properties": {
    "iso:country":"US",
    "sg:address":"300 W Dominick St",
    "sg:city":"Rome",
    "sg:classifiers":[
        {
            "category":"Shopping",
            "subcategory":"Clothing, Apparel, & Fashions",
            "type":"Retail Goods"
        }
    ],
    "sg:phone":"+1   ",
    "sg:postcode":"13440",
    "sg:province":"NY",
    "sg:tags":[
        "sporting",
        "footwear",
        "family"
    ],
    "wof:name":"Herb Philipsons Army",
    "wof:placetype":"venue"
},
  "geometry": {"coordinates":[-75.463916,43.213822],"type":"Point"}
}