{
  "type": "Feature",
  "properties": {
    "iso:country":"US",
    "sg:address":"60-60 Myrtle Avenue",
    "sg:city":"Queens",
    "sg:classifiers":[
        {
            "category":"Government",
            "subcategory":"Post Office",
            "type":"Public Place"
        }
    ],
    "sg:phone":"+1 718 321 6800",
    "sg:postcode":"11385",
    "sg:province":"NY",
    "sg:website":"www.usps.com",
    "wof:name":"United States Post Office",
    "wof:placetype":"venue"
},
  "geometry": {"coordinates":[-73.895707,40.700459],"type":"Point"}
}