{
  "type": "Feature",
  "properties": {
    "iso:country":"US",
    "sg:address":"2 N Pearl St",
    "sg:city":"Pearl River",
    "sg:classifiers":[
        {
            "category":"Professional",
            "subcategory":"Computer Services",
            "type":"Services"
        }
    ],
    "sg:phone":"+1 845 227 9126",
    "sg:postcode":"10965",
    "sg:province":"NY",
    "sg:tags":[
        "datum"
    ],
    "wof:name":"True North Data Service",
    "wof:placetype":"venue"
},
  "geometry": {"coordinates":[-74.02418900000001,41.060185],"type":"Point"}
}