{
  "type": "Feature",
  "properties": {
    "iso:country":"US",
    "sg:address":"91 Angels Path",
    "sg:city":"Webster",
    "sg:classifiers":[
        {
            "category":"Health Services",
            "subcategory":"Doctor",
            "type":"Services"
        }
    ],
    "sg:phone":"+1 585 787 1175",
    "sg:postcode":"14580",
    "sg:province":"NY",
    "sg:tags":[
        "dentist"
    ],
    "wof:name":"Steven G Damelio DDS",
    "wof:placetype":"venue"
},
  "geometry": {"coordinates":[-77.489481,43.185318],"type":"Point"}
}