{
  "type": "Feature",
  "properties": {
    "addr:full":"445 Fort Salonga Rd Northport NY 11768",
    "addr:housenumber":"445",
    "addr:postcode":"11768",
    "addr:street":"Fort Salonga Rd",
    "iso:country":"US",
    "sg:address":"445 Fort Salonga Rd",
    "sg:city":"Northport",
    "sg:classifiers":[
        {
            "category":"Retail",
            "subcategory":"Auto Repair",
            "type":"Services"
        }
    ],
    "sg:phone":"+1 631 262 7800",
    "sg:postcode":"11768",
    "sg:province":"NY",
    "sg:tags":[
        "repairing",
        "automobile",
        "general"
    ],
    "wof:name":"Auto Service Center Northport",
    "wof:placetype":"venue"
},
  "geometry": {"coordinates":[-73.33735799999999,40.893193],"type":"Point"}
}