{
  "type": "Feature",
  "properties": {
    "iso:country":"US",
    "sg:address":"2180 Jericho Tpke",
    "sg:city":"Commack",
    "sg:classifiers":[
        {
            "category":"Restaurant",
            "type":"Food & Drink"
        }
    ],
    "sg:menulink":"http://www.allmenus.com/ny/smithtown/181891-wendys/menu/",
    "sg:phone":"+1 631 499 9887",
    "sg:postcode":"11725",
    "sg:province":"NY",
    "sg:tags":[
        "burger",
        "american",
        "soup"
    ],
    "wof:name":"Wendy's",
    "wof:placetype":"venue"
},
  "geometry": {"coordinates":[-73.28648099999999,40.842776],"type":"Point"}
}