{
  "type": "Feature",
  "properties": {
    "addr:full":"69 Delaware Ave Buffalo NY 14202",
    "addr:housenumber":"69",
    "addr:postcode":"14202",
    "addr:street":"Delaware Ave",
    "iso:country":"US",
    "sg:address":"69 Delaware Ave",
    "sg:city":"Buffalo",
    "sg:classifiers":[
        {
            "category":"Professional",
            "subcategory":"Lawyer & Legal Services",
            "type":"Services"
        }
    ],
    "sg:phone":"+1 716 856 1010",
    "sg:postcode":"14202",
    "sg:province":"NY",
    "sg:tags":[
        "attorney"
    ],
    "sg:website":"www.migliacciolaw.com",
    "wof:name":"Godinho & Galeziowski",
    "wof:placetype":"venue"
},
  "geometry": {"coordinates":[-78.87852599999999,42.88536],"type":"Point"}
}