{
  "type": "Feature",
  "properties": {
    "iso:country":"US",
    "sg:address":"87 E Washington St",
    "sg:city":"Hornell",
    "sg:classifiers":[
        {
            "category":"Real Estate",
            "subcategory":"Real Estate Operator",
            "type":"Services"
        }
    ],
    "sg:phone":"+1 607 324 7912",
    "sg:postcode":"14843",
    "sg:province":"NY",
    "sg:tags":[
        "building",
        "apartment",
        "executive"
    ],
    "wof:name":"Hornell Housing Authority",
    "wof:placetype":"venue"
},
  "geometry": {"coordinates":[-77.65691099999999,42.331734],"type":"Point"}
}