{
  "type": "Feature",
  "properties": {
    "addr:full":"72 US Hwy 9w Haverstraw NY 10927",
    "addr:housenumber":"72",
    "addr:postcode":"10927",
    "addr:street":"Us Hwy 9W",
    "iso:country":"US",
    "sg:address":"72 US Hwy 9w",
    "sg:city":"Haverstraw",
    "sg:classifiers":[
        {
            "category":"Professional",
            "type":"Services"
        }
    ],
    "sg:phone":"+1 845 786 3140",
    "sg:postcode":"10927",
    "sg:province":"NY",
    "sg:tags":[
        "establishment"
    ],
    "wof:name":"Jimmy Martin's Auto",
    "wof:placetype":"venue"
},
  "geometry": {"coordinates":[-73.965298,41.191859],"type":"Point"}
}