{
  "type": "Feature",
  "properties": {
    "addr:full":"24 Cleveland Ave Gansevoort NY 12866",
    "addr:housenumber":"24",
    "addr:postcode":"12866",
    "addr:street":"Cleveland Ave",
    "iso:country":"US",
    "sg:address":"24 Cleveland Ave",
    "sg:city":"Gansevoort",
    "sg:classifiers":[
        {
            "category":"Shopping",
            "subcategory":"Clothing, Apparel, & Fashions",
            "type":"Retail Goods"
        }
    ],
    "sg:phone":"+1   ",
    "sg:postcode":"12866",
    "sg:province":"NY",
    "wof:name":"Sugar Britches Beach Wear",
    "wof:placetype":"venue"
},
  "geometry": {"coordinates":[-73.78142099999999,43.062426],"type":"Point"}
}