{
  "type": "Feature",
  "properties": {
    "iso:country":"US",
    "sg:address":"272 Hillside Ave",
    "sg:city":"Williston Park",
    "sg:classifiers":[
        {
            "category":"Personal",
            "subcategory":"Beauty Salon",
            "type":"Services"
        }
    ],
    "sg:phone":"+1 516 739 8600",
    "sg:postcode":"11596",
    "sg:province":"NY",
    "sg:tags":[
        "nail",
        "shop"
    ],
    "wof:name":"Le Salon",
    "wof:placetype":"venue"
},
  "geometry": {"coordinates":[-73.6493,40.755001],"type":"Point"}
}