{
  "type": "Feature",
  "properties": {
    "addr:full":"351 N Broadway Yonkers NY 10701",
    "addr:housenumber":"351",
    "addr:postcode":"10701",
    "addr:street":"N Broadway",
    "iso:country":"US",
    "sg:address":"351 N Broadway",
    "sg:city":"Yonkers",
    "sg:classifiers":[
        {
            "category":"Real Estate",
            "subcategory":"Real Estate Agent",
            "type":"Services"
        }
    ],
    "sg:phone":"+1 914 965 4425",
    "sg:postcode":"10701",
    "sg:province":"NY",
    "wof:name":"3 C Realty Inc",
    "wof:placetype":"venue"
},
  "geometry": {"coordinates":[-73.89344,40.946821],"type":"Point"}
}