{
  "type": "Feature",
  "properties": {
    "iso:country":"US",
    "sg:address":"802 Hempstead Blvd",
    "sg:city":"Uniondale",
    "sg:classifiers":[
        {
            "category":"Building & Trades",
            "subcategory":"Electrical",
            "type":"Services"
        }
    ],
    "sg:phone":"+1 516 485 4706",
    "sg:postcode":"11553",
    "sg:province":"NY",
    "sg:tags":[
        "television",
        "installation",
        "telecommunication",
        "cable",
        "telephone",
        "contractor",
        "equipment"
    ],
    "wof:name":"Cathcomm Network Services Inc",
    "wof:placetype":"venue"
},
  "geometry": {"coordinates":[-73.587046,40.703123],"type":"Point"}
}