{
  "type": "Feature",
  "properties": {
    "addr:full":"325 Calyer St Brooklyn NY 11222",
    "addr:housenumber":"325",
    "addr:postcode":"11222",
    "addr:street":"Calyer St",
    "iso:country":"US",
    "sg:address":"325 Calyer St",
    "sg:city":"Brooklyn",
    "sg:classifiers":[
        {
            "category":"Building & Trades",
            "subcategory":"Construction",
            "type":"Services"
        }
    ],
    "sg:phone":"+1 718 389 5505",
    "sg:postcode":"11222",
    "sg:province":"NY",
    "sg:tags":[
        "woodwork",
        "architectural"
    ],
    "wof:name":"Calyer Architectural Woodwork",
    "wof:placetype":"venue"
},
  "geometry": {"coordinates":[-73.94664899999999,40.730379],"type":"Point"}
}