{
  "type": "Feature",
  "properties": {
    "addr:full":"199 Canal Street Rm 204 New York NY 10013",
    "addr:housenumber":"199;204",
    "addr:postcode":"10013",
    "addr:street":"Canal Street Rm",
    "iso:country":"US",
    "sg:address":"199 Canal Street Rm 204",
    "sg:city":"New York",
    "sg:classifiers":[
        {
            "category":"Professional",
            "subcategory":"Accounting & Tax Preparation",
            "type":"Services"
        }
    ],
    "sg:phone":"+1 212 219 2152",
    "sg:postcode":"10013",
    "sg:province":"NY",
    "sg:tags":[
        "accountant"
    ],
    "wof:name":"Victor S Chien",
    "wof:placetype":"venue"
},
  "geometry": {"coordinates":[-73.998712,40.717141],"type":"Point"}
}