{
  "type": "Feature",
  "properties": {
    "addr:full":"2 Morgan Ave Port Jefferson Station NY 11776",
    "addr:housenumber":"2",
    "addr:postcode":"11776",
    "addr:street":"Morgan Ave",
    "iso:country":"US",
    "sg:address":"2 Morgan Ave",
    "sg:city":"Port Jefferson Station",
    "sg:classifiers":[
        {
            "category":"Health Services",
            "subcategory":"Dentist",
            "type":"Services"
        }
    ],
    "sg:phone":"+1 631 928 6684",
    "sg:postcode":"11776",
    "sg:province":"NY",
    "wof:name":"DAMASKOS JOHN DDS",
    "wof:placetype":"venue"
},
  "geometry": {"coordinates":[-73.02212400000001,40.923247],"type":"Point"}
}