{
  "type": "Feature",
  "properties": {
    "addr:full":"27 Whittier Dr Mastic Beach NY 11951",
    "addr:housenumber":"27",
    "addr:postcode":"11951",
    "addr:street":"Whittier Dr",
    "iso:country":"US",
    "sg:address":"27 Whittier Dr",
    "sg:city":"Mastic Beach",
    "sg:classifiers":[
        {
            "category":"Real Estate",
            "subcategory":"Real Estate Agent",
            "type":"Services"
        }
    ],
    "sg:phone":"+1 631 742 0297",
    "sg:postcode":"11951",
    "sg:province":"NY",
    "wof:name":"Deborah Barbuto",
    "wof:placetype":"venue"
},
  "geometry": {"coordinates":[-72.835881,40.762786],"type":"Point"}
}