{
  "type": "Feature",
  "properties": {
    "iso:country":"US",
    "sg:address":"50 Glen St",
    "sg:city":"Glen Cove",
    "sg:classifiers":[
        {
            "category":"Wholesale",
            "subcategory":"Medical Equipment & Supplies",
            "type":"Manufacturing & Wholesale Goods"
        }
    ],
    "sg:phone":"+1 516 671 2674",
    "sg:postcode":"11542",
    "sg:province":"NY",
    "wof:name":"Continental Culture Trade",
    "wof:placetype":"venue"
},
  "geometry": {"coordinates":[-73.630686,40.863892],"type":"Point"}
}