{
  "type": "Feature",
  "properties": {
    "iso:country":"US",
    "sg:address":"2164 Broadway",
    "sg:city":"New York",
    "sg:classifiers":[
        {
            "category":"Restaurant",
            "type":"Food & Drink"
        }
    ],
    "sg:phone":"+1   ",
    "sg:postcode":"10024",
    "sg:province":"NY",
    "sg:tags":[
        "eating"
    ],
    "wof:name":"Akaihana",
    "wof:placetype":"venue"
},
  "geometry": {"coordinates":[-73.98078099999999,40.782293],"type":"Point"}
}