{
  "type": "Feature",
  "properties": {
    "addr:full":"73 Benedict Blvd Croton On Hudson NY 10520",
    "addr:housenumber":"73",
    "addr:postcode":"10520",
    "addr:street":"Benedict Blvd",
    "iso:country":"US",
    "sg:address":"73 Benedict Blvd",
    "sg:city":"Croton On Hudson",
    "sg:classifiers":[
        {
            "category":"Personal",
            "subcategory":"Beauty Salon",
            "type":"Services"
        }
    ],
    "sg:phone":"+1 914 271 1111",
    "sg:postcode":"10520",
    "sg:province":"NY",
    "sg:tags":[
        "manicuring"
    ],
    "wof:name":"Perfect 10 Plus Nail Salon",
    "wof:placetype":"venue"
},
  "geometry": {"coordinates":[-73.880889,41.195772],"type":"Point"}
}