{
  "type": "Feature",
  "properties": {
    "iso:country":"US",
    "sg:address":"9880 Tonawanda Creek Rd",
    "sg:city":"Clarence Center",
    "sg:classifiers":[
        {
            "category":"Manufacturing",
            "subcategory":"Tools & Machinery",
            "type":"Manufacturing & Wholesale Goods"
        }
    ],
    "sg:phone":"+1   ",
    "sg:postcode":"14032",
    "sg:province":"NY",
    "sg:tags":[
        "devices",
        "mfg"
    ],
    "wof:name":"Intelligent Microsystems Inc",
    "wof:placetype":"venue"
},
  "geometry": {"coordinates":[-78.620857,43.079729],"type":"Point"}
}