{
  "type": "Feature",
  "properties": {
    "addr:full":"5824 11th Ave Brooklyn NY 11219",
    "addr:housenumber":"5824",
    "addr:postcode":"11219",
    "addr:street":"11Th Ave",
    "iso:country":"US",
    "sg:address":"5824 11th Ave",
    "sg:city":"Brooklyn",
    "sg:classifiers":[
        {
            "category":"Shopping",
            "subcategory":"Antiques",
            "type":"Retail Goods"
        }
    ],
    "sg:phone":"+1 718 436 0807",
    "sg:postcode":"11219",
    "sg:province":"NY",
    "wof:name":"Rivka's Antiques",
    "wof:placetype":"venue"
},
  "geometry": {"coordinates":[-74.01938800000001,40.632602],"type":"Point"}
}