{
  "type": "Feature",
  "properties": {
    "addr:full":"3870 White Plains Rd Bronx NY 10467",
    "addr:housenumber":"3870",
    "addr:postcode":"10467",
    "addr:street":"White Plains Rd",
    "iso:country":"US",
    "sg:address":"3870 White Plains Rd",
    "sg:city":"Bronx",
    "sg:classifiers":[
        {
            "category":"Building & Trades",
            "subcategory":"Construction",
            "type":"Services"
        }
    ],
    "sg:phone":"+1 718 654 0107",
    "sg:postcode":"10467",
    "sg:province":"NY",
    "sg:tags":[
        "house"
    ],
    "wof:name":"Pataron Construction Corp",
    "wof:placetype":"venue"
},
  "geometry": {"coordinates":[-73.861693,40.88537],"type":"Point"}
}