{
  "type": "Feature",
  "properties": {
    "addr:full":"2022 Benedict Ave Bronx NY 10462",
    "addr:housenumber":"2022",
    "addr:postcode":"10462",
    "addr:street":"Benedict Ave",
    "iso:country":"US",
    "sg:address":"2022 Benedict Ave",
    "sg:city":"Bronx",
    "sg:classifiers":[
        {
            "category":"Real Estate",
            "subcategory":"Real Estate Agent",
            "type":"Services"
        }
    ],
    "sg:phone":"+1 718 828 2129",
    "sg:postcode":"10462",
    "sg:province":"NY",
    "wof:name":"Benedict Properties",
    "wof:placetype":"venue"
},
  "geometry": {"coordinates":[-73.855339,40.834496],"type":"Point"}
}