{
  "type": "Feature",
  "properties": {
    "addr:full":"3291 3rd Ave Bronx NY 10456",
    "addr:housenumber":"3291",
    "addr:postcode":"10456",
    "addr:street":"3Rd Ave",
    "iso:country":"US",
    "sg:address":"3291 3rd Ave",
    "sg:city":"Bronx",
    "sg:classifiers":[
        {
            "category":"Organizations",
            "subcategory":"Religious Organization",
            "type":"Services"
        }
    ],
    "sg:phone":"+1 718 742 0873",
    "sg:postcode":"10456",
    "sg:province":"NY",
    "wof:name":"Follower of Christ Penticostal Church",
    "wof:placetype":"venue"
},
  "geometry": {"coordinates":[-73.90830200000001,40.8255],"type":"Point"}
}