{
  "type": "Feature",
  "properties": {
    "iso:country":"US",
    "sg:address":"14 N Pearl St",
    "sg:city":"Pearl River",
    "sg:classifiers":[
        {
            "category":"Building & Trades",
            "subcategory":"Construction",
            "type":"Services"
        }
    ],
    "sg:phone":"+1 845 735 3894",
    "sg:postcode":"10965",
    "sg:province":"NY",
    "sg:tags":[
        "coping",
        "plastering",
        "tiling",
        "pool",
        "swimming"
    ],
    "wof:name":"Don's Pool Svc",
    "wof:placetype":"venue"
},
  "geometry": {"coordinates":[-74.02413900000001,41.059529],"type":"Point"}
}