{
  "type": "Feature",
  "properties": {
    "iso:country":"US",
    "sg:address":"145 Sunrise Hwy",
    "sg:city":"Lindenhurst",
    "sg:classifiers":[
        {
            "category":"Building & Trades",
            "subcategory":"Construction",
            "type":"Services"
        }
    ],
    "sg:phone":"+1 631 376 9297",
    "sg:postcode":"11757",
    "sg:province":"NY",
    "sg:tags":[
        "home",
        "improvement"
    ],
    "wof:name":"Dormers Express Inc",
    "wof:placetype":"venue"
},
  "geometry": {"coordinates":[-73.376463,40.702593],"type":"Point"}
}