{
  "type": "Feature",
  "properties": {
    "addr:full":"18 Garden St Rhinebeck NY 12572",
    "addr:housenumber":"18",
    "addr:postcode":"12572",
    "addr:street":"Garden St",
    "iso:country":"US",
    "sg:address":"18 Garden St",
    "sg:city":"Rhinebeck",
    "sg:classifiers":[
        {
            "category":"Restaurant",
            "type":"Food & Drink"
        }
    ],
    "sg:phone":"+1 845 876 7338",
    "sg:postcode":"12572",
    "sg:province":"NY",
    "wof:name":"Osaka Japanese Restaurant",
    "wof:placetype":"venue"
},
  "geometry": {"coordinates":[-73.913676,41.927912],"type":"Point"}
}