{
  "type": "Feature",
  "properties": {
    "addr:full":"39 Secor Rd Mahopac NY 10541",
    "addr:housenumber":"39",
    "addr:postcode":"ny 10541",
    "addr:street":"Secor Rd",
    "iso:country":"US",
    "sg:address":"39 Secor Rd",
    "sg:city":"Mahopac",
    "sg:phone":"+1 845 621 5100",
    "sg:postcode":"10541",
    "sg:province":"NY",
    "sg:tags":[
        "oil"
    ],
    "wof:name":"Action Fuel Oil",
    "wof:placetype":"venue"
},
  "geometry": {"coordinates":[-73.794265,41.37138],"type":"Point"}
}