{
  "type": "Feature",
  "properties": {
    "addr:full":"330 Madison Ave New York NY 10017",
    "addr:housenumber":"330",
    "addr:postcode":"10017",
    "addr:street":"Madison Ave",
    "iso:country":"US",
    "sg:address":"330 Madison Ave",
    "sg:city":"New York",
    "sg:classifiers":[
        {
            "category":"Banks & Credit Unions",
            "subcategory":"Bank",
            "type":"Services"
        }
    ],
    "sg:phone":"+1 212 653 8860",
    "sg:postcode":"10017",
    "sg:province":"NY",
    "sg:tags":[
        "loan",
        "real estate"
    ],
    "wof:name":"Arbor Commercial Mortgage",
    "wof:placetype":"venue"
},
  "geometry": {"coordinates":[-73.979287,40.752801],"type":"Point"}
}