{
  "type": "Feature",
  "properties": {
    "iso:country":"US",
    "sg:address":"10 George St",
    "sg:city":"Oswego",
    "sg:classifiers":[
        {
            "category":"Social Services",
            "type":"Services"
        }
    ],
    "sg:phone":"+1 315 342 0888",
    "sg:postcode":"13126",
    "sg:province":"NY",
    "sg:tags":[
        "information",
        "planning",
        "center",
        "family"
    ],
    "sg:website":"www.oco.org",
    "wof:name":"Oswego Health Ctr",
    "wof:placetype":"venue"
},
  "geometry": {"coordinates":[-76.485247,43.466867],"type":"Point"}
}