{
  "type": "Feature",
  "properties": {
    "iso:country":"US",
    "sg:address":"262 Suburban Ave Ste A",
    "sg:city":"Deer Park",
    "sg:classifiers":[
        {
            "category":"Home & Garden",
            "subcategory":"Carpets & Floor Coverings",
            "type":"Retail Goods"
        }
    ],
    "sg:phone":"+1 631 667 2610",
    "sg:postcode":"11729",
    "sg:province":"NY",
    "sg:tags":[
        "carpeting"
    ],
    "wof:name":"B M Carpet Inc",
    "wof:placetype":"venue"
},
  "geometry": {"coordinates":[-73.30392399999999,40.753348],"type":"Point"}
}