{
  "type": "Feature",
  "properties": {
    "iso:country":"US",
    "sg:address":"2476 State Hwy 9",
    "sg:city":"Ballston Spa",
    "sg:classifiers":[
        {
            "category":"Restaurant",
            "type":"Food & Drink"
        }
    ],
    "sg:phone":"+1   ",
    "sg:postcode":"12020",
    "sg:province":"NY",
    "sg:tags":[
        "diner"
    ],
    "wof:name":"Malta Diner",
    "wof:placetype":"venue"
},
  "geometry": {"coordinates":[-73.793027,42.970497],"type":"Point"}
}