{
  "type": "Feature",
  "properties": {
    "addr:full":"801 4th Ave Troy NY 12182",
    "addr:housenumber":"801",
    "addr:postcode":"12182",
    "addr:street":"4Th Ave",
    "iso:country":"US",
    "sg:address":"801 4th Ave",
    "sg:city":"Troy",
    "sg:classifiers":[
        {
            "category":"Building & Trades",
            "subcategory":"Construction",
            "type":"Services"
        }
    ],
    "sg:phone":"+1 518 590 0417",
    "sg:postcode":"12182",
    "sg:province":"NY",
    "sg:tags":[
        "house"
    ],
    "wof:name":"Home Improvement Guide Inc",
    "wof:placetype":"venue"
},
  "geometry": {"coordinates":[-73.670734,42.783215],"type":"Point"}
}