{
  "type": "Feature",
  "properties": {
    "addr:full":"1115 Montauk Hwy Copiague NY 11726",
    "addr:housenumber":"1115",
    "addr:postcode":"11726",
    "addr:street":"Montauk Hwy",
    "iso:country":"US",
    "sg:address":"1115 Montauk Hwy",
    "sg:city":"Copiague",
    "sg:classifiers":[
        {
            "category":"Retail",
            "subcategory":"Auto Repair",
            "type":"Services"
        }
    ],
    "sg:phone":"+1 631 841 0895",
    "sg:postcode":"11726",
    "sg:province":"NY",
    "sg:tags":[
        "repairing",
        "automobile"
    ],
    "wof:name":"East Coast Transmissions",
    "wof:placetype":"venue"
},
  "geometry": {"coordinates":[-73.38887099999999,40.669954],"type":"Point"}
}