{
  "type": "Feature",
  "properties": {
    "addr:full":"99 Roycroft Rd Syracuse NY 13214",
    "addr:housenumber":"99",
    "addr:postcode":"13214",
    "addr:street":"Roycroft Rd",
    "iso:country":"US",
    "sg:address":"99 Roycroft Rd",
    "sg:city":"Syracuse",
    "sg:classifiers":[
        {
            "category":"Communications",
            "type":"Services"
        }
    ],
    "sg:phone":"+1   ",
    "sg:postcode":"13214",
    "sg:province":"NY",
    "sg:tags":[
        "communication"
    ],
    "wof:name":"Del Communication Corporation",
    "wof:placetype":"venue"
},
  "geometry": {"coordinates":[-76.08207299999999,43.044064],"type":"Point"}
}