{
  "type": "Feature",
  "properties": {
    "iso:country":"US",
    "sg:address":"125 W Main St",
    "sg:city":"Riverhead",
    "sg:classifiers":[
        {
            "category":"Restaurant",
            "type":"Food & Drink"
        }
    ],
    "sg:phone":"+1 631 369 2102",
    "sg:postcode":"11901",
    "sg:province":"NY",
    "sg:tags":[
        "deli",
        "delicatessen"
    ],
    "wof:name":"Wisla Delicacy Deli Corp",
    "wof:placetype":"venue"
},
  "geometry": {"coordinates":[-72.6632,40.916801],"type":"Point"}
}