{
  "type": "Feature",
  "properties": {
    "iso:country":"US",
    "sg:address":"7 Hunter's Dr S",
    "sg:city":"Fairport",
    "sg:classifiers":[
        {
            "category":"Building & Trades",
            "subcategory":"Construction",
            "type":"Services"
        }
    ],
    "sg:phone":"+1 585 377 8990",
    "sg:postcode":"14450",
    "sg:province":"NY",
    "sg:tags":[
        "home",
        "improvement"
    ],
    "wof:name":"On The Level Home Improvement",
    "wof:placetype":"venue"
},
  "geometry": {"coordinates":[-77.430206,43.126293],"type":"Point"}
}