{
  "type": "Feature",
  "properties": {
    "addr:full":"1149 Sprout Hill Rd Dundee NY 14842",
    "addr:housenumber":"1149",
    "addr:postcode":"14842",
    "addr:street":"Sprout Hill Rd",
    "iso:country":"US",
    "sg:address":"1149 Sprout Hill Rd",
    "sg:city":"Dundee",
    "sg:classifiers":[
        {
            "category":"Building & Trades",
            "subcategory":"Construction",
            "type":"Services"
        }
    ],
    "sg:phone":"+1 607 243 7827",
    "sg:postcode":"14842",
    "sg:province":"NY",
    "sg:tags":[
        "general",
        "contractor"
    ],
    "wof:name":"Starlight Custom Homes Inc",
    "wof:placetype":"venue"
},
  "geometry": {"coordinates":[-76.98996,42.567536],"type":"Point"}
}