{
  "type": "Feature",
  "properties": {
    "addr:full":"105 Millers Grove Rd Frankfort NY 13340",
    "addr:housenumber":"105",
    "addr:postcode":"13340",
    "addr:street":"Millers Grove Rd",
    "iso:country":"US",
    "sg:address":"105 Millers Grove Rd",
    "sg:city":"Frankfort",
    "sg:classifiers":[
        {
            "category":"Real Estate",
            "subcategory":"Real Estate Operator",
            "type":"Services"
        }
    ],
    "sg:phone":"+1 315 894 8012",
    "sg:postcode":"13340",
    "sg:province":"NY",
    "sg:tags":[
        "mobile",
        "home",
        "community"
    ],
    "wof:name":"Country Meadows",
    "wof:placetype":"venue"
},
  "geometry": {"coordinates":[-75.081311,43.06062],"type":"Point"}
}