{
  "type": "Feature",
  "properties": {
    "addr:full":"455 W 23rd St New York NY 10011",
    "addr:housenumber":"455",
    "addr:postcode":"10011",
    "addr:street":"W 23Rd St",
    "iso:country":"US",
    "sg:address":"455 W 23rd St",
    "sg:city":"New York",
    "sg:classifiers":[
        {
            "category":"Professional",
            "subcategory":"Management & Consulting",
            "type":"Services"
        }
    ],
    "sg:phone":"+1 212 366 1893",
    "sg:postcode":"10011",
    "sg:province":"NY",
    "sg:tags":[
        "agent",
        "artist"
    ],
    "wof:name":"Artworks Usa The Inc",
    "wof:placetype":"venue"
},
  "geometry": {"coordinates":[-74.002945,40.747095],"type":"Point"}
}