{
  "type": "Feature",
  "properties": {
    "iso:country":"US",
    "sg:address":"136 E 28 St",
    "sg:city":"New York",
    "sg:classifiers":[
        {
            "category":"Professional",
            "subcategory":"Management & Consulting",
            "type":"Services"
        }
    ],
    "sg:phone":"+1   ",
    "sg:postcode":"10016",
    "sg:province":"NY",
    "sg:tags":[
        "public",
        "relations"
    ],
    "wof:name":"Orange Media Relations",
    "wof:placetype":"venue"
},
  "geometry": {"coordinates":[-73.98237899999999,40.742749],"type":"Point"}
}