{
  "type": "Feature",
  "properties": {
    "iso:country":"US",
    "sg:address":"244 Greece Ridge Center Dr",
    "sg:city":"Rochester",
    "sg:classifiers":[
        {
            "category":"Shopping",
            "subcategory":"Shoes",
            "type":"Retail Goods"
        }
    ],
    "sg:phone":"+1 585 225 0490",
    "sg:postcode":"14626",
    "sg:province":"NY",
    "sg:tags":[
        "store"
    ],
    "sg:website":"http://www.journeys.com/",
    "wof:name":"Journeys",
    "wof:placetype":"venue"
},
  "geometry": {"coordinates":[-77.694087,43.206625],"type":"Point"}
}