{
  "type": "Feature",
  "properties": {
    "addr:full":"971 1st Ave New York NY 10022",
    "addr:housenumber":"971",
    "addr:postcode":"10022",
    "addr:street":"1St Ave",
    "iso:country":"US",
    "sg:address":"971 1st Ave",
    "sg:city":"New York",
    "sg:classifiers":[
        {
            "category":"Retail",
            "subcategory":"Laundry & Dry Cleaning",
            "type":"Services"
        }
    ],
    "sg:phone":"+1 212 750 0656",
    "sg:postcode":"10022",
    "sg:province":"NY",
    "wof:name":"Symphony Cleaners",
    "wof:placetype":"venue"
},
  "geometry": {"coordinates":[-73.964839,40.756189],"type":"Point"}
}