{
  "type": "Feature",
  "properties": {
    "addr:full":"2861 Manitou Rd Rochester NY 14624",
    "addr:housenumber":"2861",
    "addr:postcode":"14624",
    "addr:street":"Manitou Rd",
    "iso:country":"US",
    "sg:address":"2861 Manitou Rd",
    "sg:city":"Rochester",
    "sg:classifiers":[
        {
            "category":"Building & Trades",
            "subcategory":"Construction",
            "type":"Services"
        }
    ],
    "sg:phone":"+1 585 738 5878",
    "sg:postcode":"14624",
    "sg:province":"NY",
    "sg:tags":[
        "company"
    ],
    "wof:name":"Jacobson Development",
    "wof:placetype":"venue"
},
  "geometry": {"coordinates":[-77.754283,43.140865],"type":"Point"}
}