{
  "type": "Feature",
  "properties": {
    "iso:country":"US",
    "sg:address":"1392 Glidden Cir",
    "sg:city":"Derby",
    "sg:classifiers":[
        {
            "category":"Building & Trades",
            "subcategory":"Landscaping Services",
            "type":"Services"
        }
    ],
    "sg:phone":"+1 716 947 4570",
    "sg:postcode":"14047",
    "sg:province":"NY",
    "sg:tags":[
        "landscape"
    ],
    "wof:name":"S&K Land Creations",
    "wof:placetype":"venue"
},
  "geometry": {"coordinates":[-78.981298,42.693396],"type":"Point"}
}