{
  "type": "Feature",
  "properties": {
    "addr:full":"471 Myrtle Avenue Brooklyn NY 11205",
    "addr:housenumber":"471",
    "addr:postcode":"11205",
    "addr:street":"Myrtle Avenue",
    "iso:country":"US",
    "sg:address":"471 Myrtle Avenue",
    "sg:city":"Brooklyn",
    "sg:classifiers":[
        {
            "category":"Retail",
            "subcategory":"Portrait Studio",
            "type":"Services"
        }
    ],
    "sg:phone":"+1 718 230 9399",
    "sg:postcode":"11205",
    "sg:province":"NY",
    "sg:tags":[
        "photography",
        "store"
    ],
    "wof:name":"Sunshine Photo",
    "wof:placetype":"venue"
},
  "geometry": {"coordinates":[-73.966478,40.693505],"type":"Point"}
}