{
  "type": "Feature",
  "properties": {
    "iso:country":"US",
    "sg:address":"4435 State Hwy 5",
    "sg:city":"Frankfort",
    "sg:classifiers":[
        {
            "category":"Autos & Motor Vehicles",
            "subcategory":"Automobile Sales",
            "type":"Retail Goods"
        }
    ],
    "sg:phone":"+1   ",
    "sg:postcode":"13340",
    "sg:province":"NY",
    "sg:tags":[
        "used"
    ],
    "wof:name":"S & S J Auto",
    "wof:placetype":"venue"
},
  "geometry": {"coordinates":[-75.032195,43.023137],"type":"Point"}
}