{
  "type": "Feature",
  "properties": {
    "iso:country":"US",
    "sg:address":"2 Revolutionary Rd",
    "sg:city":"Ossining",
    "sg:classifiers":[
        {
            "category":"Local Transit",
            "type":"Transportation"
        }
    ],
    "sg:phone":"+1   ",
    "sg:postcode":"10562",
    "sg:province":"NY",
    "sg:tags":[
        "passenger"
    ],
    "wof:name":"Scarsdale Limo Trip Svce",
    "wof:placetype":"venue"
},
  "geometry": {"coordinates":[-73.860411,41.148835],"type":"Point"}
}