{
  "type": "Feature",
  "properties": {
    "addr:full":"429 Forest Ave Buffalo NY 14213",
    "addr:housenumber":"429",
    "addr:postcode":"14213",
    "addr:street":"Forest Ave",
    "iso:country":"US",
    "sg:address":"429 Forest Ave",
    "sg:city":"Buffalo",
    "sg:classifiers":[
        {
            "category":"Building & Trades",
            "subcategory":"Construction",
            "type":"Services"
        }
    ],
    "sg:phone":"+1 716 882 3647",
    "sg:postcode":"14213",
    "sg:province":"NY",
    "sg:tags":[
        "nonresidential"
    ],
    "wof:name":"Serena & Sons",
    "wof:placetype":"venue"
},
  "geometry": {"coordinates":[-78.882546,42.927808],"type":"Point"}
}