{
  "type": "Feature",
  "properties": {
    "addr:full":"4918 New Utrecht Ave Brooklyn NY 11219",
    "addr:housenumber":"4918",
    "addr:postcode":"11219",
    "addr:street":"New Utrecht Ave",
    "iso:country":"US",
    "sg:address":"4918 New Utrecht Ave",
    "sg:city":"Brooklyn",
    "sg:classifiers":[
        {
            "category":"Communications",
            "subcategory":"Newspaper",
            "type":"Services"
        }
    ],
    "sg:phone":"+1 718 851 1828",
    "sg:postcode":"11219",
    "sg:province":"NY",
    "sg:tags":[
        "print",
        "medium"
    ],
    "wof:name":"4918 Newstand",
    "wof:placetype":"venue"
},
  "geometry": {"coordinates":[-73.994919,40.636471],"type":"Point"}
}