{
  "type": "Feature",
  "properties": {
    "addr:full":"21-23 Maiden Ln New York NY 10003",
    "addr:housenumber":"21-23",
    "addr:postcode":"10003",
    "addr:street":"Maiden Ln",
    "iso:country":"US",
    "sg:address":"21-23 Maiden Ln",
    "sg:city":"New York",
    "sg:classifiers":[
        {
            "category":"Restaurant",
            "type":"Food & Drink"
        }
    ],
    "sg:phone":"+1 212 608 7272",
    "sg:postcode":"10003",
    "sg:province":"NY",
    "sg:tags":[
        "pizza"
    ],
    "wof:name":"Papa John's Pizza",
    "wof:placetype":"venue"
},
  "geometry": {"coordinates":[-74.004752,40.705239],"type":"Point"}
}