{
  "type": "Feature",
  "properties": {
    "iso:country":"US",
    "sg:address":"40 W Mosholu Pkwy S",
    "sg:city":"Bronx",
    "sg:classifiers":[
        {
            "category":"Utilities",
            "subcategory":"Mobile Phone",
            "type":"Services"
        }
    ],
    "sg:phone":"+1 718 733 7471",
    "sg:postcode":"10468",
    "sg:province":"NY",
    "sg:tags":[
        "telephone",
        "cellular"
    ],
    "wof:name":"Verizon Wireless",
    "wof:placetype":"venue"
},
  "geometry": {"coordinates":[-73.887007,40.882263],"type":"Point"}
}