{
  "type": "Feature",
  "properties": {
    "iso:country":"US",
    "sg:address":"570 Oakley Ave",
    "sg:city":"Elmont",
    "sg:classifiers":[
        {
            "category":"Restaurant",
            "type":"Food & Drink"
        }
    ],
    "sg:phone":"+1 516 326 9727",
    "sg:postcode":"11003",
    "sg:province":"NY",
    "wof:name":"Wrap N Roll Deli & Bbq Grill",
    "wof:placetype":"venue"
},
  "geometry": {"coordinates":[-73.693389,40.691667],"type":"Point"}
}