{
  "type": "Feature",
  "properties": {
    "iso:country":"US",
    "sg:address":"52 Covert Ave",
    "sg:city":"Garden City",
    "sg:classifiers":[
        {
            "category":"Professional",
            "subcategory":"Testing Lab",
            "type":"Services"
        }
    ],
    "sg:phone":"+1 516 616 1104",
    "sg:postcode":"11530",
    "sg:province":"NY",
    "sg:tags":[
        "laboratory",
        "consulting",
        "c",
        "business",
        "trade"
    ],
    "wof:name":"Leadcare Inc",
    "wof:placetype":"venue"
},
  "geometry": {"coordinates":[-73.688411,40.721269],"type":"Point"}
}