{
  "type": "Feature",
  "properties": {
    "iso:country":"US",
    "sg:address":"321 Leavenworth Ave",
    "sg:city":"Syracuse",
    "sg:classifiers":[
        {
            "category":"Retail",
            "subcategory":"Auto Repair",
            "type":"Services"
        }
    ],
    "sg:phone":"+1 315 478 3355",
    "sg:postcode":"13204",
    "sg:province":"NY",
    "sg:tags":[
        "repairing",
        "automobile"
    ],
    "wof:name":"Muller Towing & Repair",
    "wof:placetype":"venue"
},
  "geometry": {"coordinates":[-76.163088,43.054505],"type":"Point"}
}