{
  "type": "Feature",
  "properties": {
    "addr:full":"15515 Jewel Ave Suite 3C Flushing NY 11367",
    "addr:housenumber":"15515",
    "addr:postcode":"11367",
    "addr:street":"Jewel Ave Suite 3C",
    "iso:country":"US",
    "sg:address":"15515 Jewel Ave Suite 3C",
    "sg:city":"Flushing",
    "sg:phone":"+1 407 264 1513",
    "sg:postcode":"11367",
    "sg:province":"NY",
    "wof:name":"Trademark Flood Restorers",
    "wof:placetype":"venue"
},
  "geometry": {"coordinates":[-73.836437,40.72621],"type":"Point"}
}