{
  "type": "Feature",
  "properties": {
    "addr:full":"391 W Broadway New York NY 10012",
    "addr:housenumber":"391",
    "addr:postcode":"10012",
    "addr:street":"W Broadway",
    "iso:country":"US",
    "sg:address":"391 W Broadway",
    "sg:city":"New York",
    "sg:classifiers":[
        {
            "category":"Real Estate",
            "subcategory":"Real Estate Agent",
            "type":"Services"
        }
    ],
    "sg:phone":"+1 212 966 4705",
    "sg:postcode":"10012",
    "sg:province":"NY",
    "sg:tags":[
        "management"
    ],
    "wof:name":"Tribeach Holdings LLC",
    "wof:placetype":"venue"
},
  "geometry": {"coordinates":[-74.00235600000001,40.72375],"type":"Point"}
}