{
  "type": "Feature",
  "properties": {
    "addr:full":"1516 Bellmore Ave Bellmore NY 11710",
    "addr:housenumber":"1516",
    "addr:postcode":"11710",
    "addr:street":"Bellmore Ave",
    "iso:country":"US",
    "sg:address":"1516 Bellmore Ave",
    "sg:city":"Bellmore",
    "sg:classifiers":[
        {
            "category":"Personal",
            "subcategory":"Beauty Salon",
            "type":"Services"
        }
    ],
    "sg:phone":"+1   ",
    "sg:postcode":"11710",
    "sg:province":"NY",
    "sg:tags":[
        "shop"
    ],
    "wof:name":"Emerald City Hair Designs",
    "wof:placetype":"venue"
},
  "geometry": {"coordinates":[-73.540587,40.684251],"type":"Point"}
}