{
  "type": "Feature",
  "properties": {
    "iso:country":"US",
    "sg:address":"15002 Liberty Avenue",
    "sg:city":"Jamaica",
    "sg:classifiers":[
        {
            "category":"Restaurant",
            "type":"Food & Drink"
        }
    ],
    "sg:phone":"+1 718 206 1200",
    "sg:postcode":"11433",
    "sg:province":"NY",
    "sg:tags":[
        "pizza"
    ],
    "wof:name":"Liberty Pizza",
    "wof:placetype":"venue"
},
  "geometry": {"coordinates":[-73.80229,40.697806],"type":"Point"}
}