{
  "type": "Feature",
  "properties": {
    "iso:country":"US",
    "sg:address":"2 Bridle Pl",
    "sg:city":"East Greenbush",
    "sg:classifiers":[
        {
            "category":"Utilities",
            "subcategory":"Telephone",
            "type":"Services"
        }
    ],
    "sg:phone":"+1   ",
    "sg:postcode":"12061",
    "sg:province":"NY",
    "sg:tags":[
        "communications"
    ],
    "wof:name":"I Presence Made Simple",
    "wof:placetype":"venue"
},
  "geometry": {"coordinates":[-73.698832,42.617061],"type":"Point"}
}