{
  "type": "Feature",
  "properties": {
    "addr:full":"309 Morgan Ave Brooklyn NY 11211",
    "addr:housenumber":"309",
    "addr:postcode":"11211",
    "addr:street":"Morgan Ave",
    "iso:country":"US",
    "sg:address":"309 Morgan Ave",
    "sg:city":"Brooklyn",
    "sg:classifiers":[
        {
            "category":"Wholesale",
            "subcategory":"Electrical",
            "type":"Manufacturing & Wholesale Goods"
        }
    ],
    "sg:phone":"+1 718 782 5800",
    "sg:postcode":"11211",
    "sg:province":"NY",
    "sg:tags":[
        "bearing",
        "industrial",
        "power",
        "transmission",
        "p",
        "other"
    ],
    "sg:website":"www.nsptcorp.com",
    "wof:name":"North Side Power Transmission",
    "wof:placetype":"venue"
},
  "geometry": {"coordinates":[-73.935579,40.714852],"type":"Point"}
}