{
  "type": "Feature",
  "properties": {
    "addr:full":"2575 Hempstead Tpke East Meadow NY 11554",
    "addr:housenumber":"2575",
    "addr:postcode":"11554",
    "addr:street":"Hempstead Tpke",
    "iso:country":"US",
    "sg:address":"2575 Hempstead Tpke",
    "sg:city":"East Meadow",
    "sg:classifiers":[
        {
            "category":"Freight",
            "type":"Transportation"
        },
        {
            "category":"Professional",
            "subcategory":"Printing & Photocopies",
            "type":"Services"
        }
    ],
    "sg:phone":"+1 516 731 1026",
    "sg:postcode":"11554",
    "sg:province":"NY",
    "sg:tags":[
        "shipping"
    ],
    "sg:website":"www.fedex.com/us/office/",
    "wof:name":"FedEx Office Print & Ship Center",
    "wof:placetype":"venue"
},
  "geometry": {"coordinates":[-73.541892,40.724474],"type":"Point"}
}