{
  "type": "Feature",
  "properties": {
    "addr:full":"114 Stanton St New York NY 10002",
    "addr:housenumber":"114",
    "addr:postcode":"10002",
    "addr:street":"Stanton St",
    "iso:country":"US",
    "sg:address":"114 Stanton St",
    "sg:city":"New York",
    "sg:classifiers":[
        {
            "category":"Home & Garden",
            "subcategory":"Home Furnishings",
            "type":"Retail Goods"
        }
    ],
    "sg:phone":"+1   ",
    "sg:postcode":"10002",
    "sg:province":"NY",
    "sg:tags":[
        "linen",
        "bedding"
    ],
    "wof:name":"Gandelam Shmil",
    "wof:placetype":"venue"
},
  "geometry": {"coordinates":[-73.98723200000001,40.721178],"type":"Point"}
}