{
  "type": "Feature",
  "properties": {
    "addr:full":"140 Griffing Ave Riverhead NY 11901",
    "addr:housenumber":"140",
    "addr:postcode":"11901",
    "addr:street":"Griffing Ave",
    "iso:country":"US",
    "sg:address":"140 Griffing Ave",
    "sg:city":"Riverhead",
    "sg:classifiers":[
        {
            "category":"Professional",
            "type":"Services"
        }
    ],
    "sg:phone":"+1 631 208 9270",
    "sg:postcode":"11901",
    "sg:province":"NY",
    "sg:tags":[
        "establishment"
    ],
    "wof:name":"Innoventive Power LLC",
    "wof:placetype":"venue"
},
  "geometry": {"coordinates":[-72.664387,40.917923],"type":"Point"}
}