{
  "type": "Feature",
  "properties": {
    "iso:country":"US",
    "sg:address":"985 Church St",
    "sg:city":"North Syracuse",
    "sg:classifiers":[
        {
            "category":"Retail",
            "subcategory":"Repair Shop",
            "type":"Services"
        }
    ],
    "sg:phone":"+1 315 458 7184",
    "sg:postcode":"13212",
    "sg:province":"NY",
    "sg:tags":[
        "kitchen",
        "cabinet"
    ],
    "wof:name":"Ultimate Kitchen",
    "wof:placetype":"venue"
},
  "geometry": {"coordinates":[-76.113978,43.126677],"type":"Point"}
}