{
  "type": "Feature",
  "properties": {
    "addr:full":"1689 Flatbush Ave Brooklyn NY 11210",
    "addr:housenumber":"1689",
    "addr:postcode":"11210",
    "addr:street":"Flatbush Ave",
    "iso:country":"US",
    "sg:address":"1689 Flatbush Ave",
    "sg:city":"Brooklyn",
    "sg:classifiers":[
        {
            "category":"Banks & Credit Unions",
            "subcategory":"Financial Services",
            "type":"Services"
        }
    ],
    "sg:phone":"+1 347 702 9904",
    "sg:postcode":"11210",
    "sg:province":"NY",
    "sg:tags":[
        "broker",
        "mortgage"
    ],
    "wof:name":"Premiere Finance Group",
    "wof:placetype":"venue"
},
  "geometry": {"coordinates":[-73.943299,40.628926],"type":"Point"}
}