{
  "type": "Feature",
  "properties": {
    "iso:country":"US",
    "sg:address":"349 E 65th St Frnt",
    "sg:city":"New York",
    "sg:classifiers":[
        {
            "category":"Retail",
            "subcategory":"Laundry & Dry Cleaning",
            "type":"Services"
        }
    ],
    "sg:phone":"+1 212 288 9698",
    "sg:postcode":"10021",
    "sg:province":"NY",
    "wof:name":"Modern French Cleaners",
    "wof:placetype":"venue"
},
  "geometry": {"coordinates":[-73.95970199999999,40.763599],"type":"Point"}
}