{
  "type": "Feature",
  "properties": {
    "iso:country":"US",
    "sg:address":"50 Hendrick St",
    "sg:city":"Lake George",
    "sg:classifiers":[
        {
            "category":"Manufacturing",
            "subcategory":"Lumber",
            "type":"Manufacturing & Wholesale Goods"
        }
    ],
    "sg:phone":"+1 518 668 2623",
    "sg:postcode":"12845",
    "sg:province":"NY",
    "sg:tags":[
        "forestry"
    ],
    "wof:name":"Christian G Gearwar",
    "wof:placetype":"venue"
},
  "geometry": {"coordinates":[-73.71505999999999,43.426306],"type":"Point"}
}