{
  "type": "Feature",
  "properties": {
    "iso:country":"US",
    "sg:address":"691 Wellwood Ave",
    "sg:city":"Lindenhurst",
    "sg:classifiers":[
        {
            "category":"Autos & Motor Vehicles",
            "subcategory":"Fuel & Gas Station",
            "type":"Retail Goods"
        }
    ],
    "sg:phone":"+1 631 226 9631",
    "sg:postcode":"11757",
    "sg:province":"NY",
    "sg:tags":[
        "oil"
    ],
    "wof:name":"Kanmor Sunoco Svc Station",
    "wof:placetype":"venue"
},
  "geometry": {"coordinates":[-73.386922,40.704333],"type":"Point"}
}