{
  "type": "Feature",
  "properties": {
    "addr:full":"5312 New Utrecht Avenue Brooklyn NY 11219",
    "addr:housenumber":"5312",
    "addr:postcode":"11219",
    "addr:street":"New Utrecht Avenue",
    "iso:country":"US",
    "sg:address":"5312 New Utrecht Avenue",
    "sg:city":"Brooklyn",
    "sg:classifiers":[
        {
            "category":"Building & Trades",
            "subcategory":"Pest Control",
            "type":"Services"
        }
    ],
    "sg:phone":"+1 718 972 5506",
    "sg:postcode":"11219",
    "sg:province":"NY",
    "wof:name":"Topco Pest Control",
    "wof:placetype":"venue"
},
  "geometry": {"coordinates":[-73.99537599999999,40.632869],"type":"Point"}
}