{
  "type": "Feature",
  "properties": {
    "addr:full":"375 E 163rd St Bronx NY 10451",
    "addr:housenumber":"375",
    "addr:postcode":"10451",
    "addr:street":"E 163Rd St",
    "iso:country":"US",
    "sg:address":"375 E 163rd St",
    "sg:city":"Bronx",
    "sg:classifiers":[
        {
            "category":"Manufacturing",
            "subcategory":"Wood Products",
            "type":"Manufacturing & Wholesale Goods"
        }
    ],
    "sg:phone":"+1   ",
    "sg:postcode":"10451",
    "sg:province":"NY",
    "sg:tags":[
        "mfg"
    ],
    "wof:name":"Urban Architectural Wdwkg",
    "wof:placetype":"venue"
},
  "geometry": {"coordinates":[-73.913167,40.825457],"type":"Point"}
}