{
  "type": "Feature",
  "properties": {
    "iso:country":"US",
    "sg:address":"4187 Lake Shore Rd",
    "sg:city":"Hamburg",
    "sg:classifiers":[
        {
            "category":"Professional",
            "type":"Services"
        }
    ],
    "sg:phone":"+1 716 627 3471",
    "sg:postcode":"14075",
    "sg:province":"NY",
    "sg:tags":[
        "establishment"
    ],
    "wof:name":"Noco Express",
    "wof:placetype":"venue"
},
  "geometry": {"coordinates":[-78.865634,42.771208],"type":"Point"}
}