{
  "type": "Feature",
  "properties": {
    "addr:full":"445 5th Ave New York NY 10016",
    "addr:housenumber":"445",
    "addr:postcode":"10016",
    "addr:street":"5Th Ave",
    "iso:country":"US",
    "sg:address":"445 5th Ave",
    "sg:city":"New York",
    "sg:classifiers":[
        {
            "category":"Professional",
            "type":"Services"
        }
    ],
    "sg:phone":"+1 212 447 6033",
    "sg:postcode":"10016",
    "sg:province":"NY",
    "sg:tags":[
        "establishment"
    ],
    "wof:name":"Language Works",
    "wof:placetype":"venue"
},
  "geometry": {"coordinates":[-73.98183299999999,40.752022],"type":"Point"}
}