{
  "type": "Feature",
  "properties": {
    "addr:full":"482 Main St Northport NY 11768",
    "addr:housenumber":"482",
    "addr:postcode":"11768",
    "addr:street":"Main St",
    "iso:country":"US",
    "sg:address":"482 Main St",
    "sg:city":"Northport",
    "sg:classifiers":[
        {
            "category":"Health Services",
            "subcategory":"Podiatrist",
            "type":"Services"
        }
    ],
    "sg:phone":"+1 631 754 7000",
    "sg:postcode":"11768",
    "sg:province":"NY",
    "wof:name":"Iannacone Ronald F DPM",
    "wof:placetype":"venue"
},
  "geometry": {"coordinates":[-73.336304,40.900902],"type":"Point"}
}