{
  "type": "Feature",
  "properties": {
    "addr:full":"2503 Middle Country Rd Centereach NY 11720",
    "addr:housenumber":"2503",
    "addr:postcode":"11720",
    "addr:street":"Middle Country Rd",
    "iso:country":"US",
    "sg:address":"2503 Middle Country Rd",
    "sg:city":"Centereach",
    "sg:classifiers":[
        {
            "category":"Shopping",
            "subcategory":"Bicycles & Sporting Goods",
            "type":"Retail Goods"
        }
    ],
    "sg:phone":"+1 631 471 3230",
    "sg:postcode":"11720",
    "sg:province":"NY",
    "sg:website":"www.ebikediscounters.com",
    "wof:name":"Bike Discounters",
    "wof:placetype":"venue"
},
  "geometry": {"coordinates":[-73.096659,40.858153],"type":"Point"}
}