{
  "type": "Feature",
  "properties": {
    "addr:full":"587 Baty St Elmira NY 14904",
    "addr:housenumber":"587",
    "addr:postcode":"14904",
    "addr:street":"Baty St",
    "iso:country":"US",
    "sg:address":"587 Baty St",
    "sg:city":"Elmira",
    "sg:classifiers":[
        {
            "category":"Freight",
            "type":"Transportation"
        }
    ],
    "sg:phone":"+1 607 734 8495",
    "sg:postcode":"14904",
    "sg:province":"NY",
    "sg:tags":[
        "trucking"
    ],
    "wof:name":"Early Bird Trucking",
    "wof:placetype":"venue"
},
  "geometry": {"coordinates":[-76.811638,42.07223],"type":"Point"}
}