{
  "type": "Feature",
  "properties": {
    "addr:full":"220 Chapel Dr Syracuse NY 13219",
    "addr:housenumber":"220",
    "addr:postcode":"13219",
    "addr:street":"Chapel Dr",
    "iso:country":"US",
    "sg:address":"220 Chapel Dr",
    "sg:city":"Syracuse",
    "sg:classifiers":[
        {
            "category":"Bars & Pubs",
            "type":"Food & Drink"
        }
    ],
    "sg:phone":"+1   ",
    "sg:postcode":"13219",
    "sg:province":"NY",
    "sg:tags":[
        "drinking"
    ],
    "wof:name":"Munchys",
    "wof:placetype":"venue"
},
  "geometry": {"coordinates":[-76.24491999999999,43.044663],"type":"Point"}
}