{
  "type": "Feature",
  "properties": {
    "iso:country":"US",
    "sg:address":"10 Wind Mill Rd",
    "sg:city":"Pittsford",
    "sg:classifiers":[
        {
            "category":"Professional",
            "subcategory":"Lawyer & Legal Services",
            "type":"Services"
        }
    ],
    "sg:phone":"+1 585 264 1880",
    "sg:postcode":"14534",
    "sg:province":"NY",
    "sg:tags":[
        "attorney"
    ],
    "wof:name":"Judith Holender Loeb",
    "wof:placetype":"venue"
},
  "geometry": {"coordinates":[-77.51319100000001,43.070896],"type":"Point"}
}