{
  "type": "Feature",
  "properties": {
    "iso:country":"US",
    "sg:address":"256 N Main St",
    "sg:city":"Freeport",
    "sg:classifiers":[
        {
            "category":"Professional",
            "type":"Services"
        }
    ],
    "sg:phone":"+1 516 223 3029",
    "sg:postcode":"11520",
    "sg:province":"NY",
    "sg:tags":[
        "establishment"
    ],
    "wof:name":"Island Reinforcing Corp",
    "wof:placetype":"venue"
},
  "geometry": {"coordinates":[-73.586809,40.665823],"type":"Point"}
}