{
  "type": "Feature",
  "properties": {
    "addr:full":"160 Wildey St Tarrytown NY 10591",
    "addr:housenumber":"160",
    "addr:postcode":"10591",
    "addr:street":"Wildey St",
    "iso:country":"US",
    "sg:address":"160 Wildey St",
    "sg:city":"Tarrytown",
    "sg:classifiers":[
        {
            "category":"Home & Garden",
            "subcategory":"Building Materials",
            "type":"Retail Goods"
        },
        {
            "category":"Manufacturing",
            "subcategory":"Building Materials",
            "type":"Manufacturing & Wholesale Goods"
        }
    ],
    "sg:phone":"+1 914 631 2013",
    "sg:postcode":"10591",
    "sg:province":"NY",
    "sg:tags":[
        "lumber",
        "mfg"
    ],
    "wof:name":"Modular Molding Co",
    "wof:placetype":"venue"
},
  "geometry": {"coordinates":[-73.865295,41.080256],"type":"Point"}
}