{
  "type": "Feature",
  "properties": {
    "addr:full":"20 Old Mamaroneck Rd White Plains NY 10605",
    "addr:housenumber":"20",
    "addr:postcode":"10605",
    "addr:street":"Old Mamaroneck Rd",
    "iso:country":"US",
    "sg:address":"20 Old Mamaroneck Rd",
    "sg:city":"White Plains",
    "sg:classifiers":[
        {
            "category":"Professional",
            "subcategory":"Lawyer & Legal Services",
            "type":"Services"
        }
    ],
    "sg:phone":"+1   ",
    "sg:postcode":"10605",
    "sg:province":"NY",
    "wof:name":"Seymour Robinowitz Atty",
    "wof:placetype":"venue"
},
  "geometry": {"coordinates":[-73.761544,41.022273],"type":"Point"}
}