{
  "type": "Feature",
  "properties": {
    "addr:full":"146 Split Rock Rd Syosset NY 11791",
    "addr:housenumber":"146",
    "addr:postcode":"11791",
    "addr:street":"Split Rock Rd",
    "iso:country":"US",
    "sg:address":"146 Split Rock Rd",
    "sg:city":"Syosset",
    "sg:classifiers":[
        {
            "category":"Wholesale",
            "subcategory":"Apparel",
            "type":"Manufacturing & Wholesale Goods"
        }
    ],
    "sg:phone":"+1 516 294 3900",
    "sg:postcode":"11791",
    "sg:province":"NY",
    "sg:tags":[
        "textile",
        "broker"
    ],
    "wof:name":"Grubman & Co Inc",
    "wof:placetype":"venue"
},
  "geometry": {"coordinates":[-73.504659,40.830148],"type":"Point"}
}