{
  "type": "Feature",
  "properties": {
    "addr:full":"238 Mohawk Ave Scotia NY 12302",
    "addr:housenumber":"238",
    "addr:postcode":"12302",
    "addr:street":"Mohawk Ave",
    "iso:country":"US",
    "sg:address":"238 Mohawk Ave",
    "sg:city":"Scotia",
    "sg:classifiers":[
        {
            "category":"Retail",
            "subcategory":"Auto Rental",
            "type":"Services"
        }
    ],
    "sg:phone":"+1 518 374 8780",
    "sg:postcode":"12302",
    "sg:province":"NY",
    "sg:tags":[
        "renting",
        "truck",
        "leasing"
    ],
    "wof:name":"Budget Truck Rental",
    "wof:placetype":"venue"
},
  "geometry": {"coordinates":[-73.96797100000001,42.827739],"type":"Point"}
}