{
  "type": "Feature",
  "properties": {
    "addr:full":"219 Eldridge St New York NY 10002",
    "addr:housenumber":"219",
    "addr:postcode":"10002",
    "addr:street":"Eldridge St",
    "iso:country":"US",
    "sg:address":"219 Eldridge St",
    "sg:city":"New York",
    "sg:classifiers":[
        {
            "category":"Retail",
            "subcategory":"Auto Repair",
            "type":"Services"
        }
    ],
    "sg:phone":"+1 917 464 2645",
    "sg:postcode":"10002",
    "sg:province":"NY",
    "sg:tags":[
        "wrecker"
    ],
    "wof:name":"24 Hour 7 Day Emrgncy Towing",
    "wof:placetype":"venue"
},
  "geometry": {"coordinates":[-73.990528,40.720865],"type":"Point"}
}