{
  "type": "Feature",
  "properties": {
    "addr:full":"268 Stewart Ave Garden City NY 11530",
    "addr:housenumber":"268",
    "addr:postcode":"11530",
    "addr:street":"Stewart Ave",
    "iso:country":"US",
    "sg:address":"268 Stewart Ave",
    "sg:city":"Garden City",
    "sg:classifiers":[
        {
            "category":"Freight",
            "type":"Transportation"
        }
    ],
    "sg:phone":"+1   ",
    "sg:postcode":"11530",
    "sg:province":"NY",
    "sg:tags":[
        "operator",
        "local",
        "trucking"
    ],
    "wof:name":"Classic Trucking & Equip Inc",
    "wof:placetype":"venue"
},
  "geometry": {"coordinates":[-73.65336499999999,40.724729],"type":"Point"}
}