{
  "type": "Feature",
  "properties": {
    "addr:full":"1890 Palmer Ave Larchmont NY 10538",
    "addr:housenumber":"1890",
    "addr:postcode":"10538",
    "addr:street":"Palmer Ave",
    "iso:country":"US",
    "sg:address":"1890 Palmer Ave",
    "sg:city":"Larchmont",
    "sg:classifiers":[
        {
            "category":"Professional",
            "subcategory":"Management & Consulting",
            "type":"Services"
        }
    ],
    "sg:phone":"+1 914 833 7679",
    "sg:postcode":"10538",
    "sg:province":"NY",
    "sg:tags":[
        "consultant",
        "business"
    ],
    "wof:name":"Arnold Becker Group",
    "wof:placetype":"venue"
},
  "geometry": {"coordinates":[-73.75815,40.933585],"type":"Point"}
}