{
  "type": "Feature",
  "properties": {
    "addr:full":"1441 Bushwick Ave Brooklyn NY 11207",
    "addr:housenumber":"1441",
    "addr:postcode":"11207",
    "addr:street":"Bushwick Ave",
    "iso:country":"US",
    "sg:address":"1441 Bushwick Ave",
    "sg:city":"Brooklyn",
    "sg:classifiers":[
        {
            "category":"Building & Trades",
            "subcategory":"Plumbing",
            "type":"Services"
        }
    ],
    "sg:phone":"+1 516 426 0606",
    "sg:postcode":"11207",
    "sg:province":"NY",
    "sg:tags":[
        "sprinkler",
        "heating",
        "air",
        "ventilation",
        "piping",
        "conditioning"
    ],
    "wof:name":"Tj Piping Heating & Sprinkler",
    "wof:placetype":"venue"
},
  "geometry": {"coordinates":[-73.90793600000001,40.683795],"type":"Point"}
}