{
  "type": "Feature",
  "properties": {
    "addr:full":"155 Washington Ave Albany NY 12210",
    "addr:housenumber":"155",
    "addr:postcode":"12210",
    "addr:street":"Washington Ave",
    "iso:country":"US",
    "sg:address":"155 Washington Ave",
    "sg:city":"Albany",
    "sg:classifiers":[
        {
            "category":"Government",
            "subcategory":"Office",
            "type":"Public Place"
        }
    ],
    "sg:phone":"+1 518 486 7505",
    "sg:postcode":"12210",
    "sg:province":"NY",
    "sg:tags":[
        "state",
        "resource"
    ],
    "sg:website":"www.dddt.state.ny.us.com",
    "wof:name":"Developmental Disabilities",
    "wof:placetype":"venue"
},
  "geometry": {"coordinates":[-73.762738,42.65643],"type":"Point"}
}