{
  "type": "Feature",
  "properties": {
    "addr:full":"3106 E Tremont Ave Bronx NY 10461",
    "addr:housenumber":"3106",
    "addr:postcode":"10461",
    "addr:street":"E Tremont Ave",
    "iso:country":"US",
    "sg:address":"3106 E Tremont Ave",
    "sg:city":"Bronx",
    "sg:classifiers":[
        {
            "category":"Personal",
            "subcategory":"Barber",
            "type":"Services"
        }
    ],
    "sg:phone":"+1 718 409 0049",
    "sg:postcode":"10461",
    "sg:province":"NY",
    "wof:name":"Joey Cuts",
    "wof:placetype":"venue"
},
  "geometry": {"coordinates":[-73.835246,40.838264],"type":"Point"}
}