{
  "type": "Feature",
  "properties": {
    "iso:country":"US",
    "sg:address":"39 Biscayne Dr",
    "sg:city":"Selden",
    "sg:classifiers":[
        {
            "category":"Building & Trades",
            "subcategory":"Cleaning & Sanitation",
            "type":"Services"
        }
    ],
    "sg:phone":"+1 631 698 5646",
    "sg:postcode":"11784",
    "sg:province":"NY",
    "sg:tags":[
        "carpet"
    ],
    "sg:website":"www.mrjohnscleaning.com",
    "wof:name":"Mr Johns Floor & Upholsterhy Cleaning",
    "wof:placetype":"venue"
},
  "geometry": {"coordinates":[-73.463812,40.892174],"type":"Point"}
}