{
  "type": "Feature",
  "properties": {
    "iso:country":"US",
    "sg:address":"1985 Grand Ave",
    "sg:city":"North Baldwin",
    "sg:classifiers":[
        {
            "category":"Retail",
            "subcategory":"Auto Repair",
            "type":"Services"
        }
    ],
    "sg:phone":"+1 516 868 6969",
    "sg:postcode":"11510",
    "sg:province":"NY",
    "sg:tags":[
        "repairing",
        "automobile",
        "general"
    ],
    "wof:name":"Venturi Automotive",
    "wof:placetype":"venue"
},
  "geometry": {"coordinates":[-73.607524,40.661515],"type":"Point"}
}