{
  "type": "Feature",
  "properties": {
    "addr:full":"236 James St Clayton NY 13624",
    "addr:housenumber":"236",
    "addr:postcode":"13624",
    "addr:street":"James St",
    "iso:country":"US",
    "sg:address":"236 James St",
    "sg:city":"Clayton",
    "sg:classifiers":[
        {
            "category":"Professional",
            "subcategory":"Business Services",
            "type":"Services"
        }
    ],
    "sg:phone":"+1 315 686 3148",
    "sg:postcode":"13624",
    "sg:province":"NY",
    "sg:tags":[
        "interior",
        "consultant",
        "design",
        "decorator"
    ],
    "sg:website":"www.porchandpaddle.com",
    "wof:name":"Porch and Paddle",
    "wof:placetype":"venue"
},
  "geometry": {"coordinates":[-76.08915500000001,44.241396],"type":"Point"}
}