{
  "type": "Feature",
  "properties": {
    "iso:country":"US",
    "sg:address":"117 11th St Ste 209",
    "sg:city":"Brooklyn",
    "sg:classifiers":[
        {
            "category":"Professional",
            "type":"Services"
        },
        {
            "category":"Personal",
            "type":"Services"
        }
    ],
    "sg:phone":"+1 800 996 8658",
    "sg:postcode":"11215",
    "sg:province":"NY",
    "sg:tags":[
        "mover",
        "relocation"
    ],
    "wof:name":"Volt Relocation Services",
    "wof:placetype":"venue"
},
  "geometry": {"coordinates":[-73.992752,40.670611],"type":"Point"}
}