{
  "type": "Feature",
  "properties": {
    "addr:full":"2512 Avenue U Brooklyn NY 11229",
    "addr:housenumber":"2512",
    "addr:postcode":"11229",
    "addr:street":"Avenue U",
    "iso:country":"US",
    "sg:address":"2512 Avenue U",
    "sg:city":"Brooklyn",
    "sg:classifiers":[
        {
            "category":"Banks & Credit Unions",
            "subcategory":"Bank",
            "type":"Services"
        }
    ],
    "sg:phone":"+1 718 648 2549",
    "sg:postcode":"11229",
    "sg:province":"NY",
    "wof:name":"Chase",
    "wof:placetype":"venue"
},
  "geometry": {"coordinates":[-73.946484,40.599785],"type":"Point"}
}