{
  "type": "Feature",
  "properties": {
    "iso:country":"US",
    "sg:address":"1 Walnut St",
    "sg:city":"Lockport",
    "sg:classifiers":[
        {
            "category":"Food & Beverages",
            "subcategory":"Groceries & Convenience Stores",
            "type":"Retail Goods"
        }
    ],
    "sg:phone":"+1 716 434 2244",
    "sg:postcode":"14094",
    "sg:province":"NY",
    "wof:name":"Kenyon's Variety",
    "wof:placetype":"venue"
},
  "geometry": {"coordinates":[-78.693848,43.168386],"type":"Point"}
}