{
  "type": "Feature",
  "properties": {
    "addr:full":"507 Westbury Ave Carle Place NY 11514",
    "addr:housenumber":"507",
    "addr:postcode":"11514",
    "addr:street":"Westbury Ave",
    "iso:country":"US",
    "sg:address":"507 Westbury Ave",
    "sg:city":"Carle Place",
    "sg:classifiers":[
        {
            "category":"Real Estate",
            "subcategory":"Real Estate Services",
            "type":"Services"
        },
        {
            "category":"Real Estate",
            "subcategory":"Real Estate Operator",
            "type":"Services"
        }
    ],
    "sg:phone":"+1 516 333 1122",
    "sg:postcode":"11514",
    "sg:province":"NY",
    "sg:tags":[
        "apartment"
    ],
    "wof:name":"Rowan Realty Rl Est",
    "wof:placetype":"venue"
},
  "geometry": {"coordinates":[-73.60659800000001,40.7509],"type":"Point"}
}