{
  "type": "Feature",
  "properties": {
    "iso:country":"US",
    "sg:address":"979 Fulton St",
    "sg:city":"Brooklyn",
    "sg:classifiers":[
        {
            "category":"Home & Garden",
            "subcategory":"Furniture",
            "type":"Retail Goods"
        }
    ],
    "sg:phone":"+1 718 857 2588",
    "sg:postcode":"11238",
    "sg:province":"NY",
    "sg:tags":[
        "store"
    ],
    "wof:name":"Furniture Lot",
    "wof:placetype":"venue"
},
  "geometry": {"coordinates":[-73.96379899999999,40.682899],"type":"Point"}
}