{
  "type": "Feature",
  "properties": {
    "iso:country":"US",
    "sg:address":"1295 Elijahs Ln",
    "sg:city":"Mattituck",
    "sg:classifiers":[
        {
            "category":"Building & Trades",
            "subcategory":"Construction",
            "type":"Services"
        }
    ],
    "sg:phone":"+1 631 298 8944",
    "sg:postcode":"11952",
    "sg:province":"NY",
    "sg:tags":[
        "system",
        "contractor",
        "air conditioning"
    ],
    "wof:name":"Perfection Plumbing & Heating",
    "wof:placetype":"venue"
},
  "geometry": {"coordinates":[-72.512725,41.002092],"type":"Point"}
}