{
  "type": "Feature",
  "properties": {
    "iso:country":"US",
    "sg:address":"7567 Oswego Rd Ste 6",
    "sg:city":"Liverpool",
    "sg:classifiers":[
        {
            "category":"Personal",
            "subcategory":"Tanning Parlor",
            "type":"Services"
        }
    ],
    "sg:phone":"+1 315 622 4820",
    "sg:postcode":"13090",
    "sg:province":"NY",
    "sg:tags":[
        "salon"
    ],
    "wof:name":"Aztec Tanning",
    "wof:placetype":"venue"
},
  "geometry": {"coordinates":[-76.22525,43.13664],"type":"Point"}
}