{
  "type": "Feature",
  "properties": {
    "iso:country":"US",
    "sg:address":"702 Burke Ave",
    "sg:city":"Bronx",
    "sg:classifiers":[
        {
            "category":"Food & Beverages",
            "subcategory":"Groceries & Convenience Stores",
            "type":"Retail Goods"
        }
    ],
    "sg:phone":"+1 718 655 2707",
    "sg:postcode":"10467",
    "sg:province":"NY",
    "sg:tags":[
        "grocer"
    ],
    "wof:name":"Deli Grocery Inc",
    "wof:placetype":"venue"
},
  "geometry": {"coordinates":[-73.86621599999999,40.87135],"type":"Point"}
}