{
  "type": "Feature",
  "properties": {
    "iso:country":"US",
    "sg:address":"39 Elm St",
    "sg:city":"New Canaan",
    "sg:classifiers":[
        {
            "category":"Shopping",
            "subcategory":"Clothing, Apparel, & Fashions",
            "type":"Retail Goods"
        }
    ],
    "sg:phone":"+1 203 966 0518",
    "sg:postcode":"06840",
    "sg:province":"NY",
    "sg:tags":[
        "furnishing"
    ],
    "wof:name":"Family Britches Inc",
    "wof:placetype":"venue"
},
  "geometry": {"coordinates":[-73.49256699999999,41.147078],"type":"Point"}
}