{
  "type": "Feature",
  "properties": {
    "addr:full":"118 W 22nd Street New York NY 10011",
    "addr:housenumber":"118",
    "addr:postcode":"10011",
    "addr:street":"W 22Nd Street",
    "iso:country":"US",
    "sg:address":"118 W 22nd Street",
    "sg:city":"New York",
    "sg:classifiers":[
        {
            "category":"Real Estate",
            "subcategory":"Architect",
            "type":"Services"
        }
    ],
    "sg:phone":"+1 212 807 1960",
    "sg:postcode":"10011",
    "sg:province":"NY",
    "sg:website":"www.messanaororke.com",
    "wof:name":"Messana O'rorke Architects",
    "wof:placetype":"venue"
},
  "geometry": {"coordinates":[-73.993736,40.742523],"type":"Point"}
}