{
  "type": "Feature",
  "properties": {
    "addr:full":"480 Fashion Ave New York NY 10018",
    "addr:housenumber":"480",
    "addr:postcode":"10018",
    "addr:street":"Fashion Ave",
    "iso:country":"US",
    "sg:address":"480 Fashion Ave",
    "sg:city":"New York",
    "sg:classifiers":[
        {
            "category":"Banks & Credit Unions",
            "subcategory":"Bank",
            "type":"Services"
        }
    ],
    "sg:phone":"+1 917 339 0361",
    "sg:postcode":"10018",
    "sg:province":"NY",
    "sg:tags":[
        "machine",
        "teller",
        "automated"
    ],
    "wof:name":"Nam's Atm Bankcard Svc Inc",
    "wof:placetype":"venue"
},
  "geometry": {"coordinates":[-73.990134,40.751659],"type":"Point"}
}