{
  "type": "Feature",
  "properties": {
    "addr:full":"11146 Lefferts Boulevard South Ozone Park NY 11420",
    "addr:housenumber":"11146",
    "addr:postcode":"11420",
    "addr:street":"Lefferts Boulevard",
    "iso:country":"US",
    "sg:address":"11146 Lefferts Boulevard",
    "sg:city":"South Ozone Park",
    "sg:classifiers":[
        {
            "category":"Restaurant",
            "type":"Food & Drink"
        }
    ],
    "sg:phone":"+1 718 529 5580",
    "sg:postcode":"11420",
    "sg:province":"NY",
    "wof:name":"Eclipse Restaurant",
    "wof:placetype":"venue"
},
  "geometry": {"coordinates":[-73.821268,40.679995],"type":"Point"}
}