{
  "type": "Feature",
  "properties": {
    "addr:full":"90 Joseph Ave Staten Island NY 10314",
    "addr:housenumber":"90",
    "addr:postcode":"10314",
    "addr:street":"Joseph Ave",
    "iso:country":"US",
    "sg:address":"90 Joseph Ave",
    "sg:city":"Staten Island",
    "sg:classifiers":[
        {
            "category":"Real Estate",
            "subcategory":"Real Estate Agent",
            "type":"Services"
        }
    ],
    "sg:phone":"+1 718 494 6153",
    "sg:postcode":"10314",
    "sg:province":"NY",
    "wof:name":"Kalev Realty Ltd",
    "wof:placetype":"venue"
},
  "geometry": {"coordinates":[-74.136872,40.600826],"type":"Point"}
}