{
  "type": "Feature",
  "properties": {
    "iso:country":"US",
    "sg:address":"37 Legion Pl",
    "sg:city":"Malverne",
    "sg:classifiers":[
        {
            "category":"Real Estate",
            "subcategory":"Real Estate Operator",
            "type":"Services"
        }
    ],
    "sg:phone":"+1 516 593 5617",
    "sg:postcode":"11565",
    "sg:province":"NY",
    "sg:tags":[
        "building",
        "nonresidential"
    ],
    "wof:name":"Marginal Street Realty",
    "wof:placetype":"venue"
},
  "geometry": {"coordinates":[-73.680103,40.675891],"type":"Point"}
}