{
  "type": "Feature",
  "properties": {
    "iso:country":"US",
    "sg:address":"1361 Old Northern Blvd",
    "sg:city":"Roslyn",
    "sg:classifiers":[
        {
            "category":"Restaurant",
            "type":"Food & Drink"
        }
    ],
    "sg:phone":"+1 516 621 8868",
    "sg:postcode":"11576",
    "sg:province":"NY",
    "sg:tags":[
        "japanese"
    ],
    "sg:website":"www.yuzufusion.com",
    "wof:name":"Yuzu Fusion",
    "wof:placetype":"venue"
},
  "geometry": {"coordinates":[-73.647717,40.800967],"type":"Point"}
}