{
  "type": "Feature",
  "properties": {
    "addr:full":"59 W 21st St Manhattan NY 10011",
    "addr:housenumber":"59",
    "addr:postcode":"10011",
    "addr:street":"W 21St St",
    "iso:country":"US",
    "sg:address":"59 W 21st St",
    "sg:city":"Manhattan",
    "sg:classifiers":[
        {
            "category":"Bars & Pubs",
            "subcategory":"Lounge",
            "type":"Food & Drink"
        }
    ],
    "sg:phone":"+1 212 359 4200",
    "sg:postcode":"10011",
    "sg:province":"NY",
    "sg:website":"www.studioxxinyc.com/",
    "wof:name":"Studio XXI",
    "wof:placetype":"venue"
},
  "geometry": {"coordinates":[-73.993289,40.741469],"type":"Point"}
}