{
  "type": "Feature",
  "properties": {
    "iso:country":"US",
    "sg:address":"325 Sand Hill Rd",
    "sg:city":"Greenfield Center",
    "sg:classifiers":[
        {
            "category":"Building & Trades",
            "subcategory":"Construction",
            "type":"Services"
        }
    ],
    "sg:phone":"+1 518 584 2952",
    "sg:postcode":"12833",
    "sg:province":"NY",
    "sg:tags":[
        "excavation",
        "contractor"
    ],
    "wof:name":"Dm Wardell Excavation Inc",
    "wof:placetype":"venue"
},
  "geometry": {"coordinates":[-73.90752999999999,43.109846],"type":"Point"}
}