{
  "type": "Feature",
  "properties": {
    "addr:full":"385 Countryside Ln Buffalo NY 14221",
    "addr:housenumber":"385",
    "addr:postcode":"14221",
    "addr:street":"Countryside Ln",
    "iso:country":"US",
    "sg:address":"385 Countryside Ln",
    "sg:city":"Buffalo",
    "sg:classifiers":[
        {
            "category":"Wholesale",
            "subcategory":"Metals & Minerals",
            "type":"Manufacturing & Wholesale Goods"
        }
    ],
    "sg:phone":"+1 716 688 2943",
    "sg:postcode":"14221",
    "sg:province":"NY",
    "wof:name":"Seyferts Minerals & Fossils",
    "wof:placetype":"venue"
},
  "geometry": {"coordinates":[-78.747991,43.009019],"type":"Point"}
}