{
  "type": "Feature",
  "properties": {
    "addr:full":"9802 Foster Avenue Brooklyn NY 11236",
    "addr:housenumber":"9802",
    "addr:postcode":"11236",
    "addr:street":"Foster Avenue",
    "iso:country":"US",
    "sg:address":"9802 Foster Avenue",
    "sg:city":"Brooklyn",
    "sg:classifiers":[
        {
            "category":"Restaurant",
            "type":"Food & Drink"
        }
    ],
    "sg:phone":"+1 718 927 3360",
    "sg:postcode":"11236",
    "sg:province":"NY",
    "wof:name":"Foster Avenue Deli",
    "wof:placetype":"venue"
},
  "geometry": {"coordinates":[-73.904714,40.64881],"type":"Point"}
}