{
  "type": "Feature",
  "properties": {
    "addr:full":"539 Highland Ave Horseheads NY 14845",
    "addr:housenumber":"539",
    "addr:postcode":"14845",
    "addr:street":"Highland Ave",
    "iso:country":"US",
    "sg:address":"539 Highland Ave",
    "sg:city":"Horseheads",
    "sg:classifiers":[
        {
            "category":"Social Services",
            "subcategory":"Child Care",
            "type":"Services"
        }
    ],
    "sg:phone":"+1   ",
    "sg:postcode":"14845",
    "sg:province":"NY",
    "sg:tags":[
        "day"
    ],
    "wof:name":"Kerrys Daycare",
    "wof:placetype":"venue"
},
  "geometry": {"coordinates":[-76.831991,42.176701],"type":"Point"}
}