{
  "type": "Feature",
  "properties": {
    "addr:full":"2214 86th St Brooklyn NY 11214",
    "addr:housenumber":"2214",
    "addr:postcode":"11214",
    "addr:street":"86Th St",
    "iso:country":"US",
    "sg:address":"2214 86th St",
    "sg:city":"Brooklyn",
    "sg:classifiers":[
        {
            "category":"Food & Beverages",
            "subcategory":"Bakery",
            "type":"Retail Goods"
        }
    ],
    "sg:phone":"+1 718 714 0988",
    "sg:postcode":"11214",
    "sg:province":"NY",
    "sg:tags":[
        "baker",
        "restaurant"
    ],
    "wof:name":"Golden Crown Bakery",
    "wof:placetype":"venue"
},
  "geometry": {"coordinates":[-73.9935,40.601601],"type":"Point"}
}