{
  "type": "Feature",
  "properties": {
    "addr:full":"884 Merrick Rd Baldwin NY 11510",
    "addr:housenumber":"884",
    "addr:postcode":"11510",
    "addr:street":"Merrick Rd",
    "iso:country":"US",
    "sg:address":"884 Merrick Rd",
    "sg:city":"Baldwin",
    "sg:classifiers":[
        {
            "category":"Real Estate",
            "subcategory":"Real Estate Agent",
            "type":"Services"
        }
    ],
    "sg:phone":"+1 516 546 2520",
    "sg:postcode":"11510",
    "sg:province":"NY",
    "wof:name":"Equitable Property Solutions",
    "wof:placetype":"venue"
},
  "geometry": {"coordinates":[-73.610021,40.650822],"type":"Point"}
}