{
  "type": "Feature",
  "properties": {
    "addr:full":"244 5th Ave New York NY 10009",
    "addr:housenumber":"244",
    "addr:postcode":"10009",
    "addr:street":"5Th Ave",
    "iso:country":"US",
    "sg:address":"244 5th Ave",
    "sg:city":"New York",
    "sg:classifiers":[
        {
            "category":"Travel",
            "subcategory":"Travel Agent",
            "type":"Entertainment"
        }
    ],
    "sg:phone":"+1 917 515 8255",
    "sg:postcode":"10009",
    "sg:province":"NY",
    "sg:website":"www.kravingbeyondtravel.com",
    "wof:name":"Kraving Beyond Travel",
    "wof:placetype":"venue"
},
  "geometry": {"coordinates":[-73.987764,40.744618],"type":"Point"}
}