{
  "type": "Feature",
  "properties": {
    "addr:full":"180 Lawrence Rd Kings Park NY 11754",
    "addr:housenumber":"180",
    "addr:postcode":"11754",
    "addr:street":"Lawrence Rd",
    "iso:country":"US",
    "sg:address":"180 Lawrence Rd",
    "sg:city":"Kings Park",
    "sg:classifiers":[
        {
            "category":"Retail",
            "subcategory":"Repair Shop",
            "type":"Services"
        }
    ],
    "sg:phone":"+1 631 460 0009",
    "sg:postcode":"11754",
    "sg:province":"NY",
    "sg:tags":[
        "lock",
        "locksmith"
    ],
    "wof:name":"Locksmith Services",
    "wof:placetype":"venue"
},
  "geometry": {"coordinates":[-73.240905,40.888048],"type":"Point"}
}