{
  "type": "Feature",
  "properties": {
    "iso:country":"US",
    "sg:address":"87 Church Ave",
    "sg:city":"Brooklyn",
    "sg:classifiers":[
        {
            "category":"Food & Beverages",
            "subcategory":"Groceries & Convenience Stores",
            "type":"Retail Goods"
        }
    ],
    "sg:phone":"+1 718 436 5816",
    "sg:postcode":"11218",
    "sg:province":"NY",
    "sg:tags":[
        "grocer"
    ],
    "wof:name":"Red Farm Inc",
    "wof:placetype":"venue"
},
  "geometry": {"coordinates":[-73.980003,40.6427],"type":"Point"}
}