{
  "type": "Feature",
  "properties": {
    "iso:country":"US",
    "sg:address":"1723 N Ocean Ave",
    "sg:city":"Medford",
    "sg:classifiers":[
        {
            "category":"Social Services",
            "subcategory":"Child Care",
            "type":"Services"
        }
    ],
    "sg:phone":"+1 631 475 4991",
    "sg:postcode":"11763",
    "sg:province":"NY",
    "sg:tags":[
        "day"
    ],
    "wof:name":"Childrens Garden Day Care & Learning Center Inc",
    "wof:placetype":"venue"
},
  "geometry": {"coordinates":[-73.020302,40.819],"type":"Point"}
}