{
  "type": "Feature",
  "properties": {
    "iso:country":"US",
    "sg:address":"67 Lakeland Ave",
    "sg:city":"Sayville",
    "sg:classifiers":[
        {
            "category":"Wholesale",
            "subcategory":"Machinery & Supplies",
            "type":"Manufacturing & Wholesale Goods"
        }
    ],
    "sg:phone":"+1 631 244 7493",
    "sg:postcode":"11782",
    "sg:province":"NY",
    "sg:tags":[
        "bearing"
    ],
    "wof:name":"Alliance Bearings Industrial",
    "wof:placetype":"venue"
},
  "geometry": {"coordinates":[-73.086285,40.742834],"type":"Point"}
}