{
  "type": "Feature",
  "properties": {
    "iso:country":"US",
    "sg:address":"28 W Main St",
    "sg:city":"Tarrytown",
    "sg:classifiers":[
        {
            "category":"Shopping",
            "subcategory":"Used Merchandise",
            "type":"Retail Goods"
        }
    ],
    "sg:phone":"+1   ",
    "sg:postcode":"10591",
    "sg:province":"NY",
    "wof:name":"North Castle Antiques",
    "wof:placetype":"venue"
},
  "geometry": {"coordinates":[-73.859887,41.07653],"type":"Point"}
}