{
  "type": "Feature",
  "properties": {
    "iso:country":"US",
    "sg:address":"11821 Queens Boulevard",
    "sg:city":"Forest Hills",
    "sg:classifiers":[
        {
            "category":"Professional",
            "subcategory":"Lawyer & Legal Services",
            "type":"Services"
        }
    ],
    "sg:phone":"+1 718 261 4141",
    "sg:postcode":"11375",
    "sg:province":"NY",
    "wof:name":"Rovegno Robert P Atty",
    "wof:placetype":"venue"
},
  "geometry": {"coordinates":[-73.84506,40.724095],"type":"Point"}
}