{
  "type": "Feature",
  "properties": {
    "iso:country":"US",
    "sg:address":"32 W Islip Rd",
    "sg:city":"West Islip",
    "sg:classifiers":[
        {
            "category":"Building & Trades",
            "subcategory":"Construction",
            "type":"Services"
        }
    ],
    "sg:phone":"+1 631 669 6685",
    "sg:postcode":"11795",
    "sg:province":"NY",
    "sg:tags":[
        "house"
    ],
    "wof:name":"Decks To Dens",
    "wof:placetype":"venue"
},
  "geometry": {"coordinates":[-73.315735,40.688406],"type":"Point"}
}