{
  "type": "Feature",
  "properties": {
    "addr:full":"994 Arthur Kill Rd Staten Island NY 10312",
    "addr:housenumber":"994",
    "addr:postcode":"10312",
    "addr:street":"Arthur Kill Rd",
    "iso:country":"US",
    "sg:address":"994 Arthur Kill Rd",
    "sg:city":"Staten Island",
    "sg:classifiers":[
        {
            "category":"Building & Trades",
            "subcategory":"Construction",
            "type":"Services"
        }
    ],
    "sg:phone":"+1 646 662 8771",
    "sg:postcode":"10312",
    "sg:province":"NY",
    "sg:tags":[
        "concrete",
        "contractor"
    ],
    "wof:name":"A V Masonry",
    "wof:placetype":"venue"
},
  "geometry": {"coordinates":[-74.173728,40.562218],"type":"Point"}
}