{
  "type": "Feature",
  "properties": {
    "iso:country":"US",
    "sg:address":"100 5th Ave",
    "sg:city":"New York",
    "sg:classifiers":[
        {
            "category":"Museum",
            "type":"Entertainment"
        }
    ],
    "sg:phone":"+1 212 535 7710",
    "sg:postcode":"10011",
    "sg:province":"NY",
    "wof:name":"Metropolitan Museum Of Art",
    "wof:placetype":"venue"
},
  "geometry": {"coordinates":[-73.992654,40.73733],"type":"Point"}
}