{
  "type": "Feature",
  "properties": {
    "addr:full":"1000 Fifth Avenue, Manhattan, New York, NY, USA",
    "addr:housenumber":"1000",
    "addr:postcode":"10023",
    "addr:street":"Fifth Avenue",
    "addr:twitter":"https://twitter.com/metmuseum",
    "addr:website":"http://metmuseum.org/",
    "iso:country":"US",
    "sg:classifiers":[
        {
            "category":"Museum",
            "type":"Entertainment"
        }
    ],
    "sg:phone":"+1 212 535 7710",
    "wof:name":"Metropolitan Museum of Art",
    "wof:placetype":"venue"
},
  "geometry": {"coordinates":[-73.96275,40.779258],"type":"Point"}
}