{
  "type": "Feature",
  "properties": {
    "iso:country":"US",
    "sg:address":"1872 81st St",
    "sg:city":"Brooklyn",
    "sg:classifiers":[
        {
            "category":"Communications",
            "type":"Services"
        }
    ],
    "sg:phone":"+1   ",
    "sg:postcode":"11214",
    "sg:province":"NY",
    "sg:tags":[
        "communication"
    ],
    "wof:name":"Vadim Communication Services",
    "wof:placetype":"venue"
},
  "geometry": {"coordinates":[-73.998638,40.60958],"type":"Point"}
}