{
  "type": "Feature",
  "properties": {
    "addr:full":"273 Grand St New York NY 10002",
    "addr:housenumber":"273",
    "addr:postcode":"10002",
    "addr:street":"Grand St",
    "iso:country":"US",
    "sg:address":"273 Grand St",
    "sg:city":"New York",
    "sg:classifiers":[
        {
            "category":"Shopping",
            "subcategory":"Music",
            "type":"Retail Goods"
        }
    ],
    "sg:phone":"+1 212 334 3818",
    "sg:postcode":"10002",
    "sg:province":"NY",
    "sg:tags":[
        "compact",
        "record",
        "disc",
        "tape",
        "dvd's"
    ],
    "wof:name":"Gold Music & Video Store Inc",
    "wof:placetype":"venue"
},
  "geometry": {"coordinates":[-73.99291700000001,40.71766],"type":"Point"}
}