{
  "type": "Feature",
  "properties": {
    "addr:full":"3373 Clinton St Buffalo NY 14224",
    "addr:housenumber":"3373",
    "addr:postcode":"14224",
    "addr:street":"Clinton St",
    "iso:country":"US",
    "sg:address":"3373 Clinton St",
    "sg:city":"Buffalo",
    "sg:classifiers":[
        {
            "category":"Restaurant",
            "type":"Food & Drink"
        }
    ],
    "sg:phone":"+1   ",
    "sg:postcode":"14224",
    "sg:province":"NY",
    "sg:tags":[
        "eating"
    ],
    "wof:name":"Mackies Countryside Inn Inc",
    "wof:placetype":"venue"
},
  "geometry": {"coordinates":[-78.754648,42.855084],"type":"Point"}
}