{
  "type": "Feature",
  "properties": {
    "iso:country":"US",
    "sg:address":"10 S Park Ave",
    "sg:city":"Rockville Centre",
    "sg:classifiers":[
        {
            "category":"Sports & Exercise",
            "subcategory":"Gym",
            "type":"Entertainment"
        }
    ],
    "sg:phone":"+1 516 432 7777",
    "sg:postcode":"11570",
    "sg:province":"NY",
    "sg:tags":[
        "yoga"
    ],
    "sg:website":"www.bikramyogarvc.com/",
    "wof:name":"Bikram Yoga Rockville Centre",
    "wof:placetype":"venue"
},
  "geometry": {"coordinates":[-73.645585,40.655715],"type":"Point"}
}