{
  "type": "Feature",
  "properties": {
    "iso:country":"US",
    "sg:address":"16 W 61 St",
    "sg:city":"New York",
    "sg:classifiers":[
        {
            "category":"Real Estate",
            "subcategory":"Real Estate Agent",
            "type":"Services"
        }
    ],
    "sg:phone":"+1 212 580 4107",
    "sg:postcode":"10023",
    "sg:province":"NY",
    "sg:tags":[
        "company"
    ],
    "wof:name":"Heit Realty Corp",
    "wof:placetype":"venue"
},
  "geometry": {"coordinates":[-73.983801,40.770364],"type":"Point"}
}