{
  "type": "Feature",
  "properties": {
    "addr:full":"666 Dogwood Ave Franklin Square NY 11010",
    "addr:housenumber":"666",
    "addr:postcode":"11010",
    "addr:street":"Dogwood Ave",
    "iso:country":"US",
    "sg:address":"666 Dogwood Ave",
    "sg:city":"Franklin Square",
    "sg:classifiers":[
        {
            "category":"Personal",
            "subcategory":"Barber",
            "type":"Services"
        }
    ],
    "sg:phone":"+1 516 486 9196",
    "sg:postcode":"11010",
    "sg:province":"NY",
    "wof:name":"Estates Barber Shop",
    "wof:placetype":"venue"
},
  "geometry": {"coordinates":[-73.66770200000001,40.6894],"type":"Point"}
}