{
  "type": "Feature",
  "properties": {
    "addr:full":"1821 Scottsville Mumford Rd Scottsville NY 14546",
    "addr:housenumber":"1821",
    "addr:postcode":"scottsville;14546",
    "addr:street":"Scottsville Mumford Rd",
    "iso:country":"US",
    "sg:address":"1821 Scottsville Mumford Rd",
    "sg:city":"Scottsville",
    "sg:classifiers":[
        {
            "category":"Building & Trades",
            "subcategory":"Construction",
            "type":"Services"
        }
    ],
    "sg:phone":"+1 585 538 2328",
    "sg:postcode":"14546",
    "sg:province":"NY",
    "sg:tags":[
        "boring",
        "drilling",
        "contractor"
    ],
    "sg:website":"www.nothnagledrilling.com",
    "wof:name":"Nothnagle Drilling",
    "wof:placetype":"venue"
},
  "geometry": {"coordinates":[-77.819097,43.013345],"type":"Point"}
}