{
  "type": "Feature",
  "properties": {
    "addr:full":"24 6th Ave Brooklyn NY 11217",
    "addr:housenumber":"24",
    "addr:postcode":"11217",
    "addr:street":"6Th Ave",
    "iso:country":"US",
    "sg:address":"24 6th Ave",
    "sg:city":"Brooklyn",
    "sg:classifiers":[
        {
            "category":"Real Estate",
            "subcategory":"Real Estate Agent",
            "type":"Services"
        }
    ],
    "sg:phone":"+1 718 623 3757",
    "sg:postcode":"11217",
    "sg:province":"NY",
    "sg:tags":[
        "management"
    ],
    "wof:name":"Yoshizumi Corp",
    "wof:placetype":"venue"
},
  "geometry": {"coordinates":[-73.974227,40.681505],"type":"Point"}
}