{
  "type": "Feature",
  "properties": {
    "iso:country":"US",
    "sg:address":"161 Delaware Ave",
    "sg:city":"Delmar",
    "sg:classifiers":[
        {
            "category":"Government",
            "subcategory":"Office",
            "type":"Public Place"
        }
    ],
    "sg:phone":"+1 518 478 1022",
    "sg:postcode":"12054",
    "sg:province":"NY",
    "sg:tags":[
        "administrative",
        "program",
        "health"
    ],
    "wof:name":"Division HM & Cmnty Based Care",
    "wof:placetype":"venue"
},
  "geometry": {"coordinates":[-73.81361099999999,42.628884],"type":"Point"}
}