{
  "type": "Feature",
  "properties": {
    "addr:full":"1775 Richmond Ave Staten Island NY 10314",
    "addr:housenumber":"1775",
    "addr:postcode":"10314",
    "addr:street":"Richmond Ave",
    "iso:country":"US",
    "sg:address":"1775 Richmond Ave",
    "sg:city":"Staten Island",
    "sg:classifiers":[
        {
            "category":"Health Services",
            "subcategory":"Doctor",
            "type":"Services"
        }
    ],
    "sg:phone":"+1 718 494 3499",
    "sg:postcode":"10314",
    "sg:province":"NY",
    "wof:name":"Terrani MD PC",
    "wof:placetype":"venue"
},
  "geometry": {"coordinates":[-74.161939,40.605282],"type":"Point"}
}