{
  "type": "Feature",
  "properties": {
    "iso:country":"US",
    "sg:address":"520 Industrial Loop",
    "sg:city":"Staten Island",
    "sg:classifiers":[
        {
            "category":"Home & Garden",
            "subcategory":"Building Materials",
            "type":"Retail Goods"
        }
    ],
    "sg:phone":"+1 718 948 2182",
    "sg:postcode":"10309",
    "sg:province":"NY",
    "sg:tags":[
        "supply"
    ],
    "wof:name":"Dinaso & Sons Bldg Supls",
    "wof:placetype":"venue"
},
  "geometry": {"coordinates":[-74.230301,40.546799],"type":"Point"}
}