{
  "type": "Feature",
  "properties": {
    "addr:full":"3485 E Tremont Avenue Bronx NY 10465",
    "addr:housenumber":"3485",
    "addr:postcode":"10465",
    "addr:street":"E Tremont Avenue",
    "iso:country":"US",
    "sg:address":"3485 E Tremont Avenue",
    "sg:city":"Bronx",
    "sg:classifiers":[
        {
            "category":"Real Estate",
            "subcategory":"Real Estate Services",
            "type":"Services"
        }
    ],
    "sg:phone":"+1 718 822 7377",
    "sg:postcode":"10465",
    "sg:province":"NY",
    "sg:tags":[
        "management",
        "property"
    ],
    "sg:website":"www.prestigemgt.com",
    "wof:name":"Prestige Management",
    "wof:placetype":"venue"
},
  "geometry": {"coordinates":[-73.826735,40.831447],"type":"Point"}
}