{
  "type": "Feature",
  "properties": {
    "iso:country":"US",
    "sg:address":"345 Ridge Rd",
    "sg:city":"Horseheads",
    "sg:classifiers":[
        {
            "category":"Professional",
            "subcategory":"Management & Consulting",
            "type":"Services"
        }
    ],
    "sg:phone":"+1 607 734 5012",
    "sg:postcode":"14845",
    "sg:province":"NY",
    "sg:tags":[
        "consultant"
    ],
    "wof:name":"Air Management Systems",
    "wof:placetype":"venue"
},
  "geometry": {"coordinates":[-76.810919,42.205645],"type":"Point"}
}