{
  "type": "Feature",
  "properties": {
    "iso:country":"US",
    "sg:address":"140 Keyland Ct Unit 14",
    "sg:city":"Bohemia",
    "sg:classifiers":[
        {
            "category":"Building & Trades",
            "subcategory":"Plumbing",
            "type":"Services"
        }
    ],
    "sg:phone":"+1 631 563 8533",
    "sg:postcode":"11716",
    "sg:province":"NY",
    "wof:name":"Mazo Plumbing Inc",
    "wof:placetype":"venue"
},
  "geometry": {"coordinates":[-73.847714,40.776572],"type":"Point"}
}