{
  "type": "Feature",
  "properties": {
    "iso:country":"US",
    "sg:address":"2310 44th Drive",
    "sg:city":"Long Island City",
    "sg:classifiers":[
        {
            "category":"Building & Trades",
            "subcategory":"Construction",
            "type":"Services"
        }
    ],
    "sg:phone":"+1 718 472 3105",
    "sg:postcode":"11101",
    "sg:province":"NY",
    "sg:tags":[
        "contractor"
    ],
    "wof:name":"Turner Construction Field Office",
    "wof:placetype":"venue"
},
  "geometry": {"coordinates":[-73.94408300000001,40.747349],"type":"Point"}
}