{
  "type": "Feature",
  "properties": {
    "addr:full":"250 W 49 St New York NY 10019",
    "addr:housenumber":"250",
    "addr:postcode":"10019",
    "addr:street":"W 49 St",
    "iso:country":"US",
    "sg:address":"250 W 49 St",
    "sg:city":"New York",
    "sg:classifiers":[
        {
            "category":"Professional",
            "subcategory":"Business Services",
            "type":"Services"
        }
    ],
    "sg:phone":"+1 212 586 1972",
    "sg:postcode":"10019",
    "sg:province":"NY",
    "sg:tags":[
        "audio",
        "facility",
        "di",
        "recording",
        "production",
        "video",
        "convention",
        "duplication",
        "meeting"
    ],
    "wof:name":"National Audio Video Inc",
    "wof:placetype":"venue"
},
  "geometry": {"coordinates":[-73.985856,40.761181],"type":"Point"}
}