{
  "type": "Feature",
  "properties": {
    "addr:full":"1 Sullivan St Cazenovia NY 13035",
    "addr:housenumber":"1",
    "addr:postcode":"13035",
    "addr:street":"Sullivan St",
    "iso:country":"US",
    "sg:address":"1 Sullivan St",
    "sg:city":"Cazenovia",
    "sg:classifiers":[
        {
            "category":"Restaurant",
            "type":"Food & Drink"
        }
    ],
    "sg:phone":"+1 315 655 9292",
    "sg:postcode":"13035",
    "sg:province":"NY",
    "wof:name":"Magpies Pizza",
    "wof:placetype":"venue"
},
  "geometry": {"coordinates":[-75.855216,42.93284],"type":"Point"}
}