{
  "type": "Feature",
  "properties": {
    "addr:full":"2 Bellevue Dr Syracuse NY 13212",
    "addr:housenumber":"2",
    "addr:postcode":"13212",
    "addr:street":"Bellevue Dr",
    "iso:country":"US",
    "sg:address":"2 Bellevue Dr",
    "sg:city":"Syracuse",
    "sg:classifiers":[
        {
            "category":"Professional",
            "subcategory":"Business Services",
            "type":"Services"
        }
    ],
    "sg:phone":"+1 315 317 5617",
    "sg:postcode":"13212",
    "sg:province":"NY",
    "sg:tags":[
        "auctioneer"
    ],
    "wof:name":"Hutchturbos",
    "wof:placetype":"venue"
},
  "geometry": {"coordinates":[-76.115674,43.126366],"type":"Point"}
}