{
  "type": "Feature",
  "properties": {
    "addr:full":"99 Blizzard Rd Stillwater NY 12170",
    "addr:housenumber":"99",
    "addr:postcode":"12170",
    "addr:street":"Blizzard Rd",
    "iso:country":"US",
    "sg:address":"99 Blizzard Rd",
    "sg:city":"Stillwater",
    "sg:classifiers":[
        {
            "category":"Wholesale",
            "subcategory":"Vending Machines",
            "type":"Manufacturing & Wholesale Goods"
        }
    ],
    "sg:phone":"+1   ",
    "sg:postcode":"12170",
    "sg:province":"NY",
    "sg:tags":[
        "operates"
    ],
    "wof:name":"Monco Vending Inc",
    "wof:placetype":"venue"
},
  "geometry": {"coordinates":[-73.67847999999999,42.96644],"type":"Point"}
}