{
  "type": "Feature",
  "properties": {
    "addr:full":"630 Mastic Rd Mastic NY 11950",
    "addr:housenumber":"630",
    "addr:postcode":"11950",
    "addr:street":"Mastic Rd",
    "iso:country":"US",
    "sg:address":"630 Mastic Rd",
    "sg:city":"Mastic",
    "sg:classifiers":[
        {
            "category":"Food & Beverages",
            "subcategory":"Groceries & Convenience Stores",
            "type":"Retail Goods"
        }
    ],
    "sg:phone":"+1 631 399 0552",
    "sg:postcode":"11950",
    "sg:province":"NY",
    "wof:name":"Handy Pantry",
    "wof:placetype":"venue"
},
  "geometry": {"coordinates":[-72.849098,40.806099],"type":"Point"}
}