{
  "type": "Feature",
  "properties": {
    "addr:full":"495 Winton Rd N Rochester NY 14610",
    "addr:housenumber":"495",
    "addr:postcode":"14610",
    "addr:street":"Winton Rd N",
    "iso:country":"US",
    "sg:address":"495 Winton Rd N",
    "sg:city":"Rochester",
    "sg:classifiers":[
        {
            "category":"Professional",
            "subcategory":"Advertising",
            "type":"Services"
        }
    ],
    "sg:phone":"+1 585 288 8444",
    "sg:postcode":"14610",
    "sg:province":"NY",
    "sg:tags":[
        "counselor"
    ],
    "wof:name":"CDL Advertising",
    "wof:placetype":"venue"
},
  "geometry": {"coordinates":[-77.549897,43.155197],"type":"Point"}
}