{
  "type": "Feature",
  "properties": {
    "iso:country":"US",
    "sg:address":"232 Townline Rd",
    "sg:city":"Commack",
    "sg:classifiers":[
        {
            "category":"Professional",
            "subcategory":"Business Services",
            "type":"Services"
        }
    ],
    "sg:phone":"+1   ",
    "sg:postcode":"11725",
    "sg:province":"NY",
    "wof:name":"Japaneeds NY Inc",
    "wof:placetype":"venue"
},
  "geometry": {"coordinates":[-73.289709,40.867698],"type":"Point"}
}