{
  "type": "Feature",
  "properties": {
    "addr:full":"65 Spring St Saratoga Springs NY 12866",
    "addr:housenumber":"65",
    "addr:postcode":"12866",
    "addr:street":"Spring St",
    "iso:country":"US",
    "sg:address":"65 Spring St",
    "sg:city":"Saratoga Springs",
    "sg:classifiers":[
        {
            "category":"Food & Beverages",
            "subcategory":"Bakery",
            "type":"Retail Goods"
        }
    ],
    "sg:phone":"+1   ",
    "sg:postcode":"12866",
    "sg:province":"NY",
    "wof:name":"Breadbasket",
    "wof:placetype":"venue"
},
  "geometry": {"coordinates":[-73.78206900000001,43.079311],"type":"Point"}
}