{
  "type": "Feature",
  "properties": {
    "addr:full":"113 Pennsylvania Ave Hempstead NY 11550",
    "addr:housenumber":"113",
    "addr:postcode":"11550",
    "addr:street":"Pennsylvania Ave",
    "iso:country":"US",
    "sg:address":"113 Pennsylvania Ave",
    "sg:city":"Hempstead",
    "sg:classifiers":[
        {
            "category":"Shopping",
            "subcategory":"Gifts & Souvenirs",
            "type":"Retail Goods"
        }
    ],
    "sg:phone":"+1   ",
    "sg:postcode":"11550",
    "sg:province":"NY",
    "wof:name":"Aj Gifts",
    "wof:placetype":"venue"
},
  "geometry": {"coordinates":[-73.611932,40.71267],"type":"Point"}
}