{
  "type": "Feature",
  "properties": {
    "addr:full":"1277 County Route 85 Hannibal NY 13074",
    "addr:housenumber":"1277",
    "addr:postcode":"13074",
    "addr:street":"County Route 85",
    "iso:country":"US",
    "sg:address":"1277 County Route 85",
    "sg:city":"Hannibal",
    "sg:classifiers":[
        {
            "category":"Manufacturing",
            "subcategory":"Food",
            "type":"Manufacturing & Wholesale Goods"
        },
        {
            "category":"Farming",
            "subcategory":"Farm",
            "type":"Manufacturing & Wholesale Goods"
        }
    ],
    "sg:phone":"+1 315 564 6446",
    "sg:postcode":"13074",
    "sg:province":"NY",
    "sg:tags":[
        "corn",
        "product"
    ],
    "wof:name":"William H Fowler",
    "wof:placetype":"venue"
},
  "geometry": {"coordinates":[-76.55772899999999,43.353447],"type":"Point"}
}