{
  "type": "Feature",
  "properties": {
    "iso:country":"US",
    "sg:address":"136 N 1st St",
    "sg:city":"Dryden",
    "sg:classifiers":[
        {
            "category":"Retail",
            "subcategory":"Veterinary Services",
            "type":"Services"
        }
    ],
    "sg:phone":"+1 607 844 9188",
    "sg:postcode":"13069",
    "sg:province":"NY",
    "sg:tags":[
        "hospital",
        "animal"
    ],
    "wof:name":"Countryside Veterinary Hosp",
    "wof:placetype":"venue"
},
  "geometry": {"coordinates":[-76.418527,43.330787],"type":"Point"}
}