{
  "type": "Feature",
  "properties": {
    "iso:country":"US",
    "sg:address":"161 Spring Tree Ln",
    "sg:city":"Rochester",
    "sg:classifiers":[
        {
            "category":"Building & Trades",
            "subcategory":"Electrical",
            "type":"Services"
        }
    ],
    "sg:phone":"+1 585 227 2547",
    "sg:postcode":"14612",
    "sg:province":"NY",
    "sg:tags":[
        "electrical",
        "contractor"
    ],
    "wof:name":"Jerry Schneider Electric",
    "wof:placetype":"venue"
},
  "geometry": {"coordinates":[-77.722544,43.251112],"type":"Point"}
}