{
  "type": "Feature",
  "properties": {
    "iso:country":"US",
    "sg:address":"4223 State Highway 30",
    "sg:city":"Amsterdam",
    "sg:classifiers":[
        {
            "category":"Autos & Motor Vehicles",
            "subcategory":"Automobile Sales",
            "type":"Retail Goods"
        },
        {
            "category":"Retail",
            "subcategory":"Auto Repair",
            "type":"Services"
        }
    ],
    "sg:phone":"+1 518 843 5103",
    "sg:postcode":"12010",
    "sg:province":"NY",
    "sg:tags":[
        "body",
        "car",
        "new",
        "painting",
        "repairing"
    ],
    "wof:name":"Creative Auto Body",
    "wof:placetype":"venue"
},
  "geometry": {"coordinates":[-74.19277,43.015638],"type":"Point"}
}