{
  "type": "Feature",
  "properties": {
    "addr:full":"1742 Union St Schenectady NY 12309",
    "addr:housenumber":"1742",
    "addr:postcode":"12309",
    "addr:street":"Union St",
    "iso:country":"US",
    "sg:address":"1742 Union St",
    "sg:city":"Schenectady",
    "sg:classifiers":[
        {
            "category":"Banks & Credit Unions",
            "subcategory":"Bank",
            "type":"Services"
        }
    ],
    "sg:phone":"+1 518 631 0478",
    "sg:postcode":"12309",
    "sg:province":"NY",
    "sg:tags":[
        "commercial",
        "saving"
    ],
    "wof:name":"Hudson River Bank",
    "wof:placetype":"venue"
},
  "geometry": {"coordinates":[-73.90072600000001,42.803211],"type":"Point"}
}