{
  "type": "Feature",
  "properties": {
    "iso:country":"US",
    "sg:address":"126 13th St",
    "sg:city":"Brooklyn",
    "sg:classifiers":[
        {
            "category":"Arts & Performance",
            "subcategory":"Arts Center",
            "type":"Entertainment"
        }
    ],
    "sg:phone":"+1 718 832 5610",
    "sg:postcode":"11215",
    "sg:province":"NY",
    "sg:tags":[
        "performing"
    ],
    "wof:name":"Brooklyn's Finest Salsa Dance Studio",
    "wof:placetype":"venue"
},
  "geometry": {"coordinates":[-73.994102,40.669498],"type":"Point"}
}