{
  "type": "Feature",
  "properties": {
    "iso:country":"US",
    "sg:address":"1163 E State St",
    "sg:city":"Olean",
    "sg:classifiers":[
        {
            "category":"Building & Trades",
            "subcategory":"Pest Control",
            "type":"Services"
        }
    ],
    "sg:phone":"+1 716 372 1957",
    "sg:postcode":"14760",
    "sg:province":"NY",
    "wof:name":"Accurate Pest Control Inc",
    "wof:placetype":"venue"
},
  "geometry": {"coordinates":[-78.40705699999999,42.074032],"type":"Point"}
}