{
  "type": "Feature",
  "properties": {
    "iso:country":"US",
    "sg:address":"568 Union Street",
    "sg:city":"Brooklyn",
    "sg:classifiers":[
        {
            "category":"Education",
            "subcategory":"Music School",
            "type":"Public Place"
        }
    ],
    "sg:phone":"+1 718 875 4638",
    "sg:postcode":"11215",
    "sg:province":"NY",
    "sg:tags":[
        "instrument",
        "teacher",
        "musical"
    ],
    "wof:name":"Keur Djembe",
    "wof:placetype":"venue"
},
  "geometry": {"coordinates":[-73.98537399999999,40.678261],"type":"Point"}
}