{
  "type": "Feature",
  "properties": {
    "iso:country":"US",
    "sg:address":"1115 Broadway",
    "sg:city":"New York",
    "sg:classifiers":[
        {
            "category":"Retail",
            "subcategory":"Repair Shop",
            "type":"Services"
        }
    ],
    "sg:phone":"+1 917 558 9585",
    "sg:postcode":"10010",
    "sg:province":"NY",
    "sg:tags":[
        "lock",
        "locksmith"
    ],
    "wof:name":"EMERGENCY Locksmith",
    "wof:placetype":"venue"
},
  "geometry": {"coordinates":[-73.989279,40.742376],"type":"Point"}
}