{
  "type": "Feature",
  "properties": {
    "iso:country":"US",
    "sg:address":"253 Applegate Rd N",
    "sg:city":"Ithaca",
    "sg:classifiers":[
        {
            "category":"Communications",
            "subcategory":"Film & Video Production",
            "type":"Services"
        }
    ],
    "sg:phone":"+1 607 256 4106",
    "sg:postcode":"14850",
    "sg:province":"NY",
    "sg:tags":[
        "taping"
    ],
    "sg:website":"www.jorgevisions.com",
    "wof:name":"Jorge Visions Video & DJ",
    "wof:placetype":"venue"
},
  "geometry": {"coordinates":[-76.612363,42.469613],"type":"Point"}
}