{
  "type": "Feature",
  "properties": {
    "addr:full":"17 State St New York NY 10004",
    "addr:housenumber":"17",
    "addr:postcode":"10004",
    "addr:street":"State St",
    "iso:country":"US",
    "sg:address":"17 State St",
    "sg:city":"New York",
    "sg:classifiers":[
        {
            "category":"Professional",
            "subcategory":"Lawyer & Legal Services",
            "type":"Services"
        }
    ],
    "sg:phone":"+1 646 695 2000",
    "sg:postcode":"10004",
    "sg:province":"NY",
    "sg:website":"www.managedobjects.com",
    "wof:name":"Managed Objects",
    "wof:placetype":"venue"
},
  "geometry": {"coordinates":[-74.014397,40.703098],"type":"Point"}
}