{
  "type": "Feature",
  "properties": {
    "addr:full":"1285 Beach Avenue Bronx NY 10472",
    "addr:housenumber":"1285",
    "addr:postcode":"10472",
    "addr:street":"Beach Avenue",
    "iso:country":"US",
    "sg:address":"1285 Beach Avenue",
    "sg:city":"Bronx",
    "sg:classifiers":[
        {
            "category":"Personal",
            "type":"Services"
        }
    ],
    "sg:phone":"+1 800 924 1777",
    "sg:postcode":"10472",
    "sg:province":"NY",
    "sg:tags":[
        "mover"
    ],
    "wof:name":"Cavaluzzi & Sons",
    "wof:placetype":"venue"
},
  "geometry": {"coordinates":[-73.86666200000001,40.832759],"type":"Point"}
}