{
  "type": "Feature",
  "properties": {
    "addr:full":"441 Center St Lewiston NY 14092",
    "addr:housenumber":"441",
    "addr:postcode":"14092",
    "addr:street":"Center St",
    "iso:country":"US",
    "sg:address":"441 Center St",
    "sg:city":"Lewiston",
    "sg:classifiers":[
        {
            "category":"Personal",
            "subcategory":"Beauty Salon",
            "type":"Services"
        }
    ],
    "sg:phone":"+1 716 754 8555",
    "sg:postcode":"14092",
    "sg:province":"NY",
    "wof:name":"Francesco's Hair Fashion",
    "wof:placetype":"venue"
},
  "geometry": {"coordinates":[-79.043572,43.172811],"type":"Point"}
}