{
  "type": "Feature",
  "properties": {
    "addr:full":"5 Wilputte Pl New Rochelle NY 10804",
    "addr:housenumber":"5",
    "addr:postcode":"10804",
    "addr:street":"Wilputte Pl",
    "iso:country":"US",
    "sg:address":"5 Wilputte Pl",
    "sg:city":"New Rochelle",
    "sg:classifiers":[
        {
            "category":"Professional",
            "subcategory":"Lawyer & Legal Services",
            "type":"Services"
        }
    ],
    "sg:phone":"+1   ",
    "sg:postcode":"10804",
    "sg:province":"NY",
    "wof:name":"Frank P Mangiatordi",
    "wof:placetype":"venue"
},
  "geometry": {"coordinates":[-73.78782099999999,40.966451],"type":"Point"}
}