{
  "type": "Feature",
  "properties": {
    "addr:full":"415 Babcock St Buffalo NY 14206",
    "addr:housenumber":"415",
    "addr:postcode":"14206",
    "addr:street":"Babcock St",
    "iso:country":"US",
    "sg:address":"415 Babcock St",
    "sg:city":"Buffalo",
    "sg:classifiers":[
        {
            "category":"Freight",
            "type":"Transportation"
        }
    ],
    "sg:phone":"+1 716 823 9562",
    "sg:postcode":"14206",
    "sg:province":"NY",
    "sg:tags":[
        "trucking"
    ],
    "wof:name":"Nova Cor LTD",
    "wof:placetype":"venue"
},
  "geometry": {"coordinates":[-78.830761,42.875196],"type":"Point"}
}