{
  "type": "Feature",
  "properties": {
    "addr:full":"104 Mc Kinley Pl Bellmore NY 11710",
    "addr:housenumber":"104",
    "addr:postcode":"11710",
    "addr:street":"Mc Kinley Pl",
    "iso:country":"US",
    "sg:address":"104 Mc Kinley Pl",
    "sg:city":"Bellmore",
    "sg:classifiers":[
        {
            "category":"Wholesale",
            "subcategory":"Electrical",
            "type":"Manufacturing & Wholesale Goods"
        }
    ],
    "sg:phone":"+1 516 826 9865",
    "sg:postcode":"11710",
    "sg:province":"NY",
    "sg:tags":[
        "equipment"
    ],
    "wof:name":"Palladium Protection Inc",
    "wof:placetype":"venue"
},
  "geometry": {"coordinates":[-73.535804,40.685739],"type":"Point"}
}