{
  "type": "Feature",
  "properties": {
    "addr:full":"12307 Liberty Ave South Richmond Hill NY 11419",
    "addr:housenumber":"12307",
    "addr:postcode":"11419",
    "addr:street":"Liberty Ave South",
    "iso:country":"US",
    "sg:address":"12307 Liberty Ave",
    "sg:city":"South Richmond Hill",
    "sg:classifiers":[
        {
            "category":"Bars & Pubs",
            "subcategory":"Nightclub",
            "type":"Food & Drink"
        }
    ],
    "sg:phone":"+1 718 322 3000",
    "sg:postcode":"11419",
    "sg:province":"NY",
    "sg:tags":[
        "nightlife"
    ],
    "wof:name":"Level Ultra Lounge",
    "wof:placetype":"venue"
},
  "geometry": {"coordinates":[-73.820953,40.68764],"type":"Point"}
}