{
  "type": "Feature",
  "properties": {
    "addr:full":"118 S Country Rd Bellport NY 11713",
    "addr:housenumber":"118",
    "addr:postcode":"11713",
    "addr:street":"S Country Rd",
    "iso:country":"US",
    "sg:address":"118 S Country Rd",
    "sg:city":"Bellport",
    "sg:classifiers":[
        {
            "category":"Food & Beverages",
            "subcategory":"Specialty",
            "type":"Retail Goods"
        }
    ],
    "sg:phone":"+1 631 286 9774",
    "sg:postcode":"11713",
    "sg:province":"NY",
    "sg:tags":[
        "health",
        "diet"
    ],
    "wof:name":"It's Only Natural",
    "wof:placetype":"venue"
},
  "geometry": {"coordinates":[-72.940648,40.756312],"type":"Point"}
}