{
  "type": "Feature",
  "properties": {
    "iso:country":"US",
    "sg:address":"49 Jackson Ave",
    "sg:city":"Syosset",
    "sg:classifiers":[
        {
            "category":"Personal",
            "subcategory":"Shoe Repair & Shine",
            "type":"Services"
        }
    ],
    "sg:phone":"+1 516 496 0683",
    "sg:postcode":"11791",
    "sg:province":"NY",
    "sg:tags":[
        "repairing",
        "boot"
    ],
    "wof:name":"Sandy's Shoe Repair",
    "wof:placetype":"venue"
},
  "geometry": {"coordinates":[-73.50200599999999,40.825006],"type":"Point"}
}