{
  "type": "Feature",
  "properties": {
    "iso:country":"US",
    "sg:address":"181 53rd St",
    "sg:city":"Brooklyn",
    "sg:classifiers":[
        {
            "category":"Wholesale",
            "subcategory":"Groceries",
            "type":"Manufacturing & Wholesale Goods"
        }
    ],
    "sg:phone":"+1 718 492 9820",
    "sg:postcode":"11232",
    "sg:province":"NY",
    "sg:tags":[
        "import",
        "export"
    ],
    "wof:name":"Lupa Import & Export Inc",
    "wof:placetype":"venue"
},
  "geometry": {"coordinates":[-74.019465,40.647714],"type":"Point"}
}