{
  "type": "Feature",
  "properties": {
    "addr:full":"349 W 48th Street New York NY 10036",
    "addr:housenumber":"349",
    "addr:postcode":"10036",
    "addr:street":"W 48Th Street",
    "iso:country":"US",
    "sg:address":"349 W 48th Street",
    "sg:city":"New York",
    "sg:classifiers":[
        {
            "category":"Organizations",
            "subcategory":"Religious Organization",
            "type":"Services"
        }
    ],
    "sg:phone":"+1 212 581 3772",
    "sg:postcode":"10036",
    "sg:province":"NY",
    "wof:name":"Fssc Eastern US",
    "wof:placetype":"venue"
},
  "geometry": {"coordinates":[-73.988243,40.761539],"type":"Point"}
}