{
  "type": "Feature",
  "properties": {
    "iso:country":"US",
    "sg:address":"1031 Rte 112",
    "sg:city":"Port Jefferson Station",
    "sg:classifiers":[
        {
            "category":"Restaurant",
            "type":"Food & Drink"
        }
    ],
    "sg:phone":"+1   ",
    "sg:postcode":"11776",
    "sg:province":"NY",
    "sg:tags":[
        "eating"
    ],
    "wof:name":"Bagel Brothers Cafe",
    "wof:placetype":"venue"
},
  "geometry": {"coordinates":[-73.046088,40.923815],"type":"Point"}
}