{
  "type": "Feature",
  "properties": {
    "iso:country":"US",
    "sg:address":"1900 Pine Neck Rd",
    "sg:city":"Southold",
    "sg:classifiers":[
        {
            "category":"Personal",
            "type":"Services"
        }
    ],
    "sg:phone":"+1 631 765 0033",
    "sg:postcode":"11971",
    "sg:province":"NY",
    "sg:tags":[
        "therapist",
        "massage"
    ],
    "wof:name":"Alyce M Giorgi Massage Therapy",
    "wof:placetype":"venue"
},
  "geometry": {"coordinates":[-72.42595300000001,41.053886],"type":"Point"}
}