{
  "type": "Feature",
  "properties": {
    "iso:country":"US",
    "sg:address":"2700 Central Ave",
    "sg:city":"Baldwin",
    "sg:classifiers":[
        {
            "category":"Building & Trades",
            "subcategory":"Construction",
            "type":"Services"
        }
    ],
    "sg:phone":"+1 516 623 8474",
    "sg:postcode":"11510",
    "sg:province":"NY",
    "sg:tags":[
        "heavy"
    ],
    "wof:name":"Natures Way Gardens",
    "wof:placetype":"venue"
},
  "geometry": {"coordinates":[-73.60737,40.645202],"type":"Point"}
}