{
  "type": "Feature",
  "properties": {
    "addr:full":"20 Queens St Syosset NY 11791",
    "addr:housenumber":"20",
    "addr:postcode":"11791",
    "addr:street":"Queens St",
    "iso:country":"US",
    "sg:address":"20 Queens St",
    "sg:city":"Syosset",
    "sg:classifiers":[
        {
            "category":"Organizations",
            "subcategory":"Community Association",
            "type":"Services"
        }
    ],
    "sg:phone":"+1 516 921 7956",
    "sg:postcode":"11791",
    "sg:province":"NY",
    "sg:tags":[
        "military"
    ],
    "sg:website":"www.vfw.org",
    "wof:name":"Veterans Of Foreign Wars",
    "wof:placetype":"venue"
},
  "geometry": {"coordinates":[-73.503823,40.82432],"type":"Point"}
}