{
  "type": "Feature",
  "properties": {
    "addr:full":"408 Third Avenue Brooklyn NY 11215",
    "addr:housenumber":"408",
    "addr:postcode":"11215",
    "addr:street":"Third Avenue",
    "iso:country":"US",
    "sg:address":"408 Third Avenue",
    "sg:city":"Brooklyn",
    "sg:classifiers":[
        {
            "category":"Arena",
            "subcategory":"Sports Club",
            "type":"Entertainment"
        }
    ],
    "sg:phone":"+1 718 643 6044",
    "sg:postcode":"11215",
    "sg:province":"NY",
    "sg:tags":[
        "martial art",
        "instruction"
    ],
    "sg:website":"www.brooklynaikikai.com",
    "wof:name":"Brooklyn Aikikai",
    "wof:placetype":"venue"
},
  "geometry": {"coordinates":[-73.989885,40.673268],"type":"Point"}
}