{
  "type": "Feature",
  "properties": {
    "iso:country":"US",
    "sg:address":"895 Walton Ave",
    "sg:city":"Bronx",
    "sg:classifiers":[
        {
            "category":"Personal",
            "subcategory":"Beauty Salon",
            "type":"Services"
        }
    ],
    "sg:phone":"+1 718 293 0200",
    "sg:postcode":"10452",
    "sg:province":"NY",
    "wof:name":"Dori's Nail Salon",
    "wof:placetype":"venue"
},
  "geometry": {"coordinates":[-73.92254800000001,40.82993],"type":"Point"}
}