{
  "type": "Feature",
  "properties": {
    "addr:full":"2 Split Rock Rd Chester NY 10918",
    "addr:housenumber":"2",
    "addr:postcode":"10918",
    "addr:street":"Split Rock Rd",
    "iso:country":"US",
    "sg:address":"2 Split Rock Rd",
    "sg:city":"Chester",
    "sg:classifiers":[
        {
            "category":"Insurance",
            "subcategory":"Insurance Agent",
            "type":"Services"
        }
    ],
    "sg:phone":"+1 845 469 6092",
    "sg:postcode":"10918",
    "sg:province":"NY",
    "wof:name":"Seely Durland Inc",
    "wof:placetype":"venue"
},
  "geometry": {"coordinates":[-74.30855,41.316047],"type":"Point"}
}