{
  "type": "Feature",
  "properties": {
    "addr:full":"16 W 46 St New York NY 10036",
    "addr:housenumber":"16",
    "addr:postcode":"10036",
    "addr:street":"W 46 St",
    "iso:country":"US",
    "sg:address":"16 W 46 St",
    "sg:city":"New York",
    "sg:classifiers":[
        {
            "category":"Banks & Credit Unions",
            "subcategory":"Bank",
            "type":"Services"
        }
    ],
    "sg:phone":"+1 212 764 4646",
    "sg:postcode":"10036",
    "sg:province":"NY",
    "sg:tags":[
        "funds",
        "electronic",
        "transfer"
    ],
    "wof:name":"Trans-Fast Remittance Inc",
    "wof:placetype":"venue"
},
  "geometry": {"coordinates":[-73.981934,40.757124],"type":"Point"}
}