{
  "type": "Feature",
  "properties": {
    "addr:full":"26 Candlelight Cir Liverpool NY 13090",
    "addr:housenumber":"26",
    "addr:postcode":"13090",
    "addr:street":"Candlelight Cir",
    "iso:country":"US",
    "sg:address":"26 Candlelight Cir",
    "sg:city":"Liverpool",
    "sg:classifiers":[
        {
            "category":"Freight",
            "type":"Transportation"
        }
    ],
    "sg:phone":"+1 315 243 5300",
    "sg:postcode":"13090",
    "sg:province":"NY",
    "wof:name":"Excellent Transportation",
    "wof:placetype":"venue"
},
  "geometry": {"coordinates":[-76.21358499999999,43.129588],"type":"Point"}
}