{
  "type": "Feature",
  "properties": {
    "addr:full":"88 Abeel Ave Greenwich NY 12834",
    "addr:housenumber":"88",
    "addr:postcode":"12834",
    "addr:street":"Abeel Ave",
    "iso:country":"US",
    "sg:address":"88 Abeel Ave",
    "sg:city":"Greenwich",
    "sg:classifiers":[
        {
            "category":"Retail",
            "subcategory":"Auto Repair",
            "type":"Services"
        }
    ],
    "sg:phone":"+1 518 692 8535",
    "sg:postcode":"12834",
    "sg:province":"NY",
    "sg:tags":[
        "repairing",
        "automobile"
    ],
    "wof:name":"Warren Tire Svc Inc",
    "wof:placetype":"venue"
},
  "geometry": {"coordinates":[-73.508173,43.092532],"type":"Point"}
}