{
  "type": "Feature",
  "properties": {
    "addr:full":"1085 Northern Blvd Roslyn NY 11576",
    "addr:housenumber":"1085",
    "addr:postcode":"11576",
    "addr:street":"Northern Blvd",
    "iso:country":"US",
    "sg:address":"1085 Northern Blvd",
    "sg:city":"Roslyn",
    "sg:classifiers":[
        {
            "category":"Home & Garden",
            "subcategory":"Home Furnishings",
            "type":"Retail Goods"
        },
        {
            "category":"Home & Garden",
            "subcategory":"Furniture",
            "type":"Retail Goods"
        }
    ],
    "sg:phone":"+1 516 365 3158",
    "sg:postcode":"11576",
    "sg:province":"NY",
    "sg:tags":[
        "decor",
        "store"
    ],
    "sg:website":"www.dwr.com",
    "wof:name":"Design Within Reach",
    "wof:placetype":"venue"
},
  "geometry": {"coordinates":[-73.661181,40.799256],"type":"Point"}
}