{
  "type": "Feature",
  "properties": {
    "addr:full":"304 8th Ave New York NY 10001",
    "addr:housenumber":"304",
    "addr:postcode":"10001",
    "addr:street":"8Th Ave",
    "iso:country":"US",
    "sg:address":"304 8th Ave",
    "sg:city":"New York",
    "sg:classifiers":[
        {
            "category":"Building & Trades",
            "subcategory":"Locksmith",
            "type":"Services"
        }
    ],
    "sg:phone":"+1 212 903 0690",
    "sg:postcode":"10001",
    "sg:province":"NY",
    "sg:tags":[
        "key"
    ],
    "wof:name":"24 Hour A Day Locksmith",
    "wof:placetype":"venue"
},
  "geometry": {"coordinates":[-73.997597,40.7467],"type":"Point"}
}