{
  "type": "Feature",
  "properties": {
    "iso:country":"US",
    "sg:address":"57 Walker St",
    "sg:city":"New York",
    "sg:classifiers":[
        {
            "category":"Professional",
            "subcategory":"Art Services",
            "type":"Services"
        }
    ],
    "sg:phone":"+1 212 965 5007",
    "sg:postcode":"10013",
    "sg:province":"NY",
    "sg:tags":[
        "arts",
        "graphic",
        "design"
    ],
    "wof:name":"LI Design Inc",
    "wof:placetype":"venue"
},
  "geometry": {"coordinates":[-74.00355,40.719151],"type":"Point"}
}