{
  "type": "Feature",
  "properties": {
    "addr:full":"303 Main St. Beacon NY 12508",
    "addr:housenumber":"303",
    "addr:postcode":"12508",
    "addr:street":"Main St.",
    "iso:country":"US",
    "sg:address":"303 Main St.",
    "sg:city":"Beacon",
    "sg:classifiers":[
        {
            "category":"Restaurant",
            "type":"Food & Drink"
        }
    ],
    "sg:phone":"+1 845 765 2540",
    "sg:postcode":"12508",
    "sg:province":"NY",
    "sg:tags":[
        "american",
        "latin"
    ],
    "wof:name":"Dona Julia's",
    "wof:placetype":"venue"
},
  "geometry": {"coordinates":[-73.971131,41.505682],"type":"Point"}
}