{
  "type": "Feature",
  "properties": {
    "addr:full":"484 Broadway New York NY 10013",
    "addr:housenumber":"484",
    "addr:postcode":"10013",
    "addr:street":"Broadway",
    "iso:country":"US",
    "sg:address":"484 Broadway",
    "sg:city":"New York",
    "sg:classifiers":[
        {
            "category":"Shopping",
            "subcategory":"Clothing, Apparel, & Fashions",
            "type":"Retail Goods"
        },
        {
            "category":"Restaurant",
            "type":"Food & Drink"
        }
    ],
    "sg:phone":"+1 212 343 0020",
    "sg:postcode":"10013",
    "sg:province":"NY",
    "sg:tags":[
        "clothing",
        "women's"
    ],
    "wof:name":"Olarte-Foussard Emee",
    "wof:placetype":"venue"
},
  "geometry": {"coordinates":[-74.000006,40.721607],"type":"Point"}
}