{
  "type": "Feature",
  "properties": {
    "iso:country":"US",
    "sg:address":"2851 McCann Rd",
    "sg:city":"Canandaigua",
    "sg:classifiers":[
        {
            "category":"Building & Trades",
            "subcategory":"Construction",
            "type":"Services"
        }
    ],
    "sg:phone":"+1 585 394 4761",
    "sg:postcode":"14424",
    "sg:province":"NY",
    "sg:tags":[
        "water",
        "well",
        "drilling",
        "contractor"
    ],
    "wof:name":"C G Jensen",
    "wof:placetype":"venue"
},
  "geometry": {"coordinates":[-77.359354,42.885023],"type":"Point"}
}