{
  "type": "Feature",
  "properties": {
    "addr:full":"49 Walker Ave Sag Harbor NY 11963",
    "addr:housenumber":"49",
    "addr:postcode":"11963",
    "addr:street":"Walker Ave",
    "iso:country":"US",
    "sg:address":"49 Walker Ave",
    "sg:city":"Sag Harbor",
    "sg:classifiers":[
        {
            "category":"Professional",
            "type":"Services"
        }
    ],
    "sg:phone":"+1 631 725 1974",
    "sg:postcode":"11963",
    "sg:province":"NY",
    "sg:tags":[
        "establishment"
    ],
    "wof:name":"Gay & Hardaway",
    "wof:placetype":"venue"
},
  "geometry": {"coordinates":[-72.276563,40.997727],"type":"Point"}
}