{
  "type": "Feature",
  "properties": {
    "iso:country":"US",
    "sg:address":"590 Tuckahoe Rd",
    "sg:city":"Yonkers",
    "sg:classifiers":[
        {
            "category":"Home & Garden",
            "subcategory":"Hardware",
            "type":"Retail Goods"
        }
    ],
    "sg:phone":"+1   ",
    "sg:postcode":"10710",
    "sg:province":"NY",
    "sg:tags":[
        "store"
    ],
    "wof:name":"Grassy Sprain Paint & Hardware",
    "wof:placetype":"venue"
},
  "geometry": {"coordinates":[-73.84593,40.953617],"type":"Point"}
}