{
  "type": "Feature",
  "properties": {
    "addr:full":"6165 Jericho Tpke Commack NY 11725",
    "addr:housenumber":"6165",
    "addr:postcode":"11725",
    "addr:street":"Jericho Tpke",
    "iso:country":"US",
    "sg:address":"6165 Jericho Tpke",
    "sg:city":"Commack",
    "sg:classifiers":[
        {
            "category":"Professional",
            "subcategory":"Lawyer & Legal Services",
            "type":"Services"
        }
    ],
    "sg:phone":"+1 631 543 8305",
    "sg:postcode":"11725",
    "sg:province":"NY",
    "wof:name":"Breslow Allen",
    "wof:placetype":"venue"
},
  "geometry": {"coordinates":[-73.301315,40.842303],"type":"Point"}
}