{
  "type": "Feature",
  "properties": {
    "addr:full":"20 Glen St Alfred NY 14802",
    "addr:housenumber":"20",
    "addr:postcode":"14802",
    "addr:street":"Glen St Alfred",
    "iso:country":"US",
    "sg:address":"20 Glen St",
    "sg:city":"Alfred",
    "sg:classifiers":[
        {
            "category":"Banks & Credit Unions",
            "subcategory":"Financial Services",
            "type":"Services"
        }
    ],
    "sg:phone":"+1 607 587 8701",
    "sg:postcode":"14802",
    "sg:province":"NY",
    "sg:tags":[
        "investor"
    ],
    "wof:name":"Fraser",
    "wof:placetype":"venue"
},
  "geometry": {"coordinates":[-77.786965,42.26215],"type":"Point"}
}