{
  "type": "Feature",
  "properties": {
    "addr:full":"555 W 42nd Street New York NY 10036",
    "addr:housenumber":"555",
    "addr:postcode":"10036",
    "addr:street":"W 42Nd Street",
    "iso:country":"US",
    "sg:address":"555 W 42nd Street",
    "sg:city":"New York",
    "sg:classifiers":[
        {
            "category":"Real Estate",
            "subcategory":"Real Estate Services",
            "type":"Services"
        }
    ],
    "sg:phone":"+1 212 564 4200",
    "sg:postcode":"10036",
    "sg:province":"NY",
    "sg:tags":[
        "management",
        "property"
    ],
    "wof:name":"Manhattan Pacific Management Company",
    "wof:placetype":"venue"
},
  "geometry": {"coordinates":[-73.98253699999999,40.754293],"type":"Point"}
}