{
  "type": "Feature",
  "properties": {
    "iso:country":"US",
    "sg:address":"1988 Amsterdam Avenue",
    "sg:city":"New York",
    "sg:classifiers":[
        {
            "category":"Home & Garden",
            "subcategory":"Hardware",
            "type":"Retail Goods"
        },
        {
            "category":"Building & Trades",
            "subcategory":"Locksmith",
            "type":"Services"
        }
    ],
    "sg:phone":"+1 212 928 4234",
    "sg:postcode":"10032",
    "sg:province":"NY",
    "sg:tags":[
        "store",
        "key"
    ],
    "wof:name":"Center Locksmith",
    "wof:placetype":"venue"
},
  "geometry": {"coordinates":[-73.941362,40.83377],"type":"Point"}
}