{
  "type": "Feature",
  "properties": {
    "iso:country":"US",
    "sg:address":"65 Whippoorwill Rd",
    "sg:city":"Hillsdale",
    "sg:classifiers":[
        {
            "category":"Farming",
            "subcategory":"Farm",
            "type":"Manufacturing & Wholesale Goods"
        }
    ],
    "sg:phone":"+1 518 325 3384",
    "sg:postcode":"12529",
    "sg:province":"NY",
    "wof:name":"White Oak Farm",
    "wof:placetype":"venue"
},
  "geometry": {"coordinates":[-73.518372,42.19294],"type":"Point"}
}