{
  "type": "Feature",
  "properties": {
    "addr:full":"220 W 93 St New York NY 10025",
    "addr:housenumber":"220",
    "addr:postcode":"10025",
    "addr:street":"W 93 St",
    "iso:country":"US",
    "sg:address":"220 W 93 St",
    "sg:city":"New York",
    "sg:classifiers":[
        {
            "category":"Retail",
            "subcategory":"Repair Shop",
            "type":"Services"
        }
    ],
    "sg:phone":"+1 646 224 0937",
    "sg:postcode":"10025",
    "sg:province":"NY",
    "sg:tags":[
        "lock",
        "locksmith"
    ],
    "wof:name":"Number 1 Emergency Locksmith",
    "wof:placetype":"venue"
},
  "geometry": {"coordinates":[-73.972782,40.79241],"type":"Point"}
}