{
  "type": "Feature",
  "properties": {
    "iso:country":"US",
    "sg:address":"478 W 1st St",
    "sg:city":"Oswego",
    "sg:classifiers":[
        {
            "category":"Organizations",
            "subcategory":"Non-profit Organization",
            "type":"Services"
        }
    ],
    "sg:phone":"+1 315 343 2003",
    "sg:postcode":"13126",
    "sg:province":"NY",
    "wof:name":"Hillside Children's Ctr",
    "wof:placetype":"venue"
},
  "geometry": {"coordinates":[-76.502132,43.445892],"type":"Point"}
}