{
  "type": "Feature",
  "properties": {
    "addr:full":"570 Pine Aire Dr Bay Shore NY 11706",
    "addr:housenumber":"570",
    "addr:postcode":"11706",
    "addr:street":"Pine Aire Dr",
    "iso:country":"US",
    "sg:address":"570 Pine Aire Dr",
    "sg:city":"Bay Shore",
    "sg:classifiers":[
        {
            "category":"Shopping",
            "subcategory":"Catalog Store",
            "type":"Retail Goods"
        }
    ],
    "sg:phone":"+1 631 254 0021",
    "sg:postcode":"11706",
    "sg:province":"NY",
    "sg:tags":[
        "internet"
    ],
    "wof:name":"Tri-State Car Wholesalers",
    "wof:placetype":"venue"
},
  "geometry": {"coordinates":[-73.28381400000001,40.771166],"type":"Point"}
}