{
  "type": "Feature",
  "properties": {
    "addr:full":"207 Merrymount St Staten Island NY 10314",
    "addr:housenumber":"207",
    "addr:postcode":"10314",
    "addr:street":"Merrymount St",
    "iso:country":"US",
    "sg:address":"207 Merrymount St",
    "sg:city":"Staten Island",
    "sg:classifiers":[
        {
            "category":"Health Services",
            "subcategory":"Health Practitioner",
            "type":"Services"
        }
    ],
    "sg:phone":"+1   ",
    "sg:postcode":"10314",
    "sg:province":"NY",
    "wof:name":"Jona Care Physical Therapy PC",
    "wof:placetype":"venue"
},
  "geometry": {"coordinates":[-74.161091,40.588182],"type":"Point"}
}