{
  "type": "Feature",
  "properties": {
    "iso:country":"US",
    "sg:address":"43 Partition St",
    "sg:city":"Saugerties",
    "sg:classifiers":[
        {
            "category":"Organizations",
            "subcategory":"Community Association",
            "type":"Services"
        }
    ],
    "sg:phone":"+1 845 246 7671",
    "sg:postcode":"12477",
    "sg:province":"NY",
    "sg:tags":[
        "club"
    ],
    "wof:name":"Boys & Girls Clubs - Sgrts",
    "wof:placetype":"venue"
},
  "geometry": {"coordinates":[-73.953052,42.079459],"type":"Point"}
}