{
  "type": "Feature",
  "properties": {
    "addr:full":"490 Center Rd Ste 4 Buffalo NY 14224",
    "addr:housenumber":"490",
    "addr:postcode":"14224",
    "addr:street":"Center Rd Ste 4",
    "iso:country":"US",
    "sg:address":"490 Center Rd Ste 4",
    "sg:city":"Buffalo",
    "sg:classifiers":[
        {
            "category":"Banks & Credit Unions",
            "subcategory":"Financial Services",
            "type":"Services"
        }
    ],
    "sg:phone":"+1 716 677 4456",
    "sg:postcode":"14224",
    "sg:province":"NY",
    "sg:tags":[
        "card-merchant",
        "card"
    ],
    "wof:name":"Innovative Card Solutions",
    "wof:placetype":"venue"
},
  "geometry": {"coordinates":[-78.764449,42.839618],"type":"Point"}
}