{
  "type": "Feature",
  "properties": {
    "addr:full":"70 Mount Sinai Ave Mt Sinai NY 11766",
    "addr:housenumber":"70",
    "addr:postcode":"11766",
    "addr:street":"Mount Sinai Ave",
    "iso:country":"US",
    "sg:address":"70 Mount Sinai Ave",
    "sg:city":"Mt Sinai",
    "sg:classifiers":[
        {
            "category":"Professional",
            "subcategory":"Lawyer & Legal Services",
            "type":"Services"
        }
    ],
    "sg:phone":"+1 631 331 0700",
    "sg:postcode":"11766",
    "sg:province":"NY",
    "sg:tags":[
        "attorney",
        "bureau"
    ],
    "wof:name":"Reda's Attorney Svc",
    "wof:placetype":"venue"
},
  "geometry": {"coordinates":[-73.016402,40.93626],"type":"Point"}
}