{
  "type": "Feature",
  "properties": {
    "addr:full":"28 Van Wyck Rd Blauvelt NY 10913",
    "addr:housenumber":"28",
    "addr:postcode":"10913",
    "addr:street":"Van Wyck Rd",
    "iso:country":"US",
    "sg:address":"28 Van Wyck Rd",
    "sg:city":"Blauvelt",
    "sg:classifiers":[
        {
            "category":"Food & Beverages",
            "subcategory":"Groceries & Convenience Stores",
            "type":"Retail Goods"
        }
    ],
    "sg:phone":"+1 845 365 6137",
    "sg:postcode":"10913",
    "sg:province":"NY",
    "wof:name":"Quick Stop Deli",
    "wof:placetype":"venue"
},
  "geometry": {"coordinates":[-73.97111,41.05496],"type":"Point"}
}