{
  "type": "Feature",
  "properties": {
    "addr:full":"720 Classon Ave Brooklyn NY 11238",
    "addr:housenumber":"720",
    "addr:postcode":"11238",
    "addr:street":"Classon Ave",
    "iso:country":"US",
    "sg:address":"720 Classon Ave",
    "sg:city":"Brooklyn",
    "sg:classifiers":[
        {
            "category":"Shopping",
            "subcategory":"Pharmacy",
            "type":"Retail Goods"
        }
    ],
    "sg:phone":"+1   ",
    "sg:postcode":"11238",
    "sg:province":"NY",
    "sg:tags":[
        "drug",
        "store"
    ],
    "wof:name":"Hospital Rx Inc",
    "wof:placetype":"venue"
},
  "geometry": {"coordinates":[-73.96006,40.675211],"type":"Point"}
}