{
  "type": "Feature",
  "properties": {
    "addr:full":"2 Bennett Ave New York NY 10033",
    "addr:housenumber":"2",
    "addr:postcode":"10033",
    "addr:street":"Bennett Ave",
    "iso:country":"US",
    "sg:address":"2 Bennett Ave",
    "sg:city":"New York",
    "sg:classifiers":[
        {
            "category":"Real Estate",
            "subcategory":"Real Estate Operator",
            "type":"Services"
        }
    ],
    "sg:phone":"+1 212 795 5600",
    "sg:postcode":"10033",
    "sg:province":"NY",
    "sg:tags":[
        "owner",
        "res",
        "commercial",
        "for"
    ],
    "wof:name":"C K M R Corporation",
    "wof:placetype":"venue"
},
  "geometry": {"coordinates":[-73.936342,40.851085],"type":"Point"}
}