{
  "type": "Feature",
  "properties": {
    "addr:full":"1844 Rte 112 Coram NY 11727",
    "addr:housenumber":"1844",
    "addr:postcode":"11727",
    "addr:street":"Rte 112",
    "iso:country":"US",
    "sg:address":"1844 Rte 112",
    "sg:city":"Coram",
    "sg:classifiers":[
        {
            "category":"Restaurant",
            "type":"Food & Drink"
        }
    ],
    "sg:phone":"+1   ",
    "sg:postcode":"11727",
    "sg:province":"NY",
    "sg:tags":[
        "eating"
    ],
    "wof:name":"Francesca Mama Pizza",
    "wof:placetype":"venue"
},
  "geometry": {"coordinates":[-73.017505,40.894586],"type":"Point"}
}