{
  "type": "Feature",
  "properties": {
    "addr:full":"500 Western Ave Staten Island NY 10303",
    "addr:housenumber":"500",
    "addr:postcode":"10303",
    "addr:street":"Western Ave",
    "iso:country":"US",
    "sg:address":"500 Western Ave",
    "sg:city":"Staten Island",
    "sg:classifiers":[
        {
            "category":"Professional",
            "subcategory":"Research",
            "type":"Services"
        }
    ],
    "sg:phone":"+1 718 447 7711",
    "sg:postcode":"10303",
    "sg:province":"NY",
    "sg:tags":[
        "environmental",
        "ecological"
    ],
    "wof:name":"Environmental Transportation",
    "wof:placetype":"venue"
},
  "geometry": {"coordinates":[-74.186224,40.630508],"type":"Point"}
}