{
  "type": "Feature",
  "properties": {
    "iso:country":"US",
    "sg:address":"330 Grand St",
    "sg:city":"New York",
    "sg:classifiers":[
        {
            "category":"Wholesale",
            "subcategory":"Apparel",
            "type":"Manufacturing & Wholesale Goods"
        },
        {
            "category":"Shopping",
            "subcategory":"Clothing, Apparel, & Fashions",
            "type":"Retail Goods"
        }
    ],
    "sg:phone":"+1 212 979 1645",
    "sg:postcode":"10002",
    "sg:province":"NY",
    "sg:tags":[
        "lingerie",
        "brassiere"
    ],
    "wof:name":"Isaac Sultan & Sons Inc",
    "wof:placetype":"venue"
},
  "geometry": {"coordinates":[-73.990303,40.717194],"type":"Point"}
}