{
  "type": "Feature",
  "properties": {
    "addr:full":"7873 Oswego Rd Liverpool NY 13090",
    "addr:housenumber":"7873",
    "addr:postcode":"13090",
    "addr:street":"Oswego Rd",
    "iso:country":"US",
    "sg:address":"7873 Oswego Rd",
    "sg:city":"Liverpool",
    "sg:classifiers":[
        {
            "category":"Restaurant",
            "type":"Food & Drink"
        }
    ],
    "sg:phone":"+1 315 622 2738",
    "sg:postcode":"13090",
    "sg:province":"NY",
    "sg:tags":[
        "parlor",
        "ice",
        "cream"
    ],
    "sg:website":"www.carvel.com",
    "wof:name":"Carvel Ice Cream & Bakery",
    "wof:placetype":"venue"
},
  "geometry": {"coordinates":[-76.227555,43.154494],"type":"Point"}
}