{
  "type": "Feature",
  "properties": {
    "addr:full":"55 Main St Oneonta NY 13820",
    "addr:housenumber":"55",
    "addr:postcode":"13820",
    "addr:street":"Main St",
    "iso:country":"US",
    "sg:address":"55 Main St",
    "sg:city":"Oneonta",
    "sg:classifiers":[
        {
            "category":"Personal",
            "subcategory":"Tattoo Parlor",
            "type":"Services"
        }
    ],
    "sg:phone":"+1 607 431 1858",
    "sg:postcode":"13820",
    "sg:province":"NY",
    "sg:tags":[
        "tattooing"
    ],
    "wof:name":"Body Piercing By Lollipop",
    "wof:placetype":"venue"
},
  "geometry": {"coordinates":[-75.06389299999999,42.449206],"type":"Point"}
}