{
  "type": "Feature",
  "properties": {
    "addr:full":"270 W 39th St New York NY 10018",
    "addr:housenumber":"270",
    "addr:postcode":"10018",
    "addr:street":"W 39Th St",
    "iso:country":"US",
    "sg:address":"270 W 39th St",
    "sg:city":"New York",
    "sg:classifiers":[
        {
            "category":"Shopping",
            "subcategory":"Hobbies, Toys, & Games",
            "type":"Retail Goods"
        },
        {
            "category":"Shopping",
            "subcategory":"Bridal",
            "type":"Retail Goods"
        }
    ],
    "sg:phone":"+1 212 869 0235",
    "sg:postcode":"10018",
    "sg:province":"NY",
    "sg:tags":[
        "shop",
        "hobby"
    ],
    "sg:website":"www.fashionfabric.biz",
    "wof:name":"Fashion Fabrics,inc.",
    "wof:placetype":"venue"
},
  "geometry": {"coordinates":[-73.99065899999999,40.755107],"type":"Point"}
}