{
  "type": "Feature",
  "properties": {
    "iso:country":"US",
    "sg:address":"1265 Suffolk Ave",
    "sg:city":"Brentwood",
    "sg:classifiers":[
        {
            "category":"Communications",
            "type":"Services"
        }
    ],
    "sg:phone":"+1 631 231 1495",
    "sg:postcode":"11717",
    "sg:province":"NY",
    "wof:name":"Conversent Communications",
    "wof:placetype":"venue"
},
  "geometry": {"coordinates":[-73.223429,40.786251],"type":"Point"}
}