{
  "type": "Feature",
  "properties": {
    "addr:full":"9261 246th St Floral Park NY 11001",
    "addr:housenumber":"9261",
    "addr:postcode":"11001",
    "addr:street":"246Th St",
    "iso:country":"US",
    "sg:address":"9261 246th St",
    "sg:city":"Floral Park",
    "sg:classifiers":[
        {
            "category":"Shopping",
            "subcategory":"Catalog Store",
            "type":"Retail Goods"
        }
    ],
    "sg:phone":"+1   ",
    "sg:postcode":"11001",
    "sg:province":"NY",
    "sg:tags":[
        "house",
        "mail"
    ],
    "wof:name":"Joes Train Parts",
    "wof:placetype":"venue"
},
  "geometry": {"coordinates":[-73.721825,40.72416],"type":"Point"}
}