{
  "type": "Feature",
  "properties": {
    "iso:country":"US",
    "sg:address":"363 Rasbach Rd",
    "sg:city":"Clayville",
    "sg:classifiers":[
        {
            "category":"Building & Trades",
            "subcategory":"Construction",
            "type":"Services"
        }
    ],
    "sg:phone":"+1 315 737 9471",
    "sg:postcode":"13322",
    "sg:province":"NY",
    "sg:tags":[
        "paving",
        "contractor"
    ],
    "sg:website":"www.barrettpaving.com",
    "wof:name":"Barrett Paving Materials Inc",
    "wof:placetype":"venue"
},
  "geometry": {"coordinates":[-75.194366,42.967293],"type":"Point"}
}