{
  "type": "Feature",
  "properties": {
    "addr:full":"30 Briarwood Dr Lockport NY 14094",
    "addr:housenumber":"30",
    "addr:postcode":"14094",
    "addr:street":"Briarwood Dr",
    "iso:country":"US",
    "sg:address":"30 Briarwood Dr",
    "sg:city":"Lockport",
    "sg:classifiers":[
        {
            "category":"Shopping",
            "subcategory":"Jewelry",
            "type":"Retail Goods"
        }
    ],
    "sg:phone":"+1   ",
    "sg:postcode":"14094",
    "sg:province":"NY",
    "wof:name":"Jamell",
    "wof:placetype":"venue"
},
  "geometry": {"coordinates":[-78.667221,43.160183],"type":"Point"}
}