{
  "type": "Feature",
  "properties": {
    "addr:full":"75 Union Ave Amityville NY 11701",
    "addr:housenumber":"75",
    "addr:postcode":"11701",
    "addr:street":"Union Ave",
    "iso:country":"US",
    "sg:address":"75 Union Ave",
    "sg:city":"Amityville",
    "sg:classifiers":[
        {
            "category":"Health Services",
            "subcategory":"Chiropractor",
            "type":"Services"
        }
    ],
    "sg:phone":"+1 631 264 0100",
    "sg:postcode":"11701",
    "sg:province":"NY",
    "wof:name":"Total Life Care Ctr",
    "wof:placetype":"venue"
},
  "geometry": {"coordinates":[-73.41569,40.677769],"type":"Point"}
}