{
  "type": "Feature",
  "properties": {
    "iso:country":"US",
    "sg:address":"666 Broadway",
    "sg:city":"New York",
    "sg:classifiers":[
        {
            "category":"Organizations",
            "subcategory":"Non-profit Organization",
            "type":"Services"
        }
    ],
    "sg:phone":"+1 212 780 1400",
    "sg:postcode":"10012",
    "sg:province":"NY",
    "sg:tags":[
        "nonprofit",
        "social"
    ],
    "wof:name":"Community Access Inc",
    "wof:placetype":"venue"
},
  "geometry": {"coordinates":[-73.99475099999999,40.727819],"type":"Point"}
}