{
  "type": "Feature",
  "properties": {
    "iso:country":"US",
    "sg:address":"10 Shore Dr",
    "sg:city":"Mastic Beach",
    "sg:classifiers":[
        {
            "category":"Retail",
            "subcategory":"Repair Shop",
            "type":"Services"
        }
    ],
    "sg:phone":"+1 631 281 8244",
    "sg:postcode":"11951",
    "sg:province":"NY",
    "sg:tags":[
        "boating"
    ],
    "wof:name":"Southwest Marina",
    "wof:placetype":"venue"
},
  "geometry": {"coordinates":[-72.816002,40.774101],"type":"Point"}
}