{
  "type": "Feature",
  "properties": {
    "addr:full":"22 Jones St New York NY 10014",
    "addr:housenumber":"22",
    "addr:postcode":"10014",
    "addr:street":"Jones St",
    "iso:country":"US",
    "sg:address":"22 Jones St",
    "sg:city":"New York",
    "sg:classifiers":[
        {
            "category":"Shopping",
            "subcategory":"Music",
            "type":"Retail Goods"
        }
    ],
    "sg:phone":"+1 212 675 3040",
    "sg:postcode":"10014",
    "sg:province":"NY",
    "sg:tags":[
        "dvd's"
    ],
    "sg:website":"www.striderrecords.com/",
    "wof:name":"Strider Records",
    "wof:placetype":"venue"
},
  "geometry": {"coordinates":[-74.00252999999999,40.73177],"type":"Point"}
}