{
  "type": "Feature",
  "properties": {
    "addr:full":"116 Pinehurst Ave New York NY 10033",
    "addr:housenumber":"116",
    "addr:postcode":"10033",
    "addr:street":"Pinehurst Ave",
    "iso:country":"US",
    "sg:address":"116 Pinehurst Ave",
    "sg:city":"New York",
    "sg:classifiers":[
        {
            "category":"Coffee & Tea",
            "type":"Food & Drink"
        },
        {
            "category":"Restaurant",
            "type":"Food & Drink"
        }
    ],
    "sg:phone":"+1 212 543 9015",
    "sg:postcode":"10033",
    "sg:province":"NY",
    "wof:name":"Archway Cafe",
    "wof:placetype":"venue"
},
  "geometry": {"coordinates":[-73.939003,40.8522],"type":"Point"}
}