{
  "type": "Feature",
  "properties": {
    "addr:full":"1200 Eastchester Rd Bronx NY 10461",
    "addr:housenumber":"1200",
    "addr:postcode":"10461",
    "addr:street":"Eastchester Rd",
    "iso:country":"US",
    "sg:address":"1200 Eastchester Rd",
    "sg:city":"Bronx",
    "sg:classifiers":[
        {
            "category":"Food & Beverages",
            "subcategory":"Meat & Fish",
            "type":"Retail Goods"
        },
        {
            "category":"Food & Beverages",
            "subcategory":"Groceries & Convenience Stores",
            "type":"Retail Goods"
        }
    ],
    "sg:postcode":"10461",
    "sg:province":"NY",
    "sg:tags":[
        "shop"
    ],
    "wof:name":"M&R Deli and Hero Shop",
    "wof:placetype":"venue"
},
  "geometry": {"coordinates":[-73.84620099999999,40.844488],"type":"Point"}
}