{
  "type": "Feature",
  "properties": {
    "iso:country":"US",
    "sg:address":"4234 College Point Blvd",
    "sg:city":"Flushing",
    "sg:classifiers":[
        {
            "category":"Wholesale",
            "subcategory":"Groceries",
            "type":"Manufacturing & Wholesale Goods"
        }
    ],
    "sg:phone":"+1 718 358 1806",
    "sg:postcode":"11355",
    "sg:province":"NY",
    "sg:tags":[
        "grocers-wholesale"
    ],
    "wof:name":"Ding Xiang Inc",
    "wof:placetype":"venue"
},
  "geometry": {"coordinates":[-73.83715100000001,40.743555],"type":"Point"}
}