{
  "type": "Feature",
  "properties": {
    "addr:full":"1520 Avenue U Brooklyn NY 11229",
    "addr:housenumber":"1520",
    "addr:postcode":"11229",
    "addr:street":"Avenue U",
    "iso:country":"US",
    "sg:address":"1520 Avenue U",
    "sg:city":"Brooklyn",
    "sg:classifiers":[
        {
            "category":"Retail",
            "subcategory":"Laundry & Dry Cleaning",
            "type":"Services"
        }
    ],
    "sg:phone":"+1 718 376 9578",
    "sg:postcode":"11229",
    "sg:province":"NY",
    "sg:website":"www.peter-kim.com",
    "wof:name":"Peter Kim",
    "wof:placetype":"venue"
},
  "geometry": {"coordinates":[-73.95590199999999,40.598801],"type":"Point"}
}