{
  "type": "Feature",
  "properties": {
    "iso:country":"US",
    "sg:address":"54 W Main St",
    "sg:city":"Goshen",
    "sg:classifiers":[
        {
            "category":"Banks & Credit Unions",
            "subcategory":"Bank",
            "type":"Services"
        }
    ],
    "sg:phone":"+1 845 294 2068",
    "sg:postcode":"10924",
    "sg:province":"NY",
    "wof:name":"Fleet Bank",
    "wof:placetype":"venue"
},
  "geometry": {"coordinates":[-74.324741,41.402221],"type":"Point"}
}