{
  "type": "Feature",
  "properties": {
    "iso:country":"US",
    "sg:address":"27 Branch Ln",
    "sg:city":"Levittown",
    "sg:classifiers":[
        {
            "category":"Building & Trades",
            "subcategory":"Construction",
            "type":"Services"
        }
    ],
    "sg:phone":"+1 516 822 0857",
    "sg:postcode":"11756",
    "sg:province":"NY",
    "sg:tags":[
        "house"
    ],
    "wof:name":"Will A Way",
    "wof:placetype":"venue"
},
  "geometry": {"coordinates":[-73.54212,40.743208],"type":"Point"}
}