{
  "type": "Feature",
  "properties": {
    "iso:country":"US",
    "sg:address":"4508 Skillman Ave",
    "sg:city":"Sunnyside",
    "sg:classifiers":[
        {
            "category":"Social Services",
            "subcategory":"Child Care",
            "type":"Services"
        }
    ],
    "sg:phone":"+1 718 361 0080",
    "sg:postcode":"11104",
    "sg:province":"NY",
    "sg:tags":[
        "day"
    ],
    "wof:name":"Holy Mountain Nursery School Inc",
    "wof:placetype":"venue"
},
  "geometry": {"coordinates":[-73.918503,40.746498],"type":"Point"}
}