{
  "type": "Feature",
  "properties": {
    "addr:full":"6 Mountain View Rd Staatsburg NY 12580",
    "addr:housenumber":"6",
    "addr:postcode":"12580",
    "addr:street":"Mountain View Rd",
    "iso:country":"US",
    "sg:address":"6 Mountain View Rd",
    "sg:city":"Staatsburg",
    "sg:classifiers":[
        {
            "category":"Building & Trades",
            "subcategory":"Construction",
            "type":"Services"
        }
    ],
    "sg:phone":"+1 845 889 8534",
    "sg:postcode":"12580",
    "sg:province":"NY",
    "sg:tags":[
        "house"
    ],
    "wof:name":"Blue Sky Restoration",
    "wof:placetype":"venue"
},
  "geometry": {"coordinates":[-73.920095,41.844536],"type":"Point"}
}