{
  "type": "Feature",
  "properties": {
    "iso:country":"US",
    "sg:address":"6 Chase St",
    "sg:city":"Avoca",
    "sg:classifiers":[
        {
            "category":"Home & Garden",
            "subcategory":"Hardware",
            "type":"Retail Goods"
        }
    ],
    "sg:phone":"+1 607 566 3996",
    "sg:postcode":"14809",
    "sg:province":"NY",
    "sg:website":"www.stihlman.com",
    "wof:name":"Avoca Village Sales-Stihl",
    "wof:placetype":"venue"
},
  "geometry": {"coordinates":[-77.418457,42.409606],"type":"Point"}
}