{
  "type": "Feature",
  "properties": {
    "addr:full":"2360 8th Ave New York NY 10027",
    "addr:housenumber":"2360",
    "addr:postcode":"10027",
    "addr:street":"8Th Ave",
    "iso:country":"US",
    "sg:address":"2360 8th Ave",
    "sg:city":"New York",
    "sg:classifiers":[
        {
            "category":"Shopping",
            "subcategory":"Beauty & Cosmetics",
            "type":"Retail Goods"
        }
    ],
    "sg:phone":"+1   ",
    "sg:postcode":"10027",
    "sg:province":"NY",
    "sg:tags":[
        "merchandise"
    ],
    "wof:name":"Saloum Darrou Store",
    "wof:placetype":"venue"
},
  "geometry": {"coordinates":[-73.95036899999999,40.811045],"type":"Point"}
}