{
  "type": "Feature",
  "properties": {
    "addr:full":"153 Brady Ave Hawthorne NY 10532",
    "addr:housenumber":"153",
    "addr:postcode":"10532",
    "addr:street":"Brady Ave",
    "iso:country":"US",
    "sg:address":"153 Brady Ave",
    "sg:city":"Hawthorne",
    "sg:classifiers":[
        {
            "category":"Building & Trades",
            "subcategory":"Electrical",
            "type":"Services"
        }
    ],
    "sg:phone":"+1 914 741 5662",
    "sg:postcode":"10532",
    "sg:province":"NY",
    "sg:tags":[
        "electrical",
        "contractor"
    ],
    "wof:name":"Alfred Difalco Electric Corp",
    "wof:placetype":"venue"
},
  "geometry": {"coordinates":[-73.793738,41.098319],"type":"Point"}
}