{
  "type": "Feature",
  "properties": {
    "addr:full":"11 Holiday Way Staten Island NY 10314",
    "addr:housenumber":"11",
    "addr:postcode":"10314",
    "addr:street":"Holiday Way",
    "iso:country":"US",
    "sg:address":"11 Holiday Way",
    "sg:city":"Staten Island",
    "sg:classifiers":[
        {
            "category":"Building & Trades",
            "subcategory":"Construction",
            "type":"Services"
        }
    ],
    "sg:phone":"+1 718 698 4870",
    "sg:postcode":"10314",
    "sg:province":"NY",
    "sg:tags":[
        "contractor",
        "architectural",
        "metalwork",
        "mfg"
    ],
    "wof:name":"G & G Fence",
    "wof:placetype":"venue"
},
  "geometry": {"coordinates":[-74.151027,40.621215],"type":"Point"}
}