{
  "type": "Feature",
  "properties": {
    "addr:full":"102 W Seneca St Manlius NY 13104",
    "addr:housenumber":"102",
    "addr:postcode":"13104",
    "addr:street":"W Seneca St",
    "iso:country":"US",
    "sg:address":"102 W Seneca St",
    "sg:city":"Manlius",
    "sg:classifiers":[
        {
            "category":"Banks & Credit Unions",
            "subcategory":"Investment Brokerage",
            "type":"Services"
        }
    ],
    "sg:phone":"+1 315 682 4800",
    "sg:postcode":"13104",
    "sg:province":"NY",
    "sg:tags":[
        "security"
    ],
    "sg:website":"www.edwardjones.com",
    "wof:name":"Edward Jones",
    "wof:placetype":"venue"
},
  "geometry": {"coordinates":[-75.98041600000001,43.000447],"type":"Point"}
}