{
  "type": "Feature",
  "properties": {
    "iso:country":"US",
    "sg:address":"96 Bayview Ave",
    "sg:city":"Great Neck",
    "sg:classifiers":[
        {
            "category":"Real Estate",
            "subcategory":"Developer",
            "type":"Services"
        }
    ],
    "sg:phone":"+1 516 466 1407",
    "sg:postcode":"11021",
    "sg:province":"NY",
    "wof:name":"M & M Development Inc",
    "wof:placetype":"venue"
},
  "geometry": {"coordinates":[-73.742923,40.790449],"type":"Point"}
}