{
  "type": "Feature",
  "properties": {
    "iso:country":"US",
    "sg:address":"40 Pine St",
    "sg:city":"Perry",
    "sg:classifiers":[
        {
            "category":"Building & Trades",
            "subcategory":"Construction",
            "type":"Services"
        }
    ],
    "sg:phone":"+1 585 237 2519",
    "sg:postcode":"14530",
    "sg:province":"NY",
    "sg:tags":[
        "altering",
        "remodeling",
        "contractor"
    ],
    "wof:name":"Elegant Design Remodeling",
    "wof:placetype":"venue"
},
  "geometry": {"coordinates":[-78.007544,42.721189],"type":"Point"}
}