{
  "type": "Feature",
  "properties": {
    "iso:country":"US",
    "sg:address":"24 Cedar St",
    "sg:city":"Dobbs Ferry",
    "sg:classifiers":[
        {
            "category":"Shopping",
            "type":"Retail Goods"
        }
    ],
    "sg:phone":"+1   ",
    "sg:postcode":"10522",
    "sg:province":"NY",
    "sg:tags":[
        "merchandise"
    ],
    "wof:name":"Elegant Poster Ltd Inc",
    "wof:placetype":"venue"
},
  "geometry": {"coordinates":[-73.871824,41.015484],"type":"Point"}
}