{
  "type": "Feature",
  "properties": {
    "addr:full":"1807 Archer St Bronx NY 10460",
    "addr:housenumber":"1807",
    "addr:postcode":"10460",
    "addr:street":"Archer St",
    "iso:country":"US",
    "sg:address":"1807 Archer St",
    "sg:city":"Bronx",
    "sg:classifiers":[
        {
            "category":"Personal",
            "subcategory":"Beauty Salon",
            "type":"Services"
        }
    ],
    "sg:phone":"+1 718 863 4495",
    "sg:postcode":"10460",
    "sg:province":"NY",
    "wof:name":"Leland Hair Styling",
    "wof:placetype":"venue"
},
  "geometry": {"coordinates":[-73.86661599999999,40.837633],"type":"Point"}
}