{
  "type": "Feature",
  "properties": {
    "addr:full":"511 Fulton St Farmingdale NY 11735",
    "addr:housenumber":"511",
    "addr:postcode":"11735",
    "addr:street":"Fulton St",
    "iso:country":"US",
    "sg:address":"511 Fulton St",
    "sg:city":"Farmingdale",
    "sg:classifiers":[
        {
            "category":"Retail",
            "subcategory":"Auto Repair",
            "type":"Services"
        }
    ],
    "sg:phone":"+1   ",
    "sg:postcode":"11735",
    "sg:province":"NY",
    "sg:tags":[
        "general"
    ],
    "wof:name":"Magic Touch Auto Repair Inc",
    "wof:placetype":"venue"
},
  "geometry": {"coordinates":[-73.45235099999999,40.730024],"type":"Point"}
}