{
  "type": "Feature",
  "properties": {
    "addr:full":"53 Maize Ln Kingston NY 12401",
    "addr:housenumber":"53",
    "addr:postcode":"12401",
    "addr:street":"Maize Ln",
    "iso:country":"US",
    "sg:address":"53 Maize Ln",
    "sg:city":"Kingston",
    "sg:classifiers":[
        {
            "category":"Restaurant",
            "type":"Food & Drink"
        }
    ],
    "sg:phone":"+1 845 336 4399",
    "sg:postcode":"12401",
    "sg:province":"NY",
    "sg:website":"www.99restaurants.com",
    "wof:name":"Ninety Nine Restaurant & Pub",
    "wof:placetype":"venue"
},
  "geometry": {"coordinates":[-74.021164,41.941485],"type":"Point"}
}