{
  "type": "Feature",
  "properties": {
    "addr:full":"425 Lexington Avenue New York NY 10017",
    "addr:housenumber":"425",
    "addr:postcode":"10017",
    "addr:street":"Lexington Avenue",
    "iso:country":"US",
    "sg:address":"425 Lexington Avenue",
    "sg:city":"New York",
    "sg:classifiers":[
        {
            "category":"Professional",
            "subcategory":"Lawyer & Legal Services",
            "type":"Services"
        }
    ],
    "sg:phone":"+1 212 455 2000",
    "sg:postcode":"10017",
    "sg:province":"NY",
    "wof:name":"Lee Edward H Atty",
    "wof:placetype":"venue"
},
  "geometry": {"coordinates":[-73.975258,40.752553],"type":"Point"}
}