{
  "type": "Feature",
  "properties": {
    "addr:full":"22 Central Park S New York NY 10019",
    "addr:housenumber":"22",
    "addr:postcode":"10019",
    "addr:street":"Central Park S",
    "iso:country":"US",
    "sg:address":"22 Central Park S",
    "sg:city":"New York",
    "sg:classifiers":[
        {
            "category":"Shopping",
            "subcategory":"Shoes",
            "type":"Retail Goods"
        }
    ],
    "sg:phone":"+1 212 527 2414",
    "sg:postcode":"10019",
    "sg:province":"NY",
    "sg:tags":[
        "store"
    ],
    "wof:name":"Fennix Italy",
    "wof:placetype":"venue"
},
  "geometry": {"coordinates":[-73.974785,40.764752],"type":"Point"}
}