{
  "type": "Feature",
  "properties": {
    "addr:full":"1610 York Ave New York NY 10028",
    "addr:housenumber":"1610",
    "addr:postcode":"10028",
    "addr:street":"York Ave",
    "iso:country":"US",
    "sg:address":"1610 York Ave",
    "sg:city":"New York",
    "sg:classifiers":[
        {
            "category":"Retail",
            "subcategory":"Repair Shop",
            "type":"Services"
        }
    ],
    "sg:phone":"+1 212 903 0501",
    "sg:postcode":"10028",
    "sg:province":"NY",
    "sg:tags":[
        "lock",
        "key",
        "locksmith"
    ],
    "wof:name":"7 Day Anyplace A Locksmith",
    "wof:placetype":"venue"
},
  "geometry": {"coordinates":[-73.947197,40.7756],"type":"Point"}
}