{
  "type": "Feature",
  "properties": {
    "addr:full":"8010 Brewerton Rd Cicero NY 13039",
    "addr:housenumber":"8010",
    "addr:postcode":"13039",
    "addr:street":"Brewerton Rd",
    "iso:country":"US",
    "sg:address":"8010 Brewerton Rd",
    "sg:city":"Cicero",
    "sg:classifiers":[
        {
            "category":"Building & Trades",
            "subcategory":"Construction",
            "type":"Services"
        }
    ],
    "sg:phone":"+1 315 698 4500",
    "sg:postcode":"13039",
    "sg:province":"NY",
    "sg:tags":[
        "sun",
        "solarium",
        "rooms"
    ],
    "wof:name":"Sun Service Ctr",
    "wof:placetype":"venue"
},
  "geometry": {"coordinates":[-76.121781,43.157432],"type":"Point"}
}