{
  "type": "Feature",
  "properties": {
    "iso:country":"US",
    "sg:address":"760 Manor Rd",
    "sg:city":"Staten Island",
    "sg:classifiers":[
        {
            "category":"Shopping",
            "subcategory":"Clothing, Apparel, & Fashions",
            "type":"Retail Goods"
        }
    ],
    "sg:phone":"+1 718 494 2366",
    "sg:postcode":"10314",
    "sg:province":"NY",
    "sg:tags":[
        "athletic",
        "boy",
        "designer",
        "foo"
    ],
    "wof:name":"Charlies Clothing Center",
    "wof:placetype":"venue"
},
  "geometry": {"coordinates":[-74.12128,40.609068],"type":"Point"}
}