{
  "type": "Feature",
  "properties": {
    "addr:full":"208 Emerson St Port Jefferson NY 11777",
    "addr:housenumber":"208",
    "addr:postcode":"11777",
    "addr:street":"Emerson St",
    "iso:country":"US",
    "sg:address":"208 Emerson St",
    "sg:city":"Port Jefferson",
    "sg:classifiers":[
        {
            "category":"Building & Trades",
            "subcategory":"Construction",
            "type":"Services"
        }
    ],
    "sg:phone":"+1 631 331 3794",
    "sg:postcode":"11777",
    "sg:province":"NY",
    "sg:tags":[
        "general",
        "contractor"
    ],
    "wof:name":"Tano Construction Inc",
    "wof:placetype":"venue"
},
  "geometry": {"coordinates":[-73.074125,40.939889],"type":"Point"}
}