{
  "type": "Feature",
  "properties": {
    "addr:full":"109 3rd Avenue Brooklyn NY 11217",
    "addr:housenumber":"109",
    "addr:postcode":"11217",
    "addr:street":"3Rd Avenue",
    "iso:country":"US",
    "sg:address":"109 3rd Avenue",
    "sg:city":"Brooklyn",
    "sg:classifiers":[
        {
            "category":"Food & Beverages",
            "subcategory":"Groceries & Convenience Stores",
            "type":"Retail Goods"
        }
    ],
    "sg:phone":"+1 718 643 2955",
    "sg:postcode":"11217",
    "sg:province":"NY",
    "wof:name":"Israel Mini Market",
    "wof:placetype":"venue"
},
  "geometry": {"coordinates":[-73.982235,40.683057],"type":"Point"}
}