{
  "type": "Feature",
  "properties": {
    "addr:full":"3513 Broadway Astoria NY 11106",
    "addr:housenumber":"3513",
    "addr:postcode":"11106",
    "addr:street":"Broadway",
    "iso:country":"US",
    "sg:address":"3513 Broadway",
    "sg:city":"Astoria",
    "sg:classifiers":[
        {
            "category":"Professional",
            "type":"Services"
        }
    ],
    "sg:phone":"+1 718 728 2422",
    "sg:postcode":"11106",
    "sg:province":"NY",
    "sg:tags":[
        "caterer"
    ],
    "wof:name":"D&F Italian Deli",
    "wof:placetype":"venue"
},
  "geometry": {"coordinates":[-73.92152299999999,40.760432],"type":"Point"}
}