{
  "type": "Feature",
  "properties": {
    "iso:country":"US",
    "sg:address":"66 Suzette Dr",
    "sg:city":"Buffalo",
    "sg:classifiers":[
        {
            "category":"Shopping",
            "subcategory":"Hobbies, Toys, & Games",
            "type":"Retail Goods"
        }
    ],
    "sg:phone":"+1   ",
    "sg:postcode":"14227",
    "sg:province":"NY",
    "sg:tags":[
        "motion"
    ],
    "wof:name":"Sue Emilia",
    "wof:placetype":"venue"
},
  "geometry": {"coordinates":[-78.712343,42.867535],"type":"Point"}
}