{
  "type": "Feature",
  "properties": {
    "iso:country":"US",
    "sg:address":"S5980 S Park Ave",
    "sg:city":"Hamburg",
    "sg:classifiers":[
        {
            "category":"Autos & Motor Vehicles",
            "subcategory":"Fuel & Gas Station",
            "type":"Retail Goods"
        },
        {
            "category":"Food & Beverages",
            "subcategory":"Groceries & Convenience Stores",
            "type":"Retail Goods"
        }
    ],
    "sg:phone":"+1 716 649 8707",
    "sg:postcode":"14075",
    "sg:province":"NY",
    "sg:website":"http://www.noco.com",
    "wof:name":"Noco Express 29",
    "wof:placetype":"venue"
},
  "geometry": {"coordinates":[-78.825388,42.735309],"type":"Point"}
}