{
  "type": "Feature",
  "properties": {
    "addr:full":"4911 Chipmunk Dr Canandaigua NY 14424",
    "addr:housenumber":"4911",
    "addr:postcode":"14424",
    "addr:street":"Chipmunk Dr",
    "iso:country":"US",
    "sg:address":"4911 Chipmunk Dr",
    "sg:city":"Canandaigua",
    "sg:classifiers":[
        {
            "category":"Building & Trades",
            "subcategory":"Landscaping Services",
            "type":"Services"
        }
    ],
    "sg:phone":"+1 585 229 5276",
    "sg:postcode":"14424",
    "sg:province":"NY",
    "sg:tags":[
        "lawn",
        "garden",
        "landscape"
    ],
    "wof:name":"Walker Del Landscaping",
    "wof:placetype":"venue"
},
  "geometry": {"coordinates":[-77.452242,42.788775],"type":"Point"}
}