{
  "type": "Feature",
  "properties": {
    "addr:full":"5 Avenue 82 Middle Village NY 11379",
    "addr:housenumber":"5;82",
    "addr:postcode":"11379",
    "addr:street":"Avenue",
    "iso:country":"US",
    "sg:address":"5 Avenue 82",
    "sg:city":"Middle Village",
    "sg:classifiers":[
        {
            "category":"Museum",
            "type":"Entertainment"
        }
    ],
    "sg:phone":"+1 718 326 7050",
    "sg:postcode":"11379",
    "sg:province":"NY",
    "wof:name":"Metropolitan Museum Of Art",
    "wof:placetype":"venue"
},
  "geometry": {"coordinates":[-73.87342599999999,40.722212],"type":"Point"}
}