{
  "type": "Feature",
  "properties": {
    "iso:country":"US",
    "sg:address":"1417 57th St",
    "sg:city":"Brooklyn",
    "sg:classifiers":[
        {
            "category":"Professional",
            "subcategory":"Research",
            "type":"Services"
        }
    ],
    "sg:phone":"+1   ",
    "sg:postcode":"11219",
    "sg:province":"NY",
    "sg:tags":[
        "business"
    ],
    "wof:name":"Jakobovitsco Inc",
    "wof:placetype":"venue"
},
  "geometry": {"coordinates":[-73.992604,40.62816],"type":"Point"}
}