{
  "type": "Feature",
  "properties": {
    "iso:country":"US",
    "sg:address":"1290 Westchester Ave",
    "sg:city":"Bronx",
    "sg:classifiers":[
        {
            "category":"Personal",
            "subcategory":"Barber",
            "type":"Services"
        }
    ],
    "sg:phone":"+1 718 842 7634",
    "sg:postcode":"10459",
    "sg:province":"NY",
    "wof:name":"Mecca's Barbershop",
    "wof:placetype":"venue"
},
  "geometry": {"coordinates":[-73.887293,40.826813],"type":"Point"}
}