{
  "type": "Feature",
  "properties": {
    "iso:country":"US",
    "sg:address":"1330 Niagara Falls Blvd",
    "sg:city":"Tonawanda",
    "sg:classifiers":[
        {
            "category":"Shopping",
            "subcategory":"Clothing, Apparel, & Fashions",
            "type":"Retail Goods"
        }
    ],
    "sg:phone":"+1 716 835 5950",
    "sg:postcode":"14150",
    "sg:province":"NY",
    "sg:tags":[
        "tailor"
    ],
    "wof:name":"Alfio's Tailor Shop",
    "wof:placetype":"venue"
},
  "geometry": {"coordinates":[-78.822728,42.987211],"type":"Point"}
}