{
  "type": "Feature",
  "properties": {
    "addr:full":"1762 Merrick Ave Merrick NY 11566",
    "addr:housenumber":"1762",
    "addr:postcode":"11566",
    "addr:street":"Merrick Ave",
    "iso:country":"US",
    "sg:address":"1762 Merrick Ave",
    "sg:city":"Merrick",
    "sg:classifiers":[
        {
            "category":"Fast Food",
            "type":"Food & Drink"
        },
        {
            "category":"Food & Beverages",
            "subcategory":"Bakery",
            "type":"Retail Goods"
        }
    ],
    "sg:phone":"+1 516 442 1330",
    "sg:postcode":"11566",
    "sg:province":"NY",
    "sg:tags":[
        "sandwich"
    ],
    "sg:website":"myspace.com/souperfry",
    "wof:name":"Souper Fry",
    "wof:placetype":"venue"
},
  "geometry": {"coordinates":[-73.556935,40.675304],"type":"Point"}
}