{
  "type": "Feature",
  "properties": {
    "addr:full":"1901 Brewerton Rd Syracuse NY 13211",
    "addr:housenumber":"1901",
    "addr:postcode":"13211",
    "addr:street":"Brewerton Rd",
    "iso:country":"US",
    "sg:address":"1901 Brewerton Rd",
    "sg:city":"Syracuse",
    "sg:classifiers":[
        {
            "category":"Home & Garden",
            "subcategory":"Household Appliances",
            "type":"Retail Goods"
        }
    ],
    "sg:phone":"+1 315 455 2552",
    "sg:postcode":"13211",
    "sg:province":"NY",
    "sg:tags":[
        "cleaners",
        "vacuum"
    ],
    "wof:name":"Kirby Co",
    "wof:placetype":"venue"
},
  "geometry": {"coordinates":[-76.14642499999999,43.095473],"type":"Point"}
}