{
  "type": "Feature",
  "properties": {
    "addr:full":"106 Windelin Dr Henrietta NY 14467",
    "addr:housenumber":"106",
    "addr:postcode":"14467",
    "addr:street":"Windelin Dr",
    "iso:country":"US",
    "sg:address":"106 Windelin Dr",
    "sg:city":"Henrietta",
    "sg:classifiers":[
        {
            "category":"Professional",
            "subcategory":"Art Services",
            "type":"Services"
        }
    ],
    "sg:phone":"+1 585 334 5130",
    "sg:postcode":"14467",
    "sg:province":"NY",
    "sg:tags":[
        "designer",
        "display",
        "producer"
    ],
    "wof:name":"True Colors Hair Design",
    "wof:placetype":"venue"
},
  "geometry": {"coordinates":[-77.627877,43.042543],"type":"Point"}
}