{
  "type": "Feature",
  "properties": {
    "addr:full":"340 Villa Roma Rd Callicoon NY 12723",
    "addr:housenumber":"340",
    "addr:postcode":"12723",
    "addr:street":"Villa Roma Rd",
    "iso:country":"US",
    "sg:address":"340 Villa Roma Rd",
    "sg:city":"Callicoon",
    "sg:classifiers":[
        {
            "category":"Real Estate",
            "subcategory":"Real Estate Agent",
            "type":"Services"
        }
    ],
    "sg:phone":"+1 845 887 6400",
    "sg:postcode":"12723",
    "sg:province":"NY",
    "wof:name":"Beechwood Estates",
    "wof:placetype":"venue"
},
  "geometry": {"coordinates":[-74.974947,41.761691],"type":"Point"}
}