{
  "type": "Feature",
  "properties": {
    "addr:full":"947 Montauk Hwy Oakdale NY 11769",
    "addr:housenumber":"947",
    "addr:postcode":"11769",
    "addr:street":"Montauk Hwy",
    "iso:country":"US",
    "sg:address":"947 Montauk Hwy",
    "sg:city":"Oakdale",
    "sg:classifiers":[
        {
            "category":"Cinema",
            "subcategory":"Movie Rental",
            "type":"Entertainment"
        }
    ],
    "sg:phone":"+1 631 563 4484",
    "sg:postcode":"11769",
    "sg:province":"NY",
    "sg:tags":[
        "game",
        "video"
    ],
    "wof:name":"Mr Video",
    "wof:placetype":"venue"
},
  "geometry": {"coordinates":[-73.12069700000001,40.7379],"type":"Point"}
}