{
  "type": "Feature",
  "properties": {
    "addr:full":"83 Melanie Ln Syosset NY 11791",
    "addr:housenumber":"83",
    "addr:postcode":"11791",
    "addr:street":"Melanie Ln",
    "iso:country":"US",
    "sg:address":"83 Melanie Ln",
    "sg:city":"Syosset",
    "sg:classifiers":[
        {
            "category":"Manufacturing",
            "subcategory":"Printing",
            "type":"Manufacturing & Wholesale Goods"
        }
    ],
    "sg:phone":"+1   ",
    "sg:postcode":"11791",
    "sg:province":"NY",
    "sg:tags":[
        "book"
    ],
    "wof:name":"Springboards Unlimited Inc",
    "wof:placetype":"venue"
},
  "geometry": {"coordinates":[-73.497106,40.807503],"type":"Point"}
}