{
  "type": "Feature",
  "properties": {
    "iso:country":"US",
    "sg:address":"14 Liberty St",
    "sg:city":"Arcade",
    "sg:classifiers":[
        {
            "category":"Professional",
            "subcategory":"Accounting & Tax Preparation",
            "type":"Services"
        }
    ],
    "sg:phone":"+1 585 492 2407",
    "sg:postcode":"14009",
    "sg:province":"NY",
    "sg:tags":[
        "accountant",
        "public",
        "accountants-certified"
    ],
    "wof:name":"Leonard Zablonski Jr",
    "wof:placetype":"venue"
},
  "geometry": {"coordinates":[-78.422546,42.533664],"type":"Point"}
}