{
  "type": "Feature",
  "properties": {
    "addr:full":"26 Church St Canajoharie NY 13317",
    "addr:housenumber":"26",
    "addr:postcode":"13317",
    "addr:street":"Church St",
    "iso:country":"US",
    "sg:address":"26 Church St",
    "sg:city":"Canajoharie",
    "sg:classifiers":[
        {
            "category":"Shopping",
            "subcategory":"Pharmacy",
            "type":"Retail Goods"
        }
    ],
    "sg:phone":"+1 518 673 8086",
    "sg:postcode":"13317",
    "sg:province":"NY",
    "sg:tags":[
        "drug",
        "gift"
    ],
    "wof:name":"Village Apothecary Inc",
    "wof:placetype":"venue"
},
  "geometry": {"coordinates":[-74.571972,42.905744],"type":"Point"}
}