{
  "type": "Feature",
  "properties": {
    "addr:full":"19 Aviation Rd Albany NY 12205",
    "addr:housenumber":"19",
    "addr:postcode":"12205",
    "addr:street":"Aviation Rd",
    "iso:country":"US",
    "sg:address":"19 Aviation Rd",
    "sg:city":"Albany",
    "sg:classifiers":[
        {
            "category":"Shopping",
            "subcategory":"Computers & Home Electronics",
            "type":"Retail Goods"
        }
    ],
    "sg:phone":"+1 518 458 7099",
    "sg:postcode":"12205",
    "sg:province":"NY",
    "sg:tags":[
        "equipment",
        "dealer"
    ],
    "wof:name":"Telex Computer Prods",
    "wof:placetype":"venue"
},
  "geometry": {"coordinates":[-73.80284,42.71604],"type":"Point"}
}