{
  "type": "Feature",
  "properties": {
    "addr:full":"230 New York Ave Huntington NY 11743",
    "addr:housenumber":"230",
    "addr:postcode":"11743",
    "addr:street":"New York Ave",
    "iso:country":"US",
    "sg:address":"230 New York Ave",
    "sg:city":"Huntington",
    "sg:classifiers":[
        {
            "category":"Communications",
            "subcategory":"Film & Video Production",
            "type":"Services"
        },
        {
            "category":"Communications",
            "subcategory":"Television Station",
            "type":"Services"
        }
    ],
    "sg:phone":"+1 631 351 5878",
    "sg:postcode":"11743",
    "sg:province":"NY",
    "sg:tags":[
        "companies-film",
        "producer",
        "tv",
        "program",
        "radio",
        "distributor"
    ],
    "wof:name":"Jalbert Productions Inc",
    "wof:placetype":"venue"
},
  "geometry": {"coordinates":[-73.424615,40.874644],"type":"Point"}
}