{
  "type": "Feature",
  "properties": {
    "addr:full":"166 E 174th St Bronx NY 10457",
    "addr:housenumber":"166",
    "addr:postcode":"10457",
    "addr:street":"E 174Th St",
    "iso:country":"US",
    "sg:address":"166 E 174th St",
    "sg:city":"Bronx",
    "sg:classifiers":[
        {
            "category":"Retail",
            "subcategory":"Laundry & Dry Cleaning",
            "type":"Services"
        }
    ],
    "sg:phone":"+1 347 758 6727",
    "sg:postcode":"10457",
    "sg:province":"NY",
    "wof:name":"Cross Bronx Cleaners",
    "wof:placetype":"venue"
},
  "geometry": {"coordinates":[-73.90924099999999,40.844705],"type":"Point"}
}