{
  "type": "Feature",
  "properties": {
    "addr:full":"242 E 60th Street New York NY 10022",
    "addr:housenumber":"242",
    "addr:postcode":"10022",
    "addr:street":"E 60Th Street",
    "iso:country":"US",
    "sg:address":"242 E 60th Street",
    "sg:city":"New York",
    "sg:classifiers":[
        {
            "category":"Health Services",
            "subcategory":"Health Practitioner",
            "type":"Services"
        }
    ],
    "sg:phone":"+1 212 980 9828",
    "sg:postcode":"10022",
    "sg:province":"NY",
    "sg:tags":[
        "nutritionist"
    ],
    "wof:name":"Eat Food",
    "wof:placetype":"venue"
},
  "geometry": {"coordinates":[-73.965653,40.761951],"type":"Point"}
}