{
  "type": "Feature",
  "properties": {
    "addr:full":"61 Clinton St Center Moriches NY 11934",
    "addr:housenumber":"61",
    "addr:postcode":"11934",
    "addr:street":"Clinton St",
    "iso:country":"US",
    "sg:address":"61 Clinton St",
    "sg:city":"Center Moriches",
    "sg:classifiers":[
        {
            "category":"Building & Trades",
            "subcategory":"Construction",
            "type":"Services"
        }
    ],
    "sg:phone":"+1 631 878 6666",
    "sg:postcode":"11934",
    "sg:province":"NY",
    "sg:tags":[
        "contractor"
    ],
    "wof:name":"Newborn Constr Inc",
    "wof:placetype":"venue"
},
  "geometry": {"coordinates":[-72.79180100000001,40.804001],"type":"Point"}
}