{
  "type": "Feature",
  "properties": {
    "addr:full":"11 Kisco Ave Mt Kisco NY 10549",
    "addr:housenumber":"11",
    "addr:postcode":"10549",
    "addr:street":"Kisco Ave Mt Kisco",
    "iso:country":"US",
    "sg:address":"11 Kisco Ave",
    "sg:city":"Mt Kisco",
    "sg:classifiers":[
        {
            "category":"Shopping",
            "subcategory":"Gifts & Souvenirs",
            "type":"Retail Goods"
        }
    ],
    "sg:phone":"+1 914 242 9661",
    "sg:postcode":"10549",
    "sg:province":"NY",
    "sg:tags":[
        "basket",
        "parcel"
    ],
    "wof:name":"Ladle Of Love",
    "wof:placetype":"venue"
},
  "geometry": {"coordinates":[-73.72914,41.209784],"type":"Point"}
}