{
  "type": "Feature",
  "properties": {
    "addr:full":"42 Brick Church Rd Troy NY 12180",
    "addr:housenumber":"42",
    "addr:postcode":"12180",
    "addr:street":"Brick Church Rd",
    "iso:country":"US",
    "sg:address":"42 Brick Church Rd",
    "sg:city":"Troy",
    "sg:classifiers":[
        {
            "category":"Freight",
            "type":"Transportation"
        }
    ],
    "sg:phone":"+1   ",
    "sg:postcode":"12180",
    "sg:province":"NY",
    "sg:tags":[
        "special"
    ],
    "wof:name":"Brunswick Self Storage",
    "wof:placetype":"venue"
},
  "geometry": {"coordinates":[-73.59432700000001,42.760476],"type":"Point"}
}