{
  "type": "Feature",
  "properties": {
    "addr:full":"333 Hudson Street Canal Street NY 10013",
    "addr:housenumber":"333",
    "addr:postcode":"10013",
    "addr:street":"Hudson Street Canal Street",
    "iso:country":"US",
    "sg:address":"333 Hudson Street",
    "sg:city":"Canal Street",
    "sg:classifiers":[
        {
            "category":"Communications",
            "subcategory":"Newspaper",
            "type":"Services"
        }
    ],
    "sg:phone":"+1 212 328 0800",
    "sg:postcode":"10013",
    "sg:province":"NY",
    "sg:tags":[
        "print",
        "medium"
    ],
    "wof:name":"M Bl Communications",
    "wof:placetype":"venue"
},
  "geometry": {"coordinates":[-74.007364,40.727049],"type":"Point"}
}