{
  "type": "Feature",
  "properties": {
    "addr:full":"14136 77th Ave Flushing NY 11367",
    "addr:housenumber":"14136",
    "addr:postcode":"11367",
    "addr:street":"77Th Ave",
    "iso:country":"US",
    "sg:address":"14136 77th Ave",
    "sg:city":"Flushing",
    "sg:classifiers":[
        {
            "category":"Organizations",
            "subcategory":"Religious Organization",
            "type":"Services"
        }
    ],
    "sg:phone":"+1 718 969 2025",
    "sg:postcode":"11367",
    "sg:province":"NY",
    "wof:name":"Church Queen of Peace Rc",
    "wof:placetype":"venue"
},
  "geometry": {"coordinates":[-73.820396,40.721298],"type":"Point"}
}