{
  "type": "Feature",
  "properties": {
    "addr:full":"1218 Lexington Avenue New York NY 10028",
    "addr:housenumber":"1218",
    "addr:postcode":"10028",
    "addr:street":"Lexington Avenue",
    "iso:country":"US",
    "sg:address":"1218 Lexington Avenue",
    "sg:city":"New York",
    "sg:classifiers":[
        {
            "category":"Arts & Performance",
            "subcategory":"Art Gallery",
            "type":"Entertainment"
        },
        {
            "category":"Shopping",
            "subcategory":"Antiques",
            "type":"Retail Goods"
        }
    ],
    "sg:phone":"+1 212 249 6275",
    "sg:postcode":"10028",
    "sg:province":"NY",
    "sg:website":"www.thelandsbeyondprecolumbian.com",
    "wof:name":"Lands Beyond Ltd",
    "wof:placetype":"venue"
},
  "geometry": {"coordinates":[-73.957024,40.777261],"type":"Point"}
}