{
  "type": "Feature",
  "properties": {
    "addr:full":"3711 23rd Avenue Astoria NY 11105",
    "addr:housenumber":"3711",
    "addr:postcode":"11105",
    "addr:street":"23Rd Avenue",
    "iso:country":"US",
    "sg:address":"3711 23rd Avenue",
    "sg:city":"Astoria",
    "sg:classifiers":[
        {
            "category":"Health Services",
            "subcategory":"Doctor",
            "type":"Services"
        }
    ],
    "sg:phone":"+1 718 721 6166",
    "sg:postcode":"11105",
    "sg:province":"NY",
    "wof:name":"Astoria Pediatric Associates PC",
    "wof:placetype":"venue"
},
  "geometry": {"coordinates":[-73.90902699999999,40.7718],"type":"Point"}
}