{
  "type": "Feature",
  "properties": {
    "addr:full":"1 Game Ct East Setauket NY 11733",
    "addr:housenumber":"1",
    "addr:postcode":"11733",
    "addr:street":"Game Ct East",
    "iso:country":"US",
    "sg:address":"1 Game Ct",
    "sg:city":"East Setauket",
    "sg:classifiers":[
        {
            "category":"Professional",
            "type":"Services"
        }
    ],
    "sg:phone":"+1   ",
    "sg:postcode":"11733",
    "sg:province":"NY",
    "wof:name":"Zohrah Moghadasinia",
    "wof:placetype":"venue"
},
  "geometry": {"coordinates":[-73.079386,40.910381],"type":"Point"}
}