{
  "type": "Feature",
  "properties": {
    "iso:country":"US",
    "sg:address":"755 7th St",
    "sg:city":"Niagara Falls",
    "sg:classifiers":[
        {
            "category":"Health Services",
            "subcategory":"Doctor",
            "type":"Services"
        }
    ],
    "sg:phone":"+1   ",
    "sg:postcode":"14301",
    "sg:province":"NY",
    "wof:name":"Guido Losasso DDS",
    "wof:placetype":"venue"
},
  "geometry": {"coordinates":[-79.054401,43.095436],"type":"Point"}
}