{
  "type": "Feature",
  "properties": {
    "addr:full":"249 Sportsmans Ave Freeport NY 11520",
    "addr:housenumber":"249",
    "addr:postcode":"11520",
    "addr:street":"Sportsmans Ave",
    "iso:country":"US",
    "sg:address":"249 Sportsmans Ave",
    "sg:city":"Freeport",
    "sg:classifiers":[
        {
            "category":"Building & Trades",
            "subcategory":"Construction",
            "type":"Services"
        }
    ],
    "sg:phone":"+1 516 623 1325",
    "sg:postcode":"11520",
    "sg:province":"NY",
    "sg:tags":[
        "home",
        "improvement"
    ],
    "wof:name":"Innovative Home Improvement",
    "wof:placetype":"venue"
},
  "geometry": {"coordinates":[-73.5812,40.643427],"type":"Point"}
}