{
  "type": "Feature",
  "properties": {
    "addr:full":"273 Court St Brooklyn NY 11231",
    "addr:housenumber":"273",
    "addr:postcode":"11231",
    "addr:street":"Court St",
    "iso:country":"US",
    "sg:address":"273 Court St",
    "sg:city":"Brooklyn",
    "sg:classifiers":[
        {
            "category":"Organizations",
            "subcategory":"Religious Organization",
            "type":"Services"
        }
    ],
    "sg:phone":"+1 718 625 4776",
    "sg:postcode":"11231",
    "sg:province":"NY",
    "sg:tags":[
        "church"
    ],
    "wof:name":"Strong Place Baptist Church",
    "wof:placetype":"venue"
},
  "geometry": {"coordinates":[-73.994708,40.684739],"type":"Point"}
}