{
  "type": "Feature",
  "properties": {
    "addr:full":"390 Elmira Rd Ithaca NY 14850",
    "addr:housenumber":"390",
    "addr:postcode":"14850",
    "addr:street":"Elmira Rd",
    "iso:country":"US",
    "sg:address":"390 Elmira Rd",
    "sg:city":"Ithaca",
    "sg:classifiers":[
        {
            "category":"Building & Trades",
            "subcategory":"Construction",
            "type":"Services"
        }
    ],
    "sg:phone":"+1 607 273 0872",
    "sg:postcode":"14850",
    "sg:province":"NY",
    "sg:tags":[
        "downspouts",
        "gutter"
    ],
    "wof:name":"J D Ferro Roofing Co",
    "wof:placetype":"venue"
},
  "geometry": {"coordinates":[-76.51964099999999,42.419993],"type":"Point"}
}