{
  "type": "Feature",
  "properties": {
    "iso:country":"US",
    "sg:address":"1364 Lexington Ave",
    "sg:city":"New York",
    "sg:classifiers":[
        {
            "category":"Utilities",
            "subcategory":"Mobile Phone",
            "type":"Services"
        }
    ],
    "sg:phone":"+1 212 876 4801",
    "sg:postcode":"10128",
    "sg:province":"NY",
    "sg:tags":[
        "telephone",
        "cellular"
    ],
    "wof:name":"KOBE Wireless",
    "wof:placetype":"venue"
},
  "geometry": {"coordinates":[-73.953369,40.78264],"type":"Point"}
}