{
  "type": "Feature",
  "properties": {
    "addr:full":"3584 Long Beach Road Oceanside NY 11572",
    "addr:housenumber":"3584",
    "addr:postcode":"11572",
    "addr:street":"Long Beach Road",
    "iso:country":"US",
    "sg:address":"3584 Long Beach Road",
    "sg:city":"Oceanside",
    "sg:classifiers":[
        {
            "category":"Banks & Credit Unions",
            "subcategory":"Bank",
            "type":"Services"
        }
    ],
    "sg:phone":"+1 516 764 6868",
    "sg:postcode":"11572",
    "sg:province":"NY",
    "sg:website":"www.wachovia.com",
    "wof:name":"Wachovia",
    "wof:placetype":"venue"
},
  "geometry": {"coordinates":[-73.639881,40.624302],"type":"Point"}
}