{
  "type": "Feature",
  "properties": {
    "addr:full":"120 Plant Ave Hauppauge NY 11788",
    "addr:housenumber":"120",
    "addr:postcode":"11788",
    "addr:street":"Plant Ave",
    "iso:country":"US",
    "sg:address":"120 Plant Ave",
    "sg:city":"Hauppauge",
    "sg:classifiers":[
        {
            "category":"Local Transit",
            "type":"Transportation"
        }
    ],
    "sg:phone":"+1   ",
    "sg:postcode":"11788",
    "sg:province":"NY",
    "sg:tags":[
        "disabled",
        "to",
        "provides",
        "person"
    ],
    "wof:name":"Rides Unlimited Nassau Suffolk",
    "wof:placetype":"venue"
},
  "geometry": {"coordinates":[-73.24306,40.816718],"type":"Point"}
}