{
  "type": "Feature",
  "properties": {
    "addr:full":"309 E 18 St New York NY 10003",
    "addr:housenumber":"309;18",
    "addr:postcode":"10003",
    "addr:street":"E;St",
    "iso:country":"US",
    "sg:address":"309 E 18 St",
    "sg:city":"New York",
    "sg:classifiers":[
        {
            "category":"Shopping",
            "subcategory":"Clothing, Apparel, & Fashions",
            "type":"Retail Goods"
        }
    ],
    "sg:phone":"+1   ",
    "sg:postcode":"10003",
    "sg:province":"NY",
    "wof:name":"Like Clockwork Inc",
    "wof:placetype":"venue"
},
  "geometry": {"coordinates":[-73.980823,40.733963],"type":"Point"}
}