{
  "type": "Feature",
  "properties": {
    "addr:full":"515 E 75 St New York NY 10021",
    "addr:housenumber":"515;75",
    "addr:postcode":"10021",
    "addr:street":"E;St",
    "iso:country":"US",
    "sg:address":"515 E 75 St",
    "sg:city":"New York",
    "sg:classifiers":[
        {
            "category":"Arts & Performance",
            "subcategory":"Theater",
            "type":"Entertainment"
        }
    ],
    "sg:phone":"+1 212 288 0969",
    "sg:postcode":"10021",
    "sg:province":"NY",
    "sg:tags":[
        "group"
    ],
    "wof:name":"Brevis Music Inc",
    "wof:placetype":"venue"
},
  "geometry": {"coordinates":[-73.949997,40.767944],"type":"Point"}
}