{
  "type": "Feature",
  "properties": {
    "addr:full":"37 State Hwy 303 Tappan NY 10983",
    "addr:housenumber":"37",
    "addr:postcode":"10983",
    "addr:street":"State Hwy 303",
    "iso:country":"US",
    "sg:address":"37 State Hwy 303",
    "sg:city":"Tappan",
    "sg:classifiers":[
        {
            "category":"Food & Beverages",
            "subcategory":"Groceries & Convenience Stores",
            "type":"Retail Goods"
        }
    ],
    "sg:phone":"+1   ",
    "sg:postcode":"10983",
    "sg:province":"NY",
    "sg:tags":[
        "supermarket"
    ],
    "wof:name":"Food World Supermarket Inc",
    "wof:placetype":"venue"
},
  "geometry": {"coordinates":[-73.943994,41.017144],"type":"Point"}
}