{
  "type": "Feature",
  "properties": {
    "addr:full":"53 Highview Ter Pleasantville NY 10570",
    "addr:housenumber":"53",
    "addr:postcode":"10570",
    "addr:street":"Highview Ter",
    "iso:country":"US",
    "sg:address":"53 Highview Ter",
    "sg:city":"Pleasantville",
    "sg:classifiers":[
        {
            "category":"Building & Trades",
            "subcategory":"Landscaping Services",
            "type":"Services"
        }
    ],
    "sg:phone":"+1 914 769 4717",
    "sg:postcode":"10570",
    "sg:province":"NY",
    "wof:name":"Bernard Glinski Inc",
    "wof:placetype":"venue"
},
  "geometry": {"coordinates":[-73.775462,41.146198],"type":"Point"}
}