{
  "type": "Feature",
  "properties": {
    "addr:full":"100 Clinton St Brooklyn NY 11201",
    "addr:housenumber":"100",
    "addr:postcode":"11201",
    "addr:street":"Clinton St",
    "iso:country":"US",
    "sg:address":"100 Clinton St",
    "sg:city":"Brooklyn",
    "sg:classifiers":[
        {
            "category":"Health Services",
            "subcategory":"Doctor",
            "type":"Services"
        }
    ],
    "sg:phone":"+1 718 643 6005",
    "sg:postcode":"11201",
    "sg:province":"NY",
    "wof:name":"Caccavo Nicholas Dr",
    "wof:placetype":"venue"
},
  "geometry": {"coordinates":[-73.99279799999999,40.6936],"type":"Point"}
}