{
  "type": "Feature",
  "properties": {
    "iso:country":"US",
    "sg:address":"29 Grove St",
    "sg:city":"Homer",
    "sg:classifiers":[
        {
            "category":"Organizations",
            "subcategory":"Religious Organization",
            "type":"Services"
        }
    ],
    "sg:phone":"+1 607 749 7022",
    "sg:postcode":"13077",
    "sg:province":"NY",
    "sg:tags":[
        "clergy"
    ],
    "wof:name":"Brett J Reider",
    "wof:placetype":"venue"
},
  "geometry": {"coordinates":[-76.187735,42.637508],"type":"Point"}
}