{
  "type": "Feature",
  "properties": {
    "addr:full":"8218 192nd St Hollis NY 11423",
    "addr:housenumber":"8218",
    "addr:postcode":"11423",
    "addr:street":"192Nd St",
    "iso:country":"US",
    "sg:address":"8218 192nd St",
    "sg:city":"Hollis",
    "sg:classifiers":[
        {
            "category":"Building & Trades",
            "subcategory":"Construction",
            "type":"Services"
        }
    ],
    "sg:phone":"+1 718 464 2222",
    "sg:postcode":"11423",
    "sg:province":"NY",
    "sg:tags":[
        "asbestos",
        "detection",
        "removal"
    ],
    "wof:name":"Main Contracting Corporation",
    "wof:placetype":"venue"
},
  "geometry": {"coordinates":[-73.776833,40.726462],"type":"Point"}
}