{
  "type": "Feature",
  "properties": {
    "iso:country":"US",
    "sg:address":"615 Cramer Ave",
    "sg:city":"Schenectady",
    "sg:classifiers":[
        {
            "category":"Retail",
            "subcategory":"Auto Repair",
            "type":"Services"
        }
    ],
    "sg:phone":"+1   ",
    "sg:postcode":"12306",
    "sg:province":"NY",
    "sg:tags":[
        "glass",
        "replacement"
    ],
    "wof:name":"EDS",
    "wof:placetype":"venue"
},
  "geometry": {"coordinates":[-73.973919,42.79178],"type":"Point"}
}