{
  "type": "Feature",
  "properties": {
    "addr:full":"310 E 75 St New York NY 10021",
    "addr:housenumber":"310;75",
    "addr:postcode":"10021",
    "addr:street":"E;St",
    "iso:country":"US",
    "sg:address":"310 E 75 St",
    "sg:city":"New York",
    "sg:classifiers":[
        {
            "category":"Home & Garden",
            "subcategory":"Hardware",
            "type":"Retail Goods"
        }
    ],
    "sg:phone":"+1 212 861 0651",
    "sg:postcode":"10021",
    "sg:province":"NY",
    "wof:name":"Gotham City Hardware",
    "wof:placetype":"venue"
},
  "geometry": {"coordinates":[-73.954793,40.769791],"type":"Point"}
}