{
  "type": "Feature",
  "properties": {
    "addr:full":"2162 Bruynswick Rd Wallkill NY 12589",
    "addr:housenumber":"2162",
    "addr:postcode":"12589",
    "addr:street":"Bruynswick Rd",
    "iso:country":"US",
    "sg:address":"2162 Bruynswick Rd",
    "sg:city":"Wallkill",
    "sg:classifiers":[
        {
            "category":"Restaurant",
            "type":"Food & Drink"
        }
    ],
    "sg:phone":"+1 845 895 1147",
    "sg:postcode":"12589",
    "sg:province":"NY",
    "wof:name":"Bruynswick Inn",
    "wof:placetype":"venue"
},
  "geometry": {"coordinates":[-74.225826,41.659053],"type":"Point"}
}