{
  "type": "Feature",
  "properties": {
    "iso:country":"US",
    "sg:address":"6 Eaton Ln",
    "sg:city":"Scarsdale",
    "sg:classifiers":[
        {
            "category":"Professional",
            "subcategory":"Lawyer & Legal Services",
            "type":"Services"
        }
    ],
    "sg:phone":"+1 914 723 1900",
    "sg:postcode":"10583",
    "sg:province":"NY",
    "sg:tags":[
        "attorney"
    ],
    "wof:name":"Gary Pillersdorf & Assoc",
    "wof:placetype":"venue"
},
  "geometry": {"coordinates":[-73.832188,40.994782],"type":"Point"}
}