{
  "type": "Feature",
  "properties": {
    "addr:full":"264 W 40th St New York NY 10018",
    "addr:housenumber":"264",
    "addr:postcode":"10018",
    "addr:street":"W 40Th St",
    "iso:country":"US",
    "sg:address":"264 W 40th St",
    "sg:city":"New York",
    "sg:classifiers":[
        {
            "category":"Shopping",
            "subcategory":"Clothing, Apparel, & Fashions",
            "type":"Retail Goods"
        }
    ],
    "sg:phone":"+1 212 575 5692",
    "sg:postcode":"10018",
    "sg:province":"NY",
    "sg:tags":[
        "clothing",
        "women's"
    ],
    "wof:name":"Eric Gaskins Design",
    "wof:placetype":"venue"
},
  "geometry": {"coordinates":[-73.99028800000001,40.755608],"type":"Point"}
}