{
  "type": "Feature",
  "properties": {
    "addr:full":"25 S Lincoln Ave Orchard Park NY 14127",
    "addr:housenumber":"25",
    "addr:postcode":"14127",
    "addr:street":"S Lincoln Ave",
    "iso:country":"US",
    "sg:address":"25 S Lincoln Ave",
    "sg:city":"Orchard Park",
    "sg:classifiers":[
        {
            "category":"Social Services",
            "subcategory":"Child Care",
            "type":"Services"
        }
    ],
    "sg:phone":"+1 716 662 5982",
    "sg:postcode":"14127",
    "sg:province":"NY",
    "sg:website":"www.edukidsinc.com",
    "wof:name":"Edukids",
    "wof:placetype":"venue"
},
  "geometry": {"coordinates":[-78.74723400000001,42.765671],"type":"Point"}
}