{
  "type": "Feature",
  "properties": {
    "addr:full":"635 9th Ave New York NY 10036",
    "addr:housenumber":"635",
    "addr:postcode":"10036",
    "addr:street":"9Th Ave",
    "iso:country":"US",
    "sg:address":"635 9th Ave",
    "sg:city":"New York",
    "sg:classifiers":[
        {
            "category":"Restaurant",
            "type":"Food & Drink"
        }
    ],
    "sg:phone":"+1 212 262 2525",
    "sg:postcode":"10036",
    "sg:province":"NY",
    "sg:tags":[
        "new",
        "american",
        "brunch",
        "breakfast"
    ],
    "sg:website":"OrderFilmCenterCafe.com",
    "wof:name":"Film Center Cafe",
    "wof:placetype":"venue"
},
  "geometry": {"coordinates":[-73.991384,40.76013],"type":"Point"}
}