{
  "type": "Feature",
  "properties": {
    "addr:full":"530 E 20th Street New York NY 10009",
    "addr:housenumber":"530",
    "addr:postcode":"10009",
    "addr:street":"E 20Th Street",
    "iso:country":"US",
    "sg:address":"530 E 20th Street",
    "sg:city":"New York",
    "sg:classifiers":[
        {
            "category":"Health Services",
            "subcategory":"Doctor",
            "type":"Services"
        }
    ],
    "sg:phone":"+1 212 777 8407",
    "sg:postcode":"10009",
    "sg:province":"NY",
    "wof:name":"Rappaport Irwin MD",
    "wof:placetype":"venue"
},
  "geometry": {"coordinates":[-73.97750000000001,40.733803],"type":"Point"}
}