{
  "type": "Feature",
  "properties": {
    "iso:country":"US",
    "sg:address":"9613 Allen St",
    "sg:city":"Dayton",
    "sg:classifiers":[
        {
            "category":"Shopping",
            "subcategory":"Hobbies, Toys, & Games",
            "type":"Retail Goods"
        }
    ],
    "sg:phone":"+1 716 532 1414",
    "sg:postcode":"14041",
    "sg:province":"NY",
    "sg:tags":[
        "equipment",
        "ceramic",
        "supply"
    ],
    "wof:name":"Linda's Crafts & Ceramics",
    "wof:placetype":"venue"
},
  "geometry": {"coordinates":[-78.97856,42.417832],"type":"Point"}
}