{
  "type": "Feature",
  "properties": {
    "addr:full":"96 E Main St East Islip NY 11730",
    "addr:housenumber":"96",
    "addr:postcode":"11730",
    "addr:street":"E Main St",
    "iso:country":"US",
    "sg:address":"96 E Main St",
    "sg:city":"East Islip",
    "sg:classifiers":[
        {
            "category":"Professional",
            "subcategory":"Management & Consulting",
            "type":"Services"
        }
    ],
    "sg:phone":"+1 631 277 5573",
    "sg:postcode":"11730",
    "sg:province":"NY",
    "sg:tags":[
        "consultant",
        "recreation",
        "program"
    ],
    "wof:name":"Recreation Services-Elderly",
    "wof:placetype":"venue"
},
  "geometry": {"coordinates":[-73.18733,40.73186],"type":"Point"}
}