{
  "type": "Feature",
  "properties": {
    "iso:country":"US",
    "sg:address":"5 Ford Ave",
    "sg:city":"Oneonta",
    "sg:classifiers":[
        {
            "category":"Professional",
            "subcategory":"Lawyer & Legal Services",
            "type":"Services"
        }
    ],
    "sg:phone":"+1 607 432 5331",
    "sg:postcode":"13820",
    "sg:province":"NY",
    "sg:tags":[
        "attorney"
    ],
    "sg:website":"www.hhk.com",
    "wof:name":"Hinman Howard & Kattell LLP",
    "wof:placetype":"venue"
},
  "geometry": {"coordinates":[-75.061049,42.455158],"type":"Point"}
}