{
  "type": "Feature",
  "properties": {
    "addr:full":"101 Park Ave Lbby New York NY 10178",
    "addr:housenumber":"101",
    "addr:postcode":"10178",
    "addr:street":"Park Ave",
    "iso:country":"US",
    "sg:address":"101 Park Ave Lbby",
    "sg:city":"New York",
    "sg:classifiers":[
        {
            "category":"Professional",
            "subcategory":"Lawyer & Legal Services",
            "type":"Services"
        }
    ],
    "sg:phone":"+1 212 808 7653",
    "sg:postcode":"10178",
    "sg:province":"NY",
    "wof:name":"Garraty John A Jr Attorney",
    "wof:placetype":"venue"
},
  "geometry": {"coordinates":[-73.9785,40.750599],"type":"Point"}
}