{
  "type": "Feature",
  "properties": {
    "addr:full":"5025 Jericho Tpke Commack NY 11725",
    "addr:housenumber":"5025",
    "addr:postcode":"11725",
    "addr:street":"Jericho Tpke",
    "iso:country":"US",
    "sg:address":"5025 Jericho Tpke",
    "sg:city":"Commack",
    "sg:classifiers":[
        {
            "category":"Shopping",
            "subcategory":"Clothing, Apparel, & Fashions",
            "type":"Retail Goods"
        },
        {
            "category":"Shopping",
            "subcategory":"Bicycles & Sporting Goods",
            "type":"Retail Goods"
        },
        {
            "category":"Shopping",
            "subcategory":"Shoes",
            "type":"Retail Goods"
        }
    ],
    "sg:phone":"+1 631 493 1200",
    "sg:postcode":"11725",
    "sg:province":"NY",
    "sg:tags":[
        "clothing",
        "store",
        "women's"
    ],
    "wof:name":"Famous Footwear",
    "wof:placetype":"venue"
},
  "geometry": {"coordinates":[-73.30210099999999,40.842201],"type":"Point"}
}