{
  "type": "Feature",
  "properties": {
    "iso:country":"US",
    "sg:address":"2200 Penfield Rd",
    "sg:city":"Penfield",
    "sg:classifiers":[
        {
            "category":"Shopping",
            "subcategory":"Pharmacy",
            "type":"Retail Goods"
        }
    ],
    "sg:phone":"+1 585 377 6170",
    "sg:postcode":"14526",
    "sg:province":"NY",
    "wof:name":"CVS Pharmacy",
    "wof:placetype":"venue"
},
  "geometry": {"coordinates":[-77.435633,43.130655],"type":"Point"}
}