{
  "type": "Feature",
  "properties": {
    "addr:full":"1311 Brightwater Ave Brooklyn NY 11235",
    "addr:housenumber":"1311",
    "addr:postcode":"11235",
    "addr:street":"Brightwater Ave",
    "iso:country":"US",
    "sg:address":"1311 Brightwater Ave",
    "sg:city":"Brooklyn",
    "sg:classifiers":[
        {
            "category":"Organizations",
            "subcategory":"Religious Organization",
            "type":"Services"
        }
    ],
    "sg:phone":"+1 718 646 2438",
    "sg:postcode":"11235",
    "sg:province":"NY",
    "sg:tags":[
        "clergy"
    ],
    "wof:name":"Maurice Ganchoff",
    "wof:placetype":"venue"
},
  "geometry": {"coordinates":[-73.956012,40.575721],"type":"Point"}
}