{
  "type": "Feature",
  "properties": {
    "addr:full":"493 Doane Ave Staten Island NY 10308",
    "addr:housenumber":"493",
    "addr:postcode":"10308",
    "addr:street":"Doane Ave",
    "iso:country":"US",
    "sg:address":"493 Doane Ave",
    "sg:city":"Staten Island",
    "sg:classifiers":[
        {
            "category":"Shopping",
            "subcategory":"Clothing, Apparel, & Fashions",
            "type":"Retail Goods"
        }
    ],
    "sg:phone":"+1 718 317 5779",
    "sg:postcode":"10308",
    "sg:province":"NY",
    "sg:tags":[
        "t"
    ],
    "wof:name":"G & S Mugs & Tees",
    "wof:placetype":"venue"
},
  "geometry": {"coordinates":[-74.157819,40.56112],"type":"Point"}
}