{
  "type": "Feature",
  "properties": {
    "addr:full":"496 Court St Brooklyn NY 11231",
    "addr:housenumber":"496",
    "addr:postcode":"11231",
    "addr:street":"Court St",
    "iso:country":"US",
    "sg:address":"496 Court St",
    "sg:city":"Brooklyn",
    "sg:classifiers":[
        {
            "category":"Building & Trades",
            "subcategory":"Plumbing",
            "type":"Services"
        }
    ],
    "sg:phone":"+1 718 857 1700",
    "sg:postcode":"11231",
    "sg:province":"NY",
    "sg:tags":[
        "plumbing",
        "contractor"
    ],
    "wof:name":"CTA Mechanical Piping & Htg",
    "wof:placetype":"venue"
},
  "geometry": {"coordinates":[-73.99871,40.676756],"type":"Point"}
}