{
  "type": "Feature",
  "properties": {
    "iso:country":"US",
    "sg:address":"1827 5th Ave",
    "sg:city":"Bay Shore",
    "sg:classifiers":[
        {
            "category":"Restaurant",
            "type":"Food & Drink"
        }
    ],
    "sg:phone":"+1 631 273 9218",
    "sg:postcode":"11706",
    "sg:province":"NY",
    "wof:name":"La Cubanita Deli",
    "wof:placetype":"venue"
},
  "geometry": {"coordinates":[-73.26010100000001,40.775101],"type":"Point"}
}