{
  "type": "Feature",
  "properties": {
    "iso:country":"US",
    "sg:address":"615 Bond Ct",
    "sg:city":"Merrick",
    "sg:classifiers":[
        {
            "category":"Manufacturing",
            "subcategory":"Apparel",
            "type":"Manufacturing & Wholesale Goods"
        }
    ],
    "sg:phone":"+1   ",
    "sg:postcode":"11566",
    "sg:province":"NY",
    "sg:tags":[
        "outerwear",
        "mfg"
    ],
    "wof:name":"Ray Can Inc",
    "wof:placetype":"venue"
},
  "geometry": {"coordinates":[-73.563985,40.697429],"type":"Point"}
}