{
  "type": "Feature",
  "properties": {
    "iso:country":"US",
    "sg:address":"1435 Old Rte 17M",
    "sg:city":"Chester",
    "sg:classifiers":[
        {
            "category":"Retail",
            "subcategory":"Veterinary Services",
            "type":"Services"
        }
    ],
    "sg:phone":"+1 845 469 4600",
    "sg:postcode":"10918",
    "sg:province":"NY",
    "sg:tags":[
        "veterinarian"
    ],
    "wof:name":"All Pets Veterinary Hospital",
    "wof:placetype":"venue"
},
  "geometry": {"coordinates":[-74.27256300000001,41.345342],"type":"Point"}
}