{
  "type": "Feature",
  "properties": {
    "addr:full":"383 Main St Armonk NY 10504",
    "addr:housenumber":"383",
    "addr:postcode":"10504",
    "addr:street":"Main St",
    "iso:country":"US",
    "sg:address":"383 Main St",
    "sg:city":"Armonk",
    "sg:classifiers":[
        {
            "category":"Food & Beverages",
            "subcategory":"Liquor & Beverages",
            "type":"Retail Goods"
        }
    ],
    "sg:phone":"+1   ",
    "sg:postcode":"10504",
    "sg:province":"NY",
    "sg:tags":[
        "alcoholic"
    ],
    "wof:name":"Armonk Wines & Spirits",
    "wof:placetype":"venue"
},
  "geometry": {"coordinates":[-73.713089,41.129536],"type":"Point"}
}