{
  "type": "Feature",
  "properties": {
    "iso:country":"US",
    "sg:address":"12 Lake Ave",
    "sg:city":"Auburn",
    "sg:classifiers":[
        {
            "category":"Freight",
            "type":"Transportation"
        }
    ],
    "sg:phone":"+1 315 252 9214",
    "sg:postcode":"13021",
    "sg:province":"NY",
    "sg:tags":[
        "mover"
    ],
    "wof:name":"Reliable Movers",
    "wof:placetype":"venue"
},
  "geometry": {"coordinates":[-76.55426199999999,42.925144],"type":"Point"}
}