{
  "type": "Feature",
  "properties": {
    "iso:country":"US",
    "sg:address":"451 Rockaway Ave",
    "sg:city":"Brooklyn",
    "sg:classifiers":[
        {
            "category":"Shopping",
            "subcategory":"Discount & Variety Stores",
            "type":"Retail Goods"
        }
    ],
    "sg:phone":"+1 718 498 0069",
    "sg:postcode":"11212",
    "sg:province":"NY",
    "wof:name":"Fatima's Spot",
    "wof:placetype":"venue"
},
  "geometry": {"coordinates":[-73.910476,40.669113],"type":"Point"}
}