{
  "type": "Feature",
  "properties": {
    "iso:country":"US",
    "sg:address":"208 W 118th St",
    "sg:city":"New York",
    "sg:classifiers":[
        {
            "category":"Arts & Performance",
            "subcategory":"Jazz & Blues",
            "type":"Entertainment"
        }
    ],
    "sg:phone":"+1 212 864 8346",
    "sg:postcode":"10022",
    "sg:province":"NY",
    "sg:website":"www.mintonsuptown.com",
    "wof:name":"Minton's Playhouse",
    "wof:placetype":"venue"
},
  "geometry": {"coordinates":[-73.952105,40.80475],"type":"Point"}
}