{
  "type": "Feature",
  "properties": {
    "addr:full":"1651 Carla Ln East Meadow NY 11554",
    "addr:housenumber":"1651",
    "addr:postcode":"11554",
    "addr:street":"Carla Ln",
    "iso:country":"US",
    "sg:address":"1651 Carla Ln",
    "sg:city":"East Meadow",
    "sg:classifiers":[
        {
            "category":"Shopping",
            "type":"Retail Goods"
        }
    ],
    "sg:phone":"+1 516 374 0880",
    "sg:postcode":"11554",
    "sg:province":"NY",
    "sg:tags":[
        "machine",
        "equipment",
        "product",
        "repair"
    ],
    "wof:name":"A A A Business Machines",
    "wof:placetype":"venue"
},
  "geometry": {"coordinates":[-73.56410200000001,40.701],"type":"Point"}
}