{
  "type": "Feature",
  "properties": {
    "addr:full":"94 James Clark Dr Middletown NY 10940",
    "addr:housenumber":"94",
    "addr:postcode":"10940",
    "addr:street":"James Clark Dr",
    "iso:country":"US",
    "sg:address":"94 James Clark Dr",
    "sg:city":"Middletown",
    "sg:classifiers":[
        {
            "category":"Social Services",
            "subcategory":"Child Care",
            "type":"Services"
        }
    ],
    "sg:phone":"+1 845 733 4977",
    "sg:postcode":"10940",
    "sg:province":"NY",
    "wof:name":"Belle Family Day Care",
    "wof:placetype":"venue"
},
  "geometry": {"coordinates":[-74.43556100000001,41.52429],"type":"Point"}
}