{
  "type": "Feature",
  "properties": {
    "addr:full":"109 Ditmas Ave Brooklyn NY 11218",
    "addr:housenumber":"109",
    "addr:postcode":"11218",
    "addr:street":"Ditmas Ave",
    "iso:country":"US",
    "sg:address":"109 Ditmas Ave",
    "sg:city":"Brooklyn",
    "sg:classifiers":[
        {
            "category":"Professional",
            "subcategory":"Advertising",
            "type":"Services"
        }
    ],
    "sg:phone":"+1 718 431 0030",
    "sg:postcode":"11218",
    "sg:province":"NY",
    "wof:name":"USTOISRAEL.COM",
    "wof:placetype":"venue"
},
  "geometry": {"coordinates":[-73.976969,40.635739],"type":"Point"}
}