{
  "type": "Feature",
  "properties": {
    "addr:full":"6 Covey Rd Hyde Park NY 12538",
    "addr:housenumber":"6",
    "addr:postcode":"12538",
    "addr:street":"Covey Rd",
    "iso:country":"US",
    "sg:address":"6 Covey Rd",
    "sg:city":"Hyde Park",
    "sg:classifiers":[
        {
            "category":"Organizations",
            "subcategory":"Membership Organization",
            "type":"Services"
        }
    ],
    "sg:phone":"+1   ",
    "sg:postcode":"12538",
    "sg:province":"NY",
    "wof:name":"Poughkeepsie Amateur Radio CLB",
    "wof:placetype":"venue"
},
  "geometry": {"coordinates":[-73.887309,41.795739],"type":"Point"}
}