{
  "type": "Feature",
  "properties": {
    "addr:full":"65 Saint Marks Place New York NY 10003",
    "addr:housenumber":"65",
    "addr:postcode":"10003",
    "addr:street":"Saint Marks Place",
    "iso:country":"US",
    "sg:address":"65 Saint Marks Place",
    "sg:city":"New York",
    "sg:classifiers":[
        {
            "category":"Restaurant",
            "type":"Food & Drink"
        }
    ],
    "sg:phone":"+1 212 420 0998",
    "sg:postcode":"10003",
    "sg:province":"NY",
    "wof:name":"Jules Restaurant",
    "wof:placetype":"venue"
},
  "geometry": {"coordinates":[-73.98626899999999,40.728005],"type":"Point"}
}