{
  "type": "Feature",
  "properties": {
    "iso:country":"US",
    "sg:address":"195 Chrystie St",
    "sg:city":"New York",
    "sg:classifiers":[
        {
            "category":"Professional",
            "type":"Services"
        }
    ],
    "sg:phone":"+1 212 529 7303",
    "sg:postcode":"10002",
    "sg:province":"NY",
    "sg:tags":[
        "arts",
        "artist"
    ],
    "wof:name":"Tom Boutis",
    "wof:placetype":"venue"
},
  "geometry": {"coordinates":[-73.992215,40.721365],"type":"Point"}
}