{
  "type": "Feature",
  "properties": {
    "addr:full":"301 Fort Hamilton Pkwy Brooklyn NY 11219",
    "addr:housenumber":"301",
    "addr:postcode":"11219",
    "addr:street":"Fort Hamilton Pkwy",
    "iso:country":"US",
    "sg:address":"301 Fort Hamilton Pkwy",
    "sg:city":"Brooklyn",
    "sg:classifiers":[
        {
            "category":"Professional",
            "subcategory":"Engineering",
            "type":"Services"
        }
    ],
    "sg:phone":"+1 718 921 5206",
    "sg:postcode":"11219",
    "sg:province":"NY",
    "sg:tags":[
        "civil",
        "consulting",
        "engineer"
    ],
    "wof:name":"Society Of American Military E",
    "wof:placetype":"venue"
},
  "geometry": {"coordinates":[-73.99419,40.640684],"type":"Point"}
}