{
  "type": "Feature",
  "properties": {
    "addr:full":"755 E 100th Street Brooklyn NY 11236",
    "addr:housenumber":"755",
    "addr:postcode":"11236",
    "addr:street":"E 100Th Street",
    "iso:country":"US",
    "sg:address":"755 E 100th Street",
    "sg:city":"Brooklyn",
    "sg:classifiers":[
        {
            "category":"Education",
            "subcategory":"School",
            "type":"Public Place"
        }
    ],
    "sg:phone":"+1 718 330 9298",
    "sg:postcode":"11236",
    "sg:province":"NY",
    "sg:tags":[
        "high",
        "middle",
        "elementary"
    ],
    "wof:name":"N Y City of",
    "wof:placetype":"venue"
},
  "geometry": {"coordinates":[-73.89849100000001,40.645503],"type":"Point"}
}