{
  "type": "Feature",
  "properties": {
    "iso:country":"US",
    "sg:address":"105 Calvert St",
    "sg:city":"Harrison",
    "sg:classifiers":[
        {
            "category":"Real Estate",
            "subcategory":"Real Estate Agent",
            "type":"Services"
        }
    ],
    "sg:phone":"+1 914 835 6879",
    "sg:postcode":"10528",
    "sg:province":"NY",
    "sg:tags":[
        "management"
    ],
    "wof:name":"PMC Consulting Inc",
    "wof:placetype":"venue"
},
  "geometry": {"coordinates":[-73.717744,40.968955],"type":"Point"}
}