{
  "type": "Feature",
  "properties": {
    "iso:country":"US",
    "sg:address":"948 45th St",
    "sg:city":"Brooklyn",
    "sg:classifiers":[
        {
            "category":"Autos & Motor Vehicles",
            "subcategory":"Automobile Sales",
            "type":"Retail Goods"
        }
    ],
    "sg:phone":"+1 718 972 0223",
    "sg:postcode":"11219",
    "sg:province":"NY",
    "sg:tags":[
        "car",
        "dealer"
    ],
    "wof:name":"Citilink Motors",
    "wof:placetype":"venue"
},
  "geometry": {"coordinates":[-73.997258,40.641848],"type":"Point"}
}