{
  "type": "Feature",
  "properties": {
    "addr:full":"24 Sarah Dr Farmingdale NY 11735",
    "addr:housenumber":"24",
    "addr:postcode":"11735",
    "addr:street":"Sarah Dr",
    "iso:country":"US",
    "sg:address":"24 Sarah Dr",
    "sg:city":"Farmingdale",
    "sg:classifiers":[
        {
            "category":"Shopping",
            "subcategory":"Computers & Home Electronics",
            "type":"Retail Goods"
        }
    ],
    "sg:phone":"+1 631 752 2795",
    "sg:postcode":"11735",
    "sg:province":"NY",
    "sg:tags":[
        "software"
    ],
    "wof:name":"Nova Data Inc",
    "wof:placetype":"venue"
},
  "geometry": {"coordinates":[-73.40796,40.754613],"type":"Point"}
}