{
  "type": "Feature",
  "properties": {
    "iso:country":"US",
    "sg:address":"620 Longacre Ave",
    "sg:city":"Woodmere",
    "sg:classifiers":[
        {
            "category":"Retail",
            "subcategory":"Car Wash",
            "type":"Services"
        }
    ],
    "sg:phone":"+1   ",
    "sg:postcode":"11598",
    "sg:province":"NY",
    "sg:tags":[
        "carwash",
        "auto",
        "body"
    ],
    "wof:name":"Every Little Detail",
    "wof:placetype":"venue"
},
  "geometry": {"coordinates":[-73.72457199999999,40.638048],"type":"Point"}
}