{
  "type": "Feature",
  "properties": {
    "addr:full":"111 Mount Hope Pl Bronx NY 10453",
    "addr:housenumber":"111",
    "addr:postcode":"10453",
    "addr:street":"Mount Hope Pl",
    "iso:country":"US",
    "sg:address":"111 Mount Hope Pl",
    "sg:city":"Bronx",
    "sg:classifiers":[
        {
            "category":"Freight",
            "type":"Transportation"
        }
    ],
    "sg:phone":"+1   ",
    "sg:postcode":"10453",
    "sg:province":"NY",
    "sg:tags":[
        "truck",
        "hauling",
        "dump"
    ],
    "wof:name":"Adrienne Trucking Corp",
    "wof:placetype":"venue"
},
  "geometry": {"coordinates":[-73.90698999999999,40.848677],"type":"Point"}
}