{
  "type": "Feature",
  "properties": {
    "iso:country":"US",
    "sg:address":"5400 Nesconset Hwy",
    "sg:city":"Port Jeffrsn Sta",
    "sg:classifiers":[
        {
            "category":"Health Services",
            "subcategory":"Clinic",
            "type":"Services"
        }
    ],
    "sg:phone":"+1 631 476 4015",
    "sg:postcode":"11776",
    "sg:province":"NY",
    "wof:name":"Executive Health",
    "wof:placetype":"venue"
},
  "geometry": {"coordinates":[-73.041622,40.928515],"type":"Point"}
}