{
  "type": "Feature",
  "properties": {
    "iso:country":"US",
    "sg:address":"655 Deer Park Ave",
    "sg:city":"Babylon",
    "sg:classifiers":[
        {
            "category":"Health Services",
            "subcategory":"Doctor",
            "type":"Services"
        }
    ],
    "sg:phone":"+1 631 665 5000",
    "sg:postcode":"11702",
    "sg:province":"NY",
    "sg:tags":[
        "physician",
        "surgeon"
    ],
    "wof:name":"Great South Bay Surgical Assoc",
    "wof:placetype":"venue"
},
  "geometry": {"coordinates":[-73.321639,40.711565],"type":"Point"}
}