{
  "type": "Feature",
  "properties": {
    "iso:country":"US",
    "sg:address":"4267 Swamp College Rd",
    "sg:city":"Trumansburg",
    "sg:classifiers":[
        {
            "category":"Building & Trades",
            "subcategory":"Construction",
            "type":"Services"
        }
    ],
    "sg:phone":"+1 607 387 5906",
    "sg:postcode":"14886",
    "sg:province":"NY",
    "sg:tags":[
        "carpentry",
        "contractor"
    ],
    "wof:name":"Sterlingwork",
    "wof:placetype":"venue"
},
  "geometry": {"coordinates":[-76.64673500000001,42.509086],"type":"Point"}
}