{
  "type": "Feature",
  "properties": {
    "iso:country":"US",
    "sg:address":"1080 Cutler St",
    "sg:city":"Schenectady",
    "sg:classifiers":[
        {
            "category":"Retail",
            "subcategory":"Repair Shop",
            "type":"Services"
        }
    ],
    "sg:phone":"+1 518 346 0132",
    "sg:postcode":"12303",
    "sg:province":"NY",
    "sg:tags":[
        "upholsterer"
    ],
    "wof:name":"Robert's Upholstery",
    "wof:placetype":"venue"
},
  "geometry": {"coordinates":[-73.953086,42.795666],"type":"Point"}
}