{
  "type": "Feature",
  "properties": {
    "addr:full":"4707 13th Ave Brooklyn NY 11219",
    "addr:housenumber":"4707",
    "addr:postcode":"11219",
    "addr:street":"13Th Ave",
    "iso:country":"US",
    "sg:address":"4707 13th Ave",
    "sg:city":"Brooklyn",
    "sg:classifiers":[
        {
            "category":"Insurance",
            "subcategory":"Insurance Agent",
            "type":"Services"
        }
    ],
    "sg:phone":"+1 718 436 5111",
    "sg:postcode":"11219",
    "sg:province":"NY",
    "sg:tags":[
        "broker"
    ],
    "wof:name":"Insure Secure",
    "wof:placetype":"venue"
},
  "geometry": {"coordinates":[-73.99145300000001,40.635571],"type":"Point"}
}