{
  "type": "Feature",
  "properties": {
    "addr:full":"4566 Stoneledge Ln Manlius NY 13104",
    "addr:housenumber":"4566",
    "addr:postcode":"13104",
    "addr:street":"Stoneledge Ln",
    "iso:country":"US",
    "sg:address":"4566 Stoneledge Ln",
    "sg:city":"Manlius",
    "sg:classifiers":[
        {
            "category":"Insurance",
            "subcategory":"Hazard Insurance",
            "type":"Services"
        }
    ],
    "sg:phone":"+1 315 682 8072",
    "sg:postcode":"13104",
    "sg:province":"NY",
    "sg:tags":[
        "bond"
    ],
    "wof:name":"J David Joor Stocks & Bonds",
    "wof:placetype":"venue"
},
  "geometry": {"coordinates":[-75.995221,42.995115],"type":"Point"}
}