{
  "type": "Feature",
  "properties": {
    "iso:country":"US",
    "sg:address":"557 Lake Ave",
    "sg:city":"St James",
    "sg:classifiers":[
        {
            "category":"Real Estate",
            "subcategory":"Real Estate Agent",
            "type":"Services"
        }
    ],
    "sg:phone":"+1 631 265 2674",
    "sg:postcode":"11780",
    "sg:province":"NY",
    "wof:name":"Fox Hollow Realty Inc",
    "wof:placetype":"venue"
},
  "geometry": {"coordinates":[-73.157608,40.883429],"type":"Point"}
}