{
  "type": "Feature",
  "properties": {
    "addr:full":"433 E 66 St New York NY 10065",
    "addr:housenumber":"433;66",
    "addr:postcode":"10065",
    "addr:street":"E;St",
    "iso:country":"US",
    "sg:address":"433 E 66 St",
    "sg:city":"New York",
    "sg:classifiers":[
        {
            "category":"Parking",
            "type":"Transportation"
        }
    ],
    "sg:phone":"+1 212 639 2338",
    "sg:postcode":"10065",
    "sg:province":"NY",
    "sg:tags":[
        "automobile"
    ],
    "wof:name":"Hospital Garage",
    "wof:placetype":"venue"
},
  "geometry": {"coordinates":[-73.957047,40.763417],"type":"Point"}
}