{
  "type": "Feature",
  "properties": {
    "iso:country":"US",
    "sg:address":"2820 Merrick Rd",
    "sg:city":"Bellmore",
    "sg:classifiers":[
        {
            "category":"Insurance",
            "subcategory":"Insurance Agent",
            "type":"Services"
        }
    ],
    "sg:phone":"+1 516 781 0300",
    "sg:postcode":"11710",
    "sg:province":"NY",
    "wof:name":"M R Korman Insurance",
    "wof:placetype":"venue"
},
  "geometry": {"coordinates":[-73.5222,40.664319],"type":"Point"}
}