{
  "type": "Feature",
  "properties": {
    "iso:country":"US",
    "sg:address":"86 Smith St",
    "sg:city":"Massapequa Park",
    "sg:classifiers":[
        {
            "category":"Building & Trades",
            "subcategory":"Construction",
            "type":"Services"
        }
    ],
    "sg:phone":"+1 516 795 1561",
    "sg:postcode":"11762",
    "sg:province":"NY",
    "sg:tags":[
        "residential"
    ],
    "wof:name":"Tc General Contracting",
    "wof:placetype":"venue"
},
  "geometry": {"coordinates":[-73.45477700000001,40.687345],"type":"Point"}
}