{
  "type": "Feature",
  "properties": {
    "addr:full":"1115 E 80th St Brooklyn NY 11236",
    "addr:housenumber":"1115",
    "addr:postcode":"11236",
    "addr:street":"E 80Th St",
    "iso:country":"US",
    "sg:address":"1115 E 80th St",
    "sg:city":"Brooklyn",
    "sg:classifiers":[
        {
            "category":"Travel",
            "subcategory":"Travel Agent",
            "type":"Entertainment"
        }
    ],
    "sg:phone":"+1 718 968 2565",
    "sg:postcode":"11236",
    "sg:province":"NY",
    "sg:tags":[
        "tours",
        "promoter"
    ],
    "wof:name":"Bon Jour West Africa Tours",
    "wof:placetype":"venue"
},
  "geometry": {"coordinates":[-73.90911699999999,40.63194],"type":"Point"}
}