{
  "type": "Feature",
  "properties": {
    "addr:full":"5614 Tec Dr Avon NY 14414",
    "addr:postcode":"5614;14414",
    "addr:street":"Tec Dr",
    "iso:country":"US",
    "sg:address":"5614 Tec Dr",
    "sg:city":"Avon",
    "sg:classifiers":[
        {
            "category":"Wholesale",
            "subcategory":"Hardware",
            "type":"Manufacturing & Wholesale Goods"
        },
        {
            "category":"Home & Garden",
            "subcategory":"Garden Supply",
            "type":"Retail Goods"
        },
        {
            "category":"Retail",
            "subcategory":"Repair Shop",
            "type":"Services"
        }
    ],
    "sg:phone":"+1 585 226 9680",
    "sg:postcode":"14414",
    "sg:province":"NY",
    "sg:tags":[
        "renting",
        "lawn",
        "outdoor",
        "power",
        "landscaping",
        "equipment-sales",
        "equipment",
        "saw"
    ],
    "sg:website":"http://www.stihldealer.net/default-dealer-044886.aspx",
    "wof:name":"Lakeland Equipment",
    "wof:placetype":"venue"
},
  "geometry": {"coordinates":[-77.70352200000001,42.912708],"type":"Point"}
}