{
  "type": "Feature",
  "properties": {
    "iso:country":"US",
    "sg:address":"2925 N Wading River Rd",
    "sg:city":"Wading River",
    "sg:classifiers":[
        {
            "category":"Restaurant",
            "type":"Food & Drink"
        }
    ],
    "sg:phone":"+1 631 929 8800",
    "sg:postcode":"11792",
    "sg:province":"NY",
    "wof:name":"Michael Anthony's Food Bar",
    "wof:placetype":"venue"
},
  "geometry": {"coordinates":[-72.814611,40.965274],"type":"Point"}
}