{
  "type": "Feature",
  "properties": {
    "addr:full":"156 Dyckman Street New York NY 10040",
    "addr:housenumber":"156",
    "addr:postcode":"10040",
    "addr:street":"Dyckman Street",
    "iso:country":"US",
    "sg:address":"156 Dyckman Street",
    "sg:city":"New York",
    "sg:classifiers":[
        {
            "category":"Shopping",
            "subcategory":"Shoes",
            "type":"Retail Goods"
        }
    ],
    "sg:phone":"+1 212 942 5495",
    "sg:postcode":"10040",
    "sg:province":"NY",
    "sg:tags":[
        "store"
    ],
    "wof:name":"Dyckman Outlet",
    "wof:placetype":"venue"
},
  "geometry": {"coordinates":[-73.925697,40.86334],"type":"Point"}
}