{
  "type": "Feature",
  "properties": {
    "iso:country":"US",
    "sg:address":"1103 45th Avenue",
    "sg:city":"Long Island City",
    "sg:classifiers":[
        {
            "category":"Arts & Performance",
            "subcategory":"Art Gallery",
            "type":"Entertainment"
        }
    ],
    "sg:phone":"+1 718 937 6317",
    "sg:postcode":"11101",
    "sg:province":"NY",
    "wof:name":"Dorsky Gallery Curatorial Programs",
    "wof:placetype":"venue"
},
  "geometry": {"coordinates":[-73.949386,40.747825],"type":"Point"}
}