{
  "type": "Feature",
  "properties": {
    "iso:country":"US",
    "sg:address":"5302 11th St",
    "sg:city":"Long Island City",
    "sg:classifiers":[
        {
            "category":"Retail",
            "subcategory":"Auto Repair",
            "type":"Services"
        }
    ],
    "sg:phone":"+1 718 433 1150",
    "sg:postcode":"11101",
    "sg:province":"NY",
    "wof:name":"Republic Auto Repair",
    "wof:placetype":"venue"
},
  "geometry": {"coordinates":[-73.952698,40.740101],"type":"Point"}
}