{
  "type": "Feature",
  "properties": {
    "addr:full":"10 Hunter St Bergen NY 14416",
    "addr:housenumber":"10",
    "addr:postcode":"14416",
    "addr:street":"Hunter St",
    "iso:country":"US",
    "sg:address":"10 Hunter St",
    "sg:city":"Bergen",
    "sg:classifiers":[
        {
            "category":"Sports & Exercise",
            "subcategory":"Gym",
            "type":"Entertainment"
        }
    ],
    "sg:phone":"+1   ",
    "sg:postcode":"14416",
    "sg:province":"NY",
    "sg:tags":[
        "fitness",
        "physical",
        "facility"
    ],
    "wof:name":"Rec Center-Business",
    "wof:placetype":"venue"
},
  "geometry": {"coordinates":[-77.942319,43.088791],"type":"Point"}
}