{
  "type": "Feature",
  "properties": {
    "iso:country":"US",
    "sg:address":"5790 Depot Rd",
    "sg:city":"Voorheesville",
    "sg:classifiers":[
        {
            "category":"Wholesale",
            "subcategory":"Construction Materials",
            "type":"Manufacturing & Wholesale Goods"
        }
    ],
    "sg:phone":"+1 518 861 0370",
    "sg:postcode":"12186",
    "sg:province":"NY",
    "sg:tags":[
        "fence"
    ],
    "wof:name":"North American Pipe Corp",
    "wof:placetype":"venue"
},
  "geometry": {"coordinates":[-73.955724,42.678135],"type":"Point"}
}