{
  "type": "Feature",
  "properties": {
    "addr:full":"401 Hancock St Ithaca NY 14850",
    "addr:housenumber":"401",
    "addr:postcode":"14850",
    "addr:street":"Hancock St",
    "iso:country":"US",
    "sg:address":"401 Hancock St",
    "sg:city":"Ithaca",
    "sg:classifiers":[
        {
            "category":"Professional",
            "subcategory":"Lawyer & Legal Services",
            "type":"Services"
        }
    ],
    "sg:phone":"+1 607 277 8121",
    "sg:postcode":"14850",
    "sg:province":"NY",
    "sg:tags":[
        "attorney"
    ],
    "wof:name":"Martha Nebelsick Law Office",
    "wof:placetype":"venue"
},
  "geometry": {"coordinates":[-76.504085,42.44688],"type":"Point"}
}