{
  "type": "Feature",
  "properties": {
    "addr:full":"116 Chestnut St Fredonia NY 14063",
    "addr:housenumber":"116",
    "addr:postcode":"14063",
    "addr:street":"Chestnut St",
    "iso:country":"US",
    "sg:address":"116 Chestnut St",
    "sg:city":"Fredonia",
    "sg:classifiers":[
        {
            "category":"Restaurant",
            "type":"Food & Drink"
        }
    ],
    "sg:phone":"+1 716 679 3388",
    "sg:postcode":"14063",
    "sg:province":"NY",
    "sg:tags":[
        "caterer"
    ],
    "wof:name":"Suski & Suski",
    "wof:placetype":"venue"
},
  "geometry": {"coordinates":[-79.341954,42.440314],"type":"Point"}
}