{
  "type": "Feature",
  "properties": {
    "addr:full":"38 Glascoe Ave Staten Island NY 10314",
    "addr:housenumber":"38",
    "addr:postcode":"10314",
    "addr:street":"Glascoe Ave",
    "iso:country":"US",
    "sg:address":"38 Glascoe Ave",
    "sg:city":"Staten Island",
    "sg:classifiers":[
        {
            "category":"Building & Trades",
            "subcategory":"Construction",
            "type":"Services"
        }
    ],
    "sg:phone":"+1 718 273 7620",
    "sg:postcode":"10314",
    "sg:province":"NY",
    "sg:tags":[
        "contractor"
    ],
    "wof:name":"Cela Construction",
    "wof:placetype":"venue"
},
  "geometry": {"coordinates":[-74.139422,40.621278],"type":"Point"}
}