{
  "type": "Feature",
  "properties": {
    "addr:full":"311 Bedford Ave Brooklyn NY 11211",
    "addr:housenumber":"311",
    "addr:postcode":"11211",
    "addr:street":"Bedford Ave",
    "iso:country":"US",
    "sg:address":"311 Bedford Ave",
    "sg:city":"Brooklyn",
    "sg:classifiers":[
        {
            "category":"Building & Trades",
            "subcategory":"Locksmith",
            "type":"Services"
        }
    ],
    "sg:phone":"+1 347 464 3747",
    "sg:postcode":"11211",
    "sg:province":"NY",
    "sg:tags":[
        "key"
    ],
    "wof:name":"20 Street Lock and Key of Brooklyn",
    "wof:placetype":"venue"
},
  "geometry": {"coordinates":[-73.961915,40.713198],"type":"Point"}
}