{
  "type": "Feature",
  "properties": {
    "addr:full":"512 Fashion Avenue New York NY 10018",
    "addr:housenumber":"512",
    "addr:postcode":"10018",
    "addr:street":"Fashion Avenue",
    "iso:country":"US",
    "sg:address":"512 Fashion Avenue",
    "sg:city":"New York",
    "sg:classifiers":[
        {
            "category":"Shopping",
            "subcategory":"Clothing, Apparel, & Fashions",
            "type":"Retail Goods"
        }
    ],
    "sg:phone":"+1 212 730 4806",
    "sg:postcode":"10018",
    "sg:province":"NY",
    "sg:tags":[
        "clothing",
        "women's"
    ],
    "wof:name":"Fame New York",
    "wof:placetype":"venue"
},
  "geometry": {"coordinates":[-73.9888,40.753429],"type":"Point"}
}