{
  "type": "Feature",
  "properties": {
    "iso:country":"US",
    "sg:address":"12418 Queens Blvd",
    "sg:city":"Kew Gardens",
    "sg:classifiers":[
        {
            "category":"Restaurant",
            "type":"Food & Drink"
        }
    ],
    "sg:menulink":"http://www.allmenus.com/ny/queens/25171-pasta-lovers-trattorias/menu/",
    "sg:phone":"+1 718 520 1908",
    "sg:postcode":"11415",
    "sg:province":"NY",
    "sg:tags":[
        "italian"
    ],
    "wof:name":"Pasta Lover's Trattorias",
    "wof:placetype":"venue"
},
  "geometry": {"coordinates":[-73.82732799999999,40.71267],"type":"Point"}
}