{
  "type": "Feature",
  "properties": {
    "iso:country":"US",
    "sg:address":"996 W Jericho Tpke",
    "sg:city":"Smithtown",
    "sg:classifiers":[
        {
            "category":"Building & Trades",
            "subcategory":"Construction",
            "type":"Services"
        }
    ],
    "sg:phone":"+1 631 493 0077",
    "sg:postcode":"11787",
    "sg:province":"NY",
    "sg:tags":[
        "company"
    ],
    "wof:name":"Kummer Construction Co",
    "wof:placetype":"venue"
},
  "geometry": {"coordinates":[-73.251407,40.847521],"type":"Point"}
}