{
  "type": "Feature",
  "properties": {
    "iso:country":"US",
    "sg:address":"532 Lefferts Ave",
    "sg:city":"Brooklyn",
    "sg:classifiers":[
        {
            "category":"Freight",
            "type":"Transportation"
        }
    ],
    "sg:phone":"+1   ",
    "sg:postcode":"11225",
    "sg:province":"NY",
    "sg:tags":[
        "local",
        "trucking"
    ],
    "wof:name":"Roljo Express Company",
    "wof:placetype":"venue"
},
  "geometry": {"coordinates":[-73.943411,40.662724],"type":"Point"}
}