{
  "type": "Feature",
  "properties": {
    "iso:country":"US",
    "sg:address":"244 Elizabeth St",
    "sg:city":"New York",
    "sg:classifiers":[
        {
            "category":"Shopping",
            "subcategory":"Jewelry",
            "type":"Retail Goods"
        }
    ],
    "sg:phone":"+1   ",
    "sg:postcode":"10012",
    "sg:province":"NY",
    "wof:name":"One Family Jewels",
    "wof:placetype":"venue"
},
  "geometry": {"coordinates":[-73.9936,40.723714],"type":"Point"}
}