{
  "type": "Feature",
  "properties": {
    "addr:full":"1545 North Rd Waterloo NY 13165",
    "addr:housenumber":"1545",
    "addr:postcode":"13165",
    "addr:street":"North Rd",
    "iso:country":"US",
    "sg:address":"1545 North Rd",
    "sg:city":"Waterloo",
    "sg:classifiers":[
        {
            "category":"Social Services",
            "subcategory":"Adult Care",
            "type":"Services"
        }
    ],
    "sg:phone":"+1 315 539 5049",
    "sg:postcode":"13165",
    "sg:province":"NY",
    "sg:tags":[
        "home",
        "group"
    ],
    "wof:name":"Route 96 ICF",
    "wof:placetype":"venue"
},
  "geometry": {"coordinates":[-76.86429800000001,42.916269],"type":"Point"}
}