{
  "type": "Feature",
  "properties": {
    "iso:country":"US",
    "sg:address":"215 Skyline Dr",
    "sg:city":"Highland Mills",
    "sg:classifiers":[
        {
            "category":"Restaurant",
            "type":"Food & Drink"
        }
    ],
    "sg:phone":"+1   ",
    "sg:postcode":"10930",
    "sg:province":"NY",
    "sg:tags":[
        "eating"
    ],
    "wof:name":"Jangos Pizza",
    "wof:placetype":"venue"
},
  "geometry": {"coordinates":[-74.104229,41.355718],"type":"Point"}
}