{
  "type": "Feature",
  "properties": {
    "addr:full":"6292 N Glen Haven Rd Moravia NY 13118",
    "addr:housenumber":"6292",
    "addr:postcode":"13118",
    "addr:street":"N Glen Haven Rd",
    "iso:country":"US",
    "sg:address":"6292 N Glen Haven Rd",
    "sg:city":"Moravia",
    "sg:classifiers":[
        {
            "category":"Farming",
            "subcategory":"Livestock Farm",
            "type":"Manufacturing & Wholesale Goods"
        },
        {
            "category":"Farming",
            "subcategory":"Farm",
            "type":"Manufacturing & Wholesale Goods"
        }
    ],
    "sg:phone":"+1 315 497 0458",
    "sg:postcode":"13118",
    "sg:province":"NY",
    "wof:name":"Badman Farms",
    "wof:placetype":"venue"
},
  "geometry": {"coordinates":[-76.32783499999999,42.798872],"type":"Point"}
}