{
  "type": "Feature",
  "properties": {
    "addr:full":"4305 31st Ave Astoria NY 11103",
    "addr:housenumber":"4305",
    "addr:postcode":"11103",
    "addr:street":"31St Ave",
    "iso:country":"US",
    "sg:address":"4305 31st Ave",
    "sg:city":"Astoria",
    "sg:classifiers":[
        {
            "category":"Education",
            "subcategory":"Kindergarten",
            "type":"Public Place"
        }
    ],
    "sg:phone":"+1 718 932 5545",
    "sg:postcode":"11103",
    "sg:province":"NY",
    "sg:tags":[
        "school",
        "driving"
    ],
    "wof:name":"All Roads Driving School Inc",
    "wof:placetype":"venue"
},
  "geometry": {"coordinates":[-73.914299,40.760201],"type":"Point"}
}