{
  "type": "Feature",
  "properties": {
    "iso:country":"US",
    "sg:address":"13110 Hillside Ave",
    "sg:city":"Richmond Hill",
    "sg:classifiers":[
        {
            "category":"Fast Food",
            "type":"Food & Drink"
        }
    ],
    "sg:phone":"+1 718 441 0925",
    "sg:postcode":"11418",
    "sg:province":"NY",
    "wof:name":"Burger King",
    "wof:placetype":"venue"
},
  "geometry": {"coordinates":[-73.821485,40.703596],"type":"Point"}
}