{
  "type": "Feature",
  "properties": {
    "addr:full":"1050 Leggett Ave Bronx NY 10455",
    "addr:housenumber":"1050",
    "addr:postcode":"10455",
    "addr:street":"Leggett Ave",
    "iso:country":"US",
    "sg:address":"1050 Leggett Ave",
    "sg:city":"Bronx",
    "sg:classifiers":[
        {
            "category":"Retail",
            "subcategory":"Auto Repair",
            "type":"Services"
        }
    ],
    "sg:phone":"+1   ",
    "sg:postcode":"10455",
    "sg:province":"NY",
    "sg:tags":[
        "body"
    ],
    "wof:name":"Rite Muffler Inc",
    "wof:placetype":"venue"
},
  "geometry": {"coordinates":[-73.897958,40.812968],"type":"Point"}
}