{
  "type": "Feature",
  "properties": {
    "iso:country":"US",
    "sg:address":"270 S Transit St",
    "sg:city":"Lockport",
    "sg:classifiers":[
        {
            "category":"Home & Garden",
            "subcategory":"Furniture",
            "type":"Retail Goods"
        }
    ],
    "sg:phone":"+1   ",
    "sg:postcode":"14094",
    "sg:province":"NY",
    "wof:name":"K M L Sales Inc",
    "wof:placetype":"venue"
},
  "geometry": {"coordinates":[-78.696792,43.159768],"type":"Point"}
}