{
  "type": "Feature",
  "properties": {
    "addr:full":"3771 Federal Rd Livonia NY 14487",
    "addr:housenumber":"3771",
    "addr:postcode":"14487",
    "addr:street":"Federal Rd",
    "iso:country":"US",
    "sg:address":"3771 Federal Rd",
    "sg:city":"Livonia",
    "sg:classifiers":[
        {
            "category":"Home & Garden",
            "subcategory":"Household Appliances",
            "type":"Retail Goods"
        }
    ],
    "sg:phone":"+1   ",
    "sg:postcode":"14487",
    "sg:province":"NY",
    "wof:name":"S & B Auto and Tire",
    "wof:placetype":"venue"
},
  "geometry": {"coordinates":[-77.640075,42.823796],"type":"Point"}
}