{
  "type": "Feature",
  "properties": {
    "addr:full":"77 Van Buren St Brooklyn NY 11221",
    "addr:housenumber":"77",
    "addr:postcode":"11221",
    "addr:street":"Van Buren St",
    "iso:country":"US",
    "sg:address":"77 Van Buren St",
    "sg:city":"Brooklyn",
    "sg:classifiers":[
        {
            "category":"Food & Beverages",
            "subcategory":"Groceries & Convenience Stores",
            "type":"Retail Goods"
        }
    ],
    "sg:phone":"+1 718 302 1529",
    "sg:postcode":"11221",
    "sg:province":"NY",
    "sg:tags":[
        "grocer"
    ],
    "wof:name":"Rocky Grocery",
    "wof:placetype":"venue"
},
  "geometry": {"coordinates":[-73.944469,40.689922],"type":"Point"}
}