{
  "type": "Feature",
  "properties": {
    "addr:full":"151 Mount Vernon Ave Mt Vernon NY 10550",
    "addr:housenumber":"151",
    "addr:postcode":"10550",
    "addr:street":"Mount Vernon Ave",
    "iso:country":"US",
    "sg:address":"151 Mount Vernon Ave",
    "sg:city":"Mt Vernon",
    "sg:classifiers":[
        {
            "category":"Real Estate",
            "subcategory":"Real Estate Agent",
            "type":"Services"
        }
    ],
    "sg:phone":"+1 914 699 6454",
    "sg:postcode":"10550",
    "sg:province":"NY",
    "sg:tags":[
        "consultant"
    ],
    "wof:name":"Pierrot Realty",
    "wof:placetype":"venue"
},
  "geometry": {"coordinates":[-73.84984,40.913528],"type":"Point"}
}