{
  "type": "Feature",
  "properties": {
    "iso:country":"US",
    "sg:address":"1495 E 34th St",
    "sg:city":"Brooklyn",
    "sg:classifiers":[
        {
            "category":"Food & Beverages",
            "subcategory":"Groceries & Convenience Stores",
            "type":"Retail Goods"
        }
    ],
    "sg:phone":"+1   ",
    "sg:postcode":"11234",
    "sg:province":"NY",
    "wof:name":"Food Minder",
    "wof:placetype":"venue"
},
  "geometry": {"coordinates":[-73.941344,40.618584],"type":"Point"}
}