{
  "type": "Feature",
  "properties": {
    "iso:country":"US",
    "sg:address":"635 Madison Ave",
    "sg:city":"New York",
    "sg:classifiers":[
        {
            "category":"Banks & Credit Unions",
            "subcategory":"Financial Services",
            "type":"Services"
        }
    ],
    "sg:phone":"+1 212 753 9294",
    "sg:postcode":"10022",
    "sg:province":"NY",
    "sg:tags":[
        "investor"
    ],
    "wof:name":"Gaymark Associates",
    "wof:placetype":"venue"
},
  "geometry": {"coordinates":[-73.97096000000001,40.764054],"type":"Point"}
}