{
  "type": "Feature",
  "properties": {
    "iso:country":"US",
    "sg:address":"786 Brighton Rd",
    "sg:city":"Tonawanda",
    "sg:classifiers":[
        {
            "category":"Personal",
            "subcategory":"Beauty Salon",
            "type":"Services"
        }
    ],
    "sg:phone":"+1 716 838 1888",
    "sg:postcode":"14150",
    "sg:province":"NY",
    "wof:name":"Hair I AM Unisex Salon",
    "wof:placetype":"venue"
},
  "geometry": {"coordinates":[-78.843598,42.991157],"type":"Point"}
}