{
  "type": "Feature",
  "properties": {
    "iso:country":"US",
    "sg:address":"34897 County Route 28",
    "sg:city":"Philadelphia",
    "sg:classifiers":[
        {
            "category":"Farming",
            "subcategory":"Farm",
            "type":"Manufacturing & Wholesale Goods"
        }
    ],
    "sg:phone":"+1 315 642 3219",
    "sg:postcode":"13673",
    "sg:province":"NY",
    "wof:name":"Vandervegt, Herman",
    "wof:placetype":"venue"
},
  "geometry": {"coordinates":[-75.714017,44.176307],"type":"Point"}
}