{
  "type": "Feature",
  "properties": {
    "iso:country":"US",
    "sg:address":"196 Prospect Place",
    "sg:city":"Brooklyn",
    "sg:classifiers":[
        {
            "category":"Health Services",
            "subcategory":"Optometrist",
            "type":"Services"
        }
    ],
    "sg:phone":"+1 718 623 9122",
    "sg:postcode":"11238",
    "sg:province":"NY",
    "sg:website":"www.drparkin.com",
    "wof:name":"Dr. Desmond Parkin, OD",
    "wof:placetype":"venue"
},
  "geometry": {"coordinates":[-73.970378,40.677645],"type":"Point"}
}