{
  "type": "Feature",
  "properties": {
    "addr:full":"1 Nissan Ct Monsey NY 10952",
    "addr:postcode":"10952",
    "addr:street":"Nissan Ct",
    "iso:country":"US",
    "sg:address":"1 Nissan Ct",
    "sg:city":"Monsey",
    "sg:classifiers":[
        {
            "category":"Home & Garden",
            "subcategory":"Furniture",
            "type":"Retail Goods"
        }
    ],
    "sg:phone":"+1   ",
    "sg:postcode":"10952",
    "sg:province":"NY",
    "sg:tags":[
        "retailer"
    ],
    "wof:name":"Lounge Inc",
    "wof:placetype":"venue"
},
  "geometry": {"coordinates":[-74.06035799999999,41.113518],"type":"Point"}
}