{
  "type": "Feature",
  "properties": {
    "addr:full":"280 Mayflower Ave New Rochelle NY 10801",
    "addr:housenumber":"280",
    "addr:postcode":"10801",
    "addr:street":"Mayflower Ave",
    "iso:country":"US",
    "sg:address":"280 Mayflower Ave",
    "sg:city":"New Rochelle",
    "sg:classifiers":[
        {
            "category":"Organizations",
            "subcategory":"Religious Organization",
            "type":"Services"
        }
    ],
    "sg:phone":"+1 914 632 5698",
    "sg:postcode":"10801",
    "sg:province":"NY",
    "sg:tags":[
        "church"
    ],
    "wof:name":"Evangelical Covenant Church",
    "wof:placetype":"venue"
},
  "geometry": {"coordinates":[-73.79948400000001,40.922212],"type":"Point"}
}