{
  "type": "Feature",
  "properties": {
    "addr:full":"1556 74th Street Brooklyn NY 11228",
    "addr:housenumber":"1556",
    "addr:postcode":"11228",
    "addr:street":"74Th Street",
    "iso:country":"US",
    "sg:address":"1556 74th Street",
    "sg:city":"Brooklyn",
    "sg:classifiers":[
        {
            "category":"Building & Trades",
            "subcategory":"Construction",
            "type":"Services"
        }
    ],
    "sg:phone":"+1 718 236 5433",
    "sg:postcode":"11228",
    "sg:province":"NY",
    "sg:tags":[
        "contractor"
    ],
    "wof:name":"Achille & Son General Contracting",
    "wof:placetype":"venue"
},
  "geometry": {"coordinates":[-74.001034,40.617279],"type":"Point"}
}