{
  "type": "Feature",
  "properties": {
    "addr:full":"465 Rte 25A Miller Place NY 11764",
    "addr:housenumber":"465",
    "addr:postcode":"11764",
    "addr:street":"Rte 25A",
    "iso:country":"US",
    "sg:address":"465 Rte 25A",
    "sg:city":"Miller Place",
    "sg:classifiers":[
        {
            "category":"Real Estate",
            "subcategory":"Real Estate Agent",
            "type":"Services"
        }
    ],
    "sg:phone":"+1 631 474 2000",
    "sg:postcode":"11764",
    "sg:province":"NY",
    "sg:website":"www.hgrealtysold.com",
    "wof:name":"Hough Guidice Realty Assoc",
    "wof:placetype":"venue"
},
  "geometry": {"coordinates":[-72.98797399999999,40.941654],"type":"Point"}
}