{
  "type": "Feature",
  "properties": {
    "iso:country":"US",
    "sg:address":"110 E 153rd St",
    "sg:city":"Bronx",
    "sg:classifiers":[
        {
            "category":"Manufacturing",
            "subcategory":"Textiles",
            "type":"Manufacturing & Wholesale Goods"
        }
    ],
    "sg:phone":"+1 888 798 1500",
    "sg:postcode":"10451",
    "sg:province":"NY",
    "sg:tags":[
        "cloth",
        "wiping"
    ],
    "sg:website":"http://www.wipe-tex.com",
    "wof:name":"Wipe-Tex International Corp Toll Free-Dial '1' & Then",
    "wof:placetype":"venue"
},
  "geometry": {"coordinates":[-73.927818,40.823614],"type":"Point"}
}