{
  "type": "Feature",
  "properties": {
    "addr:full":"4062 Amboy Rd Staten Island NY 10308",
    "addr:housenumber":"4062",
    "addr:postcode":"10308",
    "addr:street":"Amboy Rd",
    "iso:country":"US",
    "sg:address":"4062 Amboy Rd",
    "sg:city":"Staten Island",
    "sg:classifiers":[
        {
            "category":"Insurance",
            "subcategory":"Insurance Agent",
            "type":"Services"
        }
    ],
    "sg:phone":"+1 718 967 3033",
    "sg:postcode":"10308",
    "sg:province":"NY",
    "wof:name":"Petoff Insurance",
    "wof:placetype":"venue"
},
  "geometry": {"coordinates":[-74.15231799999999,40.549316],"type":"Point"}
}