{
  "type": "Feature",
  "properties": {
    "addr:full":"790 Coney Island Ave Brooklyn NY 11218",
    "addr:housenumber":"790",
    "addr:postcode":"11218",
    "addr:street":"Coney Island Ave",
    "iso:country":"US",
    "sg:address":"790 Coney Island Ave",
    "sg:city":"Brooklyn",
    "sg:classifiers":[
        {
            "category":"Retail",
            "subcategory":"Auto Repair",
            "type":"Services"
        }
    ],
    "sg:phone":"+1 718 633 6161",
    "sg:postcode":"11218",
    "sg:province":"NY",
    "sg:tags":[
        "body",
        "automobile",
        "painting"
    ],
    "wof:name":"Allstate Auto Body Ctr Inc",
    "wof:placetype":"venue"
},
  "geometry": {"coordinates":[-73.968459,40.638018],"type":"Point"}
}