{
  "type": "Feature",
  "properties": {
    "addr:full":"386 Troutman St Brooklyn NY 11237",
    "addr:housenumber":"386",
    "addr:postcode":"11237",
    "addr:street":"Troutman St",
    "iso:country":"US",
    "sg:address":"386 Troutman St",
    "sg:city":"Brooklyn",
    "sg:classifiers":[
        {
            "category":"Wholesale",
            "subcategory":"Machinery & Supplies",
            "type":"Manufacturing & Wholesale Goods"
        }
    ],
    "sg:phone":"+1 718 381 9242",
    "sg:postcode":"11237",
    "sg:province":"NY",
    "sg:tags":[
        "contractor"
    ],
    "wof:name":"Demo-Tech Corp",
    "wof:placetype":"venue"
},
  "geometry": {"coordinates":[-73.923839,40.705141],"type":"Point"}
}