{
  "type": "Feature",
  "properties": {
    "addr:full":"210 E 22 St New York NY 10010",
    "addr:housenumber":"210;22",
    "addr:postcode":"10010",
    "addr:street":"E;St",
    "iso:country":"US",
    "sg:address":"210 E 22 St",
    "sg:city":"New York",
    "sg:classifiers":[
        {
            "category":"Professional",
            "type":"Services"
        }
    ],
    "sg:phone":"+1 212 979 0022",
    "sg:postcode":"10010",
    "sg:province":"NY",
    "sg:tags":[
        "establishment"
    ],
    "wof:name":"Core Brands",
    "wof:placetype":"venue"
},
  "geometry": {"coordinates":[-73.982134,40.737534],"type":"Point"}
}