{
  "type": "Feature",
  "properties": {
    "addr:full":"155 26th St Fl 2 Brooklyn NY 11232",
    "addr:housenumber":"155;2",
    "addr:postcode":"11232",
    "addr:street":"26Th St",
    "iso:country":"US",
    "sg:address":"155 26th St Fl 2",
    "sg:city":"Brooklyn",
    "sg:classifiers":[
        {
            "category":"Shopping",
            "subcategory":"Clothing, Apparel, & Fashions",
            "type":"Retail Goods"
        },
        {
            "category":"Wholesale",
            "subcategory":"Apparel",
            "type":"Manufacturing & Wholesale Goods"
        }
    ],
    "sg:phone":"+1 718 369 4925",
    "sg:postcode":"11232",
    "sg:province":"NY",
    "sg:tags":[
        "sportswear-wholesale",
        "sportswear",
        "manufacturer"
    ],
    "sg:website":"http://www.jonden.com",
    "wof:name":"Jonden",
    "wof:placetype":"venue"
},
  "geometry": {"coordinates":[-74.00029499999999,40.66092],"type":"Point"}
}