{
  "type": "Feature",
  "properties": {
    "iso:country":"US",
    "sg:address":"7690 State Hwy 79",
    "sg:city":"Whitney Point",
    "sg:classifiers":[
        {
            "category":"Autos & Motor Vehicles",
            "subcategory":"Automobile Sales",
            "type":"Retail Goods"
        }
    ],
    "sg:phone":"+1 607 692 3609",
    "sg:postcode":"13862",
    "sg:province":"NY",
    "sg:tags":[
        "car",
        "used",
        "dealer"
    ],
    "wof:name":"Bambi Lynn Autos",
    "wof:placetype":"venue"
},
  "geometry": {"coordinates":[-75.90795,42.298939],"type":"Point"}
}