{
  "type": "Feature",
  "properties": {
    "addr:full":"707 Faile St Bronx NY 10474",
    "addr:housenumber":"707",
    "addr:postcode":"10474",
    "addr:street":"Faile St",
    "iso:country":"US",
    "sg:address":"707 Faile St",
    "sg:city":"Bronx",
    "sg:classifiers":[
        {
            "category":"Personal",
            "subcategory":"Beauty Salon",
            "type":"Services"
        }
    ],
    "sg:phone":"+1 347 297 6611",
    "sg:postcode":"10474",
    "sg:province":"NY",
    "sg:tags":[
        "hair"
    ],
    "wof:name":"Brothers Barber Shop",
    "wof:placetype":"venue"
},
  "geometry": {"coordinates":[-73.886684,40.814574],"type":"Point"}
}