{
  "type": "Feature",
  "properties": {
    "iso:country":"US",
    "sg:address":"32 Broad St",
    "sg:city":"Plattsburgh",
    "sg:classifiers":[
        {
            "category":"Home & Garden",
            "subcategory":"Household Appliances",
            "type":"Retail Goods"
        }
    ],
    "sg:phone":"+1   ",
    "sg:postcode":"12901",
    "sg:province":"NY",
    "wof:name":"Wilson Appliance Center Inc",
    "wof:placetype":"venue"
},
  "geometry": {"coordinates":[-73.456638,44.695035],"type":"Point"}
}