{
  "type": "Feature",
  "properties": {
    "addr:full":"2225 Lodovick Ave Bronx NY 10469",
    "addr:housenumber":"2225",
    "addr:postcode":"10469",
    "addr:street":"Lodovick Ave",
    "iso:country":"US",
    "sg:address":"2225 Lodovick Ave",
    "sg:city":"Bronx",
    "sg:classifiers":[
        {
            "category":"Health Services",
            "subcategory":"Nursing And Care Facility",
            "type":"Services"
        }
    ],
    "sg:phone":"+1 718 655 7700",
    "sg:postcode":"10469",
    "sg:province":"NY",
    "sg:tags":[
        "home",
        "for",
        "mentally",
        "challenged"
    ],
    "wof:name":"Community Action For Humn Svcs",
    "wof:placetype":"venue"
},
  "geometry": {"coordinates":[-73.837264,40.85862],"type":"Point"}
}