{
  "type": "Feature",
  "properties": {
    "iso:country":"US",
    "sg:address":"35 Mc Harrie St",
    "sg:city":"Baldwinsville",
    "sg:classifiers":[
        {
            "category":"Building & Trades",
            "subcategory":"Construction",
            "type":"Services"
        }
    ],
    "sg:phone":"+1 315 415 6639",
    "sg:postcode":"13027",
    "sg:province":"NY",
    "sg:tags":[
        "house"
    ],
    "wof:name":"Grand Homes Construction",
    "wof:placetype":"venue"
},
  "geometry": {"coordinates":[-76.337548,43.15517],"type":"Point"}
}