{
  "type": "Feature",
  "properties": {
    "iso:country":"US",
    "sg:address":"2174 Amsterdam Ave",
    "sg:city":"New York",
    "sg:classifiers":[
        {
            "category":"Banks & Credit Unions",
            "subcategory":"Bank",
            "type":"Services"
        }
    ],
    "sg:phone":"+1 212 568 4255",
    "sg:postcode":"10032",
    "sg:province":"NY",
    "sg:tags":[
        "money",
        "transfer"
    ],
    "wof:name":"Lana Nacional Limpio",
    "wof:placetype":"venue"
},
  "geometry": {"coordinates":[-73.93721600000001,40.839473],"type":"Point"}
}