{
  "type": "Feature",
  "properties": {
    "iso:country":"US",
    "sg:address":"311 Charles St",
    "sg:city":"Boonville",
    "sg:classifiers":[
        {
            "category":"Professional",
            "subcategory":"Accounting & Tax Preparation",
            "type":"Services"
        }
    ],
    "sg:phone":"+1 315 942 2436",
    "sg:postcode":"13309",
    "sg:province":"NY",
    "sg:tags":[
        "return",
        "preparation-business"
    ],
    "wof:name":"Saddle Up Tax Shop",
    "wof:placetype":"venue"
},
  "geometry": {"coordinates":[-75.32868000000001,43.479783],"type":"Point"}
}