{
  "type": "Feature",
  "properties": {
    "iso:country":"US",
    "sg:address":"1331 N Forest Rd",
    "sg:city":"Buffalo",
    "sg:classifiers":[
        {
            "category":"Health Services",
            "subcategory":"Chiropractor",
            "type":"Services"
        }
    ],
    "sg:phone":"+1 716 639 3939",
    "sg:postcode":"14221",
    "sg:province":"NY",
    "wof:name":"Misiak Family Chiropractic",
    "wof:placetype":"venue"
},
  "geometry": {"coordinates":[-78.75964,42.99498],"type":"Point"}
}