{
  "type": "Feature",
  "properties": {
    "iso:country":"US",
    "sg:address":"138 Montrose Ave",
    "sg:city":"Brooklyn",
    "sg:classifiers":[
        {
            "category":"Organizations",
            "subcategory":"Religious Organization",
            "type":"Services"
        }
    ],
    "sg:phone":"+1 718 384 0215",
    "sg:postcode":"11206",
    "sg:province":"NY",
    "sg:tags":[
        "church"
    ],
    "sg:website":"www.mhtbrooklyn.org",
    "wof:name":"Most Holy Trinity Church",
    "wof:placetype":"venue"
},
  "geometry": {"coordinates":[-73.943838,40.707178],"type":"Point"}
}