{
  "type": "Feature",
  "properties": {
    "addr:full":"16 W 49th St Manhattan NY 10020",
    "addr:housenumber":"16",
    "addr:postcode":"10020",
    "addr:street":"W 49Th St",
    "iso:country":"US",
    "sg:address":"16 W 49th St",
    "sg:city":"Manhattan",
    "sg:classifiers":[
        {
            "category":"Personal",
            "type":"Services"
        }
    ],
    "sg:phone":"+1 646 556 7952",
    "sg:postcode":"10020",
    "sg:province":"NY",
    "sg:tags":[
        "towing"
    ],
    "sg:website":"www.rockafellercentertowing.com",
    "wof:name":"Rockafeller Center Towing",
    "wof:placetype":"venue"
},
  "geometry": {"coordinates":[-73.978166,40.758113],"type":"Point"}
}