{
  "type": "Feature",
  "properties": {
    "addr:full":"52 Congress St Saratoga Springs NY 12866",
    "addr:housenumber":"52",
    "addr:postcode":"12866",
    "addr:street":"Congress St",
    "iso:country":"US",
    "sg:address":"52 Congress St",
    "sg:city":"Saratoga Springs",
    "sg:classifiers":[
        {
            "category":"Organizations",
            "subcategory":"Religious Organization",
            "type":"Services"
        }
    ],
    "sg:phone":"+1 518 580 1810",
    "sg:postcode":"12866",
    "sg:province":"NY",
    "wof:name":"New Life Fellowship",
    "wof:placetype":"venue"
},
  "geometry": {"coordinates":[-73.789913,43.079179],"type":"Point"}
}