{
  "type": "Feature",
  "properties": {
    "iso:country":"US",
    "sg:address":"52 Grove St",
    "sg:city":"Hempstead",
    "sg:classifiers":[
        {
            "category":"Building & Trades",
            "subcategory":"Construction",
            "type":"Services"
        }
    ],
    "sg:phone":"+1 516 642 7535",
    "sg:postcode":"11550",
    "sg:province":"NY",
    "sg:tags":[
        "contractor"
    ],
    "wof:name":"Carmig Installer Corp",
    "wof:placetype":"venue"
},
  "geometry": {"coordinates":[-73.620807,40.703719],"type":"Point"}
}