{
  "type": "Feature",
  "properties": {
    "iso:country":"US",
    "sg:address":"42 Buhl Ln",
    "sg:city":"East Northport",
    "sg:classifiers":[
        {
            "category":"Building & Trades",
            "subcategory":"Construction",
            "type":"Services"
        }
    ],
    "sg:phone":"+1 516 639 6411",
    "sg:postcode":"11731",
    "sg:province":"NY",
    "sg:tags":[
        "house"
    ],
    "wof:name":"Mfs Construction Corp",
    "wof:placetype":"venue"
},
  "geometry": {"coordinates":[-73.29895999999999,40.858879],"type":"Point"}
}