{
  "type": "Feature",
  "properties": {
    "addr:full":"55 Water Street 49th Floor New York NY 10041",
    "addr:housenumber":"55;49th floor",
    "addr:postcode":"10041",
    "addr:street":"Water Street",
    "iso:country":"US",
    "sg:address":"55 Water Street 49th Floor",
    "sg:city":"New York",
    "sg:classifiers":[
        {
            "category":"Professional",
            "subcategory":"Computer Services",
            "type":"Services"
        }
    ],
    "sg:phone":"+1 212 438 5349",
    "sg:postcode":"10041",
    "sg:province":"NY",
    "sg:website":"http://www.clarifi.com/",
    "wof:name":"ClariFI",
    "wof:placetype":"venue"
},
  "geometry": {"coordinates":[-74.010991,40.702962],"type":"Point"}
}