{
  "type": "Feature",
  "properties": {
    "addr:full":"249 Wallins Corners Rd Amsterdam NY 12010",
    "addr:housenumber":"249",
    "addr:postcode":"12010",
    "addr:street":"Wallins Corners Rd",
    "iso:country":"US",
    "sg:address":"249 Wallins Corners Rd",
    "sg:city":"Amsterdam",
    "sg:classifiers":[
        {
            "category":"Restaurant",
            "type":"Food & Drink"
        }
    ],
    "sg:menulink":"http://www.allmenus.com/ny/amsterdam/115920-quiznos-sub/menu/",
    "sg:phone":"+1 518 843 6688",
    "sg:postcode":"12010",
    "sg:province":"NY",
    "sg:tags":[
        "wrap",
        "american",
        "sandwich"
    ],
    "wof:name":"Quiznos Sub",
    "wof:placetype":"venue"
},
  "geometry": {"coordinates":[-74.18375,42.970789],"type":"Point"}
}