{
  "type": "Feature",
  "properties": {
    "iso:country":"US",
    "sg:address":"2412 Broadway",
    "sg:city":"New York",
    "sg:classifiers":[
        {
            "category":"Shopping",
            "subcategory":"Gifts & Souvenirs",
            "type":"Retail Goods"
        }
    ],
    "sg:phone":"+1 212 583 2422",
    "sg:postcode":"10024",
    "sg:province":"NY",
    "sg:tags":[
        "flower"
    ],
    "wof:name":"West Side Judaica",
    "wof:placetype":"venue"
},
  "geometry": {"coordinates":[-73.97479199999999,40.789877],"type":"Point"}
}