{
  "type": "Feature",
  "properties": {
    "iso:country":"US",
    "sg:address":"23320 Merrick Blvd",
    "sg:city":"Rosedale",
    "sg:classifiers":[
        {
            "category":"Personal",
            "subcategory":"Barber",
            "type":"Services"
        }
    ],
    "sg:phone":"+1 718 276 0619",
    "sg:postcode":"11422",
    "sg:province":"NY",
    "wof:name":"Cristina Beauty Salon Inc",
    "wof:placetype":"venue"
},
  "geometry": {"coordinates":[-73.736814,40.674673],"type":"Point"}
}