{
  "type": "Feature",
  "properties": {
    "iso:country":"US",
    "sg:address":"112 W 31 St",
    "sg:city":"New York",
    "sg:classifiers":[
        {
            "category":"Manufacturing",
            "subcategory":"Printing",
            "type":"Manufacturing & Wholesale Goods"
        }
    ],
    "sg:phone":"+1   ",
    "sg:postcode":"10001",
    "sg:province":"NY",
    "sg:tags":[
        "commercial",
        "letterpress",
        "offset"
    ],
    "wof:name":"Randell Press Inc",
    "wof:placetype":"venue"
},
  "geometry": {"coordinates":[-73.99177899999999,40.748887],"type":"Point"}
}