{
  "type": "Feature",
  "properties": {
    "addr:full":"16587 Glidden Rd Holley NY 14470",
    "addr:housenumber":"16587",
    "addr:postcode":"14470",
    "addr:street":"Glidden Rd",
    "iso:country":"US",
    "sg:address":"16587 Glidden Rd",
    "sg:city":"Holley",
    "sg:classifiers":[
        {
            "category":"Building & Trades",
            "subcategory":"Electrical",
            "type":"Services"
        }
    ],
    "sg:phone":"+1 585 638 8204",
    "sg:postcode":"14470",
    "sg:province":"NY",
    "sg:tags":[
        "electrical",
        "contractor"
    ],
    "wof:name":"Kinsey & Mancuso Electric",
    "wof:placetype":"venue"
},
  "geometry": {"coordinates":[-78.04255499999999,43.164303],"type":"Point"}
}