{
  "type": "Feature",
  "properties": {
    "addr:full":"1000 Ellicott Creek Rd Tonawanda NY 14150",
    "addr:housenumber":"1000",
    "addr:postcode":"14150",
    "addr:street":"Ellicott Creek Rd",
    "iso:country":"US",
    "sg:address":"1000 Ellicott Creek Rd",
    "sg:city":"Tonawanda",
    "sg:classifiers":[
        {
            "category":"Education",
            "subcategory":"Dance Studio",
            "type":"Public Place"
        }
    ],
    "sg:phone":"+1 716 695 6558",
    "sg:postcode":"14150",
    "sg:province":"NY",
    "sg:tags":[
        "instruction",
        "dancing"
    ],
    "wof:name":"Carmarie's Dance Studio",
    "wof:placetype":"venue"
},
  "geometry": {"coordinates":[-78.833253,43.016206],"type":"Point"}
}