{
  "type": "Feature",
  "properties": {
    "addr:full":"5 North Ave Garden City NY 11530",
    "addr:housenumber":"5",
    "addr:postcode":"11530",
    "addr:street":"North Ave",
    "iso:country":"US",
    "sg:address":"5 North Ave",
    "sg:city":"Garden City",
    "sg:classifiers":[
        {
            "category":"Travel",
            "subcategory":"Hotels & Motels",
            "type":"Entertainment"
        }
    ],
    "sg:phone":"+1 516 222 6277",
    "sg:postcode":"11530",
    "sg:province":"NY",
    "wof:name":"Hyatt Place Of Garden City",
    "wof:placetype":"venue"
},
  "geometry": {"coordinates":[-73.687681,40.723576],"type":"Point"}
}