{
  "type": "Feature",
  "properties": {
    "addr:full":"508 Tarrytown Rd White Plains NY 10607",
    "addr:housenumber":"508",
    "addr:postcode":"10607",
    "addr:street":"Tarrytown Rd",
    "iso:country":"US",
    "sg:address":"508 Tarrytown Rd",
    "sg:city":"White Plains",
    "sg:classifiers":[
        {
            "category":"Health Services",
            "subcategory":"Clinic",
            "type":"Services"
        }
    ],
    "sg:phone":"+1   ",
    "sg:postcode":"10607",
    "sg:province":"NY",
    "sg:tags":[
        "carwash"
    ],
    "wof:name":"Colucci Marketing",
    "wof:placetype":"venue"
},
  "geometry": {"coordinates":[-73.802035,41.043822],"type":"Point"}
}