{
  "type": "Feature",
  "properties": {
    "addr:full":"1001 45th Ave Long Island City NY 11101",
    "addr:housenumber":"1001",
    "addr:postcode":"11101",
    "addr:street":"45Th Ave",
    "iso:country":"US",
    "sg:address":"1001 45th Ave",
    "sg:city":"Long Island City",
    "sg:classifiers":[
        {
            "category":"Retail",
            "subcategory":"Auto Repair",
            "type":"Services"
        }
    ],
    "sg:phone":"+1 718 389 0430",
    "sg:postcode":"11101",
    "sg:province":"NY",
    "wof:name":"Evandro Tech Motors Ltd",
    "wof:placetype":"venue"
},
  "geometry": {"coordinates":[-73.952195,40.748404],"type":"Point"}
}