{
  "type": "Feature",
  "properties": {
    "iso:country":"US",
    "sg:address":"1019 46th St",
    "sg:city":"Brooklyn",
    "sg:classifiers":[
        {
            "category":"Education",
            "subcategory":"School",
            "type":"Public Place"
        }
    ],
    "sg:phone":"+1 718 854 7777",
    "sg:postcode":"11219",
    "sg:province":"NY",
    "wof:name":"Bais Isaac Tzvi",
    "wof:placetype":"venue"
},
  "geometry": {"coordinates":[-73.99577600000001,40.640117],"type":"Point"}
}