{
  "type": "Feature",
  "properties": {
    "addr:full":"1062 Inner Dr Schenectady NY 12303",
    "addr:housenumber":"1062",
    "addr:postcode":"12303",
    "addr:street":"Inner Dr",
    "iso:country":"US",
    "sg:address":"1062 Inner Dr",
    "sg:city":"Schenectady",
    "sg:classifiers":[
        {
            "category":"Organizations",
            "subcategory":"Religious Organization",
            "type":"Services"
        }
    ],
    "sg:phone":"+1 518 355 1531",
    "sg:postcode":"12303",
    "sg:province":"NY",
    "sg:tags":[
        "church"
    ],
    "wof:name":"Our Saviour Lutheran Church",
    "wof:placetype":"venue"
},
  "geometry": {"coordinates":[-73.941896,42.774789],"type":"Point"}
}