{
  "type": "Feature",
  "properties": {
    "addr:full":"901 Father Capodanno Blvd Staten Island NY 10305",
    "addr:housenumber":"901",
    "addr:postcode":"10305",
    "addr:street":"Father Capodanno Blvd",
    "iso:country":"US",
    "sg:address":"901 Father Capodanno Blvd",
    "sg:city":"Staten Island",
    "sg:classifiers":[
        {
            "category":"Building & Trades",
            "subcategory":"Electrical",
            "type":"Services"
        }
    ],
    "sg:phone":"+1 718 987 3629",
    "sg:postcode":"10305",
    "sg:province":"NY",
    "sg:tags":[
        "electrical",
        "contractor"
    ],
    "wof:name":"Ampco Tech Electric",
    "wof:placetype":"venue"
},
  "geometry": {"coordinates":[-74.085234,40.574606],"type":"Point"}
}