{
  "type": "Feature",
  "properties": {
    "addr:full":"229 E 167th St Bronx NY 10456",
    "addr:housenumber":"229",
    "addr:postcode":"10456",
    "addr:street":"E 167Th St",
    "iso:country":"US",
    "sg:address":"229 E 167th St",
    "sg:city":"Bronx",
    "sg:classifiers":[
        {
            "category":"Personal",
            "subcategory":"Beauty Salon",
            "type":"Services"
        }
    ],
    "sg:phone":"+1 718 410 2904",
    "sg:postcode":"10456",
    "sg:province":"NY",
    "wof:name":"Norma Beauty Salon",
    "wof:placetype":"venue"
},
  "geometry": {"coordinates":[-73.915167,40.833742],"type":"Point"}
}