{
  "type": "Feature",
  "properties": {
    "iso:country":"US",
    "sg:address":"77 Ogden Parma Townline Rd",
    "sg:city":"Spencerport",
    "sg:classifiers":[
        {
            "category":"Arts & Performance",
            "subcategory":"Theater",
            "type":"Entertainment"
        }
    ],
    "sg:phone":"+1   ",
    "sg:postcode":"14559",
    "sg:province":"NY",
    "sg:tags":[
        "entertainer",
        "group"
    ],
    "wof:name":"Music Tyme",
    "wof:placetype":"venue"
},
  "geometry": {"coordinates":[-77.75922799999999,43.203493],"type":"Point"}
}