{
  "type": "Feature",
  "properties": {
    "addr:full":"106 Merz Ave Syracuse NY 13203",
    "addr:housenumber":"106",
    "addr:postcode":"13203",
    "addr:street":"Merz Ave",
    "iso:country":"US",
    "sg:address":"106 Merz Ave",
    "sg:city":"Syracuse",
    "sg:classifiers":[
        {
            "category":"Building & Trades",
            "subcategory":"Construction",
            "type":"Services"
        }
    ],
    "sg:phone":"+1 315 472 1139",
    "sg:postcode":"13203",
    "sg:province":"NY",
    "sg:tags":[
        "house"
    ],
    "wof:name":"Frank Procopio Remodeling",
    "wof:placetype":"venue"
},
  "geometry": {"coordinates":[-76.13849500000001,43.064168],"type":"Point"}
}