{
  "type": "Feature",
  "properties": {
    "iso:country":"US",
    "sg:address":"122 N Aurora St",
    "sg:city":"Ithaca",
    "sg:classifiers":[
        {
            "category":"Food & Beverages",
            "subcategory":"Groceries & Convenience Stores",
            "type":"Retail Goods"
        },
        {
            "category":"Food & Beverages",
            "subcategory":"Liquor & Beverages",
            "type":"Retail Goods"
        }
    ],
    "sg:phone":"+1 607 273 3236",
    "sg:postcode":"14850",
    "sg:province":"NY",
    "sg:tags":[
        "grocer",
        "alcoholic"
    ],
    "wof:name":"Common's Market",
    "wof:placetype":"venue"
},
  "geometry": {"coordinates":[-76.495751,42.440312],"type":"Point"}
}