{
  "type": "Feature",
  "properties": {
    "addr:full":"560 Broadway New York NY 10012",
    "addr:housenumber":"560",
    "addr:postcode":"10012",
    "addr:street":"Broadway",
    "iso:country":"US",
    "sg:address":"560 Broadway",
    "sg:city":"New York",
    "sg:classifiers":[
        {
            "category":"Shopping",
            "subcategory":"Shoes",
            "type":"Retail Goods"
        }
    ],
    "sg:postcode":"10012",
    "sg:province":"NY",
    "sg:tags":[
        "store"
    ],
    "sg:website":"www.converse.com/?CSID=44_kwid/#...",
    "wof:name":"Converse",
    "wof:placetype":"venue"
},
  "geometry": {"coordinates":[-73.997963,40.723995],"type":"Point"}
}