{
  "type": "Feature",
  "properties": {
    "iso:country":"US",
    "sg:address":"2477 Harbor Ln",
    "sg:city":"Bellmore",
    "sg:classifiers":[
        {
            "category":"Professional",
            "subcategory":"Management & Consulting",
            "type":"Services"
        }
    ],
    "sg:phone":"+1 516 679 2078",
    "sg:postcode":"11710",
    "sg:province":"NY",
    "sg:tags":[
        "company"
    ],
    "wof:name":"Criscay Management Corporation",
    "wof:placetype":"venue"
},
  "geometry": {"coordinates":[-73.52816199999999,40.647708],"type":"Point"}
}