{
  "type": "Feature",
  "properties": {
    "iso:country":"US",
    "sg:address":"248 Washington Ave",
    "sg:city":"New Rochelle",
    "sg:classifiers":[
        {
            "category":"Retail",
            "subcategory":"Auto Repair",
            "type":"Services"
        }
    ],
    "sg:phone":"+1 914 235 2760",
    "sg:postcode":"10801",
    "sg:province":"NY",
    "sg:tags":[
        "repairing",
        "automobile"
    ],
    "wof:name":"Lopez Auto Repair",
    "wof:placetype":"venue"
},
  "geometry": {"coordinates":[-73.795811,40.910122],"type":"Point"}
}