{
  "type": "Feature",
  "properties": {
    "addr:full":"3409 Erie Blvd E Syracuse NY 13214",
    "addr:housenumber":"3409",
    "addr:postcode":"13214",
    "addr:street":"Erie Blvd E",
    "iso:country":"US",
    "sg:address":"3409 Erie Blvd E",
    "sg:city":"Syracuse",
    "sg:classifiers":[
        {
            "category":"Restaurant",
            "type":"Food & Drink"
        }
    ],
    "sg:menulink":"http://www.allmenus.com/ny/de-witt/281188-nothing-but-noodles/menu/",
    "sg:phone":"+1 315 445 4000",
    "sg:postcode":"13214",
    "sg:province":"NY",
    "sg:tags":[
        "pasta",
        "american"
    ],
    "wof:name":"Nothing But Noodles",
    "wof:placetype":"venue"
},
  "geometry": {"coordinates":[-76.069564,43.046918],"type":"Point"}
}