{
  "type": "Feature",
  "properties": {
    "iso:country":"US",
    "sg:address":"151 W 34th St",
    "sg:city":"New York",
    "sg:classifiers":[
        {
            "category":"Coffee & Tea",
            "type":"Food & Drink"
        }
    ],
    "sg:menulink":"http://www.allmenus.com/ny/new-york/113507-starbucks-coffee/menu/",
    "sg:phone":"+1 212 564 7178",
    "sg:postcode":"10001",
    "sg:province":"NY",
    "sg:tags":[
        "american"
    ],
    "wof:name":"Starbucks Coffee",
    "wof:placetype":"venue"
},
  "geometry": {"coordinates":[-73.989322,40.750447],"type":"Point"}
}