{
  "type": "Feature",
  "properties": {
    "addr:full":"3560 E Genesee St Syracuse NY 13214",
    "addr:housenumber":"3560",
    "addr:postcode":"13214",
    "addr:street":"E Genesee St",
    "iso:country":"US",
    "sg:address":"3560 E Genesee St",
    "sg:city":"Syracuse",
    "sg:classifiers":[
        {
            "category":"Manufacturing",
            "subcategory":"Printing",
            "type":"Manufacturing & Wholesale Goods"
        }
    ],
    "sg:phone":"+1 315 449 1150",
    "sg:postcode":"13214",
    "sg:province":"NY",
    "sg:tags":[
        "newspaper"
    ],
    "wof:name":"Good Newspaper",
    "wof:placetype":"venue"
},
  "geometry": {"coordinates":[-76.08743800000001,43.041797],"type":"Point"}
}