{
  "type": "Feature",
  "properties": {
    "addr:full":"182 W Montauk Hwy Hampton Bays NY 11946",
    "addr:housenumber":"182",
    "addr:postcode":"11946",
    "addr:street":"W Montauk Hwy",
    "iso:country":"US",
    "sg:address":"182 W Montauk Hwy",
    "sg:city":"Hampton Bays",
    "sg:classifiers":[
        {
            "category":"Health Services",
            "subcategory":"Doctor",
            "type":"Services"
        }
    ],
    "sg:phone":"+1 631 723 0022",
    "sg:postcode":"11946",
    "sg:province":"NY",
    "sg:tags":[
        "medical"
    ],
    "wof:name":"Shoten S Lieverman Alexandra",
    "wof:placetype":"venue"
},
  "geometry": {"coordinates":[-72.53873900000001,40.87286],"type":"Point"}
}