{
  "type": "Feature",
  "properties": {
    "addr:full":"3036 Alt Blvd Grand Island NY 14072",
    "addr:housenumber":"3036",
    "addr:postcode":"14072",
    "addr:street":"Alt Blvd",
    "iso:country":"US",
    "sg:address":"3036 Alt Blvd",
    "sg:city":"Grand Island",
    "sg:classifiers":[
        {
            "category":"Manufacturing",
            "subcategory":"Motor Vehicles & Parts",
            "type":"Manufacturing & Wholesale Goods"
        }
    ],
    "sg:phone":"+1   ",
    "sg:postcode":"14072",
    "sg:province":"NY",
    "sg:tags":[
        "on",
        "product",
        "printing",
        "metal",
        "plastic"
    ],
    "sg:website":"www.starline.com",
    "wof:name":"Starline USA Inc",
    "wof:placetype":"venue"
},
  "geometry": {"coordinates":[-78.986974,43.04145],"type":"Point"}
}