{
  "type": "Feature",
  "properties": {
    "addr:full":"1783 84th Street Brooklyn NY 11214",
    "addr:housenumber":"1783",
    "addr:postcode":"11214",
    "addr:street":"84Th Street",
    "iso:country":"US",
    "sg:address":"1783 84th Street",
    "sg:city":"Brooklyn",
    "sg:classifiers":[
        {
            "category":"Food & Beverages",
            "subcategory":"Liquor & Beverages",
            "type":"Retail Goods"
        }
    ],
    "sg:phone":"+1 718 256 3300",
    "sg:postcode":"11214",
    "sg:province":"NY",
    "sg:tags":[
        "beer",
        "spirit",
        "wine"
    ],
    "wof:name":"84 St Beverage Center",
    "wof:placetype":"venue"
},
  "geometry": {"coordinates":[-74.00136999999999,40.609019],"type":"Point"}
}