{
  "type": "Feature",
  "properties": {
    "iso:country":"US",
    "sg:address":"60 Smithfield Blvd",
    "sg:city":"Plattsburgh",
    "sg:classifiers":[
        {
            "category":"Bakery",
            "type":"Food & Drink"
        }
    ],
    "sg:menulink":"http://www.allmenus.com/ny/plattsburgh/220095-auntie-annes-pretzels/menu/",
    "sg:phone":"+1 518 566 8145",
    "sg:postcode":"12901",
    "sg:province":"NY",
    "sg:tags":[
        "american",
        "pastry"
    ],
    "wof:name":"Auntie Anne's Pretzels",
    "wof:placetype":"venue"
},
  "geometry": {"coordinates":[-73.49368800000001,44.700734],"type":"Point"}
}