{
  "type": "Feature",
  "properties": {
    "iso:country":"US",
    "sg:address":"81 Livonia Ave",
    "sg:city":"Brooklyn",
    "sg:classifiers":[
        {
            "category":"Building & Trades",
            "subcategory":"Plumbing",
            "type":"Services"
        }
    ],
    "sg:phone":"+1 347 435 3404",
    "sg:postcode":"11212",
    "sg:province":"NY",
    "wof:name":"Brooklyn Finest Barbershop",
    "wof:placetype":"venue"
},
  "geometry": {"coordinates":[-73.91515,40.66177],"type":"Point"}
}