{
  "type": "Feature",
  "properties": {
    "iso:country":"US",
    "sg:address":"156 William St Rm 802",
    "sg:city":"New York",
    "sg:classifiers":[
        {
            "category":"Real Estate",
            "subcategory":"Real Estate Services",
            "type":"Services"
        }
    ],
    "sg:phone":"+1 212 587 6100",
    "sg:postcode":"10038",
    "sg:province":"NY",
    "sg:tags":[
        "management",
        "property"
    ],
    "wof:name":"East Realty",
    "wof:placetype":"venue"
},
  "geometry": {"coordinates":[-74.006203,40.709801],"type":"Point"}
}