{
  "type": "Feature",
  "properties": {
    "iso:country":"US",
    "sg:address":"26 W 9 St",
    "sg:city":"New York",
    "sg:classifiers":[
        {
            "category":"Social Services",
            "type":"Services"
        }
    ],
    "sg:phone":"+1 212 387 9429",
    "sg:postcode":"10011",
    "sg:province":"NY",
    "wof:name":"Gestalt Center Psychotherapy",
    "wof:placetype":"venue"
},
  "geometry": {"coordinates":[-73.99855100000001,40.733804],"type":"Point"}
}