{
  "type": "Feature",
  "properties": {
    "addr:full":"223 Schenectady Ave Brooklyn NY 11213",
    "addr:housenumber":"223",
    "addr:postcode":"11213",
    "addr:street":"Schenectady Ave",
    "iso:country":"US",
    "sg:address":"223 Schenectady Ave",
    "sg:city":"Brooklyn",
    "sg:classifiers":[
        {
            "category":"Health Services",
            "subcategory":"Doctor",
            "type":"Services"
        }
    ],
    "sg:phone":"+1 718 676 9309",
    "sg:postcode":"11213",
    "sg:province":"NY",
    "wof:name":"Mlk Medical",
    "wof:placetype":"venue"
},
  "geometry": {"coordinates":[-73.933486,40.671208],"type":"Point"}
}