{
  "type": "Feature",
  "properties": {
    "iso:country":"US",
    "sg:address":"24 Lumber Rd",
    "sg:city":"Roslyn",
    "sg:classifiers":[
        {
            "category":"Wholesale",
            "subcategory":"Computers",
            "type":"Manufacturing & Wholesale Goods"
        }
    ],
    "sg:phone":"+1 516 705 0786",
    "sg:postcode":"11576",
    "sg:province":"NY",
    "wof:name":"Aqua Systems Inc",
    "wof:placetype":"venue"
},
  "geometry": {"coordinates":[-73.650902,40.801399],"type":"Point"}
}