{
  "type": "Feature",
  "properties": {
    "addr:full":"35 Jervis Rd Yonkers NY 10705",
    "addr:housenumber":"35",
    "addr:postcode":"10705",
    "addr:street":"Jervis Rd",
    "iso:country":"US",
    "sg:address":"35 Jervis Rd",
    "sg:city":"Yonkers",
    "sg:classifiers":[
        {
            "category":"Arts & Performance",
            "subcategory":"Theater",
            "type":"Entertainment"
        }
    ],
    "sg:phone":"+1   ",
    "sg:postcode":"10705",
    "sg:province":"NY",
    "sg:tags":[
        "theatrical"
    ],
    "wof:name":"Hamm & Clov Stage Co Inc",
    "wof:placetype":"venue"
},
  "geometry": {"coordinates":[-73.880471,40.913847],"type":"Point"}
}