{
  "type": "Feature",
  "properties": {
    "addr:full":"174 E Lake Rd Tuxedo Park NY 10987",
    "addr:housenumber":"174",
    "addr:postcode":"10987",
    "addr:street":"E Lake Rd",
    "iso:country":"US",
    "sg:address":"174 E Lake Rd",
    "sg:city":"Tuxedo Park",
    "sg:classifiers":[
        {
            "category":"Banks & Credit Unions",
            "subcategory":"Financial Services",
            "type":"Services"
        }
    ],
    "sg:phone":"+1 845 351 1059",
    "sg:postcode":"10987",
    "sg:province":"NY",
    "sg:tags":[
        "trust",
        "nonprofit",
        "management"
    ],
    "wof:name":"Gary W Parr Family Founda",
    "wof:placetype":"venue"
},
  "geometry": {"coordinates":[-74.20858699999999,41.189734],"type":"Point"}
}