{
  "type": "Feature",
  "properties": {
    "addr:full":"9701 Atlantic Avenue Woodhaven NY 11421",
    "addr:housenumber":"9701",
    "addr:postcode":"11421",
    "addr:street":"Atlantic Avenue",
    "iso:country":"US",
    "sg:address":"9701 Atlantic Avenue",
    "sg:city":"Woodhaven",
    "sg:classifiers":[
        {
            "category":"Restaurant",
            "type":"Food & Drink"
        }
    ],
    "sg:phone":"+1 718 805 9123",
    "sg:postcode":"11421",
    "sg:province":"NY",
    "wof:name":"Taco Bell Restaurant",
    "wof:placetype":"venue"
},
  "geometry": {"coordinates":[-73.845685,40.689244],"type":"Point"}
}