{
  "type": "Feature",
  "properties": {
    "addr:full":"29 Bart Dr Selden NY 11784",
    "addr:housenumber":"29",
    "addr:postcode":"11784",
    "addr:street":"Bart Dr",
    "iso:country":"US",
    "sg:address":"29 Bart Dr",
    "sg:city":"Selden",
    "sg:classifiers":[
        {
            "category":"Building & Trades",
            "subcategory":"Construction",
            "type":"Services"
        }
    ],
    "sg:phone":"+1 631 698 3717",
    "sg:postcode":"11784",
    "sg:province":"NY",
    "sg:tags":[
        "contractor"
    ],
    "wof:name":"Michael Ryan Roofing & Siding",
    "wof:placetype":"venue"
},
  "geometry": {"coordinates":[-73.057412,40.852885],"type":"Point"}
}