{
  "type": "Feature",
  "properties": {
    "iso:country":"US",
    "sg:address":"223 Rockaway Pkwy",
    "sg:city":"Valley Stream",
    "sg:classifiers":[
        {
            "category":"Health Services",
            "subcategory":"Doctor",
            "type":"Services"
        }
    ],
    "sg:phone":"+1 516 872 9388",
    "sg:postcode":"11580",
    "sg:province":"NY",
    "sg:tags":[
        "medical"
    ],
    "wof:name":"Choong K Kim MD P C",
    "wof:placetype":"venue"
},
  "geometry": {"coordinates":[-73.694239,40.672398],"type":"Point"}
}