{
  "type": "Feature",
  "properties": {
    "iso:country":"US",
    "sg:address":"49 Ferdon Ave",
    "sg:city":"Sparkill",
    "sg:classifiers":[
        {
            "category":"Building & Trades",
            "subcategory":"Construction",
            "type":"Services"
        }
    ],
    "sg:phone":"+1 845 365 1488",
    "sg:postcode":"10976",
    "sg:province":"NY",
    "sg:tags":[
        "residential"
    ],
    "wof:name":"Piermont Design Construct",
    "wof:placetype":"venue"
},
  "geometry": {"coordinates":[-73.922952,41.032169],"type":"Point"}
}