{
  "type": "Feature",
  "properties": {
    "addr:full":"20 Stone Ct Syracuse NY 13204",
    "addr:housenumber":"20",
    "addr:postcode":"13204",
    "addr:street":"Stone Ct",
    "iso:country":"US",
    "sg:address":"20 Stone Ct",
    "sg:city":"Syracuse",
    "sg:classifiers":[
        {
            "category":"Organizations",
            "subcategory":"Non-profit Organization",
            "type":"Services"
        }
    ],
    "sg:phone":"+1 315 478 9762",
    "sg:postcode":"13204",
    "sg:province":"NY",
    "sg:tags":[
        "information",
        "alcoholism",
        "treatment"
    ],
    "wof:name":"Jericho",
    "wof:placetype":"venue"
},
  "geometry": {"coordinates":[-76.16167799999999,43.0458],"type":"Point"}
}