{
  "type": "Feature",
  "properties": {
    "addr:full":"370 Western Hwy S Tappan NY 10983",
    "addr:housenumber":"370",
    "addr:postcode":"10983",
    "addr:street":"Western Hwy S",
    "iso:country":"US",
    "sg:address":"370 Western Hwy S",
    "sg:city":"Tappan",
    "sg:classifiers":[
        {
            "category":"Education",
            "subcategory":"Special Training",
            "type":"Public Place"
        }
    ],
    "sg:phone":"+1 845 359 9101",
    "sg:postcode":"10983",
    "sg:province":"NY",
    "sg:tags":[
        "center"
    ],
    "wof:name":"Sage Learning",
    "wof:placetype":"venue"
},
  "geometry": {"coordinates":[-73.95222099999999,41.035938],"type":"Point"}
}