{
  "type": "Feature",
  "properties": {
    "addr:full":"72 Bowery New York NY 10013",
    "addr:housenumber":"72",
    "addr:postcode":"10013",
    "addr:street":"Bowery",
    "iso:country":"US",
    "sg:address":"72 Bowery",
    "sg:city":"New York",
    "sg:classifiers":[
        {
            "category":"Shopping",
            "subcategory":"Jewelry",
            "type":"Retail Goods"
        }
    ],
    "sg:phone":"+1 212 431 8820",
    "sg:postcode":"10013",
    "sg:province":"NY",
    "wof:name":"Kirsh M",
    "wof:placetype":"venue"
},
  "geometry": {"coordinates":[-73.995717,40.716802],"type":"Point"}
}