{
  "type": "Feature",
  "properties": {
    "addr:full":"71 Hudson Avenue Brooklyn NY 11201",
    "addr:housenumber":"71",
    "addr:postcode":"11201",
    "addr:street":"Hudson Avenue",
    "iso:country":"US",
    "sg:address":"71 Hudson Avenue",
    "sg:city":"Brooklyn",
    "sg:classifiers":[
        {
            "category":"Shopping",
            "subcategory":"Jewelry",
            "type":"Retail Goods"
        },
        {
            "category":"Restaurant",
            "type":"Food & Drink"
        }
    ],
    "sg:phone":"+1 718 625 9264",
    "sg:postcode":"11201",
    "sg:province":"NY",
    "wof:name":"Al's Lunchnet",
    "wof:placetype":"venue"
},
  "geometry": {"coordinates":[-73.980698,40.701483],"type":"Point"}
}