{
  "type": "Feature",
  "properties": {
    "iso:country":"US",
    "sg:address":"17 Charles St",
    "sg:city":"Frewsburg",
    "sg:classifiers":[
        {
            "category":"Professional",
            "subcategory":"Detective & Security Services",
            "type":"Services"
        }
    ],
    "sg:phone":"+1 716 569 2332",
    "sg:postcode":"14738",
    "sg:province":"NY",
    "sg:tags":[
        "investigator"
    ],
    "wof:name":"Twin Tiers Investigative Svc",
    "wof:placetype":"venue"
},
  "geometry": {"coordinates":[-79.154552,42.061866],"type":"Point"}
}