{
  "type": "Feature",
  "properties": {
    "addr:full":"10 Astor Pl Fl 5 New York NY 10003",
    "addr:housenumber":"10;5",
    "addr:postcode":"10003",
    "addr:street":"Astor Pl Fl",
    "iso:country":"US",
    "sg:address":"10 Astor Pl Fl 5",
    "sg:city":"New York",
    "sg:classifiers":[
        {
            "category":"Education",
            "subcategory":"University",
            "type":"Public Place"
        }
    ],
    "sg:phone":"+1 212 998 7190",
    "sg:postcode":"10003",
    "sg:province":"NY",
    "sg:tags":[
        "college"
    ],
    "wof:name":"New York University",
    "wof:placetype":"venue"
},
  "geometry": {"coordinates":[-73.992638,40.729891],"type":"Point"}
}