{
  "type": "Feature",
  "properties": {
    "addr:full":"108 Boxwood Ln Minoa NY 13116",
    "addr:housenumber":"108",
    "addr:postcode":"13116",
    "addr:street":"Boxwood Ln",
    "iso:country":"US",
    "sg:address":"108 Boxwood Ln",
    "sg:city":"Minoa",
    "sg:classifiers":[
        {
            "category":"Building & Trades",
            "subcategory":"Construction",
            "type":"Services"
        }
    ],
    "sg:phone":"+1 315 656 8847",
    "sg:postcode":"13116",
    "sg:province":"NY",
    "sg:tags":[
        "house"
    ],
    "wof:name":"Gpg Constructors Incorporated",
    "wof:placetype":"venue"
},
  "geometry": {"coordinates":[-76.00972400000001,43.079934],"type":"Point"}
}