{
  "type": "Feature",
  "properties": {
    "iso:country":"US",
    "sg:address":"500 W 140th St",
    "sg:city":"New York",
    "sg:classifiers":[
        {
            "category":"Personal",
            "subcategory":"Beauty Salon",
            "type":"Services"
        }
    ],
    "sg:phone":"+1 212 491 3008",
    "sg:postcode":"10031",
    "sg:province":"NY",
    "wof:name":"Guy Beard's Hair Salon",
    "wof:placetype":"venue"
},
  "geometry": {"coordinates":[-73.9513,40.822649],"type":"Point"}
}