{
  "type": "Feature",
  "properties": {
    "addr:full":"1230 Hicksville Rd Seaford NY 11758",
    "addr:housenumber":"1230",
    "addr:postcode":"11758",
    "addr:street":"Hicksville Rd",
    "iso:country":"US",
    "sg:address":"1230 Hicksville Rd",
    "sg:city":"Seaford",
    "sg:classifiers":[
        {
            "category":"Recreation",
            "type":"Entertainment"
        }
    ],
    "sg:phone":"+1 516 799 5425",
    "sg:postcode":"11758",
    "sg:province":"NY",
    "sg:tags":[
        "martial",
        "arts",
        "instruction"
    ],
    "wof:name":"Shaolin Self Defense Center",
    "wof:placetype":"venue"
},
  "geometry": {"coordinates":[-73.482907,40.707281],"type":"Point"}
}