{
  "type": "Feature",
  "properties": {
    "iso:country":"US",
    "sg:address":"92 Serenity Rd",
    "sg:city":"Wilmington",
    "sg:classifiers":[
        {
            "category":"Building & Trades",
            "subcategory":"Construction",
            "type":"Services"
        }
    ],
    "sg:phone":"+1 518 946 7642",
    "sg:postcode":"12997",
    "sg:province":"NY",
    "sg:tags":[
        "home",
        "improvement"
    ],
    "wof:name":"General Home & Camp Imprvmnt",
    "wof:placetype":"venue"
},
  "geometry": {"coordinates":[-73.79047799999999,44.444229],"type":"Point"}
}