{
  "type": "Feature",
  "properties": {
    "iso:country":"US",
    "sg:address":"5 W Cross St",
    "sg:city":"Hawthorne",
    "sg:classifiers":[
        {
            "category":"Organizations",
            "subcategory":"Labor Organization",
            "type":"Services"
        }
    ],
    "sg:phone":"+1 914 747 0309",
    "sg:postcode":"10532",
    "sg:province":"NY",
    "sg:website":"www.uwua.org",
    "wof:name":"Utility Workers Union-America",
    "wof:placetype":"venue"
},
  "geometry": {"coordinates":[-73.798312,41.107434],"type":"Point"}
}