{
  "type": "Feature",
  "properties": {
    "iso:country":"US",
    "sg:address":"10 W 32 St",
    "sg:city":"New York",
    "sg:classifiers":[
        {
            "category":"Restaurant",
            "type":"Food & Drink"
        }
    ],
    "sg:phone":"+1   ",
    "sg:postcode":"10001",
    "sg:province":"NY",
    "wof:name":"ABB Goo Jung",
    "wof:placetype":"venue"
},
  "geometry": {"coordinates":[-73.987889,40.748042],"type":"Point"}
}