{
  "type": "Feature",
  "properties": {
    "addr:full":"14 Longview Ave White Plains NY 10605",
    "addr:housenumber":"14",
    "addr:postcode":"10605",
    "addr:street":"Longview Ave",
    "iso:country":"US",
    "sg:address":"14 Longview Ave",
    "sg:city":"White Plains",
    "sg:classifiers":[
        {
            "category":"Social Services",
            "subcategory":"Adult Care",
            "type":"Services"
        }
    ],
    "sg:phone":"+1 914 946 0949",
    "sg:postcode":"10605",
    "sg:province":"NY",
    "sg:tags":[
        "residential",
        "hospital",
        "specialty"
    ],
    "wof:name":"Hawthorne House",
    "wof:placetype":"venue"
},
  "geometry": {"coordinates":[-73.76702299999999,41.024921],"type":"Point"}
}