{
  "type": "Feature",
  "properties": {
    "addr:full":"1800 E Tremont Ave Bronx NY 10460",
    "addr:housenumber":"1800",
    "addr:postcode":"10460",
    "addr:street":"E Tremont Ave",
    "iso:country":"US",
    "sg:address":"1800 E Tremont Ave",
    "sg:city":"Bronx",
    "sg:classifiers":[
        {
            "category":"Retail",
            "subcategory":"Auto Repair",
            "type":"Services"
        }
    ],
    "sg:phone":"+1 347 270 1066",
    "sg:postcode":"10460",
    "sg:province":"NY",
    "wof:name":"East Tremont Auto Repair Incorporated",
    "wof:placetype":"venue"
},
  "geometry": {"coordinates":[-73.86736399999999,40.840105],"type":"Point"}
}