{
  "type": "Feature",
  "properties": {
    "iso:country":"US",
    "sg:address":"38 Moccasin View Rd",
    "sg:city":"Fishkill",
    "sg:classifiers":[
        {
            "category":"Building & Trades",
            "subcategory":"Construction",
            "type":"Services"
        }
    ],
    "sg:phone":"+1 845 896 2358",
    "sg:postcode":"12524",
    "sg:province":"NY",
    "sg:tags":[
        "house"
    ],
    "wof:name":"Hudson Greystone Builders Inc",
    "wof:placetype":"venue"
},
  "geometry": {"coordinates":[-73.86237,41.559293],"type":"Point"}
}