{
  "type": "Feature",
  "properties": {
    "addr:full":"20 Alder Dr New Windsor NY 12553",
    "addr:housenumber":"20",
    "addr:postcode":"12553",
    "addr:street":"Alder Dr",
    "iso:country":"US",
    "sg:address":"20 Alder Dr",
    "sg:city":"New Windsor",
    "sg:classifiers":[
        {
            "category":"Freight",
            "type":"Transportation"
        }
    ],
    "sg:phone":"+1 845 497 3890",
    "sg:postcode":"12553",
    "sg:province":"NY",
    "sg:tags":[
        "trucking"
    ],
    "wof:name":"Anderson Brothers",
    "wof:placetype":"venue"
},
  "geometry": {"coordinates":[-74.105859,41.44242],"type":"Point"}
}