{
  "type": "Feature",
  "properties": {
    "iso:country":"US",
    "sg:address":"22 Queens Ct",
    "sg:city":"Orangeburg",
    "sg:classifiers":[
        {
            "category":"Place Of Worship",
            "type":"Public Place"
        },
        {
            "category":"Place Of Worship",
            "subcategory":"Temple",
            "type":"Public Place"
        }
    ],
    "sg:phone":"+1 845 359 1809",
    "sg:postcode":"10962",
    "sg:province":"NY",
    "sg:tags":[
        "church"
    ],
    "wof:name":"Timothy Temple",
    "wof:placetype":"venue"
},
  "geometry": {"coordinates":[-73.928978,41.034973],"type":"Point"}
}