{
  "type": "Feature",
  "properties": {
    "iso:country":"US",
    "sg:address":"6481 Co Rd 12",
    "sg:city":"Naples",
    "sg:classifiers":[
        {
            "category":"Organizations",
            "subcategory":"Religious Organization",
            "type":"Services"
        }
    ],
    "sg:phone":"+1   ",
    "sg:postcode":"14512",
    "sg:province":"NY",
    "wof:name":"Bristol Springs Free Church",
    "wof:placetype":"venue"
},
  "geometry": {"coordinates":[-77.38052,42.704922],"type":"Point"}
}