{
  "type": "Feature",
  "properties": {
    "iso:country":"US",
    "sg:address":"1180 3rd Ave Frnt 1",
    "sg:city":"New York",
    "sg:classifiers":[
        {
            "category":"Banks & Credit Unions",
            "subcategory":"Bank",
            "type":"Services"
        }
    ],
    "sg:phone":"+1 212 744 6670",
    "sg:postcode":"10065",
    "sg:province":"NY",
    "sg:website":"www.northforkbank.com",
    "wof:name":"CapitalOne",
    "wof:placetype":"venue"
},
  "geometry": {"coordinates":[-73.96226799999999,40.767705],"type":"Point"}
}