{
  "type": "Feature",
  "properties": {
    "iso:country":"US",
    "sg:address":"1 Lakeview Dr",
    "sg:city":"Warwick",
    "sg:classifiers":[
        {
            "category":"Building & Trades",
            "subcategory":"Construction",
            "type":"Services"
        }
    ],
    "sg:phone":"+1 845 986 4811",
    "sg:postcode":"10990",
    "sg:province":"NY",
    "sg:tags":[
        "carpentry",
        "contractor"
    ],
    "wof:name":"Oak Land Carpentry Inc",
    "wof:placetype":"venue"
},
  "geometry": {"coordinates":[-74.314521,41.287124],"type":"Point"}
}