{
  "type": "Feature",
  "properties": {
    "addr:full":"101 W Main St Macedon NY 14502",
    "addr:housenumber":"101",
    "addr:postcode":"14502",
    "addr:street":"W Main St",
    "iso:country":"US",
    "sg:address":"101 W Main St",
    "sg:city":"Macedon",
    "sg:classifiers":[
        {
            "category":"Retail",
            "subcategory":"Animal Services",
            "type":"Services"
        }
    ],
    "sg:phone":"+1 315 986 2876",
    "sg:postcode":"14502",
    "sg:province":"NY",
    "sg:tags":[
        "pet",
        "grooming",
        "washing"
    ],
    "wof:name":"Angis Groom Room",
    "wof:placetype":"venue"
},
  "geometry": {"coordinates":[-77.300386,43.068641],"type":"Point"}
}