{
  "type": "Feature",
  "properties": {
    "addr:full":"106 W Elm St Oneida NY 13421",
    "addr:housenumber":"106",
    "addr:postcode":"13421",
    "addr:street":"W Elm St",
    "iso:country":"US",
    "sg:address":"106 W Elm St",
    "sg:city":"Oneida",
    "sg:classifiers":[
        {
            "category":"Building & Trades",
            "subcategory":"Construction",
            "type":"Services"
        }
    ],
    "sg:phone":"+1 315 363 9086",
    "sg:postcode":"13421",
    "sg:province":"NY",
    "sg:tags":[
        "roofing",
        "contractor"
    ],
    "wof:name":"Campany Roofing",
    "wof:placetype":"venue"
},
  "geometry": {"coordinates":[-75.65360800000001,43.097423],"type":"Point"}
}