{
  "type": "Feature",
  "properties": {
    "addr:full":"1625A Cody Ave Ridgewood NY 11385",
    "addr:housenumber":"1625a",
    "addr:postcode":"11385",
    "addr:street":"Cody Ave",
    "iso:country":"US",
    "sg:address":"1625A Cody Ave",
    "sg:city":"Ridgewood",
    "sg:classifiers":[
        {
            "category":"Home & Garden",
            "subcategory":"Home Furnishings",
            "type":"Retail Goods"
        },
        {
            "category":"Manufacturing",
            "subcategory":"Glass & Minerals",
            "type":"Manufacturing & Wholesale Goods"
        }
    ],
    "sg:phone":"+1 718 530 0167",
    "sg:postcode":"11385",
    "sg:province":"NY",
    "sg:tags":[
        "mirrors-resilver",
        "mirror"
    ],
    "sg:website":"http://www.waltersmirror.com",
    "wof:name":"Walter's Mirror",
    "wof:placetype":"venue"
},
  "geometry": {"coordinates":[-73.89976299999999,40.694996],"type":"Point"}
}