{
  "type": "Feature",
  "properties": {
    "addr:full":"1983 Marcus Ave New Hyde Park NY 11042",
    "addr:housenumber":"1983",
    "addr:postcode":"11042",
    "addr:street":"Marcus Ave",
    "iso:country":"US",
    "sg:address":"1983 Marcus Ave",
    "sg:city":"New Hyde Park",
    "sg:classifiers":[
        {
            "category":"Wholesale",
            "subcategory":"Electrical",
            "type":"Manufacturing & Wholesale Goods"
        }
    ],
    "sg:phone":"+1 516 326 0730",
    "sg:postcode":"11042",
    "sg:province":"NY",
    "sg:tags":[
        "control",
        "electronic",
        "motor"
    ],
    "wof:name":"Eaton Electrical Inc",
    "wof:placetype":"venue"
},
  "geometry": {"coordinates":[-73.69170099999999,40.757063],"type":"Point"}
}