{
  "type": "Feature",
  "properties": {
    "addr:full":"206 W 40 St New York NY 10018",
    "addr:housenumber":"206",
    "addr:postcode":"10018",
    "addr:street":"W 40 St",
    "iso:country":"US",
    "sg:address":"206 W 40 St",
    "sg:city":"New York",
    "sg:classifiers":[
        {
            "category":"Wholesale",
            "subcategory":"Apparel",
            "type":"Manufacturing & Wholesale Goods"
        }
    ],
    "sg:phone":"+1 212 768 4771",
    "sg:postcode":"10018",
    "sg:province":"NY",
    "sg:tags":[
        "button"
    ],
    "wof:name":"Button World",
    "wof:placetype":"venue"
},
  "geometry": {"coordinates":[-73.99063099999999,40.755811],"type":"Point"}
}