{
  "type": "Feature",
  "properties": {
    "addr:full":"40 S Ferris St Irvington NY 10533",
    "addr:housenumber":"40",
    "addr:postcode":"ny 10533",
    "addr:street":"S Ferris St",
    "iso:country":"US",
    "sg:address":"40 S Ferris St",
    "sg:city":"Irvington",
    "sg:classifiers":[
        {
            "category":"Manufacturing",
            "subcategory":"Printing",
            "type":"Manufacturing & Wholesale Goods"
        }
    ],
    "sg:phone":"+1   ",
    "sg:postcode":"10533",
    "sg:province":"NY",
    "sg:tags":[
        "lithographic",
        "b",
        "commercial",
        "typesetting"
    ],
    "wof:name":"Kelly Graphics",
    "wof:placetype":"venue"
},
  "geometry": {"coordinates":[-73.86866999999999,41.037793],"type":"Point"}
}