{
  "type": "Feature",
  "properties": {
    "addr:full":"457 Main St Farmingdale NY 11735",
    "addr:housenumber":"457",
    "addr:postcode":"11735",
    "addr:street":"Main St",
    "iso:country":"US",
    "sg:address":"457 Main St",
    "sg:city":"Farmingdale",
    "sg:classifiers":[
        {
            "category":"Professional",
            "subcategory":"Printing & Photocopies",
            "type":"Services"
        }
    ],
    "sg:phone":"+1 516 293 4444",
    "sg:postcode":"11735",
    "sg:province":"NY",
    "sg:tags":[
        "duplicating",
        "copying"
    ],
    "wof:name":"Main Street Mail Ctr",
    "wof:placetype":"venue"
},
  "geometry": {"coordinates":[-73.444681,40.728896],"type":"Point"}
}