{
  "type": "Feature",
  "properties": {
    "addr:full":"582 Revere Dr Yorktown Heights NY 10598",
    "addr:housenumber":"582",
    "addr:postcode":"10598",
    "addr:street":"Revere Dr",
    "iso:country":"US",
    "sg:address":"582 Revere Dr",
    "sg:city":"Yorktown Heights",
    "sg:classifiers":[
        {
            "category":"Building & Trades",
            "subcategory":"Construction",
            "type":"Services"
        }
    ],
    "sg:phone":"+1 914 962 5347",
    "sg:postcode":"10598",
    "sg:province":"NY",
    "sg:tags":[
        "carpentry",
        "contractor"
    ],
    "wof:name":"Fanelli Carpentry",
    "wof:placetype":"venue"
},
  "geometry": {"coordinates":[-73.787244,41.25276],"type":"Point"}
}