{
  "type": "Feature",
  "properties": {
    "iso:country":"US",
    "sg:address":"558 Broadway",
    "sg:city":"New York",
    "sg:classifiers":[
        {
            "category":"Shopping",
            "subcategory":"Clothing, Apparel, & Fashions",
            "type":"Retail Goods"
        }
    ],
    "sg:phone":"+1 212 343 2722",
    "sg:postcode":"10012",
    "sg:province":"NY",
    "sg:tags":[
        "clothing",
        "women's"
    ],
    "sg:website":"www.hm.com",
    "wof:name":"H & M",
    "wof:placetype":"venue"
},
  "geometry": {"coordinates":[-73.997803,40.7239],"type":"Point"}
}