{
  "type": "Feature",
  "properties": {
    "addr:full":"10545 Main St Clarence NY 14031",
    "addr:housenumber":"10545",
    "addr:postcode":"14031",
    "addr:street":"Main St",
    "iso:country":"US",
    "sg:address":"10545 Main St",
    "sg:city":"Clarence",
    "sg:classifiers":[
        {
            "category":"Shopping",
            "type":"Retail Goods"
        }
    ],
    "sg:phone":"+1   ",
    "sg:postcode":"14031",
    "sg:province":"NY",
    "sg:tags":[
        "merchandise"
    ],
    "wof:name":"West Art Gallery",
    "wof:placetype":"venue"
},
  "geometry": {"coordinates":[-78.595822,42.980268],"type":"Point"}
}