{
  "type": "Feature",
  "properties": {
    "addr:full":"8 Cold Brook St Poland NY 13431",
    "addr:housenumber":"8",
    "addr:postcode":"13431",
    "addr:street":"Cold Brook St",
    "iso:country":"US",
    "sg:address":"8 Cold Brook St",
    "sg:city":"Poland",
    "sg:classifiers":[
        {
            "category":"Food & Beverages",
            "subcategory":"Groceries & Convenience Stores",
            "type":"Retail Goods"
        }
    ],
    "sg:phone":"+1 315 826 5417",
    "sg:postcode":"13431",
    "sg:province":"NY",
    "sg:website":"http://www.stewartsshops.com",
    "wof:name":"Stewart's Shop",
    "wof:placetype":"venue"
},
  "geometry": {"coordinates":[-75.061053,43.226033],"type":"Point"}
}