{
  "type": "Feature",
  "properties": {
    "addr:full":"1291 Lexington Ave New York NY 10028",
    "addr:housenumber":"1291",
    "addr:postcode":"10028",
    "addr:street":"Lexington Ave",
    "iso:country":"US",
    "sg:address":"1291 Lexington Ave",
    "sg:city":"New York",
    "sg:classifiers":[
        {
            "category":"Professional",
            "type":"Services"
        }
    ],
    "sg:phone":"+1 212 987 1515",
    "sg:postcode":"10028",
    "sg:province":"NY",
    "sg:tags":[
        "optician",
        "eyewear"
    ],
    "wof:name":"Bella Vista Optics",
    "wof:placetype":"venue"
},
  "geometry": {"coordinates":[-73.95504,40.77996],"type":"Point"}
}