{
  "type": "Feature",
  "properties": {
    "addr:full":"30 Washington Ave Suffern NY 10901",
    "addr:housenumber":"30",
    "addr:postcode":"10901",
    "addr:street":"Washington Ave",
    "iso:country":"US",
    "sg:address":"30 Washington Ave",
    "sg:city":"Suffern",
    "sg:classifiers":[
        {
            "category":"Retail",
            "subcategory":"Auto Repair",
            "type":"Services"
        }
    ],
    "sg:phone":"+1 845 357 7770",
    "sg:postcode":"10901",
    "sg:province":"NY",
    "sg:tags":[
        "repairing",
        "automobile"
    ],
    "wof:name":"Royal Coach Inc",
    "wof:placetype":"venue"
},
  "geometry": {"coordinates":[-74.148189,41.117578],"type":"Point"}
}