{
  "type": "Feature",
  "properties": {
    "iso:country":"US",
    "sg:address":"1932 English Rd",
    "sg:city":"Rochester",
    "sg:classifiers":[
        {
            "category":"Building & Trades",
            "subcategory":"Construction",
            "type":"Services"
        }
    ],
    "sg:phone":"+1 585 225 7463",
    "sg:postcode":"14616",
    "sg:province":"NY",
    "sg:tags":[
        "carpentry",
        "contractor"
    ],
    "wof:name":"David Scorse",
    "wof:placetype":"venue"
},
  "geometry": {"coordinates":[-77.703468,43.23866],"type":"Point"}
}