{
  "type": "Feature",
  "properties": {
    "addr:full":"811 Tonawanda St Buffalo NY 14207",
    "addr:housenumber":"811",
    "addr:postcode":"14207",
    "addr:street":"Tonawanda St",
    "iso:country":"US",
    "sg:address":"811 Tonawanda St",
    "sg:city":"Buffalo",
    "sg:classifiers":[
        {
            "category":"Organizations",
            "subcategory":"Labor Organization",
            "type":"Services"
        }
    ],
    "sg:phone":"+1 716 876 1016",
    "sg:postcode":"14207",
    "sg:province":"NY",
    "wof:name":"United Auto Workers",
    "wof:placetype":"venue"
},
  "geometry": {"coordinates":[-78.90380399999999,42.949686],"type":"Point"}
}