{
  "type": "Feature",
  "properties": {
    "addr:full":"337 Peekskill Hollow Rd Putnam Valley NY 10579",
    "addr:housenumber":"337",
    "addr:postcode":"10579",
    "addr:street":"Peekskill Hollow Rd",
    "iso:country":"US",
    "sg:address":"337 Peekskill Hollow Rd",
    "sg:city":"Putnam Valley",
    "sg:classifiers":[
        {
            "category":"Organizations",
            "subcategory":"Religious Organization",
            "type":"Services"
        }
    ],
    "sg:phone":"+1 845 526 3788",
    "sg:postcode":"10579",
    "sg:province":"NY",
    "sg:tags":[
        "executive"
    ],
    "wof:name":"Grace United Methodist Church",
    "wof:placetype":"venue"
},
  "geometry": {"coordinates":[-73.83313099999999,41.364909],"type":"Point"}
}