{
  "type": "Feature",
  "properties": {
    "addr:full":"24 Circle Dr Voorheesville NY 12186",
    "addr:housenumber":"24",
    "addr:postcode":"12186",
    "addr:street":"Circle Dr",
    "iso:country":"US",
    "sg:address":"24 Circle Dr",
    "sg:city":"Voorheesville",
    "sg:classifiers":[
        {
            "category":"Building & Trades",
            "subcategory":"Construction",
            "type":"Services"
        }
    ],
    "sg:phone":"+1 518 765 9374",
    "sg:postcode":"12186",
    "sg:province":"NY",
    "sg:tags":[
        "floor",
        "laying",
        "contractor"
    ],
    "wof:name":"Kris Konis Installation",
    "wof:placetype":"venue"
},
  "geometry": {"coordinates":[-73.920543,42.648033],"type":"Point"}
}