{
  "type": "Feature",
  "properties": {
    "addr:full":"2016 Linden Blvd Elmont NY 11003",
    "addr:housenumber":"2016",
    "addr:postcode":"11003",
    "addr:street":"Linden Blvd",
    "iso:country":"US",
    "sg:address":"2016 Linden Blvd",
    "sg:city":"Elmont",
    "sg:classifiers":[
        {
            "category":"Wholesale",
            "subcategory":"Toys & Hobbies",
            "type":"Manufacturing & Wholesale Goods"
        }
    ],
    "sg:phone":"+1 516 285 3929",
    "sg:postcode":"11003",
    "sg:province":"NY",
    "sg:tags":[
        "wholesaler"
    ],
    "wof:name":"Jeff Berkowitz Sales",
    "wof:placetype":"venue"
},
  "geometry": {"coordinates":[-73.72082399999999,40.689071],"type":"Point"}
}