{
  "type": "Feature",
  "properties": {
    "addr:full":"175 N Main St Wellsville NY 14895",
    "addr:housenumber":"175",
    "addr:postcode":"14895",
    "addr:street":"N Main St",
    "iso:country":"US",
    "sg:address":"175 N Main St",
    "sg:city":"Wellsville",
    "sg:classifiers":[
        {
            "category":"Health Services",
            "subcategory":"Doctor",
            "type":"Services"
        },
        {
            "category":"Wholesale",
            "subcategory":"Medical Equipment & Supplies",
            "type":"Manufacturing & Wholesale Goods"
        },
        {
            "category":"Retail",
            "subcategory":"Repair Shop",
            "type":"Services"
        },
        {
            "category":"Health Services",
            "subcategory":"Health Practitioner",
            "type":"Services"
        }
    ],
    "sg:phone":"+1 585 593 3310",
    "sg:postcode":"14895",
    "sg:province":"NY",
    "sg:tags":[
        "sound",
        "repairing",
        "level",
        "testing",
        "aids-parts",
        "hearing",
        "device",
        "assistive",
        "aid",
        "audiologists"
    ],
    "sg:website":"http://www.beltone.com",
    "wof:name":"Beltone Hearing Aid Center",
    "wof:placetype":"venue"
},
  "geometry": {"coordinates":[-77.949692,42.122822],"type":"Point"}
}