{
  "type": "Feature",
  "properties": {
    "addr:full":"22 Mackay Dr Hauppauge NY 11788",
    "addr:housenumber":"22",
    "addr:postcode":"11788",
    "addr:street":"Mackay Dr",
    "iso:country":"US",
    "sg:address":"22 Mackay Dr",
    "sg:city":"Hauppauge",
    "sg:classifiers":[
        {
            "category":"Freight",
            "type":"Transportation"
        }
    ],
    "sg:phone":"+1 631 232 0007",
    "sg:postcode":"11788",
    "sg:province":"NY",
    "wof:name":"GSS Transportation Inc",
    "wof:placetype":"venue"
},
  "geometry": {"coordinates":[-73.231037,40.818925],"type":"Point"}
}