{
  "type": "Feature",
  "properties": {
    "addr:full":"3 Owens Rd Croton Falls NY 10519",
    "addr:housenumber":"3",
    "addr:postcode":"10519",
    "addr:street":"Owens Rd",
    "iso:country":"US",
    "sg:address":"3 Owens Rd",
    "sg:city":"Croton Falls",
    "sg:classifiers":[
        {
            "category":"Professional",
            "type":"Services"
        }
    ],
    "sg:phone":"+1 914 277 4435",
    "sg:postcode":"10519",
    "sg:province":"NY",
    "sg:tags":[
        "establishment"
    ],
    "wof:name":"KAHG Inc",
    "wof:placetype":"venue"
},
  "geometry": {"coordinates":[-73.660651,41.349175],"type":"Point"}
}