{
  "type": "Feature",
  "properties": {
    "iso:country":"US",
    "sg:address":"1329 North Ave",
    "sg:city":"New Rochelle",
    "sg:classifiers":[
        {
            "category":"Restaurant",
            "type":"Food & Drink"
        }
    ],
    "sg:phone":"+1 914 636 6813",
    "sg:postcode":"10804",
    "sg:province":"NY",
    "wof:name":"Broadway Sam's Pizza",
    "wof:placetype":"venue"
},
  "geometry": {"coordinates":[-73.795585,40.946749],"type":"Point"}
}