{
  "type": "Feature",
  "properties": {
    "addr:full":"128 Court St White Plains NY 10601",
    "addr:housenumber":"128",
    "addr:postcode":"10601",
    "addr:street":"Court St",
    "iso:country":"US",
    "sg:address":"128 Court St",
    "sg:city":"White Plains",
    "sg:classifiers":[
        {
            "category":"Insurance",
            "subcategory":"Insurance Agent",
            "type":"Services"
        }
    ],
    "sg:phone":"+1 914 682 4444",
    "sg:postcode":"10601",
    "sg:province":"NY",
    "sg:tags":[
        "adjuster"
    ],
    "sg:website":"www.terrierclaims.com",
    "wof:name":"Terrier Claims Svc",
    "wof:placetype":"venue"
},
  "geometry": {"coordinates":[-73.766425,41.028921],"type":"Point"}
}