{
  "type": "Feature",
  "properties": {
    "iso:country":"US",
    "sg:address":"219 North Ave",
    "sg:city":"New Rochelle",
    "sg:classifiers":[
        {
            "category":"Bars & Pubs",
            "type":"Food & Drink"
        }
    ],
    "sg:phone":"+1   ",
    "sg:postcode":"10801",
    "sg:province":"NY",
    "sg:tags":[
        "bar"
    ],
    "wof:name":"Spectators",
    "wof:placetype":"venue"
},
  "geometry": {"coordinates":[-73.78084800000001,40.909734],"type":"Point"}
}