{
  "type": "Feature",
  "properties": {
    "addr:full":"575 Lexington Avenue New York NY 10022",
    "addr:housenumber":"575",
    "addr:postcode":"10022",
    "addr:street":"Lexington Avenue",
    "iso:country":"US",
    "sg:address":"575 Lexington Avenue",
    "sg:city":"New York",
    "sg:classifiers":[
        {
            "category":"Professional",
            "subcategory":"Accounting & Tax Preparation",
            "type":"Services"
        }
    ],
    "sg:phone":"+1 212 758 8050",
    "sg:postcode":"10022",
    "sg:province":"NY",
    "sg:tags":[
        "accountant"
    ],
    "wof:name":"Krant & Bialick",
    "wof:placetype":"venue"
},
  "geometry": {"coordinates":[-73.971767,40.75718],"type":"Point"}
}