{
  "type": "Feature",
  "properties": {
    "iso:country":"US",
    "sg:address":"1938 McDonald Ave",
    "sg:city":"Brooklyn",
    "sg:classifiers":[
        {
            "category":"Professional",
            "type":"Services"
        }
    ],
    "sg:phone":"+1 718 627 8124",
    "sg:postcode":"11223",
    "sg:province":"NY",
    "sg:tags":[
        "establishment"
    ],
    "sg:website":"www.infinitiphoto.com",
    "wof:name":"Infiniti Photo",
    "wof:placetype":"venue"
},
  "geometry": {"coordinates":[-73.972537,40.606092],"type":"Point"}
}