{
  "type": "Feature",
  "properties": {
    "iso:country":"US",
    "sg:address":"54 Country Dr",
    "sg:city":"Plainview",
    "sg:classifiers":[
        {
            "category":"Health Services",
            "subcategory":"Chiropractor",
            "type":"Services"
        },
        {
            "category":"Professional",
            "subcategory":"Management & Consulting",
            "type":"Services"
        }
    ],
    "sg:phone":"+1 516 935 9400",
    "sg:postcode":"11803",
    "sg:province":"NY",
    "sg:tags":[
        "business"
    ],
    "wof:name":"Professional Medical PC",
    "wof:placetype":"venue"
},
  "geometry": {"coordinates":[-73.47299,40.784172],"type":"Point"}
}