{
  "type": "Feature",
  "properties": {
    "addr:full":"4922 Merrill Dr Liverpool NY 13088",
    "addr:housenumber":"4922",
    "addr:postcode":"13088",
    "addr:street":"Merrill Dr",
    "iso:country":"US",
    "sg:address":"4922 Merrill Dr",
    "sg:city":"Liverpool",
    "sg:classifiers":[
        {
            "category":"Building & Trades",
            "subcategory":"Landscaping Services",
            "type":"Services"
        }
    ],
    "sg:phone":"+1 315 451 2011",
    "sg:postcode":"13088",
    "sg:province":"NY",
    "sg:tags":[
        "lawn",
        "maintenance",
        "grounds"
    ],
    "wof:name":"Ward's Lawn Care",
    "wof:placetype":"venue"
},
  "geometry": {"coordinates":[-76.173821,43.107547],"type":"Point"}
}