{
  "type": "Feature",
  "properties": {
    "iso:country":"US",
    "sg:address":"490 Canal Rd",
    "sg:city":"Port Jefferson Station",
    "sg:classifiers":[
        {
            "category":"Shopping",
            "type":"Retail Goods"
        }
    ],
    "sg:phone":"+1   ",
    "sg:postcode":"11776",
    "sg:province":"NY",
    "sg:tags":[
        "merchandise"
    ],
    "wof:name":"Uncle Rays Discount Sls & Dist",
    "wof:placetype":"venue"
},
  "geometry": {"coordinates":[-73.02482500000001,40.91939],"type":"Point"}
}