{
  "type": "Feature",
  "properties": {
    "addr:full":"555 5th Avenue New York NY 10017",
    "addr:housenumber":"555",
    "addr:postcode":"10017",
    "addr:street":"5Th Avenue",
    "iso:country":"US",
    "sg:address":"555 5th Avenue",
    "sg:city":"New York",
    "sg:classifiers":[
        {
            "category":"Shopping",
            "subcategory":"Books",
            "type":"Retail Goods"
        }
    ],
    "sg:phone":"+1 212 697 3048",
    "sg:postcode":"10017",
    "sg:province":"NY",
    "sg:tags":[
        "bookstore"
    ],
    "wof:name":"Barnes & Noble Booksellers",
    "wof:placetype":"venue"
},
  "geometry": {"coordinates":[-73.979056,40.75581],"type":"Point"}
}