{
  "type": "Feature",
  "properties": {
    "addr:full":"127 Maxwell Ave Syracuse NY 13212",
    "addr:housenumber":"127",
    "addr:postcode":"13212",
    "addr:street":"Maxwell Ave",
    "iso:country":"US",
    "sg:address":"127 Maxwell Ave",
    "sg:city":"Syracuse",
    "sg:classifiers":[
        {
            "category":"Building & Trades",
            "subcategory":"Landscaping Services",
            "type":"Services"
        }
    ],
    "sg:phone":"+1 315 458 5786",
    "sg:postcode":"13212",
    "sg:province":"NY",
    "wof:name":"Honest Lawn Care Plus",
    "wof:placetype":"venue"
},
  "geometry": {"coordinates":[-76.1242,43.139626],"type":"Point"}
}