{
  "type": "Feature",
  "properties": {
    "addr:full":"236 E 47th St New York NY 10017",
    "addr:housenumber":"236",
    "addr:postcode":"10017",
    "addr:street":"E 47Th St",
    "iso:country":"US",
    "sg:address":"236 E 47th St",
    "sg:city":"New York",
    "sg:classifiers":[
        {
            "category":"Real Estate",
            "subcategory":"Real Estate Operator",
            "type":"Services"
        }
    ],
    "sg:phone":"+1 212 754 0285",
    "sg:postcode":"10017",
    "sg:province":"NY",
    "sg:tags":[
        "condominium"
    ],
    "sg:website":"www.heronltd.com",
    "wof:name":"Club At Turtle Bay",
    "wof:placetype":"venue"
},
  "geometry": {"coordinates":[-73.970567,40.753259],"type":"Point"}
}