{
  "type": "Feature",
  "properties": {
    "addr:full":"716 State St Schenectady NY 12307",
    "addr:housenumber":"716",
    "addr:postcode":"12307",
    "addr:street":"State St",
    "iso:country":"US",
    "sg:address":"716 State St",
    "sg:city":"Schenectady",
    "sg:classifiers":[
        {
            "category":"Restaurant",
            "type":"Food & Drink"
        }
    ],
    "sg:phone":"+1   ",
    "sg:postcode":"12307",
    "sg:province":"NY",
    "sg:tags":[
        "eating"
    ],
    "wof:name":"Dominos Pizza",
    "wof:placetype":"venue"
},
  "geometry": {"coordinates":[-73.936707,42.809253],"type":"Point"}
}