{
  "type": "Feature",
  "properties": {
    "iso:country":"US",
    "sg:address":"471 Washington Ave",
    "sg:city":"Albany",
    "sg:classifiers":[
        {
            "category":"Manufacturing",
            "subcategory":"Buildings",
            "type":"Manufacturing & Wholesale Goods"
        },
        {
            "category":"Real Estate",
            "subcategory":"Developer",
            "type":"Services"
        },
        {
            "category":"Building & Trades",
            "subcategory":"Construction",
            "type":"Services"
        }
    ],
    "sg:phone":"+1 518 438 0528",
    "sg:postcode":"12206",
    "sg:province":"NY",
    "sg:tags":[
        "home",
        "builder",
        "contractor"
    ],
    "wof:name":"France, K R & Company Builders",
    "wof:placetype":"venue"
},
  "geometry": {"coordinates":[-73.773495,42.662658],"type":"Point"}
}