{
  "type": "Feature",
  "properties": {
    "addr:full":"578 Seneca St Ste 2 Oneida NY 13421",
    "addr:housenumber":"578",
    "addr:postcode":"13421",
    "addr:street":"Seneca St Ste 2",
    "iso:country":"US",
    "sg:address":"578 Seneca St Ste 2",
    "sg:city":"Oneida",
    "sg:classifiers":[
        {
            "category":"Health Services",
            "subcategory":"Doctor",
            "type":"Services"
        }
    ],
    "sg:phone":"+1 315 824 2420",
    "sg:postcode":"13421",
    "sg:province":"NY",
    "sg:tags":[
        "physician",
        "surgeon"
    ],
    "wof:name":"John J Costello Jr Do Pllc",
    "wof:placetype":"venue"
},
  "geometry": {"coordinates":[-75.652236,43.079093],"type":"Point"}
}