{
  "type": "Feature",
  "properties": {
    "addr:full":"110 Lafayette Street New York NY 10013",
    "addr:housenumber":"110",
    "addr:postcode":"10013",
    "addr:street":"Lafayette Street",
    "iso:country":"US",
    "sg:address":"110 Lafayette Street",
    "sg:city":"New York",
    "sg:classifiers":[
        {
            "category":"Organizations",
            "subcategory":"Non-profit Organization",
            "type":"Services"
        }
    ],
    "sg:phone":"+1 212 966 6420",
    "sg:postcode":"10013",
    "sg:province":"NY",
    "sg:tags":[
        "service/non-profit",
        "community"
    ],
    "sg:website":"www.lawyersforchildren.com",
    "wof:name":"Lawyers For Children",
    "wof:placetype":"venue"
},
  "geometry": {"coordinates":[-74.000721,40.718201],"type":"Point"}
}