{
  "type": "Feature",
  "properties": {
    "iso:country":"US",
    "sg:address":"42 Executive Blvd",
    "sg:city":"Farmingdale",
    "sg:classifiers":[
        {
            "category":"Shopping",
            "subcategory":"Optical Goods",
            "type":"Retail Goods"
        }
    ],
    "sg:phone":"+1 631 752 0234",
    "sg:postcode":"11735",
    "sg:province":"NY",
    "sg:tags":[
        "optician"
    ],
    "wof:name":"Seeing Technologies Intl",
    "wof:placetype":"venue"
},
  "geometry": {"coordinates":[-73.429361,40.720992],"type":"Point"}
}