{
  "type": "Feature",
  "properties": {
    "iso:country":"US",
    "sg:address":"182 Sobieski St",
    "sg:city":"Buffalo",
    "sg:classifiers":[
        {
            "category":"Organizations",
            "subcategory":"Religious Organization",
            "type":"Services"
        }
    ],
    "sg:phone":"+1 716 892 2606",
    "sg:postcode":"14212",
    "sg:province":"NY",
    "wof:name":"Darul Uloom Al Madania Inc",
    "wof:placetype":"venue"
},
  "geometry": {"coordinates":[-78.832756,42.897522],"type":"Point"}
}