{
  "type": "Feature",
  "properties": {
    "addr:full":"4725 Vernon Boulevard Long Island City NY 11101",
    "addr:housenumber":"4725",
    "addr:postcode":"11101",
    "addr:street":"Vernon Boulevard",
    "iso:country":"US",
    "sg:address":"4725 Vernon Boulevard",
    "sg:city":"Long Island City",
    "sg:classifiers":[
        {
            "category":"Restaurant",
            "type":"Food & Drink"
        }
    ],
    "sg:phone":"+1 718 482 8151",
    "sg:postcode":"11101",
    "sg:province":"NY",
    "sg:tags":[
        "italian"
    ],
    "sg:website":"www.lucaloungenyc.com/masso.html",
    "wof:name":"Masso",
    "wof:placetype":"venue"
},
  "geometry": {"coordinates":[-73.953396,40.744822],"type":"Point"}
}