{
  "type": "Feature",
  "properties": {
    "addr:full":"50 W 17 St New York NY 10011",
    "addr:housenumber":"50",
    "addr:postcode":"10011",
    "addr:street":"W 17 St",
    "iso:country":"US",
    "sg:address":"50 W 17 St",
    "sg:city":"New York",
    "sg:classifiers":[
        {
            "category":"Professional",
            "subcategory":"Business Services",
            "type":"Services"
        },
        {
            "category":"Building & Trades",
            "subcategory":"Construction",
            "type":"Services"
        }
    ],
    "sg:phone":"+1 212 843 8800",
    "sg:postcode":"10011",
    "sg:province":"NY",
    "sg:tags":[
        "shop",
        "scenic",
        "set",
        "design",
        "designer"
    ],
    "wof:name":"Hotopp Associates Ltd",
    "wof:placetype":"venue"
},
  "geometry": {"coordinates":[-73.99426200000001,40.738528],"type":"Point"}
}