{
  "type": "Feature",
  "properties": {
    "iso:country":"US",
    "sg:address":"122 Linden Blvd",
    "sg:city":"Brooklyn",
    "sg:classifiers":[
        {
            "category":"Real Estate",
            "subcategory":"Real Estate Agent",
            "type":"Services"
        }
    ],
    "sg:phone":"+1 718 941 2576",
    "sg:postcode":"11226",
    "sg:province":"NY",
    "wof:name":"Homeland Recovery LLC",
    "wof:placetype":"venue"
},
  "geometry": {"coordinates":[-73.953959,40.652325],"type":"Point"}
}