{
  "type": "Feature",
  "properties": {
    "addr:full":"1202 Cortelyou Rd Brooklyn NY 11218",
    "addr:housenumber":"1202",
    "addr:postcode":"11218",
    "addr:street":"Cortelyou Rd",
    "iso:country":"US",
    "sg:address":"1202 Cortelyou Rd",
    "sg:city":"Brooklyn",
    "sg:classifiers":[
        {
            "category":"Restaurant",
            "type":"Food & Drink"
        }
    ],
    "sg:phone":"+1 718 693 1022",
    "sg:postcode":"11218",
    "sg:province":"NY",
    "sg:tags":[
        "mexican"
    ],
    "wof:name":"Cinco de Mayo Restaurant",
    "wof:placetype":"venue"
},
  "geometry": {"coordinates":[-73.96701899999999,40.640044],"type":"Point"}
}