{
  "type": "Feature",
  "properties": {
    "addr:full":"4211 Broadway Astoria NY 11103",
    "addr:housenumber":"4211",
    "addr:postcode":"11103",
    "addr:street":"Broadway",
    "iso:country":"US",
    "sg:address":"4211 Broadway",
    "sg:city":"Astoria",
    "sg:classifiers":[
        {
            "category":"Deli",
            "type":"Food & Drink"
        }
    ],
    "sg:phone":"+1 718 726 2047",
    "sg:postcode":"11103",
    "sg:province":"NY",
    "wof:name":"Tma Grocery Inc",
    "wof:placetype":"venue"
},
  "geometry": {"coordinates":[-73.917,40.758099],"type":"Point"}
}