{
  "type": "Feature",
  "properties": {
    "iso:country":"US",
    "sg:address":"32 Sullivan Dr",
    "sg:city":"Lake George",
    "sg:classifiers":[
        {
            "category":"Real Estate",
            "subcategory":"Real Estate Agent",
            "type":"Services"
        }
    ],
    "sg:phone":"+1 518 793 7895",
    "sg:postcode":"12845",
    "sg:province":"NY",
    "wof:name":"Df Properties",
    "wof:placetype":"venue"
},
  "geometry": {"coordinates":[-73.679202,43.367192],"type":"Point"}
}