{
  "type": "Feature",
  "properties": {
    "addr:full":"304 E 48th St New York NY 10017",
    "addr:housenumber":"304",
    "addr:postcode":"10017",
    "addr:street":"E 48Th St",
    "iso:country":"US",
    "sg:address":"304 E 48th St",
    "sg:city":"New York",
    "sg:classifiers":[
        {
            "category":"Building & Trades",
            "subcategory":"Locksmith",
            "type":"Services"
        }
    ],
    "sg:phone":"+1 917 289 1388",
    "sg:postcode":"10017",
    "sg:province":"NY",
    "sg:tags":[
        "key"
    ],
    "wof:name":"1 24 Hour 7 Day Emergency Locksmith",
    "wof:placetype":"venue"
},
  "geometry": {"coordinates":[-73.969114,40.753488],"type":"Point"}
}