{
  "type": "Feature",
  "properties": {
    "iso:country":"US",
    "sg:address":"1839 Nostrand Ave",
    "sg:city":"Brooklyn",
    "sg:classifiers":[
        {
            "category":"Wholesale",
            "subcategory":"Dairy",
            "type":"Manufacturing & Wholesale Goods"
        }
    ],
    "sg:phone":"+1 718 856 0821",
    "sg:postcode":"11226",
    "sg:province":"NY",
    "sg:tags":[
        "product",
        "eating"
    ],
    "wof:name":"Taste The Tropics USA Inc",
    "wof:placetype":"venue"
},
  "geometry": {"coordinates":[-73.948414,40.639987],"type":"Point"}
}