{
  "type": "Feature",
  "properties": {
    "addr:full":"321 Riverside Dr Binghamton NY 13905",
    "addr:housenumber":"321",
    "addr:postcode":"13905",
    "addr:street":"Riverside Dr",
    "iso:country":"US",
    "sg:address":"321 Riverside Dr",
    "sg:city":"Binghamton",
    "sg:classifiers":[
        {
            "category":"Real Estate",
            "subcategory":"Developer",
            "type":"Services"
        }
    ],
    "sg:phone":"+1 607 798 8883",
    "sg:postcode":"13905",
    "sg:province":"NY",
    "sg:tags":[
        "cemetery",
        "association"
    ],
    "wof:name":"Slovak Catholic Cemeteries",
    "wof:placetype":"venue"
},
  "geometry": {"coordinates":[-75.94748199999999,42.097128],"type":"Point"}
}