{
  "type": "Feature",
  "properties": {
    "iso:country":"US",
    "sg:address":"379 Division St",
    "sg:city":"Amsterdam",
    "sg:classifiers":[
        {
            "category":"Organizations",
            "subcategory":"Religious Organization",
            "type":"Services"
        }
    ],
    "sg:phone":"+1 518 843 2577",
    "sg:postcode":"12010",
    "sg:province":"NY",
    "sg:tags":[
        "church"
    ],
    "wof:name":"Seventh Day Adventist Church",
    "wof:placetype":"venue"
},
  "geometry": {"coordinates":[-74.21367600000001,42.951725],"type":"Point"}
}