{
  "type": "Feature",
  "properties": {
    "addr:full":"8304 13th Ave Brooklyn NY 11228",
    "addr:housenumber":"8304",
    "addr:postcode":"11228",
    "addr:street":"13Th Ave",
    "iso:country":"US",
    "sg:address":"8304 13th Ave",
    "sg:city":"Brooklyn",
    "sg:classifiers":[
        {
            "category":"Banks & Credit Unions",
            "subcategory":"Bank",
            "type":"Services"
        }
    ],
    "sg:phone":"+1 718 491 5540",
    "sg:postcode":"11228",
    "sg:province":"NY",
    "sg:tags":[
        "broker",
        "mortgage"
    ],
    "wof:name":"Select Quote Mortgage",
    "wof:placetype":"venue"
},
  "geometry": {"coordinates":[-74.01275,40.615296],"type":"Point"}
}