{
  "type": "Feature",
  "properties": {
    "addr:full":"47 Baker St Saranac Lake NY 12983",
    "addr:housenumber":"47",
    "addr:postcode":"12983",
    "addr:street":"Baker St",
    "iso:country":"US",
    "sg:address":"47 Baker St",
    "sg:city":"Saranac Lake",
    "sg:classifiers":[
        {
            "category":"Retail",
            "subcategory":"Veterinary Services",
            "type":"Services"
        }
    ],
    "sg:phone":"+1 518 891 3421",
    "sg:postcode":"12983",
    "sg:province":"NY",
    "sg:tags":[
        "veterinarian"
    ],
    "wof:name":"Karl Zaunbrecher DVM",
    "wof:placetype":"venue"
},
  "geometry": {"coordinates":[-74.130613,44.333169],"type":"Point"}
}