{
  "type": "Feature",
  "properties": {
    "addr:full":"3100 47th Avenue Long Island City NY 11101",
    "addr:housenumber":"3100",
    "addr:postcode":"11101",
    "addr:street":"47Th Avenue",
    "iso:country":"US",
    "sg:address":"3100 47th Avenue",
    "sg:city":"Long Island City",
    "sg:classifiers":[
        {
            "category":"Shopping",
            "subcategory":"Jewelry",
            "type":"Retail Goods"
        }
    ],
    "sg:phone":"+1 718 316 9100",
    "sg:postcode":"11101",
    "sg:province":"NY",
    "wof:name":"Silverado Jewelry",
    "wof:placetype":"venue"
},
  "geometry": {"coordinates":[-73.93578599999999,40.743054],"type":"Point"}
}