{
  "type": "Feature",
  "properties": {
    "iso:country":"US",
    "sg:address":"253 Hempstead Tpke",
    "sg:city":"Elmont",
    "sg:classifiers":[
        {
            "category":"Shopping",
            "subcategory":"Bicycles & Sporting Goods",
            "type":"Retail Goods"
        }
    ],
    "sg:phone":"+1 516 775 3716",
    "sg:postcode":"11003",
    "sg:province":"NY",
    "sg:tags":[
        "horse",
        "furnishing"
    ],
    "sg:website":"www.tackroomproducts.com",
    "wof:name":"Tack Room Products",
    "wof:placetype":"venue"
},
  "geometry": {"coordinates":[-73.716679,40.707982],"type":"Point"}
}