{
  "type": "Feature",
  "properties": {
    "addr:full":"34 Park Pl Queensbury NY 12804",
    "addr:housenumber":"34",
    "addr:postcode":"12804",
    "addr:street":"Park Pl",
    "iso:country":"US",
    "sg:address":"34 Park Pl",
    "sg:city":"Queensbury",
    "sg:classifiers":[
        {
            "category":"Freight",
            "type":"Transportation"
        }
    ],
    "sg:phone":"+1   ",
    "sg:postcode":"12804",
    "sg:province":"NY",
    "sg:tags":[
        "storage",
        "individual",
        "rental"
    ],
    "wof:name":"Key Lock Mini Storage",
    "wof:placetype":"venue"
},
  "geometry": {"coordinates":[-73.66755999999999,43.319444],"type":"Point"}
}