{
  "type": "Feature",
  "properties": {
    "addr:full":"574 Montauk Hwy Ste 2 Shirley NY 11967",
    "addr:housenumber":"574",
    "addr:postcode":"11967",
    "addr:street":"Montauk Hwy Ste 2",
    "iso:country":"US",
    "sg:address":"574 Montauk Hwy Ste 2",
    "sg:city":"Shirley",
    "sg:classifiers":[
        {
            "category":"Shopping",
            "subcategory":"Department Store",
            "type":"Retail Goods"
        },
        {
            "category":"Home & Garden",
            "subcategory":"Hardware",
            "type":"Retail Goods"
        }
    ],
    "sg:phone":"+1 631 281 5308",
    "sg:postcode":"11967",
    "sg:province":"NY",
    "sg:tags":[
        "equipment",
        "cleaner",
        "janitor",
        "supply"
    ],
    "wof:name":"Alliance Maintenance & Management",
    "wof:placetype":"venue"
},
  "geometry": {"coordinates":[-72.87824000000001,40.800555],"type":"Point"}
}