{
  "type": "Feature",
  "properties": {
    "addr:full":"375 Lexington Ave New York NY 10017",
    "addr:housenumber":"375",
    "addr:postcode":"10017",
    "addr:street":"Lexington Ave",
    "iso:country":"US",
    "sg:address":"375 Lexington Ave",
    "sg:city":"New York",
    "sg:classifiers":[
        {
            "category":"Communications",
            "subcategory":"Newspaper",
            "type":"Services"
        }
    ],
    "sg:phone":"+1 212 499 2000",
    "sg:postcode":"10017",
    "sg:province":"NY",
    "sg:tags":[
        "print",
        "medium"
    ],
    "wof:name":"McCall's Magazine",
    "wof:placetype":"venue"
},
  "geometry": {"coordinates":[-73.97640199999999,40.7509],"type":"Point"}
}