{
  "type": "Feature",
  "properties": {
    "iso:country":"US",
    "sg:address":"19 E 73rd St Ofc",
    "sg:city":"New York",
    "sg:classifiers":[
        {
            "category":"Health Services",
            "subcategory":"Clinic",
            "type":"Services"
        }
    ],
    "sg:phone":"+1 212 744 4500",
    "sg:postcode":"10021",
    "sg:province":"NY",
    "sg:tags":[
        "counseling",
        "mental"
    ],
    "wof:name":"Waters Virginia Psychotherapist",
    "wof:placetype":"venue"
},
  "geometry": {"coordinates":[-73.96579699999999,40.7729],"type":"Point"}
}