{
  "type": "Feature",
  "properties": {
    "addr:full":"14912 41st Ave Apt 1 Flushing NY 11355",
    "addr:housenumber":"14912;1",
    "addr:postcode":"11355",
    "addr:street":"41St Ave Apt",
    "iso:country":"US",
    "sg:address":"14912 41st Ave Apt 1",
    "sg:city":"Flushing",
    "sg:classifiers":[
        {
            "category":"Utilities",
            "subcategory":"Mobile Phone",
            "type":"Services"
        },
        {
            "category":"Utilities",
            "subcategory":"Telephone",
            "type":"Services"
        },
        {
            "category":"Communications",
            "type":"Services"
        },
        {
            "category":"Manufacturing",
            "subcategory":"Electronics",
            "type":"Manufacturing & Wholesale Goods"
        }
    ],
    "sg:phone":"+1 718 353 2255",
    "sg:postcode":"11355",
    "sg:province":"NY",
    "sg:tags":[
        "telecommunications-equipment",
        "cellular",
        "systems-repair",
        "supply",
        "system",
        "equipment",
        "carrier",
        "radiotelephone",
        "communications-common"
    ],
    "wof:name":"Kyorae Telecom, Inc.",
    "wof:placetype":"venue"
},
  "geometry": {"coordinates":[-73.81544,40.76218],"type":"Point"}
}