{
  "type": "Feature",
  "properties": {
    "addr:full":"29 E 22nd Street New York NY 10010",
    "addr:housenumber":"29",
    "addr:postcode":"10010",
    "addr:street":"E 22Nd Street",
    "iso:country":"US",
    "sg:address":"29 E 22nd Street",
    "sg:city":"New York",
    "sg:classifiers":[
        {
            "category":"Home & Garden",
            "subcategory":"Home Furnishings",
            "type":"Retail Goods"
        },
        {
            "category":"Shopping",
            "subcategory":"Antiques",
            "type":"Retail Goods"
        }
    ],
    "sg:phone":"+1 212 260 3100",
    "sg:postcode":"10010",
    "sg:province":"NY",
    "sg:tags":[
        "decor"
    ],
    "sg:website":"www.carolestupell.com",
    "wof:name":"Carole Stupell Ltd",
    "wof:placetype":"venue"
},
  "geometry": {"coordinates":[-73.982913,40.737853],"type":"Point"}
}