{
  "type": "Feature",
  "properties": {
    "iso:country":"US",
    "sg:address":"75 Crosby St",
    "sg:city":"New York",
    "sg:classifiers":[
        {
            "category":"Manufacturing",
            "subcategory":"Apparel",
            "type":"Manufacturing & Wholesale Goods"
        }
    ],
    "sg:phone":"+1 212 226 1433",
    "sg:postcode":"10012",
    "sg:province":"NY",
    "sg:tags":[
        "clothing"
    ],
    "wof:name":"Nick Angelilli",
    "wof:placetype":"venue"
},
  "geometry": {"coordinates":[-73.99695199999999,40.72388],"type":"Point"}
}