{
  "type": "Feature",
  "properties": {
    "iso:country":"US",
    "sg:address":"899 E 169th St",
    "sg:city":"Bronx",
    "sg:classifiers":[
        {
            "category":"Shopping",
            "subcategory":"Department Store",
            "type":"Retail Goods"
        }
    ],
    "sg:phone":"+1 718 842 2666",
    "sg:postcode":"10459",
    "sg:province":"NY",
    "sg:tags":[
        "shop"
    ],
    "wof:name":"A & J Discount",
    "wof:placetype":"venue"
},
  "geometry": {"coordinates":[-73.896395,40.828762],"type":"Point"}
}