{
  "type": "Feature",
  "properties": {
    "addr:full":"19 E Gate Copiague NY 11726",
    "addr:housenumber":"19",
    "addr:postcode":"11726",
    "addr:street":"E Gate",
    "iso:country":"US",
    "sg:address":"19 E Gate",
    "sg:city":"Copiague",
    "sg:classifiers":[
        {
            "category":"Professional",
            "subcategory":"Computer Services",
            "type":"Services"
        }
    ],
    "sg:phone":"+1 631 841 2326",
    "sg:postcode":"11726",
    "sg:province":"NY",
    "sg:tags":[
        "related"
    ],
    "wof:name":"Louis Csak",
    "wof:placetype":"venue"
},
  "geometry": {"coordinates":[-73.395526,40.679635],"type":"Point"}
}