{
  "type": "Feature",
  "properties": {
    "addr:full":"34141 Hell St Cape Vincent NY 13618",
    "addr:housenumber":"34141",
    "addr:postcode":"13618",
    "addr:street":"Hell St",
    "iso:country":"US",
    "sg:address":"34141 Hell St",
    "sg:city":"Cape Vincent",
    "sg:classifiers":[
        {
            "category":"Professional",
            "subcategory":"Business Services",
            "type":"Services"
        }
    ],
    "sg:phone":"+1 315 654 4745",
    "sg:postcode":"13618",
    "sg:province":"NY",
    "sg:tags":[
        "painter",
        "sign"
    ],
    "wof:name":"Stewart Signs & Graphics",
    "wof:placetype":"venue"
},
  "geometry": {"coordinates":[-76.25773100000001,44.145903],"type":"Point"}
}