{
  "type": "Feature",
  "properties": {
    "iso:country":"US",
    "sg:address":"482 Elmwood Ave",
    "sg:city":"Buffalo",
    "sg:classifiers":[
        {
            "category":"Professional",
            "subcategory":"Secretarial Services",
            "type":"Services"
        }
    ],
    "sg:phone":"+1 716 881 2045",
    "sg:postcode":"14222",
    "sg:province":"NY",
    "sg:tags":[
        "reporting",
        "court"
    ],
    "wof:name":"Putnam's Connections",
    "wof:placetype":"venue"
},
  "geometry": {"coordinates":[-78.877162,42.910975],"type":"Point"}
}