{
  "type": "Feature",
  "properties": {
    "iso:country":"US",
    "sg:address":"80 Shore Rd",
    "sg:city":"Port Washington",
    "sg:classifiers":[
        {
            "category":"Autos & Motor Vehicles",
            "subcategory":"Fuel & Gas Station",
            "type":"Retail Goods"
        }
    ],
    "sg:phone":"+1   ",
    "sg:postcode":"11050",
    "sg:province":"NY",
    "sg:tags":[
        "station",
        "gasoline"
    ],
    "wof:name":"Botts Amoco Svce Cntr",
    "wof:placetype":"venue"
},
  "geometry": {"coordinates":[-73.705045,40.840379],"type":"Point"}
}