{
  "type": "Feature",
  "properties": {
    "iso:country":"US",
    "sg:address":"84 Newtown Plz",
    "sg:city":"Plainview",
    "sg:classifiers":[
        {
            "category":"Home & Garden",
            "subcategory":"Household Appliances",
            "type":"Retail Goods"
        }
    ],
    "sg:phone":"+1 516 845 4097",
    "sg:postcode":"11803",
    "sg:province":"NY",
    "wof:name":"Tri State Appliance Sales Inc",
    "wof:placetype":"venue"
},
  "geometry": {"coordinates":[-73.451284,40.781942],"type":"Point"}
}