{
  "type": "Feature",
  "properties": {
    "addr:full":"1159 Town Line Rd Alden NY 14004",
    "addr:housenumber":"1159",
    "addr:postcode":"14004",
    "addr:street":"Town Line Rd",
    "iso:country":"US",
    "sg:address":"1159 Town Line Rd",
    "sg:city":"Alden",
    "sg:classifiers":[
        {
            "category":"Place Of Worship",
            "subcategory":"Church",
            "type":"Public Place"
        },
        {
            "category":"Place Of Worship",
            "type":"Public Place"
        },
        {
            "category":"Education",
            "subcategory":"Preschool",
            "type":"Public Place"
        }
    ],
    "sg:phone":"+1 716 684 1467",
    "sg:postcode":"14004",
    "sg:province":"NY",
    "sg:tags":[
        "lutheran",
        "school",
        "nursery",
        "churches-lutheran-evangelical",
        "america",
        "churches-lutheran"
    ],
    "wof:name":"Town Line Nursery School",
    "wof:placetype":"venue"
},
  "geometry": {"coordinates":[-78.57800899999999,42.891207],"type":"Point"}
}