{
  "type": "Feature",
  "properties": {
    "addr:full":"4594 Abbott Rd Orchard Park NY 14127",
    "addr:housenumber":"4594",
    "addr:postcode":"14127",
    "addr:street":"Abbott Rd",
    "iso:country":"US",
    "sg:address":"4594 Abbott Rd",
    "sg:city":"Orchard Park",
    "sg:classifiers":[
        {
            "category":"Building & Trades",
            "subcategory":"Construction",
            "type":"Services"
        }
    ],
    "sg:phone":"+1 716 646 1417",
    "sg:postcode":"14127",
    "sg:province":"NY",
    "sg:tags":[
        "painter"
    ],
    "wof:name":"RNM Painting",
    "wof:placetype":"venue"
},
  "geometry": {"coordinates":[-78.79492399999999,42.755536],"type":"Point"}
}