{
  "type": "Feature",
  "properties": {
    "iso:country":"US",
    "sg:address":"492 Merrick Rd",
    "sg:city":"Rockville Centre",
    "sg:classifiers":[
        {
            "category":"Wholesale",
            "subcategory":"Plants",
            "type":"Manufacturing & Wholesale Goods"
        }
    ],
    "sg:phone":"+1 516 731 0867",
    "sg:postcode":"11570",
    "sg:province":"NY",
    "sg:tags":[
        "florist"
    ],
    "wof:name":"Playtime Baby Novelties",
    "wof:placetype":"venue"
},
  "geometry": {"coordinates":[-73.63582100000001,40.654814],"type":"Point"}
}