{
  "type": "Feature",
  "properties": {
    "addr:full":"168 Duane St New York NY 10013",
    "addr:housenumber":"168",
    "addr:postcode":"10013",
    "addr:street":"Duane St",
    "iso:country":"US",
    "sg:address":"168 Duane St",
    "sg:city":"New York",
    "sg:classifiers":[
        {
            "category":"Professional",
            "subcategory":"Lawyer & Legal Services",
            "type":"Services"
        }
    ],
    "sg:phone":"+1   ",
    "sg:postcode":"10013",
    "sg:province":"NY",
    "wof:name":"Richard Yellen",
    "wof:placetype":"venue"
},
  "geometry": {"coordinates":[-74.009591,40.71701],"type":"Point"}
}