{
  "type": "Feature",
  "properties": {
    "iso:country":"US",
    "sg:address":"270 N Michigan Ave",
    "sg:city":"Massapequa",
    "sg:classifiers":[
        {
            "category":"Professional",
            "subcategory":"Computer Services",
            "type":"Services"
        }
    ],
    "sg:phone":"+1 516 249 5432",
    "sg:postcode":"11758",
    "sg:province":"NY",
    "sg:tags":[
        "design",
        "system",
        "programing",
        "custom"
    ],
    "wof:name":"Cryptic Storage Inc",
    "wof:placetype":"venue"
},
  "geometry": {"coordinates":[-73.467839,40.711805],"type":"Point"}
}