{
  "type": "Feature",
  "properties": {
    "addr:full":"99 Main St Tappan NY 10983",
    "addr:housenumber":"99",
    "addr:postcode":"10983",
    "addr:street":"Main St",
    "iso:country":"US",
    "sg:address":"99 Main St",
    "sg:city":"Tappan",
    "sg:classifiers":[
        {
            "category":"Food & Beverages",
            "subcategory":"Liquor & Beverages",
            "type":"Retail Goods"
        },
        {
            "category":"Wholesale",
            "subcategory":"Wine & Distilled Alcoholic Beverages",
            "type":"Manufacturing & Wholesale Goods"
        }
    ],
    "sg:phone":"+1 845 359 2141",
    "sg:postcode":"10983",
    "sg:province":"NY",
    "sg:tags":[
        "broker",
        "store"
    ],
    "wof:name":"Grape D'vine",
    "wof:placetype":"venue"
},
  "geometry": {"coordinates":[-73.947839,41.021049],"type":"Point"}
}