{
  "type": "Feature",
  "properties": {
    "addr:full":"100 W 42nd St New York NY 10036",
    "addr:housenumber":"100",
    "addr:postcode":"10036",
    "addr:street":"W 42Nd St",
    "iso:country":"US",
    "sg:address":"100 W 42nd St",
    "sg:city":"New York",
    "sg:classifiers":[
        {
            "category":"Communications",
            "subcategory":"Newspaper",
            "type":"Services"
        }
    ],
    "sg:phone":"+1 212 764 0164",
    "sg:postcode":"10036",
    "sg:province":"NY",
    "sg:tags":[
        "magazine"
    ],
    "wof:name":"Mehatn Newstand",
    "wof:placetype":"venue"
},
  "geometry": {"coordinates":[-73.984168,40.754851],"type":"Point"}
}