{
  "type": "Feature",
  "properties": {
    "iso:country":"US",
    "sg:address":"3564 California Rd",
    "sg:city":"Orchard Park",
    "sg:classifiers":[
        {
            "category":"Banks & Credit Unions",
            "subcategory":"Bank",
            "type":"Services"
        }
    ],
    "sg:phone":"+1 716 662 6133",
    "sg:postcode":"14127",
    "sg:province":"NY",
    "wof:name":"International Brotherhood Of",
    "wof:placetype":"venue"
},
  "geometry": {"coordinates":[-78.785268,42.785583],"type":"Point"}
}