{
  "type": "Feature",
  "properties": {
    "iso:country":"US",
    "sg:address":"62 E 88 St",
    "sg:city":"New York",
    "sg:classifiers":[
        {
            "category":"Health Services",
            "subcategory":"Doctor",
            "type":"Services"
        }
    ],
    "sg:phone":"+1 212 831 5919",
    "sg:postcode":"10128",
    "sg:province":"NY",
    "sg:tags":[
        "physician",
        "surgeon"
    ],
    "wof:name":"Stanley S Heller MD",
    "wof:placetype":"venue"
},
  "geometry": {"coordinates":[-73.956751,40.781674],"type":"Point"}
}