{
  "type": "Feature",
  "properties": {
    "iso:country":"US",
    "sg:address":"350 Grove St",
    "sg:city":"Brooklyn",
    "sg:classifiers":[
        {
            "category":"Professional",
            "subcategory":"Detective & Security Services",
            "type":"Services"
        }
    ],
    "sg:phone":"+1 718 907 0588",
    "sg:postcode":"11237",
    "sg:province":"NY",
    "sg:tags":[
        "investigator"
    ],
    "wof:name":"Active Investigators",
    "wof:placetype":"venue"
},
  "geometry": {"coordinates":[-73.913618,40.700263],"type":"Point"}
}