{
  "type": "Feature",
  "properties": {
    "iso:country":"US",
    "sg:address":"1778 County Highway 107",
    "sg:city":"Amsterdam",
    "sg:classifiers":[
        {
            "category":"Restaurant",
            "type":"Food & Drink"
        }
    ],
    "sg:phone":"+1 518 842 3467",
    "sg:postcode":"12010",
    "sg:province":"NY",
    "wof:name":"Jackie",
    "wof:placetype":"venue"
},
  "geometry": {"coordinates":[-74.201458,43.015063],"type":"Point"}
}