{
  "type": "Feature",
  "properties": {
    "addr:full":"695 W End Ave Carthage NY 13619",
    "addr:housenumber":"695",
    "addr:postcode":"13619",
    "addr:street":"W End Ave",
    "iso:country":"US",
    "sg:address":"695 W End Ave",
    "sg:city":"Carthage",
    "sg:classifiers":[
        {
            "category":"Utilities",
            "subcategory":"Electric",
            "type":"Services"
        }
    ],
    "sg:phone":"+1 315 493 3331",
    "sg:postcode":"13619",
    "sg:province":"NY",
    "sg:tags":[
        "company"
    ],
    "wof:name":"West End Dam Hydro Assoc",
    "wof:placetype":"venue"
},
  "geometry": {"coordinates":[-75.615577,43.982969],"type":"Point"}
}