{
  "type": "Feature",
  "properties": {
    "addr:full":"4222 S Taylor Rd Orchard Park NY 14127",
    "addr:housenumber":"4222",
    "addr:postcode":"14127",
    "addr:street":"S Taylor Rd",
    "iso:country":"US",
    "sg:address":"4222 S Taylor Rd",
    "sg:city":"Orchard Park",
    "sg:classifiers":[
        {
            "category":"Real Estate",
            "subcategory":"Real Estate Operator",
            "type":"Services"
        }
    ],
    "sg:phone":"+1 716 662 9720",
    "sg:postcode":"14127",
    "sg:province":"NY",
    "sg:tags":[
        "manager",
        "property",
        "commercial"
    ],
    "wof:name":"Bubar Partnership",
    "wof:placetype":"venue"
},
  "geometry": {"coordinates":[-78.761382,42.765787],"type":"Point"}
}