{
  "type": "Feature",
  "properties": {
    "iso:country":"US",
    "sg:address":"4929 30th Pl",
    "sg:city":"Long Island City",
    "sg:classifiers":[
        {
            "category":"Autos & Motor Vehicles",
            "subcategory":"Automobile Sales",
            "type":"Retail Goods"
        }
    ],
    "sg:phone":"+1 718 706 5500",
    "sg:postcode":"11101",
    "sg:province":"NY",
    "sg:tags":[
        "limo"
    ],
    "wof:name":"Commonwealth Limousine Worldwide",
    "wof:placetype":"venue"
},
  "geometry": {"coordinates":[-73.93710400000001,40.740317],"type":"Point"}
}