{
  "type": "Feature",
  "properties": {
    "addr:full":"6 Millbrook Rd New Paltz NY 12561",
    "addr:housenumber":"6",
    "addr:postcode":"12561",
    "addr:street":"Millbrook Rd",
    "iso:country":"US",
    "sg:address":"6 Millbrook Rd",
    "sg:city":"New Paltz",
    "sg:classifiers":[
        {
            "category":"Manufacturing",
            "subcategory":"Retail Goods",
            "type":"Manufacturing & Wholesale Goods"
        }
    ],
    "sg:phone":"+1   ",
    "sg:postcode":"12561",
    "sg:province":"NY",
    "sg:tags":[
        "product",
        "mfg"
    ],
    "wof:name":"Engineering Educational Eqp Co",
    "wof:placetype":"venue"
},
  "geometry": {"coordinates":[-74.07214999999999,41.749322],"type":"Point"}
}