{
  "type": "Feature",
  "properties": {
    "addr:full":"1071 Brighton Beach Ave Brooklyn NY 11235",
    "addr:housenumber":"1071",
    "addr:postcode":"11235",
    "addr:street":"Brighton Beach Ave",
    "iso:country":"US",
    "sg:address":"1071 Brighton Beach Ave",
    "sg:city":"Brooklyn",
    "sg:classifiers":[
        {
            "category":"Food & Beverages",
            "subcategory":"Groceries & Convenience Stores",
            "type":"Retail Goods"
        }
    ],
    "sg:phone":"+1 718 743 0178",
    "sg:postcode":"11235",
    "sg:province":"NY",
    "sg:tags":[
        "grocer"
    ],
    "wof:name":"Chang Young WHA Grocery",
    "wof:placetype":"venue"
},
  "geometry": {"coordinates":[-73.95703899999999,40.578151],"type":"Point"}
}