{
  "type": "Feature",
  "properties": {
    "iso:country":"US",
    "sg:address":"202 Franklin St",
    "sg:city":"Auburn",
    "sg:classifiers":[
        {
            "category":"Social Services",
            "subcategory":"Adult Care",
            "type":"Services"
        },
        {
            "category":"Social Services",
            "type":"Services"
        }
    ],
    "sg:phone":"+1 315 255 3321",
    "sg:postcode":"13021",
    "sg:province":"NY",
    "sg:tags":[
        "home",
        "individual",
        "group",
        "family"
    ],
    "wof:name":"Cayuga Home For Children Aobh",
    "wof:placetype":"venue"
},
  "geometry": {"coordinates":[-76.54460899999999,42.941436],"type":"Point"}
}