{
  "type": "Feature",
  "properties": {
    "iso:country":"US",
    "sg:address":"35 5th Avenue",
    "sg:city":"New York",
    "sg:classifiers":[
        {
            "category":"Banks & Credit Unions",
            "subcategory":"Financial Services",
            "type":"Services"
        }
    ],
    "sg:phone":"+1 212 601 2723",
    "sg:postcode":"10003",
    "sg:province":"NY",
    "sg:tags":[
        "broker",
        "mortgage"
    ],
    "wof:name":"Strategic Capital Group",
    "wof:placetype":"venue"
},
  "geometry": {"coordinates":[-73.995357,40.733575],"type":"Point"}
}