{
  "type": "Feature",
  "properties": {
    "iso:country":"US",
    "sg:address":"177 Ballston Ave",
    "sg:city":"Saratoga Springs",
    "sg:classifiers":[
        {
            "category":"Personal",
            "subcategory":"Tanning Parlor",
            "type":"Services"
        }
    ],
    "sg:phone":"+1 518 691 0092",
    "sg:postcode":"12866",
    "sg:province":"NY",
    "sg:tags":[
        "salon"
    ],
    "wof:name":"Total Tan",
    "wof:placetype":"venue"
},
  "geometry": {"coordinates":[-73.793837,43.069929],"type":"Point"}
}