{
  "type": "Feature",
  "properties": {
    "iso:country":"US",
    "sg:address":"929 Front St",
    "sg:city":"Uniondale",
    "sg:classifiers":[
        {
            "category":"Banks & Credit Unions",
            "subcategory":"Bank",
            "type":"Services"
        }
    ],
    "sg:phone":"+1 516 483 0300",
    "sg:postcode":"11553",
    "sg:province":"NY",
    "wof:name":"CapitalOne",
    "wof:placetype":"venue"
},
  "geometry": {"coordinates":[-73.596548,40.709497],"type":"Point"}
}