{
  "type": "Feature",
  "properties": {
    "iso:country":"US",
    "sg:address":"8 Old Knollwood Rd",
    "sg:city":"White Plains",
    "sg:classifiers":[
        {
            "category":"Professional",
            "subcategory":"Management & Consulting",
            "type":"Services"
        }
    ],
    "sg:phone":"+1 914 328 1858",
    "sg:postcode":"10607",
    "sg:province":"NY",
    "wof:name":"New York Best",
    "wof:placetype":"venue"
},
  "geometry": {"coordinates":[-73.807558,41.041671],"type":"Point"}
}