{
  "type": "Feature",
  "properties": {
    "iso:country":"US",
    "sg:address":"908 Park Ave",
    "sg:city":"Syracuse",
    "sg:classifiers":[
        {
            "category":"Travel",
            "subcategory":"Travel Agent",
            "type":"Entertainment"
        }
    ],
    "sg:phone":"+1   ",
    "sg:postcode":"13204",
    "sg:province":"NY",
    "sg:tags":[
        "agency"
    ],
    "wof:name":"A P R Travel",
    "wof:placetype":"venue"
},
  "geometry": {"coordinates":[-76.17787199999999,43.05234],"type":"Point"}
}