{
  "type": "Feature",
  "properties": {
    "addr:full":"422 Fulton St Brooklyn NY 11201",
    "addr:housenumber":"422",
    "addr:postcode":"11201",
    "addr:street":"Fulton St",
    "iso:country":"US",
    "sg:address":"422 Fulton St",
    "sg:city":"Brooklyn",
    "sg:classifiers":[
        {
            "category":"Building & Trades",
            "subcategory":"Locksmith",
            "type":"Services"
        }
    ],
    "sg:phone":"+1 718 285 3703",
    "sg:postcode":"11201",
    "sg:province":"NY",
    "sg:tags":[
        "key"
    ],
    "sg:website":"www.brooklyn-locksmith-ny.com/",
    "wof:name":"Brooklyn Locksmith",
    "wof:placetype":"venue"
},
  "geometry": {"coordinates":[-73.986234,40.690315],"type":"Point"}
}