{
  "type": "Feature",
  "properties": {
    "addr:full":"3331 Great Neck Rd Amityville NY 11701",
    "addr:housenumber":"3331",
    "addr:postcode":"11701",
    "addr:street":"Great Neck Rd",
    "iso:country":"US",
    "sg:address":"3331 Great Neck Rd",
    "sg:city":"Amityville",
    "sg:classifiers":[
        {
            "category":"Retail",
            "subcategory":"Auto Repair",
            "type":"Services"
        }
    ],
    "sg:phone":"+1 631 789 7819",
    "sg:postcode":"11701",
    "sg:province":"NY",
    "sg:tags":[
        "body"
    ],
    "wof:name":"Benloss Auto Body",
    "wof:placetype":"venue"
},
  "geometry": {"coordinates":[-73.40608400000001,40.69629],"type":"Point"}
}