{
  "type": "Feature",
  "properties": {
    "addr:full":"20 W 20th Street Suite 1104 New York NY 10011",
    "addr:housenumber":"20",
    "addr:postcode":"10011",
    "addr:street":"W 20Th Street Suite 1104",
    "iso:country":"US",
    "sg:address":"20 W 20th Street Suite 1104",
    "sg:city":"New York",
    "sg:classifiers":[
        {
            "category":"Professional",
            "subcategory":"Computer Services",
            "type":"Services"
        }
    ],
    "sg:phone":"+1 212 647 1022",
    "sg:postcode":"10011",
    "sg:province":"NY",
    "sg:tags":[
        "repair"
    ],
    "wof:name":"Ny Computer Servics",
    "wof:placetype":"venue"
},
  "geometry": {"coordinates":[-73.991546,40.739884],"type":"Point"}
}