{
  "type": "Feature",
  "properties": {
    "iso:country":"US",
    "sg:address":"26 Gruber Dr",
    "sg:city":"Glen Cove",
    "sg:classifiers":[
        {
            "category":"Manufacturing",
            "subcategory":"Printing",
            "type":"Manufacturing & Wholesale Goods"
        }
    ],
    "sg:phone":"+1 516 674 9438",
    "sg:postcode":"11542",
    "sg:province":"NY",
    "sg:tags":[
        "typesetting"
    ],
    "wof:name":"Typrints Co",
    "wof:placetype":"venue"
},
  "geometry": {"coordinates":[-73.605737,40.861512],"type":"Point"}
}