{
  "type": "Feature",
  "properties": {
    "iso:country":"US",
    "sg:address":"23 Timber Ln",
    "sg:city":"Glenmont",
    "sg:classifiers":[
        {
            "category":"Building & Trades",
            "subcategory":"Construction",
            "type":"Services"
        }
    ],
    "sg:phone":"+1 518 449 9852",
    "sg:postcode":"12077",
    "sg:province":"NY",
    "sg:tags":[
        "residential"
    ],
    "wof:name":"JM Wolf",
    "wof:placetype":"venue"
},
  "geometry": {"coordinates":[-73.793899,42.604706],"type":"Point"}
}