{
  "type": "Feature",
  "properties": {
    "iso:country":"US",
    "sg:address":"40 Brandywine St",
    "sg:city":"Binghamton",
    "sg:classifiers":[
        {
            "category":"Professional",
            "subcategory":"Business Services",
            "type":"Services"
        }
    ],
    "sg:phone":"+1 607 771 6303",
    "sg:postcode":"13901",
    "sg:province":"NY",
    "sg:tags":[
        "water",
        "treatment"
    ],
    "sg:website":"www.purewaterconsultants.com",
    "wof:name":"Rain Soft Pure Water Conslnts",
    "wof:placetype":"venue"
},
  "geometry": {"coordinates":[-75.89907100000001,42.11141],"type":"Point"}
}