{
  "type": "Feature",
  "properties": {
    "addr:full":"1 Raymond St Islip NY 11751",
    "addr:housenumber":"1",
    "addr:postcode":"11751",
    "addr:street":"Raymond St",
    "iso:country":"US",
    "sg:address":"1 Raymond St",
    "sg:city":"Islip",
    "sg:classifiers":[
        {
            "category":"Autos & Motor Vehicles",
            "subcategory":"Auto Supplies",
            "type":"Retail Goods"
        }
    ],
    "sg:phone":"+1 631 581 5440",
    "sg:postcode":"11751",
    "sg:province":"NY",
    "sg:tags":[
        "automobile",
        "part"
    ],
    "wof:name":"207 Freeman Ave Corp",
    "wof:placetype":"venue"
},
  "geometry": {"coordinates":[-73.221153,40.725422],"type":"Point"}
}