{
  "type": "Feature",
  "properties": {
    "addr:full":"311 Baxtertown Rd Fishkill NY 12524",
    "addr:housenumber":"311",
    "addr:postcode":"12524",
    "addr:street":"Baxtertown Rd",
    "iso:country":"US",
    "sg:address":"311 Baxtertown Rd",
    "sg:city":"Fishkill",
    "sg:classifiers":[
        {
            "category":"Professional",
            "subcategory":"Computer Services",
            "type":"Services"
        }
    ],
    "sg:phone":"+1   ",
    "sg:postcode":"12524",
    "sg:province":"NY",
    "sg:tags":[
        "programing",
        "custom"
    ],
    "wof:name":"Sls Custom Works Inc",
    "wof:placetype":"venue"
},
  "geometry": {"coordinates":[-73.92685299999999,41.5488],"type":"Point"}
}