{
  "type": "Feature",
  "properties": {
    "addr:full":"11 Public Sq Watertown NY 13601",
    "addr:housenumber":"11",
    "addr:postcode":"13601",
    "addr:street":"Public Sq",
    "iso:country":"US",
    "sg:address":"11 Public Sq",
    "sg:city":"Watertown",
    "sg:classifiers":[
        {
            "category":"Organizations",
            "subcategory":"Non-profit Organization",
            "type":"Services"
        }
    ],
    "sg:phone":"+1 315 642 3488",
    "sg:postcode":"13601",
    "sg:province":"NY",
    "sg:tags":[
        "info",
        "addiction",
        "abuse",
        "treatment",
        "drug"
    ],
    "wof:name":"Credo Foundation",
    "wof:placetype":"venue"
},
  "geometry": {"coordinates":[-75.910858,43.975054],"type":"Point"}
}