{
  "type": "Feature",
  "properties": {
    "addr:full":"969 2nd Avenue New York NY 10022",
    "addr:housenumber":"969",
    "addr:postcode":"10022",
    "addr:street":"2Nd Avenue",
    "iso:country":"US",
    "sg:address":"969 2nd Avenue",
    "sg:city":"New York",
    "sg:classifiers":[
        {
            "category":"Food & Beverages",
            "subcategory":"Groceries & Convenience Stores",
            "type":"Retail Goods"
        }
    ],
    "sg:phone":"+1 212 355 9613",
    "sg:postcode":"10022",
    "sg:province":"NY",
    "wof:name":"Food Emporium",
    "wof:placetype":"venue"
},
  "geometry": {"coordinates":[-73.968099,40.755677],"type":"Point"}
}