{
  "type": "Feature",
  "properties": {
    "addr:full":"23 Coventry Cir Mahopac NY 10541",
    "addr:housenumber":"23",
    "addr:postcode":"10541",
    "addr:street":"Coventry Cir",
    "iso:country":"US",
    "sg:address":"23 Coventry Cir",
    "sg:city":"Mahopac",
    "sg:classifiers":[
        {
            "category":"Banks & Credit Unions",
            "subcategory":"Investment Brokerage",
            "type":"Services"
        }
    ],
    "sg:phone":"+1 845 621 4412",
    "sg:postcode":"10541",
    "sg:province":"NY",
    "sg:tags":[
        "fund",
        "security",
        "mutual"
    ],
    "wof:name":"Mutual Aide",
    "wof:placetype":"venue"
},
  "geometry": {"coordinates":[-73.739659,41.361444],"type":"Point"}
}