{
  "type": "Feature",
  "properties": {
    "addr:full":"344 Newbridge Rd East Meadow NY 11554",
    "addr:housenumber":"344",
    "addr:postcode":"11554",
    "addr:street":"Newbridge Rd",
    "iso:country":"US",
    "sg:address":"344 Newbridge Rd",
    "sg:city":"East Meadow",
    "sg:classifiers":[
        {
            "category":"Restaurant",
            "type":"Food & Drink"
        }
    ],
    "sg:phone":"+1 516 826 8282",
    "sg:postcode":"11554",
    "sg:province":"NY",
    "sg:tags":[
        "pizza"
    ],
    "wof:name":"Steverino's Pizzeria",
    "wof:placetype":"venue"
},
  "geometry": {"coordinates":[-73.544979,40.714856],"type":"Point"}
}