{
  "type": "Feature",
  "properties": {
    "iso:country":"US",
    "sg:address":"223 Bedford Ave",
    "sg:city":"Brooklyn",
    "sg:classifiers":[
        {
            "category":"Shopping",
            "subcategory":"Used Merchandise",
            "type":"Retail Goods"
        }
    ],
    "sg:phone":"+1 718 963 4001",
    "sg:postcode":"11211",
    "sg:province":"NY",
    "sg:tags":[
        "vintage",
        "consignment"
    ],
    "sg:website":"amarcordvintagefashion.com/",
    "wof:name":"Amarcord Vintage Fashion",
    "wof:placetype":"venue"
},
  "geometry": {"coordinates":[-73.95590199999999,40.710098],"type":"Point"}
}