{
  "type": "Feature",
  "properties": {
    "iso:country":"US",
    "sg:address":"255 Manetto Hill Rd",
    "sg:city":"Plainview",
    "sg:classifiers":[
        {
            "category":"Organizations",
            "subcategory":"Religious Organization",
            "type":"Services"
        }
    ],
    "sg:phone":"+1 516 433 6590",
    "sg:postcode":"11803",
    "sg:province":"NY",
    "sg:tags":[
        "synagogue"
    ],
    "wof:name":"Plainview Synagogue",
    "wof:placetype":"venue"
},
  "geometry": {"coordinates":[-73.47544000000001,40.789714],"type":"Point"}
}