{
  "type": "Feature",
  "properties": {
    "iso:country":"US",
    "sg:address":"628 Fulton Ave",
    "sg:city":"Hempstead",
    "sg:classifiers":[
        {
            "category":"Bars & Pubs",
            "type":"Food & Drink"
        }
    ],
    "sg:phone":"+1   ",
    "sg:postcode":"11550",
    "sg:province":"NY",
    "sg:tags":[
        "tavern"
    ],
    "wof:name":"Avenue D",
    "wof:placetype":"venue"
},
  "geometry": {"coordinates":[-73.61094900000001,40.71131],"type":"Point"}
}