{
  "type": "Feature",
  "properties": {
    "iso:country":"US",
    "sg:address":"95 Kirkwood Ave",
    "sg:city":"Merrick",
    "sg:classifiers":[
        {
            "category":"Professional",
            "subcategory":"Printing & Photocopies",
            "type":"Services"
        }
    ],
    "sg:phone":"+1 516 546 4500",
    "sg:postcode":"11566",
    "sg:province":"NY",
    "sg:tags":[
        "photographers-commercial"
    ],
    "wof:name":"Vanblerck Photographers",
    "wof:placetype":"venue"
},
  "geometry": {"coordinates":[-73.553196,40.658171],"type":"Point"}
}