{
  "type": "Feature",
  "properties": {
    "iso:country":"US",
    "sg:address":"9 Center St",
    "sg:city":"Geneseo",
    "sg:classifiers":[
        {
            "category":"Professional",
            "subcategory":"Accounting & Tax Preparation",
            "type":"Services"
        }
    ],
    "sg:phone":"+1 585 243 3580",
    "sg:postcode":"14454",
    "sg:province":"NY",
    "sg:tags":[
        "accountant"
    ],
    "wof:name":"Gerald W Spezzano",
    "wof:placetype":"venue"
},
  "geometry": {"coordinates":[-77.816183,42.79622],"type":"Point"}
}