{
  "type": "Feature",
  "properties": {
    "addr:full":"16 E 52 St New York NY 10022",
    "addr:housenumber":"16;52",
    "addr:postcode":"10022",
    "addr:street":"E;St",
    "iso:country":"US",
    "sg:address":"16 E 52 St",
    "sg:city":"New York",
    "sg:classifiers":[
        {
            "category":"Professional",
            "subcategory":"Employment Agencies",
            "type":"Services"
        }
    ],
    "sg:phone":"+1 212 922 9544",
    "sg:postcode":"10022",
    "sg:province":"NY",
    "wof:name":"S G Partners Inc",
    "wof:placetype":"venue"
},
  "geometry": {"coordinates":[-73.975427,40.75944],"type":"Point"}
}