{
  "type": "Feature",
  "properties": {
    "iso:country":"US",
    "sg:address":"105 Lake Hill Rd",
    "sg:city":"Burnt Hills",
    "sg:classifiers":[
        {
            "category":"Professional",
            "subcategory":"Lawyer & Legal Services",
            "type":"Services"
        }
    ],
    "sg:phone":"+1 518 399 2588",
    "sg:postcode":"12027",
    "sg:province":"NY",
    "wof:name":"Atty Robert Vanvraken",
    "wof:placetype":"venue"
},
  "geometry": {"coordinates":[-73.89287899999999,42.909925],"type":"Point"}
}