{
  "type": "Feature",
  "properties": {
    "iso:country":"US",
    "sg:address":"1212 Cold Spring Rd",
    "sg:city":"Forestburgh",
    "sg:classifiers":[
        {
            "category":"Travel",
            "subcategory":"Campground",
            "type":"Entertainment"
        }
    ],
    "sg:phone":"+1 845 794 8899",
    "sg:postcode":"12777",
    "sg:province":"NY",
    "sg:tags":[
        "camp"
    ],
    "wof:name":"Crystal Run Village Inc",
    "wof:placetype":"venue"
},
  "geometry": {"coordinates":[-74.67194000000001,41.574209],"type":"Point"}
}