{
  "type": "Feature",
  "properties": {
    "iso:country":"US",
    "sg:address":"3925 W Henrietta Rd",
    "sg:city":"Rochester",
    "sg:classifiers":[
        {
            "category":"Autos & Motor Vehicles",
            "subcategory":"Automobile Sales",
            "type":"Retail Goods"
        }
    ],
    "sg:phone":"+1   ",
    "sg:postcode":"14623",
    "sg:province":"NY",
    "sg:tags":[
        "new",
        "used"
    ],
    "wof:name":"John H BMW",
    "wof:placetype":"venue"
},
  "geometry": {"coordinates":[-77.644391,43.07333],"type":"Point"}
}