{
  "type": "Feature",
  "properties": {
    "addr:full":"155 Pinelawn Rd Melville NY 11747",
    "addr:housenumber":"155",
    "addr:postcode":"11747",
    "addr:street":"Pinelawn Rd",
    "iso:country":"US",
    "sg:address":"155 Pinelawn Rd",
    "sg:city":"Melville",
    "sg:classifiers":[
        {
            "category":"Banks & Credit Unions",
            "subcategory":"Bank",
            "type":"Services"
        }
    ],
    "sg:phone":"+1 631 420 3837",
    "sg:postcode":"11747",
    "sg:province":"NY",
    "sg:tags":[
        "financing"
    ],
    "wof:name":"Beneficial Finance",
    "wof:placetype":"venue"
},
  "geometry": {"coordinates":[-73.41244,40.786216],"type":"Point"}
}