{
  "type": "Feature",
  "properties": {
    "addr:full":"158 Troy Rd Ithaca NY 14850",
    "addr:housenumber":"158",
    "addr:postcode":"14850",
    "addr:street":"Troy Rd",
    "iso:country":"US",
    "sg:address":"158 Troy Rd",
    "sg:city":"Ithaca",
    "sg:classifiers":[
        {
            "category":"Professional",
            "subcategory":"Detective & Security Services",
            "type":"Services"
        }
    ],
    "sg:phone":"+1 607 272 1122",
    "sg:postcode":"14850",
    "sg:province":"NY",
    "sg:tags":[
        "guard",
        "patrol"
    ],
    "wof:name":"International Security Prod",
    "wof:placetype":"venue"
},
  "geometry": {"coordinates":[-76.477903,42.406255],"type":"Point"}
}