{
  "type": "Feature",
  "properties": {
    "addr:full":"349 5th Avenue New York NY 10016",
    "addr:housenumber":"349",
    "addr:postcode":"10016",
    "addr:street":"5Th Avenue",
    "iso:country":"US",
    "sg:address":"349 5th Avenue",
    "sg:city":"New York",
    "sg:classifiers":[
        {
            "category":"Banks & Credit Unions",
            "subcategory":"Bank",
            "type":"Services"
        }
    ],
    "sg:phone":"+1 212 696 3131",
    "sg:postcode":"10016",
    "sg:province":"NY",
    "wof:name":"Banklink Incorp",
    "wof:placetype":"venue"
},
  "geometry": {"coordinates":[-73.98464,40.748297],"type":"Point"}
}