{
  "type": "Feature",
  "properties": {
    "addr:full":"47 W Huron St Buffalo NY 14202",
    "addr:housenumber":"47",
    "addr:postcode":"14202",
    "addr:street":"W Huron St",
    "iso:country":"US",
    "sg:address":"47 W Huron St",
    "sg:city":"Buffalo",
    "sg:classifiers":[
        {
            "category":"Organizations",
            "subcategory":"Religious Organization",
            "type":"Services"
        }
    ],
    "sg:phone":"+1 716 842 6141",
    "sg:postcode":"14202",
    "sg:province":"NY",
    "wof:name":"Scientology Church",
    "wof:placetype":"venue"
},
  "geometry": {"coordinates":[-78.87509900000001,42.889],"type":"Point"}
}