{
  "type": "Feature",
  "properties": {
    "addr:full":"471 E Main St Gouverneur NY 13642",
    "addr:housenumber":"471",
    "addr:postcode":"13642",
    "addr:street":"E Main St",
    "iso:country":"US",
    "sg:address":"471 E Main St",
    "sg:city":"Gouverneur",
    "sg:classifiers":[
        {
            "category":"Home & Garden",
            "subcategory":"Hardware",
            "type":"Retail Goods"
        }
    ],
    "sg:phone":"+1 315 287 0711",
    "sg:postcode":"13642",
    "sg:province":"NY",
    "wof:name":"Wise Buys Do It Best",
    "wof:placetype":"venue"
},
  "geometry": {"coordinates":[-75.451606,44.342693],"type":"Point"}
}