{
  "type": "Feature",
  "properties": {
    "addr:full":"113 Pittsford-Palmyra Rd Macedon NY 14502",
    "addr:housenumber":"113",
    "addr:postcode":"14502",
    "addr:street":"Pittsford-Palmyra Rd",
    "iso:country":"US",
    "sg:address":"113 Pittsford-Palmyra Rd",
    "sg:city":"Macedon",
    "sg:classifiers":[
        {
            "category":"Restaurant",
            "type":"Food & Drink"
        }
    ],
    "sg:phone":"+1   ",
    "sg:postcode":"14502",
    "sg:province":"NY",
    "sg:tags":[
        "tavern"
    ],
    "wof:name":"Flahertys",
    "wof:placetype":"venue"
},
  "geometry": {"coordinates":[-77.37022,43.064391],"type":"Point"}
}