{
  "type": "Feature",
  "properties": {
    "iso:country":"US",
    "sg:address":"39 W Booker Ave",
    "sg:city":"Wyandanch",
    "sg:classifiers":[
        {
            "category":"Social Services",
            "subcategory":"Child Care",
            "type":"Services"
        }
    ],
    "sg:phone":"+1 631 643 2937",
    "sg:postcode":"11798",
    "sg:province":"NY",
    "sg:tags":[
        "center",
        "day"
    ],
    "wof:name":"Phillips Day Care Center",
    "wof:placetype":"venue"
},
  "geometry": {"coordinates":[-73.371201,40.73906],"type":"Point"}
}