{
  "type": "Feature",
  "properties": {
    "iso:country":"US",
    "sg:address":"202 E 29th St",
    "sg:city":"New York",
    "sg:classifiers":[
        {
            "category":"Home & Garden",
            "subcategory":"Hardware",
            "type":"Retail Goods"
        }
    ],
    "sg:phone":"+1   ",
    "sg:postcode":"10016",
    "sg:province":"NY",
    "sg:tags":[
        "appliance"
    ],
    "wof:name":"Homefronthardwarecom",
    "wof:placetype":"venue"
},
  "geometry": {"coordinates":[-73.978239,40.741597],"type":"Point"}
}