{
  "type": "Feature",
  "properties": {
    "iso:country":"US",
    "sg:address":"4801 8th Ave",
    "sg:city":"Brooklyn",
    "sg:classifiers":[
        {
            "category":"Restaurant",
            "type":"Food & Drink"
        }
    ],
    "sg:phone":"+1 718 437 3542",
    "sg:postcode":"11220",
    "sg:province":"NY",
    "sg:tags":[
        "dim",
        "sum"
    ],
    "wof:name":"Kai Feng Fu",
    "wof:placetype":"venue"
},
  "geometry": {"coordinates":[-74.00255799999999,40.642231],"type":"Point"}
}