{
  "type": "Feature",
  "properties": {
    "iso:country":"US",
    "sg:address":"324 E 74 St",
    "sg:city":"New York",
    "sg:classifiers":[
        {
            "category":"Professional",
            "subcategory":"Business Services",
            "type":"Services"
        }
    ],
    "sg:phone":"+1 212 772 3504",
    "sg:postcode":"10021",
    "sg:province":"NY",
    "sg:tags":[
        "wholesale",
        "design",
        "accessory"
    ],
    "wof:name":"Audrey Weaver Designs",
    "wof:placetype":"venue"
},
  "geometry": {"coordinates":[-73.955512,40.769299],"type":"Point"}
}