{
  "type": "Feature",
  "properties": {
    "addr:full":"102 Madison Ave New York NY 10016",
    "addr:housenumber":"102",
    "addr:postcode":"10016",
    "addr:street":"Madison Ave",
    "iso:country":"US",
    "sg:address":"102 Madison Ave",
    "sg:city":"New York",
    "sg:classifiers":[
        {
            "category":"Building & Trades",
            "subcategory":"Construction",
            "type":"Services"
        }
    ],
    "sg:phone":"+1 212 252 8900",
    "sg:postcode":"10016",
    "sg:province":"NY",
    "sg:tags":[
        "residential",
        "contractor",
        "commercial",
        "general"
    ],
    "sg:website":"www.gallin.com",
    "wof:name":"John Gallin & Son Inc",
    "wof:placetype":"venue"
},
  "geometry": {"coordinates":[-73.98493499999999,40.745143],"type":"Point"}
}