{
  "type": "Feature",
  "properties": {
    "iso:country":"US",
    "sg:address":"877 25th St",
    "sg:city":"Watervliet",
    "sg:classifiers":[
        {
            "category":"Professional",
            "subcategory":"Testing Lab",
            "type":"Services"
        }
    ],
    "sg:phone":"+1 518 276 8716",
    "sg:postcode":"12189",
    "sg:province":"NY",
    "sg:tags":[
        "laboratory"
    ],
    "wof:name":"Lighting Research Lab",
    "wof:placetype":"venue"
},
  "geometry": {"coordinates":[-73.708491,42.736053],"type":"Point"}
}