{
  "type": "Feature",
  "properties": {
    "iso:country":"US",
    "sg:address":"102 Islip Blvd",
    "sg:city":"Islip Terrace",
    "sg:classifiers":[
        {
            "category":"Insurance",
            "subcategory":"Insurance Agent",
            "type":"Services"
        }
    ],
    "sg:phone":"+1 631 581 4600",
    "sg:postcode":"11752",
    "sg:province":"NY",
    "sg:tags":[
        "agency"
    ],
    "wof:name":"State Farm Insurance",
    "wof:placetype":"venue"
},
  "geometry": {"coordinates":[-73.19711100000001,40.74369],"type":"Point"}
}