{
  "type": "Feature",
  "properties": {
    "iso:country":"US",
    "sg:address":"245 Moses Ln",
    "sg:city":"Southampton",
    "sg:classifiers":[
        {
            "category":"Building & Trades",
            "subcategory":"Landscaping Services",
            "type":"Services"
        }
    ],
    "sg:phone":"+1 631 283 5099",
    "sg:postcode":"11968",
    "sg:province":"NY",
    "sg:tags":[
        "designer",
        "landscape"
    ],
    "wof:name":"A & E Estates",
    "wof:placetype":"venue"
},
  "geometry": {"coordinates":[-72.409452,40.890933],"type":"Point"}
}