{
  "type": "Feature",
  "properties": {
    "addr:full":"240 Madison Ave New York NY 10016",
    "addr:housenumber":"240",
    "addr:postcode":"10016",
    "addr:street":"Madison Ave",
    "iso:country":"US",
    "sg:address":"240 Madison Ave",
    "sg:city":"New York",
    "sg:classifiers":[
        {
            "category":"Health Services",
            "subcategory":"Doctor",
            "type":"Services"
        }
    ],
    "sg:phone":"+1 212 490 3930",
    "sg:postcode":"10016",
    "sg:province":"NY",
    "wof:name":"Ko William MD",
    "wof:placetype":"venue"
},
  "geometry": {"coordinates":[-73.981478,40.750073],"type":"Point"}
}