{
  "type": "Feature",
  "properties": {
    "addr:full":"8424 3rd Ave Brooklyn NY 11209",
    "addr:housenumber":"8424",
    "addr:postcode":"11209",
    "addr:street":"3Rd Ave",
    "iso:country":"US",
    "sg:address":"8424 3rd Ave",
    "sg:city":"Brooklyn",
    "sg:classifiers":[
        {
            "category":"Restaurant",
            "type":"Food & Drink"
        }
    ],
    "sg:phone":"+1 718 238 0079",
    "sg:postcode":"11209",
    "sg:province":"NY",
    "sg:tags":[
        "style",
        "seafood",
        "family",
        "italian"
    ],
    "wof:name":"Areo Ristorante",
    "wof:placetype":"venue"
},
  "geometry": {"coordinates":[-74.03050399999999,40.624838],"type":"Point"}
}