{
  "type": "Feature",
  "properties": {
    "iso:country":"US",
    "sg:address":"3443 Lawson Rd",
    "sg:city":"Jamestown",
    "sg:classifiers":[
        {
            "category":"Organizations",
            "subcategory":"Membership Organization",
            "type":"Services"
        }
    ],
    "sg:phone":"+1 716 483 3670",
    "sg:postcode":"14701",
    "sg:province":"NY",
    "sg:tags":[
        "historical"
    ],
    "wof:name":"Busti Historical Society",
    "wof:placetype":"venue"
},
  "geometry": {"coordinates":[-79.281873,42.03156],"type":"Point"}
}