{
  "type": "Feature",
  "properties": {
    "addr:full":"1729 Rt 23 B Catskill NY 12414",
    "addr:housenumber":"1729",
    "addr:postcode":"12414",
    "addr:street":"Rt 23 B",
    "iso:country":"US",
    "sg:address":"1729 Rt 23 B",
    "sg:city":"Catskill",
    "sg:classifiers":[
        {
            "category":"Building & Trades",
            "subcategory":"Cleaning & Sanitation",
            "type":"Services"
        },
        {
            "category":"Building & Trades",
            "subcategory":"Construction",
            "type":"Services"
        }
    ],
    "sg:phone":"+1 518 965 0720",
    "sg:postcode":"12414",
    "sg:province":"NY",
    "sg:tags":[
        "window",
        "washing",
        "painter"
    ],
    "sg:website":"www.kelloggspainting.com",
    "wof:name":"Kellogg's Painting Company",
    "wof:placetype":"venue"
},
  "geometry": {"coordinates":[-73.868787,42.216991],"type":"Point"}
}