{
  "type": "Feature",
  "properties": {
    "iso:country":"US",
    "sg:address":"33 E 3rd St",
    "sg:city":"Mount Vernon",
    "sg:classifiers":[
        {
            "category":"Wholesale",
            "subcategory":"Hardware",
            "type":"Manufacturing & Wholesale Goods"
        },
        {
            "category":"Personal",
            "subcategory":"Beauty Salon",
            "type":"Services"
        }
    ],
    "sg:phone":"+1 914 668 6323",
    "sg:postcode":"10550",
    "sg:province":"NY",
    "wof:name":"Malado African Hair Braiding",
    "wof:placetype":"venue"
},
  "geometry": {"coordinates":[-73.833952,40.907148],"type":"Point"}
}