{
  "type": "Feature",
  "properties": {
    "iso:country":"US",
    "sg:address":"5504 Brush Hollow Rd",
    "sg:city":"Westbury",
    "sg:classifiers":[
        {
            "category":"Restaurant",
            "type":"Food & Drink"
        }
    ],
    "sg:phone":"+1 516 333 7595",
    "sg:postcode":"11590",
    "sg:province":"NY",
    "sg:website":"www.subway.com",
    "wof:name":"Subway & Carvel",
    "wof:placetype":"venue"
},
  "geometry": {"coordinates":[-73.561798,40.773499],"type":"Point"}
}