{
  "type": "Feature",
  "properties": {
    "iso:country":"US",
    "sg:address":"167 Wood Ln",
    "sg:city":"Newark",
    "sg:classifiers":[
        {
            "category":"Real Estate",
            "subcategory":"Architect",
            "type":"Services"
        }
    ],
    "sg:phone":"+1 315 331 8610",
    "sg:postcode":"14513",
    "sg:province":"NY",
    "wof:name":"John L Benzel",
    "wof:placetype":"venue"
},
  "geometry": {"coordinates":[-77.103736,43.035962],"type":"Point"}
}