{
  "type": "Feature",
  "properties": {
    "addr:full":"430 Delaware Ave Buffalo NY 14202",
    "addr:housenumber":"430",
    "addr:postcode":"14202",
    "addr:street":"Delaware Ave",
    "iso:country":"US",
    "sg:address":"430 Delaware Ave",
    "sg:city":"Buffalo",
    "sg:classifiers":[
        {
            "category":"Organizations",
            "subcategory":"Religious Organization",
            "type":"Services"
        }
    ],
    "sg:phone":"+1 716 883 0360",
    "sg:postcode":"14202",
    "sg:province":"NY",
    "wof:name":"Zionquest Christian Fellowship",
    "wof:placetype":"venue"
},
  "geometry": {"coordinates":[-78.87521599999999,42.896062],"type":"Point"}
}