{
  "type": "Feature",
  "properties": {
    "iso:country":"US",
    "sg:address":"300 S Central Ave",
    "sg:city":"Hartsdale",
    "sg:classifiers":[
        {
            "category":"Building & Trades",
            "subcategory":"Construction",
            "type":"Services"
        }
    ],
    "sg:phone":"+1 914 472 3467",
    "sg:postcode":"10530",
    "sg:province":"NY",
    "sg:tags":[
        "house"
    ],
    "wof:name":"Nick Remodeling",
    "wof:placetype":"venue"
},
  "geometry": {"coordinates":[-73.806726,41.01158],"type":"Point"}
}