{
  "type": "Feature",
  "properties": {
    "addr:full":"200 Giffords Church Rd Schenectady NY 12306",
    "addr:housenumber":"200",
    "addr:postcode":"12306",
    "addr:street":"Giffords Church Rd",
    "iso:country":"US",
    "sg:address":"200 Giffords Church Rd",
    "sg:city":"Schenectady",
    "sg:classifiers":[
        {
            "category":"Shopping",
            "subcategory":"Used Merchandise",
            "type":"Retail Goods"
        }
    ],
    "sg:phone":"+1   ",
    "sg:postcode":"12306",
    "sg:province":"NY",
    "wof:name":"Allen Gusse",
    "wof:placetype":"venue"
},
  "geometry": {"coordinates":[-73.98775500000001,42.763619],"type":"Point"}
}