{
  "type": "Feature",
  "properties": {
    "addr:full":"1450 Western Ave Albany NY 12203",
    "addr:housenumber":"1450",
    "addr:postcode":"12203",
    "addr:street":"Western Ave",
    "iso:country":"US",
    "sg:address":"1450 Western Ave",
    "sg:city":"Albany",
    "sg:classifiers":[
        {
            "category":"Banks & Credit Unions",
            "subcategory":"Bank",
            "type":"Services"
        }
    ],
    "sg:phone":"+1 518 447 4027",
    "sg:postcode":"12203",
    "sg:province":"NY",
    "sg:tags":[
        "state",
        "commercial"
    ],
    "wof:name":"Fleet",
    "wof:placetype":"venue"
},
  "geometry": {"coordinates":[-73.834052,42.679949],"type":"Point"}
}