{
  "type": "Feature",
  "properties": {
    "iso:country":"US",
    "sg:address":"643 E Monroe St",
    "sg:city":"Little Falls",
    "sg:classifiers":[
        {
            "category":"Taxi",
            "type":"Transportation"
        }
    ],
    "sg:phone":"+1 315 823 0700",
    "sg:postcode":"13365",
    "sg:province":"NY",
    "sg:tags":[
        "taxicab"
    ],
    "wof:name":"Little Falls Taxi & Limousine",
    "wof:placetype":"venue"
},
  "geometry": {"coordinates":[-74.85446899999999,43.047469],"type":"Point"}
}