{
  "type": "Feature",
  "properties": {
    "iso:country":"US",
    "sg:address":"4966 Blackman Rd",
    "sg:city":"Lockport",
    "sg:classifiers":[
        {
            "category":"Building & Trades",
            "subcategory":"Construction",
            "type":"Services"
        }
    ],
    "sg:phone":"+1 716 433 9649",
    "sg:postcode":"14094",
    "sg:province":"NY",
    "sg:tags":[
        "carpentry",
        "contractor"
    ],
    "wof:name":"Schwab Interior Carpentry",
    "wof:placetype":"venue"
},
  "geometry": {"coordinates":[-78.80069399999999,43.163678],"type":"Point"}
}