{
  "type": "Feature",
  "properties": {
    "addr:full":"138 Delaware St Walton NY 13856",
    "addr:housenumber":"138",
    "addr:postcode":"13856",
    "addr:street":"Delaware St",
    "iso:country":"US",
    "sg:address":"138 Delaware St",
    "sg:city":"Walton",
    "sg:classifiers":[
        {
            "category":"Insurance",
            "subcategory":"Insurance Agent",
            "type":"Services"
        }
    ],
    "sg:phone":"+1 607 865 4416",
    "sg:postcode":"13856",
    "sg:province":"NY",
    "wof:name":"Eggelton & Mc Nee Insurance",
    "wof:placetype":"venue"
},
  "geometry": {"coordinates":[-75.130422,42.168161],"type":"Point"}
}