{
  "type": "Feature",
  "properties": {
    "iso:country":"US",
    "sg:address":"200 S Caroline St",
    "sg:city":"Herkimer",
    "sg:classifiers":[
        {
            "category":"Manufacturing",
            "subcategory":"Food",
            "type":"Manufacturing & Wholesale Goods"
        }
    ],
    "sg:phone":"+1   ",
    "sg:postcode":"13350",
    "sg:province":"NY",
    "sg:tags":[
        "plant",
        "milk"
    ],
    "wof:name":"Tuscan/Lehigh Dairies Inc",
    "wof:placetype":"venue"
},
  "geometry": {"coordinates":[-74.99208299999999,43.021037],"type":"Point"}
}