{
  "type": "Feature",
  "properties": {
    "addr:full":"20 Front St Ballston Spa NY 12020",
    "addr:housenumber":"20",
    "addr:postcode":"12020",
    "addr:street":"Front St",
    "iso:country":"US",
    "sg:address":"20 Front St",
    "sg:city":"Ballston Spa",
    "sg:classifiers":[
        {
            "category":"Wholesale",
            "subcategory":"Non-durable Goods",
            "type":"Manufacturing & Wholesale Goods"
        }
    ],
    "sg:phone":"+1 518 885 0816",
    "sg:postcode":"12020",
    "sg:province":"NY",
    "sg:tags":[
        "religious"
    ],
    "wof:name":"New York Gnostic Institute",
    "wof:placetype":"venue"
},
  "geometry": {"coordinates":[-73.849639,43.002558],"type":"Point"}
}