{
  "type": "Feature",
  "properties": {
    "iso:country":"US",
    "sg:address":"3331 Co Rd 20",
    "sg:city":"Stanley",
    "sg:classifiers":[
        {
            "category":"Manufacturing",
            "subcategory":"Apparel",
            "type":"Manufacturing & Wholesale Goods"
        }
    ],
    "sg:phone":"+1   ",
    "sg:postcode":"14561",
    "sg:province":"NY",
    "wof:name":"Tobins Quilt Factory",
    "wof:placetype":"venue"
},
  "geometry": {"coordinates":[-77.1135,42.869086],"type":"Point"}
}