{
  "type": "Feature",
  "properties": {
    "addr:full":"412 Lafayette St Jamestown NY 14701",
    "addr:housenumber":"412",
    "addr:postcode":"14701",
    "addr:street":"Lafayette St",
    "iso:country":"US",
    "sg:address":"412 Lafayette St",
    "sg:city":"Jamestown",
    "sg:classifiers":[
        {
            "category":"Professional",
            "subcategory":"Accounting & Tax Preparation",
            "type":"Services"
        }
    ],
    "sg:phone":"+1 716 488 8452",
    "sg:postcode":"14701",
    "sg:province":"NY",
    "sg:tags":[
        "accountant",
        "public",
        "accountants-certified"
    ],
    "wof:name":"A M Suchar & Son",
    "wof:placetype":"venue"
},
  "geometry": {"coordinates":[-79.245142,42.096749],"type":"Point"}
}