{
  "type": "Feature",
  "properties": {
    "addr:full":"8 W 23rd St New York NY 10010",
    "addr:housenumber":"8",
    "addr:postcode":"10010",
    "addr:street":"W 23Rd St",
    "iso:country":"US",
    "sg:address":"8 W 23rd St",
    "sg:city":"New York",
    "sg:classifiers":[
        {
            "category":"Personal",
            "subcategory":"Shoe Repair & Shine",
            "type":"Services"
        }
    ],
    "sg:phone":"+1 212 645 9764",
    "sg:postcode":"10010",
    "sg:province":"NY",
    "wof:name":"Luz's Shoe Repair",
    "wof:placetype":"venue"
},
  "geometry": {"coordinates":[-73.98990499999999,40.741689],"type":"Point"}
}