{
  "type": "Feature",
  "properties": {
    "iso:country":"US",
    "sg:address":"120 Jean Ave",
    "sg:city":"Hempstead",
    "sg:classifiers":[
        {
            "category":"Real Estate",
            "subcategory":"Real Estate Agent",
            "type":"Services"
        }
    ],
    "sg:phone":"+1 516 489 8204",
    "sg:postcode":"11550",
    "sg:province":"NY",
    "wof:name":"Laroche Realty",
    "wof:placetype":"venue"
},
  "geometry": {"coordinates":[-73.607769,40.698443],"type":"Point"}
}