{
  "type": "Feature",
  "properties": {
    "iso:country":"US",
    "sg:address":"3259 S Winton Rd",
    "sg:city":"Rochester",
    "sg:classifiers":[
        {
            "category":"Autos & Motor Vehicles",
            "subcategory":"Motorcycle Sales",
            "type":"Retail Goods"
        }
    ],
    "sg:phone":"+1   ",
    "sg:postcode":"14623",
    "sg:province":"NY",
    "wof:name":"Flaming Pig Cycle Supply",
    "wof:placetype":"venue"
},
  "geometry": {"coordinates":[-77.58204499999999,43.091444],"type":"Point"}
}