{
  "type": "Feature",
  "properties": {
    "iso:country":"US",
    "sg:address":"1160 Strong Rd",
    "sg:city":"Victor",
    "sg:classifiers":[
        {
            "category":"Farming",
            "subcategory":"Livestock Farm",
            "type":"Manufacturing & Wholesale Goods"
        }
    ],
    "sg:phone":"+1 585 924 5444",
    "sg:postcode":"14564",
    "sg:province":"NY",
    "sg:tags":[
        "beef",
        "feedlot",
        "cattle"
    ],
    "wof:name":"Nestledale Farm",
    "wof:placetype":"venue"
},
  "geometry": {"coordinates":[-77.474828,42.979745],"type":"Point"}
}