{
  "type": "Feature",
  "properties": {
    "iso:country":"US",
    "sg:address":"22 Main St",
    "sg:city":"Narrowsburg",
    "sg:classifiers":[
        {
            "category":"Professional",
            "subcategory":"Business Services",
            "type":"Services"
        }
    ],
    "sg:phone":"+1 845 252 3829",
    "sg:postcode":"12764",
    "sg:province":"NY",
    "sg:tags":[
        "development",
        "product",
        "designers-industrial",
        "marketing",
        "commercial",
        "design"
    ],
    "wof:name":"Karl Wasner",
    "wof:placetype":"venue"
},
  "geometry": {"coordinates":[-75.061228,41.608595],"type":"Point"}
}