{
  "type": "Feature",
  "properties": {
    "iso:country":"US",
    "sg:address":"160 Orange Tpke",
    "sg:city":"Sloatsburg",
    "sg:classifiers":[
        {
            "category":"Shopping",
            "subcategory":"Hobbies, Toys, & Games",
            "type":"Retail Goods"
        },
        {
            "category":"Shopping",
            "subcategory":"Bicycles & Sporting Goods",
            "type":"Retail Goods"
        },
        {
            "category":"Recreation",
            "subcategory":"Gun Range",
            "type":"Entertainment"
        }
    ],
    "sg:phone":"+1 845 753 5303",
    "sg:postcode":"10974",
    "sg:province":"NY",
    "sg:tags":[
        "ammunition",
        "gunsmith"
    ],
    "sg:website":"http://www.masterarmsllc.com",
    "wof:name":"Master Arms LLC",
    "wof:placetype":"venue"
},
  "geometry": {"coordinates":[-74.192232,41.164796],"type":"Point"}
}