{
  "type": "Feature",
  "properties": {
    "addr:full":"2285 Davidson Ave Bronx NY 10468",
    "addr:housenumber":"2285",
    "addr:postcode":"10468",
    "addr:street":"Davidson Ave",
    "iso:country":"US",
    "sg:address":"2285 Davidson Ave",
    "sg:city":"Bronx",
    "sg:classifiers":[
        {
            "category":"Restaurant",
            "type":"Food & Drink"
        }
    ],
    "sg:phone":"+1 718 933 4666",
    "sg:postcode":"10468",
    "sg:province":"NY",
    "wof:name":"Sushi PC World",
    "wof:placetype":"venue"
},
  "geometry": {"coordinates":[-73.90462599999999,40.859191],"type":"Point"}
}