{
  "type": "Feature",
  "properties": {
    "addr:full":"4343 Northern Blvd Long Island City NY 11101",
    "addr:housenumber":"4343",
    "addr:postcode":"11101",
    "addr:street":"Northern Blvd",
    "iso:country":"US",
    "sg:address":"4343 Northern Blvd",
    "sg:city":"Long Island City",
    "sg:classifiers":[
        {
            "category":"Retail",
            "subcategory":"Auto Repair",
            "type":"Services"
        }
    ],
    "sg:phone":"+1 718 730 1888",
    "sg:postcode":"11101",
    "sg:province":"NY",
    "wof:name":"Long Island City Auto LLC",
    "wof:placetype":"venue"
},
  "geometry": {"coordinates":[-73.919676,40.75365],"type":"Point"}
}