{
  "type": "Feature",
  "properties": {
    "addr:full":"10 West St Nyack NY 10960",
    "addr:housenumber":"10",
    "addr:postcode":"10960",
    "addr:street":"West St",
    "iso:country":"US",
    "sg:address":"10 West St",
    "sg:city":"Nyack",
    "sg:classifiers":[
        {
            "category":"Building & Trades",
            "subcategory":"Cleaning & Sanitation",
            "type":"Services"
        }
    ],
    "sg:phone":"+1 845 353 5551",
    "sg:postcode":"10960",
    "sg:province":"NY",
    "wof:name":"Gateway Building Svc",
    "wof:placetype":"venue"
},
  "geometry": {"coordinates":[-73.94132,41.092946],"type":"Point"}
}