{
  "type": "Feature",
  "properties": {
    "addr:full":"411 W Broadway New York NY 10012",
    "addr:housenumber":"411",
    "addr:postcode":"10012",
    "addr:street":"W Broadway",
    "iso:country":"US",
    "sg:address":"411 W Broadway",
    "sg:city":"New York",
    "sg:classifiers":[
        {
            "category":"Professional",
            "type":"Services"
        }
    ],
    "sg:phone":"+1 212 219 0278",
    "sg:postcode":"10012",
    "sg:province":"NY",
    "sg:tags":[
        "establishment"
    ],
    "wof:name":"Fridi Inc",
    "wof:placetype":"venue"
},
  "geometry": {"coordinates":[-74.00092100000001,40.725597],"type":"Point"}
}