{
  "type": "Feature",
  "properties": {
    "iso:country":"US",
    "sg:address":"785 Sheridan Dr",
    "sg:city":"Tonawanda",
    "sg:classifiers":[
        {
            "category":"Building & Trades",
            "subcategory":"Equipment Rental",
            "type":"Services"
        }
    ],
    "sg:phone":"+1   ",
    "sg:postcode":"14150",
    "sg:province":"NY",
    "sg:tags":[
        "lawnmowers",
        "lawn",
        "tool",
        "garden"
    ],
    "wof:name":"J B Tool Rental & Paint Co",
    "wof:placetype":"venue"
},
  "geometry": {"coordinates":[-78.905325,42.977959],"type":"Point"}
}