{
  "type": "Feature",
  "properties": {
    "addr:full":"1686 Sweets Corners Rd Fairport NY 14450",
    "addr:housenumber":"1686",
    "addr:postcode":"14450",
    "addr:street":"Sweets Corners Rd",
    "iso:country":"US",
    "sg:address":"1686 Sweets Corners Rd",
    "sg:city":"Fairport",
    "sg:classifiers":[
        {
            "category":"Building & Trades",
            "subcategory":"Construction",
            "type":"Services"
        }
    ],
    "sg:phone":"+1 585 388 0666",
    "sg:postcode":"14450",
    "sg:province":"NY",
    "sg:tags":[
        "designer",
        "dealer",
        "pool",
        "swimming"
    ],
    "wof:name":"North Eastern Construction",
    "wof:placetype":"venue"
},
  "geometry": {"coordinates":[-77.39773599999999,43.152538],"type":"Point"}
}