{
  "type": "Feature",
  "properties": {
    "addr:full":"2305 Orleans Ave Niagara Falls NY 14303",
    "addr:housenumber":"2305",
    "addr:postcode":"14303",
    "addr:street":"Orleans Ave",
    "iso:country":"US",
    "sg:address":"2305 Orleans Ave",
    "sg:city":"Niagara Falls",
    "sg:classifiers":[
        {
            "category":"Insurance",
            "subcategory":"Insurance Agent",
            "type":"Services"
        }
    ],
    "sg:phone":"+1 716 285 1943",
    "sg:postcode":"14303",
    "sg:province":"NY",
    "wof:name":"Thrivent Fincl For Lutherans",
    "wof:placetype":"venue"
},
  "geometry": {"coordinates":[-79.034119,43.089888],"type":"Point"}
}