{
  "type": "Feature",
  "properties": {
    "addr:full":"541 Doe Rd Waterville NY 13480",
    "addr:housenumber":"541",
    "addr:postcode":"13480",
    "addr:street":"Doe Rd",
    "iso:country":"US",
    "sg:address":"541 Doe Rd",
    "sg:city":"Waterville",
    "sg:classifiers":[
        {
            "category":"Building & Trades",
            "subcategory":"Construction",
            "type":"Services"
        }
    ],
    "sg:phone":"+1 315 841 3284",
    "sg:postcode":"13480",
    "sg:province":"NY",
    "sg:tags":[
        "general",
        "contractor"
    ],
    "wof:name":"WRA Construction",
    "wof:placetype":"venue"
},
  "geometry": {"coordinates":[-75.30063699999999,42.895382],"type":"Point"}
}