{
  "type": "Feature",
  "properties": {
    "iso:country":"US",
    "sg:address":"414 E 73 St",
    "sg:city":"New York",
    "sg:classifiers":[
        {
            "category":"Building & Trades",
            "subcategory":"Construction",
            "type":"Services"
        }
    ],
    "sg:phone":"+1 212 879 3589",
    "sg:postcode":"10021",
    "sg:province":"NY",
    "sg:tags":[
        "interior",
        "painting",
        "commercial",
        "exterior",
        "space"
    ],
    "wof:name":"Reece Restoration & Finishing",
    "wof:placetype":"venue"
},
  "geometry": {"coordinates":[-73.95422600000001,40.767899],"type":"Point"}
}