{
  "type": "Feature",
  "properties": {
    "addr:full":"34 Danville Dr Greenlawn NY 11740",
    "addr:housenumber":"34",
    "addr:postcode":"11740",
    "addr:street":"Danville Dr",
    "iso:country":"US",
    "sg:address":"34 Danville Dr",
    "sg:city":"Greenlawn",
    "sg:classifiers":[
        {
            "category":"Health Services",
            "subcategory":"Medical Lab",
            "type":"Services"
        }
    ],
    "sg:phone":"+1 631 754 5738",
    "sg:postcode":"11740",
    "sg:province":"NY",
    "sg:tags":[
        "laboratory"
    ],
    "wof:name":"Doctors Office For Pediatrics",
    "wof:placetype":"venue"
},
  "geometry": {"coordinates":[-73.348569,40.861918],"type":"Point"}
}