{
  "type": "Feature",
  "properties": {
    "addr:full":"791 Westchester Avenue Bronx NY 10455",
    "addr:housenumber":"791",
    "addr:postcode":"10455",
    "addr:street":"Westchester Avenue",
    "iso:country":"US",
    "sg:address":"791 Westchester Avenue",
    "sg:city":"Bronx",
    "sg:classifiers":[
        {
            "category":"Home & Garden",
            "subcategory":"Furniture",
            "type":"Retail Goods"
        }
    ],
    "sg:phone":"+1 718 861 4151",
    "sg:postcode":"10455",
    "sg:province":"NY",
    "sg:tags":[
        "store"
    ],
    "wof:name":"Frank P Diaz Furniture",
    "wof:placetype":"venue"
},
  "geometry": {"coordinates":[-73.904149,40.818561],"type":"Point"}
}