{
  "type": "Feature",
  "properties": {
    "addr:full":"63 Penn St Brooklyn NY 11211",
    "addr:housenumber":"63",
    "addr:postcode":"11211",
    "addr:street":"Penn St",
    "iso:country":"US",
    "sg:address":"63 Penn St",
    "sg:city":"Brooklyn",
    "sg:classifiers":[
        {
            "category":"Insurance",
            "subcategory":"Insurance Agent",
            "type":"Services"
        }
    ],
    "sg:phone":"+1 718 596 0948",
    "sg:postcode":"11211",
    "sg:province":"NY",
    "wof:name":"Moses Glanzer Ins",
    "wof:placetype":"venue"
},
  "geometry": {"coordinates":[-73.95912199999999,40.701684],"type":"Point"}
}