{
  "type": "Feature",
  "properties": {
    "addr:full":"117 Lake St Rouses Point NY 12979",
    "addr:housenumber":"117",
    "addr:postcode":"12979",
    "addr:street":"Lake St",
    "iso:country":"US",
    "sg:address":"117 Lake St",
    "sg:city":"Rouses Point",
    "sg:classifiers":[
        {
            "category":"Home & Garden",
            "subcategory":"Furniture",
            "type":"Retail Goods"
        }
    ],
    "sg:phone":"+1   ",
    "sg:postcode":"12979",
    "sg:province":"NY",
    "sg:tags":[
        "carpeting"
    ],
    "wof:name":"Kathys Furniture and Carpet",
    "wof:placetype":"venue"
},
  "geometry": {"coordinates":[-73.36425699999999,44.992382],"type":"Point"}
}