{
  "type": "Feature",
  "properties": {
    "iso:country":"US",
    "sg:address":"313 Guy Lombardo Ave",
    "sg:city":"Freeport",
    "sg:classifiers":[
        {
            "category":"Personal",
            "subcategory":"Beauty Salon",
            "type":"Services"
        }
    ],
    "sg:phone":"+1   ",
    "sg:postcode":"11520",
    "sg:province":"NY",
    "sg:tags":[
        "shop"
    ],
    "wof:name":"Visage Hair Studio",
    "wof:placetype":"venue"
},
  "geometry": {"coordinates":[-73.583164,40.646921],"type":"Point"}
}