{
  "type": "Feature",
  "properties": {
    "iso:country":"US",
    "sg:address":"142 Fulton Ave",
    "sg:city":"New Hyde Park",
    "sg:classifiers":[
        {
            "category":"Manufacturing",
            "subcategory":"Printing",
            "type":"Manufacturing & Wholesale Goods"
        }
    ],
    "sg:phone":"+1 516 746 4142",
    "sg:postcode":"11040",
    "sg:province":"NY",
    "sg:tags":[
        "reproduction",
        "offset"
    ],
    "wof:name":"Reflex Offset Inc",
    "wof:placetype":"venue"
},
  "geometry": {"coordinates":[-73.658866,40.73721],"type":"Point"}
}