{
  "type": "Feature",
  "properties": {
    "addr:full":"7711 Rockaway Boulevard Woodhaven NY 11421",
    "addr:housenumber":"7711",
    "addr:postcode":"11421",
    "addr:street":"Rockaway Boulevard",
    "iso:country":"US",
    "sg:address":"7711 Rockaway Boulevard",
    "sg:city":"Woodhaven",
    "sg:classifiers":[
        {
            "category":"Real Estate",
            "subcategory":"Real Estate Services",
            "type":"Services"
        }
    ],
    "sg:phone":"+1 347 494 4180",
    "sg:postcode":"11421",
    "sg:province":"NY",
    "sg:tags":[
        "management",
        "property"
    ],
    "wof:name":"Royal Homes Realty",
    "wof:placetype":"venue"
},
  "geometry": {"coordinates":[-73.862754,40.685392],"type":"Point"}
}