{
  "type": "Feature",
  "properties": {
    "addr:full":"1 Lincoln Plz Apt 33L New York NY 10023",
    "addr:housenumber":"1",
    "addr:postcode":"10023",
    "addr:street":"Lincoln Plz Apt 33L",
    "iso:country":"US",
    "sg:address":"1 Lincoln Plz Apt 33L",
    "sg:city":"New York",
    "sg:classifiers":[
        {
            "category":"Health Services",
            "subcategory":"Doctor",
            "type":"Services"
        }
    ],
    "sg:phone":"+1 212 799 1060",
    "sg:postcode":"10023",
    "sg:province":"NY",
    "sg:tags":[
        "psychiatrist"
    ],
    "wof:name":"Saffron Dorothy MD",
    "wof:placetype":"venue"
},
  "geometry": {"coordinates":[-73.981697,40.771999],"type":"Point"}
}