{
  "type": "Feature",
  "properties": {
    "addr:full":"290 Larkin Dr Ste 104 Monroe NY 10950",
    "addr:housenumber":"290",
    "addr:postcode":"10950",
    "addr:street":"Larkin Dr Ste 104",
    "iso:country":"US",
    "sg:address":"290 Larkin Dr Ste 104",
    "sg:city":"Monroe",
    "sg:classifiers":[
        {
            "category":"Shopping",
            "subcategory":"Mobile Phones",
            "type":"Retail Goods"
        }
    ],
    "sg:phone":"+1 845 783 3696",
    "sg:postcode":"10950",
    "sg:province":"NY",
    "wof:name":"Wireless Icon Verizon Wireless",
    "wof:placetype":"venue"
},
  "geometry": {"coordinates":[-74.150516,41.320482],"type":"Point"}
}