{
  "type": "Feature",
  "properties": {
    "iso:country":"US",
    "sg:address":"4390 Buffalo Rd",
    "sg:city":"North Chili",
    "sg:classifiers":[
        {
            "category":"Education",
            "subcategory":"Dance Studio",
            "type":"Public Place"
        }
    ],
    "sg:phone":"+1 585 594 0373",
    "sg:postcode":"14514",
    "sg:province":"NY",
    "sg:tags":[
        "instruction",
        "dancing"
    ],
    "wof:name":"Chili Performing Dance Ctr",
    "wof:placetype":"venue"
},
  "geometry": {"coordinates":[-77.807405,43.119613],"type":"Point"}
}