{
  "type": "Feature",
  "properties": {
    "addr:full":"4802 3rd Ave Brooklyn NY 11220",
    "addr:housenumber":"4802",
    "addr:postcode":"11220",
    "addr:street":"3Rd Ave",
    "iso:country":"US",
    "sg:address":"4802 3rd Ave",
    "sg:city":"Brooklyn",
    "sg:classifiers":[
        {
            "category":"Building & Trades",
            "subcategory":"Construction",
            "type":"Services"
        }
    ],
    "sg:phone":"+1 718 680 2875",
    "sg:postcode":"11220",
    "sg:province":"NY",
    "sg:tags":[
        "roofing",
        "contractor"
    ],
    "wof:name":"Condor Roofing",
    "wof:placetype":"venue"
},
  "geometry": {"coordinates":[-74.013785,40.648134],"type":"Point"}
}