{
  "type": "Feature",
  "properties": {
    "addr:full":"52 W 12 St New York NY 10011",
    "addr:housenumber":"52",
    "addr:postcode":"10011",
    "addr:street":"W 12 St",
    "iso:country":"US",
    "sg:address":"52 W 12 St",
    "sg:city":"New York",
    "sg:classifiers":[
        {
            "category":"Real Estate",
            "subcategory":"Real Estate Agent",
            "type":"Services"
        }
    ],
    "sg:phone":"+1 212 620 0418",
    "sg:postcode":"10011",
    "sg:province":"NY",
    "wof:name":"David Lidsky",
    "wof:placetype":"venue"
},
  "geometry": {"coordinates":[-73.996571,40.735258],"type":"Point"}
}