{
  "type": "Feature",
  "properties": {
    "iso:country":"US",
    "sg:address":"2 Broad St",
    "sg:city":"Lyons",
    "sg:classifiers":[
        {
            "category":"Social Services",
            "type":"Services"
        }
    ],
    "sg:phone":"+1 315 946 5333",
    "sg:postcode":"14489",
    "sg:province":"NY",
    "wof:name":"Literacy Volunteers Wayne Cnty",
    "wof:placetype":"venue"
},
  "geometry": {"coordinates":[-76.994326,43.063385],"type":"Point"}
}