{
  "type": "Feature",
  "properties": {
    "addr:full":"400 Central Park W New York NY 10025",
    "addr:housenumber":"400",
    "addr:postcode":"10025",
    "addr:street":"Central Park W",
    "iso:country":"US",
    "sg:address":"400 Central Park W",
    "sg:city":"New York",
    "sg:classifiers":[
        {
            "category":"Social Services",
            "subcategory":"Adult Care",
            "type":"Services"
        }
    ],
    "sg:phone":"+1 212 222 9163",
    "sg:postcode":"10025",
    "sg:province":"NY",
    "sg:tags":[
        "organization",
        "senior",
        "citizen"
    ],
    "wof:name":"Greater NY Assn-Private Grtc",
    "wof:placetype":"venue"
},
  "geometry": {"coordinates":[-73.963804,40.792881],"type":"Point"}
}