{
  "type": "Feature",
  "properties": {
    "iso:country":"US",
    "sg:address":"871 Monroe Ave",
    "sg:city":"Rochester",
    "sg:classifiers":[
        {
            "category":"Personal",
            "subcategory":"Beauty Salon",
            "type":"Services"
        }
    ],
    "sg:phone":"+1 585 271 3730",
    "sg:postcode":"14620",
    "sg:province":"NY",
    "wof:name":"J H Salon",
    "wof:placetype":"venue"
},
  "geometry": {"coordinates":[-77.58579899999999,43.142012],"type":"Point"}
}