{
  "type": "Feature",
  "properties": {
    "iso:country":"US",
    "sg:address":"554 Morrison St",
    "sg:city":"Watertown",
    "sg:classifiers":[
        {
            "category":"Building & Trades",
            "subcategory":"Construction",
            "type":"Services"
        }
    ],
    "sg:phone":"+1 315 788 6632",
    "sg:postcode":"13601",
    "sg:province":"NY",
    "sg:tags":[
        "specializing",
        "roofing",
        "work",
        "siding",
        "contractor",
        "window"
    ],
    "wof:name":"Piazza Construction",
    "wof:placetype":"venue"
},
  "geometry": {"coordinates":[-75.91548,43.983665],"type":"Point"}
}