{
  "type": "Feature",
  "properties": {
    "addr:full":"209 Walt Whitman Rd Huntington Station NY 11746",
    "addr:housenumber":"209",
    "addr:postcode":"11746",
    "addr:street":"Walt Whitman Rd",
    "iso:country":"US",
    "sg:address":"209 Walt Whitman Rd",
    "sg:city":"Huntington Station",
    "sg:classifiers":[
        {
            "category":"Restaurant",
            "type":"Food & Drink"
        }
    ],
    "sg:phone":"+1   ",
    "sg:postcode":"11746",
    "sg:province":"NY",
    "sg:tags":[
        "eating"
    ],
    "wof:name":"Francescos Pizza Restaurant",
    "wof:placetype":"venue"
},
  "geometry": {"coordinates":[-73.41030000000001,40.814705],"type":"Point"}
}