{
  "type": "Feature",
  "properties": {
    "addr:full":"6375 Genesee St Lancaster NY 14086",
    "addr:housenumber":"6375",
    "addr:postcode":"14086",
    "addr:street":"Genesee St",
    "iso:country":"US",
    "sg:address":"6375 Genesee St",
    "sg:city":"Lancaster",
    "sg:classifiers":[
        {
            "category":"Professional",
            "type":"Services"
        }
    ],
    "sg:phone":"+1   ",
    "sg:postcode":"14086",
    "sg:province":"NY",
    "wof:name":"Albert H Meyer",
    "wof:placetype":"venue"
},
  "geometry": {"coordinates":[-78.58353099999999,42.946702],"type":"Point"}
}