{
  "type": "Feature",
  "properties": {
    "addr:full":"2120 Niagara Falls Blvd Tonawanda NY 14150",
    "addr:housenumber":"2120",
    "addr:postcode":"14150",
    "addr:street":"Niagara Falls Blvd",
    "iso:country":"US",
    "sg:address":"2120 Niagara Falls Blvd",
    "sg:city":"Tonawanda",
    "sg:classifiers":[
        {
            "category":"Insurance",
            "subcategory":"Insurance Agent",
            "type":"Services"
        }
    ],
    "sg:phone":"+1 716 694 9400",
    "sg:postcode":"14150",
    "sg:province":"NY",
    "wof:name":"Allstate Insurance Co",
    "wof:placetype":"venue"
},
  "geometry": {"coordinates":[-78.82233100000001,43.014584],"type":"Point"}
}