{
  "type": "Feature",
  "properties": {
    "iso:country":"US",
    "sg:address":"1722 1st Ave",
    "sg:city":"New York",
    "sg:classifiers":[
        {
            "category":"Personal",
            "subcategory":"Nail Salon",
            "type":"Services"
        }
    ],
    "sg:phone":"+1 212 427 1122",
    "sg:postcode":"10128",
    "sg:province":"NY",
    "wof:name":"Yong's Nails",
    "wof:placetype":"venue"
},
  "geometry": {"coordinates":[-73.94760100000001,40.779099],"type":"Point"}
}