{
  "type": "Feature",
  "properties": {
    "iso:country":"US",
    "sg:address":"31 Patrician St",
    "sg:city":"Holbrook",
    "sg:classifiers":[
        {
            "category":"Freight",
            "type":"Transportation"
        }
    ],
    "sg:phone":"+1 631 471 8632",
    "sg:postcode":"11741",
    "sg:province":"NY",
    "sg:tags":[
        "business",
        "trucking",
        "operator",
        "contractor",
        "trade",
        "local"
    ],
    "wof:name":"PR Movers Inc",
    "wof:placetype":"venue"
},
  "geometry": {"coordinates":[-73.072788,40.783514],"type":"Point"}
}