{
  "type": "Feature",
  "properties": {
    "addr:full":"963 Kings Hwy Saugerties NY 12477",
    "addr:housenumber":"963",
    "addr:postcode":"12477",
    "addr:street":"Kings Hwy",
    "iso:country":"US",
    "sg:address":"963 Kings Hwy",
    "sg:city":"Saugerties",
    "sg:classifiers":[
        {
            "category":"Food & Beverages",
            "subcategory":"Groceries & Convenience Stores",
            "type":"Retail Goods"
        }
    ],
    "sg:phone":"+1   ",
    "sg:postcode":"12477",
    "sg:province":"NY",
    "wof:name":"Stone Pony",
    "wof:placetype":"venue"
},
  "geometry": {"coordinates":[-73.979398,42.050861],"type":"Point"}
}