{
  "type": "Feature",
  "properties": {
    "addr:full":"141 2nd Ave Frnt A New York NY 10003",
    "addr:housenumber":"141",
    "addr:postcode":"10003",
    "addr:street":"2Nd Ave;A",
    "iso:country":"US",
    "sg:address":"141 2nd Ave Frnt A",
    "sg:city":"New York",
    "sg:classifiers":[
        {
            "category":"Food & Beverages",
            "subcategory":"Bakery",
            "type":"Retail Goods"
        }
    ],
    "sg:phone":"+1 212 777 8611",
    "sg:postcode":"10003",
    "sg:province":"NY",
    "sg:tags":[
        "sandwich"
    ],
    "wof:name":"Subway Sandwiches",
    "wof:placetype":"venue"
},
  "geometry": {"coordinates":[-73.98744000000001,40.729146],"type":"Point"}
}