{
  "type": "Feature",
  "properties": {
    "addr:full":"49 Wadsworth Ave New York NY 10033",
    "addr:housenumber":"49",
    "addr:postcode":"10033",
    "addr:street":"Wadsworth Ave",
    "iso:country":"US",
    "sg:address":"49 Wadsworth Ave",
    "sg:city":"New York",
    "sg:classifiers":[
        {
            "category":"Health Services",
            "subcategory":"Doctor",
            "type":"Services"
        }
    ],
    "sg:phone":"+1 845 429 2993",
    "sg:postcode":"10033",
    "sg:province":"NY",
    "sg:tags":[
        "dentist"
    ],
    "wof:name":"Claudia Botero-Mondul DDS",
    "wof:placetype":"venue"
},
  "geometry": {"coordinates":[-73.93743499999999,40.846249],"type":"Point"}
}