{
  "type": "Feature",
  "properties": {
    "addr:full":"241 Blake Ave Brooklyn NY 11212",
    "addr:housenumber":"241",
    "addr:postcode":"11212",
    "addr:street":"Blake Ave",
    "iso:country":"US",
    "sg:address":"241 Blake Ave",
    "sg:city":"Brooklyn",
    "sg:classifiers":[
        {
            "category":"Food & Beverages",
            "subcategory":"Groceries & Convenience Stores",
            "type":"Retail Goods"
        }
    ],
    "sg:phone":"+1 718 922 2225",
    "sg:postcode":"11212",
    "sg:province":"NY",
    "sg:tags":[
        "grocer"
    ],
    "wof:name":"Castro Grocery",
    "wof:placetype":"venue"
},
  "geometry": {"coordinates":[-73.909699,40.665628],"type":"Point"}
}