{
  "type": "Feature",
  "properties": {
    "addr:full":"186 E Broadway Monticello NY 12701",
    "addr:housenumber":"186",
    "addr:postcode":"12701",
    "addr:street":"E Broadway",
    "iso:country":"US",
    "sg:address":"186 E Broadway",
    "sg:city":"Monticello",
    "sg:classifiers":[
        {
            "category":"Shopping",
            "subcategory":"Antiques",
            "type":"Retail Goods"
        },
        {
            "category":"Professional",
            "subcategory":"Business Services",
            "type":"Services"
        }
    ],
    "sg:phone":"+1 845 796 7653",
    "sg:postcode":"12701",
    "sg:province":"NY",
    "sg:tags":[
        "auction",
        "auctioneer"
    ],
    "wof:name":"Malek Auction Sales Inc",
    "wof:placetype":"venue"
},
  "geometry": {"coordinates":[-74.66533699999999,41.649361],"type":"Point"}
}