{
  "type": "Feature",
  "properties": {
    "addr:full":"2149 State Rte 66 Ghent NY 12075",
    "addr:housenumber":"2149",
    "addr:postcode":"12075",
    "addr:street":"State Rte 66",
    "iso:country":"US",
    "sg:address":"2149 State Rte 66",
    "sg:city":"Ghent",
    "sg:classifiers":[
        {
            "category":"Building & Trades",
            "subcategory":"Landscaping Services",
            "type":"Services"
        }
    ],
    "sg:phone":"+1 518 392 6010",
    "sg:postcode":"12075",
    "sg:province":"NY",
    "sg:tags":[
        "lawn",
        "maintenance",
        "grounds"
    ],
    "wof:name":"Columbia Estates Caretaking",
    "wof:placetype":"venue"
},
  "geometry": {"coordinates":[-73.623051,42.322403],"type":"Point"}
}