{
  "type": "Feature",
  "properties": {
    "addr:full":"154 Grand St New York NY 10013",
    "addr:housenumber":"154",
    "addr:postcode":"10013",
    "addr:street":"Grand St",
    "iso:country":"US",
    "sg:address":"154 Grand St",
    "sg:city":"New York",
    "sg:classifiers":[
        {
            "category":"Professional",
            "subcategory":"Computer Services",
            "type":"Services"
        }
    ],
    "sg:postcode":"10013",
    "sg:province":"NY",
    "wof:name":"Interpersonal Frequency",
    "wof:placetype":"venue"
},
  "geometry": {"coordinates":[-73.998565,40.719901],"type":"Point"}
}