{
  "type": "Feature",
  "properties": {
    "addr:full":"77 Myrtle Blvd Larchmont NY 10538",
    "addr:housenumber":"77",
    "addr:postcode":"10538",
    "addr:street":"Myrtle Blvd",
    "iso:country":"US",
    "sg:address":"77 Myrtle Blvd",
    "sg:city":"Larchmont",
    "sg:classifiers":[
        {
            "category":"Real Estate",
            "subcategory":"Developer",
            "type":"Services"
        }
    ],
    "sg:phone":"+1 914 834 2616",
    "sg:postcode":"10538",
    "sg:province":"NY",
    "wof:name":"Earth Smarts Development Inc",
    "wof:placetype":"venue"
},
  "geometry": {"coordinates":[-73.754409,40.9403],"type":"Point"}
}