{
  "type": "Feature",
  "properties": {
    "addr:full":"7 Palatine Ct Syosset NY 11791",
    "addr:housenumber":"7",
    "addr:postcode":"11791",
    "addr:street":"Palatine Ct",
    "iso:country":"US",
    "sg:address":"7 Palatine Ct",
    "sg:city":"Syosset",
    "sg:classifiers":[
        {
            "category":"Health Services",
            "subcategory":"Doctor",
            "type":"Services"
        }
    ],
    "sg:phone":"+1   ",
    "sg:postcode":"11791",
    "sg:province":"NY",
    "wof:name":"Elaine Rogers",
    "wof:placetype":"venue"
},
  "geometry": {"coordinates":[-73.494608,40.845903],"type":"Point"}
}