{
  "type": "Feature",
  "properties": {
    "addr:full":"71 Goodway Dr Rochester NY 14623",
    "addr:housenumber":"71",
    "addr:postcode":"14623",
    "addr:street":"Goodway Dr",
    "iso:country":"US",
    "sg:address":"71 Goodway Dr",
    "sg:city":"Rochester",
    "sg:classifiers":[
        {
            "category":"Professional",
            "subcategory":"Management & Consulting",
            "type":"Services"
        }
    ],
    "sg:phone":"+1 585 424 2702",
    "sg:postcode":"14623",
    "sg:province":"NY",
    "sg:tags":[
        "consultant"
    ],
    "wof:name":"Bennett Group",
    "wof:placetype":"venue"
},
  "geometry": {"coordinates":[-77.58080200000001,43.091997],"type":"Point"}
}