{
  "type": "Feature",
  "properties": {
    "addr:full":"1310 Surf Ave Brooklyn NY 11224",
    "addr:housenumber":"1310",
    "addr:postcode":"11224",
    "addr:street":"Surf Ave",
    "iso:country":"US",
    "sg:address":"1310 Surf Ave",
    "sg:city":"Brooklyn",
    "sg:classifiers":[
        {
            "category":"Restaurant",
            "type":"Food & Drink"
        }
    ],
    "sg:menulink":"http://www.allmenus.com/ny/brooklyn/162618-nathans-famous/menu/",
    "sg:phone":"+1 718 946 2202",
    "sg:postcode":"11224",
    "sg:province":"NY",
    "sg:tags":[
        "american",
        "hot",
        "dog"
    ],
    "wof:name":"Nathan's Famous",
    "wof:placetype":"venue"
},
  "geometry": {"coordinates":[-73.98166500000001,40.575519],"type":"Point"}
}