{
  "type": "Feature",
  "properties": {
    "iso:country":"US",
    "sg:address":"25 Mile Rd",
    "sg:city":"Suffern",
    "sg:classifiers":[
        {
            "category":"Communications",
            "type":"Services"
        }
    ],
    "sg:phone":"+1 845 369 9612",
    "sg:postcode":"10901",
    "sg:province":"NY",
    "wof:name":"Abovenet Communications Inc",
    "wof:placetype":"venue"
},
  "geometry": {"coordinates":[-74.115234,41.131218],"type":"Point"}
}