{
  "type": "Feature",
  "properties": {
    "addr:full":"10 Commercial Ave Highland NY 12528",
    "addr:housenumber":"10",
    "addr:postcode":"12528",
    "addr:street":"Commercial Ave",
    "iso:country":"US",
    "sg:address":"10 Commercial Ave",
    "sg:city":"Highland",
    "sg:classifiers":[
        {
            "category":"Utilities",
            "subcategory":"Refuse",
            "type":"Services"
        }
    ],
    "sg:phone":"+1   ",
    "sg:postcode":"12528",
    "sg:province":"NY",
    "sg:tags":[
        "auto",
        "recycling",
        "oil"
    ],
    "wof:name":"Vaz Co Reclaiming Services",
    "wof:placetype":"venue"
},
  "geometry": {"coordinates":[-73.967755,41.718981],"type":"Point"}
}