{
  "type": "Feature",
  "properties": {
    "iso:country":"US",
    "sg:address":"93 Maple St Apt 2L",
    "sg:city":"Yonkers",
    "sg:classifiers":[
        {
            "category":"Professional",
            "subcategory":"Detective & Security Services",
            "type":"Services"
        }
    ],
    "sg:phone":"+1 914 316 3131",
    "sg:postcode":"10701",
    "sg:province":"NY",
    "sg:tags":[
        "information",
        "bureau"
    ],
    "wof:name":"Pet Service",
    "wof:placetype":"venue"
},
  "geometry": {"coordinates":[-73.88954099999999,40.931741],"type":"Point"}
}