{
  "type": "Feature",
  "properties": {
    "iso:country":"US",
    "sg:address":"95 Hartley Rd",
    "sg:city":"Goshen",
    "sg:classifiers":[
        {
            "category":"Wholesale",
            "subcategory":"Scrap",
            "type":"Manufacturing & Wholesale Goods"
        }
    ],
    "sg:phone":"+1 845 294 3789",
    "sg:postcode":"10924",
    "sg:province":"NY",
    "sg:tags":[
        "recycling",
        "center"
    ],
    "wof:name":"Waste Management",
    "wof:placetype":"venue"
},
  "geometry": {"coordinates":[-74.37211000000001,41.408705],"type":"Point"}
}