{
  "type": "Feature",
  "properties": {
    "iso:country":"US",
    "sg:address":"3 Windy Hill Cir",
    "sg:city":"Fairport",
    "sg:classifiers":[
        {
            "category":"Shopping",
            "subcategory":"Clothing, Apparel, & Fashions",
            "type":"Retail Goods"
        }
    ],
    "sg:phone":"+1   ",
    "sg:postcode":"14450",
    "sg:province":"NY",
    "wof:name":"Perfection Uniform Co",
    "wof:placetype":"venue"
},
  "geometry": {"coordinates":[-77.406952,43.083765],"type":"Point"}
}