{
  "type": "Feature",
  "properties": {
    "iso:country":"US",
    "sg:address":"1786 E 49th St",
    "sg:city":"Brooklyn",
    "sg:classifiers":[
        {
            "category":"Wholesale",
            "subcategory":"Machinery & Supplies",
            "type":"Manufacturing & Wholesale Goods"
        }
    ],
    "sg:phone":"+1 718 376 9301",
    "sg:postcode":"11234",
    "sg:province":"NY",
    "sg:tags":[
        "equipment",
        "establishment"
    ],
    "wof:name":"Gotham Chemical Corp",
    "wof:placetype":"venue"
},
  "geometry": {"coordinates":[-73.92787300000001,40.61857],"type":"Point"}
}