{
  "type": "Feature",
  "properties": {
    "iso:country":"US",
    "sg:address":"31 W 47th St Ste 701",
    "sg:city":"New York",
    "sg:classifiers":[
        {
            "category":"Building & Trades",
            "subcategory":"Landscaping Services",
            "type":"Services"
        },
        {
            "category":"Shopping",
            "subcategory":"Jewelry",
            "type":"Retail Goods"
        }
    ],
    "sg:phone":"+1 212 840 8166",
    "sg:postcode":"10036",
    "sg:province":"NY",
    "sg:tags":[
        "gardener"
    ],
    "wof:name":"Engel Mike",
    "wof:placetype":"venue"
},
  "geometry": {"coordinates":[-73.99099699999999,40.7607],"type":"Point"}
}