{
  "type": "Feature",
  "properties": {
    "iso:country":"US",
    "sg:address":"2006 Ocean Ave",
    "sg:city":"Brooklyn",
    "sg:classifiers":[
        {
            "category":"Health Services",
            "subcategory":"Doctor",
            "type":"Services"
        }
    ],
    "sg:phone":"+1 718 645 7474",
    "sg:postcode":"11230",
    "sg:province":"NY",
    "wof:name":"New York Physician House Call PC",
    "wof:placetype":"venue"
},
  "geometry": {"coordinates":[-73.954382,40.612891],"type":"Point"}
}