{
  "type": "Feature",
  "properties": {
    "addr:full":"579 E 187th St Bronx NY 10458",
    "addr:housenumber":"579",
    "addr:postcode":"10458",
    "addr:street":"E 187Th St",
    "iso:country":"US",
    "sg:address":"579 E 187th St",
    "sg:city":"Bronx",
    "sg:classifiers":[
        {
            "category":"Shopping",
            "subcategory":"Clothing, Apparel, & Fashions",
            "type":"Retail Goods"
        }
    ],
    "sg:phone":"+1 718 220 8867",
    "sg:postcode":"10458",
    "sg:province":"NY",
    "wof:name":"J & P Svc",
    "wof:placetype":"venue"
},
  "geometry": {"coordinates":[-73.887715,40.855751],"type":"Point"}
}