{
  "type": "Feature",
  "properties": {
    "iso:country":"US",
    "sg:address":"477 Hamilton St",
    "sg:city":"Geneva",
    "sg:classifiers":[
        {
            "category":"Restaurant",
            "type":"Food & Drink"
        }
    ],
    "sg:menulink":"http://www.allmenus.com/ny/geneva/200629-long-john-silvers/menu/",
    "sg:phone":"+1 315 789 8507",
    "sg:postcode":"14456",
    "sg:province":"NY",
    "sg:tags":[
        "seafood",
        "american"
    ],
    "wof:name":"Long John Silver's",
    "wof:placetype":"venue"
},
  "geometry": {"coordinates":[-77.00378000000001,42.856393],"type":"Point"}
}