{
  "type": "Feature",
  "properties": {
    "iso:country":"US",
    "sg:address":"191 Main St",
    "sg:city":"New Canaan",
    "sg:classifiers":[
        {
            "category":"Real Estate",
            "subcategory":"Architect",
            "type":"Services"
        }
    ],
    "sg:phone":"+1   ",
    "sg:postcode":"06840",
    "sg:province":"NY",
    "sg:tags":[
        "architectural"
    ],
    "wof:name":"Dupont Laurent T PC",
    "wof:placetype":"venue"
},
  "geometry": {"coordinates":[-73.49065299999999,41.144619],"type":"Point"}
}