{
  "type": "Feature",
  "properties": {
    "addr:full":"413 Bay Ridge Ave Brooklyn NY 11220",
    "addr:housenumber":"413",
    "addr:postcode":"11220",
    "addr:street":"Bay Ridge Ave",
    "iso:country":"US",
    "sg:address":"413 Bay Ridge Ave",
    "sg:city":"Brooklyn",
    "sg:classifiers":[
        {
            "category":"Utilities",
            "subcategory":"Mobile Phone",
            "type":"Services"
        }
    ],
    "sg:phone":"+1 718 921 2385",
    "sg:postcode":"11220",
    "sg:province":"NY",
    "sg:tags":[
        "repair",
        "beeper"
    ],
    "wof:name":"F N Inc",
    "wof:placetype":"venue"
},
  "geometry": {"coordinates":[-74.02120600000001,40.633674],"type":"Point"}
}