{
  "type": "Feature",
  "properties": {
    "iso:country":"US",
    "sg:address":"115 W Locust St",
    "sg:city":"Rome",
    "sg:classifiers":[
        {
            "category":"Building & Trades",
            "subcategory":"Construction",
            "type":"Services"
        }
    ],
    "sg:phone":"+1 315 336 3801",
    "sg:postcode":"13440",
    "sg:province":"NY",
    "sg:tags":[
        "contractor"
    ],
    "wof:name":"William Evans Contractor",
    "wof:placetype":"venue"
},
  "geometry": {"coordinates":[-75.448679,43.224199],"type":"Point"}
}