{
  "type": "Feature",
  "properties": {
    "addr:full":"81 E Fairmount Ave Lakewood NY 14750",
    "addr:housenumber":"81",
    "addr:postcode":"14750",
    "addr:street":"E Fairmount Ave",
    "iso:country":"US",
    "sg:address":"81 E Fairmount Ave",
    "sg:city":"Lakewood",
    "sg:classifiers":[
        {
            "category":"Retail",
            "subcategory":"Repair Shop",
            "type":"Services"
        }
    ],
    "sg:phone":"+1 716 763 7541",
    "sg:postcode":"14750",
    "sg:province":"NY",
    "sg:tags":[
        "upholstery",
        "work"
    ],
    "wof:name":"Speedy Auto",
    "wof:placetype":"venue"
},
  "geometry": {"coordinates":[-79.31947099999999,42.09817],"type":"Point"}
}