{
  "type": "Feature",
  "properties": {
    "addr:full":"298 Golf Dr Oceanside NY 11572",
    "addr:housenumber":"298",
    "addr:postcode":"11572",
    "addr:street":"Golf Dr",
    "iso:country":"US",
    "sg:address":"298 Golf Dr",
    "sg:city":"Oceanside",
    "sg:classifiers":[
        {
            "category":"Shopping",
            "subcategory":"Stationery & Office Supplies",
            "type":"Retail Goods"
        }
    ],
    "sg:phone":"+1   ",
    "sg:postcode":"11572",
    "sg:province":"NY",
    "wof:name":"Print Shop",
    "wof:placetype":"venue"
},
  "geometry": {"coordinates":[-73.62866099999999,40.626703],"type":"Point"}
}