{
  "type": "Feature",
  "properties": {
    "addr:full":"15 Ackert Hook Rd Rhinebeck NY 12572",
    "addr:housenumber":"15",
    "addr:postcode":"12572",
    "addr:street":"Ackert Hook Rd",
    "iso:country":"US",
    "sg:address":"15 Ackert Hook Rd",
    "sg:city":"Rhinebeck",
    "sg:classifiers":[
        {
            "category":"Home & Garden",
            "subcategory":"Hardware",
            "type":"Retail Goods"
        }
    ],
    "sg:phone":"+1 845 876 7841",
    "sg:postcode":"12572",
    "sg:province":"NY",
    "sg:tags":[
        "tool",
        "used"
    ],
    "wof:name":"A-1 Tool Repair",
    "wof:placetype":"venue"
},
  "geometry": {"coordinates":[-73.899823,41.910168],"type":"Point"}
}