{
  "type": "Feature",
  "properties": {
    "addr:full":"137 Rivington St New York NY 10002",
    "addr:housenumber":"137",
    "addr:postcode":"10002",
    "addr:street":"Rivington St",
    "iso:country":"US",
    "sg:address":"137 Rivington St",
    "sg:city":"New York",
    "sg:classifiers":[
        {
            "category":"Professional",
            "subcategory":"Accounting & Tax Preparation",
            "type":"Services"
        }
    ],
    "sg:phone":"+1 212 982 3829",
    "sg:postcode":"10002",
    "sg:province":"NY",
    "sg:tags":[
        "return",
        "filing"
    ],
    "wof:name":"Liberty Tax Svc",
    "wof:placetype":"venue"
},
  "geometry": {"coordinates":[-73.98621199999999,40.719378],"type":"Point"}
}