{
  "type": "Feature",
  "properties": {
    "addr:full":"6066 Cold Springs Rd Trumansburg NY 14886",
    "addr:housenumber":"6066",
    "addr:postcode":"14886",
    "addr:street":"Cold Springs Rd",
    "iso:country":"US",
    "sg:address":"6066 Cold Springs Rd",
    "sg:city":"Trumansburg",
    "sg:classifiers":[
        {
            "category":"Farming",
            "subcategory":"Livestock Farm",
            "type":"Manufacturing & Wholesale Goods"
        }
    ],
    "sg:phone":"+1 607 387 6022",
    "sg:postcode":"14886",
    "sg:province":"NY",
    "sg:tags":[
        "beef",
        "feedlot",
        "cattle"
    ],
    "wof:name":"Hillside Hereford Farm",
    "wof:placetype":"venue"
},
  "geometry": {"coordinates":[-76.65633699999999,42.51915],"type":"Point"}
}