{
  "type": "Feature",
  "properties": {
    "addr:full":"164 E 72nd St New York NY 10021",
    "addr:housenumber":"164",
    "addr:postcode":"10021",
    "addr:street":"E 72Nd St",
    "iso:country":"US",
    "sg:address":"164 E 72nd St",
    "sg:city":"New York",
    "sg:classifiers":[
        {
            "category":"Health Services",
            "subcategory":"Dentist",
            "type":"Services"
        }
    ],
    "sg:phone":"+1 212 288 5252",
    "sg:postcode":"10021",
    "sg:province":"NY",
    "wof:name":"Rubenstein Steven Dr",
    "wof:placetype":"venue"
},
  "geometry": {"coordinates":[-73.96162,40.770011],"type":"Point"}
}