{
  "type": "Feature",
  "properties": {
    "iso:country":"US",
    "sg:address":"164 E 72nd St",
    "sg:city":"New York",
    "sg:classifiers":[
        {
            "category":"Health Services",
            "subcategory":"Dentist",
            "type":"Services"
        }
    ],
    "sg:phone":"+1 212 288 5252",
    "sg:postcode":"10021",
    "sg:province":"NY",
    "wof:name":"Rubenstein Steven Dr",
    "wof:placetype":"venue"
},
  "geometry": {"coordinates":[-73.961502,40.7701],"type":"Point"}
}