{
  "type": "Feature",
  "properties": {
    "addr:full":"825 E Gate Blvd Garden City NY 11530",
    "addr:housenumber":"825",
    "addr:postcode":"11530",
    "addr:street":"E Gate Blvd",
    "iso:country":"US",
    "sg:address":"825 E Gate Blvd",
    "sg:city":"Garden City",
    "sg:classifiers":[
        {
            "category":"Professional",
            "type":"Services"
        }
    ],
    "sg:phone":"+1 516 794 9634",
    "sg:postcode":"11530",
    "sg:province":"NY",
    "sg:tags":[
        "establishment"
    ],
    "wof:name":"Pursino & Assocs",
    "wof:placetype":"venue"
},
  "geometry": {"coordinates":[-73.605892,40.740035],"type":"Point"}
}