{
  "type": "Feature",
  "properties": {
    "iso:country":"US",
    "sg:address":"4087 Johnson Rd",
    "sg:city":"Lockport",
    "sg:classifiers":[
        {
            "category":"Organizations",
            "subcategory":"Religious Organization",
            "type":"Services"
        }
    ],
    "sg:phone":"+1 716 433 2518",
    "sg:postcode":"14094",
    "sg:province":"NY",
    "sg:tags":[
        "church"
    ],
    "wof:name":"Church Of Jesus Christ Of Lds",
    "wof:placetype":"venue"
},
  "geometry": {"coordinates":[-78.729572,43.218847],"type":"Point"}
}