{
  "type": "Feature",
  "properties": {
    "addr:full":"965 E Main St Riverhead NY 11901",
    "addr:housenumber":"965",
    "addr:postcode":"11901",
    "addr:street":"E Main St",
    "iso:country":"US",
    "sg:address":"965 E Main St",
    "sg:city":"Riverhead",
    "sg:classifiers":[
        {
            "category":"Retail",
            "subcategory":"Auto Repair",
            "type":"Services"
        }
    ],
    "sg:phone":"+1 631 727 1074",
    "sg:postcode":"11901",
    "sg:province":"NY",
    "sg:tags":[
        "towing",
        "wrecker"
    ],
    "wof:name":"Jimmy's Jet Towing Inc",
    "wof:placetype":"venue"
},
  "geometry": {"coordinates":[-72.649191,40.925807],"type":"Point"}
}