{
  "type": "Feature",
  "properties": {
    "addr:full":"8 Nicole Ct Patchogue NY 11772",
    "addr:housenumber":"8",
    "addr:postcode":"11772",
    "addr:street":"Nicole Ct",
    "iso:country":"US",
    "sg:address":"8 Nicole Ct",
    "sg:city":"Patchogue",
    "sg:classifiers":[
        {
            "category":"Organizations",
            "subcategory":"Religious Organization",
            "type":"Services"
        }
    ],
    "sg:phone":"+1 631 289 3584",
    "sg:postcode":"11772",
    "sg:province":"NY",
    "sg:tags":[
        "clergy"
    ],
    "wof:name":"Denise Bishop",
    "wof:placetype":"venue"
},
  "geometry": {"coordinates":[-72.996977,40.789178],"type":"Point"}
}