{
  "type": "Feature",
  "properties": {
    "iso:country":"US",
    "sg:address":"124 Division Ave",
    "sg:city":"Salamanca",
    "sg:classifiers":[
        {
            "category":"Organizations",
            "subcategory":"Religious Organization",
            "type":"Services"
        }
    ],
    "sg:phone":"+1 716 945 1408",
    "sg:postcode":"14779",
    "sg:province":"NY",
    "sg:tags":[
        "clergy"
    ],
    "wof:name":"Joseph Lowry",
    "wof:placetype":"venue"
},
  "geometry": {"coordinates":[-78.72175,42.152653],"type":"Point"}
}