{
  "type": "Feature",
  "properties": {
    "iso:country":"US",
    "sg:address":"311 N Greeley Ave",
    "sg:city":"Chappaqua",
    "sg:classifiers":[
        {
            "category":"Wholesale",
            "subcategory":"Electrical",
            "type":"Manufacturing & Wholesale Goods"
        }
    ],
    "sg:phone":"+1 914 238 4439",
    "sg:postcode":"10514",
    "sg:province":"NY",
    "sg:tags":[
        "light",
        "tube",
        "bulb"
    ],
    "wof:name":"Hy & Sy Intl Inc",
    "wof:placetype":"venue"
},
  "geometry": {"coordinates":[-73.766201,41.167873],"type":"Point"}
}