{
  "type": "Feature",
  "properties": {
    "iso:country":"US",
    "sg:address":"138 W 2nd St",
    "sg:city":"Ronkonkoma",
    "sg:classifiers":[
        {
            "category":"Building & Trades",
            "subcategory":"Construction",
            "type":"Services"
        }
    ],
    "sg:phone":"+1 631 737 5677",
    "sg:postcode":"11779",
    "sg:province":"NY",
    "sg:tags":[
        "fire",
        "restoration",
        "damage"
    ],
    "sg:website":"www.whitegloverestoration.com",
    "wof:name":"White Glove Restoration Svc",
    "wof:placetype":"venue"
},
  "geometry": {"coordinates":[-73.13521900000001,40.826321],"type":"Point"}
}