{
  "type": "Feature",
  "properties": {
    "addr:full":"466 Main St Armonk NY 10504",
    "addr:housenumber":"466",
    "addr:postcode":"10504",
    "addr:street":"Main St",
    "iso:country":"US",
    "sg:address":"466 Main St",
    "sg:city":"Armonk",
    "sg:classifiers":[
        {
            "category":"Restaurant",
            "type":"Food & Drink"
        }
    ],
    "sg:phone":"+1   ",
    "sg:postcode":"10504",
    "sg:province":"NY",
    "sg:tags":[
        "eating"
    ],
    "wof:name":"Lucias",
    "wof:placetype":"venue"
},
  "geometry": {"coordinates":[-73.71307899999999,41.129202],"type":"Point"}
}