{
  "type": "Feature",
  "properties": {
    "iso:country":"US",
    "sg:address":"353 7th Ave",
    "sg:city":"Brooklyn",
    "sg:classifiers":[
        {
            "category":"Real Estate",
            "subcategory":"Real Estate Agent",
            "type":"Services"
        }
    ],
    "sg:phone":"+1 718 965 1155",
    "sg:postcode":"11215",
    "sg:province":"NY",
    "wof:name":"Steven Sommers Real Estate",
    "wof:placetype":"venue"
},
  "geometry": {"coordinates":[-73.982433,40.665787],"type":"Point"}
}