{
  "type": "Feature",
  "properties": {
    "iso:country":"US",
    "sg:address":"331 W 57th St",
    "sg:city":"Manhattan",
    "sg:classifiers":[
        {
            "category":"Freight",
            "type":"Transportation"
        },
        {
            "category":"Professional",
            "subcategory":"Printing & Photocopies",
            "type":"Services"
        }
    ],
    "sg:phone":"+1 212 489 8004",
    "sg:postcode":"10019",
    "sg:province":"NY",
    "sg:tags":[
        "shipping"
    ],
    "wof:name":"The UPS Store",
    "wof:placetype":"venue"
},
  "geometry": {"coordinates":[-73.984425,40.767379],"type":"Point"}
}