{
  "type": "Feature",
  "properties": {
    "addr:full":"7 Day St Fredonia NY 14063",
    "addr:housenumber":"7",
    "addr:postcode":"14063",
    "addr:street":"Day St",
    "iso:country":"US",
    "sg:address":"7 Day St",
    "sg:city":"Fredonia",
    "sg:classifiers":[
        {
            "category":"Organizations",
            "subcategory":"Religious Organization",
            "type":"Services"
        }
    ],
    "sg:phone":"+1 212 227 5191",
    "sg:postcode":"14063",
    "sg:province":"NY",
    "sg:tags":[
        "church"
    ],
    "sg:website":"www.mosaicmanhattan.com",
    "wof:name":"Mosaic Manhattan",
    "wof:placetype":"venue"
},
  "geometry": {"coordinates":[-79.331498,42.440742],"type":"Point"}
}