{
  "type": "Feature",
  "properties": {
    "addr:full":"9 Salem Ln South Salem NY 10590",
    "addr:housenumber":"9",
    "addr:postcode":"10590",
    "addr:street":"Salem Ln",
    "iso:country":"US",
    "sg:address":"9 Salem Ln",
    "sg:city":"South Salem",
    "sg:classifiers":[
        {
            "category":"Building & Trades",
            "subcategory":"Electrical",
            "type":"Services"
        }
    ],
    "sg:phone":"+1 914 763 5772",
    "sg:postcode":"10590",
    "sg:province":"NY",
    "sg:tags":[
        "electrical",
        "contractor"
    ],
    "wof:name":"Sam Gill Electric",
    "wof:placetype":"venue"
},
  "geometry": {"coordinates":[-73.548967,41.277923],"type":"Point"}
}