{
  "type": "Feature",
  "properties": {
    "addr:full":"1356 Broadway New York NY 10018",
    "addr:housenumber":"1356",
    "addr:postcode":"10018",
    "addr:street":"Broadway",
    "iso:country":"US",
    "sg:address":"1356 Broadway",
    "sg:city":"New York",
    "sg:classifiers":[
        {
            "category":"Banks & Credit Unions",
            "subcategory":"Bank",
            "type":"Services"
        }
    ],
    "sg:phone":"+1 718 522 0030",
    "sg:postcode":"10018",
    "sg:province":"NY",
    "sg:tags":[
        "state",
        "commercial"
    ],
    "wof:name":"Hsbc Bank USA National Assn",
    "wof:placetype":"venue"
},
  "geometry": {"coordinates":[-73.987442,40.751983],"type":"Point"}
}