{
  "type": "Feature",
  "properties": {
    "iso:country":"US",
    "sg:address":"1115 Flushing Ave",
    "sg:city":"Brooklyn",
    "sg:classifiers":[
        {
            "category":"Retail",
            "subcategory":"Auto Repair",
            "type":"Services"
        }
    ],
    "sg:phone":"+1 718 821 0300",
    "sg:postcode":"11237",
    "sg:province":"NY",
    "sg:tags":[
        "repairing",
        "automobile"
    ],
    "wof:name":"System Transmission",
    "wof:placetype":"venue"
},
  "geometry": {"coordinates":[-73.926948,40.705452],"type":"Point"}
}