{
  "type": "Feature",
  "properties": {
    "iso:country":"US",
    "sg:address":"1375 E 8th Street",
    "sg:city":"Brooklyn",
    "sg:classifiers":[
        {
            "category":"Health Services",
            "subcategory":"Dentist",
            "type":"Services"
        }
    ],
    "sg:phone":"+1 718 336 3229",
    "sg:postcode":"11230",
    "sg:province":"NY",
    "wof:name":"Nagelblatt Aaron DDS",
    "wof:placetype":"venue"
},
  "geometry": {"coordinates":[-73.96616899999999,40.615452],"type":"Point"}
}