{
  "type": "Feature",
  "properties": {
    "addr:full":"1347 49th St Brooklyn NY 11219",
    "addr:housenumber":"1347",
    "addr:postcode":"11219",
    "addr:street":"49Th St",
    "iso:country":"US",
    "sg:address":"1347 49th St",
    "sg:city":"Brooklyn",
    "sg:classifiers":[
        {
            "category":"Banks & Credit Unions",
            "subcategory":"Investment Brokerage",
            "type":"Services"
        }
    ],
    "sg:phone":"+1 718 851 7502",
    "sg:postcode":"11219",
    "sg:province":"NY",
    "sg:tags":[
        "security",
        "dealer"
    ],
    "wof:name":"Geldsahler J J & M",
    "wof:placetype":"venue"
},
  "geometry": {"coordinates":[-73.99065400000001,40.634379],"type":"Point"}
}