{
  "type": "Feature",
  "properties": {
    "addr:full":"366 Pearsall Ave Ste 1 Cedarhurst NY 11516",
    "addr:housenumber":"366",
    "addr:postcode":"11516",
    "addr:street":"Pearsall Ave Ste 1 Cedarhurst",
    "iso:country":"US",
    "sg:address":"366 Pearsall Ave Ste 1",
    "sg:city":"Cedarhurst",
    "sg:classifiers":[
        {
            "category":"Professional",
            "subcategory":"Lawyer & Legal Services",
            "type":"Services"
        }
    ],
    "sg:phone":"+1 516 596 6000",
    "sg:postcode":"11516",
    "sg:province":"NY",
    "wof:name":"Brick Marc Atty",
    "wof:placetype":"venue"
},
  "geometry": {"coordinates":[-73.729893,40.619937],"type":"Point"}
}