{
  "type": "Feature",
  "properties": {
    "iso:country":"US",
    "sg:address":"66 Cruikshank Ave",
    "sg:city":"Hempstead",
    "sg:classifiers":[
        {
            "category":"Building & Trades",
            "subcategory":"Construction",
            "type":"Services"
        }
    ],
    "sg:phone":"+1 516 565 0705",
    "sg:postcode":"11550",
    "sg:province":"NY",
    "sg:tags":[
        "contractor",
        "co",
        "carpentry"
    ],
    "wof:name":"J&R Construction",
    "wof:placetype":"venue"
},
  "geometry": {"coordinates":[-73.61942500000001,40.700577],"type":"Point"}
}