{
  "type": "Feature",
  "properties": {
    "iso:country":"US",
    "sg:address":"1161 Pleasant St",
    "sg:city":"Horseheads",
    "sg:classifiers":[
        {
            "category":"Manufacturing",
            "subcategory":"Apparel",
            "type":"Manufacturing & Wholesale Goods"
        }
    ],
    "sg:phone":"+1   ",
    "sg:postcode":"14845",
    "sg:province":"NY",
    "sg:tags":[
        "embroidery"
    ],
    "wof:name":"Unique Solution",
    "wof:placetype":"venue"
},
  "geometry": {"coordinates":[-76.816175,42.153776],"type":"Point"}
}