{
  "type": "Feature",
  "properties": {
    "addr:full":"156 Wendover Rd Rochester NY 14610",
    "addr:housenumber":"156",
    "addr:postcode":"14610",
    "addr:street":"Wendover Rd",
    "iso:country":"US",
    "sg:address":"156 Wendover Rd",
    "sg:city":"Rochester",
    "sg:classifiers":[
        {
            "category":"Building & Trades",
            "subcategory":"Landscaping Services",
            "type":"Services"
        }
    ],
    "sg:phone":"+1 585 482 8882",
    "sg:postcode":"14610",
    "sg:province":"NY",
    "sg:tags":[
        "tree"
    ],
    "wof:name":"Wendover Wholesale",
    "wof:placetype":"venue"
},
  "geometry": {"coordinates":[-77.53269400000001,43.145907],"type":"Point"}
}