{
  "type": "Feature",
  "properties": {
    "addr:full":"64 E 94 St New York NY 10128",
    "addr:housenumber":"64;94",
    "addr:postcode":"10128",
    "addr:street":"E;St",
    "iso:country":"US",
    "sg:address":"64 E 94 St",
    "sg:city":"New York",
    "sg:classifiers":[
        {
            "category":"Retail",
            "subcategory":"Auto Repair",
            "type":"Services"
        }
    ],
    "sg:phone":"+1 212 492 9490",
    "sg:postcode":"10128",
    "sg:province":"NY",
    "sg:tags":[
        "wrecker"
    ],
    "wof:name":"24 Hour A Day Towing",
    "wof:placetype":"venue"
},
  "geometry": {"coordinates":[-73.954044,40.785462],"type":"Point"}
}