{
  "type": "Feature",
  "properties": {
    "addr:full":"1498 3rd Ave New York NY 10028",
    "addr:housenumber":"1498",
    "addr:postcode":"10028",
    "addr:street":"3Rd Ave",
    "iso:country":"US",
    "sg:address":"1498 3rd Ave",
    "sg:city":"New York",
    "sg:classifiers":[
        {
            "category":"Personal",
            "subcategory":"Massage",
            "type":"Services"
        },
        {
            "category":"Health Services",
            "subcategory":"Health Practitioner",
            "type":"Services"
        }
    ],
    "sg:phone":"+1 212 288 9588",
    "sg:postcode":"10028",
    "sg:province":"NY",
    "sg:tags":[
        "acupuncture"
    ],
    "wof:name":"Kings Well Inc",
    "wof:placetype":"venue"
},
  "geometry": {"coordinates":[-73.954871,40.77786],"type":"Point"}
}