{
  "type": "Feature",
  "properties": {
    "addr:full":"167 E 87 St New York NY 10128",
    "addr:housenumber":"167;87",
    "addr:postcode":"10128",
    "addr:street":"E;St",
    "iso:country":"US",
    "sg:address":"167 E 87 St",
    "sg:city":"New York",
    "sg:classifiers":[
        {
            "category":"Banks & Credit Unions",
            "subcategory":"Bank",
            "type":"Services"
        }
    ],
    "sg:phone":"+1 212 876 5040",
    "sg:postcode":"10128",
    "sg:province":"NY",
    "sg:tags":[
        "cashing",
        "check"
    ],
    "wof:name":"Karbill Check Cashing",
    "wof:placetype":"venue"
},
  "geometry": {"coordinates":[-73.95392099999999,40.779821],"type":"Point"}
}