{
  "type": "Feature",
  "properties": {
    "addr:full":"194 Court Street Brooklyn NY 11201",
    "addr:housenumber":"194",
    "addr:postcode":"11201",
    "addr:street":"Court Street",
    "iso:country":"US",
    "sg:address":"194 Court Street",
    "sg:city":"Brooklyn",
    "sg:classifiers":[
        {
            "category":"Personal",
            "subcategory":"Barber",
            "type":"Services"
        }
    ],
    "sg:phone":"+1 718 643 3930",
    "sg:postcode":"11201",
    "sg:province":"NY",
    "wof:name":"David Today Style",
    "wof:placetype":"venue"
},
  "geometry": {"coordinates":[-73.99352399999999,40.687303],"type":"Point"}
}