{
  "type": "Feature",
  "properties": {
    "iso:country":"US",
    "sg:address":"25 S Cliff Manor Dr",
    "sg:city":"Plattsburgh",
    "sg:classifiers":[
        {
            "category":"Professional",
            "subcategory":"Detective & Security Services",
            "type":"Services"
        }
    ],
    "sg:phone":"+1 518 562 1968",
    "sg:postcode":"12901",
    "sg:province":"NY",
    "sg:tags":[
        "information",
        "bureau"
    ],
    "wof:name":"Robert Christopher Cioffi",
    "wof:placetype":"venue"
},
  "geometry": {"coordinates":[-73.444705,44.651598],"type":"Point"}
}