{
  "type": "Feature",
  "properties": {
    "addr:full":"5586 Main St Buffalo NY 14221",
    "addr:housenumber":"5586",
    "addr:postcode":"14221",
    "addr:street":"Main St",
    "iso:country":"US",
    "sg:address":"5586 Main St",
    "sg:city":"Buffalo",
    "sg:classifiers":[
        {
            "category":"Building & Trades",
            "subcategory":"Construction",
            "type":"Services"
        }
    ],
    "sg:phone":"+1 716 634 0188",
    "sg:postcode":"14221",
    "sg:province":"NY",
    "sg:tags":[
        "contractor"
    ],
    "sg:website":"www.plastics.saint-gobain.com",
    "wof:name":"Saint-Gobain Performance Plstc",
    "wof:placetype":"venue"
},
  "geometry": {"coordinates":[-78.74585999999999,42.962668],"type":"Point"}
}