{
  "type": "Feature",
  "properties": {
    "addr:full":"1460 Rockaway Parkway Brooklyn NY 11236",
    "addr:housenumber":"1460",
    "addr:postcode":"11236",
    "addr:street":"Rockaway Parkway",
    "iso:country":"US",
    "sg:address":"1460 Rockaway Parkway",
    "sg:city":"Brooklyn",
    "sg:classifiers":[
        {
            "category":"Restaurant",
            "type":"Food & Drink"
        }
    ],
    "sg:phone":"+1 718 257 3610",
    "sg:postcode":"11236",
    "sg:province":"NY",
    "wof:name":"New Food King",
    "wof:placetype":"venue"
},
  "geometry": {"coordinates":[-73.901777,40.644474],"type":"Point"}
}