{
  "type": "Feature",
  "properties": {
    "addr:full":"365 1 Ave New York NY 10010",
    "addr:housenumber":"365",
    "addr:postcode":"10010",
    "addr:street":"1 Ave",
    "iso:country":"US",
    "sg:address":"365 1 Ave",
    "sg:city":"New York",
    "sg:classifiers":[
        {
            "category":"Retail",
            "subcategory":"Portrait Studio",
            "type":"Services"
        }
    ],
    "sg:phone":"+1 212 598 4191",
    "sg:postcode":"10010",
    "sg:province":"NY",
    "sg:tags":[
        "photographer",
        "commercial"
    ],
    "wof:name":"Daniel Aubry Photography",
    "wof:placetype":"venue"
},
  "geometry": {"coordinates":[-73.979557,40.735417],"type":"Point"}
}