{
  "type": "Feature",
  "properties": {
    "iso:country":"US",
    "sg:address":"400 Hart St",
    "sg:city":"Brooklyn",
    "sg:classifiers":[
        {
            "category":"Social Services",
            "type":"Services"
        }
    ],
    "sg:phone":"+1 718 452 7474",
    "sg:postcode":"11206",
    "sg:province":"NY",
    "wof:name":"Maria Lawton Sr Ctr",
    "wof:placetype":"venue"
},
  "geometry": {"coordinates":[-73.936194,40.694476],"type":"Point"}
}