{
  "type": "Feature",
  "properties": {
    "iso:country":"US",
    "sg:address":"8 Pine Tree Pl",
    "sg:city":"Clifton Park",
    "sg:classifiers":[
        {
            "category":"Manufacturing",
            "subcategory":"Tools & Machinery",
            "type":"Manufacturing & Wholesale Goods"
        }
    ],
    "sg:phone":"+1   ",
    "sg:postcode":"12065",
    "sg:province":"NY",
    "sg:tags":[
        "engine",
        "internal",
        "combustion",
        "mfg"
    ],
    "wof:name":"Robert Keiper",
    "wof:placetype":"venue"
},
  "geometry": {"coordinates":[-73.782718,42.845735],"type":"Point"}
}