{
  "type": "Feature",
  "properties": {
    "addr:full":"3533 Bruckner Blvd Bronx NY 10461",
    "addr:housenumber":"3533",
    "addr:postcode":"10461",
    "addr:street":"Bruckner Blvd",
    "iso:country":"US",
    "sg:address":"3533 Bruckner Blvd",
    "sg:city":"Bronx",
    "sg:classifiers":[
        {
            "category":"Professional",
            "subcategory":"Lawyer & Legal Services",
            "type":"Services"
        }
    ],
    "sg:phone":"+1 718 292 4124",
    "sg:postcode":"10461",
    "sg:province":"NY",
    "sg:tags":[
        "attorney"
    ],
    "wof:name":"Louis A Garcia",
    "wof:placetype":"venue"
},
  "geometry": {"coordinates":[-73.827442,40.847319],"type":"Point"}
}