{
  "type": "Feature",
  "properties": {
    "addr:full":"108 Prospect Park W Brooklyn NY 11215",
    "addr:housenumber":"108",
    "addr:postcode":"11215",
    "addr:street":"Prospect Park W",
    "iso:country":"US",
    "sg:address":"108 Prospect Park W",
    "sg:city":"Brooklyn",
    "sg:classifiers":[
        {
            "category":"Health Services",
            "subcategory":"Doctor",
            "type":"Services"
        }
    ],
    "sg:phone":"+1 718 499 5300",
    "sg:postcode":"11215",
    "sg:province":"NY",
    "sg:tags":[
        "physician",
        "surgeon"
    ],
    "wof:name":"David R Schifter MD",
    "wof:placetype":"venue"
},
  "geometry": {"coordinates":[-73.974834,40.667021],"type":"Point"}
}