{
  "type": "Feature",
  "properties": {
    "iso:country":"US",
    "sg:address":"38 Kenneth Rd",
    "sg:city":"Hartsdale",
    "sg:classifiers":[
        {
            "category":"Shopping",
            "type":"Retail Goods"
        }
    ],
    "sg:phone":"+1   ",
    "sg:postcode":"10530",
    "sg:province":"NY",
    "sg:tags":[
        "merchandise"
    ],
    "wof:name":"Diamond Donna Hope Gallery",
    "wof:placetype":"venue"
},
  "geometry": {"coordinates":[-73.832379,41.023424],"type":"Point"}
}