{
  "type": "Feature",
  "properties": {
    "addr:full":"1112 Longwood Avenue Bronx NY 10474",
    "addr:housenumber":"1112",
    "addr:postcode":"10474",
    "addr:street":"Longwood Avenue",
    "iso:country":"US",
    "sg:address":"1112 Longwood Avenue",
    "sg:city":"Bronx",
    "sg:classifiers":[
        {
            "category":"Communications",
            "type":"Services"
        }
    ],
    "sg:phone":"+1 718 893 8800",
    "sg:postcode":"10474",
    "sg:province":"NY",
    "sg:tags":[
        "web",
        "design"
    ],
    "wof:name":"My Angel Enterprise Corporation",
    "wof:placetype":"venue"
},
  "geometry": {"coordinates":[-73.893631,40.81463],"type":"Point"}
}