{
  "type": "Feature",
  "properties": {
    "iso:country":"US",
    "sg:address":"Haven Plaza 188 Avenue C",
    "sg:city":"New York",
    "sg:classifiers":[
        {
            "category":"Personal",
            "type":"Services"
        }
    ],
    "sg:phone":"+1 646 373 6561",
    "sg:postcode":"10009",
    "sg:province":"NY",
    "sg:tags":[
        "home"
    ],
    "sg:website":"www.blindsshadesshelves.com",
    "wof:name":"Blinds, Shades & Shelves",
    "wof:placetype":"venue"
},
  "geometry": {"coordinates":[-73.97569799999999,40.727107],"type":"Point"}
}