{
  "type": "Feature",
  "properties": {
    "iso:country":"US",
    "sg:address":"101 Maiden Ln",
    "sg:city":"New York",
    "sg:classifiers":[
        {
            "category":"Wholesale",
            "subcategory":"Groceries",
            "type":"Manufacturing & Wholesale Goods"
        }
    ],
    "sg:phone":"+1 212 344 7545",
    "sg:postcode":"10038",
    "sg:province":"NY",
    "sg:tags":[
        "tea",
        "coffee"
    ],
    "wof:name":"Fallar Co",
    "wof:placetype":"venue"
},
  "geometry": {"coordinates":[-74.007009,40.707048],"type":"Point"}
}