{
  "type": "Feature",
  "properties": {
    "iso:country":"US",
    "sg:address":"1322 54th St",
    "sg:city":"Brooklyn",
    "sg:classifiers":[
        {
            "category":"Shopping",
            "subcategory":"Clothing, Apparel, & Fashions",
            "type":"Retail Goods"
        }
    ],
    "sg:phone":"+1 718 853 4546",
    "sg:postcode":"11219",
    "sg:province":"NY",
    "sg:tags":[
        "tailor"
    ],
    "wof:name":"Expert Dress Making & Tailor",
    "wof:placetype":"venue"
},
  "geometry": {"coordinates":[-73.993613,40.631426],"type":"Point"}
}