{
  "type": "Feature",
  "properties": {
    "addr:full":"120 Boyd Dr Rochester NY 14616",
    "addr:housenumber":"120",
    "addr:postcode":"14616",
    "addr:street":"Boyd Dr",
    "iso:country":"US",
    "sg:address":"120 Boyd Dr",
    "sg:city":"Rochester",
    "sg:classifiers":[
        {
            "category":"Professional",
            "type":"Services"
        }
    ],
    "sg:phone":"+1 585 703 4174",
    "sg:postcode":"14616",
    "sg:province":"NY",
    "sg:tags":[
        "establishment"
    ],
    "wof:name":"P C Central",
    "wof:placetype":"venue"
},
  "geometry": {"coordinates":[-77.649244,43.221138],"type":"Point"}
}