{
  "type": "Feature",
  "properties": {
    "addr:full":"2934 Ave X Brooklyn NY 11235",
    "addr:housenumber":"2934",
    "addr:postcode":"11235",
    "addr:street":"Ave X",
    "iso:country":"US",
    "sg:address":"2934 Ave X",
    "sg:city":"Brooklyn",
    "sg:classifiers":[
        {
            "category":"Government",
            "subcategory":"Post Office",
            "type":"Public Place"
        }
    ],
    "sg:phone":"+1   ",
    "sg:postcode":"11235",
    "sg:province":"NY",
    "sg:tags":[
        "postal",
        "us"
    ],
    "wof:name":"Nostrand Finance Station",
    "wof:placetype":"venue"
},
  "geometry": {"coordinates":[-73.93983,40.593817],"type":"Point"}
}