{
  "type": "Feature",
  "properties": {
    "iso:country":"US",
    "sg:address":"92 Old Rte 9",
    "sg:city":"Wappingers Falls",
    "sg:classifiers":[
        {
            "category":"Professional",
            "subcategory":"Lawyer & Legal Services",
            "type":"Services"
        }
    ],
    "sg:phone":"+1 845 297 0600",
    "sg:postcode":"12590",
    "sg:province":"NY",
    "sg:tags":[
        "attorney"
    ],
    "wof:name":"Gregory D Supple",
    "wof:placetype":"venue"
},
  "geometry": {"coordinates":[-73.909485,41.57919],"type":"Point"}
}