{
  "type": "Feature",
  "properties": {
    "iso:country":"US",
    "sg:address":"7 Hanover Sq",
    "sg:city":"New York",
    "sg:classifiers":[
        {
            "category":"Insurance",
            "subcategory":"Life Insurance",
            "type":"Services"
        }
    ],
    "sg:phone":"+1 212 598 8000",
    "sg:postcode":"10004",
    "sg:province":"NY",
    "sg:website":"www.glic.com",
    "wof:name":"Guardian Life Ins Co-America",
    "wof:placetype":"venue"
},
  "geometry": {"coordinates":[-74.009479,40.704672],"type":"Point"}
}