{
  "type": "Feature",
  "properties": {
    "iso:country":"US",
    "sg:address":"116 Winthrop St",
    "sg:city":"Brooklyn",
    "sg:classifiers":[
        {
            "category":"Real Estate",
            "subcategory":"Real Estate Agent",
            "type":"Services"
        }
    ],
    "sg:phone":"+1 718 469 1771",
    "sg:postcode":"11225",
    "sg:province":"NY",
    "wof:name":"Peach Realty LLC",
    "wof:placetype":"venue"
},
  "geometry": {"coordinates":[-73.95328499999999,40.656828],"type":"Point"}
}