{
  "type": "Feature",
  "properties": {
    "addr:full":"584 North Ave New Rochelle NY 10801",
    "addr:housenumber":"584",
    "addr:postcode":"10801",
    "addr:street":"North Ave",
    "iso:country":"US",
    "sg:address":"584 North Ave",
    "sg:city":"New Rochelle",
    "sg:classifiers":[
        {
            "category":"Personal",
            "subcategory":"Beauty Salon",
            "type":"Services"
        }
    ],
    "sg:phone":"+1   ",
    "sg:postcode":"10801",
    "sg:province":"NY",
    "sg:tags":[
        "shop"
    ],
    "wof:name":"Hair Design With You In Mind",
    "wof:placetype":"venue"
},
  "geometry": {"coordinates":[-73.787914,40.922991],"type":"Point"}
}