{
  "type": "Feature",
  "properties": {
    "addr:full":"6 Majorca Ln Clifton Park NY 12065",
    "addr:housenumber":"6",
    "addr:postcode":"12065",
    "addr:street":"Majorca Ln",
    "iso:country":"US",
    "sg:address":"6 Majorca Ln",
    "sg:city":"Clifton Park",
    "sg:classifiers":[
        {
            "category":"Building & Trades",
            "subcategory":"Landscaping Services",
            "type":"Services"
        }
    ],
    "sg:phone":"+1 518 383 0423",
    "sg:postcode":"12065",
    "sg:province":"NY",
    "wof:name":"Clifton Park Lawn Care",
    "wof:placetype":"venue"
},
  "geometry": {"coordinates":[-73.795118,42.848099],"type":"Point"}
}