{
  "type": "Feature",
  "properties": {
    "addr:full":"2503 Vestal Pkwy E Vestal NY 13850",
    "addr:housenumber":"2503",
    "addr:postcode":"13850",
    "addr:street":"Vestal Pkwy E",
    "iso:country":"US",
    "sg:address":"2503 Vestal Pkwy E",
    "sg:city":"Vestal",
    "sg:classifiers":[
        {
            "category":"Restaurant",
            "type":"Food & Drink"
        }
    ],
    "sg:menulink":"http://www.allmenus.com/ny/vestal/68293-uno-chicago-grill/menu/",
    "sg:phone":"+1 607 770 7000",
    "sg:postcode":"13850",
    "sg:province":"NY",
    "sg:tags":[
        "american",
        "italian",
        "pizza"
    ],
    "wof:name":"Uno Chicago Grill",
    "wof:placetype":"venue"
},
  "geometry": {"coordinates":[-76.008728,42.095051],"type":"Point"}
}