{
  "type": "Feature",
  "properties": {
    "addr:full":"122E W 42nd St New York NY 10036",
    "addr:housenumber":"122e",
    "addr:postcode":"10036",
    "addr:street":"W 42Nd St",
    "iso:country":"US",
    "sg:address":"122E W 42nd St",
    "sg:city":"New York",
    "sg:classifiers":[
        {
            "category":"Professional",
            "subcategory":"Lawyer & Legal Services",
            "type":"Services"
        }
    ],
    "sg:phone":"+1 212 808 8008",
    "sg:postcode":"10036",
    "sg:province":"NY",
    "sg:tags":[
        "personal",
        "injury"
    ],
    "wof:name":"Brand Brand & Burke",
    "wof:placetype":"venue"
},
  "geometry": {"coordinates":[-73.984596,40.755199],"type":"Point"}
}