{
  "type": "Feature",
  "properties": {
    "iso:country":"US",
    "sg:address":"94 McClean Ave",
    "sg:city":"Staten Island",
    "sg:classifiers":[
        {
            "category":"Insurance",
            "subcategory":"Insurance Agent",
            "type":"Services"
        }
    ],
    "sg:phone":"+1 718 815 5200",
    "sg:postcode":"10305",
    "sg:province":"NY",
    "wof:name":"Allstates Sales Office",
    "wof:placetype":"venue"
},
  "geometry": {"coordinates":[-74.064128,40.598842],"type":"Point"}
}