{
  "type": "Feature",
  "properties": {
    "addr:full":"3149 Coney Island Avenue Brooklyn NY 11235",
    "addr:housenumber":"3149",
    "addr:postcode":"11235",
    "addr:street":"Coney Island Avenue",
    "iso:country":"US",
    "sg:address":"3149 Coney Island Avenue",
    "sg:city":"Brooklyn",
    "sg:classifiers":[
        {
            "category":"Restaurant",
            "type":"Food & Drink"
        }
    ],
    "sg:phone":"+1 718 332 8100",
    "sg:postcode":"11235",
    "sg:province":"NY",
    "wof:name":"Pak Nashamen Restaurant",
    "wof:placetype":"venue"
},
  "geometry": {"coordinates":[-73.959586,40.5792],"type":"Point"}
}