{
  "type": "Feature",
  "properties": {
    "addr:full":"19 Woodcliffe Ter Buffalo NY 14215",
    "addr:housenumber":"19",
    "addr:postcode":"14215",
    "addr:street":"Woodcliffe Ter",
    "iso:country":"US",
    "sg:address":"19 Woodcliffe Ter",
    "sg:city":"Buffalo",
    "sg:classifiers":[
        {
            "category":"Organizations",
            "subcategory":"Community Association",
            "type":"Services"
        }
    ],
    "sg:phone":"+1   ",
    "sg:postcode":"14215",
    "sg:province":"NY",
    "wof:name":"Town Park Homeowners Assn",
    "wof:placetype":"venue"
},
  "geometry": {"coordinates":[-78.78442800000001,42.943989],"type":"Point"}
}