{
  "type": "Feature",
  "properties": {
    "iso:country":"US",
    "sg:address":"351 S Broadway",
    "sg:city":"Yonkers",
    "sg:classifiers":[
        {
            "category":"Restaurant",
            "type":"Food & Drink"
        }
    ],
    "sg:phone":"+1 914 476 2000",
    "sg:postcode":"10705",
    "sg:province":"NY",
    "sg:tags":[
        "pizza",
        "italian"
    ],
    "wof:name":"Silvio's Italian Restaurant",
    "wof:placetype":"venue"
},
  "geometry": {"coordinates":[-73.89599200000001,40.921402],"type":"Point"}
}