{
  "type": "Feature",
  "properties": {
    "addr:full":"1077 Gravel Rd Webster NY 14580",
    "addr:housenumber":"1077",
    "addr:postcode":"14580",
    "addr:street":"Gravel Rd",
    "iso:country":"US",
    "sg:address":"1077 Gravel Rd",
    "sg:city":"Webster",
    "sg:classifiers":[
        {
            "category":"Personal",
            "subcategory":"Beauty Salon",
            "type":"Services"
        }
    ],
    "sg:phone":"+1 585 671 8100",
    "sg:postcode":"14580",
    "sg:province":"NY",
    "wof:name":"Sophisticut Hair Studio",
    "wof:placetype":"venue"
},
  "geometry": {"coordinates":[-77.498114,43.201214],"type":"Point"}
}