{
  "type": "Feature",
  "properties": {
    "iso:country":"US",
    "sg:address":"5 Old Shore Rd",
    "sg:city":"Port Washington",
    "sg:classifiers":[
        {
            "category":"Restaurant",
            "type":"Food & Drink"
        }
    ],
    "sg:menulink":"http://www.allmenus.com/ny/port-washington/170027-burger-king/menu/",
    "sg:phone":"+1 516 883 8673",
    "sg:postcode":"11050",
    "sg:province":"NY",
    "sg:tags":[
        "burger",
        "american"
    ],
    "wof:name":"Burger King",
    "wof:placetype":"venue"
},
  "geometry": {"coordinates":[-73.70348300000001,40.838347],"type":"Point"}
}