{
  "type": "Feature",
  "properties": {
    "addr:full":"10 Ohio Pl Middletown NY 10940",
    "addr:housenumber":"10",
    "addr:postcode":"10940",
    "addr:street":"Ohio Pl",
    "iso:country":"US",
    "sg:address":"10 Ohio Pl",
    "sg:city":"Middletown",
    "sg:classifiers":[
        {
            "category":"Government",
            "subcategory":"Fire Station",
            "type":"Public Place"
        }
    ],
    "sg:phone":"+1 845 343 2285",
    "sg:postcode":"10940",
    "sg:province":"NY",
    "sg:tags":[
        "department"
    ],
    "wof:name":"Washington Heights Fire Dist",
    "wof:placetype":"venue"
},
  "geometry": {"coordinates":[-74.41383999999999,41.469276],"type":"Point"}
}