{
  "type": "Feature",
  "properties": {
    "iso:country":"US",
    "sg:address":"25 Roslyn Rd",
    "sg:city":"Mineola",
    "sg:classifiers":[
        {
            "category":"Building & Trades",
            "subcategory":"Electrical",
            "type":"Services"
        }
    ],
    "sg:phone":"+1 516 359 5197",
    "sg:postcode":"11501",
    "sg:province":"NY",
    "sg:tags":[
        "electric",
        "contractor"
    ],
    "wof:name":"Local 118 Electrical Prdctn",
    "wof:placetype":"venue"
},
  "geometry": {"coordinates":[-73.633994,40.741395],"type":"Point"}
}