{
  "type": "Feature",
  "properties": {
    "iso:country":"US",
    "sg:address":"811 W Merrick Rd",
    "sg:city":"Valley Stream",
    "sg:classifiers":[
        {
            "category":"Organizations",
            "subcategory":"Religious Organization",
            "type":"Services"
        }
    ],
    "sg:phone":"+1 516 285 0375",
    "sg:postcode":"11580",
    "sg:province":"NY",
    "sg:website":"www.calvaryfaithtabernacle.com",
    "wof:name":"Calvary Faith Tabernacle",
    "wof:placetype":"venue"
},
  "geometry": {"coordinates":[-73.725273,40.67369],"type":"Point"}
}