{
  "type": "Feature",
  "properties": {
    "iso:country":"US",
    "sg:address":"399 Turkey Hill Rd",
    "sg:city":"Ithaca",
    "sg:classifiers":[
        {
            "category":"Education",
            "subcategory":"School",
            "type":"Public Place"
        }
    ],
    "sg:phone":"+1 607 273 5184",
    "sg:postcode":"14850",
    "sg:province":"NY",
    "wof:name":"Stone Circle School",
    "wof:placetype":"venue"
},
  "geometry": {"coordinates":[-76.428039,42.430781],"type":"Point"}
}