{
  "type": "Feature",
  "properties": {
    "iso:country":"US",
    "sg:address":"10926 130th Street",
    "sg:city":"South Ozone Park",
    "sg:classifiers":[
        {
            "category":"Organizations",
            "subcategory":"Religious Organization",
            "type":"Services"
        }
    ],
    "sg:phone":"+1 718 641 5710",
    "sg:postcode":"11420",
    "sg:province":"NY",
    "wof:name":"Religious Education Office-St Teresa of Avila Roman Catholic Chu",
    "wof:placetype":"venue"
},
  "geometry": {"coordinates":[-73.813063,40.684237],"type":"Point"}
}