{
  "type": "Feature",
  "properties": {
    "addr:full":"2055 Sackett Rd Avon NY 14414",
    "addr:housenumber":"2055",
    "addr:postcode":"14414",
    "addr:street":"Sackett Rd",
    "iso:country":"US",
    "sg:address":"2055 Sackett Rd",
    "sg:city":"Avon",
    "sg:classifiers":[
        {
            "category":"Professional",
            "subcategory":"Business Services",
            "type":"Services"
        }
    ],
    "sg:phone":"+1   ",
    "sg:postcode":"14414",
    "sg:province":"NY",
    "wof:name":"Conesus Creek River Rocks",
    "wof:placetype":"venue"
},
  "geometry": {"coordinates":[-77.7589,42.899427],"type":"Point"}
}