{
  "type": "Feature",
  "properties": {
    "addr:full":"213 E Broadway New York NY 10002",
    "addr:housenumber":"213",
    "addr:postcode":"10002",
    "addr:street":"E Broadway",
    "iso:country":"US",
    "sg:address":"213 E Broadway",
    "sg:city":"New York",
    "sg:classifiers":[
        {
            "category":"Restaurant",
            "type":"Food & Drink"
        }
    ],
    "sg:phone":"+1   ",
    "sg:postcode":"10002",
    "sg:province":"NY",
    "sg:tags":[
        "eating"
    ],
    "wof:name":"Herley Ch Corp",
    "wof:placetype":"venue"
},
  "geometry": {"coordinates":[-73.988072,40.714137],"type":"Point"}
}