{
  "type": "Feature",
  "properties": {
    "addr:full":"140 Shepherd St Rockville Centre NY 11570",
    "addr:housenumber":"140",
    "addr:postcode":"11570",
    "addr:street":"Shepherd St",
    "iso:country":"US",
    "sg:address":"140 Shepherd St",
    "sg:city":"Rockville Centre",
    "sg:classifiers":[
        {
            "category":"Utilities",
            "subcategory":"Cable",
            "type":"Services"
        }
    ],
    "sg:phone":"+1 516 594 2188",
    "sg:postcode":"11570",
    "sg:province":"NY",
    "sg:tags":[
        "satellite"
    ],
    "wof:name":"DIRECTV",
    "wof:placetype":"venue"
},
  "geometry": {"coordinates":[-73.622873,40.66696],"type":"Point"}
}