{
  "type": "Feature",
  "properties": {
    "iso:country":"US",
    "sg:address":"64 E Main St",
    "sg:city":"Arcade",
    "sg:classifiers":[
        {
            "category":"Autos & Motor Vehicles",
            "subcategory":"Fuel & Gas Station",
            "type":"Retail Goods"
        }
    ],
    "sg:phone":"+1 585 492 0552",
    "sg:postcode":"14009",
    "sg:province":"NY",
    "wof:name":"Michael R Doster",
    "wof:placetype":"venue"
},
  "geometry": {"coordinates":[-78.414647,42.535019],"type":"Point"}
}