{
  "type": "Feature",
  "properties": {
    "iso:country":"US",
    "sg:address":"Seaman Ave",
    "sg:city":"New York",
    "sg:classifiers":[
        {
            "category":"Park",
            "type":"Public Place"
        }
    ],
    "sg:postcode":"10034",
    "sg:province":"NY",
    "wof:name":"Inwood Hill Park",
    "wof:placetype":"venue"
},
  "geometry": {"coordinates":[-73.9235,40.868698],"type":"Point"}
}