{
  "type": "Feature",
  "properties": {
    "iso:country":"US",
    "sg:address":"4112 W Genesee St",
    "sg:city":"Syracuse",
    "sg:classifiers":[
        {
            "category":"Personal",
            "subcategory":"Beauty Salon",
            "type":"Services"
        }
    ],
    "sg:phone":"+1 315 487 7752",
    "sg:postcode":"13219",
    "sg:province":"NY",
    "wof:name":"Hair & Body Experience",
    "wof:placetype":"venue"
},
  "geometry": {"coordinates":[-76.243467,43.045963],"type":"Point"}
}