{
  "type": "Feature",
  "properties": {
    "addr:full":"30-44 29th St Ste 1D Astoria NY 11102",
    "addr:housenumber":"30-44",
    "addr:postcode":"11102",
    "addr:street":"29Th St Ste 1D",
    "iso:country":"US",
    "sg:address":"30-44 29th St Ste 1D",
    "sg:city":"Astoria",
    "sg:classifiers":[
        {
            "category":"Health Services",
            "subcategory":"Doctor",
            "type":"Services"
        },
        {
            "category":"Health Services",
            "subcategory":"Dentist",
            "type":"Services"
        }
    ],
    "sg:phone":"+1 718 545 7770",
    "sg:postcode":"11102",
    "sg:province":"NY",
    "sg:tags":[
        "surgeon",
        "oral",
        "endodontist"
    ],
    "sg:website":"www.endodontistnyc.com",
    "wof:name":"Cezar M Mitrut, DMD",
    "wof:placetype":"venue"
},
  "geometry": {"coordinates":[-73.923931,40.766516],"type":"Point"}
}