{
  "type": "Feature",
  "properties": {
    "iso:country":"US",
    "sg:address":"145 Mineola Blvd",
    "sg:city":"Mineola",
    "sg:classifiers":[
        {
            "category":"Manufacturing",
            "subcategory":"Printing",
            "type":"Manufacturing & Wholesale Goods"
        }
    ],
    "sg:phone":"+1 516 334 4410",
    "sg:postcode":"11501",
    "sg:province":"NY",
    "sg:tags":[
        "printer"
    ],
    "wof:name":"Caliber Printing",
    "wof:placetype":"venue"
},
  "geometry": {"coordinates":[-73.64078499999999,40.742491],"type":"Point"}
}