{
  "type": "Feature",
  "properties": {
    "addr:full":"333 Meacham Ave Elmont NY 11003",
    "addr:housenumber":"333",
    "addr:postcode":"11003",
    "addr:street":"Meacham Ave",
    "iso:country":"US",
    "sg:address":"333 Meacham Ave",
    "sg:city":"Elmont",
    "sg:classifiers":[
        {
            "category":"Health Services",
            "subcategory":"Chiropractor",
            "type":"Services"
        }
    ],
    "sg:phone":"+1 516 358 0902",
    "sg:postcode":"11003",
    "sg:province":"NY",
    "wof:name":"Thoden Pierre PC",
    "wof:placetype":"venue"
},
  "geometry": {"coordinates":[-73.69059799999999,40.700401],"type":"Point"}
}