{
  "type": "Feature",
  "properties": {
    "addr:full":"594 Grand Concourse Bronx NY 10451",
    "addr:housenumber":"594",
    "addr:postcode":"10451",
    "addr:street":"Grand Concourse",
    "iso:country":"US",
    "sg:address":"594 Grand Concourse",
    "sg:city":"Bronx",
    "sg:classifiers":[
        {
            "category":"Restaurant",
            "type":"Food & Drink"
        }
    ],
    "sg:menulink":"http://www.allmenus.com/ny/bronx/59238-great-wall/menu/",
    "sg:phone":"+1 718 993 5420",
    "sg:postcode":"10451",
    "sg:province":"NY",
    "sg:tags":[
        "asian",
        "chinese"
    ],
    "wof:name":"Great Wall",
    "wof:placetype":"venue"
},
  "geometry": {"coordinates":[-73.926708,40.819669],"type":"Point"}
}