{
  "type": "Feature",
  "properties": {
    "addr:full":"3 Mickey Ct Huntington Station NY 11746",
    "addr:housenumber":"3",
    "addr:postcode":"11746",
    "addr:street":"Mickey Ct Huntington",
    "iso:country":"US",
    "sg:address":"3 Mickey Ct",
    "sg:city":"Huntington Station",
    "sg:classifiers":[
        {
            "category":"Local Transit",
            "type":"Transportation"
        }
    ],
    "sg:phone":"+1 631 549 9050",
    "sg:postcode":"11746",
    "sg:province":"NY",
    "sg:tags":[
        "limousine",
        "limo"
    ],
    "wof:name":"Patricia Ann's Limousine Svce",
    "wof:placetype":"venue"
},
  "geometry": {"coordinates":[-73.38490299999999,40.8447],"type":"Point"}
}