{
  "type": "Feature",
  "properties": {
    "addr:full":"15 Mount Sinai Ave Mt Sinai NY 11766",
    "addr:housenumber":"15",
    "addr:postcode":"11766",
    "addr:street":"Mount Sinai Ave",
    "iso:country":"US",
    "sg:address":"15 Mount Sinai Ave",
    "sg:city":"Mt Sinai",
    "sg:phone":"+1 631 928 5927",
    "sg:postcode":"11766",
    "sg:province":"NY",
    "sg:tags":[
        "oil"
    ],
    "wof:name":"Coldgate Fuel Oil Corp",
    "wof:placetype":"venue"
},
  "geometry": {"coordinates":[-73.015113,40.928998],"type":"Point"}
}