{
  "type": "Feature",
  "properties": {
    "addr:full":"10 Osage Dr E Ossining NY 10562",
    "addr:housenumber":"10",
    "addr:postcode":"10562",
    "addr:street":"Osage Dr E",
    "iso:country":"US",
    "sg:address":"10 Osage Dr E",
    "sg:city":"Ossining",
    "sg:classifiers":[
        {
            "category":"Banks & Credit Unions",
            "subcategory":"Financial Services",
            "type":"Services"
        }
    ],
    "sg:phone":"+1 914 923 5226",
    "sg:postcode":"10562",
    "sg:province":"NY",
    "sg:tags":[
        "company",
        "holding"
    ],
    "wof:name":"Wooden Wagon The",
    "wof:placetype":"venue"
},
  "geometry": {"coordinates":[-73.840931,41.162101],"type":"Point"}
}