{
  "type": "Feature",
  "properties": {
    "addr:full":"410 Quaker Rd Queensbury NY 12804",
    "addr:housenumber":"410",
    "addr:postcode":"12804",
    "addr:street":"Quaker Rd",
    "iso:country":"US",
    "sg:address":"410 Quaker Rd",
    "sg:city":"Queensbury",
    "sg:classifiers":[
        {
            "category":"Food & Beverages",
            "subcategory":"Groceries & Convenience Stores",
            "type":"Retail Goods"
        }
    ],
    "sg:phone":"+1 518 792 6285",
    "sg:postcode":"12804",
    "sg:province":"NY",
    "sg:website":"http://www.cumberlandfarms.com",
    "wof:name":"Cumberland Farms 1504",
    "wof:placetype":"venue"
},
  "geometry": {"coordinates":[-73.63534799999999,43.330944],"type":"Point"}
}