{
  "type": "Feature",
  "properties": {
    "addr:full":"500 Normanskill Dr Duanesburg NY 12056",
    "addr:housenumber":"500",
    "addr:postcode":"12056",
    "addr:street":"Normanskill Dr",
    "iso:country":"US",
    "sg:address":"500 Normanskill Dr",
    "sg:city":"Duanesburg",
    "sg:classifiers":[
        {
            "category":"Professional",
            "type":"Services"
        }
    ],
    "sg:phone":"+1 518 355 6152",
    "sg:postcode":"12056",
    "sg:province":"NY",
    "sg:tags":[
        "establishment"
    ],
    "wof:name":"Schenectady Arc",
    "wof:placetype":"venue"
},
  "geometry": {"coordinates":[-74.04246999999999,42.772102],"type":"Point"}
}