{
  "type": "Feature",
  "properties": {
    "iso:country":"US",
    "sg:address":"8324 Woodhaven Blvd",
    "sg:city":"Glendale",
    "sg:classifiers":[
        {
            "category":"Banks & Credit Unions",
            "subcategory":"Bank",
            "type":"Services"
        }
    ],
    "sg:phone":"+1 718 849 1300",
    "sg:postcode":"11385",
    "sg:province":"NY",
    "wof:name":"CapitalOne",
    "wof:placetype":"venue"
},
  "geometry": {"coordinates":[-73.85554999999999,40.702264],"type":"Point"}
}