{
  "type": "Feature",
  "properties": {
    "addr:full":"5845 Big Tree Rd Lakeville NY 14480",
    "addr:housenumber":"5845",
    "addr:postcode":"14480",
    "addr:street":"Big Tree Rd",
    "iso:country":"US",
    "sg:address":"5845 Big Tree Rd",
    "sg:city":"Lakeville",
    "sg:classifiers":[
        {
            "category":"Wholesale",
            "subcategory":"Durable Goods & Equipment",
            "type":"Manufacturing & Wholesale Goods"
        }
    ],
    "sg:phone":"+1 585 346 0020",
    "sg:postcode":"14480",
    "sg:province":"NY",
    "sg:tags":[
        "representative",
        "manufacturer"
    ],
    "sg:website":"www.agbioinc.com",
    "wof:name":"A G Bio Tech Inc",
    "wof:placetype":"venue"
},
  "geometry": {"coordinates":[-77.703987,42.836007],"type":"Point"}
}