{
  "type": "Feature",
  "properties": {
    "iso:country":"US",
    "sg:address":"760 Old White Plains Rd",
    "sg:city":"Mamaroneck",
    "sg:classifiers":[
        {
            "category":"Retail",
            "subcategory":"Auto Repair",
            "type":"Services"
        }
    ],
    "sg:phone":"+1 914 777 5830",
    "sg:postcode":"10543",
    "sg:province":"NY",
    "sg:tags":[
        "body",
        "automobile",
        "painting",
        "repairing"
    ],
    "wof:name":"Vasco Tech Center, Inc",
    "wof:placetype":"venue"
},
  "geometry": {"coordinates":[-73.740961,40.955999],"type":"Point"}
}