{
  "type": "Feature",
  "properties": {
    "addr:full":"178 MacDougal St New York NY 10011",
    "addr:housenumber":"178",
    "addr:postcode":"10011",
    "addr:street":"Macdougal St",
    "iso:country":"US",
    "sg:address":"178 MacDougal St",
    "sg:city":"New York",
    "sg:classifiers":[
        {
            "category":"Deli",
            "type":"Food & Drink"
        },
        {
            "category":"Food & Beverages",
            "subcategory":"Bakery",
            "type":"Retail Goods"
        }
    ],
    "sg:phone":"+1 212 995 0771",
    "sg:postcode":"10011",
    "sg:province":"NY",
    "sg:tags":[
        "sandwich"
    ],
    "wof:name":"Gus & US",
    "wof:placetype":"venue"
},
  "geometry": {"coordinates":[-73.998001,40.7328],"type":"Point"}
}