{
  "type": "Feature",
  "properties": {
    "iso:country":"US",
    "sg:address":"265 W Woodside Ave",
    "sg:city":"Patchogue",
    "sg:classifiers":[
        {
            "category":"Professional",
            "type":"Services"
        }
    ],
    "sg:phone":"+1 631 758 0820",
    "sg:postcode":"11772",
    "sg:province":"NY",
    "sg:tags":[
        "establishment"
    ],
    "wof:name":"Northeast Technology Solutions",
    "wof:placetype":"venue"
},
  "geometry": {"coordinates":[-73.022881,40.793461],"type":"Point"}
}