{
  "type": "Feature",
  "properties": {
    "addr:full":"633 E Main St Jefferson Valley NY 10535",
    "addr:housenumber":"633",
    "addr:postcode":"10535",
    "addr:street":"E Main St",
    "iso:country":"US",
    "sg:address":"633 E Main St",
    "sg:city":"Jefferson Valley",
    "sg:classifiers":[
        {
            "category":"Retail",
            "subcategory":"Repair Shop",
            "type":"Services"
        }
    ],
    "sg:phone":"+1 914 245 4373",
    "sg:postcode":"10535",
    "sg:province":"NY",
    "sg:tags":[
        "sharpening"
    ],
    "wof:name":"Precision Tool Sharpining",
    "wof:placetype":"venue"
},
  "geometry": {"coordinates":[-73.807941,41.332903],"type":"Point"}
}