{
  "type": "Feature",
  "properties": {
    "addr:full":"64 Grand St New York NY 10013",
    "addr:housenumber":"64",
    "addr:postcode":"10013",
    "addr:street":"Grand St",
    "iso:country":"US",
    "sg:address":"64 Grand St",
    "sg:city":"New York",
    "sg:classifiers":[
        {
            "category":"Building & Trades",
            "subcategory":"Construction",
            "type":"Services"
        }
    ],
    "sg:phone":"+1 917 628 0868",
    "sg:postcode":"10013",
    "sg:province":"NY",
    "sg:tags":[
        "interior",
        "design"
    ],
    "sg:website":"www.tamaramagel.com",
    "wof:name":"Tamara Magel",
    "wof:placetype":"venue"
},
  "geometry": {"coordinates":[-74.003304,40.722265],"type":"Point"}
}