{
  "type": "Feature",
  "properties": {
    "iso:country":"US",
    "sg:address":"999 Rein Rd",
    "sg:city":"Buffalo",
    "sg:classifiers":[
        {
            "category":"Freight",
            "type":"Transportation"
        }
    ],
    "sg:phone":"+1 716 633 4200",
    "sg:postcode":"14225",
    "sg:province":"NY",
    "sg:tags":[
        "delivery"
    ],
    "wof:name":"Radio Express Courier Svc Inc",
    "wof:placetype":"venue"
},
  "geometry": {"coordinates":[-78.710247,42.941048],"type":"Point"}
}