{
  "type": "Feature",
  "properties": {
    "iso:country":"US",
    "sg:address":"13 Center St",
    "sg:city":"Glens Falls",
    "sg:classifiers":[
        {
            "category":"Professional",
            "subcategory":"Lawyer & Legal Services",
            "type":"Services"
        }
    ],
    "sg:phone":"+1 518 743 8416",
    "sg:postcode":"12801",
    "sg:province":"NY",
    "sg:tags":[
        "attorney"
    ],
    "wof:name":"Ronald J Kim Law Offices",
    "wof:placetype":"venue"
},
  "geometry": {"coordinates":[-73.641047,43.310841],"type":"Point"}
}