{
  "type": "Feature",
  "properties": {
    "addr:full":"7067 US Hwy 9 Plattsburgh NY 12901",
    "addr:housenumber":"7067",
    "addr:postcode":"12901",
    "addr:street":"Us Hwy 9",
    "iso:country":"US",
    "sg:address":"7067 US Hwy 9",
    "sg:city":"Plattsburgh",
    "sg:classifiers":[
        {
            "category":"Restaurant",
            "type":"Food & Drink"
        }
    ],
    "sg:phone":"+1 518 562 9309",
    "sg:postcode":"12901",
    "sg:province":"NY",
    "wof:name":"Mc Sweeney's Red Hots",
    "wof:placetype":"venue"
},
  "geometry": {"coordinates":[-73.44116099999999,44.719225],"type":"Point"}
}