{
  "type": "Feature",
  "properties": {
    "addr:full":"155 W 68th St New York NY 10023",
    "addr:housenumber":"155",
    "addr:postcode":"10023",
    "addr:street":"W 68Th St",
    "iso:country":"US",
    "sg:address":"155 W 68th St",
    "sg:city":"New York",
    "sg:classifiers":[
        {
            "category":"Professional",
            "subcategory":"Lawyer & Legal Services",
            "type":"Services"
        }
    ],
    "sg:phone":"+1 212 370 4444",
    "sg:postcode":"10023",
    "sg:province":"NY",
    "wof:name":"Lipkind Jack Atty",
    "wof:placetype":"venue"
},
  "geometry": {"coordinates":[-73.982596,40.776162],"type":"Point"}
}