{
  "type": "Feature",
  "properties": {
    "addr:full":"1345 Utica Ave Brooklyn NY 11203",
    "addr:housenumber":"1345",
    "addr:postcode":"11203",
    "addr:street":"Utica Ave",
    "iso:country":"US",
    "sg:address":"1345 Utica Ave",
    "sg:city":"Brooklyn",
    "sg:classifiers":[
        {
            "category":"Restaurant",
            "type":"Food & Drink"
        }
    ],
    "sg:phone":"+1 718 629 0405",
    "sg:postcode":"11203",
    "sg:province":"NY",
    "sg:tags":[
        "eating"
    ],
    "wof:name":"Josephine's Heros",
    "wof:placetype":"venue"
},
  "geometry": {"coordinates":[-73.928786,40.637514],"type":"Point"}
}