{
  "type": "Feature",
  "properties": {
    "addr:full":"15124 Beaver Rd Jamaica NY 11433",
    "addr:housenumber":"15124",
    "addr:postcode":"11433",
    "addr:street":"Beaver Rd",
    "iso:country":"US",
    "sg:address":"15124 Beaver Rd",
    "sg:city":"Jamaica",
    "sg:classifiers":[
        {
            "category":"Farming",
            "subcategory":"Poultry Farm",
            "type":"Manufacturing & Wholesale Goods"
        }
    ],
    "sg:phone":"+1 800 671 0217",
    "sg:postcode":"11433",
    "sg:province":"NY",
    "wof:name":"Nenku Live Poultry Toll Free-Dial '1' & Then",
    "wof:placetype":"venue"
},
  "geometry": {"coordinates":[-73.802376,40.700176],"type":"Point"}
}