{
  "type": "Feature",
  "properties": {
    "addr:full":"501 W Main St Elkland NY 16920",
    "addr:housenumber":"501",
    "addr:postcode":"16920",
    "addr:street":"W Main St",
    "iso:country":"US",
    "sg:address":"501 W Main St",
    "sg:city":"Elkland",
    "sg:classifiers":[
        {
            "category":"Shopping",
            "subcategory":"Hobbies, Toys, & Games",
            "type":"Retail Goods"
        }
    ],
    "sg:phone":"+1 814 258 5232",
    "sg:postcode":"16920",
    "sg:province":"NY",
    "sg:tags":[
        "craft",
        "supply"
    ],
    "wof:name":"Mary's Country Corner",
    "wof:placetype":"venue"
},
  "geometry": {"coordinates":[-77.321129,41.987297],"type":"Point"}
}