{
  "type": "Feature",
  "properties": {
    "addr:full":"1692 Prospect Pl Brooklyn NY 11233",
    "addr:housenumber":"1692",
    "addr:postcode":"11233",
    "addr:street":"Prospect Pl",
    "iso:country":"US",
    "sg:address":"1692 Prospect Pl",
    "sg:city":"Brooklyn",
    "sg:classifiers":[
        {
            "category":"Shopping",
            "subcategory":"Clothing, Apparel, & Fashions",
            "type":"Retail Goods"
        }
    ],
    "sg:phone":"+1 718 604 1831",
    "sg:postcode":"11233",
    "sg:province":"NY",
    "sg:tags":[
        "tailor",
        "alterations-clothing"
    ],
    "wof:name":"Building Alteration & Legalize",
    "wof:placetype":"venue"
},
  "geometry": {"coordinates":[-73.92038100000001,40.672704],"type":"Point"}
}