{
  "type": "Feature",
  "properties": {
    "addr:full":"469 French Ave North Babylon NY 11703",
    "addr:housenumber":"469",
    "addr:postcode":"11703",
    "addr:street":"French Ave North",
    "iso:country":"US",
    "sg:address":"469 French Ave",
    "sg:city":"North Babylon",
    "sg:classifiers":[
        {
            "category":"Social Services",
            "type":"Services"
        }
    ],
    "sg:phone":"+1 631 595 2673",
    "sg:postcode":"11703",
    "sg:province":"NY",
    "sg:tags":[
        "worker"
    ],
    "wof:name":"Robert Digiovanna",
    "wof:placetype":"venue"
},
  "geometry": {"coordinates":[-73.32688400000001,40.74093],"type":"Point"}
}