{
  "type": "Feature",
  "properties": {
    "iso:country":"US",
    "sg:address":"269 Avenue U",
    "sg:city":"Brooklyn",
    "sg:classifiers":[
        {
            "category":"Personal",
            "subcategory":"Day Spa",
            "type":"Services"
        }
    ],
    "sg:phone":"+1 718 373 0137",
    "sg:postcode":"11223",
    "sg:province":"NY",
    "wof:name":"V S Day Spa",
    "wof:placetype":"venue"
},
  "geometry": {"coordinates":[-73.97425,40.596977],"type":"Point"}
}