{
  "type": "Feature",
  "properties": {
    "iso:country":"US",
    "sg:address":"471 Fulton St",
    "sg:city":"Brooklyn",
    "sg:classifiers":[
        {
            "category":"Shopping",
            "subcategory":"Clothing, Apparel, & Fashions",
            "type":"Retail Goods"
        }
    ],
    "sg:phone":"+1 718 243 1918",
    "sg:postcode":"11201",
    "sg:province":"NY",
    "sg:tags":[
        "clothing",
        "women's"
    ],
    "sg:website":"www.drjays.com",
    "wof:name":"Dr Jay's Ladies",
    "wof:placetype":"venue"
},
  "geometry": {"coordinates":[-73.986198,40.691101],"type":"Point"}
}