{
  "type": "Feature",
  "properties": {
    "iso:country":"US",
    "sg:address":"4643 W Lake Rd",
    "sg:city":"Mayville",
    "sg:classifiers":[
        {
            "category":"Education",
            "subcategory":"Special Training",
            "type":"Public Place"
        }
    ],
    "sg:phone":"+1 716 269 3629",
    "sg:postcode":"14757",
    "sg:province":"NY",
    "sg:tags":[
        "school",
        "instruction",
        "art"
    ],
    "wof:name":"Chautauqua School Of Art",
    "wof:placetype":"venue"
},
  "geometry": {"coordinates":[-79.46619200000001,42.204726],"type":"Point"}
}