{
  "type": "Feature",
  "properties": {
    "addr:full":"1368 Grand St Westbury NY 11590",
    "addr:housenumber":"1368",
    "addr:postcode":"11590",
    "addr:street":"Grand St",
    "iso:country":"US",
    "sg:address":"1368 Grand St",
    "sg:city":"Westbury",
    "sg:classifiers":[
        {
            "category":"Food & Beverages",
            "subcategory":"Meat & Fish",
            "type":"Retail Goods"
        }
    ],
    "sg:phone":"+1   ",
    "sg:postcode":"11590",
    "sg:province":"NY",
    "wof:name":"Apple Gourmet Meat & Seafood",
    "wof:placetype":"venue"
},
  "geometry": {"coordinates":[-73.591362,40.761184],"type":"Point"}
}