{
  "type": "Feature",
  "properties": {
    "addr:full":"230 Tabor Rd Jefferson NY 12023",
    "addr:housenumber":"230",
    "addr:postcode":"12023",
    "addr:street":"Tabor Rd",
    "iso:country":"US",
    "sg:address":"230 Tabor Rd",
    "sg:city":"Jefferson",
    "sg:classifiers":[
        {
            "category":"Home & Garden",
            "subcategory":"Building Materials",
            "type":"Retail Goods"
        }
    ],
    "sg:phone":"+1   ",
    "sg:postcode":"12023",
    "sg:province":"NY",
    "wof:name":"Taber Lumber Co",
    "wof:placetype":"venue"
},
  "geometry": {"coordinates":[-74.108771,42.636114],"type":"Point"}
}