{
  "type": "Feature",
  "properties": {
    "iso:country":"US",
    "sg:address":"309 Lincoln Ave",
    "sg:city":"Rockville Centre",
    "sg:classifiers":[
        {
            "category":"Social Services",
            "subcategory":"Job Training",
            "type":"Services"
        }
    ],
    "sg:phone":"+1 516 763 1263",
    "sg:postcode":"11570",
    "sg:province":"NY",
    "wof:name":"Nassau County A R C",
    "wof:placetype":"venue"
},
  "geometry": {"coordinates":[-73.640339,40.649744],"type":"Point"}
}