{
  "type": "Feature",
  "properties": {
    "iso:country":"US",
    "sg:address":"3549 Long Beach Rd # A",
    "sg:city":"Oceanside",
    "sg:classifiers":[
        {
            "category":"Coffee & Tea",
            "type":"Food & Drink"
        }
    ],
    "sg:phone":"+1 516 536 4363",
    "sg:postcode":"11572",
    "sg:province":"NY",
    "wof:name":"Starbucks Coffee",
    "wof:placetype":"venue"
},
  "geometry": {"coordinates":[-73.639397,40.6245],"type":"Point"}
}