{
  "type": "Feature",
  "properties": {
    "addr:full":"483 Medford Ave Patchogue NY 11772",
    "addr:housenumber":"483",
    "addr:postcode":"11772",
    "addr:street":"Medford Ave",
    "iso:country":"US",
    "sg:address":"483 Medford Ave",
    "sg:city":"Patchogue",
    "sg:classifiers":[
        {
            "category":"Autos & Motor Vehicles",
            "subcategory":"Automobile Sales",
            "type":"Retail Goods"
        }
    ],
    "sg:phone":"+1 631 289 8507",
    "sg:postcode":"11772",
    "sg:province":"NY",
    "sg:tags":[
        "car",
        "dealer"
    ],
    "wof:name":"Crysler Island Crysler Plymth",
    "wof:placetype":"venue"
},
  "geometry": {"coordinates":[-73.008775,40.784262],"type":"Point"}
}