{
  "type": "Feature",
  "properties": {
    "iso:country":"US",
    "sg:address":"187 Houseman St",
    "sg:city":"Mayfield",
    "sg:classifiers":[
        {
            "category":"Personal",
            "subcategory":"Beauty Salon",
            "type":"Services"
        }
    ],
    "sg:phone":"+1 518 863 8758",
    "sg:postcode":"12117",
    "sg:province":"NY",
    "sg:tags":[
        "shop"
    ],
    "wof:name":"Scissor Shoppe Unisex",
    "wof:placetype":"venue"
},
  "geometry": {"coordinates":[-74.18146900000001,43.199332],"type":"Point"}
}