{
  "type": "Feature",
  "properties": {
    "addr:full":"9 Oakdale Dr Westbury NY 11590",
    "addr:housenumber":"9",
    "addr:postcode":"11590",
    "addr:street":"Oakdale Dr",
    "iso:country":"US",
    "sg:address":"9 Oakdale Dr",
    "sg:city":"Westbury",
    "sg:classifiers":[
        {
            "category":"Health Services",
            "subcategory":"Clinic",
            "type":"Services"
        }
    ],
    "sg:phone":"+1   ",
    "sg:postcode":"11590",
    "sg:province":"NY",
    "wof:name":"Health & Wellness Family",
    "wof:placetype":"venue"
},
  "geometry": {"coordinates":[-73.556618,40.768293],"type":"Point"}
}