{
  "type": "Feature",
  "properties": {
    "iso:country":"US",
    "sg:address":"98 Inwood Ave",
    "sg:city":"Poughkeepsie",
    "sg:classifiers":[
        {
            "category":"Building & Trades",
            "subcategory":"Landscaping Services",
            "type":"Services"
        }
    ],
    "sg:phone":"+1 845 473 8349",
    "sg:postcode":"12601",
    "sg:province":"NY",
    "sg:tags":[
        "landscape"
    ],
    "wof:name":"B&L Binn",
    "wof:placetype":"venue"
},
  "geometry": {"coordinates":[-73.916409,41.731148],"type":"Point"}
}