{
  "type": "Feature",
  "properties": {
    "iso:country":"US",
    "sg:address":"1458 Plum Ln",
    "sg:city":"East Meadow",
    "sg:classifiers":[
        {
            "category":"Professional",
            "subcategory":"Business Services",
            "type":"Services"
        }
    ],
    "sg:phone":"+1 516 489 4363",
    "sg:postcode":"11554",
    "sg:province":"NY",
    "wof:name":"For Decor",
    "wof:placetype":"venue"
},
  "geometry": {"coordinates":[-73.568523,40.709142],"type":"Point"}
}