{
  "type": "Feature",
  "properties": {
    "iso:country":"US",
    "sg:address":"3128 State Hwy 417",
    "sg:city":"Olean",
    "sg:classifiers":[
        {
            "category":"Retail",
            "subcategory":"Funeral Services",
            "type":"Services"
        }
    ],
    "sg:phone":"+1 716 372 0254",
    "sg:postcode":"14760",
    "sg:province":"NY",
    "sg:tags":[
        "director"
    ],
    "wof:name":"Casey Halwig & Hartle Funeral",
    "wof:placetype":"venue"
},
  "geometry": {"coordinates":[-78.46713800000001,42.076836],"type":"Point"}
}