{
  "type": "Feature",
  "properties": {
    "iso:country":"US",
    "sg:address":"318 Clarkson Ave",
    "sg:city":"Brooklyn",
    "sg:classifiers":[
        {
            "category":"Parking",
            "type":"Transportation"
        }
    ],
    "sg:phone":"+1 718 469 7672",
    "sg:postcode":"11226",
    "sg:province":"NY",
    "sg:tags":[
        "garage"
    ],
    "wof:name":"ESP Parking",
    "wof:placetype":"venue"
},
  "geometry": {"coordinates":[-73.94779,40.65547],"type":"Point"}
}