{
  "type": "Feature",
  "properties": {
    "iso:country":"US",
    "sg:address":"211 W 1st St",
    "sg:city":"Oswego",
    "sg:classifiers":[
        {
            "category":"Personal",
            "type":"Services"
        }
    ],
    "sg:phone":"+1   ",
    "sg:postcode":"13126",
    "sg:province":"NY",
    "wof:name":"Sun Seekers Tanning Salon",
    "wof:placetype":"venue"
},
  "geometry": {"coordinates":[-76.51081600000001,43.455697],"type":"Point"}
}