{
  "type": "Feature",
  "properties": {
    "iso:country":"US",
    "sg:address":"67 Atlantic Ave",
    "sg:city":"Brooklyn",
    "sg:classifiers":[
        {
            "category":"Building & Trades",
            "subcategory":"Construction",
            "type":"Services"
        }
    ],
    "sg:phone":"+1 718 858 9893",
    "sg:postcode":"11201",
    "sg:province":"NY",
    "sg:tags":[
        "developer"
    ],
    "wof:name":"67 On Hanson Inc",
    "wof:placetype":"venue"
},
  "geometry": {"coordinates":[-73.998164,40.691402],"type":"Point"}
}