{
  "type": "Feature",
  "properties": {
    "iso:country":"US",
    "sg:address":"10 Henhawk Ln",
    "sg:city":"Roslyn",
    "sg:classifiers":[
        {
            "category":"Health Services",
            "subcategory":"Health Practitioner",
            "type":"Services"
        }
    ],
    "sg:phone":"+1 516 626 7273",
    "sg:postcode":"11576",
    "sg:province":"NY",
    "sg:tags":[
        "occupational",
        "therapist"
    ],
    "wof:name":"North Shore Hand Therapy",
    "wof:placetype":"venue"
},
  "geometry": {"coordinates":[-73.61835499999999,40.805424],"type":"Point"}
}