{
  "type": "Feature",
  "properties": {
    "addr:full":"31 W Market St Rhinebeck NY 12572",
    "addr:housenumber":"31",
    "addr:postcode":"12572",
    "addr:street":"W Market St",
    "iso:country":"US",
    "sg:address":"31 W Market St",
    "sg:city":"Rhinebeck",
    "sg:classifiers":[
        {
            "category":"Food & Beverages",
            "subcategory":"Bakery",
            "type":"Retail Goods"
        }
    ],
    "sg:phone":"+1   ",
    "sg:postcode":"12572",
    "sg:province":"NY",
    "wof:name":"Rhinebeck Bagels & Cafe",
    "wof:placetype":"venue"
},
  "geometry": {"coordinates":[-73.914123,41.926912],"type":"Point"}
}