{
  "type": "Feature",
  "properties": {
    "addr:full":"765 Amsterdam Ave Apt 1F New York NY 10025",
    "addr:housenumber":"765",
    "addr:postcode":"10025",
    "addr:street":"Amsterdam Ave Apt 1F",
    "iso:country":"US",
    "sg:address":"765 Amsterdam Ave Apt 1F",
    "sg:city":"New York",
    "sg:classifiers":[
        {
            "category":"Health Services",
            "subcategory":"Doctor",
            "type":"Services"
        }
    ],
    "sg:phone":"+1 212 663 3601",
    "sg:postcode":"10025",
    "sg:province":"NY",
    "wof:name":"Ronak Medical Care",
    "wof:placetype":"venue"
},
  "geometry": {"coordinates":[-73.969711,40.794924],"type":"Point"}
}