{
  "type": "Feature",
  "properties": {
    "addr:full":"2 E 61st St New York NY 10065",
    "addr:housenumber":"2",
    "addr:postcode":"10065",
    "addr:street":"E 61St St",
    "iso:country":"US",
    "sg:address":"2 E 61st St",
    "sg:city":"New York",
    "sg:classifiers":[
        {
            "category":"Bars & Pubs",
            "subcategory":"Lounge",
            "type":"Food & Drink"
        }
    ],
    "sg:phone":"+1 212 940 8113",
    "sg:postcode":"10065",
    "sg:province":"NY",
    "sg:website":"www.twoeny.com",
    "wof:name":"Two E Bar/Lounge",
    "wof:placetype":"venue"
},
  "geometry": {"coordinates":[-73.971878,40.765342],"type":"Point"}
}