{
  "type": "Feature",
  "properties": {
    "iso:country":"US",
    "sg:address":"152 Central Ave",
    "sg:city":"Albany",
    "sg:classifiers":[
        {
            "category":"Professional",
            "subcategory":"Lawyer & Legal Services",
            "type":"Services"
        }
    ],
    "sg:phone":"+1 518 434 1022",
    "sg:postcode":"12206",
    "sg:province":"NY",
    "sg:tags":[
        "attorney"
    ],
    "wof:name":"Sullivan Cunningham Keenan",
    "wof:placetype":"venue"
},
  "geometry": {"coordinates":[-73.768635,42.661071],"type":"Point"}
}