{
  "type": "Feature",
  "properties": {
    "addr:full":"4299 Newtown Rd Burdett NY 14818",
    "addr:housenumber":"4299",
    "addr:postcode":"14818",
    "addr:street":"Newtown Rd",
    "iso:country":"US",
    "sg:address":"4299 Newtown Rd",
    "sg:city":"Burdett",
    "sg:classifiers":[
        {
            "category":"Building & Trades",
            "subcategory":"Construction",
            "type":"Services"
        }
    ],
    "sg:phone":"+1 607 546 8289",
    "sg:postcode":"14818",
    "sg:province":"NY",
    "sg:tags":[
        "bridge"
    ],
    "wof:name":"Silverline Construction Inc",
    "wof:placetype":"venue"
},
  "geometry": {"coordinates":[-76.766943,42.442398],"type":"Point"}
}