{
  "type": "Feature",
  "properties": {
    "addr:full":"128 Graham Ave Brooklyn NY 11206",
    "addr:housenumber":"128",
    "addr:postcode":"11206",
    "addr:street":"Graham Ave",
    "iso:country":"US",
    "sg:address":"128 Graham Ave",
    "sg:city":"Brooklyn",
    "sg:classifiers":[
        {
            "category":"Professional",
            "type":"Services"
        }
    ],
    "sg:phone":"+1 718 388 0702",
    "sg:postcode":"11206",
    "sg:province":"NY",
    "sg:tags":[
        "bureau"
    ],
    "wof:name":"CGM Check Cashing Corp",
    "wof:placetype":"venue"
},
  "geometry": {"coordinates":[-73.94281599999999,40.705292],"type":"Point"}
}