{
  "type": "Feature",
  "properties": {
    "iso:country":"US",
    "sg:address":"78 Maplewood Ave",
    "sg:city":"Selden",
    "sg:classifiers":[
        {
            "category":"Home & Garden",
            "subcategory":"Building Materials",
            "type":"Retail Goods"
        },
        {
            "category":"Building & Trades",
            "subcategory":"Construction",
            "type":"Services"
        }
    ],
    "sg:phone":"+1 631 698 1226",
    "sg:postcode":"11784",
    "sg:province":"NY",
    "sg:tags":[
        "industrial",
        "contractor",
        "concrete",
        "contractors-commercial",
        "staining",
        "masonry",
        "mason"
    ],
    "wof:name":"Allstate Concrete & Masonary C",
    "wof:placetype":"venue"
},
  "geometry": {"coordinates":[-73.042002,40.85751],"type":"Point"}
}