{
  "type": "Feature",
  "properties": {
    "addr:full":"408 E 118th St New York NY 10035",
    "addr:housenumber":"408",
    "addr:postcode":"10035",
    "addr:street":"E 118Th St",
    "iso:country":"US",
    "sg:address":"408 E 118th St",
    "sg:city":"New York",
    "sg:classifiers":[
        {
            "category":"Professional",
            "subcategory":"Accounting & Tax Preparation",
            "type":"Services"
        }
    ],
    "sg:phone":"+1   ",
    "sg:postcode":"10035",
    "sg:province":"NY",
    "wof:name":"Manhattan Bookkeeping Services",
    "wof:placetype":"venue"
},
  "geometry": {"coordinates":[-73.932376,40.79637],"type":"Point"}
}