{
  "type": "Feature",
  "properties": {
    "iso:country":"US",
    "sg:address":"439 Co Rd 39",
    "sg:city":"Afton",
    "sg:classifiers":[
        {
            "category":"Building & Trades",
            "subcategory":"Construction",
            "type":"Services"
        }
    ],
    "sg:phone":"+1 607 639 1351",
    "sg:postcode":"13730",
    "sg:province":"NY",
    "sg:tags":[
        "house"
    ],
    "wof:name":"Valentine Samler Carpentry",
    "wof:placetype":"venue"
},
  "geometry": {"coordinates":[-75.48080899999999,42.250454],"type":"Point"}
}