{
  "type": "Feature",
  "properties": {
    "addr:full":"3165 Delaware Ave Buffalo NY 14217",
    "addr:housenumber":"3165",
    "addr:postcode":"14217",
    "addr:street":"Delaware Ave",
    "iso:country":"US",
    "sg:address":"3165 Delaware Ave",
    "sg:city":"Buffalo",
    "sg:classifiers":[
        {
            "category":"Personal",
            "subcategory":"Shoe Repair & Shine",
            "type":"Services"
        }
    ],
    "sg:phone":"+1 716 873 7464",
    "sg:postcode":"14217",
    "sg:province":"NY",
    "sg:tags":[
        "repairing",
        "boot"
    ],
    "wof:name":"Model Shoe Shop",
    "wof:placetype":"venue"
},
  "geometry": {"coordinates":[-78.870919,42.970527],"type":"Point"}
}