{
  "type": "Feature",
  "properties": {
    "iso:country":"US",
    "sg:address":"150 Rosebrook Rd",
    "sg:city":"New Canaan",
    "sg:classifiers":[
        {
            "category":"Professional",
            "subcategory":"Business Services",
            "type":"Services"
        }
    ],
    "sg:phone":"+1   ",
    "sg:postcode":"06840",
    "sg:province":"NY",
    "sg:tags":[
        "interior",
        "decorator"
    ],
    "wof:name":"Layng Interiors",
    "wof:placetype":"venue"
},
  "geometry": {"coordinates":[-73.488553,41.162489],"type":"Point"}
}