{
  "type": "Feature",
  "properties": {
    "addr:full":"943 Ulster Landing Rd Saugerties NY 12477",
    "addr:housenumber":"943",
    "addr:postcode":"12477",
    "addr:street":"Ulster Landing Rd",
    "iso:country":"US",
    "sg:address":"943 Ulster Landing Rd",
    "sg:city":"Saugerties",
    "sg:classifiers":[
        {
            "category":"Real Estate",
            "subcategory":"Surveying",
            "type":"Services"
        }
    ],
    "sg:phone":"+1 845 336 0043",
    "sg:postcode":"12477",
    "sg:province":"NY",
    "sg:tags":[
        "surveyor"
    ],
    "wof:name":"Michael Vetere Land Surveyors",
    "wof:placetype":"venue"
},
  "geometry": {"coordinates":[-73.94838,41.995173],"type":"Point"}
}