{
  "type": "Feature",
  "properties": {
    "iso:country":"US",
    "sg:address":"256 E 10 St",
    "sg:city":"New York",
    "sg:classifiers":[
        {
            "category":"Manufacturing",
            "subcategory":"Printing",
            "type":"Manufacturing & Wholesale Goods"
        }
    ],
    "sg:phone":"+1   ",
    "sg:postcode":"10009",
    "sg:province":"NY",
    "sg:tags":[
        "commercial"
    ],
    "wof:name":"Recycled Paper Company Inc",
    "wof:placetype":"venue"
},
  "geometry": {"coordinates":[-73.982587,40.72796],"type":"Point"}
}