{
  "type": "Feature",
  "properties": {
    "iso:country":"US",
    "sg:address":"65 Heyward St",
    "sg:city":"Brooklyn",
    "sg:classifiers":[
        {
            "category":"Banks & Credit Unions",
            "subcategory":"Bank",
            "type":"Services"
        }
    ],
    "sg:phone":"+1 718 522 6467",
    "sg:postcode":"11211",
    "sg:province":"NY",
    "sg:tags":[
        "loan",
        "real estate"
    ],
    "wof:name":"First Universal Network Inc",
    "wof:placetype":"venue"
},
  "geometry": {"coordinates":[-73.958614,40.69993],"type":"Point"}
}