{
  "type": "Feature",
  "properties": {
    "addr:full":"61 4 Ave New York NY 10003",
    "addr:postcode":"10003",
    "addr:street":"61 4 Ave",
    "iso:country":"US",
    "sg:address":"61 4 Ave",
    "sg:city":"New York",
    "sg:classifiers":[
        {
            "category":"Manufacturing",
            "subcategory":"Printing",
            "type":"Manufacturing & Wholesale Goods"
        }
    ],
    "sg:phone":"+1 212 777 2480",
    "sg:postcode":"10003",
    "sg:province":"NY",
    "sg:tags":[
        "publisher"
    ],
    "sg:website":"www.evergreenreview.com",
    "wof:name":"Evergreen Review Inc",
    "wof:placetype":"venue"
},
  "geometry": {"coordinates":[-73.990583,40.730562],"type":"Point"}
}