{
  "type": "Feature",
  "properties": {
    "iso:country":"US",
    "sg:address":"846 Main Rd",
    "sg:city":"Corfu",
    "sg:classifiers":[
        {
            "category":"Autos & Motor Vehicles",
            "subcategory":"Automobile Sales",
            "type":"Retail Goods"
        }
    ],
    "sg:phone":"+1   ",
    "sg:postcode":"14036",
    "sg:province":"NY",
    "sg:tags":[
        "used"
    ],
    "wof:name":"Kly International",
    "wof:placetype":"venue"
},
  "geometry": {"coordinates":[-78.424227,42.994337],"type":"Point"}
}