{
  "type": "Feature",
  "properties": {
    "addr:full":"245 W 107th St New York NY 10025",
    "addr:housenumber":"245",
    "addr:postcode":"10025",
    "addr:street":"W 107Th St",
    "iso:country":"US",
    "sg:address":"245 W 107th St",
    "sg:city":"New York",
    "sg:classifiers":[
        {
            "category":"Professional",
            "subcategory":"Advertising",
            "type":"Services"
        }
    ],
    "sg:phone":"+1 212 866 5707",
    "sg:postcode":"10025",
    "sg:province":"NY",
    "sg:tags":[
        "mail",
        "direct"
    ],
    "wof:name":"Vogelman & Associates",
    "wof:placetype":"venue"
},
  "geometry": {"coordinates":[-73.96637,40.801493],"type":"Point"}
}