{
  "type": "Feature",
  "properties": {
    "addr:full":"49 Van Wyck St Croton On Hudson NY 10520",
    "addr:housenumber":"49",
    "addr:postcode":"10520",
    "addr:street":"Van Wyck St",
    "iso:country":"US",
    "sg:address":"49 Van Wyck St",
    "sg:city":"Croton On Hudson",
    "sg:classifiers":[
        {
            "category":"Travel",
            "subcategory":"Hotels & Motels",
            "type":"Entertainment"
        }
    ],
    "sg:phone":"+1   ",
    "sg:postcode":"10520",
    "sg:province":"NY",
    "sg:tags":[
        "operation",
        "used",
        "merchandise"
    ],
    "sg:website":"www.alexanderhamiltonhouse.com",
    "wof:name":"Alexander Hamilton House",
    "wof:placetype":"venue"
},
  "geometry": {"coordinates":[-73.88925999999999,41.206025],"type":"Point"}
}