{
  "type": "Feature",
  "properties": {
    "addr:full":"496 Laguardia Pl New York NY 10012",
    "addr:housenumber":"496",
    "addr:postcode":"10012",
    "addr:street":"Laguardia Pl",
    "iso:country":"US",
    "sg:address":"496 Laguardia Pl",
    "sg:city":"New York",
    "sg:classifiers":[
        {
            "category":"Restaurant",
            "type":"Food & Drink"
        }
    ],
    "sg:menulink":"http://www.allmenus.com/ny/new-york/2249-okinawa-japanese-restaurant/menu/",
    "sg:phone":"+1 212 253 8886",
    "sg:postcode":"10012",
    "sg:province":"NY",
    "sg:tags":[
        "japanese",
        "asian"
    ],
    "wof:name":"Okinawa Japanese Restaurant",
    "wof:placetype":"venue"
},
  "geometry": {"coordinates":[-73.999787,40.727474],"type":"Point"}
}