{
  "type": "Feature",
  "properties": {
    "addr:full":"9849 Huyck Rd Farmersville Station NY 14060",
    "addr:housenumber":"9849",
    "addr:postcode":"14060",
    "addr:street":"Huyck Rd",
    "iso:country":"US",
    "sg:address":"9849 Huyck Rd",
    "sg:city":"Farmersville Station",
    "sg:phone":"+1 716 676 5932",
    "sg:postcode":"14060",
    "sg:province":"NY",
    "sg:tags":[
        "farm",
        "corn"
    ],
    "wof:name":"Norman D Nichols",
    "wof:placetype":"venue"
},
  "geometry": {"coordinates":[-78.322789,42.425433],"type":"Point"}
}