{
  "type": "Feature",
  "properties": {
    "addr:full":"636 Elmwood Rd West Babylon NY 11704",
    "addr:housenumber":"636",
    "addr:postcode":"11704",
    "addr:street":"Elmwood Rd",
    "iso:country":"US",
    "sg:address":"636 Elmwood Rd",
    "sg:city":"West Babylon",
    "sg:classifiers":[
        {
            "category":"Building & Trades",
            "subcategory":"Plumbing",
            "type":"Services"
        }
    ],
    "sg:phone":"+1 631 669 2770",
    "sg:postcode":"11704",
    "sg:province":"NY",
    "sg:tags":[
        "contractor"
    ],
    "wof:name":"SPI Plumbing Industries Ltd",
    "wof:placetype":"venue"
},
  "geometry": {"coordinates":[-73.351748,40.705204],"type":"Point"}
}