{
  "type": "Feature",
  "properties": {
    "iso:country":"US",
    "sg:address":"2707 S Salina St",
    "sg:city":"Syracuse",
    "sg:classifiers":[
        {
            "category":"Restaurant",
            "type":"Food & Drink"
        }
    ],
    "sg:menulink":"http://www.allmenus.com/ny/syracuse/17663-new-wan-fa-restaurant/menu/",
    "sg:phone":"+1 315 422 1110",
    "sg:postcode":"13205",
    "sg:province":"NY",
    "sg:tags":[
        "asian",
        "chinese"
    ],
    "wof:name":"New Wan Fa Restaurant",
    "wof:placetype":"venue"
},
  "geometry": {"coordinates":[-76.143282,43.02129],"type":"Point"}
}