{
  "type": "Feature",
  "properties": {
    "addr:full":"773 Bergen St Brooklyn NY 11238",
    "addr:housenumber":"773",
    "addr:postcode":"11238",
    "addr:street":"Bergen St",
    "iso:country":"US",
    "sg:address":"773 Bergen St",
    "sg:city":"Brooklyn",
    "sg:classifiers":[
        {
            "category":"Personal",
            "type":"Services"
        }
    ],
    "sg:phone":"+1 718 771 3600",
    "sg:postcode":"11238",
    "sg:province":"NY",
    "sg:tags":[
        "towing"
    ],
    "wof:name":"Forrester's Towing",
    "wof:placetype":"venue"
},
  "geometry": {"coordinates":[-73.962799,40.678398],"type":"Point"}
}