{
  "type": "Feature",
  "properties": {
    "addr:full":"22 Gerke Ave New City NY 10956",
    "addr:housenumber":"22",
    "addr:postcode":"10956",
    "addr:street":"Gerke Ave",
    "iso:country":"US",
    "sg:address":"22 Gerke Ave",
    "sg:city":"New City",
    "sg:classifiers":[
        {
            "category":"Real Estate",
            "subcategory":"Real Estate Agent",
            "type":"Services"
        }
    ],
    "sg:phone":"+1 845 356 1957",
    "sg:postcode":"10956",
    "sg:province":"NY",
    "wof:name":"Anthony F Pollice Realty Inc",
    "wof:placetype":"venue"
},
  "geometry": {"coordinates":[-74.021137,41.11983],"type":"Point"}
}