{
  "type": "Feature",
  "properties": {
    "addr:full":"55 New Street New York NY 10004",
    "addr:housenumber":"55",
    "addr:postcode":"10004",
    "addr:street":"New Street",
    "iso:country":"US",
    "sg:address":"55 New Street",
    "sg:city":"New York",
    "sg:classifiers":[
        {
            "category":"Personal",
            "subcategory":"Beauty Salon",
            "type":"Services"
        },
        {
            "category":"Personal",
            "subcategory":"Barber",
            "type":"Services"
        }
    ],
    "sg:phone":"+1 212 248 3939",
    "sg:postcode":"10004",
    "sg:province":"NY",
    "sg:tags":[
        "hair"
    ],
    "wof:name":"New Street Barber Shop",
    "wof:placetype":"venue"
},
  "geometry": {"coordinates":[-74.012457,40.704986],"type":"Point"}
}