{
  "type": "Feature",
  "properties": {
    "iso:country":"US",
    "sg:address":"13 Liberty Ave",
    "sg:city":"Selden",
    "sg:classifiers":[
        {
            "category":"Building & Trades",
            "subcategory":"Construction",
            "type":"Services"
        }
    ],
    "sg:phone":"+1 631 732 0271",
    "sg:postcode":"11784",
    "sg:province":"NY",
    "wof:name":"Bob Esposito",
    "wof:placetype":"venue"
},
  "geometry": {"coordinates":[-73.044363,40.878406],"type":"Point"}
}