{
  "type": "Feature",
  "properties": {
    "iso:country":"US",
    "sg:address":"3145 Beaver Brook Ln",
    "sg:city":"Baldwinsville",
    "sg:classifiers":[
        {
            "category":"Professional",
            "subcategory":"Management & Consulting",
            "type":"Services"
        }
    ],
    "sg:phone":"+1 315 638 7814",
    "sg:postcode":"13027",
    "sg:province":"NY",
    "sg:tags":[
        "marketing",
        "consultant"
    ],
    "wof:name":"Brown & Co",
    "wof:placetype":"venue"
},
  "geometry": {"coordinates":[-76.29272899999999,43.194577],"type":"Point"}
}