{
  "type": "Feature",
  "properties": {
    "addr:full":"4309 13th Ave Brooklyn NY 11219",
    "addr:housenumber":"4309",
    "addr:postcode":"11219",
    "addr:street":"13Th Ave",
    "iso:country":"US",
    "sg:address":"4309 13th Ave",
    "sg:city":"Brooklyn",
    "sg:classifiers":[
        {
            "category":"Retail",
            "subcategory":"Laundry & Dry Cleaning",
            "type":"Services"
        },
        {
            "category":"Shopping",
            "subcategory":"Clothing, Apparel, & Fashions",
            "type":"Retail Goods"
        }
    ],
    "sg:phone":"+1 718 437 0036",
    "sg:postcode":"11219",
    "sg:province":"NY",
    "sg:tags":[
        "robe",
        "lingerie",
        "towel",
        "supply"
    ],
    "wof:name":"Robe Collection LLC",
    "wof:placetype":"venue"
},
  "geometry": {"coordinates":[-73.98911099999999,40.637822],"type":"Point"}
}