{
  "type": "Feature",
  "properties": {
    "iso:country":"US",
    "sg:address":"1350 E Boston Post Rd",
    "sg:city":"Mamaroneck",
    "sg:classifiers":[
        {
            "category":"Banks & Credit Unions",
            "subcategory":"Bank",
            "type":"Services"
        }
    ],
    "sg:phone":"+1 914 935 9935",
    "sg:postcode":"10543",
    "sg:province":"NY",
    "wof:name":"Chase",
    "wof:placetype":"venue"
},
  "geometry": {"coordinates":[-73.716537,40.954773],"type":"Point"}
}