{
  "type": "Feature",
  "properties": {
    "addr:full":"644 Old Post Rd Bedford NY 10506",
    "addr:housenumber":"644",
    "addr:postcode":"10506",
    "addr:street":"Old Post Rd",
    "iso:country":"US",
    "sg:address":"644 Old Post Rd",
    "sg:city":"Bedford",
    "sg:classifiers":[
        {
            "category":"Real Estate",
            "subcategory":"Architect",
            "type":"Services"
        }
    ],
    "sg:phone":"+1 914 234 2595",
    "sg:postcode":"10506",
    "sg:province":"NY",
    "wof:name":"Carol JW Kurth Architects",
    "wof:placetype":"venue"
},
  "geometry": {"coordinates":[-73.643677,41.208027],"type":"Point"}
}