{
  "type": "Feature",
  "properties": {
    "iso:country":"US",
    "sg:address":"1771 Popham Ave",
    "sg:city":"Bronx",
    "sg:classifiers":[
        {
            "category":"Arts & Performance",
            "subcategory":"Art Gallery",
            "type":"Entertainment"
        }
    ],
    "sg:phone":"+1 718 294 0034",
    "sg:postcode":"10453",
    "sg:province":"NY",
    "wof:name":"Bronx Arts Ensemble",
    "wof:placetype":"venue"
},
  "geometry": {"coordinates":[-73.918665,40.851481],"type":"Point"}
}