{
  "type": "Feature",
  "properties": {
    "iso:country":"US",
    "sg:address":"706 Arbuckle Ave",
    "sg:city":"Woodmere",
    "sg:classifiers":[
        {
            "category":"Organizations",
            "subcategory":"Religious Organization",
            "type":"Services"
        }
    ],
    "sg:phone":"+1 516 295 4008",
    "sg:postcode":"11598",
    "sg:province":"NY",
    "sg:tags":[
        "clergy"
    ],
    "wof:name":"David Abikzer",
    "wof:placetype":"venue"
},
  "geometry": {"coordinates":[-73.729448,40.635512],"type":"Point"}
}