{
  "type": "Feature",
  "properties": {
    "addr:full":"457 Atlantic Ave Ground Flst Brooklyn NY 11217",
    "addr:housenumber":"457",
    "addr:postcode":"11217",
    "addr:street":"Atlantic Ave Ground Flst",
    "iso:country":"US",
    "sg:address":"457 Atlantic Ave Ground Flst",
    "sg:city":"Brooklyn",
    "sg:classifiers":[
        {
            "category":"Banks & Credit Unions",
            "subcategory":"Financial Services",
            "type":"Services"
        }
    ],
    "sg:phone":"+1 718 780 9103",
    "sg:postcode":"11217",
    "sg:province":"NY",
    "sg:tags":[
        "broker",
        "mortgage"
    ],
    "sg:website":"www.wfhm.com",
    "wof:name":"Wells Fargo Home Mortgage",
    "wof:placetype":"venue"
},
  "geometry": {"coordinates":[-73.982337,40.686232],"type":"Point"}
}