{
  "type": "Feature",
  "properties": {
    "addr:full":"6359 Fly Rd East Syracuse NY 13057",
    "addr:housenumber":"6359",
    "addr:postcode":"13057",
    "addr:street":"Fly Rd",
    "iso:country":"US",
    "sg:address":"6359 Fly Rd",
    "sg:city":"East Syracuse",
    "sg:classifiers":[
        {
            "category":"Building & Trades",
            "subcategory":"Cleaning & Sanitation",
            "type":"Services"
        }
    ],
    "sg:phone":"+1 315 437 1746",
    "sg:postcode":"13057",
    "sg:province":"NY",
    "sg:tags":[
        "janitor"
    ],
    "wof:name":"Service Master Bldg Mntnc Inc",
    "wof:placetype":"venue"
},
  "geometry": {"coordinates":[-76.05846099999999,43.079252],"type":"Point"}
}