{
  "type": "Feature",
  "properties": {
    "addr:full":"2551 Harlem Rd Buffalo NY 14225",
    "addr:housenumber":"2551",
    "addr:postcode":"14225",
    "addr:street":"Harlem Rd",
    "iso:country":"US",
    "sg:address":"2551 Harlem Rd",
    "sg:city":"Buffalo",
    "sg:classifiers":[
        {
            "category":"Food & Beverages",
            "subcategory":"Liquor & Beverages",
            "type":"Retail Goods"
        }
    ],
    "sg:phone":"+1 716 897 0665",
    "sg:postcode":"14225",
    "sg:province":"NY",
    "sg:tags":[
        "beer",
        "wine",
        "spirit",
        "alcoholic"
    ],
    "wof:name":"Town Park Liquor",
    "wof:placetype":"venue"
},
  "geometry": {"coordinates":[-78.78449999999999,42.9128],"type":"Point"}
}