{
  "type": "Feature",
  "properties": {
    "iso:country":"US",
    "sg:address":"150 Myrtle Ave",
    "sg:city":"Albany",
    "sg:phone":"+1 518 477 5755",
    "sg:postcode":"12202",
    "sg:province":"NY",
    "sg:tags":[
        "oil"
    ],
    "wof:name":"Sullivan Fuel Svc",
    "wof:placetype":"venue"
},
  "geometry": {"coordinates":[-73.76667999999999,42.648916],"type":"Point"}
}