{
  "type": "Feature",
  "properties": {
    "iso:country":"US",
    "sg:address":"587 Seneca Ave",
    "sg:city":"Ridgewood",
    "sg:classifiers":[
        {
            "category":"Real Estate",
            "subcategory":"Real Estate Services",
            "type":"Services"
        }
    ],
    "sg:phone":"+1 718 381 4333",
    "sg:postcode":"11385",
    "sg:province":"NY",
    "wof:name":"Ficano Stephen Rl Est",
    "wof:placetype":"venue"
},
  "geometry": {"coordinates":[-73.910301,40.7043],"type":"Point"}
}