{
  "type": "Feature",
  "properties": {
    "addr:full":"948 Kenmore Ave Buffalo NY 14216",
    "addr:housenumber":"948",
    "addr:postcode":"14216",
    "addr:street":"Kenmore Ave",
    "iso:country":"US",
    "sg:address":"948 Kenmore Ave",
    "sg:city":"Buffalo",
    "sg:classifiers":[
        {
            "category":"Personal",
            "subcategory":"Barber",
            "type":"Services"
        }
    ],
    "sg:phone":"+1 716 876 1978",
    "sg:postcode":"14216",
    "sg:province":"NY",
    "wof:name":"George's Barber Shop",
    "wof:placetype":"venue"
},
  "geometry": {"coordinates":[-78.852898,42.958698],"type":"Point"}
}