{
  "type": "Feature",
  "properties": {
    "addr:full":"263 Canal St New York NY 10013",
    "addr:housenumber":"263",
    "addr:postcode":"10013",
    "addr:street":"Canal St",
    "iso:country":"US",
    "sg:address":"263 Canal St",
    "sg:city":"New York",
    "sg:classifiers":[
        {
            "category":"Shopping",
            "subcategory":"Discount & Variety Stores",
            "type":"Retail Goods"
        }
    ],
    "sg:phone":"+1 212 334 8250",
    "sg:postcode":"10013",
    "sg:province":"NY",
    "sg:tags":[
        "post",
        "trading"
    ],
    "wof:name":"Hao Hong Trading Co",
    "wof:placetype":"venue"
},
  "geometry": {"coordinates":[-74.00084699999999,40.718661],"type":"Point"}
}