{
  "type": "Feature",
  "properties": {
    "iso:country":"US",
    "sg:address":"797 Main St",
    "sg:city":"Poughkeepsie",
    "sg:classifiers":[
        {
            "category":"Autos & Motor Vehicles",
            "subcategory":"Automobile Sales",
            "type":"Retail Goods"
        }
    ],
    "sg:phone":"+1   ",
    "sg:postcode":"12603",
    "sg:province":"NY",
    "sg:tags":[
        "used"
    ],
    "wof:name":"R & R Auto Sales",
    "wof:placetype":"venue"
},
  "geometry": {"coordinates":[-73.89948099999999,41.696027],"type":"Point"}
}