{
  "type": "Feature",
  "properties": {
    "addr:full":"5212 5th Ave Brooklyn NY 11220",
    "addr:housenumber":"5212",
    "addr:postcode":"11220",
    "addr:street":"5Th Ave",
    "iso:country":"US",
    "sg:address":"5212 5th Ave",
    "sg:city":"Brooklyn",
    "sg:classifiers":[
        {
            "category":"Restaurant",
            "type":"Food & Drink"
        }
    ],
    "sg:menulink":"http://www.allmenus.com/ny/brooklyn/169834-burger-king/menu/",
    "sg:phone":"+1 718 765 0844",
    "sg:postcode":"11220",
    "sg:province":"NY",
    "sg:tags":[
        "burger",
        "american"
    ],
    "wof:name":"Burger King",
    "wof:placetype":"venue"
},
  "geometry": {"coordinates":[-74.011551,40.643914],"type":"Point"}
}