{
  "type": "Feature",
  "properties": {
    "addr:full":"4 Cranbrook Dr Centerport NY 11721",
    "addr:housenumber":"4",
    "addr:postcode":"11721",
    "addr:street":"Cranbrook Dr",
    "iso:country":"US",
    "sg:address":"4 Cranbrook Dr",
    "sg:city":"Centerport",
    "sg:classifiers":[
        {
            "category":"Building & Trades",
            "subcategory":"Construction",
            "type":"Services"
        }
    ],
    "sg:phone":"+1 631 266 2263",
    "sg:postcode":"11721",
    "sg:province":"NY",
    "sg:tags":[
        "floor",
        "laying",
        "contractor"
    ],
    "wof:name":"Ago Productions",
    "wof:placetype":"venue"
},
  "geometry": {"coordinates":[-73.37526699999999,40.881902],"type":"Point"}
}