{
  "type": "Feature",
  "properties": {
    "iso:country":"US",
    "sg:address":"322 S Caroline St",
    "sg:city":"Herkimer",
    "sg:classifiers":[
        {
            "category":"Food & Beverages",
            "subcategory":"Liquor & Beverages",
            "type":"Retail Goods"
        }
    ],
    "sg:phone":"+1 315 866 6800",
    "sg:postcode":"13350",
    "sg:province":"NY",
    "wof:name":"Discount Liquor",
    "wof:placetype":"venue"
},
  "geometry": {"coordinates":[-74.991578,43.020027],"type":"Point"}
}