{
  "type": "Feature",
  "properties": {
    "iso:country":"US",
    "sg:address":"700 Main St Ste B",
    "sg:city":"Islip",
    "sg:classifiers":[
        {
            "category":"Personal",
            "subcategory":"Massage",
            "type":"Services"
        },
        {
            "category":"Sports & Exercise",
            "subcategory":"Gym",
            "type":"Entertainment"
        },
        {
            "category":"Personal",
            "subcategory":"Skin Care",
            "type":"Services"
        }
    ],
    "sg:phone":"+1 631 859 3900",
    "sg:postcode":"11751",
    "sg:province":"NY",
    "sg:tags":[
        "pilate"
    ],
    "sg:website":"www.amethystrosehealing.com",
    "wof:name":"Amethyst Rose - Massage Healing Skin Care & Pilates",
    "wof:placetype":"venue"
},
  "geometry": {"coordinates":[-73.209431,40.729678],"type":"Point"}
}