{
  "type": "Feature",
  "properties": {
    "addr:full":"909 Union St Brooklyn NY 11215",
    "addr:housenumber":"909",
    "addr:postcode":"11215",
    "addr:street":"Union St",
    "iso:country":"US",
    "sg:address":"909 Union St",
    "sg:city":"Brooklyn",
    "sg:classifiers":[
        {
            "category":"Banks & Credit Unions",
            "subcategory":"Investment Brokerage",
            "type":"Services"
        }
    ],
    "sg:phone":"+1 718 622 1560",
    "sg:postcode":"11215",
    "sg:province":"NY",
    "sg:tags":[
        "investing"
    ],
    "wof:name":"Fireside Financial Planning Inc",
    "wof:placetype":"venue"
},
  "geometry": {"coordinates":[-73.973297,40.673599],"type":"Point"}
}