{
  "type": "Feature",
  "properties": {
    "addr:full":"1632 Coney Island Ave Brooklyn NY 11230",
    "addr:housenumber":"1632",
    "addr:postcode":"11230",
    "addr:street":"Coney Island Ave",
    "iso:country":"US",
    "sg:address":"1632 Coney Island Ave",
    "sg:city":"Brooklyn",
    "sg:classifiers":[
        {
            "category":"Shopping",
            "subcategory":"Clothing, Apparel, & Fashions",
            "type":"Retail Goods"
        }
    ],
    "sg:phone":"+1 718 252 2397",
    "sg:postcode":"11230",
    "sg:province":"NY",
    "wof:name":"VIP Clothers",
    "wof:placetype":"venue"
},
  "geometry": {"coordinates":[-73.963933,40.617907],"type":"Point"}
}