{
  "type": "Feature",
  "properties": {
    "addr:full":"86 Lincoln Ave Wyandanch NY 11798",
    "addr:housenumber":"86",
    "addr:postcode":"11798",
    "addr:street":"Lincoln Ave",
    "iso:country":"US",
    "sg:address":"86 Lincoln Ave",
    "sg:city":"Wyandanch",
    "sg:classifiers":[
        {
            "category":"Professional",
            "type":"Services"
        }
    ],
    "sg:phone":"+1 518 671 6492",
    "sg:postcode":"11798",
    "sg:province":"NY",
    "sg:tags":[
        "establishment"
    ],
    "wof:name":"Negron Myiesha",
    "wof:placetype":"venue"
},
  "geometry": {"coordinates":[-73.36960999999999,40.741156],"type":"Point"}
}