{
  "type": "Feature",
  "properties": {
    "iso:country":"US",
    "sg:address":"77 N Broadway",
    "sg:city":"Hicksville",
    "sg:classifiers":[
        {
            "category":"Travel",
            "subcategory":"Travel Agent",
            "type":"Entertainment"
        }
    ],
    "sg:phone":"+1 516 433 0014",
    "sg:postcode":"11801",
    "sg:province":"NY",
    "sg:tags":[
        "agency",
        "bureau"
    ],
    "wof:name":"Peak Time Travel",
    "wof:placetype":"venue"
},
  "geometry": {"coordinates":[-73.531532,40.780879],"type":"Point"}
}