{
  "type": "Feature",
  "properties": {
    "addr:full":"436 Main St Arcade NY 14009",
    "addr:housenumber":"436",
    "addr:postcode":"14009",
    "addr:street":"Main St",
    "iso:country":"US",
    "sg:address":"436 Main St",
    "sg:city":"Arcade",
    "sg:classifiers":[
        {
            "category":"Food & Beverages",
            "subcategory":"Liquor & Beverages",
            "type":"Retail Goods"
        }
    ],
    "sg:phone":"+1 585 492 1650",
    "sg:postcode":"14009",
    "sg:province":"NY",
    "wof:name":"Heppner's Liquor Store",
    "wof:placetype":"venue"
},
  "geometry": {"coordinates":[-78.42443400000001,42.533832],"type":"Point"}
}