{
  "type": "Feature",
  "properties": {
    "iso:country":"US",
    "sg:address":"54 W 39th St",
    "sg:city":"New York",
    "sg:classifiers":[
        {
            "category":"Real Estate",
            "subcategory":"Architect",
            "type":"Services"
        }
    ],
    "sg:phone":"+1 212 278 0138",
    "sg:postcode":"10018",
    "sg:province":"NY",
    "wof:name":"Frank Repas Architecture Pllc",
    "wof:placetype":"venue"
},
  "geometry": {"coordinates":[-73.984004,40.752181],"type":"Point"}
}