{
  "type": "Feature",
  "properties": {
    "addr:full":"1075 Northern Blvd Roslyn NY 11576",
    "addr:housenumber":"1075",
    "addr:postcode":"11576",
    "addr:street":"Northern Blvd",
    "iso:country":"US",
    "sg:address":"1075 Northern Blvd",
    "sg:city":"Roslyn",
    "sg:classifiers":[
        {
            "category":"Banks & Credit Unions",
            "subcategory":"Bank",
            "type":"Services"
        }
    ],
    "sg:phone":"+1 718 428 1803",
    "sg:postcode":"11576",
    "sg:province":"NY",
    "wof:name":"Dime Savings Bank of Williamsburgh",
    "wof:placetype":"venue"
},
  "geometry": {"coordinates":[-73.66300200000001,40.798801],"type":"Point"}
}