{
  "type": "Feature",
  "properties": {
    "addr:full":"1981 Marcus Ave New Hyde Park NY 11042",
    "addr:housenumber":"1981",
    "addr:postcode":"11042",
    "addr:street":"Marcus Ave",
    "iso:country":"US",
    "sg:address":"1981 Marcus Ave",
    "sg:city":"New Hyde Park",
    "sg:classifiers":[
        {
            "category":"Professional",
            "subcategory":"Accounting & Tax Preparation",
            "type":"Services"
        }
    ],
    "sg:phone":"+1   ",
    "sg:postcode":"11042",
    "sg:province":"NY",
    "wof:name":"Pipia Cohen & Co",
    "wof:placetype":"venue"
},
  "geometry": {"coordinates":[-73.691784,40.75718],"type":"Point"}
}