{
  "type": "Feature",
  "properties": {
    "iso:country":"US",
    "sg:address":"10 Brinkerhoff St",
    "sg:city":"Plattsburgh",
    "sg:classifiers":[
        {
            "category":"Government",
            "subcategory":"Police Station",
            "type":"Public Place"
        }
    ],
    "sg:phone":"+1 518 562 0156",
    "sg:postcode":"12901",
    "sg:province":"NY",
    "sg:tags":[
        "federal"
    ],
    "wof:name":"Federal Protective Svc",
    "wof:placetype":"venue"
},
  "geometry": {"coordinates":[-73.45337600000001,44.697161],"type":"Point"}
}