{
  "type": "Feature",
  "properties": {
    "iso:country":"US",
    "sg:address":"106 Columbia Tpke",
    "sg:city":"Rensselaer",
    "sg:classifiers":[
        {
            "category":"Autos & Motor Vehicles",
            "subcategory":"Automobile Sales",
            "type":"Retail Goods"
        }
    ],
    "sg:phone":"+1 518 443 2277",
    "sg:postcode":"12144",
    "sg:province":"NY",
    "sg:tags":[
        "used"
    ],
    "wof:name":"City View Auto Sales",
    "wof:placetype":"venue"
},
  "geometry": {"coordinates":[-73.738871,42.623521],"type":"Point"}
}