{
  "type": "Feature",
  "properties": {
    "addr:full":"835 Center Dr Baldwin NY 11510",
    "addr:housenumber":"835",
    "addr:postcode":"11510",
    "addr:street":"Center Dr",
    "iso:country":"US",
    "sg:address":"835 Center Dr",
    "sg:city":"Baldwin",
    "sg:classifiers":[
        {
            "category":"Freight",
            "type":"Transportation"
        }
    ],
    "sg:phone":"+1   ",
    "sg:postcode":"11510",
    "sg:province":"NY",
    "sg:tags":[
        "operator",
        "local",
        "trucking"
    ],
    "wof:name":"Hj Dillard Trucking Inc",
    "wof:placetype":"venue"
},
  "geometry": {"coordinates":[-73.609829,40.682251],"type":"Point"}
}