{
  "type": "Feature",
  "properties": {
    "addr:full":"Roosevelt Ave & Benham St Elmhurst NY 11373",
    "addr:postcode":"11373",
    "addr:street":"Roosevelt Ave & Benham St",
    "iso:country":"US",
    "sg:address":"Roosevelt Ave & Benham St",
    "sg:city":"Elmhurst",
    "sg:classifiers":[
        {
            "category":"Food Court",
            "type":"Food & Drink"
        },
        {
            "category":"Restaurant",
            "type":"Food & Drink"
        }
    ],
    "sg:phone":"+1 917 757 1633",
    "sg:postcode":"11373",
    "sg:province":"NY",
    "sg:tags":[
        "mexican",
        "stand"
    ],
    "wof:name":"Tia Julia Taco Truck",
    "wof:placetype":"venue"
},
  "geometry": {"coordinates":[-73.87556499999999,40.74854],"type":"Point"}
}