{
  "type": "Feature",
  "properties": {
    "addr:full":"21 Bonnie Hollow Ln Montrose NY 10548",
    "addr:housenumber":"21",
    "addr:postcode":"10548",
    "addr:street":"Bonnie Hollow Ln",
    "iso:country":"US",
    "sg:address":"21 Bonnie Hollow Ln",
    "sg:city":"Montrose",
    "sg:classifiers":[
        {
            "category":"Building & Trades",
            "subcategory":"Construction",
            "type":"Services"
        }
    ],
    "sg:phone":"+1 914 739 8800",
    "sg:postcode":"10548",
    "sg:province":"NY",
    "sg:tags":[
        "home",
        "improvement"
    ],
    "wof:name":"Dengler & Sons Home Imprvmt",
    "wof:placetype":"venue"
},
  "geometry": {"coordinates":[-73.93521200000001,41.243474],"type":"Point"}
}