{
  "type": "Feature",
  "properties": {
    "addr:full":"160 Madison Avenue 6th Floor New York NY 10016",
    "addr:housenumber":"160;6th floor",
    "addr:postcode":"10016",
    "addr:street":"Madison Avenue",
    "iso:country":"US",
    "sg:address":"160 Madison Avenue 6th Floor",
    "sg:city":"New York",
    "sg:classifiers":[
        {
            "category":"Professional",
            "subcategory":"Computer Services",
            "type":"Services"
        }
    ],
    "sg:postcode":"10016",
    "sg:province":"NY",
    "sg:tags":[
        "onlinetravel",
        "tourbooking",
        "travelpackages",
        "vacations",
        "travel-agents"
    ],
    "sg:website":"http://www.tripology.com",
    "wof:name":"Tripology",
    "wof:placetype":"venue"
},
  "geometry": {"coordinates":[-73.983661,40.746858],"type":"Point"}
}