{
  "type": "Feature",
  "properties": {
    "iso:country":"US",
    "sg:address":"644 Ridge Rd",
    "sg:city":"Webster",
    "sg:classifiers":[
        {
            "category":"Autos & Motor Vehicles",
            "subcategory":"Automobile Sales",
            "type":"Retail Goods"
        },
        {
            "category":"Retail",
            "subcategory":"Auto Repair",
            "type":"Services"
        }
    ],
    "sg:phone":"+1 585 787 1110",
    "sg:postcode":"14580",
    "sg:province":"NY",
    "sg:tags":[
        "repairing",
        "used"
    ],
    "wof:name":"International Automotive Inc",
    "wof:placetype":"venue"
},
  "geometry": {"coordinates":[-77.49541600000001,43.20464],"type":"Point"}
}