{
  "type": "Feature",
  "properties": {
    "addr:full":"117 Brook Ave Deer Park NY 11729",
    "addr:housenumber":"117",
    "addr:postcode":"11729",
    "addr:street":"Brook Ave",
    "iso:country":"US",
    "sg:address":"117 Brook Ave",
    "sg:city":"Deer Park",
    "sg:classifiers":[
        {
            "category":"Manufacturing",
            "subcategory":"Retail Goods",
            "type":"Manufacturing & Wholesale Goods"
        }
    ],
    "sg:phone":"+1 631 586 4400",
    "sg:postcode":"11729",
    "sg:province":"NY",
    "sg:tags":[
        "manufacturer"
    ],
    "wof:name":"Gombert Organization",
    "wof:placetype":"venue"
},
  "geometry": {"coordinates":[-73.30615299999999,40.748818],"type":"Point"}
}