{
  "type": "Feature",
  "properties": {
    "iso:country":"US",
    "sg:address":"20 Mystic Ln",
    "sg:city":"Clifton Park",
    "sg:classifiers":[
        {
            "category":"Personal",
            "type":"Services"
        }
    ],
    "sg:phone":"+1 518 783 5756",
    "sg:postcode":"12065",
    "sg:province":"NY",
    "wof:name":"Body Beautiful Inc",
    "wof:placetype":"venue"
},
  "geometry": {"coordinates":[-73.786871,42.822513],"type":"Point"}
}