{
  "type": "Feature",
  "properties": {
    "addr:full":"270 Pleasant View Dr Lancaster NY 14086",
    "addr:housenumber":"270",
    "addr:postcode":"14086",
    "addr:street":"Pleasant View Dr",
    "iso:country":"US",
    "sg:address":"270 Pleasant View Dr",
    "sg:city":"Lancaster",
    "sg:phone":"+1 716 683 7923",
    "sg:postcode":"14086",
    "sg:province":"NY",
    "sg:tags":[
        "equipment",
        "commercial"
    ],
    "wof:name":"J M Equipment Inc",
    "wof:placetype":"venue"
},
  "geometry": {"coordinates":[-78.650567,42.931985],"type":"Point"}
}