{
  "type": "Feature",
  "properties": {
    "addr:full":"45 W 47th St New York NY 10036",
    "addr:housenumber":"45",
    "addr:postcode":"10036",
    "addr:street":"W 47Th St",
    "iso:country":"US",
    "sg:address":"45 W 47th St",
    "sg:city":"New York",
    "sg:classifiers":[
        {
            "category":"Shopping",
            "subcategory":"Jewelry",
            "type":"Retail Goods"
        }
    ],
    "sg:phone":"+1 212 398 2299",
    "sg:postcode":"10036",
    "sg:province":"NY",
    "wof:name":"Yahalom Trading Co Inc",
    "wof:placetype":"venue"
},
  "geometry": {"coordinates":[-73.97994300000001,40.757395],"type":"Point"}
}