{
  "type": "Feature",
  "properties": {
    "addr:full":"367 White Oak Shade Rd New Canaan NY 06840",
    "addr:housenumber":"367",
    "addr:postcode":"06840",
    "addr:street":"White Oak Shade Rd",
    "iso:country":"US",
    "sg:address":"367 White Oak Shade Rd",
    "sg:city":"New Canaan",
    "sg:classifiers":[
        {
            "category":"Personal",
            "subcategory":"Barber",
            "type":"Services"
        }
    ],
    "sg:phone":"+1   ",
    "sg:postcode":"06840",
    "sg:province":"NY",
    "sg:tags":[
        "shop"
    ],
    "wof:name":"Albert Barber",
    "wof:placetype":"venue"
},
  "geometry": {"coordinates":[-73.473955,41.124063],"type":"Point"}
}