{
  "type": "Feature",
  "properties": {
    "addr:full":"2081 Coon Hill Rd Skaneateles NY 13152",
    "addr:housenumber":"2081",
    "addr:postcode":"13152",
    "addr:street":"Coon Hill Rd",
    "iso:country":"US",
    "sg:address":"2081 Coon Hill Rd",
    "sg:city":"Skaneateles",
    "sg:classifiers":[
        {
            "category":"Shopping",
            "subcategory":"Gifts & Souvenirs",
            "type":"Retail Goods"
        }
    ],
    "sg:phone":"+1   ",
    "sg:postcode":"13152",
    "sg:province":"NY",
    "sg:tags":[
        "merchandise"
    ],
    "wof:name":"Duck Blind",
    "wof:placetype":"venue"
},
  "geometry": {"coordinates":[-76.353865,42.918806],"type":"Point"}
}