{
  "type": "Feature",
  "properties": {
    "addr:full":"1460 Titus Ave Rochester NY 14622",
    "addr:housenumber":"1460",
    "addr:postcode":"14622",
    "addr:street":"Titus Ave",
    "iso:country":"US",
    "sg:address":"1460 Titus Ave",
    "sg:city":"Rochester",
    "sg:classifiers":[
        {
            "category":"Health Services",
            "subcategory":"Clinic",
            "type":"Services"
        }
    ],
    "sg:phone":"+1   ",
    "sg:postcode":"14622",
    "sg:province":"NY",
    "sg:tags":[
        "p",
        "hospital",
        "specialty",
        "outpatient"
    ],
    "wof:name":"Robert Insull PHD",
    "wof:placetype":"venue"
},
  "geometry": {"coordinates":[-77.577292,43.211287],"type":"Point"}
}