{
  "type": "Feature",
  "properties": {
    "addr:full":"5003 13th Avenue Brooklyn NY 11219",
    "addr:housenumber":"5003",
    "addr:postcode":"11219",
    "addr:street":"13Th Avenue",
    "iso:country":"US",
    "sg:address":"5003 13th Avenue",
    "sg:city":"Brooklyn",
    "sg:classifiers":[
        {
            "category":"Retail",
            "subcategory":"Portrait Studio",
            "type":"Services"
        },
        {
            "category":"Professional",
            "subcategory":"Art Services",
            "type":"Services"
        }
    ],
    "sg:phone":"+1 718 633 1846",
    "sg:postcode":"11219",
    "sg:province":"NY",
    "sg:tags":[
        "photographer",
        "photography",
        "store"
    ],
    "wof:name":"Eagle Photo",
    "wof:placetype":"venue"
},
  "geometry": {"coordinates":[-73.992712,40.634271],"type":"Point"}
}