{
  "type": "Feature",
  "properties": {
    "iso:country":"US",
    "sg:address":"1165 Leggett Avenue",
    "sg:city":"Bronx",
    "sg:classifiers":[
        {
            "category":"Autos & Motor Vehicles",
            "subcategory":"Auto Supplies",
            "type":"Retail Goods"
        }
    ],
    "sg:phone":"+1 718 893 1898",
    "sg:postcode":"10474",
    "sg:province":"NY",
    "sg:tags":[
        "tire"
    ],
    "wof:name":"Gannin Tire",
    "wof:placetype":"venue"
},
  "geometry": {"coordinates":[-73.894469,40.811645],"type":"Point"}
}