{
  "type": "Feature",
  "properties": {
    "addr:full":"29 Old Dock Rd Yaphank NY 11980",
    "addr:housenumber":"29",
    "addr:postcode":"11980",
    "addr:street":"Old Dock Rd",
    "iso:country":"US",
    "sg:address":"29 Old Dock Rd",
    "sg:city":"Yaphank",
    "sg:classifiers":[
        {
            "category":"Shopping",
            "subcategory":"Discount & Variety Stores",
            "type":"Retail Goods"
        }
    ],
    "sg:phone":"+1 631 205 5560",
    "sg:postcode":"11980",
    "sg:province":"NY",
    "sg:tags":[
        "merchandise",
        "general"
    ],
    "sg:website":"www.circuitsales.com",
    "wof:name":"Circuit Sales Intl",
    "wof:placetype":"venue"
},
  "geometry": {"coordinates":[-72.943978,40.808858],"type":"Point"}
}