{
  "type": "Feature",
  "properties": {
    "addr:full":"620 Park Pl Long Beach NY 11561",
    "addr:housenumber":"620",
    "addr:postcode":"11561",
    "addr:street":"Park Pl",
    "iso:country":"US",
    "sg:address":"620 Park Pl",
    "sg:city":"Long Beach",
    "sg:classifiers":[
        {
            "category":"Organizations",
            "subcategory":"Religious Organization",
            "type":"Services"
        }
    ],
    "sg:phone":"+1   ",
    "sg:postcode":"11561",
    "sg:province":"NY",
    "wof:name":"Christian Light Bapt Church",
    "wof:placetype":"venue"
},
  "geometry": {"coordinates":[-73.664255,40.592],"type":"Point"}
}