{
  "type": "Feature",
  "properties": {
    "iso:country":"US",
    "sg:address":"35 E Main St",
    "sg:city":"Walden",
    "sg:classifiers":[
        {
            "category":"Education",
            "subcategory":"Dance Studio",
            "type":"Public Place"
        }
    ],
    "sg:phone":"+1 845 778 2478",
    "sg:postcode":"12586",
    "sg:province":"NY",
    "sg:tags":[
        "school"
    ],
    "wof:name":"Hudson Vly Cnservtry Fine Arts",
    "wof:placetype":"venue"
},
  "geometry": {"coordinates":[-74.185867,41.560735],"type":"Point"}
}