{
  "type": "Feature",
  "properties": {
    "addr:full":"8315 116th St Richmond Hill NY 11418",
    "addr:housenumber":"8315",
    "addr:postcode":"11418",
    "addr:street":"116Th St",
    "iso:country":"US",
    "sg:address":"8315 116th St",
    "sg:city":"Richmond Hill",
    "sg:classifiers":[
        {
            "category":"Real Estate",
            "subcategory":"Real Estate Services",
            "type":"Services"
        },
        {
            "category":"Real Estate",
            "subcategory":"Real Estate Operator",
            "type":"Services"
        }
    ],
    "sg:phone":"+1 718 441 4963",
    "sg:postcode":"11418",
    "sg:province":"NY",
    "sg:tags":[
        "apartment",
        "property",
        "management"
    ],
    "wof:name":"83-15-19 116st Apt Corp",
    "wof:placetype":"venue"
},
  "geometry": {"coordinates":[-73.836197,40.7061],"type":"Point"}
}