{
  "type": "Feature",
  "properties": {
    "addr:full":"925 Fairport Rd East Rochester NY 14445",
    "addr:housenumber":"925",
    "addr:postcode":"14445",
    "addr:street":"Fairport Rd",
    "iso:country":"US",
    "sg:address":"925 Fairport Rd",
    "sg:city":"East Rochester",
    "sg:classifiers":[
        {
            "category":"Retail",
            "subcategory":"Portrait Studio",
            "type":"Services"
        }
    ],
    "sg:phone":"+1   ",
    "sg:postcode":"14445",
    "sg:province":"NY",
    "sg:tags":[
        "photo"
    ],
    "wof:name":"Vitelli Photography",
    "wof:placetype":"venue"
},
  "geometry": {"coordinates":[-77.47848999999999,43.102306],"type":"Point"}
}