{
  "type": "Feature",
  "properties": {
    "addr:full":"73 Oleander Dr Northport NY 11768",
    "addr:housenumber":"73",
    "addr:postcode":"11768",
    "addr:street":"Oleander Dr",
    "iso:country":"US",
    "sg:address":"73 Oleander Dr",
    "sg:city":"Northport",
    "sg:classifiers":[
        {
            "category":"Professional",
            "subcategory":"Management & Consulting",
            "type":"Services"
        }
    ],
    "sg:phone":"+1   ",
    "sg:postcode":"11768",
    "sg:province":"NY",
    "sg:tags":[
        "business"
    ],
    "wof:name":"Fj Consulting Ltd",
    "wof:placetype":"venue"
},
  "geometry": {"coordinates":[-73.35037699999999,40.879774],"type":"Point"}
}