{
  "type": "Feature",
  "properties": {
    "addr:full":"1910 Pelham Pkwy S Bronx NY 10461",
    "addr:housenumber":"1910",
    "addr:postcode":"10461",
    "addr:street":"Pelham Pkwy S",
    "iso:country":"US",
    "sg:address":"1910 Pelham Pkwy S",
    "sg:city":"Bronx",
    "sg:classifiers":[
        {
            "category":"Organizations",
            "subcategory":"Professional Association",
            "type":"Services"
        }
    ],
    "sg:phone":"+1 718 829 9680",
    "sg:postcode":"10461",
    "sg:province":"NY",
    "wof:name":"Parkway Owners",
    "wof:placetype":"venue"
},
  "geometry": {"coordinates":[-73.82911,40.855595],"type":"Point"}
}