{
  "type": "Feature",
  "properties": {
    "iso:country":"US",
    "sg:address":"4512 47th St",
    "sg:city":"Sunnyside",
    "sg:classifiers":[
        {
            "category":"Restaurant",
            "type":"Food & Drink"
        }
    ],
    "sg:menulink":"http://www.allmenus.com/ny/queens/38396-tasty-thai/menu/",
    "sg:phone":"+1 718 391 0180",
    "sg:postcode":"11104",
    "sg:province":"NY",
    "sg:tags":[
        "thai",
        "asian"
    ],
    "wof:name":"Tasty Thai",
    "wof:placetype":"venue"
},
  "geometry": {"coordinates":[-73.917858,40.742538],"type":"Point"}
}