{
  "type": "Feature",
  "properties": {
    "iso:country":"US",
    "sg:address":"504 Delaware Ave",
    "sg:city":"Delmar",
    "sg:classifiers":[
        {
            "category":"Professional",
            "subcategory":"Computer Services",
            "type":"Services"
        }
    ],
    "sg:phone":"+1   ",
    "sg:postcode":"12054",
    "sg:province":"NY",
    "sg:tags":[
        "datum"
    ],
    "sg:website":"www.518webdesign.com",
    "wof:name":"Web Design",
    "wof:placetype":"venue"
},
  "geometry": {"coordinates":[-73.845406,42.617698],"type":"Point"}
}