{
  "type": "Feature",
  "properties": {
    "iso:country":"US",
    "sg:address":"139 Croton Ave",
    "sg:city":"Ossining",
    "sg:classifiers":[
        {
            "category":"Personal",
            "subcategory":"Beauty Salon",
            "type":"Services"
        }
    ],
    "sg:phone":"+1 914 944 3155",
    "sg:postcode":"10562",
    "sg:province":"NY",
    "sg:tags":[
        "nail",
        "manicuring"
    ],
    "wof:name":"Queen Nails",
    "wof:placetype":"venue"
},
  "geometry": {"coordinates":[-73.85230300000001,41.167198],"type":"Point"}
}