{
  "type": "Feature",
  "properties": {
    "addr:full":"319 Columbia Street Brooklyn NY 11231",
    "addr:housenumber":"319",
    "addr:postcode":"11231",
    "addr:street":"Columbia Street",
    "iso:country":"US",
    "sg:address":"319 Columbia Street",
    "sg:city":"Brooklyn",
    "sg:classifiers":[
        {
            "category":"Deli",
            "type":"Food & Drink"
        },
        {
            "category":"Restaurant",
            "type":"Food & Drink"
        }
    ],
    "sg:phone":"+1 718 797 5571",
    "sg:postcode":"11231",
    "sg:province":"NY",
    "sg:tags":[
        "greek",
        "mediterranean"
    ],
    "wof:name":"Brother Cafe and Deli",
    "wof:placetype":"venue"
},
  "geometry": {"coordinates":[-74.004216,40.681199],"type":"Point"}
}