{
  "type": "Feature",
  "properties": {
    "addr:full":"19 West 34th St. Suite 1018 New York NY 10001",
    "addr:housenumber":"19",
    "addr:postcode":"10001",
    "addr:street":"West 34Th St. Suite 1018",
    "iso:country":"US",
    "sg:address":"19 West 34th St. Suite 1018",
    "sg:city":"New York",
    "sg:classifiers":[
        {
            "category":"Professional",
            "subcategory":"Computer Services",
            "type":"Services"
        }
    ],
    "sg:phone":"+1 646 755 9885",
    "sg:postcode":"10001",
    "sg:province":"NY",
    "sg:tags":[
        "ecommerce",
        "social",
        "commerce",
        "sell",
        "sales",
        "easy",
        "tinypayme",
        "tinypay",
        "tiny",
        "pay"
    ],
    "sg:website":"http://tinypay.me",
    "wof:name":"Tinypay.me",
    "wof:placetype":"venue"
},
  "geometry": {"coordinates":[-73.987296,40.749593],"type":"Point"}
}