{
  "type": "Feature",
  "properties": {
    "addr:full":"3411 Wayne Ave Bronx NY 10467",
    "addr:housenumber":"3411",
    "addr:postcode":"10467",
    "addr:street":"Wayne Ave",
    "iso:country":"US",
    "sg:address":"3411 Wayne Ave",
    "sg:city":"Bronx",
    "sg:classifiers":[
        {
            "category":"Organizations",
            "subcategory":"Professional Association",
            "type":"Services"
        }
    ],
    "sg:phone":"+1 718 231 5482",
    "sg:postcode":"10467",
    "sg:province":"NY",
    "wof:name":"Bronx Community Health Center",
    "wof:placetype":"venue"
},
  "geometry": {"coordinates":[-73.877719,40.880551],"type":"Point"}
}