{
  "type": "Feature",
  "properties": {
    "iso:country":"US",
    "sg:address":"70 S Bayles Ave",
    "sg:city":"Port Washington",
    "sg:classifiers":[
        {
            "category":"Manufacturing",
            "subcategory":"Retail Goods",
            "type":"Manufacturing & Wholesale Goods"
        }
    ],
    "sg:phone":"+1 516 944 2481",
    "sg:postcode":"11050",
    "sg:province":"NY",
    "sg:tags":[
        "manufacturer"
    ],
    "wof:name":"Brower Industries Inc",
    "wof:placetype":"venue"
},
  "geometry": {"coordinates":[-73.68552699999999,40.825327],"type":"Point"}
}