{
  "type": "Feature",
  "properties": {
    "addr:full":"1927 Slaterville Rd Ithaca NY 14850",
    "addr:housenumber":"1927",
    "addr:postcode":"14850",
    "addr:street":"Slaterville Rd",
    "iso:country":"US",
    "sg:address":"1927 Slaterville Rd",
    "sg:city":"Ithaca",
    "sg:classifiers":[
        {
            "category":"Utilities",
            "subcategory":"Telephone",
            "type":"Services"
        }
    ],
    "sg:phone":"+1   ",
    "sg:postcode":"14850",
    "sg:province":"NY",
    "sg:tags":[
        "communications"
    ],
    "wof:name":"Digital Flash",
    "wof:placetype":"venue"
},
  "geometry": {"coordinates":[-76.421537,42.401245],"type":"Point"}
}