{
  "type": "Feature",
  "properties": {
    "iso:country":"US",
    "sg:address":"590 N State Rd",
    "sg:city":"Briarcliff Manor",
    "sg:classifiers":[
        {
            "category":"Animal Shelter",
            "type":"Public Place"
        },
        {
            "category":"Shopping",
            "subcategory":"Pets & Pet Supplies",
            "type":"Retail Goods"
        }
    ],
    "sg:phone":"+1 914 941 2894",
    "sg:postcode":"10510",
    "sg:province":"NY",
    "sg:tags":[
        "store"
    ],
    "wof:name":"Simpson Spay Neuter Clinic",
    "wof:placetype":"venue"
},
  "geometry": {"coordinates":[-73.816002,41.1716],"type":"Point"}
}