{
  "type": "Feature",
  "properties": {
    "addr:full":"93 Saint Edwards St Brooklyn NY 11205",
    "addr:housenumber":"93",
    "addr:postcode":"11205",
    "addr:street":"Saint Edwards St",
    "iso:country":"US",
    "sg:address":"93 Saint Edwards St",
    "sg:city":"Brooklyn",
    "sg:classifiers":[
        {
            "category":"Education",
            "subcategory":"Library",
            "type":"Public Place"
        }
    ],
    "sg:phone":"+1 718 855 1508",
    "sg:postcode":"11205",
    "sg:province":"NY",
    "wof:name":"Walt Whitman",
    "wof:placetype":"venue"
},
  "geometry": {"coordinates":[-73.977988,40.694607],"type":"Point"}
}