{
  "type": "Feature",
  "properties": {
    "addr:full":"71 Boss St Bolivar NY 14715",
    "addr:housenumber":"71",
    "addr:postcode":"14715",
    "addr:street":"Boss St Bolivar",
    "iso:country":"US",
    "sg:address":"71 Boss St",
    "sg:city":"Bolivar",
    "sg:classifiers":[
        {
            "category":"Education",
            "subcategory":"Library",
            "type":"Public Place"
        }
    ],
    "sg:phone":"+1 585 928 2648",
    "sg:postcode":"14715",
    "sg:province":"NY",
    "wof:name":"Hertiage Flame Inc",
    "wof:placetype":"venue"
},
  "geometry": {"coordinates":[-78.16986799999999,42.066908],"type":"Point"}
}