{
  "type": "Feature",
  "properties": {
    "iso:country":"US",
    "sg:address":"1717 Motor Pkwy",
    "sg:city":"Hauppauge",
    "sg:classifiers":[
        {
            "category":"Shopping",
            "subcategory":"Florist",
            "type":"Retail Goods"
        }
    ],
    "sg:phone":"+1 631 234 3222",
    "sg:postcode":"11788",
    "sg:province":"NY",
    "wof:name":"Flowers & Gifts At Wyndam Windwatch",
    "wof:placetype":"venue"
},
  "geometry": {"coordinates":[-73.1698,40.813499],"type":"Point"}
}