{
  "type": "Feature",
  "properties": {
    "addr:full":"70 Santa Barbara Dr Plainview NY 11803",
    "addr:housenumber":"70",
    "addr:postcode":"11803",
    "addr:street":"Santa Barbara Dr",
    "iso:country":"US",
    "sg:address":"70 Santa Barbara Dr",
    "sg:city":"Plainview",
    "sg:classifiers":[
        {
            "category":"Education",
            "subcategory":"Junior College",
            "type":"Public Place"
        }
    ],
    "sg:phone":"+1 718 304 7643",
    "sg:postcode":"11803",
    "sg:province":"NY",
    "sg:tags":[
        "doll"
    ],
    "wof:name":"Jailbreak Toys, Inc.",
    "wof:placetype":"venue"
},
  "geometry": {"coordinates":[-73.461654,40.774393],"type":"Point"}
}