{
  "type": "Feature",
  "properties": {
    "iso:country":"US",
    "sg:address":"1033 Erie Blvd",
    "sg:city":"Schenectady",
    "sg:classifiers":[
        {
            "category":"Food & Beverages",
            "subcategory":"Groceries & Convenience Stores",
            "type":"Retail Goods"
        }
    ],
    "sg:phone":"+1 518 377 6951",
    "sg:postcode":"12305",
    "sg:province":"NY",
    "sg:website":"www.stewartsicecream.com",
    "wof:name":"Stewart's Shop",
    "wof:placetype":"venue"
},
  "geometry": {"coordinates":[-73.940293,42.817861],"type":"Point"}
}