{
  "type": "Feature",
  "properties": {
    "iso:country":"US",
    "sg:address":"3904 Abbott Rd",
    "sg:city":"Orchard Park",
    "sg:classifiers":[
        {
            "category":"Wholesale",
            "subcategory":"Apparel",
            "type":"Manufacturing & Wholesale Goods"
        }
    ],
    "sg:phone":"+1 716 648 3432",
    "sg:postcode":"14127",
    "sg:province":"NY",
    "sg:tags":[
        "clothing"
    ],
    "wof:name":"Debbie McDonell",
    "wof:placetype":"venue"
},
  "geometry": {"coordinates":[-78.79006099999999,42.772837],"type":"Point"}
}