{
  "type": "Feature",
  "properties": {
    "addr:full":"111 Broadway Rm 1103 New York NY 10006",
    "addr:housenumber":"111;1103",
    "addr:postcode":"10006",
    "addr:street":"Broadway Rm",
    "iso:country":"US",
    "sg:address":"111 Broadway Rm 1103",
    "sg:city":"New York",
    "sg:classifiers":[
        {
            "category":"Professional",
            "subcategory":"Lawyer & Legal Services",
            "type":"Services"
        }
    ],
    "sg:phone":"+1 212 343 1481",
    "sg:postcode":"10006",
    "sg:province":"NY",
    "wof:name":"Associates Richard Yellen",
    "wof:placetype":"venue"
},
  "geometry": {"coordinates":[-74.13063,40.7085],"type":"Point"}
}