{
  "type": "Feature",
  "properties": {
    "addr:full":"156 W 56th St Ste 903 New York NY 10019",
    "addr:housenumber":"156;903",
    "addr:postcode":"10019",
    "addr:street":"W 56Th St Ste",
    "iso:country":"US",
    "sg:address":"156 W 56th St Ste 903",
    "sg:city":"New York",
    "sg:classifiers":[
        {
            "category":"Communications",
            "subcategory":"Radio Station",
            "type":"Services"
        }
    ],
    "sg:phone":"+1 212 265 5700",
    "sg:postcode":"10019",
    "sg:province":"NY",
    "sg:website":"www.npb.com",
    "wof:name":"National Public Broadcasting",
    "wof:placetype":"venue"
},
  "geometry": {"coordinates":[-73.97968400000001,40.764329],"type":"Point"}
}