{
  "type": "Feature",
  "properties": {
    "addr:full":"3390 Co Rte 28 Watkins Glen NY 14891",
    "addr:housenumber":"3390",
    "addr:postcode":"14891",
    "addr:street":"Co Rte 28",
    "iso:country":"US",
    "sg:address":"3390 Co Rte 28",
    "sg:city":"Watkins Glen",
    "sg:classifiers":[
        {
            "category":"Travel",
            "subcategory":"Hotels & Motels",
            "type":"Entertainment"
        }
    ],
    "sg:phone":"+1 607 535 5437",
    "sg:postcode":"14891",
    "sg:province":"NY",
    "sg:tags":[
        "breakfast",
        "accommodation",
        "bed"
    ],
    "wof:name":"Manor Bed & Breakfast Castel",
    "wof:placetype":"venue"
},
  "geometry": {"coordinates":[-76.906333,42.398494],"type":"Point"}
}