{
  "type": "Feature",
  "properties": {
    "iso:country":"US",
    "sg:address":"855 E 233rd St",
    "sg:city":"Bronx",
    "sg:classifiers":[
        {
            "category":"Organizations",
            "subcategory":"Religious Organization",
            "type":"Services"
        }
    ],
    "sg:phone":"+1 718 994 5648",
    "sg:postcode":"10466",
    "sg:province":"NY",
    "sg:tags":[
        "clergy"
    ],
    "wof:name":"Carman I Garcia",
    "wof:placetype":"venue"
},
  "geometry": {"coordinates":[-73.853827,40.892392],"type":"Point"}
}