{
  "type": "Feature",
  "properties": {
    "iso:country":"US",
    "sg:address":"925 Montauk Hwy",
    "sg:city":"Bayport",
    "sg:classifiers":[
        {
            "category":"Banks & Credit Unions",
            "subcategory":"Bank",
            "type":"Services"
        }
    ],
    "sg:phone":"+1 631 472 2201",
    "sg:postcode":"11705",
    "sg:province":"NY",
    "sg:website":"www.chase.com",
    "wof:name":"Chase",
    "wof:placetype":"venue"
},
  "geometry": {"coordinates":[-73.702901,40.748693],"type":"Point"}
}