{
  "type": "Feature",
  "properties": {
    "iso:country":"US",
    "sg:address":"200 N Water St",
    "sg:city":"Peekskill",
    "sg:classifiers":[
        {
            "category":"Wholesale",
            "subcategory":"Apparel",
            "type":"Manufacturing & Wholesale Goods"
        }
    ],
    "sg:phone":"+1 914 739 7410",
    "sg:postcode":"10566",
    "sg:province":"NY",
    "sg:tags":[
        "umbrella"
    ],
    "sg:website":"www.strombergbrand.com",
    "wof:name":"Hudson Valley Umbrella",
    "wof:placetype":"venue"
},
  "geometry": {"coordinates":[-73.929795,41.288674],"type":"Point"}
}