{
  "type": "Feature",
  "properties": {
    "addr:full":"531 Lookout Ct Slingerlands NY 12159",
    "addr:housenumber":"531",
    "addr:postcode":"12159",
    "addr:street":"Lookout Ct",
    "iso:country":"US",
    "sg:address":"531 Lookout Ct",
    "sg:city":"Slingerlands",
    "sg:classifiers":[
        {
            "category":"Professional",
            "subcategory":"Advertising",
            "type":"Services"
        }
    ],
    "sg:phone":"+1   ",
    "sg:postcode":"12159",
    "sg:province":"NY",
    "sg:tags":[
        "medium",
        "agency",
        "buying"
    ],
    "wof:name":"Desmond Media & Marketing",
    "wof:placetype":"venue"
},
  "geometry": {"coordinates":[-73.898911,42.683351],"type":"Point"}
}