{
  "type": "Feature",
  "properties": {
    "addr:full":"158 Ingham Ave Buffalo NY 14218",
    "addr:housenumber":"158",
    "addr:postcode":"14218",
    "addr:street":"Ingham Ave",
    "iso:country":"US",
    "sg:address":"158 Ingham Ave",
    "sg:city":"Buffalo",
    "sg:classifiers":[
        {
            "category":"Building & Trades",
            "subcategory":"Construction",
            "type":"Services"
        }
    ],
    "sg:phone":"+1 716 823 3234",
    "sg:postcode":"14218",
    "sg:province":"NY",
    "sg:tags":[
        "house"
    ],
    "wof:name":"Fears Construction",
    "wof:placetype":"venue"
},
  "geometry": {"coordinates":[-78.840514,42.822467],"type":"Point"}
}