{
  "type": "Feature",
  "properties": {
    "addr:full":"60 Cedar Hill Ave Nyack NY 10960",
    "addr:housenumber":"60",
    "addr:postcode":"10960",
    "addr:street":"Cedar Hill Ave",
    "iso:country":"US",
    "sg:address":"60 Cedar Hill Ave",
    "sg:city":"Nyack",
    "sg:classifiers":[
        {
            "category":"Professional",
            "subcategory":"Lawyer & Legal Services",
            "type":"Services"
        }
    ],
    "sg:phone":"+1 845 358 4858",
    "sg:postcode":"10960",
    "sg:province":"NY",
    "sg:tags":[
        "attorney"
    ],
    "wof:name":"Barbara Balaber-Strauss PC",
    "wof:placetype":"venue"
},
  "geometry": {"coordinates":[-73.919254,41.087323],"type":"Point"}
}