{
  "type": "Feature",
  "properties": {
    "addr:full":"353 E Pine St Long Beach NY 11561",
    "addr:housenumber":"353",
    "addr:postcode":"11561",
    "addr:street":"E Pine St",
    "iso:country":"US",
    "sg:address":"353 E Pine St",
    "sg:city":"Long Beach",
    "sg:classifiers":[
        {
            "category":"Shopping",
            "subcategory":"Computers & Home Electronics",
            "type":"Retail Goods"
        }
    ],
    "sg:phone":"+1 516 431 3535",
    "sg:postcode":"11561",
    "sg:province":"NY",
    "sg:tags":[
        "equipment",
        "dealer"
    ],
    "wof:name":"Computer MD",
    "wof:placetype":"venue"
},
  "geometry": {"coordinates":[-73.653684,40.592409],"type":"Point"}
}