{
  "type": "Feature",
  "properties": {
    "addr:full":"512 Linden Ave Rochester NY 14625",
    "addr:housenumber":"512",
    "addr:postcode":"14625",
    "addr:street":"Linden Ave",
    "iso:country":"US",
    "sg:address":"512 Linden Ave",
    "sg:city":"Rochester",
    "sg:classifiers":[
        {
            "category":"Real Estate",
            "subcategory":"Real Estate Operator",
            "type":"Services"
        }
    ],
    "sg:phone":"+1 585 586 5740",
    "sg:postcode":"14625",
    "sg:province":"NY",
    "sg:tags":[
        "mobile",
        "home",
        "community"
    ],
    "wof:name":"Penfield Trailor Court",
    "wof:placetype":"venue"
},
  "geometry": {"coordinates":[-77.512382,43.124574],"type":"Point"}
}