{
  "type": "Feature",
  "properties": {
    "iso:country":"US",
    "sg:address":"3204 31st Ave",
    "sg:city":"Astoria",
    "sg:classifiers":[
        {
            "category":"Social Services",
            "subcategory":"Child Care",
            "type":"Services"
        }
    ],
    "sg:phone":"+1 718 777 2011",
    "sg:postcode":"11106",
    "sg:province":"NY",
    "sg:tags":[
        "day"
    ],
    "wof:name":"ALL CHILDREN'S CHILD CARE",
    "wof:placetype":"venue"
},
  "geometry": {"coordinates":[-73.922731,40.763839],"type":"Point"}
}