{
  "type": "Feature",
  "properties": {
    "addr:full":"589 Prospect Ave Brooklyn NY 11215",
    "addr:housenumber":"589",
    "addr:postcode":"11215",
    "addr:street":"Prospect Ave",
    "iso:country":"US",
    "sg:address":"589 Prospect Ave",
    "sg:city":"Brooklyn",
    "sg:classifiers":[
        {
            "category":"Food & Beverages",
            "subcategory":"Groceries & Convenience Stores",
            "type":"Retail Goods"
        }
    ],
    "sg:phone":"+1 718 768 1025",
    "sg:postcode":"11215",
    "sg:province":"NY",
    "sg:tags":[
        "grocer",
        "supermarket"
    ],
    "wof:name":"Key Foods",
    "wof:placetype":"venue"
},
  "geometry": {"coordinates":[-73.977707,40.656563],"type":"Point"}
}