{
  "type": "Feature",
  "properties": {
    "addr:full":"39 Goodman St S Rochester NY 14607",
    "addr:housenumber":"39",
    "addr:postcode":"14607",
    "addr:street":"Goodman St S",
    "iso:country":"US",
    "sg:address":"39 Goodman St S",
    "sg:city":"Rochester",
    "sg:classifiers":[
        {
            "category":"Banks & Credit Unions",
            "subcategory":"Bank",
            "type":"Services"
        },
        {
            "category":"Shopping",
            "subcategory":"Antiques",
            "type":"Retail Goods"
        },
        {
            "category":"Shopping",
            "subcategory":"Used Merchandise",
            "type":"Retail Goods"
        }
    ],
    "sg:phone":"+1 585 244 7720",
    "sg:postcode":"14607",
    "sg:province":"NY",
    "sg:tags":[
        "shop",
        "resale",
        "second",
        "hand"
    ],
    "wof:name":"Talulah Petunia's",
    "wof:placetype":"venue"
},
  "geometry": {"coordinates":[-77.58842799999999,43.15294],"type":"Point"}
}