{
  "type": "Feature",
  "properties": {
    "iso:country":"US",
    "sg:address":"7 North Rd",
    "sg:city":"Hampton Bays",
    "sg:classifiers":[
        {
            "category":"Restaurant",
            "type":"Food & Drink"
        }
    ],
    "sg:menulink":"http://www.allmenus.com/ny/southampton/272270-tide-runners/menu/",
    "sg:phone":"+1 631 728 7373",
    "sg:postcode":"11946",
    "sg:province":"NY",
    "sg:tags":[
        "seafood",
        "american"
    ],
    "wof:name":"Tide Runners",
    "wof:placetype":"venue"
},
  "geometry": {"coordinates":[-72.493092,40.893384],"type":"Point"}
}