{
  "type": "Feature",
  "properties": {
    "addr:full":"19 Sagamore Dr Plainview NY 11803",
    "addr:housenumber":"19",
    "addr:postcode":"11803",
    "addr:street":"Sagamore Dr",
    "iso:country":"US",
    "sg:address":"19 Sagamore Dr",
    "sg:city":"Plainview",
    "sg:classifiers":[
        {
            "category":"Food & Beverages",
            "subcategory":"Meat & Fish",
            "type":"Retail Goods"
        }
    ],
    "sg:phone":"+1   ",
    "sg:postcode":"11803",
    "sg:province":"NY",
    "wof:name":"Wild Way Food Service",
    "wof:placetype":"venue"
},
  "geometry": {"coordinates":[-73.474282,40.792764],"type":"Point"}
}