{
  "type": "Feature",
  "properties": {
    "addr:full":"565 Plandome Rd Manhasset NY 11030",
    "addr:housenumber":"565",
    "addr:postcode":"11030",
    "addr:street":"Plandome Rd",
    "iso:country":"US",
    "sg:address":"565 Plandome Rd",
    "sg:city":"Manhasset",
    "sg:classifiers":[
        {
            "category":"Wholesale",
            "subcategory":"Apparel",
            "type":"Manufacturing & Wholesale Goods"
        }
    ],
    "sg:phone":"+1 516 850 3341",
    "sg:postcode":"11030",
    "sg:province":"NY",
    "sg:tags":[
        "clothing"
    ],
    "wof:name":"Knj Apparel Inc",
    "wof:placetype":"venue"
},
  "geometry": {"coordinates":[-73.70164800000001,40.800165],"type":"Point"}
}