{
  "type": "Feature",
  "properties": {
    "addr:full":"600 Whalen Rd Penfield NY 14526",
    "addr:housenumber":"600",
    "addr:postcode":"14526",
    "addr:street":"Whalen Rd",
    "iso:country":"US",
    "sg:address":"600 Whalen Rd",
    "sg:city":"Penfield",
    "sg:classifiers":[
        {
            "category":"Shopping",
            "subcategory":"Bicycles & Sporting Goods",
            "type":"Retail Goods"
        }
    ],
    "sg:phone":"+1   ",
    "sg:postcode":"14526",
    "sg:province":"NY",
    "sg:tags":[
        "shop"
    ],
    "wof:name":"Shadow Pines Pro Shop",
    "wof:placetype":"venue"
},
  "geometry": {"coordinates":[-77.484886,43.150607],"type":"Point"}
}