{
  "type": "Feature",
  "properties": {
    "iso:country":"US",
    "sg:address":"8 Franklin St",
    "sg:city":"Greene",
    "sg:classifiers":[
        {
            "category":"Building & Trades",
            "subcategory":"Plumbing",
            "type":"Services"
        }
    ],
    "sg:phone":"+1 607 656 4484",
    "sg:postcode":"13778",
    "sg:province":"NY",
    "sg:tags":[
        "plumbing",
        "contractor"
    ],
    "wof:name":"Hotchkiss & Driscall",
    "wof:placetype":"venue"
},
  "geometry": {"coordinates":[-75.773741,42.330721],"type":"Point"}
}