{
  "type": "Feature",
  "properties": {
    "addr:full":"130 Westland Pkwy Buffalo NY 14225",
    "addr:housenumber":"130",
    "addr:postcode":"14225",
    "addr:street":"Westland Pkwy",
    "iso:country":"US",
    "sg:address":"130 Westland Pkwy",
    "sg:city":"Buffalo",
    "sg:classifiers":[
        {
            "category":"Wholesale",
            "subcategory":"Machinery & Supplies",
            "type":"Manufacturing & Wholesale Goods"
        }
    ],
    "sg:phone":"+1 716 894 7266",
    "sg:postcode":"14225",
    "sg:province":"NY",
    "sg:tags":[
        "parts"
    ],
    "wof:name":"Russell Mustang Inc",
    "wof:placetype":"venue"
},
  "geometry": {"coordinates":[-78.77966600000001,42.921634],"type":"Point"}
}