{
  "type": "Feature",
  "properties": {
    "iso:country":"US",
    "sg:address":"97 Union Ave",
    "sg:city":"New Rochelle",
    "sg:classifiers":[
        {
            "category":"Building & Trades",
            "subcategory":"Construction",
            "type":"Services"
        }
    ],
    "sg:phone":"+1 914 632 9534",
    "sg:postcode":"10801",
    "sg:province":"NY",
    "sg:tags":[
        "carpentry",
        "work",
        "general",
        "contractor"
    ],
    "wof:name":"F & F Carpentry Cstm Cabinets",
    "wof:placetype":"venue"
},
  "geometry": {"coordinates":[-73.789024,40.910155],"type":"Point"}
}