{
  "type": "Feature",
  "properties": {
    "addr:full":"430 Lomond Pl Utica NY 13502",
    "addr:housenumber":"430",
    "addr:postcode":"13502",
    "addr:street":"Lomond Pl",
    "iso:country":"US",
    "sg:address":"430 Lomond Pl",
    "sg:city":"Utica",
    "sg:classifiers":[
        {
            "category":"Retail",
            "subcategory":"Auto Rental",
            "type":"Services"
        }
    ],
    "sg:phone":"+1 315 733 2386",
    "sg:postcode":"13502",
    "sg:province":"NY",
    "sg:tags":[
        "renting",
        "truck",
        "leasing"
    ],
    "wof:name":"U-Haul Co",
    "wof:placetype":"venue"
},
  "geometry": {"coordinates":[-75.28635,43.081832],"type":"Point"}
}