{
  "type": "Feature",
  "properties": {
    "iso:country":"US",
    "sg:address":"132 9th Ave",
    "sg:city":"New York",
    "sg:classifiers":[
        {
            "category":"Shopping",
            "subcategory":"Antiques",
            "type":"Retail Goods"
        }
    ],
    "sg:phone":"+1 800 290 6535",
    "sg:postcode":"10011",
    "sg:province":"NY",
    "wof:name":"R B Co Antique Reprs",
    "wof:placetype":"venue"
},
  "geometry": {"coordinates":[-74.29817,40.7435],"type":"Point"}
}