{
  "type": "Feature",
  "properties": {
    "addr:full":"25-80 Steinway St Astoria NY 11103",
    "addr:housenumber":"25-80",
    "addr:postcode":"11103",
    "addr:street":"Steinway St",
    "iso:country":"US",
    "sg:address":"25-80 Steinway St",
    "sg:city":"Astoria",
    "sg:classifiers":[
        {
            "category":"Building & Trades",
            "subcategory":"Pest Control",
            "type":"Services"
        }
    ],
    "sg:phone":"+1 718 728 4040",
    "sg:postcode":"11103",
    "sg:province":"NY",
    "sg:website":"standardpest.com",
    "wof:name":"Standard Pest Management",
    "wof:placetype":"venue"
},
  "geometry": {"coordinates":[-73.914147,40.770013],"type":"Point"}
}