{
  "type": "Feature",
  "properties": {
    "addr:full":"1912 Crotona Pkwy Bronx NY 10460",
    "addr:housenumber":"1912",
    "addr:postcode":"10460",
    "addr:street":"Crotona Pkwy",
    "iso:country":"US",
    "sg:address":"1912 Crotona Pkwy",
    "sg:city":"Bronx",
    "sg:classifiers":[
        {
            "category":"Real Estate",
            "subcategory":"Developer",
            "type":"Services"
        }
    ],
    "sg:phone":"+1 718 842 6440",
    "sg:postcode":"10460",
    "sg:province":"NY",
    "sg:tags":[
        "residential"
    ],
    "wof:name":"Aquinas Housing Corp",
    "wof:placetype":"venue"
},
  "geometry": {"coordinates":[-73.88545000000001,40.840939],"type":"Point"}
}