{
  "type": "Feature",
  "properties": {
    "addr:full":"8339 Parsons Blvd Jamaica NY 11432",
    "addr:housenumber":"8339",
    "addr:postcode":"11432",
    "addr:street":"Parsons Blvd",
    "iso:country":"US",
    "sg:address":"8339 Parsons Blvd",
    "sg:city":"Jamaica",
    "sg:classifiers":[
        {
            "category":"Food & Beverages",
            "subcategory":"Groceries & Convenience Stores",
            "type":"Retail Goods"
        }
    ],
    "sg:phone":"+1 718 658 6676",
    "sg:postcode":"11432",
    "sg:province":"NY",
    "sg:website":"www.poshora.com",
    "wof:name":"Poshora Inc",
    "wof:placetype":"venue"
},
  "geometry": {"coordinates":[-73.80740400000001,40.7145],"type":"Point"}
}