{
  "type": "Feature",
  "properties": {
    "addr:full":"10 Kent St Westfield NY 14787",
    "addr:housenumber":"10",
    "addr:postcode":"14787",
    "addr:street":"Kent St",
    "iso:country":"US",
    "sg:address":"10 Kent St",
    "sg:city":"Westfield",
    "sg:classifiers":[
        {
            "category":"Organizations",
            "subcategory":"Religious Organization",
            "type":"Services"
        }
    ],
    "sg:phone":"+1 716 326 7603",
    "sg:postcode":"14787",
    "sg:province":"NY",
    "sg:tags":[
        "clergy"
    ],
    "wof:name":"Paul L Denise",
    "wof:placetype":"venue"
},
  "geometry": {"coordinates":[-79.57368200000001,42.322139],"type":"Point"}
}