{
  "type": "Feature",
  "properties": {
    "addr:full":"1400 Altamont Ave Schenectady NY 12303",
    "addr:housenumber":"1400",
    "addr:postcode":"12303",
    "addr:street":"Altamont Ave",
    "iso:country":"US",
    "sg:address":"1400 Altamont Ave",
    "sg:city":"Schenectady",
    "sg:classifiers":[
        {
            "category":"Shopping",
            "subcategory":"Gifts & Souvenirs",
            "type":"Retail Goods"
        }
    ],
    "sg:phone":"+1 518 630 0046",
    "sg:postcode":"12303",
    "sg:province":"NY",
    "sg:tags":[
        "shop",
        "cards",
        "greeting"
    ],
    "wof:name":"Tracy's Hallmark",
    "wof:placetype":"venue"
},
  "geometry": {"coordinates":[-73.945894,42.784538],"type":"Point"}
}