{
  "type": "Feature",
  "properties": {
    "addr:full":"150 N Main St Port Chester NY 10573",
    "addr:housenumber":"150",
    "addr:postcode":"10573",
    "addr:street":"N Main St",
    "iso:country":"US",
    "sg:address":"150 N Main St",
    "sg:city":"Port Chester",
    "sg:classifiers":[
        {
            "category":"Restaurant",
            "type":"Food & Drink"
        }
    ],
    "sg:menulink":"http://www.allmenus.com/ny/rye/146646-el-rinconcito-ecuatoriano/menu/",
    "sg:phone":"+1 914 937 7343",
    "sg:postcode":"10573",
    "sg:province":"NY",
    "sg:tags":[
        "caribbean"
    ],
    "wof:name":"El Rinconcito Ecuatoriano",
    "wof:placetype":"venue"
},
  "geometry": {"coordinates":[-73.66110999999999,41.003282],"type":"Point"}
}