{
  "type": "Feature",
  "properties": {
    "addr:full":"36 Broadway Greenlawn NY 11740",
    "addr:housenumber":"36",
    "addr:postcode":"11740",
    "addr:street":"Broadway",
    "iso:country":"US",
    "sg:address":"36 Broadway",
    "sg:city":"Greenlawn",
    "sg:classifiers":[
        {
            "category":"Health Services",
            "subcategory":"Doctor",
            "type":"Services"
        },
        {
            "category":"Health Services",
            "subcategory":"Dentist",
            "type":"Services"
        }
    ],
    "sg:phone":"+1 631 261 5100",
    "sg:postcode":"11740",
    "sg:province":"NY",
    "sg:tags":[
        "surgeon",
        "oral",
        "pediatric"
    ],
    "wof:name":"Pediatric Dentistry Howard Miller Ross Grueber DDS",
    "wof:placetype":"venue"
},
  "geometry": {"coordinates":[-73.366096,40.8717],"type":"Point"}
}