{
  "type": "Feature",
  "properties": {
    "addr:full":"195 Bedford Ave Brooklyn NY 11211",
    "addr:housenumber":"195",
    "addr:postcode":"11211",
    "addr:street":"Bedford Ave",
    "iso:country":"US",
    "sg:address":"195 Bedford Ave",
    "sg:city":"Brooklyn",
    "sg:classifiers":[
        {
            "category":"Restaurant",
            "type":"Food & Drink"
        }
    ],
    "sg:menulink":"http://www.allmenus.com/ny/brooklyn/107623-vera-cruz/menu/",
    "sg:phone":"+1 718 599 7914",
    "sg:postcode":"11211",
    "sg:province":"NY",
    "sg:tags":[
        "mexican"
    ],
    "wof:name":"Vera Cruz",
    "wof:placetype":"venue"
},
  "geometry": {"coordinates":[-73.95813,40.71742],"type":"Point"}
}