{
  "type": "Feature",
  "properties": {
    "addr:full":"847 Fort Salonga Rd Northport NY 11768",
    "addr:housenumber":"847",
    "addr:postcode":"11768",
    "addr:street":"Fort Salonga Rd",
    "iso:country":"US",
    "sg:address":"847 Fort Salonga Rd",
    "sg:city":"Northport",
    "sg:classifiers":[
        {
            "category":"Manufacturing",
            "subcategory":"Food",
            "type":"Manufacturing & Wholesale Goods"
        }
    ],
    "sg:phone":"+1   ",
    "sg:postcode":"11768",
    "sg:province":"NY",
    "sg:tags":[
        "product",
        "confectionery",
        "mfg"
    ],
    "wof:name":"Long Island Chocolate Factory",
    "wof:placetype":"venue"
},
  "geometry": {"coordinates":[-73.327468,40.899602],"type":"Point"}
}