{
  "type": "Feature",
  "properties": {
    "addr:full":"999 Middle Country Rd Selden NY 11784",
    "addr:housenumber":"999",
    "addr:postcode":"11784",
    "addr:street":"Middle Country Rd",
    "iso:country":"US",
    "sg:address":"999 Middle Country Rd",
    "sg:city":"Selden",
    "sg:classifiers":[
        {
            "category":"Banks & Credit Unions",
            "subcategory":"Bank",
            "type":"Services"
        }
    ],
    "sg:phone":"+1 631 736 4770",
    "sg:postcode":"11784",
    "sg:province":"NY",
    "wof:name":"Chase",
    "wof:placetype":"venue"
},
  "geometry": {"coordinates":[-73.943578,40.863775],"type":"Point"}
}