{
  "type": "Feature",
  "properties": {
    "iso:country":"US",
    "sg:address":"3625 Newark Rd",
    "sg:city":"Marion",
    "sg:classifiers":[
        {
            "category":"Real Estate",
            "subcategory":"Real Estate Agent",
            "type":"Services"
        }
    ],
    "sg:phone":"+1 315 926 5074",
    "sg:postcode":"14505",
    "sg:province":"NY",
    "sg:tags":[
        "investment"
    ],
    "wof:name":"B C Enterprises",
    "wof:placetype":"venue"
},
  "geometry": {"coordinates":[-77.185239,43.134535],"type":"Point"}
}