{
  "type": "Feature",
  "properties": {
    "addr:full":"702 154th Street Whitestone NY 11357",
    "addr:housenumber":"702",
    "addr:postcode":"11357",
    "addr:street":"154Th Street",
    "iso:country":"US",
    "sg:address":"702 154th Street",
    "sg:city":"Whitestone",
    "sg:classifiers":[
        {
            "category":"Food & Beverages",
            "subcategory":"Liquor & Beverages",
            "type":"Retail Goods"
        }
    ],
    "sg:phone":"+1 718 767 5900",
    "sg:postcode":"11357",
    "sg:province":"NY",
    "sg:tags":[
        "beer",
        "spirit",
        "wine"
    ],
    "wof:name":"Citrus Bowl",
    "wof:placetype":"venue"
},
  "geometry": {"coordinates":[-73.807053,40.794578],"type":"Point"}
}