{
  "type": "Feature",
  "properties": {
    "iso:country":"US",
    "sg:address":"4369 10th St",
    "sg:city":"Long Island City",
    "sg:classifiers":[
        {
            "category":"Shopping",
            "subcategory":"Beauty & Cosmetics",
            "type":"Retail Goods"
        }
    ],
    "sg:phone":"+1 718 482 8575",
    "sg:postcode":"11101",
    "sg:province":"NY",
    "sg:tags":[
        "supply"
    ],
    "wof:name":"Beautyfly Corp",
    "wof:placetype":"venue"
},
  "geometry": {"coordinates":[-73.949799,40.750801],"type":"Point"}
}