{
  "type": "Feature",
  "properties": {
    "addr:full":"414 Willis Ave Bronx NY 10454",
    "addr:housenumber":"414",
    "addr:postcode":"10454",
    "addr:street":"Willis Ave",
    "iso:country":"US",
    "sg:address":"414 Willis Ave",
    "sg:city":"Bronx",
    "sg:classifiers":[
        {
            "category":"Professional",
            "subcategory":"Testing Lab",
            "type":"Services"
        }
    ],
    "sg:phone":"+1 718 665 9626",
    "sg:postcode":"10454",
    "sg:province":"NY",
    "sg:tags":[
        "laboratory"
    ],
    "wof:name":"Universal Diagnostic",
    "wof:placetype":"venue"
},
  "geometry": {"coordinates":[-73.91962700000001,40.813421],"type":"Point"}
}