{
  "type": "Feature",
  "properties": {
    "addr:full":"52 Wilson Avenue Apt 108 Brooklyn NY 11237",
    "addr:housenumber":"52;108",
    "addr:postcode":"11237",
    "addr:street":"Wilson Avenue Apt",
    "iso:country":"US",
    "sg:address":"52 Wilson Avenue Apt 108",
    "sg:city":"Brooklyn",
    "sg:classifiers":[
        {
            "category":"Organizations",
            "subcategory":"Non-profit Organization",
            "type":"Services"
        }
    ],
    "sg:phone":"+1 718 497 8560",
    "sg:postcode":"11237",
    "sg:province":"NY",
    "sg:tags":[
        "service/non-profit",
        "community"
    ],
    "wof:name":"St Leonard's Family Housing",
    "wof:placetype":"venue"
},
  "geometry": {"coordinates":[-73.929097,40.70262],"type":"Point"}
}