{
  "type": "Feature",
  "properties": {
    "addr:full":"59 Central Ave Farmingdale NY 11735",
    "addr:housenumber":"59",
    "addr:postcode":"11735",
    "addr:street":"Central Ave",
    "iso:country":"US",
    "sg:address":"59 Central Ave",
    "sg:city":"Farmingdale",
    "sg:classifiers":[
        {
            "category":"Manufacturing",
            "subcategory":"Signs",
            "type":"Manufacturing & Wholesale Goods"
        }
    ],
    "sg:phone":"+1   ",
    "sg:postcode":"11735",
    "sg:province":"NY",
    "sg:tags":[
        "specialty",
        "mfg"
    ],
    "wof:name":"Signs n Things Inc",
    "wof:placetype":"venue"
},
  "geometry": {"coordinates":[-73.41085099999999,40.753013],"type":"Point"}
}