{
  "type": "Feature",
  "properties": {
    "iso:country":"US",
    "sg:address":"451 Classon Ave",
    "sg:city":"Brooklyn",
    "sg:classifiers":[
        {
            "category":"Food & Beverages",
            "subcategory":"Groceries & Convenience Stores",
            "type":"Retail Goods"
        }
    ],
    "sg:postcode":"11238",
    "sg:province":"NY",
    "wof:name":"Paula Food Market",
    "wof:placetype":"venue"
},
  "geometry": {"coordinates":[-73.959052,40.685345],"type":"Point"}
}