{
  "type": "Feature",
  "properties": {
    "addr:full":"240 Park Hill Ave Staten Island NY 10304",
    "addr:housenumber":"240",
    "addr:postcode":"10304",
    "addr:street":"Park Hill Ave",
    "iso:country":"US",
    "sg:address":"240 Park Hill Ave",
    "sg:city":"Staten Island",
    "sg:classifiers":[
        {
            "category":"Real Estate",
            "subcategory":"Real Estate Operator",
            "type":"Services"
        }
    ],
    "sg:phone":"+1 718 448 6100",
    "sg:postcode":"10304",
    "sg:province":"NY",
    "sg:tags":[
        "apartment"
    ],
    "wof:name":"Park Hill Apts Renting Office",
    "wof:placetype":"venue"
},
  "geometry": {"coordinates":[-74.08290100000001,40.612999],"type":"Point"}
}