{
  "type": "Feature",
  "properties": {
    "iso:country":"US",
    "sg:address":"103 N Geddes St",
    "sg:city":"Syracuse",
    "sg:classifiers":[
        {
            "category":"Bars & Pubs",
            "type":"Food & Drink"
        }
    ],
    "sg:phone":"+1 315 426 8742",
    "sg:postcode":"13204",
    "sg:province":"NY",
    "wof:name":"Johnny B's Jukebox",
    "wof:placetype":"venue"
},
  "geometry": {"coordinates":[-76.170777,43.050086],"type":"Point"}
}