{
  "type": "Feature",
  "properties": {
    "addr:full":"250 Victory Blvd New Rochelle NY 10804",
    "addr:housenumber":"250",
    "addr:postcode":"10804",
    "addr:street":"Victory Blvd",
    "iso:country":"US",
    "sg:address":"250 Victory Blvd",
    "sg:city":"New Rochelle",
    "sg:classifiers":[
        {
            "category":"Real Estate",
            "subcategory":"Real Estate Agent",
            "type":"Services"
        }
    ],
    "sg:phone":"+1 914 633 0908",
    "sg:postcode":"10804",
    "sg:province":"NY",
    "wof:name":"1536 Stillwell Realty Corp",
    "wof:placetype":"venue"
},
  "geometry": {"coordinates":[-73.789754,40.956129],"type":"Point"}
}