{
  "type": "Feature",
  "properties": {
    "iso:country":"US",
    "sg:address":"3014 Beach Dr",
    "sg:city":"Merrick",
    "sg:classifiers":[
        {
            "category":"Travel",
            "subcategory":"Travel Agent",
            "type":"Entertainment"
        }
    ],
    "sg:phone":"+1 516 223 3408",
    "sg:postcode":"11566",
    "sg:province":"NY",
    "sg:tags":[
        "agency",
        "bureau"
    ],
    "wof:name":"Let's Go Travel",
    "wof:placetype":"venue"
},
  "geometry": {"coordinates":[-73.551153,40.641329],"type":"Point"}
}