{
  "type": "Feature",
  "properties": {
    "addr:full":"114 State Hwy 17K Newburgh NY 12550",
    "addr:housenumber":"114",
    "addr:postcode":"12550",
    "addr:street":"State Hwy 17K",
    "iso:country":"US",
    "sg:address":"114 State Hwy 17K",
    "sg:city":"Newburgh",
    "sg:classifiers":[
        {
            "category":"Banks & Credit Unions",
            "subcategory":"Investment Brokerage",
            "type":"Services"
        }
    ],
    "sg:phone":"+1 845 564 3654",
    "sg:postcode":"12550",
    "sg:province":"NY",
    "sg:tags":[
        "security"
    ],
    "wof:name":"De Lorenzo Financial Planning",
    "wof:placetype":"venue"
},
  "geometry": {"coordinates":[-74.079691,41.506727],"type":"Point"}
}