{
  "type": "Feature",
  "properties": {
    "addr:full":"7124 Fresh Pond Rd Ridgewood NY 11385",
    "addr:housenumber":"7124",
    "addr:postcode":"11385",
    "addr:street":"Fresh Pond Rd",
    "iso:country":"US",
    "sg:address":"7124 Fresh Pond Rd",
    "sg:city":"Ridgewood",
    "sg:classifiers":[
        {
            "category":"Restaurant",
            "type":"Food & Drink"
        }
    ],
    "sg:phone":"+1 718 386 4400",
    "sg:postcode":"11385",
    "sg:province":"NY",
    "sg:tags":[
        "polish"
    ],
    "wof:name":"Bona Restaurant",
    "wof:placetype":"venue"
},
  "geometry": {"coordinates":[-73.895003,40.701116],"type":"Point"}
}