{
  "type": "Feature",
  "properties": {
    "addr:full":"568 W 125 St Manhattan NY 10027",
    "addr:housenumber":"568",
    "addr:postcode":"10027",
    "addr:street":"W 125 St",
    "iso:country":"US",
    "sg:address":"568 W 125 St",
    "sg:city":"Manhattan",
    "sg:classifiers":[
        {
            "category":"Shopping",
            "subcategory":"Pharmacy",
            "type":"Retail Goods"
        }
    ],
    "sg:phone":"+1 212 865 3894",
    "sg:postcode":"10027",
    "sg:province":"NY",
    "sg:tags":[
        "drugstore"
    ],
    "sg:website":"www.duanereade.com",
    "wof:name":"Duane Reade",
    "wof:placetype":"venue"
},
  "geometry": {"coordinates":[-73.95802500000001,40.81537],"type":"Point"}
}