{
  "type": "Feature",
  "properties": {
    "iso:country":"US",
    "sg:address":"88 Woodcrest Ave",
    "sg:city":"White Plains",
    "sg:classifiers":[
        {
            "category":"Education",
            "subcategory":"Vocational School",
            "type":"Public Place"
        }
    ],
    "sg:phone":"+1 914 682 8773",
    "sg:postcode":"10604",
    "sg:province":"NY",
    "sg:tags":[
        "training",
        "computer"
    ],
    "wof:name":"Computer Options Inc",
    "wof:placetype":"venue"
},
  "geometry": {"coordinates":[-73.755268,41.04381],"type":"Point"}
}