{
  "type": "Feature",
  "properties": {
    "iso:country":"US",
    "sg:address":"6735 Amboy Rd",
    "sg:city":"Staten Island",
    "sg:classifiers":[
        {
            "category":"Professional",
            "subcategory":"Detective & Security Services",
            "type":"Services"
        }
    ],
    "sg:phone":"+1 718 966 8196",
    "sg:postcode":"10309",
    "sg:province":"NY",
    "sg:tags":[
        "investigator"
    ],
    "wof:name":"Confidential Research",
    "wof:placetype":"venue"
},
  "geometry": {"coordinates":[-74.22832699999999,40.519651],"type":"Point"}
}