{
  "type": "Feature",
  "properties": {
    "iso:country":"US",
    "sg:address":"313 Lansdowne Rd",
    "sg:city":"Syracuse",
    "sg:classifiers":[
        {
            "category":"Shopping",
            "type":"Retail Goods"
        },
        {
            "category":"Organizations",
            "subcategory":"Non-profit Organization",
            "type":"Services"
        }
    ],
    "sg:phone":"+1 315 449 4510",
    "sg:postcode":"13214",
    "sg:province":"NY",
    "sg:tags":[
        "fund",
        "games",
        "raising",
        "merchandise",
        "supply"
    ],
    "wof:name":"Trg Services",
    "wof:placetype":"venue"
},
  "geometry": {"coordinates":[-76.069221,43.036755],"type":"Point"}
}