{
  "type": "Feature",
  "properties": {
    "iso:country":"US",
    "sg:address":"1761 Scottsville Rd",
    "sg:city":"Rochester",
    "sg:classifiers":[
        {
            "category":"Restaurant",
            "type":"Food & Drink"
        }
    ],
    "sg:menulink":"http://www.allmenus.com/ny/chili/280235-sylvios-pizza/menu/",
    "sg:phone":"+1 585 436 6390",
    "sg:postcode":"14623",
    "sg:province":"NY",
    "sg:tags":[
        "salad",
        "seafood",
        "burger",
        "american",
        "pasta",
        "pizza",
        "wing",
        "italian"
    ],
    "wof:name":"Sylvios Pizza",
    "wof:placetype":"venue"
},
  "geometry": {"coordinates":[-77.68424,43.088865],"type":"Point"}
}