{
  "type": "Feature",
  "properties": {
    "addr:full":"3128 Villa Ave Bronx NY 10468",
    "addr:housenumber":"3128",
    "addr:postcode":"10468",
    "addr:street":"Villa Ave",
    "iso:country":"US",
    "sg:address":"3128 Villa Ave",
    "sg:city":"Bronx",
    "sg:classifiers":[
        {
            "category":"Restaurant",
            "type":"Food & Drink"
        }
    ],
    "sg:phone":"+1 718 933 0385",
    "sg:postcode":"10468",
    "sg:province":"NY",
    "wof:name":"Villa Pizza",
    "wof:placetype":"venue"
},
  "geometry": {"coordinates":[-73.887286,40.875427],"type":"Point"}
}