{
  "type": "Feature",
  "properties": {
    "iso:country":"US",
    "sg:address":"187 Ashford Ave",
    "sg:city":"Dobbs Ferry",
    "sg:classifiers":[
        {
            "category":"Retail",
            "subcategory":"Laundry & Dry Cleaning",
            "type":"Services"
        }
    ],
    "sg:phone":"+1 914 693 6704",
    "sg:postcode":"10522",
    "sg:province":"NY",
    "sg:tags":[
        "drycleaning",
        "plant",
        "cleaners"
    ],
    "wof:name":"Vicky's Laundry & Dry Cleaners",
    "wof:placetype":"venue"
},
  "geometry": {"coordinates":[-73.86221,41.014891],"type":"Point"}
}