{
  "type": "Feature",
  "properties": {
    "addr:full":"28 Xavier Dr Yonkers NY 10704",
    "addr:housenumber":"28",
    "addr:postcode":"10704",
    "addr:street":"Xavier Dr",
    "iso:country":"US",
    "sg:address":"28 Xavier Dr",
    "sg:city":"Yonkers",
    "sg:classifiers":[
        {
            "category":"Utilities",
            "subcategory":"Mobile Phone",
            "type":"Services"
        }
    ],
    "sg:phone":"+1   ",
    "sg:postcode":"10704",
    "sg:province":"NY",
    "sg:tags":[
        "communication",
        "radiotelephone"
    ],
    "wof:name":"Phone Store  The",
    "wof:placetype":"venue"
},
  "geometry": {"coordinates":[-73.852947,40.926491],"type":"Point"}
}