{
  "type": "Feature",
  "properties": {
    "addr:full":"4 Disbrow Ln New Rochelle NY 10804",
    "addr:housenumber":"4",
    "addr:postcode":"10804",
    "addr:street":"Disbrow Ln",
    "iso:country":"US",
    "sg:address":"4 Disbrow Ln",
    "sg:city":"New Rochelle",
    "sg:classifiers":[
        {
            "category":"Shopping",
            "subcategory":"Gifts & Souvenirs",
            "type":"Retail Goods"
        }
    ],
    "sg:phone":"+1 914 235 4653",
    "sg:postcode":"10804",
    "sg:province":"NY",
    "sg:tags":[
        "supply"
    ],
    "wof:name":"Youre Invited",
    "wof:placetype":"venue"
},
  "geometry": {"coordinates":[-73.796685,40.942116],"type":"Point"}
}