{
  "type": "Feature",
  "properties": {
    "addr:full":"201 S Main St Canandaigua NY 14424",
    "addr:housenumber":"201",
    "addr:postcode":"14424",
    "addr:street":"S Main St",
    "iso:country":"US",
    "sg:address":"201 S Main St",
    "sg:city":"Canandaigua",
    "sg:classifiers":[
        {
            "category":"Personal",
            "subcategory":"Beauty Salon",
            "type":"Services"
        }
    ],
    "sg:phone":"+1 585 394 7258",
    "sg:postcode":"14424",
    "sg:province":"NY",
    "wof:name":"Studio 2000",
    "wof:placetype":"venue"
},
  "geometry": {"coordinates":[-77.279239,42.884795],"type":"Point"}
}