{
  "type": "Feature",
  "properties": {
    "iso:country":"US",
    "sg:address":"189 S Wellwood Ave",
    "sg:city":"Lindenhurst",
    "sg:classifiers":[
        {
            "category":"Utilities",
            "subcategory":"Mobile Phone",
            "type":"Services"
        }
    ],
    "sg:phone":"+1 631 225 8880",
    "sg:postcode":"11757",
    "sg:province":"NY",
    "sg:tags":[
        "telephone",
        "cellular"
    ],
    "wof:name":"Digicom Wireless",
    "wof:placetype":"venue"
},
  "geometry": {"coordinates":[-73.371877,40.685359],"type":"Point"}
}