{
  "type": "Feature",
  "properties": {
    "addr:full":"565 E Gansevoort St Little Falls NY 13365",
    "addr:housenumber":"565",
    "addr:postcode":"13365",
    "addr:street":"E Gansevoort St",
    "iso:country":"US",
    "sg:address":"565 E Gansevoort St",
    "sg:city":"Little Falls",
    "sg:classifiers":[
        {
            "category":"Travel",
            "subcategory":"Travel Agent",
            "type":"Entertainment"
        }
    ],
    "sg:phone":"+1   ",
    "sg:postcode":"13365",
    "sg:province":"NY",
    "sg:tags":[
        "operator",
        "tour"
    ],
    "wof:name":"Heritage Tours LLC",
    "wof:placetype":"venue"
},
  "geometry": {"coordinates":[-74.857969,43.045964],"type":"Point"}
}