{
  "type": "Feature",
  "properties": {
    "iso:country":"US",
    "sg:address":"1414 Newkirk Ave Ste A",
    "sg:city":"Brooklyn",
    "sg:classifiers":[
        {
            "category":"Health Services",
            "subcategory":"Doctor",
            "type":"Services"
        }
    ],
    "sg:phone":"+1 718 693 1011",
    "sg:postcode":"11226",
    "sg:province":"NY",
    "sg:tags":[
        "obstetrician",
        "gynecologist"
    ],
    "sg:website":"www.boroparkobgyn.com",
    "wof:name":"Boro Park Obstetrics & Gynecology",
    "wof:placetype":"venue"
},
  "geometry": {"coordinates":[-73.963606,40.635055],"type":"Point"}
}