{
  "type": "Feature",
  "properties": {
    "addr:full":"3020 Surf Ave Brooklyn NY 11224",
    "addr:housenumber":"3020",
    "addr:postcode":"11224",
    "addr:street":"Surf Ave",
    "iso:country":"US",
    "sg:address":"3020 Surf Ave",
    "sg:city":"Brooklyn",
    "sg:classifiers":[
        {
            "category":"Government",
            "subcategory":"Office",
            "type":"Public Place"
        }
    ],
    "sg:phone":"+1 718 996 9483",
    "sg:postcode":"11224",
    "sg:province":"NY",
    "wof:name":"New York City Housing",
    "wof:placetype":"venue"
},
  "geometry": {"coordinates":[-73.99687299999999,40.572683],"type":"Point"}
}