{
  "type": "Feature",
  "properties": {
    "addr:full":"25350 149th Avenue Jamaica NY 11422",
    "addr:housenumber":"25350",
    "addr:postcode":"11422",
    "addr:street":"149Th Avenue",
    "iso:country":"US",
    "sg:address":"25350 149th Avenue",
    "sg:city":"Jamaica",
    "sg:classifiers":[
        {
            "category":"Education",
            "subcategory":"School",
            "type":"Public Place"
        }
    ],
    "sg:phone":"+1 718 723 0313",
    "sg:postcode":"11422",
    "sg:province":"NY",
    "sg:tags":[
        "high",
        "middle",
        "elementary"
    ],
    "wof:name":"New York City Community School District 29 Region 3",
    "wof:placetype":"venue"
},
  "geometry": {"coordinates":[-73.73661300000001,40.652936],"type":"Point"}
}