{
  "type": "Feature",
  "properties": {
    "iso:country":"US",
    "sg:address":"228 Palmetto St",
    "sg:city":"Brooklyn",
    "sg:classifiers":[
        {
            "category":"Wholesale",
            "subcategory":"Apparel",
            "type":"Manufacturing & Wholesale Goods"
        }
    ],
    "sg:phone":"+1 718 573 6011",
    "sg:postcode":"11221",
    "sg:province":"NY",
    "sg:tags":[
        "handbag"
    ],
    "wof:name":"Skydag Co",
    "wof:placetype":"venue"
},
  "geometry": {"coordinates":[-73.91426,40.696076],"type":"Point"}
}