{
  "type": "Feature",
  "properties": {
    "addr:full":"31 Decker Rd Newfield NY 14867",
    "addr:housenumber":"31",
    "addr:postcode":"14867",
    "addr:street":"Decker Rd",
    "iso:country":"US",
    "sg:address":"31 Decker Rd",
    "sg:city":"Newfield",
    "sg:classifiers":[
        {
            "category":"Professional",
            "subcategory":"Computer Services",
            "type":"Services"
        }
    ],
    "sg:phone":"+1 607 277 8000",
    "sg:postcode":"14867",
    "sg:province":"NY",
    "sg:tags":[
        "development",
        "sales",
        "software"
    ],
    "wof:name":"Palisade Corporation",
    "wof:placetype":"venue"
},
  "geometry": {"coordinates":[-76.554151,42.388957],"type":"Point"}
}