{
  "type": "Feature",
  "properties": {
    "iso:country":"US",
    "sg:address":"22 Georgia St",
    "sg:city":"Valley Stream",
    "sg:classifiers":[
        {
            "category":"Wholesale",
            "subcategory":"Machinery & Supplies",
            "type":"Manufacturing & Wholesale Goods"
        }
    ],
    "sg:phone":"+1 516 285 0171",
    "sg:postcode":"11580",
    "sg:province":"NY",
    "sg:tags":[
        "equipment",
        "industrial"
    ],
    "wof:name":"F J S Industries",
    "wof:placetype":"venue"
},
  "geometry": {"coordinates":[-73.72138,40.682506],"type":"Point"}
}