{
  "type": "Feature",
  "properties": {
    "iso:country":"US",
    "sg:address":"Walmart Plaza",
    "sg:city":"Brockport",
    "sg:classifiers":[
        {
            "category":"Ice Cream",
            "type":"Food & Drink"
        }
    ],
    "sg:menulink":"http://www.allmenus.com/ny/sweden/216977-abbotts-frozen-custard/menu/",
    "sg:phone":"+1 585 637 4333",
    "sg:postcode":"14420",
    "sg:province":"NY",
    "sg:tags":[
        "american"
    ],
    "wof:name":"Abbott's Frozen Custard",
    "wof:placetype":"venue"
},
  "geometry": {"coordinates":[-77.94159000000001,43.194674],"type":"Point"}
}