{
  "type": "Feature",
  "properties": {
    "iso:country":"US",
    "sg:address":"4630 E River Rd",
    "sg:city":"Grand Island",
    "sg:classifiers":[
        {
            "category":"Building & Trades",
            "subcategory":"Cleaning & Sanitation",
            "type":"Services"
        }
    ],
    "sg:phone":"+1 716 628 0074",
    "sg:postcode":"14072",
    "sg:province":"NY",
    "sg:tags":[
        "maintenance"
    ],
    "wof:name":"Aeromech",
    "wof:placetype":"venue"
},
  "geometry": {"coordinates":[-78.941408,43.059487],"type":"Point"}
}