{
  "type": "Feature",
  "properties": {
    "addr:full":"211 Croton Lake Rd Mount Kisco NY 10549",
    "addr:housenumber":"211",
    "addr:postcode":"10549",
    "addr:street":"Croton Lake Rd",
    "iso:country":"US",
    "sg:address":"211 Croton Lake Rd",
    "sg:city":"Mount Kisco",
    "sg:classifiers":[
        {
            "category":"Building & Trades",
            "subcategory":"Construction",
            "type":"Services"
        }
    ],
    "sg:phone":"+1 914 242 6298",
    "sg:postcode":"10549",
    "sg:province":"NY",
    "sg:tags":[
        "house"
    ],
    "wof:name":"Haricon Inc",
    "wof:placetype":"venue"
},
  "geometry": {"coordinates":[-73.745552,41.232105],"type":"Point"}
}