{
  "type": "Feature",
  "properties": {
    "addr:full":"930 2nd Avenue New York NY 10022",
    "addr:housenumber":"930",
    "addr:postcode":"10022",
    "addr:street":"2Nd Avenue",
    "iso:country":"US",
    "sg:address":"930 2nd Avenue",
    "sg:city":"New York",
    "sg:classifiers":[
        {
            "category":"Shopping",
            "subcategory":"Beauty & Cosmetics",
            "type":"Retail Goods"
        }
    ],
    "sg:phone":"+1 212 935 6464",
    "sg:postcode":"10022",
    "sg:province":"NY",
    "sg:tags":[
        "supply"
    ],
    "wof:name":"A To Z Cosmetics",
    "wof:placetype":"venue"
},
  "geometry": {"coordinates":[-73.96881,40.754438],"type":"Point"}
}