{
  "type": "Feature",
  "properties": {
    "addr:full":"483 10th Ave New York NY 10018",
    "addr:housenumber":"483",
    "addr:postcode":"10018",
    "addr:street":"10Th Ave",
    "iso:country":"US",
    "sg:address":"483 10th Ave",
    "sg:city":"New York",
    "sg:classifiers":[
        {
            "category":"Banks & Credit Unions",
            "subcategory":"Investment Brokerage",
            "type":"Services"
        }
    ],
    "sg:phone":"+1 212 967 1222",
    "sg:postcode":"10018",
    "sg:province":"NY",
    "sg:tags":[
        "investing"
    ],
    "wof:name":"Seafire Capital Management",
    "wof:placetype":"venue"
},
  "geometry": {"coordinates":[-73.997895,40.756582],"type":"Point"}
}