{
  "type": "Feature",
  "properties": {
    "iso:country":"US",
    "sg:address":"155 E 34th St",
    "sg:city":"New York",
    "sg:classifiers":[
        {
            "category":"Building & Trades",
            "subcategory":"Locksmith",
            "type":"Services"
        }
    ],
    "sg:phone":"+1 646 237 1133",
    "sg:postcode":"10016",
    "sg:province":"NY",
    "sg:tags":[
        "key"
    ],
    "wof:name":"Abca 24 Hour Locksmith",
    "wof:placetype":"venue"
},
  "geometry": {"coordinates":[-73.97930100000001,40.746201],"type":"Point"}
}