{
  "type": "Feature",
  "properties": {
    "addr:full":"250 Rumsey Rd Yonkers NY 10705",
    "addr:housenumber":"250",
    "addr:postcode":"10705",
    "addr:street":"Rumsey Rd",
    "iso:country":"US",
    "sg:address":"250 Rumsey Rd",
    "sg:city":"Yonkers",
    "sg:classifiers":[
        {
            "category":"Health Services",
            "subcategory":"Doctor",
            "type":"Services"
        }
    ],
    "sg:phone":"+1 914 963 1034",
    "sg:postcode":"10705",
    "sg:province":"NY",
    "sg:tags":[
        "dentist"
    ],
    "wof:name":"Max Rothschild DDS",
    "wof:placetype":"venue"
},
  "geometry": {"coordinates":[-73.88386,40.927229],"type":"Point"}
}