{
  "type": "Feature",
  "properties": {
    "iso:country":"US",
    "sg:address":"186 Van Dyke St",
    "sg:city":"Brooklyn",
    "sg:classifiers":[
        {
            "category":"Wholesale",
            "subcategory":"Home Furnishings",
            "type":"Manufacturing & Wholesale Goods"
        }
    ],
    "sg:phone":"+1 718 222 1234",
    "sg:postcode":"11231",
    "sg:province":"NY",
    "sg:tags":[
        "blind",
        "shade"
    ],
    "wof:name":"Al Einstein Window Fashion Inc",
    "wof:placetype":"venue"
},
  "geometry": {"coordinates":[-74.016899,40.677299],"type":"Point"}
}