{
  "type": "Feature",
  "properties": {
    "addr:full":"102 Newbury Hollow Ln Syracuse NY 13210",
    "addr:housenumber":"102",
    "addr:postcode":"13210",
    "addr:street":"Newbury Hollow Ln",
    "iso:country":"US",
    "sg:address":"102 Newbury Hollow Ln",
    "sg:city":"Syracuse",
    "sg:classifiers":[
        {
            "category":"Sports & Exercise",
            "subcategory":"Gym",
            "type":"Entertainment"
        }
    ],
    "sg:phone":"+1 315 475 4290",
    "sg:postcode":"13210",
    "sg:province":"NY",
    "sg:tags":[
        "facility",
        "salon",
        "physical",
        "beauty",
        "fitness"
    ],
    "wof:name":"Cosmos Oriental Health Spa",
    "wof:placetype":"venue"
},
  "geometry": {"coordinates":[-76.13503300000001,43.013246],"type":"Point"}
}