{
  "type": "Feature",
  "properties": {
    "addr:full":"679 Riverside Dr New York NY 10031",
    "addr:housenumber":"679",
    "addr:postcode":"10031",
    "addr:street":"Riverside Dr",
    "iso:country":"US",
    "sg:address":"679 Riverside Dr",
    "sg:city":"New York",
    "sg:classifiers":[
        {
            "category":"Building & Trades",
            "subcategory":"Construction",
            "type":"Services"
        }
    ],
    "sg:phone":"+1 212 234 3459",
    "sg:postcode":"10031",
    "sg:province":"NY",
    "sg:tags":[
        "contractor"
    ],
    "wof:name":"Liro Program & Construction Management Pc",
    "wof:placetype":"venue"
},
  "geometry": {"coordinates":[-73.953221,40.825923],"type":"Point"}
}