{
  "type": "Feature",
  "properties": {
    "addr:full":"2 Derby Ave Huntington NY 11743",
    "addr:housenumber":"2",
    "addr:postcode":"11743",
    "addr:street":"Derby Ave",
    "iso:country":"US",
    "sg:address":"2 Derby Ave",
    "sg:city":"Huntington",
    "sg:classifiers":[
        {
            "category":"Wholesale",
            "subcategory":"Jewelry",
            "type":"Manufacturing & Wholesale Goods"
        }
    ],
    "sg:phone":"+1   ",
    "sg:postcode":"11743",
    "sg:province":"NY",
    "sg:tags":[
        "stone",
        "metal",
        "precious",
        "mfg"
    ],
    "wof:name":"Sanctuary",
    "wof:placetype":"venue"
},
  "geometry": {"coordinates":[-73.370175,40.851935],"type":"Point"}
}