{
  "type": "Feature",
  "properties": {
    "iso:country":"US",
    "sg:address":"322 E Meadow Ave",
    "sg:city":"East Meadow",
    "sg:classifiers":[
        {
            "category":"Professional",
            "subcategory":"Art Services",
            "type":"Services"
        }
    ],
    "sg:phone":"+1 516 483 8377",
    "sg:postcode":"11554",
    "sg:province":"NY",
    "sg:tags":[
        "graphic",
        "designer"
    ],
    "wof:name":"Design-A-Roni",
    "wof:placetype":"venue"
},
  "geometry": {"coordinates":[-73.559732,40.714371],"type":"Point"}
}