{
  "type": "Feature",
  "properties": {
    "iso:country":"US",
    "sg:address":"574 Ashland Ave",
    "sg:city":"Baldwin",
    "sg:classifiers":[
        {
            "category":"Real Estate",
            "subcategory":"Real Estate Agent",
            "type":"Services"
        }
    ],
    "sg:phone":"+1 516 223 5737",
    "sg:postcode":"11510",
    "sg:province":"NY",
    "wof:name":"Eileen Proietto Realty",
    "wof:placetype":"venue"
},
  "geometry": {"coordinates":[-73.614468,40.661036],"type":"Point"}
}