{
  "type": "Feature",
  "properties": {
    "addr:full":"5 Bellport Ln Bellport NY 11713",
    "addr:housenumber":"5",
    "addr:postcode":"11713",
    "addr:street":"Bellport Ln",
    "iso:country":"US",
    "sg:address":"5 Bellport Ln",
    "sg:city":"Bellport",
    "sg:classifiers":[
        {
            "category":"Health Services",
            "subcategory":"Optometrist",
            "type":"Services"
        }
    ],
    "sg:phone":"+1 631 286 4014",
    "sg:postcode":"11713",
    "sg:province":"NY",
    "sg:tags":[
        "good",
        "optical"
    ],
    "wof:name":"Bellport Optical",
    "wof:placetype":"venue"
},
  "geometry": {"coordinates":[-72.93924699999999,40.757108],"type":"Point"}
}