{
  "type": "Feature",
  "properties": {
    "addr:full":"530 Lexington Ave Rochester NY 14613",
    "addr:housenumber":"530",
    "addr:postcode":"14613",
    "addr:street":"Lexington Ave",
    "iso:country":"US",
    "sg:address":"530 Lexington Ave",
    "sg:city":"Rochester",
    "sg:classifiers":[
        {
            "category":"Education",
            "subcategory":"School",
            "type":"Public Place"
        }
    ],
    "sg:phone":"+1 585 458 3210",
    "sg:postcode":"14613",
    "sg:province":"NY",
    "sg:website":"http://www.easthighschool.net",
    "wof:name":"Public School 34",
    "wof:placetype":"venue"
},
  "geometry": {"coordinates":[-77.644493,43.179272],"type":"Point"}
}