{
  "type": "Feature",
  "properties": {
    "addr:full":"3 Lewis Rd Saratoga Springs NY 12866",
    "addr:housenumber":"3",
    "addr:postcode":"12866",
    "addr:street":"Lewis Rd",
    "iso:country":"US",
    "sg:address":"3 Lewis Rd",
    "sg:city":"Saratoga Springs",
    "sg:classifiers":[
        {
            "category":"Restaurant",
            "type":"Food & Drink"
        }
    ],
    "sg:phone":"+1   ",
    "sg:postcode":"12866",
    "sg:province":"NY",
    "sg:tags":[
        "eating"
    ],
    "wof:name":"Applebees",
    "wof:placetype":"venue"
},
  "geometry": {"coordinates":[-73.75067799999999,43.118866],"type":"Point"}
}