{
  "type": "Feature",
  "properties": {
    "iso:country":"US",
    "sg:address":"7326 Cross Lake Rd",
    "sg:city":"Memphis",
    "sg:classifiers":[
        {
            "category":"Manufacturing",
            "subcategory":"Food",
            "type":"Manufacturing & Wholesale Goods"
        },
        {
            "category":"Farming",
            "subcategory":"Farm",
            "type":"Manufacturing & Wholesale Goods"
        }
    ],
    "sg:phone":"+1 315 635 6165",
    "sg:postcode":"13112",
    "sg:province":"NY",
    "sg:tags":[
        "corn",
        "product"
    ],
    "wof:name":"Schader, Harold Farm",
    "wof:placetype":"venue"
},
  "geometry": {"coordinates":[-76.45985,43.123786],"type":"Point"}
}