{
  "type": "Feature",
  "properties": {
    "iso:country":"US",
    "sg:address":"1686 Logan St",
    "sg:city":"North Bellmore",
    "sg:classifiers":[
        {
            "category":"Wholesale",
            "subcategory":"Furniture",
            "type":"Manufacturing & Wholesale Goods"
        }
    ],
    "sg:phone":"+1 516 783 6491",
    "sg:postcode":"11710",
    "sg:province":"NY",
    "sg:tags":[
        "stool",
        "store"
    ],
    "wof:name":"Custom Display Mfg Ltd",
    "wof:placetype":"venue"
},
  "geometry": {"coordinates":[-73.543098,40.681599],"type":"Point"}
}