{
  "type": "Feature",
  "properties": {
    "iso:country":"US",
    "sg:address":"229 Lake St",
    "sg:city":"Hamburg",
    "sg:classifiers":[
        {
            "category":"Government",
            "subcategory":"Office",
            "type":"Public Place"
        }
    ],
    "sg:phone":"+1 716 646 5227",
    "sg:postcode":"14075",
    "sg:province":"NY",
    "sg:tags":[
        "federal"
    ],
    "sg:website":"www.fra.dot.gov",
    "wof:name":"US Federal Railroad Adm",
    "wof:placetype":"venue"
},
  "geometry": {"coordinates":[-78.838936,42.722407],"type":"Point"}
}