{
  "type": "Feature",
  "properties": {
    "addr:full":"111 E 48th St New York NY 10017",
    "addr:housenumber":"111",
    "addr:postcode":"10017",
    "addr:street":"E 48Th St",
    "iso:country":"US",
    "sg:address":"111 E 48th St",
    "sg:city":"New York",
    "sg:classifiers":[
        {
            "category":"Shopping",
            "subcategory":"Gifts & Souvenirs",
            "type":"Retail Goods"
        }
    ],
    "sg:phone":"+1   ",
    "sg:postcode":"10017",
    "sg:province":"NY",
    "wof:name":"W H Smith Retail",
    "wof:placetype":"venue"
},
  "geometry": {"coordinates":[-73.97371200000001,40.755572],"type":"Point"}
}