{
  "type": "Feature",
  "properties": {
    "iso:country":"US",
    "sg:address":"116 Buffalo St",
    "sg:city":"Canandaigua",
    "sg:classifiers":[
        {
            "category":"Manufacturing",
            "subcategory":"Food",
            "type":"Manufacturing & Wholesale Goods"
        }
    ],
    "sg:phone":"+1 585 396 7600",
    "sg:postcode":"14424",
    "sg:province":"NY",
    "sg:tags":[
        "winery"
    ],
    "sg:website":"www.cwine.com",
    "wof:name":"Centerra Wine Co",
    "wof:placetype":"venue"
},
  "geometry": {"coordinates":[-77.29382200000001,42.896412],"type":"Point"}
}