{
  "type": "Feature",
  "properties": {
    "iso:country":"US",
    "sg:address":"282 Montauk Hwy",
    "sg:city":"East Moriches",
    "sg:classifiers":[
        {
            "category":"Insurance",
            "subcategory":"Health Insurance",
            "type":"Services"
        }
    ],
    "sg:phone":"+1 631 878 1007",
    "sg:postcode":"11940",
    "sg:province":"NY",
    "sg:tags":[
        "market"
    ],
    "sg:website":"www.whollynaturalmarket.com/page...",
    "wof:name":"Wholly Natural Inc",
    "wof:placetype":"venue"
},
  "geometry": {"coordinates":[-72.756798,40.8144],"type":"Point"}
}