{
  "type": "Feature",
  "properties": {
    "addr:full":"3201 East Rd Cazenovia NY 13035",
    "addr:housenumber":"3201",
    "addr:postcode":"13035",
    "addr:street":"East Rd",
    "iso:country":"US",
    "sg:address":"3201 East Rd",
    "sg:city":"Cazenovia",
    "sg:classifiers":[
        {
            "category":"Building & Trades",
            "subcategory":"Construction",
            "type":"Services"
        }
    ],
    "sg:phone":"+1 315 655 4208",
    "sg:postcode":"13035",
    "sg:province":"NY",
    "sg:tags":[
        "house"
    ],
    "wof:name":"M & M Construction & Rmdlg",
    "wof:placetype":"venue"
},
  "geometry": {"coordinates":[-75.847115,42.897745],"type":"Point"}
}