{
  "type": "Feature",
  "properties": {
    "iso:country":"US",
    "sg:address":"1679 58th St Fl 1",
    "sg:city":"Brooklyn",
    "sg:classifiers":[
        {
            "category":"Banks & Credit Unions",
            "subcategory":"Bank",
            "type":"Services"
        },
        {
            "category":"Banks & Credit Unions",
            "subcategory":"Financial Services",
            "type":"Services"
        }
    ],
    "sg:phone":"+1 718 331 5594",
    "sg:postcode":"11204",
    "sg:province":"NY",
    "sg:tags":[
        "investment",
        "management",
        "stock",
        "broker",
        "bond"
    ],
    "wof:name":"Rof Trading Ltd",
    "wof:placetype":"venue"
},
  "geometry": {"coordinates":[-73.98872,40.624742],"type":"Point"}
}