{
  "type": "Feature",
  "properties": {
    "iso:country":"US",
    "sg:address":"90 Broad St",
    "sg:city":"Schuylerville",
    "sg:classifiers":[
        {
            "category":"Shopping",
            "subcategory":"Gifts & Souvenirs",
            "type":"Retail Goods"
        }
    ],
    "sg:phone":"+1 518 695 5243",
    "sg:postcode":"12871",
    "sg:province":"NY",
    "sg:tags":[
        "shop"
    ],
    "wof:name":"Barking Frog",
    "wof:placetype":"venue"
},
  "geometry": {"coordinates":[-73.58151700000001,43.098985],"type":"Point"}
}