{
  "type": "Feature",
  "properties": {
    "addr:full":"565 Liberty Ave Brooklyn NY 11207",
    "addr:housenumber":"565",
    "addr:postcode":"11207",
    "addr:street":"Liberty Ave",
    "iso:country":"US",
    "sg:address":"565 Liberty Ave",
    "sg:city":"Brooklyn",
    "sg:classifiers":[
        {
            "category":"Retail",
            "subcategory":"Repair Shop",
            "type":"Services"
        }
    ],
    "sg:phone":"+1 718 277 2772",
    "sg:postcode":"11207",
    "sg:province":"NY",
    "sg:tags":[
        "ironwork"
    ],
    "wof:name":"Steve & Ronald Iron Work",
    "wof:placetype":"venue"
},
  "geometry": {"coordinates":[-73.88845499999999,40.675663],"type":"Point"}
}