{
  "type": "Feature",
  "properties": {
    "iso:country":"US",
    "sg:address":"691 Wellwood Ave",
    "sg:city":"Lindenhurst",
    "sg:classifiers":[
        {
            "category":"Retail",
            "subcategory":"Auto Repair",
            "type":"Services"
        }
    ],
    "sg:phone":"+1 631 957 8473",
    "sg:postcode":"11757",
    "sg:province":"NY",
    "sg:tags":[
        "repairing",
        "automobile"
    ],
    "wof:name":"Keystone Tire & Auto Repair",
    "wof:placetype":"venue"
},
  "geometry": {"coordinates":[-73.386922,40.704333],"type":"Point"}
}