{
  "type": "Feature",
  "properties": {
    "addr:full":"9 Standish Pl Smithtown NY 11787",
    "addr:housenumber":"9",
    "addr:postcode":"11787",
    "addr:street":"Standish Pl",
    "iso:country":"US",
    "sg:address":"9 Standish Pl",
    "sg:city":"Smithtown",
    "sg:classifiers":[
        {
            "category":"Building & Trades",
            "subcategory":"Construction",
            "type":"Services"
        },
        {
            "category":"Home & Garden",
            "subcategory":"Carpets & Floor Coverings",
            "type":"Retail Goods"
        }
    ],
    "sg:phone":"+1 631 265 8416",
    "sg:postcode":"11787",
    "sg:province":"NY",
    "sg:tags":[
        "carpeting",
        "contractor"
    ],
    "sg:website":"www.fardigfloors.com",
    "wof:name":"Fardig G H & Son Inc",
    "wof:placetype":"venue"
},
  "geometry": {"coordinates":[-73.169601,40.8461],"type":"Point"}
}