{
  "type": "Feature",
  "properties": {
    "iso:country":"US",
    "sg:address":"25 6th Ave",
    "sg:city":"Brooklyn",
    "sg:classifiers":[
        {
            "category":"Professional",
            "subcategory":"Art Services",
            "type":"Services"
        }
    ],
    "sg:phone":"+1 718 783 1915",
    "sg:postcode":"11217",
    "sg:province":"NY",
    "sg:tags":[
        "artist"
    ],
    "wof:name":"Studio Gruss",
    "wof:placetype":"venue"
},
  "geometry": {"coordinates":[-73.97413400000001,40.681563],"type":"Point"}
}