{
  "type": "Feature",
  "properties": {
    "addr:full":"2210 William St Buffalo NY 14206",
    "addr:housenumber":"2210",
    "addr:postcode":"14206",
    "addr:street":"William St",
    "iso:country":"US",
    "sg:address":"2210 William St",
    "sg:city":"Buffalo",
    "sg:classifiers":[
        {
            "category":"Home & Garden",
            "subcategory":"Building Materials",
            "type":"Retail Goods"
        },
        {
            "category":"Building & Trades",
            "subcategory":"Construction",
            "type":"Services"
        },
        {
            "category":"Building & Trades",
            "subcategory":"Electrical",
            "type":"Services"
        }
    ],
    "sg:phone":"+1 716 608 4405",
    "sg:postcode":"14206",
    "sg:province":"NY",
    "sg:tags":[
        "repair",
        "system",
        "specialty",
        "contractor",
        "equipment",
        "furnaces-heating",
        "heating",
        "air conditioning"
    ],
    "sg:website":"http://www.centralheatingandcooling.com",
    "wof:name":"Central Heating and Cooling",
    "wof:placetype":"venue"
},
  "geometry": {"coordinates":[-78.78873,42.884444],"type":"Point"}
}