{
  "type": "Feature",
  "properties": {
    "addr:full":"17 Laight St # 21 New York NY 10013",
    "addr:housenumber":"17;21",
    "addr:postcode":"10013",
    "addr:street":"Laight St #",
    "iso:country":"US",
    "sg:address":"17 Laight St # 21",
    "sg:city":"New York",
    "sg:classifiers":[
        {
            "category":"Shopping",
            "subcategory":"Clothing, Apparel, & Fashions",
            "type":"Retail Goods"
        }
    ],
    "sg:phone":"+1 212 625 0081",
    "sg:postcode":"10013",
    "sg:province":"NY",
    "sg:tags":[
        "accessory"
    ],
    "sg:website":"www.maryjaeger.com",
    "wof:name":"Mary Jaeger",
    "wof:placetype":"venue"
},
  "geometry": {"coordinates":[-74.00617200000001,40.721757],"type":"Point"}
}