{
  "type": "Feature",
  "properties": {
    "iso:country":"US",
    "sg:address":"158 Lakeland Ave",
    "sg:city":"Sayville",
    "sg:classifiers":[
        {
            "category":"Restaurant",
            "type":"Food & Drink"
        }
    ],
    "sg:menulink":"http://www.allmenus.com/ny/islip/82732-dominos-pizza/menu/",
    "sg:phone":"+1 631 244 2900",
    "sg:postcode":"11782",
    "sg:province":"NY",
    "sg:tags":[
        "american",
        "wing",
        "pizza"
    ],
    "wof:name":"Domino's Pizza",
    "wof:placetype":"venue"
},
  "geometry": {"coordinates":[-73.08869300000001,40.746001],"type":"Point"}
}