{
  "type": "Feature",
  "properties": {
    "iso:country":"US",
    "sg:address":"300 Robbins Ln",
    "sg:city":"Syosset",
    "sg:classifiers":[
        {
            "category":"Manufacturing",
            "subcategory":"Tools & Machinery",
            "type":"Manufacturing & Wholesale Goods"
        }
    ],
    "sg:phone":"+1   ",
    "sg:postcode":"11791",
    "sg:province":"NY",
    "sg:tags":[
        "photo",
        "mfg"
    ],
    "wof:name":"Lockheed Martin",
    "wof:placetype":"venue"
},
  "geometry": {"coordinates":[-73.515941,40.797916],"type":"Point"}
}