{
  "type": "Feature",
  "properties": {
    "addr:full":"407 Long Beach Rd Oceanside NY 11572",
    "addr:housenumber":"407",
    "addr:postcode":"11572",
    "addr:street":"Long Beach Rd",
    "iso:country":"US",
    "sg:address":"407 Long Beach Rd",
    "sg:city":"Oceanside",
    "sg:classifiers":[
        {
            "category":"Restaurant",
            "type":"Food & Drink"
        }
    ],
    "sg:phone":"+1 516 536 0527",
    "sg:postcode":"11572",
    "sg:province":"NY",
    "wof:name":"International House of Pancakes",
    "wof:placetype":"venue"
},
  "geometry": {"coordinates":[-73.638496,40.6371],"type":"Point"}
}