{
  "type": "Feature",
  "properties": {
    "iso:country":"US",
    "sg:address":"13431 Ward Rd",
    "sg:city":"Holland",
    "sg:classifiers":[
        {
            "category":"Building & Trades",
            "subcategory":"Cleaning & Sanitation",
            "type":"Services"
        }
    ],
    "sg:phone":"+1   ",
    "sg:postcode":"14080",
    "sg:province":"NY",
    "sg:tags":[
        "maintenance"
    ],
    "wof:name":"Empire Distributing",
    "wof:placetype":"venue"
},
  "geometry": {"coordinates":[-78.48533500000001,42.610201],"type":"Point"}
}