{
  "type": "Feature",
  "properties": {
    "addr:full":"220 5th Avenue New York NY 10001",
    "addr:housenumber":"220",
    "addr:postcode":"10001",
    "addr:street":"5Th Avenue",
    "iso:country":"US",
    "sg:address":"220 5th Avenue",
    "sg:city":"New York",
    "sg:classifiers":[
        {
            "category":"Real Estate",
            "subcategory":"Architect",
            "type":"Services"
        }
    ],
    "sg:phone":"+1 212 229 9211",
    "sg:postcode":"10001",
    "sg:province":"NY",
    "wof:name":"Berke Deborah",
    "wof:placetype":"venue"
},
  "geometry": {"coordinates":[-73.988011,40.743718],"type":"Point"}
}