{
  "type": "Feature",
  "properties": {
    "addr:full":"185 Havemeyer St Brooklyn NY 11211",
    "addr:housenumber":"185",
    "addr:postcode":"11211",
    "addr:street":"Havemeyer St",
    "iso:country":"US",
    "sg:address":"185 Havemeyer St",
    "sg:city":"Brooklyn",
    "sg:classifiers":[
        {
            "category":"Personal",
            "subcategory":"Beauty Salon",
            "type":"Services"
        }
    ],
    "sg:phone":"+1   ",
    "sg:postcode":"11211",
    "sg:province":"NY",
    "sg:tags":[
        "shop"
    ],
    "wof:name":"Millennium Nail",
    "wof:placetype":"venue"
},
  "geometry": {"coordinates":[-73.958215,40.710452],"type":"Point"}
}