{
  "type": "Feature",
  "properties": {
    "addr:full":"4015 Casillio Pkwy Clarence NY 14031",
    "addr:housenumber":"4015",
    "addr:postcode":"14031",
    "addr:street":"Casillio Pkwy",
    "iso:country":"US",
    "sg:address":"4015 Casillio Pkwy",
    "sg:city":"Clarence",
    "sg:classifiers":[
        {
            "category":"Animal Shelter",
            "type":"Public Place"
        }
    ],
    "sg:phone":"+1 716 759 2222",
    "sg:postcode":"14031",
    "sg:province":"NY",
    "sg:tags":[
        "seals-o-ring"
    ],
    "sg:website":"http://www.sealanddesign.com",
    "wof:name":"Seal & Design Inc",
    "wof:placetype":"venue"
},
  "geometry": {"coordinates":[-78.63072099999999,42.958734],"type":"Point"}
}