{
  "type": "Feature",
  "properties": {
    "addr:full":"54 Little Neck Pkwy Little Neck NY 11362",
    "addr:housenumber":"54",
    "addr:postcode":"11362",
    "addr:street":"Little Neck Pkwy",
    "iso:country":"US",
    "sg:address":"54 Little Neck Pkwy",
    "sg:city":"Little Neck",
    "sg:classifiers":[
        {
            "category":"Organizations",
            "subcategory":"Religious Organization",
            "type":"Services"
        }
    ],
    "sg:phone":"+1 718 423 1235",
    "sg:postcode":"11362",
    "sg:province":"NY",
    "wof:name":"Temple Torah of Little Neck",
    "wof:placetype":"venue"
},
  "geometry": {"coordinates":[-73.729551,40.768119],"type":"Point"}
}