{
  "type": "Feature",
  "properties": {
    "iso:country":"US",
    "sg:address":"479 Locust Grove Rd",
    "sg:city":"Greenfield Center",
    "sg:classifiers":[
        {
            "category":"Building & Trades",
            "subcategory":"Construction",
            "type":"Services"
        }
    ],
    "sg:phone":"+1 518 893 2844",
    "sg:postcode":"12833",
    "sg:province":"NY",
    "sg:tags":[
        "contractor"
    ],
    "wof:name":"Benjamin Contracting Serv",
    "wof:placetype":"venue"
},
  "geometry": {"coordinates":[-73.830713,43.131538],"type":"Point"}
}