{
  "type": "Feature",
  "properties": {
    "iso:country":"US",
    "sg:address":"70 Main St",
    "sg:city":"Brewster",
    "sg:classifiers":[
        {
            "category":"Restaurant",
            "type":"Food & Drink"
        }
    ],
    "sg:phone":"+1   ",
    "sg:postcode":"10509",
    "sg:province":"NY",
    "sg:tags":[
        "eating"
    ],
    "wof:name":"Pizza Place The",
    "wof:placetype":"venue"
},
  "geometry": {"coordinates":[-73.61854099999999,41.394396],"type":"Point"}
}