{
  "type": "Feature",
  "properties": {
    "addr:full":"2035 Lakeville Rd New Hyde Park NY 11040",
    "addr:housenumber":"2035",
    "addr:postcode":"11040",
    "addr:street":"Lakeville Rd",
    "iso:country":"US",
    "sg:address":"2035 Lakeville Rd",
    "sg:city":"New Hyde Park",
    "sg:classifiers":[
        {
            "category":"Health Services",
            "subcategory":"Doctor",
            "type":"Services"
        }
    ],
    "sg:phone":"+1 516 488 1010",
    "sg:postcode":"11040",
    "sg:province":"NY",
    "sg:tags":[
        "cardiologist"
    ],
    "wof:name":"Dharia Nimish MD",
    "wof:placetype":"venue"
},
  "geometry": {"coordinates":[-73.700918,40.751579],"type":"Point"}
}