{
  "type": "Feature",
  "properties": {
    "iso:country":"US",
    "sg:address":"75 Acorn Ln",
    "sg:city":"Chatham",
    "sg:classifiers":[
        {
            "category":"Building & Trades",
            "subcategory":"Construction",
            "type":"Services"
        }
    ],
    "sg:phone":"+1 518 392 7564",
    "sg:postcode":"12037",
    "sg:province":"NY",
    "sg:tags":[
        "excavating",
        "contractor"
    ],
    "wof:name":"Evergreen Excavating LLC",
    "wof:placetype":"venue"
},
  "geometry": {"coordinates":[-73.564757,42.315292],"type":"Point"}
}