{
  "type": "Feature",
  "properties": {
    "addr:full":"4403 S Salina St Syracuse NY 13205",
    "addr:housenumber":"4403",
    "addr:postcode":"13205",
    "addr:street":"S Salina St",
    "iso:country":"US",
    "sg:address":"4403 S Salina St",
    "sg:city":"Syracuse",
    "sg:classifiers":[
        {
            "category":"Personal",
            "subcategory":"Barber",
            "type":"Services"
        }
    ],
    "sg:phone":"+1 315 492 3412",
    "sg:postcode":"13205",
    "sg:province":"NY",
    "wof:name":"John's Appointment Barber Shop",
    "wof:placetype":"venue"
},
  "geometry": {"coordinates":[-76.143152,43.005339],"type":"Point"}
}