{
  "type": "Feature",
  "properties": {
    "iso:country":"US",
    "sg:address":"330 Broad Hollow Rd",
    "sg:city":"Farmingdale",
    "sg:classifiers":[
        {
            "category":"Manufacturing",
            "subcategory":"Furniture",
            "type":"Manufacturing & Wholesale Goods"
        }
    ],
    "sg:phone":"+1 631 231 0001",
    "sg:postcode":"11735",
    "sg:province":"NY",
    "sg:tags":[
        "mfg",
        "trade",
        "drapery",
        "contractor"
    ],
    "wof:name":"Instant Verticals Inc",
    "wof:placetype":"venue"
},
  "geometry": {"coordinates":[-73.426224,40.718252],"type":"Point"}
}