{
  "type": "Feature",
  "properties": {
    "addr:full":"1866 Elmwood Ave Buffalo NY 14207",
    "addr:housenumber":"1866",
    "addr:postcode":"14207",
    "addr:street":"Elmwood Ave",
    "iso:country":"US",
    "sg:address":"1866 Elmwood Ave",
    "sg:city":"Buffalo",
    "sg:classifiers":[
        {
            "category":"Food & Beverages",
            "subcategory":"Bakery",
            "type":"Retail Goods"
        }
    ],
    "sg:phone":"+1   ",
    "sg:postcode":"14207",
    "sg:province":"NY",
    "wof:name":"Dunkin Donuts",
    "wof:placetype":"venue"
},
  "geometry": {"coordinates":[-78.87838600000001,42.944782],"type":"Point"}
}