{
  "type": "Feature",
  "properties": {
    "iso:country":"US",
    "sg:address":"1568 Central Park Ave",
    "sg:city":"Yonkers",
    "sg:classifiers":[
        {
            "category":"Personal",
            "subcategory":"Beauty Salon",
            "type":"Services"
        }
    ],
    "sg:phone":"+1 914 337 3766",
    "sg:postcode":"10710",
    "sg:province":"NY",
    "wof:name":"Salon Allure",
    "wof:placetype":"venue"
},
  "geometry": {"coordinates":[-73.84353,40.952863],"type":"Point"}
}