{
  "type": "Feature",
  "properties": {
    "iso:country":"US",
    "sg:address":"202 Rachel Carson Way",
    "sg:city":"Ithaca",
    "sg:classifiers":[
        {
            "category":"Personal",
            "type":"Services"
        }
    ],
    "sg:phone":"+1 607 280 8705",
    "sg:postcode":"14850",
    "sg:province":"NY",
    "sg:tags":[
        "image",
        "consultants-personal"
    ],
    "wof:name":"Soundswellstudio",
    "wof:placetype":"venue"
},
  "geometry": {"coordinates":[-76.53948,42.444631],"type":"Point"}
}