{
  "type": "Feature",
  "properties": {
    "addr:full":"204 Keap St Brooklyn NY 11211",
    "addr:housenumber":"204",
    "addr:postcode":"11211",
    "addr:street":"Keap St",
    "iso:country":"US",
    "sg:address":"204 Keap St",
    "sg:city":"Brooklyn",
    "sg:classifiers":[
        {
            "category":"Social Services",
            "subcategory":"Child Care",
            "type":"Services"
        }
    ],
    "sg:phone":"+1 718 384 4735",
    "sg:postcode":"11211",
    "sg:province":"NY",
    "sg:tags":[
        "day"
    ],
    "wof:name":"Yeled Vyalda Head Start",
    "wof:placetype":"venue"
},
  "geometry": {"coordinates":[-73.95756900000001,40.705392],"type":"Point"}
}