{
  "type": "Feature",
  "properties": {
    "addr:full":"32 Lawrence Ave Smithtown NY 11787",
    "addr:housenumber":"32",
    "addr:postcode":"11787",
    "addr:street":"Lawrence Ave",
    "iso:country":"US",
    "sg:address":"32 Lawrence Ave",
    "sg:city":"Smithtown",
    "sg:classifiers":[
        {
            "category":"Health Services",
            "subcategory":"Health Practitioner",
            "type":"Services"
        }
    ],
    "sg:phone":"+1   ",
    "sg:postcode":"11787",
    "sg:province":"NY",
    "wof:name":"Wallman David A DC Dacbn Ccsp",
    "wof:placetype":"venue"
},
  "geometry": {"coordinates":[-73.19353599999999,40.853729],"type":"Point"}
}