{
  "type": "Feature",
  "properties": {
    "iso:country":"US",
    "sg:address":"11 Xavier Dr",
    "sg:city":"Yonkers",
    "sg:classifiers":[
        {
            "category":"Cinema",
            "subcategory":"Movie Rental",
            "type":"Entertainment"
        }
    ],
    "sg:phone":"+1 914 965 1033",
    "sg:postcode":"10704",
    "sg:province":"NY",
    "sg:tags":[
        "leasing",
        "video",
        "disc",
        "tape"
    ],
    "sg:website":"www.blockbuster.com",
    "wof:name":"Blockbuster Video",
    "wof:placetype":"venue"
},
  "geometry": {"coordinates":[-73.852158,40.929125],"type":"Point"}
}