{
  "type": "Feature",
  "properties": {
    "iso:country":"US",
    "sg:address":"112 W 31 St",
    "sg:city":"New York",
    "sg:classifiers":[
        {
            "category":"Professional",
            "subcategory":"Lawyer & Legal Services",
            "type":"Services"
        }
    ],
    "sg:phone":"+1 212 967 3114",
    "sg:postcode":"10001",
    "sg:province":"NY",
    "sg:tags":[
        "attorney"
    ],
    "wof:name":"Key Productions Inc",
    "wof:placetype":"venue"
},
  "geometry": {"coordinates":[-73.99177899999999,40.748887],"type":"Point"}
}