{
  "type": "Feature",
  "properties": {
    "iso:country":"US",
    "sg:address":"1035 Nostrand Ave",
    "sg:city":"Brooklyn",
    "sg:classifiers":[
        {
            "category":"Shopping",
            "subcategory":"Gifts & Souvenirs",
            "type":"Retail Goods"
        }
    ],
    "sg:phone":"+1 718 773 6336",
    "sg:postcode":"11225",
    "sg:province":"NY",
    "sg:tags":[
        "shop"
    ],
    "wof:name":"Angel Stationery & Gifts",
    "wof:placetype":"venue"
},
  "geometry": {"coordinates":[-73.95074,40.66243],"type":"Point"}
}