{
  "type": "Feature",
  "properties": {
    "addr:full":"33 Kavanaugh Rd Honeoye Falls NY 14472",
    "addr:housenumber":"33",
    "addr:postcode":"14472",
    "addr:street":"Kavanaugh Rd",
    "iso:country":"US",
    "sg:address":"33 Kavanaugh Rd",
    "sg:city":"Honeoye Falls",
    "sg:classifiers":[
        {
            "category":"Banks & Credit Unions",
            "subcategory":"Investment Brokerage",
            "type":"Services"
        }
    ],
    "sg:phone":"+1 585 275 3916",
    "sg:postcode":"14472",
    "sg:province":"NY",
    "sg:tags":[
        "consulting",
        "financial"
    ],
    "wof:name":"Michael Barclay",
    "wof:placetype":"venue"
},
  "geometry": {"coordinates":[-77.64437599999999,42.967733],"type":"Point"}
}