{
  "type": "Feature",
  "properties": {
    "addr:full":"4210 Arthur Kill Rd Staten Island NY 10309",
    "addr:housenumber":"4210",
    "addr:postcode":"10309",
    "addr:street":"Arthur Kill Rd",
    "iso:country":"US",
    "sg:address":"4210 Arthur Kill Rd",
    "sg:city":"Staten Island",
    "sg:classifiers":[
        {
            "category":"Education",
            "subcategory":"School",
            "type":"Public Place"
        }
    ],
    "sg:phone":"+1 718 984 7800",
    "sg:postcode":"10309",
    "sg:province":"NY",
    "wof:name":"Public School 25",
    "wof:placetype":"venue"
},
  "geometry": {"coordinates":[-74.23743,40.540404],"type":"Point"}
}