{
  "type": "Feature",
  "properties": {
    "iso:country":"US",
    "sg:address":"942 E Gun Hill Rd",
    "sg:city":"Bronx",
    "sg:classifiers":[
        {
            "category":"Sports & Exercise",
            "subcategory":"Gym",
            "type":"Entertainment"
        }
    ],
    "sg:phone":"+1 718 882 4760",
    "sg:postcode":"10469",
    "sg:province":"NY",
    "sg:tags":[
        "spa",
        "health"
    ],
    "wof:name":"DDL Barber Shop Two",
    "wof:placetype":"venue"
},
  "geometry": {"coordinates":[-73.85969,40.875229],"type":"Point"}
}