{
  "type": "Feature",
  "properties": {
    "iso:country":"US",
    "sg:address":"6302 E Molloy Rd",
    "sg:city":"East Syracuse",
    "sg:classifiers":[
        {
            "category":"Autos & Motor Vehicles",
            "subcategory":"Auto Supplies",
            "type":"Retail Goods"
        }
    ],
    "sg:phone":"+1 315 463 5973",
    "sg:postcode":"13057",
    "sg:province":"NY",
    "sg:tags":[
        "tire"
    ],
    "wof:name":"Valley Tire Co Inc",
    "wof:placetype":"venue"
},
  "geometry": {"coordinates":[-76.085222,43.099826],"type":"Point"}
}