{
  "type": "Feature",
  "properties": {
    "iso:country":"US",
    "sg:address":"7005 Ave U",
    "sg:city":"Brooklyn",
    "sg:classifiers":[
        {
            "category":"Building & Trades",
            "subcategory":"Construction",
            "type":"Services"
        }
    ],
    "sg:phone":"+1 212 353 3003",
    "sg:postcode":"11234",
    "sg:province":"NY",
    "sg:tags":[
        "hanging",
        "contractor"
    ],
    "wof:name":"Concord Painting",
    "wof:placetype":"venue"
},
  "geometry": {"coordinates":[-73.907517,40.619872],"type":"Point"}
}