{
  "type": "Feature",
  "properties": {
    "iso:country":"US",
    "sg:address":"751 Montauk Hwy",
    "sg:city":"Bayport",
    "sg:classifiers":[
        {
            "category":"Shopping",
            "subcategory":"Clothing, Apparel, & Fashions",
            "type":"Retail Goods"
        }
    ],
    "sg:phone":"+1 631 472 0469",
    "sg:postcode":"11705",
    "sg:province":"NY",
    "wof:name":"YTT Nails",
    "wof:placetype":"venue"
},
  "geometry": {"coordinates":[-73.05375100000001,40.74686],"type":"Point"}
}