{
  "type": "Feature",
  "properties": {
    "addr:full":"135 Pinelawn Rd Melville NY 11747",
    "addr:housenumber":"135",
    "addr:postcode":"11747",
    "addr:street":"Pinelawn Rd",
    "iso:country":"US",
    "sg:address":"135 Pinelawn Rd",
    "sg:city":"Melville",
    "sg:classifiers":[
        {
            "category":"Professional",
            "type":"Services"
        }
    ],
    "sg:phone":"+1 631 293 2170",
    "sg:postcode":"11747",
    "sg:province":"NY",
    "sg:tags":[
        "establishment"
    ],
    "wof:name":"Hardesty & Hanover LLP",
    "wof:placetype":"venue"
},
  "geometry": {"coordinates":[-73.412085,40.785756],"type":"Point"}
}