{
  "type": "Feature",
  "properties": {
    "iso:country":"US",
    "sg:address":"406 New York Ave",
    "sg:city":"Huntington",
    "sg:classifiers":[
        {
            "category":"Restaurant",
            "type":"Food & Drink"
        }
    ],
    "sg:menulink":"http://www.allmenus.com/ny/huntington/148447-subway/menu/",
    "sg:phone":"+1 631 351 8229",
    "sg:postcode":"11743",
    "sg:province":"NY",
    "sg:tags":[
        "american",
        "sandwich"
    ],
    "wof:name":"Subway",
    "wof:placetype":"venue"
},
  "geometry": {"coordinates":[-73.425859,40.868435],"type":"Point"}
}