{
  "type": "Feature",
  "properties": {
    "addr:full":"159 Columbus Ave New York NY 10023",
    "addr:housenumber":"159",
    "addr:postcode":"10023",
    "addr:street":"Columbus Ave",
    "iso:country":"US",
    "sg:address":"159 Columbus Ave",
    "sg:city":"New York",
    "sg:classifiers":[
        {
            "category":"Food & Beverages",
            "subcategory":"Specialty",
            "type":"Retail Goods"
        }
    ],
    "sg:phone":"+1 212 721 1876",
    "sg:postcode":"10023",
    "sg:province":"NY",
    "sg:tags":[
        "health",
        "diet"
    ],
    "wof:name":"GNC",
    "wof:placetype":"venue"
},
  "geometry": {"coordinates":[-73.98075300000001,40.774412],"type":"Point"}
}