{
  "type": "Feature",
  "properties": {
    "addr:full":"11 Brookside Dr Delmar NY 12054",
    "addr:housenumber":"11",
    "addr:postcode":"12054",
    "addr:street":"Brookside Dr",
    "iso:country":"US",
    "sg:address":"11 Brookside Dr",
    "sg:city":"Delmar",
    "sg:classifiers":[
        {
            "category":"Building & Trades",
            "subcategory":"Construction",
            "type":"Services"
        }
    ],
    "sg:phone":"+1 518 475 9071",
    "sg:postcode":"12054",
    "sg:province":"NY",
    "sg:tags":[
        "contractor"
    ],
    "wof:name":"Stephen Koenig",
    "wof:placetype":"venue"
},
  "geometry": {"coordinates":[-73.826025,42.613857],"type":"Point"}
}