{
  "type": "Feature",
  "properties": {
    "addr:full":"74 Morris Ave W Malverne NY 11565",
    "addr:housenumber":"74",
    "addr:postcode":"11565",
    "addr:street":"Morris Ave W",
    "iso:country":"US",
    "sg:address":"74 Morris Ave W",
    "sg:city":"Malverne",
    "sg:classifiers":[
        {
            "category":"Building & Trades",
            "subcategory":"Construction",
            "type":"Services"
        }
    ],
    "sg:phone":"+1 516 561 3328",
    "sg:postcode":"11565",
    "sg:province":"NY",
    "sg:tags":[
        "general",
        "contractor"
    ],
    "wof:name":"All Pride Construction",
    "wof:placetype":"venue"
},
  "geometry": {"coordinates":[-73.675372,40.68084],"type":"Point"}
}