{
  "type": "Feature",
  "properties": {
    "addr:full":"580 N Kings Ave Lindenhurst NY 11757",
    "addr:housenumber":"580",
    "addr:postcode":"11757",
    "addr:street":"N Kings Ave",
    "iso:country":"US",
    "sg:address":"580 N Kings Ave",
    "sg:city":"Lindenhurst",
    "sg:classifiers":[
        {
            "category":"Building & Trades",
            "subcategory":"Plumbing",
            "type":"Services"
        }
    ],
    "sg:phone":"+1 631 884 1172",
    "sg:postcode":"11757",
    "sg:province":"NY",
    "sg:tags":[
        "contractor"
    ],
    "wof:name":"24/7 Hvac Services Inc",
    "wof:placetype":"venue"
},
  "geometry": {"coordinates":[-73.36882900000001,40.699898],"type":"Point"}
}