{
  "type": "Feature",
  "properties": {
    "addr:full":"1269 Erie Ave North Tonawanda NY 14120",
    "addr:housenumber":"1269",
    "addr:postcode":"14120",
    "addr:street":"Erie Ave",
    "iso:country":"US",
    "sg:address":"1269 Erie Ave",
    "sg:city":"North Tonawanda",
    "sg:classifiers":[
        {
            "category":"Restaurant",
            "type":"Food & Drink"
        }
    ],
    "sg:phone":"+1 716 693 6500",
    "sg:postcode":"14120",
    "sg:province":"NY",
    "wof:name":"P J's Casual Dining",
    "wof:placetype":"venue"
},
  "geometry": {"coordinates":[-78.84334800000001,43.05394],"type":"Point"}
}