{
  "type": "Feature",
  "properties": {
    "addr:full":"1 Tilrose Ave Oceanside NY 11572",
    "addr:housenumber":"1",
    "addr:postcode":"11572",
    "addr:street":"Tilrose Ave",
    "iso:country":"US",
    "sg:address":"1 Tilrose Ave",
    "sg:city":"Oceanside",
    "sg:classifiers":[
        {
            "category":"Personal",
            "subcategory":"Nail Salon",
            "type":"Services"
        }
    ],
    "sg:phone":"+1 516 764 3360",
    "sg:postcode":"11572",
    "sg:province":"NY",
    "wof:name":"Lavender Nails",
    "wof:placetype":"venue"
},
  "geometry": {"coordinates":[-73.641296,40.645302],"type":"Point"}
}