{
  "type": "Feature",
  "properties": {
    "addr:full":"40 Central Park S New York NY 10019",
    "addr:housenumber":"40",
    "addr:postcode":"10019",
    "addr:street":"Central Park S",
    "iso:country":"US",
    "sg:address":"40 Central Park S",
    "sg:city":"New York",
    "sg:classifiers":[
        {
            "category":"Professional",
            "type":"Services"
        }
    ],
    "sg:phone":"+1 212 593 1548",
    "sg:postcode":"10019",
    "sg:province":"NY",
    "sg:tags":[
        "establishment"
    ],
    "wof:name":"Larry Aldrich Assocs",
    "wof:placetype":"venue"
},
  "geometry": {"coordinates":[-73.97549100000001,40.765172],"type":"Point"}
}