{
  "type": "Feature",
  "properties": {
    "addr:full":"231 Arlington Ave Brooklyn NY 11207",
    "addr:housenumber":"231",
    "addr:postcode":"11207",
    "addr:street":"Arlington Ave",
    "iso:country":"US",
    "sg:address":"231 Arlington Ave",
    "sg:city":"Brooklyn",
    "sg:classifiers":[
        {
            "category":"Wholesale",
            "subcategory":"Electrical",
            "type":"Manufacturing & Wholesale Goods"
        }
    ],
    "sg:phone":"+1 718 827 0974",
    "sg:postcode":"11207",
    "sg:province":"NY",
    "sg:tags":[
        "electronic"
    ],
    "wof:name":"Gb Entertainment Inc",
    "wof:placetype":"venue"
},
  "geometry": {"coordinates":[-73.886273,40.680661],"type":"Point"}
}