{
  "type": "Feature",
  "properties": {
    "iso:country":"US",
    "sg:address":"11171 Urban Rd",
    "sg:city":"Dunkirk",
    "sg:classifiers":[
        {
            "category":"Retail",
            "subcategory":"Animal Services",
            "type":"Services"
        }
    ],
    "sg:phone":"+1 716 366 1207",
    "sg:postcode":"14048",
    "sg:province":"NY",
    "sg:tags":[
        "pet",
        "grooming",
        "washing"
    ],
    "wof:name":"Patty's Pet Grooming",
    "wof:placetype":"venue"
},
  "geometry": {"coordinates":[-79.29974300000001,42.485531],"type":"Point"}
}