{
  "type": "Feature",
  "properties": {
    "addr:full":"550 Westbury Ave Carle Place NY 11514",
    "addr:housenumber":"550",
    "addr:postcode":"11514",
    "addr:street":"Westbury Ave",
    "iso:country":"US",
    "sg:address":"550 Westbury Ave",
    "sg:city":"Carle Place",
    "sg:classifiers":[
        {
            "category":"Professional",
            "type":"Services"
        }
    ],
    "sg:phone":"+1 516 333 1187",
    "sg:postcode":"11514",
    "sg:province":"NY",
    "sg:tags":[
        "caterer"
    ],
    "wof:name":"Fran Zaslow Catering Inc",
    "wof:placetype":"venue"
},
  "geometry": {"coordinates":[-73.605698,40.7509],"type":"Point"}
}