{
  "type": "Feature",
  "properties": {
    "addr:full":"110 Montcalm St Ticonderoga NY 12883",
    "addr:housenumber":"110",
    "addr:postcode":"12883",
    "addr:street":"Montcalm St",
    "iso:country":"US",
    "sg:address":"110 Montcalm St",
    "sg:city":"Ticonderoga",
    "sg:classifiers":[
        {
            "category":"Shopping",
            "subcategory":"Jewelry",
            "type":"Retail Goods"
        }
    ],
    "sg:phone":"+1   ",
    "sg:postcode":"12883",
    "sg:province":"NY",
    "sg:tags":[
        "store"
    ],
    "wof:name":"Rathbun Jewelers",
    "wof:placetype":"venue"
},
  "geometry": {"coordinates":[-73.42529500000001,43.848839],"type":"Point"}
}