{
  "type": "Feature",
  "properties": {
    "iso:country":"US",
    "sg:address":"104 Wedgewood Dr",
    "sg:city":"Coram",
    "sg:classifiers":[
        {
            "category":"Banks & Credit Unions",
            "subcategory":"Investment Brokerage",
            "type":"Services"
        },
        {
            "category":"Insurance",
            "subcategory":"Hazard Insurance",
            "type":"Services"
        }
    ],
    "sg:phone":"+1 631 331 8557",
    "sg:postcode":"11727",
    "sg:province":"NY",
    "sg:tags":[
        "agent",
        "resume"
    ],
    "wof:name":"I A Glainkin Agency",
    "wof:placetype":"venue"
},
  "geometry": {"coordinates":[-73.023618,40.898255],"type":"Point"}
}