{
  "type": "Feature",
  "properties": {
    "addr:full":"60 Lawrence Bell Dr Buffalo NY 14221",
    "addr:housenumber":"60",
    "addr:postcode":"14221",
    "addr:street":"Lawrence Bell Dr",
    "iso:country":"US",
    "sg:address":"60 Lawrence Bell Dr",
    "sg:city":"Buffalo",
    "sg:classifiers":[
        {
            "category":"Wholesale",
            "subcategory":"Hardware",
            "type":"Manufacturing & Wholesale Goods"
        },
        {
            "category":"Wholesale",
            "subcategory":"Durable Goods & Equipment",
            "type":"Manufacturing & Wholesale Goods"
        }
    ],
    "sg:phone":"+1 716 634 7587",
    "sg:postcode":"14221",
    "sg:province":"NY",
    "sg:tags":[
        "representative",
        "heating",
        "air",
        "conditioning",
        "ventilating",
        "manufacturer"
    ],
    "wof:name":"Quality Plus Inc",
    "wof:placetype":"venue"
},
  "geometry": {"coordinates":[-78.71708099999999,42.952733],"type":"Point"}
}