{
  "type": "Feature",
  "properties": {
    "addr:full":"49 Clinton St New York NY 10002",
    "addr:housenumber":"49",
    "addr:postcode":"10002",
    "addr:street":"Clinton St",
    "iso:country":"US",
    "sg:address":"49 Clinton St",
    "sg:city":"New York",
    "sg:classifiers":[
        {
            "category":"Bars & Pubs",
            "type":"Food & Drink"
        },
        {
            "category":"Restaurant",
            "type":"Food & Drink"
        }
    ],
    "sg:phone":"+1 212 614 3234",
    "sg:postcode":"10002",
    "sg:province":"NY",
    "sg:tags":[
        "gastropubs",
        "british"
    ],
    "sg:website":"www.clerkenwellny.com",
    "wof:name":"The Clerkenwell",
    "wof:placetype":"venue"
},
  "geometry": {"coordinates":[-73.985011,40.719758],"type":"Point"}
}