{
  "type": "Feature",
  "properties": {
    "addr:full":"117 Boyle Rd Selden NY 11784",
    "addr:housenumber":"117",
    "addr:postcode":"11784",
    "addr:street":"Boyle Rd",
    "iso:country":"US",
    "sg:address":"117 Boyle Rd",
    "sg:city":"Selden",
    "sg:classifiers":[
        {
            "category":"Retail",
            "subcategory":"Portrait Studio",
            "type":"Services"
        }
    ],
    "sg:phone":"+1   ",
    "sg:postcode":"11784",
    "sg:province":"NY",
    "sg:tags":[
        "photo",
        "photography",
        "commercial"
    ],
    "wof:name":"Colour Portraits Inc",
    "wof:placetype":"venue"
},
  "geometry": {"coordinates":[-73.050912,40.873688],"type":"Point"}
}