{
  "type": "Feature",
  "properties": {
    "addr:full":"2065 86th Street Brooklyn NY 11214",
    "addr:housenumber":"2065",
    "addr:postcode":"11214",
    "addr:street":"86Th Street",
    "iso:country":"US",
    "sg:address":"2065 86th Street",
    "sg:city":"Brooklyn",
    "sg:classifiers":[
        {
            "category":"Education",
            "subcategory":"Special Training",
            "type":"Public Place"
        }
    ],
    "sg:phone":"+1 718 996 1416",
    "sg:postcode":"11214",
    "sg:province":"NY",
    "sg:tags":[
        "school",
        "language"
    ],
    "wof:name":"Connection American English For Communication",
    "wof:placetype":"venue"
},
  "geometry": {"coordinates":[-73.99785300000001,40.601545],"type":"Point"}
}