{
  "type": "Feature",
  "properties": {
    "addr:full":"37 W 47 St New York NY 10036",
    "addr:housenumber":"37",
    "addr:postcode":"10036",
    "addr:street":"W 47 St",
    "iso:country":"US",
    "sg:address":"37 W 47 St",
    "sg:city":"New York",
    "sg:classifiers":[
        {
            "category":"Wholesale",
            "subcategory":"Jewelry",
            "type":"Manufacturing & Wholesale Goods"
        }
    ],
    "sg:phone":"+1 212 869 5657",
    "sg:postcode":"10036",
    "sg:province":"NY",
    "sg:tags":[
        "precious",
        "diamond"
    ],
    "wof:name":"World Wide Diamond Corp",
    "wof:placetype":"venue"
},
  "geometry": {"coordinates":[-73.980859,40.757584],"type":"Point"}
}