{
  "type": "Feature",
  "properties": {
    "iso:country":"US",
    "sg:address":"211 E 43rd St",
    "sg:city":"New York",
    "sg:classifiers":[
        {
            "category":"Organizations",
            "subcategory":"Political Organization",
            "type":"Services"
        }
    ],
    "sg:phone":"+1 212 687 7755",
    "sg:postcode":"10017",
    "sg:province":"NY",
    "sg:tags":[
        "association"
    ],
    "wof:name":"Parliamentarians Global Action",
    "wof:placetype":"venue"
},
  "geometry": {"coordinates":[-73.97185,40.750655],"type":"Point"}
}