{
  "type": "Feature",
  "properties": {
    "addr:full":"1032 Fort Salonga Rd Northport NY 11768",
    "addr:housenumber":"1032",
    "addr:postcode":"11768",
    "addr:street":"Fort Salonga Rd",
    "iso:country":"US",
    "sg:address":"1032 Fort Salonga Rd",
    "sg:city":"Northport",
    "sg:classifiers":[
        {
            "category":"Health Services",
            "subcategory":"Doctor",
            "type":"Services"
        }
    ],
    "sg:phone":"+1 631 754 3338",
    "sg:postcode":"11768",
    "sg:province":"NY",
    "sg:tags":[
        "podiatrist"
    ],
    "wof:name":"Raio Denise C DPM",
    "wof:placetype":"venue"
},
  "geometry": {"coordinates":[-73.276703,40.9053],"type":"Point"}
}