{
  "type": "Feature",
  "properties": {
    "addr:full":"5922 New Utrecht Avenue Brooklyn NY 11219",
    "addr:housenumber":"5922",
    "addr:postcode":"11219",
    "addr:street":"New Utrecht Avenue",
    "iso:country":"US",
    "sg:address":"5922 New Utrecht Avenue",
    "sg:city":"Brooklyn",
    "sg:classifiers":[
        {
            "category":"Bakery",
            "type":"Food & Drink"
        }
    ],
    "sg:phone":"+1 718 438 7770",
    "sg:postcode":"11219",
    "sg:province":"NY",
    "wof:name":"Savarese Italian Pastry Shop",
    "wof:placetype":"venue"
},
  "geometry": {"coordinates":[-73.99667599999999,40.627754],"type":"Point"}
}