{
  "type": "Feature",
  "properties": {
    "iso:country":"US",
    "sg:address":"1223 Peoples Ave",
    "sg:city":"Troy",
    "sg:classifiers":[
        {
            "category":"Professional",
            "subcategory":"Business Services",
            "type":"Services"
        }
    ],
    "sg:phone":"+1 518 276 2498",
    "sg:postcode":"12180",
    "sg:province":"NY",
    "sg:tags":[
        "information",
        "referral"
    ],
    "wof:name":"Design Info",
    "wof:placetype":"venue"
},
  "geometry": {"coordinates":[-73.67679200000001,42.732999],"type":"Point"}
}