{
  "type": "Feature",
  "properties": {
    "iso:country":"US",
    "sg:address":"1165 State Hwy 29",
    "sg:city":"Greenwich",
    "sg:classifiers":[
        {
            "category":"Shopping",
            "subcategory":"Pharmacy",
            "type":"Retail Goods"
        }
    ],
    "sg:phone":"+1 518 692 0235",
    "sg:postcode":"12834",
    "sg:province":"NY",
    "wof:name":"Hannaford Bros Co",
    "wof:placetype":"venue"
},
  "geometry": {"coordinates":[-73.51264999999999,43.100455],"type":"Point"}
}