{
  "type": "Feature",
  "properties": {
    "addr:full":"3 Lafayette Ave Brooklyn NY 11217",
    "addr:housenumber":"3",
    "addr:postcode":"11217",
    "addr:street":"Lafayette Ave",
    "iso:country":"US",
    "sg:address":"3 Lafayette Ave",
    "sg:city":"Brooklyn",
    "sg:classifiers":[
        {
            "category":"Professional",
            "type":"Services"
        }
    ],
    "sg:phone":"+1 718 858 4765",
    "sg:postcode":"11217",
    "sg:province":"NY",
    "sg:tags":[
        "establishment"
    ],
    "wof:name":"Wilde Associates Of Ny LTD",
    "wof:placetype":"venue"
},
  "geometry": {"coordinates":[-73.978301,40.686881],"type":"Point"}
}