{
  "type": "Feature",
  "properties": {
    "addr:full":"197 Webster Ave New Rochelle NY 10801",
    "addr:housenumber":"197",
    "addr:postcode":"10801",
    "addr:street":"Webster Ave",
    "iso:country":"US",
    "sg:address":"197 Webster Ave",
    "sg:city":"New Rochelle",
    "sg:classifiers":[
        {
            "category":"Local Transit",
            "type":"Transportation"
        }
    ],
    "sg:phone":"+1 914 320 2600",
    "sg:postcode":"10801",
    "sg:province":"NY",
    "sg:tags":[
        "limousine"
    ],
    "wof:name":"Brettel Exec Livery LTD",
    "wof:placetype":"venue"
},
  "geometry": {"coordinates":[-73.791769,40.910206],"type":"Point"}
}