{
  "type": "Feature",
  "properties": {
    "iso:country":"US",
    "sg:address":"5 June Ct",
    "sg:city":"White Plains",
    "sg:classifiers":[
        {
            "category":"Banks & Credit Unions",
            "subcategory":"Bank",
            "type":"Services"
        }
    ],
    "sg:phone":"+1 914 993 9089",
    "sg:postcode":"10605",
    "sg:province":"NY",
    "sg:tags":[
        "broker",
        "mortgage"
    ],
    "wof:name":"SL Brooke & Company Inc",
    "wof:placetype":"venue"
},
  "geometry": {"coordinates":[-73.745943,40.998391],"type":"Point"}
}