{
  "type": "Feature",
  "properties": {
    "iso:country":"US",
    "sg:address":"105 Glen St",
    "sg:city":"Glen Cove",
    "sg:classifiers":[
        {
            "category":"Autos & Motor Vehicles",
            "subcategory":"Automobile Sales",
            "type":"Retail Goods"
        }
    ],
    "sg:phone":"+1   ",
    "sg:postcode":"11542",
    "sg:province":"NY",
    "sg:tags":[
        "body",
        "repair",
        "general"
    ],
    "wof:name":"North Coast Auto Collision",
    "wof:placetype":"venue"
},
  "geometry": {"coordinates":[-73.628106,40.863747],"type":"Point"}
}