{
  "type": "Feature",
  "properties": {
    "addr:full":"942 W Jericho Tpke Smithtown NY 11787",
    "addr:housenumber":"942",
    "addr:postcode":"11787",
    "addr:street":"W Jericho Tpke",
    "iso:country":"US",
    "sg:address":"942 W Jericho Tpke",
    "sg:city":"Smithtown",
    "sg:classifiers":[
        {
            "category":"Restaurant",
            "type":"Food & Drink"
        }
    ],
    "sg:phone":"+1 631 543 1280",
    "sg:postcode":"11787",
    "sg:province":"NY",
    "wof:name":"Wendy's",
    "wof:placetype":"venue"
},
  "geometry": {"coordinates":[-73.25009799999999,40.847804],"type":"Point"}
}