{
  "type": "Feature",
  "properties": {
    "iso:country":"US",
    "sg:address":"3114 Military Rd",
    "sg:city":"Newport",
    "sg:classifiers":[
        {
            "category":"Recreation",
            "type":"Entertainment"
        }
    ],
    "sg:phone":"+1 315 845 8211",
    "sg:postcode":"13416",
    "sg:province":"NY",
    "sg:tags":[
        "center"
    ],
    "wof:name":"Norway Community Hall",
    "wof:placetype":"venue"
},
  "geometry": {"coordinates":[-74.94321600000001,43.203895],"type":"Point"}
}