{
  "type": "Feature",
  "properties": {
    "addr:full":"2250 E Tremont Avenue Bronx NY 10462",
    "addr:housenumber":"2250",
    "addr:postcode":"10462",
    "addr:street":"E Tremont Avenue",
    "iso:country":"US",
    "sg:address":"2250 E Tremont Avenue",
    "sg:city":"Bronx",
    "sg:classifiers":[
        {
            "category":"Professional",
            "subcategory":"Lawyer & Legal Services",
            "type":"Services"
        }
    ],
    "sg:phone":"+1 718 792 5596",
    "sg:postcode":"10462",
    "sg:province":"NY",
    "wof:name":"Joaquin Rivera Atty At Law",
    "wof:placetype":"venue"
},
  "geometry": {"coordinates":[-73.85576,40.842031],"type":"Point"}
}