{
  "type": "Feature",
  "properties": {
    "iso:country":"US",
    "sg:address":"20 W Courtney St",
    "sg:city":"Dunkirk",
    "sg:classifiers":[
        {
            "category":"Retail",
            "subcategory":"Repair Shop",
            "type":"Services"
        }
    ],
    "sg:phone":"+1   ",
    "sg:postcode":"14048",
    "sg:province":"NY",
    "sg:tags":[
        "armature",
        "rewinding",
        "merchandise"
    ],
    "wof:name":"Dunkirk Electric Motor Repair",
    "wof:placetype":"venue"
},
  "geometry": {"coordinates":[-79.321662,42.48039],"type":"Point"}
}