{
  "type": "Feature",
  "properties": {
    "addr:full":"7 E 44th St New York NY 10017",
    "addr:housenumber":"7",
    "addr:postcode":"10017",
    "addr:street":"E 44Th St",
    "iso:country":"US",
    "sg:address":"7 E 44th St",
    "sg:city":"New York",
    "sg:classifiers":[
        {
            "category":"Shopping",
            "subcategory":"Clothing, Apparel, & Fashions",
            "type":"Retail Goods"
        }
    ],
    "sg:phone":"+1 212 687 7642",
    "sg:postcode":"10017",
    "sg:province":"NY",
    "wof:name":"J Press Inc Clothiers",
    "wof:placetype":"venue"
},
  "geometry": {"coordinates":[-73.978538,40.754302],"type":"Point"}
}