{
  "type": "Feature",
  "properties": {
    "iso:country":"US",
    "sg:address":"2 W 86 St",
    "sg:city":"New York",
    "sg:classifiers":[
        {
            "category":"Health Services",
            "subcategory":"Doctor",
            "type":"Services"
        }
    ],
    "sg:phone":"+1 212 769 0666",
    "sg:postcode":"10024",
    "sg:province":"NY",
    "sg:tags":[
        "physician",
        "surgeon"
    ],
    "wof:name":"John F Clark PC",
    "wof:placetype":"venue"
},
  "geometry": {"coordinates":[-73.969802,40.785567],"type":"Point"}
}