{
  "type": "Feature",
  "properties": {
    "iso:country":"US",
    "sg:address":"2408 Grand Concourse",
    "sg:city":"Bronx",
    "sg:classifiers":[
        {
            "category":"Health Services",
            "subcategory":"Clinic",
            "type":"Services"
        }
    ],
    "sg:phone":"+1 718 733 6555",
    "sg:postcode":"10458",
    "sg:province":"NY",
    "sg:tags":[
        "home"
    ],
    "wof:name":"Liberty Home Care Inc",
    "wof:placetype":"venue"
},
  "geometry": {"coordinates":[-73.898532,40.85951],"type":"Point"}
}