{
  "type": "Feature",
  "properties": {
    "addr:full":"311 Wavel St Syracuse NY 13210",
    "addr:housenumber":"311",
    "addr:postcode":"13210",
    "addr:street":"Wavel St",
    "iso:country":"US",
    "sg:address":"311 Wavel St",
    "sg:city":"Syracuse",
    "sg:classifiers":[
        {
            "category":"Local Transit",
            "type":"Transportation"
        }
    ],
    "sg:phone":"+1 315 431 4229",
    "sg:postcode":"13210",
    "sg:province":"NY",
    "sg:tags":[
        "limousine"
    ],
    "wof:name":"Caz Limo",
    "wof:placetype":"venue"
},
  "geometry": {"coordinates":[-76.10420999999999,43.079872],"type":"Point"}
}