{
  "type": "Feature",
  "properties": {
    "iso:country":"US",
    "sg:address":"425 Lexington Avenue",
    "sg:city":"New York",
    "sg:classifiers":[
        {
            "category":"Professional",
            "subcategory":"Lawyer & Legal Services",
            "type":"Services"
        }
    ],
    "sg:phone":"+1 212 455 2000",
    "sg:postcode":"10017",
    "sg:province":"NY",
    "wof:name":"Hall Jeffrey E Atty",
    "wof:placetype":"venue"
},
  "geometry": {"coordinates":[-73.975258,40.752553],"type":"Point"}
}