{
  "type": "Feature",
  "properties": {
    "addr:full":"339 Mamaroneck Ave White Plains NY 10605",
    "addr:housenumber":"339",
    "addr:postcode":"10605",
    "addr:street":"Mamaroneck Ave",
    "iso:country":"US",
    "sg:address":"339 Mamaroneck Ave",
    "sg:city":"White Plains",
    "sg:classifiers":[
        {
            "category":"Shopping",
            "subcategory":"Stationery & Office Supplies",
            "type":"Retail Goods"
        }
    ],
    "sg:phone":"+1 914 328 3900",
    "sg:postcode":"10605",
    "sg:province":"NY",
    "wof:name":"Cartridge World",
    "wof:placetype":"venue"
},
  "geometry": {"coordinates":[-73.763564,41.025371],"type":"Point"}
}