{
  "type": "Feature",
  "properties": {
    "iso:country":"US",
    "sg:address":"79 Briarcliff Rd",
    "sg:city":"Westbury",
    "sg:classifiers":[
        {
            "category":"Professional",
            "type":"Services"
        }
    ],
    "sg:phone":"+1   ",
    "sg:postcode":"11590",
    "sg:province":"NY",
    "wof:name":"Worthway International Inc",
    "wof:placetype":"venue"
},
  "geometry": {"coordinates":[-73.56278500000001,40.776279],"type":"Point"}
}