{
  "type": "Feature",
  "properties": {
    "addr:full":"4270 Lakeville Rd Geneseo NY 14454",
    "addr:postcode":"4270;14454",
    "addr:street":"Lakeville Rd",
    "iso:country":"US",
    "sg:address":"4270 Lakeville Rd",
    "sg:city":"Geneseo",
    "sg:classifiers":[
        {
            "category":"Food & Beverages",
            "subcategory":"Liquor & Beverages",
            "type":"Retail Goods"
        }
    ],
    "sg:phone":"+1 585 243 0220",
    "sg:postcode":"14454",
    "sg:province":"NY",
    "wof:name":"Good Spirits Discount Wine",
    "wof:placetype":"venue"
},
  "geometry": {"coordinates":[-77.78776000000001,42.797339],"type":"Point"}
}