{
  "type": "Feature",
  "properties": {
    "addr:full":"12 Ave O Brooklyn NY 11204",
    "addr:postcode":"11204",
    "addr:street":"12 Ave O",
    "iso:country":"US",
    "sg:address":"12 Ave O",
    "sg:city":"Brooklyn",
    "sg:classifiers":[
        {
            "category":"Travel",
            "subcategory":"Travel Agent",
            "type":"Entertainment"
        }
    ],
    "sg:phone":"+1 718 234 2511",
    "sg:postcode":"11204",
    "sg:province":"NY",
    "sg:tags":[
        "agency",
        "bureau"
    ],
    "wof:name":"Fun Travel Agency",
    "wof:placetype":"venue"
},
  "geometry": {"coordinates":[-73.98418700000001,40.610109],"type":"Point"}
}