{
  "type": "Feature",
  "properties": {
    "iso:country":"US",
    "sg:address":"16 Garrison Dr",
    "sg:city":"Fairport",
    "sg:classifiers":[
        {
            "category":"Home & Garden",
            "subcategory":"Building Materials",
            "type":"Retail Goods"
        }
    ],
    "sg:phone":"+1 585 425 2312",
    "sg:postcode":"14450",
    "sg:province":"NY",
    "sg:tags":[
        "glass",
        "leaded"
    ],
    "wof:name":"Rescued Windows",
    "wof:placetype":"venue"
},
  "geometry": {"coordinates":[-77.422876,43.098987],"type":"Point"}
}