{
  "type": "Feature",
  "properties": {
    "iso:country":"US",
    "sg:address":"24 West Ave",
    "sg:city":"Spencerport",
    "sg:classifiers":[
        {
            "category":"Building & Trades",
            "subcategory":"Electrical",
            "type":"Services"
        }
    ],
    "sg:phone":"+1 585 352 9198",
    "sg:postcode":"14559",
    "sg:province":"NY",
    "sg:tags":[
        "electric",
        "contractor"
    ],
    "wof:name":"Rental Office",
    "wof:placetype":"venue"
},
  "geometry": {"coordinates":[-77.801284,43.191751],"type":"Point"}
}