{
  "type": "Feature",
  "properties": {
    "iso:country":"US",
    "sg:address":"2926 Main St",
    "sg:city":"Caledonia",
    "sg:classifiers":[
        {
            "category":"Freight",
            "type":"Transportation"
        }
    ],
    "sg:phone":"+1 585 538 6100",
    "sg:postcode":"14423",
    "sg:province":"NY",
    "sg:tags":[
        "commercial",
        "storage"
    ],
    "wof:name":"Western Empire Storage",
    "wof:placetype":"venue"
},
  "geometry": {"coordinates":[-77.87161999999999,42.976004],"type":"Point"}
}