{
  "type": "Feature",
  "properties": {
    "addr:full":"516 7th St Brooklyn NY 11215",
    "addr:housenumber":"516",
    "addr:postcode":"11215",
    "addr:street":"7Th St",
    "iso:country":"US",
    "sg:address":"516 7th St",
    "sg:city":"Brooklyn",
    "sg:classifiers":[
        {
            "category":"Organizations",
            "subcategory":"Membership Organization",
            "type":"Services"
        }
    ],
    "sg:phone":"+1 718 768 8347",
    "sg:postcode":"11215",
    "sg:province":"NY",
    "wof:name":"Gattegno Fundation For Educatn",
    "wof:placetype":"venue"
},
  "geometry": {"coordinates":[-73.979529,40.667713],"type":"Point"}
}