{
  "type": "Feature",
  "properties": {
    "iso:country":"US",
    "sg:address":"854 67th St",
    "sg:city":"Brooklyn",
    "sg:classifiers":[
        {
            "category":"Travel",
            "subcategory":"Travel Agent",
            "type":"Entertainment"
        }
    ],
    "sg:phone":"+1   ",
    "sg:postcode":"11220",
    "sg:province":"NY",
    "sg:tags":[
        "operator",
        "tour"
    ],
    "wof:name":"S&J Tour & Bus",
    "wof:placetype":"venue"
},
  "geometry": {"coordinates":[-74.01249,40.63083],"type":"Point"}
}