{
  "type": "Feature",
  "properties": {
    "iso:country":"US",
    "sg:address":"3985 Main St",
    "sg:city":"Warrensburg",
    "sg:classifiers":[
        {
            "category":"Retail",
            "subcategory":"Auto Rental",
            "type":"Services"
        }
    ],
    "sg:phone":"+1 518 623 4298",
    "sg:postcode":"12885",
    "sg:province":"NY",
    "sg:tags":[
        "renting",
        "truck",
        "leasing"
    ],
    "wof:name":"U-Haul Co",
    "wof:placetype":"venue"
},
  "geometry": {"coordinates":[-73.78172499999999,43.500569],"type":"Point"}
}