{
  "type": "Feature",
  "properties": {
    "addr:full":"1002 Burnet Ave Syracuse NY 13203",
    "addr:housenumber":"1002",
    "addr:postcode":"13203",
    "addr:street":"Burnet Ave",
    "iso:country":"US",
    "sg:address":"1002 Burnet Ave",
    "sg:city":"Syracuse",
    "sg:classifiers":[
        {
            "category":"Organizations",
            "subcategory":"Religious Organization",
            "type":"Services"
        }
    ],
    "sg:phone":"+1 315 423 9063",
    "sg:postcode":"13203",
    "sg:province":"NY",
    "sg:tags":[
        "church"
    ],
    "wof:name":"Living Water Ministries",
    "wof:placetype":"venue"
},
  "geometry": {"coordinates":[-76.124528,43.053472],"type":"Point"}
}