{
  "type": "Feature",
  "properties": {
    "iso:country":"US",
    "sg:address":"232 Dakota Ave",
    "sg:city":"Bay Shore",
    "sg:classifiers":[
        {
            "category":"Shopping",
            "subcategory":"Gifts & Souvenirs",
            "type":"Retail Goods"
        }
    ],
    "sg:phone":"+1   ",
    "sg:postcode":"11706",
    "sg:province":"NY",
    "wof:name":"Nautical Nook Inc",
    "wof:placetype":"venue"
},
  "geometry": {"coordinates":[-73.238962,40.744354],"type":"Point"}
}