{
  "type": "Feature",
  "properties": {
    "iso:country":"US",
    "sg:address":"110 Marcus Dr",
    "sg:city":"Melville",
    "sg:classifiers":[
        {
            "category":"Health Services",
            "subcategory":"Clinic",
            "type":"Services"
        }
    ],
    "sg:phone":"+1   ",
    "sg:postcode":"11747",
    "sg:province":"NY",
    "sg:tags":[
        "undetermined"
    ],
    "wof:name":"Melville Mri",
    "wof:placetype":"venue"
},
  "geometry": {"coordinates":[-73.409661,40.759708],"type":"Point"}
}