{
  "type": "Feature",
  "properties": {
    "addr:full":"2295 State Hwy 82 Lagrangeville NY 12569",
    "addr:housenumber":"2295",
    "addr:postcode":"12569",
    "addr:street":"State Hwy 82",
    "iso:country":"US",
    "sg:address":"2295 State Hwy 82",
    "sg:city":"Lagrangeville",
    "sg:classifiers":[
        {
            "category":"Building & Trades",
            "subcategory":"Construction",
            "type":"Services"
        }
    ],
    "sg:phone":"+1 845 223 6111",
    "sg:postcode":"12569",
    "sg:province":"NY",
    "sg:tags":[
        "contractor"
    ],
    "wof:name":"Waterfall Seamless Gutters",
    "wof:placetype":"venue"
},
  "geometry": {"coordinates":[-73.749421,41.701837],"type":"Point"}
}