{
  "type": "Feature",
  "properties": {
    "addr:full":"1026 Avenue of the Americas 5th Fl New York NY 10018",
    "addr:housenumber":"1026",
    "addr:postcode":"10018",
    "addr:street":"Avenue Of The Americas 5Th Fl",
    "iso:country":"US",
    "sg:address":"1026 Avenue of the Americas 5th Fl",
    "sg:city":"New York",
    "sg:classifiers":[
        {
            "category":"Sports & Exercise",
            "subcategory":"Playing Field",
            "type":"Entertainment"
        }
    ],
    "sg:phone":"+1 212 278 8330",
    "sg:postcode":"10018",
    "sg:province":"NY",
    "sg:tags":[
        "instruction",
        "fitness"
    ],
    "sg:website":"www.fluidfitnessny.com/",
    "wof:name":"Fluid Fitness",
    "wof:placetype":"venue"
},
  "geometry": {"coordinates":[-73.985342,40.752483],"type":"Point"}
}