{
  "type": "Feature",
  "properties": {
    "iso:country":"US",
    "sg:address":"2290 Delaware Ave",
    "sg:city":"Buffalo",
    "sg:classifiers":[
        {
            "category":"Health Services",
            "subcategory":"Clinic",
            "type":"Services"
        }
    ],
    "sg:phone":"+1 716 875 1820",
    "sg:postcode":"14216",
    "sg:province":"NY",
    "sg:tags":[
        "outpatient"
    ],
    "wof:name":"C-Pap Xpress",
    "wof:placetype":"venue"
},
  "geometry": {"coordinates":[-78.86829400000001,42.946267],"type":"Point"}
}