{
  "type": "Feature",
  "properties": {
    "addr:full":"4201 New Utrecht Ave Brooklyn NY 11219",
    "addr:housenumber":"4201",
    "addr:postcode":"11219",
    "addr:street":"New Utrecht Ave",
    "iso:country":"US",
    "sg:address":"4201 New Utrecht Ave",
    "sg:city":"Brooklyn",
    "sg:classifiers":[
        {
            "category":"Retail",
            "subcategory":"Auto Repair",
            "type":"Services"
        }
    ],
    "sg:phone":"+1 718 436 4515",
    "sg:postcode":"11219",
    "sg:province":"NY",
    "wof:name":"Hatikva Automobile Wholesale",
    "wof:placetype":"venue"
},
  "geometry": {"coordinates":[-73.994079,40.642706],"type":"Point"}
}