{
  "type": "Feature",
  "properties": {
    "iso:country":"US",
    "sg:address":"214 Morris St",
    "sg:city":"Ogdensburg",
    "sg:classifiers":[
        {
            "category":"Education",
            "subcategory":"School",
            "type":"Public Place"
        }
    ],
    "sg:phone":"+1 315 393 1820",
    "sg:postcode":"13669",
    "sg:province":"NY",
    "sg:tags":[
        "religious"
    ],
    "wof:name":"Bishop Conroy School-Religion",
    "wof:placetype":"venue"
},
  "geometry": {"coordinates":[-75.488356,44.700782],"type":"Point"}
}