{
  "type": "Feature",
  "properties": {
    "iso:country":"US",
    "sg:address":"398 Main St",
    "sg:city":"Schoharie",
    "sg:classifiers":[
        {
            "category":"Utilities",
            "subcategory":"Refuse",
            "type":"Services"
        }
    ],
    "sg:phone":"+1 518 295 7102",
    "sg:postcode":"12157",
    "sg:province":"NY",
    "sg:tags":[
        "rubbish",
        "container",
        "collection",
        "garbage",
        "removal"
    ],
    "wof:name":"Department Of Public Works",
    "wof:placetype":"venue"
},
  "geometry": {"coordinates":[-74.30766300000001,42.67094],"type":"Point"}
}