{
  "type": "Feature",
  "properties": {
    "addr:full":"327 Warren St Hudson NY 12534",
    "addr:housenumber":"327",
    "addr:postcode":"12534",
    "addr:street":"Warren St",
    "iso:country":"US",
    "sg:address":"327 Warren St",
    "sg:city":"Hudson",
    "sg:classifiers":[
        {
            "category":"Museum",
            "type":"Entertainment"
        }
    ],
    "sg:phone":"+1 518 822 1438",
    "sg:postcode":"12534",
    "sg:province":"NY",
    "sg:tags":[
        "information",
        "art",
        "venue",
        "music"
    ],
    "sg:website":"www.hudsonoperahouse.org",
    "wof:name":"Hudson Opera House Inc",
    "wof:placetype":"venue"
},
  "geometry": {"coordinates":[-73.790199,42.252399],"type":"Point"}
}