{
  "type": "Feature",
  "properties": {
    "addr:full":"7274 State Highway 10 Canajoharie NY 13317",
    "addr:housenumber":"7274",
    "addr:postcode":"13317",
    "addr:street":"State Highway 10",
    "iso:country":"US",
    "sg:address":"7274 State Highway 10",
    "sg:city":"Canajoharie",
    "sg:classifiers":[
        {
            "category":"Place Of Worship",
            "subcategory":"Church",
            "type":"Public Place"
        },
        {
            "category":"Place Of Worship",
            "type":"Public Place"
        }
    ],
    "sg:phone":"+1 518 673 3405",
    "sg:postcode":"13317",
    "sg:province":"NY",
    "sg:tags":[
        "churches-baptist-general",
        "churches-baptist"
    ],
    "wof:name":"Cornerstone Baptist Church",
    "wof:placetype":"venue"
},
  "geometry": {"coordinates":[-74.59956,42.84698],"type":"Point"}
}