{
  "type": "Feature",
  "properties": {
    "iso:country":"US",
    "sg:address":"2330 Adam Clayton Powell",
    "sg:city":"New York",
    "sg:classifiers":[
        {
            "category":"Shopping",
            "subcategory":"Clothing, Apparel, & Fashions",
            "type":"Retail Goods"
        }
    ],
    "sg:phone":"+1 212 234 5128",
    "sg:postcode":"10030",
    "sg:province":"NY",
    "sg:tags":[
        "men's",
        "clothing"
    ],
    "sg:website":"www.boyamanyc.com",
    "wof:name":"B Oyama",
    "wof:placetype":"venue"
},
  "geometry": {"coordinates":[-73.942846,40.81909],"type":"Point"}
}