{
  "type": "Feature",
  "properties": {
    "iso:country":"US",
    "sg:address":"3440 Jerome Ave",
    "sg:city":"Bronx",
    "sg:classifiers":[
        {
            "category":"Restaurant",
            "type":"Food & Drink"
        }
    ],
    "sg:menulink":"http://www.allmenus.com/ny/bronx/189085-mcdonalds/menu/",
    "sg:postcode":"10467",
    "sg:province":"NY",
    "sg:tags":[
        "burger",
        "american"
    ],
    "wof:name":"McDonald's",
    "wof:placetype":"venue"
},
  "geometry": {"coordinates":[-73.882491,40.881542],"type":"Point"}
}