{
  "type": "Feature",
  "properties": {
    "addr:full":"1328 Washington St Brushton NY 12916",
    "addr:housenumber":"1328",
    "addr:postcode":"12916",
    "addr:street":"Washington St",
    "iso:country":"US",
    "sg:address":"1328 Washington St",
    "sg:city":"Brushton",
    "sg:classifiers":[
        {
            "category":"Organizations",
            "subcategory":"Non-profit Organization",
            "type":"Services"
        }
    ],
    "sg:phone":"+1 518 529 7314",
    "sg:postcode":"12916",
    "sg:province":"NY",
    "wof:name":"Brushton-Moira Senior Citizens",
    "wof:placetype":"venue"
},
  "geometry": {"coordinates":[-74.50439,44.832814],"type":"Point"}
}