{
  "type": "Feature",
  "properties": {
    "addr:full":"27 W 20th St Ste 1203 New York NY 10011",
    "addr:housenumber":"27;1203",
    "addr:postcode":"10011",
    "addr:street":"W 20Th St Ste",
    "iso:country":"US",
    "sg:address":"27 W 20th St Ste 1203",
    "sg:city":"New York",
    "sg:classifiers":[
        {
            "category":"Health Services",
            "subcategory":"Doctor",
            "type":"Services"
        }
    ],
    "sg:phone":"+1 212 616 8490",
    "sg:postcode":"10011",
    "sg:province":"NY",
    "wof:name":"American Institute For Stuttering",
    "wof:placetype":"venue"
},
  "geometry": {"coordinates":[-73.991724,40.740174],"type":"Point"}
}