{
  "type": "Feature",
  "properties": {
    "iso:country":"US",
    "sg:address":"146 Mountain Rest Rd",
    "sg:city":"New Paltz",
    "sg:classifiers":[
        {
            "category":"Building & Trades",
            "subcategory":"Construction",
            "type":"Services"
        }
    ],
    "sg:phone":"+1 914 475 3555",
    "sg:postcode":"12561",
    "sg:province":"NY",
    "sg:tags":[
        "carpentry",
        "contractor"
    ],
    "wof:name":"Steven Takacs Carptr",
    "wof:placetype":"venue"
},
  "geometry": {"coordinates":[-74.124195,41.769546],"type":"Point"}
}