{
  "type": "Feature",
  "properties": {
    "addr:full":"175 Broadway St Fort Edward NY 12828",
    "addr:housenumber":"175",
    "addr:postcode":"12828",
    "addr:street":"Broadway St",
    "iso:country":"US",
    "sg:address":"175 Broadway St",
    "sg:city":"Fort Edward",
    "sg:classifiers":[
        {
            "category":"Health Services",
            "subcategory":"Doctor",
            "type":"Services"
        }
    ],
    "sg:phone":"+1   ",
    "sg:postcode":"12828",
    "sg:province":"NY",
    "wof:name":"Fort Edward Dental Center",
    "wof:placetype":"venue"
},
  "geometry": {"coordinates":[-73.587451,43.269515],"type":"Point"}
}