{
  "type": "Feature",
  "properties": {
    "iso:country":"US",
    "sg:address":"112 E High St",
    "sg:city":"Painted Post",
    "sg:classifiers":[
        {
            "category":"Food & Beverages",
            "subcategory":"Groceries & Convenience Stores",
            "type":"Retail Goods"
        }
    ],
    "sg:phone":"+1   ",
    "sg:postcode":"14870",
    "sg:province":"NY",
    "sg:tags":[
        "gasoline",
        "station",
        "eating"
    ],
    "wof:name":"A Plus Mini Market",
    "wof:placetype":"venue"
},
  "geometry": {"coordinates":[-77.090165,42.159793],"type":"Point"}
}