{
  "type": "Feature",
  "properties": {
    "iso:country":"US",
    "sg:address":"153 W Buffalo St",
    "sg:city":"Warsaw",
    "sg:classifiers":[
        {
            "category":"Education",
            "subcategory":"School",
            "type":"Public Place"
        }
    ],
    "sg:phone":"+1 585 786 8040",
    "sg:postcode":"14569",
    "sg:province":"NY",
    "sg:tags":[
        "elementary"
    ],
    "wof:name":"Warsaw Elementary School",
    "wof:placetype":"venue"
},
  "geometry": {"coordinates":[-78.13857899999999,42.740315],"type":"Point"}
}