{
  "type": "Feature",
  "properties": {
    "iso:country":"US",
    "sg:address":"103 E Main St",
    "sg:city":"Smithtown",
    "sg:classifiers":[
        {
            "category":"Shopping",
            "subcategory":"Mobile Phones",
            "type":"Retail Goods"
        }
    ],
    "sg:phone":"+1 631 656 0290",
    "sg:postcode":"11787",
    "sg:province":"NY",
    "wof:name":"Globel Incorporated",
    "wof:placetype":"venue"
},
  "geometry": {"coordinates":[-73.190493,40.856051],"type":"Point"}
}