{
  "type": "Feature",
  "properties": {
    "iso:country":"US",
    "sg:address":"5545 Merrick Rd",
    "sg:city":"Massapequa",
    "sg:classifiers":[
        {
            "category":"Professional",
            "type":"Services"
        }
    ],
    "sg:phone":"+1 516 541 0035",
    "sg:postcode":"11758",
    "sg:province":"NY",
    "sg:tags":[
        "establishment"
    ],
    "wof:name":"O K",
    "wof:placetype":"venue"
},
  "geometry": {"coordinates":[-73.433041,40.669311],"type":"Point"}
}