{
  "type": "Feature",
  "properties": {
    "addr:full":"3 Chase St Avoca NY 14809",
    "addr:housenumber":"3",
    "addr:postcode":"14809",
    "addr:street":"Chase St",
    "iso:country":"US",
    "sg:address":"3 Chase St",
    "sg:city":"Avoca",
    "sg:classifiers":[
        {
            "category":"Government",
            "subcategory":"Office",
            "type":"Public Place"
        }
    ],
    "sg:phone":"+1 607 566 2093",
    "sg:postcode":"14809",
    "sg:province":"NY",
    "sg:tags":[
        "village"
    ],
    "wof:name":"Avoca Town Justice",
    "wof:placetype":"venue"
},
  "geometry": {"coordinates":[-77.419967,42.409465],"type":"Point"}
}