{
  "type": "Feature",
  "properties": {
    "iso:country":"US",
    "sg:address":"330 W 38th St",
    "sg:city":"New York",
    "sg:classifiers":[
        {
            "category":"Wholesale",
            "subcategory":"Apparel",
            "type":"Manufacturing & Wholesale Goods"
        }
    ],
    "sg:phone":"+1 212 216 0609",
    "sg:postcode":"10018",
    "sg:province":"NY",
    "sg:tags":[
        "textile",
        "broker"
    ],
    "wof:name":"BTD USA Inc",
    "wof:placetype":"venue"
},
  "geometry": {"coordinates":[-73.993847,40.755475],"type":"Point"}
}