{
  "type": "Feature",
  "properties": {
    "iso:country":"US",
    "sg:address":"8525 Main St",
    "sg:city":"Buffalo",
    "sg:classifiers":[
        {
            "category":"Retail",
            "subcategory":"Self-service Laundry",
            "type":"Services"
        }
    ],
    "sg:phone":"+1   ",
    "sg:postcode":"14221",
    "sg:province":"NY",
    "sg:tags":[
        "coin"
    ],
    "wof:name":"Read Laundry",
    "wof:placetype":"venue"
},
  "geometry": {"coordinates":[-78.676984,42.964978],"type":"Point"}
}