{
  "type": "Feature",
  "properties": {
    "iso:country":"US",
    "sg:address":"125 Broad St",
    "sg:city":"New York",
    "sg:classifiers":[
        {
            "category":"Organizations",
            "subcategory":"Membership Organization",
            "type":"Services"
        }
    ],
    "sg:phone":"+1 212 344 3005",
    "sg:postcode":"10004",
    "sg:province":"NY",
    "sg:tags":[
        "civil",
        "union",
        "liberty"
    ],
    "wof:name":"New Civil Liberty Union",
    "wof:placetype":"venue"
},
  "geometry": {"coordinates":[-74.011298,40.702739],"type":"Point"}
}