{
  "type": "Feature",
  "properties": {
    "iso:country":"US",
    "sg:address":"218 19th St",
    "sg:city":"Watervliet",
    "sg:classifiers":[
        {
            "category":"Professional",
            "subcategory":"Lawyer & Legal Services",
            "type":"Services"
        }
    ],
    "sg:phone":"+1   ",
    "sg:postcode":"12189",
    "sg:province":"NY",
    "wof:name":"Peter M Torncello",
    "wof:placetype":"venue"
},
  "geometry": {"coordinates":[-73.702555,42.730293],"type":"Point"}
}