{
  "type": "Feature",
  "properties": {
    "iso:country":"US",
    "sg:address":"9446 State Hwy 5",
    "sg:city":"Ripley",
    "sg:classifiers":[
        {
            "category":"Retail",
            "subcategory":"Laundry & Dry Cleaning",
            "type":"Services"
        }
    ],
    "sg:phone":"+1 716 736 2532",
    "sg:postcode":"14775",
    "sg:province":"NY",
    "sg:tags":[
        "trade",
        "contractor"
    ],
    "wof:name":"Advanced Drying & Restorations",
    "wof:placetype":"venue"
},
  "geometry": {"coordinates":[-79.674639,42.297165],"type":"Point"}
}