{
  "type": "Feature",
  "properties": {
    "addr:full":"6720 5th Ave Brooklyn NY 11220",
    "addr:housenumber":"6720",
    "addr:postcode":"11220",
    "addr:street":"5Th Ave",
    "iso:country":"US",
    "sg:address":"6720 5th Ave",
    "sg:city":"Brooklyn",
    "sg:classifiers":[
        {
            "category":"Food & Beverages",
            "subcategory":"Meat & Fish",
            "type":"Retail Goods"
        }
    ],
    "sg:phone":"+1 718 833 3223",
    "sg:postcode":"11220",
    "sg:province":"NY",
    "sg:tags":[
        "shop"
    ],
    "wof:name":"Leader Meat Distribution LLC",
    "wof:placetype":"venue"
},
  "geometry": {"coordinates":[-74.052729,40.635064],"type":"Point"}
}