{
  "type": "Feature",
  "properties": {
    "addr:full":"1741 Julia Goldbach Ave Ronkonkoma NY 11779",
    "addr:housenumber":"1741",
    "addr:postcode":"11779",
    "addr:street":"Julia Goldbach Ave",
    "iso:country":"US",
    "sg:address":"1741 Julia Goldbach Ave",
    "sg:city":"Ronkonkoma",
    "sg:classifiers":[
        {
            "category":"Taxi",
            "type":"Transportation"
        }
    ],
    "sg:phone":"+1 631 471 2919",
    "sg:postcode":"11779",
    "sg:province":"NY",
    "sg:tags":[
        "taxicab"
    ],
    "wof:name":"General Island Taxi",
    "wof:placetype":"venue"
},
  "geometry": {"coordinates":[-73.125529,40.788327],"type":"Point"}
}