{
  "type": "Feature",
  "properties": {
    "iso:country":"US",
    "sg:address":"96 Bergen St",
    "sg:city":"Brooklyn",
    "sg:classifiers":[
        {
            "category":"Real Estate",
            "subcategory":"Architect",
            "type":"Services"
        }
    ],
    "sg:phone":"+1 718 625 2079",
    "sg:postcode":"11201",
    "sg:province":"NY",
    "sg:tags":[
        "business",
        "architectural"
    ],
    "sg:website":"www.gvzarchitects.com",
    "wof:name":"G V Z Architects",
    "wof:placetype":"venue"
},
  "geometry": {"coordinates":[-73.988602,40.685902],"type":"Point"}
}