{
  "type": "Feature",
  "properties": {
    "iso:country":"US",
    "sg:address":"244 Ontario St",
    "sg:city":"Cohoes",
    "sg:classifiers":[
        {
            "category":"Health Services",
            "subcategory":"Doctor",
            "type":"Services"
        }
    ],
    "sg:phone":"+1 518 233 8913",
    "sg:postcode":"12047",
    "sg:province":"NY",
    "sg:tags":[
        "physician",
        "surgeon"
    ],
    "wof:name":"Tri-City Radiology",
    "wof:placetype":"venue"
},
  "geometry": {"coordinates":[-73.698505,42.774187],"type":"Point"}
}