{
  "type": "Feature",
  "properties": {
    "addr:full":"137 Brandon Rd Yonkers NY 10704",
    "addr:housenumber":"137",
    "addr:postcode":"10704",
    "addr:street":"Brandon Rd",
    "iso:country":"US",
    "sg:address":"137 Brandon Rd",
    "sg:city":"Yonkers",
    "sg:classifiers":[
        {
            "category":"Building & Trades",
            "subcategory":"Construction",
            "type":"Services"
        }
    ],
    "sg:phone":"+1 914 237 7259",
    "sg:postcode":"10704",
    "sg:province":"NY",
    "sg:tags":[
        "house"
    ],
    "wof:name":"Tricolor Construction Ltd",
    "wof:placetype":"venue"
},
  "geometry": {"coordinates":[-73.848313,40.925132],"type":"Point"}
}