{
  "type": "Feature",
  "properties": {
    "iso:country":"US",
    "sg:address":"251 E 51st St Apt 16E",
    "sg:city":"New York",
    "sg:classifiers":[
        {
            "category":"Real Estate",
            "subcategory":"Architect",
            "type":"Services"
        }
    ],
    "sg:phone":"+1 212 755 3256",
    "sg:postcode":"10022",
    "sg:province":"NY",
    "wof:name":"Surface Links Llc The Mgi Group",
    "wof:placetype":"venue"
},
  "geometry": {"coordinates":[-73.969076,40.756091],"type":"Point"}
}