{
  "type": "Feature",
  "properties": {
    "addr:full":"5040 Brookfield Ln Clarence NY 14031",
    "addr:housenumber":"5040",
    "addr:postcode":"14031",
    "addr:street":"Brookfield Ln",
    "iso:country":"US",
    "sg:address":"5040 Brookfield Ln",
    "sg:city":"Clarence",
    "sg:classifiers":[
        {
            "category":"Professional",
            "subcategory":"Management & Consulting",
            "type":"Services"
        },
        {
            "category":"Social Services",
            "type":"Services"
        }
    ],
    "sg:phone":"+1 716 565 6900",
    "sg:postcode":"14031",
    "sg:province":"NY",
    "sg:tags":[
        "organization",
        "promotion",
        "welfare"
    ],
    "wof:name":"Sponsorship Network",
    "wof:placetype":"venue"
},
  "geometry": {"coordinates":[-78.658372,42.983216],"type":"Point"}
}