{
  "type": "Feature",
  "properties": {
    "addr:full":"2200 Richmond Ave Staten Island NY 10314",
    "addr:housenumber":"2200",
    "addr:postcode":"10314",
    "addr:street":"Richmond Ave",
    "iso:country":"US",
    "sg:address":"2200 Richmond Ave",
    "sg:city":"Staten Island",
    "sg:classifiers":[
        {
            "category":"Utilities",
            "subcategory":"Mobile Phone",
            "type":"Services"
        }
    ],
    "sg:phone":"+1 718 982 6622",
    "sg:postcode":"10314",
    "sg:province":"NY",
    "sg:tags":[
        "telephone",
        "cellular"
    ],
    "wof:name":"Cell Place",
    "wof:placetype":"venue"
},
  "geometry": {"coordinates":[-74.162604,40.593157],"type":"Point"}
}