{
  "type": "Feature",
  "properties": {
    "iso:country":"US",
    "sg:address":"22 Fairway Dr",
    "sg:city":"Manorville",
    "sg:classifiers":[
        {
            "category":"Personal",
            "subcategory":"Beauty Salon",
            "type":"Services"
        }
    ],
    "sg:phone":"+1   ",
    "sg:postcode":"11949",
    "sg:province":"NY",
    "sg:tags":[
        "shop"
    ],
    "wof:name":"Main Street Salon Inc",
    "wof:placetype":"venue"
},
  "geometry": {"coordinates":[-72.783671,40.847789],"type":"Point"}
}