{
  "type": "Feature",
  "properties": {
    "addr:full":"195 Main St Oneonta NY 13820",
    "addr:housenumber":"195",
    "addr:postcode":"13820",
    "addr:street":"Main St",
    "iso:country":"US",
    "sg:address":"195 Main St",
    "sg:city":"Oneonta",
    "sg:classifiers":[
        {
            "category":"Professional",
            "subcategory":"Lawyer & Legal Services",
            "type":"Services"
        }
    ],
    "sg:phone":"+1 607 432 2350",
    "sg:postcode":"13820",
    "sg:province":"NY",
    "sg:tags":[
        "attorney"
    ],
    "wof:name":"Philip J Devine",
    "wof:placetype":"venue"
},
  "geometry": {"coordinates":[-75.061881,42.454001],"type":"Point"}
}