{
  "type": "Feature",
  "properties": {
    "addr:full":"3 Union St Troy NY 12180",
    "addr:housenumber":"3",
    "addr:postcode":"12180",
    "addr:street":"Union St",
    "iso:country":"US",
    "sg:address":"3 Union St",
    "sg:city":"Troy",
    "sg:classifiers":[
        {
            "category":"Shopping",
            "subcategory":"Computers & Home Electronics",
            "type":"Retail Goods"
        }
    ],
    "sg:phone":"+1   ",
    "sg:postcode":"12180",
    "sg:province":"NY",
    "wof:name":"Multi Systems",
    "wof:placetype":"venue"
},
  "geometry": {"coordinates":[-73.68690599999999,42.73234],"type":"Point"}
}