{
  "type": "Feature",
  "properties": {
    "addr:full":"78-26 76th St Queens NY 11385",
    "addr:housenumber":"78-26",
    "addr:postcode":"11385",
    "addr:street":"76Th St",
    "iso:country":"US",
    "sg:address":"78-26 76th St",
    "sg:city":"Queens",
    "sg:classifiers":[
        {
            "category":"Shopping",
            "subcategory":"Jewelry",
            "type":"Retail Goods"
        }
    ],
    "sg:phone":"+1 917 509 3910",
    "sg:postcode":"11385",
    "sg:province":"NY",
    "sg:website":"ballestrasilver.com",
    "wof:name":"Ballestra Silver",
    "wof:placetype":"venue"
},
  "geometry": {"coordinates":[-73.873271,40.703745],"type":"Point"}
}