{
  "type": "Feature",
  "properties": {
    "addr:full":"659 Titus Ave Rochester NY 14617",
    "addr:housenumber":"659",
    "addr:postcode":"14617",
    "addr:street":"Titus Ave",
    "iso:country":"US",
    "sg:address":"659 Titus Ave",
    "sg:city":"Rochester",
    "sg:classifiers":[
        {
            "category":"Personal",
            "subcategory":"Beauty Salon",
            "type":"Services"
        }
    ],
    "sg:phone":"+1 585 266 2170",
    "sg:postcode":"14617",
    "sg:province":"NY",
    "wof:name":"Dawn Pritchard Nail's",
    "wof:placetype":"venue"
},
  "geometry": {"coordinates":[-77.59667399999999,43.210646],"type":"Point"}
}