{
  "type": "Feature",
  "properties": {
    "addr:full":"6375 Furnace Rd Ontario NY 14519",
    "addr:housenumber":"6375",
    "addr:postcode":"14519",
    "addr:street":"Furnace Rd",
    "iso:country":"US",
    "sg:address":"6375 Furnace Rd",
    "sg:city":"Ontario",
    "sg:classifiers":[
        {
            "category":"Manufacturing",
            "subcategory":"Metals",
            "type":"Manufacturing & Wholesale Goods"
        }
    ],
    "sg:phone":"+1   ",
    "sg:postcode":"14519",
    "sg:province":"NY",
    "sg:tags":[
        "mfg",
        "structural"
    ],
    "wof:name":"Integrity Tool Inc",
    "wof:placetype":"venue"
},
  "geometry": {"coordinates":[-77.278143,43.230694],"type":"Point"}
}