{
  "type": "Feature",
  "properties": {
    "iso:country":"US",
    "sg:address":"1717 Crosby Ave",
    "sg:city":"Bronx",
    "sg:classifiers":[
        {
            "category":"Insurance",
            "subcategory":"Insurance Agent",
            "type":"Services"
        }
    ],
    "sg:phone":"+1 718 824 1700",
    "sg:postcode":"10461",
    "sg:province":"NY",
    "sg:website":"www.scovotti.com",
    "wof:name":"Scovotti & Co",
    "wof:placetype":"venue"
},
  "geometry": {"coordinates":[-73.832283,40.846701],"type":"Point"}
}