{
  "type": "Feature",
  "properties": {
    "addr:full":"530 Rte 25A St James NY 11780",
    "addr:housenumber":"530",
    "addr:postcode":"11780",
    "addr:street":"Rte 25A St",
    "iso:country":"US",
    "sg:address":"530 Rte 25A",
    "sg:city":"St James",
    "sg:classifiers":[
        {
            "category":"Personal",
            "subcategory":"Beauty Salon",
            "type":"Services"
        }
    ],
    "sg:phone":"+1 631 862 0633",
    "sg:postcode":"11780",
    "sg:province":"NY",
    "sg:tags":[
        "manicuring"
    ],
    "wof:name":"Butterfly Nail Salon",
    "wof:placetype":"venue"
},
  "geometry": {"coordinates":[-73.156674,40.887728],"type":"Point"}
}