{
  "type": "Feature",
  "properties": {
    "iso:country":"US",
    "sg:address":"240 S Main St",
    "sg:city":"New City",
    "sg:classifiers":[
        {
            "category":"Health Services",
            "subcategory":"Doctor",
            "type":"Services"
        }
    ],
    "sg:phone":"+1 845 634 6755",
    "sg:postcode":"10956",
    "sg:province":"NY",
    "sg:tags":[
        "dentist"
    ],
    "wof:name":"Bernard S Sherman DDS",
    "wof:placetype":"venue"
},
  "geometry": {"coordinates":[-73.990348,41.141809],"type":"Point"}
}