{
  "type": "Feature",
  "properties": {
    "iso:country":"US",
    "sg:address":"900 Old Liverpool Rd",
    "sg:city":"Liverpool",
    "sg:classifiers":[
        {
            "category":"Restaurant",
            "type":"Food & Drink"
        }
    ],
    "sg:phone":"+1 315 453 5555",
    "sg:postcode":"13088",
    "sg:province":"NY",
    "wof:name":"Cape Cod Lobster & Clambake Co",
    "wof:placetype":"venue"
},
  "geometry": {"coordinates":[-76.198717,43.099622],"type":"Point"}
}