{
  "type": "Feature",
  "properties": {
    "addr:full":"11274 Walnut Rd Forestville NY 14062",
    "addr:housenumber":"11274",
    "addr:postcode":"14062",
    "addr:street":"Walnut Rd",
    "iso:country":"US",
    "sg:address":"11274 Walnut Rd",
    "sg:city":"Forestville",
    "sg:classifiers":[
        {
            "category":"Professional",
            "subcategory":"Lawyer & Legal Services",
            "type":"Services"
        }
    ],
    "sg:phone":"+1 716 965 2033",
    "sg:postcode":"14062",
    "sg:province":"NY",
    "sg:tags":[
        "attorney"
    ],
    "wof:name":"Rhinehart White & Steger",
    "wof:placetype":"venue"
},
  "geometry": {"coordinates":[-79.188012,42.48705],"type":"Point"}
}