{
  "type": "Feature",
  "properties": {
    "addr:full":"623 Macon St Brooklyn NY 11233",
    "addr:housenumber":"623",
    "addr:postcode":"11233",
    "addr:street":"Macon St",
    "iso:country":"US",
    "sg:address":"623 Macon St",
    "sg:city":"Brooklyn",
    "sg:classifiers":[
        {
            "category":"Manufacturing",
            "subcategory":"Glass & Minerals",
            "type":"Manufacturing & Wholesale Goods"
        }
    ],
    "sg:phone":"+1   ",
    "sg:postcode":"11233",
    "sg:province":"NY",
    "sg:tags":[
        "concrete",
        "product",
        "mfg"
    ],
    "wof:name":"Walker All Work In General",
    "wof:placetype":"venue"
},
  "geometry": {"coordinates":[-73.92916099999999,40.683437],"type":"Point"}
}