{
  "type": "Feature",
  "properties": {
    "addr:full":"5201 19th Ave Brooklyn NY 11204",
    "addr:housenumber":"5201",
    "addr:postcode":"11204",
    "addr:street":"19Th Ave",
    "iso:country":"US",
    "sg:address":"5201 19th Ave",
    "sg:city":"Brooklyn",
    "sg:classifiers":[
        {
            "category":"Banks & Credit Unions",
            "subcategory":"Financial Services",
            "type":"Services"
        }
    ],
    "sg:phone":"+1 718 377 0168",
    "sg:postcode":"11204",
    "sg:province":"NY",
    "sg:tags":[
        "trust",
        "investment",
        "real estate"
    ],
    "wof:name":"Nick & Panagiota Fronimak",
    "wof:placetype":"venue"
},
  "geometry": {"coordinates":[-73.98098400000001,40.624652],"type":"Point"}
}