{
  "type": "Feature",
  "properties": {
    "iso:country":"US",
    "sg:address":"68 Bromley Rd",
    "sg:city":"Pittsford",
    "sg:classifiers":[
        {
            "category":"Professional",
            "subcategory":"Management & Consulting",
            "type":"Services"
        }
    ],
    "sg:phone":"+1   ",
    "sg:postcode":"14534",
    "sg:province":"NY",
    "wof:name":"Qualvest",
    "wof:placetype":"venue"
},
  "geometry": {"coordinates":[-77.525173,43.060285],"type":"Point"}
}