{
  "type": "Feature",
  "properties": {
    "iso:country":"US",
    "sg:address":"5875 S Transit Rd",
    "sg:city":"Lockport",
    "sg:classifiers":[
        {
            "category":"Banks & Credit Unions",
            "subcategory":"Bank",
            "type":"Services"
        }
    ],
    "sg:phone":"+1 716 439 1596",
    "sg:postcode":"14094",
    "sg:province":"NY",
    "sg:tags":[
        "financing",
        "mortgage"
    ],
    "wof:name":"American General Finance Inc",
    "wof:placetype":"venue"
},
  "geometry": {"coordinates":[-78.696803,43.139285],"type":"Point"}
}