{
  "type": "Feature",
  "properties": {
    "iso:country":"US",
    "sg:address":"76 Montfort Dr",
    "sg:city":"Buffalo",
    "sg:classifiers":[
        {
            "category":"Retail",
            "subcategory":"Repair Shop",
            "type":"Services"
        }
    ],
    "sg:phone":"+1   ",
    "sg:postcode":"14225",
    "sg:province":"NY",
    "wof:name":"Dcl Packaging",
    "wof:placetype":"venue"
},
  "geometry": {"coordinates":[-78.75296899999999,42.948217],"type":"Point"}
}