{
  "type": "Feature",
  "properties": {
    "addr:full":"695 Broadway Amityville NY 11701",
    "addr:housenumber":"695",
    "addr:postcode":"11701",
    "addr:street":"Broadway",
    "iso:country":"US",
    "sg:address":"695 Broadway",
    "sg:city":"Amityville",
    "sg:classifiers":[
        {
            "category":"Restaurant",
            "type":"Food & Drink"
        }
    ],
    "sg:phone":"+1 631 789 1199",
    "sg:postcode":"11701",
    "sg:province":"NY",
    "wof:name":"Golden Wok",
    "wof:placetype":"venue"
},
  "geometry": {"coordinates":[-73.425625,40.698091],"type":"Point"}
}