{
  "type": "Feature",
  "properties": {
    "iso:country":"US",
    "sg:address":"1591 Rte 22",
    "sg:city":"Brewster",
    "sg:classifiers":[
        {
            "category":"Health Services",
            "subcategory":"Health Practitioner",
            "type":"Services"
        }
    ],
    "sg:phone":"+1 845 940 1050",
    "sg:postcode":"10509",
    "sg:province":"NY",
    "sg:tags":[
        "therapy",
        "physical"
    ],
    "wof:name":"Wholistic Physical Therapy",
    "wof:placetype":"venue"
},
  "geometry": {"coordinates":[-73.578503,41.426343],"type":"Point"}
}