{
  "type": "Feature",
  "properties": {
    "addr:full":"217 Linwood Ave Buffalo NY 14209",
    "addr:housenumber":"217",
    "addr:postcode":"14209",
    "addr:street":"Linwood Ave",
    "iso:country":"US",
    "sg:address":"217 Linwood Ave",
    "sg:city":"Buffalo",
    "sg:classifiers":[
        {
            "category":"Health Services",
            "subcategory":"Doctor",
            "type":"Services"
        }
    ],
    "sg:phone":"+1 716 884 8018",
    "sg:postcode":"14209",
    "sg:province":"NY",
    "wof:name":"Baron-Stone Judith MD",
    "wof:placetype":"venue"
},
  "geometry": {"coordinates":[-78.869102,42.908199],"type":"Point"}
}