{
  "type": "Feature",
  "properties": {
    "iso:country":"US",
    "sg:address":"490 Bay St",
    "sg:city":"Staten Island",
    "sg:classifiers":[
        {
            "category":"Local Transit",
            "type":"Transportation"
        }
    ],
    "sg:phone":"+1 718 442 6500",
    "sg:postcode":"10304",
    "sg:province":"NY",
    "sg:tags":[
        "limousine"
    ],
    "wof:name":"New Clifton",
    "wof:placetype":"venue"
},
  "geometry": {"coordinates":[-74.07674400000001,40.629669],"type":"Point"}
}