{
  "type": "Feature",
  "properties": {
    "addr:full":"230 W 116th St New York NY 10026",
    "addr:housenumber":"230",
    "addr:postcode":"10026",
    "addr:street":"W 116Th St",
    "iso:country":"US",
    "sg:address":"230 W 116th St",
    "sg:city":"New York",
    "sg:classifiers":[
        {
            "category":"Travel",
            "subcategory":"Travel Agent",
            "type":"Entertainment"
        }
    ],
    "sg:phone":"+1   ",
    "sg:postcode":"10026",
    "sg:province":"NY",
    "sg:tags":[
        "operator",
        "tour"
    ],
    "wof:name":"Harlem Heritage Tours",
    "wof:placetype":"venue"
},
  "geometry": {"coordinates":[-73.954745,40.803988],"type":"Point"}
}