{
  "type": "Feature",
  "properties": {
    "iso:country":"US",
    "sg:address":"950 Allerton Ave",
    "sg:city":"Bronx",
    "sg:classifiers":[
        {
            "category":"Autos & Motor Vehicles",
            "subcategory":"Fuel & Gas Station",
            "type":"Retail Goods"
        }
    ],
    "sg:phone":"+1 718 519 7391",
    "sg:postcode":"10469",
    "sg:province":"NY",
    "sg:tags":[
        "oil"
    ],
    "wof:name":"Elite Auto Care Inc",
    "wof:placetype":"venue"
},
  "geometry": {"coordinates":[-73.859999,40.865446],"type":"Point"}
}