{
  "type": "Feature",
  "properties": {
    "iso:country":"US",
    "sg:address":"415 S Transit St",
    "sg:city":"Lockport",
    "sg:classifiers":[
        {
            "category":"Professional",
            "subcategory":"Engineering",
            "type":"Services"
        }
    ],
    "sg:phone":"+1 716 625 6933",
    "sg:postcode":"14094",
    "sg:province":"NY",
    "sg:tags":[
        "civil",
        "structural"
    ],
    "sg:website":"www.glynngroup.com",
    "wof:name":"Glynn Geotechnical Engineering",
    "wof:placetype":"venue"
},
  "geometry": {"coordinates":[-78.696944,43.155419],"type":"Point"}
}