{
  "type": "Feature",
  "properties": {
    "iso:country":"US",
    "sg:address":"549 4th St",
    "sg:city":"Niagara Falls",
    "sg:classifiers":[
        {
            "category":"Health Services",
            "subcategory":"Health Practitioner",
            "type":"Services"
        }
    ],
    "sg:phone":"+1 716 284 2848",
    "sg:postcode":"14301",
    "sg:province":"NY",
    "sg:tags":[
        "therapist",
        "physical"
    ],
    "wof:name":"Michael C Gormley",
    "wof:placetype":"venue"
},
  "geometry": {"coordinates":[-79.058063,43.091735],"type":"Point"}
}