{
  "type": "Feature",
  "properties": {
    "addr:full":"220 E 23rd Street Lbby New York NY 10010",
    "addr:housenumber":"220",
    "addr:postcode":"10010",
    "addr:street":"E 23Rd Street",
    "iso:country":"US",
    "sg:address":"220 E 23rd Street Lbby",
    "sg:city":"New York",
    "sg:classifiers":[
        {
            "category":"Communications",
            "type":"Services"
        }
    ],
    "sg:phone":"+1 212 448 9692",
    "sg:postcode":"10010",
    "sg:province":"NY",
    "sg:tags":[
        "web",
        "design"
    ],
    "wof:name":"Happen Studio",
    "wof:placetype":"venue"
},
  "geometry": {"coordinates":[-73.982612,40.738588],"type":"Point"}
}