{
  "type": "Feature",
  "properties": {
    "iso:country":"US",
    "sg:address":"28 Center St",
    "sg:city":"Fort Plain",
    "sg:classifiers":[
        {
            "category":"Building & Trades",
            "subcategory":"Landscaping Services",
            "type":"Services"
        }
    ],
    "sg:phone":"+1 518 993 5472",
    "sg:postcode":"13339",
    "sg:province":"NY",
    "sg:tags":[
        "landscape"
    ],
    "wof:name":"Swadle Inc",
    "wof:placetype":"venue"
},
  "geometry": {"coordinates":[-74.62473900000001,42.931998],"type":"Point"}
}