{
  "type": "Feature",
  "properties": {
    "iso:country":"US",
    "sg:address":"3475 Main St",
    "sg:city":"Strykersville",
    "sg:classifiers":[
        {
            "category":"Building & Trades",
            "subcategory":"Construction",
            "type":"Services"
        }
    ],
    "sg:phone":"+1 585 457 9378",
    "sg:postcode":"14145",
    "sg:province":"NY",
    "sg:tags":[
        "demolition",
        "contractor"
    ],
    "wof:name":"Sheldon Construction Co Inc",
    "wof:placetype":"venue"
},
  "geometry": {"coordinates":[-78.463112,42.717386],"type":"Point"}
}