{
  "type": "Feature",
  "properties": {
    "iso:country":"US",
    "sg:address":"1320 Altamont Ave",
    "sg:city":"Schenectady",
    "sg:classifiers":[
        {
            "category":"Shopping",
            "subcategory":"Department Store",
            "type":"Retail Goods"
        }
    ],
    "sg:phone":"+1   ",
    "sg:postcode":"12303",
    "sg:province":"NY",
    "wof:name":"AJ Wright",
    "wof:placetype":"venue"
},
  "geometry": {"coordinates":[-73.944221,42.785479],"type":"Point"}
}