{
  "type": "Feature",
  "properties": {
    "addr:full":"8413 5th Ave Brooklyn NY 11209",
    "addr:housenumber":"8413",
    "addr:postcode":"11209",
    "addr:street":"5Th Ave",
    "iso:country":"US",
    "sg:address":"8413 5th Ave",
    "sg:city":"Brooklyn",
    "sg:classifiers":[
        {
            "category":"Retail",
            "subcategory":"Self-service Laundry",
            "type":"Services"
        }
    ],
    "sg:phone":"+1 718 238 3648",
    "sg:postcode":"11209",
    "sg:province":"NY",
    "wof:name":"A & A Laundry",
    "wof:placetype":"venue"
},
  "geometry": {"coordinates":[-74.025561,40.622205],"type":"Point"}
}