{
  "type": "Feature",
  "properties": {
    "addr:full":"78 Broad St Schuylerville NY 12871",
    "addr:housenumber":"78",
    "addr:postcode":"12871",
    "addr:street":"Broad St",
    "iso:country":"US",
    "sg:address":"78 Broad St",
    "sg:city":"Schuylerville",
    "sg:classifiers":[
        {
            "category":"Organizations",
            "subcategory":"Professional Association",
            "type":"Services"
        }
    ],
    "sg:phone":"+1 518 695 9228",
    "sg:postcode":"12871",
    "sg:province":"NY",
    "wof:name":"Burgoyne Retreat Youth Ctr",
    "wof:placetype":"venue"
},
  "geometry": {"coordinates":[-73.581407,43.099356],"type":"Point"}
}