{
  "type": "Feature",
  "properties": {
    "iso:country":"US",
    "sg:address":"34-38 38th St",
    "sg:city":"Long Island City",
    "sg:classifiers":[
        {
            "category":"Sports & Exercise",
            "subcategory":"Gym",
            "type":"Entertainment"
        },
        {
            "category":"Sports & Exercise",
            "subcategory":"Swimming Pool",
            "type":"Entertainment"
        }
    ],
    "sg:phone":"+1 718 729 7163",
    "sg:postcode":"11101",
    "sg:province":"NY",
    "sg:website":"www.ascsports1.com",
    "wof:name":"Astoria Sports Complex",
    "wof:placetype":"venue"
},
  "geometry": {"coordinates":[-73.92214300000001,40.756453],"type":"Point"}
}