{
  "type": "Feature",
  "properties": {
    "addr:full":"335 Mossy Brook Rd High Falls NY 12440",
    "addr:housenumber":"335",
    "addr:postcode":"12440",
    "addr:street":"Mossy Brook Rd",
    "iso:country":"US",
    "sg:address":"335 Mossy Brook Rd",
    "sg:city":"High Falls",
    "sg:classifiers":[
        {
            "category":"Building & Trades",
            "subcategory":"Landscaping Services",
            "type":"Services"
        }
    ],
    "sg:phone":"+1 845 687 2104",
    "sg:postcode":"12440",
    "sg:province":"NY",
    "sg:tags":[
        "landscape"
    ],
    "wof:name":"Brook Mossy Landscape",
    "wof:placetype":"venue"
},
  "geometry": {"coordinates":[-74.12355700000001,41.810451],"type":"Point"}
}