{
  "type": "Feature",
  "properties": {
    "iso:country":"US",
    "sg:address":"15 Maiden Ln",
    "sg:city":"New York",
    "sg:classifiers":[
        {
            "category":"Professional",
            "subcategory":"Employment Agencies",
            "type":"Services"
        }
    ],
    "sg:phone":"+1 212 227 2010",
    "sg:postcode":"10038",
    "sg:province":"NY",
    "sg:tags":[
        "consultant",
        "search",
        "instructor",
        "for"
    ],
    "wof:name":"W D P",
    "wof:placetype":"venue"
},
  "geometry": {"coordinates":[-74.00885700000001,40.709123],"type":"Point"}
}