{
  "type": "Feature",
  "properties": {
    "iso:country":"US",
    "sg:address":"3923 Oak Hill Rd",
    "sg:city":"Marietta",
    "sg:classifiers":[
        {
            "category":"Professional",
            "subcategory":"Management & Consulting",
            "type":"Services"
        }
    ],
    "sg:phone":"+1 315 696 0130",
    "sg:postcode":"13110",
    "sg:province":"NY",
    "wof:name":"Oak Hill Associates",
    "wof:placetype":"venue"
},
  "geometry": {"coordinates":[-76.24238099999999,42.864501],"type":"Point"}
}