{
  "type": "Feature",
  "properties": {
    "iso:country":"US",
    "sg:address":"104 W 17 St",
    "sg:city":"New York",
    "sg:classifiers":[
        {
            "category":"Professional",
            "subcategory":"Art Services",
            "type":"Services"
        }
    ],
    "sg:phone":"+1 212 243 6727",
    "sg:postcode":"10011",
    "sg:province":"NY",
    "sg:tags":[
        "graphic",
        "designer"
    ],
    "wof:name":"High Noon Graphics",
    "wof:placetype":"venue"
},
  "geometry": {"coordinates":[-73.99823499999999,40.740355],"type":"Point"}
}