{
  "type": "Feature",
  "properties": {
    "addr:full":"28 Bouck St Tonawanda NY 14150",
    "addr:housenumber":"28",
    "addr:postcode":"14150",
    "addr:street":"Bouck St",
    "iso:country":"US",
    "sg:address":"28 Bouck St",
    "sg:city":"Tonawanda",
    "sg:classifiers":[
        {
            "category":"Personal",
            "subcategory":"Beauty Salon",
            "type":"Services"
        }
    ],
    "sg:phone":"+1 716 693 9031",
    "sg:postcode":"14150",
    "sg:province":"NY",
    "wof:name":"Beauty Mark Hair & Nail Salon",
    "wof:placetype":"venue"
},
  "geometry": {"coordinates":[-78.88467799999999,43.017297],"type":"Point"}
}