{
  "type": "Feature",
  "properties": {
    "iso:country":"US",
    "sg:address":"4014 Boston Rd",
    "sg:city":"Bronx",
    "sg:classifiers":[
        {
            "category":"Wholesale",
            "subcategory":"Medical Equipment & Supplies",
            "type":"Manufacturing & Wholesale Goods"
        }
    ],
    "sg:phone":"+1 718 320 0600",
    "sg:postcode":"10475",
    "sg:province":"NY",
    "sg:tags":[
        "x",
        "apparatus"
    ],
    "wof:name":"Andrew Carothers",
    "wof:placetype":"venue"
},
  "geometry": {"coordinates":[-73.831896,40.884512],"type":"Point"}
}