{
  "type": "Feature",
  "properties": {
    "addr:full":"191 Oakfield Ave Dix Hills NY 11746",
    "addr:housenumber":"191",
    "addr:postcode":"11746",
    "addr:street":"Oakfield Ave",
    "iso:country":"US",
    "sg:address":"191 Oakfield Ave",
    "sg:city":"Dix Hills",
    "sg:classifiers":[
        {
            "category":"Professional",
            "subcategory":"Lawyer & Legal Services",
            "type":"Services"
        }
    ],
    "sg:phone":"+1 631 667 5911",
    "sg:postcode":"11746",
    "sg:province":"NY",
    "sg:tags":[
        "attorney"
    ],
    "wof:name":"Thomas Fernandez",
    "wof:placetype":"venue"
},
  "geometry": {"coordinates":[-73.33264699999999,40.790327],"type":"Point"}
}