{
  "type": "Feature",
  "properties": {
    "iso:country":"US",
    "sg:address":"333 Saw Mill River Rd",
    "sg:city":"Elmsford",
    "sg:classifiers":[
        {
            "category":"Utilities",
            "subcategory":"Mobile Phone",
            "type":"Services"
        }
    ],
    "sg:phone":"+1 914 347 3957",
    "sg:postcode":"10523",
    "sg:province":"NY",
    "sg:tags":[
        "telephone",
        "cellular"
    ],
    "wof:name":"Wireless Retail",
    "wof:placetype":"venue"
},
  "geometry": {"coordinates":[-73.81445600000001,41.065118],"type":"Point"}
}