{
  "type": "Feature",
  "properties": {
    "iso:country":"US",
    "sg:address":"48 Mallard Rd",
    "sg:city":"Manhasset",
    "sg:classifiers":[
        {
            "category":"Organizations",
            "subcategory":"Professional Association",
            "type":"Services"
        }
    ],
    "sg:phone":"+1 516 365 4859",
    "sg:postcode":"11030",
    "sg:province":"NY",
    "sg:tags":[
        "membership"
    ],
    "wof:name":"Yicg",
    "wof:placetype":"venue"
},
  "geometry": {"coordinates":[-73.688616,40.812202],"type":"Point"}
}