{
  "type": "Feature",
  "properties": {
    "addr:full":"878 Jerusalem Ave Uniondale NY 11553",
    "addr:housenumber":"878",
    "addr:postcode":"11553",
    "addr:street":"Jerusalem Ave",
    "iso:country":"US",
    "sg:address":"878 Jerusalem Ave",
    "sg:city":"Uniondale",
    "sg:classifiers":[
        {
            "category":"Wholesale",
            "subcategory":"Fruits & Vegetables",
            "type":"Manufacturing & Wholesale Goods"
        }
    ],
    "sg:phone":"+1 516 489 4441",
    "sg:postcode":"11553",
    "sg:province":"NY",
    "sg:tags":[
        "veggie"
    ],
    "wof:name":"K N J Farms Inc",
    "wof:placetype":"venue"
},
  "geometry": {"coordinates":[-73.587997,40.698799],"type":"Point"}
}