{
  "type": "Feature",
  "properties": {
    "iso:country":"US",
    "sg:address":"2100 Walworth Penfield Rd",
    "sg:city":"Walworth",
    "sg:classifiers":[
        {
            "category":"Health Services",
            "subcategory":"Clinic",
            "type":"Services"
        }
    ],
    "sg:phone":"+1 315 986 0974",
    "sg:postcode":"14568",
    "sg:province":"NY",
    "sg:tags":[
        "home"
    ],
    "wof:name":"Abundant Heart Home Care LLC",
    "wof:placetype":"venue"
},
  "geometry": {"coordinates":[-77.27736400000001,43.139121],"type":"Point"}
}