{
  "type": "Feature",
  "properties": {
    "addr:full":"829 Park Ave New York NY 10021",
    "addr:housenumber":"829",
    "addr:postcode":"10021",
    "addr:street":"Park Ave",
    "iso:country":"US",
    "sg:address":"829 Park Ave",
    "sg:city":"New York",
    "sg:classifiers":[
        {
            "category":"Professional",
            "subcategory":"Management & Consulting",
            "type":"Services"
        }
    ],
    "sg:phone":"+1   ",
    "sg:postcode":"10021",
    "sg:province":"NY",
    "wof:name":"Ziegler Associates",
    "wof:placetype":"venue"
},
  "geometry": {"coordinates":[-73.962074,40.773289],"type":"Point"}
}