{
  "type": "Feature",
  "properties": {
    "addr:full":"310 Greenwich St New York NY 10013",
    "addr:housenumber":"310",
    "addr:postcode":"10013",
    "addr:street":"Greenwich St",
    "iso:country":"US",
    "sg:address":"310 Greenwich St",
    "sg:city":"New York",
    "sg:classifiers":[
        {
            "category":"Park",
            "type":"Public Place"
        }
    ],
    "sg:phone":"+1 212 274 8447",
    "sg:postcode":"10013",
    "sg:province":"NY",
    "sg:website":"www.washingtonmarketpark.org",
    "wof:name":"Washington Market Park",
    "wof:placetype":"venue"
},
  "geometry": {"coordinates":[-74.011459,40.718038],"type":"Point"}
}