{
  "type": "Feature",
  "properties": {
    "addr:full":"1255 50th St Brooklyn NY 11219",
    "addr:housenumber":"1255",
    "addr:postcode":"11219",
    "addr:street":"50Th St",
    "iso:country":"US",
    "sg:address":"1255 50th St",
    "sg:city":"Brooklyn",
    "sg:classifiers":[
        {
            "category":"Organizations",
            "subcategory":"Religious Organization",
            "type":"Services"
        }
    ],
    "sg:phone":"+1 718 633 3007",
    "sg:postcode":"11219",
    "sg:province":"NY",
    "sg:tags":[
        "clergy"
    ],
    "wof:name":"N Markstein",
    "wof:placetype":"venue"
},
  "geometry": {"coordinates":[-73.993551,40.635238],"type":"Point"}
}