{
  "type": "Feature",
  "properties": {
    "addr:full":"4 Ocean Ave Lynbrook NY 11563",
    "addr:housenumber":"4",
    "addr:postcode":"11563",
    "addr:street":"Ocean Ave",
    "iso:country":"US",
    "sg:address":"4 Ocean Ave",
    "sg:city":"Lynbrook",
    "sg:classifiers":[
        {
            "category":"Autos & Motor Vehicles",
            "subcategory":"Fuel & Gas Station",
            "type":"Retail Goods"
        },
        {
            "category":"Retail",
            "subcategory":"Auto Repair",
            "type":"Services"
        }
    ],
    "sg:phone":"+1 516 596 1878",
    "sg:postcode":"11563",
    "sg:province":"NY",
    "wof:name":"Ocean Citgo",
    "wof:placetype":"venue"
},
  "geometry": {"coordinates":[-73.660797,40.667198],"type":"Point"}
}