{
  "type": "Feature",
  "properties": {
    "iso:country":"US",
    "sg:address":"5 Court St",
    "sg:city":"Norwich",
    "sg:classifiers":[
        {
            "category":"Government",
            "subcategory":"Office",
            "type":"Public Place"
        }
    ],
    "sg:phone":"+1 607 337 1470",
    "sg:postcode":"13815",
    "sg:province":"NY",
    "sg:website":"www.co.chenango.ny.us",
    "wof:name":"County Personnel",
    "wof:placetype":"venue"
},
  "geometry": {"coordinates":[-75.525211,42.53147],"type":"Point"}
}