{
  "type": "Feature",
  "properties": {
    "iso:country":"US",
    "sg:address":"246 Middle Country Rd",
    "sg:city":"Coram",
    "sg:classifiers":[
        {
            "category":"Restaurant",
            "type":"Food & Drink"
        }
    ],
    "sg:menulink":"http://www.allmenus.com/ny/brookhaven/257870-bella-romai/menu/",
    "sg:phone":"+1 631 732 3000",
    "sg:postcode":"11727",
    "sg:province":"NY",
    "sg:tags":[
        "pasta",
        "american",
        "italian",
        "salad",
        "pizza"
    ],
    "wof:name":"Bella Romai",
    "wof:placetype":"venue"
},
  "geometry": {"coordinates":[-72.99485,40.871246],"type":"Point"}
}