{
  "type": "Feature",
  "properties": {
    "addr:full":"2138 White Plains Rd Bronx NY 10462",
    "addr:housenumber":"2138",
    "addr:postcode":"10462",
    "addr:street":"White Plains Rd",
    "iso:country":"US",
    "sg:address":"2138 White Plains Rd",
    "sg:city":"Bronx",
    "sg:classifiers":[
        {
            "category":"Shopping",
            "subcategory":"Discount & Variety Stores",
            "type":"Retail Goods"
        }
    ],
    "sg:phone":"+1   ",
    "sg:postcode":"10462",
    "sg:province":"NY",
    "wof:name":"Ninety Nine Cent World",
    "wof:placetype":"venue"
},
  "geometry": {"coordinates":[-73.86772999999999,40.85366],"type":"Point"}
}