{
  "type": "Feature",
  "properties": {
    "addr:full":"50 E Main St Bay Shore NY 11706",
    "addr:housenumber":"50",
    "addr:postcode":"11706",
    "addr:street":"E Main St",
    "iso:country":"US",
    "sg:address":"50 E Main St",
    "sg:city":"Bay Shore",
    "sg:classifiers":[
        {
            "category":"Shopping",
            "type":"Retail Goods"
        }
    ],
    "sg:phone":"+1 631 665 3807",
    "sg:postcode":"11706",
    "sg:province":"NY",
    "sg:tags":[
        "coin",
        "dealer",
        "supply"
    ],
    "wof:name":"Charles Fischer",
    "wof:placetype":"venue"
},
  "geometry": {"coordinates":[-73.24730099999999,40.721713],"type":"Point"}
}