{
  "type": "Feature",
  "properties": {
    "iso:country":"US",
    "sg:address":"104 Middle Neck Rd",
    "sg:city":"Great Neck",
    "sg:classifiers":[
        {
            "category":"Shopping",
            "subcategory":"Clothing, Apparel, & Fashions",
            "type":"Retail Goods"
        }
    ],
    "sg:phone":"+1 516 482 3616",
    "sg:postcode":"11021",
    "sg:province":"NY",
    "sg:tags":[
        "tailor"
    ],
    "wof:name":"E F I's Best Tailors",
    "wof:placetype":"venue"
},
  "geometry": {"coordinates":[-73.729716,40.788807],"type":"Point"}
}