{
  "type": "Feature",
  "properties": {
    "addr:full":"34 Bernie Ln Rochester NY 14624",
    "addr:housenumber":"34",
    "addr:postcode":"14624",
    "addr:street":"Bernie Ln",
    "iso:country":"US",
    "sg:address":"34 Bernie Ln",
    "sg:city":"Rochester",
    "sg:classifiers":[
        {
            "category":"Home & Garden",
            "subcategory":"Garden Supply",
            "type":"Retail Goods"
        }
    ],
    "sg:phone":"+1 585 594 0097",
    "sg:postcode":"14624",
    "sg:province":"NY",
    "sg:tags":[
        "lawn"
    ],
    "wof:name":"United Horticultural Supply",
    "wof:placetype":"venue"
},
  "geometry": {"coordinates":[-77.761945,43.145166],"type":"Point"}
}