{
  "type": "Feature",
  "properties": {
    "addr:full":"450 W Broadway New York NY 10012",
    "addr:housenumber":"450",
    "addr:postcode":"10012",
    "addr:street":"W Broadway",
    "iso:country":"US",
    "sg:address":"450 W Broadway",
    "sg:city":"New York",
    "sg:classifiers":[
        {
            "category":"Shopping",
            "subcategory":"Clothing, Apparel, & Fashions",
            "type":"Retail Goods"
        }
    ],
    "sg:phone":"+1 212 674 1817",
    "sg:postcode":"10012",
    "sg:province":"NY",
    "sg:tags":[
        "clothing",
        "women's"
    ],
    "wof:name":"Max Mara",
    "wof:placetype":"venue"
},
  "geometry": {"coordinates":[-74.000961,40.72611],"type":"Point"}
}