{
  "type": "Feature",
  "properties": {
    "addr:full":"2 Maple Pl Ossining NY 10562",
    "addr:housenumber":"2",
    "addr:postcode":"10562",
    "addr:street":"Maple Pl",
    "iso:country":"US",
    "sg:address":"2 Maple Pl",
    "sg:city":"Ossining",
    "sg:classifiers":[
        {
            "category":"Food & Beverages",
            "subcategory":"Groceries & Convenience Stores",
            "type":"Retail Goods"
        }
    ],
    "sg:phone":"+1 914 923 0301",
    "sg:postcode":"10562",
    "sg:province":"NY",
    "wof:name":"Castillo Meat Market",
    "wof:placetype":"venue"
},
  "geometry": {"coordinates":[-73.86296,41.160098],"type":"Point"}
}