{
  "type": "Feature",
  "properties": {
    "iso:country":"US",
    "sg:address":"174 State St",
    "sg:city":"Auburn",
    "sg:classifiers":[
        {
            "category":"Building & Trades",
            "subcategory":"Electrical",
            "type":"Services"
        }
    ],
    "sg:phone":"+1 315 252 6939",
    "sg:postcode":"13021",
    "sg:province":"NY",
    "sg:tags":[
        "electrical",
        "electric",
        "contractor"
    ],
    "wof:name":"Salva Electric Inc",
    "wof:placetype":"venue"
},
  "geometry": {"coordinates":[-76.57161600000001,42.938132],"type":"Point"}
}