{
  "type": "Feature",
  "properties": {
    "iso:country":"US",
    "sg:address":"337 W Broadway # 1",
    "sg:city":"New York",
    "sg:classifiers":[
        {
            "category":"Restaurant",
            "type":"Food & Drink"
        }
    ],
    "sg:phone":"+1 212 625 1112",
    "sg:postcode":"10013",
    "sg:province":"NY",
    "wof:name":"Namaskaar Indian Bistro",
    "wof:placetype":"venue"
},
  "geometry": {"coordinates":[-74.00369999999999,40.722599],"type":"Point"}
}