{
  "type": "Feature",
  "properties": {
    "addr:full":"1083 Delaware Ave Ste 3 Buffalo NY 14209",
    "addr:housenumber":"1083",
    "addr:postcode":"14209",
    "addr:street":"Delaware Ave Ste 3",
    "iso:country":"US",
    "sg:address":"1083 Delaware Ave Ste 3",
    "sg:city":"Buffalo",
    "sg:classifiers":[
        {
            "category":"Health Services",
            "subcategory":"Doctor",
            "type":"Services"
        },
        {
            "category":"Health Services",
            "subcategory":"Dentist",
            "type":"Services"
        }
    ],
    "sg:phone":"+1 716 882 1023",
    "sg:postcode":"14209",
    "sg:province":"NY",
    "wof:name":"Haar Jean G DDS MD",
    "wof:placetype":"venue"
},
  "geometry": {"coordinates":[-78.86979700000001,42.9133],"type":"Point"}
}