{
  "type": "Feature",
  "properties": {
    "iso:country":"US",
    "sg:address":"565 Rte 25A",
    "sg:city":"Miller Place",
    "sg:classifiers":[
        {
            "category":"Health Services",
            "subcategory":"Doctor",
            "type":"Services"
        }
    ],
    "sg:phone":"+1 631 209 2827",
    "sg:postcode":"11764",
    "sg:province":"NY",
    "sg:tags":[
        "medical"
    ],
    "wof:name":"Adelaide I Masakayan MD",
    "wof:placetype":"venue"
},
  "geometry": {"coordinates":[-72.981208,40.942549],"type":"Point"}
}