{
  "type": "Feature",
  "properties": {
    "addr:full":"1176 E 8th St Brooklyn NY 11230",
    "addr:housenumber":"1176",
    "addr:postcode":"11230",
    "addr:street":"E 8Th St",
    "iso:country":"US",
    "sg:address":"1176 E 8th St",
    "sg:city":"Brooklyn",
    "sg:classifiers":[
        {
            "category":"Manufacturing",
            "subcategory":"Paper Products",
            "type":"Manufacturing & Wholesale Goods"
        }
    ],
    "sg:phone":"+1   ",
    "sg:postcode":"11230",
    "sg:province":"NY",
    "sg:tags":[
        "packaging",
        "material",
        "mfg"
    ],
    "wof:name":"Lazer Packaging",
    "wof:placetype":"venue"
},
  "geometry": {"coordinates":[-73.967454,40.621476],"type":"Point"}
}