{
  "type": "Feature",
  "properties": {
    "addr:full":"11187 US Hwy 20 Irving NY 14081",
    "addr:housenumber":"11187",
    "addr:postcode":"14081",
    "addr:street":"Us Hwy 20",
    "iso:country":"US",
    "sg:address":"11187 US Hwy 20",
    "sg:city":"Irving",
    "sg:classifiers":[
        {
            "category":"Shopping",
            "subcategory":"Discount & Variety Stores",
            "type":"Retail Goods"
        }
    ],
    "sg:phone":"+1 716 549 6540",
    "sg:postcode":"14081",
    "sg:province":"NY",
    "wof:name":"Doogies",
    "wof:placetype":"venue"
},
  "geometry": {"coordinates":[-79.062393,42.587204],"type":"Point"}
}