{
  "type": "Feature",
  "properties": {
    "iso:country":"US",
    "sg:address":"3226 Watson Blvd",
    "sg:city":"Endicott",
    "sg:classifiers":[
        {
            "category":"Shopping",
            "subcategory":"Clothing, Apparel, & Fashions",
            "type":"Retail Goods"
        }
    ],
    "sg:phone":"+1   ",
    "sg:postcode":"13760",
    "sg:province":"NY",
    "sg:tags":[
        "shop",
        "bridal"
    ],
    "wof:name":"Danel Bridal Salon",
    "wof:placetype":"venue"
},
  "geometry": {"coordinates":[-76.022322,42.110614],"type":"Point"}
}