{
  "type": "Feature",
  "properties": {
    "addr:full":"16001 Jamaica Ave Jamaica NY 11432",
    "addr:housenumber":"16001",
    "addr:postcode":"11432",
    "addr:street":"Jamaica Ave",
    "iso:country":"US",
    "sg:address":"16001 Jamaica Ave",
    "sg:city":"Jamaica",
    "sg:classifiers":[
        {
            "category":"Restaurant",
            "type":"Food & Drink"
        }
    ],
    "sg:menulink":"http://www.allmenus.com/ny/queens/208376-taco-bell/menu/",
    "sg:phone":"+1 718 262 8151",
    "sg:postcode":"11432",
    "sg:province":"NY",
    "sg:tags":[
        "mexican"
    ],
    "wof:name":"Taco Bell",
    "wof:placetype":"venue"
},
  "geometry": {"coordinates":[-73.799177,40.703791],"type":"Point"}
}