{
  "type": "Feature",
  "properties": {
    "iso:country":"US",
    "sg:address":"75 John Glenn Dr",
    "sg:city":"Amherst",
    "sg:classifiers":[
        {
            "category":"Manufacturing",
            "subcategory":"Electronics",
            "type":"Manufacturing & Wholesale Goods"
        }
    ],
    "sg:phone":"+1 716 691 5100",
    "sg:postcode":"14228",
    "sg:province":"NY",
    "sg:tags":[
        "instrument",
        "electronic"
    ],
    "sg:website":"www.kistler.com",
    "wof:name":"Kistler Instrument Corp",
    "wof:placetype":"venue"
},
  "geometry": {"coordinates":[-78.80671599999999,43.032155],"type":"Point"}
}