{
  "type": "Feature",
  "properties": {
    "iso:country":"US",
    "sg:address":"14 Cloverwood Dr",
    "sg:city":"Brockport",
    "sg:classifiers":[
        {
            "category":"Professional",
            "subcategory":"Management & Consulting",
            "type":"Services"
        },
        {
            "category":"Real Estate",
            "subcategory":"Real Estate Operator",
            "type":"Services"
        }
    ],
    "sg:phone":"+1 585 637 3730",
    "sg:postcode":"14420",
    "sg:province":"NY",
    "sg:tags":[
        "lessor",
        "floor",
        "marketing",
        "work",
        "laying",
        "n",
        "consultant",
        "property"
    ],
    "wof:name":"G P Land Developers Corp",
    "wof:placetype":"venue"
},
  "geometry": {"coordinates":[-77.920733,43.216328],"type":"Point"}
}