{
  "type": "Feature",
  "properties": {
    "addr:full":"23 Crossman St Alexandria Bay NY 13607",
    "addr:housenumber":"23",
    "addr:postcode":"13607",
    "addr:street":"Crossman St",
    "iso:country":"US",
    "sg:address":"23 Crossman St",
    "sg:city":"Alexandria Bay",
    "sg:classifiers":[
        {
            "category":"Real Estate",
            "subcategory":"Real Estate Operator",
            "type":"Services"
        }
    ],
    "sg:phone":"+1 315 482 9821",
    "sg:postcode":"13607",
    "sg:province":"NY",
    "sg:tags":[
        "boarding",
        "house"
    ],
    "wof:name":"Crossman Rooming House",
    "wof:placetype":"venue"
},
  "geometry": {"coordinates":[-75.91815,44.333681],"type":"Point"}
}