{
  "type": "Feature",
  "properties": {
    "iso:country":"US",
    "sg:address":"154 Grand St.",
    "sg:city":"New York",
    "sg:classifiers":[
        {
            "category":"Professional",
            "subcategory":"Computer Services",
            "type":"Services"
        }
    ],
    "sg:phone":"+1 646 820 0223",
    "sg:postcode":"10013",
    "sg:province":"NY",
    "sg:tags":[
        "private-placements",
        "fundraising",
        "capital-formation",
        "primary-issuance",
        "pipes",
        "placement-agent",
        "securities"
    ],
    "sg:website":"http://www.ACEportal.com",
    "wof:name":"ACE Group",
    "wof:placetype":"venue"
},
  "geometry": {"coordinates":[-73.998565,40.719901],"type":"Point"}
}