{
  "type": "Feature",
  "properties": {
    "addr:full":"140 Merrick Ave Staten Island NY 10301",
    "addr:housenumber":"140",
    "addr:postcode":"10301",
    "addr:street":"Merrick Ave",
    "iso:country":"US",
    "sg:address":"140 Merrick Ave",
    "sg:city":"Staten Island",
    "sg:classifiers":[
        {
            "category":"Communications",
            "type":"Services"
        }
    ],
    "sg:phone":"+1 718 987 7038",
    "sg:postcode":"10301",
    "sg:province":"NY",
    "sg:website":"www.gsignal.com",
    "wof:name":"Global Signal Inc",
    "wof:placetype":"venue"
},
  "geometry": {"coordinates":[-74.108951,40.601548],"type":"Point"}
}