{
  "type": "Feature",
  "properties": {
    "addr:full":"60 W 125th St New York NY 10027",
    "addr:housenumber":"60",
    "addr:postcode":"10027",
    "addr:street":"W 125Th St",
    "iso:country":"US",
    "sg:address":"60 W 125th St",
    "sg:city":"New York",
    "sg:classifiers":[
        {
            "category":"Shopping",
            "subcategory":"Shoes",
            "type":"Retail Goods"
        }
    ],
    "sg:phone":"+1   ",
    "sg:postcode":"10027",
    "sg:province":"NY",
    "wof:name":"Buster Brown Shoes",
    "wof:placetype":"venue"
},
  "geometry": {"coordinates":[-73.944046,40.806888],"type":"Point"}
}