{
  "type": "Feature",
  "properties": {
    "addr:full":"623 Park Ave Rochester NY 14607",
    "addr:housenumber":"623",
    "addr:postcode":"14607",
    "addr:street":"Park Ave",
    "iso:country":"US",
    "sg:address":"623 Park Ave",
    "sg:city":"Rochester",
    "sg:classifiers":[
        {
            "category":"Food & Beverages",
            "subcategory":"Candy",
            "type":"Retail Goods"
        }
    ],
    "sg:phone":"+1   ",
    "sg:postcode":"14607",
    "sg:province":"NY",
    "sg:tags":[
        "confectionery",
        "store"
    ],
    "wof:name":"Stevers Candy Shop",
    "wof:placetype":"venue"
},
  "geometry": {"coordinates":[-77.577974,43.148098],"type":"Point"}
}