{
  "type": "Feature",
  "properties": {
    "addr:full":"1324 E Gun Hill Rd Bronx NY 10469",
    "addr:housenumber":"1324",
    "addr:postcode":"10469",
    "addr:street":"E Gun Hill Rd",
    "iso:country":"US",
    "sg:address":"1324 E Gun Hill Rd",
    "sg:city":"Bronx",
    "sg:classifiers":[
        {
            "category":"Professional",
            "subcategory":"Accounting & Tax Preparation",
            "type":"Services"
        }
    ],
    "sg:phone":"+1 718 652 2844",
    "sg:postcode":"10469",
    "sg:province":"NY",
    "sg:tags":[
        "consultant"
    ],
    "wof:name":"Case-Williams",
    "wof:placetype":"venue"
},
  "geometry": {"coordinates":[-73.847397,40.870996],"type":"Point"}
}