{
  "type": "Feature",
  "properties": {
    "addr:full":"1166 Eastern Pkwy Brooklyn NY 11213",
    "addr:housenumber":"1166",
    "addr:postcode":"11213",
    "addr:street":"Eastern Pkwy",
    "iso:country":"US",
    "sg:address":"1166 Eastern Pkwy",
    "sg:city":"Brooklyn",
    "sg:classifiers":[
        {
            "category":"Health Services",
            "subcategory":"Doctor",
            "type":"Services"
        }
    ],
    "sg:phone":"+1 718 493 7363",
    "sg:postcode":"11213",
    "sg:province":"NY",
    "sg:tags":[
        "medical"
    ],
    "wof:name":"Carole Dubuche MD",
    "wof:placetype":"venue"
},
  "geometry": {"coordinates":[-73.929355,40.668644],"type":"Point"}
}