{
  "type": "Feature",
  "properties": {
    "addr:full":"140 Warsaw St Buffalo NY 14218",
    "addr:housenumber":"140",
    "addr:postcode":"14218",
    "addr:street":"Warsaw St",
    "iso:country":"US",
    "sg:address":"140 Warsaw St",
    "sg:city":"Buffalo",
    "sg:classifiers":[
        {
            "category":"Recreation",
            "type":"Entertainment"
        }
    ],
    "sg:phone":"+1 716 825 9415",
    "sg:postcode":"14218",
    "sg:province":"NY",
    "sg:tags":[
        "hall",
        "auditorium"
    ],
    "wof:name":"St Michael's Auditorium",
    "wof:placetype":"venue"
},
  "geometry": {"coordinates":[-78.82952400000001,42.814767],"type":"Point"}
}