{
  "type": "Feature",
  "properties": {
    "iso:country":"US",
    "sg:address":"10 Maria Ct",
    "sg:city":"Huntington Station",
    "sg:classifiers":[
        {
            "category":"Home & Garden",
            "subcategory":"Hardware",
            "type":"Retail Goods"
        },
        {
            "category":"Wholesale",
            "subcategory":"Hardware",
            "type":"Manufacturing & Wholesale Goods"
        }
    ],
    "sg:phone":"+1 631 427 5543",
    "sg:postcode":"11746",
    "sg:province":"NY",
    "sg:tags":[
        "repair",
        "tool",
        "electrical"
    ],
    "wof:name":"Stevetec Tools",
    "wof:placetype":"venue"
},
  "geometry": {"coordinates":[-73.38576500000001,40.850222],"type":"Point"}
}