{
  "type": "Feature",
  "properties": {
    "addr:full":"7412 35th Avenue Jackson Heights NY 11372",
    "addr:housenumber":"7412",
    "addr:postcode":"11372",
    "addr:street":"35Th Avenue",
    "iso:country":"US",
    "sg:address":"7412 35th Avenue",
    "sg:city":"Jackson Heights",
    "sg:classifiers":[
        {
            "category":"Building & Trades",
            "subcategory":"Construction",
            "type":"Services"
        }
    ],
    "sg:phone":"+1 718 424 6723",
    "sg:postcode":"11372",
    "sg:province":"NY",
    "sg:tags":[
        "contractor"
    ],
    "wof:name":"J K Contracting Service",
    "wof:placetype":"venue"
},
  "geometry": {"coordinates":[-73.892008,40.750991],"type":"Point"}
}