{
  "type": "Feature",
  "properties": {
    "addr:full":"137 Main St Cold Spring NY 10516",
    "addr:housenumber":"137",
    "addr:postcode":"10516",
    "addr:street":"Main St",
    "iso:country":"US",
    "sg:address":"137 Main St",
    "sg:city":"Cold Spring",
    "sg:classifiers":[
        {
            "category":"Restaurant",
            "type":"Food & Drink"
        }
    ],
    "sg:phone":"+1 845 265 4375",
    "sg:postcode":"10516",
    "sg:province":"NY",
    "sg:tags":[
        "eating",
        "caterer"
    ],
    "wof:name":"Marika's Catering",
    "wof:placetype":"venue"
},
  "geometry": {"coordinates":[-73.95652,41.418799],"type":"Point"}
}