{
  "type": "Feature",
  "properties": {
    "addr:full":"2342 E 17th St Brooklyn NY 11229",
    "addr:housenumber":"2342",
    "addr:postcode":"11229",
    "addr:street":"E 17Th St",
    "iso:country":"US",
    "sg:address":"2342 E 17th St",
    "sg:city":"Brooklyn",
    "sg:classifiers":[
        {
            "category":"Professional",
            "subcategory":"Advertising",
            "type":"Services"
        }
    ],
    "sg:phone":"+1 718 368 9665",
    "sg:postcode":"11229",
    "sg:province":"NY",
    "sg:tags":[
        "sales",
        "marketing",
        "publishing",
        "internet"
    ],
    "wof:name":"Gb Media Inc",
    "wof:placetype":"venue"
},
  "geometry": {"coordinates":[-73.953464,40.59331],"type":"Point"}
}