{
  "type": "Feature",
  "properties": {
    "addr:full":"150 Broadway Brooklyn NY 11211",
    "addr:housenumber":"150",
    "addr:postcode":"11211",
    "addr:street":"Broadway",
    "iso:country":"US",
    "sg:address":"150 Broadway",
    "sg:city":"Brooklyn",
    "sg:classifiers":[
        {
            "category":"Health Services",
            "subcategory":"Doctor",
            "type":"Services"
        }
    ],
    "sg:phone":"+1 212 233 2344",
    "sg:postcode":"11211",
    "sg:province":"NY",
    "sg:tags":[
        "medical"
    ],
    "wof:name":"A Joseph Rudick",
    "wof:placetype":"venue"
},
  "geometry": {"coordinates":[-73.963875,40.710297],"type":"Point"}
}