{
  "type": "Feature",
  "properties": {
    "addr:full":"536 Broadway Massapequa NY 11758",
    "addr:housenumber":"536",
    "addr:postcode":"11758",
    "addr:street":"Broadway",
    "iso:country":"US",
    "sg:address":"536 Broadway",
    "sg:city":"Massapequa",
    "sg:classifiers":[
        {
            "category":"Shopping",
            "subcategory":"Florist",
            "type":"Retail Goods"
        }
    ],
    "sg:phone":"+1   ",
    "sg:postcode":"11758",
    "sg:province":"NY",
    "sg:website":"www.pequaparkflorist.com",
    "wof:name":"Pequa Park Florist Inc",
    "wof:placetype":"venue"
},
  "geometry": {"coordinates":[-73.469446,40.680152],"type":"Point"}
}