{
  "type": "Feature",
  "properties": {
    "addr:full":"1515 Selwyn Ave Bronx NY 10457",
    "addr:housenumber":"1515",
    "addr:postcode":"10457",
    "addr:street":"Selwyn Ave",
    "iso:country":"US",
    "sg:address":"1515 Selwyn Ave",
    "sg:city":"Bronx",
    "sg:classifiers":[
        {
            "category":"Organizations",
            "subcategory":"Religious Organization",
            "type":"Services"
        }
    ],
    "sg:phone":"+1 718 893 4981",
    "sg:postcode":"10457",
    "sg:province":"NY",
    "sg:tags":[
        "church"
    ],
    "wof:name":"Iglesia Apost De Jesurristo",
    "wof:placetype":"venue"
},
  "geometry": {"coordinates":[-73.910444,40.842948],"type":"Point"}
}