{
  "type": "Feature",
  "properties": {
    "addr:full":"7428 Fifth Avenue Brooklyn NY 11209",
    "addr:housenumber":"7428",
    "addr:postcode":"11209",
    "addr:street":"Fifth Avenue",
    "iso:country":"US",
    "sg:address":"7428 Fifth Avenue",
    "sg:city":"Brooklyn",
    "sg:classifiers":[
        {
            "category":"Real Estate",
            "subcategory":"Real Estate Agent",
            "type":"Services"
        }
    ],
    "sg:phone":"+1 718 921 3100",
    "sg:postcode":"11209",
    "sg:province":"NY",
    "sg:website":"www.cbreliable.com/",
    "wof:name":"Coldwell Banker Reliable",
    "wof:placetype":"venue"
},
  "geometry": {"coordinates":[-74.02284400000001,40.629804],"type":"Point"}
}