{
  "type": "Feature",
  "properties": {
    "addr:full":"27 Hooper St Brooklyn NY 11211",
    "addr:housenumber":"27",
    "addr:postcode":"11211",
    "addr:street":"Hooper St",
    "iso:country":"US",
    "sg:address":"27 Hooper St",
    "sg:city":"Brooklyn",
    "sg:classifiers":[
        {
            "category":"Government",
            "subcategory":"Office",
            "type":"Public Place"
        }
    ],
    "sg:phone":"+1 718 254 8916",
    "sg:postcode":"11211",
    "sg:province":"NY",
    "sg:tags":[
        "village"
    ],
    "wof:name":"New York City Housing Dev Dept",
    "wof:placetype":"venue"
},
  "geometry": {"coordinates":[-73.962419,40.701461],"type":"Point"}
}