{
  "type": "Feature",
  "properties": {
    "iso:country":"US",
    "sg:address":"6541 Elmer Hill Rd",
    "sg:city":"Rome",
    "sg:classifiers":[
        {
            "category":"Building & Trades",
            "subcategory":"Construction",
            "type":"Services"
        }
    ],
    "sg:phone":"+1 315 336 6075",
    "sg:postcode":"13440",
    "sg:province":"NY",
    "sg:tags":[
        "house"
    ],
    "wof:name":"SJS Construction",
    "wof:placetype":"venue"
},
  "geometry": {"coordinates":[-75.45574499999999,43.282396],"type":"Point"}
}