{
  "type": "Feature",
  "properties": {
    "addr:full":"1266 Rogers Ave Brooklyn NY 11226",
    "addr:housenumber":"1266",
    "addr:postcode":"11226",
    "addr:street":"Rogers Ave",
    "iso:country":"US",
    "sg:address":"1266 Rogers Ave",
    "sg:city":"Brooklyn",
    "sg:classifiers":[
        {
            "category":"Building & Trades",
            "subcategory":"Plumbing",
            "type":"Services"
        }
    ],
    "sg:phone":"+1 347 271 3245",
    "sg:postcode":"11226",
    "sg:province":"NY",
    "wof:name":"Cat's A C & Heating",
    "wof:placetype":"venue"
},
  "geometry": {"coordinates":[-73.95134,40.638849],"type":"Point"}
}