{
  "type": "Feature",
  "properties": {
    "iso:country":"US",
    "sg:address":"5677 Groveland Hill Rd",
    "sg:city":"Geneseo",
    "sg:classifiers":[
        {
            "category":"Personal",
            "type":"Services"
        },
        {
            "category":"Professional",
            "subcategory":"Art Services",
            "type":"Services"
        }
    ],
    "sg:phone":"+1 585 738 8346",
    "sg:postcode":"14454",
    "sg:province":"NY",
    "sg:tags":[
        "photography",
        "videography",
        "wedding"
    ],
    "wof:name":"Jessica Lynn Photography",
    "wof:placetype":"venue"
},
  "geometry": {"coordinates":[-77.758357,42.738014],"type":"Point"}
}