{
  "type": "Feature",
  "properties": {
    "addr:full":"165 Park Row New York NY 10038",
    "addr:housenumber":"165",
    "addr:postcode":"10038",
    "addr:street":"Park Row",
    "iso:country":"US",
    "sg:address":"165 Park Row",
    "sg:city":"New York",
    "sg:classifiers":[
        {
            "category":"Retail",
            "subcategory":"Repair Shop",
            "type":"Services"
        }
    ],
    "sg:phone":"+1 212 624 1529",
    "sg:postcode":"10038",
    "sg:province":"NY",
    "sg:tags":[
        "lock",
        "locksmith"
    ],
    "wof:name":"Locksmith Service",
    "wof:placetype":"venue"
},
  "geometry": {"coordinates":[-73.999126,40.713259],"type":"Point"}
}