{
  "type": "Feature",
  "properties": {
    "iso:country":"US",
    "sg:address":"72 Lexington Ave",
    "sg:city":"Mount Vernon",
    "sg:classifiers":[
        {
            "category":"Education",
            "subcategory":"School",
            "type":"Public Place"
        }
    ],
    "sg:phone":"+1 914 665 5060",
    "sg:postcode":"10552",
    "sg:province":"NY",
    "wof:name":"Traphagen Elementary School",
    "wof:placetype":"venue"
},
  "geometry": {"coordinates":[-73.82122,40.921034],"type":"Point"}
}