{
  "type": "Feature",
  "properties": {
    "iso:country":"US",
    "sg:address":"5270 Caughdenoy Rd",
    "sg:city":"Clay",
    "sg:classifiers":[
        {
            "category":"Transit Center",
            "subcategory":"Freight",
            "type":"Transportation"
        },
        {
            "category":"Freight",
            "type":"Transportation"
        }
    ],
    "sg:phone":"+1 315 699 1707",
    "sg:postcode":"13041",
    "sg:province":"NY",
    "sg:tags":[
        "local",
        "trucking-motor",
        "trucking"
    ],
    "wof:name":"Sikora Trucking",
    "wof:placetype":"venue"
},
  "geometry": {"coordinates":[-76.151105,43.158853],"type":"Point"}
}