{
  "type": "Feature",
  "properties": {
    "iso:country":"US",
    "sg:address":"134 Glenwood Rd",
    "sg:city":"Glenwood Landing",
    "sg:classifiers":[
        {
            "category":"Shopping",
            "subcategory":"Used Merchandise",
            "type":"Retail Goods"
        }
    ],
    "sg:phone":"+1   ",
    "sg:postcode":"11547",
    "sg:province":"NY",
    "wof:name":"Glenwood Tag Sale Service",
    "wof:placetype":"venue"
},
  "geometry": {"coordinates":[-73.647723,40.828903],"type":"Point"}
}