{
  "type": "Feature",
  "properties": {
    "iso:country":"US",
    "sg:address":"758 5th Ave",
    "sg:city":"Brooklyn",
    "sg:classifiers":[
        {
            "category":"Bars & Pubs",
            "type":"Food & Drink"
        }
    ],
    "sg:phone":"+1 718 832 4562",
    "sg:postcode":"11232",
    "sg:province":"NY",
    "sg:tags":[
        "lounge",
        "nightlife",
        "cocktail"
    ],
    "wof:name":"D'cache",
    "wof:placetype":"venue"
},
  "geometry": {"coordinates":[-73.996498,40.6586],"type":"Point"}
}