{
  "type": "Feature",
  "properties": {
    "iso:country":"US",
    "sg:address":"1251 Flying Point Rd",
    "sg:city":"Water Mill",
    "sg:classifiers":[
        {
            "category":"Organizations",
            "subcategory":"Community Association",
            "type":"Services"
        }
    ],
    "sg:phone":"+1 631 726 6071",
    "sg:postcode":"11976",
    "sg:province":"NY",
    "sg:tags":[
        "club"
    ],
    "wof:name":"Water Mill Beach Club Inc",
    "wof:placetype":"venue"
},
  "geometry": {"coordinates":[-72.338736,40.889167],"type":"Point"}
}