{
  "type": "Feature",
  "properties": {
    "addr:full":"367 Grosvenor St Little Neck NY 11363",
    "addr:housenumber":"367",
    "addr:postcode":"11363",
    "addr:street":"Grosvenor St",
    "iso:country":"US",
    "sg:address":"367 Grosvenor St",
    "sg:city":"Little Neck",
    "sg:classifiers":[
        {
            "category":"Manufacturing",
            "subcategory":"Jewelry",
            "type":"Manufacturing & Wholesale Goods"
        }
    ],
    "sg:phone":"+1   ",
    "sg:postcode":"11363",
    "sg:province":"NY",
    "sg:tags":[
        "precious",
        "metal",
        "mfg"
    ],
    "wof:name":"Afformations LLC",
    "wof:placetype":"venue"
},
  "geometry": {"coordinates":[-73.74728899999999,40.778479],"type":"Point"}
}