{
  "type": "Feature",
  "properties": {
    "addr:full":"421 W 14th St New York NY 10014",
    "addr:housenumber":"421",
    "addr:postcode":"10014",
    "addr:street":"W 14Th St",
    "iso:country":"US",
    "sg:address":"421 W 14th St",
    "sg:city":"New York",
    "sg:classifiers":[
        {
            "category":"Shopping",
            "subcategory":"Shoes",
            "type":"Retail Goods"
        }
    ],
    "sg:phone":"+1 212 206 0109",
    "sg:postcode":"10014",
    "sg:province":"NY",
    "sg:tags":[
        "store"
    ],
    "wof:name":"Puma Black",
    "wof:placetype":"venue"
},
  "geometry": {"coordinates":[-74.006446,40.7414],"type":"Point"}
}