{
  "type": "Feature",
  "properties": {
    "iso:country":"US",
    "sg:address":"46 Webster St",
    "sg:city":"North Tonawanda",
    "sg:classifiers":[
        {
            "category":"Building & Trades",
            "subcategory":"Plumbing",
            "type":"Services"
        }
    ],
    "sg:phone":"+1 716 692 3181",
    "sg:postcode":"14120",
    "sg:province":"NY",
    "sg:tags":[
        "heating",
        "contractor"
    ],
    "wof:name":"Tully Houseworks",
    "wof:placetype":"venue"
},
  "geometry": {"coordinates":[-78.877252,43.024404],"type":"Point"}
}