{
  "type": "Feature",
  "properties": {
    "iso:country":"US",
    "sg:address":"67 1st St",
    "sg:city":"Ilion",
    "sg:classifiers":[
        {
            "category":"Communications",
            "subcategory":"Film & Video Production",
            "type":"Services"
        }
    ],
    "sg:phone":"+1 315 895 7295",
    "sg:postcode":"13357",
    "sg:province":"NY",
    "sg:tags":[
        "taping"
    ],
    "wof:name":"Walsh's Video Replay",
    "wof:placetype":"venue"
},
  "geometry": {"coordinates":[-75.03877199999999,43.014848],"type":"Point"}
}