{
  "type": "Feature",
  "properties": {
    "addr:full":"2444 Military Rd Niagara Falls NY 14304",
    "addr:housenumber":"2444",
    "addr:postcode":"14304",
    "addr:street":"Military Rd",
    "iso:country":"US",
    "sg:address":"2444 Military Rd",
    "sg:city":"Niagara Falls",
    "sg:classifiers":[
        {
            "category":"Food & Beverages",
            "subcategory":"Bakery",
            "type":"Retail Goods"
        }
    ],
    "sg:phone":"+1 716 297 0331",
    "sg:postcode":"14304",
    "sg:province":"NY",
    "sg:tags":[
        "baker"
    ],
    "wof:name":"Wonder Hostess Thrift Store",
    "wof:placetype":"venue"
},
  "geometry": {"coordinates":[-78.98071,43.102515],"type":"Point"}
}