{
  "type": "Feature",
  "properties": {
    "iso:country":"US",
    "sg:address":"500 Manhattan Ave",
    "sg:city":"Brooklyn",
    "sg:classifiers":[
        {
            "category":"Building & Trades",
            "subcategory":"Construction",
            "type":"Services"
        }
    ],
    "sg:phone":"+1 718 782 6157",
    "sg:postcode":"11222",
    "sg:province":"NY",
    "sg:tags":[
        "nonresidential"
    ],
    "wof:name":"Mayden Realty & Construction",
    "wof:placetype":"venue"
},
  "geometry": {"coordinates":[-73.948385,40.720841],"type":"Point"}
}