{
  "type": "Feature",
  "properties": {
    "addr:full":"153 E 87th Street Suite 1B New York NY 10128",
    "addr:housenumber":"153",
    "addr:postcode":"10128",
    "addr:street":"E 87Th Street Suite 1B",
    "iso:country":"US",
    "sg:address":"153 E 87th Street Suite 1B",
    "sg:city":"New York",
    "sg:classifiers":[
        {
            "category":"Health Services",
            "subcategory":"Dentist",
            "type":"Services"
        }
    ],
    "sg:phone":"+1 888 378 2976",
    "sg:postcode":"10128",
    "sg:province":"NY",
    "sg:tags":[
        "orthodontist"
    ],
    "sg:website":"www.ueso.org",
    "wof:name":"Upper Eastside Orthodontists",
    "wof:placetype":"venue"
},
  "geometry": {"coordinates":[-73.954644,40.780226],"type":"Point"}
}