{
  "type": "Feature",
  "properties": {
    "addr:full":"231 W 29th St Rm 606 New York NY 10001",
    "addr:housenumber":"231;606",
    "addr:postcode":"10001",
    "addr:street":"W 29Th St Rm",
    "iso:country":"US",
    "sg:address":"231 W 29th St Rm 606",
    "sg:city":"New York",
    "sg:classifiers":[
        {
            "category":"Building & Trades",
            "subcategory":"Construction",
            "type":"Services"
        }
    ],
    "sg:phone":"+1 212 807 1177",
    "sg:postcode":"10001",
    "sg:province":"NY",
    "sg:tags":[
        "interior",
        "design"
    ],
    "wof:name":"Mitchell Fontana Associates",
    "wof:placetype":"venue"
},
  "geometry": {"coordinates":[-73.99371600000001,40.748347],"type":"Point"}
}