{
  "type": "Feature",
  "properties": {
    "addr:full":"985 Payne Ave North Tonawanda NY 14120",
    "addr:housenumber":"985",
    "addr:postcode":"14120",
    "addr:street":"Payne Ave",
    "iso:country":"US",
    "sg:address":"985 Payne Ave",
    "sg:city":"North Tonawanda",
    "sg:classifiers":[
        {
            "category":"Personal",
            "subcategory":"Beauty Salon",
            "type":"Services"
        }
    ],
    "sg:phone":"+1 716 695 3319",
    "sg:postcode":"14120",
    "sg:province":"NY",
    "sg:tags":[
        "shop"
    ],
    "wof:name":"Supercuts",
    "wof:placetype":"venue"
},
  "geometry": {"coordinates":[-78.87728300000001,43.049446],"type":"Point"}
}