{
  "type": "Feature",
  "properties": {
    "addr:full":"561 Acorn St Deer Park NY 11729",
    "addr:housenumber":"561",
    "addr:postcode":"11729",
    "addr:street":"Acorn St",
    "iso:country":"US",
    "sg:address":"561 Acorn St",
    "sg:city":"Deer Park",
    "sg:classifiers":[
        {
            "category":"Wholesale",
            "subcategory":"Drugs",
            "type":"Manufacturing & Wholesale Goods"
        },
        {
            "category":"Wholesale",
            "subcategory":"Groceries",
            "type":"Manufacturing & Wholesale Goods"
        }
    ],
    "sg:phone":"+1 631 243 2922",
    "sg:postcode":"11729",
    "sg:province":"NY",
    "sg:tags":[
        "food",
        "tea",
        "health",
        "vitamin"
    ],
    "wof:name":"Body Breakthrough Inc",
    "wof:placetype":"venue"
},
  "geometry": {"coordinates":[-73.34024100000001,40.759072],"type":"Point"}
}