{
  "type": "Feature",
  "properties": {
    "addr:full":"44 Lauren Ct Kingston NY 12401",
    "addr:housenumber":"44",
    "addr:postcode":"12401",
    "addr:street":"Lauren Ct",
    "iso:country":"US",
    "sg:address":"44 Lauren Ct",
    "sg:city":"Kingston",
    "sg:classifiers":[
        {
            "category":"Structure",
            "subcategory":"Office Building",
            "type":"Public Place"
        }
    ],
    "sg:phone":"+1 845 246 1811",
    "sg:postcode":"12401",
    "sg:province":"NY",
    "sg:tags":[
        "park"
    ],
    "wof:name":"Asc Properties",
    "wof:placetype":"venue"
},
  "geometry": {"coordinates":[-74.050049,42.020877],"type":"Point"}
}