{
  "type": "Feature",
  "properties": {
    "addr:full":"25 Post Ave Ste A Westbury NY 11590",
    "addr:housenumber":"25",
    "addr:postcode":"11590",
    "addr:street":"Post Ave Ste A",
    "iso:country":"US",
    "sg:address":"25 Post Ave Ste A",
    "sg:city":"Westbury",
    "sg:classifiers":[
        {
            "category":"Real Estate",
            "subcategory":"Real Estate Services",
            "type":"Services"
        },
        {
            "category":"Real Estate",
            "subcategory":"Real Estate Agent",
            "type":"Services"
        }
    ],
    "sg:phone":"+1 516 833 7712",
    "sg:postcode":"11590",
    "sg:province":"NY",
    "sg:tags":[
        "buyer",
        "broker"
    ],
    "wof:name":"Quick Sell",
    "wof:placetype":"venue"
},
  "geometry": {"coordinates":[-73.58766900000001,40.748581],"type":"Point"}
}