{
  "type": "Feature",
  "properties": {
    "iso:country":"US",
    "sg:address":"1005A Morris Park Avenue",
    "sg:city":"Bronx",
    "sg:classifiers":[
        {
            "category":"Restaurant",
            "type":"Food & Drink"
        }
    ],
    "sg:phone":"+1 718 863 2850",
    "sg:postcode":"10462",
    "sg:province":"NY",
    "sg:tags":[
        "pizza"
    ],
    "wof:name":"Luciano Pizza",
    "wof:placetype":"venue"
},
  "geometry": {"coordinates":[-73.85595499999999,40.848354],"type":"Point"}
}