{
  "type": "Feature",
  "properties": {
    "iso:country":"US",
    "sg:address":"116 Lake Ave",
    "sg:city":"Yonkers",
    "sg:classifiers":[
        {
            "category":"Personal",
            "subcategory":"Beauty Salon",
            "type":"Services"
        }
    ],
    "sg:phone":"+1 914 476 7374",
    "sg:postcode":"10703",
    "sg:province":"NY",
    "wof:name":"Billie's Salon",
    "wof:placetype":"venue"
},
  "geometry": {"coordinates":[-73.886765,40.946957],"type":"Point"}
}