{
  "type": "Feature",
  "properties": {
    "addr:full":"315 Church St Fl 2 New York NY 10013",
    "addr:housenumber":"315;2",
    "addr:postcode":"10013",
    "addr:street":"Church St",
    "iso:country":"US",
    "sg:address":"315 Church St Fl 2",
    "sg:city":"New York",
    "sg:classifiers":[
        {
            "category":"Health Services",
            "subcategory":"Doctor",
            "type":"Services"
        }
    ],
    "sg:phone":"+1 212 334 3774",
    "sg:postcode":"10013",
    "sg:province":"NY",
    "sg:tags":[
        "dermatologist"
    ],
    "sg:website":"www.tribecaskincenter.com",
    "wof:name":"Tribeca Skin Center",
    "wof:placetype":"venue"
},
  "geometry": {"coordinates":[-74.004014,40.71988],"type":"Point"}
}