{
  "type": "Feature",
  "properties": {
    "addr:full":"201 8th Ave New York NY 10011",
    "addr:housenumber":"201",
    "addr:postcode":"10011",
    "addr:street":"8Th Ave",
    "iso:country":"US",
    "sg:address":"201 8th Ave",
    "sg:city":"New York",
    "sg:classifiers":[
        {
            "category":"Restaurant",
            "type":"Food & Drink"
        }
    ],
    "sg:menulink":"http://www.allmenus.com/ny/new-york/7148-the-dish-restaurant/menu/",
    "sg:phone":"+1 212 352 9800",
    "sg:postcode":"10011",
    "sg:province":"NY",
    "sg:tags":[
        "american"
    ],
    "wof:name":"The Dish Restaurant",
    "wof:placetype":"venue"
},
  "geometry": {"coordinates":[-73.99998100000001,40.743761],"type":"Point"}
}