{
  "type": "Feature",
  "properties": {
    "iso:country":"US",
    "sg:address":"36 Willowbrook Hts",
    "sg:city":"Poughkeepsie",
    "sg:classifiers":[
        {
            "category":"Home & Garden",
            "subcategory":"Building Materials",
            "type":"Retail Goods"
        }
    ],
    "sg:phone":"+1 845 462 1817",
    "sg:postcode":"12603",
    "sg:province":"NY",
    "sg:tags":[
        "downspouts",
        "gutter"
    ],
    "wof:name":"Gutterman Seamless Gutters",
    "wof:placetype":"venue"
},
  "geometry": {"coordinates":[-73.89020600000001,41.632932],"type":"Point"}
}