{
  "type": "Feature",
  "properties": {
    "addr:full":"4256 21st St Long Island City NY 11101",
    "addr:housenumber":"4256",
    "addr:postcode":"11101",
    "addr:street":"21St St",
    "iso:country":"US",
    "sg:address":"4256 21st St",
    "sg:city":"Long Island City",
    "sg:classifiers":[
        {
            "category":"Retail",
            "subcategory":"Auto Repair",
            "type":"Services"
        }
    ],
    "sg:phone":"+1 718 786 8788",
    "sg:postcode":"11101",
    "sg:province":"NY",
    "wof:name":"A & M Auto Repair & Bodywork",
    "wof:placetype":"venue"
},
  "geometry": {"coordinates":[-73.945702,40.750801],"type":"Point"}
}