{
  "type": "Feature",
  "properties": {
    "iso:country":"US",
    "sg:address":"171 Sound Ave",
    "sg:city":"Riverhead",
    "sg:classifiers":[
        {
            "category":"Professional",
            "type":"Services"
        }
    ],
    "sg:phone":"+1 631 298 2649",
    "sg:postcode":"11931",
    "sg:province":"NY",
    "sg:tags":[
        "establishment"
    ],
    "wof:name":"Martha Clara Viticulture Ofc",
    "wof:placetype":"venue"
},
  "geometry": {"coordinates":[-72.618904,40.969995],"type":"Point"}
}