{
  "type": "Feature",
  "properties": {
    "addr:full":"70 Laurel Pl New Rochelle NY 10801",
    "addr:housenumber":"70",
    "addr:postcode":"10801",
    "addr:street":"Laurel Pl",
    "iso:country":"US",
    "sg:address":"70 Laurel Pl",
    "sg:city":"New Rochelle",
    "sg:classifiers":[
        {
            "category":"Manufacturing",
            "subcategory":"Printing",
            "type":"Manufacturing & Wholesale Goods"
        }
    ],
    "sg:phone":"+1   ",
    "sg:postcode":"10801",
    "sg:province":"NY",
    "sg:tags":[
        "publisher",
        "music",
        "pamphlet"
    ],
    "sg:website":"www.notc.com",
    "wof:name":"New On The Charts",
    "wof:placetype":"venue"
},
  "geometry": {"coordinates":[-73.786276,40.903209],"type":"Point"}
}