{
  "type": "Feature",
  "properties": {
    "addr:full":"1100 E Jericho Tpke Huntington NY 11743",
    "addr:housenumber":"1100",
    "addr:postcode":"11743",
    "addr:street":"E Jericho Tpke",
    "iso:country":"US",
    "sg:address":"1100 E Jericho Tpke",
    "sg:city":"Huntington",
    "sg:classifiers":[
        {
            "category":"Banks & Credit Unions",
            "subcategory":"Bank",
            "type":"Services"
        }
    ],
    "sg:phone":"+1 631 425 9520",
    "sg:postcode":"11743",
    "sg:province":"NY",
    "sg:website":"www.citizensbank.com",
    "wof:name":"Citizens Bank",
    "wof:placetype":"venue"
},
  "geometry": {"coordinates":[-73.368825,40.834904],"type":"Point"}
}