{
  "type": "Feature",
  "properties": {
    "iso:country":"US",
    "sg:address":"666 Emerson St",
    "sg:city":"Woodmere",
    "sg:classifiers":[
        {
            "category":"Health Services",
            "subcategory":"Health Practitioner",
            "type":"Services"
        }
    ],
    "sg:phone":"+1 516 374 6118",
    "sg:postcode":"11598",
    "sg:province":"NY",
    "sg:tags":[
        "psychologist"
    ],
    "wof:name":"Shiela H Adler",
    "wof:placetype":"venue"
},
  "geometry": {"coordinates":[-73.72360399999999,40.632063],"type":"Point"}
}