{
  "type": "Feature",
  "properties": {
    "addr:full":"725 Madison Ave New York NY 10065",
    "addr:housenumber":"725",
    "addr:postcode":"10065",
    "addr:street":"Madison Ave",
    "iso:country":"US",
    "sg:address":"725 Madison Ave",
    "sg:city":"New York",
    "sg:classifiers":[
        {
            "category":"Shopping",
            "subcategory":"Jewelry",
            "type":"Retail Goods"
        }
    ],
    "sg:phone":"+1 212 725 7777",
    "sg:postcode":"10065",
    "sg:province":"NY",
    "sg:website":"www.kwiat.com",
    "wof:name":"Kwiat Jewelry",
    "wof:placetype":"venue"
},
  "geometry": {"coordinates":[-73.969191,40.766596],"type":"Point"}
}