{
  "type": "Feature",
  "properties": {
    "addr:full":"200 Military Rd Buffalo NY 14207",
    "addr:housenumber":"200",
    "addr:postcode":"14207",
    "addr:street":"Military Rd",
    "iso:country":"US",
    "sg:address":"200 Military Rd",
    "sg:city":"Buffalo",
    "sg:classifiers":[
        {
            "category":"Railroad",
            "type":"Transportation"
        }
    ],
    "sg:phone":"+1 716 874 5035",
    "sg:postcode":"14207",
    "sg:province":"NY",
    "wof:name":"Con Rail",
    "wof:placetype":"venue"
},
  "geometry": {"coordinates":[-78.89196099999999,42.94166],"type":"Point"}
}