{
  "type": "Feature",
  "properties": {
    "addr:full":"173 Lafayette St New York NY 10013",
    "addr:housenumber":"173",
    "addr:postcode":"10013",
    "addr:street":"Lafayette St",
    "iso:country":"US",
    "sg:address":"173 Lafayette St",
    "sg:city":"New York",
    "sg:classifiers":[
        {
            "category":"Professional",
            "subcategory":"Business Services",
            "type":"Services"
        }
    ],
    "sg:phone":"+1 212 343 8405",
    "sg:postcode":"10013",
    "sg:province":"NY",
    "sg:tags":[
        "fund",
        "promotion",
        "raising"
    ],
    "wof:name":"Culinaria Royale Promotions",
    "wof:placetype":"venue"
},
  "geometry": {"coordinates":[-73.99832000000001,40.720731],"type":"Point"}
}