{
  "type": "Feature",
  "properties": {
    "iso:country":"US",
    "sg:address":"16 Palmer Ave",
    "sg:city":"Bronxville",
    "sg:classifiers":[
        {
            "category":"Retail",
            "subcategory":"Laundry & Dry Cleaning",
            "type":"Services"
        }
    ],
    "sg:phone":"+1 914 337 1652",
    "sg:postcode":"10708",
    "sg:province":"NY",
    "wof:name":"Sam Kee Laundry",
    "wof:placetype":"venue"
},
  "geometry": {"coordinates":[-73.837143,40.941382],"type":"Point"}
}