{
  "type": "Feature",
  "properties": {
    "iso:country":"US",
    "sg:address":"316 E 63rd St",
    "sg:city":"New York",
    "sg:classifiers":[
        {
            "category":"Real Estate",
            "subcategory":"Real Estate Services",
            "type":"Services"
        }
    ],
    "sg:phone":"+1 212 906 2800",
    "sg:postcode":"10021",
    "sg:province":"NY",
    "sg:tags":[
        "management",
        "property"
    ],
    "sg:website":"bandlmanagement.com",
    "wof:name":"B & L",
    "wof:placetype":"venue"
},
  "geometry": {"coordinates":[-73.961901,40.762603],"type":"Point"}
}