{
  "type": "Feature",
  "properties": {
    "addr:full":"30702 State Hwy 12 La Fargeville NY 13656",
    "addr:housenumber":"30702",
    "addr:postcode":"13656",
    "addr:street":"State Hwy 12 La Fargeville",
    "iso:country":"US",
    "sg:address":"30702 State Hwy 12",
    "sg:city":"La Fargeville",
    "sg:classifiers":[
        {
            "category":"Farming",
            "subcategory":"Dairy Farm",
            "type":"Manufacturing & Wholesale Goods"
        }
    ],
    "sg:phone":"+1 315 658 4730",
    "sg:postcode":"13656",
    "sg:province":"NY",
    "wof:name":"Art Campbell",
    "wof:placetype":"venue"
},
  "geometry": {"coordinates":[-76.027592,44.112774],"type":"Point"}
}