{
  "type": "Feature",
  "properties": {
    "addr:full":"406 Connecticut St Buffalo NY 14213",
    "addr:housenumber":"406",
    "addr:postcode":"14213",
    "addr:street":"Connecticut St",
    "iso:country":"US",
    "sg:address":"406 Connecticut St",
    "sg:city":"Buffalo",
    "sg:classifiers":[
        {
            "category":"Building & Trades",
            "subcategory":"Construction",
            "type":"Services"
        }
    ],
    "sg:phone":"+1 716 881 9578",
    "sg:postcode":"14213",
    "sg:province":"NY",
    "sg:tags":[
        "general",
        "contractor"
    ],
    "wof:name":"General Contracting Svc",
    "wof:placetype":"venue"
},
  "geometry": {"coordinates":[-78.886144,42.906654],"type":"Point"}
}