{
  "type": "Feature",
  "properties": {
    "addr:full":"410 Saw Mill River Rd Yonkers NY 10701",
    "addr:housenumber":"410",
    "addr:postcode":"10701",
    "addr:street":"Saw Mill River Rd",
    "iso:country":"US",
    "sg:address":"410 Saw Mill River Rd",
    "sg:city":"Yonkers",
    "sg:classifiers":[
        {
            "category":"Retail",
            "subcategory":"Auto Repair",
            "type":"Services"
        }
    ],
    "sg:phone":"+1 914 969 4143",
    "sg:postcode":"10701",
    "sg:province":"NY",
    "sg:tags":[
        "repairing",
        "automobile"
    ],
    "wof:name":"Ben Mar Auto Repair",
    "wof:placetype":"venue"
},
  "geometry": {"coordinates":[-73.87626899999999,40.950545],"type":"Point"}
}