{
  "type": "Feature",
  "properties": {
    "addr:full":"1092 Nostrand Ave Brooklyn NY 11225",
    "addr:housenumber":"1092",
    "addr:postcode":"11225",
    "addr:street":"Nostrand Ave",
    "iso:country":"US",
    "sg:address":"1092 Nostrand Ave",
    "sg:city":"Brooklyn",
    "sg:classifiers":[
        {
            "category":"Shopping",
            "subcategory":"Music",
            "type":"Retail Goods"
        }
    ],
    "sg:phone":"+1 718 469 1325",
    "sg:postcode":"11225",
    "sg:province":"NY",
    "sg:tags":[
        "dvd's"
    ],
    "wof:name":"Tigers Reggae Hut",
    "wof:placetype":"venue"
},
  "geometry": {"coordinates":[-73.95079800000001,40.661098],"type":"Point"}
}