{
  "type": "Feature",
  "properties": {
    "iso:country":"US",
    "sg:address":"15 Heritage Dr",
    "sg:city":"New City",
    "sg:classifiers":[
        {
            "category":"Local Transit",
            "type":"Transportation"
        }
    ],
    "sg:phone":"+1 845 639 7624",
    "sg:postcode":"10956",
    "sg:province":"NY",
    "sg:tags":[
        "car"
    ],
    "wof:name":"Tri State Car Svc",
    "wof:placetype":"venue"
},
  "geometry": {"coordinates":[-73.98688300000001,41.15982],"type":"Point"}
}