{
  "type": "Feature",
  "properties": {
    "addr:full":"2668 E 22nd St Brooklyn NY 11235",
    "addr:housenumber":"2668",
    "addr:postcode":"11235",
    "addr:street":"E 22Nd St",
    "iso:country":"US",
    "sg:address":"2668 E 22nd St",
    "sg:city":"Brooklyn",
    "sg:classifiers":[
        {
            "category":"Professional",
            "subcategory":"Accounting & Tax Preparation",
            "type":"Services"
        }
    ],
    "sg:phone":"+1   ",
    "sg:postcode":"11235",
    "sg:province":"NY",
    "wof:name":"Medical Blling Cllections Svcs",
    "wof:placetype":"venue"
},
  "geometry": {"coordinates":[-73.947227,40.587804],"type":"Point"}
}