{
  "type": "Feature",
  "properties": {
    "addr:full":"1266 Madison Avenue Manhattan NY 10128",
    "addr:housenumber":"1266",
    "addr:postcode":"10128",
    "addr:street":"Madison Avenue",
    "iso:country":"US",
    "sg:address":"1266 Madison Avenue",
    "sg:city":"Manhattan",
    "sg:classifiers":[
        {
            "category":"Food & Beverages",
            "subcategory":"Candy",
            "type":"Retail Goods"
        }
    ],
    "sg:phone":"+1 888 435 3647",
    "sg:postcode":"10128",
    "sg:province":"NY",
    "sg:tags":[
        "dessert"
    ],
    "sg:website":"elenis.com/",
    "wof:name":"Eleni's of New York",
    "wof:placetype":"venue"
},
  "geometry": {"coordinates":[-73.956726,40.783781],"type":"Point"}
}