{
  "type": "Feature",
  "properties": {
    "iso:country":"US",
    "sg:address":"315 Sumpter St",
    "sg:city":"Brooklyn",
    "sg:classifiers":[
        {
            "category":"Freight",
            "type":"Transportation"
        }
    ],
    "sg:phone":"+1 718 573 6020",
    "sg:postcode":"11233",
    "sg:province":"NY",
    "sg:tags":[
        "mover"
    ],
    "wof:name":"Robinson Express",
    "wof:placetype":"venue"
},
  "geometry": {"coordinates":[-73.91270400000001,40.680855],"type":"Point"}
}