{
  "type": "Feature",
  "properties": {
    "addr:full":"2819 Wickham Ave Bronx NY 10469",
    "addr:housenumber":"2819",
    "addr:postcode":"10469",
    "addr:street":"Wickham Ave",
    "iso:country":"US",
    "sg:address":"2819 Wickham Ave",
    "sg:city":"Bronx",
    "sg:classifiers":[
        {
            "category":"Personal",
            "subcategory":"Beauty Salon",
            "type":"Services"
        }
    ],
    "sg:phone":"+1   ",
    "sg:postcode":"10469",
    "sg:province":"NY",
    "sg:tags":[
        "hair"
    ],
    "wof:name":"Shakara Hair Salon",
    "wof:placetype":"venue"
},
  "geometry": {"coordinates":[-73.837335,40.868718],"type":"Point"}
}