{
  "type": "Feature",
  "properties": {
    "addr:full":"903 Park Avenue New York NY 10075",
    "addr:housenumber":"903",
    "addr:postcode":"10075",
    "addr:street":"Park Avenue",
    "iso:country":"US",
    "sg:address":"903 Park Avenue",
    "sg:city":"New York",
    "sg:classifiers":[
        {
            "category":"Health Services",
            "subcategory":"Doctor",
            "type":"Services"
        }
    ],
    "sg:phone":"+1 212 717 4066",
    "sg:postcode":"10075",
    "sg:province":"NY",
    "sg:tags":[
        "surgeon",
        "cosmetic"
    ],
    "wof:name":"Yoel Shahar MD",
    "wof:placetype":"venue"
},
  "geometry": {"coordinates":[-73.960264,40.775765],"type":"Point"}
}