{
  "type": "Feature",
  "properties": {
    "iso:country":"US",
    "sg:address":"16310A Crossbay Blvd",
    "sg:city":"Howard Beach",
    "sg:classifiers":[
        {
            "category":"Restaurant",
            "type":"Food & Drink"
        }
    ],
    "sg:phone":"+1 800 660 3325",
    "sg:postcode":"11414",
    "sg:province":"NY",
    "sg:tags":[
        "pizza"
    ],
    "wof:name":"Luigi's Pizzeria",
    "wof:placetype":"venue"
},
  "geometry": {"coordinates":[-73.83842300000001,40.652239],"type":"Point"}
}