{
  "type": "Feature",
  "properties": {
    "addr:full":"160 Oakley Ave Elmont NY 11003",
    "addr:housenumber":"160",
    "addr:postcode":"11003",
    "addr:street":"Oakley Ave",
    "iso:country":"US",
    "sg:address":"160 Oakley Ave",
    "sg:city":"Elmont",
    "sg:classifiers":[
        {
            "category":"Building & Trades",
            "subcategory":"Electrical",
            "type":"Services"
        }
    ],
    "sg:phone":"+1 516 437 1609",
    "sg:postcode":"11003",
    "sg:province":"NY",
    "sg:tags":[
        "installation",
        "consulting",
        "electronic"
    ],
    "wof:name":"Robert Berke Electronics",
    "wof:placetype":"venue"
},
  "geometry": {"coordinates":[-73.69134699999999,40.704134],"type":"Point"}
}