{
  "type": "Feature",
  "properties": {
    "addr:full":"120 4 Ave New York NY 10003",
    "addr:housenumber":"120",
    "addr:postcode":"10003",
    "addr:street":"4 Ave",
    "iso:country":"US",
    "sg:address":"120 4 Ave",
    "sg:city":"New York",
    "sg:classifiers":[
        {
            "category":"Retail",
            "subcategory":"Repair Shop",
            "type":"Services"
        }
    ],
    "sg:phone":"+1 917 477 6022",
    "sg:postcode":"10003",
    "sg:province":"NY",
    "sg:tags":[
        "lock",
        "locksmith"
    ],
    "wof:name":"1 Hour Emergency Locksmith",
    "wof:placetype":"venue"
},
  "geometry": {"coordinates":[-73.990583,40.730562],"type":"Point"}
}