{
  "type": "Feature",
  "properties": {
    "iso:country":"US",
    "sg:address":"102 Sharron Ave",
    "sg:city":"Plattsburgh",
    "sg:classifiers":[
        {
            "category":"Restaurant",
            "type":"Food & Drink"
        }
    ],
    "sg:phone":"+1   ",
    "sg:postcode":"12901",
    "sg:province":"NY",
    "sg:tags":[
        "eating"
    ],
    "wof:name":"Pizza Barn Too",
    "wof:placetype":"venue"
},
  "geometry": {"coordinates":[-73.455454,44.676571],"type":"Point"}
}