{
  "type": "Feature",
  "properties": {
    "iso:country":"US",
    "sg:address":"10 Ferry Blvd",
    "sg:city":"S Glens Falls",
    "sg:classifiers":[
        {
            "category":"Building & Trades",
            "subcategory":"Pest Control",
            "type":"Services"
        }
    ],
    "sg:phone":"+1 518 793 6236",
    "sg:postcode":"12803",
    "sg:province":"NY",
    "sg:tags":[
        "spraying"
    ],
    "wof:name":"Craig's Pest Control",
    "wof:placetype":"venue"
},
  "geometry": {"coordinates":[-73.63248299999999,43.300107],"type":"Point"}
}