{
  "type": "Feature",
  "properties": {
    "addr:full":"3649 Erie Blvd E Syracuse NY 13214",
    "addr:housenumber":"3649",
    "addr:postcode":"13214",
    "addr:street":"Erie Blvd E",
    "iso:country":"US",
    "sg:address":"3649 Erie Blvd E",
    "sg:city":"Syracuse",
    "sg:classifiers":[
        {
            "category":"Shopping",
            "subcategory":"Hobbies, Toys, & Games",
            "type":"Retail Goods"
        }
    ],
    "sg:phone":"+1 315 446 1992",
    "sg:postcode":"13214",
    "sg:province":"NY",
    "wof:name":"KB Toys",
    "wof:placetype":"venue"
},
  "geometry": {"coordinates":[-76.06642600000001,43.039809],"type":"Point"}
}