{
  "type": "Feature",
  "properties": {
    "addr:full":"3225 Sound Ave Riverhead NY 11901",
    "addr:housenumber":"3225",
    "addr:postcode":"11901",
    "addr:street":"Sound Ave",
    "iso:country":"US",
    "sg:address":"3225 Sound Ave",
    "sg:city":"Riverhead",
    "sg:classifiers":[
        {
            "category":"Shopping",
            "subcategory":"Clothing, Apparel, & Fashions",
            "type":"Retail Goods"
        }
    ],
    "sg:phone":"+1   ",
    "sg:postcode":"11901",
    "sg:province":"NY",
    "wof:name":"Rose Cottage",
    "wof:placetype":"venue"
},
  "geometry": {"coordinates":[-72.70814,40.965434],"type":"Point"}
}