{
  "type": "Feature",
  "properties": {
    "addr:full":"485 E 21st St Brooklyn NY 11226",
    "addr:housenumber":"485",
    "addr:postcode":"11226",
    "addr:street":"E 21St St",
    "iso:country":"US",
    "sg:address":"485 E 21st St",
    "sg:city":"Brooklyn",
    "sg:classifiers":[
        {
            "category":"Professional",
            "type":"Services"
        }
    ],
    "sg:phone":"+1 718 693 4243",
    "sg:postcode":"11226",
    "sg:province":"NY",
    "sg:tags":[
        "establishment"
    ],
    "wof:name":"Corraspe Cherr",
    "wof:placetype":"venue"
},
  "geometry": {"coordinates":[-73.958753,40.643772],"type":"Point"}
}