{
  "type": "Feature",
  "properties": {
    "iso:country":"US",
    "sg:address":"132 S Pearl St",
    "sg:city":"Pearl River",
    "sg:classifiers":[
        {
            "category":"Building & Trades",
            "subcategory":"Construction",
            "type":"Services"
        }
    ],
    "sg:phone":"+1 845 494 9776",
    "sg:postcode":"10965",
    "sg:province":"NY",
    "sg:tags":[
        "concrete",
        "contractor"
    ],
    "wof:name":"Conskyian",
    "wof:placetype":"venue"
},
  "geometry": {"coordinates":[-74.024452,41.054347],"type":"Point"}
}