{
  "type": "Feature",
  "properties": {
    "addr:full":"667 Kent Ave Brooklyn NY 11211",
    "addr:housenumber":"667",
    "addr:postcode":"11211",
    "addr:street":"Kent Ave",
    "iso:country":"US",
    "sg:address":"667 Kent Ave",
    "sg:city":"Brooklyn",
    "sg:classifiers":[
        {
            "category":"Manufacturing",
            "subcategory":"Printing",
            "type":"Manufacturing & Wholesale Goods"
        }
    ],
    "sg:phone":"+1   ",
    "sg:postcode":"11211",
    "sg:province":"NY",
    "sg:tags":[
        "commercial",
        "lithographic"
    ],
    "wof:name":"NAP Industries",
    "wof:placetype":"venue"
},
  "geometry": {"coordinates":[-73.963869,40.701542],"type":"Point"}
}