{
  "type": "Feature",
  "properties": {
    "iso:country":"US",
    "sg:address":"506 Underwood Ave",
    "sg:city":"Elmira",
    "sg:classifiers":[
        {
            "category":"Airline",
            "type":"Transportation"
        }
    ],
    "sg:phone":"+1 607 734 2208",
    "sg:postcode":"14905",
    "sg:province":"NY",
    "sg:tags":[
        "cargo",
        "air"
    ],
    "wof:name":"Rapid Delivery Svc",
    "wof:placetype":"venue"
},
  "geometry": {"coordinates":[-76.844095,42.088451],"type":"Point"}
}