{
  "type": "Feature",
  "properties": {
    "iso:country":"US",
    "sg:address":"2175 Westchester Ave",
    "sg:city":"Bronx",
    "sg:classifiers":[
        {
            "category":"Health Services",
            "subcategory":"Doctor",
            "type":"Services"
        }
    ],
    "sg:phone":"+1 718 829 6770",
    "sg:postcode":"10462",
    "sg:province":"NY",
    "sg:tags":[
        "physician",
        "surgeon"
    ],
    "wof:name":"Montefiore Medical Group",
    "wof:placetype":"venue"
},
  "geometry": {"coordinates":[-73.852154,40.834209],"type":"Point"}
}