{
  "type": "Feature",
  "properties": {
    "addr:full":"57 Mc Gaw Ave Lake Grove NY 11755",
    "addr:housenumber":"57",
    "addr:postcode":"11755",
    "addr:street":"Mc Gaw Ave",
    "iso:country":"US",
    "sg:address":"57 Mc Gaw Ave",
    "sg:city":"Lake Grove",
    "sg:classifiers":[
        {
            "category":"Wholesale",
            "subcategory":"Machinery & Supplies",
            "type":"Manufacturing & Wholesale Goods"
        },
        {
            "category":"Utilities",
            "subcategory":"Refuse",
            "type":"Services"
        }
    ],
    "sg:phone":"+1 631 585 9800",
    "sg:postcode":"11755",
    "sg:province":"NY",
    "sg:tags":[
        "industrial",
        "equipment",
        "recycling",
        "system"
    ],
    "wof:name":"Eco-Line Equipment Inc",
    "wof:placetype":"venue"
},
  "geometry": {"coordinates":[-73.108284,40.863257],"type":"Point"}
}