{
  "type": "Feature",
  "properties": {
    "addr:full":"545 W End Ave New York NY 10024",
    "addr:housenumber":"545",
    "addr:postcode":"10024",
    "addr:street":"W End Ave",
    "iso:country":"US",
    "sg:address":"545 W End Ave",
    "sg:city":"New York",
    "sg:classifiers":[
        {
            "category":"Manufacturing",
            "subcategory":"Printing",
            "type":"Manufacturing & Wholesale Goods"
        }
    ],
    "sg:phone":"+1   ",
    "sg:postcode":"10024",
    "sg:province":"NY",
    "sg:tags":[
        "publishing"
    ],
    "wof:name":"Carmine Street Publishing",
    "wof:placetype":"venue"
},
  "geometry": {"coordinates":[-73.977474,40.78951],"type":"Point"}
}