{
  "type": "Feature",
  "properties": {
    "iso:country":"US",
    "sg:address":"136 Cedar St",
    "sg:city":"Amityville",
    "sg:classifiers":[
        {
            "category":"Manufacturing",
            "subcategory":"Printing",
            "type":"Manufacturing & Wholesale Goods"
        }
    ],
    "sg:phone":"+1 631 598 5812",
    "sg:postcode":"11701",
    "sg:province":"NY",
    "sg:tags":[
        "periodical"
    ],
    "wof:name":"Guadalupe Press",
    "wof:placetype":"venue"
},
  "geometry": {"coordinates":[-73.421243,40.674194],"type":"Point"}
}