{
  "type": "Feature",
  "properties": {
    "addr:full":"845 63rd St Brooklyn NY 11220",
    "addr:housenumber":"845",
    "addr:postcode":"11220",
    "addr:street":"63Rd St",
    "iso:country":"US",
    "sg:address":"845 63rd St",
    "sg:city":"Brooklyn",
    "sg:classifiers":[
        {
            "category":"Professional",
            "subcategory":"Advertising",
            "type":"Services"
        }
    ],
    "sg:phone":"+1 212 354 9898",
    "sg:postcode":"11220",
    "sg:province":"NY",
    "sg:website":"www.spritz.com",
    "wof:name":"SPRITZ.COM",
    "wof:placetype":"venue"
},
  "geometry": {"coordinates":[-74.00982500000001,40.63312],"type":"Point"}
}