{
  "type": "Feature",
  "properties": {
    "iso:country":"US",
    "sg:address":"6 Andam Way",
    "sg:city":"Saint James",
    "sg:classifiers":[
        {
            "category":"Wholesale",
            "subcategory":"Electrical",
            "type":"Manufacturing & Wholesale Goods"
        }
    ],
    "sg:phone":"+1 631 584 4225",
    "sg:postcode":"11780",
    "sg:province":"NY",
    "sg:tags":[
        "light",
        "tube",
        "fixture",
        "equipment",
        "lighting",
        "bulb"
    ],
    "wof:name":"Global Lite Corp",
    "wof:placetype":"venue"
},
  "geometry": {"coordinates":[-73.14810199999999,40.884602],"type":"Point"}
}