{
  "type": "Feature",
  "properties": {
    "iso:country":"US",
    "sg:address":"1580 Watson Ave",
    "sg:city":"Bronx",
    "sg:classifiers":[
        {
            "category":"Travel",
            "subcategory":"Travel Agent",
            "type":"Entertainment"
        }
    ],
    "sg:phone":"+1 718 893 0800",
    "sg:postcode":"10472",
    "sg:province":"NY",
    "sg:tags":[
        "agency",
        "bureau"
    ],
    "wof:name":"Grullon-Pena Brokerage",
    "wof:placetype":"venue"
},
  "geometry": {"coordinates":[-73.87672499999999,40.826277],"type":"Point"}
}