{
  "type": "Feature",
  "properties": {
    "addr:full":"216 Payne Ave North Tonawanda NY 14120",
    "addr:housenumber":"216",
    "addr:postcode":"14120",
    "addr:street":"Payne Ave",
    "iso:country":"US",
    "sg:address":"216 Payne Ave",
    "sg:city":"North Tonawanda",
    "sg:classifiers":[
        {
            "category":"Government",
            "subcategory":"Office",
            "type":"Public Place"
        }
    ],
    "sg:phone":"+1 716 695 8575",
    "sg:postcode":"14120",
    "sg:province":"NY",
    "sg:tags":[
        "city",
        "taxation"
    ],
    "wof:name":"North Tonawanda Treasurer",
    "wof:placetype":"venue"
},
  "geometry": {"coordinates":[-78.86967199999999,43.030052],"type":"Point"}
}