{
  "type": "Feature",
  "properties": {
    "addr:full":"1618 Genesee St Utica NY 13502",
    "addr:housenumber":"1618",
    "addr:postcode":"13502",
    "addr:street":"Genesee St",
    "iso:country":"US",
    "sg:address":"1618 Genesee St",
    "sg:city":"Utica",
    "sg:classifiers":[
        {
            "category":"Professional",
            "subcategory":"Secretarial Services",
            "type":"Services"
        }
    ],
    "sg:phone":"+1 315 734 9053",
    "sg:postcode":"13502",
    "sg:province":"NY",
    "sg:tags":[
        "reporting"
    ],
    "wof:name":"Accurate Court Reporting Inc",
    "wof:placetype":"venue"
},
  "geometry": {"coordinates":[-75.253867,43.090289],"type":"Point"}
}