{
  "type": "Feature",
  "properties": {
    "addr:full":"387 Main St Bolivar NY 14715",
    "addr:housenumber":"387",
    "addr:postcode":"14715",
    "addr:street":"Main St Bolivar",
    "iso:country":"US",
    "sg:address":"387 Main St",
    "sg:city":"Bolivar",
    "sg:classifiers":[
        {
            "category":"Organizations",
            "subcategory":"Community Association",
            "type":"Services"
        }
    ],
    "sg:phone":"+1 585 928 2427",
    "sg:postcode":"14715",
    "sg:province":"NY",
    "sg:tags":[
        "military"
    ],
    "wof:name":"American Legion",
    "wof:placetype":"venue"
},
  "geometry": {"coordinates":[-78.167975,42.065336],"type":"Point"}
}