{
  "type": "Feature",
  "properties": {
    "addr:full":"3 W Mosholu Pkwy N Bronx NY 10467",
    "addr:housenumber":"3",
    "addr:postcode":"10467",
    "addr:street":"W Mosholu Pkwy N",
    "iso:country":"US",
    "sg:address":"3 W Mosholu Pkwy N",
    "sg:city":"Bronx",
    "sg:classifiers":[
        {
            "category":"Food & Beverages",
            "subcategory":"Groceries & Convenience Stores",
            "type":"Retail Goods"
        }
    ],
    "sg:phone":"+1 718 653 4739",
    "sg:postcode":"10467",
    "sg:province":"NY",
    "sg:tags":[
        "grocer"
    ],
    "wof:name":"Mercedes Food Market",
    "wof:placetype":"venue"
},
  "geometry": {"coordinates":[-73.884179,40.881197],"type":"Point"}
}