{
  "type": "Feature",
  "properties": {
    "iso:country":"US",
    "sg:address":"19 Sylvan Glen",
    "sg:city":"Fairport",
    "sg:classifiers":[
        {
            "category":"Professional",
            "subcategory":"Management & Consulting",
            "type":"Services"
        }
    ],
    "sg:phone":"+1 585 233 6707",
    "sg:postcode":"14450",
    "sg:province":"NY",
    "sg:tags":[
        "marketing",
        "s",
        "business",
        "strategy"
    ],
    "wof:name":"Northpoint Advisors LLC",
    "wof:placetype":"venue"
},
  "geometry": {"coordinates":[-77.448584,43.048157],"type":"Point"}
}