{
  "type": "Feature",
  "properties": {
    "iso:country":"US",
    "sg:address":"17 Mill Hill Rd",
    "sg:city":"Woodstock",
    "sg:classifiers":[
        {
            "category":"Bars & Pubs",
            "type":"Food & Drink"
        }
    ],
    "sg:phone":"+1   ",
    "sg:postcode":"12498",
    "sg:province":"NY",
    "sg:tags":[
        "drinking",
        "eating"
    ],
    "wof:name":"Landau Grill",
    "wof:placetype":"venue"
},
  "geometry": {"coordinates":[-74.118329,42.041003],"type":"Point"}
}