{
  "type": "Feature",
  "properties": {
    "addr:full":"289 Granite Ave Staten Island NY 10303",
    "addr:housenumber":"289",
    "addr:postcode":"10303",
    "addr:street":"Granite Ave",
    "iso:country":"US",
    "sg:address":"289 Granite Ave",
    "sg:city":"Staten Island",
    "sg:classifiers":[
        {
            "category":"Professional",
            "subcategory":"Advertising",
            "type":"Services"
        }
    ],
    "sg:phone":"+1 718 448 1524",
    "sg:postcode":"10303",
    "sg:province":"NY",
    "sg:tags":[
        "distribution"
    ],
    "wof:name":"Ernie B's Reggie Distribution",
    "wof:placetype":"venue"
},
  "geometry": {"coordinates":[-74.149783,40.628541],"type":"Point"}
}