{
  "type": "Feature",
  "properties": {
    "addr:full":"408 Hunts Point Ave Bronx NY 10474",
    "addr:housenumber":"408",
    "addr:postcode":"10474",
    "addr:street":"Hunts Point Ave",
    "iso:country":"US",
    "sg:address":"408 Hunts Point Ave",
    "sg:city":"Bronx",
    "sg:classifiers":[
        {
            "category":"Professional",
            "type":"Services"
        }
    ],
    "sg:phone":"+1 718 861 4929",
    "sg:postcode":"10474",
    "sg:province":"NY",
    "sg:tags":[
        "establishment"
    ],
    "wof:name":"Hunt's Point Triangle Inc",
    "wof:placetype":"venue"
},
  "geometry": {"coordinates":[-73.881106,40.810056],"type":"Point"}
}