{
  "type": "Feature",
  "properties": {
    "iso:country":"US",
    "sg:address":"1845 Straight Path",
    "sg:city":"Lindenhurst",
    "sg:classifiers":[
        {
            "category":"Shopping",
            "type":"Retail Goods"
        }
    ],
    "sg:phone":"+1 631 225 7724",
    "sg:postcode":"11757",
    "sg:province":"NY",
    "sg:tags":[
        "telephone",
        "cellular"
    ],
    "wof:name":"Luna Technology Inc",
    "wof:placetype":"venue"
},
  "geometry": {"coordinates":[-73.38186,40.713972],"type":"Point"}
}