{
  "type": "Feature",
  "properties": {
    "addr:full":"5287 Van Buren Rd Dunkirk NY 14048",
    "addr:housenumber":"5287",
    "addr:postcode":"14048",
    "addr:street":"Van Buren Rd",
    "iso:country":"US",
    "sg:address":"5287 Van Buren Rd",
    "sg:city":"Dunkirk",
    "sg:classifiers":[
        {
            "category":"Retail",
            "subcategory":"Animal Services",
            "type":"Services"
        }
    ],
    "sg:phone":"+1 716 672 8685",
    "sg:postcode":"14048",
    "sg:province":"NY",
    "sg:tags":[
        "pet",
        "grooming",
        "washing"
    ],
    "wof:name":"Julie's Pet Palace",
    "wof:placetype":"venue"
},
  "geometry": {"coordinates":[-79.40616199999999,42.446172],"type":"Point"}
}