{
  "type": "Feature",
  "properties": {
    "addr:full":"464 Broome St New York NY 10013",
    "addr:housenumber":"464",
    "addr:postcode":"10013",
    "addr:street":"Broome St",
    "iso:country":"US",
    "sg:address":"464 Broome St",
    "sg:city":"New York",
    "sg:classifiers":[
        {
            "category":"Shopping",
            "subcategory":"Jewelry",
            "type":"Retail Goods"
        }
    ],
    "sg:phone":"+1 212 941 5410",
    "sg:postcode":"10013",
    "sg:province":"NY",
    "sg:tags":[
        "jeweler"
    ],
    "wof:name":"Niwaka U S A Inc",
    "wof:placetype":"venue"
},
  "geometry": {"coordinates":[-74.000957,40.722352],"type":"Point"}
}