{
  "type": "Feature",
  "properties": {
    "addr:full":"1556 Parkview Ave Seaford NY 11783",
    "addr:housenumber":"1556",
    "addr:postcode":"11783",
    "addr:street":"Parkview Ave",
    "iso:country":"US",
    "sg:address":"1556 Parkview Ave",
    "sg:city":"Seaford",
    "sg:classifiers":[
        {
            "category":"Retail",
            "subcategory":"Laundry & Dry Cleaning",
            "type":"Services"
        }
    ],
    "sg:phone":"+1 516 679 8903",
    "sg:postcode":"11783",
    "sg:province":"NY",
    "sg:tags":[
        "cleaner",
        "rug",
        "carpet"
    ],
    "wof:name":"Classy Carpet Cleaners Inc",
    "wof:placetype":"venue"
},
  "geometry": {"coordinates":[-73.48411299999999,40.685682],"type":"Point"}
}