{
  "type": "Feature",
  "properties": {
    "iso:country":"US",
    "sg:address":"180 W Islip Rd",
    "sg:city":"West Islip",
    "sg:classifiers":[
        {
            "category":"Health Services",
            "subcategory":"Doctor",
            "type":"Services"
        }
    ],
    "sg:phone":"+1 631 893 0150",
    "sg:postcode":"11795",
    "sg:province":"NY",
    "sg:tags":[
        "physician",
        "surgeon"
    ],
    "sg:website":"www.plannedparenthood.org",
    "wof:name":"Planned Parenthood",
    "wof:placetype":"venue"
},
  "geometry": {"coordinates":[-73.316952,40.693716],"type":"Point"}
}