{
  "type": "Feature",
  "properties": {
    "addr:full":"461 Lincoln Pl Brooklyn NY 11238",
    "addr:housenumber":"461",
    "addr:postcode":"11238",
    "addr:street":"Lincoln Pl",
    "iso:country":"US",
    "sg:address":"461 Lincoln Pl",
    "sg:city":"Brooklyn",
    "sg:classifiers":[
        {
            "category":"Deli",
            "type":"Food & Drink"
        },
        {
            "category":"Food & Beverages",
            "subcategory":"Bakery",
            "type":"Retail Goods"
        }
    ],
    "sg:phone":"+1 718 783 0700",
    "sg:postcode":"11238",
    "sg:province":"NY",
    "sg:tags":[
        "sandwich"
    ],
    "wof:name":"Lincoln Place Deli Corporation",
    "wof:placetype":"venue"
},
  "geometry": {"coordinates":[-73.960973,40.672374],"type":"Point"}
}