{
  "type": "Feature",
  "properties": {
    "iso:country":"US",
    "sg:address":"64 Maiden Ln",
    "sg:city":"Rochester",
    "sg:classifiers":[
        {
            "category":"Education",
            "subcategory":"School",
            "type":"Public Place"
        }
    ],
    "sg:phone":"+1 585 663 1220",
    "sg:postcode":"14616",
    "sg:province":"NY",
    "sg:tags":[
        "elementary"
    ],
    "wof:name":"St Charles Borromeo School",
    "wof:placetype":"venue"
},
  "geometry": {"coordinates":[-77.643202,43.223775],"type":"Point"}
}