{
  "type": "Feature",
  "properties": {
    "addr:full":"131 E 10 St New York NY 10003",
    "addr:housenumber":"131;10",
    "addr:postcode":"10003",
    "addr:street":"E",
    "iso:country":"US",
    "sg:address":"131 E 10 St",
    "sg:city":"New York",
    "sg:classifiers":[
        {
            "category":"Organizations",
            "subcategory":"Membership Organization",
            "type":"Services"
        }
    ],
    "sg:phone":"+1   ",
    "sg:postcode":"10003",
    "sg:province":"NY",
    "sg:tags":[
        "book"
    ],
    "wof:name":"Poetry Project Limited Inc",
    "wof:placetype":"venue"
},
  "geometry": {"coordinates":[-73.988454,40.730704],"type":"Point"}
}