{
  "type": "Feature",
  "properties": {
    "addr:full":"626 State Hwy 163 Fort Plain NY 13339",
    "addr:housenumber":"626",
    "addr:postcode":"13339",
    "addr:street":"State Hwy 163;Plain",
    "iso:country":"US",
    "sg:address":"626 State Hwy 163",
    "sg:city":"Fort Plain",
    "sg:classifiers":[
        {
            "category":"Farming",
            "subcategory":"Dairy Farm",
            "type":"Manufacturing & Wholesale Goods"
        }
    ],
    "sg:phone":"+1 518 993 2410",
    "sg:postcode":"13339",
    "sg:province":"NY",
    "wof:name":"Frys Bush Farm",
    "wof:placetype":"venue"
},
  "geometry": {"coordinates":[-74.663923,42.900284],"type":"Point"}
}