{
  "type": "Feature",
  "properties": {
    "addr:full":"612 W 47 St New York NY 10036",
    "addr:housenumber":"612",
    "addr:postcode":"10036",
    "addr:street":"W 47 St",
    "iso:country":"US",
    "sg:address":"612 W 47 St",
    "sg:city":"New York",
    "sg:classifiers":[
        {
            "category":"Autos & Motor Vehicles",
            "subcategory":"Auto Supplies",
            "type":"Retail Goods"
        }
    ],
    "sg:phone":"+1 212 582 1918",
    "sg:postcode":"10036",
    "sg:province":"NY",
    "sg:tags":[
        "automobile",
        "parts"
    ],
    "wof:name":"AMU Intl",
    "wof:placetype":"venue"
},
  "geometry": {"coordinates":[-73.99802200000001,40.764746],"type":"Point"}
}