{
  "type": "Feature",
  "properties": {
    "addr:full":"230 Delaware Ave Albany NY 12209",
    "addr:housenumber":"230",
    "addr:postcode":"12209",
    "addr:street":"Delaware Ave",
    "iso:country":"US",
    "sg:address":"230 Delaware Ave",
    "sg:city":"Albany",
    "sg:classifiers":[
        {
            "category":"Health Services",
            "subcategory":"Medical Lab",
            "type":"Services"
        }
    ],
    "sg:phone":"+1 518 449 5194",
    "sg:postcode":"12209",
    "sg:province":"NY",
    "sg:tags":[
        "laboratory"
    ],
    "wof:name":"Northeastern Dental Lab Corp",
    "wof:placetype":"venue"
},
  "geometry": {"coordinates":[-73.77673900000001,42.64323],"type":"Point"}
}