{
  "type": "Feature",
  "properties": {
    "addr:full":"138 Montague St Brooklyn NY 11201",
    "addr:housenumber":"138",
    "addr:postcode":"11201",
    "addr:street":"Montague St",
    "iso:country":"US",
    "sg:address":"138 Montague St",
    "sg:city":"Brooklyn",
    "sg:classifiers":[
        {
            "category":"Shopping",
            "type":"Retail Goods"
        }
    ],
    "sg:phone":"+1   ",
    "sg:postcode":"11201",
    "sg:province":"NY",
    "sg:tags":[
        "picture",
        "art",
        "framing",
        "supply"
    ],
    "wof:name":"Montague Arts Inc",
    "wof:placetype":"venue"
},
  "geometry": {"coordinates":[-73.992824,40.694341],"type":"Point"}
}