{
  "type": "Feature",
  "properties": {
    "iso:country":"US",
    "sg:address":"1509 Jerome Ave",
    "sg:city":"Bronx",
    "sg:classifiers":[
        {
            "category":"Food & Beverages",
            "subcategory":"Specialty",
            "type":"Retail Goods"
        }
    ],
    "sg:phone":"+1 718 716 8699",
    "sg:postcode":"10452",
    "sg:province":"NY",
    "sg:tags":[
        "poultry"
    ],
    "wof:name":"Great Farm Live Poultry Inc",
    "wof:placetype":"venue"
},
  "geometry": {"coordinates":[-73.91561900000001,40.843207],"type":"Point"}
}