{
  "type": "Feature",
  "properties": {
    "iso:country":"US",
    "sg:address":"1342 New York Ave",
    "sg:city":"Huntington Station",
    "sg:classifiers":[
        {
            "category":"Real Estate",
            "subcategory":"Real Estate Agent",
            "type":"Services"
        }
    ],
    "sg:phone":"+1 631 427 4065",
    "sg:postcode":"11746",
    "sg:province":"NY",
    "sg:tags":[
        "broker"
    ],
    "sg:website":"www.fer-jonrealty.com",
    "wof:name":"Fer-Jon Realty Corp",
    "wof:placetype":"venue"
},
  "geometry": {"coordinates":[-73.41150500000001,40.850871],"type":"Point"}
}