{
  "type": "Feature",
  "properties": {
    "iso:country":"US",
    "sg:address":"9 Summit St",
    "sg:city":"Fairport",
    "sg:classifiers":[
        {
            "category":"Banks & Credit Unions",
            "subcategory":"Investment Brokerage",
            "type":"Services"
        }
    ],
    "sg:phone":"+1 585 239 5850",
    "sg:postcode":"14450",
    "sg:province":"NY",
    "sg:tags":[
        "consultant",
        "financing"
    ],
    "wof:name":"Summit View Consulting",
    "wof:placetype":"venue"
},
  "geometry": {"coordinates":[-77.437256,43.094757],"type":"Point"}
}