{
  "type": "Feature",
  "properties": {
    "addr:full":"1302 County Route 25 Malone NY 12953",
    "addr:housenumber":"1302",
    "addr:postcode":"12953",
    "addr:street":"County Route 25",
    "iso:country":"US",
    "sg:address":"1302 County Route 25",
    "sg:city":"Malone",
    "sg:classifiers":[
        {
            "category":"Manufacturing",
            "subcategory":"Buildings",
            "type":"Manufacturing & Wholesale Goods"
        },
        {
            "category":"Building & Trades",
            "subcategory":"Construction",
            "type":"Services"
        }
    ],
    "sg:phone":"+1 518 483 4021",
    "sg:postcode":"12953",
    "sg:province":"NY",
    "sg:tags":[
        "home",
        "builder",
        "contractor"
    ],
    "wof:name":"C S Lawrence & Associates",
    "wof:placetype":"venue"
},
  "geometry": {"coordinates":[-74.269199,44.819876],"type":"Point"}
}