{
  "type": "Feature",
  "properties": {
    "addr:full":"1402 Kings Hwy Brooklyn NY 11229",
    "addr:housenumber":"1402",
    "addr:postcode":"11229",
    "addr:street":"Kings Hwy",
    "iso:country":"US",
    "sg:address":"1402 Kings Hwy",
    "sg:city":"Brooklyn",
    "sg:classifiers":[
        {
            "category":"Shopping",
            "subcategory":"Shoes",
            "type":"Retail Goods"
        }
    ],
    "sg:phone":"+1 718 645 2280",
    "sg:postcode":"11229",
    "sg:province":"NY",
    "sg:tags":[
        "store"
    ],
    "wof:name":"Parade of Shoes",
    "wof:placetype":"venue"
},
  "geometry": {"coordinates":[-73.95902,40.608317],"type":"Point"}
}