{
  "type": "Feature",
  "properties": {
    "iso:country":"US",
    "sg:address":"169 E 106th St",
    "sg:city":"New York",
    "sg:classifiers":[
        {
            "category":"Restaurant",
            "type":"Food & Drink"
        }
    ],
    "sg:phone":"+1 212 410 7292",
    "sg:postcode":"10029",
    "sg:province":"NY",
    "sg:tags":[
        "american",
        "latin",
        "spanish"
    ],
    "sg:website":"www.fondaboricua.com",
    "wof:name":"La Fonda Boricua",
    "wof:placetype":"venue"
},
  "geometry": {"coordinates":[-73.945536,40.791905],"type":"Point"}
}