{
  "type": "Feature",
  "properties": {
    "iso:country":"US",
    "sg:address":"1 Eddy St",
    "sg:city":"Fort Edward",
    "sg:classifiers":[
        {
            "category":"Wholesale",
            "subcategory":"Furniture",
            "type":"Manufacturing & Wholesale Goods"
        }
    ],
    "sg:phone":"+1 518 747 3174",
    "sg:postcode":"12828",
    "sg:province":"NY",
    "wof:name":"Protran Services Inc",
    "wof:placetype":"venue"
},
  "geometry": {"coordinates":[-73.58913200000001,43.269231],"type":"Point"}
}