{
  "type": "Feature",
  "properties": {
    "iso:country":"US",
    "sg:address":"962 Broadway",
    "sg:city":"Thornwood",
    "sg:classifiers":[
        {
            "category":"Banks & Credit Unions",
            "subcategory":"Bank",
            "type":"Services"
        }
    ],
    "sg:phone":"+1 914 769 7500",
    "sg:postcode":"10594",
    "sg:province":"NY",
    "sg:website":"www.wachovia.com",
    "wof:name":"Wachovia",
    "wof:placetype":"venue"
},
  "geometry": {"coordinates":[-73.780197,41.1255],"type":"Point"}
}