{
  "type": "Feature",
  "properties": {
    "addr:full":"250 W. 54th St. New York NY 10019",
    "addr:housenumber":"250",
    "addr:postcode":"10019",
    "addr:street":"W. 54Th St.",
    "iso:country":"US",
    "sg:address":"250 W. 54th St.",
    "sg:city":"New York",
    "sg:classifiers":[
        {
            "category":"Building & Trades",
            "subcategory":"Pest Control",
            "type":"Services"
        }
    ],
    "sg:phone":"+1 888 737 8007",
    "sg:postcode":"10019",
    "sg:province":"NY",
    "sg:website":"www.proactivepestcontrol.com",
    "wof:name":"ProActive Pest Control",
    "wof:placetype":"venue"
},
  "geometry": {"coordinates":[-73.983503,40.764411],"type":"Point"}
}