{
  "type": "Feature",
  "properties": {
    "addr:full":"2992 3rd Ave Bronx NY 10455",
    "addr:housenumber":"2992",
    "addr:postcode":"10455",
    "addr:street":"3Rd Ave",
    "iso:country":"US",
    "sg:address":"2992 3rd Ave",
    "sg:city":"Bronx",
    "sg:classifiers":[
        {
            "category":"Shopping",
            "subcategory":"Discount & Variety Stores",
            "type":"Retail Goods"
        }
    ],
    "sg:phone":"+1 718 585 3878",
    "sg:postcode":"10455",
    "sg:province":"NY",
    "sg:tags":[
        "outlet"
    ],
    "sg:website":"www.ninewest.com",
    "wof:name":"Nine West Outlet",
    "wof:placetype":"venue"
},
  "geometry": {"coordinates":[-73.91422300000001,40.818541],"type":"Point"}
}