{
  "type": "Feature",
  "properties": {
    "addr:full":"333 W 17 St New York NY 10011",
    "addr:housenumber":"333",
    "addr:postcode":"10011",
    "addr:street":"W 17 St",
    "iso:country":"US",
    "sg:address":"333 W 17 St",
    "sg:city":"New York",
    "sg:classifiers":[
        {
            "category":"Education",
            "subcategory":"School",
            "type":"Public Place"
        }
    ],
    "sg:phone":"+1 212 674 4545",
    "sg:postcode":"10011",
    "sg:province":"NY",
    "wof:name":"PS 70",
    "wof:placetype":"venue"
},
  "geometry": {"coordinates":[-74.00323,40.742538],"type":"Point"}
}