{
  "type": "Feature",
  "properties": {
    "addr:full":"116 W Houston St New York NY 10012",
    "addr:housenumber":"116",
    "addr:postcode":"10012",
    "addr:street":"W Houston St",
    "iso:country":"US",
    "sg:address":"116 W Houston St",
    "sg:city":"New York",
    "sg:classifiers":[
        {
            "category":"Wholesale",
            "subcategory":"Home Furnishings",
            "type":"Manufacturing & Wholesale Goods"
        }
    ],
    "sg:phone":"+1 212 614 2146",
    "sg:postcode":"10012",
    "sg:province":"NY",
    "sg:tags":[
        "warehouse"
    ],
    "wof:name":"Y & H Realty Corp",
    "wof:placetype":"venue"
},
  "geometry": {"coordinates":[-74.001119,40.727574],"type":"Point"}
}