{
  "type": "Feature",
  "properties": {
    "addr:full":"1261 Eastern Pkwy Brooklyn NY 11213",
    "addr:housenumber":"1261",
    "addr:postcode":"11213",
    "addr:street":"Eastern Pkwy",
    "iso:country":"US",
    "sg:address":"1261 Eastern Pkwy",
    "sg:city":"Brooklyn",
    "sg:classifiers":[
        {
            "category":"Real Estate",
            "subcategory":"Real Estate Agent",
            "type":"Services"
        }
    ],
    "sg:phone":"+1 718 467 2472",
    "sg:postcode":"11213",
    "sg:province":"NY",
    "sg:tags":[
        "manager"
    ],
    "wof:name":"CBS Realty Management LLC",
    "wof:placetype":"venue"
},
  "geometry": {"coordinates":[-73.92694899999999,40.668669],"type":"Point"}
}