{
  "type": "Feature",
  "properties": {
    "addr:full":"111 College Pl Syracuse NY 13210",
    "addr:housenumber":"111",
    "addr:postcode":"13210",
    "addr:street":"College Pl",
    "iso:country":"US",
    "sg:address":"111 College Pl",
    "sg:city":"Syracuse",
    "sg:classifiers":[
        {
            "category":"Education",
            "subcategory":"College",
            "type":"Public Place"
        }
    ],
    "sg:phone":"+1 315 443 2925",
    "sg:postcode":"13210",
    "sg:province":"NY",
    "sg:tags":[
        "university"
    ],
    "wof:name":"Chemistry Department",
    "wof:placetype":"venue"
},
  "geometry": {"coordinates":[-76.131298,43.036572],"type":"Point"}
}