{
  "type": "Feature",
  "properties": {
    "addr:full":"247 Decatur St Brooklyn NY 11233",
    "addr:housenumber":"247",
    "addr:postcode":"11233",
    "addr:street":"Decatur St",
    "iso:country":"US",
    "sg:address":"247 Decatur St",
    "sg:city":"Brooklyn",
    "sg:classifiers":[
        {
            "category":"Real Estate",
            "subcategory":"Real Estate Agent",
            "type":"Services"
        }
    ],
    "sg:phone":"+1 718 774 1831",
    "sg:postcode":"11233",
    "sg:province":"NY",
    "wof:name":"Madison Ward Realty Inc",
    "wof:placetype":"venue"
},
  "geometry": {"coordinates":[-73.932463,40.681608],"type":"Point"}
}