{
  "type": "Feature",
  "properties": {
    "iso:country":"US",
    "sg:address":"97 Main St",
    "sg:city":"Delhi",
    "sg:classifiers":[
        {
            "category":"Social Services",
            "subcategory":"Job Training",
            "type":"Services"
        }
    ],
    "sg:phone":"+1 607 746 7477",
    "sg:postcode":"13753",
    "sg:province":"NY",
    "wof:name":"Private Industry Council",
    "wof:placetype":"venue"
},
  "geometry": {"coordinates":[-74.91611399999999,42.277905],"type":"Point"}
}