{
  "type": "Feature",
  "properties": {
    "iso:country":"US",
    "sg:address":"745 Waverly Ave",
    "sg:city":"Holtsville",
    "sg:classifiers":[
        {
            "category":"Social Services",
            "type":"Services"
        }
    ],
    "sg:phone":"+1 631 654 8007",
    "sg:postcode":"11742",
    "sg:province":"NY",
    "wof:name":"Silo",
    "wof:placetype":"venue"
},
  "geometry": {"coordinates":[-73.043125,40.791311],"type":"Point"}
}