{
  "type": "Feature",
  "properties": {
    "addr:full":"4877 Broadway New York NY 10034",
    "addr:housenumber":"4877",
    "addr:postcode":"10034",
    "addr:street":"Broadway",
    "iso:country":"US",
    "sg:address":"4877 Broadway",
    "sg:city":"New York",
    "sg:classifiers":[
        {
            "category":"Shopping",
            "subcategory":"Clothing, Apparel, & Fashions",
            "type":"Retail Goods"
        }
    ],
    "sg:phone":"+1 212 567 5566",
    "sg:postcode":"10034",
    "sg:province":"NY",
    "sg:tags":[
        "accessory",
        "clothing",
        "women's"
    ],
    "wof:name":"So Ho New York",
    "wof:placetype":"venue"
},
  "geometry": {"coordinates":[-73.92354899999999,40.866858],"type":"Point"}
}