{
  "type": "Feature",
  "properties": {
    "iso:country":"US",
    "sg:address":"65 Center St",
    "sg:city":"Waterloo",
    "sg:classifiers":[
        {
            "category":"Building & Trades",
            "subcategory":"Construction",
            "type":"Services"
        }
    ],
    "sg:phone":"+1 315 539 2220",
    "sg:postcode":"13165",
    "sg:province":"NY",
    "sg:tags":[
        "general",
        "contractor"
    ],
    "wof:name":"Difiore Construction",
    "wof:placetype":"venue"
},
  "geometry": {"coordinates":[-76.864902,42.910095],"type":"Point"}
}