{
  "type": "Feature",
  "properties": {
    "addr:full":"1211 Montauk Hwy Oakdale NY 11769",
    "addr:housenumber":"1211",
    "addr:postcode":"11769",
    "addr:street":"Montauk Hwy",
    "iso:country":"US",
    "sg:address":"1211 Montauk Hwy",
    "sg:city":"Oakdale",
    "sg:classifiers":[
        {
            "category":"Home & Garden",
            "subcategory":"Building Materials",
            "type":"Retail Goods"
        }
    ],
    "sg:phone":"+1 631 244 7447",
    "sg:postcode":"11769",
    "sg:province":"NY",
    "sg:tags":[
        "screen",
        "window"
    ],
    "wof:name":"Universal Screen Process Inc",
    "wof:placetype":"venue"
},
  "geometry": {"coordinates":[-73.129412,40.741618],"type":"Point"}
}