{
  "type": "Feature",
  "properties": {
    "addr:full":"2850 Clover St Pittsford NY 14534",
    "addr:housenumber":"2850",
    "addr:postcode":"14534",
    "addr:street":"Clover St",
    "iso:country":"US",
    "sg:address":"2850 Clover St",
    "sg:city":"Pittsford",
    "sg:classifiers":[
        {
            "category":"Real Estate",
            "subcategory":"Real Estate Agent",
            "type":"Services"
        }
    ],
    "sg:phone":"+1 585 381 7660",
    "sg:postcode":"14534",
    "sg:province":"NY",
    "wof:name":"Property Advisory LLC",
    "wof:placetype":"venue"
},
  "geometry": {"coordinates":[-77.542661,43.085236],"type":"Point"}
}