{
  "type": "Feature",
  "properties": {
    "addr:full":"631 Niagara St Buffalo NY 14201",
    "addr:housenumber":"631",
    "addr:postcode":"14201",
    "addr:street":"Niagara St",
    "iso:country":"US",
    "sg:address":"631 Niagara St",
    "sg:city":"Buffalo",
    "sg:classifiers":[
        {
            "category":"Education",
            "subcategory":"University",
            "type":"Public Place"
        }
    ],
    "sg:phone":"+1 716 883 0502",
    "sg:postcode":"14201",
    "sg:province":"NY",
    "sg:tags":[
        "college"
    ],
    "wof:name":"D'Youville College",
    "wof:placetype":"venue"
},
  "geometry": {"coordinates":[-78.892053,42.901414],"type":"Point"}
}