{
  "type": "Feature",
  "properties": {
    "addr:full":"666 Main St West Seneca NY 14224",
    "addr:housenumber":"666",
    "addr:postcode":"14224",
    "addr:street":"Main St",
    "iso:country":"US",
    "sg:address":"666 Main St",
    "sg:city":"West Seneca",
    "sg:classifiers":[
        {
            "category":"Government",
            "subcategory":"Fire Station",
            "type":"Public Place"
        }
    ],
    "sg:phone":"+1 716 674 0420",
    "sg:postcode":"14224",
    "sg:province":"NY",
    "sg:tags":[
        "department"
    ],
    "wof:name":"Vigilant Fire Dept",
    "wof:placetype":"venue"
},
  "geometry": {"coordinates":[-78.750637,42.834071],"type":"Point"}
}