{
  "type": "Feature",
  "properties": {
    "addr:full":"101 Glen Cove Dr Glen Head NY 11545",
    "addr:housenumber":"101",
    "addr:postcode":"11545",
    "addr:street":"Glen Cove Dr Glen Head",
    "iso:country":"US",
    "sg:address":"101 Glen Cove Dr",
    "sg:city":"Glen Head",
    "sg:classifiers":[
        {
            "category":"Building & Trades",
            "subcategory":"Construction",
            "type":"Services"
        }
    ],
    "sg:phone":"+1 516 759 7396",
    "sg:postcode":"11545",
    "sg:province":"NY",
    "sg:tags":[
        "contractor"
    ],
    "wof:name":"Independent Contracting Group",
    "wof:placetype":"venue"
},
  "geometry": {"coordinates":[-73.618212,40.841364],"type":"Point"}
}