{
  "type": "Feature",
  "properties": {
    "addr:full":"1956 Clinton Ave Bronx NY 10457",
    "addr:housenumber":"1956",
    "addr:postcode":"10457",
    "addr:street":"Clinton Ave",
    "iso:country":"US",
    "sg:address":"1956 Clinton Ave",
    "sg:city":"Bronx",
    "sg:classifiers":[
        {
            "category":"Retail",
            "subcategory":"Auto Repair",
            "type":"Services"
        }
    ],
    "sg:phone":"+1 718 535 9302",
    "sg:postcode":"10457",
    "sg:province":"NY",
    "sg:tags":[
        "wrecker"
    ],
    "wof:name":"7 Day Emergency 24 Hr",
    "wof:placetype":"venue"
},
  "geometry": {"coordinates":[-73.890694,40.843833],"type":"Point"}
}