{
  "type": "Feature",
  "properties": {
    "iso:country":"US",
    "sg:address":"420 Jefferson Rd",
    "sg:city":"Rochester",
    "sg:classifiers":[
        {
            "category":"Home & Garden",
            "subcategory":"Furniture",
            "type":"Retail Goods"
        }
    ],
    "sg:phone":"+1   ",
    "sg:postcode":"14623",
    "sg:province":"NY",
    "wof:name":"Raymour & Flanigan Furniture",
    "wof:placetype":"venue"
},
  "geometry": {"coordinates":[-77.64090899999999,43.089085],"type":"Point"}
}