{
  "type": "Feature",
  "properties": {
    "addr:full":"109 West St Ilion NY 13357",
    "addr:housenumber":"109",
    "addr:postcode":"13357",
    "addr:street":"West St",
    "iso:country":"US",
    "sg:address":"109 West St",
    "sg:city":"Ilion",
    "sg:classifiers":[
        {
            "category":"Organizations",
            "subcategory":"Religious Organization",
            "type":"Services"
        }
    ],
    "sg:phone":"+1 315 894 3766",
    "sg:postcode":"13357",
    "sg:province":"NY",
    "sg:tags":[
        "church"
    ],
    "wof:name":"Annunciation Church",
    "wof:placetype":"venue"
},
  "geometry": {"coordinates":[-75.039513,43.012614],"type":"Point"}
}