{
  "type": "Feature",
  "properties": {
    "addr:full":"200 W 134th St New York NY 10030",
    "addr:housenumber":"200",
    "addr:postcode":"10030",
    "addr:street":"W 134Th St",
    "iso:country":"US",
    "sg:address":"200 W 134th St",
    "sg:city":"New York",
    "sg:classifiers":[
        {
            "category":"Professional",
            "type":"Services"
        }
    ],
    "sg:phone":"+1 212 368 1897",
    "sg:postcode":"10030",
    "sg:province":"NY",
    "sg:tags":[
        "establishment"
    ],
    "wof:name":"133-135 STREET LLC",
    "wof:placetype":"venue"
},
  "geometry": {"coordinates":[-73.947034,40.81583],"type":"Point"}
}