{
  "type": "Feature",
  "properties": {
    "addr:full":"230 West 108th New York NY 10025",
    "addr:housenumber":"230",
    "addr:postcode":"10025",
    "addr:street":"West 108Th",
    "iso:country":"US",
    "sg:address":"230 West 108th",
    "sg:city":"New York",
    "sg:classifiers":[
        {
            "category":"Professional",
            "subcategory":"Advertising",
            "type":"Services"
        },
        {
            "category":"Professional",
            "subcategory":"Art Services",
            "type":"Services"
        }
    ],
    "sg:phone":"+1 646 374 8688",
    "sg:postcode":"10025",
    "sg:province":"NY",
    "sg:tags":[
        "photographer",
        "videographers"
    ],
    "sg:website":"www.weddingsbyjoshuabrown.com",
    "wof:name":"Weddings by Joshua Brown",
    "wof:placetype":"venue"
},
  "geometry": {"coordinates":[-73.96656,40.802245],"type":"Point"}
}