{
  "type": "Feature",
  "properties": {
    "addr:full":"15 Old Westbury Rd Roslyn Heights NY 11577",
    "addr:housenumber":"15",
    "addr:postcode":"11577",
    "addr:street":"Old Westbury Rd",
    "iso:country":"US",
    "sg:address":"15 Old Westbury Rd",
    "sg:city":"Roslyn Heights",
    "sg:classifiers":[
        {
            "category":"Retail",
            "subcategory":"Laundry & Dry Cleaning",
            "type":"Services"
        }
    ],
    "sg:phone":"+1 516 484 7479",
    "sg:postcode":"11577",
    "sg:province":"NY",
    "wof:name":"Imperial Cleaners",
    "wof:placetype":"venue"
},
  "geometry": {"coordinates":[-73.624199,40.784401],"type":"Point"}
}