{
  "type": "Feature",
  "properties": {
    "iso:country":"US",
    "sg:address":"52 N Sea Rd",
    "sg:city":"Southampton",
    "sg:classifiers":[
        {
            "category":"Restaurant",
            "type":"Food & Drink"
        }
    ],
    "sg:phone":"+1 631 283 2800",
    "sg:postcode":"11968",
    "sg:province":"NY",
    "wof:name":"Southampton Publick House",
    "wof:placetype":"venue"
},
  "geometry": {"coordinates":[-72.39355,40.890575],"type":"Point"}
}