{
  "type": "Feature",
  "properties": {
    "addr:full":"21 Washington St Brooklyn NY 11201",
    "addr:housenumber":"21",
    "addr:postcode":"11201",
    "addr:street":"Washington St",
    "iso:country":"US",
    "sg:address":"21 Washington St",
    "sg:city":"Brooklyn",
    "sg:classifiers":[
        {
            "category":"Retail",
            "subcategory":"Repair Shop",
            "type":"Services"
        }
    ],
    "sg:phone":"+1 718 359 8488",
    "sg:postcode":"11201",
    "sg:province":"NY",
    "sg:tags":[
        "lock",
        "locksmith"
    ],
    "wof:name":"Always Ready Locksmith",
    "wof:placetype":"venue"
},
  "geometry": {"coordinates":[-73.989583,40.7032],"type":"Point"}
}