{
  "type": "Feature",
  "properties": {
    "iso:country":"US",
    "sg:address":"1056 Luther Rd",
    "sg:city":"East Greenbush",
    "sg:classifiers":[
        {
            "category":"Professional",
            "type":"Services"
        }
    ],
    "sg:phone":"+1 518 479 1712",
    "sg:postcode":"12061",
    "sg:province":"NY",
    "sg:tags":[
        "establishment"
    ],
    "wof:name":"L A Swyer Co Inc",
    "wof:placetype":"venue"
},
  "geometry": {"coordinates":[-73.69534299999999,42.620132],"type":"Point"}
}