{
  "type": "Feature",
  "properties": {
    "addr:full":"265 S Broadway Unit 3 Hicksville NY 11801",
    "addr:housenumber":"265;unit 3",
    "addr:postcode":"11801",
    "addr:street":"S Broadway",
    "iso:country":"US",
    "sg:address":"265 S Broadway Unit 3",
    "sg:city":"Hicksville",
    "sg:classifiers":[
        {
            "category":"Shopping",
            "subcategory":"Clothing, Apparel, & Fashions",
            "type":"Retail Goods"
        }
    ],
    "sg:phone":"+1 516 937 5410",
    "sg:postcode":"11801",
    "sg:province":"NY",
    "sg:tags":[
        "accessory",
        "clothing",
        "women's"
    ],
    "wof:name":"Dress Barn",
    "wof:placetype":"venue"
},
  "geometry": {"coordinates":[-73.517713,40.762971],"type":"Point"}
}