{
  "type": "Feature",
  "properties": {
    "iso:country":"US",
    "sg:address":"250 E 84th St",
    "sg:city":"New York",
    "sg:classifiers":[
        {
            "category":"Personal",
            "subcategory":"Nail Salon",
            "type":"Services"
        }
    ],
    "sg:phone":"+1 212 744 1895",
    "sg:postcode":"10028",
    "sg:province":"NY",
    "wof:name":"Young's Sunny Nail",
    "wof:placetype":"venue"
},
  "geometry": {"coordinates":[-73.953102,40.7766],"type":"Point"}
}