{
  "type": "Feature",
  "properties": {
    "addr:full":"3 Imperial Ct Great Neck NY 11023",
    "addr:housenumber":"3",
    "addr:postcode":"11023",
    "addr:street":"Imperial Ct",
    "iso:country":"US",
    "sg:address":"3 Imperial Ct",
    "sg:city":"Great Neck",
    "sg:classifiers":[
        {
            "category":"Shopping",
            "subcategory":"Used Merchandise",
            "type":"Retail Goods"
        }
    ],
    "sg:phone":"+1   ",
    "sg:postcode":"11023",
    "sg:province":"NY",
    "wof:name":"Sohrab Oriental Rug",
    "wof:placetype":"venue"
},
  "geometry": {"coordinates":[-73.72991500000001,40.794179],"type":"Point"}
}