{
  "type": "Feature",
  "properties": {
    "iso:country":"US",
    "sg:address":"50 Clinton Ave",
    "sg:city":"Cortland",
    "sg:classifiers":[
        {
            "category":"Social Services",
            "type":"Services"
        }
    ],
    "sg:phone":"+1   ",
    "sg:postcode":"13045",
    "sg:province":"NY",
    "wof:name":"United Way of Cortland",
    "wof:placetype":"venue"
},
  "geometry": {"coordinates":[-76.176503,42.602765],"type":"Point"}
}