{
  "type": "Feature",
  "properties": {
    "iso:country":"US",
    "sg:address":"618 River Rd",
    "sg:city":"Schodack Landing",
    "sg:classifiers":[
        {
            "category":"Real Estate",
            "subcategory":"Real Estate Services",
            "type":"Services"
        }
    ],
    "sg:phone":"+1 518 732 7195",
    "sg:postcode":"12156",
    "sg:province":"NY",
    "wof:name":"Croft Title & Abstract",
    "wof:placetype":"venue"
},
  "geometry": {"coordinates":[-73.770015,42.480228],"type":"Point"}
}