{
  "type": "Feature",
  "properties": {
    "addr:full":"12622 150th Ave South Ozone Park NY 11420",
    "addr:housenumber":"12622",
    "addr:postcode":"11420",
    "addr:street":"150Th Ave",
    "iso:country":"US",
    "sg:address":"12622 150th Ave",
    "sg:city":"South Ozone Park",
    "sg:classifiers":[
        {
            "category":"Organizations",
            "subcategory":"Religious Organization",
            "type":"Services"
        }
    ],
    "sg:phone":"+1 718 529 3691",
    "sg:postcode":"11420",
    "sg:province":"NY",
    "wof:name":"United Methodist Ch Of S Oz Pk",
    "wof:placetype":"venue"
},
  "geometry": {"coordinates":[-73.814487,40.665401],"type":"Point"}
}