{
  "type": "Feature",
  "properties": {
    "addr:full":"180 Brook St Scarsdale NY 10583",
    "addr:housenumber":"180",
    "addr:postcode":"10583",
    "addr:street":"Brook St",
    "iso:country":"US",
    "sg:address":"180 Brook St",
    "sg:city":"Scarsdale",
    "sg:classifiers":[
        {
            "category":"Professional",
            "subcategory":"Lawyer & Legal Services",
            "type":"Services"
        }
    ],
    "sg:phone":"+1 914 722 1933",
    "sg:postcode":"10583",
    "sg:province":"NY",
    "sg:tags":[
        "attorney"
    ],
    "wof:name":"Christopher Tiso",
    "wof:placetype":"venue"
},
  "geometry": {"coordinates":[-73.804823,40.976645],"type":"Point"}
}