{
  "type": "Feature",
  "properties": {
    "addr:full":"7096 Marigold Dr North Tonawanda NY 14120",
    "addr:housenumber":"7096",
    "addr:postcode":"14120",
    "addr:street":"Marigold Dr",
    "iso:country":"US",
    "sg:address":"7096 Marigold Dr",
    "sg:city":"North Tonawanda",
    "sg:classifiers":[
        {
            "category":"Real Estate",
            "subcategory":"Real Estate Operator",
            "type":"Services"
        }
    ],
    "sg:phone":"+1 716 695 8826",
    "sg:postcode":"14120",
    "sg:province":"NY",
    "sg:tags":[
        "building",
        "nonresidential"
    ],
    "wof:name":"American Property Professional",
    "wof:placetype":"venue"
},
  "geometry": {"coordinates":[-78.86269299999999,43.083469],"type":"Point"}
}