{
  "type": "Feature",
  "properties": {
    "addr:full":"4017 State St Schenectady NY 12304",
    "addr:housenumber":"4017",
    "addr:postcode":"12304",
    "addr:street":"State St",
    "iso:country":"US",
    "sg:address":"4017 State St",
    "sg:city":"Schenectady",
    "sg:classifiers":[
        {
            "category":"Insurance",
            "subcategory":"Insurance Agent",
            "type":"Services"
        }
    ],
    "sg:phone":"+1 518 372 1561",
    "sg:postcode":"12304",
    "sg:province":"NY",
    "wof:name":"State Farm Insurance",
    "wof:placetype":"venue"
},
  "geometry": {"coordinates":[-73.88777899999999,42.766053],"type":"Point"}
}