{
  "type": "Feature",
  "properties": {
    "iso:country":"US",
    "sg:address":"1350 Ave of the Americas",
    "sg:city":"New York",
    "sg:classifiers":[
        {
            "category":"Insurance",
            "subcategory":"Hazard Insurance",
            "type":"Services"
        }
    ],
    "sg:phone":"+1 212 887 6000",
    "sg:postcode":"10019",
    "sg:province":"NY",
    "sg:tags":[
        "reinsurance",
        "casualty"
    ],
    "wof:name":"American Rnsrnce Risk Partners",
    "wof:placetype":"venue"
},
  "geometry": {"coordinates":[-73.978268,40.762638],"type":"Point"}
}