{
  "type": "Feature",
  "properties": {
    "addr:full":"543 E 11 St New York NY 10009",
    "addr:housenumber":"543;11",
    "addr:postcode":"10009",
    "addr:street":"E",
    "iso:country":"US",
    "sg:address":"543 E 11 St",
    "sg:city":"New York",
    "sg:classifiers":[
        {
            "category":"Organizations",
            "subcategory":"Religious Organization",
            "type":"Services"
        }
    ],
    "sg:phone":"+1 212 375 1765",
    "sg:postcode":"10009",
    "sg:province":"NY",
    "sg:tags":[
        "church"
    ],
    "sg:website":"www.fathersheartnyc.com",
    "wof:name":"Father's Heart Ministries",
    "wof:placetype":"venue"
},
  "geometry": {"coordinates":[-73.980186,40.727952],"type":"Point"}
}