{
  "type": "Feature",
  "properties": {
    "iso:country":"US",
    "sg:address":"330 E Meadow Ave",
    "sg:city":"East Meadow",
    "sg:classifiers":[
        {
            "category":"Health Services",
            "subcategory":"Doctor",
            "type":"Services"
        }
    ],
    "sg:phone":"+1 516 785 7718",
    "sg:postcode":"11554",
    "sg:province":"NY",
    "sg:tags":[
        "dentist"
    ],
    "wof:name":"Dino W Insalaco DDS",
    "wof:placetype":"venue"
},
  "geometry": {"coordinates":[-73.55985099999999,40.714567],"type":"Point"}
}