{
  "type": "Feature",
  "properties": {
    "addr:full":"59 E 96 St New York NY 10128",
    "addr:housenumber":"59;96",
    "addr:postcode":"10128",
    "addr:street":"E;St",
    "iso:country":"US",
    "sg:address":"59 E 96 St",
    "sg:city":"New York",
    "sg:classifiers":[
        {
            "category":"Retail",
            "subcategory":"Repair Shop",
            "type":"Services"
        }
    ],
    "sg:phone":"+1 212 624 1391",
    "sg:postcode":"10128",
    "sg:province":"NY",
    "sg:tags":[
        "lock",
        "locksmith"
    ],
    "wof:name":"Emergency Locksmith",
    "wof:placetype":"venue"
},
  "geometry": {"coordinates":[-73.952759,40.78675],"type":"Point"}
}