{
  "type": "Feature",
  "properties": {
    "iso:country":"US",
    "sg:address":"853 Charlesgate Cir",
    "sg:city":"East Amherst",
    "sg:classifiers":[
        {
            "category":"Professional",
            "subcategory":"Business Services",
            "type":"Services"
        }
    ],
    "sg:phone":"+1 716 688 8173",
    "sg:postcode":"14051",
    "sg:province":"NY",
    "wof:name":"Sadoo Enterprises Inc",
    "wof:placetype":"venue"
},
  "geometry": {"coordinates":[-78.72265299999999,43.049657],"type":"Point"}
}