{
  "type": "Feature",
  "properties": {
    "iso:country":"US",
    "sg:address":"2303 Grand Ave Ste 200A",
    "sg:city":"Baldwin",
    "sg:classifiers":[
        {
            "category":"Banks & Credit Unions",
            "subcategory":"Financial Services",
            "type":"Services"
        }
    ],
    "sg:phone":"+1 516 377 2700",
    "sg:postcode":"11510",
    "sg:province":"NY",
    "sg:tags":[
        "mortgage"
    ],
    "sg:website":"http://www.ajmfunding.com",
    "wof:name":"Ajm Funding Corp",
    "wof:placetype":"venue"
},
  "geometry": {"coordinates":[-73.610384,40.654926],"type":"Point"}
}