{
  "type": "Feature",
  "properties": {
    "addr:full":"75 E Montauk Hwy Lindenhurst NY 11757",
    "addr:housenumber":"75",
    "addr:postcode":"11757",
    "addr:street":"E Montauk Hwy",
    "iso:country":"US",
    "sg:address":"75 E Montauk Hwy",
    "sg:city":"Lindenhurst",
    "sg:classifiers":[
        {
            "category":"Wholesale",
            "subcategory":"Construction Materials",
            "type":"Manufacturing & Wholesale Goods"
        },
        {
            "category":"Manufacturing",
            "subcategory":"Glass & Minerals",
            "type":"Manufacturing & Wholesale Goods"
        }
    ],
    "sg:phone":"+1 631 225 6360",
    "sg:postcode":"11757",
    "sg:province":"NY",
    "sg:tags":[
        "granite",
        "cut",
        "mfg"
    ],
    "wof:name":"Bari Granite & Marble Corp",
    "wof:placetype":"venue"
},
  "geometry": {"coordinates":[-73.361857,40.679151],"type":"Point"}
}