{
  "type": "Feature",
  "properties": {
    "addr:full":"99 W Main St Canajoharie NY 13317",
    "addr:housenumber":"99",
    "addr:postcode":"13317",
    "addr:street":"W Main St",
    "iso:country":"US",
    "sg:address":"99 W Main St",
    "sg:city":"Canajoharie",
    "sg:classifiers":[
        {
            "category":"Government",
            "subcategory":"Office",
            "type":"Public Place"
        }
    ],
    "sg:phone":"+1 518 673 5213",
    "sg:postcode":"13317",
    "sg:province":"NY",
    "sg:tags":[
        "state",
        "program"
    ],
    "wof:name":"New York Thruway Authority",
    "wof:placetype":"venue"
},
  "geometry": {"coordinates":[-74.573153,42.906117],"type":"Point"}
}