{
  "type": "Feature",
  "properties": {
    "addr:full":"729 Manhattan Ave Brooklyn NY 11222",
    "addr:housenumber":"729",
    "addr:postcode":"11222",
    "addr:street":"Manhattan Ave",
    "iso:country":"US",
    "sg:address":"729 Manhattan Ave",
    "sg:city":"Brooklyn",
    "sg:classifiers":[
        {
            "category":"Shopping",
            "subcategory":"Jewelry",
            "type":"Retail Goods"
        }
    ],
    "sg:phone":"+1 718 389 0006",
    "sg:postcode":"11222",
    "sg:province":"NY",
    "wof:name":"Greenpoint Jewelry",
    "wof:placetype":"venue"
},
  "geometry": {"coordinates":[-73.952296,40.726074],"type":"Point"}
}