{
  "type": "Feature",
  "properties": {
    "addr:full":"105 W Montauk Hwy Hampton Bays NY 11946",
    "addr:housenumber":"105",
    "addr:postcode":"11946",
    "addr:street":"W Montauk Hwy",
    "iso:country":"US",
    "sg:address":"105 W Montauk Hwy",
    "sg:city":"Hampton Bays",
    "sg:classifiers":[
        {
            "category":"Professional",
            "subcategory":"Computer Services",
            "type":"Services"
        }
    ],
    "sg:phone":"+1 631 728 1989",
    "sg:postcode":"11946",
    "sg:province":"NY",
    "sg:tags":[
        "repair"
    ],
    "wof:name":"My Computer Guy",
    "wof:placetype":"venue"
},
  "geometry": {"coordinates":[-72.53166899999999,40.876586],"type":"Point"}
}