{
  "type": "Feature",
  "properties": {
    "addr:full":"335 Central Ave Albany NY 12206",
    "addr:housenumber":"335",
    "addr:postcode":"12206",
    "addr:street":"Central Ave",
    "iso:country":"US",
    "sg:address":"335 Central Ave",
    "sg:city":"Albany",
    "sg:classifiers":[
        {
            "category":"Bars & Pubs",
            "type":"Food & Drink"
        }
    ],
    "sg:phone":"+1 518 463 9402",
    "sg:postcode":"12206",
    "sg:province":"NY",
    "sg:tags":[
        "tavern"
    ],
    "wof:name":"Cagney's Bar",
    "wof:placetype":"venue"
},
  "geometry": {"coordinates":[-73.773331,42.66552],"type":"Point"}
}