{
  "type": "Feature",
  "properties": {
    "addr:full":"1939 Wantagh Ave Wantagh NY 11793",
    "addr:housenumber":"1939",
    "addr:postcode":"11793",
    "addr:street":"Wantagh Ave",
    "iso:country":"US",
    "sg:address":"1939 Wantagh Ave",
    "sg:city":"Wantagh",
    "sg:classifiers":[
        {
            "category":"Restaurant",
            "type":"Food & Drink"
        }
    ],
    "sg:phone":"+1 516 785 9508",
    "sg:postcode":"11793",
    "sg:province":"NY",
    "sg:tags":[
        "delicatessen"
    ],
    "wof:name":"Beck's Delicatessen",
    "wof:placetype":"venue"
},
  "geometry": {"coordinates":[-73.510126,40.673598],"type":"Point"}
}