{
  "type": "Feature",
  "properties": {
    "addr:full":"53 E 23 St New York NY 10010",
    "addr:housenumber":"53;23",
    "addr:postcode":"10010",
    "addr:street":"E",
    "iso:country":"US",
    "sg:address":"53 E 23 St",
    "sg:city":"New York",
    "sg:classifiers":[
        {
            "category":"Organizations",
            "subcategory":"Religious Organization",
            "type":"Services"
        }
    ],
    "sg:phone":"+1 212 645 4048",
    "sg:postcode":"10010",
    "sg:province":"NY",
    "sg:tags":[
        "social",
        "welfare"
    ],
    "wof:name":"N C J W",
    "wof:placetype":"venue"
},
  "geometry": {"coordinates":[-73.987021,40.740639],"type":"Point"}
}