{
  "type": "Feature",
  "properties": {
    "iso:country":"US",
    "sg:address":"455 Center Rd Ste 1",
    "sg:city":"Buffalo",
    "sg:classifiers":[
        {
            "category":"Manufacturing",
            "subcategory":"Metals",
            "type":"Manufacturing & Wholesale Goods"
        },
        {
            "category":"Manufacturing",
            "subcategory":"Building Materials",
            "type":"Manufacturing & Wholesale Goods"
        }
    ],
    "sg:phone":"+1 716 712 0180",
    "sg:postcode":"14224",
    "sg:province":"NY",
    "sg:tags":[
        "product",
        "aluminum"
    ],
    "sg:website":"http://www.brunnerent.com",
    "wof:name":"Brunner Enterprises Inc",
    "wof:placetype":"venue"
},
  "geometry": {"coordinates":[-78.765801,42.83963],"type":"Point"}
}