{
  "type": "Feature",
  "properties": {
    "iso:country":"US",
    "sg:address":"5330 State Hwy 417",
    "sg:city":"Allegany",
    "sg:classifiers":[
        {
            "category":"Wholesale",
            "subcategory":"Vending Machines",
            "type":"Manufacturing & Wholesale Goods"
        }
    ],
    "sg:phone":"+1   ",
    "sg:postcode":"14706",
    "sg:province":"NY",
    "sg:tags":[
        "operator"
    ],
    "wof:name":"Hartburg Vending",
    "wof:placetype":"venue"
},
  "geometry": {"coordinates":[-78.601584,42.095556],"type":"Point"}
}