{
  "type": "Feature",
  "properties": {
    "iso:country":"US",
    "sg:address":"1 Old Mamaroneck Rd",
    "sg:city":"White Plains",
    "sg:classifiers":[
        {
            "category":"Health Services",
            "subcategory":"Doctor",
            "type":"Services"
        }
    ],
    "sg:phone":"+1 914 681 0300",
    "sg:postcode":"10605",
    "sg:province":"NY",
    "sg:tags":[
        "medical"
    ],
    "wof:name":"Steven B Kase MD PC",
    "wof:placetype":"venue"
},
  "geometry": {"coordinates":[-73.762168,41.02292],"type":"Point"}
}