{
  "type": "Feature",
  "properties": {
    "addr:full":"1316 Armer Rd Rock City Falls NY 12863",
    "addr:housenumber":"1316",
    "addr:postcode":"12863",
    "addr:street":"Armer Rd",
    "iso:country":"US",
    "sg:address":"1316 Armer Rd",
    "sg:city":"Rock City Falls",
    "sg:classifiers":[
        {
            "category":"Building & Trades",
            "subcategory":"Plumbing",
            "type":"Services"
        }
    ],
    "sg:phone":"+1 518 884 8301",
    "sg:postcode":"12863",
    "sg:province":"NY",
    "sg:tags":[
        "contractor"
    ],
    "wof:name":"Lisieski Rick & Pepper",
    "wof:placetype":"venue"
},
  "geometry": {"coordinates":[-73.93987799999999,43.059053],"type":"Point"}
}