{
  "type": "Feature",
  "properties": {
    "addr:full":"3065 Hamburg St Schenectady NY 12303",
    "addr:housenumber":"3065",
    "addr:postcode":"12303",
    "addr:street":"Hamburg St",
    "iso:country":"US",
    "sg:address":"3065 Hamburg St",
    "sg:city":"Schenectady",
    "sg:classifiers":[
        {
            "category":"Autos & Motor Vehicles",
            "subcategory":"Fuel & Gas Station",
            "type":"Retail Goods"
        }
    ],
    "sg:phone":"+1 518 355 1743",
    "sg:postcode":"12303",
    "sg:province":"NY",
    "sg:tags":[
        "oil"
    ],
    "wof:name":"Mobil On The Run",
    "wof:placetype":"venue"
},
  "geometry": {"coordinates":[-73.93803800000001,42.768026],"type":"Point"}
}