{
  "type": "Feature",
  "properties": {
    "iso:country":"US",
    "sg:address":"1816 Church Avenue",
    "sg:city":"Brooklyn",
    "sg:classifiers":[
        {
            "category":"Restaurant",
            "type":"Food & Drink"
        }
    ],
    "sg:phone":"+1 718 282 7020",
    "sg:postcode":"11226",
    "sg:province":"NY",
    "wof:name":"Don Carlos Restaurant",
    "wof:placetype":"venue"
},
  "geometry": {"coordinates":[-73.962475,40.649554],"type":"Point"}
}