{
  "type": "Feature",
  "properties": {
    "addr:full":"800 Community Dr Manhasset NY 11030",
    "addr:housenumber":"800",
    "addr:postcode":"11030",
    "addr:street":"Community Dr",
    "iso:country":"US",
    "sg:address":"800 Community Dr",
    "sg:city":"Manhasset",
    "sg:classifiers":[
        {
            "category":"Health Services",
            "subcategory":"Dentist",
            "type":"Services"
        }
    ],
    "sg:phone":"+1 516 869 9500",
    "sg:postcode":"11030",
    "sg:province":"NY",
    "wof:name":"Homer Mindy",
    "wof:placetype":"venue"
},
  "geometry": {"coordinates":[-73.703566,40.771855],"type":"Point"}
}