{
  "type": "Feature",
  "properties": {
    "addr:full":"595 Stewart Ave Garden City NY 11530",
    "addr:housenumber":"595",
    "addr:postcode":"11530",
    "addr:street":"Stewart Ave",
    "iso:country":"US",
    "sg:address":"595 Stewart Ave",
    "sg:city":"Garden City",
    "sg:classifiers":[
        {
            "category":"Professional",
            "subcategory":"Lawyer & Legal Services",
            "type":"Services"
        }
    ],
    "sg:phone":"+1 516 222 1500",
    "sg:postcode":"11530",
    "sg:province":"NY",
    "sg:website":"www.matrimonialcaselaw.com",
    "wof:name":"Matrimonial Caselaw Corp",
    "wof:placetype":"venue"
},
  "geometry": {"coordinates":[-73.6129,40.731499],"type":"Point"}
}