{
  "type": "Feature",
  "properties": {
    "iso:country":"US",
    "sg:address":"386 Oakwood Rd",
    "sg:city":"Huntington Sta",
    "sg:classifiers":[
        {
            "category":"Professional",
            "subcategory":"Management & Consulting",
            "type":"Services"
        }
    ],
    "sg:phone":"+1 631 425 7881",
    "sg:postcode":"11746",
    "sg:province":"NY",
    "sg:tags":[
        "consultant",
        "business"
    ],
    "wof:name":"Elite Manufacturing Group",
    "wof:placetype":"venue"
},
  "geometry": {"coordinates":[-73.42948199999999,40.839324],"type":"Point"}
}