{
  "type": "Feature",
  "properties": {
    "addr:full":"278 Vanderbilt Avenue Brooklyn NY 11205",
    "addr:housenumber":"278",
    "addr:postcode":"11205",
    "addr:street":"Vanderbilt Avenue",
    "iso:country":"US",
    "sg:address":"278 Vanderbilt Avenue",
    "sg:city":"Brooklyn",
    "sg:classifiers":[
        {
            "category":"Building & Trades",
            "subcategory":"Construction",
            "type":"Services"
        }
    ],
    "sg:phone":"+1 718 857 1011",
    "sg:postcode":"11205",
    "sg:province":"NY",
    "sg:tags":[
        "contractor"
    ],
    "wof:name":"North River Construction",
    "wof:placetype":"venue"
},
  "geometry": {"coordinates":[-73.96904499999999,40.688393],"type":"Point"}
}