{
  "type": "Feature",
  "properties": {
    "addr:full":"860 65th St Brooklyn NY 11220",
    "addr:housenumber":"860",
    "addr:postcode":"11220",
    "addr:street":"65Th St",
    "iso:country":"US",
    "sg:address":"860 65th St",
    "sg:city":"Brooklyn",
    "sg:classifiers":[
        {
            "category":"Building & Trades",
            "subcategory":"Plumbing",
            "type":"Services"
        }
    ],
    "sg:phone":"+1 718 799 5847",
    "sg:postcode":"11220",
    "sg:province":"NY",
    "wof:name":"United Plumbing & Heating",
    "wof:placetype":"venue"
},
  "geometry": {"coordinates":[-74.011101,40.631745],"type":"Point"}
}