{
  "type": "Feature",
  "properties": {
    "iso:country":"US",
    "sg:address":"365 Atlantic Ave",
    "sg:city":"Freeport",
    "sg:classifiers":[
        {
            "category":"Restaurant",
            "type":"Food & Drink"
        }
    ],
    "sg:menulink":"http://www.allmenus.com/ny/freeport/241328-la-via-pizzeria--caterers/menu/",
    "sg:phone":"+1 516 223 6770",
    "sg:postcode":"11520",
    "sg:province":"NY",
    "sg:tags":[
        "italian"
    ],
    "wof:name":"La Via Pizzeria & Caterers",
    "wof:placetype":"venue"
},
  "geometry": {"coordinates":[-73.59264,40.644717],"type":"Point"}
}