{
  "type": "Feature",
  "properties": {
    "iso:country":"US",
    "sg:address":"279 Falls Rd",
    "sg:city":"Hudson",
    "sg:classifiers":[
        {
            "category":"Freight",
            "type":"Transportation"
        }
    ],
    "sg:phone":"+1   ",
    "sg:postcode":"12534",
    "sg:province":"NY",
    "wof:name":"Babs Transport Inc",
    "wof:placetype":"venue"
},
  "geometry": {"coordinates":[-73.70553,42.330942],"type":"Point"}
}