{
  "type": "Feature",
  "properties": {
    "addr:full":"6 Clifford St Fairport NY 14450",
    "addr:housenumber":"6",
    "addr:postcode":"14450",
    "addr:street":"Clifford St",
    "iso:country":"US",
    "sg:address":"6 Clifford St",
    "sg:city":"Fairport",
    "sg:classifiers":[
        {
            "category":"Retail",
            "subcategory":"Animal Services",
            "type":"Services"
        }
    ],
    "sg:phone":"+1 585 377 5632",
    "sg:postcode":"14450",
    "sg:province":"NY",
    "wof:name":"Healing Hearts & Paws",
    "wof:placetype":"venue"
},
  "geometry": {"coordinates":[-77.451936,43.099833],"type":"Point"}
}