{
  "type": "Feature",
  "properties": {
    "iso:country":"US",
    "sg:address":"56 Roosevelt Ave",
    "sg:city":"Syosset",
    "sg:classifiers":[
        {
            "category":"Building & Trades",
            "subcategory":"Construction",
            "type":"Services"
        }
    ],
    "sg:phone":"+1 516 997 2455",
    "sg:postcode":"11791",
    "sg:province":"NY",
    "sg:tags":[
        "residential"
    ],
    "wof:name":"Louis Steall Inc",
    "wof:placetype":"venue"
},
  "geometry": {"coordinates":[-73.50411200000001,40.823972],"type":"Point"}
}