{
  "type": "Feature",
  "properties": {
    "addr:full":"242 Falcon Ave Patchogue NY 11772",
    "addr:housenumber":"242",
    "addr:postcode":"11772",
    "addr:street":"Falcon Ave",
    "iso:country":"US",
    "sg:address":"242 Falcon Ave",
    "sg:city":"Patchogue",
    "sg:classifiers":[
        {
            "category":"Building & Trades",
            "subcategory":"Plumbing",
            "type":"Services"
        }
    ],
    "sg:phone":"+1 631 654 1957",
    "sg:postcode":"11772",
    "sg:province":"NY",
    "sg:tags":[
        "plumber",
        "industrial",
        "contractors-commercial"
    ],
    "wof:name":"Martin Thomas Plumbing",
    "wof:placetype":"venue"
},
  "geometry": {"coordinates":[-73.00291900000001,40.774401],"type":"Point"}
}