{
  "type": "Feature",
  "properties": {
    "addr:full":"288 W 11 St New York NY 10014",
    "addr:housenumber":"288",
    "addr:postcode":"10014",
    "addr:street":"W 11 St",
    "iso:country":"US",
    "sg:address":"288 W 11 St",
    "sg:city":"New York",
    "sg:classifiers":[
        {
            "category":"Retail",
            "subcategory":"Repair Shop",
            "type":"Services"
        }
    ],
    "sg:phone":"+1 646 237 9691",
    "sg:postcode":"10014",
    "sg:province":"NY",
    "sg:tags":[
        "lock",
        "locksmith"
    ],
    "wof:name":"Accurate 24 Hours Emergency",
    "wof:placetype":"venue"
},
  "geometry": {"coordinates":[-74.00596,40.735845],"type":"Point"}
}