{
  "type": "Feature",
  "properties": {
    "iso:country":"US",
    "sg:address":"34 Devon Dr",
    "sg:city":"Orangeburg",
    "sg:classifiers":[
        {
            "category":"Retail",
            "subcategory":"Repair Shop",
            "type":"Services"
        }
    ],
    "sg:phone":"+1 845 359 1394",
    "sg:postcode":"10962",
    "sg:province":"NY",
    "sg:tags":[
        "television",
        "radio"
    ],
    "wof:name":"Marstan TV Co",
    "wof:placetype":"venue"
},
  "geometry": {"coordinates":[-73.956108,41.04838],"type":"Point"}
}