{
  "type": "Feature",
  "properties": {
    "addr:full":"715 Lexington Ave New York NY 10022",
    "addr:housenumber":"715",
    "addr:postcode":"10022",
    "addr:street":"Lexington Ave",
    "iso:country":"US",
    "sg:address":"715 Lexington Ave",
    "sg:city":"New York",
    "sg:classifiers":[
        {
            "category":"Utilities",
            "subcategory":"Mobile Phone",
            "type":"Services"
        }
    ],
    "sg:phone":"+1 646 840 4600",
    "sg:postcode":"10022",
    "sg:province":"NY",
    "sg:tags":[
        "telephone",
        "cellular"
    ],
    "wof:name":"Janney Montgomery Scott",
    "wof:placetype":"venue"
},
  "geometry": {"coordinates":[-73.968836,40.761094],"type":"Point"}
}