{
  "type": "Feature",
  "properties": {
    "addr:full":"120 Mountainview Ave Nyack NY 10960",
    "addr:housenumber":"120",
    "addr:postcode":"10960",
    "addr:street":"Mountainview Ave",
    "iso:country":"US",
    "sg:address":"120 Mountainview Ave",
    "sg:city":"Nyack",
    "sg:classifiers":[
        {
            "category":"Building & Trades",
            "subcategory":"Construction",
            "type":"Services"
        }
    ],
    "sg:phone":"+1 845 353 3867",
    "sg:postcode":"10960",
    "sg:province":"NY",
    "sg:tags":[
        "general",
        "contractor"
    ],
    "wof:name":"LA Bozz Design Builders Inc",
    "wof:placetype":"venue"
},
  "geometry": {"coordinates":[-73.936334,41.100215],"type":"Point"}
}