{
  "type": "Feature",
  "properties": {
    "iso:country":"US",
    "sg:address":"7 2nd Ave",
    "sg:city":"Auburn",
    "sg:classifiers":[
        {
            "category":"Shopping",
            "subcategory":"Used Merchandise",
            "type":"Retail Goods"
        }
    ],
    "sg:phone":"+1 315 252 9701",
    "sg:postcode":"13021",
    "sg:province":"NY",
    "sg:tags":[
        "antique"
    ],
    "wof:name":"Auburn Antiques",
    "wof:placetype":"venue"
},
  "geometry": {"coordinates":[-76.542877,42.921924],"type":"Point"}
}