{
  "type": "Feature",
  "properties": {
    "addr:full":"3792 Perry St Jefferson Valley NY 10535",
    "addr:housenumber":"3792",
    "addr:postcode":"10535",
    "addr:street":"Perry St",
    "iso:country":"US",
    "sg:address":"3792 Perry St",
    "sg:city":"Jefferson Valley",
    "sg:classifiers":[
        {
            "category":"Building & Trades",
            "subcategory":"Landscaping Services",
            "type":"Services"
        }
    ],
    "sg:phone":"+1 914 245 3189",
    "sg:postcode":"10535",
    "sg:province":"NY",
    "wof:name":"Brad Lewis Landscaping Inc",
    "wof:placetype":"venue"
},
  "geometry": {"coordinates":[-73.796921,41.339147],"type":"Point"}
}