{
  "type": "Feature",
  "properties": {
    "addr:full":"707 Brady Ave Bronx NY 10462",
    "addr:housenumber":"707",
    "addr:postcode":"10462",
    "addr:street":"Brady Ave",
    "iso:country":"US",
    "sg:address":"707 Brady Ave",
    "sg:city":"Bronx",
    "sg:classifiers":[
        {
            "category":"Recreation",
            "type":"Entertainment"
        }
    ],
    "sg:phone":"+1 718 828 5995",
    "sg:postcode":"10462",
    "sg:province":"NY",
    "sg:tags":[
        "martial art",
        "instruction"
    ],
    "sg:website":"http://www.ultimatestudioma.com",
    "wof:name":"Ultimate Studio Martial",
    "wof:placetype":"venue"
},
  "geometry": {"coordinates":[-73.867493,40.852404],"type":"Point"}
}