{
  "type": "Feature",
  "properties": {
    "addr:full":"206 Portion Rd Ronkonkoma NY 11779",
    "addr:housenumber":"206",
    "addr:postcode":"11779",
    "addr:street":"Portion Rd",
    "iso:country":"US",
    "sg:address":"206 Portion Rd",
    "sg:city":"Ronkonkoma",
    "sg:classifiers":[
        {
            "category":"Retail",
            "subcategory":"Auto Repair",
            "type":"Services"
        }
    ],
    "sg:phone":"+1 631 981 3457",
    "sg:postcode":"11779",
    "sg:province":"NY",
    "sg:tags":[
        "repairing",
        "automobile"
    ],
    "wof:name":"Hayes's Automotive Repair",
    "wof:placetype":"venue"
},
  "geometry": {"coordinates":[-73.104596,40.826749],"type":"Point"}
}