{
  "type": "Feature",
  "properties": {
    "iso:country":"US",
    "sg:address":"809 State Hwy 3",
    "sg:city":"Plattsburgh",
    "sg:classifiers":[
        {
            "category":"Food & Beverages",
            "subcategory":"Groceries & Convenience Stores",
            "type":"Retail Goods"
        }
    ],
    "sg:phone":"+1   ",
    "sg:postcode":"12901",
    "sg:province":"NY",
    "wof:name":"Stewarts",
    "wof:placetype":"venue"
},
  "geometry": {"coordinates":[-73.52302,44.695316],"type":"Point"}
}