{
  "type": "Feature",
  "properties": {
    "addr:full":"603 Jericho Tpke Huntington Sta NY 11746",
    "addr:housenumber":"603",
    "addr:postcode":"11746",
    "addr:street":"Jericho Tpke",
    "iso:country":"US",
    "sg:address":"603 Jericho Tpke",
    "sg:city":"Huntington Sta",
    "sg:classifiers":[
        {
            "category":"Shopping",
            "subcategory":"Clothing, Apparel, & Fashions",
            "type":"Retail Goods"
        }
    ],
    "sg:phone":"+1 631 421 7088",
    "sg:postcode":"11746",
    "sg:province":"NY",
    "sg:tags":[
        "infant",
        "wear"
    ],
    "wof:name":"Pretty Baby Of Westhill Inc",
    "wof:placetype":"venue"
},
  "geometry": {"coordinates":[-73.389696,40.832982],"type":"Point"}
}