{
  "type": "Feature",
  "properties": {
    "addr:full":"322 Washington Ave Oneida NY 13421",
    "addr:housenumber":"322",
    "addr:postcode":"13421",
    "addr:street":"Washington Ave",
    "iso:country":"US",
    "sg:address":"322 Washington Ave",
    "sg:city":"Oneida",
    "sg:classifiers":[
        {
            "category":"Retail",
            "subcategory":"Funeral Services",
            "type":"Services"
        }
    ],
    "sg:phone":"+1 315 363 2650",
    "sg:postcode":"13421",
    "sg:province":"NY",
    "sg:tags":[
        "director"
    ],
    "wof:name":"Coolican-Mc Sweeney Funeral",
    "wof:placetype":"venue"
},
  "geometry": {"coordinates":[-75.654833,43.091711],"type":"Point"}
}