{
  "type": "Feature",
  "properties": {
    "addr:full":"100 River Rock Dr Buffalo NY 14207",
    "addr:housenumber":"100",
    "addr:postcode":"14207",
    "addr:street":"River Rock Dr",
    "iso:country":"US",
    "sg:address":"100 River Rock Dr",
    "sg:city":"Buffalo",
    "sg:classifiers":[
        {
            "category":"Real Estate",
            "subcategory":"Real Estate Agent",
            "type":"Services"
        }
    ],
    "sg:phone":"+1 716 873 6928",
    "sg:postcode":"14207",
    "sg:province":"NY",
    "wof:name":"Can-AM Building",
    "wof:placetype":"venue"
},
  "geometry": {"coordinates":[-78.898414,42.945346],"type":"Point"}
}