{
  "type": "Feature",
  "properties": {
    "iso:country":"US",
    "sg:address":"115 W 27 St",
    "sg:city":"New York",
    "sg:classifiers":[
        {
            "category":"Manufacturing",
            "subcategory":"Metals",
            "type":"Manufacturing & Wholesale Goods"
        }
    ],
    "sg:phone":"+1   ",
    "sg:postcode":"10001",
    "sg:province":"NY",
    "wof:name":"Dan Kane Plating Co Inc",
    "wof:placetype":"venue"
},
  "geometry": {"coordinates":[-73.993396,40.746472],"type":"Point"}
}