{
  "type": "Feature",
  "properties": {
    "iso:country":"US",
    "sg:address":"1475 New York Ave",
    "sg:city":"Huntington Sta",
    "sg:classifiers":[
        {
            "category":"Travel",
            "subcategory":"Travel Agent",
            "type":"Entertainment"
        }
    ],
    "sg:phone":"+1 631 423 5096",
    "sg:postcode":"11746",
    "sg:province":"NY",
    "sg:tags":[
        "agency",
        "bureau"
    ],
    "wof:name":"Jimmy Travel Svc",
    "wof:placetype":"venue"
},
  "geometry": {"coordinates":[-73.411591,40.848158],"type":"Point"}
}