{
  "type": "Feature",
  "properties": {
    "addr:full":"13354 41st Avenue Flushing NY 11355",
    "addr:housenumber":"13354",
    "addr:postcode":"11355",
    "addr:street":"41St Avenue",
    "iso:country":"US",
    "sg:address":"13354 41st Avenue",
    "sg:city":"Flushing",
    "sg:classifiers":[
        {
            "category":"Health Services",
            "subcategory":"Doctor",
            "type":"Services"
        }
    ],
    "sg:phone":"+1 718 670 0006",
    "sg:postcode":"11355",
    "sg:province":"NY",
    "wof:name":"New York Otolaryngology",
    "wof:placetype":"venue"
},
  "geometry": {"coordinates":[-73.830536,40.757729],"type":"Point"}
}