{
  "type": "Feature",
  "properties": {
    "iso:country":"US",
    "sg:address":"607 Founders Path",
    "sg:city":"Calverton",
    "sg:classifiers":[
        {
            "category":"Professional",
            "subcategory":"Business Services",
            "type":"Services"
        }
    ],
    "sg:phone":"+1 631 369 8394",
    "sg:postcode":"11933",
    "sg:province":"NY",
    "sg:tags":[
        "auctioneer"
    ],
    "wof:name":"C & S Liquidators Auctioneers",
    "wof:placetype":"venue"
},
  "geometry": {"coordinates":[-72.763487,40.964017],"type":"Point"}
}