{
  "type": "Feature",
  "properties": {
    "addr:full":"4549 Utopia Pkwy Flushing NY 11358",
    "addr:housenumber":"4549",
    "addr:postcode":"11358",
    "addr:street":"Utopia Pkwy",
    "iso:country":"US",
    "sg:address":"4549 Utopia Pkwy",
    "sg:city":"Flushing",
    "sg:classifiers":[
        {
            "category":"Professional",
            "subcategory":"Advertising",
            "type":"Services"
        }
    ],
    "sg:phone":"+1 718 358 4512",
    "sg:postcode":"11358",
    "sg:province":"NY",
    "sg:tags":[
        "promotion",
        "sale"
    ],
    "wof:name":"A C B Services Inc",
    "wof:placetype":"venue"
},
  "geometry": {"coordinates":[-73.792615,40.75518],"type":"Point"}
}