{
  "type": "Feature",
  "properties": {
    "addr:full":"204 W 4th Street New York NY 10014",
    "addr:housenumber":"204",
    "addr:postcode":"10014",
    "addr:street":"W 4Th Street",
    "iso:country":"US",
    "sg:address":"204 W 4th Street",
    "sg:city":"New York",
    "sg:classifiers":[
        {
            "category":"Banks & Credit Unions",
            "subcategory":"Bank",
            "type":"Services"
        }
    ],
    "sg:phone":"+1 212 935 9935",
    "sg:postcode":"10014",
    "sg:province":"NY",
    "wof:name":"Chase Manhattan Bank",
    "wof:placetype":"venue"
},
  "geometry": {"coordinates":[-74.00247899999999,40.733476],"type":"Point"}
}