{
  "type": "Feature",
  "properties": {
    "iso:country":"US",
    "sg:address":"125 Carbide Rd",
    "sg:city":"Plattsburgh",
    "sg:classifiers":[
        {
            "category":"Shopping",
            "subcategory":"Crafts & Fabrics",
            "type":"Retail Goods"
        }
    ],
    "sg:phone":"+1   ",
    "sg:postcode":"12901",
    "sg:province":"NY",
    "sg:tags":[
        "sewing"
    ],
    "wof:name":"Needle & Thread Creations",
    "wof:placetype":"venue"
},
  "geometry": {"coordinates":[-73.502836,44.666328],"type":"Point"}
}