{
  "type": "Feature",
  "properties": {
    "iso:country":"US",
    "sg:address":"533 Canal St",
    "sg:city":"New York",
    "sg:classifiers":[
        {
            "category":"Arts & Performance",
            "subcategory":"Theater",
            "type":"Entertainment"
        },
        {
            "category":"Manufacturing",
            "subcategory":"Tools & Machinery",
            "type":"Manufacturing & Wholesale Goods"
        }
    ],
    "sg:phone":"+1 212 226 0925",
    "sg:postcode":"10013",
    "sg:province":"NY",
    "sg:tags":[
        "equipment",
        "lighting",
        "rent",
        "stage"
    ],
    "sg:website":"www.balny.com",
    "wof:name":"Big Apple Lights Corp",
    "wof:placetype":"venue"
},
  "geometry": {"coordinates":[-74.00976199999999,40.725024],"type":"Point"}
}