{
  "type": "Feature",
  "properties": {
    "addr:full":"19 Forman St Cazenovia NY 13035",
    "addr:housenumber":"19",
    "addr:postcode":"13035",
    "addr:street":"Forman St",
    "iso:country":"US",
    "sg:address":"19 Forman St",
    "sg:city":"Cazenovia",
    "sg:classifiers":[
        {
            "category":"Professional",
            "subcategory":"Business Services",
            "type":"Services"
        }
    ],
    "sg:phone":"+1 315 655 5999",
    "sg:postcode":"13035",
    "sg:province":"NY",
    "wof:name":"Good Sight-Herrmann Inc",
    "wof:placetype":"venue"
},
  "geometry": {"coordinates":[-75.859341,42.928213],"type":"Point"}
}