{
  "type": "Feature",
  "properties": {
    "addr:full":"955 Pennsylvania Ave Brooklyn NY 11207",
    "addr:housenumber":"955",
    "addr:postcode":"11207",
    "addr:street":"Pennsylvania Ave",
    "iso:country":"US",
    "sg:address":"955 Pennsylvania Ave",
    "sg:city":"Brooklyn",
    "sg:classifiers":[
        {
            "category":"Health Services",
            "subcategory":"Doctor",
            "type":"Services"
        }
    ],
    "sg:phone":"+1 718 272 8300",
    "sg:postcode":"11207",
    "sg:province":"NY",
    "sg:tags":[
        "dentist"
    ],
    "wof:name":"Oral Surgery",
    "wof:placetype":"venue"
},
  "geometry": {"coordinates":[-73.88736400000001,40.654387],"type":"Point"}
}