{
  "type": "Feature",
  "properties": {
    "iso:country":"US",
    "sg:address":"1017 Smith St",
    "sg:city":"Buffalo",
    "sg:classifiers":[
        {
            "category":"Real Estate",
            "subcategory":"Real Estate Services",
            "type":"Services"
        }
    ],
    "sg:phone":"+1 716 853 0058",
    "sg:postcode":"14212",
    "sg:province":"NY",
    "sg:tags":[
        "abstract",
        "title"
    ],
    "wof:name":"Community Quick Deeds Finder",
    "wof:placetype":"venue"
},
  "geometry": {"coordinates":[-78.843931,42.888358],"type":"Point"}
}