{
  "type": "Feature",
  "properties": {
    "addr:full":"214 1st Ave Manhattan NY 10009",
    "addr:housenumber":"214",
    "addr:postcode":"10009",
    "addr:street":"1St Ave",
    "iso:country":"US",
    "sg:address":"214 1st Ave",
    "sg:city":"Manhattan",
    "sg:classifiers":[
        {
            "category":"Restaurant",
            "type":"Food & Drink"
        },
        {
            "category":"Professional",
            "subcategory":"Business Services",
            "type":"Services"
        }
    ],
    "sg:phone":"+1 212 533 3030",
    "sg:postcode":"10009",
    "sg:province":"NY",
    "sg:tags":[
        "delivery",
        "sushi",
        "bar",
        "japanese"
    ],
    "wof:name":"Kumo Sushi",
    "wof:placetype":"venue"
},
  "geometry": {"coordinates":[-73.982879,40.730414],"type":"Point"}
}