{
  "type": "Feature",
  "properties": {
    "iso:country":"US",
    "sg:address":"40 Slayton Ave",
    "sg:city":"Spencerport",
    "sg:classifiers":[
        {
            "category":"Wholesale",
            "subcategory":"Office Equipment",
            "type":"Manufacturing & Wholesale Goods"
        },
        {
            "category":"Professional",
            "subcategory":"Printing & Photocopies",
            "type":"Services"
        },
        {
            "category":"Shopping",
            "subcategory":"Computers & Home Electronics",
            "type":"Retail Goods"
        }
    ],
    "sg:phone":"+1 585 349 0955",
    "sg:postcode":"14559",
    "sg:province":"NY",
    "sg:tags":[
        "scanning",
        "printer",
        "services-commercial",
        "plotting",
        "supply"
    ],
    "wof:name":"Cdl Printing",
    "wof:placetype":"venue"
},
  "geometry": {"coordinates":[-77.799201,43.190824],"type":"Point"}
}