{
  "type": "Feature",
  "properties": {
    "iso:country":"US",
    "sg:address":"247 Broadway St",
    "sg:city":"Fort Edward",
    "sg:classifiers":[
        {
            "category":"Shopping",
            "subcategory":"Discount & Variety Stores",
            "type":"Retail Goods"
        }
    ],
    "sg:phone":"+1 518 747 6065",
    "sg:postcode":"12828",
    "sg:province":"NY",
    "wof:name":"Adirondack Dollar",
    "wof:placetype":"venue"
},
  "geometry": {"coordinates":[-73.586456,43.275361],"type":"Point"}
}