{
  "type": "Feature",
  "properties": {
    "addr:full":"189 Sherman Ave New York NY 10034",
    "addr:housenumber":"189",
    "addr:postcode":"10034",
    "addr:street":"Sherman Ave",
    "iso:country":"US",
    "sg:address":"189 Sherman Ave",
    "sg:city":"New York",
    "sg:classifiers":[
        {
            "category":"Wholesale",
            "subcategory":"Apparel",
            "type":"Manufacturing & Wholesale Goods"
        }
    ],
    "sg:phone":"+1 212 544 2065",
    "sg:postcode":"10034",
    "sg:province":"NY",
    "sg:tags":[
        "infant",
        "wear"
    ],
    "wof:name":"Lil' Ones Fashions",
    "wof:placetype":"venue"
},
  "geometry": {"coordinates":[-73.919996,40.865797],"type":"Point"}
}