{
  "type": "Feature",
  "properties": {
    "addr:full":"1133 New Loudon Rd Cohoes NY 12047",
    "addr:housenumber":"1133",
    "addr:postcode":"12047",
    "addr:street":"New Loudon Rd",
    "iso:country":"US",
    "sg:address":"1133 New Loudon Rd",
    "sg:city":"Cohoes",
    "sg:classifiers":[
        {
            "category":"Travel",
            "subcategory":"Hotels & Motels",
            "type":"Entertainment"
        }
    ],
    "sg:phone":"+1 518 785 8818",
    "sg:postcode":"12047",
    "sg:province":"NY",
    "wof:name":"Karl's Motel & Efficiency Apts",
    "wof:placetype":"venue"
},
  "geometry": {"coordinates":[-73.74419,42.783437],"type":"Point"}
}