{
  "type": "Feature",
  "properties": {
    "addr:full":"16 Seminary Hill Rd Carmel NY 10512",
    "addr:housenumber":"16",
    "addr:postcode":"10512",
    "addr:street":"Seminary Hill Rd",
    "iso:country":"US",
    "sg:address":"16 Seminary Hill Rd",
    "sg:city":"Carmel",
    "sg:classifiers":[
        {
            "category":"Restaurant",
            "type":"Food & Drink"
        }
    ],
    "sg:phone":"+1 845 228 2759",
    "sg:postcode":"10512",
    "sg:province":"NY",
    "sg:tags":[
        "cafe",
        "eating"
    ],
    "wof:name":"Magnolia's Cafe",
    "wof:placetype":"venue"
},
  "geometry": {"coordinates":[-73.67859900000001,41.420384],"type":"Point"}
}