{
  "type": "Feature",
  "properties": {
    "addr:full":"909 W Beech St Long Beach NY 11561",
    "addr:housenumber":"909",
    "addr:postcode":"11561",
    "addr:street":"W Beech St",
    "iso:country":"US",
    "sg:address":"909 W Beech St",
    "sg:city":"Long Beach",
    "sg:classifiers":[
        {
            "category":"Restaurant",
            "type":"Food & Drink"
        }
    ],
    "sg:phone":"+1 516 431 3464",
    "sg:postcode":"11561",
    "sg:province":"NY",
    "sg:tags":[
        "barbeque"
    ],
    "sg:website":"www.swingbellysbbq.com",
    "wof:name":"Swingbelly's",
    "wof:placetype":"venue"
},
  "geometry": {"coordinates":[-73.69124600000001,40.586034],"type":"Point"}
}