{
  "type": "Feature",
  "properties": {
    "iso:country":"US",
    "sg:address":"360 Knickerbocker Ave",
    "sg:city":"Bohemia",
    "sg:classifiers":[
        {
            "category":"Manufacturing",
            "subcategory":"Metals",
            "type":"Manufacturing & Wholesale Goods"
        }
    ],
    "sg:phone":"+1   ",
    "sg:postcode":"11716",
    "sg:province":"NY",
    "sg:tags":[
        "blast",
        "furnace",
        "business",
        "works"
    ],
    "wof:name":"Thomas Heinlein Tool & Die",
    "wof:placetype":"venue"
},
  "geometry": {"coordinates":[-73.087838,40.780992],"type":"Point"}
}