{
  "type": "Feature",
  "properties": {
    "addr:full":"1105 60th Street NY Brooklyn NY 11219",
    "addr:housenumber":"1105",
    "addr:postcode":"11219",
    "addr:street":"60Th Street",
    "iso:country":"US",
    "sg:address":"1105 60th Street NY",
    "sg:city":"Brooklyn",
    "sg:classifiers":[
        {
            "category":"Autos & Motor Vehicles",
            "subcategory":"Fuel & Gas Station",
            "type":"Retail Goods"
        }
    ],
    "sg:phone":"+1 718 686 7783",
    "sg:postcode":"11219",
    "sg:province":"NY",
    "wof:name":"BP Gas Station",
    "wof:placetype":"venue"
},
  "geometry": {"coordinates":[-74.002456,40.631525],"type":"Point"}
}