{
  "type": "Feature",
  "properties": {
    "iso:country":"US",
    "sg:address":"146 Delaware St",
    "sg:city":"Walton",
    "sg:classifiers":[
        {
            "category":"Shopping",
            "subcategory":"Clothing, Apparel, & Fashions",
            "type":"Retail Goods"
        }
    ],
    "sg:phone":"+1 607 865 4302",
    "sg:postcode":"13856",
    "sg:province":"NY",
    "wof:name":"Webb's Clothing",
    "wof:placetype":"venue"
},
  "geometry": {"coordinates":[-75.130157,42.168107],"type":"Point"}
}