{
  "type": "Feature",
  "properties": {
    "iso:country":"US",
    "sg:address":"82 Roslyn Ave",
    "sg:city":"Sea Cliff",
    "sg:classifiers":[
        {
            "category":"Food & Beverages",
            "subcategory":"Groceries & Convenience Stores",
            "type":"Retail Goods"
        }
    ],
    "sg:phone":"+1   ",
    "sg:postcode":"11579",
    "sg:province":"NY",
    "sg:tags":[
        "delicatessen"
    ],
    "wof:name":"Mc Carthys Deli",
    "wof:placetype":"venue"
},
  "geometry": {"coordinates":[-73.64489399999999,40.848377],"type":"Point"}
}