{
  "type": "Feature",
  "properties": {
    "addr:full":"2115 Batchelder St Brooklyn NY 11229",
    "addr:housenumber":"2115",
    "addr:postcode":"11229",
    "addr:street":"Batchelder St",
    "iso:country":"US",
    "sg:address":"2115 Batchelder St",
    "sg:city":"Brooklyn",
    "sg:classifiers":[
        {
            "category":"Organizations",
            "subcategory":"Religious Organization",
            "type":"Services"
        }
    ],
    "sg:phone":"+1 718 891 5709",
    "sg:postcode":"11229",
    "sg:province":"NY",
    "sg:tags":[
        "clergy"
    ],
    "wof:name":"Dov Chechik",
    "wof:placetype":"venue"
},
  "geometry": {"coordinates":[-73.938607,40.598924],"type":"Point"}
}