{
  "type": "Feature",
  "properties": {
    "iso:country":"US",
    "sg:address":"350 Madison Ave 12th Floor",
    "sg:city":"New York",
    "sg:classifiers":[
        {
            "category":"Communications",
            "subcategory":"Newspaper",
            "type":"Services"
        },
        {
            "category":"Communications",
            "type":"Services"
        }
    ],
    "sg:phone":"+1 212 490 4644",
    "sg:postcode":"10017",
    "sg:province":"NY",
    "sg:tags":[
        "web",
        "design",
        "advertising"
    ],
    "sg:website":"www.digitalmediainsights.com",
    "wof:name":"Digital Media Insights, Inc.",
    "wof:placetype":"venue"
},
  "geometry": {"coordinates":[-73.978094,40.75445],"type":"Point"}
}