{
  "type": "Feature",
  "properties": {
    "addr:full":"957 E 218th St Bronx NY 10469",
    "addr:housenumber":"957",
    "addr:postcode":"10469",
    "addr:street":"E 218Th St",
    "iso:country":"US",
    "sg:address":"957 E 218th St",
    "sg:city":"Bronx",
    "sg:classifiers":[
        {
            "category":"Real Estate",
            "subcategory":"Real Estate Agent",
            "type":"Services"
        }
    ],
    "sg:phone":"+1 718 519 1744",
    "sg:postcode":"10469",
    "sg:province":"NY",
    "wof:name":"Acres Realty & Management Inc",
    "wof:placetype":"venue"
},
  "geometry": {"coordinates":[-73.855991,40.880768],"type":"Point"}
}