{
  "type": "Feature",
  "properties": {
    "addr:full":"1638 Broadway Manhattan NY 10019",
    "addr:housenumber":"1638",
    "addr:postcode":"10019",
    "addr:street":"Broadway",
    "iso:country":"US",
    "sg:address":"1638 Broadway",
    "sg:city":"Manhattan",
    "sg:classifiers":[
        {
            "category":"Food & Beverages",
            "subcategory":"Specialty",
            "type":"Retail Goods"
        },
        {
            "category":"Shopping",
            "subcategory":"Gifts & Souvenirs",
            "type":"Retail Goods"
        }
    ],
    "sg:phone":"+1 212 582 5996",
    "sg:postcode":"10019",
    "sg:province":"NY",
    "sg:tags":[
        "theater",
        "flower",
        "oriental",
        "memorabilia"
    ],
    "wof:name":"Backstage Memories",
    "wof:placetype":"venue"
},
  "geometry": {"coordinates":[-73.983822,40.761737],"type":"Point"}
}