{
  "type": "Feature",
  "properties": {
    "addr:full":"217 Prospect Park W Brooklyn NY 11215",
    "addr:housenumber":"217",
    "addr:postcode":"11215",
    "addr:street":"Prospect Park W",
    "iso:country":"US",
    "sg:address":"217 Prospect Park W",
    "sg:city":"Brooklyn",
    "sg:classifiers":[
        {
            "category":"Restaurant",
            "type":"Food & Drink"
        }
    ],
    "sg:phone":"+1 718 499 3150",
    "sg:postcode":"11215",
    "sg:province":"NY",
    "sg:tags":[
        "house",
        "steak",
        "pizza",
        "barbecue"
    ],
    "wof:name":"Enzo's Brickoven",
    "wof:placetype":"venue"
},
  "geometry": {"coordinates":[-73.98042599999999,40.660324],"type":"Point"}
}