{
  "type": "Feature",
  "properties": {
    "addr:full":"1794 Sheepshead Bay Rd Brooklyn NY 11235",
    "addr:housenumber":"1794",
    "addr:postcode":"11235",
    "addr:street":"Sheepshead Bay Rd",
    "iso:country":"US",
    "sg:address":"1794 Sheepshead Bay Rd",
    "sg:city":"Brooklyn",
    "sg:classifiers":[
        {
            "category":"Shopping",
            "subcategory":"Pharmacy",
            "type":"Retail Goods"
        }
    ],
    "sg:phone":"+1 718 646 3030",
    "sg:postcode":"11235",
    "sg:province":"NY",
    "wof:name":"Care Beach Pharmacy",
    "wof:placetype":"venue"
},
  "geometry": {"coordinates":[-73.95034800000001,40.583302],"type":"Point"}
}