{
  "type": "Feature",
  "properties": {
    "iso:country":"US",
    "sg:address":"745 Heim Rd",
    "sg:city":"Getzville",
    "sg:classifiers":[
        {
            "category":"Wholesale",
            "subcategory":"Construction Materials",
            "type":"Manufacturing & Wholesale Goods"
        }
    ],
    "sg:phone":"+1 716 568 1013",
    "sg:postcode":"14068",
    "sg:province":"NY",
    "sg:tags":[
        "mosaic"
    ],
    "wof:name":"Muslim Community Ctr",
    "wof:placetype":"venue"
},
  "geometry": {"coordinates":[-78.743554,43.021498],"type":"Point"}
}