{
  "type": "Feature",
  "properties": {
    "addr:full":"76 W Hill Rd New Lebanon NY 12125",
    "addr:housenumber":"76",
    "addr:postcode":"12125",
    "addr:street":"W Hill Rd",
    "iso:country":"US",
    "sg:address":"76 W Hill Rd",
    "sg:city":"New Lebanon",
    "sg:classifiers":[
        {
            "category":"Farming",
            "subcategory":"Dairy Farm",
            "type":"Manufacturing & Wholesale Goods"
        }
    ],
    "sg:phone":"+1 518 794 8069",
    "sg:postcode":"12125",
    "sg:province":"NY",
    "wof:name":"Scott Carson",
    "wof:placetype":"venue"
},
  "geometry": {"coordinates":[-73.414,42.477687],"type":"Point"}
}