{
  "type": "Feature",
  "properties": {
    "addr:full":"457 Fdr Dr New York NY 10002",
    "addr:housenumber":"457",
    "addr:postcode":"10002",
    "addr:street":"Fdr Dr",
    "iso:country":"US",
    "sg:address":"457 Fdr Dr",
    "sg:city":"New York",
    "sg:classifiers":[
        {
            "category":"Freight",
            "type":"Transportation"
        }
    ],
    "sg:phone":"+1   ",
    "sg:postcode":"10002",
    "sg:province":"NY",
    "sg:tags":[
        "operator",
        "local",
        "trucking"
    ],
    "wof:name":"Ghost Rider Services",
    "wof:placetype":"venue"
},
  "geometry": {"coordinates":[-73.97783,40.712828],"type":"Point"}
}