{
  "type": "Feature",
  "properties": {
    "addr:full":"637 E 6 St New York NY 10009",
    "addr:housenumber":"637;6",
    "addr:postcode":"10009",
    "addr:street":"E",
    "iso:country":"US",
    "sg:address":"637 E 6 St",
    "sg:city":"New York",
    "sg:classifiers":[
        {
            "category":"Professional",
            "subcategory":"Art Services",
            "type":"Services"
        }
    ],
    "sg:phone":"+1 212 228 5552",
    "sg:postcode":"10009",
    "sg:province":"NY",
    "sg:tags":[
        "graphic",
        "designer"
    ],
    "wof:name":"Art Department Creative Svc",
    "wof:placetype":"venue"
},
  "geometry": {"coordinates":[-73.9799,40.723933],"type":"Point"}
}