{
  "type": "Feature",
  "properties": {
    "iso:country":"US",
    "sg:address":"581 Merrick Rd",
    "sg:city":"Lynbrook",
    "sg:classifiers":[
        {
            "category":"Wholesale",
            "subcategory":"Home Furnishings",
            "type":"Manufacturing & Wholesale Goods"
        }
    ],
    "sg:phone":"+1 516 887 0100",
    "sg:postcode":"11563",
    "sg:province":"NY",
    "sg:tags":[
        "merchandise"
    ],
    "wof:name":"S & R Keystone Corp",
    "wof:placetype":"venue"
},
  "geometry": {"coordinates":[-73.68297099999999,40.660392],"type":"Point"}
}