{
  "type": "Feature",
  "properties": {
    "addr:full":"5981 Seneca St Elma NY 14059",
    "addr:housenumber":"5981",
    "addr:postcode":"14059",
    "addr:street":"Seneca St",
    "iso:country":"US",
    "sg:address":"5981 Seneca St",
    "sg:city":"Elma",
    "sg:classifiers":[
        {
            "category":"Building & Trades",
            "subcategory":"Construction",
            "type":"Services"
        }
    ],
    "sg:phone":"+1 716 674 6910",
    "sg:postcode":"14059",
    "sg:province":"NY",
    "sg:tags":[
        "house"
    ],
    "wof:name":"TLC Home Improvements",
    "wof:placetype":"venue"
},
  "geometry": {"coordinates":[-78.684669,42.823396],"type":"Point"}
}