{
  "type": "Feature",
  "properties": {
    "iso:country":"US",
    "sg:address":"275 Lakeville Rd",
    "sg:city":"Great Neck",
    "sg:classifiers":[
        {
            "category":"Social Services",
            "subcategory":"Child Care",
            "type":"Services"
        },
        {
            "category":"Education",
            "subcategory":"Preschool",
            "type":"Public Place"
        },
        {
            "category":"Education",
            "subcategory":"School",
            "type":"Public Place"
        }
    ],
    "sg:phone":"+1 516 466 8906",
    "sg:postcode":"11020",
    "sg:province":"NY",
    "sg:tags":[
        "elementary",
        "day"
    ],
    "sg:website":"www.romperroomschool.com",
    "wof:name":"Romper Room Nursery School",
    "wof:placetype":"venue"
},
  "geometry": {"coordinates":[-73.711304,40.772701],"type":"Point"}
}