{
  "type": "Feature",
  "properties": {
    "iso:country":"US",
    "sg:address":"49 N Main St",
    "sg:city":"Manchester",
    "sg:classifiers":[
        {
            "category":"Manufacturing",
            "subcategory":"Paper Products",
            "type":"Manufacturing & Wholesale Goods"
        }
    ],
    "sg:phone":"+1 716 298 4822",
    "sg:postcode":"14504",
    "sg:province":"NY",
    "sg:tags":[
        "box"
    ],
    "wof:name":"A B Cowles Co Inc",
    "wof:placetype":"venue"
},
  "geometry": {"coordinates":[-77.229321,42.973648],"type":"Point"}
}