{
  "type": "Feature",
  "properties": {
    "addr:full":"306 W 93 St New York NY 10025",
    "addr:housenumber":"306",
    "addr:postcode":"10025",
    "addr:street":"W 93 St",
    "iso:country":"US",
    "sg:address":"306 W 93 St",
    "sg:city":"New York",
    "sg:classifiers":[
        {
            "category":"Professional",
            "subcategory":"Art Services",
            "type":"Services"
        }
    ],
    "sg:phone":"+1   ",
    "sg:postcode":"10025",
    "sg:province":"NY",
    "sg:tags":[
        "commercial",
        "design"
    ],
    "wof:name":"Kantrameyer",
    "wof:placetype":"venue"
},
  "geometry": {"coordinates":[-73.976264,40.793923],"type":"Point"}
}