{
  "type": "Feature",
  "properties": {
    "addr:full":"152 E 23 St New York NY 10010",
    "addr:housenumber":"152;23",
    "addr:postcode":"10010",
    "addr:street":"E",
    "iso:country":"US",
    "sg:address":"152 E 23 St",
    "sg:city":"New York",
    "sg:classifiers":[
        {
            "category":"Real Estate",
            "subcategory":"Real Estate Agent",
            "type":"Services"
        }
    ],
    "sg:phone":"+1 212 982 2244",
    "sg:postcode":"10010",
    "sg:province":"NY",
    "wof:name":"Bleru Realty Corp",
    "wof:placetype":"venue"
},
  "geometry": {"coordinates":[-73.983525,40.738955],"type":"Point"}
}