{
  "type": "Feature",
  "properties": {
    "iso:country":"US",
    "sg:address":"224 Tremaine Ave",
    "sg:city":"Kenmore",
    "sg:classifiers":[
        {
            "category":"Personal",
            "subcategory":"Beauty Salon",
            "type":"Services"
        }
    ],
    "sg:phone":"+1 716 871 1825",
    "sg:postcode":"14217",
    "sg:province":"NY",
    "sg:tags":[
        "shop"
    ],
    "wof:name":"Dantonio's Salon For Hair",
    "wof:placetype":"venue"
},
  "geometry": {"coordinates":[-78.87526699999999,42.960113],"type":"Point"}
}