{
  "type": "Feature",
  "properties": {
    "addr:full":"82 Vineyard Ave Highland NY 12528",
    "addr:housenumber":"82",
    "addr:postcode":"12528",
    "addr:street":"Vineyard Ave",
    "iso:country":"US",
    "sg:address":"82 Vineyard Ave",
    "sg:city":"Highland",
    "sg:classifiers":[
        {
            "category":"Insurance",
            "subcategory":"Insurance Agent",
            "type":"Services"
        }
    ],
    "sg:phone":"+1 845 566 5203",
    "sg:postcode":"12528",
    "sg:province":"NY",
    "wof:name":"Fox Insurance",
    "wof:placetype":"venue"
},
  "geometry": {"coordinates":[-73.964367,41.71889],"type":"Point"}
}