{
  "type": "Feature",
  "properties": {
    "iso:country":"US",
    "sg:address":"135 Reed Ave",
    "sg:city":"Syracuse",
    "sg:classifiers":[
        {
            "category":"Social Services",
            "subcategory":"Child Care",
            "type":"Services"
        }
    ],
    "sg:phone":"+1 315 476 9080",
    "sg:postcode":"13207",
    "sg:province":"NY",
    "wof:name":"Chavon's Daycare",
    "wof:placetype":"venue"
},
  "geometry": {"coordinates":[-76.181555,43.030803],"type":"Point"}
}