{
  "type": "Feature",
  "properties": {
    "addr:full":"733 Grand St Brooklyn NY 11211",
    "addr:housenumber":"733",
    "addr:postcode":"11211",
    "addr:street":"Grand St",
    "iso:country":"US",
    "sg:address":"733 Grand St",
    "sg:city":"Brooklyn",
    "sg:phone":"+1 718 599 8882",
    "sg:postcode":"11211",
    "sg:province":"NY",
    "sg:tags":[
        "equipment",
        "commercial"
    ],
    "wof:name":"J&B Restaurant Supply",
    "wof:placetype":"venue"
},
  "geometry": {"coordinates":[-73.942459,40.711848],"type":"Point"}
}