{
  "type": "Feature",
  "properties": {
    "addr:full":"2635 Genesee St Utica NY 13501",
    "addr:housenumber":"2635",
    "addr:postcode":"13501",
    "addr:street":"Genesee St",
    "iso:country":"US",
    "sg:address":"2635 Genesee St",
    "sg:city":"Utica",
    "sg:classifiers":[
        {
            "category":"Professional",
            "subcategory":"Lawyer & Legal Services",
            "type":"Services"
        }
    ],
    "sg:phone":"+1   ",
    "sg:postcode":"13501",
    "sg:province":"NY",
    "wof:name":"Attorney At Law",
    "wof:placetype":"venue"
},
  "geometry": {"coordinates":[-75.280022,43.077144],"type":"Point"}
}