{
  "type": "Feature",
  "properties": {
    "iso:country":"US",
    "sg:address":"183 Caesars Ln",
    "sg:city":"New Windsor",
    "sg:classifiers":[
        {
            "category":"Professional",
            "subcategory":"Computer Services",
            "type":"Services"
        }
    ],
    "sg:phone":"+1 845 562 6227",
    "sg:postcode":"12553",
    "sg:province":"NY",
    "sg:tags":[
        "consultant",
        "designer"
    ],
    "wof:name":"VPS Assoc",
    "wof:placetype":"venue"
},
  "geometry": {"coordinates":[-74.03140399999999,41.463221],"type":"Point"}
}