{
  "type": "Feature",
  "properties": {
    "addr:full":"2 Wooster St New York NY 10013",
    "addr:housenumber":"2",
    "addr:postcode":"10013",
    "addr:street":"Wooster St",
    "iso:country":"US",
    "sg:address":"2 Wooster St",
    "sg:city":"New York",
    "sg:classifiers":[
        {
            "category":"Professional",
            "type":"Services"
        }
    ],
    "sg:phone":"+1 212 941 8135",
    "sg:postcode":"10013",
    "sg:province":"NY",
    "sg:tags":[
        "establishment"
    ],
    "wof:name":"Nadia Roden Designs LTD",
    "wof:placetype":"venue"
},
  "geometry": {"coordinates":[-74.002971,40.721995],"type":"Point"}
}