{
  "type": "Feature",
  "properties": {
    "addr:full":"50 4th Ave Brooklyn NY 11217",
    "addr:housenumber":"50",
    "addr:postcode":"11217",
    "addr:street":"4Th Ave",
    "iso:country":"US",
    "sg:address":"50 4th Ave",
    "sg:city":"Brooklyn",
    "sg:classifiers":[
        {
            "category":"Restaurant",
            "type":"Food & Drink"
        }
    ],
    "sg:phone":"+1 718 875 9888",
    "sg:postcode":"11217",
    "sg:province":"NY",
    "sg:tags":[
        "chinese"
    ],
    "wof:name":"No Pork Halal Kitchen",
    "wof:placetype":"venue"
},
  "geometry": {"coordinates":[-73.979247,40.683197],"type":"Point"}
}