{
  "type": "Feature",
  "properties": {
    "addr:full":"4232 10th Ave Brooklyn NY 11219",
    "addr:housenumber":"4232",
    "addr:postcode":"11219",
    "addr:street":"10Th Ave",
    "iso:country":"US",
    "sg:address":"4232 10th Ave",
    "sg:city":"Brooklyn",
    "sg:classifiers":[
        {
            "category":"Professional",
            "type":"Services"
        }
    ],
    "sg:phone":"+1 718 854 1863",
    "sg:postcode":"11219",
    "sg:province":"NY",
    "sg:tags":[
        "establishment"
    ],
    "wof:name":"Gao Sheng",
    "wof:placetype":"venue"
},
  "geometry": {"coordinates":[-73.995142,40.642606],"type":"Point"}
}