{
  "type": "Feature",
  "properties": {
    "addr:full":"551 Madison Ave New York NY 10022",
    "addr:housenumber":"551",
    "addr:postcode":"10022",
    "addr:street":"Madison Ave",
    "iso:country":"US",
    "sg:address":"551 Madison Ave",
    "sg:city":"New York",
    "sg:classifiers":[
        {
            "category":"Real Estate",
            "subcategory":"Real Estate Agent",
            "type":"Services"
        }
    ],
    "sg:phone":"+1 212 750 0544",
    "sg:postcode":"10022",
    "sg:province":"NY",
    "wof:name":"Salome Realty",
    "wof:placetype":"venue"
},
  "geometry": {"coordinates":[-73.972852,40.761614],"type":"Point"}
}