{
  "type": "Feature",
  "properties": {
    "iso:country":"US",
    "sg:address":"152 W 36 St",
    "sg:city":"New York",
    "sg:classifiers":[
        {
            "category":"Professional",
            "type":"Services"
        }
    ],
    "sg:phone":"+1 646 674 1102",
    "sg:postcode":"10018",
    "sg:province":"NY",
    "sg:tags":[
        "establishment"
    ],
    "wof:name":"Lydia St Claire Intl",
    "wof:placetype":"venue"
},
  "geometry": {"coordinates":[-73.98904899999999,40.751836],"type":"Point"}
}