{
  "type": "Feature",
  "properties": {
    "addr:full":"589 Old Rte 212 Saugerties NY 12477",
    "addr:housenumber":"589",
    "addr:postcode":"12477",
    "addr:street":"Old Rte 212",
    "iso:country":"US",
    "sg:address":"589 Old Rte 212",
    "sg:city":"Saugerties",
    "sg:classifiers":[
        {
            "category":"Retail",
            "subcategory":"Repair Shop",
            "type":"Services"
        }
    ],
    "sg:phone":"+1   ",
    "sg:postcode":"12477",
    "sg:province":"NY",
    "sg:tags":[
        "equipment",
        "lawn",
        "garden"
    ],
    "wof:name":"Steves Repair",
    "wof:placetype":"venue"
},
  "geometry": {"coordinates":[-74.07283099999999,42.044756],"type":"Point"}
}