{
  "type": "Feature",
  "properties": {
    "iso:country":"US",
    "sg:address":"21 Montezuma St",
    "sg:city":"Lyons",
    "sg:classifiers":[
        {
            "category":"Restaurant",
            "type":"Food & Drink"
        }
    ],
    "sg:phone":"+1   ",
    "sg:postcode":"14489",
    "sg:province":"NY",
    "sg:tags":[
        "eating"
    ],
    "wof:name":"Nickys Soda Spa",
    "wof:placetype":"venue"
},
  "geometry": {"coordinates":[-76.98938099999999,43.063062],"type":"Point"}
}