{
  "type": "Feature",
  "properties": {
    "iso:country":"US",
    "sg:address":"311 Clifton Ave",
    "sg:city":"Kingston",
    "sg:classifiers":[
        {
            "category":"Real Estate",
            "subcategory":"Real Estate Services",
            "type":"Services"
        },
        {
            "category":"Personal",
            "type":"Services"
        },
        {
            "category":"Building & Trades",
            "subcategory":"Cleaning & Sanitation",
            "type":"Services"
        }
    ],
    "sg:phone":"+1 914 388 5215",
    "sg:postcode":"12401",
    "sg:province":"NY",
    "sg:tags":[
        "window",
        "property",
        "janitorial",
        "maintenance"
    ],
    "sg:website":"http://www.dpspropertymanagementservices.com",
    "wof:name":"DPS Property Management Services",
    "wof:placetype":"venue"
},
  "geometry": {"coordinates":[-73.987951,41.937853],"type":"Point"}
}