{
  "type": "Feature",
  "properties": {
    "iso:country":"US",
    "sg:address":"331 W 38th St",
    "sg:city":"New York",
    "sg:classifiers":[
        {
            "category":"Retail",
            "subcategory":"Repair Shop",
            "type":"Services"
        }
    ],
    "sg:phone":"+1 917 546 1674",
    "sg:postcode":"10018",
    "sg:province":"NY",
    "sg:tags":[
        "lock",
        "locksmith"
    ],
    "wof:name":"24 Hour 7 Day Emergency Towing",
    "wof:placetype":"venue"
},
  "geometry": {"coordinates":[-73.993774,40.755605],"type":"Point"}
}