{
  "type": "Feature",
  "properties": {
    "iso:country":"US",
    "sg:address":"5460 Pinecrest Dr",
    "sg:city":"Lockport",
    "sg:classifiers":[
        {
            "category":"Wholesale",
            "subcategory":"Books, Periodicals, & Newspapers",
            "type":"Manufacturing & Wholesale Goods"
        },
        {
            "category":"Manufacturing",
            "subcategory":"Printing",
            "type":"Manufacturing & Wholesale Goods"
        }
    ],
    "sg:phone":"+1 716 478 0059",
    "sg:postcode":"14094",
    "sg:province":"NY",
    "sg:tags":[
        "antique",
        "publisher",
        "literature",
        "auto"
    ],
    "wof:name":"Lincoln Publishing Co Inc",
    "wof:placetype":"venue"
},
  "geometry": {"coordinates":[-78.620817,43.15329],"type":"Point"}
}