{
  "type": "Feature",
  "properties": {
    "iso:country":"US",
    "sg:address":"373 N Hickory St",
    "sg:city":"Massapequa",
    "sg:classifiers":[
        {
            "category":"Education",
            "subcategory":"Special Training",
            "type":"Public Place"
        }
    ],
    "sg:phone":"+1 516 795 6182",
    "sg:postcode":"11758",
    "sg:province":"NY",
    "sg:tags":[
        "piano"
    ],
    "wof:name":"Joan Harris Piano Lessons",
    "wof:placetype":"venue"
},
  "geometry": {"coordinates":[-73.48107299999999,40.698226],"type":"Point"}
}