{
  "type": "Feature",
  "properties": {
    "iso:country":"US",
    "sg:address":"42 Grove St",
    "sg:city":"Gouverneur",
    "sg:classifiers":[
        {
            "category":"Real Estate",
            "subcategory":"Developer",
            "type":"Services"
        }
    ],
    "sg:phone":"+1 315 287 3575",
    "sg:postcode":"13642",
    "sg:province":"NY",
    "wof:name":"Keystone LLC",
    "wof:placetype":"venue"
},
  "geometry": {"coordinates":[-75.465127,44.33362],"type":"Point"}
}