{
  "type": "Feature",
  "properties": {
    "iso:country":"US",
    "sg:address":"60 Bay St",
    "sg:city":"Sag Harbor",
    "sg:classifiers":[
        {
            "category":"Health Services",
            "subcategory":"Health Practitioner",
            "type":"Services"
        }
    ],
    "sg:phone":"+1   ",
    "sg:postcode":"11963",
    "sg:province":"NY",
    "wof:name":"Manual & Sports Physcl Therapy",
    "wof:placetype":"venue"
},
  "geometry": {"coordinates":[-72.28954899999999,41.000475],"type":"Point"}
}