{
  "type": "Feature",
  "properties": {
    "addr:full":"1 E 75 St New York NY 10021",
    "addr:housenumber":"1;75",
    "addr:postcode":"10021",
    "addr:street":"E;St",
    "iso:country":"US",
    "sg:address":"1 E 75 St",
    "sg:city":"New York",
    "sg:classifiers":[
        {
            "category":"Professional",
            "subcategory":"Research",
            "type":"Services"
        }
    ],
    "sg:phone":"+1 212 535 0400",
    "sg:postcode":"10021",
    "sg:province":"NY",
    "sg:tags":[
        "foundation",
        "philanthropic"
    ],
    "sg:website":"www.cmwf.org",
    "wof:name":"Commonwealth Funds",
    "wof:placetype":"venue"
},
  "geometry": {"coordinates":[-73.964012,40.773733],"type":"Point"}
}