{
  "type": "Feature",
  "properties": {
    "iso:country":"US",
    "sg:address":"775 Park Ave",
    "sg:city":"Huntington",
    "sg:classifiers":[
        {
            "category":"Health Services",
            "subcategory":"Doctor",
            "type":"Services"
        }
    ],
    "sg:phone":"+1 631 784 7704",
    "sg:postcode":"11743",
    "sg:province":"NY",
    "wof:name":"Pereira Selwyn Dr",
    "wof:placetype":"venue"
},
  "geometry": {"coordinates":[-73.380402,40.850899],"type":"Point"}
}