{
  "type": "Feature",
  "properties": {
    "iso:country":"US",
    "sg:address":"181 River Rd",
    "sg:city":"Nyack",
    "sg:classifiers":[
        {
            "category":"Building & Trades",
            "subcategory":"Construction",
            "type":"Services"
        }
    ],
    "sg:phone":"+1 845 365 0271",
    "sg:postcode":"10960",
    "sg:province":"NY",
    "sg:tags":[
        "painting",
        "contractor"
    ],
    "sg:website":"http://www.evergreene.com",
    "wof:name":"Evergreene",
    "wof:placetype":"venue"
},
  "geometry": {"coordinates":[-73.920838,41.064168],"type":"Point"}
}