{
  "type": "Feature",
  "properties": {
    "iso:country":"US",
    "sg:address":"36 Pennant Dr",
    "sg:city":"Mastic Beach",
    "sg:classifiers":[
        {
            "category":"Wholesale",
            "subcategory":"Groceries",
            "type":"Manufacturing & Wholesale Goods"
        }
    ],
    "sg:phone":"+1 631 395 9131",
    "sg:postcode":"11951",
    "sg:province":"NY",
    "sg:tags":[
        "confectionery"
    ],
    "wof:name":"Stilson Distributors Inc",
    "wof:placetype":"venue"
},
  "geometry": {"coordinates":[-72.823223,40.775056],"type":"Point"}
}