{
  "type": "Feature",
  "properties": {
    "addr:full":"121 John St New Windsor NY 12553",
    "addr:housenumber":"121",
    "addr:postcode":"12553",
    "addr:street":"John St",
    "iso:country":"US",
    "sg:address":"121 John St",
    "sg:city":"New Windsor",
    "sg:classifiers":[
        {
            "category":"Retail",
            "subcategory":"Laundry & Dry Cleaning",
            "type":"Services"
        }
    ],
    "sg:phone":"+1 845 565 7847",
    "sg:postcode":"12553",
    "sg:province":"NY",
    "sg:tags":[
        "cleaners",
        "rug",
        "carpet"
    ],
    "wof:name":"Bob Cairns Carpet Cleaning",
    "wof:placetype":"venue"
},
  "geometry": {"coordinates":[-74.021852,41.490316],"type":"Point"}
}