{
  "type": "Feature",
  "properties": {
    "addr:full":"1101 Victory Blvd Staten Island NY 10301",
    "addr:housenumber":"1101",
    "addr:postcode":"10301",
    "addr:street":"Victory Blvd",
    "iso:country":"US",
    "sg:address":"1101 Victory Blvd",
    "sg:city":"Staten Island",
    "sg:classifiers":[
        {
            "category":"Real Estate",
            "subcategory":"Real Estate Agent",
            "type":"Services"
        }
    ],
    "sg:phone":"+1 718 447 0656",
    "sg:postcode":"10301",
    "sg:province":"NY",
    "sg:tags":[
        "manager",
        "broker"
    ],
    "wof:name":"Jaeger Realty Co",
    "wof:placetype":"venue"
},
  "geometry": {"coordinates":[-74.10189699999999,40.617453],"type":"Point"}
}