{
  "type": "Feature",
  "properties": {
    "iso:country":"US",
    "sg:address":"90 Smith Rd",
    "sg:city":"Parksville",
    "sg:classifiers":[
        {
            "category":"Building & Trades",
            "subcategory":"Construction",
            "type":"Services"
        }
    ],
    "sg:phone":"+1 845 295 8786",
    "sg:postcode":"12768",
    "sg:province":"NY",
    "sg:tags":[
        "general",
        "contractor"
    ],
    "wof:name":"Picker Contracting",
    "wof:placetype":"venue"
},
  "geometry": {"coordinates":[-74.699057,41.854647],"type":"Point"}
}