{
  "type": "Feature",
  "properties": {
    "addr:full":"5960 Joy Rd Sodus NY 14551",
    "addr:housenumber":"5960",
    "addr:postcode":"14551",
    "addr:street":"Joy Rd",
    "iso:country":"US",
    "sg:address":"5960 Joy Rd",
    "sg:city":"Sodus",
    "sg:classifiers":[
        {
            "category":"Building & Trades",
            "subcategory":"Landscaping Services",
            "type":"Services"
        }
    ],
    "sg:phone":"+1 315 483 6412",
    "sg:postcode":"14551",
    "sg:province":"NY",
    "sg:tags":[
        "tree"
    ],
    "wof:name":"Apple Tree Enterprises",
    "wof:placetype":"venue"
},
  "geometry": {"coordinates":[-77.097527,43.183609],"type":"Point"}
}