{
  "type": "Feature",
  "properties": {
    "iso:country":"US",
    "sg:address":"353 Irona Rd",
    "sg:city":"Altona",
    "sg:classifiers":[
        {
            "category":"Shopping",
            "subcategory":"Florist",
            "type":"Retail Goods"
        }
    ],
    "sg:phone":"+1   ",
    "sg:postcode":"12910",
    "sg:province":"NY",
    "wof:name":"Ernie Florists & Greener",
    "wof:placetype":"venue"
},
  "geometry": {"coordinates":[-73.670191,44.899527],"type":"Point"}
}