{
  "type": "Feature",
  "properties": {
    "addr:full":"575 King St Port Chester NY 10573",
    "addr:housenumber":"575",
    "addr:postcode":"10573",
    "addr:street":"King St",
    "iso:country":"US",
    "sg:address":"575 King St",
    "sg:city":"Port Chester",
    "sg:classifiers":[
        {
            "category":"Organizations",
            "subcategory":"Religious Organization",
            "type":"Services"
        }
    ],
    "sg:phone":"+1 914 939 1004",
    "sg:postcode":"10573",
    "sg:province":"NY",
    "wof:name":"Congrgtion Knses Tfreth Israel",
    "wof:placetype":"venue"
},
  "geometry": {"coordinates":[-73.66865900000001,41.016487],"type":"Point"}
}