{
  "type": "Feature",
  "properties": {
    "addr:full":"770 W Jericho Tpke Huntington NY 11743",
    "addr:housenumber":"770",
    "addr:postcode":"11743",
    "addr:street":"W Jericho Tpke",
    "iso:country":"US",
    "sg:address":"770 W Jericho Tpke",
    "sg:city":"Huntington",
    "sg:classifiers":[
        {
            "category":"Professional",
            "subcategory":"Computer Services",
            "type":"Services"
        }
    ],
    "sg:phone":"+1 631 692 5500",
    "sg:postcode":"11743",
    "sg:province":"NY",
    "sg:tags":[
        "consultant",
        "designer"
    ],
    "wof:name":"Advanced Digital Security",
    "wof:placetype":"venue"
},
  "geometry": {"coordinates":[-73.445435,40.821255],"type":"Point"}
}