{
  "type": "Feature",
  "properties": {
    "iso:country":"US",
    "sg:address":"91 Magnolia Ave",
    "sg:city":"Westbury",
    "sg:classifiers":[
        {
            "category":"Professional",
            "type":"Services"
        }
    ],
    "sg:phone":"+1 516 334 5310",
    "sg:postcode":"11590",
    "sg:province":"NY",
    "sg:tags":[
        "mineral"
    ],
    "wof:name":"Walling Enterprises",
    "wof:placetype":"venue"
},
  "geometry": {"coordinates":[-73.567583,40.75533],"type":"Point"}
}