{
  "type": "Feature",
  "properties": {
    "iso:country":"US",
    "sg:address":"3789 Howlett Hill Rd",
    "sg:city":"Syracuse",
    "sg:classifiers":[
        {
            "category":"Building & Trades",
            "subcategory":"Plumbing",
            "type":"Services"
        }
    ],
    "sg:phone":"+1 315 488 0839",
    "sg:postcode":"13215",
    "sg:province":"NY",
    "sg:tags":[
        "contractor"
    ],
    "wof:name":"Salt City Heating AC",
    "wof:placetype":"venue"
},
  "geometry": {"coordinates":[-76.248386,43.014544],"type":"Point"}
}