{
  "type": "Feature",
  "properties": {
    "addr:full":"126 W 23rd St New York NY 10011",
    "addr:housenumber":"126",
    "addr:postcode":"10011",
    "addr:street":"W 23Rd St",
    "iso:country":"US",
    "sg:address":"126 W 23rd St",
    "sg:city":"New York",
    "sg:classifiers":[
        {
            "category":"Retail",
            "subcategory":"Repair Shop",
            "type":"Services"
        }
    ],
    "sg:phone":"+1 917 591 2024",
    "sg:postcode":"10011",
    "sg:province":"NY",
    "sg:tags":[
        "lock",
        "locksmith"
    ],
    "wof:name":"Adasa Locksmith",
    "wof:placetype":"venue"
},
  "geometry": {"coordinates":[-73.99511,40.743715],"type":"Point"}
}