{
  "type": "Feature",
  "properties": {
    "iso:country":"US",
    "sg:address":"507 E Center St",
    "sg:city":"Medina",
    "sg:classifiers":[
        {
            "category":"Farming",
            "subcategory":"Nursery",
            "type":"Manufacturing & Wholesale Goods"
        }
    ],
    "sg:phone":"+1 585 798 0045",
    "sg:postcode":"14103",
    "sg:province":"NY",
    "sg:tags":[
        "greenhouse"
    ],
    "wof:name":"Muchow's Green House",
    "wof:placetype":"venue"
},
  "geometry": {"coordinates":[-78.37449599999999,43.220691],"type":"Point"}
}