{
  "type": "Feature",
  "properties": {
    "iso:country":"US",
    "sg:address":"1900 Jerome Ave",
    "sg:city":"Bronx",
    "sg:classifiers":[
        {
            "category":"Bars & Pubs",
            "subcategory":"Sports Bar",
            "type":"Food & Drink"
        }
    ],
    "sg:phone":"+1 718 731 0056",
    "sg:postcode":"10453",
    "sg:province":"NY",
    "wof:name":"Momumento Sports Bar",
    "wof:placetype":"venue"
},
  "geometry": {"coordinates":[-73.910301,40.850399],"type":"Point"}
}