{
  "type": "Feature",
  "properties": {
    "iso:country":"US",
    "sg:address":"65 New York Ave",
    "sg:city":"Congers",
    "sg:classifiers":[
        {
            "category":"Retail",
            "subcategory":"Repair Shop",
            "type":"Services"
        }
    ],
    "sg:phone":"+1 845 634 2234",
    "sg:postcode":"10920",
    "sg:province":"NY",
    "sg:tags":[
        "lock",
        "locksmith"
    ],
    "wof:name":"A-1 Locksmith & Alarm",
    "wof:placetype":"venue"
},
  "geometry": {"coordinates":[-73.931825,41.139592],"type":"Point"}
}