{
  "type": "Feature",
  "properties": {
    "iso:country":"US",
    "sg:address":"1172 Bedford Ave",
    "sg:city":"Brooklyn",
    "sg:classifiers":[
        {
            "category":"Professional",
            "type":"Services"
        }
    ],
    "sg:phone":"+1 718 230 5430",
    "sg:postcode":"11216",
    "sg:province":"NY",
    "sg:tags":[
        "establishment"
    ],
    "wof:name":"Global Trading Ctr",
    "wof:placetype":"venue"
},
  "geometry": {"coordinates":[-73.954065,40.683813],"type":"Point"}
}