{
  "type": "Feature",
  "properties": {
    "addr:full":"3147 Eastern Pkwy Baldwin NY 11510",
    "addr:housenumber":"3147",
    "addr:postcode":"11510",
    "addr:street":"Eastern Pkwy",
    "iso:country":"US",
    "sg:address":"3147 Eastern Pkwy",
    "sg:city":"Baldwin",
    "sg:classifiers":[
        {
            "category":"Organizations",
            "subcategory":"Religious Organization",
            "type":"Services"
        }
    ],
    "sg:phone":"+1 516 379 0720",
    "sg:postcode":"11510",
    "sg:province":"NY",
    "sg:tags":[
        "church"
    ],
    "wof:name":"South Nassau Christian Church",
    "wof:placetype":"venue"
},
  "geometry": {"coordinates":[-73.599414,40.634857],"type":"Point"}
}