{
  "type": "Feature",
  "properties": {
    "addr:full":"16 Lee Ave Brooklyn NY 11211",
    "addr:housenumber":"16",
    "addr:postcode":"11211",
    "addr:street":"Lee Ave",
    "iso:country":"US",
    "sg:address":"16 Lee Ave",
    "sg:city":"Brooklyn",
    "sg:classifiers":[
        {
            "category":"Wholesale",
            "subcategory":"Stationery",
            "type":"Manufacturing & Wholesale Goods"
        }
    ],
    "sg:phone":"+1 718 783 2300",
    "sg:postcode":"11211",
    "sg:province":"NY",
    "sg:tags":[
        "industrial",
        "paper"
    ],
    "wof:name":"Guardian Better Pak Corp",
    "wof:placetype":"venue"
},
  "geometry": {"coordinates":[-73.961907,40.707425],"type":"Point"}
}