{
  "type": "Feature",
  "properties": {
    "addr:full":"6 Muellers Ln Yaphank NY 11980",
    "addr:housenumber":"6",
    "addr:postcode":"11980",
    "addr:street":"Muellers Ln",
    "iso:country":"US",
    "sg:address":"6 Muellers Ln",
    "sg:city":"Yaphank",
    "sg:classifiers":[
        {
            "category":"Professional",
            "subcategory":"Business Services",
            "type":"Services"
        },
        {
            "category":"Building & Trades",
            "subcategory":"Construction",
            "type":"Services"
        }
    ],
    "sg:phone":"+1 631 345 6800",
    "sg:postcode":"11980",
    "sg:province":"NY",
    "sg:tags":[
        "coping",
        "plastering",
        "tiling",
        "pool",
        "swimming"
    ],
    "wof:name":"Plum Perfect Pool & Spa Inc",
    "wof:placetype":"venue"
},
  "geometry": {"coordinates":[-72.92353199999999,40.837602],"type":"Point"}
}