{
  "type": "Feature",
  "properties": {
    "addr:full":"1916 Genesee St Buffalo NY 14211",
    "addr:housenumber":"1916",
    "addr:postcode":"14211",
    "addr:street":"Genesee St",
    "iso:country":"US",
    "sg:address":"1916 Genesee St",
    "sg:city":"Buffalo",
    "sg:classifiers":[
        {
            "category":"Retail",
            "subcategory":"Auto Repair",
            "type":"Services"
        }
    ],
    "sg:phone":"+1 716 892 1105",
    "sg:postcode":"14211",
    "sg:province":"NY",
    "sg:tags":[
        "repairing",
        "automobile"
    ],
    "wof:name":"Genesee Auto Svce",
    "wof:placetype":"venue"
},
  "geometry": {"coordinates":[-78.81109600000001,42.913601],"type":"Point"}
}