{
  "type": "Feature",
  "properties": {
    "addr:full":"6501 Roosevelt Ave Woodside NY 11377",
    "addr:housenumber":"6501",
    "addr:postcode":"11377",
    "addr:street":"Roosevelt Ave",
    "iso:country":"US",
    "sg:address":"6501 Roosevelt Ave",
    "sg:city":"Woodside",
    "sg:classifiers":[
        {
            "category":"Home & Garden",
            "subcategory":"Home Furnishings",
            "type":"Retail Goods"
        },
        {
            "category":"Home & Garden",
            "subcategory":"Hardware",
            "type":"Retail Goods"
        }
    ],
    "sg:phone":"+1 718 779 9259",
    "sg:postcode":"11377",
    "sg:province":"NY",
    "sg:tags":[
        "decor",
        "store"
    ],
    "wof:name":"Gleason Paints",
    "wof:placetype":"venue"
},
  "geometry": {"coordinates":[-73.899002,40.745899],"type":"Point"}
}