{
  "type": "Feature",
  "properties": {
    "iso:country":"US",
    "sg:address":"30 Monroe Blvd",
    "sg:city":"West Monroe",
    "sg:classifiers":[
        {
            "category":"Retail",
            "subcategory":"Repair Shop",
            "type":"Services"
        }
    ],
    "sg:phone":"+1 315 668 7356",
    "sg:postcode":"13167",
    "sg:province":"NY",
    "sg:tags":[
        "repairing",
        "lawn",
        "mower"
    ],
    "wof:name":"West Monroe Lawn & Snow",
    "wof:placetype":"venue"
},
  "geometry": {"coordinates":[-76.064733,43.298439],"type":"Point"}
}