{
  "type": "Feature",
  "properties": {
    "iso:country":"US",
    "sg:address":"5551 Martha's Vineyard",
    "sg:city":"Clarence Center",
    "sg:classifiers":[
        {
            "category":"Banks & Credit Unions",
            "subcategory":"Investment Brokerage",
            "type":"Services"
        }
    ],
    "sg:phone":"+1 716 741 1180",
    "sg:postcode":"14032",
    "sg:province":"NY",
    "sg:tags":[
        "advisory"
    ],
    "wof:name":"Marlowe Financial Services",
    "wof:placetype":"venue"
},
  "geometry": {"coordinates":[-78.639521,43.000507],"type":"Point"}
}