{
  "type": "Feature",
  "properties": {
    "addr:full":"4141 Co Rd 9 Hudson NY 12544",
    "addr:housenumber":"4141",
    "addr:postcode":"12544",
    "addr:street":"Co Rd 9",
    "iso:country":"US",
    "sg:address":"4141 Co Rd 9",
    "sg:city":"Hudson",
    "sg:classifiers":[
        {
            "category":"Retail",
            "subcategory":"Veterinary Services",
            "type":"Services"
        }
    ],
    "sg:phone":"+1 518 828 1622",
    "sg:postcode":"12544",
    "sg:province":"NY",
    "wof:name":"Mountainview Animal Hospital",
    "wof:placetype":"venue"
},
  "geometry": {"coordinates":[-73.666471,42.262618],"type":"Point"}
}