{
  "type": "Feature",
  "properties": {
    "addr:full":"2004 Chili Ave Rochester NY 14624",
    "addr:housenumber":"2004",
    "addr:postcode":"14624",
    "addr:street":"Chili Ave",
    "iso:country":"US",
    "sg:address":"2004 Chili Ave",
    "sg:city":"Rochester",
    "sg:classifiers":[
        {
            "category":"Shopping",
            "subcategory":"Discount & Variety Stores",
            "type":"Retail Goods"
        }
    ],
    "sg:phone":"+1 585 247 8790",
    "sg:postcode":"14624",
    "sg:province":"NY",
    "sg:website":"www.dollartree.com",
    "wof:name":"Dollar Tree",
    "wof:placetype":"venue"
},
  "geometry": {"coordinates":[-77.688085,43.131422],"type":"Point"}
}