{
  "type": "Feature",
  "properties": {
    "iso:country":"US",
    "sg:address":"4804 Merrick Rd",
    "sg:city":"Massapequa",
    "sg:classifiers":[
        {
            "category":"Real Estate",
            "subcategory":"Real Estate Agent",
            "type":"Services"
        }
    ],
    "sg:phone":"+1 516 798 1353",
    "sg:postcode":"11758",
    "sg:province":"NY",
    "sg:website":"www.prudentiallirealty.com",
    "wof:name":"Prudential Douglas Elliman",
    "wof:placetype":"venue"
},
  "geometry": {"coordinates":[-73.457235,40.666446],"type":"Point"}
}