{
  "type": "Feature",
  "properties": {
    "iso:country":"US",
    "sg:address":"19 Bridge St",
    "sg:city":"Glen Cove",
    "sg:classifiers":[
        {
            "category":"Professional",
            "type":"Services"
        }
    ],
    "sg:phone":"+1 516 609 9010",
    "sg:postcode":"11542",
    "sg:province":"NY",
    "sg:tags":[
        "establishment"
    ],
    "wof:name":"Rhyno Sky Enterprises",
    "wof:placetype":"venue"
},
  "geometry": {"coordinates":[-73.631871,40.863785],"type":"Point"}
}