{
  "type": "Feature",
  "properties": {
    "addr:full":"408 Manhattan Ave New York NY 10026",
    "addr:housenumber":"408",
    "addr:postcode":"10026",
    "addr:street":"Manhattan Ave",
    "iso:country":"US",
    "sg:address":"408 Manhattan Ave",
    "sg:city":"New York",
    "sg:classifiers":[
        {
            "category":"Building & Trades",
            "subcategory":"Construction",
            "type":"Services"
        }
    ],
    "sg:phone":"+1 212 222 6512",
    "sg:postcode":"10026",
    "sg:province":"NY",
    "sg:tags":[
        "general",
        "contractor"
    ],
    "wof:name":"Diggs Construction Co",
    "wof:placetype":"venue"
},
  "geometry": {"coordinates":[-73.955927,40.806075],"type":"Point"}
}