{
  "type": "Feature",
  "properties": {
    "addr:full":"230 E 79th Street New York NY 10021",
    "addr:housenumber":"230",
    "addr:postcode":"10021",
    "addr:street":"E 79Th Street",
    "iso:country":"US",
    "sg:address":"230 E 79th Street",
    "sg:city":"New York",
    "sg:classifiers":[
        {
            "category":"Health Services",
            "subcategory":"Dentist",
            "type":"Services"
        }
    ],
    "sg:phone":"+1 212 396 3069",
    "sg:postcode":"10021",
    "sg:province":"NY",
    "wof:name":"Pirvan Mihai DDS",
    "wof:placetype":"venue"
},
  "geometry": {"coordinates":[-73.956605,40.77396],"type":"Point"}
}