{
  "type": "Feature",
  "properties": {
    "addr:full":"155 Maple Ave Westbury NY 11590",
    "addr:housenumber":"155",
    "addr:postcode":"11590",
    "addr:street":"Maple Ave",
    "iso:country":"US",
    "sg:address":"155 Maple Ave",
    "sg:city":"Westbury",
    "sg:classifiers":[
        {
            "category":"Building & Trades",
            "subcategory":"Landscaping Services",
            "type":"Services"
        }
    ],
    "sg:phone":"+1 516 334 0922",
    "sg:postcode":"11590",
    "sg:province":"NY",
    "sg:tags":[
        "landscape"
    ],
    "wof:name":"D Alessandro Michele Ldscpg",
    "wof:placetype":"venue"
},
  "geometry": {"coordinates":[-73.59118599999999,40.755259],"type":"Point"}
}