{
  "type": "Feature",
  "properties": {
    "iso:country":"US",
    "sg:address":"531 Farber Lakes Dr",
    "sg:city":"Williamsville",
    "sg:classifiers":[
        {
            "category":"Professional",
            "subcategory":"Lawyer & Legal Services",
            "type":"Services"
        }
    ],
    "sg:phone":"+1 716 632 4648",
    "sg:postcode":"14221",
    "sg:province":"NY",
    "sg:tags":[
        "attorney"
    ],
    "wof:name":"Lucian Parlato",
    "wof:placetype":"venue"
},
  "geometry": {"coordinates":[-78.73258199999999,42.976185],"type":"Point"}
}