{
  "type": "Feature",
  "properties": {
    "addr:full":"24 West St Spring Valley NY 10977",
    "addr:housenumber":"24",
    "addr:postcode":"10977",
    "addr:street":"West St",
    "iso:country":"US",
    "sg:address":"24 West St",
    "sg:city":"Spring Valley",
    "sg:classifiers":[
        {
            "category":"Building & Trades",
            "subcategory":"Construction",
            "type":"Services"
        }
    ],
    "sg:phone":"+1 845 356 0778",
    "sg:postcode":"10977",
    "sg:province":"NY",
    "sg:tags":[
        "designer",
        "dealer",
        "pool",
        "swimming"
    ],
    "sg:website":"www.bbpoolandspa.com",
    "wof:name":"B & B Pool & Spa Ctr",
    "wof:placetype":"venue"
},
  "geometry": {"coordinates":[-74.050603,41.113253],"type":"Point"}
}