{
  "type": "Feature",
  "properties": {
    "addr:full":"7 Oakwood Ave White Plains NY 10605",
    "addr:housenumber":"7",
    "addr:postcode":"10605",
    "addr:street":"Oakwood Ave",
    "iso:country":"US",
    "sg:address":"7 Oakwood Ave",
    "sg:city":"White Plains",
    "sg:classifiers":[
        {
            "category":"Building & Trades",
            "subcategory":"Construction",
            "type":"Services"
        }
    ],
    "sg:phone":"+1 914 949 8484",
    "sg:postcode":"10605",
    "sg:province":"NY",
    "sg:tags":[
        "hanging",
        "contractor"
    ],
    "wof:name":"Del Commercial Spray",
    "wof:placetype":"venue"
},
  "geometry": {"coordinates":[-73.766966,41.022774],"type":"Point"}
}