{
  "type": "Feature",
  "properties": {
    "iso:country":"US",
    "sg:address":"115 Allen St",
    "sg:city":"New York",
    "sg:classifiers":[
        {
            "category":"Shopping",
            "subcategory":"Clothing, Apparel, & Fashions",
            "type":"Retail Goods"
        }
    ],
    "sg:phone":"+1   ",
    "sg:postcode":"10002",
    "sg:province":"NY",
    "wof:name":"Vanelay Inc",
    "wof:placetype":"venue"
},
  "geometry": {"coordinates":[-73.989958,40.720478],"type":"Point"}
}