{
  "type": "Feature",
  "properties": {
    "addr:full":"8118 13th Ave Brooklyn NY 11228",
    "addr:housenumber":"8118",
    "addr:postcode":"11228",
    "addr:street":"13Th Ave",
    "iso:country":"US",
    "sg:address":"8118 13th Ave",
    "sg:city":"Brooklyn",
    "sg:classifiers":[
        {
            "category":"Professional",
            "subcategory":"Lawyer & Legal Services",
            "type":"Services"
        }
    ],
    "sg:phone":"+1   ",
    "sg:postcode":"11228",
    "sg:province":"NY",
    "wof:name":"Martin Freedhand",
    "wof:placetype":"venue"
},
  "geometry": {"coordinates":[-74.011521,40.616494],"type":"Point"}
}