{
  "type": "Feature",
  "properties": {
    "addr:full":"1071 Ave of the Americas New York NY 10018",
    "addr:housenumber":"1071",
    "addr:postcode":"10018",
    "addr:street":"Ave Of The Americas",
    "iso:country":"US",
    "sg:address":"1071 Ave of the Americas",
    "sg:city":"New York",
    "sg:classifiers":[
        {
            "category":"Wholesale",
            "subcategory":"Apparel",
            "type":"Manufacturing & Wholesale Goods"
        }
    ],
    "sg:phone":"+1 212 382 1444",
    "sg:postcode":"10018",
    "sg:province":"NY",
    "sg:tags":[
        "import"
    ],
    "wof:name":"Forsyth of Canada Inc",
    "wof:placetype":"venue"
},
  "geometry": {"coordinates":[-73.984118,40.754842],"type":"Point"}
}