{
  "type": "Feature",
  "properties": {
    "addr:full":"1664 Coney Island Ave Brooklyn NY 11230",
    "addr:housenumber":"1664",
    "addr:postcode":"11230",
    "addr:street":"Coney Island Ave",
    "iso:country":"US",
    "sg:address":"1664 Coney Island Ave",
    "sg:city":"Brooklyn",
    "sg:classifiers":[
        {
            "category":"Organizations",
            "subcategory":"Religious Organization",
            "type":"Services"
        }
    ],
    "sg:phone":"+1 718 627 0915",
    "sg:postcode":"11230",
    "sg:province":"NY",
    "sg:tags":[
        "clergy"
    ],
    "wof:name":"H C Pincus",
    "wof:placetype":"venue"
},
  "geometry": {"coordinates":[-73.96376600000001,40.617071],"type":"Point"}
}