{
  "type": "Feature",
  "properties": {
    "iso:country":"US",
    "sg:address":"131 Ronkonkoma Ave",
    "sg:city":"Ronkonkoma",
    "sg:classifiers":[
        {
            "category":"Shopping",
            "subcategory":"Shoes",
            "type":"Retail Goods"
        }
    ],
    "sg:phone":"+1 631 585 1491",
    "sg:postcode":"11779",
    "sg:province":"NY",
    "sg:tags":[
        "store"
    ],
    "wof:name":"Payless ShoeSource",
    "wof:placetype":"venue"
},
  "geometry": {"coordinates":[-73.111268,40.824934],"type":"Point"}
}