{
  "type": "Feature",
  "properties": {
    "addr:full":"6 W Main St Lancaster NY 14086",
    "addr:housenumber":"6",
    "addr:postcode":"14086",
    "addr:street":"W Main St",
    "iso:country":"US",
    "sg:address":"6 W Main St",
    "sg:city":"Lancaster",
    "sg:classifiers":[
        {
            "category":"Sports & Exercise",
            "subcategory":"Gym",
            "type":"Entertainment"
        }
    ],
    "sg:phone":"+1 716 683 7373",
    "sg:postcode":"14086",
    "sg:province":"NY",
    "sg:tags":[
        "facility",
        "club",
        "gymnasium",
        "health",
        "fitness",
        "studio",
        "physical"
    ],
    "wof:name":"Fitness Factory of Lancaster",
    "wof:placetype":"venue"
},
  "geometry": {"coordinates":[-78.671605,42.901486],"type":"Point"}
}