{
  "type": "Feature",
  "properties": {
    "addr:full":"675 Manhattan Ave Brooklyn NY 11222",
    "addr:housenumber":"675",
    "addr:postcode":"11222",
    "addr:street":"Manhattan Ave",
    "iso:country":"US",
    "sg:address":"675 Manhattan Ave",
    "sg:city":"Brooklyn",
    "sg:classifiers":[
        {
            "category":"Shopping",
            "subcategory":"Crafts & Fabrics",
            "type":"Retail Goods"
        }
    ],
    "sg:phone":"+1 718 383 5229",
    "sg:postcode":"11222",
    "sg:province":"NY",
    "sg:tags":[
        "shop",
        "store"
    ],
    "sg:website":"www.style-fabrics.com",
    "wof:name":"Style Fabrics",
    "wof:placetype":"venue"
},
  "geometry": {"coordinates":[-73.951599,40.724998],"type":"Point"}
}