{
  "type": "Feature",
  "properties": {
    "addr:full":"385 Halstead Ave Harrison NY 10528",
    "addr:housenumber":"385",
    "addr:postcode":"10528",
    "addr:street":"Halstead Ave",
    "iso:country":"US",
    "sg:address":"385 Halstead Ave",
    "sg:city":"Harrison",
    "sg:classifiers":[
        {
            "category":"Restaurant",
            "type":"Food & Drink"
        }
    ],
    "sg:menulink":"http://www.allmenus.com/ny/harrison/151057-atavola-bistro-385/menu/",
    "sg:phone":"+1 914 381 6050",
    "sg:postcode":"10528",
    "sg:province":"NY",
    "sg:tags":[
        "italian"
    ],
    "wof:name":"A'Tavola Bistro 385",
    "wof:placetype":"venue"
},
  "geometry": {"coordinates":[-73.70898200000001,40.969605],"type":"Point"}
}