{
  "type": "Feature",
  "properties": {
    "addr:full":"10 Jefferson Blvd Staten Island NY 10312",
    "addr:housenumber":"10",
    "addr:postcode":"10312",
    "addr:street":"Jefferson Blvd",
    "iso:country":"US",
    "sg:address":"10 Jefferson Blvd",
    "sg:city":"Staten Island",
    "sg:classifiers":[
        {
            "category":"Shopping",
            "subcategory":"Gifts & Souvenirs",
            "type":"Retail Goods"
        }
    ],
    "sg:phone":"+1   ",
    "sg:postcode":"10312",
    "sg:province":"NY",
    "wof:name":"JS Baseball Card Exchange",
    "wof:placetype":"venue"
},
  "geometry": {"coordinates":[-74.177997,40.541032],"type":"Point"}
}