{
  "type": "Feature",
  "properties": {
    "iso:country":"US",
    "sg:address":"161 Nichols Ave",
    "sg:city":"Brooklyn",
    "sg:classifiers":[
        {
            "category":"Health Services",
            "subcategory":"Medical Lab",
            "type":"Services"
        }
    ],
    "sg:phone":"+1 718 381 4783",
    "sg:postcode":"11208",
    "sg:province":"NY",
    "sg:tags":[
        "laboratory"
    ],
    "wof:name":"Universal Diagnostic Labs Inc",
    "wof:placetype":"venue"
},
  "geometry": {"coordinates":[-73.86927900000001,40.687734],"type":"Point"}
}