{
  "type": "Feature",
  "properties": {
    "iso:country":"US",
    "sg:address":"184 Main St",
    "sg:city":"Fishkill",
    "sg:classifiers":[
        {
            "category":"Shopping",
            "subcategory":"Pharmacy",
            "type":"Retail Goods"
        }
    ],
    "sg:phone":"+1   ",
    "sg:postcode":"12524",
    "sg:province":"NY",
    "wof:name":"CVS",
    "wof:placetype":"venue"
},
  "geometry": {"coordinates":[-73.908061,41.530755],"type":"Point"}
}