{
  "type": "Feature",
  "properties": {
    "addr:full":"505 62nd St Brooklyn NY 11220",
    "addr:housenumber":"505",
    "addr:postcode":"11220",
    "addr:street":"62Nd St",
    "iso:country":"US",
    "sg:address":"505 62nd St",
    "sg:city":"Brooklyn",
    "sg:classifiers":[
        {
            "category":"Manufacturing",
            "subcategory":"Printing",
            "type":"Manufacturing & Wholesale Goods"
        }
    ],
    "sg:phone":"+1   ",
    "sg:postcode":"11220",
    "sg:province":"NY",
    "sg:tags":[
        "publishing"
    ],
    "wof:name":"Disability Network",
    "wof:placetype":"venue"
},
  "geometry": {"coordinates":[-74.015168,40.637127],"type":"Point"}
}