{
  "type": "Feature",
  "properties": {
    "addr:full":"900 Broadway Suite 404 New York NY 10003",
    "addr:housenumber":"900;suite 404",
    "addr:postcode":"10003",
    "addr:street":"Broadway",
    "iso:country":"US",
    "sg:address":"900 Broadway Suite 404",
    "sg:city":"New York",
    "sg:classifiers":[
        {
            "category":"Health Services",
            "subcategory":"Health Practitioner",
            "type":"Services"
        }
    ],
    "sg:phone":"+1 718 577 2699",
    "sg:postcode":"10003",
    "sg:province":"NY",
    "sg:tags":[
        "acupuncture"
    ],
    "wof:name":"Eastgate Acupuncture",
    "wof:placetype":"venue"
},
  "geometry": {"coordinates":[-73.989514,40.738899],"type":"Point"}
}