{
  "type": "Feature",
  "properties": {
    "iso:country":"US",
    "sg:address":"370 Summit Point Dr",
    "sg:city":"Henrietta",
    "sg:classifiers":[
        {
            "category":"Banks & Credit Unions",
            "subcategory":"Bank",
            "type":"Services"
        }
    ],
    "sg:phone":"+1 585 321 0020",
    "sg:postcode":"14467",
    "sg:province":"NY",
    "sg:tags":[
        "mortgage",
        "loan",
        "broker",
        "real estate"
    ],
    "wof:name":"Riverview Mortgage Corp",
    "wof:placetype":"venue"
},
  "geometry": {"coordinates":[-77.649384,43.056167],"type":"Point"}
}