{
  "type": "Feature",
  "properties": {
    "iso:country":"US",
    "sg:address":"999 Montauk Hwy Unit 8",
    "sg:city":"Shirley",
    "sg:classifiers":[
        {
            "category":"Bakery",
            "type":"Food & Drink"
        },
        {
            "category":"Bagels",
            "subcategory":"None",
            "type":"Food & Drink"
        }
    ],
    "sg:phone":"+1 631 281 1476",
    "sg:postcode":"11967",
    "sg:province":"NY",
    "wof:name":"Strathmore Bagels",
    "wof:placetype":"venue"
},
  "geometry": {"coordinates":[-72.862602,40.801998],"type":"Point"}
}