{
  "type": "Feature",
  "properties": {
    "iso:country":"US",
    "sg:address":"2253 Van Rensselaer Dr",
    "sg:city":"Schenectady",
    "sg:classifiers":[
        {
            "category":"Professional",
            "subcategory":"Art Services",
            "type":"Services"
        }
    ],
    "sg:phone":"+1 518 381 4566",
    "sg:postcode":"12309",
    "sg:province":"NY",
    "sg:tags":[
        "graphic",
        "designer"
    ],
    "wof:name":"Visual Winds",
    "wof:placetype":"venue"
},
  "geometry": {"coordinates":[-73.901447,42.826587],"type":"Point"}
}