{
  "type": "Feature",
  "properties": {
    "addr:full":"25 Mandia Ln Goldens Bridge NY 10526",
    "addr:housenumber":"25",
    "addr:postcode":"10526",
    "addr:street":"Mandia Ln",
    "iso:country":"US",
    "sg:address":"25 Mandia Ln",
    "sg:city":"Goldens Bridge",
    "sg:classifiers":[
        {
            "category":"Professional",
            "subcategory":"Computer Services",
            "type":"Services"
        }
    ],
    "sg:phone":"+1 914 232 1960",
    "sg:postcode":"10526",
    "sg:province":"NY",
    "sg:tags":[
        "repair"
    ],
    "wof:name":"21st Century Computer Svc",
    "wof:placetype":"venue"
},
  "geometry": {"coordinates":[-73.68132799999999,41.28934],"type":"Point"}
}