{
  "type": "Feature",
  "properties": {
    "addr:full":"62 South St Oyster Bay NY 11771",
    "addr:housenumber":"62",
    "addr:postcode":"11771",
    "addr:street":"South St",
    "iso:country":"US",
    "sg:address":"62 South St",
    "sg:city":"Oyster Bay",
    "sg:classifiers":[
        {
            "category":"Education",
            "subcategory":"Special Training",
            "type":"Public Place"
        }
    ],
    "sg:phone":"+1 516 628 3170",
    "sg:postcode":"11771",
    "sg:province":"NY",
    "sg:tags":[
        "instruction",
        "music"
    ],
    "wof:name":"North Cove Guitar Institute",
    "wof:placetype":"venue"
},
  "geometry": {"coordinates":[-73.526994,40.874727],"type":"Point"}
}