{
  "type": "Feature",
  "properties": {
    "addr:full":"461 Evergreen Ct Central Valley NY 10917",
    "addr:housenumber":"461",
    "addr:postcode":"10917",
    "addr:street":"Evergreen Ct",
    "iso:country":"US",
    "sg:address":"461 Evergreen Ct",
    "sg:city":"Central Valley",
    "sg:classifiers":[
        {
            "category":"Manufacturing",
            "subcategory":"Apparel",
            "type":"Manufacturing & Wholesale Goods"
        }
    ],
    "sg:phone":"+1   ",
    "sg:postcode":"10917",
    "sg:province":"NY",
    "sg:tags":[
        "clothing",
        "outerwear",
        "mfg"
    ],
    "wof:name":"V F Outdoor Inc",
    "wof:placetype":"venue"
},
  "geometry": {"coordinates":[-74.126676,41.316662],"type":"Point"}
}