{
  "type": "Feature",
  "properties": {
    "iso:country":"US",
    "sg:address":"12 River St",
    "sg:city":"Batavia",
    "sg:classifiers":[
        {
            "category":"Farming",
            "subcategory":"Dairy Farm",
            "type":"Manufacturing & Wholesale Goods"
        }
    ],
    "sg:phone":"+1 585 343 1692",
    "sg:postcode":"14020",
    "sg:province":"NY",
    "wof:name":"Brantons Dairy Inc",
    "wof:placetype":"venue"
},
  "geometry": {"coordinates":[-78.20399999999999,43.003172],"type":"Point"}
}