{
  "type": "Feature",
  "properties": {
    "iso:country":"US",
    "sg:address":"4 Tobi Ln",
    "sg:city":"New City",
    "sg:classifiers":[
        {
            "category":"Building & Trades",
            "subcategory":"Construction",
            "type":"Services"
        }
    ],
    "sg:phone":"+1 845 708 0355",
    "sg:postcode":"10956",
    "sg:province":"NY",
    "sg:tags":[
        "general",
        "contractor"
    ],
    "wof:name":"CJS Contracting Inc",
    "wof:placetype":"venue"
},
  "geometry": {"coordinates":[-73.96693,41.178346],"type":"Point"}
}