{
  "type": "Feature",
  "properties": {
    "iso:country":"US",
    "sg:address":"252 E Water St",
    "sg:city":"Syracuse",
    "sg:classifiers":[
        {
            "category":"Professional",
            "subcategory":"Credit Reporting & Collection",
            "type":"Services"
        }
    ],
    "sg:phone":"+1 315 478 0057",
    "sg:postcode":"13210",
    "sg:province":"NY",
    "sg:tags":[
        "agency"
    ],
    "wof:name":"Abbott-Nicholson Svc",
    "wof:placetype":"venue"
},
  "geometry": {"coordinates":[-76.15000499999999,43.050428],"type":"Point"}
}