{
  "type": "Feature",
  "properties": {
    "iso:country":"US",
    "sg:address":"685 Oliver St",
    "sg:city":"North Tonawanda",
    "sg:classifiers":[
        {
            "category":"Bars & Pubs",
            "type":"Food & Drink"
        }
    ],
    "sg:phone":"+1 716 694 0487",
    "sg:postcode":"14120",
    "sg:province":"NY",
    "sg:tags":[
        "tavern"
    ],
    "wof:name":"Klimek's Tavern",
    "wof:placetype":"venue"
},
  "geometry": {"coordinates":[-78.88068699999999,43.041019],"type":"Point"}
}