{
  "type": "Feature",
  "properties": {
    "addr:full":"3794 County Route 4 Oswego NY 13126",
    "addr:housenumber":"3794",
    "addr:postcode":"13126",
    "addr:street":"County Route 4",
    "iso:country":"US",
    "sg:address":"3794 County Route 4",
    "sg:city":"Oswego",
    "sg:classifiers":[
        {
            "category":"Retail",
            "subcategory":"Auto Rental",
            "type":"Services"
        },
        {
            "category":"Retail",
            "subcategory":"Storage",
            "type":"Services"
        }
    ],
    "sg:phone":"+1 315 207 4010",
    "sg:postcode":"13126",
    "sg:province":"NY",
    "sg:tags":[
        "renting",
        "truck",
        "moving-self",
        "leasing",
        "trailer"
    ],
    "wof:name":"U-Haul Co",
    "wof:placetype":"venue"
},
  "geometry": {"coordinates":[-76.40080500000001,43.431899],"type":"Point"}
}