{
  "type": "Feature",
  "properties": {
    "iso:country":"US",
    "sg:address":"315 Hudson St",
    "sg:city":"New York",
    "sg:classifiers":[
        {
            "category":"Shopping",
            "subcategory":"Computers & Home Electronics",
            "type":"Retail Goods"
        }
    ],
    "sg:phone":"+1 212 366 8181",
    "sg:postcode":"10013",
    "sg:province":"NY",
    "sg:tags":[
        "software"
    ],
    "wof:name":"All Sector Technology Group",
    "wof:placetype":"venue"
},
  "geometry": {"coordinates":[-74.00757,40.726102],"type":"Point"}
}