{
  "type": "Feature",
  "properties": {
    "iso:country":"US",
    "sg:address":"63 Old Brook Rd",
    "sg:city":"Dix Hills",
    "sg:classifiers":[
        {
            "category":"Building & Trades",
            "subcategory":"Construction",
            "type":"Services"
        }
    ],
    "sg:phone":"+1 631 242 9485",
    "sg:postcode":"11746",
    "sg:province":"NY",
    "sg:tags":[
        "excavating",
        "contractor"
    ],
    "wof:name":"American Sand & Gravel",
    "wof:placetype":"venue"
},
  "geometry": {"coordinates":[-73.31700600000001,40.789446],"type":"Point"}
}