{
  "type": "Feature",
  "properties": {
    "iso:country":"US",
    "sg:address":"736 Center St",
    "sg:city":"Lewiston",
    "sg:classifiers":[
        {
            "category":"Wholesale",
            "subcategory":"Groceries",
            "type":"Manufacturing & Wholesale Goods"
        }
    ],
    "sg:phone":"+1 716 754 0795",
    "sg:postcode":"14092",
    "sg:province":"NY",
    "sg:tags":[
        "food",
        "broker"
    ],
    "wof:name":"Pnf",
    "wof:placetype":"venue"
},
  "geometry": {"coordinates":[-79.037565,43.172607],"type":"Point"}
}