{
  "type": "Feature",
  "properties": {
    "addr:full":"1052 Southern Blvd Bronx NY 10459",
    "addr:housenumber":"1052",
    "addr:postcode":"10459",
    "addr:street":"Southern Blvd",
    "iso:country":"US",
    "sg:address":"1052 Southern Blvd",
    "sg:city":"Bronx",
    "sg:classifiers":[
        {
            "category":"Shopping",
            "subcategory":"Shoes",
            "type":"Retail Goods"
        }
    ],
    "sg:phone":"+1 718 991 9212",
    "sg:postcode":"10459",
    "sg:province":"NY",
    "wof:name":"Fabco Shoes",
    "wof:placetype":"venue"
},
  "geometry": {"coordinates":[-73.891761,40.823247],"type":"Point"}
}