{
  "type": "Feature",
  "properties": {
    "iso:country":"US",
    "sg:address":"1646 Amsterdam Ave",
    "sg:city":"New York",
    "sg:classifiers":[
        {
            "category":"Professional",
            "subcategory":"Computer Services",
            "type":"Services"
        }
    ],
    "sg:phone":"+1 212 234 1210",
    "sg:postcode":"10031",
    "sg:province":"NY",
    "sg:tags":[
        "programming"
    ],
    "wof:name":"FMA Computer Solutions",
    "wof:placetype":"venue"
},
  "geometry": {"coordinates":[-73.94922,40.823084],"type":"Point"}
}