{
  "type": "Feature",
  "properties": {
    "addr:full":"415 76th St Brooklyn NY 11209",
    "addr:housenumber":"415",
    "addr:postcode":"11209",
    "addr:street":"76Th St",
    "iso:country":"US",
    "sg:address":"415 76th St",
    "sg:city":"Brooklyn",
    "sg:classifiers":[
        {
            "category":"Professional",
            "subcategory":"Engineering",
            "type":"Services"
        }
    ],
    "sg:phone":"+1 718 745 5795",
    "sg:postcode":"11209",
    "sg:province":"NY",
    "sg:tags":[
        "engineer"
    ],
    "wof:name":"Urban Engineering",
    "wof:placetype":"venue"
},
  "geometry": {"coordinates":[-74.023174,40.628961],"type":"Point"}
}