{
  "type": "Feature",
  "properties": {
    "addr:full":"636 Palisade Ave Yonkers NY 10703",
    "addr:housenumber":"636",
    "addr:postcode":"10703",
    "addr:street":"Palisade Ave",
    "iso:country":"US",
    "sg:address":"636 Palisade Ave",
    "sg:city":"Yonkers",
    "sg:classifiers":[
        {
            "category":"Organizations",
            "subcategory":"Religious Organization",
            "type":"Services"
        }
    ],
    "sg:phone":"+1 914 965 4967",
    "sg:postcode":"10703",
    "sg:province":"NY",
    "sg:tags":[
        "church"
    ],
    "wof:name":"St Paul's Episcopal Church",
    "wof:placetype":"venue"
},
  "geometry": {"coordinates":[-73.887759,40.954449],"type":"Point"}
}