{
  "type": "Feature",
  "properties": {
    "addr:full":"31 Main St East Rockaway NY 11518",
    "addr:housenumber":"31",
    "addr:postcode":"11518",
    "addr:street":"Main St East",
    "iso:country":"US",
    "sg:address":"31 Main St",
    "sg:city":"East Rockaway",
    "sg:classifiers":[
        {
            "category":"Sports & Exercise",
            "subcategory":"Gym",
            "type":"Entertainment"
        }
    ],
    "sg:phone":"+1   ",
    "sg:postcode":"11518",
    "sg:province":"NY",
    "sg:tags":[
        "fitness",
        "physical",
        "facility"
    ],
    "wof:name":"NS Fitness Inc",
    "wof:placetype":"venue"
},
  "geometry": {"coordinates":[-73.66127,40.639738],"type":"Point"}
}