{
  "type": "Feature",
  "properties": {
    "iso:country":"US",
    "sg:address":"11 Birchwood Ct E",
    "sg:city":"Syosset",
    "sg:classifiers":[
        {
            "category":"Shopping",
            "subcategory":"News",
            "type":"Retail Goods"
        }
    ],
    "sg:phone":"+1   ",
    "sg:postcode":"11791",
    "sg:province":"NY",
    "wof:name":"Madhumehta News Stand Inc",
    "wof:placetype":"venue"
},
  "geometry": {"coordinates":[-73.50457400000001,40.790914],"type":"Point"}
}