{
  "type": "Feature",
  "properties": {
    "iso:country":"US",
    "sg:address":"38-17 Main St",
    "sg:city":"Flushing",
    "sg:classifiers":[
        {
            "category":"Banks & Credit Unions",
            "subcategory":"Bank",
            "type":"Services"
        }
    ],
    "sg:phone":"+1 718 460 1798",
    "sg:postcode":"11354",
    "sg:province":"NY",
    "sg:website":"www.citibank.com",
    "wof:name":"Citibank",
    "wof:placetype":"venue"
},
  "geometry": {"coordinates":[-73.83046400000001,40.760553],"type":"Point"}
}