{
  "type": "Feature",
  "properties": {
    "addr:full":"377 Hoffman Ln Hauppauge NY 11788",
    "addr:housenumber":"377",
    "addr:postcode":"11788",
    "addr:street":"Hoffman Ln",
    "iso:country":"US",
    "sg:address":"377 Hoffman Ln",
    "sg:city":"Hauppauge",
    "sg:classifiers":[
        {
            "category":"Farming",
            "subcategory":"Farm & Veterinary Services",
            "type":"Manufacturing & Wholesale Goods"
        }
    ],
    "sg:phone":"+1 631 582 5810",
    "sg:postcode":"11788",
    "sg:province":"NY",
    "wof:name":"Saddlebrook Farm",
    "wof:placetype":"venue"
},
  "geometry": {"coordinates":[-73.18635,40.81688],"type":"Point"}
}