{
  "type": "Feature",
  "properties": {
    "addr:full":"133 New York Ave Huntington NY 11743",
    "addr:housenumber":"133",
    "addr:postcode":"11743",
    "addr:street":"New York Ave",
    "iso:country":"US",
    "sg:address":"133 New York Ave",
    "sg:city":"Huntington",
    "sg:classifiers":[
        {
            "category":"Wholesale",
            "subcategory":"Office Equipment",
            "type":"Manufacturing & Wholesale Goods"
        }
    ],
    "sg:phone":"+1 631 385 7390",
    "sg:postcode":"11743",
    "sg:province":"NY",
    "sg:tags":[
        "credit"
    ],
    "wof:name":"A-D Millennium Corp",
    "wof:placetype":"venue"
},
  "geometry": {"coordinates":[-73.418738,40.884611],"type":"Point"}
}