{
  "type": "Feature",
  "properties": {
    "iso:country":"US",
    "sg:address":"2771 Scottsville Rd",
    "sg:city":"Scottsville",
    "sg:classifiers":[
        {
            "category":"Restaurant",
            "type":"Food & Drink"
        }
    ],
    "sg:phone":"+1 585 889 1400",
    "sg:postcode":"14546",
    "sg:province":"NY",
    "sg:tags":[
        "eating"
    ],
    "wof:name":"Pando's Family Restaurant",
    "wof:placetype":"venue"
},
  "geometry": {"coordinates":[-77.738556,43.036195],"type":"Point"}
}