{
  "type": "Feature",
  "properties": {
    "iso:country":"US",
    "sg:address":"11 Waterview Dr",
    "sg:city":"Centerport",
    "sg:classifiers":[
        {
            "category":"Real Estate",
            "subcategory":"Architect",
            "type":"Services"
        }
    ],
    "sg:phone":"+1 631 424 4881",
    "sg:postcode":"11721",
    "sg:province":"NY",
    "sg:tags":[
        "architects'",
        "specification",
        "construction",
        "builders'",
        "architectural"
    ],
    "wof:name":"David P. Mcgullam, Architect, P.C.",
    "wof:placetype":"venue"
},
  "geometry": {"coordinates":[-73.366657,40.893367],"type":"Point"}
}