{
  "type": "Feature",
  "properties": {
    "addr:full":"1607 York Ave At 85th St New York NY 10028",
    "addr:housenumber":"1607",
    "addr:postcode":"10028",
    "addr:street":"York Ave At 85Th St",
    "iso:country":"US",
    "sg:address":"1607 York Ave At 85th St",
    "sg:city":"New York",
    "sg:classifiers":[
        {
            "category":"Bars & Pubs",
            "type":"Food & Drink"
        }
    ],
    "sg:phone":"+1 212 650 1341",
    "sg:postcode":"10028",
    "sg:province":"NY",
    "wof:name":"Bailey's Corner Pub",
    "wof:placetype":"venue"
},
  "geometry": {"coordinates":[-73.94774,40.775071],"type":"Point"}
}