{
  "type": "Feature",
  "properties": {
    "iso:country":"US",
    "sg:address":"8630 Broadway Ste 2B",
    "sg:city":"Elmhurst",
    "sg:classifiers":[
        {
            "category":"Health Services",
            "subcategory":"Dentist",
            "type":"Services"
        }
    ],
    "sg:phone":"+1 718 760 5500",
    "sg:postcode":"11373",
    "sg:province":"NY",
    "wof:name":"Today's Dental",
    "wof:placetype":"venue"
},
  "geometry": {"coordinates":[-73.877224,40.737713],"type":"Point"}
}