{
  "type": "Feature",
  "properties": {
    "addr:full":"1301 8th Avenue Brooklyn NY 11215",
    "addr:housenumber":"1301",
    "addr:postcode":"11215",
    "addr:street":"8Th Avenue",
    "iso:country":"US",
    "sg:address":"1301 8th Avenue",
    "sg:city":"Brooklyn",
    "sg:classifiers":[
        {
            "category":"Education",
            "subcategory":"School",
            "type":"Public Place"
        }
    ],
    "sg:phone":"+1 718 330 9340",
    "sg:postcode":"11215",
    "sg:province":"NY",
    "sg:tags":[
        "high",
        "middle",
        "elementary"
    ],
    "wof:name":"N Y City of",
    "wof:placetype":"venue"
},
  "geometry": {"coordinates":[-73.981262,40.663088],"type":"Point"}
}