{
  "type": "Feature",
  "properties": {
    "iso:country":"US",
    "sg:address":"2080 Coney Island Ave",
    "sg:city":"Brooklyn",
    "sg:phone":"+1 718 259 5993",
    "sg:postcode":"11223",
    "sg:province":"NY",
    "wof:name":"Zest Designs Tailoring Boutiqu",
    "wof:placetype":"venue"
},
  "geometry": {"coordinates":[-73.961811,40.606701],"type":"Point"}
}