{
  "type": "Feature",
  "properties": {
    "iso:country":"US",
    "sg:address":"9105 4th Ave",
    "sg:city":"Brooklyn",
    "sg:classifiers":[
        {
            "category":"Retail",
            "subcategory":"Repair Shop",
            "type":"Services"
        }
    ],
    "sg:phone":"+1 718 535 9114",
    "sg:postcode":"11209",
    "sg:province":"NY",
    "sg:tags":[
        "lock",
        "locksmith"
    ],
    "wof:name":"24 Hour A Day Locksmith",
    "wof:placetype":"venue"
},
  "geometry": {"coordinates":[-74.030092,40.618351],"type":"Point"}
}