{
  "type": "Feature",
  "properties": {
    "addr:full":"310 W 259th St Bronx NY 10471",
    "addr:housenumber":"310",
    "addr:postcode":"10471",
    "addr:street":"W 259Th St",
    "iso:country":"US",
    "sg:address":"310 W 259th St",
    "sg:city":"Bronx",
    "sg:classifiers":[
        {
            "category":"Banks & Credit Unions",
            "subcategory":"Bank",
            "type":"Services"
        }
    ],
    "sg:phone":"+1 718 884 3279",
    "sg:postcode":"10471",
    "sg:province":"NY",
    "sg:tags":[
        "loan",
        "real estate"
    ],
    "wof:name":"Easy Commercial Funding",
    "wof:placetype":"venue"
},
  "geometry": {"coordinates":[-73.90025900000001,40.906644],"type":"Point"}
}