{
  "type": "Feature",
  "properties": {
    "addr:full":"1636 E 14th St Brooklyn NY 11229",
    "addr:housenumber":"1636",
    "addr:postcode":"11229",
    "addr:street":"E 14Th St",
    "iso:country":"US",
    "sg:address":"1636 E 14th St",
    "sg:city":"Brooklyn",
    "sg:classifiers":[
        {
            "category":"Health Services",
            "subcategory":"Doctor",
            "type":"Services"
        }
    ],
    "sg:phone":"+1 718 627 2400",
    "sg:postcode":"11229",
    "sg:province":"NY",
    "wof:name":"Shamah Morris MD",
    "wof:placetype":"venue"
},
  "geometry": {"coordinates":[-73.959396,40.609501],"type":"Point"}
}