{
  "type": "Feature",
  "properties": {
    "addr:full":"428 Menahan St Flushing NY 11237",
    "addr:housenumber":"428",
    "addr:postcode":"11237",
    "addr:street":"Menahan St",
    "iso:country":"US",
    "sg:address":"428 Menahan St",
    "sg:city":"Flushing",
    "sg:classifiers":[
        {
            "category":"Professional",
            "type":"Services"
        }
    ],
    "sg:phone":"+1 718 417 6255",
    "sg:postcode":"11237",
    "sg:province":"NY",
    "sg:tags":[
        "establishment"
    ],
    "wof:name":"Catania Caffe",
    "wof:placetype":"venue"
},
  "geometry": {"coordinates":[-73.912485,40.702747],"type":"Point"}
}