{
  "type": "Feature",
  "properties": {
    "addr:full":"4141 W Main Street Rd Batavia NY 14020",
    "addr:housenumber":"4141",
    "addr:postcode":"14020",
    "addr:street":"W Main Street Rd",
    "iso:country":"US",
    "sg:address":"4141 W Main Street Rd",
    "sg:city":"Batavia",
    "sg:classifiers":[
        {
            "category":"Personal",
            "subcategory":"Beauty Salon",
            "type":"Services"
        }
    ],
    "sg:phone":"+1 585 343 5512",
    "sg:postcode":"14020",
    "sg:province":"NY",
    "wof:name":"Batavia Beautique",
    "wof:placetype":"venue"
},
  "geometry": {"coordinates":[-78.206281,43.005872],"type":"Point"}
}