{
  "type": "Feature",
  "properties": {
    "addr:full":"304 W Seneca St Manlius NY 13104",
    "addr:housenumber":"304",
    "addr:postcode":"13104",
    "addr:street":"W Seneca St",
    "iso:country":"US",
    "sg:address":"304 W Seneca St",
    "sg:city":"Manlius",
    "sg:classifiers":[
        {
            "category":"Social Services",
            "subcategory":"Child Care",
            "type":"Services"
        }
    ],
    "sg:phone":"+1 315 682 4250",
    "sg:postcode":"13104",
    "sg:province":"NY",
    "wof:name":"TEDDY Time Day Care",
    "wof:placetype":"venue"
},
  "geometry": {"coordinates":[-75.9877,42.996598],"type":"Point"}
}