{
  "type": "Feature",
  "properties": {
    "iso:country":"US",
    "sg:address":"1001 Avenue of the Americas Rm 302",
    "sg:city":"New York",
    "sg:classifiers":[
        {
            "category":"Shopping",
            "subcategory":"Optician",
            "type":"Retail Goods"
        }
    ],
    "sg:phone":"+1 212 921 2510",
    "sg:postcode":"10018",
    "sg:province":"NY",
    "sg:tags":[
        "eyewear"
    ],
    "wof:name":"Icon Eyewear",
    "wof:placetype":"venue"
},
  "geometry": {"coordinates":[-73.98653299999999,40.751783],"type":"Point"}
}