{
  "type": "Feature",
  "properties": {
    "addr:full":"511 E 163rd Street Bronx NY 10451",
    "addr:housenumber":"511",
    "addr:postcode":"10451",
    "addr:street":"E 163Rd Street",
    "iso:country":"US",
    "sg:address":"511 E 163rd Street",
    "sg:city":"Bronx",
    "sg:classifiers":[
        {
            "category":"Restaurant",
            "type":"Food & Drink"
        }
    ],
    "sg:phone":"+1 718 292 3411",
    "sg:postcode":"10451",
    "sg:province":"NY",
    "sg:tags":[
        "chinese"
    ],
    "wof:name":"Merry Land Chinese Buffet",
    "wof:placetype":"venue"
},
  "geometry": {"coordinates":[-73.9089,40.824241],"type":"Point"}
}