{
  "type": "Feature",
  "properties": {
    "addr:full":"6315 New Utrecht Ave Brooklyn NY 11219",
    "addr:housenumber":"6315",
    "addr:postcode":"11219",
    "addr:street":"New Utrecht Ave",
    "iso:country":"US",
    "sg:address":"6315 New Utrecht Ave",
    "sg:city":"Brooklyn",
    "sg:classifiers":[
        {
            "category":"Retail",
            "subcategory":"Auto Repair",
            "type":"Services"
        }
    ],
    "sg:phone":"+1 718 837 1135",
    "sg:postcode":"11219",
    "sg:province":"NY",
    "sg:tags":[
        "repairing",
        "automobile"
    ],
    "wof:name":"Nunzi's Automotive",
    "wof:placetype":"venue"
},
  "geometry": {"coordinates":[-73.99720000000001,40.624802],"type":"Point"}
}