{
  "type": "Feature",
  "properties": {
    "iso:country":"US",
    "sg:address":"71 Gage Rd",
    "sg:city":"Schoharie",
    "sg:classifiers":[
        {
            "category":"Farming",
            "subcategory":"Livestock Farm",
            "type":"Manufacturing & Wholesale Goods"
        }
    ],
    "sg:phone":"+1 518 872 1102",
    "sg:postcode":"12157",
    "sg:province":"NY",
    "sg:tags":[
        "beef",
        "feedlot",
        "cattle"
    ],
    "wof:name":"Duincans Greenhouse",
    "wof:placetype":"venue"
},
  "geometry": {"coordinates":[-74.164243,42.669444],"type":"Point"}
}