{
  "type": "Feature",
  "properties": {
    "addr:full":"2760 Union Rd Buffalo NY 14227",
    "addr:housenumber":"2760",
    "addr:postcode":"14227",
    "addr:street":"Union Rd",
    "iso:country":"US",
    "sg:address":"2760 Union Rd",
    "sg:city":"Buffalo",
    "sg:classifiers":[
        {
            "category":"Restaurant",
            "type":"Food & Drink"
        },
        {
            "category":"Ice Cream",
            "type":"Food & Drink"
        }
    ],
    "sg:menulink":"http://www.allmenus.com/ny/cheektowaga/98766-friendlys/menu/",
    "sg:phone":"+1 716 683 1015",
    "sg:postcode":"14227",
    "sg:province":"NY",
    "sg:tags":[
        "burger",
        "american",
        "ice",
        "cream"
    ],
    "wof:name":"Friendly's",
    "wof:placetype":"venue"
},
  "geometry": {"coordinates":[-78.754752,42.887352],"type":"Point"}
}