{
  "type": "Feature",
  "properties": {
    "addr:full":"1737 Orchard Park Rd Buffalo NY 14224",
    "addr:housenumber":"1737",
    "addr:postcode":"14224",
    "addr:street":"Orchard Park Rd",
    "iso:country":"US",
    "sg:address":"1737 Orchard Park Rd",
    "sg:city":"Buffalo",
    "sg:classifiers":[
        {
            "category":"Fast Food",
            "type":"Food & Drink"
        },
        {
            "category":"Restaurant",
            "type":"Food & Drink"
        }
    ],
    "sg:phone":"+1 716 674 9066",
    "sg:postcode":"14224",
    "sg:province":"NY",
    "sg:tags":[
        "take",
        "pizza"
    ],
    "wof:name":"Nino's Pizzeria",
    "wof:placetype":"venue"
},
  "geometry": {"coordinates":[-78.756522,42.805123],"type":"Point"}
}