{
  "type": "Feature",
  "properties": {
    "iso:country":"US",
    "sg:address":"505 Post Ave",
    "sg:city":"Westbury",
    "sg:classifiers":[
        {
            "category":"Professional",
            "subcategory":"Accounting & Tax Preparation",
            "type":"Services"
        }
    ],
    "sg:phone":"+1 516 338 0200",
    "sg:postcode":"11590",
    "sg:province":"NY",
    "sg:tags":[
        "accountant"
    ],
    "wof:name":"Levy Howard E PC",
    "wof:placetype":"venue"
},
  "geometry": {"coordinates":[-73.58699799999999,40.7645],"type":"Point"}
}