{
  "type": "Feature",
  "properties": {
    "addr:full":"340 Jefferson Rd Rochester NY 14623",
    "addr:housenumber":"340",
    "addr:postcode":"14623",
    "addr:street":"Jefferson Rd",
    "iso:country":"US",
    "sg:address":"340 Jefferson Rd",
    "sg:city":"Rochester",
    "sg:classifiers":[
        {
            "category":"Retail",
            "subcategory":"Car Wash",
            "type":"Services"
        }
    ],
    "sg:phone":"+1 585 272 0320",
    "sg:postcode":"14623",
    "sg:province":"NY",
    "sg:tags":[
        "polishing",
        "washing"
    ],
    "sg:website":"www.kleecorp.com",
    "wof:name":"Klee's Carwash",
    "wof:placetype":"venue"
},
  "geometry": {"coordinates":[-77.64154000000001,43.089416],"type":"Point"}
}