{
  "type": "Feature",
  "properties": {
    "addr:full":"4 Martine Ave White Plains NY 10606",
    "addr:housenumber":"4",
    "addr:postcode":"10606",
    "addr:street":"Martine Ave",
    "iso:country":"US",
    "sg:address":"4 Martine Ave",
    "sg:city":"White Plains",
    "sg:classifiers":[
        {
            "category":"Health Services",
            "subcategory":"Doctor",
            "type":"Services"
        }
    ],
    "sg:phone":"+1 914 686 3291",
    "sg:postcode":"10606",
    "sg:province":"NY",
    "sg:tags":[
        "dentist"
    ],
    "wof:name":"Levine Stanley DDS Ofc",
    "wof:placetype":"venue"
},
  "geometry": {"coordinates":[-73.77219100000001,41.030414],"type":"Point"}
}