{
  "type": "Feature",
  "properties": {
    "iso:country":"US",
    "sg:address":"272 Mill St",
    "sg:city":"Poughkeepsie",
    "sg:classifiers":[
        {
            "category":"Professional",
            "subcategory":"Lawyer & Legal Services",
            "type":"Services"
        }
    ],
    "sg:phone":"+1   ",
    "sg:postcode":"12601",
    "sg:province":"NY",
    "sg:tags":[
        "car"
    ],
    "wof:name":"Benvie Group",
    "wof:placetype":"venue"
},
  "geometry": {"coordinates":[-73.92692599999999,41.705126],"type":"Point"}
}