{
  "type": "Feature",
  "properties": {
    "addr:full":"477 Central Park W New York NY 10025",
    "addr:housenumber":"477",
    "addr:postcode":"10025",
    "addr:street":"Central Park W",
    "iso:country":"US",
    "sg:address":"477 Central Park W",
    "sg:city":"New York",
    "sg:classifiers":[
        {
            "category":"Real Estate",
            "subcategory":"Real Estate Operator",
            "type":"Services"
        }
    ],
    "sg:phone":"+1 212 243 6722",
    "sg:postcode":"10025",
    "sg:province":"NY",
    "sg:tags":[
        "building",
        "apartment"
    ],
    "wof:name":"477 Central Park West Owners",
    "wof:placetype":"venue"
},
  "geometry": {"coordinates":[-73.959537,40.798719],"type":"Point"}
}