{
  "type": "Feature",
  "properties": {
    "addr:full":"3 Sandfort Ln Warwick NY 10990",
    "addr:housenumber":"3",
    "addr:postcode":"10990",
    "addr:street":"Sandfort Ln",
    "iso:country":"US",
    "sg:address":"3 Sandfort Ln",
    "sg:city":"Warwick",
    "sg:classifiers":[
        {
            "category":"Building & Trades",
            "subcategory":"Construction",
            "type":"Services"
        }
    ],
    "sg:phone":"+1 845 987 7982",
    "sg:postcode":"10990",
    "sg:province":"NY",
    "sg:tags":[
        "nonresidential"
    ],
    "wof:name":"Stone Bridge Associates",
    "wof:placetype":"venue"
},
  "geometry": {"coordinates":[-74.343547,41.268247],"type":"Point"}
}