{
  "type": "Feature",
  "properties": {
    "iso:country":"US",
    "sg:address":"RR 6",
    "sg:city":"Mahopac Falls",
    "sg:classifiers":[
        {
            "category":"Food & Beverages",
            "subcategory":"Groceries & Convenience Stores",
            "type":"Retail Goods"
        }
    ],
    "sg:phone":"+1 845 628 3406",
    "sg:postcode":"10542",
    "sg:province":"NY",
    "wof:name":"Red Mills Mkt Inc",
    "wof:placetype":"venue"
},
  "geometry": {"coordinates":[-73.76149700000001,41.374401],"type":"Point"}
}