{
  "type": "Feature",
  "properties": {
    "addr:full":"11 Nassau Ave Melville NY 11751",
    "addr:housenumber":"11",
    "addr:postcode":"11751",
    "addr:street":"Nassau Ave",
    "iso:country":"US",
    "sg:address":"11 Nassau Ave",
    "sg:city":"Melville",
    "sg:classifiers":[
        {
            "category":"Building & Trades",
            "subcategory":"Plumbing",
            "type":"Services"
        }
    ],
    "sg:phone":"+1 631 360 4900",
    "sg:postcode":"11751",
    "sg:province":"NY",
    "sg:tags":[
        "plumbing",
        "contractor"
    ],
    "wof:name":"Suffolk Plumbing & Sewer",
    "wof:placetype":"venue"
},
  "geometry": {"coordinates":[-73.210842,40.730738],"type":"Point"}
}