{
  "type": "Feature",
  "properties": {
    "addr:full":"310 Ivy Ave Westbury NY 11590",
    "addr:housenumber":"310",
    "addr:postcode":"11590",
    "addr:street":"Ivy Ave",
    "iso:country":"US",
    "sg:address":"310 Ivy Ave",
    "sg:city":"Westbury",
    "sg:classifiers":[
        {
            "category":"Building & Trades",
            "subcategory":"Plumbing",
            "type":"Services"
        },
        {
            "category":"Home & Garden",
            "subcategory":"Garden Supply",
            "type":"Retail Goods"
        }
    ],
    "sg:phone":"+1 516 334 1310",
    "sg:postcode":"11590",
    "sg:province":"NY",
    "sg:tags":[
        "sprinkler",
        "contractor"
    ],
    "wof:name":"A B C Irrigations",
    "wof:placetype":"venue"
},
  "geometry": {"coordinates":[-73.596485,40.757422],"type":"Point"}
}