{
  "type": "Feature",
  "properties": {
    "addr:full":"40 Central Pkwy Medford NY 11763",
    "addr:housenumber":"40",
    "addr:postcode":"11763",
    "addr:street":"Central Pkwy",
    "iso:country":"US",
    "sg:address":"40 Central Pkwy",
    "sg:city":"Medford",
    "sg:classifiers":[
        {
            "category":"Organizations",
            "subcategory":"Religious Organization",
            "type":"Services"
        }
    ],
    "sg:phone":"+1 631 732 3816",
    "sg:postcode":"11763",
    "sg:province":"NY",
    "wof:name":"Cornerstone New Cvenant Church",
    "wof:placetype":"venue"
},
  "geometry": {"coordinates":[-72.964935,40.855494],"type":"Point"}
}