{
  "type": "Feature",
  "properties": {
    "iso:country":"US",
    "sg:address":"41 Chestnut St",
    "sg:city":"Jamestown",
    "sg:classifiers":[
        {
            "category":"Professional",
            "subcategory":"Lawyer & Legal Services",
            "type":"Services"
        }
    ],
    "sg:phone":"+1   ",
    "sg:postcode":"14701",
    "sg:province":"NY",
    "wof:name":"Westman & Assoc",
    "wof:placetype":"venue"
},
  "geometry": {"coordinates":[-79.233329,42.109283],"type":"Point"}
}