{
  "type": "Feature",
  "properties": {
    "iso:country":"US",
    "sg:address":"1 Riverside Ct",
    "sg:city":"Stillwater",
    "sg:classifiers":[
        {
            "category":"Building & Trades",
            "subcategory":"Construction",
            "type":"Services"
        }
    ],
    "sg:phone":"+1 518 664 4214",
    "sg:postcode":"12170",
    "sg:province":"NY",
    "sg:tags":[
        "windows-repair",
        "installation",
        "replacement"
    ],
    "wof:name":"Capital District Windows & Doors",
    "wof:placetype":"venue"
},
  "geometry": {"coordinates":[-73.634872,42.958961],"type":"Point"}
}