{
  "type": "Feature",
  "properties": {
    "iso:country":"US",
    "sg:address":"203 W Main St",
    "sg:city":"Endicott",
    "sg:classifiers":[
        {
            "category":"Shopping",
            "subcategory":"Pharmacy",
            "type":"Retail Goods"
        }
    ],
    "sg:phone":"+1 607 748 7339",
    "sg:postcode":"13760",
    "sg:province":"NY",
    "wof:name":"Eckerd Pharmacy",
    "wof:placetype":"venue"
},
  "geometry": {"coordinates":[-76.068572,42.094864],"type":"Point"}
}