{
  "type": "Feature",
  "properties": {
    "addr:full":"5 Devon Pl Southampton NY 11968",
    "addr:housenumber":"5",
    "addr:postcode":"11968",
    "addr:street":"Devon Pl",
    "iso:country":"US",
    "sg:address":"5 Devon Pl",
    "sg:city":"Southampton",
    "sg:classifiers":[
        {
            "category":"Manufacturing",
            "subcategory":"Tools & Machinery",
            "type":"Manufacturing & Wholesale Goods"
        }
    ],
    "sg:phone":"+1   ",
    "sg:postcode":"11968",
    "sg:province":"NY",
    "sg:tags":[
        "devices",
        "mfg"
    ],
    "wof:name":"Biomet Partners Inc",
    "wof:placetype":"venue"
},
  "geometry": {"coordinates":[-72.395622,40.955194],"type":"Point"}
}