{
  "type": "Feature",
  "properties": {
    "addr:full":"219 Cook St Brooklyn NY 11206",
    "addr:housenumber":"219",
    "addr:postcode":"11206",
    "addr:street":"Cook St",
    "iso:country":"US",
    "sg:address":"219 Cook St",
    "sg:city":"Brooklyn",
    "sg:classifiers":[
        {
            "category":"Building & Trades",
            "subcategory":"Construction",
            "type":"Services"
        }
    ],
    "sg:phone":"+1 718 366 6565",
    "sg:postcode":"11206",
    "sg:province":"NY",
    "sg:tags":[
        "security",
        "manufacturer"
    ],
    "wof:name":"Avant Guard Manufacturing",
    "wof:placetype":"venue"
},
  "geometry": {"coordinates":[-73.93291499999999,40.703628],"type":"Point"}
}