{
  "type": "Feature",
  "properties": {
    "iso:country":"US",
    "sg:address":"542 Thurston Rd",
    "sg:city":"Rochester",
    "sg:classifiers":[
        {
            "category":"Retail",
            "subcategory":"Auto Repair",
            "type":"Services"
        }
    ],
    "sg:phone":"+1   ",
    "sg:postcode":"14619",
    "sg:province":"NY",
    "sg:tags":[
        "station",
        "gasoline",
        "general"
    ],
    "wof:name":"Thurston Garage",
    "wof:placetype":"venue"
},
  "geometry": {"coordinates":[-77.650874,43.133977],"type":"Point"}
}