{
  "type": "Feature",
  "properties": {
    "addr:full":"4801 Tilden Ave Brooklyn NY 11203",
    "addr:housenumber":"4801",
    "addr:postcode":"11203",
    "addr:street":"Tilden Ave",
    "iso:country":"US",
    "sg:address":"4801 Tilden Ave",
    "sg:city":"Brooklyn",
    "sg:classifiers":[
        {
            "category":"Freight",
            "type":"Transportation"
        }
    ],
    "sg:phone":"+1 718 346 7844",
    "sg:postcode":"11203",
    "sg:province":"NY",
    "sg:tags":[
        "commercial",
        "storage"
    ],
    "wof:name":"Self Auto Supplies",
    "wof:placetype":"venue"
},
  "geometry": {"coordinates":[-73.931005,40.648118],"type":"Point"}
}