{
  "type": "Feature",
  "properties": {
    "addr:full":"800 2 Ave New York NY 10017",
    "addr:housenumber":"800",
    "addr:postcode":"10017",
    "addr:street":"2 Ave",
    "iso:country":"US",
    "sg:address":"800 2 Ave",
    "sg:city":"New York",
    "sg:classifiers":[
        {
            "category":"Personal",
            "subcategory":"Beauty Salon",
            "type":"Services"
        }
    ],
    "sg:phone":"+1 212 867 4716",
    "sg:postcode":"10017",
    "sg:province":"NY",
    "wof:name":"Jean Louis David",
    "wof:placetype":"venue"
},
  "geometry": {"coordinates":[-73.972692,40.749157],"type":"Point"}
}