{
  "type": "Feature",
  "properties": {
    "addr:full":"83 Astor Ave St James NY 11780",
    "addr:housenumber":"83",
    "addr:postcode":"11780",
    "addr:street":"Astor Ave",
    "iso:country":"US",
    "sg:address":"83 Astor Ave",
    "sg:city":"St James",
    "sg:classifiers":[
        {
            "category":"Professional",
            "type":"Services"
        }
    ],
    "sg:phone":"+1 631 584 6961",
    "sg:postcode":"11780",
    "sg:province":"NY",
    "sg:tags":[
        "establishment"
    ],
    "wof:name":"RJR Development Corp",
    "wof:placetype":"venue"
},
  "geometry": {"coordinates":[-73.147231,40.866359],"type":"Point"}
}