{
  "type": "Feature",
  "properties": {
    "addr:full":"1489 West Avenue Bronx NY 10462",
    "addr:housenumber":"1489",
    "addr:postcode":"10462",
    "addr:street":"West Avenue",
    "iso:country":"US",
    "sg:address":"1489 West Avenue",
    "sg:city":"Bronx",
    "sg:classifiers":[
        {
            "category":"Food & Beverages",
            "subcategory":"Groceries & Convenience Stores",
            "type":"Retail Goods"
        }
    ],
    "sg:phone":"+1 718 822 2922",
    "sg:postcode":"10462",
    "sg:province":"NY",
    "wof:name":"Food Town",
    "wof:placetype":"venue"
},
  "geometry": {"coordinates":[-73.86139,40.836654],"type":"Point"}
}