{
  "type": "Feature",
  "properties": {
    "addr:full":"191 W 52nd St New York NY 10019",
    "addr:housenumber":"191",
    "addr:postcode":"10019",
    "addr:street":"W 52Nd St",
    "iso:country":"US",
    "sg:address":"191 W 52nd St",
    "sg:city":"New York",
    "sg:classifiers":[
        {
            "category":"Shopping",
            "type":"Retail Goods"
        }
    ],
    "sg:phone":"+1   ",
    "sg:postcode":"10019",
    "sg:province":"NY",
    "sg:tags":[
        "merchandise"
    ],
    "wof:name":"Nact Telecommunications Inc",
    "wof:placetype":"venue"
},
  "geometry": {"coordinates":[-73.98034,40.761311],"type":"Point"}
}