{
  "type": "Feature",
  "properties": {
    "addr:full":"4 Harford Dr Coram NY 11727",
    "addr:housenumber":"4",
    "addr:postcode":"11727",
    "addr:street":"Harford Dr",
    "iso:country":"US",
    "sg:address":"4 Harford Dr",
    "sg:city":"Coram",
    "sg:classifiers":[
        {
            "category":"Wholesale",
            "subcategory":"Drugs",
            "type":"Manufacturing & Wholesale Goods"
        }
    ],
    "sg:phone":"+1 631 698 4347",
    "sg:postcode":"11727",
    "sg:province":"NY",
    "wof:name":"Creative Generations",
    "wof:placetype":"venue"
},
  "geometry": {"coordinates":[-73.020173,40.875333],"type":"Point"}
}