{
  "type": "Feature",
  "properties": {
    "addr:full":"13529 40th Rd Flushing NY 11354",
    "addr:housenumber":"13529",
    "addr:postcode":"11354",
    "addr:street":"40Th Rd",
    "iso:country":"US",
    "sg:address":"13529 40th Rd",
    "sg:city":"Flushing",
    "sg:classifiers":[
        {
            "category":"Personal",
            "subcategory":"Beauty Salon",
            "type":"Services"
        }
    ],
    "sg:phone":"+1 718 888 1508",
    "sg:postcode":"11354",
    "sg:province":"NY",
    "sg:tags":[
        "hair"
    ],
    "wof:name":"Amy Beauty Salon",
    "wof:placetype":"venue"
},
  "geometry": {"coordinates":[-73.830101,40.7589],"type":"Point"}
}