{
  "type": "Feature",
  "properties": {
    "addr:full":"698 Warburton Ave Yonkers NY 10701",
    "addr:housenumber":"698",
    "addr:postcode":"10701",
    "addr:street":"Warburton Ave",
    "iso:country":"US",
    "sg:address":"698 Warburton Ave",
    "sg:city":"Yonkers",
    "sg:classifiers":[
        {
            "category":"Building & Trades",
            "subcategory":"Cleaning & Sanitation",
            "type":"Services"
        },
        {
            "category":"Building & Trades",
            "subcategory":"Construction",
            "type":"Services"
        }
    ],
    "sg:phone":"+1 646 758 0629",
    "sg:postcode":"10701",
    "sg:province":"NY",
    "sg:tags":[
        "roofing",
        "washing",
        "power",
        "deck",
        "altering",
        "painting",
        "handyman",
        "contractor",
        "treatment",
        "remodeling"
    ],
    "wof:name":"A & T Painting & Renovations Corp.",
    "wof:placetype":"venue"
},
  "geometry": {"coordinates":[-73.893129,40.959887],"type":"Point"}
}