{
  "type": "Feature",
  "properties": {
    "addr:full":"1310 Broadway Hewlett NY 11557",
    "addr:housenumber":"1310",
    "addr:postcode":"11557",
    "addr:street":"Broadway",
    "iso:country":"US",
    "sg:address":"1310 Broadway",
    "sg:city":"Hewlett",
    "sg:classifiers":[
        {
            "category":"Shopping",
            "subcategory":"Shoes",
            "type":"Retail Goods"
        }
    ],
    "sg:phone":"+1 516 569 2428",
    "sg:postcode":"11557",
    "sg:province":"NY",
    "sg:tags":[
        "store"
    ],
    "wof:name":"Broadway Bootery",
    "wof:placetype":"venue"
},
  "geometry": {"coordinates":[-73.700996,40.638599],"type":"Point"}
}