{
  "type": "Feature",
  "properties": {
    "addr:full":"416 W 46th St New York NY 10036",
    "addr:housenumber":"416",
    "addr:postcode":"10036",
    "addr:street":"W 46Th St",
    "iso:country":"US",
    "sg:address":"416 W 46th St",
    "sg:city":"New York",
    "sg:classifiers":[
        {
            "category":"Fast Food",
            "type":"Food & Drink"
        }
    ],
    "sg:phone":"+1 212 489 2992",
    "sg:postcode":"10036",
    "sg:province":"NY",
    "sg:tags":[
        "burger"
    ],
    "wof:name":"Best Burgers & Shakes",
    "wof:placetype":"venue"
},
  "geometry": {"coordinates":[-73.991891,40.761202],"type":"Point"}
}