{
  "type": "Feature",
  "properties": {
    "addr:full":"1381 Castle Hill Ave Bronx NY 10462",
    "addr:housenumber":"1381",
    "addr:postcode":"10462",
    "addr:street":"Castle Hill Ave",
    "iso:country":"US",
    "sg:address":"1381 Castle Hill Ave",
    "sg:city":"Bronx",
    "sg:classifiers":[
        {
            "category":"Health Services",
            "subcategory":"Podiatrist",
            "type":"Services"
        }
    ],
    "sg:phone":"+1 718 828 6500",
    "sg:postcode":"10462",
    "sg:province":"NY",
    "wof:name":"Errington Williams DPM",
    "wof:placetype":"venue"
},
  "geometry": {"coordinates":[-73.85227,40.83626],"type":"Point"}
}