{
  "type": "Feature",
  "properties": {
    "addr:full":"956 E 82nd St Brooklyn NY 11236",
    "addr:housenumber":"956",
    "addr:postcode":"11236",
    "addr:street":"E 82Nd St",
    "iso:country":"US",
    "sg:address":"956 E 82nd St",
    "sg:city":"Brooklyn",
    "sg:classifiers":[
        {
            "category":"Organizations",
            "subcategory":"Community Association",
            "type":"Services"
        }
    ],
    "sg:phone":"+1 718 241 3847",
    "sg:postcode":"11236",
    "sg:province":"NY",
    "sg:tags":[
        "club"
    ],
    "wof:name":"Sesame Flyers Intl Inc",
    "wof:placetype":"venue"
},
  "geometry": {"coordinates":[-73.910808,40.63571],"type":"Point"}
}