{
  "type": "Feature",
  "properties": {
    "iso:country":"US",
    "sg:address":"159 Front St",
    "sg:city":"Deposit",
    "sg:classifiers":[
        {
            "category":"Education",
            "subcategory":"Library",
            "type":"Public Place"
        }
    ],
    "sg:phone":"+1   ",
    "sg:postcode":"13754",
    "sg:province":"NY",
    "wof:name":"Deposit Free Library",
    "wof:placetype":"venue"
},
  "geometry": {"coordinates":[-75.425698,42.060809],"type":"Point"}
}