{
  "type": "Feature",
  "properties": {
    "iso:country":"US",
    "sg:address":"213 N Aurora St",
    "sg:city":"Ithaca",
    "sg:classifiers":[
        {
            "category":"Health Services",
            "subcategory":"Health Practitioner",
            "type":"Services"
        }
    ],
    "sg:phone":"+1 607 273 9870",
    "sg:postcode":"14850",
    "sg:province":"NY",
    "sg:tags":[
        "psychotherapist"
    ],
    "wof:name":"Ann Hales Phd Nurse Prcttnr",
    "wof:placetype":"venue"
},
  "geometry": {"coordinates":[-76.495651,42.441299],"type":"Point"}
}