{
  "type": "Feature",
  "properties": {
    "addr:full":"1229 Franklin Avenue Bronx NY 10456",
    "addr:housenumber":"1229",
    "addr:postcode":"10456",
    "addr:street":"Franklin Avenue",
    "iso:country":"US",
    "sg:address":"1229 Franklin Avenue",
    "sg:city":"Bronx",
    "sg:classifiers":[
        {
            "category":"Food & Beverages",
            "subcategory":"Groceries & Convenience Stores",
            "type":"Retail Goods"
        }
    ],
    "sg:phone":"+1 718 588 0923",
    "sg:postcode":"10456",
    "sg:province":"NY",
    "wof:name":"Market Deli Grocery",
    "wof:placetype":"venue"
},
  "geometry": {"coordinates":[-73.90325799999999,40.830341],"type":"Point"}
}