{
  "type": "Feature",
  "properties": {
    "addr:full":"20 W 47th St Ph New York NY 10036",
    "addr:housenumber":"20",
    "addr:postcode":"10036",
    "addr:street":"W 47Th St Ph",
    "iso:country":"US",
    "sg:address":"20 W 47th St Ph",
    "sg:city":"New York",
    "sg:classifiers":[
        {
            "category":"Real Estate",
            "subcategory":"Real Estate Services",
            "type":"Services"
        }
    ],
    "sg:phone":"+1 212 582 7494",
    "sg:postcode":"10036",
    "sg:province":"NY",
    "sg:tags":[
        "management",
        "property"
    ],
    "wof:name":"Ring F M Assoc Inc",
    "wof:placetype":"venue"
},
  "geometry": {"coordinates":[-73.979202,40.756901],"type":"Point"}
}