{
  "type": "Feature",
  "properties": {
    "addr:full":"200 Cabrini Blvd New York NY 10033",
    "addr:housenumber":"200",
    "addr:postcode":"10033",
    "addr:street":"Cabrini Blvd",
    "iso:country":"US",
    "sg:address":"200 Cabrini Blvd",
    "sg:city":"New York",
    "sg:classifiers":[
        {
            "category":"Professional",
            "subcategory":"Lawyer & Legal Services",
            "type":"Services"
        }
    ],
    "sg:phone":"+1 212 568 7978",
    "sg:postcode":"10033",
    "sg:province":"NY",
    "sg:tags":[
        "attorney"
    ],
    "wof:name":"Paul S Johnson",
    "wof:placetype":"venue"
},
  "geometry": {"coordinates":[-73.940235,40.851326],"type":"Point"}
}