{
  "type": "Feature",
  "properties": {
    "addr:full":"9417 104th Street Ozone Park NY 11416",
    "addr:housenumber":"9417",
    "addr:postcode":"11416",
    "addr:street":"104Th Street",
    "iso:country":"US",
    "sg:address":"9417 104th Street",
    "sg:city":"Ozone Park",
    "sg:classifiers":[
        {
            "category":"Building & Trades",
            "subcategory":"Plumbing",
            "type":"Services"
        }
    ],
    "sg:phone":"+1 718 209 0338",
    "sg:postcode":"11416",
    "sg:province":"NY",
    "wof:name":"C & H Plumbing & Heating",
    "wof:placetype":"venue"
},
  "geometry": {"coordinates":[-73.840389,40.689262],"type":"Point"}
}