{
  "type": "Feature",
  "properties": {
    "iso:country":"US",
    "sg:address":"9440 Laidlaw Rd",
    "sg:city":"Franklinville",
    "sg:classifiers":[
        {
            "category":"Shopping",
            "subcategory":"Gifts & Souvenirs",
            "type":"Retail Goods"
        }
    ],
    "sg:phone":"+1 716 676 3615",
    "sg:postcode":"14737",
    "sg:province":"NY",
    "sg:tags":[
        "shop"
    ],
    "wof:name":"Chicory Hill Country Store",
    "wof:placetype":"venue"
},
  "geometry": {"coordinates":[-78.40635899999999,42.411544],"type":"Point"}
}