{
  "type": "Feature",
  "properties": {
    "addr:full":"6 Park Ave Massena NY 13662",
    "addr:housenumber":"6",
    "addr:postcode":"13662",
    "addr:street":"Park Ave",
    "iso:country":"US",
    "sg:address":"6 Park Ave",
    "sg:city":"Massena",
    "sg:classifiers":[
        {
            "category":"Retail",
            "subcategory":"Repair Shop",
            "type":"Services"
        }
    ],
    "sg:phone":"+1 315 764 0978",
    "sg:postcode":"13662",
    "sg:province":"NY",
    "sg:tags":[
        "ironwork"
    ],
    "wof:name":"Chicago Ironwork",
    "wof:placetype":"venue"
},
  "geometry": {"coordinates":[-74.890709,44.935143],"type":"Point"}
}