{
  "type": "Feature",
  "properties": {
    "addr:full":"43 Lesoir Ave Floral Park NY 11001",
    "addr:housenumber":"43",
    "addr:postcode":"11001",
    "addr:street":"Lesoir Ave",
    "iso:country":"US",
    "sg:address":"43 Lesoir Ave",
    "sg:city":"Floral Park",
    "sg:classifiers":[
        {
            "category":"Autos & Motor Vehicles",
            "subcategory":"Automobile Sales",
            "type":"Retail Goods"
        }
    ],
    "sg:phone":"+1 516 775 7441",
    "sg:postcode":"11001",
    "sg:province":"NY",
    "sg:tags":[
        "limo"
    ],
    "wof:name":"Interstate Limousine & Chauffeur Svc Corp",
    "wof:placetype":"venue"
},
  "geometry": {"coordinates":[-73.68890399999999,40.7122],"type":"Point"}
}