{
  "type": "Feature",
  "properties": {
    "addr:full":"485 Fashion Avenue Rm 608 New York NY 10018",
    "addr:housenumber":"485;608",
    "addr:postcode":"10018",
    "addr:street":"Fashion Avenue Rm",
    "iso:country":"US",
    "sg:address":"485 Fashion Avenue Rm 608",
    "sg:city":"New York",
    "sg:classifiers":[
        {
            "category":"Building & Trades",
            "subcategory":"Construction",
            "type":"Services"
        }
    ],
    "sg:phone":"+1 212 714 1638",
    "sg:postcode":"10018",
    "sg:province":"NY",
    "sg:tags":[
        "contractor"
    ],
    "wof:name":"J C General Contracting",
    "wof:placetype":"venue"
},
  "geometry": {"coordinates":[-73.989474,40.7524],"type":"Point"}
}