{
  "type": "Feature",
  "properties": {
    "iso:country":"US",
    "sg:address":"444 Madison Ave",
    "sg:city":"New York",
    "sg:classifiers":[
        {
            "category":"Personal",
            "type":"Services"
        }
    ],
    "sg:phone":"+1 212 355 0007",
    "sg:postcode":"10022",
    "sg:province":"NY",
    "sg:tags":[
        "singles",
        "organization"
    ],
    "wof:name":"Events & Adventures",
    "wof:placetype":"venue"
},
  "geometry": {"coordinates":[-73.975853,40.757537],"type":"Point"}
}