{
  "type": "Feature",
  "properties": {
    "addr:full":"384 E 155th St Bronx NY 10455",
    "addr:housenumber":"384",
    "addr:postcode":"10455",
    "addr:street":"E 155Th St",
    "iso:country":"US",
    "sg:address":"384 E 155th St",
    "sg:city":"Bronx",
    "sg:classifiers":[
        {
            "category":"Organizations",
            "subcategory":"Religious Organization",
            "type":"Services"
        }
    ],
    "sg:phone":"+1 718 292 7480",
    "sg:postcode":"10455",
    "sg:province":"NY",
    "sg:tags":[
        "church"
    ],
    "wof:name":"Brown's Union AME Church",
    "wof:placetype":"venue"
},
  "geometry": {"coordinates":[-73.91683999999999,40.820419],"type":"Point"}
}