{
  "type": "Feature",
  "properties": {
    "iso:country":"US",
    "sg:address":"24 Colvin Ave",
    "sg:city":"Albany",
    "sg:classifiers":[
        {
            "category":"Professional",
            "subcategory":"Testing Lab",
            "type":"Services"
        }
    ],
    "sg:phone":"+1 518 454 9500",
    "sg:postcode":"12206",
    "sg:province":"NY",
    "sg:tags":[
        "laboratory",
        "consulting",
        "business"
    ],
    "wof:name":"Testwell Laboratories Inc",
    "wof:placetype":"venue"
},
  "geometry": {"coordinates":[-73.797206,42.676812],"type":"Point"}
}