{
  "type": "Feature",
  "properties": {
    "iso:country":"US",
    "sg:address":"2170 Union Rd",
    "sg:city":"Buffalo",
    "sg:classifiers":[
        {
            "category":"Building & Trades",
            "subcategory":"Equipment Rental",
            "type":"Services"
        },
        {
            "category":"Manufacturing",
            "subcategory":"Tools & Machinery",
            "type":"Manufacturing & Wholesale Goods"
        }
    ],
    "sg:phone":"+1 716 656 0195",
    "sg:postcode":"14224",
    "sg:province":"NY",
    "sg:tags":[
        "physician",
        "surgeon",
        "medical"
    ],
    "wof:name":"American Homecare Supply LLC",
    "wof:placetype":"venue"
},
  "geometry": {"coordinates":[-78.754608,42.859941],"type":"Point"}
}