{
  "type": "Feature",
  "properties": {
    "iso:country":"US",
    "sg:address":"535 Van Nest Ave",
    "sg:city":"Bronx",
    "sg:classifiers":[
        {
            "category":"Manufacturing",
            "subcategory":"Rubber & Plastics",
            "type":"Manufacturing & Wholesale Goods"
        }
    ],
    "sg:phone":"+1   ",
    "sg:postcode":"10460",
    "sg:province":"NY",
    "sg:tags":[
        "product",
        "mfg"
    ],
    "wof:name":"F F Mold Inc",
    "wof:placetype":"venue"
},
  "geometry": {"coordinates":[-73.869687,40.841473],"type":"Point"}
}