{
  "type": "Feature",
  "properties": {
    "addr:full":"50 Nottingham Rd Rockville Centre NY 11570",
    "addr:housenumber":"50",
    "addr:postcode":"11570",
    "addr:street":"Nottingham Rd",
    "iso:country":"US",
    "sg:address":"50 Nottingham Rd",
    "sg:city":"Rockville Centre",
    "sg:classifiers":[
        {
            "category":"Professional",
            "subcategory":"Business Services",
            "type":"Services"
        }
    ],
    "sg:phone":"+1 516 764 1447",
    "sg:postcode":"11570",
    "sg:province":"NY",
    "sg:tags":[
        "interior",
        "consultant",
        "design",
        "decorator"
    ],
    "wof:name":"Diana Bier Interiors",
    "wof:placetype":"venue"
},
  "geometry": {"coordinates":[-73.630675,40.676235],"type":"Point"}
}