{
  "type": "Feature",
  "properties": {
    "iso:country":"US",
    "sg:address":"147 Biltmore Blvd",
    "sg:city":"Massapequa",
    "sg:classifiers":[
        {
            "category":"Real Estate",
            "subcategory":"Real Estate Services",
            "type":"Services"
        }
    ],
    "sg:phone":"+1 516 541 7301",
    "sg:postcode":"11758",
    "sg:province":"NY",
    "sg:tags":[
        "buyer",
        "broker"
    ],
    "wof:name":"Christopher M Re",
    "wof:placetype":"venue"
},
  "geometry": {"coordinates":[-73.46822,40.658884],"type":"Point"}
}