{
  "type": "Feature",
  "properties": {
    "addr:full":"Bronx River Parkway & Rd Bronx NY 10451",
    "addr:postcode":"10451",
    "addr:street":"Bronx River Parkway & Rd",
    "iso:country":"US",
    "sg:address":"Bronx River Parkway & Rd",
    "sg:city":"Bronx",
    "sg:classifiers":[
        {
            "category":"Education",
            "subcategory":"School",
            "type":"Public Place"
        },
        {
            "category":"Museum",
            "subcategory":"Zoo",
            "type":"Entertainment"
        }
    ],
    "sg:phone":"+1 718 220 5100",
    "sg:postcode":"10451",
    "sg:province":"NY",
    "sg:website":"www.bronxzoo.com",
    "wof:name":"Zoos",
    "wof:placetype":"venue"
},
  "geometry": {"coordinates":[-73.877628,40.835789],"type":"Point"}
}