{
  "type": "Feature",
  "properties": {
    "iso:country":"US",
    "sg:address":"185 Hall St",
    "sg:city":"Brooklyn",
    "sg:classifiers":[
        {
            "category":"Shopping",
            "subcategory":"Gifts & Souvenirs",
            "type":"Retail Goods"
        }
    ],
    "sg:phone":"+1 718 604 8010",
    "sg:postcode":"11205",
    "sg:province":"NY",
    "sg:tags":[
        "shop"
    ],
    "wof:name":"Jelly Bean Tree Gift Shop",
    "wof:placetype":"venue"
},
  "geometry": {"coordinates":[-73.965701,40.693067],"type":"Point"}
}