{
  "type": "Feature",
  "properties": {
    "iso:country":"US",
    "sg:address":"31 Lafayette Ave",
    "sg:city":"Suffern",
    "sg:classifiers":[
        {
            "category":"Restaurant",
            "type":"Food & Drink"
        }
    ],
    "sg:phone":"+1 845 369 0780",
    "sg:postcode":"10901",
    "sg:province":"NY",
    "sg:tags":[
        "delicatessen"
    ],
    "wof:name":"Wahidy Corp",
    "wof:placetype":"venue"
},
  "geometry": {"coordinates":[-74.153808,41.116148],"type":"Point"}
}