{
  "type": "Feature",
  "properties": {
    "iso:country":"US",
    "sg:address":"7 Howard Pl",
    "sg:city":"Malone",
    "sg:classifiers":[
        {
            "category":"Shopping",
            "subcategory":"Pets & Pet Supplies",
            "type":"Retail Goods"
        }
    ],
    "sg:phone":"+1 518 481 5537",
    "sg:postcode":"12953",
    "sg:province":"NY",
    "sg:tags":[
        "furnishing",
        "dog",
        "store",
        "cat"
    ],
    "wof:name":"Tri Lakes Aquarium & Pets",
    "wof:placetype":"venue"
},
  "geometry": {"coordinates":[-74.291087,44.849199],"type":"Point"}
}