{
  "type": "Feature",
  "properties": {
    "addr:full":"22 Sunset Ave Westhampton Beach NY 11978",
    "addr:housenumber":"22",
    "addr:postcode":"11978",
    "addr:street":"Sunset Ave",
    "iso:country":"US",
    "sg:address":"22 Sunset Ave",
    "sg:city":"Westhampton Beach",
    "sg:classifiers":[
        {
            "category":"Real Estate",
            "subcategory":"Real Estate Agent",
            "type":"Services"
        }
    ],
    "sg:phone":"+1 631 288 6244",
    "sg:postcode":"11978",
    "sg:province":"NY",
    "sg:tags":[
        "broker"
    ],
    "wof:name":"Prudential",
    "wof:placetype":"venue"
},
  "geometry": {"coordinates":[-72.64502,40.809978],"type":"Point"}
}