{
  "type": "Feature",
  "properties": {
    "iso:country":"US",
    "sg:address":"968 Anderson Ave",
    "sg:city":"Bronx",
    "sg:classifiers":[
        {
            "category":"Professional",
            "subcategory":"Business Services",
            "type":"Services"
        }
    ],
    "sg:phone":"+1 718 293 3001",
    "sg:postcode":"10452",
    "sg:province":"NY",
    "wof:name":"USA Legal Svc",
    "wof:placetype":"venue"
},
  "geometry": {"coordinates":[-73.928361,40.830184],"type":"Point"}
}