{
  "type": "Feature",
  "properties": {
    "iso:country":"US",
    "sg:address":"16 Mill St",
    "sg:city":"Gloversville",
    "sg:classifiers":[
        {
            "category":"Wholesale",
            "subcategory":"Apparel",
            "type":"Manufacturing & Wholesale Goods"
        }
    ],
    "sg:phone":"+1 518 725 3725",
    "sg:postcode":"12078",
    "sg:province":"NY",
    "sg:tags":[
        "mitten",
        "glove"
    ],
    "wof:name":"Vertucci Gloves",
    "wof:placetype":"venue"
},
  "geometry": {"coordinates":[-74.347466,43.045997],"type":"Point"}
}