{
  "type": "Feature",
  "properties": {
    "iso:country":"US",
    "sg:address":"41 Cornell Dr",
    "sg:city":"Great Neck",
    "sg:classifiers":[
        {
            "category":"Building & Trades",
            "subcategory":"Electrical",
            "type":"Services"
        }
    ],
    "sg:phone":"+1 516 482 3232",
    "sg:postcode":"11020",
    "sg:province":"NY",
    "sg:tags":[
        "installation",
        "telecommunication"
    ],
    "wof:name":"T R Systems Inc",
    "wof:placetype":"venue"
},
  "geometry": {"coordinates":[-73.720736,40.766312],"type":"Point"}
}