{
  "type": "Feature",
  "properties": {
    "addr:full":"11481 177th Pl Jamaica NY 11434",
    "addr:housenumber":"11481",
    "addr:postcode":"11434",
    "addr:street":"177Th Pl",
    "iso:country":"US",
    "sg:address":"11481 177th Pl",
    "sg:city":"Jamaica",
    "sg:classifiers":[
        {
            "category":"Health Services",
            "subcategory":"Doctor",
            "type":"Services"
        }
    ],
    "sg:phone":"+1 718 658 6767",
    "sg:postcode":"11434",
    "sg:province":"NY",
    "wof:name":"Walker Sonia Dr",
    "wof:placetype":"venue"
},
  "geometry": {"coordinates":[-73.7714,40.692699],"type":"Point"}
}