{
  "type": "Feature",
  "properties": {
    "iso:country":"US",
    "sg:address":"6410 8th Ave",
    "sg:city":"Brooklyn",
    "sg:classifiers":[
        {
            "category":"Retail",
            "subcategory":"Auto Repair",
            "type":"Services"
        }
    ],
    "sg:phone":"+1 718 745 6591",
    "sg:postcode":"11220",
    "sg:province":"NY",
    "wof:name":"S & D Auto Reprs Inc",
    "wof:placetype":"venue"
},
  "geometry": {"coordinates":[-74.012398,40.6329],"type":"Point"}
}