{
  "type": "Feature",
  "properties": {
    "addr:full":"116 Bleecker St Utica NY 13501",
    "addr:housenumber":"116",
    "addr:postcode":"13501",
    "addr:street":"Bleecker St",
    "iso:country":"US",
    "sg:address":"116 Bleecker St",
    "sg:city":"Utica",
    "sg:classifiers":[
        {
            "category":"Shopping",
            "subcategory":"Gifts & Souvenirs",
            "type":"Retail Goods"
        }
    ],
    "sg:phone":"+1   ",
    "sg:postcode":"13501",
    "sg:province":"NY",
    "wof:name":"Off Center Rec & Collectibles",
    "wof:placetype":"venue"
},
  "geometry": {"coordinates":[-75.229067,43.101669],"type":"Point"}
}