{
  "type": "Feature",
  "properties": {
    "addr:full":"74 E Pulaski Rd Huntington Station NY 11746",
    "addr:housenumber":"74",
    "addr:postcode":"11746",
    "addr:street":"E Pulaski Rd",
    "iso:country":"US",
    "sg:address":"74 E Pulaski Rd",
    "sg:city":"Huntington Station",
    "sg:classifiers":[
        {
            "category":"Restaurant",
            "type":"Food & Drink"
        }
    ],
    "sg:phone":"+1 631 351 9255",
    "sg:postcode":"11746",
    "sg:province":"NY",
    "sg:tags":[
        "eating"
    ],
    "wof:name":"El Sauce Restaurant",
    "wof:placetype":"venue"
},
  "geometry": {"coordinates":[-73.409448,40.848464],"type":"Point"}
}