{
  "type": "Feature",
  "properties": {
    "addr:full":"1746 1st Ave New York NY 10128",
    "addr:housenumber":"1746",
    "addr:postcode":"10128",
    "addr:street":"1St Ave",
    "iso:country":"US",
    "sg:address":"1746 1st Ave",
    "sg:city":"New York",
    "sg:classifiers":[
        {
            "category":"Restaurant",
            "type":"Food & Drink"
        }
    ],
    "sg:phone":"+1 212 426 5800",
    "sg:postcode":"10128",
    "sg:province":"NY",
    "sg:tags":[
        "peruvian"
    ],
    "sg:website":"www.piopionyc.com",
    "wof:name":"Pio Pio",
    "wof:placetype":"venue"
},
  "geometry": {"coordinates":[-73.94718,40.779664],"type":"Point"}
}