{
  "type": "Feature",
  "properties": {
    "addr:full":"4435 Victory Blvd Staten Island NY 10314",
    "addr:housenumber":"4435",
    "addr:postcode":"10314",
    "addr:street":"Victory Blvd",
    "iso:country":"US",
    "sg:address":"4435 Victory Blvd",
    "sg:city":"Staten Island",
    "sg:classifiers":[
        {
            "category":"Manufacturing",
            "subcategory":"Apparel",
            "type":"Manufacturing & Wholesale Goods"
        }
    ],
    "sg:phone":"+1   ",
    "sg:postcode":"10314",
    "sg:province":"NY",
    "sg:tags":[
        "mill",
        "mfg",
        "paperboard",
        "pulp",
        "furnishing"
    ],
    "wof:name":"Pratt Inustries",
    "wof:placetype":"venue"
},
  "geometry": {"coordinates":[-74.202505,40.585593],"type":"Point"}
}