{
  "type": "Feature",
  "properties": {
    "iso:country":"US",
    "sg:address":"1263 Erie Ave",
    "sg:city":"North Tonawanda",
    "sg:classifiers":[
        {
            "category":"Health Services",
            "subcategory":"Chiropractor",
            "type":"Services"
        }
    ],
    "sg:phone":"+1 716 693 0556",
    "sg:postcode":"14120",
    "sg:province":"NY",
    "wof:name":"Baase Family Chiropractic",
    "wof:placetype":"venue"
},
  "geometry": {"coordinates":[-78.84315100000001,43.054073],"type":"Point"}
}