{
  "type": "Feature",
  "properties": {
    "iso:country":"US",
    "sg:address":"390 Mc Guinness Blvd",
    "sg:city":"Brooklyn",
    "sg:classifiers":[
        {
            "category":"Manufacturing",
            "subcategory":"Metals",
            "type":"Manufacturing & Wholesale Goods"
        }
    ],
    "sg:phone":"+1   ",
    "sg:postcode":"11222",
    "sg:province":"NY",
    "sg:tags":[
        "plate",
        "sheet",
        "mfg",
        "work",
        "fabricated",
        "metalwork"
    ],
    "wof:name":"Themis Industries LTD",
    "wof:placetype":"venue"
},
  "geometry": {"coordinates":[-73.953,40.736695],"type":"Point"}
}