{
  "type": "Feature",
  "properties": {
    "iso:country":"US",
    "sg:address":"120 W 116th St",
    "sg:city":"New York",
    "sg:classifiers":[
        {
            "category":"Personal",
            "subcategory":"Beauty Salon",
            "type":"Services"
        }
    ],
    "sg:phone":"+1 212 316 1793",
    "sg:postcode":"10026",
    "sg:province":"NY",
    "wof:name":"F Alloue",
    "wof:placetype":"venue"
},
  "geometry": {"coordinates":[-73.95212100000001,40.802912],"type":"Point"}
}