{
  "type": "Feature",
  "properties": {
    "iso:country":"US",
    "sg:address":"375 Sunrise Hwy",
    "sg:city":"Lynbrook",
    "sg:classifiers":[
        {
            "category":"Insurance",
            "subcategory":"Insurance Agent",
            "type":"Services"
        }
    ],
    "sg:phone":"+1 516 887 5454",
    "sg:postcode":"11563",
    "sg:province":"NY",
    "sg:tags":[
        "processing"
    ],
    "wof:name":"Kelson Billing Svc",
    "wof:placetype":"venue"
},
  "geometry": {"coordinates":[-73.67098900000001,40.654948],"type":"Point"}
}