{
  "type": "Feature",
  "properties": {
    "addr:full":"1700 Broadway New York NY 10019",
    "addr:housenumber":"1700",
    "addr:postcode":"10019",
    "addr:street":"Broadway",
    "iso:country":"US",
    "sg:address":"1700 Broadway",
    "sg:city":"New York",
    "sg:classifiers":[
        {
            "category":"Banks & Credit Unions",
            "subcategory":"Bank",
            "type":"Services"
        }
    ],
    "sg:phone":"+1 212 247 7106",
    "sg:postcode":"10019",
    "sg:province":"NY",
    "wof:name":"Open Society Institute",
    "wof:placetype":"venue"
},
  "geometry": {"coordinates":[-73.982326,40.763981],"type":"Point"}
}