{
  "type": "Feature",
  "properties": {
    "iso:country":"US",
    "sg:address":"131 Albany Ave",
    "sg:city":"Freeport",
    "sg:classifiers":[
        {
            "category":"Retail",
            "subcategory":"Auto Repair",
            "type":"Services"
        }
    ],
    "sg:phone":"+1 516 378 5461",
    "sg:postcode":"11520",
    "sg:province":"NY",
    "sg:tags":[
        "automobile",
        "customizing"
    ],
    "wof:name":"HRE Motorcars Inc",
    "wof:placetype":"venue"
},
  "geometry": {"coordinates":[-73.568405,40.649501],"type":"Point"}
}