{
  "type": "Feature",
  "properties": {
    "addr:full":"132 Springville Rd Hampton Bays NY 11946",
    "addr:housenumber":"132",
    "addr:postcode":"11946",
    "addr:street":"Springville Rd",
    "iso:country":"US",
    "sg:address":"132 Springville Rd",
    "sg:city":"Hampton Bays",
    "sg:classifiers":[
        {
            "category":"Retail",
            "subcategory":"Repair Shop",
            "type":"Services"
        }
    ],
    "sg:phone":"+1   ",
    "sg:postcode":"11946",
    "sg:province":"NY",
    "sg:tags":[
        "upholstery",
        "mfg",
        "custom",
        "also",
        "through",
        "home",
        "marine"
    ],
    "wof:name":"Canyon Products",
    "wof:placetype":"venue"
},
  "geometry": {"coordinates":[-72.525187,40.858771],"type":"Point"}
}