{
  "type": "Feature",
  "properties": {
    "addr:full":"250 Lawrence Hill Rd Cold Spring Harbor NY 11724",
    "addr:housenumber":"250",
    "addr:postcode":"11724",
    "addr:street":"Lawrence Hill Rd",
    "iso:country":"US",
    "sg:address":"250 Lawrence Hill Rd",
    "sg:city":"Cold Spring Harbor",
    "sg:classifiers":[
        {
            "category":"Organizations",
            "subcategory":"Membership Organization",
            "type":"Services"
        }
    ],
    "sg:phone":"+1 631 367 3225",
    "sg:postcode":"11724",
    "sg:province":"NY",
    "sg:tags":[
        "association"
    ],
    "wof:name":"Long Island Chapter",
    "wof:placetype":"venue"
},
  "geometry": {"coordinates":[-73.458472,40.858225],"type":"Point"}
}