{
  "type": "Feature",
  "properties": {
    "iso:country":"US",
    "sg:address":"8249 Dexter Pkwy",
    "sg:city":"Baldwinsville",
    "sg:classifiers":[
        {
            "category":"Professional",
            "subcategory":"Art Services",
            "type":"Services"
        },
        {
            "category":"Professional",
            "subcategory":"Computer Services",
            "type":"Services"
        }
    ],
    "sg:phone":"+1 315 635 7096",
    "sg:postcode":"13027",
    "sg:province":"NY",
    "sg:tags":[
        "graphic",
        "designer"
    ],
    "wof:name":"Electronic Data Graphics",
    "wof:placetype":"venue"
},
  "geometry": {"coordinates":[-76.35117,43.168907],"type":"Point"}
}