{
  "type": "Feature",
  "properties": {
    "iso:country":"US",
    "sg:address":"351 N Central Ave",
    "sg:city":"Valley Stream",
    "sg:classifiers":[
        {
            "category":"Shopping",
            "subcategory":"Shoes",
            "type":"Retail Goods"
        }
    ],
    "sg:phone":"+1 516 256 4633",
    "sg:postcode":"11580",
    "sg:province":"NY",
    "sg:website":"www.marty-shoes.net",
    "wof:name":"Marty's Shoes Inc",
    "wof:placetype":"venue"
},
  "geometry": {"coordinates":[-73.709402,40.677334],"type":"Point"}
}