{
  "type": "Feature",
  "properties": {
    "addr:full":"200 Park Ave S New York NY 10003",
    "addr:housenumber":"200",
    "addr:postcode":"10003",
    "addr:street":"Park Ave S",
    "iso:country":"US",
    "sg:address":"200 Park Ave S",
    "sg:city":"New York",
    "sg:classifiers":[
        {
            "category":"Organizations",
            "subcategory":"Non-profit Organization",
            "type":"Services"
        }
    ],
    "sg:phone":"+1 212 780 2500",
    "sg:postcode":"10003",
    "sg:province":"NY",
    "sg:tags":[
        "association",
        "social"
    ],
    "wof:name":"Association For The",
    "wof:placetype":"venue"
},
  "geometry": {"coordinates":[-73.98857700000001,40.737147],"type":"Point"}
}