{
  "type": "Feature",
  "properties": {
    "iso:country":"US",
    "sg:address":"81 Greenwich Ave",
    "sg:city":"New York",
    "sg:classifiers":[
        {
            "category":"Restaurant",
            "type":"Food & Drink"
        }
    ],
    "sg:menulink":"http://www.allmenus.com/ny/new-york/249573-arte-pasta/menu/",
    "sg:phone":"+1 212 229 0234",
    "sg:postcode":"10014",
    "sg:province":"NY",
    "sg:tags":[
        "italian"
    ],
    "wof:name":"Arte Pasta",
    "wof:placetype":"venue"
},
  "geometry": {"coordinates":[-74.00135400000001,40.737006],"type":"Point"}
}