{
  "type": "Feature",
  "properties": {
    "addr:full":"10801 Queens Boulevard Forest Hills NY 11375",
    "addr:housenumber":"10801",
    "addr:postcode":"11375",
    "addr:street":"Queens Boulevard",
    "iso:country":"US",
    "sg:address":"10801 Queens Boulevard",
    "sg:city":"Forest Hills",
    "sg:classifiers":[
        {
            "category":"Banks & Credit Unions",
            "subcategory":"Financial Services",
            "type":"Services"
        }
    ],
    "sg:phone":"+1 718 896 4557",
    "sg:postcode":"11375",
    "sg:province":"NY",
    "sg:tags":[
        "broker",
        "mortgage"
    ],
    "wof:name":"Sterling National Mortgage",
    "wof:placetype":"venue"
},
  "geometry": {"coordinates":[-73.843887,40.72151],"type":"Point"}
}