{
  "type": "Feature",
  "properties": {
    "addr:full":"3060 Hempstead Tpke Levittown NY 11756",
    "addr:housenumber":"3060",
    "addr:postcode":"11756",
    "addr:street":"Hempstead Tpke",
    "iso:country":"US",
    "sg:address":"3060 Hempstead Tpke",
    "sg:city":"Levittown",
    "sg:classifiers":[
        {
            "category":"Professional",
            "subcategory":"Management & Consulting",
            "type":"Services"
        }
    ],
    "sg:phone":"+1   ",
    "sg:postcode":"11756",
    "sg:province":"NY",
    "wof:name":"Chip Collins Company",
    "wof:placetype":"venue"
},
  "geometry": {"coordinates":[-73.52276000000001,40.72483],"type":"Point"}
}