{
  "type": "Feature",
  "properties": {
    "addr:full":"426 Co Rd 23 Dundee NY 14837",
    "addr:housenumber":"426;23",
    "addr:postcode":"14837",
    "addr:street":"Co Rd",
    "iso:country":"US",
    "sg:address":"426 Co Rd 23",
    "sg:city":"Dundee",
    "sg:classifiers":[
        {
            "category":"Government",
            "subcategory":"Office",
            "type":"Public Place"
        }
    ],
    "sg:phone":"+1 607 292 3705",
    "sg:postcode":"14837",
    "sg:province":"NY",
    "sg:tags":[
        "city",
        "taxation"
    ],
    "wof:name":"Tyrone Town Assessor",
    "wof:placetype":"venue"
},
  "geometry": {"coordinates":[-77.077986,42.421917],"type":"Point"}
}