{
  "type": "Feature",
  "properties": {
    "iso:country":"US",
    "sg:address":"5724 Thompson Rd",
    "sg:city":"Syracuse",
    "sg:classifiers":[
        {
            "category":"Real Estate",
            "subcategory":"Real Estate Agent",
            "type":"Services"
        }
    ],
    "sg:phone":"+1 315 445 1234",
    "sg:postcode":"13214",
    "sg:province":"NY",
    "sg:tags":[
        "inspection"
    ],
    "wof:name":"Diraddo's Home Inspection",
    "wof:placetype":"venue"
},
  "geometry": {"coordinates":[-76.078731,43.049803],"type":"Point"}
}