{
  "type": "Feature",
  "properties": {
    "addr:full":"384 Tupper Rd Locke NY 13092",
    "addr:housenumber":"384",
    "addr:postcode":"13092",
    "addr:street":"Tupper Rd",
    "iso:country":"US",
    "sg:address":"384 Tupper Rd",
    "sg:city":"Locke",
    "sg:classifiers":[
        {
            "category":"Farming",
            "subcategory":"Dairy Farm",
            "type":"Manufacturing & Wholesale Goods"
        }
    ],
    "sg:phone":"+1 315 497 9548",
    "sg:postcode":"13092",
    "sg:province":"NY",
    "wof:name":"Elkendale Farms LLC",
    "wof:placetype":"venue"
},
  "geometry": {"coordinates":[-76.50420699999999,42.62757],"type":"Point"}
}