{
  "type": "Feature",
  "properties": {
    "addr:full":"46 Brighton Avenue Staten Island NY 10301",
    "addr:housenumber":"46",
    "addr:postcode":"10301",
    "addr:street":"Brighton Avenue",
    "iso:country":"US",
    "sg:address":"46 Brighton Avenue",
    "sg:city":"Staten Island",
    "sg:classifiers":[
        {
            "category":"Building & Trades",
            "subcategory":"Plumbing",
            "type":"Services"
        }
    ],
    "sg:phone":"+1 718 442 1341",
    "sg:postcode":"10301",
    "sg:province":"NY",
    "wof:name":"Brighton Corporation Plumbing & Heating",
    "wof:placetype":"venue"
},
  "geometry": {"coordinates":[-74.08856900000001,40.637312],"type":"Point"}
}