{
  "type": "Feature",
  "properties": {
    "addr:full":"250 Spencer Pl Bronx NY 10471",
    "addr:housenumber":"250",
    "addr:postcode":"10471",
    "addr:street":"Spencer Pl",
    "iso:country":"US",
    "sg:address":"250 Spencer Pl",
    "sg:city":"Bronx",
    "sg:classifiers":[
        {
            "category":"Professional",
            "type":"Services"
        }
    ],
    "sg:phone":"+1   ",
    "sg:postcode":"10471",
    "sg:province":"NY",
    "wof:name":"Ira S Sanders",
    "wof:placetype":"venue"
},
  "geometry": {"coordinates":[-73.89768100000001,40.911668],"type":"Point"}
}