{
  "type": "Feature",
  "properties": {
    "addr:full":"23 Flower St New Rochelle NY 10801",
    "addr:housenumber":"23",
    "addr:postcode":"10801",
    "addr:street":"Flower St",
    "iso:country":"US",
    "sg:address":"23 Flower St",
    "sg:city":"New Rochelle",
    "sg:phone":"+1 914 235 9386",
    "sg:postcode":"10801",
    "sg:province":"NY",
    "sg:tags":[
        "oil"
    ],
    "wof:name":"Champion Petroleum Distrs Inc",
    "wof:placetype":"venue"
},
  "geometry": {"coordinates":[-73.79868,40.900452],"type":"Point"}
}