{
  "type": "Feature",
  "properties": {
    "iso:country":"US",
    "sg:address":"303 E 50 St",
    "sg:city":"New York",
    "sg:classifiers":[
        {
            "category":"Retail",
            "subcategory":"Auto Repair",
            "type":"Services"
        }
    ],
    "sg:phone":"+1 917 477 6066",
    "sg:postcode":"10022",
    "sg:province":"NY",
    "sg:tags":[
        "wrecker"
    ],
    "wof:name":"Emergency 7 Day Towing",
    "wof:placetype":"venue"
},
  "geometry": {"coordinates":[-73.966157,40.753964],"type":"Point"}
}