{
  "type": "Feature",
  "properties": {
    "iso:country":"US",
    "sg:address":"20 Dutch Mill Rd",
    "sg:city":"Ithaca",
    "sg:classifiers":[
        {
            "category":"Manufacturing",
            "subcategory":"Tools & Machinery",
            "type":"Manufacturing & Wholesale Goods"
        }
    ],
    "sg:phone":"+1 607 257 5544",
    "sg:postcode":"14850",
    "sg:province":"NY",
    "sg:tags":[
        "physician",
        "surgeon"
    ],
    "sg:website":"www.pmiapp.com",
    "wof:name":"Porous Materials Inc",
    "wof:placetype":"venue"
},
  "geometry": {"coordinates":[-76.467051,42.507835],"type":"Point"}
}