{
  "type": "Feature",
  "properties": {
    "addr:full":"3073 State Hwy 50 Saratoga Springs NY 12866",
    "addr:housenumber":"3073",
    "addr:postcode":"12866",
    "addr:street":"State Hwy 50",
    "iso:country":"US",
    "sg:address":"3073 State Hwy 50",
    "sg:city":"Saratoga Springs",
    "sg:classifiers":[
        {
            "category":"Shopping",
            "subcategory":"Computers & Home Electronics",
            "type":"Retail Goods"
        }
    ],
    "sg:phone":"+1 518 226 0541",
    "sg:postcode":"12866",
    "sg:province":"NY",
    "sg:tags":[
        "television",
        "radio"
    ],
    "wof:name":"Rex TV & Appliances",
    "wof:placetype":"venue"
},
  "geometry": {"coordinates":[-73.739459,43.106187],"type":"Point"}
}