{
  "type": "Feature",
  "properties": {
    "iso:country":"US",
    "sg:address":"43 Willow Pond Way # 200",
    "sg:city":"Penfield",
    "sg:classifiers":[
        {
            "category":"Health Services",
            "subcategory":"Doctor",
            "type":"Services"
        }
    ],
    "sg:phone":"+1 585 377 5420",
    "sg:postcode":"14526",
    "sg:province":"NY",
    "sg:tags":[
        "physician",
        "surgeon"
    ],
    "wof:name":"Dickinson, Karin R, Md - Penfield Ob/Gyn",
    "wof:placetype":"venue"
},
  "geometry": {"coordinates":[-77.454081,43.129164],"type":"Point"}
}