{
  "type": "Feature",
  "properties": {
    "addr:full":"4 Karlin Blvd Unit 104 Monroe NY 10950",
    "addr:housenumber":"4;104",
    "addr:postcode":"10950",
    "addr:street":"Karlin Blvd Unit",
    "iso:country":"US",
    "sg:address":"4 Karlin Blvd Unit 104",
    "sg:city":"Monroe",
    "sg:classifiers":[
        {
            "category":"Insurance",
            "subcategory":"Hazard Insurance",
            "type":"Services"
        }
    ],
    "sg:phone":"+1 845 781 7325",
    "sg:postcode":"10950",
    "sg:province":"NY",
    "wof:name":"Insurance Advocates",
    "wof:placetype":"venue"
},
  "geometry": {"coordinates":[-74.16848400000001,41.347821],"type":"Point"}
}