{
  "type": "Feature",
  "properties": {
    "iso:country":"US",
    "sg:address":"816 Blakesley Rd",
    "sg:city":"Afton",
    "sg:classifiers":[
        {
            "category":"Real Estate",
            "subcategory":"Real Estate Agent",
            "type":"Services"
        }
    ],
    "sg:phone":"+1 607 693 2867",
    "sg:postcode":"13730",
    "sg:province":"NY",
    "wof:name":"Jeffrey Longwell",
    "wof:placetype":"venue"
},
  "geometry": {"coordinates":[-75.596638,42.258356],"type":"Point"}
}