{
  "type": "Feature",
  "properties": {
    "addr:full":"1055 Hawkins Ave Lake Grove NY 11755",
    "addr:housenumber":"1055",
    "addr:postcode":"11755",
    "addr:street":"Hawkins Ave",
    "iso:country":"US",
    "sg:address":"1055 Hawkins Ave",
    "sg:city":"Lake Grove",
    "sg:classifiers":[
        {
            "category":"Building & Trades",
            "subcategory":"Construction",
            "type":"Services"
        }
    ],
    "sg:phone":"+1 631 588 5086",
    "sg:postcode":"11755",
    "sg:province":"NY",
    "sg:tags":[
        "carpentry",
        "contractor"
    ],
    "wof:name":"Timothy Carpenter",
    "wof:placetype":"venue"
},
  "geometry": {"coordinates":[-73.112877,40.858946],"type":"Point"}
}