{
  "type": "Feature",
  "properties": {
    "iso:country":"US",
    "sg:address":"702 Nostrand Ave",
    "sg:city":"Brooklyn",
    "sg:classifiers":[
        {
            "category":"Shopping",
            "subcategory":"Shoes",
            "type":"Retail Goods"
        }
    ],
    "sg:phone":"+1   ",
    "sg:postcode":"11216",
    "sg:province":"NY",
    "sg:tags":[
        "repair",
        "lady",
        "shoe"
    ],
    "wof:name":"Modern Shoe Repair",
    "wof:placetype":"venue"
},
  "geometry": {"coordinates":[-73.950114,40.674935],"type":"Point"}
}