{
  "type": "Feature",
  "properties": {
    "addr:full":"171 Geary St Buffalo NY 14210",
    "addr:housenumber":"171",
    "addr:postcode":"14210",
    "addr:street":"Geary St",
    "iso:country":"US",
    "sg:address":"171 Geary St",
    "sg:city":"Buffalo",
    "sg:classifiers":[
        {
            "category":"Wholesale",
            "subcategory":"Durable Goods & Equipment",
            "type":"Manufacturing & Wholesale Goods"
        }
    ],
    "sg:phone":"+1 716 826 0348",
    "sg:postcode":"14210",
    "sg:province":"NY",
    "wof:name":"Olde Towne Treasures",
    "wof:placetype":"venue"
},
  "geometry": {"coordinates":[-78.807434,42.857795],"type":"Point"}
}