{
  "type": "Feature",
  "properties": {
    "iso:country":"US",
    "sg:address":"5922 Collins Dr",
    "sg:city":"Lockport",
    "sg:classifiers":[
        {
            "category":"Building & Trades",
            "subcategory":"Construction",
            "type":"Services"
        }
    ],
    "sg:phone":"+1 716 433 4030",
    "sg:postcode":"14094",
    "sg:province":"NY",
    "sg:tags":[
        "contractor"
    ],
    "wof:name":"I I C S of New York Inc",
    "wof:placetype":"venue"
},
  "geometry": {"coordinates":[-78.67639200000001,43.13668],"type":"Point"}
}