{
  "type": "Feature",
  "properties": {
    "addr:full":"304 Clinton St Brooklyn NY 11201",
    "addr:housenumber":"304",
    "addr:postcode":"11201",
    "addr:street":"Clinton St",
    "iso:country":"US",
    "sg:address":"304 Clinton St",
    "sg:city":"Brooklyn",
    "sg:classifiers":[
        {
            "category":"Professional",
            "subcategory":"Art Services",
            "type":"Services"
        }
    ],
    "sg:phone":"+1 212 334 5730",
    "sg:postcode":"11201",
    "sg:province":"NY",
    "sg:tags":[
        "graphic",
        "designer"
    ],
    "wof:name":"Peter Millen Design Inc",
    "wof:placetype":"venue"
},
  "geometry": {"coordinates":[-73.99633799999999,40.686368],"type":"Point"}
}