{
  "type": "Feature",
  "properties": {
    "addr:full":"196 8th Ave New York NY 10011",
    "addr:housenumber":"196",
    "addr:postcode":"10011",
    "addr:street":"8Th Ave",
    "iso:country":"US",
    "sg:address":"196 8th Ave",
    "sg:city":"New York",
    "sg:classifiers":[
        {
            "category":"Restaurant",
            "type":"Food & Drink"
        }
    ],
    "sg:phone":"+1 212 242 4551",
    "sg:postcode":"10011",
    "sg:province":"NY",
    "sg:tags":[
        "italian"
    ],
    "sg:website":"www.lasagnarestaurant.com",
    "wof:name":"Lasagna Ristorante",
    "wof:placetype":"venue"
},
  "geometry": {"coordinates":[-73.99967100000001,40.743213],"type":"Point"}
}