{
  "type": "Feature",
  "properties": {
    "addr:full":"33 Bay Ridge Ave Brooklyn NY 11220",
    "addr:housenumber":"33",
    "addr:postcode":"11220",
    "addr:street":"Bay Ridge Ave",
    "iso:country":"US",
    "sg:address":"33 Bay Ridge Ave",
    "sg:city":"Brooklyn",
    "sg:classifiers":[
        {
            "category":"Banks & Credit Unions",
            "subcategory":"Financial Services",
            "type":"Services"
        }
    ],
    "sg:phone":"+1 718 238 3040",
    "sg:postcode":"11220",
    "sg:province":"NY",
    "sg:tags":[
        "broker",
        "mortgage"
    ],
    "wof:name":"Rbi Associates",
    "wof:placetype":"venue"
},
  "geometry": {"coordinates":[-74.034553,40.638401],"type":"Point"}
}