{
  "type": "Feature",
  "properties": {
    "addr:full":"691 Rte 25A Miller Place NY 11764",
    "addr:housenumber":"691",
    "addr:postcode":"11764",
    "addr:street":"Rte 25A",
    "iso:country":"US",
    "sg:address":"691 Rte 25A",
    "sg:city":"Miller Place",
    "sg:classifiers":[
        {
            "category":"Retail",
            "subcategory":"Photofinishing",
            "type":"Services"
        }
    ],
    "sg:phone":"+1 631 744 2202",
    "sg:postcode":"11764",
    "sg:province":"NY",
    "sg:tags":[
        "photo",
        "finishing",
        "processing",
        "film"
    ],
    "wof:name":"Ashford One Hour Photo",
    "wof:placetype":"venue"
},
  "geometry": {"coordinates":[-72.97303599999999,40.943602],"type":"Point"}
}