{
  "type": "Feature",
  "properties": {
    "addr:full":"15 Neptune Ave New Rochelle NY 10805",
    "addr:housenumber":"15",
    "addr:postcode":"10805",
    "addr:street":"Neptune Ave",
    "iso:country":"US",
    "sg:address":"15 Neptune Ave",
    "sg:city":"New Rochelle",
    "sg:classifiers":[
        {
            "category":"Retail",
            "subcategory":"Repair Shop",
            "type":"Services"
        }
    ],
    "sg:phone":"+1   ",
    "sg:postcode":"10805",
    "sg:province":"NY",
    "sg:tags":[
        "electrical"
    ],
    "wof:name":"L & L Home Appliance Service",
    "wof:placetype":"venue"
},
  "geometry": {"coordinates":[-73.786243,40.895107],"type":"Point"}
}