{
  "type": "Feature",
  "properties": {
    "addr:full":"590 Avenue of the Americ New York NY 10011",
    "addr:housenumber":"590",
    "addr:postcode":"10011",
    "addr:street":"Avenue Of The",
    "iso:country":"US",
    "sg:address":"590 Avenue of the Americ",
    "sg:city":"New York",
    "sg:classifiers":[
        {
            "category":"Health Services",
            "subcategory":"Hospital",
            "type":"Services"
        }
    ],
    "sg:phone":"+1 646 459 3600",
    "sg:postcode":"10011",
    "sg:province":"NY",
    "wof:name":"Elizabeth Seton Pediatric Center",
    "wof:placetype":"venue"
},
  "geometry": {"coordinates":[-73.995411,40.73908],"type":"Point"}
}