{
  "type": "Feature",
  "properties": {
    "addr:full":"12 Apple Ln Monticello NY 12785",
    "addr:housenumber":"12",
    "addr:postcode":"12785",
    "addr:street":"Apple Ln",
    "iso:country":"US",
    "sg:address":"12 Apple Ln",
    "sg:city":"Monticello",
    "sg:classifiers":[
        {
            "category":"Retail",
            "subcategory":"Auto Rental",
            "type":"Services"
        }
    ],
    "sg:phone":"+1   ",
    "sg:postcode":"12785",
    "sg:province":"NY",
    "sg:tags":[
        "passenger",
        "car"
    ],
    "wof:name":"Budget Rent-A-Car",
    "wof:placetype":"venue"
},
  "geometry": {"coordinates":[-74.559417,41.499597],"type":"Point"}
}