{
  "type": "Feature",
  "properties": {
    "addr:full":"34-17 Northern Blvd Queens NY 11101",
    "addr:housenumber":"34-17",
    "addr:postcode":"11101",
    "addr:street":"Northern Blvd",
    "iso:country":"US",
    "sg:address":"34-17 Northern Blvd",
    "sg:city":"Queens",
    "sg:classifiers":[
        {
            "category":"Food & Beverages",
            "subcategory":"Groceries & Convenience Stores",
            "type":"Retail Goods"
        }
    ],
    "sg:phone":"+1 718 392 2891",
    "sg:postcode":"11101",
    "sg:province":"NY",
    "sg:website":"www.7-eleven.com",
    "wof:name":"7-Eleven",
    "wof:placetype":"venue"
},
  "geometry": {"coordinates":[-73.929536,40.752056],"type":"Point"}
}