{
  "type": "Feature",
  "properties": {
    "iso:country":"US",
    "sg:address":"1535 Broadway",
    "sg:city":"New York",
    "sg:classifiers":[
        {
            "category":"Professional",
            "type":"Services"
        }
    ],
    "sg:phone":"+1 212 398 5967",
    "sg:postcode":"10036",
    "sg:province":"NY",
    "sg:tags":[
        "establishment"
    ],
    "wof:name":"Modern Millie",
    "wof:placetype":"venue"
},
  "geometry": {"coordinates":[-73.985417,40.758614],"type":"Point"}
}