{
  "type": "Feature",
  "properties": {
    "iso:country":"US",
    "sg:address":"430 Birch Hollow Dr",
    "sg:city":"Shirley",
    "sg:classifiers":[
        {
            "category":"Building & Trades",
            "subcategory":"Construction",
            "type":"Services"
        }
    ],
    "sg:phone":"+1 631 281 0874",
    "sg:postcode":"11967",
    "sg:province":"NY",
    "sg:tags":[
        "contractor"
    ],
    "wof:name":"By Design Contracting Corp",
    "wof:placetype":"venue"
},
  "geometry": {"coordinates":[-72.867192,40.834302],"type":"Point"}
}