{
  "type": "Feature",
  "properties": {
    "addr:full":"3362 Long Beach Rd Oceanside NY 11572",
    "addr:housenumber":"3362",
    "addr:postcode":"11572",
    "addr:street":"Long Beach Rd",
    "iso:country":"US",
    "sg:address":"3362 Long Beach Rd",
    "sg:city":"Oceanside",
    "sg:classifiers":[
        {
            "category":"Retail",
            "subcategory":"Repair Shop",
            "type":"Services"
        }
    ],
    "sg:phone":"+1   ",
    "sg:postcode":"11572",
    "sg:province":"NY",
    "sg:tags":[
        "hardware",
        "mfg"
    ],
    "wof:name":"South Nassau Locksmiths",
    "wof:placetype":"venue"
},
  "geometry": {"coordinates":[-73.641122,40.629114],"type":"Point"}
}