{
  "type": "Feature",
  "properties": {
    "addr:full":"211 E 53 St New York NY 10022",
    "addr:housenumber":"211;53",
    "addr:postcode":"10022",
    "addr:street":"E",
    "iso:country":"US",
    "sg:address":"211 E 53 St",
    "sg:city":"New York",
    "sg:classifiers":[
        {
            "category":"Health Services",
            "subcategory":"Doctor",
            "type":"Services"
        }
    ],
    "sg:phone":"+1 212 751 2272",
    "sg:postcode":"10022",
    "sg:province":"NY",
    "sg:tags":[
        "medical"
    ],
    "wof:name":"A B Vivera MD PC",
    "wof:placetype":"venue"
},
  "geometry": {"coordinates":[-73.96728899999999,40.756927],"type":"Point"}
}