{
  "type": "Feature",
  "properties": {
    "addr:full":"728 E 136th Street Bronx NY 10454",
    "addr:housenumber":"728",
    "addr:postcode":"10454",
    "addr:street":"E 136Th Street",
    "iso:country":"US",
    "sg:address":"728 E 136th Street",
    "sg:city":"Bronx",
    "sg:classifiers":[
        {
            "category":"Personal",
            "type":"Services"
        }
    ],
    "sg:phone":"+1 212 452 6683",
    "sg:postcode":"10454",
    "sg:province":"NY",
    "sg:tags":[
        "mover"
    ],
    "wof:name":"Oz the Wizard of Moving",
    "wof:placetype":"venue"
},
  "geometry": {"coordinates":[-73.9132,40.803321],"type":"Point"}
}