{
  "type": "Feature",
  "properties": {
    "addr:full":"7142 Main St Flushing NY 11367",
    "addr:housenumber":"7142",
    "addr:postcode":"11367",
    "addr:street":"Main St",
    "iso:country":"US",
    "sg:address":"7142 Main St",
    "sg:city":"Flushing",
    "sg:classifiers":[
        {
            "category":"Retail",
            "subcategory":"Laundry & Dry Cleaning",
            "type":"Services"
        }
    ],
    "sg:phone":"+1 718 544 7500",
    "sg:postcode":"11367",
    "sg:province":"NY",
    "wof:name":"David's Cleaners",
    "wof:placetype":"venue"
},
  "geometry": {"coordinates":[-73.822098,40.726898],"type":"Point"}
}