{
  "type": "Feature",
  "properties": {
    "addr:full":"50 Amity St Brooklyn NY 11201",
    "addr:housenumber":"50",
    "addr:postcode":"11201",
    "addr:street":"Amity St",
    "iso:country":"US",
    "sg:address":"50 Amity St",
    "sg:city":"Brooklyn",
    "sg:classifiers":[
        {
            "category":"Building & Trades",
            "subcategory":"Construction",
            "type":"Services"
        }
    ],
    "sg:phone":"+1 718 393 7651",
    "sg:postcode":"11201",
    "sg:province":"NY",
    "sg:tags":[
        "repairing",
        "remodeling",
        "contractor"
    ],
    "wof:name":"Adam Daves Renovation King",
    "wof:placetype":"venue"
},
  "geometry": {"coordinates":[-73.997427,40.689554],"type":"Point"}
}