{
  "type": "Feature",
  "properties": {
    "addr:full":"541 State Hwy 29 Ballston Spa NY 12020",
    "addr:housenumber":"541",
    "addr:postcode":"12020",
    "addr:street":"State Hwy 29",
    "iso:country":"US",
    "sg:address":"541 State Hwy 29",
    "sg:city":"Ballston Spa",
    "sg:classifiers":[
        {
            "category":"Building & Trades",
            "subcategory":"Landscaping Services",
            "type":"Services"
        }
    ],
    "sg:phone":"+1 518 226 4560",
    "sg:postcode":"12020",
    "sg:province":"NY",
    "wof:name":"Shade Easy Lawn Care",
    "wof:placetype":"venue"
},
  "geometry": {"coordinates":[-73.877888,43.071597],"type":"Point"}
}