{
  "type": "Feature",
  "properties": {
    "addr:full":"677 8 Ave New York NY 10036",
    "addr:housenumber":"677",
    "addr:postcode":"10036",
    "addr:street":"8 Ave",
    "iso:country":"US",
    "sg:address":"677 8 Ave",
    "sg:city":"New York",
    "sg:classifiers":[
        {
            "category":"Shopping",
            "subcategory":"Used Merchandise",
            "type":"Retail Goods"
        }
    ],
    "sg:phone":"+1 212 245 1428",
    "sg:postcode":"10036",
    "sg:province":"NY",
    "sg:tags":[
        "pawnbroker"
    ],
    "wof:name":"ATM Cash America",
    "wof:placetype":"venue"
},
  "geometry": {"coordinates":[-73.989791,40.757234],"type":"Point"}
}