{
  "type": "Feature",
  "properties": {
    "iso:country":"US",
    "sg:address":"8 E 199th St",
    "sg:city":"Bronx",
    "sg:classifiers":[
        {
            "category":"Personal",
            "subcategory":"Beauty Salon",
            "type":"Services"
        }
    ],
    "sg:phone":"+1 718 563 8483",
    "sg:postcode":"10468",
    "sg:province":"NY",
    "wof:name":"Maritza Salon Unisex",
    "wof:placetype":"venue"
},
  "geometry": {"coordinates":[-73.88876500000001,40.871485],"type":"Point"}
}