{
  "type": "Feature",
  "properties": {
    "addr:full":"11662 Mexico St Saint Albans NY 11412",
    "addr:housenumber":"11662",
    "addr:postcode":"11412",
    "addr:street":"Mexico St",
    "iso:country":"US",
    "sg:address":"11662 Mexico St",
    "sg:city":"Saint Albans",
    "sg:classifiers":[
        {
            "category":"Retail",
            "subcategory":"Repair Shop",
            "type":"Services"
        },
        {
            "category":"Shopping",
            "subcategory":"Antiques",
            "type":"Retail Goods"
        }
    ],
    "sg:phone":"+1 718 525 9454",
    "sg:postcode":"11412",
    "sg:province":"NY",
    "sg:tags":[
        "reupholstery",
        "furniture"
    ],
    "wof:name":"L & P Upholstery Shop",
    "wof:placetype":"venue"
},
  "geometry": {"coordinates":[-73.76419799999999,40.692101],"type":"Point"}
}