{
  "type": "Feature",
  "properties": {
    "iso:country":"US",
    "sg:address":"90 W 3rd St",
    "sg:city":"New York",
    "sg:classifiers":[
        {
            "category":"Restaurant",
            "type":"Food & Drink"
        }
    ],
    "sg:menulink":"http://www.allmenus.com/ny/new-york/20551-baluchis/menu/",
    "sg:phone":"+1 212 529 5353",
    "sg:postcode":"10012",
    "sg:province":"NY",
    "sg:tags":[
        "indian",
        "asian"
    ],
    "wof:name":"Baluchi's",
    "wof:placetype":"venue"
},
  "geometry": {"coordinates":[-73.99934500000001,40.729858],"type":"Point"}
}