{
  "type": "Feature",
  "properties": {
    "addr:full":"31 W 54 St New York NY 10019",
    "addr:housenumber":"31",
    "addr:postcode":"10019",
    "addr:street":"W 54 St",
    "iso:country":"US",
    "sg:address":"31 W 54 St",
    "sg:city":"New York",
    "sg:classifiers":[
        {
            "category":"Farming",
            "subcategory":"Farm",
            "type":"Manufacturing & Wholesale Goods"
        }
    ],
    "sg:phone":"+1 212 582 5647",
    "sg:postcode":"10019",
    "sg:province":"NY",
    "sg:tags":[
        "crop",
        "general"
    ],
    "wof:name":"Arethusa Farm LLC",
    "wof:placetype":"venue"
},
  "geometry": {"coordinates":[-73.977816,40.762046],"type":"Point"}
}