{
  "type": "Feature",
  "properties": {
    "iso:country":"US",
    "sg:address":"445 Broad Hollow Rd",
    "sg:city":"Melville",
    "sg:classifiers":[
        {
            "category":"Real Estate",
            "subcategory":"Real Estate Agent",
            "type":"Services"
        }
    ],
    "sg:phone":"+1 631 293 7800",
    "sg:postcode":"11747",
    "sg:province":"NY",
    "sg:tags":[
        "broker"
    ],
    "wof:name":"Inlaw Realty Associates",
    "wof:placetype":"venue"
},
  "geometry": {"coordinates":[-73.423451,40.765042],"type":"Point"}
}