{
  "type": "Feature",
  "properties": {
    "iso:country":"US",
    "sg:address":"55 Spring St",
    "sg:city":"New York",
    "sg:classifiers":[
        {
            "category":"Retail",
            "subcategory":"Repair Shop",
            "type":"Services"
        }
    ],
    "sg:phone":"+1 212 616 6773",
    "sg:postcode":"10012",
    "sg:province":"NY",
    "sg:tags":[
        "lock",
        "key",
        "locksmith"
    ],
    "wof:name":"7 Days A Locksmith",
    "wof:placetype":"venue"
},
  "geometry": {"coordinates":[-73.996696,40.722099],"type":"Point"}
}