{
  "type": "Feature",
  "properties": {
    "addr:full":"7 Dene Rd Newburgh NY 12550",
    "addr:housenumber":"7",
    "addr:postcode":"12550",
    "addr:street":"Dene Rd",
    "iso:country":"US",
    "sg:address":"7 Dene Rd",
    "sg:city":"Newburgh",
    "sg:classifiers":[
        {
            "category":"Organizations",
            "subcategory":"Religious Organization",
            "type":"Services"
        }
    ],
    "sg:phone":"+1 845 564 1336",
    "sg:postcode":"12550",
    "sg:province":"NY",
    "sg:tags":[
        "clergy"
    ],
    "wof:name":"G W Johnson",
    "wof:placetype":"venue"
},
  "geometry": {"coordinates":[-74.09247999999999,41.512933],"type":"Point"}
}