{
  "type": "Feature",
  "properties": {
    "iso:country":"US",
    "sg:address":"95 Midvale Dr",
    "sg:city":"Fairport",
    "sg:classifiers":[
        {
            "category":"Building & Trades",
            "subcategory":"Construction",
            "type":"Services"
        }
    ],
    "sg:phone":"+1 585 586 3370",
    "sg:postcode":"14450",
    "sg:province":"NY",
    "sg:tags":[
        "home",
        "improvement"
    ],
    "wof:name":"Teton Woodworks Inc",
    "wof:placetype":"venue"
},
  "geometry": {"coordinates":[-77.46725000000001,43.106962],"type":"Point"}
}