{
  "type": "Feature",
  "properties": {
    "addr:full":"9 Station Sq Forest Hills NY 11375",
    "addr:housenumber":"9",
    "addr:postcode":"11375",
    "addr:street":"Station Sq",
    "iso:country":"US",
    "sg:address":"9 Station Sq",
    "sg:city":"Forest Hills",
    "sg:classifiers":[
        {
            "category":"Personal",
            "subcategory":"Beauty Salon",
            "type":"Services"
        }
    ],
    "sg:phone":"+1 718 263 7774",
    "sg:postcode":"11375",
    "sg:province":"NY",
    "sg:tags":[
        "shop"
    ],
    "wof:name":"Mario Alcamo",
    "wof:placetype":"venue"
},
  "geometry": {"coordinates":[-73.84496300000001,40.719235],"type":"Point"}
}