{
  "type": "Feature",
  "properties": {
    "iso:country":"US",
    "sg:address":"157 Lexington Avenue, Apt 2F",
    "sg:city":"New York",
    "sg:classifiers":[
        {
            "category":"Professional",
            "type":"Services"
        }
    ],
    "sg:phone":"+1 212 725 1658",
    "sg:postcode":"10016",
    "sg:province":"NY",
    "sg:tags":[
        "planning",
        "event"
    ],
    "sg:website":"www.marygiuliani.com",
    "wof:name":"Mary Giuliani Catering & Events",
    "wof:placetype":"venue"
},
  "geometry": {"coordinates":[-73.98146699999999,40.743679],"type":"Point"}
}