{
  "type": "Feature",
  "properties": {
    "iso:country":"US",
    "sg:address":"95 Public Sq",
    "sg:city":"Watertown",
    "sg:classifiers":[
        {
            "category":"Health Services",
            "subcategory":"Doctor",
            "type":"Services"
        }
    ],
    "sg:phone":"+1 315 782 1791",
    "sg:postcode":"13601",
    "sg:province":"NY",
    "sg:tags":[
        "clinic"
    ],
    "wof:name":"Heart Association-NORTHERN Ny",
    "wof:placetype":"venue"
},
  "geometry": {"coordinates":[-75.90992199999999,43.974841],"type":"Point"}
}