{
  "type": "Feature",
  "properties": {
    "iso:country":"US",
    "sg:address":"129 Lockwood Ave",
    "sg:city":"New Rochelle",
    "sg:classifiers":[
        {
            "category":"Real Estate",
            "subcategory":"Real Estate Agent",
            "type":"Services"
        }
    ],
    "sg:phone":"+1 914 636 0727",
    "sg:postcode":"10801",
    "sg:province":"NY",
    "sg:tags":[
        "management"
    ],
    "wof:name":"Community Housing Mgmt Corp",
    "wof:placetype":"venue"
},
  "geometry": {"coordinates":[-73.791298,40.913329],"type":"Point"}
}