{
  "type": "Feature",
  "properties": {
    "iso:country":"US",
    "sg:address":"317 Madison Avenue",
    "sg:city":"New York",
    "sg:classifiers":[
        {
            "category":"Real Estate",
            "subcategory":"Real Estate Services",
            "type":"Services"
        }
    ],
    "sg:phone":"+1 212 682 8351",
    "sg:postcode":"10017",
    "sg:province":"NY",
    "sg:tags":[
        "management",
        "property"
    ],
    "wof:name":"North American Realty Advisor",
    "wof:placetype":"venue"
},
  "geometry": {"coordinates":[-73.97907499999999,40.753085],"type":"Point"}
}