{
  "type": "Feature",
  "properties": {
    "addr:full":"PS 87 William T Sherman School 160 W 78th St New York NY 10024",
    "addr:housenumber":"87;160",
    "addr:postcode":"10024",
    "addr:street":"Ps;William T;W 78Th St",
    "iso:country":"US",
    "sg:address":"PS 87 William T Sherman School 160 W 78th St",
    "sg:city":"New York",
    "sg:classifiers":[
        {
            "category":"Place Of Worship",
            "subcategory":"Church",
            "type":"Public Place"
        }
    ],
    "sg:phone":"+1 646 872 9048",
    "sg:postcode":"10024",
    "sg:province":"NY",
    "sg:website":"www.allsoulschristianchurch.com",
    "wof:name":"All Souls Christian Church",
    "wof:placetype":"venue"
},
  "geometry": {"coordinates":[-73.97791700000001,40.782066],"type":"Point"}
}