{
  "type": "Feature",
  "properties": {
    "iso:country":"US",
    "sg:address":"64 Sunrise Ave",
    "sg:city":"New Canaan",
    "sg:classifiers":[
        {
            "category":"Building & Trades",
            "subcategory":"Plumbing",
            "type":"Services"
        }
    ],
    "sg:phone":"+1 203 966 5718",
    "sg:postcode":"06840",
    "sg:province":"NY",
    "sg:tags":[
        "air",
        "conditioning",
        "heating"
    ],
    "wof:name":"William Tiani Jr",
    "wof:placetype":"venue"
},
  "geometry": {"coordinates":[-73.499173,41.141398],"type":"Point"}
}