{
  "type": "Feature",
  "properties": {
    "iso:country":"US",
    "sg:address":"255 Canal St",
    "sg:city":"New York",
    "sg:classifiers":[
        {
            "category":"Shopping",
            "subcategory":"Clothing, Apparel, & Fashions",
            "type":"Retail Goods"
        }
    ],
    "sg:phone":"+1 212 334 3546",
    "sg:postcode":"10013",
    "sg:province":"NY",
    "wof:name":"Fooden Fashion",
    "wof:placetype":"venue"
},
  "geometry": {"coordinates":[-74.001097,40.718897],"type":"Point"}
}