{
  "type": "Feature",
  "properties": {
    "iso:country":"US",
    "sg:address":"1650 Champlin Ave",
    "sg:city":"New Hartford",
    "sg:classifiers":[
        {
            "category":"Travel",
            "subcategory":"Hotels & Motels",
            "type":"Entertainment"
        }
    ],
    "sg:phone":"+1 315 798 6184",
    "sg:postcode":"13413",
    "sg:province":"NY",
    "sg:tags":[
        "operation"
    ],
    "wof:name":"Marriott",
    "wof:placetype":"venue"
},
  "geometry": {"coordinates":[-75.27423899999999,43.096076],"type":"Point"}
}