{
  "type": "Feature",
  "properties": {
    "iso:country":"US",
    "sg:address":"2430 Ridgeway Ave Ste 1",
    "sg:city":"Rochester",
    "sg:classifiers":[
        {
            "category":"Professional",
            "subcategory":"Accounting & Tax Preparation",
            "type":"Services"
        }
    ],
    "sg:phone":"+1 585 225 9290",
    "sg:postcode":"14626",
    "sg:province":"NY",
    "sg:tags":[
        "bookkeeping",
        "public",
        "accountants-certified"
    ],
    "sg:website":"http://www.goldenagecomics.com",
    "wof:name":"Nacca & Capizzi",
    "wof:placetype":"venue"
},
  "geometry": {"coordinates":[-77.700695,43.187038],"type":"Point"}
}