{
  "type": "Feature",
  "properties": {
    "addr:full":"17 W Courtney St Dunkirk NY 14048",
    "addr:housenumber":"17",
    "addr:postcode":"14048",
    "addr:street":"W Courtney St",
    "iso:country":"US",
    "sg:address":"17 W Courtney St",
    "sg:city":"Dunkirk",
    "sg:classifiers":[
        {
            "category":"Shopping",
            "subcategory":"Party Supplies",
            "type":"Retail Goods"
        },
        {
            "category":"Shopping",
            "subcategory":"Bridal",
            "type":"Retail Goods"
        }
    ],
    "sg:phone":"+1 716 366 1468",
    "sg:postcode":"14048",
    "sg:province":"NY",
    "sg:tags":[
        "shop",
        "wedding"
    ],
    "wof:name":"Dee's Bridal Shop",
    "wof:placetype":"venue"
},
  "geometry": {"coordinates":[-79.321546,42.480444],"type":"Point"}
}