{
  "type": "Feature",
  "properties": {
    "iso:country":"US",
    "sg:address":"210 24th St",
    "sg:city":"Niagara Falls",
    "sg:classifiers":[
        {
            "category":"Organizations",
            "subcategory":"Religious Organization",
            "type":"Services"
        }
    ],
    "sg:phone":"+1 716 284 8514",
    "sg:postcode":"14303",
    "sg:province":"NY",
    "sg:tags":[
        "church"
    ],
    "wof:name":"Damascus Baptist Church",
    "wof:placetype":"venue"
},
  "geometry": {"coordinates":[-79.03317300000001,43.085562],"type":"Point"}
}