{
  "type": "Feature",
  "properties": {
    "iso:country":"US",
    "sg:address":"131 Prince St",
    "sg:city":"New York",
    "sg:classifiers":[
        {
            "category":"Real Estate",
            "subcategory":"Real Estate Agent",
            "type":"Services"
        }
    ],
    "sg:phone":"+1 212 254 3827",
    "sg:postcode":"10012",
    "sg:province":"NY",
    "wof:name":"131 Prince St Co-Op Inc",
    "wof:placetype":"venue"
},
  "geometry": {"coordinates":[-74.00073500000001,40.725757],"type":"Point"}
}