{
  "type": "Feature",
  "properties": {
    "addr:full":"1872 Monroe Ave Bronx NY 10457",
    "addr:housenumber":"1872",
    "addr:postcode":"10457",
    "addr:street":"Monroe Ave",
    "iso:country":"US",
    "sg:address":"1872 Monroe Ave",
    "sg:city":"Bronx",
    "sg:classifiers":[
        {
            "category":"Building & Trades",
            "subcategory":"Construction",
            "type":"Services"
        }
    ],
    "sg:phone":"+1 718 583 4250",
    "sg:postcode":"10457",
    "sg:province":"NY",
    "sg:tags":[
        "carpentry",
        "contractor"
    ],
    "wof:name":"Mooises Rodriguez Carpentry",
    "wof:placetype":"venue"
},
  "geometry": {"coordinates":[-73.90567900000001,40.849205],"type":"Point"}
}