{
  "type": "Feature",
  "properties": {
    "iso:country":"US",
    "sg:address":"25 Plattekill Ave",
    "sg:city":"New Paltz",
    "sg:classifiers":[
        {
            "category":"Government",
            "subcategory":"Office",
            "type":"Public Place"
        }
    ],
    "sg:phone":"+1 845 255 1980",
    "sg:postcode":"12561",
    "sg:province":"NY",
    "sg:tags":[
        "village"
    ],
    "wof:name":"DPW Garage",
    "wof:placetype":"venue"
},
  "geometry": {"coordinates":[-74.08413,41.746611],"type":"Point"}
}