{
  "type": "Feature",
  "properties": {
    "addr:full":"1241 Prospect Ave Brooklyn NY 11215",
    "addr:housenumber":"1241",
    "addr:postcode":"11215",
    "addr:street":"Prospect Ave",
    "iso:country":"US",
    "sg:address":"1241 Prospect Ave",
    "sg:city":"Brooklyn",
    "sg:classifiers":[
        {
            "category":"Building & Trades",
            "subcategory":"Locksmith",
            "type":"Services"
        }
    ],
    "sg:phone":"+1 718 435 9055",
    "sg:postcode":"11215",
    "sg:province":"NY",
    "sg:tags":[
        "key"
    ],
    "sg:website":"www.allsecurity.tv",
    "wof:name":"All Security Locksmith",
    "wof:placetype":"venue"
},
  "geometry": {"coordinates":[-73.976061,40.652705],"type":"Point"}
}