{
  "type": "Feature",
  "properties": {
    "addr:full":"38 Brookside Cir Bronxville NY 10708",
    "addr:housenumber":"38",
    "addr:postcode":"10708",
    "addr:street":"Brookside Cir",
    "iso:country":"US",
    "sg:address":"38 Brookside Cir",
    "sg:city":"Bronxville",
    "sg:classifiers":[
        {
            "category":"Building & Trades",
            "subcategory":"Construction",
            "type":"Services"
        }
    ],
    "sg:phone":"+1 914 961 6756",
    "sg:postcode":"10708",
    "sg:province":"NY",
    "sg:tags":[
        "contractor",
        "painting",
        "hanging"
    ],
    "wof:name":"Pagliaroli Paperhanging Co",
    "wof:placetype":"venue"
},
  "geometry": {"coordinates":[-73.84116899999999,40.938247],"type":"Point"}
}