{
  "type": "Feature",
  "properties": {
    "iso:country":"US",
    "sg:address":"900 Wheeler Rd",
    "sg:city":"Hauppauge",
    "sg:classifiers":[
        {
            "category":"Communications",
            "type":"Services"
        }
    ],
    "sg:phone":"+1 631 979 2358",
    "sg:postcode":"11788",
    "sg:province":"NY",
    "wof:name":"Phone Review",
    "wof:placetype":"venue"
},
  "geometry": {"coordinates":[-73.205107,40.824546],"type":"Point"}
}