{
  "type": "Feature",
  "properties": {
    "addr:full":"509 Rte 22 Purdys NY 10578",
    "addr:housenumber":"509",
    "addr:postcode":"10578",
    "addr:street":"Rte 22",
    "iso:country":"US",
    "sg:address":"509 Rte 22",
    "sg:city":"Purdys",
    "sg:classifiers":[
        {
            "category":"Shopping",
            "subcategory":"Computers & Home Electronics",
            "type":"Retail Goods"
        }
    ],
    "sg:phone":"+1 914 276 0252",
    "sg:postcode":"10578",
    "sg:province":"NY",
    "sg:tags":[
        "software"
    ],
    "wof:name":"M P Assoc Inc",
    "wof:placetype":"venue"
},
  "geometry": {"coordinates":[-73.660724,41.319472],"type":"Point"}
}