{
  "type": "Feature",
  "properties": {
    "addr:full":"19 E 7th St Deer Park NY 11729",
    "addr:housenumber":"19",
    "addr:postcode":"11729",
    "addr:street":"E 7Th St",
    "iso:country":"US",
    "sg:address":"19 E 7th St",
    "sg:city":"Deer Park",
    "sg:classifiers":[
        {
            "category":"Wholesale",
            "subcategory":"Construction Materials",
            "type":"Manufacturing & Wholesale Goods"
        }
    ],
    "sg:phone":"+1 516 551 7490",
    "sg:postcode":"11729",
    "sg:province":"NY",
    "sg:tags":[
        "distributor",
        "custom",
        "co",
        "kitchen",
        "cabinet"
    ],
    "wof:name":"Town & Country Distrs Inc",
    "wof:placetype":"venue"
},
  "geometry": {"coordinates":[-73.32180200000001,40.760592],"type":"Point"}
}