{
  "type": "Feature",
  "properties": {
    "addr:full":"4501 Queens Boulevard Sunnyside NY 11104",
    "addr:housenumber":"4501",
    "addr:postcode":"11104",
    "addr:street":"Queens Boulevard",
    "iso:country":"US",
    "sg:address":"4501 Queens Boulevard",
    "sg:city":"Sunnyside",
    "sg:classifiers":[
        {
            "category":"Shopping",
            "subcategory":"Stationery & Office Supplies",
            "type":"Retail Goods"
        }
    ],
    "sg:phone":"+1 718 786 0760",
    "sg:postcode":"11104",
    "sg:province":"NY",
    "sg:tags":[
        "equipment"
    ],
    "wof:name":"Queens Mini Market",
    "wof:placetype":"venue"
},
  "geometry": {"coordinates":[-73.91945699999999,40.743514],"type":"Point"}
}