{
  "type": "Feature",
  "properties": {
    "iso:country":"US",
    "sg:address":"72 Colonial Ave",
    "sg:city":"Dobbs Ferry",
    "sg:classifiers":[
        {
            "category":"Professional",
            "subcategory":"Business Services",
            "type":"Services"
        }
    ],
    "sg:phone":"+1 914 674 0064",
    "sg:postcode":"10522",
    "sg:province":"NY",
    "sg:tags":[
        "entertainment"
    ],
    "wof:name":"Warren Z Productions",
    "wof:placetype":"venue"
},
  "geometry": {"coordinates":[-73.87615599999999,41.007897],"type":"Point"}
}