{
  "type": "Feature",
  "properties": {
    "addr:full":"2003 Jericho Tpke New Hyde Park NY 11040",
    "addr:housenumber":"2003",
    "addr:postcode":"11040",
    "addr:street":"Jericho Tpke;Hyde Park",
    "iso:country":"US",
    "sg:address":"2003 Jericho Tpke",
    "sg:city":"New Hyde Park",
    "sg:classifiers":[
        {
            "category":"Insurance",
            "subcategory":"Insurance Agent",
            "type":"Services"
        }
    ],
    "sg:phone":"+1 516 352 7000",
    "sg:postcode":"11040",
    "sg:province":"NY",
    "sg:tags":[
        "administrator",
        "agency",
        "benefit"
    ],
    "sg:website":"www.fnainsurance.com",
    "wof:name":"First National Administrators",
    "wof:placetype":"venue"
},
  "geometry": {"coordinates":[-73.67318899999999,40.736185],"type":"Point"}
}