{
  "type": "Feature",
  "properties": {
    "addr:full":"330 Wall St Kingston NY 12401",
    "addr:housenumber":"330",
    "addr:postcode":"12401",
    "addr:street":"Wall St",
    "iso:country":"US",
    "sg:address":"330 Wall St",
    "sg:city":"Kingston",
    "sg:classifiers":[
        {
            "category":"Professional",
            "type":"Services"
        }
    ],
    "sg:phone":"+1   ",
    "sg:postcode":"12401",
    "sg:province":"NY",
    "sg:tags":[
        "gallery"
    ],
    "wof:name":"Klm Studios",
    "wof:placetype":"venue"
},
  "geometry": {"coordinates":[-74.01987699999999,41.934763],"type":"Point"}
}