{
  "type": "Feature",
  "properties": {
    "addr:full":"6 Sunset Dr Sag Harbor NY 11963",
    "addr:housenumber":"6",
    "addr:postcode":"11963",
    "addr:street":"Sunset Dr",
    "iso:country":"US",
    "sg:address":"6 Sunset Dr",
    "sg:city":"Sag Harbor",
    "sg:classifiers":[
        {
            "category":"Building & Trades",
            "subcategory":"Landscaping Services",
            "type":"Services"
        }
    ],
    "sg:phone":"+1 631 287 4045",
    "sg:postcode":"11963",
    "sg:province":"NY",
    "sg:tags":[
        "landscape",
        "contractor"
    ],
    "wof:name":"Secatogue Property Care",
    "wof:placetype":"venue"
},
  "geometry": {"coordinates":[-72.313289,41.001499],"type":"Point"}
}