{
  "type": "Feature",
  "properties": {
    "iso:country":"US",
    "sg:address":"238 Cook Rd",
    "sg:city":"Hamlin",
    "sg:classifiers":[
        {
            "category":"Restaurant",
            "type":"Food & Drink"
        }
    ],
    "sg:phone":"+1 585 964 2087",
    "sg:postcode":"14464",
    "sg:province":"NY",
    "sg:tags":[
        "pizza"
    ],
    "wof:name":"Firehouse Pizza",
    "wof:placetype":"venue"
},
  "geometry": {"coordinates":[-77.97787700000001,43.35938],"type":"Point"}
}