{
  "type": "Feature",
  "properties": {
    "iso:country":"US",
    "sg:address":"90 Schenck Ave",
    "sg:city":"Great Neck",
    "sg:classifiers":[
        {
            "category":"Manufacturing",
            "subcategory":"Chemicals & Compounds",
            "type":"Manufacturing & Wholesale Goods"
        }
    ],
    "sg:phone":"+1 516 466 9342",
    "sg:postcode":"11021",
    "sg:province":"NY",
    "sg:tags":[
        "plastic"
    ],
    "sg:website":"www.bambergerpolymers.com",
    "wof:name":"Bamberger Polymers Inc",
    "wof:placetype":"venue"
},
  "geometry": {"coordinates":[-73.723794,40.78611],"type":"Point"}
}