{
  "type": "Feature",
  "properties": {
    "addr:full":"61 Maple Ave Voorheesville NY 12186",
    "addr:housenumber":"61",
    "addr:postcode":"12186",
    "addr:street":"Maple Ave",
    "iso:country":"US",
    "sg:address":"61 Maple Ave",
    "sg:city":"Voorheesville",
    "sg:classifiers":[
        {
            "category":"Building & Trades",
            "subcategory":"Construction",
            "type":"Services"
        }
    ],
    "sg:phone":"+1 518 765 3679",
    "sg:postcode":"12186",
    "sg:province":"NY",
    "sg:tags":[
        "contractor"
    ],
    "wof:name":"Has Contractors",
    "wof:placetype":"venue"
},
  "geometry": {"coordinates":[-73.927708,42.650241],"type":"Point"}
}