{
  "type": "Feature",
  "properties": {
    "iso:country":"US",
    "sg:address":"4 Hollow Ct",
    "sg:city":"Port Washington",
    "sg:classifiers":[
        {
            "category":"Real Estate",
            "subcategory":"Developer",
            "type":"Services"
        }
    ],
    "sg:phone":"+1 516 767 2551",
    "sg:postcode":"11050",
    "sg:province":"NY",
    "wof:name":"Wnb Development Co",
    "wof:placetype":"venue"
},
  "geometry": {"coordinates":[-73.71304000000001,40.854741],"type":"Point"}
}