{
  "type": "Feature",
  "properties": {
    "addr:full":"199 Lee Ave Brooklyn NY 11211",
    "addr:housenumber":"199",
    "addr:postcode":"11211",
    "addr:street":"Lee Ave",
    "iso:country":"US",
    "sg:address":"199 Lee Ave",
    "sg:city":"Brooklyn",
    "sg:classifiers":[
        {
            "category":"Professional",
            "subcategory":"Business Services",
            "type":"Services"
        }
    ],
    "sg:phone":"+1 718 218 8160",
    "sg:postcode":"11211",
    "sg:province":"NY",
    "sg:tags":[
        "interior",
        "consultant",
        "design",
        "decorator"
    ],
    "sg:website":"www.homedecorofusa.com",
    "wof:name":"Home Decor Of USA Inc",
    "wof:placetype":"venue"
},
  "geometry": {"coordinates":[-73.955589,40.702042],"type":"Point"}
}