{
  "type": "Feature",
  "properties": {
    "addr:full":"35 Tyrol Dr Buffalo NY 14227",
    "addr:housenumber":"35",
    "addr:postcode":"14227",
    "addr:street":"Tyrol Dr",
    "iso:country":"US",
    "sg:address":"35 Tyrol Dr",
    "sg:city":"Buffalo",
    "sg:classifiers":[
        {
            "category":"Insurance",
            "subcategory":"Health Insurance",
            "type":"Services"
        }
    ],
    "sg:phone":"+1 716 608 7777",
    "sg:postcode":"14227",
    "sg:province":"NY",
    "sg:tags":[
        "carrier"
    ],
    "wof:name":"Labor Health Trust Fund",
    "wof:placetype":"venue"
},
  "geometry": {"coordinates":[-78.75282300000001,42.873224],"type":"Point"}
}