{
  "type": "Feature",
  "properties": {
    "addr:full":"110 W 31 St New York NY 10001",
    "addr:housenumber":"110",
    "addr:postcode":"10001",
    "addr:street":"W 31 St",
    "iso:country":"US",
    "sg:address":"110 W 31 St",
    "sg:city":"New York",
    "sg:classifiers":[
        {
            "category":"Real Estate",
            "subcategory":"Real Estate Agent",
            "type":"Services"
        }
    ],
    "sg:phone":"+1 212 967 3264",
    "sg:postcode":"10001",
    "sg:province":"NY",
    "wof:name":"100 W 31st Realty Corp",
    "wof:placetype":"venue"
},
  "geometry": {"coordinates":[-73.991823,40.748912],"type":"Point"}
}