{
  "type": "Feature",
  "properties": {
    "iso:country":"US",
    "sg:address":"2100 South Rd",
    "sg:city":"Poughkeepsie",
    "sg:classifiers":[
        {
            "category":"Shopping",
            "subcategory":"Clothing, Apparel, & Fashions",
            "type":"Retail Goods"
        }
    ],
    "sg:phone":"+1 845 298 2843",
    "sg:postcode":"12601",
    "sg:province":"NY",
    "sg:tags":[
        "girls'",
        "clothing"
    ],
    "sg:website":"http://www.limitedtoo.com/",
    "wof:name":"Limited Too",
    "wof:placetype":"venue"
},
  "geometry": {"coordinates":[-73.91651899999999,41.632858],"type":"Point"}
}