{
  "type": "Feature",
  "properties": {
    "addr:full":"182 Co Rd 21 Hermon NY 13617",
    "addr:housenumber":"182;21",
    "addr:postcode":"13617",
    "addr:street":"Co Rd",
    "iso:country":"US",
    "sg:address":"182 Co Rd 21",
    "sg:city":"Hermon",
    "sg:classifiers":[
        {
            "category":"Restaurant",
            "type":"Food & Drink"
        }
    ],
    "sg:phone":"+1   ",
    "sg:postcode":"13617",
    "sg:province":"NY",
    "sg:tags":[
        "eating"
    ],
    "wof:name":"Wishbone Acres Farms",
    "wof:placetype":"venue"
},
  "geometry": {"coordinates":[-75.225458,44.477382],"type":"Point"}
}