{
  "type": "Feature",
  "properties": {
    "iso:country":"US",
    "sg:address":"25 W. 36th Street 8th Floor",
    "sg:city":"New York",
    "sg:classifiers":[
        {
            "category":"Professional",
            "subcategory":"Advertising",
            "type":"Services"
        }
    ],
    "sg:phone":"+1 646 473 1383",
    "sg:postcode":"10018",
    "sg:province":"NY",
    "sg:tags":[
        "virtual-worlds",
        "social-media",
        "casual-games",
        "visual-web",
        "interactive-advertising"
    ],
    "sg:website":"http://www.electricsheepcompany.com/",
    "wof:name":"The Electric Sheep",
    "wof:placetype":"venue"
},
  "geometry": {"coordinates":[-73.984291,40.750057],"type":"Point"}
}