{
  "type": "Feature",
  "properties": {
    "addr:full":"274 Madison Ave New York NY 10016",
    "addr:housenumber":"274",
    "addr:postcode":"10016",
    "addr:street":"Madison Ave",
    "iso:country":"US",
    "sg:address":"274 Madison Ave",
    "sg:city":"New York",
    "sg:classifiers":[
        {
            "category":"Real Estate",
            "subcategory":"Real Estate Operator",
            "type":"Services"
        }
    ],
    "sg:phone":"+1 212 689 4097",
    "sg:postcode":"10016",
    "sg:province":"NY",
    "sg:tags":[
        "building",
        "nonresidential"
    ],
    "wof:name":"274 Madison Co LP",
    "wof:placetype":"venue"
},
  "geometry": {"coordinates":[-73.98048300000001,40.751205],"type":"Point"}
}