{
  "type": "Feature",
  "properties": {
    "addr:full":"235 Hoyt St Brooklyn NY 11217",
    "addr:housenumber":"235",
    "addr:postcode":"11217",
    "addr:street":"Hoyt St",
    "iso:country":"US",
    "sg:address":"235 Hoyt St",
    "sg:city":"Brooklyn",
    "sg:classifiers":[
        {
            "category":"Personal",
            "type":"Services"
        }
    ],
    "sg:phone":"+1 347 420 2888",
    "sg:postcode":"11217",
    "sg:province":"NY",
    "sg:tags":[
        "car",
        "loading",
        "unloading"
    ],
    "wof:name":"Maddog Movers",
    "wof:placetype":"venue"
},
  "geometry": {"coordinates":[-73.990122,40.683167],"type":"Point"}
}