{
  "type": "Feature",
  "properties": {
    "iso:country":"US",
    "sg:address":"3184 Pepperwood Bend",
    "sg:city":"Marcellus",
    "sg:classifiers":[
        {
            "category":"Real Estate",
            "subcategory":"Architect",
            "type":"Services"
        }
    ],
    "sg:phone":"+1 315 673 4125",
    "sg:postcode":"13108",
    "sg:province":"NY",
    "wof:name":"Thomas Arctander Architects",
    "wof:placetype":"venue"
},
  "geometry": {"coordinates":[-76.291083,42.987535],"type":"Point"}
}