{
  "type": "Feature",
  "properties": {
    "iso:country":"US",
    "sg:address":"364 Route 25A",
    "sg:city":"Mount Sinai",
    "sg:classifiers":[
        {
            "category":"Autos & Motor Vehicles",
            "subcategory":"Automobile Sales",
            "type":"Retail Goods"
        },
        {
            "category":"Taxi",
            "type":"Transportation"
        },
        {
            "category":"Airline",
            "type":"Transportation"
        }
    ],
    "sg:phone":"+1 631 473 0707",
    "sg:postcode":"11766",
    "sg:province":"NY",
    "sg:tags":[
        "shuttle",
        "airport",
        "limo"
    ],
    "wof:name":"Call A Cab Transport Inc",
    "wof:placetype":"venue"
},
  "geometry": {"coordinates":[-73.02488099999999,40.934061],"type":"Point"}
}