{
  "type": "Feature",
  "properties": {
    "addr:full":"2629 Elmwood Ave Buffalo NY 14217",
    "addr:housenumber":"2629",
    "addr:postcode":"14217",
    "addr:street":"Elmwood Ave",
    "iso:country":"US",
    "sg:address":"2629 Elmwood Ave",
    "sg:city":"Buffalo",
    "sg:classifiers":[
        {
            "category":"Health Services",
            "subcategory":"Doctor",
            "type":"Services"
        }
    ],
    "sg:phone":"+1 716 876 8136",
    "sg:postcode":"14217",
    "sg:province":"NY",
    "wof:name":"Collard J Michael",
    "wof:placetype":"venue"
},
  "geometry": {"coordinates":[-78.878665,42.968628],"type":"Point"}
}