{
  "type": "Feature",
  "properties": {
    "addr:full":"240 W 40 St New York NY 10018",
    "addr:housenumber":"240",
    "addr:postcode":"10018",
    "addr:street":"W 40 St",
    "iso:country":"US",
    "sg:address":"240 W 40 St",
    "sg:city":"New York",
    "sg:classifiers":[
        {
            "category":"Retail",
            "subcategory":"Repair Shop",
            "type":"Services"
        }
    ],
    "sg:phone":"+1 646 509 2828",
    "sg:postcode":"10018",
    "sg:province":"NY",
    "sg:tags":[
        "lock",
        "locksmith"
    ],
    "wof:name":"24 Hr Locksmith",
    "wof:placetype":"venue"
},
  "geometry": {"coordinates":[-73.989886,40.755395],"type":"Point"}
}