{
  "type": "Feature",
  "properties": {
    "addr:full":"2313 E 19th St Brooklyn NY 11229",
    "addr:housenumber":"2313",
    "addr:postcode":"11229",
    "addr:street":"E 19Th St",
    "iso:country":"US",
    "sg:address":"2313 E 19th St",
    "sg:city":"Brooklyn",
    "sg:phone":"+1 718 648 4603",
    "sg:postcode":"11229",
    "sg:province":"NY",
    "wof:name":"Allstate Transmission",
    "wof:placetype":"venue"
},
  "geometry": {"coordinates":[-73.951702,40.59448],"type":"Point"}
}