{
  "type": "Feature",
  "properties": {
    "addr:full":"203 Mamaroneck Ave White Plains NY 10601",
    "addr:housenumber":"203",
    "addr:postcode":"10601",
    "addr:street":"Mamaroneck Ave",
    "iso:country":"US",
    "sg:address":"203 Mamaroneck Ave",
    "sg:city":"White Plains",
    "sg:classifiers":[
        {
            "category":"Shopping",
            "subcategory":"Musical Instruments",
            "type":"Retail Goods"
        }
    ],
    "sg:phone":"+1 914 421 0069",
    "sg:postcode":"10601",
    "sg:province":"NY",
    "sg:website":"www.tfta.com",
    "wof:name":"Toys From The Attic Inc",
    "wof:placetype":"venue"
},
  "geometry": {"coordinates":[-73.764933,41.028581],"type":"Point"}
}