{
  "type": "Feature",
  "properties": {
    "addr:full":"324 E 95th St New York NY 10128",
    "addr:housenumber":"324",
    "addr:postcode":"10128",
    "addr:street":"E 95Th St",
    "iso:country":"US",
    "sg:address":"324 E 95th St",
    "sg:city":"New York",
    "sg:classifiers":[
        {
            "category":"Retail",
            "subcategory":"Auto Repair",
            "type":"Services"
        }
    ],
    "sg:phone":"+1 917 492 1573",
    "sg:postcode":"10128",
    "sg:province":"NY",
    "sg:tags":[
        "motorcycle"
    ],
    "sg:website":"www.speedmotorcyclesnyc.com",
    "wof:name":"Speed Motorcycle Repair",
    "wof:placetype":"venue"
},
  "geometry": {"coordinates":[-73.946308,40.782803],"type":"Point"}
}