{
  "type": "Feature",
  "properties": {
    "addr:full":"149 N Park Ave Rockville Centre NY 11570",
    "addr:housenumber":"149",
    "addr:postcode":"11570",
    "addr:street":"N Park Ave",
    "iso:country":"US",
    "sg:address":"149 N Park Ave",
    "sg:city":"Rockville Centre",
    "sg:classifiers":[
        {
            "category":"Food & Beverages",
            "subcategory":"Groceries & Convenience Stores",
            "type":"Retail Goods"
        }
    ],
    "sg:phone":"+1 516 763 2044",
    "sg:postcode":"11570",
    "sg:province":"NY",
    "sg:tags":[
        "deli",
        "grocer"
    ],
    "wof:name":"North Park Deli & Grocery",
    "wof:placetype":"venue"
},
  "geometry": {"coordinates":[-73.64487,40.661152],"type":"Point"}
}