{
  "type": "Feature",
  "properties": {
    "addr:full":"9 Hemlock Ln Thiells NY 10984",
    "addr:housenumber":"9",
    "addr:postcode":"10984",
    "addr:street":"Hemlock Ln",
    "iso:country":"US",
    "sg:address":"9 Hemlock Ln",
    "sg:city":"Thiells",
    "sg:classifiers":[
        {
            "category":"Building & Trades",
            "subcategory":"Construction",
            "type":"Services"
        }
    ],
    "sg:phone":"+1 845 947 0331",
    "sg:postcode":"10984",
    "sg:province":"NY",
    "sg:tags":[
        "carpentry",
        "contractor"
    ],
    "wof:name":"Bnv Carpentry",
    "wof:placetype":"venue"
},
  "geometry": {"coordinates":[-74.01115299999999,41.210225],"type":"Point"}
}