{
  "type": "Feature",
  "properties": {
    "addr:full":"1184 Troy Schenectady Rd # 101 Latham NY 12110",
    "addr:housenumber":"1184",
    "addr:postcode":"12110",
    "addr:street":"Troy Schenectady Rd # 101",
    "iso:country":"US",
    "sg:address":"1184 Troy Schenectady Rd # 101",
    "sg:city":"Latham",
    "sg:classifiers":[
        {
            "category":"Wholesale",
            "subcategory":"Groceries",
            "type":"Manufacturing & Wholesale Goods"
        }
    ],
    "sg:phone":"+1 518 452 1834",
    "sg:postcode":"12110",
    "sg:province":"NY",
    "sg:tags":[
        "food",
        "products-wholesale"
    ],
    "wof:name":"Advantage Sales & Marketing Inc",
    "wof:placetype":"venue"
},
  "geometry": {"coordinates":[-73.82071999999999,42.770287],"type":"Point"}
}