{
  "type": "Feature",
  "properties": {
    "iso:country":"US",
    "sg:address":"120 Broadway",
    "sg:city":"Albany",
    "sg:classifiers":[
        {
            "category":"Professional",
            "subcategory":"Lawyer & Legal Services",
            "type":"Services"
        }
    ],
    "sg:phone":"+1   ",
    "sg:postcode":"12204",
    "sg:province":"NY",
    "sg:tags":[
        "medical"
    ],
    "wof:name":"Bruce Maston Dr",
    "wof:placetype":"venue"
},
  "geometry": {"coordinates":[-73.72990900000001,42.685291],"type":"Point"}
}