{
  "type": "Feature",
  "properties": {
    "iso:country":"US",
    "sg:address":"2 Gracie Ln",
    "sg:city":"Shirley",
    "sg:classifiers":[
        {
            "category":"Health Services",
            "subcategory":"Doctor",
            "type":"Services"
        }
    ],
    "sg:phone":"+1 631 399 6003",
    "sg:postcode":"11937",
    "sg:province":"NY",
    "sg:tags":[
        "physician",
        "surgeon"
    ],
    "wof:name":"N V Karhade MD",
    "wof:placetype":"venue"
},
  "geometry": {"coordinates":[-72.201037,40.940661],"type":"Point"}
}