{
  "type": "Feature",
  "properties": {
    "addr:full":"214 State St Schenectady NY 12305",
    "addr:housenumber":"214",
    "addr:postcode":"12305",
    "addr:street":"State St",
    "iso:country":"US",
    "sg:address":"214 State St",
    "sg:city":"Schenectady",
    "sg:classifiers":[
        {
            "category":"Social Services",
            "type":"Services"
        }
    ],
    "sg:phone":"+1   ",
    "sg:postcode":"12305",
    "sg:province":"NY",
    "sg:tags":[
        "consulting",
        "management"
    ],
    "wof:name":"Ridge Health Services",
    "wof:placetype":"venue"
},
  "geometry": {"coordinates":[-73.94437600000001,42.814259],"type":"Point"}
}