{
  "type": "Feature",
  "properties": {
    "addr:full":"9799 Harper Rd Corfu NY 14036",
    "addr:housenumber":"9799",
    "addr:postcode":"14036",
    "addr:street":"Harper Rd",
    "iso:country":"US",
    "sg:address":"9799 Harper Rd",
    "sg:city":"Corfu",
    "sg:classifiers":[
        {
            "category":"Real Estate",
            "subcategory":"Developer",
            "type":"Services"
        }
    ],
    "sg:phone":"+1 585 547 9218",
    "sg:postcode":"14036",
    "sg:province":"NY",
    "sg:tags":[
        "cemetery"
    ],
    "wof:name":"Darien Cemetery Association",
    "wof:placetype":"venue"
},
  "geometry": {"coordinates":[-78.354416,42.93819],"type":"Point"}
}