{
  "type": "Feature",
  "properties": {
    "addr:full":"12 New St Walton NY 13856",
    "addr:housenumber":"12",
    "addr:postcode":"13856",
    "addr:street":"New St",
    "iso:country":"US",
    "sg:address":"12 New St",
    "sg:city":"Walton",
    "sg:classifiers":[
        {
            "category":"Social Services",
            "type":"Services"
        }
    ],
    "sg:phone":"+1 607 865 8129",
    "sg:postcode":"13856",
    "sg:province":"NY",
    "sg:tags":[
        "mission"
    ],
    "wof:name":"Mormon Missionaries",
    "wof:placetype":"venue"
},
  "geometry": {"coordinates":[-75.141527,42.171728],"type":"Point"}
}