{
  "type": "Feature",
  "properties": {
    "addr:full":"2124 2nd Ave Frnt 1 New York NY 10029",
    "addr:housenumber":"2124;1",
    "addr:postcode":"10029",
    "addr:street":"2Nd Ave Frnt",
    "iso:country":"US",
    "sg:address":"2124 2nd Ave Frnt 1",
    "sg:city":"New York",
    "sg:classifiers":[
        {
            "category":"Home & Garden",
            "subcategory":"Hardware",
            "type":"Retail Goods"
        }
    ],
    "sg:phone":"+1 212 369 2219",
    "sg:postcode":"10029",
    "sg:province":"NY",
    "sg:tags":[
        "store"
    ],
    "wof:name":"Lenox Hardware Inc",
    "wof:placetype":"venue"
},
  "geometry": {"coordinates":[-73.94082,40.792537],"type":"Point"}
}