{
  "type": "Feature",
  "properties": {
    "addr:full":"400 E Gun Hill Rd Bronx NY 10467",
    "addr:housenumber":"400",
    "addr:postcode":"10467",
    "addr:street":"E Gun Hill Rd",
    "iso:country":"US",
    "sg:address":"400 E Gun Hill Rd",
    "sg:city":"Bronx",
    "sg:classifiers":[
        {
            "category":"Insurance",
            "subcategory":"Insurance Agent",
            "type":"Services"
        }
    ],
    "sg:phone":"+1 718 798 6090",
    "sg:postcode":"10467",
    "sg:province":"NY",
    "wof:name":"Douglas Brokers Associated",
    "wof:placetype":"venue"
},
  "geometry": {"coordinates":[-73.87094399999999,40.87851],"type":"Point"}
}