{
  "type": "Feature",
  "properties": {
    "addr:full":"747 Manhattan Ave Brooklyn NY 11222",
    "addr:housenumber":"747",
    "addr:postcode":"11222",
    "addr:street":"Manhattan Ave",
    "iso:country":"US",
    "sg:address":"747 Manhattan Ave",
    "sg:city":"Brooklyn",
    "sg:classifiers":[
        {
            "category":"Wholesale",
            "subcategory":"Electrical",
            "type":"Manufacturing & Wholesale Goods"
        }
    ],
    "sg:phone":"+1 718 383 7110",
    "sg:postcode":"11222",
    "sg:province":"NY",
    "sg:tags":[
        "electronic"
    ],
    "wof:name":"Mtv Super Sound Elec & Appls",
    "wof:placetype":"venue"
},
  "geometry": {"coordinates":[-73.95226099999999,40.725928],"type":"Point"}
}