{
  "type": "Feature",
  "properties": {
    "addr:full":"13 Weed St Plattsburgh NY 12901",
    "addr:housenumber":"13",
    "addr:postcode":"12901",
    "addr:street":"Weed St",
    "iso:country":"US",
    "sg:address":"13 Weed St",
    "sg:city":"Plattsburgh",
    "sg:classifiers":[
        {
            "category":"Wholesale",
            "subcategory":"Durable Goods & Equipment",
            "type":"Manufacturing & Wholesale Goods"
        }
    ],
    "sg:phone":"+1 518 563 4211",
    "sg:postcode":"12901",
    "sg:province":"NY",
    "sg:tags":[
        "fire",
        "extinguisher"
    ],
    "wof:name":"Plattsburgh Gauge Repair Svc",
    "wof:placetype":"venue"
},
  "geometry": {"coordinates":[-73.454075,44.708889],"type":"Point"}
}