{
  "type": "Feature",
  "properties": {
    "addr:full":"10 Stuffle St Cropseyville NY 12052",
    "addr:housenumber":"10",
    "addr:postcode":"12052",
    "addr:street":"Stuffle St",
    "iso:country":"US",
    "sg:address":"10 Stuffle St",
    "sg:city":"Cropseyville",
    "sg:classifiers":[
        {
            "category":"Building & Trades",
            "subcategory":"Construction",
            "type":"Services"
        }
    ],
    "sg:phone":"+1 518 279 3724",
    "sg:postcode":"12052",
    "sg:province":"NY",
    "sg:tags":[
        "excavating",
        "contractor"
    ],
    "wof:name":"KMR Enterprises Inc",
    "wof:placetype":"venue"
},
  "geometry": {"coordinates":[-73.49894,42.7829],"type":"Point"}
}