{
  "type": "Feature",
  "properties": {
    "addr:full":"70 Harper St Rochester NY 14607",
    "addr:housenumber":"70",
    "addr:postcode":"14607",
    "addr:street":"Harper St",
    "iso:country":"US",
    "sg:address":"70 Harper St",
    "sg:city":"Rochester",
    "sg:classifiers":[
        {
            "category":"Organizations",
            "subcategory":"Religious Organization",
            "type":"Services"
        }
    ],
    "sg:phone":"+1 585 244 7403",
    "sg:postcode":"14607",
    "sg:province":"NY",
    "sg:tags":[
        "clergy"
    ],
    "wof:name":"Richard Gilbert",
    "wof:placetype":"venue"
},
  "geometry": {"coordinates":[-77.58994300000001,43.146847],"type":"Point"}
}