{
  "type": "Feature",
  "properties": {
    "addr:full":"1283 Arsenal St Watertown NY 13601",
    "addr:housenumber":"1283",
    "addr:postcode":"st;13601",
    "addr:street":"Arsenal",
    "iso:country":"US",
    "sg:address":"1283 Arsenal St",
    "sg:city":"Watertown",
    "sg:classifiers":[
        {
            "category":"Health Services",
            "subcategory":"Doctor",
            "type":"Services"
        }
    ],
    "sg:phone":"+1 315 785 9620",
    "sg:postcode":"13601",
    "sg:province":"NY",
    "sg:tags":[
        "dentist"
    ],
    "wof:name":"Aspen Dental",
    "wof:placetype":"venue"
},
  "geometry": {"coordinates":[-75.947052,43.975858],"type":"Point"}
}