{
  "type": "Feature",
  "properties": {
    "addr:full":"1300 Ulster Ave Kingston NY 12401",
    "addr:housenumber":"1300",
    "addr:postcode":"12401",
    "addr:street":"Ulster Ave",
    "iso:country":"US",
    "sg:address":"1300 Ulster Ave",
    "sg:city":"Kingston",
    "sg:classifiers":[
        {
            "category":"Professional",
            "subcategory":"Accounting & Tax Preparation",
            "type":"Services"
        },
        {
            "category":"Banks & Credit Unions",
            "subcategory":"Financial Services",
            "type":"Services"
        }
    ],
    "sg:phone":"+1 845 382 1749",
    "sg:postcode":"12401",
    "sg:province":"NY",
    "sg:tags":[
        "return",
        "preparation-business",
        "taxes-consultants",
        "loan",
        "reporting",
        "representative",
        "alternative",
        "bookkeeping"
    ],
    "sg:website":"http://www.hrblock.com",
    "wof:name":"H&R Block",
    "wof:placetype":"venue"
},
  "geometry": {"coordinates":[-73.99052,41.960405],"type":"Point"}
}