{
  "type": "Feature",
  "properties": {
    "iso:country":"US",
    "sg:address":"300 West Ave",
    "sg:city":"Brockport",
    "sg:classifiers":[
        {
            "category":"Health Services",
            "subcategory":"Doctor",
            "type":"Services"
        }
    ],
    "sg:phone":"+1 585 637 3905",
    "sg:postcode":"14420",
    "sg:province":"NY",
    "sg:tags":[
        "medical"
    ],
    "wof:name":"Lake Side Hospital",
    "wof:placetype":"venue"
},
  "geometry": {"coordinates":[-77.952742,43.220125],"type":"Point"}
}