{
  "type": "Feature",
  "properties": {
    "iso:country":"US",
    "sg:address":"2471 Browncroft Blvd",
    "sg:city":"Rochester",
    "sg:classifiers":[
        {
            "category":"Building & Trades",
            "subcategory":"Plumbing",
            "type":"Services"
        }
    ],
    "sg:phone":"+1 585 381 4384",
    "sg:postcode":"14625",
    "sg:province":"NY",
    "sg:tags":[
        "plumbing",
        "contractor"
    ],
    "wof:name":"John W Hebbs Plumbing & Htg",
    "wof:placetype":"venue"
},
  "geometry": {"coordinates":[-77.508422,43.153581],"type":"Point"}
}