{
  "type": "Feature",
  "properties": {
    "iso:country":"US",
    "sg:address":"364 Main St",
    "sg:city":"Newfield",
    "sg:classifiers":[
        {
            "category":"Organizations",
            "subcategory":"Religious Organization",
            "type":"Services"
        }
    ],
    "sg:phone":"+1 607 564 7716",
    "sg:postcode":"14867",
    "sg:province":"NY",
    "sg:tags":[
        "church"
    ],
    "sg:website":"www.pbcnewfield.org",
    "wof:name":"Peoples Baptist Church",
    "wof:placetype":"venue"
},
  "geometry": {"coordinates":[-76.601178,42.354911],"type":"Point"}
}