{
  "type": "Feature",
  "properties": {
    "iso:country":"US",
    "sg:address":"4 High St",
    "sg:city":"Saugerties",
    "sg:classifiers":[
        {
            "category":"Government",
            "subcategory":"Office",
            "type":"Public Place"
        }
    ],
    "sg:phone":"+1 845 246 5657",
    "sg:postcode":"12477",
    "sg:province":"NY",
    "sg:tags":[
        "village"
    ],
    "wof:name":"Saugerties Supervisor",
    "wof:placetype":"venue"
},
  "geometry": {"coordinates":[-73.95850900000001,42.080645],"type":"Point"}
}