{
  "type": "Feature",
  "properties": {
    "addr:full":"623 Idlewood Ct Baldwinsville NY 13027",
    "addr:housenumber":"623",
    "addr:postcode":"13027",
    "addr:street":"Idlewood Ct",
    "iso:country":"US",
    "sg:address":"623 Idlewood Ct",
    "sg:city":"Baldwinsville",
    "sg:classifiers":[
        {
            "category":"Shopping",
            "subcategory":"Bicycles & Sporting Goods",
            "type":"Retail Goods"
        }
    ],
    "sg:phone":"+1   ",
    "sg:postcode":"13027",
    "sg:province":"NY",
    "wof:name":"Foxfire Golf Tennis",
    "wof:placetype":"venue"
},
  "geometry": {"coordinates":[-76.317041,43.135563],"type":"Point"}
}