{
  "type": "Feature",
  "properties": {
    "iso:country":"US",
    "sg:address":"105 Bennett Rd",
    "sg:city":"Camillus",
    "sg:classifiers":[
        {
            "category":"Building & Trades",
            "subcategory":"Electrical",
            "type":"Services"
        }
    ],
    "sg:phone":"+1 315 488 5888",
    "sg:postcode":"13031",
    "sg:province":"NY",
    "sg:tags":[
        "electrician"
    ],
    "wof:name":"Universal Electric",
    "wof:placetype":"venue"
},
  "geometry": {"coordinates":[-76.278442,43.05378],"type":"Point"}
}