{
  "type": "Feature",
  "properties": {
    "iso:country":"US",
    "sg:address":"2551 Bainbridge Ave",
    "sg:city":"Bronx",
    "sg:classifiers":[
        {
            "category":"Government",
            "subcategory":"Office",
            "type":"Public Place"
        }
    ],
    "sg:phone":"+1 718 220 6609",
    "sg:postcode":"10458",
    "sg:province":"NY",
    "sg:tags":[
        "village"
    ],
    "wof:name":"Bronx Human Resources Dept",
    "wof:placetype":"venue"
},
  "geometry": {"coordinates":[-73.893365,40.862347],"type":"Point"}
}