{
  "type": "Feature",
  "properties": {
    "addr:full":"33 W State St Binghamton NY 13901",
    "addr:housenumber":"33",
    "addr:postcode":"13901",
    "addr:street":"W State St",
    "iso:country":"US",
    "sg:address":"33 W State St",
    "sg:city":"Binghamton",
    "sg:classifiers":[
        {
            "category":"Personal",
            "subcategory":"Shoe Repair & Shine",
            "type":"Services"
        }
    ],
    "sg:phone":"+1 607 722 1872",
    "sg:postcode":"13901",
    "sg:province":"NY",
    "sg:tags":[
        "repairing",
        "boot"
    ],
    "wof:name":"Leather Corner Shoe Repair",
    "wof:placetype":"venue"
},
  "geometry": {"coordinates":[-75.90472,42.109638],"type":"Point"}
}