{
  "type": "Feature",
  "properties": {
    "iso:country":"US",
    "sg:address":"4 Westfall Ave",
    "sg:city":"Troy",
    "sg:classifiers":[
        {
            "category":"Restaurant",
            "type":"Food & Drink"
        }
    ],
    "sg:phone":"+1   ",
    "sg:postcode":"12180",
    "sg:province":"NY",
    "sg:tags":[
        "eating"
    ],
    "wof:name":"Giulianos Premier Party Rental",
    "wof:placetype":"venue"
},
  "geometry": {"coordinates":[-73.65196899999999,42.703859],"type":"Point"}
}