{
  "type": "Feature",
  "properties": {
    "addr:full":"31 Kallop Rd Kingston NY 12401",
    "addr:housenumber":"31",
    "addr:postcode":"12401",
    "addr:street":"Kallop Rd",
    "iso:country":"US",
    "sg:address":"31 Kallop Rd",
    "sg:city":"Kingston",
    "sg:classifiers":[
        {
            "category":"Food & Beverages",
            "subcategory":"Meat & Fish",
            "type":"Retail Goods"
        }
    ],
    "sg:phone":"+1   ",
    "sg:postcode":"12401",
    "sg:province":"NY",
    "wof:name":"Five Bears Meats LLC",
    "wof:placetype":"venue"
},
  "geometry": {"coordinates":[-74.07353999999999,41.855677],"type":"Point"}
}