{
  "type": "Feature",
  "properties": {
    "iso:country":"US",
    "sg:address":"629 Medford Ave Ste 2",
    "sg:city":"Patchogue",
    "sg:classifiers":[
        {
            "category":"Professional",
            "subcategory":"Lawyer & Legal Services",
            "type":"Services"
        }
    ],
    "sg:phone":"+1 631 289 3745",
    "sg:postcode":"11772",
    "sg:province":"NY",
    "wof:name":"Zysk Robert J",
    "wof:placetype":"venue"
},
  "geometry": {"coordinates":[-73.008698,40.783699],"type":"Point"}
}