{
  "type": "Feature",
  "properties": {
    "addr:full":"30 W 57th St New York NY 10019",
    "addr:housenumber":"30",
    "addr:postcode":"10019",
    "addr:street":"W 57Th St",
    "iso:country":"US",
    "sg:address":"30 W 57th St",
    "sg:city":"New York",
    "sg:classifiers":[
        {
            "category":"Shopping",
            "subcategory":"Clothing, Apparel, & Fashions",
            "type":"Retail Goods"
        }
    ],
    "sg:phone":"+1 212 246 0085",
    "sg:postcode":"10019",
    "sg:province":"NY",
    "sg:tags":[
        "clothing",
        "women's"
    ],
    "wof:name":"Marinella",
    "wof:placetype":"venue"
},
  "geometry": {"coordinates":[-73.974964,40.763237],"type":"Point"}
}