{
  "type": "Feature",
  "properties": {
    "addr:full":"133 Saratoga Rd S Glens Falls NY 12803",
    "addr:housenumber":"133",
    "addr:postcode":"12803",
    "addr:street":"Saratoga Rd",
    "iso:country":"US",
    "sg:address":"133 Saratoga Rd",
    "sg:city":"S Glens Falls",
    "sg:classifiers":[
        {
            "category":"Banks & Credit Unions",
            "subcategory":"Bank",
            "type":"Services"
        }
    ],
    "sg:phone":"+1 518 793 7668",
    "sg:postcode":"12803",
    "sg:province":"NY",
    "wof:name":"Trustco Bank",
    "wof:placetype":"venue"
},
  "geometry": {"coordinates":[-73.63766099999999,43.290133],"type":"Point"}
}