{
  "type": "Feature",
  "properties": {
    "addr:full":"978 Clay Ave Bronx NY 10456",
    "addr:housenumber":"978",
    "addr:postcode":"10456",
    "addr:street":"Clay Ave",
    "iso:country":"US",
    "sg:address":"978 Clay Ave",
    "sg:city":"Bronx",
    "sg:classifiers":[
        {
            "category":"Building & Trades",
            "subcategory":"Construction",
            "type":"Services"
        }
    ],
    "sg:phone":"+1 718 537 3167",
    "sg:postcode":"10456",
    "sg:province":"NY",
    "sg:tags":[
        "company"
    ],
    "wof:name":"Wolet Construction Corp",
    "wof:placetype":"venue"
},
  "geometry": {"coordinates":[-73.91296199999999,40.82816],"type":"Point"}
}