{
  "type": "Feature",
  "properties": {
    "addr:full":"1491 Westchester Ave Bronx NY 10472",
    "addr:housenumber":"1491",
    "addr:postcode":"10472",
    "addr:street":"Westchester Ave",
    "iso:country":"US",
    "sg:address":"1491 Westchester Ave",
    "sg:city":"Bronx",
    "sg:classifiers":[
        {
            "category":"Personal",
            "subcategory":"Barber",
            "type":"Services"
        }
    ],
    "sg:phone":"+1 718 328 5854",
    "sg:postcode":"10472",
    "sg:province":"NY",
    "wof:name":"La Ideal Barber Shop",
    "wof:placetype":"venue"
},
  "geometry": {"coordinates":[-73.88059699999999,40.828736],"type":"Point"}
}