{
  "type": "Feature",
  "properties": {
    "addr:full":"22 Holland Ave Pine Bush NY 12566",
    "addr:housenumber":"22",
    "addr:postcode":"12566",
    "addr:street":"Holland Ave",
    "iso:country":"US",
    "sg:address":"22 Holland Ave",
    "sg:city":"Pine Bush",
    "sg:classifiers":[
        {
            "category":"Organizations",
            "subcategory":"Religious Organization",
            "type":"Services"
        }
    ],
    "sg:phone":"+1 845 744 2391",
    "sg:postcode":"12566",
    "sg:province":"NY",
    "wof:name":"Church Of The Infant Saviour",
    "wof:placetype":"venue"
},
  "geometry": {"coordinates":[-74.303364,41.606624],"type":"Point"}
}