{
  "type": "Feature",
  "properties": {
    "addr:full":"22423 Co Rd 42 Carthage NY 13619",
    "addr:housenumber":"22423;42",
    "addr:postcode":"13619",
    "addr:street":"Co Rd",
    "iso:country":"US",
    "sg:address":"22423 Co Rd 42",
    "sg:city":"Carthage",
    "sg:classifiers":[
        {
            "category":"Shopping",
            "subcategory":"Bicycles & Sporting Goods",
            "type":"Retail Goods"
        }
    ],
    "sg:phone":"+1 315 493 2295",
    "sg:postcode":"13619",
    "sg:province":"NY",
    "sg:tags":[
        "equipment",
        "archery",
        "supply"
    ],
    "wof:name":"Ferari's Archery",
    "wof:placetype":"venue"
},
  "geometry": {"coordinates":[-75.56016,44.014246],"type":"Point"}
}