{
  "type": "Feature",
  "properties": {
    "addr:full":"76 North State Rd. Briarcliff Manor NY 10510",
    "addr:housenumber":"76",
    "addr:postcode":"10510",
    "addr:street":"North State Rd.",
    "iso:country":"US",
    "sg:address":"76 North State Rd.",
    "sg:city":"Briarcliff Manor",
    "sg:classifiers":[
        {
            "category":"Arts & Performance",
            "subcategory":"Arts Center",
            "type":"Entertainment"
        }
    ],
    "sg:phone":"+1 914 502 0088",
    "sg:postcode":"10510",
    "sg:province":"NY",
    "sg:website":"www.amazeinpottery.com/",
    "wof:name":"A Maze In Pottery",
    "wof:placetype":"venue"
},
  "geometry": {"coordinates":[-73.830236,41.152062],"type":"Point"}
}