{
  "type": "Feature",
  "properties": {
    "addr:full":"156 Main St Fishkill NY 12524",
    "addr:housenumber":"156",
    "addr:postcode":"12524",
    "addr:street":"Main St",
    "iso:country":"US",
    "sg:address":"156 Main St",
    "sg:city":"Fishkill",
    "sg:classifiers":[
        {
            "category":"Retail",
            "subcategory":"Self-service Laundry",
            "type":"Services"
        }
    ],
    "sg:phone":"+1 845 896 7692",
    "sg:postcode":"12524",
    "sg:province":"NY",
    "wof:name":"Wash & Dry",
    "wof:placetype":"venue"
},
  "geometry": {"coordinates":[-73.907257,41.531444],"type":"Point"}
}