{
  "type": "Feature",
  "properties": {
    "addr:full":"10105 120th St South Richmond Hill NY 11419",
    "addr:housenumber":"10105",
    "addr:postcode":"11419",
    "addr:street":"120Th St South",
    "iso:country":"US",
    "sg:address":"10105 120th St",
    "sg:city":"South Richmond Hill",
    "sg:classifiers":[
        {
            "category":"Banks & Credit Unions",
            "subcategory":"Financial Services",
            "type":"Services"
        }
    ],
    "sg:phone":"+1 718 850 0100",
    "sg:postcode":"11419",
    "sg:province":"NY",
    "sg:tags":[
        "broker",
        "mortgage"
    ],
    "wof:name":"Empire Capital Mortgage Corp",
    "wof:placetype":"venue"
},
  "geometry": {"coordinates":[-73.824799,40.690201],"type":"Point"}
}