{
  "type": "Feature",
  "properties": {
    "iso:country":"US",
    "sg:address":"289 Adam St",
    "sg:city":"Tonawanda",
    "sg:classifiers":[
        {
            "category":"Bars & Pubs",
            "type":"Food & Drink"
        }
    ],
    "sg:phone":"+1 716 693 3946",
    "sg:postcode":"14150",
    "sg:province":"NY",
    "wof:name":"Jake's Grill",
    "wof:placetype":"venue"
},
  "geometry": {"coordinates":[-78.89131399999999,43.015356],"type":"Point"}
}