{
  "type": "Feature",
  "properties": {
    "iso:country":"US",
    "sg:address":"34 Summit View Dr",
    "sg:city":"Bayville",
    "sg:classifiers":[
        {
            "category":"Professional",
            "subcategory":"Art Services",
            "type":"Services"
        }
    ],
    "sg:phone":"+1   ",
    "sg:postcode":"11709",
    "sg:province":"NY",
    "sg:tags":[
        "commercial",
        "design",
        "datum"
    ],
    "wof:name":"Medical Media",
    "wof:placetype":"venue"
},
  "geometry": {"coordinates":[-73.574676,40.90544],"type":"Point"}
}