{
  "type": "Feature",
  "properties": {
    "addr:full":"1912 McGraw Marathon Rd Marathon NY 13803",
    "addr:housenumber":"1912",
    "addr:postcode":"13803",
    "addr:street":"Mcgraw Marathon Rd",
    "iso:country":"US",
    "sg:address":"1912 McGraw Marathon Rd",
    "sg:city":"Marathon",
    "sg:classifiers":[
        {
            "category":"Farming",
            "subcategory":"Dairy Farm",
            "type":"Manufacturing & Wholesale Goods"
        }
    ],
    "sg:phone":"+1 607 849 4288",
    "sg:postcode":"13803",
    "sg:province":"NY",
    "wof:name":"Michael Silvanic",
    "wof:placetype":"venue"
},
  "geometry": {"coordinates":[-76.03549700000001,42.513283],"type":"Point"}
}