{
  "type": "Feature",
  "properties": {
    "addr:full":"324 E Main St Riverhead NY 11901",
    "addr:housenumber":"324",
    "addr:postcode":"11901",
    "addr:street":"E Main St",
    "iso:country":"US",
    "sg:address":"324 E Main St",
    "sg:city":"Riverhead",
    "sg:classifiers":[
        {
            "category":"Retail",
            "subcategory":"Repair Shop",
            "type":"Services"
        }
    ],
    "sg:phone":"+1 631 460 0672",
    "sg:postcode":"11901",
    "sg:province":"NY",
    "sg:tags":[
        "lock",
        "locksmith"
    ],
    "wof:name":"24 Hour Emergency Locksmith",
    "wof:placetype":"venue"
},
  "geometry": {"coordinates":[-72.658057,40.91817],"type":"Point"}
}