{
  "type": "Feature",
  "properties": {
    "addr:full":"41 Windwood Dr Newburgh NY 12550",
    "addr:housenumber":"41",
    "addr:postcode":"12550",
    "addr:street":"Windwood Dr",
    "iso:country":"US",
    "sg:address":"41 Windwood Dr",
    "sg:city":"Newburgh",
    "sg:classifiers":[
        {
            "category":"Building & Trades",
            "subcategory":"Construction",
            "type":"Services"
        }
    ],
    "sg:phone":"+1 845 567 0018",
    "sg:postcode":"12550",
    "sg:province":"NY",
    "sg:tags":[
        "home",
        "improvement"
    ],
    "wof:name":"J & K Home Improvements",
    "wof:placetype":"venue"
},
  "geometry": {"coordinates":[-74.121775,41.517449],"type":"Point"}
}