{
  "type": "Feature",
  "properties": {
    "iso:country":"US",
    "sg:address":"50 Front St",
    "sg:city":"East Rockaway",
    "sg:classifiers":[
        {
            "category":"Building & Trades",
            "subcategory":"Construction",
            "type":"Services"
        }
    ],
    "sg:phone":"+1 516 596 4766",
    "sg:postcode":"11518",
    "sg:province":"NY",
    "sg:tags":[
        "contractor"
    ],
    "wof:name":"Artisan Construction Inc",
    "wof:placetype":"venue"
},
  "geometry": {"coordinates":[-73.660262,40.637906],"type":"Point"}
}