{
  "type": "Feature",
  "properties": {
    "iso:country":"US",
    "sg:address":"1 Ralph Ave",
    "sg:city":"Brentwood",
    "sg:classifiers":[
        {
            "category":"Building & Trades",
            "subcategory":"Construction",
            "type":"Services"
        }
    ],
    "sg:phone":"+1 631 951 4088",
    "sg:postcode":"11717",
    "sg:province":"NY",
    "sg:tags":[
        "contractor"
    ],
    "wof:name":"3 C K Acoustics",
    "wof:placetype":"venue"
},
  "geometry": {"coordinates":[-73.234983,40.789913],"type":"Point"}
}