{
  "type": "Feature",
  "properties": {
    "iso:country":"US",
    "sg:address":"505 Beahan Rd",
    "sg:city":"Rochester",
    "sg:classifiers":[
        {
            "category":"Personal",
            "subcategory":"Beauty Salon",
            "type":"Services"
        }
    ],
    "sg:phone":"+1 585 426 1471",
    "sg:postcode":"14624",
    "sg:province":"NY",
    "wof:name":"Laser For Hair & Skin",
    "wof:placetype":"venue"
},
  "geometry": {"coordinates":[-77.68974799999999,43.13077],"type":"Point"}
}