{
  "type": "Feature",
  "properties": {
    "iso:country":"US",
    "sg:address":"1797 1 Ave",
    "sg:city":"New York",
    "sg:classifiers":[
        {
            "category":"Farming",
            "subcategory":"Farm",
            "type":"Manufacturing & Wholesale Goods"
        }
    ],
    "sg:phone":"+1 646 672 9328",
    "sg:postcode":"10128",
    "sg:province":"NY",
    "sg:tags":[
        "crop",
        "general"
    ],
    "wof:name":"Hansol Farm Corp",
    "wof:placetype":"venue"
},
  "geometry": {"coordinates":[-73.94842199999999,40.778182],"type":"Point"}
}