{
  "type": "Feature",
  "properties": {
    "addr:full":"1379 Avenue of the Americ New York NY 10019",
    "addr:housenumber":"1379",
    "addr:postcode":"10019",
    "addr:street":"Avenue Of The",
    "iso:country":"US",
    "sg:address":"1379 Avenue of the Americ",
    "sg:city":"New York",
    "sg:classifiers":[
        {
            "category":"Banks & Credit Unions",
            "subcategory":"Bank",
            "type":"Services"
        }
    ],
    "sg:phone":"+1 212 586 2810",
    "sg:postcode":"10019",
    "sg:province":"NY",
    "wof:name":"Washington Mutual",
    "wof:placetype":"venue"
},
  "geometry": {"coordinates":[-73.977884,40.763598],"type":"Point"}
}