{
  "type": "Feature",
  "properties": {
    "addr:full":"39 Jerome Dr Farmingdale NY 11735",
    "addr:housenumber":"39",
    "addr:postcode":"11735",
    "addr:street":"Jerome Dr",
    "iso:country":"US",
    "sg:address":"39 Jerome Dr",
    "sg:city":"Farmingdale",
    "sg:classifiers":[
        {
            "category":"Professional",
            "subcategory":"Accounting & Tax Preparation",
            "type":"Services"
        }
    ],
    "sg:phone":"+1   ",
    "sg:postcode":"11735",
    "sg:province":"NY",
    "wof:name":"Betz Ruth A Sattig CPA",
    "wof:placetype":"venue"
},
  "geometry": {"coordinates":[-73.455584,40.736952],"type":"Point"}
}