{
  "type": "Feature",
  "properties": {
    "addr:full":"1537 Rosser Ave Elmont NY 11003",
    "addr:housenumber":"1537",
    "addr:postcode":"11003",
    "addr:street":"Rosser Ave",
    "iso:country":"US",
    "sg:address":"1537 Rosser Ave",
    "sg:city":"Elmont",
    "sg:classifiers":[
        {
            "category":"Manufacturing",
            "subcategory":"Apparel",
            "type":"Manufacturing & Wholesale Goods"
        }
    ],
    "sg:phone":"+1   ",
    "sg:postcode":"11003",
    "sg:province":"NY",
    "sg:tags":[
        "manufacture",
        "uniform"
    ],
    "wof:name":"Cristina Natale Inc",
    "wof:placetype":"venue"
},
  "geometry": {"coordinates":[-73.699288,40.698748],"type":"Point"}
}