{
  "type": "Feature",
  "properties": {
    "addr:full":"237 Bay Ridge Parkway Brooklyn NY 11209",
    "addr:housenumber":"237",
    "addr:postcode":"11209",
    "addr:street":"Bay Ridge Parkway",
    "iso:country":"US",
    "sg:address":"237 Bay Ridge Parkway",
    "sg:city":"Brooklyn",
    "sg:classifiers":[
        {
            "category":"Health Services",
            "subcategory":"Doctor",
            "type":"Services"
        }
    ],
    "sg:phone":"+1 718 833 5886",
    "sg:postcode":"11209",
    "sg:province":"NY",
    "wof:name":"Almoudarres Maher Physician",
    "wof:placetype":"venue"
},
  "geometry": {"coordinates":[-74.028864,40.631828],"type":"Point"}
}