{
  "type": "Feature",
  "properties": {
    "addr:full":"659 Thurston Rd Rochester NY 14619",
    "addr:housenumber":"659",
    "addr:postcode":"14619",
    "addr:street":"Thurston Rd",
    "iso:country":"US",
    "sg:address":"659 Thurston Rd",
    "sg:city":"Rochester",
    "sg:classifiers":[
        {
            "category":"Shopping",
            "subcategory":"Clothing, Apparel, & Fashions",
            "type":"Retail Goods"
        }
    ],
    "sg:phone":"+1 585 436 5820",
    "sg:postcode":"14619",
    "sg:province":"NY",
    "sg:tags":[
        "tailor"
    ],
    "wof:name":"Ali's Tailor Shop",
    "wof:placetype":"venue"
},
  "geometry": {"coordinates":[-77.650993,43.131011],"type":"Point"}
}