{
  "type": "Feature",
  "properties": {
    "addr:full":"62 Woodberry Rd New Hartford NY 13413",
    "addr:housenumber":"62",
    "addr:postcode":"13413",
    "addr:street":"Woodberry Rd",
    "iso:country":"US",
    "sg:address":"62 Woodberry Rd",
    "sg:city":"New Hartford",
    "sg:classifiers":[
        {
            "category":"Professional",
            "subcategory":"Computer Services",
            "type":"Services"
        }
    ],
    "sg:phone":"+1 315 733 8750",
    "sg:postcode":"13413",
    "sg:province":"NY",
    "sg:tags":[
        "related"
    ],
    "wof:name":"Hallways Computing",
    "wof:placetype":"venue"
},
  "geometry": {"coordinates":[-75.294259,43.060063],"type":"Point"}
}