{
  "type": "Feature",
  "properties": {
    "addr:full":"420 Franklin St Buffalo NY 14202",
    "addr:housenumber":"420",
    "addr:postcode":"14202",
    "addr:street":"Franklin St",
    "iso:country":"US",
    "sg:address":"420 Franklin St",
    "sg:city":"Buffalo",
    "sg:classifiers":[
        {
            "category":"Professional",
            "subcategory":"Lawyer & Legal Services",
            "type":"Services"
        }
    ],
    "sg:phone":"+1 716 881 1890",
    "sg:postcode":"14202",
    "sg:province":"NY",
    "wof:name":"Makowski Joseph G Esq",
    "wof:placetype":"venue"
},
  "geometry": {"coordinates":[-78.87327399999999,42.896926],"type":"Point"}
}