{
  "type": "Feature",
  "properties": {
    "iso:country":"US",
    "sg:address":"30836 Depauville Rd",
    "sg:city":"Chaumont",
    "sg:classifiers":[
        {
            "category":"Farming",
            "subcategory":"Livestock Farm",
            "type":"Manufacturing & Wholesale Goods"
        }
    ],
    "sg:phone":"+1 315 686 3341",
    "sg:postcode":"13622",
    "sg:province":"NY",
    "sg:tags":[
        "raise",
        "cattle"
    ],
    "wof:name":"Parker Henry Group LLC",
    "wof:placetype":"venue"
},
  "geometry": {"coordinates":[-76.048197,44.097474],"type":"Point"}
}