{
  "type": "Feature",
  "properties": {
    "iso:country":"US",
    "sg:address":"7028 Suzanne Ln",
    "sg:city":"Schenectady",
    "sg:classifiers":[
        {
            "category":"Retail",
            "subcategory":"Laundry & Dry Cleaning",
            "type":"Services"
        }
    ],
    "sg:phone":"+1   ",
    "sg:postcode":"12303",
    "sg:province":"NY",
    "wof:name":"Jzr Commercial Carpet Cleaning",
    "wof:placetype":"venue"
},
  "geometry": {"coordinates":[-73.91231399999999,42.719438],"type":"Point"}
}