{
  "type": "Feature",
  "properties": {
    "iso:country":"US",
    "sg:address":"1892 Central Ave",
    "sg:city":"Albany",
    "sg:classifiers":[
        {
            "category":"Banks & Credit Unions",
            "subcategory":"Bank",
            "type":"Services"
        }
    ],
    "sg:phone":"+1 518 456 0041",
    "sg:postcode":"12205",
    "sg:province":"NY",
    "wof:name":"Trustco Bank",
    "wof:placetype":"venue"
},
  "geometry": {"coordinates":[-73.85252199999999,42.73486],"type":"Point"}
}