{
  "type": "Feature",
  "properties": {
    "iso:country":"US",
    "sg:address":"735 3rd St",
    "sg:city":"Albany",
    "sg:classifiers":[
        {
            "category":"Autos & Motor Vehicles",
            "subcategory":"Automobile Sales",
            "type":"Retail Goods"
        }
    ],
    "sg:phone":"+1 518 438 2982",
    "sg:postcode":"12206",
    "sg:province":"NY",
    "sg:tags":[
        "car",
        "used"
    ],
    "wof:name":"V C Auto Sales",
    "wof:placetype":"venue"
},
  "geometry": {"coordinates":[-73.780317,42.67591],"type":"Point"}
}