{
  "type": "Feature",
  "properties": {
    "iso:country":"US",
    "sg:address":"305 N Work St",
    "sg:city":"Falconer",
    "sg:classifiers":[
        {
            "category":"Real Estate",
            "subcategory":"Real Estate Operator",
            "type":"Services"
        }
    ],
    "sg:phone":"+1 716 665 6267",
    "sg:postcode":"14733",
    "sg:province":"NY",
    "sg:tags":[
        "apartment"
    ],
    "wof:name":"Falconer Apartments",
    "wof:placetype":"venue"
},
  "geometry": {"coordinates":[-79.20072399999999,42.120576],"type":"Point"}
}