{
  "type": "Feature",
  "properties": {
    "iso:country":"US",
    "sg:address":"315 West 57th Street Suite 308",
    "sg:city":"New York",
    "sg:classifiers":[
        {
            "category":"Personal",
            "subcategory":"Skin Care",
            "type":"Services"
        }
    ],
    "sg:phone":"+1 212 397 3851",
    "sg:postcode":"10019",
    "sg:province":"NY",
    "sg:website":"www.wrinklefreenyc.com",
    "wof:name":"Lauren B. Shanker R.N., N.P.",
    "wof:placetype":"venue"
},
  "geometry": {"coordinates":[-73.978673,40.763616],"type":"Point"}
}