{
  "type": "Feature",
  "properties": {
    "addr:full":"6011 7th Ave Brooklyn NY 11220",
    "addr:housenumber":"6011",
    "addr:postcode":"11220",
    "addr:street":"7Th Ave",
    "iso:country":"US",
    "sg:address":"6011 7th Ave",
    "sg:city":"Brooklyn",
    "sg:classifiers":[
        {
            "category":"Professional",
            "subcategory":"Computer Services",
            "type":"Services"
        }
    ],
    "sg:phone":"+1 718 439 1198",
    "sg:postcode":"11220",
    "sg:province":"NY",
    "sg:tags":[
        "internet"
    ],
    "wof:name":"Heavenly Dreams Internet Cafe",
    "wof:placetype":"venue"
},
  "geometry": {"coordinates":[-74.01225700000001,40.636256],"type":"Point"}
}