{
  "type": "Feature",
  "properties": {
    "addr:full":"524 Old Rte 11 Canton NY 13617",
    "addr:housenumber":"524",
    "addr:postcode":"13617",
    "addr:street":"Old Rte 11",
    "iso:country":"US",
    "sg:address":"524 Old Rte 11",
    "sg:city":"Canton",
    "sg:classifiers":[
        {
            "category":"Shopping",
            "subcategory":"Bicycles & Sporting Goods",
            "type":"Retail Goods"
        }
    ],
    "sg:phone":"+1   ",
    "sg:postcode":"13617",
    "sg:province":"NY",
    "wof:name":"L T Gun Shop",
    "wof:placetype":"venue"
},
  "geometry": {"coordinates":[-75.18944999999999,44.578098],"type":"Point"}
}