{
  "type": "Feature",
  "properties": {
    "iso:country":"US",
    "sg:address":"209 Steinway Ave",
    "sg:city":"Staten Island",
    "sg:classifiers":[
        {
            "category":"Shopping",
            "subcategory":"Crafts & Fabrics",
            "type":"Retail Goods"
        }
    ],
    "sg:phone":"+1   ",
    "sg:postcode":"10314",
    "sg:province":"NY",
    "sg:tags":[
        "sewing"
    ],
    "wof:name":"Sew A H",
    "wof:placetype":"venue"
},
  "geometry": {"coordinates":[-74.161858,40.592555],"type":"Point"}
}