{
  "type": "Feature",
  "properties": {
    "addr:full":"209 Steinway Ave Staten Island NY 10314",
    "addr:housenumber":"209",
    "addr:postcode":"10314",
    "addr:street":"Steinway Ave",
    "iso:country":"US",
    "sg:address":"209 Steinway Ave",
    "sg:city":"Staten Island",
    "sg:classifiers":[
        {
            "category":"Shopping",
            "subcategory":"Crafts & Fabrics",
            "type":"Retail Goods"
        }
    ],
    "sg:phone":"+1   ",
    "sg:postcode":"10314",
    "sg:province":"NY",
    "sg:tags":[
        "sewing"
    ],
    "wof:name":"Sew A H",
    "wof:placetype":"venue"
},
  "geometry": {"coordinates":[-74.161858,40.592555],"type":"Point"}
}