{
  "type": "Feature",
  "properties": {
    "iso:country":"US",
    "sg:address":"32 W 31st St",
    "sg:city":"New York",
    "sg:classifiers":[
        {
            "category":"Restaurant",
            "type":"Food & Drink"
        }
    ],
    "sg:menulink":"http://www.allmenus.com/ny/new-york/7118-yatra/menu/",
    "sg:phone":"+1 212 502 0552",
    "sg:postcode":"10001",
    "sg:province":"NY",
    "sg:tags":[
        "indian",
        "asian"
    ],
    "wof:name":"Yatra",
    "wof:placetype":"venue"
},
  "geometry": {"coordinates":[-73.98771000000001,40.746947],"type":"Point"}
}