{
  "type": "Feature",
  "properties": {
    "iso:country":"US",
    "sg:address":"1304 Bleecker St",
    "sg:city":"Utica",
    "sg:classifiers":[
        {
            "category":"Professional",
            "type":"Services"
        },
        {
            "category":"Restaurant",
            "type":"Food & Drink"
        }
    ],
    "sg:phone":"+1 315 732 1400",
    "sg:postcode":"13501",
    "sg:province":"NY",
    "sg:tags":[
        "caterer",
        "pizza"
    ],
    "wof:name":"Original Novo's Pizzeria & Del",
    "wof:placetype":"venue"
},
  "geometry": {"coordinates":[-75.20447799999999,43.094279],"type":"Point"}
}