{
  "type": "Feature",
  "properties": {
    "iso:country":"US",
    "sg:address":"65 Hackett Ave",
    "sg:city":"Albany",
    "sg:classifiers":[
        {
            "category":"Professional",
            "subcategory":"Art Services",
            "type":"Services"
        }
    ],
    "sg:phone":"+1 518 438 6127",
    "sg:postcode":"12205",
    "sg:province":"NY",
    "sg:tags":[
        "designer",
        "display",
        "producer"
    ],
    "wof:name":"Tollisen Design Inc",
    "wof:placetype":"venue"
},
  "geometry": {"coordinates":[-73.813227,42.70674],"type":"Point"}
}