{
  "type": "Feature",
  "properties": {
    "addr:full":"100 Knickerbocker Ave Ste E Bohemia NY 11716",
    "addr:housenumber":"100",
    "addr:postcode":"11716",
    "addr:street":"Knickerbocker Ave Ste E",
    "iso:country":"US",
    "sg:address":"100 Knickerbocker Ave Ste E",
    "sg:city":"Bohemia",
    "sg:classifiers":[
        {
            "category":"Shopping",
            "subcategory":"Optician",
            "type":"Retail Goods"
        }
    ],
    "sg:phone":"+1 631 589 3502",
    "sg:postcode":"11716",
    "sg:province":"NY",
    "sg:tags":[
        "eyewear"
    ],
    "wof:name":"Spectrum Thin Films",
    "wof:placetype":"venue"
},
  "geometry": {"coordinates":[-73.114304,40.770901],"type":"Point"}
}