{
  "type": "Feature",
  "properties": {
    "addr:full":"13521 Lefferts Blvd South Ozone Park NY 11420",
    "addr:housenumber":"13521",
    "addr:postcode":"11420",
    "addr:street":"Lefferts Blvd",
    "iso:country":"US",
    "sg:address":"13521 Lefferts Blvd",
    "sg:city":"South Ozone Park",
    "sg:classifiers":[
        {
            "category":"Building & Trades",
            "subcategory":"Construction",
            "type":"Services"
        }
    ],
    "sg:phone":"+1 718 845 0630",
    "sg:postcode":"11420",
    "sg:province":"NY",
    "sg:tags":[
        "contractor"
    ],
    "wof:name":"Evershine",
    "wof:placetype":"venue"
},
  "geometry": {"coordinates":[-73.820705,40.670482],"type":"Point"}
}