{
  "type": "Feature",
  "properties": {
    "addr:full":"255 W 75 St New York NY 10023",
    "addr:housenumber":"255",
    "addr:postcode":"10023",
    "addr:street":"W 75 St",
    "iso:country":"US",
    "sg:address":"255 W 75 St",
    "sg:city":"New York",
    "sg:classifiers":[
        {
            "category":"Health Services",
            "subcategory":"Doctor",
            "type":"Services"
        }
    ],
    "sg:phone":"+1 212 928 1220",
    "sg:postcode":"10023",
    "sg:province":"NY",
    "sg:tags":[
        "physician",
        "surgeon"
    ],
    "wof:name":"Ramon Guzman MD",
    "wof:placetype":"venue"
},
  "geometry": {"coordinates":[-73.98260399999999,40.781596],"type":"Point"}
}