{
  "type": "Feature",
  "properties": {
    "iso:country":"US",
    "sg:address":"6767 Rice Rd",
    "sg:city":"Bloomfield",
    "sg:classifiers":[
        {
            "category":"Farming",
            "subcategory":"Fish & Marine Products",
            "type":"Manufacturing & Wholesale Goods"
        }
    ],
    "sg:phone":"+1 585 657 7742",
    "sg:postcode":"14469",
    "sg:province":"NY",
    "sg:tags":[
        "management"
    ],
    "wof:name":"Geese Control of New York",
    "wof:placetype":"venue"
},
  "geometry": {"coordinates":[-77.400031,42.928205],"type":"Point"}
}