{
  "type": "Feature",
  "properties": {
    "addr:full":"152 Lockwood Ave Yonkers NY 10701",
    "addr:housenumber":"152",
    "addr:postcode":"10701",
    "addr:street":"Lockwood Ave",
    "iso:country":"US",
    "sg:address":"152 Lockwood Ave",
    "sg:city":"Yonkers",
    "sg:classifiers":[
        {
            "category":"Personal",
            "subcategory":"Beauty Salon",
            "type":"Services"
        }
    ],
    "sg:phone":"+1 914 966 1166",
    "sg:postcode":"10701",
    "sg:province":"NY",
    "wof:name":"Luigi's Hair Styles",
    "wof:placetype":"venue"
},
  "geometry": {"coordinates":[-73.867482,40.948305],"type":"Point"}
}