{
  "type": "Feature",
  "properties": {
    "iso:country":"US",
    "sg:address":"7 W Main St",
    "sg:city":"Gowanda",
    "sg:classifiers":[
        {
            "category":"Shopping",
            "subcategory":"Computers & Home Electronics",
            "type":"Retail Goods"
        }
    ],
    "sg:phone":"+1   ",
    "sg:postcode":"14070",
    "sg:province":"NY",
    "wof:name":"Radio Shack",
    "wof:placetype":"venue"
},
  "geometry": {"coordinates":[-78.935287,42.463126],"type":"Point"}
}