{
  "type": "Feature",
  "properties": {
    "iso:country":"US",
    "sg:address":"348 Elm St",
    "sg:city":"Penn Yan",
    "sg:classifiers":[
        {
            "category":"Real Estate",
            "subcategory":"Real Estate Operator",
            "type":"Services"
        }
    ],
    "sg:phone":"+1 315 536 9301",
    "sg:postcode":"14527",
    "sg:province":"NY",
    "sg:tags":[
        "building",
        "nonresidential"
    ],
    "wof:name":"Podsiadlo Thomas",
    "wof:placetype":"venue"
},
  "geometry": {"coordinates":[-77.061545,42.65991],"type":"Point"}
}