{
  "type": "Feature",
  "properties": {
    "addr:full":"12284 State Hwy 38 Berkshire NY 13736",
    "addr:housenumber":"12284",
    "addr:postcode":"13736",
    "addr:street":"State Hwy 38",
    "iso:country":"US",
    "sg:address":"12284 State Hwy 38",
    "sg:city":"Berkshire",
    "sg:classifiers":[
        {
            "category":"Insurance",
            "subcategory":"Insurance Agent",
            "type":"Services"
        }
    ],
    "sg:phone":"+1 607 657 8067",
    "sg:postcode":"13736",
    "sg:province":"NY",
    "wof:name":"Swaney Business Advisors",
    "wof:placetype":"venue"
},
  "geometry": {"coordinates":[-76.18336600000001,42.282229],"type":"Point"}
}