{
  "type": "Feature",
  "properties": {
    "addr:full":"157 E 18th Street New York NY 10003",
    "addr:housenumber":"157",
    "addr:postcode":"10003",
    "addr:street":"E 18Th Street",
    "iso:country":"US",
    "sg:address":"157 E 18th Street",
    "sg:city":"New York",
    "sg:classifiers":[
        {
            "category":"Coffee & Tea",
            "type":"Food & Drink"
        }
    ],
    "sg:phone":"+1 212 674 1702",
    "sg:postcode":"10003",
    "sg:province":"NY",
    "wof:name":"Espresso Coffee Roaster Corporation",
    "wof:placetype":"venue"
},
  "geometry": {"coordinates":[-73.98641600000001,40.736231],"type":"Point"}
}