{
  "type": "Feature",
  "properties": {
    "addr:full":"2723 Atlantic Ave Brooklyn NY 11207",
    "addr:housenumber":"2723",
    "addr:postcode":"11207",
    "addr:street":"Atlantic Ave",
    "iso:country":"US",
    "sg:address":"2723 Atlantic Ave",
    "sg:city":"Brooklyn",
    "sg:classifiers":[
        {
            "category":"Building & Trades",
            "subcategory":"Construction",
            "type":"Services"
        }
    ],
    "sg:phone":"+1 718 647 9314",
    "sg:postcode":"11207",
    "sg:province":"NY",
    "sg:tags":[
        "re",
        "nonresidential",
        "contractor"
    ],
    "wof:name":"Valencia Mirrors",
    "wof:placetype":"venue"
},
  "geometry": {"coordinates":[-73.893207,40.676195],"type":"Point"}
}