{
  "type": "Feature",
  "properties": {
    "iso:country":"US",
    "sg:address":"265 W 37th St Ph",
    "sg:city":"New York",
    "sg:classifiers":[
        {
            "category":"Organizations",
            "subcategory":"Non-profit Organization",
            "type":"Services"
        }
    ],
    "sg:phone":"+1 212 221 4377",
    "sg:postcode":"10018",
    "sg:province":"NY",
    "sg:tags":[
        "service/non-profit",
        "community"
    ],
    "wof:name":"Cheetah Express Svc",
    "wof:placetype":"venue"
},
  "geometry": {"coordinates":[-73.991203,40.7537],"type":"Point"}
}