{
  "type": "Feature",
  "properties": {
    "addr:full":"5872 Springbrook Rd Dewittville NY 14728",
    "addr:housenumber":"5872",
    "addr:postcode":"14728",
    "addr:street":"Springbrook Rd",
    "iso:country":"US",
    "sg:address":"5872 Springbrook Rd",
    "sg:city":"Dewittville",
    "sg:classifiers":[
        {
            "category":"Building & Trades",
            "subcategory":"Plumbing",
            "type":"Services"
        }
    ],
    "sg:phone":"+1 716 753 7901",
    "sg:postcode":"14728",
    "sg:province":"NY",
    "sg:tags":[
        "heating",
        "contractor"
    ],
    "wof:name":"Tempelec Mechanical",
    "wof:placetype":"venue"
},
  "geometry": {"coordinates":[-79.444508,42.239141],"type":"Point"}
}