{
  "type": "Feature",
  "properties": {
    "addr:full":"149 Birch Hill Rd Locust Valley NY 11560",
    "addr:housenumber":"149",
    "addr:postcode":"11560",
    "addr:street":"Birch Hill Rd",
    "iso:country":"US",
    "sg:address":"149 Birch Hill Rd",
    "sg:city":"Locust Valley",
    "sg:classifiers":[
        {
            "category":"Restaurant",
            "type":"Food & Drink"
        }
    ],
    "sg:phone":"+1 516 676 2207",
    "sg:postcode":"11560",
    "sg:province":"NY",
    "sg:tags":[
        "caterer"
    ],
    "wof:name":"Birch Hill Catering",
    "wof:placetype":"venue"
},
  "geometry": {"coordinates":[-73.597122,40.87783],"type":"Point"}
}