{
  "type": "Feature",
  "properties": {
    "addr:full":"3000 Hempstead Tpke Levittown NY 11756",
    "addr:housenumber":"3000",
    "addr:postcode":"11756",
    "addr:street":"Hempstead Tpke",
    "iso:country":"US",
    "sg:address":"3000 Hempstead Tpke",
    "sg:city":"Levittown",
    "sg:classifiers":[
        {
            "category":"Health Services",
            "subcategory":"Clinic",
            "type":"Services"
        }
    ],
    "sg:phone":"+1 516 731 3770",
    "sg:postcode":"11756",
    "sg:province":"NY",
    "sg:tags":[
        "home"
    ],
    "sg:website":"www.bestcare.com",
    "wof:name":"Bestcare Inc",
    "wof:placetype":"venue"
},
  "geometry": {"coordinates":[-73.523493,40.724866],"type":"Point"}
}