{
  "type": "Feature",
  "properties": {
    "iso:country":"US",
    "sg:address":"5 Toni Ann Cir",
    "sg:city":"Plainview",
    "sg:classifiers":[
        {
            "category":"Wholesale",
            "subcategory":"Durable Goods & Equipment",
            "type":"Manufacturing & Wholesale Goods"
        }
    ],
    "sg:phone":"+1 516 939 6144",
    "sg:postcode":"11803",
    "sg:province":"NY",
    "sg:tags":[
        "importer"
    ],
    "wof:name":"Stellan Sward LTD",
    "wof:placetype":"venue"
},
  "geometry": {"coordinates":[-73.471279,40.764546],"type":"Point"}
}