{
  "type": "Feature",
  "properties": {
    "addr:full":"200 E 72nd St New York NY 10021",
    "addr:housenumber":"200",
    "addr:postcode":"10021",
    "addr:street":"E 72Nd St",
    "iso:country":"US",
    "sg:address":"200 E 72nd St",
    "sg:city":"New York",
    "sg:classifiers":[
        {
            "category":"Personal",
            "type":"Services"
        }
    ],
    "sg:phone":"+1 212 492 9513",
    "sg:postcode":"10021",
    "sg:province":"NY",
    "sg:tags":[
        "towing"
    ],
    "wof:name":"7 24 Anyplace Emergency Towing",
    "wof:placetype":"venue"
},
  "geometry": {"coordinates":[-73.96060199999999,40.769699],"type":"Point"}
}