{
  "type": "Feature",
  "properties": {
    "addr:full":"770 Grote St Bronx NY 10460",
    "addr:housenumber":"770",
    "addr:postcode":"10460",
    "addr:street":"Grote St",
    "iso:country":"US",
    "sg:address":"770 Grote St",
    "sg:city":"Bronx",
    "sg:classifiers":[
        {
            "category":"Education",
            "subcategory":"School",
            "type":"Public Place"
        }
    ],
    "sg:phone":"+1 718 561 2052",
    "sg:postcode":"10460",
    "sg:province":"NY",
    "wof:name":"Bronx Elementary School # 34",
    "wof:placetype":"venue"
},
  "geometry": {"coordinates":[-73.883656,40.850485],"type":"Point"}
}