{
  "type": "Feature",
  "properties": {
    "addr:full":"3550 Genesee St Buffalo NY 14225",
    "addr:housenumber":"3550",
    "addr:postcode":"14225",
    "addr:street":"Genesee St",
    "iso:country":"US",
    "sg:address":"3550 Genesee St",
    "sg:city":"Buffalo",
    "sg:classifiers":[
        {
            "category":"Autos & Motor Vehicles",
            "subcategory":"Fuel & Gas Station",
            "type":"Retail Goods"
        }
    ],
    "sg:phone":"+1 716 632 1512",
    "sg:postcode":"14225",
    "sg:province":"NY",
    "sg:tags":[
        "oil"
    ],
    "wof:name":"Jack Manko's Mobil Svc",
    "wof:placetype":"venue"
},
  "geometry": {"coordinates":[-78.75294100000001,42.927377],"type":"Point"}
}