{
  "type": "Feature",
  "properties": {
    "addr:full":"940 E 174th St Bronx NY 10460",
    "addr:housenumber":"940",
    "addr:postcode":"10460",
    "addr:street":"E 174Th St",
    "iso:country":"US",
    "sg:address":"940 E 174th St",
    "sg:city":"Bronx",
    "sg:classifiers":[
        {
            "category":"Professional",
            "type":"Services"
        }
    ],
    "sg:phone":"+1 718 589 8541",
    "sg:postcode":"10460",
    "sg:province":"NY",
    "sg:tags":[
        "establishment"
    ],
    "wof:name":"2 Stop I II",
    "wof:placetype":"venue"
},
  "geometry": {"coordinates":[-73.885964,40.836769],"type":"Point"}
}