{
  "type": "Feature",
  "properties": {
    "addr:full":"14 Tucker Dr Poughkeepsie NY 12603",
    "addr:housenumber":"14",
    "addr:postcode":"12603",
    "addr:street":"Tucker Dr",
    "iso:country":"US",
    "sg:address":"14 Tucker Dr",
    "sg:city":"Poughkeepsie",
    "sg:classifiers":[
        {
            "category":"Freight",
            "type":"Transportation"
        }
    ],
    "sg:phone":"+1 845 454 1440",
    "sg:postcode":"12603",
    "sg:province":"NY",
    "sg:tags":[
        "distance",
        "storage",
        "long",
        "moving",
        "mover",
        "local"
    ],
    "wof:name":"Admiral Moving & Storage Inc",
    "wof:placetype":"venue"
},
  "geometry": {"coordinates":[-73.889324,41.7007],"type":"Point"}
}