{
  "type": "Feature",
  "properties": {
    "iso:country":"US",
    "sg:address":"3 Cayuga Ln",
    "sg:city":"Patchogue",
    "sg:classifiers":[
        {
            "category":"Building & Trades",
            "subcategory":"Construction",
            "type":"Services"
        }
    ],
    "sg:phone":"+1 631 758 6508",
    "sg:postcode":"11772",
    "sg:province":"NY",
    "sg:tags":[
        "house"
    ],
    "wof:name":"Eddies General Contracting",
    "wof:placetype":"venue"
},
  "geometry": {"coordinates":[-72.991589,40.78576],"type":"Point"}
}