{
  "type": "Feature",
  "properties": {
    "iso:country":"US",
    "sg:address":"11 Summit Ave",
    "sg:city":"Spring Valley",
    "sg:classifiers":[
        {
            "category":"Organizations",
            "subcategory":"Religious Organization",
            "type":"Services"
        }
    ],
    "sg:phone":"+1 845 425 2076",
    "sg:postcode":"10977",
    "sg:province":"NY",
    "sg:tags":[
        "clergy"
    ],
    "wof:name":"Elijah Peters",
    "wof:placetype":"venue"
},
  "geometry": {"coordinates":[-74.053549,41.108701],"type":"Point"}
}