{
  "type": "Feature",
  "properties": {
    "iso:country":"US",
    "sg:address":"355 E 72 St",
    "sg:city":"New York",
    "sg:classifiers":[
        {
            "category":"Professional",
            "subcategory":"Management & Consulting",
            "type":"Services"
        }
    ],
    "sg:phone":"+1 212 879 6808",
    "sg:postcode":"10021",
    "sg:province":"NY",
    "sg:tags":[
        "technology",
        "seminar"
    ],
    "wof:name":"Angelbeatcom LLC",
    "wof:placetype":"venue"
},
  "geometry": {"coordinates":[-73.957234,40.768579],"type":"Point"}
}