{
  "type": "Feature",
  "properties": {
    "addr:full":"12 Jay St Schenectady NY 12305",
    "addr:housenumber":"12",
    "addr:postcode":"12305",
    "addr:street":"Jay St",
    "iso:country":"US",
    "sg:address":"12 Jay St",
    "sg:city":"Schenectady",
    "sg:classifiers":[
        {
            "category":"Education",
            "subcategory":"School",
            "type":"Public Place"
        }
    ],
    "sg:phone":"+1 518 346 5662",
    "sg:postcode":"12305",
    "sg:province":"NY",
    "sg:website":"www.nysais.org",
    "wof:name":"N Y State Assoc-Indpndnt Schls",
    "wof:placetype":"venue"
},
  "geometry": {"coordinates":[-73.93883,42.816117],"type":"Point"}
}