{
  "type": "Feature",
  "properties": {
    "addr:full":"631 Lake Ave St James NY 11780",
    "addr:housenumber":"631",
    "addr:postcode":"11780",
    "addr:street":"Lake Ave",
    "iso:country":"US",
    "sg:address":"631 Lake Ave",
    "sg:city":"St James",
    "sg:classifiers":[
        {
            "category":"Professional",
            "subcategory":"Management & Consulting",
            "type":"Services"
        }
    ],
    "sg:phone":"+1 631 584 6400",
    "sg:postcode":"11780",
    "sg:province":"NY",
    "sg:tags":[
        "personnel",
        "consultant"
    ],
    "wof:name":"Active Premier Staffing",
    "wof:placetype":"venue"
},
  "geometry": {"coordinates":[-73.158096,40.885735],"type":"Point"}
}