{
  "type": "Feature",
  "properties": {
    "iso:country":"US",
    "sg:address":"2186 5th Ave Apt 1E",
    "sg:city":"New York",
    "sg:classifiers":[
        {
            "category":"Health Services",
            "subcategory":"Dentist",
            "type":"Services"
        }
    ],
    "sg:phone":"+1 212 281 8755",
    "sg:postcode":"10037",
    "sg:province":"NY",
    "wof:name":"Marsan Earl A Dr Dntst",
    "wof:placetype":"venue"
},
  "geometry": {"coordinates":[-73.93800400000001,40.812199],"type":"Point"}
}