{
  "type": "Feature",
  "properties": {
    "addr:full":"96 Broadway Greenlawn NY 11740",
    "addr:housenumber":"96",
    "addr:postcode":"11740",
    "addr:street":"Broadway",
    "iso:country":"US",
    "sg:address":"96 Broadway",
    "sg:city":"Greenlawn",
    "sg:classifiers":[
        {
            "category":"Retail",
            "subcategory":"Auto Repair",
            "type":"Services"
        }
    ],
    "sg:phone":"+1 631 757 6767",
    "sg:postcode":"11740",
    "sg:province":"NY",
    "sg:tags":[
        "automobile",
        "customizing"
    ],
    "wof:name":"Auto-Play LTD",
    "wof:placetype":"venue"
},
  "geometry": {"coordinates":[-73.36438800000001,40.866959],"type":"Point"}
}