{
  "type": "Feature",
  "properties": {
    "addr:full":"8 Indian Hill Rd New Rochelle NY 10804",
    "addr:housenumber":"8",
    "addr:postcode":"10804",
    "addr:street":"Indian Hill Rd",
    "iso:country":"US",
    "sg:address":"8 Indian Hill Rd",
    "sg:city":"New Rochelle",
    "sg:classifiers":[
        {
            "category":"Professional",
            "subcategory":"Management & Consulting",
            "type":"Services"
        }
    ],
    "sg:phone":"+1 914 633 9808",
    "sg:postcode":"10804",
    "sg:province":"NY",
    "sg:tags":[
        "promotion"
    ],
    "wof:name":"Linder Associates",
    "wof:placetype":"venue"
},
  "geometry": {"coordinates":[-73.77848,40.948553],"type":"Point"}
}