{
  "type": "Feature",
  "properties": {
    "addr:full":"4861 State Hwy 80 Tully NY 13159",
    "addr:housenumber":"4861",
    "addr:postcode":"13159",
    "addr:street":"State Hwy 80",
    "iso:country":"US",
    "sg:address":"4861 State Hwy 80",
    "sg:city":"Tully",
    "sg:classifiers":[
        {
            "category":"Building & Trades",
            "subcategory":"Construction",
            "type":"Services"
        }
    ],
    "sg:phone":"+1 315 696 6107",
    "sg:postcode":"13159",
    "sg:province":"NY",
    "sg:tags":[
        "home",
        "builder"
    ],
    "wof:name":"J Bishop Builders Inc",
    "wof:placetype":"venue"
},
  "geometry": {"coordinates":[-76.179958,42.816513],"type":"Point"}
}