{
  "type": "Feature",
  "properties": {
    "iso:country":"US",
    "sg:address":"244 E 71 St",
    "sg:city":"New York",
    "sg:classifiers":[
        {
            "category":"Building & Trades",
            "subcategory":"Construction",
            "type":"Services"
        }
    ],
    "sg:phone":"+1 212 288 0537",
    "sg:postcode":"10021",
    "sg:province":"NY",
    "sg:tags":[
        "nonresidential",
        "general",
        "contractor"
    ],
    "wof:name":"Batac Construction Co Inc",
    "wof:placetype":"venue"
},
  "geometry": {"coordinates":[-73.9594,40.768331],"type":"Point"}
}