{
  "type": "Feature",
  "properties": {
    "addr:full":"225 E 34 St New York NY 10016",
    "addr:housenumber":"225;34",
    "addr:postcode":"10016",
    "addr:street":"E;St",
    "iso:country":"US",
    "sg:address":"225 E 34 St",
    "sg:city":"New York",
    "sg:classifiers":[
        {
            "category":"Retail",
            "subcategory":"Auto Repair",
            "type":"Services"
        }
    ],
    "sg:phone":"+1 212 634 6044",
    "sg:postcode":"10016",
    "sg:province":"NY",
    "sg:tags":[
        "wrecker"
    ],
    "wof:name":"Downtown Number 1 Towing",
    "wof:placetype":"venue"
},
  "geometry": {"coordinates":[-73.975902,40.744877],"type":"Point"}
}