{
  "type": "Feature",
  "properties": {
    "addr:full":"107 Stutzman Rd Bowmansville NY 14026",
    "addr:housenumber":"107",
    "addr:postcode":"14026",
    "addr:street":"Stutzman Rd",
    "iso:country":"US",
    "sg:address":"107 Stutzman Rd",
    "sg:city":"Bowmansville",
    "sg:classifiers":[
        {
            "category":"Real Estate",
            "subcategory":"Real Estate Services",
            "type":"Services"
        }
    ],
    "sg:phone":"+1 716 684 4653",
    "sg:postcode":"14026",
    "sg:province":"NY",
    "sg:tags":[
        "management"
    ],
    "wof:name":"Bowmansville Square",
    "wof:placetype":"venue"
},
  "geometry": {"coordinates":[-78.684624,42.939831],"type":"Point"}
}