{
  "type": "Feature",
  "properties": {
    "iso:country":"US",
    "sg:address":"3536 Fluvanna Ave Exd",
    "sg:city":"Jamestown",
    "sg:classifiers":[
        {
            "category":"Government",
            "subcategory":"Fire Station",
            "type":"Public Place"
        }
    ],
    "sg:phone":"+1 716 483 8505",
    "sg:postcode":"14701",
    "sg:province":"NY",
    "sg:tags":[
        "department",
        "protection"
    ],
    "wof:name":"Fluvanna Fire Dept",
    "wof:placetype":"venue"
},
  "geometry": {"coordinates":[-79.292748,42.119906],"type":"Point"}
}