{
  "type": "Feature",
  "properties": {
    "addr:full":"70 Main St Phoenicia NY 12464",
    "addr:housenumber":"70",
    "addr:postcode":"12464",
    "addr:street":"Main St",
    "iso:country":"US",
    "sg:address":"70 Main St",
    "sg:city":"Phoenicia",
    "sg:classifiers":[
        {
            "category":"Bars & Pubs",
            "type":"Food & Drink"
        }
    ],
    "sg:phone":"+1 845 688 9922",
    "sg:postcode":"12464",
    "sg:province":"NY",
    "wof:name":"Sportsman Bar & Grill",
    "wof:placetype":"venue"
},
  "geometry": {"coordinates":[-74.313188,42.083334],"type":"Point"}
}