{
  "type": "Feature",
  "properties": {
    "addr:full":"2614 Amsdell Rd Hamburg NY 14075",
    "addr:housenumber":"2614",
    "addr:postcode":"14075",
    "addr:street":"Amsdell Rd",
    "iso:country":"US",
    "sg:address":"2614 Amsdell Rd",
    "sg:city":"Hamburg",
    "sg:classifiers":[
        {
            "category":"Building & Trades",
            "subcategory":"Landscaping Services",
            "type":"Services"
        }
    ],
    "sg:phone":"+1 716 627 4105",
    "sg:postcode":"14075",
    "sg:province":"NY",
    "wof:name":"M&D Lawn Care",
    "wof:placetype":"venue"
},
  "geometry": {"coordinates":[-78.90018000000001,42.742247],"type":"Point"}
}