{
  "type": "Feature",
  "properties": {
    "iso:country":"US",
    "sg:address":"48 Ronald Reagan Blvd",
    "sg:city":"Warwick",
    "sg:classifiers":[
        {
            "category":"Shopping",
            "type":"Retail Goods"
        }
    ],
    "sg:phone":"+1 845 987 9444",
    "sg:postcode":"10990",
    "sg:province":"NY",
    "sg:tags":[
        "pet",
        "food",
        "supply"
    ],
    "wof:name":"Hometowne Pet & Supply Inc",
    "wof:placetype":"venue"
},
  "geometry": {"coordinates":[-74.33255200000001,41.27127],"type":"Point"}
}