{
  "type": "Feature",
  "properties": {
    "addr:full":"3 Spencer St Hicksville NY 11801",
    "addr:housenumber":"3",
    "addr:postcode":"11801",
    "addr:street":"Spencer St",
    "iso:country":"US",
    "sg:address":"3 Spencer St",
    "sg:city":"Hicksville",
    "sg:classifiers":[
        {
            "category":"Building & Trades",
            "subcategory":"Landscaping Services",
            "type":"Services"
        }
    ],
    "sg:phone":"+1 516 935 7145",
    "sg:postcode":"11801",
    "sg:province":"NY",
    "wof:name":"Tony Fava Ldscpg & Mansonry",
    "wof:placetype":"venue"
},
  "geometry": {"coordinates":[-73.50797799999999,40.771784],"type":"Point"}
}