{
  "type": "Feature",
  "properties": {
    "addr:full":"3572 Co Rd 9 Hudson NY 12544",
    "addr:housenumber":"3572",
    "addr:postcode":"12544",
    "addr:street":"Co Rd 9",
    "iso:country":"US",
    "sg:address":"3572 Co Rd 9",
    "sg:city":"Hudson",
    "sg:classifiers":[
        {
            "category":"Freight",
            "type":"Transportation"
        }
    ],
    "sg:phone":"+1 518 851 9917",
    "sg:postcode":"12544",
    "sg:province":"NY",
    "sg:tags":[
        "installs",
        "mobile",
        "transport",
        "home"
    ],
    "wof:name":"Jaa Transport and Installers",
    "wof:placetype":"venue"
},
  "geometry": {"coordinates":[-73.66652000000001,42.263137],"type":"Point"}
}