{
  "type": "Feature",
  "properties": {
    "iso:country":"US",
    "sg:address":"555 8 Ave",
    "sg:city":"New York",
    "sg:classifiers":[
        {
            "category":"Professional",
            "subcategory":"Detective & Security Services",
            "type":"Services"
        }
    ],
    "sg:phone":"+1 212 629 9201",
    "sg:postcode":"10018",
    "sg:province":"NY",
    "sg:tags":[
        "mess",
        "consultant",
        "guard",
        "investigator"
    ],
    "wof:name":"Bowles Corporate Services",
    "wof:placetype":"venue"
},
  "geometry": {"coordinates":[-73.99252799999999,40.753474],"type":"Point"}
}