{
  "type": "Feature",
  "properties": {
    "addr:full":"6724 11th Ave Brooklyn NY 11219",
    "addr:housenumber":"6724",
    "addr:postcode":"11219",
    "addr:street":"11Th Ave",
    "iso:country":"US",
    "sg:address":"6724 11th Ave",
    "sg:city":"Brooklyn",
    "sg:classifiers":[
        {
            "category":"Professional",
            "subcategory":"Detective & Security Services",
            "type":"Services"
        }
    ],
    "sg:phone":"+1 718 659 1600",
    "sg:postcode":"11219",
    "sg:province":"NY",
    "sg:tags":[
        "investigator"
    ],
    "wof:name":"A J Sterling & Assoc LTD",
    "wof:placetype":"venue"
},
  "geometry": {"coordinates":[-74.007763,40.62702],"type":"Point"}
}