{
  "type": "Feature",
  "properties": {
    "iso:country":"US",
    "sg:address":"718 Main St",
    "sg:city":"Farmingdale",
    "sg:classifiers":[
        {
            "category":"Restaurant",
            "type":"Food & Drink"
        }
    ],
    "sg:phone":"+1 516 752 7045",
    "sg:postcode":"11735",
    "sg:province":"NY",
    "sg:tags":[
        "eating",
        "pizza"
    ],
    "wof:name":"Alitalia Pizza & Family Rstrnt",
    "wof:placetype":"venue"
},
  "geometry": {"coordinates":[-73.441768,40.722938],"type":"Point"}
}