{
  "type": "Feature",
  "properties": {
    "addr:full":"1075 Rte 112 Port Jefferson Station NY 11776",
    "addr:housenumber":"1075",
    "addr:postcode":"11776",
    "addr:street":"Rte 112",
    "iso:country":"US",
    "sg:address":"1075 Rte 112",
    "sg:city":"Port Jefferson Station",
    "sg:classifiers":[
        {
            "category":"Professional",
            "subcategory":"Accounting & Tax Preparation",
            "type":"Services"
        }
    ],
    "sg:phone":"+1   ",
    "sg:postcode":"11776",
    "sg:province":"NY",
    "wof:name":"James D Forrer CPA PC",
    "wof:placetype":"venue"
},
  "geometry": {"coordinates":[-73.044731,40.922262],"type":"Point"}
}