{
  "type": "Feature",
  "properties": {
    "iso:country":"US",
    "sg:address":"96 Clark St",
    "sg:city":"Auburn",
    "sg:classifiers":[
        {
            "category":"Restaurant",
            "type":"Food & Drink"
        }
    ],
    "sg:phone":"+1 315 253 4201",
    "sg:postcode":"13021",
    "sg:province":"NY",
    "wof:name":"New York Cafe",
    "wof:placetype":"venue"
},
  "geometry": {"coordinates":[-76.576345,42.930827],"type":"Point"}
}