{
  "type": "Feature",
  "properties": {
    "iso:country":"US",
    "sg:address":"103 Apple Ln",
    "sg:city":"Briarcliff Manor",
    "sg:classifiers":[
        {
            "category":"Real Estate",
            "subcategory":"Real Estate Agent",
            "type":"Services"
        }
    ],
    "sg:phone":"+1 914 773 9000",
    "sg:postcode":"10510",
    "sg:province":"NY",
    "wof:name":"ERA Realty Professionals",
    "wof:placetype":"venue"
},
  "geometry": {"coordinates":[-73.846276,41.160283],"type":"Point"}
}