{
  "type": "Feature",
  "properties": {
    "iso:country":"US",
    "sg:address":"168 Malcolm X Blvd",
    "sg:city":"New York",
    "sg:classifiers":[
        {
            "category":"Food & Beverages",
            "subcategory":"Meat & Fish",
            "type":"Retail Goods"
        }
    ],
    "sg:phone":"+1 212 534 1999",
    "sg:postcode":"10026",
    "sg:province":"NY",
    "sg:tags":[
        "shop"
    ],
    "wof:name":"G & M Meat Market Corporation",
    "wof:placetype":"venue"
},
  "geometry": {"coordinates":[-73.948502,40.803501],"type":"Point"}
}