{
  "type": "Feature",
  "properties": {
    "addr:full":"701 Rte 25A Rocky Point NY 11778",
    "addr:housenumber":"701",
    "addr:postcode":"11778",
    "addr:street":"Rte 25A",
    "iso:country":"US",
    "sg:address":"701 Rte 25A",
    "sg:city":"Rocky Point",
    "sg:classifiers":[
        {
            "category":"Social Services",
            "type":"Services"
        }
    ],
    "sg:phone":"+1 631 744 3800",
    "sg:postcode":"11778",
    "sg:province":"NY",
    "sg:tags":[
        "counselor",
        "marriage",
        "family"
    ],
    "wof:name":"Nick Aiello",
    "wof:placetype":"venue"
},
  "geometry": {"coordinates":[-72.91404300000001,40.947981],"type":"Point"}
}