{
  "type": "Feature",
  "properties": {
    "addr:full":"31 Eads St West Babylon NY 11704",
    "addr:housenumber":"31",
    "addr:postcode":"11704",
    "addr:street":"Eads St",
    "iso:country":"US",
    "sg:address":"31 Eads St",
    "sg:city":"West Babylon",
    "sg:classifiers":[
        {
            "category":"Manufacturing",
            "subcategory":"Tools & Machinery",
            "type":"Manufacturing & Wholesale Goods"
        }
    ],
    "sg:phone":"+1 631 420 3993",
    "sg:postcode":"11704",
    "sg:province":"NY",
    "sg:tags":[
        "equipment",
        "dental",
        "supply"
    ],
    "wof:name":"Exxel Dental & Medical Eqpt",
    "wof:placetype":"venue"
},
  "geometry": {"coordinates":[-73.38930499999999,40.732669],"type":"Point"}
}