{
  "type": "Feature",
  "properties": {
    "addr:full":"719 E Tremont Ave Bronx NY 10457",
    "addr:housenumber":"719",
    "addr:postcode":"10457",
    "addr:street":"E Tremont Ave",
    "iso:country":"US",
    "sg:address":"719 E Tremont Ave",
    "sg:city":"Bronx",
    "sg:classifiers":[
        {
            "category":"Autos & Motor Vehicles",
            "subcategory":"Auto Supplies",
            "type":"Retail Goods"
        },
        {
            "category":"Retail",
            "subcategory":"Repair Shop",
            "type":"Services"
        }
    ],
    "sg:phone":"+1 718 583 5228",
    "sg:postcode":"10457",
    "sg:province":"NY",
    "sg:tags":[
        "upholstery",
        "upholsterer",
        "automobile",
        "top",
        "covers",
        "seat"
    ],
    "sg:website":"http://www.victorsupholstery.com",
    "wof:name":"Victor's Plastic Covers & Upholstery",
    "wof:placetype":"venue"
},
  "geometry": {"coordinates":[-73.890478,40.845085],"type":"Point"}
}