{
  "type": "Feature",
  "properties": {
    "iso:country":"US",
    "sg:address":"99 Maplewood Rd",
    "sg:city":"Ithaca",
    "sg:classifiers":[
        {
            "category":"Professional",
            "type":"Services"
        }
    ],
    "sg:phone":"+1 607 273 0566",
    "sg:postcode":"14850",
    "sg:province":"NY",
    "wof:name":"Mapleleaf Design & Plan Svc",
    "wof:placetype":"venue"
},
  "geometry": {"coordinates":[-76.546057,42.507692],"type":"Point"}
}