{
  "type": "Feature",
  "properties": {
    "addr:full":"1845 Haring St Brooklyn NY 11229",
    "addr:housenumber":"1845",
    "addr:postcode":"11229",
    "addr:street":"Haring St",
    "iso:country":"US",
    "sg:address":"1845 Haring St",
    "sg:city":"Brooklyn",
    "sg:classifiers":[
        {
            "category":"Autos & Motor Vehicles",
            "subcategory":"Automobile Sales",
            "type":"Retail Goods"
        }
    ],
    "sg:phone":"+1 718 375 3150",
    "sg:postcode":"11229",
    "sg:province":"NY",
    "sg:tags":[
        "car",
        "dealer"
    ],
    "wof:name":"GMS Enterprises",
    "wof:placetype":"venue"
},
  "geometry": {"coordinates":[-73.941845,40.606235],"type":"Point"}
}