{
  "type": "Feature",
  "properties": {
    "addr:full":"260 Middle Country Rd Coram NY 11727",
    "addr:housenumber":"260",
    "addr:postcode":"11727",
    "addr:street":"Middle Country Rd",
    "iso:country":"US",
    "sg:address":"260 Middle Country Rd",
    "sg:city":"Coram",
    "sg:classifiers":[
        {
            "category":"Insurance",
            "subcategory":"Insurance Agent",
            "type":"Services"
        }
    ],
    "sg:phone":"+1 631 736 0236",
    "sg:postcode":"11727",
    "sg:province":"NY",
    "wof:name":"Knights Of Columbus Insurance",
    "wof:placetype":"venue"
},
  "geometry": {"coordinates":[-72.994883,40.871207],"type":"Point"}
}