{
  "type": "Feature",
  "properties": {
    "iso:country":"US",
    "sg:address":"10 Medical Plz",
    "sg:city":"Glen Cove",
    "sg:classifiers":[
        {
            "category":"Health Services",
            "subcategory":"Clinic",
            "type":"Services"
        }
    ],
    "sg:phone":"+1 516 676 2907",
    "sg:postcode":"11542",
    "sg:province":"NY",
    "wof:name":"North Shore LIJ Health Syst",
    "wof:placetype":"venue"
},
  "geometry": {"coordinates":[-73.62258799999999,40.874192],"type":"Point"}
}