{
  "type": "Feature",
  "properties": {
    "iso:country":"US",
    "sg:address":"32 Colonel Glenn Dr",
    "sg:city":"Carmel",
    "sg:classifiers":[
        {
            "category":"Building & Trades",
            "subcategory":"Landscaping Services",
            "type":"Services"
        }
    ],
    "sg:phone":"+1 845 531 2281",
    "sg:postcode":"10512",
    "sg:province":"NY",
    "sg:tags":[
        "landscape",
        "contractor"
    ],
    "wof:name":"Bambace Landscape",
    "wof:placetype":"venue"
},
  "geometry": {"coordinates":[-73.697006,41.404771],"type":"Point"}
}