{
  "type": "Feature",
  "properties": {
    "addr:full":"181 Croton Ave Ossining NY 10562",
    "addr:housenumber":"181",
    "addr:postcode":"10562",
    "addr:street":"Croton Ave",
    "iso:country":"US",
    "sg:address":"181 Croton Ave",
    "sg:city":"Ossining",
    "sg:classifiers":[
        {
            "category":"Restaurant",
            "type":"Food & Drink"
        }
    ],
    "sg:phone":"+1 914 923 0501",
    "sg:postcode":"10562",
    "sg:province":"NY",
    "sg:tags":[
        "cafe"
    ],
    "wof:name":"Sapori D Italia",
    "wof:placetype":"venue"
},
  "geometry": {"coordinates":[-73.848439,41.167031],"type":"Point"}
}