{
  "type": "Feature",
  "properties": {
    "iso:country":"US",
    "sg:address":"17 Davis St",
    "sg:city":"Locust Valley",
    "sg:classifiers":[
        {
            "category":"Local Transit",
            "type":"Transportation"
        }
    ],
    "sg:phone":"+1   ",
    "sg:postcode":"11560",
    "sg:province":"NY",
    "sg:tags":[
        "passenger"
    ],
    "wof:name":"Simons Limousine Service Inc",
    "wof:placetype":"venue"
},
  "geometry": {"coordinates":[-73.592952,40.878093],"type":"Point"}
}