{
  "type": "Feature",
  "properties": {
    "iso:country":"US",
    "sg:address":"395 Newbridge Rd",
    "sg:city":"Hicksville",
    "sg:classifiers":[
        {
            "category":"Retail",
            "subcategory":"Auto Repair",
            "type":"Services"
        }
    ],
    "sg:phone":"+1 516 931 0563",
    "sg:postcode":"11801",
    "sg:province":"NY",
    "wof:name":"Friends Auto Repair Inc",
    "wof:placetype":"venue"
},
  "geometry": {"coordinates":[-73.53299699999999,40.749298],"type":"Point"}
}