{
  "type": "Feature",
  "properties": {
    "addr:full":"15232 Rockaway Blvd Ste 203 Jamaica NY 11434",
    "addr:housenumber":"15232",
    "addr:postcode":"11434",
    "addr:street":"Rockaway Blvd Ste 203",
    "iso:country":"US",
    "sg:address":"15232 Rockaway Blvd Ste 203",
    "sg:city":"Jamaica",
    "sg:classifiers":[
        {
            "category":"Professional",
            "subcategory":"Employment Agencies",
            "type":"Services"
        },
        {
            "category":"Professional",
            "subcategory":"Business Services",
            "type":"Services"
        }
    ],
    "sg:phone":"+1 718 712 2583",
    "sg:postcode":"11434",
    "sg:province":"NY",
    "sg:tags":[
        "consultant",
        "broker",
        "custom"
    ],
    "wof:name":"Castaneda Haings Customs",
    "wof:placetype":"venue"
},
  "geometry": {"coordinates":[-73.77512400000001,40.660151],"type":"Point"}
}