{
  "type": "Feature",
  "properties": {
    "iso:country":"US",
    "sg:address":"2845 Richmond Ave",
    "sg:city":"Staten Island",
    "sg:classifiers":[
        {
            "category":"Deli",
            "type":"Food & Drink"
        },
        {
            "category":"Restaurant",
            "type":"Food & Drink"
        }
    ],
    "sg:phone":"+1 718 494 6000",
    "sg:postcode":"10314",
    "sg:province":"NY",
    "sg:tags":[
        "kosher"
    ],
    "wof:name":"Golden's Kosher Deli & Restaurant",
    "wof:placetype":"venue"
},
  "geometry": {"coordinates":[-74.169601,40.576599],"type":"Point"}
}