{
  "type": "Feature",
  "properties": {
    "iso:country":"US",
    "sg:address":"15 N Dutcher St",
    "sg:city":"Irvington",
    "sg:classifiers":[
        {
            "category":"Wholesale",
            "subcategory":"Jewelry",
            "type":"Manufacturing & Wholesale Goods"
        }
    ],
    "sg:phone":"+1 914 591 5975",
    "sg:postcode":"10533",
    "sg:province":"NY",
    "sg:tags":[
        "stone"
    ],
    "wof:name":"Robin Graham Jewelry",
    "wof:placetype":"venue"
},
  "geometry": {"coordinates":[-73.869857,41.040475],"type":"Point"}
}