{
  "type": "Feature",
  "properties": {
    "addr:full":"8 Banta St Phelps NY 14532",
    "addr:housenumber":"8",
    "addr:postcode":"14532",
    "addr:street":"Banta St",
    "iso:country":"US",
    "sg:address":"8 Banta St",
    "sg:city":"Phelps",
    "sg:classifiers":[
        {
            "category":"Education",
            "subcategory":"Library",
            "type":"Public Place"
        }
    ],
    "sg:phone":"+1 315 548 3120",
    "sg:postcode":"14532",
    "sg:province":"NY",
    "wof:name":"Phelps Community Library",
    "wof:placetype":"venue"
},
  "geometry": {"coordinates":[-77.06176000000001,42.958923],"type":"Point"}
}