{
  "type": "Feature",
  "properties": {
    "addr:full":"529 Worthen St Bronx NY 10474",
    "addr:housenumber":"529",
    "addr:postcode":"10474",
    "addr:street":"Worthen St",
    "iso:country":"US",
    "sg:address":"529 Worthen St",
    "sg:city":"Bronx",
    "sg:classifiers":[
        {
            "category":"Manufacturing",
            "subcategory":"Metals",
            "type":"Manufacturing & Wholesale Goods"
        }
    ],
    "sg:phone":"+1 718 991 7400",
    "sg:postcode":"10474",
    "sg:province":"NY",
    "sg:tags":[
        "duct",
        "fitting"
    ],
    "wof:name":"Modular Metals Inc",
    "wof:placetype":"venue"
},
  "geometry": {"coordinates":[-73.891447,40.810816],"type":"Point"}
}