{
  "type": "Feature",
  "properties": {
    "iso:country":"US",
    "sg:address":"28 Ave B",
    "sg:city":"Mechanicville",
    "sg:classifiers":[
        {
            "category":"Building & Trades",
            "subcategory":"Landscaping Services",
            "type":"Services"
        }
    ],
    "sg:phone":"+1 518 899 7765",
    "sg:postcode":"12118",
    "sg:province":"NY",
    "sg:tags":[
        "landscape"
    ],
    "wof:name":"Harpis Landscaping Services",
    "wof:placetype":"venue"
},
  "geometry": {"coordinates":[-73.79350100000001,42.956408],"type":"Point"}
}