{
  "type": "Feature",
  "properties": {
    "addr:full":"505 Bedford Rd Pleasantville NY 10570",
    "addr:housenumber":"505",
    "addr:postcode":"10570",
    "addr:street":"Bedford Rd",
    "iso:country":"US",
    "sg:address":"505 Bedford Rd",
    "sg:city":"Pleasantville",
    "sg:classifiers":[
        {
            "category":"Restaurant",
            "type":"Food & Drink"
        }
    ],
    "sg:phone":"+1 914 769 8990",
    "sg:postcode":"10570",
    "sg:province":"NY",
    "sg:tags":[
        "parlor",
        "ice",
        "cream"
    ],
    "wof:name":"Carvel Ice Cream & Bakery",
    "wof:placetype":"venue"
},
  "geometry": {"coordinates":[-73.794842,41.131609],"type":"Point"}
}