{
  "type": "Feature",
  "properties": {
    "iso:country":"US",
    "sg:address":"1245 Niagara Falls Blvd",
    "sg:city":"Buffalo",
    "sg:classifiers":[
        {
            "category":"Shopping",
            "subcategory":"Shoes",
            "type":"Retail Goods"
        }
    ],
    "sg:phone":"+1   ",
    "sg:postcode":"14226",
    "sg:province":"NY",
    "wof:name":"Easy Spirit Shoes Store",
    "wof:placetype":"venue"
},
  "geometry": {"coordinates":[-78.82252800000001,42.989229],"type":"Point"}
}