{
  "type": "Feature",
  "properties": {
    "iso:country":"US",
    "sg:address":"148 Water St",
    "sg:city":"Oswego",
    "sg:classifiers":[
        {
            "category":"Coffee & Tea",
            "type":"Food & Drink"
        },
        {
            "category":"Restaurant",
            "type":"Food & Drink"
        }
    ],
    "sg:phone":"+1 315 342 6916",
    "sg:postcode":"13126",
    "sg:province":"NY",
    "sg:tags":[
        "shop",
        "espresso"
    ],
    "wof:name":"Coffee Connection",
    "wof:placetype":"venue"
},
  "geometry": {"coordinates":[-76.509799,43.455523],"type":"Point"}
}