{
  "type": "Feature",
  "properties": {
    "addr:full":"20 Orchard Street New York NY 10002",
    "addr:housenumber":"20",
    "addr:postcode":"10002",
    "addr:street":"Orchard Street",
    "iso:country":"US",
    "sg:address":"20 Orchard Street",
    "sg:city":"New York",
    "sg:classifiers":[
        {
            "category":"Home & Garden",
            "subcategory":"Furniture",
            "type":"Retail Goods"
        }
    ],
    "sg:phone":"+1 212 677 8528",
    "sg:postcode":"10002",
    "sg:province":"NY",
    "sg:tags":[
        "store"
    ],
    "wof:name":"Katz Furniture",
    "wof:placetype":"venue"
},
  "geometry": {"coordinates":[-73.99142500000001,40.715274],"type":"Point"}
}