{
  "type": "Feature",
  "properties": {
    "iso:country":"US",
    "sg:address":"350 Broadway",
    "sg:city":"New York",
    "sg:classifiers":[
        {
            "category":"Professional",
            "type":"Services"
        }
    ],
    "sg:phone":"+1 212 274 0882",
    "sg:postcode":"10013",
    "sg:province":"NY",
    "sg:tags":[
        "establishment"
    ],
    "wof:name":"GITS Inc",
    "wof:placetype":"venue"
},
  "geometry": {"coordinates":[-74.00353200000001,40.717448],"type":"Point"}
}