{
  "type": "Feature",
  "properties": {
    "addr:full":"8315 Western Tpke Delanson NY 12053",
    "addr:housenumber":"8315",
    "addr:postcode":"12053",
    "addr:street":"Western Tpke",
    "iso:country":"US",
    "sg:address":"8315 Western Tpke",
    "sg:city":"Delanson",
    "sg:classifiers":[
        {
            "category":"Autos & Motor Vehicles",
            "subcategory":"Fuel & Gas Station",
            "type":"Retail Goods"
        }
    ],
    "sg:phone":"+1 518 895 8328",
    "sg:postcode":"12053",
    "sg:province":"NY",
    "sg:tags":[
        "oil"
    ],
    "wof:name":"Tiffany's Petroleum",
    "wof:placetype":"venue"
},
  "geometry": {"coordinates":[-74.190769,42.766586],"type":"Point"}
}