{
  "type": "Feature",
  "properties": {
    "addr:full":"48 Wall St 11th Fl New York NY 10005",
    "addr:housenumber":"48",
    "addr:postcode":"10005",
    "addr:street":"Wall St;Fl",
    "iso:country":"US",
    "sg:address":"48 Wall St 11th Fl",
    "sg:city":"New York",
    "sg:classifiers":[
        {
            "category":"Real Estate",
            "subcategory":"Real Estate Services",
            "type":"Services"
        },
        {
            "category":"Real Estate",
            "subcategory":"Real Estate Agent",
            "type":"Services"
        },
        {
            "category":"Real Estate",
            "subcategory":"Real Estate Operator",
            "type":"Services"
        }
    ],
    "sg:phone":"+1 212 918 4851",
    "sg:postcode":"10005",
    "sg:province":"NY",
    "sg:tags":[
        "apartment"
    ],
    "sg:website":"www.NYCasaGroup.com",
    "wof:name":"NY Casa Group",
    "wof:placetype":"venue"
},
  "geometry": {"coordinates":[-74.00924000000001,40.70627],"type":"Point"}
}