{
  "type": "Feature",
  "properties": {
    "iso:country":"US",
    "sg:address":"126 S Salina St",
    "sg:city":"Syracuse",
    "sg:classifiers":[
        {
            "category":"Professional",
            "subcategory":"Management & Consulting",
            "type":"Services"
        }
    ],
    "sg:phone":"+1 315 478 6608",
    "sg:postcode":"13202",
    "sg:province":"NY",
    "sg:tags":[
        "food"
    ],
    "sg:website":"www.corporatechefs.com",
    "wof:name":"Corporate Chef's Inc",
    "wof:placetype":"venue"
},
  "geometry": {"coordinates":[-76.152275,43.049843],"type":"Point"}
}