{
  "type": "Feature",
  "properties": {
    "addr:full":"144 Bowery Frnt New York NY 10013",
    "addr:housenumber":"144",
    "addr:postcode":"10013",
    "addr:street":"Bowery",
    "iso:country":"US",
    "sg:address":"144 Bowery Frnt",
    "sg:city":"New York",
    "sg:classifiers":[
        {
            "category":"Organizations",
            "subcategory":"Non-profit Organization",
            "type":"Services"
        }
    ],
    "sg:phone":"+1 212 219 8060",
    "sg:postcode":"10013",
    "sg:province":"NY",
    "sg:tags":[
        "service/non-profit",
        "community"
    ],
    "wof:name":"Sam Jo Association",
    "wof:placetype":"venue"
},
  "geometry": {"coordinates":[-73.994499,40.719299],"type":"Point"}
}