{
  "type": "Feature",
  "properties": {
    "addr:full":"32-15 Broadway Long Island City Queens NY 11106",
    "addr:housenumber":"32-15",
    "addr:postcode":"11106",
    "addr:street":"Broadway",
    "iso:country":"US",
    "sg:address":"32-15 Broadway Long Island City",
    "sg:city":"Queens",
    "sg:classifiers":[
        {
            "category":"Personal",
            "subcategory":"Beauty Salon",
            "type":"Services"
        },
        {
            "category":"Personal",
            "subcategory":"Nail Salon",
            "type":"Services"
        }
    ],
    "sg:phone":"+1 718 728 1819",
    "sg:postcode":"11106",
    "sg:province":"NY",
    "sg:tags":[
        "hair"
    ],
    "sg:website":"www.viyahair.com",
    "wof:name":"Viya",
    "wof:placetype":"venue"
},
  "geometry": {"coordinates":[-73.924038,40.761451],"type":"Point"}
}