{
  "type": "Feature",
  "properties": {
    "iso:country":"US",
    "sg:address":"53 Riverside Dr",
    "sg:city":"Saranac Lake",
    "sg:classifiers":[
        {
            "category":"Professional",
            "subcategory":"Accounting & Tax Preparation",
            "type":"Services"
        }
    ],
    "sg:phone":"+1   ",
    "sg:postcode":"12983",
    "sg:province":"NY",
    "wof:name":"Scott D Stiles",
    "wof:placetype":"venue"
},
  "geometry": {"coordinates":[-74.128028,44.321499],"type":"Point"}
}