{
  "type": "Feature",
  "properties": {
    "iso:country":"US",
    "sg:address":"226 Stone St",
    "sg:city":"Elmont",
    "sg:classifiers":[
        {
            "category":"Real Estate",
            "subcategory":"Real Estate Operator",
            "type":"Services"
        }
    ],
    "sg:phone":"+1 516 437 1546",
    "sg:postcode":"11003",
    "sg:province":"NY",
    "sg:tags":[
        "mall",
        "shopping",
        "center"
    ],
    "wof:name":"Gonzalez Mall",
    "wof:placetype":"venue"
},
  "geometry": {"coordinates":[-73.70524500000001,40.70201],"type":"Point"}
}