{
  "type": "Feature",
  "properties": {
    "addr:full":"297 Co Rd 6 Mahopac NY 10541",
    "addr:housenumber":"297",
    "addr:postcode":"10541",
    "addr:street":"Co Rd 6",
    "iso:country":"US",
    "sg:address":"297 Co Rd 6",
    "sg:city":"Mahopac",
    "sg:classifiers":[
        {
            "category":"Mining & Drilling",
            "type":"Manufacturing & Wholesale Goods"
        }
    ],
    "sg:phone":"+1 845 621 3076",
    "sg:postcode":"10541",
    "sg:province":"NY",
    "sg:tags":[
        "field",
        "oil"
    ],
    "wof:name":"Enivro Waste Oil Recovery",
    "wof:placetype":"venue"
},
  "geometry": {"coordinates":[-73.727283,41.385321],"type":"Point"}
}