{
  "type": "Feature",
  "properties": {
    "iso:country":"US",
    "sg:address":"347 W Hills Rd",
    "sg:city":"Huntington",
    "sg:classifiers":[
        {
            "category":"Farming",
            "subcategory":"Livestock Farm",
            "type":"Manufacturing & Wholesale Goods"
        }
    ],
    "sg:phone":"+1 631 424 4505",
    "sg:postcode":"11743",
    "sg:province":"NY",
    "sg:tags":[
        "equine"
    ],
    "wof:name":"Searer Farm LLC",
    "wof:placetype":"venue"
},
  "geometry": {"coordinates":[-73.421814,40.822551],"type":"Point"}
}