{
  "type": "Feature",
  "properties": {
    "iso:country":"US",
    "sg:address":"3560 Bivona St",
    "sg:city":"Bronx",
    "sg:classifiers":[
        {
            "category":"Professional",
            "subcategory":"Management & Consulting",
            "type":"Services"
        }
    ],
    "sg:phone":"+1 718 320 7902",
    "sg:postcode":"10475",
    "sg:province":"NY",
    "sg:tags":[
        "consultant",
        "business"
    ],
    "wof:name":"Friends Of The Renny Inc",
    "wof:placetype":"venue"
},
  "geometry": {"coordinates":[-73.83304200000001,40.882571],"type":"Point"}
}