{
  "type": "Feature",
  "properties": {
    "iso:country":"US",
    "sg:address":"127 Marine St",
    "sg:city":"Farmingdale",
    "sg:classifiers":[
        {
            "category":"Manufacturing",
            "subcategory":"Metals",
            "type":"Manufacturing & Wholesale Goods"
        }
    ],
    "sg:phone":"+1 516 293 9169",
    "sg:postcode":"11735",
    "sg:province":"NY",
    "sg:tags":[
        "fabricator",
        "metalwork",
        "sheet",
        "mfg"
    ],
    "wof:name":"F & M Precise Metals Inc",
    "wof:placetype":"venue"
},
  "geometry": {"coordinates":[-73.41486999999999,40.714783],"type":"Point"}
}