{
  "type": "Feature",
  "properties": {
    "iso:country":"US",
    "sg:address":"26 Electronic Pkwy",
    "sg:city":"Rome",
    "sg:classifiers":[
        {
            "category":"Manufacturing",
            "subcategory":"Printing",
            "type":"Manufacturing & Wholesale Goods"
        }
    ],
    "sg:phone":"+1   ",
    "sg:postcode":"13441",
    "sg:province":"NY",
    "wof:name":"Document Automation & Prod Svc",
    "wof:placetype":"venue"
},
  "geometry": {"coordinates":[-75.41116700000001,43.221815],"type":"Point"}
}