{
  "type": "Feature",
  "properties": {
    "iso:country":"US",
    "sg:address":"189 Brown Rd",
    "sg:city":"Hannibal",
    "sg:classifiers":[
        {
            "category":"Professional",
            "subcategory":"Engineering",
            "type":"Services"
        }
    ],
    "sg:phone":"+1 315 564 7100",
    "sg:postcode":"13074",
    "sg:province":"NY",
    "sg:tags":[
        "engineer"
    ],
    "sg:website":"www.svensonengineering.com",
    "wof:name":"Svenson Engineering",
    "wof:placetype":"venue"
},
  "geometry": {"coordinates":[-76.560309,43.314735],"type":"Point"}
}