{
  "type": "Feature",
  "properties": {
    "addr:full":"40 Drexel Dr Bay Shore NY 11706",
    "addr:housenumber":"40",
    "addr:postcode":"11706",
    "addr:street":"Drexel Dr",
    "iso:country":"US",
    "sg:address":"40 Drexel Dr",
    "sg:city":"Bay Shore",
    "sg:classifiers":[
        {
            "category":"Manufacturing",
            "subcategory":"Tools & Machinery",
            "type":"Manufacturing & Wholesale Goods"
        }
    ],
    "sg:phone":"+1 631 434 7586",
    "sg:postcode":"11706",
    "sg:province":"NY",
    "wof:name":"Lexan Industries Inc",
    "wof:placetype":"venue"
},
  "geometry": {"coordinates":[-73.264115,40.760513],"type":"Point"}
}