{
  "type": "Feature",
  "properties": {
    "addr:full":"37 S Ocean Ave Freeport NY 11520",
    "addr:housenumber":"37",
    "addr:postcode":"11520",
    "addr:street":"S Ocean Ave",
    "iso:country":"US",
    "sg:address":"37 S Ocean Ave",
    "sg:city":"Freeport",
    "sg:classifiers":[
        {
            "category":"Organizations",
            "subcategory":"Religious Organization",
            "type":"Services"
        }
    ],
    "sg:phone":"+1 516 378 0665",
    "sg:postcode":"11520",
    "sg:province":"NY",
    "sg:tags":[
        "church"
    ],
    "sg:website":"www.ohrfreeport.org",
    "wof:name":"Our Holy Redeemer Parish",
    "wof:placetype":"venue"
},
  "geometry": {"coordinates":[-73.58659,40.655993],"type":"Point"}
}