{
  "type": "Feature",
  "properties": {
    "iso:country":"US",
    "sg:address":"105 Roslyn Rd",
    "sg:city":"Roslyn Heights",
    "sg:classifiers":[
        {
            "category":"Shopping",
            "subcategory":"Discount & Variety Stores",
            "type":"Retail Goods"
        }
    ],
    "sg:phone":"+1 516 484 6690",
    "sg:postcode":"11577",
    "sg:province":"NY",
    "sg:tags":[
        "merchandise",
        "general"
    ],
    "wof:name":"Riegel Consumer Products",
    "wof:placetype":"venue"
},
  "geometry": {"coordinates":[-73.640798,40.790808],"type":"Point"}
}