{
  "type": "Feature",
  "properties": {
    "addr:full":"1 N Main St Massena NY 13662",
    "addr:housenumber":"1",
    "addr:postcode":"13662",
    "addr:street":"N Main St",
    "iso:country":"US",
    "sg:address":"1 N Main St",
    "sg:city":"Massena",
    "sg:classifiers":[
        {
            "category":"Organizations",
            "subcategory":"Professional Association",
            "type":"Services"
        }
    ],
    "sg:phone":"+1 315 769 7722",
    "sg:postcode":"13662",
    "sg:province":"NY",
    "wof:name":"Masonic Lodge",
    "wof:placetype":"venue"
},
  "geometry": {"coordinates":[-74.89296899999999,44.933153],"type":"Point"}
}