{
  "type": "Feature",
  "properties": {
    "iso:country":"US",
    "sg:address":"211 Main St",
    "sg:city":"New Rochelle",
    "sg:classifiers":[
        {
            "category":"Shopping",
            "type":"Retail Goods"
        }
    ],
    "sg:phone":"+1 914 235 2220",
    "sg:postcode":"10801",
    "sg:province":"NY",
    "sg:tags":[
        "merchandise",
        "cellular",
        "telephone"
    ],
    "wof:name":"Jet Communications Inc",
    "wof:placetype":"venue"
},
  "geometry": {"coordinates":[-73.771286,40.915421],"type":"Point"}
}