{
  "type": "Feature",
  "properties": {
    "iso:country":"US",
    "sg:address":"7519 State Hwy 22",
    "sg:city":"Copake",
    "sg:classifiers":[
        {
            "category":"Travel",
            "subcategory":"Hotels & Motels",
            "type":"Entertainment"
        }
    ],
    "sg:phone":"+1 518 329 3000",
    "sg:postcode":"12516",
    "sg:province":"NY",
    "wof:name":"Johanna's Motel & Restaurant",
    "wof:placetype":"venue"
},
  "geometry": {"coordinates":[-73.54132300000001,42.077495],"type":"Point"}
}