{
  "type": "Feature",
  "properties": {
    "iso:country":"US",
    "sg:address":"1165 W Main St",
    "sg:city":"Riverhead",
    "sg:classifiers":[
        {
            "category":"Home & Garden",
            "subcategory":"Garden Supply",
            "type":"Retail Goods"
        }
    ],
    "sg:phone":"+1 631 473 1787",
    "sg:postcode":"11901",
    "sg:province":"NY",
    "sg:tags":[
        "sprinkler"
    ],
    "wof:name":"D & T Irrigation Inc",
    "wof:placetype":"venue"
},
  "geometry": {"coordinates":[-72.686899,40.914588],"type":"Point"}
}