{
  "type": "Feature",
  "properties": {
    "addr:full":"25 McCouns Ln Glen Head NY 11545",
    "addr:housenumber":"25",
    "addr:postcode":"11545",
    "addr:street":"Mccouns Ln Glen",
    "iso:country":"US",
    "sg:address":"25 McCouns Ln",
    "sg:city":"Glen Head",
    "sg:classifiers":[
        {
            "category":"Health Services",
            "subcategory":"Medical Lab",
            "type":"Services"
        }
    ],
    "sg:phone":"+1   ",
    "sg:postcode":"11545",
    "sg:province":"NY",
    "sg:tags":[
        "laboratory",
        "dental"
    ],
    "wof:name":"Patrick Dental Studio",
    "wof:placetype":"venue"
},
  "geometry": {"coordinates":[-73.619514,40.834116],"type":"Point"}
}