{
  "type": "Feature",
  "properties": {
    "addr:full":"14585 Wilson Rd Collins NY 14034",
    "addr:housenumber":"14585",
    "addr:postcode":"14034",
    "addr:street":"Wilson Rd",
    "iso:country":"US",
    "sg:address":"14585 Wilson Rd",
    "sg:city":"Collins",
    "sg:classifiers":[
        {
            "category":"Farming",
            "subcategory":"Farm",
            "type":"Manufacturing & Wholesale Goods"
        }
    ],
    "sg:phone":"+1 716 532 9527",
    "sg:postcode":"14034",
    "sg:province":"NY",
    "sg:tags":[
        "crop",
        "general"
    ],
    "wof:name":"Kyle Mesch",
    "wof:placetype":"venue"
},
  "geometry": {"coordinates":[-78.814193,42.476826],"type":"Point"}
}