{
  "type": "Feature",
  "properties": {
    "iso:country":"US",
    "sg:address":"1729 Empire Blvd",
    "sg:city":"Webster",
    "sg:classifiers":[
        {
            "category":"Real Estate",
            "subcategory":"Real Estate Operator",
            "type":"Services"
        }
    ],
    "sg:phone":"+1 585 787 9692",
    "sg:postcode":"14580",
    "sg:province":"NY",
    "sg:tags":[
        "building",
        "nonresidential"
    ],
    "wof:name":"Lavander Properties",
    "wof:placetype":"venue"
},
  "geometry": {"coordinates":[-77.50595,43.186118],"type":"Point"}
}