{
  "type": "Feature",
  "properties": {
    "addr:full":"22 Brevoort Pl Brooklyn NY 11216",
    "addr:housenumber":"22",
    "addr:postcode":"11216",
    "addr:street":"Brevoort Pl",
    "iso:country":"US",
    "sg:address":"22 Brevoort Pl",
    "sg:city":"Brooklyn",
    "sg:classifiers":[
        {
            "category":"Wholesale",
            "subcategory":"Non-durable Goods",
            "type":"Manufacturing & Wholesale Goods"
        }
    ],
    "sg:phone":"+1 718 399 2036",
    "sg:postcode":"11216",
    "sg:province":"NY",
    "wof:name":"SA Khi Nuu Distributors LLC",
    "wof:placetype":"venue"
},
  "geometry": {"coordinates":[-73.955033,40.679903],"type":"Point"}
}