{
  "type": "Feature",
  "properties": {
    "iso:country":"US",
    "sg:address":"2 W Main St",
    "sg:city":"Elmsford",
    "sg:classifiers":[
        {
            "category":"Restaurant",
            "type":"Food & Drink"
        }
    ],
    "sg:phone":"+1 914 592 2335",
    "sg:postcode":"10523",
    "sg:province":"NY",
    "wof:name":"Mary's Mexican Restaurant",
    "wof:placetype":"venue"
},
  "geometry": {"coordinates":[-73.820494,41.055189],"type":"Point"}
}