{
  "type": "Feature",
  "properties": {
    "addr:full":"465 Willis Ave Williston Park NY 11596",
    "addr:housenumber":"465",
    "addr:postcode":"11596",
    "addr:street":"Willis Ave",
    "iso:country":"US",
    "sg:address":"465 Willis Ave",
    "sg:city":"Williston Park",
    "sg:classifiers":[
        {
            "category":"Health Services",
            "subcategory":"Doctor",
            "type":"Services"
        }
    ],
    "sg:phone":"+1   ",
    "sg:postcode":"11596",
    "sg:province":"NY",
    "sg:tags":[
        "osteopathic"
    ],
    "wof:name":"Lager Steven",
    "wof:placetype":"venue"
},
  "geometry": {"coordinates":[-73.645231,40.756429],"type":"Point"}
}