{
  "type": "Feature",
  "properties": {
    "addr:full":"635 Madison Ave Fl 16 New York NY 10022",
    "addr:housenumber":"635;16",
    "addr:postcode":"10022",
    "addr:street":"Madison Ave Fl",
    "iso:country":"US",
    "sg:address":"635 Madison Ave Fl 16",
    "sg:city":"New York",
    "sg:classifiers":[
        {
            "category":"Health Services",
            "subcategory":"Doctor",
            "type":"Services"
        }
    ],
    "sg:phone":"+1 212 794 2500",
    "sg:postcode":"10022",
    "sg:province":"NY",
    "wof:name":"Loeffler Lisa Md",
    "wof:placetype":"venue"
},
  "geometry": {"coordinates":[-73.97108900000001,40.763752],"type":"Point"}
}