{
  "type": "Feature",
  "properties": {
    "addr:full":"70 E 55 St New York NY 10022",
    "addr:housenumber":"70;55",
    "addr:postcode":"10022",
    "addr:street":"E;St",
    "iso:country":"US",
    "sg:address":"70 E 55 St",
    "sg:city":"New York",
    "sg:classifiers":[
        {
            "category":"Professional",
            "type":"Services"
        },
        {
            "category":"Real Estate",
            "subcategory":"Real Estate Agent",
            "type":"Services"
        }
    ],
    "sg:phone":"+1 212 759 7705",
    "sg:postcode":"10022",
    "sg:province":"NY",
    "sg:tags":[
        "lease",
        "establishment",
        "space"
    ],
    "wof:name":"Heron Tower",
    "wof:placetype":"venue"
},
  "geometry": {"coordinates":[-73.97245100000001,40.760644],"type":"Point"}
}