{
  "type": "Feature",
  "properties": {
    "iso:country":"US",
    "sg:address":"159 Trinity Dr",
    "sg:city":"Holley",
    "sg:classifiers":[
        {
            "category":"Food & Beverages",
            "subcategory":"Groceries & Convenience Stores",
            "type":"Retail Goods"
        }
    ],
    "sg:phone":"+1   ",
    "sg:postcode":"14470",
    "sg:province":"NY",
    "wof:name":"Food Express",
    "wof:placetype":"venue"
},
  "geometry": {"coordinates":[-78.01019599999999,43.193484],"type":"Point"}
}