{
  "type": "Feature",
  "properties": {
    "addr:full":"161 Brookside Farms Rd Newburgh NY 12550",
    "addr:housenumber":"161",
    "addr:postcode":"12550",
    "addr:street":"Brookside Farms Rd",
    "iso:country":"US",
    "sg:address":"161 Brookside Farms Rd",
    "sg:city":"Newburgh",
    "sg:classifiers":[
        {
            "category":"Government",
            "subcategory":"Office",
            "type":"Public Place"
        }
    ],
    "sg:phone":"+1 845 569 0240",
    "sg:postcode":"12550",
    "sg:province":"NY",
    "sg:tags":[
        "state",
        "program",
        "transportation"
    ],
    "wof:name":"N Y S Thruway Authority",
    "wof:placetype":"venue"
},
  "geometry": {"coordinates":[-74.055907,41.512406],"type":"Point"}
}