{
  "type": "Feature",
  "properties": {
    "addr:full":"6111 Thunderhead Ln Jamesville NY 13078",
    "addr:housenumber":"6111",
    "addr:postcode":"13078",
    "addr:street":"Thunderhead Ln",
    "iso:country":"US",
    "sg:address":"6111 Thunderhead Ln",
    "sg:city":"Jamesville",
    "sg:classifiers":[
        {
            "category":"Shopping",
            "subcategory":"Catalog Store",
            "type":"Retail Goods"
        }
    ],
    "sg:phone":"+1   ",
    "sg:postcode":"13078",
    "sg:province":"NY",
    "sg:tags":[
        "mail",
        "house"
    ],
    "wof:name":"Simply Maui",
    "wof:placetype":"venue"
},
  "geometry": {"coordinates":[-76.10077200000001,42.991097],"type":"Point"}
}