{
  "type": "Feature",
  "properties": {
    "iso:country":"US",
    "sg:address":"666 State Hwy 211",
    "sg:city":"Middletown",
    "sg:classifiers":[
        {
            "category":"Retail",
            "subcategory":"Self-service Laundry",
            "type":"Services"
        }
    ],
    "sg:phone":"+1 845 692 6266",
    "sg:postcode":"10941",
    "sg:province":"NY",
    "wof:name":"Laundry Room Inc",
    "wof:placetype":"venue"
},
  "geometry": {"coordinates":[-74.36197,41.465295],"type":"Point"}
}