{
  "type": "Feature",
  "properties": {
    "iso:country":"US",
    "sg:address":"8213 Ridge Rd W",
    "sg:city":"Brockport",
    "sg:classifiers":[
        {
            "category":"Autos & Motor Vehicles",
            "subcategory":"Auto Supplies",
            "type":"Retail Goods"
        }
    ],
    "sg:phone":"+1   ",
    "sg:postcode":"14420",
    "sg:province":"NY",
    "sg:tags":[
        "car",
        "truck",
        "accessory"
    ],
    "wof:name":"Vans Truck Toys",
    "wof:placetype":"venue"
},
  "geometry": {"coordinates":[-77.921955,43.231438],"type":"Point"}
}