{
  "type": "Feature",
  "properties": {
    "addr:full":"8836 Bay Pkwy Brooklyn NY 11214",
    "addr:housenumber":"8836",
    "addr:postcode":"11214",
    "addr:street":"Bay Pkwy",
    "iso:country":"US",
    "sg:address":"8836 Bay Pkwy",
    "sg:city":"Brooklyn",
    "sg:classifiers":[
        {
            "category":"Health Services",
            "subcategory":"Chiropractor",
            "type":"Services"
        }
    ],
    "sg:phone":"+1   ",
    "sg:postcode":"11214",
    "sg:province":"NY",
    "wof:name":"Alfred A Pecora DC",
    "wof:placetype":"venue"
},
  "geometry": {"coordinates":[-73.998209,40.597977],"type":"Point"}
}