{
  "type": "Feature",
  "properties": {
    "addr:full":"390 Washington St Newburgh NY 12550",
    "addr:housenumber":"390",
    "addr:postcode":"12550",
    "addr:street":"Washington St",
    "iso:country":"US",
    "sg:address":"390 Washington St",
    "sg:city":"Newburgh",
    "sg:classifiers":[
        {
            "category":"Building & Trades",
            "subcategory":"Electrical",
            "type":"Services"
        }
    ],
    "sg:phone":"+1 845 565 1367",
    "sg:postcode":"12550",
    "sg:province":"NY",
    "sg:tags":[
        "electric",
        "contractor"
    ],
    "wof:name":"R A Electric",
    "wof:placetype":"venue"
},
  "geometry": {"coordinates":[-74.024548,41.49934],"type":"Point"}
}