{
  "type": "Feature",
  "properties": {
    "addr:full":"779 Genesee St Buffalo NY 14211",
    "addr:housenumber":"779",
    "addr:postcode":"14211",
    "addr:street":"Genesee St",
    "iso:country":"US",
    "sg:address":"779 Genesee St",
    "sg:city":"Buffalo",
    "sg:classifiers":[
        {
            "category":"Retail",
            "subcategory":"Auto Repair",
            "type":"Services"
        }
    ],
    "sg:phone":"+1 716 892 1768",
    "sg:postcode":"14211",
    "sg:province":"NY",
    "sg:tags":[
        "muffler",
        "exhaust",
        "system"
    ],
    "wof:name":"Muffler & Brake First Klass",
    "wof:placetype":"venue"
},
  "geometry": {"coordinates":[-78.847151,42.89894],"type":"Point"}
}