{
  "type": "Feature",
  "properties": {
    "addr:full":"724 Manhattan Ave Brooklyn NY 11222",
    "addr:housenumber":"724",
    "addr:postcode":"11222",
    "addr:street":"Manhattan Ave",
    "iso:country":"US",
    "sg:address":"724 Manhattan Ave",
    "sg:city":"Brooklyn",
    "sg:classifiers":[
        {
            "category":"Shopping",
            "type":"Retail Goods"
        }
    ],
    "sg:phone":"+1 718 609 9200",
    "sg:postcode":"11222",
    "sg:province":"NY",
    "sg:tags":[
        "telephone",
        "cellular"
    ],
    "wof:name":"Compucell 15 Inc",
    "wof:placetype":"venue"
},
  "geometry": {"coordinates":[-73.95237,40.726558],"type":"Point"}
}