{
  "type": "Feature",
  "properties": {
    "addr:full":"123 Columbus Ave New York NY 10023",
    "addr:housenumber":"123",
    "addr:postcode":"10023",
    "addr:street":"Columbus Ave",
    "iso:country":"US",
    "sg:address":"123 Columbus Ave",
    "sg:city":"New York",
    "sg:classifiers":[
        {
            "category":"Retail",
            "subcategory":"Repair Shop",
            "type":"Services"
        }
    ],
    "sg:phone":"+1 646 237 9671",
    "sg:postcode":"10023",
    "sg:province":"NY",
    "sg:tags":[
        "lock",
        "locksmith"
    ],
    "wof:name":"Accurate 24 Hours Emergency",
    "wof:placetype":"venue"
},
  "geometry": {"coordinates":[-73.981728,40.773207],"type":"Point"}
}