{
  "type": "Feature",
  "properties": {
    "addr:full":"10 S Water St Garrison NY 10566",
    "addr:housenumber":"10",
    "addr:postcode":"10566",
    "addr:street":"S Water St",
    "iso:country":"US",
    "sg:address":"10 S Water St",
    "sg:city":"Garrison",
    "sg:classifiers":[
        {
            "category":"Home & Garden",
            "subcategory":"Home Furnishings",
            "type":"Retail Goods"
        }
    ],
    "sg:phone":"+1 845 737 3073",
    "sg:postcode":"10566",
    "sg:province":"NY",
    "sg:tags":[
        "fireplace"
    ],
    "wof:name":"Coleman Distributors Inc",
    "wof:placetype":"venue"
},
  "geometry": {"coordinates":[-73.929005,41.287836],"type":"Point"}
}