{
  "type": "Feature",
  "properties": {
    "iso:country":"US",
    "sg:address":"1030 Long Pond Rd",
    "sg:city":"Rochester",
    "sg:classifiers":[
        {
            "category":"Wholesale",
            "subcategory":"Non-durable Goods",
            "type":"Manufacturing & Wholesale Goods"
        }
    ],
    "sg:phone":"+1 585 225 4357",
    "sg:postcode":"14626",
    "sg:province":"NY",
    "sg:tags":[
        "merchandise-wholesale"
    ],
    "wof:name":"Long Pond Trading Company",
    "wof:placetype":"venue"
},
  "geometry": {"coordinates":[-77.696816,43.228886],"type":"Point"}
}