{
  "type": "Feature",
  "properties": {
    "addr:full":"144 Freeman St Brooklyn NY 11222",
    "addr:housenumber":"144",
    "addr:postcode":"11222",
    "addr:street":"Freeman St",
    "iso:country":"US",
    "sg:address":"144 Freeman St",
    "sg:city":"Brooklyn",
    "sg:classifiers":[
        {
            "category":"Manufacturing",
            "subcategory":"Food",
            "type":"Manufacturing & Wholesale Goods"
        }
    ],
    "sg:phone":"+1   ",
    "sg:postcode":"11222",
    "sg:province":"NY",
    "sg:tags":[
        "mfg"
    ],
    "wof:name":"Peanut Butter & Co",
    "wof:placetype":"venue"
},
  "geometry": {"coordinates":[-73.956694,40.734157],"type":"Point"}
}