{
  "type": "Feature",
  "properties": {
    "addr:full":"50 Main St Lockport NY 14094",
    "addr:housenumber":"50",
    "addr:postcode":"14094",
    "addr:street":"Main St",
    "iso:country":"US",
    "sg:address":"50 Main St",
    "sg:city":"Lockport",
    "sg:classifiers":[
        {
            "category":"Banks & Credit Unions",
            "subcategory":"Bank",
            "type":"Services"
        }
    ],
    "sg:phone":"+1 716 625 9222",
    "sg:postcode":"14094",
    "sg:province":"NY",
    "sg:tags":[
        "state",
        "commercial"
    ],
    "wof:name":"Hsbc Bank USA National Assn",
    "wof:placetype":"venue"
},
  "geometry": {"coordinates":[-78.69347399999999,43.16964],"type":"Point"}
}