{
  "type": "Feature",
  "properties": {
    "addr:full":"7401 Roosevelt Avenue Jackson Heights NY 11372",
    "addr:housenumber":"7401",
    "addr:postcode":"11372",
    "addr:street":"Roosevelt Avenue",
    "iso:country":"US",
    "sg:address":"7401 Roosevelt Avenue",
    "sg:city":"Jackson Heights",
    "sg:classifiers":[
        {
            "category":"Personal",
            "subcategory":"Hair Removal",
            "type":"Services"
        }
    ],
    "sg:phone":"+1 718 779 2800",
    "sg:postcode":"11372",
    "sg:province":"NY",
    "wof:name":"Gulzar Beauty Salon",
    "wof:placetype":"venue"
},
  "geometry": {"coordinates":[-73.891193,40.746981],"type":"Point"}
}