{
  "type": "Feature",
  "properties": {
    "addr:full":"64 Westbury Ct Clifton Park NY 12065",
    "addr:housenumber":"64",
    "addr:postcode":"12065",
    "addr:street":"Westbury Ct",
    "iso:country":"US",
    "sg:address":"64 Westbury Ct",
    "sg:city":"Clifton Park",
    "sg:classifiers":[
        {
            "category":"Shopping",
            "subcategory":"Jewelry",
            "type":"Retail Goods"
        }
    ],
    "sg:phone":"+1 518 373 8122",
    "sg:postcode":"12065",
    "sg:province":"NY",
    "sg:tags":[
        "jeweler"
    ],
    "wof:name":"C A Tomchik",
    "wof:placetype":"venue"
},
  "geometry": {"coordinates":[-73.79291600000001,42.827339],"type":"Point"}
}