{
  "type": "Feature",
  "properties": {
    "iso:country":"US",
    "sg:address":"1995 Broadway",
    "sg:city":"New York",
    "sg:classifiers":[
        {
            "category":"Professional",
            "type":"Services"
        }
    ],
    "sg:phone":"+1 212 724 3544",
    "sg:postcode":"10023",
    "sg:province":"NY",
    "sg:tags":[
        "establishment"
    ],
    "wof:name":"BBC",
    "wof:placetype":"venue"
},
  "geometry": {"coordinates":[-73.982263,40.774861],"type":"Point"}
}