{
  "type": "Feature",
  "properties": {
    "addr:full":"29 Bleecker St New York NY 10012",
    "addr:housenumber":"29",
    "addr:postcode":"10012",
    "addr:street":"Bleecker St",
    "iso:country":"US",
    "sg:address":"29 Bleecker St",
    "sg:city":"New York",
    "sg:classifiers":[
        {
            "category":"Professional",
            "subcategory":"Art Services",
            "type":"Services"
        }
    ],
    "sg:phone":"+1   ",
    "sg:postcode":"10012",
    "sg:province":"NY",
    "sg:tags":[
        "photo",
        "photography",
        "commercial",
        "studio",
        "portrait"
    ],
    "wof:name":"Peter Nicholas Photography",
    "wof:placetype":"venue"
},
  "geometry": {"coordinates":[-73.99430599999999,40.725866],"type":"Point"}
}