{
  "type": "Feature",
  "properties": {
    "addr:full":"406 W 13 St New York NY 10014",
    "addr:housenumber":"406",
    "addr:postcode":"10014",
    "addr:street":"W 13 St",
    "iso:country":"US",
    "sg:address":"406 W 13 St",
    "sg:city":"New York",
    "sg:classifiers":[
        {
            "category":"Personal",
            "type":"Services"
        }
    ],
    "sg:phone":"+1 212 691 6100",
    "sg:postcode":"10014",
    "sg:province":"NY",
    "sg:tags":[
        "full",
        "event",
        "planner"
    ],
    "sg:website":"www.eventgroupinc.com",
    "wof:name":"Event Group Inc",
    "wof:placetype":"venue"
},
  "geometry": {"coordinates":[-74.00731500000001,40.740763],"type":"Point"}
}