{
  "type": "Feature",
  "properties": {
    "iso:country":"US",
    "sg:address":"2002 Broadway",
    "sg:city":"New York",
    "sg:classifiers":[
        {
            "category":"Building & Trades",
            "subcategory":"Locksmith",
            "type":"Services"
        }
    ],
    "sg:phone":"+1 212 492 9539",
    "sg:postcode":"10023",
    "sg:province":"NY",
    "sg:tags":[
        "key"
    ],
    "wof:name":"7 24 Anyplace Emergency Locksmith",
    "wof:placetype":"venue"
},
  "geometry": {"coordinates":[-73.981903,40.7756],"type":"Point"}
}