{
  "type": "Feature",
  "properties": {
    "addr:full":"2025 Richmond Ave Staten Island NY 10314",
    "addr:housenumber":"2025",
    "addr:postcode":"10314",
    "addr:street":"Richmond Ave",
    "iso:country":"US",
    "sg:address":"2025 Richmond Ave",
    "sg:city":"Staten Island",
    "sg:classifiers":[
        {
            "category":"Bars & Pubs",
            "subcategory":"Nightclub",
            "type":"Food & Drink"
        }
    ],
    "sg:phone":"+1 718 370 8080",
    "sg:postcode":"10314",
    "sg:province":"NY",
    "sg:tags":[
        "nightlife"
    ],
    "sg:website":"www.facebook.com/#!/group.php?gi...",
    "wof:name":"1001 Nights Cafe & Lounge",
    "wof:placetype":"venue"
},
  "geometry": {"coordinates":[-74.161907,40.598235],"type":"Point"}
}