{
  "type": "Feature",
  "properties": {
    "iso:country":"US",
    "sg:address":"585 N Barry Ave",
    "sg:city":"Mamaroneck",
    "sg:classifiers":[
        {
            "category":"Banks & Credit Unions",
            "subcategory":"Bank",
            "type":"Services"
        }
    ],
    "sg:phone":"+1 914 332 4550",
    "sg:postcode":"10543",
    "sg:province":"NY",
    "sg:tags":[
        "loan",
        "real estate"
    ],
    "wof:name":"Aran Capital Corp",
    "wof:placetype":"venue"
},
  "geometry": {"coordinates":[-73.731027,40.958762],"type":"Point"}
}