{
  "type": "Feature",
  "properties": {
    "iso:country":"US",
    "sg:address":"180 Adams Ave",
    "sg:city":"Hauppauge",
    "sg:classifiers":[
        {
            "category":"Wholesale",
            "subcategory":"Auto Parts",
            "type":"Manufacturing & Wholesale Goods"
        }
    ],
    "sg:phone":"+1   ",
    "sg:postcode":"11788",
    "sg:province":"NY",
    "sg:tags":[
        "mfg",
        "motor",
        "vehicle"
    ],
    "wof:name":"Q-Mobil Automotive",
    "wof:placetype":"venue"
},
  "geometry": {"coordinates":[-73.256097,40.810384],"type":"Point"}
}