{
  "type": "Feature",
  "properties": {
    "addr:full":"351 Ridgewood Ave Brooklyn NY 11208",
    "addr:housenumber":"351",
    "addr:postcode":"11208",
    "addr:street":"Ridgewood Ave",
    "iso:country":"US",
    "sg:address":"351 Ridgewood Ave",
    "sg:city":"Brooklyn",
    "sg:classifiers":[
        {
            "category":"Personal",
            "subcategory":"Beauty Salon",
            "type":"Services"
        }
    ],
    "sg:phone":"+1 800 323 0764",
    "sg:postcode":"11208",
    "sg:province":"NY",
    "sg:tags":[
        "hair"
    ],
    "wof:name":"Maria's Beauty Salon",
    "wof:placetype":"venue"
},
  "geometry": {"coordinates":[-73.87586899999999,40.684773],"type":"Point"}
}