{
  "type": "Feature",
  "properties": {
    "addr:full":"1040 Park Ave New York NY 10028",
    "addr:housenumber":"1040",
    "addr:postcode":"10028",
    "addr:street":"Park Ave",
    "iso:country":"US",
    "sg:address":"1040 Park Ave",
    "sg:city":"New York",
    "sg:classifiers":[
        {
            "category":"Professional",
            "subcategory":"Management & Consulting",
            "type":"Services"
        }
    ],
    "sg:phone":"+1 212 289 5448",
    "sg:postcode":"10028",
    "sg:province":"NY",
    "wof:name":"Midland Management Corp",
    "wof:placetype":"venue"
},
  "geometry": {"coordinates":[-73.95670699999999,40.780856],"type":"Point"}
}