{
  "type": "Feature",
  "properties": {
    "addr:full":"136 Main St East Rockaway NY 11518",
    "addr:housenumber":"136",
    "addr:postcode":"11518",
    "addr:street":"Main St East",
    "iso:country":"US",
    "sg:address":"136 Main St",
    "sg:city":"East Rockaway",
    "sg:classifiers":[
        {
            "category":"Bars & Pubs",
            "type":"Food & Drink"
        }
    ],
    "sg:phone":"+1 516 887 2495",
    "sg:postcode":"11518",
    "sg:province":"NY",
    "wof:name":"Danno's Tavern",
    "wof:placetype":"venue"
},
  "geometry": {"coordinates":[-73.665826,40.641619],"type":"Point"}
}