{
  "type": "Feature",
  "properties": {
    "addr:full":"9201 102nd Street Richmond Hill NY 11418",
    "addr:housenumber":"9201",
    "addr:postcode":"11418",
    "addr:street":"102Nd Street",
    "iso:country":"US",
    "sg:address":"9201 102nd Street",
    "sg:city":"Richmond Hill",
    "sg:classifiers":[
        {
            "category":"Place Of Worship",
            "subcategory":"Synagogue",
            "type":"Public Place"
        }
    ],
    "sg:phone":"+1 718 847 9688",
    "sg:postcode":"11418",
    "sg:province":"NY",
    "wof:name":"Congregation Beth Israel of Richmond Hill",
    "wof:placetype":"venue"
},
  "geometry": {"coordinates":[-73.843191,40.690977],"type":"Point"}
}