{
  "type": "Feature",
  "properties": {
    "addr:full":"116 Lynch St Syracuse NY 13210",
    "addr:housenumber":"116",
    "addr:postcode":"13210",
    "addr:street":"Lynch St",
    "iso:country":"US",
    "sg:address":"116 Lynch St",
    "sg:city":"Syracuse",
    "sg:classifiers":[
        {
            "category":"Wholesale",
            "subcategory":"Seafood",
            "type":"Manufacturing & Wholesale Goods"
        }
    ],
    "sg:phone":"+1 315 422 3474",
    "sg:postcode":"13210",
    "sg:province":"NY",
    "sg:tags":[
        "food",
        "spec"
    ],
    "wof:name":"Polge Seafood Distributing Inc",
    "wof:placetype":"venue"
},
  "geometry": {"coordinates":[-76.11873900000001,43.051508],"type":"Point"}
}