{
  "type": "Feature",
  "properties": {
    "addr:full":"555 Westchester Ave Rye Brook NY 10573",
    "addr:housenumber":"555",
    "addr:postcode":"10573",
    "addr:street":"Westchester Ave",
    "iso:country":"US",
    "sg:address":"555 Westchester Ave",
    "sg:city":"Rye Brook",
    "sg:classifiers":[
        {
            "category":"Insurance",
            "subcategory":"Insurance Agent",
            "type":"Services"
        }
    ],
    "sg:phone":"+1 914 939 0011",
    "sg:postcode":"10573",
    "sg:province":"NY",
    "wof:name":"Borelli & Russo Insurance Agcy",
    "wof:placetype":"venue"
},
  "geometry": {"coordinates":[-73.68091200000001,41.005805],"type":"Point"}
}