{
  "type": "Feature",
  "properties": {
    "iso:country":"US",
    "sg:address":"21 Red Oaks Mill Rd",
    "sg:city":"Poughkeepsie",
    "sg:classifiers":[
        {
            "category":"Government",
            "subcategory":"Fire Station",
            "type":"Public Place"
        }
    ],
    "sg:phone":"+1 845 462 2277",
    "sg:postcode":"12603",
    "sg:province":"NY",
    "sg:tags":[
        "protection"
    ],
    "wof:name":"SW Lagrange Fire Company 3",
    "wof:placetype":"venue"
},
  "geometry": {"coordinates":[-73.868256,41.6567],"type":"Point"}
}