{
  "type": "Feature",
  "properties": {
    "addr:full":"147 W 79 St New York NY 10024",
    "addr:housenumber":"147",
    "addr:postcode":"10024",
    "addr:street":"W 79 St",
    "iso:country":"US",
    "sg:address":"147 W 79 St",
    "sg:city":"New York",
    "sg:classifiers":[
        {
            "category":"Health Services",
            "subcategory":"Health Practitioner",
            "type":"Services"
        }
    ],
    "sg:phone":"+1 212 875 0400",
    "sg:postcode":"10024",
    "sg:province":"NY",
    "sg:tags":[
        "psychologist"
    ],
    "wof:name":"Neal K May",
    "wof:placetype":"venue"
},
  "geometry": {"coordinates":[-73.97669999999999,40.782331],"type":"Point"}
}