{
  "type": "Feature",
  "properties": {
    "addr:full":"298 W 147th Street New York NY 10039",
    "addr:housenumber":"298",
    "addr:postcode":"10039",
    "addr:street":"W 147Th Street",
    "iso:country":"US",
    "sg:address":"298 W 147th Street",
    "sg:city":"New York",
    "sg:classifiers":[
        {
            "category":"Organizations",
            "subcategory":"Religious Organization",
            "type":"Services"
        }
    ],
    "sg:phone":"+1 212 491 3663",
    "sg:postcode":"10039",
    "sg:province":"NY",
    "wof:name":"Nazareth Associates",
    "wof:placetype":"venue"
},
  "geometry": {"coordinates":[-73.940967,40.824132],"type":"Point"}
}