{
  "type": "Feature",
  "properties": {
    "addr:full":"653 Washington St New York NY 10014",
    "addr:housenumber":"653",
    "addr:postcode":"10014",
    "addr:street":"Washington St",
    "iso:country":"US",
    "sg:address":"653 Washington St",
    "sg:city":"New York",
    "sg:classifiers":[
        {
            "category":"Health Services",
            "subcategory":"Health Practitioner",
            "type":"Services"
        }
    ],
    "sg:phone":"+1 212 741 6817",
    "sg:postcode":"10014",
    "sg:province":"NY",
    "sg:tags":[
        "psychologist"
    ],
    "wof:name":"Mary M Frederick",
    "wof:placetype":"venue"
},
  "geometry": {"coordinates":[-74.008494,40.733205],"type":"Point"}
}