{
  "type": "Feature",
  "properties": {
    "addr:full":"760 Winton Rd N Rochester NY 14609",
    "addr:housenumber":"760",
    "addr:postcode":"14609",
    "addr:street":"Winton Rd N",
    "iso:country":"US",
    "sg:address":"760 Winton Rd N",
    "sg:city":"Rochester",
    "sg:classifiers":[
        {
            "category":"Professional",
            "subcategory":"Accounting & Tax Preparation",
            "type":"Services"
        }
    ],
    "sg:phone":"+1 585 654 7300",
    "sg:postcode":"14609",
    "sg:province":"NY",
    "sg:tags":[
        "accountant"
    ],
    "wof:name":"Nelson P Maracle CPA",
    "wof:placetype":"venue"
},
  "geometry": {"coordinates":[-77.547224,43.160032],"type":"Point"}
}