{
  "type": "Feature",
  "properties": {
    "addr:full":"49th St and Lexington Ave New York NY 10079",
    "addr:postcode":"10079",
    "addr:street":"49Th St",
    "iso:country":"US",
    "sg:address":"49th St and Lexington Ave",
    "sg:city":"New York",
    "sg:classifiers":[
        {
            "category":"Food & Beverages",
            "subcategory":"Specialty",
            "type":"Retail Goods"
        },
        {
            "category":"Food Court",
            "type":"Food & Drink"
        }
    ],
    "sg:postcode":"10079",
    "sg:province":"NY",
    "sg:tags":[
        "stand"
    ],
    "wof:name":"Chicken and Rice Plate Vendor",
    "wof:placetype":"venue"
},
  "geometry": {"coordinates":[-73.97281099999999,40.755856],"type":"Point"}
}