{
  "type": "Feature",
  "properties": {
    "addr:full":"116 Hillwood Dr Huntington Station NY 11746",
    "addr:housenumber":"116",
    "addr:postcode":"11746",
    "addr:street":"Hillwood Dr",
    "iso:country":"US",
    "sg:address":"116 Hillwood Dr",
    "sg:city":"Huntington Station",
    "sg:classifiers":[
        {
            "category":"Food & Beverages",
            "subcategory":"Groceries & Convenience Stores",
            "type":"Retail Goods"
        }
    ],
    "sg:phone":"+1   ",
    "sg:postcode":"11746",
    "sg:province":"NY",
    "sg:tags":[
        "advisory",
        "investment"
    ],
    "wof:name":"AGC Financial Srervices Inc",
    "wof:placetype":"venue"
},
  "geometry": {"coordinates":[-73.424854,40.849706],"type":"Point"}
}