{
  "type": "Feature",
  "properties": {
    "addr:full":"15019 Liberty Ave Jamaica NY 11433",
    "addr:housenumber":"15019",
    "addr:postcode":"11433",
    "addr:street":"Liberty Ave",
    "iso:country":"US",
    "sg:address":"15019 Liberty Ave",
    "sg:city":"Jamaica",
    "sg:classifiers":[
        {
            "category":"Deli",
            "type":"Food & Drink"
        }
    ],
    "sg:phone":"+1 718 523 6700",
    "sg:postcode":"11433",
    "sg:province":"NY",
    "wof:name":"Lil Anthony's Deli",
    "wof:placetype":"venue"
},
  "geometry": {"coordinates":[-73.801804,40.6982],"type":"Point"}
}