{
  "type": "Feature",
  "properties": {
    "addr:full":"414 E 71st St New York NY 10021",
    "addr:housenumber":"414",
    "addr:postcode":"10021",
    "addr:street":"E 71St St",
    "iso:country":"US",
    "sg:address":"414 E 71st St",
    "sg:city":"New York",
    "sg:classifiers":[
        {
            "category":"Professional",
            "type":"Services"
        }
    ],
    "sg:phone":"+1   ",
    "sg:postcode":"10021",
    "sg:province":"NY",
    "wof:name":"Wood Essentials Ltd",
    "wof:placetype":"venue"
},
  "geometry": {"coordinates":[-73.954528,40.766236],"type":"Point"}
}