{
  "type": "Feature",
  "properties": {
    "iso:country":"US",
    "sg:address":"31 Green Brook Dr",
    "sg:city":"Brainard",
    "sg:classifiers":[
        {
            "category":"Building & Trades",
            "subcategory":"Construction",
            "type":"Services"
        }
    ],
    "sg:phone":"+1 518 766 4921",
    "sg:postcode":"12115",
    "sg:province":"NY",
    "sg:tags":[
        "roofing",
        "contractor"
    ],
    "wof:name":"Luft Lightning Protection",
    "wof:placetype":"venue"
},
  "geometry": {"coordinates":[-73.564769,42.480225],"type":"Point"}
}