{
  "type": "Feature",
  "properties": {
    "iso:country":"US",
    "sg:address":"454 Tim Hill Rd",
    "sg:city":"Marathon",
    "sg:classifiers":[
        {
            "category":"Manufacturing",
            "subcategory":"Buildings",
            "type":"Manufacturing & Wholesale Goods"
        },
        {
            "category":"Building & Trades",
            "subcategory":"Construction",
            "type":"Services"
        }
    ],
    "sg:phone":"+1 607 849 6086",
    "sg:postcode":"13803",
    "sg:province":"NY",
    "sg:tags":[
        "home",
        "builder",
        "contractor"
    ],
    "wof:name":"Dbs Construction",
    "wof:placetype":"venue"
},
  "geometry": {"coordinates":[-76.042451,42.432693],"type":"Point"}
}