{
  "type": "Feature",
  "properties": {
    "addr:full":"461 State Hwy 144 Glenmont NY 12077",
    "addr:housenumber":"461",
    "addr:postcode":"12077",
    "addr:street":"State Hwy 144",
    "iso:country":"US",
    "sg:address":"461 State Hwy 144",
    "sg:city":"Glenmont",
    "sg:phone":"+1 518 449 9095",
    "sg:postcode":"12077",
    "sg:province":"NY",
    "sg:tags":[
        "bulk",
        "gas"
    ],
    "wof:name":"Praxair Inc",
    "wof:placetype":"venue"
},
  "geometry": {"coordinates":[-73.76649999999999,42.62016],"type":"Point"}
}