{
  "type": "Feature",
  "properties": {
    "addr:full":"414 Albemarle Rd Brooklyn NY 11218",
    "addr:housenumber":"414",
    "addr:postcode":"11218",
    "addr:street":"Albemarle Rd",
    "iso:country":"US",
    "sg:address":"414 Albemarle Rd",
    "sg:city":"Brooklyn",
    "sg:classifiers":[
        {
            "category":"Professional",
            "subcategory":"Management & Consulting",
            "type":"Services"
        }
    ],
    "sg:phone":"+1 718 633 5131",
    "sg:postcode":"11218",
    "sg:province":"NY",
    "wof:name":"Fin Alley Management",
    "wof:placetype":"venue"
},
  "geometry": {"coordinates":[-73.97600799999999,40.645455],"type":"Point"}
}