{
  "type": "Feature",
  "properties": {
    "addr:full":"9 Continental Avenue Forest Hills NY 11375",
    "addr:housenumber":"9",
    "addr:postcode":"11375",
    "addr:street":"Continental Avenue",
    "iso:country":"US",
    "sg:address":"9 Continental Avenue",
    "sg:city":"Forest Hills",
    "sg:classifiers":[
        {
            "category":"Professional",
            "subcategory":"Lawyer & Legal Services",
            "type":"Services"
        }
    ],
    "sg:phone":"+1 718 268 8111",
    "sg:postcode":"11375",
    "sg:province":"NY",
    "sg:tags":[
        "divorce",
        "law",
        "family"
    ],
    "wof:name":"Mastrodomenico Donald Attorney",
    "wof:placetype":"venue"
},
  "geometry": {"coordinates":[-73.84547499999999,40.719063],"type":"Point"}
}