{
  "type": "Feature",
  "properties": {
    "addr:full":"200 W 54 St New York NY 10019",
    "addr:housenumber":"200",
    "addr:postcode":"10019",
    "addr:street":"W 54 St",
    "iso:country":"US",
    "sg:address":"200 W 54 St",
    "sg:city":"New York",
    "sg:classifiers":[
        {
            "category":"Banks & Credit Unions",
            "subcategory":"Investment Brokerage",
            "type":"Services"
        }
    ],
    "sg:phone":"+1 212 397 7791",
    "sg:postcode":"10019",
    "sg:province":"NY",
    "sg:tags":[
        "advisory",
        "financial"
    ],
    "wof:name":"Chiron Global Advisory",
    "wof:placetype":"venue"
},
  "geometry": {"coordinates":[-73.98246899999999,40.764033],"type":"Point"}
}