{
  "type": "Feature",
  "properties": {
    "addr:full":"668 3rd Ave Brooklyn NY 11232",
    "addr:housenumber":"668",
    "addr:postcode":"11232",
    "addr:street":"3Rd Ave",
    "iso:country":"US",
    "sg:address":"668 3rd Ave",
    "sg:city":"Brooklyn",
    "sg:classifiers":[
        {
            "category":"Autos & Motor Vehicles",
            "subcategory":"Fuel & Gas Station",
            "type":"Retail Goods"
        }
    ],
    "sg:phone":"+1 718 369 2072",
    "sg:postcode":"11232",
    "sg:province":"NY",
    "wof:name":"289 Management Inc",
    "wof:placetype":"venue"
},
  "geometry": {"coordinates":[-73.997394,40.664699],"type":"Point"}
}