{
  "type": "Feature",
  "properties": {
    "addr:full":"904 Morris Park Avenue Bronx NY 10462",
    "addr:housenumber":"904",
    "addr:postcode":"10462",
    "addr:street":"Morris Park Avenue",
    "iso:country":"US",
    "sg:address":"904 Morris Park Avenue",
    "sg:city":"Bronx",
    "sg:classifiers":[
        {
            "category":"Social Services",
            "subcategory":"Child Care",
            "type":"Services"
        }
    ],
    "sg:phone":"+1 718 823 8345",
    "sg:postcode":"10462",
    "sg:province":"NY",
    "sg:tags":[
        "day"
    ],
    "wof:name":"For Kids Only",
    "wof:placetype":"venue"
},
  "geometry": {"coordinates":[-73.859442,40.846654],"type":"Point"}
}