{
  "type": "Feature",
  "properties": {
    "addr:full":"789 E 163rd St Bronx NY 10456",
    "addr:housenumber":"789",
    "addr:postcode":"10456",
    "addr:street":"E 163Rd St",
    "iso:country":"US",
    "sg:address":"789 E 163rd St",
    "sg:city":"Bronx",
    "sg:classifiers":[
        {
            "category":"Restaurant",
            "type":"Food & Drink"
        }
    ],
    "sg:phone":"+1   ",
    "sg:postcode":"10456",
    "sg:province":"NY",
    "sg:tags":[
        "eating"
    ],
    "wof:name":"Stop At Spot Restaurant",
    "wof:placetype":"venue"
},
  "geometry": {"coordinates":[-73.902198,40.822585],"type":"Point"}
}