{
  "type": "Feature",
  "properties": {
    "iso:country":"US",
    "sg:address":"6084 State Hwy 5",
    "sg:city":"Palatine Bridge",
    "sg:classifiers":[
        {
            "category":"Bars & Pubs",
            "type":"Food & Drink"
        }
    ],
    "sg:phone":"+1   ",
    "sg:postcode":"13428",
    "sg:province":"NY",
    "sg:tags":[
        "drinking"
    ],
    "wof:name":"Valley Inn D Js",
    "wof:placetype":"venue"
},
  "geometry": {"coordinates":[-74.591711,42.916422],"type":"Point"}
}