{
  "type": "Feature",
  "properties": {
    "iso:country":"US",
    "sg:address":"1425 Taylor Ave",
    "sg:city":"Utica",
    "sg:classifiers":[
        {
            "category":"Building & Trades",
            "subcategory":"Construction",
            "type":"Services"
        }
    ],
    "sg:phone":"+1 315 724 9583",
    "sg:postcode":"13501",
    "sg:province":"NY",
    "sg:tags":[
        "contractor"
    ],
    "wof:name":"Paulson Contracting",
    "wof:placetype":"venue"
},
  "geometry": {"coordinates":[-75.231154,43.087571],"type":"Point"}
}