{
  "type": "Feature",
  "properties": {
    "addr:full":"363 Greenwich St New York NY 10013",
    "addr:housenumber":"363",
    "addr:postcode":"10013",
    "addr:street":"Greenwich St",
    "iso:country":"US",
    "sg:address":"363 Greenwich St",
    "sg:city":"New York",
    "sg:classifiers":[
        {
            "category":"Restaurant",
            "type":"Food & Drink"
        }
    ],
    "sg:phone":"+1   ",
    "sg:postcode":"10013",
    "sg:province":"NY",
    "sg:tags":[
        "eating"
    ],
    "wof:name":"Andrew Chan",
    "wof:placetype":"venue"
},
  "geometry": {"coordinates":[-74.010265,40.719071],"type":"Point"}
}