{
  "type": "Feature",
  "properties": {
    "iso:country":"US",
    "sg:address":"456 Broadway",
    "sg:city":"Monticello",
    "sg:classifiers":[
        {
            "category":"Bars & Pubs",
            "type":"Food & Drink"
        }
    ],
    "sg:phone":"+1 845 791 9463",
    "sg:postcode":"12701",
    "sg:province":"NY",
    "wof:name":"Vino",
    "wof:placetype":"venue"
},
  "geometry": {"coordinates":[-74.699457,41.658345],"type":"Point"}
}