{
  "type": "Feature",
  "properties": {
    "iso:country":"US",
    "sg:address":"4 Springfield Cir",
    "sg:city":"Central Islip",
    "sg:classifiers":[
        {
            "category":"Professional",
            "type":"Services"
        }
    ],
    "sg:phone":"+1 631 286 8070",
    "sg:postcode":"11722",
    "sg:province":"NY",
    "sg:tags":[
        "establishment"
    ],
    "wof:name":"Tri State Filter & Hvac",
    "wof:placetype":"venue"
},
  "geometry": {"coordinates":[-73.197469,40.779216],"type":"Point"}
}