{
  "type": "Feature",
  "properties": {
    "addr:full":"288 Grumman Rd W Bethpage NY 11714",
    "addr:housenumber":"288",
    "addr:postcode":"11714",
    "addr:street":"Grumman Rd W Bethpage",
    "iso:country":"US",
    "sg:address":"288 Grumman Rd W",
    "sg:city":"Bethpage",
    "sg:classifiers":[
        {
            "category":"Professional",
            "type":"Services"
        }
    ],
    "sg:phone":"+1 516 349 1970",
    "sg:postcode":"11714",
    "sg:province":"NY",
    "sg:tags":[
        "establishment"
    ],
    "wof:name":"M T Of New York",
    "wof:placetype":"venue"
},
  "geometry": {"coordinates":[-73.497191,40.74964],"type":"Point"}
}