{
  "type": "Feature",
  "properties": {
    "iso:country":"US",
    "sg:address":"16 Court St",
    "sg:city":"Brooklyn",
    "sg:classifiers":[
        {
            "category":"Professional",
            "subcategory":"Lawyer & Legal Services",
            "type":"Services"
        }
    ],
    "sg:phone":"+1 718 797 4100",
    "sg:postcode":"11241",
    "sg:province":"NY",
    "wof:name":"Caspi Avi",
    "wof:placetype":"venue"
},
  "geometry": {"coordinates":[-73.9907,40.693298],"type":"Point"}
}