{
  "type": "Feature",
  "properties": {
    "iso:country":"US",
    "sg:address":"32 Campbell Ave",
    "sg:city":"Williston Park",
    "sg:classifiers":[
        {
            "category":"Manufacturing",
            "subcategory":"Printing",
            "type":"Manufacturing & Wholesale Goods"
        }
    ],
    "sg:phone":"+1   ",
    "sg:postcode":"11596",
    "sg:province":"NY",
    "sg:tags":[
        "commercial"
    ],
    "wof:name":"Paper Mill Stationers",
    "wof:placetype":"venue"
},
  "geometry": {"coordinates":[-73.649038,40.755422],"type":"Point"}
}