{
  "type": "Feature",
  "properties": {
    "addr:full":"3532 Holland Ave Bronx NY 10467",
    "addr:housenumber":"3532",
    "addr:postcode":"10467",
    "addr:street":"Holland Ave",
    "iso:country":"US",
    "sg:address":"3532 Holland Ave",
    "sg:city":"Bronx",
    "sg:classifiers":[
        {
            "category":"Manufacturing",
            "subcategory":"Wood Products",
            "type":"Manufacturing & Wholesale Goods"
        }
    ],
    "sg:phone":"+1 718 652 4670",
    "sg:postcode":"10467",
    "sg:province":"NY",
    "wof:name":"Alpa Moulding Co",
    "wof:placetype":"venue"
},
  "geometry": {"coordinates":[-73.86409999999999,40.878074],"type":"Point"}
}