{
  "type": "Feature",
  "properties": {
    "addr:full":"33 Halstead Ave Harrison NY 10528",
    "addr:housenumber":"33",
    "addr:postcode":"10528",
    "addr:street":"Halstead Ave",
    "iso:country":"US",
    "sg:address":"33 Halstead Ave",
    "sg:city":"Harrison",
    "sg:classifiers":[
        {
            "category":"Manufacturing",
            "subcategory":"Printing",
            "type":"Manufacturing & Wholesale Goods"
        }
    ],
    "sg:phone":"+1 914 835 5400",
    "sg:postcode":"10528",
    "sg:province":"NY",
    "sg:tags":[
        "newspaper"
    ],
    "wof:name":"Womens's News",
    "wof:placetype":"venue"
},
  "geometry": {"coordinates":[-73.72156,40.963001],"type":"Point"}
}