{
  "type": "Feature",
  "properties": {
    "addr:full":"131 Sherrill Rd Sherrill NY 13461",
    "addr:housenumber":"131",
    "addr:postcode":"13461",
    "addr:street":"Sherrill Rd",
    "iso:country":"US",
    "sg:address":"131 Sherrill Rd",
    "sg:city":"Sherrill",
    "sg:classifiers":[
        {
            "category":"Insurance",
            "subcategory":"Insurance Agent",
            "type":"Services"
        }
    ],
    "sg:phone":"+1 315 361 8700",
    "sg:postcode":"13461",
    "sg:province":"NY",
    "wof:name":"Todd C Roberts & Assoc",
    "wof:placetype":"venue"
},
  "geometry": {"coordinates":[-75.59810400000001,43.076563],"type":"Point"}
}