{
  "type": "Feature",
  "properties": {
    "iso:country":"US",
    "sg:address":"228 Hansen Rd",
    "sg:city":"Schaghticoke",
    "sg:classifiers":[
        {
            "category":"Shopping",
            "type":"Retail Goods"
        }
    ],
    "sg:phone":"+1 518 753 6589",
    "sg:postcode":"12154",
    "sg:province":"NY",
    "sg:tags":[
        "merchandise"
    ],
    "wof:name":"Kimberly S Bargain Shop",
    "wof:placetype":"venue"
},
  "geometry": {"coordinates":[-73.624509,42.879823],"type":"Point"}
}