{
  "type": "Feature",
  "properties": {
    "iso:country":"US",
    "sg:address":"2116 Merrick Ave",
    "sg:city":"Merrick",
    "sg:classifiers":[
        {
            "category":"Cinema",
            "subcategory":"Movie Theater",
            "type":"Entertainment"
        }
    ],
    "sg:phone":"+1 516 377 4767",
    "sg:postcode":"11566",
    "sg:province":"NY",
    "wof:name":"Movieland Cinemas",
    "wof:placetype":"venue"
},
  "geometry": {"coordinates":[-73.55383500000001,40.667765],"type":"Point"}
}