{
  "type": "Feature",
  "properties": {
    "addr:full":"345 Dug Rd Accord NY 12404",
    "addr:housenumber":"345",
    "addr:postcode":"12404",
    "addr:street":"Dug Rd",
    "iso:country":"US",
    "sg:address":"345 Dug Rd",
    "sg:city":"Accord",
    "sg:classifiers":[
        {
            "category":"Arts & Performance",
            "subcategory":"Theater",
            "type":"Entertainment"
        }
    ],
    "sg:phone":"+1   ",
    "sg:postcode":"12404",
    "sg:province":"NY",
    "sg:tags":[
        "production",
        "radio",
        "audio"
    ],
    "wof:name":"Jim Metzner Productions Inc",
    "wof:placetype":"venue"
},
  "geometry": {"coordinates":[-74.271525,41.848997],"type":"Point"}
}