{
  "type": "Feature",
  "properties": {
    "addr:full":"329 Roehrer Ave Buffalo NY 14208",
    "addr:housenumber":"329",
    "addr:postcode":"14208",
    "addr:street":"Roehrer Ave",
    "iso:country":"US",
    "sg:address":"329 Roehrer Ave",
    "sg:city":"Buffalo",
    "sg:classifiers":[
        {
            "category":"Organizations",
            "subcategory":"Non-profit Organization",
            "type":"Services"
        }
    ],
    "sg:phone":"+1 716 886 4285",
    "sg:postcode":"14208",
    "sg:province":"NY",
    "sg:tags":[
        "charitable",
        "institution"
    ],
    "wof:name":"Catholic Charities",
    "wof:placetype":"venue"
},
  "geometry": {"coordinates":[-78.849046,42.912657],"type":"Point"}
}