{
  "type": "Feature",
  "properties": {
    "addr:full":"530 Franklin Ave Franklin Square NY 11010",
    "addr:housenumber":"530",
    "addr:postcode":"11010",
    "addr:street":"Franklin Ave",
    "iso:country":"US",
    "sg:address":"530 Franklin Ave",
    "sg:city":"Franklin Square",
    "sg:classifiers":[
        {
            "category":"Autos & Motor Vehicles",
            "subcategory":"Fuel & Gas Station",
            "type":"Retail Goods"
        }
    ],
    "sg:phone":"+1 516 327 9707",
    "sg:postcode":"11010",
    "sg:province":"NY",
    "sg:website":"www.surbhi.com",
    "wof:name":"Surbhi LLC",
    "wof:placetype":"venue"
},
  "geometry": {"coordinates":[-73.683513,40.693779],"type":"Point"}
}