{
  "type": "Feature",
  "properties": {
    "addr:full":"17 Morrow Ave Lockport NY 14094",
    "addr:housenumber":"17",
    "addr:postcode":"14094",
    "addr:street":"Morrow Ave",
    "iso:country":"US",
    "sg:address":"17 Morrow Ave",
    "sg:city":"Lockport",
    "sg:classifiers":[
        {
            "category":"Retail",
            "subcategory":"Laundry & Dry Cleaning",
            "type":"Services"
        }
    ],
    "sg:phone":"+1 716 433 3860",
    "sg:postcode":"14094",
    "sg:province":"NY",
    "sg:tags":[
        "cleaners",
        "rug",
        "carpet"
    ],
    "wof:name":"Pro Carpet Cleaners",
    "wof:placetype":"venue"
},
  "geometry": {"coordinates":[-78.680784,43.160959],"type":"Point"}
}