{
  "type": "Feature",
  "properties": {
    "iso:country":"US",
    "sg:address":"5014 Jericho Tpke",
    "sg:city":"Commack",
    "sg:classifiers":[
        {
            "category":"Shopping",
            "type":"Retail Goods"
        }
    ],
    "sg:phone":"+1 631 493 4725",
    "sg:postcode":"11725",
    "sg:province":"NY",
    "sg:website":"www.dollartree.com",
    "wof:name":"Dollar Tree",
    "wof:placetype":"venue"
},
  "geometry": {"coordinates":[-73.31250199999999,40.840604],"type":"Point"}
}