{
  "type": "Feature",
  "properties": {
    "addr:full":"232 E 82nd St New York NY 10028",
    "addr:housenumber":"232",
    "addr:postcode":"10028",
    "addr:street":"E 82Nd St",
    "iso:country":"US",
    "sg:address":"232 E 82nd St",
    "sg:city":"New York",
    "sg:classifiers":[
        {
            "category":"Professional",
            "subcategory":"Computer Services",
            "type":"Services"
        }
    ],
    "sg:phone":"+1 212 794 9288",
    "sg:postcode":"10028",
    "sg:province":"NY",
    "sg:tags":[
        "website",
        "graphic",
        "design"
    ],
    "wof:name":"Y Interact",
    "wof:placetype":"venue"
},
  "geometry": {"coordinates":[-73.95421899999999,40.775533],"type":"Point"}
}