{
  "type": "Feature",
  "properties": {
    "iso:country":"US",
    "sg:address":"1275 York Ave",
    "sg:city":"New York",
    "sg:classifiers":[
        {
            "category":"Health Services",
            "subcategory":"Doctor",
            "type":"Services"
        }
    ],
    "sg:phone":"+1 212 639 7562",
    "sg:postcode":"10021",
    "sg:province":"NY",
    "wof:name":"Turnbull Alan MD",
    "wof:placetype":"venue"
},
  "geometry": {"coordinates":[-73.95549800000001,40.764599],"type":"Point"}
}