{
  "type": "Feature",
  "properties": {
    "iso:country":"US",
    "sg:address":"67 Wall St",
    "sg:city":"New York",
    "sg:classifiers":[
        {
            "category":"Professional",
            "subcategory":"Lawyer & Legal Services",
            "type":"Services"
        }
    ],
    "sg:phone":"+1 212 292 0463",
    "sg:postcode":"10005",
    "sg:province":"NY",
    "sg:tags":[
        "attorney"
    ],
    "wof:name":"Law Offices-Anthony Ladevaia",
    "wof:placetype":"venue"
},
  "geometry": {"coordinates":[-74.008284,40.705692],"type":"Point"}
}