{
  "type": "Feature",
  "properties": {
    "addr:full":"299 Grand St New York NY 10002",
    "addr:housenumber":"299",
    "addr:postcode":"10002",
    "addr:street":"Grand St",
    "iso:country":"US",
    "sg:address":"299 Grand St",
    "sg:city":"New York",
    "sg:classifiers":[
        {
            "category":"Shopping",
            "subcategory":"Shoes",
            "type":"Retail Goods"
        }
    ],
    "sg:phone":"+1 212 219 9452",
    "sg:postcode":"10002",
    "sg:province":"NY",
    "sg:tags":[
        "store"
    ],
    "wof:name":"D Extra Trading Corp",
    "wof:placetype":"venue"
},
  "geometry": {"coordinates":[-73.99203,40.717464],"type":"Point"}
}