{
  "type": "Feature",
  "properties": {
    "iso:country":"US",
    "sg:address":"1297 State Hwy 420",
    "sg:city":"Brasher Falls",
    "sg:classifiers":[
        {
            "category":"Autos & Motor Vehicles",
            "subcategory":"Automobile Sales",
            "type":"Retail Goods"
        }
    ],
    "sg:phone":"+1   ",
    "sg:postcode":"13662",
    "sg:province":"NY",
    "sg:tags":[
        "repair"
    ],
    "wof:name":"Laflesh Garage",
    "wof:placetype":"venue"
},
  "geometry": {"coordinates":[-74.84162999999999,44.843384],"type":"Point"}
}