{
  "type": "Feature",
  "properties": {
    "addr:full":"31 E Main St Victor NY 14564",
    "addr:housenumber":"31",
    "addr:postcode":"14564",
    "addr:street":"E Main St",
    "iso:country":"US",
    "sg:address":"31 E Main St",
    "sg:city":"Victor",
    "sg:classifiers":[
        {
            "category":"Shopping",
            "subcategory":"Used Merchandise",
            "type":"Retail Goods"
        }
    ],
    "sg:phone":"+1   ",
    "sg:postcode":"14564",
    "sg:province":"NY",
    "wof:name":"Act 2 Consignment Shop",
    "wof:placetype":"venue"
},
  "geometry": {"coordinates":[-77.408602,42.982405],"type":"Point"}
}