{
  "type": "Feature",
  "properties": {
    "addr:full":"167 E Park Ave Long Beach NY 11561",
    "addr:housenumber":"167",
    "addr:postcode":"11561",
    "addr:street":"E Park Ave",
    "iso:country":"US",
    "sg:address":"167 E Park Ave",
    "sg:city":"Long Beach",
    "sg:classifiers":[
        {
            "category":"Government",
            "subcategory":"Office",
            "type":"Public Place"
        }
    ],
    "sg:phone":"+1 516 571 7766",
    "sg:postcode":"11561",
    "sg:province":"NY",
    "wof:name":"Nassau County Senior Citizen",
    "wof:placetype":"venue"
},
  "geometry": {"coordinates":[-73.659734,40.58859],"type":"Point"}
}