{
  "type": "Feature",
  "properties": {
    "iso:country":"US",
    "sg:address":"1557 Westchester Ave",
    "sg:city":"Bronx",
    "sg:classifiers":[
        {
            "category":"Shopping",
            "subcategory":"Hobbies, Toys, & Games",
            "type":"Retail Goods"
        }
    ],
    "sg:phone":"+1 718 991 0015",
    "sg:postcode":"10472",
    "sg:province":"NY",
    "wof:name":"Uncle Jay Inc",
    "wof:placetype":"venue"
},
  "geometry": {"coordinates":[-73.877937,40.828744],"type":"Point"}
}