{
  "type": "Feature",
  "properties": {
    "iso:country":"US",
    "sg:address":"34 E 23rd St",
    "sg:city":"New York",
    "sg:classifiers":[
        {
            "category":"Food & Beverages",
            "subcategory":"Bakery",
            "type":"Retail Goods"
        }
    ],
    "sg:phone":"+1 212 679 4699",
    "sg:postcode":"10010",
    "sg:province":"NY",
    "sg:tags":[
        "sandwich"
    ],
    "sg:website":"www.pressny.com",
    "wof:name":"Press",
    "wof:placetype":"venue"
},
  "geometry": {"coordinates":[-73.987534,40.74055],"type":"Point"}
}