{
  "type": "Feature",
  "properties": {
    "addr:full":"81 Union Ave New Rochelle NY 10801",
    "addr:housenumber":"81",
    "addr:postcode":"10801",
    "addr:street":"Union Ave",
    "iso:country":"US",
    "sg:address":"81 Union Ave",
    "sg:city":"New Rochelle",
    "sg:classifiers":[
        {
            "category":"Organizations",
            "subcategory":"Community Association",
            "type":"Services"
        }
    ],
    "sg:phone":"+1 914 632 9742",
    "sg:postcode":"10801",
    "sg:province":"NY",
    "sg:tags":[
        "club"
    ],
    "wof:name":"Calabria Mutual Aid Society",
    "wof:placetype":"venue"
},
  "geometry": {"coordinates":[-73.788158,40.910244],"type":"Point"}
}