{
  "type": "Feature",
  "properties": {
    "addr:full":"37 Phila St Saratoga Springs NY 12866",
    "addr:housenumber":"37",
    "addr:postcode":"12866",
    "addr:street":"Phila St",
    "iso:country":"US",
    "sg:address":"37 Phila St",
    "sg:city":"Saratoga Springs",
    "sg:classifiers":[
        {
            "category":"Restaurant",
            "type":"Food & Drink"
        }
    ],
    "sg:phone":"+1 518 583 6060",
    "sg:postcode":"12866",
    "sg:province":"NY",
    "sg:tags":[
        "eating"
    ],
    "sg:website":"www.baileyscafe.com",
    "wof:name":"Bailey's Cafe",
    "wof:placetype":"venue"
},
  "geometry": {"coordinates":[-73.783766,43.080489],"type":"Point"}
}