{
  "type": "Feature",
  "properties": {
    "addr:full":"275 Madison Avenue New York NY 10016",
    "addr:housenumber":"275",
    "addr:postcode":"10016",
    "addr:street":"Madison Avenue",
    "iso:country":"US",
    "sg:address":"275 Madison Avenue",
    "sg:city":"New York",
    "sg:classifiers":[
        {
            "category":"Autos & Motor Vehicles",
            "subcategory":"Automobile Sales",
            "type":"Retail Goods"
        },
        {
            "category":"Taxi",
            "type":"Transportation"
        }
    ],
    "sg:phone":"+1 212 873 4444",
    "sg:postcode":"10016",
    "sg:province":"NY",
    "sg:tags":[
        "limo"
    ],
    "sg:website":"www.LimousineNewYorkNY.com",
    "wof:name":"Limousine New York NY",
    "wof:placetype":"venue"
},
  "geometry": {"coordinates":[-73.979981,40.751223],"type":"Point"}
}