{
  "type": "Feature",
  "properties": {
    "addr:full":"631 Newport Rd Utica NY 13502",
    "addr:housenumber":"631",
    "addr:postcode":"13502",
    "addr:street":"Newport Rd",
    "iso:country":"US",
    "sg:address":"631 Newport Rd",
    "sg:city":"Utica",
    "sg:classifiers":[
        {
            "category":"Building & Trades",
            "subcategory":"Construction",
            "type":"Services"
        }
    ],
    "sg:phone":"+1 315 732 0654",
    "sg:postcode":"13502",
    "sg:province":"NY",
    "sg:tags":[
        "excavation",
        "contractor"
    ],
    "wof:name":"R G Excavating",
    "wof:placetype":"venue"
},
  "geometry": {"coordinates":[-75.13746500000001,43.115414],"type":"Point"}
}