{
  "type": "Feature",
  "properties": {
    "iso:country":"US",
    "sg:address":"661 Classon Ave",
    "sg:city":"Brooklyn",
    "sg:classifiers":[
        {
            "category":"Shopping",
            "subcategory":"Department Store",
            "type":"Retail Goods"
        }
    ],
    "sg:phone":"+1 718 638 7653",
    "sg:postcode":"11238",
    "sg:province":"NY",
    "sg:tags":[
        "shop"
    ],
    "wof:name":"Dalit Inc",
    "wof:placetype":"venue"
},
  "geometry": {"coordinates":[-73.958887,40.67809],"type":"Point"}
}