{
  "type": "Feature",
  "properties": {
    "addr:full":"9 Gleason Rd Schenectady NY 12302",
    "addr:housenumber":"9",
    "addr:postcode":"12302",
    "addr:street":"Gleason Rd",
    "iso:country":"US",
    "sg:address":"9 Gleason Rd",
    "sg:city":"Schenectady",
    "sg:classifiers":[
        {
            "category":"Health Services",
            "subcategory":"Optometrist",
            "type":"Services"
        }
    ],
    "sg:phone":"+1 518 399 6368",
    "sg:postcode":"12302",
    "sg:province":"NY",
    "wof:name":"Cusma Lawrence M Dr Optmtrst",
    "wof:placetype":"venue"
},
  "geometry": {"coordinates":[-73.922997,42.889999],"type":"Point"}
}