{
  "type": "Feature",
  "properties": {
    "iso:country":"US",
    "sg:address":"3610 State Hwy 31",
    "sg:city":"Baldwinsville",
    "sg:classifiers":[
        {
            "category":"Restaurant",
            "type":"Food & Drink"
        }
    ],
    "sg:phone":"+1   ",
    "sg:postcode":"13027",
    "sg:province":"NY",
    "sg:tags":[
        "eating"
    ],
    "wof:name":"Dougs Fish Fry",
    "wof:placetype":"venue"
},
  "geometry": {"coordinates":[-76.26598300000001,43.178684],"type":"Point"}
}