{
  "type": "Feature",
  "properties": {
    "addr:full":"4329 209th St Bayside NY 11361",
    "addr:housenumber":"4329",
    "addr:postcode":"11361",
    "addr:street":"209Th St",
    "iso:country":"US",
    "sg:address":"4329 209th St",
    "sg:city":"Bayside",
    "sg:phone":"+1 718 357 6165",
    "sg:postcode":"11361",
    "sg:province":"NY",
    "wof:name":"Kim Sun Young Haircutting Club",
    "wof:placetype":"venue"
},
  "geometry": {"coordinates":[-73.77596699999999,40.761669],"type":"Point"}
}