{
  "type": "Feature",
  "properties": {
    "addr:full":"576 Bradford St Brooklyn NY 11207",
    "addr:housenumber":"576",
    "addr:postcode":"11207",
    "addr:street":"Bradford St",
    "iso:country":"US",
    "sg:address":"576 Bradford St",
    "sg:city":"Brooklyn",
    "sg:classifiers":[
        {
            "category":"Building & Trades",
            "subcategory":"Cleaning & Sanitation",
            "type":"Services"
        }
    ],
    "sg:phone":"+1 718 495 1512",
    "sg:postcode":"11207",
    "sg:province":"NY",
    "sg:tags":[
        "janitor"
    ],
    "wof:name":"Absolutely Clean Inc",
    "wof:placetype":"venue"
},
  "geometry": {"coordinates":[-73.890092,40.664339],"type":"Point"}
}