{
  "type": "Feature",
  "properties": {
    "addr:full":"2711 Ave I Brooklyn NY 11210",
    "addr:housenumber":"2711",
    "addr:postcode":"11210",
    "addr:street":"Ave I",
    "iso:country":"US",
    "sg:address":"2711 Ave I",
    "sg:city":"Brooklyn",
    "sg:classifiers":[
        {
            "category":"Organizations",
            "subcategory":"Religious Organization",
            "type":"Services"
        }
    ],
    "sg:phone":"+1 718 253 4821",
    "sg:postcode":"11210",
    "sg:province":"NY",
    "sg:tags":[
        "clergy"
    ],
    "wof:name":"Hanania Himy",
    "wof:placetype":"venue"
},
  "geometry": {"coordinates":[-73.949335,40.629019],"type":"Point"}
}