{
  "type": "Feature",
  "properties": {
    "iso:country":"US",
    "sg:address":"7487 Fourth Section Rd",
    "sg:city":"Brockport",
    "sg:classifiers":[
        {
            "category":"Recreation",
            "type":"Entertainment"
        }
    ],
    "sg:phone":"+1 585 637 9580",
    "sg:postcode":"14420",
    "sg:province":"NY",
    "sg:tags":[
        "course",
        "golf"
    ],
    "wof:name":"Fawn Ridge Golf",
    "wof:placetype":"venue"
},
  "geometry": {"coordinates":[-77.995535,43.19772],"type":"Point"}
}