{
  "type": "Feature",
  "properties": {
    "addr:full":"46 Sheldon Pl Commack NY 11725",
    "addr:housenumber":"46",
    "addr:postcode":"11725",
    "addr:street":"Sheldon Pl",
    "iso:country":"US",
    "sg:address":"46 Sheldon Pl",
    "sg:city":"Commack",
    "sg:classifiers":[
        {
            "category":"Retail",
            "subcategory":"Repair Shop",
            "type":"Services"
        }
    ],
    "sg:phone":"+1 631 493 0356",
    "sg:postcode":"11725",
    "sg:province":"NY",
    "sg:tags":[
        "lock",
        "locksmith"
    ],
    "wof:name":"Lightning Locks",
    "wof:placetype":"venue"
},
  "geometry": {"coordinates":[-73.30715499999999,40.837271],"type":"Point"}
}