{
  "type": "Feature",
  "properties": {
    "iso:country":"US",
    "sg:address":"46 Tracey St",
    "sg:city":"Whitesboro",
    "sg:classifiers":[
        {
            "category":"Professional",
            "subcategory":"Business Services",
            "type":"Services"
        }
    ],
    "sg:phone":"+1 315 768 1737",
    "sg:postcode":"13492",
    "sg:province":"NY",
    "sg:tags":[
        "trade",
        "contractor"
    ],
    "wof:name":"Porcelain Plus",
    "wof:placetype":"venue"
},
  "geometry": {"coordinates":[-75.295272,43.121559],"type":"Point"}
}