{
  "type": "Feature",
  "properties": {
    "addr:full":"240 Kelly Blvd Staten Island NY 10314",
    "addr:housenumber":"240",
    "addr:postcode":"10314",
    "addr:street":"Kelly Blvd",
    "iso:country":"US",
    "sg:address":"240 Kelly Blvd",
    "sg:city":"Staten Island",
    "sg:classifiers":[
        {
            "category":"Home & Garden",
            "subcategory":"Hardware",
            "type":"Retail Goods"
        }
    ],
    "sg:phone":"+1   ",
    "sg:postcode":"10314",
    "sg:province":"NY",
    "wof:name":"Mermaid Hardware Corp",
    "wof:placetype":"venue"
},
  "geometry": {"coordinates":[-74.157049,40.584299],"type":"Point"}
}