{
  "type": "Feature",
  "properties": {
    "addr:full":"1140 Front St Vestal NY 13850",
    "addr:housenumber":"1140",
    "addr:postcode":"13850",
    "addr:street":"Front St",
    "iso:country":"US",
    "sg:address":"1140 Front St",
    "sg:city":"Vestal",
    "sg:classifiers":[
        {
            "category":"Building & Trades",
            "subcategory":"Plumbing",
            "type":"Services"
        }
    ],
    "sg:phone":"+1 607 754 6376",
    "sg:postcode":"13850",
    "sg:province":"NY",
    "sg:tags":[
        "contractor"
    ],
    "wof:name":"Bakers Plumbing & Heating",
    "wof:placetype":"venue"
},
  "geometry": {"coordinates":[-76.071527,42.080197],"type":"Point"}
}