{
  "type": "Feature",
  "properties": {
    "iso:country":"US",
    "sg:address":"4140 Parsons Blvd Apt 3H",
    "sg:city":"Flushing",
    "sg:classifiers":[
        {
            "category":"Professional",
            "subcategory":"Art Services",
            "type":"Services"
        }
    ],
    "sg:phone":"+1 718 461 8795",
    "sg:postcode":"11355",
    "sg:province":"NY",
    "sg:tags":[
        "ornamental",
        "work",
        "metal"
    ],
    "wof:name":"Tung Hai Ironworks & Construction Inc",
    "wof:placetype":"venue"
},
  "geometry": {"coordinates":[-73.815487,40.755529],"type":"Point"}
}