{
  "type": "Feature",
  "properties": {
    "iso:country":"US",
    "sg:address":"150 5th Ave",
    "sg:city":"New York",
    "sg:classifiers":[
        {
            "category":"Health Services",
            "subcategory":"Health Practitioner",
            "type":"Services"
        }
    ],
    "sg:phone":"+1 917 365 1428",
    "sg:postcode":"10011",
    "sg:province":"NY",
    "wof:name":"Living Creature",
    "wof:placetype":"venue"
},
  "geometry": {"coordinates":[-73.99137399999999,40.739087],"type":"Point"}
}