{
  "type": "Feature",
  "properties": {
    "iso:country":"US",
    "sg:address":"1609 Main St",
    "sg:city":"Buffalo",
    "sg:classifiers":[
        {
            "category":"Retail",
            "subcategory":"Auto Rental",
            "type":"Services"
        }
    ],
    "sg:phone":"+1 716 881 7368",
    "sg:postcode":"14209",
    "sg:province":"NY",
    "sg:tags":[
        "car"
    ],
    "wof:name":"Drive Tyme Rental Car Company",
    "wof:placetype":"venue"
},
  "geometry": {"coordinates":[-78.86274400000001,42.916757],"type":"Point"}
}