{
  "type": "Feature",
  "properties": {
    "addr:full":"215 N Syracuse Ave Massapequa NY 11758",
    "addr:housenumber":"215",
    "addr:postcode":"11758",
    "addr:street":"N Syracuse Ave",
    "iso:country":"US",
    "sg:address":"215 N Syracuse Ave",
    "sg:city":"Massapequa",
    "sg:classifiers":[
        {
            "category":"Travel",
            "subcategory":"Travel Agent",
            "type":"Entertainment"
        }
    ],
    "sg:phone":"+1 516 752 1134",
    "sg:postcode":"11758",
    "sg:province":"NY",
    "sg:tags":[
        "agency",
        "bureau"
    ],
    "wof:name":"Opal Travel",
    "wof:placetype":"venue"
},
  "geometry": {"coordinates":[-73.464223,40.709135],"type":"Point"}
}