{
  "type": "Feature",
  "properties": {
    "addr:full":"1 Vista Dr Great Neck NY 11021",
    "addr:housenumber":"1",
    "addr:postcode":"11021",
    "addr:street":"Vista Dr",
    "iso:country":"US",
    "sg:address":"1 Vista Dr",
    "sg:city":"Great Neck",
    "sg:classifiers":[
        {
            "category":"Banks & Credit Unions",
            "subcategory":"Investment Brokerage",
            "type":"Services"
        }
    ],
    "sg:phone":"+1 516 482 7770",
    "sg:postcode":"11021",
    "sg:province":"NY",
    "sg:tags":[
        "food",
        "exchange"
    ],
    "wof:name":"Quality First Trading Corp",
    "wof:placetype":"venue"
},
  "geometry": {"coordinates":[-73.74432,40.785581],"type":"Point"}
}