{
  "type": "Feature",
  "properties": {
    "addr:full":"360 W 31st St 11th Fl New York NY 10001",
    "addr:housenumber":"360",
    "addr:postcode":"10001",
    "addr:street":"W 31St St;Fl",
    "iso:country":"US",
    "sg:address":"360 W 31st St 11th Fl",
    "sg:city":"New York",
    "sg:classifiers":[
        {
            "category":"Parking",
            "type":"Transportation"
        }
    ],
    "sg:phone":"+1 800 836 6666",
    "sg:postcode":"10001",
    "sg:province":"NY",
    "sg:website":"nyc.centralparking.com/New-York....",
    "wof:name":"Central Parking System",
    "wof:placetype":"venue"
},
  "geometry": {"coordinates":[-73.99696400000001,40.751087],"type":"Point"}
}