{
  "type": "Feature",
  "properties": {
    "iso:country":"US",
    "sg:address":"145 Wright Ave",
    "sg:city":"Deer Park",
    "sg:classifiers":[
        {
            "category":"Local Transit",
            "type":"Transportation"
        }
    ],
    "sg:phone":"+1   ",
    "sg:postcode":"11729",
    "sg:province":"NY",
    "sg:tags":[
        "passenger"
    ],
    "wof:name":"Marc Bob Limousine Inc",
    "wof:placetype":"venue"
},
  "geometry": {"coordinates":[-73.32364699999999,40.771035],"type":"Point"}
}