{
  "type": "Feature",
  "properties": {
    "iso:country":"US",
    "sg:address":"289 Walden Ave",
    "sg:city":"Buffalo",
    "sg:classifiers":[
        {
            "category":"Professional",
            "subcategory":"Computer Services",
            "type":"Services"
        }
    ],
    "sg:phone":"+1 716 995 0705",
    "sg:postcode":"14211",
    "sg:province":"NY",
    "sg:tags":[
        "technical",
        "assistance",
        "support"
    ],
    "wof:name":"Enterprise Technologies",
    "wof:placetype":"venue"
},
  "geometry": {"coordinates":[-78.825287,42.903488],"type":"Point"}
}