{
  "type": "Feature",
  "properties": {
    "addr:full":"41 Dexter Rd Yonkers NY 10710",
    "addr:housenumber":"41",
    "addr:postcode":"10710",
    "addr:street":"Dexter Rd",
    "iso:country":"US",
    "sg:address":"41 Dexter Rd",
    "sg:city":"Yonkers",
    "sg:classifiers":[
        {
            "category":"Professional",
            "type":"Services"
        }
    ],
    "sg:phone":"+1   ",
    "sg:postcode":"10710",
    "sg:province":"NY",
    "wof:name":"Mastandrea Snacks Inc",
    "wof:placetype":"venue"
},
  "geometry": {"coordinates":[-73.845173,40.964357],"type":"Point"}
}