{
  "type": "Feature",
  "properties": {
    "iso:country":"US",
    "sg:address":"409 N Peterboro St",
    "sg:city":"Canastota",
    "sg:classifiers":[
        {
            "category":"Restaurant",
            "type":"Food & Drink"
        }
    ],
    "sg:phone":"+1   ",
    "sg:postcode":"13032",
    "sg:province":"NY",
    "sg:tags":[
        "eating"
    ],
    "wof:name":"Grazianos Cafe Mia",
    "wof:placetype":"venue"
},
  "geometry": {"coordinates":[-75.751409,43.091556],"type":"Point"}
}