{
  "type": "Feature",
  "properties": {
    "iso:country":"US",
    "sg:address":"919 38th Avenue",
    "sg:city":"Long Island City",
    "sg:classifiers":[
        {
            "category":"Building & Trades",
            "subcategory":"Plumbing",
            "type":"Services"
        }
    ],
    "sg:phone":"+1 718 392 0044",
    "sg:postcode":"11101",
    "sg:province":"NY",
    "wof:name":"Appollo Plumbing and Heating",
    "wof:placetype":"venue"
},
  "geometry": {"coordinates":[-73.942654,40.758874],"type":"Point"}
}