{
  "type": "Feature",
  "properties": {
    "iso:country":"US",
    "sg:address":"4902 13th Ave",
    "sg:city":"Brooklyn",
    "sg:classifiers":[
        {
            "category":"Shopping",
            "subcategory":"Shoes",
            "type":"Retail Goods"
        }
    ],
    "sg:phone":"+1   ",
    "sg:postcode":"11219",
    "sg:province":"NY",
    "wof:name":"Italian Shoes",
    "wof:placetype":"venue"
},
  "geometry": {"coordinates":[-73.99275,40.634525],"type":"Point"}
}