{
  "type": "Feature",
  "properties": {
    "addr:full":"135 Windmill Ln Southampton NY 11968",
    "addr:housenumber":"135",
    "addr:postcode":"11968",
    "addr:street":"Windmill Ln",
    "iso:country":"US",
    "sg:address":"135 Windmill Ln",
    "sg:city":"Southampton",
    "sg:classifiers":[
        {
            "category":"Manufacturing",
            "subcategory":"Printing",
            "type":"Manufacturing & Wholesale Goods"
        }
    ],
    "sg:phone":"+1 631 283 4100",
    "sg:postcode":"11968",
    "sg:province":"NY",
    "sg:tags":[
        "newspaper"
    ],
    "sg:website":"www.southamptonpress.com",
    "wof:name":"Southampton Press-Eastern Edtn",
    "wof:placetype":"venue"
},
  "geometry": {"coordinates":[-72.392797,40.886479],"type":"Point"}
}