{
  "type": "Feature",
  "properties": {
    "addr:full":"178 Fulton St Farmingdale NY 11735",
    "addr:housenumber":"178",
    "addr:postcode":"11735",
    "addr:street":"Fulton St",
    "iso:country":"US",
    "sg:address":"178 Fulton St",
    "sg:city":"Farmingdale",
    "sg:classifiers":[
        {
            "category":"Building & Trades",
            "subcategory":"Landscaping Services",
            "type":"Services"
        }
    ],
    "sg:phone":"+1 516 756 7228",
    "sg:postcode":"11735",
    "sg:province":"NY",
    "sg:tags":[
        "tree"
    ],
    "wof:name":"Franks Tree Service",
    "wof:placetype":"venue"
},
  "geometry": {"coordinates":[-73.456081,40.731138],"type":"Point"}
}