{
  "type": "Feature",
  "properties": {
    "addr:full":"2201 Kensington Ave Buffalo NY 14226",
    "addr:housenumber":"2201",
    "addr:postcode":"14226",
    "addr:street":"Kensington Ave",
    "iso:country":"US",
    "sg:address":"2201 Kensington Ave",
    "sg:city":"Buffalo",
    "sg:classifiers":[
        {
            "category":"Insurance",
            "subcategory":"Insurance Agent",
            "type":"Services"
        }
    ],
    "sg:phone":"+1 716 332 0121",
    "sg:postcode":"14226",
    "sg:province":"NY",
    "wof:name":"Fairl Agency",
    "wof:placetype":"venue"
},
  "geometry": {"coordinates":[-78.77806,42.952665],"type":"Point"}
}