{
  "type": "Feature",
  "properties": {
    "iso:country":"US",
    "sg:address":"22 Wightman Ave",
    "sg:city":"Hornell",
    "sg:classifiers":[
        {
            "category":"Retail",
            "subcategory":"Veterinary Services",
            "type":"Services"
        }
    ],
    "sg:phone":"+1 607 324 1092",
    "sg:postcode":"14843",
    "sg:province":"NY",
    "wof:name":"Hornell Animal Hospital",
    "wof:placetype":"venue"
},
  "geometry": {"coordinates":[-77.659109,42.343417],"type":"Point"}
}