{
  "type": "Feature",
  "properties": {
    "addr:full":"15 Salem Ln South Salem NY 10590",
    "addr:housenumber":"15",
    "addr:postcode":"10590",
    "addr:street":"Salem Ln",
    "iso:country":"US",
    "sg:address":"15 Salem Ln",
    "sg:city":"South Salem",
    "sg:classifiers":[
        {
            "category":"Health Services",
            "subcategory":"Nursing And Care Facility",
            "type":"Services"
        }
    ],
    "sg:phone":"+1 914 763 4630",
    "sg:postcode":"10590",
    "sg:province":"NY",
    "sg:tags":[
        "home",
        "convalescent"
    ],
    "wof:name":"Waccabuc River Rest Home Inc",
    "wof:placetype":"venue"
},
  "geometry": {"coordinates":[-73.54938900000001,41.277868],"type":"Point"}
}