{
  "type": "Feature",
  "properties": {
    "iso:country":"US",
    "sg:address":"395 John St",
    "sg:city":"Rochester",
    "sg:classifiers":[
        {
            "category":"Social Services",
            "subcategory":"Child Care",
            "type":"Services"
        }
    ],
    "sg:phone":"+1 585 292 4880",
    "sg:postcode":"14623",
    "sg:province":"NY",
    "sg:website":"www.childrenscenter.net",
    "wof:name":"Care-A-Lot Child Care Inc",
    "wof:placetype":"venue"
},
  "geometry": {"coordinates":[-77.66023199999999,43.080951],"type":"Point"}
}