{
  "type": "Feature",
  "properties": {
    "addr:full":"309 College Ave Ithaca NY 14850",
    "addr:housenumber":"309",
    "addr:postcode":"14850",
    "addr:street":"College Ave",
    "iso:country":"US",
    "sg:address":"309 College Ave",
    "sg:city":"Ithaca",
    "sg:classifiers":[
        {
            "category":"Government",
            "subcategory":"Fire Station",
            "type":"Public Place"
        }
    ],
    "sg:phone":"+1 607 272 1631",
    "sg:postcode":"14850",
    "sg:province":"NY",
    "sg:tags":[
        "protection"
    ],
    "wof:name":"Ithaca Fire Dept Station 9",
    "wof:placetype":"venue"
},
  "geometry": {"coordinates":[-76.485148,42.441101],"type":"Point"}
}