{
  "type": "Feature",
  "properties": {
    "iso:country":"US",
    "sg:address":"68 Willoughby St",
    "sg:city":"Brooklyn",
    "sg:classifiers":[
        {
            "category":"Professional",
            "subcategory":"Detective & Security Services",
            "type":"Services"
        }
    ],
    "sg:phone":"+1   ",
    "sg:postcode":"11201",
    "sg:province":"NY",
    "sg:tags":[
        "car"
    ],
    "wof:name":"Joseph Reed",
    "wof:placetype":"venue"
},
  "geometry": {"coordinates":[-73.985449,40.692091],"type":"Point"}
}