{
  "type": "Feature",
  "properties": {
    "iso:country":"US",
    "sg:address":"500 Westcott St",
    "sg:city":"Syracuse",
    "sg:classifiers":[
        {
            "category":"Real Estate",
            "subcategory":"Real Estate Agent",
            "type":"Services"
        },
        {
            "category":"Real Estate",
            "subcategory":"Real Estate Operator",
            "type":"Services"
        }
    ],
    "sg:phone":"+1 315 422 0709",
    "sg:postcode":"13210",
    "sg:province":"NY",
    "sg:tags":[
        "manager",
        "apartment"
    ],
    "sg:website":"www.universityhill.com",
    "wof:name":"University Hill Realty LTD",
    "wof:placetype":"venue"
},
  "geometry": {"coordinates":[-76.119344,43.041501],"type":"Point"}
}