{
  "type": "Feature",
  "properties": {
    "iso:country":"US",
    "sg:address":"47 Boundary Ave",
    "sg:city":"Farmingdale",
    "sg:classifiers":[
        {
            "category":"Food & Beverages",
            "subcategory":"Bakery",
            "type":"Retail Goods"
        }
    ],
    "sg:phone":"+1 516 694 1694",
    "sg:postcode":"11735",
    "sg:province":"NY",
    "sg:tags":[
        "baker"
    ],
    "wof:name":"My Little Cupcake LTD",
    "wof:placetype":"venue"
},
  "geometry": {"coordinates":[-73.46127799999999,40.717348],"type":"Point"}
}