{
  "type": "Feature",
  "properties": {
    "iso:country":"US",
    "sg:address":"311 Lemoyne Ave",
    "sg:city":"Syracuse",
    "sg:classifiers":[
        {
            "category":"Building & Trades",
            "subcategory":"Construction",
            "type":"Services"
        }
    ],
    "sg:phone":"+1 315 863 3547",
    "sg:postcode":"13208",
    "sg:province":"NY",
    "sg:tags":[
        "floor",
        "laying",
        "contractor"
    ],
    "wof:name":"All American Crpt & Flrg Outl",
    "wof:placetype":"venue"
},
  "geometry": {"coordinates":[-76.163304,43.069864],"type":"Point"}
}