{
  "type": "Feature",
  "properties": {
    "addr:full":"1971 Lakeland Ave Ronkonkoma NY 11779",
    "addr:housenumber":"1971",
    "addr:postcode":"11779",
    "addr:street":"Lakeland Ave",
    "iso:country":"US",
    "sg:address":"1971 Lakeland Ave",
    "sg:city":"Ronkonkoma",
    "sg:classifiers":[
        {
            "category":"Retail",
            "subcategory":"Auto Rental",
            "type":"Services"
        }
    ],
    "sg:phone":"+1 631 580 1019",
    "sg:postcode":"11779",
    "sg:province":"NY",
    "sg:tags":[
        "renting",
        "truck",
        "leasing"
    ],
    "wof:name":"Budget Truck Rental",
    "wof:placetype":"venue"
},
  "geometry": {"coordinates":[-73.121094,40.796094],"type":"Point"}
}