{
  "type": "Feature",
  "properties": {
    "addr:full":"858 W End Avenue New York NY 10025",
    "addr:housenumber":"858",
    "addr:postcode":"10025",
    "addr:street":"W End Avenue",
    "iso:country":"US",
    "sg:address":"858 W End Avenue",
    "sg:city":"New York",
    "sg:classifiers":[
        {
            "category":"Education",
            "subcategory":"School",
            "type":"Public Place"
        }
    ],
    "sg:phone":"+1 212 749 1800",
    "sg:postcode":"10025",
    "sg:province":"NY",
    "wof:name":"Restore-Restoration Training Program",
    "wof:placetype":"venue"
},
  "geometry": {"coordinates":[-73.970491,40.798966],"type":"Point"}
}