{
  "type": "Feature",
  "properties": {
    "iso:country":"US",
    "sg:address":"75 Brookside Ave",
    "sg:city":"Chester",
    "sg:classifiers":[
        {
            "category":"Communications",
            "type":"Services"
        }
    ],
    "sg:phone":"+1 845 469 5275",
    "sg:postcode":"10918",
    "sg:province":"NY",
    "wof:name":"Verizon",
    "wof:placetype":"venue"
},
  "geometry": {"coordinates":[-74.28273799999999,41.356052],"type":"Point"}
}