{
  "type": "Feature",
  "properties": {
    "addr:full":"821 Washington Ave Dunkirk NY 14048",
    "addr:housenumber":"821",
    "addr:postcode":"14048",
    "addr:street":"Washington Ave",
    "iso:country":"US",
    "sg:address":"821 Washington Ave",
    "sg:city":"Dunkirk",
    "sg:classifiers":[
        {
            "category":"Shopping",
            "subcategory":"Gifts & Souvenirs",
            "type":"Retail Goods"
        }
    ],
    "sg:phone":"+1   ",
    "sg:postcode":"14048",
    "sg:province":"NY",
    "wof:name":"Top Line Sports",
    "wof:placetype":"venue"
},
  "geometry": {"coordinates":[-79.33162299999999,42.472918],"type":"Point"}
}