{
  "type": "Feature",
  "properties": {
    "addr:full":"2155 Grand Ave Bronx NY 10453",
    "addr:housenumber":"2155",
    "addr:postcode":"10453",
    "addr:street":"Grand Ave",
    "iso:country":"US",
    "sg:address":"2155 Grand Ave",
    "sg:city":"Bronx",
    "sg:classifiers":[
        {
            "category":"Social Services",
            "subcategory":"Child Care",
            "type":"Services"
        }
    ],
    "sg:phone":"+1 718 733 7200",
    "sg:postcode":"10453",
    "sg:province":"NY",
    "sg:tags":[
        "day"
    ],
    "wof:name":"Arlene's Day Care",
    "wof:placetype":"venue"
},
  "geometry": {"coordinates":[-73.907315,40.856467],"type":"Point"}
}