{
  "type": "Feature",
  "properties": {
    "addr:full":"1245 Erie Blvd W Rome NY 13440",
    "addr:housenumber":"1245",
    "addr:postcode":"13440",
    "addr:street":"Erie Blvd W",
    "iso:country":"US",
    "sg:address":"1245 Erie Blvd W",
    "sg:city":"Rome",
    "sg:classifiers":[
        {
            "category":"Shopping",
            "subcategory":"Gifts & Souvenirs",
            "type":"Retail Goods"
        }
    ],
    "sg:phone":"+1   ",
    "sg:postcode":"13440",
    "sg:province":"NY",
    "sg:tags":[
        "h",
        "sewing"
    ],
    "wof:name":"Carols Crafts",
    "wof:placetype":"venue"
},
  "geometry": {"coordinates":[-75.48509,43.223928],"type":"Point"}
}