{
  "type": "Feature",
  "properties": {
    "iso:country":"US",
    "sg:address":"1667 Flatbush Ave",
    "sg:city":"Brooklyn",
    "sg:classifiers":[
        {
            "category":"Retail",
            "subcategory":"Laundry & Dry Cleaning",
            "type":"Services"
        }
    ],
    "sg:phone":"+1 718 253 0315",
    "sg:postcode":"11210",
    "sg:province":"NY",
    "sg:tags":[
        "cleaners"
    ],
    "wof:name":"Jung Cleaners",
    "wof:placetype":"venue"
},
  "geometry": {"coordinates":[-73.94415499999999,40.629508],"type":"Point"}
}