{
  "type": "Feature",
  "properties": {
    "iso:country":"US",
    "sg:address":"32 Bengal Ter",
    "sg:city":"Rochester",
    "sg:classifiers":[
        {
            "category":"Professional",
            "subcategory":"Advertising",
            "type":"Services"
        }
    ],
    "sg:phone":"+1 585 473 3792",
    "sg:postcode":"14610",
    "sg:province":"NY",
    "sg:tags":[
        "counselor"
    ],
    "sg:website":"www.minetor.com",
    "wof:name":"Minetor & Co",
    "wof:placetype":"venue"
},
  "geometry": {"coordinates":[-77.561931,43.142627],"type":"Point"}
}