{
  "type": "Feature",
  "properties": {
    "iso:country":"US",
    "sg:address":"1650 Military Rd",
    "sg:city":"Niagara Falls",
    "sg:classifiers":[
        {
            "category":"Shopping",
            "subcategory":"Luggage & Leather Goods",
            "type":"Retail Goods"
        }
    ],
    "sg:phone":"+1 716 297 3810",
    "sg:postcode":"14304",
    "sg:province":"NY",
    "sg:website":"www.samsonite.com",
    "wof:name":"Samsonite",
    "wof:placetype":"venue"
},
  "geometry": {"coordinates":[-78.97118500000001,43.093458],"type":"Point"}
}