{
  "type": "Feature",
  "properties": {
    "addr:full":"15017 Cross Island Pkwy Whitestone NY 11357",
    "addr:housenumber":"15017",
    "addr:postcode":"11357",
    "addr:street":"Cross Island Pkwy",
    "iso:country":"US",
    "sg:address":"15017 Cross Island Pkwy",
    "sg:city":"Whitestone",
    "sg:classifiers":[
        {
            "category":"Retail",
            "subcategory":"Auto Repair",
            "type":"Services"
        }
    ],
    "sg:phone":"+1 718 357 2666",
    "sg:postcode":"11357",
    "sg:province":"NY",
    "wof:name":"Power Auto Sports",
    "wof:placetype":"venue"
},
  "geometry": {"coordinates":[-73.81238,40.787553],"type":"Point"}
}