{
  "type": "Feature",
  "properties": {
    "iso:country":"US",
    "sg:address":"600 Franklin St",
    "sg:city":"Schenectady",
    "sg:classifiers":[
        {
            "category":"Health Services",
            "subcategory":"Doctor",
            "type":"Services"
        }
    ],
    "sg:phone":"+1 518 374 6343",
    "sg:postcode":"12305",
    "sg:province":"NY",
    "sg:tags":[
        "dental",
        "surgeon"
    ],
    "wof:name":"Michael S Freedus DDS PC",
    "wof:placetype":"venue"
},
  "geometry": {"coordinates":[-73.93592599999999,42.811654],"type":"Point"}
}