{
  "type": "Feature",
  "properties": {
    "addr:full":"2641 28th Street Astoria NY 11102",
    "addr:housenumber":"2641",
    "addr:postcode":"11102",
    "addr:street":"28Th Street",
    "iso:country":"US",
    "sg:address":"2641 28th Street",
    "sg:city":"Astoria",
    "sg:classifiers":[
        {
            "category":"Education",
            "subcategory":"School",
            "type":"Public Place"
        }
    ],
    "sg:phone":"+1 718 937 1463",
    "sg:postcode":"11102",
    "sg:province":"NY",
    "sg:tags":[
        "high",
        "middle",
        "elementary"
    ],
    "wof:name":"New York City Community School District 30 Region 4",
    "wof:placetype":"venue"
},
  "geometry": {"coordinates":[-73.92170299999999,40.76985],"type":"Point"}
}