{
  "type": "Feature",
  "properties": {
    "addr:full":"42 Genesee St Greene NY 13778",
    "addr:housenumber":"42",
    "addr:postcode":"13778",
    "addr:street":"Genesee St",
    "iso:country":"US",
    "sg:address":"42 Genesee St",
    "sg:city":"Greene",
    "sg:classifiers":[
        {
            "category":"Shopping",
            "subcategory":"Gifts & Souvenirs",
            "type":"Retail Goods"
        }
    ],
    "sg:phone":"+1   ",
    "sg:postcode":"13778",
    "sg:province":"NY",
    "wof:name":"Fireworks Hot Glass Gallery",
    "wof:placetype":"venue"
},
  "geometry": {"coordinates":[-75.77045099999999,42.329815],"type":"Point"}
}