{
  "type": "Feature",
  "properties": {
    "addr:full":"244 Market Ln Clinton Corners NY 12514",
    "addr:housenumber":"244",
    "addr:postcode":"12514",
    "addr:street":"Market Ln",
    "iso:country":"US",
    "sg:address":"244 Market Ln",
    "sg:city":"Clinton Corners",
    "sg:classifiers":[
        {
            "category":"Professional",
            "subcategory":"Business Services",
            "type":"Services"
        }
    ],
    "sg:phone":"+1 845 266 4210",
    "sg:postcode":"12514",
    "sg:province":"NY",
    "sg:tags":[
        "organizing"
    ],
    "wof:name":"Giuli Cordara Assoc LLC",
    "wof:placetype":"venue"
},
  "geometry": {"coordinates":[-73.744006,41.872428],"type":"Point"}
}