{
  "type": "Feature",
  "properties": {
    "iso:country":"US",
    "sg:address":"1112 Park Ave",
    "sg:city":"New York",
    "sg:classifiers":[
        {
            "category":"Health Services",
            "subcategory":"Doctor",
            "type":"Services"
        }
    ],
    "sg:phone":"+1 212 876 2641",
    "sg:postcode":"10128",
    "sg:province":"NY",
    "sg:tags":[
        "medical"
    ],
    "wof:name":"Jonathan N Lazare",
    "wof:placetype":"venue"
},
  "geometry": {"coordinates":[-73.955679,40.782271],"type":"Point"}
}