{
  "type": "Feature",
  "properties": {
    "iso:country":"US",
    "sg:address":"57 Cindy Dr",
    "sg:city":"West Babylon",
    "sg:classifiers":[
        {
            "category":"Manufacturing",
            "subcategory":"Metals",
            "type":"Manufacturing & Wholesale Goods"
        }
    ],
    "sg:phone":"+1   ",
    "sg:postcode":"11704",
    "sg:province":"NY",
    "sg:tags":[
        "production",
        "sheet",
        "precision"
    ],
    "wof:name":"R-G Kluge Co Ltd",
    "wof:placetype":"venue"
},
  "geometry": {"coordinates":[-73.357389,40.714495],"type":"Point"}
}