{
  "type": "Feature",
  "properties": {
    "addr:full":"81 Copperflagg Ln Staten Island NY 10304",
    "addr:housenumber":"81",
    "addr:postcode":"10304",
    "addr:street":"Copperflagg Ln",
    "iso:country":"US",
    "sg:address":"81 Copperflagg Ln",
    "sg:city":"Staten Island",
    "sg:classifiers":[
        {
            "category":"Real Estate",
            "subcategory":"Real Estate Agent",
            "type":"Services"
        }
    ],
    "sg:phone":"+1 718 980 9555",
    "sg:postcode":"10304",
    "sg:province":"NY",
    "wof:name":"3555 Victory Blvd Realty Assoc",
    "wof:placetype":"venue"
},
  "geometry": {"coordinates":[-74.108442,40.587418],"type":"Point"}
}