{
  "type": "Feature",
  "properties": {
    "iso:country":"US",
    "sg:address":"8983 Covert Cottages Rd",
    "sg:city":"Trumansburg",
    "sg:classifiers":[
        {
            "category":"Professional",
            "type":"Services"
        }
    ],
    "sg:phone":"+1 607 387 4857",
    "sg:postcode":"14886",
    "sg:province":"NY",
    "sg:tags":[
        "establishment"
    ],
    "wof:name":"Stuart Lovejoy Grinnell",
    "wof:placetype":"venue"
},
  "geometry": {"coordinates":[-76.661783,42.587728],"type":"Point"}
}