{
  "type": "Feature",
  "properties": {
    "addr:full":"201 W 70th St New York NY 10023",
    "addr:housenumber":"201",
    "addr:postcode":"10023",
    "addr:street":"W 70Th St",
    "iso:country":"US",
    "sg:address":"201 W 70th St",
    "sg:city":"New York",
    "sg:classifiers":[
        {
            "category":"Building & Trades",
            "subcategory":"Pest Control",
            "type":"Services"
        }
    ],
    "sg:phone":"+1 646 434 2037",
    "sg:postcode":"10023",
    "sg:province":"NY",
    "wof:name":"Action Pest Control Of New York",
    "wof:placetype":"venue"
},
  "geometry": {"coordinates":[-73.98257,40.777312],"type":"Point"}
}