{
  "type": "Feature",
  "properties": {
    "iso:country":"US",
    "sg:address":"239 W 39th Street",
    "sg:city":"New York",
    "sg:classifiers":[
        {
            "category":"Personal",
            "type":"Services"
        }
    ],
    "sg:phone":"+1 212 840 1871",
    "sg:postcode":"10018",
    "sg:province":"NY",
    "sg:tags":[
        "sewing",
        "alteration"
    ],
    "sg:website":"www.tailornewyork.com",
    "wof:name":"Tailor New York",
    "wof:placetype":"venue"
},
  "geometry": {"coordinates":[-73.988507,40.754097],"type":"Point"}
}