{
  "type": "Feature",
  "properties": {
    "addr:full":"2037 Webster Avenue Bronx NY 10457",
    "addr:housenumber":"2037",
    "addr:postcode":"10457",
    "addr:street":"Webster Avenue",
    "iso:country":"US",
    "sg:address":"2037 Webster Avenue",
    "sg:city":"Bronx",
    "sg:classifiers":[
        {
            "category":"Personal",
            "subcategory":"Barber",
            "type":"Services"
        }
    ],
    "sg:phone":"+1 718 562 3756",
    "sg:postcode":"10457",
    "sg:province":"NY",
    "wof:name":"Smity's Barber Shop",
    "wof:placetype":"venue"
},
  "geometry": {"coordinates":[-73.899021,40.850902],"type":"Point"}
}