{
  "type": "Feature",
  "properties": {
    "iso:country":"US",
    "sg:address":"300 W 135th St Frnt 1",
    "sg:city":"New York",
    "sg:classifiers":[
        {
            "category":"Banks & Credit Unions",
            "subcategory":"Bank",
            "type":"Services"
        }
    ],
    "sg:phone":"+1 212 234 5194",
    "sg:postcode":"10030",
    "sg:province":"NY",
    "wof:name":"Chase",
    "wof:placetype":"venue"
},
  "geometry": {"coordinates":[-73.946597,40.816382],"type":"Point"}
}