{
  "type": "Feature",
  "properties": {
    "iso:country":"US",
    "sg:address":"763 Allerton Avenue",
    "sg:city":"Bronx",
    "sg:classifiers":[
        {
            "category":"Health Services",
            "subcategory":"Optometrist",
            "type":"Services"
        }
    ],
    "sg:phone":"+1 718 644 0014",
    "sg:postcode":"10467",
    "sg:province":"NY",
    "wof:name":"Vision Phonecard Dist",
    "wof:placetype":"venue"
},
  "geometry": {"coordinates":[-73.86493299999999,40.865589],"type":"Point"}
}