{
  "type": "Feature",
  "properties": {
    "addr:full":"133 Gibson St Canandaigua NY 14424",
    "addr:housenumber":"133",
    "addr:postcode":"14424",
    "addr:street":"Gibson St",
    "iso:country":"US",
    "sg:address":"133 Gibson St",
    "sg:city":"Canandaigua",
    "sg:classifiers":[
        {
            "category":"Sports & Exercise",
            "subcategory":"Gym",
            "type":"Entertainment"
        }
    ],
    "sg:phone":"+1   ",
    "sg:postcode":"14424",
    "sg:province":"NY",
    "sg:tags":[
        "fitness",
        "physical",
        "facility"
    ],
    "wof:name":"Functional Fitness & Training",
    "wof:placetype":"venue"
},
  "geometry": {"coordinates":[-77.277805,42.892425],"type":"Point"}
}