{
  "type": "Feature",
  "properties": {
    "addr:full":"1225 Lyell Ave Rochester NY 14606",
    "addr:housenumber":"1225",
    "addr:postcode":"14606",
    "addr:street":"Lyell Ave",
    "iso:country":"US",
    "sg:address":"1225 Lyell Ave",
    "sg:city":"Rochester",
    "sg:classifiers":[
        {
            "category":"Taxi",
            "type":"Transportation"
        },
        {
            "category":"Airport",
            "type":"Transportation"
        }
    ],
    "sg:phone":"+1 585 351 6783",
    "sg:postcode":"14606",
    "sg:province":"NY",
    "sg:tags":[
        "delivery"
    ],
    "sg:website":"http://www.midtowntaxicab.com",
    "wof:name":"Midtown Cab",
    "wof:placetype":"venue"
},
  "geometry": {"coordinates":[-77.65760899999999,43.164644],"type":"Point"}
}