{
  "type": "Feature",
  "properties": {
    "iso:country":"US",
    "name:eng_x_preferred":[
        "57 St - 7 Av"
    ],
    "wof:name":"57 St - 7 Av",
    "wof:placetype":"venue"
},
  "geometry": {"coordinates":[-73.98065800000001,40.764664],"type":"Point"}
}