{
  "type": "Feature",
  "properties": {
    "iso:country":"US",
    "sg:address":"220 E 42nd St",
    "sg:city":"New York",
    "sg:classifiers":[
        {
            "category":"Manufacturing",
            "subcategory":"Printing",
            "type":"Manufacturing & Wholesale Goods"
        }
    ],
    "sg:phone":"+1 212 254 0890",
    "sg:postcode":"10017",
    "sg:province":"NY",
    "sg:tags":[
        "publisher"
    ],
    "wof:name":"Crain News Svc",
    "wof:placetype":"venue"
},
  "geometry": {"coordinates":[-73.972587,40.74995],"type":"Point"}
}