{
  "type": "Feature",
  "properties": {
    "addr:full":"297 Grand St Brooklyn NY 11211",
    "addr:housenumber":"297",
    "addr:postcode":"11211",
    "addr:street":"Grand St",
    "iso:country":"US",
    "sg:address":"297 Grand St",
    "sg:city":"Brooklyn",
    "sg:classifiers":[
        {
            "category":"Personal",
            "subcategory":"Massage",
            "type":"Services"
        },
        {
            "category":"Personal",
            "subcategory":"Day Spa",
            "type":"Services"
        }
    ],
    "sg:phone":"+1 718 302 3898",
    "sg:postcode":"11211",
    "sg:province":"NY",
    "sg:website":"www.grandrelaxcenter.com",
    "wof:name":"Grand Relax Day Spa",
    "wof:placetype":"venue"
},
  "geometry": {"coordinates":[-73.95717500000001,40.713124],"type":"Point"}
}