{
  "type": "Feature",
  "properties": {
    "addr:full":"8 Park Pl Canton NY 13617",
    "addr:housenumber":"8",
    "addr:postcode":"13617",
    "addr:street":"Park Pl",
    "iso:country":"US",
    "sg:address":"8 Park Pl",
    "sg:city":"Canton",
    "sg:classifiers":[
        {
            "category":"Education",
            "subcategory":"Library",
            "type":"Public Place"
        }
    ],
    "sg:phone":"+1 315 386 3712",
    "sg:postcode":"13617",
    "sg:province":"NY",
    "sg:website":"www.cantonfreelibrary.org",
    "wof:name":"Canton Free Library",
    "wof:placetype":"venue"
},
  "geometry": {"coordinates":[-75.167063,44.595042],"type":"Point"}
}