{
  "type": "Feature",
  "properties": {
    "addr:full":"1305 Franklin Ave Bronx NY 10456",
    "addr:housenumber":"1305",
    "addr:postcode":"10456",
    "addr:street":"Franklin Ave",
    "iso:country":"US",
    "sg:address":"1305 Franklin Ave",
    "sg:city":"Bronx",
    "sg:classifiers":[
        {
            "category":"Banks & Credit Unions",
            "subcategory":"Bank",
            "type":"Services"
        }
    ],
    "sg:phone":"+1 516 873 9486",
    "sg:postcode":"10456",
    "sg:province":"NY",
    "wof:name":"Hemisphere National Bank",
    "wof:placetype":"venue"
},
  "geometry": {"coordinates":[-73.900758,40.833407],"type":"Point"}
}