{
  "type": "Feature",
  "properties": {
    "iso:country":"US",
    "sg:address":"595 Cedar St",
    "sg:city":"Uniondale",
    "sg:classifiers":[
        {
            "category":"Professional",
            "subcategory":"Management & Consulting",
            "type":"Services"
        }
    ],
    "sg:phone":"+1 516 505 7601",
    "sg:postcode":"11553",
    "sg:province":"NY",
    "sg:tags":[
        "business"
    ],
    "wof:name":"Las Americas Link Corp",
    "wof:placetype":"venue"
},
  "geometry": {"coordinates":[-73.59495,40.704754],"type":"Point"}
}