{
  "type": "Feature",
  "properties": {
    "iso:country":"US",
    "sg:address":"176 N Main St",
    "sg:city":"Florida",
    "sg:classifiers":[
        {
            "category":"Food & Beverages",
            "subcategory":"Groceries & Convenience Stores",
            "type":"Retail Goods"
        }
    ],
    "sg:phone":"+1 845 651 4411",
    "sg:postcode":"10921",
    "sg:province":"NY",
    "wof:name":"Shop-Rite",
    "wof:placetype":"venue"
},
  "geometry": {"coordinates":[-74.358695,41.337819],"type":"Point"}
}