{
  "type": "Feature",
  "properties": {
    "iso:country":"US",
    "sg:address":"3733 Richmond Ave",
    "sg:city":"Staten Island",
    "sg:classifiers":[
        {
            "category":"Professional",
            "subcategory":"Accounting & Tax Preparation",
            "type":"Services"
        }
    ],
    "sg:phone":"+1 718 948 2218",
    "sg:postcode":"10312",
    "sg:province":"NY",
    "sg:tags":[
        "accountant"
    ],
    "wof:name":"Loretta Aquino CPA",
    "wof:placetype":"venue"
},
  "geometry": {"coordinates":[-74.165708,40.545607],"type":"Point"}
}