{
  "type": "Feature",
  "properties": {
    "iso:country":"US",
    "sg:address":"2021 Western Ave",
    "sg:city":"Albany",
    "sg:classifiers":[
        {
            "category":"Professional",
            "subcategory":"Engineering",
            "type":"Services"
        }
    ],
    "sg:phone":"+1 518 452 0289",
    "sg:postcode":"12203",
    "sg:province":"NY",
    "sg:tags":[
        "engineer"
    ],
    "wof:name":"ICF Consulting",
    "wof:placetype":"venue"
},
  "geometry": {"coordinates":[-73.886331,42.697029],"type":"Point"}
}