{
  "type": "Feature",
  "properties": {
    "addr:full":"7007 Co Rd 10 Lisbon NY 13658",
    "addr:housenumber":"7007;10",
    "addr:postcode":"13658",
    "addr:street":"Co Rd",
    "iso:country":"US",
    "sg:address":"7007 Co Rd 10",
    "sg:city":"Lisbon",
    "sg:classifiers":[
        {
            "category":"Government",
            "subcategory":"Post Office",
            "type":"Public Place"
        }
    ],
    "sg:phone":"+1 315 393 0312",
    "sg:postcode":"13658",
    "sg:province":"NY",
    "wof:name":"US Post Office",
    "wof:placetype":"venue"
},
  "geometry": {"coordinates":[-75.320542,44.730686],"type":"Point"}
}