{
  "type": "Feature",
  "properties": {
    "iso:country":"US",
    "sg:address":"3 Northern Blvd",
    "sg:city":"Greenvale",
    "sg:classifiers":[
        {
            "category":"Restaurant",
            "type":"Food & Drink"
        }
    ],
    "sg:phone":"+1 516 621 6616",
    "sg:postcode":"11548",
    "sg:province":"NY",
    "sg:website":"www.hunantasteli.com",
    "wof:name":"Hunan Taste Restrnt",
    "wof:placetype":"venue"
},
  "geometry": {"coordinates":[-73.628197,40.8097],"type":"Point"}
}