{
  "type": "Feature",
  "properties": {
    "addr:full":"88 Jefferson St Brooklyn NY 11206",
    "addr:housenumber":"88",
    "addr:postcode":"11206",
    "addr:street":"Jefferson St",
    "iso:country":"US",
    "sg:address":"88 Jefferson St",
    "sg:city":"Brooklyn",
    "sg:classifiers":[
        {
            "category":"Building & Trades",
            "subcategory":"Plumbing",
            "type":"Services"
        }
    ],
    "sg:phone":"+1 718 574 7300",
    "sg:postcode":"11206",
    "sg:province":"NY",
    "sg:tags":[
        "contractor"
    ],
    "wof:name":"New York Carrier Trading Inc",
    "wof:placetype":"venue"
},
  "geometry": {"coordinates":[-73.93273000000001,40.69862],"type":"Point"}
}