{
  "type": "Feature",
  "properties": {
    "addr:full":"57 May Ave Westbury NY 11590",
    "addr:housenumber":"57",
    "addr:postcode":"11590",
    "addr:street":"May Ave",
    "iso:country":"US",
    "sg:address":"57 May Ave",
    "sg:city":"Westbury",
    "sg:classifiers":[
        {
            "category":"Shopping",
            "subcategory":"Gifts & Souvenirs",
            "type":"Retail Goods"
        }
    ],
    "sg:phone":"+1   ",
    "sg:postcode":"11590",
    "sg:province":"NY",
    "wof:name":"Party Interiors",
    "wof:placetype":"venue"
},
  "geometry": {"coordinates":[-73.59483299999999,40.759751],"type":"Point"}
}