{
  "type": "Feature",
  "properties": {
    "addr:full":"99 Pine St Albany NY 12207",
    "addr:housenumber":"99",
    "addr:postcode":"12207",
    "addr:street":"Pine St",
    "iso:country":"US",
    "sg:address":"99 Pine St",
    "sg:city":"Albany",
    "sg:classifiers":[
        {
            "category":"Professional",
            "subcategory":"Lawyer & Legal Services",
            "type":"Services"
        }
    ],
    "sg:phone":"+1 518 436 0786",
    "sg:postcode":"12207",
    "sg:province":"NY",
    "sg:tags":[
        "attorney"
    ],
    "sg:website":"www.fcwc-law.com",
    "wof:name":"Feather Stonhaugh Wileyclyne&C",
    "wof:placetype":"venue"
},
  "geometry": {"coordinates":[-73.75211899999999,42.651204],"type":"Point"}
}