{
  "type": "Feature",
  "properties": {
    "iso:country":"US",
    "sg:address":"7004 Sunset Ln",
    "sg:city":"Boston",
    "sg:classifiers":[
        {
            "category":"Building & Trades",
            "subcategory":"Cleaning & Sanitation",
            "type":"Services"
        }
    ],
    "sg:phone":"+1 716 941 6913",
    "sg:postcode":"14025",
    "sg:province":"NY",
    "sg:tags":[
        "maintenance"
    ],
    "wof:name":"Terjon Service Co",
    "wof:placetype":"venue"
},
  "geometry": {"coordinates":[-78.732989,42.626589],"type":"Point"}
}