{
  "type": "Feature",
  "properties": {
    "iso:country":"US",
    "sg:address":"115 Oak Ridge Rd",
    "sg:city":"Hopewell Junction",
    "sg:classifiers":[
        {
            "category":"Building & Trades",
            "subcategory":"Plumbing",
            "type":"Services"
        }
    ],
    "sg:phone":"+1 845 227 5852",
    "sg:postcode":"12533",
    "sg:province":"NY",
    "sg:tags":[
        "fire",
        "equipment",
        "safety",
        "system",
        "suppression"
    ],
    "wof:name":"Imperial Fire Systems",
    "wof:placetype":"venue"
},
  "geometry": {"coordinates":[-73.78193899999999,41.607926],"type":"Point"}
}