{
  "type": "Feature",
  "properties": {
    "addr:full":"132 Thompson St. New York NY 10012",
    "addr:housenumber":"132",
    "addr:postcode":"10012",
    "addr:street":"Thompson St.",
    "iso:country":"US",
    "sg:address":"132 Thompson St.",
    "sg:city":"New York",
    "sg:classifiers":[
        {
            "category":"Shopping",
            "subcategory":"Pets & Pet Supplies",
            "type":"Retail Goods"
        },
        {
            "category":"Retail",
            "subcategory":"Pet Boarding",
            "type":"Services"
        },
        {
            "category":"Retail",
            "subcategory":"Animal Services",
            "type":"Services"
        }
    ],
    "sg:phone":"+1 212 253 9250",
    "sg:postcode":"10012",
    "sg:province":"NY",
    "sg:tags":[
        "boarding/pet",
        "store",
        "sitting"
    ],
    "wof:name":"The Pet Bar",
    "wof:placetype":"venue"
},
  "geometry": {"coordinates":[-74.00132000000001,40.726448],"type":"Point"}
}