{
  "type": "Feature",
  "properties": {
    "iso:country":"US",
    "sg:address":"871 Lake St",
    "sg:city":"Angola",
    "sg:classifiers":[
        {
            "category":"Freight",
            "type":"Transportation"
        }
    ],
    "sg:phone":"+1   ",
    "sg:postcode":"14006",
    "sg:province":"NY",
    "sg:tags":[
        "operator",
        "local",
        "trucking"
    ],
    "wof:name":"Frank Monteleone Dump Truck",
    "wof:placetype":"venue"
},
  "geometry": {"coordinates":[-79.042232,42.638409],"type":"Point"}
}