{
  "type": "Feature",
  "properties": {
    "iso:country":"US",
    "sg:address":"845 Madison Ave",
    "sg:city":"Albany",
    "sg:classifiers":[
        {
            "category":"Building & Trades",
            "subcategory":"Equipment Rental",
            "type":"Services"
        }
    ],
    "sg:phone":"+1 518 435 9755",
    "sg:postcode":"12208",
    "sg:province":"NY",
    "sg:tags":[
        "leasing"
    ],
    "wof:name":"Madison Wireless",
    "wof:placetype":"venue"
},
  "geometry": {"coordinates":[-73.783795,42.661681],"type":"Point"}
}