{
  "type": "Feature",
  "properties": {
    "addr:full":"644 Greenwich St New York NY 10014",
    "addr:housenumber":"644",
    "addr:postcode":"10014",
    "addr:street":"Greenwich St",
    "iso:country":"US",
    "sg:address":"644 Greenwich St",
    "sg:city":"New York",
    "sg:classifiers":[
        {
            "category":"Retail",
            "subcategory":"Auto Repair",
            "type":"Services"
        }
    ],
    "sg:phone":"+1 212 937 1267",
    "sg:postcode":"10014",
    "sg:province":"NY",
    "sg:tags":[
        "wrecker"
    ],
    "wof:name":"Arkadi Towing & Recovery",
    "wof:placetype":"venue"
},
  "geometry": {"coordinates":[-74.007947,40.73148],"type":"Point"}
}