{
  "type": "Feature",
  "properties": {
    "iso:country":"US",
    "sg:address":"322 Victory Boulevard",
    "sg:city":"Staten Island",
    "sg:classifiers":[
        {
            "category":"Restaurant",
            "type":"Food & Drink"
        }
    ],
    "sg:phone":"+1 718 420 0796",
    "sg:postcode":"10301",
    "sg:province":"NY",
    "sg:website":"www.newasharestaurant.com",
    "wof:name":"New Shaan Restaurant",
    "wof:placetype":"venue"
},
  "geometry": {"coordinates":[-74.084367,40.635577],"type":"Point"}
}