{
  "type": "Feature",
  "properties": {
    "addr:full":"450 Oakdale Dr Rochester NY 14618",
    "addr:housenumber":"450",
    "addr:postcode":"14618",
    "addr:street":"Oakdale Dr",
    "iso:country":"US",
    "sg:address":"450 Oakdale Dr",
    "sg:city":"Rochester",
    "sg:classifiers":[
        {
            "category":"Professional",
            "type":"Services"
        }
    ],
    "sg:phone":"+1 585 756 8618",
    "sg:postcode":"14618",
    "sg:province":"NY",
    "sg:tags":[
        "establishment"
    ],
    "wof:name":"I P Protector",
    "wof:placetype":"venue"
},
  "geometry": {"coordinates":[-77.561289,43.136082],"type":"Point"}
}