{
  "type": "Feature",
  "properties": {
    "addr:full":"7359 Oswego Rd Liverpool NY 13090",
    "addr:housenumber":"7359",
    "addr:postcode":"13090",
    "addr:street":"Oswego Rd",
    "iso:country":"US",
    "sg:address":"7359 Oswego Rd",
    "sg:city":"Liverpool",
    "sg:classifiers":[
        {
            "category":"Home & Garden",
            "subcategory":"Hardware",
            "type":"Retail Goods"
        }
    ],
    "sg:phone":"+1 315 451 4352",
    "sg:postcode":"13090",
    "sg:province":"NY",
    "wof:name":"Sears Hardware Store",
    "wof:placetype":"venue"
},
  "geometry": {"coordinates":[-76.218896,43.128847],"type":"Point"}
}