{
  "type": "Feature",
  "properties": {
    "iso:country":"US",
    "sg:address":"623 New York Ave",
    "sg:city":"Huntington",
    "sg:classifiers":[
        {
            "category":"Manufacturing",
            "subcategory":"Electronics",
            "type":"Manufacturing & Wholesale Goods"
        }
    ],
    "sg:phone":"+1 631 351 1203",
    "sg:postcode":"11743",
    "sg:province":"NY",
    "sg:tags":[
        "equipment",
        "electronic",
        "supply"
    ],
    "sg:website":"www.jorway.com",
    "wof:name":"Jorway Corp",
    "wof:placetype":"venue"
},
  "geometry": {"coordinates":[-73.422786,40.863276],"type":"Point"}
}