{
  "type": "Feature",
  "properties": {
    "iso:country":"US",
    "sg:address":"1670 Longfellow Ave",
    "sg:city":"Bronx",
    "sg:classifiers":[
        {
            "category":"Local Transit",
            "type":"Transportation"
        }
    ],
    "sg:phone":"+1 718 617 1111",
    "sg:postcode":"10460",
    "sg:province":"NY",
    "sg:tags":[
        "car"
    ],
    "wof:name":"South Car Svc",
    "wof:placetype":"venue"
},
  "geometry": {"coordinates":[-73.884258,40.835978],"type":"Point"}
}