{
  "type": "Feature",
  "properties": {
    "addr:full":"1163 Forest Ave Staten Island NY 10310",
    "addr:housenumber":"1163",
    "addr:postcode":"10310",
    "addr:street":"Forest Ave",
    "iso:country":"US",
    "sg:address":"1163 Forest Ave",
    "sg:city":"Staten Island",
    "sg:classifiers":[
        {
            "category":"Health Services",
            "subcategory":"Chiropractor",
            "type":"Services"
        }
    ],
    "sg:phone":"+1 718 727 0055",
    "sg:postcode":"10310",
    "sg:province":"NY",
    "wof:name":"Julewicz Denny A",
    "wof:placetype":"venue"
},
  "geometry": {"coordinates":[-74.128748,40.626746],"type":"Point"}
}