{
  "type": "Feature",
  "properties": {
    "addr:full":"1250 Scottsville Rd Rochester NY 14624",
    "addr:housenumber":"1250",
    "addr:postcode":"14624",
    "addr:street":"Scottsville Rd",
    "iso:country":"US",
    "sg:address":"1250 Scottsville Rd",
    "sg:city":"Rochester",
    "sg:classifiers":[
        {
            "category":"Professional",
            "subcategory":"Business Services",
            "type":"Services"
        }
    ],
    "sg:phone":"+1 585 235 3580",
    "sg:postcode":"14624",
    "sg:province":"NY",
    "wof:name":"Kimmins Coffee Service Inc",
    "wof:placetype":"venue"
},
  "geometry": {"coordinates":[-77.65704599999999,43.118525],"type":"Point"}
}