{
  "type": "Feature",
  "properties": {
    "iso:country":"US",
    "sg:address":"147 E 86th St",
    "sg:city":"New York",
    "sg:classifiers":[
        {
            "category":"Personal",
            "subcategory":"Barber",
            "type":"Services"
        },
        {
            "category":"Retail",
            "subcategory":"Repair Shop",
            "type":"Services"
        },
        {
            "category":"Personal",
            "subcategory":"Shoe Repair & Shine",
            "type":"Services"
        }
    ],
    "sg:phone":"+1 212 348 4054",
    "sg:postcode":"10028",
    "sg:province":"NY",
    "sg:tags":[
        "watch"
    ],
    "wof:name":"Lexington Exclusive",
    "wof:placetype":"venue"
},
  "geometry": {"coordinates":[-73.955358,40.779424],"type":"Point"}
}