{
  "type": "Feature",
  "properties": {
    "iso:country":"US",
    "sg:address":"2700 Stillwell Ave",
    "sg:city":"Brooklyn",
    "sg:classifiers":[
        {
            "category":"Arts & Performance",
            "subcategory":"Theater",
            "type":"Entertainment"
        }
    ],
    "sg:phone":"+1 718 372 5427",
    "sg:postcode":"11224",
    "sg:province":"NY",
    "sg:tags":[
        "music",
        "agent"
    ],
    "wof:name":"Jus Flava Records",
    "wof:placetype":"venue"
},
  "geometry": {"coordinates":[-73.98214900000001,40.580117],"type":"Point"}
}