{
  "type": "Feature",
  "properties": {
    "addr:full":"1 Arden Ln New Paltz NY 12561",
    "addr:housenumber":"1",
    "addr:postcode":"12561",
    "addr:street":"Arden Ln",
    "iso:country":"US",
    "sg:address":"1 Arden Ln",
    "sg:city":"New Paltz",
    "sg:classifiers":[
        {
            "category":"Manufacturing",
            "subcategory":"Printing",
            "type":"Manufacturing & Wholesale Goods"
        }
    ],
    "sg:phone":"+1   ",
    "sg:postcode":"12561",
    "sg:province":"NY",
    "sg:tags":[
        "book"
    ],
    "wof:name":"Codhill Press",
    "wof:placetype":"venue"
},
  "geometry": {"coordinates":[-74.16525300000001,41.743837],"type":"Point"}
}