{
  "type": "Feature",
  "properties": {
    "iso:country":"US",
    "sg:address":"189 Winkler Dr",
    "sg:city":"Grand Island",
    "sg:classifiers":[
        {
            "category":"Wholesale",
            "subcategory":"Jewelry",
            "type":"Manufacturing & Wholesale Goods"
        }
    ],
    "sg:phone":"+1 716 775 1237",
    "sg:postcode":"14072",
    "sg:province":"NY",
    "sg:tags":[
        "stone"
    ],
    "wof:name":"Carrato Joeseph",
    "wof:placetype":"venue"
},
  "geometry": {"coordinates":[-78.935942,43.005451],"type":"Point"}
}