{
  "type": "Feature",
  "properties": {
    "iso:country":"US",
    "sg:address":"92 Orchard St",
    "sg:city":"New York",
    "sg:classifiers":[
        {
            "category":"Shopping",
            "subcategory":"Luggage & Leather Goods",
            "type":"Retail Goods"
        }
    ],
    "sg:phone":"+1   ",
    "sg:postcode":"10002",
    "sg:province":"NY",
    "wof:name":"Luggage Plus",
    "wof:placetype":"venue"
},
  "geometry": {"coordinates":[-73.98973700000001,40.718899],"type":"Point"}
}