{
  "type": "Feature",
  "properties": {
    "iso:country":"US",
    "sg:address":"1 Jericho Tpke",
    "sg:city":"Jericho",
    "sg:classifiers":[
        {
            "category":"Insurance",
            "subcategory":"Insurance Agent",
            "type":"Services"
        }
    ],
    "sg:phone":"+1 516 935 3700",
    "sg:postcode":"11753",
    "sg:province":"NY",
    "sg:tags":[
        "security"
    ],
    "wof:name":"St Paul Fire & Marine Insur",
    "wof:placetype":"venue"
},
  "geometry": {"coordinates":[-73.554305,40.782193],"type":"Point"}
}