{
  "type": "Feature",
  "properties": {
    "addr:full":"16424 Crossbay Blvd Howard Beach NY 11414",
    "addr:postcode":"16424;11414",
    "addr:street":"Crossbay Blvd",
    "iso:country":"US",
    "sg:address":"16424 Crossbay Blvd",
    "sg:city":"Howard Beach",
    "sg:classifiers":[
        {
            "category":"Retail",
            "subcategory":"Laundry & Dry Cleaning",
            "type":"Services"
        }
    ],
    "sg:phone":"+1 718 843 5357",
    "sg:postcode":"11414",
    "sg:province":"NY",
    "wof:name":"Michele Cleaners & Custom Tailoring",
    "wof:placetype":"venue"
},
  "geometry": {"coordinates":[-73.837997,40.650398],"type":"Point"}
}