{
  "type": "Feature",
  "properties": {
    "addr:full":"7189 Oswego Rd Liverpool NY 13090",
    "addr:housenumber":"7189",
    "addr:postcode":"13090",
    "addr:street":"Oswego Rd",
    "iso:country":"US",
    "sg:address":"7189 Oswego Rd",
    "sg:city":"Liverpool",
    "sg:classifiers":[
        {
            "category":"Food & Beverages",
            "subcategory":"Groceries & Convenience Stores",
            "type":"Retail Goods"
        }
    ],
    "sg:phone":"+1 315 457 0199",
    "sg:postcode":"13090",
    "sg:province":"NY",
    "wof:name":"Fastrac Markets LLC",
    "wof:placetype":"venue"
},
  "geometry": {"coordinates":[-76.214986,43.119667],"type":"Point"}
}