{
  "type": "Feature",
  "properties": {
    "addr:full":"6694 Co Rte 17 Redfield NY 13437",
    "addr:housenumber":"6694",
    "addr:postcode":"13437",
    "addr:street":"Co Rte 17",
    "iso:country":"US",
    "sg:address":"6694 Co Rte 17",
    "sg:city":"Redfield",
    "sg:classifiers":[
        {
            "category":"Professional",
            "subcategory":"Computer Services",
            "type":"Services"
        }
    ],
    "sg:phone":"+1 315 387 5995",
    "sg:postcode":"13437",
    "sg:province":"NY",
    "sg:tags":[
        "consultant",
        "designer"
    ],
    "wof:name":"Orange Computing",
    "wof:placetype":"venue"
},
  "geometry": {"coordinates":[-75.876441,43.633368],"type":"Point"}
}