{
  "type": "Feature",
  "properties": {
    "iso:country":"US",
    "sg:address":"4128 Main Street",
    "sg:city":"Flushing",
    "sg:classifiers":[
        {
            "category":"Shopping",
            "subcategory":"Pharmacy",
            "type":"Retail Goods"
        }
    ],
    "sg:phone":"+1 718 886 8968",
    "sg:postcode":"11355",
    "sg:province":"NY",
    "sg:tags":[
        "drugstore"
    ],
    "wof:name":"Primacare Pharmacy",
    "wof:placetype":"venue"
},
  "geometry": {"coordinates":[-73.82913000000001,40.757142],"type":"Point"}
}