{
  "type": "Feature",
  "properties": {
    "addr:full":"150 Broadway Ste 301 Menands NY 12204",
    "addr:housenumber":"150",
    "addr:postcode":"12204",
    "addr:street":"Broadway Ste 301",
    "iso:country":"US",
    "sg:address":"150 Broadway Ste 301",
    "sg:city":"Menands",
    "sg:classifiers":[
        {
            "category":"Science Facility",
            "type":"Public Place"
        }
    ],
    "sg:phone":"+1 518 474 5661",
    "sg:postcode":"12204",
    "sg:province":"NY",
    "sg:tags":[
        "development",
        "laboratories-research"
    ],
    "wof:name":"Research Foundation For Mental Hygiene Inc",
    "wof:placetype":"venue"
},
  "geometry": {"coordinates":[-73.72962200000001,42.685782],"type":"Point"}
}