{
  "type": "Feature",
  "properties": {
    "addr:full":"428 Lake Shore Dr E Dunkirk NY 14048",
    "addr:housenumber":"428",
    "addr:postcode":"14048",
    "addr:street":"Lake Shore Dr E",
    "iso:country":"US",
    "sg:address":"428 Lake Shore Dr E",
    "sg:city":"Dunkirk",
    "sg:phone":"+1 716 366 0480",
    "sg:postcode":"14048",
    "sg:province":"NY",
    "sg:website":"http://www.limoadventures.com",
    "wof:name":"Adventure Limousine",
    "wof:placetype":"venue"
},
  "geometry": {"coordinates":[-79.31146200000001,42.496208],"type":"Point"}
}