{
  "type": "Feature",
  "properties": {
    "addr:full":"2532 Boston Rd Bronx NY 10467",
    "addr:housenumber":"2532",
    "addr:postcode":"10467",
    "addr:street":"Boston Rd",
    "iso:country":"US",
    "sg:address":"2532 Boston Rd",
    "sg:city":"Bronx",
    "sg:classifiers":[
        {
            "category":"Building & Trades",
            "subcategory":"Construction",
            "type":"Services"
        }
    ],
    "sg:phone":"+1 718 792 9100",
    "sg:postcode":"10467",
    "sg:province":"NY",
    "sg:tags":[
        "insulation",
        "roofing",
        "contractor"
    ],
    "wof:name":"Triboro Insulg & Roofg Co Inc",
    "wof:placetype":"venue"
},
  "geometry": {"coordinates":[-73.863653,40.864449],"type":"Point"}
}