{
  "type": "Feature",
  "properties": {
    "addr:full":"401 E State St Ithaca NY 14850",
    "addr:housenumber":"401",
    "addr:postcode":"14850",
    "addr:street":"E State St",
    "iso:country":"US",
    "sg:address":"401 E State St",
    "sg:city":"Ithaca",
    "sg:classifiers":[
        {
            "category":"Restaurant",
            "type":"Food & Drink"
        }
    ],
    "sg:menulink":"http://www.allmenus.com/ny/ithaca/247546-napoli-pizzeria/menu/",
    "sg:phone":"+1 607 272 3232",
    "sg:postcode":"14850",
    "sg:province":"NY",
    "sg:tags":[
        "american",
        "italian",
        "wing",
        "pizza"
    ],
    "wof:name":"Napoli Pizzeria",
    "wof:placetype":"venue"
},
  "geometry": {"coordinates":[-76.492183,42.439272],"type":"Point"}
}