{
  "type": "Feature",
  "properties": {
    "addr:full":"953 Franklin Ave Garden City NY 11530",
    "addr:housenumber":"953",
    "addr:postcode":"11530",
    "addr:street":"Franklin Ave",
    "iso:country":"US",
    "sg:address":"953 Franklin Ave",
    "sg:city":"Garden City",
    "sg:classifiers":[
        {
            "category":"Banks & Credit Unions",
            "subcategory":"Investment Brokerage",
            "type":"Services"
        }
    ],
    "sg:phone":"+1 516 248 1022",
    "sg:postcode":"11530",
    "sg:province":"NY",
    "sg:tags":[
        "stock",
        "bond"
    ],
    "wof:name":"Garden City Security Ctr",
    "wof:placetype":"venue"
},
  "geometry": {"coordinates":[-73.63545000000001,40.728623],"type":"Point"}
}