{
  "type": "Feature",
  "properties": {
    "iso:country":"US",
    "sg:address":"22 Louise Ct",
    "sg:city":"Riverhead",
    "sg:classifiers":[
        {
            "category":"Building & Trades",
            "subcategory":"Construction",
            "type":"Services"
        }
    ],
    "sg:phone":"+1 631 727 0520",
    "sg:postcode":"11901",
    "sg:province":"NY",
    "sg:tags":[
        "contractor"
    ],
    "wof:name":"Martin Meskill Drywall",
    "wof:placetype":"venue"
},
  "geometry": {"coordinates":[-72.703345,40.972108],"type":"Point"}
}