{
  "type": "Feature",
  "properties": {
    "addr:full":"161 10th Street New York NY 10016",
    "addr:housenumber":"161",
    "addr:postcode":"10016",
    "addr:street":"10Th Street",
    "iso:country":"US",
    "sg:address":"161 10th Street",
    "sg:city":"New York",
    "sg:classifiers":[
        {
            "category":"Health Services",
            "subcategory":"Doctor",
            "type":"Services"
        }
    ],
    "sg:phone":"+1 212 683 8905",
    "sg:postcode":"10016",
    "sg:province":"NY",
    "wof:name":"Capalbo Andrea MD",
    "wof:placetype":"venue"
},
  "geometry": {"coordinates":[-74.006012,40.745713],"type":"Point"}
}