{
  "type": "Feature",
  "properties": {
    "addr:full":"844 Dickens St Woodmere NY 11598",
    "addr:housenumber":"844",
    "addr:postcode":"11598",
    "addr:street":"Dickens St",
    "iso:country":"US",
    "sg:address":"844 Dickens St",
    "sg:city":"Woodmere",
    "sg:classifiers":[
        {
            "category":"Professional",
            "subcategory":"Computer Services",
            "type":"Services"
        }
    ],
    "sg:phone":"+1   ",
    "sg:postcode":"11598",
    "sg:province":"NY",
    "sg:tags":[
        "datum",
        "facility"
    ],
    "wof:name":"Paq Systems",
    "wof:placetype":"venue"
},
  "geometry": {"coordinates":[-73.718047,40.634724],"type":"Point"}
}