{
  "type": "Feature",
  "properties": {
    "addr:full":"115 E 184th St Bronx NY 10468",
    "addr:housenumber":"115",
    "addr:postcode":"10468",
    "addr:street":"E 184Th St",
    "iso:country":"US",
    "sg:address":"115 E 184th St",
    "sg:city":"Bronx",
    "sg:classifiers":[
        {
            "category":"Food & Beverages",
            "subcategory":"Groceries & Convenience Stores",
            "type":"Retail Goods"
        }
    ],
    "sg:phone":"+1   ",
    "sg:postcode":"10468",
    "sg:province":"NY",
    "wof:name":"115 E Food Center Corp",
    "wof:placetype":"venue"
},
  "geometry": {"coordinates":[-73.90033699999999,40.859962],"type":"Point"}
}