{
  "type": "Feature",
  "properties": {
    "addr:full":"23 Loines Ave Merrick NY 11566",
    "addr:housenumber":"23",
    "addr:postcode":"11566",
    "addr:street":"Loines Ave",
    "iso:country":"US",
    "sg:address":"23 Loines Ave",
    "sg:city":"Merrick",
    "sg:classifiers":[
        {
            "category":"Insurance",
            "subcategory":"Insurance Agent",
            "type":"Services"
        }
    ],
    "sg:phone":"+1 516 868 0443",
    "sg:postcode":"11566",
    "sg:province":"NY",
    "wof:name":"Gary Wood Associates Inc",
    "wof:placetype":"venue"
},
  "geometry": {"coordinates":[-73.55456599999999,40.668524],"type":"Point"}
}