{
  "type": "Feature",
  "properties": {
    "addr:full":"38 Marcy Avenue Brooklyn NY 11211",
    "addr:housenumber":"38",
    "addr:postcode":"11211",
    "addr:street":"Marcy Avenue",
    "iso:country":"US",
    "sg:address":"38 Marcy Avenue",
    "sg:city":"Brooklyn",
    "sg:classifiers":[
        {
            "category":"Arts & Performance",
            "subcategory":"Art Gallery",
            "type":"Entertainment"
        }
    ],
    "sg:postcode":"11211",
    "sg:province":"NY",
    "sg:website":"graphiteny.com/",
    "wof:name":"Graphite",
    "wof:placetype":"venue"
},
  "geometry": {"coordinates":[-73.95517599999999,40.713062],"type":"Point"}
}