{
  "type": "Feature",
  "properties": {
    "addr:full":"20 E Market St Red Hook NY 12571",
    "addr:housenumber":"20",
    "addr:postcode":"12571",
    "addr:street":"E Market St",
    "iso:country":"US",
    "sg:address":"20 E Market St",
    "sg:city":"Red Hook",
    "sg:classifiers":[
        {
            "category":"Home & Garden",
            "subcategory":"Household Appliances",
            "type":"Retail Goods"
        }
    ],
    "sg:phone":"+1   ",
    "sg:postcode":"12571",
    "sg:province":"NY",
    "wof:name":"Rifenburgh Refrigeration",
    "wof:placetype":"venue"
},
  "geometry": {"coordinates":[-73.87519899999999,41.99492],"type":"Point"}
}