{
  "type": "Feature",
  "properties": {
    "addr:full":"8302 Queens Boulevard Elmhurst NY 11373",
    "addr:housenumber":"8302",
    "addr:postcode":"11373",
    "addr:street":"Queens Boulevard",
    "iso:country":"US",
    "sg:address":"8302 Queens Boulevard",
    "sg:city":"Elmhurst",
    "sg:classifiers":[
        {
            "category":"Building & Trades",
            "subcategory":"Locksmith",
            "type":"Services"
        }
    ],
    "sg:phone":"+1 718 685 5604",
    "sg:postcode":"11373",
    "sg:province":"NY",
    "sg:tags":[
        "key"
    ],
    "wof:name":"A #1 24 Hour A Locksmith",
    "wof:placetype":"venue"
},
  "geometry": {"coordinates":[-73.880156,40.73698],"type":"Point"}
}