{
  "type": "Feature",
  "properties": {
    "iso:country":"US",
    "sg:address":"18 E 41st St",
    "sg:city":"New York",
    "sg:classifiers":[
        {
            "category":"Professional",
            "subcategory":"Lawyer & Legal Services",
            "type":"Services"
        }
    ],
    "sg:phone":"+1 212 986 5303",
    "sg:postcode":"10017",
    "sg:province":"NY",
    "wof:name":"Jiang Kenneth W",
    "wof:placetype":"venue"
},
  "geometry": {"coordinates":[-73.980504,40.752449],"type":"Point"}
}