{
  "type": "Feature",
  "properties": {
    "addr:full":"167 Windsor Ave Buffalo NY 14209",
    "addr:housenumber":"167",
    "addr:postcode":"14209",
    "addr:street":"Windsor Ave",
    "iso:country":"US",
    "sg:address":"167 Windsor Ave",
    "sg:city":"Buffalo",
    "sg:classifiers":[
        {
            "category":"Professional",
            "subcategory":"Lawyer & Legal Services",
            "type":"Services"
        }
    ],
    "sg:phone":"+1   ",
    "sg:postcode":"14209",
    "sg:province":"NY",
    "wof:name":"Frederick B Cohen Atty",
    "wof:placetype":"venue"
},
  "geometry": {"coordinates":[-78.87169799999999,42.929595],"type":"Point"}
}