{
  "type": "Feature",
  "properties": {
    "addr:full":"5526 Niagara St Exd Lockport NY 14094",
    "addr:housenumber":"5526",
    "addr:postcode":"14094",
    "addr:street":"Niagara St Exd",
    "iso:country":"US",
    "sg:address":"5526 Niagara St Exd",
    "sg:city":"Lockport",
    "sg:classifiers":[
        {
            "category":"Government",
            "subcategory":"Police Station",
            "type":"Public Place"
        }
    ],
    "sg:phone":"+1 716 438 3393",
    "sg:postcode":"14094",
    "sg:province":"NY",
    "sg:tags":[
        "sheriff"
    ],
    "wof:name":"Sheriff Niagara County",
    "wof:placetype":"venue"
},
  "geometry": {"coordinates":[-78.736086,43.181509],"type":"Point"}
}