{
  "type": "Feature",
  "properties": {
    "addr:full":"120 Kenilworth Pl Brooklyn NY 11210",
    "addr:housenumber":"120",
    "addr:postcode":"11210",
    "addr:street":"Kenilworth Pl",
    "iso:country":"US",
    "sg:address":"120 Kenilworth Pl",
    "sg:city":"Brooklyn",
    "sg:classifiers":[
        {
            "category":"Professional",
            "subcategory":"Management & Consulting",
            "type":"Services"
        }
    ],
    "sg:phone":"+1 718 421 2585",
    "sg:postcode":"11210",
    "sg:province":"NY",
    "sg:tags":[
        "consultant"
    ],
    "wof:name":"Dacator Enterprises",
    "wof:placetype":"venue"
},
  "geometry": {"coordinates":[-73.949215,40.63319],"type":"Point"}
}