{
  "type": "Feature",
  "properties": {
    "addr:full":"156-33 CrossBay Boulevard New York NY 11414",
    "addr:housenumber":"156-33",
    "addr:postcode":"11414",
    "addr:street":"Crossbay Boulevard",
    "iso:country":"US",
    "sg:address":"156-33 CrossBay Boulevard",
    "sg:city":"New York",
    "sg:classifiers":[
        {
            "category":"Banks & Credit Unions",
            "subcategory":"Bank",
            "type":"Services"
        }
    ],
    "sg:phone":"+1 718 835 0231",
    "sg:postcode":"11414",
    "sg:province":"NY",
    "sg:website":"www.chase.com",
    "wof:name":"Chase Bank",
    "wof:placetype":"venue"
},
  "geometry": {"coordinates":[-73.84089400000001,40.663658],"type":"Point"}
}