{
  "type": "Feature",
  "properties": {
    "iso:country":"US",
    "sg:address":"3048 Linden Place",
    "sg:city":"Flushing",
    "sg:classifiers":[
        {
            "category":"Education",
            "subcategory":"School",
            "type":"Public Place"
        }
    ],
    "sg:phone":"+1 718 281 7600",
    "sg:postcode":"11354",
    "sg:province":"NY",
    "sg:tags":[
        "high",
        "middle",
        "elementary"
    ],
    "wof:name":"N Y City of",
    "wof:placetype":"venue"
},
  "geometry": {"coordinates":[-73.83285600000001,40.769657],"type":"Point"}
}