{
  "type": "Feature",
  "properties": {
    "addr:full":"1107 E Lovejoy St Buffalo NY 14206",
    "addr:housenumber":"1107",
    "addr:postcode":"14206",
    "addr:street":"E Lovejoy St",
    "iso:country":"US",
    "sg:address":"1107 E Lovejoy St",
    "sg:city":"Buffalo",
    "sg:classifiers":[
        {
            "category":"Banks & Credit Unions",
            "subcategory":"Bank",
            "type":"Services"
        }
    ],
    "sg:phone":"+1 716 892 1339",
    "sg:postcode":"14206",
    "sg:province":"NY",
    "wof:name":"HSBC Bank USA N.A.",
    "wof:placetype":"venue"
},
  "geometry": {"coordinates":[-78.807282,42.889612],"type":"Point"}
}