{
  "type": "Feature",
  "properties": {
    "addr:full":"863 Park Ave New York NY 10075",
    "addr:housenumber":"863",
    "addr:postcode":"10075",
    "addr:street":"Park Ave",
    "iso:country":"US",
    "sg:address":"863 Park Ave",
    "sg:city":"New York",
    "sg:classifiers":[
        {
            "category":"Real Estate",
            "subcategory":"Real Estate Operator",
            "type":"Services"
        }
    ],
    "sg:phone":"+1 212 288 6330",
    "sg:postcode":"10075",
    "sg:province":"NY",
    "sg:tags":[
        "apartment"
    ],
    "wof:name":"Apartments & Apartment Houses",
    "wof:placetype":"venue"
},
  "geometry": {"coordinates":[-73.961136,40.774277],"type":"Point"}
}