{
  "type": "Feature",
  "properties": {
    "iso:country":"US",
    "sg:address":"84A Elizabeth St",
    "sg:city":"New York",
    "sg:classifiers":[
        {
            "category":"Shopping",
            "subcategory":"Hobbies, Toys, & Games",
            "type":"Retail Goods"
        }
    ],
    "sg:postcode":"10013",
    "sg:province":"NY",
    "sg:tags":[
        "shop",
        "hobby"
    ],
    "wof:name":"Wah Choi Collectible Co.",
    "wof:placetype":"venue"
},
  "geometry": {"coordinates":[-73.996033,40.718121],"type":"Point"}
}