{
  "type": "Feature",
  "properties": {
    "iso:country":"US",
    "sg:address":"146 Remington Blvd",
    "sg:city":"Ronkonkoma",
    "sg:classifiers":[
        {
            "category":"Retail",
            "subcategory":"Repair Shop",
            "type":"Services"
        }
    ],
    "sg:phone":"+1 631 913 0261",
    "sg:postcode":"11779",
    "sg:province":"NY",
    "sg:tags":[
        "wholesale",
        "export",
        "industrial",
        "e",
        "refrigeration"
    ],
    "wof:name":"Industrial Refrigeration Inc",
    "wof:placetype":"venue"
},
  "geometry": {"coordinates":[-73.13584299999999,40.791563],"type":"Point"}
}