{
  "type": "Feature",
  "properties": {
    "addr:full":"1450 Union Tpke New Hyde Park NY 11040",
    "addr:housenumber":"1450",
    "addr:postcode":"11040",
    "addr:street":"Union Tpke;Hyde Park",
    "iso:country":"US",
    "sg:address":"1450 Union Tpke",
    "sg:city":"New Hyde Park",
    "sg:classifiers":[
        {
            "category":"Shopping",
            "subcategory":"Pharmacy",
            "type":"Retail Goods"
        }
    ],
    "sg:phone":"+1 516 488 1212",
    "sg:postcode":"11040",
    "sg:province":"NY",
    "wof:name":"Drugs Plus",
    "wof:placetype":"venue"
},
  "geometry": {"coordinates":[-73.69301400000001,40.754065],"type":"Point"}
}