{
  "type": "Feature",
  "properties": {
    "iso:country":"US",
    "sg:address":"171 West St",
    "sg:city":"Brooklyn",
    "sg:classifiers":[
        {
            "category":"Freight",
            "type":"Transportation"
        }
    ],
    "sg:phone":"+1 718 389 8300",
    "sg:postcode":"11222",
    "sg:province":"NY",
    "sg:tags":[
        "trucking"
    ],
    "wof:name":"Citi Wide Transport",
    "wof:placetype":"venue"
},
  "geometry": {"coordinates":[-73.959846,40.732818],"type":"Point"}
}