{
  "type": "Feature",
  "properties": {
    "addr:full":"6060 Main Rd Stafford NY 14143",
    "addr:housenumber":"6060",
    "addr:postcode":"14143",
    "addr:street":"Main Rd",
    "iso:country":"US",
    "sg:address":"6060 Main Rd",
    "sg:city":"Stafford",
    "sg:classifiers":[
        {
            "category":"Shopping",
            "subcategory":"Crafts & Fabrics",
            "type":"Retail Goods"
        }
    ],
    "sg:phone":"+1   ",
    "sg:postcode":"14143",
    "sg:province":"NY",
    "sg:tags":[
        "sewing"
    ],
    "wof:name":"Yarn Shop",
    "wof:placetype":"venue"
},
  "geometry": {"coordinates":[-78.081391,42.982463],"type":"Point"}
}