{
  "type": "Feature",
  "properties": {
    "iso:country":"US",
    "sg:address":"609 State Hwy 6n",
    "sg:city":"Mahopac",
    "sg:classifiers":[
        {
            "category":"Personal",
            "subcategory":"Beauty Salon",
            "type":"Services"
        }
    ],
    "sg:phone":"+1 845 628 9200",
    "sg:postcode":"10541",
    "sg:province":"NY",
    "sg:tags":[
        "manicuring"
    ],
    "wof:name":"Diamond Nails By Rose",
    "wof:placetype":"venue"
},
  "geometry": {"coordinates":[-73.760728,41.374639],"type":"Point"}
}