{
  "type": "Feature",
  "properties": {
    "addr:full":"130 Main St Little Valley NY 14755",
    "addr:housenumber":"130",
    "addr:postcode":"14755",
    "addr:street":"Main St",
    "iso:country":"US",
    "sg:address":"130 Main St",
    "sg:city":"Little Valley",
    "sg:classifiers":[
        {
            "category":"Professional",
            "type":"Services"
        }
    ],
    "sg:phone":"+1 716 938 6762",
    "sg:postcode":"14755",
    "sg:province":"NY",
    "sg:tags":[
        "establishment"
    ],
    "wof:name":"Pirshlo Inc",
    "wof:placetype":"venue"
},
  "geometry": {"coordinates":[-78.797769,42.250022],"type":"Point"}
}