{
  "type": "Feature",
  "properties": {
    "addr:full":"25 Covert Ave Floral Park NY 11001",
    "addr:housenumber":"25",
    "addr:postcode":"11001",
    "addr:street":"Covert Ave",
    "iso:country":"US",
    "sg:address":"25 Covert Ave",
    "sg:city":"Floral Park",
    "sg:classifiers":[
        {
            "category":"Bakery",
            "type":"Food & Drink"
        }
    ],
    "sg:phone":"+1 516 437 0101",
    "sg:postcode":"11001",
    "sg:province":"NY",
    "wof:name":"La Bella Bakery",
    "wof:placetype":"venue"
},
  "geometry": {"coordinates":[-73.6875,40.724098],"type":"Point"}
}