{
  "type": "Feature",
  "properties": {
    "addr:full":"2 Livingston Rd Scarsdale NY 10583",
    "addr:housenumber":"2",
    "addr:postcode":"10583",
    "addr:street":"Livingston Rd",
    "iso:country":"US",
    "sg:address":"2 Livingston Rd",
    "sg:city":"Scarsdale",
    "sg:classifiers":[
        {
            "category":"Health Services",
            "subcategory":"Doctor",
            "type":"Services"
        }
    ],
    "sg:phone":"+1 914 472 9089",
    "sg:postcode":"10583",
    "sg:province":"NY",
    "sg:tags":[
        "medical"
    ],
    "wof:name":"Anna Kadish MD",
    "wof:placetype":"venue"
},
  "geometry": {"coordinates":[-73.777514,40.981823],"type":"Point"}
}