{
  "type": "Feature",
  "properties": {
    "addr:full":"119 Carey St Mahopac NY 10541",
    "addr:housenumber":"119",
    "addr:postcode":"10541",
    "addr:street":"Carey St",
    "iso:country":"US",
    "sg:address":"119 Carey St",
    "sg:city":"Mahopac",
    "sg:classifiers":[
        {
            "category":"Professional",
            "subcategory":"Business Services",
            "type":"Services"
        }
    ],
    "sg:phone":"+1   ",
    "sg:postcode":"10541",
    "sg:province":"NY",
    "wof:name":"Johns Auto Customizing In",
    "wof:placetype":"venue"
},
  "geometry": {"coordinates":[-73.781648,41.344401],"type":"Point"}
}