{
  "type": "Feature",
  "properties": {
    "iso:country":"US",
    "sg:address":"19 Broadfield Rd",
    "sg:city":"New Rochelle",
    "sg:classifiers":[
        {
            "category":"Real Estate",
            "subcategory":"Real Estate Operator",
            "type":"Services"
        }
    ],
    "sg:phone":"+1 914 632 8122",
    "sg:postcode":"10804",
    "sg:province":"NY",
    "sg:tags":[
        "building",
        "nonresidential"
    ],
    "wof:name":"15 Madeline Ave Realty Corp",
    "wof:placetype":"venue"
},
  "geometry": {"coordinates":[-73.793757,40.954041],"type":"Point"}
}