{
  "type": "Feature",
  "properties": {
    "addr:full":"77 Windsor Pl Central Islip NY 11722",
    "addr:housenumber":"77",
    "addr:postcode":"11722",
    "addr:street":"Windsor Pl",
    "iso:country":"US",
    "sg:address":"77 Windsor Pl",
    "sg:city":"Central Islip",
    "sg:classifiers":[
        {
            "category":"Professional",
            "subcategory":"Business Services",
            "type":"Services"
        }
    ],
    "sg:phone":"+1 631 761 6016",
    "sg:postcode":"11722",
    "sg:province":"NY",
    "sg:tags":[
        "broker"
    ],
    "wof:name":"Bridge Business & Property",
    "wof:placetype":"venue"
},
  "geometry": {"coordinates":[-73.17297600000001,40.796392],"type":"Point"}
}