{
  "type": "Feature",
  "properties": {
    "addr:full":"349 W30th St, No.1 New York NY 10001",
    "addr:housenumber":"349",
    "addr:postcode":"10001",
    "addr:street":"W30Th St",
    "iso:country":"US",
    "sg:address":"349 W30th St, No.1",
    "sg:city":"New York",
    "sg:classifiers":[
        {
            "category":"Professional",
            "subcategory":"Computer Services",
            "type":"Services"
        }
    ],
    "sg:phone":"+1 800 594 9349",
    "sg:postcode":"10001",
    "sg:province":"NY",
    "sg:tags":[
        "recruitment-and-staffing",
        "jobs",
        "hiring",
        "careers",
        "assessment",
        "job-person-matching"
    ],
    "sg:website":"http://www.matchpointcareers.com",
    "wof:name":"Matchpoint Careers",
    "wof:placetype":"venue"
},
  "geometry": {"coordinates":[-74.01262800000001,40.705003],"type":"Point"}
}