{
  "type": "Feature",
  "properties": {
    "addr:full":"1722 Kings Hwy Brooklyn NY 11229",
    "addr:housenumber":"1722",
    "addr:postcode":"11229",
    "addr:street":"Kings Hwy",
    "iso:country":"US",
    "sg:address":"1722 Kings Hwy",
    "sg:city":"Brooklyn",
    "sg:classifiers":[
        {
            "category":"Shopping",
            "subcategory":"Computers & Home Electronics",
            "type":"Retail Goods"
        }
    ],
    "sg:phone":"+1 718 627 7866",
    "sg:postcode":"11229",
    "sg:province":"NY",
    "sg:tags":[
        "software"
    ],
    "sg:website":"www.computersoftwareplus.com",
    "wof:name":"Computer Software Plus",
    "wof:placetype":"venue"
},
  "geometry": {"coordinates":[-73.955781,40.609732],"type":"Point"}
}