{
  "type": "Feature",
  "properties": {
    "iso:country":"US",
    "sg:address":"2180 Route 6",
    "sg:city":"Carmel",
    "sg:classifiers":[
        {
            "category":"Retail",
            "subcategory":"Veterinary Services",
            "type":"Services"
        }
    ],
    "sg:phone":"+1 845 278 8000",
    "sg:postcode":"10512",
    "sg:province":"NY",
    "sg:tags":[
        "veterinarian"
    ],
    "wof:name":"Pfeifer Lou Ann DVM",
    "wof:placetype":"venue"
},
  "geometry": {"coordinates":[-73.64810199999999,41.416302],"type":"Point"}
}