{
  "type": "Feature",
  "properties": {
    "iso:country":"US",
    "sg:address":"470 Park Ave S Frnt 1",
    "sg:city":"New York",
    "sg:classifiers":[
        {
            "category":"Banks & Credit Unions",
            "subcategory":"Bank",
            "type":"Services"
        }
    ],
    "sg:phone":"+1 212 679 1140",
    "sg:postcode":"10016",
    "sg:province":"NY",
    "wof:name":"CapitalOne",
    "wof:placetype":"venue"
},
  "geometry": {"coordinates":[-73.98281299999999,40.745476],"type":"Point"}
}