{
  "type": "Feature",
  "properties": {
    "addr:full":"3500 Elm Rd Geneseo NY 14454",
    "addr:housenumber":"3500",
    "addr:postcode":"14454",
    "addr:street":"Elm Rd",
    "iso:country":"US",
    "sg:address":"3500 Elm Rd",
    "sg:city":"Geneseo",
    "sg:classifiers":[
        {
            "category":"Farming",
            "subcategory":"Farm",
            "type":"Manufacturing & Wholesale Goods"
        }
    ],
    "sg:phone":"+1 585 243 2516",
    "sg:postcode":"14454",
    "sg:province":"NY",
    "sg:tags":[
        "crop",
        "general"
    ],
    "wof:name":"Bailey Farms",
    "wof:placetype":"venue"
},
  "geometry": {"coordinates":[-77.759945,42.836522],"type":"Point"}
}