{
  "type": "Feature",
  "properties": {
    "addr:full":"681 Kelly St Bronx NY 10455",
    "addr:housenumber":"681",
    "addr:postcode":"10455",
    "addr:street":"Kelly St",
    "iso:country":"US",
    "sg:address":"681 Kelly St",
    "sg:city":"Bronx",
    "sg:classifiers":[
        {
            "category":"Education",
            "subcategory":"School",
            "type":"Public Place"
        }
    ],
    "sg:phone":"+1 718 993 7358",
    "sg:postcode":"10455",
    "sg:province":"NY",
    "sg:tags":[
        "high",
        "middle",
        "elementary"
    ],
    "wof:name":"Episcopal Social Services",
    "wof:placetype":"venue"
},
  "geometry": {"coordinates":[-73.90199200000001,40.815474],"type":"Point"}
}