{
  "type": "Feature",
  "properties": {
    "iso:country":"US",
    "sg:address":"7227 State Rte 31",
    "sg:city":"Lyons",
    "sg:classifiers":[
        {
            "category":"Government",
            "subcategory":"Office",
            "type":"Public Place"
        }
    ],
    "sg:phone":"+1 315 946 5606",
    "sg:postcode":"14489",
    "sg:province":"NY",
    "wof:name":"Wayne County Highway Garage",
    "wof:placetype":"venue"
},
  "geometry": {"coordinates":[-77.034678,43.067984],"type":"Point"}
}