{
  "type": "Feature",
  "properties": {
    "iso:country":"US",
    "sg:address":"1224 Wildwood Ln",
    "sg:city":"Vestal",
    "sg:classifiers":[
        {
            "category":"Shopping",
            "subcategory":"Books",
            "type":"Retail Goods"
        }
    ],
    "sg:phone":"+1   ",
    "sg:postcode":"13850",
    "sg:province":"NY",
    "wof:name":"Salvador Fajardo Professor",
    "wof:placetype":"venue"
},
  "geometry": {"coordinates":[-75.95464,42.074813],"type":"Point"}
}