{
  "type": "Feature",
  "properties": {
    "addr:full":"24 Division St New Rochelle NY 10801",
    "addr:housenumber":"24",
    "addr:postcode":"10801",
    "addr:street":"Division St",
    "iso:country":"US",
    "sg:address":"24 Division St",
    "sg:city":"New Rochelle",
    "sg:classifiers":[
        {
            "category":"Personal",
            "subcategory":"Barber",
            "type":"Services"
        }
    ],
    "sg:phone":"+1 914 636 1360",
    "sg:postcode":"10801",
    "sg:province":"NY",
    "sg:tags":[
        "shop"
    ],
    "wof:name":"Dino & Dan Barber Shop",
    "wof:placetype":"venue"
},
  "geometry": {"coordinates":[-73.78308699999999,40.908431],"type":"Point"}
}