{
  "type": "Feature",
  "properties": {
    "addr:full":"7215 18th Ave Brooklyn NY 11204",
    "addr:housenumber":"7215",
    "addr:postcode":"11204",
    "addr:street":"18Th Ave",
    "iso:country":"US",
    "sg:address":"7215 18th Ave",
    "sg:city":"Brooklyn",
    "sg:classifiers":[
        {
            "category":"Shopping",
            "type":"Retail Goods"
        }
    ],
    "sg:phone":"+1 718 259 3798",
    "sg:postcode":"11204",
    "sg:province":"NY",
    "sg:tags":[
        "wedding",
        "supply"
    ],
    "wof:name":"Fantasia Wedding Ctr",
    "wof:placetype":"venue"
},
  "geometry": {"coordinates":[-73.994674,40.614598],"type":"Point"}
}