{
  "type": "Feature",
  "properties": {
    "iso:country":"US",
    "sg:address":"409 Oriskany Blvd",
    "sg:city":"Whitesboro",
    "sg:classifiers":[
        {
            "category":"Restaurant",
            "type":"Food & Drink"
        }
    ],
    "sg:phone":"+1 315 736 7869",
    "sg:postcode":"13492",
    "sg:province":"NY",
    "wof:name":"Route 69 Steakhouse & Saloon",
    "wof:placetype":"venue"
},
  "geometry": {"coordinates":[-75.303675,43.134637],"type":"Point"}
}