{
  "type": "Feature",
  "properties": {
    "addr:full":"722 King Ave Bronx NY 10464",
    "addr:housenumber":"722",
    "addr:postcode":"10464",
    "addr:street":"King Ave",
    "iso:country":"US",
    "sg:address":"722 King Ave",
    "sg:city":"Bronx",
    "sg:classifiers":[
        {
            "category":"Organizations",
            "subcategory":"Religious Organization",
            "type":"Services"
        }
    ],
    "sg:phone":"+1 718 885 9533",
    "sg:postcode":"10464",
    "sg:province":"NY",
    "wof:name":"Adventis Community At Columbia",
    "wof:placetype":"venue"
},
  "geometry": {"coordinates":[-73.790192,40.85805],"type":"Point"}
}