{
  "type": "Feature",
  "properties": {
    "addr:full":"1706 Cropsey Ave Ste A Brooklyn NY 11214",
    "addr:housenumber":"1706",
    "addr:postcode":"11214",
    "addr:street":"Cropsey Ave Ste A",
    "iso:country":"US",
    "sg:address":"1706 Cropsey Ave Ste A",
    "sg:city":"Brooklyn",
    "sg:classifiers":[
        {
            "category":"Health Services",
            "subcategory":"Doctor",
            "type":"Services"
        }
    ],
    "sg:phone":"+1 718 234 5858",
    "sg:postcode":"11214",
    "sg:province":"NY",
    "wof:name":"Goncharuk Inna",
    "wof:placetype":"venue"
},
  "geometry": {"coordinates":[-74.009598,40.603802],"type":"Point"}
}