{
  "type": "Feature",
  "properties": {
    "iso:country":"US",
    "sg:address":"1703 Lexington Ave",
    "sg:city":"New York",
    "sg:classifiers":[
        {
            "category":"Communications",
            "type":"Services"
        }
    ],
    "sg:phone":"+1 212 348 0332",
    "sg:postcode":"10029",
    "sg:province":"NY",
    "wof:name":"Lexington Communication Access",
    "wof:placetype":"venue"
},
  "geometry": {"coordinates":[-73.946011,40.79236],"type":"Point"}
}