{
  "type": "Feature",
  "properties": {
    "addr:full":"65 E 19th St Brooklyn NY 11226",
    "addr:housenumber":"65",
    "addr:postcode":"11226",
    "addr:street":"E 19Th St",
    "iso:country":"US",
    "sg:address":"65 E 19th St",
    "sg:city":"Brooklyn",
    "sg:classifiers":[
        {
            "category":"Real Estate",
            "subcategory":"Real Estate Operator",
            "type":"Services"
        }
    ],
    "sg:phone":"+1 718 856 4900",
    "sg:postcode":"11226",
    "sg:province":"NY",
    "sg:tags":[
        "building",
        "apartment"
    ],
    "wof:name":"Keystone Towers Ltd",
    "wof:placetype":"venue"
},
  "geometry": {"coordinates":[-73.961662,40.647572],"type":"Point"}
}