{
  "type": "Feature",
  "properties": {
    "iso:country":"US",
    "sg:address":"2 Greenbush Ave",
    "sg:city":"East Greenbush",
    "sg:classifiers":[
        {
            "category":"Personal",
            "subcategory":"Beauty Salon",
            "type":"Services"
        },
        {
            "category":"Personal",
            "subcategory":"Day Spa",
            "type":"Services"
        }
    ],
    "sg:phone":"+1 518 479 1500",
    "sg:postcode":"12061",
    "sg:province":"NY",
    "sg:tags":[
        "hair"
    ],
    "sg:website":"www.shelleysalon.com",
    "wof:name":"Shelley Salon & Day Spa",
    "wof:placetype":"venue"
},
  "geometry": {"coordinates":[-73.706397,42.605726],"type":"Point"}
}