{
  "type": "Feature",
  "properties": {
    "iso:country":"US",
    "sg:address":"128 5th Ave",
    "sg:city":"Pelham",
    "sg:classifiers":[
        {
            "category":"Personal",
            "subcategory":"Beauty Salon",
            "type":"Services"
        }
    ],
    "sg:phone":"+1 914 633 6803",
    "sg:postcode":"10803",
    "sg:province":"NY",
    "sg:tags":[
        "manicuring"
    ],
    "wof:name":"Top 2 Nail",
    "wof:placetype":"venue"
},
  "geometry": {"coordinates":[-73.808424,40.913526],"type":"Point"}
}