{
  "type": "Feature",
  "properties": {
    "addr:full":"6083 Fisk Rd Lockport NY 14094",
    "addr:housenumber":"6083",
    "addr:postcode":"14094",
    "addr:street":"Fisk Rd",
    "iso:country":"US",
    "sg:address":"6083 Fisk Rd",
    "sg:city":"Lockport",
    "sg:classifiers":[
        {
            "category":"Building & Trades",
            "subcategory":"Landscaping Services",
            "type":"Services"
        }
    ],
    "sg:phone":"+1 716 625 8153",
    "sg:postcode":"14094",
    "sg:province":"NY",
    "sg:tags":[
        "heavy",
        "sanitary",
        "construction",
        "landscape",
        "contractor"
    ],
    "wof:name":"Wolf's Nursery",
    "wof:placetype":"venue"
},
  "geometry": {"coordinates":[-78.70293599999999,43.113403],"type":"Point"}
}