{
  "type": "Feature",
  "properties": {
    "addr:full":"196 Highlawn Ave Brooklyn NY 11223",
    "addr:housenumber":"196",
    "addr:postcode":"11223",
    "addr:street":"Highlawn Ave",
    "iso:country":"US",
    "sg:address":"196 Highlawn Ave",
    "sg:city":"Brooklyn",
    "sg:classifiers":[
        {
            "category":"Insurance",
            "subcategory":"Insurance Agent",
            "type":"Services"
        }
    ],
    "sg:phone":"+1 718 627 2121",
    "sg:postcode":"11223",
    "sg:province":"NY",
    "wof:name":"All Boroughs Insurance Brkg",
    "wof:placetype":"venue"
},
  "geometry": {"coordinates":[-73.977828,40.603586],"type":"Point"}
}