{
  "type": "Feature",
  "properties": {
    "iso:country":"US",
    "sg:address":"60 Main St",
    "sg:city":"Massena",
    "sg:classifiers":[
        {
            "category":"Government",
            "subcategory":"Office",
            "type":"Public Place"
        }
    ],
    "sg:phone":"+1 315 769 8625",
    "sg:postcode":"13662",
    "sg:province":"NY",
    "sg:tags":[
        "village"
    ],
    "wof:name":"Village of Massena",
    "wof:placetype":"venue"
},
  "geometry": {"coordinates":[-74.892926,44.931096],"type":"Point"}
}