{
  "type": "Feature",
  "properties": {
    "iso:country":"US",
    "sg:address":"9417 Roosevelt Avenue",
    "sg:city":"Jackson Heights",
    "sg:classifiers":[
        {
            "category":"Manufacturing",
            "subcategory":"Leather Goods",
            "type":"Manufacturing & Wholesale Goods"
        }
    ],
    "sg:phone":"+1 718 898 0728",
    "sg:postcode":"11372",
    "sg:province":"NY",
    "sg:website":"www.FrankyFashion.com",
    "wof:name":"Franky Fashion",
    "wof:placetype":"venue"
},
  "geometry": {"coordinates":[-73.872128,40.748986],"type":"Point"}
}