{
  "type": "Feature",
  "properties": {
    "iso:country":"US",
    "sg:address":"184 N Windhorst Ave",
    "sg:city":"Bethpage",
    "sg:classifiers":[
        {
            "category":"Shopping",
            "subcategory":"Computers & Home Electronics",
            "type":"Retail Goods"
        }
    ],
    "sg:phone":"+1   ",
    "sg:postcode":"11714",
    "sg:province":"NY",
    "sg:website":"www.entertainmentalternatives.com",
    "wof:name":"Entertainment Alternatives",
    "wof:placetype":"venue"
},
  "geometry": {"coordinates":[-73.47846,40.737946],"type":"Point"}
}