{
  "type": "Feature",
  "properties": {
    "iso:country":"US",
    "sg:address":"107 Mechanic St",
    "sg:city":"Corinth",
    "sg:classifiers":[
        {
            "category":"Government",
            "subcategory":"Fire Station",
            "type":"Public Place"
        }
    ],
    "sg:phone":"+1 518 654 9015",
    "sg:postcode":"12822",
    "sg:province":"NY",
    "sg:tags":[
        "protection"
    ],
    "wof:name":"Corinth Fire Dept",
    "wof:placetype":"venue"
},
  "geometry": {"coordinates":[-73.832961,43.244089],"type":"Point"}
}