{
  "type": "Feature",
  "properties": {
    "addr:full":"149 E Lake Blvd Mahopac NY 10541",
    "addr:housenumber":"149",
    "addr:postcode":"10541",
    "addr:street":"E Lake Blvd",
    "iso:country":"US",
    "sg:address":"149 E Lake Blvd",
    "sg:city":"Mahopac",
    "sg:classifiers":[
        {
            "category":"Wholesale",
            "subcategory":"Books, Periodicals, & Newspapers",
            "type":"Manufacturing & Wholesale Goods"
        }
    ],
    "sg:phone":"+1 845 621 0813",
    "sg:postcode":"10541",
    "sg:province":"NY",
    "sg:tags":[
        "publisher",
        "book"
    ],
    "wof:name":"Arbco Networks",
    "wof:placetype":"venue"
},
  "geometry": {"coordinates":[-73.728852,41.375754],"type":"Point"}
}