{
  "type": "Feature",
  "properties": {
    "addr:full":"260 Arnold Rd Preston Hollow NY 12469",
    "addr:housenumber":"260",
    "addr:postcode":"12469",
    "addr:street":"Arnold Rd",
    "iso:country":"US",
    "sg:address":"260 Arnold Rd",
    "sg:city":"Preston Hollow",
    "sg:classifiers":[
        {
            "category":"Wholesale",
            "subcategory":"Construction Materials",
            "type":"Manufacturing & Wholesale Goods"
        }
    ],
    "sg:phone":"+1 518 239 8106",
    "sg:postcode":"12469",
    "sg:province":"NY",
    "wof:name":"Molloy Sales Rs",
    "wof:placetype":"venue"
},
  "geometry": {"coordinates":[-74.200643,42.428191],"type":"Point"}
}