{
  "type": "Feature",
  "properties": {
    "addr:full":"86 Kean St West Babylon NY 11704",
    "addr:housenumber":"86",
    "addr:postcode":"11704",
    "addr:street":"Kean St",
    "iso:country":"US",
    "sg:address":"86 Kean St",
    "sg:city":"West Babylon",
    "sg:classifiers":[
        {
            "category":"Building & Trades",
            "subcategory":"Plumbing",
            "type":"Services"
        }
    ],
    "sg:phone":"+1 631 253 4900",
    "sg:postcode":"11704",
    "sg:province":"NY",
    "sg:tags":[
        "contractor"
    ],
    "wof:name":"Atlantic Sheet Metal Works",
    "wof:placetype":"venue"
},
  "geometry": {"coordinates":[-73.38038400000001,40.737225],"type":"Point"}
}