{
  "type": "Feature",
  "properties": {
    "addr:full":"31 Warsoff Pl Brooklyn NY 11205",
    "addr:housenumber":"31",
    "addr:postcode":"11205",
    "addr:street":"Warsoff Pl",
    "iso:country":"US",
    "sg:address":"31 Warsoff Pl",
    "sg:city":"Brooklyn",
    "sg:classifiers":[
        {
            "category":"Wholesale",
            "subcategory":"Office Equipment",
            "type":"Manufacturing & Wholesale Goods"
        }
    ],
    "sg:phone":"+1 718 782 2823",
    "sg:postcode":"11205",
    "sg:province":"NY",
    "sg:tags":[
        "wholesaler",
        "credit",
        "processing",
        "card"
    ],
    "wof:name":"Fidelity Payment Services",
    "wof:placetype":"venue"
},
  "geometry": {"coordinates":[-73.953929,40.698109],"type":"Point"}
}