{
  "type": "Feature",
  "properties": {
    "iso:country":"US",
    "sg:address":"528 Industrial Loop",
    "sg:city":"Staten Island",
    "sg:classifiers":[
        {
            "category":"Banks & Credit Unions",
            "subcategory":"Bank",
            "type":"Services"
        }
    ],
    "sg:phone":"+1 718 948 3477",
    "sg:postcode":"10309",
    "sg:province":"NY",
    "sg:tags":[
        "leasing",
        "ambulance"
    ],
    "wof:name":"Emergency Vehicle Leasing",
    "wof:placetype":"venue"
},
  "geometry": {"coordinates":[-74.22887299999999,40.546602],"type":"Point"}
}