{
  "type": "Feature",
  "properties": {
    "iso:country":"US",
    "sg:address":"378 5th Ave",
    "sg:city":"New York",
    "sg:classifiers":[
        {
            "category":"Shopping",
            "subcategory":"Photographic Equipment",
            "type":"Retail Goods"
        }
    ],
    "sg:phone":"+1 888 810 4242",
    "sg:postcode":"10018",
    "sg:province":"NY",
    "sg:tags":[
        "photography",
        "store",
        "supply"
    ],
    "sg:website":"www.42photo.com",
    "wof:name":"42nd Street Photo",
    "wof:placetype":"venue"
},
  "geometry": {"coordinates":[-73.983951,40.749272],"type":"Point"}
}