{
  "type": "Feature",
  "properties": {
    "iso:country":"US",
    "sg:address":"558 Gramatan Ave",
    "sg:city":"Mount Vernon",
    "sg:classifiers":[
        {
            "category":"Shopping",
            "subcategory":"Shoes",
            "type":"Retail Goods"
        }
    ],
    "sg:phone":"+1   ",
    "sg:postcode":"10552",
    "sg:province":"NY",
    "sg:tags":[
        "family"
    ],
    "wof:name":"Alfonso Shoe Co Inc",
    "wof:placetype":"venue"
},
  "geometry": {"coordinates":[-73.836095,40.925209],"type":"Point"}
}