{
  "type": "Feature",
  "properties": {
    "addr:full":"6312 E Molloy Rd East Syracuse NY 13057",
    "addr:housenumber":"6312",
    "addr:postcode":"13057",
    "addr:street":"E Molloy Rd",
    "iso:country":"US",
    "sg:address":"6312 E Molloy Rd",
    "sg:city":"East Syracuse",
    "sg:classifiers":[
        {
            "category":"Retail",
            "subcategory":"Auto Repair",
            "type":"Services"
        }
    ],
    "sg:phone":"+1   ",
    "sg:postcode":"13057",
    "sg:province":"NY",
    "sg:tags":[
        "automotive",
        "mfr",
        "bracket",
        "trailer",
        "general"
    ],
    "wof:name":"Toms Repairing and Fabricating",
    "wof:placetype":"venue"
},
  "geometry": {"coordinates":[-76.08588899999999,43.099713],"type":"Point"}
}