{
  "type": "Feature",
  "properties": {
    "addr:full":"133 E 73rd Street New York NY 10021",
    "addr:housenumber":"133",
    "addr:postcode":"10021",
    "addr:street":"E 73Rd Street",
    "iso:country":"US",
    "sg:address":"133 E 73rd Street",
    "sg:city":"New York",
    "sg:classifiers":[
        {
            "category":"Health Services",
            "subcategory":"Doctor",
            "type":"Services"
        }
    ],
    "sg:phone":"+1 212 861 9000",
    "sg:postcode":"10021",
    "sg:province":"NY",
    "wof:name":"Redmond Geoffrey P MD",
    "wof:placetype":"venue"
},
  "geometry": {"coordinates":[-73.96169399999999,40.771097],"type":"Point"}
}