{
  "type": "Feature",
  "properties": {
    "addr:full":"1180 Henrietta Pl Hewlett NY 11557",
    "addr:housenumber":"1180",
    "addr:postcode":"11557",
    "addr:street":"Henrietta Pl",
    "iso:country":"US",
    "sg:address":"1180 Henrietta Pl",
    "sg:city":"Hewlett",
    "sg:classifiers":[
        {
            "category":"Education",
            "subcategory":"School",
            "type":"Public Place"
        }
    ],
    "sg:phone":"+1 516 374 8151",
    "sg:postcode":"11557",
    "sg:province":"NY",
    "wof:name":"Franklin Early Childhood Ctr",
    "wof:placetype":"venue"
},
  "geometry": {"coordinates":[-73.706197,40.639297],"type":"Point"}
}