{
  "type": "Feature",
  "properties": {
    "iso:country":"US",
    "sg:address":"40 Auburn St",
    "sg:city":"Lake Grove",
    "sg:classifiers":[
        {
            "category":"Building & Trades",
            "subcategory":"Landscaping Services",
            "type":"Services"
        }
    ],
    "sg:phone":"+1 631 648 3698",
    "sg:postcode":"11757",
    "sg:province":"NY",
    "sg:tags":[
        "landscape",
        "contractor"
    ],
    "wof:name":"Greyhound Landscape Svc",
    "wof:placetype":"venue"
},
  "geometry": {"coordinates":[-73.371666,40.688226],"type":"Point"}
}