{
  "type": "Feature",
  "properties": {
    "iso:country":"US",
    "sg:address":"10 Aladdin Ct",
    "sg:city":"Wappingers Falls",
    "sg:classifiers":[
        {
            "category":"Wholesale",
            "subcategory":"Stationery",
            "type":"Manufacturing & Wholesale Goods"
        }
    ],
    "sg:phone":"+1 845 298 1171",
    "sg:postcode":"12590",
    "sg:province":"NY",
    "sg:tags":[
        "durable",
        "paper"
    ],
    "wof:name":"Bernal General Wholesale",
    "wof:placetype":"venue"
},
  "geometry": {"coordinates":[-73.898968,41.588857],"type":"Point"}
}