{
  "type": "Feature",
  "properties": {
    "addr:full":"1800 Kings Hwy Brooklyn NY 11229",
    "addr:housenumber":"1800",
    "addr:postcode":"11229",
    "addr:street":"Kings Hwy",
    "iso:country":"US",
    "sg:address":"1800 Kings Hwy",
    "sg:city":"Brooklyn",
    "sg:classifiers":[
        {
            "category":"Government",
            "subcategory":"Police Station",
            "type":"Public Place"
        }
    ],
    "sg:phone":"+1 718 998 1852",
    "sg:postcode":"11229",
    "sg:province":"NY",
    "sg:tags":[
        "protection"
    ],
    "wof:name":"City Marshall",
    "wof:placetype":"venue"
},
  "geometry": {"coordinates":[-73.954695,40.610265],"type":"Point"}
}