{
  "type": "Feature",
  "properties": {
    "addr:full":"1745 Penfield Rd Penfield NY 14526",
    "addr:housenumber":"1745",
    "addr:postcode":"14526",
    "addr:street":"Penfield Rd",
    "iso:country":"US",
    "sg:address":"1745 Penfield Rd",
    "sg:city":"Penfield",
    "sg:classifiers":[
        {
            "category":"Insurance",
            "subcategory":"Insurance Agent",
            "type":"Services"
        }
    ],
    "sg:phone":"+1 585 381 7008",
    "sg:postcode":"14526",
    "sg:province":"NY",
    "sg:website":"www.mgminsure.com",
    "wof:name":"MGM Assoc",
    "wof:placetype":"venue"
},
  "geometry": {"coordinates":[-77.480788,43.12878],"type":"Point"}
}