{
  "type": "Feature",
  "properties": {
    "addr:full":"6652 State Hwy 39 Springville NY 14141",
    "addr:housenumber":"6652",
    "addr:postcode":"14141",
    "addr:street":"State Hwy 39",
    "iso:country":"US",
    "sg:address":"6652 State Hwy 39",
    "sg:city":"Springville",
    "sg:classifiers":[
        {
            "category":"Education",
            "subcategory":"School",
            "type":"Public Place"
        }
    ],
    "sg:phone":"+1   ",
    "sg:postcode":"14141",
    "sg:province":"NY",
    "wof:name":"Concord Amish Village",
    "wof:placetype":"venue"
},
  "geometry": {"coordinates":[-78.74528599999999,42.512078],"type":"Point"}
}