{
  "type": "Feature",
  "properties": {
    "addr:full":"1161 Broadway Brooklyn NY 11221",
    "addr:housenumber":"1161",
    "addr:postcode":"11221",
    "addr:street":"Broadway",
    "iso:country":"US",
    "sg:address":"1161 Broadway",
    "sg:city":"Brooklyn",
    "sg:classifiers":[
        {
            "category":"Food & Beverages",
            "subcategory":"Meat & Fish",
            "type":"Retail Goods"
        }
    ],
    "sg:phone":"+1 718 455 2998",
    "sg:postcode":"11221",
    "sg:province":"NY",
    "sg:tags":[
        "seafood",
        "market"
    ],
    "wof:name":"K & B Fish Mini Market Inc",
    "wof:placetype":"venue"
},
  "geometry": {"coordinates":[-73.92801300000001,40.693023],"type":"Point"}
}