{
  "type": "Feature",
  "properties": {
    "addr:full":"5 Tudor City Pl New York NY 10017",
    "addr:housenumber":"5",
    "addr:postcode":"10017",
    "addr:street":"Tudor City Pl",
    "iso:country":"US",
    "sg:address":"5 Tudor City Pl",
    "sg:city":"New York",
    "sg:classifiers":[
        {
            "category":"Building & Trades",
            "subcategory":"Locksmith",
            "type":"Services"
        }
    ],
    "sg:phone":"+1 212 972 7057",
    "sg:postcode":"10017",
    "sg:province":"NY",
    "sg:tags":[
        "key"
    ],
    "wof:name":"Eastside Locksmith 24 Hr Svc",
    "wof:placetype":"venue"
},
  "geometry": {"coordinates":[-73.971001,40.748402],"type":"Point"}
}