{
  "type": "Feature",
  "properties": {
    "iso:country":"US",
    "sg:address":"5126 Commercial Dr",
    "sg:city":"Yorkville",
    "sg:classifiers":[
        {
            "category":"Home & Garden",
            "subcategory":"Carpets & Floor Coverings",
            "type":"Retail Goods"
        }
    ],
    "sg:phone":"+1 315 736 7723",
    "sg:postcode":"13495",
    "sg:province":"NY",
    "sg:tags":[
        "dealer",
        "rug"
    ],
    "sg:website":"www.meelanfloors.com",
    "wof:name":"Meelan Floors Carpet One",
    "wof:placetype":"venue"
},
  "geometry": {"coordinates":[-75.290474,43.114267],"type":"Point"}
}