{
  "type": "Feature",
  "properties": {
    "addr:full":"45 Oak St Patchogue NY 11772",
    "addr:housenumber":"45",
    "addr:postcode":"11772",
    "addr:street":"Oak St",
    "iso:country":"US",
    "sg:address":"45 Oak St",
    "sg:city":"Patchogue",
    "sg:classifiers":[
        {
            "category":"Organizations",
            "subcategory":"Religious Organization",
            "type":"Services"
        }
    ],
    "sg:phone":"+1   ",
    "sg:postcode":"11772",
    "sg:province":"NY",
    "wof:name":"Temple Beth-El Of Patchogue",
    "wof:placetype":"venue"
},
  "geometry": {"coordinates":[-73.01152399999999,40.768001],"type":"Point"}
}