{
  "type": "Feature",
  "properties": {
    "addr:full":"1678 85th St Brooklyn NY 11214",
    "addr:housenumber":"1678",
    "addr:postcode":"11214",
    "addr:street":"85Th St",
    "iso:country":"US",
    "sg:address":"1678 85th St",
    "sg:city":"Brooklyn",
    "sg:classifiers":[
        {
            "category":"Utilities",
            "subcategory":"Telephone",
            "type":"Services"
        }
    ],
    "sg:phone":"+1   ",
    "sg:postcode":"11214",
    "sg:province":"NY",
    "sg:tags":[
        "communications"
    ],
    "wof:name":"Collin Jouve Productions",
    "wof:placetype":"venue"
},
  "geometry": {"coordinates":[-74.005758,40.610319],"type":"Point"}
}