{
  "type": "Feature",
  "properties": {
    "addr:full":"69-15 Yellowstone Blvd Ste 3 Forest Hills NY 11375",
    "addr:housenumber":"69-15",
    "addr:postcode":"11375",
    "addr:street":"Yellowstone Blvd Ste 3",
    "iso:country":"US",
    "sg:address":"69-15 Yellowstone Blvd Ste 3",
    "sg:city":"Forest Hills",
    "sg:classifiers":[
        {
            "category":"Health Services",
            "subcategory":"Doctor",
            "type":"Services"
        }
    ],
    "sg:phone":"+1 718 275 7200",
    "sg:postcode":"11375",
    "sg:province":"NY",
    "sg:tags":[
        "obstetrician",
        "gynecologist"
    ],
    "sg:website":"www.drhesselmd.com/",
    "wof:name":"Hessel Barbara",
    "wof:placetype":"venue"
},
  "geometry": {"coordinates":[-73.846627,40.724193],"type":"Point"}
}