{
  "type": "Feature",
  "properties": {
    "iso:country":"US",
    "sg:address":"1322 Gravesend Neck Road",
    "sg:city":"Brooklyn",
    "sg:classifiers":[
        {
            "category":"Professional",
            "subcategory":"Lawyer & Legal Services",
            "type":"Services"
        }
    ],
    "sg:phone":"+1 718 743 6611",
    "sg:postcode":"11229",
    "sg:province":"NY",
    "wof:name":"Vaiman Irina P ESQ",
    "wof:placetype":"venue"
},
  "geometry": {"coordinates":[-73.956844,40.594472],"type":"Point"}
}