{
  "type": "Feature",
  "properties": {
    "addr:full":"8606 Ave L Brooklyn NY 11236",
    "addr:housenumber":"8606",
    "addr:postcode":"11236",
    "addr:street":"Ave L",
    "iso:country":"US",
    "sg:address":"8606 Ave L",
    "sg:city":"Brooklyn",
    "sg:classifiers":[
        {
            "category":"Real Estate",
            "subcategory":"Real Estate Agent",
            "type":"Services"
        }
    ],
    "sg:phone":"+1 718 241 0811",
    "sg:postcode":"11236",
    "sg:province":"NY",
    "wof:name":"JAH Management Inc",
    "wof:placetype":"venue"
},
  "geometry": {"coordinates":[-73.90267799999999,40.633809],"type":"Point"}
}