{
  "type": "Feature",
  "properties": {
    "addr:full":"5845 W Lake Rd Conesus NY 14435",
    "addr:housenumber":"5845",
    "addr:postcode":"14435",
    "addr:street":"W Lake Rd",
    "iso:country":"US",
    "sg:address":"5845 W Lake Rd",
    "sg:city":"Conesus",
    "sg:classifiers":[
        {
            "category":"Real Estate",
            "subcategory":"Real Estate Agent",
            "type":"Services"
        }
    ],
    "sg:phone":"+1 585 243 2716",
    "sg:postcode":"14435",
    "sg:province":"NY",
    "wof:name":"Carolyn Schwan Keogh Plan",
    "wof:placetype":"venue"
},
  "geometry": {"coordinates":[-77.72483699999999,42.735416],"type":"Point"}
}