{
  "type": "Feature",
  "properties": {
    "addr:full":"2062 Grand Ave Bronx NY 10453",
    "addr:housenumber":"2062",
    "addr:postcode":"10453",
    "addr:street":"Grand Ave",
    "iso:country":"US",
    "sg:address":"2062 Grand Ave",
    "sg:city":"Bronx",
    "sg:classifiers":[
        {
            "category":"Social Services",
            "subcategory":"Child Care",
            "type":"Services"
        }
    ],
    "sg:phone":"+1   ",
    "sg:postcode":"10453",
    "sg:province":"NY",
    "sg:tags":[
        "day"
    ],
    "wof:name":"Busy Bee Family Day Care",
    "wof:placetype":"venue"
},
  "geometry": {"coordinates":[-73.908722,40.854479],"type":"Point"}
}