{
  "type": "Feature",
  "properties": {
    "iso:country":"US",
    "sg:address":"32 Smith St",
    "sg:city":"Rockville Centre",
    "sg:classifiers":[
        {
            "category":"Professional",
            "subcategory":"Business Services",
            "type":"Services"
        }
    ],
    "sg:phone":"+1 516 678 3173",
    "sg:postcode":"11570",
    "sg:province":"NY",
    "sg:tags":[
        "inspection"
    ],
    "wof:name":"Lorix Inspection Svc",
    "wof:placetype":"venue"
},
  "geometry": {"coordinates":[-73.64449399999999,40.653462],"type":"Point"}
}