{
  "type": "Feature",
  "properties": {
    "addr:full":"171 Sheridan Ave Brooklyn NY 11208",
    "addr:housenumber":"171",
    "addr:postcode":"11208",
    "addr:street":"Sheridan Ave",
    "iso:country":"US",
    "sg:address":"171 Sheridan Ave",
    "sg:city":"Brooklyn",
    "sg:classifiers":[
        {
            "category":"Shopping",
            "subcategory":"News",
            "type":"Retail Goods"
        }
    ],
    "sg:phone":"+1 718 647 8141",
    "sg:postcode":"11208",
    "sg:province":"NY",
    "sg:tags":[
        "dealer"
    ],
    "wof:name":"Chino's Newsstand",
    "wof:placetype":"venue"
},
  "geometry": {"coordinates":[-73.866676,40.677754],"type":"Point"}
}