{
  "type": "Feature",
  "properties": {
    "addr:full":"349 William Floyd Pkwy Shirley NY 11967",
    "addr:housenumber":"349",
    "addr:postcode":"11967",
    "addr:street":"William Floyd Pkwy",
    "iso:country":"US",
    "sg:address":"349 William Floyd Pkwy",
    "sg:city":"Shirley",
    "sg:classifiers":[
        {
            "category":"Sports & Exercise",
            "subcategory":"Gym",
            "type":"Entertainment"
        }
    ],
    "sg:phone":"+1 631 399 9464",
    "sg:postcode":"11967",
    "sg:province":"NY",
    "wof:name":"Lucille Roberts Health Club Store",
    "wof:placetype":"venue"
},
  "geometry": {"coordinates":[-72.87200199999999,40.7579],"type":"Point"}
}