{
  "type": "Feature",
  "properties": {
    "addr:full":"467 Virginia St Buffalo NY 14202",
    "addr:housenumber":"467",
    "addr:postcode":"14202",
    "addr:street":"Virginia St",
    "iso:country":"US",
    "sg:address":"467 Virginia St",
    "sg:city":"Buffalo",
    "sg:classifiers":[
        {
            "category":"Organizations",
            "subcategory":"Labor Organization",
            "type":"Services"
        }
    ],
    "sg:phone":"+1 800 491 1990",
    "sg:postcode":"14202",
    "sg:province":"NY",
    "sg:tags":[
        "employee",
        "assistance",
        "program"
    ],
    "wof:name":"Employee Resources Inc Toll Free-Dial '1' & Then",
    "wof:placetype":"venue"
},
  "geometry": {"coordinates":[-78.87424900000001,42.896824],"type":"Point"}
}