{
  "type": "Feature",
  "properties": {
    "addr:full":"402 Balltown Rd Schenectady NY 12304",
    "addr:housenumber":"402",
    "addr:postcode":"12304",
    "addr:street":"Balltown Rd",
    "iso:country":"US",
    "sg:address":"402 Balltown Rd",
    "sg:city":"Schenectady",
    "sg:classifiers":[
        {
            "category":"Shopping",
            "subcategory":"Gifts & Souvenirs",
            "type":"Retail Goods"
        }
    ],
    "sg:phone":"+1 518 370 4400",
    "sg:postcode":"12304",
    "sg:province":"NY",
    "sg:tags":[
        "party",
        "supply"
    ],
    "sg:website":"www.partycity.com",
    "wof:name":"Party City",
    "wof:placetype":"venue"
},
  "geometry": {"coordinates":[-73.89335699999999,42.772595],"type":"Point"}
}