{
  "type": "Feature",
  "properties": {
    "iso:country":"US",
    "sg:address":"875 Elmwood Ave",
    "sg:city":"Buffalo",
    "sg:classifiers":[
        {
            "category":"Social Services",
            "subcategory":"Child Care",
            "type":"Services"
        },
        {
            "category":"Real Estate",
            "subcategory":"Developer",
            "type":"Services"
        },
        {
            "category":"Education",
            "subcategory":"School",
            "type":"Public Place"
        }
    ],
    "sg:phone":"+1 716 886 5857",
    "sg:postcode":"14222",
    "sg:province":"NY",
    "sg:tags":[
        "day"
    ],
    "wof:name":"Language Development Program of Wny Inc",
    "wof:placetype":"venue"
},
  "geometry": {"coordinates":[-78.877296,42.921101],"type":"Point"}
}