{
  "type": "Feature",
  "properties": {
    "addr:full":"36 Main St Ste C Lockport NY 14094",
    "addr:housenumber":"36",
    "addr:postcode":"14094",
    "addr:street":"Main St Ste C",
    "iso:country":"US",
    "sg:address":"36 Main St Ste C",
    "sg:city":"Lockport",
    "sg:classifiers":[
        {
            "category":"Professional",
            "subcategory":"Accounting & Tax Preparation",
            "type":"Services"
        },
        {
            "category":"Banks & Credit Unions",
            "subcategory":"Financial Services",
            "type":"Services"
        }
    ],
    "sg:phone":"+1 716 438 3749",
    "sg:postcode":"14094",
    "sg:province":"NY",
    "sg:tags":[
        "return",
        "preparation-business",
        "taxes-consultants",
        "loan",
        "reporting",
        "representative",
        "alternative",
        "bookkeeping"
    ],
    "sg:website":"http://www.hrblock.com",
    "wof:name":"H&R Block",
    "wof:placetype":"venue"
},
  "geometry": {"coordinates":[-78.692886,43.169785],"type":"Point"}
}