{
  "type": "Feature",
  "properties": {
    "addr:full":"174 W Fordham Rd Bronx NY 10468",
    "addr:housenumber":"174",
    "addr:postcode":"10468",
    "addr:street":"W Fordham Rd",
    "iso:country":"US",
    "sg:address":"174 W Fordham Rd",
    "sg:city":"Bronx",
    "sg:classifiers":[
        {
            "category":"Shopping",
            "subcategory":"Gifts & Souvenirs",
            "type":"Retail Goods"
        }
    ],
    "sg:phone":"+1 718 733 9730",
    "sg:postcode":"10468",
    "sg:province":"NY",
    "sg:tags":[
        "shop"
    ],
    "wof:name":"Hing Loon Gift Shop",
    "wof:placetype":"venue"
},
  "geometry": {"coordinates":[-73.90837000000001,40.862686],"type":"Point"}
}