{
  "type": "Feature",
  "properties": {
    "iso:country":"US",
    "sg:address":"7546 Glencrest Ave",
    "sg:city":"Liverpool",
    "sg:classifiers":[
        {
            "category":"Manufacturing",
            "subcategory":"Metals",
            "type":"Manufacturing & Wholesale Goods"
        }
    ],
    "sg:phone":"+1   ",
    "sg:postcode":"13088",
    "sg:province":"NY",
    "sg:tags":[
        "product",
        "fabricated",
        "lead",
        "mfg"
    ],
    "wof:name":"K & L Associates",
    "wof:placetype":"venue"
},
  "geometry": {"coordinates":[-76.18140699999999,43.133894],"type":"Point"}
}