{
  "type": "Feature",
  "properties": {
    "iso:country":"US",
    "sg:address":"136 Hill Rd",
    "sg:city":"Copake",
    "sg:classifiers":[
        {
            "category":"Farming",
            "subcategory":"Dairy Farm",
            "type":"Manufacturing & Wholesale Goods"
        }
    ],
    "sg:phone":"+1 518 329 4174",
    "sg:postcode":"12534",
    "sg:province":"NY",
    "wof:name":"Dolltate",
    "wof:placetype":"venue"
},
  "geometry": {"coordinates":[-73.738034,42.286482],"type":"Point"}
}