{
  "type": "Feature",
  "properties": {
    "iso:country":"US",
    "sg:address":"767 3rd Ave",
    "sg:city":"New York",
    "sg:classifiers":[
        {
            "category":"Professional",
            "subcategory":"Lawyer & Legal Services",
            "type":"Services"
        }
    ],
    "sg:phone":"+1 212 486 7800",
    "sg:postcode":"10017",
    "sg:province":"NY",
    "wof:name":"Taylor Elizabeth M Atty",
    "wof:placetype":"venue"
},
  "geometry": {"coordinates":[-73.97170300000001,40.754299],"type":"Point"}
}