{
  "type": "Feature",
  "properties": {
    "addr:full":"95 W End Ave New York NY 10023",
    "addr:housenumber":"95",
    "addr:postcode":"10023",
    "addr:street":"W End Ave",
    "iso:country":"US",
    "sg:address":"95 W End Ave",
    "sg:city":"New York",
    "sg:classifiers":[
        {
            "category":"Retail",
            "subcategory":"Auto Repair",
            "type":"Services"
        }
    ],
    "sg:phone":"+1 917 210 5431",
    "sg:postcode":"10023",
    "sg:province":"NY",
    "sg:tags":[
        "wrecker"
    ],
    "wof:name":"Loonee 24 Hr Tow",
    "wof:placetype":"venue"
},
  "geometry": {"coordinates":[-73.988551,40.774217],"type":"Point"}
}