{
  "type": "Feature",
  "properties": {
    "addr:full":"4344 40th St Sunnyside NY 11104",
    "addr:housenumber":"4344",
    "addr:postcode":"11104",
    "addr:street":"40Th St",
    "iso:country":"US",
    "sg:address":"4344 40th St",
    "sg:city":"Sunnyside",
    "sg:classifiers":[
        {
            "category":"Personal",
            "subcategory":"Beauty Salon",
            "type":"Services"
        }
    ],
    "sg:phone":"+1 718 729 8384",
    "sg:postcode":"11104",
    "sg:province":"NY",
    "sg:tags":[
        "hair",
        "stylist"
    ],
    "wof:name":"Jolre Hair Studio Inc.",
    "wof:placetype":"venue"
},
  "geometry": {"coordinates":[-73.92424800000001,40.743885],"type":"Point"}
}