{
  "type": "Feature",
  "properties": {
    "iso:country":"US",
    "sg:address":"560 W 34th St",
    "sg:city":"New York",
    "sg:classifiers":[
        {
            "category":"Restaurant",
            "type":"Food & Drink"
        }
    ],
    "sg:phone":"+1 212 239 2672",
    "sg:postcode":"10001",
    "sg:province":"NY",
    "sg:website":"www.copacabanany.com",
    "wof:name":"Copa Cabana",
    "wof:placetype":"venue"
},
  "geometry": {"coordinates":[-74.00063,40.755114],"type":"Point"}
}