{
  "type": "Feature",
  "properties": {
    "addr:full":"185 Madison Ave New York NY 10016",
    "addr:housenumber":"185",
    "addr:postcode":"10016",
    "addr:street":"Madison Ave",
    "iso:country":"US",
    "sg:address":"185 Madison Ave",
    "sg:city":"New York",
    "sg:classifiers":[
        {
            "category":"Professional",
            "subcategory":"Lawyer & Legal Services",
            "type":"Services"
        }
    ],
    "sg:phone":"+1 212 447 6202",
    "sg:postcode":"10016",
    "sg:province":"NY",
    "sg:tags":[
        "attorney"
    ],
    "sg:website":"www.247agents.com",
    "wof:name":"Mitchell A Dix & Assoc",
    "wof:placetype":"venue"
},
  "geometry": {"coordinates":[-73.982473,40.748432],"type":"Point"}
}