{
  "type": "Feature",
  "properties": {
    "iso:country":"US",
    "sg:address":"10 Cuttermill Rd",
    "sg:city":"Great Neck",
    "sg:classifiers":[
        {
            "category":"Professional",
            "subcategory":"Lawyer & Legal Services",
            "type":"Services"
        }
    ],
    "sg:phone":"+1 516 829 7190",
    "sg:postcode":"11021",
    "sg:province":"NY",
    "sg:tags":[
        "attorney"
    ],
    "wof:name":"Bernard Bronner Law Offices",
    "wof:placetype":"venue"
},
  "geometry": {"coordinates":[-73.728702,40.7867],"type":"Point"}
}