{
  "type": "Feature",
  "properties": {
    "addr:full":"243 W 30 St New York NY 10001",
    "addr:housenumber":"243",
    "addr:postcode":"10001",
    "addr:street":"W 30 St",
    "iso:country":"US",
    "sg:address":"243 W 30 St",
    "sg:city":"New York",
    "sg:classifiers":[
        {
            "category":"Building & Trades",
            "subcategory":"Cleaning & Sanitation",
            "type":"Services"
        }
    ],
    "sg:phone":"+1 212 594 0585",
    "sg:postcode":"10001",
    "sg:province":"NY",
    "sg:tags":[
        "commercial"
    ],
    "wof:name":"A Better Envmt Bldg Maint",
    "wof:placetype":"venue"
},
  "geometry": {"coordinates":[-73.994342,40.749221],"type":"Point"}
}