{
  "type": "Feature",
  "properties": {
    "iso:country":"US",
    "sg:address":"400 Ridge Rd W",
    "sg:city":"Rochester",
    "sg:classifiers":[
        {
            "category":"Restaurant",
            "type":"Food & Drink"
        }
    ],
    "sg:menulink":"http://www.allmenus.com/ny/rochester/3853-princess-restaurant-2/menu/",
    "sg:phone":"+1 585 621 3335",
    "sg:postcode":"14615",
    "sg:province":"NY",
    "sg:tags":[
        "american"
    ],
    "wof:name":"Princess Restaurant 2",
    "wof:placetype":"venue"
},
  "geometry": {"coordinates":[-77.637573,43.199948],"type":"Point"}
}