{
  "type": "Feature",
  "properties": {
    "addr:full":"134 5th Ave New York NY 10011",
    "addr:housenumber":"134",
    "addr:postcode":"10011",
    "addr:street":"5Th Ave",
    "iso:country":"US",
    "sg:address":"134 5th Ave",
    "sg:city":"New York",
    "sg:classifiers":[
        {
            "category":"Professional",
            "subcategory":"Computer Services",
            "type":"Services"
        }
    ],
    "sg:phone":"+1 212 627 4981",
    "sg:postcode":"10011",
    "sg:province":"NY",
    "sg:tags":[
        "internet"
    ],
    "wof:name":"Forman Interactive Corp",
    "wof:placetype":"venue"
},
  "geometry": {"coordinates":[-73.99137399999999,40.739087],"type":"Point"}
}