{
  "type": "Feature",
  "properties": {
    "addr:full":"76 Menahan St Brooklyn NY 11221",
    "addr:housenumber":"76",
    "addr:postcode":"11221",
    "addr:street":"Menahan St",
    "iso:country":"US",
    "sg:address":"76 Menahan St",
    "sg:city":"Brooklyn",
    "sg:classifiers":[
        {
            "category":"Building & Trades",
            "subcategory":"Construction",
            "type":"Services"
        }
    ],
    "sg:phone":"+1 718 455 7160",
    "sg:postcode":"11221",
    "sg:province":"NY",
    "sg:tags":[
        "hanging",
        "contractor"
    ],
    "wof:name":"Panama Taping & Painting Co",
    "wof:placetype":"venue"
},
  "geometry": {"coordinates":[-73.920828,40.693937],"type":"Point"}
}