{
  "type": "Feature",
  "properties": {
    "addr:full":"10 W 46th St Ste 1409 New York NY 10036",
    "addr:housenumber":"10",
    "addr:postcode":"10036",
    "addr:street":"W 46Th St Ste 1409",
    "iso:country":"US",
    "sg:address":"10 W 46th St Ste 1409",
    "sg:city":"New York",
    "sg:classifiers":[
        {
            "category":"Shopping",
            "subcategory":"Hobbies, Toys, & Games",
            "type":"Retail Goods"
        }
    ],
    "sg:phone":"+1 212 593 1168",
    "sg:postcode":"10036",
    "sg:province":"NY",
    "sg:tags":[
        "shop",
        "hobby"
    ],
    "wof:name":"M G Trading International Ltd",
    "wof:placetype":"venue"
},
  "geometry": {"coordinates":[-73.980071,40.756226],"type":"Point"}
}