{
  "type": "Feature",
  "properties": {
    "iso:country":"US",
    "sg:address":"172 S Main St",
    "sg:city":"Florida",
    "sg:classifiers":[
        {
            "category":"Personal",
            "subcategory":"Beauty Salon",
            "type":"Services"
        }
    ],
    "sg:phone":"+1 845 651 7350",
    "sg:postcode":"10921",
    "sg:province":"NY",
    "wof:name":"Linda's Beauty Salon",
    "wof:placetype":"venue"
},
  "geometry": {"coordinates":[-74.352637,41.320243],"type":"Point"}
}