{
  "type": "Feature",
  "properties": {
    "iso:country":"US",
    "sg:address":"1 Riverdale Ave",
    "sg:city":"Bronx",
    "sg:classifiers":[
        {
            "category":"Manufacturing",
            "subcategory":"Printing",
            "type":"Manufacturing & Wholesale Goods"
        }
    ],
    "sg:phone":"+1   ",
    "sg:postcode":"10463",
    "sg:province":"NY",
    "sg:tags":[
        "supply"
    ],
    "wof:name":"All Printing Inc",
    "wof:placetype":"venue"
},
  "geometry": {"coordinates":[-73.910185,40.880705],"type":"Point"}
}