{
  "type": "Feature",
  "properties": {
    "addr:full":"116 Jackson Ave Syosset NY 11743",
    "addr:housenumber":"116",
    "addr:postcode":"11743",
    "addr:street":"Jackson Ave",
    "iso:country":"US",
    "sg:address":"116 Jackson Ave",
    "sg:city":"Syosset",
    "sg:classifiers":[
        {
            "category":"Professional",
            "subcategory":"Lawyer & Legal Services",
            "type":"Services"
        }
    ],
    "sg:phone":"+1   ",
    "sg:postcode":"11743",
    "sg:province":"NY",
    "wof:name":"Coschignano Chris J",
    "wof:placetype":"venue"
},
  "geometry": {"coordinates":[-73.41627699999999,40.871375],"type":"Point"}
}