{
  "type": "Feature",
  "properties": {
    "addr:full":"585 Rogers Ave Brooklyn NY 11225",
    "addr:housenumber":"585",
    "addr:postcode":"11225",
    "addr:street":"Rogers Ave",
    "iso:country":"US",
    "sg:address":"585 Rogers Ave",
    "sg:city":"Brooklyn",
    "sg:classifiers":[
        {
            "category":"Professional",
            "subcategory":"Printing & Photocopies",
            "type":"Services"
        }
    ],
    "sg:phone":"+1   ",
    "sg:postcode":"11225",
    "sg:province":"NY",
    "sg:tags":[
        "photocopying"
    ],
    "wof:name":"Anzouma Bailo",
    "wof:placetype":"venue"
},
  "geometry": {"coordinates":[-73.95308,40.657108],"type":"Point"}
}