{
  "type": "Feature",
  "properties": {
    "iso:country":"US",
    "sg:address":"7 Huron Rd",
    "sg:city":"Floral Park",
    "sg:classifiers":[
        {
            "category":"Professional",
            "subcategory":"Management & Consulting",
            "type":"Services"
        }
    ],
    "sg:phone":"+1   ",
    "sg:postcode":"11001",
    "sg:province":"NY",
    "wof:name":"Consurve LLC",
    "wof:placetype":"venue"
},
  "geometry": {"coordinates":[-73.720895,40.724509],"type":"Point"}
}