{
  "type": "Feature",
  "properties": {
    "iso:country":"US",
    "sg:address":"101 Hitchcock Dr",
    "sg:city":"Depew",
    "sg:classifiers":[
        {
            "category":"Real Estate",
            "subcategory":"Real Estate Services",
            "type":"Services"
        },
        {
            "category":"Real Estate",
            "subcategory":"Surveying",
            "type":"Services"
        }
    ],
    "sg:phone":"+1 716 684 7157",
    "sg:postcode":"14043",
    "sg:province":"NY",
    "sg:tags":[
        "industrial",
        "appraisers-commercial",
        "appraiser"
    ],
    "wof:name":"Hampton Brook Appraisal & Real Estate",
    "wof:placetype":"venue"
},
  "geometry": {"coordinates":[-78.71093399999999,42.890308],"type":"Point"}
}