{
  "type": "Feature",
  "properties": {
    "addr:full":"2713 State Hwy 17M New Hampton NY 10958",
    "addr:housenumber":"2713",
    "addr:postcode":"10958",
    "addr:street":"State Hwy",
    "iso:country":"US",
    "sg:address":"2713 State Hwy 17M",
    "sg:city":"New Hampton",
    "sg:classifiers":[
        {
            "category":"Building & Trades",
            "subcategory":"Construction",
            "type":"Services"
        }
    ],
    "sg:phone":"+1 845 294 8242",
    "sg:postcode":"10958",
    "sg:province":"NY",
    "sg:tags":[
        "house",
        "general",
        "family",
        "contractor"
    ],
    "wof:name":"Ferrante Homes",
    "wof:placetype":"venue"
},
  "geometry": {"coordinates":[-74.38346300000001,41.399271],"type":"Point"}
}