{
  "type": "Feature",
  "properties": {
    "iso:country":"US",
    "sg:address":"35 Walden Ave",
    "sg:city":"Buffalo",
    "sg:classifiers":[
        {
            "category":"Shopping",
            "subcategory":"Clothing, Apparel, & Fashions",
            "type":"Retail Goods"
        }
    ],
    "sg:phone":"+1 716 651 1010",
    "sg:postcode":"14225",
    "sg:province":"NY",
    "sg:website":"www.delias.com",
    "wof:name":"Delias",
    "wof:placetype":"venue"
},
  "geometry": {"coordinates":[-78.83479800000001,42.903602],"type":"Point"}
}