{
  "type": "Feature",
  "properties": {
    "iso:country":"US",
    "sg:address":"4 Highland Ave",
    "sg:city":"Glens Falls",
    "sg:classifiers":[
        {
            "category":"Retail",
            "subcategory":"Auto Repair",
            "type":"Services"
        }
    ],
    "sg:phone":"+1 518 792 0316",
    "sg:postcode":"12804",
    "sg:province":"NY",
    "sg:tags":[
        "repairing",
        "automobile"
    ],
    "wof:name":"Warren Tire Svc Ctr Inc",
    "wof:placetype":"venue"
},
  "geometry": {"coordinates":[-73.60785300000001,43.314893],"type":"Point"}
}