{
  "type": "Feature",
  "properties": {
    "addr:full":"75 W Mosholu Pkwy N 4C Bronx NY 10467",
    "addr:housenumber":"75;4c",
    "addr:postcode":"10467",
    "addr:street":"W Mosholu Pkwy N",
    "iso:country":"US",
    "sg:address":"75 W Mosholu Pkwy N 4C",
    "sg:city":"Bronx",
    "sg:classifiers":[
        {
            "category":"Arts & Performance",
            "subcategory":"Theater",
            "type":"Entertainment"
        }
    ],
    "sg:phone":"+1 718 882 2454",
    "sg:postcode":"10467",
    "sg:province":"NY",
    "sg:tags":[
        "theatrical",
        "manager",
        "producer"
    ],
    "wof:name":"Mass Transit Street Theater, Inc.",
    "wof:placetype":"venue"
},
  "geometry": {"coordinates":[-73.885136,40.882873],"type":"Point"}
}