{
  "type": "Feature",
  "properties": {
    "iso:country":"US",
    "sg:address":"1137 Washington Avenue",
    "sg:city":"Brooklyn",
    "sg:classifiers":[
        {
            "category":"Restaurant",
            "type":"Food & Drink"
        }
    ],
    "sg:phone":"+1 718 693 6163",
    "sg:postcode":"11225",
    "sg:province":"NY",
    "sg:tags":[
        "chinese"
    ],
    "wof:name":"New Peking Restaurant",
    "wof:placetype":"venue"
},
  "geometry": {"coordinates":[-73.960559,40.661066],"type":"Point"}
}