{
  "type": "Feature",
  "properties": {
    "addr:full":"3 Crooked Hill Rd Commack NY 11725",
    "addr:housenumber":"3",
    "addr:postcode":"11725",
    "addr:street":"Crooked Hill Rd",
    "iso:country":"US",
    "sg:address":"3 Crooked Hill Rd",
    "sg:city":"Commack",
    "sg:classifiers":[
        {
            "category":"Shopping",
            "subcategory":"Bridal",
            "type":"Retail Goods"
        }
    ],
    "sg:phone":"+1 631 543 6898",
    "sg:postcode":"11725",
    "sg:province":"NY",
    "wof:name":"The Wedding Center",
    "wof:placetype":"venue"
},
  "geometry": {"coordinates":[-73.288399,40.805599],"type":"Point"}
}