{
  "type": "Feature",
  "properties": {
    "addr:full":"222 E 39th St Brooklyn NY 11203",
    "addr:housenumber":"222",
    "addr:postcode":"11203",
    "addr:street":"E 39Th St",
    "iso:country":"US",
    "sg:address":"222 E 39th St",
    "sg:city":"Brooklyn",
    "sg:classifiers":[
        {
            "category":"Building & Trades",
            "subcategory":"Construction",
            "type":"Services"
        }
    ],
    "sg:phone":"+1 718 484 8104",
    "sg:postcode":"11203",
    "sg:province":"NY",
    "sg:tags":[
        "contractor"
    ],
    "wof:name":"Speldid Home Construction",
    "wof:placetype":"venue"
},
  "geometry": {"coordinates":[-73.94119600000001,40.65188],"type":"Point"}
}