{
  "type": "Feature",
  "properties": {
    "iso:country":"US",
    "sg:address":"5135 Merrick Rd",
    "sg:city":"Massapequa Park",
    "sg:classifiers":[
        {
            "category":"Home & Garden",
            "subcategory":"Hardware",
            "type":"Retail Goods"
        }
    ],
    "sg:phone":"+1 516 798 5757",
    "sg:postcode":"11762",
    "sg:province":"NY",
    "sg:website":"www.acehardware.com",
    "wof:name":"Ace Hardware",
    "wof:placetype":"venue"
},
  "geometry": {"coordinates":[-73.446549,40.666346],"type":"Point"}
}