{
  "type": "Feature",
  "properties": {
    "addr:full":"2130 Nesconset Hwy Lake Grove NY 11755",
    "addr:postcode":"2130;11755",
    "addr:street":"Nesconset Hwy",
    "iso:country":"US",
    "sg:address":"2130 Nesconset Hwy",
    "sg:city":"Lake Grove",
    "sg:classifiers":[
        {
            "category":"Shopping",
            "subcategory":"Music",
            "type":"Retail Goods"
        }
    ],
    "sg:phone":"+1 631 979 0500",
    "sg:postcode":"11755",
    "sg:province":"NY",
    "sg:tags":[
        "dvd's"
    ],
    "wof:name":"Borders Books Music & Cafe",
    "wof:placetype":"venue"
},
  "geometry": {"coordinates":[-73.135902,40.865898],"type":"Point"}
}