{
  "type": "Feature",
  "properties": {
    "addr:full":"10848 70th Rd Forest Hills NY 11375",
    "addr:housenumber":"10848",
    "addr:postcode":"11375",
    "addr:street":"70Th Rd",
    "iso:country":"US",
    "sg:address":"10848 70th Rd",
    "sg:city":"Forest Hills",
    "sg:classifiers":[
        {
            "category":"Health Services",
            "subcategory":"Doctor",
            "type":"Services"
        }
    ],
    "sg:phone":"+1 718 520 1520",
    "sg:postcode":"11375",
    "sg:province":"NY",
    "sg:tags":[
        "obstetrician",
        "gynecologist"
    ],
    "wof:name":"Cholakian Ohanes MD",
    "wof:placetype":"venue"
},
  "geometry": {"coordinates":[-73.843498,40.722401],"type":"Point"}
}