{
  "type": "Feature",
  "properties": {
    "addr:full":"86 Evans St Staten Island NY 10314",
    "addr:housenumber":"86",
    "addr:postcode":"10314",
    "addr:street":"Evans St",
    "iso:country":"US",
    "sg:address":"86 Evans St",
    "sg:city":"Staten Island",
    "sg:classifiers":[
        {
            "category":"Building & Trades",
            "subcategory":"Construction",
            "type":"Services"
        }
    ],
    "sg:phone":"+1 718 351 8186",
    "sg:postcode":"10314",
    "sg:province":"NY",
    "sg:tags":[
        "residential"
    ],
    "wof:name":"Charles McGrath Construction",
    "wof:placetype":"venue"
},
  "geometry": {"coordinates":[-74.150719,40.586898],"type":"Point"}
}