{
  "type": "Feature",
  "properties": {
    "addr:full":"37 Pelton Ave Staten Island NY 10310",
    "addr:housenumber":"37",
    "addr:postcode":"10310",
    "addr:street":"Pelton Ave",
    "iso:country":"US",
    "sg:address":"37 Pelton Ave",
    "sg:city":"Staten Island",
    "sg:classifiers":[
        {
            "category":"Shopping",
            "type":"Retail Goods"
        }
    ],
    "sg:phone":"+1   ",
    "sg:postcode":"10310",
    "sg:province":"NY",
    "sg:tags":[
        "merchandise"
    ],
    "wof:name":"Charting Your Course",
    "wof:placetype":"venue"
},
  "geometry": {"coordinates":[-74.111717,40.642644],"type":"Point"}
}