{
  "type": "Feature",
  "properties": {
    "iso:country":"US",
    "sg:address":"109 Main St",
    "sg:city":"Port Jefferson Station",
    "sg:classifiers":[
        {
            "category":"Restaurant",
            "type":"Food & Drink"
        }
    ],
    "sg:phone":"+1   ",
    "sg:postcode":"11776",
    "sg:province":"NY",
    "sg:tags":[
        "eating"
    ],
    "wof:name":"Love That Pizza",
    "wof:placetype":"venue"
},
  "geometry": {"coordinates":[-73.053725,40.933448],"type":"Point"}
}