{
  "type": "Feature",
  "properties": {
    "addr:full":"1 Orchard St Spring Valley NY 10977",
    "addr:housenumber":"1",
    "addr:postcode":"10977",
    "addr:street":"Orchard St",
    "iso:country":"US",
    "sg:address":"1 Orchard St",
    "sg:city":"Spring Valley",
    "sg:classifiers":[
        {
            "category":"Health Services",
            "subcategory":"Health Practitioner",
            "type":"Services"
        }
    ],
    "sg:phone":"+1 845 371 3055",
    "sg:postcode":"10977",
    "sg:province":"NY",
    "sg:tags":[
        "therapist",
        "physical"
    ],
    "wof:name":"Valley Medical Ctr",
    "wof:placetype":"venue"
},
  "geometry": {"coordinates":[-74.045101,41.126988],"type":"Point"}
}