{
  "type": "Feature",
  "properties": {
    "addr:full":"256 Beach 20th St Far Rockaway NY 11691",
    "addr:housenumber":"256",
    "addr:postcode":"11691",
    "addr:street":"Beach 20Th St",
    "iso:country":"US",
    "sg:address":"256 Beach 20th St",
    "sg:city":"Far Rockaway",
    "sg:classifiers":[
        {
            "category":"Health Services",
            "subcategory":"Doctor",
            "type":"Services"
        }
    ],
    "sg:phone":"+1 718 337 0533",
    "sg:postcode":"11691",
    "sg:province":"NY",
    "wof:name":"Azad A K MD",
    "wof:placetype":"venue"
},
  "geometry": {"coordinates":[-73.754097,40.597301],"type":"Point"}
}