{
  "type": "Feature",
  "properties": {
    "iso:country":"US",
    "sg:address":"33 First St",
    "sg:city":"South Dayton",
    "sg:classifiers":[
        {
            "category":"Building & Trades",
            "subcategory":"Construction",
            "type":"Services"
        }
    ],
    "sg:phone":"+1 716 988 3342",
    "sg:postcode":"14138",
    "sg:province":"NY",
    "sg:tags":[
        "marking",
        "maintenance",
        "parking"
    ],
    "wof:name":"South Dayton Public Works Dept",
    "wof:placetype":"venue"
},
  "geometry": {"coordinates":[-79.05251800000001,42.360294],"type":"Point"}
}