{
  "type": "Feature",
  "properties": {
    "addr:full":"115 W 29th St Rm 1104 New York NY 10001",
    "addr:housenumber":"115;1104",
    "addr:postcode":"10001",
    "addr:street":"W 29Th St",
    "iso:country":"US",
    "sg:address":"115 W 29th St Rm 1104",
    "sg:city":"New York",
    "sg:classifiers":[
        {
            "category":"Real Estate",
            "subcategory":"Architect",
            "type":"Services"
        }
    ],
    "sg:phone":"+1 212 695 9305",
    "sg:postcode":"10001",
    "sg:province":"NY",
    "sg:website":"www.studiolindfors.com",
    "wof:name":"Studio Lindfors",
    "wof:placetype":"venue"
},
  "geometry": {"coordinates":[-73.99039999999999,40.746966],"type":"Point"}
}