{
  "type": "Feature",
  "properties": {
    "iso:country":"US",
    "sg:address":"22 E 72 St",
    "sg:city":"New York",
    "sg:classifiers":[
        {
            "category":"Building & Trades",
            "subcategory":"Construction",
            "type":"Services"
        }
    ],
    "sg:phone":"+1 212 535 5905",
    "sg:postcode":"10021",
    "sg:province":"NY",
    "sg:tags":[
        "house",
        "hospital",
        "general"
    ],
    "wof:name":"Dormer-Lourence Medical Spa",
    "wof:placetype":"venue"
},
  "geometry": {"coordinates":[-73.966576,40.772334],"type":"Point"}
}