{
  "type": "Feature",
  "properties": {
    "addr:full":"5 W Main St Elmsford NY 10523",
    "addr:housenumber":"5",
    "addr:postcode":"10523",
    "addr:street":"W Main St",
    "iso:country":"US",
    "sg:address":"5 W Main St",
    "sg:city":"Elmsford",
    "sg:classifiers":[
        {
            "category":"Freight",
            "type":"Transportation"
        }
    ],
    "sg:phone":"+1 914 345 0795",
    "sg:postcode":"10523",
    "sg:province":"NY",
    "sg:tags":[
        "delivery"
    ],
    "wof:name":"Eddy Messenger Svc",
    "wof:placetype":"venue"
},
  "geometry": {"coordinates":[-73.81986499999999,41.054932],"type":"Point"}
}