{
  "type": "Feature",
  "properties": {
    "addr:full":"22 Oakcrest Dr Goshen NY 10924",
    "addr:housenumber":"22",
    "addr:postcode":"10924",
    "addr:street":"Oakcrest Dr",
    "iso:country":"US",
    "sg:address":"22 Oakcrest Dr",
    "sg:city":"Goshen",
    "sg:classifiers":[
        {
            "category":"Real Estate",
            "subcategory":"Real Estate Operator",
            "type":"Services"
        }
    ],
    "sg:phone":"+1 845 294 2602",
    "sg:postcode":"10924",
    "sg:province":"NY",
    "sg:tags":[
        "building",
        "nonresidential"
    ],
    "wof:name":"Tuo Girls",
    "wof:placetype":"venue"
},
  "geometry": {"coordinates":[-74.336983,41.406147],"type":"Point"}
}