{
  "type": "Feature",
  "properties": {
    "addr:full":"755 White Plains Rd Bronx NY 10473",
    "addr:housenumber":"755",
    "addr:postcode":"10473",
    "addr:street":"White Plains Rd",
    "iso:country":"US",
    "sg:address":"755 White Plains Rd",
    "sg:city":"Bronx",
    "sg:classifiers":[
        {
            "category":"Recreation",
            "type":"Entertainment"
        }
    ],
    "sg:phone":"+1 718 542 0238",
    "sg:postcode":"10473",
    "sg:province":"NY",
    "sg:tags":[
        "membership"
    ],
    "wof:name":"Nyjtl",
    "wof:placetype":"venue"
},
  "geometry": {"coordinates":[-73.858048,40.821042],"type":"Point"}
}