{
  "type": "Feature",
  "properties": {
    "addr:full":"255 Canterbury Rd Rochester NY 14607",
    "addr:housenumber":"255",
    "addr:postcode":"14607",
    "addr:street":"Canterbury Rd",
    "iso:country":"US",
    "sg:address":"255 Canterbury Rd",
    "sg:city":"Rochester",
    "sg:classifiers":[
        {
            "category":"Personal",
            "subcategory":"Barber",
            "type":"Services"
        }
    ],
    "sg:phone":"+1 585 461 5740",
    "sg:postcode":"14607",
    "sg:province":"NY",
    "wof:name":"Mens Room",
    "wof:placetype":"venue"
},
  "geometry": {"coordinates":[-77.57978799999999,43.143576],"type":"Point"}
}