{
  "type": "Feature",
  "properties": {
    "addr:full":"20 Clinton Ave Huntington NY 11743",
    "addr:housenumber":"20",
    "addr:postcode":"11743",
    "addr:street":"Clinton Ave",
    "iso:country":"US",
    "sg:address":"20 Clinton Ave",
    "sg:city":"Huntington",
    "sg:classifiers":[
        {
            "category":"Food & Beverages",
            "subcategory":"Specialty",
            "type":"Retail Goods"
        },
        {
            "category":"Coffee & Tea",
            "type":"Food & Drink"
        }
    ],
    "sg:menulink":"http://www.allmenus.com/ny/huntington/28697-classy-coffee/menu/",
    "sg:phone":"+1 631 421 5745",
    "sg:postcode":"11743",
    "sg:province":"NY",
    "sg:tags":[
        "tea",
        "coffee",
        "american"
    ],
    "wof:name":"Classy Coffee",
    "wof:placetype":"venue"
},
  "geometry": {"coordinates":[-73.42876800000001,40.8715],"type":"Point"}
}