{
  "type": "Feature",
  "properties": {
    "iso:country":"US",
    "sg:address":"9706 Church Ave",
    "sg:city":"Brooklyn",
    "sg:classifiers":[
        {
            "category":"Health Services",
            "subcategory":"Hospital",
            "type":"Services"
        }
    ],
    "sg:phone":"+1 718 240 5808",
    "sg:postcode":"11212",
    "sg:province":"NY",
    "wof:name":"Brookdale University Hospital & Medical",
    "wof:placetype":"venue"
},
  "geometry": {"coordinates":[-73.914486,40.656131],"type":"Point"}
}