{
  "type": "Feature",
  "properties": {
    "iso:country":"US",
    "sg:address":"3820 McKinley Pkwy",
    "sg:city":"Blasdell",
    "sg:classifiers":[
        {
            "category":"Food & Beverages",
            "subcategory":"Liquor & Beverages",
            "type":"Retail Goods"
        }
    ],
    "sg:phone":"+1 716 827 8277",
    "sg:postcode":"14219",
    "sg:province":"NY",
    "wof:name":"Mc Kinley Liquor",
    "wof:placetype":"venue"
},
  "geometry": {"coordinates":[-78.81133800000001,42.78187],"type":"Point"}
}