{
  "type": "Feature",
  "properties": {
    "addr:full":"598 Montauk Hwy East Moriches NY 11940",
    "addr:housenumber":"598",
    "addr:postcode":"11940",
    "addr:street":"Montauk Hwy East",
    "iso:country":"US",
    "sg:address":"598 Montauk Hwy",
    "sg:city":"East Moriches",
    "sg:classifiers":[
        {
            "category":"Shopping",
            "subcategory":"Florist",
            "type":"Retail Goods"
        }
    ],
    "sg:phone":"+1 631 878 0359",
    "sg:postcode":"11940",
    "sg:province":"NY",
    "wof:name":"Bailstone Florist & Nursery",
    "wof:placetype":"venue"
},
  "geometry": {"coordinates":[-72.769096,40.8013],"type":"Point"}
}