{
  "type": "Feature",
  "properties": {
    "addr:full":"4 Bensin Dr Melville NY 11747",
    "addr:housenumber":"4",
    "addr:postcode":"11747",
    "addr:street":"Bensin Dr",
    "iso:country":"US",
    "sg:address":"4 Bensin Dr",
    "sg:city":"Melville",
    "sg:classifiers":[
        {
            "category":"Wholesale",
            "subcategory":"Stationery",
            "type":"Manufacturing & Wholesale Goods"
        }
    ],
    "sg:phone":"+1 631 367 3922",
    "sg:postcode":"11747",
    "sg:province":"NY",
    "sg:tags":[
        "supply"
    ],
    "wof:name":"Viable Business Supplies",
    "wof:placetype":"venue"
},
  "geometry": {"coordinates":[-73.437005,40.787636],"type":"Point"}
}