{
  "type": "Feature",
  "properties": {
    "addr:full":"1512 Kings Hwy Brooklyn NY 11229",
    "addr:housenumber":"1512",
    "addr:postcode":"11229",
    "addr:street":"Kings Hwy",
    "iso:country":"US",
    "sg:address":"1512 Kings Hwy",
    "sg:city":"Brooklyn",
    "sg:classifiers":[
        {
            "category":"Retail",
            "subcategory":"Photofinishing",
            "type":"Services"
        }
    ],
    "sg:phone":"+1   ",
    "sg:postcode":"11229",
    "sg:province":"NY",
    "sg:tags":[
        "laboratory"
    ],
    "wof:name":"Red Rose Photo Lab Inc",
    "wof:placetype":"venue"
},
  "geometry": {"coordinates":[-73.957954,40.608796],"type":"Point"}
}