{
  "type": "Feature",
  "properties": {
    "iso:country":"US",
    "sg:address":"1894 State Highway 68",
    "sg:city":"Canton",
    "sg:classifiers":[
        {
            "category":"Government",
            "subcategory":"Office",
            "type":"Public Place"
        }
    ],
    "sg:phone":"+1 315 379 9192",
    "sg:postcode":"13617",
    "sg:province":"NY",
    "sg:tags":[
        "parish",
        "government-county"
    ],
    "sg:website":"http://www.co.st-lawrence.ny.us",
    "wof:name":"Cornell Cooperative Extension",
    "wof:placetype":"venue"
},
  "geometry": {"coordinates":[-75.093018,44.576661],"type":"Point"}
}