{
  "type": "Feature",
  "properties": {
    "iso:country":"US",
    "sg:address":"100 Lafayette St Frnt A",
    "sg:city":"New York",
    "sg:classifiers":[
        {
            "category":"Retail",
            "subcategory":"Portrait Studio",
            "type":"Services"
        }
    ],
    "sg:phone":"+1 212 966 9250",
    "sg:postcode":"10013",
    "sg:province":"NY",
    "sg:tags":[
        "photography",
        "store"
    ],
    "wof:name":"88 Images Photo Lab",
    "wof:placetype":"venue"
},
  "geometry": {"coordinates":[-73.86097700000001,40.832332],"type":"Point"}
}