{
  "type": "Feature",
  "properties": {
    "iso:country":"US",
    "sg:address":"531 Middle Neck Rd",
    "sg:city":"Great Neck",
    "sg:classifiers":[
        {
            "category":"Shopping",
            "subcategory":"Pharmacy",
            "type":"Retail Goods"
        }
    ],
    "sg:phone":"+1 516 482 4880",
    "sg:postcode":"11023",
    "sg:province":"NY",
    "sg:tags":[
        "store"
    ],
    "wof:name":"Century Middle Neck Pharmacy",
    "wof:placetype":"venue"
},
  "geometry": {"coordinates":[-73.735747,40.802078],"type":"Point"}
}