{
  "type": "Feature",
  "properties": {
    "addr:full":"1303 Sweets Corners Rd Penfield NY 14526",
    "addr:housenumber":"1303",
    "addr:postcode":"14526",
    "addr:street":"Sweets Corners Rd",
    "iso:country":"US",
    "sg:address":"1303 Sweets Corners Rd",
    "sg:city":"Penfield",
    "sg:classifiers":[
        {
            "category":"Farming",
            "subcategory":"Nursery",
            "type":"Manufacturing & Wholesale Goods"
        }
    ],
    "sg:phone":"+1 585 377 0522",
    "sg:postcode":"14526",
    "sg:province":"NY",
    "sg:tags":[
        "ornamental"
    ],
    "wof:name":"George Frank & Son Nursery",
    "wof:placetype":"venue"
},
  "geometry": {"coordinates":[-77.42997800000001,43.152782],"type":"Point"}
}