{
  "type": "Feature",
  "properties": {
    "addr:full":"405 Ocean Point Ave Cedarhurst NY 11516",
    "addr:housenumber":"405",
    "addr:postcode":"11516",
    "addr:street":"Ocean Point Ave",
    "iso:country":"US",
    "sg:address":"405 Ocean Point Ave",
    "sg:city":"Cedarhurst",
    "sg:classifiers":[
        {
            "category":"Organizations",
            "subcategory":"Membership Organization",
            "type":"Services"
        }
    ],
    "sg:phone":"+1 516 295 0670",
    "sg:postcode":"11516",
    "sg:province":"NY",
    "wof:name":"Rock & Wrap It Up Inc",
    "wof:placetype":"venue"
},
  "geometry": {"coordinates":[-73.72790000000001,40.62815],"type":"Point"}
}