{
  "type": "Feature",
  "properties": {
    "iso:country":"US",
    "sg:address":"151 W 30 St",
    "sg:city":"New York",
    "sg:classifiers":[
        {
            "category":"Professional",
            "subcategory":"Business Services",
            "type":"Services"
        }
    ],
    "sg:phone":"+1   ",
    "sg:postcode":"10001",
    "sg:province":"NY",
    "sg:tags":[
        "record",
        "distribution",
        "broadcasting",
        "radio"
    ],
    "wof:name":"King Biscuit Flower Hour Rec",
    "wof:placetype":"venue"
},
  "geometry": {"coordinates":[-73.991327,40.747926],"type":"Point"}
}