{
  "type": "Feature",
  "properties": {
    "addr:full":"9853 63rd Road Flushing NY 11374",
    "addr:housenumber":"9853",
    "addr:postcode":"11374",
    "addr:street":"63Rd Road",
    "iso:country":"US",
    "sg:address":"9853 63rd Road",
    "sg:city":"Flushing",
    "sg:classifiers":[
        {
            "category":"Building & Trades",
            "subcategory":"Locksmith",
            "type":"Services"
        }
    ],
    "sg:phone":"+1 718 807 3703",
    "sg:postcode":"11374",
    "sg:province":"NY",
    "sg:tags":[
        "key"
    ],
    "wof:name":"Certified Locksmith of Rego Park",
    "wof:placetype":"venue"
},
  "geometry": {"coordinates":[-73.85799299999999,40.732463],"type":"Point"}
}