{
  "type": "Feature",
  "properties": {
    "addr:full":"60 W 47th St New York NY 10036",
    "addr:housenumber":"60",
    "addr:postcode":"10036",
    "addr:street":"W 47Th St",
    "iso:country":"US",
    "sg:address":"60 W 47th St",
    "sg:city":"New York",
    "sg:classifiers":[
        {
            "category":"Shopping",
            "subcategory":"Jewelry",
            "type":"Retail Goods"
        }
    ],
    "sg:phone":"+1 212 391 6466",
    "sg:postcode":"10036",
    "sg:province":"NY",
    "wof:name":"Awad Jeweler",
    "wof:placetype":"venue"
},
  "geometry": {"coordinates":[-73.980964,40.757655],"type":"Point"}
}