{
  "type": "Feature",
  "properties": {
    "addr:full":"349 William Floyd Pkwy Shirley NY 11967",
    "addr:housenumber":"349",
    "addr:postcode":"11967",
    "addr:street":"William Floyd Pkwy",
    "iso:country":"US",
    "sg:address":"349 William Floyd Pkwy",
    "sg:city":"Shirley",
    "sg:classifiers":[
        {
            "category":"Home & Garden",
            "subcategory":"Furniture",
            "type":"Retail Goods"
        }
    ],
    "sg:phone":"+1 631 399 9001",
    "sg:postcode":"11967",
    "sg:province":"NY",
    "sg:tags":[
        "store"
    ],
    "wof:name":"Global Discount Furniture Inc",
    "wof:placetype":"venue"
},
  "geometry": {"coordinates":[-72.86756800000001,40.772806],"type":"Point"}
}