{
  "type": "Feature",
  "properties": {
    "addr:full":"37 W 26th St New York NY 10010",
    "addr:housenumber":"37",
    "addr:postcode":"10010",
    "addr:street":"W 26Th St",
    "iso:country":"US",
    "sg:address":"37 W 26th St",
    "sg:city":"New York",
    "sg:classifiers":[
        {
            "category":"Social Services",
            "type":"Services"
        }
    ],
    "sg:phone":"+1 212 696 1550",
    "sg:postcode":"10010",
    "sg:province":"NY",
    "sg:tags":[
        "organization",
        "welfare"
    ],
    "sg:website":"www.nac-inc.org",
    "wof:name":"New Alternatives For Children",
    "wof:placetype":"venue"
},
  "geometry": {"coordinates":[-73.990712,40.744498],"type":"Point"}
}