{
  "type": "Feature",
  "properties": {
    "iso:country":"US",
    "sg:address":"6042 Old Beattie Rd",
    "sg:city":"Lockport",
    "sg:classifiers":[
        {
            "category":"Retail",
            "subcategory":"Auto Repair",
            "type":"Services"
        }
    ],
    "sg:phone":"+1 716 433 1025",
    "sg:postcode":"14094",
    "sg:province":"NY",
    "sg:tags":[
        "body",
        "automobile",
        "painting",
        "repairing"
    ],
    "wof:name":"Jerry's Custom & Upholstery Inc",
    "wof:placetype":"venue"
},
  "geometry": {"coordinates":[-78.67936899999999,43.128735],"type":"Point"}
}