{
  "type": "Feature",
  "properties": {
    "addr:full":"296 W End Rd Hillsdale NY 12529",
    "addr:housenumber":"296",
    "addr:postcode":"12529",
    "addr:street":"W End Rd",
    "iso:country":"US",
    "sg:address":"296 W End Rd",
    "sg:city":"Hillsdale",
    "sg:classifiers":[
        {
            "category":"Farming",
            "subcategory":"Farm",
            "type":"Manufacturing & Wholesale Goods"
        }
    ],
    "sg:phone":"+1 518 325 7349",
    "sg:postcode":"12529",
    "sg:province":"NY",
    "sg:tags":[
        "crop",
        "general"
    ],
    "wof:name":"Sunny Mead Farms Inc Barn",
    "wof:placetype":"venue"
},
  "geometry": {"coordinates":[-73.576999,42.19143],"type":"Point"}
}