{
  "type": "Feature",
  "properties": {
    "iso:country":"US",
    "sg:address":"25 W Main St",
    "sg:city":"Falconer",
    "sg:classifiers":[
        {
            "category":"Shopping",
            "subcategory":"Pharmacy",
            "type":"Retail Goods"
        }
    ],
    "sg:phone":"+1   ",
    "sg:postcode":"14733",
    "sg:province":"NY",
    "wof:name":"Village Pharmacy",
    "wof:placetype":"venue"
},
  "geometry": {"coordinates":[-79.198941,42.118129],"type":"Point"}
}