{
  "type": "Feature",
  "properties": {
    "iso:country":"US",
    "sg:address":"372 Doughty Blvd",
    "sg:city":"Inwood",
    "sg:classifiers":[
        {
            "category":"Autos & Motor Vehicles",
            "subcategory":"Fuel & Gas Station",
            "type":"Retail Goods"
        }
    ],
    "sg:phone":"+1 516 565 6478",
    "sg:postcode":"11096",
    "sg:province":"NY",
    "wof:name":"Woodfield Eagle Operating Corp",
    "wof:placetype":"venue"
},
  "geometry": {"coordinates":[-73.74659699999999,40.622101],"type":"Point"}
}