{
  "type": "Feature",
  "properties": {
    "addr:full":"451 Unqua Rd Massapequa NY 11758",
    "addr:housenumber":"451",
    "addr:postcode":"11758",
    "addr:street":"Unqua Rd",
    "iso:country":"US",
    "sg:address":"451 Unqua Rd",
    "sg:city":"Massapequa",
    "sg:classifiers":[
        {
            "category":"Recreation",
            "type":"Entertainment"
        }
    ],
    "sg:phone":"+1 516 797 7990",
    "sg:postcode":"11758",
    "sg:province":"NY",
    "sg:tags":[
        "parks"
    ],
    "wof:name":"Marjorie R Post Community Park",
    "wof:placetype":"venue"
},
  "geometry": {"coordinates":[-73.43971999999999,40.670695],"type":"Point"}
}