{
  "type": "Feature",
  "properties": {
    "addr:full":"77 Stahley St Brentwood NY 11717",
    "addr:housenumber":"77",
    "addr:postcode":"11717",
    "addr:street":"Stahley St",
    "iso:country":"US",
    "sg:address":"77 Stahley St",
    "sg:city":"Brentwood",
    "sg:classifiers":[
        {
            "category":"Education",
            "subcategory":"School",
            "type":"Public Place"
        }
    ],
    "sg:phone":"+1 631 434 2246",
    "sg:postcode":"11717",
    "sg:province":"NY",
    "wof:name":"Loretta Park Elementary School",
    "wof:placetype":"venue"
},
  "geometry": {"coordinates":[-73.229116,40.760402],"type":"Point"}
}