{
  "type": "Feature",
  "properties": {
    "iso:country":"US",
    "sg:address":"13 E State St",
    "sg:city":"Mount Morris",
    "sg:classifiers":[
        {
            "category":"Restaurant",
            "type":"Food & Drink"
        }
    ],
    "sg:phone":"+1   ",
    "sg:postcode":"14510",
    "sg:province":"NY",
    "sg:tags":[
        "eating"
    ],
    "wof:name":"McDonalds",
    "wof:placetype":"venue"
},
  "geometry": {"coordinates":[-77.87277899999999,42.726219],"type":"Point"}
}