{
  "type": "Feature",
  "properties": {
    "addr:full":"346 Bedford Ave Brooklyn NY 11211",
    "addr:housenumber":"346",
    "addr:postcode":"11211",
    "addr:street":"Bedford Ave",
    "iso:country":"US",
    "sg:address":"346 Bedford Ave",
    "sg:city":"Brooklyn",
    "sg:classifiers":[
        {
            "category":"Restaurant",
            "type":"Food & Drink"
        }
    ],
    "sg:phone":"+1 718 218 7067",
    "sg:postcode":"11211",
    "sg:province":"NY",
    "sg:tags":[
        "vietnamese"
    ],
    "sg:website":"beprestaurant.blogspot.com/",
    "wof:name":"Bep",
    "wof:placetype":"venue"
},
  "geometry": {"coordinates":[-73.962583,40.712491],"type":"Point"}
}