{
  "type": "Feature",
  "properties": {
    "addr:full":"405 Whittier Rd Spencerport NY 14559",
    "addr:housenumber":"405",
    "addr:postcode":"14559",
    "addr:street":"Whittier Rd",
    "iso:country":"US",
    "sg:address":"405 Whittier Rd",
    "sg:city":"Spencerport",
    "sg:classifiers":[
        {
            "category":"Shopping",
            "subcategory":"Hobbies, Toys, & Games",
            "type":"Retail Goods"
        }
    ],
    "sg:phone":"+1   ",
    "sg:postcode":"14559",
    "sg:province":"NY",
    "wof:name":"Lakeside Crafts",
    "wof:placetype":"venue"
},
  "geometry": {"coordinates":[-77.811252,43.149981],"type":"Point"}
}