{
  "type": "Feature",
  "properties": {
    "addr:full":"1529 Bath Ave Brooklyn NY 11228",
    "addr:housenumber":"1529",
    "addr:postcode":"11228",
    "addr:street":"Bath Ave",
    "iso:country":"US",
    "sg:address":"1529 Bath Ave",
    "sg:city":"Brooklyn",
    "sg:classifiers":[
        {
            "category":"Social Services",
            "subcategory":"Child Care",
            "type":"Services"
        }
    ],
    "sg:phone":"+1 718 331 6128",
    "sg:postcode":"11228",
    "sg:province":"NY",
    "sg:tags":[
        "kindergarten",
        "academic",
        "school"
    ],
    "wof:name":"Royal Adventures",
    "wof:placetype":"venue"
},
  "geometry": {"coordinates":[-74.011618,40.607286],"type":"Point"}
}