{
  "type": "Feature",
  "properties": {
    "addr:full":"15 E Main St Port Jervis NY 12771",
    "addr:housenumber":"15",
    "addr:postcode":"12771",
    "addr:street":"E Main St",
    "iso:country":"US",
    "sg:address":"15 E Main St",
    "sg:city":"Port Jervis",
    "sg:classifiers":[
        {
            "category":"Health Services",
            "subcategory":"Doctor",
            "type":"Services"
        }
    ],
    "sg:phone":"+1 845 856 5277",
    "sg:postcode":"12771",
    "sg:province":"NY",
    "sg:tags":[
        "medical"
    ],
    "wof:name":"Stanley F Brunn MD",
    "wof:placetype":"venue"
},
  "geometry": {"coordinates":[-74.687746,41.377265],"type":"Point"}
}