{
  "type": "Feature",
  "properties": {
    "addr:full":"110 Industrial Rd New Windsor NY 12553",
    "addr:housenumber":"110",
    "addr:postcode":"12553",
    "addr:street":"Industrial Rd",
    "iso:country":"US",
    "sg:address":"110 Industrial Rd",
    "sg:city":"New Windsor",
    "sg:classifiers":[
        {
            "category":"Manufacturing",
            "subcategory":"Retail Goods",
            "type":"Manufacturing & Wholesale Goods"
        }
    ],
    "sg:phone":"+1 845 561 6040",
    "sg:postcode":"12553",
    "sg:province":"NY",
    "sg:tags":[
        "carbon",
        "paper"
    ],
    "sg:website":"www.fryetech.com",
    "wof:name":"Frye Copysystems Inc",
    "wof:placetype":"venue"
},
  "geometry": {"coordinates":[-74.035588,41.486743],"type":"Point"}
}