{
  "type": "Feature",
  "properties": {
    "addr:full":"413 Grand St New York NY 10002",
    "addr:housenumber":"413",
    "addr:postcode":"10002",
    "addr:street":"Grand St",
    "iso:country":"US",
    "sg:address":"413 Grand St",
    "sg:city":"New York",
    "sg:classifiers":[
        {
            "category":"Real Estate",
            "subcategory":"Real Estate Agent",
            "type":"Services"
        }
    ],
    "sg:phone":"+1 212 982 2221",
    "sg:postcode":"10002",
    "sg:province":"NY",
    "sg:tags":[
        "building",
        "operator",
        "apartment"
    ],
    "wof:name":"Maintenance Dept",
    "wof:placetype":"venue"
},
  "geometry": {"coordinates":[-73.98598699999999,40.715664],"type":"Point"}
}