{
  "type": "Feature",
  "properties": {
    "addr:full":"166 Nelson Rd Scarsdale NY 10583",
    "addr:housenumber":"166",
    "addr:postcode":"10583",
    "addr:street":"Nelson Rd",
    "iso:country":"US",
    "sg:address":"166 Nelson Rd",
    "sg:city":"Scarsdale",
    "sg:classifiers":[
        {
            "category":"Professional",
            "subcategory":"Advertising",
            "type":"Services"
        }
    ],
    "sg:phone":"+1 914 969 3440",
    "sg:postcode":"10583",
    "sg:province":"NY",
    "sg:tags":[
        "agency"
    ],
    "wof:name":"Dormor Advertising Agency Inc",
    "wof:placetype":"venue"
},
  "geometry": {"coordinates":[-73.796886,40.979301],"type":"Point"}
}