{
  "type": "Feature",
  "properties": {
    "iso:country":"US",
    "sg:address":"135 E 29th St",
    "sg:city":"New York",
    "sg:classifiers":[
        {
            "category":"Sports & Exercise",
            "subcategory":"Gym",
            "type":"Entertainment"
        }
    ],
    "sg:phone":"+1 212 216 0023",
    "sg:postcode":"10016",
    "sg:province":"NY",
    "sg:tags":[
        "trainer"
    ],
    "wof:name":"Kaplanidis William",
    "wof:placetype":"venue"
},
  "geometry": {"coordinates":[-73.981791,40.743328],"type":"Point"}
}