{
  "type": "Feature",
  "properties": {
    "addr:full":"2425 Rochester Rd Canandaigua NY 14424",
    "addr:housenumber":"2425",
    "addr:postcode":"14424",
    "addr:street":"Rochester Rd",
    "iso:country":"US",
    "sg:address":"2425 Rochester Rd",
    "sg:city":"Canandaigua",
    "sg:classifiers":[
        {
            "category":"Banks & Credit Unions",
            "subcategory":"Bank",
            "type":"Services"
        }
    ],
    "sg:phone":"+1 585 396 1000",
    "sg:postcode":"14424",
    "sg:province":"NY",
    "sg:tags":[
        "national",
        "commercial"
    ],
    "wof:name":"National Bank of Geneva",
    "wof:placetype":"venue"
},
  "geometry": {"coordinates":[-77.302144,42.914627],"type":"Point"}
}