{
  "type": "Feature",
  "properties": {
    "addr:full":"306 W 39 St New York NY 10018",
    "addr:housenumber":"306",
    "addr:postcode":"10018",
    "addr:street":"W 39 St",
    "iso:country":"US",
    "sg:address":"306 W 39 St",
    "sg:city":"New York",
    "sg:classifiers":[
        {
            "category":"Home & Garden",
            "subcategory":"Household Appliances",
            "type":"Retail Goods"
        }
    ],
    "sg:phone":"+1   ",
    "sg:postcode":"10018",
    "sg:province":"NY",
    "sg:tags":[
        "machine",
        "sewing",
        "parts"
    ],
    "wof:name":"Midtown Sewing Machine Corp",
    "wof:placetype":"venue"
},
  "geometry": {"coordinates":[-73.99392400000001,40.756388],"type":"Point"}
}