{
  "type": "Feature",
  "properties": {
    "addr:full":"9 E 47th St New York NY 10017",
    "addr:housenumber":"9",
    "addr:postcode":"10017",
    "addr:street":"E 47Th St",
    "iso:country":"US",
    "sg:address":"9 E 47th St",
    "sg:city":"New York",
    "sg:classifiers":[
        {
            "category":"Professional",
            "subcategory":"Lawyer & Legal Services",
            "type":"Services"
        }
    ],
    "sg:phone":"+1 212 935 1301",
    "sg:postcode":"10017",
    "sg:province":"NY",
    "wof:name":"Podemski Smuel Attorney At Law",
    "wof:placetype":"venue"
},
  "geometry": {"coordinates":[-73.977328,40.75627],"type":"Point"}
}