{
  "type": "Feature",
  "properties": {
    "iso:country":"US",
    "sg:address":"38 Larry Pl",
    "sg:city":"Yonkers",
    "sg:classifiers":[
        {
            "category":"Building & Trades",
            "subcategory":"Construction",
            "type":"Services"
        }
    ],
    "sg:phone":"+1 914 423 8904",
    "sg:postcode":"10701",
    "sg:province":"NY",
    "sg:tags":[
        "house"
    ],
    "wof:name":"Arezza Renovations Inc",
    "wof:placetype":"venue"
},
  "geometry": {"coordinates":[-73.86281700000001,40.948993],"type":"Point"}
}