{
  "type": "Feature",
  "properties": {
    "addr:full":"600 Wellwood Ave Lindenhurst NY 11757",
    "addr:housenumber":"600",
    "addr:postcode":"11757",
    "addr:street":"Wellwood Ave",
    "iso:country":"US",
    "sg:address":"600 Wellwood Ave",
    "sg:city":"Lindenhurst",
    "sg:classifiers":[
        {
            "category":"Food & Beverages",
            "subcategory":"Groceries & Convenience Stores",
            "type":"Retail Goods"
        }
    ],
    "sg:phone":"+1 631 226 9559",
    "sg:postcode":"11757",
    "sg:province":"NY",
    "sg:tags":[
        "grocer"
    ],
    "sg:website":"www.kingkullen.com",
    "wof:name":"King Kullen Grocery",
    "wof:placetype":"venue"
},
  "geometry": {"coordinates":[-73.38354099999999,40.700117],"type":"Point"}
}