{
  "type": "Feature",
  "properties": {
    "addr:full":"114 Pemberton Ave Staten Island NY 10308",
    "addr:housenumber":"114",
    "addr:postcode":"10308",
    "addr:street":"Pemberton Ave",
    "iso:country":"US",
    "sg:address":"114 Pemberton Ave",
    "sg:city":"Staten Island",
    "sg:classifiers":[
        {
            "category":"Freight",
            "type":"Transportation"
        }
    ],
    "sg:phone":"+1 718 967 7912",
    "sg:postcode":"10308",
    "sg:province":"NY",
    "sg:tags":[
        "trucking"
    ],
    "wof:name":"R & V Trucking Co LLC",
    "wof:placetype":"venue"
},
  "geometry": {"coordinates":[-74.15609499999999,40.56129],"type":"Point"}
}