{
  "type": "Feature",
  "properties": {
    "addr:full":"8533 E Seneca Tpke Manlius NY 13104",
    "addr:housenumber":"8533",
    "addr:postcode":"13104",
    "addr:street":"E Seneca Tpke",
    "iso:country":"US",
    "sg:address":"8533 E Seneca Tpke",
    "sg:city":"Manlius",
    "sg:classifiers":[
        {
            "category":"Building & Trades",
            "subcategory":"Construction",
            "type":"Services"
        }
    ],
    "sg:phone":"+1 315 682 5172",
    "sg:postcode":"13104",
    "sg:province":"NY",
    "sg:tags":[
        "house",
        "nonresidential"
    ],
    "wof:name":"Jarvis Builders",
    "wof:placetype":"venue"
},
  "geometry": {"coordinates":[-75.938017,43.015944],"type":"Point"}
}