{
  "type": "Feature",
  "properties": {
    "addr:full":"11 Waverly Pl New York NY 10003",
    "addr:housenumber":"11",
    "addr:postcode":"10003",
    "addr:street":"Waverly Pl",
    "iso:country":"US",
    "sg:address":"11 Waverly Pl",
    "sg:city":"New York",
    "sg:classifiers":[
        {
            "category":"Professional",
            "subcategory":"Printing & Photocopies",
            "type":"Services"
        }
    ],
    "sg:phone":"+1 212 473 7369",
    "sg:postcode":"10003",
    "sg:province":"NY",
    "sg:tags":[
        "photocopying",
        "duplicating",
        "copying"
    ],
    "wof:name":"New University Copy & Graphic",
    "wof:placetype":"venue"
},
  "geometry": {"coordinates":[-73.994822,40.73035],"type":"Point"}
}