{
  "type": "Feature",
  "properties": {
    "addr:full":"31 E Grand St Palatine Bridge NY 13428",
    "addr:housenumber":"31",
    "addr:postcode":"13428",
    "addr:street":"E Grand St",
    "iso:country":"US",
    "sg:address":"31 E Grand St",
    "sg:city":"Palatine Bridge",
    "sg:classifiers":[
        {
            "category":"Professional",
            "subcategory":"Lawyer & Legal Services",
            "type":"Services"
        }
    ],
    "sg:phone":"+1 518 673 5002",
    "sg:postcode":"13428",
    "sg:province":"NY",
    "sg:tags":[
        "attorney"
    ],
    "wof:name":"Bruce S Bandes",
    "wof:placetype":"venue"
},
  "geometry": {"coordinates":[-74.57412600000001,42.911088],"type":"Point"}
}