{
  "type": "Feature",
  "properties": {
    "iso:country":"US",
    "sg:address":"110 N Main St",
    "sg:city":"Wellsville",
    "sg:classifiers":[
        {
            "category":"Personal",
            "subcategory":"Beauty Salon",
            "type":"Services"
        }
    ],
    "sg:phone":"+1 585 593 3280",
    "sg:postcode":"14895",
    "sg:province":"NY",
    "sg:tags":[
        "shop"
    ],
    "wof:name":"Hairdressers",
    "wof:placetype":"venue"
},
  "geometry": {"coordinates":[-77.947761,42.121782],"type":"Point"}
}