{
  "type": "Feature",
  "properties": {
    "addr:full":"2105 W Genesee St Syracuse NY 13219",
    "addr:housenumber":"2105",
    "addr:postcode":"13219",
    "addr:street":"W Genesee St",
    "iso:country":"US",
    "sg:address":"2105 W Genesee St",
    "sg:city":"Syracuse",
    "sg:classifiers":[
        {
            "category":"Health Services",
            "subcategory":"Health Practitioner",
            "type":"Services"
        }
    ],
    "sg:phone":"+1 315 458 2552",
    "sg:postcode":"13219",
    "sg:province":"NY",
    "sg:tags":[
        "therapist",
        "physical"
    ],
    "wof:name":"Pro Active Physical Therapy",
    "wof:placetype":"venue"
},
  "geometry": {"coordinates":[-76.197774,43.047654],"type":"Point"}
}