{
  "type": "Feature",
  "properties": {
    "iso:country":"US",
    "sg:address":"1091 E 3rd St",
    "sg:city":"Brooklyn",
    "sg:classifiers":[
        {
            "category":"Professional",
            "subcategory":"Lawyer & Legal Services",
            "type":"Services"
        }
    ],
    "sg:phone":"+1   ",
    "sg:postcode":"11230",
    "sg:province":"NY",
    "wof:name":"Marc J Attia Esq PC",
    "wof:placetype":"venue"
},
  "geometry": {"coordinates":[-73.97387000000001,40.625564],"type":"Point"}
}