{
  "type": "Feature",
  "properties": {
    "iso:country":"US",
    "sg:address":"1700 Guide Board Rd",
    "sg:city":"Schuyler Falls",
    "sg:classifiers":[
        {
            "category":"Real Estate",
            "subcategory":"Surveying",
            "type":"Services"
        }
    ],
    "sg:phone":"+1 518 643 8073",
    "sg:postcode":"12985",
    "sg:province":"NY",
    "wof:name":"Land Surveyor",
    "wof:placetype":"venue"
},
  "geometry": {"coordinates":[-73.752773,44.575833],"type":"Point"}
}