{
  "type": "Feature",
  "properties": {
    "iso:country":"US",
    "sg:address":"1 Stone Pl",
    "sg:city":"Bronxville",
    "sg:classifiers":[
        {
            "category":"Real Estate",
            "subcategory":"Real Estate Operator",
            "type":"Services"
        }
    ],
    "sg:phone":"+1 914 779 1400",
    "sg:postcode":"10708",
    "sg:province":"NY",
    "sg:tags":[
        "holding"
    ],
    "wof:name":"Hdw Stone Place LLC",
    "wof:placetype":"venue"
},
  "geometry": {"coordinates":[-73.836856,40.940816],"type":"Point"}
}