{
  "type": "Feature",
  "properties": {
    "addr:full":"1367 1st Ave Manhattan NY 10021",
    "addr:housenumber":"1367",
    "addr:postcode":"10021",
    "addr:street":"1St Ave",
    "iso:country":"US",
    "sg:address":"1367 1st Ave",
    "sg:city":"Manhattan",
    "sg:classifiers":[
        {
            "category":"Restaurant",
            "type":"Food & Drink"
        }
    ],
    "sg:phone":"+1 212 396 3388",
    "sg:postcode":"10021",
    "sg:province":"NY",
    "sg:tags":[
        "sushi",
        "bar",
        "japanese",
        "chinese"
    ],
    "sg:website":"www.Fuji-Asian.com",
    "wof:name":"Fuji Asian Restaurant",
    "wof:placetype":"venue"
},
  "geometry": {"coordinates":[-73.9556,40.768902],"type":"Point"}
}