{
  "type": "Feature",
  "properties": {
    "iso:country":"US",
    "sg:address":"1309 US Hwy 9",
    "sg:city":"Keeseville",
    "sg:classifiers":[
        {
            "category":"Organizations",
            "subcategory":"Community Association",
            "type":"Services"
        }
    ],
    "sg:phone":"+1 518 834 1505",
    "sg:postcode":"12944",
    "sg:province":"NY",
    "sg:tags":[
        "club"
    ],
    "sg:website":"www.vfw.org",
    "wof:name":"Veterans Of Foreign Wars",
    "wof:placetype":"venue"
},
  "geometry": {"coordinates":[-73.482399,44.496873],"type":"Point"}
}