{
  "type": "Feature",
  "properties": {
    "iso:country":"US",
    "sg:address":"1740 Broadway",
    "sg:city":"New York",
    "sg:classifiers":[
        {
            "category":"Professional",
            "subcategory":"Lawyer & Legal Services",
            "type":"Services"
        }
    ],
    "sg:phone":"+1 212 489 8230",
    "sg:postcode":"10019",
    "sg:province":"NY",
    "wof:name":"Kurtz Daniel L Atty",
    "wof:placetype":"venue"
},
  "geometry": {"coordinates":[-73.98200199999999,40.765099],"type":"Point"}
}