{
  "type": "Feature",
  "properties": {
    "iso:country":"US",
    "sg:address":"6700 Old Collamer Rd",
    "sg:city":"East Syracuse",
    "sg:classifiers":[
        {
            "category":"Professional",
            "subcategory":"Computer Services",
            "type":"Services"
        }
    ],
    "sg:phone":"+1 315 463 1629",
    "sg:postcode":"13057",
    "sg:province":"NY",
    "sg:tags":[
        "repair"
    ],
    "sg:website":"www.bowebellhowell.com",
    "wof:name":"BOWE Bell & Howell",
    "wof:placetype":"venue"
},
  "geometry": {"coordinates":[-76.082573,43.096326],"type":"Point"}
}