{
  "type": "Feature",
  "properties": {
    "addr:full":"1885 Gleason Ave Bronx NY 10472",
    "addr:housenumber":"1885",
    "addr:postcode":"10472",
    "addr:street":"Gleason Ave",
    "iso:country":"US",
    "sg:address":"1885 Gleason Ave",
    "sg:city":"Bronx",
    "sg:classifiers":[
        {
            "category":"Insurance",
            "subcategory":"Insurance Agent",
            "type":"Services"
        }
    ],
    "sg:phone":"+1 718 518 0800",
    "sg:postcode":"10472",
    "sg:province":"NY",
    "wof:name":"International Insurance Broker",
    "wof:placetype":"venue"
},
  "geometry": {"coordinates":[-73.86168600000001,40.830568],"type":"Point"}
}