{
  "type": "Feature",
  "properties": {
    "addr:full":"220 Bowery New York NY 10012",
    "addr:housenumber":"220",
    "addr:postcode":"10012",
    "addr:street":"Bowery",
    "iso:country":"US",
    "sg:address":"220 Bowery",
    "sg:city":"New York",
    "sg:classifiers":[
        {
            "category":"Building & Trades",
            "subcategory":"Plumbing",
            "type":"Services"
        }
    ],
    "sg:phone":"+1 866 359 0165",
    "sg:postcode":"10012",
    "sg:province":"NY",
    "wof:name":"A Times Square Plumbing",
    "wof:placetype":"venue"
},
  "geometry": {"coordinates":[-73.99361399999999,40.722057],"type":"Point"}
}