{
  "type": "Feature",
  "properties": {
    "iso:country":"US",
    "sg:address":"18 Weeks St",
    "sg:city":"Blue Point",
    "sg:classifiers":[
        {
            "category":"Restaurant",
            "type":"Food & Drink"
        }
    ],
    "sg:phone":"+1 631 363 5704",
    "sg:postcode":"11715",
    "sg:province":"NY",
    "sg:tags":[
        "delicatessen"
    ],
    "wof:name":"Atlantic Avenue Deli",
    "wof:placetype":"venue"
},
  "geometry": {"coordinates":[-73.02558399999999,40.75355],"type":"Point"}
}