{
  "type": "Feature",
  "properties": {
    "addr:full":"18 Wayne St Haverstraw NY 10927",
    "addr:housenumber":"18",
    "addr:postcode":"10927",
    "addr:street":"Wayne St",
    "iso:country":"US",
    "sg:address":"18 Wayne St",
    "sg:city":"Haverstraw",
    "sg:classifiers":[
        {
            "category":"Wholesale",
            "subcategory":"Vending Machines",
            "type":"Manufacturing & Wholesale Goods"
        }
    ],
    "sg:phone":"+1   ",
    "sg:postcode":"10927",
    "sg:province":"NY",
    "sg:tags":[
        "operator"
    ],
    "wof:name":"Bailey Vending Co",
    "wof:placetype":"venue"
},
  "geometry": {"coordinates":[-73.963504,41.196731],"type":"Point"}
}