{
  "type": "Feature",
  "properties": {
    "iso:country":"US",
    "sg:address":"4710 Vestal Pkwy E",
    "sg:city":"Vestal",
    "sg:classifiers":[
        {
            "category":"Real Estate",
            "subcategory":"Real Estate Operator",
            "type":"Services"
        }
    ],
    "sg:phone":"+1 607 729 1542",
    "sg:postcode":"13850",
    "sg:province":"NY",
    "sg:tags":[
        "apartment"
    ],
    "wof:name":"University Plaza Apartments",
    "wof:placetype":"venue"
},
  "geometry": {"coordinates":[-75.951728,42.093022],"type":"Point"}
}