{
  "type": "Feature",
  "properties": {
    "addr:full":"12 Greenvale Rd Sound Beach NY 11789",
    "addr:housenumber":"12",
    "addr:postcode":"11789",
    "addr:street":"Greenvale Rd",
    "iso:country":"US",
    "sg:address":"12 Greenvale Rd",
    "sg:city":"Sound Beach",
    "sg:classifiers":[
        {
            "category":"Retail",
            "subcategory":"Laundry & Dry Cleaning",
            "type":"Services"
        }
    ],
    "sg:phone":"+1 631 821 1626",
    "sg:postcode":"11789",
    "sg:province":"NY",
    "sg:tags":[
        "cleaners",
        "rug",
        "carpet"
    ],
    "wof:name":"Triple A & G Maintenance",
    "wof:placetype":"venue"
},
  "geometry": {"coordinates":[-72.97120700000001,40.961138],"type":"Point"}
}