{
  "type": "Feature",
  "properties": {
    "iso:country":"US",
    "sg:address":"17 Van Leuven Dr E",
    "sg:city":"Rensselaer",
    "sg:classifiers":[
        {
            "category":"Building & Trades",
            "subcategory":"Construction",
            "type":"Services"
        }
    ],
    "sg:phone":"+1 518 283 8110",
    "sg:postcode":"12144",
    "sg:province":"NY",
    "sg:tags":[
        "residential",
        "new"
    ],
    "wof:name":"Zelenke Builders",
    "wof:placetype":"venue"
},
  "geometry": {"coordinates":[-73.682114,42.645455],"type":"Point"}
}