{
  "type": "Feature",
  "properties": {
    "addr:full":"106 Morris Ave Rockville Centre NY 11570",
    "addr:housenumber":"106",
    "addr:postcode":"11570",
    "addr:street":"Morris Ave",
    "iso:country":"US",
    "sg:address":"106 Morris Ave",
    "sg:city":"Rockville Centre",
    "sg:classifiers":[
        {
            "category":"Building & Trades",
            "subcategory":"Construction",
            "type":"Services"
        }
    ],
    "sg:phone":"+1 516 255 3700",
    "sg:postcode":"11570",
    "sg:province":"NY",
    "sg:tags":[
        "contractor"
    ],
    "wof:name":"Hilltop Contracting Corp",
    "wof:placetype":"venue"
},
  "geometry": {"coordinates":[-73.641177,40.659064],"type":"Point"}
}