{
  "type": "Feature",
  "properties": {
    "addr:full":"6915 8th Ave Brooklyn NY 11228",
    "addr:housenumber":"6915",
    "addr:postcode":"11228",
    "addr:street":"8Th Ave",
    "iso:country":"US",
    "sg:address":"6915 8th Ave",
    "sg:city":"Brooklyn",
    "sg:classifiers":[
        {
            "category":"Professional",
            "subcategory":"Accounting & Tax Preparation",
            "type":"Services"
        }
    ],
    "sg:phone":"+1 718 238 8500",
    "sg:postcode":"11228",
    "sg:province":"NY",
    "sg:tags":[
        "return",
        "filing"
    ],
    "wof:name":"Walker Tax Svc",
    "wof:placetype":"venue"
},
  "geometry": {"coordinates":[-74.015365,40.629825],"type":"Point"}
}