{
  "type": "Feature",
  "properties": {
    "addr:full":"3657 Hill Blvd Jefferson Valley NY 10535",
    "addr:housenumber":"3657",
    "addr:postcode":"10535",
    "addr:street":"Hill Blvd Jefferson",
    "iso:country":"US",
    "sg:address":"3657 Hill Blvd",
    "sg:city":"Jefferson Valley",
    "sg:classifiers":[
        {
            "category":"Retail",
            "subcategory":"Laundry & Dry Cleaning",
            "type":"Services"
        }
    ],
    "sg:phone":"+1 914 245 7900",
    "sg:postcode":"10535",
    "sg:province":"NY",
    "sg:tags":[
        "drycleaning",
        "plant",
        "cleaners"
    ],
    "wof:name":"Rite Price Cleaners LLC",
    "wof:placetype":"venue"
},
  "geometry": {"coordinates":[-73.801794,41.329186],"type":"Point"}
}