{
  "type": "Feature",
  "properties": {
    "addr:full":"56 Ridge Rd Ridge NY 11961",
    "addr:housenumber":"56",
    "addr:postcode":"11961",
    "addr:street":"Ridge Rd",
    "iso:country":"US",
    "sg:address":"56 Ridge Rd",
    "sg:city":"Ridge",
    "sg:classifiers":[
        {
            "category":"Building & Trades",
            "subcategory":"Construction",
            "type":"Services"
        }
    ],
    "sg:phone":"+1 631 345 5586",
    "sg:postcode":"11961",
    "sg:province":"NY",
    "sg:tags":[
        "concrete",
        "masonry",
        "contractor"
    ],
    "wof:name":"Chorzepa Construction Corp",
    "wof:placetype":"venue"
},
  "geometry": {"coordinates":[-72.89833299999999,40.90063],"type":"Point"}
}