{
  "type": "Feature",
  "properties": {
    "addr:full":"725 Sterling Rd Cutchogue NY 11935",
    "addr:housenumber":"725",
    "addr:postcode":"11935",
    "addr:street":"Sterling Rd",
    "iso:country":"US",
    "sg:address":"725 Sterling Rd",
    "sg:city":"Cutchogue",
    "sg:classifiers":[
        {
            "category":"Professional",
            "type":"Services"
        }
    ],
    "sg:phone":"+1 631 765 3546",
    "sg:postcode":"11935",
    "sg:province":"NY",
    "sg:tags":[
        "establishment"
    ],
    "wof:name":"Glover Perennial Growers",
    "wof:placetype":"venue"
},
  "geometry": {"coordinates":[-72.456844,41.016065],"type":"Point"}
}