{
  "type": "Feature",
  "properties": {
    "addr:full":"4278 Main Street Fl 2 Flushing NY 11355",
    "addr:housenumber":"4278;2",
    "addr:postcode":"11355",
    "addr:street":"Main Street",
    "iso:country":"US",
    "sg:address":"4278 Main Street Fl 2",
    "sg:city":"Flushing",
    "sg:classifiers":[
        {
            "category":"Health Services",
            "subcategory":"Doctor",
            "type":"Services"
        }
    ],
    "sg:phone":"+1 718 539 8800",
    "sg:postcode":"11355",
    "sg:province":"NY",
    "wof:name":"Linardos Medical",
    "wof:placetype":"venue"
},
  "geometry": {"coordinates":[-73.827074,40.752519],"type":"Point"}
}