{
  "type": "Feature",
  "properties": {
    "iso:country":"US",
    "sg:address":"12229 Olean Rd",
    "sg:city":"Chaffee",
    "sg:classifiers":[
        {
            "category":"Retail",
            "subcategory":"Auto Repair",
            "type":"Services"
        }
    ],
    "sg:phone":"+1 716 537 3124",
    "sg:postcode":"14030",
    "sg:province":"NY",
    "sg:tags":[
        "repairing",
        "automobile"
    ],
    "wof:name":"Precision Engines",
    "wof:placetype":"venue"
},
  "geometry": {"coordinates":[-78.47804600000001,42.550487],"type":"Point"}
}