{
  "type": "Feature",
  "properties": {
    "iso:country":"US",
    "sg:address":"41 John St Ste 6",
    "sg:city":"Babylon",
    "sg:classifiers":[
        {
            "category":"Organizations",
            "subcategory":"Community Association",
            "type":"Services"
        }
    ],
    "sg:phone":"+1 631 376 0640",
    "sg:postcode":"11702",
    "sg:province":"NY",
    "sg:tags":[
        "club"
    ],
    "wof:name":"Strictly Softball Inc",
    "wof:placetype":"venue"
},
  "geometry": {"coordinates":[-73.317474,40.70236],"type":"Point"}
}