{
  "type": "Feature",
  "properties": {
    "addr:full":"200 W 103rd St New York NY 10025",
    "addr:housenumber":"200",
    "addr:postcode":"10025",
    "addr:street":"W 103Rd St",
    "iso:country":"US",
    "sg:address":"200 W 103rd St",
    "sg:city":"New York",
    "sg:classifiers":[
        {
            "category":"Retail",
            "subcategory":"Repair Shop",
            "type":"Services"
        }
    ],
    "sg:phone":"+1 646 224 9162",
    "sg:postcode":"10025",
    "sg:province":"NY",
    "sg:tags":[
        "lock",
        "locksmith"
    ],
    "wof:name":"Emergency Locksmith",
    "wof:placetype":"venue"
},
  "geometry": {"coordinates":[-73.96855600000001,40.799109],"type":"Point"}
}