{
  "type": "Feature",
  "properties": {
    "addr:full":"430 N Main St Sayville NY 11782",
    "addr:housenumber":"430",
    "addr:postcode":"11782",
    "addr:street":"N Main St",
    "iso:country":"US",
    "sg:address":"430 N Main St",
    "sg:city":"Sayville",
    "sg:classifiers":[
        {
            "category":"Health Services",
            "subcategory":"Doctor",
            "type":"Services"
        }
    ],
    "sg:phone":"+1 631 589 9303",
    "sg:postcode":"11782",
    "sg:province":"NY",
    "sg:tags":[
        "physician",
        "surgeon"
    ],
    "wof:name":"Philip La Barbera MD",
    "wof:placetype":"venue"
},
  "geometry": {"coordinates":[-73.072058,40.745488],"type":"Point"}
}