{
  "type": "Feature",
  "properties": {
    "addr:full":"8 Gladwyne Ct Spring Valley NY 10977",
    "addr:housenumber":"8",
    "addr:postcode":"10977",
    "addr:street":"Gladwyne Ct",
    "iso:country":"US",
    "sg:address":"8 Gladwyne Ct",
    "sg:city":"Spring Valley",
    "sg:classifiers":[
        {
            "category":"Banks & Credit Unions",
            "subcategory":"Financial Services",
            "type":"Services"
        }
    ],
    "sg:phone":"+1 845 362 3280",
    "sg:postcode":"10977",
    "sg:province":"NY",
    "sg:tags":[
        "company",
        "holding"
    ],
    "wof:name":"1471 Amsterdam LLC",
    "wof:placetype":"venue"
},
  "geometry": {"coordinates":[-74.066619,41.14633],"type":"Point"}
}