{
  "type": "Feature",
  "properties": {
    "addr:full":"200 Park Ave New York NY 10017",
    "addr:housenumber":"200",
    "addr:postcode":"10017",
    "addr:street":"Park Ave",
    "iso:country":"US",
    "sg:address":"200 Park Ave",
    "sg:city":"New York",
    "sg:classifiers":[
        {
            "category":"Manufacturing",
            "subcategory":"Metals",
            "type":"Manufacturing & Wholesale Goods"
        },
        {
            "category":"Wholesale",
            "subcategory":"Metals & Minerals",
            "type":"Manufacturing & Wholesale Goods"
        }
    ],
    "sg:phone":"+1 212 878 4381",
    "sg:postcode":"10017",
    "sg:province":"NY",
    "sg:tags":[
        "steel",
        "company",
        "investor",
        "center",
        "related"
    ],
    "wof:name":"Mitsui Steel Dev Co Inc",
    "wof:placetype":"venue"
},
  "geometry": {"coordinates":[-73.975807,40.754678],"type":"Point"}
}