{
  "type": "Feature",
  "properties": {
    "iso:country":"US",
    "sg:address":"3735 W Seneca Tpke",
    "sg:city":"Syracuse",
    "sg:classifiers":[
        {
            "category":"Food & Beverages",
            "subcategory":"Fruits & Vegetables",
            "type":"Retail Goods"
        }
    ],
    "sg:phone":"+1 315 492 7450",
    "sg:postcode":"13215",
    "sg:province":"NY",
    "sg:tags":[
        "farm",
        "market"
    ],
    "wof:name":"Hollow",
    "wof:placetype":"venue"
},
  "geometry": {"coordinates":[-76.257836,42.987313],"type":"Point"}
}