{
  "type": "Feature",
  "properties": {
    "iso:country":"US",
    "sg:address":"1663 E 17th St",
    "sg:city":"Brooklyn",
    "sg:classifiers":[
        {
            "category":"Health Services",
            "subcategory":"Health Practitioner",
            "type":"Services"
        }
    ],
    "sg:phone":"+1 718 339 5362",
    "sg:postcode":"11229",
    "sg:province":"NY",
    "sg:tags":[
        "agency",
        "employment"
    ],
    "wof:name":"Therapists Network Inc",
    "wof:placetype":"venue"
},
  "geometry": {"coordinates":[-73.9562,40.608799],"type":"Point"}
}