{
  "type": "Feature",
  "properties": {
    "addr:full":"15020 16th Rd Whitestone NY 11357",
    "addr:housenumber":"15020",
    "addr:postcode":"11357",
    "addr:street":"16Th Rd",
    "iso:country":"US",
    "sg:address":"15020 16th Rd",
    "sg:city":"Whitestone",
    "sg:classifiers":[
        {
            "category":"Organizations",
            "subcategory":"Religious Organization",
            "type":"Services"
        }
    ],
    "sg:phone":"+1 718 747 5282",
    "sg:postcode":"11357",
    "sg:province":"NY",
    "wof:name":"Sisters of Charity",
    "wof:placetype":"venue"
},
  "geometry": {"coordinates":[-73.812923,40.784757],"type":"Point"}
}