{
  "type": "Feature",
  "properties": {
    "addr:full":"42 W 38th Street Lbby New York NY 10018",
    "addr:housenumber":"42",
    "addr:postcode":"10018",
    "addr:street":"W 38Th Street",
    "iso:country":"US",
    "sg:address":"42 W 38th Street Lbby",
    "sg:city":"New York",
    "sg:classifiers":[
        {
            "category":"Shopping",
            "subcategory":"Jewelry",
            "type":"Retail Goods"
        }
    ],
    "sg:phone":"+1 212 840 8828",
    "sg:postcode":"10018",
    "sg:province":"NY",
    "wof:name":"Jc Nova",
    "wof:placetype":"venue"
},
  "geometry": {"coordinates":[-73.984049,40.751486],"type":"Point"}
}