{
  "type": "Feature",
  "properties": {
    "iso:country":"US",
    "sg:address":"3845 Sedgwick Ave",
    "sg:city":"Bronx",
    "sg:classifiers":[
        {
            "category":"Health Services",
            "subcategory":"Doctor",
            "type":"Services"
        }
    ],
    "sg:phone":"+1 718 543 0044",
    "sg:postcode":"10463",
    "sg:province":"NY",
    "sg:tags":[
        "dentist"
    ],
    "wof:name":"Harold I Ginsburg DDS",
    "wof:placetype":"venue"
},
  "geometry": {"coordinates":[-73.894919,40.882788],"type":"Point"}
}