{
  "type": "Feature",
  "properties": {
    "iso:country":"US",
    "sg:address":"6 Deb Ellen Dr",
    "sg:city":"Rochester",
    "sg:classifiers":[
        {
            "category":"Building & Trades",
            "subcategory":"Construction",
            "type":"Services"
        }
    ],
    "sg:phone":"+1 585 889 5004",
    "sg:postcode":"14624",
    "sg:province":"NY",
    "sg:tags":[
        "home",
        "general",
        "remodeling",
        "family",
        "contractor"
    ],
    "wof:name":"Intec Holding Corp",
    "wof:placetype":"venue"
},
  "geometry": {"coordinates":[-77.75824,43.103083],"type":"Point"}
}