{
  "type": "Feature",
  "properties": {
    "addr:full":"22 Highland Rd Ulster Park NY 12487",
    "addr:housenumber":"22",
    "addr:postcode":"12487",
    "addr:street":"Highland Rd",
    "iso:country":"US",
    "sg:address":"22 Highland Rd",
    "sg:city":"Ulster Park",
    "sg:classifiers":[
        {
            "category":"Retail",
            "subcategory":"Animal Services",
            "type":"Services"
        }
    ],
    "sg:phone":"+1 845 331 8639",
    "sg:postcode":"12487",
    "sg:province":"NY",
    "wof:name":"Leisure Time Kennels",
    "wof:placetype":"venue"
},
  "geometry": {"coordinates":[-74.019766,41.869245],"type":"Point"}
}