{
  "type": "Feature",
  "properties": {
    "addr:full":"481 W Creek Rd Owego NY 13827",
    "addr:housenumber":"481",
    "addr:postcode":"13827",
    "addr:street":"W Creek Rd",
    "iso:country":"US",
    "sg:address":"481 W Creek Rd",
    "sg:city":"Owego",
    "sg:classifiers":[
        {
            "category":"Farming",
            "subcategory":"Farm",
            "type":"Manufacturing & Wholesale Goods"
        }
    ],
    "sg:phone":"+1 607 687 9622",
    "sg:postcode":"13827",
    "sg:province":"NY",
    "wof:name":"Tri-K Farms",
    "wof:placetype":"venue"
},
  "geometry": {"coordinates":[-76.251475,42.161166],"type":"Point"}
}