{
  "type": "Feature",
  "properties": {
    "addr:full":"3544 Roger Dr Wantagh NY 11793",
    "addr:housenumber":"3544",
    "addr:postcode":"11793",
    "addr:street":"Roger Dr",
    "iso:country":"US",
    "sg:address":"3544 Roger Dr",
    "sg:city":"Wantagh",
    "sg:classifiers":[
        {
            "category":"Real Estate",
            "subcategory":"Real Estate Services",
            "type":"Services"
        },
        {
            "category":"Real Estate",
            "subcategory":"Real Estate Agent",
            "type":"Services"
        }
    ],
    "sg:phone":"+1 516 221 1348",
    "sg:postcode":"11793",
    "sg:province":"NY",
    "sg:tags":[
        "buyer",
        "broker"
    ],
    "wof:name":"Vaiano Realty Corp.",
    "wof:placetype":"venue"
},
  "geometry": {"coordinates":[-73.50247899999999,40.690303],"type":"Point"}
}