{
  "type": "Feature",
  "properties": {
    "addr:full":"471 E 138th St Bronx NY 10454",
    "addr:housenumber":"471",
    "addr:postcode":"10454",
    "addr:street":"E 138Th St",
    "iso:country":"US",
    "sg:address":"471 E 138th St",
    "sg:city":"Bronx",
    "sg:classifiers":[
        {
            "category":"Professional",
            "subcategory":"Advertising",
            "type":"Services"
        }
    ],
    "sg:phone":"+1 718 292 0434",
    "sg:postcode":"10454",
    "sg:province":"NY",
    "sg:tags":[
        "agency"
    ],
    "wof:name":"Empress Advertising",
    "wof:placetype":"venue"
},
  "geometry": {"coordinates":[-73.921544,40.808829],"type":"Point"}
}