{
  "type": "Feature",
  "properties": {
    "addr:full":"434 Avenue of the Americ New York NY 10011",
    "addr:housenumber":"434",
    "addr:postcode":"10011",
    "addr:street":"Avenue Of The",
    "iso:country":"US",
    "sg:address":"434 Avenue of the Americ",
    "sg:city":"New York",
    "sg:classifiers":[
        {
            "category":"Bagels",
            "subcategory":"None",
            "type":"Food & Drink"
        }
    ],
    "sg:phone":"+1 212 777 3303",
    "sg:postcode":"10011",
    "sg:province":"NY",
    "wof:name":"Bagel Bob's On 6th",
    "wof:placetype":"venue"
},
  "geometry": {"coordinates":[-73.998802,40.73465],"type":"Point"}
}