{
  "type": "Feature",
  "properties": {
    "addr:full":"1214 Irving Pkwy Olean NY 14760",
    "addr:housenumber":"1214",
    "addr:postcode":"14760",
    "addr:street":"Irving Pkwy",
    "iso:country":"US",
    "sg:address":"1214 Irving Pkwy",
    "sg:city":"Olean",
    "sg:classifiers":[
        {
            "category":"Shopping",
            "subcategory":"Musical Instruments",
            "type":"Retail Goods"
        }
    ],
    "sg:phone":"+1   ",
    "sg:postcode":"14760",
    "sg:province":"NY",
    "sg:tags":[
        "piano"
    ],
    "wof:name":"Broadway Piano Company",
    "wof:placetype":"venue"
},
  "geometry": {"coordinates":[-78.445657,42.073936],"type":"Point"}
}