{
  "type": "Feature",
  "properties": {
    "addr:full":"4260 Main Street Flushing NY 11355",
    "addr:housenumber":"4260",
    "addr:postcode":"11355",
    "addr:street":"Main Street",
    "iso:country":"US",
    "sg:address":"4260 Main Street",
    "sg:city":"Flushing",
    "sg:classifiers":[
        {
            "category":"Health Services",
            "subcategory":"Doctor",
            "type":"Services"
        }
    ],
    "sg:phone":"+1 718 359 2827",
    "sg:postcode":"11355",
    "sg:province":"NY",
    "wof:name":"Hon King Chen MD",
    "wof:placetype":"venue"
},
  "geometry": {"coordinates":[-73.827673,40.75373],"type":"Point"}
}