{
  "type": "Feature",
  "properties": {
    "addr:full":"22 Graham Ave Brooklyn NY 11206",
    "addr:housenumber":"22",
    "addr:postcode":"11206",
    "addr:street":"Graham Ave",
    "iso:country":"US",
    "sg:address":"22 Graham Ave",
    "sg:city":"Brooklyn",
    "sg:classifiers":[
        {
            "category":"Shopping",
            "subcategory":"Clothing, Apparel, & Fashions",
            "type":"Retail Goods"
        }
    ],
    "sg:phone":"+1 718 387 2210",
    "sg:postcode":"11206",
    "sg:province":"NY",
    "wof:name":"Graham Fashions",
    "wof:placetype":"venue"
},
  "geometry": {"coordinates":[-73.94215,40.70102],"type":"Point"}
}