{
  "type": "Feature",
  "properties": {
    "iso:country":"US",
    "sg:address":"73 Gannon Rd",
    "sg:city":"Eagle Bridge",
    "sg:classifiers":[
        {
            "category":"Building & Trades",
            "subcategory":"Construction",
            "type":"Services"
        }
    ],
    "sg:phone":"+1 518 686 4385",
    "sg:postcode":"12057",
    "sg:province":"NY",
    "sg:tags":[
        "carpentry",
        "contractor"
    ],
    "wof:name":"SL Carpentry",
    "wof:placetype":"venue"
},
  "geometry": {"coordinates":[-73.279804,42.982768],"type":"Point"}
}