{
  "type": "Feature",
  "properties": {
    "iso:country":"US",
    "sg:address":"231 Union Ave",
    "sg:city":"New Rochelle",
    "sg:classifiers":[
        {
            "category":"Restaurant",
            "type":"Food & Drink"
        }
    ],
    "sg:phone":"+1 914 633 9604",
    "sg:postcode":"10801",
    "sg:province":"NY",
    "sg:tags":[
        "delicatessen"
    ],
    "wof:name":"El Jalisco",
    "wof:placetype":"venue"
},
  "geometry": {"coordinates":[-73.79489700000001,40.909444],"type":"Point"}
}