{
  "type": "Feature",
  "properties": {
    "addr:full":"4160 Hylan Blvd Staten Island NY 10308",
    "addr:housenumber":"4160",
    "addr:postcode":"10308",
    "addr:street":"Hylan Blvd",
    "iso:country":"US",
    "sg:address":"4160 Hylan Blvd",
    "sg:city":"Staten Island",
    "sg:classifiers":[
        {
            "category":"Restaurant",
            "type":"Food & Drink"
        }
    ],
    "sg:phone":"+1 718 227 7768",
    "sg:postcode":"10308",
    "sg:province":"NY",
    "wof:name":"Andrew's Diner",
    "wof:placetype":"venue"
},
  "geometry": {"coordinates":[-74.1493,40.538502],"type":"Point"}
}