{
  "type": "Feature",
  "properties": {
    "addr:full":"135 South St Lockport NY 14094",
    "addr:housenumber":"135",
    "addr:postcode":"14094",
    "addr:street":"South St",
    "iso:country":"US",
    "sg:address":"135 South St",
    "sg:city":"Lockport",
    "sg:classifiers":[
        {
            "category":"Building & Trades",
            "subcategory":"Plumbing",
            "type":"Services"
        }
    ],
    "sg:phone":"+1 716 434 8533",
    "sg:postcode":"14094",
    "sg:province":"NY",
    "sg:tags":[
        "plumbing",
        "contractor"
    ],
    "wof:name":"Roto-Rooter Plumbing & Drain",
    "wof:placetype":"venue"
},
  "geometry": {"coordinates":[-78.686956,43.168655],"type":"Point"}
}