{
  "type": "Feature",
  "properties": {
    "iso:country":"US",
    "sg:address":"24 Prospect St",
    "sg:city":"Yonkers",
    "sg:classifiers":[
        {
            "category":"Travel",
            "subcategory":"Travel Agent",
            "type":"Entertainment"
        }
    ],
    "sg:phone":"+1   ",
    "sg:postcode":"10701",
    "sg:province":"NY",
    "sg:tags":[
        "agency"
    ],
    "wof:name":"Roots Travel",
    "wof:placetype":"venue"
},
  "geometry": {"coordinates":[-73.902168,40.932516],"type":"Point"}
}