{
  "type": "Feature",
  "properties": {
    "addr:full":"28 E 12 St New York NY 10003",
    "addr:housenumber":"28;12",
    "addr:postcode":"10003",
    "addr:street":"E",
    "iso:country":"US",
    "sg:address":"28 E 12 St",
    "sg:city":"New York",
    "sg:classifiers":[
        {
            "category":"Shopping",
            "subcategory":"Stationery & Office Supplies",
            "type":"Retail Goods"
        }
    ],
    "sg:phone":"+1   ",
    "sg:postcode":"10003",
    "sg:province":"NY",
    "sg:tags":[
        "store"
    ],
    "wof:name":"University Stationery Inc",
    "wof:placetype":"venue"
},
  "geometry": {"coordinates":[-73.994006,40.734505],"type":"Point"}
}