{
  "type": "Feature",
  "properties": {
    "iso:country":"US",
    "sg:address":"40 Church St",
    "sg:city":"Saranac Lake",
    "sg:classifiers":[
        {
            "category":"Retail",
            "subcategory":"Funeral Services",
            "type":"Services"
        }
    ],
    "sg:phone":"+1 518 891 3613",
    "sg:postcode":"12983",
    "sg:province":"NY",
    "sg:tags":[
        "director"
    ],
    "wof:name":"Fortune-Keough Funeral Home",
    "wof:placetype":"venue"
},
  "geometry": {"coordinates":[-74.12755,44.325224],"type":"Point"}
}