{
  "type": "Feature",
  "properties": {
    "iso:country":"US",
    "sg:address":"414 Country Club Dr",
    "sg:city":"Cutchogue",
    "sg:classifiers":[
        {
            "category":"Home & Garden",
            "subcategory":"Home Furnishings",
            "type":"Retail Goods"
        }
    ],
    "sg:phone":"+1 516 505 0954",
    "sg:postcode":"11935",
    "sg:province":"NY",
    "sg:tags":[
        "venetian",
        "blind"
    ],
    "wof:name":"Blinds By Me",
    "wof:placetype":"venue"
},
  "geometry": {"coordinates":[-72.492407,41.00077],"type":"Point"}
}