{
  "type": "Feature",
  "properties": {
    "addr:full":"1602 S Park Ave Buffalo NY 14220",
    "addr:housenumber":"1602",
    "addr:postcode":"14220",
    "addr:street":"S Park Ave",
    "iso:country":"US",
    "sg:address":"1602 S Park Ave",
    "sg:city":"Buffalo",
    "sg:classifiers":[
        {
            "category":"Retail",
            "subcategory":"Auto Repair",
            "type":"Services"
        }
    ],
    "sg:phone":"+1 716 823 4451",
    "sg:postcode":"14220",
    "sg:province":"NY",
    "sg:tags":[
        "repairing",
        "automobile"
    ],
    "wof:name":"2151 Auto Svce",
    "wof:placetype":"venue"
},
  "geometry": {"coordinates":[-78.82730100000001,42.854698],"type":"Point"}
}