{
  "type": "Feature",
  "properties": {
    "addr:full":"3387 3rd Ave Bronx NY 10456",
    "addr:housenumber":"3387",
    "addr:postcode":"10456",
    "addr:street":"3Rd Ave",
    "iso:country":"US",
    "sg:address":"3387 3rd Ave",
    "sg:city":"Bronx",
    "sg:classifiers":[
        {
            "category":"Home & Garden",
            "subcategory":"Furniture",
            "type":"Retail Goods"
        }
    ],
    "sg:phone":"+1   ",
    "sg:postcode":"10456",
    "sg:province":"NY",
    "wof:name":"Marlen Furniture Inc",
    "wof:placetype":"venue"
},
  "geometry": {"coordinates":[-73.907459,40.82726],"type":"Point"}
}