{
  "type": "Feature",
  "properties": {
    "addr:full":"208 Martense St Brooklyn NY 11226",
    "addr:housenumber":"208",
    "addr:postcode":"11226",
    "addr:street":"Martense St",
    "iso:country":"US",
    "sg:address":"208 Martense St",
    "sg:city":"Brooklyn",
    "sg:classifiers":[
        {
            "category":"Building & Trades",
            "subcategory":"Construction",
            "type":"Services"
        }
    ],
    "sg:phone":"+1 718 693 8525",
    "sg:postcode":"11226",
    "sg:province":"NY",
    "sg:tags":[
        "house"
    ],
    "wof:name":"Irving Smith Remodeling",
    "wof:placetype":"venue"
},
  "geometry": {"coordinates":[-73.950141,40.651589],"type":"Point"}
}