{
  "type": "Feature",
  "properties": {
    "iso:country":"US",
    "sg:address":"7609 Winterhaven Dr",
    "sg:city":"Liverpool",
    "sg:classifiers":[
        {
            "category":"Building & Trades",
            "subcategory":"Construction",
            "type":"Services"
        }
    ],
    "sg:phone":"+1 315 457 4524",
    "sg:postcode":"13088",
    "sg:province":"NY",
    "sg:tags":[
        "general",
        "contractor"
    ],
    "wof:name":"Vicott Residential Svc",
    "wof:placetype":"venue"
},
  "geometry": {"coordinates":[-76.182682,43.139804],"type":"Point"}
}