{
  "type": "Feature",
  "properties": {
    "iso:country":"US",
    "sg:address":"3631 US Hwy 69",
    "sg:city":"Mexico",
    "sg:classifiers":[
        {
            "category":"Personal",
            "subcategory":"Beauty Salon",
            "type":"Services"
        }
    ],
    "sg:phone":"+1 315 963 8692",
    "sg:postcode":"13114",
    "sg:province":"NY",
    "wof:name":"Perfections Hair Designs",
    "wof:placetype":"venue"
},
  "geometry": {"coordinates":[-76.22161,43.448111],"type":"Point"}
}