{
  "type": "Feature",
  "properties": {
    "addr:full":"445 New Karner Rd Albany NY 12205",
    "addr:housenumber":"445",
    "addr:postcode":"12205",
    "addr:street":"New Karner Rd",
    "iso:country":"US",
    "sg:address":"445 New Karner Rd",
    "sg:city":"Albany",
    "sg:classifiers":[
        {
            "category":"Health Services",
            "subcategory":"Clinic",
            "type":"Services"
        }
    ],
    "sg:phone":"+1 518 724 0200",
    "sg:postcode":"12205",
    "sg:province":"NY",
    "sg:tags":[
        "home"
    ],
    "sg:website":"www.stpetershealthcare.org",
    "wof:name":"Community Hospice",
    "wof:placetype":"venue"
},
  "geometry": {"coordinates":[-73.841408,42.740571],"type":"Point"}
}