{
  "type": "Feature",
  "properties": {
    "addr:full":"225 S Wellwood Ave Lindenhurst NY 11757",
    "addr:housenumber":"225",
    "addr:postcode":"11757",
    "addr:street":"S Wellwood Ave",
    "iso:country":"US",
    "sg:address":"225 S Wellwood Ave",
    "sg:city":"Lindenhurst",
    "sg:classifiers":[
        {
            "category":"Government",
            "subcategory":"Office",
            "type":"Public Place"
        }
    ],
    "sg:phone":"+1 631 957 7530",
    "sg:postcode":"11757",
    "sg:province":"NY",
    "sg:tags":[
        "fire",
        "protection"
    ],
    "wof:name":"Fire Department",
    "wof:placetype":"venue"
},
  "geometry": {"coordinates":[-73.372281,40.685811],"type":"Point"}
}