{
  "type": "Feature",
  "properties": {
    "iso:country":"US",
    "sg:address":"134 E Montauk Hwy",
    "sg:city":"Lindenhurst",
    "sg:classifiers":[
        {
            "category":"Travel",
            "subcategory":"Hotels & Motels",
            "type":"Entertainment"
        }
    ],
    "sg:phone":"+1 631 957 6300",
    "sg:postcode":"11757",
    "sg:province":"NY",
    "wof:name":"Marina Motel LLC",
    "wof:placetype":"venue"
},
  "geometry": {"coordinates":[-73.361217,40.67952],"type":"Point"}
}