{
  "type": "Feature",
  "properties": {
    "addr:full":"242 W 49th St New York NY 10019",
    "addr:housenumber":"242",
    "addr:postcode":"10019",
    "addr:street":"W 49Th St",
    "iso:country":"US",
    "sg:address":"242 W 49th St",
    "sg:city":"New York",
    "sg:classifiers":[
        {
            "category":"Travel",
            "subcategory":"Hotels & Motels",
            "type":"Entertainment"
        }
    ],
    "sg:phone":"+1 212 489 1797",
    "sg:postcode":"10019",
    "sg:province":"NY",
    "sg:website":"www.mayfairnewyork.com/",
    "wof:name":"Mayfair New York",
    "wof:placetype":"venue"
},
  "geometry": {"coordinates":[-73.9851,40.7612],"type":"Point"}
}