{
  "type": "Feature",
  "properties": {
    "addr:full":"531 Farber Lakes Dr Buffalo NY 14221",
    "addr:housenumber":"531",
    "addr:postcode":"14221",
    "addr:street":"Farber Lakes Dr",
    "iso:country":"US",
    "sg:address":"531 Farber Lakes Dr",
    "sg:city":"Buffalo",
    "sg:classifiers":[
        {
            "category":"Health Services",
            "subcategory":"Doctor",
            "type":"Services"
        }
    ],
    "sg:phone":"+1 716 633 7070",
    "sg:postcode":"14221",
    "sg:province":"NY",
    "wof:name":"Marshall D Fagin DDS",
    "wof:placetype":"venue"
},
  "geometry": {"coordinates":[-78.73258199999999,42.976185],"type":"Point"}
}