{
  "type": "Feature",
  "properties": {
    "addr:full":"319 E 85th St New York NY 10028",
    "addr:housenumber":"319",
    "addr:postcode":"10028",
    "addr:street":"E 85Th St",
    "iso:country":"US",
    "sg:address":"319 E 85th St",
    "sg:city":"New York",
    "sg:classifiers":[
        {
            "category":"Arts & Performance",
            "subcategory":"Theater",
            "type":"Entertainment"
        }
    ],
    "sg:phone":"+1 212 734 5145",
    "sg:postcode":"10028",
    "sg:province":"NY",
    "sg:tags":[
        "television",
        "program",
        "producer"
    ],
    "wof:name":"Gini International",
    "wof:placetype":"venue"
},
  "geometry": {"coordinates":[-73.950165,40.776445],"type":"Point"}
}