{
  "type": "Feature",
  "properties": {
    "iso:country":"US",
    "sg:address":"25 Hubbels Dr",
    "sg:city":"Mount Kisco",
    "sg:classifiers":[
        {
            "category":"Personal",
            "type":"Services"
        }
    ],
    "sg:phone":"+1 914 244 8811",
    "sg:postcode":"10549",
    "sg:province":"NY",
    "sg:tags":[
        "party",
        "planning",
        "event"
    ],
    "wof:name":"Jodi's Gym",
    "wof:placetype":"venue"
},
  "geometry": {"coordinates":[-73.724602,41.2164],"type":"Point"}
}