{
  "type": "Feature",
  "properties": {
    "addr:full":"7206 New Utrecht Avenue Brooklyn NY 11228",
    "addr:housenumber":"7206",
    "addr:postcode":"11228",
    "addr:street":"New Utrecht Avenue",
    "iso:country":"US",
    "sg:address":"7206 New Utrecht Avenue",
    "sg:city":"Brooklyn",
    "sg:classifiers":[
        {
            "category":"Restaurant",
            "type":"Food & Drink"
        }
    ],
    "sg:phone":"+1 718 331 7573",
    "sg:postcode":"11228",
    "sg:province":"NY",
    "wof:name":"Antonio Lombardo Luncheonette",
    "wof:placetype":"venue"
},
  "geometry": {"coordinates":[-73.999476,40.617966],"type":"Point"}
}