{
  "type": "Feature",
  "properties": {
    "addr:full":"704 Corporations Park Scotia NY 12302",
    "addr:housenumber":"704",
    "addr:postcode":"12302",
    "addr:street":"Corporations Park",
    "iso:country":"US",
    "sg:address":"704 Corporations Park",
    "sg:city":"Scotia",
    "sg:classifiers":[
        {
            "category":"Manufacturing",
            "subcategory":"Tools & Machinery",
            "type":"Manufacturing & Wholesale Goods"
        }
    ],
    "sg:phone":"+1 518 347 0955",
    "sg:postcode":"12302",
    "sg:province":"NY",
    "sg:tags":[
        "shop",
        "mfg",
        "machine",
        "equipment",
        "job",
        "original"
    ],
    "sg:website":"www.interactiveinstruments.com",
    "wof:name":"Interactive Instruments Inc",
    "wof:placetype":"venue"
},
  "geometry": {"coordinates":[-73.980868,42.837614],"type":"Point"}
}