{
  "type": "Feature",
  "properties": {
    "addr:full":"5020 Route 9W Newburgh NY 12550",
    "addr:housenumber":"5020",
    "addr:postcode":"12550",
    "addr:street":"Route 9W",
    "iso:country":"US",
    "sg:address":"5020 Route 9W",
    "sg:city":"Newburgh",
    "sg:classifiers":[
        {
            "category":"Building & Trades",
            "subcategory":"Construction",
            "type":"Services"
        }
    ],
    "sg:phone":"+1 845 569 9898",
    "sg:postcode":"12550",
    "sg:province":"NY",
    "sg:tags":[
        "contractor"
    ],
    "wof:name":"Hudson Highland Homes Inc",
    "wof:placetype":"venue"
},
  "geometry": {"coordinates":[-74.0214,41.521999],"type":"Point"}
}