{
  "type": "Feature",
  "properties": {
    "iso:country":"US",
    "sg:address":"1018 Oregon Rd",
    "sg:city":"Cortlandt Manor",
    "sg:classifiers":[
        {
            "category":"Shopping",
            "type":"Retail Goods"
        }
    ],
    "sg:phone":"+1 845 225 1323",
    "sg:postcode":"10567",
    "sg:province":"NY",
    "sg:tags":[
        "monument"
    ],
    "wof:name":"Hillside Memorials",
    "wof:placetype":"venue"
},
  "geometry": {"coordinates":[-73.900233,41.315274],"type":"Point"}
}