{
  "type": "Feature",
  "properties": {
    "iso:country":"US",
    "sg:address":"1005 Fulton St Ste B",
    "sg:city":"Farmingdale",
    "sg:classifiers":[
        {
            "category":"Shopping",
            "subcategory":"Party Supplies",
            "type":"Retail Goods"
        }
    ],
    "sg:phone":"+1 631 755 8695",
    "sg:postcode":"11735",
    "sg:province":"NY",
    "sg:tags":[
        "decorating",
        "convention"
    ],
    "wof:name":"Jd's Place",
    "wof:placetype":"venue"
},
  "geometry": {"coordinates":[-73.432777,40.724838],"type":"Point"}
}