{
  "type": "Feature",
  "properties": {
    "addr:full":"17 Rocky Ridge Rd White Plains NY 10604",
    "addr:housenumber":"17",
    "addr:postcode":"10604",
    "addr:street":"Rocky Ridge Rd",
    "iso:country":"US",
    "sg:address":"17 Rocky Ridge Rd",
    "sg:city":"White Plains",
    "sg:classifiers":[
        {
            "category":"Professional",
            "subcategory":"Computer Services",
            "type":"Services"
        }
    ],
    "sg:phone":"+1   ",
    "sg:postcode":"10604",
    "sg:province":"NY",
    "sg:tags":[
        "related"
    ],
    "wof:name":"Panda Group",
    "wof:placetype":"venue"
},
  "geometry": {"coordinates":[-73.739321,41.048275],"type":"Point"}
}