{
  "type": "Feature",
  "properties": {
    "iso:country":"US",
    "sg:address":"220 Church St",
    "sg:city":"New York",
    "sg:classifiers":[
        {
            "category":"Government",
            "subcategory":"Office",
            "type":"Public Place"
        }
    ],
    "sg:phone":"+1 212 442 2595",
    "sg:postcode":"10013",
    "sg:province":"NY",
    "sg:tags":[
        "village"
    ],
    "sg:website":"www.nycitydoe.com",
    "wof:name":"New York City Employment Dept",
    "wof:placetype":"venue"
},
  "geometry": {"coordinates":[-74.00649199999999,40.716812],"type":"Point"}
}