{
  "type": "Feature",
  "properties": {
    "addr:full":"5045 Lockport Rd Lockport NY 14094",
    "addr:housenumber":"5045",
    "addr:postcode":"14094",
    "addr:street":"Lockport Rd",
    "iso:country":"US",
    "sg:address":"5045 Lockport Rd",
    "sg:city":"Lockport",
    "sg:classifiers":[
        {
            "category":"Building & Trades",
            "subcategory":"Construction",
            "type":"Services"
        }
    ],
    "sg:phone":"+1 716 625 9866",
    "sg:postcode":"14094",
    "sg:province":"NY",
    "sg:tags":[
        "carpentry",
        "contractor"
    ],
    "wof:name":"Northwood Custom Shop",
    "wof:placetype":"venue"
},
  "geometry": {"coordinates":[-78.763451,43.133422],"type":"Point"}
}