{
  "type": "Feature",
  "properties": {
    "addr:full":"307 W 89 St New York NY 10024",
    "addr:housenumber":"307",
    "addr:postcode":"10024",
    "addr:street":"W 89 St",
    "iso:country":"US",
    "sg:address":"307 W 89 St",
    "sg:city":"New York",
    "sg:classifiers":[
        {
            "category":"Professional",
            "subcategory":"Research",
            "type":"Services"
        }
    ],
    "sg:phone":"+1   ",
    "sg:postcode":"10024",
    "sg:province":"NY",
    "sg:tags":[
        "organization",
        "noncommercial"
    ],
    "wof:name":"Vyronis Center For Study O",
    "wof:placetype":"venue"
},
  "geometry": {"coordinates":[-73.978531,40.791759],"type":"Point"}
}