{
  "type": "Feature",
  "properties": {
    "addr:full":"3513 Harlem Rd Buffalo NY 14225",
    "addr:housenumber":"3513",
    "addr:postcode":"14225",
    "addr:street":"Harlem Rd",
    "iso:country":"US",
    "sg:address":"3513 Harlem Rd",
    "sg:city":"Buffalo",
    "sg:classifiers":[
        {
            "category":"Restaurant",
            "type":"Food & Drink"
        }
    ],
    "sg:phone":"+1 716 836 7093",
    "sg:postcode":"14225",
    "sg:province":"NY",
    "wof:name":"John & Mary's",
    "wof:placetype":"venue"
},
  "geometry": {"coordinates":[-78.784302,42.939499],"type":"Point"}
}