{
  "type": "Feature",
  "properties": {
    "addr:full":"145 Guilford Ave Oakdale NY 11769",
    "addr:housenumber":"145",
    "addr:postcode":"11769",
    "addr:street":"Guilford Ave",
    "iso:country":"US",
    "sg:address":"145 Guilford Ave",
    "sg:city":"Oakdale",
    "sg:classifiers":[
        {
            "category":"Building & Trades",
            "subcategory":"Construction",
            "type":"Services"
        }
    ],
    "sg:phone":"+1 631 589 1431",
    "sg:postcode":"11769",
    "sg:province":"NY",
    "sg:tags":[
        "contractor"
    ],
    "wof:name":"Shannon of Long Island Constr",
    "wof:placetype":"venue"
},
  "geometry": {"coordinates":[-73.15302200000001,40.739694],"type":"Point"}
}