{
  "type": "Feature",
  "properties": {
    "addr:full":"42-08 30th Ave Astoria NY 11103",
    "addr:housenumber":"42-08",
    "addr:postcode":"11103",
    "addr:street":"30Th Ave",
    "iso:country":"US",
    "sg:address":"42-08 30th Ave",
    "sg:city":"Astoria",
    "sg:classifiers":[
        {
            "category":"Restaurant",
            "type":"Food & Drink"
        }
    ],
    "sg:phone":"+1 718 267 8587",
    "sg:postcode":"11103",
    "sg:province":"NY",
    "wof:name":"Ukus",
    "wof:placetype":"venue"
},
  "geometry": {"coordinates":[-73.913301,40.763075],"type":"Point"}
}