{
  "type": "Feature",
  "properties": {
    "iso:country":"US",
    "sg:address":"274 W Main St",
    "sg:city":"Victor",
    "sg:classifiers":[
        {
            "category":"Personal",
            "subcategory":"Beauty Salon",
            "type":"Services"
        }
    ],
    "sg:phone":"+1 585 924 7820",
    "sg:postcode":"14564",
    "sg:province":"NY",
    "wof:name":"Hair Parlor",
    "wof:placetype":"venue"
},
  "geometry": {"coordinates":[-77.41874900000001,42.987041],"type":"Point"}
}