{
  "type": "Feature",
  "properties": {
    "addr:full":"195 Morgan Ave Brooklyn NY 11237",
    "addr:housenumber":"195",
    "addr:postcode":"11237",
    "addr:street":"Morgan Ave",
    "iso:country":"US",
    "sg:address":"195 Morgan Ave",
    "sg:city":"Brooklyn",
    "sg:classifiers":[
        {
            "category":"Bars & Pubs",
            "subcategory":"Nightclub",
            "type":"Food & Drink"
        }
    ],
    "sg:phone":"+1 718 366 5174",
    "sg:postcode":"11237",
    "sg:province":"NY",
    "sg:tags":[
        "nightlife"
    ],
    "wof:name":"Detour",
    "wof:placetype":"venue"
},
  "geometry": {"coordinates":[-73.933789,40.710694],"type":"Point"}
}