{
  "type": "Feature",
  "properties": {
    "addr:full":"88 Guyon Ave Staten Island NY 10306",
    "addr:housenumber":"88",
    "addr:postcode":"10306",
    "addr:street":"Guyon Ave",
    "iso:country":"US",
    "sg:address":"88 Guyon Ave",
    "sg:city":"Staten Island",
    "sg:classifiers":[
        {
            "category":"Shopping",
            "subcategory":"Bicycles & Sporting Goods",
            "type":"Retail Goods"
        }
    ],
    "sg:phone":"+1 718 980 7547",
    "sg:postcode":"10306",
    "sg:province":"NY",
    "sg:tags":[
        "equipment",
        "diver",
        "supply"
    ],
    "wof:name":"Down Under Sports",
    "wof:placetype":"venue"
},
  "geometry": {"coordinates":[-74.12948900000001,40.565061],"type":"Point"}
}