{
  "type": "Feature",
  "properties": {
    "iso:country":"US",
    "sg:address":"600 Hallock Ave",
    "sg:city":"Port Jefferson Sta",
    "sg:classifiers":[
        {
            "category":"Food & Beverages",
            "subcategory":"Groceries & Convenience Stores",
            "type":"Retail Goods"
        }
    ],
    "sg:phone":"+1 631 331 5688",
    "sg:postcode":"11776",
    "sg:province":"NY",
    "wof:name":"Koolmart Inc",
    "wof:placetype":"venue"
},
  "geometry": {"coordinates":[-73.046898,40.932098],"type":"Point"}
}