{
  "type": "Feature",
  "properties": {
    "iso:country":"US",
    "sg:address":"75 Madison Ave",
    "sg:city":"Valhalla",
    "sg:classifiers":[
        {
            "category":"Building & Trades",
            "subcategory":"Construction",
            "type":"Services"
        }
    ],
    "sg:phone":"+1 914 946 2562",
    "sg:postcode":"10595",
    "sg:province":"NY",
    "sg:tags":[
        "floor",
        "laying",
        "contractor"
    ],
    "wof:name":"Complete Wood Flooring Inc",
    "wof:placetype":"venue"
},
  "geometry": {"coordinates":[-73.77381200000001,41.077839],"type":"Point"}
}