{
  "type": "Feature",
  "properties": {
    "iso:country":"US",
    "sg:address":"875 W Jericho Tpke",
    "sg:city":"Smithtown",
    "sg:classifiers":[
        {
            "category":"Banks & Credit Unions",
            "subcategory":"Financial Services",
            "type":"Services"
        }
    ],
    "sg:phone":"+1 631 864 4400",
    "sg:postcode":"11787",
    "sg:province":"NY",
    "sg:tags":[
        "broker",
        "mortgage"
    ],
    "wof:name":"Dream Home Equities",
    "wof:placetype":"venue"
},
  "geometry": {"coordinates":[-73.240886,40.847827],"type":"Point"}
}