{
  "type": "Feature",
  "properties": {
    "addr:full":"21 W 16th St New York NY 10011",
    "addr:housenumber":"21",
    "addr:postcode":"10011",
    "addr:street":"W 16Th St",
    "iso:country":"US",
    "sg:address":"21 W 16th St",
    "sg:city":"New York",
    "sg:classifiers":[
        {
            "category":"Building & Trades",
            "subcategory":"Construction",
            "type":"Services"
        }
    ],
    "sg:phone":"+1 646 230 7222",
    "sg:postcode":"10011",
    "sg:province":"NY",
    "sg:tags":[
        "interior",
        "design"
    ],
    "wof:name":"Courtney Sloane Design",
    "wof:placetype":"venue"
},
  "geometry": {"coordinates":[-73.99369799999999,40.737598],"type":"Point"}
}