{
  "type": "Feature",
  "properties": {
    "addr:full":"2 Brinkerhoff St Plattsburgh NY 12901",
    "addr:housenumber":"2",
    "addr:postcode":"12901",
    "addr:street":"Brinkerhoff St",
    "iso:country":"US",
    "sg:address":"2 Brinkerhoff St",
    "sg:city":"Plattsburgh",
    "sg:classifiers":[
        {
            "category":"Banks & Credit Unions",
            "subcategory":"Bank",
            "type":"Services"
        }
    ],
    "sg:phone":"+1 518 565 3500",
    "sg:postcode":"12901",
    "sg:province":"NY",
    "wof:name":"Key Bank",
    "wof:placetype":"venue"
},
  "geometry": {"coordinates":[-73.453065,44.69712],"type":"Point"}
}