{
  "type": "Feature",
  "properties": {
    "addr:full":"126 Lake Ave Sto Yonkers NY 10703",
    "addr:housenumber":"126",
    "addr:postcode":"10703",
    "addr:street":"Lake Ave",
    "iso:country":"US",
    "sg:address":"126 Lake Ave Sto",
    "sg:city":"Yonkers",
    "sg:classifiers":[
        {
            "category":"Retail",
            "subcategory":"Laundry & Dry Cleaning",
            "type":"Services"
        }
    ],
    "sg:phone":"+1 914 961 0178",
    "sg:postcode":"10703",
    "sg:province":"NY",
    "sg:tags":[
        "laundries-self",
        "operated",
        "washer",
        "dryer",
        "coin"
    ],
    "wof:name":"Lake Morningside Laundrynet",
    "wof:placetype":"venue"
},
  "geometry": {"coordinates":[-73.886865,40.947003],"type":"Point"}
}