{
  "type": "Feature",
  "properties": {
    "addr:full":"537 N Conduit Blvd Brooklyn NY 11208",
    "addr:housenumber":"537",
    "addr:postcode":"11208",
    "addr:street":"N Conduit Blvd",
    "iso:country":"US",
    "sg:address":"537 N Conduit Blvd",
    "sg:city":"Brooklyn",
    "sg:classifiers":[
        {
            "category":"Retail",
            "subcategory":"Auto Repair",
            "type":"Services"
        }
    ],
    "sg:phone":"+1   ",
    "sg:postcode":"11208",
    "sg:province":"NY",
    "sg:tags":[
        "shop",
        "automotive",
        "ti",
        "a",
        "general"
    ],
    "wof:name":"Goodyear",
    "wof:placetype":"venue"
},
  "geometry": {"coordinates":[-73.86886199999999,40.677236],"type":"Point"}
}