{
  "type": "Feature",
  "properties": {
    "iso:country":"US",
    "sg:address":"216 Crow Hill Rd",
    "sg:city":"Laurens",
    "sg:classifiers":[
        {
            "category":"Sports & Exercise",
            "subcategory":"Golf",
            "type":"Entertainment"
        }
    ],
    "sg:phone":"+1 607 432 2713",
    "sg:postcode":"13796",
    "sg:province":"NY",
    "sg:tags":[
        "course"
    ],
    "wof:name":"Edgewood Golf Course",
    "wof:placetype":"venue"
},
  "geometry": {"coordinates":[-75.126392,42.561491],"type":"Point"}
}