{
  "type": "Feature",
  "properties": {
    "addr:full":"1157 Sutter Ave Brooklyn NY 11208",
    "addr:housenumber":"1157",
    "addr:postcode":"11208",
    "addr:street":"Sutter Ave",
    "iso:country":"US",
    "sg:address":"1157 Sutter Ave",
    "sg:city":"Brooklyn",
    "sg:classifiers":[
        {
            "category":"Food & Beverages",
            "subcategory":"Groceries & Convenience Stores",
            "type":"Retail Goods"
        }
    ],
    "sg:phone":"+1   ",
    "sg:postcode":"11208",
    "sg:province":"NY",
    "wof:name":"Felio Food Corp",
    "wof:placetype":"venue"
},
  "geometry": {"coordinates":[-73.874832,40.672428],"type":"Point"}
}