{
  "type": "Feature",
  "properties": {
    "addr:full":"27 William St Cazenovia NY 13035",
    "addr:housenumber":"27",
    "addr:postcode":"13035",
    "addr:street":"William St",
    "iso:country":"US",
    "sg:address":"27 William St",
    "sg:city":"Cazenovia",
    "sg:classifiers":[
        {
            "category":"Home & Garden",
            "subcategory":"Hardware",
            "type":"Retail Goods"
        },
        {
            "category":"Home & Garden",
            "subcategory":"Building Materials",
            "type":"Retail Goods"
        }
    ],
    "sg:phone":"+1 315 655 3417",
    "sg:postcode":"13035",
    "sg:province":"NY",
    "sg:tags":[
        "store"
    ],
    "wof:name":"Do It Best",
    "wof:placetype":"venue"
},
  "geometry": {"coordinates":[-75.849532,42.932199],"type":"Point"}
}