{
  "type": "Feature",
  "properties": {
    "addr:full":"433 W Broadway New York NY 10012",
    "addr:housenumber":"433",
    "addr:postcode":"10012",
    "addr:street":"W Broadway",
    "iso:country":"US",
    "sg:address":"433 W Broadway",
    "sg:city":"New York",
    "sg:classifiers":[
        {
            "category":"Personal",
            "subcategory":"Beauty Salon",
            "type":"Services"
        }
    ],
    "sg:phone":"+1 212 925 4461",
    "sg:postcode":"10012",
    "sg:province":"NY",
    "sg:tags":[
        "hair"
    ],
    "sg:website":"www.johndellaria.com",
    "wof:name":"John Dellaria Salon",
    "wof:placetype":"venue"
},
  "geometry": {"coordinates":[-74.000995,40.725418],"type":"Point"}
}