{
  "type": "Feature",
  "properties": {
    "addr:full":"182 Merritts Rd Farmingdale NY 11735",
    "addr:housenumber":"182",
    "addr:postcode":"11735",
    "addr:street":"Merritts Rd",
    "iso:country":"US",
    "sg:address":"182 Merritts Rd",
    "sg:city":"Farmingdale",
    "sg:classifiers":[
        {
            "category":"Shopping",
            "subcategory":"Gifts & Souvenirs",
            "type":"Retail Goods"
        }
    ],
    "sg:phone":"+1 516 420 0690",
    "sg:postcode":"11735",
    "sg:province":"NY",
    "sg:tags":[
        "cards",
        "greeting"
    ],
    "wof:name":"Sharon's Novelties Inc",
    "wof:placetype":"venue"
},
  "geometry": {"coordinates":[-73.45851399999999,40.723639],"type":"Point"}
}