{
  "type": "Feature",
  "properties": {
    "addr:full":"520 Bedford Rd Pleasantville NY 10570",
    "addr:housenumber":"520",
    "addr:postcode":"10570",
    "addr:street":"Bedford Rd",
    "iso:country":"US",
    "sg:address":"520 Bedford Rd",
    "sg:city":"Pleasantville",
    "sg:classifiers":[
        {
            "category":"Arena",
            "subcategory":"Sports Club",
            "type":"Entertainment"
        }
    ],
    "sg:phone":"+1 914 741 2710",
    "sg:postcode":"10570",
    "sg:province":"NY",
    "sg:tags":[
        "martial art"
    ],
    "sg:website":"www.cmaec.com",
    "wof:name":"Chinese Martial Arts & Educational Center",
    "wof:placetype":"venue"
},
  "geometry": {"coordinates":[-73.79459300000001,41.131816],"type":"Point"}
}