{
  "type": "Feature",
  "properties": {
    "iso:country":"US",
    "sg:address":"3522 154th St",
    "sg:city":"Flushing",
    "sg:classifiers":[
        {
            "category":"Professional",
            "subcategory":"Lawyer & Legal Services",
            "type":"Services"
        }
    ],
    "sg:phone":"+1 718 358 9400",
    "sg:postcode":"11354",
    "sg:province":"NY",
    "wof:name":"Bach Seyun Atty",
    "wof:placetype":"venue"
},
  "geometry": {"coordinates":[-73.810997,40.7658],"type":"Point"}
}