{
  "type": "Feature",
  "properties": {
    "addr:full":"423 Commerce Rd Vestal NY 13850",
    "addr:housenumber":"423",
    "addr:postcode":"13850",
    "addr:street":"Commerce Rd",
    "iso:country":"US",
    "sg:address":"423 Commerce Rd",
    "sg:city":"Vestal",
    "sg:classifiers":[
        {
            "category":"Shopping",
            "type":"Retail Goods"
        }
    ],
    "sg:phone":"+1 607 789 9203",
    "sg:postcode":"13850",
    "sg:province":"NY",
    "sg:tags":[
        "electronic",
        "merchandise"
    ],
    "sg:website":"www.easterncopy.com",
    "wof:name":"Eastern Copy Products LLC",
    "wof:placetype":"venue"
},
  "geometry": {"coordinates":[-75.980799,42.108487],"type":"Point"}
}