{
  "type": "Feature",
  "properties": {
    "iso:country":"US",
    "sg:address":"171 Manor Ln",
    "sg:city":"Jamesport",
    "sg:classifiers":[
        {
            "category":"Retail",
            "subcategory":"Repair Shop",
            "type":"Services"
        }
    ],
    "sg:phone":"+1 631 722 4806",
    "sg:postcode":"11901",
    "sg:province":"NY",
    "sg:tags":[
        "equipment",
        "electronic",
        "supply"
    ],
    "wof:name":"Electronic Repair Wholesale",
    "wof:placetype":"venue"
},
  "geometry": {"coordinates":[-72.581622,40.951836],"type":"Point"}
}