{
  "type": "Feature",
  "properties": {
    "addr:full":"104 Federal St Plattsburgh NY 12956",
    "addr:housenumber":"104",
    "addr:postcode":"12956",
    "addr:street":"Federal St",
    "iso:country":"US",
    "sg:address":"104 Federal St",
    "sg:city":"Plattsburgh",
    "sg:classifiers":[
        {
            "category":"Government",
            "subcategory":"Office",
            "type":"Public Place"
        }
    ],
    "sg:phone":"+1 518 563 1406",
    "sg:postcode":"12956",
    "sg:province":"NY",
    "sg:tags":[
        "congressman"
    ],
    "wof:name":"Congressmans McHughs Office",
    "wof:placetype":"venue"
},
  "geometry": {"coordinates":[-73.50796,44.074262],"type":"Point"}
}