{
  "type": "Feature",
  "properties": {
    "iso:country":"US",
    "sg:address":"1504 86th St",
    "sg:city":"Brooklyn",
    "sg:classifiers":[
        {
            "category":"Retail",
            "subcategory":"Portrait Studio",
            "type":"Services"
        }
    ],
    "sg:phone":"+1   ",
    "sg:postcode":"11228",
    "sg:province":"NY",
    "sg:tags":[
        "disc",
        "photography",
        "jockey",
        "wedding",
        "entertainment"
    ],
    "wof:name":"DElegance Wedding Center",
    "wof:placetype":"venue"
},
  "geometry": {"coordinates":[-74.008893,40.610961],"type":"Point"}
}