{
  "type": "Feature",
  "properties": {
    "addr:full":"674 S Country Rd Patchogue NY 11772",
    "addr:housenumber":"674",
    "addr:postcode":"11772",
    "addr:street":"S Country Rd",
    "iso:country":"US",
    "sg:address":"674 S Country Rd",
    "sg:city":"Patchogue",
    "sg:classifiers":[
        {
            "category":"Recreation",
            "type":"Entertainment"
        }
    ],
    "sg:phone":"+1   ",
    "sg:postcode":"11772",
    "sg:province":"NY",
    "wof:name":"Simms Karate Studio",
    "wof:placetype":"venue"
},
  "geometry": {"coordinates":[-72.963578,40.756723],"type":"Point"}
}