{
  "type": "Feature",
  "properties": {
    "addr:full":"6024 7th Ave Brooklyn NY 11220",
    "addr:housenumber":"6024",
    "addr:postcode":"11220",
    "addr:street":"7Th Ave",
    "iso:country":"US",
    "sg:address":"6024 7th Ave",
    "sg:city":"Brooklyn",
    "sg:classifiers":[
        {
            "category":"Food & Beverages",
            "subcategory":"Groceries & Convenience Stores",
            "type":"Retail Goods"
        }
    ],
    "sg:phone":"+1 718 492 2309",
    "sg:postcode":"11220",
    "sg:province":"NY",
    "sg:tags":[
        "grocer"
    ],
    "wof:name":"Rainbow Grocery & Deli",
    "wof:placetype":"venue"
},
  "geometry": {"coordinates":[-74.012398,40.636398],"type":"Point"}
}