{
  "type": "Feature",
  "properties": {
    "addr:full":"1279 1st Ave Manhattan NY 10065",
    "addr:housenumber":"1279",
    "addr:postcode":"10065",
    "addr:street":"1St Ave",
    "iso:country":"US",
    "sg:address":"1279 1st Ave",
    "sg:city":"Manhattan",
    "sg:classifiers":[
        {
            "category":"Food & Beverages",
            "subcategory":"Bakery",
            "type":"Retail Goods"
        }
    ],
    "sg:phone":"+1 212 570 9500",
    "sg:postcode":"10065",
    "sg:province":"NY",
    "sg:tags":[
        "sandwich"
    ],
    "wof:name":"Vicky's Cafe",
    "wof:placetype":"venue"
},
  "geometry": {"coordinates":[-73.957803,40.765813],"type":"Point"}
}