{
  "type": "Feature",
  "properties": {
    "iso:country":"US",
    "sg:address":"4152 W Main Street Rd 189",
    "sg:city":"Batavia",
    "sg:classifiers":[
        {
            "category":"Professional",
            "subcategory":"Business Services",
            "type":"Services"
        }
    ],
    "sg:phone":"+1 585 344 1727",
    "sg:postcode":"14020",
    "sg:province":"NY",
    "sg:tags":[
        "consultant",
        "coach"
    ],
    "sg:website":"http://www.keysite.com",
    "wof:name":"Key Business Services",
    "wof:placetype":"venue"
},
  "geometry": {"coordinates":[-78.20850900000001,43.002428],"type":"Point"}
}