{
  "type": "Feature",
  "properties": {
    "addr:full":"6406 Sunray Crst Victor NY 14564",
    "addr:housenumber":"6406",
    "addr:postcode":"14564",
    "addr:street":"Sunray Crst",
    "iso:country":"US",
    "sg:address":"6406 Sunray Crst",
    "sg:city":"Victor",
    "sg:classifiers":[
        {
            "category":"Building & Trades",
            "subcategory":"Construction",
            "type":"Services"
        }
    ],
    "sg:phone":"+1 585 924 9459",
    "sg:postcode":"14564",
    "sg:province":"NY",
    "sg:tags":[
        "contractor"
    ],
    "wof:name":"S Prez Enterprises Inc",
    "wof:placetype":"venue"
},
  "geometry": {"coordinates":[-77.381764,42.971273],"type":"Point"}
}