{
  "type": "Feature",
  "properties": {
    "addr:full":"450 Fashion Avenue, s. 2000 New York NY 10123",
    "addr:housenumber":"450",
    "addr:postcode":"2000;10123",
    "addr:street":"Fashion Avenue S.",
    "iso:country":"US",
    "sg:address":"450 Fashion Avenue, s. 2000",
    "sg:city":"New York",
    "sg:classifiers":[
        {
            "category":"Professional",
            "subcategory":"Advertising",
            "type":"Services"
        }
    ],
    "sg:postcode":"10123",
    "sg:province":"NY",
    "sg:tags":[
        "advertising",
        "optimization",
        "landing-page",
        "google",
        "campaign",
        "facebook",
        "performance",
        "online",
        "media"
    ],
    "sg:website":"http://www.ozonion.com",
    "wof:name":"Ozonion",
    "wof:placetype":"venue"
},
  "geometry": {"coordinates":[-73.990385,40.751362],"type":"Point"}
}