{
  "type": "Feature",
  "properties": {
    "iso:country":"US",
    "sg:address":"140 W 36 St",
    "sg:city":"New York",
    "sg:classifiers":[
        {
            "category":"Wholesale",
            "subcategory":"Apparel",
            "type":"Manufacturing & Wholesale Goods"
        }
    ],
    "sg:phone":"+1 212 967 2895",
    "sg:postcode":"10018",
    "sg:province":"NY",
    "sg:tags":[
        "textile",
        "importing"
    ],
    "wof:name":"Jenny Textiles USA Inc",
    "wof:placetype":"venue"
},
  "geometry": {"coordinates":[-73.989276,40.751962],"type":"Point"}
}