{
  "type": "Feature",
  "properties": {
    "addr:full":"201 Boulevard Scarsdale NY 10583",
    "addr:housenumber":"201",
    "addr:postcode":"10583",
    "addr:street":"Boulevard",
    "iso:country":"US",
    "sg:address":"201 Boulevard",
    "sg:city":"Scarsdale",
    "sg:classifiers":[
        {
            "category":"Education",
            "subcategory":"School",
            "type":"Public Place"
        }
    ],
    "sg:phone":"+1 914 723 5608",
    "sg:postcode":"10583",
    "sg:province":"NY",
    "sg:tags":[
        "elementary",
        "8",
        "k"
    ],
    "wof:name":"Immaculate Heart Of Mary Schl",
    "wof:placetype":"venue"
},
  "geometry": {"coordinates":[-73.799808,40.981131],"type":"Point"}
}