{
  "type": "Feature",
  "properties": {
    "addr:full":"292 Greenwich St Hempstead NY 11550",
    "addr:housenumber":"292",
    "addr:postcode":"11550",
    "addr:street":"Greenwich St",
    "iso:country":"US",
    "sg:address":"292 Greenwich St",
    "sg:city":"Hempstead",
    "sg:classifiers":[
        {
            "category":"Personal",
            "subcategory":"Beauty Salon",
            "type":"Services"
        }
    ],
    "sg:phone":"+1 516 538 8742",
    "sg:postcode":"11550",
    "sg:province":"NY",
    "sg:tags":[
        "hair"
    ],
    "wof:name":"Expert Beauty Salon",
    "wof:placetype":"venue"
},
  "geometry": {"coordinates":[-73.615601,40.700001],"type":"Point"}
}