{
  "type": "Feature",
  "properties": {
    "addr:full":"83 Oak Hollow Garrison NY 10524",
    "addr:housenumber":"83",
    "addr:postcode":"10524",
    "addr:street":"Oak Hollow",
    "iso:country":"US",
    "sg:address":"83 Oak Hollow",
    "sg:city":"Garrison",
    "sg:classifiers":[
        {
            "category":"Communications",
            "subcategory":"Radio Station",
            "type":"Services"
        }
    ],
    "sg:phone":"+1   ",
    "sg:postcode":"10524",
    "sg:province":"NY",
    "sg:tags":[
        "broadcast",
        "motion",
        "production"
    ],
    "wof:name":"Smith Muniz Productions Inc",
    "wof:placetype":"venue"
},
  "geometry": {"coordinates":[-73.915632,41.395138],"type":"Point"}
}