{
  "type": "Feature",
  "properties": {
    "addr:full":"29 W 38th St New York NY 10018",
    "addr:housenumber":"29",
    "addr:postcode":"10018",
    "addr:street":"W 38Th St",
    "iso:country":"US",
    "sg:address":"29 W 38th St",
    "sg:city":"New York",
    "sg:classifiers":[
        {
            "category":"Sports & Exercise",
            "subcategory":"Bicycle Rental",
            "type":"Entertainment"
        }
    ],
    "sg:phone":"+1 212 768 8450",
    "sg:postcode":"10018",
    "sg:province":"NY",
    "sg:tags":[
        "wear"
    ],
    "wof:name":"Sportswear International",
    "wof:placetype":"venue"
},
  "geometry": {"coordinates":[-73.98356699999999,40.751496],"type":"Point"}
}