{
  "type": "Feature",
  "properties": {
    "iso:country":"US",
    "sg:address":"23 Cosgrove Ave",
    "sg:city":"West Haverstraw",
    "sg:classifiers":[
        {
            "category":"Retail",
            "subcategory":"Auto Repair",
            "type":"Services"
        }
    ],
    "sg:phone":"+1 845 429 1699",
    "sg:postcode":"10993",
    "sg:province":"NY",
    "sg:tags":[
        "repairing",
        "automobile"
    ],
    "wof:name":"IGN Auto Care",
    "wof:placetype":"venue"
},
  "geometry": {"coordinates":[-73.984043,41.209901],"type":"Point"}
}