{
  "type": "Feature",
  "properties": {
    "iso:country":"US",
    "sg:address":"228 Keller Ave",
    "sg:city":"Elmont",
    "sg:classifiers":[
        {
            "category":"Social Services",
            "subcategory":"Child Care",
            "type":"Services"
        }
    ],
    "sg:phone":"+1 516 216 1659",
    "sg:postcode":"11003",
    "sg:province":"NY",
    "sg:tags":[
        "day"
    ],
    "sg:website":"www.thefamilytreehousedaycare.com",
    "wof:name":"The \u00a0Family TreeHouse Day Care",
    "wof:placetype":"venue"
},
  "geometry": {"coordinates":[-73.692624,40.702058],"type":"Point"}
}