{
  "type": "Feature",
  "properties": {
    "iso:country":"US",
    "sg:address":"125 Neelytown Rd",
    "sg:city":"Montgomery",
    "sg:classifiers":[
        {
            "category":"Restaurant",
            "type":"Food & Drink"
        }
    ],
    "sg:phone":"+1 845 457 3163",
    "sg:postcode":"12549",
    "sg:province":"NY",
    "wof:name":"Days Inn",
    "wof:placetype":"venue"
},
  "geometry": {"coordinates":[-74.218002,41.505901],"type":"Point"}
}