{
  "type": "Feature",
  "properties": {
    "iso:country":"US",
    "sg:address":"97 W End Ave",
    "sg:city":"Brooklyn",
    "sg:classifiers":[
        {
            "category":"Deli",
            "type":"Food & Drink"
        },
        {
            "category":"Food & Beverages",
            "subcategory":"Bakery",
            "type":"Retail Goods"
        }
    ],
    "sg:phone":"+1 718 616 1095",
    "sg:postcode":"11235",
    "sg:province":"NY",
    "sg:tags":[
        "sandwich"
    ],
    "wof:name":"Ocean View Deli",
    "wof:placetype":"venue"
},
  "geometry": {"coordinates":[-73.95320100000001,40.579399],"type":"Point"}
}