{
  "type": "Feature",
  "properties": {
    "iso:country":"US",
    "sg:address":"17519 Old Rices Rd",
    "sg:city":"Watertown",
    "sg:classifiers":[
        {
            "category":"Building & Trades",
            "subcategory":"Construction",
            "type":"Services"
        }
    ],
    "sg:phone":"+1 315 782 3888",
    "sg:postcode":"13601",
    "sg:province":"NY",
    "sg:tags":[
        "excavation",
        "operator",
        "contractor",
        "general",
        "trucking"
    ],
    "wof:name":"Ives Construction Inc",
    "wof:placetype":"venue"
},
  "geometry": {"coordinates":[-75.970731,43.917774],"type":"Point"}
}