{
  "type": "Feature",
  "properties": {
    "iso:country":"US",
    "sg:address":"42 Arden Pkwy",
    "sg:city":"Jamestown",
    "sg:classifiers":[
        {
            "category":"Organizations",
            "subcategory":"Religious Organization",
            "type":"Services"
        }
    ],
    "sg:phone":"+1 716 487 0676",
    "sg:postcode":"14701",
    "sg:province":"NY",
    "sg:tags":[
        "clergy"
    ],
    "wof:name":"Carmen D Taylor",
    "wof:placetype":"venue"
},
  "geometry": {"coordinates":[-79.251998,42.081281],"type":"Point"}
}