{
  "type": "Feature",
  "properties": {
    "addr:full":"4670 Margaret Dr Clarence NY 14031",
    "addr:housenumber":"4670",
    "addr:postcode":"14031",
    "addr:street":"Margaret Dr",
    "iso:country":"US",
    "sg:address":"4670 Margaret Dr",
    "sg:city":"Clarence",
    "sg:classifiers":[
        {
            "category":"Retail",
            "subcategory":"Auto Repair",
            "type":"Services"
        }
    ],
    "sg:phone":"+1   ",
    "sg:postcode":"14031",
    "sg:province":"NY",
    "sg:tags":[
        "shop",
        "tire",
        "general"
    ],
    "wof:name":"Clayton Tire & Auto",
    "wof:placetype":"venue"
},
  "geometry": {"coordinates":[-78.58433599999999,42.976489],"type":"Point"}
}