{
  "type": "Feature",
  "properties": {
    "addr:full":"80 Maple Ave Smithtown NY 11787",
    "addr:housenumber":"80",
    "addr:postcode":"11787",
    "addr:street":"Maple Ave",
    "iso:country":"US",
    "sg:address":"80 Maple Ave",
    "sg:city":"Smithtown",
    "sg:classifiers":[
        {
            "category":"Health Services",
            "subcategory":"Doctor",
            "type":"Services"
        }
    ],
    "sg:phone":"+1 516 473 0013",
    "sg:postcode":"11787",
    "sg:province":"NY",
    "sg:tags":[
        "medical"
    ],
    "wof:name":"Glenn Edward MD",
    "wof:placetype":"venue"
},
  "geometry": {"coordinates":[-73.19734,40.853673],"type":"Point"}
}