{
  "type": "Feature",
  "properties": {
    "iso:country":"US",
    "sg:address":"921 Montauk Hwy",
    "sg:city":"Shirley",
    "sg:classifiers":[
        {
            "category":"Shopping",
            "subcategory":"Musical Instruments",
            "type":"Retail Goods"
        }
    ],
    "sg:phone":"+1 631 395 0234",
    "sg:postcode":"11967",
    "sg:province":"NY",
    "sg:tags":[
        "music",
        "dealer"
    ],
    "wof:name":"Power Play Music & Electronics",
    "wof:placetype":"venue"
},
  "geometry": {"coordinates":[-72.864172,40.801791],"type":"Point"}
}