{
  "type": "Feature",
  "properties": {
    "addr:full":"780 3 Ave New York NY 10017",
    "addr:housenumber":"780",
    "addr:postcode":"10017",
    "addr:street":"3 Ave",
    "iso:country":"US",
    "sg:address":"780 3 Ave",
    "sg:city":"New York",
    "sg:classifiers":[
        {
            "category":"Banks & Credit Unions",
            "subcategory":"Investment Brokerage",
            "type":"Services"
        }
    ],
    "sg:phone":"+1 212 551 1600",
    "sg:postcode":"10017",
    "sg:province":"NY",
    "sg:tags":[
        "advisory",
        "manager",
        "financial"
    ],
    "wof:name":"Deerfield Management LP",
    "wof:placetype":"venue"
},
  "geometry": {"coordinates":[-73.974935,40.7501],"type":"Point"}
}