{
  "type": "Feature",
  "properties": {
    "iso:country":"US",
    "sg:address":"704 Emerson St",
    "sg:city":"Woodmere",
    "sg:classifiers":[
        {
            "category":"Manufacturing",
            "subcategory":"Retail Goods",
            "type":"Manufacturing & Wholesale Goods"
        }
    ],
    "sg:phone":"+1 516 295 9733",
    "sg:postcode":"11598",
    "sg:province":"NY",
    "sg:tags":[
        "manufacturer"
    ],
    "sg:website":"www.mtletching.com",
    "wof:name":"MTL Etching Industries Inc",
    "wof:placetype":"venue"
},
  "geometry": {"coordinates":[-73.722877,40.632308],"type":"Point"}
}