{
  "type": "Feature",
  "properties": {
    "iso:country":"US",
    "sg:address":"559 North Ave",
    "sg:city":"New Rochelle",
    "sg:classifiers":[
        {
            "category":"Home & Garden",
            "subcategory":"Building Materials",
            "type":"Retail Goods"
        }
    ],
    "sg:phone":"+1 212 869 8449",
    "sg:postcode":"10801",
    "sg:province":"NY",
    "sg:tags":[
        "roofing"
    ],
    "wof:name":"Roofing Maintenance Conslnts",
    "wof:placetype":"venue"
},
  "geometry": {"coordinates":[-73.787211,40.920895],"type":"Point"}
}