{
  "type": "Feature",
  "properties": {
    "addr:full":"455 3 Ave New York NY 10016",
    "addr:housenumber":"455",
    "addr:postcode":"10016",
    "addr:street":"3 Ave",
    "iso:country":"US",
    "sg:address":"455 3 Ave",
    "sg:city":"New York",
    "sg:classifiers":[
        {
            "category":"Retail",
            "subcategory":"Repair Shop",
            "type":"Services"
        }
    ],
    "sg:phone":"+1 212 584 7026",
    "sg:postcode":"10016",
    "sg:province":"NY",
    "sg:tags":[
        "lock",
        "locksmith"
    ],
    "wof:name":"24 Hour Emergency Locksmith",
    "wof:placetype":"venue"
},
  "geometry": {"coordinates":[-73.981312,40.741351],"type":"Point"}
}