{
  "type": "Feature",
  "properties": {
    "addr:full":"1181 Lincoln Ave Lockport NY 14094",
    "addr:housenumber":"1181",
    "addr:postcode":"14094",
    "addr:street":"Lincoln Ave",
    "iso:country":"US",
    "sg:address":"1181 Lincoln Ave",
    "sg:city":"Lockport",
    "sg:classifiers":[
        {
            "category":"Shopping",
            "subcategory":"Books",
            "type":"Retail Goods"
        },
        {
            "category":"Shopping",
            "type":"Retail Goods"
        }
    ],
    "sg:phone":"+1 716 433 6049",
    "sg:postcode":"14094",
    "sg:province":"NY",
    "sg:tags":[
        "bookstore",
        "religious",
        "bible"
    ],
    "wof:name":"Pathways Christian Bookstore Inc",
    "wof:placetype":"venue"
},
  "geometry": {"coordinates":[-78.665071,43.153096],"type":"Point"}
}