{
  "type": "Feature",
  "properties": {
    "addr:full":"182 E 109th Street New York NY 10029",
    "addr:housenumber":"182",
    "addr:postcode":"10029",
    "addr:street":"E 109Th Street",
    "iso:country":"US",
    "sg:address":"182 E 109th Street",
    "sg:city":"New York",
    "sg:classifiers":[
        {
            "category":"Food & Beverages",
            "subcategory":"Groceries & Convenience Stores",
            "type":"Retail Goods"
        }
    ],
    "sg:phone":"+1 212 996 0961",
    "sg:postcode":"10029",
    "sg:province":"NY",
    "wof:name":"Urbano Spanish American",
    "wof:placetype":"venue"
},
  "geometry": {"coordinates":[-73.94393599999999,40.793722],"type":"Point"}
}