{
  "type": "Feature",
  "properties": {
    "addr:full":"6558 State Highway 56 Potsdam NY 13676",
    "addr:housenumber":"6558",
    "addr:postcode":"13676",
    "addr:street":"State Highway 56",
    "iso:country":"US",
    "sg:address":"6558 State Highway 56",
    "sg:city":"Potsdam",
    "sg:classifiers":[
        {
            "category":"Real Estate",
            "subcategory":"Real Estate Services",
            "type":"Services"
        },
        {
            "category":"Real Estate",
            "subcategory":"Real Estate Agent",
            "type":"Services"
        }
    ],
    "sg:phone":"+1 315 265 6720",
    "sg:postcode":"13676",
    "sg:province":"NY",
    "sg:tags":[
        "buyer",
        "consultant",
        "management",
        "broker"
    ],
    "sg:website":"http://www.plumleyre.com",
    "wof:name":"Plumley Real Estate",
    "wof:placetype":"venue"
},
  "geometry": {"coordinates":[-74.987011,44.686056],"type":"Point"}
}