{
  "type": "Feature",
  "properties": {
    "iso:country":"US",
    "sg:address":"15 S Long Beach Rd",
    "sg:city":"Rockville Centre",
    "sg:classifiers":[
        {
            "category":"Food & Beverages",
            "subcategory":"Meat & Fish",
            "type":"Retail Goods"
        }
    ],
    "sg:phone":"+1 516 764 9591",
    "sg:postcode":"11570",
    "sg:province":"NY",
    "sg:tags":[
        "shop"
    ],
    "wof:name":"Janowski's Hamburgers Inc",
    "wof:placetype":"venue"
},
  "geometry": {"coordinates":[-73.6362,40.652],"type":"Point"}
}