{
  "type": "Feature",
  "properties": {
    "addr:full":"978 Rutland Rd Brooklyn NY 11212",
    "addr:housenumber":"978",
    "addr:postcode":"11212",
    "addr:street":"Rutland Rd",
    "iso:country":"US",
    "sg:address":"978 Rutland Rd",
    "sg:city":"Brooklyn",
    "sg:classifiers":[
        {
            "category":"Retail",
            "subcategory":"Laundry & Dry Cleaning",
            "type":"Services"
        }
    ],
    "sg:phone":"+1 718 773 1618",
    "sg:postcode":"11212",
    "sg:province":"NY",
    "sg:tags":[
        "cleaners",
        "plant",
        "drycleaning"
    ],
    "wof:name":"Willie's Cleaners",
    "wof:placetype":"venue"
},
  "geometry": {"coordinates":[-73.927148,40.662019],"type":"Point"}
}