{
  "type": "Feature",
  "properties": {
    "addr:full":"117 Pierpont Pl Staten Island NY 10314",
    "addr:housenumber":"117",
    "addr:postcode":"10314",
    "addr:street":"Pierpont Pl",
    "iso:country":"US",
    "sg:address":"117 Pierpont Pl",
    "sg:city":"Staten Island",
    "sg:classifiers":[
        {
            "category":"Manufacturing",
            "subcategory":"Furniture",
            "type":"Manufacturing & Wholesale Goods"
        }
    ],
    "sg:phone":"+1   ",
    "sg:postcode":"10314",
    "sg:province":"NY",
    "sg:tags":[
        "public",
        "household",
        "durable",
        "mfg"
    ],
    "wof:name":"Stuart Beitelman & Assoc",
    "wof:placetype":"venue"
},
  "geometry": {"coordinates":[-74.15614600000001,40.5785],"type":"Point"}
}