{
  "type": "Feature",
  "properties": {
    "addr:full":"40 Mohawk Ln Greenwich NY 06831",
    "addr:housenumber":"40",
    "addr:postcode":"06831",
    "addr:street":"Mohawk Ln",
    "iso:country":"US",
    "sg:address":"40 Mohawk Ln",
    "sg:city":"Greenwich",
    "sg:classifiers":[
        {
            "category":"Building & Trades",
            "subcategory":"Construction",
            "type":"Services"
        }
    ],
    "sg:phone":"+1 203 861 6616",
    "sg:postcode":"06831",
    "sg:province":"NY",
    "sg:tags":[
        "general",
        "contractor"
    ],
    "wof:name":"Art & Science Intl Inc",
    "wof:placetype":"venue"
},
  "geometry": {"coordinates":[-73.60722800000001,41.102577],"type":"Point"}
}