{
  "type": "Feature",
  "properties": {
    "addr:full":"1036 McDonald Ave Brooklyn NY 11230",
    "addr:housenumber":"1036",
    "addr:postcode":"11230",
    "addr:street":"Mcdonald Ave",
    "iso:country":"US",
    "sg:address":"1036 McDonald Ave",
    "sg:city":"Brooklyn",
    "sg:classifiers":[
        {
            "category":"Retail",
            "subcategory":"Car Wash",
            "type":"Services"
        }
    ],
    "sg:phone":"+1 718 436 2201",
    "sg:postcode":"11230",
    "sg:province":"NY",
    "sg:tags":[
        "polishing",
        "washing"
    ],
    "wof:name":"Imperial Car Wash",
    "wof:placetype":"venue"
},
  "geometry": {"coordinates":[-73.976799,40.628101],"type":"Point"}
}