{
  "type": "Feature",
  "properties": {
    "addr:full":"250 Broadway New York NY 10007",
    "addr:housenumber":"250",
    "addr:postcode":"10007",
    "addr:street":"Broadway",
    "iso:country":"US",
    "sg:address":"250 Broadway",
    "sg:city":"New York",
    "sg:classifiers":[
        {
            "category":"Government",
            "subcategory":"Office",
            "type":"Public Place"
        }
    ],
    "sg:phone":"+1 212 306 4385",
    "sg:postcode":"10007",
    "sg:province":"NY",
    "sg:tags":[
        "housing",
        "program"
    ],
    "wof:name":"Planning and Development Dept",
    "wof:placetype":"venue"
},
  "geometry": {"coordinates":[-74.006753,40.713618],"type":"Point"}
}