{
  "type": "Feature",
  "properties": {
    "addr:full":"38 W Main St Canajoharie NY 13317",
    "addr:housenumber":"38",
    "addr:postcode":"13317",
    "addr:street":"W Main St",
    "iso:country":"US",
    "sg:address":"38 W Main St",
    "sg:city":"Canajoharie",
    "sg:classifiers":[
        {
            "category":"Restaurant",
            "type":"Food & Drink"
        }
    ],
    "sg:phone":"+1 518 673 4411",
    "sg:postcode":"13317",
    "sg:province":"NY",
    "wof:name":"Mercato Pizza Restaurant",
    "wof:placetype":"venue"
},
  "geometry": {"coordinates":[-74.574291,42.906545],"type":"Point"}
}