{
  "type": "Feature",
  "properties": {
    "addr:full":"87 Birch Ln Valley Stream NY 11581",
    "addr:housenumber":"87",
    "addr:postcode":"11581",
    "addr:street":"Birch Ln",
    "iso:country":"US",
    "sg:address":"87 Birch Ln",
    "sg:city":"Valley Stream",
    "sg:classifiers":[
        {
            "category":"Professional",
            "subcategory":"Accounting & Tax Preparation",
            "type":"Services"
        }
    ],
    "sg:phone":"+1 516 791 6722",
    "sg:postcode":"11581",
    "sg:province":"NY",
    "sg:tags":[
        "bookkeeping"
    ],
    "wof:name":"Accountax USA Inc",
    "wof:placetype":"venue"
},
  "geometry": {"coordinates":[-73.708061,40.652481],"type":"Point"}
}