{
  "type": "Feature",
  "properties": {
    "iso:country":"US",
    "sg:address":"563 Argyle Rd",
    "sg:city":"Brooklyn",
    "sg:classifiers":[
        {
            "category":"Professional",
            "type":"Services"
        }
    ],
    "sg:phone":"+1 718 693 0729",
    "sg:postcode":"11230",
    "sg:province":"NY",
    "sg:tags":[
        "establishment"
    ],
    "wof:name":"Argyle Design Inc",
    "wof:placetype":"venue"
},
  "geometry": {"coordinates":[-73.965115,40.635444],"type":"Point"}
}