{
  "type": "Feature",
  "properties": {
    "addr:full":"76 Blueberry Ridge Dr Holtsville NY 11742",
    "addr:housenumber":"76",
    "addr:postcode":"11742",
    "addr:street":"Blueberry Ridge Dr",
    "iso:country":"US",
    "sg:address":"76 Blueberry Ridge Dr",
    "sg:city":"Holtsville",
    "sg:classifiers":[
        {
            "category":"Retail",
            "subcategory":"Portrait Studio",
            "type":"Services"
        }
    ],
    "sg:phone":"+1 631 207 7468",
    "sg:postcode":"11742",
    "sg:province":"NY",
    "sg:tags":[
        "photography"
    ],
    "wof:name":"Top Performance Photography",
    "wof:placetype":"venue"
},
  "geometry": {"coordinates":[-73.03451800000001,40.808086],"type":"Point"}
}