{
  "type": "Feature",
  "properties": {
    "iso:country":"US",
    "sg:address":"350 3rd St",
    "sg:city":"Niagara Falls",
    "sg:classifiers":[
        {
            "category":"Professional",
            "type":"Services"
        }
    ],
    "sg:phone":"+1 716 278 8310",
    "sg:postcode":"14303",
    "sg:province":"NY",
    "sg:tags":[
        "establishment"
    ],
    "wof:name":"Niagara Ramps Inc",
    "wof:placetype":"venue"
},
  "geometry": {"coordinates":[-79.05920399999999,43.088221],"type":"Point"}
}