{
  "type": "Feature",
  "properties": {
    "addr:full":"60 Gregory Hill Rd Greenville NY 12083",
    "addr:housenumber":"60",
    "addr:postcode":"12083",
    "addr:street":"Gregory Hill Rd",
    "iso:country":"US",
    "sg:address":"60 Gregory Hill Rd",
    "sg:city":"Greenville",
    "sg:classifiers":[
        {
            "category":"Shopping",
            "subcategory":"Bicycles & Sporting Goods",
            "type":"Retail Goods"
        }
    ],
    "sg:phone":"+1 518 966 8441",
    "sg:postcode":"12083",
    "sg:province":"NY",
    "wof:name":"Witt's Firearms & Gunsmithing",
    "wof:placetype":"venue"
},
  "geometry": {"coordinates":[-73.99645,42.456741],"type":"Point"}
}