{
  "type": "Feature",
  "properties": {
    "iso:country":"US",
    "sg:address":"307 W 37th St",
    "sg:city":"New York",
    "sg:classifiers":[
        {
            "category":"Food & Beverages",
            "subcategory":"Liquor & Beverages",
            "type":"Retail Goods"
        }
    ],
    "sg:phone":"+1 212 279 6455",
    "sg:postcode":"10018",
    "sg:province":"NY",
    "sg:tags":[
        "beer",
        "spirit",
        "wine"
    ],
    "wof:name":"Mitchells Beverage Direct",
    "wof:placetype":"venue"
},
  "geometry": {"coordinates":[-73.992599,40.7542],"type":"Point"}
}