{
  "type": "Feature",
  "properties": {
    "iso:country":"US",
    "sg:address":"256 Moe Rd",
    "sg:city":"Clifton Park",
    "sg:classifiers":[
        {
            "category":"Home & Garden",
            "subcategory":"Building Materials",
            "type":"Retail Goods"
        }
    ],
    "sg:phone":"+1 518 348 1044",
    "sg:postcode":"12065",
    "sg:province":"NY",
    "sg:tags":[
        "mixed",
        "concrete"
    ],
    "wof:name":"Clifton Park Concrete",
    "wof:placetype":"venue"
},
  "geometry": {"coordinates":[-73.79008899999999,42.831128],"type":"Point"}
}