{
  "type": "Feature",
  "properties": {
    "iso:country":"US",
    "sg:address":"930 Water St",
    "sg:city":"Kent",
    "sg:classifiers":[
        {
            "category":"Recreation",
            "subcategory":"Marina",
            "type":"Entertainment"
        }
    ],
    "sg:phone":"+1   ",
    "sg:postcode":"14477",
    "sg:province":"NY",
    "sg:tags":[
        "operation",
        "boat"
    ],
    "wof:name":"Oak Orchard Riverside Marine",
    "wof:placetype":"venue"
},
  "geometry": {"coordinates":[-78.190755,43.370677],"type":"Point"}
}