{
  "type": "Feature",
  "properties": {
    "addr:full":"129 Southside Dr Owego NY 13827",
    "addr:housenumber":"129",
    "addr:postcode":"13827",
    "addr:street":"Southside Dr",
    "iso:country":"US",
    "sg:address":"129 Southside Dr",
    "sg:city":"Owego",
    "sg:classifiers":[
        {
            "category":"Home & Garden",
            "subcategory":"Carpets & Floor Coverings",
            "type":"Retail Goods"
        }
    ],
    "sg:phone":"+1   ",
    "sg:postcode":"13827",
    "sg:province":"NY",
    "wof:name":"3 D Floors",
    "wof:placetype":"venue"
},
  "geometry": {"coordinates":[-76.258472,42.098788],"type":"Point"}
}