{
  "type": "Feature",
  "properties": {
    "addr:full":"128 Cedarhurst Ave Cedarhurst NY 11516",
    "addr:housenumber":"128",
    "addr:postcode":"11516",
    "addr:street":"Cedarhurst Ave",
    "iso:country":"US",
    "sg:address":"128 Cedarhurst Ave",
    "sg:city":"Cedarhurst",
    "sg:classifiers":[
        {
            "category":"Wholesale",
            "subcategory":"Electrical",
            "type":"Manufacturing & Wholesale Goods"
        }
    ],
    "sg:phone":"+1 516 374 3003",
    "sg:postcode":"11516",
    "sg:province":"NY",
    "sg:tags":[
        "wireless",
        "communications"
    ],
    "wof:name":"Proxi Communications Inc",
    "wof:placetype":"venue"
},
  "geometry": {"coordinates":[-73.72452800000001,40.622886],"type":"Point"}
}