{
  "type": "Feature",
  "properties": {
    "iso:country":"US",
    "sg:address":"434 Evergreen Ct",
    "sg:city":"Central Valley",
    "sg:classifiers":[
        {
            "category":"Shopping",
            "subcategory":"Clothing, Apparel, & Fashions",
            "type":"Retail Goods"
        }
    ],
    "sg:phone":"+1   ",
    "sg:postcode":"10917",
    "sg:province":"NY",
    "sg:tags":[
        "wear"
    ],
    "wof:name":"Carters Factory Outlet",
    "wof:placetype":"venue"
},
  "geometry": {"coordinates":[-74.126352,41.316539],"type":"Point"}
}