{
  "type": "Feature",
  "properties": {
    "iso:country":"US",
    "sg:address":"14 Thomas St",
    "sg:city":"Kingston",
    "sg:classifiers":[
        {
            "category":"Restaurant",
            "type":"Food & Drink"
        }
    ],
    "sg:menulink":"http://www.allmenus.com/ny/kingston/82535-cosimos-kingston/menu/",
    "sg:phone":"+1 845 340 0550",
    "sg:postcode":"12401",
    "sg:province":"NY",
    "sg:tags":[
        "american",
        "pizza"
    ],
    "wof:name":"Cosimo's Kingston",
    "wof:placetype":"venue"
},
  "geometry": {"coordinates":[-74.002287,41.929334],"type":"Point"}
}