{
  "type": "Feature",
  "properties": {
    "addr:full":"40 W Burnside Avenue Bronx NY 10453",
    "addr:housenumber":"40",
    "addr:postcode":"10453",
    "addr:street":"W Burnside Avenue",
    "iso:country":"US",
    "sg:address":"40 W Burnside Avenue",
    "sg:city":"Bronx",
    "sg:classifiers":[
        {
            "category":"Retail",
            "subcategory":"Event Space",
            "type":"Services"
        }
    ],
    "sg:phone":"+1 718 299 7770",
    "sg:postcode":"10453",
    "sg:province":"NY",
    "sg:tags":[
        "venue"
    ],
    "wof:name":"Burnside Hall",
    "wof:placetype":"venue"
},
  "geometry": {"coordinates":[-73.909284,40.854022],"type":"Point"}
}