{
  "type": "Feature",
  "properties": {
    "addr:full":"5284 Main St Munnsville NY 13409",
    "addr:housenumber":"5284",
    "addr:postcode":"13409",
    "addr:street":"Main St",
    "iso:country":"US",
    "sg:address":"5284 Main St",
    "sg:city":"Munnsville",
    "sg:classifiers":[
        {
            "category":"Retail",
            "subcategory":"Auto Repair",
            "type":"Services"
        }
    ],
    "sg:phone":"+1 315 495 2230",
    "sg:postcode":"13409",
    "sg:province":"NY",
    "sg:tags":[
        "repairing",
        "automobile"
    ],
    "wof:name":"3D Sales & Svc LLC",
    "wof:placetype":"venue"
},
  "geometry": {"coordinates":[-75.590102,42.978621],"type":"Point"}
}