{
  "type": "Feature",
  "properties": {
    "addr:full":"6421 Avenue N Brooklyn NY 11234",
    "addr:housenumber":"6421",
    "addr:postcode":"11234",
    "addr:street":"Avenue N",
    "iso:country":"US",
    "sg:address":"6421 Avenue N",
    "sg:city":"Brooklyn",
    "sg:classifiers":[
        {
            "category":"Real Estate",
            "subcategory":"Real Estate Agent",
            "type":"Services"
        }
    ],
    "sg:phone":"+1 718 444 6448",
    "sg:postcode":"11234",
    "sg:province":"NY",
    "wof:name":"935 Metropolitan Realty LLC",
    "wof:placetype":"venue"
},
  "geometry": {"coordinates":[-73.915346,40.620177],"type":"Point"}
}