{
  "type": "Feature",
  "properties": {
    "addr:full":"1255 Deer Park Ave North Babylon NY 11703",
    "addr:housenumber":"1255",
    "addr:postcode":"11703",
    "addr:street":"Deer Park Ave North",
    "iso:country":"US",
    "sg:address":"1255 Deer Park Ave",
    "sg:city":"North Babylon",
    "sg:classifiers":[
        {
            "category":"Restaurant",
            "type":"Food & Drink"
        }
    ],
    "sg:menulink":"http://www.allmenus.com/ny/babylon/188832-mcdonalds/menu/",
    "sg:postcode":"11703",
    "sg:province":"NY",
    "sg:tags":[
        "burger",
        "american"
    ],
    "wof:name":"McDonald's",
    "wof:placetype":"venue"
},
  "geometry": {"coordinates":[-73.32056300000001,40.738487],"type":"Point"}
}