{
  "type": "Feature",
  "properties": {
    "addr:full":"247 Cayuga Rd Buffalo NY 14225",
    "addr:housenumber":"247",
    "addr:postcode":"14225",
    "addr:street":"Cayuga Rd",
    "iso:country":"US",
    "sg:address":"247 Cayuga Rd",
    "sg:city":"Buffalo",
    "sg:classifiers":[
        {
            "category":"Real Estate",
            "subcategory":"Real Estate Services",
            "type":"Services"
        }
    ],
    "sg:phone":"+1 716 632 2100",
    "sg:postcode":"14225",
    "sg:province":"NY",
    "sg:tags":[
        "consultant",
        "commercial"
    ],
    "sg:website":"http://www.klwgroup.com",
    "wof:name":"KLW Group",
    "wof:placetype":"venue"
},
  "geometry": {"coordinates":[-78.744169,42.935003],"type":"Point"}
}