{
  "type": "Feature",
  "properties": {
    "iso:country":"US",
    "sg:address":"2468 US Hwy 11",
    "sg:city":"La Fayette",
    "sg:classifiers":[
        {
            "category":"Retail",
            "subcategory":"Veterinary Services",
            "type":"Services"
        }
    ],
    "sg:phone":"+1 315 677 3838",
    "sg:postcode":"13084",
    "sg:province":"NY",
    "wof:name":"Lafayette Veterinary Clinic",
    "wof:placetype":"venue"
},
  "geometry": {"coordinates":[-76.107061,42.874539],"type":"Point"}
}