{
  "type": "Feature",
  "properties": {
    "iso:country":"US",
    "sg:address":"122 Mastic Rd",
    "sg:city":"Mastic Beach",
    "sg:classifiers":[
        {
            "category":"Shopping",
            "subcategory":"Tobacco",
            "type":"Retail Goods"
        },
        {
            "category":"Food & Beverages",
            "subcategory":"Groceries & Convenience Stores",
            "type":"Retail Goods"
        }
    ],
    "sg:phone":"+1 631 399 6294",
    "sg:postcode":"11951",
    "sg:province":"NY",
    "sg:tags":[
        "shop"
    ],
    "wof:name":"Mikes One Stop",
    "wof:placetype":"venue"
},
  "geometry": {"coordinates":[-72.852097,40.7668],"type":"Point"}
}