{
  "type": "Feature",
  "properties": {
    "addr:full":"2116 Ridge Dr Valatie NY 12184",
    "addr:housenumber":"2116",
    "addr:postcode":"12184",
    "addr:street":"Ridge Dr",
    "iso:country":"US",
    "sg:address":"2116 Ridge Dr",
    "sg:city":"Valatie",
    "sg:classifiers":[
        {
            "category":"Insurance",
            "subcategory":"Insurance Agent",
            "type":"Services"
        }
    ],
    "sg:phone":"+1 518 581 9698",
    "sg:postcode":"12184",
    "sg:province":"NY",
    "wof:name":"Frontier Adjusters of Albany",
    "wof:placetype":"venue"
},
  "geometry": {"coordinates":[-73.68048400000001,42.416015],"type":"Point"}
}