{
  "type": "Feature",
  "properties": {
    "addr:full":"3505 Veterans Memorial Hwy Ronkonkoma NY 11779",
    "addr:housenumber":"3505",
    "addr:postcode":"11779",
    "addr:street":"Veterans Memorial Hwy",
    "iso:country":"US",
    "sg:address":"3505 Veterans Memorial Hwy",
    "sg:city":"Ronkonkoma",
    "sg:classifiers":[
        {
            "category":"Real Estate",
            "subcategory":"Real Estate Services",
            "type":"Services"
        },
        {
            "category":"Real Estate",
            "subcategory":"Real Estate Agent",
            "type":"Services"
        }
    ],
    "sg:phone":"+1 631 224 2694",
    "sg:postcode":"11779",
    "sg:province":"NY",
    "sg:tags":[
        "buyer",
        "consultant",
        "broker"
    ],
    "wof:name":"Property Assessment Consultants Inc",
    "wof:placetype":"venue"
},
  "geometry": {"coordinates":[-73.120587,40.786951],"type":"Point"}
}