{
  "type": "Feature",
  "properties": {
    "iso:country":"US",
    "sg:address":"199 Russell St",
    "sg:city":"Brooklyn",
    "sg:classifiers":[
        {
            "category":"Bars & Pubs",
            "type":"Food & Drink"
        }
    ],
    "sg:phone":"+1 718 383 5091",
    "sg:postcode":"11222",
    "sg:province":"NY",
    "sg:tags":[
        "drinking"
    ],
    "wof:name":"K & Z's Place Inc",
    "wof:placetype":"venue"
},
  "geometry": {"coordinates":[-73.944498,40.725615],"type":"Point"}
}