{
  "type": "Feature",
  "properties": {
    "iso:country":"US",
    "sg:address":"5426 W Genesee St",
    "sg:city":"Camillus",
    "sg:classifiers":[
        {
            "category":"Organizations",
            "subcategory":"Labor Organization",
            "type":"Services"
        }
    ],
    "sg:phone":"+1 315 484 9255",
    "sg:postcode":"13031",
    "sg:province":"NY",
    "sg:website":"www.canlawpc.com",
    "wof:name":"Cantone Law Firm",
    "wof:placetype":"venue"
},
  "geometry": {"coordinates":[-76.277078,43.040949],"type":"Point"}
}