{
  "type": "Feature",
  "properties": {
    "addr:full":"State University of NY, University at Buffalo Baird Research and Technology Park Amherst NY 14224",
    "addr:postcode":"14224",
    "iso:country":"US",
    "sg:address":"State University of NY, University at Buffalo Baird Research and Technology Park",
    "sg:city":"Amherst",
    "sg:classifiers":[
        {
            "category":"Professional",
            "subcategory":"Computer Services",
            "type":"Services"
        }
    ],
    "sg:postcode":"14224",
    "sg:province":"NY",
    "sg:tags":[
        "social-networking",
        "knowledge-networking",
        "artificial-intelligence",
        "web-3-0"
    ],
    "sg:website":"http://asitisinc.com",
    "wof:name":"As It Is",
    "wof:placetype":"venue"
},
  "geometry": {"coordinates":[-78.735062,42.859673],"type":"Point"}
}