{
  "type": "Feature",
  "properties": {
    "iso:country":"US",
    "sg:address":"33 Adirondack Ln",
    "sg:city":"Plattsburgh",
    "sg:classifiers":[
        {
            "category":"Building & Trades",
            "subcategory":"Construction",
            "type":"Services"
        }
    ],
    "sg:phone":"+1 518 570 8171",
    "sg:postcode":"12901",
    "sg:province":"NY",
    "sg:tags":[
        "house"
    ],
    "wof:name":"Benchmark Bldg & Devolpment",
    "wof:placetype":"venue"
},
  "geometry": {"coordinates":[-73.47204600000001,44.685204],"type":"Point"}
}