{
  "type": "Feature",
  "properties": {
    "iso:country":"US",
    "sg:address":"4408 Milestrip Rd",
    "sg:city":"Buffalo",
    "sg:classifiers":[
        {
            "category":"Restaurant",
            "type":"Food & Drink"
        }
    ],
    "sg:menulink":"http://www.allmenus.com/ny/hamburg/146723-boston-market/menu/",
    "sg:phone":"+1 716 823 2818",
    "sg:postcode":"14219",
    "sg:province":"NY",
    "sg:tags":[
        "barbecue",
        "american",
        "soup"
    ],
    "wof:name":"Boston Market",
    "wof:placetype":"venue"
},
  "geometry": {"coordinates":[-78.810148,42.789689],"type":"Point"}
}