{
  "type": "Feature",
  "properties": {
    "addr:full":"145 Stanton St Buffalo NY 14206",
    "addr:housenumber":"145",
    "addr:postcode":"14206",
    "addr:street":"Stanton St",
    "iso:country":"US",
    "sg:address":"145 Stanton St",
    "sg:city":"Buffalo",
    "sg:classifiers":[
        {
            "category":"Organizations",
            "subcategory":"Religious Organization",
            "type":"Services"
        }
    ],
    "sg:phone":"+1 716 856 0223",
    "sg:postcode":"14206",
    "sg:province":"NY",
    "sg:tags":[
        "church"
    ],
    "wof:name":"Peace Miss Baptist Church",
    "wof:placetype":"venue"
},
  "geometry": {"coordinates":[-78.84590300000001,42.885679],"type":"Point"}
}