{
  "type": "Feature",
  "properties": {
    "iso:country":"US",
    "sg:address":"14823 Holley Rd",
    "sg:city":"Albion",
    "sg:classifiers":[
        {
            "category":"Farming",
            "subcategory":"Farm",
            "type":"Manufacturing & Wholesale Goods"
        }
    ],
    "sg:phone":"+1 585 737 7461",
    "sg:postcode":"14411",
    "sg:province":"NY",
    "sg:tags":[
        "crop",
        "general"
    ],
    "wof:name":"Daniel Wright Farms",
    "wof:placetype":"venue"
},
  "geometry": {"coordinates":[-78.15419300000001,43.230691],"type":"Point"}
}