{
  "type": "Feature",
  "properties": {
    "iso:country":"US",
    "sg:address":"66 Deer Ridge Ct",
    "sg:city":"Getzville",
    "sg:classifiers":[
        {
            "category":"Shopping",
            "subcategory":"Catalog Store",
            "type":"Retail Goods"
        }
    ],
    "sg:phone":"+1   ",
    "sg:postcode":"14068",
    "sg:province":"NY",
    "sg:tags":[
        "mail",
        "house"
    ],
    "wof:name":"Biogen Idec Inc",
    "wof:placetype":"venue"
},
  "geometry": {"coordinates":[-78.76291500000001,43.011451],"type":"Point"}
}