{
  "type": "Feature",
  "properties": {
    "iso:country":"US",
    "sg:address":"215 E 68th St Ofc 2",
    "sg:city":"New York",
    "sg:classifiers":[
        {
            "category":"Health Services",
            "subcategory":"Doctor",
            "type":"Services"
        }
    ],
    "sg:phone":"+1 212 288 2869",
    "sg:postcode":"10065",
    "sg:province":"NY",
    "wof:name":"Martorella Andrew J MD",
    "wof:placetype":"venue"
},
  "geometry": {"coordinates":[-73.962067,40.767172],"type":"Point"}
}