{
  "type": "Feature",
  "properties": {
    "addr:full":"2 Nice Pak Ln Orangeburg NY 10962",
    "addr:housenumber":"2",
    "addr:postcode":"10962",
    "addr:street":"Nice Pak Ln",
    "iso:country":"US",
    "sg:address":"2 Nice Pak Ln",
    "sg:city":"Orangeburg",
    "sg:classifiers":[
        {
            "category":"Manufacturing",
            "subcategory":"Paper Products",
            "type":"Manufacturing & Wholesale Goods"
        }
    ],
    "sg:phone":"+1   ",
    "sg:postcode":"10962",
    "sg:province":"NY",
    "sg:tags":[
        "sanitary",
        "mill",
        "business",
        "mfg"
    ],
    "sg:website":"www.nicepak.com",
    "wof:name":"NICE-Pak Products Inc",
    "wof:placetype":"venue"
},
  "geometry": {"coordinates":[-73.940663,41.048702],"type":"Point"}
}