{
  "type": "Feature",
  "properties": {
    "iso:country":"US",
    "sg:address":"401 Co Rd 132",
    "sg:city":"Hagaman",
    "sg:classifiers":[
        {
            "category":"Building & Trades",
            "subcategory":"Construction",
            "type":"Services"
        }
    ],
    "sg:phone":"+1 518 843 1833",
    "sg:postcode":"12086",
    "sg:province":"NY",
    "sg:tags":[
        "house"
    ],
    "wof:name":"Watrobski Builders Inc",
    "wof:placetype":"venue"
},
  "geometry": {"coordinates":[-74.11498899999999,42.998255],"type":"Point"}
}