{
  "type": "Feature",
  "properties": {
    "addr:full":"2878 Nichols St Spencerport NY 14559",
    "addr:housenumber":"2878",
    "addr:postcode":"14559",
    "addr:street":"Nichols St",
    "iso:country":"US",
    "sg:address":"2878 Nichols St",
    "sg:city":"Spencerport",
    "sg:classifiers":[
        {
            "category":"Local Transit",
            "type":"Transportation"
        }
    ],
    "sg:phone":"+1   ",
    "sg:postcode":"14559",
    "sg:province":"NY",
    "wof:name":"Spencrprt Cntrl Schls Bus Tran",
    "wof:placetype":"venue"
},
  "geometry": {"coordinates":[-77.801672,43.18163],"type":"Point"}
}