{
  "type": "Feature",
  "properties": {
    "addr:full":"7 Sparrow Ln Hauppauge NY 11788",
    "addr:housenumber":"7",
    "addr:postcode":"11788",
    "addr:street":"Sparrow Ln",
    "iso:country":"US",
    "sg:address":"7 Sparrow Ln",
    "sg:city":"Hauppauge",
    "sg:classifiers":[
        {
            "category":"Organizations",
            "subcategory":"Membership Organization",
            "type":"Services"
        }
    ],
    "sg:phone":"+1 631 724 7331",
    "sg:postcode":"11788",
    "sg:province":"NY",
    "sg:tags":[
        "club",
        "private"
    ],
    "wof:name":"Honey Hills Garden Club",
    "wof:placetype":"venue"
},
  "geometry": {"coordinates":[-73.23799,40.818906],"type":"Point"}
}