{
  "type": "Feature",
  "properties": {
    "iso:country":"US",
    "sg:address":"30 Sunburst Dr",
    "sg:city":"Deer Park",
    "sg:classifiers":[
        {
            "category":"Education",
            "subcategory":"Special Training",
            "type":"Public Place"
        }
    ],
    "sg:phone":"+1 631 586 3941",
    "sg:postcode":"11729",
    "sg:province":"NY",
    "sg:tags":[
        "instruction",
        "music"
    ],
    "wof:name":"C J's Vocal Studio",
    "wof:placetype":"venue"
},
  "geometry": {"coordinates":[-73.30550700000001,40.754943],"type":"Point"}
}