{
  "type": "Feature",
  "properties": {
    "addr:full":"2745 Broadway St Buffalo NY 14227",
    "addr:housenumber":"2745",
    "addr:postcode":"14227",
    "addr:street":"Broadway St",
    "iso:country":"US",
    "sg:address":"2745 Broadway St",
    "sg:city":"Buffalo",
    "sg:classifiers":[
        {
            "category":"Wholesale",
            "subcategory":"Hardware",
            "type":"Manufacturing & Wholesale Goods"
        }
    ],
    "sg:phone":"+1 716 895 2964",
    "sg:postcode":"14227",
    "sg:province":"NY",
    "sg:tags":[
        "equipment",
        "heating",
        "system"
    ],
    "wof:name":"Sid Harvey's",
    "wof:placetype":"venue"
},
  "geometry": {"coordinates":[-78.770898,42.901928],"type":"Point"}
}