{
  "type": "Feature",
  "properties": {
    "iso:country":"US",
    "sg:address":"1868 Eastern Pkwy",
    "sg:city":"Schenectady",
    "sg:classifiers":[
        {
            "category":"Communications",
            "type":"Services"
        }
    ],
    "sg:phone":"+1 518 377 3810",
    "sg:postcode":"12309",
    "sg:province":"NY",
    "wof:name":"Curran Communications",
    "wof:placetype":"venue"
},
  "geometry": {"coordinates":[-73.90722700000001,42.804591],"type":"Point"}
}