{
  "type": "Feature",
  "properties": {
    "addr:full":"600 Pelham Parkway S Bronx NY 10462",
    "addr:housenumber":"600",
    "addr:postcode":"10462",
    "addr:street":"Pelham Parkway S",
    "iso:country":"US",
    "sg:address":"600 Pelham Parkway S",
    "sg:city":"Bronx",
    "sg:classifiers":[
        {
            "category":"Autos & Motor Vehicles",
            "subcategory":"Fuel & Gas Station",
            "type":"Retail Goods"
        }
    ],
    "sg:phone":"+1 718 931 5452",
    "sg:postcode":"10462",
    "sg:province":"NY",
    "wof:name":"G & H",
    "wof:placetype":"venue"
},
  "geometry": {"coordinates":[-73.868506,40.856495],"type":"Point"}
}