{
  "type": "Feature",
  "properties": {
    "addr:full":"760 Parkside Ave Brooklyn NY 11226",
    "addr:housenumber":"760",
    "addr:postcode":"11226",
    "addr:street":"Parkside Ave",
    "iso:country":"US",
    "sg:address":"760 Parkside Ave",
    "sg:city":"Brooklyn",
    "sg:classifiers":[
        {
            "category":"Shopping",
            "subcategory":"Pharmacy",
            "type":"Retail Goods"
        }
    ],
    "sg:phone":"+1 718 826 1254",
    "sg:postcode":"11226",
    "sg:province":"NY",
    "wof:name":"N I Rx Medical Tech LLC",
    "wof:placetype":"venue"
},
  "geometry": {"coordinates":[-73.94879,40.656238],"type":"Point"}
}