{
  "type": "Feature",
  "properties": {
    "addr:full":"2217 Starling Ave Bronx NY 10462",
    "addr:housenumber":"2217",
    "addr:postcode":"10462",
    "addr:street":"Starling Ave",
    "iso:country":"US",
    "sg:address":"2217 Starling Ave",
    "sg:city":"Bronx",
    "sg:classifiers":[
        {
            "category":"Taxi",
            "type":"Transportation"
        }
    ],
    "sg:phone":"+1 718 823 0311",
    "sg:postcode":"10462",
    "sg:province":"NY",
    "wof:name":"Choudhury, Burak A & Moklisur R",
    "wof:placetype":"venue"
},
  "geometry": {"coordinates":[-73.851972,40.836355],"type":"Point"}
}