{
  "type": "Feature",
  "properties": {
    "iso:country":"US",
    "sg:address":"63 Cooper St",
    "sg:city":"Accord",
    "sg:classifiers":[
        {
            "category":"Cinema",
            "subcategory":"Movie Rental",
            "type":"Entertainment"
        }
    ],
    "sg:phone":"+1 845 626 3096",
    "sg:postcode":"12404",
    "sg:province":"NY",
    "sg:tags":[
        "motion",
        "picture",
        "distributor",
        "film",
        "exchange"
    ],
    "wof:name":"Serge Blue Productions Inc",
    "wof:placetype":"venue"
},
  "geometry": {"coordinates":[-74.21793599999999,41.823191],"type":"Point"}
}