{
  "type": "Feature",
  "properties": {
    "iso:country":"US",
    "sg:address":"157 W 35 St",
    "sg:city":"New York",
    "sg:classifiers":[
        {
            "category":"Professional",
            "subcategory":"Advertising",
            "type":"Services"
        }
    ],
    "sg:phone":"+1 212 594 7369",
    "sg:postcode":"10001",
    "sg:province":"NY",
    "sg:tags":[
        "mailing",
        "shipping"
    ],
    "wof:name":"Fed Ex Kinko's Ofc & Print Ctr",
    "wof:placetype":"venue"
},
  "geometry": {"coordinates":[-73.98912799999999,40.751182],"type":"Point"}
}