{
  "type": "Feature",
  "properties": {
    "addr:full":"6630 Forest Ave Ridgewood NY 11385",
    "addr:housenumber":"6630",
    "addr:postcode":"11385",
    "addr:street":"Forest Ave",
    "iso:country":"US",
    "sg:address":"6630 Forest Ave",
    "sg:city":"Ridgewood",
    "sg:classifiers":[
        {
            "category":"Real Estate",
            "subcategory":"Real Estate Services",
            "type":"Services"
        },
        {
            "category":"Real Estate",
            "subcategory":"Real Estate Agent",
            "type":"Services"
        }
    ],
    "sg:phone":"+1 718 456 1400",
    "sg:postcode":"11385",
    "sg:province":"NY",
    "sg:tags":[
        "buyer",
        "broker"
    ],
    "wof:name":"Grimaldi Realty Corp",
    "wof:placetype":"venue"
},
  "geometry": {"coordinates":[-73.901661,40.704014],"type":"Point"}
}