{
  "type": "Feature",
  "properties": {
    "addr:full":"676 Sunrise Hwy Baldwin NY 11510",
    "addr:housenumber":"676",
    "addr:postcode":"11510",
    "addr:street":"Sunrise Hwy",
    "iso:country":"US",
    "sg:address":"676 Sunrise Hwy",
    "sg:city":"Baldwin",
    "sg:classifiers":[
        {
            "category":"Banks & Credit Unions",
            "subcategory":"Bank",
            "type":"Services"
        }
    ],
    "sg:phone":"+1 516 378 0439",
    "sg:postcode":"11510",
    "sg:province":"NY",
    "wof:name":"Washington Mutual",
    "wof:placetype":"venue"
},
  "geometry": {"coordinates":[-73.613966,40.656426],"type":"Point"}
}