{
  "type": "Feature",
  "properties": {
    "addr:full":"6178 Tower Hill Rd Byron NY 14422",
    "addr:housenumber":"6178",
    "addr:postcode":"14422",
    "addr:street":"Tower Hill Rd",
    "iso:country":"US",
    "sg:address":"6178 Tower Hill Rd",
    "sg:city":"Byron",
    "sg:classifiers":[
        {
            "category":"Building & Trades",
            "subcategory":"Landscaping Services",
            "type":"Services"
        }
    ],
    "sg:phone":"+1 585 548 9924",
    "sg:postcode":"14422",
    "sg:province":"NY",
    "wof:name":"Orion Lawn Care",
    "wof:placetype":"venue"
},
  "geometry": {"coordinates":[-78.06808700000001,43.090705],"type":"Point"}
}