{
  "type": "Feature",
  "properties": {
    "addr:full":"151 Sunnyside Blvd Plainview NY 11803",
    "addr:housenumber":"151",
    "addr:postcode":"11803",
    "addr:street":"Sunnyside Blvd",
    "iso:country":"US",
    "sg:address":"151 Sunnyside Blvd",
    "sg:city":"Plainview",
    "sg:classifiers":[
        {
            "category":"Freight",
            "type":"Transportation"
        }
    ],
    "sg:phone":"+1   ",
    "sg:postcode":"11803",
    "sg:province":"NY",
    "sg:tags":[
        "paper",
        "special"
    ],
    "sg:website":"www.extraspace.com",
    "wof:name":"Extra Space Storage",
    "wof:placetype":"venue"
},
  "geometry": {"coordinates":[-73.468683,40.794765],"type":"Point"}
}