{
  "type": "Feature",
  "properties": {
    "addr:full":"312 W 55 St New York NY 10019",
    "addr:housenumber":"312",
    "addr:postcode":"10019",
    "addr:street":"W 55 St",
    "iso:country":"US",
    "sg:address":"312 W 55 St",
    "sg:city":"New York",
    "sg:classifiers":[
        {
            "category":"Real Estate",
            "subcategory":"Real Estate Agent",
            "type":"Services"
        }
    ],
    "sg:phone":"+1 212 315 1717",
    "sg:postcode":"10019",
    "sg:province":"NY",
    "wof:name":"Carl Gershon & Co",
    "wof:placetype":"venue"
},
  "geometry": {"coordinates":[-73.98643199999999,40.766404],"type":"Point"}
}