{
  "type": "Feature",
  "properties": {
    "iso:country":"US",
    "sg:address":"121 Victor Heights Pkwy",
    "sg:city":"Victor",
    "sg:classifiers":[
        {
            "category":"Professional",
            "type":"Services"
        }
    ],
    "sg:phone":"+1 585 869 0123",
    "sg:postcode":"14564",
    "sg:province":"NY",
    "sg:tags":[
        "establishment"
    ],
    "sg:website":"www.symon.com",
    "wof:name":"Symon Communications",
    "wof:placetype":"venue"
},
  "geometry": {"coordinates":[-77.445081,42.9966],"type":"Point"}
}