{
  "type": "Feature",
  "properties": {
    "addr:full":"4 West 37th St 5th Floor New York NY 10018",
    "addr:housenumber":"4;5th floor",
    "addr:postcode":"10018",
    "addr:street":"West 37Th St",
    "iso:country":"US",
    "sg:address":"4 West 37th St 5th Floor",
    "sg:city":"New York",
    "sg:classifiers":[
        {
            "category":"Professional",
            "type":"Services"
        }
    ],
    "sg:phone":"+1 917 208 9791",
    "sg:postcode":"10018",
    "sg:province":"NY",
    "sg:website":"www.mvlabs.com",
    "wof:name":"Mv Labs",
    "wof:placetype":"venue"
},
  "geometry": {"coordinates":[-73.983947,40.750422],"type":"Point"}
}