{
  "type": "Feature",
  "properties": {
    "iso:country":"US",
    "sg:address":"333 3rd Avenue",
    "sg:city":"New York",
    "sg:classifiers":[
        {
            "category":"Food & Beverages",
            "subcategory":"Liquor & Beverages",
            "type":"Retail Goods"
        }
    ],
    "sg:phone":"+1 212 726 0033",
    "sg:postcode":"10010",
    "sg:province":"NY",
    "sg:tags":[
        "beer",
        "spirit",
        "wine"
    ],
    "wof:name":"333 Wine Heaven",
    "wof:placetype":"venue"
},
  "geometry": {"coordinates":[-73.98231199999999,40.739902],"type":"Point"}
}