{
  "type": "Feature",
  "properties": {
    "addr:full":"417 46th St Brooklyn NY 11220",
    "addr:housenumber":"417",
    "addr:postcode":"11220",
    "addr:street":"46Th St",
    "iso:country":"US",
    "sg:address":"417 46th St",
    "sg:city":"Brooklyn",
    "sg:classifiers":[
        {
            "category":"Organizations",
            "subcategory":"Membership Organization",
            "type":"Services"
        }
    ],
    "sg:phone":"+1   ",
    "sg:postcode":"11220",
    "sg:province":"NY",
    "wof:name":"Womens Wing Gujarat Federation",
    "wof:placetype":"venue"
},
  "geometry": {"coordinates":[-74.00822100000001,40.647625],"type":"Point"}
}