{
  "type": "Feature",
  "properties": {
    "addr:full":"3080 Grand Island Blvd Grand Island NY 14072",
    "addr:housenumber":"3080",
    "addr:postcode":"14072",
    "addr:street":"Grand Island Blvd",
    "iso:country":"US",
    "sg:address":"3080 Grand Island Blvd",
    "sg:city":"Grand Island",
    "sg:classifiers":[
        {
            "category":"Travel",
            "subcategory":"Hotels & Motels",
            "type":"Entertainment"
        }
    ],
    "sg:phone":"+1 716 773 3902",
    "sg:postcode":"14072",
    "sg:province":"NY",
    "wof:name":"Budget Motel",
    "wof:placetype":"venue"
},
  "geometry": {"coordinates":[-78.982186,43.041603],"type":"Point"}
}