{
  "type": "Feature",
  "properties": {
    "addr:full":"340 Main St Lake Placid NY 12946",
    "addr:housenumber":"340",
    "addr:postcode":"12946",
    "addr:street":"Main St",
    "iso:country":"US",
    "sg:address":"340 Main St",
    "sg:city":"Lake Placid",
    "sg:classifiers":[
        {
            "category":"Sports & Exercise",
            "subcategory":"Bowling",
            "type":"Entertainment"
        }
    ],
    "sg:phone":"+1 518 523 7868",
    "sg:postcode":"12946",
    "sg:province":"NY",
    "sg:tags":[
        "center"
    ],
    "wof:name":"Bowl Winkles",
    "wof:placetype":"venue"
},
  "geometry": {"coordinates":[-73.981584,44.280927],"type":"Point"}
}