{
  "type": "Feature",
  "properties": {
    "iso:country":"US",
    "sg:address":"313 E Willow St",
    "sg:city":"Syracuse",
    "sg:classifiers":[
        {
            "category":"Travel",
            "subcategory":"Travel Agent",
            "type":"Entertainment"
        }
    ],
    "sg:phone":"+1 315 426 0538",
    "sg:postcode":"13203",
    "sg:province":"NY",
    "sg:tags":[
        "agency",
        "bureau"
    ],
    "wof:name":"William Louer",
    "wof:placetype":"venue"
},
  "geometry": {"coordinates":[-76.14914400000001,43.053247],"type":"Point"}
}