{
  "type": "Feature",
  "properties": {
    "addr:full":"103 Old Broadway Ave Sayville NY 11782",
    "addr:housenumber":"103",
    "addr:postcode":"11782",
    "addr:street":"Old Broadway Ave",
    "iso:country":"US",
    "sg:address":"103 Old Broadway Ave",
    "sg:city":"Sayville",
    "sg:classifiers":[
        {
            "category":"Building & Trades",
            "subcategory":"Electrical",
            "type":"Services"
        }
    ],
    "sg:phone":"+1 631 589 2486",
    "sg:postcode":"11782",
    "sg:province":"NY",
    "sg:tags":[
        "electrical",
        "contractor"
    ],
    "wof:name":"P D Marcley Inc",
    "wof:placetype":"venue"
},
  "geometry": {"coordinates":[-73.064047,40.750973],"type":"Point"}
}