{
  "type": "Feature",
  "properties": {
    "iso:country":"US",
    "sg:address":"42 Ponquogue Ave",
    "sg:city":"Hampton Bays",
    "sg:classifiers":[
        {
            "category":"Professional",
            "subcategory":"Lawyer & Legal Services",
            "type":"Services"
        }
    ],
    "sg:phone":"+1   ",
    "sg:postcode":"11946",
    "sg:province":"NY",
    "wof:name":"Eugene Francolini",
    "wof:placetype":"venue"
},
  "geometry": {"coordinates":[-72.5209,40.874208],"type":"Point"}
}