{
  "type": "Feature",
  "properties": {
    "iso:country":"US",
    "sg:address":"4 Gabriel Pl",
    "sg:city":"Glen Cove",
    "sg:classifiers":[
        {
            "category":"Building & Trades",
            "subcategory":"Construction",
            "type":"Services"
        }
    ],
    "sg:phone":"+1 516 671 7237",
    "sg:postcode":"11542",
    "sg:province":"NY",
    "sg:tags":[
        "house"
    ],
    "wof:name":"Izzo Contracting",
    "wof:placetype":"venue"
},
  "geometry": {"coordinates":[-73.618369,40.854732],"type":"Point"}
}