{
  "type": "Feature",
  "properties": {
    "addr:full":"400 Townline Rd Hauppauge NY 11788",
    "addr:housenumber":"400",
    "addr:postcode":"11788",
    "addr:street":"Townline Rd",
    "iso:country":"US",
    "sg:address":"400 Townline Rd",
    "sg:city":"Hauppauge",
    "sg:classifiers":[
        {
            "category":"Travel",
            "subcategory":"Travel Agent",
            "type":"Entertainment"
        }
    ],
    "sg:phone":"+1   ",
    "sg:postcode":"11788",
    "sg:province":"NY",
    "sg:tags":[
        "agency"
    ],
    "wof:name":"Anne Marie Riley",
    "wof:placetype":"venue"
},
  "geometry": {"coordinates":[-73.208798,40.825065],"type":"Point"}
}