{
  "type": "Feature",
  "properties": {
    "addr:full":"617 Ballantyne Rd Syracuse NY 13207",
    "addr:housenumber":"617",
    "addr:postcode":"13207",
    "addr:street":"Ballantyne Rd",
    "iso:country":"US",
    "sg:address":"617 Ballantyne Rd",
    "sg:city":"Syracuse",
    "sg:classifiers":[
        {
            "category":"Manufacturing",
            "subcategory":"Tools & Machinery",
            "type":"Manufacturing & Wholesale Goods"
        }
    ],
    "sg:phone":"+1 315 469 0077",
    "sg:postcode":"13207",
    "sg:province":"NY",
    "sg:tags":[
        "machine",
        "shop"
    ],
    "wof:name":"Gerecke & Sons Machine",
    "wof:placetype":"venue"
},
  "geometry": {"coordinates":[-76.150378,43.010333],"type":"Point"}
}