{
  "type": "Feature",
  "properties": {
    "addr:full":"128 Bates Rd Harpursville NY 13787",
    "addr:housenumber":"128",
    "addr:postcode":"13787",
    "addr:street":"Bates Rd",
    "iso:country":"US",
    "sg:address":"128 Bates Rd",
    "sg:city":"Harpursville",
    "sg:classifiers":[
        {
            "category":"Professional",
            "type":"Services"
        }
    ],
    "sg:phone":"+1   ",
    "sg:postcode":"13787",
    "sg:province":"NY",
    "wof:name":"Patty Jenks",
    "wof:placetype":"venue"
},
  "geometry": {"coordinates":[-75.663319,42.187533],"type":"Point"}
}