{
  "type": "Feature",
  "properties": {
    "addr:full":"240 Jackson Ave Syosset NY 11791",
    "addr:housenumber":"240",
    "addr:postcode":"11791",
    "addr:street":"Jackson Ave",
    "iso:country":"US",
    "sg:address":"240 Jackson Ave",
    "sg:city":"Syosset",
    "sg:classifiers":[
        {
            "category":"Health Services",
            "subcategory":"Health Practitioner",
            "type":"Services"
        }
    ],
    "sg:phone":"+1 516 692 4786",
    "sg:postcode":"11791",
    "sg:province":"NY",
    "sg:tags":[
        "acupuncture"
    ],
    "wof:name":"Shao Licensed Acupuncturist PC",
    "wof:placetype":"venue"
},
  "geometry": {"coordinates":[-73.50121799999999,40.816417],"type":"Point"}
}