{
  "type": "Feature",
  "properties": {
    "addr:full":"807 Morris Park Ave Bronx NY 10462",
    "addr:housenumber":"807",
    "addr:postcode":"10462",
    "addr:street":"Morris Park Ave",
    "iso:country":"US",
    "sg:address":"807 Morris Park Ave",
    "sg:city":"Bronx",
    "sg:classifiers":[
        {
            "category":"Shopping",
            "type":"Retail Goods"
        }
    ],
    "sg:phone":"+1 718 931 9317",
    "sg:postcode":"10462",
    "sg:province":"NY",
    "sg:tags":[
        "religious"
    ],
    "wof:name":"Ave Maria",
    "wof:placetype":"venue"
},
  "geometry": {"coordinates":[-73.861908,40.846163],"type":"Point"}
}