{
  "type": "Feature",
  "properties": {
    "addr:full":"549 Albany Ave Kingston NY 12401",
    "addr:housenumber":"549",
    "addr:postcode":"12401",
    "addr:street":"Albany Ave",
    "iso:country":"US",
    "sg:address":"549 Albany Ave",
    "sg:city":"Kingston",
    "sg:classifiers":[
        {
            "category":"Shopping",
            "type":"Retail Goods"
        }
    ],
    "sg:phone":"+1 845 339 1512",
    "sg:postcode":"12401",
    "sg:province":"NY",
    "sg:tags":[
        "cards",
        "sport",
        "baseball",
        "memorabilia"
    ],
    "wof:name":"Sportscard Outlet",
    "wof:placetype":"venue"
},
  "geometry": {"coordinates":[-73.997032,41.943925],"type":"Point"}
}