{
  "type": "Feature",
  "properties": {
    "iso:country":"US",
    "sg:address":"516 Pine Aire Dr",
    "sg:city":"Bay Shore",
    "sg:classifiers":[
        {
            "category":"Building & Trades",
            "subcategory":"Construction",
            "type":"Services"
        }
    ],
    "sg:phone":"+1 631 595 1330",
    "sg:postcode":"11706",
    "sg:province":"NY",
    "wof:name":"Mohawk Asphalt Sealing Inc",
    "wof:placetype":"venue"
},
  "geometry": {"coordinates":[-73.28274999999999,40.771175],"type":"Point"}
}