{
  "type": "Feature",
  "properties": {
    "addr:full":"2134 Middle Country Rd Centereach NY 11720",
    "addr:housenumber":"2134",
    "addr:postcode":"11720",
    "addr:street":"Middle Country Rd",
    "iso:country":"US",
    "sg:address":"2134 Middle Country Rd",
    "sg:city":"Centereach",
    "sg:classifiers":[
        {
            "category":"Health Services",
            "subcategory":"Doctor",
            "type":"Services"
        }
    ],
    "sg:phone":"+1 631 588 0550",
    "sg:postcode":"11720",
    "sg:province":"NY",
    "wof:name":"Community Medical Care",
    "wof:placetype":"venue"
},
  "geometry": {"coordinates":[-73.07869700000001,40.859001],"type":"Point"}
}