{
  "type": "Feature",
  "properties": {
    "addr:full":"26 Buckingham Dr Dix Hills NY 11746",
    "addr:housenumber":"26",
    "addr:postcode":"11746",
    "addr:street":"Buckingham Dr",
    "iso:country":"US",
    "sg:address":"26 Buckingham Dr",
    "sg:city":"Dix Hills",
    "sg:classifiers":[
        {
            "category":"Wholesale",
            "subcategory":"Metals & Minerals",
            "type":"Manufacturing & Wholesale Goods"
        }
    ],
    "sg:phone":"+1 631 543 4723",
    "sg:postcode":"11746",
    "sg:province":"NY",
    "sg:tags":[
        "aluminum"
    ],
    "wof:name":"Cornell Aluminum Products Inc",
    "wof:placetype":"venue"
},
  "geometry": {"coordinates":[-73.32511700000001,40.805515],"type":"Point"}
}