{
  "type": "Feature",
  "properties": {
    "addr:full":"105 Chambers St New York NY 10007",
    "addr:housenumber":"105",
    "addr:postcode":"10007",
    "addr:street":"Chambers St",
    "iso:country":"US",
    "sg:address":"105 Chambers St",
    "sg:city":"New York",
    "sg:classifiers":[
        {
            "category":"Restaurant",
            "type":"Food & Drink"
        }
    ],
    "sg:menulink":"http://www.allmenus.com/ny/new-york/249921-the-new-york-city-hot-dog-company/menu/",
    "sg:phone":"+1 212 240 9550",
    "sg:postcode":"10007",
    "sg:province":"NY",
    "sg:tags":[
        "american",
        "hot",
        "dog"
    ],
    "wof:name":"The New York City Hot Dog Company",
    "wof:placetype":"venue"
},
  "geometry": {"coordinates":[-74.00796800000001,40.715265],"type":"Point"}
}