{
  "type": "Feature",
  "properties": {
    "iso:country":"US",
    "sg:address":"172 Babylon Tpke",
    "sg:city":"Roosevelt",
    "sg:classifiers":[
        {
            "category":"Retail",
            "subcategory":"Auto Repair",
            "type":"Services"
        }
    ],
    "sg:phone":"+1 516 208 3479",
    "sg:postcode":"11575",
    "sg:province":"NY",
    "wof:name":"B And B Auto",
    "wof:placetype":"venue"
},
  "geometry": {"coordinates":[-73.583968,40.675428],"type":"Point"}
}