{
  "type": "Feature",
  "properties": {
    "iso:country":"US",
    "sg:address":"4261 Broadway",
    "sg:city":"New York",
    "sg:classifiers":[
        {
            "category":"Shopping",
            "subcategory":"Clothing, Apparel, & Fashions",
            "type":"Retail Goods"
        }
    ],
    "sg:phone":"+1 212 927 3624",
    "sg:postcode":"10033",
    "sg:province":"NY",
    "wof:name":"N Y & Co",
    "wof:placetype":"venue"
},
  "geometry": {"coordinates":[-73.935425,40.850774],"type":"Point"}
}