{
  "type": "Feature",
  "properties": {
    "addr:full":"2814 14th Street Astoria NY 11102",
    "addr:housenumber":"2814",
    "addr:postcode":"11102",
    "addr:street":"14Th Street",
    "iso:country":"US",
    "sg:address":"2814 14th Street",
    "sg:city":"Astoria",
    "sg:classifiers":[
        {
            "category":"Building & Trades",
            "subcategory":"Cleaning & Sanitation",
            "type":"Services"
        }
    ],
    "sg:phone":"+1 718 629 2101",
    "sg:postcode":"11102",
    "sg:province":"NY",
    "sg:tags":[
        "carpet"
    ],
    "wof:name":"Babay Carpet Cleaning",
    "wof:placetype":"venue"
},
  "geometry": {"coordinates":[-73.928989,40.77215],"type":"Point"}
}