{
  "type": "Feature",
  "properties": {
    "iso:country":"US",
    "sg:address":"11 Clinton Ave",
    "sg:city":"Cortland",
    "sg:classifiers":[
        {
            "category":"Personal",
            "type":"Services"
        },
        {
            "category":"Autos & Motor Vehicles",
            "subcategory":"Motorcycle Sales",
            "type":"Retail Goods"
        }
    ],
    "sg:phone":"+1 607 756 4205",
    "sg:postcode":"13045",
    "sg:province":"NY",
    "sg:tags":[
        "scooter"
    ],
    "wof:name":"Underground Leather & Cycle",
    "wof:placetype":"venue"
},
  "geometry": {"coordinates":[-76.179429,42.601428],"type":"Point"}
}