{
  "type": "Feature",
  "properties": {
    "iso:country":"US",
    "sg:address":"71 W 12 St",
    "sg:city":"New York",
    "sg:classifiers":[
        {
            "category":"Professional",
            "subcategory":"Computer Services",
            "type":"Services"
        }
    ],
    "sg:phone":"+1   ",
    "sg:postcode":"10011",
    "sg:province":"NY",
    "sg:tags":[
        "datum"
    ],
    "wof:name":"William Obeid",
    "wof:placetype":"venue"
},
  "geometry": {"coordinates":[-73.996026,40.735125],"type":"Point"}
}