{
  "type": "Feature",
  "properties": {
    "addr:full":"57 Maplewood Ave Hempstead NY 11550",
    "addr:housenumber":"57",
    "addr:postcode":"11550",
    "addr:street":"Maplewood Ave",
    "iso:country":"US",
    "sg:address":"57 Maplewood Ave",
    "sg:city":"Hempstead",
    "sg:classifiers":[
        {
            "category":"Building & Trades",
            "subcategory":"Construction",
            "type":"Services"
        }
    ],
    "sg:phone":"+1 516 481 0147",
    "sg:postcode":"11550",
    "sg:province":"NY",
    "sg:tags":[
        "rigging",
        "contractor"
    ],
    "wof:name":"Alpha Rigging Co Long Island",
    "wof:placetype":"venue"
},
  "geometry": {"coordinates":[-73.60574800000001,40.699422],"type":"Point"}
}