{
  "type": "Feature",
  "properties": {
    "addr:full":"119 7th Ave Brooklyn NY 11215",
    "addr:housenumber":"119",
    "addr:postcode":"11215",
    "addr:street":"7Th Ave",
    "iso:country":"US",
    "sg:address":"119 7th Ave",
    "sg:city":"Brooklyn",
    "sg:classifiers":[
        {
            "category":"Shopping",
            "subcategory":"Clothing, Apparel, & Fashions",
            "type":"Retail Goods"
        }
    ],
    "sg:phone":"+1 718 622 5551",
    "sg:postcode":"11215",
    "sg:province":"NY",
    "sg:tags":[
        "accessory",
        "clothing",
        "women's"
    ],
    "sg:website":"kiwidesignco.com",
    "wof:name":"Kiwi",
    "wof:placetype":"venue"
},
  "geometry": {"coordinates":[-73.975859,40.673386],"type":"Point"}
}