{
  "type": "Feature",
  "properties": {
    "addr:full":"77 E Mount Eden Ave Bronx NY 10452",
    "addr:housenumber":"77",
    "addr:postcode":"10452",
    "addr:street":"E Mount Eden Ave",
    "iso:country":"US",
    "sg:address":"77 E Mount Eden Ave",
    "sg:city":"Bronx",
    "sg:classifiers":[
        {
            "category":"Food & Beverages",
            "subcategory":"Meat & Fish",
            "type":"Retail Goods"
        }
    ],
    "sg:phone":"+1 800 640 3902",
    "sg:postcode":"10452",
    "sg:province":"NY",
    "sg:tags":[
        "shop"
    ],
    "wof:name":"Big Way Meat Mkt",
    "wof:placetype":"venue"
},
  "geometry": {"coordinates":[-73.913336,40.843927],"type":"Point"}
}