{
  "type": "Feature",
  "properties": {
    "addr:full":"7 Lebanon St Hamilton NY 13346",
    "addr:housenumber":"7",
    "addr:postcode":"13346",
    "addr:street":"Lebanon St",
    "iso:country":"US",
    "sg:address":"7 Lebanon St",
    "sg:city":"Hamilton",
    "sg:classifiers":[
        {
            "category":"Shopping",
            "subcategory":"Jewelry",
            "type":"Retail Goods"
        }
    ],
    "sg:phone":"+1   ",
    "sg:postcode":"13346",
    "sg:province":"NY",
    "sg:website":"www.cazjewelry.com",
    "wof:name":"Cazenovia Jewelry",
    "wof:placetype":"venue"
},
  "geometry": {"coordinates":[-75.544533,42.826708],"type":"Point"}
}