{
  "type": "Feature",
  "properties": {
    "iso:country":"US",
    "sg:address":"133 2nd Ave",
    "sg:city":"New York",
    "sg:classifiers":[
        {
            "category":"Insurance",
            "subcategory":"Health Insurance",
            "type":"Services"
        }
    ],
    "sg:phone":"+1 212 353 8129",
    "sg:postcode":"10003",
    "sg:province":"NY",
    "sg:tags":[
        "market"
    ],
    "sg:website":"www.gnc.com",
    "wof:name":"GNC",
    "wof:placetype":"venue"
},
  "geometry": {"coordinates":[-73.98778900000001,40.728667],"type":"Point"}
}