{
  "type": "Feature",
  "properties": {
    "addr:full":"150 Knickerbocker Ave Bohemia NY 11716",
    "addr:housenumber":"150",
    "addr:postcode":"11716",
    "addr:street":"Knickerbocker Ave",
    "iso:country":"US",
    "sg:address":"150 Knickerbocker Ave",
    "sg:city":"Bohemia",
    "sg:classifiers":[
        {
            "category":"Building & Trades",
            "subcategory":"Equipment Rental",
            "type":"Services"
        }
    ],
    "sg:phone":"+1 631 288 7282",
    "sg:postcode":"11716",
    "sg:province":"NY",
    "sg:tags":[
        "camping"
    ],
    "wof:name":"Empire Tent Rental & Event",
    "wof:placetype":"venue"
},
  "geometry": {"coordinates":[-73.08713899999999,40.773437],"type":"Point"}
}