{
  "type": "Feature",
  "properties": {
    "addr:full":"1033 Waverly Ave Holtsville NY 11742",
    "addr:housenumber":"1033",
    "addr:postcode":"11742",
    "addr:street":"Waverly Ave",
    "iso:country":"US",
    "sg:address":"1033 Waverly Ave",
    "sg:city":"Holtsville",
    "sg:classifiers":[
        {
            "category":"Autos & Motor Vehicles",
            "subcategory":"Automobile Sales",
            "type":"Retail Goods"
        }
    ],
    "sg:phone":"+1 631 615 7293",
    "sg:postcode":"11742",
    "sg:province":"NY",
    "sg:tags":[
        "limo"
    ],
    "wof:name":"Roslyn Limousine",
    "wof:placetype":"venue"
},
  "geometry": {"coordinates":[-73.04455400000001,40.815624],"type":"Point"}
}