{
  "type": "Feature",
  "properties": {
    "addr:full":"47 Gildner Rd Central Square NY 13036",
    "addr:housenumber":"47",
    "addr:postcode":"13036",
    "addr:street":"Gildner Rd",
    "iso:country":"US",
    "sg:address":"47 Gildner Rd",
    "sg:city":"Central Square",
    "sg:classifiers":[
        {
            "category":"Building & Trades",
            "subcategory":"Construction",
            "type":"Services"
        }
    ],
    "sg:phone":"+1 315 668 6160",
    "sg:postcode":"13036",
    "sg:province":"NY",
    "sg:tags":[
        "general",
        "contractor"
    ],
    "wof:name":"Henderson Brothers Contracting",
    "wof:placetype":"venue"
},
  "geometry": {"coordinates":[-76.14787800000001,43.263064],"type":"Point"}
}