{
  "type": "Feature",
  "properties": {
    "iso:country":"US",
    "sg:address":"2258 Allen St Exd",
    "sg:city":"Jamestown",
    "sg:classifiers":[
        {
            "category":"Manufacturing",
            "subcategory":"Motor Vehicles & Parts",
            "type":"Manufacturing & Wholesale Goods"
        }
    ],
    "sg:phone":"+1 716 665 2620",
    "sg:postcode":"14701",
    "sg:province":"NY",
    "sg:tags":[
        "automobile",
        "radiator"
    ],
    "wof:name":"Valeo Engine Cooling Inc",
    "wof:placetype":"venue"
},
  "geometry": {"coordinates":[-79.189127,42.114859],"type":"Point"}
}