{
  "type": "Feature",
  "properties": {
    "addr:full":"19 Ryder Ave Huntington Station NY 11746",
    "addr:housenumber":"19",
    "addr:postcode":"11746",
    "addr:street":"Ryder Ave Huntington",
    "iso:country":"US",
    "sg:address":"19 Ryder Ave",
    "sg:city":"Huntington Station",
    "sg:classifiers":[
        {
            "category":"Shopping",
            "subcategory":"Clothing, Apparel, & Fashions",
            "type":"Retail Goods"
        }
    ],
    "sg:phone":"+1   ",
    "sg:postcode":"11746",
    "sg:province":"NY",
    "sg:tags":[
        "wear"
    ],
    "wof:name":"Verdi Boutique Inc",
    "wof:placetype":"venue"
},
  "geometry": {"coordinates":[-73.343237,40.784019],"type":"Point"}
}