{
  "type": "Feature",
  "properties": {
    "addr:full":"2300 Westchester Ave Bronx NY 10462",
    "addr:housenumber":"2300",
    "addr:postcode":"10462",
    "addr:street":"Westchester Ave",
    "iso:country":"US",
    "sg:address":"2300 Westchester Ave",
    "sg:city":"Bronx",
    "sg:classifiers":[
        {
            "category":"Health Services",
            "subcategory":"Doctor",
            "type":"Services"
        }
    ],
    "sg:phone":"+1 718 829 1900",
    "sg:postcode":"10462",
    "sg:province":"NY",
    "sg:tags":[
        "physician",
        "surgeon"
    ],
    "wof:name":"Montefiore Medical Group",
    "wof:placetype":"venue"
},
  "geometry": {"coordinates":[-73.84731499999999,40.836264],"type":"Point"}
}