{
  "type": "Feature",
  "properties": {
    "iso:country":"US",
    "sg:address":"633 Eagle Ave",
    "sg:city":"West Hempstead",
    "sg:classifiers":[
        {
            "category":"Recreation",
            "type":"Entertainment"
        }
    ],
    "sg:phone":"+1 516 486 9673",
    "sg:postcode":"11552",
    "sg:province":"NY",
    "sg:tags":[
        "personal",
        "animal"
    ],
    "wof:name":"Lakeside Riding Academy",
    "wof:placetype":"venue"
},
  "geometry": {"coordinates":[-73.646705,40.685796],"type":"Point"}
}