{
  "type": "Feature",
  "properties": {
    "iso:country":"US",
    "sg:address":"566 East Ave",
    "sg:city":"Rochester",
    "sg:classifiers":[
        {
            "category":"Organizations",
            "subcategory":"Community Association",
            "type":"Services"
        }
    ],
    "sg:phone":"+1 585 271 7533",
    "sg:postcode":"14607",
    "sg:province":"NY",
    "sg:tags":[
        "real estate"
    ],
    "wof:name":"Century Club",
    "wof:placetype":"venue"
},
  "geometry": {"coordinates":[-77.589658,43.153841],"type":"Point"}
}