{
  "type": "Feature",
  "properties": {
    "addr:full":"7601 18th Ave Brooklyn NY 11214",
    "addr:housenumber":"7601",
    "addr:postcode":"11214",
    "addr:street":"18Th Ave",
    "iso:country":"US",
    "sg:address":"7601 18th Ave",
    "sg:city":"Brooklyn",
    "sg:classifiers":[
        {
            "category":"Shopping",
            "subcategory":"Clothing, Apparel, & Fashions",
            "type":"Retail Goods"
        }
    ],
    "sg:phone":"+1   ",
    "sg:postcode":"11214",
    "sg:province":"NY",
    "wof:name":"Princess Lingerie",
    "wof:placetype":"venue"
},
  "geometry": {"coordinates":[-73.99717099999999,40.612215],"type":"Point"}
}