{
  "type": "Feature",
  "properties": {
    "iso:country":"US",
    "sg:address":"808 Lexington Ave",
    "sg:city":"New York",
    "sg:classifiers":[
        {
            "category":"Restaurant",
            "type":"Food & Drink"
        }
    ],
    "sg:phone":"+1 212 207 4555",
    "sg:postcode":"10021",
    "sg:province":"NY",
    "sg:tags":[
        "greek",
        "mediterranean"
    ],
    "sg:website":"www.figandolive.com",
    "wof:name":"Fig & Olive",
    "wof:placetype":"venue"
},
  "geometry": {"coordinates":[-73.96692400000001,40.764405],"type":"Point"}
}