{
  "type": "Feature",
  "properties": {
    "iso:country":"US",
    "sg:address":"3180 Sunrise Hwy",
    "sg:city":"Wantagh",
    "sg:classifiers":[
        {
            "category":"Real Estate",
            "subcategory":"Real Estate Operator",
            "type":"Services"
        }
    ],
    "sg:phone":"+1 516 826 7788",
    "sg:postcode":"11793",
    "sg:province":"NY",
    "sg:tags":[
        "new",
        "holding",
        "car"
    ],
    "sg:website":"http://www.wantaghmazda.com",
    "wof:name":"Wantagh Mazda",
    "wof:placetype":"venue"
},
  "geometry": {"coordinates":[-73.512714,40.671685],"type":"Point"}
}