{
  "type": "Feature",
  "properties": {
    "addr:full":"11 Northern Blvd Great Neck NY 11021",
    "addr:housenumber":"11",
    "addr:postcode":"11021",
    "addr:street":"Northern Blvd",
    "iso:country":"US",
    "sg:address":"11 Northern Blvd",
    "sg:city":"Great Neck",
    "sg:classifiers":[
        {
            "category":"Professional",
            "subcategory":"Advertising",
            "type":"Services"
        }
    ],
    "sg:phone":"+1 516 482 3738",
    "sg:postcode":"11021",
    "sg:province":"NY",
    "wof:name":"Hi Productions",
    "wof:placetype":"venue"
},
  "geometry": {"coordinates":[-73.732997,40.773545],"type":"Point"}
}