{
  "type": "Feature",
  "properties": {
    "iso:country":"US",
    "sg:address":"7560 Burke Rd",
    "sg:city":"Jamesville",
    "sg:classifiers":[
        {
            "category":"Professional",
            "subcategory":"Computer Services",
            "type":"Services"
        }
    ],
    "sg:phone":"+1 315 682 6199",
    "sg:postcode":"13078",
    "sg:province":"NY",
    "sg:tags":[
        "internet"
    ],
    "wof:name":"Treasure Box",
    "wof:placetype":"venue"
},
  "geometry": {"coordinates":[-76.01750199999999,42.946508],"type":"Point"}
}