{
  "type": "Feature",
  "properties": {
    "addr:full":"403 Rockhill Rd Voorheesville NY 12186",
    "addr:housenumber":"403",
    "addr:postcode":"12186",
    "addr:street":"Rockhill Rd",
    "iso:country":"US",
    "sg:address":"403 Rockhill Rd",
    "sg:city":"Voorheesville",
    "sg:classifiers":[
        {
            "category":"Organizations",
            "subcategory":"Professional Association",
            "type":"Services"
        }
    ],
    "sg:phone":"+1   ",
    "sg:postcode":"12186",
    "sg:province":"NY",
    "sg:tags":[
        "education",
        "assoc",
        "teacher"
    ],
    "wof:name":"American Federation Teachers",
    "wof:placetype":"venue"
},
  "geometry": {"coordinates":[-73.95881799999999,42.612354],"type":"Point"}
}