{
  "type": "Feature",
  "properties": {
    "addr:full":"2500 Westchester Ave # 401 Purchase NY 10577",
    "addr:housenumber":"2500",
    "addr:postcode":"10577",
    "addr:street":"Westchester Ave # 401",
    "iso:country":"US",
    "sg:address":"2500 Westchester Ave # 401",
    "sg:city":"Purchase",
    "sg:classifiers":[
        {
            "category":"Professional",
            "subcategory":"Management & Consulting",
            "type":"Services"
        },
        {
            "category":"Banks & Credit Unions",
            "subcategory":"Financial Services",
            "type":"Services"
        }
    ],
    "sg:phone":"+1 914 777 2500",
    "sg:postcode":"10577",
    "sg:province":"NY",
    "sg:tags":[
        "consultant",
        "financing",
        "planning"
    ],
    "sg:website":"http://www.opusadvisory.com",
    "wof:name":"Opus Advisory Group",
    "wof:placetype":"venue"
},
  "geometry": {"coordinates":[-73.700996,41.011921],"type":"Point"}
}