{
  "type": "Feature",
  "properties": {
    "addr:full":"5263 W Lake Rd Dunkirk NY 14048",
    "addr:housenumber":"5263",
    "addr:postcode":"14048",
    "addr:street":"W Lake Rd",
    "iso:country":"US",
    "sg:address":"5263 W Lake Rd",
    "sg:city":"Dunkirk",
    "sg:classifiers":[
        {
            "category":"Building & Trades",
            "subcategory":"Construction",
            "type":"Services"
        }
    ],
    "sg:phone":"+1 716 680 3626",
    "sg:postcode":"14048",
    "sg:province":"NY",
    "sg:tags":[
        "house",
        "contractor"
    ],
    "wof:name":"Miller & Crane Builders",
    "wof:placetype":"venue"
},
  "geometry": {"coordinates":[-79.401956,42.452964],"type":"Point"}
}