{
  "type": "Feature",
  "properties": {
    "iso:country":"US",
    "sg:address":"60 Oak Dr Ste 3",
    "sg:city":"Syosset",
    "sg:classifiers":[
        {
            "category":"Real Estate",
            "subcategory":"Real Estate Services",
            "type":"Services"
        },
        {
            "category":"Real Estate",
            "subcategory":"Real Estate Agent",
            "type":"Services"
        }
    ],
    "sg:phone":"+1 516 364 9870",
    "sg:postcode":"11791",
    "sg:province":"NY",
    "sg:tags":[
        "apartment",
        "broker",
        "management",
        "buyer",
        "rental",
        "finder"
    ],
    "wof:name":"S K S Associates",
    "wof:placetype":"venue"
},
  "geometry": {"coordinates":[-73.515198,40.806702],"type":"Point"}
}