{
  "type": "Feature",
  "properties": {
    "iso:country":"US",
    "sg:address":"12605 Main Rd",
    "sg:city":"Mattituck",
    "sg:classifiers":[
        {
            "category":"Place Of Worship",
            "subcategory":"Church",
            "type":"Public Place"
        },
        {
            "category":"Place Of Worship",
            "type":"Public Place"
        }
    ],
    "sg:phone":"+1 631 298 4145",
    "sg:postcode":"11952",
    "sg:province":"NY",
    "sg:tags":[
        "churches-interdenominational",
        "churches-various",
        "denomination"
    ],
    "wof:name":"Mattituck Pres Church",
    "wof:placetype":"venue"
},
  "geometry": {"coordinates":[-72.53422999999999,40.99063],"type":"Point"}
}