{
  "type": "Feature",
  "properties": {
    "iso:country":"US",
    "sg:address":"284 Flatbush Ave",
    "sg:city":"Brooklyn",
    "sg:classifiers":[
        {
            "category":"Shopping",
            "subcategory":"Florist",
            "type":"Retail Goods"
        }
    ],
    "sg:phone":"+1   ",
    "sg:postcode":"11217",
    "sg:province":"NY",
    "wof:name":"In Bloom Florist",
    "wof:placetype":"venue"
},
  "geometry": {"coordinates":[-73.97320499999999,40.678123],"type":"Point"}
}