{
  "type": "Feature",
  "properties": {
    "iso:country":"US",
    "sg:address":"150 Faulkener Rd",
    "sg:city":"Hancock",
    "sg:classifiers":[
        {
            "category":"Travel",
            "subcategory":"Hotels & Motels",
            "type":"Entertainment"
        }
    ],
    "sg:phone":"+1 607 467 5525",
    "sg:postcode":"13754",
    "sg:province":"NY",
    "sg:tags":[
        "resort"
    ],
    "sg:website":"www.westbranchangler.com",
    "wof:name":"West Branch Angler & Sportman",
    "wof:placetype":"venue"
},
  "geometry": {"coordinates":[-75.365996,42.003676],"type":"Point"}
}