{
  "type": "Feature",
  "properties": {
    "iso:country":"US",
    "sg:address":"1640 40th St",
    "sg:city":"Brooklyn",
    "sg:classifiers":[
        {
            "category":"Manufacturing",
            "subcategory":"Apparel",
            "type":"Manufacturing & Wholesale Goods"
        }
    ],
    "sg:phone":"+1   ",
    "sg:postcode":"11218",
    "sg:province":"NY",
    "sg:tags":[
        "import"
    ],
    "wof:name":"Pak 21",
    "wof:placetype":"venue"
},
  "geometry": {"coordinates":[-73.979567,40.635616],"type":"Point"}
}