{
  "type": "Feature",
  "properties": {
    "iso:country":"US",
    "sg:address":"78 Allen St",
    "sg:city":"Buffalo",
    "sg:classifiers":[
        {
            "category":"Arts & Performance",
            "subcategory":"Art Gallery",
            "type":"Entertainment"
        }
    ],
    "sg:phone":"+1 716 884 1777",
    "sg:postcode":"14202",
    "sg:province":"NY",
    "sg:website":"www.buffalobigprint.com",
    "wof:name":"Buffalo Big Print",
    "wof:placetype":"venue"
},
  "geometry": {"coordinates":[-78.872902,42.899502],"type":"Point"}
}