{
  "type": "Feature",
  "properties": {
    "iso:country":"US",
    "sg:address":"62 Yorkshire Dr",
    "sg:city":"Suffern",
    "sg:classifiers":[
        {
            "category":"Building & Trades",
            "subcategory":"Landscaping Services",
            "type":"Services"
        }
    ],
    "sg:phone":"+1 845 369 8812",
    "sg:postcode":"10901",
    "sg:province":"NY",
    "wof:name":"2nd Nature Lawn Care",
    "wof:placetype":"venue"
},
  "geometry": {"coordinates":[-74.13194900000001,41.10479],"type":"Point"}
}