{
  "type": "Feature",
  "properties": {
    "addr:full":"281 S Lenox Ave Patchogue NY 11772",
    "addr:housenumber":"281",
    "addr:postcode":"11772",
    "addr:street":"S Lenox Ave",
    "iso:country":"US",
    "sg:address":"281 S Lenox Ave",
    "sg:city":"Patchogue",
    "sg:classifiers":[
        {
            "category":"Manufacturing",
            "subcategory":"Printing",
            "type":"Manufacturing & Wholesale Goods"
        }
    ],
    "sg:phone":"+1   ",
    "sg:postcode":"11772",
    "sg:province":"NY",
    "sg:tags":[
        "miscellaneous",
        "publishing"
    ],
    "wof:name":"Artsforgoldenage",
    "wof:placetype":"venue"
},
  "geometry": {"coordinates":[-72.95834000000001,40.765093],"type":"Point"}
}