{
  "type": "Feature",
  "properties": {
    "addr:full":"1046 W Beech St Long Beach NY 11561",
    "addr:housenumber":"1046",
    "addr:postcode":"11561",
    "addr:street":"W Beech St",
    "iso:country":"US",
    "sg:address":"1046 W Beech St",
    "sg:city":"Long Beach",
    "sg:classifiers":[
        {
            "category":"Taxi",
            "type":"Transportation"
        }
    ],
    "sg:phone":"+1 516 431 8888",
    "sg:postcode":"11561",
    "sg:province":"NY",
    "wof:name":"Long Beach Checker Inc.",
    "wof:placetype":"venue"
},
  "geometry": {"coordinates":[-73.697884,40.585999],"type":"Point"}
}