{
  "type": "Feature",
  "properties": {
    "addr:full":"355 Lexington Ave New York NY 10017",
    "addr:housenumber":"355",
    "addr:postcode":"10017",
    "addr:street":"Lexington Ave",
    "iso:country":"US",
    "sg:address":"355 Lexington Ave",
    "sg:city":"New York",
    "sg:classifiers":[
        {
            "category":"Organizations",
            "subcategory":"Non-profit Organization",
            "type":"Services"
        }
    ],
    "sg:phone":"+1 212 973 0325",
    "sg:postcode":"10017",
    "sg:province":"NY",
    "wof:name":"Wedo",
    "wof:placetype":"venue"
},
  "geometry": {"coordinates":[-73.976535,40.750775],"type":"Point"}
}