{
  "type": "Feature",
  "properties": {
    "iso:country":"US",
    "sg:address":"3 Jessitar Rd",
    "sg:city":"Katonah",
    "sg:classifiers":[
        {
            "category":"Restaurant",
            "type":"Food & Drink"
        }
    ],
    "sg:phone":"+1   ",
    "sg:postcode":"10560",
    "sg:province":"NY",
    "sg:tags":[
        "pizzeria"
    ],
    "wof:name":"Broadway Three Pizzeria",
    "wof:placetype":"venue"
},
  "geometry": {"coordinates":[-73.666554,41.308612],"type":"Point"}
}