{
  "type": "Feature",
  "properties": {
    "iso:country":"US",
    "sg:address":"285 Irondequoit Blvd",
    "sg:city":"Rochester",
    "sg:classifiers":[
        {
            "category":"Personal",
            "subcategory":"Beauty Salon",
            "type":"Services"
        }
    ],
    "sg:phone":"+1 585 266 4400",
    "sg:postcode":"14609",
    "sg:province":"NY",
    "wof:name":"Trade Secret",
    "wof:placetype":"venue"
},
  "geometry": {"coordinates":[-77.535918,43.176301],"type":"Point"}
}