{
  "type": "Feature",
  "properties": {
    "addr:full":"220 E 42nd St New York NY 10017",
    "addr:housenumber":"220",
    "addr:postcode":"10017",
    "addr:street":"E 42Nd St",
    "iso:country":"US",
    "sg:address":"220 E 42nd St",
    "sg:city":"New York",
    "sg:classifiers":[
        {
            "category":"Professional",
            "subcategory":"Advertising",
            "type":"Services"
        }
    ],
    "sg:phone":"+1 646 674 3300",
    "sg:postcode":"10017",
    "sg:province":"NY",
    "sg:tags":[
        "counselor"
    ],
    "wof:name":"Company X",
    "wof:placetype":"venue"
},
  "geometry": {"coordinates":[-73.972587,40.74995],"type":"Point"}
}