{
  "type": "Feature",
  "properties": {
    "addr:full":"600 Bear Ridge Rd Pleasantville NY 10570",
    "addr:housenumber":"600",
    "addr:postcode":"10570",
    "addr:street":"Bear Ridge Rd",
    "iso:country":"US",
    "sg:address":"600 Bear Ridge Rd",
    "sg:city":"Pleasantville",
    "sg:classifiers":[
        {
            "category":"Arts & Performance",
            "subcategory":"Arts Center",
            "type":"Entertainment"
        },
        {
            "category":"Cinema",
            "subcategory":"Movie Theater",
            "type":"Entertainment"
        }
    ],
    "sg:phone":"+1 914 741 0333",
    "sg:postcode":"10570",
    "sg:province":"NY",
    "sg:tags":[
        "performing"
    ],
    "wof:name":"Ym-Ywha of Northern Westchester",
    "wof:placetype":"venue"
},
  "geometry": {"coordinates":[-73.756897,41.131001],"type":"Point"}
}