{
  "type": "Feature",
  "properties": {
    "addr:full":"8816 State Hwy 415 Avoca NY 14809",
    "addr:housenumber":"8816",
    "addr:postcode":"14809",
    "addr:street":"State Hwy 415",
    "iso:country":"US",
    "sg:address":"8816 State Hwy 415",
    "sg:city":"Avoca",
    "sg:classifiers":[
        {
            "category":"Freight",
            "type":"Transportation"
        }
    ],
    "sg:phone":"+1   ",
    "sg:postcode":"14809",
    "sg:province":"NY",
    "sg:tags":[
        "operator",
        "trucking"
    ],
    "wof:name":"D & S Trucking",
    "wof:placetype":"venue"
},
  "geometry": {"coordinates":[-77.44285600000001,42.423927],"type":"Point"}
}