{
  "type": "Feature",
  "properties": {
    "addr:full":"35 W 177th St Bronx NY 10453",
    "addr:housenumber":"35",
    "addr:postcode":"10453",
    "addr:street":"W 177Th St",
    "iso:country":"US",
    "sg:address":"35 W 177th St",
    "sg:city":"Bronx",
    "sg:classifiers":[
        {
            "category":"Travel",
            "subcategory":"Bed & Breakfast",
            "type":"Entertainment"
        }
    ],
    "sg:phone":"+1   ",
    "sg:postcode":"10453",
    "sg:province":"NY",
    "sg:tags":[
        "house"
    ],
    "wof:name":"Dors Century Dwelling Corp",
    "wof:placetype":"venue"
},
  "geometry": {"coordinates":[-73.912021,40.850283],"type":"Point"}
}