{
  "type": "Feature",
  "properties": {
    "addr:full":"275 Ave U Brooklyn NY 11223",
    "addr:housenumber":"275",
    "addr:postcode":"11223",
    "addr:street":"Ave U",
    "iso:country":"US",
    "sg:address":"275 Ave U",
    "sg:city":"Brooklyn",
    "sg:classifiers":[
        {
            "category":"Banks & Credit Unions",
            "subcategory":"Bank",
            "type":"Services"
        }
    ],
    "sg:phone":"+1 718 376 2900",
    "sg:postcode":"11223",
    "sg:province":"NY",
    "sg:tags":[
        "loan",
        "real estate"
    ],
    "sg:website":"www.ezmoney.com",
    "wof:name":"USA Team One",
    "wof:placetype":"venue"
},
  "geometry": {"coordinates":[-73.973308,40.597044],"type":"Point"}
}