{
  "type": "Feature",
  "properties": {
    "iso:country":"US",
    "sg:address":"15 Elk St",
    "sg:city":"Amsterdam",
    "sg:classifiers":[
        {
            "category":"Freight",
            "type":"Transportation"
        }
    ],
    "sg:phone":"+1   ",
    "sg:postcode":"12010",
    "sg:province":"NY",
    "sg:tags":[
        "leather",
        "general",
        "mfg"
    ],
    "wof:name":"Fownes Brothers & Co Inc",
    "wof:placetype":"venue"
},
  "geometry": {"coordinates":[-74.17846400000001,42.930331],"type":"Point"}
}