{
  "type": "Feature",
  "properties": {
    "iso:country":"US",
    "sg:address":"5 Marine Air Terminal",
    "sg:city":"Flushing",
    "sg:classifiers":[
        {
            "category":"Education",
            "subcategory":"Special Training",
            "type":"Public Place"
        }
    ],
    "sg:phone":"+1 718 397 8494",
    "sg:postcode":"11371",
    "sg:province":"NY",
    "sg:tags":[
        "aircraft",
        "flight",
        "school"
    ],
    "wof:name":"Flight Safety International Inc",
    "wof:placetype":"venue"
},
  "geometry": {"coordinates":[-73.887725,40.768516],"type":"Point"}
}