{
  "type": "Feature",
  "properties": {
    "addr:full":"160 Forts Ferry Rd Latham NY 12110",
    "addr:housenumber":"160",
    "addr:postcode":"12110",
    "addr:street":"Forts Ferry Rd",
    "iso:country":"US",
    "sg:address":"160 Forts Ferry Rd",
    "sg:city":"Latham",
    "sg:classifiers":[
        {
            "category":"Education",
            "subcategory":"Dance Studio",
            "type":"Public Place"
        }
    ],
    "sg:phone":"+1   ",
    "sg:postcode":"12110",
    "sg:province":"NY",
    "wof:name":"Jo Anns Academy of Dance",
    "wof:placetype":"venue"
},
  "geometry": {"coordinates":[-73.784677,42.772728],"type":"Point"}
}