{
  "type": "Feature",
  "properties": {
    "addr:full":"441 E Allen St Hudson NY 12534",
    "addr:housenumber":"441",
    "addr:postcode":"12534",
    "addr:street":"E Allen St",
    "iso:country":"US",
    "sg:address":"441 E Allen St",
    "sg:city":"Hudson",
    "sg:classifiers":[
        {
            "category":"Professional",
            "subcategory":"Lawyer & Legal Services",
            "type":"Services"
        }
    ],
    "sg:phone":"+1 518 828 1521",
    "sg:postcode":"12534",
    "sg:province":"NY",
    "wof:name":"Connor Curran & Schram PC",
    "wof:placetype":"venue"
},
  "geometry": {"coordinates":[-73.78939800000001,42.249298],"type":"Point"}
}