{
  "type": "Feature",
  "properties": {
    "addr:full":"155 S 1st Ave Mount Vernon NY 10550",
    "addr:housenumber":"155",
    "addr:postcode":"10550",
    "addr:street":"S 1St Ave",
    "iso:country":"US",
    "sg:address":"155 S 1st Ave",
    "sg:city":"Mount Vernon",
    "sg:classifiers":[
        {
            "category":"Wholesale",
            "subcategory":"Machinery & Supplies",
            "type":"Manufacturing & Wholesale Goods"
        }
    ],
    "sg:phone":"+1 914 438 4638",
    "sg:postcode":"10550",
    "sg:province":"NY",
    "sg:tags":[
        "equipment",
        "welding"
    ],
    "wof:name":"Superior Welding Equipment",
    "wof:placetype":"venue"
},
  "geometry": {"coordinates":[-73.832728,40.908712],"type":"Point"}
}