{
  "type": "Feature",
  "properties": {
    "addr:full":"7 Pine Grove Ave Rosendale NY 12472",
    "addr:housenumber":"7",
    "addr:postcode":"12472",
    "addr:street":"Pine Grove Ave",
    "iso:country":"US",
    "sg:address":"7 Pine Grove Ave",
    "sg:city":"Rosendale",
    "sg:classifiers":[
        {
            "category":"Organizations",
            "subcategory":"Membership Organization",
            "type":"Services"
        }
    ],
    "sg:phone":"+1 845 658 9450",
    "sg:postcode":"12472",
    "sg:province":"NY",
    "wof:name":"Interntnal Assn of Lions Clubs",
    "wof:placetype":"venue"
},
  "geometry": {"coordinates":[-74.081682,41.837095],"type":"Point"}
}