{
  "type": "Feature",
  "properties": {
    "addr:full":"5 Danbury Ct Albany NY 12205",
    "addr:housenumber":"5",
    "addr:postcode":"12205",
    "addr:street":"Danbury Ct",
    "iso:country":"US",
    "sg:address":"5 Danbury Ct",
    "sg:city":"Albany",
    "sg:classifiers":[
        {
            "category":"Professional",
            "subcategory":"Management & Consulting",
            "type":"Services"
        }
    ],
    "sg:phone":"+1 518 489 4395",
    "sg:postcode":"12205",
    "sg:province":"NY",
    "sg:tags":[
        "consultant",
        "business"
    ],
    "wof:name":"Energy Strategies Inc",
    "wof:placetype":"venue"
},
  "geometry": {"coordinates":[-73.85518500000001,42.750254],"type":"Point"}
}