{
  "type": "Feature",
  "properties": {
    "iso:country":"US",
    "sg:address":"560 W 3rd St",
    "sg:city":"Jamestown",
    "sg:classifiers":[
        {
            "category":"Shopping",
            "subcategory":"News",
            "type":"Retail Goods"
        }
    ],
    "sg:phone":"+1 716 661 3017",
    "sg:postcode":"14701",
    "sg:province":"NY",
    "sg:tags":[
        "dealer"
    ],
    "wof:name":"West Park Direct",
    "wof:placetype":"venue"
},
  "geometry": {"coordinates":[-79.253225,42.094364],"type":"Point"}
}