{
  "type": "Feature",
  "properties": {
    "iso:country":"US",
    "sg:address":"6751 Michael Rd",
    "sg:city":"Orchard Park",
    "sg:classifiers":[
        {
            "category":"Professional",
            "subcategory":"Business Services",
            "type":"Services"
        }
    ],
    "sg:phone":"+1 716 675 2044",
    "sg:postcode":"14127",
    "sg:province":"NY",
    "sg:tags":[
        "recording",
        "studio"
    ],
    "wof:name":"Advanced Audio Productions",
    "wof:placetype":"venue"
},
  "geometry": {"coordinates":[-78.73976999999999,42.803795],"type":"Point"}
}