{
  "type": "Feature",
  "properties": {
    "iso:country":"US",
    "sg:address":"654 Main St",
    "sg:city":"East Aurora",
    "sg:classifiers":[
        {
            "category":"Shopping",
            "subcategory":"Used Merchandise",
            "type":"Retail Goods"
        }
    ],
    "sg:phone":"+1   ",
    "sg:postcode":"14052",
    "sg:province":"NY",
    "sg:tags":[
        "book",
        "rare"
    ],
    "wof:name":"Bookmark",
    "wof:placetype":"venue"
},
  "geometry": {"coordinates":[-78.61058,42.767952],"type":"Point"}
}