{
  "type": "Feature",
  "properties": {
    "addr:full":"375 N French Rd Buffalo NY 14228",
    "addr:housenumber":"375",
    "addr:postcode":"14228",
    "addr:street":"N French Rd",
    "iso:country":"US",
    "sg:address":"375 N French Rd",
    "sg:city":"Buffalo",
    "sg:classifiers":[
        {
            "category":"Autos & Motor Vehicles",
            "subcategory":"Automobile Sales",
            "type":"Retail Goods"
        },
        {
            "category":"Banks & Credit Unions",
            "subcategory":"Bank",
            "type":"Services"
        }
    ],
    "sg:phone":"+1 716 564 3671",
    "sg:postcode":"14228",
    "sg:province":"NY",
    "sg:tags":[
        "loan",
        "used"
    ],
    "wof:name":"United Auto Credit Corp",
    "wof:placetype":"venue"
},
  "geometry": {"coordinates":[-78.806747,43.034699],"type":"Point"}
}