{
  "type": "Feature",
  "properties": {
    "addr:full":"2684 Coney Island Ave Brooklyn NY 11235",
    "addr:housenumber":"2684",
    "addr:postcode":"11235",
    "addr:street":"Coney Island Ave",
    "iso:country":"US",
    "sg:address":"2684 Coney Island Ave",
    "sg:city":"Brooklyn",
    "sg:classifiers":[
        {
            "category":"Personal",
            "type":"Services"
        }
    ],
    "sg:phone":"+1 718 648 2952",
    "sg:postcode":"11235",
    "sg:province":"NY",
    "sg:tags":[
        "electrolysis"
    ],
    "wof:name":"Electrolysis By Sofia",
    "wof:placetype":"venue"
},
  "geometry": {"coordinates":[-73.96071999999999,40.591226],"type":"Point"}
}