{
  "type": "Feature",
  "properties": {
    "iso:country":"US",
    "sg:address":"52 Caversham Woods",
    "sg:city":"Pittsford",
    "sg:classifiers":[
        {
            "category":"Professional",
            "type":"Services"
        }
    ],
    "sg:phone":"+1 585 381 1254",
    "sg:postcode":"14534",
    "sg:province":"NY",
    "sg:tags":[
        "marketing",
        "training",
        "writings",
        "commercial"
    ],
    "wof:name":"Shenouda Associates Inc",
    "wof:placetype":"venue"
},
  "geometry": {"coordinates":[-77.544922,43.074075],"type":"Point"}
}