{
  "type": "Feature",
  "properties": {
    "addr:full":"125 W 92 St New York NY 10025",
    "addr:housenumber":"125",
    "addr:postcode":"10025",
    "addr:street":"W 92 St",
    "iso:country":"US",
    "sg:address":"125 W 92 St",
    "sg:city":"New York",
    "sg:classifiers":[
        {
            "category":"Education",
            "subcategory":"Special Training",
            "type":"Public Place"
        }
    ],
    "sg:phone":"+1 212 678 2500",
    "sg:postcode":"10025",
    "sg:province":"NY",
    "wof:name":"Access France",
    "wof:placetype":"venue"
},
  "geometry": {"coordinates":[-73.97166900000001,40.791269],"type":"Point"}
}