{
  "type": "Feature",
  "properties": {
    "iso:country":"US",
    "sg:address":"133 Hawley St",
    "sg:city":"Buffalo",
    "sg:classifiers":[
        {
            "category":"Personal",
            "subcategory":"Barber",
            "type":"Services"
        }
    ],
    "sg:phone":"+1 716 882 7700",
    "sg:postcode":"14213",
    "sg:province":"NY",
    "wof:name":"B & M Barbers",
    "wof:placetype":"venue"
},
  "geometry": {"coordinates":[-78.89,42.930954],"type":"Point"}
}