{
  "type": "Feature",
  "properties": {
    "iso:country":"US",
    "sg:address":"412 Ave of the Americas",
    "sg:city":"New York",
    "sg:classifiers":[
        {
            "category":"Health Services",
            "subcategory":"Health Practitioner",
            "type":"Services"
        }
    ],
    "sg:phone":"+1 212 777 7579",
    "sg:postcode":"10011",
    "sg:province":"NY",
    "sg:tags":[
        "psychotherapist"
    ],
    "wof:name":"Paula Marchese",
    "wof:placetype":"venue"
},
  "geometry": {"coordinates":[-73.999307,40.73375],"type":"Point"}
}