{
  "type": "Feature",
  "properties": {
    "addr:full":"3535 Old Yorktown Rd Yorktown Heights NY 10598",
    "addr:housenumber":"3535",
    "addr:postcode":"10598",
    "addr:street":"Old Yorktown Rd",
    "iso:country":"US",
    "sg:address":"3535 Old Yorktown Rd",
    "sg:city":"Yorktown Heights",
    "sg:classifiers":[
        {
            "category":"Health Services",
            "subcategory":"Doctor",
            "type":"Services"
        }
    ],
    "sg:phone":"+1   ",
    "sg:postcode":"10598",
    "sg:province":"NY",
    "wof:name":"Kenneth A Minichello DDS",
    "wof:placetype":"venue"
},
  "geometry": {"coordinates":[-73.818184,41.32505],"type":"Point"}
}