{
  "type": "Feature",
  "properties": {
    "iso:country":"US",
    "sg:address":"1500 Big Moose Rd",
    "sg:city":"Eagle Bay",
    "sg:classifiers":[
        {
            "category":"Autos & Motor Vehicles",
            "subcategory":"Boat Sales",
            "type":"Retail Goods"
        }
    ],
    "sg:phone":"+1 315 357 3532",
    "sg:postcode":"13331",
    "sg:province":"NY",
    "sg:tags":[
        "dealer",
        "sales"
    ],
    "wof:name":"Dunn's Boat Svc",
    "wof:placetype":"venue"
},
  "geometry": {"coordinates":[-74.879653,43.817337],"type":"Point"}
}