{
  "type": "Feature",
  "properties": {
    "addr:full":"220 Maple Ave Rockville Centre NY 11570",
    "addr:housenumber":"220",
    "addr:postcode":"11570",
    "addr:street":"Maple Ave",
    "iso:country":"US",
    "sg:address":"220 Maple Ave",
    "sg:city":"Rockville Centre",
    "sg:classifiers":[
        {
            "category":"Arts & Performance",
            "subcategory":"Arts Center",
            "type":"Entertainment"
        },
        {
            "category":"Education",
            "subcategory":"School",
            "type":"Public Place"
        }
    ],
    "sg:phone":"+1 516 594 9745",
    "sg:postcode":"11570",
    "sg:province":"NY",
    "sg:tags":[
        "performing"
    ],
    "sg:website":"www.mapleavenuedance.com",
    "wof:name":"Maple Avenue Dance Center",
    "wof:placetype":"venue"
},
  "geometry": {"coordinates":[-73.638397,40.664501],"type":"Point"}
}