{
  "type": "Feature",
  "properties": {
    "iso:country":"US",
    "sg:address":"476 Elmont Rd",
    "sg:city":"Elmont",
    "sg:classifiers":[
        {
            "category":"Health Services",
            "subcategory":"Dentist",
            "type":"Services"
        }
    ],
    "sg:phone":"+1 516 354 5805",
    "sg:postcode":"11003",
    "sg:province":"NY",
    "wof:name":"Beague Thomas P Dntst",
    "wof:placetype":"venue"
},
  "geometry": {"coordinates":[-73.714798,40.697498],"type":"Point"}
}