{
  "type": "Feature",
  "properties": {
    "addr:full":"6 Lady Godiva Way New City NY 10956",
    "addr:housenumber":"6",
    "addr:postcode":"10956",
    "addr:street":"Lady Godiva Way",
    "iso:country":"US",
    "sg:address":"6 Lady Godiva Way",
    "sg:city":"New City",
    "sg:classifiers":[
        {
            "category":"Real Estate",
            "subcategory":"Real Estate Agent",
            "type":"Services"
        }
    ],
    "sg:phone":"+1 845 634 0584",
    "sg:postcode":"10956",
    "sg:province":"NY",
    "sg:tags":[
        "inspection"
    ],
    "wof:name":"Stuart Schrager Cnsultng Engnr",
    "wof:placetype":"venue"
},
  "geometry": {"coordinates":[-73.97559800000001,41.155138],"type":"Point"}
}