{
  "type": "Feature",
  "properties": {
    "iso:country":"US",
    "sg:address":"2205 Teall Ave",
    "sg:city":"Syracuse",
    "sg:classifiers":[
        {
            "category":"Food & Beverages",
            "subcategory":"Bakery",
            "type":"Retail Goods"
        }
    ],
    "sg:phone":"+1   ",
    "sg:postcode":"13206",
    "sg:province":"NY",
    "sg:website":"www.lyncourtbakery.com",
    "wof:name":"Lyncourt Bakery",
    "wof:placetype":"venue"
},
  "geometry": {"coordinates":[-76.12362899999999,43.08174],"type":"Point"}
}