{
  "type": "Feature",
  "properties": {
    "addr:full":"4206 Snyder Ave Brooklyn NY 11203",
    "addr:housenumber":"4206",
    "addr:postcode":"11203",
    "addr:street":"Snyder Ave",
    "iso:country":"US",
    "sg:address":"4206 Snyder Ave",
    "sg:city":"Brooklyn",
    "sg:classifiers":[
        {
            "category":"Building & Trades",
            "subcategory":"Construction",
            "type":"Services"
        }
    ],
    "sg:phone":"+1 347 529 0861",
    "sg:postcode":"11203",
    "sg:province":"NY",
    "sg:tags":[
        "contractor"
    ],
    "wof:name":"Superb Contractor",
    "wof:placetype":"venue"
},
  "geometry": {"coordinates":[-73.93782,40.649507],"type":"Point"}
}