{
  "type": "Feature",
  "properties": {
    "iso:country":"US",
    "sg:address":"4 Bittersweet Pl",
    "sg:city":"Huntington",
    "sg:classifiers":[
        {
            "category":"Professional",
            "subcategory":"Management & Consulting",
            "type":"Services"
        }
    ],
    "sg:phone":"+1   ",
    "sg:postcode":"11743",
    "sg:province":"NY",
    "sg:tags":[
        "business"
    ],
    "wof:name":"Jalem Consulting Inc",
    "wof:placetype":"venue"
},
  "geometry": {"coordinates":[-73.433463,40.887911],"type":"Point"}
}