{
  "type": "Feature",
  "properties": {
    "iso:country":"US",
    "sg:address":"19 North Blvd",
    "sg:city":"Gloversville",
    "sg:classifiers":[
        {
            "category":"Restaurant",
            "type":"Food & Drink"
        }
    ],
    "sg:phone":"+1 518 725 7685",
    "sg:postcode":"12078",
    "sg:province":"NY",
    "wof:name":"Fonda A",
    "wof:placetype":"venue"
},
  "geometry": {"coordinates":[-74.332964,43.060559],"type":"Point"}
}