{
  "type": "Feature",
  "properties": {
    "addr:full":"12 Graves St Brockport NY 14420",
    "addr:housenumber":"12",
    "addr:postcode":"14420",
    "addr:street":"Graves St",
    "iso:country":"US",
    "sg:address":"12 Graves St",
    "sg:city":"Brockport",
    "sg:classifiers":[
        {
            "category":"Health Services",
            "subcategory":"Doctor",
            "type":"Services"
        }
    ],
    "sg:phone":"+1 585 637 5585",
    "sg:postcode":"14420",
    "sg:province":"NY",
    "sg:tags":[
        "physician",
        "family",
        "practice",
        "surgeons",
        "medicine",
        "surgeon"
    ],
    "wof:name":"Musheer Hussain Md",
    "wof:placetype":"venue"
},
  "geometry": {"coordinates":[-77.941997,43.218611],"type":"Point"}
}