{
  "type": "Feature",
  "properties": {
    "iso:country":"US",
    "sg:address":"19 Woodlake Dr E",
    "sg:city":"Woodbury",
    "sg:classifiers":[
        {
            "category":"Railroad",
            "type":"Transportation"
        }
    ],
    "sg:phone":"+1   ",
    "sg:postcode":"11797",
    "sg:province":"NY",
    "sg:tags":[
        "operator",
        "line"
    ],
    "wof:name":"RR Enterprises",
    "wof:placetype":"venue"
},
  "geometry": {"coordinates":[-73.47409399999999,40.812726],"type":"Point"}
}