{
  "type": "Feature",
  "properties": {
    "iso:country":"US",
    "sg:address":"316 Towne Dr",
    "sg:city":"Fayetteville",
    "sg:phone":"+1 315 637 3287",
    "sg:postcode":"13066",
    "sg:province":"NY",
    "wof:name":"Great Northern Pizza Kitchen",
    "wof:placetype":"venue"
},
  "geometry": {"coordinates":[-76.018562,43.03252],"type":"Point"}
}