{
  "type": "Feature",
  "properties": {
    "addr:full":"1315 Avenue J Brooklyn NY 11230",
    "addr:housenumber":"1315",
    "addr:postcode":"11230",
    "addr:street":"Avenue J",
    "iso:country":"US",
    "sg:address":"1315 Avenue J",
    "sg:city":"Brooklyn",
    "sg:classifiers":[
        {
            "category":"Real Estate",
            "subcategory":"Real Estate Services",
            "type":"Services"
        }
    ],
    "sg:phone":"+1 718 258 8343",
    "sg:postcode":"11230",
    "sg:province":"NY",
    "sg:tags":[
        "management",
        "property"
    ],
    "wof:name":"L P Hudson Incorporated",
    "wof:placetype":"venue"
},
  "geometry": {"coordinates":[-73.963126,40.62513],"type":"Point"}
}