{
  "type": "Feature",
  "properties": {
    "iso:country":"US",
    "sg:address":"2019 Glasco Tpke",
    "sg:city":"Woodstock",
    "sg:classifiers":[
        {
            "category":"Manufacturing",
            "subcategory":"Apparel",
            "type":"Manufacturing & Wholesale Goods"
        }
    ],
    "sg:phone":"+1   ",
    "sg:postcode":"12498",
    "sg:province":"NY",
    "sg:tags":[
        "sweater",
        "mfg"
    ],
    "wof:name":"Basia",
    "wof:placetype":"venue"
},
  "geometry": {"coordinates":[-74.100791,42.052488],"type":"Point"}
}