{
  "type": "Feature",
  "properties": {
    "addr:full":"202 Paul Saxe Rd Catskill NY 12414",
    "addr:housenumber":"202",
    "addr:postcode":"12414",
    "addr:street":"Paul Saxe Rd",
    "iso:country":"US",
    "sg:address":"202 Paul Saxe Rd",
    "sg:city":"Catskill",
    "sg:phone":"+1 518 678 0306",
    "sg:postcode":"12414",
    "sg:province":"NY",
    "wof:name":"Catskill Computer Service",
    "wof:placetype":"venue"
},
  "geometry": {"coordinates":[-73.968189,42.216709],"type":"Point"}
}