{
  "type": "Feature",
  "properties": {
    "iso:country":"US",
    "sg:address":"229 Wickham Ave",
    "sg:city":"Middletown",
    "sg:classifiers":[
        {
            "category":"Restaurant",
            "type":"Food & Drink"
        }
    ],
    "sg:phone":"+1 845 342 5155",
    "sg:postcode":"10940",
    "sg:province":"NY",
    "wof:name":"Johnny's D's",
    "wof:placetype":"venue"
},
  "geometry": {"coordinates":[-74.403398,41.453621],"type":"Point"}
}