{
  "type": "Feature",
  "properties": {
    "iso:country":"US",
    "sg:address":"33 Sioux Dr",
    "sg:city":"Commack",
    "sg:classifiers":[
        {
            "category":"Cinema",
            "subcategory":"Movie Rental",
            "type":"Entertainment"
        }
    ],
    "sg:phone":"+1   ",
    "sg:postcode":"11725",
    "sg:province":"NY",
    "sg:tags":[
        "video",
        "tape"
    ],
    "wof:name":"Saga Video Tributes",
    "wof:placetype":"venue"
},
  "geometry": {"coordinates":[-73.277467,40.82988],"type":"Point"}
}