{
  "type": "Feature",
  "properties": {
    "iso:country":"US",
    "sg:address":"243 E 237th St",
    "sg:city":"Bronx",
    "sg:classifiers":[
        {
            "category":"Building & Trades",
            "subcategory":"Construction",
            "type":"Services"
        }
    ],
    "sg:phone":"+1 718 324 1443",
    "sg:postcode":"10470",
    "sg:province":"NY",
    "sg:tags":[
        "tile",
        "marble",
        "contractor"
    ],
    "wof:name":"Tsm Marble Inc",
    "wof:placetype":"venue"
},
  "geometry": {"coordinates":[-73.86856,40.89887],"type":"Point"}
}