{
  "type": "Feature",
  "properties": {
    "iso:country":"US",
    "sg:address":"58 Rockwood Cir",
    "sg:city":"Middletown",
    "sg:classifiers":[
        {
            "category":"Wholesale",
            "subcategory":"Metals & Minerals",
            "type":"Manufacturing & Wholesale Goods"
        }
    ],
    "sg:phone":"+1 845 692 2540",
    "sg:postcode":"10941",
    "sg:province":"NY",
    "sg:tags":[
        "center"
    ],
    "wof:name":"US Pipe & Foundry",
    "wof:placetype":"venue"
},
  "geometry": {"coordinates":[-74.374297,41.473544],"type":"Point"}
}