{
  "type": "Feature",
  "properties": {
    "addr:full":"3212 Lehigh St Caledonia NY 14423",
    "addr:housenumber":"3212",
    "addr:postcode":"14423",
    "addr:street":"Lehigh St",
    "iso:country":"US",
    "sg:address":"3212 Lehigh St",
    "sg:city":"Caledonia",
    "sg:classifiers":[
        {
            "category":"Building & Trades",
            "subcategory":"Construction",
            "type":"Services"
        }
    ],
    "sg:phone":"+1 585 538 4515",
    "sg:postcode":"14423",
    "sg:province":"NY",
    "sg:tags":[
        "woodworker"
    ],
    "wof:name":"Burnett Woodworks",
    "wof:placetype":"venue"
},
  "geometry": {"coordinates":[-77.85304499999999,42.977076],"type":"Point"}
}