{
  "type": "Feature",
  "properties": {
    "iso:country":"US",
    "sg:address":"372 Main St",
    "sg:city":"Massena",
    "sg:classifiers":[
        {
            "category":"Autos & Motor Vehicles",
            "subcategory":"Fuel & Gas Station",
            "type":"Retail Goods"
        }
    ],
    "sg:phone":"+1 315 769 8667",
    "sg:postcode":"13662",
    "sg:province":"NY",
    "sg:tags":[
        "oil"
    ],
    "wof:name":"Bill's Auto Repairs",
    "wof:placetype":"venue"
},
  "geometry": {"coordinates":[-74.889725,44.920568],"type":"Point"}
}