{
  "type": "Feature",
  "properties": {
    "iso:country":"US",
    "sg:address":"752 Somerdale Dr",
    "sg:city":"Webster",
    "sg:classifiers":[
        {
            "category":"Insurance",
            "subcategory":"Hazard Insurance",
            "type":"Services"
        }
    ],
    "sg:phone":"+1 585 670 0350",
    "sg:postcode":"14580",
    "sg:province":"NY",
    "wof:name":"Ohio Casualty",
    "wof:placetype":"venue"
},
  "geometry": {"coordinates":[-77.480999,43.221583],"type":"Point"}
}