{
  "type": "Feature",
  "properties": {
    "addr:full":"31 Timber Ridge Dr Spencerport NY 14559",
    "addr:housenumber":"31",
    "addr:postcode":"14559",
    "addr:street":"Timber Ridge Dr",
    "iso:country":"US",
    "sg:address":"31 Timber Ridge Dr",
    "sg:city":"Spencerport",
    "sg:classifiers":[
        {
            "category":"Building & Trades",
            "subcategory":"Construction",
            "type":"Services"
        }
    ],
    "sg:phone":"+1 585 349 2686",
    "sg:postcode":"14559",
    "sg:province":"NY",
    "sg:tags":[
        "residential"
    ],
    "wof:name":"Anthony D Clemente Inc",
    "wof:placetype":"venue"
},
  "geometry": {"coordinates":[-77.808132,43.181156],"type":"Point"}
}