{
  "type": "Feature",
  "properties": {
    "addr:full":"139 Senator St Brooklyn NY 11220",
    "addr:housenumber":"139",
    "addr:postcode":"11220",
    "addr:street":"Senator St",
    "iso:country":"US",
    "sg:address":"139 Senator St",
    "sg:city":"Brooklyn",
    "sg:classifiers":[
        {
            "category":"Professional",
            "subcategory":"Printing & Photocopies",
            "type":"Services"
        },
        {
            "category":"Manufacturing",
            "subcategory":"Printing",
            "type":"Manufacturing & Wholesale Goods"
        }
    ],
    "sg:phone":"+1 718 748 3353",
    "sg:postcode":"11220",
    "sg:province":"NY",
    "sg:tags":[
        "commercial",
        "printer",
        "financial",
        "law"
    ],
    "wof:name":"Ann E Donahue",
    "wof:placetype":"venue"
},
  "geometry": {"coordinates":[-74.028741,40.638531],"type":"Point"}
}