{
  "type": "Feature",
  "properties": {
    "iso:country":"US",
    "sg:address":"16 Bransford St",
    "sg:city":"Patchogue",
    "sg:classifiers":[
        {
            "category":"Professional",
            "subcategory":"Accounting & Tax Preparation",
            "type":"Services"
        }
    ],
    "sg:phone":"+1 631 289 0187",
    "sg:postcode":"11772",
    "sg:province":"NY",
    "sg:tags":[
        "accountant"
    ],
    "wof:name":"A G Zahnd",
    "wof:placetype":"venue"
},
  "geometry": {"coordinates":[-73.020816,40.756578],"type":"Point"}
}