{
  "type": "Feature",
  "properties": {
    "addr:full":"699 Middle Country Rd Middle Island NY 11953",
    "addr:housenumber":"699",
    "addr:postcode":"11953",
    "addr:street":"Middle Country Rd Middle Island",
    "iso:country":"US",
    "sg:address":"699 Middle Country Rd",
    "sg:city":"Middle Island",
    "sg:classifiers":[
        {
            "category":"Health Services",
            "subcategory":"Doctor",
            "type":"Services"
        }
    ],
    "sg:phone":"+1 631 924 8155",
    "sg:postcode":"11953",
    "sg:province":"NY",
    "sg:tags":[
        "dentist"
    ],
    "sg:website":"www.tdc.com",
    "wof:name":"Total Dental Care",
    "wof:placetype":"venue"
},
  "geometry": {"coordinates":[-72.95319600000001,40.881053],"type":"Point"}
}