{
  "type": "Feature",
  "properties": {
    "iso:country":"US",
    "sg:address":"95 Nichols Rd",
    "sg:city":"Nesconset",
    "sg:classifiers":[
        {
            "category":"Organizations",
            "subcategory":"Religious Organization",
            "type":"Services"
        }
    ],
    "sg:phone":"+1 631 265 2200",
    "sg:postcode":"11767",
    "sg:province":"NY",
    "sg:tags":[
        "church"
    ],
    "sg:website":"www.pothc.org",
    "wof:name":"Holy Cross Catholic Church",
    "wof:placetype":"venue"
},
  "geometry": {"coordinates":[-73.141711,40.838345],"type":"Point"}
}