{
  "type": "Feature",
  "properties": {
    "addr:full":"1478 Victory Blvd Ste 1 Staten Island NY 10301",
    "addr:housenumber":"1478",
    "addr:postcode":"10301",
    "addr:street":"Victory Blvd Ste 1",
    "iso:country":"US",
    "sg:address":"1478 Victory Blvd Ste 1",
    "sg:city":"Staten Island",
    "sg:classifiers":[
        {
            "category":"Health Services",
            "subcategory":"Doctor",
            "type":"Services"
        }
    ],
    "sg:phone":"+1 718 442 3434",
    "sg:postcode":"10301",
    "sg:province":"NY",
    "wof:name":"Otway Toni MD",
    "wof:placetype":"venue"
},
  "geometry": {"coordinates":[-74.11274,40.613612],"type":"Point"}
}