{
  "type": "Feature",
  "properties": {
    "addr:full":"1384 Bay Street Staten Island NY 10305",
    "addr:housenumber":"1384",
    "addr:postcode":"10305",
    "addr:street":"Bay Street",
    "iso:country":"US",
    "sg:address":"1384 Bay Street",
    "sg:city":"Staten Island",
    "sg:classifiers":[
        {
            "category":"Restaurant",
            "type":"Food & Drink"
        }
    ],
    "sg:phone":"+1 718 720 3254",
    "sg:postcode":"10305",
    "sg:province":"NY",
    "wof:name":"Danny Blaine's Bay St Saloon",
    "wof:placetype":"venue"
},
  "geometry": {"coordinates":[-74.06309400000001,40.609769],"type":"Point"}
}