{
  "type": "Feature",
  "properties": {
    "addr:full":"5597 Zerfass Rd Dansville NY 14437",
    "addr:housenumber":"5597",
    "addr:postcode":"14437",
    "addr:street":"Zerfass Rd",
    "iso:country":"US",
    "sg:address":"5597 Zerfass Rd",
    "sg:city":"Dansville",
    "sg:classifiers":[
        {
            "category":"Farming",
            "subcategory":"Dairy Farm",
            "type":"Manufacturing & Wholesale Goods"
        },
        {
            "category":"Farming",
            "subcategory":"Farm",
            "type":"Manufacturing & Wholesale Goods"
        }
    ],
    "sg:phone":"+1 585 335 5497",
    "sg:postcode":"14437",
    "sg:province":"NY",
    "wof:name":"Nicholas Mark",
    "wof:placetype":"venue"
},
  "geometry": {"coordinates":[-77.719083,42.578782],"type":"Point"}
}