{
  "type": "Feature",
  "properties": {
    "iso:country":"US",
    "sg:address":"10 Nathan D Perlman Pl",
    "sg:city":"New York",
    "sg:classifiers":[
        {
            "category":"Health Services",
            "subcategory":"Doctor",
            "type":"Services"
        }
    ],
    "sg:phone":"+1 212 844 1538",
    "sg:postcode":"10003",
    "sg:province":"NY",
    "sg:tags":[
        "physician",
        "surgeon"
    ],
    "wof:name":"Ellen B Eisenstadt MD",
    "wof:placetype":"venue"
},
  "geometry": {"coordinates":[-73.982753,40.733923],"type":"Point"}
}