{
  "type": "Feature",
  "properties": {
    "addr:full":"363 Crown St Brooklyn NY 11225",
    "addr:housenumber":"363",
    "addr:postcode":"11225",
    "addr:street":"Crown St",
    "iso:country":"US",
    "sg:address":"363 Crown St",
    "sg:city":"Brooklyn",
    "sg:classifiers":[
        {
            "category":"Wholesale",
            "subcategory":"Painting Supplies",
            "type":"Manufacturing & Wholesale Goods"
        }
    ],
    "sg:phone":"+1 718 953 5433",
    "sg:postcode":"11225",
    "sg:province":"NY",
    "wof:name":"Fidelity Industries Inc",
    "wof:placetype":"venue"
},
  "geometry": {"coordinates":[-73.94571500000001,40.666093],"type":"Point"}
}