{
  "type": "Feature",
  "properties": {
    "iso:country":"US",
    "sg:address":"47 Midlawn Dr",
    "sg:city":"Massapequa",
    "sg:classifiers":[
        {
            "category":"Local Transit",
            "type":"Transportation"
        }
    ],
    "sg:phone":"+1   ",
    "sg:postcode":"11758",
    "sg:province":"NY",
    "sg:tags":[
        "passenger"
    ],
    "wof:name":"Avalon Limousine",
    "wof:placetype":"venue"
},
  "geometry": {"coordinates":[-73.47976199999999,40.709279],"type":"Point"}
}