{
  "type": "Feature",
  "properties": {
    "addr:full":"115 W 29th St New York NY 10001",
    "addr:housenumber":"115",
    "addr:postcode":"10001",
    "addr:street":"W 29Th St",
    "iso:country":"US",
    "sg:address":"115 W 29th St",
    "sg:city":"New York",
    "sg:classifiers":[
        {
            "category":"Communications",
            "subcategory":"Film & Video Production",
            "type":"Services"
        }
    ],
    "sg:phone":"+1 212 268 7603",
    "sg:postcode":"10001",
    "sg:province":"NY",
    "sg:tags":[
        "motion",
        "picture",
        "taping"
    ],
    "sg:website":"www.cicalafilmworks.com",
    "wof:name":"Cicala Filmworks",
    "wof:placetype":"venue"
},
  "geometry": {"coordinates":[-73.992566,40.74775],"type":"Point"}
}