{
  "type": "Feature",
  "properties": {
    "addr:full":"1091 Culver Rd Rochester NY 14609",
    "addr:housenumber":"1091",
    "addr:postcode":"14609",
    "addr:street":"Culver Rd",
    "iso:country":"US",
    "sg:address":"1091 Culver Rd",
    "sg:city":"Rochester",
    "sg:classifiers":[
        {
            "category":"Autos & Motor Vehicles",
            "subcategory":"Fuel & Gas Station",
            "type":"Retail Goods"
        }
    ],
    "sg:phone":"+1 585 288 3211",
    "sg:postcode":"14609",
    "sg:province":"NY",
    "sg:tags":[
        "oil"
    ],
    "wof:name":"John's National Garage",
    "wof:placetype":"venue"
},
  "geometry": {"coordinates":[-77.563299,43.165279],"type":"Point"}
}