{
  "type": "Feature",
  "properties": {
    "addr:full":"407 W Main St Endicott NY 13760",
    "addr:housenumber":"407",
    "addr:postcode":"13760",
    "addr:street":"W Main St",
    "iso:country":"US",
    "sg:address":"407 W Main St",
    "sg:city":"Endicott",
    "sg:classifiers":[
        {
            "category":"Banks & Credit Unions",
            "subcategory":"Investment Brokerage",
            "type":"Services"
        }
    ],
    "sg:phone":"+1 607 754 7979",
    "sg:postcode":"13760",
    "sg:province":"NY",
    "sg:tags":[
        "consultant",
        "planning",
        "financial"
    ],
    "wof:name":"Arac Enterprises",
    "wof:placetype":"venue"
},
  "geometry": {"coordinates":[-76.06976400000001,42.094425],"type":"Point"}
}