{
  "type": "Feature",
  "properties": {
    "addr:full":"521 W 38th St New York NY 10018",
    "addr:housenumber":"521",
    "addr:postcode":"10018",
    "addr:street":"W 38Th St",
    "iso:country":"US",
    "sg:address":"521 W 38th St",
    "sg:city":"New York",
    "sg:classifiers":[
        {
            "category":"Retail",
            "subcategory":"Auto Repair",
            "type":"Services"
        }
    ],
    "sg:phone":"+1 212 564 2020",
    "sg:postcode":"10018",
    "sg:province":"NY",
    "wof:name":"Aaa Auto Body Shop",
    "wof:placetype":"venue"
},
  "geometry": {"coordinates":[-73.998017,40.757569],"type":"Point"}
}