{
  "type": "Feature",
  "properties": {
    "iso:country":"US",
    "sg:address":"1540 Montauk Hwy",
    "sg:city":"Bellport",
    "sg:classifiers":[
        {
            "category":"Manufacturing",
            "subcategory":"Tools & Machinery",
            "type":"Manufacturing & Wholesale Goods"
        }
    ],
    "sg:phone":"+1   ",
    "sg:postcode":"11713",
    "sg:province":"NY",
    "sg:tags":[
        "machine",
        "shop"
    ],
    "wof:name":"Bossler & Sweezey Inc",
    "wof:placetype":"venue"
},
  "geometry": {"coordinates":[-72.953339,40.772423],"type":"Point"}
}