{
  "type": "Feature",
  "properties": {
    "addr:full":"152 Madison Avenue New York NY 10016",
    "addr:housenumber":"152",
    "addr:postcode":"10016",
    "addr:street":"Madison Avenue",
    "iso:country":"US",
    "sg:address":"152 Madison Avenue",
    "sg:city":"New York",
    "sg:classifiers":[
        {
            "category":"Shopping",
            "subcategory":"Beauty & Cosmetics",
            "type":"Retail Goods"
        }
    ],
    "sg:phone":"+1 212 673 7104",
    "sg:postcode":"10016",
    "sg:province":"NY",
    "sg:tags":[
        "supply"
    ],
    "wof:name":"Sue Devitt Studio",
    "wof:placetype":"venue"
},
  "geometry": {"coordinates":[-73.983822,40.746565],"type":"Point"}
}