{
  "type": "Feature",
  "properties": {
    "addr:full":"1524 44th St Brooklyn NY 11219",
    "addr:housenumber":"1524",
    "addr:postcode":"11219",
    "addr:street":"44Th St",
    "iso:country":"US",
    "sg:address":"1524 44th St",
    "sg:city":"Brooklyn",
    "sg:classifiers":[
        {
            "category":"Professional",
            "type":"Services"
        }
    ],
    "sg:phone":"+1 718 435 0992",
    "sg:postcode":"11219",
    "sg:province":"NY",
    "sg:tags":[
        "establishment"
    ],
    "wof:name":"Shatnez",
    "wof:placetype":"venue"
},
  "geometry": {"coordinates":[-73.983053,40.634104],"type":"Point"}
}