{
  "type": "Feature",
  "properties": {
    "addr:full":"3259 Waterbury Dr Wantagh NY 11793",
    "addr:housenumber":"3259",
    "addr:postcode":"11793",
    "addr:street":"Waterbury Dr",
    "iso:country":"US",
    "sg:address":"3259 Waterbury Dr",
    "sg:city":"Wantagh",
    "sg:classifiers":[
        {
            "category":"Health Services",
            "subcategory":"Hospital",
            "type":"Services"
        }
    ],
    "sg:phone":"+1 516 223 3222",
    "sg:postcode":"11793",
    "sg:province":"NY",
    "sg:tags":[
        "mental"
    ],
    "wof:name":"Nassau Shores Counseling LTD",
    "wof:placetype":"venue"
},
  "geometry": {"coordinates":[-73.5127,40.682808],"type":"Point"}
}