{
  "type": "Feature",
  "properties": {
    "addr:full":"7 Gerard St Huntington NY 11743",
    "addr:housenumber":"7",
    "addr:postcode":"11743",
    "addr:street":"Gerard St",
    "iso:country":"US",
    "sg:address":"7 Gerard St",
    "sg:city":"Huntington",
    "sg:classifiers":[
        {
            "category":"Restaurant",
            "type":"Food & Drink"
        }
    ],
    "sg:phone":"+1 631 385 8486",
    "sg:postcode":"11743",
    "sg:province":"NY",
    "sg:tags":[
        "italian"
    ],
    "sg:website":"www.porto-vivo.com",
    "wof:name":"Porto Vivo Restaurant and Bar",
    "wof:placetype":"venue"
},
  "geometry": {"coordinates":[-73.424357,40.872399],"type":"Point"}
}