{
  "type": "Feature",
  "properties": {
    "addr:full":"1406 57th St Brooklyn NY 11219",
    "addr:housenumber":"1406",
    "addr:postcode":"11219",
    "addr:street":"57Th St",
    "iso:country":"US",
    "sg:address":"1406 57th St",
    "sg:city":"Brooklyn",
    "sg:classifiers":[
        {
            "category":"Professional",
            "subcategory":"Accounting & Tax Preparation",
            "type":"Services"
        }
    ],
    "sg:phone":"+1   ",
    "sg:postcode":"11219",
    "sg:province":"NY",
    "wof:name":"M Pinter & Co",
    "wof:placetype":"venue"
},
  "geometry": {"coordinates":[-73.992527,40.627907],"type":"Point"}
}