{
  "type": "Feature",
  "properties": {
    "iso:country":"US",
    "sg:address":"650 Madison Ave",
    "sg:city":"New York",
    "sg:classifiers":[
        {
            "category":"Arts & Performance",
            "subcategory":"Theater",
            "type":"Entertainment"
        }
    ],
    "sg:phone":"+1 212 813 9400",
    "sg:postcode":"10022",
    "sg:province":"NY",
    "sg:tags":[
        "theatrical"
    ],
    "wof:name":"Beach Concerts Inc",
    "wof:placetype":"venue"
},
  "geometry": {"coordinates":[-73.971411,40.763588],"type":"Point"}
}