{
  "type": "Feature",
  "properties": {
    "iso:country":"US",
    "sg:address":"125 E 52nd St",
    "sg:city":"Brooklyn",
    "sg:classifiers":[
        {
            "category":"Retail",
            "subcategory":"Repair Shop",
            "type":"Services"
        }
    ],
    "sg:phone":"+1 646 365 3027",
    "sg:postcode":"11203",
    "sg:province":"NY",
    "sg:tags":[
        "lock",
        "locksmith"
    ],
    "wof:name":"Amitchi Locks & Gates",
    "wof:placetype":"venue"
},
  "geometry": {"coordinates":[-73.92891299999999,40.657041],"type":"Point"}
}