{
  "type": "Feature",
  "properties": {
    "addr:full":"51 Ridge Rd E Rochester NY 14621",
    "addr:housenumber":"51",
    "addr:postcode":"14621",
    "addr:street":"Ridge Rd E",
    "iso:country":"US",
    "sg:address":"51 Ridge Rd E",
    "sg:city":"Rochester",
    "sg:classifiers":[
        {
            "category":"Personal",
            "subcategory":"Beauty Salon",
            "type":"Services"
        }
    ],
    "sg:phone":"+1 585 342 7426",
    "sg:postcode":"14621",
    "sg:province":"NY",
    "wof:name":"Salon 45 House Of Style",
    "wof:placetype":"venue"
},
  "geometry": {"coordinates":[-77.61567599999999,43.192824],"type":"Point"}
}