{
  "type": "Feature",
  "properties": {
    "iso:country":"US",
    "sg:address":"115 Merrick Ave",
    "sg:city":"Merrick",
    "sg:classifiers":[
        {
            "category":"Shopping",
            "subcategory":"Clothing, Apparel, & Fashions",
            "type":"Retail Goods"
        }
    ],
    "sg:phone":"+1 516 665 8060",
    "sg:postcode":"11566",
    "sg:province":"NY",
    "sg:tags":[
        "children's",
        "clothing"
    ],
    "wof:name":"So Nikki",
    "wof:placetype":"venue"
},
  "geometry": {"coordinates":[-73.56529999999999,40.696098],"type":"Point"}
}