{
  "type": "Feature",
  "properties": {
    "iso:country":"US",
    "sg:address":"126 Main St",
    "sg:city":"Morris",
    "sg:classifiers":[
        {
            "category":"Restaurant",
            "type":"Food & Drink"
        }
    ],
    "sg:phone":"+1 607 263 9988",
    "sg:postcode":"13808",
    "sg:province":"NY",
    "sg:tags":[
        "cafeteria"
    ],
    "wof:name":"Nicole's Family Dinning",
    "wof:placetype":"venue"
},
  "geometry": {"coordinates":[-75.24683899999999,42.548135],"type":"Point"}
}