{
  "type": "Feature",
  "properties": {
    "addr:full":"1279 E 17th St Brooklyn NY 11230",
    "addr:housenumber":"1279",
    "addr:postcode":"11230",
    "addr:street":"E 17Th St",
    "iso:country":"US",
    "sg:address":"1279 E 17th St",
    "sg:city":"Brooklyn",
    "sg:classifiers":[
        {
            "category":"Building & Trades",
            "subcategory":"Construction",
            "type":"Services"
        }
    ],
    "sg:phone":"+1 718 377 1943",
    "sg:postcode":"11230",
    "sg:province":"NY",
    "sg:tags":[
        "contractor"
    ],
    "wof:name":"Ergul Contracting Inc",
    "wof:placetype":"venue"
},
  "geometry": {"coordinates":[-73.958099,40.619007],"type":"Point"}
}