{
  "type": "Feature",
  "properties": {
    "iso:country":"US",
    "sg:address":"39 Bella Casa Ln",
    "sg:city":"Central Islip",
    "sg:classifiers":[
        {
            "category":"Shopping",
            "subcategory":"Pharmacy",
            "type":"Retail Goods"
        }
    ],
    "sg:phone":"+1 631 851 1119",
    "sg:postcode":"11722",
    "sg:province":"NY",
    "sg:tags":[
        "pharmaceutical",
        "consultant"
    ],
    "wof:name":"Bernadette Anderson-Jones",
    "wof:placetype":"venue"
},
  "geometry": {"coordinates":[-73.181287,40.796554],"type":"Point"}
}