{
  "type": "Feature",
  "properties": {
    "addr:full":"2524 Ave M Brooklyn NY 11210",
    "addr:housenumber":"2524",
    "addr:postcode":"11210",
    "addr:street":"Ave M",
    "iso:country":"US",
    "sg:address":"2524 Ave M",
    "sg:city":"Brooklyn",
    "sg:classifiers":[
        {
            "category":"Organizations",
            "subcategory":"Religious Organization",
            "type":"Services"
        }
    ],
    "sg:phone":"+1 718 252 7691",
    "sg:postcode":"11210",
    "sg:province":"NY",
    "sg:tags":[
        "clergy"
    ],
    "wof:name":"Abba Kronenberg",
    "wof:placetype":"venue"
},
  "geometry": {"coordinates":[-73.94946299999999,40.619088],"type":"Point"}
}