{
  "type": "Feature",
  "properties": {
    "addr:full":"621 Hudson St New York NY 10014",
    "addr:housenumber":"621",
    "addr:postcode":"10014",
    "addr:street":"Hudson St",
    "iso:country":"US",
    "sg:address":"621 Hudson St",
    "sg:city":"New York",
    "sg:classifiers":[
        {
            "category":"Real Estate",
            "subcategory":"Real Estate Operator",
            "type":"Services"
        }
    ],
    "sg:phone":"+1 212 736 6888",
    "sg:postcode":"10014",
    "sg:province":"NY",
    "sg:tags":[
        "dwelling"
    ],
    "wof:name":"58 Jane Street Associates",
    "wof:placetype":"venue"
},
  "geometry": {"coordinates":[-74.00568699999999,40.737552],"type":"Point"}
}