{
  "type": "Feature",
  "properties": {
    "iso:country":"US",
    "sg:address":"152 Lawrence St",
    "sg:city":"Brooklyn",
    "sg:classifiers":[
        {
            "category":"Building & Trades",
            "subcategory":"Locksmith",
            "type":"Services"
        }
    ],
    "sg:phone":"+1 347 464 3662",
    "sg:postcode":"11201",
    "sg:province":"NY",
    "sg:tags":[
        "key"
    ],
    "wof:name":"24 7 Kwikset Lock And Key",
    "wof:placetype":"venue"
},
  "geometry": {"coordinates":[-73.986445,40.691876],"type":"Point"}
}