{
  "type": "Feature",
  "properties": {
    "addr:full":"4516 National Street Corona NY 11368",
    "addr:housenumber":"4516",
    "addr:postcode":"11368",
    "addr:street":"National Street",
    "iso:country":"US",
    "sg:address":"4516 National Street",
    "sg:city":"Corona",
    "sg:classifiers":[
        {
            "category":"Building & Trades",
            "subcategory":"Locksmith",
            "type":"Services"
        }
    ],
    "sg:phone":"+1 718 592 7298",
    "sg:postcode":"11368",
    "sg:province":"NY",
    "sg:tags":[
        "key"
    ],
    "wof:name":"Realiable Locksmith Corporation",
    "wof:placetype":"venue"
},
  "geometry": {"coordinates":[-73.864397,40.745674],"type":"Point"}
}