{
  "type": "Feature",
  "properties": {
    "addr:full":"11121 Davis Rd Utica NY 13502",
    "addr:housenumber":"11121",
    "addr:postcode":"13502",
    "addr:street":"Davis Rd",
    "iso:country":"US",
    "sg:address":"11121 Davis Rd",
    "sg:city":"Utica",
    "sg:classifiers":[
        {
            "category":"Manufacturing",
            "subcategory":"Buildings",
            "type":"Manufacturing & Wholesale Goods"
        },
        {
            "category":"Home & Garden",
            "subcategory":"Building Materials",
            "type":"Retail Goods"
        },
        {
            "category":"Building & Trades",
            "subcategory":"Construction",
            "type":"Services"
        }
    ],
    "sg:phone":"+1 315 738 1301",
    "sg:postcode":"13502",
    "sg:province":"NY",
    "sg:tags":[
        "foundation",
        "industrial",
        "builder",
        "contractor",
        "concrete",
        "contractors-commercial",
        "staining",
        "masonry",
        "mason"
    ],
    "wof:name":"Michael P Horan Masonry Inc",
    "wof:placetype":"venue"
},
  "geometry": {"coordinates":[-75.147638,43.170722],"type":"Point"}
}