{
  "type": "Feature",
  "properties": {
    "iso:country":"US",
    "sg:address":"1185 Parkwood Blvd",
    "sg:city":"Schenectady",
    "sg:classifiers":[
        {
            "category":"Shopping",
            "subcategory":"Catalog Store",
            "type":"Retail Goods"
        }
    ],
    "sg:phone":"+1 518 377 1294",
    "sg:postcode":"12308",
    "sg:province":"NY",
    "sg:tags":[
        "mail",
        "order",
        "online"
    ],
    "sg:website":"http://www.sassysatellite.com",
    "wof:name":"Sassy's Satellite",
    "wof:placetype":"venue"
},
  "geometry": {"coordinates":[-73.915218,42.813836],"type":"Point"}
}