{
  "type": "Feature",
  "properties": {
    "iso:country":"US",
    "sg:address":"62 Wyandanch Blvd",
    "sg:city":"Commack",
    "sg:classifiers":[
        {
            "category":"Utilities",
            "subcategory":"Fuel Oil & Lpg",
            "type":"Services"
        }
    ],
    "sg:phone":"+1   ",
    "sg:postcode":"11725",
    "sg:province":"NY",
    "sg:tags":[
        "dealer"
    ],
    "wof:name":"Fort Hill Fuel Oil Inc",
    "wof:placetype":"venue"
},
  "geometry": {"coordinates":[-73.25891,40.838313],"type":"Point"}
}