{
  "type": "Feature",
  "properties": {
    "addr:full":"1190 Castleton Ave Staten Island NY 10310",
    "addr:housenumber":"1190",
    "addr:postcode":"10310",
    "addr:street":"Castleton Ave",
    "iso:country":"US",
    "sg:address":"1190 Castleton Ave",
    "sg:city":"Staten Island",
    "sg:classifiers":[
        {
            "category":"Retail",
            "subcategory":"Repair Shop",
            "type":"Services"
        }
    ],
    "sg:phone":"+1   ",
    "sg:postcode":"10310",
    "sg:province":"NY",
    "sg:tags":[
        "electrical"
    ],
    "wof:name":"Sid Phillips Appliance Svc Co",
    "wof:placetype":"venue"
},
  "geometry": {"coordinates":[-74.122969,40.634011],"type":"Point"}
}