{
  "type": "Feature",
  "properties": {
    "iso:country":"US",
    "sg:address":"221 US Hwy 11",
    "sg:city":"Tully",
    "sg:classifiers":[
        {
            "category":"Farming",
            "subcategory":"Livestock Farm",
            "type":"Manufacturing & Wholesale Goods"
        }
    ],
    "sg:phone":"+1 315 696 8867",
    "sg:postcode":"13159",
    "sg:province":"NY",
    "sg:tags":[
        "corn",
        "wheat",
        "feedlot",
        "beef",
        "cattle"
    ],
    "wof:name":"Phillip Potter",
    "wof:placetype":"venue"
},
  "geometry": {"coordinates":[-76.114541,42.780353],"type":"Point"}
}