{
  "type": "Feature",
  "properties": {
    "addr:full":"2364 US Hwy 9 Mechanicville NY 12118",
    "addr:housenumber":"2364",
    "addr:postcode":"12118",
    "addr:street":"Us Hwy 9",
    "iso:country":"US",
    "sg:address":"2364 US Hwy 9",
    "sg:city":"Mechanicville",
    "sg:classifiers":[
        {
            "category":"Freight",
            "type":"Transportation"
        }
    ],
    "sg:phone":"+1   ",
    "sg:postcode":"12118",
    "sg:province":"NY",
    "sg:tags":[
        "product",
        "mfg",
        "trucking",
        "concrete",
        "operator",
        "local"
    ],
    "wof:name":"Malta Tank Co Inc",
    "wof:placetype":"venue"
},
  "geometry": {"coordinates":[-73.79032100000001,42.957595],"type":"Point"}
}