{
  "type": "Feature",
  "properties": {
    "addr:full":"5390 Merrick Rd Massapequa NY 11758",
    "addr:housenumber":"5390",
    "addr:postcode":"11758",
    "addr:street":"Merrick Rd",
    "iso:country":"US",
    "sg:address":"5390 Merrick Rd",
    "sg:city":"Massapequa",
    "sg:classifiers":[
        {
            "category":"Building & Trades",
            "subcategory":"Construction",
            "type":"Services"
        }
    ],
    "sg:phone":"+1 516 798 3900",
    "sg:postcode":"11758",
    "sg:province":"NY",
    "sg:tags":[
        "general",
        "contractor"
    ],
    "wof:name":"C J Rubino & Co",
    "wof:placetype":"venue"
},
  "geometry": {"coordinates":[-73.43468300000001,40.668732],"type":"Point"}
}