{
  "type": "Feature",
  "properties": {
    "addr:full":"415 Broad St Oneida NY 13421",
    "addr:housenumber":"415",
    "addr:postcode":"13421",
    "addr:street":"Broad St",
    "iso:country":"US",
    "sg:address":"415 Broad St",
    "sg:city":"Oneida",
    "sg:classifiers":[
        {
            "category":"Professional",
            "type":"Services"
        }
    ],
    "sg:phone":"+1   ",
    "sg:postcode":"13421",
    "sg:province":"NY",
    "wof:name":"Morgan Trailer Mfg Co",
    "wof:placetype":"venue"
},
  "geometry": {"coordinates":[-75.649187,43.087424],"type":"Point"}
}