{
  "type": "Feature",
  "properties": {
    "iso:country":"US",
    "sg:address":"2333 65th St",
    "sg:city":"Brooklyn",
    "sg:classifiers":[
        {
            "category":"Health Services",
            "subcategory":"Doctor",
            "type":"Services"
        }
    ],
    "sg:phone":"+1 718 645 7733",
    "sg:postcode":"11204",
    "sg:province":"NY",
    "sg:tags":[
        "physician",
        "surgeon"
    ],
    "wof:name":"Pro Medica PC",
    "wof:placetype":"venue"
},
  "geometry": {"coordinates":[-73.97748300000001,40.611565],"type":"Point"}
}