{
  "type": "Feature",
  "properties": {
    "iso:country":"US",
    "sg:address":"145 W 119th St",
    "sg:city":"New York",
    "sg:classifiers":[
        {
            "category":"Building & Trades",
            "subcategory":"Construction",
            "type":"Services"
        }
    ],
    "sg:phone":"+1 212 662 6065",
    "sg:postcode":"10026",
    "sg:province":"NY",
    "sg:tags":[
        "floor",
        "laying",
        "contractor"
    ],
    "wof:name":"Brownstone Floors Unlimited",
    "wof:placetype":"venue"
},
  "geometry": {"coordinates":[-73.95011100000001,40.804682],"type":"Point"}
}