{
  "type": "Feature",
  "properties": {
    "addr:full":"423 Loudon Rd Albany NY 12211",
    "addr:housenumber":"423",
    "addr:postcode":"12211",
    "addr:street":"Loudon Rd",
    "iso:country":"US",
    "sg:address":"423 Loudon Rd",
    "sg:city":"Albany",
    "sg:classifiers":[
        {
            "category":"Government",
            "subcategory":"Police Station",
            "type":"Public Place"
        },
        {
            "category":"Professional",
            "subcategory":"Lawyer & Legal Services",
            "type":"Services"
        }
    ],
    "sg:phone":"+1 518 436 0775",
    "sg:postcode":"12211",
    "sg:province":"NY",
    "sg:tags":[
        "attorney",
        "dwi",
        "duo",
        "damage",
        "property",
        "accident",
        "traffic",
        "criminal",
        "law"
    ],
    "sg:website":"http://www.proskinlawfirm.com",
    "wof:name":"Proskin Law Firm PC",
    "wof:placetype":"venue"
},
  "geometry": {"coordinates":[-73.75443799999999,42.70395],"type":"Point"}
}