{
  "type": "Feature",
  "properties": {
    "iso:country":"US",
    "sg:address":"466 Montauk Hwy",
    "sg:city":"East Moriches",
    "sg:classifiers":[
        {
            "category":"Restaurant",
            "type":"Food & Drink"
        }
    ],
    "sg:menulink":"http://www.allmenus.com/ny/brookhaven/255536-tonys-sushi-ii/menu/",
    "sg:phone":"+1 631 878 9575",
    "sg:postcode":"11940",
    "sg:province":"NY",
    "sg:tags":[
        "thai",
        "sushi",
        "asian"
    ],
    "wof:name":"Tony's Sushi Ii",
    "wof:placetype":"venue"
},
  "geometry": {"coordinates":[-72.744958,40.825178],"type":"Point"}
}