{
  "type": "Feature",
  "properties": {
    "addr:full":"100 Tec St Hicksville NY 11801",
    "addr:housenumber":"100",
    "addr:postcode":"11801",
    "addr:street":"Tec St",
    "iso:country":"US",
    "sg:address":"100 Tec St",
    "sg:city":"Hicksville",
    "sg:classifiers":[
        {
            "category":"Freight",
            "type":"Transportation"
        }
    ],
    "sg:phone":"+1   ",
    "sg:postcode":"11801",
    "sg:province":"NY",
    "sg:tags":[
        "equipment",
        "electrical",
        "general"
    ],
    "wof:name":"Lake Electronic Cable",
    "wof:placetype":"venue"
},
  "geometry": {"coordinates":[-73.54404700000001,40.757906],"type":"Point"}
}