{
  "type": "Feature",
  "properties": {
    "addr:full":"4960 Shearing Rd Gainesville NY 14066",
    "addr:housenumber":"4960",
    "addr:postcode":"14066",
    "addr:street":"Shearing Rd",
    "iso:country":"US",
    "sg:address":"4960 Shearing Rd",
    "sg:city":"Gainesville",
    "sg:classifiers":[
        {
            "category":"Organizations",
            "subcategory":"Professional Association",
            "type":"Services"
        }
    ],
    "sg:phone":"+1 585 493 5894",
    "sg:postcode":"14066",
    "sg:province":"NY",
    "sg:tags":[
        "business"
    ],
    "wof:name":"National Rural Letter Carriers",
    "wof:placetype":"venue"
},
  "geometry": {"coordinates":[-78.146924,42.637951],"type":"Point"}
}