{
  "type": "Feature",
  "properties": {
    "addr:full":"2809 Thornwoods Dr Niagara Falls NY 14304",
    "addr:housenumber":"2809",
    "addr:postcode":"14304",
    "addr:street":"Thornwoods Dr",
    "iso:country":"US",
    "sg:address":"2809 Thornwoods Dr",
    "sg:city":"Niagara Falls",
    "sg:classifiers":[
        {
            "category":"Health Services",
            "subcategory":"Clinic",
            "type":"Services"
        }
    ],
    "sg:phone":"+1   ",
    "sg:postcode":"14304",
    "sg:province":"NY",
    "wof:name":"Wny Health & Wellness",
    "wof:placetype":"venue"
},
  "geometry": {"coordinates":[-78.894402,43.100671],"type":"Point"}
}