{
  "type": "Feature",
  "properties": {
    "iso:country":"US",
    "sg:address":"218 S 4th Ave",
    "sg:city":"Ilion",
    "sg:classifiers":[
        {
            "category":"Building & Trades",
            "subcategory":"Construction",
            "type":"Services"
        }
    ],
    "sg:phone":"+1 315 894 0020",
    "sg:postcode":"13357",
    "sg:province":"NY",
    "sg:tags":[
        "contractor"
    ],
    "wof:name":"Sweet General Contractor",
    "wof:placetype":"venue"
},
  "geometry": {"coordinates":[-75.048185,43.008056],"type":"Point"}
}