{
  "type": "Feature",
  "properties": {
    "iso:country":"US",
    "sg:address":"225 Portage Rd",
    "sg:city":"Lewiston",
    "sg:classifiers":[
        {
            "category":"Health Services",
            "subcategory":"Podiatrist",
            "type":"Services"
        }
    ],
    "sg:phone":"+1 716 754 8926",
    "sg:postcode":"14092",
    "sg:province":"NY",
    "wof:name":"James R Hanna DPM",
    "wof:placetype":"venue"
},
  "geometry": {"coordinates":[-79.032499,43.169832],"type":"Point"}
}