{
  "type": "Feature",
  "properties": {
    "addr:full":"303 Lexington Ave New York NY 10016",
    "addr:housenumber":"303",
    "addr:postcode":"10016",
    "addr:street":"Lexington Ave",
    "iso:country":"US",
    "sg:address":"303 Lexington Ave",
    "sg:city":"New York",
    "sg:classifiers":[
        {
            "category":"Travel",
            "subcategory":"Hotels & Motels",
            "type":"Entertainment"
        }
    ],
    "sg:phone":"+1 212 689 5200",
    "sg:postcode":"10016",
    "sg:province":"NY",
    "sg:website":"www.affinia.com/New-York-City-Ho...",
    "wof:name":"Shelburne-Murray Hill Suite Hotel",
    "wof:placetype":"venue"
},
  "geometry": {"coordinates":[-73.97787,40.748364],"type":"Point"}
}