{
  "type": "Feature",
  "properties": {
    "addr:full":"453 Co Rd 39 Southampton NY 11968",
    "addr:housenumber":"453;39",
    "addr:postcode":"11968",
    "addr:street":"Co Rd",
    "iso:country":"US",
    "sg:address":"453 Co Rd 39",
    "sg:city":"Southampton",
    "sg:classifiers":[
        {
            "category":"Retail",
            "subcategory":"Auto Repair",
            "type":"Services"
        }
    ],
    "sg:phone":"+1 631 283 4565",
    "sg:postcode":"11968",
    "sg:province":"NY",
    "sg:tags":[
        "repairing",
        "automobile"
    ],
    "wof:name":"J & V Auto Body",
    "wof:placetype":"venue"
},
  "geometry": {"coordinates":[-72.411666,40.897995],"type":"Point"}
}