{
  "type": "Feature",
  "properties": {
    "addr:full":"159 Doughty Blvd Inwood NY 11096",
    "addr:housenumber":"159",
    "addr:postcode":"11096",
    "addr:street":"Doughty Blvd",
    "iso:country":"US",
    "sg:address":"159 Doughty Blvd",
    "sg:city":"Inwood",
    "sg:classifiers":[
        {
            "category":"Wholesale",
            "subcategory":"Durable Goods & Equipment",
            "type":"Manufacturing & Wholesale Goods"
        }
    ],
    "sg:phone":"+1 516 371 3500",
    "sg:postcode":"11096",
    "sg:province":"NY",
    "sg:tags":[
        "importer"
    ],
    "wof:name":"Unique Specialty Products LTD",
    "wof:placetype":"venue"
},
  "geometry": {"coordinates":[-73.74670500000001,40.616311],"type":"Point"}
}