{
  "type": "Feature",
  "properties": {
    "addr:full":"324 Dean St Brooklyn NY 11217",
    "addr:housenumber":"324",
    "addr:postcode":"11217",
    "addr:street":"Dean St",
    "iso:country":"US",
    "sg:address":"324 Dean St",
    "sg:city":"Brooklyn",
    "sg:classifiers":[
        {
            "category":"Wholesale",
            "subcategory":"Metals & Minerals",
            "type":"Manufacturing & Wholesale Goods"
        }
    ],
    "sg:phone":"+1 718 834 8984",
    "sg:postcode":"11217",
    "sg:province":"NY",
    "sg:tags":[
        "iron"
    ],
    "wof:name":"Yemen Iron Works",
    "wof:placetype":"venue"
},
  "geometry": {"coordinates":[-73.979603,40.683264],"type":"Point"}
}