{
  "type": "Feature",
  "properties": {
    "iso:country":"US",
    "sg:address":"804 S Crouse Ave",
    "sg:city":"Syracuse",
    "sg:classifiers":[
        {
            "category":"Shopping",
            "subcategory":"Luggage & Leather Goods",
            "type":"Retail Goods"
        }
    ],
    "sg:phone":"+1 315 475 4039",
    "sg:postcode":"13210",
    "sg:province":"NY",
    "wof:name":"Down Under Leather Inc",
    "wof:placetype":"venue"
},
  "geometry": {"coordinates":[-76.136718,43.03975],"type":"Point"}
}