{
  "type": "Feature",
  "properties": {
    "iso:country":"US",
    "sg:address":"1001 Stanley Ave",
    "sg:city":"Brooklyn",
    "sg:classifiers":[
        {
            "category":"Retail",
            "subcategory":"Auto Repair",
            "type":"Services"
        }
    ],
    "sg:phone":"+1 718 272 5970",
    "sg:postcode":"11208",
    "sg:province":"NY",
    "sg:tags":[
        "truck"
    ],
    "wof:name":"Americas Fleet Care",
    "wof:placetype":"venue"
},
  "geometry": {"coordinates":[-73.87267900000001,40.664219],"type":"Point"}
}