{
  "type": "Feature",
  "properties": {
    "addr:full":"51 E 25th St Fl 6 New York NY 10010",
    "addr:housenumber":"51;6",
    "addr:postcode":"10010",
    "addr:street":"E 25Th St",
    "iso:country":"US",
    "sg:address":"51 E 25th St Fl 6",
    "sg:city":"New York",
    "sg:classifiers":[
        {
            "category":"Health Services",
            "subcategory":"Doctor",
            "type":"Services"
        }
    ],
    "sg:phone":"+1 212 813 3199",
    "sg:postcode":"10010",
    "sg:province":"NY",
    "wof:name":"Kaisman Arden M Dr",
    "wof:placetype":"venue"
},
  "geometry": {"coordinates":[-73.985941,40.74172],"type":"Point"}
}