{
  "type": "Feature",
  "properties": {
    "addr:full":"1641 Bedford Ave Brooklyn NY 11225",
    "addr:housenumber":"1641",
    "addr:postcode":"11225",
    "addr:street":"Bedford Ave",
    "iso:country":"US",
    "sg:address":"1641 Bedford Ave",
    "sg:city":"Brooklyn",
    "sg:classifiers":[
        {
            "category":"Food & Beverages",
            "subcategory":"Bakery",
            "type":"Retail Goods"
        }
    ],
    "sg:phone":"+1 718 773 4960",
    "sg:postcode":"11225",
    "sg:province":"NY",
    "sg:tags":[
        "grocery"
    ],
    "wof:name":"Food Empire For Bakery Rstrnt",
    "wof:placetype":"venue"
},
  "geometry": {"coordinates":[-73.956771,40.665759],"type":"Point"}
}