{
  "type": "Feature",
  "properties": {
    "iso:country":"US",
    "sg:address":"120 New York Ave",
    "sg:city":"Huntington",
    "sg:classifiers":[
        {
            "category":"Health Services",
            "subcategory":"Doctor",
            "type":"Services"
        }
    ],
    "sg:phone":"+1 631 351 3766",
    "sg:postcode":"11743",
    "sg:province":"NY",
    "sg:tags":[
        "medical"
    ],
    "wof:name":"Donna M Schneider",
    "wof:placetype":"venue"
},
  "geometry": {"coordinates":[-73.41886,40.884088],"type":"Point"}
}