{
  "type": "Feature",
  "properties": {
    "addr:full":"8223 E Lake Rd Westfield NY 14787",
    "addr:housenumber":"8223",
    "addr:postcode":"14787",
    "addr:street":"E Lake Rd",
    "iso:country":"US",
    "sg:address":"8223 E Lake Rd",
    "sg:city":"Westfield",
    "sg:classifiers":[
        {
            "category":"Professional",
            "subcategory":"Business Services",
            "type":"Services"
        }
    ],
    "sg:phone":"+1   ",
    "sg:postcode":"14787",
    "sg:province":"NY",
    "sg:tags":[
        "hospitality"
    ],
    "wof:name":"Lakeside Bed and Breakfast",
    "wof:placetype":"venue"
},
  "geometry": {"coordinates":[-79.59512700000001,42.340677],"type":"Point"}
}