{
  "type": "Feature",
  "properties": {
    "addr:full":"534 Main St Westbury NY 11590",
    "addr:housenumber":"534",
    "addr:postcode":"11590",
    "addr:street":"Main St",
    "iso:country":"US",
    "sg:address":"534 Main St",
    "sg:city":"Westbury",
    "sg:classifiers":[
        {
            "category":"Wholesale",
            "subcategory":"Auto Parts",
            "type":"Manufacturing & Wholesale Goods"
        },
        {
            "category":"Wholesale",
            "subcategory":"Scrap",
            "type":"Manufacturing & Wholesale Goods"
        }
    ],
    "sg:phone":"+1 516 997 2842",
    "sg:postcode":"11590",
    "sg:province":"NY",
    "sg:tags":[
        "recycling",
        "center",
        "used"
    ],
    "wof:name":"Global Recycling",
    "wof:placetype":"venue"
},
  "geometry": {"coordinates":[-73.566562,40.756393],"type":"Point"}
}