{
  "type": "Feature",
  "properties": {
    "iso:country":"US",
    "sg:address":"1142 Mamaroneck Ave",
    "sg:city":"White Plains",
    "sg:classifiers":[
        {
            "category":"Building & Trades",
            "subcategory":"Construction",
            "type":"Services"
        }
    ],
    "sg:phone":"+1 914 328 3311",
    "sg:postcode":"10605",
    "sg:province":"NY",
    "sg:tags":[
        "handyman"
    ],
    "wof:name":"House Doctors Handyman Svc",
    "wof:placetype":"venue"
},
  "geometry": {"coordinates":[-73.746364,40.997071],"type":"Point"}
}