{
  "type": "Feature",
  "properties": {
    "addr:full":"160 5th Ave New York NY 10010",
    "addr:housenumber":"160",
    "addr:postcode":"10010",
    "addr:street":"5Th Ave",
    "iso:country":"US",
    "sg:address":"160 5th Ave",
    "sg:city":"New York",
    "sg:classifiers":[
        {
            "category":"Communications",
            "subcategory":"Newspaper",
            "type":"Services"
        }
    ],
    "sg:phone":"+1 212 620 7773",
    "sg:postcode":"10010",
    "sg:province":"NY",
    "sg:tags":[
        "print",
        "medium"
    ],
    "wof:name":"Digital One",
    "wof:placetype":"venue"
},
  "geometry": {"coordinates":[-73.99068800000001,40.740338],"type":"Point"}
}