{
  "type": "Feature",
  "properties": {
    "addr:full":"7905 3rd Ave Brooklyn NY 11209",
    "addr:housenumber":"7905",
    "addr:postcode":"11209",
    "addr:street":"3Rd Ave",
    "iso:country":"US",
    "sg:address":"7905 3rd Ave",
    "sg:city":"Brooklyn",
    "sg:classifiers":[
        {
            "category":"Shopping",
            "subcategory":"Computers & Home Electronics",
            "type":"Retail Goods"
        }
    ],
    "sg:phone":"+1 718 748 5232",
    "sg:postcode":"11209",
    "sg:province":"NY",
    "sg:tags":[
        "web",
        "design",
        "equipment"
    ],
    "wof:name":"East Coast Computers",
    "wof:placetype":"venue"
},
  "geometry": {"coordinates":[-74.02873200000001,40.628274],"type":"Point"}
}