{
  "type": "Feature",
  "properties": {
    "addr:full":"8 Hulse Rd East Setauket NY 11733",
    "addr:housenumber":"8",
    "addr:postcode":"11733",
    "addr:street":"Hulse Rd",
    "iso:country":"US",
    "sg:address":"8 Hulse Rd",
    "sg:city":"East Setauket",
    "sg:classifiers":[
        {
            "category":"Freight",
            "type":"Transportation"
        }
    ],
    "sg:phone":"+1 631 928 6843",
    "sg:postcode":"11733",
    "sg:province":"NY",
    "sg:tags":[
        "delivery"
    ],
    "wof:name":"Kay Delivieries Inc",
    "wof:placetype":"venue"
},
  "geometry": {"coordinates":[-73.081205,40.933704],"type":"Point"}
}