{
  "type": "Feature",
  "properties": {
    "addr:full":"580 Woodbury Rd Plainview NY 11803",
    "addr:housenumber":"580",
    "addr:postcode":"11803",
    "addr:street":"Woodbury Rd",
    "iso:country":"US",
    "sg:address":"580 Woodbury Rd",
    "sg:city":"Plainview",
    "sg:classifiers":[
        {
            "category":"Education",
            "subcategory":"School",
            "type":"Public Place"
        }
    ],
    "sg:phone":"+1 516 364 5798",
    "sg:postcode":"11803",
    "sg:province":"NY",
    "wof:name":"Baylis School",
    "wof:placetype":"venue"
},
  "geometry": {"coordinates":[-73.49365,40.790955],"type":"Point"}
}