{
  "type": "Feature",
  "properties": {
    "addr:full":"6014 Roosevelt Avenue Woodside NY 11377",
    "addr:housenumber":"6014",
    "addr:postcode":"11377",
    "addr:street":"Roosevelt Avenue",
    "iso:country":"US",
    "sg:address":"6014 Roosevelt Avenue",
    "sg:city":"Woodside",
    "sg:classifiers":[
        {
            "category":"Real Estate",
            "subcategory":"Real Estate Services",
            "type":"Services"
        },
        {
            "category":"Building & Trades",
            "subcategory":"Pest Control",
            "type":"Services"
        }
    ],
    "sg:phone":"+1 718 672 6453",
    "sg:postcode":"11377",
    "sg:province":"NY",
    "sg:tags":[
        "home",
        "inspector"
    ],
    "wof:name":"Iit Services",
    "wof:placetype":"venue"
},
  "geometry": {"coordinates":[-73.90386599999999,40.745431],"type":"Point"}
}