{
  "type": "Feature",
  "properties": {
    "addr:full":"850 Co Rte 25 Oswego NY 13126",
    "addr:housenumber":"850",
    "addr:postcode":"13126",
    "addr:street":"Co Rte 25",
    "iso:country":"US",
    "sg:address":"850 Co Rte 25",
    "sg:city":"Oswego",
    "sg:classifiers":[
        {
            "category":"Personal",
            "subcategory":"Beauty Salon",
            "type":"Services"
        }
    ],
    "sg:phone":"+1 315 343 5100",
    "sg:postcode":"13126",
    "sg:province":"NY",
    "wof:name":"A Hair View",
    "wof:placetype":"venue"
},
  "geometry": {"coordinates":[-76.502371,43.410713],"type":"Point"}
}