{
  "type": "Feature",
  "properties": {
    "iso:country":"US",
    "sg:address":"34 Cross Ridge Rd",
    "sg:city":"Chappaqua",
    "sg:classifiers":[
        {
            "category":"Professional",
            "type":"Services"
        }
    ],
    "sg:phone":"+1 914 238 0813",
    "sg:postcode":"10514",
    "sg:province":"NY",
    "sg:tags":[
        "establishment"
    ],
    "wof:name":"Calba Corp",
    "wof:placetype":"venue"
},
  "geometry": {"coordinates":[-73.77243799999999,41.177969],"type":"Point"}
}