{
  "type": "Feature",
  "properties": {
    "addr:full":"501 Day Hollow Rd Endicott NY 13760",
    "addr:housenumber":"501",
    "addr:postcode":"13760",
    "addr:street":"Day Hollow Rd",
    "iso:country":"US",
    "sg:address":"501 Day Hollow Rd",
    "sg:city":"Endicott",
    "sg:classifiers":[
        {
            "category":"Retail",
            "subcategory":"Auto Repair",
            "type":"Services"
        }
    ],
    "sg:phone":"+1 607 748 5351",
    "sg:postcode":"13760",
    "sg:province":"NY",
    "sg:tags":[
        "general"
    ],
    "wof:name":"Tim Voorhees Auto Repair",
    "wof:placetype":"venue"
},
  "geometry": {"coordinates":[-76.074348,42.111599],"type":"Point"}
}