{
  "type": "Feature",
  "properties": {
    "addr:full":"37 Lambert Rd New Canaan NY 06840",
    "addr:housenumber":"37",
    "addr:postcode":"06840",
    "addr:street":"Lambert Rd",
    "iso:country":"US",
    "sg:address":"37 Lambert Rd",
    "sg:city":"New Canaan",
    "sg:classifiers":[
        {
            "category":"Real Estate",
            "subcategory":"Real Estate Agent",
            "type":"Services"
        }
    ],
    "sg:phone":"+1 203 966 3400",
    "sg:postcode":"06840",
    "sg:province":"NY",
    "wof:name":"HRA Realty Advisors",
    "wof:placetype":"venue"
},
  "geometry": {"coordinates":[-73.503596,41.164131],"type":"Point"}
}