{
  "type": "Feature",
  "properties": {
    "addr:full":"210 Forest Dr Greenvale NY 11548",
    "addr:housenumber":"210",
    "addr:postcode":"11548",
    "addr:street":"Forest Dr",
    "iso:country":"US",
    "sg:address":"210 Forest Dr",
    "sg:city":"Greenvale",
    "sg:classifiers":[
        {
            "category":"Wholesale",
            "subcategory":"Groceries",
            "type":"Manufacturing & Wholesale Goods"
        }
    ],
    "sg:phone":"+1 516 626 3500",
    "sg:postcode":"11548",
    "sg:province":"NY",
    "sg:tags":[
        "food",
        "product"
    ],
    "wof:name":"D & J Health Food Distr Inc",
    "wof:placetype":"venue"
},
  "geometry": {"coordinates":[-73.63403,40.80735],"type":"Point"}
}