{
  "type": "Feature",
  "properties": {
    "iso:country":"US",
    "sg:address":"395 S Youngs Rd",
    "sg:city":"Buffalo",
    "sg:classifiers":[
        {
            "category":"Professional",
            "subcategory":"Business Services",
            "type":"Services"
        }
    ],
    "sg:phone":"+1 716 633 3463",
    "sg:postcode":"14221",
    "sg:province":"NY",
    "sg:tags":[
        "consultant",
        "coach"
    ],
    "sg:website":"http://www.cognigencorp.com",
    "wof:name":"Cognigen Corporation",
    "wof:placetype":"venue"
},
  "geometry": {"coordinates":[-78.7247,42.954252],"type":"Point"}
}