{
  "type": "Feature",
  "properties": {
    "iso:country":"US",
    "sg:address":"2876 State Hwy 11B",
    "sg:city":"Nicholville",
    "sg:classifiers":[
        {
            "category":"Government",
            "subcategory":"Fire Station",
            "type":"Public Place"
        }
    ],
    "sg:phone":"+1 315 328 4682",
    "sg:postcode":"12965",
    "sg:province":"NY",
    "sg:tags":[
        "department",
        "volunteer"
    ],
    "wof:name":"Hopkinton-Ft Jackson Vfd",
    "wof:placetype":"venue"
},
  "geometry": {"coordinates":[-74.695719,44.690587],"type":"Point"}
}