{
  "type": "Feature",
  "properties": {
    "iso:country":"US",
    "sg:address":"656 S Wellwood Ave",
    "sg:city":"Lindenhurst",
    "sg:classifiers":[
        {
            "category":"Shopping",
            "subcategory":"Beauty & Cosmetics",
            "type":"Retail Goods"
        }
    ],
    "sg:phone":"+1 631 225 6565",
    "sg:postcode":"11757",
    "sg:province":"NY",
    "sg:tags":[
        "establishment",
        "merchandise"
    ],
    "wof:name":"Sally Beauty Supply",
    "wof:placetype":"venue"
},
  "geometry": {"coordinates":[-73.36301899999999,40.676711],"type":"Point"}
}