{
  "type": "Feature",
  "properties": {
    "addr:full":"33 Baldwin Blvd Bayville NY 11709",
    "addr:housenumber":"33",
    "addr:postcode":"11709",
    "addr:street":"Baldwin Blvd",
    "iso:country":"US",
    "sg:address":"33 Baldwin Blvd",
    "sg:city":"Bayville",
    "sg:classifiers":[
        {
            "category":"Building & Trades",
            "subcategory":"Landscaping Services",
            "type":"Services"
        }
    ],
    "sg:phone":"+1 516 628 2469",
    "sg:postcode":"11709",
    "sg:province":"NY",
    "sg:tags":[
        "consultant",
        "designer",
        "landscape"
    ],
    "wof:name":"Pete Huysman Landscaping",
    "wof:placetype":"venue"
},
  "geometry": {"coordinates":[-73.57100699999999,40.90955],"type":"Point"}
}