{
  "type": "Feature",
  "properties": {
    "iso:country":"US",
    "sg:address":"245 W 38th St",
    "sg:city":"New York",
    "sg:classifiers":[
        {
            "category":"Restaurant",
            "type":"Food & Drink"
        }
    ],
    "sg:phone":"+1   ",
    "sg:postcode":"10018",
    "sg:province":"NY",
    "sg:tags":[
        "eating"
    ],
    "wof:name":"Ggfb Inc",
    "wof:placetype":"venue"
},
  "geometry": {"coordinates":[-73.990629,40.754237],"type":"Point"}
}