{
  "type": "Feature",
  "properties": {
    "iso:country":"US",
    "sg:address":"3103 Fairfield Ave",
    "sg:city":"Bronx",
    "sg:classifiers":[
        {
            "category":"Professional",
            "subcategory":"Art Services",
            "type":"Services"
        }
    ],
    "sg:phone":"+1 718 796 0303",
    "sg:postcode":"10463",
    "sg:province":"NY",
    "sg:tags":[
        "photographer"
    ],
    "wof:name":"Phil Mansfield Photography",
    "wof:placetype":"venue"
},
  "geometry": {"coordinates":[-73.91381699999999,40.884322],"type":"Point"}
}