{
  "type": "Feature",
  "properties": {
    "addr:full":"8778A Sutphin Boulevard Jamaica NY 11435",
    "addr:housenumber":"8778a",
    "addr:postcode":"11435",
    "addr:street":"Sutphin Boulevard",
    "iso:country":"US",
    "sg:address":"8778A Sutphin Boulevard",
    "sg:city":"Jamaica",
    "sg:classifiers":[
        {
            "category":"Personal",
            "subcategory":"Nail Salon",
            "type":"Services"
        }
    ],
    "sg:phone":"+1 718 206 1380",
    "sg:postcode":"11435",
    "sg:province":"NY",
    "wof:name":"New Sky Nails",
    "wof:placetype":"venue"
},
  "geometry": {"coordinates":[-73.80946,40.70493],"type":"Point"}
}