{
  "type": "Feature",
  "properties": {
    "addr:full":"1137 Myrtle Ave Brooklyn NY 11206",
    "addr:housenumber":"1137",
    "addr:postcode":"11206",
    "addr:street":"Myrtle Ave",
    "iso:country":"US",
    "sg:address":"1137 Myrtle Ave",
    "sg:city":"Brooklyn",
    "sg:classifiers":[
        {
            "category":"Utilities",
            "subcategory":"Cable",
            "type":"Services"
        }
    ],
    "sg:phone":"+1 718 835 8042",
    "sg:postcode":"11206",
    "sg:province":"NY",
    "sg:tags":[
        "satellite"
    ],
    "wof:name":"Satellite Systems USA Inc",
    "wof:placetype":"venue"
},
  "geometry": {"coordinates":[-73.936758,40.696828],"type":"Point"}
}