{
  "type": "Feature",
  "properties": {
    "iso:country":"US",
    "sg:address":"4603 Middle Country Rd",
    "sg:city":"Calverton",
    "sg:classifiers":[
        {
            "category":"Health Services",
            "subcategory":"Doctor",
            "type":"Services"
        }
    ],
    "sg:phone":"+1 631 591 1278",
    "sg:postcode":"11933",
    "sg:province":"NY",
    "wof:name":"Applied Phys",
    "wof:placetype":"venue"
},
  "geometry": {"coordinates":[-72.78937000000001,40.927715],"type":"Point"}
}