{
  "type": "Feature",
  "properties": {
    "iso:country":"US",
    "sg:address":"401 Herkimer Rd",
    "sg:city":"Utica",
    "sg:classifiers":[
        {
            "category":"Freight",
            "type":"Transportation"
        }
    ],
    "sg:phone":"+1   ",
    "sg:postcode":"13502",
    "sg:province":"NY",
    "sg:tags":[
        "product",
        "petroleum",
        "special"
    ],
    "wof:name":"Herkimer Petroleum Storage",
    "wof:placetype":"venue"
},
  "geometry": {"coordinates":[-75.202961,43.114135],"type":"Point"}
}