{
  "type": "Feature",
  "properties": {
    "addr:full":"37 E 29th St New York NY 10016",
    "addr:housenumber":"37",
    "addr:postcode":"10016",
    "addr:street":"E 29Th St",
    "iso:country":"US",
    "sg:address":"37 E 29th St",
    "sg:city":"New York",
    "sg:classifiers":[
        {
            "category":"Restaurant",
            "type":"Food & Drink"
        }
    ],
    "sg:phone":"+1 212 686 9691",
    "sg:postcode":"10016",
    "sg:province":"NY",
    "wof:name":"Green House",
    "wof:placetype":"venue"
},
  "geometry": {"coordinates":[-73.983761,40.744105],"type":"Point"}
}