{
  "type": "Feature",
  "properties": {
    "addr:full":"190 Ogden Center Rd Spencerport NY 14559",
    "addr:housenumber":"190",
    "addr:postcode":"14559",
    "addr:street":"Ogden Center Rd",
    "iso:country":"US",
    "sg:address":"190 Ogden Center Rd",
    "sg:city":"Spencerport",
    "sg:classifiers":[
        {
            "category":"Building & Trades",
            "subcategory":"Construction",
            "type":"Services"
        }
    ],
    "sg:phone":"+1 585 352 7105",
    "sg:postcode":"14559",
    "sg:province":"NY",
    "sg:tags":[
        "restoration",
        "cleaning",
        "patio",
        "deck"
    ],
    "wof:name":"Eraser's Mobile Powerwash",
    "wof:placetype":"venue"
},
  "geometry": {"coordinates":[-77.790603,43.172189],"type":"Point"}
}