{
  "type": "Feature",
  "properties": {
    "addr:full":"36 Parkwood Dr Albany NY 12205",
    "addr:housenumber":"36",
    "addr:postcode":"12205",
    "addr:street":"Parkwood Dr",
    "iso:country":"US",
    "sg:address":"36 Parkwood Dr",
    "sg:city":"Albany",
    "sg:classifiers":[
        {
            "category":"Manufacturing",
            "subcategory":"Tools & Machinery",
            "type":"Manufacturing & Wholesale Goods"
        }
    ],
    "sg:phone":"+1 518 452 0317",
    "sg:postcode":"12205",
    "sg:province":"NY",
    "sg:tags":[
        "cleaners",
        "household",
        "vacuum"
    ],
    "wof:name":"Ron Lewis Vacuum",
    "wof:placetype":"venue"
},
  "geometry": {"coordinates":[-73.82604499999999,42.718155],"type":"Point"}
}