{
  "type": "Feature",
  "properties": {
    "addr:full":"250 E 40th St New York NY 10016",
    "addr:housenumber":"250",
    "addr:postcode":"10016",
    "addr:street":"E 40Th St",
    "iso:country":"US",
    "sg:address":"250 E 40th St",
    "sg:city":"New York",
    "sg:classifiers":[
        {
            "category":"Professional",
            "subcategory":"Management & Consulting",
            "type":"Services"
        }
    ],
    "sg:phone":"+1 212 681 8949",
    "sg:postcode":"10016",
    "sg:province":"NY",
    "sg:tags":[
        "consultant"
    ],
    "wof:name":"Bach Consulting",
    "wof:placetype":"venue"
},
  "geometry": {"coordinates":[-73.97335699999999,40.748572],"type":"Point"}
}