{
  "type": "Feature",
  "properties": {
    "addr:full":"76 Keswick Ln Plainview NY 11803",
    "addr:housenumber":"76",
    "addr:postcode":"11803",
    "addr:street":"Keswick Ln",
    "iso:country":"US",
    "sg:address":"76 Keswick Ln",
    "sg:city":"Plainview",
    "sg:classifiers":[
        {
            "category":"Building & Trades",
            "subcategory":"Construction",
            "type":"Services"
        }
    ],
    "sg:phone":"+1 516 938 2852",
    "sg:postcode":"11803",
    "sg:province":"NY",
    "sg:tags":[
        "drywall",
        "contractor"
    ],
    "wof:name":"Tlc Drywall & Construction Inc",
    "wof:placetype":"venue"
},
  "geometry": {"coordinates":[-73.482286,40.768697],"type":"Point"}
}