{
  "type": "Feature",
  "properties": {
    "addr:full":"504 E 118th St Apt 1- B Manhattan NY 10035",
    "addr:housenumber":"504;1 b",
    "addr:postcode":"10035",
    "addr:street":"E 118Th St Apt",
    "iso:country":"US",
    "sg:address":"504 E 118th St Apt 1- B",
    "sg:city":"Manhattan",
    "sg:classifiers":[
        {
            "category":"Personal",
            "subcategory":"Beauty Salon",
            "type":"Services"
        },
        {
            "category":"Personal",
            "subcategory":"Barber",
            "type":"Services"
        }
    ],
    "sg:phone":"+1 646 549 7473",
    "sg:postcode":"10035",
    "sg:province":"NY",
    "sg:tags":[
        "hair"
    ],
    "sg:website":"www.makemystylehairsalon.com",
    "wof:name":"Make My Style Hair Salon",
    "wof:placetype":"venue"
},
  "geometry": {"coordinates":[-73.932091,40.796294],"type":"Point"}
}