{
  "type": "Feature",
  "properties": {
    "addr:full":"5 Etna Ln Huntington Station NY 11746",
    "addr:housenumber":"5",
    "addr:postcode":"11746",
    "addr:street":"Etna Ln Huntington",
    "iso:country":"US",
    "sg:address":"5 Etna Ln",
    "sg:city":"Huntington Station",
    "sg:classifiers":[
        {
            "category":"Professional",
            "subcategory":"Management & Consulting",
            "type":"Services"
        }
    ],
    "sg:phone":"+1   ",
    "sg:postcode":"11746",
    "sg:province":"NY",
    "sg:tags":[
        "control",
        "product",
        "sales",
        "crowd",
        "system"
    ],
    "wof:name":"Twin Discovery Systems Inc",
    "wof:placetype":"venue"
},
  "geometry": {"coordinates":[-73.367085,40.798319],"type":"Point"}
}