{
  "type": "Feature",
  "properties": {
    "iso:country":"US",
    "sg:address":"179 Taghkanic Rd",
    "sg:city":"Elizaville",
    "sg:classifiers":[
        {
            "category":"Recreation",
            "type":"Entertainment"
        }
    ],
    "sg:phone":"+1 518 537 6579",
    "sg:postcode":"12523",
    "sg:province":"NY",
    "sg:tags":[
        "instruction",
        "yoga"
    ],
    "wof:name":"Yoga For Health",
    "wof:placetype":"venue"
},
  "geometry": {"coordinates":[-73.760762,42.098597],"type":"Point"}
}