{
  "type": "Feature",
  "properties": {
    "addr:full":"292 Red Apple Ct Central Valley NY 10917",
    "addr:housenumber":"292",
    "addr:postcode":"10917",
    "addr:street":"Red Apple Ct",
    "iso:country":"US",
    "sg:address":"292 Red Apple Ct",
    "sg:city":"Central Valley",
    "sg:classifiers":[
        {
            "category":"Shopping",
            "type":"Retail Goods"
        }
    ],
    "sg:phone":"+1 845 928 7973",
    "sg:postcode":"10917",
    "sg:province":"NY",
    "sg:tags":[
        "factory",
        "outlet"
    ],
    "wof:name":"Lacoste & Paris Collections",
    "wof:placetype":"venue"
},
  "geometry": {"coordinates":[-74.126417,41.315257],"type":"Point"}
}