{
  "type": "Feature",
  "properties": {
    "iso:country":"US",
    "sg:address":"1014 Lafayette Ave",
    "sg:city":"Brooklyn",
    "sg:classifiers":[
        {
            "category":"Travel",
            "subcategory":"Campground",
            "type":"Entertainment"
        }
    ],
    "sg:phone":"+1 718 602 6082",
    "sg:postcode":"11221",
    "sg:province":"NY",
    "sg:tags":[
        "camp"
    ],
    "wof:name":"Clear Pool Camp",
    "wof:placetype":"venue"
},
  "geometry": {"coordinates":[-73.932698,40.691882],"type":"Point"}
}