{
  "type": "Feature",
  "properties": {
    "addr:full":"224 Milton Ave Ballston Spa NY 12020",
    "addr:housenumber":"224",
    "addr:postcode":"12020",
    "addr:street":"Milton Ave",
    "iso:country":"US",
    "sg:address":"224 Milton Ave",
    "sg:city":"Ballston Spa",
    "sg:classifiers":[
        {
            "category":"Retail",
            "subcategory":"Funeral Services",
            "type":"Services"
        }
    ],
    "sg:phone":"+1   ",
    "sg:postcode":"12020",
    "sg:province":"NY",
    "sg:tags":[
        "home"
    ],
    "wof:name":"Mevec Funeral Home Inc",
    "wof:placetype":"venue"
},
  "geometry": {"coordinates":[-73.849542,43.007799],"type":"Point"}
}