{
  "type": "Feature",
  "properties": {
    "addr:full":"448 Central Park W New York NY 10025",
    "addr:housenumber":"448",
    "addr:postcode":"10025",
    "addr:street":"Central Park W",
    "iso:country":"US",
    "sg:address":"448 Central Park W",
    "sg:city":"New York",
    "sg:classifiers":[
        {
            "category":"Personal",
            "subcategory":"Beauty Salon",
            "type":"Services"
        }
    ],
    "sg:phone":"+1 212 932 1940",
    "sg:postcode":"10025",
    "sg:province":"NY",
    "sg:tags":[
        "treatment",
        "skin"
    ],
    "wof:name":"E Harcourts",
    "wof:placetype":"venue"
},
  "geometry": {"coordinates":[-73.96097899999999,40.796738],"type":"Point"}
}