{
  "type": "Feature",
  "properties": {
    "addr:full":"3226 Fish Ave Bronx NY 10469",
    "addr:housenumber":"3226",
    "addr:postcode":"10469",
    "addr:street":"Fish Ave",
    "iso:country":"US",
    "sg:address":"3226 Fish Ave",
    "sg:city":"Bronx",
    "sg:classifiers":[
        {
            "category":"Professional",
            "subcategory":"Management & Consulting",
            "type":"Services"
        }
    ],
    "sg:phone":"+1 718 653 3672",
    "sg:postcode":"10469",
    "sg:province":"NY",
    "sg:tags":[
        "consultant",
        "educational"
    ],
    "wof:name":"J Gay Educational Consultant",
    "wof:placetype":"venue"
},
  "geometry": {"coordinates":[-73.84841,40.873198],"type":"Point"}
}