{
  "type": "Feature",
  "properties": {
    "addr:full":"204 Twomey Rd West Winfield NY 13491",
    "addr:housenumber":"204",
    "addr:postcode":"13491",
    "addr:street":"Twomey Rd",
    "iso:country":"US",
    "sg:address":"204 Twomey Rd",
    "sg:city":"West Winfield",
    "sg:classifiers":[
        {
            "category":"Farming",
            "subcategory":"Livestock Farm",
            "type":"Manufacturing & Wholesale Goods"
        }
    ],
    "sg:phone":"+1 315 822 3841",
    "sg:postcode":"13491",
    "sg:province":"NY",
    "sg:tags":[
        "beef",
        "feedlot",
        "cattle"
    ],
    "wof:name":"Hidden Valley Horseback Advent",
    "wof:placetype":"venue"
},
  "geometry": {"coordinates":[-75.16448699999999,42.878051],"type":"Point"}
}