{
  "type": "Feature",
  "properties": {
    "iso:country":"US",
    "sg:address":"309 Weidner Ave",
    "sg:city":"Oceanside",
    "sg:classifiers":[
        {
            "category":"Communications",
            "type":"Services"
        }
    ],
    "sg:phone":"+1   ",
    "sg:postcode":"11572",
    "sg:province":"NY",
    "sg:tags":[
        "communication"
    ],
    "wof:name":"Imagine Media Inc",
    "wof:placetype":"venue"
},
  "geometry": {"coordinates":[-73.650462,40.634067],"type":"Point"}
}