{
  "type": "Feature",
  "properties": {
    "iso:country":"US",
    "sg:address":"720 Old Country Rd",
    "sg:city":"Plainview",
    "sg:classifiers":[
        {
            "category":"Health Services",
            "subcategory":"Doctor",
            "type":"Services"
        }
    ],
    "sg:phone":"+1 516 931 1133",
    "sg:postcode":"11803",
    "sg:province":"NY",
    "sg:tags":[
        "physician",
        "surgeon"
    ],
    "wof:name":"Comprehensive Pain Management",
    "wof:placetype":"venue"
},
  "geometry": {"coordinates":[-73.48899299999999,40.772277],"type":"Point"}
}