{
  "type": "Feature",
  "properties": {
    "addr:full":"61 Cedar Ln Ossining NY 10562",
    "addr:housenumber":"61",
    "addr:postcode":"10562",
    "addr:street":"Cedar Ln",
    "iso:country":"US",
    "sg:address":"61 Cedar Ln",
    "sg:city":"Ossining",
    "sg:classifiers":[
        {
            "category":"Organizations",
            "subcategory":"Professional Association",
            "type":"Services"
        }
    ],
    "sg:phone":"+1   ",
    "sg:postcode":"10562",
    "sg:province":"NY",
    "sg:tags":[
        "business"
    ],
    "wof:name":"Knights of Columbus 0311",
    "wof:placetype":"venue"
},
  "geometry": {"coordinates":[-73.864864,41.176106],"type":"Point"}
}