{
  "type": "Feature",
  "properties": {
    "addr:full":"Penn Plaza 250 W 34th St New York NY 10079",
    "addr:housenumber":"250",
    "addr:postcode":"10079",
    "addr:street":"Penn;W 34Th St",
    "iso:country":"US",
    "sg:address":"Penn Plaza 250 W 34th St",
    "sg:city":"New York",
    "sg:classifiers":[
        {
            "category":"Shopping",
            "subcategory":"Shoes",
            "type":"Retail Goods"
        }
    ],
    "sg:phone":"+1 212 244 4810",
    "sg:postcode":"10079",
    "sg:province":"NY",
    "sg:tags":[
        "store"
    ],
    "sg:website":"famousfootwear.com",
    "wof:name":"Famous Footwear",
    "wof:placetype":"venue"
},
  "geometry": {"coordinates":[-73.992633,40.751843],"type":"Point"}
}