{
  "type": "Feature",
  "properties": {
    "addr:full":"1078 1st Ave New York NY 10022",
    "addr:housenumber":"1078",
    "addr:postcode":"10022",
    "addr:street":"1St Ave",
    "iso:country":"US",
    "sg:address":"1078 1st Ave",
    "sg:city":"New York",
    "sg:classifiers":[
        {
            "category":"Bars & Pubs",
            "type":"Food & Drink"
        }
    ],
    "sg:phone":"+1 212 421 8282",
    "sg:postcode":"10022",
    "sg:province":"NY",
    "sg:tags":[
        "tapa"
    ],
    "wof:name":"Tapas Lounge",
    "wof:placetype":"venue"
},
  "geometry": {"coordinates":[-73.961949,40.759635],"type":"Point"}
}