{
  "type": "Feature",
  "properties": {
    "addr:full":"6278 Empire Ave Schenectady NY 12306",
    "addr:housenumber":"6278",
    "addr:postcode":"12306",
    "addr:street":"Empire Ave",
    "iso:country":"US",
    "sg:address":"6278 Empire Ave",
    "sg:city":"Schenectady",
    "sg:classifiers":[
        {
            "category":"Professional",
            "subcategory":"Accounting & Tax Preparation",
            "type":"Services"
        }
    ],
    "sg:phone":"+1 518 437 0430",
    "sg:postcode":"12306",
    "sg:province":"NY",
    "sg:tags":[
        "accountant"
    ],
    "wof:name":"Dean M Gent CPA Residence",
    "wof:placetype":"venue"
},
  "geometry": {"coordinates":[-73.95505900000001,42.746011],"type":"Point"}
}