{
  "type": "Feature",
  "properties": {
    "addr:full":"141 Matthews St Binghamton NY 13905",
    "addr:housenumber":"141",
    "addr:postcode":"13905",
    "addr:street":"Matthews St",
    "iso:country":"US",
    "sg:address":"141 Matthews St",
    "sg:city":"Binghamton",
    "sg:classifiers":[
        {
            "category":"Shopping",
            "subcategory":"Catalog Store",
            "type":"Retail Goods"
        }
    ],
    "sg:phone":"+1   ",
    "sg:postcode":"13905",
    "sg:province":"NY",
    "sg:tags":[
        "mail",
        "house"
    ],
    "wof:name":"Ondrejko Corp",
    "wof:placetype":"venue"
},
  "geometry": {"coordinates":[-75.943164,42.10439],"type":"Point"}
}