{
  "type": "Feature",
  "properties": {
    "iso:country":"US",
    "sg:address":"6410 108th St",
    "sg:city":"Forest Hills",
    "sg:classifiers":[
        {
            "category":"Shopping",
            "subcategory":"Discount & Variety Stores",
            "type":"Retail Goods"
        }
    ],
    "sg:phone":"+1 718 830 3889",
    "sg:postcode":"11375",
    "sg:province":"NY",
    "wof:name":"Ix Ming 99 Cents City",
    "wof:placetype":"venue"
},
  "geometry": {"coordinates":[-73.84939900000001,40.732493],"type":"Point"}
}