{
  "type": "Feature",
  "properties": {
    "iso:country":"US",
    "sg:address":"1 Worth St",
    "sg:city":"New York",
    "sg:classifiers":[
        {
            "category":"Communications",
            "subcategory":"Film & Video Production",
            "type":"Services"
        }
    ],
    "sg:phone":"+1 212 941 9494",
    "sg:postcode":"10013",
    "sg:province":"NY",
    "sg:tags":[
        "rental",
        "equipment",
        "industry",
        "lighting",
        "for"
    ],
    "wof:name":"Xeno Lights Inc",
    "wof:placetype":"venue"
},
  "geometry": {"coordinates":[-74.007536,40.717661],"type":"Point"}
}