{
  "type": "Feature",
  "properties": {
    "addr:full":"45 Vantage Point Dr Rochester NY 14624",
    "addr:housenumber":"45",
    "addr:postcode":"14624",
    "addr:street":"Vantage Point Dr",
    "iso:country":"US",
    "sg:address":"45 Vantage Point Dr",
    "sg:city":"Rochester",
    "sg:classifiers":[
        {
            "category":"Wholesale",
            "subcategory":"Medical Equipment & Supplies",
            "type":"Manufacturing & Wholesale Goods"
        }
    ],
    "sg:phone":"+1 585 352 7060",
    "sg:postcode":"14624",
    "sg:province":"NY",
    "wof:name":"McKesson",
    "wof:placetype":"venue"
},
  "geometry": {"coordinates":[-77.758709,43.155926],"type":"Point"}
}