{
  "type": "Feature",
  "properties": {
    "iso:country":"US",
    "sg:address":"2007 Genesee St",
    "sg:city":"Utica",
    "sg:classifiers":[
        {
            "category":"Personal",
            "subcategory":"Tanning Parlor",
            "type":"Services"
        }
    ],
    "sg:phone":"+1 315 733 0837",
    "sg:postcode":"13501",
    "sg:province":"NY",
    "sg:tags":[
        "salon"
    ],
    "wof:name":"Bare It All Tanning Salon",
    "wof:placetype":"venue"
},
  "geometry": {"coordinates":[-75.26130000000001,43.086594],"type":"Point"}
}