{
  "type": "Feature",
  "properties": {
    "iso:country":"US",
    "sg:address":"125 Bronson Rd",
    "sg:city":"Syracuse",
    "sg:classifiers":[
        {
            "category":"Manufacturing",
            "subcategory":"Tools & Machinery",
            "type":"Manufacturing & Wholesale Goods"
        }
    ],
    "sg:phone":"+1   ",
    "sg:postcode":"13219",
    "sg:province":"NY",
    "sg:tags":[
        "security",
        "system",
        "mfg"
    ],
    "sg:website":"www.sensormatic.com",
    "wof:name":"Sensormatic Electronics Corp",
    "wof:placetype":"venue"
},
  "geometry": {"coordinates":[-76.218458,43.04506],"type":"Point"}
}