{
  "type": "Feature",
  "properties": {
    "addr:full":"133 Wall St Ste 3 Schenectady NY 12305",
    "addr:housenumber":"133",
    "addr:postcode":"12305",
    "addr:street":"Wall St Ste 3",
    "iso:country":"US",
    "sg:address":"133 Wall St Ste 3",
    "sg:city":"Schenectady",
    "sg:classifiers":[
        {
            "category":"Professional",
            "subcategory":"Accounting & Tax Preparation",
            "type":"Services"
        },
        {
            "category":"Banks & Credit Unions",
            "subcategory":"Financial Services",
            "type":"Services"
        }
    ],
    "sg:phone":"+1 518 377 6448",
    "sg:postcode":"12305",
    "sg:province":"NY",
    "sg:tags":[
        "return",
        "preparation-business",
        "taxes-consultants",
        "loan",
        "reporting",
        "representative",
        "alternative",
        "bookkeeping"
    ],
    "sg:website":"http://www.hrblock.com",
    "wof:name":"H&R Block",
    "wof:placetype":"venue"
},
  "geometry": {"coordinates":[-73.943504,42.814458],"type":"Point"}
}