{
  "type": "Feature",
  "properties": {
    "addr:full":"875 Horseblock Rd Farmingville NY 11738",
    "addr:housenumber":"875",
    "addr:postcode":"11738",
    "addr:street":"Horseblock Rd",
    "iso:country":"US",
    "sg:address":"875 Horseblock Rd",
    "sg:city":"Farmingville",
    "sg:classifiers":[
        {
            "category":"Professional",
            "type":"Services"
        }
    ],
    "sg:phone":"+1 631 732 6271",
    "sg:postcode":"11738",
    "sg:province":"NY",
    "sg:tags":[
        "establishment"
    ],
    "wof:name":"Pelliccia & Pelliccia",
    "wof:placetype":"venue"
},
  "geometry": {"coordinates":[-73.021911,40.830305],"type":"Point"}
}