{
  "type": "Feature",
  "properties": {
    "iso:country":"US",
    "sg:address":"399 Montauk Hwy",
    "sg:city":"Sayville",
    "sg:classifiers":[
        {
            "category":"Retail",
            "subcategory":"Laundry & Dry Cleaning",
            "type":"Services"
        }
    ],
    "sg:phone":"+1 631 589 7004",
    "sg:postcode":"11782",
    "sg:province":"NY",
    "sg:tags":[
        "cleaners"
    ],
    "wof:name":"Alessandra Cleaners",
    "wof:placetype":"venue"
},
  "geometry": {"coordinates":[-73.072163,40.74525],"type":"Point"}
}