{
  "type": "Feature",
  "properties": {
    "iso:country":"US",
    "sg:address":"60 Commerce Dr",
    "sg:city":"Rochester",
    "sg:classifiers":[
        {
            "category":"Manufacturing",
            "subcategory":"Tools & Machinery",
            "type":"Manufacturing & Wholesale Goods"
        }
    ],
    "sg:phone":"+1   ",
    "sg:postcode":"14623",
    "sg:province":"NY",
    "sg:tags":[
        "measuring",
        "instrument",
        "electric",
        "mfg"
    ],
    "wof:name":"S C J Associates Inc",
    "wof:placetype":"venue"
},
  "geometry": {"coordinates":[-77.648949,43.080852],"type":"Point"}
}