{
  "type": "Feature",
  "properties": {
    "addr:full":"325 Madison Ave New York NY 10017",
    "addr:housenumber":"325",
    "addr:postcode":"10017",
    "addr:street":"Madison Ave",
    "iso:country":"US",
    "sg:address":"325 Madison Ave",
    "sg:city":"New York",
    "sg:classifiers":[
        {
            "category":"Retail",
            "subcategory":"Repair Shop",
            "type":"Services"
        }
    ],
    "sg:phone":"+1 212 632 7291",
    "sg:postcode":"10017",
    "sg:province":"NY",
    "sg:tags":[
        "lock",
        "locksmith"
    ],
    "wof:name":"24 All Day Emergency Locksmith",
    "wof:placetype":"venue"
},
  "geometry": {"coordinates":[-73.978936,40.753056],"type":"Point"}
}