{
  "type": "Feature",
  "properties": {
    "addr:full":"102 W 116th St Ste A12 Manhattan NY 10026",
    "addr:housenumber":"102",
    "addr:postcode":"10026",
    "addr:street":"W 116Th St Ste A12",
    "iso:country":"US",
    "sg:address":"102 W 116th St Ste A12",
    "sg:city":"Manhattan",
    "sg:classifiers":[
        {
            "category":"Building & Trades",
            "subcategory":"Locksmith",
            "type":"Services"
        }
    ],
    "sg:phone":"+1 347 226 5968",
    "sg:postcode":"10026",
    "sg:province":"NY",
    "sg:tags":[
        "key"
    ],
    "sg:website":"certifiedlocksmithny.com/",
    "wof:name":"Certified Locks, Keys, & Security",
    "wof:placetype":"venue"
},
  "geometry": {"coordinates":[-73.949826,40.802065],"type":"Point"}
}