{
  "type": "Feature",
  "properties": {
    "addr:full":"46 W 45 St New York NY 10036",
    "addr:housenumber":"46",
    "addr:postcode":"10036",
    "addr:street":"W 45 St",
    "iso:country":"US",
    "sg:address":"46 W 45 St",
    "sg:city":"New York",
    "sg:classifiers":[
        {
            "category":"Manufacturing",
            "subcategory":"Jewelry",
            "type":"Manufacturing & Wholesale Goods"
        }
    ],
    "sg:phone":"+1   ",
    "sg:postcode":"10036",
    "sg:province":"NY",
    "sg:tags":[
        "precious",
        "metal",
        "mfg"
    ],
    "wof:name":"Essence Jewelry",
    "wof:placetype":"venue"
},
  "geometry": {"coordinates":[-73.981627,40.756079],"type":"Point"}
}