{
  "type": "Feature",
  "properties": {
    "addr:full":"1661 State Rte 104 Ontario NY 14519",
    "addr:housenumber":"1661",
    "addr:postcode":"14519",
    "addr:street":"State Rte 104",
    "iso:country":"US",
    "sg:address":"1661 State Rte 104",
    "sg:city":"Ontario",
    "sg:classifiers":[
        {
            "category":"Autos & Motor Vehicles",
            "subcategory":"Fuel & Gas Station",
            "type":"Retail Goods"
        }
    ],
    "sg:phone":"+1   ",
    "sg:postcode":"14519",
    "sg:province":"NY",
    "sg:tags":[
        "grocery",
        "station",
        "gasoline"
    ],
    "wof:name":"Kwik - Fill",
    "wof:placetype":"venue"
},
  "geometry": {"coordinates":[-77.302397,43.227724],"type":"Point"}
}