{
  "type": "Feature",
  "properties": {
    "iso:country":"US",
    "sg:address":"7 Pumpkin St",
    "sg:city":"East Northport",
    "sg:classifiers":[
        {
            "category":"Building & Trades",
            "subcategory":"Construction",
            "type":"Services"
        }
    ],
    "sg:phone":"+1 516 986 5226",
    "sg:postcode":"11731",
    "sg:province":"NY",
    "sg:tags":[
        "contractor"
    ],
    "sg:website":"www.prestigecbc.com",
    "wof:name":"PRESTIGE CUSTOM BUILDING CORP",
    "wof:placetype":"venue"
},
  "geometry": {"coordinates":[-73.316518,40.863419],"type":"Point"}
}