{
  "type": "Feature",
  "properties": {
    "iso:country":"US",
    "sg:address":"90 Biarritz St",
    "sg:city":"Long Beach",
    "sg:classifiers":[
        {
            "category":"Building & Trades",
            "subcategory":"Construction",
            "type":"Services"
        }
    ],
    "sg:phone":"+1 516 432 2269",
    "sg:postcode":"11561",
    "sg:province":"NY",
    "wof:name":"AGC Contracting",
    "wof:placetype":"venue"
},
  "geometry": {"coordinates":[-73.62352199999999,40.5892],"type":"Point"}
}