{
  "type": "Feature",
  "properties": {
    "addr:full":"112 W Main St Fredonia NY 14063",
    "addr:housenumber":"112",
    "addr:postcode":"14063",
    "addr:street":"W Main St",
    "iso:country":"US",
    "sg:address":"112 W Main St",
    "sg:city":"Fredonia",
    "sg:classifiers":[
        {
            "category":"Education",
            "subcategory":"College",
            "type":"Public Place"
        }
    ],
    "sg:phone":"+1 716 673 1200",
    "sg:postcode":"14063",
    "sg:province":"NY",
    "sg:tags":[
        "academic",
        "school"
    ],
    "wof:name":"Empire State College",
    "wof:placetype":"venue"
},
  "geometry": {"coordinates":[-79.333928,42.43727],"type":"Point"}
}