{
  "type": "Feature",
  "properties": {
    "addr:full":"216 W 30 St New York NY 10001",
    "addr:housenumber":"216",
    "addr:postcode":"10001",
    "addr:street":"W 30 St",
    "iso:country":"US",
    "sg:address":"216 W 30 St",
    "sg:city":"New York",
    "sg:classifiers":[
        {
            "category":"Wholesale",
            "subcategory":"Apparel",
            "type":"Manufacturing & Wholesale Goods"
        }
    ],
    "sg:phone":"+1 212 279 3820",
    "sg:postcode":"10001",
    "sg:province":"NY",
    "sg:tags":[
        "clothing"
    ],
    "wof:name":"Fur Studio",
    "wof:placetype":"venue"
},
  "geometry": {"coordinates":[-73.994985,40.749409],"type":"Point"}
}