{
  "type": "Feature",
  "properties": {
    "addr:full":"260 Butler St Brooklyn NY 11217",
    "addr:housenumber":"260",
    "addr:postcode":"11217",
    "addr:street":"Butler St",
    "iso:country":"US",
    "sg:address":"260 Butler St",
    "sg:city":"Brooklyn",
    "sg:classifiers":[
        {
            "category":"Building & Trades",
            "subcategory":"Construction",
            "type":"Services"
        }
    ],
    "sg:phone":"+1 718 852 1451",
    "sg:postcode":"11217",
    "sg:province":"NY",
    "sg:tags":[
        "contractor",
        "product",
        "wood",
        "carpentry",
        "mfg"
    ],
    "wof:name":"Douglas Woodworking Co Inc",
    "wof:placetype":"venue"
},
  "geometry": {"coordinates":[-73.984459,40.681179],"type":"Point"}
}