{
  "type": "Feature",
  "properties": {
    "addr:full":"3335 Bedford Ave Brooklyn NY 11210",
    "addr:housenumber":"3335",
    "addr:postcode":"11210",
    "addr:street":"Bedford Ave",
    "iso:country":"US",
    "sg:address":"3335 Bedford Ave",
    "sg:city":"Brooklyn",
    "sg:classifiers":[
        {
            "category":"Building & Trades",
            "subcategory":"Landscaping Services",
            "type":"Services"
        }
    ],
    "sg:phone":"+1 718 258 6489",
    "sg:postcode":"11210",
    "sg:province":"NY",
    "sg:tags":[
        "landscape"
    ],
    "wof:name":"Lou Fuschetto Landscape Inc",
    "wof:placetype":"venue"
},
  "geometry": {"coordinates":[-73.95023999999999,40.619501],"type":"Point"}
}