{
  "type": "Feature",
  "properties": {
    "iso:country":"US",
    "sg:address":"430 E 63 St",
    "sg:city":"New York",
    "sg:classifiers":[
        {
            "category":"Professional",
            "type":"Services"
        }
    ],
    "sg:phone":"+1 212 980 2037",
    "sg:postcode":"10065",
    "sg:province":"NY",
    "sg:tags":[
        "establishment"
    ],
    "wof:name":"Epigroup",
    "wof:placetype":"venue"
},
  "geometry": {"coordinates":[-73.958066,40.761187],"type":"Point"}
}