{
  "type": "Feature",
  "properties": {
    "iso:country":"US",
    "sg:address":"37 Deer Ridge",
    "sg:city":"Millwood",
    "sg:classifiers":[
        {
            "category":"Professional",
            "subcategory":"Management & Consulting",
            "type":"Services"
        }
    ],
    "sg:phone":"+1 914 923 3359",
    "sg:postcode":"10546",
    "sg:province":"NY",
    "sg:tags":[
        "marketing",
        "consultant"
    ],
    "wof:name":"Highbloom Group",
    "wof:placetype":"venue"
},
  "geometry": {"coordinates":[-73.791473,41.206084],"type":"Point"}
}