{
  "type": "Feature",
  "properties": {
    "addr:full":"15 Linwood Rd N Port Washington NY 11050",
    "addr:housenumber":"15",
    "addr:postcode":"11050",
    "addr:street":"Linwood Rd N",
    "iso:country":"US",
    "sg:address":"15 Linwood Rd N",
    "sg:city":"Port Washington",
    "sg:classifiers":[
        {
            "category":"Manufacturing",
            "subcategory":"Apparel",
            "type":"Manufacturing & Wholesale Goods"
        }
    ],
    "sg:phone":"+1   ",
    "sg:postcode":"11050",
    "sg:province":"NY",
    "sg:tags":[
        "household",
        "furnishing",
        "mfg"
    ],
    "wof:name":"Artisanat",
    "wof:placetype":"venue"
},
  "geometry": {"coordinates":[-73.71918100000001,40.841797],"type":"Point"}
}