{
  "type": "Feature",
  "properties": {
    "addr:full":"523 Turin St Rome NY 13440",
    "addr:housenumber":"523",
    "addr:postcode":"13440",
    "addr:street":"Turin St",
    "iso:country":"US",
    "sg:address":"523 Turin St",
    "sg:city":"Rome",
    "sg:classifiers":[
        {
            "category":"Shopping",
            "subcategory":"Hobbies, Toys, & Games",
            "type":"Retail Goods"
        }
    ],
    "sg:phone":"+1 315 336 4748",
    "sg:postcode":"13440",
    "sg:province":"NY",
    "sg:tags":[
        "craft"
    ],
    "wof:name":"J D Crafts",
    "wof:placetype":"venue"
},
  "geometry": {"coordinates":[-75.45553,43.228939],"type":"Point"}
}