{
  "type": "Feature",
  "properties": {
    "iso:country":"US",
    "sg:address":"74 Cruickshank Rd",
    "sg:city":"Big Indian",
    "sg:classifiers":[
        {
            "category":"Professional",
            "type":"Services"
        }
    ],
    "sg:phone":"+1 845 254 5505",
    "sg:postcode":"12410",
    "sg:province":"NY",
    "sg:tags":[
        "establishment"
    ],
    "wof:name":"Jennings & Jennings",
    "wof:placetype":"venue"
},
  "geometry": {"coordinates":[-74.45337499999999,42.088543],"type":"Point"}
}