{
  "type": "Feature",
  "properties": {
    "iso:country":"US",
    "sg:address":"88 Academy St",
    "sg:city":"Patchogue",
    "sg:classifiers":[
        {
            "category":"Home & Garden",
            "subcategory":"Building Materials",
            "type":"Retail Goods"
        }
    ],
    "sg:phone":"+1 631 447 1116",
    "sg:postcode":"11772",
    "sg:province":"NY",
    "sg:tags":[
        "glass",
        "window",
        "plate"
    ],
    "wof:name":"Triple P Glass & Mirror",
    "wof:placetype":"venue"
},
  "geometry": {"coordinates":[-73.009775,40.763438],"type":"Point"}
}