{
  "type": "Feature",
  "properties": {
    "iso:country":"US",
    "sg:address":"87 Millwood Rd",
    "sg:city":"Millwood",
    "sg:classifiers":[
        {
            "category":"Home & Garden",
            "subcategory":"Building Materials",
            "type":"Retail Goods"
        }
    ],
    "sg:phone":"+1 914 941 2171",
    "sg:postcode":"10546",
    "sg:province":"NY",
    "sg:tags":[
        "lumber"
    ],
    "wof:name":"Millwood Supply",
    "wof:placetype":"venue"
},
  "geometry": {"coordinates":[-73.797095,41.190075],"type":"Point"}
}