{
  "type": "Feature",
  "properties": {
    "addr:full":"34 Route 17K Newburgh NY 12550",
    "addr:housenumber":"34",
    "addr:postcode":"12550",
    "addr:street":"Route 17K",
    "iso:country":"US",
    "sg:address":"34 Route 17K",
    "sg:city":"Newburgh",
    "sg:classifiers":[
        {
            "category":"Professional",
            "subcategory":"Lawyer & Legal Services",
            "type":"Services"
        }
    ],
    "sg:phone":"+1 845 562 0098",
    "sg:postcode":"12550",
    "sg:province":"NY",
    "sg:website":"www.law5141.com",
    "wof:name":"Carolei Anthony A Atty",
    "wof:placetype":"venue"
},
  "geometry": {"coordinates":[-74.05789900000001,41.503399],"type":"Point"}
}