{
  "type": "Feature",
  "properties": {
    "iso:country":"US",
    "sg:address":"3177 Route 112",
    "sg:city":"Medford",
    "sg:classifiers":[
        {
            "category":"Wholesale",
            "subcategory":"Hardware",
            "type":"Manufacturing & Wholesale Goods"
        },
        {
            "category":"Home & Garden",
            "subcategory":"Building Materials",
            "type":"Retail Goods"
        },
        {
            "category":"Manufacturing",
            "subcategory":"Building Materials",
            "type":"Manufacturing & Wholesale Goods"
        }
    ],
    "sg:phone":"+1 631 732 8000",
    "sg:postcode":"11763",
    "sg:province":"NY",
    "sg:tags":[
        "roofing",
        "supply",
        "hardware-builders",
        "equipment"
    ],
    "sg:website":"http://www.sandhbuildingmaterials.com",
    "wof:name":"S & H Building Material Corp.",
    "wof:placetype":"venue"
},
  "geometry": {"coordinates":[-72.996359,40.838937],"type":"Point"}
}