{
  "type": "Feature",
  "properties": {
    "addr:full":"472 4th Ave Brooklyn NY 11215",
    "addr:housenumber":"472",
    "addr:postcode":"11215",
    "addr:street":"4Th Ave",
    "iso:country":"US",
    "sg:address":"472 4th Ave",
    "sg:city":"Brooklyn",
    "sg:classifiers":[
        {
            "category":"Real Estate",
            "subcategory":"Real Estate Agent",
            "type":"Services"
        }
    ],
    "sg:phone":"+1 718 499 0333",
    "sg:postcode":"11215",
    "sg:province":"NY",
    "wof:name":"B Yang Realty",
    "wof:placetype":"venue"
},
  "geometry": {"coordinates":[-73.98959600000001,40.669487],"type":"Point"}
}