{
  "type": "Feature",
  "properties": {
    "addr:full":"6044 Main St Buffalo NY 14221",
    "addr:housenumber":"6044",
    "addr:postcode":"14221",
    "addr:street":"Main St",
    "iso:country":"US",
    "sg:address":"6044 Main St",
    "sg:city":"Buffalo",
    "sg:classifiers":[
        {
            "category":"Health Services",
            "subcategory":"Doctor",
            "type":"Services"
        }
    ],
    "sg:phone":"+1 716 634 1702",
    "sg:postcode":"14221",
    "sg:province":"NY",
    "sg:tags":[
        "physician",
        "surgeon"
    ],
    "wof:name":"Community Medical",
    "wof:placetype":"venue"
},
  "geometry": {"coordinates":[-78.729011,42.965413],"type":"Point"}
}