{
  "type": "Feature",
  "properties": {
    "iso:country":"US",
    "sg:address":"44 Sterling St",
    "sg:city":"Kingston",
    "sg:classifiers":[
        {
            "category":"Building & Trades",
            "subcategory":"Construction",
            "type":"Services"
        }
    ],
    "sg:phone":"+1 845 590 0509",
    "sg:postcode":"12401",
    "sg:province":"NY",
    "sg:tags":[
        "handyman"
    ],
    "wof:name":"Jerrys Computer Repair",
    "wof:placetype":"venue"
},
  "geometry": {"coordinates":[-74.007087,41.927915],"type":"Point"}
}