{
  "type": "Feature",
  "properties": {
    "addr:full":"330 Bowery New York NY 10003",
    "addr:housenumber":"330",
    "addr:postcode":"10003",
    "addr:street":"Bowery",
    "iso:country":"US",
    "sg:address":"330 Bowery",
    "sg:city":"New York",
    "sg:classifiers":[
        {
            "category":"Shopping",
            "subcategory":"Clothing, Apparel, & Fashions",
            "type":"Retail Goods"
        }
    ],
    "sg:phone":"+1 646 827 7567",
    "sg:postcode":"10003",
    "sg:province":"NY",
    "sg:tags":[
        "men's",
        "clothing",
        "women's"
    ],
    "sg:website":"www.rogannyc.com",
    "wof:name":"Rogan Bowery",
    "wof:placetype":"venue"
},
  "geometry": {"coordinates":[-73.992074,40.725838],"type":"Point"}
}