{
  "type": "Feature",
  "properties": {
    "iso:country":"US",
    "sg:address":"52 Washington St",
    "sg:city":"Rensselaer",
    "sg:classifiers":[
        {
            "category":"Government",
            "subcategory":"Office",
            "type":"Public Place"
        }
    ],
    "sg:phone":"+1 518 474 3715",
    "sg:postcode":"12144",
    "sg:province":"NY",
    "sg:tags":[
        "employment"
    ],
    "wof:name":"Equal Opprtunity Diversity Dev",
    "wof:placetype":"venue"
},
  "geometry": {"coordinates":[-73.745403,42.6386],"type":"Point"}
}