{
  "type": "Feature",
  "properties": {
    "addr:full":"23801 88th Ave Bellerose NY 11426",
    "addr:housenumber":"23801",
    "addr:postcode":"11426",
    "addr:street":"88Th Ave",
    "iso:country":"US",
    "sg:address":"23801 88th Ave",
    "sg:city":"Bellerose",
    "sg:classifiers":[
        {
            "category":"Farming",
            "subcategory":"Livestock Farm",
            "type":"Manufacturing & Wholesale Goods"
        }
    ],
    "sg:phone":"+1 718 343 6140",
    "sg:postcode":"11426",
    "sg:province":"NY",
    "sg:tags":[
        "horse"
    ],
    "wof:name":"Winning Touch Esmt",
    "wof:placetype":"venue"
},
  "geometry": {"coordinates":[-73.72875999999999,40.730186],"type":"Point"}
}