{
  "type": "Feature",
  "properties": {
    "addr:full":"55 Carleton Ave Ste 3 East Islip NY 11730",
    "addr:housenumber":"55",
    "addr:postcode":"11730",
    "addr:street":"Carleton Ave Ste 3",
    "iso:country":"US",
    "sg:address":"55 Carleton Ave Ste 3",
    "sg:city":"East Islip",
    "sg:classifiers":[
        {
            "category":"Health Services",
            "subcategory":"Doctor",
            "type":"Services"
        }
    ],
    "sg:phone":"+1 631 859 0994",
    "sg:postcode":"11730",
    "sg:province":"NY",
    "sg:website":"www.michael-will.com",
    "wof:name":"Will Michael",
    "wof:placetype":"venue"
},
  "geometry": {"coordinates":[-73.19061600000001,40.733431],"type":"Point"}
}