{
  "type": "Feature",
  "properties": {
    "iso:country":"US",
    "sg:address":"320 State Hwy 37",
    "sg:city":"Hogansburg",
    "sg:classifiers":[
        {
            "category":"Shopping",
            "subcategory":"Tobacco",
            "type":"Retail Goods"
        }
    ],
    "sg:phone":"+1 518 358 3362",
    "sg:postcode":"13655",
    "sg:province":"NY",
    "sg:tags":[
        "cigarette",
        "cigar",
        "dealer"
    ],
    "wof:name":"Mohawk Tobacco",
    "wof:placetype":"venue"
},
  "geometry": {"coordinates":[-74.69799,44.978073],"type":"Point"}
}