{
  "type": "Feature",
  "properties": {
    "addr:full":"5 Nobles Way Newburgh NY 12550",
    "addr:housenumber":"5",
    "addr:postcode":"12550",
    "addr:street":"Nobles Way",
    "iso:country":"US",
    "sg:address":"5 Nobles Way",
    "sg:city":"Newburgh",
    "sg:classifiers":[
        {
            "category":"Farming",
            "subcategory":"Nursery",
            "type":"Manufacturing & Wholesale Goods"
        }
    ],
    "sg:phone":"+1 845 564 0466",
    "sg:postcode":"12550",
    "sg:province":"NY",
    "wof:name":"Leptondale Nursery & Grnhse",
    "wof:placetype":"venue"
},
  "geometry": {"coordinates":[-74.09202999999999,41.570567],"type":"Point"}
}