{
  "type": "Feature",
  "properties": {
    "addr:full":"1157 Kuttruff Rd Walworth NY 14568",
    "addr:housenumber":"1157",
    "addr:postcode":"14568",
    "addr:street":"Kuttruff Rd",
    "iso:country":"US",
    "sg:address":"1157 Kuttruff Rd",
    "sg:city":"Walworth",
    "sg:classifiers":[
        {
            "category":"Building & Trades",
            "subcategory":"Pest Control",
            "type":"Services"
        }
    ],
    "sg:phone":"+1 315 986 7555",
    "sg:postcode":"14568",
    "sg:province":"NY",
    "wof:name":"Anderson Wildlife Removal Svc",
    "wof:placetype":"venue"
},
  "geometry": {"coordinates":[-77.32493599999999,43.152734],"type":"Point"}
}