{
  "type": "Feature",
  "properties": {
    "addr:full":"1995 Bly Rd East Meadow NY 11554",
    "addr:housenumber":"1995",
    "addr:postcode":"11554",
    "addr:street":"Bly Rd",
    "iso:country":"US",
    "sg:address":"1995 Bly Rd",
    "sg:city":"East Meadow",
    "sg:classifiers":[
        {
            "category":"Building & Trades",
            "subcategory":"Construction",
            "type":"Services"
        }
    ],
    "sg:phone":"+1 516 542 1277",
    "sg:postcode":"11554",
    "sg:province":"NY",
    "sg:tags":[
        "concrete",
        "contractor"
    ],
    "wof:name":"Goncalves Concrete Inc",
    "wof:placetype":"venue"
},
  "geometry": {"coordinates":[-73.562645,40.726177],"type":"Point"}
}