{
  "type": "Feature",
  "properties": {
    "iso:country":"US",
    "sg:address":"1025 Lafayette Ave",
    "sg:city":"Brooklyn",
    "sg:classifiers":[
        {
            "category":"Restaurant",
            "type":"Food & Drink"
        }
    ],
    "sg:phone":"+1 718 573 8383",
    "sg:postcode":"11221",
    "sg:province":"NY",
    "sg:tags":[
        "mexican"
    ],
    "wof:name":"El Buen Sabor Dominicano",
    "wof:placetype":"venue"
},
  "geometry": {"coordinates":[-73.93092,40.692356],"type":"Point"}
}