{
  "type": "Feature",
  "properties": {
    "addr:full":"6 Spruce Hill Rd Armonk NY 10504",
    "addr:housenumber":"6",
    "addr:postcode":"10504",
    "addr:street":"Spruce Hill Rd",
    "iso:country":"US",
    "sg:address":"6 Spruce Hill Rd",
    "sg:city":"Armonk",
    "sg:classifiers":[
        {
            "category":"Professional",
            "subcategory":"Computer Services",
            "type":"Services"
        }
    ],
    "sg:phone":"+1 516 887 0178",
    "sg:postcode":"10504",
    "sg:province":"NY",
    "sg:tags":[
        "development",
        "system",
        "software"
    ],
    "wof:name":"Complyguard Networks Inc",
    "wof:placetype":"venue"
},
  "geometry": {"coordinates":[-73.680885,41.142272],"type":"Point"}
}