{
  "type": "Feature",
  "properties": {
    "iso:country":"US",
    "sg:address":"452 5th Ave",
    "sg:city":"New York",
    "sg:classifiers":[
        {
            "category":"Professional",
            "subcategory":"Credit Reporting & Collection",
            "type":"Services"
        }
    ],
    "sg:phone":"+1 212 525 5000",
    "sg:postcode":"10018",
    "sg:province":"NY",
    "sg:tags":[
        "department",
        "domestic"
    ],
    "wof:name":"Hsbc Bank USA National Assn",
    "wof:placetype":"venue"
},
  "geometry": {"coordinates":[-73.982133,40.75179],"type":"Point"}
}