{
  "type": "Feature",
  "properties": {
    "iso:country":"US",
    "sg:address":"58 State Hwy 200",
    "sg:city":"Richford",
    "sg:classifiers":[
        {
            "category":"Freight",
            "type":"Transportation"
        }
    ],
    "sg:phone":"+1   ",
    "sg:postcode":"13835",
    "sg:province":"NY",
    "sg:tags":[
        "operator",
        "local",
        "trucking"
    ],
    "wof:name":"LMS Co",
    "wof:placetype":"venue"
},
  "geometry": {"coordinates":[-76.205431,42.410228],"type":"Point"}
}