{
  "type": "Feature",
  "properties": {
    "iso:country":"US",
    "sg:address":"227 Prospect Park W",
    "sg:city":"Brooklyn",
    "sg:classifiers":[
        {
            "category":"Retail",
            "subcategory":"Repair Shop",
            "type":"Services"
        }
    ],
    "sg:phone":"+1 718 499 8102",
    "sg:postcode":"11215",
    "sg:province":"NY",
    "sg:tags":[
        "lock",
        "locksmith"
    ],
    "wof:name":"Brooklyn House Of Locks",
    "wof:placetype":"venue"
},
  "geometry": {"coordinates":[-73.980557,40.660157],"type":"Point"}
}