{
  "type": "Feature",
  "properties": {
    "iso:country":"US",
    "sg:address":"105 Landing Rd",
    "sg:city":"Glen Cove",
    "sg:classifiers":[
        {
            "category":"Building & Trades",
            "subcategory":"Plumbing",
            "type":"Services"
        }
    ],
    "sg:phone":"+1 516 671 6726",
    "sg:postcode":"11542",
    "sg:province":"NY",
    "sg:tags":[
        "plumbing",
        "contractor"
    ],
    "wof:name":"Hassel Plumbing Corp",
    "wof:placetype":"venue"
},
  "geometry": {"coordinates":[-73.646637,40.866834],"type":"Point"}
}