{
  "type": "Feature",
  "properties": {
    "addr:full":"553 New York Ave Brooklyn NY 11225",
    "addr:housenumber":"553",
    "addr:postcode":"11225",
    "addr:street":"New York Ave",
    "iso:country":"US",
    "sg:address":"553 New York Ave",
    "sg:city":"Brooklyn",
    "sg:classifiers":[
        {
            "category":"Autos & Motor Vehicles",
            "subcategory":"Automobile Sales",
            "type":"Retail Goods"
        }
    ],
    "sg:phone":"+1 718 495 8631",
    "sg:postcode":"11225",
    "sg:province":"NY",
    "sg:tags":[
        "limo"
    ],
    "sg:website":"www.graylinelimousine.net",
    "wof:name":"Grayline Limousine",
    "wof:placetype":"venue"
},
  "geometry": {"coordinates":[-73.94433100000001,40.661962],"type":"Point"}
}