{
  "type": "Feature",
  "properties": {
    "addr:full":"90 Plant Ave Hauppauge NY 11788",
    "addr:housenumber":"90",
    "addr:postcode":"11788",
    "addr:street":"Plant Ave",
    "iso:country":"US",
    "sg:address":"90 Plant Ave",
    "sg:city":"Hauppauge",
    "sg:classifiers":[
        {
            "category":"Wholesale",
            "subcategory":"Hardware",
            "type":"Manufacturing & Wholesale Goods"
        }
    ],
    "sg:phone":"+1 631 435 8726",
    "sg:postcode":"11788",
    "sg:province":"NY",
    "sg:tags":[
        "equipment",
        "heating"
    ],
    "wof:name":"Applied Technology",
    "wof:placetype":"venue"
},
  "geometry": {"coordinates":[-73.243236,40.813798],"type":"Point"}
}