{
  "type": "Feature",
  "properties": {
    "addr:full":"719 Main St New Rochelle NY 10801",
    "addr:housenumber":"719",
    "addr:postcode":"10801",
    "addr:street":"Main St",
    "iso:country":"US",
    "sg:address":"719 Main St",
    "sg:city":"New Rochelle",
    "sg:classifiers":[
        {
            "category":"Manufacturing",
            "subcategory":"Signs",
            "type":"Manufacturing & Wholesale Goods"
        }
    ],
    "sg:phone":"+1   ",
    "sg:postcode":"10801",
    "sg:province":"NY",
    "sg:tags":[
        "display",
        "custom",
        "painting",
        "advertising",
        "mfg"
    ],
    "wof:name":"Adamo Signs",
    "wof:placetype":"venue"
},
  "geometry": {"coordinates":[-73.788636,40.903975],"type":"Point"}
}