{
  "type": "Feature",
  "properties": {
    "addr:full":"230 Broadway Brooklyn NY 11211",
    "addr:housenumber":"230",
    "addr:postcode":"11211",
    "addr:street":"Broadway",
    "iso:country":"US",
    "sg:address":"230 Broadway",
    "sg:city":"Brooklyn",
    "sg:classifiers":[
        {
            "category":"Building & Trades",
            "subcategory":"Locksmith",
            "type":"Services"
        }
    ],
    "sg:phone":"+1 718 387 9595",
    "sg:postcode":"11211",
    "sg:province":"NY",
    "sg:tags":[
        "equipment",
        "supply"
    ],
    "sg:website":"http://www.brooklynlock.com",
    "wof:name":"Brooklyn Lock & Hardware Supplies, Inc",
    "wof:placetype":"venue"
},
  "geometry": {"coordinates":[-73.960318,40.709268],"type":"Point"}
}