{
  "type": "Feature",
  "properties": {
    "iso:country":"US",
    "sg:address":"27 N Moore Street",
    "sg:city":"New York",
    "sg:classifiers":[
        {
            "category":"Arts & Performance",
            "subcategory":"Art Gallery",
            "type":"Entertainment"
        }
    ],
    "sg:phone":"+1 212 966 3897",
    "sg:postcode":"10013",
    "sg:province":"NY",
    "wof:name":"Icosadron Gallery",
    "wof:placetype":"venue"
},
  "geometry": {"coordinates":[-74.007473,40.719847],"type":"Point"}
}