{
  "type": "Feature",
  "properties": {
    "addr:full":"508 Broadway Monticello NY 12701",
    "addr:housenumber":"508",
    "addr:postcode":"12701",
    "addr:street":"Broadway",
    "iso:country":"US",
    "sg:address":"508 Broadway",
    "sg:city":"Monticello",
    "sg:classifiers":[
        {
            "category":"Shopping",
            "subcategory":"Optical Goods",
            "type":"Retail Goods"
        }
    ],
    "sg:phone":"+1   ",
    "sg:postcode":"12701",
    "sg:province":"NY",
    "wof:name":"Fashion Eyewear",
    "wof:placetype":"venue"
},
  "geometry": {"coordinates":[-74.703726,41.661652],"type":"Point"}
}