{
  "type": "Feature",
  "properties": {
    "iso:country":"US",
    "sg:address":"1 Merry Ln",
    "sg:city":"Jericho",
    "sg:classifiers":[
        {
            "category":"Education",
            "subcategory":"Library",
            "type":"Public Place"
        }
    ],
    "sg:phone":"+1 516 935 6790",
    "sg:postcode":"11753",
    "sg:province":"NY",
    "sg:tags":[
        "executive"
    ],
    "wof:name":"Jericho Public Library",
    "wof:placetype":"venue"
},
  "geometry": {"coordinates":[-73.53303099999999,40.791792],"type":"Point"}
}