{
  "type": "Feature",
  "properties": {
    "iso:country":"US",
    "sg:address":"4 Railroad Ave",
    "sg:city":"Clifton Springs",
    "sg:classifiers":[
        {
            "category":"Education",
            "subcategory":"Library",
            "type":"Public Place"
        }
    ],
    "sg:phone":"+1 315 462 7371",
    "sg:postcode":"14432",
    "sg:province":"NY",
    "sg:tags":[
        "executive"
    ],
    "wof:name":"Clifton Springs Library",
    "wof:placetype":"venue"
},
  "geometry": {"coordinates":[-77.136416,42.963266],"type":"Point"}
}