{
  "type": "Feature",
  "properties": {
    "iso:country":"US",
    "sg:address":"60 Holiday Harbor",
    "sg:city":"Canandaigua",
    "sg:classifiers":[
        {
            "category":"Real Estate",
            "subcategory":"Real Estate Agent",
            "type":"Services"
        }
    ],
    "sg:phone":"+1 585 396 1063",
    "sg:postcode":"14424",
    "sg:province":"NY",
    "sg:tags":[
        "manager"
    ],
    "wof:name":"Holiday Harbour Condominium",
    "wof:placetype":"venue"
},
  "geometry": {"coordinates":[-77.28243999999999,42.875431],"type":"Point"}
}