{
  "type": "Feature",
  "properties": {
    "addr:full":"969 Columbus Ave New York NY 10025",
    "addr:housenumber":"969",
    "addr:postcode":"10025",
    "addr:street":"Columbus Ave",
    "iso:country":"US",
    "sg:address":"969 Columbus Ave",
    "sg:city":"New York",
    "sg:classifiers":[
        {
            "category":"Professional",
            "type":"Services"
        }
    ],
    "sg:phone":"+1 212 222 0406",
    "sg:postcode":"10025",
    "sg:province":"NY",
    "sg:tags":[
        "establishment"
    ],
    "wof:name":"A & N No2",
    "wof:placetype":"venue"
},
  "geometry": {"coordinates":[-73.962045,40.800158],"type":"Point"}
}