{
  "type": "Feature",
  "properties": {
    "addr:full":"1531 51st St Brooklyn NY 11219",
    "addr:housenumber":"1531",
    "addr:postcode":"11219",
    "addr:street":"51St St",
    "iso:country":"US",
    "sg:address":"1531 51st St",
    "sg:city":"Brooklyn",
    "sg:classifiers":[
        {
            "category":"Real Estate",
            "subcategory":"Real Estate Agent",
            "type":"Services"
        }
    ],
    "sg:phone":"+1 718 851 3097",
    "sg:postcode":"11219",
    "sg:province":"NY",
    "wof:name":"David Freier Realty",
    "wof:placetype":"venue"
},
  "geometry": {"coordinates":[-73.98714,40.630382],"type":"Point"}
}