{
  "type": "Feature",
  "properties": {
    "iso:country":"US",
    "sg:address":"205 S Main St",
    "sg:city":"Perry",
    "sg:classifiers":[
        {
            "category":"Autos & Motor Vehicles",
            "subcategory":"Fuel & Gas Station",
            "type":"Retail Goods"
        }
    ],
    "sg:phone":"+1   ",
    "sg:postcode":"14530",
    "sg:province":"NY",
    "wof:name":"Silver Lake Country Mkt",
    "wof:placetype":"venue"
},
  "geometry": {"coordinates":[-78.01153600000001,42.709675],"type":"Point"}
}