{
  "type": "Feature",
  "properties": {
    "iso:country":"US",
    "sg:address":"725 South Ave",
    "sg:city":"Rochester",
    "sg:classifiers":[
        {
            "category":"Wholesale",
            "subcategory":"Stationery",
            "type":"Manufacturing & Wholesale Goods"
        }
    ],
    "sg:phone":"+1 585 473 2420",
    "sg:postcode":"14620",
    "sg:province":"NY",
    "sg:tags":[
        "paper"
    ],
    "wof:name":"International Paper",
    "wof:placetype":"venue"
},
  "geometry": {"coordinates":[-77.604417,43.141949],"type":"Point"}
}