{
  "type": "Feature",
  "properties": {
    "addr:full":"51 Buffalo Ave Brooklyn NY 11233",
    "addr:housenumber":"51",
    "addr:postcode":"11233",
    "addr:street":"Buffalo Ave",
    "iso:country":"US",
    "sg:address":"51 Buffalo Ave",
    "sg:city":"Brooklyn",
    "sg:classifiers":[
        {
            "category":"Professional",
            "subcategory":"Management & Consulting",
            "type":"Services"
        }
    ],
    "sg:phone":"+1 718 221 9200",
    "sg:postcode":"11233",
    "sg:province":"NY",
    "sg:tags":[
        "marketing",
        "consultant"
    ],
    "wof:name":"Southern Star Mortgage Corp",
    "wof:placetype":"venue"
},
  "geometry": {"coordinates":[-73.924617,40.678202],"type":"Point"}
}