{
  "type": "Feature",
  "properties": {
    "addr:full":"5 Secor Ln Pelham NY 10803",
    "addr:housenumber":"5",
    "addr:postcode":"10803",
    "addr:street":"Secor Ln",
    "iso:country":"US",
    "sg:address":"5 Secor Ln",
    "sg:city":"Pelham",
    "sg:classifiers":[
        {
            "category":"Building & Trades",
            "subcategory":"Construction",
            "type":"Services"
        }
    ],
    "sg:phone":"+1 914 712 9158",
    "sg:postcode":"10803",
    "sg:province":"NY",
    "sg:tags":[
        "general",
        "contractor"
    ],
    "wof:name":"Westchester Contracting",
    "wof:placetype":"venue"
},
  "geometry": {"coordinates":[-73.82089999999999,40.893951],"type":"Point"}
}