{
  "type": "Feature",
  "properties": {
    "iso:country":"US",
    "sg:address":"5170 W Taft Rd",
    "sg:city":"Syracuse",
    "sg:classifiers":[
        {
            "category":"Banks & Credit Unions",
            "subcategory":"Bank",
            "type":"Services"
        }
    ],
    "sg:phone":"+1 315 458 9011",
    "sg:postcode":"13212",
    "sg:province":"NY",
    "sg:tags":[
        "state",
        "commercial"
    ],
    "wof:name":"M&T",
    "wof:placetype":"venue"
},
  "geometry": {"coordinates":[-76.157212,43.121931],"type":"Point"}
}