{
  "type": "Feature",
  "properties": {
    "addr:full":"1 Hudson St New York NY 10013",
    "addr:housenumber":"1",
    "addr:postcode":"10013",
    "addr:street":"Hudson St",
    "iso:country":"US",
    "sg:address":"1 Hudson St",
    "sg:city":"New York",
    "sg:classifiers":[
        {
            "category":"Restaurant",
            "type":"Food & Drink"
        }
    ],
    "sg:phone":"+1   ",
    "sg:postcode":"10013",
    "sg:province":"NY",
    "wof:name":"Acapella Restaurant",
    "wof:placetype":"venue"
},
  "geometry": {"coordinates":[-74.00920499999999,40.716187],"type":"Point"}
}