{
  "type": "Feature",
  "properties": {
    "addr:full":"594 16th St Brooklyn NY 11218",
    "addr:housenumber":"594",
    "addr:postcode":"11218",
    "addr:street":"16Th St",
    "iso:country":"US",
    "sg:address":"594 16th St",
    "sg:city":"Brooklyn",
    "sg:classifiers":[
        {
            "category":"Food & Beverages",
            "subcategory":"Farmers Market",
            "type":"Retail Goods"
        },
        {
            "category":"Wholesale",
            "subcategory":"Fruits & Vegetables",
            "type":"Manufacturing & Wholesale Goods"
        }
    ],
    "sg:phone":"+1 718 789 2880",
    "sg:postcode":"11218",
    "sg:province":"NY",
    "sg:tags":[
        "veggie",
        "vegetables-wholesale"
    ],
    "sg:website":"www.ger-nis.com",
    "wof:name":"Ger-Nis International LLC",
    "wof:placetype":"venue"
},
  "geometry": {"coordinates":[-73.975347,40.657811],"type":"Point"}
}