{
  "type": "Feature",
  "properties": {
    "addr:full":"58 East Ave Fairport NY 14450",
    "addr:housenumber":"58",
    "addr:postcode":"14450",
    "addr:street":"East Ave",
    "iso:country":"US",
    "sg:address":"58 East Ave",
    "sg:city":"Fairport",
    "sg:classifiers":[
        {
            "category":"Building & Trades",
            "subcategory":"Construction",
            "type":"Services"
        }
    ],
    "sg:phone":"+1 585 388 1391",
    "sg:postcode":"14450",
    "sg:province":"NY",
    "sg:tags":[
        "carpentry",
        "contractor"
    ],
    "wof:name":"Jim Sparks Carpenter",
    "wof:placetype":"venue"
},
  "geometry": {"coordinates":[-77.439351,43.105588],"type":"Point"}
}