{
  "type": "Feature",
  "properties": {
    "iso:country":"US",
    "sg:address":"7815 3rd Ave",
    "sg:city":"Brooklyn",
    "sg:classifiers":[
        {
            "category":"Shopping",
            "subcategory":"Jewelry",
            "type":"Retail Goods"
        }
    ],
    "sg:phone":"+1   ",
    "sg:postcode":"11209",
    "sg:province":"NY",
    "wof:name":"Al Aqsa Jewelry Ltd",
    "wof:placetype":"venue"
},
  "geometry": {"coordinates":[-74.02887200000001,40.628646],"type":"Point"}
}