{
  "type": "Feature",
  "properties": {
    "addr:full":"5 Henry St New York NY 10038",
    "addr:housenumber":"5",
    "addr:postcode":"10038",
    "addr:street":"Henry St",
    "iso:country":"US",
    "sg:address":"5 Henry St",
    "sg:city":"New York",
    "sg:classifiers":[
        {
            "category":"Retail",
            "subcategory":"Repair Shop",
            "type":"Services"
        }
    ],
    "sg:phone":"+1 212 632 7312",
    "sg:postcode":"10038",
    "sg:province":"NY",
    "sg:tags":[
        "lock",
        "locksmith"
    ],
    "wof:name":"24 Hour All Day Locksmith",
    "wof:placetype":"venue"
},
  "geometry": {"coordinates":[-73.99739,40.712843],"type":"Point"}
}