{
  "type": "Feature",
  "properties": {
    "addr:full":"85 Travis Ave Staten Island NY 10314",
    "addr:housenumber":"85",
    "addr:postcode":"10314",
    "addr:street":"Travis Ave",
    "iso:country":"US",
    "sg:address":"85 Travis Ave",
    "sg:city":"Staten Island",
    "sg:classifiers":[
        {
            "category":"Building & Trades",
            "subcategory":"Construction",
            "type":"Services"
        }
    ],
    "sg:phone":"+1 718 982 8482",
    "sg:postcode":"10314",
    "sg:province":"NY",
    "sg:tags":[
        "contractor"
    ],
    "wof:name":"Brothers Contractors",
    "wof:placetype":"venue"
},
  "geometry": {"coordinates":[-74.1502,40.586201],"type":"Point"}
}