{
  "type": "Feature",
  "properties": {
    "addr:full":"32 Union Sq E New York NY 10003",
    "addr:housenumber":"32",
    "addr:postcode":"10003",
    "addr:street":"Union Sq E",
    "iso:country":"US",
    "sg:address":"32 Union Sq E",
    "sg:city":"New York",
    "sg:classifiers":[
        {
            "category":"Banks & Credit Unions",
            "subcategory":"Investment Brokerage",
            "type":"Services"
        }
    ],
    "sg:phone":"+1 212 477 7130",
    "sg:postcode":"10003",
    "sg:province":"NY",
    "sg:tags":[
        "consultant",
        "financing"
    ],
    "wof:name":"CSS Partners",
    "wof:placetype":"venue"
},
  "geometry": {"coordinates":[-73.989076,40.736335],"type":"Point"}
}