{
  "type": "Feature",
  "properties": {
    "iso:country":"US",
    "sg:address":"21 Finkle Rd",
    "sg:city":"Pine Plains",
    "sg:classifiers":[
        {
            "category":"Recreation",
            "subcategory":"Amusement Park",
            "type":"Entertainment"
        }
    ],
    "sg:phone":"+1 518 789 3176",
    "sg:postcode":"12503",
    "sg:province":"NY",
    "wof:name":"Mid-Way Go Carts",
    "wof:placetype":"venue"
},
  "geometry": {"coordinates":[-73.628372,42.009675],"type":"Point"}
}