{
  "type": "Feature",
  "properties": {
    "iso:country":"US",
    "sg:address":"8297 Niagara Falls Blvd",
    "sg:city":"Niagara Falls",
    "sg:classifiers":[
        {
            "category":"Shopping",
            "subcategory":"Clothing, Apparel, & Fashions",
            "type":"Retail Goods"
        }
    ],
    "sg:phone":"+1 716 283 5258",
    "sg:postcode":"14304",
    "sg:province":"NY",
    "wof:name":"Fashion Bug",
    "wof:placetype":"venue"
},
  "geometry": {"coordinates":[-78.96888800000001,43.089826],"type":"Point"}
}