{
  "type": "Feature",
  "properties": {
    "iso:country":"US",
    "sg:address":"163 Broadway",
    "sg:city":"Amityville",
    "sg:classifiers":[
        {
            "category":"Retail",
            "subcategory":"Laundry & Dry Cleaning",
            "type":"Services"
        }
    ],
    "sg:phone":"+1 631 264 3828",
    "sg:postcode":"11701",
    "sg:province":"NY",
    "sg:tags":[
        "cleaners"
    ],
    "wof:name":"Triangle Cleaners",
    "wof:placetype":"venue"
},
  "geometry": {"coordinates":[-73.41716,40.676712],"type":"Point"}
}