{
  "type": "Feature",
  "properties": {
    "iso:country":"US",
    "sg:address":"258 Hawkins Ave",
    "sg:city":"Ronkonkoma",
    "sg:classifiers":[
        {
            "category":"Building & Trades",
            "subcategory":"Construction",
            "type":"Services"
        }
    ],
    "sg:phone":"+1 631 738 7422",
    "sg:postcode":"11779",
    "sg:province":"NY",
    "sg:tags":[
        "contractor"
    ],
    "wof:name":"J & J Creative Builders Corp",
    "wof:placetype":"venue"
},
  "geometry": {"coordinates":[-73.107885,40.818742],"type":"Point"}
}