{
  "type": "Feature",
  "properties": {
    "iso:country":"US",
    "sg:address":"80 Exchange St",
    "sg:city":"Binghamton",
    "sg:classifiers":[
        {
            "category":"Professional",
            "subcategory":"Management & Consulting",
            "type":"Services"
        }
    ],
    "sg:phone":"+1 607 722 6706",
    "sg:postcode":"13901",
    "sg:province":"NY",
    "wof:name":"Stewart W &WIllma C Hoyt Fndtn",
    "wof:placetype":"venue"
},
  "geometry": {"coordinates":[-75.909514,42.096789],"type":"Point"}
}