{
  "type": "Feature",
  "properties": {
    "addr:full":"1269 Co Rte 54 Fulton NY 13069",
    "addr:housenumber":"1269",
    "addr:postcode":"13069",
    "addr:street":"Co Rte 54",
    "iso:country":"US",
    "sg:address":"1269 Co Rte 54",
    "sg:city":"Fulton",
    "sg:classifiers":[
        {
            "category":"Autos & Motor Vehicles",
            "subcategory":"Automobile Sales",
            "type":"Retail Goods"
        }
    ],
    "sg:phone":"+1   ",
    "sg:postcode":"13069",
    "sg:province":"NY",
    "sg:tags":[
        "used"
    ],
    "wof:name":"J & A Sales",
    "wof:placetype":"venue"
},
  "geometry": {"coordinates":[-76.240236,43.340672],"type":"Point"}
}