{
  "type": "Feature",
  "properties": {
    "addr:full":"962 S Lake Blvd Mahopac NY 10541",
    "addr:housenumber":"962",
    "addr:postcode":"10541",
    "addr:street":"S Lake Blvd",
    "iso:country":"US",
    "sg:address":"962 S Lake Blvd",
    "sg:city":"Mahopac",
    "sg:classifiers":[
        {
            "category":"Personal",
            "subcategory":"Skin Care",
            "type":"Services"
        },
        {
            "category":"Personal",
            "subcategory":"Day Spa",
            "type":"Services"
        }
    ],
    "sg:phone":"+1 845 621 1022",
    "sg:postcode":"10541",
    "sg:province":"NY",
    "sg:website":"www.blueremedy.com",
    "wof:name":"Blue Remedy",
    "wof:placetype":"venue"
},
  "geometry": {"coordinates":[-73.733475,41.372586],"type":"Point"}
}