{
  "type": "Feature",
  "properties": {
    "addr:full":"1000 N River St Rochester NY 14612",
    "addr:housenumber":"1000",
    "addr:postcode":"14612",
    "addr:street":"N River St",
    "iso:country":"US",
    "sg:address":"1000 N River St",
    "sg:city":"Rochester",
    "sg:classifiers":[
        {
            "category":"Bars & Pubs",
            "type":"Food & Drink"
        }
    ],
    "sg:menulink":"http://www.allmenus.com/ny/rochester/25826-california-rollin-sushi-bar/menu/",
    "sg:phone":"+1 585 271 8920",
    "sg:postcode":"14612",
    "sg:province":"NY",
    "sg:tags":[
        "sushi",
        "asian"
    ],
    "wof:name":"California Rollin' Sushi Bar",
    "wof:placetype":"venue"
},
  "geometry": {"coordinates":[-77.60940100000001,43.252986],"type":"Point"}
}