{
  "type": "Feature",
  "properties": {
    "iso:country":"US",
    "sg:address":"2938 Hempstead Tpke",
    "sg:city":"Levittown",
    "sg:classifiers":[
        {
            "category":"Professional",
            "type":"Services"
        }
    ],
    "sg:phone":"+1 516 520 7985",
    "sg:postcode":"11756",
    "sg:province":"NY",
    "sg:tags":[
        "establishment"
    ],
    "wof:name":"NABCOT",
    "wof:placetype":"venue"
},
  "geometry": {"coordinates":[-73.529366,40.724551],"type":"Point"}
}