{
  "type": "Feature",
  "properties": {
    "iso:country":"US",
    "sg:address":"493 Flushing Ave",
    "sg:city":"Brooklyn",
    "sg:classifiers":[
        {
            "category":"Professional",
            "type":"Services"
        }
    ],
    "sg:phone":"+1 718 852 3016",
    "sg:postcode":"11205",
    "sg:province":"NY",
    "sg:tags":[
        "establishment"
    ],
    "wof:name":"J & F Enterprise USA Inc",
    "wof:placetype":"venue"
},
  "geometry": {"coordinates":[-73.955758,40.699181],"type":"Point"}
}