{
  "type": "Feature",
  "properties": {
    "iso:country":"US",
    "sg:address":"207 Canal St",
    "sg:city":"New York",
    "sg:classifiers":[
        {
            "category":"Shopping",
            "subcategory":"Jewelry",
            "type":"Retail Goods"
        }
    ],
    "sg:phone":"+1 212 966 8532",
    "sg:postcode":"10013",
    "sg:province":"NY",
    "sg:tags":[
        "watch"
    ],
    "wof:name":"Parbes Perfume & Fashion Watches",
    "wof:placetype":"venue"
},
  "geometry": {"coordinates":[-73.998656,40.717293],"type":"Point"}
}