{
  "type": "Feature",
  "properties": {
    "addr:full":"3 Roberts Ave Buffalo NY 14206",
    "addr:housenumber":"3",
    "addr:postcode":"14206",
    "addr:street":"Roberts Ave",
    "iso:country":"US",
    "sg:address":"3 Roberts Ave",
    "sg:city":"Buffalo",
    "sg:classifiers":[
        {
            "category":"Wholesale",
            "subcategory":"Machinery & Supplies",
            "type":"Manufacturing & Wholesale Goods"
        }
    ],
    "sg:phone":"+1 716 826 1658",
    "sg:postcode":"14206",
    "sg:province":"NY",
    "sg:tags":[
        "sandblasting"
    ],
    "wof:name":"Surface Finishing Systems",
    "wof:placetype":"venue"
},
  "geometry": {"coordinates":[-78.815837,42.871964],"type":"Point"}
}