{
  "type": "Feature",
  "properties": {
    "addr:full":"86 E Main St Wappingers Falls NY 12590",
    "addr:housenumber":"86",
    "addr:postcode":"12590",
    "addr:street":"E Main St",
    "iso:country":"US",
    "sg:address":"86 E Main St",
    "sg:city":"Wappingers Falls",
    "sg:classifiers":[
        {
            "category":"Manufacturing",
            "subcategory":"Printing",
            "type":"Manufacturing & Wholesale Goods"
        }
    ],
    "sg:phone":"+1 845 298 6236",
    "sg:postcode":"12590",
    "sg:province":"NY",
    "sg:tags":[
        "newspaper"
    ],
    "wof:name":"Hudson Valley Busieness Jrnl",
    "wof:placetype":"venue"
},
  "geometry": {"coordinates":[-73.913145,41.597009],"type":"Point"}
}