{
  "type": "Feature",
  "properties": {
    "addr:full":"2 Rte 112 Port Jeffrsn Sta NY 11776",
    "addr:housenumber":"2",
    "addr:postcode":"11776",
    "addr:street":"Rte 112 Port Jeffrsn Sta",
    "iso:country":"US",
    "sg:address":"2 Rte 112",
    "sg:city":"Port Jeffrsn Sta",
    "sg:classifiers":[
        {
            "category":"Home & Garden",
            "subcategory":"Building Materials",
            "type":"Retail Goods"
        }
    ],
    "sg:phone":"+1 631 473 0148",
    "sg:postcode":"11776",
    "sg:province":"NY",
    "sg:tags":[
        "lumber"
    ],
    "sg:website":"www.84lumber.com",
    "wof:name":"84 Lumber",
    "wof:placetype":"venue"
},
  "geometry": {"coordinates":[-73.053803,40.933433],"type":"Point"}
}