{
  "type": "Feature",
  "properties": {
    "iso:country":"US",
    "sg:address":"457 State St",
    "sg:city":"Binghamton",
    "sg:classifiers":[
        {
            "category":"Social Services",
            "type":"Services"
        }
    ],
    "sg:phone":"+1 607 724 5464",
    "sg:postcode":"13901",
    "sg:province":"NY",
    "wof:name":"Greater Broome County Chapter",
    "wof:placetype":"venue"
},
  "geometry": {"coordinates":[-75.905103,42.107405],"type":"Point"}
}