{
  "type": "Feature",
  "properties": {
    "iso:country":"US",
    "sg:address":"701 Seneca St Ste 145",
    "sg:city":"Buffalo",
    "sg:classifiers":[
        {
            "category":"Building & Trades",
            "subcategory":"Cleaning & Sanitation",
            "type":"Services"
        }
    ],
    "sg:phone":"+1 716 842 6833",
    "sg:postcode":"14210",
    "sg:province":"NY",
    "sg:tags":[
        "carpet"
    ],
    "sg:website":"www.pristineny.com",
    "wof:name":"CHEM-DRY PRISTINE CHEM-DRY",
    "wof:placetype":"venue"
},
  "geometry": {"coordinates":[-78.850707,42.876133],"type":"Point"}
}