{
  "type": "Feature",
  "properties": {
    "addr:full":"201 Ward St Ste 2A Montgomery NY 12549",
    "addr:housenumber":"201",
    "addr:postcode":"12549",
    "addr:street":"Ward St Ste 2A",
    "iso:country":"US",
    "sg:address":"201 Ward St Ste 2A",
    "sg:city":"Montgomery",
    "sg:classifiers":[
        {
            "category":"Professional",
            "subcategory":"Lawyer & Legal Services",
            "type":"Services"
        }
    ],
    "sg:phone":"+1 845 457 7501",
    "sg:postcode":"12549",
    "sg:province":"NY",
    "sg:website":"www.frlawny.com",
    "wof:name":"FASSNACHT & RAMOS LLP",
    "wof:placetype":"venue"
},
  "geometry": {"coordinates":[-74.230673,41.525712],"type":"Point"}
}