{
  "type": "Feature",
  "properties": {
    "iso:country":"US",
    "sg:address":"17 Culvert St",
    "sg:city":"Phoenix",
    "sg:classifiers":[
        {
            "category":"Autos & Motor Vehicles",
            "subcategory":"Auto Supplies",
            "type":"Retail Goods"
        }
    ],
    "sg:phone":"+1 315 695 4397",
    "sg:postcode":"13135",
    "sg:province":"NY",
    "sg:tags":[
        "equipment",
        "part",
        "automotive",
        "automobile"
    ],
    "wof:name":"Capital Automotive Equipment",
    "wof:placetype":"venue"
},
  "geometry": {"coordinates":[-76.301132,43.230469],"type":"Point"}
}