{
  "type": "Feature",
  "properties": {
    "iso:country":"US",
    "sg:address":"1774 Sound Ave",
    "sg:city":"Calverton",
    "sg:classifiers":[
        {
            "category":"Travel",
            "subcategory":"Campground",
            "type":"Entertainment"
        }
    ],
    "sg:phone":"+1 631 727 1614",
    "sg:postcode":"11933",
    "sg:province":"NY",
    "sg:tags":[
        "camp"
    ],
    "sg:website":"www.scouting.org",
    "wof:name":"Boy Scouts Of America",
    "wof:placetype":"venue"
},
  "geometry": {"coordinates":[-72.769806,40.957504],"type":"Point"}
}