{
  "type": "Feature",
  "properties": {
    "addr:full":"180 Union Ave Brooklyn NY 11211",
    "addr:housenumber":"180",
    "addr:postcode":"11211",
    "addr:street":"Union Ave",
    "iso:country":"US",
    "sg:address":"180 Union Ave",
    "sg:city":"Brooklyn",
    "sg:classifiers":[
        {
            "category":"Shopping",
            "subcategory":"Discount & Variety Stores",
            "type":"Retail Goods"
        }
    ],
    "sg:phone":"+1 718 782 6998",
    "sg:postcode":"11211",
    "sg:province":"NY",
    "wof:name":"Dollar Smile Inc",
    "wof:placetype":"venue"
},
  "geometry": {"coordinates":[-73.950186,40.705605],"type":"Point"}
}