{
  "type": "Feature",
  "properties": {
    "addr:full":"640 Baltic St Brooklyn NY 11217",
    "addr:housenumber":"640",
    "addr:postcode":"11217",
    "addr:street":"Baltic St",
    "iso:country":"US",
    "sg:address":"640 Baltic St",
    "sg:city":"Brooklyn",
    "sg:classifiers":[
        {
            "category":"Professional",
            "subcategory":"Lawyer & Legal Services",
            "type":"Services"
        }
    ],
    "sg:phone":"+1 718 857 8999",
    "sg:postcode":"11217",
    "sg:province":"NY",
    "wof:name":"Dawson Richard W Atty",
    "wof:placetype":"venue"
},
  "geometry": {"coordinates":[-73.97989699999999,40.680099],"type":"Point"}
}