{
  "type": "Feature",
  "properties": {
    "addr:full":"1427 Forest Ave Staten Island NY 10302",
    "addr:housenumber":"1427",
    "addr:postcode":"10302",
    "addr:street":"Forest Ave",
    "iso:country":"US",
    "sg:address":"1427 Forest Ave",
    "sg:city":"Staten Island",
    "sg:classifiers":[
        {
            "category":"Shopping",
            "subcategory":"Clothing, Apparel, & Fashions",
            "type":"Retail Goods"
        }
    ],
    "sg:phone":"+1 718 420 6216",
    "sg:postcode":"10302",
    "sg:province":"NY",
    "sg:tags":[
        "infant",
        "wear"
    ],
    "wof:name":"Yohngema's Elegant Treasures",
    "wof:placetype":"venue"
},
  "geometry": {"coordinates":[-74.137197,40.624407],"type":"Point"}
}