{
  "type": "Feature",
  "properties": {
    "iso:country":"US",
    "sg:address":"4547 Brickyard Falls Rd",
    "sg:city":"Manlius",
    "sg:classifiers":[
        {
            "category":"Banks & Credit Unions",
            "subcategory":"Investment Brokerage",
            "type":"Services"
        }
    ],
    "sg:phone":"+1 315 682 2168",
    "sg:postcode":"13104",
    "sg:province":"NY",
    "sg:tags":[
        "advisory",
        "financial"
    ],
    "wof:name":"Kenneth Walcyk",
    "wof:placetype":"venue"
},
  "geometry": {"coordinates":[-75.98406199999999,42.990318],"type":"Point"}
}