{
  "type": "Feature",
  "properties": {
    "addr:full":"172 Herricks Rd Mineola NY 11501",
    "addr:housenumber":"172",
    "addr:postcode":"11501",
    "addr:street":"Herricks Rd",
    "iso:country":"US",
    "sg:address":"172 Herricks Rd",
    "sg:city":"Mineola",
    "sg:classifiers":[
        {
            "category":"Wholesale",
            "subcategory":"Hardware",
            "type":"Manufacturing & Wholesale Goods"
        }
    ],
    "sg:phone":"+1 516 873 8295",
    "sg:postcode":"11501",
    "sg:province":"NY",
    "sg:tags":[
        "steel",
        "machine",
        "saw",
        "bi"
    ],
    "wof:name":"Chang Xing Enterprises USA",
    "wof:placetype":"venue"
},
  "geometry": {"coordinates":[-73.654614,40.741075],"type":"Point"}
}