{
  "type": "Feature",
  "properties": {
    "iso:country":"US",
    "sg:address":"126 Pine Woods Rd",
    "sg:city":"Melrose",
    "sg:classifiers":[
        {
            "category":"Building & Trades",
            "subcategory":"Construction",
            "type":"Services"
        }
    ],
    "sg:phone":"+1 518 238 0741",
    "sg:postcode":"12121",
    "sg:province":"NY",
    "sg:tags":[
        "house"
    ],
    "wof:name":"Oaklane Construction",
    "wof:placetype":"venue"
},
  "geometry": {"coordinates":[-73.62694,42.845936],"type":"Point"}
}