{
  "type": "Feature",
  "properties": {
    "iso:country":"US",
    "sg:address":"21 Palisade Ave",
    "sg:city":"Yonkers",
    "sg:classifiers":[
        {
            "category":"Personal",
            "subcategory":"Beauty Salon",
            "type":"Services"
        }
    ],
    "sg:phone":"+1 914 965 6613",
    "sg:postcode":"10701",
    "sg:province":"NY",
    "wof:name":"Roots Hair Braiding",
    "wof:placetype":"venue"
},
  "geometry": {"coordinates":[-73.89600799999999,40.934487],"type":"Point"}
}