{
  "type": "Feature",
  "properties": {
    "addr:full":"34 Lamar St West Babylon NY 11704",
    "addr:housenumber":"34",
    "addr:postcode":"11704",
    "addr:street":"Lamar St",
    "iso:country":"US",
    "sg:address":"34 Lamar St",
    "sg:city":"West Babylon",
    "sg:classifiers":[
        {
            "category":"Real Estate",
            "subcategory":"Real Estate Operator",
            "type":"Services"
        }
    ],
    "sg:phone":"+1 516 643 5000",
    "sg:postcode":"11704",
    "sg:province":"NY",
    "sg:tags":[
        "building"
    ],
    "wof:name":"Edison Realty",
    "wof:placetype":"venue"
},
  "geometry": {"coordinates":[-73.377133,40.734373],"type":"Point"}
}