{
  "type": "Feature",
  "properties": {
    "addr:full":"611 2nd Avenue New York NY 10016",
    "addr:housenumber":"611",
    "addr:postcode":"10016",
    "addr:street":"2Nd Avenue",
    "iso:country":"US",
    "sg:address":"611 2nd Avenue",
    "sg:city":"New York",
    "sg:classifiers":[
        {
            "category":"Bars & Pubs",
            "type":"Food & Drink"
        }
    ],
    "sg:phone":"+1 212 213 5034",
    "sg:postcode":"10016",
    "sg:province":"NY",
    "wof:name":"The Hook & Ladder Pub",
    "wof:placetype":"venue"
},
  "geometry": {"coordinates":[-73.976303,40.744499],"type":"Point"}
}