{
  "type": "Feature",
  "properties": {
    "addr:full":"4064 White Plains Rd Bronx NY 10466",
    "addr:housenumber":"4064",
    "addr:postcode":"10466",
    "addr:street":"White Plains Rd",
    "iso:country":"US",
    "sg:address":"4064 White Plains Rd",
    "sg:city":"Bronx",
    "sg:classifiers":[
        {
            "category":"Personal",
            "subcategory":"Beauty Salon",
            "type":"Services"
        }
    ],
    "sg:phone":"+1   ",
    "sg:postcode":"10466",
    "sg:province":"NY",
    "sg:tags":[
        "shop"
    ],
    "wof:name":"Lamine Doukoure",
    "wof:placetype":"venue"
},
  "geometry": {"coordinates":[-73.858925,40.890396],"type":"Point"}
}