{
  "type": "Feature",
  "properties": {
    "addr:full":"457 Walt Whitman Rd Melville NY 11747",
    "addr:housenumber":"457",
    "addr:postcode":"11747",
    "addr:street":"Walt Whitman Rd",
    "iso:country":"US",
    "sg:address":"457 Walt Whitman Rd",
    "sg:city":"Melville",
    "sg:classifiers":[
        {
            "category":"Food & Beverages",
            "subcategory":"Candy",
            "type":"Retail Goods"
        },
        {
            "category":"Travel",
            "subcategory":"Campground",
            "type":"Entertainment"
        }
    ],
    "sg:phone":"+1 631 351 1638",
    "sg:postcode":"11747",
    "sg:province":"NY",
    "sg:tags":[
        "fruit",
        "nut",
        "camp",
        "gift"
    ],
    "wof:name":"Ralph Rotten's Nut Pound",
    "wof:placetype":"venue"
},
  "geometry": {"coordinates":[-73.40954600000001,40.810556],"type":"Point"}
}