{
  "type": "Feature",
  "properties": {
    "addr:full":"290 Madison Ave Manhattan NY 10017",
    "addr:housenumber":"290",
    "addr:postcode":"10017",
    "addr:street":"Madison Ave",
    "iso:country":"US",
    "sg:address":"290 Madison Ave",
    "sg:city":"Manhattan",
    "sg:classifiers":[
        {
            "category":"Personal",
            "subcategory":"Beauty Salon",
            "type":"Services"
        }
    ],
    "sg:phone":"+1 212 683 2719",
    "sg:postcode":"10017",
    "sg:province":"NY",
    "sg:tags":[
        "makeup",
        "artist"
    ],
    "sg:website":"www.nocturnellebeauty.com",
    "wof:name":"Nocturnelle Beauty Makeup Studio",
    "wof:placetype":"venue"
},
  "geometry": {"coordinates":[-73.980208,40.751801],"type":"Point"}
}