{
  "type": "Feature",
  "properties": {
    "iso:country":"US",
    "sg:address":"1099 Alhambra Rd",
    "sg:city":"Baldwin",
    "sg:classifiers":[
        {
            "category":"Organizations",
            "subcategory":"Membership Organization",
            "type":"Services"
        }
    ],
    "sg:phone":"+1   ",
    "sg:postcode":"11510",
    "sg:province":"NY",
    "wof:name":"Lemar Automobile Inc",
    "wof:placetype":"venue"
},
  "geometry": {"coordinates":[-73.599541,40.678576],"type":"Point"}
}