{
  "type": "Feature",
  "properties": {
    "iso:country":"US",
    "sg:address":"55 Hoffman St",
    "sg:city":"Elmira",
    "sg:classifiers":[
        {
            "category":"Wholesale",
            "subcategory":"Vending Machines",
            "type":"Manufacturing & Wholesale Goods"
        }
    ],
    "sg:phone":"+1   ",
    "sg:postcode":"14905",
    "sg:province":"NY",
    "sg:tags":[
        "operator"
    ],
    "wof:name":"A Plus Vending",
    "wof:placetype":"venue"
},
  "geometry": {"coordinates":[-76.82179499999999,42.083402],"type":"Point"}
}