{
  "type": "Feature",
  "properties": {
    "addr:full":"369 Dewitt Mills Rd Kingston NY 12401",
    "addr:housenumber":"369",
    "addr:postcode":"12401",
    "addr:street":"Dewitt Mills Rd",
    "iso:country":"US",
    "sg:address":"369 Dewitt Mills Rd",
    "sg:city":"Kingston",
    "sg:classifiers":[
        {
            "category":"Social Services",
            "type":"Services"
        }
    ],
    "sg:phone":"+1 845 338 4815",
    "sg:postcode":"12401",
    "sg:province":"NY",
    "sg:tags":[
        "care",
        "center",
        "day"
    ],
    "wof:name":"Hurley Child Care",
    "wof:placetype":"venue"
},
  "geometry": {"coordinates":[-74.047982,41.896914],"type":"Point"}
}