{
  "type": "Feature",
  "properties": {
    "addr:full":"1274 51st St Brooklyn NY 11219",
    "addr:housenumber":"1274",
    "addr:postcode":"11219",
    "addr:street":"51St St",
    "iso:country":"US",
    "sg:address":"1274 51st St",
    "sg:city":"Brooklyn",
    "sg:classifiers":[
        {
            "category":"Shopping",
            "subcategory":"Clothing, Apparel, & Fashions",
            "type":"Retail Goods"
        }
    ],
    "sg:phone":"+1   ",
    "sg:postcode":"11219",
    "sg:province":"NY",
    "sg:tags":[
        "small",
        "electronics"
    ],
    "wof:name":"All In One",
    "wof:placetype":"venue"
},
  "geometry": {"coordinates":[-73.994167,40.634511],"type":"Point"}
}