{
  "type": "Feature",
  "properties": {
    "iso:country":"US",
    "sg:address":"2911 Sullivan Pl",
    "sg:city":"Bronx",
    "sg:classifiers":[
        {
            "category":"Wholesale",
            "subcategory":"Electrical",
            "type":"Manufacturing & Wholesale Goods"
        }
    ],
    "sg:phone":"+1 718 409 3712",
    "sg:postcode":"10465",
    "sg:province":"NY",
    "sg:tags":[
        "control",
        "security",
        "system"
    ],
    "wof:name":"Labco Securities",
    "wof:placetype":"venue"
},
  "geometry": {"coordinates":[-73.823577,40.829673],"type":"Point"}
}