{
  "type": "Feature",
  "properties": {
    "iso:country":"US",
    "sg:address":"2817 31st St",
    "sg:city":"Astoria",
    "sg:classifiers":[
        {
            "category":"Building & Trades",
            "subcategory":"Electrical",
            "type":"Services"
        }
    ],
    "sg:phone":"+1 718 721 9500",
    "sg:postcode":"11102",
    "sg:province":"NY",
    "sg:tags":[
        "electrician"
    ],
    "wof:name":"Levis Electric",
    "wof:placetype":"venue"
},
  "geometry": {"coordinates":[-73.920303,40.768002],"type":"Point"}
}