{
  "type": "Feature",
  "properties": {
    "addr:full":"233 W 14th Street New York NY 10011",
    "addr:housenumber":"233",
    "addr:postcode":"10011",
    "addr:street":"W 14Th Street",
    "iso:country":"US",
    "sg:address":"233 W 14th Street",
    "sg:city":"New York",
    "sg:classifiers":[
        {
            "category":"Health Services",
            "subcategory":"Doctor",
            "type":"Services"
        }
    ],
    "sg:phone":"+1 212 242 1970",
    "sg:postcode":"10011",
    "sg:province":"NY",
    "wof:name":"Affiliated Foot Group",
    "wof:placetype":"venue"
},
  "geometry": {"coordinates":[-74.000575,40.738971],"type":"Point"}
}