{
  "type": "Feature",
  "properties": {
    "addr:full":"155 Knickerbocker Ave Bohemia NY 11716",
    "addr:housenumber":"155",
    "addr:postcode":"11716",
    "addr:street":"Knickerbocker Ave",
    "iso:country":"US",
    "sg:address":"155 Knickerbocker Ave",
    "sg:city":"Bohemia",
    "sg:classifiers":[
        {
            "category":"Wholesale",
            "subcategory":"Medical Equipment & Supplies",
            "type":"Manufacturing & Wholesale Goods"
        }
    ],
    "sg:phone":"+1 631 218 2850",
    "sg:postcode":"11716",
    "sg:province":"NY",
    "sg:tags":[
        "veterinary"
    ],
    "wof:name":"American Veterinary Supply",
    "wof:placetype":"venue"
},
  "geometry": {"coordinates":[-73.08709899999999,40.773944],"type":"Point"}
}