{
  "type": "Feature",
  "properties": {
    "addr:full":"1666 Bathgate Avenue Bronx NY 10457",
    "addr:housenumber":"1666",
    "addr:postcode":"10457",
    "addr:street":"Bathgate Avenue",
    "iso:country":"US",
    "sg:address":"1666 Bathgate Avenue",
    "sg:city":"Bronx",
    "sg:classifiers":[
        {
            "category":"Education",
            "subcategory":"School",
            "type":"Public Place"
        }
    ],
    "sg:phone":"+1 718 530 7000",
    "sg:postcode":"10457",
    "sg:province":"NY",
    "wof:name":"Educational Opportunity Center of the Bronx",
    "wof:placetype":"venue"
},
  "geometry": {"coordinates":[-73.90092,40.839938],"type":"Point"}
}