{
  "type": "Feature",
  "properties": {
    "addr:full":"111 Prince St New York NY 10012",
    "addr:housenumber":"111",
    "addr:postcode":"10012",
    "addr:street":"Prince St",
    "iso:country":"US",
    "sg:address":"111 Prince St",
    "sg:city":"New York",
    "sg:classifiers":[
        {
            "category":"Retail",
            "subcategory":"Auto Repair",
            "type":"Services"
        }
    ],
    "sg:phone":"+1 917 522 2158",
    "sg:postcode":"10012",
    "sg:province":"NY",
    "wof:name":"Gwb Towing & Auto Repair",
    "wof:placetype":"venue"
},
  "geometry": {"coordinates":[-73.99971600000001,40.725054],"type":"Point"}
}