{
  "type": "Feature",
  "properties": {
    "addr:full":"204 Spackenkill Rd Poughkeepsie NY 12603",
    "addr:housenumber":"204",
    "addr:postcode":"12603",
    "addr:street":"Spackenkill Rd",
    "iso:country":"US",
    "sg:address":"204 Spackenkill Rd",
    "sg:city":"Poughkeepsie",
    "sg:classifiers":[
        {
            "category":"Organizations",
            "subcategory":"Religious Organization",
            "type":"Services"
        }
    ],
    "sg:phone":"+1 845 462 2470",
    "sg:postcode":"12603",
    "sg:province":"NY",
    "sg:tags":[
        "church"
    ],
    "sg:website":"www.lds.org",
    "wof:name":"Church Of Jesus Christ Of Lds",
    "wof:placetype":"venue"
},
  "geometry": {"coordinates":[-73.901276,41.658735],"type":"Point"}
}