{
  "type": "Feature",
  "properties": {
    "addr:full":"109 Governors Isl New York NY 10001",
    "addr:housenumber":"109",
    "addr:postcode":"10001",
    "addr:street":"Governors Isl",
    "iso:country":"US",
    "sg:address":"109 Governors Isl",
    "sg:city":"New York",
    "sg:classifiers":[
        {
            "category":"Building & Trades",
            "subcategory":"Construction",
            "type":"Services"
        }
    ],
    "sg:phone":"+1 212 809 2580",
    "sg:postcode":"10001",
    "sg:province":"NY",
    "sg:tags":[
        "contractor"
    ],
    "wof:name":"Turner Construction",
    "wof:placetype":"venue"
},
  "geometry": {"coordinates":[-73.996213,40.750051],"type":"Point"}
}