{
  "type": "Feature",
  "properties": {
    "addr:full":"89 Lexington Ave Westbury NY 11590",
    "addr:housenumber":"89",
    "addr:postcode":"11590",
    "addr:street":"Lexington Ave",
    "iso:country":"US",
    "sg:address":"89 Lexington Ave",
    "sg:city":"Westbury",
    "sg:classifiers":[
        {
            "category":"Banks & Credit Unions",
            "subcategory":"Financial Services",
            "type":"Services"
        }
    ],
    "sg:phone":"+1 516 280 5521",
    "sg:postcode":"11590",
    "sg:province":"NY",
    "sg:tags":[
        "broker",
        "mortgage"
    ],
    "wof:name":"Custom Captial Corp",
    "wof:placetype":"venue"
},
  "geometry": {"coordinates":[-73.589201,40.751437],"type":"Point"}
}