{
  "type": "Feature",
  "properties": {
    "addr:full":"1353 3rd Avenue New York NY 10021",
    "addr:housenumber":"1353",
    "addr:postcode":"10021",
    "addr:street":"3Rd Avenue",
    "iso:country":"US",
    "sg:address":"1353 3rd Avenue",
    "sg:city":"New York",
    "sg:classifiers":[
        {
            "category":"Health Services",
            "subcategory":"Optometrist",
            "type":"Services"
        },
        {
            "category":"Shopping",
            "subcategory":"Optician",
            "type":"Retail Goods"
        }
    ],
    "sg:phone":"+1 212 249 6365",
    "sg:postcode":"10021",
    "sg:province":"NY",
    "sg:tags":[
        "eyewear"
    ],
    "wof:name":"Ziama Opticians",
    "wof:placetype":"venue"
},
  "geometry": {"coordinates":[-73.958304,40.773091],"type":"Point"}
}