{
  "type": "Feature",
  "properties": {
    "iso:country":"US",
    "sg:address":"41 E Main St",
    "sg:city":"Springville",
    "sg:classifiers":[
        {
            "category":"Organizations",
            "subcategory":"Community Association",
            "type":"Services"
        }
    ],
    "sg:phone":"+1 716 592 3838",
    "sg:postcode":"14141",
    "sg:province":"NY",
    "sg:tags":[
        "club"
    ],
    "wof:name":"Boys & Girls Club Of Sp",
    "wof:placetype":"venue"
},
  "geometry": {"coordinates":[-78.67000899999999,42.508648],"type":"Point"}
}