{
  "type": "Feature",
  "properties": {
    "addr:full":"261 W 35th St Ste 501 New York NY 10001",
    "addr:housenumber":"261;501",
    "addr:postcode":"10001",
    "addr:street":"W 35Th St Ste",
    "iso:country":"US",
    "sg:address":"261 W 35th St Ste 501",
    "sg:city":"New York",
    "sg:classifiers":[
        {
            "category":"Professional",
            "subcategory":"Printing & Photocopies",
            "type":"Services"
        }
    ],
    "sg:phone":"+1 212 290 7660",
    "sg:postcode":"10001",
    "sg:province":"NY",
    "wof:name":"Parrot Color Copy Center",
    "wof:placetype":"venue"
},
  "geometry": {"coordinates":[-73.991997,40.752499],"type":"Point"}
}