{
  "type": "Feature",
  "properties": {
    "addr:full":"37 Sweet Rd Gansevoort NY 12831",
    "addr:housenumber":"37",
    "addr:postcode":"12831",
    "addr:street":"Sweet Rd",
    "iso:country":"US",
    "sg:address":"37 Sweet Rd",
    "sg:city":"Gansevoort",
    "sg:classifiers":[
        {
            "category":"Building & Trades",
            "subcategory":"Construction",
            "type":"Services"
        }
    ],
    "sg:phone":"+1 518 793 3291",
    "sg:postcode":"12831",
    "sg:province":"NY",
    "sg:tags":[
        "excavation",
        "contractor"
    ],
    "wof:name":"A & D Excavating",
    "wof:placetype":"venue"
},
  "geometry": {"coordinates":[-73.64133,43.241295],"type":"Point"}
}