{
  "type": "Feature",
  "properties": {
    "addr:full":"84 Westchester Dr Rocky Point NY 11778",
    "addr:housenumber":"84",
    "addr:postcode":"11778",
    "addr:street":"Westchester Dr",
    "iso:country":"US",
    "sg:address":"84 Westchester Dr",
    "sg:city":"Rocky Point",
    "sg:classifiers":[
        {
            "category":"Health Services",
            "subcategory":"Chiropractor",
            "type":"Services"
        }
    ],
    "sg:phone":"+1 631 744 6672",
    "sg:postcode":"11778",
    "sg:province":"NY",
    "wof:name":"Connetquot Chiropractic Ctr",
    "wof:placetype":"venue"
},
  "geometry": {"coordinates":[-72.960404,40.961313],"type":"Point"}
}