{
  "type": "Feature",
  "properties": {
    "iso:country":"US",
    "sg:address":"110 W Lake Rd",
    "sg:city":"Penn Yan",
    "sg:classifiers":[
        {
            "category":"Manufacturing",
            "subcategory":"Tools & Machinery",
            "type":"Manufacturing & Wholesale Goods"
        }
    ],
    "sg:phone":"+1   ",
    "sg:postcode":"14527",
    "sg:province":"NY",
    "sg:tags":[
        "industrial",
        "mfg"
    ],
    "wof:name":"Weichenthal Machine & Repair",
    "wof:placetype":"venue"
},
  "geometry": {"coordinates":[-77.080003,42.64881],"type":"Point"}
}