{
  "type": "Feature",
  "properties": {
    "addr:full":"651 E 183rd St Bronx NY 10458",
    "addr:housenumber":"651",
    "addr:postcode":"10458",
    "addr:street":"E 183Rd St",
    "iso:country":"US",
    "sg:address":"651 E 183rd St",
    "sg:city":"Bronx",
    "sg:classifiers":[
        {
            "category":"Professional",
            "type":"Services"
        }
    ],
    "sg:phone":"+1 718 933 1354",
    "sg:postcode":"10458",
    "sg:province":"NY",
    "wof:name":"International Merchant Svc",
    "wof:placetype":"venue"
},
  "geometry": {"coordinates":[-73.887608,40.852715],"type":"Point"}
}