{
  "type": "Feature",
  "properties": {
    "addr:full":"16 Bedford Rd Chappaqua NY 10514",
    "addr:housenumber":"16",
    "addr:postcode":"10514",
    "addr:street":"Bedford Rd",
    "iso:country":"US",
    "sg:address":"16 Bedford Rd",
    "sg:city":"Chappaqua",
    "sg:classifiers":[
        {
            "category":"Real Estate",
            "subcategory":"Real Estate Agent",
            "type":"Services"
        }
    ],
    "sg:phone":"+1 914 238 6186",
    "sg:postcode":"10514",
    "sg:province":"NY",
    "wof:name":"Valentina Realty LLC",
    "wof:placetype":"venue"
},
  "geometry": {"coordinates":[-73.76540199999999,41.158217],"type":"Point"}
}