{
  "type": "Feature",
  "properties": {
    "iso:country":"US",
    "sg:address":"610 Merrick Rd",
    "sg:city":"Lynbrook",
    "sg:classifiers":[
        {
            "category":"Wholesale",
            "subcategory":"Electrical",
            "type":"Manufacturing & Wholesale Goods"
        }
    ],
    "sg:phone":"+1 516 593 5399",
    "sg:postcode":"11563",
    "sg:province":"NY",
    "sg:tags":[
        "control",
        "security",
        "system"
    ],
    "wof:name":"Security Protection Tech Corp",
    "wof:placetype":"venue"
},
  "geometry": {"coordinates":[-73.68571900000001,40.661032],"type":"Point"}
}