{
  "type": "Feature",
  "properties": {
    "addr:full":"2695 Cedar Ct Oceanside NY 11572",
    "addr:housenumber":"2695",
    "addr:postcode":"11572",
    "addr:street":"Cedar Ct",
    "iso:country":"US",
    "sg:address":"2695 Cedar Ct",
    "sg:city":"Oceanside",
    "sg:classifiers":[
        {
            "category":"Building & Trades",
            "subcategory":"Landscaping Services",
            "type":"Services"
        }
    ],
    "sg:phone":"+1 516 599 0794",
    "sg:postcode":"11572",
    "sg:province":"NY",
    "wof:name":"Howards Tree Service Inc",
    "wof:placetype":"venue"
},
  "geometry": {"coordinates":[-73.650723,40.644371],"type":"Point"}
}