{
  "type": "Feature",
  "properties": {
    "iso:country":"US",
    "sg:address":"1460 French Rd",
    "sg:city":"Depew",
    "sg:classifiers":[
        {
            "category":"Retail",
            "subcategory":"Auto Repair",
            "type":"Services"
        }
    ],
    "sg:phone":"+1 716 656 8537",
    "sg:postcode":"14227",
    "sg:province":"NY",
    "sg:tags":[
        "repairing",
        "automobile"
    ],
    "wof:name":"Midas Auto Svc Experts",
    "wof:placetype":"venue"
},
  "geometry": {"coordinates":[-78.69923799999999,42.868048],"type":"Point"}
}