{
  "type": "Feature",
  "properties": {
    "addr:full":"36 East 12th Street New York NY 10003",
    "addr:housenumber":"36",
    "addr:postcode":"10003",
    "addr:street":"East 12Th Street",
    "iso:country":"US",
    "sg:address":"36 East 12th Street",
    "sg:city":"New York",
    "sg:classifiers":[
        {
            "category":"Professional",
            "subcategory":"Computer Services",
            "type":"Services"
        }
    ],
    "sg:postcode":"10003",
    "sg:province":"NY",
    "sg:tags":[
        "barcodes",
        "mobile",
        "objects",
        "tagging"
    ],
    "sg:website":"http://www.stickybits.com/",
    "wof:name":"Stickybits",
    "wof:placetype":"venue"
},
  "geometry": {"coordinates":[-73.99125600000001,40.733207],"type":"Point"}
}