{
  "type": "Feature",
  "properties": {
    "iso:country":"US",
    "sg:address":"21 Plant St",
    "sg:city":"Southampton",
    "sg:classifiers":[
        {
            "category":"Retail",
            "subcategory":"Auto Repair",
            "type":"Services"
        }
    ],
    "sg:phone":"+1 631 283 9409",
    "sg:postcode":"11968",
    "sg:province":"NY",
    "sg:tags":[
        "body",
        "automobile",
        "painting"
    ],
    "wof:name":"Vav Classics",
    "wof:placetype":"venue"
},
  "geometry": {"coordinates":[-72.385064,40.896122],"type":"Point"}
}