{
  "type": "Feature",
  "properties": {
    "iso:country":"US",
    "sg:address":"6625 Maurice Ave",
    "sg:city":"Woodside",
    "sg:classifiers":[
        {
            "category":"Health Services",
            "subcategory":"Dentist",
            "type":"Services"
        }
    ],
    "sg:phone":"+1 718 651 5941",
    "sg:postcode":"11377",
    "sg:province":"NY",
    "wof:name":"Carrasquillo Jeffrey DMD",
    "wof:placetype":"venue"
},
  "geometry": {"coordinates":[-73.897903,40.735298],"type":"Point"}
}