{
  "type": "Feature",
  "properties": {
    "iso:country":"US",
    "sg:address":"157 Liberty St",
    "sg:city":"Newburgh",
    "sg:classifiers":[
        {
            "category":"Organizations",
            "subcategory":"Religious Organization",
            "type":"Services"
        }
    ],
    "sg:phone":"+1 845 561 4354",
    "sg:postcode":"12550",
    "sg:province":"NY",
    "sg:tags":[
        "church"
    ],
    "wof:name":"Centro Catolico Hispano",
    "wof:placetype":"venue"
},
  "geometry": {"coordinates":[-74.010637,41.507633],"type":"Point"}
}