{
  "type": "Feature",
  "properties": {
    "addr:full":"1 Cross Island Pkwy Jamaica NY 11426",
    "addr:housenumber":"1",
    "addr:postcode":"11426",
    "addr:street":"Cross Island Pkwy",
    "iso:country":"US",
    "sg:address":"1 Cross Island Pkwy",
    "sg:city":"Jamaica",
    "sg:classifiers":[
        {
            "category":"Building & Trades",
            "subcategory":"Construction",
            "type":"Services"
        }
    ],
    "sg:phone":"+1 718 978 7147",
    "sg:postcode":"11426",
    "sg:province":"NY",
    "sg:tags":[
        "general",
        "contractor"
    ],
    "wof:name":"Stoneridge Homes",
    "wof:placetype":"venue"
},
  "geometry": {"coordinates":[-73.72489,40.739566],"type":"Point"}
}