{
  "type": "Feature",
  "properties": {
    "addr:full":"207 W 11 St New York NY 10014",
    "addr:housenumber":"207",
    "addr:postcode":"10014",
    "addr:street":"W 11 St",
    "iso:country":"US",
    "sg:address":"207 W 11 St",
    "sg:city":"New York",
    "sg:classifiers":[
        {
            "category":"Professional",
            "subcategory":"Computer Services",
            "type":"Services"
        }
    ],
    "sg:phone":"+1 212 334 0385",
    "sg:postcode":"10014",
    "sg:province":"NY",
    "sg:tags":[
        "website",
        "design"
    ],
    "wof:name":"DNA Studio",
    "wof:placetype":"venue"
},
  "geometry": {"coordinates":[-74.00177100000001,40.736532],"type":"Point"}
}