{
  "type": "Feature",
  "properties": {
    "iso:country":"US",
    "sg:address":"43 Lake Ave",
    "sg:city":"Binghamton",
    "sg:classifiers":[
        {
            "category":"Building & Trades",
            "subcategory":"Plumbing",
            "type":"Services"
        }
    ],
    "sg:phone":"+1 607 729 6800",
    "sg:postcode":"13905",
    "sg:province":"NY",
    "sg:tags":[
        "conditioning",
        "air",
        "system",
        "contractor"
    ],
    "sg:website":"www.suretemp.com",
    "wof:name":"Sure Temp Co Inc",
    "wof:placetype":"venue"
},
  "geometry": {"coordinates":[-75.94235500000001,42.113047],"type":"Point"}
}