{
  "type": "Feature",
  "properties": {
    "addr:full":"485 5th Ave New York NY 10017",
    "addr:housenumber":"485",
    "addr:postcode":"10017",
    "addr:street":"5Th Ave",
    "iso:country":"US",
    "sg:address":"485 5th Ave",
    "sg:city":"New York",
    "sg:classifiers":[
        {
            "category":"Manufacturing",
            "subcategory":"Textiles",
            "type":"Manufacturing & Wholesale Goods"
        }
    ],
    "sg:phone":"+1   ",
    "sg:postcode":"10017",
    "sg:province":"NY",
    "sg:tags":[
        "mfg"
    ],
    "wof:name":"Novel Denim Holding LTD",
    "wof:placetype":"venue"
},
  "geometry": {"coordinates":[-73.981534,40.752366],"type":"Point"}
}