{
  "type": "Feature",
  "properties": {
    "iso:country":"US",
    "sg:address":"2065 Harlem Rd",
    "sg:city":"Buffalo",
    "sg:classifiers":[
        {
            "category":"Wholesale",
            "subcategory":"Machinery & Supplies",
            "type":"Manufacturing & Wholesale Goods"
        }
    ],
    "sg:phone":"+1 716 895 7800",
    "sg:postcode":"14206",
    "sg:province":"NY",
    "sg:tags":[
        "equipment",
        "material",
        "handling"
    ],
    "wof:name":"Halsey-Reid Equipment Inc",
    "wof:placetype":"venue"
},
  "geometry": {"coordinates":[-78.784226,42.899399],"type":"Point"}
}