{
  "type": "Feature",
  "properties": {
    "addr:full":"515 Madison Ave Rm 1218 New York NY 10022",
    "addr:housenumber":"515;1218",
    "addr:postcode":"10022",
    "addr:street":"Madison Ave Rm",
    "iso:country":"US",
    "sg:address":"515 Madison Ave Rm 1218",
    "sg:city":"New York",
    "sg:classifiers":[
        {
            "category":"Shopping",
            "subcategory":"Jewelry",
            "type":"Retail Goods"
        }
    ],
    "sg:phone":"+1 212 753 4556",
    "sg:postcode":"10022",
    "sg:province":"NY",
    "wof:name":"Lederman Geo",
    "wof:placetype":"venue"
},
  "geometry": {"coordinates":[-73.93104599999999,40.816461],"type":"Point"}
}