{
  "type": "Feature",
  "properties": {
    "iso:country":"US",
    "sg:address":"13 Ingelore Ct",
    "sg:city":"Smithtown",
    "sg:classifiers":[
        {
            "category":"Building & Trades",
            "subcategory":"Construction",
            "type":"Services"
        }
    ],
    "sg:phone":"+1 631 979 8231",
    "sg:postcode":"11787",
    "sg:province":"NY",
    "sg:tags":[
        "residential"
    ],
    "wof:name":"Landing Home Improvement Inc",
    "wof:placetype":"venue"
},
  "geometry": {"coordinates":[-73.214581,40.865572],"type":"Point"}
}