{
  "type": "Feature",
  "properties": {
    "iso:country":"US",
    "sg:address":"114 W 17 St",
    "sg:city":"New York",
    "sg:classifiers":[
        {
            "category":"Communications",
            "subcategory":"Film & Video Production",
            "type":"Services"
        }
    ],
    "sg:phone":"+1 212 366 0588",
    "sg:postcode":"10011",
    "sg:province":"NY",
    "sg:tags":[
        "editing",
        "tape"
    ],
    "wof:name":"Chelsea Loft Editing",
    "wof:placetype":"venue"
},
  "geometry": {"coordinates":[-73.998015,40.740232],"type":"Point"}
}