{
  "type": "Feature",
  "properties": {
    "addr:full":"122 East 42nd Street Suite 620 New York NY 10018",
    "addr:housenumber":"122;620",
    "addr:postcode":"10018",
    "addr:street":"East 42Nd Street Suite",
    "iso:country":"US",
    "sg:address":"122 East 42nd Street Suite 620",
    "sg:city":"New York",
    "sg:classifiers":[
        {
            "category":"Professional",
            "subcategory":"Advertising",
            "type":"Services"
        }
    ],
    "sg:phone":"+1 646 367 5300",
    "sg:postcode":"10018",
    "sg:province":"NY",
    "sg:website":"http://www.adspacenetworks.com/index2.php",
    "wof:name":"Adspace Networks",
    "wof:placetype":"venue"
},
  "geometry": {"coordinates":[-73.976714,40.751723],"type":"Point"}
}