{
  "type": "Feature",
  "properties": {
    "iso:country":"US",
    "sg:address":"807 Albany St",
    "sg:city":"Schenectady",
    "sg:classifiers":[
        {
            "category":"Food & Beverages",
            "subcategory":"Fruits & Vegetables",
            "type":"Retail Goods"
        }
    ],
    "sg:phone":"+1 518 372 2282",
    "sg:postcode":"12307",
    "sg:province":"NY",
    "sg:tags":[
        "produce"
    ],
    "wof:name":"Roy Fresh & Frozen Produce",
    "wof:placetype":"venue"
},
  "geometry": {"coordinates":[-73.935596,42.806414],"type":"Point"}
}