{
  "type": "Feature",
  "properties": {
    "addr:full":"13 E 47th Street New York NY 10017",
    "addr:housenumber":"13",
    "addr:postcode":"10017",
    "addr:street":"E 47Th Street",
    "iso:country":"US",
    "sg:address":"13 E 47th Street",
    "sg:city":"New York",
    "sg:classifiers":[
        {
            "category":"Real Estate",
            "subcategory":"Architect",
            "type":"Services"
        }
    ],
    "sg:phone":"+1 212 980 9530",
    "sg:postcode":"10017",
    "sg:province":"NY",
    "wof:name":"Terzis Costas",
    "wof:placetype":"venue"
},
  "geometry": {"coordinates":[-73.977895,40.756412],"type":"Point"}
}