{
  "type": "Feature",
  "properties": {
    "iso:country":"US",
    "sg:address":"13 E 47th Street",
    "sg:city":"New York",
    "sg:classifiers":[
        {
            "category":"Real Estate",
            "subcategory":"Architect",
            "type":"Services"
        }
    ],
    "sg:phone":"+1 212 980 9530",
    "sg:postcode":"10017",
    "sg:province":"NY",
    "wof:name":"Terzis Costas",
    "wof:placetype":"venue"
},
  "geometry": {"coordinates":[-73.977895,40.756412],"type":"Point"}
}