{
  "type": "Feature",
  "properties": {
    "addr:full":"9 Union Ln Mt Vernon NY 10553",
    "addr:housenumber":"9",
    "addr:postcode":"10553",
    "addr:street":"Union Ln",
    "iso:country":"US",
    "sg:address":"9 Union Ln",
    "sg:city":"Mt Vernon",
    "sg:classifiers":[
        {
            "category":"Health Services",
            "subcategory":"Clinic",
            "type":"Services"
        }
    ],
    "sg:phone":"+1 914 668 6828",
    "sg:postcode":"10553",
    "sg:province":"NY",
    "wof:name":"Mt Vernon Neighborhood Health",
    "wof:placetype":"venue"
},
  "geometry": {"coordinates":[-73.82933199999999,40.903389],"type":"Point"}
}