{
  "type": "Feature",
  "properties": {
    "addr:full":"3 Saint Anthony St Auburn NY 13021",
    "addr:housenumber":"3",
    "addr:postcode":"13021",
    "addr:street":"Saint Anthony St",
    "iso:country":"US",
    "sg:address":"3 Saint Anthony St",
    "sg:city":"Auburn",
    "sg:classifiers":[
        {
            "category":"Health Services",
            "subcategory":"Nursing And Care Facility",
            "type":"Services"
        }
    ],
    "sg:phone":"+1 315 253 0351",
    "sg:postcode":"13021",
    "sg:province":"NY",
    "sg:tags":[
        "home",
        "referral"
    ],
    "wof:name":"Boyd's of Madison Ave",
    "wof:placetype":"venue"
},
  "geometry": {"coordinates":[-76.58057599999999,42.917942],"type":"Point"}
}