{
  "type": "Feature",
  "properties": {
    "iso:country":"US",
    "sg:address":"214 Mill St",
    "sg:city":"Lawrence",
    "sg:classifiers":[
        {
            "category":"Manufacturing",
            "subcategory":"Tools & Machinery",
            "type":"Manufacturing & Wholesale Goods"
        }
    ],
    "sg:phone":"+1   ",
    "sg:postcode":"11559",
    "sg:province":"NY",
    "sg:tags":[
        "industrial",
        "mfg"
    ],
    "wof:name":"Vacstar Machine Products Corp",
    "wof:placetype":"venue"
},
  "geometry": {"coordinates":[-73.736723,40.616697],"type":"Point"}
}