{
  "type": "Feature",
  "properties": {
    "iso:country":"US",
    "sg:address":"178 Broad Ave",
    "sg:city":"Binghamton",
    "sg:classifiers":[
        {
            "category":"Wholesale",
            "subcategory":"Beer",
            "type":"Manufacturing & Wholesale Goods"
        }
    ],
    "sg:phone":"+1 607 723 5315",
    "sg:postcode":"13904",
    "sg:province":"NY",
    "sg:tags":[
        "ale"
    ],
    "wof:name":"Mincolla Distributing Co",
    "wof:placetype":"venue"
},
  "geometry": {"coordinates":[-75.889948,42.118261],"type":"Point"}
}