{
  "type": "Feature",
  "properties": {
    "iso:country":"US",
    "sg:address":"3411 Hampton Rd",
    "sg:city":"Oceanside",
    "sg:classifiers":[
        {
            "category":"Retail",
            "subcategory":"Auto Repair",
            "type":"Services"
        }
    ],
    "sg:phone":"+1 516 764 0110",
    "sg:postcode":"11572",
    "sg:province":"NY",
    "wof:name":"Truck Rentals",
    "wof:placetype":"venue"
},
  "geometry": {"coordinates":[-73.654999,40.6231],"type":"Point"}
}