{
  "type": "Feature",
  "properties": {
    "iso:country":"US",
    "sg:address":"1728 Black River Blvd N",
    "sg:city":"Rome",
    "sg:classifiers":[
        {
            "category":"Utilities",
            "subcategory":"Mobile Phone",
            "type":"Services"
        }
    ],
    "sg:phone":"+1   ",
    "sg:postcode":"13440",
    "sg:province":"NY",
    "sg:tags":[
        "communications",
        "radiotelephone"
    ],
    "wof:name":"Upstate Wireless Inc",
    "wof:placetype":"venue"
},
  "geometry": {"coordinates":[-75.436559,43.238918],"type":"Point"}
}