{
  "type": "Feature",
  "properties": {
    "addr:full":"160 W Main St Catskill NY 12414",
    "addr:housenumber":"160",
    "addr:postcode":"12414",
    "addr:street":"W Main St",
    "iso:country":"US",
    "sg:address":"160 W Main St",
    "sg:city":"Catskill",
    "sg:classifiers":[
        {
            "category":"Restaurant",
            "type":"Food & Drink"
        }
    ],
    "sg:phone":"+1 518 943 6522",
    "sg:postcode":"12414",
    "sg:province":"NY",
    "wof:name":"Creek Side Restaurant",
    "wof:placetype":"venue"
},
  "geometry": {"coordinates":[-73.86599699999999,42.212502],"type":"Point"}
}