{
  "type": "Feature",
  "properties": {
    "addr:full":"41 State Hwy 59 Nyack NY 10960",
    "addr:housenumber":"41",
    "addr:postcode":"10960",
    "addr:street":"State Hwy 59",
    "iso:country":"US",
    "sg:address":"41 State Hwy 59",
    "sg:city":"Nyack",
    "sg:classifiers":[
        {
            "category":"Retail",
            "subcategory":"Repair Shop",
            "type":"Services"
        }
    ],
    "sg:phone":"+1 845 348 9500",
    "sg:postcode":"10960",
    "sg:province":"NY",
    "sg:tags":[
        "cleaners",
        "parts",
        "vacuum"
    ],
    "wof:name":"T W Central Vacuum",
    "wof:placetype":"venue"
},
  "geometry": {"coordinates":[-73.930823,41.092966],"type":"Point"}
}