{
  "type": "Feature",
  "properties": {
    "iso:country":"US",
    "sg:address":"4 Main St",
    "sg:city":"Amagansett",
    "sg:classifiers":[
        {
            "category":"Utilities",
            "subcategory":"Cable",
            "type":"Services"
        }
    ],
    "sg:phone":"+1 631 267 6900",
    "sg:postcode":"11975",
    "sg:province":"NY",
    "sg:tags":[
        "television"
    ],
    "wof:name":"Cablevision",
    "wof:placetype":"venue"
},
  "geometry": {"coordinates":[-72.24458,40.935973],"type":"Point"}
}