{
  "type": "Feature",
  "properties": {
    "iso:country":"US",
    "sg:address":"217 River Ave",
    "sg:city":"Patchogue",
    "sg:classifiers":[
        {
            "category":"Marine",
            "type":"Transportation"
        }
    ],
    "sg:phone":"+1 631 447 1884",
    "sg:postcode":"11772",
    "sg:province":"NY",
    "sg:tags":[
        "salvage"
    ],
    "wof:name":"Anything Marine",
    "wof:placetype":"venue"
},
  "geometry": {"coordinates":[-73.021376,40.757105],"type":"Point"}
}