{
  "type": "Feature",
  "properties": {
    "addr:full":"46 Lee Ave Yonkers NY 10705",
    "addr:housenumber":"46",
    "addr:postcode":"10705",
    "addr:street":"Lee Ave",
    "iso:country":"US",
    "sg:address":"46 Lee Ave",
    "sg:city":"Yonkers",
    "sg:classifiers":[
        {
            "category":"Building & Trades",
            "subcategory":"Construction",
            "type":"Services"
        }
    ],
    "sg:phone":"+1 212 280 6966",
    "sg:postcode":"10705",
    "sg:province":"NY",
    "sg:tags":[
        "contractor"
    ],
    "wof:name":"Bailey Francis",
    "wof:placetype":"venue"
},
  "geometry": {"coordinates":[-73.87981000000001,40.907871],"type":"Point"}
}