{
  "type": "Feature",
  "properties": {
    "addr:full":"133 E 58th Street, #1204 Manhattan NY 10022",
    "addr:housenumber":"133",
    "addr:postcode":"10022",
    "addr:street":"E 58Th Street # 1204",
    "iso:country":"US",
    "sg:address":"133 E 58th Street, #1204",
    "sg:city":"Manhattan",
    "sg:classifiers":[
        {
            "category":"Health Services",
            "subcategory":"Clinic",
            "type":"Services"
        }
    ],
    "sg:phone":"+1 212 588 1500",
    "sg:postcode":"10022",
    "sg:province":"NY",
    "sg:tags":[
        "medical"
    ],
    "wof:name":"Marianna Faber, DDS",
    "wof:placetype":"venue"
},
  "geometry": {"coordinates":[-73.968946,40.761819],"type":"Point"}
}