{
  "type": "Feature",
  "properties": {
    "addr:full":"2300 Crompond Rd Yorktown Heights NY 10598",
    "addr:housenumber":"2300",
    "addr:postcode":"10598",
    "addr:street":"Crompond Rd",
    "iso:country":"US",
    "sg:address":"2300 Crompond Rd",
    "sg:city":"Yorktown Heights",
    "sg:classifiers":[
        {
            "category":"Organizations",
            "subcategory":"Religious Organization",
            "type":"Services"
        }
    ],
    "sg:phone":"+1 914 962 5749",
    "sg:postcode":"10598",
    "sg:province":"NY",
    "sg:tags":[
        "church"
    ],
    "wof:name":"Yorktown United Methodist Chr",
    "wof:placetype":"venue"
},
  "geometry": {"coordinates":[-73.79161499999999,41.280349],"type":"Point"}
}