{
  "type": "Feature",
  "properties": {
    "addr:full":"3767 75th St Jackson Heights NY 11372",
    "addr:housenumber":"3767",
    "addr:postcode":"11372",
    "addr:street":"75Th St",
    "iso:country":"US",
    "sg:address":"3767 75th St",
    "sg:city":"Jackson Heights",
    "sg:classifiers":[
        {
            "category":"Banks & Credit Unions",
            "subcategory":"Bank",
            "type":"Services"
        }
    ],
    "sg:phone":"+1 718 935 9935",
    "sg:postcode":"11372",
    "sg:province":"NY",
    "wof:name":"Chase Manhattan Bank",
    "wof:placetype":"venue"
},
  "geometry": {"coordinates":[-73.89070100000001,40.747398],"type":"Point"}
}