{
  "type": "Feature",
  "properties": {
    "addr:full":"590 E 191st St Bronx NY 10458",
    "addr:housenumber":"590",
    "addr:postcode":"10458",
    "addr:street":"E 191St St",
    "iso:country":"US",
    "sg:address":"590 E 191st St",
    "sg:city":"Bronx",
    "sg:classifiers":[
        {
            "category":"Retail",
            "subcategory":"Repair Shop",
            "type":"Services"
        }
    ],
    "sg:phone":"+1 646 224 1080",
    "sg:postcode":"10458",
    "sg:province":"NY",
    "sg:tags":[
        "lock",
        "locksmith"
    ],
    "wof:name":"USA Locksmiths",
    "wof:placetype":"venue"
},
  "geometry": {"coordinates":[-73.88444200000001,40.858915],"type":"Point"}
}