{
  "type": "Feature",
  "properties": {
    "addr:full":"3312 Pearsall Ave Bronx NY 10469",
    "addr:housenumber":"3312",
    "addr:postcode":"10469",
    "addr:street":"Pearsall Ave",
    "iso:country":"US",
    "sg:address":"3312 Pearsall Ave",
    "sg:city":"Bronx",
    "sg:classifiers":[
        {
            "category":"Freight",
            "type":"Transportation"
        }
    ],
    "sg:phone":"+1   ",
    "sg:postcode":"10469",
    "sg:province":"NY",
    "sg:tags":[
        "operator",
        "local",
        "trucking"
    ],
    "wof:name":"Hdl Trucking Corporation",
    "wof:placetype":"venue"
},
  "geometry": {"coordinates":[-73.851901,40.874011],"type":"Point"}
}