{
  "type": "Feature",
  "properties": {
    "iso:country":"US",
    "sg:address":"445 Broad Hollow Rd",
    "sg:city":"Melville",
    "sg:classifiers":[
        {
            "category":"Travel",
            "subcategory":"Travel Agent",
            "type":"Entertainment"
        }
    ],
    "sg:phone":"+1 631 420 8888",
    "sg:postcode":"11747",
    "sg:province":"NY",
    "sg:tags":[
        "agency",
        "bureau"
    ],
    "wof:name":"Ginko International Inc",
    "wof:placetype":"venue"
},
  "geometry": {"coordinates":[-73.423451,40.765042],"type":"Point"}
}