{
  "type": "Feature",
  "properties": {
    "addr:full":"1721 University Ave Bronx NY 10453",
    "addr:housenumber":"1721",
    "addr:postcode":"10453",
    "addr:street":"University Ave",
    "iso:country":"US",
    "sg:address":"1721 University Ave",
    "sg:city":"Bronx",
    "sg:classifiers":[
        {
            "category":"Shopping",
            "subcategory":"Jewelry",
            "type":"Retail Goods"
        }
    ],
    "sg:phone":"+1   ",
    "sg:postcode":"10453",
    "sg:province":"NY",
    "wof:name":"Veways",
    "wof:placetype":"venue"
},
  "geometry": {"coordinates":[-73.916292,40.849924],"type":"Point"}
}