{
  "type": "Feature",
  "properties": {
    "addr:full":"24 3rd St New Rochelle NY 10801",
    "addr:housenumber":"24",
    "addr:postcode":"10801",
    "addr:street":"3Rd St",
    "iso:country":"US",
    "sg:address":"24 3rd St",
    "sg:city":"New Rochelle",
    "sg:classifiers":[
        {
            "category":"Wholesale",
            "subcategory":"Wine & Distilled Alcoholic Beverages",
            "type":"Manufacturing & Wholesale Goods"
        }
    ],
    "sg:phone":"+1 914 523 3867",
    "sg:postcode":"10801",
    "sg:province":"NY",
    "sg:tags":[
        "waters",
        "imported",
        "mineral"
    ],
    "wof:name":"Sapori Italiani Inc",
    "wof:placetype":"venue"
},
  "geometry": {"coordinates":[-73.79480599999999,40.907513],"type":"Point"}
}