{
  "type": "Feature",
  "properties": {
    "addr:full":"100 College Ave Sleepy Hollow NY 10591",
    "addr:housenumber":"100",
    "addr:postcode":"10591",
    "addr:street":"College Ave",
    "iso:country":"US",
    "sg:address":"100 College Ave",
    "sg:city":"Sleepy Hollow",
    "sg:classifiers":[
        {
            "category":"Real Estate",
            "subcategory":"Real Estate Agent",
            "type":"Services"
        }
    ],
    "sg:phone":"+1 914 332 5554",
    "sg:postcode":"10591",
    "sg:province":"NY",
    "wof:name":"North Tarrytown Realty Assoc",
    "wof:placetype":"venue"
},
  "geometry": {"coordinates":[-73.862673,41.081764],"type":"Point"}
}