{
  "type": "Feature",
  "properties": {
    "addr:full":"62 William St New York NY 10005",
    "addr:housenumber":"62",
    "addr:postcode":"10005",
    "addr:street":"William St",
    "iso:country":"US",
    "sg:address":"62 William St",
    "sg:city":"New York",
    "sg:classifiers":[
        {
            "category":"Banks & Credit Unions",
            "subcategory":"Bank",
            "type":"Services"
        }
    ],
    "sg:phone":"+1 212 825 9000",
    "sg:postcode":"10005",
    "sg:province":"NY",
    "sg:tags":[
        "financing",
        "business",
        "mortgage",
        "loan",
        "real estate",
        "broker"
    ],
    "wof:name":"Kensington Capital Partners Llc",
    "wof:placetype":"venue"
},
  "geometry": {"coordinates":[-74.008904,40.7071],"type":"Point"}
}