{
  "type": "Feature",
  "properties": {
    "iso:country":"US",
    "sg:address":"4234 Vireo Ave",
    "sg:city":"Bronx",
    "sg:classifiers":[
        {
            "category":"Building & Trades",
            "subcategory":"Construction",
            "type":"Services"
        }
    ],
    "sg:phone":"+1 718 324 3643",
    "sg:postcode":"10470",
    "sg:province":"NY",
    "sg:tags":[
        "general",
        "contractor"
    ],
    "wof:name":"James O'Connell & Sons Inc",
    "wof:placetype":"venue"
},
  "geometry": {"coordinates":[-73.864577,40.896152],"type":"Point"}
}