{
  "type": "Feature",
  "properties": {
    "addr:full":"322 Lake Ave Rochester NY 14608",
    "addr:housenumber":"322",
    "addr:postcode":"14608",
    "addr:street":"Lake Ave",
    "iso:country":"US",
    "sg:address":"322 Lake Ave",
    "sg:city":"Rochester",
    "sg:classifiers":[
        {
            "category":"Health Services",
            "subcategory":"Doctor",
            "type":"Services"
        }
    ],
    "sg:phone":"+1 585 254 6480",
    "sg:postcode":"14608",
    "sg:province":"NY",
    "sg:tags":[
        "physician",
        "surgeon"
    ],
    "wof:name":"Westside Health Svc Inc",
    "wof:placetype":"venue"
},
  "geometry": {"coordinates":[-77.62578600000001,43.167623],"type":"Point"}
}