{
  "type": "Feature",
  "properties": {
    "addr:full":"277 E Kingsbridge Road Bronx NY 10458",
    "addr:housenumber":"277",
    "addr:postcode":"10458",
    "addr:street":"E Kingsbridge Road",
    "iso:country":"US",
    "sg:address":"277 E Kingsbridge Road",
    "sg:city":"Bronx",
    "sg:classifiers":[
        {
            "category":"Restaurant",
            "type":"Food & Drink"
        }
    ],
    "sg:phone":"+1 718 295 5588",
    "sg:postcode":"10458",
    "sg:province":"NY",
    "wof:name":"Happy Garden",
    "wof:placetype":"venue"
},
  "geometry": {"coordinates":[-73.894159,40.864213],"type":"Point"}
}