{
  "type": "Feature",
  "properties": {
    "iso:country":"US",
    "sg:address":"10209 Queens Boulevard",
    "sg:city":"Forest Hills",
    "sg:classifiers":[
        {
            "category":"Restaurant",
            "type":"Food & Drink"
        }
    ],
    "sg:phone":"+1 718 896 4411",
    "sg:postcode":"11375",
    "sg:province":"NY",
    "wof:name":"Chop Stick",
    "wof:placetype":"venue"
},
  "geometry": {"coordinates":[-73.851029,40.726051],"type":"Point"}
}