{
  "type": "Feature",
  "properties": {
    "iso:country":"US",
    "sg:address":"669 Old Town Rd",
    "sg:city":"Port Jefferson Station",
    "sg:classifiers":[
        {
            "category":"Autos & Motor Vehicles",
            "subcategory":"Fuel & Gas Station",
            "type":"Retail Goods"
        }
    ],
    "sg:phone":"+1 631 331 7435",
    "sg:postcode":"11776",
    "sg:province":"NY",
    "sg:tags":[
        "station",
        "gasoline",
        "oil"
    ],
    "wof:name":"Sunoco",
    "wof:placetype":"venue"
},
  "geometry": {"coordinates":[-73.045446,40.897095],"type":"Point"}
}