{
  "type": "Feature",
  "properties": {
    "addr:full":"464 Main St Port Washington NY 11050",
    "addr:housenumber":"464",
    "addr:postcode":"11050",
    "addr:street":"Main St",
    "iso:country":"US",
    "sg:address":"464 Main St",
    "sg:city":"Port Washington",
    "sg:classifiers":[
        {
            "category":"Real Estate",
            "subcategory":"Real Estate Operator",
            "type":"Services"
        }
    ],
    "sg:phone":"+1 516 944 6808",
    "sg:postcode":"11050",
    "sg:province":"NY",
    "sg:tags":[
        "building",
        "apartment"
    ],
    "wof:name":"Hadley House Apartments",
    "wof:placetype":"venue"
},
  "geometry": {"coordinates":[-73.701401,40.82738],"type":"Point"}
}