{
  "type": "Feature",
  "properties": {
    "addr:full":"127 Pearl St Port Chester NY 10573",
    "addr:housenumber":"127",
    "addr:postcode":"10573",
    "addr:street":"Pearl St",
    "iso:country":"US",
    "sg:address":"127 Pearl St",
    "sg:city":"Port Chester",
    "sg:classifiers":[
        {
            "category":"Building & Trades",
            "subcategory":"Construction",
            "type":"Services"
        }
    ],
    "sg:phone":"+1 914 937 7800",
    "sg:postcode":"10573",
    "sg:province":"NY",
    "sg:tags":[
        "general",
        "contractor"
    ],
    "wof:name":"Estate Services",
    "wof:placetype":"venue"
},
  "geometry": {"coordinates":[-73.66839899999999,40.997738],"type":"Point"}
}