{
  "type": "Feature",
  "properties": {
    "iso:country":"US",
    "sg:address":"827 Park Ave",
    "sg:city":"Huntington",
    "sg:classifiers":[
        {
            "category":"Health Services",
            "subcategory":"Dentist",
            "type":"Services"
        }
    ],
    "sg:phone":"+1 631 423 8212",
    "sg:postcode":"11743",
    "sg:province":"NY",
    "wof:name":"Eric L Tobias D M D P C",
    "wof:placetype":"venue"
},
  "geometry": {"coordinates":[-73.377403,40.8489],"type":"Point"}
}