{
  "type": "Feature",
  "properties": {
    "addr:full":"4312 50th St Woodside NY 11377",
    "addr:housenumber":"4312",
    "addr:postcode":"11377",
    "addr:street":"50Th St",
    "iso:country":"US",
    "sg:address":"4312 50th St",
    "sg:city":"Woodside",
    "sg:classifiers":[
        {
            "category":"Bars & Pubs",
            "subcategory":"Sports Bar",
            "type":"Food & Drink"
        }
    ],
    "sg:phone":"+1 718 507 1660",
    "sg:postcode":"11377",
    "sg:province":"NY",
    "sg:tags":[
        "hall",
        "pool"
    ],
    "wof:name":"Spin City",
    "wof:placetype":"venue"
},
  "geometry": {"coordinates":[-73.914597,40.744499],"type":"Point"}
}