{
  "type": "Feature",
  "properties": {
    "iso:country":"US",
    "sg:address":"240 E Main St",
    "sg:city":"Fredonia",
    "sg:classifiers":[
        {
            "category":"Insurance",
            "subcategory":"Hazard Insurance",
            "type":"Services"
        }
    ],
    "sg:phone":"+1 716 672 6868",
    "sg:postcode":"14063",
    "sg:province":"NY",
    "sg:website":"http://statefarm.mqgroup.com/url.asp?usr=527170",
    "wof:name":"State Farm Insurance Agent-Steve Strothman",
    "wof:placetype":"venue"
},
  "geometry": {"coordinates":[-79.320837,42.445353],"type":"Point"}
}