{
  "type": "Feature",
  "properties": {
    "addr:full":"120 Corporate Woods Rochester NY 14623",
    "addr:housenumber":"120",
    "addr:postcode":"14623",
    "addr:street":"Corporate Woods",
    "iso:country":"US",
    "sg:address":"120 Corporate Woods",
    "sg:city":"Rochester",
    "sg:classifiers":[
        {
            "category":"Insurance",
            "subcategory":"Insurance Agent",
            "type":"Services"
        }
    ],
    "sg:phone":"+1 585 554 4700",
    "sg:postcode":"14623",
    "sg:province":"NY",
    "sg:website":"www.principal.com",
    "wof:name":"Principal Financial Group",
    "wof:placetype":"venue"
},
  "geometry": {"coordinates":[-77.620802,43.107695],"type":"Point"}
}