{
  "type": "Feature",
  "properties": {
    "iso:country":"US",
    "sg:address":"201 Jefferson Ave",
    "sg:city":"Staten Island",
    "sg:classifiers":[
        {
            "category":"Professional",
            "subcategory":"Computer Services",
            "type":"Services"
        }
    ],
    "sg:phone":"+1 718 273 3571",
    "sg:postcode":"10306",
    "sg:province":"NY",
    "sg:tags":[
        "repair"
    ],
    "wof:name":"A Lan Consulting",
    "wof:placetype":"venue"
},
  "geometry": {"coordinates":[-74.099408,40.582237],"type":"Point"}
}