{
  "type": "Feature",
  "properties": {
    "addr:full":"261 5th Avenue New York NY 10016",
    "addr:housenumber":"261",
    "addr:postcode":"10016",
    "addr:street":"5Th Avenue",
    "iso:country":"US",
    "sg:address":"261 5th Avenue",
    "sg:city":"New York",
    "sg:classifiers":[
        {
            "category":"Building & Trades",
            "subcategory":"Construction",
            "type":"Services"
        }
    ],
    "sg:phone":"+1 646 472 0183",
    "sg:postcode":"10016",
    "sg:province":"NY",
    "sg:tags":[
        "interior",
        "design"
    ],
    "wof:name":"India Ink",
    "wof:placetype":"venue"
},
  "geometry": {"coordinates":[-73.986851,40.745182],"type":"Point"}
}