{
  "type": "Feature",
  "properties": {
    "addr:full":"276 Middle Country Rd Middle Island NY 11953",
    "addr:housenumber":"276",
    "addr:postcode":"11953",
    "addr:street":"Middle Country Rd Middle Island",
    "iso:country":"US",
    "sg:address":"276 Middle Country Rd",
    "sg:city":"Middle Island",
    "sg:classifiers":[
        {
            "category":"Restaurant",
            "type":"Food & Drink"
        }
    ],
    "sg:phone":"+1 631 732 1697",
    "sg:postcode":"11953",
    "sg:province":"NY",
    "wof:name":"Country Cottage Diner II",
    "wof:placetype":"venue"
},
  "geometry": {"coordinates":[-72.96460399999999,40.878094],"type":"Point"}
}