{
  "type": "Feature",
  "properties": {
    "iso:country":"US",
    "sg:address":"21 Driftwood Dr",
    "sg:city":"Albany",
    "sg:classifiers":[
        {
            "category":"Professional",
            "type":"Services"
        }
    ],
    "sg:phone":"+1   ",
    "sg:postcode":"12205",
    "sg:province":"NY",
    "wof:name":"Michael J Audi",
    "wof:placetype":"venue"
},
  "geometry": {"coordinates":[-73.788363,42.705145],"type":"Point"}
}