{
  "type": "Feature",
  "properties": {
    "iso:country":"US",
    "sg:address":"939 Broadway",
    "sg:city":"Brooklyn",
    "sg:classifiers":[
        {
            "category":"Bars & Pubs",
            "type":"Food & Drink"
        }
    ],
    "sg:phone":"+1 718 573 7987",
    "sg:postcode":"11206",
    "sg:province":"NY",
    "sg:tags":[
        "lounge",
        "cocktail"
    ],
    "wof:name":"Groove Lounge",
    "wof:placetype":"venue"
},
  "geometry": {"coordinates":[-73.935535,40.697299],"type":"Point"}
}