{
  "type": "Feature",
  "properties": {
    "addr:full":"150 20th St Brooklyn NY 11232",
    "addr:housenumber":"150",
    "addr:postcode":"11232",
    "addr:street":"20Th St",
    "iso:country":"US",
    "sg:address":"150 20th St",
    "sg:city":"Brooklyn",
    "sg:classifiers":[
        {
            "category":"Wholesale",
            "subcategory":"Electrical",
            "type":"Manufacturing & Wholesale Goods"
        }
    ],
    "sg:phone":"+1 718 965 1324",
    "sg:postcode":"11232",
    "sg:province":"NY",
    "sg:tags":[
        "photo",
        "parts",
        "electronic"
    ],
    "wof:name":"Stephen Imports Inc",
    "wof:placetype":"venue"
},
  "geometry": {"coordinates":[-73.99598899999999,40.663884],"type":"Point"}
}