{
  "type": "Feature",
  "properties": {
    "addr:full":"30 Riverside Dr Colton NY 13625",
    "addr:housenumber":"30",
    "addr:postcode":"13625",
    "addr:street":"Riverside Dr",
    "iso:country":"US",
    "sg:address":"30 Riverside Dr",
    "sg:city":"Colton",
    "sg:classifiers":[
        {
            "category":"Building & Trades",
            "subcategory":"Construction",
            "type":"Services"
        }
    ],
    "sg:phone":"+1 315 262 2451",
    "sg:postcode":"13625",
    "sg:province":"NY",
    "sg:tags":[
        "home",
        "builder"
    ],
    "wof:name":"Colton Corp",
    "wof:placetype":"venue"
},
  "geometry": {"coordinates":[-74.937929,44.555065],"type":"Point"}
}