{
  "type": "Feature",
  "properties": {
    "addr:full":"236 Bushwick Ave Brooklyn NY 11206",
    "addr:housenumber":"236",
    "addr:postcode":"11206",
    "addr:street":"Bushwick Ave",
    "iso:country":"US",
    "sg:address":"236 Bushwick Ave",
    "sg:city":"Brooklyn",
    "sg:classifiers":[
        {
            "category":"Shopping",
            "subcategory":"Pharmacy",
            "type":"Retail Goods"
        }
    ],
    "sg:phone":"+1 718 417 9031",
    "sg:postcode":"11206",
    "sg:province":"NY",
    "sg:tags":[
        "drug",
        "store"
    ],
    "wof:name":"Vista Pharmacy Inc",
    "wof:placetype":"venue"
},
  "geometry": {"coordinates":[-73.93998499999999,40.708234],"type":"Point"}
}