{
  "type": "Feature",
  "properties": {
    "iso:country":"US",
    "sg:address":"264 School St",
    "sg:city":"Buffalo",
    "sg:classifiers":[
        {
            "category":"Shopping",
            "subcategory":"Clothing, Apparel, & Fashions",
            "type":"Retail Goods"
        },
        {
            "category":"Manufacturing",
            "subcategory":"Retail Goods",
            "type":"Manufacturing & Wholesale Goods"
        }
    ],
    "sg:phone":"+1 716 877 8233",
    "sg:postcode":"14217",
    "sg:province":"NY",
    "sg:tags":[
        "handbag",
        "handbags-wholesale",
        "manufacturer"
    ],
    "wof:name":"Handbags For Hire",
    "wof:placetype":"venue"
},
  "geometry": {"coordinates":[-78.88148099999999,42.982051],"type":"Point"}
}