{
  "type": "Feature",
  "properties": {
    "iso:country":"US",
    "sg:address":"140 South Ave",
    "sg:city":"Penn Yan",
    "sg:classifiers":[
        {
            "category":"Retail",
            "subcategory":"Auto Repair",
            "type":"Services"
        }
    ],
    "sg:phone":"+1 315 536 2745",
    "sg:postcode":"14527",
    "sg:province":"NY",
    "sg:tags":[
        "repairing",
        "automobile",
        "radiator"
    ],
    "wof:name":"Radiator World",
    "wof:placetype":"venue"
},
  "geometry": {"coordinates":[-77.051962,42.654438],"type":"Point"}
}