{
  "type": "Feature",
  "properties": {
    "addr:full":"226 W 79 St New York NY 10024",
    "addr:housenumber":"226",
    "addr:postcode":"10024",
    "addr:street":"W 79 St",
    "iso:country":"US",
    "sg:address":"226 W 79 St",
    "sg:city":"New York",
    "sg:classifiers":[
        {
            "category":"Restaurant",
            "type":"Food & Drink"
        }
    ],
    "sg:phone":"+1   ",
    "sg:postcode":"10024",
    "sg:province":"NY",
    "sg:tags":[
        "bar"
    ],
    "wof:name":"Miss Ellies Homesick Bar Grill",
    "wof:placetype":"venue"
},
  "geometry": {"coordinates":[-73.979342,40.7834],"type":"Point"}
}