{
  "type": "Feature",
  "properties": {
    "addr:full":"418 S Main St Elmira NY 14904",
    "addr:housenumber":"418",
    "addr:postcode":"14904",
    "addr:street":"S Main St",
    "iso:country":"US",
    "sg:address":"418 S Main St",
    "sg:city":"Elmira",
    "sg:classifiers":[
        {
            "category":"Government",
            "subcategory":"Post Office",
            "type":"Public Place"
        }
    ],
    "sg:phone":"+1 607 734 6482",
    "sg:postcode":"14904",
    "sg:province":"NY",
    "wof:name":"US Post Office",
    "wof:placetype":"venue"
},
  "geometry": {"coordinates":[-76.80326700000001,42.078802],"type":"Point"}
}