{
  "type": "Feature",
  "properties": {
    "iso:country":"US",
    "sg:address":"22 N Tyson Ave",
    "sg:city":"Floral Park",
    "sg:classifiers":[
        {
            "category":"Wholesale",
            "subcategory":"Groceries",
            "type":"Manufacturing & Wholesale Goods"
        }
    ],
    "sg:phone":"+1 516 437 8600",
    "sg:postcode":"11001",
    "sg:province":"NY",
    "sg:tags":[
        "bakery",
        "product"
    ],
    "wof:name":"S W International Ltd",
    "wof:placetype":"venue"
},
  "geometry": {"coordinates":[-73.705354,40.729012],"type":"Point"}
}