{
  "type": "Feature",
  "properties": {
    "addr:full":"808 Bellinger Ave Herkimer NY 13350",
    "addr:housenumber":"808",
    "addr:postcode":"13350",
    "addr:street":"Bellinger Ave",
    "iso:country":"US",
    "sg:address":"808 Bellinger Ave",
    "sg:city":"Herkimer",
    "sg:classifiers":[
        {
            "category":"Organizations",
            "subcategory":"Labor Organization",
            "type":"Services"
        }
    ],
    "sg:phone":"+1   ",
    "sg:postcode":"13350",
    "sg:province":"NY",
    "wof:name":"National Society of Daughers",
    "wof:placetype":"venue"
},
  "geometry": {"coordinates":[-74.996521,43.024542],"type":"Point"}
}