{
  "type": "Feature",
  "properties": {
    "iso:country":"US",
    "sg:address":"127 W 56 St",
    "sg:city":"New York",
    "sg:classifiers":[
        {
            "category":"Professional",
            "subcategory":"Art Services",
            "type":"Services"
        }
    ],
    "sg:phone":"+1 212 262 4489",
    "sg:postcode":"10019",
    "sg:province":"NY",
    "sg:tags":[
        "graphic",
        "designer"
    ],
    "wof:name":"BDK Books",
    "wof:placetype":"venue"
},
  "geometry": {"coordinates":[-73.979919,40.764591],"type":"Point"}
}