{
  "type": "Feature",
  "properties": {
    "addr:full":"37 E Main St East Islip NY 11730",
    "addr:housenumber":"37",
    "addr:postcode":"11730",
    "addr:street":"E Main St",
    "iso:country":"US",
    "sg:address":"37 E Main St",
    "sg:city":"East Islip",
    "sg:classifiers":[
        {
            "category":"Personal",
            "subcategory":"Beauty Salon",
            "type":"Services"
        }
    ],
    "sg:phone":"+1 631 581 9589",
    "sg:postcode":"11730",
    "sg:province":"NY",
    "wof:name":"Casablanca Hair Studios",
    "wof:placetype":"venue"
},
  "geometry": {"coordinates":[-73.18855000000001,40.731681],"type":"Point"}
}