{
  "type": "Feature",
  "properties": {
    "iso:country":"US",
    "sg:address":"1270 Ave of the Americas",
    "sg:city":"New York",
    "sg:classifiers":[
        {
            "category":"Insurance",
            "subcategory":"Insurance Agent",
            "type":"Services"
        }
    ],
    "sg:phone":"+1 212 307 7750",
    "sg:postcode":"10020",
    "sg:province":"NY",
    "wof:name":"Allstate Insurance Co",
    "wof:placetype":"venue"
},
  "geometry": {"coordinates":[-73.980097,40.760141],"type":"Point"}
}