{
  "type": "Feature",
  "properties": {
    "addr:full":"5027 Duboise Rd Ithaca NY 14850",
    "addr:housenumber":"5027",
    "addr:postcode":"14850",
    "addr:street":"Duboise Rd",
    "iso:country":"US",
    "sg:address":"5027 Duboise Rd",
    "sg:city":"Ithaca",
    "sg:classifiers":[
        {
            "category":"Professional",
            "type":"Services"
        }
    ],
    "sg:phone":"+1 607 387 9608",
    "sg:postcode":"14850",
    "sg:province":"NY",
    "sg:tags":[
        "art",
        "restoring"
    ],
    "wof:name":"Clement Art Conservation Inc",
    "wof:placetype":"venue"
},
  "geometry": {"coordinates":[-76.57446899999999,42.515459],"type":"Point"}
}