{
  "type": "Feature",
  "properties": {
    "addr:full":"2243 82nd St Brooklyn NY 11214",
    "addr:housenumber":"2243",
    "addr:postcode":"11214",
    "addr:street":"82Nd St",
    "iso:country":"US",
    "sg:address":"2243 82nd St",
    "sg:city":"Brooklyn",
    "sg:classifiers":[
        {
            "category":"Professional",
            "type":"Services"
        }
    ],
    "sg:phone":"+1   ",
    "sg:postcode":"11214",
    "sg:province":"NY",
    "wof:name":"Rp Tech Inc",
    "wof:placetype":"venue"
},
  "geometry": {"coordinates":[-73.989903,40.6035],"type":"Point"}
}