{
  "type": "Feature",
  "properties": {
    "addr:full":"116 Fulton Street New York NY 10038",
    "addr:housenumber":"116",
    "addr:postcode":"10038",
    "addr:street":"Fulton Street",
    "iso:country":"US",
    "sg:address":"116 Fulton Street",
    "sg:city":"New York",
    "sg:classifiers":[
        {
            "category":"Shopping",
            "subcategory":"Jewelry",
            "type":"Retail Goods"
        }
    ],
    "sg:phone":"+1 212 962 2850",
    "sg:postcode":"10038",
    "sg:province":"NY",
    "wof:name":"Gold Master Ny",
    "wof:placetype":"venue"
},
  "geometry": {"coordinates":[-74.007195,40.710075],"type":"Point"}
}