{
  "type": "Feature",
  "properties": {
    "addr:full":"9374 Pinyon Ct Clarence Center NY 14032",
    "addr:housenumber":"9374",
    "addr:postcode":"14032",
    "addr:street":"Pinyon Ct Clarence Center",
    "iso:country":"US",
    "sg:address":"9374 Pinyon Ct",
    "sg:city":"Clarence Center",
    "sg:classifiers":[
        {
            "category":"Wholesale",
            "subcategory":"Hardware",
            "type":"Manufacturing & Wholesale Goods"
        }
    ],
    "sg:phone":"+1 716 741 3599",
    "sg:postcode":"14032",
    "sg:province":"NY",
    "wof:name":"In Clean Air Technologies",
    "wof:placetype":"venue"
},
  "geometry": {"coordinates":[-78.640199,43.01907],"type":"Point"}
}