{
  "type": "Feature",
  "properties": {
    "addr:full":"88 Bush Ave Staten Island NY 10303",
    "addr:housenumber":"88",
    "addr:postcode":"10303",
    "addr:street":"Bush Ave",
    "iso:country":"US",
    "sg:address":"88 Bush Ave",
    "sg:city":"Staten Island",
    "sg:classifiers":[
        {
            "category":"Building & Trades",
            "subcategory":"Construction",
            "type":"Services"
        }
    ],
    "sg:phone":"+1 718 720 9681",
    "sg:postcode":"10303",
    "sg:province":"NY",
    "sg:tags":[
        "general",
        "contractor"
    ],
    "wof:name":"Dawud & Sons",
    "wof:placetype":"venue"
},
  "geometry": {"coordinates":[-74.15935500000001,40.634287],"type":"Point"}
}