{
  "type": "Feature",
  "properties": {
    "addr:full":"555 W 180th St New York NY 10033",
    "addr:housenumber":"555",
    "addr:postcode":"10033",
    "addr:street":"W 180Th St",
    "iso:country":"US",
    "sg:address":"555 W 180th St",
    "sg:city":"New York",
    "sg:classifiers":[
        {
            "category":"Government",
            "subcategory":"Post Office",
            "type":"Public Place"
        }
    ],
    "sg:phone":"+1 212 568 2690",
    "sg:postcode":"10033",
    "sg:province":"NY",
    "sg:tags":[
        "postal",
        "u"
    ],
    "sg:website":"usps.com/",
    "wof:name":"US Post Office",
    "wof:placetype":"venue"
},
  "geometry": {"coordinates":[-73.933768,40.84844],"type":"Point"}
}