{
  "type": "Feature",
  "properties": {
    "iso:country":"US",
    "sg:address":"410 Park Avenue Fl 14",
    "sg:city":"New York",
    "sg:classifiers":[
        {
            "category":"Banks & Credit Unions",
            "subcategory":"Bank",
            "type":"Services"
        }
    ],
    "sg:phone":"+1 212 891 5000",
    "sg:postcode":"10022",
    "sg:province":"NY",
    "wof:name":"First Union Securities",
    "wof:placetype":"venue"
},
  "geometry": {"coordinates":[-73.972025,40.760084],"type":"Point"}
}