{
  "type": "Feature",
  "properties": {
    "addr:full":"777 Hoosick Rd Troy NY 12180",
    "addr:housenumber":"777",
    "addr:postcode":"12180",
    "addr:street":"Hoosick Rd",
    "iso:country":"US",
    "sg:address":"777 Hoosick Rd",
    "sg:city":"Troy",
    "sg:classifiers":[
        {
            "category":"Wholesale",
            "subcategory":"Scrap",
            "type":"Manufacturing & Wholesale Goods"
        }
    ],
    "sg:phone":"+1 518 279 4311",
    "sg:postcode":"12180",
    "sg:province":"NY",
    "sg:tags":[
        "textile",
        "waste",
        "plastic"
    ],
    "wof:name":"Enstar Corp",
    "wof:placetype":"venue"
},
  "geometry": {"coordinates":[-73.64013799999999,42.746629],"type":"Point"}
}