{
  "type": "Feature",
  "properties": {
    "iso:country":"US",
    "sg:address":"4496 US Hwy 209",
    "sg:city":"Stone Ridge",
    "sg:classifiers":[
        {
            "category":"Museum",
            "type":"Entertainment"
        }
    ],
    "sg:phone":"+1 845 687 2687",
    "sg:postcode":"12484",
    "sg:province":"NY",
    "sg:tags":[
        "organization",
        "arts",
        "information"
    ],
    "wof:name":"Chamber Arts Festival",
    "wof:placetype":"venue"
},
  "geometry": {"coordinates":[-74.191312,41.823668],"type":"Point"}
}