{
  "type": "Feature",
  "properties": {
    "addr:full":"29 William St Amityville NY 11701",
    "addr:housenumber":"29",
    "addr:postcode":"11701",
    "addr:street":"William St",
    "iso:country":"US",
    "sg:address":"29 William St",
    "sg:city":"Amityville",
    "sg:classifiers":[
        {
            "category":"Wholesale",
            "subcategory":"Toys & Hobbies",
            "type":"Manufacturing & Wholesale Goods"
        }
    ],
    "sg:phone":"+1 631 789 2954",
    "sg:postcode":"11701",
    "sg:province":"NY",
    "sg:tags":[
        "wholesaler"
    ],
    "wof:name":"Preffered Directer Chair",
    "wof:placetype":"venue"
},
  "geometry": {"coordinates":[-73.423608,40.680484],"type":"Point"}
}