{
  "type": "Feature",
  "properties": {
    "addr:full":"200 5th Ave New York NY 10010",
    "addr:housenumber":"200",
    "addr:postcode":"10010",
    "addr:street":"5Th Ave",
    "iso:country":"US",
    "sg:address":"200 5th Ave",
    "sg:city":"New York",
    "sg:classifiers":[
        {
            "category":"Professional",
            "type":"Services"
        }
    ],
    "sg:phone":"+1 212 414 9353",
    "sg:postcode":"10010",
    "sg:province":"NY",
    "sg:tags":[
        "establishment"
    ],
    "wof:name":"Lisa Frank Inc",
    "wof:placetype":"venue"
},
  "geometry": {"coordinates":[-73.989532,40.741642],"type":"Point"}
}