{
  "type": "Feature",
  "properties": {
    "iso:country":"US",
    "sg:address":"24 2nd Ave",
    "sg:city":"New York",
    "sg:classifiers":[
        {
            "category":"Personal",
            "type":"Services"
        }
    ],
    "sg:phone":"+1 917 289 1371",
    "sg:postcode":"10003",
    "sg:province":"NY",
    "sg:tags":[
        "towing"
    ],
    "wof:name":"7 24 Hour Emergency Towing",
    "wof:placetype":"venue"
},
  "geometry": {"coordinates":[-73.99050099999999,40.7244],"type":"Point"}
}