{
  "type": "Feature",
  "properties": {
    "addr:full":"2262 Broadway New York NY 10024",
    "addr:housenumber":"2262",
    "addr:postcode":"10024",
    "addr:street":"Broadway",
    "iso:country":"US",
    "sg:address":"2262 Broadway",
    "sg:city":"New York",
    "sg:classifiers":[
        {
            "category":"Restaurant",
            "type":"Food & Drink"
        }
    ],
    "sg:phone":"+1 212 721 4900",
    "sg:postcode":"10024",
    "sg:province":"NY",
    "sg:website":"www.haleandhearty.com/",
    "wof:name":"Hale & Hearty Soups",
    "wof:placetype":"venue"
},
  "geometry": {"coordinates":[-73.978615,40.785271],"type":"Point"}
}