{
  "type": "Feature",
  "properties": {
    "addr:full":"123 4th Ave 2nd Fl New York NY 10003",
    "addr:housenumber":"123",
    "addr:postcode":"10003",
    "addr:street":"4Th Ave 2Nd Fl",
    "iso:country":"US",
    "sg:address":"123 4th Ave 2nd Fl",
    "sg:city":"New York",
    "sg:classifiers":[
        {
            "category":"Personal",
            "type":"Services"
        }
    ],
    "sg:phone":"+1 212 677 8621",
    "sg:postcode":"10003",
    "sg:province":"NY",
    "sg:tags":[
        "local"
    ],
    "sg:website":"www.crsny.org",
    "wof:name":"CRS - Center for Remembering & Sharing",
    "wof:placetype":"venue"
},
  "geometry": {"coordinates":[-73.989947,40.733099],"type":"Point"}
}