{
  "type": "Feature",
  "properties": {
    "iso:country":"US",
    "sg:address":"188 Running Creek Rd",
    "sg:city":"Valatie",
    "sg:classifiers":[
        {
            "category":"Professional",
            "subcategory":"Business Services",
            "type":"Services"
        }
    ],
    "sg:phone":"+1   ",
    "sg:postcode":"12184",
    "sg:province":"NY",
    "wof:name":"Den Besten Enterprises Inc",
    "wof:placetype":"venue"
},
  "geometry": {"coordinates":[-73.714793,42.451384],"type":"Point"}
}