{
  "type": "Feature",
  "properties": {
    "addr:full":"5729 Main Street Flushing NY 11355",
    "addr:housenumber":"5729",
    "addr:postcode":"11355",
    "addr:street":"Main Street",
    "iso:country":"US",
    "sg:address":"5729 Main Street",
    "sg:city":"Flushing",
    "sg:classifiers":[
        {
            "category":"Restaurant",
            "type":"Food & Drink"
        }
    ],
    "sg:phone":"+1 718 961 0263",
    "sg:postcode":"11355",
    "sg:province":"NY",
    "sg:tags":[
        "pizza"
    ],
    "wof:name":"Phil & Sons Pizzeria & Restaurant",
    "wof:placetype":"venue"
},
  "geometry": {"coordinates":[-73.825869,40.745621],"type":"Point"}
}