{
  "type": "Feature",
  "properties": {
    "addr:full":"163 W 125th St New York NY 10027",
    "addr:housenumber":"163",
    "addr:postcode":"10027",
    "addr:street":"W 125Th St",
    "iso:country":"US",
    "sg:address":"163 W 125th St",
    "sg:city":"New York",
    "sg:classifiers":[
        {
            "category":"Government",
            "subcategory":"Office",
            "type":"Public Place"
        }
    ],
    "sg:phone":"+1 212 961 4390",
    "sg:postcode":"10027",
    "sg:province":"NY",
    "sg:tags":[
        "building",
        "standard"
    ],
    "wof:name":"Building Administration",
    "wof:placetype":"venue"
},
  "geometry": {"coordinates":[-73.946928,40.808279],"type":"Point"}
}