{
  "type": "Feature",
  "properties": {
    "addr:full":"10018 159th Ave Howard Beach NY 11414",
    "addr:housenumber":"10018",
    "addr:postcode":"11414",
    "addr:street":"159Th Ave",
    "iso:country":"US",
    "sg:address":"10018 159th Ave",
    "sg:city":"Howard Beach",
    "sg:classifiers":[
        {
            "category":"Retail",
            "subcategory":"Funeral Services",
            "type":"Services"
        }
    ],
    "sg:phone":"+1 718 843 7820",
    "sg:postcode":"11414",
    "sg:province":"NY",
    "sg:tags":[
        "cemetery"
    ],
    "wof:name":"Casey & Porrello Funeral Home",
    "wof:placetype":"venue"
},
  "geometry": {"coordinates":[-73.83260300000001,40.660099],"type":"Point"}
}