{
  "type": "Feature",
  "properties": {
    "iso:country":"US",
    "sg:address":"539 Old Riverhead Rd",
    "sg:city":"Westhampton Beach",
    "sg:classifiers":[
        {
            "category":"Shopping",
            "subcategory":"Gifts & Souvenirs",
            "type":"Retail Goods"
        }
    ],
    "sg:phone":"+1   ",
    "sg:postcode":"11978",
    "sg:province":"NY",
    "wof:name":"Suhrack Distributon",
    "wof:placetype":"venue"
},
  "geometry": {"coordinates":[-72.64625599999999,40.838665],"type":"Point"}
}