{
  "type": "Feature",
  "properties": {
    "iso:country":"US",
    "sg:address":"283 Commack Rd",
    "sg:city":"Commack",
    "sg:classifiers":[
        {
            "category":"Health Services",
            "subcategory":"Doctor",
            "type":"Services"
        },
        {
            "category":"Professional",
            "subcategory":"Lawyer & Legal Services",
            "type":"Services"
        }
    ],
    "sg:phone":"+1 631 462 2980",
    "sg:postcode":"11725",
    "sg:province":"NY",
    "wof:name":"Strauss Raphael MD",
    "wof:placetype":"venue"
},
  "geometry": {"coordinates":[-73.293297,40.8293],"type":"Point"}
}