{
  "type": "Feature",
  "properties": {
    "iso:country":"US",
    "sg:address":"791 Canal St",
    "sg:city":"Syracuse",
    "sg:classifiers":[
        {
            "category":"Retail",
            "subcategory":"Repair Shop",
            "type":"Services"
        }
    ],
    "sg:phone":"+1 315 428 0701",
    "sg:postcode":"13210",
    "sg:province":"NY",
    "sg:tags":[
        "refinishing",
        "furniture"
    ],
    "wof:name":"Tobin's Refinishing",
    "wof:placetype":"venue"
},
  "geometry": {"coordinates":[-76.131519,43.051145],"type":"Point"}
}