{
  "type": "Feature",
  "properties": {
    "iso:country":"US",
    "sg:address":"360 Linden Oaks",
    "sg:city":"Rochester",
    "sg:classifiers":[
        {
            "category":"Insurance",
            "subcategory":"Hazard Insurance",
            "type":"Services"
        },
        {
            "category":"Insurance",
            "subcategory":"Insurance Agent",
            "type":"Services"
        }
    ],
    "sg:phone":"+1 585 272 9250",
    "sg:postcode":"14625",
    "sg:province":"NY",
    "sg:tags":[
        "fund",
        "car"
    ],
    "wof:name":"Mutual of America",
    "wof:placetype":"venue"
},
  "geometry": {"coordinates":[-77.510175,43.1201],"type":"Point"}
}