{
  "type": "Feature",
  "properties": {
    "addr:full":"63 E 1st St Mt Vernon NY 10550",
    "addr:housenumber":"63",
    "addr:postcode":"10550",
    "addr:street":"E 1St St",
    "iso:country":"US",
    "sg:address":"63 E 1st St",
    "sg:city":"Mt Vernon",
    "sg:classifiers":[
        {
            "category":"Real Estate",
            "subcategory":"Architect",
            "type":"Services"
        }
    ],
    "sg:phone":"+1 914 699 7783",
    "sg:postcode":"10550",
    "sg:province":"NY",
    "sg:tags":[
        "estimate",
        "construction"
    ],
    "wof:name":"Bibeau Construction",
    "wof:placetype":"venue"
},
  "geometry": {"coordinates":[-73.83320500000001,40.911666],"type":"Point"}
}