{
  "type": "Feature",
  "properties": {
    "iso:country":"US",
    "sg:address":"6 Casperkill Dr",
    "sg:city":"Poughkeepsie",
    "sg:classifiers":[
        {
            "category":"Professional",
            "subcategory":"Art Services",
            "type":"Services"
        }
    ],
    "sg:phone":"+1 845 463 0051",
    "sg:postcode":"12603",
    "sg:province":"NY",
    "sg:tags":[
        "graphic",
        "designer"
    ],
    "wof:name":"De'Shay Desktop Publishing",
    "wof:placetype":"venue"
},
  "geometry": {"coordinates":[-73.911368,41.649347],"type":"Point"}
}