{
  "type": "Feature",
  "properties": {
    "addr:full":"275 Madison Avenue 14th Floor New York NY 10016 ",
    "addr:housenumber":"275;14th floor",
    "addr:postcode":"10016",
    "addr:street":"Madison Avenue",
    "iso:country":"US",
    "sg:address":"275 Madison Avenue 14th Floor",
    "sg:city":"New York",
    "sg:classifiers":[
        {
            "category":"Professional",
            "subcategory":"Computer Services",
            "type":"Services"
        }
    ],
    "sg:phone":"+1 617 301 4550",
    "sg:postcode":"10016 ",
    "sg:province":"NY",
    "sg:tags":[
        "mobile-advertising",
        "mobile-search"
    ],
    "sg:website":"http://www.jumptap.com/",
    "wof:name":"Jumptap",
    "wof:placetype":"venue"
},
  "geometry": {"coordinates":[-73.98045,40.750956],"type":"Point"}
}