{
  "type": "Feature",
  "properties": {
    "iso:country":"US",
    "sg:address":"62 38th St",
    "sg:city":"Islip",
    "sg:classifiers":[
        {
            "category":"Shopping",
            "subcategory":"Tobacco",
            "type":"Retail Goods"
        }
    ],
    "sg:phone":"+1 631 277 9312",
    "sg:postcode":"11751",
    "sg:province":"NY",
    "sg:tags":[
        "cigarette",
        "cigar",
        "dealer"
    ],
    "wof:name":"B & H Cigar Co",
    "wof:placetype":"venue"
},
  "geometry": {"coordinates":[-73.225239,40.753287],"type":"Point"}
}