{
  "type": "Feature",
  "properties": {
    "iso:country":"US",
    "sg:address":"29 Dianas Trl",
    "sg:city":"Roslyn",
    "sg:classifiers":[
        {
            "category":"Insurance",
            "subcategory":"Insurance Agent",
            "type":"Services"
        }
    ],
    "sg:phone":"+1 516 484 5800",
    "sg:postcode":"11576",
    "sg:province":"NY",
    "sg:tags":[
        "consultant",
        "planning",
        "pension"
    ],
    "wof:name":"Pension Actuarial",
    "wof:placetype":"venue"
},
  "geometry": {"coordinates":[-73.664028,40.789224],"type":"Point"}
}