{
  "type": "Feature",
  "properties": {
    "addr:full":"459 Bay Ridge Pkwy Brooklyn NY 11209",
    "addr:housenumber":"459",
    "addr:postcode":"11209",
    "addr:street":"Bay Ridge Pkwy",
    "iso:country":"US",
    "sg:address":"459 Bay Ridge Pkwy",
    "sg:city":"Brooklyn",
    "sg:classifiers":[
        {
            "category":"Professional",
            "subcategory":"Lawyer & Legal Services",
            "type":"Services"
        }
    ],
    "sg:phone":"+1   ",
    "sg:postcode":"11209",
    "sg:province":"NY",
    "wof:name":"Stanton Margrett M Esquire",
    "wof:placetype":"venue"
},
  "geometry": {"coordinates":[-74.023672,40.630404],"type":"Point"}
}