{
  "type": "Feature",
  "properties": {
    "iso:country":"US",
    "sg:address":"1449 Norton St",
    "sg:city":"Rochester",
    "sg:classifiers":[
        {
            "category":"Organizations",
            "subcategory":"Religious Organization",
            "type":"Services"
        }
    ],
    "sg:phone":"+1 585 342 6360",
    "sg:postcode":"14621",
    "sg:province":"NY",
    "sg:tags":[
        "church"
    ],
    "wof:name":"Greater Deliverance Outreach M",
    "wof:placetype":"venue"
},
  "geometry": {"coordinates":[-77.58099799999999,43.187459],"type":"Point"}
}