{
  "type": "Feature",
  "properties": {
    "iso:country":"US",
    "sg:address":"132 Bella Vista St",
    "sg:city":"Tuckahoe",
    "sg:classifiers":[
        {
            "category":"Professional",
            "subcategory":"Art Services",
            "type":"Services"
        }
    ],
    "sg:phone":"+1 914 337 5045",
    "sg:postcode":"10707",
    "sg:province":"NY",
    "sg:tags":[
        "designer",
        "display",
        "producer"
    ],
    "wof:name":"Design Interactive Group, Ltd",
    "wof:placetype":"venue"
},
  "geometry": {"coordinates":[-73.820334,40.957129],"type":"Point"}
}