{
  "type": "Feature",
  "properties": {
    "iso:country":"US",
    "sg:address":"1683 Carlton Ave",
    "sg:city":"Staten Island",
    "sg:classifiers":[
        {
            "category":"Building & Trades",
            "subcategory":"Construction",
            "type":"Services"
        }
    ],
    "sg:phone":"+1 718 967 3198",
    "sg:postcode":"10309",
    "sg:province":"NY",
    "sg:tags":[
        "house"
    ],
    "wof:name":"Cruz Construction Corp",
    "wof:placetype":"venue"
},
  "geometry": {"coordinates":[-74.199873,40.534146],"type":"Point"}
}