{
  "type": "Feature",
  "properties": {
    "addr:full":"1014 Oak Hill Rd Frewsburg NY 14738",
    "addr:housenumber":"1014",
    "addr:postcode":"14738",
    "addr:street":"Oak Hill Rd",
    "iso:country":"US",
    "sg:address":"1014 Oak Hill Rd",
    "sg:city":"Frewsburg",
    "sg:classifiers":[
        {
            "category":"Retail",
            "subcategory":"Animal Services",
            "type":"Services"
        }
    ],
    "sg:phone":"+1 716 569 2461",
    "sg:postcode":"14738",
    "sg:province":"NY",
    "sg:tags":[
        "pet",
        "boarding",
        "sitting"
    ],
    "wof:name":"TLC Pet Kennel Pet Grooming",
    "wof:placetype":"venue"
},
  "geometry": {"coordinates":[-79.124994,42.047503],"type":"Point"}
}