{
  "type": "Feature",
  "properties": {
    "addr:full":"116 19 Blvd Jamaica NY 11434",
    "addr:postcode":"11434",
    "addr:street":"116 19 Blvd",
    "iso:country":"US",
    "sg:address":"116 19 Blvd",
    "sg:city":"Jamaica",
    "sg:classifiers":[
        {
            "category":"Food & Beverages",
            "subcategory":"Groceries & Convenience Stores",
            "type":"Retail Goods"
        }
    ],
    "sg:phone":"+1 718 845 2657",
    "sg:postcode":"11434",
    "sg:province":"NY",
    "wof:name":"Family Food Center",
    "wof:placetype":"venue"
},
  "geometry": {"coordinates":[-73.832846,40.699593],"type":"Point"}
}