{
  "type": "Feature",
  "properties": {
    "iso:country":"US",
    "sg:address":"13 Sage Rd",
    "sg:city":"Pawling",
    "sg:classifiers":[
        {
            "category":"Recreation",
            "type":"Entertainment"
        }
    ],
    "sg:phone":"+1   ",
    "sg:postcode":"12564",
    "sg:province":"NY",
    "wof:name":"Ryu Renshi Dan Karate",
    "wof:placetype":"venue"
},
  "geometry": {"coordinates":[-73.627447,41.570895],"type":"Point"}
}