{
  "type": "Feature",
  "properties": {
    "addr:full":"12721 111th Ave South Ozone Park NY 11420",
    "addr:housenumber":"12721",
    "addr:postcode":"11420",
    "addr:street":"111Th Ave",
    "iso:country":"US",
    "sg:address":"12721 111th Ave",
    "sg:city":"South Ozone Park",
    "sg:classifiers":[
        {
            "category":"Food & Beverages",
            "subcategory":"Groceries & Convenience Stores",
            "type":"Retail Goods"
        }
    ],
    "sg:phone":"+1 800 507 6702",
    "sg:postcode":"11420",
    "sg:province":"NY",
    "wof:name":"D & R Supermarket Inc",
    "wof:placetype":"venue"
},
  "geometry": {"coordinates":[-73.814159,40.682682],"type":"Point"}
}