{
  "type": "Feature",
  "properties": {
    "addr:full":"164 Delancey St New York NY 10002",
    "addr:housenumber":"164",
    "addr:postcode":"10002",
    "addr:street":"Delancey St",
    "iso:country":"US",
    "sg:address":"164 Delancey St",
    "sg:city":"New York",
    "sg:classifiers":[
        {
            "category":"Shopping",
            "subcategory":"Jewelry",
            "type":"Retail Goods"
        }
    ],
    "sg:phone":"+1   ",
    "sg:postcode":"10002",
    "sg:province":"NY",
    "wof:name":"Joyeria Pepe",
    "wof:placetype":"venue"
},
  "geometry": {"coordinates":[-73.98660099999999,40.718008],"type":"Point"}
}