{
  "type": "Feature",
  "properties": {
    "iso:country":"US",
    "sg:address":"5816 New Utrecht Ave",
    "sg:city":"Brooklyn",
    "sg:classifiers":[
        {
            "category":"Professional",
            "subcategory":"Computer Services",
            "type":"Services"
        }
    ],
    "sg:phone":"+1 718 438 2132",
    "sg:postcode":"11219",
    "sg:province":"NY",
    "sg:tags":[
        "repair"
    ],
    "wof:name":"Computer Guy",
    "wof:placetype":"venue"
},
  "geometry": {"coordinates":[-73.996308,40.62914],"type":"Point"}
}