{
  "type": "Feature",
  "properties": {
    "addr:full":"6731 48th Avenue Woodside NY 11377",
    "addr:housenumber":"6731",
    "addr:postcode":"11377",
    "addr:street":"48Th Avenue",
    "iso:country":"US",
    "sg:address":"6731 48th Avenue",
    "sg:city":"Woodside",
    "sg:classifiers":[
        {
            "category":"Building & Trades",
            "subcategory":"Pest Control",
            "type":"Services"
        }
    ],
    "sg:phone":"+1 718 533 6767",
    "sg:postcode":"11377",
    "sg:province":"NY",
    "wof:name":"Exterminadora Latina",
    "wof:placetype":"venue"
},
  "geometry": {"coordinates":[-73.89743300000001,40.738501],"type":"Point"}
}