{
  "type": "Feature",
  "properties": {
    "iso:country":"US",
    "sg:address":"65 Fairchild Ave",
    "sg:city":"Plainview",
    "sg:classifiers":[
        {
            "category":"Building & Trades",
            "subcategory":"Construction",
            "type":"Services"
        }
    ],
    "sg:phone":"+1 516 349 9225",
    "sg:postcode":"11803",
    "sg:province":"NY",
    "sg:tags":[
        "elevator"
    ],
    "wof:name":"Otis Elevator Co",
    "wof:placetype":"venue"
},
  "geometry": {"coordinates":[-73.464889,40.796415],"type":"Point"}
}