{
  "type": "Feature",
  "properties": {
    "iso:country":"US",
    "sg:address":"305 Stratton Rd",
    "sg:city":"New Rochelle",
    "sg:classifiers":[
        {
            "category":"Professional",
            "type":"Services"
        }
    ],
    "sg:phone":"+1   ",
    "sg:postcode":"10804",
    "sg:province":"NY",
    "wof:name":"D & M Creations Inc",
    "wof:placetype":"venue"
},
  "geometry": {"coordinates":[-73.78373000000001,40.969225],"type":"Point"}
}