{
  "type": "Feature",
  "properties": {
    "addr:full":"40 Broad St New York NY 10004",
    "addr:housenumber":"40",
    "addr:postcode":"10004",
    "addr:street":"Broad St",
    "iso:country":"US",
    "sg:address":"40 Broad St",
    "sg:city":"New York",
    "sg:classifiers":[
        {
            "category":"Coffee & Tea",
            "type":"Food & Drink"
        }
    ],
    "sg:phone":"+1 212 248 0902",
    "sg:postcode":"10004",
    "sg:province":"NY",
    "wof:name":"Timothy's Coffees of the World",
    "wof:placetype":"venue"
},
  "geometry": {"coordinates":[-74.011398,40.7057],"type":"Point"}
}