{
  "type": "Feature",
  "properties": {
    "iso:country":"US",
    "sg:address":"5154 Kings Hwy",
    "sg:city":"Brooklyn",
    "sg:classifiers":[
        {
            "category":"Shopping",
            "subcategory":"Gifts & Souvenirs",
            "type":"Retail Goods"
        }
    ],
    "sg:phone":"+1 718 253 0960",
    "sg:postcode":"11234",
    "sg:province":"NY",
    "sg:tags":[
        "shop"
    ],
    "wof:name":"Diamonds Hallmark",
    "wof:placetype":"venue"
},
  "geometry": {"coordinates":[-73.92701,40.63588],"type":"Point"}
}