{
  "type": "Feature",
  "properties": {
    "iso:country":"US",
    "sg:address":"3444 Kossuth Ave",
    "sg:city":"Bronx",
    "sg:classifiers":[
        {
            "category":"Health Services",
            "subcategory":"Doctor",
            "type":"Services"
        }
    ],
    "sg:phone":"+1 718 920 6567",
    "sg:postcode":"10467",
    "sg:province":"NY",
    "sg:tags":[
        "physician",
        "surgeon"
    ],
    "wof:name":"Sylvia W Lim MD",
    "wof:placetype":"venue"
},
  "geometry": {"coordinates":[-73.881429,40.880789],"type":"Point"}
}