{
  "type": "Feature",
  "properties": {
    "addr:full":"19 E Market St Red Hook NY 12571",
    "addr:housenumber":"19",
    "addr:postcode":"12571",
    "addr:street":"E Market St",
    "iso:country":"US",
    "sg:address":"19 E Market St",
    "sg:city":"Red Hook",
    "sg:classifiers":[
        {
            "category":"Home & Garden",
            "subcategory":"Carpets & Floor Coverings",
            "type":"Retail Goods"
        },
        {
            "category":"Building & Trades",
            "subcategory":"Construction",
            "type":"Services"
        }
    ],
    "sg:phone":"+1 845 758 2005",
    "sg:postcode":"12571",
    "sg:province":"NY",
    "sg:tags":[
        "resurfacing",
        "laying",
        "refinishing"
    ],
    "wof:name":"Northern Dutchess Hardwoods",
    "wof:placetype":"venue"
},
  "geometry": {"coordinates":[-73.87514,41.995062],"type":"Point"}
}